public abstract class scala.actors.threadpool.AbstractCollection extends java.util.AbstractCollection
  minor version: 0
  major version: 49
  Constant pool:
const #1 = Method	#5.#12;	//  java/util/AbstractCollection."<init>":()V
const #2 = Method	#13.#14;	//  scala/actors/threadpool/helpers/Utils.collectionToArray:(Ljava/util/Collection;)[Ljava/lang/Object;
const #3 = Method	#13.#15;	//  scala/actors/threadpool/helpers/Utils.collectionToArray:(Ljava/util/Collection;[Ljava/lang/Object;)[Ljava/lang/Object;
const #4 = class	#16;	//  scala/actors/threadpool/AbstractCollection
const #5 = class	#17;	//  java/util/AbstractCollection
const #6 = Asciz	<init>;
const #7 = Asciz	()V;
const #8 = Asciz	Code;
const #9 = Asciz	toArray;
const #10 = Asciz	()[Ljava/lang/Object;;
const #11 = Asciz	([Ljava/lang/Object;)[Ljava/lang/Object;;
const #12 = NameAndType	#6:#7;//  "<init>":()V
const #13 = class	#18;	//  scala/actors/threadpool/helpers/Utils
const #14 = NameAndType	#19:#20;//  collectionToArray:(Ljava/util/Collection;)[Ljava/lang/Object;
const #15 = NameAndType	#19:#21;//  collectionToArray:(Ljava/util/Collection;[Ljava/lang/Object;)[Ljava/lang/Object;
const #16 = Asciz	scala/actors/threadpool/AbstractCollection;
const #17 = Asciz	java/util/AbstractCollection;
const #18 = Asciz	scala/actors/threadpool/helpers/Utils;
const #19 = Asciz	collectionToArray;
const #20 = Asciz	(Ljava/util/Collection;)[Ljava/lang/Object;;
const #21 = Asciz	(Ljava/util/Collection;[Ljava/lang/Object;)[Ljava/lang/Object;;

{
protected scala.actors.threadpool.AbstractCollection();
  Code:
   Stack=1, Locals=1, Args_size=1
   0:	aload_0
   1:	invokespecial	#1; //Method java/util/AbstractCollection."<init>":()V
   4:	return

public java.lang.Object[] toArray();
  Code:
   Stack=1, Locals=1, Args_size=1
   0:	aload_0
   1:	invokestatic	#2; //Method scala/actors/threadpool/helpers/Utils.collectionToArray:(Ljava/util/Collection;)[Ljava/lang/Object;
   4:	areturn

public java.lang.Object[] toArray(java.lang.Object[]);
  Code:
   Stack=2, Locals=2, Args_size=2
   0:	aload_0
   1:	aload_1
   2:	invokestatic	#3; //Method scala/actors/threadpool/helpers/Utils.collectionToArray:(Ljava/util/Collection;[Ljava/lang/Object;)[Ljava/lang/Object;
   5:	areturn

}

