public abstract class scala.actors.threadpool.AbstractExecutorService extends java.lang.Object implements scala.actors.threadpool.ExecutorService
  minor version: 0
  major version: 49
  Constant pool:
Method	java/lang/Object."<init>":()V
class	scala/actors/threadpool/FutureTask
Method	scala/actors/threadpool/FutureTask."<init>":(Ljava/lang/Runnable;Ljava/lang/Object;)V
Method	scala/actors/threadpool/FutureTask."<init>":(Lscala/actors/threadpool/Callable;)V
class	java/lang/NullPointerException
Method	java/lang/NullPointerException."<init>":()V
Method	scala/actors/threadpool/AbstractExecutorService.newTaskFor:(Ljava/lang/Runnable;Ljava/lang/Object;)Lscala/actors/threadpool/RunnableFuture;
Method	scala/actors/threadpool/AbstractExecutorService.execute:(Ljava/lang/Runnable;)V
Method	scala/actors/threadpool/AbstractExecutorService.newTaskFor:(Lscala/actors/threadpool/Callable;)Lscala/actors/threadpool/RunnableFuture;
InterfaceMethod	java/util/Collection.size:()I
class	java/lang/IllegalArgumentException
Method	java/lang/IllegalArgumentException."<init>":()V
class	java/util/ArrayList
Method	java/util/ArrayList."<init>":(I)V
class	scala/actors/threadpool/ExecutorCompletionService
Method	scala/actors/threadpool/ExecutorCompletionService."<init>":(Lscala/actors/threadpool/Executor;)V
Method	scala/actors/threadpool/helpers/Utils.nanoTime:()J
InterfaceMethod	java/util/Collection.iterator:()Ljava/util/Iterator;
InterfaceMethod	java/util/Iterator.next:()Ljava/lang/Object;
class	scala/actors/threadpool/Callable
Method	scala/actors/threadpool/ExecutorCompletionService.submit:(Lscala/actors/threadpool/Callable;)Lscala/actors/threadpool/Future;
InterfaceMethod	java/util/List.add:(Ljava/lang/Object;)Z
Method	scala/actors/threadpool/ExecutorCompletionService.poll:()Lscala/actors/threadpool/Future;
Field	scala/actors/threadpool/TimeUnit.NANOSECONDS:Lscala/actors/threadpool/TimeUnit;
Method	scala/actors/threadpool/ExecutorCompletionService.poll:(JLscala/actors/threadpool/TimeUnit;)Lscala/actors/threadpool/Future;
class	scala/actors/threadpool/TimeoutException
Method	scala/actors/threadpool/TimeoutException."<init>":()V
Method	scala/actors/threadpool/ExecutorCompletionService.take:()Lscala/actors/threadpool/Future;
InterfaceMethod	scala/actors/threadpool/Future.get:()Ljava/lang/Object;
InterfaceMethod	java/util/List.iterator:()Ljava/util/Iterator;
InterfaceMethod	java/util/Iterator.hasNext:()Z
class	scala/actors/threadpool/Future
InterfaceMethod	scala/actors/threadpool/Future.cancel:(Z)Z
class	java/lang/InterruptedException
class	scala/actors/threadpool/ExecutionException
class	java/lang/RuntimeException
Method	scala/actors/threadpool/ExecutionException."<init>":(Ljava/lang/Throwable;)V
Method	scala/actors/threadpool/ExecutionException."<init>":()V
Method	scala/actors/threadpool/AbstractExecutorService.doInvokeAny:(Ljava/util/Collection;ZJ)Ljava/lang/Object;
Field	scala/actors/threadpool/AbstractExecutorService.$assertionsDisabled:Z
class	java/lang/AssertionError
Method	java/lang/AssertionError."<init>":()V
Method	scala/actors/threadpool/TimeUnit.toNanos:(J)J
InterfaceMethod	scala/actors/threadpool/Future.isDone:()Z
class	scala/actors/threadpool/CancellationException
class	java/lang/Runnable
InterfaceMethod	scala/actors/threadpool/Future.get:(JLscala/actors/threadpool/TimeUnit;)Ljava/lang/Object;
class	scala/actors/threadpool/AbstractExecutorService
Method	java/lang/Class.desiredAssertionStatus:()Z
class	java/lang/Object
class	scala/actors/threadpool/ExecutorService
Asciz	$assertionsDisabled;
Asciz	Z;
Asciz	<init>;
Asciz	()V;
Asciz	Code;
Asciz	newTaskFor;
Asciz	(Ljava/lang/Runnable;Ljava/lang/Object;)Lscala/actors/threadpool/RunnableFuture;;
Asciz	(Lscala/actors/threadpool/Callable;)Lscala/actors/threadpool/RunnableFuture;;
Asciz	submit;
Asciz	(Ljava/lang/Runnable;)Lscala/actors/threadpool/Future;;
Asciz	(Ljava/lang/Runnable;Ljava/lang/Object;)Lscala/actors/threadpool/Future;;
Asciz	(Lscala/actors/threadpool/Callable;)Lscala/actors/threadpool/Future;;
Asciz	doInvokeAny;
Asciz	(Ljava/util/Collection;ZJ)Ljava/lang/Object;;
Asciz	Exceptions;
Asciz	invokeAny;
Asciz	(Ljava/util/Collection;)Ljava/lang/Object;;
Asciz	(Ljava/util/Collection;JLscala/actors/threadpool/TimeUnit;)Ljava/lang/Object;;
Asciz	invokeAll;
Asciz	(Ljava/util/Collection;)Ljava/util/List;;
Asciz	(Ljava/util/Collection;JLscala/actors/threadpool/TimeUnit;)Ljava/util/List;;
Asciz	<clinit>;
NameAndType	"<init>":()V
Asciz	scala/actors/threadpool/FutureTask;
NameAndType	"<init>":(Ljava/lang/Runnable;Ljava/lang/Object;)V
NameAndType	"<init>":(Lscala/actors/threadpool/Callable;)V
Asciz	java/lang/NullPointerException;
NameAndType	newTaskFor:(Ljava/lang/Runnable;Ljava/lang/Object;)Lscala/actors/threadpool/RunnableFuture;
NameAndType	execute:(Ljava/lang/Runnable;)V
NameAndType	newTaskFor:(Lscala/actors/threadpool/Callable;)Lscala/actors/threadpool/RunnableFuture;
class	java/util/Collection
NameAndType	size:()I
Asciz	java/lang/IllegalArgumentException;
Asciz	java/util/ArrayList;
NameAndType	"<init>":(I)V
Asciz	scala/actors/threadpool/ExecutorCompletionService;
NameAndType	"<init>":(Lscala/actors/threadpool/Executor;)V
class	scala/actors/threadpool/helpers/Utils
NameAndType	nanoTime:()J
NameAndType	iterator:()Ljava/util/Iterator;
class	java/util/Iterator
NameAndType	next:()Ljava/lang/Object;
Asciz	scala/actors/threadpool/Callable;
NameAndType	submit:(Lscala/actors/threadpool/Callable;)Lscala/actors/threadpool/Future;
class	java/util/List
NameAndType	add:(Ljava/lang/Object;)Z
NameAndType	poll:()Lscala/actors/threadpool/Future;
class	scala/actors/threadpool/TimeUnit
NameAndType	NANOSECONDS:Lscala/actors/threadpool/TimeUnit;
NameAndType	poll:(JLscala/actors/threadpool/TimeUnit;)Lscala/actors/threadpool/Future;
Asciz	scala/actors/threadpool/TimeoutException;
NameAndType	take:()Lscala/actors/threadpool/Future;
NameAndType	get:()Ljava/lang/Object;
NameAndType	hasNext:()Z
Asciz	scala/actors/threadpool/Future;
NameAndType	cancel:(Z)Z
Asciz	java/lang/InterruptedException;
Asciz	scala/actors/threadpool/ExecutionException;
Asciz	java/lang/RuntimeException;
NameAndType	"<init>":(Ljava/lang/Throwable;)V
NameAndType	doInvokeAny:(Ljava/util/Collection;ZJ)Ljava/lang/Object;
NameAndType	$assertionsDisabled:Z
Asciz	java/lang/AssertionError;
NameAndType	toNanos:(J)J
NameAndType	isDone:()Z
Asciz	scala/actors/threadpool/CancellationException;
Asciz	java/lang/Runnable;
NameAndType	get:(JLscala/actors/threadpool/TimeUnit;)Ljava/lang/Object;
Asciz	scala/actors/threadpool/AbstractExecutorService;
class	java/lang/Class
NameAndType	desiredAssertionStatus:()Z
Asciz	java/lang/Object;
Asciz	scala/actors/threadpool/ExecutorService;
Asciz	(Ljava/lang/Runnable;Ljava/lang/Object;)V;
Asciz	(Lscala/actors/threadpool/Callable;)V;
Asciz	execute;
Asciz	(Ljava/lang/Runnable;)V;
Asciz	java/util/Collection;
Asciz	size;
Asciz	()I;
Asciz	(I)V;
Asciz	(Lscala/actors/threadpool/Executor;)V;
Asciz	scala/actors/threadpool/helpers/Utils;
Asciz	nanoTime;
Asciz	()J;
Asciz	iterator;
Asciz	()Ljava/util/Iterator;;
Asciz	java/util/Iterator;
Asciz	next;
Asciz	()Ljava/lang/Object;;
Asciz	java/util/List;
Asciz	add;
Asciz	(Ljava/lang/Object;)Z;
Asciz	poll;
Asciz	()Lscala/actors/threadpool/Future;;
Asciz	scala/actors/threadpool/TimeUnit;
Asciz	NANOSECONDS;
Asciz	Lscala/actors/threadpool/TimeUnit;;
Asciz	(JLscala/actors/threadpool/TimeUnit;)Lscala/actors/threadpool/Future;;
Asciz	take;
Asciz	get;
Asciz	hasNext;
Asciz	()Z;
Asciz	cancel;
Asciz	(Z)Z;
Asciz	(Ljava/lang/Throwable;)V;
Asciz	toNanos;
Asciz	(J)J;
Asciz	isDone;
Asciz	(JLscala/actors/threadpool/TimeUnit;)Ljava/lang/Object;;
Asciz	java/lang/Class;
Asciz	desiredAssertionStatus;

{
static final boolean $assertionsDisabled;
  Signature: Z

public scala.actors.threadpool.AbstractExecutorService();
  Signature: ()V
  Code:
   Stack=1, Locals=1, Args_size=1
	aload_0
	invokespecial	Method java/lang/Object."<init>":()V
	return
  Labels:

protected scala.actors.threadpool.RunnableFuture newTaskFor(java.lang.Runnable, java.lang.Object);
  Signature: (Ljava/lang/Runnable;Ljava/lang/Object;)Lscala/actors/threadpool/RunnableFuture;
  Code:
   Stack=4, Locals=3, Args_size=3
	new	class scala/actors/threadpool/FutureTask
	dup
	aload_1
	aload_2
	invokespecial	Method scala/actors/threadpool/FutureTask."<init>":(Ljava/lang/Runnable;Ljava/lang/Object;)V
	areturn
  Labels:

protected scala.actors.threadpool.RunnableFuture newTaskFor(scala.actors.threadpool.Callable);
  Signature: (Lscala/actors/threadpool/Callable;)Lscala/actors/threadpool/RunnableFuture;
  Code:
   Stack=3, Locals=2, Args_size=2
	new	class scala/actors/threadpool/FutureTask
	dup
	aload_1
	invokespecial	Method scala/actors/threadpool/FutureTask."<init>":(Lscala/actors/threadpool/Callable;)V
	areturn
  Labels:

public scala.actors.threadpool.Future submit(java.lang.Runnable);
  Signature: (Ljava/lang/Runnable;)Lscala/actors/threadpool/Future;
  Code:
   Stack=3, Locals=3, Args_size=2
	aload_1
	ifnonnull	l1 // aload_0
	new	class java/lang/NullPointerException
	dup
	invokespecial	Method java/lang/NullPointerException."<init>":()V
	athrow
l1	aload_0
	aload_1
	aconst_null
	invokevirtual	Method newTaskFor:(Ljava/lang/Runnable;Ljava/lang/Object;)Lscala/actors/threadpool/RunnableFuture;
	astore_2
	aload_0
	aload_2
	invokevirtual	Method execute:(Ljava/lang/Runnable;)V
	aload_2
	areturn
  Labels:
   	l1 = 12 // aload_0

public scala.actors.threadpool.Future submit(java.lang.Runnable, java.lang.Object);
  Signature: (Ljava/lang/Runnable;Ljava/lang/Object;)Lscala/actors/threadpool/Future;
  Code:
   Stack=3, Locals=4, Args_size=3
	aload_1
	ifnonnull	l1 // aload_0
	new	class java/lang/NullPointerException
	dup
	invokespecial	Method java/lang/NullPointerException."<init>":()V
	athrow
l1	aload_0
	aload_1
	aload_2
	invokevirtual	Method newTaskFor:(Ljava/lang/Runnable;Ljava/lang/Object;)Lscala/actors/threadpool/RunnableFuture;
	astore_3
	aload_0
	aload_3
	invokevirtual	Method execute:(Ljava/lang/Runnable;)V
	aload_3
	areturn
  Labels:
   	l1 = 12 // aload_0

public scala.actors.threadpool.Future submit(scala.actors.threadpool.Callable);
  Signature: (Lscala/actors/threadpool/Callable;)Lscala/actors/threadpool/Future;
  Code:
   Stack=2, Locals=3, Args_size=2
	aload_1
	ifnonnull	l1 // aload_0
	new	class java/lang/NullPointerException
	dup
	invokespecial	Method java/lang/NullPointerException."<init>":()V
	athrow
l1	aload_0
	aload_1
	invokevirtual	Method newTaskFor:(Lscala/actors/threadpool/Callable;)Lscala/actors/threadpool/RunnableFuture;
	astore_2
	aload_0
	aload_2
	invokevirtual	Method execute:(Ljava/lang/Runnable;)V
	aload_2
	areturn
  Labels:
   	l1 = 12 // aload_0

private java.lang.Object doInvokeAny(java.util.Collection, boolean, long)   throws java.lang.InterruptedException, scala.actors.threadpool.ExecutionException, scala.actors.threadpool.TimeoutException;
  Signature: (Ljava/util/Collection;ZJ)Ljava/lang/Object;
  Code:
   Stack=6, Locals=18, Args_size=4
	aload_1
	ifnonnull	l1 // aload_1
	new	class java/lang/NullPointerException
	dup
	invokespecial	Method java/lang/NullPointerException."<init>":()V
	athrow
l1	aload_1
	invokeinterface	InterfaceMethod java/util/Collection.size:()I
	istore	5
	iload	5
	ifne	l2 // new
	new	class java/lang/IllegalArgumentException
	dup
	invokespecial	Method java/lang/IllegalArgumentException."<init>":()V
	athrow
l2	new	class java/util/ArrayList
	dup
	iload	5
	invokespecial	Method java/util/ArrayList."<init>":(I)V
	astore	6
	new	class scala/actors/threadpool/ExecutorCompletionService
	dup
	aload_0
	invokespecial	Method scala/actors/threadpool/ExecutorCompletionService."<init>":(Lscala/actors/threadpool/Executor;)V
	astore	7
	aconst_null
	astore	8
	iload_2
	ifeq	l3 // lconst_0
	invokestatic	Method scala/actors/threadpool/helpers/Utils.nanoTime:()J
	goto	l4 // lstore
l3	lconst_0
l4	lstore	9
	aload_1
	invokeinterface	InterfaceMethod java/util/Collection.iterator:()Ljava/util/Iterator;
	astore	11
	aload	6
	aload	7
	aload	11
	invokeinterface	InterfaceMethod java/util/Iterator.next:()Ljava/lang/Object;
	checkcast	class scala/actors/threadpool/Callable
	invokevirtual	Method scala/actors/threadpool/ExecutorCompletionService.submit:(Lscala/actors/threadpool/Callable;)Lscala/actors/threadpool/Future;
	invokeinterface	InterfaceMethod java/util/List.add:(Ljava/lang/Object;)Z
	pop
	iinc	5, -1
	iconst_1
	istore	12
l14	aload	7
	invokevirtual	Method scala/actors/threadpool/ExecutorCompletionService.poll:()Lscala/actors/threadpool/Future;
	astore	13
	aload	13
	ifnonnull	l5 // aload
	iload	5
	ifle	l6 // iload
	iinc	5, -1
	aload	6
	aload	7
	aload	11
	invokeinterface	InterfaceMethod java/util/Iterator.next:()Ljava/lang/Object;
	checkcast	class scala/actors/threadpool/Callable
	invokevirtual	Method scala/actors/threadpool/ExecutorCompletionService.submit:(Lscala/actors/threadpool/Callable;)Lscala/actors/threadpool/Future;
	invokeinterface	InterfaceMethod java/util/List.add:(Ljava/lang/Object;)Z
	pop
	iinc	12, 1
	goto	l5 // aload
l6	iload	12
	ifne	l7 // iload_2
	goto	l8 // aload
l7	iload_2
	ifeq	l9 // aload
	aload	7
	lload_3
	getstatic	Field scala/actors/threadpool/TimeUnit.NANOSECONDS:Lscala/actors/threadpool/TimeUnit;
	invokevirtual	Method scala/actors/threadpool/ExecutorCompletionService.poll:(JLscala/actors/threadpool/TimeUnit;)Lscala/actors/threadpool/Future;
	astore	13
	aload	13
	ifnonnull	l10 // invokestatic
	new	class scala/actors/threadpool/TimeoutException
	dup
	invokespecial	Method scala/actors/threadpool/TimeoutException."<init>":()V
	athrow
l10	invokestatic	Method scala/actors/threadpool/helpers/Utils.nanoTime:()J
	lstore	14
	lload_3
	lload	14
	lload	9
	lsub
	lsub
	lstore_3
	lload	14
	lstore	9
	goto	l5 // aload
l9	aload	7
	invokevirtual	Method scala/actors/threadpool/ExecutorCompletionService.take:()Lscala/actors/threadpool/Future;
	astore	13
l5	aload	13
	ifnull	l11 // goto
	iinc	12, -1
	aload	13
	invokeinterface	InterfaceMethod scala/actors/threadpool/Future.get:()Ljava/lang/Object;
	astore	14
	aload	6
	invokeinterface	InterfaceMethod java/util/List.iterator:()Ljava/util/Iterator;
	astore	15
l13	aload	15
	invokeinterface	InterfaceMethod java/util/Iterator.hasNext:()Z
	ifeq	l12 // aload
	aload	15
	invokeinterface	InterfaceMethod java/util/Iterator.next:()Ljava/lang/Object;
	checkcast	class scala/actors/threadpool/Future
	iconst_1
	invokeinterface	InterfaceMethod scala/actors/threadpool/Future.cancel:(Z)Z
	pop
	goto	l13 // aload
l12	aload	14
	areturn
	astore	14
	aload	14
	athrow
	astore	14
	aload	14
	astore	8
	goto	l11 // goto
	astore	14
	new	class scala/actors/threadpool/ExecutionException
	dup
	aload	14
	invokespecial	Method scala/actors/threadpool/ExecutionException."<init>":(Ljava/lang/Throwable;)V
	astore	8
l11	goto	l14 // aload
l8	aload	8
	ifnonnull	l15 // aload
	new	class scala/actors/threadpool/ExecutionException
	dup
	invokespecial	Method scala/actors/threadpool/ExecutionException."<init>":()V
	astore	8
l15	aload	8
	athrow
	astore	16
	aload	6
	invokeinterface	InterfaceMethod java/util/List.iterator:()Ljava/util/Iterator;
	astore	17
l17	aload	17
	invokeinterface	InterfaceMethod java/util/Iterator.hasNext:()Z
	ifeq	l16 // aload
	aload	17
	invokeinterface	InterfaceMethod java/util/Iterator.next:()Ljava/lang/Object;
	checkcast	class scala/actors/threadpool/Future
	iconst_1
	invokeinterface	InterfaceMethod scala/actors/threadpool/Future.cancel:(Z)Z
	pop
	goto	l17 // aload
l16	aload	16
	athrow
  Labels:
   	l1 = 12 // aload_1
   	l2 = 33 // new
   	l3 = 67 // lconst_0
   	l4 = 68 // lstore
   	l14 = 107 // aload
   	l6 = 156 // iload
   	l7 = 164 // iload_2
   	l10 = 192 // invokestatic
   	l9 = 212 // aload
   	l5 = 219 // aload
   	l13 = 245 // aload
   	l12 = 275 // aload
   	l11 = 305 // goto
   	l8 = 308 // aload
   	l15 = 322 // aload
   	l17 = 336 // aload
   	l16 = 366 // aload
  Exception table:
   from   to  target type
   227   236   278   Class java/lang/InterruptedException

   227   236   283   Class scala/actors/threadpool/ExecutionException

   227   236   292   Class java/lang/RuntimeException

    54   236   325   any
   278   327   325   any
  Exceptions: 
   throws java.lang.InterruptedException, scala.actors.threadpool.ExecutionException, scala.actors.threadpool.TimeoutException
public java.lang.Object invokeAny(java.util.Collection)   throws java.lang.InterruptedException, scala.actors.threadpool.ExecutionException;
  Signature: (Ljava/util/Collection;)Ljava/lang/Object;
  Code:
   Stack=5, Locals=3, Args_size=2
	aload_0
	aload_1
	iconst_0
	lconst_0
	invokespecial	Method doInvokeAny:(Ljava/util/Collection;ZJ)Ljava/lang/Object;
	areturn
	astore_2
	getstatic	Field $assertionsDisabled:Z
	ifne	l1 // aconst_null
	new	class java/lang/AssertionError
	dup
	invokespecial	Method java/lang/AssertionError."<init>":()V
	athrow
l1	aconst_null
	areturn
  Labels:
   	l1 = 23 // aconst_null
  Exception table:
   from   to  target type
     0     7     8   Class scala/actors/threadpool/TimeoutException

  Exceptions: 
   throws java.lang.InterruptedException, scala.actors.threadpool.ExecutionException
public java.lang.Object invokeAny(java.util.Collection, long, scala.actors.threadpool.TimeUnit)   throws java.lang.InterruptedException, scala.actors.threadpool.ExecutionException, scala.actors.threadpool.TimeoutException;
  Signature: (Ljava/util/Collection;JLscala/actors/threadpool/TimeUnit;)Ljava/lang/Object;
  Code:
   Stack=6, Locals=5, Args_size=4
	aload_0
	aload_1
	iconst_1
	aload	4
	lload_2
	invokevirtual	Method scala/actors/threadpool/TimeUnit.toNanos:(J)J
	invokespecial	Method doInvokeAny:(Ljava/util/Collection;ZJ)Ljava/lang/Object;
	areturn
  Labels:
  Exceptions: 
   throws java.lang.InterruptedException, scala.actors.threadpool.ExecutionException, scala.actors.threadpool.TimeoutException
public java.util.List invokeAll(java.util.Collection)   throws java.lang.InterruptedException;
  Signature: (Ljava/util/Collection;)Ljava/util/List;
  Code:
   Stack=3, Locals=10, Args_size=2
	aload_1
	ifnonnull	l1 // new
	new	class java/lang/NullPointerException
	dup
	invokespecial	Method java/lang/NullPointerException."<init>":()V
	athrow
l1	new	class java/util/ArrayList
	dup
	aload_1
	invokeinterface	InterfaceMethod java/util/Collection.size:()I
	invokespecial	Method java/util/ArrayList."<init>":(I)V
	astore_2
	iconst_0
	istore_3
	aload_1
	invokeinterface	InterfaceMethod java/util/Collection.iterator:()Ljava/util/Iterator;
	astore	4
l3	aload	4
	invokeinterface	InterfaceMethod java/util/Iterator.hasNext:()Z
	ifeq	l2 // aload_2
	aload_0
	aload	4
	invokeinterface	InterfaceMethod java/util/Iterator.next:()Ljava/lang/Object;
	checkcast	class scala/actors/threadpool/Callable
	invokevirtual	Method newTaskFor:(Lscala/actors/threadpool/Callable;)Lscala/actors/threadpool/RunnableFuture;
	astore	5
	aload_2
	aload	5
	invokeinterface	InterfaceMethod java/util/List.add:(Ljava/lang/Object;)Z
	pop
	aload_0
	aload	5
	invokevirtual	Method execute:(Ljava/lang/Runnable;)V
	goto	l3 // aload
l2	aload_2
	invokeinterface	InterfaceMethod java/util/List.iterator:()Ljava/util/Iterator;
	astore	4
l6	aload	4
	invokeinterface	InterfaceMethod java/util/Iterator.hasNext:()Z
	ifeq	l4 // iconst_1
	aload	4
	invokeinterface	InterfaceMethod java/util/Iterator.next:()Ljava/lang/Object;
	checkcast	class scala/actors/threadpool/Future
	astore	5
	aload	5
	invokeinterface	InterfaceMethod scala/actors/threadpool/Future.isDone:()Z
	ifne	l5 // goto
	aload	5
	invokeinterface	InterfaceMethod scala/actors/threadpool/Future.get:()Ljava/lang/Object;
	pop
	goto	l5 // goto
	astore	6
	goto	l5 // goto
	astore	6
l5	goto	l6 // aload
l4	iconst_1
	istore_3
	aload_2
	astore	4
	iload_3
	ifne	l7 // aload
	aload_2
	invokeinterface	InterfaceMethod java/util/List.iterator:()Ljava/util/Iterator;
	astore	5
l8	aload	5
	invokeinterface	InterfaceMethod java/util/Iterator.hasNext:()Z
	ifeq	l7 // aload
	aload	5
	invokeinterface	InterfaceMethod java/util/Iterator.next:()Ljava/lang/Object;
	checkcast	class scala/actors/threadpool/Future
	astore	6
	aload	6
	iconst_1
	invokeinterface	InterfaceMethod scala/actors/threadpool/Future.cancel:(Z)Z
	pop
	goto	l8 // aload
l7	aload	4
	areturn
	astore	7
	iload_3
	ifne	l9 // aload
	aload_2
	invokeinterface	InterfaceMethod java/util/List.iterator:()Ljava/util/Iterator;
	astore	8
l10	aload	8
	invokeinterface	InterfaceMethod java/util/Iterator.hasNext:()Z
	ifeq	l9 // aload
	aload	8
	invokeinterface	InterfaceMethod java/util/Iterator.next:()Ljava/lang/Object;
	checkcast	class scala/actors/threadpool/Future
	astore	9
	aload	9
	iconst_1
	invokeinterface	InterfaceMethod scala/actors/threadpool/Future.cancel:(Z)Z
	pop
	goto	l10 // aload
l9	aload	7
	athrow
  Labels:
   	l1 = 12 // new
   	l3 = 36 // aload
   	l2 = 80 // aload_2
   	l6 = 88 // aload
   	l5 = 138 // goto
   	l4 = 141 // iconst_1
   	l8 = 158 // aload
   	l7 = 192 // aload
   	l10 = 209 // aload
   	l9 = 243 // aload
  Exception table:
   from   to  target type
   120   128   131   Class scala/actors/threadpool/CancellationException

   120   128   136   Class scala/actors/threadpool/ExecutionException

    28   146   195   any
   195   197   195   any
  Exceptions: 
   throws java.lang.InterruptedException
public java.util.List invokeAll(java.util.Collection, long, scala.actors.threadpool.TimeUnit)   throws java.lang.InterruptedException;
  Signature: (Ljava/util/Collection;JLscala/actors/threadpool/TimeUnit;)Ljava/util/List;
  Code:
   Stack=6, Locals=21, Args_size=4
	aload_1
	ifnull	l1 // new
	aload	4
	ifnonnull	l2 // aload
l1	new	class java/lang/NullPointerException
	dup
	invokespecial	Method java/lang/NullPointerException."<init>":()V
	athrow
l2	aload	4
	lload_2
	invokevirtual	Method scala/actors/threadpool/TimeUnit.toNanos:(J)J
	lstore	5
	new	class java/util/ArrayList
	dup
	aload_1
	invokeinterface	InterfaceMethod java/util/Collection.size:()I
	invokespecial	Method java/util/ArrayList."<init>":(I)V
	astore	7
	iconst_0
	istore	8
	aload_1
	invokeinterface	InterfaceMethod java/util/Collection.iterator:()Ljava/util/Iterator;
	astore	9
l4	aload	9
	invokeinterface	InterfaceMethod java/util/Iterator.hasNext:()Z
	ifeq	l3 // invokestatic
	aload	7
	aload_0
	aload	9
	invokeinterface	InterfaceMethod java/util/Iterator.next:()Ljava/lang/Object;
	checkcast	class scala/actors/threadpool/Callable
	invokevirtual	Method newTaskFor:(Lscala/actors/threadpool/Callable;)Lscala/actors/threadpool/RunnableFuture;
	invokeinterface	InterfaceMethod java/util/List.add:(Ljava/lang/Object;)Z
	pop
	goto	l4 // aload
l3	invokestatic	Method scala/actors/threadpool/helpers/Utils.nanoTime:()J
	lstore	9
	aload	7
	invokeinterface	InterfaceMethod java/util/List.iterator:()Ljava/util/Iterator;
	astore	11
l9	aload	11
	invokeinterface	InterfaceMethod java/util/Iterator.hasNext:()Z
	ifeq	l5 // aload
	aload_0
	aload	11
	invokeinterface	InterfaceMethod java/util/Iterator.next:()Ljava/lang/Object;
	checkcast	class java/lang/Runnable
	checkcast	class java/lang/Runnable
	invokevirtual	Method execute:(Ljava/lang/Runnable;)V
	invokestatic	Method scala/actors/threadpool/helpers/Utils.nanoTime:()J
	lstore	12
	lload	5
	lload	12
	lload	9
	lsub
	lsub
	lstore	5
	lload	12
	lstore	9
	lload	5
	lconst_0
	lcmp
	ifgt	l6 // goto
	aload	7
	astore	14
	iload	8
	ifne	l7 // aload
	aload	7
	invokeinterface	InterfaceMethod java/util/List.iterator:()Ljava/util/Iterator;
	astore	15
l8	aload	15
	invokeinterface	InterfaceMethod java/util/Iterator.hasNext:()Z
	ifeq	l7 // aload
	aload	15
	invokeinterface	InterfaceMethod java/util/Iterator.next:()Ljava/lang/Object;
	checkcast	class scala/actors/threadpool/Future
	astore	16
	aload	16
	iconst_1
	invokeinterface	InterfaceMethod scala/actors/threadpool/Future.cancel:(Z)Z
	pop
	goto	l8 // aload
l7	aload	14
	areturn
l6	goto	l9 // aload
l5	aload	7
	invokeinterface	InterfaceMethod java/util/List.iterator:()Ljava/util/Iterator;
	astore	12
l18	aload	12
	invokeinterface	InterfaceMethod java/util/Iterator.hasNext:()Z
	ifeq	l10 // iconst_1
	aload	12
	invokeinterface	InterfaceMethod java/util/Iterator.next:()Ljava/lang/Object;
	checkcast	class scala/actors/threadpool/Future
	astore	13
	aload	13
	invokeinterface	InterfaceMethod scala/actors/threadpool/Future.isDone:()Z
	ifne	l11 // goto
	lload	5
	lconst_0
	lcmp
	ifgt	l12 // aload
	aload	7
	astore	14
	iload	8
	ifne	l13 // aload
	aload	7
	invokeinterface	InterfaceMethod java/util/List.iterator:()Ljava/util/Iterator;
	astore	15
l14	aload	15
	invokeinterface	InterfaceMethod java/util/Iterator.hasNext:()Z
	ifeq	l13 // aload
	aload	15
	invokeinterface	InterfaceMethod java/util/Iterator.next:()Ljava/lang/Object;
	checkcast	class scala/actors/threadpool/Future
	astore	16
	aload	16
	iconst_1
	invokeinterface	InterfaceMethod scala/actors/threadpool/Future.cancel:(Z)Z
	pop
	goto	l14 // aload
l13	aload	14
	areturn
l12	aload	13
	lload	5
	getstatic	Field scala/actors/threadpool/TimeUnit.NANOSECONDS:Lscala/actors/threadpool/TimeUnit;
	invokeinterface	InterfaceMethod scala/actors/threadpool/Future.get:(JLscala/actors/threadpool/TimeUnit;)Ljava/lang/Object;
	pop
	goto	l15 // invokestatic
	astore	14
	goto	l15 // invokestatic
	astore	14
	goto	l15 // invokestatic
	astore	14
	aload	7
	astore	15
	iload	8
	ifne	l16 // aload
	aload	7
	invokeinterface	InterfaceMethod java/util/List.iterator:()Ljava/util/Iterator;
	astore	16
l17	aload	16
	invokeinterface	InterfaceMethod java/util/Iterator.hasNext:()Z
	ifeq	l16 // aload
	aload	16
	invokeinterface	InterfaceMethod java/util/Iterator.next:()Ljava/lang/Object;
	checkcast	class scala/actors/threadpool/Future
	astore	17
	aload	17
	iconst_1
	invokeinterface	InterfaceMethod scala/actors/threadpool/Future.cancel:(Z)Z
	pop
	goto	l17 // aload
l16	aload	15
	areturn
l15	invokestatic	Method scala/actors/threadpool/helpers/Utils.nanoTime:()J
	lstore	14
	lload	5
	lload	14
	lload	9
	lsub
	lsub
	lstore	5
	lload	14
	lstore	9
l11	goto	l18 // aload
l10	iconst_1
	istore	8
	aload	7
	astore	12
	iload	8
	ifne	l19 // aload
	aload	7
	invokeinterface	InterfaceMethod java/util/List.iterator:()Ljava/util/Iterator;
	astore	13
l20	aload	13
	invokeinterface	InterfaceMethod java/util/Iterator.hasNext:()Z
	ifeq	l19 // aload
	aload	13
	invokeinterface	InterfaceMethod java/util/Iterator.next:()Ljava/lang/Object;
	checkcast	class scala/actors/threadpool/Future
	astore	14
	aload	14
	iconst_1
	invokeinterface	InterfaceMethod scala/actors/threadpool/Future.cancel:(Z)Z
	pop
	goto	l20 // aload
l19	aload	12
	areturn
	astore	18
	iload	8
	ifne	l21 // aload
	aload	7
	invokeinterface	InterfaceMethod java/util/List.iterator:()Ljava/util/Iterator;
	astore	19
l22	aload	19
	invokeinterface	InterfaceMethod java/util/Iterator.hasNext:()Z
	ifeq	l21 // aload
	aload	19
	invokeinterface	InterfaceMethod java/util/Iterator.next:()Ljava/lang/Object;
	checkcast	class scala/actors/threadpool/Future
	astore	20
	aload	20
	iconst_1
	invokeinterface	InterfaceMethod scala/actors/threadpool/Future.cancel:(Z)Z
	pop
	goto	l22 // aload
l21	aload	18
	athrow
  Labels:
   	l1 = 9 // new
   	l2 = 17 // aload
   	l4 = 51 // aload
   	l3 = 86 // invokestatic
   	l9 = 100 // aload
   	l8 = 171 // aload
   	l7 = 205 // aload
   	l6 = 208 // goto
   	l5 = 211 // aload
   	l18 = 220 // aload
   	l14 = 277 // aload
   	l13 = 311 // aload
   	l12 = 314 // aload
   	l17 = 360 // aload
   	l16 = 394 // aload
   	l15 = 397 // invokestatic
   	l11 = 416 // goto
   	l10 = 419 // iconst_1
   	l20 = 440 // aload
   	l19 = 474 // aload
   	l22 = 493 // aload
   	l21 = 527 // aload
  Exception table:
   from   to  target type
   314   327   330   Class scala/actors/threadpool/CancellationException

   314   327   335   Class scala/actors/threadpool/ExecutionException

   314   327   340   Class scala/actors/threadpool/TimeoutException

    43   157   477   any
   208   263   477   any
   314   346   477   any
   397   426   477   any
   477   479   477   any
  Exceptions: 
   throws java.lang.InterruptedException
static {};
  Signature: ()V
  Code:
   Stack=1, Locals=0, Args_size=0
	ldc_w	class scala/actors/threadpool/AbstractExecutorService
	invokevirtual	Method java/lang/Class.desiredAssertionStatus:()Z
	ifne	l1 // iconst_0
	iconst_1
	goto	l2 // putstatic
l1	iconst_0
l2	putstatic	Field $assertionsDisabled:Z
	return
  Labels:
   	l1 = 13 // iconst_0
   	l2 = 14 // putstatic

}

