public class scala.actors.threadpool.Arrays extends java.lang.Object
  minor version: 0
  major version: 49
  Constant pool:
Method	java/lang/Object."<init>":()V
Method	java/util/Arrays.sort:([J)V
Method	java/util/Arrays.sort:([JII)V
Method	java/util/Arrays.sort:([I)V
Method	java/util/Arrays.sort:([III)V
Method	java/util/Arrays.sort:([S)V
Method	java/util/Arrays.sort:([SII)V
Method	java/util/Arrays.sort:([C)V
Method	java/util/Arrays.sort:([CII)V
Method	java/util/Arrays.sort:([B)V
Method	java/util/Arrays.sort:([BII)V
Method	java/util/Arrays.sort:([D)V
Method	java/util/Arrays.sort:([DII)V
Method	java/util/Arrays.sort:([F)V
Method	java/util/Arrays.sort:([FII)V
Method	java/util/Arrays.sort:([Ljava/lang/Object;)V
Method	java/util/Arrays.sort:([Ljava/lang/Object;II)V
Method	java/util/Arrays.sort:([Ljava/lang/Object;Ljava/util/Comparator;)V
Method	java/util/Arrays.sort:([Ljava/lang/Object;IILjava/util/Comparator;)V
Method	java/util/Arrays.binarySearch:([JJ)I
Method	java/util/Arrays.binarySearch:([II)I
Method	java/util/Arrays.binarySearch:([SS)I
Method	java/util/Arrays.binarySearch:([CC)I
Method	java/util/Arrays.binarySearch:([BB)I
Method	java/util/Arrays.binarySearch:([DD)I
Method	java/util/Arrays.binarySearch:([FF)I
Method	java/util/Arrays.binarySearch:([Ljava/lang/Object;Ljava/lang/Object;)I
Method	java/util/Arrays.binarySearch:([Ljava/lang/Object;Ljava/lang/Object;Ljava/util/Comparator;)I
Method	java/util/Arrays.equals:([J[J)Z
Method	java/util/Arrays.equals:([I[I)Z
Method	java/util/Arrays.equals:([S[S)Z
Method	java/util/Arrays.equals:([C[C)Z
Method	java/util/Arrays.equals:([B[B)Z
Method	java/util/Arrays.equals:([Z[Z)Z
Method	java/util/Arrays.equals:([D[D)Z
Method	java/util/Arrays.equals:([F[F)Z
Method	java/util/Arrays.equals:([Ljava/lang/Object;[Ljava/lang/Object;)Z
Method	java/util/Arrays.fill:([JJ)V
Method	java/util/Arrays.fill:([JIIJ)V
Method	java/util/Arrays.fill:([II)V
Method	java/util/Arrays.fill:([IIII)V
Method	java/util/Arrays.fill:([SS)V
Method	java/util/Arrays.fill:([SIIS)V
Method	java/util/Arrays.fill:([CC)V
Method	java/util/Arrays.fill:([CIIC)V
Method	java/util/Arrays.fill:([BB)V
Method	java/util/Arrays.fill:([BIIB)V
Method	java/util/Arrays.fill:([ZZ)V
Method	java/util/Arrays.fill:([ZIIZ)V
Method	java/util/Arrays.fill:([DD)V
Method	java/util/Arrays.fill:([DIID)V
Method	java/util/Arrays.fill:([FF)V
Method	java/util/Arrays.fill:([FIIF)V
Method	java/util/Arrays.fill:([Ljava/lang/Object;Ljava/lang/Object;)V
Method	java/util/Arrays.fill:([Ljava/lang/Object;IILjava/lang/Object;)V
Method	java/lang/Object.getClass:()Ljava/lang/Class;
Method	scala/actors/threadpool/Arrays.copyOf:([Ljava/lang/Object;ILjava/lang/Class;)[Ljava/lang/Object;
class	"[Ljava/lang/Object;"
class	java/lang/Object
Method	java/lang/Class.getComponentType:()Ljava/lang/Class;
Method	java/lang/reflect/Array.newInstance:(Ljava/lang/Class;I)Ljava/lang/Object;
Method	java/lang/System.arraycopy:(Ljava/lang/Object;ILjava/lang/Object;II)V
Method	scala/actors/threadpool/Arrays.copyOfRange:([Ljava/lang/Object;IILjava/lang/Class;)[Ljava/lang/Object;
class	java/lang/IllegalArgumentException
class	java/lang/StringBuilder
Method	java/lang/StringBuilder."<init>":()V
Method	java/lang/StringBuilder.append:(I)Ljava/lang/StringBuilder;
String	 > 
Method	java/lang/StringBuilder.append:(Ljava/lang/String;)Ljava/lang/StringBuilder;
Method	java/lang/StringBuilder.toString:()Ljava/lang/String;
Method	java/lang/IllegalArgumentException."<init>":(Ljava/lang/String;)V
Method	java/util/Arrays.asList:([Ljava/lang/Object;)Ljava/util/List;
Method	java/lang/Float.floatToIntBits:(F)I
Method	java/lang/Double.doubleToLongBits:(D)J
Method	java/lang/Object.hashCode:()I
Method	scala/actors/threadpool/Arrays.deepHashCode:([Ljava/lang/Object;)I
class	"[B"
Method	scala/actors/threadpool/Arrays.hashCode:([B)I
class	"[S"
Method	scala/actors/threadpool/Arrays.hashCode:([S)I
class	"[I"
Method	scala/actors/threadpool/Arrays.hashCode:([I)I
class	"[J"
Method	scala/actors/threadpool/Arrays.hashCode:([J)I
class	"[C"
Method	scala/actors/threadpool/Arrays.hashCode:([C)I
class	"[Z"
Method	scala/actors/threadpool/Arrays.hashCode:([Z)I
class	"[F"
Method	scala/actors/threadpool/Arrays.hashCode:([F)I
class	"[D"
Method	scala/actors/threadpool/Arrays.hashCode:([D)I
Method	java/lang/Class.isArray:()Z
Method	java/lang/Object.equals:(Ljava/lang/Object;)Z
Method	scala/actors/threadpool/Arrays.deepEquals:([Ljava/lang/Object;[Ljava/lang/Object;)Z
Method	scala/actors/threadpool/Arrays.equals:([B[B)Z
Method	scala/actors/threadpool/Arrays.equals:([S[S)Z
Method	scala/actors/threadpool/Arrays.equals:([I[I)Z
Method	scala/actors/threadpool/Arrays.equals:([J[J)Z
Method	scala/actors/threadpool/Arrays.equals:([C[C)Z
Method	scala/actors/threadpool/Arrays.equals:([Z[Z)Z
Method	scala/actors/threadpool/Arrays.equals:([F[F)Z
Method	scala/actors/threadpool/Arrays.equals:([D[D)Z
String	null
String	[]
class	java/lang/StringBuffer
Method	java/lang/StringBuffer."<init>":()V
Method	java/lang/StringBuffer.append:(C)Ljava/lang/StringBuffer;
Method	java/lang/StringBuffer.append:(J)Ljava/lang/StringBuffer;
String	, 
Method	java/lang/StringBuffer.append:(Ljava/lang/String;)Ljava/lang/StringBuffer;
Method	java/lang/StringBuffer.toString:()Ljava/lang/String;
Method	java/lang/StringBuffer.append:(I)Ljava/lang/StringBuffer;
Method	java/lang/StringBuffer.append:(Z)Ljava/lang/StringBuffer;
Method	java/lang/StringBuffer.append:(F)Ljava/lang/StringBuffer;
Method	java/lang/StringBuffer.append:(D)Ljava/lang/StringBuffer;
Method	java/lang/StringBuffer.append:(Ljava/lang/Object;)Ljava/lang/StringBuffer;
class	java/util/ArrayList
Method	java/util/ArrayList."<init>":()V
Method	scala/actors/threadpool/Arrays.deepToString:([Ljava/lang/Object;Ljava/lang/StringBuffer;Ljava/util/List;)V
InterfaceMethod	java/util/List.add:(Ljava/lang/Object;)Z
Method	java/lang/Object.toString:()Ljava/lang/String;
InterfaceMethod	java/util/List.contains:(Ljava/lang/Object;)Z
String	[...]
Method	scala/actors/threadpool/Arrays.toString:([B)Ljava/lang/String;
Method	scala/actors/threadpool/Arrays.toString:([S)Ljava/lang/String;
Method	scala/actors/threadpool/Arrays.toString:([I)Ljava/lang/String;
Method	scala/actors/threadpool/Arrays.toString:([J)Ljava/lang/String;
Method	scala/actors/threadpool/Arrays.toString:([C)Ljava/lang/String;
Method	scala/actors/threadpool/Arrays.toString:([Z)Ljava/lang/String;
Method	scala/actors/threadpool/Arrays.toString:([F)Ljava/lang/String;
Method	scala/actors/threadpool/Arrays.toString:([D)Ljava/lang/String;
String	
InterfaceMethod	java/util/List.size:()I
InterfaceMethod	java/util/List.remove:(I)Ljava/lang/Object;
class	scala/actors/threadpool/Arrays
Asciz	<init>;
Asciz	()V;
Asciz	Code;
Asciz	sort;
Asciz	([J)V;
Asciz	([JII)V;
Asciz	([I)V;
Asciz	([III)V;
Asciz	([S)V;
Asciz	([SII)V;
Asciz	([C)V;
Asciz	([CII)V;
Asciz	([B)V;
Asciz	([BII)V;
Asciz	([D)V;
Asciz	([DII)V;
Asciz	([F)V;
Asciz	([FII)V;
Asciz	([Ljava/lang/Object;)V;
Asciz	([Ljava/lang/Object;II)V;
Asciz	([Ljava/lang/Object;Ljava/util/Comparator;)V;
Asciz	([Ljava/lang/Object;IILjava/util/Comparator;)V;
Asciz	binarySearch;
Asciz	([JJ)I;
Asciz	([II)I;
Asciz	([SS)I;
Asciz	([CC)I;
Asciz	([BB)I;
Asciz	([DD)I;
Asciz	([FF)I;
Asciz	([Ljava/lang/Object;Ljava/lang/Object;)I;
Asciz	([Ljava/lang/Object;Ljava/lang/Object;Ljava/util/Comparator;)I;
Asciz	equals;
Asciz	([J[J)Z;
Asciz	([I[I)Z;
Asciz	([S[S)Z;
Asciz	([C[C)Z;
Asciz	([B[B)Z;
Asciz	([Z[Z)Z;
Asciz	([D[D)Z;
Asciz	([F[F)Z;
Asciz	([Ljava/lang/Object;[Ljava/lang/Object;)Z;
Asciz	fill;
Asciz	([JJ)V;
Asciz	([JIIJ)V;
Asciz	([II)V;
Asciz	([IIII)V;
Asciz	([SS)V;
Asciz	([SIIS)V;
Asciz	([CC)V;
Asciz	([CIIC)V;
Asciz	([BB)V;
Asciz	([BIIB)V;
Asciz	([ZZ)V;
Asciz	([ZIIZ)V;
Asciz	([DD)V;
Asciz	([DIID)V;
Asciz	([FF)V;
Asciz	([FIIF)V;
Asciz	([Ljava/lang/Object;Ljava/lang/Object;)V;
Asciz	([Ljava/lang/Object;IILjava/lang/Object;)V;
Asciz	copyOf;
Asciz	([Ljava/lang/Object;I)[Ljava/lang/Object;;
Asciz	([Ljava/lang/Object;ILjava/lang/Class;)[Ljava/lang/Object;;
Asciz	([BI)[B;
Asciz	([SI)[S;
Asciz	([II)[I;
Asciz	([JI)[J;
Asciz	([CI)[C;
Asciz	([FI)[F;
Asciz	([DI)[D;
Asciz	([ZI)[Z;
Asciz	copyOfRange;
Asciz	([Ljava/lang/Object;II)[Ljava/lang/Object;;
Asciz	([Ljava/lang/Object;IILjava/lang/Class;)[Ljava/lang/Object;;
Asciz	([BII)[B;
Asciz	([SII)[S;
Asciz	([III)[I;
Asciz	([JII)[J;
Asciz	([CII)[C;
Asciz	([FII)[F;
Asciz	([DII)[D;
Asciz	([ZII)[Z;
Asciz	asList;
Asciz	([Ljava/lang/Object;)Ljava/util/List;;
Asciz	hashCode;
Asciz	([J)I;
Asciz	([I)I;
Asciz	([S)I;
Asciz	([C)I;
Asciz	([B)I;
Asciz	([Z)I;
Asciz	([F)I;
Asciz	([D)I;
Asciz	([Ljava/lang/Object;)I;
Asciz	deepHashCode;
Asciz	deepEquals;
Asciz	toString;
Asciz	([J)Ljava/lang/String;;
Asciz	([I)Ljava/lang/String;;
Asciz	([S)Ljava/lang/String;;
Asciz	([C)Ljava/lang/String;;
Asciz	([B)Ljava/lang/String;;
Asciz	([Z)Ljava/lang/String;;
Asciz	([F)Ljava/lang/String;;
Asciz	([D)Ljava/lang/String;;
Asciz	([Ljava/lang/Object;)Ljava/lang/String;;
Asciz	deepToString;
Asciz	([Ljava/lang/Object;Ljava/lang/StringBuffer;Ljava/util/List;)V;
NameAndType	"<init>":()V
class	java/util/Arrays
NameAndType	sort:([J)V
NameAndType	sort:([JII)V
NameAndType	sort:([I)V
NameAndType	sort:([III)V
NameAndType	sort:([S)V
NameAndType	sort:([SII)V
NameAndType	sort:([C)V
NameAndType	sort:([CII)V
NameAndType	sort:([B)V
NameAndType	sort:([BII)V
NameAndType	sort:([D)V
NameAndType	sort:([DII)V
NameAndType	sort:([F)V
NameAndType	sort:([FII)V
NameAndType	sort:([Ljava/lang/Object;)V
NameAndType	sort:([Ljava/lang/Object;II)V
NameAndType	sort:([Ljava/lang/Object;Ljava/util/Comparator;)V
NameAndType	sort:([Ljava/lang/Object;IILjava/util/Comparator;)V
NameAndType	binarySearch:([JJ)I
NameAndType	binarySearch:([II)I
NameAndType	binarySearch:([SS)I
NameAndType	binarySearch:([CC)I
NameAndType	binarySearch:([BB)I
NameAndType	binarySearch:([DD)I
NameAndType	binarySearch:([FF)I
NameAndType	binarySearch:([Ljava/lang/Object;Ljava/lang/Object;)I
NameAndType	binarySearch:([Ljava/lang/Object;Ljava/lang/Object;Ljava/util/Comparator;)I
NameAndType	equals:([J[J)Z
NameAndType	equals:([I[I)Z
NameAndType	equals:([S[S)Z
NameAndType	equals:([C[C)Z
NameAndType	equals:([B[B)Z
NameAndType	equals:([Z[Z)Z
NameAndType	equals:([D[D)Z
NameAndType	equals:([F[F)Z
NameAndType	equals:([Ljava/lang/Object;[Ljava/lang/Object;)Z
NameAndType	fill:([JJ)V
NameAndType	fill:([JIIJ)V
NameAndType	fill:([II)V
NameAndType	fill:([IIII)V
NameAndType	fill:([SS)V
NameAndType	fill:([SIIS)V
NameAndType	fill:([CC)V
NameAndType	fill:([CIIC)V
NameAndType	fill:([BB)V
NameAndType	fill:([BIIB)V
NameAndType	fill:([ZZ)V
NameAndType	fill:([ZIIZ)V
NameAndType	fill:([DD)V
NameAndType	fill:([DIID)V
NameAndType	fill:([FF)V
NameAndType	fill:([FIIF)V
NameAndType	fill:([Ljava/lang/Object;Ljava/lang/Object;)V
NameAndType	fill:([Ljava/lang/Object;IILjava/lang/Object;)V
NameAndType	getClass:()Ljava/lang/Class;
NameAndType	copyOf:([Ljava/lang/Object;ILjava/lang/Class;)[Ljava/lang/Object;
Asciz	[Ljava/lang/Object;;
Asciz	java/lang/Object;
class	java/lang/Class
NameAndType	getComponentType:()Ljava/lang/Class;
class	java/lang/reflect/Array
NameAndType	newInstance:(Ljava/lang/Class;I)Ljava/lang/Object;
class	java/lang/System
NameAndType	arraycopy:(Ljava/lang/Object;ILjava/lang/Object;II)V
NameAndType	copyOfRange:([Ljava/lang/Object;IILjava/lang/Class;)[Ljava/lang/Object;
Asciz	java/lang/IllegalArgumentException;
Asciz	java/lang/StringBuilder;
NameAndType	append:(I)Ljava/lang/StringBuilder;
Asciz	 > ;
NameAndType	append:(Ljava/lang/String;)Ljava/lang/StringBuilder;
NameAndType	toString:()Ljava/lang/String;
NameAndType	"<init>":(Ljava/lang/String;)V
NameAndType	asList:([Ljava/lang/Object;)Ljava/util/List;
class	java/lang/Float
NameAndType	floatToIntBits:(F)I
class	java/lang/Double
NameAndType	doubleToLongBits:(D)J
NameAndType	hashCode:()I
NameAndType	deepHashCode:([Ljava/lang/Object;)I
Asciz	[B;
NameAndType	hashCode:([B)I
Asciz	[S;
NameAndType	hashCode:([S)I
Asciz	[I;
NameAndType	hashCode:([I)I
Asciz	[J;
NameAndType	hashCode:([J)I
Asciz	[C;
NameAndType	hashCode:([C)I
Asciz	[Z;
NameAndType	hashCode:([Z)I
Asciz	[F;
NameAndType	hashCode:([F)I
Asciz	[D;
NameAndType	hashCode:([D)I
NameAndType	isArray:()Z
NameAndType	equals:(Ljava/lang/Object;)Z
NameAndType	deepEquals:([Ljava/lang/Object;[Ljava/lang/Object;)Z
Asciz	null;
Asciz	[];
Asciz	java/lang/StringBuffer;
NameAndType	append:(C)Ljava/lang/StringBuffer;
NameAndType	append:(J)Ljava/lang/StringBuffer;
Asciz	, ;
NameAndType	append:(Ljava/lang/String;)Ljava/lang/StringBuffer;
NameAndType	append:(I)Ljava/lang/StringBuffer;
NameAndType	append:(Z)Ljava/lang/StringBuffer;
NameAndType	append:(F)Ljava/lang/StringBuffer;
NameAndType	append:(D)Ljava/lang/StringBuffer;
NameAndType	append:(Ljava/lang/Object;)Ljava/lang/StringBuffer;
Asciz	java/util/ArrayList;
NameAndType	deepToString:([Ljava/lang/Object;Ljava/lang/StringBuffer;Ljava/util/List;)V
class	java/util/List
NameAndType	add:(Ljava/lang/Object;)Z
NameAndType	contains:(Ljava/lang/Object;)Z
Asciz	[...];
NameAndType	toString:([B)Ljava/lang/String;
NameAndType	toString:([S)Ljava/lang/String;
NameAndType	toString:([I)Ljava/lang/String;
NameAndType	toString:([J)Ljava/lang/String;
NameAndType	toString:([C)Ljava/lang/String;
NameAndType	toString:([Z)Ljava/lang/String;
NameAndType	toString:([F)Ljava/lang/String;
NameAndType	toString:([D)Ljava/lang/String;
Asciz	;
NameAndType	size:()I
NameAndType	remove:(I)Ljava/lang/Object;
Asciz	scala/actors/threadpool/Arrays;
Asciz	java/util/Arrays;
Asciz	getClass;
Asciz	()Ljava/lang/Class;;
Asciz	java/lang/Class;
Asciz	getComponentType;
Asciz	java/lang/reflect/Array;
Asciz	newInstance;
Asciz	(Ljava/lang/Class;I)Ljava/lang/Object;;
Asciz	java/lang/System;
Asciz	arraycopy;
Asciz	(Ljava/lang/Object;ILjava/lang/Object;II)V;
Asciz	append;
Asciz	(I)Ljava/lang/StringBuilder;;
Asciz	(Ljava/lang/String;)Ljava/lang/StringBuilder;;
Asciz	()Ljava/lang/String;;
Asciz	(Ljava/lang/String;)V;
Asciz	java/lang/Float;
Asciz	floatToIntBits;
Asciz	(F)I;
Asciz	java/lang/Double;
Asciz	doubleToLongBits;
Asciz	(D)J;
Asciz	()I;
Asciz	isArray;
Asciz	()Z;
Asciz	(Ljava/lang/Object;)Z;
Asciz	(C)Ljava/lang/StringBuffer;;
Asciz	(J)Ljava/lang/StringBuffer;;
Asciz	(Ljava/lang/String;)Ljava/lang/StringBuffer;;
Asciz	(I)Ljava/lang/StringBuffer;;
Asciz	(Z)Ljava/lang/StringBuffer;;
Asciz	(F)Ljava/lang/StringBuffer;;
Asciz	(D)Ljava/lang/StringBuffer;;
Asciz	(Ljava/lang/Object;)Ljava/lang/StringBuffer;;
Asciz	java/util/List;
Asciz	add;
Asciz	contains;
Asciz	size;
Asciz	remove;
Asciz	(I)Ljava/lang/Object;;

{
private scala.actors.threadpool.Arrays();
  Signature: ()V
  Code:
   Stack=1, Locals=1, Args_size=1
	aload_0
	invokespecial	Method java/lang/Object."<init>":()V
	return
  Labels:

public static void sort(long[]);
  Signature: ([J)V
  Code:
   Stack=1, Locals=1, Args_size=1
	aload_0
	invokestatic	Method java/util/Arrays.sort:([J)V
	return
  Labels:

public static void sort(long[], int, int);
  Signature: ([JII)V
  Code:
   Stack=3, Locals=3, Args_size=3
	aload_0
	iload_1
	iload_2
	invokestatic	Method java/util/Arrays.sort:([JII)V
	return
  Labels:

public static void sort(int[]);
  Signature: ([I)V
  Code:
   Stack=1, Locals=1, Args_size=1
	aload_0
	invokestatic	Method java/util/Arrays.sort:([I)V
	return
  Labels:

public static void sort(int[], int, int);
  Signature: ([III)V
  Code:
   Stack=3, Locals=3, Args_size=3
	aload_0
	iload_1
	iload_2
	invokestatic	Method java/util/Arrays.sort:([III)V
	return
  Labels:

public static void sort(short[]);
  Signature: ([S)V
  Code:
   Stack=1, Locals=1, Args_size=1
	aload_0
	invokestatic	Method java/util/Arrays.sort:([S)V
	return
  Labels:

public static void sort(short[], int, int);
  Signature: ([SII)V
  Code:
   Stack=3, Locals=3, Args_size=3
	aload_0
	iload_1
	iload_2
	invokestatic	Method java/util/Arrays.sort:([SII)V
	return
  Labels:

public static void sort(char[]);
  Signature: ([C)V
  Code:
   Stack=1, Locals=1, Args_size=1
	aload_0
	invokestatic	Method java/util/Arrays.sort:([C)V
	return
  Labels:

public static void sort(char[], int, int);
  Signature: ([CII)V
  Code:
   Stack=3, Locals=3, Args_size=3
	aload_0
	iload_1
	iload_2
	invokestatic	Method java/util/Arrays.sort:([CII)V
	return
  Labels:

public static void sort(byte[]);
  Signature: ([B)V
  Code:
   Stack=1, Locals=1, Args_size=1
	aload_0
	invokestatic	Method java/util/Arrays.sort:([B)V
	return
  Labels:

public static void sort(byte[], int, int);
  Signature: ([BII)V
  Code:
   Stack=3, Locals=3, Args_size=3
	aload_0
	iload_1
	iload_2
	invokestatic	Method java/util/Arrays.sort:([BII)V
	return
  Labels:

public static void sort(double[]);
  Signature: ([D)V
  Code:
   Stack=1, Locals=1, Args_size=1
	aload_0
	invokestatic	Method java/util/Arrays.sort:([D)V
	return
  Labels:

public static void sort(double[], int, int);
  Signature: ([DII)V
  Code:
   Stack=3, Locals=3, Args_size=3
	aload_0
	iload_1
	iload_2
	invokestatic	Method java/util/Arrays.sort:([DII)V
	return
  Labels:

public static void sort(float[]);
  Signature: ([F)V
  Code:
   Stack=1, Locals=1, Args_size=1
	aload_0
	invokestatic	Method java/util/Arrays.sort:([F)V
	return
  Labels:

public static void sort(float[], int, int);
  Signature: ([FII)V
  Code:
   Stack=3, Locals=3, Args_size=3
	aload_0
	iload_1
	iload_2
	invokestatic	Method java/util/Arrays.sort:([FII)V
	return
  Labels:

public static void sort(java.lang.Object[]);
  Signature: ([Ljava/lang/Object;)V
  Code:
   Stack=1, Locals=1, Args_size=1
	aload_0
	invokestatic	Method java/util/Arrays.sort:([Ljava/lang/Object;)V
	return
  Labels:

public static void sort(java.lang.Object[], int, int);
  Signature: ([Ljava/lang/Object;II)V
  Code:
   Stack=3, Locals=3, Args_size=3
	aload_0
	iload_1
	iload_2
	invokestatic	Method java/util/Arrays.sort:([Ljava/lang/Object;II)V
	return
  Labels:

public static void sort(java.lang.Object[], java.util.Comparator);
  Signature: ([Ljava/lang/Object;Ljava/util/Comparator;)V
  Code:
   Stack=2, Locals=2, Args_size=2
	aload_0
	aload_1
	invokestatic	Method java/util/Arrays.sort:([Ljava/lang/Object;Ljava/util/Comparator;)V
	return
  Labels:

public static void sort(java.lang.Object[], int, int, java.util.Comparator);
  Signature: ([Ljava/lang/Object;IILjava/util/Comparator;)V
  Code:
   Stack=4, Locals=4, Args_size=4
	aload_0
	iload_1
	iload_2
	aload_3
	invokestatic	Method java/util/Arrays.sort:([Ljava/lang/Object;IILjava/util/Comparator;)V
	return
  Labels:

public static int binarySearch(long[], long);
  Signature: ([JJ)I
  Code:
   Stack=3, Locals=3, Args_size=2
	aload_0
	lload_1
	invokestatic	Method java/util/Arrays.binarySearch:([JJ)I
	ireturn
  Labels:

public static int binarySearch(int[], int);
  Signature: ([II)I
  Code:
   Stack=2, Locals=2, Args_size=2
	aload_0
	iload_1
	invokestatic	Method java/util/Arrays.binarySearch:([II)I
	ireturn
  Labels:

public static int binarySearch(short[], short);
  Signature: ([SS)I
  Code:
   Stack=2, Locals=2, Args_size=2
	aload_0
	iload_1
	invokestatic	Method java/util/Arrays.binarySearch:([SS)I
	ireturn
  Labels:

public static int binarySearch(char[], char);
  Signature: ([CC)I
  Code:
   Stack=2, Locals=2, Args_size=2
	aload_0
	iload_1
	invokestatic	Method java/util/Arrays.binarySearch:([CC)I
	ireturn
  Labels:

public static int binarySearch(byte[], byte);
  Signature: ([BB)I
  Code:
   Stack=2, Locals=2, Args_size=2
	aload_0
	iload_1
	invokestatic	Method java/util/Arrays.binarySearch:([BB)I
	ireturn
  Labels:

public static int binarySearch(double[], double);
  Signature: ([DD)I
  Code:
   Stack=3, Locals=3, Args_size=2
	aload_0
	dload_1
	invokestatic	Method java/util/Arrays.binarySearch:([DD)I
	ireturn
  Labels:

public static int binarySearch(float[], float);
  Signature: ([FF)I
  Code:
   Stack=2, Locals=2, Args_size=2
	aload_0
	fload_1
	invokestatic	Method java/util/Arrays.binarySearch:([FF)I
	ireturn
  Labels:

public static int binarySearch(java.lang.Object[], java.lang.Object);
  Signature: ([Ljava/lang/Object;Ljava/lang/Object;)I
  Code:
   Stack=2, Locals=2, Args_size=2
	aload_0
	aload_1
	invokestatic	Method java/util/Arrays.binarySearch:([Ljava/lang/Object;Ljava/lang/Object;)I
	ireturn
  Labels:

public static int binarySearch(java.lang.Object[], java.lang.Object, java.util.Comparator);
  Signature: ([Ljava/lang/Object;Ljava/lang/Object;Ljava/util/Comparator;)I
  Code:
   Stack=3, Locals=3, Args_size=3
	aload_0
	aload_1
	aload_2
	invokestatic	Method java/util/Arrays.binarySearch:([Ljava/lang/Object;Ljava/lang/Object;Ljava/util/Comparator;)I
	ireturn
  Labels:

public static boolean equals(long[], long[]);
  Signature: ([J[J)Z
  Code:
   Stack=2, Locals=2, Args_size=2
	aload_0
	aload_1
	invokestatic	Method java/util/Arrays.equals:([J[J)Z
	ireturn
  Labels:

public static boolean equals(int[], int[]);
  Signature: ([I[I)Z
  Code:
   Stack=2, Locals=2, Args_size=2
	aload_0
	aload_1
	invokestatic	Method java/util/Arrays.equals:([I[I)Z
	ireturn
  Labels:

public static boolean equals(short[], short[]);
  Signature: ([S[S)Z
  Code:
   Stack=2, Locals=2, Args_size=2
	aload_0
	aload_1
	invokestatic	Method java/util/Arrays.equals:([S[S)Z
	ireturn
  Labels:

public static boolean equals(char[], char[]);
  Signature: ([C[C)Z
  Code:
   Stack=2, Locals=2, Args_size=2
	aload_0
	aload_1
	invokestatic	Method java/util/Arrays.equals:([C[C)Z
	ireturn
  Labels:

public static boolean equals(byte[], byte[]);
  Signature: ([B[B)Z
  Code:
   Stack=2, Locals=2, Args_size=2
	aload_0
	aload_1
	invokestatic	Method java/util/Arrays.equals:([B[B)Z
	ireturn
  Labels:

public static boolean equals(boolean[], boolean[]);
  Signature: ([Z[Z)Z
  Code:
   Stack=2, Locals=2, Args_size=2
	aload_0
	aload_1
	invokestatic	Method java/util/Arrays.equals:([Z[Z)Z
	ireturn
  Labels:

public static boolean equals(double[], double[]);
  Signature: ([D[D)Z
  Code:
   Stack=2, Locals=2, Args_size=2
	aload_0
	aload_1
	invokestatic	Method java/util/Arrays.equals:([D[D)Z
	ireturn
  Labels:

public static boolean equals(float[], float[]);
  Signature: ([F[F)Z
  Code:
   Stack=2, Locals=2, Args_size=2
	aload_0
	aload_1
	invokestatic	Method java/util/Arrays.equals:([F[F)Z
	ireturn
  Labels:

public static boolean equals(java.lang.Object[], java.lang.Object[]);
  Signature: ([Ljava/lang/Object;[Ljava/lang/Object;)Z
  Code:
   Stack=2, Locals=2, Args_size=2
	aload_0
	aload_1
	invokestatic	Method java/util/Arrays.equals:([Ljava/lang/Object;[Ljava/lang/Object;)Z
	ireturn
  Labels:

public static void fill(long[], long);
  Signature: ([JJ)V
  Code:
   Stack=3, Locals=3, Args_size=2
	aload_0
	lload_1
	invokestatic	Method java/util/Arrays.fill:([JJ)V
	return
  Labels:

public static void fill(long[], int, int, long);
  Signature: ([JIIJ)V
  Code:
   Stack=5, Locals=5, Args_size=4
	aload_0
	iload_1
	iload_2
	lload_3
	invokestatic	Method java/util/Arrays.fill:([JIIJ)V
	return
  Labels:

public static void fill(int[], int);
  Signature: ([II)V
  Code:
   Stack=2, Locals=2, Args_size=2
	aload_0
	iload_1
	invokestatic	Method java/util/Arrays.fill:([II)V
	return
  Labels:

public static void fill(int[], int, int, int);
  Signature: ([IIII)V
  Code:
   Stack=4, Locals=4, Args_size=4
	aload_0
	iload_1
	iload_2
	iload_3
	invokestatic	Method java/util/Arrays.fill:([IIII)V
	return
  Labels:

public static void fill(short[], short);
  Signature: ([SS)V
  Code:
   Stack=2, Locals=2, Args_size=2
	aload_0
	iload_1
	invokestatic	Method java/util/Arrays.fill:([SS)V
	return
  Labels:

public static void fill(short[], int, int, short);
  Signature: ([SIIS)V
  Code:
   Stack=4, Locals=4, Args_size=4
	aload_0
	iload_1
	iload_2
	iload_3
	invokestatic	Method java/util/Arrays.fill:([SIIS)V
	return
  Labels:

public static void fill(char[], char);
  Signature: ([CC)V
  Code:
   Stack=2, Locals=2, Args_size=2
	aload_0
	iload_1
	invokestatic	Method java/util/Arrays.fill:([CC)V
	return
  Labels:

public static void fill(char[], int, int, char);
  Signature: ([CIIC)V
  Code:
   Stack=4, Locals=4, Args_size=4
	aload_0
	iload_1
	iload_2
	iload_3
	invokestatic	Method java/util/Arrays.fill:([CIIC)V
	return
  Labels:

public static void fill(byte[], byte);
  Signature: ([BB)V
  Code:
   Stack=2, Locals=2, Args_size=2
	aload_0
	iload_1
	invokestatic	Method java/util/Arrays.fill:([BB)V
	return
  Labels:

public static void fill(byte[], int, int, byte);
  Signature: ([BIIB)V
  Code:
   Stack=4, Locals=4, Args_size=4
	aload_0
	iload_1
	iload_2
	iload_3
	invokestatic	Method java/util/Arrays.fill:([BIIB)V
	return
  Labels:

public static void fill(boolean[], boolean);
  Signature: ([ZZ)V
  Code:
   Stack=2, Locals=2, Args_size=2
	aload_0
	iload_1
	invokestatic	Method java/util/Arrays.fill:([ZZ)V
	return
  Labels:

public static void fill(boolean[], int, int, boolean);
  Signature: ([ZIIZ)V
  Code:
   Stack=4, Locals=4, Args_size=4
	aload_0
	iload_1
	iload_2
	iload_3
	invokestatic	Method java/util/Arrays.fill:([ZIIZ)V
	return
  Labels:

public static void fill(double[], double);
  Signature: ([DD)V
  Code:
   Stack=3, Locals=3, Args_size=2
	aload_0
	dload_1
	invokestatic	Method java/util/Arrays.fill:([DD)V
	return
  Labels:

public static void fill(double[], int, int, double);
  Signature: ([DIID)V
  Code:
   Stack=5, Locals=5, Args_size=4
	aload_0
	iload_1
	iload_2
	dload_3
	invokestatic	Method java/util/Arrays.fill:([DIID)V
	return
  Labels:

public static void fill(float[], float);
  Signature: ([FF)V
  Code:
   Stack=2, Locals=2, Args_size=2
	aload_0
	fload_1
	invokestatic	Method java/util/Arrays.fill:([FF)V
	return
  Labels:

public static void fill(float[], int, int, float);
  Signature: ([FIIF)V
  Code:
   Stack=4, Locals=4, Args_size=4
	aload_0
	iload_1
	iload_2
	fload_3
	invokestatic	Method java/util/Arrays.fill:([FIIF)V
	return
  Labels:

public static void fill(java.lang.Object[], java.lang.Object);
  Signature: ([Ljava/lang/Object;Ljava/lang/Object;)V
  Code:
   Stack=2, Locals=2, Args_size=2
	aload_0
	aload_1
	invokestatic	Method java/util/Arrays.fill:([Ljava/lang/Object;Ljava/lang/Object;)V
	return
  Labels:

public static void fill(java.lang.Object[], int, int, java.lang.Object);
  Signature: ([Ljava/lang/Object;IILjava/lang/Object;)V
  Code:
   Stack=4, Locals=4, Args_size=4
	aload_0
	iload_1
	iload_2
	aload_3
	invokestatic	Method java/util/Arrays.fill:([Ljava/lang/Object;IILjava/lang/Object;)V
	return
  Labels:

public static java.lang.Object[] copyOf(java.lang.Object[], int);
  Signature: ([Ljava/lang/Object;I)[Ljava/lang/Object;
  Code:
   Stack=3, Locals=2, Args_size=2
	aload_0
	iload_1
	aload_0
	invokevirtual	Method java/lang/Object.getClass:()Ljava/lang/Class;
	invokestatic	Method copyOf:([Ljava/lang/Object;ILjava/lang/Class;)[Ljava/lang/Object;
	areturn
  Labels:

public static java.lang.Object[] copyOf(java.lang.Object[], int, java.lang.Class);
  Signature: ([Ljava/lang/Object;ILjava/lang/Class;)[Ljava/lang/Object;
  Code:
   Stack=5, Locals=5, Args_size=3
	aload_2
	ldc_w	class "[Ljava/lang/Object;"
	if_acmpne	l1 // aload_2
	iload_1
	anewarray	class java/lang/Object
	goto	l2 // astore_3
l1	aload_2
	invokevirtual	Method java/lang/Class.getComponentType:()Ljava/lang/Class;
	iload_1
	invokestatic	Method java/lang/reflect/Array.newInstance:(Ljava/lang/Class;I)Ljava/lang/Object;
	checkcast	class "[Ljava/lang/Object;"
	checkcast	class "[Ljava/lang/Object;"
l2	astore_3
	aload_0
	arraylength
	iload_1
	if_icmpge	l3 // iload_1
	aload_0
	arraylength
	goto	l4 // istore
l3	iload_1
l4	istore	4
	aload_0
	iconst_0
	aload_3
	iconst_0
	iload	4
	invokestatic	Method java/lang/System.arraycopy:(Ljava/lang/Object;ILjava/lang/Object;II)V
	aload_3
	areturn
  Labels:
   	l1 = 14 // aload_2
   	l2 = 28 // astore_3
   	l3 = 40 // iload_1
   	l4 = 41 // istore

public static byte[] copyOf(byte[], int);
  Signature: ([BI)[B
  Code:
   Stack=5, Locals=4, Args_size=2
	iload_1
	newarray byte
	astore_2
	aload_0
	arraylength
	iload_1
	if_icmpge	l1 // iload_1
	aload_0
	arraylength
	goto	l2 // istore_3
l1	iload_1
l2	istore_3
	aload_0
	iconst_0
	aload_2
	iconst_0
	iload_3
	invokestatic	Method java/lang/System.arraycopy:(Ljava/lang/Object;ILjava/lang/Object;II)V
	aload_2
	areturn
  Labels:
   	l1 = 15 // iload_1
   	l2 = 16 // istore_3

public static short[] copyOf(short[], int);
  Signature: ([SI)[S
  Code:
   Stack=5, Locals=4, Args_size=2
	iload_1
	newarray short
	astore_2
	aload_0
	arraylength
	iload_1
	if_icmpge	l1 // iload_1
	aload_0
	arraylength
	goto	l2 // istore_3
l1	iload_1
l2	istore_3
	aload_0
	iconst_0
	aload_2
	iconst_0
	iload_3
	invokestatic	Method java/lang/System.arraycopy:(Ljava/lang/Object;ILjava/lang/Object;II)V
	aload_2
	areturn
  Labels:
   	l1 = 15 // iload_1
   	l2 = 16 // istore_3

public static int[] copyOf(int[], int);
  Signature: ([II)[I
  Code:
   Stack=5, Locals=4, Args_size=2
	iload_1
	newarray int
	astore_2
	aload_0
	arraylength
	iload_1
	if_icmpge	l1 // iload_1
	aload_0
	arraylength
	goto	l2 // istore_3
l1	iload_1
l2	istore_3
	aload_0
	iconst_0
	aload_2
	iconst_0
	iload_3
	invokestatic	Method java/lang/System.arraycopy:(Ljava/lang/Object;ILjava/lang/Object;II)V
	aload_2
	areturn
  Labels:
   	l1 = 15 // iload_1
   	l2 = 16 // istore_3

public static long[] copyOf(long[], int);
  Signature: ([JI)[J
  Code:
   Stack=5, Locals=4, Args_size=2
	iload_1
	newarray long
	astore_2
	aload_0
	arraylength
	iload_1
	if_icmpge	l1 // iload_1
	aload_0
	arraylength
	goto	l2 // istore_3
l1	iload_1
l2	istore_3
	aload_0
	iconst_0
	aload_2
	iconst_0
	iload_3
	invokestatic	Method java/lang/System.arraycopy:(Ljava/lang/Object;ILjava/lang/Object;II)V
	aload_2
	areturn
  Labels:
   	l1 = 15 // iload_1
   	l2 = 16 // istore_3

public static char[] copyOf(char[], int);
  Signature: ([CI)[C
  Code:
   Stack=5, Locals=4, Args_size=2
	iload_1
	newarray char
	astore_2
	aload_0
	arraylength
	iload_1
	if_icmpge	l1 // iload_1
	aload_0
	arraylength
	goto	l2 // istore_3
l1	iload_1
l2	istore_3
	aload_0
	iconst_0
	aload_2
	iconst_0
	iload_3
	invokestatic	Method java/lang/System.arraycopy:(Ljava/lang/Object;ILjava/lang/Object;II)V
	aload_2
	areturn
  Labels:
   	l1 = 15 // iload_1
   	l2 = 16 // istore_3

public static float[] copyOf(float[], int);
  Signature: ([FI)[F
  Code:
   Stack=5, Locals=4, Args_size=2
	iload_1
	newarray float
	astore_2
	aload_0
	arraylength
	iload_1
	if_icmpge	l1 // iload_1
	aload_0
	arraylength
	goto	l2 // istore_3
l1	iload_1
l2	istore_3
	aload_0
	iconst_0
	aload_2
	iconst_0
	iload_3
	invokestatic	Method java/lang/System.arraycopy:(Ljava/lang/Object;ILjava/lang/Object;II)V
	aload_2
	areturn
  Labels:
   	l1 = 15 // iload_1
   	l2 = 16 // istore_3

public static double[] copyOf(double[], int);
  Signature: ([DI)[D
  Code:
   Stack=5, Locals=4, Args_size=2
	iload_1
	newarray double
	astore_2
	aload_0
	arraylength
	iload_1
	if_icmpge	l1 // iload_1
	aload_0
	arraylength
	goto	l2 // istore_3
l1	iload_1
l2	istore_3
	aload_0
	iconst_0
	aload_2
	iconst_0
	iload_3
	invokestatic	Method java/lang/System.arraycopy:(Ljava/lang/Object;ILjava/lang/Object;II)V
	aload_2
	areturn
  Labels:
   	l1 = 15 // iload_1
   	l2 = 16 // istore_3

public static boolean[] copyOf(boolean[], int);
  Signature: ([ZI)[Z
  Code:
   Stack=5, Locals=4, Args_size=2
	iload_1
	newarray boolean
	astore_2
	aload_0
	arraylength
	iload_1
	if_icmpge	l1 // iload_1
	aload_0
	arraylength
	goto	l2 // istore_3
l1	iload_1
l2	istore_3
	aload_0
	iconst_0
	aload_2
	iconst_0
	iload_3
	invokestatic	Method java/lang/System.arraycopy:(Ljava/lang/Object;ILjava/lang/Object;II)V
	aload_2
	areturn
  Labels:
   	l1 = 15 // iload_1
   	l2 = 16 // istore_3

public static java.lang.Object[] copyOfRange(java.lang.Object[], int, int);
  Signature: ([Ljava/lang/Object;II)[Ljava/lang/Object;
  Code:
   Stack=4, Locals=3, Args_size=3
	aload_0
	iload_1
	iload_2
	aload_0
	invokevirtual	Method java/lang/Object.getClass:()Ljava/lang/Class;
	invokestatic	Method copyOfRange:([Ljava/lang/Object;IILjava/lang/Class;)[Ljava/lang/Object;
	areturn
  Labels:

public static java.lang.Object[] copyOfRange(java.lang.Object[], int, int, java.lang.Class);
  Signature: ([Ljava/lang/Object;IILjava/lang/Class;)[Ljava/lang/Object;
  Code:
   Stack=5, Locals=8, Args_size=4
	iload_2
	iload_1
	isub
	istore	4
	iload	4
	ifge	l1 // aload_3
	new	class java/lang/IllegalArgumentException
	dup
	new	class java/lang/StringBuilder
	dup
	invokespecial	Method java/lang/StringBuilder."<init>":()V
	iload_1
	invokevirtual	Method java/lang/StringBuilder.append:(I)Ljava/lang/StringBuilder;
	ldc	String  > 
	invokevirtual	Method java/lang/StringBuilder.append:(Ljava/lang/String;)Ljava/lang/StringBuilder;
	iload_2
	invokevirtual	Method java/lang/StringBuilder.append:(I)Ljava/lang/StringBuilder;
	invokevirtual	Method java/lang/StringBuilder.toString:()Ljava/lang/String;
	invokespecial	Method java/lang/IllegalArgumentException."<init>":(Ljava/lang/String;)V
	athrow
l1	aload_3
	ldc_w	class "[Ljava/lang/Object;"
	if_acmpne	l2 // aload_3
	iload	4
	anewarray	class java/lang/Object
	goto	l3 // astore
l2	aload_3
	invokevirtual	Method java/lang/Class.getComponentType:()Ljava/lang/Class;
	iload	4
	invokestatic	Method java/lang/reflect/Array.newInstance:(Ljava/lang/Class;I)Ljava/lang/Object;
	checkcast	class "[Ljava/lang/Object;"
	checkcast	class "[Ljava/lang/Object;"
l3	astore	5
	aload_0
	arraylength
	iload_1
	isub
	istore	6
	iload	6
	iload	4
	if_icmpge	l4 // iload
	iload	6
	goto	l5 // istore
l4	iload	4
l5	istore	7
	aload_0
	iload_1
	aload	5
	iconst_0
	iload	7
	invokestatic	Method java/lang/System.arraycopy:(Ljava/lang/Object;ILjava/lang/Object;II)V
	aload	5
	areturn
  Labels:
   	l1 = 41 // aload_3
   	l2 = 56 // aload_3
   	l3 = 71 // astore
   	l4 = 91 // iload
   	l5 = 93 // istore

public static byte[] copyOfRange(byte[], int, int);
  Signature: ([BII)[B
  Code:
   Stack=5, Locals=7, Args_size=3
	iload_2
	iload_1
	isub
	istore_3
	iload_3
	ifge	l1 // iload_3
	new	class java/lang/IllegalArgumentException
	dup
	new	class java/lang/StringBuilder
	dup
	invokespecial	Method java/lang/StringBuilder."<init>":()V
	iload_1
	invokevirtual	Method java/lang/StringBuilder.append:(I)Ljava/lang/StringBuilder;
	ldc	String  > 
	invokevirtual	Method java/lang/StringBuilder.append:(Ljava/lang/String;)Ljava/lang/StringBuilder;
	iload_2
	invokevirtual	Method java/lang/StringBuilder.append:(I)Ljava/lang/StringBuilder;
	invokevirtual	Method java/lang/StringBuilder.toString:()Ljava/lang/String;
	invokespecial	Method java/lang/IllegalArgumentException."<init>":(Ljava/lang/String;)V
	athrow
l1	iload_3
	newarray byte
	astore	4
	aload_0
	arraylength
	iload_1
	isub
	istore	5
	iload	5
	iload_3
	if_icmpge	l2 // iload_3
	iload	5
	goto	l3 // istore
l2	iload_3
l3	istore	6
	aload_0
	iload_1
	aload	4
	iconst_0
	iload	6
	invokestatic	Method java/lang/System.arraycopy:(Ljava/lang/Object;ILjava/lang/Object;II)V
	aload	4
	areturn
  Labels:
   	l1 = 39 // iload_3
   	l2 = 61 // iload_3
   	l3 = 62 // istore

public static short[] copyOfRange(short[], int, int);
  Signature: ([SII)[S
  Code:
   Stack=5, Locals=7, Args_size=3
	iload_2
	iload_1
	isub
	istore_3
	iload_3
	ifge	l1 // iload_3
	new	class java/lang/IllegalArgumentException
	dup
	new	class java/lang/StringBuilder
	dup
	invokespecial	Method java/lang/StringBuilder."<init>":()V
	iload_1
	invokevirtual	Method java/lang/StringBuilder.append:(I)Ljava/lang/StringBuilder;
	ldc	String  > 
	invokevirtual	Method java/lang/StringBuilder.append:(Ljava/lang/String;)Ljava/lang/StringBuilder;
	iload_2
	invokevirtual	Method java/lang/StringBuilder.append:(I)Ljava/lang/StringBuilder;
	invokevirtual	Method java/lang/StringBuilder.toString:()Ljava/lang/String;
	invokespecial	Method java/lang/IllegalArgumentException."<init>":(Ljava/lang/String;)V
	athrow
l1	iload_3
	newarray short
	astore	4
	aload_0
	arraylength
	iload_1
	isub
	istore	5
	iload	5
	iload_3
	if_icmpge	l2 // iload_3
	iload	5
	goto	l3 // istore
l2	iload_3
l3	istore	6
	aload_0
	iload_1
	aload	4
	iconst_0
	iload	6
	invokestatic	Method java/lang/System.arraycopy:(Ljava/lang/Object;ILjava/lang/Object;II)V
	aload	4
	areturn
  Labels:
   	l1 = 39 // iload_3
   	l2 = 61 // iload_3
   	l3 = 62 // istore

public static int[] copyOfRange(int[], int, int);
  Signature: ([III)[I
  Code:
   Stack=5, Locals=7, Args_size=3
	iload_2
	iload_1
	isub
	istore_3
	iload_3
	ifge	l1 // iload_3
	new	class java/lang/IllegalArgumentException
	dup
	new	class java/lang/StringBuilder
	dup
	invokespecial	Method java/lang/StringBuilder."<init>":()V
	iload_1
	invokevirtual	Method java/lang/StringBuilder.append:(I)Ljava/lang/StringBuilder;
	ldc	String  > 
	invokevirtual	Method java/lang/StringBuilder.append:(Ljava/lang/String;)Ljava/lang/StringBuilder;
	iload_2
	invokevirtual	Method java/lang/StringBuilder.append:(I)Ljava/lang/StringBuilder;
	invokevirtual	Method java/lang/StringBuilder.toString:()Ljava/lang/String;
	invokespecial	Method java/lang/IllegalArgumentException."<init>":(Ljava/lang/String;)V
	athrow
l1	iload_3
	newarray int
	astore	4
	aload_0
	arraylength
	iload_1
	isub
	istore	5
	iload	5
	iload_3
	if_icmpge	l2 // iload_3
	iload	5
	goto	l3 // istore
l2	iload_3
l3	istore	6
	aload_0
	iload_1
	aload	4
	iconst_0
	iload	6
	invokestatic	Method java/lang/System.arraycopy:(Ljava/lang/Object;ILjava/lang/Object;II)V
	aload	4
	areturn
  Labels:
   	l1 = 39 // iload_3
   	l2 = 61 // iload_3
   	l3 = 62 // istore

public static long[] copyOfRange(long[], int, int);
  Signature: ([JII)[J
  Code:
   Stack=5, Locals=7, Args_size=3
	iload_2
	iload_1
	isub
	istore_3
	iload_3
	ifge	l1 // iload_3
	new	class java/lang/IllegalArgumentException
	dup
	new	class java/lang/StringBuilder
	dup
	invokespecial	Method java/lang/StringBuilder."<init>":()V
	iload_1
	invokevirtual	Method java/lang/StringBuilder.append:(I)Ljava/lang/StringBuilder;
	ldc	String  > 
	invokevirtual	Method java/lang/StringBuilder.append:(Ljava/lang/String;)Ljava/lang/StringBuilder;
	iload_2
	invokevirtual	Method java/lang/StringBuilder.append:(I)Ljava/lang/StringBuilder;
	invokevirtual	Method java/lang/StringBuilder.toString:()Ljava/lang/String;
	invokespecial	Method java/lang/IllegalArgumentException."<init>":(Ljava/lang/String;)V
	athrow
l1	iload_3
	newarray long
	astore	4
	aload_0
	arraylength
	iload_1
	isub
	istore	5
	iload	5
	iload_3
	if_icmpge	l2 // iload_3
	iload	5
	goto	l3 // istore
l2	iload_3
l3	istore	6
	aload_0
	iload_1
	aload	4
	iconst_0
	iload	6
	invokestatic	Method java/lang/System.arraycopy:(Ljava/lang/Object;ILjava/lang/Object;II)V
	aload	4
	areturn
  Labels:
   	l1 = 39 // iload_3
   	l2 = 61 // iload_3
   	l3 = 62 // istore

public static char[] copyOfRange(char[], int, int);
  Signature: ([CII)[C
  Code:
   Stack=5, Locals=7, Args_size=3
	iload_2
	iload_1
	isub
	istore_3
	iload_3
	ifge	l1 // iload_3
	new	class java/lang/IllegalArgumentException
	dup
	new	class java/lang/StringBuilder
	dup
	invokespecial	Method java/lang/StringBuilder."<init>":()V
	iload_1
	invokevirtual	Method java/lang/StringBuilder.append:(I)Ljava/lang/StringBuilder;
	ldc	String  > 
	invokevirtual	Method java/lang/StringBuilder.append:(Ljava/lang/String;)Ljava/lang/StringBuilder;
	iload_2
	invokevirtual	Method java/lang/StringBuilder.append:(I)Ljava/lang/StringBuilder;
	invokevirtual	Method java/lang/StringBuilder.toString:()Ljava/lang/String;
	invokespecial	Method java/lang/IllegalArgumentException."<init>":(Ljava/lang/String;)V
	athrow
l1	iload_3
	newarray char
	astore	4
	aload_0
	arraylength
	iload_1
	isub
	istore	5
	iload	5
	iload_3
	if_icmpge	l2 // iload_3
	iload	5
	goto	l3 // istore
l2	iload_3
l3	istore	6
	aload_0
	iload_1
	aload	4
	iconst_0
	iload	6
	invokestatic	Method java/lang/System.arraycopy:(Ljava/lang/Object;ILjava/lang/Object;II)V
	aload	4
	areturn
  Labels:
   	l1 = 39 // iload_3
   	l2 = 61 // iload_3
   	l3 = 62 // istore

public static float[] copyOfRange(float[], int, int);
  Signature: ([FII)[F
  Code:
   Stack=5, Locals=7, Args_size=3
	iload_2
	iload_1
	isub
	istore_3
	iload_3
	ifge	l1 // iload_3
	new	class java/lang/IllegalArgumentException
	dup
	new	class java/lang/StringBuilder
	dup
	invokespecial	Method java/lang/StringBuilder."<init>":()V
	iload_1
	invokevirtual	Method java/lang/StringBuilder.append:(I)Ljava/lang/StringBuilder;
	ldc	String  > 
	invokevirtual	Method java/lang/StringBuilder.append:(Ljava/lang/String;)Ljava/lang/StringBuilder;
	iload_2
	invokevirtual	Method java/lang/StringBuilder.append:(I)Ljava/lang/StringBuilder;
	invokevirtual	Method java/lang/StringBuilder.toString:()Ljava/lang/String;
	invokespecial	Method java/lang/IllegalArgumentException."<init>":(Ljava/lang/String;)V
	athrow
l1	iload_3
	newarray float
	astore	4
	aload_0
	arraylength
	iload_1
	isub
	istore	5
	iload	5
	iload_3
	if_icmpge	l2 // iload_3
	iload	5
	goto	l3 // istore
l2	iload_3
l3	istore	6
	aload_0
	iload_1
	aload	4
	iconst_0
	iload	6
	invokestatic	Method java/lang/System.arraycopy:(Ljava/lang/Object;ILjava/lang/Object;II)V
	aload	4
	areturn
  Labels:
   	l1 = 39 // iload_3
   	l2 = 61 // iload_3
   	l3 = 62 // istore

public static double[] copyOfRange(double[], int, int);
  Signature: ([DII)[D
  Code:
   Stack=5, Locals=7, Args_size=3
	iload_2
	iload_1
	isub
	istore_3
	iload_3
	ifge	l1 // iload_3
	new	class java/lang/IllegalArgumentException
	dup
	new	class java/lang/StringBuilder
	dup
	invokespecial	Method java/lang/StringBuilder."<init>":()V
	iload_1
	invokevirtual	Method java/lang/StringBuilder.append:(I)Ljava/lang/StringBuilder;
	ldc	String  > 
	invokevirtual	Method java/lang/StringBuilder.append:(Ljava/lang/String;)Ljava/lang/StringBuilder;
	iload_2
	invokevirtual	Method java/lang/StringBuilder.append:(I)Ljava/lang/StringBuilder;
	invokevirtual	Method java/lang/StringBuilder.toString:()Ljava/lang/String;
	invokespecial	Method java/lang/IllegalArgumentException."<init>":(Ljava/lang/String;)V
	athrow
l1	iload_3
	newarray double
	astore	4
	aload_0
	arraylength
	iload_1
	isub
	istore	5
	iload	5
	iload_3
	if_icmpge	l2 // iload_3
	iload	5
	goto	l3 // istore
l2	iload_3
l3	istore	6
	aload_0
	iload_1
	aload	4
	iconst_0
	iload	6
	invokestatic	Method java/lang/System.arraycopy:(Ljava/lang/Object;ILjava/lang/Object;II)V
	aload	4
	areturn
  Labels:
   	l1 = 39 // iload_3
   	l2 = 61 // iload_3
   	l3 = 62 // istore

public static boolean[] copyOfRange(boolean[], int, int);
  Signature: ([ZII)[Z
  Code:
   Stack=5, Locals=7, Args_size=3
	iload_2
	iload_1
	isub
	istore_3
	iload_3
	ifge	l1 // iload_3
	new	class java/lang/IllegalArgumentException
	dup
	new	class java/lang/StringBuilder
	dup
	invokespecial	Method java/lang/StringBuilder."<init>":()V
	iload_1
	invokevirtual	Method java/lang/StringBuilder.append:(I)Ljava/lang/StringBuilder;
	ldc	String  > 
	invokevirtual	Method java/lang/StringBuilder.append:(Ljava/lang/String;)Ljava/lang/StringBuilder;
	iload_2
	invokevirtual	Method java/lang/StringBuilder.append:(I)Ljava/lang/StringBuilder;
	invokevirtual	Method java/lang/StringBuilder.toString:()Ljava/lang/String;
	invokespecial	Method java/lang/IllegalArgumentException."<init>":(Ljava/lang/String;)V
	athrow
l1	iload_3
	newarray boolean
	astore	4
	aload_0
	arraylength
	iload_1
	isub
	istore	5
	iload	5
	iload_3
	if_icmpge	l2 // iload_3
	iload	5
	goto	l3 // istore
l2	iload_3
l3	istore	6
	aload_0
	iload_1
	aload	4
	iconst_0
	iload	6
	invokestatic	Method java/lang/System.arraycopy:(Ljava/lang/Object;ILjava/lang/Object;II)V
	aload	4
	areturn
  Labels:
   	l1 = 39 // iload_3
   	l2 = 61 // iload_3
   	l3 = 62 // istore

public static java.util.List asList(java.lang.Object[]);
  Signature: ([Ljava/lang/Object;)Ljava/util/List;
  Code:
   Stack=1, Locals=1, Args_size=1
	aload_0
	invokestatic	Method java/util/Arrays.asList:([Ljava/lang/Object;)Ljava/util/List;
	areturn
  Labels:

public static int hashCode(long[]);
  Signature: ([J)I
  Code:
   Stack=6, Locals=5, Args_size=1
	aload_0
	ifnonnull	l1 // iconst_1
	iconst_0
	ireturn
l1	iconst_1
	istore_1
	iconst_0
	istore_2
l3	iload_2
	aload_0
	arraylength
	if_icmpge	l2 // iload_1
	aload_0
	iload_2
	laload
	lstore_3
	bipush	31
	iload_1
	imul
	lload_3
	lload_3
	bipush	32
	lushr
	lxor
	l2i
	iadd
	istore_1
	iinc	2, 1
	goto	l3 // iload_2
l2	iload_1
	ireturn
  Labels:
   	l1 = 6 // iconst_1
   	l3 = 10 // iload_2
   	l2 = 39 // iload_1

public static int hashCode(int[]);
  Signature: ([I)I
  Code:
   Stack=3, Locals=3, Args_size=1
	aload_0
	ifnonnull	l1 // iconst_1
	iconst_0
	ireturn
l1	iconst_1
	istore_1
	iconst_0
	istore_2
l3	iload_2
	aload_0
	arraylength
	if_icmpge	l2 // iload_1
	bipush	31
	iload_1
	imul
	aload_0
	iload_2
	iaload
	iadd
	istore_1
	iinc	2, 1
	goto	l3 // iload_2
l2	iload_1
	ireturn
  Labels:
   	l1 = 6 // iconst_1
   	l3 = 10 // iload_2
   	l2 = 31 // iload_1

public static int hashCode(short[]);
  Signature: ([S)I
  Code:
   Stack=3, Locals=3, Args_size=1
	aload_0
	ifnonnull	l1 // iconst_1
	iconst_0
	ireturn
l1	iconst_1
	istore_1
	iconst_0
	istore_2
l3	iload_2
	aload_0
	arraylength
	if_icmpge	l2 // iload_1
	bipush	31
	iload_1
	imul
	aload_0
	iload_2
	saload
	iadd
	istore_1
	iinc	2, 1
	goto	l3 // iload_2
l2	iload_1
	ireturn
  Labels:
   	l1 = 6 // iconst_1
   	l3 = 10 // iload_2
   	l2 = 31 // iload_1

public static int hashCode(char[]);
  Signature: ([C)I
  Code:
   Stack=3, Locals=3, Args_size=1
	aload_0
	ifnonnull	l1 // iconst_1
	iconst_0
	ireturn
l1	iconst_1
	istore_1
	iconst_0
	istore_2
l3	iload_2
	aload_0
	arraylength
	if_icmpge	l2 // iload_1
	bipush	31
	iload_1
	imul
	aload_0
	iload_2
	caload
	iadd
	istore_1
	iinc	2, 1
	goto	l3 // iload_2
l2	iload_1
	ireturn
  Labels:
   	l1 = 6 // iconst_1
   	l3 = 10 // iload_2
   	l2 = 31 // iload_1

public static int hashCode(byte[]);
  Signature: ([B)I
  Code:
   Stack=3, Locals=3, Args_size=1
	aload_0
	ifnonnull	l1 // iconst_1
	iconst_0
	ireturn
l1	iconst_1
	istore_1
	iconst_0
	istore_2
l3	iload_2
	aload_0
	arraylength
	if_icmpge	l2 // iload_1
	bipush	31
	iload_1
	imul
	aload_0
	iload_2
	baload
	iadd
	istore_1
	iinc	2, 1
	goto	l3 // iload_2
l2	iload_1
	ireturn
  Labels:
   	l1 = 6 // iconst_1
   	l3 = 10 // iload_2
   	l2 = 31 // iload_1

public static int hashCode(boolean[]);
  Signature: ([Z)I
  Code:
   Stack=3, Locals=3, Args_size=1
	aload_0
	ifnonnull	l1 // iconst_1
	iconst_0
	ireturn
l1	iconst_1
	istore_1
	iconst_0
	istore_2
l5	iload_2
	aload_0
	arraylength
	if_icmpge	l2 // iload_1
	bipush	31
	iload_1
	imul
	aload_0
	iload_2
	baload
	ifeq	l3 // sipush
	sipush	1231
	goto	l4 // iadd
l3	sipush	1237
l4	iadd
	istore_1
	iinc	2, 1
	goto	l5 // iload_2
l2	iload_1
	ireturn
  Labels:
   	l1 = 6 // iconst_1
   	l5 = 10 // iload_2
   	l3 = 32 // sipush
   	l4 = 35 // iadd
   	l2 = 43 // iload_1

public static int hashCode(float[]);
  Signature: ([F)I
  Code:
   Stack=3, Locals=3, Args_size=1
	aload_0
	ifnonnull	l1 // iconst_1
	iconst_0
	ireturn
l1	iconst_1
	istore_1
	iconst_0
	istore_2
l3	iload_2
	aload_0
	arraylength
	if_icmpge	l2 // iload_1
	bipush	31
	iload_1
	imul
	aload_0
	iload_2
	faload
	invokestatic	Method java/lang/Float.floatToIntBits:(F)I
	iadd
	istore_1
	iinc	2, 1
	goto	l3 // iload_2
l2	iload_1
	ireturn
  Labels:
   	l1 = 6 // iconst_1
   	l3 = 10 // iload_2
   	l2 = 34 // iload_1

public static int hashCode(double[]);
  Signature: ([D)I
  Code:
   Stack=6, Locals=5, Args_size=1
	aload_0
	ifnonnull	l1 // iconst_1
	iconst_0
	ireturn
l1	iconst_1
	istore_1
	iconst_0
	istore_2
l3	iload_2
	aload_0
	arraylength
	if_icmpge	l2 // iload_1
	aload_0
	iload_2
	daload
	invokestatic	Method java/lang/Double.doubleToLongBits:(D)J
	lstore_3
	bipush	31
	iload_1
	imul
	lload_3
	lload_3
	bipush	32
	lushr
	lxor
	l2i
	iadd
	istore_1
	iinc	2, 1
	goto	l3 // iload_2
l2	iload_1
	ireturn
  Labels:
   	l1 = 6 // iconst_1
   	l3 = 10 // iload_2
   	l2 = 42 // iload_1

public static int hashCode(java.lang.Object[]);
  Signature: ([Ljava/lang/Object;)I
  Code:
   Stack=2, Locals=4, Args_size=1
	aload_0
	ifnonnull	l1 // iconst_1
	iconst_0
	ireturn
l1	iconst_1
	istore_1
	iconst_0
	istore_2
l5	iload_2
	aload_0
	arraylength
	if_icmpge	l2 // iload_1
	aload_0
	iload_2
	aaload
	astore_3
	bipush	31
	iload_1
	imul
	aload_3
	ifnonnull	l3 // aload_3
	iconst_0
	goto	l4 // iadd
l3	aload_3
	invokevirtual	Method java/lang/Object.hashCode:()I
l4	iadd
	istore_1
	iinc	2, 1
	goto	l5 // iload_2
l2	iload_1
	ireturn
  Labels:
   	l1 = 6 // iconst_1
   	l5 = 10 // iload_2
   	l3 = 32 // aload_3
   	l4 = 36 // iadd
   	l2 = 44 // iload_1

public static int deepHashCode(java.lang.Object[]);
  Signature: ([Ljava/lang/Object;)I
  Code:
   Stack=2, Locals=4, Args_size=1
	aload_0
	ifnonnull	l1 // iconst_1
	iconst_0
	ireturn
l1	iconst_1
	istore_1
	iconst_0
	istore_2
l14	iload_2
	aload_0
	arraylength
	if_icmpge	l2 // iload_1
	aload_0
	iload_2
	aaload
	astore_3
	bipush	31
	iload_1
	imul
	aload_3
	instanceof	class "[Ljava/lang/Object;"
	ifeq	l3 // aload_3
	aload_3
	checkcast	class "[Ljava/lang/Object;"
	checkcast	class "[Ljava/lang/Object;"
	invokestatic	Method deepHashCode:([Ljava/lang/Object;)I
	goto	l4 // iadd
l3	aload_3
	instanceof	class "[B"
	ifeq	l5 // aload_3
	aload_3
	checkcast	class "[B"
	checkcast	class "[B"
	invokestatic	Method hashCode:([B)I
	goto	l4 // iadd
l5	aload_3
	instanceof	class "[S"
	ifeq	l6 // aload_3
	aload_3
	checkcast	class "[S"
	checkcast	class "[S"
	invokestatic	Method hashCode:([S)I
	goto	l4 // iadd
l6	aload_3
	instanceof	class "[I"
	ifeq	l7 // aload_3
	aload_3
	checkcast	class "[I"
	checkcast	class "[I"
	invokestatic	Method hashCode:([I)I
	goto	l4 // iadd
l7	aload_3
	instanceof	class "[J"
	ifeq	l8 // aload_3
	aload_3
	checkcast	class "[J"
	checkcast	class "[J"
	invokestatic	Method hashCode:([J)I
	goto	l4 // iadd
l8	aload_3
	instanceof	class "[C"
	ifeq	l9 // aload_3
	aload_3
	checkcast	class "[C"
	checkcast	class "[C"
	invokestatic	Method hashCode:([C)I
	goto	l4 // iadd
l9	aload_3
	instanceof	class "[Z"
	ifeq	l10 // aload_3
	aload_3
	checkcast	class "[Z"
	checkcast	class "[Z"
	invokestatic	Method hashCode:([Z)I
	goto	l4 // iadd
l10	aload_3
	instanceof	class "[F"
	ifeq	l11 // aload_3
	aload_3
	checkcast	class "[F"
	checkcast	class "[F"
	invokestatic	Method hashCode:([F)I
	goto	l4 // iadd
l11	aload_3
	instanceof	class "[D"
	ifeq	l12 // aload_3
	aload_3
	checkcast	class "[D"
	checkcast	class "[D"
	invokestatic	Method hashCode:([D)I
	goto	l4 // iadd
l12	aload_3
	ifnull	l13 // iconst_0
	aload_3
	invokevirtual	Method java/lang/Object.hashCode:()I
	goto	l4 // iadd
l13	iconst_0
l4	iadd
	istore_1
	iinc	2, 1
	goto	l14 // iload_2
l2	iload_1
	ireturn
  Labels:
   	l1 = 6 // iconst_1
   	l14 = 10 // iload_2
   	l3 = 44 // aload_3
   	l5 = 64 // aload_3
   	l6 = 84 // aload_3
   	l7 = 104 // aload_3
   	l8 = 124 // aload_3
   	l9 = 144 // aload_3
   	l10 = 164 // aload_3
   	l11 = 184 // aload_3
   	l12 = 204 // aload_3
   	l13 = 215 // iconst_0
   	l4 = 216 // iadd
   	l2 = 224 // iload_1

public static boolean deepEquals(java.lang.Object[], java.lang.Object[]);
  Signature: ([Ljava/lang/Object;[Ljava/lang/Object;)Z
  Code:
   Stack=2, Locals=7, Args_size=2
	aload_0
	aload_1
	if_acmpne	l1 // aload_0
	iconst_1
	ireturn
l1	aload_0
	ifnull	l2 // iconst_0
	aload_1
	ifnonnull	l3 // aload_0
l2	iconst_0
	ireturn
l3	aload_0
	arraylength
	istore_2
	iload_2
	aload_1
	arraylength
	if_icmpeq	l4 // iconst_0
	iconst_0
	ireturn
l4	iconst_0
	istore_3
l21	iload_3
	iload_2
	if_icmpge	l5 // iconst_1
	aload_0
	iload_3
	aaload
	astore	4
	aload_1
	iload_3
	aaload
	astore	5
	aload	4
	aload	5
	if_acmpne	l6 // aload
	goto	l7 // iinc
l6	aload	4
	ifnonnull	l8 // aload
	iconst_0
	ireturn
l8	aload	4
	invokevirtual	Method java/lang/Object.getClass:()Ljava/lang/Class;
	aload	5
	invokevirtual	Method java/lang/Object.getClass:()Ljava/lang/Class;
	if_acmpne	l9 // aload
	aload	4
	invokevirtual	Method java/lang/Object.getClass:()Ljava/lang/Class;
	invokevirtual	Method java/lang/Class.isArray:()Z
	ifeq	l10 // aload
l9	aload	4
	aload	5
	invokevirtual	Method java/lang/Object.equals:(Ljava/lang/Object;)Z
	goto	l11 // istore
l10	aload	4
	instanceof	class "[Ljava/lang/Object;"
	ifeq	l12 // aload
	aload	5
	instanceof	class "[Ljava/lang/Object;"
	ifeq	l12 // aload
	aload	4
	checkcast	class "[Ljava/lang/Object;"
	checkcast	class "[Ljava/lang/Object;"
	aload	5
	checkcast	class "[Ljava/lang/Object;"
	checkcast	class "[Ljava/lang/Object;"
	invokestatic	Method deepEquals:([Ljava/lang/Object;[Ljava/lang/Object;)Z
	goto	l11 // istore
l12	aload	4
	instanceof	class "[B"
	ifeq	l13 // aload
	aload	5
	instanceof	class "[B"
	ifeq	l13 // aload
	aload	4
	checkcast	class "[B"
	checkcast	class "[B"
	aload	5
	checkcast	class "[B"
	checkcast	class "[B"
	invokestatic	Method equals:([B[B)Z
	goto	l11 // istore
l13	aload	4
	instanceof	class "[S"
	ifeq	l14 // aload
	aload	5
	instanceof	class "[S"
	ifeq	l14 // aload
	aload	4
	checkcast	class "[S"
	checkcast	class "[S"
	aload	5
	checkcast	class "[S"
	checkcast	class "[S"
	invokestatic	Method equals:([S[S)Z
	goto	l11 // istore
l14	aload	4
	instanceof	class "[I"
	ifeq	l15 // aload
	aload	5
	instanceof	class "[I"
	ifeq	l15 // aload
	aload	4
	checkcast	class "[I"
	checkcast	class "[I"
	aload	5
	checkcast	class "[I"
	checkcast	class "[I"
	invokestatic	Method equals:([I[I)Z
	goto	l11 // istore
l15	aload	4
	instanceof	class "[J"
	ifeq	l16 // aload
	aload	5
	instanceof	class "[J"
	ifeq	l16 // aload
	aload	4
	checkcast	class "[J"
	checkcast	class "[J"
	aload	5
	checkcast	class "[J"
	checkcast	class "[J"
	invokestatic	Method equals:([J[J)Z
	goto	l11 // istore
l16	aload	4
	instanceof	class "[C"
	ifeq	l17 // aload
	aload	5
	instanceof	class "[C"
	ifeq	l17 // aload
	aload	4
	checkcast	class "[C"
	checkcast	class "[C"
	aload	5
	checkcast	class "[C"
	checkcast	class "[C"
	invokestatic	Method equals:([C[C)Z
	goto	l11 // istore
l17	aload	4
	instanceof	class "[Z"
	ifeq	l18 // aload
	aload	5
	instanceof	class "[Z"
	ifeq	l18 // aload
	aload	4
	checkcast	class "[Z"
	checkcast	class "[Z"
	aload	5
	checkcast	class "[Z"
	checkcast	class "[Z"
	invokestatic	Method equals:([Z[Z)Z
	goto	l11 // istore
l18	aload	4
	instanceof	class "[F"
	ifeq	l19 // aload
	aload	5
	instanceof	class "[F"
	ifeq	l19 // aload
	aload	4
	checkcast	class "[F"
	checkcast	class "[F"
	aload	5
	checkcast	class "[F"
	checkcast	class "[F"
	invokestatic	Method equals:([F[F)Z
	goto	l11 // istore
l19	aload	4
	instanceof	class "[D"
	ifeq	l20 // aload
	aload	5
	instanceof	class "[D"
	ifeq	l20 // aload
	aload	4
	checkcast	class "[D"
	checkcast	class "[D"
	aload	5
	checkcast	class "[D"
	checkcast	class "[D"
	invokestatic	Method equals:([D[D)Z
	goto	l11 // istore
l20	aload	4
	aload	5
	invokevirtual	Method java/lang/Object.equals:(Ljava/lang/Object;)Z
l11	istore	6
	iload	6
	ifne	l7 // iinc
	iconst_0
	ireturn
l7	iinc	3, 1
	goto	l21 // iload_3
l5	iconst_1
	ireturn
  Labels:
   	l1 = 7 // aload_0
   	l2 = 15 // iconst_0
   	l3 = 17 // aload_0
   	l4 = 28 // iconst_0
   	l21 = 30 // iload_3
   	l6 = 55 // aload
   	l8 = 62 // aload
   	l9 = 86 // aload
   	l10 = 96 // aload
   	l12 = 134 // aload
   	l13 = 172 // aload
   	l14 = 210 // aload
   	l15 = 248 // aload
   	l16 = 286 // aload
   	l17 = 324 // aload
   	l18 = 362 // aload
   	l19 = 400 // aload
   	l20 = 438 // aload
   	l11 = 445 // istore
   	l7 = 454 // iinc
   	l5 = 460 // iconst_1

public static java.lang.String toString(long[]);
  Signature: ([J)Ljava/lang/String;
  Code:
   Stack=3, Locals=3, Args_size=1
	aload_0
	ifnonnull	l1 // aload_0
	ldc	String null
	areturn
l1	aload_0
	arraylength
	ifne	l2 // new
	ldc	String []
	areturn
l2	new	class java/lang/StringBuffer
	dup
	invokespecial	Method java/lang/StringBuffer."<init>":()V
	astore_1
	aload_1
	bipush	91
	invokevirtual	Method java/lang/StringBuffer.append:(C)Ljava/lang/StringBuffer;
	aload_0
	iconst_0
	laload
	invokevirtual	Method java/lang/StringBuffer.append:(J)Ljava/lang/StringBuffer;
	pop
	iconst_1
	istore_2
l4	iload_2
	aload_0
	arraylength
	if_icmpge	l3 // aload_1
	aload_1
	ldc	String , 
	invokevirtual	Method java/lang/StringBuffer.append:(Ljava/lang/String;)Ljava/lang/StringBuffer;
	aload_0
	iload_2
	laload
	invokevirtual	Method java/lang/StringBuffer.append:(J)Ljava/lang/StringBuffer;
	pop
	iinc	2, 1
	goto	l4 // iload_2
l3	aload_1
	bipush	93
	invokevirtual	Method java/lang/StringBuffer.append:(C)Ljava/lang/StringBuffer;
	pop
	aload_1
	invokevirtual	Method java/lang/StringBuffer.toString:()Ljava/lang/String;
	areturn
  Labels:
   	l1 = 7 // aload_0
   	l2 = 15 // new
   	l4 = 38 // iload_2
   	l3 = 63 // aload_1

public static java.lang.String toString(int[]);
  Signature: ([I)Ljava/lang/String;
  Code:
   Stack=3, Locals=3, Args_size=1
	aload_0
	ifnonnull	l1 // aload_0
	ldc	String null
	areturn
l1	aload_0
	arraylength
	ifne	l2 // new
	ldc	String []
	areturn
l2	new	class java/lang/StringBuffer
	dup
	invokespecial	Method java/lang/StringBuffer."<init>":()V
	astore_1
	aload_1
	bipush	91
	invokevirtual	Method java/lang/StringBuffer.append:(C)Ljava/lang/StringBuffer;
	aload_0
	iconst_0
	iaload
	invokevirtual	Method java/lang/StringBuffer.append:(I)Ljava/lang/StringBuffer;
	pop
	iconst_1
	istore_2
l4	iload_2
	aload_0
	arraylength
	if_icmpge	l3 // aload_1
	aload_1
	ldc	String , 
	invokevirtual	Method java/lang/StringBuffer.append:(Ljava/lang/String;)Ljava/lang/StringBuffer;
	aload_0
	iload_2
	iaload
	invokevirtual	Method java/lang/StringBuffer.append:(I)Ljava/lang/StringBuffer;
	pop
	iinc	2, 1
	goto	l4 // iload_2
l3	aload_1
	bipush	93
	invokevirtual	Method java/lang/StringBuffer.append:(C)Ljava/lang/StringBuffer;
	pop
	aload_1
	invokevirtual	Method java/lang/StringBuffer.toString:()Ljava/lang/String;
	areturn
  Labels:
   	l1 = 7 // aload_0
   	l2 = 15 // new
   	l4 = 38 // iload_2
   	l3 = 63 // aload_1

public static java.lang.String toString(short[]);
  Signature: ([S)Ljava/lang/String;
  Code:
   Stack=3, Locals=3, Args_size=1
	aload_0
	ifnonnull	l1 // aload_0
	ldc	String null
	areturn
l1	aload_0
	arraylength
	ifne	l2 // new
	ldc	String []
	areturn
l2	new	class java/lang/StringBuffer
	dup
	invokespecial	Method java/lang/StringBuffer."<init>":()V
	astore_1
	aload_1
	bipush	91
	invokevirtual	Method java/lang/StringBuffer.append:(C)Ljava/lang/StringBuffer;
	aload_0
	iconst_0
	saload
	invokevirtual	Method java/lang/StringBuffer.append:(I)Ljava/lang/StringBuffer;
	pop
	iconst_1
	istore_2
l4	iload_2
	aload_0
	arraylength
	if_icmpge	l3 // aload_1
	aload_1
	ldc	String , 
	invokevirtual	Method java/lang/StringBuffer.append:(Ljava/lang/String;)Ljava/lang/StringBuffer;
	aload_0
	iload_2
	saload
	invokevirtual	Method java/lang/StringBuffer.append:(I)Ljava/lang/StringBuffer;
	pop
	iinc	2, 1
	goto	l4 // iload_2
l3	aload_1
	bipush	93
	invokevirtual	Method java/lang/StringBuffer.append:(C)Ljava/lang/StringBuffer;
	pop
	aload_1
	invokevirtual	Method java/lang/StringBuffer.toString:()Ljava/lang/String;
	areturn
  Labels:
   	l1 = 7 // aload_0
   	l2 = 15 // new
   	l4 = 38 // iload_2
   	l3 = 63 // aload_1

public static java.lang.String toString(char[]);
  Signature: ([C)Ljava/lang/String;
  Code:
   Stack=3, Locals=3, Args_size=1
	aload_0
	ifnonnull	l1 // aload_0
	ldc	String null
	areturn
l1	aload_0
	arraylength
	ifne	l2 // new
	ldc	String []
	areturn
l2	new	class java/lang/StringBuffer
	dup
	invokespecial	Method java/lang/StringBuffer."<init>":()V
	astore_1
	aload_1
	bipush	91
	invokevirtual	Method java/lang/StringBuffer.append:(C)Ljava/lang/StringBuffer;
	aload_0
	iconst_0
	caload
	invokevirtual	Method java/lang/StringBuffer.append:(C)Ljava/lang/StringBuffer;
	pop
	iconst_1
	istore_2
l4	iload_2
	aload_0
	arraylength
	if_icmpge	l3 // aload_1
	aload_1
	ldc	String , 
	invokevirtual	Method java/lang/StringBuffer.append:(Ljava/lang/String;)Ljava/lang/StringBuffer;
	aload_0
	iload_2
	caload
	invokevirtual	Method java/lang/StringBuffer.append:(C)Ljava/lang/StringBuffer;
	pop
	iinc	2, 1
	goto	l4 // iload_2
l3	aload_1
	bipush	93
	invokevirtual	Method java/lang/StringBuffer.append:(C)Ljava/lang/StringBuffer;
	pop
	aload_1
	invokevirtual	Method java/lang/StringBuffer.toString:()Ljava/lang/String;
	areturn
  Labels:
   	l1 = 7 // aload_0
   	l2 = 15 // new
   	l4 = 38 // iload_2
   	l3 = 63 // aload_1

public static java.lang.String toString(byte[]);
  Signature: ([B)Ljava/lang/String;
  Code:
   Stack=3, Locals=3, Args_size=1
	aload_0
	ifnonnull	l1 // aload_0
	ldc	String null
	areturn
l1	aload_0
	arraylength
	ifne	l2 // new
	ldc	String []
	areturn
l2	new	class java/lang/StringBuffer
	dup
	invokespecial	Method java/lang/StringBuffer."<init>":()V
	astore_1
	aload_1
	bipush	91
	invokevirtual	Method java/lang/StringBuffer.append:(C)Ljava/lang/StringBuffer;
	aload_0
	iconst_0
	baload
	invokevirtual	Method java/lang/StringBuffer.append:(I)Ljava/lang/StringBuffer;
	pop
	iconst_1
	istore_2
l4	iload_2
	aload_0
	arraylength
	if_icmpge	l3 // aload_1
	aload_1
	ldc	String , 
	invokevirtual	Method java/lang/StringBuffer.append:(Ljava/lang/String;)Ljava/lang/StringBuffer;
	aload_0
	iload_2
	baload
	invokevirtual	Method java/lang/StringBuffer.append:(I)Ljava/lang/StringBuffer;
	pop
	iinc	2, 1
	goto	l4 // iload_2
l3	aload_1
	bipush	93
	invokevirtual	Method java/lang/StringBuffer.append:(C)Ljava/lang/StringBuffer;
	pop
	aload_1
	invokevirtual	Method java/lang/StringBuffer.toString:()Ljava/lang/String;
	areturn
  Labels:
   	l1 = 7 // aload_0
   	l2 = 15 // new
   	l4 = 38 // iload_2
   	l3 = 63 // aload_1

public static java.lang.String toString(boolean[]);
  Signature: ([Z)Ljava/lang/String;
  Code:
   Stack=3, Locals=3, Args_size=1
	aload_0
	ifnonnull	l1 // aload_0
	ldc	String null
	areturn
l1	aload_0
	arraylength
	ifne	l2 // new
	ldc	String []
	areturn
l2	new	class java/lang/StringBuffer
	dup
	invokespecial	Method java/lang/StringBuffer."<init>":()V
	astore_1
	aload_1
	bipush	91
	invokevirtual	Method java/lang/StringBuffer.append:(C)Ljava/lang/StringBuffer;
	aload_0
	iconst_0
	baload
	invokevirtual	Method java/lang/StringBuffer.append:(Z)Ljava/lang/StringBuffer;
	pop
	iconst_1
	istore_2
l4	iload_2
	aload_0
	arraylength
	if_icmpge	l3 // aload_1
	aload_1
	ldc	String , 
	invokevirtual	Method java/lang/StringBuffer.append:(Ljava/lang/String;)Ljava/lang/StringBuffer;
	aload_0
	iload_2
	baload
	invokevirtual	Method java/lang/StringBuffer.append:(Z)Ljava/lang/StringBuffer;
	pop
	iinc	2, 1
	goto	l4 // iload_2
l3	aload_1
	bipush	93
	invokevirtual	Method java/lang/StringBuffer.append:(C)Ljava/lang/StringBuffer;
	pop
	aload_1
	invokevirtual	Method java/lang/StringBuffer.toString:()Ljava/lang/String;
	areturn
  Labels:
   	l1 = 7 // aload_0
   	l2 = 15 // new
   	l4 = 38 // iload_2
   	l3 = 63 // aload_1

public static java.lang.String toString(float[]);
  Signature: ([F)Ljava/lang/String;
  Code:
   Stack=3, Locals=3, Args_size=1
	aload_0
	ifnonnull	l1 // aload_0
	ldc	String null
	areturn
l1	aload_0
	arraylength
	ifne	l2 // new
	ldc	String []
	areturn
l2	new	class java/lang/StringBuffer
	dup
	invokespecial	Method java/lang/StringBuffer."<init>":()V
	astore_1
	aload_1
	bipush	91
	invokevirtual	Method java/lang/StringBuffer.append:(C)Ljava/lang/StringBuffer;
	aload_0
	iconst_0
	faload
	invokevirtual	Method java/lang/StringBuffer.append:(F)Ljava/lang/StringBuffer;
	pop
	iconst_1
	istore_2
l4	iload_2
	aload_0
	arraylength
	if_icmpge	l3 // aload_1
	aload_1
	ldc	String , 
	invokevirtual	Method java/lang/StringBuffer.append:(Ljava/lang/String;)Ljava/lang/StringBuffer;
	aload_0
	iload_2
	faload
	invokevirtual	Method java/lang/StringBuffer.append:(F)Ljava/lang/StringBuffer;
	pop
	iinc	2, 1
	goto	l4 // iload_2
l3	aload_1
	bipush	93
	invokevirtual	Method java/lang/StringBuffer.append:(C)Ljava/lang/StringBuffer;
	pop
	aload_1
	invokevirtual	Method java/lang/StringBuffer.toString:()Ljava/lang/String;
	areturn
  Labels:
   	l1 = 7 // aload_0
   	l2 = 15 // new
   	l4 = 38 // iload_2
   	l3 = 63 // aload_1

public static java.lang.String toString(double[]);
  Signature: ([D)Ljava/lang/String;
  Code:
   Stack=3, Locals=3, Args_size=1
	aload_0
	ifnonnull	l1 // aload_0
	ldc	String null
	areturn
l1	aload_0
	arraylength
	ifne	l2 // new
	ldc	String []
	areturn
l2	new	class java/lang/StringBuffer
	dup
	invokespecial	Method java/lang/StringBuffer."<init>":()V
	astore_1
	aload_1
	bipush	91
	invokevirtual	Method java/lang/StringBuffer.append:(C)Ljava/lang/StringBuffer;
	aload_0
	iconst_0
	daload
	invokevirtual	Method java/lang/StringBuffer.append:(D)Ljava/lang/StringBuffer;
	pop
	iconst_1
	istore_2
l4	iload_2
	aload_0
	arraylength
	if_icmpge	l3 // aload_1
	aload_1
	ldc	String , 
	invokevirtual	Method java/lang/StringBuffer.append:(Ljava/lang/String;)Ljava/lang/StringBuffer;
	aload_0
	iload_2
	daload
	invokevirtual	Method java/lang/StringBuffer.append:(D)Ljava/lang/StringBuffer;
	pop
	iinc	2, 1
	goto	l4 // iload_2
l3	aload_1
	bipush	93
	invokevirtual	Method java/lang/StringBuffer.append:(C)Ljava/lang/StringBuffer;
	pop
	aload_1
	invokevirtual	Method java/lang/StringBuffer.toString:()Ljava/lang/String;
	areturn
  Labels:
   	l1 = 7 // aload_0
   	l2 = 15 // new
   	l4 = 38 // iload_2
   	l3 = 63 // aload_1

public static java.lang.String toString(java.lang.Object[]);
  Signature: ([Ljava/lang/Object;)Ljava/lang/String;
  Code:
   Stack=3, Locals=3, Args_size=1
	aload_0
	ifnonnull	l1 // aload_0
	ldc	String null
	areturn
l1	aload_0
	arraylength
	ifne	l2 // new
	ldc	String []
	areturn
l2	new	class java/lang/StringBuffer
	dup
	invokespecial	Method java/lang/StringBuffer."<init>":()V
	astore_1
	aload_1
	bipush	91
	invokevirtual	Method java/lang/StringBuffer.append:(C)Ljava/lang/StringBuffer;
	aload_0
	iconst_0
	aaload
	invokevirtual	Method java/lang/StringBuffer.append:(Ljava/lang/Object;)Ljava/lang/StringBuffer;
	pop
	iconst_1
	istore_2
l4	iload_2
	aload_0
	arraylength
	if_icmpge	l3 // aload_1
	aload_1
	ldc	String , 
	invokevirtual	Method java/lang/StringBuffer.append:(Ljava/lang/String;)Ljava/lang/StringBuffer;
	aload_0
	iload_2
	aaload
	invokevirtual	Method java/lang/StringBuffer.append:(Ljava/lang/Object;)Ljava/lang/StringBuffer;
	pop
	iinc	2, 1
	goto	l4 // iload_2
l3	aload_1
	bipush	93
	invokevirtual	Method java/lang/StringBuffer.append:(C)Ljava/lang/StringBuffer;
	pop
	aload_1
	invokevirtual	Method java/lang/StringBuffer.toString:()Ljava/lang/String;
	areturn
  Labels:
   	l1 = 7 // aload_0
   	l2 = 15 // new
   	l4 = 38 // iload_2
   	l3 = 63 // aload_1

public static java.lang.String deepToString(java.lang.Object[]);
  Signature: ([Ljava/lang/Object;)Ljava/lang/String;
  Code:
   Stack=4, Locals=2, Args_size=1
	aload_0
	ifnonnull	l1 // new
	ldc	String null
	areturn
l1	new	class java/lang/StringBuffer
	dup
	invokespecial	Method java/lang/StringBuffer."<init>":()V
	astore_1
	aload_0
	aload_1
	new	class java/util/ArrayList
	dup
	invokespecial	Method java/util/ArrayList."<init>":()V
	invokestatic	Method deepToString:([Ljava/lang/Object;Ljava/lang/StringBuffer;Ljava/util/List;)V
	aload_1
	invokevirtual	Method java/lang/StringBuffer.toString:()Ljava/lang/String;
	areturn
  Labels:
   	l1 = 7 // new

private static void deepToString(java.lang.Object[], java.lang.StringBuffer, java.util.List);
  Signature: ([Ljava/lang/Object;Ljava/lang/StringBuffer;Ljava/util/List;)V
  Code:
   Stack=3, Locals=5, Args_size=3
	aload_2
	aload_0
	invokeinterface	InterfaceMethod java/util/List.add:(Ljava/lang/Object;)Z
	pop
	aload_1
	bipush	91
	invokevirtual	Method java/lang/StringBuffer.append:(C)Ljava/lang/StringBuffer;
	pop
	iconst_0
	istore_3
l17	iload_3
	aload_0
	arraylength
	if_icmpge	l1 // aload_1
	iload_3
	ifle	l2 // aload_0
	aload_1
	ldc	String , 
	invokevirtual	Method java/lang/StringBuffer.append:(Ljava/lang/String;)Ljava/lang/StringBuffer;
	pop
l2	aload_0
	iload_3
	aaload
	astore	4
	aload	4
	ifnonnull	l3 // aload
	aload_1
	ldc	String null
	invokevirtual	Method java/lang/StringBuffer.append:(Ljava/lang/String;)Ljava/lang/StringBuffer;
	pop
	goto	l4 // iinc
l3	aload	4
	invokevirtual	Method java/lang/Object.getClass:()Ljava/lang/Class;
	invokevirtual	Method java/lang/Class.isArray:()Z
	ifne	l5 // aload
	aload_1
	aload	4
	invokevirtual	Method java/lang/Object.toString:()Ljava/lang/String;
	invokevirtual	Method java/lang/StringBuffer.append:(Ljava/lang/String;)Ljava/lang/StringBuffer;
	pop
	goto	l4 // iinc
l5	aload	4
	instanceof	class "[Ljava/lang/Object;"
	ifeq	l6 // aload_1
	aload_2
	aload	4
	invokeinterface	InterfaceMethod java/util/List.contains:(Ljava/lang/Object;)Z
	ifeq	l7 // aload
	aload_1
	ldc	String [...]
	invokevirtual	Method java/lang/StringBuffer.append:(Ljava/lang/String;)Ljava/lang/StringBuffer;
	pop
	goto	l4 // iinc
l7	aload	4
	checkcast	class "[Ljava/lang/Object;"
	checkcast	class "[Ljava/lang/Object;"
	aload_1
	aload_2
	invokestatic	Method deepToString:([Ljava/lang/Object;Ljava/lang/StringBuffer;Ljava/util/List;)V
	goto	l4 // iinc
l6	aload_1
	aload	4
	instanceof	class "[B"
	ifeq	l8 // aload
	aload	4
	checkcast	class "[B"
	checkcast	class "[B"
	invokestatic	Method toString:([B)Ljava/lang/String;
	goto	l9 // invokevirtual
l8	aload	4
	instanceof	class "[S"
	ifeq	l10 // aload
	aload	4
	checkcast	class "[S"
	checkcast	class "[S"
	invokestatic	Method toString:([S)Ljava/lang/String;
	goto	l9 // invokevirtual
l10	aload	4
	instanceof	class "[I"
	ifeq	l11 // aload
	aload	4
	checkcast	class "[I"
	checkcast	class "[I"
	invokestatic	Method toString:([I)Ljava/lang/String;
	goto	l9 // invokevirtual
l11	aload	4
	instanceof	class "[J"
	ifeq	l12 // aload
	aload	4
	checkcast	class "[J"
	checkcast	class "[J"
	invokestatic	Method toString:([J)Ljava/lang/String;
	goto	l9 // invokevirtual
l12	aload	4
	instanceof	class "[C"
	ifeq	l13 // aload
	aload	4
	checkcast	class "[C"
	checkcast	class "[C"
	invokestatic	Method toString:([C)Ljava/lang/String;
	goto	l9 // invokevirtual
l13	aload	4
	instanceof	class "[Z"
	ifeq	l14 // aload
	aload	4
	checkcast	class "[Z"
	checkcast	class "[Z"
	invokestatic	Method toString:([Z)Ljava/lang/String;
	goto	l9 // invokevirtual
l14	aload	4
	instanceof	class "[F"
	ifeq	l15 // aload
	aload	4
	checkcast	class "[F"
	checkcast	class "[F"
	invokestatic	Method toString:([F)Ljava/lang/String;
	goto	l9 // invokevirtual
l15	aload	4
	instanceof	class "[D"
	ifeq	l16 // ldc
	aload	4
	checkcast	class "[D"
	checkcast	class "[D"
	invokestatic	Method toString:([D)Ljava/lang/String;
	goto	l9 // invokevirtual
l16	ldc	String 
l9	invokevirtual	Method java/lang/StringBuffer.append:(Ljava/lang/String;)Ljava/lang/StringBuffer;
	pop
l4	iinc	3, 1
	goto	l17 // iload_3
l1	aload_1
	bipush	93
	invokevirtual	Method java/lang/StringBuffer.append:(C)Ljava/lang/StringBuffer;
	pop
	aload_2
	aload_2
	invokeinterface	InterfaceMethod java/util/List.size:()I
	iconst_1
	isub
	invokeinterface	InterfaceMethod java/util/List.remove:(I)Ljava/lang/Object;
	pop
	return
  Labels:
   	l17 = 17 // iload_3
   	l2 = 34 // aload_0
   	l3 = 54 // aload
   	l5 = 78 // aload
   	l7 = 107 // aload
   	l6 = 123 // aload_1
   	l8 = 146 // aload
   	l10 = 168 // aload
   	l11 = 190 // aload
   	l12 = 212 // aload
   	l13 = 234 // aload
   	l14 = 256 // aload
   	l15 = 278 // aload
   	l16 = 300 // ldc
   	l9 = 302 // invokevirtual
   	l4 = 306 // iinc
   	l1 = 312 // aload_1

}

