public class scala.actors.threadpool.AtomicInteger extends java.lang.Number implements java.io.Serializable
  minor version: 0
  major version: 49
  Constant pool:
Method	java/lang/Number."<init>":()V
Field	scala/actors/threadpool/AtomicInteger.value:I
Method	scala/actors/threadpool/AtomicInteger.get:()I
Method	java/lang/Integer.toString:(I)Ljava/lang/String;
class	scala/actors/threadpool/AtomicInteger
class	java/lang/Number
class	java/io/Serializable
Asciz	serialVersionUID;
Asciz	J;
Asciz	ConstantValue;
long	6214790243416807050l;
Asciz	value;
Asciz	I;
Asciz	<init>;
Asciz	(I)V;
Asciz	Code;
Asciz	()V;
Asciz	get;
Asciz	()I;
Asciz	set;
Asciz	lazySet;
Asciz	getAndSet;
Asciz	(I)I;
Asciz	compareAndSet;
Asciz	(II)Z;
Asciz	weakCompareAndSet;
Asciz	getAndIncrement;
Asciz	getAndDecrement;
Asciz	getAndAdd;
Asciz	incrementAndGet;
Asciz	decrementAndGet;
Asciz	addAndGet;
Asciz	toString;
Asciz	()Ljava/lang/String;;
Asciz	intValue;
Asciz	longValue;
Asciz	()J;
Asciz	floatValue;
Asciz	()F;
Asciz	doubleValue;
Asciz	()D;
NameAndType	"<init>":()V
NameAndType	value:I
NameAndType	get:()I
class	java/lang/Integer
NameAndType	toString:(I)Ljava/lang/String;
Asciz	scala/actors/threadpool/AtomicInteger;
Asciz	java/lang/Number;
Asciz	java/io/Serializable;
Asciz	java/lang/Integer;
Asciz	(I)Ljava/lang/String;;

{
private static final long serialVersionUID;
  Signature: J
  Constant value: long 6214790243416807050l
private volatile int value;
  Signature: I

public scala.actors.threadpool.AtomicInteger(int);
  Signature: (I)V
  Code:
   Stack=2, Locals=2, Args_size=2
	aload_0
	invokespecial	Method java/lang/Number."<init>":()V
	aload_0
	iload_1
	putfield	Field value:I
	return
  Labels:

public scala.actors.threadpool.AtomicInteger();
  Signature: ()V
  Code:
   Stack=1, Locals=1, Args_size=1
	aload_0
	invokespecial	Method java/lang/Number."<init>":()V
	return
  Labels:

public final int get();
  Signature: ()I
  Code:
   Stack=1, Locals=1, Args_size=1
	aload_0
	getfield	Field value:I
	ireturn
  Labels:

public final synchronized void set(int);
  Signature: (I)V
  Code:
   Stack=2, Locals=2, Args_size=2
	aload_0
	iload_1
	putfield	Field value:I
	return
  Labels:

public final synchronized void lazySet(int);
  Signature: (I)V
  Code:
   Stack=2, Locals=2, Args_size=2
	aload_0
	iload_1
	putfield	Field value:I
	return
  Labels:

public final synchronized int getAndSet(int);
  Signature: (I)I
  Code:
   Stack=2, Locals=3, Args_size=2
	aload_0
	getfield	Field value:I
	istore_2
	aload_0
	iload_1
	putfield	Field value:I
	iload_2
	ireturn
  Labels:

public final synchronized boolean compareAndSet(int, int);
  Signature: (II)Z
  Code:
   Stack=2, Locals=3, Args_size=3
	aload_0
	getfield	Field value:I
	iload_1
	if_icmpne	l1 // iconst_0
	aload_0
	iload_2
	putfield	Field value:I
	iconst_1
	ireturn
l1	iconst_0
	ireturn
  Labels:
   	l1 = 15 // iconst_0

public final synchronized boolean weakCompareAndSet(int, int);
  Signature: (II)Z
  Code:
   Stack=2, Locals=3, Args_size=3
	aload_0
	getfield	Field value:I
	iload_1
	if_icmpne	l1 // iconst_0
	aload_0
	iload_2
	putfield	Field value:I
	iconst_1
	ireturn
l1	iconst_0
	ireturn
  Labels:
   	l1 = 15 // iconst_0

public final synchronized int getAndIncrement();
  Signature: ()I
  Code:
   Stack=4, Locals=1, Args_size=1
	aload_0
	dup
	getfield	Field value:I
	dup_x1
	iconst_1
	iadd
	putfield	Field value:I
	ireturn
  Labels:

public final synchronized int getAndDecrement();
  Signature: ()I
  Code:
   Stack=4, Locals=1, Args_size=1
	aload_0
	dup
	getfield	Field value:I
	dup_x1
	iconst_1
	isub
	putfield	Field value:I
	ireturn
  Labels:

public final synchronized int getAndAdd(int);
  Signature: (I)I
  Code:
   Stack=3, Locals=3, Args_size=2
	aload_0
	getfield	Field value:I
	istore_2
	aload_0
	dup
	getfield	Field value:I
	iload_1
	iadd
	putfield	Field value:I
	iload_2
	ireturn
  Labels:

public final synchronized int incrementAndGet();
  Signature: ()I
  Code:
   Stack=3, Locals=1, Args_size=1
	aload_0
	dup
	getfield	Field value:I
	iconst_1
	iadd
	dup_x1
	putfield	Field value:I
	ireturn
  Labels:

public final synchronized int decrementAndGet();
  Signature: ()I
  Code:
   Stack=3, Locals=1, Args_size=1
	aload_0
	dup
	getfield	Field value:I
	iconst_1
	isub
	dup_x1
	putfield	Field value:I
	ireturn
  Labels:

public final synchronized int addAndGet(int);
  Signature: (I)I
  Code:
   Stack=3, Locals=2, Args_size=2
	aload_0
	dup
	getfield	Field value:I
	iload_1
	iadd
	dup_x1
	putfield	Field value:I
	ireturn
  Labels:

public java.lang.String toString();
  Signature: ()Ljava/lang/String;
  Code:
   Stack=1, Locals=1, Args_size=1
	aload_0
	invokevirtual	Method get:()I
	invokestatic	Method java/lang/Integer.toString:(I)Ljava/lang/String;
	areturn
  Labels:

public int intValue();
  Signature: ()I
  Code:
   Stack=1, Locals=1, Args_size=1
	aload_0
	invokevirtual	Method get:()I
	ireturn
  Labels:

public long longValue();
  Signature: ()J
  Code:
   Stack=2, Locals=1, Args_size=1
	aload_0
	invokevirtual	Method get:()I
	i2l
	lreturn
  Labels:

public float floatValue();
  Signature: ()F
  Code:
   Stack=1, Locals=1, Args_size=1
	aload_0
	invokevirtual	Method get:()I
	i2f
	freturn
  Labels:

public double doubleValue();
  Signature: ()D
  Code:
   Stack=2, Locals=1, Args_size=1
	aload_0
	invokevirtual	Method get:()I
	i2d
	dreturn
  Labels:

}

