public class scala.actors.threadpool.ExecutorCompletionService extends java.lang.Object implements scala.actors.threadpool.CompletionService
  InnerClass: 
   QueueingFuture=class scala/actors/threadpool/ExecutorCompletionService$QueueingFuture of class scala/actors/threadpool/ExecutorCompletionService
  minor version: 0
  major version: 49
  Constant pool:
Field	scala/actors/threadpool/ExecutorCompletionService.completionQueue:Lscala/actors/threadpool/BlockingQueue;
Field	scala/actors/threadpool/ExecutorCompletionService.aes:Lscala/actors/threadpool/AbstractExecutorService;
class	scala/actors/threadpool/FutureTask
Method	scala/actors/threadpool/FutureTask."<init>":(Lscala/actors/threadpool/Callable;)V
Method	scala/actors/threadpool/AbstractExecutorService.newTaskFor:(Lscala/actors/threadpool/Callable;)Lscala/actors/threadpool/RunnableFuture;
Method	scala/actors/threadpool/FutureTask."<init>":(Ljava/lang/Runnable;Ljava/lang/Object;)V
Method	scala/actors/threadpool/AbstractExecutorService.newTaskFor:(Ljava/lang/Runnable;Ljava/lang/Object;)Lscala/actors/threadpool/RunnableFuture;
Method	java/lang/Object."<init>":()V
class	java/lang/NullPointerException
Method	java/lang/NullPointerException."<init>":()V
Field	scala/actors/threadpool/ExecutorCompletionService.executor:Lscala/actors/threadpool/Executor;
class	scala/actors/threadpool/AbstractExecutorService
class	scala/actors/threadpool/LinkedBlockingQueue
Method	scala/actors/threadpool/LinkedBlockingQueue."<init>":()V
Method	scala/actors/threadpool/ExecutorCompletionService.newTaskFor:(Lscala/actors/threadpool/Callable;)Lscala/actors/threadpool/RunnableFuture;
class	scala/actors/threadpool/ExecutorCompletionService$QueueingFuture
Method	scala/actors/threadpool/ExecutorCompletionService$QueueingFuture."<init>":(Lscala/actors/threadpool/ExecutorCompletionService;Lscala/actors/threadpool/RunnableFuture;)V
InterfaceMethod	scala/actors/threadpool/Executor.execute:(Ljava/lang/Runnable;)V
Method	scala/actors/threadpool/ExecutorCompletionService.newTaskFor:(Ljava/lang/Runnable;Ljava/lang/Object;)Lscala/actors/threadpool/RunnableFuture;
InterfaceMethod	scala/actors/threadpool/BlockingQueue.take:()Ljava/lang/Object;
class	scala/actors/threadpool/Future
InterfaceMethod	scala/actors/threadpool/BlockingQueue.poll:()Ljava/lang/Object;
InterfaceMethod	scala/actors/threadpool/BlockingQueue.poll:(JLscala/actors/threadpool/TimeUnit;)Ljava/lang/Object;
class	scala/actors/threadpool/ExecutorCompletionService
class	java/lang/Object
class	scala/actors/threadpool/CompletionService
Asciz	QueueingFuture;
Asciz	InnerClasses;
Asciz	executor;
Asciz	Lscala/actors/threadpool/Executor;;
Asciz	aes;
Asciz	Lscala/actors/threadpool/AbstractExecutorService;;
Asciz	completionQueue;
Asciz	Lscala/actors/threadpool/BlockingQueue;;
Asciz	newTaskFor;
Asciz	(Lscala/actors/threadpool/Callable;)Lscala/actors/threadpool/RunnableFuture;;
Asciz	Code;
Asciz	(Ljava/lang/Runnable;Ljava/lang/Object;)Lscala/actors/threadpool/RunnableFuture;;
Asciz	<init>;
Asciz	(Lscala/actors/threadpool/Executor;)V;
Asciz	(Lscala/actors/threadpool/Executor;Lscala/actors/threadpool/BlockingQueue;)V;
Asciz	submit;
Asciz	(Lscala/actors/threadpool/Callable;)Lscala/actors/threadpool/Future;;
Asciz	(Ljava/lang/Runnable;Ljava/lang/Object;)Lscala/actors/threadpool/Future;;
Asciz	take;
Asciz	()Lscala/actors/threadpool/Future;;
Asciz	Exceptions;
class	java/lang/InterruptedException
Asciz	poll;
Asciz	(JLscala/actors/threadpool/TimeUnit;)Lscala/actors/threadpool/Future;;
Asciz	access$000;
Asciz	(Lscala/actors/threadpool/ExecutorCompletionService;)Lscala/actors/threadpool/BlockingQueue;;
NameAndType	completionQueue:Lscala/actors/threadpool/BlockingQueue;
NameAndType	aes:Lscala/actors/threadpool/AbstractExecutorService;
Asciz	scala/actors/threadpool/FutureTask;
NameAndType	"<init>":(Lscala/actors/threadpool/Callable;)V
NameAndType	newTaskFor:(Lscala/actors/threadpool/Callable;)Lscala/actors/threadpool/RunnableFuture;
NameAndType	"<init>":(Ljava/lang/Runnable;Ljava/lang/Object;)V
NameAndType	newTaskFor:(Ljava/lang/Runnable;Ljava/lang/Object;)Lscala/actors/threadpool/RunnableFuture;
NameAndType	"<init>":()V
Asciz	java/lang/NullPointerException;
NameAndType	executor:Lscala/actors/threadpool/Executor;
Asciz	scala/actors/threadpool/AbstractExecutorService;
Asciz	scala/actors/threadpool/LinkedBlockingQueue;
Asciz	scala/actors/threadpool/ExecutorCompletionService$QueueingFuture;
NameAndType	"<init>":(Lscala/actors/threadpool/ExecutorCompletionService;Lscala/actors/threadpool/RunnableFuture;)V
class	scala/actors/threadpool/Executor
NameAndType	execute:(Ljava/lang/Runnable;)V
class	scala/actors/threadpool/BlockingQueue
NameAndType	take:()Ljava/lang/Object;
Asciz	scala/actors/threadpool/Future;
NameAndType	poll:()Ljava/lang/Object;
NameAndType	poll:(JLscala/actors/threadpool/TimeUnit;)Ljava/lang/Object;
Asciz	scala/actors/threadpool/ExecutorCompletionService;
Asciz	java/lang/Object;
Asciz	scala/actors/threadpool/CompletionService;
Asciz	java/lang/InterruptedException;
Asciz	(Lscala/actors/threadpool/Callable;)V;
Asciz	(Ljava/lang/Runnable;Ljava/lang/Object;)V;
Asciz	()V;
Asciz	(Lscala/actors/threadpool/ExecutorCompletionService;Lscala/actors/threadpool/RunnableFuture;)V;
Asciz	scala/actors/threadpool/Executor;
Asciz	execute;
Asciz	(Ljava/lang/Runnable;)V;
Asciz	scala/actors/threadpool/BlockingQueue;
Asciz	()Ljava/lang/Object;;
Asciz	(JLscala/actors/threadpool/TimeUnit;)Ljava/lang/Object;;

{
private final scala.actors.threadpool.Executor executor;
  Signature: Lscala/actors/threadpool/Executor;

private final scala.actors.threadpool.AbstractExecutorService aes;
  Signature: Lscala/actors/threadpool/AbstractExecutorService;

private final scala.actors.threadpool.BlockingQueue completionQueue;
  Signature: Lscala/actors/threadpool/BlockingQueue;

private scala.actors.threadpool.RunnableFuture newTaskFor(scala.actors.threadpool.Callable);
  Signature: (Lscala/actors/threadpool/Callable;)Lscala/actors/threadpool/RunnableFuture;
  Code:
   Stack=3, Locals=2, Args_size=2
	aload_0
	getfield	Field aes:Lscala/actors/threadpool/AbstractExecutorService;
	ifnonnull	l1 // aload_0
	new	class scala/actors/threadpool/FutureTask
	dup
	aload_1
	invokespecial	Method scala/actors/threadpool/FutureTask."<init>":(Lscala/actors/threadpool/Callable;)V
	areturn
l1	aload_0
	getfield	Field aes:Lscala/actors/threadpool/AbstractExecutorService;
	aload_1
	invokevirtual	Method scala/actors/threadpool/AbstractExecutorService.newTaskFor:(Lscala/actors/threadpool/Callable;)Lscala/actors/threadpool/RunnableFuture;
	areturn
  Labels:
   	l1 = 16 // aload_0

private scala.actors.threadpool.RunnableFuture newTaskFor(java.lang.Runnable, java.lang.Object);
  Signature: (Ljava/lang/Runnable;Ljava/lang/Object;)Lscala/actors/threadpool/RunnableFuture;
  Code:
   Stack=4, Locals=3, Args_size=3
	aload_0
	getfield	Field aes:Lscala/actors/threadpool/AbstractExecutorService;
	ifnonnull	l1 // aload_0
	new	class scala/actors/threadpool/FutureTask
	dup
	aload_1
	aload_2
	invokespecial	Method scala/actors/threadpool/FutureTask."<init>":(Ljava/lang/Runnable;Ljava/lang/Object;)V
	areturn
l1	aload_0
	getfield	Field aes:Lscala/actors/threadpool/AbstractExecutorService;
	aload_1
	aload_2
	invokevirtual	Method scala/actors/threadpool/AbstractExecutorService.newTaskFor:(Ljava/lang/Runnable;Ljava/lang/Object;)Lscala/actors/threadpool/RunnableFuture;
	areturn
  Labels:
   	l1 = 17 // aload_0

public scala.actors.threadpool.ExecutorCompletionService(scala.actors.threadpool.Executor);
  Signature: (Lscala/actors/threadpool/Executor;)V
  Code:
   Stack=3, Locals=2, Args_size=2
	aload_0
	invokespecial	Method java/lang/Object."<init>":()V
	aload_1
	ifnonnull	l1 // aload_0
	new	class java/lang/NullPointerException
	dup
	invokespecial	Method java/lang/NullPointerException."<init>":()V
	athrow
l1	aload_0
	aload_1
	putfield	Field executor:Lscala/actors/threadpool/Executor;
	aload_0
	aload_1
	instanceof	class scala/actors/threadpool/AbstractExecutorService
	ifeq	l2 // aconst_null
	aload_1
	checkcast	class scala/actors/threadpool/AbstractExecutorService
	goto	l3 // putfield
l2	aconst_null
l3	putfield	Field aes:Lscala/actors/threadpool/AbstractExecutorService;
	aload_0
	new	class scala/actors/threadpool/LinkedBlockingQueue
	dup
	invokespecial	Method scala/actors/threadpool/LinkedBlockingQueue."<init>":()V
	putfield	Field completionQueue:Lscala/actors/threadpool/BlockingQueue;
	return
  Labels:
   	l1 = 16 // aload_0
   	l2 = 36 // aconst_null
   	l3 = 37 // putfield

public scala.actors.threadpool.ExecutorCompletionService(scala.actors.threadpool.Executor, scala.actors.threadpool.BlockingQueue);
  Signature: (Lscala/actors/threadpool/Executor;Lscala/actors/threadpool/BlockingQueue;)V
  Code:
   Stack=2, Locals=3, Args_size=3
	aload_0
	invokespecial	Method java/lang/Object."<init>":()V
	aload_1
	ifnull	l1 // new
	aload_2
	ifnonnull	l2 // aload_0
l1	new	class java/lang/NullPointerException
	dup
	invokespecial	Method java/lang/NullPointerException."<init>":()V
	athrow
l2	aload_0
	aload_1
	putfield	Field executor:Lscala/actors/threadpool/Executor;
	aload_0
	aload_1
	instanceof	class scala/actors/threadpool/AbstractExecutorService
	ifeq	l3 // aconst_null
	aload_1
	checkcast	class scala/actors/threadpool/AbstractExecutorService
	goto	l4 // putfield
l3	aconst_null
l4	putfield	Field aes:Lscala/actors/threadpool/AbstractExecutorService;
	aload_0
	aload_2
	putfield	Field completionQueue:Lscala/actors/threadpool/BlockingQueue;
	return
  Labels:
   	l1 = 12 // new
   	l2 = 20 // aload_0
   	l3 = 40 // aconst_null
   	l4 = 41 // putfield

public scala.actors.threadpool.Future submit(scala.actors.threadpool.Callable);
  Signature: (Lscala/actors/threadpool/Callable;)Lscala/actors/threadpool/Future;
  Code:
   Stack=5, Locals=3, Args_size=2
	aload_1
	ifnonnull	l1 // aload_0
	new	class java/lang/NullPointerException
	dup
	invokespecial	Method java/lang/NullPointerException."<init>":()V
	athrow
l1	aload_0
	aload_1
	invokespecial	Method newTaskFor:(Lscala/actors/threadpool/Callable;)Lscala/actors/threadpool/RunnableFuture;
	astore_2
	aload_0
	getfield	Field executor:Lscala/actors/threadpool/Executor;
	new	class scala/actors/threadpool/ExecutorCompletionService$QueueingFuture
	dup
	aload_0
	aload_2
	invokespecial	Method scala/actors/threadpool/ExecutorCompletionService$QueueingFuture."<init>":(Lscala/actors/threadpool/ExecutorCompletionService;Lscala/actors/threadpool/RunnableFuture;)V
	invokeinterface	InterfaceMethod scala/actors/threadpool/Executor.execute:(Ljava/lang/Runnable;)V
	aload_2
	areturn
  Labels:
   	l1 = 12 // aload_0

public scala.actors.threadpool.Future submit(java.lang.Runnable, java.lang.Object);
  Signature: (Ljava/lang/Runnable;Ljava/lang/Object;)Lscala/actors/threadpool/Future;
  Code:
   Stack=5, Locals=4, Args_size=3
	aload_1
	ifnonnull	l1 // aload_0
	new	class java/lang/NullPointerException
	dup
	invokespecial	Method java/lang/NullPointerException."<init>":()V
	athrow
l1	aload_0
	aload_1
	aload_2
	invokespecial	Method newTaskFor:(Ljava/lang/Runnable;Ljava/lang/Object;)Lscala/actors/threadpool/RunnableFuture;
	astore_3
	aload_0
	getfield	Field executor:Lscala/actors/threadpool/Executor;
	new	class scala/actors/threadpool/ExecutorCompletionService$QueueingFuture
	dup
	aload_0
	aload_3
	invokespecial	Method scala/actors/threadpool/ExecutorCompletionService$QueueingFuture."<init>":(Lscala/actors/threadpool/ExecutorCompletionService;Lscala/actors/threadpool/RunnableFuture;)V
	invokeinterface	InterfaceMethod scala/actors/threadpool/Executor.execute:(Ljava/lang/Runnable;)V
	aload_3
	areturn
  Labels:
   	l1 = 12 // aload_0

public scala.actors.threadpool.Future take()   throws java.lang.InterruptedException;
  Signature: ()Lscala/actors/threadpool/Future;
  Code:
   Stack=1, Locals=1, Args_size=1
	aload_0
	getfield	Field completionQueue:Lscala/actors/threadpool/BlockingQueue;
	invokeinterface	InterfaceMethod scala/actors/threadpool/BlockingQueue.take:()Ljava/lang/Object;
	checkcast	class scala/actors/threadpool/Future
	areturn
  Labels:
  Exceptions: 
   throws java.lang.InterruptedException
public scala.actors.threadpool.Future poll();
  Signature: ()Lscala/actors/threadpool/Future;
  Code:
   Stack=1, Locals=1, Args_size=1
	aload_0
	getfield	Field completionQueue:Lscala/actors/threadpool/BlockingQueue;
	invokeinterface	InterfaceMethod scala/actors/threadpool/BlockingQueue.poll:()Ljava/lang/Object;
	checkcast	class scala/actors/threadpool/Future
	areturn
  Labels:

public scala.actors.threadpool.Future poll(long, scala.actors.threadpool.TimeUnit)   throws java.lang.InterruptedException;
  Signature: (JLscala/actors/threadpool/TimeUnit;)Lscala/actors/threadpool/Future;
  Code:
   Stack=4, Locals=4, Args_size=3
	aload_0
	getfield	Field completionQueue:Lscala/actors/threadpool/BlockingQueue;
	lload_1
	aload_3
	invokeinterface	InterfaceMethod scala/actors/threadpool/BlockingQueue.poll:(JLscala/actors/threadpool/TimeUnit;)Ljava/lang/Object;
	checkcast	class scala/actors/threadpool/Future
	areturn
  Labels:
  Exceptions: 
   throws java.lang.InterruptedException
static scala.actors.threadpool.BlockingQueue access$000(scala.actors.threadpool.ExecutorCompletionService);
  Signature: (Lscala/actors/threadpool/ExecutorCompletionService;)Lscala/actors/threadpool/BlockingQueue;
  Code:
   Stack=1, Locals=1, Args_size=1
	aload_0
	getfield	Field completionQueue:Lscala/actors/threadpool/BlockingQueue;
	areturn
  Labels:

}

