final class scala.actors.threadpool.Executors$PrivilegedCallable extends java.lang.Object implements scala.actors.threadpool.Callable
  InnerClass: 
   final PrivilegedCallable=class scala/actors/threadpool/Executors$PrivilegedCallable of class scala/actors/threadpool/Executors
   class scala/actors/threadpool/Executors$PrivilegedCallable$1
  minor version: 0
  major version: 49
  Constant pool:
Field	scala/actors/threadpool/Executors$PrivilegedCallable.exception:Ljava/lang/Exception;
Field	scala/actors/threadpool/Executors$PrivilegedCallable.task:Lscala/actors/threadpool/Callable;
Field	scala/actors/threadpool/Executors$PrivilegedCallable.result:Ljava/lang/Object;
Method	java/lang/Object."<init>":()V
Method	java/security/AccessController.getContext:()Ljava/security/AccessControlContext;
Field	scala/actors/threadpool/Executors$PrivilegedCallable.acc:Ljava/security/AccessControlContext;
class	scala/actors/threadpool/Executors$PrivilegedCallable$1
Method	scala/actors/threadpool/Executors$PrivilegedCallable$1."<init>":(Lscala/actors/threadpool/Executors$PrivilegedCallable;)V
Method	java/security/AccessController.doPrivileged:(Ljava/security/PrivilegedAction;Ljava/security/AccessControlContext;)Ljava/lang/Object;
class	scala/actors/threadpool/Executors$PrivilegedCallable
class	java/lang/Object
class	scala/actors/threadpool/Callable
Asciz	acc;
Asciz	Ljava/security/AccessControlContext;;
Asciz	task;
Asciz	Lscala/actors/threadpool/Callable;;
Asciz	result;
Asciz	Ljava/lang/Object;;
Asciz	exception;
Asciz	Ljava/lang/Exception;;
Asciz	<init>;
Asciz	(Lscala/actors/threadpool/Callable;)V;
Asciz	Code;
Asciz	call;
Asciz	()Ljava/lang/Object;;
Asciz	Exceptions;
class	java/lang/Exception
Asciz	access$002;
Asciz	PrivilegedCallable;
Asciz	InnerClasses;
Asciz	(Lscala/actors/threadpool/Executors$PrivilegedCallable;Ljava/lang/Object;)Ljava/lang/Object;;
Asciz	access$100;
Asciz	(Lscala/actors/threadpool/Executors$PrivilegedCallable;)Lscala/actors/threadpool/Callable;;
Asciz	access$202;
Asciz	(Lscala/actors/threadpool/Executors$PrivilegedCallable;Ljava/lang/Exception;)Ljava/lang/Exception;;
NameAndType	exception:Ljava/lang/Exception;
NameAndType	task:Lscala/actors/threadpool/Callable;
NameAndType	result:Ljava/lang/Object;
NameAndType	"<init>":()V
class	java/security/AccessController
NameAndType	getContext:()Ljava/security/AccessControlContext;
NameAndType	acc:Ljava/security/AccessControlContext;
Asciz	scala/actors/threadpool/Executors$PrivilegedCallable$1;
Asciz	;
NameAndType	"<init>":(Lscala/actors/threadpool/Executors$PrivilegedCallable;)V
NameAndType	doPrivileged:(Ljava/security/PrivilegedAction;Ljava/security/AccessControlContext;)Ljava/lang/Object;
class	scala/actors/threadpool/Executors
Asciz	scala/actors/threadpool/Executors$PrivilegedCallable;
Asciz	java/lang/Object;
Asciz	scala/actors/threadpool/Callable;
Asciz	java/lang/Exception;
Asciz	()V;
Asciz	java/security/AccessController;
Asciz	getContext;
Asciz	()Ljava/security/AccessControlContext;;
Asciz	(Lscala/actors/threadpool/Executors$PrivilegedCallable;)V;
Asciz	doPrivileged;
Asciz	(Ljava/security/PrivilegedAction;Ljava/security/AccessControlContext;)Ljava/lang/Object;;
Asciz	scala/actors/threadpool/Executors;

{
private final java.security.AccessControlContext acc;
  Signature: Ljava/security/AccessControlContext;

private final scala.actors.threadpool.Callable task;
  Signature: Lscala/actors/threadpool/Callable;

private java.lang.Object result;
  Signature: Ljava/lang/Object;

private java.lang.Exception exception;
  Signature: Ljava/lang/Exception;

scala.actors.threadpool.Executors$PrivilegedCallable(scala.actors.threadpool.Callable);
  Signature: (Lscala/actors/threadpool/Callable;)V
  Code:
   Stack=2, Locals=2, Args_size=2
	aload_0
	invokespecial	Method java/lang/Object."<init>":()V
	aload_0
	aload_1
	putfield	Field task:Lscala/actors/threadpool/Callable;
	aload_0
	invokestatic	Method java/security/AccessController.getContext:()Ljava/security/AccessControlContext;
	putfield	Field acc:Ljava/security/AccessControlContext;
	return
  Labels:

public java.lang.Object call()   throws java.lang.Exception;
  Signature: ()Ljava/lang/Object;
  Code:
   Stack=3, Locals=1, Args_size=1
	new	class scala/actors/threadpool/Executors$PrivilegedCallable$1
	dup
	aload_0
	invokespecial	Method scala/actors/threadpool/Executors$PrivilegedCallable$1."<init>":(Lscala/actors/threadpool/Executors$PrivilegedCallable;)V
	aload_0
	getfield	Field acc:Ljava/security/AccessControlContext;
	invokestatic	Method java/security/AccessController.doPrivileged:(Ljava/security/PrivilegedAction;Ljava/security/AccessControlContext;)Ljava/lang/Object;
	pop
	aload_0
	getfield	Field exception:Ljava/lang/Exception;
	ifnull	l1 // aload_0
	aload_0
	getfield	Field exception:Ljava/lang/Exception;
	athrow
l1	aload_0
	getfield	Field result:Ljava/lang/Object;
	areturn
  Labels:
   	l1 = 28 // aload_0
  Exceptions: 
   throws java.lang.Exception
static java.lang.Object access$002(scala.actors.threadpool.Executors$PrivilegedCallable, java.lang.Object);
  Signature: (Lscala/actors/threadpool/Executors$PrivilegedCallable;Ljava/lang/Object;)Ljava/lang/Object;
  Code:
   Stack=3, Locals=2, Args_size=2
	aload_0
	aload_1
	dup_x1
	putfield	Field result:Ljava/lang/Object;
	areturn
  Labels:

static scala.actors.threadpool.Callable access$100(scala.actors.threadpool.Executors$PrivilegedCallable);
  Signature: (Lscala/actors/threadpool/Executors$PrivilegedCallable;)Lscala/actors/threadpool/Callable;
  Code:
   Stack=1, Locals=1, Args_size=1
	aload_0
	getfield	Field task:Lscala/actors/threadpool/Callable;
	areturn
  Labels:

static java.lang.Exception access$202(scala.actors.threadpool.Executors$PrivilegedCallable, java.lang.Exception);
  Signature: (Lscala/actors/threadpool/Executors$PrivilegedCallable;Ljava/lang/Exception;)Ljava/lang/Exception;
  Code:
   Stack=3, Locals=2, Args_size=2
	aload_0
	aload_1
	dup_x1
	putfield	Field exception:Ljava/lang/Exception;
	areturn
  Labels:

}

