class scala.actors.threadpool.Executors$PrivilegedCallable$1 extends java.lang.Object implements java.security.PrivilegedAction
  EnclosingMethod: length = 0x4
   00 0C 00 16 
  InnerClass: 
   final #13= #12 of #34; //PrivilegedCallable=class scala/actors/threadpool/Executors$PrivilegedCallable of class scala/actors/threadpool/Executors
   #8; //class scala/actors/threadpool/Executors$PrivilegedCallable$1
  minor version: 0
  major version: 49
  Constant pool:
const #1 = Field	#8.#23;	//  scala/actors/threadpool/Executors$PrivilegedCallable$1.this$0:Lscala/actors/threadpool/Executors$PrivilegedCallable;
const #2 = Method	#9.#24;	//  java/lang/Object."<init>":()V
const #3 = Method	#12.#25;	//  scala/actors/threadpool/Executors$PrivilegedCallable.access$100:(Lscala/actors/threadpool/Executors$PrivilegedCallable;)Lscala/actors/threadpool/Callable;
const #4 = InterfaceMethod	#26.#22;	//  scala/actors/threadpool/Callable.call:()Ljava/lang/Object;
const #5 = Method	#12.#27;	//  scala/actors/threadpool/Executors$PrivilegedCallable.access$002:(Lscala/actors/threadpool/Executors$PrivilegedCallable;Ljava/lang/Object;)Ljava/lang/Object;
const #6 = class	#28;	//  java/lang/Exception
const #7 = Method	#12.#29;	//  scala/actors/threadpool/Executors$PrivilegedCallable.access$202:(Lscala/actors/threadpool/Executors$PrivilegedCallable;Ljava/lang/Exception;)Ljava/lang/Exception;
const #8 = class	#30;	//  scala/actors/threadpool/Executors$PrivilegedCallable$1
const #9 = class	#32;	//  java/lang/Object
const #10 = class	#33;	//  java/security/PrivilegedAction
const #11 = Asciz	this$0;
const #12 = class	#35;	//  scala/actors/threadpool/Executors$PrivilegedCallable
const #13 = Asciz	PrivilegedCallable;
const #14 = Asciz	InnerClasses;
const #15 = Asciz	Lscala/actors/threadpool/Executors$PrivilegedCallable;;
const #16 = Asciz	<init>;
const #17 = Asciz	(Lscala/actors/threadpool/Executors$PrivilegedCallable;)V;
const #18 = Asciz	Code;
const #19 = Asciz	run;
const #20 = Asciz	()Ljava/lang/Object;;
const #21 = Asciz	EnclosingMethod;
const #22 = NameAndType	#36:#20;//  call:()Ljava/lang/Object;
const #23 = NameAndType	#11:#15;//  this$0:Lscala/actors/threadpool/Executors$PrivilegedCallable;
const #24 = NameAndType	#16:#37;//  "<init>":()V
const #25 = NameAndType	#38:#39;//  access$100:(Lscala/actors/threadpool/Executors$PrivilegedCallable;)Lscala/actors/threadpool/Callable;
const #26 = class	#40;	//  scala/actors/threadpool/Callable
const #27 = NameAndType	#41:#42;//  access$002:(Lscala/actors/threadpool/Executors$PrivilegedCallable;Ljava/lang/Object;)Ljava/lang/Object;
const #28 = Asciz	java/lang/Exception;
const #29 = NameAndType	#43:#44;//  access$202:(Lscala/actors/threadpool/Executors$PrivilegedCallable;Ljava/lang/Exception;)Ljava/lang/Exception;
const #30 = Asciz	scala/actors/threadpool/Executors$PrivilegedCallable$1;
const #31 = Asciz	;
const #32 = Asciz	java/lang/Object;
const #33 = Asciz	java/security/PrivilegedAction;
const #34 = class	#45;	//  scala/actors/threadpool/Executors
const #35 = Asciz	scala/actors/threadpool/Executors$PrivilegedCallable;
const #36 = Asciz	call;
const #37 = Asciz	()V;
const #38 = Asciz	access$100;
const #39 = Asciz	(Lscala/actors/threadpool/Executors$PrivilegedCallable;)Lscala/actors/threadpool/Callable;;
const #40 = Asciz	scala/actors/threadpool/Callable;
const #41 = Asciz	access$002;
const #42 = Asciz	(Lscala/actors/threadpool/Executors$PrivilegedCallable;Ljava/lang/Object;)Ljava/lang/Object;;
const #43 = Asciz	access$202;
const #44 = Asciz	(Lscala/actors/threadpool/Executors$PrivilegedCallable;Ljava/lang/Exception;)Ljava/lang/Exception;;
const #45 = Asciz	scala/actors/threadpool/Executors;

{
final scala.actors.threadpool.Executors$PrivilegedCallable this$0;

scala.actors.threadpool.Executors$PrivilegedCallable$1(scala.actors.threadpool.Executors$PrivilegedCallable);
  Code:
   Stack=2, Locals=2, Args_size=2
   0:	aload_0
   1:	aload_1
   2:	putfield	#1; //Field this$0:Lscala/actors/threadpool/Executors$PrivilegedCallable;
   5:	aload_0
   6:	invokespecial	#2; //Method java/lang/Object."<init>":()V
   9:	return

public java.lang.Object run();
  Code:
   Stack=2, Locals=2, Args_size=1
   0:	aload_0
   1:	getfield	#1; //Field this$0:Lscala/actors/threadpool/Executors$PrivilegedCallable;
   4:	aload_0
   5:	getfield	#1; //Field this$0:Lscala/actors/threadpool/Executors$PrivilegedCallable;
   8:	invokestatic	#3; //Method scala/actors/threadpool/Executors$PrivilegedCallable.access$100:(Lscala/actors/threadpool/Executors$PrivilegedCallable;)Lscala/actors/threadpool/Callable;
   11:	invokeinterface	#4,  1; //InterfaceMethod scala/actors/threadpool/Callable.call:()Ljava/lang/Object;
   16:	invokestatic	#5; //Method scala/actors/threadpool/Executors$PrivilegedCallable.access$002:(Lscala/actors/threadpool/Executors$PrivilegedCallable;Ljava/lang/Object;)Ljava/lang/Object;
   19:	pop
   20:	goto	33
   23:	astore_1
   24:	aload_0
   25:	getfield	#1; //Field this$0:Lscala/actors/threadpool/Executors$PrivilegedCallable;
   28:	aload_1
   29:	invokestatic	#7; //Method scala/actors/threadpool/Executors$PrivilegedCallable.access$202:(Lscala/actors/threadpool/Executors$PrivilegedCallable;Ljava/lang/Exception;)Ljava/lang/Exception;
   32:	pop
   33:	aconst_null
   34:	areturn
  Exception table:
   from   to  target type
     0    20    23   Class java/lang/Exception


}

