class scala.actors.threadpool.ExecutorCompletionService$QueueingFuture extends scala.actors.threadpool.FutureTask
  InnerClass: 
   #25= #6 of #20; //QueueingFuture=class scala/actors/threadpool/ExecutorCompletionService$QueueingFuture of class scala/actors/threadpool/ExecutorCompletionService
  minor version: 0
  major version: 49
  Constant pool:
const #1 = Field	#6.#17;	//  scala/actors/threadpool/ExecutorCompletionService$QueueingFuture.this$0:Lscala/actors/threadpool/ExecutorCompletionService;
const #2 = Method	#7.#18;	//  scala/actors/threadpool/FutureTask."<init>":(Ljava/lang/Runnable;Ljava/lang/Object;)V
const #3 = Field	#6.#19;	//  scala/actors/threadpool/ExecutorCompletionService$QueueingFuture.task:Lscala/actors/threadpool/Future;
const #4 = Method	#20.#21;	//  scala/actors/threadpool/ExecutorCompletionService.access$000:(Lscala/actors/threadpool/ExecutorCompletionService;)Lscala/actors/threadpool/BlockingQueue;
const #5 = InterfaceMethod	#22.#23;	//  scala/actors/threadpool/BlockingQueue.add:(Ljava/lang/Object;)Z
const #6 = class	#24;	//  scala/actors/threadpool/ExecutorCompletionService$QueueingFuture
const #7 = class	#27;	//  scala/actors/threadpool/FutureTask
const #8 = Asciz	task;
const #9 = Asciz	Lscala/actors/threadpool/Future;;
const #10 = Asciz	this$0;
const #11 = Asciz	Lscala/actors/threadpool/ExecutorCompletionService;;
const #12 = Asciz	<init>;
const #13 = Asciz	(Lscala/actors/threadpool/ExecutorCompletionService;Lscala/actors/threadpool/RunnableFuture;)V;
const #14 = Asciz	Code;
const #15 = Asciz	done;
const #16 = Asciz	()V;
const #17 = NameAndType	#10:#11;//  this$0:Lscala/actors/threadpool/ExecutorCompletionService;
const #18 = NameAndType	#12:#28;//  "<init>":(Ljava/lang/Runnable;Ljava/lang/Object;)V
const #19 = NameAndType	#8:#9;//  task:Lscala/actors/threadpool/Future;
const #20 = class	#29;	//  scala/actors/threadpool/ExecutorCompletionService
const #21 = NameAndType	#30:#31;//  access$000:(Lscala/actors/threadpool/ExecutorCompletionService;)Lscala/actors/threadpool/BlockingQueue;
const #22 = class	#32;	//  scala/actors/threadpool/BlockingQueue
const #23 = NameAndType	#33:#34;//  add:(Ljava/lang/Object;)Z
const #24 = Asciz	scala/actors/threadpool/ExecutorCompletionService$QueueingFuture;
const #25 = Asciz	QueueingFuture;
const #26 = Asciz	InnerClasses;
const #27 = Asciz	scala/actors/threadpool/FutureTask;
const #28 = Asciz	(Ljava/lang/Runnable;Ljava/lang/Object;)V;
const #29 = Asciz	scala/actors/threadpool/ExecutorCompletionService;
const #30 = Asciz	access$000;
const #31 = Asciz	(Lscala/actors/threadpool/ExecutorCompletionService;)Lscala/actors/threadpool/BlockingQueue;;
const #32 = Asciz	scala/actors/threadpool/BlockingQueue;
const #33 = Asciz	add;
const #34 = Asciz	(Ljava/lang/Object;)Z;

{
final scala.actors.threadpool.ExecutorCompletionService this$0;

scala.actors.threadpool.ExecutorCompletionService$QueueingFuture(scala.actors.threadpool.ExecutorCompletionService, scala.actors.threadpool.RunnableFuture);
  Code:
   Stack=3, Locals=3, Args_size=3
   0:	aload_0
   1:	aload_1
   2:	putfield	#1; //Field this$0:Lscala/actors/threadpool/ExecutorCompletionService;
   5:	aload_0
   6:	aload_2
   7:	aconst_null
   8:	invokespecial	#2; //Method scala/actors/threadpool/FutureTask."<init>":(Ljava/lang/Runnable;Ljava/lang/Object;)V
   11:	aload_0
   12:	aload_2
   13:	putfield	#3; //Field task:Lscala/actors/threadpool/Future;
   16:	return

protected void done();
  Code:
   Stack=2, Locals=1, Args_size=1
   0:	aload_0
   1:	getfield	#1; //Field this$0:Lscala/actors/threadpool/ExecutorCompletionService;
   4:	invokestatic	#4; //Method scala/actors/threadpool/ExecutorCompletionService.access$000:(Lscala/actors/threadpool/ExecutorCompletionService;)Lscala/actors/threadpool/BlockingQueue;
   7:	aload_0
   8:	getfield	#3; //Field task:Lscala/actors/threadpool/Future;
   11:	invokeinterface	#5,  2; //InterfaceMethod scala/actors/threadpool/BlockingQueue.add:(Ljava/lang/Object;)Z
   16:	pop
   17:	return

}

