class scala.actors.threadpool.Executors$2 extends java.lang.Object implements scala.actors.threadpool.Callable
  EnclosingMethod: length = 0x4
   00 11 00 12 
  InnerClass: 
   #4; //class scala/actors/threadpool/Executors$2
  minor version: 0
  major version: 49
  Constant pool:
const #1 = Field	#4.#19;	//  scala/actors/threadpool/Executors$2.val$action:Ljava/security/PrivilegedExceptionAction;
const #2 = Method	#5.#20;	//  java/lang/Object."<init>":()V
const #3 = InterfaceMethod	#21.#22;	//  java/security/PrivilegedExceptionAction.run:()Ljava/lang/Object;
const #4 = class	#23;	//  scala/actors/threadpool/Executors$2
const #5 = class	#26;	//  java/lang/Object
const #6 = class	#27;	//  scala/actors/threadpool/Callable
const #7 = Asciz	val$action;
const #8 = Asciz	Ljava/security/PrivilegedExceptionAction;;
const #9 = Asciz	<init>;
const #10 = Asciz	(Ljava/security/PrivilegedExceptionAction;)V;
const #11 = Asciz	Code;
const #12 = Asciz	Exceptions;
const #13 = class	#28;	//  java/lang/Exception
const #14 = Asciz	call;
const #15 = Asciz	()Ljava/lang/Object;;
const #16 = Asciz	EnclosingMethod;
const #17 = class	#29;	//  scala/actors/threadpool/Executors
const #18 = NameAndType	#30:#31;//  callable:(Ljava/security/PrivilegedExceptionAction;)Lscala/actors/threadpool/Callable;
const #19 = NameAndType	#7:#8;//  val$action:Ljava/security/PrivilegedExceptionAction;
const #20 = NameAndType	#9:#32;//  "<init>":()V
const #21 = class	#33;	//  java/security/PrivilegedExceptionAction
const #22 = NameAndType	#34:#15;//  run:()Ljava/lang/Object;
const #23 = Asciz	scala/actors/threadpool/Executors$2;
const #24 = Asciz	;
const #25 = Asciz	InnerClasses;
const #26 = Asciz	java/lang/Object;
const #27 = Asciz	scala/actors/threadpool/Callable;
const #28 = Asciz	java/lang/Exception;
const #29 = Asciz	scala/actors/threadpool/Executors;
const #30 = Asciz	callable;
const #31 = Asciz	(Ljava/security/PrivilegedExceptionAction;)Lscala/actors/threadpool/Callable;;
const #32 = Asciz	()V;
const #33 = Asciz	java/security/PrivilegedExceptionAction;
const #34 = Asciz	run;

{
final java.security.PrivilegedExceptionAction val$action;

scala.actors.threadpool.Executors$2(java.security.PrivilegedExceptionAction)   throws java.lang.Exception;
  Code:
   Stack=2, Locals=2, Args_size=2
   0:	aload_0
   1:	aload_1
   2:	putfield	#1; //Field val$action:Ljava/security/PrivilegedExceptionAction;
   5:	aload_0
   6:	invokespecial	#2; //Method java/lang/Object."<init>":()V
   9:	return
  Exceptions: 
   throws java.lang.Exception
public java.lang.Object call()   throws java.lang.Exception;
  Code:
   Stack=1, Locals=1, Args_size=1
   0:	aload_0
   1:	getfield	#1; //Field val$action:Ljava/security/PrivilegedExceptionAction;
   4:	invokeinterface	#3,  1; //InterfaceMethod java/security/PrivilegedExceptionAction.run:()Ljava/lang/Object;
   9:	areturn
  Exceptions: 
   throws java.lang.Exception
}

