class scala.actors.threadpool.ExecutorCompletionService$QueueingFuture extends scala.actors.threadpool.FutureTask
  InnerClass: 
   QueueingFuture=class scala/actors/threadpool/ExecutorCompletionService$QueueingFuture of class scala/actors/threadpool/ExecutorCompletionService
  minor version: 0
  major version: 49
  Constant pool:
Field	scala/actors/threadpool/ExecutorCompletionService$QueueingFuture.this$0:Lscala/actors/threadpool/ExecutorCompletionService;
Method	scala/actors/threadpool/FutureTask."<init>":(Ljava/lang/Runnable;Ljava/lang/Object;)V
Field	scala/actors/threadpool/ExecutorCompletionService$QueueingFuture.task:Lscala/actors/threadpool/Future;
Method	scala/actors/threadpool/ExecutorCompletionService.access$000:(Lscala/actors/threadpool/ExecutorCompletionService;)Lscala/actors/threadpool/BlockingQueue;
InterfaceMethod	scala/actors/threadpool/BlockingQueue.add:(Ljava/lang/Object;)Z
class	scala/actors/threadpool/ExecutorCompletionService$QueueingFuture
class	scala/actors/threadpool/FutureTask
Asciz	task;
Asciz	Lscala/actors/threadpool/Future;;
Asciz	this$0;
Asciz	Lscala/actors/threadpool/ExecutorCompletionService;;
Asciz	<init>;
Asciz	(Lscala/actors/threadpool/ExecutorCompletionService;Lscala/actors/threadpool/RunnableFuture;)V;
Asciz	Code;
Asciz	done;
Asciz	()V;
NameAndType	this$0:Lscala/actors/threadpool/ExecutorCompletionService;
NameAndType	"<init>":(Ljava/lang/Runnable;Ljava/lang/Object;)V
NameAndType	task:Lscala/actors/threadpool/Future;
class	scala/actors/threadpool/ExecutorCompletionService
NameAndType	access$000:(Lscala/actors/threadpool/ExecutorCompletionService;)Lscala/actors/threadpool/BlockingQueue;
class	scala/actors/threadpool/BlockingQueue
NameAndType	add:(Ljava/lang/Object;)Z
Asciz	scala/actors/threadpool/ExecutorCompletionService$QueueingFuture;
Asciz	QueueingFuture;
Asciz	InnerClasses;
Asciz	scala/actors/threadpool/FutureTask;
Asciz	(Ljava/lang/Runnable;Ljava/lang/Object;)V;
Asciz	scala/actors/threadpool/ExecutorCompletionService;
Asciz	access$000;
Asciz	(Lscala/actors/threadpool/ExecutorCompletionService;)Lscala/actors/threadpool/BlockingQueue;;
Asciz	scala/actors/threadpool/BlockingQueue;
Asciz	add;
Asciz	(Ljava/lang/Object;)Z;

{
private final scala.actors.threadpool.Future task;
  Signature: Lscala/actors/threadpool/Future;

final scala.actors.threadpool.ExecutorCompletionService this$0;
  Signature: Lscala/actors/threadpool/ExecutorCompletionService;

scala.actors.threadpool.ExecutorCompletionService$QueueingFuture(scala.actors.threadpool.ExecutorCompletionService, scala.actors.threadpool.RunnableFuture);
  Signature: (Lscala/actors/threadpool/ExecutorCompletionService;Lscala/actors/threadpool/RunnableFuture;)V
  Code:
   Stack=3, Locals=3, Args_size=3
	aload_0
	aload_1
	putfield	Field this$0:Lscala/actors/threadpool/ExecutorCompletionService;
	aload_0
	aload_2
	aconst_null
	invokespecial	Method scala/actors/threadpool/FutureTask."<init>":(Ljava/lang/Runnable;Ljava/lang/Object;)V
	aload_0
	aload_2
	putfield	Field task:Lscala/actors/threadpool/Future;
	return
  Labels:

protected void done();
  Signature: ()V
  Code:
   Stack=2, Locals=1, Args_size=1
	aload_0
	getfield	Field this$0:Lscala/actors/threadpool/ExecutorCompletionService;
	invokestatic	Method scala/actors/threadpool/ExecutorCompletionService.access$000:(Lscala/actors/threadpool/ExecutorCompletionService;)Lscala/actors/threadpool/BlockingQueue;
	aload_0
	getfield	Field task:Lscala/actors/threadpool/Future;
	invokeinterface	InterfaceMethod scala/actors/threadpool/BlockingQueue.add:(Ljava/lang/Object;)Z
	pop
	return
  Labels:

}

