class scala.actors.threadpool.Executors$PrivilegedCallableUsingCurrentClassLoader$1 extends java.lang.Object implements java.security.PrivilegedAction
  EnclosingMethod: length = 0x4
   00 10 00 1A 
  InnerClass: 
   final #17= #16 of #43; //PrivilegedCallableUsingCurrentClassLoader=class scala/actors/threadpool/Executors$PrivilegedCallableUsingCurrentClassLoader of class scala/actors/threadpool/Executors
   #12; //class scala/actors/threadpool/Executors$PrivilegedCallableUsingCurrentClassLoader$1
  minor version: 0
  major version: 49
  Constant pool:
const #1 = Field	#12.#27;	//  scala/actors/threadpool/Executors$PrivilegedCallableUsingCurrentClassLoader$1.this$0:Lscala/actors/threadpool/Executors$PrivilegedCallableUsingCurrentClassLoader;
const #2 = Method	#13.#28;	//  java/lang/Object."<init>":()V
const #3 = Method	#29.#30;	//  java/lang/Thread.currentThread:()Ljava/lang/Thread;
const #4 = Method	#29.#31;	//  java/lang/Thread.getContextClassLoader:()Ljava/lang/ClassLoader;
const #5 = Method	#16.#32;	//  scala/actors/threadpool/Executors$PrivilegedCallableUsingCurrentClassLoader.access$300:(Lscala/actors/threadpool/Executors$PrivilegedCallableUsingCurrentClassLoader;)Ljava/lang/ClassLoader;
const #6 = Method	#29.#33;	//  java/lang/Thread.setContextClassLoader:(Ljava/lang/ClassLoader;)V
const #7 = Method	#16.#34;	//  scala/actors/threadpool/Executors$PrivilegedCallableUsingCurrentClassLoader.access$500:(Lscala/actors/threadpool/Executors$PrivilegedCallableUsingCurrentClassLoader;)Lscala/actors/threadpool/Callable;
const #8 = InterfaceMethod	#35.#26;	//  scala/actors/threadpool/Callable.call:()Ljava/lang/Object;
const #9 = Method	#16.#36;	//  scala/actors/threadpool/Executors$PrivilegedCallableUsingCurrentClassLoader.access$402:(Lscala/actors/threadpool/Executors$PrivilegedCallableUsingCurrentClassLoader;Ljava/lang/Object;)Ljava/lang/Object;
const #10 = class	#37;	//  java/lang/Exception
const #11 = Method	#16.#38;	//  scala/actors/threadpool/Executors$PrivilegedCallableUsingCurrentClassLoader.access$602:(Lscala/actors/threadpool/Executors$PrivilegedCallableUsingCurrentClassLoader;Ljava/lang/Exception;)Ljava/lang/Exception;
const #12 = class	#39;	//  scala/actors/threadpool/Executors$PrivilegedCallableUsingCurrentClassLoader$1
const #13 = class	#41;	//  java/lang/Object
const #14 = class	#42;	//  java/security/PrivilegedAction
const #15 = Asciz	this$0;
const #16 = class	#44;	//  scala/actors/threadpool/Executors$PrivilegedCallableUsingCurrentClassLoader
const #17 = Asciz	PrivilegedCallableUsingCurrentClassLoader;
const #18 = Asciz	InnerClasses;
const #19 = Asciz	Lscala/actors/threadpool/Executors$PrivilegedCallableUsingCurrentClassLoader;;
const #20 = Asciz	<init>;
const #21 = Asciz	(Lscala/actors/threadpool/Executors$PrivilegedCallableUsingCurrentClassLoader;)V;
const #22 = Asciz	Code;
const #23 = Asciz	run;
const #24 = Asciz	()Ljava/lang/Object;;
const #25 = Asciz	EnclosingMethod;
const #26 = NameAndType	#45:#24;//  call:()Ljava/lang/Object;
const #27 = NameAndType	#15:#19;//  this$0:Lscala/actors/threadpool/Executors$PrivilegedCallableUsingCurrentClassLoader;
const #28 = NameAndType	#20:#46;//  "<init>":()V
const #29 = class	#47;	//  java/lang/Thread
const #30 = NameAndType	#48:#49;//  currentThread:()Ljava/lang/Thread;
const #31 = NameAndType	#50:#51;//  getContextClassLoader:()Ljava/lang/ClassLoader;
const #32 = NameAndType	#52:#53;//  access$300:(Lscala/actors/threadpool/Executors$PrivilegedCallableUsingCurrentClassLoader;)Ljava/lang/ClassLoader;
const #33 = NameAndType	#54:#55;//  setContextClassLoader:(Ljava/lang/ClassLoader;)V
const #34 = NameAndType	#56:#57;//  access$500:(Lscala/actors/threadpool/Executors$PrivilegedCallableUsingCurrentClassLoader;)Lscala/actors/threadpool/Callable;
const #35 = class	#58;	//  scala/actors/threadpool/Callable
const #36 = NameAndType	#59:#60;//  access$402:(Lscala/actors/threadpool/Executors$PrivilegedCallableUsingCurrentClassLoader;Ljava/lang/Object;)Ljava/lang/Object;
const #37 = Asciz	java/lang/Exception;
const #38 = NameAndType	#61:#62;//  access$602:(Lscala/actors/threadpool/Executors$PrivilegedCallableUsingCurrentClassLoader;Ljava/lang/Exception;)Ljava/lang/Exception;
const #39 = Asciz	scala/actors/threadpool/Executors$PrivilegedCallableUsingCurrentClassLoader$1;
const #40 = Asciz	;
const #41 = Asciz	java/lang/Object;
const #42 = Asciz	java/security/PrivilegedAction;
const #43 = class	#63;	//  scala/actors/threadpool/Executors
const #44 = Asciz	scala/actors/threadpool/Executors$PrivilegedCallableUsingCurrentClassLoader;
const #45 = Asciz	call;
const #46 = Asciz	()V;
const #47 = Asciz	java/lang/Thread;
const #48 = Asciz	currentThread;
const #49 = Asciz	()Ljava/lang/Thread;;
const #50 = Asciz	getContextClassLoader;
const #51 = Asciz	()Ljava/lang/ClassLoader;;
const #52 = Asciz	access$300;
const #53 = Asciz	(Lscala/actors/threadpool/Executors$PrivilegedCallableUsingCurrentClassLoader;)Ljava/lang/ClassLoader;;
const #54 = Asciz	setContextClassLoader;
const #55 = Asciz	(Ljava/lang/ClassLoader;)V;
const #56 = Asciz	access$500;
const #57 = Asciz	(Lscala/actors/threadpool/Executors$PrivilegedCallableUsingCurrentClassLoader;)Lscala/actors/threadpool/Callable;;
const #58 = Asciz	scala/actors/threadpool/Callable;
const #59 = Asciz	access$402;
const #60 = Asciz	(Lscala/actors/threadpool/Executors$PrivilegedCallableUsingCurrentClassLoader;Ljava/lang/Object;)Ljava/lang/Object;;
const #61 = Asciz	access$602;
const #62 = Asciz	(Lscala/actors/threadpool/Executors$PrivilegedCallableUsingCurrentClassLoader;Ljava/lang/Exception;)Ljava/lang/Exception;;
const #63 = Asciz	scala/actors/threadpool/Executors;

{
final scala.actors.threadpool.Executors$PrivilegedCallableUsingCurrentClassLoader this$0;

scala.actors.threadpool.Executors$PrivilegedCallableUsingCurrentClassLoader$1(scala.actors.threadpool.Executors$PrivilegedCallableUsingCurrentClassLoader);
  Code:
   Stack=2, Locals=2, Args_size=2
   0:	aload_0
   1:	aload_1
   2:	putfield	#1; //Field this$0:Lscala/actors/threadpool/Executors$PrivilegedCallableUsingCurrentClassLoader;
   5:	aload_0
   6:	invokespecial	#2; //Method java/lang/Object."<init>":()V
   9:	return

public java.lang.Object run();
  Code:
   Stack=2, Locals=5, Args_size=1
   0:	aconst_null
   1:	astore_1
   2:	invokestatic	#3; //Method java/lang/Thread.currentThread:()Ljava/lang/Thread;
   5:	astore_2
   6:	aload_2
   7:	invokevirtual	#4; //Method java/lang/Thread.getContextClassLoader:()Ljava/lang/ClassLoader;
   10:	astore_3
   11:	aload_0
   12:	getfield	#1; //Field this$0:Lscala/actors/threadpool/Executors$PrivilegedCallableUsingCurrentClassLoader;
   15:	invokestatic	#5; //Method scala/actors/threadpool/Executors$PrivilegedCallableUsingCurrentClassLoader.access$300:(Lscala/actors/threadpool/Executors$PrivilegedCallableUsingCurrentClassLoader;)Ljava/lang/ClassLoader;
   18:	aload_3
   19:	if_acmpeq	35
   22:	aload_2
   23:	aload_0
   24:	getfield	#1; //Field this$0:Lscala/actors/threadpool/Executors$PrivilegedCallableUsingCurrentClassLoader;
   27:	invokestatic	#5; //Method scala/actors/threadpool/Executors$PrivilegedCallableUsingCurrentClassLoader.access$300:(Lscala/actors/threadpool/Executors$PrivilegedCallableUsingCurrentClassLoader;)Ljava/lang/ClassLoader;
   30:	invokevirtual	#6; //Method java/lang/Thread.setContextClassLoader:(Ljava/lang/ClassLoader;)V
   33:	aload_3
   34:	astore_1
   35:	aload_0
   36:	getfield	#1; //Field this$0:Lscala/actors/threadpool/Executors$PrivilegedCallableUsingCurrentClassLoader;
   39:	aload_0
   40:	getfield	#1; //Field this$0:Lscala/actors/threadpool/Executors$PrivilegedCallableUsingCurrentClassLoader;
   43:	invokestatic	#7; //Method scala/actors/threadpool/Executors$PrivilegedCallableUsingCurrentClassLoader.access$500:(Lscala/actors/threadpool/Executors$PrivilegedCallableUsingCurrentClassLoader;)Lscala/actors/threadpool/Callable;
   46:	invokeinterface	#8,  1; //InterfaceMethod scala/actors/threadpool/Callable.call:()Ljava/lang/Object;
   51:	invokestatic	#9; //Method scala/actors/threadpool/Executors$PrivilegedCallableUsingCurrentClassLoader.access$402:(Lscala/actors/threadpool/Executors$PrivilegedCallableUsingCurrentClassLoader;Ljava/lang/Object;)Ljava/lang/Object;
   54:	pop
   55:	aload_1
   56:	ifnull	103
   59:	aload_2
   60:	aload_1
   61:	invokevirtual	#6; //Method java/lang/Thread.setContextClassLoader:(Ljava/lang/ClassLoader;)V
   64:	goto	103
   67:	astore_3
   68:	aload_0
   69:	getfield	#1; //Field this$0:Lscala/actors/threadpool/Executors$PrivilegedCallableUsingCurrentClassLoader;
   72:	aload_3
   73:	invokestatic	#11; //Method scala/actors/threadpool/Executors$PrivilegedCallableUsingCurrentClassLoader.access$602:(Lscala/actors/threadpool/Executors$PrivilegedCallableUsingCurrentClassLoader;Ljava/lang/Exception;)Ljava/lang/Exception;
   76:	pop
   77:	aload_1
   78:	ifnull	103
   81:	aload_2
   82:	aload_1
   83:	invokevirtual	#6; //Method java/lang/Thread.setContextClassLoader:(Ljava/lang/ClassLoader;)V
   86:	goto	103
   89:	astore	4
   91:	aload_1
   92:	ifnull	100
   95:	aload_2
   96:	aload_1
   97:	invokevirtual	#6; //Method java/lang/Thread.setContextClassLoader:(Ljava/lang/ClassLoader;)V
   100:	aload	4
   102:	athrow
   103:	aconst_null
   104:	areturn
  Exception table:
   from   to  target type
     6    55    67   Class java/lang/Exception

     6    55    89   any
    67    77    89   any
    89    91    89   any

}

