public class scala.actors.threadpool.Executors extends java.lang.Object
  InnerClass: 
   #36= #7 of #34; //FinalizableDelegatedExecutorService=class scala/actors/threadpool/Executors$FinalizableDelegatedExecutorService of class scala/actors/threadpool/Executors
   #38= #17 of #34; //DelegatedExecutorService=class scala/actors/threadpool/Executors$DelegatedExecutorService of class scala/actors/threadpool/Executors
   #39= #21 of #34; //PrivilegedThreadFactory=class scala/actors/threadpool/Executors$PrivilegedThreadFactory of class scala/actors/threadpool/Executors
   #40= #19 of #34; //DefaultThreadFactory=class scala/actors/threadpool/Executors$DefaultThreadFactory of class scala/actors/threadpool/Executors
   final #41= #31 of #34; //PrivilegedCallableUsingCurrentClassLoader=class scala/actors/threadpool/Executors$PrivilegedCallableUsingCurrentClassLoader of class scala/actors/threadpool/Executors
   final #42= #29 of #34; //PrivilegedCallable=class scala/actors/threadpool/Executors$PrivilegedCallable of class scala/actors/threadpool/Executors
   final #43= #23 of #34; //RunnableAdapter=class scala/actors/threadpool/Executors$RunnableAdapter of class scala/actors/threadpool/Executors
   #25; //class scala/actors/threadpool/Executors$1
   #27; //class scala/actors/threadpool/Executors$2
  minor version: 0
  major version: 49
  Constant pool:
const #1 = class	#67;	//  scala/actors/threadpool/ThreadPoolExecutor
const #2 = Field	#68.#69;	//  scala/actors/threadpool/TimeUnit.MILLISECONDS:Lscala/actors/threadpool/TimeUnit;
const #3 = class	#70;	//  scala/actors/threadpool/LinkedBlockingQueue
const #4 = Method	#3.#71;	//  scala/actors/threadpool/LinkedBlockingQueue."<init>":()V
const #5 = Method	#1.#72;	//  scala/actors/threadpool/ThreadPoolExecutor."<init>":(IIJLscala/actors/threadpool/TimeUnit;Lscala/actors/threadpool/BlockingQueue;)V
const #6 = Method	#1.#73;	//  scala/actors/threadpool/ThreadPoolExecutor."<init>":(IIJLscala/actors/threadpool/TimeUnit;Lscala/actors/threadpool/BlockingQueue;Lscala/actors/threadpool/ThreadFactory;)V
const #7 = class	#74;	//  scala/actors/threadpool/Executors$FinalizableDelegatedExecutorService
const #8 = Method	#7.#75;	//  scala/actors/threadpool/Executors$FinalizableDelegatedExecutorService."<init>":(Lscala/actors/threadpool/ExecutorService;)V
const #9 = int	2147483647;
const #10 = long	60l;
const #12 = Field	#68.#76;	//  scala/actors/threadpool/TimeUnit.SECONDS:Lscala/actors/threadpool/TimeUnit;
const #13 = class	#77;	//  scala/actors/threadpool/SynchronousQueue
const #14 = Method	#13.#71;	//  scala/actors/threadpool/SynchronousQueue."<init>":()V
const #15 = class	#78;	//  java/lang/NullPointerException
const #16 = Method	#15.#71;	//  java/lang/NullPointerException."<init>":()V
const #17 = class	#79;	//  scala/actors/threadpool/Executors$DelegatedExecutorService
const #18 = Method	#17.#75;	//  scala/actors/threadpool/Executors$DelegatedExecutorService."<init>":(Lscala/actors/threadpool/ExecutorService;)V
const #19 = class	#80;	//  scala/actors/threadpool/Executors$DefaultThreadFactory
const #20 = Method	#19.#71;	//  scala/actors/threadpool/Executors$DefaultThreadFactory."<init>":()V
const #21 = class	#81;	//  scala/actors/threadpool/Executors$PrivilegedThreadFactory
const #22 = Method	#21.#71;	//  scala/actors/threadpool/Executors$PrivilegedThreadFactory."<init>":()V
const #23 = class	#82;	//  scala/actors/threadpool/Executors$RunnableAdapter
const #24 = Method	#23.#83;	//  scala/actors/threadpool/Executors$RunnableAdapter."<init>":(Ljava/lang/Runnable;Ljava/lang/Object;)V
const #25 = class	#84;	//  scala/actors/threadpool/Executors$1
const #26 = Method	#25.#86;	//  scala/actors/threadpool/Executors$1."<init>":(Ljava/security/PrivilegedAction;)V
const #27 = class	#87;	//  scala/actors/threadpool/Executors$2
const #28 = Method	#27.#88;	//  scala/actors/threadpool/Executors$2."<init>":(Ljava/security/PrivilegedExceptionAction;)V
const #29 = class	#89;	//  scala/actors/threadpool/Executors$PrivilegedCallable
const #30 = Method	#29.#90;	//  scala/actors/threadpool/Executors$PrivilegedCallable."<init>":(Lscala/actors/threadpool/Callable;)V
const #31 = class	#91;	//  scala/actors/threadpool/Executors$PrivilegedCallableUsingCurrentClassLoader
const #32 = Method	#31.#90;	//  scala/actors/threadpool/Executors$PrivilegedCallableUsingCurrentClassLoader."<init>":(Lscala/actors/threadpool/Callable;)V
const #33 = Method	#35.#71;	//  java/lang/Object."<init>":()V
const #34 = class	#92;	//  scala/actors/threadpool/Executors
const #35 = class	#93;	//  java/lang/Object
const #36 = Asciz	FinalizableDelegatedExecutorService;
const #37 = Asciz	InnerClasses;
const #38 = Asciz	DelegatedExecutorService;
const #39 = Asciz	PrivilegedThreadFactory;
const #40 = Asciz	DefaultThreadFactory;
const #41 = Asciz	PrivilegedCallableUsingCurrentClassLoader;
const #42 = Asciz	PrivilegedCallable;
const #43 = Asciz	RunnableAdapter;
const #44 = Asciz	newFixedThreadPool;
const #45 = Asciz	(I)Lscala/actors/threadpool/ExecutorService;;
const #46 = Asciz	Code;
const #47 = Asciz	(ILscala/actors/threadpool/ThreadFactory;)Lscala/actors/threadpool/ExecutorService;;
const #48 = Asciz	newSingleThreadExecutor;
const #49 = Asciz	()Lscala/actors/threadpool/ExecutorService;;
const #50 = Asciz	(Lscala/actors/threadpool/ThreadFactory;)Lscala/actors/threadpool/ExecutorService;;
const #51 = Asciz	newCachedThreadPool;
const #52 = Asciz	unconfigurableExecutorService;
const #53 = Asciz	(Lscala/actors/threadpool/ExecutorService;)Lscala/actors/threadpool/ExecutorService;;
const #54 = Asciz	defaultThreadFactory;
const #55 = Asciz	()Lscala/actors/threadpool/ThreadFactory;;
const #56 = Asciz	privilegedThreadFactory;
const #57 = Asciz	callable;
const #58 = Asciz	(Ljava/lang/Runnable;Ljava/lang/Object;)Lscala/actors/threadpool/Callable;;
const #59 = Asciz	(Ljava/lang/Runnable;)Lscala/actors/threadpool/Callable;;
const #60 = Asciz	(Ljava/security/PrivilegedAction;)Lscala/actors/threadpool/Callable;;
const #61 = Asciz	(Ljava/security/PrivilegedExceptionAction;)Lscala/actors/threadpool/Callable;;
const #62 = Asciz	privilegedCallable;
const #63 = Asciz	(Lscala/actors/threadpool/Callable;)Lscala/actors/threadpool/Callable;;
const #64 = Asciz	privilegedCallableUsingCurrentClassLoader;
const #65 = Asciz	<init>;
const #66 = Asciz	()V;
const #67 = Asciz	scala/actors/threadpool/ThreadPoolExecutor;
const #68 = class	#94;	//  scala/actors/threadpool/TimeUnit
const #69 = NameAndType	#95:#96;//  MILLISECONDS:Lscala/actors/threadpool/TimeUnit;
const #70 = Asciz	scala/actors/threadpool/LinkedBlockingQueue;
const #71 = NameAndType	#65:#66;//  "<init>":()V
const #72 = NameAndType	#65:#97;//  "<init>":(IIJLscala/actors/threadpool/TimeUnit;Lscala/actors/threadpool/BlockingQueue;)V
const #73 = NameAndType	#65:#98;//  "<init>":(IIJLscala/actors/threadpool/TimeUnit;Lscala/actors/threadpool/BlockingQueue;Lscala/actors/threadpool/ThreadFactory;)V
const #74 = Asciz	scala/actors/threadpool/Executors$FinalizableDelegatedExecutorService;
const #75 = NameAndType	#65:#99;//  "<init>":(Lscala/actors/threadpool/ExecutorService;)V
const #76 = NameAndType	#100:#96;//  SECONDS:Lscala/actors/threadpool/TimeUnit;
const #77 = Asciz	scala/actors/threadpool/SynchronousQueue;
const #78 = Asciz	java/lang/NullPointerException;
const #79 = Asciz	scala/actors/threadpool/Executors$DelegatedExecutorService;
const #80 = Asciz	scala/actors/threadpool/Executors$DefaultThreadFactory;
const #81 = Asciz	scala/actors/threadpool/Executors$PrivilegedThreadFactory;
const #82 = Asciz	scala/actors/threadpool/Executors$RunnableAdapter;
const #83 = NameAndType	#65:#101;//  "<init>":(Ljava/lang/Runnable;Ljava/lang/Object;)V
const #84 = Asciz	scala/actors/threadpool/Executors$1;
const #85 = Asciz	;
const #86 = NameAndType	#65:#102;//  "<init>":(Ljava/security/PrivilegedAction;)V
const #87 = Asciz	scala/actors/threadpool/Executors$2;
const #88 = NameAndType	#65:#103;//  "<init>":(Ljava/security/PrivilegedExceptionAction;)V
const #89 = Asciz	scala/actors/threadpool/Executors$PrivilegedCallable;
const #90 = NameAndType	#65:#104;//  "<init>":(Lscala/actors/threadpool/Callable;)V
const #91 = Asciz	scala/actors/threadpool/Executors$PrivilegedCallableUsingCurrentClassLoader;
const #92 = Asciz	scala/actors/threadpool/Executors;
const #93 = Asciz	java/lang/Object;
const #94 = Asciz	scala/actors/threadpool/TimeUnit;
const #95 = Asciz	MILLISECONDS;
const #96 = Asciz	Lscala/actors/threadpool/TimeUnit;;
const #97 = Asciz	(IIJLscala/actors/threadpool/TimeUnit;Lscala/actors/threadpool/BlockingQueue;)V;
const #98 = Asciz	(IIJLscala/actors/threadpool/TimeUnit;Lscala/actors/threadpool/BlockingQueue;Lscala/actors/threadpool/ThreadFactory;)V;
const #99 = Asciz	(Lscala/actors/threadpool/ExecutorService;)V;
const #100 = Asciz	SECONDS;
const #101 = Asciz	(Ljava/lang/Runnable;Ljava/lang/Object;)V;
const #102 = Asciz	(Ljava/security/PrivilegedAction;)V;
const #103 = Asciz	(Ljava/security/PrivilegedExceptionAction;)V;
const #104 = Asciz	(Lscala/actors/threadpool/Callable;)V;

{
public static scala.actors.threadpool.ExecutorService newFixedThreadPool(int);
  Code:
   Stack=9, Locals=1, Args_size=1
   0:	new	#1; //class scala/actors/threadpool/ThreadPoolExecutor
   3:	dup
   4:	iload_0
   5:	iload_0
   6:	lconst_0
   7:	getstatic	#2; //Field scala/actors/threadpool/TimeUnit.MILLISECONDS:Lscala/actors/threadpool/TimeUnit;
   10:	new	#3; //class scala/actors/threadpool/LinkedBlockingQueue
   13:	dup
   14:	invokespecial	#4; //Method scala/actors/threadpool/LinkedBlockingQueue."<init>":()V
   17:	invokespecial	#5; //Method scala/actors/threadpool/ThreadPoolExecutor."<init>":(IIJLscala/actors/threadpool/TimeUnit;Lscala/actors/threadpool/BlockingQueue;)V
   20:	areturn

public static scala.actors.threadpool.ExecutorService newFixedThreadPool(int, scala.actors.threadpool.ThreadFactory);
  Code:
   Stack=9, Locals=2, Args_size=2
   0:	new	#1; //class scala/actors/threadpool/ThreadPoolExecutor
   3:	dup
   4:	iload_0
   5:	iload_0
   6:	lconst_0
   7:	getstatic	#2; //Field scala/actors/threadpool/TimeUnit.MILLISECONDS:Lscala/actors/threadpool/TimeUnit;
   10:	new	#3; //class scala/actors/threadpool/LinkedBlockingQueue
   13:	dup
   14:	invokespecial	#4; //Method scala/actors/threadpool/LinkedBlockingQueue."<init>":()V
   17:	aload_1
   18:	invokespecial	#6; //Method scala/actors/threadpool/ThreadPoolExecutor."<init>":(IIJLscala/actors/threadpool/TimeUnit;Lscala/actors/threadpool/BlockingQueue;Lscala/actors/threadpool/ThreadFactory;)V
   21:	areturn

public static scala.actors.threadpool.ExecutorService newSingleThreadExecutor();
  Code:
   Stack=11, Locals=0, Args_size=0
   0:	new	#7; //class scala/actors/threadpool/Executors$FinalizableDelegatedExecutorService
   3:	dup
   4:	new	#1; //class scala/actors/threadpool/ThreadPoolExecutor
   7:	dup
   8:	iconst_1
   9:	iconst_1
   10:	lconst_0
   11:	getstatic	#2; //Field scala/actors/threadpool/TimeUnit.MILLISECONDS:Lscala/actors/threadpool/TimeUnit;
   14:	new	#3; //class scala/actors/threadpool/LinkedBlockingQueue
   17:	dup
   18:	invokespecial	#4; //Method scala/actors/threadpool/LinkedBlockingQueue."<init>":()V
   21:	invokespecial	#5; //Method scala/actors/threadpool/ThreadPoolExecutor."<init>":(IIJLscala/actors/threadpool/TimeUnit;Lscala/actors/threadpool/BlockingQueue;)V
   24:	invokespecial	#8; //Method scala/actors/threadpool/Executors$FinalizableDelegatedExecutorService."<init>":(Lscala/actors/threadpool/ExecutorService;)V
   27:	areturn

public static scala.actors.threadpool.ExecutorService newSingleThreadExecutor(scala.actors.threadpool.ThreadFactory);
  Code:
   Stack=11, Locals=1, Args_size=1
   0:	new	#7; //class scala/actors/threadpool/Executors$FinalizableDelegatedExecutorService
   3:	dup
   4:	new	#1; //class scala/actors/threadpool/ThreadPoolExecutor
   7:	dup
   8:	iconst_1
   9:	iconst_1
   10:	lconst_0
   11:	getstatic	#2; //Field scala/actors/threadpool/TimeUnit.MILLISECONDS:Lscala/actors/threadpool/TimeUnit;
   14:	new	#3; //class scala/actors/threadpool/LinkedBlockingQueue
   17:	dup
   18:	invokespecial	#4; //Method scala/actors/threadpool/LinkedBlockingQueue."<init>":()V
   21:	aload_0
   22:	invokespecial	#6; //Method scala/actors/threadpool/ThreadPoolExecutor."<init>":(IIJLscala/actors/threadpool/TimeUnit;Lscala/actors/threadpool/BlockingQueue;Lscala/actors/threadpool/ThreadFactory;)V
   25:	invokespecial	#8; //Method scala/actors/threadpool/Executors$FinalizableDelegatedExecutorService."<init>":(Lscala/actors/threadpool/ExecutorService;)V
   28:	areturn

public static scala.actors.threadpool.ExecutorService newCachedThreadPool();
  Code:
   Stack=9, Locals=0, Args_size=0
   0:	new	#1; //class scala/actors/threadpool/ThreadPoolExecutor
   3:	dup
   4:	iconst_0
   5:	ldc	#9; //int 2147483647
   7:	ldc2_w	#10; //long 60l
   10:	getstatic	#12; //Field scala/actors/threadpool/TimeUnit.SECONDS:Lscala/actors/threadpool/TimeUnit;
   13:	new	#13; //class scala/actors/threadpool/SynchronousQueue
   16:	dup
   17:	invokespecial	#14; //Method scala/actors/threadpool/SynchronousQueue."<init>":()V
   20:	invokespecial	#5; //Method scala/actors/threadpool/ThreadPoolExecutor."<init>":(IIJLscala/actors/threadpool/TimeUnit;Lscala/actors/threadpool/BlockingQueue;)V
   23:	areturn

public static scala.actors.threadpool.ExecutorService newCachedThreadPool(scala.actors.threadpool.ThreadFactory);
  Code:
   Stack=9, Locals=1, Args_size=1
   0:	new	#1; //class scala/actors/threadpool/ThreadPoolExecutor
   3:	dup
   4:	iconst_0
   5:	ldc	#9; //int 2147483647
   7:	ldc2_w	#10; //long 60l
   10:	getstatic	#12; //Field scala/actors/threadpool/TimeUnit.SECONDS:Lscala/actors/threadpool/TimeUnit;
   13:	new	#13; //class scala/actors/threadpool/SynchronousQueue
   16:	dup
   17:	invokespecial	#14; //Method scala/actors/threadpool/SynchronousQueue."<init>":()V
   20:	aload_0
   21:	invokespecial	#6; //Method scala/actors/threadpool/ThreadPoolExecutor."<init>":(IIJLscala/actors/threadpool/TimeUnit;Lscala/actors/threadpool/BlockingQueue;Lscala/actors/threadpool/ThreadFactory;)V
   24:	areturn

public static scala.actors.threadpool.ExecutorService unconfigurableExecutorService(scala.actors.threadpool.ExecutorService);
  Code:
   Stack=3, Locals=1, Args_size=1
   0:	aload_0
   1:	ifnonnull	12
   4:	new	#15; //class java/lang/NullPointerException
   7:	dup
   8:	invokespecial	#16; //Method java/lang/NullPointerException."<init>":()V
   11:	athrow
   12:	new	#17; //class scala/actors/threadpool/Executors$DelegatedExecutorService
   15:	dup
   16:	aload_0
   17:	invokespecial	#18; //Method scala/actors/threadpool/Executors$DelegatedExecutorService."<init>":(Lscala/actors/threadpool/ExecutorService;)V
   20:	areturn

public static scala.actors.threadpool.ThreadFactory defaultThreadFactory();
  Code:
   Stack=2, Locals=0, Args_size=0
   0:	new	#19; //class scala/actors/threadpool/Executors$DefaultThreadFactory
   3:	dup
   4:	invokespecial	#20; //Method scala/actors/threadpool/Executors$DefaultThreadFactory."<init>":()V
   7:	areturn

public static scala.actors.threadpool.ThreadFactory privilegedThreadFactory();
  Code:
   Stack=2, Locals=0, Args_size=0
   0:	new	#21; //class scala/actors/threadpool/Executors$PrivilegedThreadFactory
   3:	dup
   4:	invokespecial	#22; //Method scala/actors/threadpool/Executors$PrivilegedThreadFactory."<init>":()V
   7:	areturn

public static scala.actors.threadpool.Callable callable(java.lang.Runnable, java.lang.Object);
  Code:
   Stack=4, Locals=2, Args_size=2
   0:	aload_0
   1:	ifnonnull	12
   4:	new	#15; //class java/lang/NullPointerException
   7:	dup
   8:	invokespecial	#16; //Method java/lang/NullPointerException."<init>":()V
   11:	athrow
   12:	new	#23; //class scala/actors/threadpool/Executors$RunnableAdapter
   15:	dup
   16:	aload_0
   17:	aload_1
   18:	invokespecial	#24; //Method scala/actors/threadpool/Executors$RunnableAdapter."<init>":(Ljava/lang/Runnable;Ljava/lang/Object;)V
   21:	areturn

public static scala.actors.threadpool.Callable callable(java.lang.Runnable);
  Code:
   Stack=4, Locals=1, Args_size=1
   0:	aload_0
   1:	ifnonnull	12
   4:	new	#15; //class java/lang/NullPointerException
   7:	dup
   8:	invokespecial	#16; //Method java/lang/NullPointerException."<init>":()V
   11:	athrow
   12:	new	#23; //class scala/actors/threadpool/Executors$RunnableAdapter
   15:	dup
   16:	aload_0
   17:	aconst_null
   18:	invokespecial	#24; //Method scala/actors/threadpool/Executors$RunnableAdapter."<init>":(Ljava/lang/Runnable;Ljava/lang/Object;)V
   21:	areturn

public static scala.actors.threadpool.Callable callable(java.security.PrivilegedAction);
  Code:
   Stack=3, Locals=1, Args_size=1
   0:	aload_0
   1:	ifnonnull	12
   4:	new	#15; //class java/lang/NullPointerException
   7:	dup
   8:	invokespecial	#16; //Method java/lang/NullPointerException."<init>":()V
   11:	athrow
   12:	new	#25; //class scala/actors/threadpool/Executors$1
   15:	dup
   16:	aload_0
   17:	invokespecial	#26; //Method scala/actors/threadpool/Executors$1."<init>":(Ljava/security/PrivilegedAction;)V
   20:	areturn

public static scala.actors.threadpool.Callable callable(java.security.PrivilegedExceptionAction);
  Code:
   Stack=3, Locals=1, Args_size=1
   0:	aload_0
   1:	ifnonnull	12
   4:	new	#15; //class java/lang/NullPointerException
   7:	dup
   8:	invokespecial	#16; //Method java/lang/NullPointerException."<init>":()V
   11:	athrow
   12:	new	#27; //class scala/actors/threadpool/Executors$2
   15:	dup
   16:	aload_0
   17:	invokespecial	#28; //Method scala/actors/threadpool/Executors$2."<init>":(Ljava/security/PrivilegedExceptionAction;)V
   20:	areturn

public static scala.actors.threadpool.Callable privilegedCallable(scala.actors.threadpool.Callable);
  Code:
   Stack=3, Locals=1, Args_size=1
   0:	aload_0
   1:	ifnonnull	12
   4:	new	#15; //class java/lang/NullPointerException
   7:	dup
   8:	invokespecial	#16; //Method java/lang/NullPointerException."<init>":()V
   11:	athrow
   12:	new	#29; //class scala/actors/threadpool/Executors$PrivilegedCallable
   15:	dup
   16:	aload_0
   17:	invokespecial	#30; //Method scala/actors/threadpool/Executors$PrivilegedCallable."<init>":(Lscala/actors/threadpool/Callable;)V
   20:	areturn

public static scala.actors.threadpool.Callable privilegedCallableUsingCurrentClassLoader(scala.actors.threadpool.Callable);
  Code:
   Stack=3, Locals=1, Args_size=1
   0:	aload_0
   1:	ifnonnull	12
   4:	new	#15; //class java/lang/NullPointerException
   7:	dup
   8:	invokespecial	#16; //Method java/lang/NullPointerException."<init>":()V
   11:	athrow
   12:	new	#31; //class scala/actors/threadpool/Executors$PrivilegedCallableUsingCurrentClassLoader
   15:	dup
   16:	aload_0
   17:	invokespecial	#32; //Method scala/actors/threadpool/Executors$PrivilegedCallableUsingCurrentClassLoader."<init>":(Lscala/actors/threadpool/Callable;)V
   20:	areturn

}

