public class scala.actors.threadpool.ExecutorCompletionService extends java.lang.Object implements scala.actors.threadpool.CompletionService
  InnerClass: 
   #27= #16 of #24; //QueueingFuture=class scala/actors/threadpool/ExecutorCompletionService$QueueingFuture of class scala/actors/threadpool/ExecutorCompletionService
  minor version: 0
  major version: 49
  Constant pool:
const #1 = Field	#24.#53;	//  scala/actors/threadpool/ExecutorCompletionService.completionQueue:Lscala/actors/threadpool/BlockingQueue;
const #2 = Field	#24.#54;	//  scala/actors/threadpool/ExecutorCompletionService.aes:Lscala/actors/threadpool/AbstractExecutorService;
const #3 = class	#55;	//  scala/actors/threadpool/FutureTask
const #4 = Method	#3.#56;	//  scala/actors/threadpool/FutureTask."<init>":(Lscala/actors/threadpool/Callable;)V
const #5 = Method	#12.#57;	//  scala/actors/threadpool/AbstractExecutorService.newTaskFor:(Lscala/actors/threadpool/Callable;)Lscala/actors/threadpool/RunnableFuture;
const #6 = Method	#3.#58;	//  scala/actors/threadpool/FutureTask."<init>":(Ljava/lang/Runnable;Ljava/lang/Object;)V
const #7 = Method	#12.#59;	//  scala/actors/threadpool/AbstractExecutorService.newTaskFor:(Ljava/lang/Runnable;Ljava/lang/Object;)Lscala/actors/threadpool/RunnableFuture;
const #8 = Method	#25.#60;	//  java/lang/Object."<init>":()V
const #9 = class	#61;	//  java/lang/NullPointerException
const #10 = Method	#9.#60;	//  java/lang/NullPointerException."<init>":()V
const #11 = Field	#24.#62;	//  scala/actors/threadpool/ExecutorCompletionService.executor:Lscala/actors/threadpool/Executor;
const #12 = class	#63;	//  scala/actors/threadpool/AbstractExecutorService
const #13 = class	#64;	//  scala/actors/threadpool/LinkedBlockingQueue
const #14 = Method	#13.#60;	//  scala/actors/threadpool/LinkedBlockingQueue."<init>":()V
const #15 = Method	#24.#57;	//  scala/actors/threadpool/ExecutorCompletionService.newTaskFor:(Lscala/actors/threadpool/Callable;)Lscala/actors/threadpool/RunnableFuture;
const #16 = class	#65;	//  scala/actors/threadpool/ExecutorCompletionService$QueueingFuture
const #17 = Method	#16.#66;	//  scala/actors/threadpool/ExecutorCompletionService$QueueingFuture."<init>":(Lscala/actors/threadpool/ExecutorCompletionService;Lscala/actors/threadpool/RunnableFuture;)V
const #18 = InterfaceMethod	#67.#68;	//  scala/actors/threadpool/Executor.execute:(Ljava/lang/Runnable;)V
const #19 = Method	#24.#59;	//  scala/actors/threadpool/ExecutorCompletionService.newTaskFor:(Ljava/lang/Runnable;Ljava/lang/Object;)Lscala/actors/threadpool/RunnableFuture;
const #20 = InterfaceMethod	#69.#70;	//  scala/actors/threadpool/BlockingQueue.take:()Ljava/lang/Object;
const #21 = class	#71;	//  scala/actors/threadpool/Future
const #22 = InterfaceMethod	#69.#72;	//  scala/actors/threadpool/BlockingQueue.poll:()Ljava/lang/Object;
const #23 = InterfaceMethod	#69.#73;	//  scala/actors/threadpool/BlockingQueue.poll:(JLscala/actors/threadpool/TimeUnit;)Ljava/lang/Object;
const #24 = class	#74;	//  scala/actors/threadpool/ExecutorCompletionService
const #25 = class	#75;	//  java/lang/Object
const #26 = class	#76;	//  scala/actors/threadpool/CompletionService
const #27 = Asciz	QueueingFuture;
const #28 = Asciz	InnerClasses;
const #29 = Asciz	executor;
const #30 = Asciz	Lscala/actors/threadpool/Executor;;
const #31 = Asciz	aes;
const #32 = Asciz	Lscala/actors/threadpool/AbstractExecutorService;;
const #33 = Asciz	completionQueue;
const #34 = Asciz	Lscala/actors/threadpool/BlockingQueue;;
const #35 = Asciz	newTaskFor;
const #36 = Asciz	(Lscala/actors/threadpool/Callable;)Lscala/actors/threadpool/RunnableFuture;;
const #37 = Asciz	Code;
const #38 = Asciz	(Ljava/lang/Runnable;Ljava/lang/Object;)Lscala/actors/threadpool/RunnableFuture;;
const #39 = Asciz	<init>;
const #40 = Asciz	(Lscala/actors/threadpool/Executor;)V;
const #41 = Asciz	(Lscala/actors/threadpool/Executor;Lscala/actors/threadpool/BlockingQueue;)V;
const #42 = Asciz	submit;
const #43 = Asciz	(Lscala/actors/threadpool/Callable;)Lscala/actors/threadpool/Future;;
const #44 = Asciz	(Ljava/lang/Runnable;Ljava/lang/Object;)Lscala/actors/threadpool/Future;;
const #45 = Asciz	take;
const #46 = Asciz	()Lscala/actors/threadpool/Future;;
const #47 = Asciz	Exceptions;
const #48 = class	#77;	//  java/lang/InterruptedException
const #49 = Asciz	poll;
const #50 = Asciz	(JLscala/actors/threadpool/TimeUnit;)Lscala/actors/threadpool/Future;;
const #51 = Asciz	access$000;
const #52 = Asciz	(Lscala/actors/threadpool/ExecutorCompletionService;)Lscala/actors/threadpool/BlockingQueue;;
const #53 = NameAndType	#33:#34;//  completionQueue:Lscala/actors/threadpool/BlockingQueue;
const #54 = NameAndType	#31:#32;//  aes:Lscala/actors/threadpool/AbstractExecutorService;
const #55 = Asciz	scala/actors/threadpool/FutureTask;
const #56 = NameAndType	#39:#78;//  "<init>":(Lscala/actors/threadpool/Callable;)V
const #57 = NameAndType	#35:#36;//  newTaskFor:(Lscala/actors/threadpool/Callable;)Lscala/actors/threadpool/RunnableFuture;
const #58 = NameAndType	#39:#79;//  "<init>":(Ljava/lang/Runnable;Ljava/lang/Object;)V
const #59 = NameAndType	#35:#38;//  newTaskFor:(Ljava/lang/Runnable;Ljava/lang/Object;)Lscala/actors/threadpool/RunnableFuture;
const #60 = NameAndType	#39:#80;//  "<init>":()V
const #61 = Asciz	java/lang/NullPointerException;
const #62 = NameAndType	#29:#30;//  executor:Lscala/actors/threadpool/Executor;
const #63 = Asciz	scala/actors/threadpool/AbstractExecutorService;
const #64 = Asciz	scala/actors/threadpool/LinkedBlockingQueue;
const #65 = Asciz	scala/actors/threadpool/ExecutorCompletionService$QueueingFuture;
const #66 = NameAndType	#39:#81;//  "<init>":(Lscala/actors/threadpool/ExecutorCompletionService;Lscala/actors/threadpool/RunnableFuture;)V
const #67 = class	#82;	//  scala/actors/threadpool/Executor
const #68 = NameAndType	#83:#84;//  execute:(Ljava/lang/Runnable;)V
const #69 = class	#85;	//  scala/actors/threadpool/BlockingQueue
const #70 = NameAndType	#45:#86;//  take:()Ljava/lang/Object;
const #71 = Asciz	scala/actors/threadpool/Future;
const #72 = NameAndType	#49:#86;//  poll:()Ljava/lang/Object;
const #73 = NameAndType	#49:#87;//  poll:(JLscala/actors/threadpool/TimeUnit;)Ljava/lang/Object;
const #74 = Asciz	scala/actors/threadpool/ExecutorCompletionService;
const #75 = Asciz	java/lang/Object;
const #76 = Asciz	scala/actors/threadpool/CompletionService;
const #77 = Asciz	java/lang/InterruptedException;
const #78 = Asciz	(Lscala/actors/threadpool/Callable;)V;
const #79 = Asciz	(Ljava/lang/Runnable;Ljava/lang/Object;)V;
const #80 = Asciz	()V;
const #81 = Asciz	(Lscala/actors/threadpool/ExecutorCompletionService;Lscala/actors/threadpool/RunnableFuture;)V;
const #82 = Asciz	scala/actors/threadpool/Executor;
const #83 = Asciz	execute;
const #84 = Asciz	(Ljava/lang/Runnable;)V;
const #85 = Asciz	scala/actors/threadpool/BlockingQueue;
const #86 = Asciz	()Ljava/lang/Object;;
const #87 = Asciz	(JLscala/actors/threadpool/TimeUnit;)Ljava/lang/Object;;

{
public scala.actors.threadpool.ExecutorCompletionService(scala.actors.threadpool.Executor);
  Code:
   Stack=3, Locals=2, Args_size=2
   0:	aload_0
   1:	invokespecial	#8; //Method java/lang/Object."<init>":()V
   4:	aload_1
   5:	ifnonnull	16
   8:	new	#9; //class java/lang/NullPointerException
   11:	dup
   12:	invokespecial	#10; //Method java/lang/NullPointerException."<init>":()V
   15:	athrow
   16:	aload_0
   17:	aload_1
   18:	putfield	#11; //Field executor:Lscala/actors/threadpool/Executor;
   21:	aload_0
   22:	aload_1
   23:	instanceof	#12; //class scala/actors/threadpool/AbstractExecutorService
   26:	ifeq	36
   29:	aload_1
   30:	checkcast	#12; //class scala/actors/threadpool/AbstractExecutorService
   33:	goto	37
   36:	aconst_null
   37:	putfield	#2; //Field aes:Lscala/actors/threadpool/AbstractExecutorService;
   40:	aload_0
   41:	new	#13; //class scala/actors/threadpool/LinkedBlockingQueue
   44:	dup
   45:	invokespecial	#14; //Method scala/actors/threadpool/LinkedBlockingQueue."<init>":()V
   48:	putfield	#1; //Field completionQueue:Lscala/actors/threadpool/BlockingQueue;
   51:	return

public scala.actors.threadpool.ExecutorCompletionService(scala.actors.threadpool.Executor, scala.actors.threadpool.BlockingQueue);
  Code:
   Stack=2, Locals=3, Args_size=3
   0:	aload_0
   1:	invokespecial	#8; //Method java/lang/Object."<init>":()V
   4:	aload_1
   5:	ifnull	12
   8:	aload_2
   9:	ifnonnull	20
   12:	new	#9; //class java/lang/NullPointerException
   15:	dup
   16:	invokespecial	#10; //Method java/lang/NullPointerException."<init>":()V
   19:	athrow
   20:	aload_0
   21:	aload_1
   22:	putfield	#11; //Field executor:Lscala/actors/threadpool/Executor;
   25:	aload_0
   26:	aload_1
   27:	instanceof	#12; //class scala/actors/threadpool/AbstractExecutorService
   30:	ifeq	40
   33:	aload_1
   34:	checkcast	#12; //class scala/actors/threadpool/AbstractExecutorService
   37:	goto	41
   40:	aconst_null
   41:	putfield	#2; //Field aes:Lscala/actors/threadpool/AbstractExecutorService;
   44:	aload_0
   45:	aload_2
   46:	putfield	#1; //Field completionQueue:Lscala/actors/threadpool/BlockingQueue;
   49:	return

public scala.actors.threadpool.Future submit(scala.actors.threadpool.Callable);
  Code:
   Stack=5, Locals=3, Args_size=2
   0:	aload_1
   1:	ifnonnull	12
   4:	new	#9; //class java/lang/NullPointerException
   7:	dup
   8:	invokespecial	#10; //Method java/lang/NullPointerException."<init>":()V
   11:	athrow
   12:	aload_0
   13:	aload_1
   14:	invokespecial	#15; //Method newTaskFor:(Lscala/actors/threadpool/Callable;)Lscala/actors/threadpool/RunnableFuture;
   17:	astore_2
   18:	aload_0
   19:	getfield	#11; //Field executor:Lscala/actors/threadpool/Executor;
   22:	new	#16; //class scala/actors/threadpool/ExecutorCompletionService$QueueingFuture
   25:	dup
   26:	aload_0
   27:	aload_2
   28:	invokespecial	#17; //Method scala/actors/threadpool/ExecutorCompletionService$QueueingFuture."<init>":(Lscala/actors/threadpool/ExecutorCompletionService;Lscala/actors/threadpool/RunnableFuture;)V
   31:	invokeinterface	#18,  2; //InterfaceMethod scala/actors/threadpool/Executor.execute:(Ljava/lang/Runnable;)V
   36:	aload_2
   37:	areturn

public scala.actors.threadpool.Future submit(java.lang.Runnable, java.lang.Object);
  Code:
   Stack=5, Locals=4, Args_size=3
   0:	aload_1
   1:	ifnonnull	12
   4:	new	#9; //class java/lang/NullPointerException
   7:	dup
   8:	invokespecial	#10; //Method java/lang/NullPointerException."<init>":()V
   11:	athrow
   12:	aload_0
   13:	aload_1
   14:	aload_2
   15:	invokespecial	#19; //Method newTaskFor:(Ljava/lang/Runnable;Ljava/lang/Object;)Lscala/actors/threadpool/RunnableFuture;
   18:	astore_3
   19:	aload_0
   20:	getfield	#11; //Field executor:Lscala/actors/threadpool/Executor;
   23:	new	#16; //class scala/actors/threadpool/ExecutorCompletionService$QueueingFuture
   26:	dup
   27:	aload_0
   28:	aload_3
   29:	invokespecial	#17; //Method scala/actors/threadpool/ExecutorCompletionService$QueueingFuture."<init>":(Lscala/actors/threadpool/ExecutorCompletionService;Lscala/actors/threadpool/RunnableFuture;)V
   32:	invokeinterface	#18,  2; //InterfaceMethod scala/actors/threadpool/Executor.execute:(Ljava/lang/Runnable;)V
   37:	aload_3
   38:	areturn

public scala.actors.threadpool.Future take()   throws java.lang.InterruptedException;
  Code:
   Stack=1, Locals=1, Args_size=1
   0:	aload_0
   1:	getfield	#1; //Field completionQueue:Lscala/actors/threadpool/BlockingQueue;
   4:	invokeinterface	#20,  1; //InterfaceMethod scala/actors/threadpool/BlockingQueue.take:()Ljava/lang/Object;
   9:	checkcast	#21; //class scala/actors/threadpool/Future
   12:	areturn
  Exceptions: 
   throws java.lang.InterruptedException
public scala.actors.threadpool.Future poll();
  Code:
   Stack=1, Locals=1, Args_size=1
   0:	aload_0
   1:	getfield	#1; //Field completionQueue:Lscala/actors/threadpool/BlockingQueue;
   4:	invokeinterface	#22,  1; //InterfaceMethod scala/actors/threadpool/BlockingQueue.poll:()Ljava/lang/Object;
   9:	checkcast	#21; //class scala/actors/threadpool/Future
   12:	areturn

public scala.actors.threadpool.Future poll(long, scala.actors.threadpool.TimeUnit)   throws java.lang.InterruptedException;
  Code:
   Stack=4, Locals=4, Args_size=3
   0:	aload_0
   1:	getfield	#1; //Field completionQueue:Lscala/actors/threadpool/BlockingQueue;
   4:	lload_1
   5:	aload_3
   6:	invokeinterface	#23,  4; //InterfaceMethod scala/actors/threadpool/BlockingQueue.poll:(JLscala/actors/threadpool/TimeUnit;)Ljava/lang/Object;
   11:	checkcast	#21; //class scala/actors/threadpool/Future
   14:	areturn
  Exceptions: 
   throws java.lang.InterruptedException
static scala.actors.threadpool.BlockingQueue access$000(scala.actors.threadpool.ExecutorCompletionService);
  Code:
   Stack=1, Locals=1, Args_size=1
   0:	aload_0
   1:	getfield	#1; //Field completionQueue:Lscala/actors/threadpool/BlockingQueue;
   4:	areturn

}

