class scala.actors.threadpool.Executors$PrivilegedCallable$1 extends java.lang.Object implements java.security.PrivilegedAction
  EnclosingMethod: length = 0x4
   00 0C 00 16 
  InnerClass: 
   final PrivilegedCallable=class scala/actors/threadpool/Executors$PrivilegedCallable of class scala/actors/threadpool/Executors
   class scala/actors/threadpool/Executors$PrivilegedCallable$1
  minor version: 0
  major version: 49
  Constant pool:
Field	scala/actors/threadpool/Executors$PrivilegedCallable$1.this$0:Lscala/actors/threadpool/Executors$PrivilegedCallable;
Method	java/lang/Object."<init>":()V
Method	scala/actors/threadpool/Executors$PrivilegedCallable.access$100:(Lscala/actors/threadpool/Executors$PrivilegedCallable;)Lscala/actors/threadpool/Callable;
InterfaceMethod	scala/actors/threadpool/Callable.call:()Ljava/lang/Object;
Method	scala/actors/threadpool/Executors$PrivilegedCallable.access$002:(Lscala/actors/threadpool/Executors$PrivilegedCallable;Ljava/lang/Object;)Ljava/lang/Object;
class	java/lang/Exception
Method	scala/actors/threadpool/Executors$PrivilegedCallable.access$202:(Lscala/actors/threadpool/Executors$PrivilegedCallable;Ljava/lang/Exception;)Ljava/lang/Exception;
class	scala/actors/threadpool/Executors$PrivilegedCallable$1
class	java/lang/Object
class	java/security/PrivilegedAction
Asciz	this$0;
class	scala/actors/threadpool/Executors$PrivilegedCallable
Asciz	PrivilegedCallable;
Asciz	InnerClasses;
Asciz	Lscala/actors/threadpool/Executors$PrivilegedCallable;;
Asciz	<init>;
Asciz	(Lscala/actors/threadpool/Executors$PrivilegedCallable;)V;
Asciz	Code;
Asciz	run;
Asciz	()Ljava/lang/Object;;
Asciz	EnclosingMethod;
NameAndType	call:()Ljava/lang/Object;
NameAndType	this$0:Lscala/actors/threadpool/Executors$PrivilegedCallable;
NameAndType	"<init>":()V
NameAndType	access$100:(Lscala/actors/threadpool/Executors$PrivilegedCallable;)Lscala/actors/threadpool/Callable;
class	scala/actors/threadpool/Callable
NameAndType	access$002:(Lscala/actors/threadpool/Executors$PrivilegedCallable;Ljava/lang/Object;)Ljava/lang/Object;
Asciz	java/lang/Exception;
NameAndType	access$202:(Lscala/actors/threadpool/Executors$PrivilegedCallable;Ljava/lang/Exception;)Ljava/lang/Exception;
Asciz	scala/actors/threadpool/Executors$PrivilegedCallable$1;
Asciz	;
Asciz	java/lang/Object;
Asciz	java/security/PrivilegedAction;
class	scala/actors/threadpool/Executors
Asciz	scala/actors/threadpool/Executors$PrivilegedCallable;
Asciz	call;
Asciz	()V;
Asciz	access$100;
Asciz	(Lscala/actors/threadpool/Executors$PrivilegedCallable;)Lscala/actors/threadpool/Callable;;
Asciz	scala/actors/threadpool/Callable;
Asciz	access$002;
Asciz	(Lscala/actors/threadpool/Executors$PrivilegedCallable;Ljava/lang/Object;)Ljava/lang/Object;;
Asciz	access$202;
Asciz	(Lscala/actors/threadpool/Executors$PrivilegedCallable;Ljava/lang/Exception;)Ljava/lang/Exception;;
Asciz	scala/actors/threadpool/Executors;

{
final scala.actors.threadpool.Executors$PrivilegedCallable this$0;
  Signature: Lscala/actors/threadpool/Executors$PrivilegedCallable;

scala.actors.threadpool.Executors$PrivilegedCallable$1(scala.actors.threadpool.Executors$PrivilegedCallable);
  Signature: (Lscala/actors/threadpool/Executors$PrivilegedCallable;)V
  Code:
   Stack=2, Locals=2, Args_size=2
	aload_0
	aload_1
	putfield	Field this$0:Lscala/actors/threadpool/Executors$PrivilegedCallable;
	aload_0
	invokespecial	Method java/lang/Object."<init>":()V
	return
  Labels:

public java.lang.Object run();
  Signature: ()Ljava/lang/Object;
  Code:
   Stack=2, Locals=2, Args_size=1
	aload_0
	getfield	Field this$0:Lscala/actors/threadpool/Executors$PrivilegedCallable;
	aload_0
	getfield	Field this$0:Lscala/actors/threadpool/Executors$PrivilegedCallable;
	invokestatic	Method scala/actors/threadpool/Executors$PrivilegedCallable.access$100:(Lscala/actors/threadpool/Executors$PrivilegedCallable;)Lscala/actors/threadpool/Callable;
	invokeinterface	InterfaceMethod scala/actors/threadpool/Callable.call:()Ljava/lang/Object;
	invokestatic	Method scala/actors/threadpool/Executors$PrivilegedCallable.access$002:(Lscala/actors/threadpool/Executors$PrivilegedCallable;Ljava/lang/Object;)Ljava/lang/Object;
	pop
	goto	l1 // aconst_null
	astore_1
	aload_0
	getfield	Field this$0:Lscala/actors/threadpool/Executors$PrivilegedCallable;
	aload_1
	invokestatic	Method scala/actors/threadpool/Executors$PrivilegedCallable.access$202:(Lscala/actors/threadpool/Executors$PrivilegedCallable;Ljava/lang/Exception;)Ljava/lang/Exception;
	pop
l1	aconst_null
	areturn
  Labels:
   	l1 = 33 // aconst_null
  Exception table:
   from   to  target type
     0    20    23   Class java/lang/Exception


}

