public class scala.actors.threadpool.ExecutionException extends java.lang.Exception
  minor version: 0
  major version: 49
  Constant pool:
Method	java/lang/Exception."<init>":()V
Method	java/lang/Exception."<init>":(Ljava/lang/String;)V
Method	java/lang/Exception."<init>":(Ljava/lang/String;Ljava/lang/Throwable;)V
Method	java/lang/Exception."<init>":(Ljava/lang/Throwable;)V
class	scala/actors/threadpool/ExecutionException
class	java/lang/Exception
Asciz	serialVersionUID;
Asciz	J;
Asciz	ConstantValue;
long	7830266012832686185l;
Asciz	<init>;
Asciz	()V;
Asciz	Code;
Asciz	(Ljava/lang/String;)V;
Asciz	(Ljava/lang/String;Ljava/lang/Throwable;)V;
Asciz	(Ljava/lang/Throwable;)V;
NameAndType	"<init>":()V
NameAndType	"<init>":(Ljava/lang/String;)V
NameAndType	"<init>":(Ljava/lang/String;Ljava/lang/Throwable;)V
NameAndType	"<init>":(Ljava/lang/Throwable;)V
Asciz	scala/actors/threadpool/ExecutionException;
Asciz	java/lang/Exception;

{
private static final long serialVersionUID;
  Signature: J
  Constant value: long 7830266012832686185l
protected scala.actors.threadpool.ExecutionException();
  Signature: ()V
  Code:
   Stack=1, Locals=1, Args_size=1
	aload_0
	invokespecial	Method java/lang/Exception."<init>":()V
	return
  Labels:

protected scala.actors.threadpool.ExecutionException(java.lang.String);
  Signature: (Ljava/lang/String;)V
  Code:
   Stack=2, Locals=2, Args_size=2
	aload_0
	aload_1
	invokespecial	Method java/lang/Exception."<init>":(Ljava/lang/String;)V
	return
  Labels:

public scala.actors.threadpool.ExecutionException(java.lang.String, java.lang.Throwable);
  Signature: (Ljava/lang/String;Ljava/lang/Throwable;)V
  Code:
   Stack=3, Locals=3, Args_size=3
	aload_0
	aload_1
	aload_2
	invokespecial	Method java/lang/Exception."<init>":(Ljava/lang/String;Ljava/lang/Throwable;)V
	return
  Labels:

public scala.actors.threadpool.ExecutionException(java.lang.Throwable);
  Signature: (Ljava/lang/Throwable;)V
  Code:
   Stack=2, Locals=2, Args_size=2
	aload_0
	aload_1
	invokespecial	Method java/lang/Exception."<init>":(Ljava/lang/Throwable;)V
	return
  Labels:

}

