class scala.actors.threadpool.Executors$DelegatedExecutorService extends scala.actors.threadpool.AbstractExecutorService
  InnerClass: 
   #66= #16 of #64; //DelegatedExecutorService=class scala/actors/threadpool/Executors$DelegatedExecutorService of class scala/actors/threadpool/Executors
  minor version: 0
  major version: 49
  Constant pool:
const #1 = Method	#17.#48;	//  scala/actors/threadpool/AbstractExecutorService."<init>":()V
const #2 = Field	#16.#49;	//  scala/actors/threadpool/Executors$DelegatedExecutorService.e:Lscala/actors/threadpool/ExecutorService;
const #3 = InterfaceMethod	#50.#51;	//  scala/actors/threadpool/ExecutorService.execute:(Ljava/lang/Runnable;)V
const #4 = InterfaceMethod	#50.#52;	//  scala/actors/threadpool/ExecutorService.shutdown:()V
const #5 = InterfaceMethod	#50.#53;	//  scala/actors/threadpool/ExecutorService.shutdownNow:()Ljava/util/List;
const #6 = InterfaceMethod	#50.#54;	//  scala/actors/threadpool/ExecutorService.isShutdown:()Z
const #7 = InterfaceMethod	#50.#55;	//  scala/actors/threadpool/ExecutorService.isTerminated:()Z
const #8 = InterfaceMethod	#50.#56;	//  scala/actors/threadpool/ExecutorService.awaitTermination:(JLscala/actors/threadpool/TimeUnit;)Z
const #9 = InterfaceMethod	#50.#57;	//  scala/actors/threadpool/ExecutorService.submit:(Ljava/lang/Runnable;)Lscala/actors/threadpool/Future;
const #10 = InterfaceMethod	#50.#58;	//  scala/actors/threadpool/ExecutorService.submit:(Lscala/actors/threadpool/Callable;)Lscala/actors/threadpool/Future;
const #11 = InterfaceMethod	#50.#59;	//  scala/actors/threadpool/ExecutorService.submit:(Ljava/lang/Runnable;Ljava/lang/Object;)Lscala/actors/threadpool/Future;
const #12 = InterfaceMethod	#50.#60;	//  scala/actors/threadpool/ExecutorService.invokeAll:(Ljava/util/Collection;)Ljava/util/List;
const #13 = InterfaceMethod	#50.#61;	//  scala/actors/threadpool/ExecutorService.invokeAll:(Ljava/util/Collection;JLscala/actors/threadpool/TimeUnit;)Ljava/util/List;
const #14 = InterfaceMethod	#50.#62;	//  scala/actors/threadpool/ExecutorService.invokeAny:(Ljava/util/Collection;)Ljava/lang/Object;
const #15 = InterfaceMethod	#50.#63;	//  scala/actors/threadpool/ExecutorService.invokeAny:(Ljava/util/Collection;JLscala/actors/threadpool/TimeUnit;)Ljava/lang/Object;
const #16 = class	#65;	//  scala/actors/threadpool/Executors$DelegatedExecutorService
const #17 = class	#68;	//  scala/actors/threadpool/AbstractExecutorService
const #18 = Asciz	e;
const #19 = Asciz	Lscala/actors/threadpool/ExecutorService;;
const #20 = Asciz	<init>;
const #21 = Asciz	(Lscala/actors/threadpool/ExecutorService;)V;
const #22 = Asciz	Code;
const #23 = Asciz	execute;
const #24 = Asciz	(Ljava/lang/Runnable;)V;
const #25 = Asciz	shutdown;
const #26 = Asciz	()V;
const #27 = Asciz	shutdownNow;
const #28 = Asciz	()Ljava/util/List;;
const #29 = Asciz	isShutdown;
const #30 = Asciz	()Z;
const #31 = Asciz	isTerminated;
const #32 = Asciz	awaitTermination;
const #33 = Asciz	(JLscala/actors/threadpool/TimeUnit;)Z;
const #34 = Asciz	Exceptions;
const #35 = class	#69;	//  java/lang/InterruptedException
const #36 = Asciz	submit;
const #37 = Asciz	(Ljava/lang/Runnable;)Lscala/actors/threadpool/Future;;
const #38 = Asciz	(Lscala/actors/threadpool/Callable;)Lscala/actors/threadpool/Future;;
const #39 = Asciz	(Ljava/lang/Runnable;Ljava/lang/Object;)Lscala/actors/threadpool/Future;;
const #40 = Asciz	invokeAll;
const #41 = Asciz	(Ljava/util/Collection;)Ljava/util/List;;
const #42 = Asciz	(Ljava/util/Collection;JLscala/actors/threadpool/TimeUnit;)Ljava/util/List;;
const #43 = Asciz	invokeAny;
const #44 = Asciz	(Ljava/util/Collection;)Ljava/lang/Object;;
const #45 = class	#70;	//  scala/actors/threadpool/ExecutionException
const #46 = Asciz	(Ljava/util/Collection;JLscala/actors/threadpool/TimeUnit;)Ljava/lang/Object;;
const #47 = class	#71;	//  scala/actors/threadpool/TimeoutException
const #48 = NameAndType	#20:#26;//  "<init>":()V
const #49 = NameAndType	#18:#19;//  e:Lscala/actors/threadpool/ExecutorService;
const #50 = class	#72;	//  scala/actors/threadpool/ExecutorService
const #51 = NameAndType	#23:#24;//  execute:(Ljava/lang/Runnable;)V
const #52 = NameAndType	#25:#26;//  shutdown:()V
const #53 = NameAndType	#27:#28;//  shutdownNow:()Ljava/util/List;
const #54 = NameAndType	#29:#30;//  isShutdown:()Z
const #55 = NameAndType	#31:#30;//  isTerminated:()Z
const #56 = NameAndType	#32:#33;//  awaitTermination:(JLscala/actors/threadpool/TimeUnit;)Z
const #57 = NameAndType	#36:#37;//  submit:(Ljava/lang/Runnable;)Lscala/actors/threadpool/Future;
const #58 = NameAndType	#36:#38;//  submit:(Lscala/actors/threadpool/Callable;)Lscala/actors/threadpool/Future;
const #59 = NameAndType	#36:#39;//  submit:(Ljava/lang/Runnable;Ljava/lang/Object;)Lscala/actors/threadpool/Future;
const #60 = NameAndType	#40:#41;//  invokeAll:(Ljava/util/Collection;)Ljava/util/List;
const #61 = NameAndType	#40:#42;//  invokeAll:(Ljava/util/Collection;JLscala/actors/threadpool/TimeUnit;)Ljava/util/List;
const #62 = NameAndType	#43:#44;//  invokeAny:(Ljava/util/Collection;)Ljava/lang/Object;
const #63 = NameAndType	#43:#46;//  invokeAny:(Ljava/util/Collection;JLscala/actors/threadpool/TimeUnit;)Ljava/lang/Object;
const #64 = class	#73;	//  scala/actors/threadpool/Executors
const #65 = Asciz	scala/actors/threadpool/Executors$DelegatedExecutorService;
const #66 = Asciz	DelegatedExecutorService;
const #67 = Asciz	InnerClasses;
const #68 = Asciz	scala/actors/threadpool/AbstractExecutorService;
const #69 = Asciz	java/lang/InterruptedException;
const #70 = Asciz	scala/actors/threadpool/ExecutionException;
const #71 = Asciz	scala/actors/threadpool/TimeoutException;
const #72 = Asciz	scala/actors/threadpool/ExecutorService;
const #73 = Asciz	scala/actors/threadpool/Executors;

{
scala.actors.threadpool.Executors$DelegatedExecutorService(scala.actors.threadpool.ExecutorService);
  Code:
   Stack=2, Locals=2, Args_size=2
   0:	aload_0
   1:	invokespecial	#1; //Method scala/actors/threadpool/AbstractExecutorService."<init>":()V
   4:	aload_0
   5:	aload_1
   6:	putfield	#2; //Field e:Lscala/actors/threadpool/ExecutorService;
   9:	return

public void execute(java.lang.Runnable);
  Code:
   Stack=2, Locals=2, Args_size=2
   0:	aload_0
   1:	getfield	#2; //Field e:Lscala/actors/threadpool/ExecutorService;
   4:	aload_1
   5:	invokeinterface	#3,  2; //InterfaceMethod scala/actors/threadpool/ExecutorService.execute:(Ljava/lang/Runnable;)V
   10:	return

public void shutdown();
  Code:
   Stack=1, Locals=1, Args_size=1
   0:	aload_0
   1:	getfield	#2; //Field e:Lscala/actors/threadpool/ExecutorService;
   4:	invokeinterface	#4,  1; //InterfaceMethod scala/actors/threadpool/ExecutorService.shutdown:()V
   9:	return

public java.util.List shutdownNow();
  Code:
   Stack=1, Locals=1, Args_size=1
   0:	aload_0
   1:	getfield	#2; //Field e:Lscala/actors/threadpool/ExecutorService;
   4:	invokeinterface	#5,  1; //InterfaceMethod scala/actors/threadpool/ExecutorService.shutdownNow:()Ljava/util/List;
   9:	areturn

public boolean isShutdown();
  Code:
   Stack=1, Locals=1, Args_size=1
   0:	aload_0
   1:	getfield	#2; //Field e:Lscala/actors/threadpool/ExecutorService;
   4:	invokeinterface	#6,  1; //InterfaceMethod scala/actors/threadpool/ExecutorService.isShutdown:()Z
   9:	ireturn

public boolean isTerminated();
  Code:
   Stack=1, Locals=1, Args_size=1
   0:	aload_0
   1:	getfield	#2; //Field e:Lscala/actors/threadpool/ExecutorService;
   4:	invokeinterface	#7,  1; //InterfaceMethod scala/actors/threadpool/ExecutorService.isTerminated:()Z
   9:	ireturn

public boolean awaitTermination(long, scala.actors.threadpool.TimeUnit)   throws java.lang.InterruptedException;
  Code:
   Stack=4, Locals=4, Args_size=3
   0:	aload_0
   1:	getfield	#2; //Field e:Lscala/actors/threadpool/ExecutorService;
   4:	lload_1
   5:	aload_3
   6:	invokeinterface	#8,  4; //InterfaceMethod scala/actors/threadpool/ExecutorService.awaitTermination:(JLscala/actors/threadpool/TimeUnit;)Z
   11:	ireturn
  Exceptions: 
   throws java.lang.InterruptedException
public scala.actors.threadpool.Future submit(java.lang.Runnable);
  Code:
   Stack=2, Locals=2, Args_size=2
   0:	aload_0
   1:	getfield	#2; //Field e:Lscala/actors/threadpool/ExecutorService;
   4:	aload_1
   5:	invokeinterface	#9,  2; //InterfaceMethod scala/actors/threadpool/ExecutorService.submit:(Ljava/lang/Runnable;)Lscala/actors/threadpool/Future;
   10:	areturn

public scala.actors.threadpool.Future submit(scala.actors.threadpool.Callable);
  Code:
   Stack=2, Locals=2, Args_size=2
   0:	aload_0
   1:	getfield	#2; //Field e:Lscala/actors/threadpool/ExecutorService;
   4:	aload_1
   5:	invokeinterface	#10,  2; //InterfaceMethod scala/actors/threadpool/ExecutorService.submit:(Lscala/actors/threadpool/Callable;)Lscala/actors/threadpool/Future;
   10:	areturn

public scala.actors.threadpool.Future submit(java.lang.Runnable, java.lang.Object);
  Code:
   Stack=3, Locals=3, Args_size=3
   0:	aload_0
   1:	getfield	#2; //Field e:Lscala/actors/threadpool/ExecutorService;
   4:	aload_1
   5:	aload_2
   6:	invokeinterface	#11,  3; //InterfaceMethod scala/actors/threadpool/ExecutorService.submit:(Ljava/lang/Runnable;Ljava/lang/Object;)Lscala/actors/threadpool/Future;
   11:	areturn

public java.util.List invokeAll(java.util.Collection)   throws java.lang.InterruptedException;
  Code:
   Stack=2, Locals=2, Args_size=2
   0:	aload_0
   1:	getfield	#2; //Field e:Lscala/actors/threadpool/ExecutorService;
   4:	aload_1
   5:	invokeinterface	#12,  2; //InterfaceMethod scala/actors/threadpool/ExecutorService.invokeAll:(Ljava/util/Collection;)Ljava/util/List;
   10:	areturn
  Exceptions: 
   throws java.lang.InterruptedException
public java.util.List invokeAll(java.util.Collection, long, scala.actors.threadpool.TimeUnit)   throws java.lang.InterruptedException;
  Code:
   Stack=5, Locals=5, Args_size=4
   0:	aload_0
   1:	getfield	#2; //Field e:Lscala/actors/threadpool/ExecutorService;
   4:	aload_1
   5:	lload_2
   6:	aload	4
   8:	invokeinterface	#13,  5; //InterfaceMethod scala/actors/threadpool/ExecutorService.invokeAll:(Ljava/util/Collection;JLscala/actors/threadpool/TimeUnit;)Ljava/util/List;
   13:	areturn
  Exceptions: 
   throws java.lang.InterruptedException
public java.lang.Object invokeAny(java.util.Collection)   throws java.lang.InterruptedException, scala.actors.threadpool.ExecutionException;
  Code:
   Stack=2, Locals=2, Args_size=2
   0:	aload_0
   1:	getfield	#2; //Field e:Lscala/actors/threadpool/ExecutorService;
   4:	aload_1
   5:	invokeinterface	#14,  2; //InterfaceMethod scala/actors/threadpool/ExecutorService.invokeAny:(Ljava/util/Collection;)Ljava/lang/Object;
   10:	areturn
  Exceptions: 
   throws java.lang.InterruptedException, scala.actors.threadpool.ExecutionException
public java.lang.Object invokeAny(java.util.Collection, long, scala.actors.threadpool.TimeUnit)   throws java.lang.InterruptedException, scala.actors.threadpool.ExecutionException, scala.actors.threadpool.TimeoutException;
  Code:
   Stack=5, Locals=5, Args_size=4
   0:	aload_0
   1:	getfield	#2; //Field e:Lscala/actors/threadpool/ExecutorService;
   4:	aload_1
   5:	lload_2
   6:	aload	4
   8:	invokeinterface	#15,  5; //InterfaceMethod scala/actors/threadpool/ExecutorService.invokeAny:(Ljava/util/Collection;JLscala/actors/threadpool/TimeUnit;)Ljava/lang/Object;
   13:	areturn
  Exceptions: 
   throws java.lang.InterruptedException, scala.actors.threadpool.ExecutionException, scala.actors.threadpool.TimeoutException
}

