class scala.actors.threadpool.Executors$PrivilegedThreadFactory extends scala.actors.threadpool.Executors$DefaultThreadFactory
  InnerClass: 
   PrivilegedThreadFactory=class scala/actors/threadpool/Executors$PrivilegedThreadFactory of class scala/actors/threadpool/Executors
   class scala/actors/threadpool/Executors$PrivilegedThreadFactory$1
   DefaultThreadFactory=class scala/actors/threadpool/Executors$DefaultThreadFactory of class scala/actors/threadpool/Executors
  minor version: 0
  major version: 49
  Constant pool:
Field	scala/actors/threadpool/Executors$PrivilegedThreadFactory.acc:Ljava/security/AccessControlContext;
Field	scala/actors/threadpool/Executors$PrivilegedThreadFactory.ccl:Ljava/lang/ClassLoader;
Method	scala/actors/threadpool/Executors$DefaultThreadFactory."<init>":()V
Method	java/lang/Thread.currentThread:()Ljava/lang/Thread;
Method	java/lang/Thread.getContextClassLoader:()Ljava/lang/ClassLoader;
Method	java/security/AccessController.getContext:()Ljava/security/AccessControlContext;
class	java/lang/RuntimePermission
String	setContextClassLoader
Method	java/lang/RuntimePermission."<init>":(Ljava/lang/String;)V
Method	java/security/AccessControlContext.checkPermission:(Ljava/security/Permission;)V
class	scala/actors/threadpool/Executors$PrivilegedThreadFactory$1
Method	scala/actors/threadpool/Executors$PrivilegedThreadFactory$1."<init>":(Lscala/actors/threadpool/Executors$PrivilegedThreadFactory;Ljava/lang/Runnable;)V
Method	scala/actors/threadpool/Executors$DefaultThreadFactory.newThread:(Ljava/lang/Runnable;)Ljava/lang/Thread;
class	scala/actors/threadpool/Executors$PrivilegedThreadFactory
class	scala/actors/threadpool/Executors$DefaultThreadFactory
Asciz	ccl;
Asciz	Ljava/lang/ClassLoader;;
Asciz	acc;
Asciz	Ljava/security/AccessControlContext;;
Asciz	<init>;
Asciz	()V;
Asciz	Code;
Asciz	newThread;
Asciz	(Ljava/lang/Runnable;)Ljava/lang/Thread;;
Asciz	access$700;
Asciz	PrivilegedThreadFactory;
Asciz	InnerClasses;
Asciz	(Lscala/actors/threadpool/Executors$PrivilegedThreadFactory;)Ljava/lang/ClassLoader;;
Asciz	access$800;
Asciz	(Lscala/actors/threadpool/Executors$PrivilegedThreadFactory;)Ljava/security/AccessControlContext;;
NameAndType	acc:Ljava/security/AccessControlContext;
NameAndType	ccl:Ljava/lang/ClassLoader;
NameAndType	"<init>":()V
class	java/lang/Thread
NameAndType	currentThread:()Ljava/lang/Thread;
NameAndType	getContextClassLoader:()Ljava/lang/ClassLoader;
class	java/security/AccessController
NameAndType	getContext:()Ljava/security/AccessControlContext;
Asciz	java/lang/RuntimePermission;
Asciz	setContextClassLoader;
NameAndType	"<init>":(Ljava/lang/String;)V
class	java/security/AccessControlContext
NameAndType	checkPermission:(Ljava/security/Permission;)V
Asciz	scala/actors/threadpool/Executors$PrivilegedThreadFactory$1;
Asciz	;
NameAndType	"<init>":(Lscala/actors/threadpool/Executors$PrivilegedThreadFactory;Ljava/lang/Runnable;)V
NameAndType	newThread:(Ljava/lang/Runnable;)Ljava/lang/Thread;
class	scala/actors/threadpool/Executors
Asciz	scala/actors/threadpool/Executors$PrivilegedThreadFactory;
Asciz	scala/actors/threadpool/Executors$DefaultThreadFactory;
Asciz	DefaultThreadFactory;
Asciz	java/lang/Thread;
Asciz	currentThread;
Asciz	()Ljava/lang/Thread;;
Asciz	getContextClassLoader;
Asciz	()Ljava/lang/ClassLoader;;
Asciz	java/security/AccessController;
Asciz	getContext;
Asciz	()Ljava/security/AccessControlContext;;
Asciz	(Ljava/lang/String;)V;
Asciz	java/security/AccessControlContext;
Asciz	checkPermission;
Asciz	(Ljava/security/Permission;)V;
Asciz	(Lscala/actors/threadpool/Executors$PrivilegedThreadFactory;Ljava/lang/Runnable;)V;
Asciz	scala/actors/threadpool/Executors;

{
private final java.lang.ClassLoader ccl;
  Signature: Ljava/lang/ClassLoader;

private final java.security.AccessControlContext acc;
  Signature: Ljava/security/AccessControlContext;

scala.actors.threadpool.Executors$PrivilegedThreadFactory();
  Signature: ()V
  Code:
   Stack=4, Locals=1, Args_size=1
	aload_0
	invokespecial	Method scala/actors/threadpool/Executors$DefaultThreadFactory."<init>":()V
	aload_0
	invokestatic	Method java/lang/Thread.currentThread:()Ljava/lang/Thread;
	invokevirtual	Method java/lang/Thread.getContextClassLoader:()Ljava/lang/ClassLoader;
	putfield	Field ccl:Ljava/lang/ClassLoader;
	aload_0
	invokestatic	Method java/security/AccessController.getContext:()Ljava/security/AccessControlContext;
	putfield	Field acc:Ljava/security/AccessControlContext;
	aload_0
	getfield	Field acc:Ljava/security/AccessControlContext;
	new	class java/lang/RuntimePermission
	dup
	ldc	String setContextClassLoader
	invokespecial	Method java/lang/RuntimePermission."<init>":(Ljava/lang/String;)V
	invokevirtual	Method java/security/AccessControlContext.checkPermission:(Ljava/security/Permission;)V
	return
  Labels:

public java.lang.Thread newThread(java.lang.Runnable);
  Signature: (Ljava/lang/Runnable;)Ljava/lang/Thread;
  Code:
   Stack=5, Locals=2, Args_size=2
	aload_0
	new	class scala/actors/threadpool/Executors$PrivilegedThreadFactory$1
	dup
	aload_0
	aload_1
	invokespecial	Method scala/actors/threadpool/Executors$PrivilegedThreadFactory$1."<init>":(Lscala/actors/threadpool/Executors$PrivilegedThreadFactory;Ljava/lang/Runnable;)V
	invokespecial	Method scala/actors/threadpool/Executors$DefaultThreadFactory.newThread:(Ljava/lang/Runnable;)Ljava/lang/Thread;
	areturn
  Labels:

static java.lang.ClassLoader access$700(scala.actors.threadpool.Executors$PrivilegedThreadFactory);
  Signature: (Lscala/actors/threadpool/Executors$PrivilegedThreadFactory;)Ljava/lang/ClassLoader;
  Code:
   Stack=1, Locals=1, Args_size=1
	aload_0
	getfield	Field ccl:Ljava/lang/ClassLoader;
	areturn
  Labels:

static java.security.AccessControlContext access$800(scala.actors.threadpool.Executors$PrivilegedThreadFactory);
  Signature: (Lscala/actors/threadpool/Executors$PrivilegedThreadFactory;)Ljava/security/AccessControlContext;
  Code:
   Stack=1, Locals=1, Args_size=1
	aload_0
	getfield	Field acc:Ljava/security/AccessControlContext;
	areturn
  Labels:

}

