class scala.actors.threadpool.Executors$DelegatedExecutorService extends scala.actors.threadpool.AbstractExecutorService
  InnerClass: 
   DelegatedExecutorService=class scala/actors/threadpool/Executors$DelegatedExecutorService of class scala/actors/threadpool/Executors
  minor version: 0
  major version: 49
  Constant pool:
Method	scala/actors/threadpool/AbstractExecutorService."<init>":()V
Field	scala/actors/threadpool/Executors$DelegatedExecutorService.e:Lscala/actors/threadpool/ExecutorService;
InterfaceMethod	scala/actors/threadpool/ExecutorService.execute:(Ljava/lang/Runnable;)V
InterfaceMethod	scala/actors/threadpool/ExecutorService.shutdown:()V
InterfaceMethod	scala/actors/threadpool/ExecutorService.shutdownNow:()Ljava/util/List;
InterfaceMethod	scala/actors/threadpool/ExecutorService.isShutdown:()Z
InterfaceMethod	scala/actors/threadpool/ExecutorService.isTerminated:()Z
InterfaceMethod	scala/actors/threadpool/ExecutorService.awaitTermination:(JLscala/actors/threadpool/TimeUnit;)Z
InterfaceMethod	scala/actors/threadpool/ExecutorService.submit:(Ljava/lang/Runnable;)Lscala/actors/threadpool/Future;
InterfaceMethod	scala/actors/threadpool/ExecutorService.submit:(Lscala/actors/threadpool/Callable;)Lscala/actors/threadpool/Future;
InterfaceMethod	scala/actors/threadpool/ExecutorService.submit:(Ljava/lang/Runnable;Ljava/lang/Object;)Lscala/actors/threadpool/Future;
InterfaceMethod	scala/actors/threadpool/ExecutorService.invokeAll:(Ljava/util/Collection;)Ljava/util/List;
InterfaceMethod	scala/actors/threadpool/ExecutorService.invokeAll:(Ljava/util/Collection;JLscala/actors/threadpool/TimeUnit;)Ljava/util/List;
InterfaceMethod	scala/actors/threadpool/ExecutorService.invokeAny:(Ljava/util/Collection;)Ljava/lang/Object;
InterfaceMethod	scala/actors/threadpool/ExecutorService.invokeAny:(Ljava/util/Collection;JLscala/actors/threadpool/TimeUnit;)Ljava/lang/Object;
class	scala/actors/threadpool/Executors$DelegatedExecutorService
class	scala/actors/threadpool/AbstractExecutorService
Asciz	e;
Asciz	Lscala/actors/threadpool/ExecutorService;;
Asciz	<init>;
Asciz	(Lscala/actors/threadpool/ExecutorService;)V;
Asciz	Code;
Asciz	execute;
Asciz	(Ljava/lang/Runnable;)V;
Asciz	shutdown;
Asciz	()V;
Asciz	shutdownNow;
Asciz	()Ljava/util/List;;
Asciz	isShutdown;
Asciz	()Z;
Asciz	isTerminated;
Asciz	awaitTermination;
Asciz	(JLscala/actors/threadpool/TimeUnit;)Z;
Asciz	Exceptions;
class	java/lang/InterruptedException
Asciz	submit;
Asciz	(Ljava/lang/Runnable;)Lscala/actors/threadpool/Future;;
Asciz	(Lscala/actors/threadpool/Callable;)Lscala/actors/threadpool/Future;;
Asciz	(Ljava/lang/Runnable;Ljava/lang/Object;)Lscala/actors/threadpool/Future;;
Asciz	invokeAll;
Asciz	(Ljava/util/Collection;)Ljava/util/List;;
Asciz	(Ljava/util/Collection;JLscala/actors/threadpool/TimeUnit;)Ljava/util/List;;
Asciz	invokeAny;
Asciz	(Ljava/util/Collection;)Ljava/lang/Object;;
class	scala/actors/threadpool/ExecutionException
Asciz	(Ljava/util/Collection;JLscala/actors/threadpool/TimeUnit;)Ljava/lang/Object;;
class	scala/actors/threadpool/TimeoutException
NameAndType	"<init>":()V
NameAndType	e:Lscala/actors/threadpool/ExecutorService;
class	scala/actors/threadpool/ExecutorService
NameAndType	execute:(Ljava/lang/Runnable;)V
NameAndType	shutdown:()V
NameAndType	shutdownNow:()Ljava/util/List;
NameAndType	isShutdown:()Z
NameAndType	isTerminated:()Z
NameAndType	awaitTermination:(JLscala/actors/threadpool/TimeUnit;)Z
NameAndType	submit:(Ljava/lang/Runnable;)Lscala/actors/threadpool/Future;
NameAndType	submit:(Lscala/actors/threadpool/Callable;)Lscala/actors/threadpool/Future;
NameAndType	submit:(Ljava/lang/Runnable;Ljava/lang/Object;)Lscala/actors/threadpool/Future;
NameAndType	invokeAll:(Ljava/util/Collection;)Ljava/util/List;
NameAndType	invokeAll:(Ljava/util/Collection;JLscala/actors/threadpool/TimeUnit;)Ljava/util/List;
NameAndType	invokeAny:(Ljava/util/Collection;)Ljava/lang/Object;
NameAndType	invokeAny:(Ljava/util/Collection;JLscala/actors/threadpool/TimeUnit;)Ljava/lang/Object;
class	scala/actors/threadpool/Executors
Asciz	scala/actors/threadpool/Executors$DelegatedExecutorService;
Asciz	DelegatedExecutorService;
Asciz	InnerClasses;
Asciz	scala/actors/threadpool/AbstractExecutorService;
Asciz	java/lang/InterruptedException;
Asciz	scala/actors/threadpool/ExecutionException;
Asciz	scala/actors/threadpool/TimeoutException;
Asciz	scala/actors/threadpool/ExecutorService;
Asciz	scala/actors/threadpool/Executors;

{
private final scala.actors.threadpool.ExecutorService e;
  Signature: Lscala/actors/threadpool/ExecutorService;

scala.actors.threadpool.Executors$DelegatedExecutorService(scala.actors.threadpool.ExecutorService);
  Signature: (Lscala/actors/threadpool/ExecutorService;)V
  Code:
   Stack=2, Locals=2, Args_size=2
	aload_0
	invokespecial	Method scala/actors/threadpool/AbstractExecutorService."<init>":()V
	aload_0
	aload_1
	putfield	Field e:Lscala/actors/threadpool/ExecutorService;
	return
  Labels:

public void execute(java.lang.Runnable);
  Signature: (Ljava/lang/Runnable;)V
  Code:
   Stack=2, Locals=2, Args_size=2
	aload_0
	getfield	Field e:Lscala/actors/threadpool/ExecutorService;
	aload_1
	invokeinterface	InterfaceMethod scala/actors/threadpool/ExecutorService.execute:(Ljava/lang/Runnable;)V
	return
  Labels:

public void shutdown();
  Signature: ()V
  Code:
   Stack=1, Locals=1, Args_size=1
	aload_0
	getfield	Field e:Lscala/actors/threadpool/ExecutorService;
	invokeinterface	InterfaceMethod scala/actors/threadpool/ExecutorService.shutdown:()V
	return
  Labels:

public java.util.List shutdownNow();
  Signature: ()Ljava/util/List;
  Code:
   Stack=1, Locals=1, Args_size=1
	aload_0
	getfield	Field e:Lscala/actors/threadpool/ExecutorService;
	invokeinterface	InterfaceMethod scala/actors/threadpool/ExecutorService.shutdownNow:()Ljava/util/List;
	areturn
  Labels:

public boolean isShutdown();
  Signature: ()Z
  Code:
   Stack=1, Locals=1, Args_size=1
	aload_0
	getfield	Field e:Lscala/actors/threadpool/ExecutorService;
	invokeinterface	InterfaceMethod scala/actors/threadpool/ExecutorService.isShutdown:()Z
	ireturn
  Labels:

public boolean isTerminated();
  Signature: ()Z
  Code:
   Stack=1, Locals=1, Args_size=1
	aload_0
	getfield	Field e:Lscala/actors/threadpool/ExecutorService;
	invokeinterface	InterfaceMethod scala/actors/threadpool/ExecutorService.isTerminated:()Z
	ireturn
  Labels:

public boolean awaitTermination(long, scala.actors.threadpool.TimeUnit)   throws java.lang.InterruptedException;
  Signature: (JLscala/actors/threadpool/TimeUnit;)Z
  Code:
   Stack=4, Locals=4, Args_size=3
	aload_0
	getfield	Field e:Lscala/actors/threadpool/ExecutorService;
	lload_1
	aload_3
	invokeinterface	InterfaceMethod scala/actors/threadpool/ExecutorService.awaitTermination:(JLscala/actors/threadpool/TimeUnit;)Z
	ireturn
  Labels:
  Exceptions: 
   throws java.lang.InterruptedException
public scala.actors.threadpool.Future submit(java.lang.Runnable);
  Signature: (Ljava/lang/Runnable;)Lscala/actors/threadpool/Future;
  Code:
   Stack=2, Locals=2, Args_size=2
	aload_0
	getfield	Field e:Lscala/actors/threadpool/ExecutorService;
	aload_1
	invokeinterface	InterfaceMethod scala/actors/threadpool/ExecutorService.submit:(Ljava/lang/Runnable;)Lscala/actors/threadpool/Future;
	areturn
  Labels:

public scala.actors.threadpool.Future submit(scala.actors.threadpool.Callable);
  Signature: (Lscala/actors/threadpool/Callable;)Lscala/actors/threadpool/Future;
  Code:
   Stack=2, Locals=2, Args_size=2
	aload_0
	getfield	Field e:Lscala/actors/threadpool/ExecutorService;
	aload_1
	invokeinterface	InterfaceMethod scala/actors/threadpool/ExecutorService.submit:(Lscala/actors/threadpool/Callable;)Lscala/actors/threadpool/Future;
	areturn
  Labels:

public scala.actors.threadpool.Future submit(java.lang.Runnable, java.lang.Object);
  Signature: (Ljava/lang/Runnable;Ljava/lang/Object;)Lscala/actors/threadpool/Future;
  Code:
   Stack=3, Locals=3, Args_size=3
	aload_0
	getfield	Field e:Lscala/actors/threadpool/ExecutorService;
	aload_1
	aload_2
	invokeinterface	InterfaceMethod scala/actors/threadpool/ExecutorService.submit:(Ljava/lang/Runnable;Ljava/lang/Object;)Lscala/actors/threadpool/Future;
	areturn
  Labels:

public java.util.List invokeAll(java.util.Collection)   throws java.lang.InterruptedException;
  Signature: (Ljava/util/Collection;)Ljava/util/List;
  Code:
   Stack=2, Locals=2, Args_size=2
	aload_0
	getfield	Field e:Lscala/actors/threadpool/ExecutorService;
	aload_1
	invokeinterface	InterfaceMethod scala/actors/threadpool/ExecutorService.invokeAll:(Ljava/util/Collection;)Ljava/util/List;
	areturn
  Labels:
  Exceptions: 
   throws java.lang.InterruptedException
public java.util.List invokeAll(java.util.Collection, long, scala.actors.threadpool.TimeUnit)   throws java.lang.InterruptedException;
  Signature: (Ljava/util/Collection;JLscala/actors/threadpool/TimeUnit;)Ljava/util/List;
  Code:
   Stack=5, Locals=5, Args_size=4
	aload_0
	getfield	Field e:Lscala/actors/threadpool/ExecutorService;
	aload_1
	lload_2
	aload	4
	invokeinterface	InterfaceMethod scala/actors/threadpool/ExecutorService.invokeAll:(Ljava/util/Collection;JLscala/actors/threadpool/TimeUnit;)Ljava/util/List;
	areturn
  Labels:
  Exceptions: 
   throws java.lang.InterruptedException
public java.lang.Object invokeAny(java.util.Collection)   throws java.lang.InterruptedException, scala.actors.threadpool.ExecutionException;
  Signature: (Ljava/util/Collection;)Ljava/lang/Object;
  Code:
   Stack=2, Locals=2, Args_size=2
	aload_0
	getfield	Field e:Lscala/actors/threadpool/ExecutorService;
	aload_1
	invokeinterface	InterfaceMethod scala/actors/threadpool/ExecutorService.invokeAny:(Ljava/util/Collection;)Ljava/lang/Object;
	areturn
  Labels:
  Exceptions: 
   throws java.lang.InterruptedException, scala.actors.threadpool.ExecutionException
public java.lang.Object invokeAny(java.util.Collection, long, scala.actors.threadpool.TimeUnit)   throws java.lang.InterruptedException, scala.actors.threadpool.ExecutionException, scala.actors.threadpool.TimeoutException;
  Signature: (Ljava/util/Collection;JLscala/actors/threadpool/TimeUnit;)Ljava/lang/Object;
  Code:
   Stack=5, Locals=5, Args_size=4
	aload_0
	getfield	Field e:Lscala/actors/threadpool/ExecutorService;
	aload_1
	lload_2
	aload	4
	invokeinterface	InterfaceMethod scala/actors/threadpool/ExecutorService.invokeAny:(Ljava/util/Collection;JLscala/actors/threadpool/TimeUnit;)Ljava/lang/Object;
	areturn
  Labels:
  Exceptions: 
   throws java.lang.InterruptedException, scala.actors.threadpool.ExecutionException, scala.actors.threadpool.TimeoutException
}

