public class scala.actors.threadpool.Executors extends java.lang.Object
  InnerClass: 
   FinalizableDelegatedExecutorService=class scala/actors/threadpool/Executors$FinalizableDelegatedExecutorService of class scala/actors/threadpool/Executors
   DelegatedExecutorService=class scala/actors/threadpool/Executors$DelegatedExecutorService of class scala/actors/threadpool/Executors
   PrivilegedThreadFactory=class scala/actors/threadpool/Executors$PrivilegedThreadFactory of class scala/actors/threadpool/Executors
   DefaultThreadFactory=class scala/actors/threadpool/Executors$DefaultThreadFactory of class scala/actors/threadpool/Executors
   final PrivilegedCallableUsingCurrentClassLoader=class scala/actors/threadpool/Executors$PrivilegedCallableUsingCurrentClassLoader of class scala/actors/threadpool/Executors
   final PrivilegedCallable=class scala/actors/threadpool/Executors$PrivilegedCallable of class scala/actors/threadpool/Executors
   final RunnableAdapter=class scala/actors/threadpool/Executors$RunnableAdapter of class scala/actors/threadpool/Executors
   class scala/actors/threadpool/Executors$1
   class scala/actors/threadpool/Executors$2
  minor version: 0
  major version: 49
  Constant pool:
class	scala/actors/threadpool/ThreadPoolExecutor
Field	scala/actors/threadpool/TimeUnit.MILLISECONDS:Lscala/actors/threadpool/TimeUnit;
class	scala/actors/threadpool/LinkedBlockingQueue
Method	scala/actors/threadpool/LinkedBlockingQueue."<init>":()V
Method	scala/actors/threadpool/ThreadPoolExecutor."<init>":(IIJLscala/actors/threadpool/TimeUnit;Lscala/actors/threadpool/BlockingQueue;)V
Method	scala/actors/threadpool/ThreadPoolExecutor."<init>":(IIJLscala/actors/threadpool/TimeUnit;Lscala/actors/threadpool/BlockingQueue;Lscala/actors/threadpool/ThreadFactory;)V
class	scala/actors/threadpool/Executors$FinalizableDelegatedExecutorService
Method	scala/actors/threadpool/Executors$FinalizableDelegatedExecutorService."<init>":(Lscala/actors/threadpool/ExecutorService;)V
int	2147483647;
long	60l;
Field	scala/actors/threadpool/TimeUnit.SECONDS:Lscala/actors/threadpool/TimeUnit;
class	scala/actors/threadpool/SynchronousQueue
Method	scala/actors/threadpool/SynchronousQueue."<init>":()V
class	java/lang/NullPointerException
Method	java/lang/NullPointerException."<init>":()V
class	scala/actors/threadpool/Executors$DelegatedExecutorService
Method	scala/actors/threadpool/Executors$DelegatedExecutorService."<init>":(Lscala/actors/threadpool/ExecutorService;)V
class	scala/actors/threadpool/Executors$DefaultThreadFactory
Method	scala/actors/threadpool/Executors$DefaultThreadFactory."<init>":()V
class	scala/actors/threadpool/Executors$PrivilegedThreadFactory
Method	scala/actors/threadpool/Executors$PrivilegedThreadFactory."<init>":()V
class	scala/actors/threadpool/Executors$RunnableAdapter
Method	scala/actors/threadpool/Executors$RunnableAdapter."<init>":(Ljava/lang/Runnable;Ljava/lang/Object;)V
class	scala/actors/threadpool/Executors$1
Method	scala/actors/threadpool/Executors$1."<init>":(Ljava/security/PrivilegedAction;)V
class	scala/actors/threadpool/Executors$2
Method	scala/actors/threadpool/Executors$2."<init>":(Ljava/security/PrivilegedExceptionAction;)V
class	scala/actors/threadpool/Executors$PrivilegedCallable
Method	scala/actors/threadpool/Executors$PrivilegedCallable."<init>":(Lscala/actors/threadpool/Callable;)V
class	scala/actors/threadpool/Executors$PrivilegedCallableUsingCurrentClassLoader
Method	scala/actors/threadpool/Executors$PrivilegedCallableUsingCurrentClassLoader."<init>":(Lscala/actors/threadpool/Callable;)V
Method	java/lang/Object."<init>":()V
class	scala/actors/threadpool/Executors
class	java/lang/Object
Asciz	FinalizableDelegatedExecutorService;
Asciz	InnerClasses;
Asciz	DelegatedExecutorService;
Asciz	PrivilegedThreadFactory;
Asciz	DefaultThreadFactory;
Asciz	PrivilegedCallableUsingCurrentClassLoader;
Asciz	PrivilegedCallable;
Asciz	RunnableAdapter;
Asciz	newFixedThreadPool;
Asciz	(I)Lscala/actors/threadpool/ExecutorService;;
Asciz	Code;
Asciz	(ILscala/actors/threadpool/ThreadFactory;)Lscala/actors/threadpool/ExecutorService;;
Asciz	newSingleThreadExecutor;
Asciz	()Lscala/actors/threadpool/ExecutorService;;
Asciz	(Lscala/actors/threadpool/ThreadFactory;)Lscala/actors/threadpool/ExecutorService;;
Asciz	newCachedThreadPool;
Asciz	unconfigurableExecutorService;
Asciz	(Lscala/actors/threadpool/ExecutorService;)Lscala/actors/threadpool/ExecutorService;;
Asciz	defaultThreadFactory;
Asciz	()Lscala/actors/threadpool/ThreadFactory;;
Asciz	privilegedThreadFactory;
Asciz	callable;
Asciz	(Ljava/lang/Runnable;Ljava/lang/Object;)Lscala/actors/threadpool/Callable;;
Asciz	(Ljava/lang/Runnable;)Lscala/actors/threadpool/Callable;;
Asciz	(Ljava/security/PrivilegedAction;)Lscala/actors/threadpool/Callable;;
Asciz	(Ljava/security/PrivilegedExceptionAction;)Lscala/actors/threadpool/Callable;;
Asciz	privilegedCallable;
Asciz	(Lscala/actors/threadpool/Callable;)Lscala/actors/threadpool/Callable;;
Asciz	privilegedCallableUsingCurrentClassLoader;
Asciz	<init>;
Asciz	()V;
Asciz	scala/actors/threadpool/ThreadPoolExecutor;
class	scala/actors/threadpool/TimeUnit
NameAndType	MILLISECONDS:Lscala/actors/threadpool/TimeUnit;
Asciz	scala/actors/threadpool/LinkedBlockingQueue;
NameAndType	"<init>":()V
NameAndType	"<init>":(IIJLscala/actors/threadpool/TimeUnit;Lscala/actors/threadpool/BlockingQueue;)V
NameAndType	"<init>":(IIJLscala/actors/threadpool/TimeUnit;Lscala/actors/threadpool/BlockingQueue;Lscala/actors/threadpool/ThreadFactory;)V
Asciz	scala/actors/threadpool/Executors$FinalizableDelegatedExecutorService;
NameAndType	"<init>":(Lscala/actors/threadpool/ExecutorService;)V
NameAndType	SECONDS:Lscala/actors/threadpool/TimeUnit;
Asciz	scala/actors/threadpool/SynchronousQueue;
Asciz	java/lang/NullPointerException;
Asciz	scala/actors/threadpool/Executors$DelegatedExecutorService;
Asciz	scala/actors/threadpool/Executors$DefaultThreadFactory;
Asciz	scala/actors/threadpool/Executors$PrivilegedThreadFactory;
Asciz	scala/actors/threadpool/Executors$RunnableAdapter;
NameAndType	"<init>":(Ljava/lang/Runnable;Ljava/lang/Object;)V
Asciz	scala/actors/threadpool/Executors$1;
Asciz	;
NameAndType	"<init>":(Ljava/security/PrivilegedAction;)V
Asciz	scala/actors/threadpool/Executors$2;
NameAndType	"<init>":(Ljava/security/PrivilegedExceptionAction;)V
Asciz	scala/actors/threadpool/Executors$PrivilegedCallable;
NameAndType	"<init>":(Lscala/actors/threadpool/Callable;)V
Asciz	scala/actors/threadpool/Executors$PrivilegedCallableUsingCurrentClassLoader;
Asciz	scala/actors/threadpool/Executors;
Asciz	java/lang/Object;
Asciz	scala/actors/threadpool/TimeUnit;
Asciz	MILLISECONDS;
Asciz	Lscala/actors/threadpool/TimeUnit;;
Asciz	(IIJLscala/actors/threadpool/TimeUnit;Lscala/actors/threadpool/BlockingQueue;)V;
Asciz	(IIJLscala/actors/threadpool/TimeUnit;Lscala/actors/threadpool/BlockingQueue;Lscala/actors/threadpool/ThreadFactory;)V;
Asciz	(Lscala/actors/threadpool/ExecutorService;)V;
Asciz	SECONDS;
Asciz	(Ljava/lang/Runnable;Ljava/lang/Object;)V;
Asciz	(Ljava/security/PrivilegedAction;)V;
Asciz	(Ljava/security/PrivilegedExceptionAction;)V;
Asciz	(Lscala/actors/threadpool/Callable;)V;

{
public static scala.actors.threadpool.ExecutorService newFixedThreadPool(int);
  Signature: (I)Lscala/actors/threadpool/ExecutorService;
  Code:
   Stack=9, Locals=1, Args_size=1
	new	class scala/actors/threadpool/ThreadPoolExecutor
	dup
	iload_0
	iload_0
	lconst_0
	getstatic	Field scala/actors/threadpool/TimeUnit.MILLISECONDS:Lscala/actors/threadpool/TimeUnit;
	new	class scala/actors/threadpool/LinkedBlockingQueue
	dup
	invokespecial	Method scala/actors/threadpool/LinkedBlockingQueue."<init>":()V
	invokespecial	Method scala/actors/threadpool/ThreadPoolExecutor."<init>":(IIJLscala/actors/threadpool/TimeUnit;Lscala/actors/threadpool/BlockingQueue;)V
	areturn
  Labels:

public static scala.actors.threadpool.ExecutorService newFixedThreadPool(int, scala.actors.threadpool.ThreadFactory);
  Signature: (ILscala/actors/threadpool/ThreadFactory;)Lscala/actors/threadpool/ExecutorService;
  Code:
   Stack=9, Locals=2, Args_size=2
	new	class scala/actors/threadpool/ThreadPoolExecutor
	dup
	iload_0
	iload_0
	lconst_0
	getstatic	Field scala/actors/threadpool/TimeUnit.MILLISECONDS:Lscala/actors/threadpool/TimeUnit;
	new	class scala/actors/threadpool/LinkedBlockingQueue
	dup
	invokespecial	Method scala/actors/threadpool/LinkedBlockingQueue."<init>":()V
	aload_1
	invokespecial	Method scala/actors/threadpool/ThreadPoolExecutor."<init>":(IIJLscala/actors/threadpool/TimeUnit;Lscala/actors/threadpool/BlockingQueue;Lscala/actors/threadpool/ThreadFactory;)V
	areturn
  Labels:

public static scala.actors.threadpool.ExecutorService newSingleThreadExecutor();
  Signature: ()Lscala/actors/threadpool/ExecutorService;
  Code:
   Stack=11, Locals=0, Args_size=0
	new	class scala/actors/threadpool/Executors$FinalizableDelegatedExecutorService
	dup
	new	class scala/actors/threadpool/ThreadPoolExecutor
	dup
	iconst_1
	iconst_1
	lconst_0
	getstatic	Field scala/actors/threadpool/TimeUnit.MILLISECONDS:Lscala/actors/threadpool/TimeUnit;
	new	class scala/actors/threadpool/LinkedBlockingQueue
	dup
	invokespecial	Method scala/actors/threadpool/LinkedBlockingQueue."<init>":()V
	invokespecial	Method scala/actors/threadpool/ThreadPoolExecutor."<init>":(IIJLscala/actors/threadpool/TimeUnit;Lscala/actors/threadpool/BlockingQueue;)V
	invokespecial	Method scala/actors/threadpool/Executors$FinalizableDelegatedExecutorService."<init>":(Lscala/actors/threadpool/ExecutorService;)V
	areturn
  Labels:

public static scala.actors.threadpool.ExecutorService newSingleThreadExecutor(scala.actors.threadpool.ThreadFactory);
  Signature: (Lscala/actors/threadpool/ThreadFactory;)Lscala/actors/threadpool/ExecutorService;
  Code:
   Stack=11, Locals=1, Args_size=1
	new	class scala/actors/threadpool/Executors$FinalizableDelegatedExecutorService
	dup
	new	class scala/actors/threadpool/ThreadPoolExecutor
	dup
	iconst_1
	iconst_1
	lconst_0
	getstatic	Field scala/actors/threadpool/TimeUnit.MILLISECONDS:Lscala/actors/threadpool/TimeUnit;
	new	class scala/actors/threadpool/LinkedBlockingQueue
	dup
	invokespecial	Method scala/actors/threadpool/LinkedBlockingQueue."<init>":()V
	aload_0
	invokespecial	Method scala/actors/threadpool/ThreadPoolExecutor."<init>":(IIJLscala/actors/threadpool/TimeUnit;Lscala/actors/threadpool/BlockingQueue;Lscala/actors/threadpool/ThreadFactory;)V
	invokespecial	Method scala/actors/threadpool/Executors$FinalizableDelegatedExecutorService."<init>":(Lscala/actors/threadpool/ExecutorService;)V
	areturn
  Labels:

public static scala.actors.threadpool.ExecutorService newCachedThreadPool();
  Signature: ()Lscala/actors/threadpool/ExecutorService;
  Code:
   Stack=9, Locals=0, Args_size=0
	new	class scala/actors/threadpool/ThreadPoolExecutor
	dup
	iconst_0
	ldc	int 2147483647
	ldc2_w	long 60l
	getstatic	Field scala/actors/threadpool/TimeUnit.SECONDS:Lscala/actors/threadpool/TimeUnit;
	new	class scala/actors/threadpool/SynchronousQueue
	dup
	invokespecial	Method scala/actors/threadpool/SynchronousQueue."<init>":()V
	invokespecial	Method scala/actors/threadpool/ThreadPoolExecutor."<init>":(IIJLscala/actors/threadpool/TimeUnit;Lscala/actors/threadpool/BlockingQueue;)V
	areturn
  Labels:

public static scala.actors.threadpool.ExecutorService newCachedThreadPool(scala.actors.threadpool.ThreadFactory);
  Signature: (Lscala/actors/threadpool/ThreadFactory;)Lscala/actors/threadpool/ExecutorService;
  Code:
   Stack=9, Locals=1, Args_size=1
	new	class scala/actors/threadpool/ThreadPoolExecutor
	dup
	iconst_0
	ldc	int 2147483647
	ldc2_w	long 60l
	getstatic	Field scala/actors/threadpool/TimeUnit.SECONDS:Lscala/actors/threadpool/TimeUnit;
	new	class scala/actors/threadpool/SynchronousQueue
	dup
	invokespecial	Method scala/actors/threadpool/SynchronousQueue."<init>":()V
	aload_0
	invokespecial	Method scala/actors/threadpool/ThreadPoolExecutor."<init>":(IIJLscala/actors/threadpool/TimeUnit;Lscala/actors/threadpool/BlockingQueue;Lscala/actors/threadpool/ThreadFactory;)V
	areturn
  Labels:

public static scala.actors.threadpool.ExecutorService unconfigurableExecutorService(scala.actors.threadpool.ExecutorService);
  Signature: (Lscala/actors/threadpool/ExecutorService;)Lscala/actors/threadpool/ExecutorService;
  Code:
   Stack=3, Locals=1, Args_size=1
	aload_0
	ifnonnull	l1 // new
	new	class java/lang/NullPointerException
	dup
	invokespecial	Method java/lang/NullPointerException."<init>":()V
	athrow
l1	new	class scala/actors/threadpool/Executors$DelegatedExecutorService
	dup
	aload_0
	invokespecial	Method scala/actors/threadpool/Executors$DelegatedExecutorService."<init>":(Lscala/actors/threadpool/ExecutorService;)V
	areturn
  Labels:
   	l1 = 12 // new

public static scala.actors.threadpool.ThreadFactory defaultThreadFactory();
  Signature: ()Lscala/actors/threadpool/ThreadFactory;
  Code:
   Stack=2, Locals=0, Args_size=0
	new	class scala/actors/threadpool/Executors$DefaultThreadFactory
	dup
	invokespecial	Method scala/actors/threadpool/Executors$DefaultThreadFactory."<init>":()V
	areturn
  Labels:

public static scala.actors.threadpool.ThreadFactory privilegedThreadFactory();
  Signature: ()Lscala/actors/threadpool/ThreadFactory;
  Code:
   Stack=2, Locals=0, Args_size=0
	new	class scala/actors/threadpool/Executors$PrivilegedThreadFactory
	dup
	invokespecial	Method scala/actors/threadpool/Executors$PrivilegedThreadFactory."<init>":()V
	areturn
  Labels:

public static scala.actors.threadpool.Callable callable(java.lang.Runnable, java.lang.Object);
  Signature: (Ljava/lang/Runnable;Ljava/lang/Object;)Lscala/actors/threadpool/Callable;
  Code:
   Stack=4, Locals=2, Args_size=2
	aload_0
	ifnonnull	l1 // new
	new	class java/lang/NullPointerException
	dup
	invokespecial	Method java/lang/NullPointerException."<init>":()V
	athrow
l1	new	class scala/actors/threadpool/Executors$RunnableAdapter
	dup
	aload_0
	aload_1
	invokespecial	Method scala/actors/threadpool/Executors$RunnableAdapter."<init>":(Ljava/lang/Runnable;Ljava/lang/Object;)V
	areturn
  Labels:
   	l1 = 12 // new

public static scala.actors.threadpool.Callable callable(java.lang.Runnable);
  Signature: (Ljava/lang/Runnable;)Lscala/actors/threadpool/Callable;
  Code:
   Stack=4, Locals=1, Args_size=1
	aload_0
	ifnonnull	l1 // new
	new	class java/lang/NullPointerException
	dup
	invokespecial	Method java/lang/NullPointerException."<init>":()V
	athrow
l1	new	class scala/actors/threadpool/Executors$RunnableAdapter
	dup
	aload_0
	aconst_null
	invokespecial	Method scala/actors/threadpool/Executors$RunnableAdapter."<init>":(Ljava/lang/Runnable;Ljava/lang/Object;)V
	areturn
  Labels:
   	l1 = 12 // new

public static scala.actors.threadpool.Callable callable(java.security.PrivilegedAction);
  Signature: (Ljava/security/PrivilegedAction;)Lscala/actors/threadpool/Callable;
  Code:
   Stack=3, Locals=1, Args_size=1
	aload_0
	ifnonnull	l1 // new
	new	class java/lang/NullPointerException
	dup
	invokespecial	Method java/lang/NullPointerException."<init>":()V
	athrow
l1	new	class scala/actors/threadpool/Executors$1
	dup
	aload_0
	invokespecial	Method scala/actors/threadpool/Executors$1."<init>":(Ljava/security/PrivilegedAction;)V
	areturn
  Labels:
   	l1 = 12 // new

public static scala.actors.threadpool.Callable callable(java.security.PrivilegedExceptionAction);
  Signature: (Ljava/security/PrivilegedExceptionAction;)Lscala/actors/threadpool/Callable;
  Code:
   Stack=3, Locals=1, Args_size=1
	aload_0
	ifnonnull	l1 // new
	new	class java/lang/NullPointerException
	dup
	invokespecial	Method java/lang/NullPointerException."<init>":()V
	athrow
l1	new	class scala/actors/threadpool/Executors$2
	dup
	aload_0
	invokespecial	Method scala/actors/threadpool/Executors$2."<init>":(Ljava/security/PrivilegedExceptionAction;)V
	areturn
  Labels:
   	l1 = 12 // new

public static scala.actors.threadpool.Callable privilegedCallable(scala.actors.threadpool.Callable);
  Signature: (Lscala/actors/threadpool/Callable;)Lscala/actors/threadpool/Callable;
  Code:
   Stack=3, Locals=1, Args_size=1
	aload_0
	ifnonnull	l1 // new
	new	class java/lang/NullPointerException
	dup
	invokespecial	Method java/lang/NullPointerException."<init>":()V
	athrow
l1	new	class scala/actors/threadpool/Executors$PrivilegedCallable
	dup
	aload_0
	invokespecial	Method scala/actors/threadpool/Executors$PrivilegedCallable."<init>":(Lscala/actors/threadpool/Callable;)V
	areturn
  Labels:
   	l1 = 12 // new

public static scala.actors.threadpool.Callable privilegedCallableUsingCurrentClassLoader(scala.actors.threadpool.Callable);
  Signature: (Lscala/actors/threadpool/Callable;)Lscala/actors/threadpool/Callable;
  Code:
   Stack=3, Locals=1, Args_size=1
	aload_0
	ifnonnull	l1 // new
	new	class java/lang/NullPointerException
	dup
	invokespecial	Method java/lang/NullPointerException."<init>":()V
	athrow
l1	new	class scala/actors/threadpool/Executors$PrivilegedCallableUsingCurrentClassLoader
	dup
	aload_0
	invokespecial	Method scala/actors/threadpool/Executors$PrivilegedCallableUsingCurrentClassLoader."<init>":(Lscala/actors/threadpool/Callable;)V
	areturn
  Labels:
   	l1 = 12 // new

private scala.actors.threadpool.Executors();
  Signature: ()V
  Code:
   Stack=1, Locals=1, Args_size=1
	aload_0
	invokespecial	Method java/lang/Object."<init>":()V
	return
  Labels:

}

