final class scala.actors.threadpool.Executors$PrivilegedCallableUsingCurrentClassLoader extends java.lang.Object implements scala.actors.threadpool.Callable
  InnerClass: 
   final PrivilegedCallableUsingCurrentClassLoader=class scala/actors/threadpool/Executors$PrivilegedCallableUsingCurrentClassLoader of class scala/actors/threadpool/Executors
   class scala/actors/threadpool/Executors$PrivilegedCallableUsingCurrentClassLoader$1
  minor version: 0
  major version: 49
  Constant pool:
Field	scala/actors/threadpool/Executors$PrivilegedCallableUsingCurrentClassLoader.exception:Ljava/lang/Exception;
Field	scala/actors/threadpool/Executors$PrivilegedCallableUsingCurrentClassLoader.task:Lscala/actors/threadpool/Callable;
Field	scala/actors/threadpool/Executors$PrivilegedCallableUsingCurrentClassLoader.result:Ljava/lang/Object;
Field	scala/actors/threadpool/Executors$PrivilegedCallableUsingCurrentClassLoader.ccl:Ljava/lang/ClassLoader;
Method	java/lang/Object."<init>":()V
Method	java/lang/Thread.currentThread:()Ljava/lang/Thread;
Method	java/lang/Thread.getContextClassLoader:()Ljava/lang/ClassLoader;
Method	java/security/AccessController.getContext:()Ljava/security/AccessControlContext;
Field	scala/actors/threadpool/Executors$PrivilegedCallableUsingCurrentClassLoader.acc:Ljava/security/AccessControlContext;
class	java/lang/RuntimePermission
String	getContextClassLoader
Method	java/lang/RuntimePermission."<init>":(Ljava/lang/String;)V
Method	java/security/AccessControlContext.checkPermission:(Ljava/security/Permission;)V
String	setContextClassLoader
class	scala/actors/threadpool/Executors$PrivilegedCallableUsingCurrentClassLoader$1
Method	scala/actors/threadpool/Executors$PrivilegedCallableUsingCurrentClassLoader$1."<init>":(Lscala/actors/threadpool/Executors$PrivilegedCallableUsingCurrentClassLoader;)V
Method	java/security/AccessController.doPrivileged:(Ljava/security/PrivilegedAction;Ljava/security/AccessControlContext;)Ljava/lang/Object;
class	scala/actors/threadpool/Executors$PrivilegedCallableUsingCurrentClassLoader
class	java/lang/Object
class	scala/actors/threadpool/Callable
Asciz	ccl;
Asciz	Ljava/lang/ClassLoader;;
Asciz	acc;
Asciz	Ljava/security/AccessControlContext;;
Asciz	task;
Asciz	Lscala/actors/threadpool/Callable;;
Asciz	result;
Asciz	Ljava/lang/Object;;
Asciz	exception;
Asciz	Ljava/lang/Exception;;
Asciz	<init>;
Asciz	(Lscala/actors/threadpool/Callable;)V;
Asciz	Code;
Asciz	call;
Asciz	()Ljava/lang/Object;;
Asciz	Exceptions;
class	java/lang/Exception
Asciz	access$300;
Asciz	PrivilegedCallableUsingCurrentClassLoader;
Asciz	InnerClasses;
Asciz	(Lscala/actors/threadpool/Executors$PrivilegedCallableUsingCurrentClassLoader;)Ljava/lang/ClassLoader;;
Asciz	access$402;
Asciz	(Lscala/actors/threadpool/Executors$PrivilegedCallableUsingCurrentClassLoader;Ljava/lang/Object;)Ljava/lang/Object;;
Asciz	access$500;
Asciz	(Lscala/actors/threadpool/Executors$PrivilegedCallableUsingCurrentClassLoader;)Lscala/actors/threadpool/Callable;;
Asciz	access$602;
Asciz	(Lscala/actors/threadpool/Executors$PrivilegedCallableUsingCurrentClassLoader;Ljava/lang/Exception;)Ljava/lang/Exception;;
NameAndType	exception:Ljava/lang/Exception;
NameAndType	task:Lscala/actors/threadpool/Callable;
NameAndType	result:Ljava/lang/Object;
NameAndType	ccl:Ljava/lang/ClassLoader;
NameAndType	"<init>":()V
class	java/lang/Thread
NameAndType	currentThread:()Ljava/lang/Thread;
NameAndType	getContextClassLoader:()Ljava/lang/ClassLoader;
class	java/security/AccessController
NameAndType	getContext:()Ljava/security/AccessControlContext;
NameAndType	acc:Ljava/security/AccessControlContext;
Asciz	java/lang/RuntimePermission;
Asciz	getContextClassLoader;
NameAndType	"<init>":(Ljava/lang/String;)V
class	java/security/AccessControlContext
NameAndType	checkPermission:(Ljava/security/Permission;)V
Asciz	setContextClassLoader;
Asciz	scala/actors/threadpool/Executors$PrivilegedCallableUsingCurrentClassLoader$1;
Asciz	;
NameAndType	"<init>":(Lscala/actors/threadpool/Executors$PrivilegedCallableUsingCurrentClassLoader;)V
NameAndType	doPrivileged:(Ljava/security/PrivilegedAction;Ljava/security/AccessControlContext;)Ljava/lang/Object;
class	scala/actors/threadpool/Executors
Asciz	scala/actors/threadpool/Executors$PrivilegedCallableUsingCurrentClassLoader;
Asciz	java/lang/Object;
Asciz	scala/actors/threadpool/Callable;
Asciz	java/lang/Exception;
Asciz	()V;
Asciz	java/lang/Thread;
Asciz	currentThread;
Asciz	()Ljava/lang/Thread;;
Asciz	()Ljava/lang/ClassLoader;;
Asciz	java/security/AccessController;
Asciz	getContext;
Asciz	()Ljava/security/AccessControlContext;;
Asciz	(Ljava/lang/String;)V;
Asciz	java/security/AccessControlContext;
Asciz	checkPermission;
Asciz	(Ljava/security/Permission;)V;
Asciz	(Lscala/actors/threadpool/Executors$PrivilegedCallableUsingCurrentClassLoader;)V;
Asciz	doPrivileged;
Asciz	(Ljava/security/PrivilegedAction;Ljava/security/AccessControlContext;)Ljava/lang/Object;;
Asciz	scala/actors/threadpool/Executors;

{
private final java.lang.ClassLoader ccl;
  Signature: Ljava/lang/ClassLoader;

private final java.security.AccessControlContext acc;
  Signature: Ljava/security/AccessControlContext;

private final scala.actors.threadpool.Callable task;
  Signature: Lscala/actors/threadpool/Callable;

private java.lang.Object result;
  Signature: Ljava/lang/Object;

private java.lang.Exception exception;
  Signature: Ljava/lang/Exception;

scala.actors.threadpool.Executors$PrivilegedCallableUsingCurrentClassLoader(scala.actors.threadpool.Callable);
  Signature: (Lscala/actors/threadpool/Callable;)V
  Code:
   Stack=4, Locals=2, Args_size=2
	aload_0
	invokespecial	Method java/lang/Object."<init>":()V
	aload_0
	aload_1
	putfield	Field task:Lscala/actors/threadpool/Callable;
	aload_0
	invokestatic	Method java/lang/Thread.currentThread:()Ljava/lang/Thread;
	invokevirtual	Method java/lang/Thread.getContextClassLoader:()Ljava/lang/ClassLoader;
	putfield	Field ccl:Ljava/lang/ClassLoader;
	aload_0
	invokestatic	Method java/security/AccessController.getContext:()Ljava/security/AccessControlContext;
	putfield	Field acc:Ljava/security/AccessControlContext;
	aload_0
	getfield	Field acc:Ljava/security/AccessControlContext;
	new	class java/lang/RuntimePermission
	dup
	ldc	String getContextClassLoader
	invokespecial	Method java/lang/RuntimePermission."<init>":(Ljava/lang/String;)V
	invokevirtual	Method java/security/AccessControlContext.checkPermission:(Ljava/security/Permission;)V
	aload_0
	getfield	Field acc:Ljava/security/AccessControlContext;
	new	class java/lang/RuntimePermission
	dup
	ldc	String setContextClassLoader
	invokespecial	Method java/lang/RuntimePermission."<init>":(Ljava/lang/String;)V
	invokevirtual	Method java/security/AccessControlContext.checkPermission:(Ljava/security/Permission;)V
	return
  Labels:

public java.lang.Object call()   throws java.lang.Exception;
  Signature: ()Ljava/lang/Object;
  Code:
   Stack=3, Locals=1, Args_size=1
	new	class scala/actors/threadpool/Executors$PrivilegedCallableUsingCurrentClassLoader$1
	dup
	aload_0
	invokespecial	Method scala/actors/threadpool/Executors$PrivilegedCallableUsingCurrentClassLoader$1."<init>":(Lscala/actors/threadpool/Executors$PrivilegedCallableUsingCurrentClassLoader;)V
	aload_0
	getfield	Field acc:Ljava/security/AccessControlContext;
	invokestatic	Method java/security/AccessController.doPrivileged:(Ljava/security/PrivilegedAction;Ljava/security/AccessControlContext;)Ljava/lang/Object;
	pop
	aload_0
	getfield	Field exception:Ljava/lang/Exception;
	ifnull	l1 // aload_0
	aload_0
	getfield	Field exception:Ljava/lang/Exception;
	athrow
l1	aload_0
	getfield	Field result:Ljava/lang/Object;
	areturn
  Labels:
   	l1 = 28 // aload_0
  Exceptions: 
   throws java.lang.Exception
static java.lang.ClassLoader access$300(scala.actors.threadpool.Executors$PrivilegedCallableUsingCurrentClassLoader);
  Signature: (Lscala/actors/threadpool/Executors$PrivilegedCallableUsingCurrentClassLoader;)Ljava/lang/ClassLoader;
  Code:
   Stack=1, Locals=1, Args_size=1
	aload_0
	getfield	Field ccl:Ljava/lang/ClassLoader;
	areturn
  Labels:

static java.lang.Object access$402(scala.actors.threadpool.Executors$PrivilegedCallableUsingCurrentClassLoader, java.lang.Object);
  Signature: (Lscala/actors/threadpool/Executors$PrivilegedCallableUsingCurrentClassLoader;Ljava/lang/Object;)Ljava/lang/Object;
  Code:
   Stack=3, Locals=2, Args_size=2
	aload_0
	aload_1
	dup_x1
	putfield	Field result:Ljava/lang/Object;
	areturn
  Labels:

static scala.actors.threadpool.Callable access$500(scala.actors.threadpool.Executors$PrivilegedCallableUsingCurrentClassLoader);
  Signature: (Lscala/actors/threadpool/Executors$PrivilegedCallableUsingCurrentClassLoader;)Lscala/actors/threadpool/Callable;
  Code:
   Stack=1, Locals=1, Args_size=1
	aload_0
	getfield	Field task:Lscala/actors/threadpool/Callable;
	areturn
  Labels:

static java.lang.Exception access$602(scala.actors.threadpool.Executors$PrivilegedCallableUsingCurrentClassLoader, java.lang.Exception);
  Signature: (Lscala/actors/threadpool/Executors$PrivilegedCallableUsingCurrentClassLoader;Ljava/lang/Exception;)Ljava/lang/Exception;
  Code:
   Stack=3, Locals=2, Args_size=2
	aload_0
	aload_1
	dup_x1
	putfield	Field exception:Ljava/lang/Exception;
	areturn
  Labels:

}

