final class scala.actors.threadpool.Executors$RunnableAdapter extends java.lang.Object implements scala.actors.threadpool.Callable
  InnerClass: 
   final #24= #5 of #22; //RunnableAdapter=class scala/actors/threadpool/Executors$RunnableAdapter of class scala/actors/threadpool/Executors
  minor version: 0
  major version: 49
  Constant pool:
const #1 = Method	#6.#17;	//  java/lang/Object."<init>":()V
const #2 = Field	#5.#18;	//  scala/actors/threadpool/Executors$RunnableAdapter.task:Ljava/lang/Runnable;
const #3 = Field	#5.#19;	//  scala/actors/threadpool/Executors$RunnableAdapter.result:Ljava/lang/Object;
const #4 = InterfaceMethod	#20.#21;	//  java/lang/Runnable.run:()V
const #5 = class	#23;	//  scala/actors/threadpool/Executors$RunnableAdapter
const #6 = class	#26;	//  java/lang/Object
const #7 = class	#27;	//  scala/actors/threadpool/Callable
const #8 = Asciz	task;
const #9 = Asciz	Ljava/lang/Runnable;;
const #10 = Asciz	result;
const #11 = Asciz	Ljava/lang/Object;;
const #12 = Asciz	<init>;
const #13 = Asciz	(Ljava/lang/Runnable;Ljava/lang/Object;)V;
const #14 = Asciz	Code;
const #15 = Asciz	call;
const #16 = Asciz	()Ljava/lang/Object;;
const #17 = NameAndType	#12:#28;//  "<init>":()V
const #18 = NameAndType	#8:#9;//  task:Ljava/lang/Runnable;
const #19 = NameAndType	#10:#11;//  result:Ljava/lang/Object;
const #20 = class	#29;	//  java/lang/Runnable
const #21 = NameAndType	#30:#28;//  run:()V
const #22 = class	#31;	//  scala/actors/threadpool/Executors
const #23 = Asciz	scala/actors/threadpool/Executors$RunnableAdapter;
const #24 = Asciz	RunnableAdapter;
const #25 = Asciz	InnerClasses;
const #26 = Asciz	java/lang/Object;
const #27 = Asciz	scala/actors/threadpool/Callable;
const #28 = Asciz	()V;
const #29 = Asciz	java/lang/Runnable;
const #30 = Asciz	run;
const #31 = Asciz	scala/actors/threadpool/Executors;

{
final java.lang.Runnable task;

final java.lang.Object result;

scala.actors.threadpool.Executors$RunnableAdapter(java.lang.Runnable, java.lang.Object);
  Code:
   Stack=2, Locals=3, Args_size=3
   0:	aload_0
   1:	invokespecial	#1; //Method java/lang/Object."<init>":()V
   4:	aload_0
   5:	aload_1
   6:	putfield	#2; //Field task:Ljava/lang/Runnable;
   9:	aload_0
   10:	aload_2
   11:	putfield	#3; //Field result:Ljava/lang/Object;
   14:	return

public java.lang.Object call();
  Code:
   Stack=1, Locals=1, Args_size=1
   0:	aload_0
   1:	getfield	#2; //Field task:Ljava/lang/Runnable;
   4:	invokeinterface	#4,  1; //InterfaceMethod java/lang/Runnable.run:()V
   9:	aload_0
   10:	getfield	#3; //Field result:Ljava/lang/Object;
   13:	areturn

}

