class scala.actors.threadpool.Executors$PrivilegedThreadFactory$1 extends java.lang.Object implements java.lang.Runnable
  EnclosingMethod: length = 0x4
   00 0E 00 18 
  InnerClass: 
   #15= #14 of #37; //PrivilegedThreadFactory=class scala/actors/threadpool/Executors$PrivilegedThreadFactory of class scala/actors/threadpool/Executors
   #4; //class scala/actors/threadpool/Executors$PrivilegedThreadFactory$1$1
   #8; //class scala/actors/threadpool/Executors$PrivilegedThreadFactory$1
  minor version: 0
  major version: 49
  Constant pool:
const #1 = Field	#8.#25;	//  scala/actors/threadpool/Executors$PrivilegedThreadFactory$1.this$0:Lscala/actors/threadpool/Executors$PrivilegedThreadFactory;
const #2 = Field	#8.#26;	//  scala/actors/threadpool/Executors$PrivilegedThreadFactory$1.val$r:Ljava/lang/Runnable;
const #3 = Method	#9.#27;	//  java/lang/Object."<init>":()V
const #4 = class	#28;	//  scala/actors/threadpool/Executors$PrivilegedThreadFactory$1$1
const #5 = Method	#4.#30;	//  scala/actors/threadpool/Executors$PrivilegedThreadFactory$1$1."<init>":(Lscala/actors/threadpool/Executors$PrivilegedThreadFactory$1;)V
const #6 = Method	#14.#31;	//  scala/actors/threadpool/Executors$PrivilegedThreadFactory.access$800:(Lscala/actors/threadpool/Executors$PrivilegedThreadFactory;)Ljava/security/AccessControlContext;
const #7 = Method	#32.#33;	//  java/security/AccessController.doPrivileged:(Ljava/security/PrivilegedAction;Ljava/security/AccessControlContext;)Ljava/lang/Object;
const #8 = class	#34;	//  scala/actors/threadpool/Executors$PrivilegedThreadFactory$1
const #9 = class	#35;	//  java/lang/Object
const #10 = class	#36;	//  java/lang/Runnable
const #11 = Asciz	val$r;
const #12 = Asciz	Ljava/lang/Runnable;;
const #13 = Asciz	this$0;
const #14 = class	#38;	//  scala/actors/threadpool/Executors$PrivilegedThreadFactory
const #15 = Asciz	PrivilegedThreadFactory;
const #16 = Asciz	InnerClasses;
const #17 = Asciz	Lscala/actors/threadpool/Executors$PrivilegedThreadFactory;;
const #18 = Asciz	<init>;
const #19 = Asciz	(Lscala/actors/threadpool/Executors$PrivilegedThreadFactory;Ljava/lang/Runnable;)V;
const #20 = Asciz	Code;
const #21 = Asciz	run;
const #22 = Asciz	()V;
const #23 = Asciz	EnclosingMethod;
const #24 = NameAndType	#39:#40;//  newThread:(Ljava/lang/Runnable;)Ljava/lang/Thread;
const #25 = NameAndType	#13:#17;//  this$0:Lscala/actors/threadpool/Executors$PrivilegedThreadFactory;
const #26 = NameAndType	#11:#12;//  val$r:Ljava/lang/Runnable;
const #27 = NameAndType	#18:#22;//  "<init>":()V
const #28 = Asciz	scala/actors/threadpool/Executors$PrivilegedThreadFactory$1$1;
const #29 = Asciz	;
const #30 = NameAndType	#18:#41;//  "<init>":(Lscala/actors/threadpool/Executors$PrivilegedThreadFactory$1;)V
const #31 = NameAndType	#42:#43;//  access$800:(Lscala/actors/threadpool/Executors$PrivilegedThreadFactory;)Ljava/security/AccessControlContext;
const #32 = class	#44;	//  java/security/AccessController
const #33 = NameAndType	#45:#46;//  doPrivileged:(Ljava/security/PrivilegedAction;Ljava/security/AccessControlContext;)Ljava/lang/Object;
const #34 = Asciz	scala/actors/threadpool/Executors$PrivilegedThreadFactory$1;
const #35 = Asciz	java/lang/Object;
const #36 = Asciz	java/lang/Runnable;
const #37 = class	#47;	//  scala/actors/threadpool/Executors
const #38 = Asciz	scala/actors/threadpool/Executors$PrivilegedThreadFactory;
const #39 = Asciz	newThread;
const #40 = Asciz	(Ljava/lang/Runnable;)Ljava/lang/Thread;;
const #41 = Asciz	(Lscala/actors/threadpool/Executors$PrivilegedThreadFactory$1;)V;
const #42 = Asciz	access$800;
const #43 = Asciz	(Lscala/actors/threadpool/Executors$PrivilegedThreadFactory;)Ljava/security/AccessControlContext;;
const #44 = Asciz	java/security/AccessController;
const #45 = Asciz	doPrivileged;
const #46 = Asciz	(Ljava/security/PrivilegedAction;Ljava/security/AccessControlContext;)Ljava/lang/Object;;
const #47 = Asciz	scala/actors/threadpool/Executors;

{
final java.lang.Runnable val$r;

final scala.actors.threadpool.Executors$PrivilegedThreadFactory this$0;

scala.actors.threadpool.Executors$PrivilegedThreadFactory$1(scala.actors.threadpool.Executors$PrivilegedThreadFactory, java.lang.Runnable);
  Code:
   Stack=2, Locals=3, Args_size=3
   0:	aload_0
   1:	aload_1
   2:	putfield	#1; //Field this$0:Lscala/actors/threadpool/Executors$PrivilegedThreadFactory;
   5:	aload_0
   6:	aload_2
   7:	putfield	#2; //Field val$r:Ljava/lang/Runnable;
   10:	aload_0
   11:	invokespecial	#3; //Method java/lang/Object."<init>":()V
   14:	return

public void run();
  Code:
   Stack=3, Locals=1, Args_size=1
   0:	new	#4; //class scala/actors/threadpool/Executors$PrivilegedThreadFactory$1$1
   3:	dup
   4:	aload_0
   5:	invokespecial	#5; //Method scala/actors/threadpool/Executors$PrivilegedThreadFactory$1$1."<init>":(Lscala/actors/threadpool/Executors$PrivilegedThreadFactory$1;)V
   8:	aload_0
   9:	getfield	#1; //Field this$0:Lscala/actors/threadpool/Executors$PrivilegedThreadFactory;
   12:	invokestatic	#6; //Method scala/actors/threadpool/Executors$PrivilegedThreadFactory.access$800:(Lscala/actors/threadpool/Executors$PrivilegedThreadFactory;)Ljava/security/AccessControlContext;
   15:	invokestatic	#7; //Method java/security/AccessController.doPrivileged:(Ljava/security/PrivilegedAction;Ljava/security/AccessControlContext;)Ljava/lang/Object;
   18:	pop
   19:	return

}

