final class scala.actors.threadpool.Executors$PrivilegedCallable extends java.lang.Object implements scala.actors.threadpool.Callable
  InnerClass: 
   final #29= #10 of #47; //PrivilegedCallable=class scala/actors/threadpool/Executors$PrivilegedCallable of class scala/actors/threadpool/Executors
   #7; //class scala/actors/threadpool/Executors$PrivilegedCallable$1
  minor version: 0
  major version: 49
  Constant pool:
const #1 = Field	#10.#36;	//  scala/actors/threadpool/Executors$PrivilegedCallable.exception:Ljava/lang/Exception;
const #2 = Field	#10.#37;	//  scala/actors/threadpool/Executors$PrivilegedCallable.task:Lscala/actors/threadpool/Callable;
const #3 = Field	#10.#38;	//  scala/actors/threadpool/Executors$PrivilegedCallable.result:Ljava/lang/Object;
const #4 = Method	#11.#39;	//  java/lang/Object."<init>":()V
const #5 = Method	#40.#41;	//  java/security/AccessController.getContext:()Ljava/security/AccessControlContext;
const #6 = Field	#10.#42;	//  scala/actors/threadpool/Executors$PrivilegedCallable.acc:Ljava/security/AccessControlContext;
const #7 = class	#43;	//  scala/actors/threadpool/Executors$PrivilegedCallable$1
const #8 = Method	#7.#45;	//  scala/actors/threadpool/Executors$PrivilegedCallable$1."<init>":(Lscala/actors/threadpool/Executors$PrivilegedCallable;)V
const #9 = Method	#40.#46;	//  java/security/AccessController.doPrivileged:(Ljava/security/PrivilegedAction;Ljava/security/AccessControlContext;)Ljava/lang/Object;
const #10 = class	#48;	//  scala/actors/threadpool/Executors$PrivilegedCallable
const #11 = class	#49;	//  java/lang/Object
const #12 = class	#50;	//  scala/actors/threadpool/Callable
const #13 = Asciz	acc;
const #14 = Asciz	Ljava/security/AccessControlContext;;
const #15 = Asciz	task;
const #16 = Asciz	Lscala/actors/threadpool/Callable;;
const #17 = Asciz	result;
const #18 = Asciz	Ljava/lang/Object;;
const #19 = Asciz	exception;
const #20 = Asciz	Ljava/lang/Exception;;
const #21 = Asciz	<init>;
const #22 = Asciz	(Lscala/actors/threadpool/Callable;)V;
const #23 = Asciz	Code;
const #24 = Asciz	call;
const #25 = Asciz	()Ljava/lang/Object;;
const #26 = Asciz	Exceptions;
const #27 = class	#51;	//  java/lang/Exception
const #28 = Asciz	access$002;
const #29 = Asciz	PrivilegedCallable;
const #30 = Asciz	InnerClasses;
const #31 = Asciz	(Lscala/actors/threadpool/Executors$PrivilegedCallable;Ljava/lang/Object;)Ljava/lang/Object;;
const #32 = Asciz	access$100;
const #33 = Asciz	(Lscala/actors/threadpool/Executors$PrivilegedCallable;)Lscala/actors/threadpool/Callable;;
const #34 = Asciz	access$202;
const #35 = Asciz	(Lscala/actors/threadpool/Executors$PrivilegedCallable;Ljava/lang/Exception;)Ljava/lang/Exception;;
const #36 = NameAndType	#19:#20;//  exception:Ljava/lang/Exception;
const #37 = NameAndType	#15:#16;//  task:Lscala/actors/threadpool/Callable;
const #38 = NameAndType	#17:#18;//  result:Ljava/lang/Object;
const #39 = NameAndType	#21:#52;//  "<init>":()V
const #40 = class	#53;	//  java/security/AccessController
const #41 = NameAndType	#54:#55;//  getContext:()Ljava/security/AccessControlContext;
const #42 = NameAndType	#13:#14;//  acc:Ljava/security/AccessControlContext;
const #43 = Asciz	scala/actors/threadpool/Executors$PrivilegedCallable$1;
const #44 = Asciz	;
const #45 = NameAndType	#21:#56;//  "<init>":(Lscala/actors/threadpool/Executors$PrivilegedCallable;)V
const #46 = NameAndType	#57:#58;//  doPrivileged:(Ljava/security/PrivilegedAction;Ljava/security/AccessControlContext;)Ljava/lang/Object;
const #47 = class	#59;	//  scala/actors/threadpool/Executors
const #48 = Asciz	scala/actors/threadpool/Executors$PrivilegedCallable;
const #49 = Asciz	java/lang/Object;
const #50 = Asciz	scala/actors/threadpool/Callable;
const #51 = Asciz	java/lang/Exception;
const #52 = Asciz	()V;
const #53 = Asciz	java/security/AccessController;
const #54 = Asciz	getContext;
const #55 = Asciz	()Ljava/security/AccessControlContext;;
const #56 = Asciz	(Lscala/actors/threadpool/Executors$PrivilegedCallable;)V;
const #57 = Asciz	doPrivileged;
const #58 = Asciz	(Ljava/security/PrivilegedAction;Ljava/security/AccessControlContext;)Ljava/lang/Object;;
const #59 = Asciz	scala/actors/threadpool/Executors;

{
scala.actors.threadpool.Executors$PrivilegedCallable(scala.actors.threadpool.Callable);
  Code:
   Stack=2, Locals=2, Args_size=2
   0:	aload_0
   1:	invokespecial	#4; //Method java/lang/Object."<init>":()V
   4:	aload_0
   5:	aload_1
   6:	putfield	#2; //Field task:Lscala/actors/threadpool/Callable;
   9:	aload_0
   10:	invokestatic	#5; //Method java/security/AccessController.getContext:()Ljava/security/AccessControlContext;
   13:	putfield	#6; //Field acc:Ljava/security/AccessControlContext;
   16:	return

public java.lang.Object call()   throws java.lang.Exception;
  Code:
   Stack=3, Locals=1, Args_size=1
   0:	new	#7; //class scala/actors/threadpool/Executors$PrivilegedCallable$1
   3:	dup
   4:	aload_0
   5:	invokespecial	#8; //Method scala/actors/threadpool/Executors$PrivilegedCallable$1."<init>":(Lscala/actors/threadpool/Executors$PrivilegedCallable;)V
   8:	aload_0
   9:	getfield	#6; //Field acc:Ljava/security/AccessControlContext;
   12:	invokestatic	#9; //Method java/security/AccessController.doPrivileged:(Ljava/security/PrivilegedAction;Ljava/security/AccessControlContext;)Ljava/lang/Object;
   15:	pop
   16:	aload_0
   17:	getfield	#1; //Field exception:Ljava/lang/Exception;
   20:	ifnull	28
   23:	aload_0
   24:	getfield	#1; //Field exception:Ljava/lang/Exception;
   27:	athrow
   28:	aload_0
   29:	getfield	#3; //Field result:Ljava/lang/Object;
   32:	areturn
  Exceptions: 
   throws java.lang.Exception
static java.lang.Object access$002(scala.actors.threadpool.Executors$PrivilegedCallable, java.lang.Object);
  Code:
   Stack=3, Locals=2, Args_size=2
   0:	aload_0
   1:	aload_1
   2:	dup_x1
   3:	putfield	#3; //Field result:Ljava/lang/Object;
   6:	areturn

static scala.actors.threadpool.Callable access$100(scala.actors.threadpool.Executors$PrivilegedCallable);
  Code:
   Stack=1, Locals=1, Args_size=1
   0:	aload_0
   1:	getfield	#2; //Field task:Lscala/actors/threadpool/Callable;
   4:	areturn

static java.lang.Exception access$202(scala.actors.threadpool.Executors$PrivilegedCallable, java.lang.Exception);
  Code:
   Stack=3, Locals=2, Args_size=2
   0:	aload_0
   1:	aload_1
   2:	dup_x1
   3:	putfield	#1; //Field exception:Ljava/lang/Exception;
   6:	areturn

}

