public class scala.actors.threadpool.ExecutionException extends java.lang.Exception
  minor version: 0
  major version: 49
  Constant pool:
const #1 = Method	#6.#18;	//  java/lang/Exception."<init>":()V
const #2 = Method	#6.#19;	//  java/lang/Exception."<init>":(Ljava/lang/String;)V
const #3 = Method	#6.#20;	//  java/lang/Exception."<init>":(Ljava/lang/String;Ljava/lang/Throwable;)V
const #4 = Method	#6.#21;	//  java/lang/Exception."<init>":(Ljava/lang/Throwable;)V
const #5 = class	#22;	//  scala/actors/threadpool/ExecutionException
const #6 = class	#23;	//  java/lang/Exception
const #7 = Asciz	serialVersionUID;
const #8 = Asciz	J;
const #9 = Asciz	ConstantValue;
const #10 = long	7830266012832686185l;
const #12 = Asciz	<init>;
const #13 = Asciz	()V;
const #14 = Asciz	Code;
const #15 = Asciz	(Ljava/lang/String;)V;
const #16 = Asciz	(Ljava/lang/String;Ljava/lang/Throwable;)V;
const #17 = Asciz	(Ljava/lang/Throwable;)V;
const #18 = NameAndType	#12:#13;//  "<init>":()V
const #19 = NameAndType	#12:#15;//  "<init>":(Ljava/lang/String;)V
const #20 = NameAndType	#12:#16;//  "<init>":(Ljava/lang/String;Ljava/lang/Throwable;)V
const #21 = NameAndType	#12:#17;//  "<init>":(Ljava/lang/Throwable;)V
const #22 = Asciz	scala/actors/threadpool/ExecutionException;
const #23 = Asciz	java/lang/Exception;

{
protected scala.actors.threadpool.ExecutionException();
  Code:
   Stack=1, Locals=1, Args_size=1
   0:	aload_0
   1:	invokespecial	#1; //Method java/lang/Exception."<init>":()V
   4:	return

protected scala.actors.threadpool.ExecutionException(java.lang.String);
  Code:
   Stack=2, Locals=2, Args_size=2
   0:	aload_0
   1:	aload_1
   2:	invokespecial	#2; //Method java/lang/Exception."<init>":(Ljava/lang/String;)V
   5:	return

public scala.actors.threadpool.ExecutionException(java.lang.String, java.lang.Throwable);
  Code:
   Stack=3, Locals=3, Args_size=3
   0:	aload_0
   1:	aload_1
   2:	aload_2
   3:	invokespecial	#3; //Method java/lang/Exception."<init>":(Ljava/lang/String;Ljava/lang/Throwable;)V
   6:	return

public scala.actors.threadpool.ExecutionException(java.lang.Throwable);
  Code:
   Stack=2, Locals=2, Args_size=2
   0:	aload_0
   1:	aload_1
   2:	invokespecial	#4; //Method java/lang/Exception."<init>":(Ljava/lang/Throwable;)V
   5:	return

}

