class scala.actors.threadpool.Executors$PrivilegedCallableUsingCurrentClassLoader$1 extends java.lang.Object implements java.security.PrivilegedAction
  EnclosingMethod: length = 0x4
   00 10 00 1A 
  InnerClass: 
   final PrivilegedCallableUsingCurrentClassLoader=class scala/actors/threadpool/Executors$PrivilegedCallableUsingCurrentClassLoader of class scala/actors/threadpool/Executors
   class scala/actors/threadpool/Executors$PrivilegedCallableUsingCurrentClassLoader$1
  minor version: 0
  major version: 49
  Constant pool:
Field	scala/actors/threadpool/Executors$PrivilegedCallableUsingCurrentClassLoader$1.this$0:Lscala/actors/threadpool/Executors$PrivilegedCallableUsingCurrentClassLoader;
Method	java/lang/Object."<init>":()V
Method	java/lang/Thread.currentThread:()Ljava/lang/Thread;
Method	java/lang/Thread.getContextClassLoader:()Ljava/lang/ClassLoader;
Method	scala/actors/threadpool/Executors$PrivilegedCallableUsingCurrentClassLoader.access$300:(Lscala/actors/threadpool/Executors$PrivilegedCallableUsingCurrentClassLoader;)Ljava/lang/ClassLoader;
Method	java/lang/Thread.setContextClassLoader:(Ljava/lang/ClassLoader;)V
Method	scala/actors/threadpool/Executors$PrivilegedCallableUsingCurrentClassLoader.access$500:(Lscala/actors/threadpool/Executors$PrivilegedCallableUsingCurrentClassLoader;)Lscala/actors/threadpool/Callable;
InterfaceMethod	scala/actors/threadpool/Callable.call:()Ljava/lang/Object;
Method	scala/actors/threadpool/Executors$PrivilegedCallableUsingCurrentClassLoader.access$402:(Lscala/actors/threadpool/Executors$PrivilegedCallableUsingCurrentClassLoader;Ljava/lang/Object;)Ljava/lang/Object;
class	java/lang/Exception
Method	scala/actors/threadpool/Executors$PrivilegedCallableUsingCurrentClassLoader.access$602:(Lscala/actors/threadpool/Executors$PrivilegedCallableUsingCurrentClassLoader;Ljava/lang/Exception;)Ljava/lang/Exception;
class	scala/actors/threadpool/Executors$PrivilegedCallableUsingCurrentClassLoader$1
class	java/lang/Object
class	java/security/PrivilegedAction
Asciz	this$0;
class	scala/actors/threadpool/Executors$PrivilegedCallableUsingCurrentClassLoader
Asciz	PrivilegedCallableUsingCurrentClassLoader;
Asciz	InnerClasses;
Asciz	Lscala/actors/threadpool/Executors$PrivilegedCallableUsingCurrentClassLoader;;
Asciz	<init>;
Asciz	(Lscala/actors/threadpool/Executors$PrivilegedCallableUsingCurrentClassLoader;)V;
Asciz	Code;
Asciz	run;
Asciz	()Ljava/lang/Object;;
Asciz	EnclosingMethod;
NameAndType	call:()Ljava/lang/Object;
NameAndType	this$0:Lscala/actors/threadpool/Executors$PrivilegedCallableUsingCurrentClassLoader;
NameAndType	"<init>":()V
class	java/lang/Thread
NameAndType	currentThread:()Ljava/lang/Thread;
NameAndType	getContextClassLoader:()Ljava/lang/ClassLoader;
NameAndType	access$300:(Lscala/actors/threadpool/Executors$PrivilegedCallableUsingCurrentClassLoader;)Ljava/lang/ClassLoader;
NameAndType	setContextClassLoader:(Ljava/lang/ClassLoader;)V
NameAndType	access$500:(Lscala/actors/threadpool/Executors$PrivilegedCallableUsingCurrentClassLoader;)Lscala/actors/threadpool/Callable;
class	scala/actors/threadpool/Callable
NameAndType	access$402:(Lscala/actors/threadpool/Executors$PrivilegedCallableUsingCurrentClassLoader;Ljava/lang/Object;)Ljava/lang/Object;
Asciz	java/lang/Exception;
NameAndType	access$602:(Lscala/actors/threadpool/Executors$PrivilegedCallableUsingCurrentClassLoader;Ljava/lang/Exception;)Ljava/lang/Exception;
Asciz	scala/actors/threadpool/Executors$PrivilegedCallableUsingCurrentClassLoader$1;
Asciz	;
Asciz	java/lang/Object;
Asciz	java/security/PrivilegedAction;
class	scala/actors/threadpool/Executors
Asciz	scala/actors/threadpool/Executors$PrivilegedCallableUsingCurrentClassLoader;
Asciz	call;
Asciz	()V;
Asciz	java/lang/Thread;
Asciz	currentThread;
Asciz	()Ljava/lang/Thread;;
Asciz	getContextClassLoader;
Asciz	()Ljava/lang/ClassLoader;;
Asciz	access$300;
Asciz	(Lscala/actors/threadpool/Executors$PrivilegedCallableUsingCurrentClassLoader;)Ljava/lang/ClassLoader;;
Asciz	setContextClassLoader;
Asciz	(Ljava/lang/ClassLoader;)V;
Asciz	access$500;
Asciz	(Lscala/actors/threadpool/Executors$PrivilegedCallableUsingCurrentClassLoader;)Lscala/actors/threadpool/Callable;;
Asciz	scala/actors/threadpool/Callable;
Asciz	access$402;
Asciz	(Lscala/actors/threadpool/Executors$PrivilegedCallableUsingCurrentClassLoader;Ljava/lang/Object;)Ljava/lang/Object;;
Asciz	access$602;
Asciz	(Lscala/actors/threadpool/Executors$PrivilegedCallableUsingCurrentClassLoader;Ljava/lang/Exception;)Ljava/lang/Exception;;
Asciz	scala/actors/threadpool/Executors;

{
final scala.actors.threadpool.Executors$PrivilegedCallableUsingCurrentClassLoader this$0;
  Signature: Lscala/actors/threadpool/Executors$PrivilegedCallableUsingCurrentClassLoader;

scala.actors.threadpool.Executors$PrivilegedCallableUsingCurrentClassLoader$1(scala.actors.threadpool.Executors$PrivilegedCallableUsingCurrentClassLoader);
  Signature: (Lscala/actors/threadpool/Executors$PrivilegedCallableUsingCurrentClassLoader;)V
  Code:
   Stack=2, Locals=2, Args_size=2
	aload_0
	aload_1
	putfield	Field this$0:Lscala/actors/threadpool/Executors$PrivilegedCallableUsingCurrentClassLoader;
	aload_0
	invokespecial	Method java/lang/Object."<init>":()V
	return
  Labels:

public java.lang.Object run();
  Signature: ()Ljava/lang/Object;
  Code:
   Stack=2, Locals=5, Args_size=1
	aconst_null
	astore_1
	invokestatic	Method java/lang/Thread.currentThread:()Ljava/lang/Thread;
	astore_2
	aload_2
	invokevirtual	Method java/lang/Thread.getContextClassLoader:()Ljava/lang/ClassLoader;
	astore_3
	aload_0
	getfield	Field this$0:Lscala/actors/threadpool/Executors$PrivilegedCallableUsingCurrentClassLoader;
	invokestatic	Method scala/actors/threadpool/Executors$PrivilegedCallableUsingCurrentClassLoader.access$300:(Lscala/actors/threadpool/Executors$PrivilegedCallableUsingCurrentClassLoader;)Ljava/lang/ClassLoader;
	aload_3
	if_acmpeq	l1 // aload_0
	aload_2
	aload_0
	getfield	Field this$0:Lscala/actors/threadpool/Executors$PrivilegedCallableUsingCurrentClassLoader;
	invokestatic	Method scala/actors/threadpool/Executors$PrivilegedCallableUsingCurrentClassLoader.access$300:(Lscala/actors/threadpool/Executors$PrivilegedCallableUsingCurrentClassLoader;)Ljava/lang/ClassLoader;
	invokevirtual	Method java/lang/Thread.setContextClassLoader:(Ljava/lang/ClassLoader;)V
	aload_3
	astore_1
l1	aload_0
	getfield	Field this$0:Lscala/actors/threadpool/Executors$PrivilegedCallableUsingCurrentClassLoader;
	aload_0
	getfield	Field this$0:Lscala/actors/threadpool/Executors$PrivilegedCallableUsingCurrentClassLoader;
	invokestatic	Method scala/actors/threadpool/Executors$PrivilegedCallableUsingCurrentClassLoader.access$500:(Lscala/actors/threadpool/Executors$PrivilegedCallableUsingCurrentClassLoader;)Lscala/actors/threadpool/Callable;
	invokeinterface	InterfaceMethod scala/actors/threadpool/Callable.call:()Ljava/lang/Object;
	invokestatic	Method scala/actors/threadpool/Executors$PrivilegedCallableUsingCurrentClassLoader.access$402:(Lscala/actors/threadpool/Executors$PrivilegedCallableUsingCurrentClassLoader;Ljava/lang/Object;)Ljava/lang/Object;
	pop
	aload_1
	ifnull	l2 // aconst_null
	aload_2
	aload_1
	invokevirtual	Method java/lang/Thread.setContextClassLoader:(Ljava/lang/ClassLoader;)V
	goto	l2 // aconst_null
	astore_3
	aload_0
	getfield	Field this$0:Lscala/actors/threadpool/Executors$PrivilegedCallableUsingCurrentClassLoader;
	aload_3
	invokestatic	Method scala/actors/threadpool/Executors$PrivilegedCallableUsingCurrentClassLoader.access$602:(Lscala/actors/threadpool/Executors$PrivilegedCallableUsingCurrentClassLoader;Ljava/lang/Exception;)Ljava/lang/Exception;
	pop
	aload_1
	ifnull	l2 // aconst_null
	aload_2
	aload_1
	invokevirtual	Method java/lang/Thread.setContextClassLoader:(Ljava/lang/ClassLoader;)V
	goto	l2 // aconst_null
	astore	4
	aload_1
	ifnull	l3 // aload
	aload_2
	aload_1
	invokevirtual	Method java/lang/Thread.setContextClassLoader:(Ljava/lang/ClassLoader;)V
l3	aload	4
	athrow
l2	aconst_null
	areturn
  Labels:
   	l1 = 35 // aload_0
   	l3 = 100 // aload
   	l2 = 103 // aconst_null
  Exception table:
   from   to  target type
     6    55    67   Class java/lang/Exception

     6    55    89   any
    67    77    89   any
    89    91    89   any

}

