class scala.actors.threadpool.Executors$PrivilegedThreadFactory$1$1 extends java.lang.Object implements java.security.PrivilegedAction
  EnclosingMethod: length = 0x4
   00 0D 00 17 
  InnerClass: 
   class scala/actors/threadpool/Executors$PrivilegedThreadFactory$1
   class scala/actors/threadpool/Executors$PrivilegedThreadFactory$1$1
   PrivilegedThreadFactory=class scala/actors/threadpool/Executors$PrivilegedThreadFactory of class scala/actors/threadpool/Executors
  minor version: 0
  major version: 49
  Constant pool:
Field	scala/actors/threadpool/Executors$PrivilegedThreadFactory$1$1.this$1:Lscala/actors/threadpool/Executors$PrivilegedThreadFactory$1;
Method	java/lang/Object."<init>":()V
Method	java/lang/Thread.currentThread:()Ljava/lang/Thread;
Field	scala/actors/threadpool/Executors$PrivilegedThreadFactory$1.this$0:Lscala/actors/threadpool/Executors$PrivilegedThreadFactory;
Method	scala/actors/threadpool/Executors$PrivilegedThreadFactory.access$700:(Lscala/actors/threadpool/Executors$PrivilegedThreadFactory;)Ljava/lang/ClassLoader;
Method	java/lang/Thread.setContextClassLoader:(Ljava/lang/ClassLoader;)V
Field	scala/actors/threadpool/Executors$PrivilegedThreadFactory$1.val$r:Ljava/lang/Runnable;
InterfaceMethod	java/lang/Runnable.run:()V
class	scala/actors/threadpool/Executors$PrivilegedThreadFactory$1$1
class	java/lang/Object
class	java/security/PrivilegedAction
Asciz	this$1;
class	scala/actors/threadpool/Executors$PrivilegedThreadFactory$1
Asciz	;
Asciz	InnerClasses;
Asciz	Lscala/actors/threadpool/Executors$PrivilegedThreadFactory$1;;
Asciz	<init>;
Asciz	(Lscala/actors/threadpool/Executors$PrivilegedThreadFactory$1;)V;
Asciz	Code;
Asciz	run;
Asciz	()Ljava/lang/Object;;
Asciz	EnclosingMethod;
NameAndType	run:()V
NameAndType	this$1:Lscala/actors/threadpool/Executors$PrivilegedThreadFactory$1;
NameAndType	"<init>":()V
class	java/lang/Thread
NameAndType	currentThread:()Ljava/lang/Thread;
NameAndType	this$0:Lscala/actors/threadpool/Executors$PrivilegedThreadFactory;
class	scala/actors/threadpool/Executors$PrivilegedThreadFactory
NameAndType	access$700:(Lscala/actors/threadpool/Executors$PrivilegedThreadFactory;)Ljava/lang/ClassLoader;
NameAndType	setContextClassLoader:(Ljava/lang/ClassLoader;)V
NameAndType	val$r:Ljava/lang/Runnable;
class	java/lang/Runnable
Asciz	scala/actors/threadpool/Executors$PrivilegedThreadFactory$1$1;
Asciz	java/lang/Object;
Asciz	java/security/PrivilegedAction;
Asciz	scala/actors/threadpool/Executors$PrivilegedThreadFactory$1;
Asciz	()V;
Asciz	java/lang/Thread;
Asciz	currentThread;
Asciz	()Ljava/lang/Thread;;
Asciz	this$0;
Asciz	PrivilegedThreadFactory;
Asciz	Lscala/actors/threadpool/Executors$PrivilegedThreadFactory;;
class	scala/actors/threadpool/Executors
Asciz	scala/actors/threadpool/Executors$PrivilegedThreadFactory;
Asciz	access$700;
Asciz	(Lscala/actors/threadpool/Executors$PrivilegedThreadFactory;)Ljava/lang/ClassLoader;;
Asciz	setContextClassLoader;
Asciz	(Ljava/lang/ClassLoader;)V;
Asciz	val$r;
Asciz	Ljava/lang/Runnable;;
Asciz	java/lang/Runnable;
Asciz	scala/actors/threadpool/Executors;

{
final scala.actors.threadpool.Executors$PrivilegedThreadFactory$1 this$1;
  Signature: Lscala/actors/threadpool/Executors$PrivilegedThreadFactory$1;

scala.actors.threadpool.Executors$PrivilegedThreadFactory$1$1(scala.actors.threadpool.Executors$PrivilegedThreadFactory$1);
  Signature: (Lscala/actors/threadpool/Executors$PrivilegedThreadFactory$1;)V
  Code:
   Stack=2, Locals=2, Args_size=2
	aload_0
	aload_1
	putfield	Field this$1:Lscala/actors/threadpool/Executors$PrivilegedThreadFactory$1;
	aload_0
	invokespecial	Method java/lang/Object."<init>":()V
	return
  Labels:

public java.lang.Object run();
  Signature: ()Ljava/lang/Object;
  Code:
   Stack=2, Locals=1, Args_size=1
	invokestatic	Method java/lang/Thread.currentThread:()Ljava/lang/Thread;
	aload_0
	getfield	Field this$1:Lscala/actors/threadpool/Executors$PrivilegedThreadFactory$1;
	getfield	Field scala/actors/threadpool/Executors$PrivilegedThreadFactory$1.this$0:Lscala/actors/threadpool/Executors$PrivilegedThreadFactory;
	invokestatic	Method scala/actors/threadpool/Executors$PrivilegedThreadFactory.access$700:(Lscala/actors/threadpool/Executors$PrivilegedThreadFactory;)Ljava/lang/ClassLoader;
	invokevirtual	Method java/lang/Thread.setContextClassLoader:(Ljava/lang/ClassLoader;)V
	aload_0
	getfield	Field this$1:Lscala/actors/threadpool/Executors$PrivilegedThreadFactory$1;
	getfield	Field scala/actors/threadpool/Executors$PrivilegedThreadFactory$1.val$r:Ljava/lang/Runnable;
	invokeinterface	InterfaceMethod java/lang/Runnable.run:()V
	aconst_null
	areturn
  Labels:

}

