final class scala.actors.threadpool.Executors$PrivilegedCallableUsingCurrentClassLoader extends java.lang.Object implements scala.actors.threadpool.Callable
  InnerClass: 
   final #39= #18 of #69; //PrivilegedCallableUsingCurrentClassLoader=class scala/actors/threadpool/Executors$PrivilegedCallableUsingCurrentClassLoader of class scala/actors/threadpool/Executors
   #15; //class scala/actors/threadpool/Executors$PrivilegedCallableUsingCurrentClassLoader$1
  minor version: 0
  major version: 49
  Constant pool:
const #1 = Field	#18.#48;	//  scala/actors/threadpool/Executors$PrivilegedCallableUsingCurrentClassLoader.exception:Ljava/lang/Exception;
const #2 = Field	#18.#49;	//  scala/actors/threadpool/Executors$PrivilegedCallableUsingCurrentClassLoader.task:Lscala/actors/threadpool/Callable;
const #3 = Field	#18.#50;	//  scala/actors/threadpool/Executors$PrivilegedCallableUsingCurrentClassLoader.result:Ljava/lang/Object;
const #4 = Field	#18.#51;	//  scala/actors/threadpool/Executors$PrivilegedCallableUsingCurrentClassLoader.ccl:Ljava/lang/ClassLoader;
const #5 = Method	#19.#52;	//  java/lang/Object."<init>":()V
const #6 = Method	#53.#54;	//  java/lang/Thread.currentThread:()Ljava/lang/Thread;
const #7 = Method	#53.#55;	//  java/lang/Thread.getContextClassLoader:()Ljava/lang/ClassLoader;
const #8 = Method	#56.#57;	//  java/security/AccessController.getContext:()Ljava/security/AccessControlContext;
const #9 = Field	#18.#58;	//  scala/actors/threadpool/Executors$PrivilegedCallableUsingCurrentClassLoader.acc:Ljava/security/AccessControlContext;
const #10 = class	#59;	//  java/lang/RuntimePermission
const #11 = String	#60;	//  getContextClassLoader
const #12 = Method	#10.#61;	//  java/lang/RuntimePermission."<init>":(Ljava/lang/String;)V
const #13 = Method	#62.#63;	//  java/security/AccessControlContext.checkPermission:(Ljava/security/Permission;)V
const #14 = String	#64;	//  setContextClassLoader
const #15 = class	#65;	//  scala/actors/threadpool/Executors$PrivilegedCallableUsingCurrentClassLoader$1
const #16 = Method	#15.#67;	//  scala/actors/threadpool/Executors$PrivilegedCallableUsingCurrentClassLoader$1."<init>":(Lscala/actors/threadpool/Executors$PrivilegedCallableUsingCurrentClassLoader;)V
const #17 = Method	#56.#68;	//  java/security/AccessController.doPrivileged:(Ljava/security/PrivilegedAction;Ljava/security/AccessControlContext;)Ljava/lang/Object;
const #18 = class	#70;	//  scala/actors/threadpool/Executors$PrivilegedCallableUsingCurrentClassLoader
const #19 = class	#71;	//  java/lang/Object
const #20 = class	#72;	//  scala/actors/threadpool/Callable
const #21 = Asciz	ccl;
const #22 = Asciz	Ljava/lang/ClassLoader;;
const #23 = Asciz	acc;
const #24 = Asciz	Ljava/security/AccessControlContext;;
const #25 = Asciz	task;
const #26 = Asciz	Lscala/actors/threadpool/Callable;;
const #27 = Asciz	result;
const #28 = Asciz	Ljava/lang/Object;;
const #29 = Asciz	exception;
const #30 = Asciz	Ljava/lang/Exception;;
const #31 = Asciz	<init>;
const #32 = Asciz	(Lscala/actors/threadpool/Callable;)V;
const #33 = Asciz	Code;
const #34 = Asciz	call;
const #35 = Asciz	()Ljava/lang/Object;;
const #36 = Asciz	Exceptions;
const #37 = class	#73;	//  java/lang/Exception
const #38 = Asciz	access$300;
const #39 = Asciz	PrivilegedCallableUsingCurrentClassLoader;
const #40 = Asciz	InnerClasses;
const #41 = Asciz	(Lscala/actors/threadpool/Executors$PrivilegedCallableUsingCurrentClassLoader;)Ljava/lang/ClassLoader;;
const #42 = Asciz	access$402;
const #43 = Asciz	(Lscala/actors/threadpool/Executors$PrivilegedCallableUsingCurrentClassLoader;Ljava/lang/Object;)Ljava/lang/Object;;
const #44 = Asciz	access$500;
const #45 = Asciz	(Lscala/actors/threadpool/Executors$PrivilegedCallableUsingCurrentClassLoader;)Lscala/actors/threadpool/Callable;;
const #46 = Asciz	access$602;
const #47 = Asciz	(Lscala/actors/threadpool/Executors$PrivilegedCallableUsingCurrentClassLoader;Ljava/lang/Exception;)Ljava/lang/Exception;;
const #48 = NameAndType	#29:#30;//  exception:Ljava/lang/Exception;
const #49 = NameAndType	#25:#26;//  task:Lscala/actors/threadpool/Callable;
const #50 = NameAndType	#27:#28;//  result:Ljava/lang/Object;
const #51 = NameAndType	#21:#22;//  ccl:Ljava/lang/ClassLoader;
const #52 = NameAndType	#31:#74;//  "<init>":()V
const #53 = class	#75;	//  java/lang/Thread
const #54 = NameAndType	#76:#77;//  currentThread:()Ljava/lang/Thread;
const #55 = NameAndType	#60:#78;//  getContextClassLoader:()Ljava/lang/ClassLoader;
const #56 = class	#79;	//  java/security/AccessController
const #57 = NameAndType	#80:#81;//  getContext:()Ljava/security/AccessControlContext;
const #58 = NameAndType	#23:#24;//  acc:Ljava/security/AccessControlContext;
const #59 = Asciz	java/lang/RuntimePermission;
const #60 = Asciz	getContextClassLoader;
const #61 = NameAndType	#31:#82;//  "<init>":(Ljava/lang/String;)V
const #62 = class	#83;	//  java/security/AccessControlContext
const #63 = NameAndType	#84:#85;//  checkPermission:(Ljava/security/Permission;)V
const #64 = Asciz	setContextClassLoader;
const #65 = Asciz	scala/actors/threadpool/Executors$PrivilegedCallableUsingCurrentClassLoader$1;
const #66 = Asciz	;
const #67 = NameAndType	#31:#86;//  "<init>":(Lscala/actors/threadpool/Executors$PrivilegedCallableUsingCurrentClassLoader;)V
const #68 = NameAndType	#87:#88;//  doPrivileged:(Ljava/security/PrivilegedAction;Ljava/security/AccessControlContext;)Ljava/lang/Object;
const #69 = class	#89;	//  scala/actors/threadpool/Executors
const #70 = Asciz	scala/actors/threadpool/Executors$PrivilegedCallableUsingCurrentClassLoader;
const #71 = Asciz	java/lang/Object;
const #72 = Asciz	scala/actors/threadpool/Callable;
const #73 = Asciz	java/lang/Exception;
const #74 = Asciz	()V;
const #75 = Asciz	java/lang/Thread;
const #76 = Asciz	currentThread;
const #77 = Asciz	()Ljava/lang/Thread;;
const #78 = Asciz	()Ljava/lang/ClassLoader;;
const #79 = Asciz	java/security/AccessController;
const #80 = Asciz	getContext;
const #81 = Asciz	()Ljava/security/AccessControlContext;;
const #82 = Asciz	(Ljava/lang/String;)V;
const #83 = Asciz	java/security/AccessControlContext;
const #84 = Asciz	checkPermission;
const #85 = Asciz	(Ljava/security/Permission;)V;
const #86 = Asciz	(Lscala/actors/threadpool/Executors$PrivilegedCallableUsingCurrentClassLoader;)V;
const #87 = Asciz	doPrivileged;
const #88 = Asciz	(Ljava/security/PrivilegedAction;Ljava/security/AccessControlContext;)Ljava/lang/Object;;
const #89 = Asciz	scala/actors/threadpool/Executors;

{
scala.actors.threadpool.Executors$PrivilegedCallableUsingCurrentClassLoader(scala.actors.threadpool.Callable);
  Code:
   Stack=4, Locals=2, Args_size=2
   0:	aload_0
   1:	invokespecial	#5; //Method java/lang/Object."<init>":()V
   4:	aload_0
   5:	aload_1
   6:	putfield	#2; //Field task:Lscala/actors/threadpool/Callable;
   9:	aload_0
   10:	invokestatic	#6; //Method java/lang/Thread.currentThread:()Ljava/lang/Thread;
   13:	invokevirtual	#7; //Method java/lang/Thread.getContextClassLoader:()Ljava/lang/ClassLoader;
   16:	putfield	#4; //Field ccl:Ljava/lang/ClassLoader;
   19:	aload_0
   20:	invokestatic	#8; //Method java/security/AccessController.getContext:()Ljava/security/AccessControlContext;
   23:	putfield	#9; //Field acc:Ljava/security/AccessControlContext;
   26:	aload_0
   27:	getfield	#9; //Field acc:Ljava/security/AccessControlContext;
   30:	new	#10; //class java/lang/RuntimePermission
   33:	dup
   34:	ldc	#11; //String getContextClassLoader
   36:	invokespecial	#12; //Method java/lang/RuntimePermission."<init>":(Ljava/lang/String;)V
   39:	invokevirtual	#13; //Method java/security/AccessControlContext.checkPermission:(Ljava/security/Permission;)V
   42:	aload_0
   43:	getfield	#9; //Field acc:Ljava/security/AccessControlContext;
   46:	new	#10; //class java/lang/RuntimePermission
   49:	dup
   50:	ldc	#14; //String setContextClassLoader
   52:	invokespecial	#12; //Method java/lang/RuntimePermission."<init>":(Ljava/lang/String;)V
   55:	invokevirtual	#13; //Method java/security/AccessControlContext.checkPermission:(Ljava/security/Permission;)V
   58:	return

public java.lang.Object call()   throws java.lang.Exception;
  Code:
   Stack=3, Locals=1, Args_size=1
   0:	new	#15; //class scala/actors/threadpool/Executors$PrivilegedCallableUsingCurrentClassLoader$1
   3:	dup
   4:	aload_0
   5:	invokespecial	#16; //Method scala/actors/threadpool/Executors$PrivilegedCallableUsingCurrentClassLoader$1."<init>":(Lscala/actors/threadpool/Executors$PrivilegedCallableUsingCurrentClassLoader;)V
   8:	aload_0
   9:	getfield	#9; //Field acc:Ljava/security/AccessControlContext;
   12:	invokestatic	#17; //Method java/security/AccessController.doPrivileged:(Ljava/security/PrivilegedAction;Ljava/security/AccessControlContext;)Ljava/lang/Object;
   15:	pop
   16:	aload_0
   17:	getfield	#1; //Field exception:Ljava/lang/Exception;
   20:	ifnull	28
   23:	aload_0
   24:	getfield	#1; //Field exception:Ljava/lang/Exception;
   27:	athrow
   28:	aload_0
   29:	getfield	#3; //Field result:Ljava/lang/Object;
   32:	areturn
  Exceptions: 
   throws java.lang.Exception
static java.lang.ClassLoader access$300(scala.actors.threadpool.Executors$PrivilegedCallableUsingCurrentClassLoader);
  Code:
   Stack=1, Locals=1, Args_size=1
   0:	aload_0
   1:	getfield	#4; //Field ccl:Ljava/lang/ClassLoader;
   4:	areturn

static java.lang.Object access$402(scala.actors.threadpool.Executors$PrivilegedCallableUsingCurrentClassLoader, java.lang.Object);
  Code:
   Stack=3, Locals=2, Args_size=2
   0:	aload_0
   1:	aload_1
   2:	dup_x1
   3:	putfield	#3; //Field result:Ljava/lang/Object;
   6:	areturn

static scala.actors.threadpool.Callable access$500(scala.actors.threadpool.Executors$PrivilegedCallableUsingCurrentClassLoader);
  Code:
   Stack=1, Locals=1, Args_size=1
   0:	aload_0
   1:	getfield	#2; //Field task:Lscala/actors/threadpool/Callable;
   4:	areturn

static java.lang.Exception access$602(scala.actors.threadpool.Executors$PrivilegedCallableUsingCurrentClassLoader, java.lang.Exception);
  Code:
   Stack=3, Locals=2, Args_size=2
   0:	aload_0
   1:	aload_1
   2:	dup_x1
   3:	putfield	#1; //Field exception:Ljava/lang/Exception;
   6:	areturn

}

