class scala.actors.threadpool.Executors$PrivilegedThreadFactory$1 extends java.lang.Object implements java.lang.Runnable
  EnclosingMethod: length = 0x4
   00 0E 00 18 
  InnerClass: 
   PrivilegedThreadFactory=class scala/actors/threadpool/Executors$PrivilegedThreadFactory of class scala/actors/threadpool/Executors
   class scala/actors/threadpool/Executors$PrivilegedThreadFactory$1$1
   class scala/actors/threadpool/Executors$PrivilegedThreadFactory$1
  minor version: 0
  major version: 49
  Constant pool:
Field	scala/actors/threadpool/Executors$PrivilegedThreadFactory$1.this$0:Lscala/actors/threadpool/Executors$PrivilegedThreadFactory;
Field	scala/actors/threadpool/Executors$PrivilegedThreadFactory$1.val$r:Ljava/lang/Runnable;
Method	java/lang/Object."<init>":()V
class	scala/actors/threadpool/Executors$PrivilegedThreadFactory$1$1
Method	scala/actors/threadpool/Executors$PrivilegedThreadFactory$1$1."<init>":(Lscala/actors/threadpool/Executors$PrivilegedThreadFactory$1;)V
Method	scala/actors/threadpool/Executors$PrivilegedThreadFactory.access$800:(Lscala/actors/threadpool/Executors$PrivilegedThreadFactory;)Ljava/security/AccessControlContext;
Method	java/security/AccessController.doPrivileged:(Ljava/security/PrivilegedAction;Ljava/security/AccessControlContext;)Ljava/lang/Object;
class	scala/actors/threadpool/Executors$PrivilegedThreadFactory$1
class	java/lang/Object
class	java/lang/Runnable
Asciz	val$r;
Asciz	Ljava/lang/Runnable;;
Asciz	this$0;
class	scala/actors/threadpool/Executors$PrivilegedThreadFactory
Asciz	PrivilegedThreadFactory;
Asciz	InnerClasses;
Asciz	Lscala/actors/threadpool/Executors$PrivilegedThreadFactory;;
Asciz	<init>;
Asciz	(Lscala/actors/threadpool/Executors$PrivilegedThreadFactory;Ljava/lang/Runnable;)V;
Asciz	Code;
Asciz	run;
Asciz	()V;
Asciz	EnclosingMethod;
NameAndType	newThread:(Ljava/lang/Runnable;)Ljava/lang/Thread;
NameAndType	this$0:Lscala/actors/threadpool/Executors$PrivilegedThreadFactory;
NameAndType	val$r:Ljava/lang/Runnable;
NameAndType	"<init>":()V
Asciz	scala/actors/threadpool/Executors$PrivilegedThreadFactory$1$1;
Asciz	;
NameAndType	"<init>":(Lscala/actors/threadpool/Executors$PrivilegedThreadFactory$1;)V
NameAndType	access$800:(Lscala/actors/threadpool/Executors$PrivilegedThreadFactory;)Ljava/security/AccessControlContext;
class	java/security/AccessController
NameAndType	doPrivileged:(Ljava/security/PrivilegedAction;Ljava/security/AccessControlContext;)Ljava/lang/Object;
Asciz	scala/actors/threadpool/Executors$PrivilegedThreadFactory$1;
Asciz	java/lang/Object;
Asciz	java/lang/Runnable;
class	scala/actors/threadpool/Executors
Asciz	scala/actors/threadpool/Executors$PrivilegedThreadFactory;
Asciz	newThread;
Asciz	(Ljava/lang/Runnable;)Ljava/lang/Thread;;
Asciz	(Lscala/actors/threadpool/Executors$PrivilegedThreadFactory$1;)V;
Asciz	access$800;
Asciz	(Lscala/actors/threadpool/Executors$PrivilegedThreadFactory;)Ljava/security/AccessControlContext;;
Asciz	java/security/AccessController;
Asciz	doPrivileged;
Asciz	(Ljava/security/PrivilegedAction;Ljava/security/AccessControlContext;)Ljava/lang/Object;;
Asciz	scala/actors/threadpool/Executors;

{
final java.lang.Runnable val$r;
  Signature: Ljava/lang/Runnable;

final scala.actors.threadpool.Executors$PrivilegedThreadFactory this$0;
  Signature: Lscala/actors/threadpool/Executors$PrivilegedThreadFactory;

scala.actors.threadpool.Executors$PrivilegedThreadFactory$1(scala.actors.threadpool.Executors$PrivilegedThreadFactory, java.lang.Runnable);
  Signature: (Lscala/actors/threadpool/Executors$PrivilegedThreadFactory;Ljava/lang/Runnable;)V
  Code:
   Stack=2, Locals=3, Args_size=3
	aload_0
	aload_1
	putfield	Field this$0:Lscala/actors/threadpool/Executors$PrivilegedThreadFactory;
	aload_0
	aload_2
	putfield	Field val$r:Ljava/lang/Runnable;
	aload_0
	invokespecial	Method java/lang/Object."<init>":()V
	return
  Labels:

public void run();
  Signature: ()V
  Code:
   Stack=3, Locals=1, Args_size=1
	new	class scala/actors/threadpool/Executors$PrivilegedThreadFactory$1$1
	dup
	aload_0
	invokespecial	Method scala/actors/threadpool/Executors$PrivilegedThreadFactory$1$1."<init>":(Lscala/actors/threadpool/Executors$PrivilegedThreadFactory$1;)V
	aload_0
	getfield	Field this$0:Lscala/actors/threadpool/Executors$PrivilegedThreadFactory;
	invokestatic	Method scala/actors/threadpool/Executors$PrivilegedThreadFactory.access$800:(Lscala/actors/threadpool/Executors$PrivilegedThreadFactory;)Ljava/security/AccessControlContext;
	invokestatic	Method java/security/AccessController.doPrivileged:(Ljava/security/PrivilegedAction;Ljava/security/AccessControlContext;)Ljava/lang/Object;
	pop
	return
  Labels:

}

