public class scala.actors.threadpool.FutureTask extends java.lang.Object implements scala.actors.threadpool.RunnableFuture
  minor version: 0
  major version: 49
  Constant pool:
Method	java/lang/Object."<init>":()V
class	java/lang/NullPointerException
Method	java/lang/NullPointerException."<init>":()V
Field	scala/actors/threadpool/FutureTask.callable:Lscala/actors/threadpool/Callable;
Method	scala/actors/threadpool/Executors.callable:(Ljava/lang/Runnable;Ljava/lang/Object;)Lscala/actors/threadpool/Callable;
Method	scala/actors/threadpool/FutureTask."<init>":(Lscala/actors/threadpool/Callable;)V
Field	scala/actors/threadpool/FutureTask.state:I
Method	scala/actors/threadpool/FutureTask.ranOrCancelled:()Z
Field	scala/actors/threadpool/FutureTask.runner:Ljava/lang/Thread;
Method	java/lang/Thread.interrupt:()V
Method	java/lang/Object.notifyAll:()V
Method	scala/actors/threadpool/FutureTask.done:()V
Method	scala/actors/threadpool/FutureTask.waitFor:()V
Method	scala/actors/threadpool/FutureTask.getResult:()Ljava/lang/Object;
Method	scala/actors/threadpool/TimeUnit.toNanos:(J)J
Method	scala/actors/threadpool/FutureTask.waitFor:(J)V
Method	scala/actors/threadpool/FutureTask.setCompleted:(Ljava/lang/Object;)V
Method	scala/actors/threadpool/FutureTask.setFailed:(Ljava/lang/Throwable;)V
Method	java/lang/Thread.currentThread:()Ljava/lang/Thread;
InterfaceMethod	scala/actors/threadpool/Callable.call:()Ljava/lang/Object;
Method	scala/actors/threadpool/FutureTask.set:(Ljava/lang/Object;)V
class	java/lang/Throwable
Method	scala/actors/threadpool/FutureTask.setException:(Ljava/lang/Throwable;)V
Field	scala/actors/threadpool/FutureTask.result:Ljava/lang/Object;
Field	scala/actors/threadpool/FutureTask.exception:Ljava/lang/Throwable;
Method	scala/actors/threadpool/FutureTask.isDone:()Z
Method	java/lang/Object.wait:()V
class	java/lang/IllegalArgumentException
Method	java/lang/IllegalArgumentException."<init>":()V
Method	scala/actors/threadpool/helpers/Utils.nanoTime:()J
Field	scala/actors/threadpool/TimeUnit.NANOSECONDS:Lscala/actors/threadpool/TimeUnit;
Method	scala/actors/threadpool/TimeUnit.timedWait:(Ljava/lang/Object;J)V
class	scala/actors/threadpool/TimeoutException
Method	scala/actors/threadpool/TimeoutException."<init>":()V
class	scala/actors/threadpool/CancellationException
Method	scala/actors/threadpool/CancellationException."<init>":()V
class	scala/actors/threadpool/ExecutionException
Method	scala/actors/threadpool/ExecutionException."<init>":(Ljava/lang/Throwable;)V
class	scala/actors/threadpool/FutureTask
class	java/lang/Object
class	scala/actors/threadpool/RunnableFuture
Asciz	READY;
Asciz	I;
Asciz	ConstantValue;
int	0;
Asciz	RUNNING;
int	1;
Asciz	RAN;
int	2;
Asciz	CANCELLED;
int	4;
Asciz	callable;
Asciz	Lscala/actors/threadpool/Callable;;
Asciz	result;
Asciz	Ljava/lang/Object;;
Asciz	exception;
Asciz	Ljava/lang/Throwable;;
Asciz	state;
Asciz	runner;
Asciz	Ljava/lang/Thread;;
Asciz	<init>;
Asciz	(Lscala/actors/threadpool/Callable;)V;
Asciz	Code;
Asciz	(Ljava/lang/Runnable;Ljava/lang/Object;)V;
Asciz	isCancelled;
Asciz	()Z;
Asciz	isDone;
Asciz	cancel;
Asciz	(Z)Z;
Asciz	get;
Asciz	()Ljava/lang/Object;;
Asciz	Exceptions;
class	java/lang/InterruptedException
Asciz	(JLscala/actors/threadpool/TimeUnit;)Ljava/lang/Object;;
Asciz	done;
Asciz	()V;
Asciz	set;
Asciz	(Ljava/lang/Object;)V;
Asciz	setException;
Asciz	(Ljava/lang/Throwable;)V;
Asciz	run;
Asciz	runAndReset;
Asciz	ranOrCancelled;
Asciz	setCompleted;
Asciz	setFailed;
Asciz	waitFor;
Asciz	(J)V;
Asciz	getResult;
NameAndType	"<init>":()V
Asciz	java/lang/NullPointerException;
NameAndType	callable:Lscala/actors/threadpool/Callable;
class	scala/actors/threadpool/Executors
NameAndType	callable:(Ljava/lang/Runnable;Ljava/lang/Object;)Lscala/actors/threadpool/Callable;
NameAndType	"<init>":(Lscala/actors/threadpool/Callable;)V
NameAndType	state:I
NameAndType	ranOrCancelled:()Z
NameAndType	runner:Ljava/lang/Thread;
class	java/lang/Thread
NameAndType	interrupt:()V
NameAndType	notifyAll:()V
NameAndType	done:()V
NameAndType	waitFor:()V
NameAndType	getResult:()Ljava/lang/Object;
class	scala/actors/threadpool/TimeUnit
NameAndType	toNanos:(J)J
NameAndType	waitFor:(J)V
NameAndType	setCompleted:(Ljava/lang/Object;)V
NameAndType	setFailed:(Ljava/lang/Throwable;)V
NameAndType	currentThread:()Ljava/lang/Thread;
class	scala/actors/threadpool/Callable
NameAndType	call:()Ljava/lang/Object;
NameAndType	set:(Ljava/lang/Object;)V
Asciz	java/lang/Throwable;
NameAndType	setException:(Ljava/lang/Throwable;)V
NameAndType	result:Ljava/lang/Object;
NameAndType	exception:Ljava/lang/Throwable;
NameAndType	isDone:()Z
NameAndType	wait:()V
Asciz	java/lang/IllegalArgumentException;
class	scala/actors/threadpool/helpers/Utils
NameAndType	nanoTime:()J
NameAndType	NANOSECONDS:Lscala/actors/threadpool/TimeUnit;
NameAndType	timedWait:(Ljava/lang/Object;J)V
Asciz	scala/actors/threadpool/TimeoutException;
Asciz	scala/actors/threadpool/CancellationException;
Asciz	scala/actors/threadpool/ExecutionException;
NameAndType	"<init>":(Ljava/lang/Throwable;)V
Asciz	scala/actors/threadpool/FutureTask;
Asciz	java/lang/Object;
Asciz	scala/actors/threadpool/RunnableFuture;
Asciz	java/lang/InterruptedException;
Asciz	scala/actors/threadpool/Executors;
Asciz	(Ljava/lang/Runnable;Ljava/lang/Object;)Lscala/actors/threadpool/Callable;;
Asciz	java/lang/Thread;
Asciz	interrupt;
Asciz	notifyAll;
Asciz	scala/actors/threadpool/TimeUnit;
Asciz	toNanos;
Asciz	(J)J;
Asciz	currentThread;
Asciz	()Ljava/lang/Thread;;
Asciz	scala/actors/threadpool/Callable;
Asciz	call;
Asciz	wait;
Asciz	scala/actors/threadpool/helpers/Utils;
Asciz	nanoTime;
Asciz	()J;
Asciz	NANOSECONDS;
Asciz	Lscala/actors/threadpool/TimeUnit;;
Asciz	timedWait;
Asciz	(Ljava/lang/Object;J)V;

{
private static final int READY;
  Signature: I
  Constant value: int 0
private static final int RUNNING;
  Signature: I
  Constant value: int 1
private static final int RAN;
  Signature: I
  Constant value: int 2
private static final int CANCELLED;
  Signature: I
  Constant value: int 4
private final scala.actors.threadpool.Callable callable;
  Signature: Lscala/actors/threadpool/Callable;

private java.lang.Object result;
  Signature: Ljava/lang/Object;

private java.lang.Throwable exception;
  Signature: Ljava/lang/Throwable;

private int state;
  Signature: I

private volatile java.lang.Thread runner;
  Signature: Ljava/lang/Thread;

public scala.actors.threadpool.FutureTask(scala.actors.threadpool.Callable);
  Signature: (Lscala/actors/threadpool/Callable;)V
  Code:
   Stack=2, Locals=2, Args_size=2
	aload_0
	invokespecial	Method java/lang/Object."<init>":()V
	aload_1
	ifnonnull	l1 // aload_0
	new	class java/lang/NullPointerException
	dup
	invokespecial	Method java/lang/NullPointerException."<init>":()V
	athrow
l1	aload_0
	aload_1
	putfield	Field callable:Lscala/actors/threadpool/Callable;
	return
  Labels:
   	l1 = 16 // aload_0

public scala.actors.threadpool.FutureTask(java.lang.Runnable, java.lang.Object);
  Signature: (Ljava/lang/Runnable;Ljava/lang/Object;)V
  Code:
   Stack=3, Locals=3, Args_size=3
	aload_0
	aload_1
	aload_2
	invokestatic	Method scala/actors/threadpool/Executors.callable:(Ljava/lang/Runnable;Ljava/lang/Object;)Lscala/actors/threadpool/Callable;
	invokespecial	Method "<init>":(Lscala/actors/threadpool/Callable;)V
	return
  Labels:

public synchronized boolean isCancelled();
  Signature: ()Z
  Code:
   Stack=2, Locals=1, Args_size=1
	aload_0
	getfield	Field state:I
	iconst_4
	if_icmpne	l1 // iconst_0
	iconst_1
	goto	l2 // ireturn
l1	iconst_0
l2	ireturn
  Labels:
   	l1 = 12 // iconst_0
   	l2 = 13 // ireturn

public synchronized boolean isDone();
  Signature: ()Z
  Code:
   Stack=1, Locals=1, Args_size=1
	aload_0
	invokespecial	Method ranOrCancelled:()Z
	ifeq	l1 // iconst_0
	aload_0
	getfield	Field runner:Ljava/lang/Thread;
	ifnonnull	l1 // iconst_0
	iconst_1
	goto	l2 // ireturn
l1	iconst_0
l2	ireturn
  Labels:
   	l1 = 18 // iconst_0
   	l2 = 19 // ireturn

public boolean cancel(boolean);
  Signature: (Z)Z
  Code:
   Stack=2, Locals=5, Args_size=2
	aload_0
	dup
	astore_2
	monitorenter
	aload_0
	invokespecial	Method ranOrCancelled:()Z
	ifeq	l1 // aload_0
	iconst_0
	aload_2
	monitorexit
	ireturn
l1	aload_0
	iconst_4
	putfield	Field state:I
	iload_1
	ifeq	l2 // aload_0
	aload_0
	getfield	Field runner:Ljava/lang/Thread;
	astore_3
	aload_3
	ifnull	l2 // aload_0
	aload_3
	invokevirtual	Method java/lang/Thread.interrupt:()V
l2	aload_0
	aconst_null
	putfield	Field runner:Ljava/lang/Thread;
	aload_0
	invokevirtual	Method java/lang/Object.notifyAll:()V
	aload_2
	monitorexit
	goto	l3 // aload_0
	astore	4
	aload_2
	monitorexit
	aload	4
	athrow
l3	aload_0
	invokevirtual	Method done:()V
	iconst_1
	ireturn
  Labels:
   	l1 = 15 // aload_0
   	l2 = 37 // aload_0
   	l3 = 58 // aload_0
  Exception table:
   from   to  target type
     4    14    51   any
    15    48    51   any
    51    55    51   any

public synchronized java.lang.Object get()   throws java.lang.InterruptedException, scala.actors.threadpool.ExecutionException;
  Signature: ()Ljava/lang/Object;
  Code:
   Stack=1, Locals=1, Args_size=1
	aload_0
	invokespecial	Method waitFor:()V
	aload_0
	invokespecial	Method getResult:()Ljava/lang/Object;
	areturn
  Labels:
  Exceptions: 
   throws java.lang.InterruptedException, scala.actors.threadpool.ExecutionException
public synchronized java.lang.Object get(long, scala.actors.threadpool.TimeUnit)   throws java.lang.InterruptedException, scala.actors.threadpool.ExecutionException, scala.actors.threadpool.TimeoutException;
  Signature: (JLscala/actors/threadpool/TimeUnit;)Ljava/lang/Object;
  Code:
   Stack=4, Locals=4, Args_size=3
	aload_0
	aload_3
	lload_1
	invokevirtual	Method scala/actors/threadpool/TimeUnit.toNanos:(J)J
	invokespecial	Method waitFor:(J)V
	aload_0
	invokespecial	Method getResult:()Ljava/lang/Object;
	areturn
  Labels:
  Exceptions: 
   throws java.lang.InterruptedException, scala.actors.threadpool.ExecutionException, scala.actors.threadpool.TimeoutException
protected void done();
  Signature: ()V
  Code:
   Stack=0, Locals=1, Args_size=1
	return
  Labels:

protected void set(java.lang.Object);
  Signature: (Ljava/lang/Object;)V
  Code:
   Stack=2, Locals=2, Args_size=2
	aload_0
	aload_1
	invokespecial	Method setCompleted:(Ljava/lang/Object;)V
	return
  Labels:

protected void setException(java.lang.Throwable);
  Signature: (Ljava/lang/Throwable;)V
  Code:
   Stack=2, Locals=2, Args_size=2
	aload_0
	aload_1
	invokespecial	Method setFailed:(Ljava/lang/Throwable;)V
	return
  Labels:

public void run();
  Signature: ()V
  Code:
   Stack=2, Locals=3, Args_size=1
	aload_0
	dup
	astore_1
	monitorenter
	aload_0
	getfield	Field state:I
	ifeq	l1 // aload_0
	aload_1
	monitorexit
	return
l1	aload_0
	iconst_1
	putfield	Field state:I
	aload_0
	invokestatic	Method java/lang/Thread.currentThread:()Ljava/lang/Thread;
	putfield	Field runner:Ljava/lang/Thread;
	aload_1
	monitorexit
	goto	l2 // aload_0
	astore_2
	aload_1
	monitorexit
	aload_2
	athrow
l2	aload_0
	aload_0
	getfield	Field callable:Lscala/actors/threadpool/Callable;
	invokeinterface	InterfaceMethod scala/actors/threadpool/Callable.call:()Ljava/lang/Object;
	invokevirtual	Method set:(Ljava/lang/Object;)V
	goto	l3 // return
	astore_1
	aload_0
	aload_1
	invokevirtual	Method setException:(Ljava/lang/Throwable;)V
l3	return
  Labels:
   	l1 = 14 // aload_0
   	l2 = 36 // aload_0
   	l3 = 58 // return
  Exception table:
   from   to  target type
     4    13    31   any
    14    28    31   any
    31    34    31   any
    36    49    52   Class java/lang/Throwable


protected boolean runAndReset();
  Signature: ()Z
  Code:
   Stack=2, Locals=4, Args_size=1
	aload_0
	dup
	astore_1
	monitorenter
	aload_0
	getfield	Field state:I
	ifeq	l1 // aload_0
	iconst_0
	aload_1
	monitorexit
	ireturn
l1	aload_0
	iconst_1
	putfield	Field state:I
	aload_0
	invokestatic	Method java/lang/Thread.currentThread:()Ljava/lang/Thread;
	putfield	Field runner:Ljava/lang/Thread;
	aload_1
	monitorexit
	goto	l2 // aload_0
	astore_2
	aload_1
	monitorexit
	aload_2
	athrow
l2	aload_0
	getfield	Field callable:Lscala/actors/threadpool/Callable;
	invokeinterface	InterfaceMethod scala/actors/threadpool/Callable.call:()Ljava/lang/Object;
	pop
	aload_0
	dup
	astore_1
	monitorenter
	aload_0
	aconst_null
	putfield	Field runner:Ljava/lang/Thread;
	aload_0
	getfield	Field state:I
	iconst_1
	if_icmpne	l3 // iconst_0
	aload_0
	iconst_0
	putfield	Field state:I
	iconst_1
	aload_1
	monitorexit
	ireturn
l3	iconst_0
	aload_1
	monitorexit
	ireturn
	astore_3
	aload_1
	monitorexit
	aload_3
	athrow
	astore_1
	aload_0
	aload_1
	invokevirtual	Method setException:(Ljava/lang/Throwable;)V
	iconst_0
	ireturn
  Labels:
   	l1 = 15 // aload_0
   	l2 = 37 // aload_0
   	l3 = 73 // iconst_0
  Exception table:
   from   to  target type
     4    14    32   any
    15    29    32   any
    32    35    32   any
    51    72    77   any
    73    76    77   any
    77    80    77   any
    37    72    82   Class java/lang/Throwable

    73    76    82   Class java/lang/Throwable

    77    82    82   Class java/lang/Throwable


private boolean ranOrCancelled();
  Signature: ()Z
  Code:
   Stack=2, Locals=1, Args_size=1
	aload_0
	getfield	Field state:I
	bipush	6
	iand
	ifeq	l1 // iconst_0
	iconst_1
	goto	l2 // ireturn
l1	iconst_0
l2	ireturn
  Labels:
   	l1 = 14 // iconst_0
   	l2 = 15 // ireturn

private void setCompleted(java.lang.Object);
  Signature: (Ljava/lang/Object;)V
  Code:
   Stack=2, Locals=4, Args_size=2
	aload_0
	dup
	astore_2
	monitorenter
	aload_0
	invokespecial	Method ranOrCancelled:()Z
	ifeq	l1 // aload_0
	aload_2
	monitorexit
	return
l1	aload_0
	iconst_2
	putfield	Field state:I
	aload_0
	aload_1
	putfield	Field result:Ljava/lang/Object;
	aload_0
	aconst_null
	putfield	Field runner:Ljava/lang/Thread;
	aload_0
	invokevirtual	Method java/lang/Object.notifyAll:()V
	aload_2
	monitorexit
	goto	l2 // aload_0
	astore_3
	aload_2
	monitorexit
	aload_3
	athrow
l2	aload_0
	invokevirtual	Method done:()V
	return
  Labels:
   	l1 = 14 // aload_0
   	l2 = 43 // aload_0
  Exception table:
   from   to  target type
     4    13    38   any
    14    35    38   any
    38    41    38   any

private void setFailed(java.lang.Throwable);
  Signature: (Ljava/lang/Throwable;)V
  Code:
   Stack=2, Locals=4, Args_size=2
	aload_0
	dup
	astore_2
	monitorenter
	aload_0
	invokespecial	Method ranOrCancelled:()Z
	ifeq	l1 // aload_0
	aload_2
	monitorexit
	return
l1	aload_0
	iconst_2
	putfield	Field state:I
	aload_0
	aload_1
	putfield	Field exception:Ljava/lang/Throwable;
	aload_0
	aconst_null
	putfield	Field runner:Ljava/lang/Thread;
	aload_0
	invokevirtual	Method java/lang/Object.notifyAll:()V
	aload_2
	monitorexit
	goto	l2 // aload_0
	astore_3
	aload_2
	monitorexit
	aload_3
	athrow
l2	aload_0
	invokevirtual	Method done:()V
	return
  Labels:
   	l1 = 14 // aload_0
   	l2 = 43 // aload_0
  Exception table:
   from   to  target type
     4    13    38   any
    14    35    38   any
    38    41    38   any

private void waitFor()   throws java.lang.InterruptedException;
  Signature: ()V
  Code:
   Stack=1, Locals=1, Args_size=1
l2	aload_0
	invokevirtual	Method isDone:()Z
	ifne	l1 // return
	aload_0
	invokevirtual	Method java/lang/Object.wait:()V
	goto	l2 // aload_0
l1	return
  Labels:
   	l2 = 0 // aload_0
   	l1 = 14 // return
  Exceptions: 
   throws java.lang.InterruptedException
private void waitFor(long)   throws java.lang.InterruptedException, scala.actors.threadpool.TimeoutException;
  Signature: (J)V
  Code:
   Stack=4, Locals=5, Args_size=2
	lload_1
	lconst_0
	lcmp
	ifge	l1 // aload_0
	new	class java/lang/IllegalArgumentException
	dup
	invokespecial	Method java/lang/IllegalArgumentException."<init>":()V
	athrow
l1	aload_0
	invokevirtual	Method isDone:()Z
	ifeq	l2 // invokestatic
	return
l2	invokestatic	Method scala/actors/threadpool/helpers/Utils.nanoTime:()J
	lload_1
	ladd
	lstore_3
l5	lload_1
	lconst_0
	lcmp
	ifle	l3 // new
	getstatic	Field scala/actors/threadpool/TimeUnit.NANOSECONDS:Lscala/actors/threadpool/TimeUnit;
	aload_0
	lload_1
	invokevirtual	Method scala/actors/threadpool/TimeUnit.timedWait:(Ljava/lang/Object;J)V
	aload_0
	invokevirtual	Method isDone:()Z
	ifeq	l4 // lload_3
	return
l4	lload_3
	invokestatic	Method scala/actors/threadpool/helpers/Utils.nanoTime:()J
	lsub
	lstore_1
	goto	l5 // lload_1
l3	new	class scala/actors/threadpool/TimeoutException
	dup
	invokespecial	Method scala/actors/threadpool/TimeoutException."<init>":()V
	athrow
  Labels:
   	l1 = 14 // aload_0
   	l2 = 22 // invokestatic
   	l5 = 28 // lload_1
   	l4 = 50 // lload_3
   	l3 = 59 // new
  Exceptions: 
   throws java.lang.InterruptedException, scala.actors.threadpool.TimeoutException
private java.lang.Object getResult()   throws scala.actors.threadpool.ExecutionException;
  Signature: ()Ljava/lang/Object;
  Code:
   Stack=3, Locals=1, Args_size=1
	aload_0
	getfield	Field state:I
	iconst_4
	if_icmpne	l1 // aload_0
	new	class scala/actors/threadpool/CancellationException
	dup
	invokespecial	Method scala/actors/threadpool/CancellationException."<init>":()V
	athrow
l1	aload_0
	getfield	Field exception:Ljava/lang/Throwable;
	ifnull	l2 // aload_0
	new	class scala/actors/threadpool/ExecutionException
	dup
	aload_0
	getfield	Field exception:Ljava/lang/Throwable;
	invokespecial	Method scala/actors/threadpool/ExecutionException."<init>":(Ljava/lang/Throwable;)V
	athrow
l2	aload_0
	getfield	Field result:Ljava/lang/Object;
	areturn
  Labels:
   	l1 = 16 // aload_0
   	l2 = 35 // aload_0
  Exceptions: 
   throws scala.actors.threadpool.ExecutionException
}

