public class scala.actors.threadpool.FutureTask extends java.lang.Object implements scala.actors.threadpool.RunnableFuture
  minor version: 0
  major version: 49
  Constant pool:
const #1 = Method	#40.#89;	//  java/lang/Object."<init>":()V
const #2 = class	#90;	//  java/lang/NullPointerException
const #3 = Method	#2.#89;	//  java/lang/NullPointerException."<init>":()V
const #4 = Field	#39.#91;	//  scala/actors/threadpool/FutureTask.callable:Lscala/actors/threadpool/Callable;
const #5 = Method	#92.#93;	//  scala/actors/threadpool/Executors.callable:(Ljava/lang/Runnable;Ljava/lang/Object;)Lscala/actors/threadpool/Callable;
const #6 = Method	#39.#94;	//  scala/actors/threadpool/FutureTask."<init>":(Lscala/actors/threadpool/Callable;)V
const #7 = Field	#39.#95;	//  scala/actors/threadpool/FutureTask.state:I
const #8 = Method	#39.#96;	//  scala/actors/threadpool/FutureTask.ranOrCancelled:()Z
const #9 = Field	#39.#97;	//  scala/actors/threadpool/FutureTask.runner:Ljava/lang/Thread;
const #10 = Method	#98.#99;	//  java/lang/Thread.interrupt:()V
const #11 = Method	#40.#100;	//  java/lang/Object.notifyAll:()V
const #12 = Method	#39.#101;	//  scala/actors/threadpool/FutureTask.done:()V
const #13 = Method	#39.#102;	//  scala/actors/threadpool/FutureTask.waitFor:()V
const #14 = Method	#39.#103;	//  scala/actors/threadpool/FutureTask.getResult:()Ljava/lang/Object;
const #15 = Method	#104.#105;	//  scala/actors/threadpool/TimeUnit.toNanos:(J)J
const #16 = Method	#39.#106;	//  scala/actors/threadpool/FutureTask.waitFor:(J)V
const #17 = Method	#39.#107;	//  scala/actors/threadpool/FutureTask.setCompleted:(Ljava/lang/Object;)V
const #18 = Method	#39.#108;	//  scala/actors/threadpool/FutureTask.setFailed:(Ljava/lang/Throwable;)V
const #19 = Method	#98.#109;	//  java/lang/Thread.currentThread:()Ljava/lang/Thread;
const #20 = InterfaceMethod	#110.#111;	//  scala/actors/threadpool/Callable.call:()Ljava/lang/Object;
const #21 = Method	#39.#112;	//  scala/actors/threadpool/FutureTask.set:(Ljava/lang/Object;)V
const #22 = class	#113;	//  java/lang/Throwable
const #23 = Method	#39.#114;	//  scala/actors/threadpool/FutureTask.setException:(Ljava/lang/Throwable;)V
const #24 = Field	#39.#115;	//  scala/actors/threadpool/FutureTask.result:Ljava/lang/Object;
const #25 = Field	#39.#116;	//  scala/actors/threadpool/FutureTask.exception:Ljava/lang/Throwable;
const #26 = Method	#39.#117;	//  scala/actors/threadpool/FutureTask.isDone:()Z
const #27 = Method	#40.#118;	//  java/lang/Object.wait:()V
const #28 = class	#119;	//  java/lang/IllegalArgumentException
const #29 = Method	#28.#89;	//  java/lang/IllegalArgumentException."<init>":()V
const #30 = Method	#120.#121;	//  scala/actors/threadpool/helpers/Utils.nanoTime:()J
const #31 = Field	#104.#122;	//  scala/actors/threadpool/TimeUnit.NANOSECONDS:Lscala/actors/threadpool/TimeUnit;
const #32 = Method	#104.#123;	//  scala/actors/threadpool/TimeUnit.timedWait:(Ljava/lang/Object;J)V
const #33 = class	#124;	//  scala/actors/threadpool/TimeoutException
const #34 = Method	#33.#89;	//  scala/actors/threadpool/TimeoutException."<init>":()V
const #35 = class	#125;	//  scala/actors/threadpool/CancellationException
const #36 = Method	#35.#89;	//  scala/actors/threadpool/CancellationException."<init>":()V
const #37 = class	#126;	//  scala/actors/threadpool/ExecutionException
const #38 = Method	#37.#127;	//  scala/actors/threadpool/ExecutionException."<init>":(Ljava/lang/Throwable;)V
const #39 = class	#128;	//  scala/actors/threadpool/FutureTask
const #40 = class	#129;	//  java/lang/Object
const #41 = class	#130;	//  scala/actors/threadpool/RunnableFuture
const #42 = Asciz	READY;
const #43 = Asciz	I;
const #44 = Asciz	ConstantValue;
const #45 = int	0;
const #46 = Asciz	RUNNING;
const #47 = int	1;
const #48 = Asciz	RAN;
const #49 = int	2;
const #50 = Asciz	CANCELLED;
const #51 = int	4;
const #52 = Asciz	callable;
const #53 = Asciz	Lscala/actors/threadpool/Callable;;
const #54 = Asciz	result;
const #55 = Asciz	Ljava/lang/Object;;
const #56 = Asciz	exception;
const #57 = Asciz	Ljava/lang/Throwable;;
const #58 = Asciz	state;
const #59 = Asciz	runner;
const #60 = Asciz	Ljava/lang/Thread;;
const #61 = Asciz	<init>;
const #62 = Asciz	(Lscala/actors/threadpool/Callable;)V;
const #63 = Asciz	Code;
const #64 = Asciz	(Ljava/lang/Runnable;Ljava/lang/Object;)V;
const #65 = Asciz	isCancelled;
const #66 = Asciz	()Z;
const #67 = Asciz	isDone;
const #68 = Asciz	cancel;
const #69 = Asciz	(Z)Z;
const #70 = Asciz	get;
const #71 = Asciz	()Ljava/lang/Object;;
const #72 = Asciz	Exceptions;
const #73 = class	#131;	//  java/lang/InterruptedException
const #74 = Asciz	(JLscala/actors/threadpool/TimeUnit;)Ljava/lang/Object;;
const #75 = Asciz	done;
const #76 = Asciz	()V;
const #77 = Asciz	set;
const #78 = Asciz	(Ljava/lang/Object;)V;
const #79 = Asciz	setException;
const #80 = Asciz	(Ljava/lang/Throwable;)V;
const #81 = Asciz	run;
const #82 = Asciz	runAndReset;
const #83 = Asciz	ranOrCancelled;
const #84 = Asciz	setCompleted;
const #85 = Asciz	setFailed;
const #86 = Asciz	waitFor;
const #87 = Asciz	(J)V;
const #88 = Asciz	getResult;
const #89 = NameAndType	#61:#76;//  "<init>":()V
const #90 = Asciz	java/lang/NullPointerException;
const #91 = NameAndType	#52:#53;//  callable:Lscala/actors/threadpool/Callable;
const #92 = class	#132;	//  scala/actors/threadpool/Executors
const #93 = NameAndType	#52:#133;//  callable:(Ljava/lang/Runnable;Ljava/lang/Object;)Lscala/actors/threadpool/Callable;
const #94 = NameAndType	#61:#62;//  "<init>":(Lscala/actors/threadpool/Callable;)V
const #95 = NameAndType	#58:#43;//  state:I
const #96 = NameAndType	#83:#66;//  ranOrCancelled:()Z
const #97 = NameAndType	#59:#60;//  runner:Ljava/lang/Thread;
const #98 = class	#134;	//  java/lang/Thread
const #99 = NameAndType	#135:#76;//  interrupt:()V
const #100 = NameAndType	#136:#76;//  notifyAll:()V
const #101 = NameAndType	#75:#76;//  done:()V
const #102 = NameAndType	#86:#76;//  waitFor:()V
const #103 = NameAndType	#88:#71;//  getResult:()Ljava/lang/Object;
const #104 = class	#137;	//  scala/actors/threadpool/TimeUnit
const #105 = NameAndType	#138:#139;//  toNanos:(J)J
const #106 = NameAndType	#86:#87;//  waitFor:(J)V
const #107 = NameAndType	#84:#78;//  setCompleted:(Ljava/lang/Object;)V
const #108 = NameAndType	#85:#80;//  setFailed:(Ljava/lang/Throwable;)V
const #109 = NameAndType	#140:#141;//  currentThread:()Ljava/lang/Thread;
const #110 = class	#142;	//  scala/actors/threadpool/Callable
const #111 = NameAndType	#143:#71;//  call:()Ljava/lang/Object;
const #112 = NameAndType	#77:#78;//  set:(Ljava/lang/Object;)V
const #113 = Asciz	java/lang/Throwable;
const #114 = NameAndType	#79:#80;//  setException:(Ljava/lang/Throwable;)V
const #115 = NameAndType	#54:#55;//  result:Ljava/lang/Object;
const #116 = NameAndType	#56:#57;//  exception:Ljava/lang/Throwable;
const #117 = NameAndType	#67:#66;//  isDone:()Z
const #118 = NameAndType	#144:#76;//  wait:()V
const #119 = Asciz	java/lang/IllegalArgumentException;
const #120 = class	#145;	//  scala/actors/threadpool/helpers/Utils
const #121 = NameAndType	#146:#147;//  nanoTime:()J
const #122 = NameAndType	#148:#149;//  NANOSECONDS:Lscala/actors/threadpool/TimeUnit;
const #123 = NameAndType	#150:#151;//  timedWait:(Ljava/lang/Object;J)V
const #124 = Asciz	scala/actors/threadpool/TimeoutException;
const #125 = Asciz	scala/actors/threadpool/CancellationException;
const #126 = Asciz	scala/actors/threadpool/ExecutionException;
const #127 = NameAndType	#61:#80;//  "<init>":(Ljava/lang/Throwable;)V
const #128 = Asciz	scala/actors/threadpool/FutureTask;
const #129 = Asciz	java/lang/Object;
const #130 = Asciz	scala/actors/threadpool/RunnableFuture;
const #131 = Asciz	java/lang/InterruptedException;
const #132 = Asciz	scala/actors/threadpool/Executors;
const #133 = Asciz	(Ljava/lang/Runnable;Ljava/lang/Object;)Lscala/actors/threadpool/Callable;;
const #134 = Asciz	java/lang/Thread;
const #135 = Asciz	interrupt;
const #136 = Asciz	notifyAll;
const #137 = Asciz	scala/actors/threadpool/TimeUnit;
const #138 = Asciz	toNanos;
const #139 = Asciz	(J)J;
const #140 = Asciz	currentThread;
const #141 = Asciz	()Ljava/lang/Thread;;
const #142 = Asciz	scala/actors/threadpool/Callable;
const #143 = Asciz	call;
const #144 = Asciz	wait;
const #145 = Asciz	scala/actors/threadpool/helpers/Utils;
const #146 = Asciz	nanoTime;
const #147 = Asciz	()J;
const #148 = Asciz	NANOSECONDS;
const #149 = Asciz	Lscala/actors/threadpool/TimeUnit;;
const #150 = Asciz	timedWait;
const #151 = Asciz	(Ljava/lang/Object;J)V;

{
public scala.actors.threadpool.FutureTask(scala.actors.threadpool.Callable);
  Code:
   Stack=2, Locals=2, Args_size=2
   0:	aload_0
   1:	invokespecial	#1; //Method java/lang/Object."<init>":()V
   4:	aload_1
   5:	ifnonnull	16
   8:	new	#2; //class java/lang/NullPointerException
   11:	dup
   12:	invokespecial	#3; //Method java/lang/NullPointerException."<init>":()V
   15:	athrow
   16:	aload_0
   17:	aload_1
   18:	putfield	#4; //Field callable:Lscala/actors/threadpool/Callable;
   21:	return

public scala.actors.threadpool.FutureTask(java.lang.Runnable, java.lang.Object);
  Code:
   Stack=3, Locals=3, Args_size=3
   0:	aload_0
   1:	aload_1
   2:	aload_2
   3:	invokestatic	#5; //Method scala/actors/threadpool/Executors.callable:(Ljava/lang/Runnable;Ljava/lang/Object;)Lscala/actors/threadpool/Callable;
   6:	invokespecial	#6; //Method "<init>":(Lscala/actors/threadpool/Callable;)V
   9:	return

public synchronized boolean isCancelled();
  Code:
   Stack=2, Locals=1, Args_size=1
   0:	aload_0
   1:	getfield	#7; //Field state:I
   4:	iconst_4
   5:	if_icmpne	12
   8:	iconst_1
   9:	goto	13
   12:	iconst_0
   13:	ireturn

public synchronized boolean isDone();
  Code:
   Stack=1, Locals=1, Args_size=1
   0:	aload_0
   1:	invokespecial	#8; //Method ranOrCancelled:()Z
   4:	ifeq	18
   7:	aload_0
   8:	getfield	#9; //Field runner:Ljava/lang/Thread;
   11:	ifnonnull	18
   14:	iconst_1
   15:	goto	19
   18:	iconst_0
   19:	ireturn

public boolean cancel(boolean);
  Code:
   Stack=2, Locals=5, Args_size=2
   0:	aload_0
   1:	dup
   2:	astore_2
   3:	monitorenter
   4:	aload_0
   5:	invokespecial	#8; //Method ranOrCancelled:()Z
   8:	ifeq	15
   11:	iconst_0
   12:	aload_2
   13:	monitorexit
   14:	ireturn
   15:	aload_0
   16:	iconst_4
   17:	putfield	#7; //Field state:I
   20:	iload_1
   21:	ifeq	37
   24:	aload_0
   25:	getfield	#9; //Field runner:Ljava/lang/Thread;
   28:	astore_3
   29:	aload_3
   30:	ifnull	37
   33:	aload_3
   34:	invokevirtual	#10; //Method java/lang/Thread.interrupt:()V
   37:	aload_0
   38:	aconst_null
   39:	putfield	#9; //Field runner:Ljava/lang/Thread;
   42:	aload_0
   43:	invokevirtual	#11; //Method java/lang/Object.notifyAll:()V
   46:	aload_2
   47:	monitorexit
   48:	goto	58
   51:	astore	4
   53:	aload_2
   54:	monitorexit
   55:	aload	4
   57:	athrow
   58:	aload_0
   59:	invokevirtual	#12; //Method done:()V
   62:	iconst_1
   63:	ireturn
  Exception table:
   from   to  target type
     4    14    51   any
    15    48    51   any
    51    55    51   any

public synchronized java.lang.Object get()   throws java.lang.InterruptedException, scala.actors.threadpool.ExecutionException;
  Code:
   Stack=1, Locals=1, Args_size=1
   0:	aload_0
   1:	invokespecial	#13; //Method waitFor:()V
   4:	aload_0
   5:	invokespecial	#14; //Method getResult:()Ljava/lang/Object;
   8:	areturn
  Exceptions: 
   throws java.lang.InterruptedException, scala.actors.threadpool.ExecutionException
public synchronized java.lang.Object get(long, scala.actors.threadpool.TimeUnit)   throws java.lang.InterruptedException, scala.actors.threadpool.ExecutionException, scala.actors.threadpool.TimeoutException;
  Code:
   Stack=4, Locals=4, Args_size=3
   0:	aload_0
   1:	aload_3
   2:	lload_1
   3:	invokevirtual	#15; //Method scala/actors/threadpool/TimeUnit.toNanos:(J)J
   6:	invokespecial	#16; //Method waitFor:(J)V
   9:	aload_0
   10:	invokespecial	#14; //Method getResult:()Ljava/lang/Object;
   13:	areturn
  Exceptions: 
   throws java.lang.InterruptedException, scala.actors.threadpool.ExecutionException, scala.actors.threadpool.TimeoutException
protected void done();
  Code:
   Stack=0, Locals=1, Args_size=1
   0:	return

protected void set(java.lang.Object);
  Code:
   Stack=2, Locals=2, Args_size=2
   0:	aload_0
   1:	aload_1
   2:	invokespecial	#17; //Method setCompleted:(Ljava/lang/Object;)V
   5:	return

protected void setException(java.lang.Throwable);
  Code:
   Stack=2, Locals=2, Args_size=2
   0:	aload_0
   1:	aload_1
   2:	invokespecial	#18; //Method setFailed:(Ljava/lang/Throwable;)V
   5:	return

public void run();
  Code:
   Stack=2, Locals=3, Args_size=1
   0:	aload_0
   1:	dup
   2:	astore_1
   3:	monitorenter
   4:	aload_0
   5:	getfield	#7; //Field state:I
   8:	ifeq	14
   11:	aload_1
   12:	monitorexit
   13:	return
   14:	aload_0
   15:	iconst_1
   16:	putfield	#7; //Field state:I
   19:	aload_0
   20:	invokestatic	#19; //Method java/lang/Thread.currentThread:()Ljava/lang/Thread;
   23:	putfield	#9; //Field runner:Ljava/lang/Thread;
   26:	aload_1
   27:	monitorexit
   28:	goto	36
   31:	astore_2
   32:	aload_1
   33:	monitorexit
   34:	aload_2
   35:	athrow
   36:	aload_0
   37:	aload_0
   38:	getfield	#4; //Field callable:Lscala/actors/threadpool/Callable;
   41:	invokeinterface	#20,  1; //InterfaceMethod scala/actors/threadpool/Callable.call:()Ljava/lang/Object;
   46:	invokevirtual	#21; //Method set:(Ljava/lang/Object;)V
   49:	goto	58
   52:	astore_1
   53:	aload_0
   54:	aload_1
   55:	invokevirtual	#23; //Method setException:(Ljava/lang/Throwable;)V
   58:	return
  Exception table:
   from   to  target type
     4    13    31   any
    14    28    31   any
    31    34    31   any
    36    49    52   Class java/lang/Throwable


protected boolean runAndReset();
  Code:
   Stack=2, Locals=4, Args_size=1
   0:	aload_0
   1:	dup
   2:	astore_1
   3:	monitorenter
   4:	aload_0
   5:	getfield	#7; //Field state:I
   8:	ifeq	15
   11:	iconst_0
   12:	aload_1
   13:	monitorexit
   14:	ireturn
   15:	aload_0
   16:	iconst_1
   17:	putfield	#7; //Field state:I
   20:	aload_0
   21:	invokestatic	#19; //Method java/lang/Thread.currentThread:()Ljava/lang/Thread;
   24:	putfield	#9; //Field runner:Ljava/lang/Thread;
   27:	aload_1
   28:	monitorexit
   29:	goto	37
   32:	astore_2
   33:	aload_1
   34:	monitorexit
   35:	aload_2
   36:	athrow
   37:	aload_0
   38:	getfield	#4; //Field callable:Lscala/actors/threadpool/Callable;
   41:	invokeinterface	#20,  1; //InterfaceMethod scala/actors/threadpool/Callable.call:()Ljava/lang/Object;
   46:	pop
   47:	aload_0
   48:	dup
   49:	astore_1
   50:	monitorenter
   51:	aload_0
   52:	aconst_null
   53:	putfield	#9; //Field runner:Ljava/lang/Thread;
   56:	aload_0
   57:	getfield	#7; //Field state:I
   60:	iconst_1
   61:	if_icmpne	73
   64:	aload_0
   65:	iconst_0
   66:	putfield	#7; //Field state:I
   69:	iconst_1
   70:	aload_1
   71:	monitorexit
   72:	ireturn
   73:	iconst_0
   74:	aload_1
   75:	monitorexit
   76:	ireturn
   77:	astore_3
   78:	aload_1
   79:	monitorexit
   80:	aload_3
   81:	athrow
   82:	astore_1
   83:	aload_0
   84:	aload_1
   85:	invokevirtual	#23; //Method setException:(Ljava/lang/Throwable;)V
   88:	iconst_0
   89:	ireturn
  Exception table:
   from   to  target type
     4    14    32   any
    15    29    32   any
    32    35    32   any
    51    72    77   any
    73    76    77   any
    77    80    77   any
    37    72    82   Class java/lang/Throwable

    73    76    82   Class java/lang/Throwable

    77    82    82   Class java/lang/Throwable


}

