class scala.actors.threadpool.LinkedBlockingQueue$Itr extends java.lang.Object implements java.util.Iterator
  InnerClass: 
   Node=class scala/actors/threadpool/LinkedBlockingQueue$Node of class scala/actors/threadpool/LinkedBlockingQueue
   Itr=class scala/actors/threadpool/LinkedBlockingQueue$Itr of class scala/actors/threadpool/LinkedBlockingQueue
  minor version: 0
  major version: 49
  Constant pool:
Field	scala/actors/threadpool/LinkedBlockingQueue$Itr.this$0:Lscala/actors/threadpool/LinkedBlockingQueue;
Method	java/lang/Object."<init>":()V
Method	scala/actors/threadpool/LinkedBlockingQueue.access$100:(Lscala/actors/threadpool/LinkedBlockingQueue;)Ljava/lang/Object;
Method	scala/actors/threadpool/LinkedBlockingQueue.access$200:(Lscala/actors/threadpool/LinkedBlockingQueue;)Ljava/lang/Object;
Method	scala/actors/threadpool/LinkedBlockingQueue.access$300:(Lscala/actors/threadpool/LinkedBlockingQueue;)Lscala/actors/threadpool/LinkedBlockingQueue$Node;
Field	scala/actors/threadpool/LinkedBlockingQueue$Node.next:Lscala/actors/threadpool/LinkedBlockingQueue$Node;
Field	scala/actors/threadpool/LinkedBlockingQueue$Itr.current:Lscala/actors/threadpool/LinkedBlockingQueue$Node;
Field	scala/actors/threadpool/LinkedBlockingQueue$Node.item:Ljava/lang/Object;
Field	scala/actors/threadpool/LinkedBlockingQueue$Itr.currentElement:Ljava/lang/Object;
class	java/util/NoSuchElementException
Method	java/util/NoSuchElementException."<init>":()V
Field	scala/actors/threadpool/LinkedBlockingQueue$Itr.lastRet:Lscala/actors/threadpool/LinkedBlockingQueue$Node;
class	java/lang/IllegalStateException
Method	java/lang/IllegalStateException."<init>":()V
Method	scala/actors/threadpool/LinkedBlockingQueue.access$400:(Lscala/actors/threadpool/LinkedBlockingQueue;)Lscala/actors/threadpool/LinkedBlockingQueue$Node;
Method	scala/actors/threadpool/LinkedBlockingQueue.access$402:(Lscala/actors/threadpool/LinkedBlockingQueue;Lscala/actors/threadpool/LinkedBlockingQueue$Node;)Lscala/actors/threadpool/LinkedBlockingQueue$Node;
Method	scala/actors/threadpool/LinkedBlockingQueue.access$510:(Lscala/actors/threadpool/LinkedBlockingQueue;)I
Method	scala/actors/threadpool/LinkedBlockingQueue.access$600:(Lscala/actors/threadpool/LinkedBlockingQueue;)I
Method	java/lang/Object.notifyAll:()V
class	scala/actors/threadpool/LinkedBlockingQueue$Itr
class	java/lang/Object
class	java/util/Iterator
Asciz	current;
class	scala/actors/threadpool/LinkedBlockingQueue$Node
Asciz	Node;
Asciz	InnerClasses;
Asciz	Lscala/actors/threadpool/LinkedBlockingQueue$Node;;
Asciz	lastRet;
Asciz	currentElement;
Asciz	Ljava/lang/Object;;
Asciz	this$0;
Asciz	Lscala/actors/threadpool/LinkedBlockingQueue;;
Asciz	<init>;
Asciz	(Lscala/actors/threadpool/LinkedBlockingQueue;)V;
Asciz	Code;
Asciz	hasNext;
Asciz	()Z;
Asciz	next;
Asciz	()Ljava/lang/Object;;
Asciz	remove;
Asciz	()V;
NameAndType	this$0:Lscala/actors/threadpool/LinkedBlockingQueue;
NameAndType	"<init>":()V
class	scala/actors/threadpool/LinkedBlockingQueue
NameAndType	access$100:(Lscala/actors/threadpool/LinkedBlockingQueue;)Ljava/lang/Object;
NameAndType	access$200:(Lscala/actors/threadpool/LinkedBlockingQueue;)Ljava/lang/Object;
NameAndType	access$300:(Lscala/actors/threadpool/LinkedBlockingQueue;)Lscala/actors/threadpool/LinkedBlockingQueue$Node;
NameAndType	next:Lscala/actors/threadpool/LinkedBlockingQueue$Node;
NameAndType	current:Lscala/actors/threadpool/LinkedBlockingQueue$Node;
NameAndType	item:Ljava/lang/Object;
NameAndType	currentElement:Ljava/lang/Object;
Asciz	java/util/NoSuchElementException;
NameAndType	lastRet:Lscala/actors/threadpool/LinkedBlockingQueue$Node;
Asciz	java/lang/IllegalStateException;
NameAndType	access$400:(Lscala/actors/threadpool/LinkedBlockingQueue;)Lscala/actors/threadpool/LinkedBlockingQueue$Node;
NameAndType	access$402:(Lscala/actors/threadpool/LinkedBlockingQueue;Lscala/actors/threadpool/LinkedBlockingQueue$Node;)Lscala/actors/threadpool/LinkedBlockingQueue$Node;
NameAndType	access$510:(Lscala/actors/threadpool/LinkedBlockingQueue;)I
NameAndType	access$600:(Lscala/actors/threadpool/LinkedBlockingQueue;)I
NameAndType	notifyAll:()V
Asciz	scala/actors/threadpool/LinkedBlockingQueue$Itr;
Asciz	Itr;
Asciz	java/lang/Object;
Asciz	java/util/Iterator;
Asciz	scala/actors/threadpool/LinkedBlockingQueue$Node;
Asciz	scala/actors/threadpool/LinkedBlockingQueue;
Asciz	access$100;
Asciz	(Lscala/actors/threadpool/LinkedBlockingQueue;)Ljava/lang/Object;;
Asciz	access$200;
Asciz	access$300;
Asciz	(Lscala/actors/threadpool/LinkedBlockingQueue;)Lscala/actors/threadpool/LinkedBlockingQueue$Node;;
Asciz	item;
Asciz	access$400;
Asciz	access$402;
Asciz	(Lscala/actors/threadpool/LinkedBlockingQueue;Lscala/actors/threadpool/LinkedBlockingQueue$Node;)Lscala/actors/threadpool/LinkedBlockingQueue$Node;;
Asciz	access$510;
Asciz	(Lscala/actors/threadpool/LinkedBlockingQueue;)I;
Asciz	access$600;
Asciz	notifyAll;

{
private scala.actors.threadpool.LinkedBlockingQueue$Node current;
  Signature: Lscala/actors/threadpool/LinkedBlockingQueue$Node;

private scala.actors.threadpool.LinkedBlockingQueue$Node lastRet;
  Signature: Lscala/actors/threadpool/LinkedBlockingQueue$Node;

private java.lang.Object currentElement;
  Signature: Ljava/lang/Object;

final scala.actors.threadpool.LinkedBlockingQueue this$0;
  Signature: Lscala/actors/threadpool/LinkedBlockingQueue;

scala.actors.threadpool.LinkedBlockingQueue$Itr(scala.actors.threadpool.LinkedBlockingQueue);
  Signature: (Lscala/actors/threadpool/LinkedBlockingQueue;)V
  Code:
   Stack=2, Locals=6, Args_size=2
	aload_0
	aload_1
	putfield	Field this$0:Lscala/actors/threadpool/LinkedBlockingQueue;
	aload_0
	invokespecial	Method java/lang/Object."<init>":()V
	aload_1
	invokestatic	Method scala/actors/threadpool/LinkedBlockingQueue.access$100:(Lscala/actors/threadpool/LinkedBlockingQueue;)Ljava/lang/Object;
	dup
	astore_2
	monitorenter
	aload_1
	invokestatic	Method scala/actors/threadpool/LinkedBlockingQueue.access$200:(Lscala/actors/threadpool/LinkedBlockingQueue;)Ljava/lang/Object;
	dup
	astore_3
	monitorenter
	aload_0
	aload_1
	invokestatic	Method scala/actors/threadpool/LinkedBlockingQueue.access$300:(Lscala/actors/threadpool/LinkedBlockingQueue;)Lscala/actors/threadpool/LinkedBlockingQueue$Node;
	getfield	Field scala/actors/threadpool/LinkedBlockingQueue$Node.next:Lscala/actors/threadpool/LinkedBlockingQueue$Node;
	putfield	Field current:Lscala/actors/threadpool/LinkedBlockingQueue$Node;
	aload_0
	getfield	Field current:Lscala/actors/threadpool/LinkedBlockingQueue$Node;
	ifnull	l1 // aload_3
	aload_0
	aload_0
	getfield	Field current:Lscala/actors/threadpool/LinkedBlockingQueue$Node;
	getfield	Field scala/actors/threadpool/LinkedBlockingQueue$Node.item:Ljava/lang/Object;
	putfield	Field currentElement:Ljava/lang/Object;
l1	aload_3
	monitorexit
	goto	l2 // aload_2
	astore	4
	aload_3
	monitorexit
	aload	4
	athrow
l2	aload_2
	monitorexit
	goto	l3 // return
	astore	5
	aload_2
	monitorexit
	aload	5
	athrow
l3	return
  Labels:
   	l1 = 52 // aload_3
   	l2 = 64 // aload_2
   	l3 = 76 // return
  Exception table:
   from   to  target type
    23    54    57   any
    57    61    57   any
    16    66    69   any
    69    73    69   any

public boolean hasNext();
  Signature: ()Z
  Code:
   Stack=1, Locals=1, Args_size=1
	aload_0
	getfield	Field current:Lscala/actors/threadpool/LinkedBlockingQueue$Node;
	ifnull	l1 // iconst_0
	iconst_1
	goto	l2 // ireturn
l1	iconst_0
l2	ireturn
  Labels:
   	l1 = 11 // iconst_0
   	l2 = 12 // ireturn

public java.lang.Object next();
  Signature: ()Ljava/lang/Object;
  Code:
   Stack=2, Locals=6, Args_size=1
	aload_0
	getfield	Field this$0:Lscala/actors/threadpool/LinkedBlockingQueue;
	invokestatic	Method scala/actors/threadpool/LinkedBlockingQueue.access$100:(Lscala/actors/threadpool/LinkedBlockingQueue;)Ljava/lang/Object;
	dup
	astore_1
	monitorenter
	aload_0
	getfield	Field this$0:Lscala/actors/threadpool/LinkedBlockingQueue;
	invokestatic	Method scala/actors/threadpool/LinkedBlockingQueue.access$200:(Lscala/actors/threadpool/LinkedBlockingQueue;)Ljava/lang/Object;
	dup
	astore_2
	monitorenter
	aload_0
	getfield	Field current:Lscala/actors/threadpool/LinkedBlockingQueue$Node;
	ifnonnull	l1 // aload_0
	new	class java/util/NoSuchElementException
	dup
	invokespecial	Method java/util/NoSuchElementException."<init>":()V
	athrow
l1	aload_0
	getfield	Field currentElement:Ljava/lang/Object;
	astore_3
	aload_0
	aload_0
	getfield	Field current:Lscala/actors/threadpool/LinkedBlockingQueue$Node;
	putfield	Field lastRet:Lscala/actors/threadpool/LinkedBlockingQueue$Node;
	aload_0
	aload_0
	getfield	Field current:Lscala/actors/threadpool/LinkedBlockingQueue$Node;
	getfield	Field scala/actors/threadpool/LinkedBlockingQueue$Node.next:Lscala/actors/threadpool/LinkedBlockingQueue$Node;
	putfield	Field current:Lscala/actors/threadpool/LinkedBlockingQueue$Node;
	aload_0
	getfield	Field current:Lscala/actors/threadpool/LinkedBlockingQueue$Node;
	ifnull	l2 // aload_3
	aload_0
	aload_0
	getfield	Field current:Lscala/actors/threadpool/LinkedBlockingQueue$Node;
	getfield	Field scala/actors/threadpool/LinkedBlockingQueue$Node.item:Ljava/lang/Object;
	putfield	Field currentElement:Ljava/lang/Object;
l2	aload_3
	aload_2
	monitorexit
	aload_1
	monitorexit
	areturn
	astore	4
	aload_2
	monitorexit
	aload	4
	athrow
	astore	5
	aload_1
	monitorexit
	aload	5
	athrow
  Labels:
   	l1 = 35 // aload_0
   	l2 = 77 // aload_3
  Exception table:
   from   to  target type
    20    80    83   any
    83    87    83   any
    10    82    90   any
    83    94    90   any

public void remove();
  Signature: ()V
  Code:
   Stack=2, Locals=11, Args_size=1
	aload_0
	getfield	Field lastRet:Lscala/actors/threadpool/LinkedBlockingQueue$Node;
	ifnonnull	l1 // aload_0
	new	class java/lang/IllegalStateException
	dup
	invokespecial	Method java/lang/IllegalStateException."<init>":()V
	athrow
l1	aload_0
	getfield	Field this$0:Lscala/actors/threadpool/LinkedBlockingQueue;
	invokestatic	Method scala/actors/threadpool/LinkedBlockingQueue.access$100:(Lscala/actors/threadpool/LinkedBlockingQueue;)Ljava/lang/Object;
	dup
	astore_1
	monitorenter
	aload_0
	getfield	Field this$0:Lscala/actors/threadpool/LinkedBlockingQueue;
	invokestatic	Method scala/actors/threadpool/LinkedBlockingQueue.access$200:(Lscala/actors/threadpool/LinkedBlockingQueue;)Ljava/lang/Object;
	dup
	astore_2
	monitorenter
	aload_0
	getfield	Field lastRet:Lscala/actors/threadpool/LinkedBlockingQueue$Node;
	astore_3
	aload_0
	aconst_null
	putfield	Field lastRet:Lscala/actors/threadpool/LinkedBlockingQueue$Node;
	aload_0
	getfield	Field this$0:Lscala/actors/threadpool/LinkedBlockingQueue;
	invokestatic	Method scala/actors/threadpool/LinkedBlockingQueue.access$300:(Lscala/actors/threadpool/LinkedBlockingQueue;)Lscala/actors/threadpool/LinkedBlockingQueue$Node;
	astore	4
	aload_0
	getfield	Field this$0:Lscala/actors/threadpool/LinkedBlockingQueue;
	invokestatic	Method scala/actors/threadpool/LinkedBlockingQueue.access$300:(Lscala/actors/threadpool/LinkedBlockingQueue;)Lscala/actors/threadpool/LinkedBlockingQueue$Node;
	getfield	Field scala/actors/threadpool/LinkedBlockingQueue$Node.next:Lscala/actors/threadpool/LinkedBlockingQueue$Node;
	astore	5
l3	aload	5
	ifnull	l2 // aload
	aload	5
	aload_3
	if_acmpeq	l2 // aload
	aload	5
	astore	4
	aload	5
	getfield	Field scala/actors/threadpool/LinkedBlockingQueue$Node.next:Lscala/actors/threadpool/LinkedBlockingQueue$Node;
	astore	5
	goto	l3 // aload
l2	aload	5
	aload_3
	if_acmpne	l4 // aload_2
	aload	5
	aconst_null
	putfield	Field scala/actors/threadpool/LinkedBlockingQueue$Node.item:Ljava/lang/Object;
	aload	4
	aload	5
	getfield	Field scala/actors/threadpool/LinkedBlockingQueue$Node.next:Lscala/actors/threadpool/LinkedBlockingQueue$Node;
	putfield	Field scala/actors/threadpool/LinkedBlockingQueue$Node.next:Lscala/actors/threadpool/LinkedBlockingQueue$Node;
	aload_0
	getfield	Field this$0:Lscala/actors/threadpool/LinkedBlockingQueue;
	invokestatic	Method scala/actors/threadpool/LinkedBlockingQueue.access$400:(Lscala/actors/threadpool/LinkedBlockingQueue;)Lscala/actors/threadpool/LinkedBlockingQueue$Node;
	aload	5
	if_acmpne	l5 // aload_0
	aload_0
	getfield	Field this$0:Lscala/actors/threadpool/LinkedBlockingQueue;
	aload	4
	invokestatic	Method scala/actors/threadpool/LinkedBlockingQueue.access$402:(Lscala/actors/threadpool/LinkedBlockingQueue;Lscala/actors/threadpool/LinkedBlockingQueue$Node;)Lscala/actors/threadpool/LinkedBlockingQueue$Node;
	pop
l5	aload_0
	dup
	astore	7
	monitorenter
	aload_0
	getfield	Field this$0:Lscala/actors/threadpool/LinkedBlockingQueue;
	invokestatic	Method scala/actors/threadpool/LinkedBlockingQueue.access$510:(Lscala/actors/threadpool/LinkedBlockingQueue;)I
	istore	6
	aload	7
	monitorexit
	goto	l6 // iload
	astore	8
	aload	7
	monitorexit
	aload	8
	athrow
l6	iload	6
	aload_0
	getfield	Field this$0:Lscala/actors/threadpool/LinkedBlockingQueue;
	invokestatic	Method scala/actors/threadpool/LinkedBlockingQueue.access$600:(Lscala/actors/threadpool/LinkedBlockingQueue;)I
	if_icmpne	l4 // aload_2
	aload_0
	getfield	Field this$0:Lscala/actors/threadpool/LinkedBlockingQueue;
	invokestatic	Method scala/actors/threadpool/LinkedBlockingQueue.access$100:(Lscala/actors/threadpool/LinkedBlockingQueue;)Ljava/lang/Object;
	invokevirtual	Method java/lang/Object.notifyAll:()V
l4	aload_2
	monitorexit
	goto	l7 // aload_1
	astore	9
	aload_2
	monitorexit
	aload	9
	athrow
l7	aload_1
	monitorexit
	goto	l8 // return
	astore	10
	aload_1
	monitorexit
	aload	10
	athrow
l8	return
  Labels:
   	l1 = 15 // aload_0
   	l3 = 66 // aload
   	l2 = 91 // aload
   	l5 = 135 // aload_0
   	l6 = 163 // iload
   	l4 = 185 // aload_2
   	l7 = 197 // aload_1
   	l8 = 209 // return
  Exception table:
   from   to  target type
   140   152   155   any
   155   160   155   any
    35   187   190   any
   190   194   190   any
    25   199   202   any
   202   206   202   any

}

