class scala.actors.threadpool.LinkedBlockingQueue$SerializableLock extends java.lang.Object implements java.io.Serializable
  InnerClass: 
   #14 of #19; //class scala/actors/threadpool/LinkedBlockingQueue$1 of class scala/actors/threadpool/LinkedBlockingQueue
   #21= #3 of #19; //SerializableLock=class scala/actors/threadpool/LinkedBlockingQueue$SerializableLock of class scala/actors/threadpool/LinkedBlockingQueue
  minor version: 0
  major version: 49
  Constant pool:
const #1 = Method	#3.#18;	//  scala/actors/threadpool/LinkedBlockingQueue$SerializableLock."<init>":()V
const #2 = Method	#4.#18;	//  java/lang/Object."<init>":()V
const #3 = class	#20;	//  scala/actors/threadpool/LinkedBlockingQueue$SerializableLock
const #4 = class	#22;	//  java/lang/Object
const #5 = class	#23;	//  java/io/Serializable
const #6 = Asciz	serialVersionUID;
const #7 = Asciz	J;
const #8 = Asciz	ConstantValue;
const #9 = long	-8856990691138858668l;
const #11 = Asciz	<init>;
const #12 = Asciz	()V;
const #13 = Asciz	Code;
const #14 = class	#24;	//  scala/actors/threadpool/LinkedBlockingQueue$1
const #15 = Asciz	;
const #16 = Asciz	InnerClasses;
const #17 = Asciz	(Lscala/actors/threadpool/LinkedBlockingQueue$1;)V;
const #18 = NameAndType	#11:#12;//  "<init>":()V
const #19 = class	#25;	//  scala/actors/threadpool/LinkedBlockingQueue
const #20 = Asciz	scala/actors/threadpool/LinkedBlockingQueue$SerializableLock;
const #21 = Asciz	SerializableLock;
const #22 = Asciz	java/lang/Object;
const #23 = Asciz	java/io/Serializable;
const #24 = Asciz	scala/actors/threadpool/LinkedBlockingQueue$1;
const #25 = Asciz	scala/actors/threadpool/LinkedBlockingQueue;

{
scala.actors.threadpool.LinkedBlockingQueue$SerializableLock(scala.actors.threadpool.LinkedBlockingQueue$1);
  Code:
   Stack=1, Locals=2, Args_size=2
   0:	aload_0
   1:	invokespecial	#1; //Method "<init>":()V
   4:	return

}

