public class scala.actors.threadpool.LinkedBlockingQueue extends scala.actors.threadpool.AbstractQueue implements scala.actors.threadpool.BlockingQueue,java.io.Serializable
  InnerClass: 
   class scala/actors/threadpool/LinkedBlockingQueue$1 of class scala/actors/threadpool/LinkedBlockingQueue
   SerializableLock=class scala/actors/threadpool/LinkedBlockingQueue$SerializableLock of class scala/actors/threadpool/LinkedBlockingQueue
   Itr=class scala/actors/threadpool/LinkedBlockingQueue$Itr of class scala/actors/threadpool/LinkedBlockingQueue
   Node=class scala/actors/threadpool/LinkedBlockingQueue$Node of class scala/actors/threadpool/LinkedBlockingQueue
  minor version: 0
  major version: 49
  Constant pool:
Field	scala/actors/threadpool/LinkedBlockingQueue.capacity:I
Field	scala/actors/threadpool/LinkedBlockingQueue.count:I
Field	scala/actors/threadpool/LinkedBlockingQueue.last:Lscala/actors/threadpool/LinkedBlockingQueue$Node;
Field	scala/actors/threadpool/LinkedBlockingQueue.head:Lscala/actors/threadpool/LinkedBlockingQueue$Node;
Field	scala/actors/threadpool/LinkedBlockingQueue.takeLock:Ljava/lang/Object;
Field	scala/actors/threadpool/LinkedBlockingQueue.putLock:Ljava/lang/Object;
Method	java/lang/Object.notify:()V
class	scala/actors/threadpool/LinkedBlockingQueue$Node
Method	scala/actors/threadpool/LinkedBlockingQueue$Node."<init>":(Ljava/lang/Object;)V
Field	scala/actors/threadpool/LinkedBlockingQueue$Node.next:Lscala/actors/threadpool/LinkedBlockingQueue$Node;
Field	scala/actors/threadpool/LinkedBlockingQueue$Node.item:Ljava/lang/Object;
int	2147483647;
Method	scala/actors/threadpool/LinkedBlockingQueue."<init>":(I)V
Method	scala/actors/threadpool/AbstractQueue."<init>":()V
class	scala/actors/threadpool/LinkedBlockingQueue$SerializableLock
Method	scala/actors/threadpool/LinkedBlockingQueue$SerializableLock."<init>":(Lscala/actors/threadpool/LinkedBlockingQueue$1;)V
class	java/lang/IllegalArgumentException
Method	java/lang/IllegalArgumentException."<init>":()V
InterfaceMethod	java/util/Collection.iterator:()Ljava/util/Iterator;
InterfaceMethod	java/util/Iterator.hasNext:()Z
InterfaceMethod	java/util/Iterator.next:()Ljava/lang/Object;
Method	scala/actors/threadpool/LinkedBlockingQueue.add:(Ljava/lang/Object;)Z
class	java/lang/NullPointerException
Method	java/lang/NullPointerException."<init>":()V
Method	java/lang/Object.wait:()V
class	java/lang/InterruptedException
Method	scala/actors/threadpool/LinkedBlockingQueue.insert:(Ljava/lang/Object;)V
Method	scala/actors/threadpool/LinkedBlockingQueue.signalNotEmpty:()V
Method	scala/actors/threadpool/TimeUnit.toNanos:(J)J
Method	scala/actors/threadpool/helpers/Utils.nanoTime:()J
Field	scala/actors/threadpool/TimeUnit.NANOSECONDS:Lscala/actors/threadpool/TimeUnit;
Method	scala/actors/threadpool/TimeUnit.timedWait:(Ljava/lang/Object;J)V
Method	scala/actors/threadpool/LinkedBlockingQueue.extract:()Ljava/lang/Object;
Method	scala/actors/threadpool/LinkedBlockingQueue.signalNotFull:()V
Method	java/lang/Object.equals:(Ljava/lang/Object;)Z
Method	java/lang/Object.notifyAll:()V
class	java/lang/Object
Method	java/lang/Object.getClass:()Ljava/lang/Class;
Method	java/lang/Class.getComponentType:()Ljava/lang/Class;
Method	java/lang/reflect/Array.newInstance:(Ljava/lang/Class;I)Ljava/lang/Object;
class	"[Ljava/lang/Object;"
Method	scala/actors/threadpool/AbstractQueue.toString:()Ljava/lang/String;
Field	scala/actors/threadpool/LinkedBlockingQueue.$assertionsDisabled:Z
class	java/lang/AssertionError
Method	java/lang/AssertionError."<init>":()V
InterfaceMethod	java/util/Collection.add:(Ljava/lang/Object;)Z
class	scala/actors/threadpool/LinkedBlockingQueue$Itr
Method	scala/actors/threadpool/LinkedBlockingQueue$Itr."<init>":(Lscala/actors/threadpool/LinkedBlockingQueue;)V
Method	java/io/ObjectOutputStream.defaultWriteObject:()V
Method	java/io/ObjectOutputStream.writeObject:(Ljava/lang/Object;)V
Method	java/io/ObjectInputStream.defaultReadObject:()V
Method	java/io/ObjectInputStream.readObject:()Ljava/lang/Object;
class	scala/actors/threadpool/LinkedBlockingQueue
Method	java/lang/Class.desiredAssertionStatus:()Z
class	scala/actors/threadpool/AbstractQueue
class	scala/actors/threadpool/BlockingQueue
class	java/io/Serializable
class	scala/actors/threadpool/LinkedBlockingQueue$1
Asciz	;
Asciz	InnerClasses;
Asciz	SerializableLock;
Asciz	Itr;
Asciz	Node;
Asciz	serialVersionUID;
Asciz	J;
Asciz	ConstantValue;
long	-6903933977591709194l;
Asciz	capacity;
Asciz	I;
Asciz	count;
Asciz	head;
Asciz	Lscala/actors/threadpool/LinkedBlockingQueue$Node;;
Asciz	last;
Asciz	takeLock;
Asciz	Ljava/lang/Object;;
Asciz	putLock;
Asciz	$assertionsDisabled;
Asciz	Z;
Asciz	signalNotEmpty;
Asciz	()V;
Asciz	Code;
Asciz	signalNotFull;
Asciz	insert;
Asciz	(Ljava/lang/Object;)V;
Asciz	extract;
Asciz	()Ljava/lang/Object;;
Asciz	<init>;
Asciz	(I)V;
Asciz	(Ljava/util/Collection;)V;
Asciz	size;
Asciz	()I;
Asciz	remainingCapacity;
Asciz	put;
Asciz	Exceptions;
Asciz	offer;
Asciz	(Ljava/lang/Object;JLscala/actors/threadpool/TimeUnit;)Z;
Asciz	(Ljava/lang/Object;)Z;
Asciz	take;
Asciz	poll;
Asciz	(JLscala/actors/threadpool/TimeUnit;)Ljava/lang/Object;;
Asciz	peek;
Asciz	remove;
Asciz	toArray;
Asciz	()[Ljava/lang/Object;;
Asciz	([Ljava/lang/Object;)[Ljava/lang/Object;;
Asciz	toString;
Asciz	()Ljava/lang/String;;
Asciz	clear;
Asciz	drainTo;
Asciz	(Ljava/util/Collection;)I;
Asciz	(Ljava/util/Collection;I)I;
Asciz	iterator;
Asciz	()Ljava/util/Iterator;;
Asciz	writeObject;
Asciz	(Ljava/io/ObjectOutputStream;)V;
class	java/io/IOException
Asciz	readObject;
Asciz	(Ljava/io/ObjectInputStream;)V;
class	java/lang/ClassNotFoundException
Asciz	access$100;
Asciz	(Lscala/actors/threadpool/LinkedBlockingQueue;)Ljava/lang/Object;;
Asciz	access$200;
Asciz	access$300;
Asciz	(Lscala/actors/threadpool/LinkedBlockingQueue;)Lscala/actors/threadpool/LinkedBlockingQueue$Node;;
Asciz	access$400;
Asciz	access$402;
Asciz	(Lscala/actors/threadpool/LinkedBlockingQueue;Lscala/actors/threadpool/LinkedBlockingQueue$Node;)Lscala/actors/threadpool/LinkedBlockingQueue$Node;;
Asciz	access$510;
Asciz	(Lscala/actors/threadpool/LinkedBlockingQueue;)I;
Asciz	access$600;
Asciz	<clinit>;
NameAndType	capacity:I
NameAndType	count:I
NameAndType	last:Lscala/actors/threadpool/LinkedBlockingQueue$Node;
NameAndType	head:Lscala/actors/threadpool/LinkedBlockingQueue$Node;
NameAndType	takeLock:Ljava/lang/Object;
NameAndType	putLock:Ljava/lang/Object;
NameAndType	notify:()V
Asciz	scala/actors/threadpool/LinkedBlockingQueue$Node;
NameAndType	"<init>":(Ljava/lang/Object;)V
NameAndType	next:Lscala/actors/threadpool/LinkedBlockingQueue$Node;
NameAndType	item:Ljava/lang/Object;
NameAndType	"<init>":(I)V
NameAndType	"<init>":()V
Asciz	scala/actors/threadpool/LinkedBlockingQueue$SerializableLock;
NameAndType	"<init>":(Lscala/actors/threadpool/LinkedBlockingQueue$1;)V
Asciz	java/lang/IllegalArgumentException;
class	java/util/Collection
NameAndType	iterator:()Ljava/util/Iterator;
class	java/util/Iterator
NameAndType	hasNext:()Z
NameAndType	next:()Ljava/lang/Object;
NameAndType	add:(Ljava/lang/Object;)Z
Asciz	java/lang/NullPointerException;
NameAndType	wait:()V
Asciz	java/lang/InterruptedException;
NameAndType	insert:(Ljava/lang/Object;)V
NameAndType	signalNotEmpty:()V
class	scala/actors/threadpool/TimeUnit
NameAndType	toNanos:(J)J
class	scala/actors/threadpool/helpers/Utils
NameAndType	nanoTime:()J
NameAndType	NANOSECONDS:Lscala/actors/threadpool/TimeUnit;
NameAndType	timedWait:(Ljava/lang/Object;J)V
NameAndType	extract:()Ljava/lang/Object;
NameAndType	signalNotFull:()V
NameAndType	equals:(Ljava/lang/Object;)Z
NameAndType	notifyAll:()V
Asciz	java/lang/Object;
NameAndType	getClass:()Ljava/lang/Class;
class	java/lang/Class
NameAndType	getComponentType:()Ljava/lang/Class;
class	java/lang/reflect/Array
NameAndType	newInstance:(Ljava/lang/Class;I)Ljava/lang/Object;
Asciz	[Ljava/lang/Object;;
NameAndType	toString:()Ljava/lang/String;
NameAndType	$assertionsDisabled:Z
Asciz	java/lang/AssertionError;
Asciz	scala/actors/threadpool/LinkedBlockingQueue$Itr;
NameAndType	"<init>":(Lscala/actors/threadpool/LinkedBlockingQueue;)V
class	java/io/ObjectOutputStream
NameAndType	defaultWriteObject:()V
NameAndType	writeObject:(Ljava/lang/Object;)V
class	java/io/ObjectInputStream
NameAndType	defaultReadObject:()V
NameAndType	readObject:()Ljava/lang/Object;
Asciz	scala/actors/threadpool/LinkedBlockingQueue;
NameAndType	desiredAssertionStatus:()Z
Asciz	scala/actors/threadpool/AbstractQueue;
Asciz	scala/actors/threadpool/BlockingQueue;
Asciz	java/io/Serializable;
Asciz	scala/actors/threadpool/LinkedBlockingQueue$1;
Asciz	java/io/IOException;
Asciz	java/lang/ClassNotFoundException;
Asciz	notify;
Asciz	next;
Asciz	item;
Asciz	(Lscala/actors/threadpool/LinkedBlockingQueue$1;)V;
Asciz	java/util/Collection;
Asciz	java/util/Iterator;
Asciz	hasNext;
Asciz	()Z;
Asciz	add;
Asciz	wait;
Asciz	scala/actors/threadpool/TimeUnit;
Asciz	toNanos;
Asciz	(J)J;
Asciz	scala/actors/threadpool/helpers/Utils;
Asciz	nanoTime;
Asciz	()J;
Asciz	NANOSECONDS;
Asciz	Lscala/actors/threadpool/TimeUnit;;
Asciz	timedWait;
Asciz	(Ljava/lang/Object;J)V;
Asciz	equals;
Asciz	notifyAll;
Asciz	getClass;
Asciz	()Ljava/lang/Class;;
Asciz	java/lang/Class;
Asciz	getComponentType;
Asciz	java/lang/reflect/Array;
Asciz	newInstance;
Asciz	(Ljava/lang/Class;I)Ljava/lang/Object;;
Asciz	(Lscala/actors/threadpool/LinkedBlockingQueue;)V;
Asciz	java/io/ObjectOutputStream;
Asciz	defaultWriteObject;
Asciz	java/io/ObjectInputStream;
Asciz	defaultReadObject;
Asciz	desiredAssertionStatus;

{
private static final long serialVersionUID;
  Signature: J
  Constant value: long -6903933977591709194l
private final int capacity;
  Signature: I

private volatile int count;
  Signature: I

private transient scala.actors.threadpool.LinkedBlockingQueue$Node head;
  Signature: Lscala/actors/threadpool/LinkedBlockingQueue$Node;

private transient scala.actors.threadpool.LinkedBlockingQueue$Node last;
  Signature: Lscala/actors/threadpool/LinkedBlockingQueue$Node;

private final java.lang.Object takeLock;
  Signature: Ljava/lang/Object;

private final java.lang.Object putLock;
  Signature: Ljava/lang/Object;

static final boolean $assertionsDisabled;
  Signature: Z

private void signalNotEmpty();
  Signature: ()V
  Code:
   Stack=2, Locals=3, Args_size=1
	aload_0
	getfield	Field takeLock:Ljava/lang/Object;
	dup
	astore_1
	monitorenter
	aload_0
	getfield	Field takeLock:Ljava/lang/Object;
	invokevirtual	Method java/lang/Object.notify:()V
	aload_1
	monitorexit
	goto	l1 // return
	astore_2
	aload_1
	monitorexit
	aload_2
	athrow
l1	return
  Labels:
   	l1 = 24 // return
  Exception table:
   from   to  target type
     7    16    19   any
    19    22    19   any

private void signalNotFull();
  Signature: ()V
  Code:
   Stack=2, Locals=3, Args_size=1
	aload_0
	getfield	Field putLock:Ljava/lang/Object;
	dup
	astore_1
	monitorenter
	aload_0
	getfield	Field putLock:Ljava/lang/Object;
	invokevirtual	Method java/lang/Object.notify:()V
	aload_1
	monitorexit
	goto	l1 // return
	astore_2
	aload_1
	monitorexit
	aload_2
	athrow
l1	return
  Labels:
   	l1 = 24 // return
  Exception table:
   from   to  target type
     7    16    19   any
    19    22    19   any

private void insert(java.lang.Object);
  Signature: (Ljava/lang/Object;)V
  Code:
   Stack=5, Locals=2, Args_size=2
	aload_0
	aload_0
	getfield	Field last:Lscala/actors/threadpool/LinkedBlockingQueue$Node;
	new	class scala/actors/threadpool/LinkedBlockingQueue$Node
	dup
	aload_1
	invokespecial	Method scala/actors/threadpool/LinkedBlockingQueue$Node."<init>":(Ljava/lang/Object;)V
	dup_x1
	putfield	Field scala/actors/threadpool/LinkedBlockingQueue$Node.next:Lscala/actors/threadpool/LinkedBlockingQueue$Node;
	putfield	Field last:Lscala/actors/threadpool/LinkedBlockingQueue$Node;
	return
  Labels:

private java.lang.Object extract();
  Signature: ()Ljava/lang/Object;
  Code:
   Stack=2, Locals=3, Args_size=1
	aload_0
	getfield	Field head:Lscala/actors/threadpool/LinkedBlockingQueue$Node;
	getfield	Field scala/actors/threadpool/LinkedBlockingQueue$Node.next:Lscala/actors/threadpool/LinkedBlockingQueue$Node;
	astore_1
	aload_0
	aload_1
	putfield	Field head:Lscala/actors/threadpool/LinkedBlockingQueue$Node;
	aload_1
	getfield	Field scala/actors/threadpool/LinkedBlockingQueue$Node.item:Ljava/lang/Object;
	astore_2
	aload_1
	aconst_null
	putfield	Field scala/actors/threadpool/LinkedBlockingQueue$Node.item:Ljava/lang/Object;
	aload_2
	areturn
  Labels:

public scala.actors.threadpool.LinkedBlockingQueue();
  Signature: ()V
  Code:
   Stack=2, Locals=1, Args_size=1
	aload_0
	ldc	int 2147483647
	invokespecial	Method "<init>":(I)V
	return
  Labels:

public scala.actors.threadpool.LinkedBlockingQueue(int);
  Signature: (I)V
  Code:
   Stack=5, Locals=2, Args_size=2
	aload_0
	invokespecial	Method scala/actors/threadpool/AbstractQueue."<init>":()V
	aload_0
	iconst_0
	putfield	Field count:I
	aload_0
	new	class scala/actors/threadpool/LinkedBlockingQueue$SerializableLock
	dup
	aconst_null
	invokespecial	Method scala/actors/threadpool/LinkedBlockingQueue$SerializableLock."<init>":(Lscala/actors/threadpool/LinkedBlockingQueue$1;)V
	putfield	Field takeLock:Ljava/lang/Object;
	aload_0
	new	class scala/actors/threadpool/LinkedBlockingQueue$SerializableLock
	dup
	aconst_null
	invokespecial	Method scala/actors/threadpool/LinkedBlockingQueue$SerializableLock."<init>":(Lscala/actors/threadpool/LinkedBlockingQueue$1;)V
	putfield	Field putLock:Ljava/lang/Object;
	iload_1
	ifgt	l1 // aload_0
	new	class java/lang/IllegalArgumentException
	dup
	invokespecial	Method java/lang/IllegalArgumentException."<init>":()V
	athrow
l1	aload_0
	iload_1
	putfield	Field capacity:I
	aload_0
	aload_0
	new	class scala/actors/threadpool/LinkedBlockingQueue$Node
	dup
	aconst_null
	invokespecial	Method scala/actors/threadpool/LinkedBlockingQueue$Node."<init>":(Ljava/lang/Object;)V
	dup_x1
	putfield	Field head:Lscala/actors/threadpool/LinkedBlockingQueue$Node;
	putfield	Field last:Lscala/actors/threadpool/LinkedBlockingQueue$Node;
	return
  Labels:
   	l1 = 45 // aload_0

public scala.actors.threadpool.LinkedBlockingQueue(java.util.Collection);
  Signature: (Ljava/util/Collection;)V
  Code:
   Stack=2, Locals=4, Args_size=2
	aload_0
	ldc	int 2147483647
	invokespecial	Method "<init>":(I)V
	aload_1
	invokeinterface	InterfaceMethod java/util/Collection.iterator:()Ljava/util/Iterator;
	astore_2
l2	aload_2
	invokeinterface	InterfaceMethod java/util/Iterator.hasNext:()Z
	ifeq	l1 // return
	aload_2
	invokeinterface	InterfaceMethod java/util/Iterator.next:()Ljava/lang/Object;
	astore_3
	aload_0
	aload_3
	invokevirtual	Method add:(Ljava/lang/Object;)Z
	pop
	goto	l2 // aload_2
l1	return
  Labels:
   	l2 = 13 // aload_2
   	l1 = 38 // return

public int size();
  Signature: ()I
  Code:
   Stack=1, Locals=1, Args_size=1
	aload_0
	getfield	Field count:I
	ireturn
  Labels:

public int remainingCapacity();
  Signature: ()I
  Code:
   Stack=2, Locals=1, Args_size=1
	aload_0
	getfield	Field capacity:I
	aload_0
	getfield	Field count:I
	isub
	ireturn
  Labels:

public void put(java.lang.Object)   throws java.lang.InterruptedException;
  Signature: (Ljava/lang/Object;)V
  Code:
   Stack=4, Locals=7, Args_size=2
	aload_1
	ifnonnull	l1 // iconst_m1
	new	class java/lang/NullPointerException
	dup
	invokespecial	Method java/lang/NullPointerException."<init>":()V
	athrow
l1	iconst_m1
	istore_2
	aload_0
	getfield	Field putLock:Ljava/lang/Object;
	dup
	astore_3
	monitorenter
l3	aload_0
	getfield	Field count:I
	aload_0
	getfield	Field capacity:I
	if_icmpne	l2 // goto
	aload_0
	getfield	Field putLock:Ljava/lang/Object;
	invokevirtual	Method java/lang/Object.wait:()V
	goto	l3 // aload_0
l2	goto	l4 // aload_0
	astore	4
	aload_0
	getfield	Field putLock:Ljava/lang/Object;
	invokevirtual	Method java/lang/Object.notify:()V
	aload	4
	athrow
l4	aload_0
	aload_1
	invokespecial	Method insert:(Ljava/lang/Object;)V
	aload_0
	dup
	astore	4
	monitorenter
	aload_0
	dup
	getfield	Field count:I
	dup_x1
	iconst_1
	iadd
	putfield	Field count:I
	istore_2
	aload	4
	monitorexit
	goto	l5 // iload_2
	astore	5
	aload	4
	monitorexit
	aload	5
	athrow
l5	iload_2
	iconst_1
	iadd
	aload_0
	getfield	Field capacity:I
	if_icmpge	l6 // aload_3
	aload_0
	getfield	Field putLock:Ljava/lang/Object;
	invokevirtual	Method java/lang/Object.notify:()V
l6	aload_3
	monitorexit
	goto	l7 // iload_2
	astore	6
	aload_3
	monitorexit
	aload	6
	athrow
l7	iload_2
	ifne	l8 // return
	aload_0
	invokespecial	Method signalNotEmpty:()V
l8	return
  Labels:
   	l1 = 12 // iconst_m1
   	l3 = 21 // aload_0
   	l2 = 42 // goto
   	l4 = 57 // aload_0
   	l5 = 93 // iload_2
   	l6 = 110 // aload_3
   	l7 = 122 // iload_2
   	l8 = 130 // return
  Exception table:
   from   to  target type
    21    42    45   Class java/lang/InterruptedException

    67    82    85   any
    85    90    85   any
    21   112   115   any
   115   119   115   any
  Exceptions: 
   throws java.lang.InterruptedException
public boolean offer(java.lang.Object, long, scala.actors.threadpool.TimeUnit)   throws java.lang.InterruptedException;
  Signature: (Ljava/lang/Object;JLscala/actors/threadpool/TimeUnit;)Z
  Code:
   Stack=4, Locals=14, Args_size=4
	aload_1
	ifnonnull	l1 // aload
	new	class java/lang/NullPointerException
	dup
	invokespecial	Method java/lang/NullPointerException."<init>":()V
	athrow
l1	aload	4
	lload_2
	invokevirtual	Method scala/actors/threadpool/TimeUnit.toNanos:(J)J
	lstore	5
	iconst_m1
	istore	7
	aload_0
	getfield	Field putLock:Ljava/lang/Object;
	dup
	astore	8
	monitorenter
	invokestatic	Method scala/actors/threadpool/helpers/Utils.nanoTime:()J
	lload	5
	ladd
	lstore	9
l6	aload_0
	getfield	Field count:I
	aload_0
	getfield	Field capacity:I
	if_icmpge	l2 // lload
	aload_0
	aload_1
	invokespecial	Method insert:(Ljava/lang/Object;)V
	aload_0
	dup
	astore	11
	monitorenter
	aload_0
	dup
	getfield	Field count:I
	dup_x1
	iconst_1
	iadd
	putfield	Field count:I
	istore	7
	aload	11
	monitorexit
	goto	l3 // iload
	astore	12
	aload	11
	monitorexit
	aload	12
	athrow
l3	iload	7
	iconst_1
	iadd
	aload_0
	getfield	Field capacity:I
	if_icmpge	l4 // aload
	aload_0
	getfield	Field putLock:Ljava/lang/Object;
	invokevirtual	Method java/lang/Object.notify:()V
	goto	l4 // aload
l2	lload	5
	lconst_0
	lcmp
	ifgt	l5 // getstatic
	iconst_0
	aload	8
	monitorexit
	ireturn
l5	getstatic	Field scala/actors/threadpool/TimeUnit.NANOSECONDS:Lscala/actors/threadpool/TimeUnit;
	aload_0
	getfield	Field putLock:Ljava/lang/Object;
	lload	5
	invokevirtual	Method scala/actors/threadpool/TimeUnit.timedWait:(Ljava/lang/Object;J)V
	lload	9
	invokestatic	Method scala/actors/threadpool/helpers/Utils.nanoTime:()J
	lsub
	lstore	5
	goto	l6 // aload_0
	astore	11
	aload_0
	getfield	Field putLock:Ljava/lang/Object;
	invokevirtual	Method java/lang/Object.notify:()V
	aload	11
	athrow
l4	aload	8
	monitorexit
	goto	l7 // iload
	astore	13
	aload	8
	monitorexit
	aload	13
	athrow
l7	iload	7
	ifne	l8 // iconst_1
	aload_0
	invokespecial	Method signalNotEmpty:()V
l8	iconst_1
	ireturn
  Labels:
   	l1 = 12 // aload
   	l6 = 39 // aload_0
   	l3 = 87 // iload
   	l2 = 108 // lload
   	l5 = 120 // getstatic
   	l4 = 155 // aload
   	l7 = 169 // iload
   	l8 = 178 // iconst_1
  Exception table:
   from   to  target type
    60    76    79   any
    79    84    79   any
   120   140   143   Class java/lang/InterruptedException

    31   119   161   any
   120   158   161   any
   161   166   161   any
  Exceptions: 
   throws java.lang.InterruptedException
public boolean offer(java.lang.Object);
  Signature: (Ljava/lang/Object;)Z
  Code:
   Stack=4, Locals=7, Args_size=2
	aload_1
	ifnonnull	l1 // aload_0
	new	class java/lang/NullPointerException
	dup
	invokespecial	Method java/lang/NullPointerException."<init>":()V
	athrow
l1	aload_0
	getfield	Field count:I
	aload_0
	getfield	Field capacity:I
	if_icmpne	l2 // iconst_m1
	iconst_0
	ireturn
l2	iconst_m1
	istore_2
	aload_0
	getfield	Field putLock:Ljava/lang/Object;
	dup
	astore_3
	monitorenter
	aload_0
	getfield	Field count:I
	aload_0
	getfield	Field capacity:I
	if_icmpge	l3 // aload_3
	aload_0
	aload_1
	invokespecial	Method insert:(Ljava/lang/Object;)V
	aload_0
	dup
	astore	4
	monitorenter
	aload_0
	dup
	getfield	Field count:I
	dup_x1
	iconst_1
	iadd
	putfield	Field count:I
	istore_2
	aload	4
	monitorexit
	goto	l4 // iload_2
	astore	5
	aload	4
	monitorexit
	aload	5
	athrow
l4	iload_2
	iconst_1
	iadd
	aload_0
	getfield	Field capacity:I
	if_icmpge	l3 // aload_3
	aload_0
	getfield	Field putLock:Ljava/lang/Object;
	invokevirtual	Method java/lang/Object.notify:()V
l3	aload_3
	monitorexit
	goto	l5 // iload_2
	astore	6
	aload_3
	monitorexit
	aload	6
	athrow
l5	iload_2
	ifne	l6 // iload_2
	aload_0
	invokespecial	Method signalNotEmpty:()V
l6	iload_2
	iflt	l7 // iconst_0
	iconst_1
	goto	l8 // ireturn
l7	iconst_0
l8	ireturn
  Labels:
   	l1 = 12 // aload_0
   	l2 = 25 // iconst_m1
   	l4 = 81 // iload_2
   	l3 = 98 // aload_3
   	l5 = 110 // iload_2
   	l6 = 118 // iload_2
   	l7 = 126 // iconst_0
   	l8 = 127 // ireturn
  Exception table:
   from   to  target type
    55    70    73   any
    73    78    73   any
    34   100   103   any
   103   107   103   any

public java.lang.Object take()   throws java.lang.InterruptedException;
  Signature: ()Ljava/lang/Object;
  Code:
   Stack=4, Locals=7, Args_size=1
	iconst_m1
	istore_2
	aload_0
	getfield	Field takeLock:Ljava/lang/Object;
	dup
	astore_3
	monitorenter
l2	aload_0
	getfield	Field count:I
	ifne	l1 // goto
	aload_0
	getfield	Field takeLock:Ljava/lang/Object;
	invokevirtual	Method java/lang/Object.wait:()V
	goto	l2 // aload_0
l1	goto	l3 // aload_0
	astore	4
	aload_0
	getfield	Field takeLock:Ljava/lang/Object;
	invokevirtual	Method java/lang/Object.notify:()V
	aload	4
	athrow
l3	aload_0
	invokespecial	Method extract:()Ljava/lang/Object;
	astore_1
	aload_0
	dup
	astore	4
	monitorenter
	aload_0
	dup
	getfield	Field count:I
	dup_x1
	iconst_1
	isub
	putfield	Field count:I
	istore_2
	aload	4
	monitorexit
	goto	l4 // iload_2
	astore	5
	aload	4
	monitorexit
	aload	5
	athrow
l4	iload_2
	iconst_1
	if_icmple	l5 // aload_3
	aload_0
	getfield	Field takeLock:Ljava/lang/Object;
	invokevirtual	Method java/lang/Object.notify:()V
l5	aload_3
	monitorexit
	goto	l6 // iload_2
	astore	6
	aload_3
	monitorexit
	aload	6
	athrow
l6	iload_2
	aload_0
	getfield	Field capacity:I
	if_icmpne	l7 // aload_1
	aload_0
	invokespecial	Method signalNotFull:()V
l7	aload_1
	areturn
  Labels:
   	l2 = 9 // aload_0
   	l1 = 26 // goto
   	l3 = 41 // aload_0
   	l4 = 77 // iload_2
   	l5 = 89 // aload_3
   	l6 = 101 // iload_2
   	l7 = 113 // aload_1
  Exception table:
   from   to  target type
     9    26    29   Class java/lang/InterruptedException

    51    66    69   any
    69    74    69   any
     9    91    94   any
    94    98    94   any
  Exceptions: 
   throws java.lang.InterruptedException
public java.lang.Object poll(long, scala.actors.threadpool.TimeUnit)   throws java.lang.InterruptedException;
  Signature: (JLscala/actors/threadpool/TimeUnit;)Ljava/lang/Object;
  Code:
   Stack=4, Locals=14, Args_size=3
	aconst_null
	astore	4
	iconst_m1
	istore	5
	aload_3
	lload_1
	invokevirtual	Method scala/actors/threadpool/TimeUnit.toNanos:(J)J
	lstore	6
	aload_0
	getfield	Field takeLock:Ljava/lang/Object;
	dup
	astore	8
	monitorenter
	invokestatic	Method scala/actors/threadpool/helpers/Utils.nanoTime:()J
	lload	6
	ladd
	lstore	9
l5	aload_0
	getfield	Field count:I
	ifle	l1 // lload
	aload_0
	invokespecial	Method extract:()Ljava/lang/Object;
	astore	4
	aload_0
	dup
	astore	11
	monitorenter
	aload_0
	dup
	getfield	Field count:I
	dup_x1
	iconst_1
	isub
	putfield	Field count:I
	istore	5
	aload	11
	monitorexit
	goto	l2 // iload
	astore	12
	aload	11
	monitorexit
	aload	12
	athrow
l2	iload	5
	iconst_1
	if_icmple	l3 // aload
	aload_0
	getfield	Field takeLock:Ljava/lang/Object;
	invokevirtual	Method java/lang/Object.notify:()V
	goto	l3 // aload
l1	lload	6
	lconst_0
	lcmp
	ifgt	l4 // getstatic
	aconst_null
	aload	8
	monitorexit
	areturn
l4	getstatic	Field scala/actors/threadpool/TimeUnit.NANOSECONDS:Lscala/actors/threadpool/TimeUnit;
	aload_0
	getfield	Field takeLock:Ljava/lang/Object;
	lload	6
	invokevirtual	Method scala/actors/threadpool/TimeUnit.timedWait:(Ljava/lang/Object;J)V
	lload	9
	invokestatic	Method scala/actors/threadpool/helpers/Utils.nanoTime:()J
	lsub
	lstore	6
	goto	l5 // aload_0
	astore	11
	aload_0
	getfield	Field takeLock:Ljava/lang/Object;
	invokevirtual	Method java/lang/Object.notify:()V
	aload	11
	athrow
l3	aload	8
	monitorexit
	goto	l6 // iload
	astore	13
	aload	8
	monitorexit
	aload	13
	athrow
l6	iload	5
	aload_0
	getfield	Field capacity:I
	if_icmpne	l7 // aload
	aload_0
	invokespecial	Method signalNotFull:()V
l7	aload	4
	areturn
  Labels:
   	l5 = 29 // aload_0
   	l2 = 74 // iload
   	l1 = 90 // lload
   	l4 = 102 // getstatic
   	l3 = 137 // aload
   	l6 = 151 // iload
   	l7 = 164 // aload
  Exception table:
   from   to  target type
    47    63    66   any
    66    71    66   any
   102   122   125   Class java/lang/InterruptedException

    21   101   143   any
   102   140   143   any
   143   148   143   any
  Exceptions: 
   throws java.lang.InterruptedException
public java.lang.Object poll();
  Signature: ()Ljava/lang/Object;
  Code:
   Stack=4, Locals=7, Args_size=1
	aload_0
	getfield	Field count:I
	ifne	l1 // aconst_null
	aconst_null
	areturn
l1	aconst_null
	astore_1
	iconst_m1
	istore_2
	aload_0
	getfield	Field takeLock:Ljava/lang/Object;
	dup
	astore_3
	monitorenter
	aload_0
	getfield	Field count:I
	ifle	l2 // aload_3
	aload_0
	invokespecial	Method extract:()Ljava/lang/Object;
	astore_1
	aload_0
	dup
	astore	4
	monitorenter
	aload_0
	dup
	getfield	Field count:I
	dup_x1
	iconst_1
	isub
	putfield	Field count:I
	istore_2
	aload	4
	monitorexit
	goto	l3 // iload_2
	astore	5
	aload	4
	monitorexit
	aload	5
	athrow
l3	iload_2
	iconst_1
	if_icmple	l2 // aload_3
	aload_0
	getfield	Field takeLock:Ljava/lang/Object;
	invokevirtual	Method java/lang/Object.notify:()V
l2	aload_3
	monitorexit
	goto	l4 // iload_2
	astore	6
	aload_3
	monitorexit
	aload	6
	athrow
l4	iload_2
	aload_0
	getfield	Field capacity:I
	if_icmpne	l5 // aload_1
	aload_0
	invokespecial	Method signalNotFull:()V
l5	aload_1
	areturn
  Labels:
   	l1 = 9 // aconst_null
   	l3 = 63 // iload_2
   	l2 = 75 // aload_3
   	l4 = 87 // iload_2
   	l5 = 99 // aload_1
  Exception table:
   from   to  target type
    37    52    55   any
    55    60    55   any
    20    77    80   any
    80    84    80   any

public java.lang.Object peek();
  Signature: ()Ljava/lang/Object;
  Code:
   Stack=2, Locals=4, Args_size=1
	aload_0
	getfield	Field count:I
	ifne	l1 // aload_0
	aconst_null
	areturn
l1	aload_0
	getfield	Field takeLock:Ljava/lang/Object;
	dup
	astore_1
	monitorenter
	aload_0
	getfield	Field head:Lscala/actors/threadpool/LinkedBlockingQueue$Node;
	getfield	Field scala/actors/threadpool/LinkedBlockingQueue$Node.next:Lscala/actors/threadpool/LinkedBlockingQueue$Node;
	astore_2
	aload_2
	ifnonnull	l2 // aload_2
	aconst_null
	aload_1
	monitorexit
	areturn
l2	aload_2
	getfield	Field scala/actors/threadpool/LinkedBlockingQueue$Node.item:Ljava/lang/Object;
	aload_1
	monitorexit
	areturn
	astore_3
	aload_1
	monitorexit
	aload_3
	athrow
  Labels:
   	l1 = 9 // aload_0
   	l2 = 32 // aload_2
  Exception table:
   from   to  target type
    16    31    39   any
    32    38    39   any
    39    42    39   any

public boolean remove(java.lang.Object);
  Signature: (Ljava/lang/Object;)Z
  Code:
   Stack=4, Locals=11, Args_size=2
	aload_1
	ifnonnull	l1 // iconst_0
	iconst_0
	ireturn
l1	iconst_0
	istore_2
	aload_0
	getfield	Field putLock:Ljava/lang/Object;
	dup
	astore_3
	monitorenter
	aload_0
	getfield	Field takeLock:Ljava/lang/Object;
	dup
	astore	4
	monitorenter
	aload_0
	getfield	Field head:Lscala/actors/threadpool/LinkedBlockingQueue$Node;
	astore	5
	aload_0
	getfield	Field head:Lscala/actors/threadpool/LinkedBlockingQueue$Node;
	getfield	Field scala/actors/threadpool/LinkedBlockingQueue$Node.next:Lscala/actors/threadpool/LinkedBlockingQueue$Node;
	astore	6
l4	aload	6
	ifnull	l2 // iload_2
	aload_1
	aload	6
	getfield	Field scala/actors/threadpool/LinkedBlockingQueue$Node.item:Ljava/lang/Object;
	invokevirtual	Method java/lang/Object.equals:(Ljava/lang/Object;)Z
	ifeq	l3 // aload
	iconst_1
	istore_2
	goto	l2 // iload_2
l3	aload	6
	astore	5
	aload	6
	getfield	Field scala/actors/threadpool/LinkedBlockingQueue$Node.next:Lscala/actors/threadpool/LinkedBlockingQueue$Node;
	astore	6
	goto	l4 // aload
l2	iload_2
	ifeq	l5 // aload
	aload	6
	aconst_null
	putfield	Field scala/actors/threadpool/LinkedBlockingQueue$Node.item:Ljava/lang/Object;
	aload	5
	aload	6
	getfield	Field scala/actors/threadpool/LinkedBlockingQueue$Node.next:Lscala/actors/threadpool/LinkedBlockingQueue$Node;
	putfield	Field scala/actors/threadpool/LinkedBlockingQueue$Node.next:Lscala/actors/threadpool/LinkedBlockingQueue$Node;
	aload_0
	getfield	Field last:Lscala/actors/threadpool/LinkedBlockingQueue$Node;
	aload	6
	if_acmpne	l6 // aload_0
	aload_0
	aload	5
	putfield	Field last:Lscala/actors/threadpool/LinkedBlockingQueue$Node;
l6	aload_0
	dup
	astore	7
	monitorenter
	aload_0
	dup
	getfield	Field count:I
	dup_x1
	iconst_1
	isub
	putfield	Field count:I
	aload_0
	getfield	Field capacity:I
	if_icmpne	l7 // aload
	aload_0
	getfield	Field putLock:Ljava/lang/Object;
	invokevirtual	Method java/lang/Object.notifyAll:()V
l7	aload	7
	monitorexit
	goto	l5 // aload
	astore	8
	aload	7
	monitorexit
	aload	8
	athrow
l5	aload	4
	monitorexit
	goto	l8 // aload_3
	astore	9
	aload	4
	monitorexit
	aload	9
	athrow
l8	aload_3
	monitorexit
	goto	l9 // iload_2
	astore	10
	aload_3
	monitorexit
	aload	10
	athrow
l9	iload_2
	ireturn
  Labels:
   	l1 = 6 // iconst_0
   	l4 = 38 // aload
   	l3 = 60 // aload
   	l2 = 74 // iload_2
   	l6 = 109 // aload_0
   	l7 = 139 // aload
   	l5 = 153 // aload
   	l8 = 167 // aload_3
   	l9 = 179 // iload_2
  Exception table:
   from   to  target type
   114   142   145   any
   145   150   145   any
    23   156   159   any
   159   164   159   any
    15   169   172   any
   172   176   172   any

public java.lang.Object[] toArray();
  Signature: ()[Ljava/lang/Object;
  Code:
   Stack=3, Locals=9, Args_size=1
	aload_0
	getfield	Field putLock:Ljava/lang/Object;
	dup
	astore_1
	monitorenter
	aload_0
	getfield	Field takeLock:Ljava/lang/Object;
	dup
	astore_2
	monitorenter
	aload_0
	getfield	Field count:I
	istore_3
	iload_3
	anewarray	class java/lang/Object
	astore	4
	iconst_0
	istore	5
	aload_0
	getfield	Field head:Lscala/actors/threadpool/LinkedBlockingQueue$Node;
	getfield	Field scala/actors/threadpool/LinkedBlockingQueue$Node.next:Lscala/actors/threadpool/LinkedBlockingQueue$Node;
	astore	6
l2	aload	6
	ifnull	l1 // aload
	aload	4
	iload	5
	iinc	5, 1
	aload	6
	getfield	Field scala/actors/threadpool/LinkedBlockingQueue$Node.item:Ljava/lang/Object;
	aastore
	aload	6
	getfield	Field scala/actors/threadpool/LinkedBlockingQueue$Node.next:Lscala/actors/threadpool/LinkedBlockingQueue$Node;
	astore	6
	goto	l2 // aload
l1	aload	4
	aload_2
	monitorexit
	aload_1
	monitorexit
	areturn
	astore	7
	aload_2
	monitorexit
	aload	7
	athrow
	astore	8
	aload_1
	monitorexit
	aload	8
	athrow
  Labels:
   	l2 = 37 // aload
   	l1 = 65 // aload
  Exception table:
   from   to  target type
    14    69    72   any
    72    76    72   any
     7    71    79   any
    72    83    79   any

public java.lang.Object[] toArray(java.lang.Object[]);
  Signature: ([Ljava/lang/Object;)[Ljava/lang/Object;
  Code:
   Stack=3, Locals=9, Args_size=2
	aload_0
	getfield	Field putLock:Ljava/lang/Object;
	dup
	astore_2
	monitorenter
	aload_0
	getfield	Field takeLock:Ljava/lang/Object;
	dup
	astore_3
	monitorenter
	aload_0
	getfield	Field count:I
	istore	4
	aload_1
	arraylength
	iload	4
	if_icmpge	l1 // iconst_0
	aload_1
	invokevirtual	Method java/lang/Object.getClass:()Ljava/lang/Class;
	invokevirtual	Method java/lang/Class.getComponentType:()Ljava/lang/Class;
	iload	4
	invokestatic	Method java/lang/reflect/Array.newInstance:(Ljava/lang/Class;I)Ljava/lang/Object;
	checkcast	class "[Ljava/lang/Object;"
	checkcast	class "[Ljava/lang/Object;"
	astore_1
l1	iconst_0
	istore	5
	aload_0
	getfield	Field head:Lscala/actors/threadpool/LinkedBlockingQueue$Node;
	getfield	Field scala/actors/threadpool/LinkedBlockingQueue$Node.next:Lscala/actors/threadpool/LinkedBlockingQueue$Node;
	astore	6
l3	aload	6
	ifnull	l2 // aload_1
	aload_1
	iload	5
	iinc	5, 1
	aload	6
	getfield	Field scala/actors/threadpool/LinkedBlockingQueue$Node.item:Ljava/lang/Object;
	aastore
	aload	6
	getfield	Field scala/actors/threadpool/LinkedBlockingQueue$Node.next:Lscala/actors/threadpool/LinkedBlockingQueue$Node;
	astore	6
	goto	l3 // aload
l2	aload_1
	arraylength
	iload	5
	if_icmple	l4 // aload_1
	aload_1
	iload	5
	aconst_null
	aastore
l4	aload_1
	aload_3
	monitorexit
	aload_2
	monitorexit
	areturn
	astore	7
	aload_3
	monitorexit
	aload	7
	athrow
	astore	8
	aload_2
	monitorexit
	aload	8
	athrow
  Labels:
   	l1 = 46 // iconst_0
   	l3 = 58 // aload
   	l2 = 85 // aload_1
   	l4 = 97 // aload_1
  Exception table:
   from   to  target type
    14   100   103   any
   103   107   103   any
     7   102   110   any
   103   114   110   any

public java.lang.String toString();
  Signature: ()Ljava/lang/String;
  Code:
   Stack=2, Locals=5, Args_size=1
	aload_0
	getfield	Field putLock:Ljava/lang/Object;
	dup
	astore_1
	monitorenter
	aload_0
	getfield	Field takeLock:Ljava/lang/Object;
	dup
	astore_2
	monitorenter
	aload_0
	invokespecial	Method scala/actors/threadpool/AbstractQueue.toString:()Ljava/lang/String;
	aload_2
	monitorexit
	aload_1
	monitorexit
	areturn
	astore_3
	aload_2
	monitorexit
	aload_3
	athrow
	astore	4
	aload_1
	monitorexit
	aload	4
	athrow
  Labels:
  Exception table:
   from   to  target type
    14    20    23   any
    23    26    23   any
     7    22    28   any
    23    32    28   any

public void clear();
  Signature: ()V
  Code:
   Stack=2, Locals=8, Args_size=1
	aload_0
	getfield	Field putLock:Ljava/lang/Object;
	dup
	astore_1
	monitorenter
	aload_0
	getfield	Field takeLock:Ljava/lang/Object;
	dup
	astore_2
	monitorenter
	aload_0
	getfield	Field head:Lscala/actors/threadpool/LinkedBlockingQueue$Node;
	aconst_null
	putfield	Field scala/actors/threadpool/LinkedBlockingQueue$Node.next:Lscala/actors/threadpool/LinkedBlockingQueue$Node;
	getstatic	Field $assertionsDisabled:Z
	ifne	l1 // aload_0
	aload_0
	getfield	Field head:Lscala/actors/threadpool/LinkedBlockingQueue$Node;
	getfield	Field scala/actors/threadpool/LinkedBlockingQueue$Node.item:Ljava/lang/Object;
	ifnull	l1 // aload_0
	new	class java/lang/AssertionError
	dup
	invokespecial	Method java/lang/AssertionError."<init>":()V
	athrow
l1	aload_0
	aload_0
	getfield	Field head:Lscala/actors/threadpool/LinkedBlockingQueue$Node;
	putfield	Field last:Lscala/actors/threadpool/LinkedBlockingQueue$Node;
	aload_0
	dup
	astore	4
	monitorenter
	aload_0
	getfield	Field count:I
	istore_3
	aload_0
	iconst_0
	putfield	Field count:I
	aload	4
	monitorexit
	goto	l2 // iload_3
	astore	5
	aload	4
	monitorexit
	aload	5
	athrow
l2	iload_3
	aload_0
	getfield	Field capacity:I
	if_icmpne	l3 // aload_2
	aload_0
	getfield	Field putLock:Ljava/lang/Object;
	invokevirtual	Method java/lang/Object.notifyAll:()V
l3	aload_2
	monitorexit
	goto	l4 // aload_1
	astore	6
	aload_2
	monitorexit
	aload	6
	athrow
l4	aload_1
	monitorexit
	goto	l5 // return
	astore	7
	aload_1
	monitorexit
	aload	7
	athrow
l5	return
  Labels:
   	l1 = 46 // aload_0
   	l2 = 83 // iload_3
   	l3 = 98 // aload_2
   	l4 = 110 // aload_1
   	l5 = 122 // return
  Exception table:
   from   to  target type
    59    72    75   any
    75    80    75   any
    14   100   103   any
   103   107   103   any
     7   112   115   any
   115   119   115   any

public int drainTo(java.util.Collection);
  Signature: (Ljava/util/Collection;)I
  Code:
   Stack=2, Locals=10, Args_size=2
	aload_1
	ifnonnull	l1 // aload_1
	new	class java/lang/NullPointerException
	dup
	invokespecial	Method java/lang/NullPointerException."<init>":()V
	athrow
l1	aload_1
	aload_0
	if_acmpne	l2 // aload_0
	new	class java/lang/IllegalArgumentException
	dup
	invokespecial	Method java/lang/IllegalArgumentException."<init>":()V
	athrow
l2	aload_0
	getfield	Field putLock:Ljava/lang/Object;
	dup
	astore_3
	monitorenter
	aload_0
	getfield	Field takeLock:Ljava/lang/Object;
	dup
	astore	4
	monitorenter
	aload_0
	getfield	Field head:Lscala/actors/threadpool/LinkedBlockingQueue$Node;
	getfield	Field scala/actors/threadpool/LinkedBlockingQueue$Node.next:Lscala/actors/threadpool/LinkedBlockingQueue$Node;
	astore_2
	aload_0
	getfield	Field head:Lscala/actors/threadpool/LinkedBlockingQueue$Node;
	aconst_null
	putfield	Field scala/actors/threadpool/LinkedBlockingQueue$Node.next:Lscala/actors/threadpool/LinkedBlockingQueue$Node;
	getstatic	Field $assertionsDisabled:Z
	ifne	l3 // aload_0
	aload_0
	getfield	Field head:Lscala/actors/threadpool/LinkedBlockingQueue$Node;
	getfield	Field scala/actors/threadpool/LinkedBlockingQueue$Node.item:Ljava/lang/Object;
	ifnull	l3 // aload_0
	new	class java/lang/AssertionError
	dup
	invokespecial	Method java/lang/AssertionError."<init>":()V
	athrow
l3	aload_0
	aload_0
	getfield	Field head:Lscala/actors/threadpool/LinkedBlockingQueue$Node;
	putfield	Field last:Lscala/actors/threadpool/LinkedBlockingQueue$Node;
	aload_0
	dup
	astore	6
	monitorenter
	aload_0
	getfield	Field count:I
	istore	5
	aload_0
	iconst_0
	putfield	Field count:I
	aload	6
	monitorexit
	goto	l4 // iload
	astore	7
	aload	6
	monitorexit
	aload	7
	athrow
l4	iload	5
	aload_0
	getfield	Field capacity:I
	if_icmpne	l5 // aload
	aload_0
	getfield	Field putLock:Ljava/lang/Object;
	invokevirtual	Method java/lang/Object.notifyAll:()V
l5	aload	4
	monitorexit
	goto	l6 // aload_3
	astore	8
	aload	4
	monitorexit
	aload	8
	athrow
l6	aload_3
	monitorexit
	goto	l7 // iconst_0
	astore	9
	aload_3
	monitorexit
	aload	9
	athrow
l7	iconst_0
	istore_3
	aload_2
	astore	4
l9	aload	4
	ifnull	l8 // iload_3
	aload_1
	aload	4
	getfield	Field scala/actors/threadpool/LinkedBlockingQueue$Node.item:Ljava/lang/Object;
	invokeinterface	InterfaceMethod java/util/Collection.add:(Ljava/lang/Object;)Z
	pop
	aload	4
	aconst_null
	putfield	Field scala/actors/threadpool/LinkedBlockingQueue$Node.item:Ljava/lang/Object;
	iinc	3, 1
	aload	4
	getfield	Field scala/actors/threadpool/LinkedBlockingQueue$Node.next:Lscala/actors/threadpool/LinkedBlockingQueue$Node;
	astore	4
	goto	l9 // aload
l8	iload_3
	ireturn
  Labels:
   	l1 = 12 // aload_1
   	l2 = 25 // aload_0
   	l3 = 80 // aload_0
   	l4 = 118 // iload
   	l5 = 134 // aload
   	l6 = 148 // aload_3
   	l7 = 160 // iconst_0
   	l9 = 165 // aload
   	l8 = 201 // iload_3
  Exception table:
   from   to  target type
    93   107   110   any
   110   115   110   any
    40   137   140   any
   140   145   140   any
    32   150   153   any
   153   157   153   any

public int drainTo(java.util.Collection, int);
  Signature: (Ljava/util/Collection;I)I
  Code:
   Stack=3, Locals=12, Args_size=3
	aload_1
	ifnonnull	l1 // aload_1
	new	class java/lang/NullPointerException
	dup
	invokespecial	Method java/lang/NullPointerException."<init>":()V
	athrow
l1	aload_1
	aload_0
	if_acmpne	l2 // aload_0
	new	class java/lang/IllegalArgumentException
	dup
	invokespecial	Method java/lang/IllegalArgumentException."<init>":()V
	athrow
l2	aload_0
	getfield	Field putLock:Ljava/lang/Object;
	dup
	astore_3
	monitorenter
	aload_0
	getfield	Field takeLock:Ljava/lang/Object;
	dup
	astore	4
	monitorenter
	iconst_0
	istore	5
	aload_0
	getfield	Field head:Lscala/actors/threadpool/LinkedBlockingQueue$Node;
	getfield	Field scala/actors/threadpool/LinkedBlockingQueue$Node.next:Lscala/actors/threadpool/LinkedBlockingQueue$Node;
	astore	6
l4	aload	6
	ifnull	l3 // iload
	iload	5
	iload_2
	if_icmpge	l3 // iload
	aload_1
	aload	6
	getfield	Field scala/actors/threadpool/LinkedBlockingQueue$Node.item:Ljava/lang/Object;
	invokeinterface	InterfaceMethod java/util/Collection.add:(Ljava/lang/Object;)Z
	pop
	aload	6
	aconst_null
	putfield	Field scala/actors/threadpool/LinkedBlockingQueue$Node.item:Ljava/lang/Object;
	aload	6
	getfield	Field scala/actors/threadpool/LinkedBlockingQueue$Node.next:Lscala/actors/threadpool/LinkedBlockingQueue$Node;
	astore	6
	iinc	5, 1
	goto	l4 // aload
l3	iload	5
	ifeq	l5 // iload
	aload_0
	getfield	Field head:Lscala/actors/threadpool/LinkedBlockingQueue$Node;
	aload	6
	putfield	Field scala/actors/threadpool/LinkedBlockingQueue$Node.next:Lscala/actors/threadpool/LinkedBlockingQueue$Node;
	getstatic	Field $assertionsDisabled:Z
	ifne	l6 // aload
	aload_0
	getfield	Field head:Lscala/actors/threadpool/LinkedBlockingQueue$Node;
	getfield	Field scala/actors/threadpool/LinkedBlockingQueue$Node.item:Ljava/lang/Object;
	ifnull	l6 // aload
	new	class java/lang/AssertionError
	dup
	invokespecial	Method java/lang/AssertionError."<init>":()V
	athrow
l6	aload	6
	ifnonnull	l7 // aload_0
	aload_0
	aload_0
	getfield	Field head:Lscala/actors/threadpool/LinkedBlockingQueue$Node;
	putfield	Field last:Lscala/actors/threadpool/LinkedBlockingQueue$Node;
l7	aload_0
	dup
	astore	8
	monitorenter
	aload_0
	getfield	Field count:I
	istore	7
	aload_0
	dup
	getfield	Field count:I
	iload	5
	isub
	putfield	Field count:I
	aload	8
	monitorexit
	goto	l8 // iload
	astore	9
	aload	8
	monitorexit
	aload	9
	athrow
l8	iload	7
	aload_0
	getfield	Field capacity:I
	if_icmpne	l5 // iload
	aload_0
	getfield	Field putLock:Ljava/lang/Object;
	invokevirtual	Method java/lang/Object.notifyAll:()V
l5	iload	5
	aload	4
	monitorexit
	aload_3
	monitorexit
	ireturn
	astore	10
	aload	4
	monitorexit
	aload	10
	athrow
	astore	11
	aload_3
	monitorexit
	aload	11
	athrow
  Labels:
   	l1 = 12 // aload_1
   	l2 = 25 // aload_0
   	l4 = 52 // aload
   	l3 = 94 // iload
   	l6 = 132 // aload
   	l7 = 145 // aload_0
   	l8 = 181 // iload
   	l5 = 197 // iload
  Exception table:
   from   to  target type
   150   170   173   any
   173   178   173   any
    40   202   205   any
   205   210   205   any
    32   204   213   any
   205   217   213   any

public java.util.Iterator iterator();
  Signature: ()Ljava/util/Iterator;
  Code:
   Stack=3, Locals=1, Args_size=1
	new	class scala/actors/threadpool/LinkedBlockingQueue$Itr
	dup
	aload_0
	invokespecial	Method scala/actors/threadpool/LinkedBlockingQueue$Itr."<init>":(Lscala/actors/threadpool/LinkedBlockingQueue;)V
	areturn
  Labels:

private void writeObject(java.io.ObjectOutputStream)   throws java.io.IOException;
  Signature: (Ljava/io/ObjectOutputStream;)V
  Code:
   Stack=2, Locals=7, Args_size=2
	aload_0
	getfield	Field putLock:Ljava/lang/Object;
	dup
	astore_2
	monitorenter
	aload_0
	getfield	Field takeLock:Ljava/lang/Object;
	dup
	astore_3
	monitorenter
	aload_1
	invokevirtual	Method java/io/ObjectOutputStream.defaultWriteObject:()V
	aload_0
	getfield	Field head:Lscala/actors/threadpool/LinkedBlockingQueue$Node;
	getfield	Field scala/actors/threadpool/LinkedBlockingQueue$Node.next:Lscala/actors/threadpool/LinkedBlockingQueue$Node;
	astore	4
l2	aload	4
	ifnull	l1 // aload_1
	aload_1
	aload	4
	getfield	Field scala/actors/threadpool/LinkedBlockingQueue$Node.item:Ljava/lang/Object;
	invokevirtual	Method java/io/ObjectOutputStream.writeObject:(Ljava/lang/Object;)V
	aload	4
	getfield	Field scala/actors/threadpool/LinkedBlockingQueue$Node.next:Lscala/actors/threadpool/LinkedBlockingQueue$Node;
	astore	4
	goto	l2 // aload
l1	aload_1
	aconst_null
	invokevirtual	Method java/io/ObjectOutputStream.writeObject:(Ljava/lang/Object;)V
	aload_3
	monitorexit
	goto	l3 // aload_2
	astore	5
	aload_3
	monitorexit
	aload	5
	athrow
l3	aload_2
	monitorexit
	goto	l4 // return
	astore	6
	aload_2
	monitorexit
	aload	6
	athrow
l4	return
  Labels:
   	l2 = 27 // aload
   	l1 = 51 // aload_1
   	l3 = 68 // aload_2
   	l4 = 80 // return
  Exception table:
   from   to  target type
    14    58    61   any
    61    65    61   any
     7    70    73   any
    73    77    73   any
  Exceptions: 
   throws java.io.IOException
private void readObject(java.io.ObjectInputStream)   throws java.io.IOException, java.lang.ClassNotFoundException;
  Signature: (Ljava/io/ObjectInputStream;)V
  Code:
   Stack=5, Locals=4, Args_size=2
	aload_1
	invokevirtual	Method java/io/ObjectInputStream.defaultReadObject:()V
	aload_0
	dup
	astore_2
	monitorenter
	aload_0
	iconst_0
	putfield	Field count:I
	aload_2
	monitorexit
	goto	l1 // aload_0
	astore_3
	aload_2
	monitorexit
	aload_3
	athrow
l1	aload_0
	aload_0
	new	class scala/actors/threadpool/LinkedBlockingQueue$Node
	dup
	aconst_null
	invokespecial	Method scala/actors/threadpool/LinkedBlockingQueue$Node."<init>":(Ljava/lang/Object;)V
	dup_x1
	putfield	Field head:Lscala/actors/threadpool/LinkedBlockingQueue$Node;
	putfield	Field last:Lscala/actors/threadpool/LinkedBlockingQueue$Node;
l4	aload_1
	invokevirtual	Method java/io/ObjectInputStream.readObject:()Ljava/lang/Object;
	astore_2
	aload_2
	ifnonnull	l2 // aload_0
	goto	l3 // return
l2	aload_0
	aload_2
	invokevirtual	Method add:(Ljava/lang/Object;)Z
	pop
	goto	l4 // aload_1
l3	return
  Labels:
   	l1 = 23 // aload_0
   	l4 = 40 // aload_1
   	l2 = 52 // aload_0
   	l3 = 61 // return
  Exception table:
   from   to  target type
     8    15    18   any
    18    21    18   any
  Exceptions: 
   throws java.io.IOException, java.lang.ClassNotFoundException
static java.lang.Object access$100(scala.actors.threadpool.LinkedBlockingQueue);
  Signature: (Lscala/actors/threadpool/LinkedBlockingQueue;)Ljava/lang/Object;
  Code:
   Stack=1, Locals=1, Args_size=1
	aload_0
	getfield	Field putLock:Ljava/lang/Object;
	areturn
  Labels:

static java.lang.Object access$200(scala.actors.threadpool.LinkedBlockingQueue);
  Signature: (Lscala/actors/threadpool/LinkedBlockingQueue;)Ljava/lang/Object;
  Code:
   Stack=1, Locals=1, Args_size=1
	aload_0
	getfield	Field takeLock:Ljava/lang/Object;
	areturn
  Labels:

static scala.actors.threadpool.LinkedBlockingQueue$Node access$300(scala.actors.threadpool.LinkedBlockingQueue);
  Signature: (Lscala/actors/threadpool/LinkedBlockingQueue;)Lscala/actors/threadpool/LinkedBlockingQueue$Node;
  Code:
   Stack=1, Locals=1, Args_size=1
	aload_0
	getfield	Field head:Lscala/actors/threadpool/LinkedBlockingQueue$Node;
	areturn
  Labels:

static scala.actors.threadpool.LinkedBlockingQueue$Node access$400(scala.actors.threadpool.LinkedBlockingQueue);
  Signature: (Lscala/actors/threadpool/LinkedBlockingQueue;)Lscala/actors/threadpool/LinkedBlockingQueue$Node;
  Code:
   Stack=1, Locals=1, Args_size=1
	aload_0
	getfield	Field last:Lscala/actors/threadpool/LinkedBlockingQueue$Node;
	areturn
  Labels:

static scala.actors.threadpool.LinkedBlockingQueue$Node access$402(scala.actors.threadpool.LinkedBlockingQueue, scala.actors.threadpool.LinkedBlockingQueue$Node);
  Signature: (Lscala/actors/threadpool/LinkedBlockingQueue;Lscala/actors/threadpool/LinkedBlockingQueue$Node;)Lscala/actors/threadpool/LinkedBlockingQueue$Node;
  Code:
   Stack=3, Locals=2, Args_size=2
	aload_0
	aload_1
	dup_x1
	putfield	Field last:Lscala/actors/threadpool/LinkedBlockingQueue$Node;
	areturn
  Labels:

static int access$510(scala.actors.threadpool.LinkedBlockingQueue);
  Signature: (Lscala/actors/threadpool/LinkedBlockingQueue;)I
  Code:
   Stack=4, Locals=1, Args_size=1
	aload_0
	dup
	getfield	Field count:I
	dup_x1
	iconst_1
	isub
	putfield	Field count:I
	ireturn
  Labels:

static int access$600(scala.actors.threadpool.LinkedBlockingQueue);
  Signature: (Lscala/actors/threadpool/LinkedBlockingQueue;)I
  Code:
   Stack=1, Locals=1, Args_size=1
	aload_0
	getfield	Field capacity:I
	ireturn
  Labels:

static {};
  Signature: ()V
  Code:
   Stack=1, Locals=0, Args_size=0
	ldc_w	class scala/actors/threadpool/LinkedBlockingQueue
	invokevirtual	Method java/lang/Class.desiredAssertionStatus:()Z
	ifne	l1 // iconst_0
	iconst_1
	goto	l2 // putstatic
l1	iconst_0
l2	putstatic	Field $assertionsDisabled:Z
	return
  Labels:
   	l1 = 13 // iconst_0
   	l2 = 14 // putstatic

}

