class scala.actors.threadpool.LinkedBlockingQueue$Itr extends java.lang.Object implements java.util.Iterator
  InnerClass: 
   #25= #24 of #44; //Node=class scala/actors/threadpool/LinkedBlockingQueue$Node of class scala/actors/threadpool/LinkedBlockingQueue
   #61= #20 of #44; //Itr=class scala/actors/threadpool/LinkedBlockingQueue$Itr of class scala/actors/threadpool/LinkedBlockingQueue
  minor version: 0
  major version: 49
  Constant pool:
const #1 = Field	#20.#42;	//  scala/actors/threadpool/LinkedBlockingQueue$Itr.this$0:Lscala/actors/threadpool/LinkedBlockingQueue;
const #2 = Method	#21.#43;	//  java/lang/Object."<init>":()V
const #3 = Method	#44.#45;	//  scala/actors/threadpool/LinkedBlockingQueue.access$100:(Lscala/actors/threadpool/LinkedBlockingQueue;)Ljava/lang/Object;
const #4 = Method	#44.#46;	//  scala/actors/threadpool/LinkedBlockingQueue.access$200:(Lscala/actors/threadpool/LinkedBlockingQueue;)Ljava/lang/Object;
const #5 = Method	#44.#47;	//  scala/actors/threadpool/LinkedBlockingQueue.access$300:(Lscala/actors/threadpool/LinkedBlockingQueue;)Lscala/actors/threadpool/LinkedBlockingQueue$Node;
const #6 = Field	#24.#48;	//  scala/actors/threadpool/LinkedBlockingQueue$Node.next:Lscala/actors/threadpool/LinkedBlockingQueue$Node;
const #7 = Field	#20.#49;	//  scala/actors/threadpool/LinkedBlockingQueue$Itr.current:Lscala/actors/threadpool/LinkedBlockingQueue$Node;
const #8 = Field	#24.#50;	//  scala/actors/threadpool/LinkedBlockingQueue$Node.item:Ljava/lang/Object;
const #9 = Field	#20.#51;	//  scala/actors/threadpool/LinkedBlockingQueue$Itr.currentElement:Ljava/lang/Object;
const #10 = class	#52;	//  java/util/NoSuchElementException
const #11 = Method	#10.#43;	//  java/util/NoSuchElementException."<init>":()V
const #12 = Field	#20.#53;	//  scala/actors/threadpool/LinkedBlockingQueue$Itr.lastRet:Lscala/actors/threadpool/LinkedBlockingQueue$Node;
const #13 = class	#54;	//  java/lang/IllegalStateException
const #14 = Method	#13.#43;	//  java/lang/IllegalStateException."<init>":()V
const #15 = Method	#44.#55;	//  scala/actors/threadpool/LinkedBlockingQueue.access$400:(Lscala/actors/threadpool/LinkedBlockingQueue;)Lscala/actors/threadpool/LinkedBlockingQueue$Node;
const #16 = Method	#44.#56;	//  scala/actors/threadpool/LinkedBlockingQueue.access$402:(Lscala/actors/threadpool/LinkedBlockingQueue;Lscala/actors/threadpool/LinkedBlockingQueue$Node;)Lscala/actors/threadpool/LinkedBlockingQueue$Node;
const #17 = Method	#44.#57;	//  scala/actors/threadpool/LinkedBlockingQueue.access$510:(Lscala/actors/threadpool/LinkedBlockingQueue;)I
const #18 = Method	#44.#58;	//  scala/actors/threadpool/LinkedBlockingQueue.access$600:(Lscala/actors/threadpool/LinkedBlockingQueue;)I
const #19 = Method	#21.#59;	//  java/lang/Object.notifyAll:()V
const #20 = class	#60;	//  scala/actors/threadpool/LinkedBlockingQueue$Itr
const #21 = class	#62;	//  java/lang/Object
const #22 = class	#63;	//  java/util/Iterator
const #23 = Asciz	current;
const #24 = class	#64;	//  scala/actors/threadpool/LinkedBlockingQueue$Node
const #25 = Asciz	Node;
const #26 = Asciz	InnerClasses;
const #27 = Asciz	Lscala/actors/threadpool/LinkedBlockingQueue$Node;;
const #28 = Asciz	lastRet;
const #29 = Asciz	currentElement;
const #30 = Asciz	Ljava/lang/Object;;
const #31 = Asciz	this$0;
const #32 = Asciz	Lscala/actors/threadpool/LinkedBlockingQueue;;
const #33 = Asciz	<init>;
const #34 = Asciz	(Lscala/actors/threadpool/LinkedBlockingQueue;)V;
const #35 = Asciz	Code;
const #36 = Asciz	hasNext;
const #37 = Asciz	()Z;
const #38 = Asciz	next;
const #39 = Asciz	()Ljava/lang/Object;;
const #40 = Asciz	remove;
const #41 = Asciz	()V;
const #42 = NameAndType	#31:#32;//  this$0:Lscala/actors/threadpool/LinkedBlockingQueue;
const #43 = NameAndType	#33:#41;//  "<init>":()V
const #44 = class	#65;	//  scala/actors/threadpool/LinkedBlockingQueue
const #45 = NameAndType	#66:#67;//  access$100:(Lscala/actors/threadpool/LinkedBlockingQueue;)Ljava/lang/Object;
const #46 = NameAndType	#68:#67;//  access$200:(Lscala/actors/threadpool/LinkedBlockingQueue;)Ljava/lang/Object;
const #47 = NameAndType	#69:#70;//  access$300:(Lscala/actors/threadpool/LinkedBlockingQueue;)Lscala/actors/threadpool/LinkedBlockingQueue$Node;
const #48 = NameAndType	#38:#27;//  next:Lscala/actors/threadpool/LinkedBlockingQueue$Node;
const #49 = NameAndType	#23:#27;//  current:Lscala/actors/threadpool/LinkedBlockingQueue$Node;
const #50 = NameAndType	#71:#30;//  item:Ljava/lang/Object;
const #51 = NameAndType	#29:#30;//  currentElement:Ljava/lang/Object;
const #52 = Asciz	java/util/NoSuchElementException;
const #53 = NameAndType	#28:#27;//  lastRet:Lscala/actors/threadpool/LinkedBlockingQueue$Node;
const #54 = Asciz	java/lang/IllegalStateException;
const #55 = NameAndType	#72:#70;//  access$400:(Lscala/actors/threadpool/LinkedBlockingQueue;)Lscala/actors/threadpool/LinkedBlockingQueue$Node;
const #56 = NameAndType	#73:#74;//  access$402:(Lscala/actors/threadpool/LinkedBlockingQueue;Lscala/actors/threadpool/LinkedBlockingQueue$Node;)Lscala/actors/threadpool/LinkedBlockingQueue$Node;
const #57 = NameAndType	#75:#76;//  access$510:(Lscala/actors/threadpool/LinkedBlockingQueue;)I
const #58 = NameAndType	#77:#76;//  access$600:(Lscala/actors/threadpool/LinkedBlockingQueue;)I
const #59 = NameAndType	#78:#41;//  notifyAll:()V
const #60 = Asciz	scala/actors/threadpool/LinkedBlockingQueue$Itr;
const #61 = Asciz	Itr;
const #62 = Asciz	java/lang/Object;
const #63 = Asciz	java/util/Iterator;
const #64 = Asciz	scala/actors/threadpool/LinkedBlockingQueue$Node;
const #65 = Asciz	scala/actors/threadpool/LinkedBlockingQueue;
const #66 = Asciz	access$100;
const #67 = Asciz	(Lscala/actors/threadpool/LinkedBlockingQueue;)Ljava/lang/Object;;
const #68 = Asciz	access$200;
const #69 = Asciz	access$300;
const #70 = Asciz	(Lscala/actors/threadpool/LinkedBlockingQueue;)Lscala/actors/threadpool/LinkedBlockingQueue$Node;;
const #71 = Asciz	item;
const #72 = Asciz	access$400;
const #73 = Asciz	access$402;
const #74 = Asciz	(Lscala/actors/threadpool/LinkedBlockingQueue;Lscala/actors/threadpool/LinkedBlockingQueue$Node;)Lscala/actors/threadpool/LinkedBlockingQueue$Node;;
const #75 = Asciz	access$510;
const #76 = Asciz	(Lscala/actors/threadpool/LinkedBlockingQueue;)I;
const #77 = Asciz	access$600;
const #78 = Asciz	notifyAll;

{
final scala.actors.threadpool.LinkedBlockingQueue this$0;

scala.actors.threadpool.LinkedBlockingQueue$Itr(scala.actors.threadpool.LinkedBlockingQueue);
  Code:
   Stack=2, Locals=6, Args_size=2
   0:	aload_0
   1:	aload_1
   2:	putfield	#1; //Field this$0:Lscala/actors/threadpool/LinkedBlockingQueue;
   5:	aload_0
   6:	invokespecial	#2; //Method java/lang/Object."<init>":()V
   9:	aload_1
   10:	invokestatic	#3; //Method scala/actors/threadpool/LinkedBlockingQueue.access$100:(Lscala/actors/threadpool/LinkedBlockingQueue;)Ljava/lang/Object;
   13:	dup
   14:	astore_2
   15:	monitorenter
   16:	aload_1
   17:	invokestatic	#4; //Method scala/actors/threadpool/LinkedBlockingQueue.access$200:(Lscala/actors/threadpool/LinkedBlockingQueue;)Ljava/lang/Object;
   20:	dup
   21:	astore_3
   22:	monitorenter
   23:	aload_0
   24:	aload_1
   25:	invokestatic	#5; //Method scala/actors/threadpool/LinkedBlockingQueue.access$300:(Lscala/actors/threadpool/LinkedBlockingQueue;)Lscala/actors/threadpool/LinkedBlockingQueue$Node;
   28:	getfield	#6; //Field scala/actors/threadpool/LinkedBlockingQueue$Node.next:Lscala/actors/threadpool/LinkedBlockingQueue$Node;
   31:	putfield	#7; //Field current:Lscala/actors/threadpool/LinkedBlockingQueue$Node;
   34:	aload_0
   35:	getfield	#7; //Field current:Lscala/actors/threadpool/LinkedBlockingQueue$Node;
   38:	ifnull	52
   41:	aload_0
   42:	aload_0
   43:	getfield	#7; //Field current:Lscala/actors/threadpool/LinkedBlockingQueue$Node;
   46:	getfield	#8; //Field scala/actors/threadpool/LinkedBlockingQueue$Node.item:Ljava/lang/Object;
   49:	putfield	#9; //Field currentElement:Ljava/lang/Object;
   52:	aload_3
   53:	monitorexit
   54:	goto	64
   57:	astore	4
   59:	aload_3
   60:	monitorexit
   61:	aload	4
   63:	athrow
   64:	aload_2
   65:	monitorexit
   66:	goto	76
   69:	astore	5
   71:	aload_2
   72:	monitorexit
   73:	aload	5
   75:	athrow
   76:	return
  Exception table:
   from   to  target type
    23    54    57   any
    57    61    57   any
    16    66    69   any
    69    73    69   any

public boolean hasNext();
  Code:
   Stack=1, Locals=1, Args_size=1
   0:	aload_0
   1:	getfield	#7; //Field current:Lscala/actors/threadpool/LinkedBlockingQueue$Node;
   4:	ifnull	11
   7:	iconst_1
   8:	goto	12
   11:	iconst_0
   12:	ireturn

public java.lang.Object next();
  Code:
   Stack=2, Locals=6, Args_size=1
   0:	aload_0
   1:	getfield	#1; //Field this$0:Lscala/actors/threadpool/LinkedBlockingQueue;
   4:	invokestatic	#3; //Method scala/actors/threadpool/LinkedBlockingQueue.access$100:(Lscala/actors/threadpool/LinkedBlockingQueue;)Ljava/lang/Object;
   7:	dup
   8:	astore_1
   9:	monitorenter
   10:	aload_0
   11:	getfield	#1; //Field this$0:Lscala/actors/threadpool/LinkedBlockingQueue;
   14:	invokestatic	#4; //Method scala/actors/threadpool/LinkedBlockingQueue.access$200:(Lscala/actors/threadpool/LinkedBlockingQueue;)Ljava/lang/Object;
   17:	dup
   18:	astore_2
   19:	monitorenter
   20:	aload_0
   21:	getfield	#7; //Field current:Lscala/actors/threadpool/LinkedBlockingQueue$Node;
   24:	ifnonnull	35
   27:	new	#10; //class java/util/NoSuchElementException
   30:	dup
   31:	invokespecial	#11; //Method java/util/NoSuchElementException."<init>":()V
   34:	athrow
   35:	aload_0
   36:	getfield	#9; //Field currentElement:Ljava/lang/Object;
   39:	astore_3
   40:	aload_0
   41:	aload_0
   42:	getfield	#7; //Field current:Lscala/actors/threadpool/LinkedBlockingQueue$Node;
   45:	putfield	#12; //Field lastRet:Lscala/actors/threadpool/LinkedBlockingQueue$Node;
   48:	aload_0
   49:	aload_0
   50:	getfield	#7; //Field current:Lscala/actors/threadpool/LinkedBlockingQueue$Node;
   53:	getfield	#6; //Field scala/actors/threadpool/LinkedBlockingQueue$Node.next:Lscala/actors/threadpool/LinkedBlockingQueue$Node;
   56:	putfield	#7; //Field current:Lscala/actors/threadpool/LinkedBlockingQueue$Node;
   59:	aload_0
   60:	getfield	#7; //Field current:Lscala/actors/threadpool/LinkedBlockingQueue$Node;
   63:	ifnull	77
   66:	aload_0
   67:	aload_0
   68:	getfield	#7; //Field current:Lscala/actors/threadpool/LinkedBlockingQueue$Node;
   71:	getfield	#8; //Field scala/actors/threadpool/LinkedBlockingQueue$Node.item:Ljava/lang/Object;
   74:	putfield	#9; //Field currentElement:Ljava/lang/Object;
   77:	aload_3
   78:	aload_2
   79:	monitorexit
   80:	aload_1
   81:	monitorexit
   82:	areturn
   83:	astore	4
   85:	aload_2
   86:	monitorexit
   87:	aload	4
   89:	athrow
   90:	astore	5
   92:	aload_1
   93:	monitorexit
   94:	aload	5
   96:	athrow
  Exception table:
   from   to  target type
    20    80    83   any
    83    87    83   any
    10    82    90   any
    83    94    90   any

public void remove();
  Code:
   Stack=2, Locals=11, Args_size=1
   0:	aload_0
   1:	getfield	#12; //Field lastRet:Lscala/actors/threadpool/LinkedBlockingQueue$Node;
   4:	ifnonnull	15
   7:	new	#13; //class java/lang/IllegalStateException
   10:	dup
   11:	invokespecial	#14; //Method java/lang/IllegalStateException."<init>":()V
   14:	athrow
   15:	aload_0
   16:	getfield	#1; //Field this$0:Lscala/actors/threadpool/LinkedBlockingQueue;
   19:	invokestatic	#3; //Method scala/actors/threadpool/LinkedBlockingQueue.access$100:(Lscala/actors/threadpool/LinkedBlockingQueue;)Ljava/lang/Object;
   22:	dup
   23:	astore_1
   24:	monitorenter
   25:	aload_0
   26:	getfield	#1; //Field this$0:Lscala/actors/threadpool/LinkedBlockingQueue;
   29:	invokestatic	#4; //Method scala/actors/threadpool/LinkedBlockingQueue.access$200:(Lscala/actors/threadpool/LinkedBlockingQueue;)Ljava/lang/Object;
   32:	dup
   33:	astore_2
   34:	monitorenter
   35:	aload_0
   36:	getfield	#12; //Field lastRet:Lscala/actors/threadpool/LinkedBlockingQueue$Node;
   39:	astore_3
   40:	aload_0
   41:	aconst_null
   42:	putfield	#12; //Field lastRet:Lscala/actors/threadpool/LinkedBlockingQueue$Node;
   45:	aload_0
   46:	getfield	#1; //Field this$0:Lscala/actors/threadpool/LinkedBlockingQueue;
   49:	invokestatic	#5; //Method scala/actors/threadpool/LinkedBlockingQueue.access$300:(Lscala/actors/threadpool/LinkedBlockingQueue;)Lscala/actors/threadpool/LinkedBlockingQueue$Node;
   52:	astore	4
   54:	aload_0
   55:	getfield	#1; //Field this$0:Lscala/actors/threadpool/LinkedBlockingQueue;
   58:	invokestatic	#5; //Method scala/actors/threadpool/LinkedBlockingQueue.access$300:(Lscala/actors/threadpool/LinkedBlockingQueue;)Lscala/actors/threadpool/LinkedBlockingQueue$Node;
   61:	getfield	#6; //Field scala/actors/threadpool/LinkedBlockingQueue$Node.next:Lscala/actors/threadpool/LinkedBlockingQueue$Node;
   64:	astore	5
   66:	aload	5
   68:	ifnull	91
   71:	aload	5
   73:	aload_3
   74:	if_acmpeq	91
   77:	aload	5
   79:	astore	4
   81:	aload	5
   83:	getfield	#6; //Field scala/actors/threadpool/LinkedBlockingQueue$Node.next:Lscala/actors/threadpool/LinkedBlockingQueue$Node;
   86:	astore	5
   88:	goto	66
   91:	aload	5
   93:	aload_3
   94:	if_acmpne	185
   97:	aload	5
   99:	aconst_null
   100:	putfield	#8; //Field scala/actors/threadpool/LinkedBlockingQueue$Node.item:Ljava/lang/Object;
   103:	aload	4
   105:	aload	5
   107:	getfield	#6; //Field scala/actors/threadpool/LinkedBlockingQueue$Node.next:Lscala/actors/threadpool/LinkedBlockingQueue$Node;
   110:	putfield	#6; //Field scala/actors/threadpool/LinkedBlockingQueue$Node.next:Lscala/actors/threadpool/LinkedBlockingQueue$Node;
   113:	aload_0
   114:	getfield	#1; //Field this$0:Lscala/actors/threadpool/LinkedBlockingQueue;
   117:	invokestatic	#15; //Method scala/actors/threadpool/LinkedBlockingQueue.access$400:(Lscala/actors/threadpool/LinkedBlockingQueue;)Lscala/actors/threadpool/LinkedBlockingQueue$Node;
   120:	aload	5
   122:	if_acmpne	135
   125:	aload_0
   126:	getfield	#1; //Field this$0:Lscala/actors/threadpool/LinkedBlockingQueue;
   129:	aload	4
   131:	invokestatic	#16; //Method scala/actors/threadpool/LinkedBlockingQueue.access$402:(Lscala/actors/threadpool/LinkedBlockingQueue;Lscala/actors/threadpool/LinkedBlockingQueue$Node;)Lscala/actors/threadpool/LinkedBlockingQueue$Node;
   134:	pop
   135:	aload_0
   136:	dup
   137:	astore	7
   139:	monitorenter
   140:	aload_0
   141:	getfield	#1; //Field this$0:Lscala/actors/threadpool/LinkedBlockingQueue;
   144:	invokestatic	#17; //Method scala/actors/threadpool/LinkedBlockingQueue.access$510:(Lscala/actors/threadpool/LinkedBlockingQueue;)I
   147:	istore	6
   149:	aload	7
   151:	monitorexit
   152:	goto	163
   155:	astore	8
   157:	aload	7
   159:	monitorexit
   160:	aload	8
   162:	athrow
   163:	iload	6
   165:	aload_0
   166:	getfield	#1; //Field this$0:Lscala/actors/threadpool/LinkedBlockingQueue;
   169:	invokestatic	#18; //Method scala/actors/threadpool/LinkedBlockingQueue.access$600:(Lscala/actors/threadpool/LinkedBlockingQueue;)I
   172:	if_icmpne	185
   175:	aload_0
   176:	getfield	#1; //Field this$0:Lscala/actors/threadpool/LinkedBlockingQueue;
   179:	invokestatic	#3; //Method scala/actors/threadpool/LinkedBlockingQueue.access$100:(Lscala/actors/threadpool/LinkedBlockingQueue;)Ljava/lang/Object;
   182:	invokevirtual	#19; //Method java/lang/Object.notifyAll:()V
   185:	aload_2
   186:	monitorexit
   187:	goto	197
   190:	astore	9
   192:	aload_2
   193:	monitorexit
   194:	aload	9
   196:	athrow
   197:	aload_1
   198:	monitorexit
   199:	goto	209
   202:	astore	10
   204:	aload_1
   205:	monitorexit
   206:	aload	10
   208:	athrow
   209:	return
  Exception table:
   from   to  target type
   140   152   155   any
   155   160   155   any
    35   187   190   any
   190   194   190   any
    25   199   202   any
   202   206   202   any

}

