class scala.actors.threadpool.LinkedBlockingQueue$Node extends java.lang.Object
  InnerClass: 
   #8= #3 of #16; //Node=class scala/actors/threadpool/LinkedBlockingQueue$Node of class scala/actors/threadpool/LinkedBlockingQueue
  minor version: 0
  major version: 49
  Constant pool:
const #1 = Method	#4.#14;	//  java/lang/Object."<init>":()V
const #2 = Field	#3.#15;	//  scala/actors/threadpool/LinkedBlockingQueue$Node.item:Ljava/lang/Object;
const #3 = class	#17;	//  scala/actors/threadpool/LinkedBlockingQueue$Node
const #4 = class	#18;	//  java/lang/Object
const #5 = Asciz	item;
const #6 = Asciz	Ljava/lang/Object;;
const #7 = Asciz	next;
const #8 = Asciz	Node;
const #9 = Asciz	InnerClasses;
const #10 = Asciz	Lscala/actors/threadpool/LinkedBlockingQueue$Node;;
const #11 = Asciz	<init>;
const #12 = Asciz	(Ljava/lang/Object;)V;
const #13 = Asciz	Code;
const #14 = NameAndType	#11:#19;//  "<init>":()V
const #15 = NameAndType	#5:#6;//  item:Ljava/lang/Object;
const #16 = class	#20;	//  scala/actors/threadpool/LinkedBlockingQueue
const #17 = Asciz	scala/actors/threadpool/LinkedBlockingQueue$Node;
const #18 = Asciz	java/lang/Object;
const #19 = Asciz	()V;
const #20 = Asciz	scala/actors/threadpool/LinkedBlockingQueue;

{
volatile java.lang.Object item;

scala.actors.threadpool.LinkedBlockingQueue$Node next;

scala.actors.threadpool.LinkedBlockingQueue$Node(java.lang.Object);
  Code:
   Stack=2, Locals=2, Args_size=2
   0:	aload_0
   1:	invokespecial	#1; //Method java/lang/Object."<init>":()V
   4:	aload_0
   5:	aload_1
   6:	putfield	#2; //Field item:Ljava/lang/Object;
   9:	return

}

