public final class scala.actors.threadpool.Perf extends java.lang.Object
  minor version: 0
  major version: 49
  Constant pool:
const #1 = Field	#6.#20;	//  scala/actors/threadpool/Perf.perf:Lscala/actors/threadpool/Perf;
const #2 = Method	#8.#21;	//  java/lang/Object."<init>":()V
const #3 = Method	#22.#23;	//  java/lang/System.currentTimeMillis:()J
const #4 = long	1000l;
const #6 = class	#24;	//  scala/actors/threadpool/Perf
const #7 = Method	#6.#21;	//  scala/actors/threadpool/Perf."<init>":()V
const #8 = class	#25;	//  java/lang/Object
const #9 = Asciz	perf;
const #10 = Asciz	Lscala/actors/threadpool/Perf;;
const #11 = Asciz	getPerf;
const #12 = Asciz	()Lscala/actors/threadpool/Perf;;
const #13 = Asciz	Code;
const #14 = Asciz	<init>;
const #15 = Asciz	()V;
const #16 = Asciz	highResCounter;
const #17 = Asciz	()J;
const #18 = Asciz	highResFrequency;
const #19 = Asciz	<clinit>;
const #20 = NameAndType	#9:#10;//  perf:Lscala/actors/threadpool/Perf;
const #21 = NameAndType	#14:#15;//  "<init>":()V
const #22 = class	#26;	//  java/lang/System
const #23 = NameAndType	#27:#17;//  currentTimeMillis:()J
const #24 = Asciz	scala/actors/threadpool/Perf;
const #25 = Asciz	java/lang/Object;
const #26 = Asciz	java/lang/System;
const #27 = Asciz	currentTimeMillis;

{
public static scala.actors.threadpool.Perf getPerf();
  Code:
   Stack=1, Locals=0, Args_size=0
   0:	getstatic	#1; //Field perf:Lscala/actors/threadpool/Perf;
   3:	areturn

public long highResCounter();
  Code:
   Stack=2, Locals=1, Args_size=1
   0:	invokestatic	#3; //Method java/lang/System.currentTimeMillis:()J
   3:	lreturn

public long highResFrequency();
  Code:
   Stack=2, Locals=1, Args_size=1
   0:	ldc2_w	#4; //long 1000l
   3:	lreturn

static {};
  Code:
   Stack=2, Locals=0, Args_size=0
   0:	new	#6; //class scala/actors/threadpool/Perf
   3:	dup
   4:	invokespecial	#7; //Method "<init>":()V
   7:	putstatic	#1; //Field perf:Lscala/actors/threadpool/Perf;
   10:	return

}

