public class scala.actors.threadpool.RejectedExecutionException extends java.lang.RuntimeException
  minor version: 0
  major version: 49
  Constant pool:
Method	java/lang/RuntimeException."<init>":()V
Method	java/lang/RuntimeException."<init>":(Ljava/lang/String;)V
Method	java/lang/RuntimeException."<init>":(Ljava/lang/String;Ljava/lang/Throwable;)V
Method	java/lang/RuntimeException."<init>":(Ljava/lang/Throwable;)V
class	scala/actors/threadpool/RejectedExecutionException
class	java/lang/RuntimeException
Asciz	serialVersionUID;
Asciz	J;
Asciz	ConstantValue;
long	-375805702767069545l;
Asciz	<init>;
Asciz	()V;
Asciz	Code;
Asciz	(Ljava/lang/String;)V;
Asciz	(Ljava/lang/String;Ljava/lang/Throwable;)V;
Asciz	(Ljava/lang/Throwable;)V;
NameAndType	"<init>":()V
NameAndType	"<init>":(Ljava/lang/String;)V
NameAndType	"<init>":(Ljava/lang/String;Ljava/lang/Throwable;)V
NameAndType	"<init>":(Ljava/lang/Throwable;)V
Asciz	scala/actors/threadpool/RejectedExecutionException;
Asciz	java/lang/RuntimeException;

{
private static final long serialVersionUID;
  Signature: J
  Constant value: long -375805702767069545l
public scala.actors.threadpool.RejectedExecutionException();
  Signature: ()V
  Code:
   Stack=1, Locals=1, Args_size=1
	aload_0
	invokespecial	Method java/lang/RuntimeException."<init>":()V
	return
  Labels:

public scala.actors.threadpool.RejectedExecutionException(java.lang.String);
  Signature: (Ljava/lang/String;)V
  Code:
   Stack=2, Locals=2, Args_size=2
	aload_0
	aload_1
	invokespecial	Method java/lang/RuntimeException."<init>":(Ljava/lang/String;)V
	return
  Labels:

public scala.actors.threadpool.RejectedExecutionException(java.lang.String, java.lang.Throwable);
  Signature: (Ljava/lang/String;Ljava/lang/Throwable;)V
  Code:
   Stack=3, Locals=3, Args_size=3
	aload_0
	aload_1
	aload_2
	invokespecial	Method java/lang/RuntimeException."<init>":(Ljava/lang/String;Ljava/lang/Throwable;)V
	return
  Labels:

public scala.actors.threadpool.RejectedExecutionException(java.lang.Throwable);
  Signature: (Ljava/lang/Throwable;)V
  Code:
   Stack=2, Locals=2, Args_size=2
	aload_0
	aload_1
	invokespecial	Method java/lang/RuntimeException."<init>":(Ljava/lang/Throwable;)V
	return
  Labels:

}

