final class scala.actors.threadpool.SynchronousQueue$FifoWaitQueue extends scala.actors.threadpool.SynchronousQueue$WaitQueue implements java.io.Serializable
  InnerClass: 
   final #16= #2 of #32; //Node=class scala/actors/threadpool/SynchronousQueue$Node of class scala/actors/threadpool/SynchronousQueue
   final #39= #7 of #32; //FifoWaitQueue=class scala/actors/threadpool/SynchronousQueue$FifoWaitQueue of class scala/actors/threadpool/SynchronousQueue
   abstract #41= #8 of #32; //WaitQueue=class scala/actors/threadpool/SynchronousQueue$WaitQueue of class scala/actors/threadpool/SynchronousQueue
  minor version: 0
  major version: 49
  Constant pool:
const #1 = Method	#8.#31;	//  scala/actors/threadpool/SynchronousQueue$WaitQueue."<init>":()V
const #2 = class	#33;	//  scala/actors/threadpool/SynchronousQueue$Node
const #3 = Method	#2.#34;	//  scala/actors/threadpool/SynchronousQueue$Node."<init>":(Ljava/lang/Object;)V
const #4 = Field	#7.#35;	//  scala/actors/threadpool/SynchronousQueue$FifoWaitQueue.last:Lscala/actors/threadpool/SynchronousQueue$Node;
const #5 = Field	#7.#36;	//  scala/actors/threadpool/SynchronousQueue$FifoWaitQueue.head:Lscala/actors/threadpool/SynchronousQueue$Node;
const #6 = Field	#2.#37;	//  scala/actors/threadpool/SynchronousQueue$Node.next:Lscala/actors/threadpool/SynchronousQueue$Node;
const #7 = class	#38;	//  scala/actors/threadpool/SynchronousQueue$FifoWaitQueue
const #8 = class	#40;	//  scala/actors/threadpool/SynchronousQueue$WaitQueue
const #9 = class	#42;	//  java/io/Serializable
const #10 = Asciz	serialVersionUID;
const #11 = Asciz	J;
const #12 = Asciz	ConstantValue;
const #13 = long	-3623113410248163686l;
const #15 = Asciz	head;
const #16 = Asciz	Node;
const #17 = Asciz	InnerClasses;
const #18 = Asciz	Lscala/actors/threadpool/SynchronousQueue$Node;;
const #19 = Asciz	last;
const #20 = Asciz	<init>;
const #21 = Asciz	()V;
const #22 = Asciz	Code;
const #23 = Asciz	enq;
const #24 = Asciz	(Ljava/lang/Object;)Lscala/actors/threadpool/SynchronousQueue$Node;;
const #25 = Asciz	deq;
const #26 = Asciz	()Lscala/actors/threadpool/SynchronousQueue$Node;;
const #27 = Asciz	shouldUnlink;
const #28 = Asciz	(Lscala/actors/threadpool/SynchronousQueue$Node;)Z;
const #29 = Asciz	unlink;
const #30 = Asciz	(Lscala/actors/threadpool/SynchronousQueue$Node;)V;
const #31 = NameAndType	#20:#21;//  "<init>":()V
const #32 = class	#43;	//  scala/actors/threadpool/SynchronousQueue
const #33 = Asciz	scala/actors/threadpool/SynchronousQueue$Node;
const #34 = NameAndType	#20:#44;//  "<init>":(Ljava/lang/Object;)V
const #35 = NameAndType	#19:#18;//  last:Lscala/actors/threadpool/SynchronousQueue$Node;
const #36 = NameAndType	#15:#18;//  head:Lscala/actors/threadpool/SynchronousQueue$Node;
const #37 = NameAndType	#45:#18;//  next:Lscala/actors/threadpool/SynchronousQueue$Node;
const #38 = Asciz	scala/actors/threadpool/SynchronousQueue$FifoWaitQueue;
const #39 = Asciz	FifoWaitQueue;
const #40 = Asciz	scala/actors/threadpool/SynchronousQueue$WaitQueue;
const #41 = Asciz	WaitQueue;
const #42 = Asciz	java/io/Serializable;
const #43 = Asciz	scala/actors/threadpool/SynchronousQueue;
const #44 = Asciz	(Ljava/lang/Object;)V;
const #45 = Asciz	next;

{
scala.actors.threadpool.SynchronousQueue$FifoWaitQueue();
  Code:
   Stack=1, Locals=1, Args_size=1
   0:	aload_0
   1:	invokespecial	#1; //Method scala/actors/threadpool/SynchronousQueue$WaitQueue."<init>":()V
   4:	return

scala.actors.threadpool.SynchronousQueue$Node enq(java.lang.Object);
  Code:
   Stack=4, Locals=3, Args_size=2
   0:	new	#2; //class scala/actors/threadpool/SynchronousQueue$Node
   3:	dup
   4:	aload_1
   5:	invokespecial	#3; //Method scala/actors/threadpool/SynchronousQueue$Node."<init>":(Ljava/lang/Object;)V
   8:	astore_2
   9:	aload_0
   10:	getfield	#4; //Field last:Lscala/actors/threadpool/SynchronousQueue$Node;
   13:	ifnonnull	29
   16:	aload_0
   17:	aload_0
   18:	aload_2
   19:	dup_x1
   20:	putfield	#5; //Field head:Lscala/actors/threadpool/SynchronousQueue$Node;
   23:	putfield	#4; //Field last:Lscala/actors/threadpool/SynchronousQueue$Node;
   26:	goto	42
   29:	aload_0
   30:	aload_0
   31:	getfield	#4; //Field last:Lscala/actors/threadpool/SynchronousQueue$Node;
   34:	aload_2
   35:	dup_x1
   36:	putfield	#6; //Field scala/actors/threadpool/SynchronousQueue$Node.next:Lscala/actors/threadpool/SynchronousQueue$Node;
   39:	putfield	#4; //Field last:Lscala/actors/threadpool/SynchronousQueue$Node;
   42:	aload_2
   43:	areturn

scala.actors.threadpool.SynchronousQueue$Node deq();
  Code:
   Stack=3, Locals=2, Args_size=1
   0:	aload_0
   1:	getfield	#5; //Field head:Lscala/actors/threadpool/SynchronousQueue$Node;
   4:	astore_1
   5:	aload_1
   6:	ifnull	31
   9:	aload_0
   10:	aload_1
   11:	getfield	#6; //Field scala/actors/threadpool/SynchronousQueue$Node.next:Lscala/actors/threadpool/SynchronousQueue$Node;
   14:	dup_x1
   15:	putfield	#5; //Field head:Lscala/actors/threadpool/SynchronousQueue$Node;
   18:	ifnonnull	26
   21:	aload_0
   22:	aconst_null
   23:	putfield	#4; //Field last:Lscala/actors/threadpool/SynchronousQueue$Node;
   26:	aload_1
   27:	aconst_null
   28:	putfield	#6; //Field scala/actors/threadpool/SynchronousQueue$Node.next:Lscala/actors/threadpool/SynchronousQueue$Node;
   31:	aload_1
   32:	areturn

boolean shouldUnlink(scala.actors.threadpool.SynchronousQueue$Node);
  Code:
   Stack=2, Locals=2, Args_size=2
   0:	aload_1
   1:	aload_0
   2:	getfield	#4; //Field last:Lscala/actors/threadpool/SynchronousQueue$Node;
   5:	if_acmpeq	15
   8:	aload_1
   9:	getfield	#6; //Field scala/actors/threadpool/SynchronousQueue$Node.next:Lscala/actors/threadpool/SynchronousQueue$Node;
   12:	ifnull	19
   15:	iconst_1
   16:	goto	20
   19:	iconst_0
   20:	ireturn

void unlink(scala.actors.threadpool.SynchronousQueue$Node);
  Code:
   Stack=2, Locals=5, Args_size=2
   0:	aload_0
   1:	getfield	#5; //Field head:Lscala/actors/threadpool/SynchronousQueue$Node;
   4:	astore_2
   5:	aconst_null
   6:	astore_3
   7:	aload_2
   8:	ifnull	67
   11:	aload_2
   12:	aload_1
   13:	if_acmpne	57
   16:	aload_2
   17:	getfield	#6; //Field scala/actors/threadpool/SynchronousQueue$Node.next:Lscala/actors/threadpool/SynchronousQueue$Node;
   20:	astore	4
   22:	aload_3
   23:	ifnonnull	35
   26:	aload_0
   27:	aload	4
   29:	putfield	#5; //Field head:Lscala/actors/threadpool/SynchronousQueue$Node;
   32:	goto	41
   35:	aload_3
   36:	aload	4
   38:	putfield	#6; //Field scala/actors/threadpool/SynchronousQueue$Node.next:Lscala/actors/threadpool/SynchronousQueue$Node;
   41:	aload_0
   42:	getfield	#4; //Field last:Lscala/actors/threadpool/SynchronousQueue$Node;
   45:	aload_1
   46:	if_acmpne	67
   49:	aload_0
   50:	aload_3
   51:	putfield	#4; //Field last:Lscala/actors/threadpool/SynchronousQueue$Node;
   54:	goto	67
   57:	aload_2
   58:	astore_3
   59:	aload_2
   60:	getfield	#6; //Field scala/actors/threadpool/SynchronousQueue$Node.next:Lscala/actors/threadpool/SynchronousQueue$Node;
   63:	astore_2
   64:	goto	7
   67:	return

}

