final class scala.actors.threadpool.SynchronousQueue$Node extends java.lang.Object implements java.io.Serializable
  InnerClass: 
   final #33= #16 of #72; //Node=class scala/actors/threadpool/SynchronousQueue$Node of class scala/actors/threadpool/SynchronousQueue
  minor version: 0
  major version: 49
  Constant pool:
const #1 = Method	#17.#54;	//  java/lang/Object."<init>":()V
const #2 = Field	#16.#55;	//  scala/actors/threadpool/SynchronousQueue$Node.state:I
const #3 = Field	#16.#56;	//  scala/actors/threadpool/SynchronousQueue$Node.item:Ljava/lang/Object;
const #4 = Field	#16.#57;	//  scala/actors/threadpool/SynchronousQueue$Node.next:Lscala/actors/threadpool/SynchronousQueue$Node;
const #5 = Method	#17.#58;	//  java/lang/Object.notify:()V
const #6 = Method	#59.#60;	//  java/lang/Thread.currentThread:()Ljava/lang/Thread;
const #7 = Method	#59.#61;	//  java/lang/Thread.interrupt:()V
const #8 = Method	#16.#62;	//  scala/actors/threadpool/SynchronousQueue$Node.extract:()Ljava/lang/Object;
const #9 = Method	#17.#63;	//  java/lang/Object.wait:()V
const #10 = class	#64;	//  java/lang/InterruptedException
const #11 = Method	#16.#65;	//  scala/actors/threadpool/SynchronousQueue$Node.checkCancellationOnInterrupt:(Ljava/lang/InterruptedException;)V
const #12 = Method	#66.#67;	//  scala/actors/threadpool/helpers/Utils.nanoTime:()J
const #13 = Field	#68.#69;	//  scala/actors/threadpool/TimeUnit.NANOSECONDS:Lscala/actors/threadpool/TimeUnit;
const #14 = Method	#68.#70;	//  scala/actors/threadpool/TimeUnit.timedWait:(Ljava/lang/Object;J)V
const #15 = Method	#16.#71;	//  scala/actors/threadpool/SynchronousQueue$Node.attempt:(J)Z
const #16 = class	#73;	//  scala/actors/threadpool/SynchronousQueue$Node
const #17 = class	#74;	//  java/lang/Object
const #18 = class	#75;	//  java/io/Serializable
const #19 = Asciz	serialVersionUID;
const #20 = Asciz	J;
const #21 = Asciz	ConstantValue;
const #22 = long	-3223113410248163686l;
const #24 = Asciz	ACK;
const #25 = Asciz	I;
const #26 = int	1;
const #27 = Asciz	CANCEL;
const #28 = int	-1;
const #29 = Asciz	state;
const #30 = Asciz	item;
const #31 = Asciz	Ljava/lang/Object;;
const #32 = Asciz	next;
const #33 = Asciz	Node;
const #34 = Asciz	InnerClasses;
const #35 = Asciz	Lscala/actors/threadpool/SynchronousQueue$Node;;
const #36 = Asciz	<init>;
const #37 = Asciz	(Ljava/lang/Object;)V;
const #38 = Asciz	Code;
const #39 = Asciz	(Ljava/lang/Object;Lscala/actors/threadpool/SynchronousQueue$Node;)V;
const #40 = Asciz	extract;
const #41 = Asciz	()Ljava/lang/Object;;
const #42 = Asciz	checkCancellationOnInterrupt;
const #43 = Asciz	(Ljava/lang/InterruptedException;)V;
const #44 = Asciz	Exceptions;
const #45 = Asciz	setItem;
const #46 = Asciz	(Ljava/lang/Object;)Z;
const #47 = Asciz	getItem;
const #48 = Asciz	waitForTake;
const #49 = Asciz	()V;
const #50 = Asciz	waitForPut;
const #51 = Asciz	attempt;
const #52 = Asciz	(J)Z;
const #53 = Asciz	(J)Ljava/lang/Object;;
const #54 = NameAndType	#36:#49;//  "<init>":()V
const #55 = NameAndType	#29:#25;//  state:I
const #56 = NameAndType	#30:#31;//  item:Ljava/lang/Object;
const #57 = NameAndType	#32:#35;//  next:Lscala/actors/threadpool/SynchronousQueue$Node;
const #58 = NameAndType	#76:#49;//  notify:()V
const #59 = class	#77;	//  java/lang/Thread
const #60 = NameAndType	#78:#79;//  currentThread:()Ljava/lang/Thread;
const #61 = NameAndType	#80:#49;//  interrupt:()V
const #62 = NameAndType	#40:#41;//  extract:()Ljava/lang/Object;
const #63 = NameAndType	#81:#49;//  wait:()V
const #64 = Asciz	java/lang/InterruptedException;
const #65 = NameAndType	#42:#43;//  checkCancellationOnInterrupt:(Ljava/lang/InterruptedException;)V
const #66 = class	#82;	//  scala/actors/threadpool/helpers/Utils
const #67 = NameAndType	#83:#84;//  nanoTime:()J
const #68 = class	#85;	//  scala/actors/threadpool/TimeUnit
const #69 = NameAndType	#86:#87;//  NANOSECONDS:Lscala/actors/threadpool/TimeUnit;
const #70 = NameAndType	#88:#89;//  timedWait:(Ljava/lang/Object;J)V
const #71 = NameAndType	#51:#52;//  attempt:(J)Z
const #72 = class	#90;	//  scala/actors/threadpool/SynchronousQueue
const #73 = Asciz	scala/actors/threadpool/SynchronousQueue$Node;
const #74 = Asciz	java/lang/Object;
const #75 = Asciz	java/io/Serializable;
const #76 = Asciz	notify;
const #77 = Asciz	java/lang/Thread;
const #78 = Asciz	currentThread;
const #79 = Asciz	()Ljava/lang/Thread;;
const #80 = Asciz	interrupt;
const #81 = Asciz	wait;
const #82 = Asciz	scala/actors/threadpool/helpers/Utils;
const #83 = Asciz	nanoTime;
const #84 = Asciz	()J;
const #85 = Asciz	scala/actors/threadpool/TimeUnit;
const #86 = Asciz	NANOSECONDS;
const #87 = Asciz	Lscala/actors/threadpool/TimeUnit;;
const #88 = Asciz	timedWait;
const #89 = Asciz	(Ljava/lang/Object;J)V;
const #90 = Asciz	scala/actors/threadpool/SynchronousQueue;

{
int state;

java.lang.Object item;

scala.actors.threadpool.SynchronousQueue$Node next;

scala.actors.threadpool.SynchronousQueue$Node(java.lang.Object);
  Code:
   Stack=2, Locals=2, Args_size=2
   0:	aload_0
   1:	invokespecial	#1; //Method java/lang/Object."<init>":()V
   4:	aload_0
   5:	iconst_0
   6:	putfield	#2; //Field state:I
   9:	aload_0
   10:	aload_1
   11:	putfield	#3; //Field item:Ljava/lang/Object;
   14:	return

scala.actors.threadpool.SynchronousQueue$Node(java.lang.Object, scala.actors.threadpool.SynchronousQueue$Node);
  Code:
   Stack=2, Locals=3, Args_size=3
   0:	aload_0
   1:	invokespecial	#1; //Method java/lang/Object."<init>":()V
   4:	aload_0
   5:	iconst_0
   6:	putfield	#2; //Field state:I
   9:	aload_0
   10:	aload_1
   11:	putfield	#3; //Field item:Ljava/lang/Object;
   14:	aload_0
   15:	aload_2
   16:	putfield	#4; //Field next:Lscala/actors/threadpool/SynchronousQueue$Node;
   19:	return

synchronized boolean setItem(java.lang.Object);
  Code:
   Stack=2, Locals=2, Args_size=2
   0:	aload_0
   1:	getfield	#2; //Field state:I
   4:	ifeq	9
   7:	iconst_0
   8:	ireturn
   9:	aload_0
   10:	aload_1
   11:	putfield	#3; //Field item:Ljava/lang/Object;
   14:	aload_0
   15:	iconst_1
   16:	putfield	#2; //Field state:I
   19:	aload_0
   20:	invokevirtual	#5; //Method java/lang/Object.notify:()V
   23:	iconst_1
   24:	ireturn

synchronized java.lang.Object getItem();
  Code:
   Stack=2, Locals=1, Args_size=1
   0:	aload_0
   1:	getfield	#2; //Field state:I
   4:	ifeq	9
   7:	aconst_null
   8:	areturn
   9:	aload_0
   10:	iconst_1
   11:	putfield	#2; //Field state:I
   14:	aload_0
   15:	invokevirtual	#5; //Method java/lang/Object.notify:()V
   18:	aload_0
   19:	invokespecial	#8; //Method extract:()Ljava/lang/Object;
   22:	areturn

synchronized void waitForTake()   throws java.lang.InterruptedException;
  Code:
   Stack=2, Locals=2, Args_size=1
   0:	aload_0
   1:	getfield	#2; //Field state:I
   4:	ifne	14
   7:	aload_0
   8:	invokevirtual	#9; //Method java/lang/Object.wait:()V
   11:	goto	0
   14:	goto	23
   17:	astore_1
   18:	aload_0
   19:	aload_1
   20:	invokespecial	#11; //Method checkCancellationOnInterrupt:(Ljava/lang/InterruptedException;)V
   23:	return
  Exception table:
   from   to  target type
     0    14    17   Class java/lang/InterruptedException

  Exceptions: 
   throws java.lang.InterruptedException
synchronized java.lang.Object waitForPut()   throws java.lang.InterruptedException;
  Code:
   Stack=2, Locals=2, Args_size=1
   0:	aload_0
   1:	getfield	#2; //Field state:I
   4:	ifne	14
   7:	aload_0
   8:	invokevirtual	#9; //Method java/lang/Object.wait:()V
   11:	goto	0
   14:	goto	23
   17:	astore_1
   18:	aload_0
   19:	aload_1
   20:	invokespecial	#11; //Method checkCancellationOnInterrupt:(Ljava/lang/InterruptedException;)V
   23:	aload_0
   24:	invokespecial	#8; //Method extract:()Ljava/lang/Object;
   27:	areturn
  Exception table:
   from   to  target type
     0    14    17   Class java/lang/InterruptedException

  Exceptions: 
   throws java.lang.InterruptedException
synchronized boolean waitForTake(long)   throws java.lang.InterruptedException;
  Code:
   Stack=3, Locals=4, Args_size=2
   0:	aload_0
   1:	lload_1
   2:	invokespecial	#15; //Method attempt:(J)Z
   5:	ifne	10
   8:	iconst_0
   9:	ireturn
   10:	goto	19
   13:	astore_3
   14:	aload_0
   15:	aload_3
   16:	invokespecial	#11; //Method checkCancellationOnInterrupt:(Ljava/lang/InterruptedException;)V
   19:	iconst_1
   20:	ireturn
  Exception table:
   from   to  target type
     0     9    13   Class java/lang/InterruptedException

  Exceptions: 
   throws java.lang.InterruptedException
synchronized java.lang.Object waitForPut(long)   throws java.lang.InterruptedException;
  Code:
   Stack=3, Locals=4, Args_size=2
   0:	aload_0
   1:	lload_1
   2:	invokespecial	#15; //Method attempt:(J)Z
   5:	ifne	10
   8:	aconst_null
   9:	areturn
   10:	goto	19
   13:	astore_3
   14:	aload_0
   15:	aload_3
   16:	invokespecial	#11; //Method checkCancellationOnInterrupt:(Ljava/lang/InterruptedException;)V
   19:	aload_0
   20:	invokespecial	#8; //Method extract:()Ljava/lang/Object;
   23:	areturn
  Exception table:
   from   to  target type
     0     9    13   Class java/lang/InterruptedException

  Exceptions: 
   throws java.lang.InterruptedException
}

