public final class scala.actors.threadpool.ThreadPoolExecutor$Worker extends scala.actors.threadpool.locks.ReentrantLock implements java.lang.Runnable
  InnerClass: 
   public final Worker=class scala/actors/threadpool/ThreadPoolExecutor$Worker of class scala/actors/threadpool/ThreadPoolExecutor
  minor version: 0
  major version: 49
  Constant pool:
Field	scala/actors/threadpool/ThreadPoolExecutor$Worker.this$0:Lscala/actors/threadpool/ThreadPoolExecutor;
Method	scala/actors/threadpool/locks/ReentrantLock."<init>":()V
Field	scala/actors/threadpool/ThreadPoolExecutor$Worker.firstTask:Ljava/lang/Runnable;
Method	scala/actors/threadpool/ThreadPoolExecutor.getThreadFactory:()Lscala/actors/threadpool/ThreadFactory;
InterfaceMethod	scala/actors/threadpool/ThreadFactory.newThread:(Ljava/lang/Runnable;)Ljava/lang/Thread;
Field	scala/actors/threadpool/ThreadPoolExecutor$Worker.thread:Ljava/lang/Thread;
Method	scala/actors/threadpool/ThreadPoolExecutor.runWorker:(Lscala/actors/threadpool/ThreadPoolExecutor$Worker;)V
class	scala/actors/threadpool/ThreadPoolExecutor$Worker
class	scala/actors/threadpool/locks/ReentrantLock
class	java/lang/Runnable
Asciz	serialVersionUID;
Asciz	J;
Asciz	ConstantValue;
long	6138294804551838833l;
Asciz	thread;
Asciz	Ljava/lang/Thread;;
Asciz	firstTask;
Asciz	Ljava/lang/Runnable;;
Asciz	completedTasks;
Asciz	this$0;
Asciz	Lscala/actors/threadpool/ThreadPoolExecutor;;
Asciz	<init>;
Asciz	(Lscala/actors/threadpool/ThreadPoolExecutor;Ljava/lang/Runnable;)V;
Asciz	Code;
Asciz	run;
Asciz	()V;
NameAndType	this$0:Lscala/actors/threadpool/ThreadPoolExecutor;
NameAndType	"<init>":()V
NameAndType	firstTask:Ljava/lang/Runnable;
class	scala/actors/threadpool/ThreadPoolExecutor
NameAndType	getThreadFactory:()Lscala/actors/threadpool/ThreadFactory;
class	scala/actors/threadpool/ThreadFactory
NameAndType	newThread:(Ljava/lang/Runnable;)Ljava/lang/Thread;
NameAndType	thread:Ljava/lang/Thread;
NameAndType	runWorker:(Lscala/actors/threadpool/ThreadPoolExecutor$Worker;)V
Asciz	scala/actors/threadpool/ThreadPoolExecutor$Worker;
Asciz	Worker;
Asciz	InnerClasses;
Asciz	scala/actors/threadpool/locks/ReentrantLock;
Asciz	java/lang/Runnable;
Asciz	scala/actors/threadpool/ThreadPoolExecutor;
Asciz	getThreadFactory;
Asciz	()Lscala/actors/threadpool/ThreadFactory;;
Asciz	scala/actors/threadpool/ThreadFactory;
Asciz	newThread;
Asciz	(Ljava/lang/Runnable;)Ljava/lang/Thread;;
Asciz	runWorker;
Asciz	(Lscala/actors/threadpool/ThreadPoolExecutor$Worker;)V;

{
private static final long serialVersionUID;
  Signature: J
  Constant value: long 6138294804551838833l
public final java.lang.Thread thread;
  Signature: Ljava/lang/Thread;

java.lang.Runnable firstTask;
  Signature: Ljava/lang/Runnable;

volatile long completedTasks;
  Signature: J

final scala.actors.threadpool.ThreadPoolExecutor this$0;
  Signature: Lscala/actors/threadpool/ThreadPoolExecutor;

scala.actors.threadpool.ThreadPoolExecutor$Worker(scala.actors.threadpool.ThreadPoolExecutor, java.lang.Runnable);
  Signature: (Lscala/actors/threadpool/ThreadPoolExecutor;Ljava/lang/Runnable;)V
  Code:
   Stack=3, Locals=3, Args_size=3
	aload_0
	aload_1
	putfield	Field this$0:Lscala/actors/threadpool/ThreadPoolExecutor;
	aload_0
	invokespecial	Method scala/actors/threadpool/locks/ReentrantLock."<init>":()V
	aload_0
	aload_2
	putfield	Field firstTask:Ljava/lang/Runnable;
	aload_0
	aload_1
	invokevirtual	Method scala/actors/threadpool/ThreadPoolExecutor.getThreadFactory:()Lscala/actors/threadpool/ThreadFactory;
	aload_0
	invokeinterface	InterfaceMethod scala/actors/threadpool/ThreadFactory.newThread:(Ljava/lang/Runnable;)Ljava/lang/Thread;
	putfield	Field thread:Ljava/lang/Thread;
	return
  Labels:

public void run();
  Signature: ()V
  Code:
   Stack=2, Locals=1, Args_size=1
	aload_0
	getfield	Field this$0:Lscala/actors/threadpool/ThreadPoolExecutor;
	aload_0
	invokevirtual	Method scala/actors/threadpool/ThreadPoolExecutor.runWorker:(Lscala/actors/threadpool/ThreadPoolExecutor$Worker;)V
	return
  Labels:

}

