public class scala.actors.threadpool.ThreadPoolExecutor$AbortPolicy extends java.lang.Object implements scala.actors.threadpool.RejectedExecutionHandler
  InnerClass: 
   public #16= #4 of #14; //AbortPolicy=class scala/actors/threadpool/ThreadPoolExecutor$AbortPolicy of class scala/actors/threadpool/ThreadPoolExecutor
  minor version: 0
  major version: 49
  Constant pool:
const #1 = Method	#5.#12;	//  java/lang/Object."<init>":()V
const #2 = class	#13;	//  scala/actors/threadpool/RejectedExecutionException
const #3 = Method	#2.#12;	//  scala/actors/threadpool/RejectedExecutionException."<init>":()V
const #4 = class	#15;	//  scala/actors/threadpool/ThreadPoolExecutor$AbortPolicy
const #5 = class	#18;	//  java/lang/Object
const #6 = class	#19;	//  scala/actors/threadpool/RejectedExecutionHandler
const #7 = Asciz	<init>;
const #8 = Asciz	()V;
const #9 = Asciz	Code;
const #10 = Asciz	rejectedExecution;
const #11 = Asciz	(Ljava/lang/Runnable;Lscala/actors/threadpool/ThreadPoolExecutor;)V;
const #12 = NameAndType	#7:#8;//  "<init>":()V
const #13 = Asciz	scala/actors/threadpool/RejectedExecutionException;
const #14 = class	#20;	//  scala/actors/threadpool/ThreadPoolExecutor
const #15 = Asciz	scala/actors/threadpool/ThreadPoolExecutor$AbortPolicy;
const #16 = Asciz	AbortPolicy;
const #17 = Asciz	InnerClasses;
const #18 = Asciz	java/lang/Object;
const #19 = Asciz	scala/actors/threadpool/RejectedExecutionHandler;
const #20 = Asciz	scala/actors/threadpool/ThreadPoolExecutor;

{
public scala.actors.threadpool.ThreadPoolExecutor$AbortPolicy();
  Code:
   Stack=1, Locals=1, Args_size=1
   0:	aload_0
   1:	invokespecial	#1; //Method java/lang/Object."<init>":()V
   4:	return

public void rejectedExecution(java.lang.Runnable, scala.actors.threadpool.ThreadPoolExecutor);
  Code:
   Stack=2, Locals=3, Args_size=3
   0:	new	#2; //class scala/actors/threadpool/RejectedExecutionException
   3:	dup
   4:	invokespecial	#3; //Method scala/actors/threadpool/RejectedExecutionException."<init>":()V
   7:	athrow

}

