public class scala.actors.threadpool.ThreadPoolExecutor extends scala.actors.threadpool.AbstractExecutorService
  InnerClass: 
   public DiscardOldestPolicy=class scala/actors/threadpool/ThreadPoolExecutor$DiscardOldestPolicy of class scala/actors/threadpool/ThreadPoolExecutor
   public DiscardPolicy=class scala/actors/threadpool/ThreadPoolExecutor$DiscardPolicy of class scala/actors/threadpool/ThreadPoolExecutor
   public AbortPolicy=class scala/actors/threadpool/ThreadPoolExecutor$AbortPolicy of class scala/actors/threadpool/ThreadPoolExecutor
   public CallerRunsPolicy=class scala/actors/threadpool/ThreadPoolExecutor$CallerRunsPolicy of class scala/actors/threadpool/ThreadPoolExecutor
   public final Worker=class scala/actors/threadpool/ThreadPoolExecutor$Worker of class scala/actors/threadpool/ThreadPoolExecutor
  minor version: 0
  major version: 49
  Constant pool:
int	-536870912;
int	536870911;
Field	scala/actors/threadpool/ThreadPoolExecutor.ctl:Lscala/actors/threadpool/AtomicInteger;
Method	scala/actors/threadpool/AtomicInteger.compareAndSet:(II)Z
Method	scala/actors/threadpool/AtomicInteger.get:()I
Method	scala/actors/threadpool/ThreadPoolExecutor.compareAndDecrementWorkerCount:(I)Z
Method	scala/actors/threadpool/ThreadPoolExecutor.runStateAtLeast:(II)Z
Method	scala/actors/threadpool/ThreadPoolExecutor.workerCountOf:(I)I
Method	scala/actors/threadpool/ThreadPoolExecutor.ctlOf:(II)I
Method	scala/actors/threadpool/ThreadPoolExecutor.isRunning:(I)Z
int	1073741824;
Method	scala/actors/threadpool/ThreadPoolExecutor.runStateOf:(I)I
Field	scala/actors/threadpool/ThreadPoolExecutor.workQueue:Lscala/actors/threadpool/BlockingQueue;
InterfaceMethod	scala/actors/threadpool/BlockingQueue.isEmpty:()Z
Method	scala/actors/threadpool/ThreadPoolExecutor.interruptIdleWorkers:(Z)V
Field	scala/actors/threadpool/ThreadPoolExecutor.mainLock:Lscala/actors/threadpool/locks/ReentrantLock;
Method	scala/actors/threadpool/locks/ReentrantLock.lock:()V
Method	scala/actors/threadpool/ThreadPoolExecutor.terminated:()V
int	1610612736;
Method	scala/actors/threadpool/AtomicInteger.set:(I)V
Field	scala/actors/threadpool/ThreadPoolExecutor.termination:Lscala/actors/threadpool/locks/Condition;
InterfaceMethod	scala/actors/threadpool/locks/Condition.signalAll:()V
Method	scala/actors/threadpool/locks/ReentrantLock.unlock:()V
Method	java/lang/System.getSecurityManager:()Ljava/lang/SecurityManager;
Field	scala/actors/threadpool/ThreadPoolExecutor.shutdownPerm:Ljava/lang/RuntimePermission;
Method	java/lang/SecurityManager.checkPermission:(Ljava/security/Permission;)V
Field	scala/actors/threadpool/ThreadPoolExecutor.workers:Ljava/util/HashSet;
Method	java/util/HashSet.iterator:()Ljava/util/Iterator;
InterfaceMethod	java/util/Iterator.hasNext:()Z
InterfaceMethod	java/util/Iterator.next:()Ljava/lang/Object;
class	scala/actors/threadpool/ThreadPoolExecutor$Worker
Field	scala/actors/threadpool/ThreadPoolExecutor$Worker.thread:Ljava/lang/Thread;
Method	java/lang/SecurityManager.checkAccess:(Ljava/lang/Thread;)V
Method	java/lang/Thread.interrupt:()V
class	java/lang/SecurityException
Method	java/lang/Thread.isInterrupted:()Z
Method	scala/actors/threadpool/ThreadPoolExecutor$Worker.tryLock:()Z
Method	scala/actors/threadpool/ThreadPoolExecutor$Worker.unlock:()V
int	536870912;
Method	scala/actors/threadpool/ThreadPoolExecutor.runStateLessThan:(II)Z
Method	java/lang/Thread.interrupted:()Z
Method	java/lang/Thread.currentThread:()Ljava/lang/Thread;
Field	scala/actors/threadpool/ThreadPoolExecutor.handler:Lscala/actors/threadpool/RejectedExecutionHandler;
InterfaceMethod	scala/actors/threadpool/RejectedExecutionHandler.rejectedExecution:(Ljava/lang/Runnable;Lscala/actors/threadpool/ThreadPoolExecutor;)V
class	java/util/ArrayList
Method	java/util/ArrayList."<init>":()V
InterfaceMethod	scala/actors/threadpool/BlockingQueue.drainTo:(Ljava/util/Collection;)I
class	java/lang/Runnable
InterfaceMethod	scala/actors/threadpool/BlockingQueue.toArray:([Ljava/lang/Object;)[Ljava/lang/Object;
class	"[Ljava/lang/Runnable;"
InterfaceMethod	scala/actors/threadpool/BlockingQueue.remove:(Ljava/lang/Object;)Z
InterfaceMethod	java/util/List.add:(Ljava/lang/Object;)Z
Field	scala/actors/threadpool/ThreadPoolExecutor.corePoolSize:I
Field	scala/actors/threadpool/ThreadPoolExecutor.maximumPoolSize:I
Method	scala/actors/threadpool/ThreadPoolExecutor.compareAndIncrementWorkerCount:(I)Z
Method	scala/actors/threadpool/ThreadPoolExecutor$Worker."<init>":(Lscala/actors/threadpool/ThreadPoolExecutor;Ljava/lang/Runnable;)V
Method	scala/actors/threadpool/ThreadPoolExecutor.decrementWorkerCount:()V
Method	scala/actors/threadpool/ThreadPoolExecutor.tryTerminate:()V
Method	java/util/HashSet.add:(Ljava/lang/Object;)Z
Method	java/util/HashSet.size:()I
Field	scala/actors/threadpool/ThreadPoolExecutor.largestPoolSize:I
Method	java/lang/Thread.start:()V
Field	scala/actors/threadpool/ThreadPoolExecutor.completedTaskCount:J
Field	scala/actors/threadpool/ThreadPoolExecutor$Worker.completedTasks:J
Method	java/util/HashSet.remove:(Ljava/lang/Object;)Z
Field	scala/actors/threadpool/ThreadPoolExecutor.allowCoreThreadTimeOut:Z
Method	scala/actors/threadpool/ThreadPoolExecutor.addWorker:(Ljava/lang/Runnable;Z)Z
Field	scala/actors/threadpool/ThreadPoolExecutor.keepAliveTime:J
Field	scala/actors/threadpool/TimeUnit.NANOSECONDS:Lscala/actors/threadpool/TimeUnit;
InterfaceMethod	scala/actors/threadpool/BlockingQueue.poll:(JLscala/actors/threadpool/TimeUnit;)Ljava/lang/Object;
InterfaceMethod	scala/actors/threadpool/BlockingQueue.take:()Ljava/lang/Object;
class	java/lang/InterruptedException
Field	scala/actors/threadpool/ThreadPoolExecutor$Worker.firstTask:Ljava/lang/Runnable;
Method	scala/actors/threadpool/ThreadPoolExecutor.getTask:()Ljava/lang/Runnable;
Method	scala/actors/threadpool/ThreadPoolExecutor$Worker.lock:()V
Method	scala/actors/threadpool/ThreadPoolExecutor.clearInterruptsForTaskRun:()V
Method	scala/actors/threadpool/ThreadPoolExecutor.beforeExecute:(Ljava/lang/Thread;Ljava/lang/Runnable;)V
InterfaceMethod	java/lang/Runnable.run:()V
Method	scala/actors/threadpool/ThreadPoolExecutor.afterExecute:(Ljava/lang/Runnable;Ljava/lang/Throwable;)V
class	java/lang/RuntimeException
class	java/lang/Error
class	java/lang/Throwable
Method	java/lang/Error."<init>":(Ljava/lang/Throwable;)V
Method	scala/actors/threadpool/ThreadPoolExecutor.processWorkerExit:(Lscala/actors/threadpool/ThreadPoolExecutor$Worker;Z)V
Method	scala/actors/threadpool/Executors.defaultThreadFactory:()Lscala/actors/threadpool/ThreadFactory;
Field	scala/actors/threadpool/ThreadPoolExecutor.defaultHandler:Lscala/actors/threadpool/RejectedExecutionHandler;
Method	scala/actors/threadpool/ThreadPoolExecutor."<init>":(IIJLscala/actors/threadpool/TimeUnit;Lscala/actors/threadpool/BlockingQueue;Lscala/actors/threadpool/ThreadFactory;Lscala/actors/threadpool/RejectedExecutionHandler;)V
Method	scala/actors/threadpool/AbstractExecutorService."<init>":()V
class	scala/actors/threadpool/AtomicInteger
Method	scala/actors/threadpool/AtomicInteger."<init>":(I)V
class	scala/actors/threadpool/locks/ReentrantLock
Method	scala/actors/threadpool/locks/ReentrantLock."<init>":()V
class	java/util/HashSet
Method	java/util/HashSet."<init>":()V
Method	scala/actors/threadpool/locks/ReentrantLock.newCondition:()Lscala/actors/threadpool/locks/Condition;
class	java/lang/IllegalArgumentException
Method	java/lang/IllegalArgumentException."<init>":()V
class	java/lang/NullPointerException
Method	java/lang/NullPointerException."<init>":()V
Method	scala/actors/threadpool/TimeUnit.toNanos:(J)J
Field	scala/actors/threadpool/ThreadPoolExecutor.threadFactory:Lscala/actors/threadpool/ThreadFactory;
InterfaceMethod	scala/actors/threadpool/BlockingQueue.offer:(Ljava/lang/Object;)Z
Method	scala/actors/threadpool/ThreadPoolExecutor.remove:(Ljava/lang/Runnable;)Z
Method	scala/actors/threadpool/ThreadPoolExecutor.reject:(Ljava/lang/Runnable;)V
Method	scala/actors/threadpool/ThreadPoolExecutor.checkShutdownAccess:()V
Method	scala/actors/threadpool/ThreadPoolExecutor.advanceRunState:(I)V
Method	scala/actors/threadpool/ThreadPoolExecutor.interruptIdleWorkers:()V
Method	scala/actors/threadpool/ThreadPoolExecutor.onShutdown:()V
Method	scala/actors/threadpool/ThreadPoolExecutor.interruptWorkers:()V
Method	scala/actors/threadpool/ThreadPoolExecutor.drainQueue:()Ljava/util/List;
Method	scala/actors/threadpool/helpers/Utils.nanoTime:()J
InterfaceMethod	scala/actors/threadpool/locks/Condition.await:(JLscala/actors/threadpool/TimeUnit;)Z
Method	scala/actors/threadpool/ThreadPoolExecutor.shutdown:()V
InterfaceMethod	scala/actors/threadpool/BlockingQueue.size:()I
Method	java/lang/Math.min:(II)I
String	Core threads must have nonzero keep alive times
Method	java/lang/IllegalArgumentException."<init>":(Ljava/lang/String;)V
Method	scala/actors/threadpool/ThreadPoolExecutor.allowsCoreThreadTimeOut:()Z
Method	scala/actors/threadpool/TimeUnit.convert:(JLscala/actors/threadpool/TimeUnit;)J
InterfaceMethod	scala/actors/threadpool/BlockingQueue.iterator:()Ljava/util/Iterator;
class	scala/actors/threadpool/Future
InterfaceMethod	scala/actors/threadpool/Future.isCancelled:()Z
InterfaceMethod	java/util/Iterator.remove:()V
class	java/util/ConcurrentModificationException
InterfaceMethod	scala/actors/threadpool/BlockingQueue.toArray:()[Ljava/lang/Object;
Method	scala/actors/threadpool/ThreadPoolExecutor$Worker.isLocked:()Z
class	scala/actors/threadpool/ThreadPoolExecutor$AbortPolicy
Method	scala/actors/threadpool/ThreadPoolExecutor$AbortPolicy."<init>":()V
class	java/lang/RuntimePermission
String	modifyThread
Method	java/lang/RuntimePermission."<init>":(Ljava/lang/String;)V
class	scala/actors/threadpool/ThreadPoolExecutor
class	scala/actors/threadpool/AbstractExecutorService
class	scala/actors/threadpool/ThreadPoolExecutor$DiscardOldestPolicy
Asciz	DiscardOldestPolicy;
Asciz	InnerClasses;
class	scala/actors/threadpool/ThreadPoolExecutor$DiscardPolicy
Asciz	DiscardPolicy;
Asciz	AbortPolicy;
class	scala/actors/threadpool/ThreadPoolExecutor$CallerRunsPolicy
Asciz	CallerRunsPolicy;
Asciz	Worker;
Asciz	ctl;
Asciz	Lscala/actors/threadpool/AtomicInteger;;
Asciz	COUNT_BITS;
Asciz	I;
Asciz	ConstantValue;
int	29;
Asciz	CAPACITY;
Asciz	RUNNING;
Asciz	SHUTDOWN;
int	0;
Asciz	STOP;
Asciz	TIDYING;
Asciz	TERMINATED;
Asciz	workQueue;
Asciz	Lscala/actors/threadpool/BlockingQueue;;
Asciz	mainLock;
Asciz	Lscala/actors/threadpool/locks/ReentrantLock;;
Asciz	workers;
Asciz	Ljava/util/HashSet;;
Asciz	termination;
Asciz	Lscala/actors/threadpool/locks/Condition;;
Asciz	largestPoolSize;
Asciz	completedTaskCount;
Asciz	J;
Asciz	threadFactory;
Asciz	Lscala/actors/threadpool/ThreadFactory;;
Asciz	handler;
Asciz	Lscala/actors/threadpool/RejectedExecutionHandler;;
Asciz	keepAliveTime;
Asciz	allowCoreThreadTimeOut;
Asciz	Z;
Asciz	corePoolSize;
Asciz	maximumPoolSize;
Asciz	defaultHandler;
Asciz	shutdownPerm;
Asciz	Ljava/lang/RuntimePermission;;
Asciz	ONLY_ONE;
int	1;
Asciz	runStateOf;
Asciz	(I)I;
Asciz	Code;
Asciz	workerCountOf;
Asciz	ctlOf;
Asciz	(II)I;
Asciz	runStateLessThan;
Asciz	(II)Z;
Asciz	runStateAtLeast;
Asciz	isRunning;
Asciz	(I)Z;
Asciz	compareAndIncrementWorkerCount;
Asciz	compareAndDecrementWorkerCount;
Asciz	decrementWorkerCount;
Asciz	()V;
Asciz	advanceRunState;
Asciz	(I)V;
Asciz	tryTerminate;
Asciz	checkShutdownAccess;
Asciz	interruptWorkers;
Asciz	interruptIdleWorkers;
Asciz	(Z)V;
Asciz	clearInterruptsForTaskRun;
Asciz	reject;
Asciz	(Ljava/lang/Runnable;)V;
Asciz	onShutdown;
Asciz	isRunningOrShutdown;
Asciz	(Z)Z;
Asciz	drainQueue;
Asciz	()Ljava/util/List;;
Asciz	addWorker;
Asciz	(Ljava/lang/Runnable;Z)Z;
Asciz	processWorkerExit;
Asciz	(Lscala/actors/threadpool/ThreadPoolExecutor$Worker;Z)V;
Asciz	getTask;
Asciz	()Ljava/lang/Runnable;;
Asciz	runWorker;
Asciz	(Lscala/actors/threadpool/ThreadPoolExecutor$Worker;)V;
Asciz	<init>;
Asciz	(IIJLscala/actors/threadpool/TimeUnit;Lscala/actors/threadpool/BlockingQueue;)V;
Asciz	(IIJLscala/actors/threadpool/TimeUnit;Lscala/actors/threadpool/BlockingQueue;Lscala/actors/threadpool/ThreadFactory;)V;
Asciz	(IIJLscala/actors/threadpool/TimeUnit;Lscala/actors/threadpool/BlockingQueue;Lscala/actors/threadpool/RejectedExecutionHandler;)V;
Asciz	(IIJLscala/actors/threadpool/TimeUnit;Lscala/actors/threadpool/BlockingQueue;Lscala/actors/threadpool/ThreadFactory;Lscala/actors/threadpool/RejectedExecutionHandler;)V;
Asciz	execute;
Asciz	shutdown;
Asciz	shutdownNow;
Asciz	isShutdown;
Asciz	()Z;
Asciz	isTerminating;
Asciz	isTerminated;
Asciz	awaitTermination;
Asciz	(JLscala/actors/threadpool/TimeUnit;)Z;
Asciz	Exceptions;
Asciz	finalize;
Asciz	setThreadFactory;
Asciz	(Lscala/actors/threadpool/ThreadFactory;)V;
Asciz	getThreadFactory;
Asciz	()Lscala/actors/threadpool/ThreadFactory;;
Asciz	setRejectedExecutionHandler;
Asciz	(Lscala/actors/threadpool/RejectedExecutionHandler;)V;
Asciz	getRejectedExecutionHandler;
Asciz	()Lscala/actors/threadpool/RejectedExecutionHandler;;
Asciz	setCorePoolSize;
Asciz	getCorePoolSize;
Asciz	()I;
Asciz	prestartCoreThread;
Asciz	prestartAllCoreThreads;
Asciz	allowsCoreThreadTimeOut;
Asciz	setMaximumPoolSize;
Asciz	getMaximumPoolSize;
Asciz	setKeepAliveTime;
Asciz	(JLscala/actors/threadpool/TimeUnit;)V;
Asciz	getKeepAliveTime;
Asciz	(Lscala/actors/threadpool/TimeUnit;)J;
Asciz	getQueue;
Asciz	()Lscala/actors/threadpool/BlockingQueue;;
Asciz	remove;
Asciz	(Ljava/lang/Runnable;)Z;
Asciz	purge;
Asciz	getPoolSize;
Asciz	getActiveCount;
Asciz	getLargestPoolSize;
Asciz	getTaskCount;
Asciz	()J;
Asciz	getCompletedTaskCount;
Asciz	beforeExecute;
Asciz	(Ljava/lang/Thread;Ljava/lang/Runnable;)V;
Asciz	afterExecute;
Asciz	(Ljava/lang/Runnable;Ljava/lang/Throwable;)V;
Asciz	terminated;
Asciz	<clinit>;
NameAndType	ctl:Lscala/actors/threadpool/AtomicInteger;
NameAndType	compareAndSet:(II)Z
NameAndType	get:()I
NameAndType	compareAndDecrementWorkerCount:(I)Z
NameAndType	runStateAtLeast:(II)Z
NameAndType	workerCountOf:(I)I
NameAndType	ctlOf:(II)I
NameAndType	isRunning:(I)Z
NameAndType	runStateOf:(I)I
NameAndType	workQueue:Lscala/actors/threadpool/BlockingQueue;
class	scala/actors/threadpool/BlockingQueue
NameAndType	isEmpty:()Z
NameAndType	interruptIdleWorkers:(Z)V
NameAndType	mainLock:Lscala/actors/threadpool/locks/ReentrantLock;
NameAndType	lock:()V
NameAndType	terminated:()V
NameAndType	set:(I)V
NameAndType	termination:Lscala/actors/threadpool/locks/Condition;
class	scala/actors/threadpool/locks/Condition
NameAndType	signalAll:()V
NameAndType	unlock:()V
class	java/lang/System
NameAndType	getSecurityManager:()Ljava/lang/SecurityManager;
NameAndType	shutdownPerm:Ljava/lang/RuntimePermission;
class	java/lang/SecurityManager
NameAndType	checkPermission:(Ljava/security/Permission;)V
NameAndType	workers:Ljava/util/HashSet;
NameAndType	iterator:()Ljava/util/Iterator;
class	java/util/Iterator
NameAndType	hasNext:()Z
NameAndType	next:()Ljava/lang/Object;
Asciz	scala/actors/threadpool/ThreadPoolExecutor$Worker;
NameAndType	thread:Ljava/lang/Thread;
NameAndType	checkAccess:(Ljava/lang/Thread;)V
class	java/lang/Thread
NameAndType	interrupt:()V
Asciz	java/lang/SecurityException;
NameAndType	isInterrupted:()Z
NameAndType	tryLock:()Z
NameAndType	runStateLessThan:(II)Z
NameAndType	interrupted:()Z
NameAndType	currentThread:()Ljava/lang/Thread;
NameAndType	handler:Lscala/actors/threadpool/RejectedExecutionHandler;
class	scala/actors/threadpool/RejectedExecutionHandler
NameAndType	rejectedExecution:(Ljava/lang/Runnable;Lscala/actors/threadpool/ThreadPoolExecutor;)V
Asciz	java/util/ArrayList;
NameAndType	"<init>":()V
NameAndType	drainTo:(Ljava/util/Collection;)I
Asciz	java/lang/Runnable;
NameAndType	toArray:([Ljava/lang/Object;)[Ljava/lang/Object;
Asciz	[Ljava/lang/Runnable;;
NameAndType	remove:(Ljava/lang/Object;)Z
class	java/util/List
NameAndType	add:(Ljava/lang/Object;)Z
NameAndType	corePoolSize:I
NameAndType	maximumPoolSize:I
NameAndType	compareAndIncrementWorkerCount:(I)Z
NameAndType	"<init>":(Lscala/actors/threadpool/ThreadPoolExecutor;Ljava/lang/Runnable;)V
NameAndType	decrementWorkerCount:()V
NameAndType	tryTerminate:()V
NameAndType	size:()I
NameAndType	largestPoolSize:I
NameAndType	start:()V
NameAndType	completedTaskCount:J
NameAndType	completedTasks:J
NameAndType	allowCoreThreadTimeOut:Z
NameAndType	addWorker:(Ljava/lang/Runnable;Z)Z
NameAndType	keepAliveTime:J
class	scala/actors/threadpool/TimeUnit
NameAndType	NANOSECONDS:Lscala/actors/threadpool/TimeUnit;
NameAndType	poll:(JLscala/actors/threadpool/TimeUnit;)Ljava/lang/Object;
NameAndType	take:()Ljava/lang/Object;
Asciz	java/lang/InterruptedException;
NameAndType	firstTask:Ljava/lang/Runnable;
NameAndType	getTask:()Ljava/lang/Runnable;
NameAndType	clearInterruptsForTaskRun:()V
NameAndType	beforeExecute:(Ljava/lang/Thread;Ljava/lang/Runnable;)V
NameAndType	run:()V
NameAndType	afterExecute:(Ljava/lang/Runnable;Ljava/lang/Throwable;)V
Asciz	java/lang/RuntimeException;
Asciz	java/lang/Error;
Asciz	java/lang/Throwable;
NameAndType	"<init>":(Ljava/lang/Throwable;)V
NameAndType	processWorkerExit:(Lscala/actors/threadpool/ThreadPoolExecutor$Worker;Z)V
class	scala/actors/threadpool/Executors
NameAndType	defaultThreadFactory:()Lscala/actors/threadpool/ThreadFactory;
NameAndType	defaultHandler:Lscala/actors/threadpool/RejectedExecutionHandler;
NameAndType	"<init>":(IIJLscala/actors/threadpool/TimeUnit;Lscala/actors/threadpool/BlockingQueue;Lscala/actors/threadpool/ThreadFactory;Lscala/actors/threadpool/RejectedExecutionHandler;)V
Asciz	scala/actors/threadpool/AtomicInteger;
NameAndType	"<init>":(I)V
Asciz	scala/actors/threadpool/locks/ReentrantLock;
Asciz	java/util/HashSet;
NameAndType	newCondition:()Lscala/actors/threadpool/locks/Condition;
Asciz	java/lang/IllegalArgumentException;
Asciz	java/lang/NullPointerException;
NameAndType	toNanos:(J)J
NameAndType	threadFactory:Lscala/actors/threadpool/ThreadFactory;
NameAndType	offer:(Ljava/lang/Object;)Z
NameAndType	remove:(Ljava/lang/Runnable;)Z
NameAndType	reject:(Ljava/lang/Runnable;)V
NameAndType	checkShutdownAccess:()V
NameAndType	advanceRunState:(I)V
NameAndType	interruptIdleWorkers:()V
NameAndType	onShutdown:()V
NameAndType	interruptWorkers:()V
NameAndType	drainQueue:()Ljava/util/List;
class	scala/actors/threadpool/helpers/Utils
NameAndType	nanoTime:()J
NameAndType	await:(JLscala/actors/threadpool/TimeUnit;)Z
NameAndType	shutdown:()V
class	java/lang/Math
NameAndType	min:(II)I
Asciz	Core threads must have nonzero keep alive times;
NameAndType	"<init>":(Ljava/lang/String;)V
NameAndType	allowsCoreThreadTimeOut:()Z
NameAndType	convert:(JLscala/actors/threadpool/TimeUnit;)J
Asciz	scala/actors/threadpool/Future;
NameAndType	isCancelled:()Z
NameAndType	remove:()V
Asciz	java/util/ConcurrentModificationException;
NameAndType	toArray:()[Ljava/lang/Object;
NameAndType	isLocked:()Z
Asciz	scala/actors/threadpool/ThreadPoolExecutor$AbortPolicy;
Asciz	java/lang/RuntimePermission;
Asciz	modifyThread;
Asciz	scala/actors/threadpool/ThreadPoolExecutor;
Asciz	scala/actors/threadpool/AbstractExecutorService;
Asciz	scala/actors/threadpool/ThreadPoolExecutor$DiscardOldestPolicy;
Asciz	scala/actors/threadpool/ThreadPoolExecutor$DiscardPolicy;
Asciz	scala/actors/threadpool/ThreadPoolExecutor$CallerRunsPolicy;
Asciz	compareAndSet;
Asciz	get;
Asciz	scala/actors/threadpool/BlockingQueue;
Asciz	isEmpty;
Asciz	lock;
Asciz	set;
Asciz	scala/actors/threadpool/locks/Condition;
Asciz	signalAll;
Asciz	unlock;
Asciz	java/lang/System;
Asciz	getSecurityManager;
Asciz	()Ljava/lang/SecurityManager;;
Asciz	java/lang/SecurityManager;
Asciz	checkPermission;
Asciz	(Ljava/security/Permission;)V;
Asciz	iterator;
Asciz	()Ljava/util/Iterator;;
Asciz	java/util/Iterator;
Asciz	hasNext;
Asciz	next;
Asciz	()Ljava/lang/Object;;
Asciz	thread;
Asciz	Ljava/lang/Thread;;
Asciz	checkAccess;
Asciz	(Ljava/lang/Thread;)V;
Asciz	java/lang/Thread;
Asciz	interrupt;
Asciz	isInterrupted;
Asciz	tryLock;
Asciz	interrupted;
Asciz	currentThread;
Asciz	()Ljava/lang/Thread;;
Asciz	scala/actors/threadpool/RejectedExecutionHandler;
Asciz	rejectedExecution;
Asciz	(Ljava/lang/Runnable;Lscala/actors/threadpool/ThreadPoolExecutor;)V;
Asciz	drainTo;
Asciz	(Ljava/util/Collection;)I;
Asciz	toArray;
Asciz	([Ljava/lang/Object;)[Ljava/lang/Object;;
Asciz	(Ljava/lang/Object;)Z;
Asciz	java/util/List;
Asciz	add;
Asciz	(Lscala/actors/threadpool/ThreadPoolExecutor;Ljava/lang/Runnable;)V;
Asciz	size;
Asciz	start;
Asciz	completedTasks;
Asciz	scala/actors/threadpool/TimeUnit;
Asciz	NANOSECONDS;
Asciz	Lscala/actors/threadpool/TimeUnit;;
Asciz	poll;
Asciz	(JLscala/actors/threadpool/TimeUnit;)Ljava/lang/Object;;
Asciz	take;
Asciz	firstTask;
Asciz	Ljava/lang/Runnable;;
Asciz	run;
Asciz	(Ljava/lang/Throwable;)V;
Asciz	scala/actors/threadpool/Executors;
Asciz	defaultThreadFactory;
Asciz	newCondition;
Asciz	()Lscala/actors/threadpool/locks/Condition;;
Asciz	toNanos;
Asciz	(J)J;
Asciz	offer;
Asciz	scala/actors/threadpool/helpers/Utils;
Asciz	nanoTime;
Asciz	await;
Asciz	java/lang/Math;
Asciz	min;
Asciz	(Ljava/lang/String;)V;
Asciz	convert;
Asciz	(JLscala/actors/threadpool/TimeUnit;)J;
Asciz	isCancelled;
Asciz	()[Ljava/lang/Object;;
Asciz	isLocked;

{
private final scala.actors.threadpool.AtomicInteger ctl;
  Signature: Lscala/actors/threadpool/AtomicInteger;

private static final int COUNT_BITS;
  Signature: I
  Constant value: int 29
private static final int CAPACITY;
  Signature: I
  Constant value: int 536870911
private static final int RUNNING;
  Signature: I
  Constant value: int -536870912
private static final int SHUTDOWN;
  Signature: I
  Constant value: int 0
private static final int STOP;
  Signature: I
  Constant value: int 536870912
private static final int TIDYING;
  Signature: I
  Constant value: int 1073741824
private static final int TERMINATED;
  Signature: I
  Constant value: int 1610612736
private final scala.actors.threadpool.BlockingQueue workQueue;
  Signature: Lscala/actors/threadpool/BlockingQueue;

public final scala.actors.threadpool.locks.ReentrantLock mainLock;
  Signature: Lscala/actors/threadpool/locks/ReentrantLock;

public final java.util.HashSet workers;
  Signature: Ljava/util/HashSet;

private final scala.actors.threadpool.locks.Condition termination;
  Signature: Lscala/actors/threadpool/locks/Condition;

private int largestPoolSize;
  Signature: I

private long completedTaskCount;
  Signature: J

private volatile scala.actors.threadpool.ThreadFactory threadFactory;
  Signature: Lscala/actors/threadpool/ThreadFactory;

private volatile scala.actors.threadpool.RejectedExecutionHandler handler;
  Signature: Lscala/actors/threadpool/RejectedExecutionHandler;

private volatile long keepAliveTime;
  Signature: J

private volatile boolean allowCoreThreadTimeOut;
  Signature: Z

private volatile int corePoolSize;
  Signature: I

private volatile int maximumPoolSize;
  Signature: I

private static final scala.actors.threadpool.RejectedExecutionHandler defaultHandler;
  Signature: Lscala/actors/threadpool/RejectedExecutionHandler;

private static final java.lang.RuntimePermission shutdownPerm;
  Signature: Ljava/lang/RuntimePermission;

private static final boolean ONLY_ONE;
  Signature: Z
  Constant value: int 1
private static int runStateOf(int);
  Signature: (I)I
  Code:
   Stack=2, Locals=1, Args_size=1
	iload_0
	ldc	int -536870912
	iand
	ireturn
  Labels:

private static int workerCountOf(int);
  Signature: (I)I
  Code:
   Stack=2, Locals=1, Args_size=1
	iload_0
	ldc	int 536870911
	iand
	ireturn
  Labels:

private static int ctlOf(int, int);
  Signature: (II)I
  Code:
   Stack=2, Locals=2, Args_size=2
	iload_0
	iload_1
	ior
	ireturn
  Labels:

private static boolean runStateLessThan(int, int);
  Signature: (II)Z
  Code:
   Stack=2, Locals=2, Args_size=2
	iload_0
	iload_1
	if_icmpge	l1 // iconst_0
	iconst_1
	goto	l2 // ireturn
l1	iconst_0
l2	ireturn
  Labels:
   	l1 = 9 // iconst_0
   	l2 = 10 // ireturn

private static boolean runStateAtLeast(int, int);
  Signature: (II)Z
  Code:
   Stack=2, Locals=2, Args_size=2
	iload_0
	iload_1
	if_icmplt	l1 // iconst_0
	iconst_1
	goto	l2 // ireturn
l1	iconst_0
l2	ireturn
  Labels:
   	l1 = 9 // iconst_0
   	l2 = 10 // ireturn

private static boolean isRunning(int);
  Signature: (I)Z
  Code:
   Stack=1, Locals=1, Args_size=1
	iload_0
	ifge	l1 // iconst_0
	iconst_1
	goto	l2 // ireturn
l1	iconst_0
l2	ireturn
  Labels:
   	l1 = 8 // iconst_0
   	l2 = 9 // ireturn

private boolean compareAndIncrementWorkerCount(int);
  Signature: (I)Z
  Code:
   Stack=4, Locals=2, Args_size=2
	aload_0
	getfield	Field ctl:Lscala/actors/threadpool/AtomicInteger;
	iload_1
	iload_1
	iconst_1
	iadd
	invokevirtual	Method scala/actors/threadpool/AtomicInteger.compareAndSet:(II)Z
	ireturn
  Labels:

private boolean compareAndDecrementWorkerCount(int);
  Signature: (I)Z
  Code:
   Stack=4, Locals=2, Args_size=2
	aload_0
	getfield	Field ctl:Lscala/actors/threadpool/AtomicInteger;
	iload_1
	iload_1
	iconst_1
	isub
	invokevirtual	Method scala/actors/threadpool/AtomicInteger.compareAndSet:(II)Z
	ireturn
  Labels:

private void decrementWorkerCount();
  Signature: ()V
  Code:
   Stack=2, Locals=1, Args_size=1
l1	aload_0
	aload_0
	getfield	Field ctl:Lscala/actors/threadpool/AtomicInteger;
	invokevirtual	Method scala/actors/threadpool/AtomicInteger.get:()I
	invokespecial	Method compareAndDecrementWorkerCount:(I)Z
	ifeq	l1 // aload_0
	return
  Labels:
   	l1 = 0 // aload_0

private void advanceRunState(int);
  Signature: (I)V
  Code:
   Stack=4, Locals=3, Args_size=2
l3	aload_0
	getfield	Field ctl:Lscala/actors/threadpool/AtomicInteger;
	invokevirtual	Method scala/actors/threadpool/AtomicInteger.get:()I
	istore_2
	iload_2
	iload_1
	invokestatic	Method runStateAtLeast:(II)Z
	ifne	l1 // return
	aload_0
	getfield	Field ctl:Lscala/actors/threadpool/AtomicInteger;
	iload_2
	iload_1
	iload_2
	invokestatic	Method workerCountOf:(I)I
	invokestatic	Method ctlOf:(II)I
	invokevirtual	Method scala/actors/threadpool/AtomicInteger.compareAndSet:(II)Z
	ifeq	l2 // goto
	goto	l1 // return
l2	goto	l3 // aload_0
l1	return
  Labels:
   	l3 = 0 // aload_0
   	l2 = 38 // goto
   	l1 = 41 // return

final void tryTerminate();
  Signature: ()V
  Code:
   Stack=4, Locals=5, Args_size=1
l7	aload_0
	getfield	Field ctl:Lscala/actors/threadpool/AtomicInteger;
	invokevirtual	Method scala/actors/threadpool/AtomicInteger.get:()I
	istore_1
	iload_1
	invokestatic	Method isRunning:(I)Z
	ifne	l1 // return
	iload_1
	ldc	int 1073741824
	invokestatic	Method runStateAtLeast:(II)Z
	ifne	l1 // return
	iload_1
	invokestatic	Method runStateOf:(I)I
	ifne	l2 // iload_1
	aload_0
	getfield	Field workQueue:Lscala/actors/threadpool/BlockingQueue;
	invokeinterface	InterfaceMethod scala/actors/threadpool/BlockingQueue.isEmpty:()Z
	ifne	l2 // iload_1
l1	return
l2	iload_1
	invokestatic	Method workerCountOf:(I)I
	ifeq	l3 // aload_0
	aload_0
	iconst_1
	invokespecial	Method interruptIdleWorkers:(Z)V
	return
l3	aload_0
	getfield	Field mainLock:Lscala/actors/threadpool/locks/ReentrantLock;
	astore_2
	aload_2
	invokevirtual	Method scala/actors/threadpool/locks/ReentrantLock.lock:()V
	aload_0
	getfield	Field ctl:Lscala/actors/threadpool/AtomicInteger;
	iload_1
	ldc	int 1073741824
	iconst_0
	invokestatic	Method ctlOf:(II)I
	invokevirtual	Method scala/actors/threadpool/AtomicInteger.compareAndSet:(II)Z
	ifeq	l4 // aload_2
	aload_0
	invokevirtual	Method terminated:()V
	aload_0
	getfield	Field ctl:Lscala/actors/threadpool/AtomicInteger;
	ldc	int 1610612736
	iconst_0
	invokestatic	Method ctlOf:(II)I
	invokevirtual	Method scala/actors/threadpool/AtomicInteger.set:(I)V
	aload_0
	getfield	Field termination:Lscala/actors/threadpool/locks/Condition;
	invokeinterface	InterfaceMethod scala/actors/threadpool/locks/Condition.signalAll:()V
	goto	l5 // aload_2
	astore_3
	aload_0
	getfield	Field ctl:Lscala/actors/threadpool/AtomicInteger;
	ldc	int 1610612736
	iconst_0
	invokestatic	Method ctlOf:(II)I
	invokevirtual	Method scala/actors/threadpool/AtomicInteger.set:(I)V
	aload_0
	getfield	Field termination:Lscala/actors/threadpool/locks/Condition;
	invokeinterface	InterfaceMethod scala/actors/threadpool/locks/Condition.signalAll:()V
	aload_3
	athrow
l5	aload_2
	invokevirtual	Method scala/actors/threadpool/locks/ReentrantLock.unlock:()V
	return
l4	aload_2
	invokevirtual	Method scala/actors/threadpool/locks/ReentrantLock.unlock:()V
	goto	l6 // goto
	astore	4
	aload_2
	invokevirtual	Method scala/actors/threadpool/locks/ReentrantLock.unlock:()V
	aload	4
	athrow
l6	goto	l7 // aload_0
  Labels:
   	l7 = 0 // aload_0
   	l1 = 43 // return
   	l2 = 44 // iload_1
   	l3 = 57 // aload_0
   	l5 = 137 // aload_2
   	l4 = 142 // aload_2
   	l6 = 158 // goto
  Exception table:
   from   to  target type
    83    87   112   any
   112   113   112   any
    66   137   149   any
   149   151   149   any

private void checkShutdownAccess();
  Signature: ()V
  Code:
   Stack=2, Locals=6, Args_size=1
	invokestatic	Method java/lang/System.getSecurityManager:()Ljava/lang/SecurityManager;
	astore_1
	aload_1
	ifnull	l1 // return
	aload_1
	getstatic	Field shutdownPerm:Ljava/lang/RuntimePermission;
	invokevirtual	Method java/lang/SecurityManager.checkPermission:(Ljava/security/Permission;)V
	aload_0
	getfield	Field mainLock:Lscala/actors/threadpool/locks/ReentrantLock;
	astore_2
	aload_2
	invokevirtual	Method scala/actors/threadpool/locks/ReentrantLock.lock:()V
	aload_0
	getfield	Field workers:Ljava/util/HashSet;
	invokevirtual	Method java/util/HashSet.iterator:()Ljava/util/Iterator;
	astore_3
l3	aload_3
	invokeinterface	InterfaceMethod java/util/Iterator.hasNext:()Z
	ifeq	l2 // aload_2
	aload_3
	invokeinterface	InterfaceMethod java/util/Iterator.next:()Ljava/lang/Object;
	checkcast	class scala/actors/threadpool/ThreadPoolExecutor$Worker
	astore	4
	aload_1
	aload	4
	getfield	Field scala/actors/threadpool/ThreadPoolExecutor$Worker.thread:Ljava/lang/Thread;
	invokevirtual	Method java/lang/SecurityManager.checkAccess:(Ljava/lang/Thread;)V
	goto	l3 // aload_3
l2	aload_2
	invokevirtual	Method scala/actors/threadpool/locks/ReentrantLock.unlock:()V
	goto	l1 // return
	astore	5
	aload_2
	invokevirtual	Method scala/actors/threadpool/locks/ReentrantLock.unlock:()V
	aload	5
	athrow
l1	return
  Labels:
   	l3 = 32 // aload_3
   	l2 = 64 // aload_2
   	l1 = 80 // return
  Exception table:
   from   to  target type
    24    64    71   any
    71    73    71   any

private void interruptWorkers();
  Signature: ()V
  Code:
   Stack=1, Locals=6, Args_size=1
	aload_0
	getfield	Field mainLock:Lscala/actors/threadpool/locks/ReentrantLock;
	astore_1
	aload_1
	invokevirtual	Method scala/actors/threadpool/locks/ReentrantLock.lock:()V
	aload_0
	getfield	Field workers:Ljava/util/HashSet;
	invokevirtual	Method java/util/HashSet.iterator:()Ljava/util/Iterator;
	astore_2
l3	aload_2
	invokeinterface	InterfaceMethod java/util/Iterator.hasNext:()Z
	ifeq	l1 // aload_1
	aload_2
	invokeinterface	InterfaceMethod java/util/Iterator.next:()Ljava/lang/Object;
	checkcast	class scala/actors/threadpool/ThreadPoolExecutor$Worker
	astore_3
	aload_3
	getfield	Field scala/actors/threadpool/ThreadPoolExecutor$Worker.thread:Ljava/lang/Thread;
	invokevirtual	Method java/lang/Thread.interrupt:()V
	goto	l2 // goto
	astore	4
l2	goto	l3 // aload_2
l1	aload_1
	invokevirtual	Method scala/actors/threadpool/locks/ReentrantLock.unlock:()V
	goto	l4 // return
	astore	5
	aload_1
	invokevirtual	Method scala/actors/threadpool/locks/ReentrantLock.unlock:()V
	aload	5
	athrow
l4	return
  Labels:
   	l3 = 17 // aload_2
   	l2 = 48 // goto
   	l1 = 51 // aload_1
   	l4 = 67 // return
  Exception table:
   from   to  target type
    36    43    46   Class java/lang/SecurityException

     9    51    58   any
    58    60    58   any

private void interruptIdleWorkers(boolean);
  Signature: (Z)V
  Code:
   Stack=1, Locals=9, Args_size=2
	aload_0
	getfield	Field mainLock:Lscala/actors/threadpool/locks/ReentrantLock;
	astore_2
	aload_2
	invokevirtual	Method scala/actors/threadpool/locks/ReentrantLock.lock:()V
	aload_0
	getfield	Field workers:Ljava/util/HashSet;
	invokevirtual	Method java/util/HashSet.iterator:()Ljava/util/Iterator;
	astore_3
l4	aload_3
	invokeinterface	InterfaceMethod java/util/Iterator.hasNext:()Z
	ifeq	l1 // aload_2
	aload_3
	invokeinterface	InterfaceMethod java/util/Iterator.next:()Ljava/lang/Object;
	checkcast	class scala/actors/threadpool/ThreadPoolExecutor$Worker
	astore	4
	aload	4
	getfield	Field scala/actors/threadpool/ThreadPoolExecutor$Worker.thread:Ljava/lang/Thread;
	astore	5
	aload	5
	invokevirtual	Method java/lang/Thread.isInterrupted:()Z
	ifne	l2 // iload_1
	aload	4
	invokevirtual	Method scala/actors/threadpool/ThreadPoolExecutor$Worker.tryLock:()Z
	ifeq	l2 // iload_1
	aload	5
	invokevirtual	Method java/lang/Thread.interrupt:()V
	aload	4
	invokevirtual	Method scala/actors/threadpool/ThreadPoolExecutor$Worker.unlock:()V
	goto	l2 // iload_1
	astore	6
	aload	4
	invokevirtual	Method scala/actors/threadpool/ThreadPoolExecutor$Worker.unlock:()V
	goto	l2 // iload_1
	astore	7
	aload	4
	invokevirtual	Method scala/actors/threadpool/ThreadPoolExecutor$Worker.unlock:()V
	aload	7
	athrow
l2	iload_1
	ifeq	l3 // goto
	goto	l1 // aload_2
l3	goto	l4 // aload_3
l1	aload_2
	invokevirtual	Method scala/actors/threadpool/locks/ReentrantLock.unlock:()V
	goto	l5 // return
	astore	8
	aload_2
	invokevirtual	Method scala/actors/threadpool/locks/ReentrantLock.unlock:()V
	aload	8
	athrow
l5	return
  Labels:
   	l4 = 17 // aload_3
   	l2 = 93 // iload_1
   	l3 = 100 // goto
   	l1 = 103 // aload_2
   	l5 = 119 // return
  Exception table:
   from   to  target type
    60    65    73   Class java/lang/SecurityException

    60    65    83   any
    73    75    83   any
    83    85    83   any
     9   103   110   any
   110   112   110   any

private void interruptIdleWorkers();
  Signature: ()V
  Code:
   Stack=2, Locals=1, Args_size=1
	aload_0
	iconst_0
	invokespecial	Method interruptIdleWorkers:(Z)V
	return
  Labels:

private void clearInterruptsForTaskRun();
  Signature: ()V
  Code:
   Stack=2, Locals=1, Args_size=1
	aload_0
	getfield	Field ctl:Lscala/actors/threadpool/AtomicInteger;
	invokevirtual	Method scala/actors/threadpool/AtomicInteger.get:()I
	ldc	int 536870912
	invokestatic	Method runStateLessThan:(II)Z
	ifeq	l1 // return
	invokestatic	Method java/lang/Thread.interrupted:()Z
	ifeq	l1 // return
	aload_0
	getfield	Field ctl:Lscala/actors/threadpool/AtomicInteger;
	invokevirtual	Method scala/actors/threadpool/AtomicInteger.get:()I
	ldc	int 536870912
	invokestatic	Method runStateAtLeast:(II)Z
	ifeq	l1 // return
	invokestatic	Method java/lang/Thread.currentThread:()Ljava/lang/Thread;
	invokevirtual	Method java/lang/Thread.interrupt:()V
l1	return
  Labels:
   	l1 = 42 // return

final void reject(java.lang.Runnable);
  Signature: (Ljava/lang/Runnable;)V
  Code:
   Stack=3, Locals=2, Args_size=2
	aload_0
	getfield	Field handler:Lscala/actors/threadpool/RejectedExecutionHandler;
	aload_1
	aload_0
	invokeinterface	InterfaceMethod scala/actors/threadpool/RejectedExecutionHandler.rejectedExecution:(Ljava/lang/Runnable;Lscala/actors/threadpool/ThreadPoolExecutor;)V
	return
  Labels:

void onShutdown();
  Signature: ()V
  Code:
   Stack=0, Locals=1, Args_size=1
	return
  Labels:

final boolean isRunningOrShutdown(boolean);
  Signature: (Z)Z
  Code:
   Stack=2, Locals=3, Args_size=2
	aload_0
	getfield	Field ctl:Lscala/actors/threadpool/AtomicInteger;
	invokevirtual	Method scala/actors/threadpool/AtomicInteger.get:()I
	invokestatic	Method runStateOf:(I)I
	istore_2
	iload_2
	ldc	int -536870912
	if_icmpeq	l1 // iconst_1
	iload_2
	ifne	l2 // iconst_0
	iload_1
	ifeq	l2 // iconst_0
l1	iconst_1
	goto	l3 // ireturn
l2	iconst_0
l3	ireturn
  Labels:
   	l1 = 25 // iconst_1
   	l2 = 29 // iconst_0
   	l3 = 30 // ireturn

private java.util.List drainQueue();
  Signature: ()Ljava/util/List;
  Code:
   Stack=2, Locals=6, Args_size=1
	aload_0
	getfield	Field workQueue:Lscala/actors/threadpool/BlockingQueue;
	astore_1
	new	class java/util/ArrayList
	dup
	invokespecial	Method java/util/ArrayList."<init>":()V
	astore_2
	aload_1
	aload_2
	invokeinterface	InterfaceMethod scala/actors/threadpool/BlockingQueue.drainTo:(Ljava/util/Collection;)I
	pop
	aload_1
	invokeinterface	InterfaceMethod scala/actors/threadpool/BlockingQueue.isEmpty:()Z
	ifne	l1 // aload_2
	aload_1
	iconst_0
	anewarray	class java/lang/Runnable
	invokeinterface	InterfaceMethod scala/actors/threadpool/BlockingQueue.toArray:([Ljava/lang/Object;)[Ljava/lang/Object;
	checkcast	class "[Ljava/lang/Runnable;"
	checkcast	class "[Ljava/lang/Runnable;"
	astore_3
	iconst_0
	istore	4
l3	iload	4
	aload_3
	arraylength
	if_icmpge	l1 // aload_2
	aload_3
	iload	4
	aaload
	astore	5
	aload_1
	aload	5
	invokeinterface	InterfaceMethod scala/actors/threadpool/BlockingQueue.remove:(Ljava/lang/Object;)Z
	ifeq	l2 // iinc
	aload_2
	aload	5
	invokeinterface	InterfaceMethod java/util/List.add:(Ljava/lang/Object;)Z
	pop
l2	iinc	4, 1
	goto	l3 // iload
l1	aload_2
	areturn
  Labels:
   	l3 = 50 // iload
   	l2 = 83 // iinc
   	l1 = 89 // aload_2

private boolean addWorker(java.lang.Runnable, boolean);
  Signature: (Ljava/lang/Runnable;Z)Z
  Code:
   Stack=4, Locals=10, Args_size=3
l10	aload_0
	getfield	Field ctl:Lscala/actors/threadpool/AtomicInteger;
	invokevirtual	Method scala/actors/threadpool/AtomicInteger.get:()I
	istore_3
	iload_3
	invokestatic	Method runStateOf:(I)I
	istore	4
	iload	4
	iflt	l1 // iload_3
	iload	4
	ifne	l2 // iconst_0
	aload_1
	ifnonnull	l2 // iconst_0
	aload_0
	getfield	Field workQueue:Lscala/actors/threadpool/BlockingQueue;
	invokeinterface	InterfaceMethod scala/actors/threadpool/BlockingQueue.isEmpty:()Z
	ifeq	l1 // iload_3
l2	iconst_0
	ireturn
l1	iload_3
	invokestatic	Method workerCountOf:(I)I
	istore	5
	iload	5
	ldc	int 536870911
	if_icmpge	l3 // iconst_0
	iload	5
	iload_2
	ifeq	l4 // aload_0
	aload_0
	getfield	Field corePoolSize:I
	goto	l5 // if_icmplt
l4	aload_0
	getfield	Field maximumPoolSize:I
l5	if_icmplt	l6 // aload_0
l3	iconst_0
	ireturn
l6	aload_0
	iload_3
	invokespecial	Method compareAndIncrementWorkerCount:(I)Z
	ifeq	l7 // aload_0
	goto	l8 // new
l7	aload_0
	getfield	Field ctl:Lscala/actors/threadpool/AtomicInteger;
	invokevirtual	Method scala/actors/threadpool/AtomicInteger.get:()I
	istore_3
	iload_3
	invokestatic	Method runStateOf:(I)I
	iload	4
	if_icmpeq	l9 // goto
	goto	l10 // aload_0
l9	goto	l1 // iload_3
l8	new	class scala/actors/threadpool/ThreadPoolExecutor$Worker
	dup
	aload_0
	aload_1
	invokespecial	Method scala/actors/threadpool/ThreadPoolExecutor$Worker."<init>":(Lscala/actors/threadpool/ThreadPoolExecutor;Ljava/lang/Runnable;)V
	astore_3
	aload_3
	getfield	Field scala/actors/threadpool/ThreadPoolExecutor$Worker.thread:Ljava/lang/Thread;
	astore	4
	aload_0
	getfield	Field mainLock:Lscala/actors/threadpool/locks/ReentrantLock;
	astore	5
	aload	5
	invokevirtual	Method scala/actors/threadpool/locks/ReentrantLock.lock:()V
	aload_0
	getfield	Field ctl:Lscala/actors/threadpool/AtomicInteger;
	invokevirtual	Method scala/actors/threadpool/AtomicInteger.get:()I
	istore	6
	iload	6
	invokestatic	Method runStateOf:(I)I
	istore	7
	aload	4
	ifnull	l11 // aload_0
	iload	7
	iflt	l12 // aload_0
	iload	7
	ifne	l11 // aload_0
	aload_1
	ifnull	l12 // aload_0
l11	aload_0
	invokespecial	Method decrementWorkerCount:()V
	aload_0
	invokevirtual	Method tryTerminate:()V
	iconst_0
	istore	8
	aload	5
	invokevirtual	Method scala/actors/threadpool/locks/ReentrantLock.unlock:()V
	iload	8
	ireturn
l12	aload_0
	getfield	Field workers:Ljava/util/HashSet;
	aload_3
	invokevirtual	Method java/util/HashSet.add:(Ljava/lang/Object;)Z
	pop
	aload_0
	getfield	Field workers:Ljava/util/HashSet;
	invokevirtual	Method java/util/HashSet.size:()I
	istore	8
	iload	8
	aload_0
	getfield	Field largestPoolSize:I
	if_icmple	l13 // aload
	aload_0
	iload	8
	putfield	Field largestPoolSize:I
l13	aload	5
	invokevirtual	Method scala/actors/threadpool/locks/ReentrantLock.unlock:()V
	goto	l14 // aload
	astore	9
	aload	5
	invokevirtual	Method scala/actors/threadpool/locks/ReentrantLock.unlock:()V
	aload	9
	athrow
l14	aload	4
	invokevirtual	Method java/lang/Thread.start:()V
	aload_0
	getfield	Field ctl:Lscala/actors/threadpool/AtomicInteger;
	invokevirtual	Method scala/actors/threadpool/AtomicInteger.get:()I
	invokestatic	Method runStateOf:(I)I
	ldc	int 536870912
	if_icmpne	l15 // iconst_1
	aload	4
	invokevirtual	Method java/lang/Thread.isInterrupted:()Z
	ifne	l15 // iconst_1
	aload	4
	invokevirtual	Method java/lang/Thread.interrupt:()V
l15	iconst_1
	ireturn
  Labels:
   	l10 = 0 // aload_0
   	l2 = 40 // iconst_0
   	l1 = 42 // iload_3
   	l4 = 68 // aload_0
   	l5 = 72 // if_icmplt
   	l3 = 75 // iconst_0
   	l6 = 77 // aload_0
   	l7 = 88 // aload_0
   	l9 = 108 // goto
   	l8 = 111 // new
   	l11 = 173 // aload_0
   	l12 = 192 // aload_0
   	l13 = 225 // aload
   	l14 = 243 // aload
   	l15 = 276 // iconst_1
  Exception table:
   from   to  target type
   138   184   233   any
   192   225   233   any
   233   235   233   any

private void processWorkerExit(scala.actors.threadpool.ThreadPoolExecutor$Worker, boolean);
  Signature: (Lscala/actors/threadpool/ThreadPoolExecutor$Worker;Z)V
  Code:
   Stack=5, Locals=6, Args_size=3
	iload_2
	ifeq	l1 // aload_0
	aload_0
	invokespecial	Method decrementWorkerCount:()V
l1	aload_0
	getfield	Field mainLock:Lscala/actors/threadpool/locks/ReentrantLock;
	astore_3
	aload_3
	invokevirtual	Method scala/actors/threadpool/locks/ReentrantLock.lock:()V
	aload_0
	dup
	getfield	Field completedTaskCount:J
	aload_1
	getfield	Field scala/actors/threadpool/ThreadPoolExecutor$Worker.completedTasks:J
	ladd
	putfield	Field completedTaskCount:J
	aload_0
	getfield	Field workers:Ljava/util/HashSet;
	aload_1
	invokevirtual	Method java/util/HashSet.remove:(Ljava/lang/Object;)Z
	pop
	aload_3
	invokevirtual	Method scala/actors/threadpool/locks/ReentrantLock.unlock:()V
	goto	l2 // aload_0
	astore	4
	aload_3
	invokevirtual	Method scala/actors/threadpool/locks/ReentrantLock.unlock:()V
	aload	4
	athrow
l2	aload_0
	invokevirtual	Method tryTerminate:()V
	aload_0
	getfield	Field ctl:Lscala/actors/threadpool/AtomicInteger;
	invokevirtual	Method scala/actors/threadpool/AtomicInteger.get:()I
	istore	4
	iload	4
	ldc	int 536870912
	invokestatic	Method runStateLessThan:(II)Z
	ifeq	l3 // return
	iload_2
	ifne	l4 // aload_0
	aload_0
	getfield	Field allowCoreThreadTimeOut:Z
	ifeq	l5 // aload_0
	iconst_0
	goto	l6 // istore
l5	aload_0
	getfield	Field corePoolSize:I
l6	istore	5
	iload	5
	ifne	l7 // iload
	aload_0
	getfield	Field workQueue:Lscala/actors/threadpool/BlockingQueue;
	invokeinterface	InterfaceMethod scala/actors/threadpool/BlockingQueue.isEmpty:()Z
	ifne	l7 // iload
	iconst_1
	istore	5
l7	iload	4
	invokestatic	Method workerCountOf:(I)I
	iload	5
	if_icmplt	l4 // aload_0
	return
l4	aload_0
	aconst_null
	iconst_0
	invokespecial	Method addWorker:(Ljava/lang/Runnable;Z)Z
	pop
l3	return
  Labels:
   	l1 = 8 // aload_0
   	l2 = 55 // aload_0
   	l5 = 93 // aload_0
   	l6 = 97 // istore
   	l7 = 119 // iload
   	l4 = 130 // aload_0
   	l3 = 137 // return
  Exception table:
   from   to  target type
    17    39    46   any
    46    48    46   any

private java.lang.Runnable getTask();
  Signature: ()Ljava/lang/Runnable;
  Code:
   Stack=4, Locals=6, Args_size=1
	iconst_0
	istore_1
l10	aload_0
	getfield	Field ctl:Lscala/actors/threadpool/AtomicInteger;
	invokevirtual	Method scala/actors/threadpool/AtomicInteger.get:()I
	istore_2
	iload_2
	invokestatic	Method runStateOf:(I)I
	istore_3
	iload_3
	iflt	l1 // iload_2
	iload_3
	ldc	int 536870912
	if_icmpge	l2 // aload_0
	aload_0
	getfield	Field workQueue:Lscala/actors/threadpool/BlockingQueue;
	invokeinterface	InterfaceMethod scala/actors/threadpool/BlockingQueue.isEmpty:()Z
	ifeq	l1 // iload_2
l2	aload_0
	invokespecial	Method decrementWorkerCount:()V
	aconst_null
	areturn
l1	iload_2
	invokestatic	Method workerCountOf:(I)I
	istore	5
	aload_0
	getfield	Field allowCoreThreadTimeOut:Z
	ifne	l3 // iconst_1
	iload	5
	aload_0
	getfield	Field corePoolSize:I
	if_icmple	l4 // iconst_0
l3	iconst_1
	goto	l5 // istore
l4	iconst_0
l5	istore	4
	iload	5
	aload_0
	getfield	Field maximumPoolSize:I
	if_icmpgt	l6 // aload_0
	iload_1
	ifeq	l7 // iload
	iload	4
	ifne	l6 // aload_0
	goto	l7 // iload
l6	aload_0
	iload_2
	invokespecial	Method compareAndDecrementWorkerCount:(I)Z
	ifeq	l8 // aload_0
	aconst_null
	areturn
l8	aload_0
	getfield	Field ctl:Lscala/actors/threadpool/AtomicInteger;
	invokevirtual	Method scala/actors/threadpool/AtomicInteger.get:()I
	istore_2
	iload_2
	invokestatic	Method runStateOf:(I)I
	iload_3
	if_icmpeq	l9 // goto
	goto	l10 // aload_0
l9	goto	l1 // iload_2
l7	iload	4
	ifeq	l11 // aload_0
	aload_0
	getfield	Field workQueue:Lscala/actors/threadpool/BlockingQueue;
	aload_0
	getfield	Field keepAliveTime:J
	getstatic	Field scala/actors/threadpool/TimeUnit.NANOSECONDS:Lscala/actors/threadpool/TimeUnit;
	invokeinterface	InterfaceMethod scala/actors/threadpool/BlockingQueue.poll:(JLscala/actors/threadpool/TimeUnit;)Ljava/lang/Object;
	checkcast	class java/lang/Runnable
	goto	l12 // astore
l11	aload_0
	getfield	Field workQueue:Lscala/actors/threadpool/BlockingQueue;
	invokeinterface	InterfaceMethod scala/actors/threadpool/BlockingQueue.take:()Ljava/lang/Object;
	checkcast	class java/lang/Runnable
l12	astore	5
	aload	5
	ifnull	l13 // iconst_1
	aload	5
	areturn
l13	iconst_1
	istore_1
	goto	l14 // goto
	astore	5
	iconst_0
	istore_1
l14	goto	l10 // aload_0
  Labels:
   	l10 = 2 // aload_0
   	l2 = 37 // aload_0
   	l1 = 43 // iload_2
   	l3 = 65 // iconst_1
   	l4 = 69 // iconst_0
   	l5 = 70 // istore
   	l6 = 93 // aload_0
   	l8 = 103 // aload_0
   	l9 = 122 // goto
   	l7 = 125 // iload
   	l11 = 152 // aload_0
   	l12 = 164 // astore
   	l13 = 174 // iconst_1
   	l14 = 183 // goto
  Exception table:
   from   to  target type
   125   173   179   Class java/lang/InterruptedException

   174   176   179   Class java/lang/InterruptedException


final void runWorker(scala.actors.threadpool.ThreadPoolExecutor$Worker);
  Signature: (Lscala/actors/threadpool/ThreadPoolExecutor$Worker;)V
  Code:
   Stack=5, Locals=9, Args_size=2
	aload_1
	getfield	Field scala/actors/threadpool/ThreadPoolExecutor$Worker.firstTask:Ljava/lang/Runnable;
	astore_2
	aload_1
	aconst_null
	putfield	Field scala/actors/threadpool/ThreadPoolExecutor$Worker.firstTask:Ljava/lang/Runnable;
	iconst_1
	istore_3
l5	aload_2
	ifnonnull	l1 // aload_1
	aload_0
	invokespecial	Method getTask:()Ljava/lang/Runnable;
	dup
	astore_2
	ifnull	l2 // iconst_0
l1	aload_1
	invokevirtual	Method scala/actors/threadpool/ThreadPoolExecutor$Worker.lock:()V
	aload_0
	invokespecial	Method clearInterruptsForTaskRun:()V
	aload_0
	aload_1
	getfield	Field scala/actors/threadpool/ThreadPoolExecutor$Worker.thread:Ljava/lang/Thread;
	aload_2
	invokevirtual	Method beforeExecute:(Ljava/lang/Thread;Ljava/lang/Runnable;)V
	aconst_null
	astore	4
	aload_2
	invokeinterface	InterfaceMethod java/lang/Runnable.run:()V
	aload_0
	aload_2
	aload	4
	invokevirtual	Method afterExecute:(Ljava/lang/Runnable;Ljava/lang/Throwable;)V
	goto	l3 // aconst_null
	astore	5
	aload	5
	astore	4
	aload	5
	athrow
	astore	5
	aload	5
	astore	4
	aload	5
	athrow
	astore	5
	aload	5
	astore	4
	new	class java/lang/Error
	dup
	aload	5
	invokespecial	Method java/lang/Error."<init>":(Ljava/lang/Throwable;)V
	athrow
	astore	6
	aload_0
	aload_2
	aload	4
	invokevirtual	Method afterExecute:(Ljava/lang/Runnable;Ljava/lang/Throwable;)V
	aload	6
	athrow
l3	aconst_null
	astore_2
	aload_1
	dup
	getfield	Field scala/actors/threadpool/ThreadPoolExecutor$Worker.completedTasks:J
	lconst_1
	ladd
	putfield	Field scala/actors/threadpool/ThreadPoolExecutor$Worker.completedTasks:J
	aload_1
	invokevirtual	Method scala/actors/threadpool/ThreadPoolExecutor$Worker.unlock:()V
	goto	l4 // goto
	astore	7
	aconst_null
	astore_2
	aload_1
	dup
	getfield	Field scala/actors/threadpool/ThreadPoolExecutor$Worker.completedTasks:J
	lconst_1
	ladd
	putfield	Field scala/actors/threadpool/ThreadPoolExecutor$Worker.completedTasks:J
	aload_1
	invokevirtual	Method scala/actors/threadpool/ThreadPoolExecutor$Worker.unlock:()V
	aload	7
	athrow
l4	goto	l5 // aload_2
l2	iconst_0
	istore_3
	aload_0
	aload_1
	iload_3
	invokespecial	Method processWorkerExit:(Lscala/actors/threadpool/ThreadPoolExecutor$Worker;Z)V
	goto	l6 // return
	astore	8
	aload_0
	aload_1
	iload_3
	invokespecial	Method processWorkerExit:(Lscala/actors/threadpool/ThreadPoolExecutor$Worker;Z)V
	aload	8
	athrow
l6	return
  Labels:
   	l5 = 12 // aload_2
   	l1 = 25 // aload_1
   	l3 = 107 // aconst_null
   	l4 = 147 // goto
   	l2 = 150 // iconst_0
   	l6 = 172 // return
  Exception table:
   from   to  target type
    45    51    61   Class java/lang/RuntimeException

    45    51    70   Class java/lang/Error

    45    51    79   Class java/lang/Throwable

    45    51    95   any
    61    97    95   any
    33   107   126   any
   126   128   126   any
    12   152   161   any
   161   163   161   any

public scala.actors.threadpool.ThreadPoolExecutor(int, int, long, scala.actors.threadpool.TimeUnit, scala.actors.threadpool.BlockingQueue);
  Signature: (IIJLscala/actors/threadpool/TimeUnit;Lscala/actors/threadpool/BlockingQueue;)V
  Code:
   Stack=9, Locals=7, Args_size=6
	aload_0
	iload_1
	iload_2
	lload_3
	aload	5
	aload	6
	invokestatic	Method scala/actors/threadpool/Executors.defaultThreadFactory:()Lscala/actors/threadpool/ThreadFactory;
	getstatic	Field defaultHandler:Lscala/actors/threadpool/RejectedExecutionHandler;
	invokespecial	Method "<init>":(IIJLscala/actors/threadpool/TimeUnit;Lscala/actors/threadpool/BlockingQueue;Lscala/actors/threadpool/ThreadFactory;Lscala/actors/threadpool/RejectedExecutionHandler;)V
	return
  Labels:

public scala.actors.threadpool.ThreadPoolExecutor(int, int, long, scala.actors.threadpool.TimeUnit, scala.actors.threadpool.BlockingQueue, scala.actors.threadpool.ThreadFactory);
  Signature: (IIJLscala/actors/threadpool/TimeUnit;Lscala/actors/threadpool/BlockingQueue;Lscala/actors/threadpool/ThreadFactory;)V
  Code:
   Stack=9, Locals=8, Args_size=7
	aload_0
	iload_1
	iload_2
	lload_3
	aload	5
	aload	6
	aload	7
	getstatic	Field defaultHandler:Lscala/actors/threadpool/RejectedExecutionHandler;
	invokespecial	Method "<init>":(IIJLscala/actors/threadpool/TimeUnit;Lscala/actors/threadpool/BlockingQueue;Lscala/actors/threadpool/ThreadFactory;Lscala/actors/threadpool/RejectedExecutionHandler;)V
	return
  Labels:

public scala.actors.threadpool.ThreadPoolExecutor(int, int, long, scala.actors.threadpool.TimeUnit, scala.actors.threadpool.BlockingQueue, scala.actors.threadpool.RejectedExecutionHandler);
  Signature: (IIJLscala/actors/threadpool/TimeUnit;Lscala/actors/threadpool/BlockingQueue;Lscala/actors/threadpool/RejectedExecutionHandler;)V
  Code:
   Stack=9, Locals=8, Args_size=7
	aload_0
	iload_1
	iload_2
	lload_3
	aload	5
	aload	6
	invokestatic	Method scala/actors/threadpool/Executors.defaultThreadFactory:()Lscala/actors/threadpool/ThreadFactory;
	aload	7
	invokespecial	Method "<init>":(IIJLscala/actors/threadpool/TimeUnit;Lscala/actors/threadpool/BlockingQueue;Lscala/actors/threadpool/ThreadFactory;Lscala/actors/threadpool/RejectedExecutionHandler;)V
	return
  Labels:

public scala.actors.threadpool.ThreadPoolExecutor(int, int, long, scala.actors.threadpool.TimeUnit, scala.actors.threadpool.BlockingQueue, scala.actors.threadpool.ThreadFactory, scala.actors.threadpool.RejectedExecutionHandler);
  Signature: (IIJLscala/actors/threadpool/TimeUnit;Lscala/actors/threadpool/BlockingQueue;Lscala/actors/threadpool/ThreadFactory;Lscala/actors/threadpool/RejectedExecutionHandler;)V
  Code:
   Stack=5, Locals=9, Args_size=8
	aload_0
	invokespecial	Method scala/actors/threadpool/AbstractExecutorService."<init>":()V
	aload_0
	new	class scala/actors/threadpool/AtomicInteger
	dup
	ldc	int -536870912
	iconst_0
	invokestatic	Method ctlOf:(II)I
	invokespecial	Method scala/actors/threadpool/AtomicInteger."<init>":(I)V
	putfield	Field ctl:Lscala/actors/threadpool/AtomicInteger;
	aload_0
	new	class scala/actors/threadpool/locks/ReentrantLock
	dup
	invokespecial	Method scala/actors/threadpool/locks/ReentrantLock."<init>":()V
	putfield	Field mainLock:Lscala/actors/threadpool/locks/ReentrantLock;
	aload_0
	new	class java/util/HashSet
	dup
	invokespecial	Method java/util/HashSet."<init>":()V
	putfield	Field workers:Ljava/util/HashSet;
	aload_0
	aload_0
	getfield	Field mainLock:Lscala/actors/threadpool/locks/ReentrantLock;
	invokevirtual	Method scala/actors/threadpool/locks/ReentrantLock.newCondition:()Lscala/actors/threadpool/locks/Condition;
	putfield	Field termination:Lscala/actors/threadpool/locks/Condition;
	iload_1
	iflt	l1 // new
	iload_2
	ifle	l1 // new
	iload_2
	iload_1
	if_icmplt	l1 // new
	lload_3
	lconst_0
	lcmp
	ifge	l2 // aload
l1	new	class java/lang/IllegalArgumentException
	dup
	invokespecial	Method java/lang/IllegalArgumentException."<init>":()V
	athrow
l2	aload	6
	ifnull	l3 // new
	aload	7
	ifnull	l3 // new
	aload	8
	ifnonnull	l4 // aload_0
l3	new	class java/lang/NullPointerException
	dup
	invokespecial	Method java/lang/NullPointerException."<init>":()V
	athrow
l4	aload_0
	iload_1
	putfield	Field corePoolSize:I
	aload_0
	iload_2
	putfield	Field maximumPoolSize:I
	aload_0
	aload	6
	putfield	Field workQueue:Lscala/actors/threadpool/BlockingQueue;
	aload_0
	aload	5
	lload_3
	invokevirtual	Method scala/actors/threadpool/TimeUnit.toNanos:(J)J
	putfield	Field keepAliveTime:J
	aload_0
	aload	7
	putfield	Field threadFactory:Lscala/actors/threadpool/ThreadFactory;
	aload_0
	aload	8
	putfield	Field handler:Lscala/actors/threadpool/RejectedExecutionHandler;
	return
  Labels:
   	l1 = 73 // new
   	l2 = 81 // aload
   	l3 = 96 // new
   	l4 = 104 // aload_0

public void execute(java.lang.Runnable);
  Signature: (Ljava/lang/Runnable;)V
  Code:
   Stack=3, Locals=4, Args_size=2
	aload_1
	ifnonnull	l1 // aload_0
	new	class java/lang/NullPointerException
	dup
	invokespecial	Method java/lang/NullPointerException."<init>":()V
	athrow
l1	aload_0
	getfield	Field ctl:Lscala/actors/threadpool/AtomicInteger;
	invokevirtual	Method scala/actors/threadpool/AtomicInteger.get:()I
	istore_2
	iload_2
	invokestatic	Method workerCountOf:(I)I
	aload_0
	getfield	Field corePoolSize:I
	if_icmpge	l2 // iload_2
	aload_0
	aload_1
	iconst_1
	invokespecial	Method addWorker:(Ljava/lang/Runnable;Z)Z
	ifeq	l3 // aload_0
	return
l3	aload_0
	getfield	Field ctl:Lscala/actors/threadpool/AtomicInteger;
	invokevirtual	Method scala/actors/threadpool/AtomicInteger.get:()I
	istore_2
l2	iload_2
	invokestatic	Method isRunning:(I)Z
	ifeq	l4 // aload_0
	aload_0
	getfield	Field workQueue:Lscala/actors/threadpool/BlockingQueue;
	aload_1
	invokeinterface	InterfaceMethod scala/actors/threadpool/BlockingQueue.offer:(Ljava/lang/Object;)Z
	ifeq	l4 // aload_0
	aload_0
	getfield	Field ctl:Lscala/actors/threadpool/AtomicInteger;
	invokevirtual	Method scala/actors/threadpool/AtomicInteger.get:()I
	istore_3
	iload_3
	invokestatic	Method isRunning:(I)Z
	ifne	l5 // iload_3
	aload_0
	aload_1
	invokevirtual	Method remove:(Ljava/lang/Runnable;)Z
	ifeq	l5 // iload_3
	aload_0
	aload_1
	invokevirtual	Method reject:(Ljava/lang/Runnable;)V
	goto	l6 // goto
l5	iload_3
	invokestatic	Method workerCountOf:(I)I
	ifne	l6 // goto
	aload_0
	aconst_null
	iconst_0
	invokespecial	Method addWorker:(Ljava/lang/Runnable;Z)Z
	pop
l6	goto	l7 // return
l4	aload_0
	aload_1
	iconst_0
	invokespecial	Method addWorker:(Ljava/lang/Runnable;Z)Z
	ifne	l7 // return
	aload_0
	aload_1
	invokevirtual	Method reject:(Ljava/lang/Runnable;)V
l7	return
  Labels:
   	l1 = 12 // aload_0
   	l3 = 41 // aload_0
   	l2 = 49 // iload_2
   	l5 = 100 // iload_3
   	l6 = 114 // goto
   	l4 = 117 // aload_0
   	l7 = 131 // return

public void shutdown();
  Signature: ()V
  Code:
   Stack=2, Locals=3, Args_size=1
	aload_0
	getfield	Field mainLock:Lscala/actors/threadpool/locks/ReentrantLock;
	astore_1
	aload_1
	invokevirtual	Method scala/actors/threadpool/locks/ReentrantLock.lock:()V
	aload_0
	invokespecial	Method checkShutdownAccess:()V
	aload_0
	iconst_0
	invokespecial	Method advanceRunState:(I)V
	aload_0
	invokespecial	Method interruptIdleWorkers:()V
	aload_0
	invokevirtual	Method onShutdown:()V
	aload_1
	invokevirtual	Method scala/actors/threadpool/locks/ReentrantLock.unlock:()V
	goto	l1 // aload_0
	astore_2
	aload_1
	invokevirtual	Method scala/actors/threadpool/locks/ReentrantLock.unlock:()V
	aload_2
	athrow
l1	aload_0
	invokevirtual	Method tryTerminate:()V
	return
  Labels:
   	l1 = 40 // aload_0
  Exception table:
   from   to  target type
     9    26    33   any
    33    34    33   any

public java.util.List shutdownNow();
  Signature: ()Ljava/util/List;
  Code:
   Stack=2, Locals=4, Args_size=1
	aload_0
	getfield	Field mainLock:Lscala/actors/threadpool/locks/ReentrantLock;
	astore_2
	aload_2
	invokevirtual	Method scala/actors/threadpool/locks/ReentrantLock.lock:()V
	aload_0
	invokespecial	Method checkShutdownAccess:()V
	aload_0
	ldc	int 536870912
	invokespecial	Method advanceRunState:(I)V
	aload_0
	invokespecial	Method interruptWorkers:()V
	aload_0
	invokespecial	Method drainQueue:()Ljava/util/List;
	astore_1
	aload_2
	invokevirtual	Method scala/actors/threadpool/locks/ReentrantLock.unlock:()V
	goto	l1 // aload_0
	astore_3
	aload_2
	invokevirtual	Method scala/actors/threadpool/locks/ReentrantLock.unlock:()V
	aload_3
	athrow
l1	aload_0
	invokevirtual	Method tryTerminate:()V
	aload_1
	areturn
  Labels:
   	l1 = 42 // aload_0
  Exception table:
   from   to  target type
     9    28    35   any
    35    36    35   any

public boolean isShutdown();
  Signature: ()Z
  Code:
   Stack=1, Locals=1, Args_size=1
	aload_0
	getfield	Field ctl:Lscala/actors/threadpool/AtomicInteger;
	invokevirtual	Method scala/actors/threadpool/AtomicInteger.get:()I
	invokestatic	Method isRunning:(I)Z
	ifne	l1 // iconst_0
	iconst_1
	goto	l2 // ireturn
l1	iconst_0
l2	ireturn
  Labels:
   	l1 = 17 // iconst_0
   	l2 = 18 // ireturn

public boolean isTerminating();
  Signature: ()Z
  Code:
   Stack=2, Locals=2, Args_size=1
	aload_0
	getfield	Field ctl:Lscala/actors/threadpool/AtomicInteger;
	invokevirtual	Method scala/actors/threadpool/AtomicInteger.get:()I
	istore_1
	iload_1
	invokestatic	Method isRunning:(I)Z
	ifne	l1 // iconst_0
	iload_1
	ldc	int 1610612736
	invokestatic	Method runStateLessThan:(II)Z
	ifeq	l1 // iconst_0
	iconst_1
	goto	l2 // ireturn
l1	iconst_0
l2	ireturn
  Labels:
   	l1 = 28 // iconst_0
   	l2 = 29 // ireturn

public boolean isTerminated();
  Signature: ()Z
  Code:
   Stack=2, Locals=1, Args_size=1
	aload_0
	getfield	Field ctl:Lscala/actors/threadpool/AtomicInteger;
	invokevirtual	Method scala/actors/threadpool/AtomicInteger.get:()I
	ldc	int 1610612736
	invokestatic	Method runStateAtLeast:(II)Z
	ireturn
  Labels:

public boolean awaitTermination(long, scala.actors.threadpool.TimeUnit)   throws java.lang.InterruptedException;
  Signature: (JLscala/actors/threadpool/TimeUnit;)Z
  Code:
   Stack=4, Locals=11, Args_size=3
	aload_3
	lload_1
	invokevirtual	Method scala/actors/threadpool/TimeUnit.toNanos:(J)J
	lstore	4
	invokestatic	Method scala/actors/threadpool/helpers/Utils.nanoTime:()J
	lload	4
	ladd
	lstore	6
	aload_0
	getfield	Field mainLock:Lscala/actors/threadpool/locks/ReentrantLock;
	astore	8
	aload	8
	invokevirtual	Method scala/actors/threadpool/locks/ReentrantLock.lock:()V
	aload_0
	getfield	Field ctl:Lscala/actors/threadpool/AtomicInteger;
	invokevirtual	Method scala/actors/threadpool/AtomicInteger.get:()I
	ldc	int 1610612736
	invokestatic	Method runStateAtLeast:(II)Z
	ifeq	l1 // lload
	iconst_1
	istore	9
	aload	8
	invokevirtual	Method scala/actors/threadpool/locks/ReentrantLock.unlock:()V
	iload	9
	ireturn
l1	lload	4
	lconst_0
	lcmp
	ifle	l2 // iconst_0
	aload_0
	getfield	Field termination:Lscala/actors/threadpool/locks/Condition;
	lload	4
	getstatic	Field scala/actors/threadpool/TimeUnit.NANOSECONDS:Lscala/actors/threadpool/TimeUnit;
	invokeinterface	InterfaceMethod scala/actors/threadpool/locks/Condition.await:(JLscala/actors/threadpool/TimeUnit;)Z
	pop
	aload_0
	getfield	Field ctl:Lscala/actors/threadpool/AtomicInteger;
	invokevirtual	Method scala/actors/threadpool/AtomicInteger.get:()I
	ldc	int 1610612736
	invokestatic	Method runStateAtLeast:(II)Z
	ifeq	l3 // lload
	iconst_1
	istore	9
	aload	8
	invokevirtual	Method scala/actors/threadpool/locks/ReentrantLock.unlock:()V
	iload	9
	ireturn
l3	lload	6
	invokestatic	Method scala/actors/threadpool/helpers/Utils.nanoTime:()J
	lsub
	lstore	4
	goto	l1 // lload
l2	iconst_0
	istore	9
	aload	8
	invokevirtual	Method scala/actors/threadpool/locks/ReentrantLock.unlock:()V
	iload	9
	ireturn
	astore	10
	aload	8
	invokevirtual	Method scala/actors/threadpool/locks/ReentrantLock.unlock:()V
	aload	10
	athrow
  Labels:
   	l1 = 52 // lload
   	l3 = 100 // lload
   	l2 = 111 // iconst_0
  Exception table:
   from   to  target type
    26    44   122   any
    52    92   122   any
   100   114   122   any
   122   124   122   any
  Exceptions: 
   throws java.lang.InterruptedException
protected void finalize();
  Signature: ()V
  Code:
   Stack=1, Locals=1, Args_size=1
	aload_0
	invokevirtual	Method shutdown:()V
	return
  Labels:

public void setThreadFactory(scala.actors.threadpool.ThreadFactory);
  Signature: (Lscala/actors/threadpool/ThreadFactory;)V
  Code:
   Stack=2, Locals=2, Args_size=2
	aload_1
	ifnonnull	l1 // aload_0
	new	class java/lang/NullPointerException
	dup
	invokespecial	Method java/lang/NullPointerException."<init>":()V
	athrow
l1	aload_0
	aload_1
	putfield	Field threadFactory:Lscala/actors/threadpool/ThreadFactory;
	return
  Labels:
   	l1 = 12 // aload_0

public scala.actors.threadpool.ThreadFactory getThreadFactory();
  Signature: ()Lscala/actors/threadpool/ThreadFactory;
  Code:
   Stack=1, Locals=1, Args_size=1
	aload_0
	getfield	Field threadFactory:Lscala/actors/threadpool/ThreadFactory;
	areturn
  Labels:

public void setRejectedExecutionHandler(scala.actors.threadpool.RejectedExecutionHandler);
  Signature: (Lscala/actors/threadpool/RejectedExecutionHandler;)V
  Code:
   Stack=2, Locals=2, Args_size=2
	aload_1
	ifnonnull	l1 // aload_0
	new	class java/lang/NullPointerException
	dup
	invokespecial	Method java/lang/NullPointerException."<init>":()V
	athrow
l1	aload_0
	aload_1
	putfield	Field handler:Lscala/actors/threadpool/RejectedExecutionHandler;
	return
  Labels:
   	l1 = 12 // aload_0

public scala.actors.threadpool.RejectedExecutionHandler getRejectedExecutionHandler();
  Signature: ()Lscala/actors/threadpool/RejectedExecutionHandler;
  Code:
   Stack=1, Locals=1, Args_size=1
	aload_0
	getfield	Field handler:Lscala/actors/threadpool/RejectedExecutionHandler;
	areturn
  Labels:

public void setCorePoolSize(int);
  Signature: (I)V
  Code:
   Stack=3, Locals=4, Args_size=2
	iload_1
	ifge	l1 // iload_1
	new	class java/lang/IllegalArgumentException
	dup
	invokespecial	Method java/lang/IllegalArgumentException."<init>":()V
	athrow
l1	iload_1
	aload_0
	getfield	Field corePoolSize:I
	isub
	istore_2
	aload_0
	iload_1
	putfield	Field corePoolSize:I
	aload_0
	getfield	Field ctl:Lscala/actors/threadpool/AtomicInteger;
	invokevirtual	Method scala/actors/threadpool/AtomicInteger.get:()I
	invokestatic	Method workerCountOf:(I)I
	iload_1
	if_icmple	l2 // iload_2
	aload_0
	invokespecial	Method interruptIdleWorkers:()V
	goto	l3 // return
l2	iload_2
	ifle	l3 // return
	iload_2
	aload_0
	getfield	Field workQueue:Lscala/actors/threadpool/BlockingQueue;
	invokeinterface	InterfaceMethod scala/actors/threadpool/BlockingQueue.size:()I
	invokestatic	Method java/lang/Math.min:(II)I
	istore_3
l4	iload_3
	dup
	iconst_1
	isub
	istore_3
	ifle	l3 // return
	aload_0
	aconst_null
	iconst_1
	invokespecial	Method addWorker:(Ljava/lang/Runnable;Z)Z
	ifeq	l3 // return
	aload_0
	getfield	Field workQueue:Lscala/actors/threadpool/BlockingQueue;
	invokeinterface	InterfaceMethod scala/actors/threadpool/BlockingQueue.isEmpty:()Z
	ifeq	l4 // iload_3
	goto	l3 // return
l3	return
  Labels:
   	l1 = 12 // iload_1
   	l2 = 45 // iload_2
   	l4 = 63 // iload_3
   	l3 = 95 // return

public int getCorePoolSize();
  Signature: ()I
  Code:
   Stack=1, Locals=1, Args_size=1
	aload_0
	getfield	Field corePoolSize:I
	ireturn
  Labels:

public boolean prestartCoreThread();
  Signature: ()Z
  Code:
   Stack=3, Locals=1, Args_size=1
	aload_0
	getfield	Field ctl:Lscala/actors/threadpool/AtomicInteger;
	invokevirtual	Method scala/actors/threadpool/AtomicInteger.get:()I
	invokestatic	Method workerCountOf:(I)I
	aload_0
	getfield	Field corePoolSize:I
	if_icmpge	l1 // iconst_0
	aload_0
	aconst_null
	iconst_1
	invokespecial	Method addWorker:(Ljava/lang/Runnable;Z)Z
	ifeq	l1 // iconst_0
	iconst_1
	goto	l2 // ireturn
l1	iconst_0
l2	ireturn
  Labels:
   	l1 = 30 // iconst_0
   	l2 = 31 // ireturn

public int prestartAllCoreThreads();
  Signature: ()I
  Code:
   Stack=3, Locals=2, Args_size=1
	iconst_0
	istore_1
l2	aload_0
	aconst_null
	iconst_1
	invokespecial	Method addWorker:(Ljava/lang/Runnable;Z)Z
	ifeq	l1 // iload_1
	iinc	1, 1
	goto	l2 // aload_0
l1	iload_1
	ireturn
  Labels:
   	l2 = 2 // aload_0
   	l1 = 17 // iload_1

public boolean allowsCoreThreadTimeOut();
  Signature: ()Z
  Code:
   Stack=1, Locals=1, Args_size=1
	aload_0
	getfield	Field allowCoreThreadTimeOut:Z
	ireturn
  Labels:

public void allowCoreThreadTimeOut(boolean);
  Signature: (Z)V
  Code:
   Stack=4, Locals=2, Args_size=2
	iload_1
	ifeq	l1 // iload_1
	aload_0
	getfield	Field keepAliveTime:J
	lconst_0
	lcmp
	ifgt	l1 // iload_1
	new	class java/lang/IllegalArgumentException
	dup
	ldc	String Core threads must have nonzero keep alive times
	invokespecial	Method java/lang/IllegalArgumentException."<init>":(Ljava/lang/String;)V
	athrow
l1	iload_1
	aload_0
	getfield	Field allowCoreThreadTimeOut:Z
	if_icmpeq	l2 // return
	aload_0
	iload_1
	putfield	Field allowCoreThreadTimeOut:Z
	iload_1
	ifeq	l2 // return
	aload_0
	invokespecial	Method interruptIdleWorkers:()V
l2	return
  Labels:
   	l1 = 23 // iload_1
   	l2 = 44 // return

public void setMaximumPoolSize(int);
  Signature: (I)V
  Code:
   Stack=2, Locals=2, Args_size=2
	iload_1
	ifle	l1 // new
	iload_1
	aload_0
	getfield	Field corePoolSize:I
	if_icmpge	l2 // aload_0
l1	new	class java/lang/IllegalArgumentException
	dup
	invokespecial	Method java/lang/IllegalArgumentException."<init>":()V
	athrow
l2	aload_0
	iload_1
	putfield	Field maximumPoolSize:I
	aload_0
	getfield	Field ctl:Lscala/actors/threadpool/AtomicInteger;
	invokevirtual	Method scala/actors/threadpool/AtomicInteger.get:()I
	invokestatic	Method workerCountOf:(I)I
	iload_1
	if_icmple	l3 // return
	aload_0
	invokespecial	Method interruptIdleWorkers:()V
l3	return
  Labels:
   	l1 = 12 // new
   	l2 = 20 // aload_0
   	l3 = 43 // return

public int getMaximumPoolSize();
  Signature: ()I
  Code:
   Stack=1, Locals=1, Args_size=1
	aload_0
	getfield	Field maximumPoolSize:I
	ireturn
  Labels:

public void setKeepAliveTime(long, scala.actors.threadpool.TimeUnit);
  Signature: (JLscala/actors/threadpool/TimeUnit;)V
  Code:
   Stack=4, Locals=8, Args_size=3
	lload_1
	lconst_0
	lcmp
	ifge	l1 // lload_1
	new	class java/lang/IllegalArgumentException
	dup
	invokespecial	Method java/lang/IllegalArgumentException."<init>":()V
	athrow
l1	lload_1
	lconst_0
	lcmp
	ifne	l2 // aload_3
	aload_0
	invokevirtual	Method allowsCoreThreadTimeOut:()Z
	ifeq	l2 // aload_3
	new	class java/lang/IllegalArgumentException
	dup
	ldc	String Core threads must have nonzero keep alive times
	invokespecial	Method java/lang/IllegalArgumentException."<init>":(Ljava/lang/String;)V
	athrow
l2	aload_3
	lload_1
	invokevirtual	Method scala/actors/threadpool/TimeUnit.toNanos:(J)J
	lstore	4
	lload	4
	aload_0
	getfield	Field keepAliveTime:J
	lsub
	lstore	6
	aload_0
	lload	4
	putfield	Field keepAliveTime:J
	lload	6
	lconst_0
	lcmp
	ifge	l3 // return
	aload_0
	invokespecial	Method interruptIdleWorkers:()V
l3	return
  Labels:
   	l1 = 14 // lload_1
   	l2 = 37 // aload_3
   	l3 = 70 // return

public long getKeepAliveTime(scala.actors.threadpool.TimeUnit);
  Signature: (Lscala/actors/threadpool/TimeUnit;)J
  Code:
   Stack=4, Locals=2, Args_size=2
	aload_1
	aload_0
	getfield	Field keepAliveTime:J
	getstatic	Field scala/actors/threadpool/TimeUnit.NANOSECONDS:Lscala/actors/threadpool/TimeUnit;
	invokevirtual	Method scala/actors/threadpool/TimeUnit.convert:(JLscala/actors/threadpool/TimeUnit;)J
	lreturn
  Labels:

public scala.actors.threadpool.BlockingQueue getQueue();
  Signature: ()Lscala/actors/threadpool/BlockingQueue;
  Code:
   Stack=1, Locals=1, Args_size=1
	aload_0
	getfield	Field workQueue:Lscala/actors/threadpool/BlockingQueue;
	areturn
  Labels:

public boolean remove(java.lang.Runnable);
  Signature: (Ljava/lang/Runnable;)Z
  Code:
   Stack=2, Locals=3, Args_size=2
	aload_0
	getfield	Field workQueue:Lscala/actors/threadpool/BlockingQueue;
	aload_1
	invokeinterface	InterfaceMethod scala/actors/threadpool/BlockingQueue.remove:(Ljava/lang/Object;)Z
	istore_2
	aload_0
	invokevirtual	Method tryTerminate:()V
	iload_2
	ireturn
  Labels:

public void purge();
  Signature: ()V
  Code:
   Stack=2, Locals=6, Args_size=1
	aload_0
	getfield	Field workQueue:Lscala/actors/threadpool/BlockingQueue;
	astore_1
	aload_1
	invokeinterface	InterfaceMethod scala/actors/threadpool/BlockingQueue.iterator:()Ljava/util/Iterator;
	astore_2
l3	aload_2
	invokeinterface	InterfaceMethod java/util/Iterator.hasNext:()Z
	ifeq	l1 // goto
	aload_2
	invokeinterface	InterfaceMethod java/util/Iterator.next:()Ljava/lang/Object;
	checkcast	class java/lang/Runnable
	astore_3
	aload_3
	instanceof	class scala/actors/threadpool/Future
	ifeq	l2 // goto
	aload_3
	checkcast	class scala/actors/threadpool/Future
	invokeinterface	InterfaceMethod scala/actors/threadpool/Future.isCancelled:()Z
	ifeq	l2 // goto
	aload_2
	invokeinterface	InterfaceMethod java/util/Iterator.remove:()V
l2	goto	l3 // aload_2
l1	goto	l4 // aload_0
	astore_2
	aload_1
	invokeinterface	InterfaceMethod scala/actors/threadpool/BlockingQueue.toArray:()[Ljava/lang/Object;
	astore_3
	iconst_0
	istore	4
l6	iload	4
	aload_3
	arraylength
	if_icmpge	l4 // aload_0
	aload_3
	iload	4
	aaload
	astore	5
	aload	5
	instanceof	class scala/actors/threadpool/Future
	ifeq	l5 // iinc
	aload	5
	checkcast	class scala/actors/threadpool/Future
	invokeinterface	InterfaceMethod scala/actors/threadpool/Future.isCancelled:()Z
	ifeq	l5 // iinc
	aload_1
	aload	5
	invokeinterface	InterfaceMethod scala/actors/threadpool/BlockingQueue.remove:(Ljava/lang/Object;)Z
	pop
l5	iinc	4, 1
	goto	l6 // iload
l4	aload_0
	invokevirtual	Method tryTerminate:()V
	return
  Labels:
   	l3 = 12 // aload_2
   	l2 = 56 // goto
   	l1 = 59 // goto
   	l6 = 73 // iload
   	l5 = 116 // iinc
   	l4 = 122 // aload_0
  Exception table:
   from   to  target type
     5    59    62   Class java/util/ConcurrentModificationException


public int getPoolSize();
  Signature: ()I
  Code:
   Stack=2, Locals=4, Args_size=1
	aload_0
	getfield	Field mainLock:Lscala/actors/threadpool/locks/ReentrantLock;
	astore_1
	aload_1
	invokevirtual	Method scala/actors/threadpool/locks/ReentrantLock.lock:()V
	aload_0
	getfield	Field ctl:Lscala/actors/threadpool/AtomicInteger;
	invokevirtual	Method scala/actors/threadpool/AtomicInteger.get:()I
	ldc	int 1073741824
	invokestatic	Method runStateAtLeast:(II)Z
	ifeq	l1 // aload_0
	iconst_0
	goto	l2 // istore_2
l1	aload_0
	getfield	Field workers:Ljava/util/HashSet;
	invokevirtual	Method java/util/HashSet.size:()I
l2	istore_2
	aload_1
	invokevirtual	Method scala/actors/threadpool/locks/ReentrantLock.unlock:()V
	iload_2
	ireturn
	astore_3
	aload_1
	invokevirtual	Method scala/actors/threadpool/locks/ReentrantLock.unlock:()V
	aload_3
	athrow
  Labels:
   	l1 = 28 // aload_0
   	l2 = 35 // istore_2
  Exception table:
   from   to  target type
     9    36    42   any
    42    43    42   any

public int getActiveCount();
  Signature: ()I
  Code:
   Stack=1, Locals=6, Args_size=1
	aload_0
	getfield	Field mainLock:Lscala/actors/threadpool/locks/ReentrantLock;
	astore_1
	aload_1
	invokevirtual	Method scala/actors/threadpool/locks/ReentrantLock.lock:()V
	iconst_0
	istore_2
	aload_0
	getfield	Field workers:Ljava/util/HashSet;
	invokevirtual	Method java/util/HashSet.iterator:()Ljava/util/Iterator;
	astore_3
l3	aload_3
	invokeinterface	InterfaceMethod java/util/Iterator.hasNext:()Z
	ifeq	l1 // iload_2
	aload_3
	invokeinterface	InterfaceMethod java/util/Iterator.next:()Ljava/lang/Object;
	checkcast	class scala/actors/threadpool/ThreadPoolExecutor$Worker
	astore	4
	aload	4
	invokevirtual	Method scala/actors/threadpool/ThreadPoolExecutor$Worker.isLocked:()Z
	ifeq	l2 // goto
	iinc	2, 1
l2	goto	l3 // aload_3
l1	iload_2
	istore_3
	aload_1
	invokevirtual	Method scala/actors/threadpool/locks/ReentrantLock.unlock:()V
	iload_3
	ireturn
	astore	5
	aload_1
	invokevirtual	Method scala/actors/threadpool/locks/ReentrantLock.unlock:()V
	aload	5
	athrow
  Labels:
   	l3 = 19 // aload_3
   	l2 = 50 // goto
   	l1 = 53 // iload_2
  Exception table:
   from   to  target type
     9    55    61   any
    61    63    61   any

public int getLargestPoolSize();
  Signature: ()I
  Code:
   Stack=1, Locals=4, Args_size=1
	aload_0
	getfield	Field mainLock:Lscala/actors/threadpool/locks/ReentrantLock;
	astore_1
	aload_1
	invokevirtual	Method scala/actors/threadpool/locks/ReentrantLock.lock:()V
	aload_0
	getfield	Field largestPoolSize:I
	istore_2
	aload_1
	invokevirtual	Method scala/actors/threadpool/locks/ReentrantLock.unlock:()V
	iload_2
	ireturn
	astore_3
	aload_1
	invokevirtual	Method scala/actors/threadpool/locks/ReentrantLock.unlock:()V
	aload_3
	athrow
  Labels:
  Exception table:
   from   to  target type
     9    14    20   any
    20    21    20   any

public long getTaskCount();
  Signature: ()J
  Code:
   Stack=4, Locals=7, Args_size=1
	aload_0
	getfield	Field mainLock:Lscala/actors/threadpool/locks/ReentrantLock;
	astore_1
	aload_1
	invokevirtual	Method scala/actors/threadpool/locks/ReentrantLock.lock:()V
	aload_0
	getfield	Field completedTaskCount:J
	lstore_2
	aload_0
	getfield	Field workers:Ljava/util/HashSet;
	invokevirtual	Method java/util/HashSet.iterator:()Ljava/util/Iterator;
	astore	4
l3	aload	4
	invokeinterface	InterfaceMethod java/util/Iterator.hasNext:()Z
	ifeq	l1 // lload_2
	aload	4
	invokeinterface	InterfaceMethod java/util/Iterator.next:()Ljava/lang/Object;
	checkcast	class scala/actors/threadpool/ThreadPoolExecutor$Worker
	astore	5
	lload_2
	aload	5
	getfield	Field scala/actors/threadpool/ThreadPoolExecutor$Worker.completedTasks:J
	ladd
	lstore_2
	aload	5
	invokevirtual	Method scala/actors/threadpool/ThreadPoolExecutor$Worker.isLocked:()Z
	ifeq	l2 // goto
	lload_2
	lconst_1
	ladd
	lstore_2
l2	goto	l3 // aload
l1	lload_2
	aload_0
	getfield	Field workQueue:Lscala/actors/threadpool/BlockingQueue;
	invokeinterface	InterfaceMethod scala/actors/threadpool/BlockingQueue.size:()I
	i2l
	ladd
	lstore	4
	aload_1
	invokevirtual	Method scala/actors/threadpool/locks/ReentrantLock.unlock:()V
	lload	4
	lreturn
	astore	6
	aload_1
	invokevirtual	Method scala/actors/threadpool/locks/ReentrantLock.unlock:()V
	aload	6
	athrow
  Labels:
   	l3 = 23 // aload
   	l2 = 65 // goto
   	l1 = 68 // lload_2
  Exception table:
   from   to  target type
     9    82    89   any
    89    91    89   any

public long getCompletedTaskCount();
  Signature: ()J
  Code:
   Stack=4, Locals=7, Args_size=1
	aload_0
	getfield	Field mainLock:Lscala/actors/threadpool/locks/ReentrantLock;
	astore_1
	aload_1
	invokevirtual	Method scala/actors/threadpool/locks/ReentrantLock.lock:()V
	aload_0
	getfield	Field completedTaskCount:J
	lstore_2
	aload_0
	getfield	Field workers:Ljava/util/HashSet;
	invokevirtual	Method java/util/HashSet.iterator:()Ljava/util/Iterator;
	astore	4
l2	aload	4
	invokeinterface	InterfaceMethod java/util/Iterator.hasNext:()Z
	ifeq	l1 // lload_2
	aload	4
	invokeinterface	InterfaceMethod java/util/Iterator.next:()Ljava/lang/Object;
	checkcast	class scala/actors/threadpool/ThreadPoolExecutor$Worker
	astore	5
	lload_2
	aload	5
	getfield	Field scala/actors/threadpool/ThreadPoolExecutor$Worker.completedTasks:J
	ladd
	lstore_2
	goto	l2 // aload
l1	lload_2
	lstore	4
	aload_1
	invokevirtual	Method scala/actors/threadpool/locks/ReentrantLock.unlock:()V
	lload	4
	lreturn
	astore	6
	aload_1
	invokevirtual	Method scala/actors/threadpool/locks/ReentrantLock.unlock:()V
	aload	6
	athrow
  Labels:
   	l2 = 23 // aload
   	l1 = 56 // lload_2
  Exception table:
   from   to  target type
     9    59    66   any
    66    68    66   any

protected void beforeExecute(java.lang.Thread, java.lang.Runnable);
  Signature: (Ljava/lang/Thread;Ljava/lang/Runnable;)V
  Code:
   Stack=0, Locals=3, Args_size=3
	return
  Labels:

protected void afterExecute(java.lang.Runnable, java.lang.Throwable);
  Signature: (Ljava/lang/Runnable;Ljava/lang/Throwable;)V
  Code:
   Stack=0, Locals=3, Args_size=3
	return
  Labels:

protected void terminated();
  Signature: ()V
  Code:
   Stack=0, Locals=1, Args_size=1
	return
  Labels:

static {};
  Signature: ()V
  Code:
   Stack=3, Locals=0, Args_size=0
	new	class scala/actors/threadpool/ThreadPoolExecutor$AbortPolicy
	dup
	invokespecial	Method scala/actors/threadpool/ThreadPoolExecutor$AbortPolicy."<init>":()V
	putstatic	Field defaultHandler:Lscala/actors/threadpool/RejectedExecutionHandler;
	new	class java/lang/RuntimePermission
	dup
	ldc	String modifyThread
	invokespecial	Method java/lang/RuntimePermission."<init>":(Ljava/lang/String;)V
	putstatic	Field shutdownPerm:Ljava/lang/RuntimePermission;
	return
  Labels:

}

