public class scala.actors.threadpool.ThreadPoolExecutor$DiscardOldestPolicy extends java.lang.Object implements scala.actors.threadpool.RejectedExecutionHandler
  InnerClass: 
   public DiscardOldestPolicy=class scala/actors/threadpool/ThreadPoolExecutor$DiscardOldestPolicy of class scala/actors/threadpool/ThreadPoolExecutor
  minor version: 0
  major version: 49
  Constant pool:
Method	java/lang/Object."<init>":()V
Method	scala/actors/threadpool/ThreadPoolExecutor.isShutdown:()Z
Method	scala/actors/threadpool/ThreadPoolExecutor.getQueue:()Lscala/actors/threadpool/BlockingQueue;
InterfaceMethod	scala/actors/threadpool/BlockingQueue.poll:()Ljava/lang/Object;
Method	scala/actors/threadpool/ThreadPoolExecutor.execute:(Ljava/lang/Runnable;)V
class	scala/actors/threadpool/ThreadPoolExecutor$DiscardOldestPolicy
class	java/lang/Object
class	scala/actors/threadpool/RejectedExecutionHandler
Asciz	<init>;
Asciz	()V;
Asciz	Code;
Asciz	rejectedExecution;
Asciz	(Ljava/lang/Runnable;Lscala/actors/threadpool/ThreadPoolExecutor;)V;
NameAndType	"<init>":()V
class	scala/actors/threadpool/ThreadPoolExecutor
NameAndType	isShutdown:()Z
NameAndType	getQueue:()Lscala/actors/threadpool/BlockingQueue;
class	scala/actors/threadpool/BlockingQueue
NameAndType	poll:()Ljava/lang/Object;
NameAndType	execute:(Ljava/lang/Runnable;)V
Asciz	scala/actors/threadpool/ThreadPoolExecutor$DiscardOldestPolicy;
Asciz	DiscardOldestPolicy;
Asciz	InnerClasses;
Asciz	java/lang/Object;
Asciz	scala/actors/threadpool/RejectedExecutionHandler;
Asciz	scala/actors/threadpool/ThreadPoolExecutor;
Asciz	isShutdown;
Asciz	()Z;
Asciz	getQueue;
Asciz	()Lscala/actors/threadpool/BlockingQueue;;
Asciz	scala/actors/threadpool/BlockingQueue;
Asciz	poll;
Asciz	()Ljava/lang/Object;;
Asciz	execute;
Asciz	(Ljava/lang/Runnable;)V;

{
public scala.actors.threadpool.ThreadPoolExecutor$DiscardOldestPolicy();
  Signature: ()V
  Code:
   Stack=1, Locals=1, Args_size=1
	aload_0
	invokespecial	Method java/lang/Object."<init>":()V
	return
  Labels:

public void rejectedExecution(java.lang.Runnable, scala.actors.threadpool.ThreadPoolExecutor);
  Signature: (Ljava/lang/Runnable;Lscala/actors/threadpool/ThreadPoolExecutor;)V
  Code:
   Stack=2, Locals=3, Args_size=3
	aload_2
	invokevirtual	Method scala/actors/threadpool/ThreadPoolExecutor.isShutdown:()Z
	ifne	l1 // return
	aload_2
	invokevirtual	Method scala/actors/threadpool/ThreadPoolExecutor.getQueue:()Lscala/actors/threadpool/BlockingQueue;
	invokeinterface	InterfaceMethod scala/actors/threadpool/BlockingQueue.poll:()Ljava/lang/Object;
	pop
	aload_2
	aload_1
	invokevirtual	Method scala/actors/threadpool/ThreadPoolExecutor.execute:(Ljava/lang/Runnable;)V
l1	return
  Labels:
   	l1 = 22 // return

}

