public abstract class scala.actors.threadpool.TimeUnit extends java.lang.Object implements java.io.Serializable
  InnerClass: 
   #28; //class scala/actors/threadpool/TimeUnit$1
   #32; //class scala/actors/threadpool/TimeUnit$2
   #36; //class scala/actors/threadpool/TimeUnit$3
   #40; //class scala/actors/threadpool/TimeUnit$4
   #44; //class scala/actors/threadpool/TimeUnit$5
   #48; //class scala/actors/threadpool/TimeUnit$6
   #52; //class scala/actors/threadpool/TimeUnit$7
  minor version: 0
  major version: 49
  Constant pool:
const #1 = Field	#56.#134;	//  scala/actors/threadpool/TimeUnit.values:[Lscala/actors/threadpool/TimeUnit;
const #2 = Method	#135.#136;	//  "[Lscala/actors/threadpool/TimeUnit;".clone:()Ljava/lang/Object;
const #3 = class	#68;	//  "[Lscala/actors/threadpool/TimeUnit;"
const #4 = Field	#56.#137;	//  scala/actors/threadpool/TimeUnit.name:Ljava/lang/String;
const #5 = Method	#138.#139;	//  java/lang/String.equals:(Ljava/lang/Object;)Z
const #6 = class	#140;	//  java/lang/IllegalArgumentException
const #7 = class	#141;	//  java/lang/StringBuilder
const #8 = Method	#7.#142;	//  java/lang/StringBuilder."<init>":()V
const #9 = String	#143;	//  No enum const TimeUnit.
const #10 = Method	#7.#144;	//  java/lang/StringBuilder.append:(Ljava/lang/String;)Ljava/lang/StringBuilder;
const #11 = Method	#7.#145;	//  java/lang/StringBuilder.toString:()Ljava/lang/String;
const #12 = Method	#6.#146;	//  java/lang/IllegalArgumentException."<init>":(Ljava/lang/String;)V
const #13 = Method	#57.#142;	//  java/lang/Object."<init>":()V
const #14 = Field	#56.#147;	//  scala/actors/threadpool/TimeUnit.index:I
const #15 = long	9223372036854775807l;
const #17 = long	-9223372036854775808l;
const #19 = Method	#56.#148;	//  scala/actors/threadpool/TimeUnit.valueOf:(Ljava/lang/String;)Lscala/actors/threadpool/TimeUnit;
const #20 = class	#149;	//  java/io/InvalidObjectException
const #21 = String	#150;	//   is not a valid enum for TimeUnit
const #22 = Method	#20.#146;	//  java/io/InvalidObjectException."<init>":(Ljava/lang/String;)V
const #23 = Method	#56.#151;	//  scala/actors/threadpool/TimeUnit.toMillis:(J)J
const #24 = Method	#56.#152;	//  scala/actors/threadpool/TimeUnit.excessNanos:(JJ)I
const #25 = Method	#57.#153;	//  java/lang/Object.wait:(JI)V
const #26 = Method	#154.#155;	//  java/lang/Thread.join:(JI)V
const #27 = Method	#154.#156;	//  java/lang/Thread.sleep:(JI)V
const #28 = class	#157;	//  scala/actors/threadpool/TimeUnit$1
const #29 = String	#59;	//  NANOSECONDS
const #30 = Method	#28.#160;	//  scala/actors/threadpool/TimeUnit$1."<init>":(ILjava/lang/String;)V
const #31 = Field	#56.#161;	//  scala/actors/threadpool/TimeUnit.NANOSECONDS:Lscala/actors/threadpool/TimeUnit;
const #32 = class	#162;	//  scala/actors/threadpool/TimeUnit$2
const #33 = String	#61;	//  MICROSECONDS
const #34 = Method	#32.#160;	//  scala/actors/threadpool/TimeUnit$2."<init>":(ILjava/lang/String;)V
const #35 = Field	#56.#163;	//  scala/actors/threadpool/TimeUnit.MICROSECONDS:Lscala/actors/threadpool/TimeUnit;
const #36 = class	#164;	//  scala/actors/threadpool/TimeUnit$3
const #37 = String	#62;	//  MILLISECONDS
const #38 = Method	#36.#160;	//  scala/actors/threadpool/TimeUnit$3."<init>":(ILjava/lang/String;)V
const #39 = Field	#56.#165;	//  scala/actors/threadpool/TimeUnit.MILLISECONDS:Lscala/actors/threadpool/TimeUnit;
const #40 = class	#166;	//  scala/actors/threadpool/TimeUnit$4
const #41 = String	#63;	//  SECONDS
const #42 = Method	#40.#160;	//  scala/actors/threadpool/TimeUnit$4."<init>":(ILjava/lang/String;)V
const #43 = Field	#56.#167;	//  scala/actors/threadpool/TimeUnit.SECONDS:Lscala/actors/threadpool/TimeUnit;
const #44 = class	#168;	//  scala/actors/threadpool/TimeUnit$5
const #45 = String	#64;	//  MINUTES
const #46 = Method	#44.#160;	//  scala/actors/threadpool/TimeUnit$5."<init>":(ILjava/lang/String;)V
const #47 = Field	#56.#169;	//  scala/actors/threadpool/TimeUnit.MINUTES:Lscala/actors/threadpool/TimeUnit;
const #48 = class	#170;	//  scala/actors/threadpool/TimeUnit$6
const #49 = String	#65;	//  HOURS
const #50 = Method	#48.#160;	//  scala/actors/threadpool/TimeUnit$6."<init>":(ILjava/lang/String;)V
const #51 = Field	#56.#171;	//  scala/actors/threadpool/TimeUnit.HOURS:Lscala/actors/threadpool/TimeUnit;
const #52 = class	#172;	//  scala/actors/threadpool/TimeUnit$7
const #53 = String	#66;	//  DAYS
const #54 = Method	#52.#160;	//  scala/actors/threadpool/TimeUnit$7."<init>":(ILjava/lang/String;)V
const #55 = Field	#56.#173;	//  scala/actors/threadpool/TimeUnit.DAYS:Lscala/actors/threadpool/TimeUnit;
const #56 = class	#174;	//  scala/actors/threadpool/TimeUnit
const #57 = class	#175;	//  java/lang/Object
const #58 = class	#176;	//  java/io/Serializable
const #59 = Asciz	NANOSECONDS;
const #60 = Asciz	Lscala/actors/threadpool/TimeUnit;;
const #61 = Asciz	MICROSECONDS;
const #62 = Asciz	MILLISECONDS;
const #63 = Asciz	SECONDS;
const #64 = Asciz	MINUTES;
const #65 = Asciz	HOURS;
const #66 = Asciz	DAYS;
const #67 = Asciz	values;
const #68 = Asciz	[Lscala/actors/threadpool/TimeUnit;;
const #69 = Asciz	index;
const #70 = Asciz	I;
const #71 = Asciz	name;
const #72 = Asciz	Ljava/lang/String;;
const #73 = Asciz	C0;
const #74 = Asciz	J;
const #75 = Asciz	ConstantValue;
const #76 = long	1l;
const #78 = Asciz	C1;
const #79 = long	1000l;
const #81 = Asciz	C2;
const #82 = long	1000000l;
const #84 = Asciz	C3;
const #85 = long	1000000000l;
const #87 = Asciz	C4;
const #88 = long	60000000000l;
const #90 = Asciz	C5;
const #91 = long	3600000000000l;
const #93 = Asciz	C6;
const #94 = long	86400000000000l;
const #96 = Asciz	MAX;
const #97 = Asciz	()[Lscala/actors/threadpool/TimeUnit;;
const #98 = Asciz	Code;
const #99 = Asciz	valueOf;
const #100 = Asciz	(Ljava/lang/String;)Lscala/actors/threadpool/TimeUnit;;
const #101 = Asciz	<init>;
const #102 = Asciz	(ILjava/lang/String;)V;
const #103 = Asciz	x;
const #104 = Asciz	(JJJ)J;
const #105 = Asciz	convert;
const #106 = Asciz	(JLscala/actors/threadpool/TimeUnit;)J;
const #107 = Asciz	toNanos;
const #108 = Asciz	(J)J;
const #109 = Asciz	toMicros;
const #110 = Asciz	toMillis;
const #111 = Asciz	toSeconds;
const #112 = Asciz	toMinutes;
const #113 = Asciz	toHours;
const #114 = Asciz	toDays;
const #115 = Asciz	excessNanos;
const #116 = Asciz	(JJ)I;
const #117 = Asciz	()Ljava/lang/String;;
const #118 = Asciz	ordinal;
const #119 = Asciz	()I;
const #120 = Asciz	readResolve;
const #121 = Asciz	()Ljava/lang/Object;;
const #122 = Asciz	Exceptions;
const #123 = class	#177;	//  java/io/ObjectStreamException
const #124 = Asciz	timedWait;
const #125 = Asciz	(Ljava/lang/Object;J)V;
const #126 = class	#178;	//  java/lang/InterruptedException
const #127 = Asciz	timedJoin;
const #128 = Asciz	(Ljava/lang/Thread;J)V;
const #129 = Asciz	sleep;
const #130 = Asciz	(J)V;
const #131 = Asciz	toString;
const #132 = Asciz	<clinit>;
const #133 = Asciz	()V;
const #134 = NameAndType	#67:#68;//  values:[Lscala/actors/threadpool/TimeUnit;
const #135 = class	#68;	//  "[Lscala/actors/threadpool/TimeUnit;"
const #136 = NameAndType	#179:#121;//  clone:()Ljava/lang/Object;
const #137 = NameAndType	#71:#72;//  name:Ljava/lang/String;
const #138 = class	#180;	//  java/lang/String
const #139 = NameAndType	#181:#182;//  equals:(Ljava/lang/Object;)Z
const #140 = Asciz	java/lang/IllegalArgumentException;
const #141 = Asciz	java/lang/StringBuilder;
const #142 = NameAndType	#101:#133;//  "<init>":()V
const #143 = Asciz	No enum const TimeUnit.;
const #144 = NameAndType	#183:#184;//  append:(Ljava/lang/String;)Ljava/lang/StringBuilder;
const #145 = NameAndType	#131:#117;//  toString:()Ljava/lang/String;
const #146 = NameAndType	#101:#185;//  "<init>":(Ljava/lang/String;)V
const #147 = NameAndType	#69:#70;//  index:I
const #148 = NameAndType	#99:#100;//  valueOf:(Ljava/lang/String;)Lscala/actors/threadpool/TimeUnit;
const #149 = Asciz	java/io/InvalidObjectException;
const #150 = Asciz	 is not a valid enum for TimeUnit;
const #151 = NameAndType	#110:#108;//  toMillis:(J)J
const #152 = NameAndType	#115:#116;//  excessNanos:(JJ)I
const #153 = NameAndType	#186:#187;//  wait:(JI)V
const #154 = class	#188;	//  java/lang/Thread
const #155 = NameAndType	#189:#187;//  join:(JI)V
const #156 = NameAndType	#129:#187;//  sleep:(JI)V
const #157 = Asciz	scala/actors/threadpool/TimeUnit$1;
const #158 = Asciz	;
const #159 = Asciz	InnerClasses;
const #160 = NameAndType	#101:#102;//  "<init>":(ILjava/lang/String;)V
const #161 = NameAndType	#59:#60;//  NANOSECONDS:Lscala/actors/threadpool/TimeUnit;
const #162 = Asciz	scala/actors/threadpool/TimeUnit$2;
const #163 = NameAndType	#61:#60;//  MICROSECONDS:Lscala/actors/threadpool/TimeUnit;
const #164 = Asciz	scala/actors/threadpool/TimeUnit$3;
const #165 = NameAndType	#62:#60;//  MILLISECONDS:Lscala/actors/threadpool/TimeUnit;
const #166 = Asciz	scala/actors/threadpool/TimeUnit$4;
const #167 = NameAndType	#63:#60;//  SECONDS:Lscala/actors/threadpool/TimeUnit;
const #168 = Asciz	scala/actors/threadpool/TimeUnit$5;
const #169 = NameAndType	#64:#60;//  MINUTES:Lscala/actors/threadpool/TimeUnit;
const #170 = Asciz	scala/actors/threadpool/TimeUnit$6;
const #171 = NameAndType	#65:#60;//  HOURS:Lscala/actors/threadpool/TimeUnit;
const #172 = Asciz	scala/actors/threadpool/TimeUnit$7;
const #173 = NameAndType	#66:#60;//  DAYS:Lscala/actors/threadpool/TimeUnit;
const #174 = Asciz	scala/actors/threadpool/TimeUnit;
const #175 = Asciz	java/lang/Object;
const #176 = Asciz	java/io/Serializable;
const #177 = Asciz	java/io/ObjectStreamException;
const #178 = Asciz	java/lang/InterruptedException;
const #179 = Asciz	clone;
const #180 = Asciz	java/lang/String;
const #181 = Asciz	equals;
const #182 = Asciz	(Ljava/lang/Object;)Z;
const #183 = Asciz	append;
const #184 = Asciz	(Ljava/lang/String;)Ljava/lang/StringBuilder;;
const #185 = Asciz	(Ljava/lang/String;)V;
const #186 = Asciz	wait;
const #187 = Asciz	(JI)V;
const #188 = Asciz	java/lang/Thread;
const #189 = Asciz	join;

{
public static final scala.actors.threadpool.TimeUnit NANOSECONDS;

public static final scala.actors.threadpool.TimeUnit MICROSECONDS;

public static final scala.actors.threadpool.TimeUnit MILLISECONDS;

public static final scala.actors.threadpool.TimeUnit SECONDS;

public static final scala.actors.threadpool.TimeUnit MINUTES;

public static final scala.actors.threadpool.TimeUnit HOURS;

public static final scala.actors.threadpool.TimeUnit DAYS;

static final long C0;
  Constant value: long 1l
static final long C1;
  Constant value: long 1000l
static final long C2;
  Constant value: long 1000000l
static final long C3;
  Constant value: long 1000000000l
static final long C4;
  Constant value: long 60000000000l
static final long C5;
  Constant value: long 3600000000000l
static final long C6;
  Constant value: long 86400000000000l
static final long MAX;
  Constant value: long 9223372036854775807l
public static scala.actors.threadpool.TimeUnit[] values();
  Code:
   Stack=1, Locals=0, Args_size=0
   0:	getstatic	#1; //Field values:[Lscala/actors/threadpool/TimeUnit;
   3:	invokevirtual	#2; //Method "[Lscala/actors/threadpool/TimeUnit;".clone:()Ljava/lang/Object;
   6:	checkcast	#3; //class "[Lscala/actors/threadpool/TimeUnit;"
   9:	checkcast	#3; //class "[Lscala/actors/threadpool/TimeUnit;"
   12:	areturn

public static scala.actors.threadpool.TimeUnit valueOf(java.lang.String);
  Code:
   Stack=4, Locals=2, Args_size=1
   0:	iconst_0
   1:	istore_1
   2:	iload_1
   3:	getstatic	#1; //Field values:[Lscala/actors/threadpool/TimeUnit;
   6:	arraylength
   7:	if_icmpge	37
   10:	getstatic	#1; //Field values:[Lscala/actors/threadpool/TimeUnit;
   13:	iload_1
   14:	aaload
   15:	getfield	#4; //Field name:Ljava/lang/String;
   18:	aload_0
   19:	invokevirtual	#5; //Method java/lang/String.equals:(Ljava/lang/Object;)Z
   22:	ifeq	31
   25:	getstatic	#1; //Field values:[Lscala/actors/threadpool/TimeUnit;
   28:	iload_1
   29:	aaload
   30:	areturn
   31:	iinc	1, 1
   34:	goto	2
   37:	new	#6; //class java/lang/IllegalArgumentException
   40:	dup
   41:	new	#7; //class java/lang/StringBuilder
   44:	dup
   45:	invokespecial	#8; //Method java/lang/StringBuilder."<init>":()V
   48:	ldc	#9; //String No enum const TimeUnit.
   50:	invokevirtual	#10; //Method java/lang/StringBuilder.append:(Ljava/lang/String;)Ljava/lang/StringBuilder;
   53:	aload_0
   54:	invokevirtual	#10; //Method java/lang/StringBuilder.append:(Ljava/lang/String;)Ljava/lang/StringBuilder;
   57:	invokevirtual	#11; //Method java/lang/StringBuilder.toString:()Ljava/lang/String;
   60:	invokespecial	#12; //Method java/lang/IllegalArgumentException."<init>":(Ljava/lang/String;)V
   63:	athrow

scala.actors.threadpool.TimeUnit(int, java.lang.String);
  Code:
   Stack=2, Locals=3, Args_size=3
   0:	aload_0
   1:	invokespecial	#13; //Method java/lang/Object."<init>":()V
   4:	aload_0
   5:	iload_1
   6:	putfield	#14; //Field index:I
   9:	aload_0
   10:	aload_2
   11:	putfield	#4; //Field name:Ljava/lang/String;
   14:	return

static long x(long, long, long);
  Code:
   Stack=4, Locals=6, Args_size=3
   0:	lload_0
   1:	lload	4
   3:	lcmp
   4:	ifle	11
   7:	ldc2_w	#15; //long 9223372036854775807l
   10:	lreturn
   11:	lload_0
   12:	lload	4
   14:	lneg
   15:	lcmp
   16:	ifge	23
   19:	ldc2_w	#17; //long -9223372036854775808l
   22:	lreturn
   23:	lload_0
   24:	lload_2
   25:	lmul
   26:	lreturn

public abstract long convert(long, scala.actors.threadpool.TimeUnit);

public abstract long toNanos(long);

public abstract long toMicros(long);

public abstract long toMillis(long);

public abstract long toSeconds(long);

public abstract long toMinutes(long);

public abstract long toHours(long);

public abstract long toDays(long);

abstract int excessNanos(long, long);

public java.lang.String name();
  Code:
   Stack=1, Locals=1, Args_size=1
   0:	aload_0
   1:	getfield	#4; //Field name:Ljava/lang/String;
   4:	areturn

public int ordinal();
  Code:
   Stack=1, Locals=1, Args_size=1
   0:	aload_0
   1:	getfield	#14; //Field index:I
   4:	ireturn

protected java.lang.Object readResolve()   throws java.io.ObjectStreamException;
  Code:
   Stack=4, Locals=2, Args_size=1
   0:	aload_0
   1:	getfield	#4; //Field name:Ljava/lang/String;
   4:	invokestatic	#19; //Method valueOf:(Ljava/lang/String;)Lscala/actors/threadpool/TimeUnit;
   7:	areturn
   8:	astore_1
   9:	new	#20; //class java/io/InvalidObjectException
   12:	dup
   13:	new	#7; //class java/lang/StringBuilder
   16:	dup
   17:	invokespecial	#8; //Method java/lang/StringBuilder."<init>":()V
   20:	aload_0
   21:	getfield	#4; //Field name:Ljava/lang/String;
   24:	invokevirtual	#10; //Method java/lang/StringBuilder.append:(Ljava/lang/String;)Ljava/lang/StringBuilder;
   27:	ldc	#21; //String  is not a valid enum for TimeUnit
   29:	invokevirtual	#10; //Method java/lang/StringBuilder.append:(Ljava/lang/String;)Ljava/lang/StringBuilder;
   32:	invokevirtual	#11; //Method java/lang/StringBuilder.toString:()Ljava/lang/String;
   35:	invokespecial	#22; //Method java/io/InvalidObjectException."<init>":(Ljava/lang/String;)V
   38:	athrow
  Exception table:
   from   to  target type
     0     7     8   Class java/lang/IllegalArgumentException

  Exceptions: 
   throws java.io.ObjectStreamException
public void timedWait(java.lang.Object, long)   throws java.lang.InterruptedException;
  Code:
   Stack=5, Locals=7, Args_size=3
   0:	lload_2
   1:	lconst_0
   2:	lcmp
   3:	ifle	30
   6:	aload_0
   7:	lload_2
   8:	invokevirtual	#23; //Method toMillis:(J)J
   11:	lstore	4
   13:	aload_0
   14:	lload_2
   15:	lload	4
   17:	invokevirtual	#24; //Method excessNanos:(JJ)I
   20:	istore	6
   22:	aload_1
   23:	lload	4
   25:	iload	6
   27:	invokevirtual	#25; //Method java/lang/Object.wait:(JI)V
   30:	return
  Exceptions: 
   throws java.lang.InterruptedException
public void timedJoin(java.lang.Thread, long)   throws java.lang.InterruptedException;
  Code:
   Stack=5, Locals=7, Args_size=3
   0:	lload_2
   1:	lconst_0
   2:	lcmp
   3:	ifle	30
   6:	aload_0
   7:	lload_2
   8:	invokevirtual	#23; //Method toMillis:(J)J
   11:	lstore	4
   13:	aload_0
   14:	lload_2
   15:	lload	4
   17:	invokevirtual	#24; //Method excessNanos:(JJ)I
   20:	istore	6
   22:	aload_1
   23:	lload	4
   25:	iload	6
   27:	invokevirtual	#26; //Method java/lang/Thread.join:(JI)V
   30:	return
  Exceptions: 
   throws java.lang.InterruptedException
public void sleep(long)   throws java.lang.InterruptedException;
  Code:
   Stack=5, Locals=6, Args_size=2
   0:	lload_1
   1:	lconst_0
   2:	lcmp
   3:	ifle	26
   6:	aload_0
   7:	lload_1
   8:	invokevirtual	#23; //Method toMillis:(J)J
   11:	lstore_3
   12:	aload_0
   13:	lload_1
   14:	lload_3
   15:	invokevirtual	#24; //Method excessNanos:(JJ)I
   18:	istore	5
   20:	lload_3
   21:	iload	5
   23:	invokestatic	#27; //Method java/lang/Thread.sleep:(JI)V
   26:	return
  Exceptions: 
   throws java.lang.InterruptedException
public java.lang.String toString();
  Code:
   Stack=1, Locals=1, Args_size=1
   0:	aload_0
   1:	getfield	#4; //Field name:Ljava/lang/String;
   4:	areturn

static {};
  Code:
   Stack=4, Locals=0, Args_size=0
   0:	new	#28; //class scala/actors/threadpool/TimeUnit$1
   3:	dup
   4:	iconst_0
   5:	ldc	#29; //String NANOSECONDS
   7:	invokespecial	#30; //Method scala/actors/threadpool/TimeUnit$1."<init>":(ILjava/lang/String;)V
   10:	putstatic	#31; //Field NANOSECONDS:Lscala/actors/threadpool/TimeUnit;
   13:	new	#32; //class scala/actors/threadpool/TimeUnit$2
   16:	dup
   17:	iconst_1
   18:	ldc	#33; //String MICROSECONDS
   20:	invokespecial	#34; //Method scala/actors/threadpool/TimeUnit$2."<init>":(ILjava/lang/String;)V
   23:	putstatic	#35; //Field MICROSECONDS:Lscala/actors/threadpool/TimeUnit;
   26:	new	#36; //class scala/actors/threadpool/TimeUnit$3
   29:	dup
   30:	iconst_2
   31:	ldc	#37; //String MILLISECONDS
   33:	invokespecial	#38; //Method scala/actors/threadpool/TimeUnit$3."<init>":(ILjava/lang/String;)V
   36:	putstatic	#39; //Field MILLISECONDS:Lscala/actors/threadpool/TimeUnit;
   39:	new	#40; //class scala/actors/threadpool/TimeUnit$4
   42:	dup
   43:	iconst_3
   44:	ldc	#41; //String SECONDS
   46:	invokespecial	#42; //Method scala/actors/threadpool/TimeUnit$4."<init>":(ILjava/lang/String;)V
   49:	putstatic	#43; //Field SECONDS:Lscala/actors/threadpool/TimeUnit;
   52:	new	#44; //class scala/actors/threadpool/TimeUnit$5
   55:	dup
   56:	iconst_4
   57:	ldc	#45; //String MINUTES
   59:	invokespecial	#46; //Method scala/actors/threadpool/TimeUnit$5."<init>":(ILjava/lang/String;)V
   62:	putstatic	#47; //Field MINUTES:Lscala/actors/threadpool/TimeUnit;
   65:	new	#48; //class scala/actors/threadpool/TimeUnit$6
   68:	dup
   69:	iconst_5
   70:	ldc	#49; //String HOURS
   72:	invokespecial	#50; //Method scala/actors/threadpool/TimeUnit$6."<init>":(ILjava/lang/String;)V
   75:	putstatic	#51; //Field HOURS:Lscala/actors/threadpool/TimeUnit;
   78:	new	#52; //class scala/actors/threadpool/TimeUnit$7
   81:	dup
   82:	bipush	6
   84:	ldc	#53; //String DAYS
   86:	invokespecial	#54; //Method scala/actors/threadpool/TimeUnit$7."<init>":(ILjava/lang/String;)V
   89:	putstatic	#55; //Field DAYS:Lscala/actors/threadpool/TimeUnit;
   92:	bipush	7
   94:	anewarray	#56; //class scala/actors/threadpool/TimeUnit
   97:	dup
   98:	iconst_0
   99:	getstatic	#31; //Field NANOSECONDS:Lscala/actors/threadpool/TimeUnit;
   102:	aastore
   103:	dup
   104:	iconst_1
   105:	getstatic	#35; //Field MICROSECONDS:Lscala/actors/threadpool/TimeUnit;
   108:	aastore
   109:	dup
   110:	iconst_2
   111:	getstatic	#39; //Field MILLISECONDS:Lscala/actors/threadpool/TimeUnit;
   114:	aastore
   115:	dup
   116:	iconst_3
   117:	getstatic	#43; //Field SECONDS:Lscala/actors/threadpool/TimeUnit;
   120:	aastore
   121:	dup
   122:	iconst_4
   123:	getstatic	#47; //Field MINUTES:Lscala/actors/threadpool/TimeUnit;
   126:	aastore
   127:	dup
   128:	iconst_5
   129:	getstatic	#51; //Field HOURS:Lscala/actors/threadpool/TimeUnit;
   132:	aastore
   133:	dup
   134:	bipush	6
   136:	getstatic	#55; //Field DAYS:Lscala/actors/threadpool/TimeUnit;
   139:	aastore
   140:	putstatic	#1; //Field values:[Lscala/actors/threadpool/TimeUnit;
   143:	return

}

