class scala.actors.threadpool.TimeUnit$2 extends scala.actors.threadpool.TimeUnit
  EnclosingMethod: length = 0x4
   00 11 00 00 
  InnerClass: 
   class scala/actors/threadpool/TimeUnit$2
  minor version: 0
  major version: 49
  Constant pool:
Method	scala/actors/threadpool/TimeUnit."<init>":(ILjava/lang/String;)V
long	1000l;
long	9223372036854775l;
Method	scala/actors/threadpool/TimeUnit$2.x:(JJJ)J
long	1000000l;
long	60000000l;
long	3600000000l;
long	86400000000l;
Method	scala/actors/threadpool/TimeUnit.toMicros:(J)J
class	scala/actors/threadpool/TimeUnit$2
class	scala/actors/threadpool/TimeUnit
Asciz	serialVersionUID;
Asciz	J;
Asciz	ConstantValue;
long	2185906575929579108l;
Asciz	<init>;
Asciz	(ILjava/lang/String;)V;
Asciz	Code;
Asciz	toNanos;
Asciz	(J)J;
Asciz	toMicros;
Asciz	toMillis;
Asciz	toSeconds;
Asciz	toMinutes;
Asciz	toHours;
Asciz	toDays;
Asciz	convert;
Asciz	(JLscala/actors/threadpool/TimeUnit;)J;
Asciz	excessNanos;
Asciz	(JJ)I;
Asciz	EnclosingMethod;
NameAndType	"<init>":(ILjava/lang/String;)V
NameAndType	x:(JJJ)J
NameAndType	toMicros:(J)J
Asciz	scala/actors/threadpool/TimeUnit$2;
Asciz	;
Asciz	InnerClasses;
Asciz	scala/actors/threadpool/TimeUnit;
Asciz	x;
Asciz	(JJJ)J;

{
private static final long serialVersionUID;
  Signature: J
  Constant value: long 2185906575929579108l
scala.actors.threadpool.TimeUnit$2(int, java.lang.String);
  Signature: (ILjava/lang/String;)V
  Code:
   Stack=3, Locals=3, Args_size=3
	aload_0
	iload_1
	aload_2
	invokespecial	Method scala/actors/threadpool/TimeUnit."<init>":(ILjava/lang/String;)V
	return
  Labels:

public long toNanos(long);
  Signature: (J)J
  Code:
   Stack=6, Locals=3, Args_size=2
	lload_1
	ldc2_w	long 1000l
	ldc2_w	long 9223372036854775l
	invokestatic	Method x:(JJJ)J
	lreturn
  Labels:

public long toMicros(long);
  Signature: (J)J
  Code:
   Stack=2, Locals=3, Args_size=2
	lload_1
	lreturn
  Labels:

public long toMillis(long);
  Signature: (J)J
  Code:
   Stack=4, Locals=3, Args_size=2
	lload_1
	ldc2_w	long 1000l
	ldiv
	lreturn
  Labels:

public long toSeconds(long);
  Signature: (J)J
  Code:
   Stack=4, Locals=3, Args_size=2
	lload_1
	ldc2_w	long 1000000l
	ldiv
	lreturn
  Labels:

public long toMinutes(long);
  Signature: (J)J
  Code:
   Stack=4, Locals=3, Args_size=2
	lload_1
	ldc2_w	long 60000000l
	ldiv
	lreturn
  Labels:

public long toHours(long);
  Signature: (J)J
  Code:
   Stack=4, Locals=3, Args_size=2
	lload_1
	ldc2_w	long 3600000000l
	ldiv
	lreturn
  Labels:

public long toDays(long);
  Signature: (J)J
  Code:
   Stack=4, Locals=3, Args_size=2
	lload_1
	ldc2_w	long 86400000000l
	ldiv
	lreturn
  Labels:

public long convert(long, scala.actors.threadpool.TimeUnit);
  Signature: (JLscala/actors/threadpool/TimeUnit;)J
  Code:
   Stack=3, Locals=4, Args_size=3
	aload_3
	lload_1
	invokevirtual	Method scala/actors/threadpool/TimeUnit.toMicros:(J)J
	lreturn
  Labels:

int excessNanos(long, long);
  Signature: (JJ)I
  Code:
   Stack=6, Locals=5, Args_size=3
	lload_1
	ldc2_w	long 1000l
	lmul
	lload_3
	ldc2_w	long 1000000l
	lmul
	lsub
	l2i
	ireturn
  Labels:

}

