public abstract class scala.actors.threadpool.TimeUnit extends java.lang.Object implements java.io.Serializable
  InnerClass: 
   class scala/actors/threadpool/TimeUnit$1
   class scala/actors/threadpool/TimeUnit$2
   class scala/actors/threadpool/TimeUnit$3
   class scala/actors/threadpool/TimeUnit$4
   class scala/actors/threadpool/TimeUnit$5
   class scala/actors/threadpool/TimeUnit$6
   class scala/actors/threadpool/TimeUnit$7
  minor version: 0
  major version: 49
  Constant pool:
Field	scala/actors/threadpool/TimeUnit.values:[Lscala/actors/threadpool/TimeUnit;
Method	"[Lscala/actors/threadpool/TimeUnit;".clone:()Ljava/lang/Object;
class	"[Lscala/actors/threadpool/TimeUnit;"
Field	scala/actors/threadpool/TimeUnit.name:Ljava/lang/String;
Method	java/lang/String.equals:(Ljava/lang/Object;)Z
class	java/lang/IllegalArgumentException
class	java/lang/StringBuilder
Method	java/lang/StringBuilder."<init>":()V
String	No enum const TimeUnit.
Method	java/lang/StringBuilder.append:(Ljava/lang/String;)Ljava/lang/StringBuilder;
Method	java/lang/StringBuilder.toString:()Ljava/lang/String;
Method	java/lang/IllegalArgumentException."<init>":(Ljava/lang/String;)V
Method	java/lang/Object."<init>":()V
Field	scala/actors/threadpool/TimeUnit.index:I
long	9223372036854775807l;
long	-9223372036854775808l;
Method	scala/actors/threadpool/TimeUnit.valueOf:(Ljava/lang/String;)Lscala/actors/threadpool/TimeUnit;
class	java/io/InvalidObjectException
String	 is not a valid enum for TimeUnit
Method	java/io/InvalidObjectException."<init>":(Ljava/lang/String;)V
Method	scala/actors/threadpool/TimeUnit.toMillis:(J)J
Method	scala/actors/threadpool/TimeUnit.excessNanos:(JJ)I
Method	java/lang/Object.wait:(JI)V
Method	java/lang/Thread.join:(JI)V
Method	java/lang/Thread.sleep:(JI)V
class	scala/actors/threadpool/TimeUnit$1
String	NANOSECONDS
Method	scala/actors/threadpool/TimeUnit$1."<init>":(ILjava/lang/String;)V
Field	scala/actors/threadpool/TimeUnit.NANOSECONDS:Lscala/actors/threadpool/TimeUnit;
class	scala/actors/threadpool/TimeUnit$2
String	MICROSECONDS
Method	scala/actors/threadpool/TimeUnit$2."<init>":(ILjava/lang/String;)V
Field	scala/actors/threadpool/TimeUnit.MICROSECONDS:Lscala/actors/threadpool/TimeUnit;
class	scala/actors/threadpool/TimeUnit$3
String	MILLISECONDS
Method	scala/actors/threadpool/TimeUnit$3."<init>":(ILjava/lang/String;)V
Field	scala/actors/threadpool/TimeUnit.MILLISECONDS:Lscala/actors/threadpool/TimeUnit;
class	scala/actors/threadpool/TimeUnit$4
String	SECONDS
Method	scala/actors/threadpool/TimeUnit$4."<init>":(ILjava/lang/String;)V
Field	scala/actors/threadpool/TimeUnit.SECONDS:Lscala/actors/threadpool/TimeUnit;
class	scala/actors/threadpool/TimeUnit$5
String	MINUTES
Method	scala/actors/threadpool/TimeUnit$5."<init>":(ILjava/lang/String;)V
Field	scala/actors/threadpool/TimeUnit.MINUTES:Lscala/actors/threadpool/TimeUnit;
class	scala/actors/threadpool/TimeUnit$6
String	HOURS
Method	scala/actors/threadpool/TimeUnit$6."<init>":(ILjava/lang/String;)V
Field	scala/actors/threadpool/TimeUnit.HOURS:Lscala/actors/threadpool/TimeUnit;
class	scala/actors/threadpool/TimeUnit$7
String	DAYS
Method	scala/actors/threadpool/TimeUnit$7."<init>":(ILjava/lang/String;)V
Field	scala/actors/threadpool/TimeUnit.DAYS:Lscala/actors/threadpool/TimeUnit;
class	scala/actors/threadpool/TimeUnit
class	java/lang/Object
class	java/io/Serializable
Asciz	NANOSECONDS;
Asciz	Lscala/actors/threadpool/TimeUnit;;
Asciz	MICROSECONDS;
Asciz	MILLISECONDS;
Asciz	SECONDS;
Asciz	MINUTES;
Asciz	HOURS;
Asciz	DAYS;
Asciz	values;
Asciz	[Lscala/actors/threadpool/TimeUnit;;
Asciz	index;
Asciz	I;
Asciz	name;
Asciz	Ljava/lang/String;;
Asciz	C0;
Asciz	J;
Asciz	ConstantValue;
long	1l;
Asciz	C1;
long	1000l;
Asciz	C2;
long	1000000l;
Asciz	C3;
long	1000000000l;
Asciz	C4;
long	60000000000l;
Asciz	C5;
long	3600000000000l;
Asciz	C6;
long	86400000000000l;
Asciz	MAX;
Asciz	()[Lscala/actors/threadpool/TimeUnit;;
Asciz	Code;
Asciz	valueOf;
Asciz	(Ljava/lang/String;)Lscala/actors/threadpool/TimeUnit;;
Asciz	<init>;
Asciz	(ILjava/lang/String;)V;
Asciz	x;
Asciz	(JJJ)J;
Asciz	convert;
Asciz	(JLscala/actors/threadpool/TimeUnit;)J;
Asciz	toNanos;
Asciz	(J)J;
Asciz	toMicros;
Asciz	toMillis;
Asciz	toSeconds;
Asciz	toMinutes;
Asciz	toHours;
Asciz	toDays;
Asciz	excessNanos;
Asciz	(JJ)I;
Asciz	()Ljava/lang/String;;
Asciz	ordinal;
Asciz	()I;
Asciz	readResolve;
Asciz	()Ljava/lang/Object;;
Asciz	Exceptions;
class	java/io/ObjectStreamException
Asciz	timedWait;
Asciz	(Ljava/lang/Object;J)V;
class	java/lang/InterruptedException
Asciz	timedJoin;
Asciz	(Ljava/lang/Thread;J)V;
Asciz	sleep;
Asciz	(J)V;
Asciz	toString;
Asciz	<clinit>;
Asciz	()V;
NameAndType	values:[Lscala/actors/threadpool/TimeUnit;
class	"[Lscala/actors/threadpool/TimeUnit;"
NameAndType	clone:()Ljava/lang/Object;
NameAndType	name:Ljava/lang/String;
class	java/lang/String
NameAndType	equals:(Ljava/lang/Object;)Z
Asciz	java/lang/IllegalArgumentException;
Asciz	java/lang/StringBuilder;
NameAndType	"<init>":()V
Asciz	No enum const TimeUnit.;
NameAndType	append:(Ljava/lang/String;)Ljava/lang/StringBuilder;
NameAndType	toString:()Ljava/lang/String;
NameAndType	"<init>":(Ljava/lang/String;)V
NameAndType	index:I
NameAndType	valueOf:(Ljava/lang/String;)Lscala/actors/threadpool/TimeUnit;
Asciz	java/io/InvalidObjectException;
Asciz	 is not a valid enum for TimeUnit;
NameAndType	toMillis:(J)J
NameAndType	excessNanos:(JJ)I
NameAndType	wait:(JI)V
class	java/lang/Thread
NameAndType	join:(JI)V
NameAndType	sleep:(JI)V
Asciz	scala/actors/threadpool/TimeUnit$1;
Asciz	;
Asciz	InnerClasses;
NameAndType	"<init>":(ILjava/lang/String;)V
NameAndType	NANOSECONDS:Lscala/actors/threadpool/TimeUnit;
Asciz	scala/actors/threadpool/TimeUnit$2;
NameAndType	MICROSECONDS:Lscala/actors/threadpool/TimeUnit;
Asciz	scala/actors/threadpool/TimeUnit$3;
NameAndType	MILLISECONDS:Lscala/actors/threadpool/TimeUnit;
Asciz	scala/actors/threadpool/TimeUnit$4;
NameAndType	SECONDS:Lscala/actors/threadpool/TimeUnit;
Asciz	scala/actors/threadpool/TimeUnit$5;
NameAndType	MINUTES:Lscala/actors/threadpool/TimeUnit;
Asciz	scala/actors/threadpool/TimeUnit$6;
NameAndType	HOURS:Lscala/actors/threadpool/TimeUnit;
Asciz	scala/actors/threadpool/TimeUnit$7;
NameAndType	DAYS:Lscala/actors/threadpool/TimeUnit;
Asciz	scala/actors/threadpool/TimeUnit;
Asciz	java/lang/Object;
Asciz	java/io/Serializable;
Asciz	java/io/ObjectStreamException;
Asciz	java/lang/InterruptedException;
Asciz	clone;
Asciz	java/lang/String;
Asciz	equals;
Asciz	(Ljava/lang/Object;)Z;
Asciz	append;
Asciz	(Ljava/lang/String;)Ljava/lang/StringBuilder;;
Asciz	(Ljava/lang/String;)V;
Asciz	wait;
Asciz	(JI)V;
Asciz	java/lang/Thread;
Asciz	join;

{
public static final scala.actors.threadpool.TimeUnit NANOSECONDS;
  Signature: Lscala/actors/threadpool/TimeUnit;

public static final scala.actors.threadpool.TimeUnit MICROSECONDS;
  Signature: Lscala/actors/threadpool/TimeUnit;

public static final scala.actors.threadpool.TimeUnit MILLISECONDS;
  Signature: Lscala/actors/threadpool/TimeUnit;

public static final scala.actors.threadpool.TimeUnit SECONDS;
  Signature: Lscala/actors/threadpool/TimeUnit;

public static final scala.actors.threadpool.TimeUnit MINUTES;
  Signature: Lscala/actors/threadpool/TimeUnit;

public static final scala.actors.threadpool.TimeUnit HOURS;
  Signature: Lscala/actors/threadpool/TimeUnit;

public static final scala.actors.threadpool.TimeUnit DAYS;
  Signature: Lscala/actors/threadpool/TimeUnit;

private static final scala.actors.threadpool.TimeUnit[] values;
  Signature: [Lscala/actors/threadpool/TimeUnit;

private final int index;
  Signature: I

private final java.lang.String name;
  Signature: Ljava/lang/String;

static final long C0;
  Signature: J
  Constant value: long 1l
static final long C1;
  Signature: J
  Constant value: long 1000l
static final long C2;
  Signature: J
  Constant value: long 1000000l
static final long C3;
  Signature: J
  Constant value: long 1000000000l
static final long C4;
  Signature: J
  Constant value: long 60000000000l
static final long C5;
  Signature: J
  Constant value: long 3600000000000l
static final long C6;
  Signature: J
  Constant value: long 86400000000000l
static final long MAX;
  Signature: J
  Constant value: long 9223372036854775807l
public static scala.actors.threadpool.TimeUnit[] values();
  Signature: ()[Lscala/actors/threadpool/TimeUnit;
  Code:
   Stack=1, Locals=0, Args_size=0
	getstatic	Field values:[Lscala/actors/threadpool/TimeUnit;
	invokevirtual	Method "[Lscala/actors/threadpool/TimeUnit;".clone:()Ljava/lang/Object;
	checkcast	class "[Lscala/actors/threadpool/TimeUnit;"
	checkcast	class "[Lscala/actors/threadpool/TimeUnit;"
	areturn
  Labels:

public static scala.actors.threadpool.TimeUnit valueOf(java.lang.String);
  Signature: (Ljava/lang/String;)Lscala/actors/threadpool/TimeUnit;
  Code:
   Stack=4, Locals=2, Args_size=1
	iconst_0
	istore_1
l3	iload_1
	getstatic	Field values:[Lscala/actors/threadpool/TimeUnit;
	arraylength
	if_icmpge	l1 // new
	getstatic	Field values:[Lscala/actors/threadpool/TimeUnit;
	iload_1
	aaload
	getfield	Field name:Ljava/lang/String;
	aload_0
	invokevirtual	Method java/lang/String.equals:(Ljava/lang/Object;)Z
	ifeq	l2 // iinc
	getstatic	Field values:[Lscala/actors/threadpool/TimeUnit;
	iload_1
	aaload
	areturn
l2	iinc	1, 1
	goto	l3 // iload_1
l1	new	class java/lang/IllegalArgumentException
	dup
	new	class java/lang/StringBuilder
	dup
	invokespecial	Method java/lang/StringBuilder."<init>":()V
	ldc	String No enum const TimeUnit.
	invokevirtual	Method java/lang/StringBuilder.append:(Ljava/lang/String;)Ljava/lang/StringBuilder;
	aload_0
	invokevirtual	Method java/lang/StringBuilder.append:(Ljava/lang/String;)Ljava/lang/StringBuilder;
	invokevirtual	Method java/lang/StringBuilder.toString:()Ljava/lang/String;
	invokespecial	Method java/lang/IllegalArgumentException."<init>":(Ljava/lang/String;)V
	athrow
  Labels:
   	l3 = 2 // iload_1
   	l2 = 31 // iinc
   	l1 = 37 // new

scala.actors.threadpool.TimeUnit(int, java.lang.String);
  Signature: (ILjava/lang/String;)V
  Code:
   Stack=2, Locals=3, Args_size=3
	aload_0
	invokespecial	Method java/lang/Object."<init>":()V
	aload_0
	iload_1
	putfield	Field index:I
	aload_0
	aload_2
	putfield	Field name:Ljava/lang/String;
	return
  Labels:

static long x(long, long, long);
  Signature: (JJJ)J
  Code:
   Stack=4, Locals=6, Args_size=3
	lload_0
	lload	4
	lcmp
	ifle	l1 // lload_0
	ldc2_w	long 9223372036854775807l
	lreturn
l1	lload_0
	lload	4
	lneg
	lcmp
	ifge	l2 // lload_0
	ldc2_w	long -9223372036854775808l
	lreturn
l2	lload_0
	lload_2
	lmul
	lreturn
  Labels:
   	l1 = 11 // lload_0
   	l2 = 23 // lload_0

public abstract long convert(long, scala.actors.threadpool.TimeUnit);
  Signature: (JLscala/actors/threadpool/TimeUnit;)J

public abstract long toNanos(long);
  Signature: (J)J

public abstract long toMicros(long);
  Signature: (J)J

public abstract long toMillis(long);
  Signature: (J)J

public abstract long toSeconds(long);
  Signature: (J)J

public abstract long toMinutes(long);
  Signature: (J)J

public abstract long toHours(long);
  Signature: (J)J

public abstract long toDays(long);
  Signature: (J)J

abstract int excessNanos(long, long);
  Signature: (JJ)I

public java.lang.String name();
  Signature: ()Ljava/lang/String;
  Code:
   Stack=1, Locals=1, Args_size=1
	aload_0
	getfield	Field name:Ljava/lang/String;
	areturn
  Labels:

public int ordinal();
  Signature: ()I
  Code:
   Stack=1, Locals=1, Args_size=1
	aload_0
	getfield	Field index:I
	ireturn
  Labels:

protected java.lang.Object readResolve()   throws java.io.ObjectStreamException;
  Signature: ()Ljava/lang/Object;
  Code:
   Stack=4, Locals=2, Args_size=1
	aload_0
	getfield	Field name:Ljava/lang/String;
	invokestatic	Method valueOf:(Ljava/lang/String;)Lscala/actors/threadpool/TimeUnit;
	areturn
	astore_1
	new	class java/io/InvalidObjectException
	dup
	new	class java/lang/StringBuilder
	dup
	invokespecial	Method java/lang/StringBuilder."<init>":()V
	aload_0
	getfield	Field name:Ljava/lang/String;
	invokevirtual	Method java/lang/StringBuilder.append:(Ljava/lang/String;)Ljava/lang/StringBuilder;
	ldc	String  is not a valid enum for TimeUnit
	invokevirtual	Method java/lang/StringBuilder.append:(Ljava/lang/String;)Ljava/lang/StringBuilder;
	invokevirtual	Method java/lang/StringBuilder.toString:()Ljava/lang/String;
	invokespecial	Method java/io/InvalidObjectException."<init>":(Ljava/lang/String;)V
	athrow
  Labels:
  Exception table:
   from   to  target type
     0     7     8   Class java/lang/IllegalArgumentException

  Exceptions: 
   throws java.io.ObjectStreamException
public void timedWait(java.lang.Object, long)   throws java.lang.InterruptedException;
  Signature: (Ljava/lang/Object;J)V
  Code:
   Stack=5, Locals=7, Args_size=3
	lload_2
	lconst_0
	lcmp
	ifle	l1 // return
	aload_0
	lload_2
	invokevirtual	Method toMillis:(J)J
	lstore	4
	aload_0
	lload_2
	lload	4
	invokevirtual	Method excessNanos:(JJ)I
	istore	6
	aload_1
	lload	4
	iload	6
	invokevirtual	Method java/lang/Object.wait:(JI)V
l1	return
  Labels:
   	l1 = 30 // return
  Exceptions: 
   throws java.lang.InterruptedException
public void timedJoin(java.lang.Thread, long)   throws java.lang.InterruptedException;
  Signature: (Ljava/lang/Thread;J)V
  Code:
   Stack=5, Locals=7, Args_size=3
	lload_2
	lconst_0
	lcmp
	ifle	l1 // return
	aload_0
	lload_2
	invokevirtual	Method toMillis:(J)J
	lstore	4
	aload_0
	lload_2
	lload	4
	invokevirtual	Method excessNanos:(JJ)I
	istore	6
	aload_1
	lload	4
	iload	6
	invokevirtual	Method java/lang/Thread.join:(JI)V
l1	return
  Labels:
   	l1 = 30 // return
  Exceptions: 
   throws java.lang.InterruptedException
public void sleep(long)   throws java.lang.InterruptedException;
  Signature: (J)V
  Code:
   Stack=5, Locals=6, Args_size=2
	lload_1
	lconst_0
	lcmp
	ifle	l1 // return
	aload_0
	lload_1
	invokevirtual	Method toMillis:(J)J
	lstore_3
	aload_0
	lload_1
	lload_3
	invokevirtual	Method excessNanos:(JJ)I
	istore	5
	lload_3
	iload	5
	invokestatic	Method java/lang/Thread.sleep:(JI)V
l1	return
  Labels:
   	l1 = 26 // return
  Exceptions: 
   throws java.lang.InterruptedException
public java.lang.String toString();
  Signature: ()Ljava/lang/String;
  Code:
   Stack=1, Locals=1, Args_size=1
	aload_0
	getfield	Field name:Ljava/lang/String;
	areturn
  Labels:

static {};
  Signature: ()V
  Code:
   Stack=4, Locals=0, Args_size=0
	new	class scala/actors/threadpool/TimeUnit$1
	dup
	iconst_0
	ldc	String NANOSECONDS
	invokespecial	Method scala/actors/threadpool/TimeUnit$1."<init>":(ILjava/lang/String;)V
	putstatic	Field NANOSECONDS:Lscala/actors/threadpool/TimeUnit;
	new	class scala/actors/threadpool/TimeUnit$2
	dup
	iconst_1
	ldc	String MICROSECONDS
	invokespecial	Method scala/actors/threadpool/TimeUnit$2."<init>":(ILjava/lang/String;)V
	putstatic	Field MICROSECONDS:Lscala/actors/threadpool/TimeUnit;
	new	class scala/actors/threadpool/TimeUnit$3
	dup
	iconst_2
	ldc	String MILLISECONDS
	invokespecial	Method scala/actors/threadpool/TimeUnit$3."<init>":(ILjava/lang/String;)V
	putstatic	Field MILLISECONDS:Lscala/actors/threadpool/TimeUnit;
	new	class scala/actors/threadpool/TimeUnit$4
	dup
	iconst_3
	ldc	String SECONDS
	invokespecial	Method scala/actors/threadpool/TimeUnit$4."<init>":(ILjava/lang/String;)V
	putstatic	Field SECONDS:Lscala/actors/threadpool/TimeUnit;
	new	class scala/actors/threadpool/TimeUnit$5
	dup
	iconst_4
	ldc	String MINUTES
	invokespecial	Method scala/actors/threadpool/TimeUnit$5."<init>":(ILjava/lang/String;)V
	putstatic	Field MINUTES:Lscala/actors/threadpool/TimeUnit;
	new	class scala/actors/threadpool/TimeUnit$6
	dup
	iconst_5
	ldc	String HOURS
	invokespecial	Method scala/actors/threadpool/TimeUnit$6."<init>":(ILjava/lang/String;)V
	putstatic	Field HOURS:Lscala/actors/threadpool/TimeUnit;
	new	class scala/actors/threadpool/TimeUnit$7
	dup
	bipush	6
	ldc	String DAYS
	invokespecial	Method scala/actors/threadpool/TimeUnit$7."<init>":(ILjava/lang/String;)V
	putstatic	Field DAYS:Lscala/actors/threadpool/TimeUnit;
	bipush	7
	anewarray	class scala/actors/threadpool/TimeUnit
	dup
	iconst_0
	getstatic	Field NANOSECONDS:Lscala/actors/threadpool/TimeUnit;
	aastore
	dup
	iconst_1
	getstatic	Field MICROSECONDS:Lscala/actors/threadpool/TimeUnit;
	aastore
	dup
	iconst_2
	getstatic	Field MILLISECONDS:Lscala/actors/threadpool/TimeUnit;
	aastore
	dup
	iconst_3
	getstatic	Field SECONDS:Lscala/actors/threadpool/TimeUnit;
	aastore
	dup
	iconst_4
	getstatic	Field MINUTES:Lscala/actors/threadpool/TimeUnit;
	aastore
	dup
	iconst_5
	getstatic	Field HOURS:Lscala/actors/threadpool/TimeUnit;
	aastore
	dup
	bipush	6
	getstatic	Field DAYS:Lscala/actors/threadpool/TimeUnit;
	aastore
	putstatic	Field values:[Lscala/actors/threadpool/TimeUnit;
	return
  Labels:

}

