class scala.actors.threadpool.TimeUnit$2 extends scala.actors.threadpool.TimeUnit
  EnclosingMethod: length = 0x4
   00 11 00 00 
  InnerClass: 
   #16; //class scala/actors/threadpool/TimeUnit$2
  minor version: 0
  major version: 49
  Constant pool:
const #1 = Method	#17.#39;	//  scala/actors/threadpool/TimeUnit."<init>":(ILjava/lang/String;)V
const #2 = long	1000l;
const #4 = long	9223372036854775l;
const #6 = Method	#16.#40;	//  scala/actors/threadpool/TimeUnit$2.x:(JJJ)J
const #7 = long	1000000l;
const #9 = long	60000000l;
const #11 = long	3600000000l;
const #13 = long	86400000000l;
const #15 = Method	#17.#41;	//  scala/actors/threadpool/TimeUnit.toMicros:(J)J
const #16 = class	#42;	//  scala/actors/threadpool/TimeUnit$2
const #17 = class	#45;	//  scala/actors/threadpool/TimeUnit
const #18 = Asciz	serialVersionUID;
const #19 = Asciz	J;
const #20 = Asciz	ConstantValue;
const #21 = long	2185906575929579108l;
const #23 = Asciz	<init>;
const #24 = Asciz	(ILjava/lang/String;)V;
const #25 = Asciz	Code;
const #26 = Asciz	toNanos;
const #27 = Asciz	(J)J;
const #28 = Asciz	toMicros;
const #29 = Asciz	toMillis;
const #30 = Asciz	toSeconds;
const #31 = Asciz	toMinutes;
const #32 = Asciz	toHours;
const #33 = Asciz	toDays;
const #34 = Asciz	convert;
const #35 = Asciz	(JLscala/actors/threadpool/TimeUnit;)J;
const #36 = Asciz	excessNanos;
const #37 = Asciz	(JJ)I;
const #38 = Asciz	EnclosingMethod;
const #39 = NameAndType	#23:#24;//  "<init>":(ILjava/lang/String;)V
const #40 = NameAndType	#46:#47;//  x:(JJJ)J
const #41 = NameAndType	#28:#27;//  toMicros:(J)J
const #42 = Asciz	scala/actors/threadpool/TimeUnit$2;
const #43 = Asciz	;
const #44 = Asciz	InnerClasses;
const #45 = Asciz	scala/actors/threadpool/TimeUnit;
const #46 = Asciz	x;
const #47 = Asciz	(JJJ)J;

{
scala.actors.threadpool.TimeUnit$2(int, java.lang.String);
  Code:
   Stack=3, Locals=3, Args_size=3
   0:	aload_0
   1:	iload_1
   2:	aload_2
   3:	invokespecial	#1; //Method scala/actors/threadpool/TimeUnit."<init>":(ILjava/lang/String;)V
   6:	return

public long toNanos(long);
  Code:
   Stack=6, Locals=3, Args_size=2
   0:	lload_1
   1:	ldc2_w	#2; //long 1000l
   4:	ldc2_w	#4; //long 9223372036854775l
   7:	invokestatic	#6; //Method x:(JJJ)J
   10:	lreturn

public long toMicros(long);
  Code:
   Stack=2, Locals=3, Args_size=2
   0:	lload_1
   1:	lreturn

public long toMillis(long);
  Code:
   Stack=4, Locals=3, Args_size=2
   0:	lload_1
   1:	ldc2_w	#2; //long 1000l
   4:	ldiv
   5:	lreturn

public long toSeconds(long);
  Code:
   Stack=4, Locals=3, Args_size=2
   0:	lload_1
   1:	ldc2_w	#7; //long 1000000l
   4:	ldiv
   5:	lreturn

public long toMinutes(long);
  Code:
   Stack=4, Locals=3, Args_size=2
   0:	lload_1
   1:	ldc2_w	#9; //long 60000000l
   4:	ldiv
   5:	lreturn

public long toHours(long);
  Code:
   Stack=4, Locals=3, Args_size=2
   0:	lload_1
   1:	ldc2_w	#11; //long 3600000000l
   4:	ldiv
   5:	lreturn

public long toDays(long);
  Code:
   Stack=4, Locals=3, Args_size=2
   0:	lload_1
   1:	ldc2_w	#13; //long 86400000000l
   4:	ldiv
   5:	lreturn

public long convert(long, scala.actors.threadpool.TimeUnit);
  Code:
   Stack=3, Locals=4, Args_size=3
   0:	aload_3
   1:	lload_1
   2:	invokevirtual	#15; //Method scala/actors/threadpool/TimeUnit.toMicros:(J)J
   5:	lreturn

int excessNanos(long, long);
  Code:
   Stack=6, Locals=5, Args_size=3
   0:	lload_1
   1:	ldc2_w	#2; //long 1000l
   4:	lmul
   5:	lload_3
   6:	ldc2_w	#7; //long 1000000l
   9:	lmul
   10:	lsub
   11:	l2i
   12:	ireturn

}

