Compiled from "CharSequenceReader.scala"
public class scala.util.parsing.input.CharSequenceReader extends scala.util.parsing.input.Reader implements scala.ScalaObject
  SourceFile: "CharSequenceReader.scala"
  Signature: length = 0x2
   00 52 
  ScalaSig: length = 0x23F
   05 00 5D 07 05 01 02 FFFFFF88 02 0B 01 12 43 68 61 72
   53 65 71 75 65 6E 63 65 52 65 61 64 65 72 0A 02
   03 04 01 05 69 6E 70 75 74 0A 02 05 06 01 07 70
   61 72 73 69 6E 67 0A 02 07 08 01 04 75 74 69 6C
   0A 01 09 01 05 73 63 61 6C 61 03 00 10 02 0C 0D
   0D 01 02 06 08 0E 02 FFFFFF84 FFFFFF80 FFFFFF80 FFFFFF88 02 0F 02 12 43
   68 61 72 53 65 71 75 65 6E 63 65 52 65 61 64 65
   72 13 03 0D 10 18 10 02 11 16 0D 01 12 0A 02 13
   14 01 04 6C 61 6E 67 0A 01 15 01 04 6A 61 76 61
   09 02 17 12 02 06 4F 62 6A 65 63 74 10 02 19 1A
   0D 01 08 09 02 1B 08 02 0B 53 63 61 6C 61 4F 62
   6A 65 63 74 08 05 1D 0D FFFFFF84 00 1E 01 06 3C 69 6E
   69 74 3E 14 01 0B 08 07 20 0D FFFFFFC2 FFFFFF80 FFFFFF84 02 21 01
   05 45 6F 66 43 68 15 01 22 0F 01 23 1C 01 1A 08
   06 25 0D FFFFFFA0 FFFFFF80 06 22 01 06 45 6F 66 43 68 20 06
   08 0E 02 FFFFFF84 FFFFFF80 FFFFFF80 FFFFFF80 00 27 13 03 26 28 18 10 03
   0C 29 2B 09 02 2A 02 02 06 52 65 61 64 65 72 10
   02 19 2C 09 02 2D 08 02 04 43 68 61 72 08 08 2F
   26 FFFFFF82 FFFFFFC2 FFFFFF80 FFFFFF84 20 30 01 06 73 6F 75 72 63 65 15
   01 31 10 02 11 32 09 02 33 12 02 0C 43 68 61 72
   53 65 71 75 65 6E 63 65 08 08 35 26 FFFFFF82 FFFFFF80 FFFFFFA0 FFFFFF80
   04 31 01 07 73 6F 75 72 63 65 20 08 08 37 26 FFFFFF82
   FFFFFFC2 FFFFFF80 FFFFFF84 20 38 01 06 6F 66 66 73 65 74 15 01 39
   10 02 19 3A 09 02 3B 08 02 03 49 6E 74 08 08 3D
   26 FFFFFF82 FFFFFF80 FFFFFFA0 FFFFFF80 04 39 01 07 6F 66 66 73 65 74 20
   08 05 1D 26 FFFFFF84 00 3F 14 03 40 41 42 10 02 0C 26
   08 05 2F 3E FFFFFFC0 00 31 08 05 37 3E FFFFFFC0 00 39 08 05
   1D 26 FFFFFF84 00 44 14 02 40 45 08 05 2F 43 FFFFFFC0 00 31
   08 05 47 26 FFFFFF84 00 48 01 05 66 69 72 73 74 15 01
   2B 08 05 4A 26 FFFFFF84 00 4B 01 04 72 65 73 74 15 01
   40 08 05 4D 26 FFFFFF84 00 4E 01 03 70 6F 73 15 01 4F
   10 02 0C 50 09 02 51 02 02 08 50 6F 73 69 74 69
   6F 6E 08 05 53 26 FFFFFF84 00 54 01 05 61 74 45 6E 64
   15 01 55 10 02 19 56 09 02 57 08 02 07 42 6F 6F
   6C 65 61 6E 08 05 59 26 FFFFFF84 20 5A 01 04 64 72 6F
   70 14 02 40 5B 08 05 5C 58 FFFFFFC0 00 39 01 01 6E 
  minor version: 0
  major version: 49
  Constant pool:
Asciz	SourceFile;
Asciz	CharSequenceReader.scala;
Asciz	EofCh;
Asciz	()C;
Asciz	Code;
Asciz	scala/util/parsing/input/CharSequenceReader$;
class	scala/util/parsing/input/CharSequenceReader$
Asciz	MODULE$;
Asciz	Lscala/util/parsing/input/CharSequenceReader$;;
NameAndType	MODULE$:Lscala/util/parsing/input/CharSequenceReader$;
Field	scala/util/parsing/input/CharSequenceReader$.MODULE$:Lscala/util/parsing/input/CharSequenceReader$;
NameAndType	EofCh:()C
Method	scala/util/parsing/input/CharSequenceReader$.EofCh:()C
Asciz	offset;
Asciz	I;
Asciz	source;
Asciz	Ljava/lang/CharSequence;;
Asciz	()Ljava/lang/CharSequence;;
Asciz	LineNumberTable;
Asciz	scala/util/parsing/input/CharSequenceReader;
class	scala/util/parsing/input/CharSequenceReader
NameAndType	source:Ljava/lang/CharSequence;
Field	scala/util/parsing/input/CharSequenceReader.source:Ljava/lang/CharSequence;
Asciz	()I;
NameAndType	offset:I
Field	scala/util/parsing/input/CharSequenceReader.offset:I
Asciz	<init>;
Asciz	(Ljava/lang/CharSequence;)V;
Asciz	(Ljava/lang/CharSequence;I)V;
NameAndType	"<init>":(Ljava/lang/CharSequence;I)V
Method	scala/util/parsing/input/CharSequenceReader."<init>":(Ljava/lang/CharSequence;I)V
Asciz	this;
Asciz	Lscala/util/parsing/input/CharSequenceReader;;
Asciz	LocalVariableTable;
Asciz	first;
NameAndType	offset:()I
Method	scala/util/parsing/input/CharSequenceReader.offset:()I
NameAndType	source:()Ljava/lang/CharSequence;
Method	scala/util/parsing/input/CharSequenceReader.source:()Ljava/lang/CharSequence;
Asciz	java/lang/CharSequence;
class	java/lang/CharSequence
Asciz	length;
NameAndType	length:()I
InterfaceMethod	java/lang/CharSequence.length:()I
Asciz	charAt;
Asciz	(I)C;
NameAndType	charAt:(I)C
InterfaceMethod	java/lang/CharSequence.charAt:(I)C
int	26;
Asciz	rest;
Asciz	()Lscala/util/parsing/input/CharSequenceReader;;
Asciz	pos;
Asciz	()Lscala/util/parsing/input/Position;;
Asciz	scala/util/parsing/input/OffsetPosition;
class	scala/util/parsing/input/OffsetPosition
Method	scala/util/parsing/input/OffsetPosition."<init>":(Ljava/lang/CharSequence;I)V
Asciz	atEnd;
Asciz	()Z;
Asciz	drop;
Asciz	(I)Lscala/util/parsing/input/CharSequenceReader;;
Asciz	n;
Asciz	(I)Lscala/util/parsing/input/Reader;;
NameAndType	drop:(I)Lscala/util/parsing/input/CharSequenceReader;
Method	scala/util/parsing/input/CharSequenceReader.drop:(I)Lscala/util/parsing/input/CharSequenceReader;
Asciz	()Lscala/util/parsing/input/Reader;;
NameAndType	rest:()Lscala/util/parsing/input/CharSequenceReader;
Method	scala/util/parsing/input/CharSequenceReader.rest:()Lscala/util/parsing/input/CharSequenceReader;
Asciz	()Ljava/lang/Object;;
NameAndType	first:()C
Method	scala/util/parsing/input/CharSequenceReader.first:()C
Asciz	scala/runtime/BoxesRunTime;
class	scala/runtime/BoxesRunTime
Asciz	boxToCharacter;
Asciz	(C)Ljava/lang/Character;;
NameAndType	boxToCharacter:(C)Ljava/lang/Character;
Method	scala/runtime/BoxesRunTime.boxToCharacter:(C)Ljava/lang/Character;
Asciz	scala/util/parsing/input/Reader;
class	scala/util/parsing/input/Reader
Asciz	()V;
NameAndType	"<init>":()V
Method	scala/util/parsing/input/Reader."<init>":()V
Asciz	Lscala/util/parsing/input/Reader<Ljava/lang/Character;>;Lscala/ScalaObject;;
Asciz	Signature;
Asciz	ScalaSig;
Asciz	scala/ScalaObject;
class	scala/ScalaObject

{
private final int offset;
  Signature: I

private final java.lang.CharSequence source;
  Signature: Ljava/lang/CharSequence;

public static final char EofCh();
  Signature: ()C
  Code:
   Stack=1, Locals=0, Args_size=0
	getstatic	Field scala/util/parsing/input/CharSequenceReader$.MODULE$:Lscala/util/parsing/input/CharSequenceReader$;
	invokevirtual	Method scala/util/parsing/input/CharSequenceReader$.EofCh:()C
	ireturn
  Labels:

public java.lang.CharSequence source();
  Signature: ()Ljava/lang/CharSequence;
  Code:
   Stack=1, Locals=1, Args_size=1
	aload_0
	getfield	Field source:Ljava/lang/CharSequence;
	areturn
  Labels:

public int offset();
  Signature: ()I
  Code:
   Stack=1, Locals=1, Args_size=1
	aload_0
	getfield	Field offset:I
	ireturn
  Labels:

public scala.util.parsing.input.CharSequenceReader(java.lang.CharSequence);
  Signature: (Ljava/lang/CharSequence;)V
  Code:
   Stack=3, Locals=2, Args_size=2
	aload_0
	aload_1
	iconst_0
	invokespecial	Method "<init>":(Ljava/lang/CharSequence;I)V
	return
  Labels:
  LocalVariableTable: 
   Start  Length  Slot  Name   Signature
   0      7      0    this       Lscala/util/parsing/input/CharSequenceReader;
   0      7      1    source       Ljava/lang/CharSequence;


public char first();
  Signature: ()C
  Code:
   Stack=2, Locals=1, Args_size=1
	aload_0
	invokevirtual	Method offset:()I
	aload_0
	invokevirtual	Method source:()Ljava/lang/CharSequence;
	invokeinterface	InterfaceMethod java/lang/CharSequence.length:()I
	if_icmpge	l1 // ldc
	aload_0
	invokevirtual	Method source:()Ljava/lang/CharSequence;
	aload_0
	invokevirtual	Method offset:()I
	invokeinterface	InterfaceMethod java/lang/CharSequence.charAt:(I)C
	goto	l2 // ireturn
l1	ldc	int 26
l2	ireturn
  Labels:
   	l1 = 32 // ldc
   	l2 = 34 // ireturn

public scala.util.parsing.input.CharSequenceReader rest();
  Signature: ()Lscala/util/parsing/input/CharSequenceReader;
  Code:
   Stack=5, Locals=1, Args_size=1
	aload_0
	invokevirtual	Method offset:()I
	aload_0
	invokevirtual	Method source:()Ljava/lang/CharSequence;
	invokeinterface	InterfaceMethod java/lang/CharSequence.length:()I
	if_icmpge	l1 // aload_0
	new	class scala/util/parsing/input/CharSequenceReader
	dup
	aload_0
	invokevirtual	Method source:()Ljava/lang/CharSequence;
	aload_0
	invokevirtual	Method offset:()I
	iconst_1
	iadd
	invokespecial	Method "<init>":(Ljava/lang/CharSequence;I)V
	goto	l2 // areturn
l1	aload_0
l2	areturn
  Labels:
   	l1 = 36 // aload_0
   	l2 = 37 // areturn

public scala.util.parsing.input.Position pos();
  Signature: ()Lscala/util/parsing/input/Position;
  Code:
   Stack=4, Locals=1, Args_size=1
	new	class scala/util/parsing/input/OffsetPosition
	dup
	aload_0
	invokevirtual	Method source:()Ljava/lang/CharSequence;
	aload_0
	invokevirtual	Method offset:()I
	invokespecial	Method scala/util/parsing/input/OffsetPosition."<init>":(Ljava/lang/CharSequence;I)V
	areturn
  Labels:

public boolean atEnd();
  Signature: ()Z
  Code:
   Stack=2, Locals=1, Args_size=1
	aload_0
	invokevirtual	Method offset:()I
	aload_0
	invokevirtual	Method source:()Ljava/lang/CharSequence;
	invokeinterface	InterfaceMethod java/lang/CharSequence.length:()I
	if_icmplt	l1 // iconst_0
	iconst_1
	goto	l2 // ireturn
l1	iconst_0
l2	ireturn
  Labels:
   	l1 = 20 // iconst_0
   	l2 = 21 // ireturn

public scala.util.parsing.input.CharSequenceReader drop(int);
  Signature: (I)Lscala/util/parsing/input/CharSequenceReader;
  Code:
   Stack=5, Locals=2, Args_size=2
	new	class scala/util/parsing/input/CharSequenceReader
	dup
	aload_0
	invokevirtual	Method source:()Ljava/lang/CharSequence;
	aload_0
	invokevirtual	Method offset:()I
	iload_1
	iadd
	invokespecial	Method "<init>":(Ljava/lang/CharSequence;I)V
	areturn
  Labels:
  LocalVariableTable: 
   Start  Length  Slot  Name   Signature
   0      18      0    this       Lscala/util/parsing/input/CharSequenceReader;
   0      18      1    n       I


public scala.util.parsing.input.Reader drop(int);
  Signature: (I)Lscala/util/parsing/input/Reader;
  Code:
   Stack=2, Locals=2, Args_size=2
	aload_0
	iload_1
	invokevirtual	Method drop:(I)Lscala/util/parsing/input/CharSequenceReader;
	areturn
  Labels:
  LocalVariableTable: 
   Start  Length  Slot  Name   Signature
   0      6      0    this       Lscala/util/parsing/input/CharSequenceReader;
   0      6      1    n       I


public scala.util.parsing.input.Reader rest();
  Signature: ()Lscala/util/parsing/input/Reader;
  Code:
   Stack=1, Locals=1, Args_size=1
	aload_0
	invokevirtual	Method rest:()Lscala/util/parsing/input/CharSequenceReader;
	areturn
  Labels:

public java.lang.Object first();
  Signature: ()Ljava/lang/Object;
  Code:
   Stack=1, Locals=2, Args_size=1
	aload_0
	invokevirtual	Method first:()C
	istore_1
	iload_1
	invokestatic	Method scala/runtime/BoxesRunTime.boxToCharacter:(C)Ljava/lang/Character;
	areturn
  Labels:

public scala.util.parsing.input.CharSequenceReader(java.lang.CharSequence, int);
  Signature: (Ljava/lang/CharSequence;I)V
  Code:
   Stack=2, Locals=3, Args_size=3
	aload_0
	aload_1
	putfield	Field source:Ljava/lang/CharSequence;
	aload_0
	iload_2
	putfield	Field offset:I
	aload_0
	invokespecial	Method scala/util/parsing/input/Reader."<init>":()V
	return
  Labels:
  LocalVariableTable: 
   Start  Length  Slot  Name   Signature
   0      15      0    this       Lscala/util/parsing/input/CharSequenceReader;
   0      15      1    source       Ljava/lang/CharSequence;
   0      15      2    offset       I


}

