Compiled from "CharArrayPosition.scala"
public class scala.util.parsing.input.CharArrayPosition extends java.lang.Object implements scala.util.parsing.input.Position,scala.ScalaObject
  SourceFile: "CharArrayPosition.scala"
  ScalaSig: length = 0x1D1
   05 00 46 06 08 01 02 FFFFFF84 FFFFFF80 FFFFFF80 FFFFFF80 00 0B 02 11 43
   68 61 72 41 72 72 61 79 50 6F 73 69 74 69 6F 6E
   0A 02 03 04 01 05 69 6E 70 75 74 0A 02 05 06 01
   07 70 61 72 73 69 6E 67 0A 02 07 08 01 04 75 74
   69 6C 0A 01 09 01 05 73 63 61 6C 61 03 00 13 04
   00 0C 14 18 10 02 0D 12 0D 01 0E 0A 02 0F 10 01
   04 6C 61 6E 67 0A 01 11 01 04 6A 61 76 61 09 02
   13 0E 02 06 4F 62 6A 65 63 74 10 02 15 16 0D 01
   02 09 02 17 02 02 08 50 6F 73 69 74 69 6F 6E 10
   02 19 1A 0D 01 08 09 02 1B 08 02 0B 53 63 61 6C
   61 4F 62 6A 65 63 74 08 08 1D 00 FFFFFF82 FFFFFFC2 FFFFFF80 FFFFFF84 00
   1E 01 06 73 6F 75 72 63 65 15 01 1F 10 03 19 20
   22 09 02 21 08 02 05 41 72 72 61 79 10 02 19 23
   09 02 24 08 02 04 43 68 61 72 08 08 26 00 FFFFFF82 FFFFFF80
   FFFFFFA0 FFFFFF80 04 1F 01 07 73 6F 75 72 63 65 20 08 08 28
   00 FFFFFF82 FFFFFFC2 FFFFFF80 FFFFFF84 00 29 01 04 6C 69 6E 65 15 01 2A
   10 02 19 2B 09 02 2C 08 02 03 49 6E 74 08 08 2E
   00 FFFFFF82 FFFFFF80 FFFFFFA0 FFFFFF80 04 2A 01 05 6C 69 6E 65 20 08 08
   30 00 FFFFFF82 FFFFFFC2 FFFFFF80 FFFFFF84 00 29 01 06 63 6F 6C 75 6D 6E
   08 08 32 00 FFFFFF82 FFFFFF80 FFFFFFA0 FFFFFF80 04 2A 01 07 63 6F 6C 75
   6D 6E 20 08 05 34 00 FFFFFF84 00 35 01 06 3C 69 6E 69
   74 3E 14 04 36 37 38 39 10 02 15 00 08 05 1D 33
   FFFFFFC0 00 1F 08 05 28 33 FFFFFFC0 00 2A 08 05 30 33 FFFFFFC0 00
   2A 08 05 3B 00 FFFFFF84 08 3C 01 0C 6C 69 6E 65 43 6F
   6E 74 65 6E 74 73 15 01 3D 10 02 0D 3E 09 02 3F
   0E 02 06 53 74 72 69 6E 67 28 03 00 41 44 10 02
   19 42 09 02 43 08 02 0A 64 65 70 72 65 63 61 74
   65 64 21 01 45 01 1A 75 73 65 20 4F 66 66 73 65
   74 50 6F 73 69 74 69 6F 6E 20 69 6E 73 74 65 61
   64 
  minor version: 0
  major version: 49
  Constant pool:
const #1 = Asciz	SourceFile;
const #2 = Asciz	CharArrayPosition.scala;
const #3 = Asciz	column;
const #4 = Asciz	I;
const #5 = Asciz	line;
const #6 = Asciz	source;
const #7 = Asciz	[C;
const #8 = Asciz	<init>;
const #9 = Asciz	([CII)V;
const #10 = Asciz	Code;
const #11 = Asciz	LineNumberTable;
const #12 = Asciz	scala/util/parsing/input/CharArrayPosition;
const #13 = class	#12;	//  scala/util/parsing/input/CharArrayPosition
const #14 = NameAndType	#6:#7;//  source:[C
const #15 = Field	#13.#14;	//  scala/util/parsing/input/CharArrayPosition.source:[C
const #16 = NameAndType	#5:#4;//  line:I
const #17 = Field	#13.#16;	//  scala/util/parsing/input/CharArrayPosition.line:I
const #18 = NameAndType	#3:#4;//  column:I
const #19 = Field	#13.#18;	//  scala/util/parsing/input/CharArrayPosition.column:I
const #20 = Asciz	java/lang/Object;
const #21 = class	#20;	//  java/lang/Object
const #22 = Asciz	()V;
const #23 = NameAndType	#8:#22;//  "<init>":()V
const #24 = Method	#21.#23;	//  java/lang/Object."<init>":()V
const #25 = Asciz	scala/util/parsing/input/Position$class;
const #26 = class	#25;	//  scala/util/parsing/input/Position$class
const #27 = Asciz	$init$;
const #28 = Asciz	(Lscala/util/parsing/input/Position;)V;
const #29 = NameAndType	#27:#28;//  $init$:(Lscala/util/parsing/input/Position;)V
const #30 = Method	#26.#29;	//  scala/util/parsing/input/Position$class.$init$:(Lscala/util/parsing/input/Position;)V
const #31 = Asciz	this;
const #32 = Asciz	Lscala/util/parsing/input/CharArrayPosition;;
const #33 = Asciz	LocalVariableTable;
const #34 = Asciz	lineContents;
const #35 = Asciz	()Ljava/lang/String;;
const #36 = Asciz	()[C;
const #37 = NameAndType	#6:#36;//  source:()[C
const #38 = Method	#13.#37;	//  scala/util/parsing/input/CharArrayPosition.source:()[C
const #39 = Asciz	()I;
const #40 = NameAndType	#5:#39;//  line:()I
const #41 = Method	#13.#40;	//  scala/util/parsing/input/CharArrayPosition.line:()I
const #42 = int	10;
const #43 = Asciz	java/lang/StringBuffer;
const #44 = class	#43;	//  java/lang/StringBuffer
const #45 = Method	#44.#23;	//  java/lang/StringBuffer."<init>":()V
const #46 = Asciz	append;
const #47 = Asciz	(C)Ljava/lang/StringBuffer;;
const #48 = NameAndType	#46:#47;//  append:(C)Ljava/lang/StringBuffer;
const #49 = Method	#44.#48;	//  java/lang/StringBuffer.append:(C)Ljava/lang/StringBuffer;
const #50 = Asciz	toString;
const #51 = NameAndType	#50:#35;//  toString:()Ljava/lang/String;
const #52 = Method	#44.#51;	//  java/lang/StringBuffer.toString:()Ljava/lang/String;
const #53 = Asciz	i;
const #54 = Asciz	l;
const #55 = Asciz	chars;
const #56 = Asciz	Ljava/lang/StringBuffer;;
const #57 = Asciz	$less;
const #58 = Asciz	(Lscala/util/parsing/input/Position;)Z;
const #59 = Asciz	(Lscala/util/parsing/input/Position;Lscala/util/parsing/input/Position;)Z;
const #60 = NameAndType	#57:#59;//  $less:(Lscala/util/parsing/input/Position;Lscala/util/parsing/input/Position;)Z
const #61 = Method	#26.#60;	//  scala/util/parsing/input/Position$class.$less:(Lscala/util/parsing/input/Position;Lscala/util/parsing/input/Position;)Z
const #62 = Asciz	that;
const #63 = Asciz	Lscala/util/parsing/input/Position;;
const #64 = Asciz	longString;
const #65 = Asciz	(Lscala/util/parsing/input/Position;)Ljava/lang/String;;
const #66 = NameAndType	#64:#65;//  longString:(Lscala/util/parsing/input/Position;)Ljava/lang/String;
const #67 = Method	#26.#66;	//  scala/util/parsing/input/Position$class.longString:(Lscala/util/parsing/input/Position;)Ljava/lang/String;
const #68 = NameAndType	#50:#65;//  toString:(Lscala/util/parsing/input/Position;)Ljava/lang/String;
const #69 = Method	#26.#68;	//  scala/util/parsing/input/Position$class.toString:(Lscala/util/parsing/input/Position;)Ljava/lang/String;
const #70 = Asciz	ScalaSig;
const #71 = Asciz	scala/util/parsing/input/Position;
const #72 = class	#71;	//  scala/util/parsing/input/Position
const #73 = Asciz	scala/ScalaObject;
const #74 = class	#73;	//  scala/ScalaObject

{
public scala.util.parsing.input.CharArrayPosition(char[], int, int);
  Code:
   Stack=2, Locals=4, Args_size=4
   0:	aload_0
   1:	aload_1
   2:	putfield	#15; //Field source:[C
   5:	aload_0
   6:	iload_2
   7:	putfield	#17; //Field line:I
   10:	aload_0
   11:	iload_3
   12:	putfield	#19; //Field column:I
   15:	aload_0
   16:	invokespecial	#24; //Method java/lang/Object."<init>":()V
   19:	aload_0
   20:	invokestatic	#30; //Method scala/util/parsing/input/Position$class.$init$:(Lscala/util/parsing/input/Position;)V
   23:	return
  LineNumberTable: 
   line 23: 0

  LocalVariableTable: 
   Start  Length  Slot  Name   Signature
   0      24      0    this       Lscala/util/parsing/input/CharArrayPosition;
   0      24      1    source       [C
   0      24      2    line       I
   0      24      3    column       I


public java.lang.String lineContents();
  Code:
   Stack=3, Locals=4, Args_size=1
   0:	iconst_0
   1:	istore_1
   2:	iconst_1
   3:	istore_2
   4:	iload_1
   5:	aload_0
   6:	invokevirtual	#38; //Method source:()[C
   9:	arraylength
   10:	if_icmpge	59
   13:	iload_2
   14:	aload_0
   15:	invokevirtual	#41; //Method line:()I
   18:	if_icmpge	59
   21:	iload_1
   22:	aload_0
   23:	invokevirtual	#38; //Method source:()[C
   26:	arraylength
   27:	if_icmpge	48
   30:	aload_0
   31:	invokevirtual	#38; //Method source:()[C
   34:	iload_1
   35:	caload
   36:	ldc	#42; //int 10
   38:	if_icmpeq	48
   41:	iload_1
   42:	iconst_1
   43:	iadd
   44:	istore_1
   45:	goto	21
   48:	iload_1
   49:	iconst_1
   50:	iadd
   51:	istore_1
   52:	iload_2
   53:	iconst_1
   54:	iadd
   55:	istore_2
   56:	goto	4
   59:	new	#44; //class java/lang/StringBuffer
   62:	dup
   63:	invokespecial	#45; //Method java/lang/StringBuffer."<init>":()V
   66:	astore_3
   67:	iload_1
   68:	aload_0
   69:	invokevirtual	#38; //Method source:()[C
   72:	arraylength
   73:	if_icmpge	105
   76:	aload_0
   77:	invokevirtual	#38; //Method source:()[C
   80:	iload_1
   81:	caload
   82:	ldc	#42; //int 10
   84:	if_icmpeq	105
   87:	aload_3
   88:	aload_0
   89:	invokevirtual	#38; //Method source:()[C
   92:	iload_1
   93:	caload
   94:	invokevirtual	#49; //Method java/lang/StringBuffer.append:(C)Ljava/lang/StringBuffer;
   97:	pop
   98:	iload_1
   99:	iconst_1
   100:	iadd
   101:	istore_1
   102:	goto	67
   105:	aload_3
   106:	invokevirtual	#52; //Method java/lang/StringBuffer.toString:()Ljava/lang/String;
   109:	areturn
  LineNumberTable: 
   line 29: 0
   line 30: 2
   line 31: 4
   line 32: 21
   line 33: 48
   line 34: 52
   line 31: 56
   line 36: 59
   line 37: 67
   line 38: 87
   line 39: 98
   line 37: 102
   line 41: 105

  LocalVariableTable: 
   Start  Length  Slot  Name   Signature
   0      110      0    this       Lscala/util/parsing/input/CharArrayPosition;
   2      107      1    i       I
   4      105      2    l       I
   67      42      3    chars       Ljava/lang/StringBuffer;


public int column();
  Code:
   Stack=1, Locals=1, Args_size=1
   0:	aload_0
   1:	getfield	#19; //Field column:I
   4:	ireturn
  LineNumberTable: 
   line 23: 0


public int line();
  Code:
   Stack=1, Locals=1, Args_size=1
   0:	aload_0
   1:	getfield	#17; //Field line:I
   4:	ireturn
  LineNumberTable: 
   line 23: 0


public char[] source();
  Code:
   Stack=1, Locals=1, Args_size=1
   0:	aload_0
   1:	getfield	#15; //Field source:[C
   4:	areturn
  LineNumberTable: 
   line 23: 0


public boolean $less(scala.util.parsing.input.Position);
  Code:
   Stack=2, Locals=2, Args_size=2
   0:	aload_0
   1:	aload_1
   2:	invokestatic	#61; //Method scala/util/parsing/input/Position$class.$less:(Lscala/util/parsing/input/Position;Lscala/util/parsing/input/Position;)Z
   5:	ireturn
  LineNumberTable: 
   line 23: 0

  LocalVariableTable: 
   Start  Length  Slot  Name   Signature
   0      6      0    this       Lscala/util/parsing/input/CharArrayPosition;
   0      6      1    that       Lscala/util/parsing/input/Position;


public java.lang.String longString();
  Code:
   Stack=1, Locals=1, Args_size=1
   0:	aload_0
   1:	invokestatic	#67; //Method scala/util/parsing/input/Position$class.longString:(Lscala/util/parsing/input/Position;)Ljava/lang/String;
   4:	areturn
  LineNumberTable: 
   line 23: 0


public java.lang.String toString();
  Code:
   Stack=1, Locals=1, Args_size=1
   0:	aload_0
   1:	invokestatic	#69; //Method scala/util/parsing/input/Position$class.toString:(Lscala/util/parsing/input/Position;)Ljava/lang/String;
   4:	areturn
  LineNumberTable: 
   line 23: 0


}

