Compiled from "CharArrayReader.scala"
public final class scala.util.parsing.input.CharArrayReader$ extends java.lang.Object implements scala.ScalaObject
  SourceFile: "CharArrayReader.scala"
  Scala: length = 0x
   
  minor version: 0
  major version: 49
  Constant pool:
const #1 = Asciz	SourceFile;
const #2 = Asciz	CharArrayReader.scala;
const #3 = Asciz	Scala;
const #4 = Asciz	MODULE$;
const #5 = Asciz	Lscala/util/parsing/input/CharArrayReader$;;
const #6 = Asciz	<clinit>;
const #7 = Asciz	()V;
const #8 = Asciz	Code;
const #9 = Asciz	scala/util/parsing/input/CharArrayReader$;
const #10 = class	#9;	//  scala/util/parsing/input/CharArrayReader$
const #11 = Asciz	<init>;
const #12 = NameAndType	#11:#7;//  "<init>":()V
const #13 = Method	#10.#12;	//  scala/util/parsing/input/CharArrayReader$."<init>":()V
const #14 = Asciz	CR;
const #15 = Asciz	C;
const #16 = Asciz	EofCh;
const #17 = Asciz	LineNumberTable;
const #18 = Asciz	java/lang/Object;
const #19 = class	#18;	//  java/lang/Object
const #20 = Method	#19.#12;	//  java/lang/Object."<init>":()V
const #21 = NameAndType	#4:#5;//  MODULE$:Lscala/util/parsing/input/CharArrayReader$;
const #22 = Field	#10.#21;	//  scala/util/parsing/input/CharArrayReader$.MODULE$:Lscala/util/parsing/input/CharArrayReader$;
const #23 = Asciz	()C;
const #24 = int	13;
const #25 = int	26;
const #26 = Asciz	scala/ScalaObject;
const #27 = class	#26;	//  scala/ScalaObject

{
public static final scala.util.parsing.input.CharArrayReader$ MODULE$;

public static {};
  Code:
   Stack=1, Locals=0, Args_size=0
   0:	new	#10; //class scala/util/parsing/input/CharArrayReader$
   3:	invokespecial	#13; //Method "<init>":()V
   6:	return

public final char CR();
  Code:
   Stack=1, Locals=1, Args_size=1
   0:	ldc	#24; //int 13
   2:	ireturn
  LineNumberTable: 
   line 21: 0


public final char EofCh();
  Code:
   Stack=1, Locals=1, Args_size=1
   0:	ldc	#25; //int 26
   2:	ireturn
  LineNumberTable: 
   line 18: 0


}

