Compiled from "NoPosition.scala"
public final class scala.util.parsing.input.NoPosition$ extends java.lang.Object implements scala.util.parsing.input.Position,scala.ScalaObject
  SourceFile: "NoPosition.scala"
  Scala: length = 0x
   
  minor version: 0
  major version: 49
  Constant pool:
const #1 = Asciz	SourceFile;
const #2 = Asciz	NoPosition.scala;
const #3 = Asciz	Scala;
const #4 = Asciz	MODULE$;
const #5 = Asciz	Lscala/util/parsing/input/NoPosition$;;
const #6 = Asciz	<clinit>;
const #7 = Asciz	()V;
const #8 = Asciz	Code;
const #9 = Asciz	scala/util/parsing/input/NoPosition$;
const #10 = class	#9;	//  scala/util/parsing/input/NoPosition$
const #11 = Asciz	<init>;
const #12 = NameAndType	#11:#7;//  "<init>":()V
const #13 = Method	#10.#12;	//  scala/util/parsing/input/NoPosition$."<init>":()V
const #14 = Asciz	LineNumberTable;
const #15 = Asciz	java/lang/Object;
const #16 = class	#15;	//  java/lang/Object
const #17 = Method	#16.#12;	//  java/lang/Object."<init>":()V
const #18 = NameAndType	#4:#5;//  MODULE$:Lscala/util/parsing/input/NoPosition$;
const #19 = Field	#10.#18;	//  scala/util/parsing/input/NoPosition$.MODULE$:Lscala/util/parsing/input/NoPosition$;
const #20 = Asciz	scala/util/parsing/input/Position$class;
const #21 = class	#20;	//  scala/util/parsing/input/Position$class
const #22 = Asciz	$init$;
const #23 = Asciz	(Lscala/util/parsing/input/Position;)V;
const #24 = NameAndType	#22:#23;//  $init$:(Lscala/util/parsing/input/Position;)V
const #25 = Method	#21.#24;	//  scala/util/parsing/input/Position$class.$init$:(Lscala/util/parsing/input/Position;)V
const #26 = Asciz	lineContents;
const #27 = Asciz	()Ljava/lang/String;;
const #28 = Asciz	;
const #29 = String	#28;	//  
const #30 = Asciz	longString;
const #31 = Asciz	toString;
const #32 = NameAndType	#31:#27;//  toString:()Ljava/lang/String;
const #33 = Method	#10.#32;	//  scala/util/parsing/input/NoPosition$.toString:()Ljava/lang/String;
const #34 = Asciz	<undefined position>;
const #35 = String	#34;	//  <undefined position>
const #36 = Asciz	column;
const #37 = Asciz	()I;
const #38 = Asciz	line;
const #39 = Asciz	$less;
const #40 = Asciz	(Lscala/util/parsing/input/Position;)Z;
const #41 = Asciz	(Lscala/util/parsing/input/Position;Lscala/util/parsing/input/Position;)Z;
const #42 = NameAndType	#39:#41;//  $less:(Lscala/util/parsing/input/Position;Lscala/util/parsing/input/Position;)Z
const #43 = Method	#21.#42;	//  scala/util/parsing/input/Position$class.$less:(Lscala/util/parsing/input/Position;Lscala/util/parsing/input/Position;)Z
const #44 = Asciz	this;
const #45 = Asciz	that;
const #46 = Asciz	Lscala/util/parsing/input/Position;;
const #47 = Asciz	LocalVariableTable;
const #48 = Asciz	scala/util/parsing/input/Position;
const #49 = class	#48;	//  scala/util/parsing/input/Position
const #50 = Asciz	scala/ScalaObject;
const #51 = class	#50;	//  scala/ScalaObject

{
public static final scala.util.parsing.input.NoPosition$ MODULE$;

public static {};
  Code:
   Stack=1, Locals=0, Args_size=0
   0:	new	#10; //class scala/util/parsing/input/NoPosition$
   3:	invokespecial	#13; //Method "<init>":()V
   6:	return

public java.lang.String lineContents();
  Code:
   Stack=1, Locals=1, Args_size=1
   0:	ldc	#29; //String 
   2:	areturn
  LineNumberTable: 
   line 23: 0


public java.lang.String longString();
  Code:
   Stack=1, Locals=1, Args_size=1
   0:	aload_0
   1:	invokevirtual	#33; //Method toString:()Ljava/lang/String;
   4:	areturn
  LineNumberTable: 
   line 22: 0


public java.lang.String toString();
  Code:
   Stack=1, Locals=1, Args_size=1
   0:	ldc	#35; //String <undefined position>
   2:	areturn
  LineNumberTable: 
   line 21: 0


public int column();
  Code:
   Stack=1, Locals=1, Args_size=1
   0:	iconst_0
   1:	ireturn
  LineNumberTable: 
   line 20: 0


public int line();
  Code:
   Stack=1, Locals=1, Args_size=1
   0:	iconst_0
   1:	ireturn
  LineNumberTable: 
   line 19: 0


public boolean $less(scala.util.parsing.input.Position);
  Code:
   Stack=2, Locals=2, Args_size=2
   0:	aload_0
   1:	aload_1
   2:	invokestatic	#43; //Method scala/util/parsing/input/Position$class.$less:(Lscala/util/parsing/input/Position;Lscala/util/parsing/input/Position;)Z
   5:	ireturn
  LineNumberTable: 
   line 18: 0

  LocalVariableTable: 
   Start  Length  Slot  Name   Signature
   0      6      0    this       Lscala/util/parsing/input/NoPosition$;
   0      6      1    that       Lscala/util/parsing/input/Position;


}

