Compiled from "NoPosition.scala"
public final class scala.util.parsing.input.NoPosition$ extends java.lang.Object implements scala.util.parsing.input.Position,scala.ScalaObject
  SourceFile: "NoPosition.scala"
  Scala: length = 0x
   
  minor version: 0
  major version: 49
  Constant pool:
Asciz	SourceFile;
Asciz	NoPosition.scala;
Asciz	Scala;
Asciz	MODULE$;
Asciz	Lscala/util/parsing/input/NoPosition$;;
Asciz	<clinit>;
Asciz	()V;
Asciz	Code;
Asciz	scala/util/parsing/input/NoPosition$;
class	scala/util/parsing/input/NoPosition$
Asciz	<init>;
NameAndType	"<init>":()V
Method	scala/util/parsing/input/NoPosition$."<init>":()V
Asciz	LineNumberTable;
Asciz	java/lang/Object;
class	java/lang/Object
Method	java/lang/Object."<init>":()V
NameAndType	MODULE$:Lscala/util/parsing/input/NoPosition$;
Field	scala/util/parsing/input/NoPosition$.MODULE$:Lscala/util/parsing/input/NoPosition$;
Asciz	scala/util/parsing/input/Position$class;
class	scala/util/parsing/input/Position$class
Asciz	$init$;
Asciz	(Lscala/util/parsing/input/Position;)V;
NameAndType	$init$:(Lscala/util/parsing/input/Position;)V
Method	scala/util/parsing/input/Position$class.$init$:(Lscala/util/parsing/input/Position;)V
Asciz	lineContents;
Asciz	()Ljava/lang/String;;
Asciz	;
String	
Asciz	longString;
Asciz	toString;
NameAndType	toString:()Ljava/lang/String;
Method	scala/util/parsing/input/NoPosition$.toString:()Ljava/lang/String;
Asciz	<undefined position>;
String	<undefined position>
Asciz	column;
Asciz	()I;
Asciz	line;
Asciz	$less;
Asciz	(Lscala/util/parsing/input/Position;)Z;
Asciz	(Lscala/util/parsing/input/Position;Lscala/util/parsing/input/Position;)Z;
NameAndType	$less:(Lscala/util/parsing/input/Position;Lscala/util/parsing/input/Position;)Z
Method	scala/util/parsing/input/Position$class.$less:(Lscala/util/parsing/input/Position;Lscala/util/parsing/input/Position;)Z
Asciz	this;
Asciz	that;
Asciz	Lscala/util/parsing/input/Position;;
Asciz	LocalVariableTable;
Asciz	scala/util/parsing/input/Position;
class	scala/util/parsing/input/Position
Asciz	scala/ScalaObject;
class	scala/ScalaObject

{
public static final scala.util.parsing.input.NoPosition$ MODULE$;
  Signature: Lscala/util/parsing/input/NoPosition$;

public static {};
  Signature: ()V
  Code:
   Stack=1, Locals=0, Args_size=0
	new	class scala/util/parsing/input/NoPosition$
	invokespecial	Method "<init>":()V
	return
  Labels:

private scala.util.parsing.input.NoPosition$();
  Signature: ()V
  Code:
   Stack=1, Locals=1, Args_size=1
	aload_0
	invokespecial	Method java/lang/Object."<init>":()V
	aload_0
	putstatic	Field MODULE$:Lscala/util/parsing/input/NoPosition$;
	aload_0
	invokestatic	Method scala/util/parsing/input/Position$class.$init$:(Lscala/util/parsing/input/Position;)V
	return
  Labels:

public java.lang.String lineContents();
  Signature: ()Ljava/lang/String;
  Code:
   Stack=1, Locals=1, Args_size=1
	ldc	String 
	areturn
  Labels:

public java.lang.String longString();
  Signature: ()Ljava/lang/String;
  Code:
   Stack=1, Locals=1, Args_size=1
	aload_0
	invokevirtual	Method toString:()Ljava/lang/String;
	areturn
  Labels:

public java.lang.String toString();
  Signature: ()Ljava/lang/String;
  Code:
   Stack=1, Locals=1, Args_size=1
	ldc	String <undefined position>
	areturn
  Labels:

public int column();
  Signature: ()I
  Code:
   Stack=1, Locals=1, Args_size=1
	iconst_0
	ireturn
  Labels:

public int line();
  Signature: ()I
  Code:
   Stack=1, Locals=1, Args_size=1
	iconst_0
	ireturn
  Labels:

public boolean $less(scala.util.parsing.input.Position);
  Signature: (Lscala/util/parsing/input/Position;)Z
  Code:
   Stack=2, Locals=2, Args_size=2
	aload_0
	aload_1
	invokestatic	Method scala/util/parsing/input/Position$class.$less:(Lscala/util/parsing/input/Position;Lscala/util/parsing/input/Position;)Z
	ireturn
  Labels:
  LocalVariableTable: 
   Start  Length  Slot  Name   Signature
   0      6      0    this       Lscala/util/parsing/input/NoPosition$;
   0      6      1    that       Lscala/util/parsing/input/Position;


}

