Compiled from "NoPosition.scala"
public final class scala.util.parsing.input.NoPosition extends java.lang.Object
  SourceFile: "NoPosition.scala"
  ScalaSig: length = 0x144
   05 00 35 07 05 01 02 FFFFFF88 02 0B 01 0A 4E 6F 50 6F
   73 69 74 69 6F 6E 0A 02 03 04 01 05 69 6E 70 75
   74 0A 02 05 06 01 07 70 61 72 73 69 6E 67 0A 02
   07 08 01 04 75 74 69 6C 0A 01 09 01 05 73 63 61
   6C 61 03 00 10 02 0C 0D 0D 01 02 06 08 0E 02 FFFFFF84
   FFFFFF80 FFFFFF80 FFFFFF88 02 0F 02 0A 4E 6F 50 6F 73 69 74 69 6F
   6E 13 04 0D 10 18 1B 10 02 11 16 0D 01 12 0A 02
   13 14 01 04 6C 61 6E 67 0A 01 15 01 04 6A 61 76
   61 09 02 17 12 02 06 4F 62 6A 65 63 74 10 02 0C
   19 09 02 1A 02 02 08 50 6F 73 69 74 69 6F 6E 10
   02 1C 1D 0D 01 08 09 02 1E 08 02 0B 53 63 61 6C
   61 4F 62 6A 65 63 74 08 05 20 0D FFFFFF84 00 21 01 06
   3C 69 6E 69 74 3E 14 01 0B 08 05 23 0D FFFFFF84 00 24
   01 04 6C 69 6E 65 15 01 25 10 02 1C 26 09 02 27
   08 02 03 49 6E 74 08 05 29 0D FFFFFF84 00 24 01 06 63
   6F 6C 75 6D 6E 08 05 2B 0D FFFFFF84 20 2C 01 08 74 6F
   53 74 72 69 6E 67 14 01 2D 10 02 11 2E 09 02 2F
   12 02 06 53 74 72 69 6E 67 08 05 31 0D FFFFFF84 20 32
   01 0A 6C 6F 6E 67 53 74 72 69 6E 67 15 01 2D 08
   05 34 0D FFFFFF84 00 32 01 0C 6C 69 6E 65 43 6F 6E 74
   65 6E 74 73 
  minor version: 0
  major version: 49
  Constant pool:
const #1 = Asciz	SourceFile;
const #2 = Asciz	NoPosition.scala;
const #3 = Asciz	$less;
const #4 = Asciz	(Lscala/util/parsing/input/Position;)Z;
const #5 = Asciz	Code;
const #6 = Asciz	scala/util/parsing/input/NoPosition$;
const #7 = class	#6;	//  scala/util/parsing/input/NoPosition$
const #8 = Asciz	MODULE$;
const #9 = Asciz	Lscala/util/parsing/input/NoPosition$;;
const #10 = NameAndType	#8:#9;//  MODULE$:Lscala/util/parsing/input/NoPosition$;
const #11 = Field	#7.#10;	//  scala/util/parsing/input/NoPosition$.MODULE$:Lscala/util/parsing/input/NoPosition$;
const #12 = NameAndType	#3:#4;//  $less:(Lscala/util/parsing/input/Position;)Z
const #13 = Method	#7.#12;	//  scala/util/parsing/input/NoPosition$.$less:(Lscala/util/parsing/input/Position;)Z
const #14 = Asciz	lineContents;
const #15 = Asciz	()Ljava/lang/String;;
const #16 = NameAndType	#14:#15;//  lineContents:()Ljava/lang/String;
const #17 = Method	#7.#16;	//  scala/util/parsing/input/NoPosition$.lineContents:()Ljava/lang/String;
const #18 = Asciz	longString;
const #19 = NameAndType	#18:#15;//  longString:()Ljava/lang/String;
const #20 = Method	#7.#19;	//  scala/util/parsing/input/NoPosition$.longString:()Ljava/lang/String;
const #21 = Asciz	column;
const #22 = Asciz	()I;
const #23 = NameAndType	#21:#22;//  column:()I
const #24 = Method	#7.#23;	//  scala/util/parsing/input/NoPosition$.column:()I
const #25 = Asciz	line;
const #26 = NameAndType	#25:#22;//  line:()I
const #27 = Method	#7.#26;	//  scala/util/parsing/input/NoPosition$.line:()I
const #28 = Asciz	ScalaSig;
const #29 = Asciz	scala/util/parsing/input/NoPosition;
const #30 = class	#29;	//  scala/util/parsing/input/NoPosition
const #31 = Asciz	java/lang/Object;
const #32 = class	#31;	//  java/lang/Object

{
public static final boolean $less(scala.util.parsing.input.Position);
  Code:
   Stack=2, Locals=1, Args_size=1
   0:	getstatic	#11; //Field scala/util/parsing/input/NoPosition$.MODULE$:Lscala/util/parsing/input/NoPosition$;
   3:	aload_0
   4:	invokevirtual	#13; //Method scala/util/parsing/input/NoPosition$.$less:(Lscala/util/parsing/input/Position;)Z
   7:	ireturn

public static final java.lang.String lineContents();
  Code:
   Stack=1, Locals=0, Args_size=0
   0:	getstatic	#11; //Field scala/util/parsing/input/NoPosition$.MODULE$:Lscala/util/parsing/input/NoPosition$;
   3:	invokevirtual	#17; //Method scala/util/parsing/input/NoPosition$.lineContents:()Ljava/lang/String;
   6:	areturn

public static final java.lang.String longString();
  Code:
   Stack=1, Locals=0, Args_size=0
   0:	getstatic	#11; //Field scala/util/parsing/input/NoPosition$.MODULE$:Lscala/util/parsing/input/NoPosition$;
   3:	invokevirtual	#20; //Method scala/util/parsing/input/NoPosition$.longString:()Ljava/lang/String;
   6:	areturn

public static final int column();
  Code:
   Stack=1, Locals=0, Args_size=0
   0:	getstatic	#11; //Field scala/util/parsing/input/NoPosition$.MODULE$:Lscala/util/parsing/input/NoPosition$;
   3:	invokevirtual	#24; //Method scala/util/parsing/input/NoPosition$.column:()I
   6:	ireturn

public static final int line();
  Code:
   Stack=1, Locals=0, Args_size=0
   0:	getstatic	#11; //Field scala/util/parsing/input/NoPosition$.MODULE$:Lscala/util/parsing/input/NoPosition$;
   3:	invokevirtual	#27; //Method scala/util/parsing/input/NoPosition$.line:()I
   6:	ireturn

}

