Compiled from "OffsetPosition.scala"
public class scala.util.parsing.input.OffsetPosition extends java.lang.Object implements scala.util.parsing.input.Position,scala.ScalaObject,scala.Product,java.io.Serializable
  SourceFile: "OffsetPosition.scala"
  ScalaSig: length = 0x48A
   05 00 FFFFFF81 24 06 08 01 02 FFFFFF84 FFFFFF80 FFFFFF80 FFFFFF80 40 0B 02 0E
   4F 66 66 73 65 74 50 6F 73 69 74 69 6F 6E 0A 02
   03 04 01 05 69 6E 70 75 74 0A 02 05 06 01 07 70
   61 72 73 69 6E 67 0A 02 07 08 01 04 75 74 69 6C
   0A 01 09 01 05 73 63 61 6C 61 03 00 13 05 00 0C
   14 18 1C 10 02 0D 12 0D 01 0E 0A 02 0F 10 01 04
   6C 61 6E 67 0A 01 11 01 04 6A 61 76 61 09 02 13
   0E 02 06 4F 62 6A 65 63 74 10 02 15 16 0D 01 02
   09 02 17 02 02 08 50 6F 73 69 74 69 6F 6E 10 02
   19 1A 0D 01 08 09 02 1B 08 02 0B 53 63 61 6C 61
   4F 62 6A 65 63 74 10 02 19 1D 09 02 1E 08 02 07
   50 72 6F 64 75 63 74 08 08 20 00 FFFFFF82 FFFFFFCA FFFFFF80 FFFFFF84 00
   21 01 06 73 6F 75 72 63 65 15 01 22 10 02 0D 23
   09 02 24 0E 02 0C 43 68 61 72 53 65 71 75 65 6E
   63 65 08 08 26 00 FFFFFF82 FFFFFF88 FFFFFFA0 FFFFFF80 04 22 01 07 73 6F
   75 72 63 65 20 08 08 28 00 FFFFFF82 FFFFFFCA FFFFFF80 FFFFFF84 00 29 01
   06 6F 66 66 73 65 74 15 01 2A 10 02 19 2B 09 02
   2C 08 02 03 49 6E 74 08 08 2E 00 FFFFFF82 FFFFFF88 FFFFFFA0 FFFFFF80 04
   2A 01 07 6F 66 66 73 65 74 20 08 05 30 00 FFFFFF84 00
   31 01 06 3C 69 6E 69 74 3E 14 03 32 33 34 10 02
   15 00 08 05 20 2F FFFFFFC0 00 22 08 05 28 2F FFFFFFC0 00 2A
   08 08 36 00 FFFFFF88 FFFFFFC2 FFFFFF80 FFFFFF84 04 37 01 05 69 6E 64 65
   78 15 01 38 10 03 19 39 2A 09 02 3A 08 02 05 41
   72 72 61 79 08 08 3C 00 FFFFFF88 FFFFFF80 FFFFFFA0 FFFFFFA0 04 38 01 06
   69 6E 64 65 78 20 08 05 3E 00 FFFFFF84 00 29 01 04 6C
   69 6E 65 08 05 40 00 FFFFFF84 00 29 01 06 63 6F 6C 75
   6D 6E 08 05 42 00 FFFFFF84 00 43 01 0C 6C 69 6E 65 43
   6F 6E 74 65 6E 74 73 15 01 44 10 02 45 48 0E 02
   19 46 09 02 47 08 01 06 50 72 65 64 65 66 09 02
   49 4A 02 06 53 74 72 69 6E 67 0A 02 47 08 08 05
   4C 00 FFFFFF84 20 4D 01 08 74 6F 53 74 72 69 6E 67 14
   01 4E 10 02 0D 4F 09 02 49 0E 08 05 51 00 FFFFFF84 20
   52 01 05 24 6C 65 73 73 14 02 53 56 10 02 19 54
   09 02 55 08 02 07 42 6F 6F 6C 65 61 6E 08 05 57
   50 FFFFFFC0 00 14 01 04 74 68 61 74 08 07 59 00 FFFFFF81 FFFFFF80
   FFFFFF84 00 5A 01 04 63 6F 70 79 14 03 32 5B 69 08 08
   5C 20 58 FFFFFF90 FFFFFF80 FFFFFFC0 00 22 08 07 5D 00 FFFFFF91 FFFFFF80 FFFFFF84 00
   5E 01 0E 63 6F 70 79 24 64 65 66 61 75 6C 74 24
   31 15 01 5F 2A 02 22 60 2B 01 61 10 02 62 67 0D
   01 63 0A 02 64 65 01 09 75 6E 63 68 65 63 6B 65
   64 0A 02 66 08 01 0A 61 6E 6E 6F 74 61 74 69 6F
   6E 09 02 68 63 02 11 75 6E 63 68 65 63 6B 65 64
   56 61 72 69 61 6E 63 65 08 08 6A 28 58 FFFFFF90 FFFFFF80 FFFFFFC0
   00 2A 08 07 6B 00 FFFFFF91 FFFFFF80 FFFFFF84 00 6C 01 0E 63 6F 70
   79 24 64 65 66 61 75 6C 74 24 32 15 01 6D 2A 02
   2A 60 08 08 6F 00 FFFFFF84 FFFFFF80 FFFFFF80 FFFFFF84 20 70 01 08 68 61
   73 68 43 6F 64 65 14 01 2A 08 08 72 00 FFFFFF84 FFFFFF80 FFFFFF80
   FFFFFF84 20 73 01 06 65 71 75 61 6C 73 14 02 53 74 08
   07 75 71 FFFFFF81 FFFFFF80 FFFFFFC0 00 76 01 03 78 24 31 10 02 19
   77 09 02 78 08 02 03 41 6E 79 08 08 7A 00 FFFFFF84 FFFFFF80
   FFFFFF80 FFFFFF84 20 7B 01 0D 70 72 6F 64 75 63 74 50 72 65
   66 69 78 15 01 4E 08 08 7D 00 FFFFFF84 FFFFFF80 FFFFFF80 FFFFFF84 20 29
   01 0C 70 72 6F 64 75 63 74 41 72 69 74 79 08 09
   7F 00 FFFFFF84 FFFFFF80 FFFFFF80 FFFFFF84 20 FFFFFF81 00 01 0E 70 72 6F 64 75
   63 74 45 6C 65 6D 65 6E 74 14 03 76 FFFFFF81 01 08 07
   75 7E FFFFFF81 FFFFFF80 FFFFFFC0 00 2A 08 0A FFFFFF81 03 00 FFFFFF84 FFFFFF80 FFFFFF80 FFFFFF84
   20 FFFFFF81 04 01 08 63 61 6E 45 71 75 61 6C 14 03 53
   FFFFFF81 05 08 08 75 FFFFFF81 02 FFFFFF81 FFFFFF80 FFFFFFC0 00 76 28 03 00 FFFFFF81
   07 10 03 19 FFFFFF81 08 09 03 FFFFFF81 09 08 02 0C 73 65 72
   69 61 6C 69 7A 61 62 6C 65 07 09 FFFFFF81 0B 02 FFFFFF81 FFFFFF80
   FFFFFF88 02 FFFFFF81 0C 01 0E 4F 66 66 73 65 74 50 6F 73 69
   74 69 6F 6E 10 03 15 FFFFFF81 0D 06 09 01 02 FFFFFF84 FFFFFF81 FFFFFF80
   FFFFFF88 02 FFFFFF81 0E 13 06 FFFFFF81 0D 0C FFFFFF81 0F 18 10 06 19 FFFFFF81
   10 22 2A 32 09 03 FFFFFF81 11 08 02 09 46 75 6E 63 74
   69 6F 6E 32 08 07 30 FFFFFF81 0D FFFFFF84 00 FFFFFF81 13 14 02 FFFFFF81
   0C 08 0A FFFFFF81 15 FFFFFF81 0D FFFFFF81 FFFFFF80 FFFFFF84 40 FFFFFF81 16 01 05 61
   70 70 6C 79 14 05 32 FFFFFF81 17 FFFFFF81 18 08 06 20 FFFFFF81 14
   FFFFFFC0 00 22 08 06 28 FFFFFF81 14 FFFFFFC0 00 2A 08 0A FFFFFF81 1A FFFFFF81
   0D FFFFFF81 FFFFFF80 FFFFFF84 40 FFFFFF81 1B 01 07 75 6E 61 70 70 6C 79
   14 04 FFFFFF81 1C FFFFFF81 22 10 05 19 FFFFFF81 1D FFFFFF81 1F 09 03 FFFFFF81
   1E 08 02 04 53 6F 6D 65 10 05 19 FFFFFF81 20 22 2A 09
   03 FFFFFF81 21 08 02 06 54 75 70 6C 65 32 08 07 FFFFFF81 23
   FFFFFF81 19 FFFFFFC0 00 32 01 03 78 24 30 
  InnerClass: 
   public abstract #232= #182 of #231; //ByOne=class scala/collection/immutable/Range$ByOne of class scala/collection/immutable/Range
   public final #233= #177 of #231; //$anon$2=class scala/collection/immutable/Range$$anon$2 of class scala/collection/immutable/Range
   public final #234= #184 of #28; //$anonfun$index$1=class scala/util/parsing/input/OffsetPosition$$anonfun$index$1 of class scala/util/parsing/input/OffsetPosition
  minor version: 0
  major version: 49
  Constant pool:
const #1 = Asciz	SourceFile;
const #2 = Asciz	OffsetPosition.scala;
const #3 = Asciz	tuple;
const #4 = Asciz	()Lscala/Function1;;
const #5 = Asciz	Code;
const #6 = Asciz	scala/util/parsing/input/OffsetPosition$;
const #7 = class	#6;	//  scala/util/parsing/input/OffsetPosition$
const #8 = Asciz	MODULE$;
const #9 = Asciz	Lscala/util/parsing/input/OffsetPosition$;;
const #10 = NameAndType	#8:#9;//  MODULE$:Lscala/util/parsing/input/OffsetPosition$;
const #11 = Field	#7.#10;	//  scala/util/parsing/input/OffsetPosition$.MODULE$:Lscala/util/parsing/input/OffsetPosition$;
const #12 = NameAndType	#3:#4;//  tuple:()Lscala/Function1;
const #13 = Method	#7.#12;	//  scala/util/parsing/input/OffsetPosition$.tuple:()Lscala/Function1;
const #14 = Asciz	curry;
const #15 = NameAndType	#14:#4;//  curry:()Lscala/Function1;
const #16 = Method	#7.#15;	//  scala/util/parsing/input/OffsetPosition$.curry:()Lscala/Function1;
const #17 = Asciz	bitmap$0;
const #18 = Asciz	I;
const #19 = Asciz	index;
const #20 = Asciz	[I;
const #21 = Asciz	offset;
const #22 = Asciz	source;
const #23 = Asciz	Ljava/lang/CharSequence;;
const #24 = Asciz	<init>;
const #25 = Asciz	(Ljava/lang/CharSequence;I)V;
const #26 = Asciz	LineNumberTable;
const #27 = Asciz	scala/util/parsing/input/OffsetPosition;
const #28 = class	#27;	//  scala/util/parsing/input/OffsetPosition
const #29 = NameAndType	#22:#23;//  source:Ljava/lang/CharSequence;
const #30 = Field	#28.#29;	//  scala/util/parsing/input/OffsetPosition.source:Ljava/lang/CharSequence;
const #31 = NameAndType	#21:#18;//  offset:I
const #32 = Field	#28.#31;	//  scala/util/parsing/input/OffsetPosition.offset:I
const #33 = Asciz	java/lang/Object;
const #34 = class	#33;	//  java/lang/Object
const #35 = Asciz	()V;
const #36 = NameAndType	#24:#35;//  "<init>":()V
const #37 = Method	#34.#36;	//  java/lang/Object."<init>":()V
const #38 = Asciz	scala/util/parsing/input/Position$class;
const #39 = class	#38;	//  scala/util/parsing/input/Position$class
const #40 = Asciz	$init$;
const #41 = Asciz	(Lscala/util/parsing/input/Position;)V;
const #42 = NameAndType	#40:#41;//  $init$:(Lscala/util/parsing/input/Position;)V
const #43 = Method	#39.#42;	//  scala/util/parsing/input/Position$class.$init$:(Lscala/util/parsing/input/Position;)V
const #44 = Asciz	scala/Product$class;
const #45 = class	#44;	//  scala/Product$class
const #46 = Asciz	(Lscala/Product;)V;
const #47 = NameAndType	#40:#46;//  $init$:(Lscala/Product;)V
const #48 = Method	#45.#47;	//  scala/Product$class.$init$:(Lscala/Product;)V
const #49 = Asciz	this;
const #50 = Asciz	Lscala/util/parsing/input/OffsetPosition;;
const #51 = Asciz	LocalVariableTable;
const #52 = Asciz	gd1$1;
const #53 = Asciz	(Ljava/lang/CharSequence;I)Z;
const #54 = Asciz	()Ljava/lang/CharSequence;;
const #55 = NameAndType	#22:#54;//  source:()Ljava/lang/CharSequence;
const #56 = Method	#28.#55;	//  scala/util/parsing/input/OffsetPosition.source:()Ljava/lang/CharSequence;
const #57 = Asciz	equals;
const #58 = Asciz	(Ljava/lang/Object;)Z;
const #59 = NameAndType	#57:#58;//  equals:(Ljava/lang/Object;)Z
const #60 = Method	#34.#59;	//  java/lang/Object.equals:(Ljava/lang/Object;)Z
const #61 = Asciz	()I;
const #62 = NameAndType	#21:#61;//  offset:()I
const #63 = Method	#28.#62;	//  scala/util/parsing/input/OffsetPosition.offset:()I
const #64 = Asciz	canEqual;
const #65 = Asciz	productElement;
const #66 = Asciz	(I)Ljava/lang/Object;;
const #67 = Asciz	java/lang/IndexOutOfBoundsException;
const #68 = class	#67;	//  java/lang/IndexOutOfBoundsException
const #69 = Asciz	scala/runtime/BoxesRunTime;
const #70 = class	#69;	//  scala/runtime/BoxesRunTime
const #71 = Asciz	boxToInteger;
const #72 = Asciz	(I)Ljava/lang/Integer;;
const #73 = NameAndType	#71:#72;//  boxToInteger:(I)Ljava/lang/Integer;
const #74 = Method	#70.#73;	//  scala/runtime/BoxesRunTime.boxToInteger:(I)Ljava/lang/Integer;
const #75 = Asciz	toString;
const #76 = Asciz	()Ljava/lang/String;;
const #77 = NameAndType	#75:#76;//  toString:()Ljava/lang/String;
const #78 = Method	#34.#77;	//  java/lang/Object.toString:()Ljava/lang/String;
const #79 = Asciz	(Ljava/lang/String;)V;
const #80 = NameAndType	#24:#79;//  "<init>":(Ljava/lang/String;)V
const #81 = Method	#68.#80;	//  java/lang/IndexOutOfBoundsException."<init>":(Ljava/lang/String;)V
const #82 = Asciz	scala/MatchError;
const #83 = class	#82;	//  scala/MatchError
const #84 = Method	#83.#80;	//  scala/MatchError."<init>":(Ljava/lang/String;)V
const #85 = Asciz	productArity;
const #86 = Asciz	productPrefix;
const #87 = Asciz	OffsetPosition;
const #88 = String	#87;	//  OffsetPosition
const #89 = NameAndType	#52:#53;//  gd1$1:(Ljava/lang/CharSequence;I)Z
const #90 = Method	#28.#89;	//  scala/util/parsing/input/OffsetPosition.gd1$1:(Ljava/lang/CharSequence;I)Z
const #91 = Asciz	scala/Equals;
const #92 = class	#91;	//  scala/Equals
const #93 = NameAndType	#64:#58;//  canEqual:(Ljava/lang/Object;)Z
const #94 = InterfaceMethod	#92.#93;	//  scala/Equals.canEqual:(Ljava/lang/Object;)Z
const #95 = Asciz	temp6;
const #96 = Asciz	temp7;
const #97 = Asciz	temp8;
const #98 = Asciz	hashCode;
const #99 = Asciz	scala/runtime/ScalaRunTime$;
const #100 = class	#99;	//  scala/runtime/ScalaRunTime$
const #101 = Asciz	Lscala/runtime/ScalaRunTime$;;
const #102 = NameAndType	#8:#101;//  MODULE$:Lscala/runtime/ScalaRunTime$;
const #103 = Field	#100.#102;	//  scala/runtime/ScalaRunTime$.MODULE$:Lscala/runtime/ScalaRunTime$;
const #104 = Asciz	_hashCode;
const #105 = Asciz	(Lscala/Product;)I;
const #106 = NameAndType	#104:#105;//  _hashCode:(Lscala/Product;)I
const #107 = Method	#100.#106;	//  scala/runtime/ScalaRunTime$._hashCode:(Lscala/Product;)I
const #108 = Asciz	copy;
const #109 = Asciz	(Ljava/lang/CharSequence;I)Lscala/util/parsing/input/OffsetPosition;;
const #110 = NameAndType	#24:#25;//  "<init>":(Ljava/lang/CharSequence;I)V
const #111 = Method	#28.#110;	//  scala/util/parsing/input/OffsetPosition."<init>":(Ljava/lang/CharSequence;I)V
const #112 = Asciz	$less;
const #113 = Asciz	(Lscala/util/parsing/input/Position;)Z;
const #114 = Asciz	scala/util/parsing/input/Position;
const #115 = class	#114;	//  scala/util/parsing/input/Position
const #116 = InterfaceMethod	#115.#77;	//  scala/util/parsing/input/Position.toString:()Ljava/lang/String;
const #117 = Asciz	line;
const #118 = NameAndType	#117:#61;//  line:()I
const #119 = Method	#28.#118;	//  scala/util/parsing/input/OffsetPosition.line:()I
const #120 = InterfaceMethod	#115.#118;	//  scala/util/parsing/input/Position.line:()I
const #121 = Asciz	column;
const #122 = NameAndType	#121:#61;//  column:()I
const #123 = Method	#28.#122;	//  scala/util/parsing/input/OffsetPosition.column:()I
const #124 = InterfaceMethod	#115.#122;	//  scala/util/parsing/input/Position.column:()I
const #125 = Asciz	that;
const #126 = Asciz	Lscala/util/parsing/input/Position;;
const #127 = Asciz	temp2;
const #128 = Asciz	temp4;
const #129 = Asciz	scala/collection/mutable/StringBuilder;
const #130 = class	#129;	//  scala/collection/mutable/StringBuilder
const #131 = Method	#130.#36;	//  scala/collection/mutable/StringBuilder."<init>":()V
const #132 = Asciz	append;
const #133 = Asciz	(I)Lscala/collection/mutable/StringBuilder;;
const #134 = NameAndType	#132:#133;//  append:(I)Lscala/collection/mutable/StringBuilder;
const #135 = Method	#130.#134;	//  scala/collection/mutable/StringBuilder.append:(I)Lscala/collection/mutable/StringBuilder;
const #136 = Asciz	.;
const #137 = String	#136;	//  .
const #138 = Asciz	(Ljava/lang/Object;)Lscala/collection/mutable/StringBuilder;;
const #139 = NameAndType	#132:#138;//  append:(Ljava/lang/Object;)Lscala/collection/mutable/StringBuilder;
const #140 = Method	#130.#139;	//  scala/collection/mutable/StringBuilder.append:(Ljava/lang/Object;)Lscala/collection/mutable/StringBuilder;
const #141 = Method	#130.#77;	//  scala/collection/mutable/StringBuilder.toString:()Ljava/lang/String;
const #142 = Asciz	lineContents;
const #143 = Asciz	()[I;
const #144 = NameAndType	#19:#143;//  index:()[I
const #145 = Method	#28.#144;	//  scala/util/parsing/input/OffsetPosition.index:()[I
const #146 = Asciz	java/lang/CharSequence;
const #147 = class	#146;	//  java/lang/CharSequence
const #148 = Asciz	subSequence;
const #149 = Asciz	(II)Ljava/lang/CharSequence;;
const #150 = NameAndType	#148:#149;//  subSequence:(II)Ljava/lang/CharSequence;
const #151 = InterfaceMethod	#147.#150;	//  java/lang/CharSequence.subSequence:(II)Ljava/lang/CharSequence;
const #152 = Asciz	lo;
const #153 = Asciz	hi;
const #154 = Asciz	mid;
const #155 = NameAndType	#17:#18;//  bitmap$0:I
const #156 = Field	#28.#155;	//  scala/util/parsing/input/OffsetPosition.bitmap$0:I
const #157 = Asciz	scala/runtime/ObjectRef;
const #158 = class	#157;	//  scala/runtime/ObjectRef
const #159 = Asciz	scala/collection/mutable/ArrayBuffer;
const #160 = class	#159;	//  scala/collection/mutable/ArrayBuffer
const #161 = Method	#160.#36;	//  scala/collection/mutable/ArrayBuffer."<init>":()V
const #162 = Asciz	(Ljava/lang/Object;)V;
const #163 = NameAndType	#24:#162;//  "<init>":(Ljava/lang/Object;)V
const #164 = Method	#158.#163;	//  scala/runtime/ObjectRef."<init>":(Ljava/lang/Object;)V
const #165 = Asciz	elem;
const #166 = Asciz	Ljava/lang/Object;;
const #167 = NameAndType	#165:#166;//  elem:Ljava/lang/Object;
const #168 = Field	#158.#167;	//  scala/runtime/ObjectRef.elem:Ljava/lang/Object;
const #169 = Asciz	$plus$eq;
const #170 = Asciz	(Ljava/lang/Object;)Lscala/collection/mutable/ArrayBuffer;;
const #171 = NameAndType	#169:#170;//  $plus$eq:(Ljava/lang/Object;)Lscala/collection/mutable/ArrayBuffer;
const #172 = Method	#160.#171;	//  scala/collection/mutable/ArrayBuffer.$plus$eq:(Ljava/lang/Object;)Lscala/collection/mutable/ArrayBuffer;
const #173 = Asciz	length;
const #174 = NameAndType	#173:#61;//  length:()I
const #175 = InterfaceMethod	#147.#174;	//  java/lang/CharSequence.length:()I
const #176 = Asciz	scala/collection/immutable/Range$$anon$2;
const #177 = class	#176;	//  scala/collection/immutable/Range$$anon$2
const #178 = Asciz	(II)V;
const #179 = NameAndType	#24:#178;//  "<init>":(II)V
const #180 = Method	#177.#179;	//  scala/collection/immutable/Range$$anon$2."<init>":(II)V
const #181 = Asciz	scala/collection/immutable/Range$ByOne;
const #182 = class	#181;	//  scala/collection/immutable/Range$ByOne
const #183 = Asciz	scala/util/parsing/input/OffsetPosition$$anonfun$index$1;
const #184 = class	#183;	//  scala/util/parsing/input/OffsetPosition$$anonfun$index$1
const #185 = Asciz	(Lscala/util/parsing/input/OffsetPosition;Lscala/runtime/ObjectRef;)V;
const #186 = NameAndType	#24:#185;//  "<init>":(Lscala/util/parsing/input/OffsetPosition;Lscala/runtime/ObjectRef;)V
const #187 = Method	#184.#186;	//  scala/util/parsing/input/OffsetPosition$$anonfun$index$1."<init>":(Lscala/util/parsing/input/OffsetPosition;Lscala/runtime/ObjectRef;)V
const #188 = Asciz	foreach;
const #189 = Asciz	(Lscala/Function1;)V;
const #190 = NameAndType	#188:#189;//  foreach:(Lscala/Function1;)V
const #191 = InterfaceMethod	#182.#190;	//  scala/collection/immutable/Range$ByOne.foreach:(Lscala/Function1;)V
const #192 = Asciz	scala/reflect/Manifest$;
const #193 = class	#192;	//  scala/reflect/Manifest$
const #194 = Asciz	Lscala/reflect/Manifest$;;
const #195 = NameAndType	#8:#194;//  MODULE$:Lscala/reflect/Manifest$;
const #196 = Field	#193.#195;	//  scala/reflect/Manifest$.MODULE$:Lscala/reflect/Manifest$;
const #197 = Asciz	Int;
const #198 = Asciz	()Lscala/reflect/AnyValManifest;;
const #199 = NameAndType	#197:#198;//  Int:()Lscala/reflect/AnyValManifest;
const #200 = Method	#193.#199;	//  scala/reflect/Manifest$.Int:()Lscala/reflect/AnyValManifest;
const #201 = Asciz	scala/collection/TraversableLike;
const #202 = class	#201;	//  scala/collection/TraversableLike
const #203 = Asciz	toArray;
const #204 = Asciz	(Lscala/reflect/ClassManifest;)Ljava/lang/Object;;
const #205 = NameAndType	#203:#204;//  toArray:(Lscala/reflect/ClassManifest;)Ljava/lang/Object;
const #206 = InterfaceMethod	#202.#205;	//  scala/collection/TraversableLike.toArray:(Lscala/reflect/ClassManifest;)Ljava/lang/Object;
const #207 = class	#20;	//  "[I"
const #208 = NameAndType	#19:#20;//  index:[I
const #209 = Field	#28.#208;	//  scala/util/parsing/input/OffsetPosition.index:[I
const #210 = Asciz	start$10;
const #211 = Asciz	end0;
const #212 = Asciz	lineStarts$1;
const #213 = Asciz	Lscala/runtime/ObjectRef;;
const #214 = Asciz	copy$default$1;
const #215 = Asciz	copy$default$2;
const #216 = Asciz	longString;
const #217 = Asciz	(Lscala/util/parsing/input/Position;)Ljava/lang/String;;
const #218 = NameAndType	#216:#217;//  longString:(Lscala/util/parsing/input/Position;)Ljava/lang/String;
const #219 = Method	#39.#218;	//  scala/util/parsing/input/Position$class.longString:(Lscala/util/parsing/input/Position;)Ljava/lang/String;
const #220 = Asciz	productElements;
const #221 = Asciz	()Lscala/collection/Iterator;;
const #222 = Asciz	(Lscala/Product;)Lscala/collection/Iterator;;
const #223 = NameAndType	#220:#222;//  productElements:(Lscala/Product;)Lscala/collection/Iterator;
const #224 = Method	#45.#223;	//  scala/Product$class.productElements:(Lscala/Product;)Lscala/collection/Iterator;
const #225 = Asciz	productIterator;
const #226 = NameAndType	#225:#222;//  productIterator:(Lscala/Product;)Lscala/collection/Iterator;
const #227 = Method	#45.#226;	//  scala/Product$class.productIterator:(Lscala/Product;)Lscala/collection/Iterator;
const #228 = Asciz	ScalaSig;
const #229 = Asciz	InnerClasses;
const #230 = Asciz	scala/collection/immutable/Range;
const #231 = class	#230;	//  scala/collection/immutable/Range
const #232 = Asciz	ByOne;
const #233 = Asciz	$anon$2;
const #234 = Asciz	$anonfun$index$1;
const #235 = Asciz	scala/ScalaObject;
const #236 = class	#235;	//  scala/ScalaObject
const #237 = Asciz	scala/Product;
const #238 = class	#237;	//  scala/Product
const #239 = Asciz	java/io/Serializable;
const #240 = class	#239;	//  java/io/Serializable

{
public volatile int bitmap$0;

public static final scala.Function1 tuple();
  Code:
   Stack=1, Locals=0, Args_size=0
   0:	getstatic	#11; //Field scala/util/parsing/input/OffsetPosition$.MODULE$:Lscala/util/parsing/input/OffsetPosition$;
   3:	invokevirtual	#13; //Method scala/util/parsing/input/OffsetPosition$.tuple:()Lscala/Function1;
   6:	areturn

public static final scala.Function1 curry();
  Code:
   Stack=1, Locals=0, Args_size=0
   0:	getstatic	#11; //Field scala/util/parsing/input/OffsetPosition$.MODULE$:Lscala/util/parsing/input/OffsetPosition$;
   3:	invokevirtual	#16; //Method scala/util/parsing/input/OffsetPosition$.curry:()Lscala/Function1;
   6:	areturn

public scala.util.parsing.input.OffsetPosition(java.lang.CharSequence, int);
  Code:
   Stack=2, Locals=3, Args_size=3
   0:	aload_0
   1:	aload_1
   2:	putfield	#30; //Field source:Ljava/lang/CharSequence;
   5:	aload_0
   6:	iload_2
   7:	putfield	#32; //Field offset:I
   10:	aload_0
   11:	invokespecial	#37; //Method java/lang/Object."<init>":()V
   14:	aload_0
   15:	invokestatic	#43; //Method scala/util/parsing/input/Position$class.$init$:(Lscala/util/parsing/input/Position;)V
   18:	aload_0
   19:	invokestatic	#48; //Method scala/Product$class.$init$:(Lscala/Product;)V
   22:	return
  LineNumberTable: 
   line 21: 0

  LocalVariableTable: 
   Start  Length  Slot  Name   Signature
   0      23      0    this       Lscala/util/parsing/input/OffsetPosition;
   0      23      1    source       Ljava/lang/CharSequence;
   0      23      2    offset       I


public boolean canEqual(java.lang.Object);
  Code:
   Stack=1, Locals=2, Args_size=2
   0:	aload_1
   1:	instanceof	#28; //class scala/util/parsing/input/OffsetPosition
   4:	ireturn
  LineNumberTable: 
   line 21: 0


public java.lang.Object productElement(int);
  Code:
   Stack=3, Locals=3, Args_size=2
   0:	iload_1
   1:	tableswitch{ //0 to 1
		0: 89;
		1: 58;
		default: 24 }
   24:	iconst_1
   25:	ifeq	43
   28:	new	#68; //class java/lang/IndexOutOfBoundsException
   31:	dup
   32:	iload_1
   33:	invokestatic	#74; //Method scala/runtime/BoxesRunTime.boxToInteger:(I)Ljava/lang/Integer;
   36:	invokevirtual	#78; //Method java/lang/Object.toString:()Ljava/lang/String;
   39:	invokespecial	#81; //Method java/lang/IndexOutOfBoundsException."<init>":(Ljava/lang/String;)V
   42:	athrow
   43:	new	#83; //class scala/MatchError
   46:	dup
   47:	iload_1
   48:	invokestatic	#74; //Method scala/runtime/BoxesRunTime.boxToInteger:(I)Ljava/lang/Integer;
   51:	invokevirtual	#78; //Method java/lang/Object.toString:()Ljava/lang/String;
   54:	invokespecial	#84; //Method scala/MatchError."<init>":(Ljava/lang/String;)V
   57:	athrow
   58:	iconst_1
   59:	ifeq	74
   62:	aload_0
   63:	invokevirtual	#63; //Method offset:()I
   66:	istore_2
   67:	iload_2
   68:	invokestatic	#74; //Method scala/runtime/BoxesRunTime.boxToInteger:(I)Ljava/lang/Integer;
   71:	goto	97
   74:	new	#83; //class scala/MatchError
   77:	dup
   78:	iload_1
   79:	invokestatic	#74; //Method scala/runtime/BoxesRunTime.boxToInteger:(I)Ljava/lang/Integer;
   82:	invokevirtual	#78; //Method java/lang/Object.toString:()Ljava/lang/String;
   85:	invokespecial	#84; //Method scala/MatchError."<init>":(Ljava/lang/String;)V
   88:	athrow
   89:	iconst_1
   90:	ifeq	98
   93:	aload_0
   94:	invokevirtual	#56; //Method source:()Ljava/lang/CharSequence;
   97:	areturn
   98:	new	#83; //class scala/MatchError
   101:	dup
   102:	iload_1
   103:	invokestatic	#74; //Method scala/runtime/BoxesRunTime.boxToInteger:(I)Ljava/lang/Integer;
   106:	invokevirtual	#78; //Method java/lang/Object.toString:()Ljava/lang/String;
   109:	invokespecial	#84; //Method scala/MatchError."<init>":(Ljava/lang/String;)V
   112:	athrow
  LineNumberTable: 
   line 21: 0


public int productArity();
  Code:
   Stack=1, Locals=1, Args_size=1
   0:	iconst_2
   1:	ireturn
  LineNumberTable: 
   line 21: 0


public java.lang.String productPrefix();
  Code:
   Stack=1, Locals=1, Args_size=1
   0:	ldc	#88; //String OffsetPosition
   2:	areturn
  LineNumberTable: 
   line 21: 0


public boolean equals(java.lang.Object);
  Code:
   Stack=3, Locals=5, Args_size=2
   0:	aload_0
   1:	aload_1
   2:	if_acmpeq	79
   5:	aload_1
   6:	instanceof	#28; //class scala/util/parsing/input/OffsetPosition
   9:	ifeq	71
   12:	aload_1
   13:	checkcast	#28; //class scala/util/parsing/input/OffsetPosition
   16:	astore_2
   17:	aload_2
   18:	invokevirtual	#56; //Method source:()Ljava/lang/CharSequence;
   21:	astore_3
   22:	aload_2
   23:	invokevirtual	#63; //Method offset:()I
   26:	istore	4
   28:	aload_0
   29:	aload_3
   30:	iload	4
   32:	invokespecial	#90; //Method gd1$1:(Ljava/lang/CharSequence;I)Z
   35:	ifeq	51
   38:	aload_1
   39:	checkcast	#28; //class scala/util/parsing/input/OffsetPosition
   42:	aload_0
   43:	invokeinterface	#94,  2; //InterfaceMethod scala/Equals.canEqual:(Ljava/lang/Object;)Z
   48:	goto	76
   51:	iconst_1
   52:	ifeq	59
   55:	iconst_0
   56:	goto	76
   59:	new	#83; //class scala/MatchError
   62:	dup
   63:	aload_1
   64:	invokevirtual	#78; //Method java/lang/Object.toString:()Ljava/lang/String;
   67:	invokespecial	#84; //Method scala/MatchError."<init>":(Ljava/lang/String;)V
   70:	athrow
   71:	iconst_1
   72:	ifeq	85
   75:	iconst_0
   76:	ifeq	83
   79:	iconst_1
   80:	goto	84
   83:	iconst_0
   84:	ireturn
   85:	new	#83; //class scala/MatchError
   88:	dup
   89:	aload_1
   90:	invokevirtual	#78; //Method java/lang/Object.toString:()Ljava/lang/String;
   93:	invokespecial	#84; //Method scala/MatchError."<init>":(Ljava/lang/String;)V
   96:	athrow
  LineNumberTable: 
   line 21: 0

  LocalVariableTable: 
   Start  Length  Slot  Name   Signature
   0      97      0    this       Lscala/util/parsing/input/OffsetPosition;
   17      54      2    temp6       Lscala/util/parsing/input/OffsetPosition;
   22      49      3    temp7       Ljava/lang/CharSequence;
   28      43      4    temp8       I


public int hashCode();
  Code:
   Stack=2, Locals=1, Args_size=1
   0:	getstatic	#103; //Field scala/runtime/ScalaRunTime$.MODULE$:Lscala/runtime/ScalaRunTime$;
   3:	aload_0
   4:	invokevirtual	#107; //Method scala/runtime/ScalaRunTime$._hashCode:(Lscala/Product;)I
   7:	ireturn
  LineNumberTable: 
   line 21: 0


public scala.util.parsing.input.OffsetPosition copy(java.lang.CharSequence, int);
  Code:
   Stack=4, Locals=3, Args_size=3
   0:	new	#28; //class scala/util/parsing/input/OffsetPosition
   3:	dup
   4:	aload_1
   5:	iload_2
   6:	invokespecial	#111; //Method "<init>":(Ljava/lang/CharSequence;I)V
   9:	areturn
  LineNumberTable: 
   line 21: 0

  LocalVariableTable: 
   Start  Length  Slot  Name   Signature
   0      10      0    this       Lscala/util/parsing/input/OffsetPosition;
   0      10      1    source       Ljava/lang/CharSequence;
   0      10      2    offset       I


public boolean $less(scala.util.parsing.input.Position);
  Code:
   Stack=3, Locals=4, Args_size=2
   0:	aload_1
   1:	instanceof	#28; //class scala/util/parsing/input/OffsetPosition
   4:	ifeq	51
   7:	aload_1
   8:	checkcast	#28; //class scala/util/parsing/input/OffsetPosition
   11:	astore_2
   12:	aload_2
   13:	invokevirtual	#63; //Method offset:()I
   16:	istore_3
   17:	iconst_1
   18:	ifeq	37
   21:	aload_0
   22:	invokevirtual	#63; //Method offset:()I
   25:	iload_3
   26:	if_icmpge	33
   29:	iconst_1
   30:	goto	99
   33:	iconst_0
   34:	goto	99
   37:	new	#83; //class scala/MatchError
   40:	dup
   41:	aload_1
   42:	invokeinterface	#116,  1; //InterfaceMethod scala/util/parsing/input/Position.toString:()Ljava/lang/String;
   47:	invokespecial	#84; //Method scala/MatchError."<init>":(Ljava/lang/String;)V
   50:	athrow
   51:	iconst_1
   52:	ifeq	100
   55:	aload_0
   56:	invokevirtual	#119; //Method line:()I
   59:	aload_1
   60:	invokeinterface	#120,  1; //InterfaceMethod scala/util/parsing/input/Position.line:()I
   65:	if_icmplt	94
   68:	aload_0
   69:	invokevirtual	#119; //Method line:()I
   72:	aload_1
   73:	invokeinterface	#120,  1; //InterfaceMethod scala/util/parsing/input/Position.line:()I
   78:	if_icmpne	98
   81:	aload_0
   82:	invokevirtual	#123; //Method column:()I
   85:	aload_1
   86:	invokeinterface	#124,  1; //InterfaceMethod scala/util/parsing/input/Position.column:()I
   91:	if_icmpge	98
   94:	iconst_1
   95:	goto	99
   98:	iconst_0
   99:	ireturn
   100:	new	#83; //class scala/MatchError
   103:	dup
   104:	aload_1
   105:	invokeinterface	#116,  1; //InterfaceMethod scala/util/parsing/input/Position.toString:()Ljava/lang/String;
   110:	invokespecial	#84; //Method scala/MatchError."<init>":(Ljava/lang/String;)V
   113:	athrow
  LineNumberTable: 
   line 66: 0
   line 21: 17
   line 68: 21
   line 66: 37
   line 21: 51
   line 70: 55
   line 71: 68
   line 70: 94
   line 66: 99

  LocalVariableTable: 
   Start  Length  Slot  Name   Signature
   0      114      0    this       Lscala/util/parsing/input/OffsetPosition;
   0      114      1    that       Lscala/util/parsing/input/Position;
   12      39      2    temp2       Lscala/util/parsing/input/OffsetPosition;
   17      34      3    temp4       I


public java.lang.String toString();
  Code:
   Stack=2, Locals=2, Args_size=1
   0:	new	#130; //class scala/collection/mutable/StringBuilder
   3:	dup
   4:	invokespecial	#131; //Method scala/collection/mutable/StringBuilder."<init>":()V
   7:	aload_0
   8:	invokevirtual	#119; //Method line:()I
   11:	invokevirtual	#135; //Method scala/collection/mutable/StringBuilder.append:(I)Lscala/collection/mutable/StringBuilder;
   14:	ldc	#137; //String .
   16:	invokevirtual	#140; //Method scala/collection/mutable/StringBuilder.append:(Ljava/lang/Object;)Lscala/collection/mutable/StringBuilder;
   19:	aload_0
   20:	invokevirtual	#123; //Method column:()I
   23:	istore_1
   24:	iload_1
   25:	invokestatic	#74; //Method scala/runtime/BoxesRunTime.boxToInteger:(I)Ljava/lang/Integer;
   28:	invokevirtual	#140; //Method scala/collection/mutable/StringBuilder.append:(Ljava/lang/Object;)Lscala/collection/mutable/StringBuilder;
   31:	invokevirtual	#141; //Method scala/collection/mutable/StringBuilder.toString:()Ljava/lang/String;
   34:	areturn
  LineNumberTable: 
   line 57: 0


public java.lang.String lineContents();
  Code:
   Stack=4, Locals=1, Args_size=1
   0:	aload_0
   1:	invokevirtual	#56; //Method source:()Ljava/lang/CharSequence;
   4:	aload_0
   5:	invokespecial	#145; //Method index:()[I
   8:	aload_0
   9:	invokevirtual	#119; //Method line:()I
   12:	iconst_1
   13:	isub
   14:	iaload
   15:	aload_0
   16:	invokespecial	#145; //Method index:()[I
   19:	aload_0
   20:	invokevirtual	#119; //Method line:()I
   23:	iaload
   24:	invokeinterface	#151,  3; //InterfaceMethod java/lang/CharSequence.subSequence:(II)Ljava/lang/CharSequence;
   29:	invokevirtual	#78; //Method java/lang/Object.toString:()Ljava/lang/String;
   32:	areturn
  LineNumberTable: 
   line 54: 0


public int column();
  Code:
   Stack=4, Locals=1, Args_size=1
   0:	aload_0
   1:	invokevirtual	#63; //Method offset:()I
   4:	aload_0
   5:	invokespecial	#145; //Method index:()[I
   8:	aload_0
   9:	invokevirtual	#119; //Method line:()I
   12:	iconst_1
   13:	isub
   14:	iaload
   15:	isub
   16:	iconst_1
   17:	iadd
   18:	ireturn
  LineNumberTable: 
   line 46: 0


public int line();
  Code:
   Stack=3, Locals=4, Args_size=1
   0:	iconst_0
   1:	istore_1
   2:	aload_0
   3:	invokespecial	#145; //Method index:()[I
   6:	arraylength
   7:	iconst_1
   8:	isub
   9:	istore_2
   10:	iload_1
   11:	iconst_1
   12:	iadd
   13:	iload_2
   14:	if_icmpge	46
   17:	iload_2
   18:	iload_1
   19:	iadd
   20:	iconst_2
   21:	idiv
   22:	istore_3
   23:	aload_0
   24:	invokevirtual	#63; //Method offset:()I
   27:	aload_0
   28:	invokespecial	#145; //Method index:()[I
   31:	iload_3
   32:	iaload
   33:	if_icmpge	41
   36:	iload_3
   37:	istore_2
   38:	goto	10
   41:	iload_3
   42:	istore_1
   43:	goto	10
   46:	iload_1
   47:	iconst_1
   48:	iadd
   49:	ireturn
  LineNumberTable: 
   line 35: 0
   line 36: 2
   line 37: 10
   line 38: 17
   line 39: 23
   line 40: 41
   line 39: 43
   line 42: 46

  LocalVariableTable: 
   Start  Length  Slot  Name   Signature
   0      50      0    this       Lscala/util/parsing/input/OffsetPosition;
   2      47      1    lo       I
   10      39      2    hi       I
   23      23      3    mid       I


public int offset();
  Code:
   Stack=1, Locals=1, Args_size=1
   0:	aload_0
   1:	getfield	#32; //Field offset:I
   4:	ireturn
  LineNumberTable: 
   line 21: 0


public java.lang.CharSequence source();
  Code:
   Stack=1, Locals=1, Args_size=1
   0:	aload_0
   1:	getfield	#30; //Field source:Ljava/lang/CharSequence;
   4:	areturn
  LineNumberTable: 
   line 21: 0


public java.lang.CharSequence copy$default$1();
  Code:
   Stack=1, Locals=1, Args_size=1
   0:	aload_0
   1:	invokevirtual	#56; //Method source:()Ljava/lang/CharSequence;
   4:	areturn
  LineNumberTable: 
   line 21: 0


public int copy$default$2();
  Code:
   Stack=1, Locals=1, Args_size=1
   0:	aload_0
   1:	invokevirtual	#63; //Method offset:()I
   4:	ireturn
  LineNumberTable: 
   line 21: 0


public java.lang.String longString();
  Code:
   Stack=1, Locals=1, Args_size=1
   0:	aload_0
   1:	invokestatic	#219; //Method scala/util/parsing/input/Position$class.longString:(Lscala/util/parsing/input/Position;)Ljava/lang/String;
   4:	areturn
  LineNumberTable: 
   line 21: 0


public scala.collection.Iterator productElements();
  Code:
   Stack=1, Locals=1, Args_size=1
   0:	aload_0
   1:	invokestatic	#224; //Method scala/Product$class.productElements:(Lscala/Product;)Lscala/collection/Iterator;
   4:	areturn
  LineNumberTable: 
   line 21: 0


public scala.collection.Iterator productIterator();
  Code:
   Stack=1, Locals=1, Args_size=1
   0:	aload_0
   1:	invokestatic	#227; //Method scala/Product$class.productIterator:(Lscala/Product;)Lscala/collection/Iterator;
   4:	areturn
  LineNumberTable: 
   line 21: 0


}

