Compiled from "OffsetPosition.scala"
public final class scala.util.parsing.input.OffsetPosition$$anonfun$index$1 extends java.lang.Object implements scala.Function1,scala.ScalaObject,java.io.Serializable
  SourceFile: "OffsetPosition.scala"
  Scala: length = 0x
   
  InnerClass: 
   public final $anonfun$index$1=class scala/util/parsing/input/OffsetPosition$$anonfun$index$1 of class scala/util/parsing/input/OffsetPosition
  minor version: 0
  major version: 49
  Constant pool:
Asciz	SourceFile;
Asciz	OffsetPosition.scala;
Asciz	<clinit>;
Asciz	()V;
Asciz	Code;
Asciz	serialVersionUID;
Asciz	J;
Asciz	scala/util/parsing/input/OffsetPosition$$anonfun$index$1;
class	scala/util/parsing/input/OffsetPosition$$anonfun$index$1
NameAndType	serialVersionUID:J
Field	scala/util/parsing/input/OffsetPosition$$anonfun$index$1.serialVersionUID:J
Asciz	lineStarts$1;
Asciz	Lscala/runtime/ObjectRef;;
Asciz	$outer;
Asciz	Lscala/util/parsing/input/OffsetPosition;;
Asciz	<init>;
Asciz	(Lscala/util/parsing/input/OffsetPosition;Lscala/runtime/ObjectRef;)V;
Asciz	LineNumberTable;
Asciz	java/lang/NullPointerException;
class	java/lang/NullPointerException
NameAndType	"<init>":()V
Method	java/lang/NullPointerException."<init>":()V
NameAndType	$outer:Lscala/util/parsing/input/OffsetPosition;
Field	scala/util/parsing/input/OffsetPosition$$anonfun$index$1.$outer:Lscala/util/parsing/input/OffsetPosition;
NameAndType	lineStarts$1:Lscala/runtime/ObjectRef;
Field	scala/util/parsing/input/OffsetPosition$$anonfun$index$1.lineStarts$1:Lscala/runtime/ObjectRef;
Asciz	java/lang/Object;
class	java/lang/Object
Method	java/lang/Object."<init>":()V
Asciz	scala/Function1$class;
class	scala/Function1$class
Asciz	$init$;
Asciz	(Lscala/Function1;)V;
NameAndType	$init$:(Lscala/Function1;)V
Method	scala/Function1$class.$init$:(Lscala/Function1;)V
Asciz	this;
Asciz	Lscala/util/parsing/input/OffsetPosition$$anonfun$index$1;;
Asciz	LocalVariableTable;
Asciz	apply;
Asciz	(Ljava/lang/Object;)Ljava/lang/Object;;
Asciz	scala/runtime/BoxesRunTime;
class	scala/runtime/BoxesRunTime
Asciz	unboxToInt;
Asciz	(Ljava/lang/Object;)I;
NameAndType	unboxToInt:(Ljava/lang/Object;)I
Method	scala/runtime/BoxesRunTime.unboxToInt:(Ljava/lang/Object;)I
Asciz	(I)Ljava/lang/Object;;
NameAndType	apply:(I)Ljava/lang/Object;
Method	scala/util/parsing/input/OffsetPosition$$anonfun$index$1.apply:(I)Ljava/lang/Object;
Asciz	v1;
Asciz	Ljava/lang/Object;;
Asciz	scala/util/parsing/input/OffsetPosition;
class	scala/util/parsing/input/OffsetPosition
Asciz	source;
Asciz	()Ljava/lang/CharSequence;;
NameAndType	source:()Ljava/lang/CharSequence;
Method	scala/util/parsing/input/OffsetPosition.source:()Ljava/lang/CharSequence;
Asciz	java/lang/CharSequence;
class	java/lang/CharSequence
Asciz	charAt;
Asciz	(I)C;
NameAndType	charAt:(I)C
InterfaceMethod	java/lang/CharSequence.charAt:(I)C
int	10;
Asciz	scala/runtime/ObjectRef;
class	scala/runtime/ObjectRef
Asciz	elem;
NameAndType	elem:Ljava/lang/Object;
Field	scala/runtime/ObjectRef.elem:Ljava/lang/Object;
Asciz	scala/collection/mutable/ArrayBuffer;
class	scala/collection/mutable/ArrayBuffer
Asciz	boxToInteger;
Asciz	(I)Ljava/lang/Integer;;
NameAndType	boxToInteger:(I)Ljava/lang/Integer;
Method	scala/runtime/BoxesRunTime.boxToInteger:(I)Ljava/lang/Integer;
Asciz	$plus$eq;
Asciz	(Ljava/lang/Object;)Lscala/collection/mutable/ArrayBuffer;;
NameAndType	$plus$eq:(Ljava/lang/Object;)Lscala/collection/mutable/ArrayBuffer;
Method	scala/collection/mutable/ArrayBuffer.$plus$eq:(Ljava/lang/Object;)Lscala/collection/mutable/ArrayBuffer;
Asciz	scala/runtime/BoxedUnit;
class	scala/runtime/BoxedUnit
Asciz	UNIT;
Asciz	Lscala/runtime/BoxedUnit;;
NameAndType	UNIT:Lscala/runtime/BoxedUnit;
Field	scala/runtime/BoxedUnit.UNIT:Lscala/runtime/BoxedUnit;
Asciz	i;
Asciz	I;
Asciz	andThen;
Asciz	(Lscala/Function1;)Lscala/Function1;;
Asciz	(Lscala/Function1;Lscala/Function1;)Lscala/Function1;;
NameAndType	andThen:(Lscala/Function1;Lscala/Function1;)Lscala/Function1;
Method	scala/Function1$class.andThen:(Lscala/Function1;Lscala/Function1;)Lscala/Function1;
Asciz	g;
Asciz	Lscala/Function1;;
Asciz	compose;
NameAndType	compose:(Lscala/Function1;Lscala/Function1;)Lscala/Function1;
Method	scala/Function1$class.compose:(Lscala/Function1;Lscala/Function1;)Lscala/Function1;
Asciz	toString;
Asciz	()Ljava/lang/String;;
Asciz	(Lscala/Function1;)Ljava/lang/String;;
NameAndType	toString:(Lscala/Function1;)Ljava/lang/String;
Method	scala/Function1$class.toString:(Lscala/Function1;)Ljava/lang/String;
Asciz	Scala;
Asciz	InnerClasses;
Asciz	$anonfun$index$1;
Asciz	scala/Function1;
class	scala/Function1
Asciz	scala/ScalaObject;
class	scala/ScalaObject
Asciz	java/io/Serializable;
class	java/io/Serializable

{
public static final long serialVersionUID;
  Signature: J

private final scala.runtime.ObjectRef lineStarts$1;
  Signature: Lscala/runtime/ObjectRef;

private final scala.util.parsing.input.OffsetPosition $outer;
  Signature: Lscala/util/parsing/input/OffsetPosition;

public static {};
  Signature: ()V
  Code:
   Stack=2, Locals=0, Args_size=0
	lconst_0
	putstatic	Field serialVersionUID:J
	return
  Labels:

public scala.util.parsing.input.OffsetPosition$$anonfun$index$1(scala.util.parsing.input.OffsetPosition, scala.runtime.ObjectRef);
  Signature: (Lscala/util/parsing/input/OffsetPosition;Lscala/runtime/ObjectRef;)V
  Code:
   Stack=2, Locals=3, Args_size=3
	aload_1
	ifnonnull	l1 // aload_0
	new	class java/lang/NullPointerException
	dup
	invokespecial	Method java/lang/NullPointerException."<init>":()V
	athrow
l1	aload_0
	aload_1
	putfield	Field $outer:Lscala/util/parsing/input/OffsetPosition;
	aload_0
	aload_2
	putfield	Field lineStarts$1:Lscala/runtime/ObjectRef;
	aload_0
	invokespecial	Method java/lang/Object."<init>":()V
	aload_0
	invokestatic	Method scala/Function1$class.$init$:(Lscala/Function1;)V
	return
  Labels:
   	l1 = 12 // aload_0
  LocalVariableTable: 
   Start  Length  Slot  Name   Signature
   0      31      0    this       Lscala/util/parsing/input/OffsetPosition$$anonfun$index$1;
   0      31      1    $outer       Lscala/util/parsing/input/OffsetPosition;


public final java.lang.Object apply(java.lang.Object);
  Signature: (Ljava/lang/Object;)Ljava/lang/Object;
  Code:
   Stack=2, Locals=3, Args_size=2
	aload_0
	getfield	Field $outer:Lscala/util/parsing/input/OffsetPosition;
	astore_2
	aload_0
	aload_1
	invokestatic	Method scala/runtime/BoxesRunTime.unboxToInt:(Ljava/lang/Object;)I
	invokevirtual	Method apply:(I)Ljava/lang/Object;
	areturn
  Labels:
  LocalVariableTable: 
   Start  Length  Slot  Name   Signature
   0      14      0    this       Lscala/util/parsing/input/OffsetPosition$$anonfun$index$1;
   5      9      1    v1       Ljava/lang/Object;


public final java.lang.Object apply(int);
  Signature: (I)Ljava/lang/Object;
  Code:
   Stack=3, Locals=4, Args_size=2
	aload_0
	getfield	Field $outer:Lscala/util/parsing/input/OffsetPosition;
	astore_3
	aload_0
	getfield	Field $outer:Lscala/util/parsing/input/OffsetPosition;
	invokevirtual	Method scala/util/parsing/input/OffsetPosition.source:()Ljava/lang/CharSequence;
	iload_1
	invokeinterface	InterfaceMethod java/lang/CharSequence.charAt:(I)C
	ldc	int 10
	if_icmpne	l1 // getstatic
	aload_0
	getfield	Field lineStarts$1:Lscala/runtime/ObjectRef;
	getfield	Field scala/runtime/ObjectRef.elem:Ljava/lang/Object;
	checkcast	class scala/collection/mutable/ArrayBuffer
	iload_1
	iconst_1
	iadd
	istore_2
	iload_2
	invokestatic	Method scala/runtime/BoxesRunTime.boxToInteger:(I)Ljava/lang/Integer;
	invokevirtual	Method scala/collection/mutable/ArrayBuffer.$plus$eq:(Ljava/lang/Object;)Lscala/collection/mutable/ArrayBuffer;
	goto	l2 // areturn
l1	getstatic	Field scala/runtime/BoxedUnit.UNIT:Lscala/runtime/BoxedUnit;
l2	areturn
  Labels:
   	l1 = 47 // getstatic
   	l2 = 50 // areturn
  LocalVariableTable: 
   Start  Length  Slot  Name   Signature
   0      51      0    this       Lscala/util/parsing/input/OffsetPosition$$anonfun$index$1;
   5      46      1    i       I


public scala.Function1 andThen(scala.Function1);
  Signature: (Lscala/Function1;)Lscala/Function1;
  Code:
   Stack=2, Locals=2, Args_size=2
	aload_0
	aload_1
	invokestatic	Method scala/Function1$class.andThen:(Lscala/Function1;Lscala/Function1;)Lscala/Function1;
	areturn
  Labels:
  LocalVariableTable: 
   Start  Length  Slot  Name   Signature
   0      6      0    this       Lscala/util/parsing/input/OffsetPosition$$anonfun$index$1;
   0      6      1    g       Lscala/Function1;


public scala.Function1 compose(scala.Function1);
  Signature: (Lscala/Function1;)Lscala/Function1;
  Code:
   Stack=2, Locals=2, Args_size=2
	aload_0
	aload_1
	invokestatic	Method scala/Function1$class.compose:(Lscala/Function1;Lscala/Function1;)Lscala/Function1;
	areturn
  Labels:
  LocalVariableTable: 
   Start  Length  Slot  Name   Signature
   0      6      0    this       Lscala/util/parsing/input/OffsetPosition$$anonfun$index$1;
   0      6      1    g       Lscala/Function1;


public java.lang.String toString();
  Signature: ()Ljava/lang/String;
  Code:
   Stack=1, Locals=1, Args_size=1
	aload_0
	invokestatic	Method scala/Function1$class.toString:(Lscala/Function1;)Ljava/lang/String;
	areturn
  Labels:

}

