Compiled from "OffsetPosition.scala"
public class scala.util.parsing.input.OffsetPosition extends java.lang.Object implements scala.util.parsing.input.Position,scala.ScalaObject,scala.Product,java.io.Serializable
  SourceFile: "OffsetPosition.scala"
  ScalaSig: length = 0x48A
   05 00 FFFFFF81 24 06 08 01 02 FFFFFF84 FFFFFF80 FFFFFF80 FFFFFF80 40 0B 02 0E
   4F 66 66 73 65 74 50 6F 73 69 74 69 6F 6E 0A 02
   03 04 01 05 69 6E 70 75 74 0A 02 05 06 01 07 70
   61 72 73 69 6E 67 0A 02 07 08 01 04 75 74 69 6C
   0A 01 09 01 05 73 63 61 6C 61 03 00 13 05 00 0C
   14 18 1C 10 02 0D 12 0D 01 0E 0A 02 0F 10 01 04
   6C 61 6E 67 0A 01 11 01 04 6A 61 76 61 09 02 13
   0E 02 06 4F 62 6A 65 63 74 10 02 15 16 0D 01 02
   09 02 17 02 02 08 50 6F 73 69 74 69 6F 6E 10 02
   19 1A 0D 01 08 09 02 1B 08 02 0B 53 63 61 6C 61
   4F 62 6A 65 63 74 10 02 19 1D 09 02 1E 08 02 07
   50 72 6F 64 75 63 74 08 08 20 00 FFFFFF82 FFFFFFCA FFFFFF80 FFFFFF84 00
   21 01 06 73 6F 75 72 63 65 15 01 22 10 02 0D 23
   09 02 24 0E 02 0C 43 68 61 72 53 65 71 75 65 6E
   63 65 08 08 26 00 FFFFFF82 FFFFFF88 FFFFFFA0 FFFFFF80 04 22 01 07 73 6F
   75 72 63 65 20 08 08 28 00 FFFFFF82 FFFFFFCA FFFFFF80 FFFFFF84 00 29 01
   06 6F 66 66 73 65 74 15 01 2A 10 02 19 2B 09 02
   2C 08 02 03 49 6E 74 08 08 2E 00 FFFFFF82 FFFFFF88 FFFFFFA0 FFFFFF80 04
   2A 01 07 6F 66 66 73 65 74 20 08 05 30 00 FFFFFF84 00
   31 01 06 3C 69 6E 69 74 3E 14 03 32 33 34 10 02
   15 00 08 05 20 2F FFFFFFC0 00 22 08 05 28 2F FFFFFFC0 00 2A
   08 08 36 00 FFFFFF88 FFFFFFC2 FFFFFF80 FFFFFF84 04 37 01 05 69 6E 64 65
   78 15 01 38 10 03 19 39 2A 09 02 3A 08 02 05 41
   72 72 61 79 08 08 3C 00 FFFFFF88 FFFFFF80 FFFFFFA0 FFFFFFA0 04 38 01 06
   69 6E 64 65 78 20 08 05 3E 00 FFFFFF84 00 29 01 04 6C
   69 6E 65 08 05 40 00 FFFFFF84 00 29 01 06 63 6F 6C 75
   6D 6E 08 05 42 00 FFFFFF84 00 43 01 0C 6C 69 6E 65 43
   6F 6E 74 65 6E 74 73 15 01 44 10 02 45 48 0E 02
   19 46 09 02 47 08 01 06 50 72 65 64 65 66 09 02
   49 4A 02 06 53 74 72 69 6E 67 0A 02 47 08 08 05
   4C 00 FFFFFF84 20 4D 01 08 74 6F 53 74 72 69 6E 67 14
   01 4E 10 02 0D 4F 09 02 49 0E 08 05 51 00 FFFFFF84 20
   52 01 05 24 6C 65 73 73 14 02 53 56 10 02 19 54
   09 02 55 08 02 07 42 6F 6F 6C 65 61 6E 08 05 57
   50 FFFFFFC0 00 14 01 04 74 68 61 74 08 07 59 00 FFFFFF81 FFFFFF80
   FFFFFF84 00 5A 01 04 63 6F 70 79 14 03 32 5B 69 08 08
   5C 20 58 FFFFFF90 FFFFFF80 FFFFFFC0 00 22 08 07 5D 00 FFFFFF91 FFFFFF80 FFFFFF84 00
   5E 01 0E 63 6F 70 79 24 64 65 66 61 75 6C 74 24
   31 15 01 5F 2A 02 22 60 2B 01 61 10 02 62 67 0D
   01 63 0A 02 64 65 01 09 75 6E 63 68 65 63 6B 65
   64 0A 02 66 08 01 0A 61 6E 6E 6F 74 61 74 69 6F
   6E 09 02 68 63 02 11 75 6E 63 68 65 63 6B 65 64
   56 61 72 69 61 6E 63 65 08 08 6A 28 58 FFFFFF90 FFFFFF80 FFFFFFC0
   00 2A 08 07 6B 00 FFFFFF91 FFFFFF80 FFFFFF84 00 6C 01 0E 63 6F 70
   79 24 64 65 66 61 75 6C 74 24 32 15 01 6D 2A 02
   2A 60 08 08 6F 00 FFFFFF84 FFFFFF80 FFFFFF80 FFFFFF84 20 70 01 08 68 61
   73 68 43 6F 64 65 14 01 2A 08 08 72 00 FFFFFF84 FFFFFF80 FFFFFF80
   FFFFFF84 20 73 01 06 65 71 75 61 6C 73 14 02 53 74 08
   07 75 71 FFFFFF81 FFFFFF80 FFFFFFC0 00 76 01 03 78 24 31 10 02 19
   77 09 02 78 08 02 03 41 6E 79 08 08 7A 00 FFFFFF84 FFFFFF80
   FFFFFF80 FFFFFF84 20 7B 01 0D 70 72 6F 64 75 63 74 50 72 65
   66 69 78 15 01 4E 08 08 7D 00 FFFFFF84 FFFFFF80 FFFFFF80 FFFFFF84 20 29
   01 0C 70 72 6F 64 75 63 74 41 72 69 74 79 08 09
   7F 00 FFFFFF84 FFFFFF80 FFFFFF80 FFFFFF84 20 FFFFFF81 00 01 0E 70 72 6F 64 75
   63 74 45 6C 65 6D 65 6E 74 14 03 76 FFFFFF81 01 08 07
   75 7E FFFFFF81 FFFFFF80 FFFFFFC0 00 2A 08 0A FFFFFF81 03 00 FFFFFF84 FFFFFF80 FFFFFF80 FFFFFF84
   20 FFFFFF81 04 01 08 63 61 6E 45 71 75 61 6C 14 03 53
   FFFFFF81 05 08 08 75 FFFFFF81 02 FFFFFF81 FFFFFF80 FFFFFFC0 00 76 28 03 00 FFFFFF81
   07 10 03 19 FFFFFF81 08 09 03 FFFFFF81 09 08 02 0C 73 65 72
   69 61 6C 69 7A 61 62 6C 65 07 09 FFFFFF81 0B 02 FFFFFF81 FFFFFF80
   FFFFFF88 02 FFFFFF81 0C 01 0E 4F 66 66 73 65 74 50 6F 73 69
   74 69 6F 6E 10 03 15 FFFFFF81 0D 06 09 01 02 FFFFFF84 FFFFFF81 FFFFFF80
   FFFFFF88 02 FFFFFF81 0E 13 06 FFFFFF81 0D 0C FFFFFF81 0F 18 10 06 19 FFFFFF81
   10 22 2A 32 09 03 FFFFFF81 11 08 02 09 46 75 6E 63 74
   69 6F 6E 32 08 07 30 FFFFFF81 0D FFFFFF84 00 FFFFFF81 13 14 02 FFFFFF81
   0C 08 0A FFFFFF81 15 FFFFFF81 0D FFFFFF81 FFFFFF80 FFFFFF84 40 FFFFFF81 16 01 05 61
   70 70 6C 79 14 05 32 FFFFFF81 17 FFFFFF81 18 08 06 20 FFFFFF81 14
   FFFFFFC0 00 22 08 06 28 FFFFFF81 14 FFFFFFC0 00 2A 08 0A FFFFFF81 1A FFFFFF81
   0D FFFFFF81 FFFFFF80 FFFFFF84 40 FFFFFF81 1B 01 07 75 6E 61 70 70 6C 79
   14 04 FFFFFF81 1C FFFFFF81 22 10 05 19 FFFFFF81 1D FFFFFF81 1F 09 03 FFFFFF81
   1E 08 02 04 53 6F 6D 65 10 05 19 FFFFFF81 20 22 2A 09
   03 FFFFFF81 21 08 02 06 54 75 70 6C 65 32 08 07 FFFFFF81 23
   FFFFFF81 19 FFFFFFC0 00 32 01 03 78 24 30 
  InnerClass: 
   public abstract ByOne=class scala/collection/immutable/Range$ByOne of class scala/collection/immutable/Range
   public final $anon$2=class scala/collection/immutable/Range$$anon$2 of class scala/collection/immutable/Range
   public final $anonfun$index$1=class scala/util/parsing/input/OffsetPosition$$anonfun$index$1 of class scala/util/parsing/input/OffsetPosition
  minor version: 0
  major version: 49
  Constant pool:
Asciz	SourceFile;
Asciz	OffsetPosition.scala;
Asciz	tuple;
Asciz	()Lscala/Function1;;
Asciz	Code;
Asciz	scala/util/parsing/input/OffsetPosition$;
class	scala/util/parsing/input/OffsetPosition$
Asciz	MODULE$;
Asciz	Lscala/util/parsing/input/OffsetPosition$;;
NameAndType	MODULE$:Lscala/util/parsing/input/OffsetPosition$;
Field	scala/util/parsing/input/OffsetPosition$.MODULE$:Lscala/util/parsing/input/OffsetPosition$;
NameAndType	tuple:()Lscala/Function1;
Method	scala/util/parsing/input/OffsetPosition$.tuple:()Lscala/Function1;
Asciz	curry;
NameAndType	curry:()Lscala/Function1;
Method	scala/util/parsing/input/OffsetPosition$.curry:()Lscala/Function1;
Asciz	bitmap$0;
Asciz	I;
Asciz	index;
Asciz	[I;
Asciz	offset;
Asciz	source;
Asciz	Ljava/lang/CharSequence;;
Asciz	<init>;
Asciz	(Ljava/lang/CharSequence;I)V;
Asciz	LineNumberTable;
Asciz	scala/util/parsing/input/OffsetPosition;
class	scala/util/parsing/input/OffsetPosition
NameAndType	source:Ljava/lang/CharSequence;
Field	scala/util/parsing/input/OffsetPosition.source:Ljava/lang/CharSequence;
NameAndType	offset:I
Field	scala/util/parsing/input/OffsetPosition.offset:I
Asciz	java/lang/Object;
class	java/lang/Object
Asciz	()V;
NameAndType	"<init>":()V
Method	java/lang/Object."<init>":()V
Asciz	scala/util/parsing/input/Position$class;
class	scala/util/parsing/input/Position$class
Asciz	$init$;
Asciz	(Lscala/util/parsing/input/Position;)V;
NameAndType	$init$:(Lscala/util/parsing/input/Position;)V
Method	scala/util/parsing/input/Position$class.$init$:(Lscala/util/parsing/input/Position;)V
Asciz	scala/Product$class;
class	scala/Product$class
Asciz	(Lscala/Product;)V;
NameAndType	$init$:(Lscala/Product;)V
Method	scala/Product$class.$init$:(Lscala/Product;)V
Asciz	this;
Asciz	Lscala/util/parsing/input/OffsetPosition;;
Asciz	LocalVariableTable;
Asciz	gd1$1;
Asciz	(Ljava/lang/CharSequence;I)Z;
Asciz	()Ljava/lang/CharSequence;;
NameAndType	source:()Ljava/lang/CharSequence;
Method	scala/util/parsing/input/OffsetPosition.source:()Ljava/lang/CharSequence;
Asciz	equals;
Asciz	(Ljava/lang/Object;)Z;
NameAndType	equals:(Ljava/lang/Object;)Z
Method	java/lang/Object.equals:(Ljava/lang/Object;)Z
Asciz	()I;
NameAndType	offset:()I
Method	scala/util/parsing/input/OffsetPosition.offset:()I
Asciz	canEqual;
Asciz	productElement;
Asciz	(I)Ljava/lang/Object;;
Asciz	java/lang/IndexOutOfBoundsException;
class	java/lang/IndexOutOfBoundsException
Asciz	scala/runtime/BoxesRunTime;
class	scala/runtime/BoxesRunTime
Asciz	boxToInteger;
Asciz	(I)Ljava/lang/Integer;;
NameAndType	boxToInteger:(I)Ljava/lang/Integer;
Method	scala/runtime/BoxesRunTime.boxToInteger:(I)Ljava/lang/Integer;
Asciz	toString;
Asciz	()Ljava/lang/String;;
NameAndType	toString:()Ljava/lang/String;
Method	java/lang/Object.toString:()Ljava/lang/String;
Asciz	(Ljava/lang/String;)V;
NameAndType	"<init>":(Ljava/lang/String;)V
Method	java/lang/IndexOutOfBoundsException."<init>":(Ljava/lang/String;)V
Asciz	scala/MatchError;
class	scala/MatchError
Method	scala/MatchError."<init>":(Ljava/lang/String;)V
Asciz	productArity;
Asciz	productPrefix;
Asciz	OffsetPosition;
String	OffsetPosition
NameAndType	gd1$1:(Ljava/lang/CharSequence;I)Z
Method	scala/util/parsing/input/OffsetPosition.gd1$1:(Ljava/lang/CharSequence;I)Z
Asciz	scala/Equals;
class	scala/Equals
NameAndType	canEqual:(Ljava/lang/Object;)Z
InterfaceMethod	scala/Equals.canEqual:(Ljava/lang/Object;)Z
Asciz	temp6;
Asciz	temp7;
Asciz	temp8;
Asciz	hashCode;
Asciz	scala/runtime/ScalaRunTime$;
class	scala/runtime/ScalaRunTime$
Asciz	Lscala/runtime/ScalaRunTime$;;
NameAndType	MODULE$:Lscala/runtime/ScalaRunTime$;
Field	scala/runtime/ScalaRunTime$.MODULE$:Lscala/runtime/ScalaRunTime$;
Asciz	_hashCode;
Asciz	(Lscala/Product;)I;
NameAndType	_hashCode:(Lscala/Product;)I
Method	scala/runtime/ScalaRunTime$._hashCode:(Lscala/Product;)I
Asciz	copy;
Asciz	(Ljava/lang/CharSequence;I)Lscala/util/parsing/input/OffsetPosition;;
NameAndType	"<init>":(Ljava/lang/CharSequence;I)V
Method	scala/util/parsing/input/OffsetPosition."<init>":(Ljava/lang/CharSequence;I)V
Asciz	$less;
Asciz	(Lscala/util/parsing/input/Position;)Z;
Asciz	scala/util/parsing/input/Position;
class	scala/util/parsing/input/Position
InterfaceMethod	scala/util/parsing/input/Position.toString:()Ljava/lang/String;
Asciz	line;
NameAndType	line:()I
Method	scala/util/parsing/input/OffsetPosition.line:()I
InterfaceMethod	scala/util/parsing/input/Position.line:()I
Asciz	column;
NameAndType	column:()I
Method	scala/util/parsing/input/OffsetPosition.column:()I
InterfaceMethod	scala/util/parsing/input/Position.column:()I
Asciz	that;
Asciz	Lscala/util/parsing/input/Position;;
Asciz	temp2;
Asciz	temp4;
Asciz	scala/collection/mutable/StringBuilder;
class	scala/collection/mutable/StringBuilder
Method	scala/collection/mutable/StringBuilder."<init>":()V
Asciz	append;
Asciz	(I)Lscala/collection/mutable/StringBuilder;;
NameAndType	append:(I)Lscala/collection/mutable/StringBuilder;
Method	scala/collection/mutable/StringBuilder.append:(I)Lscala/collection/mutable/StringBuilder;
Asciz	.;
String	.
Asciz	(Ljava/lang/Object;)Lscala/collection/mutable/StringBuilder;;
NameAndType	append:(Ljava/lang/Object;)Lscala/collection/mutable/StringBuilder;
Method	scala/collection/mutable/StringBuilder.append:(Ljava/lang/Object;)Lscala/collection/mutable/StringBuilder;
Method	scala/collection/mutable/StringBuilder.toString:()Ljava/lang/String;
Asciz	lineContents;
Asciz	()[I;
NameAndType	index:()[I
Method	scala/util/parsing/input/OffsetPosition.index:()[I
Asciz	java/lang/CharSequence;
class	java/lang/CharSequence
Asciz	subSequence;
Asciz	(II)Ljava/lang/CharSequence;;
NameAndType	subSequence:(II)Ljava/lang/CharSequence;
InterfaceMethod	java/lang/CharSequence.subSequence:(II)Ljava/lang/CharSequence;
Asciz	lo;
Asciz	hi;
Asciz	mid;
NameAndType	bitmap$0:I
Field	scala/util/parsing/input/OffsetPosition.bitmap$0:I
Asciz	scala/runtime/ObjectRef;
class	scala/runtime/ObjectRef
Asciz	scala/collection/mutable/ArrayBuffer;
class	scala/collection/mutable/ArrayBuffer
Method	scala/collection/mutable/ArrayBuffer."<init>":()V
Asciz	(Ljava/lang/Object;)V;
NameAndType	"<init>":(Ljava/lang/Object;)V
Method	scala/runtime/ObjectRef."<init>":(Ljava/lang/Object;)V
Asciz	elem;
Asciz	Ljava/lang/Object;;
NameAndType	elem:Ljava/lang/Object;
Field	scala/runtime/ObjectRef.elem:Ljava/lang/Object;
Asciz	$plus$eq;
Asciz	(Ljava/lang/Object;)Lscala/collection/mutable/ArrayBuffer;;
NameAndType	$plus$eq:(Ljava/lang/Object;)Lscala/collection/mutable/ArrayBuffer;
Method	scala/collection/mutable/ArrayBuffer.$plus$eq:(Ljava/lang/Object;)Lscala/collection/mutable/ArrayBuffer;
Asciz	length;
NameAndType	length:()I
InterfaceMethod	java/lang/CharSequence.length:()I
Asciz	scala/collection/immutable/Range$$anon$2;
class	scala/collection/immutable/Range$$anon$2
Asciz	(II)V;
NameAndType	"<init>":(II)V
Method	scala/collection/immutable/Range$$anon$2."<init>":(II)V
Asciz	scala/collection/immutable/Range$ByOne;
class	scala/collection/immutable/Range$ByOne
Asciz	scala/util/parsing/input/OffsetPosition$$anonfun$index$1;
class	scala/util/parsing/input/OffsetPosition$$anonfun$index$1
Asciz	(Lscala/util/parsing/input/OffsetPosition;Lscala/runtime/ObjectRef;)V;
NameAndType	"<init>":(Lscala/util/parsing/input/OffsetPosition;Lscala/runtime/ObjectRef;)V
Method	scala/util/parsing/input/OffsetPosition$$anonfun$index$1."<init>":(Lscala/util/parsing/input/OffsetPosition;Lscala/runtime/ObjectRef;)V
Asciz	foreach;
Asciz	(Lscala/Function1;)V;
NameAndType	foreach:(Lscala/Function1;)V
InterfaceMethod	scala/collection/immutable/Range$ByOne.foreach:(Lscala/Function1;)V
Asciz	scala/reflect/Manifest$;
class	scala/reflect/Manifest$
Asciz	Lscala/reflect/Manifest$;;
NameAndType	MODULE$:Lscala/reflect/Manifest$;
Field	scala/reflect/Manifest$.MODULE$:Lscala/reflect/Manifest$;
Asciz	Int;
Asciz	()Ljava/lang/Object;;
NameAndType	Int:()Ljava/lang/Object;
Method	scala/reflect/Manifest$.Int:()Ljava/lang/Object;
Asciz	scala/reflect/ClassManifest;
class	scala/reflect/ClassManifest
Asciz	scala/collection/TraversableLike;
class	scala/collection/TraversableLike
Asciz	toArray;
Asciz	(Lscala/reflect/ClassManifest;)Ljava/lang/Object;;
NameAndType	toArray:(Lscala/reflect/ClassManifest;)Ljava/lang/Object;
InterfaceMethod	scala/collection/TraversableLike.toArray:(Lscala/reflect/ClassManifest;)Ljava/lang/Object;
class	"[I"
NameAndType	index:[I
Field	scala/util/parsing/input/OffsetPosition.index:[I
Asciz	java/lang/Throwable;
class	java/lang/Throwable
Asciz	start$10;
Asciz	end0;
Asciz	lineStarts$1;
Asciz	Lscala/runtime/ObjectRef;;
Asciz	copy$default$1;
Asciz	copy$default$2;
Asciz	longString;
Asciz	(Lscala/util/parsing/input/Position;)Ljava/lang/String;;
NameAndType	longString:(Lscala/util/parsing/input/Position;)Ljava/lang/String;
Method	scala/util/parsing/input/Position$class.longString:(Lscala/util/parsing/input/Position;)Ljava/lang/String;
Asciz	productElements;
Asciz	()Lscala/collection/Iterator;;
Asciz	(Lscala/Product;)Lscala/collection/Iterator;;
NameAndType	productElements:(Lscala/Product;)Lscala/collection/Iterator;
Method	scala/Product$class.productElements:(Lscala/Product;)Lscala/collection/Iterator;
Asciz	productIterator;
NameAndType	productIterator:(Lscala/Product;)Lscala/collection/Iterator;
Method	scala/Product$class.productIterator:(Lscala/Product;)Lscala/collection/Iterator;
Asciz	ScalaSig;
Asciz	InnerClasses;
Asciz	scala/collection/immutable/Range;
class	scala/collection/immutable/Range
Asciz	ByOne;
Asciz	$anon$2;
Asciz	$anonfun$index$1;
Asciz	scala/ScalaObject;
class	scala/ScalaObject
Asciz	scala/Product;
class	scala/Product
Asciz	java/io/Serializable;
class	java/io/Serializable

{
public volatile int bitmap$0;
  Signature: I

private int[] index;
  Signature: [I

private final int offset;
  Signature: I

private final java.lang.CharSequence source;
  Signature: Ljava/lang/CharSequence;

public static final scala.Function1 tuple();
  Signature: ()Lscala/Function1;
  Code:
   Stack=1, Locals=0, Args_size=0
	getstatic	Field scala/util/parsing/input/OffsetPosition$.MODULE$:Lscala/util/parsing/input/OffsetPosition$;
	invokevirtual	Method scala/util/parsing/input/OffsetPosition$.tuple:()Lscala/Function1;
	areturn
  Labels:

public static final scala.Function1 curry();
  Signature: ()Lscala/Function1;
  Code:
   Stack=1, Locals=0, Args_size=0
	getstatic	Field scala/util/parsing/input/OffsetPosition$.MODULE$:Lscala/util/parsing/input/OffsetPosition$;
	invokevirtual	Method scala/util/parsing/input/OffsetPosition$.curry:()Lscala/Function1;
	areturn
  Labels:

public scala.util.parsing.input.OffsetPosition(java.lang.CharSequence, int);
  Signature: (Ljava/lang/CharSequence;I)V
  Code:
   Stack=2, Locals=3, Args_size=3
	aload_0
	aload_1
	putfield	Field source:Ljava/lang/CharSequence;
	aload_0
	iload_2
	putfield	Field offset:I
	aload_0
	invokespecial	Method java/lang/Object."<init>":()V
	aload_0
	invokestatic	Method scala/util/parsing/input/Position$class.$init$:(Lscala/util/parsing/input/Position;)V
	aload_0
	invokestatic	Method scala/Product$class.$init$:(Lscala/Product;)V
	return
  Labels:
  LocalVariableTable: 
   Start  Length  Slot  Name   Signature
   0      23      0    this       Lscala/util/parsing/input/OffsetPosition;
   0      23      1    source       Ljava/lang/CharSequence;
   0      23      2    offset       I


private final boolean gd1$1(java.lang.CharSequence, int);
  Signature: (Ljava/lang/CharSequence;I)Z
  Code:
   Stack=2, Locals=4, Args_size=3
	aload_1
	aload_0
	invokevirtual	Method source:()Ljava/lang/CharSequence;
	astore_3
	dup
	ifnonnull	l1 // aload_3
	pop
	aload_3
	ifnull	l2 // iload_2
	goto	l3 // iconst_0
l1	aload_3
	invokevirtual	Method java/lang/Object.equals:(Ljava/lang/Object;)Z
	ifeq	l3 // iconst_0
l2	iload_2
	aload_0
	invokevirtual	Method offset:()I
	if_icmpne	l3 // iconst_0
	iconst_1
	goto	l4 // ireturn
l3	iconst_0
l4	ireturn
  Labels:
   	l1 = 18 // aload_3
   	l2 = 25 // iload_2
   	l3 = 37 // iconst_0
   	l4 = 38 // ireturn

public boolean canEqual(java.lang.Object);
  Signature: (Ljava/lang/Object;)Z
  Code:
   Stack=1, Locals=2, Args_size=2
	aload_1
	instanceof	class scala/util/parsing/input/OffsetPosition
	ireturn
  Labels:

public java.lang.Object productElement(int);
  Signature: (I)Ljava/lang/Object;
  Code:
   Stack=3, Locals=3, Args_size=2
	iload_1
	tableswitch{ //0 to 1
		0: 89;
		1: 58;
		default: 24 }
	iconst_1
	ifeq	l1 // new
	new	class java/lang/IndexOutOfBoundsException
	dup
	iload_1
	invokestatic	Method scala/runtime/BoxesRunTime.boxToInteger:(I)Ljava/lang/Integer;
	invokevirtual	Method java/lang/Object.toString:()Ljava/lang/String;
	invokespecial	Method java/lang/IndexOutOfBoundsException."<init>":(Ljava/lang/String;)V
	athrow
l1	new	class scala/MatchError
	dup
	iload_1
	invokestatic	Method scala/runtime/BoxesRunTime.boxToInteger:(I)Ljava/lang/Integer;
	invokevirtual	Method java/lang/Object.toString:()Ljava/lang/String;
	invokespecial	Method scala/MatchError."<init>":(Ljava/lang/String;)V
	athrow
	iconst_1
	ifeq	l2 // new
	aload_0
	invokevirtual	Method offset:()I
	istore_2
	iload_2
	invokestatic	Method scala/runtime/BoxesRunTime.boxToInteger:(I)Ljava/lang/Integer;
	goto	l3 // areturn
l2	new	class scala/MatchError
	dup
	iload_1
	invokestatic	Method scala/runtime/BoxesRunTime.boxToInteger:(I)Ljava/lang/Integer;
	invokevirtual	Method java/lang/Object.toString:()Ljava/lang/String;
	invokespecial	Method scala/MatchError."<init>":(Ljava/lang/String;)V
	athrow
	iconst_1
	ifeq	l4 // new
	aload_0
	invokevirtual	Method source:()Ljava/lang/CharSequence;
l3	areturn
l4	new	class scala/MatchError
	dup
	iload_1
	invokestatic	Method scala/runtime/BoxesRunTime.boxToInteger:(I)Ljava/lang/Integer;
	invokevirtual	Method java/lang/Object.toString:()Ljava/lang/String;
	invokespecial	Method scala/MatchError."<init>":(Ljava/lang/String;)V
	athrow
  Labels:
   	l1 = 43 // new
   	l2 = 74 // new
   	l3 = 97 // areturn
   	l4 = 98 // new

public int productArity();
  Signature: ()I
  Code:
   Stack=1, Locals=1, Args_size=1
	iconst_2
	ireturn
  Labels:

public java.lang.String productPrefix();
  Signature: ()Ljava/lang/String;
  Code:
   Stack=1, Locals=1, Args_size=1
	ldc	String OffsetPosition
	areturn
  Labels:

public boolean equals(java.lang.Object);
  Signature: (Ljava/lang/Object;)Z
  Code:
   Stack=3, Locals=5, Args_size=2
	aload_0
	aload_1
	if_acmpeq	l1 // iconst_1
	aload_1
	instanceof	class scala/util/parsing/input/OffsetPosition
	ifeq	l2 // iconst_1
	aload_1
	checkcast	class scala/util/parsing/input/OffsetPosition
	astore_2
	aload_2
	invokevirtual	Method source:()Ljava/lang/CharSequence;
	astore_3
	aload_2
	invokevirtual	Method offset:()I
	istore	4
	aload_0
	aload_3
	iload	4
	invokespecial	Method gd1$1:(Ljava/lang/CharSequence;I)Z
	ifeq	l3 // iconst_1
	aload_1
	checkcast	class scala/util/parsing/input/OffsetPosition
	aload_0
	invokeinterface	InterfaceMethod scala/Equals.canEqual:(Ljava/lang/Object;)Z
	goto	l4 // ifeq
l3	iconst_1
	ifeq	l5 // new
	iconst_0
	goto	l4 // ifeq
l5	new	class scala/MatchError
	dup
	aload_1
	invokevirtual	Method java/lang/Object.toString:()Ljava/lang/String;
	invokespecial	Method scala/MatchError."<init>":(Ljava/lang/String;)V
	athrow
l2	iconst_1
	ifeq	l6 // new
	iconst_0
l4	ifeq	l7 // iconst_0
l1	iconst_1
	goto	l8 // ireturn
l7	iconst_0
l8	ireturn
l6	new	class scala/MatchError
	dup
	aload_1
	invokevirtual	Method java/lang/Object.toString:()Ljava/lang/String;
	invokespecial	Method scala/MatchError."<init>":(Ljava/lang/String;)V
	athrow
  Labels:
   	l3 = 51 // iconst_1
   	l5 = 59 // new
   	l2 = 71 // iconst_1
   	l4 = 76 // ifeq
   	l1 = 79 // iconst_1
   	l7 = 83 // iconst_0
   	l8 = 84 // ireturn
   	l6 = 85 // new
  LocalVariableTable: 
   Start  Length  Slot  Name   Signature
   0      97      0    this       Lscala/util/parsing/input/OffsetPosition;
   17      54      2    temp6       Lscala/util/parsing/input/OffsetPosition;
   22      49      3    temp7       Ljava/lang/CharSequence;
   28      43      4    temp8       I


public int hashCode();
  Signature: ()I
  Code:
   Stack=2, Locals=1, Args_size=1
	getstatic	Field scala/runtime/ScalaRunTime$.MODULE$:Lscala/runtime/ScalaRunTime$;
	aload_0
	invokevirtual	Method scala/runtime/ScalaRunTime$._hashCode:(Lscala/Product;)I
	ireturn
  Labels:

public scala.util.parsing.input.OffsetPosition copy(java.lang.CharSequence, int);
  Signature: (Ljava/lang/CharSequence;I)Lscala/util/parsing/input/OffsetPosition;
  Code:
   Stack=4, Locals=3, Args_size=3
	new	class scala/util/parsing/input/OffsetPosition
	dup
	aload_1
	iload_2
	invokespecial	Method "<init>":(Ljava/lang/CharSequence;I)V
	areturn
  Labels:
  LocalVariableTable: 
   Start  Length  Slot  Name   Signature
   0      10      0    this       Lscala/util/parsing/input/OffsetPosition;
   0      10      1    source       Ljava/lang/CharSequence;
   0      10      2    offset       I


public boolean $less(scala.util.parsing.input.Position);
  Signature: (Lscala/util/parsing/input/Position;)Z
  Code:
   Stack=3, Locals=4, Args_size=2
	aload_1
	instanceof	class scala/util/parsing/input/OffsetPosition
	ifeq	l1 // iconst_1
	aload_1
	checkcast	class scala/util/parsing/input/OffsetPosition
	astore_2
	aload_2
	invokevirtual	Method offset:()I
	istore_3
	iconst_1
	ifeq	l2 // new
	aload_0
	invokevirtual	Method offset:()I
	iload_3
	if_icmpge	l3 // iconst_0
	iconst_1
	goto	l4 // ireturn
l3	iconst_0
	goto	l4 // ireturn
l2	new	class scala/MatchError
	dup
	aload_1
	invokeinterface	InterfaceMethod scala/util/parsing/input/Position.toString:()Ljava/lang/String;
	invokespecial	Method scala/MatchError."<init>":(Ljava/lang/String;)V
	athrow
l1	iconst_1
	ifeq	l5 // new
	aload_0
	invokevirtual	Method line:()I
	aload_1
	invokeinterface	InterfaceMethod scala/util/parsing/input/Position.line:()I
	if_icmplt	l6 // iconst_1
	aload_0
	invokevirtual	Method line:()I
	aload_1
	invokeinterface	InterfaceMethod scala/util/parsing/input/Position.line:()I
	if_icmpne	l7 // iconst_0
	aload_0
	invokevirtual	Method column:()I
	aload_1
	invokeinterface	InterfaceMethod scala/util/parsing/input/Position.column:()I
	if_icmpge	l7 // iconst_0
l6	iconst_1
	goto	l4 // ireturn
l7	iconst_0
l4	ireturn
l5	new	class scala/MatchError
	dup
	aload_1
	invokeinterface	InterfaceMethod scala/util/parsing/input/Position.toString:()Ljava/lang/String;
	invokespecial	Method scala/MatchError."<init>":(Ljava/lang/String;)V
	athrow
  Labels:
   	l3 = 33 // iconst_0
   	l2 = 37 // new
   	l1 = 51 // iconst_1
   	l6 = 94 // iconst_1
   	l7 = 98 // iconst_0
   	l4 = 99 // ireturn
   	l5 = 100 // new
  LocalVariableTable: 
   Start  Length  Slot  Name   Signature
   0      114      0    this       Lscala/util/parsing/input/OffsetPosition;
   0      114      1    that       Lscala/util/parsing/input/Position;
   12      39      2    temp2       Lscala/util/parsing/input/OffsetPosition;
   17      34      3    temp4       I


public java.lang.String toString();
  Signature: ()Ljava/lang/String;
  Code:
   Stack=2, Locals=2, Args_size=1
	new	class scala/collection/mutable/StringBuilder
	dup
	invokespecial	Method scala/collection/mutable/StringBuilder."<init>":()V
	aload_0
	invokevirtual	Method line:()I
	invokevirtual	Method scala/collection/mutable/StringBuilder.append:(I)Lscala/collection/mutable/StringBuilder;
	ldc	String .
	invokevirtual	Method scala/collection/mutable/StringBuilder.append:(Ljava/lang/Object;)Lscala/collection/mutable/StringBuilder;
	aload_0
	invokevirtual	Method column:()I
	istore_1
	iload_1
	invokestatic	Method scala/runtime/BoxesRunTime.boxToInteger:(I)Ljava/lang/Integer;
	invokevirtual	Method scala/collection/mutable/StringBuilder.append:(Ljava/lang/Object;)Lscala/collection/mutable/StringBuilder;
	invokevirtual	Method scala/collection/mutable/StringBuilder.toString:()Ljava/lang/String;
	areturn
  Labels:

public java.lang.String lineContents();
  Signature: ()Ljava/lang/String;
  Code:
   Stack=4, Locals=1, Args_size=1
	aload_0
	invokevirtual	Method source:()Ljava/lang/CharSequence;
	aload_0
	invokespecial	Method index:()[I
	aload_0
	invokevirtual	Method line:()I
	iconst_1
	isub
	iaload
	aload_0
	invokespecial	Method index:()[I
	aload_0
	invokevirtual	Method line:()I
	iaload
	invokeinterface	InterfaceMethod java/lang/CharSequence.subSequence:(II)Ljava/lang/CharSequence;
	invokevirtual	Method java/lang/Object.toString:()Ljava/lang/String;
	areturn
  Labels:

public int column();
  Signature: ()I
  Code:
   Stack=4, Locals=1, Args_size=1
	aload_0
	invokevirtual	Method offset:()I
	aload_0
	invokespecial	Method index:()[I
	aload_0
	invokevirtual	Method line:()I
	iconst_1
	isub
	iaload
	isub
	iconst_1
	iadd
	ireturn
  Labels:

public int line();
  Signature: ()I
  Code:
   Stack=3, Locals=4, Args_size=1
	iconst_0
	istore_1
	aload_0
	invokespecial	Method index:()[I
	arraylength
	iconst_1
	isub
	istore_2
l3	iload_1
	iconst_1
	iadd
	iload_2
	if_icmpge	l1 // iload_1
	iload_2
	iload_1
	iadd
	iconst_2
	idiv
	istore_3
	aload_0
	invokevirtual	Method offset:()I
	aload_0
	invokespecial	Method index:()[I
	iload_3
	iaload
	if_icmpge	l2 // iload_3
	iload_3
	istore_2
	goto	l3 // iload_1
l2	iload_3
	istore_1
	goto	l3 // iload_1
l1	iload_1
	iconst_1
	iadd
	ireturn
  Labels:
   	l3 = 10 // iload_1
   	l2 = 41 // iload_3
   	l1 = 46 // iload_1
  LocalVariableTable: 
   Start  Length  Slot  Name   Signature
   0      50      0    this       Lscala/util/parsing/input/OffsetPosition;
   2      47      1    lo       I
   10      39      2    hi       I
   23      23      3    mid       I


private int[] index();
  Signature: ()[I
  Code:
   Stack=6, Locals=6, Args_size=1
	aload_0
	getfield	Field bitmap$0:I
	iconst_1
	iand
	iconst_0
	if_icmpne	l1 // aload_0
	aload_0
	dup
	pop
	monitorenter
	aload_0
	getfield	Field bitmap$0:I
	iconst_1
	iand
	iconst_0
	if_icmpne	l2 // aload_0
	aload_0
	new	class scala/runtime/ObjectRef
	dup
	new	class scala/collection/mutable/ArrayBuffer
	dup
	invokespecial	Method scala/collection/mutable/ArrayBuffer."<init>":()V
	invokespecial	Method scala/runtime/ObjectRef."<init>":(Ljava/lang/Object;)V
	astore	5
	aload	5
	getfield	Field scala/runtime/ObjectRef.elem:Ljava/lang/Object;
	checkcast	class scala/collection/mutable/ArrayBuffer
	iconst_0
	istore_1
	iload_1
	invokestatic	Method scala/runtime/BoxesRunTime.boxToInteger:(I)Ljava/lang/Integer;
	invokevirtual	Method scala/collection/mutable/ArrayBuffer.$plus$eq:(Ljava/lang/Object;)Lscala/collection/mutable/ArrayBuffer;
	pop
	aload_0
	invokevirtual	Method source:()Ljava/lang/CharSequence;
	invokeinterface	InterfaceMethod java/lang/CharSequence.length:()I
	istore_3
	iconst_0
	istore_2
	new	class scala/collection/immutable/Range$$anon$2
	dup
	iload_2
	iload_3
	invokespecial	Method scala/collection/immutable/Range$$anon$2."<init>":(II)V
	checkcast	class scala/collection/immutable/Range$ByOne
	new	class scala/util/parsing/input/OffsetPosition$$anonfun$index$1
	dup
	aload_0
	aload	5
	invokespecial	Method scala/util/parsing/input/OffsetPosition$$anonfun$index$1."<init>":(Lscala/util/parsing/input/OffsetPosition;Lscala/runtime/ObjectRef;)V
	invokeinterface	InterfaceMethod scala/collection/immutable/Range$ByOne.foreach:(Lscala/Function1;)V
	aload	5
	getfield	Field scala/runtime/ObjectRef.elem:Ljava/lang/Object;
	checkcast	class scala/collection/mutable/ArrayBuffer
	aload_0
	invokevirtual	Method source:()Ljava/lang/CharSequence;
	invokeinterface	InterfaceMethod java/lang/CharSequence.length:()I
	istore	4
	iload	4
	invokestatic	Method scala/runtime/BoxesRunTime.boxToInteger:(I)Ljava/lang/Integer;
	invokevirtual	Method scala/collection/mutable/ArrayBuffer.$plus$eq:(Ljava/lang/Object;)Lscala/collection/mutable/ArrayBuffer;
	pop
	aload	5
	getfield	Field scala/runtime/ObjectRef.elem:Ljava/lang/Object;
	checkcast	class scala/collection/mutable/ArrayBuffer
	getstatic	Field scala/reflect/Manifest$.MODULE$:Lscala/reflect/Manifest$;
	invokevirtual	Method scala/reflect/Manifest$.Int:()Ljava/lang/Object;
	checkcast	class scala/reflect/ClassManifest
	invokeinterface	InterfaceMethod scala/collection/TraversableLike.toArray:(Lscala/reflect/ClassManifest;)Ljava/lang/Object;
	checkcast	class "[I"
	putfield	Field index:[I
	aload_0
	aload_0
	getfield	Field bitmap$0:I
	iconst_1
	ior
	putfield	Field bitmap$0:I
l2	aload_0
	monitorexit
l1	aload_0
	getfield	Field index:[I
	areturn
	aload_0
	monitorexit
	athrow
  Labels:
   	l2 = 164 // aload_0
   	l1 = 166 // aload_0
  Exception table:
   from   to  target type
    14   166   171   Class java/lang/Throwable

  LocalVariableTable: 
   Start  Length  Slot  Name   Signature
   0      174      0    this       Lscala/util/parsing/input/OffsetPosition;
   71      9      2    start$10       I
   69      11      3    end0       I
   41      110      5    lineStarts$1       Lscala/runtime/ObjectRef;


public int offset();
  Signature: ()I
  Code:
   Stack=1, Locals=1, Args_size=1
	aload_0
	getfield	Field offset:I
	ireturn
  Labels:

public java.lang.CharSequence source();
  Signature: ()Ljava/lang/CharSequence;
  Code:
   Stack=1, Locals=1, Args_size=1
	aload_0
	getfield	Field source:Ljava/lang/CharSequence;
	areturn
  Labels:

public java.lang.CharSequence copy$default$1();
  Signature: ()Ljava/lang/CharSequence;
  Code:
   Stack=1, Locals=1, Args_size=1
	aload_0
	invokevirtual	Method source:()Ljava/lang/CharSequence;
	areturn
  Labels:

public int copy$default$2();
  Signature: ()I
  Code:
   Stack=1, Locals=1, Args_size=1
	aload_0
	invokevirtual	Method offset:()I
	ireturn
  Labels:

public java.lang.String longString();
  Signature: ()Ljava/lang/String;
  Code:
   Stack=1, Locals=1, Args_size=1
	aload_0
	invokestatic	Method scala/util/parsing/input/Position$class.longString:(Lscala/util/parsing/input/Position;)Ljava/lang/String;
	areturn
  Labels:

public scala.collection.Iterator productElements();
  Signature: ()Lscala/collection/Iterator;
  Code:
   Stack=1, Locals=1, Args_size=1
	aload_0
	invokestatic	Method scala/Product$class.productElements:(Lscala/Product;)Lscala/collection/Iterator;
	areturn
  Labels:

public scala.collection.Iterator productIterator();
  Signature: ()Lscala/collection/Iterator;
  Code:
   Stack=1, Locals=1, Args_size=1
	aload_0
	invokestatic	Method scala/Product$class.productIterator:(Lscala/Product;)Lscala/collection/Iterator;
	areturn
  Labels:

}

