Compiled from "OffsetPosition.scala"
public final class scala.util.parsing.input.OffsetPosition$ extends java.lang.Object implements scala.Function2,scala.ScalaObject
  SourceFile: "OffsetPosition.scala"
  Scala: length = 0x
   
  InnerClass: 
   public final $anonfun$index$1=class scala/util/parsing/input/OffsetPosition$$anonfun$index$1 of class scala/util/parsing/input/OffsetPosition
  minor version: 0
  major version: 49
  Constant pool:
Asciz	SourceFile;
Asciz	OffsetPosition.scala;
Asciz	Scala;
Asciz	MODULE$;
Asciz	Lscala/util/parsing/input/OffsetPosition$;;
Asciz	<clinit>;
Asciz	()V;
Asciz	Code;
Asciz	scala/util/parsing/input/OffsetPosition$;
class	scala/util/parsing/input/OffsetPosition$
Asciz	<init>;
NameAndType	"<init>":()V
Method	scala/util/parsing/input/OffsetPosition$."<init>":()V
Asciz	toString;
Asciz	()Ljava/lang/String;;
Asciz	LineNumberTable;
Asciz	scala/Function2$class;
class	scala/Function2$class
Asciz	(Lscala/Function2;)Ljava/lang/String;;
NameAndType	toString:(Lscala/Function2;)Ljava/lang/String;
Method	scala/Function2$class.toString:(Lscala/Function2;)Ljava/lang/String;
Asciz	curried;
Asciz	()Lscala/Function1;;
Asciz	(Lscala/Function2;)Lscala/Function1;;
NameAndType	curried:(Lscala/Function2;)Lscala/Function1;
Method	scala/Function2$class.curried:(Lscala/Function2;)Lscala/Function1;
Asciz	curry;
NameAndType	curry:(Lscala/Function2;)Lscala/Function1;
Method	scala/Function2$class.curry:(Lscala/Function2;)Lscala/Function1;
Asciz	Deprecated;
Asciz	tupled;
NameAndType	tupled:(Lscala/Function2;)Lscala/Function1;
Method	scala/Function2$class.tupled:(Lscala/Function2;)Lscala/Function1;
Asciz	unapply;
Asciz	(Lscala/util/parsing/input/OffsetPosition;)Lscala/Some;;
Asciz	scala/Some;
class	scala/Some
Asciz	scala/Tuple2;
class	scala/Tuple2
Asciz	scala/util/parsing/input/OffsetPosition;
class	scala/util/parsing/input/OffsetPosition
Asciz	source;
Asciz	()Ljava/lang/CharSequence;;
NameAndType	source:()Ljava/lang/CharSequence;
Method	scala/util/parsing/input/OffsetPosition.source:()Ljava/lang/CharSequence;
Asciz	offset;
Asciz	()I;
NameAndType	offset:()I
Method	scala/util/parsing/input/OffsetPosition.offset:()I
Asciz	scala/runtime/BoxesRunTime;
class	scala/runtime/BoxesRunTime
Asciz	boxToInteger;
Asciz	(I)Ljava/lang/Integer;;
NameAndType	boxToInteger:(I)Ljava/lang/Integer;
Method	scala/runtime/BoxesRunTime.boxToInteger:(I)Ljava/lang/Integer;
Asciz	(Ljava/lang/Object;Ljava/lang/Object;)V;
NameAndType	"<init>":(Ljava/lang/Object;Ljava/lang/Object;)V
Method	scala/Tuple2."<init>":(Ljava/lang/Object;Ljava/lang/Object;)V
Asciz	(Ljava/lang/Object;)V;
NameAndType	"<init>":(Ljava/lang/Object;)V
Method	scala/Some."<init>":(Ljava/lang/Object;)V
Asciz	this;
Asciz	x$0;
Asciz	Lscala/util/parsing/input/OffsetPosition;;
Asciz	LocalVariableTable;
Asciz	apply;
Asciz	(Ljava/lang/CharSequence;I)Lscala/util/parsing/input/OffsetPosition;;
Asciz	(Ljava/lang/CharSequence;I)V;
NameAndType	"<init>":(Ljava/lang/CharSequence;I)V
Method	scala/util/parsing/input/OffsetPosition."<init>":(Ljava/lang/CharSequence;I)V
Asciz	Ljava/lang/CharSequence;;
Asciz	I;
Asciz	(Ljava/lang/Object;Ljava/lang/Object;)Ljava/lang/Object;;
Asciz	java/lang/CharSequence;
class	java/lang/CharSequence
Asciz	unboxToInt;
Asciz	(Ljava/lang/Object;)I;
NameAndType	unboxToInt:(Ljava/lang/Object;)I
Method	scala/runtime/BoxesRunTime.unboxToInt:(Ljava/lang/Object;)I
NameAndType	apply:(Ljava/lang/CharSequence;I)Lscala/util/parsing/input/OffsetPosition;
Method	scala/util/parsing/input/OffsetPosition$.apply:(Ljava/lang/CharSequence;I)Lscala/util/parsing/input/OffsetPosition;
Asciz	v1;
Asciz	Ljava/lang/Object;;
Asciz	v2;
Asciz	java/lang/Object;
class	java/lang/Object
Method	java/lang/Object."<init>":()V
NameAndType	MODULE$:Lscala/util/parsing/input/OffsetPosition$;
Field	scala/util/parsing/input/OffsetPosition$.MODULE$:Lscala/util/parsing/input/OffsetPosition$;
Asciz	$init$;
Asciz	(Lscala/Function2;)V;
NameAndType	$init$:(Lscala/Function2;)V
Method	scala/Function2$class.$init$:(Lscala/Function2;)V
Asciz	InnerClasses;
Asciz	scala/util/parsing/input/OffsetPosition$$anonfun$index$1;
class	scala/util/parsing/input/OffsetPosition$$anonfun$index$1
Asciz	$anonfun$index$1;
Asciz	scala/Function2;
class	scala/Function2
Asciz	scala/ScalaObject;
class	scala/ScalaObject

{
public static final scala.util.parsing.input.OffsetPosition$ MODULE$;
  Signature: Lscala/util/parsing/input/OffsetPosition$;

public static {};
  Signature: ()V
  Code:
   Stack=1, Locals=0, Args_size=0
	new	class scala/util/parsing/input/OffsetPosition$
	invokespecial	Method "<init>":()V
	return
  Labels:

public java.lang.String toString();
  Signature: ()Ljava/lang/String;
  Code:
   Stack=1, Locals=1, Args_size=1
	aload_0
	invokestatic	Method scala/Function2$class.toString:(Lscala/Function2;)Ljava/lang/String;
	areturn
  Labels:

public scala.Function1 curried();
  Signature: ()Lscala/Function1;
  Code:
   Stack=1, Locals=1, Args_size=1
	aload_0
	invokestatic	Method scala/Function2$class.curried:(Lscala/Function2;)Lscala/Function1;
	areturn
  Labels:

public scala.Function1 curry();
  Signature: ()Lscala/Function1;
  Code:
   Stack=1, Locals=1, Args_size=1
	aload_0
	invokestatic	Method scala/Function2$class.curry:(Lscala/Function2;)Lscala/Function1;
	areturn
  Labels:
  Deprecated: true

public scala.Function1 tupled();
  Signature: ()Lscala/Function1;
  Code:
   Stack=1, Locals=1, Args_size=1
	aload_0
	invokestatic	Method scala/Function2$class.tupled:(Lscala/Function2;)Lscala/Function1;
	areturn
  Labels:

public scala.Some unapply(scala.util.parsing.input.OffsetPosition);
  Signature: (Lscala/util/parsing/input/OffsetPosition;)Lscala/Some;
  Code:
   Stack=6, Locals=3, Args_size=2
	new	class scala/Some
	dup
	new	class scala/Tuple2
	dup
	aload_1
	invokevirtual	Method scala/util/parsing/input/OffsetPosition.source:()Ljava/lang/CharSequence;
	aload_1
	invokevirtual	Method scala/util/parsing/input/OffsetPosition.offset:()I
	istore_2
	iload_2
	invokestatic	Method scala/runtime/BoxesRunTime.boxToInteger:(I)Ljava/lang/Integer;
	invokespecial	Method scala/Tuple2."<init>":(Ljava/lang/Object;Ljava/lang/Object;)V
	invokespecial	Method scala/Some."<init>":(Ljava/lang/Object;)V
	areturn
  Labels:
  LocalVariableTable: 
   Start  Length  Slot  Name   Signature
   0      28      0    this       Lscala/util/parsing/input/OffsetPosition$;
   0      28      1    x$0       Lscala/util/parsing/input/OffsetPosition;


public scala.util.parsing.input.OffsetPosition apply(java.lang.CharSequence, int);
  Signature: (Ljava/lang/CharSequence;I)Lscala/util/parsing/input/OffsetPosition;
  Code:
   Stack=4, Locals=3, Args_size=3
	new	class scala/util/parsing/input/OffsetPosition
	dup
	aload_1
	iload_2
	invokespecial	Method scala/util/parsing/input/OffsetPosition."<init>":(Ljava/lang/CharSequence;I)V
	areturn
  Labels:
  LocalVariableTable: 
   Start  Length  Slot  Name   Signature
   0      10      0    this       Lscala/util/parsing/input/OffsetPosition$;
   0      10      1    source       Ljava/lang/CharSequence;
   0      10      2    offset       I


public java.lang.Object apply(java.lang.Object, java.lang.Object);
  Signature: (Ljava/lang/Object;Ljava/lang/Object;)Ljava/lang/Object;
  Code:
   Stack=3, Locals=3, Args_size=3
	aload_0
	aload_1
	checkcast	class java/lang/CharSequence
	aload_2
	invokestatic	Method scala/runtime/BoxesRunTime.unboxToInt:(Ljava/lang/Object;)I
	invokevirtual	Method apply:(Ljava/lang/CharSequence;I)Lscala/util/parsing/input/OffsetPosition;
	areturn
  Labels:
  LocalVariableTable: 
   Start  Length  Slot  Name   Signature
   0      13      0    this       Lscala/util/parsing/input/OffsetPosition$;
   0      13      1    v1       Ljava/lang/Object;
   0      13      2    v2       Ljava/lang/Object;


private scala.util.parsing.input.OffsetPosition$();
  Signature: ()V
  Code:
   Stack=1, Locals=1, Args_size=1
	aload_0
	invokespecial	Method java/lang/Object."<init>":()V
	aload_0
	putstatic	Field MODULE$:Lscala/util/parsing/input/OffsetPosition$;
	aload_0
	invokestatic	Method scala/Function2$class.$init$:(Lscala/Function2;)V
	return
  Labels:

}

