Compiled from "Position.scala"
public abstract class scala.util.parsing.input.Position$class extends java.lang.Object
  SourceFile: "Position.scala"
  Scala: length = 0x
   
  minor version: 0
  major version: 49
  Constant pool:
const #1 = Asciz	SourceFile;
const #2 = Asciz	Position.scala;
const #3 = Asciz	$init$;
const #4 = Asciz	(Lscala/util/parsing/input/Position;)V;
const #5 = Asciz	Code;
const #6 = Asciz	LineNumberTable;
const #7 = Asciz	$this;
const #8 = Asciz	Lscala/util/parsing/input/Position;;
const #9 = Asciz	LocalVariableTable;
const #10 = Asciz	$less;
const #11 = Asciz	(Lscala/util/parsing/input/Position;Lscala/util/parsing/input/Position;)Z;
const #12 = Asciz	scala/util/parsing/input/Position;
const #13 = class	#12;	//  scala/util/parsing/input/Position
const #14 = Asciz	line;
const #15 = Asciz	()I;
const #16 = NameAndType	#14:#15;//  line:()I
const #17 = InterfaceMethod	#13.#16;	//  scala/util/parsing/input/Position.line:()I
const #18 = Asciz	column;
const #19 = NameAndType	#18:#15;//  column:()I
const #20 = InterfaceMethod	#13.#19;	//  scala/util/parsing/input/Position.column:()I
const #21 = Asciz	that;
const #22 = Asciz	longString;
const #23 = Asciz	(Lscala/util/parsing/input/Position;)Ljava/lang/String;;
const #24 = Asciz	scala/collection/mutable/StringBuilder;
const #25 = class	#24;	//  scala/collection/mutable/StringBuilder
const #26 = Asciz	<init>;
const #27 = Asciz	()V;
const #28 = NameAndType	#26:#27;//  "<init>":()V
const #29 = Method	#25.#28;	//  scala/collection/mutable/StringBuilder."<init>":()V
const #30 = Asciz	lineContents;
const #31 = Asciz	()Ljava/lang/String;;
const #32 = NameAndType	#30:#31;//  lineContents:()Ljava/lang/String;
const #33 = InterfaceMethod	#13.#32;	//  scala/util/parsing/input/Position.lineContents:()Ljava/lang/String;
const #34 = Asciz	append;
const #35 = Asciz	(Ljava/lang/Object;)Lscala/collection/mutable/StringBuilder;;
const #36 = NameAndType	#34:#35;//  append:(Ljava/lang/Object;)Lscala/collection/mutable/StringBuilder;
const #37 = Method	#25.#36;	//  scala/collection/mutable/StringBuilder.append:(Ljava/lang/Object;)Lscala/collection/mutable/StringBuilder;
const #38 = Asciz	\n;
const #39 = String	#38;	//  \n
const #40 = Asciz	scala/Predef$;
const #41 = class	#40;	//  scala/Predef$
const #42 = Asciz	MODULE$;
const #43 = Asciz	Lscala/Predef$;;
const #44 = NameAndType	#42:#43;//  MODULE$:Lscala/Predef$;
const #45 = Field	#41.#44;	//  scala/Predef$.MODULE$:Lscala/Predef$;
const #46 = Asciz	 ;
const #47 = String	#46;	//   
const #48 = Asciz	stringWrapper;
const #49 = Asciz	(Ljava/lang/String;)Lscala/runtime/RichString;;
const #50 = NameAndType	#48:#49;//  stringWrapper:(Ljava/lang/String;)Lscala/runtime/RichString;
const #51 = Method	#41.#50;	//  scala/Predef$.stringWrapper:(Ljava/lang/String;)Lscala/runtime/RichString;
const #52 = Asciz	scala/runtime/RichString;
const #53 = class	#52;	//  scala/runtime/RichString
const #54 = Asciz	$times;
const #55 = Asciz	(I)Ljava/lang/String;;
const #56 = NameAndType	#54:#55;//  $times:(I)Ljava/lang/String;
const #57 = Method	#53.#56;	//  scala/runtime/RichString.$times:(I)Ljava/lang/String;
const #58 = Asciz	^;
const #59 = String	#58;	//  ^
const #60 = Asciz	toString;
const #61 = NameAndType	#60:#31;//  toString:()Ljava/lang/String;
const #62 = Method	#25.#61;	//  scala/collection/mutable/StringBuilder.toString:()Ljava/lang/String;
const #63 = Asciz	;
const #64 = String	#63;	//  
const #65 = Asciz	scala/runtime/BoxesRunTime;
const #66 = class	#65;	//  scala/runtime/BoxesRunTime
const #67 = Asciz	boxToInteger;
const #68 = Asciz	(I)Ljava/lang/Integer;;
const #69 = NameAndType	#67:#68;//  boxToInteger:(I)Ljava/lang/Integer;
const #70 = Method	#66.#69;	//  scala/runtime/BoxesRunTime.boxToInteger:(I)Ljava/lang/Integer;
const #71 = Asciz	.;
const #72 = String	#71;	//  .
const #73 = Asciz	Scala;
const #74 = Asciz	scala/util/parsing/input/Position$class;
const #75 = class	#74;	//  scala/util/parsing/input/Position$class
const #76 = Asciz	java/lang/Object;
const #77 = class	#76;	//  java/lang/Object

{
public static void $init$(scala.util.parsing.input.Position);
  Code:
   Stack=0, Locals=1, Args_size=1
   0:	return
  LineNumberTable: 
   line 28: 0

  LocalVariableTable: 
   Start  Length  Slot  Name   Signature
   0      1      0    $this       Lscala/util/parsing/input/Position;


public static boolean $less(scala.util.parsing.input.Position, scala.util.parsing.input.Position);
  Code:
   Stack=2, Locals=2, Args_size=2
   0:	aload_0
   1:	invokeinterface	#17,  1; //InterfaceMethod scala/util/parsing/input/Position.line:()I
   6:	aload_1
   7:	invokeinterface	#17,  1; //InterfaceMethod scala/util/parsing/input/Position.line:()I
   12:	if_icmplt	45
   15:	aload_0
   16:	invokeinterface	#17,  1; //InterfaceMethod scala/util/parsing/input/Position.line:()I
   21:	aload_1
   22:	invokeinterface	#17,  1; //InterfaceMethod scala/util/parsing/input/Position.line:()I
   27:	if_icmpne	49
   30:	aload_0
   31:	invokeinterface	#20,  1; //InterfaceMethod scala/util/parsing/input/Position.column:()I
   36:	aload_1
   37:	invokeinterface	#20,  1; //InterfaceMethod scala/util/parsing/input/Position.column:()I
   42:	if_icmpge	49
   45:	iconst_1
   46:	goto	50
   49:	iconst_0
   50:	ireturn
  LineNumberTable: 
   line 66: 0
   line 67: 15
   line 66: 45

  LocalVariableTable: 
   Start  Length  Slot  Name   Signature
   0      51      0    $this       Lscala/util/parsing/input/Position;
   0      51      1    that       Lscala/util/parsing/input/Position;


public static java.lang.String longString(scala.util.parsing.input.Position);
  Code:
   Stack=4, Locals=1, Args_size=1
   0:	new	#25; //class scala/collection/mutable/StringBuilder
   3:	dup
   4:	invokespecial	#29; //Method scala/collection/mutable/StringBuilder."<init>":()V
   7:	aload_0
   8:	invokeinterface	#33,  1; //InterfaceMethod scala/util/parsing/input/Position.lineContents:()Ljava/lang/String;
   13:	invokevirtual	#37; //Method scala/collection/mutable/StringBuilder.append:(Ljava/lang/Object;)Lscala/collection/mutable/StringBuilder;
   16:	ldc	#39; //String \n
   18:	invokevirtual	#37; //Method scala/collection/mutable/StringBuilder.append:(Ljava/lang/Object;)Lscala/collection/mutable/StringBuilder;
   21:	getstatic	#45; //Field scala/Predef$.MODULE$:Lscala/Predef$;
   24:	ldc	#47; //String  
   26:	invokevirtual	#51; //Method scala/Predef$.stringWrapper:(Ljava/lang/String;)Lscala/runtime/RichString;
   29:	aload_0
   30:	invokeinterface	#20,  1; //InterfaceMethod scala/util/parsing/input/Position.column:()I
   35:	iconst_1
   36:	isub
   37:	invokevirtual	#57; //Method scala/runtime/RichString.$times:(I)Ljava/lang/String;
   40:	invokevirtual	#37; //Method scala/collection/mutable/StringBuilder.append:(Ljava/lang/Object;)Lscala/collection/mutable/StringBuilder;
   43:	ldc	#59; //String ^
   45:	invokevirtual	#37; //Method scala/collection/mutable/StringBuilder.append:(Ljava/lang/Object;)Lscala/collection/mutable/StringBuilder;
   48:	invokevirtual	#62; //Method scala/collection/mutable/StringBuilder.toString:()Ljava/lang/String;
   51:	areturn
  LineNumberTable: 
   line 56: 0

  LocalVariableTable: 
   Start  Length  Slot  Name   Signature
   0      52      0    $this       Lscala/util/parsing/input/Position;


public static java.lang.String toString(scala.util.parsing.input.Position);
  Code:
   Stack=2, Locals=1, Args_size=1
   0:	new	#25; //class scala/collection/mutable/StringBuilder
   3:	dup
   4:	invokespecial	#29; //Method scala/collection/mutable/StringBuilder."<init>":()V
   7:	ldc	#64; //String 
   9:	invokevirtual	#37; //Method scala/collection/mutable/StringBuilder.append:(Ljava/lang/Object;)Lscala/collection/mutable/StringBuilder;
   12:	aload_0
   13:	invokeinterface	#17,  1; //InterfaceMethod scala/util/parsing/input/Position.line:()I
   18:	invokestatic	#70; //Method scala/runtime/BoxesRunTime.boxToInteger:(I)Ljava/lang/Integer;
   21:	invokevirtual	#37; //Method scala/collection/mutable/StringBuilder.append:(Ljava/lang/Object;)Lscala/collection/mutable/StringBuilder;
   24:	ldc	#72; //String .
   26:	invokevirtual	#37; //Method scala/collection/mutable/StringBuilder.append:(Ljava/lang/Object;)Lscala/collection/mutable/StringBuilder;
   29:	aload_0
   30:	invokeinterface	#20,  1; //InterfaceMethod scala/util/parsing/input/Position.column:()I
   35:	invokestatic	#70; //Method scala/runtime/BoxesRunTime.boxToInteger:(I)Ljava/lang/Integer;
   38:	invokevirtual	#37; //Method scala/collection/mutable/StringBuilder.append:(Ljava/lang/Object;)Lscala/collection/mutable/StringBuilder;
   41:	invokevirtual	#62; //Method scala/collection/mutable/StringBuilder.toString:()Ljava/lang/String;
   44:	areturn
  LineNumberTable: 
   line 44: 0

  LocalVariableTable: 
   Start  Length  Slot  Name   Signature
   0      45      0    $this       Lscala/util/parsing/input/Position;


}

