Compiled from "Position.scala"
public abstract class scala.util.parsing.input.Position$class extends java.lang.Object
  SourceFile: "Position.scala"
  Scala: length = 0x
   
  InnerClass: 
   public final $anon$4=class scala/Predef$$anon$4 of class scala/Predef
   public final $anonfun$longString$1=class scala/util/parsing/input/Position$$anonfun$longString$1 of class scala/util/parsing/input/Position
  minor version: 0
  major version: 49
  Constant pool:
Asciz	SourceFile;
Asciz	Position.scala;
Asciz	toString;
Asciz	(Lscala/util/parsing/input/Position;)Ljava/lang/String;;
Asciz	Code;
Asciz	scala/collection/mutable/StringBuilder;
class	scala/collection/mutable/StringBuilder
Asciz	<init>;
Asciz	()V;
NameAndType	"<init>":()V
Method	scala/collection/mutable/StringBuilder."<init>":()V
Asciz	LineNumberTable;
Asciz	;
String	
Asciz	append;
Asciz	(Ljava/lang/Object;)Lscala/collection/mutable/StringBuilder;;
NameAndType	append:(Ljava/lang/Object;)Lscala/collection/mutable/StringBuilder;
Method	scala/collection/mutable/StringBuilder.append:(Ljava/lang/Object;)Lscala/collection/mutable/StringBuilder;
Asciz	scala/util/parsing/input/Position;
class	scala/util/parsing/input/Position
Asciz	line;
Asciz	()I;
NameAndType	line:()I
InterfaceMethod	scala/util/parsing/input/Position.line:()I
Asciz	scala/runtime/BoxesRunTime;
class	scala/runtime/BoxesRunTime
Asciz	boxToInteger;
Asciz	(I)Ljava/lang/Integer;;
NameAndType	boxToInteger:(I)Ljava/lang/Integer;
Method	scala/runtime/BoxesRunTime.boxToInteger:(I)Ljava/lang/Integer;
Asciz	.;
String	.
Asciz	column;
NameAndType	column:()I
InterfaceMethod	scala/util/parsing/input/Position.column:()I
Asciz	()Ljava/lang/String;;
NameAndType	toString:()Ljava/lang/String;
Method	scala/collection/mutable/StringBuilder.toString:()Ljava/lang/String;
Asciz	$this;
Asciz	Lscala/util/parsing/input/Position;;
Asciz	LocalVariableTable;
Asciz	longString;
Asciz	lineContents;
NameAndType	lineContents:()Ljava/lang/String;
InterfaceMethod	scala/util/parsing/input/Position.lineContents:()Ljava/lang/String;
Asciz	\n;
String	\n
Asciz	scala/collection/immutable/StringOps;
class	scala/collection/immutable/StringOps
Asciz	(Ljava/lang/String;)V;
NameAndType	"<init>":(Ljava/lang/String;)V
Method	scala/collection/immutable/StringOps."<init>":(Ljava/lang/String;)V
Asciz	scala/collection/IndexedSeqOptimized$class;
class	scala/collection/IndexedSeqOptimized$class
Asciz	take;
Asciz	(Lscala/collection/IndexedSeqOptimized;I)Ljava/lang/Object;;
NameAndType	take:(Lscala/collection/IndexedSeqOptimized;I)Ljava/lang/Object;
Method	scala/collection/IndexedSeqOptimized$class.take:(Lscala/collection/IndexedSeqOptimized;I)Ljava/lang/Object;
Asciz	java/lang/String;
class	java/lang/String
Asciz	scala/util/parsing/input/Position$$anonfun$longString$1;
class	scala/util/parsing/input/Position$$anonfun$longString$1
Asciz	(Lscala/util/parsing/input/Position;)V;
NameAndType	"<init>":(Lscala/util/parsing/input/Position;)V
Method	scala/util/parsing/input/Position$$anonfun$longString$1."<init>":(Lscala/util/parsing/input/Position;)V
Asciz	scala/Predef$$anon$4;
class	scala/Predef$$anon$4
Method	scala/Predef$$anon$4."<init>":()V
Asciz	scala/collection/TraversableLike$class;
class	scala/collection/TraversableLike$class
Asciz	map;
Asciz	(Lscala/collection/TraversableLike;Lscala/Function1;Lscala/collection/generic/CanBuildFrom;)Ljava/lang/Object;;
NameAndType	map:(Lscala/collection/TraversableLike;Lscala/Function1;Lscala/collection/generic/CanBuildFrom;)Ljava/lang/Object;
Method	scala/collection/TraversableLike$class.map:(Lscala/collection/TraversableLike;Lscala/Function1;Lscala/collection/generic/CanBuildFrom;)Ljava/lang/Object;
Asciz	^;
String	^
Asciz	$less;
Asciz	(Lscala/util/parsing/input/Position;Lscala/util/parsing/input/Position;)Z;
Asciz	that;
Asciz	$init$;
Asciz	Scala;
Asciz	InnerClasses;
Asciz	scala/Predef;
class	scala/Predef
Asciz	$anon$4;
Asciz	$anonfun$longString$1;
Asciz	scala/util/parsing/input/Position$class;
class	scala/util/parsing/input/Position$class
Asciz	java/lang/Object;
class	java/lang/Object

{
public static java.lang.String toString(scala.util.parsing.input.Position);
  Signature: (Lscala/util/parsing/input/Position;)Ljava/lang/String;
  Code:
   Stack=2, Locals=3, Args_size=1
	new	class scala/collection/mutable/StringBuilder
	dup
	invokespecial	Method scala/collection/mutable/StringBuilder."<init>":()V
	ldc	String 
	invokevirtual	Method scala/collection/mutable/StringBuilder.append:(Ljava/lang/Object;)Lscala/collection/mutable/StringBuilder;
	aload_0
	invokeinterface	InterfaceMethod scala/util/parsing/input/Position.line:()I
	istore_1
	iload_1
	invokestatic	Method scala/runtime/BoxesRunTime.boxToInteger:(I)Ljava/lang/Integer;
	invokevirtual	Method scala/collection/mutable/StringBuilder.append:(Ljava/lang/Object;)Lscala/collection/mutable/StringBuilder;
	ldc	String .
	invokevirtual	Method scala/collection/mutable/StringBuilder.append:(Ljava/lang/Object;)Lscala/collection/mutable/StringBuilder;
	aload_0
	invokeinterface	InterfaceMethod scala/util/parsing/input/Position.column:()I
	istore_2
	iload_2
	invokestatic	Method scala/runtime/BoxesRunTime.boxToInteger:(I)Ljava/lang/Integer;
	invokevirtual	Method scala/collection/mutable/StringBuilder.append:(Ljava/lang/Object;)Lscala/collection/mutable/StringBuilder;
	invokevirtual	Method scala/collection/mutable/StringBuilder.toString:()Ljava/lang/String;
	areturn
  Labels:
  LocalVariableTable: 
   Start  Length  Slot  Name   Signature
   0      49      0    $this       Lscala/util/parsing/input/Position;


public static java.lang.String longString(scala.util.parsing.input.Position);
  Signature: (Lscala/util/parsing/input/Position;)Ljava/lang/String;
  Code:
   Stack=5, Locals=8, Args_size=1
	new	class scala/collection/mutable/StringBuilder
	dup
	invokespecial	Method scala/collection/mutable/StringBuilder."<init>":()V
	aload_0
	invokeinterface	InterfaceMethod scala/util/parsing/input/Position.lineContents:()Ljava/lang/String;
	invokevirtual	Method scala/collection/mutable/StringBuilder.append:(Ljava/lang/Object;)Lscala/collection/mutable/StringBuilder;
	ldc	String \n
	invokevirtual	Method scala/collection/mutable/StringBuilder.append:(Ljava/lang/Object;)Lscala/collection/mutable/StringBuilder;
	aload_0
	invokeinterface	InterfaceMethod scala/util/parsing/input/Position.lineContents:()Ljava/lang/String;
	astore_1
	new	class scala/collection/immutable/StringOps
	dup
	aload_1
	invokespecial	Method scala/collection/immutable/StringOps."<init>":(Ljava/lang/String;)V
	aload_0
	invokeinterface	InterfaceMethod scala/util/parsing/input/Position.column:()I
	iconst_1
	isub
	istore_3
	astore_2
	aload_2
	iload_3
	invokestatic	Method scala/collection/IndexedSeqOptimized$class.take:(Lscala/collection/IndexedSeqOptimized;I)Ljava/lang/Object;
	checkcast	class java/lang/String
	astore	4
	new	class scala/collection/immutable/StringOps
	dup
	aload	4
	invokespecial	Method scala/collection/immutable/StringOps."<init>":(Ljava/lang/String;)V
	new	class scala/util/parsing/input/Position$$anonfun$longString$1
	dup
	aload_0
	invokespecial	Method scala/util/parsing/input/Position$$anonfun$longString$1."<init>":(Lscala/util/parsing/input/Position;)V
	new	class scala/Predef$$anon$4
	dup
	invokespecial	Method scala/Predef$$anon$4."<init>":()V
	astore	7
	astore	6
	astore	5
	aload	5
	aload	6
	aload	7
	invokestatic	Method scala/collection/TraversableLike$class.map:(Lscala/collection/TraversableLike;Lscala/Function1;Lscala/collection/generic/CanBuildFrom;)Ljava/lang/Object;
	invokevirtual	Method scala/collection/mutable/StringBuilder.append:(Ljava/lang/Object;)Lscala/collection/mutable/StringBuilder;
	ldc	String ^
	invokevirtual	Method scala/collection/mutable/StringBuilder.append:(Ljava/lang/Object;)Lscala/collection/mutable/StringBuilder;
	invokevirtual	Method scala/collection/mutable/StringBuilder.toString:()Ljava/lang/String;
	areturn
  Labels:
  LocalVariableTable: 
   Start  Length  Slot  Name   Signature
   0      107      0    $this       Lscala/util/parsing/input/Position;


public static boolean $less(scala.util.parsing.input.Position, scala.util.parsing.input.Position);
  Signature: (Lscala/util/parsing/input/Position;Lscala/util/parsing/input/Position;)Z
  Code:
   Stack=2, Locals=2, Args_size=2
	aload_0
	invokeinterface	InterfaceMethod scala/util/parsing/input/Position.line:()I
	aload_1
	invokeinterface	InterfaceMethod scala/util/parsing/input/Position.line:()I
	if_icmplt	l1 // iconst_1
	aload_0
	invokeinterface	InterfaceMethod scala/util/parsing/input/Position.line:()I
	aload_1
	invokeinterface	InterfaceMethod scala/util/parsing/input/Position.line:()I
	if_icmpne	l2 // iconst_0
	aload_0
	invokeinterface	InterfaceMethod scala/util/parsing/input/Position.column:()I
	aload_1
	invokeinterface	InterfaceMethod scala/util/parsing/input/Position.column:()I
	if_icmpge	l2 // iconst_0
l1	iconst_1
	goto	l3 // ireturn
l2	iconst_0
l3	ireturn
  Labels:
   	l1 = 45 // iconst_1
   	l2 = 49 // iconst_0
   	l3 = 50 // ireturn
  LocalVariableTable: 
   Start  Length  Slot  Name   Signature
   0      51      0    $this       Lscala/util/parsing/input/Position;
   0      51      1    that       Lscala/util/parsing/input/Position;


public static void $init$(scala.util.parsing.input.Position);
  Signature: (Lscala/util/parsing/input/Position;)V
  Code:
   Stack=0, Locals=1, Args_size=1
	return
  Labels:
  LocalVariableTable: 
   Start  Length  Slot  Name   Signature
   0      1      0    $this       Lscala/util/parsing/input/Position;


}

