Compiled from "StreamReader.scala"
public final class scala.util.parsing.input.StreamReader$ extends java.lang.Object implements scala.ScalaObject
  SourceFile: "StreamReader.scala"
  Scala: length = 0x
   
  InnerClass: 
   public final #47= #46 of #25; //$anon$1=class scala/util/parsing/input/StreamReader$$anon$1 of class scala/util/parsing/input/StreamReader
  minor version: 0
  major version: 49
  Constant pool:
const #1 = Asciz	SourceFile;
const #2 = Asciz	StreamReader.scala;
const #3 = Asciz	Scala;
const #4 = Asciz	MODULE$;
const #5 = Asciz	Lscala/util/parsing/input/StreamReader$;;
const #6 = Asciz	<clinit>;
const #7 = Asciz	()V;
const #8 = Asciz	Code;
const #9 = Asciz	scala/util/parsing/input/StreamReader$;
const #10 = class	#9;	//  scala/util/parsing/input/StreamReader$
const #11 = Asciz	<init>;
const #12 = NameAndType	#11:#7;//  "<init>":()V
const #13 = Method	#10.#12;	//  scala/util/parsing/input/StreamReader$."<init>":()V
const #14 = Asciz	EofCh;
const #15 = Asciz	C;
const #16 = Asciz	LineNumberTable;
const #17 = Asciz	java/lang/Object;
const #18 = class	#17;	//  java/lang/Object
const #19 = Method	#18.#12;	//  java/lang/Object."<init>":()V
const #20 = NameAndType	#4:#5;//  MODULE$:Lscala/util/parsing/input/StreamReader$;
const #21 = Field	#10.#20;	//  scala/util/parsing/input/StreamReader$.MODULE$:Lscala/util/parsing/input/StreamReader$;
const #22 = Asciz	apply;
const #23 = Asciz	(Ljava/io/Reader;)Lscala/util/parsing/input/StreamReader;;
const #24 = Asciz	scala/util/parsing/input/StreamReader;
const #25 = class	#24;	//  scala/util/parsing/input/StreamReader
const #26 = Asciz	scala/collection/immutable/PagedSeq$;
const #27 = class	#26;	//  scala/collection/immutable/PagedSeq$
const #28 = Asciz	Lscala/collection/immutable/PagedSeq$;;
const #29 = NameAndType	#4:#28;//  MODULE$:Lscala/collection/immutable/PagedSeq$;
const #30 = Field	#27.#29;	//  scala/collection/immutable/PagedSeq$.MODULE$:Lscala/collection/immutable/PagedSeq$;
const #31 = Asciz	fromReader;
const #32 = Asciz	(Ljava/io/Reader;)Lscala/collection/immutable/PagedSeq;;
const #33 = NameAndType	#31:#32;//  fromReader:(Ljava/io/Reader;)Lscala/collection/immutable/PagedSeq;
const #34 = Method	#27.#33;	//  scala/collection/immutable/PagedSeq$.fromReader:(Ljava/io/Reader;)Lscala/collection/immutable/PagedSeq;
const #35 = Asciz	(Lscala/collection/immutable/PagedSeq;II)V;
const #36 = NameAndType	#11:#35;//  "<init>":(Lscala/collection/immutable/PagedSeq;II)V
const #37 = Method	#25.#36;	//  scala/util/parsing/input/StreamReader."<init>":(Lscala/collection/immutable/PagedSeq;II)V
const #38 = Asciz	this;
const #39 = Asciz	in;
const #40 = Asciz	Ljava/io/Reader;;
const #41 = Asciz	LocalVariableTable;
const #42 = Asciz	()C;
const #43 = int	26;
const #44 = Asciz	InnerClasses;
const #45 = Asciz	scala/util/parsing/input/StreamReader$$anon$1;
const #46 = class	#45;	//  scala/util/parsing/input/StreamReader$$anon$1
const #47 = Asciz	$anon$1;
const #48 = Asciz	scala/ScalaObject;
const #49 = class	#48;	//  scala/ScalaObject

{
public static final scala.util.parsing.input.StreamReader$ MODULE$;

public static {};
  Code:
   Stack=1, Locals=0, Args_size=0
   0:	new	#10; //class scala/util/parsing/input/StreamReader$
   3:	invokespecial	#13; //Method "<init>":()V
   6:	return

public scala.util.parsing.input.StreamReader apply(java.io.Reader);
  Code:
   Stack=5, Locals=2, Args_size=2
   0:	new	#25; //class scala/util/parsing/input/StreamReader
   3:	dup
   4:	getstatic	#30; //Field scala/collection/immutable/PagedSeq$.MODULE$:Lscala/collection/immutable/PagedSeq$;
   7:	aload_1
   8:	invokevirtual	#34; //Method scala/collection/immutable/PagedSeq$.fromReader:(Ljava/io/Reader;)Lscala/collection/immutable/PagedSeq;
   11:	iconst_0
   12:	iconst_1
   13:	invokespecial	#37; //Method scala/util/parsing/input/StreamReader."<init>":(Lscala/collection/immutable/PagedSeq;II)V
   16:	areturn
  LineNumberTable: 
   line 27: 0

  LocalVariableTable: 
   Start  Length  Slot  Name   Signature
   0      17      0    this       Lscala/util/parsing/input/StreamReader$;
   0      17      1    in       Ljava/io/Reader;


public final char EofCh();
  Code:
   Stack=1, Locals=1, Args_size=1
   0:	ldc	#43; //int 26
   2:	ireturn
  LineNumberTable: 
   line 24: 0


}

