Compiled from "StreamReader.scala"
public final class scala.util.parsing.input.StreamReader$$anon$1 extends java.lang.Object implements scala.util.parsing.input.Position
  SourceFile: "StreamReader.scala"
  Scala: length = 0x
   
  InnerClass: 
   public final $anon$1=class scala/util/parsing/input/StreamReader$$anon$1 of class scala/util/parsing/input/StreamReader
  minor version: 0
  major version: 49
  Constant pool:
Asciz	SourceFile;
Asciz	StreamReader.scala;
Asciz	$outer;
Asciz	Lscala/util/parsing/input/StreamReader;;
Asciz	toString;
Asciz	()Ljava/lang/String;;
Asciz	Code;
Asciz	LineNumberTable;
Asciz	scala/util/parsing/input/Position$class;
class	scala/util/parsing/input/Position$class
Asciz	(Lscala/util/parsing/input/Position;)Ljava/lang/String;;
NameAndType	toString:(Lscala/util/parsing/input/Position;)Ljava/lang/String;
Method	scala/util/parsing/input/Position$class.toString:(Lscala/util/parsing/input/Position;)Ljava/lang/String;
Asciz	longString;
NameAndType	longString:(Lscala/util/parsing/input/Position;)Ljava/lang/String;
Method	scala/util/parsing/input/Position$class.longString:(Lscala/util/parsing/input/Position;)Ljava/lang/String;
Asciz	$less;
Asciz	(Lscala/util/parsing/input/Position;)Z;
Asciz	(Lscala/util/parsing/input/Position;Lscala/util/parsing/input/Position;)Z;
NameAndType	$less:(Lscala/util/parsing/input/Position;Lscala/util/parsing/input/Position;)Z
Method	scala/util/parsing/input/Position$class.$less:(Lscala/util/parsing/input/Position;Lscala/util/parsing/input/Position;)Z
Asciz	this;
Asciz	Lscala/util/parsing/input/StreamReader$$anon$1;;
Asciz	that;
Asciz	Lscala/util/parsing/input/Position;;
Asciz	LocalVariableTable;
Asciz	line;
Asciz	()I;
Asciz	scala/util/parsing/input/StreamReader$$anon$1;
class	scala/util/parsing/input/StreamReader$$anon$1
NameAndType	$outer:Lscala/util/parsing/input/StreamReader;
Field	scala/util/parsing/input/StreamReader$$anon$1.$outer:Lscala/util/parsing/input/StreamReader;
Asciz	scala/util/parsing/input/StreamReader;
class	scala/util/parsing/input/StreamReader
Asciz	scala$util$parsing$input$StreamReader$$lnum;
Asciz	I;
NameAndType	scala$util$parsing$input$StreamReader$$lnum:I
Field	scala/util/parsing/input/StreamReader.scala$util$parsing$input$StreamReader$$lnum:I
Asciz	column;
Asciz	scala$util$parsing$input$StreamReader$$super$offset;
NameAndType	scala$util$parsing$input$StreamReader$$super$offset:()I
Method	scala/util/parsing/input/StreamReader.scala$util$parsing$input$StreamReader$$super$offset:()I
Asciz	lineContents;
Asciz	scala$util$parsing$input$StreamReader$$seq;
Asciz	Lscala/collection/immutable/PagedSeq;;
NameAndType	scala$util$parsing$input$StreamReader$$seq:Lscala/collection/immutable/PagedSeq;
Field	scala/util/parsing/input/StreamReader.scala$util$parsing$input$StreamReader$$seq:Lscala/collection/immutable/PagedSeq;
Asciz	scala$util$parsing$input$StreamReader$$nextEol;
NameAndType	scala$util$parsing$input$StreamReader$$nextEol:()I
Method	scala/util/parsing/input/StreamReader.scala$util$parsing$input$StreamReader$$nextEol:()I
Asciz	scala/collection/immutable/PagedSeq;
class	scala/collection/immutable/PagedSeq
Asciz	slice;
Asciz	(II)Lscala/collection/immutable/PagedSeq;;
NameAndType	slice:(II)Lscala/collection/immutable/PagedSeq;
Method	scala/collection/immutable/PagedSeq.slice:(II)Lscala/collection/immutable/PagedSeq;
NameAndType	toString:()Ljava/lang/String;
Method	scala/collection/immutable/PagedSeq.toString:()Ljava/lang/String;
Asciz	<init>;
Asciz	(Lscala/util/parsing/input/StreamReader;)V;
Asciz	java/lang/NullPointerException;
class	java/lang/NullPointerException
Asciz	()V;
NameAndType	"<init>":()V
Method	java/lang/NullPointerException."<init>":()V
Asciz	java/lang/Object;
class	java/lang/Object
Method	java/lang/Object."<init>":()V
Asciz	$init$;
Asciz	(Lscala/util/parsing/input/Position;)V;
NameAndType	$init$:(Lscala/util/parsing/input/Position;)V
Method	scala/util/parsing/input/Position$class.$init$:(Lscala/util/parsing/input/Position;)V
Asciz	Scala;
Asciz	InnerClasses;
Asciz	$anon$1;
Asciz	scala/util/parsing/input/Position;
class	scala/util/parsing/input/Position

{
private final scala.util.parsing.input.StreamReader $outer;
  Signature: Lscala/util/parsing/input/StreamReader;

public java.lang.String toString();
  Signature: ()Ljava/lang/String;
  Code:
   Stack=1, Locals=1, Args_size=1
	aload_0
	invokestatic	Method scala/util/parsing/input/Position$class.toString:(Lscala/util/parsing/input/Position;)Ljava/lang/String;
	areturn
  Labels:

public java.lang.String longString();
  Signature: ()Ljava/lang/String;
  Code:
   Stack=1, Locals=1, Args_size=1
	aload_0
	invokestatic	Method scala/util/parsing/input/Position$class.longString:(Lscala/util/parsing/input/Position;)Ljava/lang/String;
	areturn
  Labels:

public boolean $less(scala.util.parsing.input.Position);
  Signature: (Lscala/util/parsing/input/Position;)Z
  Code:
   Stack=2, Locals=2, Args_size=2
	aload_0
	aload_1
	invokestatic	Method scala/util/parsing/input/Position$class.$less:(Lscala/util/parsing/input/Position;Lscala/util/parsing/input/Position;)Z
	ireturn
  Labels:
  LocalVariableTable: 
   Start  Length  Slot  Name   Signature
   0      6      0    this       Lscala/util/parsing/input/StreamReader$$anon$1;
   0      6      1    that       Lscala/util/parsing/input/Position;


public int line();
  Signature: ()I
  Code:
   Stack=1, Locals=1, Args_size=1
	aload_0
	getfield	Field $outer:Lscala/util/parsing/input/StreamReader;
	getfield	Field scala/util/parsing/input/StreamReader.scala$util$parsing$input$StreamReader$$lnum:I
	ireturn
  Labels:

public int column();
  Signature: ()I
  Code:
   Stack=2, Locals=1, Args_size=1
	aload_0
	getfield	Field $outer:Lscala/util/parsing/input/StreamReader;
	invokevirtual	Method scala/util/parsing/input/StreamReader.scala$util$parsing$input$StreamReader$$super$offset:()I
	iconst_1
	iadd
	ireturn
  Labels:

public java.lang.String lineContents();
  Signature: ()Ljava/lang/String;
  Code:
   Stack=3, Locals=1, Args_size=1
	aload_0
	getfield	Field $outer:Lscala/util/parsing/input/StreamReader;
	getfield	Field scala/util/parsing/input/StreamReader.scala$util$parsing$input$StreamReader$$seq:Lscala/collection/immutable/PagedSeq;
	iconst_0
	aload_0
	getfield	Field $outer:Lscala/util/parsing/input/StreamReader;
	invokevirtual	Method scala/util/parsing/input/StreamReader.scala$util$parsing$input$StreamReader$$nextEol:()I
	invokevirtual	Method scala/collection/immutable/PagedSeq.slice:(II)Lscala/collection/immutable/PagedSeq;
	invokevirtual	Method scala/collection/immutable/PagedSeq.toString:()Ljava/lang/String;
	areturn
  Labels:

public scala.util.parsing.input.StreamReader$$anon$1(scala.util.parsing.input.StreamReader);
  Signature: (Lscala/util/parsing/input/StreamReader;)V
  Code:
   Stack=2, Locals=2, Args_size=2
	aload_1
	ifnonnull	l1 // aload_0
	new	class java/lang/NullPointerException
	dup
	invokespecial	Method java/lang/NullPointerException."<init>":()V
	athrow
l1	aload_0
	aload_1
	putfield	Field $outer:Lscala/util/parsing/input/StreamReader;
	aload_0
	invokespecial	Method java/lang/Object."<init>":()V
	aload_0
	invokestatic	Method scala/util/parsing/input/Position$class.$init$:(Lscala/util/parsing/input/Position;)V
	return
  Labels:
   	l1 = 12 // aload_0
  LocalVariableTable: 
   Start  Length  Slot  Name   Signature
   0      26      0    this       Lscala/util/parsing/input/StreamReader$$anon$1;
   0      26      1    $outer       Lscala/util/parsing/input/StreamReader;


}

