Compiled from "List.scala"
public final class scala.$colon$colon extends scala.List implements java.io.Serializable,scala.Product
  ScalaSig: length = 0x3DD
   04 01 FFFFFF81 13 06 04 01 02 42 05 02 0C 24 63 6F 6C
   6F 6E 24 63 6F 6C 6F 6E 0A 01 03 01 05 73 63 61
   6C 61 03 00 15 02 06 0D 13 04 00 07 16 19 10 03
   08 09 0B 0D 01 02 09 02 0A 02 02 04 4C 69 73 74
   10 02 0C 0D 0C 00 04 08 0E 00 FFFFFF84 FFFFFF80 FFFFFF80 FFFFFFC2 00 0F
   02 01 42 11 02 10 13 10 02 08 11 09 02 12 02 02
   07 4E 6F 74 68 69 6E 67 10 02 08 14 09 02 15 02
   02 03 41 6E 79 10 02 08 17 09 02 18 02 02 0B 53
   63 61 6C 61 4F 62 6A 65 63 74 10 02 08 1A 09 02
   1B 02 02 07 50 72 6F 64 75 63 74 08 08 1D 00 FFFFFF82
   FFFFFFC0 FFFFFF80 FFFFFF84 04 1E 01 02 68 64 15 01 0B 08 08 20 00
   FFFFFF82 FFFFFFC0 FFFFFF80 FFFFFF84 04 21 01 06 68 64 5F 24 65 71 14 02
   22 0B 10 02 08 23 09 02 24 02 02 04 55 6E 69 74
   08 08 26 00 FFFFFF82 FFFFFF88 FFFFFFA0 FFFFFFA0 04 0B 01 03 68 64 20 08
   09 28 00 FFFFFF82 FFFFFFC0 FFFFFF80 FFFFFF84 00 02 29 01 02 74 6C 15 01
   07 08 09 2B 00 FFFFFF82 FFFFFFC0 FFFFFF80 FFFFFF84 00 02 2C 01 06 74 6C
   5F 24 65 71 14 02 22 07 08 08 2E 00 FFFFFF82 FFFFFF88 FFFFFFA0 FFFFFFA0
   04 07 01 03 74 6C 20 08 05 30 00 FFFFFF84 00 31 01 06
   3C 69 6E 69 74 3E 14 03 32 0B 07 10 03 08 00 0B
   08 05 34 00 FFFFFF84 00 1E 01 04 68 65 61 64 08 05 36
   00 FFFFFF84 00 29 01 04 74 61 69 6C 08 05 38 00 FFFFFF84 20
   39 01 07 69 73 45 6D 70 74 79 15 01 3A 10 02 08
   3B 09 02 3C 02 02 07 42 6F 6F 6C 65 61 6E 08 05
   3E 00 FFFFFF84 04 3F 01 0B 77 72 69 74 65 4F 62 6A 65
   63 74 14 02 22 40 10 02 41 46 0D 01 42 0A 02 43
   44 01 02 69 6F 0A 01 45 01 04 6A 61 76 61 09 02
   47 42 02 12 4F 62 6A 65 63 74 4F 75 74 70 75 74
   53 74 72 65 61 6D 08 05 49 00 FFFFFF84 04 4A 01 0A 72
   65 61 64 4F 62 6A 65 63 74 14 02 22 4B 10 02 41
   4C 09 02 4D 42 02 11 4F 62 6A 65 63 74 49 6E 70
   75 74 53 74 72 65 61 6D 08 07 4F 00 FFFFFF89 FFFFFF80 FFFFFF84 00
   1E 01 04 68 64 24 31 08 07 51 00 FFFFFF89 FFFFFF80 FFFFFF84 00 29
   01 04 74 6C 24 31 08 08 53 00 FFFFFF84 FFFFFF80 FFFFFF80 FFFFFF84 20 54
   01 04 24 74 61 67 14 01 55 10 02 08 56 09 02 57
   02 02 03 49 6E 74 08 08 59 00 FFFFFF84 FFFFFF80 FFFFFF80 FFFFFF84 20 54
   01 08 68 61 73 68 43 6F 64 65 08 08 5B 00 FFFFFF84 FFFFFF80
   FFFFFF80 FFFFFF84 20 5C 01 06 65 71 75 61 6C 73 14 02 3A 13
   08 08 5E 00 FFFFFF84 FFFFFF80 FFFFFF80 FFFFFF84 20 5F 01 0D 70 72 6F 64
   75 63 74 50 72 65 66 69 78 15 01 60 10 02 61 64
   0D 01 62 0A 02 63 44 01 04 6C 61 6E 67 09 02 65
   62 02 06 53 74 72 69 6E 67 08 08 67 00 FFFFFF84 FFFFFF80 FFFFFF80
   FFFFFF84 20 68 01 0C 70 72 6F 64 75 63 74 41 72 69 74
   79 15 01 55 08 08 6A 00 FFFFFF84 FFFFFF80 FFFFFF80 FFFFFF84 20 6B 01 0E
   70 72 6F 64 75 63 74 45 6C 65 6D 65 6E 74 14 02
   13 55 28 03 00 6D 70 10 02 08 6E 09 02 6F 02 02
   10 53 65 72 69 61 6C 56 65 72 73 69 6F 6E 55 49
   44 1E 08 FFFFFF8A 5C 63 5B FFFFFFF6 FFFFFFD8 FFFFFFF9 6D 1E 08 FFFFFF8A 5C 63
   5B FFFFFFF6 FFFFFFD8 FFFFFFF9 6D 28 02 00 73 10 02 08 74 09 02 75
   02 02 0C 73 65 72 69 61 6C 69 7A 61 62 6C 65 07
   07 77 02 FFFFFF81 FFFFFF80 FFFFFF88 02 78 01 0C 24 63 6F 6C 6F 6E
   24 63 6F 6C 6F 6E 10 02 08 79 06 08 01 02 FFFFFF84 FFFFFF81
   FFFFFF80 FFFFFF88 02 7A 13 03 79 7B 16 10 02 61 7C 09 02 7D
   62 02 06 4F 62 6A 65 63 74 08 05 30 79 FFFFFF84 00 7F
   14 01 78 08 09 FFFFFF81 01 79 FFFFFF81 FFFFFF80 FFFFFF84 40 FFFFFF81 02 01 05
   61 70 70 6C 79 15 04 FFFFFF81 03 FFFFFF81 06 14 06 FFFFFF81 04 FFFFFF81
   05 FFFFFF81 07 10 04 08 00 FFFFFF81 05 10 03 0C FFFFFF81 06 04 09
   0E FFFFFF81 00 FFFFFF84 FFFFFF80 FFFFFF80 FFFFFFC2 00 0F 10 04 08 09 FFFFFF81 05 08
   09 FFFFFF81 09 79 FFFFFF81 FFFFFF80 FFFFFF84 40 FFFFFF81 0A 01 07 75 6E 61 70
   70 6C 79 15 04 FFFFFF81 0B FFFFFF81 11 14 04 FFFFFF81 0C FFFFFF81 12 10
   05 08 FFFFFF81 0D FFFFFF81 0F 09 03 FFFFFF81 0E 02 02 04 53 6F 6D
   65 10 04 08 09 FFFFFF81 10 10 03 0C FFFFFF81 11 04 09 0E FFFFFF81
   08 FFFFFF84 FFFFFF80 FFFFFF80 FFFFFFC2 00 0F 10 04 08 00 FFFFFF81 10 
  Signature: length = 0x2
   00 40 
  SourceFile: "List.scala"
  minor version: 0
  major version: 49
  Constant pool:
String	::
class	java/io/Serializable
class	java/lang/IndexOutOfBoundsException
class	java/lang/Object
class	scala/$colon$colon
class	scala/List
class	scala/Product
class	scala/runtime/BoxesRunTime
class	scala/runtime/ScalaRunTime$
long	-8476791151983527571l;
Field	scala/$colon$colon.hd:Ljava/lang/Object;
Field	scala/$colon$colon.serialVersionUID:J
Field	scala/$colon$colon.tl:Lscala/List;
Field	scala/runtime/ScalaRunTime$.MODULE$:Lscala/runtime/ScalaRunTime$;
Method	java/lang/IndexOutOfBoundsException."<init>":(Ljava/lang/String;)V
Method	java/lang/Object.equals:(Ljava/lang/Object;)Z
Method	java/lang/Object.toString:()Ljava/lang/String;
Method	scala/$colon$colon.gd1$1:(Lscala/List;Ljava/lang/Object;)Z
Method	scala/$colon$colon.hd:()Ljava/lang/Object;
Method	scala/$colon$colon.hd$1:()Ljava/lang/Object;
Method	scala/$colon$colon.tl:()Lscala/List;
Method	scala/$colon$colon.tl$1:()Lscala/List;
Method	scala/List."<init>":()V
Method	scala/runtime/BoxesRunTime.boxToInteger:(I)Ljava/lang/Integer;
Method	scala/runtime/BoxesRunTime.equals:(Ljava/lang/Object;Ljava/lang/Object;)Z
Method	scala/runtime/ScalaRunTime$._hashCode:(Lscala/Product;)I
NameAndType	"<init>":()V
NameAndType	"<init>":(Ljava/lang/String;)V
NameAndType	MODULE$:Lscala/runtime/ScalaRunTime$;
NameAndType	_hashCode:(Lscala/Product;)I
NameAndType	boxToInteger:(I)Ljava/lang/Integer;
NameAndType	equals:(Ljava/lang/Object;)Z
NameAndType	equals:(Ljava/lang/Object;Ljava/lang/Object;)Z
NameAndType	gd1$1:(Lscala/List;Ljava/lang/Object;)Z
NameAndType	hd:()Ljava/lang/Object;
NameAndType	hd:Ljava/lang/Object;
NameAndType	hd$1:()Ljava/lang/Object;
NameAndType	serialVersionUID:J
NameAndType	tl:()Lscala/List;
NameAndType	tl:Lscala/List;
NameAndType	tl$1:()Lscala/List;
NameAndType	toString:()Ljava/lang/String;
Asciz	()I;
Asciz	()Ljava/lang/Object;;
Asciz	()Ljava/lang/String;;
Asciz	()Lscala/List;;
Asciz	()Lscala/List<TB;>;;
Asciz	()TB;;
Asciz	()V;
Asciz	()Z;
Asciz	(I)Ljava/lang/Integer;;
Asciz	(I)Ljava/lang/Object;;
Asciz	(Ljava/lang/Object;)Z;
Asciz	(Ljava/lang/Object;Ljava/lang/Object;)Z;
Asciz	(Ljava/lang/Object;Lscala/List;)V;
Asciz	(Ljava/lang/String;)V;
Asciz	(Lscala/List;)V;
Asciz	(Lscala/List;Ljava/lang/Object;)Z;
Asciz	(Lscala/List<TB;>;)V;
Asciz	(Lscala/Product;)I;
Asciz	(TB;Lscala/List<TB;>;)V;
Asciz	::;
Asciz	<B:Ljava/lang/Object;>Lscala/List<TB;>;Lscala/Product;;
Asciz	<clinit>;
Asciz	<init>;
Asciz	Code;
Asciz	I;
Asciz	J;
Asciz	LineNumberTable;
Asciz	List.scala;
Asciz	Ljava/lang/Object;;
Asciz	LocalVariableTable;
Asciz	Lscala/$colon$colon;;
Asciz	Lscala/List;;
Asciz	Lscala/List<TB;>;;
Asciz	Lscala/runtime/ScalaRunTime$;;
Asciz	MODULE$;
Asciz	ScalaSig;
Asciz	Signature;
Asciz	SourceFile;
Asciz	TB;;
Asciz	_hashCode;
Asciz	boxToInteger;
Asciz	equals;
Asciz	gd1$1;
Asciz	hashCode;
Asciz	hd;
Asciz	hd$1;
Asciz	head;
Asciz	isEmpty;
Asciz	java/io/Serializable;
Asciz	java/lang/IndexOutOfBoundsException;
Asciz	java/lang/Object;
Asciz	productArity;
Asciz	productElement;
Asciz	productPrefix;
Asciz	scala/$colon$colon;
Asciz	scala/List;
Asciz	scala/Product;
Asciz	scala/runtime/BoxesRunTime;
Asciz	scala/runtime/ScalaRunTime$;
Asciz	serialVersionUID;
Asciz	tail;
Asciz	this;
Asciz	tl;
Asciz	tl$1;
Asciz	tl_$eq;
Asciz	toString;
Asciz	x$1;
Asciz	x$2;

{
public static final long serialVersionUID;
  Signature: J

private scala.List tl;
  Signature: Lscala/List;
  Signature: length = 0x2
   00 4C 

private java.lang.Object hd;
  Signature: Ljava/lang/Object;
  Signature: length = 0x2
   00 52 

public static {};
  Signature: ()V
  Code:
   Stack=2, Locals=0, Args_size=0
	ldc2_w	long -8476791151983527571l
	putstatic	Field serialVersionUID:J
	return
  Labels:

public scala.$colon$colon(java.lang.Object, scala.List);
  Signature: (Ljava/lang/Object;Lscala/List;)V
  Code:
   Stack=2, Locals=3, Args_size=3
	aload_0
	aload_1
	putfield	Field hd:Ljava/lang/Object;
	aload_0
	aload_2
	putfield	Field tl:Lscala/List;
	aload_0
	invokespecial	Method scala/List."<init>":()V
	return
  Labels:
  LocalVariableTable: 
   Start  Length  Slot  Name   Signature
   0      15      0    this       Lscala/$colon$colon;
   0      15      1    hd       Ljava/lang/Object;
   0      15      2    tl       Lscala/List;

  Signature: length = 0x2
   00 3E 

private final boolean gd1$1(scala.List, java.lang.Object);
  Signature: (Lscala/List;Ljava/lang/Object;)Z
  Code:
   Stack=2, Locals=4, Args_size=3
	aload_2
	aload_0
	invokevirtual	Method hd$1:()Ljava/lang/Object;
	invokestatic	Method scala/runtime/BoxesRunTime.equals:(Ljava/lang/Object;Ljava/lang/Object;)Z
	ifeq	l1 // iconst_0
	aload_1
	aload_0
	invokevirtual	Method tl$1:()Lscala/List;
	astore_3
	dup
	ifnonnull	l2 // aload_3
	pop
	aload_3
	ifnull	l3 // iconst_1
	goto	l1 // iconst_0
l2	aload_3
	invokevirtual	Method java/lang/Object.equals:(Ljava/lang/Object;)Z
	ifeq	l1 // iconst_0
l3	iconst_1
	goto	l4 // ireturn
l1	iconst_0
l4	ireturn
  Labels:
   	l2 = 29 // aload_3
   	l3 = 36 // iconst_1
   	l1 = 40 // iconst_0
   	l4 = 41 // ireturn
  LocalVariableTable: 
   Start  Length  Slot  Name   Signature
   0      42      0    this       Lscala/$colon$colon;
   0      42      1    x$1       Lscala/List;
   0      42      2    x$2       Ljava/lang/Object;


public java.lang.Object productElement(int);
  Signature: (I)Ljava/lang/Object;
  Code:
   Stack=3, Locals=3, Args_size=2
	iload_1
	istore_2
	iload_2
	tableswitch{ //0 to 1
		0: 46;
		1: 39;
		default: 24 }
	new	class java/lang/IndexOutOfBoundsException
	dup
	iload_1
	invokestatic	Method scala/runtime/BoxesRunTime.boxToInteger:(I)Ljava/lang/Integer;
	invokevirtual	Method java/lang/Object.toString:()Ljava/lang/String;
	invokespecial	Method java/lang/IndexOutOfBoundsException."<init>":(Ljava/lang/String;)V
	athrow
	aload_0
	invokevirtual	Method tl$1:()Lscala/List;
	goto	l1 // areturn
	aload_0
	invokevirtual	Method hd$1:()Ljava/lang/Object;
l1	areturn
  Labels:
   	l1 = 50 // areturn
  LocalVariableTable: 
   Start  Length  Slot  Name   Signature
   0      51      0    this       Lscala/$colon$colon;
   0      51      1    x$1       I


public int productArity();
  Signature: ()I
  Code:
   Stack=1, Locals=1, Args_size=1
	iconst_2
	ireturn
  Labels:

public java.lang.String productPrefix();
  Signature: ()Ljava/lang/String;
  Code:
   Stack=1, Locals=1, Args_size=1
	ldc	String ::
	areturn
  Labels:

public boolean equals(java.lang.Object);
  Signature: (Ljava/lang/Object;)Z
  Code:
   Stack=3, Locals=4, Args_size=2
	aload_1
	instanceof	class java/lang/Object
	ifeq	l1 // iconst_0
	aload_0
	aload_1
	if_acmpeq	l2 // iconst_1
	aload_1
	astore_2
	aload_2
	instanceof	class scala/$colon$colon
	ifeq	l3 // iconst_0
	aload_2
	checkcast	class scala/$colon$colon
	astore_3
	aload_0
	aload_3
	invokevirtual	Method tl$1:()Lscala/List;
	aload_3
	invokevirtual	Method hd$1:()Ljava/lang/Object;
	invokespecial	Method gd1$1:(Lscala/List;Ljava/lang/Object;)Z
	goto	l4 // ifeq
l3	iconst_0
l4	ifeq	l1 // iconst_0
l2	iconst_1
	goto	l5 // ireturn
l1	iconst_0
l5	ireturn
  Labels:
   	l3 = 41 // iconst_0
   	l4 = 42 // ifeq
   	l2 = 45 // iconst_1
   	l1 = 49 // iconst_0
   	l5 = 50 // ireturn
  LocalVariableTable: 
   Start  Length  Slot  Name   Signature
   0      51      0    this       Lscala/$colon$colon;
   0      51      1    x$1       Ljava/lang/Object;


public int hashCode();
  Signature: ()I
  Code:
   Stack=2, Locals=1, Args_size=1
	getstatic	Field scala/runtime/ScalaRunTime$.MODULE$:Lscala/runtime/ScalaRunTime$;
	aload_0
	invokevirtual	Method scala/runtime/ScalaRunTime$._hashCode:(Lscala/Product;)I
	ireturn
  Labels:

public scala.List tl$1();
  Signature: ()Lscala/List;
  Code:
   Stack=1, Locals=1, Args_size=1
	aload_0
	getfield	Field tl:Lscala/List;
	areturn
  Labels:

public java.lang.Object hd$1();
  Signature: ()Ljava/lang/Object;
  Code:
   Stack=1, Locals=1, Args_size=1
	aload_0
	getfield	Field hd:Ljava/lang/Object;
	areturn
  Labels:

public boolean isEmpty();
  Signature: ()Z
  Code:
   Stack=1, Locals=1, Args_size=1
	iconst_0
	ireturn
  Labels:

public scala.List tail();
  Signature: ()Lscala/List;
  Code:
   Stack=1, Locals=1, Args_size=1
	aload_0
	invokevirtual	Method tl:()Lscala/List;
	areturn
  Labels:
  Signature: length = 0x2
   00 30 

public java.lang.Object head();
  Signature: ()Ljava/lang/Object;
  Code:
   Stack=1, Locals=1, Args_size=1
	aload_0
	invokespecial	Method hd:()Ljava/lang/Object;
	areturn
  Labels:
  Signature: length = 0x2
   00 31 

public void tl_$eq(scala.List);
  Signature: (Lscala/List;)V
  Code:
   Stack=2, Locals=2, Args_size=2
	aload_0
	aload_1
	putfield	Field tl:Lscala/List;
	return
  Labels:
  LocalVariableTable: 
   Start  Length  Slot  Name   Signature
   0      6      0    this       Lscala/$colon$colon;
   0      6      1    x$1       Lscala/List;

  Signature: length = 0x2
   00 3C 

public scala.List tl();
  Signature: ()Lscala/List;
  Code:
   Stack=1, Locals=1, Args_size=1
	aload_0
	getfield	Field tl:Lscala/List;
	areturn
  Labels:
  Signature: length = 0x2
   00 30 

private java.lang.Object hd();
  Signature: ()Ljava/lang/Object;
  Code:
   Stack=1, Locals=1, Args_size=1
	aload_0
	getfield	Field hd:Ljava/lang/Object;
	areturn
  Labels:
  Signature: length = 0x2
   00 31 

}

