Compiled from "Application.scala"
public abstract class scala.Application$class extends java.lang.Object
  SourceFile: "Application.scala"
  Scala: length = 0x
   
  minor version: 0
  major version: 49
  Constant pool:
const #1 = Asciz	SourceFile;
const #2 = Asciz	Application.scala;
const #3 = Asciz	$init$;
const #4 = Asciz	(Lscala/Application;)V;
const #5 = Asciz	Code;
const #6 = Asciz	LineNumberTable;
const #7 = Asciz	scala/compat/Platform$;
const #8 = class	#7;	//  scala/compat/Platform$
const #9 = Asciz	MODULE$;
const #10 = Asciz	Lscala/compat/Platform$;;
const #11 = NameAndType	#9:#10;//  MODULE$:Lscala/compat/Platform$;
const #12 = Field	#8.#11;	//  scala/compat/Platform$.MODULE$:Lscala/compat/Platform$;
const #13 = Asciz	currentTime;
const #14 = Asciz	()J;
const #15 = NameAndType	#13:#14;//  currentTime:()J
const #16 = Method	#8.#15;	//  scala/compat/Platform$.currentTime:()J
const #17 = Asciz	scala/Application;
const #18 = class	#17;	//  scala/Application
const #19 = Asciz	scala$Application$_setter_$executionStart_$eq;
const #20 = Asciz	(J)V;
const #21 = NameAndType	#19:#20;//  scala$Application$_setter_$executionStart_$eq:(J)V
const #22 = InterfaceMethod	#18.#21;	//  scala/Application.scala$Application$_setter_$executionStart_$eq:(J)V
const #23 = Asciz	$this;
const #24 = Asciz	Lscala/Application;;
const #25 = Asciz	LocalVariableTable;
const #26 = Asciz	main;
const #27 = Asciz	(Lscala/Application;[Ljava/lang/String;)V;
const #28 = Asciz	scala.time;
const #29 = String	#28;	//  scala.time
const #30 = Asciz	java/lang/System;
const #31 = class	#30;	//  java/lang/System
const #32 = Asciz	getProperty;
const #33 = Asciz	(Ljava/lang/String;)Ljava/lang/String;;
const #34 = NameAndType	#32:#33;//  getProperty:(Ljava/lang/String;)Ljava/lang/String;
const #35 = Method	#31.#34;	//  java/lang/System.getProperty:(Ljava/lang/String;)Ljava/lang/String;
const #36 = Asciz	currentTimeMillis;
const #37 = NameAndType	#36:#14;//  currentTimeMillis:()J
const #38 = Method	#31.#37;	//  java/lang/System.currentTimeMillis:()J
const #39 = Asciz	executionStart;
const #40 = NameAndType	#39:#14;//  executionStart:()J
const #41 = InterfaceMethod	#18.#40;	//  scala/Application.executionStart:()J
const #42 = Asciz	scala/Console$;
const #43 = class	#42;	//  scala/Console$
const #44 = Asciz	Lscala/Console$;;
const #45 = NameAndType	#9:#44;//  MODULE$:Lscala/Console$;
const #46 = Field	#43.#45;	//  scala/Console$.MODULE$:Lscala/Console$;
const #47 = Asciz	scala/collection/mutable/StringBuilder;
const #48 = class	#47;	//  scala/collection/mutable/StringBuilder
const #49 = Asciz	<init>;
const #50 = Asciz	()V;
const #51 = NameAndType	#49:#50;//  "<init>":()V
const #52 = Method	#48.#51;	//  scala/collection/mutable/StringBuilder."<init>":()V
const #53 = Asciz	[total ;
const #54 = String	#53;	//  [total 
const #55 = Asciz	append;
const #56 = Asciz	(Ljava/lang/Object;)Lscala/collection/mutable/StringBuilder;;
const #57 = NameAndType	#55:#56;//  append:(Ljava/lang/Object;)Lscala/collection/mutable/StringBuilder;
const #58 = Method	#48.#57;	//  scala/collection/mutable/StringBuilder.append:(Ljava/lang/Object;)Lscala/collection/mutable/StringBuilder;
const #59 = Asciz	scala/runtime/BoxesRunTime;
const #60 = class	#59;	//  scala/runtime/BoxesRunTime
const #61 = Asciz	boxToLong;
const #62 = Asciz	(J)Ljava/lang/Long;;
const #63 = NameAndType	#61:#62;//  boxToLong:(J)Ljava/lang/Long;
const #64 = Method	#60.#63;	//  scala/runtime/BoxesRunTime.boxToLong:(J)Ljava/lang/Long;
const #65 = Asciz	ms];
const #66 = String	#65;	//  ms]
const #67 = Asciz	toString;
const #68 = Asciz	()Ljava/lang/String;;
const #69 = NameAndType	#67:#68;//  toString:()Ljava/lang/String;
const #70 = Method	#48.#69;	//  scala/collection/mutable/StringBuilder.toString:()Ljava/lang/String;
const #71 = Asciz	out;
const #72 = Asciz	()Ljava/io/PrintStream;;
const #73 = NameAndType	#71:#72;//  out:()Ljava/io/PrintStream;
const #74 = Method	#43.#73;	//  scala/Console$.out:()Ljava/io/PrintStream;
const #75 = Asciz	java/io/PrintStream;
const #76 = class	#75;	//  java/io/PrintStream
const #77 = Asciz	println;
const #78 = Asciz	(Ljava/lang/Object;)V;
const #79 = NameAndType	#77:#78;//  println:(Ljava/lang/Object;)V
const #80 = Method	#76.#79;	//  java/io/PrintStream.println:(Ljava/lang/Object;)V
const #81 = Asciz	args;
const #82 = Asciz	[Ljava/lang/String;;
const #83 = Asciz	total;
const #84 = Asciz	J;
const #85 = Asciz	Scala;
const #86 = Asciz	scala/Application$class;
const #87 = class	#86;	//  scala/Application$class
const #88 = Asciz	java/lang/Object;
const #89 = class	#88;	//  java/lang/Object

{
public static void $init$(scala.Application);
  Code:
   Stack=3, Locals=1, Args_size=1
   0:	aload_0
   1:	getstatic	#12; //Field scala/compat/Platform$.MODULE$:Lscala/compat/Platform$;
   4:	invokevirtual	#16; //Method scala/compat/Platform$.currentTime:()J
   7:	invokeinterface	#22,  3; //InterfaceMethod scala/Application.scala$Application$_setter_$executionStart_$eq:(J)V
   12:	return
  LineNumberTable: 
   line 80: 0

  LocalVariableTable: 
   Start  Length  Slot  Name   Signature
   0      13      0    $this       Lscala/Application;


public static void main(scala.Application, java.lang.String[]);
  Code:
   Stack=4, Locals=6, Args_size=2
   0:	ldc	#29; //String scala.time
   2:	invokestatic	#35; //Method java/lang/System.getProperty:(Ljava/lang/String;)Ljava/lang/String;
   5:	ifnull	63
   8:	invokestatic	#38; //Method java/lang/System.currentTimeMillis:()J
   11:	aload_0
   12:	invokeinterface	#41,  1; //InterfaceMethod scala/Application.executionStart:()J
   17:	lsub
   18:	lstore_2
   19:	getstatic	#46; //Field scala/Console$.MODULE$:Lscala/Console$;
   22:	new	#48; //class scala/collection/mutable/StringBuilder
   25:	dup
   26:	invokespecial	#52; //Method scala/collection/mutable/StringBuilder."<init>":()V
   29:	ldc	#54; //String [total 
   31:	invokevirtual	#58; //Method scala/collection/mutable/StringBuilder.append:(Ljava/lang/Object;)Lscala/collection/mutable/StringBuilder;
   34:	lload_2
   35:	invokestatic	#64; //Method scala/runtime/BoxesRunTime.boxToLong:(J)Ljava/lang/Long;
   38:	invokevirtual	#58; //Method scala/collection/mutable/StringBuilder.append:(Ljava/lang/Object;)Lscala/collection/mutable/StringBuilder;
   41:	ldc	#66; //String ms]
   43:	invokevirtual	#58; //Method scala/collection/mutable/StringBuilder.append:(Ljava/lang/Object;)Lscala/collection/mutable/StringBuilder;
   46:	invokevirtual	#70; //Method scala/collection/mutable/StringBuilder.toString:()Ljava/lang/String;
   49:	astore	5
   51:	astore	4
   53:	aload	4
   55:	invokevirtual	#74; //Method scala/Console$.out:()Ljava/io/PrintStream;
   58:	aload	5
   60:	invokevirtual	#80; //Method java/io/PrintStream.println:(Ljava/lang/Object;)V
   63:	return
  LineNumberTable: 
   line 87: 0
   line 88: 8
   line 89: 19
   line 87: 63

  LocalVariableTable: 
   Start  Length  Slot  Name   Signature
   0      64      0    $this       Lscala/Application;
   0      64      1    args       [Ljava/lang/String;
   19      44      2    total       J


}

