Compiled from "Application.scala"
public abstract class scala.Application$class extends java.lang.Object
  SourceFile: "Application.scala"
  Scala: length = 0x
   
  minor version: 0
  major version: 49
  Constant pool:
Asciz	SourceFile;
Asciz	Application.scala;
Asciz	main;
Asciz	(Lscala/Application;[Ljava/lang/String;)V;
Asciz	Code;
Asciz	scala/util/Properties$;
class	scala/util/Properties$
Asciz	MODULE$;
Asciz	Lscala/util/Properties$;;
NameAndType	MODULE$:Lscala/util/Properties$;
Field	scala/util/Properties$.MODULE$:Lscala/util/Properties$;
Asciz	LineNumberTable;
Asciz	scala.time;
String	scala.time
Asciz	scala/util/PropertiesTrait$class;
class	scala/util/PropertiesTrait$class
Asciz	propIsSet;
Asciz	(Lscala/util/PropertiesTrait;Ljava/lang/String;)Z;
NameAndType	propIsSet:(Lscala/util/PropertiesTrait;Ljava/lang/String;)Z
Method	scala/util/PropertiesTrait$class.propIsSet:(Lscala/util/PropertiesTrait;Ljava/lang/String;)Z
Asciz	java/lang/System;
class	java/lang/System
Asciz	currentTimeMillis;
Asciz	()J;
NameAndType	currentTimeMillis:()J
Method	java/lang/System.currentTimeMillis:()J
Asciz	scala/Application;
class	scala/Application
Asciz	executionStart;
NameAndType	executionStart:()J
InterfaceMethod	scala/Application.executionStart:()J
Asciz	scala/Console$;
class	scala/Console$
Asciz	Lscala/Console$;;
NameAndType	MODULE$:Lscala/Console$;
Field	scala/Console$.MODULE$:Lscala/Console$;
Asciz	scala/collection/mutable/StringBuilder;
class	scala/collection/mutable/StringBuilder
Asciz	<init>;
Asciz	()V;
NameAndType	"<init>":()V
Method	scala/collection/mutable/StringBuilder."<init>":()V
Asciz	[total ;
String	[total 
Asciz	append;
Asciz	(Ljava/lang/Object;)Lscala/collection/mutable/StringBuilder;;
NameAndType	append:(Ljava/lang/Object;)Lscala/collection/mutable/StringBuilder;
Method	scala/collection/mutable/StringBuilder.append:(Ljava/lang/Object;)Lscala/collection/mutable/StringBuilder;
Asciz	scala/runtime/BoxesRunTime;
class	scala/runtime/BoxesRunTime
Asciz	boxToLong;
Asciz	(J)Ljava/lang/Long;;
NameAndType	boxToLong:(J)Ljava/lang/Long;
Method	scala/runtime/BoxesRunTime.boxToLong:(J)Ljava/lang/Long;
Asciz	ms];
String	ms]
Asciz	toString;
Asciz	()Ljava/lang/String;;
NameAndType	toString:()Ljava/lang/String;
Method	scala/collection/mutable/StringBuilder.toString:()Ljava/lang/String;
Asciz	out;
Asciz	()Ljava/io/PrintStream;;
NameAndType	out:()Ljava/io/PrintStream;
Method	scala/Console$.out:()Ljava/io/PrintStream;
Asciz	java/io/PrintStream;
class	java/io/PrintStream
Asciz	println;
Asciz	(Ljava/lang/Object;)V;
NameAndType	println:(Ljava/lang/Object;)V
Method	java/io/PrintStream.println:(Ljava/lang/Object;)V
Asciz	$this;
Asciz	Lscala/Application;;
Asciz	args;
Asciz	[Ljava/lang/String;;
Asciz	total;
Asciz	J;
Asciz	LocalVariableTable;
Asciz	$init$;
Asciz	(Lscala/Application;)V;
Asciz	scala/compat/Platform$;
class	scala/compat/Platform$
Asciz	Lscala/compat/Platform$;;
NameAndType	MODULE$:Lscala/compat/Platform$;
Field	scala/compat/Platform$.MODULE$:Lscala/compat/Platform$;
Asciz	currentTime;
NameAndType	currentTime:()J
Method	scala/compat/Platform$.currentTime:()J
Asciz	scala$Application$_setter_$executionStart_$eq;
Asciz	(J)V;
NameAndType	scala$Application$_setter_$executionStart_$eq:(J)V
InterfaceMethod	scala/Application.scala$Application$_setter_$executionStart_$eq:(J)V
Asciz	Scala;
Asciz	scala/Application$class;
class	scala/Application$class
Asciz	java/lang/Object;
class	java/lang/Object

{
public static void main(scala.Application, java.lang.String[]);
  Signature: (Lscala/Application;[Ljava/lang/String;)V
  Code:
   Stack=4, Locals=8, Args_size=2
	getstatic	Field scala/util/Properties$.MODULE$:Lscala/util/Properties$;
	ldc	String scala.time
	astore_3
	astore_2
	aload_2
	aload_3
	invokestatic	Method scala/util/PropertiesTrait$class.propIsSet:(Lscala/util/PropertiesTrait;Ljava/lang/String;)Z
	ifeq	l1 // return
	invokestatic	Method java/lang/System.currentTimeMillis:()J
	aload_0
	invokeinterface	InterfaceMethod scala/Application.executionStart:()J
	lsub
	lstore	4
	getstatic	Field scala/Console$.MODULE$:Lscala/Console$;
	new	class scala/collection/mutable/StringBuilder
	dup
	invokespecial	Method scala/collection/mutable/StringBuilder."<init>":()V
	ldc	String [total 
	invokevirtual	Method scala/collection/mutable/StringBuilder.append:(Ljava/lang/Object;)Lscala/collection/mutable/StringBuilder;
	lload	4
	invokestatic	Method scala/runtime/BoxesRunTime.boxToLong:(J)Ljava/lang/Long;
	invokevirtual	Method scala/collection/mutable/StringBuilder.append:(Ljava/lang/Object;)Lscala/collection/mutable/StringBuilder;
	ldc	String ms]
	invokevirtual	Method scala/collection/mutable/StringBuilder.append:(Ljava/lang/Object;)Lscala/collection/mutable/StringBuilder;
	invokevirtual	Method scala/collection/mutable/StringBuilder.toString:()Ljava/lang/String;
	astore	7
	astore	6
	aload	6
	invokevirtual	Method scala/Console$.out:()Ljava/io/PrintStream;
	aload	7
	invokevirtual	Method java/io/PrintStream.println:(Ljava/lang/Object;)V
l1	return
  Labels:
   	l1 = 72 // return
  LocalVariableTable: 
   Start  Length  Slot  Name   Signature
   0      73      0    $this       Lscala/Application;
   0      73      1    args       [Ljava/lang/String;
   27      45      4    total       J


public static void $init$(scala.Application);
  Signature: (Lscala/Application;)V
  Code:
   Stack=3, Locals=1, Args_size=1
	aload_0
	getstatic	Field scala/compat/Platform$.MODULE$:Lscala/compat/Platform$;
	invokevirtual	Method scala/compat/Platform$.currentTime:()J
	invokeinterface	InterfaceMethod scala/Application.scala$Application$_setter_$executionStart_$eq:(J)V
	return
  Labels:
  LocalVariableTable: 
   Start  Length  Slot  Name   Signature
   0      13      0    $this       Lscala/Application;


}

