Compiled from "Array.scala"
public final class scala.Array$$anonfun$apply$6 extends java.lang.Object implements scala.Function1,scala.ScalaObject,java.io.Serializable
  SourceFile: "Array.scala"
  Scala: length = 0x
   
  InnerClass: 
   public final $anonfun$apply$6=class scala/Array$$anonfun$apply$6 of class scala/Array
  minor version: 0
  major version: 49
  Constant pool:
Asciz	SourceFile;
Asciz	Array.scala;
Asciz	<clinit>;
Asciz	()V;
Asciz	Code;
Asciz	serialVersionUID;
Asciz	J;
Asciz	scala/Array$$anonfun$apply$6;
class	scala/Array$$anonfun$apply$6
NameAndType	serialVersionUID:J
Field	scala/Array$$anonfun$apply$6.serialVersionUID:J
Asciz	i$6;
Asciz	Lscala/runtime/IntRef;;
Asciz	array$6;
Asciz	[I;
Asciz	<init>;
Asciz	([ILscala/runtime/IntRef;)V;
Asciz	LineNumberTable;
NameAndType	array$6:[I
Field	scala/Array$$anonfun$apply$6.array$6:[I
NameAndType	i$6:Lscala/runtime/IntRef;
Field	scala/Array$$anonfun$apply$6.i$6:Lscala/runtime/IntRef;
Asciz	java/lang/Object;
class	java/lang/Object
NameAndType	"<init>":()V
Method	java/lang/Object."<init>":()V
Asciz	scala/Function1$class;
class	scala/Function1$class
Asciz	$init$;
Asciz	(Lscala/Function1;)V;
NameAndType	$init$:(Lscala/Function1;)V
Method	scala/Function1$class.$init$:(Lscala/Function1;)V
Asciz	apply;
Asciz	(Ljava/lang/Object;)Ljava/lang/Object;;
Asciz	scala/runtime/BoxesRunTime;
class	scala/runtime/BoxesRunTime
Asciz	unboxToInt;
Asciz	(Ljava/lang/Object;)I;
NameAndType	unboxToInt:(Ljava/lang/Object;)I
Method	scala/runtime/BoxesRunTime.unboxToInt:(Ljava/lang/Object;)I
Asciz	(I)V;
NameAndType	apply:(I)V
Method	scala/Array$$anonfun$apply$6.apply:(I)V
Asciz	scala/runtime/BoxedUnit;
class	scala/runtime/BoxedUnit
Asciz	UNIT;
Asciz	Lscala/runtime/BoxedUnit;;
NameAndType	UNIT:Lscala/runtime/BoxedUnit;
Field	scala/runtime/BoxedUnit.UNIT:Lscala/runtime/BoxedUnit;
Asciz	this;
Asciz	Lscala/Array$$anonfun$apply$6;;
Asciz	v1;
Asciz	Ljava/lang/Object;;
Asciz	LocalVariableTable;
Asciz	scala/runtime/IntRef;
class	scala/runtime/IntRef
Asciz	elem;
Asciz	I;
NameAndType	elem:I
Field	scala/runtime/IntRef.elem:I
Asciz	x;
Asciz	andThen;
Asciz	(Lscala/Function1;)Lscala/Function1;;
Asciz	(Lscala/Function1;Lscala/Function1;)Lscala/Function1;;
NameAndType	andThen:(Lscala/Function1;Lscala/Function1;)Lscala/Function1;
Method	scala/Function1$class.andThen:(Lscala/Function1;Lscala/Function1;)Lscala/Function1;
Asciz	g;
Asciz	Lscala/Function1;;
Asciz	compose;
NameAndType	compose:(Lscala/Function1;Lscala/Function1;)Lscala/Function1;
Method	scala/Function1$class.compose:(Lscala/Function1;Lscala/Function1;)Lscala/Function1;
Asciz	toString;
Asciz	()Ljava/lang/String;;
Asciz	(Lscala/Function1;)Ljava/lang/String;;
NameAndType	toString:(Lscala/Function1;)Ljava/lang/String;
Method	scala/Function1$class.toString:(Lscala/Function1;)Ljava/lang/String;
Asciz	Scala;
Asciz	InnerClasses;
Asciz	scala/Array;
class	scala/Array
Asciz	$anonfun$apply$6;
Asciz	scala/Function1;
class	scala/Function1
Asciz	scala/ScalaObject;
class	scala/ScalaObject
Asciz	java/io/Serializable;
class	java/io/Serializable

{
public static final long serialVersionUID;
  Signature: J

private final scala.runtime.IntRef i$6;
  Signature: Lscala/runtime/IntRef;

private final int[] array$6;
  Signature: [I

public static {};
  Signature: ()V
  Code:
   Stack=2, Locals=0, Args_size=0
	lconst_0
	putstatic	Field serialVersionUID:J
	return
  Labels:

public scala.Array$$anonfun$apply$6(int[], scala.runtime.IntRef);
  Signature: ([ILscala/runtime/IntRef;)V
  Code:
   Stack=2, Locals=3, Args_size=3
	aload_0
	aload_1
	putfield	Field array$6:[I
	aload_0
	aload_2
	putfield	Field i$6:Lscala/runtime/IntRef;
	aload_0
	invokespecial	Method java/lang/Object."<init>":()V
	aload_0
	invokestatic	Method scala/Function1$class.$init$:(Lscala/Function1;)V
	return
  Labels:

public final java.lang.Object apply(java.lang.Object);
  Signature: (Ljava/lang/Object;)Ljava/lang/Object;
  Code:
   Stack=2, Locals=2, Args_size=2
	aload_0
	aload_1
	invokestatic	Method scala/runtime/BoxesRunTime.unboxToInt:(Ljava/lang/Object;)I
	invokevirtual	Method apply:(I)V
	getstatic	Field scala/runtime/BoxedUnit.UNIT:Lscala/runtime/BoxedUnit;
	areturn
  Labels:
  LocalVariableTable: 
   Start  Length  Slot  Name   Signature
   0      12      0    this       Lscala/Array$$anonfun$apply$6;
   0      12      1    v1       Ljava/lang/Object;


public final void apply(int);
  Signature: (I)V
  Code:
   Stack=3, Locals=2, Args_size=2
	aload_0
	getfield	Field array$6:[I
	aload_0
	getfield	Field i$6:Lscala/runtime/IntRef;
	getfield	Field scala/runtime/IntRef.elem:I
	iload_1
	iastore
	aload_0
	getfield	Field i$6:Lscala/runtime/IntRef;
	aload_0
	getfield	Field i$6:Lscala/runtime/IntRef;
	getfield	Field scala/runtime/IntRef.elem:I
	iconst_1
	iadd
	putfield	Field scala/runtime/IntRef.elem:I
	return
  Labels:
  LocalVariableTable: 
   Start  Length  Slot  Name   Signature
   0      30      0    this       Lscala/Array$$anonfun$apply$6;
   0      30      1    x       I


public scala.Function1 andThen(scala.Function1);
  Signature: (Lscala/Function1;)Lscala/Function1;
  Code:
   Stack=2, Locals=2, Args_size=2
	aload_0
	aload_1
	invokestatic	Method scala/Function1$class.andThen:(Lscala/Function1;Lscala/Function1;)Lscala/Function1;
	areturn
  Labels:
  LocalVariableTable: 
   Start  Length  Slot  Name   Signature
   0      6      0    this       Lscala/Array$$anonfun$apply$6;
   0      6      1    g       Lscala/Function1;


public scala.Function1 compose(scala.Function1);
  Signature: (Lscala/Function1;)Lscala/Function1;
  Code:
   Stack=2, Locals=2, Args_size=2
	aload_0
	aload_1
	invokestatic	Method scala/Function1$class.compose:(Lscala/Function1;Lscala/Function1;)Lscala/Function1;
	areturn
  Labels:
  LocalVariableTable: 
   Start  Length  Slot  Name   Signature
   0      6      0    this       Lscala/Array$$anonfun$apply$6;
   0      6      1    g       Lscala/Function1;


public java.lang.String toString();
  Signature: ()Ljava/lang/String;
  Code:
   Stack=1, Locals=1, Args_size=1
	aload_0
	invokestatic	Method scala/Function1$class.toString:(Lscala/Function1;)Ljava/lang/String;
	areturn
  Labels:

}

