Compiled from "Array.scala"
public final class scala.Array$ extends scala.FallbackArrayBuilding implements scala.ScalaObject
  SourceFile: "Array.scala"
  Scala: length = 0x
   
  InnerClass: 
   public abstract #629= #430 of #628; //ByOne=class scala/collection/immutable/Range$ByOne of class scala/collection/immutable/Range
   public final #632= #620 of #631; //$anon$2=class scala/Array$$anon$2 of class scala/Array
   public final #633= #310 of #631; //$anonfun$fill$1=class scala/Array$$anonfun$fill$1 of class scala/Array
   public final #634= #299 of #631; //$anonfun$fill$2=class scala/Array$$anonfun$fill$2 of class scala/Array
   public final #635= #287 of #631; //$anonfun$fill$3=class scala/Array$$anonfun$fill$3 of class scala/Array
   public final #636= #273 of #631; //$anonfun$fill$4=class scala/Array$$anonfun$fill$4 of class scala/Array
   public final #637= #563 of #631; //$anonfun$apply$1=class scala/Array$$anonfun$apply$1 of class scala/Array
   public final #638= #553 of #631; //$anonfun$apply$2=class scala/Array$$anonfun$apply$2 of class scala/Array
   public final #639= #542 of #631; //$anonfun$apply$3=class scala/Array$$anonfun$apply$3 of class scala/Array
   public final #640= #531 of #631; //$anonfun$apply$4=class scala/Array$$anonfun$apply$4 of class scala/Array
   public final #641= #520 of #631; //$anonfun$apply$5=class scala/Array$$anonfun$apply$5 of class scala/Array
   public final #642= #511 of #631; //$anonfun$apply$6=class scala/Array$$anonfun$apply$6 of class scala/Array
   public final #643= #500 of #631; //$anonfun$apply$7=class scala/Array$$anonfun$apply$7 of class scala/Array
   public final #644= #489 of #631; //$anonfun$apply$8=class scala/Array$$anonfun$apply$8 of class scala/Array
   public final #645= #478 of #631; //$anonfun$apply$9=class scala/Array$$anonfun$apply$9 of class scala/Array
   public final #646= #432 of #631; //$anonfun$ofDim$1=class scala/Array$$anonfun$ofDim$1 of class scala/Array
   public final #647= #406 of #631; //$anonfun$ofDim$2=class scala/Array$$anonfun$ofDim$2 of class scala/Array
   public final #648= #395 of #631; //$anonfun$ofDim$3=class scala/Array$$anonfun$ofDim$3 of class scala/Array
   public final #649= #383 of #631; //$anonfun$ofDim$4=class scala/Array$$anonfun$ofDim$4 of class scala/Array
   public final #650= #462 of #631; //$anonfun$apply$10=class scala/Array$$anonfun$apply$10 of class scala/Array
   public final #651= #365 of #631; //$anonfun$concat$2=class scala/Array$$anonfun$concat$2 of class scala/Array
   public final #652= #332 of #631; //$anonfun$concat$1=class scala/Array$$anonfun$concat$1 of class scala/Array
   public final #653= #260 of #631; //$anonfun$tabulate$1=class scala/Array$$anonfun$tabulate$1 of class scala/Array
   public final #654= #249 of #631; //$anonfun$tabulate$2=class scala/Array$$anonfun$tabulate$2 of class scala/Array
   public final #655= #237 of #631; //$anonfun$tabulate$3=class scala/Array$$anonfun$tabulate$3 of class scala/Array
   public final #656= #221 of #631; //$anonfun$tabulate$4=class scala/Array$$anonfun$tabulate$4 of class scala/Array
   public final #657= #87 of #631; //$anonfun$fromFunction$1=class scala/Array$$anonfun$fromFunction$1 of class scala/Array
   public final #658= #73 of #631; //$anonfun$fromFunction$2=class scala/Array$$anonfun$fromFunction$2 of class scala/Array
   public final #659= #58 of #631; //$anonfun$fromFunction$3=class scala/Array$$anonfun$fromFunction$3 of class scala/Array
   public final #660= #23 of #631; //$anonfun$fromFunction$4=class scala/Array$$anonfun$fromFunction$4 of class scala/Array
  minor version: 0
  major version: 49
  Constant pool:
const #1 = Asciz	SourceFile;
const #2 = Asciz	Array.scala;
const #3 = Asciz	Scala;
const #4 = Asciz	MODULE$;
const #5 = Asciz	Lscala/Array$;;
const #6 = Asciz	<clinit>;
const #7 = Asciz	()V;
const #8 = Asciz	Code;
const #9 = Asciz	scala/Array$;
const #10 = class	#9;	//  scala/Array$
const #11 = Asciz	<init>;
const #12 = NameAndType	#11:#7;//  "<init>":()V
const #13 = Method	#10.#12;	//  scala/Array$."<init>":()V
const #14 = Asciz	LineNumberTable;
const #15 = Asciz	scala/FallbackArrayBuilding;
const #16 = class	#15;	//  scala/FallbackArrayBuilding
const #17 = Method	#16.#12;	//  scala/FallbackArrayBuilding."<init>":()V
const #18 = NameAndType	#4:#5;//  MODULE$:Lscala/Array$;
const #19 = Field	#10.#18;	//  scala/Array$.MODULE$:Lscala/Array$;
const #20 = Asciz	fromFunction;
const #21 = Asciz	(Lscala/Function5;IIIIILscala/reflect/ClassManifest;)[[[[Ljava/lang/Object;;
const #22 = Asciz	scala/Array$$anonfun$fromFunction$4;
const #23 = class	#22;	//  scala/Array$$anonfun$fromFunction$4
const #24 = Asciz	(Lscala/Function5;IIIILscala/reflect/ClassManifest;)V;
const #25 = NameAndType	#11:#24;//  "<init>":(Lscala/Function5;IIIILscala/reflect/ClassManifest;)V
const #26 = Method	#23.#25;	//  scala/Array$$anonfun$fromFunction$4."<init>":(Lscala/Function5;IIIILscala/reflect/ClassManifest;)V
const #27 = Asciz	scala/reflect/ClassManifest$;
const #28 = class	#27;	//  scala/reflect/ClassManifest$
const #29 = Asciz	Lscala/reflect/ClassManifest$;;
const #30 = NameAndType	#4:#29;//  MODULE$:Lscala/reflect/ClassManifest$;
const #31 = Field	#28.#30;	//  scala/reflect/ClassManifest$.MODULE$:Lscala/reflect/ClassManifest$;
const #32 = Asciz	arrayType;
const #33 = Asciz	(Lscala/reflect/OptManifest;)Lscala/reflect/ClassManifest;;
const #34 = NameAndType	#32:#33;//  arrayType:(Lscala/reflect/OptManifest;)Lscala/reflect/ClassManifest;
const #35 = Method	#28.#34;	//  scala/reflect/ClassManifest$.arrayType:(Lscala/reflect/OptManifest;)Lscala/reflect/ClassManifest;
const #36 = Asciz	(Lscala/Function1;ILscala/reflect/ClassManifest;)Ljava/lang/Object;;
const #37 = NameAndType	#20:#36;//  fromFunction:(Lscala/Function1;ILscala/reflect/ClassManifest;)Ljava/lang/Object;
const #38 = Method	#10.#37;	//  scala/Array$.fromFunction:(Lscala/Function1;ILscala/reflect/ClassManifest;)Ljava/lang/Object;
const #39 = Asciz	[[[[Ljava/lang/Object;;
const #40 = class	#39;	//  "[[[[Ljava/lang/Object;"
const #41 = Asciz	this;
const #42 = Asciz	f$6;
const #43 = Asciz	Lscala/Function5;;
const #44 = Asciz	n1;
const #45 = Asciz	I;
const #46 = Asciz	n2$14;
const #47 = Asciz	n3$10;
const #48 = Asciz	n4$7;
const #49 = Asciz	n5$4;
const #50 = Asciz	evidence$25$1;
const #51 = Asciz	Lscala/reflect/ClassManifest;;
const #52 = Asciz	LocalVariableTable;
const #53 = Asciz	<T:Ljava/lang/Object;>(Lscala/Function5<Ljava/lang/Integer;Ljava/lang/Integer;Ljava/lang/Integer;Ljava/lang/Integer;Ljava/lang/Integer;TT;>;IIIIILscala/reflect/ClassManifest<TT;>;)[[[[[TT;;
const #54 = Asciz	Signature;
const #55 = Asciz	Deprecated;
const #56 = Asciz	(Lscala/Function4;IIIILscala/reflect/ClassManifest;)[[[Ljava/lang/Object;;
const #57 = Asciz	scala/Array$$anonfun$fromFunction$3;
const #58 = class	#57;	//  scala/Array$$anonfun$fromFunction$3
const #59 = Asciz	(Lscala/Function4;IIILscala/reflect/ClassManifest;)V;
const #60 = NameAndType	#11:#59;//  "<init>":(Lscala/Function4;IIILscala/reflect/ClassManifest;)V
const #61 = Method	#58.#60;	//  scala/Array$$anonfun$fromFunction$3."<init>":(Lscala/Function4;IIILscala/reflect/ClassManifest;)V
const #62 = Asciz	[[[Ljava/lang/Object;;
const #63 = class	#62;	//  "[[[Ljava/lang/Object;"
const #64 = Asciz	f$7;
const #65 = Asciz	Lscala/Function4;;
const #66 = Asciz	n2$15;
const #67 = Asciz	n3$11;
const #68 = Asciz	n4$8;
const #69 = Asciz	evidence$24$1;
const #70 = Asciz	<T:Ljava/lang/Object;>(Lscala/Function4<Ljava/lang/Integer;Ljava/lang/Integer;Ljava/lang/Integer;Ljava/lang/Integer;TT;>;IIIILscala/reflect/ClassManifest<TT;>;)[[[[TT;;
const #71 = Asciz	(Lscala/Function3;IIILscala/reflect/ClassManifest;)[[Ljava/lang/Object;;
const #72 = Asciz	scala/Array$$anonfun$fromFunction$2;
const #73 = class	#72;	//  scala/Array$$anonfun$fromFunction$2
const #74 = Asciz	(Lscala/Function3;IILscala/reflect/ClassManifest;)V;
const #75 = NameAndType	#11:#74;//  "<init>":(Lscala/Function3;IILscala/reflect/ClassManifest;)V
const #76 = Method	#73.#75;	//  scala/Array$$anonfun$fromFunction$2."<init>":(Lscala/Function3;IILscala/reflect/ClassManifest;)V
const #77 = Asciz	[[Ljava/lang/Object;;
const #78 = class	#77;	//  "[[Ljava/lang/Object;"
const #79 = Asciz	f$8;
const #80 = Asciz	Lscala/Function3;;
const #81 = Asciz	n2$16;
const #82 = Asciz	n3$12;
const #83 = Asciz	evidence$23$1;
const #84 = Asciz	<T:Ljava/lang/Object;>(Lscala/Function3<Ljava/lang/Integer;Ljava/lang/Integer;Ljava/lang/Integer;TT;>;IIILscala/reflect/ClassManifest<TT;>;)[[[TT;;
const #85 = Asciz	(Lscala/Function2;IILscala/reflect/ClassManifest;)[Ljava/lang/Object;;
const #86 = Asciz	scala/Array$$anonfun$fromFunction$1;
const #87 = class	#86;	//  scala/Array$$anonfun$fromFunction$1
const #88 = Asciz	(Lscala/Function2;ILscala/reflect/ClassManifest;)V;
const #89 = NameAndType	#11:#88;//  "<init>":(Lscala/Function2;ILscala/reflect/ClassManifest;)V
const #90 = Method	#87.#89;	//  scala/Array$$anonfun$fromFunction$1."<init>":(Lscala/Function2;ILscala/reflect/ClassManifest;)V
const #91 = Asciz	[Ljava/lang/Object;;
const #92 = class	#91;	//  "[Ljava/lang/Object;"
const #93 = Asciz	f$5;
const #94 = Asciz	Lscala/Function2;;
const #95 = Asciz	n2$13;
const #96 = Asciz	evidence$22$1;
const #97 = Asciz	<T:Ljava/lang/Object;>(Lscala/Function2<Ljava/lang/Integer;Ljava/lang/Integer;TT;>;IILscala/reflect/ClassManifest<TT;>;)[[TT;;
const #98 = Asciz	scala/reflect/ClassManifest;
const #99 = class	#98;	//  scala/reflect/ClassManifest
const #100 = Asciz	newArray;
const #101 = Asciz	(I)Ljava/lang/Object;;
const #102 = NameAndType	#100:#101;//  newArray:(I)Ljava/lang/Object;
const #103 = InterfaceMethod	#99.#102;	//  scala/reflect/ClassManifest.newArray:(I)Ljava/lang/Object;
const #104 = Asciz	scala/runtime/BoxesRunTime;
const #105 = class	#104;	//  scala/runtime/BoxesRunTime
const #106 = Asciz	boxToInteger;
const #107 = Asciz	(I)Ljava/lang/Integer;;
const #108 = NameAndType	#106:#107;//  boxToInteger:(I)Ljava/lang/Integer;
const #109 = Method	#105.#108;	//  scala/runtime/BoxesRunTime.boxToInteger:(I)Ljava/lang/Integer;
const #110 = Asciz	scala/Function1;
const #111 = class	#110;	//  scala/Function1
const #112 = Asciz	apply;
const #113 = Asciz	(Ljava/lang/Object;)Ljava/lang/Object;;
const #114 = NameAndType	#112:#113;//  apply:(Ljava/lang/Object;)Ljava/lang/Object;
const #115 = InterfaceMethod	#111.#114;	//  scala/Function1.apply:(Ljava/lang/Object;)Ljava/lang/Object;
const #116 = Asciz	java/lang/reflect/Array;
const #117 = class	#116;	//  java/lang/reflect/Array
const #118 = Asciz	set;
const #119 = Asciz	(Ljava/lang/Object;ILjava/lang/Object;)V;
const #120 = NameAndType	#118:#119;//  set:(Ljava/lang/Object;ILjava/lang/Object;)V
const #121 = Method	#117.#120;	//  java/lang/reflect/Array.set:(Ljava/lang/Object;ILjava/lang/Object;)V
const #122 = Asciz	f;
const #123 = Asciz	Lscala/Function1;;
const #124 = Asciz	n;
const #125 = Asciz	evidence$21;
const #126 = Asciz	i;
const #127 = Asciz	a;
const #128 = Asciz	Ljava/lang/Object;;
const #129 = Asciz	<T:Ljava/lang/Object;>(Lscala/Function1<Ljava/lang/Integer;TT;>;ILscala/reflect/ClassManifest<TT;>;)[TT;;
const #130 = Asciz	make;
const #131 = Asciz	(ILjava/lang/Object;Lscala/reflect/ClassManifest;)Ljava/lang/Object;;
const #132 = Asciz	elem;
const #133 = Asciz	evidence$20;
const #134 = Asciz	<T:Ljava/lang/Object;>(ITT;Lscala/reflect/ClassManifest<TT;>;)[TT;;
const #135 = Asciz	unapplySeq;
const #136 = Asciz	(Ljava/lang/Object;)Lscala/Option;;
const #137 = Asciz	java/lang/Object;
const #138 = class	#137;	//  java/lang/Object
const #139 = Asciz	equals;
const #140 = Asciz	(Ljava/lang/Object;)Z;
const #141 = NameAndType	#139:#140;//  equals:(Ljava/lang/Object;)Z
const #142 = Method	#138.#141;	//  java/lang/Object.equals:(Ljava/lang/Object;)Z
const #143 = Asciz	scala/None$;
const #144 = class	#143;	//  scala/None$
const #145 = Asciz	Lscala/None$;;
const #146 = NameAndType	#4:#145;//  MODULE$:Lscala/None$;
const #147 = Field	#144.#146;	//  scala/None$.MODULE$:Lscala/None$;
const #148 = Asciz	scala/Some;
const #149 = class	#148;	//  scala/Some
const #150 = Asciz	scala/Predef$;
const #151 = class	#150;	//  scala/Predef$
const #152 = Asciz	Lscala/Predef$;;
const #153 = NameAndType	#4:#152;//  MODULE$:Lscala/Predef$;
const #154 = Field	#151.#153;	//  scala/Predef$.MODULE$:Lscala/Predef$;
const #155 = Asciz	genericArrayOps;
const #156 = Asciz	(Ljava/lang/Object;)Lscala/collection/mutable/ArrayOps;;
const #157 = NameAndType	#155:#156;//  genericArrayOps:(Ljava/lang/Object;)Lscala/collection/mutable/ArrayOps;
const #158 = Method	#151.#157;	//  scala/Predef$.genericArrayOps:(Ljava/lang/Object;)Lscala/collection/mutable/ArrayOps;
const #159 = Asciz	scala/collection/TraversableLike;
const #160 = class	#159;	//  scala/collection/TraversableLike
const #161 = Asciz	toIndexedSeq;
const #162 = Asciz	()Lscala/collection/mutable/IndexedSeq;;
const #163 = NameAndType	#161:#162;//  toIndexedSeq:()Lscala/collection/mutable/IndexedSeq;
const #164 = InterfaceMethod	#160.#163;	//  scala/collection/TraversableLike.toIndexedSeq:()Lscala/collection/mutable/IndexedSeq;
const #165 = Asciz	(Ljava/lang/Object;)V;
const #166 = NameAndType	#11:#165;//  "<init>":(Ljava/lang/Object;)V
const #167 = Method	#149.#166;	//  scala/Some."<init>":(Ljava/lang/Object;)V
const #168 = Asciz	x;
const #169 = Asciz	<T:Ljava/lang/Object;>([TT;)Lscala/Option<Lscala/collection/IndexedSeq<TT;>;>;;
const #170 = Asciz	iterate;
const #171 = Asciz	(Ljava/lang/Object;ILscala/Function1;Lscala/reflect/ClassManifest;)Ljava/lang/Object;;
const #172 = Asciz	newArrayBuilder;
const #173 = Asciz	()Lscala/collection/mutable/ArrayBuilder;;
const #174 = NameAndType	#172:#173;//  newArrayBuilder:()Lscala/collection/mutable/ArrayBuilder;
const #175 = InterfaceMethod	#99.#174;	//  scala/reflect/ClassManifest.newArrayBuilder:()Lscala/collection/mutable/ArrayBuilder;
const #176 = Asciz	scala/collection/mutable/Builder;
const #177 = class	#176;	//  scala/collection/mutable/Builder
const #178 = Asciz	$plus$eq;
const #179 = Asciz	(Ljava/lang/Object;)Lscala/collection/mutable/Builder;;
const #180 = NameAndType	#178:#179;//  $plus$eq:(Ljava/lang/Object;)Lscala/collection/mutable/Builder;
const #181 = InterfaceMethod	#177.#180;	//  scala/collection/mutable/Builder.$plus$eq:(Ljava/lang/Object;)Lscala/collection/mutable/Builder;
const #182 = Asciz	result;
const #183 = Asciz	()Ljava/lang/Object;;
const #184 = NameAndType	#182:#183;//  result:()Ljava/lang/Object;
const #185 = InterfaceMethod	#177.#184;	//  scala/collection/mutable/Builder.result:()Ljava/lang/Object;
const #186 = Asciz	start;
const #187 = Asciz	len;
const #188 = Asciz	evidence$19;
const #189 = Asciz	acc;
const #190 = Asciz	b;
const #191 = Asciz	Lscala/collection/mutable/ArrayBuilder;;
const #192 = Asciz	<T:Ljava/lang/Object;>(TT;ILscala/Function1<TT;TT;>;Lscala/reflect/ClassManifest<TT;>;)[TT;;
const #193 = Asciz	range;
const #194 = Asciz	(III)[I;
const #195 = Asciz	java/lang/IllegalArgumentException;
const #196 = class	#195;	//  java/lang/IllegalArgumentException
const #197 = Asciz	zero step;
const #198 = String	#197;	//  zero step
const #199 = Asciz	(Ljava/lang/String;)V;
const #200 = NameAndType	#11:#199;//  "<init>":(Ljava/lang/String;)V
const #201 = Method	#196.#200;	//  java/lang/IllegalArgumentException."<init>":(Ljava/lang/String;)V
const #202 = Asciz	scala/reflect/Manifest$;
const #203 = class	#202;	//  scala/reflect/Manifest$
const #204 = Asciz	Lscala/reflect/Manifest$;;
const #205 = NameAndType	#4:#204;//  MODULE$:Lscala/reflect/Manifest$;
const #206 = Field	#203.#205;	//  scala/reflect/Manifest$.MODULE$:Lscala/reflect/Manifest$;
const #207 = Asciz	Int;
const #208 = Asciz	()Lscala/reflect/AnyValManifest;;
const #209 = NameAndType	#207:#208;//  Int:()Lscala/reflect/AnyValManifest;
const #210 = Method	#203.#209;	//  scala/reflect/Manifest$.Int:()Lscala/reflect/AnyValManifest;
const #211 = Asciz	[I;
const #212 = class	#211;	//  "[I"
const #213 = Asciz	end;
const #214 = Asciz	step;
const #215 = Asciz	(II)[I;
const #216 = NameAndType	#193:#194;//  range:(III)[I
const #217 = Method	#10.#216;	//  scala/Array$.range:(III)[I
const #218 = Asciz	tabulate;
const #219 = Asciz	(IIIIILscala/Function5;Lscala/reflect/ClassManifest;)[[[[Ljava/lang/Object;;
const #220 = Asciz	scala/Array$$anonfun$tabulate$4;
const #221 = class	#220;	//  scala/Array$$anonfun$tabulate$4
const #222 = Asciz	(IIIILscala/Function5;Lscala/reflect/ClassManifest;)V;
const #223 = NameAndType	#11:#222;//  "<init>":(IIIILscala/Function5;Lscala/reflect/ClassManifest;)V
const #224 = Method	#221.#223;	//  scala/Array$$anonfun$tabulate$4."<init>":(IIIILscala/Function5;Lscala/reflect/ClassManifest;)V
const #225 = Asciz	(ILscala/Function1;Lscala/reflect/ClassManifest;)Ljava/lang/Object;;
const #226 = NameAndType	#218:#225;//  tabulate:(ILscala/Function1;Lscala/reflect/ClassManifest;)Ljava/lang/Object;
const #227 = Method	#10.#226;	//  scala/Array$.tabulate:(ILscala/Function1;Lscala/reflect/ClassManifest;)Ljava/lang/Object;
const #228 = Asciz	n2$3;
const #229 = Asciz	n3$2;
const #230 = Asciz	n4$1;
const #231 = Asciz	n5$1;
const #232 = Asciz	f$1;
const #233 = Asciz	evidence$18$1;
const #234 = Asciz	<T:Ljava/lang/Object;>(IIIIILscala/Function5<Ljava/lang/Integer;Ljava/lang/Integer;Ljava/lang/Integer;Ljava/lang/Integer;Ljava/lang/Integer;TT;>;Lscala/reflect/ClassManifest<TT;>;)[[[[[TT;;
const #235 = Asciz	(IIIILscala/Function4;Lscala/reflect/ClassManifest;)[[[Ljava/lang/Object;;
const #236 = Asciz	scala/Array$$anonfun$tabulate$3;
const #237 = class	#236;	//  scala/Array$$anonfun$tabulate$3
const #238 = Asciz	(IIILscala/Function4;Lscala/reflect/ClassManifest;)V;
const #239 = NameAndType	#11:#238;//  "<init>":(IIILscala/Function4;Lscala/reflect/ClassManifest;)V
const #240 = Method	#237.#239;	//  scala/Array$$anonfun$tabulate$3."<init>":(IIILscala/Function4;Lscala/reflect/ClassManifest;)V
const #241 = Asciz	n2$4;
const #242 = Asciz	n3$3;
const #243 = Asciz	n4$2;
const #244 = Asciz	f$2;
const #245 = Asciz	evidence$17$1;
const #246 = Asciz	<T:Ljava/lang/Object;>(IIIILscala/Function4<Ljava/lang/Integer;Ljava/lang/Integer;Ljava/lang/Integer;Ljava/lang/Integer;TT;>;Lscala/reflect/ClassManifest<TT;>;)[[[[TT;;
const #247 = Asciz	(IIILscala/Function3;Lscala/reflect/ClassManifest;)[[Ljava/lang/Object;;
const #248 = Asciz	scala/Array$$anonfun$tabulate$2;
const #249 = class	#248;	//  scala/Array$$anonfun$tabulate$2
const #250 = Asciz	(IILscala/Function3;Lscala/reflect/ClassManifest;)V;
const #251 = NameAndType	#11:#250;//  "<init>":(IILscala/Function3;Lscala/reflect/ClassManifest;)V
const #252 = Method	#249.#251;	//  scala/Array$$anonfun$tabulate$2."<init>":(IILscala/Function3;Lscala/reflect/ClassManifest;)V
const #253 = Asciz	n2$5;
const #254 = Asciz	n3$4;
const #255 = Asciz	f$3;
const #256 = Asciz	evidence$16$1;
const #257 = Asciz	<T:Ljava/lang/Object;>(IIILscala/Function3<Ljava/lang/Integer;Ljava/lang/Integer;Ljava/lang/Integer;TT;>;Lscala/reflect/ClassManifest<TT;>;)[[[TT;;
const #258 = Asciz	(IILscala/Function2;Lscala/reflect/ClassManifest;)[Ljava/lang/Object;;
const #259 = Asciz	scala/Array$$anonfun$tabulate$1;
const #260 = class	#259;	//  scala/Array$$anonfun$tabulate$1
const #261 = Asciz	(ILscala/Function2;Lscala/reflect/ClassManifest;)V;
const #262 = NameAndType	#11:#261;//  "<init>":(ILscala/Function2;Lscala/reflect/ClassManifest;)V
const #263 = Method	#260.#262;	//  scala/Array$$anonfun$tabulate$1."<init>":(ILscala/Function2;Lscala/reflect/ClassManifest;)V
const #264 = Asciz	n2$6;
const #265 = Asciz	f$4;
const #266 = Asciz	evidence$15$1;
const #267 = Asciz	<T:Ljava/lang/Object;>(IILscala/Function2<Ljava/lang/Integer;Ljava/lang/Integer;TT;>;Lscala/reflect/ClassManifest<TT;>;)[[TT;;
const #268 = Asciz	evidence$14;
const #269 = Asciz	<T:Ljava/lang/Object;>(ILscala/Function1<Ljava/lang/Integer;TT;>;Lscala/reflect/ClassManifest<TT;>;)[TT;;
const #270 = Asciz	fill;
const #271 = Asciz	(IIIIILscala/Function0;Lscala/reflect/ClassManifest;)[[[[Ljava/lang/Object;;
const #272 = Asciz	scala/Array$$anonfun$fill$4;
const #273 = class	#272;	//  scala/Array$$anonfun$fill$4
const #274 = Asciz	(IIIILscala/Function0;Lscala/reflect/ClassManifest;)V;
const #275 = NameAndType	#11:#274;//  "<init>":(IIIILscala/Function0;Lscala/reflect/ClassManifest;)V
const #276 = Method	#273.#275;	//  scala/Array$$anonfun$fill$4."<init>":(IIIILscala/Function0;Lscala/reflect/ClassManifest;)V
const #277 = Asciz	n2$10;
const #278 = Asciz	n3$7;
const #279 = Asciz	n4$5;
const #280 = Asciz	n5$3;
const #281 = Asciz	elem$2;
const #282 = Asciz	Lscala/Function0;;
const #283 = Asciz	evidence$13$1;
const #284 = Asciz	<T:Ljava/lang/Object;>(IIIIILscala/Function0<TT;>;Lscala/reflect/ClassManifest<TT;>;)[[[[[TT;;
const #285 = Asciz	(IIIILscala/Function0;Lscala/reflect/ClassManifest;)[[[Ljava/lang/Object;;
const #286 = Asciz	scala/Array$$anonfun$fill$3;
const #287 = class	#286;	//  scala/Array$$anonfun$fill$3
const #288 = Asciz	(IIILscala/Function0;Lscala/reflect/ClassManifest;)V;
const #289 = NameAndType	#11:#288;//  "<init>":(IIILscala/Function0;Lscala/reflect/ClassManifest;)V
const #290 = Method	#287.#289;	//  scala/Array$$anonfun$fill$3."<init>":(IIILscala/Function0;Lscala/reflect/ClassManifest;)V
const #291 = Asciz	n2$11;
const #292 = Asciz	n3$8;
const #293 = Asciz	n4$6;
const #294 = Asciz	elem$3;
const #295 = Asciz	evidence$12$1;
const #296 = Asciz	<T:Ljava/lang/Object;>(IIIILscala/Function0<TT;>;Lscala/reflect/ClassManifest<TT;>;)[[[[TT;;
const #297 = Asciz	(IIILscala/Function0;Lscala/reflect/ClassManifest;)[[Ljava/lang/Object;;
const #298 = Asciz	scala/Array$$anonfun$fill$2;
const #299 = class	#298;	//  scala/Array$$anonfun$fill$2
const #300 = Asciz	(IILscala/Function0;Lscala/reflect/ClassManifest;)V;
const #301 = NameAndType	#11:#300;//  "<init>":(IILscala/Function0;Lscala/reflect/ClassManifest;)V
const #302 = Method	#299.#301;	//  scala/Array$$anonfun$fill$2."<init>":(IILscala/Function0;Lscala/reflect/ClassManifest;)V
const #303 = Asciz	n2$12;
const #304 = Asciz	n3$9;
const #305 = Asciz	elem$4;
const #306 = Asciz	evidence$11$1;
const #307 = Asciz	<T:Ljava/lang/Object;>(IIILscala/Function0<TT;>;Lscala/reflect/ClassManifest<TT;>;)[[[TT;;
const #308 = Asciz	(IILscala/Function0;Lscala/reflect/ClassManifest;)[Ljava/lang/Object;;
const #309 = Asciz	scala/Array$$anonfun$fill$1;
const #310 = class	#309;	//  scala/Array$$anonfun$fill$1
const #311 = Asciz	(ILscala/Function0;Lscala/reflect/ClassManifest;)V;
const #312 = NameAndType	#11:#311;//  "<init>":(ILscala/Function0;Lscala/reflect/ClassManifest;)V
const #313 = Method	#310.#312;	//  scala/Array$$anonfun$fill$1."<init>":(ILscala/Function0;Lscala/reflect/ClassManifest;)V
const #314 = Asciz	n2$9;
const #315 = Asciz	elem$1;
const #316 = Asciz	evidence$10$1;
const #317 = Asciz	<T:Ljava/lang/Object;>(IILscala/Function0<TT;>;Lscala/reflect/ClassManifest<TT;>;)[[TT;;
const #318 = Asciz	(ILscala/Function0;Lscala/reflect/ClassManifest;)Ljava/lang/Object;;
const #319 = Asciz	scala/Function0;
const #320 = class	#319;	//  scala/Function0
const #321 = NameAndType	#112:#183;//  apply:()Ljava/lang/Object;
const #322 = InterfaceMethod	#320.#321;	//  scala/Function0.apply:()Ljava/lang/Object;
const #323 = Asciz	evidence$9;
const #324 = Asciz	<T:Ljava/lang/Object;>(ILscala/Function0<TT;>;Lscala/reflect/ClassManifest<TT;>;)[TT;;
const #325 = Asciz	concat;
const #326 = Asciz	(Lscala/collection/Seq;Lscala/reflect/ClassManifest;)Ljava/lang/Object;;
const #327 = Asciz	newBuilder;
const #328 = Asciz	(Lscala/reflect/ClassManifest;)Lscala/collection/mutable/ArrayBuilder;;
const #329 = NameAndType	#327:#328;//  newBuilder:(Lscala/reflect/ClassManifest;)Lscala/collection/mutable/ArrayBuilder;
const #330 = Method	#10.#329;	//  scala/Array$.newBuilder:(Lscala/reflect/ClassManifest;)Lscala/collection/mutable/ArrayBuilder;
const #331 = Asciz	scala/Array$$anonfun$concat$1;
const #332 = class	#331;	//  scala/Array$$anonfun$concat$1
const #333 = Method	#332.#12;	//  scala/Array$$anonfun$concat$1."<init>":()V
const #334 = Asciz	scala/collection/Seq$;
const #335 = class	#334;	//  scala/collection/Seq$
const #336 = Asciz	Lscala/collection/Seq$;;
const #337 = NameAndType	#4:#336;//  MODULE$:Lscala/collection/Seq$;
const #338 = Field	#335.#337;	//  scala/collection/Seq$.MODULE$:Lscala/collection/Seq$;
const #339 = Asciz	canBuildFrom;
const #340 = Asciz	()Lscala/collection/generic/CanBuildFrom;;
const #341 = NameAndType	#339:#340;//  canBuildFrom:()Lscala/collection/generic/CanBuildFrom;
const #342 = Method	#335.#341;	//  scala/collection/Seq$.canBuildFrom:()Lscala/collection/generic/CanBuildFrom;
const #343 = Asciz	map;
const #344 = Asciz	(Lscala/Function1;Lscala/collection/generic/CanBuildFrom;)Ljava/lang/Object;;
const #345 = NameAndType	#343:#344;//  map:(Lscala/Function1;Lscala/collection/generic/CanBuildFrom;)Ljava/lang/Object;
const #346 = InterfaceMethod	#160.#345;	//  scala/collection/TraversableLike.map:(Lscala/Function1;Lscala/collection/generic/CanBuildFrom;)Ljava/lang/Object;
const #347 = Asciz	scala/math/Numeric$IntIsIntegral$;
const #348 = class	#347;	//  scala/math/Numeric$IntIsIntegral$
const #349 = Asciz	Lscala/math/Numeric$IntIsIntegral$;;
const #350 = NameAndType	#4:#349;//  MODULE$:Lscala/math/Numeric$IntIsIntegral$;
const #351 = Field	#348.#350;	//  scala/math/Numeric$IntIsIntegral$.MODULE$:Lscala/math/Numeric$IntIsIntegral$;
const #352 = Asciz	sum;
const #353 = Asciz	(Lscala/math/Numeric;)Ljava/lang/Object;;
const #354 = NameAndType	#352:#353;//  sum:(Lscala/math/Numeric;)Ljava/lang/Object;
const #355 = InterfaceMethod	#160.#354;	//  scala/collection/TraversableLike.sum:(Lscala/math/Numeric;)Ljava/lang/Object;
const #356 = Asciz	unboxToInt;
const #357 = Asciz	(Ljava/lang/Object;)I;
const #358 = NameAndType	#356:#357;//  unboxToInt:(Ljava/lang/Object;)I
const #359 = Method	#105.#358;	//  scala/runtime/BoxesRunTime.unboxToInt:(Ljava/lang/Object;)I
const #360 = Asciz	sizeHint;
const #361 = Asciz	(I)V;
const #362 = NameAndType	#360:#361;//  sizeHint:(I)V
const #363 = InterfaceMethod	#177.#362;	//  scala/collection/mutable/Builder.sizeHint:(I)V
const #364 = Asciz	scala/Array$$anonfun$concat$2;
const #365 = class	#364;	//  scala/Array$$anonfun$concat$2
const #366 = Asciz	(Lscala/collection/mutable/ArrayBuilder;)V;
const #367 = NameAndType	#11:#366;//  "<init>":(Lscala/collection/mutable/ArrayBuilder;)V
const #368 = Method	#365.#367;	//  scala/Array$$anonfun$concat$2."<init>":(Lscala/collection/mutable/ArrayBuilder;)V
const #369 = Asciz	scala/collection/IterableLike;
const #370 = class	#369;	//  scala/collection/IterableLike
const #371 = Asciz	foreach;
const #372 = Asciz	(Lscala/Function1;)V;
const #373 = NameAndType	#371:#372;//  foreach:(Lscala/Function1;)V
const #374 = InterfaceMethod	#370.#373;	//  scala/collection/IterableLike.foreach:(Lscala/Function1;)V
const #375 = Asciz	xss;
const #376 = Asciz	Lscala/collection/Seq;;
const #377 = Asciz	evidence$8;
const #378 = Asciz	b$1;
const #379 = Asciz	<T:Ljava/lang/Object;>(Lscala/collection/Seq<[TT;>;Lscala/reflect/ClassManifest<TT;>;)[TT;;
const #380 = Asciz	ofDim;
const #381 = Asciz	(IIIIILscala/reflect/ClassManifest;)[[[[Ljava/lang/Object;;
const #382 = Asciz	scala/Array$$anonfun$ofDim$4;
const #383 = class	#382;	//  scala/Array$$anonfun$ofDim$4
const #384 = Asciz	(IIIILscala/reflect/ClassManifest;)V;
const #385 = NameAndType	#11:#384;//  "<init>":(IIIILscala/reflect/ClassManifest;)V
const #386 = Method	#383.#385;	//  scala/Array$$anonfun$ofDim$4."<init>":(IIIILscala/reflect/ClassManifest;)V
const #387 = Asciz	n2$7;
const #388 = Asciz	n3$5;
const #389 = Asciz	n4$3;
const #390 = Asciz	n5$2;
const #391 = Asciz	evidence$7$1;
const #392 = Asciz	<T:Ljava/lang/Object;>(IIIIILscala/reflect/ClassManifest<TT;>;)[[[[[TT;;
const #393 = Asciz	(IIIILscala/reflect/ClassManifest;)[[[Ljava/lang/Object;;
const #394 = Asciz	scala/Array$$anonfun$ofDim$3;
const #395 = class	#394;	//  scala/Array$$anonfun$ofDim$3
const #396 = Asciz	(IIILscala/reflect/ClassManifest;)V;
const #397 = NameAndType	#11:#396;//  "<init>":(IIILscala/reflect/ClassManifest;)V
const #398 = Method	#395.#397;	//  scala/Array$$anonfun$ofDim$3."<init>":(IIILscala/reflect/ClassManifest;)V
const #399 = Asciz	n2$8;
const #400 = Asciz	n3$6;
const #401 = Asciz	n4$4;
const #402 = Asciz	evidence$6$1;
const #403 = Asciz	<T:Ljava/lang/Object;>(IIIILscala/reflect/ClassManifest<TT;>;)[[[[TT;;
const #404 = Asciz	(IIILscala/reflect/ClassManifest;)[[Ljava/lang/Object;;
const #405 = Asciz	scala/Array$$anonfun$ofDim$2;
const #406 = class	#405;	//  scala/Array$$anonfun$ofDim$2
const #407 = Asciz	(IILscala/reflect/ClassManifest;)V;
const #408 = NameAndType	#11:#407;//  "<init>":(IILscala/reflect/ClassManifest;)V
const #409 = Method	#406.#408;	//  scala/Array$$anonfun$ofDim$2."<init>":(IILscala/reflect/ClassManifest;)V
const #410 = Asciz	n2$2;
const #411 = Asciz	n3$1;
const #412 = Asciz	evidence$5$1;
const #413 = Asciz	<T:Ljava/lang/Object;>(IIILscala/reflect/ClassManifest<TT;>;)[[[TT;;
const #414 = Asciz	(IILscala/reflect/ClassManifest;)[Ljava/lang/Object;;
const #415 = Asciz	newArray2;
const #416 = Asciz	(I)[Ljava/lang/Object;;
const #417 = NameAndType	#415:#416;//  newArray2:(I)[Ljava/lang/Object;
const #418 = InterfaceMethod	#99.#417;	//  scala/reflect/ClassManifest.newArray2:(I)[Ljava/lang/Object;
const #419 = Asciz	intWrapper;
const #420 = Asciz	(I)Lscala/runtime/RichInt;;
const #421 = NameAndType	#419:#420;//  intWrapper:(I)Lscala/runtime/RichInt;
const #422 = Method	#151.#421;	//  scala/Predef$.intWrapper:(I)Lscala/runtime/RichInt;
const #423 = Asciz	scala/runtime/RichInt;
const #424 = class	#423;	//  scala/runtime/RichInt
const #425 = Asciz	until;
const #426 = Asciz	(I)Lscala/collection/immutable/Range;;
const #427 = NameAndType	#425:#426;//  until:(I)Lscala/collection/immutable/Range;
const #428 = Method	#424.#427;	//  scala/runtime/RichInt.until:(I)Lscala/collection/immutable/Range;
const #429 = Asciz	scala/collection/immutable/Range$ByOne;
const #430 = class	#429;	//  scala/collection/immutable/Range$ByOne
const #431 = Asciz	scala/Array$$anonfun$ofDim$1;
const #432 = class	#431;	//  scala/Array$$anonfun$ofDim$1
const #433 = Asciz	(ILscala/reflect/ClassManifest;[Ljava/lang/Object;)V;
const #434 = NameAndType	#11:#433;//  "<init>":(ILscala/reflect/ClassManifest;[Ljava/lang/Object;)V
const #435 = Method	#432.#434;	//  scala/Array$$anonfun$ofDim$1."<init>":(ILscala/reflect/ClassManifest;[Ljava/lang/Object;)V
const #436 = InterfaceMethod	#430.#373;	//  scala/collection/immutable/Range$ByOne.foreach:(Lscala/Function1;)V
const #437 = Asciz	n2$1;
const #438 = Asciz	evidence$4$1;
const #439 = Asciz	arr$1;
const #440 = Asciz	<T:Ljava/lang/Object;>(IILscala/reflect/ClassManifest<TT;>;)[[TT;;
const #441 = Asciz	(ILscala/reflect/ClassManifest;)Ljava/lang/Object;;
const #442 = Asciz	evidence$3;
const #443 = Asciz	<T:Ljava/lang/Object;>(ILscala/reflect/ClassManifest<TT;>;)[TT;;
const #444 = Asciz	(Lscala/runtime/BoxedUnit;Lscala/collection/Seq;)[Lscala/runtime/BoxedUnit;;
const #445 = Asciz	scala/collection/SeqLike;
const #446 = class	#445;	//  scala/collection/SeqLike
const #447 = Asciz	length;
const #448 = Asciz	()I;
const #449 = NameAndType	#447:#448;//  length:()I
const #450 = InterfaceMethod	#446.#449;	//  scala/collection/SeqLike.length:()I
const #451 = Asciz	scala/runtime/BoxedUnit;
const #452 = class	#451;	//  scala/runtime/BoxedUnit
const #453 = Asciz	scala/runtime/IntRef;
const #454 = class	#453;	//  scala/runtime/IntRef
const #455 = NameAndType	#11:#361;//  "<init>":(I)V
const #456 = Method	#454.#455;	//  scala/runtime/IntRef."<init>":(I)V
const #457 = Asciz	iterator;
const #458 = Asciz	()Lscala/collection/Iterator;;
const #459 = NameAndType	#457:#458;//  iterator:()Lscala/collection/Iterator;
const #460 = InterfaceMethod	#370.#459;	//  scala/collection/IterableLike.iterator:()Lscala/collection/Iterator;
const #461 = Asciz	scala/Array$$anonfun$apply$10;
const #462 = class	#461;	//  scala/Array$$anonfun$apply$10
const #463 = Asciz	([Lscala/runtime/BoxedUnit;Lscala/runtime/IntRef;)V;
const #464 = NameAndType	#11:#463;//  "<init>":([Lscala/runtime/BoxedUnit;Lscala/runtime/IntRef;)V
const #465 = Method	#462.#464;	//  scala/Array$$anonfun$apply$10."<init>":([Lscala/runtime/BoxedUnit;Lscala/runtime/IntRef;)V
const #466 = Asciz	scala/collection/Iterator;
const #467 = class	#466;	//  scala/collection/Iterator
const #468 = InterfaceMethod	#467.#373;	//  scala/collection/Iterator.foreach:(Lscala/Function1;)V
const #469 = Asciz	Lscala/runtime/BoxedUnit;;
const #470 = Asciz	xs;
const #471 = Asciz	array$10;
const #472 = Asciz	[Lscala/runtime/BoxedUnit;;
const #473 = Asciz	i$10;
const #474 = Asciz	Lscala/runtime/IntRef;;
const #475 = Asciz	(Lscala/runtime/BoxedUnit;Lscala/collection/Seq<Ljava/lang/Object;>;)[Lscala/runtime/BoxedUnit;;
const #476 = Asciz	(DLscala/collection/Seq;)[D;
const #477 = Asciz	scala/Array$$anonfun$apply$9;
const #478 = class	#477;	//  scala/Array$$anonfun$apply$9
const #479 = Asciz	([DLscala/runtime/IntRef;)V;
const #480 = NameAndType	#11:#479;//  "<init>":([DLscala/runtime/IntRef;)V
const #481 = Method	#478.#480;	//  scala/Array$$anonfun$apply$9."<init>":([DLscala/runtime/IntRef;)V
const #482 = Asciz	D;
const #483 = Asciz	array$9;
const #484 = Asciz	[D;
const #485 = Asciz	i$9;
const #486 = Asciz	(DLscala/collection/Seq<Ljava/lang/Double;>;)[D;
const #487 = Asciz	(FLscala/collection/Seq;)[F;
const #488 = Asciz	scala/Array$$anonfun$apply$8;
const #489 = class	#488;	//  scala/Array$$anonfun$apply$8
const #490 = Asciz	([FLscala/runtime/IntRef;)V;
const #491 = NameAndType	#11:#490;//  "<init>":([FLscala/runtime/IntRef;)V
const #492 = Method	#489.#491;	//  scala/Array$$anonfun$apply$8."<init>":([FLscala/runtime/IntRef;)V
const #493 = Asciz	F;
const #494 = Asciz	array$8;
const #495 = Asciz	[F;
const #496 = Asciz	i$8;
const #497 = Asciz	(FLscala/collection/Seq<Ljava/lang/Float;>;)[F;
const #498 = Asciz	(JLscala/collection/Seq;)[J;
const #499 = Asciz	scala/Array$$anonfun$apply$7;
const #500 = class	#499;	//  scala/Array$$anonfun$apply$7
const #501 = Asciz	([JLscala/runtime/IntRef;)V;
const #502 = NameAndType	#11:#501;//  "<init>":([JLscala/runtime/IntRef;)V
const #503 = Method	#500.#502;	//  scala/Array$$anonfun$apply$7."<init>":([JLscala/runtime/IntRef;)V
const #504 = Asciz	J;
const #505 = Asciz	array$7;
const #506 = Asciz	[J;
const #507 = Asciz	i$7;
const #508 = Asciz	(JLscala/collection/Seq<Ljava/lang/Long;>;)[J;
const #509 = Asciz	(ILscala/collection/Seq;)[I;
const #510 = Asciz	scala/Array$$anonfun$apply$6;
const #511 = class	#510;	//  scala/Array$$anonfun$apply$6
const #512 = Asciz	([ILscala/runtime/IntRef;)V;
const #513 = NameAndType	#11:#512;//  "<init>":([ILscala/runtime/IntRef;)V
const #514 = Method	#511.#513;	//  scala/Array$$anonfun$apply$6."<init>":([ILscala/runtime/IntRef;)V
const #515 = Asciz	array$6;
const #516 = Asciz	i$6;
const #517 = Asciz	(ILscala/collection/Seq<Ljava/lang/Integer;>;)[I;
const #518 = Asciz	(CLscala/collection/Seq;)[C;
const #519 = Asciz	scala/Array$$anonfun$apply$5;
const #520 = class	#519;	//  scala/Array$$anonfun$apply$5
const #521 = Asciz	([CLscala/runtime/IntRef;)V;
const #522 = NameAndType	#11:#521;//  "<init>":([CLscala/runtime/IntRef;)V
const #523 = Method	#520.#522;	//  scala/Array$$anonfun$apply$5."<init>":([CLscala/runtime/IntRef;)V
const #524 = Asciz	C;
const #525 = Asciz	array$5;
const #526 = Asciz	[C;
const #527 = Asciz	i$5;
const #528 = Asciz	(CLscala/collection/Seq<Ljava/lang/Character;>;)[C;
const #529 = Asciz	(SLscala/collection/Seq;)[S;
const #530 = Asciz	scala/Array$$anonfun$apply$4;
const #531 = class	#530;	//  scala/Array$$anonfun$apply$4
const #532 = Asciz	([SLscala/runtime/IntRef;)V;
const #533 = NameAndType	#11:#532;//  "<init>":([SLscala/runtime/IntRef;)V
const #534 = Method	#531.#533;	//  scala/Array$$anonfun$apply$4."<init>":([SLscala/runtime/IntRef;)V
const #535 = Asciz	S;
const #536 = Asciz	array$4;
const #537 = Asciz	[S;
const #538 = Asciz	i$4;
const #539 = Asciz	(SLscala/collection/Seq<Ljava/lang/Short;>;)[S;
const #540 = Asciz	(BLscala/collection/Seq;)[B;
const #541 = Asciz	scala/Array$$anonfun$apply$3;
const #542 = class	#541;	//  scala/Array$$anonfun$apply$3
const #543 = Asciz	([BLscala/runtime/IntRef;)V;
const #544 = NameAndType	#11:#543;//  "<init>":([BLscala/runtime/IntRef;)V
const #545 = Method	#542.#544;	//  scala/Array$$anonfun$apply$3."<init>":([BLscala/runtime/IntRef;)V
const #546 = Asciz	B;
const #547 = Asciz	array$3;
const #548 = Asciz	[B;
const #549 = Asciz	i$3;
const #550 = Asciz	(BLscala/collection/Seq<Ljava/lang/Byte;>;)[B;
const #551 = Asciz	(ZLscala/collection/Seq;)[Z;
const #552 = Asciz	scala/Array$$anonfun$apply$2;
const #553 = class	#552;	//  scala/Array$$anonfun$apply$2
const #554 = Asciz	([ZLscala/runtime/IntRef;)V;
const #555 = NameAndType	#11:#554;//  "<init>":([ZLscala/runtime/IntRef;)V
const #556 = Method	#553.#555;	//  scala/Array$$anonfun$apply$2."<init>":([ZLscala/runtime/IntRef;)V
const #557 = Asciz	Z;
const #558 = Asciz	array$2;
const #559 = Asciz	[Z;
const #560 = Asciz	i$2;
const #561 = Asciz	(ZLscala/collection/Seq<Ljava/lang/Boolean;>;)[Z;
const #562 = Asciz	scala/Array$$anonfun$apply$1;
const #563 = class	#562;	//  scala/Array$$anonfun$apply$1
const #564 = Asciz	(Ljava/lang/Object;Lscala/runtime/IntRef;)V;
const #565 = NameAndType	#11:#564;//  "<init>":(Ljava/lang/Object;Lscala/runtime/IntRef;)V
const #566 = Method	#563.#565;	//  scala/Array$$anonfun$apply$1."<init>":(Ljava/lang/Object;Lscala/runtime/IntRef;)V
const #567 = Asciz	evidence$2;
const #568 = Asciz	array$1;
const #569 = Asciz	i$1;
const #570 = Asciz	<T:Ljava/lang/Object;>(Lscala/collection/Seq<TT;>;Lscala/reflect/ClassManifest<TT;>;)[TT;;
const #571 = Asciz	empty;
const #572 = Asciz	(Lscala/reflect/ClassManifest;)Ljava/lang/Object;;
const #573 = Asciz	evidence$1;
const #574 = Asciz	<T:Ljava/lang/Object;>(Lscala/reflect/ClassManifest<TT;>;)[TT;;
const #575 = Asciz	copy;
const #576 = Asciz	(Ljava/lang/Object;ILjava/lang/Object;II)V;
const #577 = Asciz	getClass;
const #578 = Asciz	()Ljava/lang/Class;;
const #579 = NameAndType	#577:#578;//  getClass:()Ljava/lang/Class;
const #580 = Method	#138.#579;	//  java/lang/Object.getClass:()Ljava/lang/Class;
const #581 = Asciz	java/lang/Class;
const #582 = class	#581;	//  java/lang/Class
const #583 = Asciz	isArray;
const #584 = Asciz	()Z;
const #585 = NameAndType	#583:#584;//  isArray:()Z
const #586 = Method	#582.#585;	//  java/lang/Class.isArray:()Z
const #587 = Asciz	isAssignableFrom;
const #588 = Asciz	(Ljava/lang/Class;)Z;
const #589 = NameAndType	#587:#588;//  isAssignableFrom:(Ljava/lang/Class;)Z
const #590 = Method	#582.#589;	//  java/lang/Class.isAssignableFrom:(Ljava/lang/Class;)Z
const #591 = Asciz	java/lang/System;
const #592 = class	#591;	//  java/lang/System
const #593 = Asciz	arraycopy;
const #594 = NameAndType	#593:#576;//  arraycopy:(Ljava/lang/Object;ILjava/lang/Object;II)V
const #595 = Method	#592.#594;	//  java/lang/System.arraycopy:(Ljava/lang/Object;ILjava/lang/Object;II)V
const #596 = Asciz	slowcopy;
const #597 = NameAndType	#596:#576;//  slowcopy:(Ljava/lang/Object;ILjava/lang/Object;II)V
const #598 = Method	#10.#597;	//  scala/Array$.slowcopy:(Ljava/lang/Object;ILjava/lang/Object;II)V
const #599 = Asciz	src;
const #600 = Asciz	srcPos;
const #601 = Asciz	dest;
const #602 = Asciz	destPos;
const #603 = Asciz	srcClass;
const #604 = Asciz	Ljava/lang/Class;;
const #605 = Asciz	get;
const #606 = Asciz	(Ljava/lang/Object;I)Ljava/lang/Object;;
const #607 = NameAndType	#605:#606;//  get:(Ljava/lang/Object;I)Ljava/lang/Object;
const #608 = Method	#117.#607;	//  java/lang/reflect/Array.get:(Ljava/lang/Object;I)Ljava/lang/Object;
const #609 = Asciz	scala/collection/mutable/ArrayBuilder$;
const #610 = class	#609;	//  scala/collection/mutable/ArrayBuilder$
const #611 = Asciz	Lscala/collection/mutable/ArrayBuilder$;;
const #612 = NameAndType	#4:#611;//  MODULE$:Lscala/collection/mutable/ArrayBuilder$;
const #613 = Field	#610.#612;	//  scala/collection/mutable/ArrayBuilder$.MODULE$:Lscala/collection/mutable/ArrayBuilder$;
const #614 = NameAndType	#130:#328;//  make:(Lscala/reflect/ClassManifest;)Lscala/collection/mutable/ArrayBuilder;
const #615 = Method	#610.#614;	//  scala/collection/mutable/ArrayBuilder$.make:(Lscala/reflect/ClassManifest;)Lscala/collection/mutable/ArrayBuilder;
const #616 = Asciz	m;
const #617 = Asciz	<T:Ljava/lang/Object;>(Lscala/reflect/ClassManifest<TT;>;)Lscala/collection/mutable/ArrayBuilder<TT;>;;
const #618 = Asciz	(Lscala/reflect/ClassManifest;)Lscala/collection/generic/CanBuildFrom;;
const #619 = Asciz	scala/Array$$anon$2;
const #620 = class	#619;	//  scala/Array$$anon$2
const #621 = Asciz	(Lscala/reflect/ClassManifest;)V;
const #622 = NameAndType	#11:#621;//  "<init>":(Lscala/reflect/ClassManifest;)V
const #623 = Method	#620.#622;	//  scala/Array$$anon$2."<init>":(Lscala/reflect/ClassManifest;)V
const #624 = Asciz	m$1;
const #625 = Asciz	<T:Ljava/lang/Object;>(Lscala/reflect/ClassManifest<TT;>;)Lscala/collection/generic/CanBuildFrom<[Ljava/lang/Object;TT;[TT;>;;
const #626 = Asciz	InnerClasses;
const #627 = Asciz	scala/collection/immutable/Range;
const #628 = class	#627;	//  scala/collection/immutable/Range
const #629 = Asciz	ByOne;
const #630 = Asciz	scala/Array;
const #631 = class	#630;	//  scala/Array
const #632 = Asciz	$anon$2;
const #633 = Asciz	$anonfun$fill$1;
const #634 = Asciz	$anonfun$fill$2;
const #635 = Asciz	$anonfun$fill$3;
const #636 = Asciz	$anonfun$fill$4;
const #637 = Asciz	$anonfun$apply$1;
const #638 = Asciz	$anonfun$apply$2;
const #639 = Asciz	$anonfun$apply$3;
const #640 = Asciz	$anonfun$apply$4;
const #641 = Asciz	$anonfun$apply$5;
const #642 = Asciz	$anonfun$apply$6;
const #643 = Asciz	$anonfun$apply$7;
const #644 = Asciz	$anonfun$apply$8;
const #645 = Asciz	$anonfun$apply$9;
const #646 = Asciz	$anonfun$ofDim$1;
const #647 = Asciz	$anonfun$ofDim$2;
const #648 = Asciz	$anonfun$ofDim$3;
const #649 = Asciz	$anonfun$ofDim$4;
const #650 = Asciz	$anonfun$apply$10;
const #651 = Asciz	$anonfun$concat$2;
const #652 = Asciz	$anonfun$concat$1;
const #653 = Asciz	$anonfun$tabulate$1;
const #654 = Asciz	$anonfun$tabulate$2;
const #655 = Asciz	$anonfun$tabulate$3;
const #656 = Asciz	$anonfun$tabulate$4;
const #657 = Asciz	$anonfun$fromFunction$1;
const #658 = Asciz	$anonfun$fromFunction$2;
const #659 = Asciz	$anonfun$fromFunction$3;
const #660 = Asciz	$anonfun$fromFunction$4;
const #661 = Asciz	scala/ScalaObject;
const #662 = class	#661;	//  scala/ScalaObject

{
public static final scala.Array$ MODULE$;

public static {};
  Code:
   Stack=1, Locals=0, Args_size=0
   0:	new	#10; //class scala/Array$
   3:	invokespecial	#13; //Method "<init>":()V
   6:	return

public java.lang.Object[][][][] fromFunction(scala.Function5, int, int, int, int, int, scala.reflect.ClassManifest);
  Code:
   Stack=9, Locals=8, Args_size=8
   0:	aload_0
   1:	new	#23; //class scala/Array$$anonfun$fromFunction$4
   4:	dup
   5:	aload_1
   6:	iload_3
   7:	iload	4
   9:	iload	5
   11:	iload	6
   13:	aload	7
   15:	invokespecial	#26; //Method scala/Array$$anonfun$fromFunction$4."<init>":(Lscala/Function5;IIIILscala/reflect/ClassManifest;)V
   18:	iload_2
   19:	getstatic	#31; //Field scala/reflect/ClassManifest$.MODULE$:Lscala/reflect/ClassManifest$;
   22:	getstatic	#31; //Field scala/reflect/ClassManifest$.MODULE$:Lscala/reflect/ClassManifest$;
   25:	getstatic	#31; //Field scala/reflect/ClassManifest$.MODULE$:Lscala/reflect/ClassManifest$;
   28:	getstatic	#31; //Field scala/reflect/ClassManifest$.MODULE$:Lscala/reflect/ClassManifest$;
   31:	aload	7
   33:	invokevirtual	#35; //Method scala/reflect/ClassManifest$.arrayType:(Lscala/reflect/OptManifest;)Lscala/reflect/ClassManifest;
   36:	invokevirtual	#35; //Method scala/reflect/ClassManifest$.arrayType:(Lscala/reflect/OptManifest;)Lscala/reflect/ClassManifest;
   39:	invokevirtual	#35; //Method scala/reflect/ClassManifest$.arrayType:(Lscala/reflect/OptManifest;)Lscala/reflect/ClassManifest;
   42:	invokevirtual	#35; //Method scala/reflect/ClassManifest$.arrayType:(Lscala/reflect/OptManifest;)Lscala/reflect/ClassManifest;
   45:	invokevirtual	#38; //Method fromFunction:(Lscala/Function1;ILscala/reflect/ClassManifest;)Ljava/lang/Object;
   48:	checkcast	#40; //class "[[[[Ljava/lang/Object;"
   51:	areturn
  LineNumberTable: 
   line 437: 0

  LocalVariableTable: 
   Start  Length  Slot  Name   Signature
   0      52      0    this       Lscala/Array$;
   0      52      1    f$6       Lscala/Function5;
   0      52      2    n1       I
   0      52      3    n2$14       I
   0      52      4    n3$10       I
   0      52      5    n4$7       I
   0      52      6    n5$4       I
   0      52      7    evidence$25$1       Lscala/reflect/ClassManifest;

  Signature: length = 0x2
   00 35 
  Deprecated: true

public java.lang.Object[][][] fromFunction(scala.Function4, int, int, int, int, scala.reflect.ClassManifest);
  Code:
   Stack=8, Locals=7, Args_size=7
   0:	aload_0
   1:	new	#58; //class scala/Array$$anonfun$fromFunction$3
   4:	dup
   5:	aload_1
   6:	iload_3
   7:	iload	4
   9:	iload	5
   11:	aload	6
   13:	invokespecial	#61; //Method scala/Array$$anonfun$fromFunction$3."<init>":(Lscala/Function4;IIILscala/reflect/ClassManifest;)V
   16:	iload_2
   17:	getstatic	#31; //Field scala/reflect/ClassManifest$.MODULE$:Lscala/reflect/ClassManifest$;
   20:	getstatic	#31; //Field scala/reflect/ClassManifest$.MODULE$:Lscala/reflect/ClassManifest$;
   23:	getstatic	#31; //Field scala/reflect/ClassManifest$.MODULE$:Lscala/reflect/ClassManifest$;
   26:	aload	6
   28:	invokevirtual	#35; //Method scala/reflect/ClassManifest$.arrayType:(Lscala/reflect/OptManifest;)Lscala/reflect/ClassManifest;
   31:	invokevirtual	#35; //Method scala/reflect/ClassManifest$.arrayType:(Lscala/reflect/OptManifest;)Lscala/reflect/ClassManifest;
   34:	invokevirtual	#35; //Method scala/reflect/ClassManifest$.arrayType:(Lscala/reflect/OptManifest;)Lscala/reflect/ClassManifest;
   37:	invokevirtual	#38; //Method fromFunction:(Lscala/Function1;ILscala/reflect/ClassManifest;)Ljava/lang/Object;
   40:	checkcast	#63; //class "[[[Ljava/lang/Object;"
   43:	areturn
  LineNumberTable: 
   line 430: 0

  LocalVariableTable: 
   Start  Length  Slot  Name   Signature
   0      44      0    this       Lscala/Array$;
   0      44      1    f$7       Lscala/Function4;
   0      44      2    n1       I
   0      44      3    n2$15       I
   0      44      4    n3$11       I
   0      44      5    n4$8       I
   0      44      6    evidence$24$1       Lscala/reflect/ClassManifest;

  Signature: length = 0x2
   00 46 
  Deprecated: true

public java.lang.Object[][] fromFunction(scala.Function3, int, int, int, scala.reflect.ClassManifest);
  Code:
   Stack=7, Locals=6, Args_size=6
   0:	aload_0
   1:	new	#73; //class scala/Array$$anonfun$fromFunction$2
   4:	dup
   5:	aload_1
   6:	iload_3
   7:	iload	4
   9:	aload	5
   11:	invokespecial	#76; //Method scala/Array$$anonfun$fromFunction$2."<init>":(Lscala/Function3;IILscala/reflect/ClassManifest;)V
   14:	iload_2
   15:	getstatic	#31; //Field scala/reflect/ClassManifest$.MODULE$:Lscala/reflect/ClassManifest$;
   18:	getstatic	#31; //Field scala/reflect/ClassManifest$.MODULE$:Lscala/reflect/ClassManifest$;
   21:	aload	5
   23:	invokevirtual	#35; //Method scala/reflect/ClassManifest$.arrayType:(Lscala/reflect/OptManifest;)Lscala/reflect/ClassManifest;
   26:	invokevirtual	#35; //Method scala/reflect/ClassManifest$.arrayType:(Lscala/reflect/OptManifest;)Lscala/reflect/ClassManifest;
   29:	invokevirtual	#38; //Method fromFunction:(Lscala/Function1;ILscala/reflect/ClassManifest;)Ljava/lang/Object;
   32:	checkcast	#78; //class "[[Ljava/lang/Object;"
   35:	areturn
  LineNumberTable: 
   line 423: 0

  LocalVariableTable: 
   Start  Length  Slot  Name   Signature
   0      36      0    this       Lscala/Array$;
   0      36      1    f$8       Lscala/Function3;
   0      36      2    n1       I
   0      36      3    n2$16       I
   0      36      4    n3$12       I
   0      36      5    evidence$23$1       Lscala/reflect/ClassManifest;

  Signature: length = 0x2
   00 54 
  Deprecated: true

public java.lang.Object[] fromFunction(scala.Function2, int, int, scala.reflect.ClassManifest);
  Code:
   Stack=6, Locals=5, Args_size=5
   0:	aload_0
   1:	new	#87; //class scala/Array$$anonfun$fromFunction$1
   4:	dup
   5:	aload_1
   6:	iload_3
   7:	aload	4
   9:	invokespecial	#90; //Method scala/Array$$anonfun$fromFunction$1."<init>":(Lscala/Function2;ILscala/reflect/ClassManifest;)V
   12:	iload_2
   13:	getstatic	#31; //Field scala/reflect/ClassManifest$.MODULE$:Lscala/reflect/ClassManifest$;
   16:	aload	4
   18:	invokevirtual	#35; //Method scala/reflect/ClassManifest$.arrayType:(Lscala/reflect/OptManifest;)Lscala/reflect/ClassManifest;
   21:	invokevirtual	#38; //Method fromFunction:(Lscala/Function1;ILscala/reflect/ClassManifest;)Ljava/lang/Object;
   24:	checkcast	#92; //class "[Ljava/lang/Object;"
   27:	areturn
  LineNumberTable: 
   line 416: 0

  LocalVariableTable: 
   Start  Length  Slot  Name   Signature
   0      28      0    this       Lscala/Array$;
   0      28      1    f$5       Lscala/Function2;
   0      28      2    n1       I
   0      28      3    n2$13       I
   0      28      4    evidence$22$1       Lscala/reflect/ClassManifest;

  Signature: length = 0x2
   00 61 
  Deprecated: true

public java.lang.Object fromFunction(scala.Function1, int, scala.reflect.ClassManifest);
  Code:
   Stack=3, Locals=7, Args_size=4
   0:	aload_3
   1:	iload_2
   2:	invokeinterface	#103,  2; //InterfaceMethod scala/reflect/ClassManifest.newArray:(I)Ljava/lang/Object;
   7:	astore	6
   9:	iconst_0
   10:	istore	5
   12:	iload	5
   14:	iload_2
   15:	if_icmpge	49
   18:	aload_1
   19:	iload	5
   21:	invokestatic	#109; //Method scala/runtime/BoxesRunTime.boxToInteger:(I)Ljava/lang/Integer;
   24:	invokeinterface	#115,  2; //InterfaceMethod scala/Function1.apply:(Ljava/lang/Object;)Ljava/lang/Object;
   29:	astore	4
   31:	aload	6
   33:	iload	5
   35:	aload	4
   37:	invokestatic	#121; //Method java/lang/reflect/Array.set:(Ljava/lang/Object;ILjava/lang/Object;)V
   40:	iload	5
   42:	iconst_1
   43:	iadd
   44:	istore	5
   46:	goto	12
   49:	aload	6
   51:	areturn
  LineNumberTable: 
   line 402: 0
   line 403: 9
   line 404: 12
   line 405: 18
   line 406: 40
   line 408: 49

  LocalVariableTable: 
   Start  Length  Slot  Name   Signature
   0      52      0    this       Lscala/Array$;
   0      52      1    f       Lscala/Function1;
   0      52      2    n       I
   0      52      3    evidence$21       Lscala/reflect/ClassManifest;
   12      39      5    i       I
   9      42      6    a       Ljava/lang/Object;

  Signature: length = 0x2
   00 FFFFFF81 
  Deprecated: true

public java.lang.Object make(int, java.lang.Object, scala.reflect.ClassManifest);
  Code:
   Stack=3, Locals=6, Args_size=4
   0:	aload_3
   1:	iload_1
   2:	invokeinterface	#103,  2; //InterfaceMethod scala/reflect/ClassManifest.newArray:(I)Ljava/lang/Object;
   7:	astore	5
   9:	iconst_0
   10:	istore	4
   12:	iload	4
   14:	iload_1
   15:	if_icmpge	35
   18:	aload	5
   20:	iload	4
   22:	aload_2
   23:	invokestatic	#121; //Method java/lang/reflect/Array.set:(Ljava/lang/Object;ILjava/lang/Object;)V
   26:	iload	4
   28:	iconst_1
   29:	iadd
   30:	istore	4
   32:	goto	12
   35:	aload	5
   37:	areturn
  LineNumberTable: 
   line 388: 0
   line 389: 9
   line 390: 12
   line 391: 18
   line 392: 26
   line 394: 35

  LocalVariableTable: 
   Start  Length  Slot  Name   Signature
   0      38      0    this       Lscala/Array$;
   0      38      1    n       I
   0      38      2    elem       Ljava/lang/Object;
   0      38      3    evidence$20       Lscala/reflect/ClassManifest;
   12      25      4    i       I
   9      28      5    a       Ljava/lang/Object;

  Signature: length = 0x2
   00 FFFFFF86 
  Deprecated: true

public scala.Option unapplySeq(java.lang.Object);
  Code:
   Stack=4, Locals=2, Args_size=2
   0:	aload_1
   1:	dup
   2:	pop
   3:	ifnull	14
   6:	aload_1
   7:	aconst_null
   8:	invokevirtual	#142; //Method java/lang/Object.equals:(Ljava/lang/Object;)Z
   11:	ifeq	20
   14:	getstatic	#147; //Field scala/None$.MODULE$:Lscala/None$;
   17:	goto	39
   20:	new	#149; //class scala/Some
   23:	dup
   24:	getstatic	#154; //Field scala/Predef$.MODULE$:Lscala/Predef$;
   27:	aload_1
   28:	invokevirtual	#158; //Method scala/Predef$.genericArrayOps:(Ljava/lang/Object;)Lscala/collection/mutable/ArrayOps;
   31:	invokeinterface	#164,  1; //InterfaceMethod scala/collection/TraversableLike.toIndexedSeq:()Lscala/collection/mutable/IndexedSeq;
   36:	invokespecial	#167; //Method scala/Some."<init>":(Ljava/lang/Object;)V
   39:	areturn
  LineNumberTable: 
   line 376: 0

  LocalVariableTable: 
   Start  Length  Slot  Name   Signature
   0      40      0    this       Lscala/Array$;
   0      40      1    x       Ljava/lang/Object;

  Signature: length = 0x2
   00 FFFFFFA9 

public java.lang.Object iterate(java.lang.Object, int, scala.Function1, scala.reflect.ClassManifest);
  Code:
   Stack=2, Locals=8, Args_size=5
   0:	aload	4
   2:	checkcast	#99; //class scala/reflect/ClassManifest
   5:	invokeinterface	#175,  1; //InterfaceMethod scala/reflect/ClassManifest.newArrayBuilder:()Lscala/collection/mutable/ArrayBuilder;
   10:	astore	7
   12:	aload_1
   13:	astore	5
   15:	iconst_0
   16:	istore	6
   18:	iload	6
   20:	iload_2
   21:	if_icmpge	53
   24:	aload	7
   26:	aload	5
   28:	invokeinterface	#181,  2; //InterfaceMethod scala/collection/mutable/Builder.$plus$eq:(Ljava/lang/Object;)Lscala/collection/mutable/Builder;
   33:	pop
   34:	aload_3
   35:	aload	5
   37:	invokeinterface	#115,  2; //InterfaceMethod scala/Function1.apply:(Ljava/lang/Object;)Ljava/lang/Object;
   42:	astore	5
   44:	iload	6
   46:	iconst_1
   47:	iadd
   48:	istore	6
   50:	goto	18
   53:	aload	7
   55:	invokeinterface	#185,  1; //InterfaceMethod scala/collection/mutable/Builder.result:()Ljava/lang/Object;
   60:	areturn
  LineNumberTable: 
   line 359: 0
   line 360: 12
   line 361: 15
   line 362: 18
   line 363: 24
   line 364: 34
   line 365: 44
   line 367: 53

  LocalVariableTable: 
   Start  Length  Slot  Name   Signature
   0      61      0    this       Lscala/Array$;
   0      61      1    start       Ljava/lang/Object;
   0      61      2    len       I
   0      61      3    f       Lscala/Function1;
   0      61      4    evidence$19       Lscala/reflect/ClassManifest;
   15      45      5    acc       Ljava/lang/Object;
   18      42      6    i       I
   12      48      7    b       Lscala/collection/mutable/ArrayBuilder;

  Signature: length = 0x2
   00 FFFFFFC0 

public int[] range(int, int, int);
  Code:
   Stack=3, Locals=7, Args_size=4
   0:	iload_3
   1:	iconst_0
   2:	if_icmpne	15
   5:	new	#196; //class java/lang/IllegalArgumentException
   8:	dup
   9:	ldc	#198; //String zero step
   11:	invokespecial	#201; //Method java/lang/IllegalArgumentException."<init>":(Ljava/lang/String;)V
   14:	athrow
   15:	getstatic	#206; //Field scala/reflect/Manifest$.MODULE$:Lscala/reflect/Manifest$;
   18:	invokevirtual	#210; //Method scala/reflect/Manifest$.Int:()Lscala/reflect/AnyValManifest;
   21:	astore	4
   23:	aload	4
   25:	checkcast	#99; //class scala/reflect/ClassManifest
   28:	invokeinterface	#175,  1; //InterfaceMethod scala/reflect/ClassManifest.newArrayBuilder:()Lscala/collection/mutable/ArrayBuilder;
   33:	astore	6
   35:	iload_1
   36:	istore	5
   38:	iload_3
   39:	iconst_0
   40:	if_icmpge	57
   43:	iload_2
   44:	iload	5
   46:	if_icmpge	53
   49:	iconst_1
   50:	goto	68
   53:	iconst_0
   54:	goto	68
   57:	iload	5
   59:	iload_2
   60:	if_icmpge	67
   63:	iconst_1
   64:	goto	68
   67:	iconst_0
   68:	ifeq	93
   71:	aload	6
   73:	iload	5
   75:	invokestatic	#109; //Method scala/runtime/BoxesRunTime.boxToInteger:(I)Ljava/lang/Integer;
   78:	invokeinterface	#181,  2; //InterfaceMethod scala/collection/mutable/Builder.$plus$eq:(Ljava/lang/Object;)Lscala/collection/mutable/Builder;
   83:	pop
   84:	iload	5
   86:	iload_3
   87:	iadd
   88:	istore	5
   90:	goto	38
   93:	aload	6
   95:	invokeinterface	#185,  1; //InterfaceMethod scala/collection/mutable/Builder.result:()Ljava/lang/Object;
   100:	checkcast	#212; //class "[I"
   103:	areturn
  LineNumberTable: 
   line 341: 0
   line 342: 15
   line 343: 35
   line 344: 38
   line 345: 71
   line 346: 84
   line 348: 93

  LocalVariableTable: 
   Start  Length  Slot  Name   Signature
   0      104      0    this       Lscala/Array$;
   0      104      1    start       I
   0      104      2    end       I
   0      104      3    step       I
   38      65      5    i       I
   35      68      6    b       Lscala/collection/mutable/ArrayBuilder;


public int[] range(int, int);
  Code:
   Stack=4, Locals=3, Args_size=3
   0:	aload_0
   1:	iload_1
   2:	iload_2
   3:	iconst_1
   4:	invokevirtual	#217; //Method range:(III)[I
   7:	areturn
  LineNumberTable: 
   line 331: 0

  LocalVariableTable: 
   Start  Length  Slot  Name   Signature
   0      8      0    this       Lscala/Array$;
   0      8      1    start       I
   0      8      2    end       I


public java.lang.Object[][][][] tabulate(int, int, int, int, int, scala.Function5, scala.reflect.ClassManifest);
  Code:
   Stack=10, Locals=8, Args_size=8
   0:	aload_0
   1:	iload_1
   2:	new	#221; //class scala/Array$$anonfun$tabulate$4
   5:	dup
   6:	iload_2
   7:	iload_3
   8:	iload	4
   10:	iload	5
   12:	aload	6
   14:	aload	7
   16:	invokespecial	#224; //Method scala/Array$$anonfun$tabulate$4."<init>":(IIIILscala/Function5;Lscala/reflect/ClassManifest;)V
   19:	getstatic	#31; //Field scala/reflect/ClassManifest$.MODULE$:Lscala/reflect/ClassManifest$;
   22:	getstatic	#31; //Field scala/reflect/ClassManifest$.MODULE$:Lscala/reflect/ClassManifest$;
   25:	getstatic	#31; //Field scala/reflect/ClassManifest$.MODULE$:Lscala/reflect/ClassManifest$;
   28:	getstatic	#31; //Field scala/reflect/ClassManifest$.MODULE$:Lscala/reflect/ClassManifest$;
   31:	aload	7
   33:	invokevirtual	#35; //Method scala/reflect/ClassManifest$.arrayType:(Lscala/reflect/OptManifest;)Lscala/reflect/ClassManifest;
   36:	invokevirtual	#35; //Method scala/reflect/ClassManifest$.arrayType:(Lscala/reflect/OptManifest;)Lscala/reflect/ClassManifest;
   39:	invokevirtual	#35; //Method scala/reflect/ClassManifest$.arrayType:(Lscala/reflect/OptManifest;)Lscala/reflect/ClassManifest;
   42:	invokevirtual	#35; //Method scala/reflect/ClassManifest$.arrayType:(Lscala/reflect/OptManifest;)Lscala/reflect/ClassManifest;
   45:	invokevirtual	#227; //Method tabulate:(ILscala/Function1;Lscala/reflect/ClassManifest;)Ljava/lang/Object;
   48:	checkcast	#40; //class "[[[[Ljava/lang/Object;"
   51:	areturn
  LineNumberTable: 
   line 322: 0

  LocalVariableTable: 
   Start  Length  Slot  Name   Signature
   0      52      0    this       Lscala/Array$;
   0      52      1    n1       I
   0      52      2    n2$3       I
   0      52      3    n3$2       I
   0      52      4    n4$1       I
   0      52      5    n5$1       I
   0      52      6    f$1       Lscala/Function5;
   0      52      7    evidence$18$1       Lscala/reflect/ClassManifest;

  Signature: length = 0x2
   00 FFFFFFEA 

public java.lang.Object[][][] tabulate(int, int, int, int, scala.Function4, scala.reflect.ClassManifest);
  Code:
   Stack=9, Locals=7, Args_size=7
   0:	aload_0
   1:	iload_1
   2:	new	#237; //class scala/Array$$anonfun$tabulate$3
   5:	dup
   6:	iload_2
   7:	iload_3
   8:	iload	4
   10:	aload	5
   12:	aload	6
   14:	invokespecial	#240; //Method scala/Array$$anonfun$tabulate$3."<init>":(IIILscala/Function4;Lscala/reflect/ClassManifest;)V
   17:	getstatic	#31; //Field scala/reflect/ClassManifest$.MODULE$:Lscala/reflect/ClassManifest$;
   20:	getstatic	#31; //Field scala/reflect/ClassManifest$.MODULE$:Lscala/reflect/ClassManifest$;
   23:	getstatic	#31; //Field scala/reflect/ClassManifest$.MODULE$:Lscala/reflect/ClassManifest$;
   26:	aload	6
   28:	invokevirtual	#35; //Method scala/reflect/ClassManifest$.arrayType:(Lscala/reflect/OptManifest;)Lscala/reflect/ClassManifest;
   31:	invokevirtual	#35; //Method scala/reflect/ClassManifest$.arrayType:(Lscala/reflect/OptManifest;)Lscala/reflect/ClassManifest;
   34:	invokevirtual	#35; //Method scala/reflect/ClassManifest$.arrayType:(Lscala/reflect/OptManifest;)Lscala/reflect/ClassManifest;
   37:	invokevirtual	#227; //Method tabulate:(ILscala/Function1;Lscala/reflect/ClassManifest;)Ljava/lang/Object;
   40:	checkcast	#63; //class "[[[Ljava/lang/Object;"
   43:	areturn
  LineNumberTable: 
   line 309: 0

  LocalVariableTable: 
   Start  Length  Slot  Name   Signature
   0      44      0    this       Lscala/Array$;
   0      44      1    n1       I
   0      44      2    n2$4       I
   0      44      3    n3$3       I
   0      44      4    n4$2       I
   0      44      5    f$2       Lscala/Function4;
   0      44      6    evidence$17$1       Lscala/reflect/ClassManifest;

  Signature: length = 0x2
   00 FFFFFFF6 

public java.lang.Object[][] tabulate(int, int, int, scala.Function3, scala.reflect.ClassManifest);
  Code:
   Stack=8, Locals=6, Args_size=6
   0:	aload_0
   1:	iload_1
   2:	new	#249; //class scala/Array$$anonfun$tabulate$2
   5:	dup
   6:	iload_2
   7:	iload_3
   8:	aload	4
   10:	aload	5
   12:	invokespecial	#252; //Method scala/Array$$anonfun$tabulate$2."<init>":(IILscala/Function3;Lscala/reflect/ClassManifest;)V
   15:	getstatic	#31; //Field scala/reflect/ClassManifest$.MODULE$:Lscala/reflect/ClassManifest$;
   18:	getstatic	#31; //Field scala/reflect/ClassManifest$.MODULE$:Lscala/reflect/ClassManifest$;
   21:	aload	5
   23:	invokevirtual	#35; //Method scala/reflect/ClassManifest$.arrayType:(Lscala/reflect/OptManifest;)Lscala/reflect/ClassManifest;
   26:	invokevirtual	#35; //Method scala/reflect/ClassManifest$.arrayType:(Lscala/reflect/OptManifest;)Lscala/reflect/ClassManifest;
   29:	invokevirtual	#227; //Method tabulate:(ILscala/Function1;Lscala/reflect/ClassManifest;)Ljava/lang/Object;
   32:	checkcast	#78; //class "[[Ljava/lang/Object;"
   35:	areturn
  LineNumberTable: 
   line 297: 0

  LocalVariableTable: 
   Start  Length  Slot  Name   Signature
   0      36      0    this       Lscala/Array$;
   0      36      1    n1       I
   0      36      2    n2$5       I
   0      36      3    n3$4       I
   0      36      4    f$3       Lscala/Function3;
   0      36      5    evidence$16$1       Lscala/reflect/ClassManifest;

  Signature: length = 0x2
   01 01 

public java.lang.Object[] tabulate(int, int, scala.Function2, scala.reflect.ClassManifest);
  Code:
   Stack=7, Locals=5, Args_size=5
   0:	aload_0
   1:	iload_1
   2:	new	#260; //class scala/Array$$anonfun$tabulate$1
   5:	dup
   6:	iload_2
   7:	aload_3
   8:	aload	4
   10:	invokespecial	#263; //Method scala/Array$$anonfun$tabulate$1."<init>":(ILscala/Function2;Lscala/reflect/ClassManifest;)V
   13:	getstatic	#31; //Field scala/reflect/ClassManifest$.MODULE$:Lscala/reflect/ClassManifest$;
   16:	aload	4
   18:	invokevirtual	#35; //Method scala/reflect/ClassManifest$.arrayType:(Lscala/reflect/OptManifest;)Lscala/reflect/ClassManifest;
   21:	invokevirtual	#227; //Method tabulate:(ILscala/Function1;Lscala/reflect/ClassManifest;)Ljava/lang/Object;
   24:	checkcast	#92; //class "[Ljava/lang/Object;"
   27:	areturn
  LineNumberTable: 
   line 286: 0

  LocalVariableTable: 
   Start  Length  Slot  Name   Signature
   0      28      0    this       Lscala/Array$;
   0      28      1    n1       I
   0      28      2    n2$6       I
   0      28      3    f$4       Lscala/Function2;
   0      28      4    evidence$15$1       Lscala/reflect/ClassManifest;

  Signature: length = 0x2
   01 0B 

public java.lang.Object tabulate(int, scala.Function1, scala.reflect.ClassManifest);
  Code:
   Stack=3, Locals=6, Args_size=4
   0:	aload_3
   1:	checkcast	#99; //class scala/reflect/ClassManifest
   4:	invokeinterface	#175,  1; //InterfaceMethod scala/reflect/ClassManifest.newArrayBuilder:()Lscala/collection/mutable/ArrayBuilder;
   9:	astore	5
   11:	iconst_0
   12:	istore	4
   14:	iload	4
   16:	iload_1
   17:	if_icmpge	48
   20:	aload	5
   22:	aload_2
   23:	iload	4
   25:	invokestatic	#109; //Method scala/runtime/BoxesRunTime.boxToInteger:(I)Ljava/lang/Integer;
   28:	invokeinterface	#115,  2; //InterfaceMethod scala/Function1.apply:(Ljava/lang/Object;)Ljava/lang/Object;
   33:	invokeinterface	#181,  2; //InterfaceMethod scala/collection/mutable/Builder.$plus$eq:(Ljava/lang/Object;)Lscala/collection/mutable/Builder;
   38:	pop
   39:	iload	4
   41:	iconst_1
   42:	iadd
   43:	istore	4
   45:	goto	14
   48:	aload	5
   50:	invokeinterface	#185,  1; //InterfaceMethod scala/collection/mutable/Builder.result:()Ljava/lang/Object;
   55:	areturn
  LineNumberTable: 
   line 269: 0
   line 270: 11
   line 271: 14
   line 272: 20
   line 273: 39
   line 275: 48

  LocalVariableTable: 
   Start  Length  Slot  Name   Signature
   0      56      0    this       Lscala/Array$;
   0      56      1    n       I
   0      56      2    f       Lscala/Function1;
   0      56      3    evidence$14       Lscala/reflect/ClassManifest;
   14      41      4    i       I
   11      44      5    b       Lscala/collection/mutable/ArrayBuilder;

  Signature: length = 0x2
   01 0D 

public java.lang.Object[][][][] fill(int, int, int, int, int, scala.Function0, scala.reflect.ClassManifest);
  Code:
   Stack=10, Locals=8, Args_size=8
   0:	aload_0
   1:	iload_1
   2:	new	#273; //class scala/Array$$anonfun$fill$4
   5:	dup
   6:	iload_2
   7:	iload_3
   8:	iload	4
   10:	iload	5
   12:	aload	6
   14:	aload	7
   16:	invokespecial	#276; //Method scala/Array$$anonfun$fill$4."<init>":(IIIILscala/Function0;Lscala/reflect/ClassManifest;)V
   19:	getstatic	#31; //Field scala/reflect/ClassManifest$.MODULE$:Lscala/reflect/ClassManifest$;
   22:	getstatic	#31; //Field scala/reflect/ClassManifest$.MODULE$:Lscala/reflect/ClassManifest$;
   25:	getstatic	#31; //Field scala/reflect/ClassManifest$.MODULE$:Lscala/reflect/ClassManifest$;
   28:	getstatic	#31; //Field scala/reflect/ClassManifest$.MODULE$:Lscala/reflect/ClassManifest$;
   31:	aload	7
   33:	invokevirtual	#35; //Method scala/reflect/ClassManifest$.arrayType:(Lscala/reflect/OptManifest;)Lscala/reflect/ClassManifest;
   36:	invokevirtual	#35; //Method scala/reflect/ClassManifest$.arrayType:(Lscala/reflect/OptManifest;)Lscala/reflect/ClassManifest;
   39:	invokevirtual	#35; //Method scala/reflect/ClassManifest$.arrayType:(Lscala/reflect/OptManifest;)Lscala/reflect/ClassManifest;
   42:	invokevirtual	#35; //Method scala/reflect/ClassManifest$.arrayType:(Lscala/reflect/OptManifest;)Lscala/reflect/ClassManifest;
   45:	invokevirtual	#227; //Method tabulate:(ILscala/Function1;Lscala/reflect/ClassManifest;)Ljava/lang/Object;
   48:	checkcast	#40; //class "[[[[Ljava/lang/Object;"
   51:	areturn
  LineNumberTable: 
   line 259: 0

  LocalVariableTable: 
   Start  Length  Slot  Name   Signature
   0      52      0    this       Lscala/Array$;
   0      52      1    n1       I
   0      52      2    n2$10       I
   0      52      3    n3$7       I
   0      52      4    n4$5       I
   0      52      5    n5$3       I
   0      52      6    elem$2       Lscala/Function0;
   0      52      7    evidence$13$1       Lscala/reflect/ClassManifest;

  Signature: length = 0x2
   01 1C 

public java.lang.Object[][][] fill(int, int, int, int, scala.Function0, scala.reflect.ClassManifest);
  Code:
   Stack=9, Locals=7, Args_size=7
   0:	aload_0
   1:	iload_1
   2:	new	#287; //class scala/Array$$anonfun$fill$3
   5:	dup
   6:	iload_2
   7:	iload_3
   8:	iload	4
   10:	aload	5
   12:	aload	6
   14:	invokespecial	#290; //Method scala/Array$$anonfun$fill$3."<init>":(IIILscala/Function0;Lscala/reflect/ClassManifest;)V
   17:	getstatic	#31; //Field scala/reflect/ClassManifest$.MODULE$:Lscala/reflect/ClassManifest$;
   20:	getstatic	#31; //Field scala/reflect/ClassManifest$.MODULE$:Lscala/reflect/ClassManifest$;
   23:	getstatic	#31; //Field scala/reflect/ClassManifest$.MODULE$:Lscala/reflect/ClassManifest$;
   26:	aload	6
   28:	invokevirtual	#35; //Method scala/reflect/ClassManifest$.arrayType:(Lscala/reflect/OptManifest;)Lscala/reflect/ClassManifest;
   31:	invokevirtual	#35; //Method scala/reflect/ClassManifest$.arrayType:(Lscala/reflect/OptManifest;)Lscala/reflect/ClassManifest;
   34:	invokevirtual	#35; //Method scala/reflect/ClassManifest$.arrayType:(Lscala/reflect/OptManifest;)Lscala/reflect/ClassManifest;
   37:	invokevirtual	#227; //Method tabulate:(ILscala/Function1;Lscala/reflect/ClassManifest;)Ljava/lang/Object;
   40:	checkcast	#63; //class "[[[Ljava/lang/Object;"
   43:	areturn
  LineNumberTable: 
   line 246: 0

  LocalVariableTable: 
   Start  Length  Slot  Name   Signature
   0      44      0    this       Lscala/Array$;
   0      44      1    n1       I
   0      44      2    n2$11       I
   0      44      3    n3$8       I
   0      44      4    n4$6       I
   0      44      5    elem$3       Lscala/Function0;
   0      44      6    evidence$12$1       Lscala/reflect/ClassManifest;

  Signature: length = 0x2
   01 28 

public java.lang.Object[][] fill(int, int, int, scala.Function0, scala.reflect.ClassManifest);
  Code:
   Stack=8, Locals=6, Args_size=6
   0:	aload_0
   1:	iload_1
   2:	new	#299; //class scala/Array$$anonfun$fill$2
   5:	dup
   6:	iload_2
   7:	iload_3
   8:	aload	4
   10:	aload	5
   12:	invokespecial	#302; //Method scala/Array$$anonfun$fill$2."<init>":(IILscala/Function0;Lscala/reflect/ClassManifest;)V
   15:	getstatic	#31; //Field scala/reflect/ClassManifest$.MODULE$:Lscala/reflect/ClassManifest$;
   18:	getstatic	#31; //Field scala/reflect/ClassManifest$.MODULE$:Lscala/reflect/ClassManifest$;
   21:	aload	5
   23:	invokevirtual	#35; //Method scala/reflect/ClassManifest$.arrayType:(Lscala/reflect/OptManifest;)Lscala/reflect/ClassManifest;
   26:	invokevirtual	#35; //Method scala/reflect/ClassManifest$.arrayType:(Lscala/reflect/OptManifest;)Lscala/reflect/ClassManifest;
   29:	invokevirtual	#227; //Method tabulate:(ILscala/Function1;Lscala/reflect/ClassManifest;)Ljava/lang/Object;
   32:	checkcast	#78; //class "[[Ljava/lang/Object;"
   35:	areturn
  LineNumberTable: 
   line 234: 0

  LocalVariableTable: 
   Start  Length  Slot  Name   Signature
   0      36      0    this       Lscala/Array$;
   0      36      1    n1       I
   0      36      2    n2$12       I
   0      36      3    n3$9       I
   0      36      4    elem$4       Lscala/Function0;
   0      36      5    evidence$11$1       Lscala/reflect/ClassManifest;

  Signature: length = 0x2
   01 33 

public java.lang.Object[] fill(int, int, scala.Function0, scala.reflect.ClassManifest);
  Code:
   Stack=7, Locals=5, Args_size=5
   0:	aload_0
   1:	iload_1
   2:	new	#310; //class scala/Array$$anonfun$fill$1
   5:	dup
   6:	iload_2
   7:	aload_3
   8:	aload	4
   10:	invokespecial	#313; //Method scala/Array$$anonfun$fill$1."<init>":(ILscala/Function0;Lscala/reflect/ClassManifest;)V
   13:	getstatic	#31; //Field scala/reflect/ClassManifest$.MODULE$:Lscala/reflect/ClassManifest$;
   16:	aload	4
   18:	invokevirtual	#35; //Method scala/reflect/ClassManifest$.arrayType:(Lscala/reflect/OptManifest;)Lscala/reflect/ClassManifest;
   21:	invokevirtual	#227; //Method tabulate:(ILscala/Function1;Lscala/reflect/ClassManifest;)Ljava/lang/Object;
   24:	checkcast	#92; //class "[Ljava/lang/Object;"
   27:	areturn
  LineNumberTable: 
   line 223: 0

  LocalVariableTable: 
   Start  Length  Slot  Name   Signature
   0      28      0    this       Lscala/Array$;
   0      28      1    n1       I
   0      28      2    n2$9       I
   0      28      3    elem$1       Lscala/Function0;
   0      28      4    evidence$10$1       Lscala/reflect/ClassManifest;

  Signature: length = 0x2
   01 3D 

public java.lang.Object fill(int, scala.Function0, scala.reflect.ClassManifest);
  Code:
   Stack=2, Locals=6, Args_size=4
   0:	aload_3
   1:	checkcast	#99; //class scala/reflect/ClassManifest
   4:	invokeinterface	#175,  1; //InterfaceMethod scala/reflect/ClassManifest.newArrayBuilder:()Lscala/collection/mutable/ArrayBuilder;
   9:	astore	5
   11:	iconst_0
   12:	istore	4
   14:	iload	4
   16:	iload_1
   17:	if_icmpge	43
   20:	aload	5
   22:	aload_2
   23:	invokeinterface	#322,  1; //InterfaceMethod scala/Function0.apply:()Ljava/lang/Object;
   28:	invokeinterface	#181,  2; //InterfaceMethod scala/collection/mutable/Builder.$plus$eq:(Ljava/lang/Object;)Lscala/collection/mutable/Builder;
   33:	pop
   34:	iload	4
   36:	iconst_1
   37:	iadd
   38:	istore	4
   40:	goto	14
   43:	aload	5
   45:	invokeinterface	#185,  1; //InterfaceMethod scala/collection/mutable/Builder.result:()Ljava/lang/Object;
   50:	areturn
  LineNumberTable: 
   line 206: 0
   line 207: 11
   line 208: 14
   line 209: 20
   line 210: 34
   line 212: 43

  LocalVariableTable: 
   Start  Length  Slot  Name   Signature
   0      51      0    this       Lscala/Array$;
   0      51      1    n       I
   0      51      2    elem       Lscala/Function0;
   0      51      3    evidence$9       Lscala/reflect/ClassManifest;
   14      36      4    i       I
   11      39      5    b       Lscala/collection/mutable/ArrayBuilder;

  Signature: length = 0x2
   01 44 

public java.lang.Object concat(scala.collection.Seq, scala.reflect.ClassManifest);
  Code:
   Stack=4, Locals=4, Args_size=3
   0:	aload_0
   1:	aload_2
   2:	invokevirtual	#330; //Method newBuilder:(Lscala/reflect/ClassManifest;)Lscala/collection/mutable/ArrayBuilder;
   5:	astore_3
   6:	aload_3
   7:	aload_1
   8:	new	#332; //class scala/Array$$anonfun$concat$1
   11:	dup
   12:	invokespecial	#333; //Method scala/Array$$anonfun$concat$1."<init>":()V
   15:	getstatic	#338; //Field scala/collection/Seq$.MODULE$:Lscala/collection/Seq$;
   18:	invokevirtual	#342; //Method scala/collection/Seq$.canBuildFrom:()Lscala/collection/generic/CanBuildFrom;
   21:	invokeinterface	#346,  3; //InterfaceMethod scala/collection/TraversableLike.map:(Lscala/Function1;Lscala/collection/generic/CanBuildFrom;)Ljava/lang/Object;
   26:	checkcast	#160; //class scala/collection/TraversableLike
   29:	getstatic	#351; //Field scala/math/Numeric$IntIsIntegral$.MODULE$:Lscala/math/Numeric$IntIsIntegral$;
   32:	invokeinterface	#355,  2; //InterfaceMethod scala/collection/TraversableLike.sum:(Lscala/math/Numeric;)Ljava/lang/Object;
   37:	invokestatic	#359; //Method scala/runtime/BoxesRunTime.unboxToInt:(Ljava/lang/Object;)I
   40:	invokeinterface	#363,  2; //InterfaceMethod scala/collection/mutable/Builder.sizeHint:(I)V
   45:	aload_1
   46:	new	#365; //class scala/Array$$anonfun$concat$2
   49:	dup
   50:	aload_3
   51:	invokespecial	#368; //Method scala/Array$$anonfun$concat$2."<init>":(Lscala/collection/mutable/ArrayBuilder;)V
   54:	invokeinterface	#374,  2; //InterfaceMethod scala/collection/IterableLike.foreach:(Lscala/Function1;)V
   59:	aload_3
   60:	invokeinterface	#185,  1; //InterfaceMethod scala/collection/mutable/Builder.result:()Ljava/lang/Object;
   65:	areturn
  LineNumberTable: 
   line 193: 0
   line 194: 6
   line 195: 45
   line 196: 59

  LocalVariableTable: 
   Start  Length  Slot  Name   Signature
   0      66      0    this       Lscala/Array$;
   0      66      1    xss       Lscala/collection/Seq;
   0      66      2    evidence$8       Lscala/reflect/ClassManifest;
   6      59      3    b$1       Lscala/collection/mutable/ArrayBuilder;

  Signature: length = 0x2
   01 7B 

public java.lang.Object[][][][] ofDim(int, int, int, int, int, scala.reflect.ClassManifest);
  Code:
   Stack=9, Locals=7, Args_size=7
   0:	aload_0
   1:	iload_1
   2:	new	#383; //class scala/Array$$anonfun$ofDim$4
   5:	dup
   6:	iload_2
   7:	iload_3
   8:	iload	4
   10:	iload	5
   12:	aload	6
   14:	invokespecial	#386; //Method scala/Array$$anonfun$ofDim$4."<init>":(IIIILscala/reflect/ClassManifest;)V
   17:	getstatic	#31; //Field scala/reflect/ClassManifest$.MODULE$:Lscala/reflect/ClassManifest$;
   20:	getstatic	#31; //Field scala/reflect/ClassManifest$.MODULE$:Lscala/reflect/ClassManifest$;
   23:	getstatic	#31; //Field scala/reflect/ClassManifest$.MODULE$:Lscala/reflect/ClassManifest$;
   26:	getstatic	#31; //Field scala/reflect/ClassManifest$.MODULE$:Lscala/reflect/ClassManifest$;
   29:	aload	6
   31:	invokevirtual	#35; //Method scala/reflect/ClassManifest$.arrayType:(Lscala/reflect/OptManifest;)Lscala/reflect/ClassManifest;
   34:	invokevirtual	#35; //Method scala/reflect/ClassManifest$.arrayType:(Lscala/reflect/OptManifest;)Lscala/reflect/ClassManifest;
   37:	invokevirtual	#35; //Method scala/reflect/ClassManifest$.arrayType:(Lscala/reflect/OptManifest;)Lscala/reflect/ClassManifest;
   40:	invokevirtual	#35; //Method scala/reflect/ClassManifest$.arrayType:(Lscala/reflect/OptManifest;)Lscala/reflect/ClassManifest;
   43:	invokevirtual	#227; //Method tabulate:(ILscala/Function1;Lscala/reflect/ClassManifest;)Ljava/lang/Object;
   46:	checkcast	#40; //class "[[[[Ljava/lang/Object;"
   49:	areturn
  LineNumberTable: 
   line 185: 0

  LocalVariableTable: 
   Start  Length  Slot  Name   Signature
   0      50      0    this       Lscala/Array$;
   0      50      1    n1       I
   0      50      2    n2$7       I
   0      50      3    n3$5       I
   0      50      4    n4$3       I
   0      50      5    n5$2       I
   0      50      6    evidence$7$1       Lscala/reflect/ClassManifest;

  Signature: length = 0x2
   01 FFFFFF88 

public java.lang.Object[][][] ofDim(int, int, int, int, scala.reflect.ClassManifest);
  Code:
   Stack=8, Locals=6, Args_size=6
   0:	aload_0
   1:	iload_1
   2:	new	#395; //class scala/Array$$anonfun$ofDim$3
   5:	dup
   6:	iload_2
   7:	iload_3
   8:	iload	4
   10:	aload	5
   12:	invokespecial	#398; //Method scala/Array$$anonfun$ofDim$3."<init>":(IIILscala/reflect/ClassManifest;)V
   15:	getstatic	#31; //Field scala/reflect/ClassManifest$.MODULE$:Lscala/reflect/ClassManifest$;
   18:	getstatic	#31; //Field scala/reflect/ClassManifest$.MODULE$:Lscala/reflect/ClassManifest$;
   21:	getstatic	#31; //Field scala/reflect/ClassManifest$.MODULE$:Lscala/reflect/ClassManifest$;
   24:	aload	5
   26:	invokevirtual	#35; //Method scala/reflect/ClassManifest$.arrayType:(Lscala/reflect/OptManifest;)Lscala/reflect/ClassManifest;
   29:	invokevirtual	#35; //Method scala/reflect/ClassManifest$.arrayType:(Lscala/reflect/OptManifest;)Lscala/reflect/ClassManifest;
   32:	invokevirtual	#35; //Method scala/reflect/ClassManifest$.arrayType:(Lscala/reflect/OptManifest;)Lscala/reflect/ClassManifest;
   35:	invokevirtual	#227; //Method tabulate:(ILscala/Function1;Lscala/reflect/ClassManifest;)Ljava/lang/Object;
   38:	checkcast	#63; //class "[[[Ljava/lang/Object;"
   41:	areturn
  LineNumberTable: 
   line 183: 0

  LocalVariableTable: 
   Start  Length  Slot  Name   Signature
   0      42      0    this       Lscala/Array$;
   0      42      1    n1       I
   0      42      2    n2$8       I
   0      42      3    n3$6       I
   0      42      4    n4$4       I
   0      42      5    evidence$6$1       Lscala/reflect/ClassManifest;

  Signature: length = 0x2
   01 FFFFFF93 

public java.lang.Object[][] ofDim(int, int, int, scala.reflect.ClassManifest);
  Code:
   Stack=7, Locals=5, Args_size=5
   0:	aload_0
   1:	iload_1
   2:	new	#406; //class scala/Array$$anonfun$ofDim$2
   5:	dup
   6:	iload_2
   7:	iload_3
   8:	aload	4
   10:	invokespecial	#409; //Method scala/Array$$anonfun$ofDim$2."<init>":(IILscala/reflect/ClassManifest;)V
   13:	getstatic	#31; //Field scala/reflect/ClassManifest$.MODULE$:Lscala/reflect/ClassManifest$;
   16:	getstatic	#31; //Field scala/reflect/ClassManifest$.MODULE$:Lscala/reflect/ClassManifest$;
   19:	aload	4
   21:	invokevirtual	#35; //Method scala/reflect/ClassManifest$.arrayType:(Lscala/reflect/OptManifest;)Lscala/reflect/ClassManifest;
   24:	invokevirtual	#35; //Method scala/reflect/ClassManifest$.arrayType:(Lscala/reflect/OptManifest;)Lscala/reflect/ClassManifest;
   27:	invokevirtual	#227; //Method tabulate:(ILscala/Function1;Lscala/reflect/ClassManifest;)Ljava/lang/Object;
   30:	checkcast	#78; //class "[[Ljava/lang/Object;"
   33:	areturn
  LineNumberTable: 
   line 181: 0

  LocalVariableTable: 
   Start  Length  Slot  Name   Signature
   0      34      0    this       Lscala/Array$;
   0      34      1    n1       I
   0      34      2    n2$2       I
   0      34      3    n3$1       I
   0      34      4    evidence$5$1       Lscala/reflect/ClassManifest;

  Signature: length = 0x2
   01 FFFFFF9D 

public java.lang.Object[] ofDim(int, int, scala.reflect.ClassManifest);
  Code:
   Stack=6, Locals=5, Args_size=4
   0:	aload_3
   1:	iload_1
   2:	invokeinterface	#418,  2; //InterfaceMethod scala/reflect/ClassManifest.newArray2:(I)[Ljava/lang/Object;
   7:	astore	4
   9:	getstatic	#154; //Field scala/Predef$.MODULE$:Lscala/Predef$;
   12:	iconst_0
   13:	invokevirtual	#422; //Method scala/Predef$.intWrapper:(I)Lscala/runtime/RichInt;
   16:	iload_1
   17:	invokevirtual	#428; //Method scala/runtime/RichInt.until:(I)Lscala/collection/immutable/Range;
   20:	checkcast	#430; //class scala/collection/immutable/Range$ByOne
   23:	new	#432; //class scala/Array$$anonfun$ofDim$1
   26:	dup
   27:	iload_2
   28:	aload_3
   29:	aload	4
   31:	invokespecial	#435; //Method scala/Array$$anonfun$ofDim$1."<init>":(ILscala/reflect/ClassManifest;[Ljava/lang/Object;)V
   34:	invokeinterface	#436,  2; //InterfaceMethod scala/collection/immutable/Range$ByOne.foreach:(Lscala/Function1;)V
   39:	aload	4
   41:	areturn
  LineNumberTable: 
   line 175: 0
   line 176: 9
   line 177: 39

  LocalVariableTable: 
   Start  Length  Slot  Name   Signature
   0      42      0    this       Lscala/Array$;
   0      42      1    n1       I
   0      42      2    n2$1       I
   0      42      3    evidence$4$1       Lscala/reflect/ClassManifest;
   9      32      4    arr$1       [Ljava/lang/Object;

  Signature: length = 0x2
   01 FFFFFFB8 

public java.lang.Object ofDim(int, scala.reflect.ClassManifest);
  Code:
   Stack=2, Locals=3, Args_size=3
   0:	aload_2
   1:	iload_1
   2:	invokeinterface	#103,  2; //InterfaceMethod scala/reflect/ClassManifest.newArray:(I)Ljava/lang/Object;
   7:	areturn
  LineNumberTable: 
   line 173: 0

  LocalVariableTable: 
   Start  Length  Slot  Name   Signature
   0      8      0    this       Lscala/Array$;
   0      8      1    n1       I
   0      8      2    evidence$3       Lscala/reflect/ClassManifest;

  Signature: length = 0x2
   01 FFFFFFBB 

public scala.runtime.BoxedUnit[] apply(scala.runtime.BoxedUnit, scala.collection.Seq);
  Code:
   Stack=5, Locals=5, Args_size=3
   0:	aload_2
   1:	invokeinterface	#450,  1; //InterfaceMethod scala/collection/SeqLike.length:()I
   6:	iconst_1
   7:	iadd
   8:	anewarray	#452; //class scala/runtime/BoxedUnit
   11:	astore_3
   12:	aload_3
   13:	iconst_0
   14:	aload_1
   15:	aastore
   16:	new	#454; //class scala/runtime/IntRef
   19:	dup
   20:	iconst_1
   21:	invokespecial	#456; //Method scala/runtime/IntRef."<init>":(I)V
   24:	astore	4
   26:	aload_2
   27:	invokeinterface	#460,  1; //InterfaceMethod scala/collection/IterableLike.iterator:()Lscala/collection/Iterator;
   32:	new	#462; //class scala/Array$$anonfun$apply$10
   35:	dup
   36:	aload_3
   37:	aload	4
   39:	invokespecial	#465; //Method scala/Array$$anonfun$apply$10."<init>":([Lscala/runtime/BoxedUnit;Lscala/runtime/IntRef;)V
   42:	invokeinterface	#468,  2; //InterfaceMethod scala/collection/Iterator.foreach:(Lscala/Function1;)V
   47:	aload_3
   48:	areturn
  LineNumberTable: 
   line 164: 0
   line 165: 12
   line 166: 16
   line 167: 26
   line 168: 47

  LocalVariableTable: 
   Start  Length  Slot  Name   Signature
   0      49      0    this       Lscala/Array$;
   0      49      1    x       Lscala/runtime/BoxedUnit;
   0      49      2    xs       Lscala/collection/Seq;
   12      36      3    array$10       [Lscala/runtime/BoxedUnit;
   26      22      4    i$10       Lscala/runtime/IntRef;

  Signature: length = 0x2
   01 FFFFFFDB 

public double[] apply(double, scala.collection.Seq);
  Code:
   Stack=5, Locals=6, Args_size=3
   0:	aload_3
   1:	invokeinterface	#450,  1; //InterfaceMethod scala/collection/SeqLike.length:()I
   6:	iconst_1
   7:	iadd
   8:	newarray double
   10:	astore	4
   12:	aload	4
   14:	iconst_0
   15:	dload_1
   16:	dastore
   17:	new	#454; //class scala/runtime/IntRef
   20:	dup
   21:	iconst_1
   22:	invokespecial	#456; //Method scala/runtime/IntRef."<init>":(I)V
   25:	astore	5
   27:	aload_3
   28:	invokeinterface	#460,  1; //InterfaceMethod scala/collection/IterableLike.iterator:()Lscala/collection/Iterator;
   33:	new	#478; //class scala/Array$$anonfun$apply$9
   36:	dup
   37:	aload	4
   39:	aload	5
   41:	invokespecial	#481; //Method scala/Array$$anonfun$apply$9."<init>":([DLscala/runtime/IntRef;)V
   44:	invokeinterface	#468,  2; //InterfaceMethod scala/collection/Iterator.foreach:(Lscala/Function1;)V
   49:	aload	4
   51:	areturn
  LineNumberTable: 
   line 156: 0
   line 157: 12
   line 158: 17
   line 159: 27
   line 160: 49

  LocalVariableTable: 
   Start  Length  Slot  Name   Signature
   0      52      0    this       Lscala/Array$;
   0      52      1    x       D
   0      52      3    xs       Lscala/collection/Seq;
   12      39      4    array$9       [D
   27      24      5    i$9       Lscala/runtime/IntRef;

  Signature: length = 0x2
   01 FFFFFFE6 

public float[] apply(float, scala.collection.Seq);
  Code:
   Stack=5, Locals=5, Args_size=3
   0:	aload_2
   1:	invokeinterface	#450,  1; //InterfaceMethod scala/collection/SeqLike.length:()I
   6:	iconst_1
   7:	iadd
   8:	newarray float
   10:	astore_3
   11:	aload_3
   12:	iconst_0
   13:	fload_1
   14:	fastore
   15:	new	#454; //class scala/runtime/IntRef
   18:	dup
   19:	iconst_1
   20:	invokespecial	#456; //Method scala/runtime/IntRef."<init>":(I)V
   23:	astore	4
   25:	aload_2
   26:	invokeinterface	#460,  1; //InterfaceMethod scala/collection/IterableLike.iterator:()Lscala/collection/Iterator;
   31:	new	#489; //class scala/Array$$anonfun$apply$8
   34:	dup
   35:	aload_3
   36:	aload	4
   38:	invokespecial	#492; //Method scala/Array$$anonfun$apply$8."<init>":([FLscala/runtime/IntRef;)V
   41:	invokeinterface	#468,  2; //InterfaceMethod scala/collection/Iterator.foreach:(Lscala/Function1;)V
   46:	aload_3
   47:	areturn
  LineNumberTable: 
   line 148: 0
   line 149: 11
   line 150: 15
   line 151: 25
   line 152: 46

  LocalVariableTable: 
   Start  Length  Slot  Name   Signature
   0      48      0    this       Lscala/Array$;
   0      48      1    x       F
   0      48      2    xs       Lscala/collection/Seq;
   11      36      3    array$8       [F
   25      22      4    i$8       Lscala/runtime/IntRef;

  Signature: length = 0x2
   01 FFFFFFF1 

public long[] apply(long, scala.collection.Seq);
  Code:
   Stack=5, Locals=6, Args_size=3
   0:	aload_3
   1:	invokeinterface	#450,  1; //InterfaceMethod scala/collection/SeqLike.length:()I
   6:	iconst_1
   7:	iadd
   8:	newarray long
   10:	astore	4
   12:	aload	4
   14:	iconst_0
   15:	lload_1
   16:	lastore
   17:	new	#454; //class scala/runtime/IntRef
   20:	dup
   21:	iconst_1
   22:	invokespecial	#456; //Method scala/runtime/IntRef."<init>":(I)V
   25:	astore	5
   27:	aload_3
   28:	invokeinterface	#460,  1; //InterfaceMethod scala/collection/IterableLike.iterator:()Lscala/collection/Iterator;
   33:	new	#500; //class scala/Array$$anonfun$apply$7
   36:	dup
   37:	aload	4
   39:	aload	5
   41:	invokespecial	#503; //Method scala/Array$$anonfun$apply$7."<init>":([JLscala/runtime/IntRef;)V
   44:	invokeinterface	#468,  2; //InterfaceMethod scala/collection/Iterator.foreach:(Lscala/Function1;)V
   49:	aload	4
   51:	areturn
  LineNumberTable: 
   line 140: 0
   line 141: 12
   line 142: 17
   line 143: 27
   line 144: 49

  LocalVariableTable: 
   Start  Length  Slot  Name   Signature
   0      52      0    this       Lscala/Array$;
   0      52      1    x       J
   0      52      3    xs       Lscala/collection/Seq;
   12      39      4    array$7       [J
   27      24      5    i$7       Lscala/runtime/IntRef;

  Signature: length = 0x2
   01 FFFFFFFC 

public int[] apply(int, scala.collection.Seq);
  Code:
   Stack=5, Locals=5, Args_size=3
   0:	aload_2
   1:	invokeinterface	#450,  1; //InterfaceMethod scala/collection/SeqLike.length:()I
   6:	iconst_1
   7:	iadd
   8:	newarray int
   10:	astore_3
   11:	aload_3
   12:	iconst_0
   13:	iload_1
   14:	iastore
   15:	new	#454; //class scala/runtime/IntRef
   18:	dup
   19:	iconst_1
   20:	invokespecial	#456; //Method scala/runtime/IntRef."<init>":(I)V
   23:	astore	4
   25:	aload_2
   26:	invokeinterface	#460,  1; //InterfaceMethod scala/collection/IterableLike.iterator:()Lscala/collection/Iterator;
   31:	new	#511; //class scala/Array$$anonfun$apply$6
   34:	dup
   35:	aload_3
   36:	aload	4
   38:	invokespecial	#514; //Method scala/Array$$anonfun$apply$6."<init>":([ILscala/runtime/IntRef;)V
   41:	invokeinterface	#468,  2; //InterfaceMethod scala/collection/Iterator.foreach:(Lscala/Function1;)V
   46:	aload_3
   47:	areturn
  LineNumberTable: 
   line 132: 0
   line 133: 11
   line 134: 15
   line 135: 25
   line 136: 46

  LocalVariableTable: 
   Start  Length  Slot  Name   Signature
   0      48      0    this       Lscala/Array$;
   0      48      1    x       I
   0      48      2    xs       Lscala/collection/Seq;
   11      36      3    array$6       [I
   25      22      4    i$6       Lscala/runtime/IntRef;

  Signature: length = 0x2
   02 05 

public char[] apply(char, scala.collection.Seq);
  Code:
   Stack=5, Locals=5, Args_size=3
   0:	aload_2
   1:	invokeinterface	#450,  1; //InterfaceMethod scala/collection/SeqLike.length:()I
   6:	iconst_1
   7:	iadd
   8:	newarray char
   10:	astore_3
   11:	aload_3
   12:	iconst_0
   13:	iload_1
   14:	castore
   15:	new	#454; //class scala/runtime/IntRef
   18:	dup
   19:	iconst_1
   20:	invokespecial	#456; //Method scala/runtime/IntRef."<init>":(I)V
   23:	astore	4
   25:	aload_2
   26:	invokeinterface	#460,  1; //InterfaceMethod scala/collection/IterableLike.iterator:()Lscala/collection/Iterator;
   31:	new	#520; //class scala/Array$$anonfun$apply$5
   34:	dup
   35:	aload_3
   36:	aload	4
   38:	invokespecial	#523; //Method scala/Array$$anonfun$apply$5."<init>":([CLscala/runtime/IntRef;)V
   41:	invokeinterface	#468,  2; //InterfaceMethod scala/collection/Iterator.foreach:(Lscala/Function1;)V
   46:	aload_3
   47:	areturn
  LineNumberTable: 
   line 124: 0
   line 125: 11
   line 126: 15
   line 127: 25
   line 128: 46

  LocalVariableTable: 
   Start  Length  Slot  Name   Signature
   0      48      0    this       Lscala/Array$;
   0      48      1    x       C
   0      48      2    xs       Lscala/collection/Seq;
   11      36      3    array$5       [C
   25      22      4    i$5       Lscala/runtime/IntRef;

  Signature: length = 0x2
   02 10 

public short[] apply(short, scala.collection.Seq);
  Code:
   Stack=5, Locals=5, Args_size=3
   0:	aload_2
   1:	invokeinterface	#450,  1; //InterfaceMethod scala/collection/SeqLike.length:()I
   6:	iconst_1
   7:	iadd
   8:	newarray short
   10:	astore_3
   11:	aload_3
   12:	iconst_0
   13:	iload_1
   14:	sastore
   15:	new	#454; //class scala/runtime/IntRef
   18:	dup
   19:	iconst_1
   20:	invokespecial	#456; //Method scala/runtime/IntRef."<init>":(I)V
   23:	astore	4
   25:	aload_2
   26:	invokeinterface	#460,  1; //InterfaceMethod scala/collection/IterableLike.iterator:()Lscala/collection/Iterator;
   31:	new	#531; //class scala/Array$$anonfun$apply$4
   34:	dup
   35:	aload_3
   36:	aload	4
   38:	invokespecial	#534; //Method scala/Array$$anonfun$apply$4."<init>":([SLscala/runtime/IntRef;)V
   41:	invokeinterface	#468,  2; //InterfaceMethod scala/collection/Iterator.foreach:(Lscala/Function1;)V
   46:	aload_3
   47:	areturn
  LineNumberTable: 
   line 116: 0
   line 117: 11
   line 118: 15
   line 119: 25
   line 120: 46

  LocalVariableTable: 
   Start  Length  Slot  Name   Signature
   0      48      0    this       Lscala/Array$;
   0      48      1    x       S
   0      48      2    xs       Lscala/collection/Seq;
   11      36      3    array$4       [S
   25      22      4    i$4       Lscala/runtime/IntRef;

  Signature: length = 0x2
   02 1B 

public byte[] apply(byte, scala.collection.Seq);
  Code:
   Stack=5, Locals=5, Args_size=3
   0:	aload_2
   1:	invokeinterface	#450,  1; //InterfaceMethod scala/collection/SeqLike.length:()I
   6:	iconst_1
   7:	iadd
   8:	newarray byte
   10:	astore_3
   11:	aload_3
   12:	iconst_0
   13:	iload_1
   14:	bastore
   15:	new	#454; //class scala/runtime/IntRef
   18:	dup
   19:	iconst_1
   20:	invokespecial	#456; //Method scala/runtime/IntRef."<init>":(I)V
   23:	astore	4
   25:	aload_2
   26:	invokeinterface	#460,  1; //InterfaceMethod scala/collection/IterableLike.iterator:()Lscala/collection/Iterator;
   31:	new	#542; //class scala/Array$$anonfun$apply$3
   34:	dup
   35:	aload_3
   36:	aload	4
   38:	invokespecial	#545; //Method scala/Array$$anonfun$apply$3."<init>":([BLscala/runtime/IntRef;)V
   41:	invokeinterface	#468,  2; //InterfaceMethod scala/collection/Iterator.foreach:(Lscala/Function1;)V
   46:	aload_3
   47:	areturn
  LineNumberTable: 
   line 108: 0
   line 109: 11
   line 110: 15
   line 111: 25
   line 112: 46

  LocalVariableTable: 
   Start  Length  Slot  Name   Signature
   0      48      0    this       Lscala/Array$;
   0      48      1    x       B
   0      48      2    xs       Lscala/collection/Seq;
   11      36      3    array$3       [B
   25      22      4    i$3       Lscala/runtime/IntRef;

  Signature: length = 0x2
   02 26 

public boolean[] apply(boolean, scala.collection.Seq);
  Code:
   Stack=5, Locals=5, Args_size=3
   0:	aload_2
   1:	invokeinterface	#450,  1; //InterfaceMethod scala/collection/SeqLike.length:()I
   6:	iconst_1
   7:	iadd
   8:	newarray boolean
   10:	astore_3
   11:	aload_3
   12:	iconst_0
   13:	iload_1
   14:	bastore
   15:	new	#454; //class scala/runtime/IntRef
   18:	dup
   19:	iconst_1
   20:	invokespecial	#456; //Method scala/runtime/IntRef."<init>":(I)V
   23:	astore	4
   25:	aload_2
   26:	invokeinterface	#460,  1; //InterfaceMethod scala/collection/IterableLike.iterator:()Lscala/collection/Iterator;
   31:	new	#553; //class scala/Array$$anonfun$apply$2
   34:	dup
   35:	aload_3
   36:	aload	4
   38:	invokespecial	#556; //Method scala/Array$$anonfun$apply$2."<init>":([ZLscala/runtime/IntRef;)V
   41:	invokeinterface	#468,  2; //InterfaceMethod scala/collection/Iterator.foreach:(Lscala/Function1;)V
   46:	aload_3
   47:	areturn
  LineNumberTable: 
   line 100: 0
   line 101: 11
   line 102: 15
   line 103: 25
   line 104: 46

  LocalVariableTable: 
   Start  Length  Slot  Name   Signature
   0      48      0    this       Lscala/Array$;
   0      48      1    x       Z
   0      48      2    xs       Lscala/collection/Seq;
   11      36      3    array$2       [Z
   25      22      4    i$2       Lscala/runtime/IntRef;

  Signature: length = 0x2
   02 31 

public java.lang.Object apply(scala.collection.Seq, scala.reflect.ClassManifest);
  Code:
   Stack=5, Locals=5, Args_size=3
   0:	aload_2
   1:	aload_1
   2:	invokeinterface	#450,  1; //InterfaceMethod scala/collection/SeqLike.length:()I
   7:	invokeinterface	#103,  2; //InterfaceMethod scala/reflect/ClassManifest.newArray:(I)Ljava/lang/Object;
   12:	astore_3
   13:	new	#454; //class scala/runtime/IntRef
   16:	dup
   17:	iconst_0
   18:	invokespecial	#456; //Method scala/runtime/IntRef."<init>":(I)V
   21:	astore	4
   23:	aload_1
   24:	invokeinterface	#460,  1; //InterfaceMethod scala/collection/IterableLike.iterator:()Lscala/collection/Iterator;
   29:	new	#563; //class scala/Array$$anonfun$apply$1
   32:	dup
   33:	aload_3
   34:	aload	4
   36:	invokespecial	#566; //Method scala/Array$$anonfun$apply$1."<init>":(Ljava/lang/Object;Lscala/runtime/IntRef;)V
   39:	invokeinterface	#468,  2; //InterfaceMethod scala/collection/Iterator.foreach:(Lscala/Function1;)V
   44:	aload_3
   45:	areturn
  LineNumberTable: 
   line 93: 0
   line 94: 13
   line 95: 23
   line 96: 44

  LocalVariableTable: 
   Start  Length  Slot  Name   Signature
   0      46      0    this       Lscala/Array$;
   0      46      1    xs       Lscala/collection/Seq;
   0      46      2    evidence$2       Lscala/reflect/ClassManifest;
   13      32      3    array$1       Ljava/lang/Object;
   23      22      4    i$1       Lscala/runtime/IntRef;

  Signature: length = 0x2
   02 3A 

public java.lang.Object empty(scala.reflect.ClassManifest);
  Code:
   Stack=2, Locals=2, Args_size=2
   0:	aload_1
   1:	iconst_0
   2:	invokeinterface	#103,  2; //InterfaceMethod scala/reflect/ClassManifest.newArray:(I)Ljava/lang/Object;
   7:	areturn
  LineNumberTable: 
   line 85: 0

  LocalVariableTable: 
   Start  Length  Slot  Name   Signature
   0      8      0    this       Lscala/Array$;
   0      8      1    evidence$1       Lscala/reflect/ClassManifest;

  Signature: length = 0x2
   02 3E 

public void copy(java.lang.Object, int, java.lang.Object, int, int);
  Code:
   Stack=6, Locals=7, Args_size=6
   0:	aload_1
   1:	invokevirtual	#580; //Method java/lang/Object.getClass:()Ljava/lang/Class;
   4:	astore	6
   6:	aload	6
   8:	invokevirtual	#586; //Method java/lang/Class.isArray:()Z
   11:	ifeq	39
   14:	aload_3
   15:	invokevirtual	#580; //Method java/lang/Object.getClass:()Ljava/lang/Class;
   18:	aload	6
   20:	invokevirtual	#590; //Method java/lang/Class.isAssignableFrom:(Ljava/lang/Class;)Z
   23:	ifeq	39
   26:	aload_1
   27:	iload_2
   28:	aload_3
   29:	iload	4
   31:	iload	5
   33:	invokestatic	#595; //Method java/lang/System.arraycopy:(Ljava/lang/Object;ILjava/lang/Object;II)V
   36:	goto	50
   39:	aload_0
   40:	aload_1
   41:	iload_2
   42:	aload_3
   43:	iload	4
   45:	iload	5
   47:	invokespecial	#598; //Method slowcopy:(Ljava/lang/Object;ILjava/lang/Object;II)V
   50:	return
  LineNumberTable: 
   line 77: 0
   line 78: 6
   line 79: 26
   line 81: 39
   line 76: 50

  LocalVariableTable: 
   Start  Length  Slot  Name   Signature
   0      51      0    this       Lscala/Array$;
   0      51      1    src       Ljava/lang/Object;
   0      51      2    srcPos       I
   0      51      3    dest       Ljava/lang/Object;
   0      51      4    destPos       I
   0      51      5    length       I
   6      45      6    srcClass       Ljava/lang/Class;


public scala.collection.mutable.ArrayBuilder newBuilder(scala.reflect.ClassManifest);
  Code:
   Stack=2, Locals=2, Args_size=2
   0:	getstatic	#613; //Field scala/collection/mutable/ArrayBuilder$.MODULE$:Lscala/collection/mutable/ArrayBuilder$;
   3:	aload_1
   4:	invokevirtual	#615; //Method scala/collection/mutable/ArrayBuilder$.make:(Lscala/reflect/ClassManifest;)Lscala/collection/mutable/ArrayBuilder;
   7:	areturn
  LineNumberTable: 
   line 51: 0

  LocalVariableTable: 
   Start  Length  Slot  Name   Signature
   0      8      0    this       Lscala/Array$;
   0      8      1    m       Lscala/reflect/ClassManifest;

  Signature: length = 0x2
   02 69 

public scala.collection.generic.CanBuildFrom canBuildFrom(scala.reflect.ClassManifest);
  Code:
   Stack=3, Locals=2, Args_size=2
   0:	new	#620; //class scala/Array$$anon$2
   3:	dup
   4:	aload_1
   5:	invokespecial	#623; //Method scala/Array$$anon$2."<init>":(Lscala/reflect/ClassManifest;)V
   8:	areturn
  LineNumberTable: 
   line 46: 0

  LocalVariableTable: 
   Start  Length  Slot  Name   Signature
   0      9      0    this       Lscala/Array$;
   0      9      1    m$1       Lscala/reflect/ClassManifest;

  Signature: length = 0x2
   02 71 

}

