Compiled from "Array.scala"
public final class scala.Array$$anonfun$fromFunction$4$$anonfun$apply$18 extends scala.runtime.AbstractFunction4 implements java.io.Serializable
  SourceFile: "Array.scala"
  Scala: length = 0x
   
  InnerClass: 
   public final $anonfun$fromFunction$4=class scala/Array$$anonfun$fromFunction$4 of class scala/Array
   public final $anonfun$apply$18=class scala/Array$$anonfun$fromFunction$4$$anonfun$apply$18 of class scala/Array$$anonfun$fromFunction$4
  minor version: 0
  major version: 49
  Constant pool:
Asciz	SourceFile;
Asciz	Array.scala;
Asciz	<clinit>;
Asciz	()V;
Asciz	Code;
Asciz	serialVersionUID;
Asciz	J;
Asciz	scala/Array$$anonfun$fromFunction$4$$anonfun$apply$18;
class	scala/Array$$anonfun$fromFunction$4$$anonfun$apply$18
NameAndType	serialVersionUID:J
Field	scala/Array$$anonfun$fromFunction$4$$anonfun$apply$18.serialVersionUID:J
Asciz	i$14;
Asciz	I;
Asciz	$outer;
Asciz	Lscala/Array$$anonfun$fromFunction$4;;
Asciz	apply;
Asciz	(IIII)Ljava/lang/Object;;
Asciz	LineNumberTable;
NameAndType	$outer:Lscala/Array$$anonfun$fromFunction$4;
Field	scala/Array$$anonfun$fromFunction$4$$anonfun$apply$18.$outer:Lscala/Array$$anonfun$fromFunction$4;
Asciz	scala/Array$$anonfun$fromFunction$4;
class	scala/Array$$anonfun$fromFunction$4
Asciz	f$6;
Asciz	Lscala/Function5;;
NameAndType	f$6:Lscala/Function5;
Field	scala/Array$$anonfun$fromFunction$4.f$6:Lscala/Function5;
NameAndType	i$14:I
Field	scala/Array$$anonfun$fromFunction$4$$anonfun$apply$18.i$14:I
Asciz	scala/runtime/BoxesRunTime;
class	scala/runtime/BoxesRunTime
Asciz	boxToInteger;
Asciz	(I)Ljava/lang/Integer;;
NameAndType	boxToInteger:(I)Ljava/lang/Integer;
Method	scala/runtime/BoxesRunTime.boxToInteger:(I)Ljava/lang/Integer;
Asciz	scala/Function5;
class	scala/Function5
Asciz	(Ljava/lang/Object;Ljava/lang/Object;Ljava/lang/Object;Ljava/lang/Object;Ljava/lang/Object;)Ljava/lang/Object;;
NameAndType	apply:(Ljava/lang/Object;Ljava/lang/Object;Ljava/lang/Object;Ljava/lang/Object;Ljava/lang/Object;)Ljava/lang/Object;
InterfaceMethod	scala/Function5.apply:(Ljava/lang/Object;Ljava/lang/Object;Ljava/lang/Object;Ljava/lang/Object;Ljava/lang/Object;)Ljava/lang/Object;
Asciz	(IIII)TT;;
Asciz	Signature;
Asciz	(Ljava/lang/Object;Ljava/lang/Object;Ljava/lang/Object;Ljava/lang/Object;)Ljava/lang/Object;;
Asciz	unboxToInt;
Asciz	(Ljava/lang/Object;)I;
NameAndType	unboxToInt:(Ljava/lang/Object;)I
Method	scala/runtime/BoxesRunTime.unboxToInt:(Ljava/lang/Object;)I
NameAndType	apply:(IIII)Ljava/lang/Object;
Method	scala/Array$$anonfun$fromFunction$4$$anonfun$apply$18.apply:(IIII)Ljava/lang/Object;
Asciz	this;
Asciz	Lscala/Array$$anonfun$fromFunction$4$$anonfun$apply$18;;
Asciz	v1;
Asciz	Ljava/lang/Object;;
Asciz	v2;
Asciz	v3;
Asciz	v4;
Asciz	LocalVariableTable;
Asciz	<init>;
Asciz	(Lscala/Array$$anonfun$fromFunction$4;I)V;
Asciz	java/lang/NullPointerException;
class	java/lang/NullPointerException
NameAndType	"<init>":()V
Method	java/lang/NullPointerException."<init>":()V
Asciz	scala/runtime/AbstractFunction4;
class	scala/runtime/AbstractFunction4
Method	scala/runtime/AbstractFunction4."<init>":()V
Asciz	Scala;
Asciz	InnerClasses;
Asciz	scala/Array;
class	scala/Array
Asciz	$anonfun$fromFunction$4;
Asciz	$anonfun$apply$18;
Asciz	java/io/Serializable;
class	java/io/Serializable

{
public static final long serialVersionUID;
  Signature: J

private final int i$14;
  Signature: I

private final scala.Array$$anonfun$fromFunction$4 $outer;
  Signature: Lscala/Array$$anonfun$fromFunction$4;

public static {};
  Signature: ()V
  Code:
   Stack=2, Locals=0, Args_size=0
	lconst_0
	putstatic	Field serialVersionUID:J
	return
  Labels:

public final java.lang.Object apply(int, int, int, int);
  Signature: (IIII)Ljava/lang/Object;
  Code:
   Stack=6, Locals=5, Args_size=5
	aload_0
	getfield	Field $outer:Lscala/Array$$anonfun$fromFunction$4;
	getfield	Field scala/Array$$anonfun$fromFunction$4.f$6:Lscala/Function5;
	aload_0
	getfield	Field i$14:I
	invokestatic	Method scala/runtime/BoxesRunTime.boxToInteger:(I)Ljava/lang/Integer;
	iload_1
	invokestatic	Method scala/runtime/BoxesRunTime.boxToInteger:(I)Ljava/lang/Integer;
	iload_2
	invokestatic	Method scala/runtime/BoxesRunTime.boxToInteger:(I)Ljava/lang/Integer;
	iload_3
	invokestatic	Method scala/runtime/BoxesRunTime.boxToInteger:(I)Ljava/lang/Integer;
	iload	4
	invokestatic	Method scala/runtime/BoxesRunTime.boxToInteger:(I)Ljava/lang/Integer;
	invokeinterface	InterfaceMethod scala/Function5.apply:(Ljava/lang/Object;Ljava/lang/Object;Ljava/lang/Object;Ljava/lang/Object;Ljava/lang/Object;)Ljava/lang/Object;
	areturn
  Labels:
  Signature: length = 0x2
   00 28 

public final java.lang.Object apply(java.lang.Object, java.lang.Object, java.lang.Object, java.lang.Object);
  Signature: (Ljava/lang/Object;Ljava/lang/Object;Ljava/lang/Object;Ljava/lang/Object;)Ljava/lang/Object;
  Code:
   Stack=5, Locals=5, Args_size=5
	aload_0
	aload_1
	invokestatic	Method scala/runtime/BoxesRunTime.unboxToInt:(Ljava/lang/Object;)I
	aload_2
	invokestatic	Method scala/runtime/BoxesRunTime.unboxToInt:(Ljava/lang/Object;)I
	aload_3
	invokestatic	Method scala/runtime/BoxesRunTime.unboxToInt:(Ljava/lang/Object;)I
	aload	4
	invokestatic	Method scala/runtime/BoxesRunTime.unboxToInt:(Ljava/lang/Object;)I
	invokevirtual	Method apply:(IIII)Ljava/lang/Object;
	areturn
  Labels:
  LocalVariableTable: 
   Start  Length  Slot  Name   Signature
   0      22      0    this       Lscala/Array$$anonfun$fromFunction$4$$anonfun$apply$18;
   0      22      1    v1       Ljava/lang/Object;
   0      22      2    v2       Ljava/lang/Object;
   0      22      3    v3       Ljava/lang/Object;
   0      22      4    v4       Ljava/lang/Object;


public scala.Array$$anonfun$fromFunction$4$$anonfun$apply$18(scala.Array$$anonfun$fromFunction$4, int);
  Signature: (Lscala/Array$$anonfun$fromFunction$4;I)V
  Code:
   Stack=2, Locals=3, Args_size=3
	aload_1
	ifnonnull	l1 // aload_0
	new	class java/lang/NullPointerException
	dup
	invokespecial	Method java/lang/NullPointerException."<init>":()V
	athrow
l1	aload_0
	aload_1
	putfield	Field $outer:Lscala/Array$$anonfun$fromFunction$4;
	aload_0
	iload_2
	putfield	Field i$14:I
	aload_0
	invokespecial	Method scala/runtime/AbstractFunction4."<init>":()V
	return
  Labels:
   	l1 = 12 // aload_0
  LocalVariableTable: 
   Start  Length  Slot  Name   Signature
   0      27      0    this       Lscala/Array$$anonfun$fromFunction$4$$anonfun$apply$18;
   0      27      1    $outer       Lscala/Array$$anonfun$fromFunction$4;


}

