Compiled from "Array.scala"
public final class scala.Array$$anonfun$concat$2 extends java.lang.Object implements scala.Function1,scala.ScalaObject,java.io.Serializable
  SourceFile: "Array.scala"
  Scala: length = 0x
   
  InnerClass: 
   public final #106= #12 of #105; //$anonfun$concat$2=class scala/Array$$anonfun$concat$2 of class scala/Array
  minor version: 0
  major version: 49
  Constant pool:
const #1 = Asciz	SourceFile;
const #2 = Asciz	Array.scala;
const #3 = Asciz	start$1;
const #4 = Asciz	Lscala/runtime/IntRef;;
const #5 = Asciz	result$1;
const #6 = Asciz	Lscala/runtime/BoxedArray;;
const #7 = Asciz	<init>;
const #8 = Asciz	(Lscala/runtime/BoxedArray;Lscala/runtime/IntRef;)V;
const #9 = Asciz	Code;
const #10 = Asciz	LineNumberTable;
const #11 = Asciz	scala/Array$$anonfun$concat$2;
const #12 = class	#11;	//  scala/Array$$anonfun$concat$2
const #13 = NameAndType	#5:#6;//  result$1:Lscala/runtime/BoxedArray;
const #14 = Field	#12.#13;	//  scala/Array$$anonfun$concat$2.result$1:Lscala/runtime/BoxedArray;
const #15 = NameAndType	#3:#4;//  start$1:Lscala/runtime/IntRef;
const #16 = Field	#12.#15;	//  scala/Array$$anonfun$concat$2.start$1:Lscala/runtime/IntRef;
const #17 = Asciz	java/lang/Object;
const #18 = class	#17;	//  java/lang/Object
const #19 = Asciz	()V;
const #20 = NameAndType	#7:#19;//  "<init>":()V
const #21 = Method	#18.#20;	//  java/lang/Object."<init>":()V
const #22 = Asciz	scala/Function1$class;
const #23 = class	#22;	//  scala/Function1$class
const #24 = Asciz	$init$;
const #25 = Asciz	(Lscala/Function1;)V;
const #26 = NameAndType	#24:#25;//  $init$:(Lscala/Function1;)V
const #27 = Method	#23.#26;	//  scala/Function1$class.$init$:(Lscala/Function1;)V
const #28 = Asciz	apply;
const #29 = Asciz	(Ljava/lang/Object;)Ljava/lang/Object;;
const #30 = Asciz	scala/collection/Sequence;
const #31 = class	#30;	//  scala/collection/Sequence
const #32 = Asciz	scala/runtime/ScalaRunTime$;
const #33 = class	#32;	//  scala/runtime/ScalaRunTime$
const #34 = Asciz	MODULE$;
const #35 = Asciz	Lscala/runtime/ScalaRunTime$;;
const #36 = NameAndType	#34:#35;//  MODULE$:Lscala/runtime/ScalaRunTime$;
const #37 = Field	#33.#36;	//  scala/runtime/ScalaRunTime$.MODULE$:Lscala/runtime/ScalaRunTime$;
const #38 = Asciz	boxArray;
const #39 = Asciz	(Ljava/lang/Object;)Lscala/runtime/BoxedArray;;
const #40 = NameAndType	#38:#39;//  boxArray:(Ljava/lang/Object;)Lscala/runtime/BoxedArray;
const #41 = Method	#33.#40;	//  scala/runtime/ScalaRunTime$.boxArray:(Ljava/lang/Object;)Lscala/runtime/BoxedArray;
const #42 = Asciz	(Lscala/collection/Sequence;)V;
const #43 = NameAndType	#28:#42;//  apply:(Lscala/collection/Sequence;)V
const #44 = Method	#12.#43;	//  scala/Array$$anonfun$concat$2.apply:(Lscala/collection/Sequence;)V
const #45 = Asciz	scala/runtime/BoxedUnit;
const #46 = class	#45;	//  scala/runtime/BoxedUnit
const #47 = Asciz	UNIT;
const #48 = Asciz	Lscala/runtime/BoxedUnit;;
const #49 = NameAndType	#47:#48;//  UNIT:Lscala/runtime/BoxedUnit;
const #50 = Field	#46.#49;	//  scala/runtime/BoxedUnit.UNIT:Lscala/runtime/BoxedUnit;
const #51 = Asciz	this;
const #52 = Asciz	Lscala/Array$$anonfun$concat$2;;
const #53 = Asciz	v1;
const #54 = Asciz	Ljava/lang/Object;;
const #55 = Asciz	LocalVariableTable;
const #56 = Asciz	scala/Array$;
const #57 = class	#56;	//  scala/Array$
const #58 = Asciz	Lscala/Array$;;
const #59 = NameAndType	#34:#58;//  MODULE$:Lscala/Array$;
const #60 = Field	#57.#59;	//  scala/Array$.MODULE$:Lscala/Array$;
const #61 = Asciz	scala/collection/generic/TraversableTemplate;
const #62 = class	#61;	//  scala/collection/generic/TraversableTemplate
const #63 = Asciz	toArray;
const #64 = Asciz	()Lscala/runtime/BoxedArray;;
const #65 = NameAndType	#63:#64;//  toArray:()Lscala/runtime/BoxedArray;
const #66 = InterfaceMethod	#62.#65;	//  scala/collection/generic/TraversableTemplate.toArray:()Lscala/runtime/BoxedArray;
const #67 = Asciz	scala/runtime/IntRef;
const #68 = class	#67;	//  scala/runtime/IntRef
const #69 = Asciz	elem;
const #70 = Asciz	I;
const #71 = NameAndType	#69:#70;//  elem:I
const #72 = Field	#68.#71;	//  scala/runtime/IntRef.elem:I
const #73 = Asciz	scala/collection/generic/SequenceTemplate;
const #74 = class	#73;	//  scala/collection/generic/SequenceTemplate
const #75 = Asciz	length;
const #76 = Asciz	()I;
const #77 = NameAndType	#75:#76;//  length:()I
const #78 = InterfaceMethod	#74.#77;	//  scala/collection/generic/SequenceTemplate.length:()I
const #79 = Asciz	copy;
const #80 = Asciz	(Ljava/lang/Object;ILjava/lang/Object;II)V;
const #81 = NameAndType	#79:#80;//  copy:(Ljava/lang/Object;ILjava/lang/Object;II)V
const #82 = Method	#57.#81;	//  scala/Array$.copy:(Ljava/lang/Object;ILjava/lang/Object;II)V
const #83 = Asciz	x;
const #84 = Asciz	Lscala/collection/Sequence;;
const #85 = Asciz	(Lscala/collection/Sequence<TT;>;)V;
const #86 = Asciz	Signature;
const #87 = Asciz	andThen;
const #88 = Asciz	(Lscala/Function1;)Lscala/Function1;;
const #89 = Asciz	(Lscala/Function1;Lscala/Function1;)Lscala/Function1;;
const #90 = NameAndType	#87:#89;//  andThen:(Lscala/Function1;Lscala/Function1;)Lscala/Function1;
const #91 = Method	#23.#90;	//  scala/Function1$class.andThen:(Lscala/Function1;Lscala/Function1;)Lscala/Function1;
const #92 = Asciz	g;
const #93 = Asciz	Lscala/Function1;;
const #94 = Asciz	compose;
const #95 = NameAndType	#94:#89;//  compose:(Lscala/Function1;Lscala/Function1;)Lscala/Function1;
const #96 = Method	#23.#95;	//  scala/Function1$class.compose:(Lscala/Function1;Lscala/Function1;)Lscala/Function1;
const #97 = Asciz	toString;
const #98 = Asciz	()Ljava/lang/String;;
const #99 = Asciz	(Lscala/Function1;)Ljava/lang/String;;
const #100 = NameAndType	#97:#99;//  toString:(Lscala/Function1;)Ljava/lang/String;
const #101 = Method	#23.#100;	//  scala/Function1$class.toString:(Lscala/Function1;)Ljava/lang/String;
const #102 = Asciz	Scala;
const #103 = Asciz	InnerClasses;
const #104 = Asciz	scala/Array;
const #105 = class	#104;	//  scala/Array
const #106 = Asciz	$anonfun$concat$2;
const #107 = Asciz	scala/Function1;
const #108 = class	#107;	//  scala/Function1
const #109 = Asciz	scala/ScalaObject;
const #110 = class	#109;	//  scala/ScalaObject
const #111 = Asciz	java/io/Serializable;
const #112 = class	#111;	//  java/io/Serializable

{
public scala.Array$$anonfun$concat$2(scala.runtime.BoxedArray, scala.runtime.IntRef);
  Code:
   Stack=2, Locals=3, Args_size=3
   0:	aload_0
   1:	aload_1
   2:	putfield	#14; //Field result$1:Lscala/runtime/BoxedArray;
   5:	aload_0
   6:	aload_2
   7:	putfield	#16; //Field start$1:Lscala/runtime/IntRef;
   10:	aload_0
   11:	invokespecial	#21; //Method java/lang/Object."<init>":()V
   14:	aload_0
   15:	invokestatic	#27; //Method scala/Function1$class.$init$:(Lscala/Function1;)V
   18:	return
  LineNumberTable: 
   line 77: 0


public final java.lang.Object apply(java.lang.Object);
  Code:
   Stack=3, Locals=2, Args_size=2
   0:	aload_0
   1:	aload_1
   2:	instanceof	#31; //class scala/collection/Sequence
   5:	ifeq	12
   8:	aload_1
   9:	goto	19
   12:	getstatic	#37; //Field scala/runtime/ScalaRunTime$.MODULE$:Lscala/runtime/ScalaRunTime$;
   15:	aload_1
   16:	invokevirtual	#41; //Method scala/runtime/ScalaRunTime$.boxArray:(Ljava/lang/Object;)Lscala/runtime/BoxedArray;
   19:	checkcast	#31; //class scala/collection/Sequence
   22:	invokevirtual	#44; //Method apply:(Lscala/collection/Sequence;)V
   25:	getstatic	#50; //Field scala/runtime/BoxedUnit.UNIT:Lscala/runtime/BoxedUnit;
   28:	areturn
  LineNumberTable: 
   line 77: 0

  LocalVariableTable: 
   Start  Length  Slot  Name   Signature
   0      29      0    this       Lscala/Array$$anonfun$concat$2;
   0      29      1    v1       Ljava/lang/Object;


public final void apply(scala.collection.Sequence);
  Code:
   Stack=6, Locals=2, Args_size=2
   0:	getstatic	#60; //Field scala/Array$.MODULE$:Lscala/Array$;
   3:	aload_1
   4:	invokeinterface	#66,  1; //InterfaceMethod scala/collection/generic/TraversableTemplate.toArray:()Lscala/runtime/BoxedArray;
   9:	iconst_0
   10:	aload_0
   11:	getfield	#14; //Field result$1:Lscala/runtime/BoxedArray;
   14:	aload_0
   15:	getfield	#16; //Field start$1:Lscala/runtime/IntRef;
   18:	getfield	#72; //Field scala/runtime/IntRef.elem:I
   21:	aload_1
   22:	invokeinterface	#78,  1; //InterfaceMethod scala/collection/generic/SequenceTemplate.length:()I
   27:	invokevirtual	#82; //Method scala/Array$.copy:(Ljava/lang/Object;ILjava/lang/Object;II)V
   30:	aload_0
   31:	getfield	#16; //Field start$1:Lscala/runtime/IntRef;
   34:	aload_0
   35:	getfield	#16; //Field start$1:Lscala/runtime/IntRef;
   38:	getfield	#72; //Field scala/runtime/IntRef.elem:I
   41:	aload_1
   42:	invokeinterface	#78,  1; //InterfaceMethod scala/collection/generic/SequenceTemplate.length:()I
   47:	iadd
   48:	putfield	#72; //Field scala/runtime/IntRef.elem:I
   51:	return
  LineNumberTable: 
   line 78: 0
   line 79: 30

  LocalVariableTable: 
   Start  Length  Slot  Name   Signature
   0      52      0    this       Lscala/Array$$anonfun$concat$2;
   0      52      1    x       Lscala/collection/Sequence;

  Signature: length = 0x2
   00 55 

public scala.Function1 andThen(scala.Function1);
  Code:
   Stack=2, Locals=2, Args_size=2
   0:	aload_0
   1:	aload_1
   2:	invokestatic	#91; //Method scala/Function1$class.andThen:(Lscala/Function1;Lscala/Function1;)Lscala/Function1;
   5:	areturn
  LineNumberTable: 
   line 77: 0

  LocalVariableTable: 
   Start  Length  Slot  Name   Signature
   0      6      0    this       Lscala/Array$$anonfun$concat$2;
   0      6      1    g       Lscala/Function1;


public scala.Function1 compose(scala.Function1);
  Code:
   Stack=2, Locals=2, Args_size=2
   0:	aload_0
   1:	aload_1
   2:	invokestatic	#96; //Method scala/Function1$class.compose:(Lscala/Function1;Lscala/Function1;)Lscala/Function1;
   5:	areturn
  LineNumberTable: 
   line 77: 0

  LocalVariableTable: 
   Start  Length  Slot  Name   Signature
   0      6      0    this       Lscala/Array$$anonfun$concat$2;
   0      6      1    g       Lscala/Function1;


public java.lang.String toString();
  Code:
   Stack=1, Locals=1, Args_size=1
   0:	aload_0
   1:	invokestatic	#101; //Method scala/Function1$class.toString:(Lscala/Function1;)Ljava/lang/String;
   4:	areturn
  LineNumberTable: 
   line 77: 0


}

