Compiled from "Array.scala"
public final class scala.Array$$anon$2 extends java.lang.Object implements scala.collection.generic.CanBuildFrom
  SourceFile: "Array.scala"
  Signature: length = 0x2
   00 2D 
  Scala: length = 0x
   
  InnerClass: 
   public final #50= #10 of #49; //$anon$2=class scala/Array$$anon$2 of class scala/Array
  minor version: 0
  major version: 49
  Constant pool:
const #1 = Asciz	SourceFile;
const #2 = Asciz	Array.scala;
const #3 = Asciz	m$1;
const #4 = Asciz	Lscala/reflect/ClassManifest;;
const #5 = Asciz	<init>;
const #6 = Asciz	(Lscala/reflect/ClassManifest;)V;
const #7 = Asciz	Code;
const #8 = Asciz	LineNumberTable;
const #9 = Asciz	scala/Array$$anon$2;
const #10 = class	#9;	//  scala/Array$$anon$2
const #11 = NameAndType	#3:#4;//  m$1:Lscala/reflect/ClassManifest;
const #12 = Field	#10.#11;	//  scala/Array$$anon$2.m$1:Lscala/reflect/ClassManifest;
const #13 = Asciz	java/lang/Object;
const #14 = class	#13;	//  java/lang/Object
const #15 = Asciz	()V;
const #16 = NameAndType	#5:#15;//  "<init>":()V
const #17 = Method	#14.#16;	//  java/lang/Object."<init>":()V
const #18 = Asciz	apply;
const #19 = Asciz	(Ljava/lang/Object;)Lscala/collection/mutable/Builder;;
const #20 = Asciz	(Ljava/lang/Object;)Lscala/collection/mutable/ArrayBuilder;;
const #21 = NameAndType	#18:#20;//  apply:(Ljava/lang/Object;)Lscala/collection/mutable/ArrayBuilder;
const #22 = Method	#10.#21;	//  scala/Array$$anon$2.apply:(Ljava/lang/Object;)Lscala/collection/mutable/ArrayBuilder;
const #23 = Asciz	this;
const #24 = Asciz	Lscala/Array$$anon$2;;
const #25 = Asciz	from;
const #26 = Asciz	Ljava/lang/Object;;
const #27 = Asciz	LocalVariableTable;
const #28 = Asciz	()Lscala/collection/mutable/Builder;;
const #29 = Asciz	()Lscala/collection/mutable/ArrayBuilder;;
const #30 = NameAndType	#18:#29;//  apply:()Lscala/collection/mutable/ArrayBuilder;
const #31 = Method	#10.#30;	//  scala/Array$$anon$2.apply:()Lscala/collection/mutable/ArrayBuilder;
const #32 = Asciz	scala/collection/mutable/ArrayBuilder$;
const #33 = class	#32;	//  scala/collection/mutable/ArrayBuilder$
const #34 = Asciz	MODULE$;
const #35 = Asciz	Lscala/collection/mutable/ArrayBuilder$;;
const #36 = NameAndType	#34:#35;//  MODULE$:Lscala/collection/mutable/ArrayBuilder$;
const #37 = Field	#33.#36;	//  scala/collection/mutable/ArrayBuilder$.MODULE$:Lscala/collection/mutable/ArrayBuilder$;
const #38 = Asciz	make;
const #39 = Asciz	(Lscala/reflect/ClassManifest;)Lscala/collection/mutable/ArrayBuilder;;
const #40 = NameAndType	#38:#39;//  make:(Lscala/reflect/ClassManifest;)Lscala/collection/mutable/ArrayBuilder;
const #41 = Method	#33.#40;	//  scala/collection/mutable/ArrayBuilder$.make:(Lscala/reflect/ClassManifest;)Lscala/collection/mutable/ArrayBuilder;
const #42 = Asciz	()Lscala/collection/mutable/ArrayBuilder<TT;>;;
const #43 = Asciz	Signature;
const #44 = Asciz	([Ljava/lang/Object;)Lscala/collection/mutable/ArrayBuilder<TT;>;;
const #45 = Asciz	Ljava/lang/Object;Lscala/collection/generic/CanBuildFrom<[Ljava/lang/Object;TT;[TT;>;;
const #46 = Asciz	Scala;
const #47 = Asciz	InnerClasses;
const #48 = Asciz	scala/Array;
const #49 = class	#48;	//  scala/Array
const #50 = Asciz	$anon$2;
const #51 = Asciz	scala/collection/generic/CanBuildFrom;
const #52 = class	#51;	//  scala/collection/generic/CanBuildFrom

{
public scala.Array$$anon$2(scala.reflect.ClassManifest);
  Code:
   Stack=2, Locals=2, Args_size=2
   0:	aload_0
   1:	aload_1
   2:	putfield	#12; //Field m$1:Lscala/reflect/ClassManifest;
   5:	aload_0
   6:	invokespecial	#17; //Method java/lang/Object."<init>":()V
   9:	return
  LineNumberTable: 
   line 46: 0


public scala.collection.mutable.Builder apply(java.lang.Object);
  Code:
   Stack=2, Locals=2, Args_size=2
   0:	aload_0
   1:	aload_1
   2:	invokevirtual	#22; //Method apply:(Ljava/lang/Object;)Lscala/collection/mutable/ArrayBuilder;
   5:	areturn
  LineNumberTable: 
   line 46: 0

  LocalVariableTable: 
   Start  Length  Slot  Name   Signature
   0      6      0    this       Lscala/Array$$anon$2;
   0      6      1    from       Ljava/lang/Object;


public scala.collection.mutable.Builder apply();
  Code:
   Stack=1, Locals=1, Args_size=1
   0:	aload_0
   1:	invokevirtual	#31; //Method apply:()Lscala/collection/mutable/ArrayBuilder;
   4:	areturn
  LineNumberTable: 
   line 46: 0


public scala.collection.mutable.ArrayBuilder apply();
  Code:
   Stack=2, Locals=1, Args_size=1
   0:	getstatic	#37; //Field scala/collection/mutable/ArrayBuilder$.MODULE$:Lscala/collection/mutable/ArrayBuilder$;
   3:	aload_0
   4:	getfield	#12; //Field m$1:Lscala/reflect/ClassManifest;
   7:	invokevirtual	#41; //Method scala/collection/mutable/ArrayBuilder$.make:(Lscala/reflect/ClassManifest;)Lscala/collection/mutable/ArrayBuilder;
   10:	areturn
  LineNumberTable: 
   line 48: 0

  Signature: length = 0x2
   00 2A 

public scala.collection.mutable.ArrayBuilder apply(java.lang.Object);
  Code:
   Stack=2, Locals=2, Args_size=2
   0:	getstatic	#37; //Field scala/collection/mutable/ArrayBuilder$.MODULE$:Lscala/collection/mutable/ArrayBuilder$;
   3:	aload_0
   4:	getfield	#12; //Field m$1:Lscala/reflect/ClassManifest;
   7:	invokevirtual	#41; //Method scala/collection/mutable/ArrayBuilder$.make:(Lscala/reflect/ClassManifest;)Lscala/collection/mutable/ArrayBuilder;
   10:	areturn
  LineNumberTable: 
   line 47: 0

  LocalVariableTable: 
   Start  Length  Slot  Name   Signature
   0      11      0    this       Lscala/Array$$anon$2;
   0      11      1    from       Ljava/lang/Object;

  Signature: length = 0x2
   00 2C 

}

