Compiled from "Array.scala"
public final class scala.Array$$anonfun$fromFunction$4 extends scala.runtime.AbstractFunction1 implements java.io.Serializable
  SourceFile: "Array.scala"
  Scala: length = 0x
   
  InnerClass: 
   public final $anonfun$fromFunction$2=class scala/Array$$anonfun$fromFunction$2 of class scala/Array
   public final $anonfun$fromFunction$3=class scala/Array$$anonfun$fromFunction$3 of class scala/Array
   public final $anonfun$fromFunction$4=class scala/Array$$anonfun$fromFunction$4 of class scala/Array
   public final $anonfun$apply$16=class scala/Array$$anonfun$fromFunction$2$$anonfun$apply$16 of class scala/Array$$anonfun$fromFunction$2
   public final $anonfun$apply$17=class scala/Array$$anonfun$fromFunction$3$$anonfun$apply$17 of class scala/Array$$anonfun$fromFunction$3
   public final $anonfun$apply$18=class scala/Array$$anonfun$fromFunction$4$$anonfun$apply$18 of class scala/Array$$anonfun$fromFunction$4
  minor version: 0
  major version: 49
  Constant pool:
Asciz	SourceFile;
Asciz	Array.scala;
Asciz	<clinit>;
Asciz	()V;
Asciz	Code;
Asciz	serialVersionUID;
Asciz	J;
Asciz	scala/Array$$anonfun$fromFunction$4;
class	scala/Array$$anonfun$fromFunction$4
NameAndType	serialVersionUID:J
Field	scala/Array$$anonfun$fromFunction$4.serialVersionUID:J
Asciz	evidence$25$1;
Asciz	Lscala/reflect/ClassManifest;;
Asciz	n5$4;
Asciz	I;
Asciz	n4$7;
Asciz	n3$10;
Asciz	n2$14;
Asciz	f$6;
Asciz	Lscala/Function5;;
Asciz	<init>;
Asciz	(Lscala/Function5;IIIILscala/reflect/ClassManifest;)V;
Asciz	LineNumberTable;
NameAndType	f$6:Lscala/Function5;
Field	scala/Array$$anonfun$fromFunction$4.f$6:Lscala/Function5;
NameAndType	n2$14:I
Field	scala/Array$$anonfun$fromFunction$4.n2$14:I
NameAndType	n3$10:I
Field	scala/Array$$anonfun$fromFunction$4.n3$10:I
NameAndType	n4$7:I
Field	scala/Array$$anonfun$fromFunction$4.n4$7:I
NameAndType	n5$4:I
Field	scala/Array$$anonfun$fromFunction$4.n5$4:I
NameAndType	evidence$25$1:Lscala/reflect/ClassManifest;
Field	scala/Array$$anonfun$fromFunction$4.evidence$25$1:Lscala/reflect/ClassManifest;
Asciz	scala/runtime/AbstractFunction1;
class	scala/runtime/AbstractFunction1
NameAndType	"<init>":()V
Method	scala/runtime/AbstractFunction1."<init>":()V
Asciz	apply;
Asciz	(Ljava/lang/Object;)Ljava/lang/Object;;
Asciz	scala/runtime/BoxesRunTime;
class	scala/runtime/BoxesRunTime
Asciz	unboxToInt;
Asciz	(Ljava/lang/Object;)I;
NameAndType	unboxToInt:(Ljava/lang/Object;)I
Method	scala/runtime/BoxesRunTime.unboxToInt:(Ljava/lang/Object;)I
Asciz	(I)[[[Ljava/lang/Object;;
NameAndType	apply:(I)[[[Ljava/lang/Object;
Method	scala/Array$$anonfun$fromFunction$4.apply:(I)[[[Ljava/lang/Object;
Asciz	this;
Asciz	Lscala/Array$$anonfun$fromFunction$4;;
Asciz	v1;
Asciz	Ljava/lang/Object;;
Asciz	LocalVariableTable;
Asciz	scala/Array$$anonfun$fromFunction$4$$anonfun$apply$18;
class	scala/Array$$anonfun$fromFunction$4$$anonfun$apply$18
Asciz	(Lscala/Array$$anonfun$fromFunction$4;I)V;
NameAndType	"<init>":(Lscala/Array$$anonfun$fromFunction$4;I)V
Method	scala/Array$$anonfun$fromFunction$4$$anonfun$apply$18."<init>":(Lscala/Array$$anonfun$fromFunction$4;I)V
Asciz	scala/Array$$anonfun$fromFunction$3;
class	scala/Array$$anonfun$fromFunction$3
Asciz	(Lscala/Function4;IIILscala/reflect/ClassManifest;)V;
NameAndType	"<init>":(Lscala/Function4;IIILscala/reflect/ClassManifest;)V
Method	scala/Array$$anonfun$fromFunction$3."<init>":(Lscala/Function4;IIILscala/reflect/ClassManifest;)V
Asciz	scala/reflect/ClassManifest$;
class	scala/reflect/ClassManifest$
Asciz	MODULE$;
Asciz	Lscala/reflect/ClassManifest$;;
NameAndType	MODULE$:Lscala/reflect/ClassManifest$;
Field	scala/reflect/ClassManifest$.MODULE$:Lscala/reflect/ClassManifest$;
Asciz	arrayType;
Asciz	(Lscala/reflect/OptManifest;)Lscala/reflect/ClassManifest;;
NameAndType	arrayType:(Lscala/reflect/OptManifest;)Lscala/reflect/ClassManifest;
Method	scala/reflect/ClassManifest$.arrayType:(Lscala/reflect/OptManifest;)Lscala/reflect/ClassManifest;
Asciz	scala/reflect/ClassManifest;
class	scala/reflect/ClassManifest
Asciz	newArray;
Asciz	(I)Ljava/lang/Object;;
NameAndType	newArray:(I)Ljava/lang/Object;
InterfaceMethod	scala/reflect/ClassManifest.newArray:(I)Ljava/lang/Object;
Asciz	scala/runtime/ScalaRunTime$;
class	scala/runtime/ScalaRunTime$
Asciz	Lscala/runtime/ScalaRunTime$;;
NameAndType	MODULE$:Lscala/runtime/ScalaRunTime$;
Field	scala/runtime/ScalaRunTime$.MODULE$:Lscala/runtime/ScalaRunTime$;
Asciz	scala/Array$$anonfun$fromFunction$3$$anonfun$apply$17;
class	scala/Array$$anonfun$fromFunction$3$$anonfun$apply$17
Asciz	(Lscala/Array$$anonfun$fromFunction$3;I)V;
NameAndType	"<init>":(Lscala/Array$$anonfun$fromFunction$3;I)V
Method	scala/Array$$anonfun$fromFunction$3$$anonfun$apply$17."<init>":(Lscala/Array$$anonfun$fromFunction$3;I)V
Asciz	scala/Array$$anonfun$fromFunction$2;
class	scala/Array$$anonfun$fromFunction$2
Asciz	(Lscala/Function3;IILscala/reflect/ClassManifest;)V;
NameAndType	"<init>":(Lscala/Function3;IILscala/reflect/ClassManifest;)V
Method	scala/Array$$anonfun$fromFunction$2."<init>":(Lscala/Function3;IILscala/reflect/ClassManifest;)V
Asciz	scala/Array$$anonfun$fromFunction$2$$anonfun$apply$16;
class	scala/Array$$anonfun$fromFunction$2$$anonfun$apply$16
Asciz	(Lscala/Array$$anonfun$fromFunction$2;I)V;
NameAndType	"<init>":(Lscala/Array$$anonfun$fromFunction$2;I)V
Method	scala/Array$$anonfun$fromFunction$2$$anonfun$apply$16."<init>":(Lscala/Array$$anonfun$fromFunction$2;I)V
Asciz	boxToInteger;
Asciz	(I)Ljava/lang/Integer;;
NameAndType	boxToInteger:(I)Ljava/lang/Integer;
Method	scala/runtime/BoxesRunTime.boxToInteger:(I)Ljava/lang/Integer;
Asciz	scala/Function2;
class	scala/Function2
Asciz	(Ljava/lang/Object;Ljava/lang/Object;)Ljava/lang/Object;;
NameAndType	apply:(Ljava/lang/Object;Ljava/lang/Object;)Ljava/lang/Object;
InterfaceMethod	scala/Function2.apply:(Ljava/lang/Object;Ljava/lang/Object;)Ljava/lang/Object;
Asciz	array_update;
Asciz	(Ljava/lang/Object;ILjava/lang/Object;)V;
NameAndType	array_update:(Ljava/lang/Object;ILjava/lang/Object;)V
Method	scala/runtime/ScalaRunTime$.array_update:(Ljava/lang/Object;ILjava/lang/Object;)V
Asciz	[Ljava/lang/Object;;
class	"[Ljava/lang/Object;"
Asciz	[[Ljava/lang/Object;;
class	"[[Ljava/lang/Object;"
Asciz	[[[Ljava/lang/Object;;
class	"[[[Ljava/lang/Object;"
Asciz	i$14;
Asciz	f$70;
Asciz	Lscala/Function4;;
Asciz	evidence$210;
Asciz	n10;
Asciz	f0;
Asciz	Lscala/Function1;;
Asciz	i$130;
Asciz	n2$150;
Asciz	f$800;
Asciz	Lscala/Function3;;
Asciz	n2$1600;
Asciz	n3$1200;
Asciz	evidence$23$100;
Asciz	evidence$2100;
Asciz	n100;
Asciz	f00;
Asciz	i$1200;
Asciz	n3$110;
Asciz	evidence$22$1000;
Asciz	evidence$21000;
Asciz	n1000;
Asciz	n4$80;
Asciz	evidence$24$10;
Asciz	evidence$21100;
Asciz	n110;
Asciz	f$5000;
Asciz	Lscala/Function2;;
Asciz	i$11000;
Asciz	i100;
Asciz	a100;
Asciz	i000;
Asciz	a000;
Asciz	i00;
Asciz	a00;
Asciz	i0;
Asciz	a0;
Asciz	(I)[[[[TT;;
Asciz	Signature;
Asciz	Scala;
Asciz	InnerClasses;
Asciz	scala/Array;
class	scala/Array
Asciz	$anonfun$fromFunction$2;
Asciz	$anonfun$fromFunction$3;
Asciz	$anonfun$fromFunction$4;
Asciz	$anonfun$apply$16;
Asciz	$anonfun$apply$17;
Asciz	$anonfun$apply$18;
Asciz	java/io/Serializable;
class	java/io/Serializable

{
public static final long serialVersionUID;
  Signature: J

public final scala.reflect.ClassManifest evidence$25$1;
  Signature: Lscala/reflect/ClassManifest;

public final int n5$4;
  Signature: I

public final int n4$7;
  Signature: I

public final int n3$10;
  Signature: I

public final int n2$14;
  Signature: I

public final scala.Function5 f$6;
  Signature: Lscala/Function5;

public static {};
  Signature: ()V
  Code:
   Stack=2, Locals=0, Args_size=0
	lconst_0
	putstatic	Field serialVersionUID:J
	return
  Labels:

public scala.Array$$anonfun$fromFunction$4(scala.Function5, int, int, int, int, scala.reflect.ClassManifest);
  Signature: (Lscala/Function5;IIIILscala/reflect/ClassManifest;)V
  Code:
   Stack=2, Locals=7, Args_size=7
	aload_0
	aload_1
	putfield	Field f$6:Lscala/Function5;
	aload_0
	iload_2
	putfield	Field n2$14:I
	aload_0
	iload_3
	putfield	Field n3$10:I
	aload_0
	iload	4
	putfield	Field n4$7:I
	aload_0
	iload	5
	putfield	Field n5$4:I
	aload_0
	aload	6
	putfield	Field evidence$25$1:Lscala/reflect/ClassManifest;
	aload_0
	invokespecial	Method scala/runtime/AbstractFunction1."<init>":()V
	return
  Labels:

public final java.lang.Object apply(java.lang.Object);
  Signature: (Ljava/lang/Object;)Ljava/lang/Object;
  Code:
   Stack=2, Locals=2, Args_size=2
	aload_0
	aload_1
	invokestatic	Method scala/runtime/BoxesRunTime.unboxToInt:(Ljava/lang/Object;)I
	invokevirtual	Method apply:(I)[[[Ljava/lang/Object;
	areturn
  Labels:
  LocalVariableTable: 
   Start  Length  Slot  Name   Signature
   0      9      0    this       Lscala/Array$$anonfun$fromFunction$4;
   0      9      1    v1       Ljava/lang/Object;


public final java.lang.Object[][][] apply(int);
  Signature: (I)[[[Ljava/lang/Object;
  Code:
   Stack=15, Locals=36, Args_size=2
	new	class scala/Array$$anonfun$fromFunction$4$$anonfun$apply$18
	dup
	aload_0
	iload_1
	invokespecial	Method scala/Array$$anonfun$fromFunction$4$$anonfun$apply$18."<init>":(Lscala/Array$$anonfun$fromFunction$4;I)V
	aload_0
	getfield	Field n2$14:I
	aload_0
	getfield	Field n3$10:I
	aload_0
	getfield	Field n4$7:I
	aload_0
	getfield	Field n5$4:I
	aload_0
	getfield	Field evidence$25$1:Lscala/reflect/ClassManifest;
	astore	21
	istore	20
	istore	16
	istore	7
	istore	4
	astore_2
	new	class scala/Array$$anonfun$fromFunction$3
	dup
	aload_2
	iload	7
	iload	16
	iload	20
	aload	21
	invokespecial	Method scala/Array$$anonfun$fromFunction$3."<init>":(Lscala/Function4;IIILscala/reflect/ClassManifest;)V
	getstatic	Field scala/reflect/ClassManifest$.MODULE$:Lscala/reflect/ClassManifest$;
	getstatic	Field scala/reflect/ClassManifest$.MODULE$:Lscala/reflect/ClassManifest$;
	getstatic	Field scala/reflect/ClassManifest$.MODULE$:Lscala/reflect/ClassManifest$;
	aload	21
	invokevirtual	Method scala/reflect/ClassManifest$.arrayType:(Lscala/reflect/OptManifest;)Lscala/reflect/ClassManifest;
	invokevirtual	Method scala/reflect/ClassManifest$.arrayType:(Lscala/reflect/OptManifest;)Lscala/reflect/ClassManifest;
	invokevirtual	Method scala/reflect/ClassManifest$.arrayType:(Lscala/reflect/OptManifest;)Lscala/reflect/ClassManifest;
	astore_3
	astore	5
	aload_3
	iload	4
	invokeinterface	InterfaceMethod scala/reflect/ClassManifest.newArray:(I)Ljava/lang/Object;
	astore	35
	iconst_0
	istore	34
l8	iload	34
	iload	4
	if_icmpge	l1 // aload
	getstatic	Field scala/runtime/ScalaRunTime$.MODULE$:Lscala/runtime/ScalaRunTime$;
	aload	35
	iload	34
	iload	34
	istore	6
	new	class scala/Array$$anonfun$fromFunction$3$$anonfun$apply$17
	dup
	aload	5
	iload	6
	invokespecial	Method scala/Array$$anonfun$fromFunction$3$$anonfun$apply$17."<init>":(Lscala/Array$$anonfun$fromFunction$3;I)V
	iload	7
	iload	16
	iload	20
	aload	21
	astore	11
	istore	10
	istore	9
	istore	13
	astore	8
	new	class scala/Array$$anonfun$fromFunction$2
	dup
	aload	8
	iload	9
	iload	10
	aload	11
	invokespecial	Method scala/Array$$anonfun$fromFunction$2."<init>":(Lscala/Function3;IILscala/reflect/ClassManifest;)V
	getstatic	Field scala/reflect/ClassManifest$.MODULE$:Lscala/reflect/ClassManifest$;
	getstatic	Field scala/reflect/ClassManifest$.MODULE$:Lscala/reflect/ClassManifest$;
	aload	11
	invokevirtual	Method scala/reflect/ClassManifest$.arrayType:(Lscala/reflect/OptManifest;)Lscala/reflect/ClassManifest;
	invokevirtual	Method scala/reflect/ClassManifest$.arrayType:(Lscala/reflect/OptManifest;)Lscala/reflect/ClassManifest;
	astore	12
	astore	14
	aload	12
	iload	13
	invokeinterface	InterfaceMethod scala/reflect/ClassManifest.newArray:(I)Ljava/lang/Object;
	astore	33
	iconst_0
	istore	32
l7	iload	32
	iload	13
	if_icmpge	l2 // aload
	getstatic	Field scala/runtime/ScalaRunTime$.MODULE$:Lscala/runtime/ScalaRunTime$;
	aload	33
	iload	32
	iload	32
	istore	15
	new	class scala/Array$$anonfun$fromFunction$2$$anonfun$apply$16
	dup
	aload	14
	iload	15
	invokespecial	Method scala/Array$$anonfun$fromFunction$2$$anonfun$apply$16."<init>":(Lscala/Array$$anonfun$fromFunction$2;I)V
	iload	16
	aload	21
	astore	17
	istore	19
	astore	24
	getstatic	Field scala/reflect/ClassManifest$.MODULE$:Lscala/reflect/ClassManifest$;
	aload	17
	invokevirtual	Method scala/reflect/ClassManifest$.arrayType:(Lscala/reflect/OptManifest;)Lscala/reflect/ClassManifest;
	astore	18
	aload	18
	iload	19
	invokeinterface	InterfaceMethod scala/reflect/ClassManifest.newArray:(I)Ljava/lang/Object;
	astore	31
	iconst_0
	istore	30
l6	iload	30
	iload	19
	if_icmpge	l3 // aload
	getstatic	Field scala/runtime/ScalaRunTime$.MODULE$:Lscala/runtime/ScalaRunTime$;
	aload	31
	iload	30
	iload	30
	istore	25
	iload	20
	aload	21
	astore	22
	istore	23
	aload	22
	iload	23
	invokeinterface	InterfaceMethod scala/reflect/ClassManifest.newArray:(I)Ljava/lang/Object;
	astore	29
	iconst_0
	istore	28
l5	iload	28
	iload	23
	if_icmpge	l4 // aload
	getstatic	Field scala/runtime/ScalaRunTime$.MODULE$:Lscala/runtime/ScalaRunTime$;
	aload	29
	iload	28
	iload	28
	istore	27
	aload	24
	iload	25
	istore	26
	iload	26
	invokestatic	Method scala/runtime/BoxesRunTime.boxToInteger:(I)Ljava/lang/Integer;
	iload	27
	invokestatic	Method scala/runtime/BoxesRunTime.boxToInteger:(I)Ljava/lang/Integer;
	invokeinterface	InterfaceMethod scala/Function2.apply:(Ljava/lang/Object;Ljava/lang/Object;)Ljava/lang/Object;
	invokevirtual	Method scala/runtime/ScalaRunTime$.array_update:(Ljava/lang/Object;ILjava/lang/Object;)V
	iload	28
	iconst_1
	iadd
	istore	28
	goto	l5 // iload
l4	aload	29
	invokevirtual	Method scala/runtime/ScalaRunTime$.array_update:(Ljava/lang/Object;ILjava/lang/Object;)V
	iload	30
	iconst_1
	iadd
	istore	30
	goto	l6 // iload
l3	aload	31
	checkcast	class "[Ljava/lang/Object;"
	invokevirtual	Method scala/runtime/ScalaRunTime$.array_update:(Ljava/lang/Object;ILjava/lang/Object;)V
	iload	32
	iconst_1
	iadd
	istore	32
	goto	l7 // iload
l2	aload	33
	checkcast	class "[[Ljava/lang/Object;"
	invokevirtual	Method scala/runtime/ScalaRunTime$.array_update:(Ljava/lang/Object;ILjava/lang/Object;)V
	iload	34
	iconst_1
	iadd
	istore	34
	goto	l8 // iload
l1	aload	35
	checkcast	class "[[[Ljava/lang/Object;"
	areturn
  Labels:
   	l8 = 92 // iload
   	l7 = 186 // iload
   	l6 = 249 // iload
   	l5 = 289 // iload
   	l4 = 340 // aload
   	l3 = 354 // aload
   	l2 = 371 // aload
   	l1 = 388 // aload
  LocalVariableTable: 
   Start  Length  Slot  Name   Signature
   0      394      0    this       Lscala/Array$$anonfun$fromFunction$4;
   0      394      1    i$14       I
   92      302      2    f$70       Lscala/Function4;
   92      302      3    evidence$210       Lscala/reflect/ClassManifest;
   92      302      4    n10       I
   92      302      5    f0       Lscala/Function1;
   186      202      6    i$130       I
   92      302      7    n2$150       I
   186      202      8    f$800       Lscala/Function3;
   186      202      9    n2$1600       I
   186      202      10    n3$1200       I
   186      202      11    evidence$23$100       Lscala/reflect/ClassManifest;
   186      202      12    evidence$2100       Lscala/reflect/ClassManifest;
   186      202      13    n100       I
   186      202      14    f00       Lscala/Function1;
   249      122      15    i$1200       I
   92      302      16    n3$110       I
   249      122      17    evidence$22$1000       Lscala/reflect/ClassManifest;
   249      122      18    evidence$21000       Lscala/reflect/ClassManifest;
   249      122      19    n1000       I
   92      302      20    n4$80       I
   92      302      21    evidence$24$10       Lscala/reflect/ClassManifest;
   289      65      22    evidence$21100       Lscala/reflect/ClassManifest;
   289      65      23    n110       I
   249      122      24    f$5000       Lscala/Function2;
   289      65      25    i$11000       I
   289      53      28    i100       I
   286      56      29    a100       Ljava/lang/Object;
   249      107      30    i000       I
   246      110      31    a000       Ljava/lang/Object;
   186      187      32    i00       I
   183      190      33    a00       Ljava/lang/Object;
   92      298      34    i0       I
   89      301      35    a0       Ljava/lang/Object;

  Signature: length = 0x2
   00 FFFFFF9E 

}

