Compiled from "Array.scala"
public final class scala.Array$$anonfun$tabulate$3 extends scala.runtime.AbstractFunction1 implements java.io.Serializable
  SourceFile: "Array.scala"
  Scala: length = 0x
   
  InnerClass: 
   public final $anonfun$tabulate$2=class scala/Array$$anonfun$tabulate$2 of class scala/Array
   public final $anonfun$tabulate$3=class scala/Array$$anonfun$tabulate$3 of class scala/Array
   public final $anonfun$apply$12=class scala/Array$$anonfun$tabulate$2$$anonfun$apply$12 of class scala/Array$$anonfun$tabulate$2
   public final $anonfun$apply$13=class scala/Array$$anonfun$tabulate$3$$anonfun$apply$13 of class scala/Array$$anonfun$tabulate$3
  minor version: 0
  major version: 49
  Constant pool:
Asciz	SourceFile;
Asciz	Array.scala;
Asciz	<clinit>;
Asciz	()V;
Asciz	Code;
Asciz	serialVersionUID;
Asciz	J;
Asciz	scala/Array$$anonfun$tabulate$3;
class	scala/Array$$anonfun$tabulate$3
NameAndType	serialVersionUID:J
Field	scala/Array$$anonfun$tabulate$3.serialVersionUID:J
Asciz	n2$4;
Asciz	I;
Asciz	n3$3;
Asciz	n4$2;
Asciz	f$2;
Asciz	Lscala/Function4;;
Asciz	evidence$17$1;
Asciz	Lscala/reflect/ClassManifest;;
Asciz	apply;
Asciz	(I)[[Ljava/lang/Object;;
Asciz	LineNumberTable;
NameAndType	n2$4:I
Field	scala/Array$$anonfun$tabulate$3.n2$4:I
NameAndType	n3$3:I
Field	scala/Array$$anonfun$tabulate$3.n3$3:I
NameAndType	n4$2:I
Field	scala/Array$$anonfun$tabulate$3.n4$2:I
Asciz	scala/Array$$anonfun$tabulate$3$$anonfun$apply$13;
class	scala/Array$$anonfun$tabulate$3$$anonfun$apply$13
Asciz	<init>;
Asciz	(Lscala/Array$$anonfun$tabulate$3;I)V;
NameAndType	"<init>":(Lscala/Array$$anonfun$tabulate$3;I)V
Method	scala/Array$$anonfun$tabulate$3$$anonfun$apply$13."<init>":(Lscala/Array$$anonfun$tabulate$3;I)V
NameAndType	evidence$17$1:Lscala/reflect/ClassManifest;
Field	scala/Array$$anonfun$tabulate$3.evidence$17$1:Lscala/reflect/ClassManifest;
Asciz	scala/Array$$anonfun$tabulate$2;
class	scala/Array$$anonfun$tabulate$2
Asciz	(IILscala/Function3;Lscala/reflect/ClassManifest;)V;
NameAndType	"<init>":(IILscala/Function3;Lscala/reflect/ClassManifest;)V
Method	scala/Array$$anonfun$tabulate$2."<init>":(IILscala/Function3;Lscala/reflect/ClassManifest;)V
Asciz	scala/reflect/ClassManifest$;
class	scala/reflect/ClassManifest$
Asciz	MODULE$;
Asciz	Lscala/reflect/ClassManifest$;;
NameAndType	MODULE$:Lscala/reflect/ClassManifest$;
Field	scala/reflect/ClassManifest$.MODULE$:Lscala/reflect/ClassManifest$;
Asciz	arrayType;
Asciz	(Lscala/reflect/OptManifest;)Lscala/reflect/ClassManifest;;
NameAndType	arrayType:(Lscala/reflect/OptManifest;)Lscala/reflect/ClassManifest;
Method	scala/reflect/ClassManifest$.arrayType:(Lscala/reflect/OptManifest;)Lscala/reflect/ClassManifest;
Asciz	scala/reflect/ClassManifest;
class	scala/reflect/ClassManifest
Asciz	newArrayBuilder;
Asciz	()Lscala/collection/mutable/ArrayBuilder;;
NameAndType	newArrayBuilder:()Lscala/collection/mutable/ArrayBuilder;
InterfaceMethod	scala/reflect/ClassManifest.newArrayBuilder:()Lscala/collection/mutable/ArrayBuilder;
Asciz	scala/Array$$anonfun$tabulate$2$$anonfun$apply$12;
class	scala/Array$$anonfun$tabulate$2$$anonfun$apply$12
Asciz	(Lscala/Array$$anonfun$tabulate$2;I)V;
NameAndType	"<init>":(Lscala/Array$$anonfun$tabulate$2;I)V
Method	scala/Array$$anonfun$tabulate$2$$anonfun$apply$12."<init>":(Lscala/Array$$anonfun$tabulate$2;I)V
Asciz	scala/runtime/BoxesRunTime;
class	scala/runtime/BoxesRunTime
Asciz	boxToInteger;
Asciz	(I)Ljava/lang/Integer;;
NameAndType	boxToInteger:(I)Ljava/lang/Integer;
Method	scala/runtime/BoxesRunTime.boxToInteger:(I)Ljava/lang/Integer;
Asciz	scala/Function2;
class	scala/Function2
Asciz	(Ljava/lang/Object;Ljava/lang/Object;)Ljava/lang/Object;;
NameAndType	apply:(Ljava/lang/Object;Ljava/lang/Object;)Ljava/lang/Object;
InterfaceMethod	scala/Function2.apply:(Ljava/lang/Object;Ljava/lang/Object;)Ljava/lang/Object;
Asciz	scala/collection/mutable/Builder;
class	scala/collection/mutable/Builder
Asciz	$plus$eq;
Asciz	(Ljava/lang/Object;)Lscala/collection/mutable/Builder;;
NameAndType	$plus$eq:(Ljava/lang/Object;)Lscala/collection/mutable/Builder;
InterfaceMethod	scala/collection/mutable/Builder.$plus$eq:(Ljava/lang/Object;)Lscala/collection/mutable/Builder;
Asciz	result;
Asciz	()Ljava/lang/Object;;
NameAndType	result:()Ljava/lang/Object;
InterfaceMethod	scala/collection/mutable/Builder.result:()Ljava/lang/Object;
Asciz	[Ljava/lang/Object;;
class	"[Ljava/lang/Object;"
Asciz	[[Ljava/lang/Object;;
class	"[[Ljava/lang/Object;"
Asciz	this;
Asciz	Lscala/Array$$anonfun$tabulate$3;;
Asciz	i1$3;
Asciz	f$30;
Asciz	Lscala/Function3;;
Asciz	evidence$140;
Asciz	n10;
Asciz	n2$50;
Asciz	f0;
Asciz	Lscala/Function1;;
Asciz	i1$20;
Asciz	evidence$15$100;
Asciz	evidence$1400;
Asciz	n100;
Asciz	n3$40;
Asciz	evidence$16$10;
Asciz	evidence$1410;
Asciz	n11;
Asciz	f$400;
Asciz	Lscala/Function2;;
Asciz	i1$100;
Asciz	i10;
Asciz	b10;
Asciz	Lscala/collection/mutable/ArrayBuilder;;
Asciz	i00;
Asciz	b00;
Asciz	i0;
Asciz	b0;
Asciz	LocalVariableTable;
Asciz	(I)[[[TT;;
Asciz	Signature;
Asciz	(Ljava/lang/Object;)Ljava/lang/Object;;
Asciz	unboxToInt;
Asciz	(Ljava/lang/Object;)I;
NameAndType	unboxToInt:(Ljava/lang/Object;)I
Method	scala/runtime/BoxesRunTime.unboxToInt:(Ljava/lang/Object;)I
NameAndType	apply:(I)[[Ljava/lang/Object;
Method	scala/Array$$anonfun$tabulate$3.apply:(I)[[Ljava/lang/Object;
Asciz	v1;
Asciz	Ljava/lang/Object;;
Asciz	(IIILscala/Function4;Lscala/reflect/ClassManifest;)V;
NameAndType	f$2:Lscala/Function4;
Field	scala/Array$$anonfun$tabulate$3.f$2:Lscala/Function4;
Asciz	scala/runtime/AbstractFunction1;
class	scala/runtime/AbstractFunction1
NameAndType	"<init>":()V
Method	scala/runtime/AbstractFunction1."<init>":()V
Asciz	Scala;
Asciz	InnerClasses;
Asciz	scala/Array;
class	scala/Array
Asciz	$anonfun$tabulate$2;
Asciz	$anonfun$tabulate$3;
Asciz	$anonfun$apply$12;
Asciz	$anonfun$apply$13;
Asciz	java/io/Serializable;
class	java/io/Serializable

{
public static final long serialVersionUID;
  Signature: J

public final int n2$4;
  Signature: I

public final int n3$3;
  Signature: I

public final int n4$2;
  Signature: I

public final scala.Function4 f$2;
  Signature: Lscala/Function4;

public final scala.reflect.ClassManifest evidence$17$1;
  Signature: Lscala/reflect/ClassManifest;

public static {};
  Signature: ()V
  Code:
   Stack=2, Locals=0, Args_size=0
	lconst_0
	putstatic	Field serialVersionUID:J
	return
  Labels:

public final java.lang.Object[][] apply(int);
  Signature: (I)[[Ljava/lang/Object;
  Code:
   Stack=7, Locals=25, Args_size=2
	aload_0
	getfield	Field n2$4:I
	aload_0
	getfield	Field n3$3:I
	aload_0
	getfield	Field n4$2:I
	new	class scala/Array$$anonfun$tabulate$3$$anonfun$apply$13
	dup
	aload_0
	iload_1
	invokespecial	Method scala/Array$$anonfun$tabulate$3$$anonfun$apply$13."<init>":(Lscala/Array$$anonfun$tabulate$3;I)V
	aload_0
	getfield	Field evidence$17$1:Lscala/reflect/ClassManifest;
	astore	12
	astore_2
	istore	11
	istore	5
	istore	4
	new	class scala/Array$$anonfun$tabulate$2
	dup
	iload	5
	iload	11
	aload_2
	aload	12
	invokespecial	Method scala/Array$$anonfun$tabulate$2."<init>":(IILscala/Function3;Lscala/reflect/ClassManifest;)V
	getstatic	Field scala/reflect/ClassManifest$.MODULE$:Lscala/reflect/ClassManifest$;
	getstatic	Field scala/reflect/ClassManifest$.MODULE$:Lscala/reflect/ClassManifest$;
	aload	12
	invokevirtual	Method scala/reflect/ClassManifest$.arrayType:(Lscala/reflect/OptManifest;)Lscala/reflect/ClassManifest;
	invokevirtual	Method scala/reflect/ClassManifest$.arrayType:(Lscala/reflect/OptManifest;)Lscala/reflect/ClassManifest;
	astore_3
	astore	6
	aload_3
	checkcast	class scala/reflect/ClassManifest
	invokeinterface	InterfaceMethod scala/reflect/ClassManifest.newArrayBuilder:()Lscala/collection/mutable/ArrayBuilder;
	astore	24
	iconst_0
	istore	23
l6	iload	23
	iload	4
	if_icmpge	l1 // aload
	aload	24
	iload	23
	istore	7
	iload	5
	new	class scala/Array$$anonfun$tabulate$2$$anonfun$apply$12
	dup
	aload	6
	iload	7
	invokespecial	Method scala/Array$$anonfun$tabulate$2$$anonfun$apply$12."<init>":(Lscala/Array$$anonfun$tabulate$2;I)V
	aload	12
	astore	8
	astore	15
	istore	10
	getstatic	Field scala/reflect/ClassManifest$.MODULE$:Lscala/reflect/ClassManifest$;
	aload	8
	invokevirtual	Method scala/reflect/ClassManifest$.arrayType:(Lscala/reflect/OptManifest;)Lscala/reflect/ClassManifest;
	astore	9
	aload	9
	checkcast	class scala/reflect/ClassManifest
	invokeinterface	InterfaceMethod scala/reflect/ClassManifest.newArrayBuilder:()Lscala/collection/mutable/ArrayBuilder;
	astore	22
	iconst_0
	istore	21
l5	iload	21
	iload	10
	if_icmpge	l2 // aload
	aload	22
	iload	21
	istore	16
	iload	11
	aload	12
	astore	13
	istore	14
	aload	13
	checkcast	class scala/reflect/ClassManifest
	invokeinterface	InterfaceMethod scala/reflect/ClassManifest.newArrayBuilder:()Lscala/collection/mutable/ArrayBuilder;
	astore	20
	iconst_0
	istore	19
l4	iload	19
	iload	14
	if_icmpge	l3 // aload
	aload	20
	iload	19
	istore	18
	aload	15
	iload	16
	istore	17
	iload	17
	invokestatic	Method scala/runtime/BoxesRunTime.boxToInteger:(I)Ljava/lang/Integer;
	iload	18
	invokestatic	Method scala/runtime/BoxesRunTime.boxToInteger:(I)Ljava/lang/Integer;
	invokeinterface	InterfaceMethod scala/Function2.apply:(Ljava/lang/Object;Ljava/lang/Object;)Ljava/lang/Object;
	invokeinterface	InterfaceMethod scala/collection/mutable/Builder.$plus$eq:(Ljava/lang/Object;)Lscala/collection/mutable/Builder;
	pop
	iload	19
	iconst_1
	iadd
	istore	19
	goto	l4 // iload
l3	aload	20
	invokeinterface	InterfaceMethod scala/collection/mutable/Builder.result:()Ljava/lang/Object;
	invokeinterface	InterfaceMethod scala/collection/mutable/Builder.$plus$eq:(Ljava/lang/Object;)Lscala/collection/mutable/Builder;
	pop
	iload	21
	iconst_1
	iadd
	istore	21
	goto	l5 // iload
l2	aload	22
	invokeinterface	InterfaceMethod scala/collection/mutable/Builder.result:()Ljava/lang/Object;
	checkcast	class "[Ljava/lang/Object;"
	invokeinterface	InterfaceMethod scala/collection/mutable/Builder.$plus$eq:(Ljava/lang/Object;)Lscala/collection/mutable/Builder;
	pop
	iload	23
	iconst_1
	iadd
	istore	23
	goto	l6 // iload
l1	aload	24
	invokeinterface	InterfaceMethod scala/collection/mutable/Builder.result:()Ljava/lang/Object;
	checkcast	class "[[Ljava/lang/Object;"
	areturn
  Labels:
   	l6 = 79 // iload
   	l5 = 138 // iload
   	l4 = 174 // iload
   	l3 = 223 // aload
   	l2 = 245 // aload
   	l1 = 270 // aload
  LocalVariableTable: 
   Start  Length  Slot  Name   Signature
   0      281      0    this       Lscala/Array$$anonfun$tabulate$3;
   0      281      1    i1$3       I
   79      202      2    f$30       Lscala/Function3;
   79      202      3    evidence$140       Lscala/reflect/ClassManifest;
   79      202      4    n10       I
   79      202      5    n2$50       I
   79      202      6    f0       Lscala/Function1;
   138      132      7    i1$20       I
   138      132      8    evidence$15$100       Lscala/reflect/ClassManifest;
   138      132      9    evidence$1400       Lscala/reflect/ClassManifest;
   138      132      10    n100       I
   79      202      11    n3$40       I
   79      202      12    evidence$16$10       Lscala/reflect/ClassManifest;
   174      71      13    evidence$1410       Lscala/reflect/ClassManifest;
   174      71      14    n11       I
   138      132      15    f$400       Lscala/Function2;
   174      71      16    i1$100       I
   174      56      19    i10       I
   171      59      20    b10       Lscala/collection/mutable/ArrayBuilder;
   138      114      21    i00       I
   135      117      22    b00       Lscala/collection/mutable/ArrayBuilder;
   79      198      23    i0       I
   76      201      24    b0       Lscala/collection/mutable/ArrayBuilder;

  Signature: length = 0x2
   00 75 

public final java.lang.Object apply(java.lang.Object);
  Signature: (Ljava/lang/Object;)Ljava/lang/Object;
  Code:
   Stack=2, Locals=2, Args_size=2
	aload_0
	aload_1
	invokestatic	Method scala/runtime/BoxesRunTime.unboxToInt:(Ljava/lang/Object;)I
	invokevirtual	Method apply:(I)[[Ljava/lang/Object;
	areturn
  Labels:
  LocalVariableTable: 
   Start  Length  Slot  Name   Signature
   0      9      0    this       Lscala/Array$$anonfun$tabulate$3;
   0      9      1    v1       Ljava/lang/Object;


public scala.Array$$anonfun$tabulate$3(int, int, int, scala.Function4, scala.reflect.ClassManifest);
  Signature: (IIILscala/Function4;Lscala/reflect/ClassManifest;)V
  Code:
   Stack=2, Locals=6, Args_size=6
	aload_0
	iload_1
	putfield	Field n2$4:I
	aload_0
	iload_2
	putfield	Field n3$3:I
	aload_0
	iload_3
	putfield	Field n4$2:I
	aload_0
	aload	4
	putfield	Field f$2:Lscala/Function4;
	aload_0
	aload	5
	putfield	Field evidence$17$1:Lscala/reflect/ClassManifest;
	aload_0
	invokespecial	Method scala/runtime/AbstractFunction1."<init>":()V
	return
  Labels:

}

