Compiled from "Array.scala"
public final class scala.Array$$anon$1 extends java.lang.Object implements scala.collection.generic.BuilderFactory
  SourceFile: "Array.scala"
  Signature: length = 0x2
   00 2F 
  Scala: length = 0x
   
  InnerClass: 
   public final #52= #26 of #51; //$anon$1=class scala/Array$$anon$1 of class scala/Array
  minor version: 0
  major version: 49
  Constant pool:
const #1 = Asciz	SourceFile;
const #2 = Asciz	Array.scala;
const #3 = Asciz	<init>;
const #4 = Asciz	()V;
const #5 = Asciz	Code;
const #6 = Asciz	LineNumberTable;
const #7 = Asciz	java/lang/Object;
const #8 = class	#7;	//  java/lang/Object
const #9 = NameAndType	#3:#4;//  "<init>":()V
const #10 = Method	#8.#9;	//  java/lang/Object."<init>":()V
const #11 = Asciz	apply;
const #12 = Asciz	(Ljava/lang/Object;)Lscala/collection/generic/Builder;;
const #13 = Asciz	scala/runtime/BoxedArray;
const #14 = class	#13;	//  scala/runtime/BoxedArray
const #15 = Asciz	scala/runtime/ScalaRunTime$;
const #16 = class	#15;	//  scala/runtime/ScalaRunTime$
const #17 = Asciz	MODULE$;
const #18 = Asciz	Lscala/runtime/ScalaRunTime$;;
const #19 = NameAndType	#17:#18;//  MODULE$:Lscala/runtime/ScalaRunTime$;
const #20 = Field	#16.#19;	//  scala/runtime/ScalaRunTime$.MODULE$:Lscala/runtime/ScalaRunTime$;
const #21 = Asciz	boxArray;
const #22 = Asciz	(Ljava/lang/Object;)Lscala/runtime/BoxedArray;;
const #23 = NameAndType	#21:#22;//  boxArray:(Ljava/lang/Object;)Lscala/runtime/BoxedArray;
const #24 = Method	#16.#23;	//  scala/runtime/ScalaRunTime$.boxArray:(Ljava/lang/Object;)Lscala/runtime/BoxedArray;
const #25 = Asciz	scala/Array$$anon$1;
const #26 = class	#25;	//  scala/Array$$anon$1
const #27 = Asciz	(Lscala/runtime/BoxedArray;)Lscala/collection/generic/Builder;;
const #28 = NameAndType	#11:#27;//  apply:(Lscala/runtime/BoxedArray;)Lscala/collection/generic/Builder;
const #29 = Method	#26.#28;	//  scala/Array$$anon$1.apply:(Lscala/runtime/BoxedArray;)Lscala/collection/generic/Builder;
const #30 = Asciz	this;
const #31 = Asciz	Lscala/Array$$anon$1;;
const #32 = Asciz	from;
const #33 = Asciz	Ljava/lang/Object;;
const #34 = Asciz	LocalVariableTable;
const #35 = Asciz	scala/Array$;
const #36 = class	#35;	//  scala/Array$
const #37 = Asciz	Lscala/Array$;;
const #38 = NameAndType	#17:#37;//  MODULE$:Lscala/Array$;
const #39 = Field	#36.#38;	//  scala/Array$.MODULE$:Lscala/Array$;
const #40 = Asciz	newBuilder;
const #41 = Asciz	()Lscala/collection/generic/Builder;;
const #42 = NameAndType	#40:#41;//  newBuilder:()Lscala/collection/generic/Builder;
const #43 = Method	#36.#42;	//  scala/Array$.newBuilder:()Lscala/collection/generic/Builder;
const #44 = Asciz	Lscala/runtime/BoxedArray;;
const #45 = Asciz	([Ljava/lang/Object;)Lscala/collection/generic/Builder<TA;[TA;>;;
const #46 = Asciz	Signature;
const #47 = Asciz	Ljava/lang/Object;Lscala/collection/generic/BuilderFactory<TA;[TA;[Ljava/lang/Object;>;;
const #48 = Asciz	Scala;
const #49 = Asciz	InnerClasses;
const #50 = Asciz	scala/Array;
const #51 = class	#50;	//  scala/Array
const #52 = Asciz	$anon$1;
const #53 = Asciz	scala/collection/generic/BuilderFactory;
const #54 = class	#53;	//  scala/collection/generic/BuilderFactory

{
public scala.Array$$anon$1();
  Code:
   Stack=1, Locals=1, Args_size=1
   0:	aload_0
   1:	invokespecial	#10; //Method java/lang/Object."<init>":()V
   4:	return
  LineNumberTable: 
   line 28: 0


public scala.collection.generic.Builder apply(java.lang.Object);
  Code:
   Stack=3, Locals=2, Args_size=2
   0:	aload_0
   1:	aload_1
   2:	instanceof	#14; //class scala/runtime/BoxedArray
   5:	ifeq	12
   8:	aload_1
   9:	goto	19
   12:	getstatic	#20; //Field scala/runtime/ScalaRunTime$.MODULE$:Lscala/runtime/ScalaRunTime$;
   15:	aload_1
   16:	invokevirtual	#24; //Method scala/runtime/ScalaRunTime$.boxArray:(Ljava/lang/Object;)Lscala/runtime/BoxedArray;
   19:	checkcast	#14; //class scala/runtime/BoxedArray
   22:	invokevirtual	#29; //Method apply:(Lscala/runtime/BoxedArray;)Lscala/collection/generic/Builder;
   25:	areturn
  LineNumberTable: 
   line 28: 0

  LocalVariableTable: 
   Start  Length  Slot  Name   Signature
   0      26      0    this       Lscala/Array$$anon$1;
   0      26      1    from       Ljava/lang/Object;


public scala.collection.generic.Builder apply(scala.runtime.BoxedArray);
  Code:
   Stack=1, Locals=2, Args_size=2
   0:	getstatic	#39; //Field scala/Array$.MODULE$:Lscala/Array$;
   3:	invokevirtual	#43; //Method scala/Array$.newBuilder:()Lscala/collection/generic/Builder;
   6:	areturn
  LineNumberTable: 
   line 28: 0

  LocalVariableTable: 
   Start  Length  Slot  Name   Signature
   0      7      0    this       Lscala/Array$$anon$1;
   0      7      1    from       Lscala/runtime/BoxedArray;

  Signature: length = 0x2
   00 2D 

}

