Compiled from "BigDecimal.scala"
public final class scala.BigDecimal$RoundingMode$ extends scala.Enumeration implements scala.ScalaObject,java.io.Serializable
  SourceFile: "BigDecimal.scala"
  Scala: length = 0x
   
  InnerClass: 
   public abstract #66= #90 of #60; //Value=class scala/Enumeration$Value of class scala/Enumeration
   public final #93= #40 of #92; //$anonfun$$init$$1=class scala/BigDecimal$RoundingMode$$anonfun$$init$$1 of class scala/BigDecimal$RoundingMode
  minor version: 0
  major version: 49
  Constant pool:
const #1 = Asciz	SourceFile;
const #2 = Asciz	BigDecimal.scala;
const #3 = Asciz	Scala;
const #4 = Asciz	MODULE$;
const #5 = Asciz	Lscala/BigDecimal$RoundingMode$;;
const #6 = Asciz	<clinit>;
const #7 = Asciz	()V;
const #8 = Asciz	Code;
const #9 = Asciz	scala/BigDecimal$RoundingMode$;
const #10 = class	#9;	//  scala/BigDecimal$RoundingMode$
const #11 = Asciz	<init>;
const #12 = NameAndType	#11:#7;//  "<init>":()V
const #13 = Method	#10.#12;	//  scala/BigDecimal$RoundingMode$."<init>":()V
const #14 = Asciz	UNNECESSARY;
const #15 = Asciz	Lscala/Enumeration$Value;;
const #16 = Asciz	HALF_EVEN;
const #17 = Asciz	HALF_DOWN;
const #18 = Asciz	HALF_UP;
const #19 = Asciz	FLOOR;
const #20 = Asciz	CEILING;
const #21 = Asciz	DOWN;
const #22 = Asciz	UP;
const #23 = Asciz	LineNumberTable;
const #24 = Asciz	scala/runtime/ScalaRunTime$;
const #25 = class	#24;	//  scala/runtime/ScalaRunTime$
const #26 = Asciz	Lscala/runtime/ScalaRunTime$;;
const #27 = NameAndType	#4:#26;//  MODULE$:Lscala/runtime/ScalaRunTime$;
const #28 = Field	#25.#27;	//  scala/runtime/ScalaRunTime$.MODULE$:Lscala/runtime/ScalaRunTime$;
const #29 = Asciz	java/math/RoundingMode;
const #30 = class	#29;	//  java/math/RoundingMode
const #31 = Asciz	values;
const #32 = Asciz	()[Ljava/math/RoundingMode;;
const #33 = NameAndType	#31:#32;//  values:()[Ljava/math/RoundingMode;
const #34 = Method	#30.#33;	//  java/math/RoundingMode.values:()[Ljava/math/RoundingMode;
const #35 = Asciz	boxArray;
const #36 = Asciz	(Ljava/lang/Object;)Lscala/runtime/BoxedArray;;
const #37 = NameAndType	#35:#36;//  boxArray:(Ljava/lang/Object;)Lscala/runtime/BoxedArray;
const #38 = Method	#25.#37;	//  scala/runtime/ScalaRunTime$.boxArray:(Ljava/lang/Object;)Lscala/runtime/BoxedArray;
const #39 = Asciz	scala/BigDecimal$RoundingMode$$anonfun$$init$$1;
const #40 = class	#39;	//  scala/BigDecimal$RoundingMode$$anonfun$$init$$1
const #41 = Method	#40.#12;	//  scala/BigDecimal$RoundingMode$$anonfun$$init$$1."<init>":()V
const #42 = Asciz	scala/Array$;
const #43 = class	#42;	//  scala/Array$
const #44 = Asciz	Lscala/Array$;;
const #45 = NameAndType	#4:#44;//  MODULE$:Lscala/Array$;
const #46 = Field	#43.#45;	//  scala/Array$.MODULE$:Lscala/Array$;
const #47 = Asciz	builderFactory;
const #48 = Asciz	()Lscala/collection/generic/BuilderFactory;;
const #49 = NameAndType	#47:#48;//  builderFactory:()Lscala/collection/generic/BuilderFactory;
const #50 = Method	#43.#49;	//  scala/Array$.builderFactory:()Lscala/collection/generic/BuilderFactory;
const #51 = Asciz	scala/collection/generic/TraversableTemplate;
const #52 = class	#51;	//  scala/collection/generic/TraversableTemplate
const #53 = Asciz	map;
const #54 = Asciz	(Lscala/Function1;Lscala/collection/generic/BuilderFactory;)Ljava/lang/Object;;
const #55 = NameAndType	#53:#54;//  map:(Lscala/Function1;Lscala/collection/generic/BuilderFactory;)Ljava/lang/Object;
const #56 = InterfaceMethod	#52.#55;	//  scala/collection/generic/TraversableTemplate.map:(Lscala/Function1;Lscala/collection/generic/BuilderFactory;)Ljava/lang/Object;
const #57 = Asciz	scala/collection/Sequence;
const #58 = class	#57;	//  scala/collection/Sequence
const #59 = Asciz	scala/Enumeration;
const #60 = class	#59;	//  scala/Enumeration
const #61 = Asciz	(Lscala/collection/Sequence;)V;
const #62 = NameAndType	#11:#61;//  "<init>":(Lscala/collection/Sequence;)V
const #63 = Method	#60.#62;	//  scala/Enumeration."<init>":(Lscala/collection/Sequence;)V
const #64 = NameAndType	#4:#5;//  MODULE$:Lscala/BigDecimal$RoundingMode$;
const #65 = Field	#10.#64;	//  scala/BigDecimal$RoundingMode$.MODULE$:Lscala/BigDecimal$RoundingMode$;
const #66 = Asciz	Value;
const #67 = Asciz	()Lscala/Enumeration$Value;;
const #68 = NameAndType	#66:#67;//  Value:()Lscala/Enumeration$Value;
const #69 = Method	#10.#68;	//  scala/BigDecimal$RoundingMode$.Value:()Lscala/Enumeration$Value;
const #70 = NameAndType	#22:#15;//  UP:Lscala/Enumeration$Value;
const #71 = Field	#10.#70;	//  scala/BigDecimal$RoundingMode$.UP:Lscala/Enumeration$Value;
const #72 = NameAndType	#21:#15;//  DOWN:Lscala/Enumeration$Value;
const #73 = Field	#10.#72;	//  scala/BigDecimal$RoundingMode$.DOWN:Lscala/Enumeration$Value;
const #74 = NameAndType	#20:#15;//  CEILING:Lscala/Enumeration$Value;
const #75 = Field	#10.#74;	//  scala/BigDecimal$RoundingMode$.CEILING:Lscala/Enumeration$Value;
const #76 = NameAndType	#19:#15;//  FLOOR:Lscala/Enumeration$Value;
const #77 = Field	#10.#76;	//  scala/BigDecimal$RoundingMode$.FLOOR:Lscala/Enumeration$Value;
const #78 = NameAndType	#18:#15;//  HALF_UP:Lscala/Enumeration$Value;
const #79 = Field	#10.#78;	//  scala/BigDecimal$RoundingMode$.HALF_UP:Lscala/Enumeration$Value;
const #80 = NameAndType	#17:#15;//  HALF_DOWN:Lscala/Enumeration$Value;
const #81 = Field	#10.#80;	//  scala/BigDecimal$RoundingMode$.HALF_DOWN:Lscala/Enumeration$Value;
const #82 = NameAndType	#16:#15;//  HALF_EVEN:Lscala/Enumeration$Value;
const #83 = Field	#10.#82;	//  scala/BigDecimal$RoundingMode$.HALF_EVEN:Lscala/Enumeration$Value;
const #84 = NameAndType	#14:#15;//  UNNECESSARY:Lscala/Enumeration$Value;
const #85 = Field	#10.#84;	//  scala/BigDecimal$RoundingMode$.UNNECESSARY:Lscala/Enumeration$Value;
const #86 = Asciz	readResolve;
const #87 = Asciz	()Ljava/lang/Object;;
const #88 = Asciz	InnerClasses;
const #89 = Asciz	scala/Enumeration$Value;
const #90 = class	#89;	//  scala/Enumeration$Value
const #91 = Asciz	scala/BigDecimal$RoundingMode;
const #92 = class	#91;	//  scala/BigDecimal$RoundingMode
const #93 = Asciz	$anonfun$$init$$1;
const #94 = Asciz	scala/ScalaObject;
const #95 = class	#94;	//  scala/ScalaObject
const #96 = Asciz	java/io/Serializable;
const #97 = class	#96;	//  java/io/Serializable

{
public static final scala.BigDecimal$RoundingMode$ MODULE$;

public static {};
  Code:
   Stack=1, Locals=0, Args_size=0
   0:	new	#10; //class scala/BigDecimal$RoundingMode$
   3:	invokespecial	#13; //Method "<init>":()V
   6:	return

public scala.BigDecimal$RoundingMode$();
  Code:
   Stack=4, Locals=2, Args_size=1
   0:	aload_0
   1:	getstatic	#28; //Field scala/runtime/ScalaRunTime$.MODULE$:Lscala/runtime/ScalaRunTime$;
   4:	invokestatic	#34; //Method java/math/RoundingMode.values:()[Ljava/math/RoundingMode;
   7:	invokevirtual	#38; //Method scala/runtime/ScalaRunTime$.boxArray:(Ljava/lang/Object;)Lscala/runtime/BoxedArray;
   10:	new	#40; //class scala/BigDecimal$RoundingMode$$anonfun$$init$$1
   13:	dup
   14:	invokespecial	#41; //Method scala/BigDecimal$RoundingMode$$anonfun$$init$$1."<init>":()V
   17:	getstatic	#46; //Field scala/Array$.MODULE$:Lscala/Array$;
   20:	invokevirtual	#50; //Method scala/Array$.builderFactory:()Lscala/collection/generic/BuilderFactory;
   23:	invokeinterface	#56,  3; //InterfaceMethod scala/collection/generic/TraversableTemplate.map:(Lscala/Function1;Lscala/collection/generic/BuilderFactory;)Ljava/lang/Object;
   28:	astore_1
   29:	aload_1
   30:	instanceof	#58; //class scala/collection/Sequence
   33:	ifeq	40
   36:	aload_1
   37:	goto	47
   40:	getstatic	#28; //Field scala/runtime/ScalaRunTime$.MODULE$:Lscala/runtime/ScalaRunTime$;
   43:	aload_1
   44:	invokevirtual	#38; //Method scala/runtime/ScalaRunTime$.boxArray:(Ljava/lang/Object;)Lscala/runtime/BoxedArray;
   47:	checkcast	#58; //class scala/collection/Sequence
   50:	invokespecial	#63; //Method scala/Enumeration."<init>":(Lscala/collection/Sequence;)V
   53:	aload_0
   54:	putstatic	#65; //Field MODULE$:Lscala/BigDecimal$RoundingMode$;
   57:	aload_0
   58:	aload_0
   59:	invokevirtual	#69; //Method Value:()Lscala/Enumeration$Value;
   62:	putfield	#71; //Field UP:Lscala/Enumeration$Value;
   65:	aload_0
   66:	aload_0
   67:	invokevirtual	#69; //Method Value:()Lscala/Enumeration$Value;
   70:	putfield	#73; //Field DOWN:Lscala/Enumeration$Value;
   73:	aload_0
   74:	aload_0
   75:	invokevirtual	#69; //Method Value:()Lscala/Enumeration$Value;
   78:	putfield	#75; //Field CEILING:Lscala/Enumeration$Value;
   81:	aload_0
   82:	aload_0
   83:	invokevirtual	#69; //Method Value:()Lscala/Enumeration$Value;
   86:	putfield	#77; //Field FLOOR:Lscala/Enumeration$Value;
   89:	aload_0
   90:	aload_0
   91:	invokevirtual	#69; //Method Value:()Lscala/Enumeration$Value;
   94:	putfield	#79; //Field HALF_UP:Lscala/Enumeration$Value;
   97:	aload_0
   98:	aload_0
   99:	invokevirtual	#69; //Method Value:()Lscala/Enumeration$Value;
   102:	putfield	#81; //Field HALF_DOWN:Lscala/Enumeration$Value;
   105:	aload_0
   106:	aload_0
   107:	invokevirtual	#69; //Method Value:()Lscala/Enumeration$Value;
   110:	putfield	#83; //Field HALF_EVEN:Lscala/Enumeration$Value;
   113:	aload_0
   114:	aload_0
   115:	invokevirtual	#69; //Method Value:()Lscala/Enumeration$Value;
   118:	putfield	#85; //Field UNNECESSARY:Lscala/Enumeration$Value;
   121:	return
  LineNumberTable: 
   line 23: 0
   line 25: 57


public java.lang.Object readResolve();
  Code:
   Stack=1, Locals=1, Args_size=1
   0:	getstatic	#65; //Field MODULE$:Lscala/BigDecimal$RoundingMode$;
   3:	areturn
  LineNumberTable: 
   line 23: 0


public scala.Enumeration$Value UNNECESSARY();
  Code:
   Stack=1, Locals=1, Args_size=1
   0:	aload_0
   1:	getfield	#85; //Field UNNECESSARY:Lscala/Enumeration$Value;
   4:	areturn
  LineNumberTable: 
   line 25: 0


public scala.Enumeration$Value HALF_EVEN();
  Code:
   Stack=1, Locals=1, Args_size=1
   0:	aload_0
   1:	getfield	#83; //Field HALF_EVEN:Lscala/Enumeration$Value;
   4:	areturn
  LineNumberTable: 
   line 25: 0


public scala.Enumeration$Value HALF_DOWN();
  Code:
   Stack=1, Locals=1, Args_size=1
   0:	aload_0
   1:	getfield	#81; //Field HALF_DOWN:Lscala/Enumeration$Value;
   4:	areturn
  LineNumberTable: 
   line 25: 0


public scala.Enumeration$Value HALF_UP();
  Code:
   Stack=1, Locals=1, Args_size=1
   0:	aload_0
   1:	getfield	#79; //Field HALF_UP:Lscala/Enumeration$Value;
   4:	areturn
  LineNumberTable: 
   line 25: 0


public scala.Enumeration$Value FLOOR();
  Code:
   Stack=1, Locals=1, Args_size=1
   0:	aload_0
   1:	getfield	#77; //Field FLOOR:Lscala/Enumeration$Value;
   4:	areturn
  LineNumberTable: 
   line 25: 0


public scala.Enumeration$Value CEILING();
  Code:
   Stack=1, Locals=1, Args_size=1
   0:	aload_0
   1:	getfield	#75; //Field CEILING:Lscala/Enumeration$Value;
   4:	areturn
  LineNumberTable: 
   line 25: 0


public scala.Enumeration$Value DOWN();
  Code:
   Stack=1, Locals=1, Args_size=1
   0:	aload_0
   1:	getfield	#73; //Field DOWN:Lscala/Enumeration$Value;
   4:	areturn
  LineNumberTable: 
   line 25: 0


public scala.Enumeration$Value UP();
  Code:
   Stack=1, Locals=1, Args_size=1
   0:	aload_0
   1:	getfield	#71; //Field UP:Lscala/Enumeration$Value;
   4:	areturn
  LineNumberTable: 
   line 25: 0


}

