Compiled from "BigDecimal.scala"
public final class scala.BigDecimal$ extends java.lang.Object implements scala.ScalaObject
  SourceFile: "BigDecimal.scala"
  Scala: length = 0x
   
  InnerClass: 
   public final #209= #208 of #88; //$anonfun$to$1=class scala/BigDecimal$$anonfun$to$1 of class scala/BigDecimal
   public final #212= #211 of #88; //$anonfun$until$1=class scala/BigDecimal$$anonfun$until$1 of class scala/BigDecimal
  minor version: 0
  major version: 49
  Constant pool:
const #1 = Asciz	SourceFile;
const #2 = Asciz	BigDecimal.scala;
const #3 = Asciz	Scala;
const #4 = Asciz	MODULE$;
const #5 = Asciz	Lscala/BigDecimal$;;
const #6 = Asciz	<clinit>;
const #7 = Asciz	()V;
const #8 = Asciz	Code;
const #9 = Asciz	scala/BigDecimal$;
const #10 = class	#9;	//  scala/BigDecimal$
const #11 = Asciz	<init>;
const #12 = NameAndType	#11:#7;//  "<init>":()V
const #13 = Method	#10.#12;	//  scala/BigDecimal$."<init>":()V
const #14 = Asciz	bitmap$0;
const #15 = Asciz	I;
const #16 = Asciz	defaultMathContext;
const #17 = Asciz	Ljava/math/MathContext;;
const #18 = Asciz	cache;
const #19 = Asciz	[Lscala/BigDecimal;;
const #20 = Asciz	maxCached;
const #21 = Asciz	minCached;
const #22 = Asciz	LineNumberTable;
const #23 = Asciz	java/lang/Object;
const #24 = class	#23;	//  java/lang/Object
const #25 = Method	#24.#12;	//  java/lang/Object."<init>":()V
const #26 = NameAndType	#4:#5;//  MODULE$:Lscala/BigDecimal$;
const #27 = Field	#10.#26;	//  scala/BigDecimal$.MODULE$:Lscala/BigDecimal$;
const #28 = int	-512;
const #29 = NameAndType	#21:#15;//  minCached:I
const #30 = Field	#10.#29;	//  scala/BigDecimal$.minCached:I
const #31 = int	512;
const #32 = NameAndType	#20:#15;//  maxCached:I
const #33 = Field	#10.#32;	//  scala/BigDecimal$.maxCached:I
const #34 = Asciz	java/math/MathContext;
const #35 = class	#34;	//  java/math/MathContext
const #36 = Asciz	UNLIMITED;
const #37 = NameAndType	#36:#17;//  UNLIMITED:Ljava/math/MathContext;
const #38 = Field	#35.#37;	//  java/math/MathContext.UNLIMITED:Ljava/math/MathContext;
const #39 = NameAndType	#16:#17;//  defaultMathContext:Ljava/math/MathContext;
const #40 = Field	#10.#39;	//  scala/BigDecimal$.defaultMathContext:Ljava/math/MathContext;
const #41 = Asciz	bigInt2bigDecimal;
const #42 = Asciz	(Lscala/BigInt;)Lscala/BigDecimal;;
const #43 = Asciz	apply;
const #44 = NameAndType	#43:#42;//  apply:(Lscala/BigInt;)Lscala/BigDecimal;
const #45 = Method	#10.#44;	//  scala/BigDecimal$.apply:(Lscala/BigInt;)Lscala/BigDecimal;
const #46 = Asciz	this;
const #47 = Asciz	x;
const #48 = Asciz	Lscala/BigInt;;
const #49 = Asciz	LocalVariableTable;
const #50 = Asciz	string2bigDecimal;
const #51 = Asciz	(Ljava/lang/String;)Lscala/BigDecimal;;
const #52 = NameAndType	#43:#51;//  apply:(Ljava/lang/String;)Lscala/BigDecimal;
const #53 = Method	#10.#52;	//  scala/BigDecimal$.apply:(Ljava/lang/String;)Lscala/BigDecimal;
const #54 = Asciz	s;
const #55 = Asciz	Ljava/lang/String;;
const #56 = Asciz	double2bigDecimal;
const #57 = Asciz	(D)Lscala/BigDecimal;;
const #58 = NameAndType	#43:#57;//  apply:(D)Lscala/BigDecimal;
const #59 = Method	#10.#58;	//  scala/BigDecimal$.apply:(D)Lscala/BigDecimal;
const #60 = Asciz	d;
const #61 = Asciz	D;
const #62 = Asciz	float2bigDecimal;
const #63 = Asciz	(F)Lscala/BigDecimal;;
const #64 = Asciz	scala/Predef$;
const #65 = class	#64;	//  scala/Predef$
const #66 = Asciz	Lscala/Predef$;;
const #67 = NameAndType	#4:#66;//  MODULE$:Lscala/Predef$;
const #68 = Field	#65.#67;	//  scala/Predef$.MODULE$:Lscala/Predef$;
const #69 = Asciz	float2double;
const #70 = Asciz	(F)D;
const #71 = NameAndType	#69:#70;//  float2double:(F)D
const #72 = Method	#65.#71;	//  scala/Predef$.float2double:(F)D
const #73 = Asciz	f;
const #74 = Asciz	F;
const #75 = Asciz	long2bigDecimal;
const #76 = Asciz	(J)Lscala/BigDecimal;;
const #77 = NameAndType	#43:#76;//  apply:(J)Lscala/BigDecimal;
const #78 = Method	#10.#77;	//  scala/BigDecimal$.apply:(J)Lscala/BigDecimal;
const #79 = Asciz	l;
const #80 = Asciz	J;
const #81 = Asciz	int2bigDecimal;
const #82 = Asciz	(I)Lscala/BigDecimal;;
const #83 = NameAndType	#43:#82;//  apply:(I)Lscala/BigDecimal;
const #84 = Method	#10.#83;	//  scala/BigDecimal$.apply:(I)Lscala/BigDecimal;
const #85 = Asciz	i;
const #86 = Asciz	(Ljava/math/BigDecimal;Ljava/math/MathContext;)Lscala/BigDecimal;;
const #87 = Asciz	scala/BigDecimal;
const #88 = class	#87;	//  scala/BigDecimal
const #89 = Asciz	(Ljava/math/BigDecimal;Ljava/math/MathContext;)V;
const #90 = NameAndType	#11:#89;//  "<init>":(Ljava/math/BigDecimal;Ljava/math/MathContext;)V
const #91 = Method	#88.#90;	//  scala/BigDecimal."<init>":(Ljava/math/BigDecimal;Ljava/math/MathContext;)V
const #92 = Asciz	bd;
const #93 = Asciz	Ljava/math/BigDecimal;;
const #94 = Asciz	mc;
const #95 = Asciz	(Ljava/math/BigDecimal;)Lscala/BigDecimal;;
const #96 = Asciz	()Ljava/math/MathContext;;
const #97 = NameAndType	#16:#96;//  defaultMathContext:()Ljava/math/MathContext;
const #98 = Method	#10.#97;	//  scala/BigDecimal$.defaultMathContext:()Ljava/math/MathContext;
const #99 = NameAndType	#43:#86;//  apply:(Ljava/math/BigDecimal;Ljava/math/MathContext;)Lscala/BigDecimal;
const #100 = Method	#10.#99;	//  scala/BigDecimal$.apply:(Ljava/math/BigDecimal;Ljava/math/MathContext;)Lscala/BigDecimal;
const #101 = Asciz	(Lscala/BigInt;ILjava/math/MathContext;)Lscala/BigDecimal;;
const #102 = Asciz	java/math/BigDecimal;
const #103 = class	#102;	//  java/math/BigDecimal
const #104 = Asciz	scala/BigInt;
const #105 = class	#104;	//  scala/BigInt
const #106 = Asciz	bigInteger;
const #107 = Asciz	()Ljava/math/BigInteger;;
const #108 = NameAndType	#106:#107;//  bigInteger:()Ljava/math/BigInteger;
const #109 = Method	#105.#108;	//  scala/BigInt.bigInteger:()Ljava/math/BigInteger;
const #110 = Asciz	(Ljava/math/BigInteger;ILjava/math/MathContext;)V;
const #111 = NameAndType	#11:#110;//  "<init>":(Ljava/math/BigInteger;ILjava/math/MathContext;)V
const #112 = Method	#103.#111;	//  java/math/BigDecimal."<init>":(Ljava/math/BigInteger;ILjava/math/MathContext;)V
const #113 = Asciz	unscaledVal;
const #114 = Asciz	scale;
const #115 = Asciz	(Lscala/BigInt;I)Lscala/BigDecimal;;
const #116 = NameAndType	#43:#101;//  apply:(Lscala/BigInt;ILjava/math/MathContext;)Lscala/BigDecimal;
const #117 = Method	#10.#116;	//  scala/BigDecimal$.apply:(Lscala/BigInt;ILjava/math/MathContext;)Lscala/BigDecimal;
const #118 = Asciz	(Lscala/BigInt;Ljava/math/MathContext;)Lscala/BigDecimal;;
const #119 = Asciz	(Ljava/math/BigInteger;Ljava/math/MathContext;)V;
const #120 = NameAndType	#11:#119;//  "<init>":(Ljava/math/BigInteger;Ljava/math/MathContext;)V
const #121 = Method	#103.#120;	//  java/math/BigDecimal."<init>":(Ljava/math/BigInteger;Ljava/math/MathContext;)V
const #122 = NameAndType	#43:#118;//  apply:(Lscala/BigInt;Ljava/math/MathContext;)Lscala/BigDecimal;
const #123 = Method	#10.#122;	//  scala/BigDecimal$.apply:(Lscala/BigInt;Ljava/math/MathContext;)Lscala/BigDecimal;
const #124 = Asciz	(Ljava/lang/String;Ljava/math/MathContext;)Lscala/BigDecimal;;
const #125 = Asciz	(Ljava/lang/String;Ljava/math/MathContext;)V;
const #126 = NameAndType	#11:#125;//  "<init>":(Ljava/lang/String;Ljava/math/MathContext;)V
const #127 = Method	#103.#126;	//  java/math/BigDecimal."<init>":(Ljava/lang/String;Ljava/math/MathContext;)V
const #128 = NameAndType	#43:#124;//  apply:(Ljava/lang/String;Ljava/math/MathContext;)Lscala/BigDecimal;
const #129 = Method	#10.#128;	//  scala/BigDecimal$.apply:(Ljava/lang/String;Ljava/math/MathContext;)Lscala/BigDecimal;
const #130 = Asciz	([CLjava/math/MathContext;)Lscala/BigDecimal;;
const #131 = Asciz	scala/runtime/ScalaRunTime$;
const #132 = class	#131;	//  scala/runtime/ScalaRunTime$
const #133 = Asciz	Lscala/runtime/ScalaRunTime$;;
const #134 = NameAndType	#4:#133;//  MODULE$:Lscala/runtime/ScalaRunTime$;
const #135 = Field	#132.#134;	//  scala/runtime/ScalaRunTime$.MODULE$:Lscala/runtime/ScalaRunTime$;
const #136 = Asciz	boxArray;
const #137 = Asciz	(Ljava/lang/Object;)Lscala/runtime/BoxedArray;;
const #138 = NameAndType	#136:#137;//  boxArray:(Ljava/lang/Object;)Lscala/runtime/BoxedArray;
const #139 = Method	#132.#138;	//  scala/runtime/ScalaRunTime$.boxArray:(Ljava/lang/Object;)Lscala/runtime/BoxedArray;
const #140 = Asciz	scala/collection/generic/SequenceTemplate;
const #141 = class	#140;	//  scala/collection/generic/SequenceTemplate
const #142 = Asciz	toString;
const #143 = Asciz	()Ljava/lang/String;;
const #144 = NameAndType	#142:#143;//  toString:()Ljava/lang/String;
const #145 = InterfaceMethod	#141.#144;	//  scala/collection/generic/SequenceTemplate.toString:()Ljava/lang/String;
const #146 = Asciz	[C;
const #147 = Asciz	([C)Lscala/BigDecimal;;
const #148 = NameAndType	#43:#130;//  apply:([CLjava/math/MathContext;)Lscala/BigDecimal;
const #149 = Method	#10.#148;	//  scala/BigDecimal$.apply:([CLjava/math/MathContext;)Lscala/BigDecimal;
const #150 = Asciz	(DLjava/math/MathContext;)Lscala/BigDecimal;;
const #151 = Asciz	java/lang/Double;
const #152 = class	#151;	//  java/lang/Double
const #153 = Asciz	(D)Ljava/lang/String;;
const #154 = NameAndType	#142:#153;//  toString:(D)Ljava/lang/String;
const #155 = Method	#152.#154;	//  java/lang/Double.toString:(D)Ljava/lang/String;
const #156 = NameAndType	#43:#150;//  apply:(DLjava/math/MathContext;)Lscala/BigDecimal;
const #157 = Method	#10.#156;	//  scala/BigDecimal$.apply:(DLjava/math/MathContext;)Lscala/BigDecimal;
const #158 = Asciz	(JILjava/math/MathContext;)Lscala/BigDecimal;;
const #159 = Asciz	scala/BigInt$;
const #160 = class	#159;	//  scala/BigInt$
const #161 = Asciz	Lscala/BigInt$;;
const #162 = NameAndType	#4:#161;//  MODULE$:Lscala/BigInt$;
const #163 = Field	#160.#162;	//  scala/BigInt$.MODULE$:Lscala/BigInt$;
const #164 = Asciz	(J)Lscala/BigInt;;
const #165 = NameAndType	#43:#164;//  apply:(J)Lscala/BigInt;
const #166 = Method	#160.#165;	//  scala/BigInt$.apply:(J)Lscala/BigInt;
const #167 = Asciz	(JI)Lscala/BigDecimal;;
const #168 = NameAndType	#43:#115;//  apply:(Lscala/BigInt;I)Lscala/BigDecimal;
const #169 = Method	#10.#168;	//  scala/BigDecimal$.apply:(Lscala/BigInt;I)Lscala/BigDecimal;
const #170 = Asciz	(JLjava/math/MathContext;)Lscala/BigDecimal;;
const #171 = Asciz	(JLjava/math/MathContext;)V;
const #172 = NameAndType	#11:#171;//  "<init>":(JLjava/math/MathContext;)V
const #173 = Method	#103.#172;	//  java/math/BigDecimal."<init>":(JLjava/math/MathContext;)V
const #174 = Asciz	()I;
const #175 = NameAndType	#21:#174;//  minCached:()I
const #176 = Method	#10.#175;	//  scala/BigDecimal$.minCached:()I
const #177 = NameAndType	#20:#174;//  maxCached:()I
const #178 = Method	#10.#177;	//  scala/BigDecimal$.maxCached:()I
const #179 = Asciz	valueOf;
const #180 = Asciz	(J)Ljava/math/BigDecimal;;
const #181 = NameAndType	#179:#180;//  valueOf:(J)Ljava/math/BigDecimal;
const #182 = Method	#103.#181;	//  java/math/BigDecimal.valueOf:(J)Ljava/math/BigDecimal;
const #183 = Asciz	(ILjava/math/MathContext;)Lscala/BigDecimal;;
const #184 = Asciz	()[Lscala/BigDecimal;;
const #185 = NameAndType	#18:#184;//  cache:()[Lscala/BigDecimal;
const #186 = Method	#10.#185;	//  scala/BigDecimal$.cache:()[Lscala/BigDecimal;
const #187 = Asciz	int2long;
const #188 = Asciz	(I)J;
const #189 = NameAndType	#187:#188;//  int2long:(I)J
const #190 = Method	#65.#189;	//  scala/Predef$.int2long:(I)J
const #191 = Asciz	offset;
const #192 = Asciz	n;
const #193 = Asciz	Lscala/BigDecimal;;
const #194 = NameAndType	#43:#183;//  apply:(ILjava/math/MathContext;)Lscala/BigDecimal;
const #195 = Method	#10.#194;	//  scala/BigDecimal$.apply:(ILjava/math/MathContext;)Lscala/BigDecimal;
const #196 = NameAndType	#14:#15;//  bitmap$0:I
const #197 = Field	#10.#196;	//  scala/BigDecimal$.bitmap$0:I
const #198 = NameAndType	#18:#19;//  cache:[Lscala/BigDecimal;
const #199 = Field	#10.#198;	//  scala/BigDecimal$.cache:[Lscala/BigDecimal;
const #200 = Asciz	scala/runtime/BoxedUnit;
const #201 = class	#200;	//  scala/runtime/BoxedUnit
const #202 = Asciz	UNIT;
const #203 = Asciz	Lscala/runtime/BoxedUnit;;
const #204 = NameAndType	#202:#203;//  UNIT:Lscala/runtime/BoxedUnit;
const #205 = Field	#201.#204;	//  scala/runtime/BoxedUnit.UNIT:Lscala/runtime/BoxedUnit;
const #206 = Asciz	InnerClasses;
const #207 = Asciz	scala/BigDecimal$$anonfun$to$1;
const #208 = class	#207;	//  scala/BigDecimal$$anonfun$to$1
const #209 = Asciz	$anonfun$to$1;
const #210 = Asciz	scala/BigDecimal$$anonfun$until$1;
const #211 = class	#210;	//  scala/BigDecimal$$anonfun$until$1
const #212 = Asciz	$anonfun$until$1;
const #213 = Asciz	scala/ScalaObject;
const #214 = class	#213;	//  scala/ScalaObject

{
public static final scala.BigDecimal$ MODULE$;

public volatile int bitmap$0;

public static {};
  Code:
   Stack=1, Locals=0, Args_size=0
   0:	new	#10; //class scala/BigDecimal$
   3:	invokespecial	#13; //Method "<init>":()V
   6:	return

public scala.BigDecimal bigInt2bigDecimal(scala.BigInt);
  Code:
   Stack=2, Locals=2, Args_size=2
   0:	aload_0
   1:	aload_1
   2:	invokevirtual	#45; //Method apply:(Lscala/BigInt;)Lscala/BigDecimal;
   5:	areturn
  LineNumberTable: 
   line 147: 0

  LocalVariableTable: 
   Start  Length  Slot  Name   Signature
   0      6      0    this       Lscala/BigDecimal$;
   0      6      1    x       Lscala/BigInt;


public scala.BigDecimal string2bigDecimal(java.lang.String);
  Code:
   Stack=2, Locals=2, Args_size=2
   0:	aload_0
   1:	aload_1
   2:	invokevirtual	#53; //Method apply:(Ljava/lang/String;)Lscala/BigDecimal;
   5:	areturn
  LineNumberTable: 
   line 142: 0

  LocalVariableTable: 
   Start  Length  Slot  Name   Signature
   0      6      0    this       Lscala/BigDecimal$;
   0      6      1    s       Ljava/lang/String;


public scala.BigDecimal double2bigDecimal(double);
  Code:
   Stack=3, Locals=3, Args_size=2
   0:	aload_0
   1:	dload_1
   2:	invokevirtual	#59; //Method apply:(D)Lscala/BigDecimal;
   5:	areturn
  LineNumberTable: 
   line 137: 0

  LocalVariableTable: 
   Start  Length  Slot  Name   Signature
   0      6      0    this       Lscala/BigDecimal$;
   0      6      1    d       D


public scala.BigDecimal float2bigDecimal(float);
  Code:
   Stack=3, Locals=2, Args_size=2
   0:	aload_0
   1:	getstatic	#68; //Field scala/Predef$.MODULE$:Lscala/Predef$;
   4:	fload_1
   5:	invokevirtual	#72; //Method scala/Predef$.float2double:(F)D
   8:	invokevirtual	#59; //Method apply:(D)Lscala/BigDecimal;
   11:	areturn
  LineNumberTable: 
   line 134: 0

  LocalVariableTable: 
   Start  Length  Slot  Name   Signature
   0      12      0    this       Lscala/BigDecimal$;
   0      12      1    f       F


public scala.BigDecimal long2bigDecimal(long);
  Code:
   Stack=3, Locals=3, Args_size=2
   0:	aload_0
   1:	lload_1
   2:	invokevirtual	#78; //Method apply:(J)Lscala/BigDecimal;
   5:	areturn
  LineNumberTable: 
   line 129: 0

  LocalVariableTable: 
   Start  Length  Slot  Name   Signature
   0      6      0    this       Lscala/BigDecimal$;
   0      6      1    l       J


public scala.BigDecimal int2bigDecimal(int);
  Code:
   Stack=2, Locals=2, Args_size=2
   0:	aload_0
   1:	iload_1
   2:	invokevirtual	#84; //Method apply:(I)Lscala/BigDecimal;
   5:	areturn
  LineNumberTable: 
   line 126: 0

  LocalVariableTable: 
   Start  Length  Slot  Name   Signature
   0      6      0    this       Lscala/BigDecimal$;
   0      6      1    i       I


public scala.BigDecimal apply(java.math.BigDecimal, java.math.MathContext);
  Code:
   Stack=4, Locals=3, Args_size=3
   0:	new	#88; //class scala/BigDecimal
   3:	dup
   4:	aload_1
   5:	aload_2
   6:	invokespecial	#91; //Method scala/BigDecimal."<init>":(Ljava/math/BigDecimal;Ljava/math/MathContext;)V
   9:	areturn
  LineNumberTable: 
   line 123: 0

  LocalVariableTable: 
   Start  Length  Slot  Name   Signature
   0      10      0    this       Lscala/BigDecimal$;
   0      10      1    bd       Ljava/math/BigDecimal;
   0      10      2    mc       Ljava/math/MathContext;


public scala.BigDecimal apply(java.math.BigDecimal);
  Code:
   Stack=3, Locals=2, Args_size=2
   0:	aload_0
   1:	aload_1
   2:	aload_0
   3:	invokevirtual	#98; //Method defaultMathContext:()Ljava/math/MathContext;
   6:	invokevirtual	#100; //Method apply:(Ljava/math/BigDecimal;Ljava/math/MathContext;)Lscala/BigDecimal;
   9:	areturn
  LineNumberTable: 
   line 122: 0

  LocalVariableTable: 
   Start  Length  Slot  Name   Signature
   0      10      0    this       Lscala/BigDecimal$;
   0      10      1    bd       Ljava/math/BigDecimal;


public scala.BigDecimal apply(scala.BigInt, int, java.math.MathContext);
  Code:
   Stack=7, Locals=4, Args_size=4
   0:	new	#88; //class scala/BigDecimal
   3:	dup
   4:	new	#103; //class java/math/BigDecimal
   7:	dup
   8:	aload_1
   9:	invokevirtual	#109; //Method scala/BigInt.bigInteger:()Ljava/math/BigInteger;
   12:	iload_2
   13:	aload_3
   14:	invokespecial	#112; //Method java/math/BigDecimal."<init>":(Ljava/math/BigInteger;ILjava/math/MathContext;)V
   17:	aload_3
   18:	invokespecial	#91; //Method scala/BigDecimal."<init>":(Ljava/math/BigDecimal;Ljava/math/MathContext;)V
   21:	areturn
  LineNumberTable: 
   line 120: 0

  LocalVariableTable: 
   Start  Length  Slot  Name   Signature
   0      22      0    this       Lscala/BigDecimal$;
   0      22      1    unscaledVal       Lscala/BigInt;
   0      22      2    scale       I
   0      22      3    mc       Ljava/math/MathContext;


public scala.BigDecimal apply(scala.BigInt, int);
  Code:
   Stack=4, Locals=3, Args_size=3
   0:	aload_0
   1:	aload_1
   2:	iload_2
   3:	aload_0
   4:	invokevirtual	#98; //Method defaultMathContext:()Ljava/math/MathContext;
   7:	invokevirtual	#117; //Method apply:(Lscala/BigInt;ILjava/math/MathContext;)Lscala/BigDecimal;
   10:	areturn
  LineNumberTable: 
   line 118: 0

  LocalVariableTable: 
   Start  Length  Slot  Name   Signature
   0      11      0    this       Lscala/BigDecimal$;
   0      11      1    unscaledVal       Lscala/BigInt;
   0      11      2    scale       I


public scala.BigDecimal apply(scala.BigInt, java.math.MathContext);
  Code:
   Stack=6, Locals=3, Args_size=3
   0:	new	#88; //class scala/BigDecimal
   3:	dup
   4:	new	#103; //class java/math/BigDecimal
   7:	dup
   8:	aload_1
   9:	invokevirtual	#109; //Method scala/BigInt.bigInteger:()Ljava/math/BigInteger;
   12:	aload_2
   13:	invokespecial	#121; //Method java/math/BigDecimal."<init>":(Ljava/math/BigInteger;Ljava/math/MathContext;)V
   16:	aload_2
   17:	invokespecial	#91; //Method scala/BigDecimal."<init>":(Ljava/math/BigDecimal;Ljava/math/MathContext;)V
   20:	areturn
  LineNumberTable: 
   line 109: 0

  LocalVariableTable: 
   Start  Length  Slot  Name   Signature
   0      21      0    this       Lscala/BigDecimal$;
   0      21      1    x       Lscala/BigInt;
   0      21      2    mc       Ljava/math/MathContext;


public scala.BigDecimal apply(scala.BigInt);
  Code:
   Stack=3, Locals=2, Args_size=2
   0:	aload_0
   1:	aload_1
   2:	aload_0
   3:	invokevirtual	#98; //Method defaultMathContext:()Ljava/math/MathContext;
   6:	invokevirtual	#123; //Method apply:(Lscala/BigInt;Ljava/math/MathContext;)Lscala/BigDecimal;
   9:	areturn
  LineNumberTable: 
   line 107: 0

  LocalVariableTable: 
   Start  Length  Slot  Name   Signature
   0      10      0    this       Lscala/BigDecimal$;
   0      10      1    x       Lscala/BigInt;


public scala.BigDecimal apply(java.lang.String, java.math.MathContext);
  Code:
   Stack=6, Locals=3, Args_size=3
   0:	new	#88; //class scala/BigDecimal
   3:	dup
   4:	new	#103; //class java/math/BigDecimal
   7:	dup
   8:	aload_1
   9:	aload_2
   10:	invokespecial	#127; //Method java/math/BigDecimal."<init>":(Ljava/lang/String;Ljava/math/MathContext;)V
   13:	aload_2
   14:	invokespecial	#91; //Method scala/BigDecimal."<init>":(Ljava/math/BigDecimal;Ljava/math/MathContext;)V
   17:	areturn
  LineNumberTable: 
   line 99: 0

  LocalVariableTable: 
   Start  Length  Slot  Name   Signature
   0      18      0    this       Lscala/BigDecimal$;
   0      18      1    x       Ljava/lang/String;
   0      18      2    mc       Ljava/math/MathContext;


public scala.BigDecimal apply(java.lang.String);
  Code:
   Stack=3, Locals=2, Args_size=2
   0:	aload_0
   1:	aload_1
   2:	aload_0
   3:	invokevirtual	#98; //Method defaultMathContext:()Ljava/math/MathContext;
   6:	invokevirtual	#129; //Method apply:(Ljava/lang/String;Ljava/math/MathContext;)Lscala/BigDecimal;
   9:	areturn
  LineNumberTable: 
   line 97: 0

  LocalVariableTable: 
   Start  Length  Slot  Name   Signature
   0      10      0    this       Lscala/BigDecimal$;
   0      10      1    x       Ljava/lang/String;


public scala.BigDecimal apply(char[], java.math.MathContext);
  Code:
   Stack=6, Locals=3, Args_size=3
   0:	new	#88; //class scala/BigDecimal
   3:	dup
   4:	new	#103; //class java/math/BigDecimal
   7:	dup
   8:	getstatic	#135; //Field scala/runtime/ScalaRunTime$.MODULE$:Lscala/runtime/ScalaRunTime$;
   11:	aload_1
   12:	invokevirtual	#139; //Method scala/runtime/ScalaRunTime$.boxArray:(Ljava/lang/Object;)Lscala/runtime/BoxedArray;
   15:	invokeinterface	#145,  1; //InterfaceMethod scala/collection/generic/SequenceTemplate.toString:()Ljava/lang/String;
   20:	aload_2
   21:	invokespecial	#127; //Method java/math/BigDecimal."<init>":(Ljava/lang/String;Ljava/math/MathContext;)V
   24:	aload_2
   25:	invokespecial	#91; //Method scala/BigDecimal."<init>":(Ljava/math/BigDecimal;Ljava/math/MathContext;)V
   28:	areturn
  LineNumberTable: 
   line 92: 0

  LocalVariableTable: 
   Start  Length  Slot  Name   Signature
   0      29      0    this       Lscala/BigDecimal$;
   0      29      1    x       [C
   0      29      2    mc       Ljava/math/MathContext;


public scala.BigDecimal apply(char[]);
  Code:
   Stack=3, Locals=2, Args_size=2
   0:	aload_0
   1:	aload_1
   2:	aload_0
   3:	invokevirtual	#98; //Method defaultMathContext:()Ljava/math/MathContext;
   6:	invokevirtual	#149; //Method apply:([CLjava/math/MathContext;)Lscala/BigDecimal;
   9:	areturn
  LineNumberTable: 
   line 90: 0

  LocalVariableTable: 
   Start  Length  Slot  Name   Signature
   0      10      0    this       Lscala/BigDecimal$;
   0      10      1    x       [C


public scala.BigDecimal apply(double, java.math.MathContext);
  Code:
   Stack=6, Locals=4, Args_size=3
   0:	new	#88; //class scala/BigDecimal
   3:	dup
   4:	new	#103; //class java/math/BigDecimal
   7:	dup
   8:	dload_1
   9:	invokestatic	#155; //Method java/lang/Double.toString:(D)Ljava/lang/String;
   12:	aload_3
   13:	invokespecial	#127; //Method java/math/BigDecimal."<init>":(Ljava/lang/String;Ljava/math/MathContext;)V
   16:	aload_3
   17:	invokespecial	#91; //Method scala/BigDecimal."<init>":(Ljava/math/BigDecimal;Ljava/math/MathContext;)V
   20:	areturn
  LineNumberTable: 
   line 85: 0

  LocalVariableTable: 
   Start  Length  Slot  Name   Signature
   0      21      0    this       Lscala/BigDecimal$;
   0      21      1    d       D
   0      21      3    mc       Ljava/math/MathContext;


public scala.BigDecimal apply(double);
  Code:
   Stack=4, Locals=3, Args_size=2
   0:	aload_0
   1:	dload_1
   2:	aload_0
   3:	invokevirtual	#98; //Method defaultMathContext:()Ljava/math/MathContext;
   6:	invokevirtual	#157; //Method apply:(DLjava/math/MathContext;)Lscala/BigDecimal;
   9:	areturn
  LineNumberTable: 
   line 81: 0

  LocalVariableTable: 
   Start  Length  Slot  Name   Signature
   0      10      0    this       Lscala/BigDecimal$;
   0      10      1    d       D


public scala.BigDecimal apply(long, int, java.math.MathContext);
  Code:
   Stack=4, Locals=5, Args_size=4
   0:	aload_0
   1:	getstatic	#163; //Field scala/BigInt$.MODULE$:Lscala/BigInt$;
   4:	lload_1
   5:	invokevirtual	#166; //Method scala/BigInt$.apply:(J)Lscala/BigInt;
   8:	iload_3
   9:	aload	4
   11:	invokevirtual	#117; //Method apply:(Lscala/BigInt;ILjava/math/MathContext;)Lscala/BigDecimal;
   14:	areturn
  LineNumberTable: 
   line 73: 0

  LocalVariableTable: 
   Start  Length  Slot  Name   Signature
   0      15      0    this       Lscala/BigDecimal$;
   0      15      1    unscaledVal       J
   0      15      3    scale       I
   0      15      4    mc       Ljava/math/MathContext;


public scala.BigDecimal apply(long, int);
  Code:
   Stack=4, Locals=4, Args_size=3
   0:	aload_0
   1:	getstatic	#163; //Field scala/BigInt$.MODULE$:Lscala/BigInt$;
   4:	lload_1
   5:	invokevirtual	#166; //Method scala/BigInt$.apply:(J)Lscala/BigInt;
   8:	iload_3
   9:	invokevirtual	#169; //Method apply:(Lscala/BigInt;I)Lscala/BigDecimal;
   12:	areturn
  LineNumberTable: 
   line 70: 0

  LocalVariableTable: 
   Start  Length  Slot  Name   Signature
   0      13      0    this       Lscala/BigDecimal$;
   0      13      1    unscaledVal       J
   0      13      3    scale       I


public scala.BigDecimal apply(long, java.math.MathContext);
  Code:
   Stack=7, Locals=4, Args_size=3
   0:	new	#88; //class scala/BigDecimal
   3:	dup
   4:	new	#103; //class java/math/BigDecimal
   7:	dup
   8:	lload_1
   9:	aload_3
   10:	invokespecial	#173; //Method java/math/BigDecimal."<init>":(JLjava/math/MathContext;)V
   13:	aload_3
   14:	invokespecial	#91; //Method scala/BigDecimal."<init>":(Ljava/math/BigDecimal;Ljava/math/MathContext;)V
   17:	areturn
  LineNumberTable: 
   line 60: 0

  LocalVariableTable: 
   Start  Length  Slot  Name   Signature
   0      18      0    this       Lscala/BigDecimal$;
   0      18      1    l       J
   0      18      3    mc       Ljava/math/MathContext;


public scala.BigDecimal apply(long);
  Code:
   Stack=4, Locals=3, Args_size=2
   0:	aload_0
   1:	invokespecial	#176; //Method minCached:()I
   4:	i2l
   5:	lload_1
   6:	lcmp
   7:	ifgt	29
   10:	lload_1
   11:	aload_0
   12:	invokespecial	#178; //Method maxCached:()I
   15:	i2l
   16:	lcmp
   17:	ifgt	29
   20:	aload_0
   21:	lload_1
   22:	l2i
   23:	invokevirtual	#84; //Method apply:(I)Lscala/BigDecimal;
   26:	goto	44
   29:	new	#88; //class scala/BigDecimal
   32:	dup
   33:	lload_1
   34:	invokestatic	#182; //Method java/math/BigDecimal.valueOf:(J)Ljava/math/BigDecimal;
   37:	aload_0
   38:	invokevirtual	#98; //Method defaultMathContext:()Ljava/math/MathContext;
   41:	invokespecial	#91; //Method scala/BigDecimal."<init>":(Ljava/math/BigDecimal;Ljava/math/MathContext;)V
   44:	areturn
  LineNumberTable: 
   line 56: 0
   line 57: 29
   line 56: 44

  LocalVariableTable: 
   Start  Length  Slot  Name   Signature
   0      45      0    this       Lscala/BigDecimal$;
   0      45      1    l       J


public scala.BigDecimal apply(int, java.math.MathContext);
  Code:
   Stack=4, Locals=5, Args_size=3
   0:	aload_0
   1:	invokespecial	#176; //Method minCached:()I
   4:	iload_1
   5:	if_icmpgt	69
   8:	iload_1
   9:	aload_0
   10:	invokespecial	#178; //Method maxCached:()I
   13:	if_icmpgt	69
   16:	iload_1
   17:	aload_0
   18:	invokespecial	#176; //Method minCached:()I
   21:	isub
   22:	istore_3
   23:	aload_0
   24:	invokespecial	#186; //Method cache:()[Lscala/BigDecimal;
   27:	iload_3
   28:	aaload
   29:	astore	4
   31:	aload	4
   33:	ifnonnull	64
   36:	new	#88; //class scala/BigDecimal
   39:	dup
   40:	getstatic	#68; //Field scala/Predef$.MODULE$:Lscala/Predef$;
   43:	iload_1
   44:	invokevirtual	#190; //Method scala/Predef$.int2long:(I)J
   47:	invokestatic	#182; //Method java/math/BigDecimal.valueOf:(J)Ljava/math/BigDecimal;
   50:	aload_2
   51:	invokespecial	#91; //Method scala/BigDecimal."<init>":(Ljava/math/BigDecimal;Ljava/math/MathContext;)V
   54:	astore	4
   56:	aload_0
   57:	invokespecial	#186; //Method cache:()[Lscala/BigDecimal;
   60:	iload_3
   61:	aload	4
   63:	aastore
   64:	aload	4
   66:	goto	87
   69:	new	#88; //class scala/BigDecimal
   72:	dup
   73:	getstatic	#68; //Field scala/Predef$.MODULE$:Lscala/Predef$;
   76:	iload_1
   77:	invokevirtual	#190; //Method scala/Predef$.int2long:(I)J
   80:	invokestatic	#182; //Method java/math/BigDecimal.valueOf:(J)Ljava/math/BigDecimal;
   83:	aload_2
   84:	invokespecial	#91; //Method scala/BigDecimal."<init>":(Ljava/math/BigDecimal;Ljava/math/MathContext;)V
   87:	areturn
  LineNumberTable: 
   line 42: 0
   line 43: 16
   line 44: 23
   line 45: 31
   line 46: 64
   line 47: 69
   line 42: 87

  LocalVariableTable: 
   Start  Length  Slot  Name   Signature
   0      88      0    this       Lscala/BigDecimal$;
   0      88      1    i       I
   0      88      2    mc       Ljava/math/MathContext;
   23      43      3    offset       I
   31      35      4    n       Lscala/BigDecimal;


public scala.BigDecimal apply(int);
  Code:
   Stack=3, Locals=2, Args_size=2
   0:	aload_0
   1:	iload_1
   2:	aload_0
   3:	invokevirtual	#98; //Method defaultMathContext:()Ljava/math/MathContext;
   6:	invokevirtual	#195; //Method apply:(ILjava/math/MathContext;)Lscala/BigDecimal;
   9:	areturn
  LineNumberTable: 
   line 40: 0

  LocalVariableTable: 
   Start  Length  Slot  Name   Signature
   0      10      0    this       Lscala/BigDecimal$;
   0      10      1    i       I


public java.math.MathContext defaultMathContext();
  Code:
   Stack=1, Locals=1, Args_size=1
   0:	aload_0
   1:	getfield	#40; //Field defaultMathContext:Ljava/math/MathContext;
   4:	areturn
  LineNumberTable: 
   line 32: 0


}

