Compiled from "BigInt.scala"
public final class scala.BigInt$ extends java.lang.Object implements scala.ScalaObject
  SourceFile: "BigInt.scala"
  Scala: length = 0x
   
  minor version: 0
  major version: 49
  Constant pool:
const #1 = Asciz	SourceFile;
const #2 = Asciz	BigInt.scala;
const #3 = Asciz	Scala;
const #4 = Asciz	MODULE$;
const #5 = Asciz	Lscala/BigInt$;;
const #6 = Asciz	<clinit>;
const #7 = Asciz	()V;
const #8 = Asciz	Code;
const #9 = Asciz	scala/BigInt$;
const #10 = class	#9;	//  scala/BigInt$
const #11 = Asciz	<init>;
const #12 = NameAndType	#11:#7;//  "<init>":()V
const #13 = Method	#10.#12;	//  scala/BigInt$."<init>":()V
const #14 = Asciz	cache;
const #15 = Asciz	[Lscala/BigInt;;
const #16 = Asciz	maxCached;
const #17 = Asciz	I;
const #18 = Asciz	minCached;
const #19 = Asciz	LineNumberTable;
const #20 = Asciz	java/lang/Object;
const #21 = class	#20;	//  java/lang/Object
const #22 = Method	#21.#12;	//  java/lang/Object."<init>":()V
const #23 = NameAndType	#4:#5;//  MODULE$:Lscala/BigInt$;
const #24 = Field	#10.#23;	//  scala/BigInt$.MODULE$:Lscala/BigInt$;
const #25 = int	-1024;
const #26 = NameAndType	#18:#17;//  minCached:I
const #27 = Field	#10.#26;	//  scala/BigInt$.minCached:I
const #28 = int	1024;
const #29 = NameAndType	#16:#17;//  maxCached:I
const #30 = Field	#10.#29;	//  scala/BigInt$.maxCached:I
const #31 = Asciz	()I;
const #32 = NameAndType	#16:#31;//  maxCached:()I
const #33 = Method	#10.#32;	//  scala/BigInt$.maxCached:()I
const #34 = NameAndType	#18:#31;//  minCached:()I
const #35 = Method	#10.#34;	//  scala/BigInt$.minCached:()I
const #36 = Asciz	scala/BigInt;
const #37 = class	#36;	//  scala/BigInt
const #38 = NameAndType	#14:#15;//  cache:[Lscala/BigInt;
const #39 = Field	#10.#38;	//  scala/BigInt$.cache:[Lscala/BigInt;
const #40 = Asciz	long2bigInt;
const #41 = Asciz	(J)Lscala/BigInt;;
const #42 = Asciz	apply;
const #43 = NameAndType	#42:#41;//  apply:(J)Lscala/BigInt;
const #44 = Method	#10.#43;	//  scala/BigInt$.apply:(J)Lscala/BigInt;
const #45 = Asciz	this;
const #46 = Asciz	l;
const #47 = Asciz	J;
const #48 = Asciz	LocalVariableTable;
const #49 = Asciz	int2bigInt;
const #50 = Asciz	(I)Lscala/BigInt;;
const #51 = NameAndType	#42:#50;//  apply:(I)Lscala/BigInt;
const #52 = Method	#10.#51;	//  scala/BigInt$.apply:(I)Lscala/BigInt;
const #53 = Asciz	i;
const #54 = Asciz	probablePrime;
const #55 = Asciz	(ILscala/util/Random;)Lscala/BigInt;;
const #56 = Asciz	scala/util/Random;
const #57 = class	#56;	//  scala/util/Random
const #58 = Asciz	self;
const #59 = Asciz	()Ljava/util/Random;;
const #60 = NameAndType	#58:#59;//  self:()Ljava/util/Random;
const #61 = Method	#57.#60;	//  scala/util/Random.self:()Ljava/util/Random;
const #62 = Asciz	java/math/BigInteger;
const #63 = class	#62;	//  java/math/BigInteger
const #64 = Asciz	(ILjava/util/Random;)Ljava/math/BigInteger;;
const #65 = NameAndType	#54:#64;//  probablePrime:(ILjava/util/Random;)Ljava/math/BigInteger;
const #66 = Method	#63.#65;	//  java/math/BigInteger.probablePrime:(ILjava/util/Random;)Ljava/math/BigInteger;
const #67 = Asciz	(Ljava/math/BigInteger;)V;
const #68 = NameAndType	#11:#67;//  "<init>":(Ljava/math/BigInteger;)V
const #69 = Method	#37.#68;	//  scala/BigInt."<init>":(Ljava/math/BigInteger;)V
const #70 = Asciz	bitLength;
const #71 = Asciz	rnd;
const #72 = Asciz	Lscala/util/Random;;
const #73 = Asciz	(Ljava/lang/String;I)Lscala/BigInt;;
const #74 = Asciz	(Ljava/lang/String;I)V;
const #75 = NameAndType	#11:#74;//  "<init>":(Ljava/lang/String;I)V
const #76 = Method	#63.#75;	//  java/math/BigInteger."<init>":(Ljava/lang/String;I)V
const #77 = Asciz	x;
const #78 = Asciz	Ljava/lang/String;;
const #79 = Asciz	radix;
const #80 = Asciz	(Ljava/lang/String;)Lscala/BigInt;;
const #81 = Asciz	(Ljava/lang/String;)V;
const #82 = NameAndType	#11:#81;//  "<init>":(Ljava/lang/String;)V
const #83 = Method	#63.#82;	//  java/math/BigInteger."<init>":(Ljava/lang/String;)V
const #84 = Asciz	(ILjava/util/Random;)V;
const #85 = NameAndType	#11:#84;//  "<init>":(ILjava/util/Random;)V
const #86 = Method	#63.#85;	//  java/math/BigInteger."<init>":(ILjava/util/Random;)V
const #87 = Asciz	numbits;
const #88 = Asciz	(IILscala/util/Random;)Lscala/BigInt;;
const #89 = Asciz	(IILjava/util/Random;)V;
const #90 = NameAndType	#11:#89;//  "<init>":(IILjava/util/Random;)V
const #91 = Method	#63.#90;	//  java/math/BigInteger."<init>":(IILjava/util/Random;)V
const #92 = Asciz	bitlength;
const #93 = Asciz	certainty;
const #94 = Asciz	(I[B)Lscala/BigInt;;
const #95 = Asciz	(I[B)V;
const #96 = NameAndType	#11:#95;//  "<init>":(I[B)V
const #97 = Method	#63.#96;	//  java/math/BigInteger."<init>":(I[B)V
const #98 = Asciz	signum;
const #99 = Asciz	magnitude;
const #100 = Asciz	[B;
const #101 = Asciz	([B)Lscala/BigInt;;
const #102 = Asciz	([B)V;
const #103 = NameAndType	#11:#102;//  "<init>":([B)V
const #104 = Method	#63.#103;	//  java/math/BigInteger."<init>":([B)V
const #105 = Asciz	valueOf;
const #106 = Asciz	(J)Ljava/math/BigInteger;;
const #107 = NameAndType	#105:#106;//  valueOf:(J)Ljava/math/BigInteger;
const #108 = Method	#63.#107;	//  java/math/BigInteger.valueOf:(J)Ljava/math/BigInteger;
const #109 = Asciz	()[Lscala/BigInt;;
const #110 = NameAndType	#14:#109;//  cache:()[Lscala/BigInt;
const #111 = Method	#10.#110;	//  scala/BigInt$.cache:()[Lscala/BigInt;
const #112 = Asciz	scala/Predef$;
const #113 = class	#112;	//  scala/Predef$
const #114 = Asciz	Lscala/Predef$;;
const #115 = NameAndType	#4:#114;//  MODULE$:Lscala/Predef$;
const #116 = Field	#113.#115;	//  scala/Predef$.MODULE$:Lscala/Predef$;
const #117 = Asciz	int2long;
const #118 = Asciz	(I)J;
const #119 = NameAndType	#117:#118;//  int2long:(I)J
const #120 = Method	#113.#119;	//  scala/Predef$.int2long:(I)J
const #121 = Asciz	offset;
const #122 = Asciz	n;
const #123 = Asciz	Lscala/BigInt;;
const #124 = Asciz	scala/ScalaObject;
const #125 = class	#124;	//  scala/ScalaObject

{
public static final scala.BigInt$ MODULE$;

public static {};
  Code:
   Stack=1, Locals=0, Args_size=0
   0:	new	#10; //class scala/BigInt$
   3:	invokespecial	#13; //Method "<init>":()V
   6:	return

public scala.BigInt long2bigInt(long);
  Code:
   Stack=3, Locals=3, Args_size=2
   0:	aload_0
   1:	lload_1
   2:	invokevirtual	#44; //Method apply:(J)Lscala/BigInt;
   5:	areturn
  LineNumberTable: 
   line 104: 0

  LocalVariableTable: 
   Start  Length  Slot  Name   Signature
   0      6      0    this       Lscala/BigInt$;
   0      6      1    l       J


public scala.BigInt int2bigInt(int);
  Code:
   Stack=2, Locals=2, Args_size=2
   0:	aload_0
   1:	iload_1
   2:	invokevirtual	#52; //Method apply:(I)Lscala/BigInt;
   5:	areturn
  LineNumberTable: 
   line 100: 0

  LocalVariableTable: 
   Start  Length  Slot  Name   Signature
   0      6      0    this       Lscala/BigInt$;
   0      6      1    i       I


public scala.BigInt probablePrime(int, scala.util.Random);
  Code:
   Stack=4, Locals=3, Args_size=3
   0:	new	#37; //class scala/BigInt
   3:	dup
   4:	iload_1
   5:	aload_2
   6:	invokevirtual	#61; //Method scala/util/Random.self:()Ljava/util/Random;
   9:	invokestatic	#66; //Method java/math/BigInteger.probablePrime:(ILjava/util/Random;)Ljava/math/BigInteger;
   12:	invokespecial	#69; //Method scala/BigInt."<init>":(Ljava/math/BigInteger;)V
   15:	areturn
  LineNumberTable: 
   line 96: 0

  LocalVariableTable: 
   Start  Length  Slot  Name   Signature
   0      16      0    this       Lscala/BigInt$;
   0      16      1    bitLength       I
   0      16      2    rnd       Lscala/util/Random;


public scala.BigInt apply(java.lang.String, int);
  Code:
   Stack=6, Locals=3, Args_size=3
   0:	new	#37; //class scala/BigInt
   3:	dup
   4:	new	#63; //class java/math/BigInteger
   7:	dup
   8:	aload_1
   9:	iload_2
   10:	invokespecial	#76; //Method java/math/BigInteger."<init>":(Ljava/lang/String;I)V
   13:	invokespecial	#69; //Method scala/BigInt."<init>":(Ljava/math/BigInteger;)V
   16:	areturn
  LineNumberTable: 
   line 91: 0

  LocalVariableTable: 
   Start  Length  Slot  Name   Signature
   0      17      0    this       Lscala/BigInt$;
   0      17      1    x       Ljava/lang/String;
   0      17      2    radix       I


public scala.BigInt apply(java.lang.String);
  Code:
   Stack=5, Locals=2, Args_size=2
   0:	new	#37; //class scala/BigInt
   3:	dup
   4:	new	#63; //class java/math/BigInteger
   7:	dup
   8:	aload_1
   9:	invokespecial	#83; //Method java/math/BigInteger."<init>":(Ljava/lang/String;)V
   12:	invokespecial	#69; //Method scala/BigInt."<init>":(Ljava/math/BigInteger;)V
   15:	areturn
  LineNumberTable: 
   line 81: 0

  LocalVariableTable: 
   Start  Length  Slot  Name   Signature
   0      16      0    this       Lscala/BigInt$;
   0      16      1    x       Ljava/lang/String;


public scala.BigInt apply(int, scala.util.Random);
  Code:
   Stack=6, Locals=3, Args_size=3
   0:	new	#37; //class scala/BigInt
   3:	dup
   4:	new	#63; //class java/math/BigInteger
   7:	dup
   8:	iload_1
   9:	aload_2
   10:	invokevirtual	#61; //Method scala/util/Random.self:()Ljava/util/Random;
   13:	invokespecial	#86; //Method java/math/BigInteger."<init>":(ILjava/util/Random;)V
   16:	invokespecial	#69; //Method scala/BigInt."<init>":(Ljava/math/BigInteger;)V
   19:	areturn
  LineNumberTable: 
   line 76: 0

  LocalVariableTable: 
   Start  Length  Slot  Name   Signature
   0      20      0    this       Lscala/BigInt$;
   0      20      1    numbits       I
   0      20      2    rnd       Lscala/util/Random;


public scala.BigInt apply(int, int, scala.util.Random);
  Code:
   Stack=7, Locals=4, Args_size=4
   0:	new	#37; //class scala/BigInt
   3:	dup
   4:	new	#63; //class java/math/BigInteger
   7:	dup
   8:	iload_1
   9:	iload_2
   10:	aload_3
   11:	invokevirtual	#61; //Method scala/util/Random.self:()Ljava/util/Random;
   14:	invokespecial	#91; //Method java/math/BigInteger."<init>":(IILjava/util/Random;)V
   17:	invokespecial	#69; //Method scala/BigInt."<init>":(Ljava/math/BigInteger;)V
   20:	areturn
  LineNumberTable: 
   line 66: 0

  LocalVariableTable: 
   Start  Length  Slot  Name   Signature
   0      21      0    this       Lscala/BigInt$;
   0      21      1    bitlength       I
   0      21      2    certainty       I
   0      21      3    rnd       Lscala/util/Random;


public scala.BigInt apply(int, byte[]);
  Code:
   Stack=6, Locals=3, Args_size=3
   0:	new	#37; //class scala/BigInt
   3:	dup
   4:	new	#63; //class java/math/BigInteger
   7:	dup
   8:	iload_1
   9:	aload_2
   10:	invokespecial	#97; //Method java/math/BigInteger."<init>":(I[B)V
   13:	invokespecial	#69; //Method scala/BigInt."<init>":(Ljava/math/BigInteger;)V
   16:	areturn
  LineNumberTable: 
   line 60: 0

  LocalVariableTable: 
   Start  Length  Slot  Name   Signature
   0      17      0    this       Lscala/BigInt$;
   0      17      1    signum       I
   0      17      2    magnitude       [B


public scala.BigInt apply(byte[]);
  Code:
   Stack=5, Locals=2, Args_size=2
   0:	new	#37; //class scala/BigInt
   3:	dup
   4:	new	#63; //class java/math/BigInteger
   7:	dup
   8:	aload_1
   9:	invokespecial	#104; //Method java/math/BigInteger."<init>":([B)V
   12:	invokespecial	#69; //Method scala/BigInt."<init>":(Ljava/math/BigInteger;)V
   15:	areturn
  LineNumberTable: 
   line 55: 0

  LocalVariableTable: 
   Start  Length  Slot  Name   Signature
   0      16      0    this       Lscala/BigInt$;
   0      16      1    x       [B


public scala.BigInt apply(long);
  Code:
   Stack=4, Locals=3, Args_size=2
   0:	aload_0
   1:	invokespecial	#35; //Method minCached:()I
   4:	i2l
   5:	lload_1
   6:	lcmp
   7:	ifgt	29
   10:	lload_1
   11:	aload_0
   12:	invokespecial	#33; //Method maxCached:()I
   15:	i2l
   16:	lcmp
   17:	ifgt	29
   20:	aload_0
   21:	lload_1
   22:	l2i
   23:	invokevirtual	#52; //Method apply:(I)Lscala/BigInt;
   26:	goto	40
   29:	new	#37; //class scala/BigInt
   32:	dup
   33:	lload_1
   34:	invokestatic	#108; //Method java/math/BigInteger.valueOf:(J)Ljava/math/BigInteger;
   37:	invokespecial	#69; //Method scala/BigInt."<init>":(Ljava/math/BigInteger;)V
   40:	areturn
  LineNumberTable: 
   line 48: 0
   line 49: 29
   line 48: 40

  LocalVariableTable: 
   Start  Length  Slot  Name   Signature
   0      41      0    this       Lscala/BigInt$;
   0      41      1    l       J


public scala.BigInt apply(int);
  Code:
   Stack=4, Locals=4, Args_size=2
   0:	aload_0
   1:	invokespecial	#35; //Method minCached:()I
   4:	iload_1
   5:	if_icmpgt	63
   8:	iload_1
   9:	aload_0
   10:	invokespecial	#33; //Method maxCached:()I
   13:	if_icmpgt	63
   16:	iload_1
   17:	aload_0
   18:	invokespecial	#35; //Method minCached:()I
   21:	isub
   22:	istore_2
   23:	aload_0
   24:	invokespecial	#111; //Method cache:()[Lscala/BigInt;
   27:	iload_2
   28:	aaload
   29:	astore_3
   30:	aload_3
   31:	ifnonnull	59
   34:	new	#37; //class scala/BigInt
   37:	dup
   38:	getstatic	#116; //Field scala/Predef$.MODULE$:Lscala/Predef$;
   41:	iload_1
   42:	invokevirtual	#120; //Method scala/Predef$.int2long:(I)J
   45:	invokestatic	#108; //Method java/math/BigInteger.valueOf:(J)Ljava/math/BigInteger;
   48:	invokespecial	#69; //Method scala/BigInt."<init>":(Ljava/math/BigInteger;)V
   51:	astore_3
   52:	aload_0
   53:	invokespecial	#111; //Method cache:()[Lscala/BigInt;
   56:	iload_2
   57:	aload_3
   58:	aastore
   59:	aload_3
   60:	goto	80
   63:	new	#37; //class scala/BigInt
   66:	dup
   67:	getstatic	#116; //Field scala/Predef$.MODULE$:Lscala/Predef$;
   70:	iload_1
   71:	invokevirtual	#120; //Method scala/Predef$.int2long:(I)J
   74:	invokestatic	#108; //Method java/math/BigInteger.valueOf:(J)Ljava/math/BigInteger;
   77:	invokespecial	#69; //Method scala/BigInt."<init>":(Ljava/math/BigInteger;)V
   80:	areturn
  LineNumberTable: 
   line 34: 0
   line 35: 16
   line 36: 23
   line 37: 30
   line 38: 59
   line 39: 63
   line 34: 80

  LocalVariableTable: 
   Start  Length  Slot  Name   Signature
   0      81      0    this       Lscala/BigInt$;
   0      81      1    i       I
   23      37      2    offset       I
   30      30      3    n       Lscala/BigInt;


}

