Compiled from "Collection.scala"
public abstract class scala.Collection$class extends java.lang.Object
  Scala: length = 0x
   
  SourceFile: "Collection.scala"
  minor version: 0
  major version: 49
  Constant pool:
int	36;
int	46;
String	(
String	)
String	, 
class	java/lang/Class
class	java/lang/Object
class	java/lang/String
class	scala/Collection
class	scala/Collection$class
class	scala/Iterable
class	scala/StringBuilder
Method	java/lang/Class.getName:()Ljava/lang/String;
Method	java/lang/Object.getClass:()Ljava/lang/Class;
Method	java/lang/String.indexOf:(I)I
Method	java/lang/String.lastIndexOf:(I)I
Method	java/lang/String.substring:(I)Ljava/lang/String;
Method	java/lang/String.substring:(II)Ljava/lang/String;
Method	scala/StringBuilder."<init>":()V
Method	scala/StringBuilder.append:(Ljava/lang/Object;)Lscala/StringBuilder;
Method	scala/StringBuilder.toString:()Ljava/lang/String;
InterfaceMethod	scala/Collection.stringPrefix:()Ljava/lang/String;
InterfaceMethod	scala/Iterable.mkString:(Ljava/lang/String;Ljava/lang/String;Ljava/lang/String;)Ljava/lang/String;
NameAndType	"<init>":()V
NameAndType	append:(Ljava/lang/Object;)Lscala/StringBuilder;
NameAndType	getClass:()Ljava/lang/Class;
NameAndType	getName:()Ljava/lang/String;
NameAndType	indexOf:(I)I
NameAndType	lastIndexOf:(I)I
NameAndType	mkString:(Ljava/lang/String;Ljava/lang/String;Ljava/lang/String;)Ljava/lang/String;
NameAndType	stringPrefix:()Ljava/lang/String;
NameAndType	substring:(I)Ljava/lang/String;
NameAndType	substring:(II)Ljava/lang/String;
NameAndType	toString:()Ljava/lang/String;
Asciz	$init$;
Asciz	$this;
Asciz	(;
Asciz	()Ljava/lang/Class;;
Asciz	()Ljava/lang/String;;
Asciz	()V;
Asciz	(I)I;
Asciz	(I)Ljava/lang/String;;
Asciz	(II)Ljava/lang/String;;
Asciz	(Ljava/lang/Object;)Lscala/StringBuilder;;
Asciz	(Ljava/lang/String;Ljava/lang/String;Ljava/lang/String;)Ljava/lang/String;;
Asciz	(Lscala/Collection;)Ljava/lang/String;;
Asciz	(Lscala/Collection;)V;
Asciz	);
Asciz	, ;
Asciz	<init>;
Asciz	Code;
Asciz	Collection.scala;
Asciz	I;
Asciz	LineNumberTable;
Asciz	Ljava/lang/String;;
Asciz	LocalVariableTable;
Asciz	Lscala/Collection;;
Asciz	Scala;
Asciz	SourceFile;
Asciz	append;
Asciz	getClass;
Asciz	getName;
Asciz	idx1;
Asciz	idx2;
Asciz	indexOf;
Asciz	java/lang/Class;
Asciz	java/lang/Object;
Asciz	java/lang/String;
Asciz	lastIndexOf;
Asciz	mkString;
Asciz	scala/Collection;
Asciz	scala/Collection$class;
Asciz	scala/Iterable;
Asciz	scala/StringBuilder;
Asciz	string;
Asciz	stringPrefix;
Asciz	substring;
Asciz	toString;

{
public static void $init$(scala.Collection);
  Signature: (Lscala/Collection;)V
  Code:
   Stack=0, Locals=1, Args_size=1
	return
  Labels:
  LocalVariableTable: 
   Start  Length  Slot  Name   Signature
   0      1      0    $this       Lscala/Collection;


public static java.lang.String stringPrefix(scala.Collection);
  Signature: (Lscala/Collection;)Ljava/lang/String;
  Code:
   Stack=3, Locals=4, Args_size=1
	aload_0
	invokevirtual	Method java/lang/Object.getClass:()Ljava/lang/Class;
	invokevirtual	Method java/lang/Class.getName:()Ljava/lang/String;
	astore_1
	aload_1
	ldc	int 46
	invokevirtual	Method java/lang/String.lastIndexOf:(I)I
	istore_2
	iload_2
	iconst_m1
	if_icmpeq	l1 // aload_1
	aload_1
	iload_2
	iconst_1
	iadd
	invokevirtual	Method java/lang/String.substring:(I)Ljava/lang/String;
	astore_1
l1	aload_1
	ldc	int 36
	invokevirtual	Method java/lang/String.indexOf:(I)I
	istore_3
	iload_3
	iconst_m1
	if_icmpeq	l2 // aload_1
	aload_1
	iconst_0
	iload_3
	invokevirtual	Method java/lang/String.substring:(II)Ljava/lang/String;
	astore_1
l2	aload_1
	areturn
  Labels:
   	l1 = 28 // aload_1
   	l2 = 47 // aload_1
  LocalVariableTable: 
   Start  Length  Slot  Name   Signature
   0      49      0    $this       Lscala/Collection;
   0      48      1    string       Ljava/lang/String;
   8      40      2    idx1       I
   28      20      3    idx2       I


public static java.lang.String toString(scala.Collection);
  Signature: (Lscala/Collection;)Ljava/lang/String;
  Code:
   Stack=4, Locals=1, Args_size=1
	aload_0
	new	class scala/StringBuilder
	dup
	invokespecial	Method scala/StringBuilder."<init>":()V
	aload_0
	invokeinterface	InterfaceMethod scala/Collection.stringPrefix:()Ljava/lang/String;
	invokevirtual	Method scala/StringBuilder.append:(Ljava/lang/Object;)Lscala/StringBuilder;
	ldc	String (
	invokevirtual	Method scala/StringBuilder.append:(Ljava/lang/Object;)Lscala/StringBuilder;
	invokevirtual	Method scala/StringBuilder.toString:()Ljava/lang/String;
	ldc	String , 
	ldc	String )
	invokeinterface	InterfaceMethod scala/Iterable.mkString:(Ljava/lang/String;Ljava/lang/String;Ljava/lang/String;)Ljava/lang/String;
	areturn
  Labels:
  LocalVariableTable: 
   Start  Length  Slot  Name   Signature
   0      35      0    $this       Lscala/Collection;


}

