Compiled from "Console.scala"
public final class scala.Console extends java.lang.Object
  SourceFile: "Console.scala"
  ScalaSig: length = 0xCF6
   05 00 FFFFFF83 54 07 05 01 02 FFFFFF88 02 05 01 07 43 6F 6E
   73 6F 6C 65 0A 01 03 01 05 73 63 61 6C 61 03 00
   10 02 06 07 0D 01 02 06 08 08 02 FFFFFF84 FFFFFF80 FFFFFF80 FFFFFF88 02
   09 02 07 43 6F 6E 73 6F 6C 65 13 03 07 0A 12 10
   02 0B 10 0D 01 0C 0A 02 0D 0E 01 04 6C 61 6E 67
   0A 01 0F 01 04 6A 61 76 61 09 02 11 0C 02 06 4F
   62 6A 65 63 74 10 02 06 13 09 02 14 02 02 0B 53
   63 61 6C 61 4F 62 6A 65 63 74 08 05 16 07 FFFFFF84 00
   17 01 06 3C 69 6E 69 74 3E 14 01 05 08 07 19 07
   FFFFFFC2 FFFFFF80 FFFFFF84 02 1A 01 05 42 4C 41 43 4B 15 01 1B 0F
   01 1C 21 01 1D 01 05 1B 5B 33 30 6D 08 06 1F 07
   FFFFFFA0 FFFFFF80 06 1B 01 06 42 4C 41 43 4B 20 08 07 21 07
   FFFFFFC2 FFFFFF80 FFFFFF84 02 22 01 03 52 45 44 15 01 23 0F 01 24
   21 01 25 01 05 1B 5B 33 31 6D 08 06 27 07 FFFFFFA0 FFFFFF80
   06 23 01 04 52 45 44 20 08 07 29 07 FFFFFFC2 FFFFFF80 FFFFFF84 02
   2A 01 05 47 52 45 45 4E 15 01 2B 0F 01 2C 21 01
   2D 01 05 1B 5B 33 32 6D 08 06 2F 07 FFFFFFA0 FFFFFF80 06 2B
   01 06 47 52 45 45 4E 20 08 07 31 07 FFFFFFC2 FFFFFF80 FFFFFF84 02
   32 01 06 59 45 4C 4C 4F 57 15 01 33 0F 01 34 21
   01 35 01 05 1B 5B 33 33 6D 08 06 37 07 FFFFFFA0 FFFFFF80 06
   33 01 07 59 45 4C 4C 4F 57 20 08 07 39 07 FFFFFFC2 FFFFFF80
   FFFFFF84 02 3A 01 04 42 4C 55 45 15 01 3B 0F 01 3C 21
   01 3D 01 05 1B 5B 33 34 6D 08 06 3F 07 FFFFFFA0 FFFFFF80 06
   3B 01 05 42 4C 55 45 20 08 07 41 07 FFFFFFC2 FFFFFF80 FFFFFF84 02
   42 01 07 4D 41 47 45 4E 54 41 15 01 43 0F 01 44
   21 01 45 01 05 1B 5B 33 35 6D 08 06 47 07 FFFFFFA0 FFFFFF80
   06 43 01 08 4D 41 47 45 4E 54 41 20 08 07 49 07
   FFFFFFC2 FFFFFF80 FFFFFF84 02 4A 01 04 43 59 41 4E 15 01 4B 0F 01
   4C 21 01 4D 01 05 1B 5B 33 36 6D 08 06 4F 07 FFFFFFA0
   FFFFFF80 06 4B 01 05 43 59 41 4E 20 08 07 51 07 FFFFFFC2 FFFFFF80
   FFFFFF84 02 52 01 05 57 48 49 54 45 15 01 53 0F 01 54
   21 01 55 01 05 1B 5B 33 37 6D 08 06 57 07 FFFFFFA0 FFFFFF80
   06 53 01 06 57 48 49 54 45 20 08 07 59 07 FFFFFFC2 FFFFFF80
   FFFFFF84 02 5A 01 07 42 4C 41 43 4B 5F 42 15 01 5B 0F
   01 5C 21 01 5D 01 05 1B 5B 34 30 6D 08 06 5F 07
   FFFFFFA0 FFFFFF80 06 5B 01 08 42 4C 41 43 4B 5F 42 20 08 07
   61 07 FFFFFFC2 FFFFFF80 FFFFFF84 02 62 01 05 52 45 44 5F 42 15 01
   63 0F 01 64 21 01 65 01 05 1B 5B 34 31 6D 08 06
   67 07 FFFFFFA0 FFFFFF80 06 63 01 06 52 45 44 5F 42 20 08 07
   69 07 FFFFFFC2 FFFFFF80 FFFFFF84 02 6A 01 07 47 52 45 45 4E 5F 42
   15 01 6B 0F 01 6C 21 01 6D 01 05 1B 5B 34 32 6D
   08 06 6F 07 FFFFFFA0 FFFFFF80 06 6B 01 08 47 52 45 45 4E 5F
   42 20 08 07 71 07 FFFFFFC2 FFFFFF80 FFFFFF84 02 72 01 08 59 45 4C
   4C 4F 57 5F 42 15 01 73 0F 01 74 21 01 75 01 05
   1B 5B 34 33 6D 08 06 77 07 FFFFFFA0 FFFFFF80 06 73 01 09 59
   45 4C 4C 4F 57 5F 42 20 08 07 79 07 FFFFFFC2 FFFFFF80 FFFFFF84 02
   7A 01 06 42 4C 55 45 5F 42 15 01 7B 0F 01 7C 21
   01 7D 01 05 1B 5B 34 34 6D 08 06 7F 07 FFFFFFA0 FFFFFF80 06
   7B 01 07 42 4C 55 45 5F 42 20 08 09 FFFFFF81 01 07 FFFFFFC2
   FFFFFF80 FFFFFF84 02 FFFFFF81 02 01 09 4D 41 47 45 4E 54 41 5F 42
   15 02 FFFFFF81 03 0F 02 FFFFFF81 04 21 02 FFFFFF81 05 01 05 1B 5B
   34 35 6D 08 08 FFFFFF81 07 07 FFFFFFA0 FFFFFF80 06 FFFFFF81 03 01 0A 4D
   41 47 45 4E 54 41 5F 42 20 08 09 FFFFFF81 09 07 FFFFFFC2 FFFFFF80
   FFFFFF84 02 FFFFFF81 0A 01 06 43 59 41 4E 5F 42 15 02 FFFFFF81 0B
   0F 02 FFFFFF81 0C 21 02 FFFFFF81 0D 01 05 1B 5B 34 36 6D 08
   08 FFFFFF81 0F 07 FFFFFFA0 FFFFFF80 06 FFFFFF81 0B 01 07 43 59 41 4E 5F
   42 20 08 09 FFFFFF81 11 07 FFFFFFC2 FFFFFF80 FFFFFF84 02 FFFFFF81 12 01 07 57
   48 49 54 45 5F 42 15 02 FFFFFF81 13 0F 02 FFFFFF81 14 21 02
   FFFFFF81 15 01 05 1B 5B 34 37 6D 08 08 FFFFFF81 17 07 FFFFFFA0 FFFFFF80
   06 FFFFFF81 13 01 08 57 48 49 54 45 5F 42 20 08 09 FFFFFF81
   19 07 FFFFFFC2 FFFFFF80 FFFFFF84 02 FFFFFF81 1A 01 05 52 45 53 45 54 15
   02 FFFFFF81 1B 0F 02 FFFFFF81 1C 21 02 FFFFFF81 1D 01 04 1B 5B 30
   6D 08 08 FFFFFF81 1F 07 FFFFFFA0 FFFFFF80 06 FFFFFF81 1B 01 06 52 45 53
   45 54 20 08 09 FFFFFF81 21 07 FFFFFFC2 FFFFFF80 FFFFFF84 02 FFFFFF81 22 01 04
   42 4F 4C 44 15 02 FFFFFF81 23 0F 02 FFFFFF81 24 21 02 FFFFFF81 25
   01 04 1B 5B 31 6D 08 08 FFFFFF81 27 07 FFFFFFA0 FFFFFF80 06 FFFFFF81 23
   01 05 42 4F 4C 44 20 08 09 FFFFFF81 29 07 FFFFFFC2 FFFFFF80 FFFFFF84 02
   FFFFFF81 2A 01 0A 55 4E 44 45 52 4C 49 4E 45 44 15 02
   FFFFFF81 2B 0F 02 FFFFFF81 2C 21 02 FFFFFF81 2D 01 04 1B 5B 34 6D
   08 08 FFFFFF81 2F 07 FFFFFFA0 FFFFFF80 06 FFFFFF81 2B 01 0B 55 4E 44 45
   52 4C 49 4E 45 44 20 08 09 FFFFFF81 31 07 FFFFFFC2 FFFFFF80 FFFFFF84 02
   FFFFFF81 32 01 05 42 4C 49 4E 4B 15 02 FFFFFF81 33 0F 02 FFFFFF81
   34 21 02 FFFFFF81 35 01 04 1B 5B 35 6D 08 08 FFFFFF81 37 07
   FFFFFFA0 FFFFFF80 06 FFFFFF81 33 01 06 42 4C 49 4E 4B 20 08 09 FFFFFF81
   39 07 FFFFFFC2 FFFFFF80 FFFFFF84 02 FFFFFF81 3A 01 08 52 45 56 45 52 53
   45 44 15 02 FFFFFF81 3B 0F 02 FFFFFF81 3C 21 02 FFFFFF81 3D 01 04
   1B 5B 37 6D 08 08 FFFFFF81 3F 07 FFFFFFA0 FFFFFF80 06 FFFFFF81 3B 01 09
   52 45 56 45 52 53 45 44 20 08 09 FFFFFF81 41 07 FFFFFFC2 FFFFFF80
   FFFFFF84 02 FFFFFF81 42 01 09 49 4E 56 49 53 49 42 4C 45 15
   02 FFFFFF81 43 0F 02 FFFFFF81 44 21 02 FFFFFF81 45 01 04 1B 5B 38
   6D 08 08 FFFFFF81 47 07 FFFFFFA0 FFFFFF80 06 FFFFFF81 43 01 0A 49 4E 56
   49 53 49 42 4C 45 20 08 09 FFFFFF81 49 07 FFFFFFC2 FFFFFF80 FFFFFF84 04
   FFFFFF81 4A 01 06 6F 75 74 56 61 72 15 02 FFFFFF81 4B 10 06
   FFFFFF81 4C FFFFFF81 4F FFFFFF81 51 0D 02 FFFFFF81 4D 0A 03 FFFFFF81 4E 02 01
   04 75 74 69 6C 09 04 FFFFFF81 50 FFFFFF81 4D 02 0F 44 79 6E
   61 6D 69 63 56 61 72 69 61 62 6C 65 10 04 FFFFFF81 52
   FFFFFF81 55 0D 02 FFFFFF81 53 0A 03 FFFFFF81 54 0E 01 02 69 6F 09
   04 FFFFFF81 56 FFFFFF81 53 02 0B 50 72 69 6E 74 53 74 72 65
   61 6D 08 08 FFFFFF81 58 07 FFFFFFA0 FFFFFF80 04 FFFFFF81 4B 01 07 6F 75
   74 56 61 72 20 08 09 FFFFFF81 5A 07 FFFFFFC2 FFFFFF80 FFFFFF84 04 FFFFFF81 4A
   01 06 65 72 72 56 61 72 08 08 FFFFFF81 5C 07 FFFFFFA0 FFFFFF80 04
   FFFFFF81 4B 01 07 65 72 72 56 61 72 20 08 09 FFFFFF81 5E 07
   FFFFFFC2 FFFFFF80 FFFFFF84 04 FFFFFF81 5F 01 05 69 6E 56 61 72 15 02 FFFFFF81
   60 10 06 FFFFFF81 4C FFFFFF81 4F FFFFFF81 61 10 04 FFFFFF81 52 FFFFFF81 62 09
   04 FFFFFF81 63 FFFFFF81 53 02 0E 42 75 66 66 65 72 65 64 52
   65 61 64 65 72 08 08 FFFFFF81 65 07 FFFFFFA0 FFFFFF80 04 FFFFFF81 60 01
   06 69 6E 56 61 72 20 08 07 FFFFFF81 67 07 FFFFFF84 00 FFFFFF81 68
   01 03 6F 75 74 15 02 FFFFFF81 51 08 07 FFFFFF81 6A 07 FFFFFF84 00
   FFFFFF81 68 01 03 65 72 72 08 07 FFFFFF81 6C 07 FFFFFF84 00 FFFFFF81 6D
   01 02 69 6E 15 02 FFFFFF81 61 08 07 FFFFFF81 6F 07 FFFFFF84 00 FFFFFF81
   70 01 06 73 65 74 4F 75 74 14 04 FFFFFF81 71 FFFFFF81 74 10
   03 06 FFFFFF81 72 09 03 FFFFFF81 73 02 02 04 55 6E 69 74 08
   08 FFFFFF81 67 FFFFFF81 6E FFFFFFC0 00 FFFFFF81 51 08 07 FFFFFF81 76 07 FFFFFF84 00
   FFFFFF81 77 01 07 77 69 74 68 4F 75 74 15 04 FFFFFF81 78 FFFFFF81
   7C 14 04 FFFFFF81 79 FFFFFF82 0A 14 04 FFFFFF81 7A FFFFFF82 05 10 04 FFFFFF81
   7B FFFFFF81 7C 0C 00 04 0B FFFFFF81 7D FFFFFF81 75 FFFFFF84 FFFFFF80 FFFFFF80 FFFFFFC2 00
   FFFFFF81 7E 02 01 54 11 04 FFFFFF81 7F FFFFFF82 02 10 03 06 FFFFFF82 00
   09 03 FFFFFF82 01 02 02 07 4E 6F 74 68 69 6E 67 10 03
   06 FFFFFF82 03 09 03 FFFFFF82 04 02 02 03 41 6E 79 08 09 FFFFFF82
   06 FFFFFF81 75 FFFFFF84 FFFFFFC0 00 FFFFFF82 07 01 05 74 68 75 6E 6B 10
   05 06 FFFFFF82 08 FFFFFF81 7A 09 03 FFFFFF82 09 02 02 08 3C 62 79
   6E 61 6D 65 3E 08 08 FFFFFF81 67 FFFFFF81 75 FFFFFFC0 00 FFFFFF81 51 08
   07 FFFFFF81 6F 07 FFFFFF84 00 FFFFFF82 0C 14 04 FFFFFF81 71 FFFFFF82 0D 08 08
   FFFFFF81 67 FFFFFF82 0B FFFFFFC0 00 FFFFFF82 0E 10 04 FFFFFF81 52 FFFFFF82 0F 09 04
   FFFFFF82 10 FFFFFF81 53 02 0C 4F 75 74 70 75 74 53 74 72 65
   61 6D 08 07 FFFFFF81 76 07 FFFFFF84 00 FFFFFF82 12 15 04 FFFFFF82 13 FFFFFF82
   16 14 04 FFFFFF82 14 FFFFFF82 19 14 04 FFFFFF82 15 FFFFFF82 17 10 04 FFFFFF81
   7B FFFFFF82 16 04 0B FFFFFF81 7D FFFFFF82 11 FFFFFF84 FFFFFF80 FFFFFF80 FFFFFFC2 00 FFFFFF81 7E
   08 09 FFFFFF82 06 FFFFFF82 11 FFFFFF84 FFFFFFC0 00 FFFFFF82 18 10 05 06 FFFFFF82 08
   FFFFFF82 15 08 08 FFFFFF81 67 FFFFFF82 11 FFFFFFC0 00 FFFFFF82 0E 08 07 FFFFFF82 1B
   07 FFFFFF84 00 FFFFFF82 1C 01 06 73 65 74 45 72 72 14 04 FFFFFF81
   71 FFFFFF82 1D 08 08 FFFFFF81 6A FFFFFF82 1A FFFFFFC0 00 FFFFFF81 51 08 07 FFFFFF82
   1F 07 FFFFFF84 00 FFFFFF82 20 01 07 77 69 74 68 45 72 72 15
   04 FFFFFF82 21 FFFFFF82 24 14 04 FFFFFF82 22 FFFFFF82 27 14 04 FFFFFF82 23 FFFFFF82
   25 10 04 FFFFFF81 7B FFFFFF82 24 04 0B FFFFFF81 7D FFFFFF82 1E FFFFFF84 FFFFFF80 FFFFFF80
   FFFFFFC2 00 FFFFFF81 7E 08 09 FFFFFF82 06 FFFFFF82 1E FFFFFF84 FFFFFFC0 00 FFFFFF82 26 10
   05 06 FFFFFF82 08 FFFFFF82 23 08 08 FFFFFF81 6A FFFFFF82 1E FFFFFFC0 00 FFFFFF81 51
   08 07 FFFFFF82 1B 07 FFFFFF84 00 FFFFFF82 29 14 04 FFFFFF81 71 FFFFFF82 2A 08
   08 FFFFFF81 6A FFFFFF82 28 FFFFFFC0 00 FFFFFF82 0E 08 07 FFFFFF82 1F 07 FFFFFF84 00
   FFFFFF82 2C 15 04 FFFFFF82 2D FFFFFF82 30 14 04 FFFFFF82 2E FFFFFF82 33 14 04
   FFFFFF82 2F FFFFFF82 31 10 04 FFFFFF81 7B FFFFFF82 30 04 0B FFFFFF81 7D FFFFFF82 2B
   FFFFFF84 FFFFFF80 FFFFFF80 FFFFFFC2 00 FFFFFF81 7E 08 09 FFFFFF82 06 FFFFFF82 2B FFFFFF84 FFFFFFC0 00
   FFFFFF82 32 10 05 06 FFFFFF82 08 FFFFFF82 2F 08 08 FFFFFF81 6A FFFFFF82 2B FFFFFFC0
   00 FFFFFF82 0E 08 07 FFFFFF82 35 07 FFFFFF84 00 FFFFFF82 36 01 05 73 65
   74 49 6E 14 04 FFFFFF81 71 FFFFFF82 37 08 08 FFFFFF82 38 FFFFFF82 34 FFFFFFC0
   00 FFFFFF82 39 01 06 72 65 61 64 65 72 10 04 FFFFFF81 52 FFFFFF82
   3A 09 04 FFFFFF82 3B FFFFFF81 53 02 06 52 65 61 64 65 72 08
   07 FFFFFF82 3D 07 FFFFFF84 00 FFFFFF82 3E 01 06 77 69 74 68 49 6E
   15 04 FFFFFF82 3F FFFFFF82 42 14 04 FFFFFF82 40 FFFFFF82 45 14 04 FFFFFF82 41
   FFFFFF82 43 10 04 FFFFFF81 7B FFFFFF82 42 04 0B FFFFFF81 7D FFFFFF82 3C FFFFFF84 FFFFFF80
   FFFFFF80 FFFFFFC2 00 FFFFFF81 7E 08 09 FFFFFF82 06 FFFFFF82 3C FFFFFF84 FFFFFFC0 00 FFFFFF82 44
   10 05 06 FFFFFF82 08 FFFFFF82 41 08 08 FFFFFF82 38 FFFFFF82 3C FFFFFFC0 00 FFFFFF82
   39 08 07 FFFFFF82 35 07 FFFFFF84 00 FFFFFF82 47 14 04 FFFFFF81 71 FFFFFF82 48
   08 08 FFFFFF81 6C FFFFFF82 46 FFFFFFC0 00 FFFFFF82 49 10 04 FFFFFF81 52 FFFFFF82 4A
   09 04 FFFFFF82 4B FFFFFF81 53 02 0B 49 6E 70 75 74 53 74 72
   65 61 6D 08 07 FFFFFF82 3D 07 FFFFFF84 00 FFFFFF82 4D 15 04 FFFFFF82 4E
   FFFFFF82 51 14 04 FFFFFF82 4F FFFFFF82 54 14 04 FFFFFF82 50 FFFFFF82 52 10 04
   FFFFFF81 7B FFFFFF82 51 04 0B FFFFFF81 7D FFFFFF82 4C FFFFFF84 FFFFFF80 FFFFFF80 FFFFFFC2 00 FFFFFF81
   7E 08 09 FFFFFF82 06 FFFFFF82 4C FFFFFF84 FFFFFFC0 00 FFFFFF82 53 10 05 06 FFFFFF82
   08 FFFFFF82 50 08 08 FFFFFF81 6C FFFFFF82 4C FFFFFFC0 00 FFFFFF82 49 08 07 FFFFFF82
   56 07 FFFFFF84 00 FFFFFF82 57 01 05 70 72 69 6E 74 14 04 FFFFFF81
   71 FFFFFF82 58 08 08 FFFFFF82 59 FFFFFF82 55 FFFFFFC0 00 FFFFFF82 02 01 03 6F
   62 6A 08 07 FFFFFF82 5B 07 FFFFFF84 00 FFFFFF82 5C 01 05 66 6C 75
   73 68 14 02 FFFFFF81 71 08 07 FFFFFF82 5E 07 FFFFFF84 00 FFFFFF82 5C 01
   07 70 72 69 6E 74 6C 6E 08 07 FFFFFF82 5E 07 FFFFFF84 00 FFFFFF82
   60 14 04 FFFFFF81 71 FFFFFF82 61 08 08 FFFFFF82 62 FFFFFF82 5F FFFFFFC0 00 FFFFFF82
   02 01 01 78 08 07 FFFFFF82 64 07 FFFFFF84 00 FFFFFF82 65 01 06 70
   72 69 6E 74 66 14 06 FFFFFF81 71 FFFFFF82 66 FFFFFF82 6F 08 08 FFFFFF82
   67 FFFFFF82 63 FFFFFFC0 00 FFFFFF82 68 01 04 74 65 78 74 10 04 FFFFFF82
   69 FFFFFF82 6C 0E 03 06 FFFFFF82 6A 09 03 FFFFFF82 6B 02 01 06 50
   72 65 64 65 66 09 04 FFFFFF82 6D FFFFFF82 6E 02 06 53 74 72
   69 6E 67 0A 03 FFFFFF82 6B 02 08 08 FFFFFF82 70 FFFFFF82 63 FFFFFFC0 00
   FFFFFF82 71 01 04 61 72 67 73 10 05 06 FFFFFF82 72 FFFFFF82 02 09
   03 FFFFFF82 73 02 02 0A 3C 72 65 70 65 61 74 65 64 3E
   08 07 FFFFFF82 75 07 FFFFFF84 00 FFFFFF82 76 01 08 72 65 61 64 4C
   69 6E 65 14 02 FFFFFF82 68 08 07 FFFFFF82 75 07 FFFFFF84 00 FFFFFF82 78
   14 06 FFFFFF82 68 FFFFFF82 79 FFFFFF82 7A 08 08 FFFFFF82 67 FFFFFF82 77 FFFFFFC0 00
   FFFFFF82 68 08 08 FFFFFF82 70 FFFFFF82 77 FFFFFFC0 00 FFFFFF82 71 08 07 FFFFFF82 7C
   07 FFFFFF84 00 FFFFFF82 7D 01 0B 72 65 61 64 42 6F 6F 6C 65
   61 6E 14 02 FFFFFF82 7E 10 03 06 FFFFFF82 7F 09 03 FFFFFF83 00 02
   02 07 42 6F 6F 6C 65 61 6E 08 07 FFFFFF83 02 07 FFFFFF84 00
   FFFFFF83 03 01 08 72 65 61 64 42 79 74 65 14 02 FFFFFF83 04
   10 03 06 FFFFFF83 05 09 03 FFFFFF83 06 02 02 04 42 79 74 65
   08 07 FFFFFF83 08 07 FFFFFF84 00 FFFFFF83 09 01 09 72 65 61 64 53
   68 6F 72 74 14 02 FFFFFF83 0A 10 03 06 FFFFFF83 0B 09 03 FFFFFF83
   0C 02 02 05 53 68 6F 72 74 08 07 FFFFFF83 0E 07 FFFFFF84 00
   FFFFFF83 0F 01 08 72 65 61 64 43 68 61 72 14 02 FFFFFF83 10
   10 03 06 FFFFFF83 11 09 03 FFFFFF83 12 02 02 04 43 68 61 72
   08 07 FFFFFF83 14 07 FFFFFF84 00 FFFFFF83 15 01 07 72 65 61 64 49
   6E 74 14 02 FFFFFF83 16 10 03 06 FFFFFF83 17 09 03 FFFFFF83 18 02
   02 03 49 6E 74 08 07 FFFFFF83 1A 07 FFFFFF84 00 FFFFFF83 1B 01 08
   72 65 61 64 4C 6F 6E 67 14 02 FFFFFF83 1C 10 03 06 FFFFFF83
   1D 09 03 FFFFFF83 1E 02 02 04 4C 6F 6E 67 08 07 FFFFFF83 20
   07 FFFFFF84 00 FFFFFF83 21 01 09 72 65 61 64 46 6C 6F 61 74
   14 02 FFFFFF83 22 10 03 06 FFFFFF83 23 09 03 FFFFFF83 24 02 02 05
   46 6C 6F 61 74 08 07 FFFFFF83 26 07 FFFFFF84 00 FFFFFF83 27 01 0A
   72 65 61 64 44 6F 75 62 6C 65 14 02 FFFFFF83 28 10 03
   06 FFFFFF83 29 09 03 FFFFFF83 2A 02 02 06 44 6F 75 62 6C 65
   08 07 FFFFFF83 2C 07 FFFFFF84 00 FFFFFF83 2D 01 05 72 65 61 64 66
   14 04 FFFFFF83 2E FFFFFF83 35 10 06 FFFFFF83 2F FFFFFF83 32 FFFFFF82 02 0E 03
   06 FFFFFF83 30 09 03 FFFFFF83 31 02 01 07 70 61 63 6B 61 67
   65 09 04 FFFFFF83 33 FFFFFF83 34 02 04 4C 69 73 74 0A 03 FFFFFF83
   31 02 08 08 FFFFFF83 36 FFFFFF83 2B FFFFFFC0 00 FFFFFF82 68 01 06 66 6F
   72 6D 61 74 08 07 FFFFFF83 38 07 FFFFFF84 00 FFFFFF83 39 01 06 72
   65 61 64 66 31 14 04 FFFFFF82 02 FFFFFF83 3A 08 08 FFFFFF83 36 FFFFFF83
   37 FFFFFFC0 00 FFFFFF82 68 08 07 FFFFFF83 3C 07 FFFFFF84 00 FFFFFF83 3D 01 06
   72 65 61 64 66 32 14 04 FFFFFF83 3E FFFFFF83 41 10 07 06 FFFFFF83
   3F FFFFFF82 02 FFFFFF82 02 09 03 FFFFFF83 40 02 02 06 54 75 70 6C
   65 32 08 08 FFFFFF83 36 FFFFFF83 3B FFFFFFC0 00 FFFFFF82 68 08 07 FFFFFF83 43
   07 FFFFFF84 00 FFFFFF83 44 01 06 72 65 61 64 66 33 14 04 FFFFFF83
   45 FFFFFF83 48 10 09 06 FFFFFF83 46 FFFFFF82 02 FFFFFF82 02 FFFFFF82 02 09 03
   FFFFFF83 47 02 02 06 54 75 70 6C 65 33 08 08 FFFFFF83 36 FFFFFF83
   42 FFFFFFC0 00 FFFFFF82 68 08 07 FFFFFF83 4A 07 FFFFFF84 04 FFFFFF83 4B 01 0E
   74 65 78 74 43 6F 6D 70 6F 6E 65 6E 74 73 14 04
   FFFFFF83 2E FFFFFF83 4C 08 08 FFFFFF83 4D FFFFFF83 49 FFFFFFC0 00 FFFFFF83 4E 01 01
   61 10 05 06 FFFFFF83 4F FFFFFF83 51 09 03 FFFFFF83 50 02 02 05 41
   72 72 61 79 10 03 06 FFFFFF83 52 09 03 FFFFFF83 53 02 02 06
   41 6E 79 52 65 66 
  minor version: 0
  major version: 49
  Constant pool:
Asciz	SourceFile;
Asciz	Console.scala;
Asciz	readf3;
Asciz	(Ljava/lang/String;)Lscala/Tuple3;;
Asciz	Code;
Asciz	scala/Console$;
class	scala/Console$
Asciz	MODULE$;
Asciz	Lscala/Console$;;
NameAndType	MODULE$:Lscala/Console$;
Field	scala/Console$.MODULE$:Lscala/Console$;
NameAndType	readf3:(Ljava/lang/String;)Lscala/Tuple3;
Method	scala/Console$.readf3:(Ljava/lang/String;)Lscala/Tuple3;
Asciz	(Ljava/lang/String;)Lscala/Tuple3<Ljava/lang/Object;Ljava/lang/Object;Ljava/lang/Object;>;;
Asciz	Signature;
Asciz	readf2;
Asciz	(Ljava/lang/String;)Lscala/Tuple2;;
NameAndType	readf2:(Ljava/lang/String;)Lscala/Tuple2;
Method	scala/Console$.readf2:(Ljava/lang/String;)Lscala/Tuple2;
Asciz	(Ljava/lang/String;)Lscala/Tuple2<Ljava/lang/Object;Ljava/lang/Object;>;;
Asciz	readf1;
Asciz	(Ljava/lang/String;)Ljava/lang/Object;;
NameAndType	readf1:(Ljava/lang/String;)Ljava/lang/Object;
Method	scala/Console$.readf1:(Ljava/lang/String;)Ljava/lang/Object;
Asciz	readf;
Asciz	(Ljava/lang/String;)Lscala/collection/immutable/List;;
NameAndType	readf:(Ljava/lang/String;)Lscala/collection/immutable/List;
Method	scala/Console$.readf:(Ljava/lang/String;)Lscala/collection/immutable/List;
Asciz	(Ljava/lang/String;)Lscala/collection/immutable/List<Ljava/lang/Object;>;;
Asciz	readDouble;
Asciz	()D;
NameAndType	readDouble:()D
Method	scala/Console$.readDouble:()D
Asciz	readFloat;
Asciz	()F;
NameAndType	readFloat:()F
Method	scala/Console$.readFloat:()F
Asciz	readLong;
Asciz	()J;
NameAndType	readLong:()J
Method	scala/Console$.readLong:()J
Asciz	readInt;
Asciz	()I;
NameAndType	readInt:()I
Method	scala/Console$.readInt:()I
Asciz	readChar;
Asciz	()C;
NameAndType	readChar:()C
Method	scala/Console$.readChar:()C
Asciz	readShort;
Asciz	()S;
NameAndType	readShort:()S
Method	scala/Console$.readShort:()S
Asciz	readByte;
Asciz	()B;
NameAndType	readByte:()B
Method	scala/Console$.readByte:()B
Asciz	readBoolean;
Asciz	()Z;
NameAndType	readBoolean:()Z
Method	scala/Console$.readBoolean:()Z
Asciz	readLine;
Asciz	(Ljava/lang/String;Lscala/collection/Seq;)Ljava/lang/String;;
NameAndType	readLine:(Ljava/lang/String;Lscala/collection/Seq;)Ljava/lang/String;
Method	scala/Console$.readLine:(Ljava/lang/String;Lscala/collection/Seq;)Ljava/lang/String;
Asciz	(Ljava/lang/String;Lscala/collection/Seq<Ljava/lang/Object;>;)Ljava/lang/String;;
Asciz	()Ljava/lang/String;;
NameAndType	readLine:()Ljava/lang/String;
Method	scala/Console$.readLine:()Ljava/lang/String;
Asciz	printf;
Asciz	(Ljava/lang/String;Lscala/collection/Seq;)V;
NameAndType	printf:(Ljava/lang/String;Lscala/collection/Seq;)V
Method	scala/Console$.printf:(Ljava/lang/String;Lscala/collection/Seq;)V
Asciz	(Ljava/lang/String;Lscala/collection/Seq<Ljava/lang/Object;>;)V;
Asciz	println;
Asciz	(Ljava/lang/Object;)V;
NameAndType	println:(Ljava/lang/Object;)V
Method	scala/Console$.println:(Ljava/lang/Object;)V
Asciz	()V;
NameAndType	println:()V
Method	scala/Console$.println:()V
Asciz	flush;
NameAndType	flush:()V
Method	scala/Console$.flush:()V
Asciz	print;
NameAndType	print:(Ljava/lang/Object;)V
Method	scala/Console$.print:(Ljava/lang/Object;)V
Asciz	withIn;
Asciz	(Ljava/io/InputStream;Lscala/Function0;)Ljava/lang/Object;;
NameAndType	withIn:(Ljava/io/InputStream;Lscala/Function0;)Ljava/lang/Object;
Method	scala/Console$.withIn:(Ljava/io/InputStream;Lscala/Function0;)Ljava/lang/Object;
Asciz	<T:Ljava/lang/Object;>(Ljava/io/InputStream;Lscala/Function0<TT;>;)TT;;
Asciz	setIn;
Asciz	(Ljava/io/InputStream;)V;
NameAndType	setIn:(Ljava/io/InputStream;)V
Method	scala/Console$.setIn:(Ljava/io/InputStream;)V
Asciz	(Ljava/io/Reader;Lscala/Function0;)Ljava/lang/Object;;
NameAndType	withIn:(Ljava/io/Reader;Lscala/Function0;)Ljava/lang/Object;
Method	scala/Console$.withIn:(Ljava/io/Reader;Lscala/Function0;)Ljava/lang/Object;
Asciz	<T:Ljava/lang/Object;>(Ljava/io/Reader;Lscala/Function0<TT;>;)TT;;
Asciz	(Ljava/io/Reader;)V;
NameAndType	setIn:(Ljava/io/Reader;)V
Method	scala/Console$.setIn:(Ljava/io/Reader;)V
Asciz	withErr;
Asciz	(Ljava/io/OutputStream;Lscala/Function0;)Ljava/lang/Object;;
NameAndType	withErr:(Ljava/io/OutputStream;Lscala/Function0;)Ljava/lang/Object;
Method	scala/Console$.withErr:(Ljava/io/OutputStream;Lscala/Function0;)Ljava/lang/Object;
Asciz	<T:Ljava/lang/Object;>(Ljava/io/OutputStream;Lscala/Function0<TT;>;)TT;;
Asciz	setErr;
Asciz	(Ljava/io/OutputStream;)V;
NameAndType	setErr:(Ljava/io/OutputStream;)V
Method	scala/Console$.setErr:(Ljava/io/OutputStream;)V
Asciz	(Ljava/io/PrintStream;Lscala/Function0;)Ljava/lang/Object;;
NameAndType	withErr:(Ljava/io/PrintStream;Lscala/Function0;)Ljava/lang/Object;
Method	scala/Console$.withErr:(Ljava/io/PrintStream;Lscala/Function0;)Ljava/lang/Object;
Asciz	<T:Ljava/lang/Object;>(Ljava/io/PrintStream;Lscala/Function0<TT;>;)TT;;
Asciz	(Ljava/io/PrintStream;)V;
NameAndType	setErr:(Ljava/io/PrintStream;)V
Method	scala/Console$.setErr:(Ljava/io/PrintStream;)V
Asciz	withOut;
NameAndType	withOut:(Ljava/io/OutputStream;Lscala/Function0;)Ljava/lang/Object;
Method	scala/Console$.withOut:(Ljava/io/OutputStream;Lscala/Function0;)Ljava/lang/Object;
Asciz	setOut;
NameAndType	setOut:(Ljava/io/OutputStream;)V
Method	scala/Console$.setOut:(Ljava/io/OutputStream;)V
NameAndType	withOut:(Ljava/io/PrintStream;Lscala/Function0;)Ljava/lang/Object;
Method	scala/Console$.withOut:(Ljava/io/PrintStream;Lscala/Function0;)Ljava/lang/Object;
NameAndType	setOut:(Ljava/io/PrintStream;)V
Method	scala/Console$.setOut:(Ljava/io/PrintStream;)V
Asciz	in;
Asciz	()Ljava/io/BufferedReader;;
NameAndType	in:()Ljava/io/BufferedReader;
Method	scala/Console$.in:()Ljava/io/BufferedReader;
Asciz	err;
Asciz	()Ljava/io/PrintStream;;
NameAndType	err:()Ljava/io/PrintStream;
Method	scala/Console$.err:()Ljava/io/PrintStream;
Asciz	out;
NameAndType	out:()Ljava/io/PrintStream;
Method	scala/Console$.out:()Ljava/io/PrintStream;
Asciz	INVISIBLE;
NameAndType	INVISIBLE:()Ljava/lang/String;
Method	scala/Console$.INVISIBLE:()Ljava/lang/String;
Asciz	REVERSED;
NameAndType	REVERSED:()Ljava/lang/String;
Method	scala/Console$.REVERSED:()Ljava/lang/String;
Asciz	BLINK;
NameAndType	BLINK:()Ljava/lang/String;
Method	scala/Console$.BLINK:()Ljava/lang/String;
Asciz	UNDERLINED;
NameAndType	UNDERLINED:()Ljava/lang/String;
Method	scala/Console$.UNDERLINED:()Ljava/lang/String;
Asciz	BOLD;
NameAndType	BOLD:()Ljava/lang/String;
Method	scala/Console$.BOLD:()Ljava/lang/String;
Asciz	RESET;
NameAndType	RESET:()Ljava/lang/String;
Method	scala/Console$.RESET:()Ljava/lang/String;
Asciz	WHITE_B;
NameAndType	WHITE_B:()Ljava/lang/String;
Method	scala/Console$.WHITE_B:()Ljava/lang/String;
Asciz	CYAN_B;
NameAndType	CYAN_B:()Ljava/lang/String;
Method	scala/Console$.CYAN_B:()Ljava/lang/String;
Asciz	MAGENTA_B;
NameAndType	MAGENTA_B:()Ljava/lang/String;
Method	scala/Console$.MAGENTA_B:()Ljava/lang/String;
Asciz	BLUE_B;
NameAndType	BLUE_B:()Ljava/lang/String;
Method	scala/Console$.BLUE_B:()Ljava/lang/String;
Asciz	YELLOW_B;
NameAndType	YELLOW_B:()Ljava/lang/String;
Method	scala/Console$.YELLOW_B:()Ljava/lang/String;
Asciz	GREEN_B;
NameAndType	GREEN_B:()Ljava/lang/String;
Method	scala/Console$.GREEN_B:()Ljava/lang/String;
Asciz	RED_B;
NameAndType	RED_B:()Ljava/lang/String;
Method	scala/Console$.RED_B:()Ljava/lang/String;
Asciz	BLACK_B;
NameAndType	BLACK_B:()Ljava/lang/String;
Method	scala/Console$.BLACK_B:()Ljava/lang/String;
Asciz	WHITE;
NameAndType	WHITE:()Ljava/lang/String;
Method	scala/Console$.WHITE:()Ljava/lang/String;
Asciz	CYAN;
NameAndType	CYAN:()Ljava/lang/String;
Method	scala/Console$.CYAN:()Ljava/lang/String;
Asciz	MAGENTA;
NameAndType	MAGENTA:()Ljava/lang/String;
Method	scala/Console$.MAGENTA:()Ljava/lang/String;
Asciz	BLUE;
NameAndType	BLUE:()Ljava/lang/String;
Method	scala/Console$.BLUE:()Ljava/lang/String;
Asciz	YELLOW;
NameAndType	YELLOW:()Ljava/lang/String;
Method	scala/Console$.YELLOW:()Ljava/lang/String;
Asciz	GREEN;
NameAndType	GREEN:()Ljava/lang/String;
Method	scala/Console$.GREEN:()Ljava/lang/String;
Asciz	RED;
NameAndType	RED:()Ljava/lang/String;
Method	scala/Console$.RED:()Ljava/lang/String;
Asciz	BLACK;
NameAndType	BLACK:()Ljava/lang/String;
Method	scala/Console$.BLACK:()Ljava/lang/String;
Asciz	ScalaSig;
Asciz	scala/Console;
class	scala/Console
Asciz	java/lang/Object;
class	java/lang/Object

{
public static final scala.Tuple3 readf3(java.lang.String);
  Signature: (Ljava/lang/String;)Lscala/Tuple3;
  Code:
   Stack=2, Locals=1, Args_size=1
	getstatic	Field scala/Console$.MODULE$:Lscala/Console$;
	aload_0
	invokevirtual	Method scala/Console$.readf3:(Ljava/lang/String;)Lscala/Tuple3;
	areturn
  Labels:
  Signature: length = 0x2
   00 0E 

public static final scala.Tuple2 readf2(java.lang.String);
  Signature: (Ljava/lang/String;)Lscala/Tuple2;
  Code:
   Stack=2, Locals=1, Args_size=1
	getstatic	Field scala/Console$.MODULE$:Lscala/Console$;
	aload_0
	invokevirtual	Method scala/Console$.readf2:(Ljava/lang/String;)Lscala/Tuple2;
	areturn
  Labels:
  Signature: length = 0x2
   00 14 

public static final java.lang.Object readf1(java.lang.String);
  Signature: (Ljava/lang/String;)Ljava/lang/Object;
  Code:
   Stack=2, Locals=1, Args_size=1
	getstatic	Field scala/Console$.MODULE$:Lscala/Console$;
	aload_0
	invokevirtual	Method scala/Console$.readf1:(Ljava/lang/String;)Ljava/lang/Object;
	areturn
  Labels:

public static final scala.collection.immutable.List readf(java.lang.String);
  Signature: (Ljava/lang/String;)Lscala/collection/immutable/List;
  Code:
   Stack=2, Locals=1, Args_size=1
	getstatic	Field scala/Console$.MODULE$:Lscala/Console$;
	aload_0
	invokevirtual	Method scala/Console$.readf:(Ljava/lang/String;)Lscala/collection/immutable/List;
	areturn
  Labels:
  Signature: length = 0x2
   00 1D 

public static final double readDouble();
  Signature: ()D
  Code:
   Stack=2, Locals=0, Args_size=0
	getstatic	Field scala/Console$.MODULE$:Lscala/Console$;
	invokevirtual	Method scala/Console$.readDouble:()D
	dreturn
  Labels:

public static final float readFloat();
  Signature: ()F
  Code:
   Stack=1, Locals=0, Args_size=0
	getstatic	Field scala/Console$.MODULE$:Lscala/Console$;
	invokevirtual	Method scala/Console$.readFloat:()F
	freturn
  Labels:

public static final long readLong();
  Signature: ()J
  Code:
   Stack=2, Locals=0, Args_size=0
	getstatic	Field scala/Console$.MODULE$:Lscala/Console$;
	invokevirtual	Method scala/Console$.readLong:()J
	lreturn
  Labels:

public static final int readInt();
  Signature: ()I
  Code:
   Stack=1, Locals=0, Args_size=0
	getstatic	Field scala/Console$.MODULE$:Lscala/Console$;
	invokevirtual	Method scala/Console$.readInt:()I
	ireturn
  Labels:

public static final char readChar();
  Signature: ()C
  Code:
   Stack=1, Locals=0, Args_size=0
	getstatic	Field scala/Console$.MODULE$:Lscala/Console$;
	invokevirtual	Method scala/Console$.readChar:()C
	ireturn
  Labels:

public static final short readShort();
  Signature: ()S
  Code:
   Stack=1, Locals=0, Args_size=0
	getstatic	Field scala/Console$.MODULE$:Lscala/Console$;
	invokevirtual	Method scala/Console$.readShort:()S
	ireturn
  Labels:

public static final byte readByte();
  Signature: ()B
  Code:
   Stack=1, Locals=0, Args_size=0
	getstatic	Field scala/Console$.MODULE$:Lscala/Console$;
	invokevirtual	Method scala/Console$.readByte:()B
	ireturn
  Labels:

public static final boolean readBoolean();
  Signature: ()Z
  Code:
   Stack=1, Locals=0, Args_size=0
	getstatic	Field scala/Console$.MODULE$:Lscala/Console$;
	invokevirtual	Method scala/Console$.readBoolean:()Z
	ireturn
  Labels:

public static final java.lang.String readLine(java.lang.String, scala.collection.Seq);
  Signature: (Ljava/lang/String;Lscala/collection/Seq;)Ljava/lang/String;
  Code:
   Stack=3, Locals=2, Args_size=2
	getstatic	Field scala/Console$.MODULE$:Lscala/Console$;
	aload_0
	aload_1
	invokevirtual	Method scala/Console$.readLine:(Ljava/lang/String;Lscala/collection/Seq;)Ljava/lang/String;
	areturn
  Labels:
  Signature: length = 0x2
   00 42 

public static final java.lang.String readLine();
  Signature: ()Ljava/lang/String;
  Code:
   Stack=1, Locals=0, Args_size=0
	getstatic	Field scala/Console$.MODULE$:Lscala/Console$;
	invokevirtual	Method scala/Console$.readLine:()Ljava/lang/String;
	areturn
  Labels:

public static final void printf(java.lang.String, scala.collection.Seq);
  Signature: (Ljava/lang/String;Lscala/collection/Seq;)V
  Code:
   Stack=3, Locals=2, Args_size=2
	getstatic	Field scala/Console$.MODULE$:Lscala/Console$;
	aload_0
	aload_1
	invokevirtual	Method scala/Console$.printf:(Ljava/lang/String;Lscala/collection/Seq;)V
	return
  Labels:
  Signature: length = 0x2
   00 4A 

public static final void println(java.lang.Object);
  Signature: (Ljava/lang/Object;)V
  Code:
   Stack=2, Locals=1, Args_size=1
	getstatic	Field scala/Console$.MODULE$:Lscala/Console$;
	aload_0
	invokevirtual	Method scala/Console$.println:(Ljava/lang/Object;)V
	return
  Labels:

public static final void println();
  Signature: ()V
  Code:
   Stack=1, Locals=0, Args_size=0
	getstatic	Field scala/Console$.MODULE$:Lscala/Console$;
	invokevirtual	Method scala/Console$.println:()V
	return
  Labels:

public static final void flush();
  Signature: ()V
  Code:
   Stack=1, Locals=0, Args_size=0
	getstatic	Field scala/Console$.MODULE$:Lscala/Console$;
	invokevirtual	Method scala/Console$.flush:()V
	return
  Labels:

public static final void print(java.lang.Object);
  Signature: (Ljava/lang/Object;)V
  Code:
   Stack=2, Locals=1, Args_size=1
	getstatic	Field scala/Console$.MODULE$:Lscala/Console$;
	aload_0
	invokevirtual	Method scala/Console$.print:(Ljava/lang/Object;)V
	return
  Labels:

public static final java.lang.Object withIn(java.io.InputStream, scala.Function0);
  Signature: (Ljava/io/InputStream;Lscala/Function0;)Ljava/lang/Object;
  Code:
   Stack=3, Locals=2, Args_size=2
	getstatic	Field scala/Console$.MODULE$:Lscala/Console$;
	aload_0
	aload_1
	invokevirtual	Method scala/Console$.withIn:(Ljava/io/InputStream;Lscala/Function0;)Ljava/lang/Object;
	areturn
  Labels:
  Signature: length = 0x2
   00 5C 

public static final void setIn(java.io.InputStream);
  Signature: (Ljava/io/InputStream;)V
  Code:
   Stack=2, Locals=1, Args_size=1
	getstatic	Field scala/Console$.MODULE$:Lscala/Console$;
	aload_0
	invokevirtual	Method scala/Console$.setIn:(Ljava/io/InputStream;)V
	return
  Labels:

public static final java.lang.Object withIn(java.io.Reader, scala.Function0);
  Signature: (Ljava/io/Reader;Lscala/Function0;)Ljava/lang/Object;
  Code:
   Stack=3, Locals=2, Args_size=2
	getstatic	Field scala/Console$.MODULE$:Lscala/Console$;
	aload_0
	aload_1
	invokevirtual	Method scala/Console$.withIn:(Ljava/io/Reader;Lscala/Function0;)Ljava/lang/Object;
	areturn
  Labels:
  Signature: length = 0x2
   00 64 

public static final void setIn(java.io.Reader);
  Signature: (Ljava/io/Reader;)V
  Code:
   Stack=2, Locals=1, Args_size=1
	getstatic	Field scala/Console$.MODULE$:Lscala/Console$;
	aload_0
	invokevirtual	Method scala/Console$.setIn:(Ljava/io/Reader;)V
	return
  Labels:

public static final java.lang.Object withErr(java.io.OutputStream, scala.Function0);
  Signature: (Ljava/io/OutputStream;Lscala/Function0;)Ljava/lang/Object;
  Code:
   Stack=3, Locals=2, Args_size=2
	getstatic	Field scala/Console$.MODULE$:Lscala/Console$;
	aload_0
	aload_1
	invokevirtual	Method scala/Console$.withErr:(Ljava/io/OutputStream;Lscala/Function0;)Ljava/lang/Object;
	areturn
  Labels:
  Signature: length = 0x2
   00 6C 

public static final void setErr(java.io.OutputStream);
  Signature: (Ljava/io/OutputStream;)V
  Code:
   Stack=2, Locals=1, Args_size=1
	getstatic	Field scala/Console$.MODULE$:Lscala/Console$;
	aload_0
	invokevirtual	Method scala/Console$.setErr:(Ljava/io/OutputStream;)V
	return
  Labels:

public static final java.lang.Object withErr(java.io.PrintStream, scala.Function0);
  Signature: (Ljava/io/PrintStream;Lscala/Function0;)Ljava/lang/Object;
  Code:
   Stack=3, Locals=2, Args_size=2
	getstatic	Field scala/Console$.MODULE$:Lscala/Console$;
	aload_0
	aload_1
	invokevirtual	Method scala/Console$.withErr:(Ljava/io/PrintStream;Lscala/Function0;)Ljava/lang/Object;
	areturn
  Labels:
  Signature: length = 0x2
   00 74 

public static final void setErr(java.io.PrintStream);
  Signature: (Ljava/io/PrintStream;)V
  Code:
   Stack=2, Locals=1, Args_size=1
	getstatic	Field scala/Console$.MODULE$:Lscala/Console$;
	aload_0
	invokevirtual	Method scala/Console$.setErr:(Ljava/io/PrintStream;)V
	return
  Labels:

public static final java.lang.Object withOut(java.io.OutputStream, scala.Function0);
  Signature: (Ljava/io/OutputStream;Lscala/Function0;)Ljava/lang/Object;
  Code:
   Stack=3, Locals=2, Args_size=2
	getstatic	Field scala/Console$.MODULE$:Lscala/Console$;
	aload_0
	aload_1
	invokevirtual	Method scala/Console$.withOut:(Ljava/io/OutputStream;Lscala/Function0;)Ljava/lang/Object;
	areturn
  Labels:
  Signature: length = 0x2
   00 6C 

public static final void setOut(java.io.OutputStream);
  Signature: (Ljava/io/OutputStream;)V
  Code:
   Stack=2, Locals=1, Args_size=1
	getstatic	Field scala/Console$.MODULE$:Lscala/Console$;
	aload_0
	invokevirtual	Method scala/Console$.setOut:(Ljava/io/OutputStream;)V
	return
  Labels:

public static final java.lang.Object withOut(java.io.PrintStream, scala.Function0);
  Signature: (Ljava/io/PrintStream;Lscala/Function0;)Ljava/lang/Object;
  Code:
   Stack=3, Locals=2, Args_size=2
	getstatic	Field scala/Console$.MODULE$:Lscala/Console$;
	aload_0
	aload_1
	invokevirtual	Method scala/Console$.withOut:(Ljava/io/PrintStream;Lscala/Function0;)Ljava/lang/Object;
	areturn
  Labels:
  Signature: length = 0x2
   00 74 

public static final void setOut(java.io.PrintStream);
  Signature: (Ljava/io/PrintStream;)V
  Code:
   Stack=2, Locals=1, Args_size=1
	getstatic	Field scala/Console$.MODULE$:Lscala/Console$;
	aload_0
	invokevirtual	Method scala/Console$.setOut:(Ljava/io/PrintStream;)V
	return
  Labels:

public static final java.io.BufferedReader in();
  Signature: ()Ljava/io/BufferedReader;
  Code:
   Stack=1, Locals=0, Args_size=0
	getstatic	Field scala/Console$.MODULE$:Lscala/Console$;
	invokevirtual	Method scala/Console$.in:()Ljava/io/BufferedReader;
	areturn
  Labels:

public static final java.io.PrintStream err();
  Signature: ()Ljava/io/PrintStream;
  Code:
   Stack=1, Locals=0, Args_size=0
	getstatic	Field scala/Console$.MODULE$:Lscala/Console$;
	invokevirtual	Method scala/Console$.err:()Ljava/io/PrintStream;
	areturn
  Labels:

public static final java.io.PrintStream out();
  Signature: ()Ljava/io/PrintStream;
  Code:
   Stack=1, Locals=0, Args_size=0
	getstatic	Field scala/Console$.MODULE$:Lscala/Console$;
	invokevirtual	Method scala/Console$.out:()Ljava/io/PrintStream;
	areturn
  Labels:

public static final java.lang.String INVISIBLE();
  Signature: ()Ljava/lang/String;
  Code:
   Stack=1, Locals=0, Args_size=0
	getstatic	Field scala/Console$.MODULE$:Lscala/Console$;
	invokevirtual	Method scala/Console$.INVISIBLE:()Ljava/lang/String;
	areturn
  Labels:

public static final java.lang.String REVERSED();
  Signature: ()Ljava/lang/String;
  Code:
   Stack=1, Locals=0, Args_size=0
	getstatic	Field scala/Console$.MODULE$:Lscala/Console$;
	invokevirtual	Method scala/Console$.REVERSED:()Ljava/lang/String;
	areturn
  Labels:

public static final java.lang.String BLINK();
  Signature: ()Ljava/lang/String;
  Code:
   Stack=1, Locals=0, Args_size=0
	getstatic	Field scala/Console$.MODULE$:Lscala/Console$;
	invokevirtual	Method scala/Console$.BLINK:()Ljava/lang/String;
	areturn
  Labels:

public static final java.lang.String UNDERLINED();
  Signature: ()Ljava/lang/String;
  Code:
   Stack=1, Locals=0, Args_size=0
	getstatic	Field scala/Console$.MODULE$:Lscala/Console$;
	invokevirtual	Method scala/Console$.UNDERLINED:()Ljava/lang/String;
	areturn
  Labels:

public static final java.lang.String BOLD();
  Signature: ()Ljava/lang/String;
  Code:
   Stack=1, Locals=0, Args_size=0
	getstatic	Field scala/Console$.MODULE$:Lscala/Console$;
	invokevirtual	Method scala/Console$.BOLD:()Ljava/lang/String;
	areturn
  Labels:

public static final java.lang.String RESET();
  Signature: ()Ljava/lang/String;
  Code:
   Stack=1, Locals=0, Args_size=0
	getstatic	Field scala/Console$.MODULE$:Lscala/Console$;
	invokevirtual	Method scala/Console$.RESET:()Ljava/lang/String;
	areturn
  Labels:

public static final java.lang.String WHITE_B();
  Signature: ()Ljava/lang/String;
  Code:
   Stack=1, Locals=0, Args_size=0
	getstatic	Field scala/Console$.MODULE$:Lscala/Console$;
	invokevirtual	Method scala/Console$.WHITE_B:()Ljava/lang/String;
	areturn
  Labels:

public static final java.lang.String CYAN_B();
  Signature: ()Ljava/lang/String;
  Code:
   Stack=1, Locals=0, Args_size=0
	getstatic	Field scala/Console$.MODULE$:Lscala/Console$;
	invokevirtual	Method scala/Console$.CYAN_B:()Ljava/lang/String;
	areturn
  Labels:

public static final java.lang.String MAGENTA_B();
  Signature: ()Ljava/lang/String;
  Code:
   Stack=1, Locals=0, Args_size=0
	getstatic	Field scala/Console$.MODULE$:Lscala/Console$;
	invokevirtual	Method scala/Console$.MAGENTA_B:()Ljava/lang/String;
	areturn
  Labels:

public static final java.lang.String BLUE_B();
  Signature: ()Ljava/lang/String;
  Code:
   Stack=1, Locals=0, Args_size=0
	getstatic	Field scala/Console$.MODULE$:Lscala/Console$;
	invokevirtual	Method scala/Console$.BLUE_B:()Ljava/lang/String;
	areturn
  Labels:

public static final java.lang.String YELLOW_B();
  Signature: ()Ljava/lang/String;
  Code:
   Stack=1, Locals=0, Args_size=0
	getstatic	Field scala/Console$.MODULE$:Lscala/Console$;
	invokevirtual	Method scala/Console$.YELLOW_B:()Ljava/lang/String;
	areturn
  Labels:

public static final java.lang.String GREEN_B();
  Signature: ()Ljava/lang/String;
  Code:
   Stack=1, Locals=0, Args_size=0
	getstatic	Field scala/Console$.MODULE$:Lscala/Console$;
	invokevirtual	Method scala/Console$.GREEN_B:()Ljava/lang/String;
	areturn
  Labels:

public static final java.lang.String RED_B();
  Signature: ()Ljava/lang/String;
  Code:
   Stack=1, Locals=0, Args_size=0
	getstatic	Field scala/Console$.MODULE$:Lscala/Console$;
	invokevirtual	Method scala/Console$.RED_B:()Ljava/lang/String;
	areturn
  Labels:

public static final java.lang.String BLACK_B();
  Signature: ()Ljava/lang/String;
  Code:
   Stack=1, Locals=0, Args_size=0
	getstatic	Field scala/Console$.MODULE$:Lscala/Console$;
	invokevirtual	Method scala/Console$.BLACK_B:()Ljava/lang/String;
	areturn
  Labels:

public static final java.lang.String WHITE();
  Signature: ()Ljava/lang/String;
  Code:
   Stack=1, Locals=0, Args_size=0
	getstatic	Field scala/Console$.MODULE$:Lscala/Console$;
	invokevirtual	Method scala/Console$.WHITE:()Ljava/lang/String;
	areturn
  Labels:

public static final java.lang.String CYAN();
  Signature: ()Ljava/lang/String;
  Code:
   Stack=1, Locals=0, Args_size=0
	getstatic	Field scala/Console$.MODULE$:Lscala/Console$;
	invokevirtual	Method scala/Console$.CYAN:()Ljava/lang/String;
	areturn
  Labels:

public static final java.lang.String MAGENTA();
  Signature: ()Ljava/lang/String;
  Code:
   Stack=1, Locals=0, Args_size=0
	getstatic	Field scala/Console$.MODULE$:Lscala/Console$;
	invokevirtual	Method scala/Console$.MAGENTA:()Ljava/lang/String;
	areturn
  Labels:

public static final java.lang.String BLUE();
  Signature: ()Ljava/lang/String;
  Code:
   Stack=1, Locals=0, Args_size=0
	getstatic	Field scala/Console$.MODULE$:Lscala/Console$;
	invokevirtual	Method scala/Console$.BLUE:()Ljava/lang/String;
	areturn
  Labels:

public static final java.lang.String YELLOW();
  Signature: ()Ljava/lang/String;
  Code:
   Stack=1, Locals=0, Args_size=0
	getstatic	Field scala/Console$.MODULE$:Lscala/Console$;
	invokevirtual	Method scala/Console$.YELLOW:()Ljava/lang/String;
	areturn
  Labels:

public static final java.lang.String GREEN();
  Signature: ()Ljava/lang/String;
  Code:
   Stack=1, Locals=0, Args_size=0
	getstatic	Field scala/Console$.MODULE$:Lscala/Console$;
	invokevirtual	Method scala/Console$.GREEN:()Ljava/lang/String;
	areturn
  Labels:

public static final java.lang.String RED();
  Signature: ()Ljava/lang/String;
  Code:
   Stack=1, Locals=0, Args_size=0
	getstatic	Field scala/Console$.MODULE$:Lscala/Console$;
	invokevirtual	Method scala/Console$.RED:()Ljava/lang/String;
	areturn
  Labels:

public static final java.lang.String BLACK();
  Signature: ()Ljava/lang/String;
  Code:
   Stack=1, Locals=0, Args_size=0
	getstatic	Field scala/Console$.MODULE$:Lscala/Console$;
	invokevirtual	Method scala/Console$.BLACK:()Ljava/lang/String;
	areturn
  Labels:

}

