Compiled from "Either.scala"
public final class scala.Either$ extends java.lang.Object implements scala.ScalaObject
  SourceFile: "Either.scala"
  Scala: length = 0x
   
  InnerClass: 
   public final LeftProjection=class scala/Either$LeftProjection of class scala/Either
   public MergeableEither=class scala/Either$MergeableEither of class scala/Either
   public final RightProjection=class scala/Either$RightProjection of class scala/Either
   public final $anonfun$joinLeft$1=class scala/Either$$anonfun$joinLeft$1 of class scala/Either
   public final $anonfun$joinRight$1=class scala/Either$$anonfun$joinRight$1 of class scala/Either
  minor version: 0
  major version: 49
  Constant pool:
Asciz	SourceFile;
Asciz	Either.scala;
Asciz	Scala;
Asciz	MODULE$;
Asciz	Lscala/Either$;;
Asciz	<clinit>;
Asciz	()V;
Asciz	Code;
Asciz	scala/Either$;
class	scala/Either$
Asciz	<init>;
NameAndType	"<init>":()V
Method	scala/Either$."<init>":()V
Asciz	LineNumberTable;
Asciz	java/lang/Object;
class	java/lang/Object
Method	java/lang/Object."<init>":()V
NameAndType	MODULE$:Lscala/Either$;
Field	scala/Either$.MODULE$:Lscala/Either$;
Asciz	cond;
Asciz	(ZLscala/Function0;Lscala/Function0;)Lscala/Either;;
Asciz	scala/Right;
class	scala/Right
Asciz	scala/Function0;
class	scala/Function0
Asciz	apply;
Asciz	()Ljava/lang/Object;;
NameAndType	apply:()Ljava/lang/Object;
InterfaceMethod	scala/Function0.apply:()Ljava/lang/Object;
Asciz	(Ljava/lang/Object;)V;
NameAndType	"<init>":(Ljava/lang/Object;)V
Method	scala/Right."<init>":(Ljava/lang/Object;)V
Asciz	scala/Left;
class	scala/Left
Method	scala/Left."<init>":(Ljava/lang/Object;)V
Asciz	this;
Asciz	test;
Asciz	Z;
Asciz	right;
Asciz	Lscala/Function0;;
Asciz	left;
Asciz	LocalVariableTable;
Asciz	<A:Ljava/lang/Object;B:Ljava/lang/Object;>(ZLscala/Function0<TB;>;Lscala/Function0<TA;>;)Lscala/Either<TA;TB;>;;
Asciz	Signature;
Asciz	merge;
Asciz	(Lscala/Either;)Ljava/lang/Object;;
Asciz	a;
Asciz	Ljava/lang/Object;;
NameAndType	a:Ljava/lang/Object;
Field	scala/Left.a:Ljava/lang/Object;
Asciz	scala/MatchError;
class	scala/MatchError
Asciz	scala/Either;
class	scala/Either
Asciz	toString;
Asciz	()Ljava/lang/String;;
NameAndType	toString:()Ljava/lang/String;
Method	scala/Either.toString:()Ljava/lang/String;
Asciz	(Ljava/lang/String;)V;
NameAndType	"<init>":(Ljava/lang/String;)V
Method	scala/MatchError."<init>":(Ljava/lang/String;)V
Asciz	b;
NameAndType	b:Ljava/lang/Object;
Field	scala/Right.b:Ljava/lang/Object;
Asciz	e;
Asciz	Lscala/Either;;
Asciz	temp143;
Asciz	Lscala/Left;;
Asciz	temp144;
Asciz	temp145;
Asciz	Lscala/Right;;
Asciz	temp146;
Asciz	<T:Ljava/lang/Object;>(Lscala/Either<TT;TT;>;)TT;;
Asciz	joinRight;
Asciz	(Lscala/Either;)Lscala/Either;;
Asciz	()Lscala/Either$RightProjection;;
NameAndType	right:()Lscala/Either$RightProjection;
Method	scala/Either.right:()Lscala/Either$RightProjection;
Asciz	scala/Either$RightProjection;
class	scala/Either$RightProjection
NameAndType	e:Lscala/Either;
Field	scala/Either$RightProjection.e:Lscala/Either;
Asciz	es;
Asciz	$inlThis0;
Asciz	temp1140;
Asciz	temp1150;
Asciz	temp1160;
Asciz	temp1170;
Asciz	temp1130;
Asciz	<A:Ljava/lang/Object;B:Ljava/lang/Object;>(Lscala/Either<TA;Lscala/Either<TA;TB;>;>;)Lscala/Either<TA;TB;>;;
Asciz	joinLeft;
Asciz	()Lscala/Either$LeftProjection;;
NameAndType	left:()Lscala/Either$LeftProjection;
Method	scala/Either.left:()Lscala/Either$LeftProjection;
Asciz	scala/Either$LeftProjection;
class	scala/Either$LeftProjection
Field	scala/Either$LeftProjection.e:Lscala/Either;
Asciz	temp600;
Asciz	temp610;
Asciz	temp620;
Asciz	temp630;
Asciz	temp590;
Asciz	<A:Ljava/lang/Object;B:Ljava/lang/Object;>(Lscala/Either<Lscala/Either<TA;TB;>;TB;>;)Lscala/Either<TA;TB;>;;
Asciz	either2mergeable;
Asciz	(Lscala/Either;)Lscala/Either$MergeableEither;;
Asciz	scala/Either$MergeableEither;
class	scala/Either$MergeableEither
Asciz	(Lscala/Either;)V;
NameAndType	"<init>":(Lscala/Either;)V
Method	scala/Either$MergeableEither."<init>":(Lscala/Either;)V
Asciz	x;
Asciz	<A:Ljava/lang/Object;>(Lscala/Either<TA;TA;>;)Lscala/Either$MergeableEither<TA;>;;
Asciz	InnerClasses;
Asciz	LeftProjection;
Asciz	MergeableEither;
Asciz	RightProjection;
Asciz	scala/Either$$anonfun$joinLeft$1;
class	scala/Either$$anonfun$joinLeft$1
Asciz	$anonfun$joinLeft$1;
Asciz	scala/Either$$anonfun$joinRight$1;
class	scala/Either$$anonfun$joinRight$1
Asciz	$anonfun$joinRight$1;
Asciz	scala/ScalaObject;
class	scala/ScalaObject

{
public static final scala.Either$ MODULE$;
  Signature: Lscala/Either$;

public static {};
  Signature: ()V
  Code:
   Stack=1, Locals=0, Args_size=0
	new	class scala/Either$
	invokespecial	Method "<init>":()V
	return
  Labels:

private scala.Either$();
  Signature: ()V
  Code:
   Stack=1, Locals=1, Args_size=1
	aload_0
	invokespecial	Method java/lang/Object."<init>":()V
	aload_0
	putstatic	Field MODULE$:Lscala/Either$;
	return
  Labels:

public scala.Either cond(boolean, scala.Function0, scala.Function0);
  Signature: (ZLscala/Function0;Lscala/Function0;)Lscala/Either;
  Code:
   Stack=3, Locals=4, Args_size=4
	iload_1
	ifeq	l1 // new
	new	class scala/Right
	dup
	aload_2
	invokeinterface	InterfaceMethod scala/Function0.apply:()Ljava/lang/Object;
	invokespecial	Method scala/Right."<init>":(Ljava/lang/Object;)V
	goto	l2 // areturn
l1	new	class scala/Left
	dup
	aload_3
	invokeinterface	InterfaceMethod scala/Function0.apply:()Ljava/lang/Object;
	invokespecial	Method scala/Left."<init>":(Ljava/lang/Object;)V
l2	areturn
  Labels:
   	l1 = 20 // new
   	l2 = 33 // areturn
  LocalVariableTable: 
   Start  Length  Slot  Name   Signature
   0      34      0    this       Lscala/Either$;
   0      34      1    test       Z
   0      34      2    right       Lscala/Function0;
   0      34      3    left       Lscala/Function0;

  Signature: length = 0x2
   00 2B 

public java.lang.Object merge(scala.Either);
  Signature: (Lscala/Either;)Ljava/lang/Object;
  Code:
   Stack=3, Locals=6, Args_size=2
	aload_1
	instanceof	class scala/Left
	ifeq	l1 // aload_1
	aload_1
	checkcast	class scala/Left
	astore_2
	aload_2
	getfield	Field scala/Left.a:Ljava/lang/Object;
	astore_3
	iconst_1
	ifeq	l2 // new
	aload_3
	goto	l3 // areturn
l2	new	class scala/MatchError
	dup
	aload_1
	invokevirtual	Method scala/Either.toString:()Ljava/lang/String;
	invokespecial	Method scala/MatchError."<init>":(Ljava/lang/String;)V
	athrow
l1	aload_1
	instanceof	class scala/Right
	ifeq	l4 // new
	aload_1
	checkcast	class scala/Right
	astore	4
	aload	4
	getfield	Field scala/Right.b:Ljava/lang/Object;
	astore	5
	iconst_1
	ifeq	l5 // new
	aload	5
l3	areturn
l5	new	class scala/MatchError
	dup
	aload_1
	invokevirtual	Method scala/Either.toString:()Ljava/lang/String;
	invokespecial	Method scala/MatchError."<init>":(Ljava/lang/String;)V
	athrow
l4	new	class scala/MatchError
	dup
	aload_1
	invokevirtual	Method scala/Either.toString:()Ljava/lang/String;
	invokespecial	Method scala/MatchError."<init>":(Ljava/lang/String;)V
	athrow
  Labels:
   	l2 = 25 // new
   	l1 = 37 // aload_1
   	l3 = 63 // areturn
   	l5 = 64 // new
   	l4 = 76 // new
  LocalVariableTable: 
   Start  Length  Slot  Name   Signature
   0      88      0    this       Lscala/Either$;
   0      88      1    e       Lscala/Either;
   12      25      2    temp143       Lscala/Left;
   17      20      3    temp144       Ljava/lang/Object;
   50      13      4    temp145       Lscala/Right;
   64      12      4    temp145       Lscala/Right;
   57      6      5    temp146       Ljava/lang/Object;
   64      12      5    temp146       Ljava/lang/Object;

  Signature: length = 0x2
   00 49 

public scala.Either joinRight(scala.Either);
  Signature: (Lscala/Either;)Lscala/Either;
  Code:
   Stack=3, Locals=9, Args_size=2
	aload_1
	invokevirtual	Method scala/Either.right:()Lscala/Either$RightProjection;
	astore_2
	aload_2
	getfield	Field scala/Either$RightProjection.e:Lscala/Either;
	astore	8
	aload	8
	instanceof	class scala/Left
	ifeq	l1 // aload
	aload	8
	checkcast	class scala/Left
	astore_3
	aload_3
	getfield	Field scala/Left.a:Ljava/lang/Object;
	astore	4
	iconst_1
	ifeq	l2 // new
	new	class scala/Left
	dup
	aload	4
	invokespecial	Method scala/Left."<init>":(Ljava/lang/Object;)V
	goto	l3 // areturn
l2	new	class scala/MatchError
	dup
	aload	8
	invokevirtual	Method scala/Either.toString:()Ljava/lang/String;
	invokespecial	Method scala/MatchError."<init>":(Ljava/lang/String;)V
	athrow
l1	aload	8
	instanceof	class scala/Right
	ifeq	l4 // new
	aload	8
	checkcast	class scala/Right
	astore	5
	aload	5
	getfield	Field scala/Right.b:Ljava/lang/Object;
	astore	6
	iconst_1
	ifeq	l5 // new
	aload	6
	checkcast	class scala/Either
	astore	7
	aload	7
	checkcast	class scala/Either
l3	areturn
l5	new	class scala/MatchError
	dup
	aload	8
	invokevirtual	Method scala/Either.toString:()Ljava/lang/String;
	invokespecial	Method scala/MatchError."<init>":(Ljava/lang/String;)V
	athrow
l4	new	class scala/MatchError
	dup
	aload	8
	invokevirtual	Method scala/Either.toString:()Ljava/lang/String;
	invokespecial	Method scala/MatchError."<init>":(Ljava/lang/String;)V
	athrow
  Labels:
   	l2 = 47 // new
   	l1 = 60 // aload
   	l3 = 98 // areturn
   	l5 = 99 // new
   	l4 = 112 // new
  LocalVariableTable: 
   Start  Length  Slot  Name   Signature
   0      125      0    this       Lscala/Either$;
   0      125      1    es       Lscala/Either;
   19      106      2    $inlThis0       Ljava/lang/Object;
   25      35      3    temp1140       Lscala/Left;
   31      29      4    temp1150       Ljava/lang/Object;
   75      23      5    temp1160       Lscala/Right;
   99      13      5    temp1160       Lscala/Right;
   82      16      6    temp1170       Ljava/lang/Object;
   99      13      6    temp1170       Ljava/lang/Object;
   11      114      8    temp1130       Lscala/Either;

  Signature: length = 0x2
   00 5A 

public scala.Either joinLeft(scala.Either);
  Signature: (Lscala/Either;)Lscala/Either;
  Code:
   Stack=3, Locals=9, Args_size=2
	aload_1
	invokevirtual	Method scala/Either.left:()Lscala/Either$LeftProjection;
	astore_2
	aload_2
	getfield	Field scala/Either$LeftProjection.e:Lscala/Either;
	astore	8
	aload	8
	instanceof	class scala/Left
	ifeq	l1 // aload
	aload	8
	checkcast	class scala/Left
	astore_3
	aload_3
	getfield	Field scala/Left.a:Ljava/lang/Object;
	astore	4
	iconst_1
	ifeq	l2 // new
	aload	4
	checkcast	class scala/Either
	astore	5
	aload	5
	checkcast	class scala/Either
	goto	l3 // areturn
l2	new	class scala/MatchError
	dup
	aload	8
	invokevirtual	Method scala/Either.toString:()Ljava/lang/String;
	invokespecial	Method scala/MatchError."<init>":(Ljava/lang/String;)V
	athrow
l1	aload	8
	instanceof	class scala/Right
	ifeq	l4 // new
	aload	8
	checkcast	class scala/Right
	astore	6
	aload	6
	getfield	Field scala/Right.b:Ljava/lang/Object;
	astore	7
	iconst_1
	ifeq	l5 // new
	new	class scala/Right
	dup
	aload	7
	invokespecial	Method scala/Right."<init>":(Ljava/lang/Object;)V
l3	areturn
l5	new	class scala/MatchError
	dup
	aload	8
	invokevirtual	Method scala/Either.toString:()Ljava/lang/String;
	invokespecial	Method scala/MatchError."<init>":(Ljava/lang/String;)V
	athrow
l4	new	class scala/MatchError
	dup
	aload	8
	invokevirtual	Method scala/Either.toString:()Ljava/lang/String;
	invokespecial	Method scala/MatchError."<init>":(Ljava/lang/String;)V
	athrow
  Labels:
   	l2 = 50 // new
   	l1 = 63 // aload
   	l3 = 98 // areturn
   	l5 = 99 // new
   	l4 = 112 // new
  LocalVariableTable: 
   Start  Length  Slot  Name   Signature
   0      125      0    this       Lscala/Either$;
   0      125      1    es       Lscala/Either;
   19      106      2    $inlThis0       Ljava/lang/Object;
   25      38      3    temp600       Lscala/Left;
   31      32      4    temp610       Ljava/lang/Object;
   78      20      6    temp620       Lscala/Right;
   99      13      6    temp620       Lscala/Right;
   85      13      7    temp630       Ljava/lang/Object;
   99      13      7    temp630       Ljava/lang/Object;
   11      114      8    temp590       Lscala/Either;

  Signature: length = 0x2
   00 67 

public scala.Either$MergeableEither either2mergeable(scala.Either);
  Signature: (Lscala/Either;)Lscala/Either$MergeableEither;
  Code:
   Stack=3, Locals=2, Args_size=2
	new	class scala/Either$MergeableEither
	dup
	aload_1
	invokespecial	Method scala/Either$MergeableEither."<init>":(Lscala/Either;)V
	areturn
  Labels:
  LocalVariableTable: 
   Start  Length  Slot  Name   Signature
   0      9      0    this       Lscala/Either$;
   0      9      1    x       Lscala/Either;

  Signature: length = 0x2
   00 70 

}

