Compiled from "Either.scala"
public final class scala.Either$RightProjection extends java.lang.Object implements scala.ScalaObject,scala.Product,java.io.Serializable
  SourceFile: "Either.scala"
  Signature: length = 0x2
   00 FFFFFFF1 
  Scala: length = 0x
   
  InnerClass: 
   public final RightProjection=class scala/Either$RightProjection of class scala/Either
  minor version: 0
  major version: 49
  Constant pool:
Asciz	SourceFile;
Asciz	Either.scala;
Asciz	e;
Asciz	Lscala/Either;;
Asciz	Lscala/Either<TA;TB;>;;
Asciz	Signature;
Asciz	<init>;
Asciz	(Lscala/Either;)V;
Asciz	Code;
Asciz	LineNumberTable;
Asciz	scala/Either$RightProjection;
class	scala/Either$RightProjection
NameAndType	e:Lscala/Either;
Field	scala/Either$RightProjection.e:Lscala/Either;
Asciz	java/lang/Object;
class	java/lang/Object
Asciz	()V;
NameAndType	"<init>":()V
Method	java/lang/Object."<init>":()V
Asciz	scala/Product$class;
class	scala/Product$class
Asciz	$init$;
Asciz	(Lscala/Product;)V;
NameAndType	$init$:(Lscala/Product;)V
Method	scala/Product$class.$init$:(Lscala/Product;)V
Asciz	this;
Asciz	Lscala/Either$RightProjection;;
Asciz	LocalVariableTable;
Asciz	(Lscala/Either<TA;TB;>;)V;
Asciz	gd4$1;
Asciz	(Lscala/Either;)Z;
Asciz	equals;
Asciz	(Ljava/lang/Object;)Z;
NameAndType	equals:(Ljava/lang/Object;)Z
Method	java/lang/Object.equals:(Ljava/lang/Object;)Z
Asciz	canEqual;
Asciz	productElement;
Asciz	(I)Ljava/lang/Object;;
Asciz	scala/MatchError;
class	scala/MatchError
Asciz	scala/runtime/BoxesRunTime;
class	scala/runtime/BoxesRunTime
Asciz	boxToInteger;
Asciz	(I)Ljava/lang/Integer;;
NameAndType	boxToInteger:(I)Ljava/lang/Integer;
Method	scala/runtime/BoxesRunTime.boxToInteger:(I)Ljava/lang/Integer;
Asciz	toString;
Asciz	()Ljava/lang/String;;
NameAndType	toString:()Ljava/lang/String;
Method	java/lang/Object.toString:()Ljava/lang/String;
Asciz	(Ljava/lang/String;)V;
NameAndType	"<init>":(Ljava/lang/String;)V
Method	scala/MatchError."<init>":(Ljava/lang/String;)V
Asciz	java/lang/IndexOutOfBoundsException;
class	java/lang/IndexOutOfBoundsException
Method	java/lang/IndexOutOfBoundsException."<init>":(Ljava/lang/String;)V
Asciz	productArity;
Asciz	()I;
Asciz	productPrefix;
Asciz	RightProjection;
String	RightProjection
NameAndType	gd4$1:(Lscala/Either;)Z
Method	scala/Either$RightProjection.gd4$1:(Lscala/Either;)Z
Asciz	temp139;
Asciz	temp140;
Asciz	scala/runtime/ScalaRunTime$;
class	scala/runtime/ScalaRunTime$
Asciz	MODULE$;
Asciz	Lscala/runtime/ScalaRunTime$;;
NameAndType	MODULE$:Lscala/runtime/ScalaRunTime$;
Field	scala/runtime/ScalaRunTime$.MODULE$:Lscala/runtime/ScalaRunTime$;
Asciz	_toString;
Asciz	(Lscala/Product;)Ljava/lang/String;;
NameAndType	_toString:(Lscala/Product;)Ljava/lang/String;
Method	scala/runtime/ScalaRunTime$._toString:(Lscala/Product;)Ljava/lang/String;
Asciz	hashCode;
Asciz	_hashCode;
Asciz	(Lscala/Product;)I;
NameAndType	_hashCode:(Lscala/Product;)I
Method	scala/runtime/ScalaRunTime$._hashCode:(Lscala/Product;)I
Asciz	copy;
Asciz	(Lscala/Either;)Lscala/Either$RightProjection;;
NameAndType	"<init>":(Lscala/Either;)V
Method	scala/Either$RightProjection."<init>":(Lscala/Either;)V
Asciz	toOption;
Asciz	()Lscala/Option;;
Asciz	scala/Left;
class	scala/Left
Asciz	scala/None$;
class	scala/None$
Asciz	Lscala/None$;;
NameAndType	MODULE$:Lscala/None$;
Field	scala/None$.MODULE$:Lscala/None$;
Asciz	scala/Either;
class	scala/Either
Method	scala/Either.toString:()Ljava/lang/String;
Asciz	scala/Right;
class	scala/Right
Asciz	b;
Asciz	Ljava/lang/Object;;
NameAndType	b:Ljava/lang/Object;
Field	scala/Right.b:Ljava/lang/Object;
Asciz	scala/Some;
class	scala/Some
Asciz	(Ljava/lang/Object;)V;
NameAndType	"<init>":(Ljava/lang/Object;)V
Method	scala/Some."<init>":(Ljava/lang/Object;)V
Asciz	temp136;
Asciz	Lscala/Right;;
Asciz	temp137;
Asciz	temp133;
Asciz	()Lscala/Option<TB;>;;
Asciz	toSeq;
Asciz	()Lscala/collection/Seq;;
Asciz	scala/collection/Seq$;
class	scala/collection/Seq$
Asciz	Lscala/collection/Seq$;;
NameAndType	MODULE$:Lscala/collection/Seq$;
Field	scala/collection/Seq$.MODULE$:Lscala/collection/Seq$;
Asciz	empty;
Asciz	()Lscala/collection/Traversable;;
NameAndType	empty:()Lscala/collection/Traversable;
Method	scala/collection/Seq$.empty:()Lscala/collection/Traversable;
Asciz	scala/collection/Seq;
class	scala/collection/Seq
Asciz	scala/Predef$;
class	scala/Predef$
Asciz	Lscala/Predef$;;
NameAndType	MODULE$:Lscala/Predef$;
Field	scala/Predef$.MODULE$:Lscala/Predef$;
Asciz	genericWrapArray;
Asciz	(Ljava/lang/Object;)Lscala/collection/mutable/WrappedArray;;
NameAndType	genericWrapArray:(Ljava/lang/Object;)Lscala/collection/mutable/WrappedArray;
Method	scala/Predef$.genericWrapArray:(Ljava/lang/Object;)Lscala/collection/mutable/WrappedArray;
Asciz	apply;
Asciz	(Lscala/collection/Seq;)Lscala/collection/Traversable;;
NameAndType	apply:(Lscala/collection/Seq;)Lscala/collection/Traversable;
Method	scala/collection/Seq$.apply:(Lscala/collection/Seq;)Lscala/collection/Traversable;
Asciz	temp131;
Asciz	temp132;
Asciz	temp128;
Asciz	()Lscala/collection/Seq<TB;>;;
Asciz	filter;
Asciz	(Lscala/Function1;)Lscala/Option;;
Asciz	scala/Function1;
class	scala/Function1
Asciz	(Ljava/lang/Object;)Ljava/lang/Object;;
NameAndType	apply:(Ljava/lang/Object;)Ljava/lang/Object;
InterfaceMethod	scala/Function1.apply:(Ljava/lang/Object;)Ljava/lang/Object;
Asciz	unboxToBoolean;
NameAndType	unboxToBoolean:(Ljava/lang/Object;)Z
Method	scala/runtime/BoxesRunTime.unboxToBoolean:(Ljava/lang/Object;)Z
Method	scala/Right."<init>":(Ljava/lang/Object;)V
Asciz	p;
Asciz	Lscala/Function1;;
Asciz	temp126;
Asciz	temp127;
Asciz	temp123;
Asciz	<X:Ljava/lang/Object;>(Lscala/Function1<TB;Ljava/lang/Boolean;>;)Lscala/Option<Lscala/Either<TX;TB;>;>;;
Asciz	map;
Asciz	(Lscala/Function1;)Lscala/Product;;
Asciz	a;
NameAndType	a:Ljava/lang/Object;
Field	scala/Left.a:Ljava/lang/Object;
Method	scala/Left."<init>":(Ljava/lang/Object;)V
Asciz	f;
Asciz	temp119;
Asciz	Lscala/Left;;
Asciz	temp120;
Asciz	temp121;
Asciz	temp122;
Asciz	temp118;
Asciz	<Y:Ljava/lang/Object;>(Lscala/Function1<TB;TY;>;)Lscala/Product;;
Asciz	flatMap;
Asciz	(Lscala/Function1;)Lscala/Either;;
Asciz	temp114;
Asciz	temp115;
Asciz	temp116;
Asciz	temp117;
Asciz	temp113;
Asciz	<AA:Ljava/lang/Object;Y:Ljava/lang/Object;>(Lscala/Function1<TB;Lscala/Either<TAA;TY;>;>;)Lscala/Either<TAA;TY;>;;
Asciz	exists;
Asciz	(Lscala/Function1;)Z;
Asciz	temp111;
Asciz	temp112;
Asciz	temp108;
Asciz	(Lscala/Function1<TB;Ljava/lang/Boolean;>;)Z;
Asciz	forall;
Asciz	temp106;
Asciz	temp107;
Asciz	temp103;
Asciz	getOrElse;
Asciz	(Lscala/Function0;)Ljava/lang/Object;;
Asciz	scala/Function0;
class	scala/Function0
Asciz	()Ljava/lang/Object;;
NameAndType	apply:()Ljava/lang/Object;
InterfaceMethod	scala/Function0.apply:()Ljava/lang/Object;
Asciz	or;
Asciz	Lscala/Function0;;
Asciz	temp101;
Asciz	temp102;
Asciz	temp98;
Asciz	<BB:Ljava/lang/Object;>(Lscala/Function0<TBB;>;)TBB;;
Asciz	foreach;
Asciz	(Lscala/Function1;)Ljava/lang/Object;;
Asciz	scala/runtime/BoxedUnit;
class	scala/runtime/BoxedUnit
Asciz	UNIT;
Asciz	Lscala/runtime/BoxedUnit;;
NameAndType	UNIT:Lscala/runtime/BoxedUnit;
Field	scala/runtime/BoxedUnit.UNIT:Lscala/runtime/BoxedUnit;
Asciz	temp96;
Asciz	temp97;
Asciz	temp93;
Asciz	<U:Ljava/lang/Object;>(Lscala/Function1<TB;TU;>;)Ljava/lang/Object;;
Asciz	get;
Asciz	java/util/NoSuchElementException;
class	java/util/NoSuchElementException
Asciz	Either.right.value on Left;
String	Either.right.value on Left
Method	java/util/NoSuchElementException."<init>":(Ljava/lang/String;)V
Asciz	temp91;
Asciz	temp92;
Asciz	temp88;
Asciz	()TB;;
Asciz	()Lscala/Either;;
Asciz	()Lscala/Either<TA;TB;>;;
Asciz	copy$default$1;
NameAndType	e:()Lscala/Either;
Method	scala/Either$RightProjection.e:()Lscala/Either;
Asciz	productElements;
Asciz	()Lscala/collection/Iterator;;
Asciz	(Lscala/Product;)Lscala/collection/Iterator;;
NameAndType	productElements:(Lscala/Product;)Lscala/collection/Iterator;
Method	scala/Product$class.productElements:(Lscala/Product;)Lscala/collection/Iterator;
Asciz	Deprecated;
Asciz	productIterator;
NameAndType	productIterator:(Lscala/Product;)Lscala/collection/Iterator;
Method	scala/Product$class.productIterator:(Lscala/Product;)Lscala/collection/Iterator;
Asciz	<A:Ljava/lang/Object;B:Ljava/lang/Object;>Ljava/lang/Object;Lscala/ScalaObject;Lscala/Product;;
Asciz	Scala;
Asciz	InnerClasses;
Asciz	scala/ScalaObject;
class	scala/ScalaObject
Asciz	scala/Product;
class	scala/Product
Asciz	java/io/Serializable;
class	java/io/Serializable

{
public final scala.Either e;
  Signature: Lscala/Either;
  Signature: length = 0x2
   00 05 

public scala.Either$RightProjection(scala.Either);
  Signature: (Lscala/Either;)V
  Code:
   Stack=2, Locals=2, Args_size=2
	aload_0
	aload_1
	putfield	Field e:Lscala/Either;
	aload_0
	invokespecial	Method java/lang/Object."<init>":()V
	aload_0
	invokestatic	Method scala/Product$class.$init$:(Lscala/Product;)V
	return
  Labels:
  LocalVariableTable: 
   Start  Length  Slot  Name   Signature
   0      14      0    this       Lscala/Either$RightProjection;
   0      14      1    e       Lscala/Either;

  Signature: length = 0x2
   00 1D 

private final boolean gd4$1(scala.Either);
  Signature: (Lscala/Either;)Z
  Code:
   Stack=2, Locals=3, Args_size=2
	aload_1
	aload_0
	getfield	Field e:Lscala/Either;
	astore_2
	dup
	ifnonnull	l1 // aload_2
	pop
	aload_2
	ifnull	l2 // iconst_1
	goto	l3 // iconst_0
l1	aload_2
	invokevirtual	Method java/lang/Object.equals:(Ljava/lang/Object;)Z
	ifeq	l3 // iconst_0
l2	iconst_1
	goto	l4 // ireturn
l3	iconst_0
l4	ireturn
  Labels:
   	l1 = 18 // aload_2
   	l2 = 25 // iconst_1
   	l3 = 29 // iconst_0
   	l4 = 30 // ireturn

public boolean canEqual(java.lang.Object);
  Signature: (Ljava/lang/Object;)Z
  Code:
   Stack=1, Locals=2, Args_size=2
	aload_1
	instanceof	class scala/Either$RightProjection
	ireturn
  Labels:

public java.lang.Object productElement(int);
  Signature: (I)Ljava/lang/Object;
  Code:
   Stack=3, Locals=2, Args_size=2
	iload_1
	iconst_0
	if_icmpne	l1 // iconst_1
	iconst_1
	ifeq	l2 // new
	aload_0
	getfield	Field e:Lscala/Either;
	areturn
l2	new	class scala/MatchError
	dup
	iload_1
	invokestatic	Method scala/runtime/BoxesRunTime.boxToInteger:(I)Ljava/lang/Integer;
	invokevirtual	Method java/lang/Object.toString:()Ljava/lang/String;
	invokespecial	Method scala/MatchError."<init>":(Ljava/lang/String;)V
	athrow
l1	iconst_1
	ifeq	l3 // new
	new	class java/lang/IndexOutOfBoundsException
	dup
	iload_1
	invokestatic	Method scala/runtime/BoxesRunTime.boxToInteger:(I)Ljava/lang/Integer;
	invokevirtual	Method java/lang/Object.toString:()Ljava/lang/String;
	invokespecial	Method java/lang/IndexOutOfBoundsException."<init>":(Ljava/lang/String;)V
	athrow
l3	new	class scala/MatchError
	dup
	iload_1
	invokestatic	Method scala/runtime/BoxesRunTime.boxToInteger:(I)Ljava/lang/Integer;
	invokevirtual	Method java/lang/Object.toString:()Ljava/lang/String;
	invokespecial	Method scala/MatchError."<init>":(Ljava/lang/String;)V
	athrow
  Labels:
   	l2 = 14 // new
   	l1 = 29 // iconst_1
   	l3 = 48 // new

public int productArity();
  Signature: ()I
  Code:
   Stack=1, Locals=1, Args_size=1
	iconst_1
	ireturn
  Labels:

public java.lang.String productPrefix();
  Signature: ()Ljava/lang/String;
  Code:
   Stack=1, Locals=1, Args_size=1
	ldc	String RightProjection
	areturn
  Labels:

public boolean equals(java.lang.Object);
  Signature: (Ljava/lang/Object;)Z
  Code:
   Stack=3, Locals=4, Args_size=2
	aload_0
	aload_1
	if_acmpeq	l1 // iconst_1
	aload_1
	instanceof	class scala/Either$RightProjection
	ifeq	l2 // iconst_1
	aload_1
	checkcast	class scala/Either$RightProjection
	astore_2
	aload_2
	getfield	Field e:Lscala/Either;
	astore_3
	aload_0
	aload_3
	invokespecial	Method gd4$1:(Lscala/Either;)Z
	ifeq	l3 // iconst_1
	aload_0
	instanceof	class scala/Either$RightProjection
	goto	l4 // ifeq
l3	iconst_1
	ifeq	l5 // new
	iconst_0
	goto	l4 // ifeq
l5	new	class scala/MatchError
	dup
	aload_1
	invokevirtual	Method java/lang/Object.toString:()Ljava/lang/String;
	invokespecial	Method scala/MatchError."<init>":(Ljava/lang/String;)V
	athrow
l2	iconst_1
	ifeq	l6 // new
	iconst_0
l4	ifeq	l7 // iconst_0
l1	iconst_1
	goto	l8 // ireturn
l7	iconst_0
l8	ireturn
l6	new	class scala/MatchError
	dup
	aload_1
	invokevirtual	Method java/lang/Object.toString:()Ljava/lang/String;
	invokespecial	Method scala/MatchError."<init>":(Ljava/lang/String;)V
	athrow
  Labels:
   	l3 = 37 // iconst_1
   	l5 = 45 // new
   	l2 = 57 // iconst_1
   	l4 = 62 // ifeq
   	l1 = 65 // iconst_1
   	l7 = 69 // iconst_0
   	l8 = 70 // ireturn
   	l6 = 71 // new
  LocalVariableTable: 
   Start  Length  Slot  Name   Signature
   0      83      0    this       Lscala/Either$RightProjection;
   17      40      2    temp139       Lscala/Either$RightProjection;
   22      35      3    temp140       Lscala/Either;


public java.lang.String toString();
  Signature: ()Ljava/lang/String;
  Code:
   Stack=2, Locals=1, Args_size=1
	getstatic	Field scala/runtime/ScalaRunTime$.MODULE$:Lscala/runtime/ScalaRunTime$;
	aload_0
	invokevirtual	Method scala/runtime/ScalaRunTime$._toString:(Lscala/Product;)Ljava/lang/String;
	areturn
  Labels:

public int hashCode();
  Signature: ()I
  Code:
   Stack=2, Locals=1, Args_size=1
	getstatic	Field scala/runtime/ScalaRunTime$.MODULE$:Lscala/runtime/ScalaRunTime$;
	aload_0
	invokevirtual	Method scala/runtime/ScalaRunTime$._hashCode:(Lscala/Product;)I
	ireturn
  Labels:

public scala.Either$RightProjection copy(scala.Either);
  Signature: (Lscala/Either;)Lscala/Either$RightProjection;
  Code:
   Stack=3, Locals=2, Args_size=2
	new	class scala/Either$RightProjection
	dup
	aload_1
	invokespecial	Method "<init>":(Lscala/Either;)V
	areturn
  Labels:
  LocalVariableTable: 
   Start  Length  Slot  Name   Signature
   0      9      0    this       Lscala/Either$RightProjection;
   0      9      1    e       Lscala/Either;


public scala.Option toOption();
  Signature: ()Lscala/Option;
  Code:
   Stack=3, Locals=4, Args_size=1
	aload_0
	getfield	Field e:Lscala/Either;
	astore_3
	aload_3
	instanceof	class scala/Left
	ifeq	l1 // aload_3
	iconst_1
	ifeq	l2 // new
	getstatic	Field scala/None$.MODULE$:Lscala/None$;
	goto	l3 // areturn
l2	new	class scala/MatchError
	dup
	aload_3
	invokevirtual	Method scala/Either.toString:()Ljava/lang/String;
	invokespecial	Method scala/MatchError."<init>":(Ljava/lang/String;)V
	athrow
l1	aload_3
	instanceof	class scala/Right
	ifeq	l4 // new
	aload_3
	checkcast	class scala/Right
	astore_1
	aload_1
	getfield	Field scala/Right.b:Ljava/lang/Object;
	astore_2
	iconst_1
	ifeq	l5 // new
	new	class scala/Some
	dup
	aload_2
	invokespecial	Method scala/Some."<init>":(Ljava/lang/Object;)V
l3	areturn
l5	new	class scala/MatchError
	dup
	aload_3
	invokevirtual	Method scala/Either.toString:()Ljava/lang/String;
	invokespecial	Method scala/MatchError."<init>":(Ljava/lang/String;)V
	athrow
l4	new	class scala/MatchError
	dup
	aload_3
	invokevirtual	Method scala/Either.toString:()Ljava/lang/String;
	invokespecial	Method scala/MatchError."<init>":(Ljava/lang/String;)V
	athrow
  Labels:
   	l2 = 22 // new
   	l1 = 34 // aload_3
   	l3 = 63 // areturn
   	l5 = 64 // new
   	l4 = 76 // new
  LocalVariableTable: 
   Start  Length  Slot  Name   Signature
   0      88      0    this       Lscala/Either$RightProjection;
   46      17      1    temp136       Lscala/Right;
   64      12      1    temp136       Lscala/Right;
   51      12      2    temp137       Ljava/lang/Object;
   64      12      2    temp137       Ljava/lang/Object;
   5      83      3    temp133       Lscala/Either;

  Signature: length = 0x2
   00 70 

public scala.collection.Seq toSeq();
  Signature: ()Lscala/collection/Seq;
  Code:
   Stack=6, Locals=4, Args_size=1
	aload_0
	getfield	Field e:Lscala/Either;
	astore_3
	aload_3
	instanceof	class scala/Left
	ifeq	l1 // aload_3
	iconst_1
	ifeq	l2 // new
	getstatic	Field scala/collection/Seq$.MODULE$:Lscala/collection/Seq$;
	invokevirtual	Method scala/collection/Seq$.empty:()Lscala/collection/Traversable;
	checkcast	class scala/collection/Seq
	goto	l3 // areturn
l2	new	class scala/MatchError
	dup
	aload_3
	invokevirtual	Method scala/Either.toString:()Ljava/lang/String;
	invokespecial	Method scala/MatchError."<init>":(Ljava/lang/String;)V
	athrow
l1	aload_3
	instanceof	class scala/Right
	ifeq	l4 // new
	aload_3
	checkcast	class scala/Right
	astore_1
	aload_1
	getfield	Field scala/Right.b:Ljava/lang/Object;
	astore_2
	iconst_1
	ifeq	l5 // new
	getstatic	Field scala/collection/Seq$.MODULE$:Lscala/collection/Seq$;
	getstatic	Field scala/Predef$.MODULE$:Lscala/Predef$;
	iconst_1
	anewarray	class java/lang/Object
	dup
	iconst_0
	aload_2
	aastore
	invokevirtual	Method scala/Predef$.genericWrapArray:(Ljava/lang/Object;)Lscala/collection/mutable/WrappedArray;
	invokevirtual	Method scala/collection/Seq$.apply:(Lscala/collection/Seq;)Lscala/collection/Traversable;
	checkcast	class scala/collection/Seq
l3	areturn
l5	new	class scala/MatchError
	dup
	aload_3
	invokevirtual	Method scala/Either.toString:()Ljava/lang/String;
	invokespecial	Method scala/MatchError."<init>":(Ljava/lang/String;)V
	athrow
l4	new	class scala/MatchError
	dup
	aload_3
	invokevirtual	Method scala/Either.toString:()Ljava/lang/String;
	invokespecial	Method scala/MatchError."<init>":(Ljava/lang/String;)V
	athrow
  Labels:
   	l2 = 28 // new
   	l1 = 40 // aload_3
   	l3 = 84 // areturn
   	l5 = 85 // new
   	l4 = 97 // new
  LocalVariableTable: 
   Start  Length  Slot  Name   Signature
   0      109      0    this       Lscala/Either$RightProjection;
   52      32      1    temp131       Lscala/Right;
   85      12      1    temp131       Lscala/Right;
   57      27      2    temp132       Ljava/lang/Object;
   85      12      2    temp132       Ljava/lang/Object;
   5      104      3    temp128       Lscala/Either;

  Signature: length = 0x2
   00 FFFFFF8E 

public scala.Option filter(scala.Function1);
  Signature: (Lscala/Function1;)Lscala/Option;
  Code:
   Stack=5, Locals=5, Args_size=2
	aload_0
	getfield	Field e:Lscala/Either;
	astore	4
	aload	4
	instanceof	class scala/Left
	ifeq	l1 // aload
	iconst_1
	ifeq	l2 // new
	getstatic	Field scala/None$.MODULE$:Lscala/None$;
	goto	l3 // areturn
l2	new	class scala/MatchError
	dup
	aload	4
	invokevirtual	Method scala/Either.toString:()Ljava/lang/String;
	invokespecial	Method scala/MatchError."<init>":(Ljava/lang/String;)V
	athrow
l1	aload	4
	instanceof	class scala/Right
	ifeq	l4 // new
	aload	4
	checkcast	class scala/Right
	astore_2
	aload_2
	getfield	Field scala/Right.b:Ljava/lang/Object;
	astore_3
	iconst_1
	ifeq	l5 // new
	aload_1
	aload_3
	invokeinterface	InterfaceMethod scala/Function1.apply:(Ljava/lang/Object;)Ljava/lang/Object;
	invokestatic	Method scala/runtime/BoxesRunTime.unboxToBoolean:(Ljava/lang/Object;)Z
	ifeq	l6 // getstatic
	new	class scala/Some
	dup
	new	class scala/Right
	dup
	aload_3
	invokespecial	Method scala/Right."<init>":(Ljava/lang/Object;)V
	invokespecial	Method scala/Some."<init>":(Ljava/lang/Object;)V
	goto	l3 // areturn
l6	getstatic	Field scala/None$.MODULE$:Lscala/None$;
l3	areturn
l5	new	class scala/MatchError
	dup
	aload	4
	invokevirtual	Method scala/Either.toString:()Ljava/lang/String;
	invokespecial	Method scala/MatchError."<init>":(Ljava/lang/String;)V
	athrow
l4	new	class scala/MatchError
	dup
	aload	4
	invokevirtual	Method scala/Either.toString:()Ljava/lang/String;
	invokespecial	Method scala/MatchError."<init>":(Ljava/lang/String;)V
	athrow
  Labels:
   	l2 = 24 // new
   	l1 = 37 // aload
   	l6 = 91 // getstatic
   	l3 = 94 // areturn
   	l5 = 95 // new
   	l4 = 108 // new
  LocalVariableTable: 
   Start  Length  Slot  Name   Signature
   0      121      0    this       Lscala/Either$RightProjection;
   0      121      1    p       Lscala/Function1;
   51      43      2    temp126       Lscala/Right;
   95      13      2    temp126       Lscala/Right;
   56      38      3    temp127       Ljava/lang/Object;
   95      13      3    temp127       Ljava/lang/Object;
   6      115      4    temp123       Lscala/Either;

  Signature: length = 0x2
   00 FFFFFF9F 

public scala.Product map(scala.Function1);
  Signature: (Lscala/Function1;)Lscala/Product;
  Code:
   Stack=4, Locals=7, Args_size=2
	aload_0
	getfield	Field e:Lscala/Either;
	astore	6
	aload	6
	instanceof	class scala/Left
	ifeq	l1 // aload
	aload	6
	checkcast	class scala/Left
	astore_2
	aload_2
	getfield	Field scala/Left.a:Ljava/lang/Object;
	astore_3
	iconst_1
	ifeq	l2 // new
	new	class scala/Left
	dup
	aload_3
	invokespecial	Method scala/Left."<init>":(Ljava/lang/Object;)V
	goto	l3 // areturn
l2	new	class scala/MatchError
	dup
	aload	6
	invokevirtual	Method scala/Either.toString:()Ljava/lang/String;
	invokespecial	Method scala/MatchError."<init>":(Ljava/lang/String;)V
	athrow
l1	aload	6
	instanceof	class scala/Right
	ifeq	l4 // new
	aload	6
	checkcast	class scala/Right
	astore	4
	aload	4
	getfield	Field scala/Right.b:Ljava/lang/Object;
	astore	5
	iconst_1
	ifeq	l5 // new
	new	class scala/Right
	dup
	aload_1
	aload	5
	invokeinterface	InterfaceMethod scala/Function1.apply:(Ljava/lang/Object;)Ljava/lang/Object;
	invokespecial	Method scala/Right."<init>":(Ljava/lang/Object;)V
l3	areturn
l5	new	class scala/MatchError
	dup
	aload	6
	invokevirtual	Method scala/Either.toString:()Ljava/lang/String;
	invokespecial	Method scala/MatchError."<init>":(Ljava/lang/String;)V
	athrow
l4	new	class scala/MatchError
	dup
	aload	6
	invokevirtual	Method scala/Either.toString:()Ljava/lang/String;
	invokespecial	Method scala/MatchError."<init>":(Ljava/lang/String;)V
	athrow
  Labels:
   	l2 = 40 // new
   	l1 = 53 // aload
   	l3 = 94 // areturn
   	l5 = 95 // new
   	l4 = 108 // new
  LocalVariableTable: 
   Start  Length  Slot  Name   Signature
   0      121      0    this       Lscala/Either$RightProjection;
   0      121      1    f       Lscala/Function1;
   20      33      2    temp119       Lscala/Left;
   25      28      3    temp120       Ljava/lang/Object;
   68      26      4    temp121       Lscala/Right;
   95      13      4    temp121       Lscala/Right;
   75      19      5    temp122       Ljava/lang/Object;
   95      13      5    temp122       Ljava/lang/Object;
   6      115      6    temp118       Lscala/Either;

  Signature: length = 0x2
   00 FFFFFFAD 

public scala.Either flatMap(scala.Function1);
  Signature: (Lscala/Function1;)Lscala/Either;
  Code:
   Stack=3, Locals=7, Args_size=2
	aload_0
	getfield	Field e:Lscala/Either;
	astore	6
	aload	6
	instanceof	class scala/Left
	ifeq	l1 // aload
	aload	6
	checkcast	class scala/Left
	astore_2
	aload_2
	getfield	Field scala/Left.a:Ljava/lang/Object;
	astore_3
	iconst_1
	ifeq	l2 // new
	new	class scala/Left
	dup
	aload_3
	invokespecial	Method scala/Left."<init>":(Ljava/lang/Object;)V
	goto	l3 // areturn
l2	new	class scala/MatchError
	dup
	aload	6
	invokevirtual	Method scala/Either.toString:()Ljava/lang/String;
	invokespecial	Method scala/MatchError."<init>":(Ljava/lang/String;)V
	athrow
l1	aload	6
	instanceof	class scala/Right
	ifeq	l4 // new
	aload	6
	checkcast	class scala/Right
	astore	4
	aload	4
	getfield	Field scala/Right.b:Ljava/lang/Object;
	astore	5
	iconst_1
	ifeq	l5 // new
	aload_1
	aload	5
	invokeinterface	InterfaceMethod scala/Function1.apply:(Ljava/lang/Object;)Ljava/lang/Object;
	checkcast	class scala/Either
l3	areturn
l5	new	class scala/MatchError
	dup
	aload	6
	invokevirtual	Method scala/Either.toString:()Ljava/lang/String;
	invokespecial	Method scala/MatchError."<init>":(Ljava/lang/String;)V
	athrow
l4	new	class scala/MatchError
	dup
	aload	6
	invokevirtual	Method scala/Either.toString:()Ljava/lang/String;
	invokespecial	Method scala/MatchError."<init>":(Ljava/lang/String;)V
	athrow
  Labels:
   	l2 = 40 // new
   	l1 = 53 // aload
   	l3 = 90 // areturn
   	l5 = 91 // new
   	l4 = 104 // new
  LocalVariableTable: 
   Start  Length  Slot  Name   Signature
   0      117      0    this       Lscala/Either$RightProjection;
   0      117      1    f       Lscala/Function1;
   20      33      2    temp114       Lscala/Left;
   25      28      3    temp115       Ljava/lang/Object;
   68      22      4    temp116       Lscala/Right;
   91      13      4    temp116       Lscala/Right;
   75      15      5    temp117       Ljava/lang/Object;
   91      13      5    temp117       Ljava/lang/Object;
   6      111      6    temp113       Lscala/Either;

  Signature: length = 0x2
   00 FFFFFFB5 

public boolean exists(scala.Function1);
  Signature: (Lscala/Function1;)Z
  Code:
   Stack=3, Locals=5, Args_size=2
	aload_0
	getfield	Field e:Lscala/Either;
	astore	4
	aload	4
	instanceof	class scala/Left
	ifeq	l1 // aload
	iconst_1
	ifeq	l2 // new
	iconst_0
	goto	l3 // ireturn
l2	new	class scala/MatchError
	dup
	aload	4
	invokevirtual	Method scala/Either.toString:()Ljava/lang/String;
	invokespecial	Method scala/MatchError."<init>":(Ljava/lang/String;)V
	athrow
l1	aload	4
	instanceof	class scala/Right
	ifeq	l4 // new
	aload	4
	checkcast	class scala/Right
	astore_2
	aload_2
	getfield	Field scala/Right.b:Ljava/lang/Object;
	astore_3
	iconst_1
	ifeq	l5 // new
	aload_1
	aload_3
	invokeinterface	InterfaceMethod scala/Function1.apply:(Ljava/lang/Object;)Ljava/lang/Object;
	invokestatic	Method scala/runtime/BoxesRunTime.unboxToBoolean:(Ljava/lang/Object;)Z
l3	ireturn
l5	new	class scala/MatchError
	dup
	aload	4
	invokevirtual	Method scala/Either.toString:()Ljava/lang/String;
	invokespecial	Method scala/MatchError."<init>":(Ljava/lang/String;)V
	athrow
l4	new	class scala/MatchError
	dup
	aload	4
	invokevirtual	Method scala/Either.toString:()Ljava/lang/String;
	invokespecial	Method scala/MatchError."<init>":(Ljava/lang/String;)V
	athrow
  Labels:
   	l2 = 22 // new
   	l1 = 35 // aload
   	l3 = 68 // ireturn
   	l5 = 69 // new
   	l4 = 82 // new
  LocalVariableTable: 
   Start  Length  Slot  Name   Signature
   0      95      0    this       Lscala/Either$RightProjection;
   0      95      1    f       Lscala/Function1;
   49      19      2    temp111       Lscala/Right;
   69      13      2    temp111       Lscala/Right;
   54      14      3    temp112       Ljava/lang/Object;
   69      13      3    temp112       Ljava/lang/Object;
   6      89      4    temp108       Lscala/Either;

  Signature: length = 0x2
   00 FFFFFFBB 

public boolean forall(scala.Function1);
  Signature: (Lscala/Function1;)Z
  Code:
   Stack=3, Locals=5, Args_size=2
	aload_0
	getfield	Field e:Lscala/Either;
	astore	4
	aload	4
	instanceof	class scala/Left
	ifeq	l1 // aload
	iconst_1
	ifeq	l2 // new
	iconst_1
	goto	l3 // ireturn
l2	new	class scala/MatchError
	dup
	aload	4
	invokevirtual	Method scala/Either.toString:()Ljava/lang/String;
	invokespecial	Method scala/MatchError."<init>":(Ljava/lang/String;)V
	athrow
l1	aload	4
	instanceof	class scala/Right
	ifeq	l4 // new
	aload	4
	checkcast	class scala/Right
	astore_2
	aload_2
	getfield	Field scala/Right.b:Ljava/lang/Object;
	astore_3
	iconst_1
	ifeq	l5 // new
	aload_1
	aload_3
	invokeinterface	InterfaceMethod scala/Function1.apply:(Ljava/lang/Object;)Ljava/lang/Object;
	invokestatic	Method scala/runtime/BoxesRunTime.unboxToBoolean:(Ljava/lang/Object;)Z
l3	ireturn
l5	new	class scala/MatchError
	dup
	aload	4
	invokevirtual	Method scala/Either.toString:()Ljava/lang/String;
	invokespecial	Method scala/MatchError."<init>":(Ljava/lang/String;)V
	athrow
l4	new	class scala/MatchError
	dup
	aload	4
	invokevirtual	Method scala/Either.toString:()Ljava/lang/String;
	invokespecial	Method scala/MatchError."<init>":(Ljava/lang/String;)V
	athrow
  Labels:
   	l2 = 22 // new
   	l1 = 35 // aload
   	l3 = 68 // ireturn
   	l5 = 69 // new
   	l4 = 82 // new
  LocalVariableTable: 
   Start  Length  Slot  Name   Signature
   0      95      0    this       Lscala/Either$RightProjection;
   0      95      1    f       Lscala/Function1;
   49      19      2    temp106       Lscala/Right;
   69      13      2    temp106       Lscala/Right;
   54      14      3    temp107       Ljava/lang/Object;
   69      13      3    temp107       Ljava/lang/Object;
   6      89      4    temp103       Lscala/Either;

  Signature: length = 0x2
   00 FFFFFFBB 

public java.lang.Object getOrElse(scala.Function0);
  Signature: (Lscala/Function0;)Ljava/lang/Object;
  Code:
   Stack=3, Locals=5, Args_size=2
	aload_0
	getfield	Field e:Lscala/Either;
	astore	4
	aload	4
	instanceof	class scala/Left
	ifeq	l1 // aload
	iconst_1
	ifeq	l2 // new
	aload_1
	invokeinterface	InterfaceMethod scala/Function0.apply:()Ljava/lang/Object;
	goto	l3 // areturn
l2	new	class scala/MatchError
	dup
	aload	4
	invokevirtual	Method scala/Either.toString:()Ljava/lang/String;
	invokespecial	Method scala/MatchError."<init>":(Ljava/lang/String;)V
	athrow
l1	aload	4
	instanceof	class scala/Right
	ifeq	l4 // new
	aload	4
	checkcast	class scala/Right
	astore_2
	aload_2
	getfield	Field scala/Right.b:Ljava/lang/Object;
	astore_3
	iconst_1
	ifeq	l5 // new
	aload_3
l3	areturn
l5	new	class scala/MatchError
	dup
	aload	4
	invokevirtual	Method scala/Either.toString:()Ljava/lang/String;
	invokespecial	Method scala/MatchError."<init>":(Ljava/lang/String;)V
	athrow
l4	new	class scala/MatchError
	dup
	aload	4
	invokevirtual	Method scala/Either.toString:()Ljava/lang/String;
	invokespecial	Method scala/MatchError."<init>":(Ljava/lang/String;)V
	athrow
  Labels:
   	l2 = 27 // new
   	l1 = 40 // aload
   	l3 = 64 // areturn
   	l5 = 65 // new
   	l4 = 78 // new
  LocalVariableTable: 
   Start  Length  Slot  Name   Signature
   0      91      0    this       Lscala/Either$RightProjection;
   0      91      1    or       Lscala/Function0;
   54      10      2    temp101       Lscala/Right;
   65      13      2    temp101       Lscala/Right;
   59      5      3    temp102       Ljava/lang/Object;
   65      13      3    temp102       Ljava/lang/Object;
   6      85      4    temp98       Lscala/Either;

  Signature: length = 0x2
   00 FFFFFFCC 

public java.lang.Object foreach(scala.Function1);
  Signature: (Lscala/Function1;)Ljava/lang/Object;
  Code:
   Stack=3, Locals=5, Args_size=2
	aload_0
	getfield	Field e:Lscala/Either;
	astore	4
	aload	4
	instanceof	class scala/Left
	ifeq	l1 // aload
	iconst_1
	ifeq	l2 // new
	getstatic	Field scala/runtime/BoxedUnit.UNIT:Lscala/runtime/BoxedUnit;
	goto	l3 // areturn
l2	new	class scala/MatchError
	dup
	aload	4
	invokevirtual	Method scala/Either.toString:()Ljava/lang/String;
	invokespecial	Method scala/MatchError."<init>":(Ljava/lang/String;)V
	athrow
l1	aload	4
	instanceof	class scala/Right
	ifeq	l4 // new
	aload	4
	checkcast	class scala/Right
	astore_2
	aload_2
	getfield	Field scala/Right.b:Ljava/lang/Object;
	astore_3
	iconst_1
	ifeq	l5 // new
	aload_1
	aload_3
	invokeinterface	InterfaceMethod scala/Function1.apply:(Ljava/lang/Object;)Ljava/lang/Object;
l3	areturn
l5	new	class scala/MatchError
	dup
	aload	4
	invokevirtual	Method scala/Either.toString:()Ljava/lang/String;
	invokespecial	Method scala/MatchError."<init>":(Ljava/lang/String;)V
	athrow
l4	new	class scala/MatchError
	dup
	aload	4
	invokevirtual	Method scala/Either.toString:()Ljava/lang/String;
	invokespecial	Method scala/MatchError."<init>":(Ljava/lang/String;)V
	athrow
  Labels:
   	l2 = 24 // new
   	l1 = 37 // aload
   	l3 = 67 // areturn
   	l5 = 68 // new
   	l4 = 81 // new
  LocalVariableTable: 
   Start  Length  Slot  Name   Signature
   0      94      0    this       Lscala/Either$RightProjection;
   0      94      1    f       Lscala/Function1;
   51      16      2    temp96       Lscala/Right;
   68      13      2    temp96       Lscala/Right;
   56      11      3    temp97       Ljava/lang/Object;
   68      13      3    temp97       Ljava/lang/Object;
   6      88      4    temp93       Lscala/Either;

  Signature: length = 0x2
   00 FFFFFFD8 

public java.lang.Object get();
  Signature: ()Ljava/lang/Object;
  Code:
   Stack=3, Locals=4, Args_size=1
	aload_0
	getfield	Field e:Lscala/Either;
	astore_3
	aload_3
	instanceof	class scala/Left
	ifeq	l1 // aload_3
	iconst_1
	ifeq	l2 // new
	new	class java/util/NoSuchElementException
	dup
	ldc	String Either.right.value on Left
	invokespecial	Method java/util/NoSuchElementException."<init>":(Ljava/lang/String;)V
	athrow
l2	new	class scala/MatchError
	dup
	aload_3
	invokevirtual	Method scala/Either.toString:()Ljava/lang/String;
	invokespecial	Method scala/MatchError."<init>":(Ljava/lang/String;)V
	athrow
l1	aload_3
	instanceof	class scala/Right
	ifeq	l3 // new
	aload_3
	checkcast	class scala/Right
	astore_1
	aload_1
	getfield	Field scala/Right.b:Ljava/lang/Object;
	astore_2
	iconst_1
	ifeq	l4 // new
	aload_2
	areturn
l4	new	class scala/MatchError
	dup
	aload_3
	invokevirtual	Method scala/Either.toString:()Ljava/lang/String;
	invokespecial	Method scala/MatchError."<init>":(Ljava/lang/String;)V
	athrow
l3	new	class scala/MatchError
	dup
	aload_3
	invokevirtual	Method scala/Either.toString:()Ljava/lang/String;
	invokespecial	Method scala/MatchError."<init>":(Ljava/lang/String;)V
	athrow
  Labels:
   	l2 = 26 // new
   	l1 = 38 // aload_3
   	l4 = 61 // new
   	l3 = 73 // new
  LocalVariableTable: 
   Start  Length  Slot  Name   Signature
   0      85      0    this       Lscala/Either$RightProjection;
   50      10      1    temp91       Lscala/Right;
   61      12      1    temp91       Lscala/Right;
   55      5      2    temp92       Ljava/lang/Object;
   61      12      2    temp92       Ljava/lang/Object;
   5      80      3    temp88       Lscala/Either;

  Signature: length = 0x2
   00 FFFFFFE2 

public scala.Either e();
  Signature: ()Lscala/Either;
  Code:
   Stack=1, Locals=1, Args_size=1
	aload_0
	getfield	Field e:Lscala/Either;
	areturn
  Labels:
  Signature: length = 0x2
   00 FFFFFFE4 

public scala.Either copy$default$1();
  Signature: ()Lscala/Either;
  Code:
   Stack=1, Locals=1, Args_size=1
	aload_0
	invokevirtual	Method e:()Lscala/Either;
	areturn
  Labels:

public scala.collection.Iterator productElements();
  Signature: ()Lscala/collection/Iterator;
  Code:
   Stack=1, Locals=1, Args_size=1
	aload_0
	invokestatic	Method scala/Product$class.productElements:(Lscala/Product;)Lscala/collection/Iterator;
	areturn
  Labels:
  Deprecated: true

public scala.collection.Iterator productIterator();
  Signature: ()Lscala/collection/Iterator;
  Code:
   Stack=1, Locals=1, Args_size=1
	aload_0
	invokestatic	Method scala/Product$class.productIterator:(Lscala/Product;)Lscala/collection/Iterator;
	areturn
  Labels:

}

