Compiled from "Either.scala"
public final class scala.Either$RightProjection extends java.lang.Object implements scala.ScalaObject,scala.Product,java.io.Serializable
  SourceFile: "Either.scala"
  Signature: length = 0x2
   00 FFFFFFF0 
  Scala: length = 0x
   
  InnerClass: 
   public final #60= #12 of #95; //RightProjection=class scala/Either$RightProjection of class scala/Either
  minor version: 0
  major version: 49
  Constant pool:
const #1 = Asciz	SourceFile;
const #2 = Asciz	Either.scala;
const #3 = Asciz	e;
const #4 = Asciz	Lscala/Either;;
const #5 = Asciz	Lscala/Either<TA;TB;>;;
const #6 = Asciz	Signature;
const #7 = Asciz	<init>;
const #8 = Asciz	(Lscala/Either;)V;
const #9 = Asciz	Code;
const #10 = Asciz	LineNumberTable;
const #11 = Asciz	scala/Either$RightProjection;
const #12 = class	#11;	//  scala/Either$RightProjection
const #13 = NameAndType	#3:#4;//  e:Lscala/Either;
const #14 = Field	#12.#13;	//  scala/Either$RightProjection.e:Lscala/Either;
const #15 = Asciz	java/lang/Object;
const #16 = class	#15;	//  java/lang/Object
const #17 = Asciz	()V;
const #18 = NameAndType	#7:#17;//  "<init>":()V
const #19 = Method	#16.#18;	//  java/lang/Object."<init>":()V
const #20 = Asciz	scala/Product$class;
const #21 = class	#20;	//  scala/Product$class
const #22 = Asciz	$init$;
const #23 = Asciz	(Lscala/Product;)V;
const #24 = NameAndType	#22:#23;//  $init$:(Lscala/Product;)V
const #25 = Method	#21.#24;	//  scala/Product$class.$init$:(Lscala/Product;)V
const #26 = Asciz	this;
const #27 = Asciz	Lscala/Either$RightProjection;;
const #28 = Asciz	LocalVariableTable;
const #29 = Asciz	(Lscala/Either<TA;TB;>;)V;
const #30 = Asciz	gd4$1;
const #31 = Asciz	(Lscala/Either;)Z;
const #32 = Asciz	equals;
const #33 = Asciz	(Ljava/lang/Object;)Z;
const #34 = NameAndType	#32:#33;//  equals:(Ljava/lang/Object;)Z
const #35 = Method	#16.#34;	//  java/lang/Object.equals:(Ljava/lang/Object;)Z
const #36 = Asciz	canEqual;
const #37 = Asciz	productElement;
const #38 = Asciz	(I)Ljava/lang/Object;;
const #39 = Asciz	scala/MatchError;
const #40 = class	#39;	//  scala/MatchError
const #41 = Asciz	scala/runtime/BoxesRunTime;
const #42 = class	#41;	//  scala/runtime/BoxesRunTime
const #43 = Asciz	boxToInteger;
const #44 = Asciz	(I)Ljava/lang/Integer;;
const #45 = NameAndType	#43:#44;//  boxToInteger:(I)Ljava/lang/Integer;
const #46 = Method	#42.#45;	//  scala/runtime/BoxesRunTime.boxToInteger:(I)Ljava/lang/Integer;
const #47 = Asciz	toString;
const #48 = Asciz	()Ljava/lang/String;;
const #49 = NameAndType	#47:#48;//  toString:()Ljava/lang/String;
const #50 = Method	#16.#49;	//  java/lang/Object.toString:()Ljava/lang/String;
const #51 = Asciz	(Ljava/lang/String;)V;
const #52 = NameAndType	#7:#51;//  "<init>":(Ljava/lang/String;)V
const #53 = Method	#40.#52;	//  scala/MatchError."<init>":(Ljava/lang/String;)V
const #54 = Asciz	java/lang/IndexOutOfBoundsException;
const #55 = class	#54;	//  java/lang/IndexOutOfBoundsException
const #56 = Method	#55.#52;	//  java/lang/IndexOutOfBoundsException."<init>":(Ljava/lang/String;)V
const #57 = Asciz	productArity;
const #58 = Asciz	()I;
const #59 = Asciz	productPrefix;
const #60 = Asciz	RightProjection;
const #61 = String	#60;	//  RightProjection
const #62 = NameAndType	#30:#31;//  gd4$1:(Lscala/Either;)Z
const #63 = Method	#12.#62;	//  scala/Either$RightProjection.gd4$1:(Lscala/Either;)Z
const #64 = Asciz	temp139;
const #65 = Asciz	temp140;
const #66 = Asciz	scala/runtime/ScalaRunTime$;
const #67 = class	#66;	//  scala/runtime/ScalaRunTime$
const #68 = Asciz	MODULE$;
const #69 = Asciz	Lscala/runtime/ScalaRunTime$;;
const #70 = NameAndType	#68:#69;//  MODULE$:Lscala/runtime/ScalaRunTime$;
const #71 = Field	#67.#70;	//  scala/runtime/ScalaRunTime$.MODULE$:Lscala/runtime/ScalaRunTime$;
const #72 = Asciz	_toString;
const #73 = Asciz	(Lscala/Product;)Ljava/lang/String;;
const #74 = NameAndType	#72:#73;//  _toString:(Lscala/Product;)Ljava/lang/String;
const #75 = Method	#67.#74;	//  scala/runtime/ScalaRunTime$._toString:(Lscala/Product;)Ljava/lang/String;
const #76 = Asciz	hashCode;
const #77 = Asciz	_hashCode;
const #78 = Asciz	(Lscala/Product;)I;
const #79 = NameAndType	#77:#78;//  _hashCode:(Lscala/Product;)I
const #80 = Method	#67.#79;	//  scala/runtime/ScalaRunTime$._hashCode:(Lscala/Product;)I
const #81 = Asciz	copy;
const #82 = Asciz	(Lscala/Either;)Lscala/Either$RightProjection;;
const #83 = NameAndType	#7:#8;//  "<init>":(Lscala/Either;)V
const #84 = Method	#12.#83;	//  scala/Either$RightProjection."<init>":(Lscala/Either;)V
const #85 = Asciz	toOption;
const #86 = Asciz	()Lscala/Option;;
const #87 = Asciz	scala/Left;
const #88 = class	#87;	//  scala/Left
const #89 = Asciz	scala/None$;
const #90 = class	#89;	//  scala/None$
const #91 = Asciz	Lscala/None$;;
const #92 = NameAndType	#68:#91;//  MODULE$:Lscala/None$;
const #93 = Field	#90.#92;	//  scala/None$.MODULE$:Lscala/None$;
const #94 = Asciz	scala/Either;
const #95 = class	#94;	//  scala/Either
const #96 = Method	#95.#49;	//  scala/Either.toString:()Ljava/lang/String;
const #97 = Asciz	scala/Right;
const #98 = class	#97;	//  scala/Right
const #99 = Asciz	b;
const #100 = Asciz	Ljava/lang/Object;;
const #101 = NameAndType	#99:#100;//  b:Ljava/lang/Object;
const #102 = Field	#98.#101;	//  scala/Right.b:Ljava/lang/Object;
const #103 = Asciz	scala/Some;
const #104 = class	#103;	//  scala/Some
const #105 = Asciz	(Ljava/lang/Object;)V;
const #106 = NameAndType	#7:#105;//  "<init>":(Ljava/lang/Object;)V
const #107 = Method	#104.#106;	//  scala/Some."<init>":(Ljava/lang/Object;)V
const #108 = Asciz	temp136;
const #109 = Asciz	Lscala/Right;;
const #110 = Asciz	temp137;
const #111 = Asciz	temp133;
const #112 = Asciz	()Lscala/Option<TB;>;;
const #113 = Asciz	toSeq;
const #114 = Asciz	()Lscala/collection/Seq;;
const #115 = Asciz	scala/collection/Seq$;
const #116 = class	#115;	//  scala/collection/Seq$
const #117 = Asciz	Lscala/collection/Seq$;;
const #118 = NameAndType	#68:#117;//  MODULE$:Lscala/collection/Seq$;
const #119 = Field	#116.#118;	//  scala/collection/Seq$.MODULE$:Lscala/collection/Seq$;
const #120 = Asciz	empty;
const #121 = Asciz	()Lscala/collection/Traversable;;
const #122 = NameAndType	#120:#121;//  empty:()Lscala/collection/Traversable;
const #123 = Method	#116.#122;	//  scala/collection/Seq$.empty:()Lscala/collection/Traversable;
const #124 = Asciz	scala/collection/Seq;
const #125 = class	#124;	//  scala/collection/Seq
const #126 = Asciz	scala/Predef$;
const #127 = class	#126;	//  scala/Predef$
const #128 = Asciz	Lscala/Predef$;;
const #129 = NameAndType	#68:#128;//  MODULE$:Lscala/Predef$;
const #130 = Field	#127.#129;	//  scala/Predef$.MODULE$:Lscala/Predef$;
const #131 = Asciz	genericWrapArray;
const #132 = Asciz	(Ljava/lang/Object;)Lscala/collection/mutable/WrappedArray;;
const #133 = NameAndType	#131:#132;//  genericWrapArray:(Ljava/lang/Object;)Lscala/collection/mutable/WrappedArray;
const #134 = Method	#127.#133;	//  scala/Predef$.genericWrapArray:(Ljava/lang/Object;)Lscala/collection/mutable/WrappedArray;
const #135 = Asciz	apply;
const #136 = Asciz	(Lscala/collection/Seq;)Lscala/collection/Traversable;;
const #137 = NameAndType	#135:#136;//  apply:(Lscala/collection/Seq;)Lscala/collection/Traversable;
const #138 = Method	#116.#137;	//  scala/collection/Seq$.apply:(Lscala/collection/Seq;)Lscala/collection/Traversable;
const #139 = Asciz	temp131;
const #140 = Asciz	temp132;
const #141 = Asciz	temp128;
const #142 = Asciz	()Lscala/collection/Seq<TB;>;;
const #143 = Asciz	filter;
const #144 = Asciz	(Lscala/Function1;)Lscala/Option;;
const #145 = Asciz	scala/Function1;
const #146 = class	#145;	//  scala/Function1
const #147 = Asciz	(Ljava/lang/Object;)Ljava/lang/Object;;
const #148 = NameAndType	#135:#147;//  apply:(Ljava/lang/Object;)Ljava/lang/Object;
const #149 = InterfaceMethod	#146.#148;	//  scala/Function1.apply:(Ljava/lang/Object;)Ljava/lang/Object;
const #150 = Asciz	unboxToBoolean;
const #151 = NameAndType	#150:#33;//  unboxToBoolean:(Ljava/lang/Object;)Z
const #152 = Method	#42.#151;	//  scala/runtime/BoxesRunTime.unboxToBoolean:(Ljava/lang/Object;)Z
const #153 = Method	#98.#106;	//  scala/Right."<init>":(Ljava/lang/Object;)V
const #154 = Asciz	p;
const #155 = Asciz	Lscala/Function1;;
const #156 = Asciz	temp126;
const #157 = Asciz	temp127;
const #158 = Asciz	temp123;
const #159 = Asciz	<X:Ljava/lang/Object;>(Lscala/Function1<TB;Ljava/lang/Boolean;>;)Lscala/Option<Lscala/Either<TX;TB;>;>;;
const #160 = Asciz	map;
const #161 = Asciz	(Lscala/Function1;)Lscala/Product;;
const #162 = Asciz	a;
const #163 = NameAndType	#162:#100;//  a:Ljava/lang/Object;
const #164 = Field	#88.#163;	//  scala/Left.a:Ljava/lang/Object;
const #165 = Method	#88.#106;	//  scala/Left."<init>":(Ljava/lang/Object;)V
const #166 = Asciz	f;
const #167 = Asciz	temp119;
const #168 = Asciz	Lscala/Left;;
const #169 = Asciz	temp120;
const #170 = Asciz	temp121;
const #171 = Asciz	temp122;
const #172 = Asciz	temp118;
const #173 = Asciz	<Y:Ljava/lang/Object;>(Lscala/Function1<TB;TY;>;)Lscala/Product;;
const #174 = Asciz	flatMap;
const #175 = Asciz	(Lscala/Function1;)Lscala/Either;;
const #176 = Asciz	temp114;
const #177 = Asciz	temp115;
const #178 = Asciz	temp116;
const #179 = Asciz	temp117;
const #180 = Asciz	temp113;
const #181 = Asciz	<AA:Ljava/lang/Object;Y:Ljava/lang/Object;>(Lscala/Function1<TB;Lscala/Either<TAA;TY;>;>;)Lscala/Either<TAA;TY;>;;
const #182 = Asciz	exists;
const #183 = Asciz	(Lscala/Function1;)Z;
const #184 = Asciz	temp111;
const #185 = Asciz	temp112;
const #186 = Asciz	temp108;
const #187 = Asciz	(Lscala/Function1<TB;Ljava/lang/Boolean;>;)Z;
const #188 = Asciz	forall;
const #189 = Asciz	temp106;
const #190 = Asciz	temp107;
const #191 = Asciz	temp103;
const #192 = Asciz	getOrElse;
const #193 = Asciz	(Lscala/Function0;)Ljava/lang/Object;;
const #194 = Asciz	scala/Function0;
const #195 = class	#194;	//  scala/Function0
const #196 = Asciz	()Ljava/lang/Object;;
const #197 = NameAndType	#135:#196;//  apply:()Ljava/lang/Object;
const #198 = InterfaceMethod	#195.#197;	//  scala/Function0.apply:()Ljava/lang/Object;
const #199 = Asciz	or;
const #200 = Asciz	Lscala/Function0;;
const #201 = Asciz	temp101;
const #202 = Asciz	temp102;
const #203 = Asciz	temp98;
const #204 = Asciz	<BB:Ljava/lang/Object;>(Lscala/Function0<TBB;>;)TBB;;
const #205 = Asciz	foreach;
const #206 = Asciz	(Lscala/Function1;)Ljava/lang/Object;;
const #207 = Asciz	scala/runtime/BoxedUnit;
const #208 = class	#207;	//  scala/runtime/BoxedUnit
const #209 = Asciz	UNIT;
const #210 = Asciz	Lscala/runtime/BoxedUnit;;
const #211 = NameAndType	#209:#210;//  UNIT:Lscala/runtime/BoxedUnit;
const #212 = Field	#208.#211;	//  scala/runtime/BoxedUnit.UNIT:Lscala/runtime/BoxedUnit;
const #213 = Asciz	temp96;
const #214 = Asciz	temp97;
const #215 = Asciz	temp93;
const #216 = Asciz	<U:Ljava/lang/Object;>(Lscala/Function1<TB;TU;>;)Ljava/lang/Object;;
const #217 = Asciz	get;
const #218 = Asciz	java/util/NoSuchElementException;
const #219 = class	#218;	//  java/util/NoSuchElementException
const #220 = Asciz	Either.right.value on Left;
const #221 = String	#220;	//  Either.right.value on Left
const #222 = Method	#219.#52;	//  java/util/NoSuchElementException."<init>":(Ljava/lang/String;)V
const #223 = Asciz	temp91;
const #224 = Asciz	temp92;
const #225 = Asciz	temp88;
const #226 = Asciz	()TB;;
const #227 = Asciz	()Lscala/Either;;
const #228 = Asciz	()Lscala/Either<TA;TB;>;;
const #229 = Asciz	copy$default$1;
const #230 = NameAndType	#3:#227;//  e:()Lscala/Either;
const #231 = Method	#12.#230;	//  scala/Either$RightProjection.e:()Lscala/Either;
const #232 = Asciz	productElements;
const #233 = Asciz	()Lscala/collection/Iterator;;
const #234 = Asciz	(Lscala/Product;)Lscala/collection/Iterator;;
const #235 = NameAndType	#232:#234;//  productElements:(Lscala/Product;)Lscala/collection/Iterator;
const #236 = Method	#21.#235;	//  scala/Product$class.productElements:(Lscala/Product;)Lscala/collection/Iterator;
const #237 = Asciz	productIterator;
const #238 = NameAndType	#237:#234;//  productIterator:(Lscala/Product;)Lscala/collection/Iterator;
const #239 = Method	#21.#238;	//  scala/Product$class.productIterator:(Lscala/Product;)Lscala/collection/Iterator;
const #240 = Asciz	<A:Ljava/lang/Object;B:Ljava/lang/Object;>Ljava/lang/Object;Lscala/ScalaObject;Lscala/Product;;
const #241 = Asciz	Scala;
const #242 = Asciz	InnerClasses;
const #243 = Asciz	scala/ScalaObject;
const #244 = class	#243;	//  scala/ScalaObject
const #245 = Asciz	scala/Product;
const #246 = class	#245;	//  scala/Product
const #247 = Asciz	java/io/Serializable;
const #248 = class	#247;	//  java/io/Serializable

{
public final scala.Either e;
  Signature: length = 0x2
   00 05 

public scala.Either$RightProjection(scala.Either);
  Code:
   Stack=2, Locals=2, Args_size=2
   0:	aload_0
   1:	aload_1
   2:	putfield	#14; //Field e:Lscala/Either;
   5:	aload_0
   6:	invokespecial	#19; //Method java/lang/Object."<init>":()V
   9:	aload_0
   10:	invokestatic	#25; //Method scala/Product$class.$init$:(Lscala/Product;)V
   13:	return
  LineNumberTable: 
   line 220: 0

  LocalVariableTable: 
   Start  Length  Slot  Name   Signature
   0      14      0    this       Lscala/Either$RightProjection;
   0      14      1    e       Lscala/Either;

  Signature: length = 0x2
   00 1D 

public boolean canEqual(java.lang.Object);
  Code:
   Stack=1, Locals=2, Args_size=2
   0:	aload_1
   1:	instanceof	#12; //class scala/Either$RightProjection
   4:	ireturn
  LineNumberTable: 
   line 220: 0


public java.lang.Object productElement(int);
  Code:
   Stack=3, Locals=2, Args_size=2
   0:	iload_1
   1:	iconst_0
   2:	if_icmpne	29
   5:	iconst_1
   6:	ifeq	14
   9:	aload_0
   10:	getfield	#14; //Field e:Lscala/Either;
   13:	areturn
   14:	new	#40; //class scala/MatchError
   17:	dup
   18:	iload_1
   19:	invokestatic	#46; //Method scala/runtime/BoxesRunTime.boxToInteger:(I)Ljava/lang/Integer;
   22:	invokevirtual	#50; //Method java/lang/Object.toString:()Ljava/lang/String;
   25:	invokespecial	#53; //Method scala/MatchError."<init>":(Ljava/lang/String;)V
   28:	athrow
   29:	iconst_1
   30:	ifeq	48
   33:	new	#55; //class java/lang/IndexOutOfBoundsException
   36:	dup
   37:	iload_1
   38:	invokestatic	#46; //Method scala/runtime/BoxesRunTime.boxToInteger:(I)Ljava/lang/Integer;
   41:	invokevirtual	#50; //Method java/lang/Object.toString:()Ljava/lang/String;
   44:	invokespecial	#56; //Method java/lang/IndexOutOfBoundsException."<init>":(Ljava/lang/String;)V
   47:	athrow
   48:	new	#40; //class scala/MatchError
   51:	dup
   52:	iload_1
   53:	invokestatic	#46; //Method scala/runtime/BoxesRunTime.boxToInteger:(I)Ljava/lang/Integer;
   56:	invokevirtual	#50; //Method java/lang/Object.toString:()Ljava/lang/String;
   59:	invokespecial	#53; //Method scala/MatchError."<init>":(Ljava/lang/String;)V
   62:	athrow
  LineNumberTable: 
   line 220: 0
   line 21: 5
   line 220: 9
   line 21: 29
   line 220: 33


public int productArity();
  Code:
   Stack=1, Locals=1, Args_size=1
   0:	iconst_1
   1:	ireturn
  LineNumberTable: 
   line 220: 0


public java.lang.String productPrefix();
  Code:
   Stack=1, Locals=1, Args_size=1
   0:	ldc	#61; //String RightProjection
   2:	areturn
  LineNumberTable: 
   line 220: 0


public boolean equals(java.lang.Object);
  Code:
   Stack=3, Locals=4, Args_size=2
   0:	aload_0
   1:	aload_1
   2:	if_acmpeq	65
   5:	aload_1
   6:	instanceof	#12; //class scala/Either$RightProjection
   9:	ifeq	57
   12:	aload_1
   13:	checkcast	#12; //class scala/Either$RightProjection
   16:	astore_2
   17:	aload_2
   18:	getfield	#14; //Field e:Lscala/Either;
   21:	astore_3
   22:	aload_0
   23:	aload_3
   24:	invokespecial	#63; //Method gd4$1:(Lscala/Either;)Z
   27:	ifeq	37
   30:	aload_0
   31:	instanceof	#12; //class scala/Either$RightProjection
   34:	goto	62
   37:	iconst_1
   38:	ifeq	45
   41:	iconst_0
   42:	goto	62
   45:	new	#40; //class scala/MatchError
   48:	dup
   49:	aload_1
   50:	invokevirtual	#50; //Method java/lang/Object.toString:()Ljava/lang/String;
   53:	invokespecial	#53; //Method scala/MatchError."<init>":(Ljava/lang/String;)V
   56:	athrow
   57:	iconst_1
   58:	ifeq	71
   61:	iconst_0
   62:	ifeq	69
   65:	iconst_1
   66:	goto	70
   69:	iconst_0
   70:	ireturn
   71:	new	#40; //class scala/MatchError
   74:	dup
   75:	aload_1
   76:	invokevirtual	#50; //Method java/lang/Object.toString:()Ljava/lang/String;
   79:	invokespecial	#53; //Method scala/MatchError."<init>":(Ljava/lang/String;)V
   82:	athrow
  LineNumberTable: 
   line 220: 0
   line 21: 37
   line 220: 45
   line 21: 57
   line 220: 62

  LocalVariableTable: 
   Start  Length  Slot  Name   Signature
   0      83      0    this       Lscala/Either$RightProjection;
   17      40      2    temp139       Lscala/Either$RightProjection;
   22      35      3    temp140       Lscala/Either;


public java.lang.String toString();
  Code:
   Stack=2, Locals=1, Args_size=1
   0:	getstatic	#71; //Field scala/runtime/ScalaRunTime$.MODULE$:Lscala/runtime/ScalaRunTime$;
   3:	aload_0
   4:	invokevirtual	#75; //Method scala/runtime/ScalaRunTime$._toString:(Lscala/Product;)Ljava/lang/String;
   7:	areturn
  LineNumberTable: 
   line 220: 0


public int hashCode();
  Code:
   Stack=2, Locals=1, Args_size=1
   0:	getstatic	#71; //Field scala/runtime/ScalaRunTime$.MODULE$:Lscala/runtime/ScalaRunTime$;
   3:	aload_0
   4:	invokevirtual	#80; //Method scala/runtime/ScalaRunTime$._hashCode:(Lscala/Product;)I
   7:	ireturn
  LineNumberTable: 
   line 220: 0


public scala.Either$RightProjection copy(scala.Either);
  Code:
   Stack=3, Locals=2, Args_size=2
   0:	new	#12; //class scala/Either$RightProjection
   3:	dup
   4:	aload_1
   5:	invokespecial	#84; //Method "<init>":(Lscala/Either;)V
   8:	areturn
  LineNumberTable: 
   line 220: 0

  LocalVariableTable: 
   Start  Length  Slot  Name   Signature
   0      9      0    this       Lscala/Either$RightProjection;
   0      9      1    e       Lscala/Either;


public scala.Option toOption();
  Code:
   Stack=3, Locals=4, Args_size=1
   0:	aload_0
   1:	getfield	#14; //Field e:Lscala/Either;
   4:	astore_3
   5:	aload_3
   6:	instanceof	#88; //class scala/Left
   9:	ifeq	34
   12:	iconst_1
   13:	ifeq	22
   16:	getstatic	#93; //Field scala/None$.MODULE$:Lscala/None$;
   19:	goto	63
   22:	new	#40; //class scala/MatchError
   25:	dup
   26:	aload_3
   27:	invokevirtual	#96; //Method scala/Either.toString:()Ljava/lang/String;
   30:	invokespecial	#53; //Method scala/MatchError."<init>":(Ljava/lang/String;)V
   33:	athrow
   34:	aload_3
   35:	instanceof	#98; //class scala/Right
   38:	ifeq	76
   41:	aload_3
   42:	checkcast	#98; //class scala/Right
   45:	astore_1
   46:	aload_1
   47:	getfield	#102; //Field scala/Right.b:Ljava/lang/Object;
   50:	astore_2
   51:	iconst_1
   52:	ifeq	64
   55:	new	#104; //class scala/Some
   58:	dup
   59:	aload_2
   60:	invokespecial	#107; //Method scala/Some."<init>":(Ljava/lang/Object;)V
   63:	areturn
   64:	new	#40; //class scala/MatchError
   67:	dup
   68:	aload_3
   69:	invokevirtual	#96; //Method scala/Either.toString:()Ljava/lang/String;
   72:	invokespecial	#53; //Method scala/MatchError."<init>":(Ljava/lang/String;)V
   75:	athrow
   76:	new	#40; //class scala/MatchError
   79:	dup
   80:	aload_3
   81:	invokevirtual	#96; //Method scala/Either.toString:()Ljava/lang/String;
   84:	invokespecial	#53; //Method scala/MatchError."<init>":(Ljava/lang/String;)V
   87:	athrow
  LineNumberTable: 
   line 307: 0
   line 21: 12
   line 308: 16
   line 307: 22
   line 21: 51
   line 309: 55
   line 307: 63

  LocalVariableTable: 
   Start  Length  Slot  Name   Signature
   0      88      0    this       Lscala/Either$RightProjection;
   46      17      1    temp136       Lscala/Right;
   64      12      1    temp136       Lscala/Right;
   51      12      2    temp137       Ljava/lang/Object;
   64      12      2    temp137       Ljava/lang/Object;
   5      83      3    temp133       Lscala/Either;

  Signature: length = 0x2
   00 70 

public scala.collection.Seq toSeq();
  Code:
   Stack=6, Locals=4, Args_size=1
   0:	aload_0
   1:	getfield	#14; //Field e:Lscala/Either;
   4:	astore_3
   5:	aload_3
   6:	instanceof	#88; //class scala/Left
   9:	ifeq	40
   12:	iconst_1
   13:	ifeq	28
   16:	getstatic	#119; //Field scala/collection/Seq$.MODULE$:Lscala/collection/Seq$;
   19:	invokevirtual	#123; //Method scala/collection/Seq$.empty:()Lscala/collection/Traversable;
   22:	checkcast	#125; //class scala/collection/Seq
   25:	goto	84
   28:	new	#40; //class scala/MatchError
   31:	dup
   32:	aload_3
   33:	invokevirtual	#96; //Method scala/Either.toString:()Ljava/lang/String;
   36:	invokespecial	#53; //Method scala/MatchError."<init>":(Ljava/lang/String;)V
   39:	athrow
   40:	aload_3
   41:	instanceof	#98; //class scala/Right
   44:	ifeq	97
   47:	aload_3
   48:	checkcast	#98; //class scala/Right
   51:	astore_1
   52:	aload_1
   53:	getfield	#102; //Field scala/Right.b:Ljava/lang/Object;
   56:	astore_2
   57:	iconst_1
   58:	ifeq	85
   61:	getstatic	#119; //Field scala/collection/Seq$.MODULE$:Lscala/collection/Seq$;
   64:	getstatic	#130; //Field scala/Predef$.MODULE$:Lscala/Predef$;
   67:	iconst_1
   68:	anewarray	#16; //class java/lang/Object
   71:	dup
   72:	iconst_0
   73:	aload_2
   74:	aastore
   75:	invokevirtual	#134; //Method scala/Predef$.genericWrapArray:(Ljava/lang/Object;)Lscala/collection/mutable/WrappedArray;
   78:	invokevirtual	#138; //Method scala/collection/Seq$.apply:(Lscala/collection/Seq;)Lscala/collection/Traversable;
   81:	checkcast	#125; //class scala/collection/Seq
   84:	areturn
   85:	new	#40; //class scala/MatchError
   88:	dup
   89:	aload_3
   90:	invokevirtual	#96; //Method scala/Either.toString:()Ljava/lang/String;
   93:	invokespecial	#53; //Method scala/MatchError."<init>":(Ljava/lang/String;)V
   96:	athrow
   97:	new	#40; //class scala/MatchError
   100:	dup
   101:	aload_3
   102:	invokevirtual	#96; //Method scala/Either.toString:()Ljava/lang/String;
   105:	invokespecial	#53; //Method scala/MatchError."<init>":(Ljava/lang/String;)V
   108:	athrow
  LineNumberTable: 
   line 299: 0
   line 21: 12
   line 300: 16
   line 299: 28
   line 21: 57
   line 301: 61
   line 299: 84

  LocalVariableTable: 
   Start  Length  Slot  Name   Signature
   0      109      0    this       Lscala/Either$RightProjection;
   52      32      1    temp131       Lscala/Right;
   85      12      1    temp131       Lscala/Right;
   57      27      2    temp132       Ljava/lang/Object;
   85      12      2    temp132       Ljava/lang/Object;
   5      104      3    temp128       Lscala/Either;

  Signature: length = 0x2
   00 FFFFFF8E 

public scala.Option filter(scala.Function1);
  Code:
   Stack=5, Locals=5, Args_size=2
   0:	aload_0
   1:	getfield	#14; //Field e:Lscala/Either;
   4:	astore	4
   6:	aload	4
   8:	instanceof	#88; //class scala/Left
   11:	ifeq	37
   14:	iconst_1
   15:	ifeq	24
   18:	getstatic	#93; //Field scala/None$.MODULE$:Lscala/None$;
   21:	goto	94
   24:	new	#40; //class scala/MatchError
   27:	dup
   28:	aload	4
   30:	invokevirtual	#96; //Method scala/Either.toString:()Ljava/lang/String;
   33:	invokespecial	#53; //Method scala/MatchError."<init>":(Ljava/lang/String;)V
   36:	athrow
   37:	aload	4
   39:	instanceof	#98; //class scala/Right
   42:	ifeq	108
   45:	aload	4
   47:	checkcast	#98; //class scala/Right
   50:	astore_2
   51:	aload_2
   52:	getfield	#102; //Field scala/Right.b:Ljava/lang/Object;
   55:	astore_3
   56:	iconst_1
   57:	ifeq	95
   60:	aload_1
   61:	aload_3
   62:	invokeinterface	#149,  2; //InterfaceMethod scala/Function1.apply:(Ljava/lang/Object;)Ljava/lang/Object;
   67:	invokestatic	#152; //Method scala/runtime/BoxesRunTime.unboxToBoolean:(Ljava/lang/Object;)Z
   70:	ifeq	91
   73:	new	#104; //class scala/Some
   76:	dup
   77:	new	#98; //class scala/Right
   80:	dup
   81:	aload_3
   82:	invokespecial	#153; //Method scala/Right."<init>":(Ljava/lang/Object;)V
   85:	invokespecial	#107; //Method scala/Some."<init>":(Ljava/lang/Object;)V
   88:	goto	94
   91:	getstatic	#93; //Field scala/None$.MODULE$:Lscala/None$;
   94:	areturn
   95:	new	#40; //class scala/MatchError
   98:	dup
   99:	aload	4
   101:	invokevirtual	#96; //Method scala/Either.toString:()Ljava/lang/String;
   104:	invokespecial	#53; //Method scala/MatchError."<init>":(Ljava/lang/String;)V
   107:	athrow
   108:	new	#40; //class scala/MatchError
   111:	dup
   112:	aload	4
   114:	invokevirtual	#96; //Method scala/Either.toString:()Ljava/lang/String;
   117:	invokespecial	#53; //Method scala/MatchError."<init>":(Ljava/lang/String;)V
   120:	athrow
  LineNumberTable: 
   line 291: 0
   line 21: 14
   line 292: 18
   line 291: 24
   line 21: 56
   line 293: 60
   line 291: 94

  LocalVariableTable: 
   Start  Length  Slot  Name   Signature
   0      121      0    this       Lscala/Either$RightProjection;
   0      121      1    p       Lscala/Function1;
   51      43      2    temp126       Lscala/Right;
   95      13      2    temp126       Lscala/Right;
   56      38      3    temp127       Ljava/lang/Object;
   95      13      3    temp127       Ljava/lang/Object;
   6      115      4    temp123       Lscala/Either;

  Signature: length = 0x2
   00 FFFFFF9F 

public scala.Product map(scala.Function1);
  Code:
   Stack=4, Locals=7, Args_size=2
   0:	aload_0
   1:	getfield	#14; //Field e:Lscala/Either;
   4:	astore	6
   6:	aload	6
   8:	instanceof	#88; //class scala/Left
   11:	ifeq	53
   14:	aload	6
   16:	checkcast	#88; //class scala/Left
   19:	astore_2
   20:	aload_2
   21:	getfield	#164; //Field scala/Left.a:Ljava/lang/Object;
   24:	astore_3
   25:	iconst_1
   26:	ifeq	40
   29:	new	#88; //class scala/Left
   32:	dup
   33:	aload_3
   34:	invokespecial	#165; //Method scala/Left."<init>":(Ljava/lang/Object;)V
   37:	goto	94
   40:	new	#40; //class scala/MatchError
   43:	dup
   44:	aload	6
   46:	invokevirtual	#96; //Method scala/Either.toString:()Ljava/lang/String;
   49:	invokespecial	#53; //Method scala/MatchError."<init>":(Ljava/lang/String;)V
   52:	athrow
   53:	aload	6
   55:	instanceof	#98; //class scala/Right
   58:	ifeq	108
   61:	aload	6
   63:	checkcast	#98; //class scala/Right
   66:	astore	4
   68:	aload	4
   70:	getfield	#102; //Field scala/Right.b:Ljava/lang/Object;
   73:	astore	5
   75:	iconst_1
   76:	ifeq	95
   79:	new	#98; //class scala/Right
   82:	dup
   83:	aload_1
   84:	aload	5
   86:	invokeinterface	#149,  2; //InterfaceMethod scala/Function1.apply:(Ljava/lang/Object;)Ljava/lang/Object;
   91:	invokespecial	#153; //Method scala/Right."<init>":(Ljava/lang/Object;)V
   94:	areturn
   95:	new	#40; //class scala/MatchError
   98:	dup
   99:	aload	6
   101:	invokevirtual	#96; //Method scala/Either.toString:()Ljava/lang/String;
   104:	invokespecial	#53; //Method scala/MatchError."<init>":(Ljava/lang/String;)V
   107:	athrow
   108:	new	#40; //class scala/MatchError
   111:	dup
   112:	aload	6
   114:	invokevirtual	#96; //Method scala/Either.toString:()Ljava/lang/String;
   117:	invokespecial	#53; //Method scala/MatchError."<init>":(Ljava/lang/String;)V
   120:	athrow
  LineNumberTable: 
   line 282: 0
   line 21: 25
   line 283: 29
   line 282: 40
   line 21: 75
   line 284: 79
   line 282: 94

  LocalVariableTable: 
   Start  Length  Slot  Name   Signature
   0      121      0    this       Lscala/Either$RightProjection;
   0      121      1    f       Lscala/Function1;
   20      33      2    temp119       Lscala/Left;
   25      28      3    temp120       Ljava/lang/Object;
   68      26      4    temp121       Lscala/Right;
   95      13      4    temp121       Lscala/Right;
   75      19      5    temp122       Ljava/lang/Object;
   95      13      5    temp122       Ljava/lang/Object;
   6      115      6    temp118       Lscala/Either;

  Signature: length = 0x2
   00 FFFFFFAD 

public scala.Either flatMap(scala.Function1);
  Code:
   Stack=3, Locals=7, Args_size=2
   0:	aload_0
   1:	getfield	#14; //Field e:Lscala/Either;
   4:	astore	6
   6:	aload	6
   8:	instanceof	#88; //class scala/Left
   11:	ifeq	53
   14:	aload	6
   16:	checkcast	#88; //class scala/Left
   19:	astore_2
   20:	aload_2
   21:	getfield	#164; //Field scala/Left.a:Ljava/lang/Object;
   24:	astore_3
   25:	iconst_1
   26:	ifeq	40
   29:	new	#88; //class scala/Left
   32:	dup
   33:	aload_3
   34:	invokespecial	#165; //Method scala/Left."<init>":(Ljava/lang/Object;)V
   37:	goto	90
   40:	new	#40; //class scala/MatchError
   43:	dup
   44:	aload	6
   46:	invokevirtual	#96; //Method scala/Either.toString:()Ljava/lang/String;
   49:	invokespecial	#53; //Method scala/MatchError."<init>":(Ljava/lang/String;)V
   52:	athrow
   53:	aload	6
   55:	instanceof	#98; //class scala/Right
   58:	ifeq	104
   61:	aload	6
   63:	checkcast	#98; //class scala/Right
   66:	astore	4
   68:	aload	4
   70:	getfield	#102; //Field scala/Right.b:Ljava/lang/Object;
   73:	astore	5
   75:	iconst_1
   76:	ifeq	91
   79:	aload_1
   80:	aload	5
   82:	invokeinterface	#149,  2; //InterfaceMethod scala/Function1.apply:(Ljava/lang/Object;)Ljava/lang/Object;
   87:	checkcast	#95; //class scala/Either
   90:	areturn
   91:	new	#40; //class scala/MatchError
   94:	dup
   95:	aload	6
   97:	invokevirtual	#96; //Method scala/Either.toString:()Ljava/lang/String;
   100:	invokespecial	#53; //Method scala/MatchError."<init>":(Ljava/lang/String;)V
   103:	athrow
   104:	new	#40; //class scala/MatchError
   107:	dup
   108:	aload	6
   110:	invokevirtual	#96; //Method scala/Either.toString:()Ljava/lang/String;
   113:	invokespecial	#53; //Method scala/MatchError."<init>":(Ljava/lang/String;)V
   116:	athrow
  LineNumberTable: 
   line 274: 0
   line 21: 25
   line 275: 29
   line 274: 40
   line 21: 75
   line 276: 79
   line 274: 90

  LocalVariableTable: 
   Start  Length  Slot  Name   Signature
   0      117      0    this       Lscala/Either$RightProjection;
   0      117      1    f       Lscala/Function1;
   20      33      2    temp114       Lscala/Left;
   25      28      3    temp115       Ljava/lang/Object;
   68      22      4    temp116       Lscala/Right;
   91      13      4    temp116       Lscala/Right;
   75      15      5    temp117       Ljava/lang/Object;
   91      13      5    temp117       Ljava/lang/Object;
   6      111      6    temp113       Lscala/Either;

  Signature: length = 0x2
   00 FFFFFFB5 

public boolean exists(scala.Function1);
  Code:
   Stack=3, Locals=5, Args_size=2
   0:	aload_0
   1:	getfield	#14; //Field e:Lscala/Either;
   4:	astore	4
   6:	aload	4
   8:	instanceof	#88; //class scala/Left
   11:	ifeq	35
   14:	iconst_1
   15:	ifeq	22
   18:	iconst_0
   19:	goto	68
   22:	new	#40; //class scala/MatchError
   25:	dup
   26:	aload	4
   28:	invokevirtual	#96; //Method scala/Either.toString:()Ljava/lang/String;
   31:	invokespecial	#53; //Method scala/MatchError."<init>":(Ljava/lang/String;)V
   34:	athrow
   35:	aload	4
   37:	instanceof	#98; //class scala/Right
   40:	ifeq	82
   43:	aload	4
   45:	checkcast	#98; //class scala/Right
   48:	astore_2
   49:	aload_2
   50:	getfield	#102; //Field scala/Right.b:Ljava/lang/Object;
   53:	astore_3
   54:	iconst_1
   55:	ifeq	69
   58:	aload_1
   59:	aload_3
   60:	invokeinterface	#149,  2; //InterfaceMethod scala/Function1.apply:(Ljava/lang/Object;)Ljava/lang/Object;
   65:	invokestatic	#152; //Method scala/runtime/BoxesRunTime.unboxToBoolean:(Ljava/lang/Object;)Z
   68:	ireturn
   69:	new	#40; //class scala/MatchError
   72:	dup
   73:	aload	4
   75:	invokevirtual	#96; //Method scala/Either.toString:()Ljava/lang/String;
   78:	invokespecial	#53; //Method scala/MatchError."<init>":(Ljava/lang/String;)V
   81:	athrow
   82:	new	#40; //class scala/MatchError
   85:	dup
   86:	aload	4
   88:	invokevirtual	#96; //Method scala/Either.toString:()Ljava/lang/String;
   91:	invokespecial	#53; //Method scala/MatchError."<init>":(Ljava/lang/String;)V
   94:	athrow
  LineNumberTable: 
   line 264: 0
   line 21: 14
   line 265: 18
   line 264: 22
   line 21: 54
   line 266: 58
   line 264: 68

  LocalVariableTable: 
   Start  Length  Slot  Name   Signature
   0      95      0    this       Lscala/Either$RightProjection;
   0      95      1    f       Lscala/Function1;
   49      19      2    temp111       Lscala/Right;
   69      13      2    temp111       Lscala/Right;
   54      14      3    temp112       Ljava/lang/Object;
   69      13      3    temp112       Ljava/lang/Object;
   6      89      4    temp108       Lscala/Either;

  Signature: length = 0x2
   00 FFFFFFBB 

public boolean forall(scala.Function1);
  Code:
   Stack=3, Locals=5, Args_size=2
   0:	aload_0
   1:	getfield	#14; //Field e:Lscala/Either;
   4:	astore	4
   6:	aload	4
   8:	instanceof	#88; //class scala/Left
   11:	ifeq	35
   14:	iconst_1
   15:	ifeq	22
   18:	iconst_1
   19:	goto	68
   22:	new	#40; //class scala/MatchError
   25:	dup
   26:	aload	4
   28:	invokevirtual	#96; //Method scala/Either.toString:()Ljava/lang/String;
   31:	invokespecial	#53; //Method scala/MatchError."<init>":(Ljava/lang/String;)V
   34:	athrow
   35:	aload	4
   37:	instanceof	#98; //class scala/Right
   40:	ifeq	82
   43:	aload	4
   45:	checkcast	#98; //class scala/Right
   48:	astore_2
   49:	aload_2
   50:	getfield	#102; //Field scala/Right.b:Ljava/lang/Object;
   53:	astore_3
   54:	iconst_1
   55:	ifeq	69
   58:	aload_1
   59:	aload_3
   60:	invokeinterface	#149,  2; //InterfaceMethod scala/Function1.apply:(Ljava/lang/Object;)Ljava/lang/Object;
   65:	invokestatic	#152; //Method scala/runtime/BoxesRunTime.unboxToBoolean:(Ljava/lang/Object;)Z
   68:	ireturn
   69:	new	#40; //class scala/MatchError
   72:	dup
   73:	aload	4
   75:	invokevirtual	#96; //Method scala/Either.toString:()Ljava/lang/String;
   78:	invokespecial	#53; //Method scala/MatchError."<init>":(Ljava/lang/String;)V
   81:	athrow
   82:	new	#40; //class scala/MatchError
   85:	dup
   86:	aload	4
   88:	invokevirtual	#96; //Method scala/Either.toString:()Ljava/lang/String;
   91:	invokespecial	#53; //Method scala/MatchError."<init>":(Ljava/lang/String;)V
   94:	athrow
  LineNumberTable: 
   line 255: 0
   line 21: 14
   line 256: 18
   line 255: 22
   line 21: 54
   line 257: 58
   line 255: 68

  LocalVariableTable: 
   Start  Length  Slot  Name   Signature
   0      95      0    this       Lscala/Either$RightProjection;
   0      95      1    f       Lscala/Function1;
   49      19      2    temp106       Lscala/Right;
   69      13      2    temp106       Lscala/Right;
   54      14      3    temp107       Ljava/lang/Object;
   69      13      3    temp107       Ljava/lang/Object;
   6      89      4    temp103       Lscala/Either;

  Signature: length = 0x2
   00 FFFFFFBB 

public java.lang.Object getOrElse(scala.Function0);
  Code:
   Stack=3, Locals=5, Args_size=2
   0:	aload_0
   1:	getfield	#14; //Field e:Lscala/Either;
   4:	astore	4
   6:	aload	4
   8:	instanceof	#88; //class scala/Left
   11:	ifeq	40
   14:	iconst_1
   15:	ifeq	27
   18:	aload_1
   19:	invokeinterface	#198,  1; //InterfaceMethod scala/Function0.apply:()Ljava/lang/Object;
   24:	goto	64
   27:	new	#40; //class scala/MatchError
   30:	dup
   31:	aload	4
   33:	invokevirtual	#96; //Method scala/Either.toString:()Ljava/lang/String;
   36:	invokespecial	#53; //Method scala/MatchError."<init>":(Ljava/lang/String;)V
   39:	athrow
   40:	aload	4
   42:	instanceof	#98; //class scala/Right
   45:	ifeq	78
   48:	aload	4
   50:	checkcast	#98; //class scala/Right
   53:	astore_2
   54:	aload_2
   55:	getfield	#102; //Field scala/Right.b:Ljava/lang/Object;
   58:	astore_3
   59:	iconst_1
   60:	ifeq	65
   63:	aload_3
   64:	areturn
   65:	new	#40; //class scala/MatchError
   68:	dup
   69:	aload	4
   71:	invokevirtual	#96; //Method scala/Either.toString:()Ljava/lang/String;
   74:	invokespecial	#53; //Method scala/MatchError."<init>":(Ljava/lang/String;)V
   77:	athrow
   78:	new	#40; //class scala/MatchError
   81:	dup
   82:	aload	4
   84:	invokevirtual	#96; //Method scala/Either.toString:()Ljava/lang/String;
   87:	invokespecial	#53; //Method scala/MatchError."<init>":(Ljava/lang/String;)V
   90:	athrow
  LineNumberTable: 
   line 246: 0
   line 21: 14
   line 247: 18
   line 246: 27
   line 21: 59
   line 248: 63
   line 246: 64

  LocalVariableTable: 
   Start  Length  Slot  Name   Signature
   0      91      0    this       Lscala/Either$RightProjection;
   0      91      1    or       Lscala/Function0;
   54      10      2    temp101       Lscala/Right;
   65      13      2    temp101       Lscala/Right;
   59      5      3    temp102       Ljava/lang/Object;
   65      13      3    temp102       Ljava/lang/Object;
   6      85      4    temp98       Lscala/Either;

  Signature: length = 0x2
   00 FFFFFFCC 

public java.lang.Object foreach(scala.Function1);
  Code:
   Stack=3, Locals=5, Args_size=2
   0:	aload_0
   1:	getfield	#14; //Field e:Lscala/Either;
   4:	astore	4
   6:	aload	4
   8:	instanceof	#88; //class scala/Left
   11:	ifeq	37
   14:	iconst_1
   15:	ifeq	24
   18:	getstatic	#212; //Field scala/runtime/BoxedUnit.UNIT:Lscala/runtime/BoxedUnit;
   21:	goto	67
   24:	new	#40; //class scala/MatchError
   27:	dup
   28:	aload	4
   30:	invokevirtual	#96; //Method scala/Either.toString:()Ljava/lang/String;
   33:	invokespecial	#53; //Method scala/MatchError."<init>":(Ljava/lang/String;)V
   36:	athrow
   37:	aload	4
   39:	instanceof	#98; //class scala/Right
   42:	ifeq	81
   45:	aload	4
   47:	checkcast	#98; //class scala/Right
   50:	astore_2
   51:	aload_2
   52:	getfield	#102; //Field scala/Right.b:Ljava/lang/Object;
   55:	astore_3
   56:	iconst_1
   57:	ifeq	68
   60:	aload_1
   61:	aload_3
   62:	invokeinterface	#149,  2; //InterfaceMethod scala/Function1.apply:(Ljava/lang/Object;)Ljava/lang/Object;
   67:	areturn
   68:	new	#40; //class scala/MatchError
   71:	dup
   72:	aload	4
   74:	invokevirtual	#96; //Method scala/Either.toString:()Ljava/lang/String;
   77:	invokespecial	#53; //Method scala/MatchError."<init>":(Ljava/lang/String;)V
   80:	athrow
   81:	new	#40; //class scala/MatchError
   84:	dup
   85:	aload	4
   87:	invokevirtual	#96; //Method scala/Either.toString:()Ljava/lang/String;
   90:	invokespecial	#53; //Method scala/MatchError."<init>":(Ljava/lang/String;)V
   93:	athrow
  LineNumberTable: 
   line 237: 0
   line 21: 14
   line 238: 18
   line 237: 24
   line 21: 56
   line 239: 60
   line 237: 67

  LocalVariableTable: 
   Start  Length  Slot  Name   Signature
   0      94      0    this       Lscala/Either$RightProjection;
   0      94      1    f       Lscala/Function1;
   51      16      2    temp96       Lscala/Right;
   68      13      2    temp96       Lscala/Right;
   56      11      3    temp97       Ljava/lang/Object;
   68      13      3    temp97       Ljava/lang/Object;
   6      88      4    temp93       Lscala/Either;

  Signature: length = 0x2
   00 FFFFFFD8 

public java.lang.Object get();
  Code:
   Stack=3, Locals=4, Args_size=1
   0:	aload_0
   1:	getfield	#14; //Field e:Lscala/Either;
   4:	astore_3
   5:	aload_3
   6:	instanceof	#88; //class scala/Left
   9:	ifeq	38
   12:	iconst_1
   13:	ifeq	26
   16:	new	#219; //class java/util/NoSuchElementException
   19:	dup
   20:	ldc	#221; //String Either.right.value on Left
   22:	invokespecial	#222; //Method java/util/NoSuchElementException."<init>":(Ljava/lang/String;)V
   25:	athrow
   26:	new	#40; //class scala/MatchError
   29:	dup
   30:	aload_3
   31:	invokevirtual	#96; //Method scala/Either.toString:()Ljava/lang/String;
   34:	invokespecial	#53; //Method scala/MatchError."<init>":(Ljava/lang/String;)V
   37:	athrow
   38:	aload_3
   39:	instanceof	#98; //class scala/Right
   42:	ifeq	73
   45:	aload_3
   46:	checkcast	#98; //class scala/Right
   49:	astore_1
   50:	aload_1
   51:	getfield	#102; //Field scala/Right.b:Ljava/lang/Object;
   54:	astore_2
   55:	iconst_1
   56:	ifeq	61
   59:	aload_2
   60:	areturn
   61:	new	#40; //class scala/MatchError
   64:	dup
   65:	aload_3
   66:	invokevirtual	#96; //Method scala/Either.toString:()Ljava/lang/String;
   69:	invokespecial	#53; //Method scala/MatchError."<init>":(Ljava/lang/String;)V
   72:	athrow
   73:	new	#40; //class scala/MatchError
   76:	dup
   77:	aload_3
   78:	invokevirtual	#96; //Method scala/Either.toString:()Ljava/lang/String;
   81:	invokespecial	#53; //Method scala/MatchError."<init>":(Ljava/lang/String;)V
   84:	athrow
  LineNumberTable: 
   line 227: 0
   line 21: 12
   line 228: 16
   line 227: 26
   line 21: 55
   line 229: 59
   line 227: 60

  LocalVariableTable: 
   Start  Length  Slot  Name   Signature
   0      85      0    this       Lscala/Either$RightProjection;
   50      10      1    temp91       Lscala/Right;
   61      12      1    temp91       Lscala/Right;
   55      5      2    temp92       Ljava/lang/Object;
   61      12      2    temp92       Ljava/lang/Object;
   5      80      3    temp88       Lscala/Either;

  Signature: length = 0x2
   00 FFFFFFE2 

public scala.Either e();
  Code:
   Stack=1, Locals=1, Args_size=1
   0:	aload_0
   1:	getfield	#14; //Field e:Lscala/Either;
   4:	areturn
  LineNumberTable: 
   line 220: 0

  Signature: length = 0x2
   00 FFFFFFE4 

public scala.Either copy$default$1();
  Code:
   Stack=1, Locals=1, Args_size=1
   0:	aload_0
   1:	invokevirtual	#231; //Method e:()Lscala/Either;
   4:	areturn
  LineNumberTable: 
   line 220: 0


public scala.collection.Iterator productElements();
  Code:
   Stack=1, Locals=1, Args_size=1
   0:	aload_0
   1:	invokestatic	#236; //Method scala/Product$class.productElements:(Lscala/Product;)Lscala/collection/Iterator;
   4:	areturn
  LineNumberTable: 
   line 220: 0


public scala.collection.Iterator productIterator();
  Code:
   Stack=1, Locals=1, Args_size=1
   0:	aload_0
   1:	invokestatic	#239; //Method scala/Product$class.productIterator:(Lscala/Product;)Lscala/collection/Iterator;
   4:	areturn
  LineNumberTable: 
   line 220: 0


}

