Compiled from "Either.scala"
public class scala.Either$MergeableEither extends java.lang.Object implements scala.ScalaObject
  SourceFile: "Either.scala"
  Signature: length = 0x2
   00 38 
  Scala: length = 0x
   
  InnerClass: 
   public #59= #12 of #35; //MergeableEither=class scala/Either$MergeableEither of class scala/Either
  minor version: 0
  major version: 49
  Constant pool:
const #1 = Asciz	SourceFile;
const #2 = Asciz	Either.scala;
const #3 = Asciz	x;
const #4 = Asciz	Lscala/Either;;
const #5 = Asciz	Lscala/Either<TA;TA;>;;
const #6 = Asciz	Signature;
const #7 = Asciz	<init>;
const #8 = Asciz	(Lscala/Either;)V;
const #9 = Asciz	Code;
const #10 = Asciz	LineNumberTable;
const #11 = Asciz	scala/Either$MergeableEither;
const #12 = class	#11;	//  scala/Either$MergeableEither
const #13 = NameAndType	#3:#4;//  x:Lscala/Either;
const #14 = Field	#12.#13;	//  scala/Either$MergeableEither.x:Lscala/Either;
const #15 = Asciz	java/lang/Object;
const #16 = class	#15;	//  java/lang/Object
const #17 = Asciz	()V;
const #18 = NameAndType	#7:#17;//  "<init>":()V
const #19 = Method	#16.#18;	//  java/lang/Object."<init>":()V
const #20 = Asciz	this;
const #21 = Asciz	Lscala/Either$MergeableEither;;
const #22 = Asciz	LocalVariableTable;
const #23 = Asciz	(Lscala/Either<TA;TA;>;)V;
const #24 = Asciz	merge;
const #25 = Asciz	()Ljava/lang/Object;;
const #26 = Asciz	scala/Left;
const #27 = class	#26;	//  scala/Left
const #28 = Asciz	a;
const #29 = Asciz	Ljava/lang/Object;;
const #30 = NameAndType	#28:#29;//  a:Ljava/lang/Object;
const #31 = Field	#27.#30;	//  scala/Left.a:Ljava/lang/Object;
const #32 = Asciz	scala/MatchError;
const #33 = class	#32;	//  scala/MatchError
const #34 = Asciz	scala/Either;
const #35 = class	#34;	//  scala/Either
const #36 = Asciz	toString;
const #37 = Asciz	()Ljava/lang/String;;
const #38 = NameAndType	#36:#37;//  toString:()Ljava/lang/String;
const #39 = Method	#35.#38;	//  scala/Either.toString:()Ljava/lang/String;
const #40 = Asciz	(Ljava/lang/String;)V;
const #41 = NameAndType	#7:#40;//  "<init>":(Ljava/lang/String;)V
const #42 = Method	#33.#41;	//  scala/MatchError."<init>":(Ljava/lang/String;)V
const #43 = Asciz	scala/Right;
const #44 = class	#43;	//  scala/Right
const #45 = Asciz	b;
const #46 = NameAndType	#45:#29;//  b:Ljava/lang/Object;
const #47 = Field	#44.#46;	//  scala/Right.b:Ljava/lang/Object;
const #48 = Asciz	temp30;
const #49 = Asciz	Lscala/Left;;
const #50 = Asciz	temp31;
const #51 = Asciz	temp32;
const #52 = Asciz	Lscala/Right;;
const #53 = Asciz	temp33;
const #54 = Asciz	temp29;
const #55 = Asciz	()TA;;
const #56 = Asciz	<A:Ljava/lang/Object;>Ljava/lang/Object;Lscala/ScalaObject;;
const #57 = Asciz	Scala;
const #58 = Asciz	InnerClasses;
const #59 = Asciz	MergeableEither;
const #60 = Asciz	scala/ScalaObject;
const #61 = class	#60;	//  scala/ScalaObject

{
public scala.Either$MergeableEither(scala.Either);
  Code:
   Stack=2, Locals=2, Args_size=2
   0:	aload_0
   1:	aload_1
   2:	putfield	#14; //Field x:Lscala/Either;
   5:	aload_0
   6:	invokespecial	#19; //Method java/lang/Object."<init>":()V
   9:	return
  LineNumberTable: 
   line 104: 0

  LocalVariableTable: 
   Start  Length  Slot  Name   Signature
   0      10      0    this       Lscala/Either$MergeableEither;
   0      10      1    x       Lscala/Either;

  Signature: length = 0x2
   00 17 

public java.lang.Object merge();
  Code:
   Stack=3, Locals=6, Args_size=1
   0:	aload_0
   1:	getfield	#14; //Field x:Lscala/Either;
   4:	astore	5
   6:	aload	5
   8:	instanceof	#27; //class scala/Left
   11:	ifeq	46
   14:	aload	5
   16:	checkcast	#27; //class scala/Left
   19:	astore_1
   20:	aload_1
   21:	getfield	#31; //Field scala/Left.a:Ljava/lang/Object;
   24:	astore_2
   25:	iconst_1
   26:	ifeq	33
   29:	aload_2
   30:	goto	72
   33:	new	#33; //class scala/MatchError
   36:	dup
   37:	aload	5
   39:	invokevirtual	#39; //Method scala/Either.toString:()Ljava/lang/String;
   42:	invokespecial	#42; //Method scala/MatchError."<init>":(Ljava/lang/String;)V
   45:	athrow
   46:	aload	5
   48:	instanceof	#44; //class scala/Right
   51:	ifeq	86
   54:	aload	5
   56:	checkcast	#44; //class scala/Right
   59:	astore_3
   60:	aload_3
   61:	getfield	#47; //Field scala/Right.b:Ljava/lang/Object;
   64:	astore	4
   66:	iconst_1
   67:	ifeq	73
   70:	aload	4
   72:	areturn
   73:	new	#33; //class scala/MatchError
   76:	dup
   77:	aload	5
   79:	invokevirtual	#39; //Method scala/Either.toString:()Ljava/lang/String;
   82:	invokespecial	#42; //Method scala/MatchError."<init>":(Ljava/lang/String;)V
   85:	athrow
   86:	new	#33; //class scala/MatchError
   89:	dup
   90:	aload	5
   92:	invokevirtual	#39; //Method scala/Either.toString:()Ljava/lang/String;
   95:	invokespecial	#42; //Method scala/MatchError."<init>":(Ljava/lang/String;)V
   98:	athrow
  LineNumberTable: 
   line 105: 0
   line 21: 25
   line 106: 29
   line 105: 33
   line 21: 66
   line 107: 70
   line 105: 72

  LocalVariableTable: 
   Start  Length  Slot  Name   Signature
   0      99      0    this       Lscala/Either$MergeableEither;
   20      26      1    temp30       Lscala/Left;
   25      21      2    temp31       Ljava/lang/Object;
   60      12      3    temp32       Lscala/Right;
   73      13      3    temp32       Lscala/Right;
   66      6      4    temp33       Ljava/lang/Object;
   73      13      4    temp33       Ljava/lang/Object;
   6      93      5    temp29       Lscala/Either;

  Signature: length = 0x2
   00 37 

}

