Compiled from "Either.scala"
public abstract class scala.Either extends java.lang.Object implements scala.ScalaObject
  SourceFile: "Either.scala"
  Signature: length = 0x2
   00 77 
  ScalaSig: length = 0x1015
   05 00 FFFFFF84 1E 06 05 01 02 FFFFFF81 10 05 02 06 45 69 74
   68 65 72 0A 01 03 01 05 73 63 61 6C 61 03 00 15
   03 06 19 23 13 03 00 07 0F 10 02 08 0D 0D 01 09
   0A 02 0A 0B 01 04 6C 61 6E 67 0A 01 0C 01 04 6A
   61 76 61 09 02 0E 09 02 06 4F 62 6A 65 63 74 10
   02 10 11 0D 01 02 09 02 12 02 02 0B 53 63 61 6C
   61 4F 62 6A 65 63 74 08 05 14 00 FFFFFF84 00 15 01 06
   3C 69 6E 69 74 3E 14 01 16 10 04 10 00 17 22 10
   02 18 19 0C 00 04 08 1A 00 FFFFFF84 FFFFFF80 FFFFFF84 FFFFFFC2 00 1B 02
   01 41 11 02 1C 1F 10 02 10 1D 09 02 1E 02 02 07
   4E 6F 74 68 69 6E 67 10 02 10 20 09 02 21 02 02
   03 41 6E 79 10 02 18 23 04 08 24 00 FFFFFF84 FFFFFF80 FFFFFF84 FFFFFFC2
   00 1B 02 01 42 08 05 26 00 FFFFFF84 00 27 01 04 6C 65
   66 74 15 01 28 10 04 29 4B 17 22 0E 02 10 2A 07
   05 2B 02 FFFFFF88 02 2C 01 06 45 69 74 68 65 72 10 02
   10 2D 06 08 01 02 FFFFFF84 FFFFFF80 FFFFFF80 FFFFFF88 02 2E 13 03 2D 07
   0F 08 05 14 2D FFFFFF84 00 30 14 01 2C 06 04 32 2D 00
   33 02 0F 4D 65 72 67 65 61 62 6C 65 45 69 74 68
   65 72 15 02 34 39 13 03 31 07 0F 08 08 36 31 FFFFFF82
   FFFFFF80 FFFFFFA0 FFFFFF80 04 37 01 01 78 10 04 10 00 38 38 10 02
   18 39 04 08 1A 31 FFFFFF84 FFFFFF80 FFFFFF80 FFFFFFC2 00 1B 08 05 14 31
   FFFFFF84 00 3B 14 02 3C 3E 10 03 3D 31 38 0D 01 2D 08
   05 36 3A FFFFFFC0 00 37 08 05 40 31 FFFFFF84 00 41 01 05 6D
   65 72 67 65 15 01 38 08 05 43 2D FFFFFF84 01 44 01 10
   65 69 74 68 65 72 32 6D 65 72 67 65 61 62 6C 65
   15 02 45 48 14 02 46 49 10 03 3D 31 47 10 02 18
   48 04 08 1A 42 FFFFFF84 FFFFFF80 FFFFFF80 FFFFFFC2 00 1B 08 05 36 42 FFFFFFC0
   00 4A 10 04 10 00 47 47 06 04 4C 2D 42 4D 02 0E
   4C 65 66 74 50 72 6F 6A 65 63 74 69 6F 6E 15 03
   4E 57 59 13 04 4B 07 0F 4F 10 02 10 50 09 02 51
   02 02 07 50 72 6F 64 75 63 74 08 08 53 4B FFFFFF82 FFFFFFCA
   FFFFFF80 FFFFFF84 00 54 01 01 65 15 01 55 10 04 10 00 56 58
   10 02 18 57 04 08 1A 4B FFFFFF84 FFFFFF80 FFFFFF84 FFFFFFC2 00 1B 10 02
   18 59 04 08 24 4B FFFFFF84 FFFFFF80 FFFFFF84 FFFFFFC2 00 1B 08 08 5B 4B
   FFFFFF82 FFFFFF88 FFFFFFA0 FFFFFF80 04 55 01 02 65 20 08 05 14 4B FFFFFF84 00
   5D 14 02 5E 5F 10 04 3D 4B 56 58 08 05 53 5C FFFFFFC0
   00 55 08 05 61 4B FFFFFF84 00 62 01 03 67 65 74 15 01
   56 08 05 64 4B FFFFFF84 00 65 01 07 66 6F 72 65 61 63
   68 15 02 66 6D 14 02 1F 67 08 05 68 63 FFFFFFC0 00 69
   01 01 66 10 04 10 6A 56 6C 09 02 6B 02 02 09 46
   75 6E 63 74 69 6F 6E 31 10 02 18 6D 04 08 6E 63
   FFFFFF84 FFFFFF80 FFFFFF80 FFFFFFC2 00 1B 02 01 55 08 05 70 4B FFFFFF84 00 71
   01 09 67 65 74 4F 72 45 6C 73 65 15 02 72 74 14
   02 73 77 10 02 18 74 04 08 75 6F FFFFFF84 FFFFFF80 FFFFFF80 FFFFFFC2 00
   76 02 02 41 41 11 02 56 1F 08 06 78 6F FFFFFF84 FFFFFFC0 00
   79 01 02 6F 72 10 03 10 7A 73 09 02 7B 02 02 08
   3C 62 79 6E 61 6D 65 3E 08 05 7D 4B FFFFFF84 00 7E 01
   06 66 6F 72 61 6C 6C 14 03 7F FFFFFF81 02 10 03 10 FFFFFF81
   00 09 03 FFFFFF81 01 02 02 07 42 6F 6F 6C 65 61 6E 08
   06 68 7C FFFFFFC0 00 FFFFFF81 03 10 04 10 6A 56 7F 08 07 FFFFFF81
   05 4B FFFFFF84 00 FFFFFF81 06 01 06 65 78 69 73 74 73 14 03
   7F FFFFFF81 07 08 07 68 FFFFFF81 04 FFFFFFC0 00 FFFFFF81 03 08 07 FFFFFF81 09
   4B FFFFFF84 00 FFFFFF81 0A 01 07 66 6C 61 74 4D 61 70 15 06
   FFFFFF81 0B FFFFFF81 11 FFFFFF81 0E 14 04 FFFFFF81 0C FFFFFF81 14 10 06 10 00
   FFFFFF81 0D FFFFFF81 10 10 03 18 FFFFFF81 0E 04 0A FFFFFF81 0F FFFFFF81 08 FFFFFF84
   FFFFFF80 FFFFFF80 FFFFFFC2 00 1B 02 01 58 10 03 18 FFFFFF81 11 04 0B FFFFFF81
   12 FFFFFF81 08 FFFFFF84 FFFFFF80 FFFFFF80 FFFFFFC2 00 FFFFFF81 13 02 02 42 42 11 02
   58 1F 08 07 68 FFFFFF81 08 FFFFFFC0 00 FFFFFF81 15 10 05 10 6A 56
   FFFFFF81 0C 08 07 FFFFFF81 17 4B FFFFFF84 00 FFFFFF81 18 01 03 6D 61 70
   15 04 FFFFFF81 19 FFFFFF81 1F 14 04 FFFFFF81 1A FFFFFF81 20 12 05 FFFFFF81 1B
   4F FFFFFF81 1D 06 0A FFFFFF81 1C 00 FFFFFF84 FFFFFF80 FFFFFF80 FFFFFF80 00 FFFFFF81 1A 02
   0C 3C 72 65 66 69 6E 65 6D 65 6E 74 3E 10 05 10
   00 FFFFFF81 1E 58 10 03 18 FFFFFF81 1F 04 0A FFFFFF81 0F FFFFFF81 16 FFFFFF84
   FFFFFF80 FFFFFF80 FFFFFFC2 00 1B 08 07 68 FFFFFF81 16 FFFFFFC0 00 FFFFFF81 21 10 05
   10 6A 56 FFFFFF81 1E 08 07 FFFFFF81 23 4B FFFFFF84 00 FFFFFF81 24 01 06
   66 69 6C 74 65 72 15 04 FFFFFF81 25 FFFFFF81 2B 14 04 FFFFFF81 26
   FFFFFF81 2D 10 05 10 FFFFFF81 27 FFFFFF81 29 09 03 FFFFFF81 28 02 02 06
   4F 70 74 69 6F 6E 10 05 10 00 56 FFFFFF81 2A 10 03 18
   FFFFFF81 2B 04 0A FFFFFF81 2C FFFFFF81 22 FFFFFF84 FFFFFF80 FFFFFF80 FFFFFFC2 00 1B 02 01
   59 08 08 FFFFFF81 2E FFFFFF81 22 FFFFFFC0 00 FFFFFF81 03 01 01 70 08 07
   FFFFFF81 30 4B FFFFFF84 00 FFFFFF81 31 01 05 74 6F 53 65 71 15 02
   FFFFFF81 32 10 05 FFFFFF81 33 FFFFFF81 36 56 0D 02 FFFFFF81 34 0A 03 FFFFFF81
   35 02 01 0A 63 6F 6C 6C 65 63 74 69 6F 6E 09 04
   FFFFFF81 37 FFFFFF81 34 02 03 53 65 71 08 07 FFFFFF81 39 4B FFFFFF84 00
   FFFFFF81 3A 01 08 74 6F 4F 70 74 69 6F 6E 15 02 FFFFFF81 3B
   10 04 10 FFFFFF81 27 56 08 09 FFFFFF81 3D 4B FFFFFF81 FFFFFF80 FFFFFF84 00 FFFFFF81
   3E 01 04 63 6F 70 79 15 06 FFFFFF81 3F FFFFFF81 42 FFFFFF81 44 14
   04 FFFFFF81 40 FFFFFF81 45 10 06 3D 4B FFFFFF81 41 FFFFFF81 43 10 03 18
   FFFFFF81 42 04 09 1A FFFFFF81 3C FFFFFF84 FFFFFF80 FFFFFF80 FFFFFFC2 00 1B 10 03 18
   FFFFFF81 44 04 09 24 FFFFFF81 3C FFFFFF84 FFFFFF80 FFFFFF80 FFFFFFC2 00 1B 08 0B FFFFFF81
   47 53 FFFFFF81 3C FFFFFF90 FFFFFF80 FFFFFFC0 00 FFFFFF81 46 10 06 10 00 FFFFFF81 41
   FFFFFF81 43 08 09 FFFFFF81 48 4B FFFFFF91 FFFFFF80 FFFFFF84 00 FFFFFF81 49 01 0E 63
   6F 70 79 24 64 65 66 61 75 6C 74 24 31 15 06 FFFFFF81
   4A FFFFFF81 54 FFFFFF81 55 2A 03 55 FFFFFF81 4B 2B 02 FFFFFF81 4C 10 04
   FFFFFF81 4D FFFFFF81 52 0D 02 FFFFFF81 4E 0A 04 FFFFFF81 4F FFFFFF81 50 01 09
   75 6E 63 68 65 63 6B 65 64 0A 03 FFFFFF81 51 02 01 0A
   61 6E 6E 6F 74 61 74 69 6F 6E 09 04 FFFFFF81 53 FFFFFF81 4E
   02 11 75 6E 63 68 65 63 6B 65 64 56 61 72 69 61
   6E 63 65 04 09 1A FFFFFF81 47 FFFFFF84 FFFFFF80 FFFFFF80 FFFFFFC2 00 1B 04 09
   24 FFFFFF81 47 FFFFFF84 FFFFFF80 FFFFFF80 FFFFFFC2 00 1B 08 0A FFFFFF81 57 4B FFFFFF84 FFFFFF80
   FFFFFF80 FFFFFF84 20 FFFFFF81 58 01 08 68 61 73 68 43 6F 64 65 14
   02 FFFFFF81 59 10 03 10 FFFFFF81 5A 09 03 FFFFFF81 5B 02 02 03 49
   6E 74 08 0A FFFFFF81 5D 4B FFFFFF84 FFFFFF80 FFFFFF80 FFFFFF84 20 FFFFFF81 5E 01 08
   74 6F 53 74 72 69 6E 67 14 02 FFFFFF81 5F 10 04 FFFFFF81 60
   FFFFFF81 63 0E 03 10 FFFFFF81 61 09 03 FFFFFF81 62 02 01 06 50 72
   65 64 65 66 09 04 FFFFFF81 64 FFFFFF81 65 02 06 53 74 72 69
   6E 67 0A 03 FFFFFF81 62 02 08 0A FFFFFF81 67 4B FFFFFF84 FFFFFF80 FFFFFF80 FFFFFF84
   20 FFFFFF81 68 01 06 65 71 75 61 6C 73 14 03 7F FFFFFF81 69
   08 09 FFFFFF81 6A FFFFFF81 66 FFFFFF81 FFFFFF80 FFFFFFC0 00 1F 01 03 78 24 31
   08 0A FFFFFF81 6C 4B FFFFFF84 FFFFFF80 FFFFFF80 FFFFFF84 20 FFFFFF81 6D 01 0D 70 72
   6F 64 75 63 74 50 72 65 66 69 78 15 02 FFFFFF81 6E 10
   03 08 FFFFFF81 6F 09 03 FFFFFF81 64 09 08 0A FFFFFF81 71 4B FFFFFF84 FFFFFF80
   FFFFFF80 FFFFFF84 20 FFFFFF81 72 01 0C 70 72 6F 64 75 63 74 41 72
   69 74 79 15 02 FFFFFF81 59 08 0A FFFFFF81 74 4B FFFFFF84 FFFFFF80 FFFFFF80 FFFFFF84
   20 FFFFFF81 75 01 0E 70 72 6F 64 75 63 74 45 6C 65 6D
   65 6E 74 14 03 1F FFFFFF81 76 08 0A FFFFFF81 6A FFFFFF81 73 FFFFFF81 FFFFFF80
   FFFFFFC0 00 FFFFFF81 59 08 0A FFFFFF81 78 4B FFFFFF84 FFFFFF80 FFFFFF80 FFFFFF84 20 FFFFFF81 79
   01 08 63 61 6E 45 71 75 61 6C 14 03 7F FFFFFF81 7A 08
   09 FFFFFF81 6A FFFFFF81 77 FFFFFF81 FFFFFF80 FFFFFFC0 00 1F 28 03 4B FFFFFF81 7C 10
   03 10 FFFFFF81 7D 09 03 FFFFFF81 7E 02 02 0C 73 65 72 69 61
   6C 69 7A 61 62 6C 65 07 09 FFFFFF82 00 2D FFFFFF81 FFFFFF80 FFFFFF88 02
   FFFFFF82 01 01 0E 4C 65 66 74 50 72 6F 6A 65 63 74 69
   6F 6E 10 03 3D FFFFFF82 02 06 09 4C 2D FFFFFF84 FFFFFF81 FFFFFF80 FFFFFF88 02
   FFFFFF82 03 13 04 FFFFFF82 02 07 0F 08 07 14 FFFFFF82 02 FFFFFF84 00 FFFFFF82
   05 14 02 FFFFFF82 01 08 0A FFFFFF82 07 FFFFFF82 02 FFFFFF81 FFFFFF80 FFFFFF84 40 FFFFFF82
   08 01 05 61 70 70 6C 79 15 06 FFFFFF82 09 FFFFFF82 0C FFFFFF82 0E
   14 04 FFFFFF82 0A FFFFFF82 0F 10 06 3D 4B FFFFFF82 0B FFFFFF82 0D 10 03
   18 FFFFFF82 0C 04 09 1A FFFFFF82 06 FFFFFF84 FFFFFF80 FFFFFF80 FFFFFFC2 00 1B 10 03
   18 FFFFFF82 0E 04 09 24 FFFFFF82 06 FFFFFF84 FFFFFF80 FFFFFF80 FFFFFFC2 00 1B 08 07
   53 FFFFFF82 06 FFFFFFC0 00 FFFFFF82 10 10 06 10 00 FFFFFF82 0B FFFFFF82 0D 08
   0A FFFFFF82 12 FFFFFF82 02 FFFFFF81 FFFFFF80 FFFFFF84 40 FFFFFF82 13 01 07 75 6E 61
   70 70 6C 79 15 06 FFFFFF82 14 FFFFFF82 1A FFFFFF82 1C 14 04 FFFFFF82 15
   FFFFFF82 1D 10 05 10 FFFFFF82 16 FFFFFF82 18 09 03 FFFFFF82 17 02 02 04
   53 6F 6D 65 10 06 10 00 FFFFFF82 19 FFFFFF82 1B 10 03 18 FFFFFF82
   1A 04 09 1A FFFFFF82 11 FFFFFF84 FFFFFF80 FFFFFF80 FFFFFFC2 00 1B 10 03 18 FFFFFF82
   1C 04 09 24 FFFFFF82 11 FFFFFF84 FFFFFF80 FFFFFF80 FFFFFFC2 00 1B 08 08 FFFFFF82 1E
   FFFFFF82 11 FFFFFFC0 00 FFFFFF82 1F 01 03 78 24 30 10 06 3D 4B FFFFFF82
   19 FFFFFF82 1B 06 06 FFFFFF82 21 2D 42 FFFFFF82 22 02 0F 52 69 67
   68 74 50 72 6F 6A 65 63 74 69 6F 6E 15 06 FFFFFF82 23
   FFFFFF82 28 FFFFFF82 2A 13 05 FFFFFF82 20 07 0F 4F 08 0A 53 FFFFFF82 20
   FFFFFF82 FFFFFFCA FFFFFF80 FFFFFF84 00 FFFFFF82 25 15 02 FFFFFF82 26 10 06 10 00 FFFFFF82
   27 FFFFFF82 29 10 03 18 FFFFFF82 28 04 09 1A FFFFFF82 20 FFFFFF84 FFFFFF80 FFFFFF84
   FFFFFFC2 00 1B 10 03 18 FFFFFF82 2A 04 09 24 FFFFFF82 20 FFFFFF84 FFFFFF80 FFFFFF84
   FFFFFFC2 00 1B 08 0A 5B FFFFFF82 20 FFFFFF82 FFFFFF88 FFFFFFA0 FFFFFF80 04 FFFFFF82 26 08
   07 14 FFFFFF82 20 FFFFFF84 00 FFFFFF82 2D 14 04 FFFFFF82 2E FFFFFF82 2F 10 07
   3D FFFFFF82 20 FFFFFF82 27 FFFFFF82 29 08 07 53 FFFFFF82 2C FFFFFFC0 00 FFFFFF82 26
   08 07 61 FFFFFF82 20 FFFFFF84 00 FFFFFF82 31 15 02 FFFFFF82 29 08 07 64
   FFFFFF82 20 FFFFFF84 00 FFFFFF82 33 15 04 FFFFFF82 34 FFFFFF82 38 14 03 1F FFFFFF82
   35 08 07 68 FFFFFF82 32 FFFFFFC0 00 FFFFFF82 36 10 06 10 6A FFFFFF82 29
   FFFFFF82 37 10 03 18 FFFFFF82 38 04 09 6E FFFFFF82 32 FFFFFF84 FFFFFF80 FFFFFF80 FFFFFFC2
   00 1B 08 07 70 FFFFFF82 20 FFFFFF84 00 FFFFFF82 3A 15 04 FFFFFF82 3B FFFFFF82
   3D 14 04 FFFFFF82 3C FFFFFF82 3F 10 03 18 FFFFFF82 3D 04 0B FFFFFF81 12
   FFFFFF82 39 FFFFFF84 FFFFFF80 FFFFFF80 FFFFFFC2 00 FFFFFF82 3E 11 03 FFFFFF82 29 1F 08 08
   78 FFFFFF82 39 FFFFFF84 FFFFFFC0 00 FFFFFF82 40 10 04 10 7A FFFFFF82 3C 08 07
   7D FFFFFF82 20 FFFFFF84 00 FFFFFF82 42 14 03 7F FFFFFF82 43 08 07 68 FFFFFF82
   41 FFFFFFC0 00 FFFFFF82 44 10 05 10 6A FFFFFF82 29 7F 08 08 FFFFFF81 05
   FFFFFF82 20 FFFFFF84 00 FFFFFF82 46 14 03 7F FFFFFF82 47 08 07 68 FFFFFF82 45
   FFFFFFC0 00 FFFFFF82 44 08 08 FFFFFF81 09 FFFFFF82 20 FFFFFF84 00 FFFFFF82 49 15 06
   FFFFFF82 4A FFFFFF82 4D FFFFFF82 50 14 04 FFFFFF82 4B FFFFFF82 51 10 06 10 00
   FFFFFF82 4C FFFFFF82 4F 10 03 18 FFFFFF82 4D 04 0A 75 FFFFFF82 48 FFFFFF84 FFFFFF80
   FFFFFF80 FFFFFFC2 00 FFFFFF82 4E 11 03 FFFFFF82 27 1F 10 03 18 FFFFFF82 50 04
   0A FFFFFF81 2C FFFFFF82 48 FFFFFF84 FFFFFF80 FFFFFF80 FFFFFFC2 00 1B 08 07 68 FFFFFF82 48
   FFFFFFC0 00 FFFFFF82 52 10 06 10 6A FFFFFF82 29 FFFFFF82 4B 08 08 FFFFFF81 17
   FFFFFF82 20 FFFFFF84 00 FFFFFF82 54 15 04 FFFFFF82 55 FFFFFF82 5A 14 04 FFFFFF82 56
   FFFFFF82 5B 12 05 FFFFFF82 57 4F FFFFFF82 58 06 0A FFFFFF81 1C 00 FFFFFF84 FFFFFF80
   FFFFFF80 FFFFFF80 00 FFFFFF82 56 10 06 10 00 FFFFFF82 27 FFFFFF82 59 10 03 18
   FFFFFF82 5A 04 0A FFFFFF81 2C FFFFFF82 53 FFFFFF84 FFFFFF80 FFFFFF80 FFFFFFC2 00 1B 08 07
   68 FFFFFF82 53 FFFFFFC0 00 FFFFFF82 5C 10 06 10 6A FFFFFF82 29 FFFFFF82 59 08
   08 FFFFFF81 23 FFFFFF82 20 FFFFFF84 00 FFFFFF82 5E 15 04 FFFFFF82 5F FFFFFF82 63 14
   04 FFFFFF82 60 FFFFFF82 64 10 05 10 FFFFFF81 27 FFFFFF82 61 10 06 10 00
   FFFFFF82 62 FFFFFF82 29 10 03 18 FFFFFF82 63 04 0A FFFFFF81 0F FFFFFF82 5D FFFFFF84
   FFFFFF80 FFFFFF80 FFFFFFC2 00 1B 08 08 FFFFFF81 2E FFFFFF82 5D FFFFFFC0 00 FFFFFF82 44 08
   08 FFFFFF81 30 FFFFFF82 20 FFFFFF84 00 FFFFFF82 66 15 02 FFFFFF82 67 10 06 FFFFFF81
   33 FFFFFF81 36 FFFFFF82 29 08 08 FFFFFF81 39 FFFFFF82 20 FFFFFF84 00 FFFFFF82 69 15
   02 FFFFFF82 6A 10 05 10 FFFFFF81 27 FFFFFF82 29 08 0A FFFFFF81 3D FFFFFF82 20
   FFFFFF81 FFFFFF80 FFFFFF84 00 FFFFFF82 6C 15 06 FFFFFF82 6D FFFFFF82 70 FFFFFF82 72 14 04
   FFFFFF82 6E FFFFFF82 73 10 07 3D FFFFFF82 20 FFFFFF82 6F FFFFFF82 71 10 03 18
   FFFFFF82 70 04 09 1A FFFFFF82 6B FFFFFF84 FFFFFF80 FFFFFF80 FFFFFFC2 00 1B 10 03 18
   FFFFFF82 72 04 09 24 FFFFFF82 6B FFFFFF84 FFFFFF80 FFFFFF80 FFFFFFC2 00 1B 08 0B FFFFFF82
   75 53 FFFFFF82 6B FFFFFF90 FFFFFF80 FFFFFFC0 00 FFFFFF82 74 10 06 10 00 FFFFFF82 6F
   FFFFFF82 71 08 0A FFFFFF81 48 FFFFFF82 20 FFFFFF91 FFFFFF80 FFFFFF84 00 FFFFFF82 76 15 06
   FFFFFF82 77 FFFFFF82 78 FFFFFF82 79 2A 04 FFFFFF82 26 FFFFFF81 4B 04 09 1A FFFFFF82
   75 FFFFFF84 FFFFFF80 FFFFFF80 FFFFFFC2 00 1B 04 09 24 FFFFFF82 75 FFFFFF84 FFFFFF80 FFFFFF80 FFFFFFC2
   00 1B 08 0B FFFFFF81 57 FFFFFF82 20 FFFFFF84 FFFFFF80 FFFFFF80 FFFFFF84 20 FFFFFF81 58 08
   0B FFFFFF81 5D FFFFFF82 20 FFFFFF84 FFFFFF80 FFFFFF80 FFFFFF84 20 FFFFFF81 5E 08 0B FFFFFF81 67
   FFFFFF82 20 FFFFFF84 FFFFFF80 FFFFFF80 FFFFFF84 20 FFFFFF82 7D 14 03 7F FFFFFF82 7E 08 09
   FFFFFF81 6A FFFFFF82 7C FFFFFF81 FFFFFF80 FFFFFFC0 00 1F 08 0B FFFFFF81 6C FFFFFF82 20 FFFFFF84
   FFFFFF80 FFFFFF80 FFFFFF84 20 FFFFFF81 6D 08 0B FFFFFF81 71 FFFFFF82 20 FFFFFF84 FFFFFF80 FFFFFF80 FFFFFF84
   20 FFFFFF81 72 08 0B FFFFFF81 74 FFFFFF82 20 FFFFFF84 FFFFFF80 FFFFFF80 FFFFFF84 20 FFFFFF83 02
   14 03 1F FFFFFF83 03 08 0A FFFFFF81 6A FFFFFF83 01 FFFFFF81 FFFFFF80 FFFFFFC0 00 FFFFFF81
   59 08 0B FFFFFF81 78 FFFFFF82 20 FFFFFF84 FFFFFF80 FFFFFF80 FFFFFF84 20 FFFFFF83 05 14 03
   7F FFFFFF83 06 08 09 FFFFFF81 6A FFFFFF83 04 FFFFFF81 FFFFFF80 FFFFFFC0 00 1F 28 04
   FFFFFF82 20 FFFFFF81 7C 07 09 FFFFFF83 09 2D FFFFFF81 FFFFFF80 FFFFFF88 02 FFFFFF83 0A 01
   0F 52 69 67 68 74 50 72 6F 6A 65 63 74 69 6F 6E
   10 03 3D FFFFFF83 0B 06 0A FFFFFF82 21 2D FFFFFF84 FFFFFF81 FFFFFF80 FFFFFF88 02 FFFFFF83
   0C 13 04 FFFFFF83 0B 07 0F 08 07 14 FFFFFF83 0B FFFFFF84 00 FFFFFF83 0E
   14 02 FFFFFF83 0A 08 0A FFFFFF82 07 FFFFFF83 0B FFFFFF81 FFFFFF80 FFFFFF84 40 FFFFFF83 10
   15 06 FFFFFF83 11 FFFFFF83 14 FFFFFF83 16 14 04 FFFFFF83 12 FFFFFF83 17 10 07
   3D FFFFFF82 20 FFFFFF83 13 FFFFFF83 15 10 03 18 FFFFFF83 14 04 09 1A FFFFFF83
   0F FFFFFF84 FFFFFF80 FFFFFF80 FFFFFFC2 00 1B 10 03 18 FFFFFF83 16 04 09 24 FFFFFF83
   0F FFFFFF84 FFFFFF80 FFFFFF80 FFFFFFC2 00 1B 08 07 53 FFFFFF83 0F FFFFFFC0 00 FFFFFF83 18
   10 06 10 00 FFFFFF83 13 FFFFFF83 15 08 0A FFFFFF82 12 FFFFFF83 0B FFFFFF81 FFFFFF80
   FFFFFF84 40 FFFFFF83 1A 15 06 FFFFFF83 1B FFFFFF83 1F FFFFFF83 21 14 04 FFFFFF83 1C
   FFFFFF83 22 10 05 10 FFFFFF82 16 FFFFFF83 1D 10 06 10 00 FFFFFF83 1E FFFFFF83
   20 10 03 18 FFFFFF83 1F 04 09 1A FFFFFF83 19 FFFFFF84 FFFFFF80 FFFFFF80 FFFFFFC2 00
   1B 10 03 18 FFFFFF83 21 04 09 24 FFFFFF83 19 FFFFFF84 FFFFFF80 FFFFFF80 FFFFFFC2 00
   1B 08 08 FFFFFF82 1E FFFFFF83 19 FFFFFFC0 00 FFFFFF83 23 10 07 3D FFFFFF82 20
   FFFFFF83 1E FFFFFF83 20 08 07 FFFFFF83 25 2D FFFFFF84 00 FFFFFF83 26 01 08 6A
   6F 69 6E 4C 65 66 74 15 06 FFFFFF83 27 FFFFFF83 2A FFFFFF83 2C 14
   04 FFFFFF83 28 FFFFFF83 2D 10 06 10 00 FFFFFF83 29 FFFFFF83 2B 10 03 18
   FFFFFF83 2A 04 09 1A FFFFFF83 24 FFFFFF84 FFFFFF80 FFFFFF80 FFFFFFC2 00 1B 10 03 18
   FFFFFF83 2C 04 09 24 FFFFFF83 24 FFFFFF84 FFFFFF80 FFFFFF80 FFFFFFC2 00 1B 08 08 FFFFFF83
   2E FFFFFF83 24 FFFFFFC0 00 FFFFFF83 2F 01 02 65 73 10 06 10 00 FFFFFF83
   28 FFFFFF83 2B 28 06 FFFFFF83 24 FFFFFF83 31 FFFFFF83 34 10 03 10 FFFFFF83 32
   09 03 FFFFFF83 33 02 02 0A 64 65 70 72 65 63 61 74 65
   64 21 02 FFFFFF83 35 01 10 75 73 65 20 60 78 2E 6A 6F
   69 6E 4C 65 66 74 27 08 07 FFFFFF83 37 2D FFFFFF84 00 FFFFFF83 38
   01 09 6A 6F 69 6E 52 69 67 68 74 15 06 FFFFFF83 39 FFFFFF83
   3C FFFFFF83 3E 14 04 FFFFFF83 3A FFFFFF83 3F 10 06 10 00 FFFFFF83 3B FFFFFF83
   3D 10 03 18 FFFFFF83 3C 04 09 1A FFFFFF83 36 FFFFFF84 FFFFFF80 FFFFFF80 FFFFFFC2 00
   1B 10 03 18 FFFFFF83 3E 04 09 24 FFFFFF83 36 FFFFFF84 FFFFFF80 FFFFFF80 FFFFFFC2 00
   1B 08 08 FFFFFF83 2E FFFFFF83 36 FFFFFFC0 00 FFFFFF83 40 10 06 10 00 FFFFFF83
   3B FFFFFF83 3A 28 06 FFFFFF83 36 FFFFFF83 31 FFFFFF83 42 21 02 FFFFFF83 43 01
   11 75 73 65 20 60 78 2E 6A 6F 69 6E 52 69 67 68
   74 27 08 06 40 2D FFFFFF84 00 FFFFFF83 45 15 04 FFFFFF83 46 FFFFFF83 48
   14 04 FFFFFF83 47 FFFFFF83 4A 10 03 18 FFFFFF83 48 04 0A FFFFFF83 49 FFFFFF83
   44 FFFFFF84 FFFFFF80 FFFFFF80 FFFFFFC2 00 1B 02 01 54 08 07 53 FFFFFF83 44 FFFFFFC0
   00 FFFFFF83 4B 10 06 10 00 FFFFFF83 47 FFFFFF83 47 28 06 FFFFFF83 44 FFFFFF83
   31 FFFFFF83 4D 21 02 FFFFFF83 4E 01 0D 75 73 65 20 60 78 2E
   6D 65 72 67 65 27 08 07 FFFFFF83 50 2D FFFFFF84 00 FFFFFF83 51 01
   04 63 6F 6E 64 15 06 FFFFFF83 52 FFFFFF83 55 FFFFFF83 57 14 08 FFFFFF83
   53 FFFFFF83 58 FFFFFF83 5A FFFFFF83 5D 10 06 10 00 FFFFFF83 54 FFFFFF83 56 10
   03 18 FFFFFF83 55 04 09 1A FFFFFF83 4F FFFFFF84 FFFFFF80 FFFFFF80 FFFFFFC2 00 1B 10
   03 18 FFFFFF83 57 04 09 24 FFFFFF83 4F FFFFFF84 FFFFFF80 FFFFFF80 FFFFFFC2 00 1B 08
   07 FFFFFF83 59 FFFFFF83 4F FFFFFFC0 00 7F 01 04 74 65 73 74 08 09
   FFFFFF83 5B FFFFFF83 4F FFFFFF84 FFFFFFC0 00 FFFFFF83 5C 01 05 72 69 67 68 74
   10 04 10 7A FFFFFF83 56 08 08 26 FFFFFF83 4F FFFFFF84 FFFFFFC0 00 FFFFFF83 5E
   10 04 10 7A FFFFFF83 54 08 07 FFFFFF83 5B 00 FFFFFF84 00 FFFFFF83 60 15
   02 FFFFFF83 61 10 05 29 FFFFFF82 20 17 22 08 07 FFFFFF83 63 00 FFFFFF84
   00 FFFFFF83 64 01 04 66 6F 6C 64 15 04 FFFFFF83 65 FFFFFF83 67 14
   06 FFFFFF83 66 FFFFFF83 68 FFFFFF83 6B 10 03 18 FFFFFF83 67 04 0A FFFFFF81 0F
   FFFFFF83 62 FFFFFF84 FFFFFF80 FFFFFF80 FFFFFFC2 00 1B 08 08 FFFFFF83 69 FFFFFF83 62 FFFFFFC0 00
   FFFFFF83 6A 01 02 66 61 10 05 10 6A 17 FFFFFF83 66 08 08 FFFFFF83
   6C FFFFFF83 62 FFFFFFC0 00 FFFFFF83 6D 01 02 66 62 10 05 10 6A 22
   FFFFFF83 66 08 07 FFFFFF83 6F 00 FFFFFF84 00 FFFFFF83 70 01 04 73 77 61
   70 15 02 FFFFFF83 71 12 05 FFFFFF83 72 4F FFFFFF83 73 06 0A FFFFFF81 1C
   00 FFFFFF84 FFFFFF80 FFFFFF80 FFFFFF80 00 FFFFFF83 71 10 04 10 00 22 17 08 07
   FFFFFF83 37 00 FFFFFF84 00 FFFFFF83 75 15 08 FFFFFF83 76 FFFFFF83 79 FFFFFF84 05 FFFFFF83
   7D 16 04 FFFFFF83 77 FFFFFF83 7F 10 06 10 00 FFFFFF83 78 FFFFFF83 7C 10
   03 18 FFFFFF83 79 04 0B FFFFFF83 7A FFFFFF83 74 FFFFFF84 FFFFFF80 FFFFFF80 FFFFFFC2 00 FFFFFF83
   7B 02 02 41 31 11 02 17 1F 10 03 18 FFFFFF83 7D 04 0A
   FFFFFF83 7E FFFFFF83 74 FFFFFF84 FFFFFF80 FFFFFF80 FFFFFFC2 00 1B 02 01 43 08 08 FFFFFF84
   00 FFFFFF83 74 FFFFFFC0 01 FFFFFF84 01 01 02 65 76 10 08 FFFFFF81 60 FFFFFF84
   02 FFFFFF84 04 FFFFFF83 77 09 04 FFFFFF84 03 FFFFFF81 65 02 10 24 6C 65
   73 73 24 63 6F 6C 6F 6E 24 6C 65 73 73 10 03 18
   FFFFFF84 05 04 0B FFFFFF84 06 FFFFFF83 74 FFFFFF84 FFFFFF80 FFFFFF80 FFFFFFC2 00 FFFFFF84 07 02
   02 42 31 11 02 22 1F 08 07 FFFFFF83 25 00 FFFFFF84 00 FFFFFF84 09
   15 08 FFFFFF84 0A FFFFFF84 13 FFFFFF84 0F FFFFFF84 0D 16 04 FFFFFF84 0B FFFFFF84 10
   10 06 10 00 FFFFFF84 0C FFFFFF84 0E 10 03 18 FFFFFF84 0D 04 0A FFFFFF83
   7E FFFFFF84 08 FFFFFF84 FFFFFF80 FFFFFF80 FFFFFFC2 00 1B 10 03 18 FFFFFF84 0F 04 0B
   FFFFFF84 06 FFFFFF84 08 FFFFFF84 FFFFFF80 FFFFFF80 FFFFFFC2 00 FFFFFF84 07 08 08 FFFFFF84 00 FFFFFF84
   08 FFFFFFC0 01 FFFFFF84 11 10 08 FFFFFF81 60 FFFFFF84 02 FFFFFF84 12 FFFFFF84 0B 10
   03 18 FFFFFF84 13 04 0B FFFFFF83 7A FFFFFF84 08 FFFFFF84 FFFFFF80 FFFFFF80 FFFFFFC2 00 FFFFFF83
   7B 08 07 FFFFFF84 15 00 FFFFFF86 00 FFFFFF84 16 01 06 69 73 4C 65
   66 74 15 01 7F 08 07 FFFFFF84 18 00 FFFFFF86 00 FFFFFF84 16 01 07
   69 73 52 69 67 68 74 29 05 00 FFFFFF84 1A FFFFFF84 1C 09 03
   FFFFFF84 1B 02 02 04 4C 65 66 74 09 03 FFFFFF84 1D 02 02 05
   52 69 67 68 74 
  InnerClass: 
   public final #122= #116 of #52; //LeftProjection=class scala/Either$LeftProjection of class scala/Either
   public final #123= #108 of #52; //RightProjection=class scala/Either$RightProjection of class scala/Either
   public #126= #125 of #52; //MergeableEither=class scala/Either$MergeableEither of class scala/Either
   public abstract #131= #128 of #130; //$less$colon$less=class scala/Predef$$less$colon$less of class scala/Predef
   public final #134= #133 of #52; //$anonfun$joinLeft$1=class scala/Either$$anonfun$joinLeft$1 of class scala/Either
   public final #137= #136 of #52; //$anonfun$joinRight$1=class scala/Either$$anonfun$joinRight$1 of class scala/Either
  minor version: 0
  major version: 49
  Constant pool:
const #1 = Asciz	SourceFile;
const #2 = Asciz	Either.scala;
const #3 = Asciz	cond;
const #4 = Asciz	(ZLscala/Function0;Lscala/Function0;)Lscala/Either;;
const #5 = Asciz	Code;
const #6 = Asciz	scala/Either$;
const #7 = class	#6;	//  scala/Either$
const #8 = Asciz	MODULE$;
const #9 = Asciz	Lscala/Either$;;
const #10 = NameAndType	#8:#9;//  MODULE$:Lscala/Either$;
const #11 = Field	#7.#10;	//  scala/Either$.MODULE$:Lscala/Either$;
const #12 = NameAndType	#3:#4;//  cond:(ZLscala/Function0;Lscala/Function0;)Lscala/Either;
const #13 = Method	#7.#12;	//  scala/Either$.cond:(ZLscala/Function0;Lscala/Function0;)Lscala/Either;
const #14 = Asciz	<A:Ljava/lang/Object;B:Ljava/lang/Object;>(ZLscala/Function0<TB;>;Lscala/Function0<TA;>;)Lscala/Either<TA;TB;>;;
const #15 = Asciz	Signature;
const #16 = Asciz	merge;
const #17 = Asciz	(Lscala/Either;)Ljava/lang/Object;;
const #18 = NameAndType	#16:#17;//  merge:(Lscala/Either;)Ljava/lang/Object;
const #19 = Method	#7.#18;	//  scala/Either$.merge:(Lscala/Either;)Ljava/lang/Object;
const #20 = Asciz	<T:Ljava/lang/Object;>(Lscala/Either<TT;TT;>;)TT;;
const #21 = Asciz	Deprecated;
const #22 = Asciz	either2mergeable;
const #23 = Asciz	(Lscala/Either;)Lscala/Either$MergeableEither;;
const #24 = NameAndType	#22:#23;//  either2mergeable:(Lscala/Either;)Lscala/Either$MergeableEither;
const #25 = Method	#7.#24;	//  scala/Either$.either2mergeable:(Lscala/Either;)Lscala/Either$MergeableEither;
const #26 = Asciz	<A:Ljava/lang/Object;>(Lscala/Either<TA;TA;>;)Lscala/Either$MergeableEither<TA;>;;
const #27 = Asciz	<init>;
const #28 = Asciz	()V;
const #29 = Asciz	LineNumberTable;
const #30 = Asciz	java/lang/Object;
const #31 = class	#30;	//  java/lang/Object
const #32 = NameAndType	#27:#28;//  "<init>":()V
const #33 = Method	#31.#32;	//  java/lang/Object."<init>":()V
const #34 = Asciz	isRight;
const #35 = Asciz	()Z;
const #36 = Asciz	isLeft;
const #37 = Asciz	joinLeft;
const #38 = Asciz	(Lscala/Predef$$less$colon$less;)Lscala/Either;;
const #39 = Asciz	scala/Left;
const #40 = class	#39;	//  scala/Left
const #41 = Asciz	a;
const #42 = Asciz	Ljava/lang/Object;;
const #43 = NameAndType	#41:#42;//  a:Ljava/lang/Object;
const #44 = Field	#40.#43;	//  scala/Left.a:Ljava/lang/Object;
const #45 = Asciz	scala/Function1;
const #46 = class	#45;	//  scala/Function1
const #47 = Asciz	apply;
const #48 = Asciz	(Ljava/lang/Object;)Ljava/lang/Object;;
const #49 = NameAndType	#47:#48;//  apply:(Ljava/lang/Object;)Ljava/lang/Object;
const #50 = InterfaceMethod	#46.#49;	//  scala/Function1.apply:(Ljava/lang/Object;)Ljava/lang/Object;
const #51 = Asciz	scala/Either;
const #52 = class	#51;	//  scala/Either
const #53 = Asciz	scala/MatchError;
const #54 = class	#53;	//  scala/MatchError
const #55 = Asciz	toString;
const #56 = Asciz	()Ljava/lang/String;;
const #57 = NameAndType	#55:#56;//  toString:()Ljava/lang/String;
const #58 = Method	#52.#57;	//  scala/Either.toString:()Ljava/lang/String;
const #59 = Asciz	(Ljava/lang/String;)V;
const #60 = NameAndType	#27:#59;//  "<init>":(Ljava/lang/String;)V
const #61 = Method	#54.#60;	//  scala/MatchError."<init>":(Ljava/lang/String;)V
const #62 = Asciz	scala/Right;
const #63 = class	#62;	//  scala/Right
const #64 = Asciz	b;
const #65 = NameAndType	#64:#42;//  b:Ljava/lang/Object;
const #66 = Field	#63.#65;	//  scala/Right.b:Ljava/lang/Object;
const #67 = Asciz	(Ljava/lang/Object;)V;
const #68 = NameAndType	#27:#67;//  "<init>":(Ljava/lang/Object;)V
const #69 = Method	#63.#68;	//  scala/Right."<init>":(Ljava/lang/Object;)V
const #70 = Asciz	this;
const #71 = Asciz	Lscala/Either;;
const #72 = Asciz	ev;
const #73 = Asciz	Lscala/Predef$$less$colon$less;;
const #74 = Asciz	temp17;
const #75 = Asciz	Lscala/Left;;
const #76 = Asciz	temp18;
const #77 = Asciz	temp19;
const #78 = Asciz	Lscala/Right;;
const #79 = Asciz	temp20;
const #80 = Asciz	LocalVariableTable;
const #81 = Asciz	<A1:Ljava/lang/Object;B1:Ljava/lang/Object;C:Ljava/lang/Object;>(Lscala/Predef$$less$colon$less<TA1;Lscala/Either<TC;TB1;>;>;)Lscala/Either<TC;TB1;>;;
const #82 = Asciz	joinRight;
const #83 = Method	#40.#68;	//  scala/Left."<init>":(Ljava/lang/Object;)V
const #84 = Asciz	temp12;
const #85 = Asciz	temp13;
const #86 = Asciz	temp14;
const #87 = Asciz	temp15;
const #88 = Asciz	<A1:Ljava/lang/Object;B1:Ljava/lang/Object;C:Ljava/lang/Object;>(Lscala/Predef$$less$colon$less<TB1;Lscala/Either<TA1;TC;>;>;)Lscala/Either<TA1;TC;>;;
const #89 = Asciz	swap;
const #90 = Asciz	()Lscala/Product;;
const #91 = Asciz	temp7;
const #92 = Asciz	temp8;
const #93 = Asciz	temp9;
const #94 = Asciz	temp10;
const #95 = Asciz	fold;
const #96 = Asciz	(Lscala/Function1;Lscala/Function1;)Ljava/lang/Object;;
const #97 = Asciz	fa;
const #98 = Asciz	Lscala/Function1;;
const #99 = Asciz	fb;
const #100 = Asciz	temp2;
const #101 = Asciz	temp3;
const #102 = Asciz	temp4;
const #103 = Asciz	temp5;
const #104 = Asciz	<X:Ljava/lang/Object;>(Lscala/Function1<TA;TX;>;Lscala/Function1<TB;TX;>;)TX;;
const #105 = Asciz	right;
const #106 = Asciz	()Lscala/Either$RightProjection;;
const #107 = Asciz	scala/Either$RightProjection;
const #108 = class	#107;	//  scala/Either$RightProjection
const #109 = Asciz	(Lscala/Either;)V;
const #110 = NameAndType	#27:#109;//  "<init>":(Lscala/Either;)V
const #111 = Method	#108.#110;	//  scala/Either$RightProjection."<init>":(Lscala/Either;)V
const #112 = Asciz	()Lscala/Either$RightProjection<TA;TB;>;;
const #113 = Asciz	left;
const #114 = Asciz	()Lscala/Either$LeftProjection;;
const #115 = Asciz	scala/Either$LeftProjection;
const #116 = class	#115;	//  scala/Either$LeftProjection
const #117 = Method	#116.#110;	//  scala/Either$LeftProjection."<init>":(Lscala/Either;)V
const #118 = Asciz	()Lscala/Either$LeftProjection<TA;TB;>;;
const #119 = Asciz	<A:Ljava/lang/Object;B:Ljava/lang/Object;>Ljava/lang/Object;Lscala/ScalaObject;;
const #120 = Asciz	ScalaSig;
const #121 = Asciz	InnerClasses;
const #122 = Asciz	LeftProjection;
const #123 = Asciz	RightProjection;
const #124 = Asciz	scala/Either$MergeableEither;
const #125 = class	#124;	//  scala/Either$MergeableEither
const #126 = Asciz	MergeableEither;
const #127 = Asciz	scala/Predef$$less$colon$less;
const #128 = class	#127;	//  scala/Predef$$less$colon$less
const #129 = Asciz	scala/Predef;
const #130 = class	#129;	//  scala/Predef
const #131 = Asciz	$less$colon$less;
const #132 = Asciz	scala/Either$$anonfun$joinLeft$1;
const #133 = class	#132;	//  scala/Either$$anonfun$joinLeft$1
const #134 = Asciz	$anonfun$joinLeft$1;
const #135 = Asciz	scala/Either$$anonfun$joinRight$1;
const #136 = class	#135;	//  scala/Either$$anonfun$joinRight$1
const #137 = Asciz	$anonfun$joinRight$1;
const #138 = Asciz	scala/ScalaObject;
const #139 = class	#138;	//  scala/ScalaObject

{
public static final scala.Either cond(boolean, scala.Function0, scala.Function0);
  Code:
   Stack=4, Locals=3, Args_size=3
   0:	getstatic	#11; //Field scala/Either$.MODULE$:Lscala/Either$;
   3:	iload_0
   4:	aload_1
   5:	aload_2
   6:	invokevirtual	#13; //Method scala/Either$.cond:(ZLscala/Function0;Lscala/Function0;)Lscala/Either;
   9:	areturn
  Signature: length = 0x2
   00 0E 

public static final java.lang.Object merge(scala.Either);
  Code:
   Stack=2, Locals=1, Args_size=1
   0:	getstatic	#11; //Field scala/Either$.MODULE$:Lscala/Either$;
   3:	aload_0
   4:	invokevirtual	#19; //Method scala/Either$.merge:(Lscala/Either;)Ljava/lang/Object;
   7:	areturn
  Signature: length = 0x2
   00 14 
  Deprecated: true

public static final scala.Either$MergeableEither either2mergeable(scala.Either);
  Code:
   Stack=2, Locals=1, Args_size=1
   0:	getstatic	#11; //Field scala/Either$.MODULE$:Lscala/Either$;
   3:	aload_0
   4:	invokevirtual	#25; //Method scala/Either$.either2mergeable:(Lscala/Either;)Lscala/Either$MergeableEither;
   7:	areturn
  Signature: length = 0x2
   00 1A 

public scala.Either();
  Code:
   Stack=1, Locals=1, Args_size=1
   0:	aload_0
   1:	invokespecial	#33; //Method java/lang/Object."<init>":()V
   4:	return
  LineNumberTable: 
   line 27: 0

  Signature: length = 0x2
   00 1C 

public abstract boolean isRight();

public abstract boolean isLeft();

public scala.Either joinLeft(scala.Predef$$less$colon$less);
  Code:
   Stack=3, Locals=6, Args_size=2
   0:	aload_0
   1:	instanceof	#40; //class scala/Left
   4:	ifeq	46
   7:	aload_0
   8:	checkcast	#40; //class scala/Left
   11:	astore_2
   12:	aload_2
   13:	getfield	#44; //Field scala/Left.a:Ljava/lang/Object;
   16:	astore_3
   17:	iconst_1
   18:	ifeq	34
   21:	aload_1
   22:	aload_3
   23:	invokeinterface	#50,  2; //InterfaceMethod scala/Function1.apply:(Ljava/lang/Object;)Ljava/lang/Object;
   28:	checkcast	#52; //class scala/Either
   31:	goto	79
   34:	new	#54; //class scala/MatchError
   37:	dup
   38:	aload_0
   39:	invokevirtual	#58; //Method toString:()Ljava/lang/String;
   42:	invokespecial	#61; //Method scala/MatchError."<init>":(Ljava/lang/String;)V
   45:	athrow
   46:	aload_0
   47:	instanceof	#63; //class scala/Right
   50:	ifeq	92
   53:	aload_0
   54:	checkcast	#63; //class scala/Right
   57:	astore	4
   59:	aload	4
   61:	getfield	#66; //Field scala/Right.b:Ljava/lang/Object;
   64:	astore	5
   66:	iconst_1
   67:	ifeq	80
   70:	new	#63; //class scala/Right
   73:	dup
   74:	aload	5
   76:	invokespecial	#69; //Method scala/Right."<init>":(Ljava/lang/Object;)V
   79:	areturn
   80:	new	#54; //class scala/MatchError
   83:	dup
   84:	aload_0
   85:	invokevirtual	#58; //Method toString:()Ljava/lang/String;
   88:	invokespecial	#61; //Method scala/MatchError."<init>":(Ljava/lang/String;)V
   91:	athrow
   92:	new	#54; //class scala/MatchError
   95:	dup
   96:	aload_0
   97:	invokevirtual	#58; //Method toString:()Ljava/lang/String;
   100:	invokespecial	#61; //Method scala/MatchError."<init>":(Ljava/lang/String;)V
   103:	athrow
  LineNumberTable: 
   line 65: 0
   line 21: 17
   line 66: 21
   line 65: 34
   line 21: 66
   line 67: 70
   line 65: 79

  LocalVariableTable: 
   Start  Length  Slot  Name   Signature
   0      104      0    this       Lscala/Either;
   0      104      1    ev       Lscala/Predef$$less$colon$less;
   12      34      2    temp17       Lscala/Left;
   17      29      3    temp18       Ljava/lang/Object;
   59      20      4    temp19       Lscala/Right;
   80      12      4    temp19       Lscala/Right;
   66      13      5    temp20       Ljava/lang/Object;
   80      12      5    temp20       Ljava/lang/Object;

  Signature: length = 0x2
   00 51 

public scala.Either joinRight(scala.Predef$$less$colon$less);
  Code:
   Stack=3, Locals=6, Args_size=2
   0:	aload_0
   1:	instanceof	#40; //class scala/Left
   4:	ifeq	44
   7:	aload_0
   8:	checkcast	#40; //class scala/Left
   11:	astore_2
   12:	aload_2
   13:	getfield	#44; //Field scala/Left.a:Ljava/lang/Object;
   16:	astore_3
   17:	iconst_1
   18:	ifeq	32
   21:	new	#40; //class scala/Left
   24:	dup
   25:	aload_3
   26:	invokespecial	#83; //Method scala/Left."<init>":(Ljava/lang/Object;)V
   29:	goto	79
   32:	new	#54; //class scala/MatchError
   35:	dup
   36:	aload_0
   37:	invokevirtual	#58; //Method toString:()Ljava/lang/String;
   40:	invokespecial	#61; //Method scala/MatchError."<init>":(Ljava/lang/String;)V
   43:	athrow
   44:	aload_0
   45:	instanceof	#63; //class scala/Right
   48:	ifeq	92
   51:	aload_0
   52:	checkcast	#63; //class scala/Right
   55:	astore	4
   57:	aload	4
   59:	getfield	#66; //Field scala/Right.b:Ljava/lang/Object;
   62:	astore	5
   64:	iconst_1
   65:	ifeq	80
   68:	aload_1
   69:	aload	5
   71:	invokeinterface	#50,  2; //InterfaceMethod scala/Function1.apply:(Ljava/lang/Object;)Ljava/lang/Object;
   76:	checkcast	#52; //class scala/Either
   79:	areturn
   80:	new	#54; //class scala/MatchError
   83:	dup
   84:	aload_0
   85:	invokevirtual	#58; //Method toString:()Ljava/lang/String;
   88:	invokespecial	#61; //Method scala/MatchError."<init>":(Ljava/lang/String;)V
   91:	athrow
   92:	new	#54; //class scala/MatchError
   95:	dup
   96:	aload_0
   97:	invokevirtual	#58; //Method toString:()Ljava/lang/String;
   100:	invokespecial	#61; //Method scala/MatchError."<init>":(Ljava/lang/String;)V
   103:	athrow
  LineNumberTable: 
   line 57: 0
   line 21: 17
   line 58: 21
   line 57: 32
   line 21: 64
   line 59: 68
   line 57: 79

  LocalVariableTable: 
   Start  Length  Slot  Name   Signature
   0      104      0    this       Lscala/Either;
   0      104      1    ev       Lscala/Predef$$less$colon$less;
   12      32      2    temp12       Lscala/Left;
   17      27      3    temp13       Ljava/lang/Object;
   57      22      4    temp14       Lscala/Right;
   80      12      4    temp14       Lscala/Right;
   64      15      5    temp15       Ljava/lang/Object;
   80      12      5    temp15       Ljava/lang/Object;

  Signature: length = 0x2
   00 58 

public scala.Product swap();
  Code:
   Stack=3, Locals=5, Args_size=1
   0:	aload_0
   1:	instanceof	#40; //class scala/Left
   4:	ifeq	44
   7:	aload_0
   8:	checkcast	#40; //class scala/Left
   11:	astore_1
   12:	aload_1
   13:	getfield	#44; //Field scala/Left.a:Ljava/lang/Object;
   16:	astore_2
   17:	iconst_1
   18:	ifeq	32
   21:	new	#63; //class scala/Right
   24:	dup
   25:	aload_2
   26:	invokespecial	#69; //Method scala/Right."<init>":(Ljava/lang/Object;)V
   29:	goto	75
   32:	new	#54; //class scala/MatchError
   35:	dup
   36:	aload_0
   37:	invokevirtual	#58; //Method toString:()Ljava/lang/String;
   40:	invokespecial	#61; //Method scala/MatchError."<init>":(Ljava/lang/String;)V
   43:	athrow
   44:	aload_0
   45:	instanceof	#63; //class scala/Right
   48:	ifeq	88
   51:	aload_0
   52:	checkcast	#63; //class scala/Right
   55:	astore_3
   56:	aload_3
   57:	getfield	#66; //Field scala/Right.b:Ljava/lang/Object;
   60:	astore	4
   62:	iconst_1
   63:	ifeq	76
   66:	new	#40; //class scala/Left
   69:	dup
   70:	aload	4
   72:	invokespecial	#83; //Method scala/Left."<init>":(Ljava/lang/Object;)V
   75:	areturn
   76:	new	#54; //class scala/MatchError
   79:	dup
   80:	aload_0
   81:	invokevirtual	#58; //Method toString:()Ljava/lang/String;
   84:	invokespecial	#61; //Method scala/MatchError."<init>":(Ljava/lang/String;)V
   87:	athrow
   88:	new	#54; //class scala/MatchError
   91:	dup
   92:	aload_0
   93:	invokevirtual	#58; //Method toString:()Ljava/lang/String;
   96:	invokespecial	#61; //Method scala/MatchError."<init>":(Ljava/lang/String;)V
   99:	athrow
  LineNumberTable: 
   line 49: 0
   line 21: 17
   line 50: 21
   line 49: 32
   line 21: 62
   line 51: 66
   line 49: 75

  LocalVariableTable: 
   Start  Length  Slot  Name   Signature
   0      100      0    this       Lscala/Either;
   12      32      1    temp7       Lscala/Left;
   17      27      2    temp8       Ljava/lang/Object;
   56      19      3    temp9       Lscala/Right;
   76      12      3    temp9       Lscala/Right;
   62      13      4    temp10       Ljava/lang/Object;
   76      12      4    temp10       Ljava/lang/Object;


public java.lang.Object fold(scala.Function1, scala.Function1);
  Code:
   Stack=3, Locals=7, Args_size=3
   0:	aload_0
   1:	instanceof	#40; //class scala/Left
   4:	ifeq	45
   7:	aload_0
   8:	checkcast	#40; //class scala/Left
   11:	astore_3
   12:	aload_3
   13:	getfield	#44; //Field scala/Left.a:Ljava/lang/Object;
   16:	astore	4
   18:	iconst_1
   19:	ifeq	33
   22:	aload_1
   23:	aload	4
   25:	invokeinterface	#50,  2; //InterfaceMethod scala/Function1.apply:(Ljava/lang/Object;)Ljava/lang/Object;
   30:	goto	77
   33:	new	#54; //class scala/MatchError
   36:	dup
   37:	aload_0
   38:	invokevirtual	#58; //Method toString:()Ljava/lang/String;
   41:	invokespecial	#61; //Method scala/MatchError."<init>":(Ljava/lang/String;)V
   44:	athrow
   45:	aload_0
   46:	instanceof	#63; //class scala/Right
   49:	ifeq	90
   52:	aload_0
   53:	checkcast	#63; //class scala/Right
   56:	astore	5
   58:	aload	5
   60:	getfield	#66; //Field scala/Right.b:Ljava/lang/Object;
   63:	astore	6
   65:	iconst_1
   66:	ifeq	78
   69:	aload_2
   70:	aload	6
   72:	invokeinterface	#50,  2; //InterfaceMethod scala/Function1.apply:(Ljava/lang/Object;)Ljava/lang/Object;
   77:	areturn
   78:	new	#54; //class scala/MatchError
   81:	dup
   82:	aload_0
   83:	invokevirtual	#58; //Method toString:()Ljava/lang/String;
   86:	invokespecial	#61; //Method scala/MatchError."<init>":(Ljava/lang/String;)V
   89:	athrow
   90:	new	#54; //class scala/MatchError
   93:	dup
   94:	aload_0
   95:	invokevirtual	#58; //Method toString:()Ljava/lang/String;
   98:	invokespecial	#61; //Method scala/MatchError."<init>":(Ljava/lang/String;)V
   101:	athrow
  LineNumberTable: 
   line 41: 0
   line 21: 18
   line 42: 22
   line 41: 33
   line 21: 65
   line 43: 69
   line 41: 77

  LocalVariableTable: 
   Start  Length  Slot  Name   Signature
   0      102      0    this       Lscala/Either;
   0      102      1    fa       Lscala/Function1;
   0      102      2    fb       Lscala/Function1;
   12      33      3    temp2       Lscala/Left;
   18      27      4    temp3       Ljava/lang/Object;
   58      19      5    temp4       Lscala/Right;
   78      12      5    temp4       Lscala/Right;
   65      12      6    temp5       Ljava/lang/Object;
   78      12      6    temp5       Ljava/lang/Object;

  Signature: length = 0x2
   00 68 

public scala.Either$RightProjection right();
  Code:
   Stack=3, Locals=1, Args_size=1
   0:	new	#108; //class scala/Either$RightProjection
   3:	dup
   4:	aload_0
   5:	invokespecial	#111; //Method scala/Either$RightProjection."<init>":(Lscala/Either;)V
   8:	areturn
  LineNumberTable: 
   line 36: 0

  Signature: length = 0x2
   00 70 

public scala.Either$LeftProjection left();
  Code:
   Stack=3, Locals=1, Args_size=1
   0:	new	#116; //class scala/Either$LeftProjection
   3:	dup
   4:	aload_0
   5:	invokespecial	#117; //Method scala/Either$LeftProjection."<init>":(Lscala/Either;)V
   8:	areturn
  LineNumberTable: 
   line 31: 0

  Signature: length = 0x2
   00 76 

}

