Compiled from "Either.scala"
public final class scala.Either$RightProjection$ extends java.lang.Object implements scala.ScalaObject
  SourceFile: "Either.scala"
  Scala: length = 0x
   
  InnerClass: 
   public final RightProjection=class scala/Either$RightProjection of class scala/Either
  minor version: 0
  major version: 49
  Constant pool:
Asciz	SourceFile;
Asciz	Either.scala;
Asciz	Scala;
Asciz	MODULE$;
Asciz	Lscala/Either$RightProjection$;;
Asciz	<clinit>;
Asciz	()V;
Asciz	Code;
Asciz	scala/Either$RightProjection$;
class	scala/Either$RightProjection$
Asciz	<init>;
NameAndType	"<init>":()V
Method	scala/Either$RightProjection$."<init>":()V
Asciz	unapply;
Asciz	(Lscala/Either$RightProjection;)Lscala/Option;;
Asciz	LineNumberTable;
Asciz	java/lang/Object;
class	java/lang/Object
Asciz	equals;
Asciz	(Ljava/lang/Object;)Z;
NameAndType	equals:(Ljava/lang/Object;)Z
Method	java/lang/Object.equals:(Ljava/lang/Object;)Z
Asciz	scala/None$;
class	scala/None$
Asciz	Lscala/None$;;
NameAndType	MODULE$:Lscala/None$;
Field	scala/None$.MODULE$:Lscala/None$;
Asciz	scala/Some;
class	scala/Some
Asciz	scala/Either$RightProjection;
class	scala/Either$RightProjection
Asciz	e;
Asciz	()Lscala/Either;;
NameAndType	e:()Lscala/Either;
Method	scala/Either$RightProjection.e:()Lscala/Either;
Asciz	(Ljava/lang/Object;)V;
NameAndType	"<init>":(Ljava/lang/Object;)V
Method	scala/Some."<init>":(Ljava/lang/Object;)V
Asciz	this;
Asciz	x$0;
Asciz	Lscala/Either$RightProjection;;
Asciz	LocalVariableTable;
Asciz	apply;
Asciz	(Lscala/Either;)Lscala/Either$RightProjection;;
Asciz	(Lscala/Either;)V;
NameAndType	"<init>":(Lscala/Either;)V
Method	scala/Either$RightProjection."<init>":(Lscala/Either;)V
Asciz	Lscala/Either;;
Method	java/lang/Object."<init>":()V
NameAndType	MODULE$:Lscala/Either$RightProjection$;
Field	scala/Either$RightProjection$.MODULE$:Lscala/Either$RightProjection$;
Asciz	InnerClasses;
Asciz	scala/Either;
class	scala/Either
Asciz	RightProjection;
Asciz	scala/ScalaObject;
class	scala/ScalaObject

{
public static final scala.Either$RightProjection$ MODULE$;
  Signature: Lscala/Either$RightProjection$;

public static {};
  Signature: ()V
  Code:
   Stack=1, Locals=0, Args_size=0
	new	class scala/Either$RightProjection$
	invokespecial	Method "<init>":()V
	return
  Labels:

public scala.Option unapply(scala.Either$RightProjection);
  Signature: (Lscala/Either$RightProjection;)Lscala/Option;
  Code:
   Stack=3, Locals=3, Args_size=2
	aload_1
	dup
	astore_2
	ifnull	l1 // getstatic
	aload_2
	aconst_null
	invokevirtual	Method java/lang/Object.equals:(Ljava/lang/Object;)Z
	ifeq	l2 // new
l1	getstatic	Field scala/None$.MODULE$:Lscala/None$;
	goto	l3 // areturn
l2	new	class scala/Some
	dup
	aload_1
	invokevirtual	Method scala/Either$RightProjection.e:()Lscala/Either;
	invokespecial	Method scala/Some."<init>":(Ljava/lang/Object;)V
l3	areturn
  Labels:
   	l1 = 14 // getstatic
   	l2 = 20 // new
   	l3 = 31 // areturn
  LocalVariableTable: 
   Start  Length  Slot  Name   Signature
   0      32      0    this       Lscala/Either$RightProjection$;
   0      32      1    x$0       Lscala/Either$RightProjection;


public scala.Either$RightProjection apply(scala.Either);
  Signature: (Lscala/Either;)Lscala/Either$RightProjection;
  Code:
   Stack=3, Locals=2, Args_size=2
	new	class scala/Either$RightProjection
	dup
	aload_1
	invokespecial	Method scala/Either$RightProjection."<init>":(Lscala/Either;)V
	areturn
  Labels:
  LocalVariableTable: 
   Start  Length  Slot  Name   Signature
   0      9      0    this       Lscala/Either$RightProjection$;
   0      9      1    e       Lscala/Either;


public scala.Either$RightProjection$();
  Signature: ()V
  Code:
   Stack=1, Locals=1, Args_size=1
	aload_0
	invokespecial	Method java/lang/Object."<init>":()V
	aload_0
	putstatic	Field MODULE$:Lscala/Either$RightProjection$;
	return
  Labels:

}

