Compiled from "Either.scala"
public class scala.Either$MergeableEither extends java.lang.Object implements scala.ScalaObject
  SourceFile: "Either.scala"
  Signature: length = 0x2
   00 38 
  Scala: length = 0x
   
  InnerClass: 
   public MergeableEither=class scala/Either$MergeableEither of class scala/Either
  minor version: 0
  major version: 49
  Constant pool:
Asciz	SourceFile;
Asciz	Either.scala;
Asciz	x;
Asciz	Lscala/Either;;
Asciz	Lscala/Either<TA;TA;>;;
Asciz	Signature;
Asciz	<init>;
Asciz	(Lscala/Either;)V;
Asciz	Code;
Asciz	LineNumberTable;
Asciz	scala/Either$MergeableEither;
class	scala/Either$MergeableEither
NameAndType	x:Lscala/Either;
Field	scala/Either$MergeableEither.x:Lscala/Either;
Asciz	java/lang/Object;
class	java/lang/Object
Asciz	()V;
NameAndType	"<init>":()V
Method	java/lang/Object."<init>":()V
Asciz	this;
Asciz	Lscala/Either$MergeableEither;;
Asciz	LocalVariableTable;
Asciz	(Lscala/Either<TA;TA;>;)V;
Asciz	merge;
Asciz	()Ljava/lang/Object;;
Asciz	scala/Left;
class	scala/Left
Asciz	a;
Asciz	Ljava/lang/Object;;
NameAndType	a:Ljava/lang/Object;
Field	scala/Left.a:Ljava/lang/Object;
Asciz	scala/MatchError;
class	scala/MatchError
Asciz	scala/Either;
class	scala/Either
Asciz	toString;
Asciz	()Ljava/lang/String;;
NameAndType	toString:()Ljava/lang/String;
Method	scala/Either.toString:()Ljava/lang/String;
Asciz	(Ljava/lang/String;)V;
NameAndType	"<init>":(Ljava/lang/String;)V
Method	scala/MatchError."<init>":(Ljava/lang/String;)V
Asciz	scala/Right;
class	scala/Right
Asciz	b;
NameAndType	b:Ljava/lang/Object;
Field	scala/Right.b:Ljava/lang/Object;
Asciz	temp30;
Asciz	Lscala/Left;;
Asciz	temp31;
Asciz	temp32;
Asciz	Lscala/Right;;
Asciz	temp33;
Asciz	temp29;
Asciz	()TA;;
Asciz	<A:Ljava/lang/Object;>Ljava/lang/Object;Lscala/ScalaObject;;
Asciz	Scala;
Asciz	InnerClasses;
Asciz	MergeableEither;
Asciz	scala/ScalaObject;
class	scala/ScalaObject

{
private final scala.Either x;
  Signature: Lscala/Either;
  Signature: length = 0x2
   00 05 

public scala.Either$MergeableEither(scala.Either);
  Signature: (Lscala/Either;)V
  Code:
   Stack=2, Locals=2, Args_size=2
	aload_0
	aload_1
	putfield	Field x:Lscala/Either;
	aload_0
	invokespecial	Method java/lang/Object."<init>":()V
	return
  Labels:
  LocalVariableTable: 
   Start  Length  Slot  Name   Signature
   0      10      0    this       Lscala/Either$MergeableEither;
   0      10      1    x       Lscala/Either;

  Signature: length = 0x2
   00 17 

public java.lang.Object merge();
  Signature: ()Ljava/lang/Object;
  Code:
   Stack=3, Locals=6, Args_size=1
	aload_0
	getfield	Field x:Lscala/Either;
	astore	5
	aload	5
	instanceof	class scala/Left
	ifeq	l1 // aload
	aload	5
	checkcast	class scala/Left
	astore_1
	aload_1
	getfield	Field scala/Left.a:Ljava/lang/Object;
	astore_2
	iconst_1
	ifeq	l2 // new
	aload_2
	goto	l3 // areturn
l2	new	class scala/MatchError
	dup
	aload	5
	invokevirtual	Method scala/Either.toString:()Ljava/lang/String;
	invokespecial	Method scala/MatchError."<init>":(Ljava/lang/String;)V
	athrow
l1	aload	5
	instanceof	class scala/Right
	ifeq	l4 // new
	aload	5
	checkcast	class scala/Right
	astore_3
	aload_3
	getfield	Field scala/Right.b:Ljava/lang/Object;
	astore	4
	iconst_1
	ifeq	l5 // new
	aload	4
l3	areturn
l5	new	class scala/MatchError
	dup
	aload	5
	invokevirtual	Method scala/Either.toString:()Ljava/lang/String;
	invokespecial	Method scala/MatchError."<init>":(Ljava/lang/String;)V
	athrow
l4	new	class scala/MatchError
	dup
	aload	5
	invokevirtual	Method scala/Either.toString:()Ljava/lang/String;
	invokespecial	Method scala/MatchError."<init>":(Ljava/lang/String;)V
	athrow
  Labels:
   	l2 = 33 // new
   	l1 = 46 // aload
   	l3 = 72 // areturn
   	l5 = 73 // new
   	l4 = 86 // new
  LocalVariableTable: 
   Start  Length  Slot  Name   Signature
   0      99      0    this       Lscala/Either$MergeableEither;
   20      26      1    temp30       Lscala/Left;
   25      21      2    temp31       Ljava/lang/Object;
   60      12      3    temp32       Lscala/Right;
   73      13      3    temp32       Lscala/Right;
   66      6      4    temp33       Ljava/lang/Object;
   73      13      4    temp33       Ljava/lang/Object;
   6      93      5    temp29       Lscala/Either;

  Signature: length = 0x2
   00 37 

}

