Compiled from "Enumeration.scala"
public final class scala.Enumeration$$anonfun$values$1 extends java.lang.Object implements scala.Function1,scala.ScalaObject,java.io.Serializable
  SourceFile: "Enumeration.scala"
  Scala: length = 0x
   
  InnerClass: 
   public abstract Value=class scala/Enumeration$Value of class scala/Enumeration
   public final $anonfun$values$1=class scala/Enumeration$$anonfun$values$1 of class scala/Enumeration
  minor version: 0
  major version: 49
  Constant pool:
Asciz	SourceFile;
Asciz	Enumeration.scala;
Asciz	<clinit>;
Asciz	()V;
Asciz	Code;
Asciz	serialVersionUID;
Asciz	J;
Asciz	scala/Enumeration$$anonfun$values$1;
class	scala/Enumeration$$anonfun$values$1
NameAndType	serialVersionUID:J
Field	scala/Enumeration$$anonfun$values$1.serialVersionUID:J
Asciz	<init>;
Asciz	(Lscala/Enumeration;)V;
Asciz	LineNumberTable;
Asciz	java/lang/Object;
class	java/lang/Object
NameAndType	"<init>":()V
Method	java/lang/Object."<init>":()V
Asciz	scala/Function1$class;
class	scala/Function1$class
Asciz	$init$;
Asciz	(Lscala/Function1;)V;
NameAndType	$init$:(Lscala/Function1;)V
Method	scala/Function1$class.$init$:(Lscala/Function1;)V
Asciz	this;
Asciz	Lscala/Enumeration$$anonfun$values$1;;
Asciz	$outer;
Asciz	Lscala/Enumeration;;
Asciz	LocalVariableTable;
Asciz	apply;
Asciz	(Ljava/lang/Object;)Ljava/lang/Object;;
Asciz	scala/Enumeration$Value;
class	scala/Enumeration$Value
Asciz	(Lscala/Enumeration$Value;)I;
NameAndType	apply:(Lscala/Enumeration$Value;)I
Method	scala/Enumeration$$anonfun$values$1.apply:(Lscala/Enumeration$Value;)I
Asciz	scala/runtime/BoxesRunTime;
class	scala/runtime/BoxesRunTime
Asciz	boxToInteger;
Asciz	(I)Ljava/lang/Integer;;
NameAndType	boxToInteger:(I)Ljava/lang/Integer;
Method	scala/runtime/BoxesRunTime.boxToInteger:(I)Ljava/lang/Integer;
Asciz	v1;
Asciz	Ljava/lang/Object;;
Asciz	id;
Asciz	()I;
NameAndType	id:()I
Method	scala/Enumeration$Value.id:()I
Asciz	andThen;
Asciz	(Lscala/Function1;)Lscala/Function1;;
Asciz	(Lscala/Function1;Lscala/Function1;)Lscala/Function1;;
NameAndType	andThen:(Lscala/Function1;Lscala/Function1;)Lscala/Function1;
Method	scala/Function1$class.andThen:(Lscala/Function1;Lscala/Function1;)Lscala/Function1;
Asciz	g;
Asciz	Lscala/Function1;;
Asciz	compose;
NameAndType	compose:(Lscala/Function1;Lscala/Function1;)Lscala/Function1;
Method	scala/Function1$class.compose:(Lscala/Function1;Lscala/Function1;)Lscala/Function1;
Asciz	toString;
Asciz	()Ljava/lang/String;;
Asciz	(Lscala/Function1;)Ljava/lang/String;;
NameAndType	toString:(Lscala/Function1;)Ljava/lang/String;
Method	scala/Function1$class.toString:(Lscala/Function1;)Ljava/lang/String;
Asciz	Scala;
Asciz	InnerClasses;
Asciz	scala/Enumeration;
class	scala/Enumeration
Asciz	Value;
Asciz	$anonfun$values$1;
Asciz	scala/Function1;
class	scala/Function1
Asciz	scala/ScalaObject;
class	scala/ScalaObject
Asciz	java/io/Serializable;
class	java/io/Serializable

{
public static final long serialVersionUID;
  Signature: J

public static {};
  Signature: ()V
  Code:
   Stack=2, Locals=0, Args_size=0
	lconst_0
	putstatic	Field serialVersionUID:J
	return
  Labels:

public scala.Enumeration$$anonfun$values$1(scala.Enumeration);
  Signature: (Lscala/Enumeration;)V
  Code:
   Stack=1, Locals=2, Args_size=2
	aload_0
	invokespecial	Method java/lang/Object."<init>":()V
	aload_0
	invokestatic	Method scala/Function1$class.$init$:(Lscala/Function1;)V
	return
  Labels:
  LocalVariableTable: 
   Start  Length  Slot  Name   Signature
   0      9      0    this       Lscala/Enumeration$$anonfun$values$1;
   0      9      1    $outer       Lscala/Enumeration;


public final java.lang.Object apply(java.lang.Object);
  Signature: (Ljava/lang/Object;)Ljava/lang/Object;
  Code:
   Stack=2, Locals=3, Args_size=2
	aload_0
	aload_1
	checkcast	class scala/Enumeration$Value
	invokevirtual	Method apply:(Lscala/Enumeration$Value;)I
	istore_2
	iload_2
	invokestatic	Method scala/runtime/BoxesRunTime.boxToInteger:(I)Ljava/lang/Integer;
	areturn
  Labels:
  LocalVariableTable: 
   Start  Length  Slot  Name   Signature
   0      14      0    this       Lscala/Enumeration$$anonfun$values$1;
   0      14      1    v1       Ljava/lang/Object;


public final int apply(scala.Enumeration$Value);
  Signature: (Lscala/Enumeration$Value;)I
  Code:
   Stack=1, Locals=2, Args_size=2
	aload_1
	invokevirtual	Method scala/Enumeration$Value.id:()I
	ireturn
  Labels:

public scala.Function1 andThen(scala.Function1);
  Signature: (Lscala/Function1;)Lscala/Function1;
  Code:
   Stack=2, Locals=2, Args_size=2
	aload_0
	aload_1
	invokestatic	Method scala/Function1$class.andThen:(Lscala/Function1;Lscala/Function1;)Lscala/Function1;
	areturn
  Labels:
  LocalVariableTable: 
   Start  Length  Slot  Name   Signature
   0      6      0    this       Lscala/Enumeration$$anonfun$values$1;
   0      6      1    g       Lscala/Function1;


public scala.Function1 compose(scala.Function1);
  Signature: (Lscala/Function1;)Lscala/Function1;
  Code:
   Stack=2, Locals=2, Args_size=2
	aload_0
	aload_1
	invokestatic	Method scala/Function1$class.compose:(Lscala/Function1;Lscala/Function1;)Lscala/Function1;
	areturn
  Labels:
  LocalVariableTable: 
   Start  Length  Slot  Name   Signature
   0      6      0    this       Lscala/Enumeration$$anonfun$values$1;
   0      6      1    g       Lscala/Function1;


public java.lang.String toString();
  Signature: ()Ljava/lang/String;
  Code:
   Stack=1, Locals=1, Args_size=1
	aload_0
	invokestatic	Method scala/Function1$class.toString:(Lscala/Function1;)Ljava/lang/String;
	areturn
  Labels:

}

