Compiled from "Enumeration.scala"
public final class scala.Enumeration$$anonfun$isValDef$1$1 extends scala.runtime.AbstractFunction1 implements java.io.Serializable
  SourceFile: "Enumeration.scala"
  Scala: length = 0x
   
  InnerClass: 
   public final $anonfun$isValDef$1$1=class scala/Enumeration$$anonfun$isValDef$1$1 of class scala/Enumeration
  minor version: 0
  major version: 49
  Constant pool:
Asciz	SourceFile;
Asciz	Enumeration.scala;
Asciz	<clinit>;
Asciz	()V;
Asciz	Code;
Asciz	serialVersionUID;
Asciz	J;
Asciz	scala/Enumeration$$anonfun$isValDef$1$1;
class	scala/Enumeration$$anonfun$isValDef$1$1
NameAndType	serialVersionUID:J
Field	scala/Enumeration$$anonfun$isValDef$1$1.serialVersionUID:J
Asciz	m$1;
Asciz	Ljava/lang/reflect/Method;;
Asciz	apply;
Asciz	(Ljava/lang/reflect/Field;)Z;
Asciz	LineNumberTable;
Asciz	java/lang/reflect/Field;
class	java/lang/reflect/Field
Asciz	getName;
Asciz	()Ljava/lang/String;;
NameAndType	getName:()Ljava/lang/String;
Method	java/lang/reflect/Field.getName:()Ljava/lang/String;
NameAndType	m$1:Ljava/lang/reflect/Method;
Field	scala/Enumeration$$anonfun$isValDef$1$1.m$1:Ljava/lang/reflect/Method;
Asciz	java/lang/reflect/Method;
class	java/lang/reflect/Method
Method	java/lang/reflect/Method.getName:()Ljava/lang/String;
Asciz	java/lang/Object;
class	java/lang/Object
Asciz	equals;
Asciz	(Ljava/lang/Object;)Z;
NameAndType	equals:(Ljava/lang/Object;)Z
Method	java/lang/Object.equals:(Ljava/lang/Object;)Z
Asciz	getType;
Asciz	()Ljava/lang/Class;;
NameAndType	getType:()Ljava/lang/Class;
Method	java/lang/reflect/Field.getType:()Ljava/lang/Class;
Asciz	getReturnType;
NameAndType	getReturnType:()Ljava/lang/Class;
Method	java/lang/reflect/Method.getReturnType:()Ljava/lang/Class;
Asciz	this;
Asciz	Lscala/Enumeration$$anonfun$isValDef$1$1;;
Asciz	fd;
Asciz	Ljava/lang/reflect/Field;;
Asciz	LocalVariableTable;
Asciz	(Ljava/lang/Object;)Ljava/lang/Object;;
NameAndType	apply:(Ljava/lang/reflect/Field;)Z
Method	scala/Enumeration$$anonfun$isValDef$1$1.apply:(Ljava/lang/reflect/Field;)Z
Asciz	scala/runtime/BoxesRunTime;
class	scala/runtime/BoxesRunTime
Asciz	boxToBoolean;
Asciz	(Z)Ljava/lang/Boolean;;
NameAndType	boxToBoolean:(Z)Ljava/lang/Boolean;
Method	scala/runtime/BoxesRunTime.boxToBoolean:(Z)Ljava/lang/Boolean;
Asciz	v1;
Asciz	Ljava/lang/Object;;
Asciz	<init>;
Asciz	(Lscala/Enumeration;Ljava/lang/reflect/Method;)V;
Asciz	scala/runtime/AbstractFunction1;
class	scala/runtime/AbstractFunction1
NameAndType	"<init>":()V
Method	scala/runtime/AbstractFunction1."<init>":()V
Asciz	$outer;
Asciz	Lscala/Enumeration;;
Asciz	Scala;
Asciz	InnerClasses;
Asciz	scala/Enumeration;
class	scala/Enumeration
Asciz	$anonfun$isValDef$1$1;
Asciz	java/io/Serializable;
class	java/io/Serializable

{
public static final long serialVersionUID;
  Signature: J

public final java.lang.reflect.Method m$1;
  Signature: Ljava/lang/reflect/Method;

public static {};
  Signature: ()V
  Code:
   Stack=2, Locals=0, Args_size=0
	lconst_0
	putstatic	Field serialVersionUID:J
	return
  Labels:

public final boolean apply(java.lang.reflect.Field);
  Signature: (Ljava/lang/reflect/Field;)Z
  Code:
   Stack=2, Locals=4, Args_size=2
	aload_1
	invokevirtual	Method java/lang/reflect/Field.getName:()Ljava/lang/String;
	aload_0
	getfield	Field m$1:Ljava/lang/reflect/Method;
	invokevirtual	Method java/lang/reflect/Method.getName:()Ljava/lang/String;
	astore_2
	dup
	ifnonnull	l1 // aload_2
	pop
	aload_2
	ifnull	l2 // aload_1
	goto	l3 // iconst_0
l1	aload_2
	invokevirtual	Method java/lang/Object.equals:(Ljava/lang/Object;)Z
	ifeq	l3 // iconst_0
l2	aload_1
	invokevirtual	Method java/lang/reflect/Field.getType:()Ljava/lang/Class;
	aload_0
	getfield	Field m$1:Ljava/lang/reflect/Method;
	invokevirtual	Method java/lang/reflect/Method.getReturnType:()Ljava/lang/Class;
	astore_3
	dup
	ifnonnull	l4 // aload_3
	pop
	aload_3
	ifnull	l5 // iconst_1
	goto	l3 // iconst_0
l4	aload_3
	invokevirtual	Method java/lang/Object.equals:(Ljava/lang/Object;)Z
	ifeq	l3 // iconst_0
l5	iconst_1
	goto	l6 // ireturn
l3	iconst_0
l6	ireturn
  Labels:
   	l1 = 24 // aload_2
   	l2 = 31 // aload_1
   	l4 = 55 // aload_3
   	l5 = 62 // iconst_1
   	l3 = 66 // iconst_0
   	l6 = 67 // ireturn
  LocalVariableTable: 
   Start  Length  Slot  Name   Signature
   0      68      0    this       Lscala/Enumeration$$anonfun$isValDef$1$1;
   0      68      1    fd       Ljava/lang/reflect/Field;


public final java.lang.Object apply(java.lang.Object);
  Signature: (Ljava/lang/Object;)Ljava/lang/Object;
  Code:
   Stack=2, Locals=3, Args_size=2
	aload_0
	aload_1
	checkcast	class java/lang/reflect/Field
	invokevirtual	Method apply:(Ljava/lang/reflect/Field;)Z
	istore_2
	iload_2
	invokestatic	Method scala/runtime/BoxesRunTime.boxToBoolean:(Z)Ljava/lang/Boolean;
	areturn
  Labels:
  LocalVariableTable: 
   Start  Length  Slot  Name   Signature
   0      14      0    this       Lscala/Enumeration$$anonfun$isValDef$1$1;
   0      14      1    v1       Ljava/lang/Object;


public scala.Enumeration$$anonfun$isValDef$1$1(scala.Enumeration, java.lang.reflect.Method);
  Signature: (Lscala/Enumeration;Ljava/lang/reflect/Method;)V
  Code:
   Stack=2, Locals=3, Args_size=3
	aload_0
	aload_2
	putfield	Field m$1:Ljava/lang/reflect/Method;
	aload_0
	invokespecial	Method scala/runtime/AbstractFunction1."<init>":()V
	return
  Labels:
  LocalVariableTable: 
   Start  Length  Slot  Name   Signature
   0      10      0    this       Lscala/Enumeration$$anonfun$isValDef$1$1;
   0      10      1    $outer       Lscala/Enumeration;


}

