Compiled from "Enumeration.scala"
public final class scala.Enumeration$ValueSet$$anonfun$apply$1 extends java.lang.Object implements scala.Function2,scala.ScalaObject,java.io.Serializable
  SourceFile: "Enumeration.scala"
  Scala: length = 0x
   
  InnerClass: 
   public abstract Value=class scala/Enumeration$Value of class scala/Enumeration
   public ValueSet=class scala/Enumeration$ValueSet of class scala/Enumeration
   public final $anonfun$apply$1=class scala/Enumeration$ValueSet$$anonfun$apply$1 of class scala/Enumeration$ValueSet$
  minor version: 0
  major version: 49
  Constant pool:
Asciz	SourceFile;
Asciz	Enumeration.scala;
Asciz	<clinit>;
Asciz	()V;
Asciz	Code;
Asciz	serialVersionUID;
Asciz	J;
Asciz	scala/Enumeration$ValueSet$$anonfun$apply$1;
class	scala/Enumeration$ValueSet$$anonfun$apply$1
NameAndType	serialVersionUID:J
Field	scala/Enumeration$ValueSet$$anonfun$apply$1.serialVersionUID:J
Asciz	<init>;
Asciz	(Lscala/Enumeration$ValueSet$;)V;
Asciz	LineNumberTable;
Asciz	java/lang/Object;
class	java/lang/Object
NameAndType	"<init>":()V
Method	java/lang/Object."<init>":()V
Asciz	scala/Function2$class;
class	scala/Function2$class
Asciz	$init$;
Asciz	(Lscala/Function2;)V;
NameAndType	$init$:(Lscala/Function2;)V
Method	scala/Function2$class.$init$:(Lscala/Function2;)V
Asciz	this;
Asciz	Lscala/Enumeration$ValueSet$$anonfun$apply$1;;
Asciz	$outer;
Asciz	Lscala/Enumeration$ValueSet$;;
Asciz	LocalVariableTable;
Asciz	apply;
Asciz	(Ljava/lang/Object;Ljava/lang/Object;)Ljava/lang/Object;;
Asciz	scala/Enumeration$ValueSet;
class	scala/Enumeration$ValueSet
Asciz	scala/Enumeration$Value;
class	scala/Enumeration$Value
Asciz	(Lscala/Enumeration$ValueSet;Lscala/Enumeration$Value;)Lscala/Enumeration$ValueSet;;
NameAndType	apply:(Lscala/Enumeration$ValueSet;Lscala/Enumeration$Value;)Lscala/Enumeration$ValueSet;
Method	scala/Enumeration$ValueSet$$anonfun$apply$1.apply:(Lscala/Enumeration$ValueSet;Lscala/Enumeration$Value;)Lscala/Enumeration$ValueSet;
Asciz	v1;
Asciz	Ljava/lang/Object;;
Asciz	v2;
Asciz	$plus;
Asciz	(Lscala/Enumeration$Value;)Lscala/Enumeration$ValueSet;;
NameAndType	$plus:(Lscala/Enumeration$Value;)Lscala/Enumeration$ValueSet;
Method	scala/Enumeration$ValueSet.$plus:(Lscala/Enumeration$Value;)Lscala/Enumeration$ValueSet;
Asciz	curry;
Asciz	()Lscala/Function1;;
Asciz	(Lscala/Function2;)Lscala/Function1;;
NameAndType	curry:(Lscala/Function2;)Lscala/Function1;
Method	scala/Function2$class.curry:(Lscala/Function2;)Lscala/Function1;
Asciz	toString;
Asciz	()Ljava/lang/String;;
Asciz	(Lscala/Function2;)Ljava/lang/String;;
NameAndType	toString:(Lscala/Function2;)Ljava/lang/String;
Method	scala/Function2$class.toString:(Lscala/Function2;)Ljava/lang/String;
Asciz	Scala;
Asciz	InnerClasses;
Asciz	scala/Enumeration;
class	scala/Enumeration
Asciz	Value;
Asciz	ValueSet;
Asciz	scala/Enumeration$ValueSet$;
class	scala/Enumeration$ValueSet$
Asciz	$anonfun$apply$1;
Asciz	scala/Function2;
class	scala/Function2
Asciz	scala/ScalaObject;
class	scala/ScalaObject
Asciz	java/io/Serializable;
class	java/io/Serializable

{
public static final long serialVersionUID;
  Signature: J

public static {};
  Signature: ()V
  Code:
   Stack=2, Locals=0, Args_size=0
	lconst_0
	putstatic	Field serialVersionUID:J
	return
  Labels:

public scala.Enumeration$ValueSet$$anonfun$apply$1(scala.Enumeration$ValueSet$);
  Signature: (Lscala/Enumeration$ValueSet$;)V
  Code:
   Stack=1, Locals=2, Args_size=2
	aload_0
	invokespecial	Method java/lang/Object."<init>":()V
	aload_0
	invokestatic	Method scala/Function2$class.$init$:(Lscala/Function2;)V
	return
  Labels:
  LocalVariableTable: 
   Start  Length  Slot  Name   Signature
   0      9      0    this       Lscala/Enumeration$ValueSet$$anonfun$apply$1;
   0      9      1    $outer       Lscala/Enumeration$ValueSet$;


public final java.lang.Object apply(java.lang.Object, java.lang.Object);
  Signature: (Ljava/lang/Object;Ljava/lang/Object;)Ljava/lang/Object;
  Code:
   Stack=3, Locals=3, Args_size=3
	aload_0
	aload_1
	checkcast	class scala/Enumeration$ValueSet
	aload_2
	checkcast	class scala/Enumeration$Value
	invokevirtual	Method apply:(Lscala/Enumeration$ValueSet;Lscala/Enumeration$Value;)Lscala/Enumeration$ValueSet;
	areturn
  Labels:
  LocalVariableTable: 
   Start  Length  Slot  Name   Signature
   0      13      0    this       Lscala/Enumeration$ValueSet$$anonfun$apply$1;
   0      13      1    v1       Ljava/lang/Object;
   0      13      2    v2       Ljava/lang/Object;


public final scala.Enumeration$ValueSet apply(scala.Enumeration$ValueSet, scala.Enumeration$Value);
  Signature: (Lscala/Enumeration$ValueSet;Lscala/Enumeration$Value;)Lscala/Enumeration$ValueSet;
  Code:
   Stack=2, Locals=3, Args_size=3
	aload_1
	aload_2
	invokevirtual	Method scala/Enumeration$ValueSet.$plus:(Lscala/Enumeration$Value;)Lscala/Enumeration$ValueSet;
	areturn
  Labels:

public scala.Function1 curry();
  Signature: ()Lscala/Function1;
  Code:
   Stack=1, Locals=1, Args_size=1
	aload_0
	invokestatic	Method scala/Function2$class.curry:(Lscala/Function2;)Lscala/Function1;
	areturn
  Labels:

public java.lang.String toString();
  Signature: ()Ljava/lang/String;
  Code:
   Stack=1, Locals=1, Args_size=1
	aload_0
	invokestatic	Method scala/Function2$class.toString:(Lscala/Function2;)Ljava/lang/String;
	areturn
  Labels:

}

