Compiled from "Enumeration.scala"
public final class scala.Enumeration$ValueSet$$anonfun$apply$1 extends java.lang.Object implements scala.Function1,scala.ScalaObject,java.io.Serializable
  SourceFile: "Enumeration.scala"
  Scala: length = 0x
   
  InnerClass: 
   public abstract #75= #32 of #74; //Value=class scala/Enumeration$Value of class scala/Enumeration
   public #76= #50 of #74; //ValueSet=class scala/Enumeration$ValueSet of class scala/Enumeration
   public final #77= #10 of #50; //$anonfun$apply$1=class scala/Enumeration$ValueSet$$anonfun$apply$1 of class scala/Enumeration$ValueSet
  minor version: 0
  major version: 49
  Constant pool:
const #1 = Asciz	SourceFile;
const #2 = Asciz	Enumeration.scala;
const #3 = Asciz	s$2;
const #4 = Asciz	Lscala/runtime/ObjectRef;;
const #5 = Asciz	<init>;
const #6 = Asciz	(Lscala/Enumeration$ValueSet$;Lscala/runtime/ObjectRef;)V;
const #7 = Asciz	Code;
const #8 = Asciz	LineNumberTable;
const #9 = Asciz	scala/Enumeration$ValueSet$$anonfun$apply$1;
const #10 = class	#9;	//  scala/Enumeration$ValueSet$$anonfun$apply$1
const #11 = NameAndType	#3:#4;//  s$2:Lscala/runtime/ObjectRef;
const #12 = Field	#10.#11;	//  scala/Enumeration$ValueSet$$anonfun$apply$1.s$2:Lscala/runtime/ObjectRef;
const #13 = Asciz	java/lang/Object;
const #14 = class	#13;	//  java/lang/Object
const #15 = Asciz	()V;
const #16 = NameAndType	#5:#15;//  "<init>":()V
const #17 = Method	#14.#16;	//  java/lang/Object."<init>":()V
const #18 = Asciz	scala/Function1$class;
const #19 = class	#18;	//  scala/Function1$class
const #20 = Asciz	$init$;
const #21 = Asciz	(Lscala/Function1;)V;
const #22 = NameAndType	#20:#21;//  $init$:(Lscala/Function1;)V
const #23 = Method	#19.#22;	//  scala/Function1$class.$init$:(Lscala/Function1;)V
const #24 = Asciz	this;
const #25 = Asciz	Lscala/Enumeration$ValueSet$$anonfun$apply$1;;
const #26 = Asciz	$outer;
const #27 = Asciz	Lscala/Enumeration$ValueSet$;;
const #28 = Asciz	LocalVariableTable;
const #29 = Asciz	apply;
const #30 = Asciz	(Ljava/lang/Object;)Ljava/lang/Object;;
const #31 = Asciz	scala/Enumeration$Value;
const #32 = class	#31;	//  scala/Enumeration$Value
const #33 = Asciz	(Lscala/Enumeration$Value;)V;
const #34 = NameAndType	#29:#33;//  apply:(Lscala/Enumeration$Value;)V
const #35 = Method	#10.#34;	//  scala/Enumeration$ValueSet$$anonfun$apply$1.apply:(Lscala/Enumeration$Value;)V
const #36 = Asciz	scala/runtime/BoxedUnit;
const #37 = class	#36;	//  scala/runtime/BoxedUnit
const #38 = Asciz	UNIT;
const #39 = Asciz	Lscala/runtime/BoxedUnit;;
const #40 = NameAndType	#38:#39;//  UNIT:Lscala/runtime/BoxedUnit;
const #41 = Field	#37.#40;	//  scala/runtime/BoxedUnit.UNIT:Lscala/runtime/BoxedUnit;
const #42 = Asciz	v1;
const #43 = Asciz	Ljava/lang/Object;;
const #44 = Asciz	scala/runtime/ObjectRef;
const #45 = class	#44;	//  scala/runtime/ObjectRef
const #46 = Asciz	elem;
const #47 = NameAndType	#46:#43;//  elem:Ljava/lang/Object;
const #48 = Field	#45.#47;	//  scala/runtime/ObjectRef.elem:Ljava/lang/Object;
const #49 = Asciz	scala/Enumeration$ValueSet;
const #50 = class	#49;	//  scala/Enumeration$ValueSet
const #51 = Asciz	$plus;
const #52 = Asciz	(Lscala/Enumeration$Value;)Lscala/Enumeration$ValueSet;;
const #53 = NameAndType	#51:#52;//  $plus:(Lscala/Enumeration$Value;)Lscala/Enumeration$ValueSet;
const #54 = Method	#50.#53;	//  scala/Enumeration$ValueSet.$plus:(Lscala/Enumeration$Value;)Lscala/Enumeration$ValueSet;
const #55 = Asciz	Lscala/Enumeration$Value;;
const #56 = Asciz	andThen;
const #57 = Asciz	(Lscala/Function1;)Lscala/Function1;;
const #58 = Asciz	(Lscala/Function1;Lscala/Function1;)Lscala/Function1;;
const #59 = NameAndType	#56:#58;//  andThen:(Lscala/Function1;Lscala/Function1;)Lscala/Function1;
const #60 = Method	#19.#59;	//  scala/Function1$class.andThen:(Lscala/Function1;Lscala/Function1;)Lscala/Function1;
const #61 = Asciz	g;
const #62 = Asciz	Lscala/Function1;;
const #63 = Asciz	compose;
const #64 = NameAndType	#63:#58;//  compose:(Lscala/Function1;Lscala/Function1;)Lscala/Function1;
const #65 = Method	#19.#64;	//  scala/Function1$class.compose:(Lscala/Function1;Lscala/Function1;)Lscala/Function1;
const #66 = Asciz	toString;
const #67 = Asciz	()Ljava/lang/String;;
const #68 = Asciz	(Lscala/Function1;)Ljava/lang/String;;
const #69 = NameAndType	#66:#68;//  toString:(Lscala/Function1;)Ljava/lang/String;
const #70 = Method	#19.#69;	//  scala/Function1$class.toString:(Lscala/Function1;)Ljava/lang/String;
const #71 = Asciz	Scala;
const #72 = Asciz	InnerClasses;
const #73 = Asciz	scala/Enumeration;
const #74 = class	#73;	//  scala/Enumeration
const #75 = Asciz	Value;
const #76 = Asciz	ValueSet;
const #77 = Asciz	$anonfun$apply$1;
const #78 = Asciz	scala/Function1;
const #79 = class	#78;	//  scala/Function1
const #80 = Asciz	scala/ScalaObject;
const #81 = class	#80;	//  scala/ScalaObject
const #82 = Asciz	java/io/Serializable;
const #83 = class	#82;	//  java/io/Serializable

{
public scala.Enumeration$ValueSet$$anonfun$apply$1(scala.Enumeration$ValueSet$, scala.runtime.ObjectRef);
  Code:
   Stack=2, Locals=3, Args_size=3
   0:	aload_0
   1:	aload_2
   2:	putfield	#12; //Field s$2:Lscala/runtime/ObjectRef;
   5:	aload_0
   6:	invokespecial	#17; //Method java/lang/Object."<init>":()V
   9:	aload_0
   10:	invokestatic	#23; //Method scala/Function1$class.$init$:(Lscala/Function1;)V
   13:	return
  LineNumberTable: 
   line 230: 0

  LocalVariableTable: 
   Start  Length  Slot  Name   Signature
   0      14      0    this       Lscala/Enumeration$ValueSet$$anonfun$apply$1;
   0      14      1    $outer       Lscala/Enumeration$ValueSet$;


public final java.lang.Object apply(java.lang.Object);
  Code:
   Stack=2, Locals=2, Args_size=2
   0:	aload_0
   1:	aload_1
   2:	checkcast	#32; //class scala/Enumeration$Value
   5:	invokevirtual	#35; //Method apply:(Lscala/Enumeration$Value;)V
   8:	getstatic	#41; //Field scala/runtime/BoxedUnit.UNIT:Lscala/runtime/BoxedUnit;
   11:	areturn
  LineNumberTable: 
   line 230: 0

  LocalVariableTable: 
   Start  Length  Slot  Name   Signature
   0      12      0    this       Lscala/Enumeration$ValueSet$$anonfun$apply$1;
   0      12      1    v1       Ljava/lang/Object;


public final void apply(scala.Enumeration$Value);
  Code:
   Stack=3, Locals=2, Args_size=2
   0:	aload_0
   1:	getfield	#12; //Field s$2:Lscala/runtime/ObjectRef;
   4:	aload_0
   5:	getfield	#12; //Field s$2:Lscala/runtime/ObjectRef;
   8:	getfield	#48; //Field scala/runtime/ObjectRef.elem:Ljava/lang/Object;
   11:	checkcast	#50; //class scala/Enumeration$ValueSet
   14:	aload_1
   15:	invokevirtual	#54; //Method scala/Enumeration$ValueSet.$plus:(Lscala/Enumeration$Value;)Lscala/Enumeration$ValueSet;
   18:	putfield	#48; //Field scala/runtime/ObjectRef.elem:Ljava/lang/Object;
   21:	return
  LineNumberTable: 
   line 230: 0

  LocalVariableTable: 
   Start  Length  Slot  Name   Signature
   0      22      0    this       Lscala/Enumeration$ValueSet$$anonfun$apply$1;
   0      22      1    elem       Lscala/Enumeration$Value;


public scala.Function1 andThen(scala.Function1);
  Code:
   Stack=2, Locals=2, Args_size=2
   0:	aload_0
   1:	aload_1
   2:	invokestatic	#60; //Method scala/Function1$class.andThen:(Lscala/Function1;Lscala/Function1;)Lscala/Function1;
   5:	areturn
  LineNumberTable: 
   line 230: 0

  LocalVariableTable: 
   Start  Length  Slot  Name   Signature
   0      6      0    this       Lscala/Enumeration$ValueSet$$anonfun$apply$1;
   0      6      1    g       Lscala/Function1;


public scala.Function1 compose(scala.Function1);
  Code:
   Stack=2, Locals=2, Args_size=2
   0:	aload_0
   1:	aload_1
   2:	invokestatic	#65; //Method scala/Function1$class.compose:(Lscala/Function1;Lscala/Function1;)Lscala/Function1;
   5:	areturn
  LineNumberTable: 
   line 230: 0

  LocalVariableTable: 
   Start  Length  Slot  Name   Signature
   0      6      0    this       Lscala/Enumeration$ValueSet$$anonfun$apply$1;
   0      6      1    g       Lscala/Function1;


public java.lang.String toString();
  Code:
   Stack=1, Locals=1, Args_size=1
   0:	aload_0
   1:	invokestatic	#70; //Method scala/Function1$class.toString:(Lscala/Function1;)Ljava/lang/String;
   4:	areturn
  LineNumberTable: 
   line 230: 0


}

