Compiled from "Enumeration.scala"
public final class scala.Enumeration$ValueSet$$anonfun$iterator$1 extends java.lang.Object implements scala.Function1,scala.ScalaObject,java.io.Serializable
  SourceFile: "Enumeration.scala"
  Scala: length = 0x
   
  InnerClass: 
   public abstract Value=class scala/Enumeration$Value of class scala/Enumeration
   public ValueSet=class scala/Enumeration$ValueSet of class scala/Enumeration
   public final $anonfun$iterator$1=class scala/Enumeration$ValueSet$$anonfun$iterator$1 of class scala/Enumeration$ValueSet
  minor version: 0
  major version: 49
  Constant pool:
Asciz	SourceFile;
Asciz	Enumeration.scala;
Asciz	<clinit>;
Asciz	()V;
Asciz	Code;
Asciz	serialVersionUID;
Asciz	J;
Asciz	scala/Enumeration$ValueSet$$anonfun$iterator$1;
class	scala/Enumeration$ValueSet$$anonfun$iterator$1
NameAndType	serialVersionUID:J
Field	scala/Enumeration$ValueSet$$anonfun$iterator$1.serialVersionUID:J
Asciz	$outer;
Asciz	Lscala/Enumeration$ValueSet;;
Asciz	<init>;
Asciz	(Lscala/Enumeration$ValueSet;)V;
Asciz	LineNumberTable;
Asciz	java/lang/NullPointerException;
class	java/lang/NullPointerException
NameAndType	"<init>":()V
Method	java/lang/NullPointerException."<init>":()V
NameAndType	$outer:Lscala/Enumeration$ValueSet;
Field	scala/Enumeration$ValueSet$$anonfun$iterator$1.$outer:Lscala/Enumeration$ValueSet;
Asciz	java/lang/Object;
class	java/lang/Object
Method	java/lang/Object."<init>":()V
Asciz	scala/Function1$class;
class	scala/Function1$class
Asciz	$init$;
Asciz	(Lscala/Function1;)V;
NameAndType	$init$:(Lscala/Function1;)V
Method	scala/Function1$class.$init$:(Lscala/Function1;)V
Asciz	this;
Asciz	Lscala/Enumeration$ValueSet$$anonfun$iterator$1;;
Asciz	LocalVariableTable;
Asciz	apply;
Asciz	(Ljava/lang/Object;)Ljava/lang/Object;;
Asciz	scala/runtime/BoxesRunTime;
class	scala/runtime/BoxesRunTime
Asciz	unboxToInt;
Asciz	(Ljava/lang/Object;)I;
NameAndType	unboxToInt:(Ljava/lang/Object;)I
Method	scala/runtime/BoxesRunTime.unboxToInt:(Ljava/lang/Object;)I
Asciz	(I)Lscala/Enumeration$Value;;
NameAndType	apply:(I)Lscala/Enumeration$Value;
Method	scala/Enumeration$ValueSet$$anonfun$iterator$1.apply:(I)Lscala/Enumeration$Value;
Asciz	v1;
Asciz	Ljava/lang/Object;;
Asciz	scala/Enumeration$ValueSet;
class	scala/Enumeration$ValueSet
Asciz	scala$Enumeration$ValueSet$$$outer;
Asciz	()Lscala/Enumeration;;
NameAndType	scala$Enumeration$ValueSet$$$outer:()Lscala/Enumeration;
Method	scala/Enumeration$ValueSet.scala$Enumeration$ValueSet$$$outer:()Lscala/Enumeration;
Asciz	scala/Enumeration;
class	scala/Enumeration
Method	scala/Enumeration.apply:(I)Lscala/Enumeration$Value;
Asciz	andThen;
Asciz	(Lscala/Function1;)Lscala/Function1;;
Asciz	(Lscala/Function1;Lscala/Function1;)Lscala/Function1;;
NameAndType	andThen:(Lscala/Function1;Lscala/Function1;)Lscala/Function1;
Method	scala/Function1$class.andThen:(Lscala/Function1;Lscala/Function1;)Lscala/Function1;
Asciz	g;
Asciz	Lscala/Function1;;
Asciz	compose;
NameAndType	compose:(Lscala/Function1;Lscala/Function1;)Lscala/Function1;
Method	scala/Function1$class.compose:(Lscala/Function1;Lscala/Function1;)Lscala/Function1;
Asciz	toString;
Asciz	()Ljava/lang/String;;
Asciz	(Lscala/Function1;)Ljava/lang/String;;
NameAndType	toString:(Lscala/Function1;)Ljava/lang/String;
Method	scala/Function1$class.toString:(Lscala/Function1;)Ljava/lang/String;
Asciz	Scala;
Asciz	InnerClasses;
Asciz	scala/Enumeration$Value;
class	scala/Enumeration$Value
Asciz	Value;
Asciz	ValueSet;
Asciz	$anonfun$iterator$1;
Asciz	scala/Function1;
class	scala/Function1
Asciz	scala/ScalaObject;
class	scala/ScalaObject
Asciz	java/io/Serializable;
class	java/io/Serializable

{
public static final long serialVersionUID;
  Signature: J

private final scala.Enumeration$ValueSet $outer;
  Signature: Lscala/Enumeration$ValueSet;

public static {};
  Signature: ()V
  Code:
   Stack=2, Locals=0, Args_size=0
	lconst_0
	putstatic	Field serialVersionUID:J
	return
  Labels:

public scala.Enumeration$ValueSet$$anonfun$iterator$1(scala.Enumeration$ValueSet);
  Signature: (Lscala/Enumeration$ValueSet;)V
  Code:
   Stack=2, Locals=2, Args_size=2
	aload_1
	ifnonnull	l1 // aload_0
	new	class java/lang/NullPointerException
	dup
	invokespecial	Method java/lang/NullPointerException."<init>":()V
	athrow
l1	aload_0
	aload_1
	putfield	Field $outer:Lscala/Enumeration$ValueSet;
	aload_0
	invokespecial	Method java/lang/Object."<init>":()V
	aload_0
	invokestatic	Method scala/Function1$class.$init$:(Lscala/Function1;)V
	return
  Labels:
   	l1 = 12 // aload_0
  LocalVariableTable: 
   Start  Length  Slot  Name   Signature
   0      26      0    this       Lscala/Enumeration$ValueSet$$anonfun$iterator$1;
   0      26      1    $outer       Lscala/Enumeration$ValueSet;


public final java.lang.Object apply(java.lang.Object);
  Signature: (Ljava/lang/Object;)Ljava/lang/Object;
  Code:
   Stack=2, Locals=3, Args_size=2
	aload_0
	getfield	Field $outer:Lscala/Enumeration$ValueSet;
	astore_2
	aload_0
	aload_1
	invokestatic	Method scala/runtime/BoxesRunTime.unboxToInt:(Ljava/lang/Object;)I
	invokevirtual	Method apply:(I)Lscala/Enumeration$Value;
	areturn
  Labels:
  LocalVariableTable: 
   Start  Length  Slot  Name   Signature
   0      14      0    this       Lscala/Enumeration$ValueSet$$anonfun$iterator$1;
   5      9      1    v1       Ljava/lang/Object;


public final scala.Enumeration$Value apply(int);
  Signature: (I)Lscala/Enumeration$Value;
  Code:
   Stack=2, Locals=3, Args_size=2
	aload_0
	getfield	Field $outer:Lscala/Enumeration$ValueSet;
	astore_2
	aload_0
	getfield	Field $outer:Lscala/Enumeration$ValueSet;
	invokevirtual	Method scala/Enumeration$ValueSet.scala$Enumeration$ValueSet$$$outer:()Lscala/Enumeration;
	iload_1
	invokevirtual	Method scala/Enumeration.apply:(I)Lscala/Enumeration$Value;
	areturn
  Labels:
  LocalVariableTable: 
   Start  Length  Slot  Name   Signature
   0      17      0    this       Lscala/Enumeration$ValueSet$$anonfun$iterator$1;


public scala.Function1 andThen(scala.Function1);
  Signature: (Lscala/Function1;)Lscala/Function1;
  Code:
   Stack=2, Locals=2, Args_size=2
	aload_0
	aload_1
	invokestatic	Method scala/Function1$class.andThen:(Lscala/Function1;Lscala/Function1;)Lscala/Function1;
	areturn
  Labels:
  LocalVariableTable: 
   Start  Length  Slot  Name   Signature
   0      6      0    this       Lscala/Enumeration$ValueSet$$anonfun$iterator$1;
   0      6      1    g       Lscala/Function1;


public scala.Function1 compose(scala.Function1);
  Signature: (Lscala/Function1;)Lscala/Function1;
  Code:
   Stack=2, Locals=2, Args_size=2
	aload_0
	aload_1
	invokestatic	Method scala/Function1$class.compose:(Lscala/Function1;Lscala/Function1;)Lscala/Function1;
	areturn
  Labels:
  LocalVariableTable: 
   Start  Length  Slot  Name   Signature
   0      6      0    this       Lscala/Enumeration$ValueSet$$anonfun$iterator$1;
   0      6      1    g       Lscala/Function1;


public java.lang.String toString();
  Signature: ()Ljava/lang/String;
  Code:
   Stack=1, Locals=1, Args_size=1
	aload_0
	invokestatic	Method scala/Function1$class.toString:(Lscala/Function1;)Ljava/lang/String;
	areturn
  Labels:

}

