Compiled from "Enumeration.scala"
public final class scala.Enumeration$$anonfun$scala$Enumeration$$nameOf$2 extends java.lang.Object implements scala.Function1,scala.ScalaObject,java.io.Serializable
  SourceFile: "Enumeration.scala"
  Scala: length = 0x
   
  InnerClass: 
   public #129= #53 of #69; //Val=class scala/Enumeration$Val of class scala/Enumeration
   public #132= #91 of #131; //ArrowAssoc=class scala/Predef$ArrowAssoc of class scala/Predef
   public final #133= #9 of #69; //$anonfun$scala$Enumeration$$nameOf$2=class scala/Enumeration$$anonfun$scala$Enumeration$$nameOf$2 of class scala/Enumeration
  minor version: 0
  major version: 49
  Constant pool:
const #1 = Asciz	SourceFile;
const #2 = Asciz	Enumeration.scala;
const #3 = Asciz	<clinit>;
const #4 = Asciz	()V;
const #5 = Asciz	Code;
const #6 = Asciz	serialVersionUID;
const #7 = Asciz	J;
const #8 = Asciz	scala/Enumeration$$anonfun$scala$Enumeration$$nameOf$2;
const #9 = class	#8;	//  scala/Enumeration$$anonfun$scala$Enumeration$$nameOf$2
const #10 = NameAndType	#6:#7;//  serialVersionUID:J
const #11 = Field	#9.#10;	//  scala/Enumeration$$anonfun$scala$Enumeration$$nameOf$2.serialVersionUID:J
const #12 = Asciz	$outer;
const #13 = Asciz	Lscala/Enumeration;;
const #14 = Asciz	<init>;
const #15 = Asciz	(Lscala/Enumeration;)V;
const #16 = Asciz	LineNumberTable;
const #17 = Asciz	java/lang/NullPointerException;
const #18 = class	#17;	//  java/lang/NullPointerException
const #19 = NameAndType	#14:#4;//  "<init>":()V
const #20 = Method	#18.#19;	//  java/lang/NullPointerException."<init>":()V
const #21 = NameAndType	#12:#13;//  $outer:Lscala/Enumeration;
const #22 = Field	#9.#21;	//  scala/Enumeration$$anonfun$scala$Enumeration$$nameOf$2.$outer:Lscala/Enumeration;
const #23 = Asciz	java/lang/Object;
const #24 = class	#23;	//  java/lang/Object
const #25 = Method	#24.#19;	//  java/lang/Object."<init>":()V
const #26 = Asciz	scala/Function1$class;
const #27 = class	#26;	//  scala/Function1$class
const #28 = Asciz	$init$;
const #29 = Asciz	(Lscala/Function1;)V;
const #30 = NameAndType	#28:#29;//  $init$:(Lscala/Function1;)V
const #31 = Method	#27.#30;	//  scala/Function1$class.$init$:(Lscala/Function1;)V
const #32 = Asciz	this;
const #33 = Asciz	Lscala/Enumeration$$anonfun$scala$Enumeration$$nameOf$2;;
const #34 = Asciz	LocalVariableTable;
const #35 = Asciz	apply;
const #36 = Asciz	(Ljava/lang/Object;)Ljava/lang/Object;;
const #37 = Asciz	java/lang/reflect/Method;
const #38 = class	#37;	//  java/lang/reflect/Method
const #39 = Asciz	(Ljava/lang/reflect/Method;)Lscala/collection/mutable/Map;;
const #40 = NameAndType	#35:#39;//  apply:(Ljava/lang/reflect/Method;)Lscala/collection/mutable/Map;
const #41 = Method	#9.#40;	//  scala/Enumeration$$anonfun$scala$Enumeration$$nameOf$2.apply:(Ljava/lang/reflect/Method;)Lscala/collection/mutable/Map;
const #42 = Asciz	v1;
const #43 = Asciz	Ljava/lang/Object;;
const #44 = Asciz	getName;
const #45 = Asciz	()Ljava/lang/String;;
const #46 = NameAndType	#44:#45;//  getName:()Ljava/lang/String;
const #47 = Method	#38.#46;	//  java/lang/reflect/Method.getName:()Ljava/lang/String;
const #48 = Asciz	invoke;
const #49 = Asciz	(Ljava/lang/Object;[Ljava/lang/Object;)Ljava/lang/Object;;
const #50 = NameAndType	#48:#49;//  invoke:(Ljava/lang/Object;[Ljava/lang/Object;)Ljava/lang/Object;
const #51 = Method	#38.#50;	//  java/lang/reflect/Method.invoke:(Ljava/lang/Object;[Ljava/lang/Object;)Ljava/lang/Object;
const #52 = Asciz	scala/Enumeration$Val;
const #53 = class	#52;	//  scala/Enumeration$Val
const #54 = Asciz	id;
const #55 = String	#54;	//  id
const #56 = Asciz	java/lang/Class;
const #57 = class	#56;	//  java/lang/Class
const #58 = Asciz	getMethod;
const #59 = Asciz	(Ljava/lang/String;[Ljava/lang/Class;)Ljava/lang/reflect/Method;;
const #60 = NameAndType	#58:#59;//  getMethod:(Ljava/lang/String;[Ljava/lang/Class;)Ljava/lang/reflect/Method;
const #61 = Method	#57.#60;	//  java/lang/Class.getMethod:(Ljava/lang/String;[Ljava/lang/Class;)Ljava/lang/reflect/Method;
const #62 = Asciz	java/lang/Integer;
const #63 = class	#62;	//  java/lang/Integer
const #64 = Asciz	intValue;
const #65 = Asciz	()I;
const #66 = NameAndType	#64:#65;//  intValue:()I
const #67 = Method	#63.#66;	//  java/lang/Integer.intValue:()I
const #68 = Asciz	scala/Enumeration;
const #69 = class	#68;	//  scala/Enumeration
const #70 = Asciz	scala$Enumeration$$nmap;
const #71 = Asciz	()Lscala/collection/mutable/Map;;
const #72 = NameAndType	#70:#71;//  scala$Enumeration$$nmap:()Lscala/collection/mutable/Map;
const #73 = Method	#69.#72;	//  scala/Enumeration.scala$Enumeration$$nmap:()Lscala/collection/mutable/Map;
const #74 = Asciz	scala/Predef$;
const #75 = class	#74;	//  scala/Predef$
const #76 = Asciz	MODULE$;
const #77 = Asciz	Lscala/Predef$;;
const #78 = NameAndType	#76:#77;//  MODULE$:Lscala/Predef$;
const #79 = Field	#75.#78;	//  scala/Predef$.MODULE$:Lscala/Predef$;
const #80 = Asciz	scala/runtime/BoxesRunTime;
const #81 = class	#80;	//  scala/runtime/BoxesRunTime
const #82 = Asciz	boxToInteger;
const #83 = Asciz	(I)Ljava/lang/Integer;;
const #84 = NameAndType	#82:#83;//  boxToInteger:(I)Ljava/lang/Integer;
const #85 = Method	#81.#84;	//  scala/runtime/BoxesRunTime.boxToInteger:(I)Ljava/lang/Integer;
const #86 = Asciz	any2ArrowAssoc;
const #87 = Asciz	(Ljava/lang/Object;)Lscala/Predef$ArrowAssoc;;
const #88 = NameAndType	#86:#87;//  any2ArrowAssoc:(Ljava/lang/Object;)Lscala/Predef$ArrowAssoc;
const #89 = Method	#75.#88;	//  scala/Predef$.any2ArrowAssoc:(Ljava/lang/Object;)Lscala/Predef$ArrowAssoc;
const #90 = Asciz	scala/Predef$ArrowAssoc;
const #91 = class	#90;	//  scala/Predef$ArrowAssoc
const #92 = Asciz	$minus$greater;
const #93 = Asciz	(Ljava/lang/Object;)Lscala/Tuple2;;
const #94 = NameAndType	#92:#93;//  $minus$greater:(Ljava/lang/Object;)Lscala/Tuple2;
const #95 = Method	#91.#94;	//  scala/Predef$ArrowAssoc.$minus$greater:(Ljava/lang/Object;)Lscala/Tuple2;
const #96 = Asciz	scala/collection/mutable/MapLike;
const #97 = class	#96;	//  scala/collection/mutable/MapLike
const #98 = Asciz	$plus$eq;
const #99 = Asciz	(Lscala/Tuple2;)Lscala/collection/mutable/MapLike;;
const #100 = NameAndType	#98:#99;//  $plus$eq:(Lscala/Tuple2;)Lscala/collection/mutable/MapLike;
const #101 = InterfaceMethod	#97.#100;	//  scala/collection/mutable/MapLike.$plus$eq:(Lscala/Tuple2;)Lscala/collection/mutable/MapLike;
const #102 = Asciz	scala/collection/mutable/Map;
const #103 = class	#102;	//  scala/collection/mutable/Map
const #104 = Asciz	m;
const #105 = Asciz	Ljava/lang/reflect/Method;;
const #106 = Asciz	idMeth;
const #107 = Asciz	value;
const #108 = Asciz	I;
const #109 = Asciz	name;
const #110 = Asciz	Ljava/lang/String;;
const #111 = Asciz	(Ljava/lang/reflect/Method;)Lscala/collection/mutable/Map<Ljava/lang/Integer;Ljava/lang/String;>;;
const #112 = Asciz	Signature;
const #113 = Asciz	andThen;
const #114 = Asciz	(Lscala/Function1;)Lscala/Function1;;
const #115 = Asciz	(Lscala/Function1;Lscala/Function1;)Lscala/Function1;;
const #116 = NameAndType	#113:#115;//  andThen:(Lscala/Function1;Lscala/Function1;)Lscala/Function1;
const #117 = Method	#27.#116;	//  scala/Function1$class.andThen:(Lscala/Function1;Lscala/Function1;)Lscala/Function1;
const #118 = Asciz	g;
const #119 = Asciz	Lscala/Function1;;
const #120 = Asciz	compose;
const #121 = NameAndType	#120:#115;//  compose:(Lscala/Function1;Lscala/Function1;)Lscala/Function1;
const #122 = Method	#27.#121;	//  scala/Function1$class.compose:(Lscala/Function1;Lscala/Function1;)Lscala/Function1;
const #123 = Asciz	toString;
const #124 = Asciz	(Lscala/Function1;)Ljava/lang/String;;
const #125 = NameAndType	#123:#124;//  toString:(Lscala/Function1;)Ljava/lang/String;
const #126 = Method	#27.#125;	//  scala/Function1$class.toString:(Lscala/Function1;)Ljava/lang/String;
const #127 = Asciz	Scala;
const #128 = Asciz	InnerClasses;
const #129 = Asciz	Val;
const #130 = Asciz	scala/Predef;
const #131 = class	#130;	//  scala/Predef
const #132 = Asciz	ArrowAssoc;
const #133 = Asciz	$anonfun$scala$Enumeration$$nameOf$2;
const #134 = Asciz	scala/Function1;
const #135 = class	#134;	//  scala/Function1
const #136 = Asciz	scala/ScalaObject;
const #137 = class	#136;	//  scala/ScalaObject
const #138 = Asciz	java/io/Serializable;
const #139 = class	#138;	//  java/io/Serializable

{
public static final long serialVersionUID;

public static {};
  Code:
   Stack=2, Locals=0, Args_size=0
   0:	lconst_0
   1:	putstatic	#11; //Field serialVersionUID:J
   4:	return

public scala.Enumeration$$anonfun$scala$Enumeration$$nameOf$2(scala.Enumeration);
  Code:
   Stack=2, Locals=2, Args_size=2
   0:	aload_1
   1:	ifnonnull	12
   4:	new	#18; //class java/lang/NullPointerException
   7:	dup
   8:	invokespecial	#20; //Method java/lang/NullPointerException."<init>":()V
   11:	athrow
   12:	aload_0
   13:	aload_1
   14:	putfield	#22; //Field $outer:Lscala/Enumeration;
   17:	aload_0
   18:	invokespecial	#25; //Method java/lang/Object."<init>":()V
   21:	aload_0
   22:	invokestatic	#31; //Method scala/Function1$class.$init$:(Lscala/Function1;)V
   25:	return
  LineNumberTable: 
   line 171: 0

  LocalVariableTable: 
   Start  Length  Slot  Name   Signature
   0      26      0    this       Lscala/Enumeration$$anonfun$scala$Enumeration$$nameOf$2;
   0      26      1    $outer       Lscala/Enumeration;


public final java.lang.Object apply(java.lang.Object);
  Code:
   Stack=2, Locals=3, Args_size=2
   0:	aload_0
   1:	getfield	#22; //Field $outer:Lscala/Enumeration;
   4:	astore_2
   5:	aload_0
   6:	aload_1
   7:	checkcast	#38; //class java/lang/reflect/Method
   10:	invokevirtual	#41; //Method apply:(Ljava/lang/reflect/Method;)Lscala/collection/mutable/Map;
   13:	areturn
  LineNumberTable: 
   line 171: 0

  LocalVariableTable: 
   Start  Length  Slot  Name   Signature
   0      14      0    this       Lscala/Enumeration$$anonfun$scala$Enumeration$$nameOf$2;
   5      9      1    v1       Ljava/lang/Object;


public final scala.collection.mutable.Map apply(java.lang.reflect.Method);
  Code:
   Stack=3, Locals=7, Args_size=2
   0:	aload_0
   1:	getfield	#22; //Field $outer:Lscala/Enumeration;
   4:	astore	6
   6:	aload_1
   7:	invokevirtual	#47; //Method java/lang/reflect/Method.getName:()Ljava/lang/String;
   10:	astore	5
   12:	aload_1
   13:	aload_0
   14:	getfield	#22; //Field $outer:Lscala/Enumeration;
   17:	iconst_0
   18:	anewarray	#24; //class java/lang/Object
   21:	invokevirtual	#51; //Method java/lang/reflect/Method.invoke:(Ljava/lang/Object;[Ljava/lang/Object;)Ljava/lang/Object;
   24:	astore_3
   25:	ldc	#53; //class scala/Enumeration$Val
   27:	ldc	#55; //String id
   29:	iconst_0
   30:	anewarray	#57; //class java/lang/Class
   33:	invokevirtual	#61; //Method java/lang/Class.getMethod:(Ljava/lang/String;[Ljava/lang/Class;)Ljava/lang/reflect/Method;
   36:	astore_2
   37:	aload_2
   38:	aload_3
   39:	iconst_0
   40:	anewarray	#24; //class java/lang/Object
   43:	invokevirtual	#51; //Method java/lang/reflect/Method.invoke:(Ljava/lang/Object;[Ljava/lang/Object;)Ljava/lang/Object;
   46:	checkcast	#63; //class java/lang/Integer
   49:	invokevirtual	#67; //Method java/lang/Integer.intValue:()I
   52:	istore	4
   54:	aload_0
   55:	getfield	#22; //Field $outer:Lscala/Enumeration;
   58:	invokevirtual	#73; //Method scala/Enumeration.scala$Enumeration$$nmap:()Lscala/collection/mutable/Map;
   61:	getstatic	#79; //Field scala/Predef$.MODULE$:Lscala/Predef$;
   64:	iload	4
   66:	invokestatic	#85; //Method scala/runtime/BoxesRunTime.boxToInteger:(I)Ljava/lang/Integer;
   69:	invokevirtual	#89; //Method scala/Predef$.any2ArrowAssoc:(Ljava/lang/Object;)Lscala/Predef$ArrowAssoc;
   72:	aload	5
   74:	invokevirtual	#95; //Method scala/Predef$ArrowAssoc.$minus$greater:(Ljava/lang/Object;)Lscala/Tuple2;
   77:	invokeinterface	#101,  2; //InterfaceMethod scala/collection/mutable/MapLike.$plus$eq:(Lscala/Tuple2;)Lscala/collection/mutable/MapLike;
   82:	checkcast	#103; //class scala/collection/mutable/Map
   85:	areturn
  LineNumberTable: 
   line 174: 0
   line 176: 12
   line 178: 25
   line 179: 37
   line 180: 54

  LocalVariableTable: 
   Start  Length  Slot  Name   Signature
   0      86      0    this       Lscala/Enumeration$$anonfun$scala$Enumeration$$nameOf$2;
   6      80      1    m       Ljava/lang/reflect/Method;
   37      48      2    idMeth       Ljava/lang/reflect/Method;
   25      60      3    value       Ljava/lang/Object;
   54      31      4    id       I
   12      73      5    name       Ljava/lang/String;

  Signature: length = 0x2
   00 6F 

public scala.Function1 andThen(scala.Function1);
  Code:
   Stack=2, Locals=2, Args_size=2
   0:	aload_0
   1:	aload_1
   2:	invokestatic	#117; //Method scala/Function1$class.andThen:(Lscala/Function1;Lscala/Function1;)Lscala/Function1;
   5:	areturn
  LineNumberTable: 
   line 171: 0

  LocalVariableTable: 
   Start  Length  Slot  Name   Signature
   0      6      0    this       Lscala/Enumeration$$anonfun$scala$Enumeration$$nameOf$2;
   0      6      1    g       Lscala/Function1;


public scala.Function1 compose(scala.Function1);
  Code:
   Stack=2, Locals=2, Args_size=2
   0:	aload_0
   1:	aload_1
   2:	invokestatic	#122; //Method scala/Function1$class.compose:(Lscala/Function1;Lscala/Function1;)Lscala/Function1;
   5:	areturn
  LineNumberTable: 
   line 171: 0

  LocalVariableTable: 
   Start  Length  Slot  Name   Signature
   0      6      0    this       Lscala/Enumeration$$anonfun$scala$Enumeration$$nameOf$2;
   0      6      1    g       Lscala/Function1;


public java.lang.String toString();
  Code:
   Stack=1, Locals=1, Args_size=1
   0:	aload_0
   1:	invokestatic	#126; //Method scala/Function1$class.toString:(Lscala/Function1;)Ljava/lang/String;
   4:	areturn
  LineNumberTable: 
   line 171: 0


}

