Compiled from "Enumeration.scala"
public final class scala.Enumeration$$anonfun$scala$Enumeration$$nameOf$1 extends java.lang.Object implements scala.Function1,scala.ScalaObject,java.io.Serializable
  SourceFile: "Enumeration.scala"
  Scala: length = 0x
   
  InnerClass: 
   public abstract #88= #46 of #87; //Value=class scala/Enumeration$Value of class scala/Enumeration
   public final #89= #9 of #87; //$anonfun$scala$Enumeration$$nameOf$1=class scala/Enumeration$$anonfun$scala$Enumeration$$nameOf$1 of class scala/Enumeration
  minor version: 0
  major version: 49
  Constant pool:
const #1 = Asciz	SourceFile;
const #2 = Asciz	Enumeration.scala;
const #3 = Asciz	<clinit>;
const #4 = Asciz	()V;
const #5 = Asciz	Code;
const #6 = Asciz	serialVersionUID;
const #7 = Asciz	J;
const #8 = Asciz	scala/Enumeration$$anonfun$scala$Enumeration$$nameOf$1;
const #9 = class	#8;	//  scala/Enumeration$$anonfun$scala$Enumeration$$nameOf$1
const #10 = NameAndType	#6:#7;//  serialVersionUID:J
const #11 = Field	#9.#10;	//  scala/Enumeration$$anonfun$scala$Enumeration$$nameOf$1.serialVersionUID:J
const #12 = Asciz	<init>;
const #13 = Asciz	(Lscala/Enumeration;)V;
const #14 = Asciz	LineNumberTable;
const #15 = Asciz	java/lang/Object;
const #16 = class	#15;	//  java/lang/Object
const #17 = NameAndType	#12:#4;//  "<init>":()V
const #18 = Method	#16.#17;	//  java/lang/Object."<init>":()V
const #19 = Asciz	scala/Function1$class;
const #20 = class	#19;	//  scala/Function1$class
const #21 = Asciz	$init$;
const #22 = Asciz	(Lscala/Function1;)V;
const #23 = NameAndType	#21:#22;//  $init$:(Lscala/Function1;)V
const #24 = Method	#20.#23;	//  scala/Function1$class.$init$:(Lscala/Function1;)V
const #25 = Asciz	this;
const #26 = Asciz	Lscala/Enumeration$$anonfun$scala$Enumeration$$nameOf$1;;
const #27 = Asciz	$outer;
const #28 = Asciz	Lscala/Enumeration;;
const #29 = Asciz	LocalVariableTable;
const #30 = Asciz	apply;
const #31 = Asciz	(Ljava/lang/Object;)Ljava/lang/Object;;
const #32 = Asciz	java/lang/reflect/Method;
const #33 = class	#32;	//  java/lang/reflect/Method
const #34 = Asciz	(Ljava/lang/reflect/Method;)Z;
const #35 = NameAndType	#30:#34;//  apply:(Ljava/lang/reflect/Method;)Z
const #36 = Method	#9.#35;	//  scala/Enumeration$$anonfun$scala$Enumeration$$nameOf$1.apply:(Ljava/lang/reflect/Method;)Z
const #37 = Asciz	scala/runtime/BoxesRunTime;
const #38 = class	#37;	//  scala/runtime/BoxesRunTime
const #39 = Asciz	boxToBoolean;
const #40 = Asciz	(Z)Ljava/lang/Boolean;;
const #41 = NameAndType	#39:#40;//  boxToBoolean:(Z)Ljava/lang/Boolean;
const #42 = Method	#38.#41;	//  scala/runtime/BoxesRunTime.boxToBoolean:(Z)Ljava/lang/Boolean;
const #43 = Asciz	v1;
const #44 = Asciz	Ljava/lang/Object;;
const #45 = Asciz	scala/Enumeration$Value;
const #46 = class	#45;	//  scala/Enumeration$Value
const #47 = Asciz	getReturnType;
const #48 = Asciz	()Ljava/lang/Class;;
const #49 = NameAndType	#47:#48;//  getReturnType:()Ljava/lang/Class;
const #50 = Method	#33.#49;	//  java/lang/reflect/Method.getReturnType:()Ljava/lang/Class;
const #51 = Asciz	java/lang/Class;
const #52 = class	#51;	//  java/lang/Class
const #53 = Asciz	isAssignableFrom;
const #54 = Asciz	(Ljava/lang/Class;)Z;
const #55 = NameAndType	#53:#54;//  isAssignableFrom:(Ljava/lang/Class;)Z
const #56 = Method	#52.#55;	//  java/lang/Class.isAssignableFrom:(Ljava/lang/Class;)Z
const #57 = Asciz	getModifiers;
const #58 = Asciz	()I;
const #59 = NameAndType	#57:#58;//  getModifiers:()I
const #60 = Method	#33.#59;	//  java/lang/reflect/Method.getModifiers:()I
const #61 = Asciz	java/lang/reflect/Modifier;
const #62 = class	#61;	//  java/lang/reflect/Modifier
const #63 = Asciz	isFinal;
const #64 = Asciz	(I)Z;
const #65 = NameAndType	#63:#64;//  isFinal:(I)Z
const #66 = Method	#62.#65;	//  java/lang/reflect/Modifier.isFinal:(I)Z
const #67 = Asciz	m;
const #68 = Asciz	Ljava/lang/reflect/Method;;
const #69 = Asciz	andThen;
const #70 = Asciz	(Lscala/Function1;)Lscala/Function1;;
const #71 = Asciz	(Lscala/Function1;Lscala/Function1;)Lscala/Function1;;
const #72 = NameAndType	#69:#71;//  andThen:(Lscala/Function1;Lscala/Function1;)Lscala/Function1;
const #73 = Method	#20.#72;	//  scala/Function1$class.andThen:(Lscala/Function1;Lscala/Function1;)Lscala/Function1;
const #74 = Asciz	g;
const #75 = Asciz	Lscala/Function1;;
const #76 = Asciz	compose;
const #77 = NameAndType	#76:#71;//  compose:(Lscala/Function1;Lscala/Function1;)Lscala/Function1;
const #78 = Method	#20.#77;	//  scala/Function1$class.compose:(Lscala/Function1;Lscala/Function1;)Lscala/Function1;
const #79 = Asciz	toString;
const #80 = Asciz	()Ljava/lang/String;;
const #81 = Asciz	(Lscala/Function1;)Ljava/lang/String;;
const #82 = NameAndType	#79:#81;//  toString:(Lscala/Function1;)Ljava/lang/String;
const #83 = Method	#20.#82;	//  scala/Function1$class.toString:(Lscala/Function1;)Ljava/lang/String;
const #84 = Asciz	Scala;
const #85 = Asciz	InnerClasses;
const #86 = Asciz	scala/Enumeration;
const #87 = class	#86;	//  scala/Enumeration
const #88 = Asciz	Value;
const #89 = Asciz	$anonfun$scala$Enumeration$$nameOf$1;
const #90 = Asciz	scala/Function1;
const #91 = class	#90;	//  scala/Function1
const #92 = Asciz	scala/ScalaObject;
const #93 = class	#92;	//  scala/ScalaObject
const #94 = Asciz	java/io/Serializable;
const #95 = class	#94;	//  java/io/Serializable

{
public static final long serialVersionUID;

public static {};
  Code:
   Stack=2, Locals=0, Args_size=0
   0:	lconst_0
   1:	putstatic	#11; //Field serialVersionUID:J
   4:	return

public scala.Enumeration$$anonfun$scala$Enumeration$$nameOf$1(scala.Enumeration);
  Code:
   Stack=1, Locals=2, Args_size=2
   0:	aload_0
   1:	invokespecial	#18; //Method java/lang/Object."<init>":()V
   4:	aload_0
   5:	invokestatic	#24; //Method scala/Function1$class.$init$:(Lscala/Function1;)V
   8:	return
  LineNumberTable: 
   line 171: 0

  LocalVariableTable: 
   Start  Length  Slot  Name   Signature
   0      9      0    this       Lscala/Enumeration$$anonfun$scala$Enumeration$$nameOf$1;
   0      9      1    $outer       Lscala/Enumeration;


public final java.lang.Object apply(java.lang.Object);
  Code:
   Stack=2, Locals=3, Args_size=2
   0:	aload_0
   1:	aload_1
   2:	checkcast	#33; //class java/lang/reflect/Method
   5:	invokevirtual	#36; //Method apply:(Ljava/lang/reflect/Method;)Z
   8:	istore_2
   9:	iload_2
   10:	invokestatic	#42; //Method scala/runtime/BoxesRunTime.boxToBoolean:(Z)Ljava/lang/Boolean;
   13:	areturn
  LineNumberTable: 
   line 171: 0

  LocalVariableTable: 
   Start  Length  Slot  Name   Signature
   0      14      0    this       Lscala/Enumeration$$anonfun$scala$Enumeration$$nameOf$1;
   0      14      1    v1       Ljava/lang/Object;


public final boolean apply(java.lang.reflect.Method);
  Code:
   Stack=2, Locals=2, Args_size=2
   0:	ldc	#46; //class scala/Enumeration$Value
   2:	aload_1
   3:	invokevirtual	#50; //Method java/lang/reflect/Method.getReturnType:()Ljava/lang/Class;
   6:	invokevirtual	#56; //Method java/lang/Class.isAssignableFrom:(Ljava/lang/Class;)Z
   9:	ifeq	26
   12:	aload_1
   13:	invokevirtual	#60; //Method java/lang/reflect/Method.getModifiers:()I
   16:	invokestatic	#66; //Method java/lang/reflect/Modifier.isFinal:(I)Z
   19:	ifne	26
   22:	iconst_1
   23:	goto	27
   26:	iconst_0
   27:	ireturn
  LineNumberTable: 
   line 172: 0
   line 173: 12
   line 172: 22

  LocalVariableTable: 
   Start  Length  Slot  Name   Signature
   0      28      0    this       Lscala/Enumeration$$anonfun$scala$Enumeration$$nameOf$1;
   0      28      1    m       Ljava/lang/reflect/Method;


public scala.Function1 andThen(scala.Function1);
  Code:
   Stack=2, Locals=2, Args_size=2
   0:	aload_0
   1:	aload_1
   2:	invokestatic	#73; //Method scala/Function1$class.andThen:(Lscala/Function1;Lscala/Function1;)Lscala/Function1;
   5:	areturn
  LineNumberTable: 
   line 171: 0

  LocalVariableTable: 
   Start  Length  Slot  Name   Signature
   0      6      0    this       Lscala/Enumeration$$anonfun$scala$Enumeration$$nameOf$1;
   0      6      1    g       Lscala/Function1;


public scala.Function1 compose(scala.Function1);
  Code:
   Stack=2, Locals=2, Args_size=2
   0:	aload_0
   1:	aload_1
   2:	invokestatic	#78; //Method scala/Function1$class.compose:(Lscala/Function1;Lscala/Function1;)Lscala/Function1;
   5:	areturn
  LineNumberTable: 
   line 171: 0

  LocalVariableTable: 
   Start  Length  Slot  Name   Signature
   0      6      0    this       Lscala/Enumeration$$anonfun$scala$Enumeration$$nameOf$1;
   0      6      1    g       Lscala/Function1;


public java.lang.String toString();
  Code:
   Stack=1, Locals=1, Args_size=1
   0:	aload_0
   1:	invokestatic	#83; //Method scala/Function1$class.toString:(Lscala/Function1;)Ljava/lang/String;
   4:	areturn
  LineNumberTable: 
   line 171: 0


}

