Compiled from "Enumeration.scala"
public final class scala.Enumeration$$anonfun$scala$Enumeration$$nameOf$2 extends java.lang.Object implements scala.Function1,scala.ScalaObject,java.io.Serializable
  SourceFile: "Enumeration.scala"
  Scala: length = 0x
   
  InnerClass: 
   public Val=class scala/Enumeration$Val of class scala/Enumeration
   public ArrowAssoc=class scala/Predef$ArrowAssoc of class scala/Predef
   public final $anonfun$scala$Enumeration$$nameOf$2=class scala/Enumeration$$anonfun$scala$Enumeration$$nameOf$2 of class scala/Enumeration
  minor version: 0
  major version: 49
  Constant pool:
Asciz	SourceFile;
Asciz	Enumeration.scala;
Asciz	<clinit>;
Asciz	()V;
Asciz	Code;
Asciz	serialVersionUID;
Asciz	J;
Asciz	scala/Enumeration$$anonfun$scala$Enumeration$$nameOf$2;
class	scala/Enumeration$$anonfun$scala$Enumeration$$nameOf$2
NameAndType	serialVersionUID:J
Field	scala/Enumeration$$anonfun$scala$Enumeration$$nameOf$2.serialVersionUID:J
Asciz	$outer;
Asciz	Lscala/Enumeration;;
Asciz	<init>;
Asciz	(Lscala/Enumeration;)V;
Asciz	LineNumberTable;
Asciz	java/lang/NullPointerException;
class	java/lang/NullPointerException
NameAndType	"<init>":()V
Method	java/lang/NullPointerException."<init>":()V
NameAndType	$outer:Lscala/Enumeration;
Field	scala/Enumeration$$anonfun$scala$Enumeration$$nameOf$2.$outer:Lscala/Enumeration;
Asciz	java/lang/Object;
class	java/lang/Object
Method	java/lang/Object."<init>":()V
Asciz	scala/Function1$class;
class	scala/Function1$class
Asciz	$init$;
Asciz	(Lscala/Function1;)V;
NameAndType	$init$:(Lscala/Function1;)V
Method	scala/Function1$class.$init$:(Lscala/Function1;)V
Asciz	this;
Asciz	Lscala/Enumeration$$anonfun$scala$Enumeration$$nameOf$2;;
Asciz	LocalVariableTable;
Asciz	apply;
Asciz	(Ljava/lang/Object;)Ljava/lang/Object;;
Asciz	java/lang/reflect/Method;
class	java/lang/reflect/Method
Asciz	(Ljava/lang/reflect/Method;)Lscala/collection/mutable/Map;;
NameAndType	apply:(Ljava/lang/reflect/Method;)Lscala/collection/mutable/Map;
Method	scala/Enumeration$$anonfun$scala$Enumeration$$nameOf$2.apply:(Ljava/lang/reflect/Method;)Lscala/collection/mutable/Map;
Asciz	v1;
Asciz	Ljava/lang/Object;;
Asciz	getName;
Asciz	()Ljava/lang/String;;
NameAndType	getName:()Ljava/lang/String;
Method	java/lang/reflect/Method.getName:()Ljava/lang/String;
Asciz	invoke;
Asciz	(Ljava/lang/Object;[Ljava/lang/Object;)Ljava/lang/Object;;
NameAndType	invoke:(Ljava/lang/Object;[Ljava/lang/Object;)Ljava/lang/Object;
Method	java/lang/reflect/Method.invoke:(Ljava/lang/Object;[Ljava/lang/Object;)Ljava/lang/Object;
Asciz	scala/Enumeration$Val;
class	scala/Enumeration$Val
Asciz	id;
String	id
Asciz	java/lang/Class;
class	java/lang/Class
Asciz	getMethod;
Asciz	(Ljava/lang/String;[Ljava/lang/Class;)Ljava/lang/reflect/Method;;
NameAndType	getMethod:(Ljava/lang/String;[Ljava/lang/Class;)Ljava/lang/reflect/Method;
Method	java/lang/Class.getMethod:(Ljava/lang/String;[Ljava/lang/Class;)Ljava/lang/reflect/Method;
Asciz	java/lang/Integer;
class	java/lang/Integer
Asciz	intValue;
Asciz	()I;
NameAndType	intValue:()I
Method	java/lang/Integer.intValue:()I
Asciz	scala/Enumeration;
class	scala/Enumeration
Asciz	scala$Enumeration$$nmap;
Asciz	()Lscala/collection/mutable/Map;;
NameAndType	scala$Enumeration$$nmap:()Lscala/collection/mutable/Map;
Method	scala/Enumeration.scala$Enumeration$$nmap:()Lscala/collection/mutable/Map;
Asciz	scala/Predef$;
class	scala/Predef$
Asciz	MODULE$;
Asciz	Lscala/Predef$;;
NameAndType	MODULE$:Lscala/Predef$;
Field	scala/Predef$.MODULE$:Lscala/Predef$;
Asciz	scala/runtime/BoxesRunTime;
class	scala/runtime/BoxesRunTime
Asciz	boxToInteger;
Asciz	(I)Ljava/lang/Integer;;
NameAndType	boxToInteger:(I)Ljava/lang/Integer;
Method	scala/runtime/BoxesRunTime.boxToInteger:(I)Ljava/lang/Integer;
Asciz	any2ArrowAssoc;
Asciz	(Ljava/lang/Object;)Lscala/Predef$ArrowAssoc;;
NameAndType	any2ArrowAssoc:(Ljava/lang/Object;)Lscala/Predef$ArrowAssoc;
Method	scala/Predef$.any2ArrowAssoc:(Ljava/lang/Object;)Lscala/Predef$ArrowAssoc;
Asciz	scala/Predef$ArrowAssoc;
class	scala/Predef$ArrowAssoc
Asciz	$minus$greater;
Asciz	(Ljava/lang/Object;)Lscala/Tuple2;;
NameAndType	$minus$greater:(Ljava/lang/Object;)Lscala/Tuple2;
Method	scala/Predef$ArrowAssoc.$minus$greater:(Ljava/lang/Object;)Lscala/Tuple2;
Asciz	scala/collection/mutable/MapLike;
class	scala/collection/mutable/MapLike
Asciz	$plus$eq;
Asciz	(Lscala/Tuple2;)Lscala/collection/mutable/MapLike;;
NameAndType	$plus$eq:(Lscala/Tuple2;)Lscala/collection/mutable/MapLike;
InterfaceMethod	scala/collection/mutable/MapLike.$plus$eq:(Lscala/Tuple2;)Lscala/collection/mutable/MapLike;
Asciz	scala/collection/mutable/Map;
class	scala/collection/mutable/Map
Asciz	m;
Asciz	Ljava/lang/reflect/Method;;
Asciz	idMeth;
Asciz	value;
Asciz	I;
Asciz	name;
Asciz	Ljava/lang/String;;
Asciz	(Ljava/lang/reflect/Method;)Lscala/collection/mutable/Map<Ljava/lang/Integer;Ljava/lang/String;>;;
Asciz	Signature;
Asciz	andThen;
Asciz	(Lscala/Function1;)Lscala/Function1;;
Asciz	(Lscala/Function1;Lscala/Function1;)Lscala/Function1;;
NameAndType	andThen:(Lscala/Function1;Lscala/Function1;)Lscala/Function1;
Method	scala/Function1$class.andThen:(Lscala/Function1;Lscala/Function1;)Lscala/Function1;
Asciz	g;
Asciz	Lscala/Function1;;
Asciz	compose;
NameAndType	compose:(Lscala/Function1;Lscala/Function1;)Lscala/Function1;
Method	scala/Function1$class.compose:(Lscala/Function1;Lscala/Function1;)Lscala/Function1;
Asciz	toString;
Asciz	(Lscala/Function1;)Ljava/lang/String;;
NameAndType	toString:(Lscala/Function1;)Ljava/lang/String;
Method	scala/Function1$class.toString:(Lscala/Function1;)Ljava/lang/String;
Asciz	Scala;
Asciz	InnerClasses;
Asciz	Val;
Asciz	scala/Predef;
class	scala/Predef
Asciz	ArrowAssoc;
Asciz	$anonfun$scala$Enumeration$$nameOf$2;
Asciz	scala/Function1;
class	scala/Function1
Asciz	scala/ScalaObject;
class	scala/ScalaObject
Asciz	java/io/Serializable;
class	java/io/Serializable

{
public static final long serialVersionUID;
  Signature: J

private final scala.Enumeration $outer;
  Signature: Lscala/Enumeration;

public static {};
  Signature: ()V
  Code:
   Stack=2, Locals=0, Args_size=0
	lconst_0
	putstatic	Field serialVersionUID:J
	return
  Labels:

public scala.Enumeration$$anonfun$scala$Enumeration$$nameOf$2(scala.Enumeration);
  Signature: (Lscala/Enumeration;)V
  Code:
   Stack=2, Locals=2, Args_size=2
	aload_1
	ifnonnull	l1 // aload_0
	new	class java/lang/NullPointerException
	dup
	invokespecial	Method java/lang/NullPointerException."<init>":()V
	athrow
l1	aload_0
	aload_1
	putfield	Field $outer:Lscala/Enumeration;
	aload_0
	invokespecial	Method java/lang/Object."<init>":()V
	aload_0
	invokestatic	Method scala/Function1$class.$init$:(Lscala/Function1;)V
	return
  Labels:
   	l1 = 12 // aload_0
  LocalVariableTable: 
   Start  Length  Slot  Name   Signature
   0      26      0    this       Lscala/Enumeration$$anonfun$scala$Enumeration$$nameOf$2;
   0      26      1    $outer       Lscala/Enumeration;


public final java.lang.Object apply(java.lang.Object);
  Signature: (Ljava/lang/Object;)Ljava/lang/Object;
  Code:
   Stack=2, Locals=3, Args_size=2
	aload_0
	getfield	Field $outer:Lscala/Enumeration;
	astore_2
	aload_0
	aload_1
	checkcast	class java/lang/reflect/Method
	invokevirtual	Method apply:(Ljava/lang/reflect/Method;)Lscala/collection/mutable/Map;
	areturn
  Labels:
  LocalVariableTable: 
   Start  Length  Slot  Name   Signature
   0      14      0    this       Lscala/Enumeration$$anonfun$scala$Enumeration$$nameOf$2;
   5      9      1    v1       Ljava/lang/Object;


public final scala.collection.mutable.Map apply(java.lang.reflect.Method);
  Signature: (Ljava/lang/reflect/Method;)Lscala/collection/mutable/Map;
  Code:
   Stack=3, Locals=7, Args_size=2
	aload_0
	getfield	Field $outer:Lscala/Enumeration;
	astore	6
	aload_1
	invokevirtual	Method java/lang/reflect/Method.getName:()Ljava/lang/String;
	astore	5
	aload_1
	aload_0
	getfield	Field $outer:Lscala/Enumeration;
	iconst_0
	anewarray	class java/lang/Object
	invokevirtual	Method java/lang/reflect/Method.invoke:(Ljava/lang/Object;[Ljava/lang/Object;)Ljava/lang/Object;
	astore_3
	ldc	class scala/Enumeration$Val
	ldc	String id
	iconst_0
	anewarray	class java/lang/Class
	invokevirtual	Method java/lang/Class.getMethod:(Ljava/lang/String;[Ljava/lang/Class;)Ljava/lang/reflect/Method;
	astore_2
	aload_2
	aload_3
	iconst_0
	anewarray	class java/lang/Object
	invokevirtual	Method java/lang/reflect/Method.invoke:(Ljava/lang/Object;[Ljava/lang/Object;)Ljava/lang/Object;
	checkcast	class java/lang/Integer
	invokevirtual	Method java/lang/Integer.intValue:()I
	istore	4
	aload_0
	getfield	Field $outer:Lscala/Enumeration;
	invokevirtual	Method scala/Enumeration.scala$Enumeration$$nmap:()Lscala/collection/mutable/Map;
	getstatic	Field scala/Predef$.MODULE$:Lscala/Predef$;
	iload	4
	invokestatic	Method scala/runtime/BoxesRunTime.boxToInteger:(I)Ljava/lang/Integer;
	invokevirtual	Method scala/Predef$.any2ArrowAssoc:(Ljava/lang/Object;)Lscala/Predef$ArrowAssoc;
	aload	5
	invokevirtual	Method scala/Predef$ArrowAssoc.$minus$greater:(Ljava/lang/Object;)Lscala/Tuple2;
	invokeinterface	InterfaceMethod scala/collection/mutable/MapLike.$plus$eq:(Lscala/Tuple2;)Lscala/collection/mutable/MapLike;
	checkcast	class scala/collection/mutable/Map
	areturn
  Labels:
  LocalVariableTable: 
   Start  Length  Slot  Name   Signature
   0      86      0    this       Lscala/Enumeration$$anonfun$scala$Enumeration$$nameOf$2;
   6      80      1    m       Ljava/lang/reflect/Method;
   37      48      2    idMeth       Ljava/lang/reflect/Method;
   25      60      3    value       Ljava/lang/Object;
   54      31      4    id       I
   12      73      5    name       Ljava/lang/String;

  Signature: length = 0x2
   00 6F 

public scala.Function1 andThen(scala.Function1);
  Signature: (Lscala/Function1;)Lscala/Function1;
  Code:
   Stack=2, Locals=2, Args_size=2
	aload_0
	aload_1
	invokestatic	Method scala/Function1$class.andThen:(Lscala/Function1;Lscala/Function1;)Lscala/Function1;
	areturn
  Labels:
  LocalVariableTable: 
   Start  Length  Slot  Name   Signature
   0      6      0    this       Lscala/Enumeration$$anonfun$scala$Enumeration$$nameOf$2;
   0      6      1    g       Lscala/Function1;


public scala.Function1 compose(scala.Function1);
  Signature: (Lscala/Function1;)Lscala/Function1;
  Code:
   Stack=2, Locals=2, Args_size=2
	aload_0
	aload_1
	invokestatic	Method scala/Function1$class.compose:(Lscala/Function1;Lscala/Function1;)Lscala/Function1;
	areturn
  Labels:
  LocalVariableTable: 
   Start  Length  Slot  Name   Signature
   0      6      0    this       Lscala/Enumeration$$anonfun$scala$Enumeration$$nameOf$2;
   0      6      1    g       Lscala/Function1;


public java.lang.String toString();
  Signature: ()Ljava/lang/String;
  Code:
   Stack=1, Locals=1, Args_size=1
	aload_0
	invokestatic	Method scala/Function1$class.toString:(Lscala/Function1;)Ljava/lang/String;
	areturn
  Labels:

}

