Compiled from "Array.scala"
public class scala.FallbackArrayBuilding extends java.lang.Object implements scala.ScalaObject
  SourceFile: "Array.scala"
  ScalaSig: length = 0x19F
   05 00 43 06 08 01 02 FFFFFF84 FFFFFF80 FFFFFF80 FFFFFF80 00 05 02 15 46
   61 6C 6C 62 61 63 6B 41 72 72 61 79 42 75 69 6C
   64 69 6E 67 0A 01 03 01 05 73 63 61 6C 61 03 00
   13 03 00 06 0E 10 02 07 0C 0D 01 08 0A 02 09 0A
   01 04 6C 61 6E 67 0A 01 0B 01 04 6A 61 76 61 09
   02 0D 08 02 06 4F 62 6A 65 63 74 10 02 0F 10 0D
   01 02 09 02 11 02 02 0B 53 63 61 6C 61 4F 62 6A
   65 63 74 08 05 13 00 FFFFFF84 00 14 01 06 3C 69 6E 69
   74 3E 14 01 15 10 02 0F 00 08 05 17 00 FFFFFF84 01 18
   01 14 66 61 6C 6C 62 61 63 6B 43 61 6E 42 75 69
   6C 64 46 72 6F 6D 15 02 19 32 16 02 1A 3A 10 05
   1B 20 22 31 34 0D 01 1C 0A 02 1D 1E 01 07 67 65
   6E 65 72 69 63 0A 02 1F 02 01 0A 63 6F 6C 6C 65
   63 74 69 6F 6E 09 02 21 1C 02 0C 43 61 6E 42 75
   69 6C 64 46 72 6F 6D 30 02 23 28 10 03 0F 24 26
   09 02 25 02 02 05 41 72 72 61 79 10 02 27 28 0C
   00 04 08 29 16 FFFFFF84 FFFFFF80 FFFFFF80 FFFFFF82 00 2A 02 03 5F 24 31
   11 02 2B 2E 10 02 0F 2C 09 02 2D 02 02 07 4E 6F
   74 68 69 6E 67 10 02 0F 2F 09 02 30 02 02 03 41
   6E 79 10 02 27 32 04 08 33 16 FFFFFF84 FFFFFF80 FFFFFF80 FFFFFFC2 00 2A
   02 01 54 10 03 35 38 31 0D 01 36 0A 02 37 1E 01
   07 6D 75 74 61 62 6C 65 09 02 39 36 02 0C 47 65
   6E 65 72 69 63 41 72 72 61 79 08 05 3B 16 FFFFFFC0 01
   3C 01 01 6D 10 02 3D 40 0E 02 0F 3E 09 02 3F 02
   01 06 50 72 65 64 65 66 09 02 41 42 02 0D 44 75
   6D 6D 79 49 6D 70 6C 69 63 69 74 0A 02 3F 02 
  InnerClass: 
   public #31= #28 of #30; //DummyImplicit=class scala/Predef$DummyImplicit of class scala/Predef
   public final #34= #14 of #33; //$anon$1=class scala/FallbackArrayBuilding$$anon$1 of class scala/FallbackArrayBuilding
  minor version: 0
  major version: 49
  Constant pool:
const #1 = Asciz	SourceFile;
const #2 = Asciz	Array.scala;
const #3 = Asciz	<init>;
const #4 = Asciz	()V;
const #5 = Asciz	Code;
const #6 = Asciz	LineNumberTable;
const #7 = Asciz	java/lang/Object;
const #8 = class	#7;	//  java/lang/Object
const #9 = NameAndType	#3:#4;//  "<init>":()V
const #10 = Method	#8.#9;	//  java/lang/Object."<init>":()V
const #11 = Asciz	fallbackCanBuildFrom;
const #12 = Asciz	(Lscala/Predef$DummyImplicit;)Lscala/collection/generic/CanBuildFrom;;
const #13 = Asciz	scala/FallbackArrayBuilding$$anon$1;
const #14 = class	#13;	//  scala/FallbackArrayBuilding$$anon$1
const #15 = Asciz	(Lscala/FallbackArrayBuilding;)V;
const #16 = NameAndType	#3:#15;//  "<init>":(Lscala/FallbackArrayBuilding;)V
const #17 = Method	#14.#16;	//  scala/FallbackArrayBuilding$$anon$1."<init>":(Lscala/FallbackArrayBuilding;)V
const #18 = Asciz	this;
const #19 = Asciz	Lscala/FallbackArrayBuilding;;
const #20 = Asciz	m;
const #21 = Asciz	Lscala/Predef$DummyImplicit;;
const #22 = Asciz	LocalVariableTable;
const #23 = Asciz	<T:Ljava/lang/Object;>(Lscala/Predef$DummyImplicit;)Lscala/collection/generic/CanBuildFrom<[Ljava/lang/Object;TT;Lscala/collection/mutable/GenericArray<TT;>;>;;
const #24 = Asciz	Signature;
const #25 = Asciz	ScalaSig;
const #26 = Asciz	InnerClasses;
const #27 = Asciz	scala/Predef$DummyImplicit;
const #28 = class	#27;	//  scala/Predef$DummyImplicit
const #29 = Asciz	scala/Predef;
const #30 = class	#29;	//  scala/Predef
const #31 = Asciz	DummyImplicit;
const #32 = Asciz	scala/FallbackArrayBuilding;
const #33 = class	#32;	//  scala/FallbackArrayBuilding
const #34 = Asciz	$anon$1;
const #35 = Asciz	scala/ScalaObject;
const #36 = class	#35;	//  scala/ScalaObject

{
public scala.FallbackArrayBuilding();
  Code:
   Stack=1, Locals=1, Args_size=1
   0:	aload_0
   1:	invokespecial	#10; //Method java/lang/Object."<init>":()V
   4:	return
  LineNumberTable: 
   line 23: 0


public scala.collection.generic.CanBuildFrom fallbackCanBuildFrom(scala.Predef$DummyImplicit);
  Code:
   Stack=3, Locals=2, Args_size=2
   0:	new	#14; //class scala/FallbackArrayBuilding$$anon$1
   3:	dup
   4:	aload_0
   5:	invokespecial	#17; //Method scala/FallbackArrayBuilding$$anon$1."<init>":(Lscala/FallbackArrayBuilding;)V
   8:	areturn
  LineNumberTable: 
   line 33: 0

  LocalVariableTable: 
   Start  Length  Slot  Name   Signature
   0      9      0    this       Lscala/FallbackArrayBuilding;
   0      9      1    m       Lscala/Predef$DummyImplicit;

  Signature: length = 0x2
   00 17 

}

