Compiled from "package.scala"
public final class scala.Font$ extends java.lang.Object implements scala.ScalaObject
  SourceFile: "package.scala"
  Scala: length = 0x
   
  minor version: 0
  major version: 49
  Constant pool:
const #1 = Asciz	SourceFile;
const #2 = Asciz	package.scala;
const #3 = Asciz	Scala;
const #4 = Asciz	MODULE$;
const #5 = Asciz	Lscala/Font$;;
const #6 = Asciz	<clinit>;
const #7 = Asciz	()V;
const #8 = Asciz	Code;
const #9 = Asciz	scala/Font$;
const #10 = class	#9;	//  scala/Font$
const #11 = Asciz	<init>;
const #12 = NameAndType	#11:#7;//  "<init>":()V
const #13 = Method	#10.#12;	//  scala/Font$."<init>":()V
const #14 = Asciz	LineNumberTable;
const #15 = Asciz	java/lang/Object;
const #16 = class	#15;	//  java/lang/Object
const #17 = Method	#16.#12;	//  java/lang/Object."<init>":()V
const #18 = NameAndType	#4:#5;//  MODULE$:Lscala/Font$;
const #19 = Field	#10.#18;	//  scala/Font$.MODULE$:Lscala/Font$;
const #20 = Asciz	Dimension;
const #21 = Asciz	(II)Ljava/awt/Dimension;;
const #22 = Asciz	java/awt/Dimension;
const #23 = class	#22;	//  java/awt/Dimension
const #24 = Asciz	(II)V;
const #25 = NameAndType	#11:#24;//  "<init>":(II)V
const #26 = Method	#23.#25;	//  java/awt/Dimension."<init>":(II)V
const #27 = Asciz	this;
const #28 = Asciz	x;
const #29 = Asciz	I;
const #30 = Asciz	y;
const #31 = Asciz	LocalVariableTable;
const #32 = Asciz	Point;
const #33 = Asciz	(II)Ljava/awt/Point;;
const #34 = Asciz	java/awt/Point;
const #35 = class	#34;	//  java/awt/Point
const #36 = Method	#35.#25;	//  java/awt/Point."<init>":(II)V
const #37 = Asciz	Rectangle;
const #38 = Asciz	(IIII)Ljava/awt/Insets;;
const #39 = Asciz	java/awt/Insets;
const #40 = class	#39;	//  java/awt/Insets
const #41 = Asciz	(IIII)V;
const #42 = NameAndType	#11:#41;//  "<init>":(IIII)V
const #43 = Method	#40.#42;	//  java/awt/Insets."<init>":(IIII)V
const #44 = Asciz	width;
const #45 = Asciz	height;
const #46 = Asciz	Insets;
const #47 = Asciz	get;
const #48 = Asciz	(Ljava/lang/String;Ljava/awt/Font;)Ljava/awt/Font;;
const #49 = Asciz	java/awt/Font;
const #50 = class	#49;	//  java/awt/Font
const #51 = Asciz	getFont;
const #52 = NameAndType	#51:#48;//  getFont:(Ljava/lang/String;Ljava/awt/Font;)Ljava/awt/Font;
const #53 = Method	#50.#52;	//  java/awt/Font.getFont:(Ljava/lang/String;Ljava/awt/Font;)Ljava/awt/Font;
const #54 = Asciz	nm;
const #55 = Asciz	Ljava/lang/String;;
const #56 = Asciz	font;
const #57 = Asciz	Ljava/awt/Font;;
const #58 = Asciz	(Ljava/lang/String;)Ljava/awt/Font;;
const #59 = NameAndType	#51:#58;//  getFont:(Ljava/lang/String;)Ljava/awt/Font;
const #60 = Method	#50.#59;	//  java/awt/Font.getFont:(Ljava/lang/String;)Ljava/awt/Font;
const #61 = Asciz	decode;
const #62 = NameAndType	#61:#58;//  decode:(Ljava/lang/String;)Ljava/awt/Font;
const #63 = Method	#50.#62;	//  java/awt/Font.decode:(Ljava/lang/String;)Ljava/awt/Font;
const #64 = Asciz	str;
const #65 = Asciz	apply;
const #66 = Asciz	(ILjava/io/InputStream;)Ljava/awt/Font;;
const #67 = Asciz	createFont;
const #68 = NameAndType	#67:#66;//  createFont:(ILjava/io/InputStream;)Ljava/awt/Font;
const #69 = Method	#50.#68;	//  java/awt/Font.createFont:(ILjava/io/InputStream;)Ljava/awt/Font;
const #70 = Asciz	fontFormat;
const #71 = Asciz	fontStream;
const #72 = Asciz	Ljava/io/InputStream;;
const #73 = Asciz	(ILjava/io/File;)Ljava/awt/Font;;
const #74 = NameAndType	#67:#73;//  createFont:(ILjava/io/File;)Ljava/awt/Font;
const #75 = Method	#50.#74;	//  java/awt/Font.createFont:(ILjava/io/File;)Ljava/awt/Font;
const #76 = Asciz	fontFile;
const #77 = Asciz	Ljava/io/File;;
const #78 = Asciz	scala/ScalaObject;
const #79 = class	#78;	//  scala/ScalaObject

{
public static final scala.Font$ MODULE$;

public static {};
  Code:
   Stack=1, Locals=0, Args_size=0
   0:	new	#10; //class scala/Font$
   3:	invokespecial	#13; //Method "<init>":()V
   6:	return

public java.awt.Dimension Dimension(int, int);
  Code:
   Stack=4, Locals=3, Args_size=3
   0:	new	#23; //class java/awt/Dimension
   3:	dup
   4:	iload_1
   5:	iload_2
   6:	invokespecial	#26; //Method java/awt/Dimension."<init>":(II)V
   9:	areturn
  LineNumberTable: 
   line 87: 0

  LocalVariableTable: 
   Start  Length  Slot  Name   Signature
   0      10      0    this       Lscala/Font$;
   0      10      1    x       I
   0      10      2    y       I


public java.awt.Point Point(int, int);
  Code:
   Stack=4, Locals=3, Args_size=3
   0:	new	#35; //class java/awt/Point
   3:	dup
   4:	iload_1
   5:	iload_2
   6:	invokespecial	#36; //Method java/awt/Point."<init>":(II)V
   9:	areturn
  LineNumberTable: 
   line 86: 0

  LocalVariableTable: 
   Start  Length  Slot  Name   Signature
   0      10      0    this       Lscala/Font$;
   0      10      1    x       I
   0      10      2    y       I


public java.awt.Insets Rectangle(int, int, int, int);
  Code:
   Stack=6, Locals=5, Args_size=5
   0:	new	#40; //class java/awt/Insets
   3:	dup
   4:	iload_1
   5:	iload_2
   6:	iload_3
   7:	iload	4
   9:	invokespecial	#43; //Method java/awt/Insets."<init>":(IIII)V
   12:	areturn
  LineNumberTable: 
   line 85: 0

  LocalVariableTable: 
   Start  Length  Slot  Name   Signature
   0      13      0    this       Lscala/Font$;
   0      13      1    x       I
   0      13      2    y       I
   0      13      3    width       I
   0      13      4    height       I


public java.awt.Insets Insets(int, int, int, int);
  Code:
   Stack=6, Locals=5, Args_size=5
   0:	new	#40; //class java/awt/Insets
   3:	dup
   4:	iload_1
   5:	iload_2
   6:	iload_3
   7:	iload	4
   9:	invokespecial	#43; //Method java/awt/Insets."<init>":(IIII)V
   12:	areturn
  LineNumberTable: 
   line 84: 0

  LocalVariableTable: 
   Start  Length  Slot  Name   Signature
   0      13      0    this       Lscala/Font$;
   0      13      1    x       I
   0      13      2    y       I
   0      13      3    width       I
   0      13      4    height       I


public java.awt.Font get(java.lang.String, java.awt.Font);
  Code:
   Stack=2, Locals=3, Args_size=3
   0:	aload_1
   1:	aload_2
   2:	invokestatic	#53; //Method java/awt/Font.getFont:(Ljava/lang/String;Ljava/awt/Font;)Ljava/awt/Font;
   5:	areturn
  LineNumberTable: 
   line 81: 0

  LocalVariableTable: 
   Start  Length  Slot  Name   Signature
   0      6      0    this       Lscala/Font$;
   0      6      1    nm       Ljava/lang/String;
   0      6      2    font       Ljava/awt/Font;


public java.awt.Font get(java.lang.String);
  Code:
   Stack=1, Locals=2, Args_size=2
   0:	aload_1
   1:	invokestatic	#60; //Method java/awt/Font.getFont:(Ljava/lang/String;)Ljava/awt/Font;
   4:	areturn
  LineNumberTable: 
   line 77: 0

  LocalVariableTable: 
   Start  Length  Slot  Name   Signature
   0      5      0    this       Lscala/Font$;
   0      5      1    nm       Ljava/lang/String;


public java.awt.Font decode(java.lang.String);
  Code:
   Stack=1, Locals=2, Args_size=2
   0:	aload_1
   1:	invokestatic	#63; //Method java/awt/Font.decode:(Ljava/lang/String;)Ljava/awt/Font;
   4:	areturn
  LineNumberTable: 
   line 23: 0

  LocalVariableTable: 
   Start  Length  Slot  Name   Signature
   0      5      0    this       Lscala/Font$;
   0      5      1    str       Ljava/lang/String;


public java.awt.Font apply(int, java.io.InputStream);
  Code:
   Stack=2, Locals=3, Args_size=3
   0:	iload_1
   1:	aload_2
   2:	invokestatic	#69; //Method java/awt/Font.createFont:(ILjava/io/InputStream;)Ljava/awt/Font;
   5:	areturn
  LineNumberTable: 
   line 22: 0

  LocalVariableTable: 
   Start  Length  Slot  Name   Signature
   0      6      0    this       Lscala/Font$;
   0      6      1    fontFormat       I
   0      6      2    fontStream       Ljava/io/InputStream;


public java.awt.Font apply(int, java.io.File);
  Code:
   Stack=2, Locals=3, Args_size=3
   0:	iload_1
   1:	aload_2
   2:	invokestatic	#75; //Method java/awt/Font.createFont:(ILjava/io/File;)Ljava/awt/Font;
   5:	areturn
  LineNumberTable: 
   line 21: 0

  LocalVariableTable: 
   Start  Length  Slot  Name   Signature
   0      6      0    this       Lscala/Font$;
   0      6      1    fontFormat       I
   0      6      2    fontFile       Ljava/io/File;


}

