Compiled from "package.scala"
public final class scala.Font$ extends java.lang.Object implements scala.ScalaObject
  SourceFile: "package.scala"
  Scala: length = 0x
   
  minor version: 0
  major version: 49
  Constant pool:
Asciz	SourceFile;
Asciz	package.scala;
Asciz	Scala;
Asciz	MODULE$;
Asciz	Lscala/Font$;;
Asciz	<clinit>;
Asciz	()V;
Asciz	Code;
Asciz	scala/Font$;
class	scala/Font$
Asciz	<init>;
NameAndType	"<init>":()V
Method	scala/Font$."<init>":()V
Asciz	apply;
Asciz	(ILjava/io/File;)Ljava/awt/Font;;
Asciz	LineNumberTable;
Asciz	java/awt/Font;
class	java/awt/Font
Asciz	createFont;
NameAndType	createFont:(ILjava/io/File;)Ljava/awt/Font;
Method	java/awt/Font.createFont:(ILjava/io/File;)Ljava/awt/Font;
Asciz	this;
Asciz	fontFormat;
Asciz	I;
Asciz	fontFile;
Asciz	Ljava/io/File;;
Asciz	LocalVariableTable;
Asciz	(ILjava/io/InputStream;)Ljava/awt/Font;;
NameAndType	createFont:(ILjava/io/InputStream;)Ljava/awt/Font;
Method	java/awt/Font.createFont:(ILjava/io/InputStream;)Ljava/awt/Font;
Asciz	fontStream;
Asciz	Ljava/io/InputStream;;
Asciz	decode;
Asciz	(Ljava/lang/String;)Ljava/awt/Font;;
NameAndType	decode:(Ljava/lang/String;)Ljava/awt/Font;
Method	java/awt/Font.decode:(Ljava/lang/String;)Ljava/awt/Font;
Asciz	str;
Asciz	Ljava/lang/String;;
Asciz	get;
Asciz	getFont;
NameAndType	getFont:(Ljava/lang/String;)Ljava/awt/Font;
Method	java/awt/Font.getFont:(Ljava/lang/String;)Ljava/awt/Font;
Asciz	nm;
Asciz	(Ljava/lang/String;Ljava/awt/Font;)Ljava/awt/Font;;
NameAndType	getFont:(Ljava/lang/String;Ljava/awt/Font;)Ljava/awt/Font;
Method	java/awt/Font.getFont:(Ljava/lang/String;Ljava/awt/Font;)Ljava/awt/Font;
Asciz	font;
Asciz	Ljava/awt/Font;;
Asciz	Insets;
Asciz	(IIII)Ljava/awt/Insets;;
Asciz	java/awt/Insets;
class	java/awt/Insets
Asciz	(IIII)V;
NameAndType	"<init>":(IIII)V
Method	java/awt/Insets."<init>":(IIII)V
Asciz	x;
Asciz	y;
Asciz	width;
Asciz	height;
Asciz	Rectangle;
Asciz	Point;
Asciz	(II)Ljava/awt/Point;;
Asciz	java/awt/Point;
class	java/awt/Point
Asciz	(II)V;
NameAndType	"<init>":(II)V
Method	java/awt/Point."<init>":(II)V
Asciz	Dimension;
Asciz	(II)Ljava/awt/Dimension;;
Asciz	java/awt/Dimension;
class	java/awt/Dimension
Method	java/awt/Dimension."<init>":(II)V
Asciz	java/lang/Object;
class	java/lang/Object
Method	java/lang/Object."<init>":()V
NameAndType	MODULE$:Lscala/Font$;
Field	scala/Font$.MODULE$:Lscala/Font$;
Asciz	scala/ScalaObject;
class	scala/ScalaObject

{
public static final scala.Font$ MODULE$;
  Signature: Lscala/Font$;

public static {};
  Signature: ()V
  Code:
   Stack=1, Locals=0, Args_size=0
	new	class scala/Font$
	invokespecial	Method "<init>":()V
	return
  Labels:

public java.awt.Font apply(int, java.io.File);
  Signature: (ILjava/io/File;)Ljava/awt/Font;
  Code:
   Stack=2, Locals=3, Args_size=3
	iload_1
	aload_2
	invokestatic	Method java/awt/Font.createFont:(ILjava/io/File;)Ljava/awt/Font;
	areturn
  Labels:
  LocalVariableTable: 
   Start  Length  Slot  Name   Signature
   0      6      0    this       Lscala/Font$;
   0      6      1    fontFormat       I
   0      6      2    fontFile       Ljava/io/File;


public java.awt.Font apply(int, java.io.InputStream);
  Signature: (ILjava/io/InputStream;)Ljava/awt/Font;
  Code:
   Stack=2, Locals=3, Args_size=3
	iload_1
	aload_2
	invokestatic	Method java/awt/Font.createFont:(ILjava/io/InputStream;)Ljava/awt/Font;
	areturn
  Labels:
  LocalVariableTable: 
   Start  Length  Slot  Name   Signature
   0      6      0    this       Lscala/Font$;
   0      6      1    fontFormat       I
   0      6      2    fontStream       Ljava/io/InputStream;


public java.awt.Font decode(java.lang.String);
  Signature: (Ljava/lang/String;)Ljava/awt/Font;
  Code:
   Stack=1, Locals=2, Args_size=2
	aload_1
	invokestatic	Method java/awt/Font.decode:(Ljava/lang/String;)Ljava/awt/Font;
	areturn
  Labels:
  LocalVariableTable: 
   Start  Length  Slot  Name   Signature
   0      5      0    this       Lscala/Font$;
   0      5      1    str       Ljava/lang/String;


public java.awt.Font get(java.lang.String);
  Signature: (Ljava/lang/String;)Ljava/awt/Font;
  Code:
   Stack=1, Locals=2, Args_size=2
	aload_1
	invokestatic	Method java/awt/Font.getFont:(Ljava/lang/String;)Ljava/awt/Font;
	areturn
  Labels:
  LocalVariableTable: 
   Start  Length  Slot  Name   Signature
   0      5      0    this       Lscala/Font$;
   0      5      1    nm       Ljava/lang/String;


public java.awt.Font get(java.lang.String, java.awt.Font);
  Signature: (Ljava/lang/String;Ljava/awt/Font;)Ljava/awt/Font;
  Code:
   Stack=2, Locals=3, Args_size=3
	aload_1
	aload_2
	invokestatic	Method java/awt/Font.getFont:(Ljava/lang/String;Ljava/awt/Font;)Ljava/awt/Font;
	areturn
  Labels:
  LocalVariableTable: 
   Start  Length  Slot  Name   Signature
   0      6      0    this       Lscala/Font$;
   0      6      1    nm       Ljava/lang/String;
   0      6      2    font       Ljava/awt/Font;


public java.awt.Insets Insets(int, int, int, int);
  Signature: (IIII)Ljava/awt/Insets;
  Code:
   Stack=6, Locals=5, Args_size=5
	new	class java/awt/Insets
	dup
	iload_1
	iload_2
	iload_3
	iload	4
	invokespecial	Method java/awt/Insets."<init>":(IIII)V
	areturn
  Labels:
  LocalVariableTable: 
   Start  Length  Slot  Name   Signature
   0      13      0    this       Lscala/Font$;
   0      13      1    x       I
   0      13      2    y       I
   0      13      3    width       I
   0      13      4    height       I


public java.awt.Insets Rectangle(int, int, int, int);
  Signature: (IIII)Ljava/awt/Insets;
  Code:
   Stack=6, Locals=5, Args_size=5
	new	class java/awt/Insets
	dup
	iload_1
	iload_2
	iload_3
	iload	4
	invokespecial	Method java/awt/Insets."<init>":(IIII)V
	areturn
  Labels:
  LocalVariableTable: 
   Start  Length  Slot  Name   Signature
   0      13      0    this       Lscala/Font$;
   0      13      1    x       I
   0      13      2    y       I
   0      13      3    width       I
   0      13      4    height       I


public java.awt.Point Point(int, int);
  Signature: (II)Ljava/awt/Point;
  Code:
   Stack=4, Locals=3, Args_size=3
	new	class java/awt/Point
	dup
	iload_1
	iload_2
	invokespecial	Method java/awt/Point."<init>":(II)V
	areturn
  Labels:
  LocalVariableTable: 
   Start  Length  Slot  Name   Signature
   0      10      0    this       Lscala/Font$;
   0      10      1    x       I
   0      10      2    y       I


public java.awt.Dimension Dimension(int, int);
  Signature: (II)Ljava/awt/Dimension;
  Code:
   Stack=4, Locals=3, Args_size=3
	new	class java/awt/Dimension
	dup
	iload_1
	iload_2
	invokespecial	Method java/awt/Dimension."<init>":(II)V
	areturn
  Labels:
  LocalVariableTable: 
   Start  Length  Slot  Name   Signature
   0      10      0    this       Lscala/Font$;
   0      10      1    x       I
   0      10      2    y       I


private scala.Font$();
  Signature: ()V
  Code:
   Stack=1, Locals=1, Args_size=1
	aload_0
	invokespecial	Method java/lang/Object."<init>":()V
	aload_0
	putstatic	Field MODULE$:Lscala/Font$;
	return
  Labels:

}

