Compiled from "Function1.scala"
public abstract class scala.Function1$mcID$sp$class extends java.lang.Object
  SourceFile: "Function1.scala"
  Scala: length = 0x
   
  InnerClass: 
   public final $anonfun$andThen$mcID$sp$1=class scala/Function1$mcID$sp$$anonfun$andThen$mcID$sp$1 of class scala/Function1$mcID$sp
   public final $anonfun$compose$mcID$sp$1=class scala/Function1$mcID$sp$$anonfun$compose$mcID$sp$1 of class scala/Function1$mcID$sp
  minor version: 0
  major version: 49
  Constant pool:
Asciz	SourceFile;
Asciz	Function1.scala;
Asciz	apply;
Asciz	(Lscala/Function1$mcID$sp;D)I;
Asciz	Code;
Asciz	LineNumberTable;
Asciz	scala/Function1;
class	scala/Function1
Asciz	apply$mcID$sp;
Asciz	(D)I;
NameAndType	apply$mcID$sp:(D)I
InterfaceMethod	scala/Function1.apply$mcID$sp:(D)I
Asciz	$this;
Asciz	Lscala/Function1$mcID$sp;;
Asciz	v1;
Asciz	D;
Asciz	LocalVariableTable;
Asciz	compose;
Asciz	(Lscala/Function1$mcID$sp;Lscala/Function1;)Lscala/Function1;;
Asciz	scala/Function1$mcID$sp;
class	scala/Function1$mcID$sp
Asciz	compose$mcID$sp;
Asciz	(Lscala/Function1;)Lscala/Function1;;
NameAndType	compose$mcID$sp:(Lscala/Function1;)Lscala/Function1;
InterfaceMethod	scala/Function1$mcID$sp.compose$mcID$sp:(Lscala/Function1;)Lscala/Function1;
Asciz	g;
Asciz	Lscala/Function1;;
Asciz	scala/Function1$mcID$sp$$anonfun$compose$mcID$sp$1;
class	scala/Function1$mcID$sp$$anonfun$compose$mcID$sp$1
Asciz	<init>;
Asciz	(Lscala/Function1$mcID$sp;Lscala/Function1;)V;
NameAndType	"<init>":(Lscala/Function1$mcID$sp;Lscala/Function1;)V
Method	scala/Function1$mcID$sp$$anonfun$compose$mcID$sp$1."<init>":(Lscala/Function1$mcID$sp;Lscala/Function1;)V
Asciz	g$27;
Asciz	andThen;
Asciz	andThen$mcID$sp;
NameAndType	andThen$mcID$sp:(Lscala/Function1;)Lscala/Function1;
InterfaceMethod	scala/Function1$mcID$sp.andThen$mcID$sp:(Lscala/Function1;)Lscala/Function1;
Asciz	scala/Function1$mcID$sp$$anonfun$andThen$mcID$sp$1;
class	scala/Function1$mcID$sp$$anonfun$andThen$mcID$sp$1
Method	scala/Function1$mcID$sp$$anonfun$andThen$mcID$sp$1."<init>":(Lscala/Function1$mcID$sp;Lscala/Function1;)V
Asciz	g$28;
Asciz	$init$;
Asciz	(Lscala/Function1$mcID$sp;)V;
Asciz	Scala;
Asciz	InnerClasses;
Asciz	$anonfun$andThen$mcID$sp$1;
Asciz	$anonfun$compose$mcID$sp$1;
Asciz	scala/Function1$mcID$sp$class;
class	scala/Function1$mcID$sp$class
Asciz	java/lang/Object;
class	java/lang/Object

{
public static int apply(scala.Function1$mcID$sp, double);
  Signature: (Lscala/Function1$mcID$sp;D)I
  Code:
   Stack=3, Locals=3, Args_size=2
	aload_0
	dload_1
	invokeinterface	InterfaceMethod scala/Function1.apply$mcID$sp:(D)I
	ireturn
  Labels:
  LocalVariableTable: 
   Start  Length  Slot  Name   Signature
   0      8      0    $this       Lscala/Function1$mcID$sp;
   0      8      1    v1       D


public static scala.Function1 compose(scala.Function1$mcID$sp, scala.Function1);
  Signature: (Lscala/Function1$mcID$sp;Lscala/Function1;)Lscala/Function1;
  Code:
   Stack=2, Locals=2, Args_size=2
	aload_0
	aload_1
	invokeinterface	InterfaceMethod scala/Function1$mcID$sp.compose$mcID$sp:(Lscala/Function1;)Lscala/Function1;
	areturn
  Labels:
  LocalVariableTable: 
   Start  Length  Slot  Name   Signature
   0      8      0    $this       Lscala/Function1$mcID$sp;
   0      8      1    g       Lscala/Function1;


public static scala.Function1 compose$mcID$sp(scala.Function1$mcID$sp, scala.Function1);
  Signature: (Lscala/Function1$mcID$sp;Lscala/Function1;)Lscala/Function1;
  Code:
   Stack=4, Locals=2, Args_size=2
	new	class scala/Function1$mcID$sp$$anonfun$compose$mcID$sp$1
	dup
	aload_0
	aload_1
	invokespecial	Method scala/Function1$mcID$sp$$anonfun$compose$mcID$sp$1."<init>":(Lscala/Function1$mcID$sp;Lscala/Function1;)V
	areturn
  Labels:
  LocalVariableTable: 
   Start  Length  Slot  Name   Signature
   0      10      0    $this       Lscala/Function1$mcID$sp;
   0      10      1    g$27       Lscala/Function1;


public static scala.Function1 andThen(scala.Function1$mcID$sp, scala.Function1);
  Signature: (Lscala/Function1$mcID$sp;Lscala/Function1;)Lscala/Function1;
  Code:
   Stack=2, Locals=2, Args_size=2
	aload_0
	aload_1
	invokeinterface	InterfaceMethod scala/Function1$mcID$sp.andThen$mcID$sp:(Lscala/Function1;)Lscala/Function1;
	areturn
  Labels:
  LocalVariableTable: 
   Start  Length  Slot  Name   Signature
   0      8      0    $this       Lscala/Function1$mcID$sp;
   0      8      1    g       Lscala/Function1;


public static scala.Function1 andThen$mcID$sp(scala.Function1$mcID$sp, scala.Function1);
  Signature: (Lscala/Function1$mcID$sp;Lscala/Function1;)Lscala/Function1;
  Code:
   Stack=4, Locals=2, Args_size=2
	new	class scala/Function1$mcID$sp$$anonfun$andThen$mcID$sp$1
	dup
	aload_0
	aload_1
	invokespecial	Method scala/Function1$mcID$sp$$anonfun$andThen$mcID$sp$1."<init>":(Lscala/Function1$mcID$sp;Lscala/Function1;)V
	areturn
  Labels:
  LocalVariableTable: 
   Start  Length  Slot  Name   Signature
   0      10      0    $this       Lscala/Function1$mcID$sp;
   0      10      1    g$28       Lscala/Function1;


public static void $init$(scala.Function1$mcID$sp);
  Signature: (Lscala/Function1$mcID$sp;)V
  Code:
   Stack=0, Locals=1, Args_size=1
	return
  Labels:
  LocalVariableTable: 
   Start  Length  Slot  Name   Signature
   0      1      0    $this       Lscala/Function1$mcID$sp;


}

