Compiled from "Function22.scala"
public final class scala.Function22$$anonfun$tuple$1 extends scala.runtime.AbstractFunction1 implements java.io.Serializable
  SourceFile: "Function22.scala"
  Scala: length = 0x
   
  InnerClass: 
   public final $anonfun$tuple$1=class scala/Function22$$anonfun$tuple$1 of class scala/Function22
  minor version: 0
  major version: 49
  Constant pool:
Asciz	SourceFile;
Asciz	Function22.scala;
Asciz	<clinit>;
Asciz	()V;
Asciz	Code;
Asciz	serialVersionUID;
Asciz	J;
Asciz	scala/Function22$$anonfun$tuple$1;
class	scala/Function22$$anonfun$tuple$1
NameAndType	serialVersionUID:J
Field	scala/Function22$$anonfun$tuple$1.serialVersionUID:J
Asciz	$outer;
Asciz	Lscala/Function22;;
Asciz	<init>;
Asciz	(Lscala/Function22;)V;
Asciz	LineNumberTable;
Asciz	java/lang/NullPointerException;
class	java/lang/NullPointerException
NameAndType	"<init>":()V
Method	java/lang/NullPointerException."<init>":()V
NameAndType	$outer:Lscala/Function22;
Field	scala/Function22$$anonfun$tuple$1.$outer:Lscala/Function22;
Asciz	scala/runtime/AbstractFunction1;
class	scala/runtime/AbstractFunction1
Method	scala/runtime/AbstractFunction1."<init>":()V
Asciz	this;
Asciz	Lscala/Function22$$anonfun$tuple$1;;
Asciz	LocalVariableTable;
Asciz	(Lscala/Function22<TT1;TT2;TT3;TT4;TT5;TT6;TT7;TT8;TT9;TT10;TT11;TT12;TT13;TT14;TT15;TT16;TT17;TT18;TT19;TT20;TT21;TT22;TR;>;)V;
Asciz	Signature;
Asciz	apply;
Asciz	(Ljava/lang/Object;)Ljava/lang/Object;;
Asciz	scala/Tuple22;
class	scala/Tuple22
Asciz	(Lscala/Tuple22;)Ljava/lang/Object;;
NameAndType	apply:(Lscala/Tuple22;)Ljava/lang/Object;
Method	scala/Function22$$anonfun$tuple$1.apply:(Lscala/Tuple22;)Ljava/lang/Object;
Asciz	v1;
Asciz	Ljava/lang/Object;;
Asciz	_1;
Asciz	()Ljava/lang/Object;;
NameAndType	_1:()Ljava/lang/Object;
Method	scala/Tuple22._1:()Ljava/lang/Object;
Asciz	_2;
NameAndType	_2:()Ljava/lang/Object;
Method	scala/Tuple22._2:()Ljava/lang/Object;
Asciz	_3;
NameAndType	_3:()Ljava/lang/Object;
Method	scala/Tuple22._3:()Ljava/lang/Object;
Asciz	_4;
NameAndType	_4:()Ljava/lang/Object;
Method	scala/Tuple22._4:()Ljava/lang/Object;
Asciz	_5;
NameAndType	_5:()Ljava/lang/Object;
Method	scala/Tuple22._5:()Ljava/lang/Object;
Asciz	_6;
NameAndType	_6:()Ljava/lang/Object;
Method	scala/Tuple22._6:()Ljava/lang/Object;
Asciz	_7;
NameAndType	_7:()Ljava/lang/Object;
Method	scala/Tuple22._7:()Ljava/lang/Object;
Asciz	_8;
NameAndType	_8:()Ljava/lang/Object;
Method	scala/Tuple22._8:()Ljava/lang/Object;
Asciz	_9;
NameAndType	_9:()Ljava/lang/Object;
Method	scala/Tuple22._9:()Ljava/lang/Object;
Asciz	_10;
NameAndType	_10:()Ljava/lang/Object;
Method	scala/Tuple22._10:()Ljava/lang/Object;
Asciz	_11;
NameAndType	_11:()Ljava/lang/Object;
Method	scala/Tuple22._11:()Ljava/lang/Object;
Asciz	_12;
NameAndType	_12:()Ljava/lang/Object;
Method	scala/Tuple22._12:()Ljava/lang/Object;
Asciz	_13;
NameAndType	_13:()Ljava/lang/Object;
Method	scala/Tuple22._13:()Ljava/lang/Object;
Asciz	_14;
NameAndType	_14:()Ljava/lang/Object;
Method	scala/Tuple22._14:()Ljava/lang/Object;
Asciz	_15;
NameAndType	_15:()Ljava/lang/Object;
Method	scala/Tuple22._15:()Ljava/lang/Object;
Asciz	_16;
NameAndType	_16:()Ljava/lang/Object;
Method	scala/Tuple22._16:()Ljava/lang/Object;
Asciz	_17;
NameAndType	_17:()Ljava/lang/Object;
Method	scala/Tuple22._17:()Ljava/lang/Object;
Asciz	_18;
NameAndType	_18:()Ljava/lang/Object;
Method	scala/Tuple22._18:()Ljava/lang/Object;
Asciz	_19;
NameAndType	_19:()Ljava/lang/Object;
Method	scala/Tuple22._19:()Ljava/lang/Object;
Asciz	_20;
NameAndType	_20:()Ljava/lang/Object;
Method	scala/Tuple22._20:()Ljava/lang/Object;
Asciz	_21;
NameAndType	_21:()Ljava/lang/Object;
Method	scala/Tuple22._21:()Ljava/lang/Object;
Asciz	_22;
NameAndType	_22:()Ljava/lang/Object;
Method	scala/Tuple22._22:()Ljava/lang/Object;
Asciz	scala/Function22;
class	scala/Function22
Asciz	(Ljava/lang/Object;Ljava/lang/Object;Ljava/lang/Object;Ljava/lang/Object;Ljava/lang/Object;Ljava/lang/Object;Ljava/lang/Object;Ljava/lang/Object;Ljava/lang/Object;Ljava/lang/Object;Ljava/lang/Object;Ljava/lang/Object;Ljava/lang/Object;Ljava/lang/Object;Ljava/lang/Object;Ljava/lang/Object;Ljava/lang/Object;Ljava/lang/Object;Ljava/lang/Object;Ljava/lang/Object;Ljava/lang/Object;Ljava/lang/Object;)Ljava/lang/Object;;
NameAndType	apply:(Ljava/lang/Object;Ljava/lang/Object;Ljava/lang/Object;Ljava/lang/Object;Ljava/lang/Object;Ljava/lang/Object;Ljava/lang/Object;Ljava/lang/Object;Ljava/lang/Object;Ljava/lang/Object;Ljava/lang/Object;Ljava/lang/Object;Ljava/lang/Object;Ljava/lang/Object;Ljava/lang/Object;Ljava/lang/Object;Ljava/lang/Object;Ljava/lang/Object;Ljava/lang/Object;Ljava/lang/Object;Ljava/lang/Object;Ljava/lang/Object;)Ljava/lang/Object;
InterfaceMethod	scala/Function22.apply:(Ljava/lang/Object;Ljava/lang/Object;Ljava/lang/Object;Ljava/lang/Object;Ljava/lang/Object;Ljava/lang/Object;Ljava/lang/Object;Ljava/lang/Object;Ljava/lang/Object;Ljava/lang/Object;Ljava/lang/Object;Ljava/lang/Object;Ljava/lang/Object;Ljava/lang/Object;Ljava/lang/Object;Ljava/lang/Object;Ljava/lang/Object;Ljava/lang/Object;Ljava/lang/Object;Ljava/lang/Object;Ljava/lang/Object;Ljava/lang/Object;)Ljava/lang/Object;
Asciz	scala/MatchError;
class	scala/MatchError
Asciz	toString;
Asciz	()Ljava/lang/String;;
NameAndType	toString:()Ljava/lang/String;
Method	scala/Tuple22.toString:()Ljava/lang/String;
Asciz	(Ljava/lang/String;)V;
NameAndType	"<init>":(Ljava/lang/String;)V
Method	scala/MatchError."<init>":(Ljava/lang/String;)V
Asciz	temp2;
Asciz	temp3;
Asciz	temp4;
Asciz	temp5;
Asciz	temp6;
Asciz	temp7;
Asciz	temp8;
Asciz	temp9;
Asciz	temp10;
Asciz	temp11;
Asciz	temp12;
Asciz	temp13;
Asciz	temp14;
Asciz	temp15;
Asciz	temp16;
Asciz	temp17;
Asciz	temp18;
Asciz	temp19;
Asciz	temp20;
Asciz	temp21;
Asciz	temp22;
Asciz	temp23;
Asciz	(Lscala/Tuple22<TT1;TT2;TT3;TT4;TT5;TT6;TT7;TT8;TT9;TT10;TT11;TT12;TT13;TT14;TT15;TT16;TT17;TT18;TT19;TT20;TT21;TT22;>;)TR;;
Asciz	Scala;
Asciz	InnerClasses;
Asciz	$anonfun$tuple$1;
Asciz	java/io/Serializable;
class	java/io/Serializable

{
public static final long serialVersionUID;
  Signature: J

public final scala.Function22 $outer;
  Signature: Lscala/Function22;

public static {};
  Signature: ()V
  Code:
   Stack=2, Locals=0, Args_size=0
	lconst_0
	putstatic	Field serialVersionUID:J
	return
  Labels:

public scala.Function22$$anonfun$tuple$1(scala.Function22);
  Signature: (Lscala/Function22;)V
  Code:
   Stack=2, Locals=2, Args_size=2
	aload_1
	ifnonnull	l1 // aload_0
	new	class java/lang/NullPointerException
	dup
	invokespecial	Method java/lang/NullPointerException."<init>":()V
	athrow
l1	aload_0
	aload_1
	putfield	Field $outer:Lscala/Function22;
	aload_0
	invokespecial	Method scala/runtime/AbstractFunction1."<init>":()V
	return
  Labels:
   	l1 = 12 // aload_0
  LocalVariableTable: 
   Start  Length  Slot  Name   Signature
   0      22      0    this       Lscala/Function22$$anonfun$tuple$1;
   0      22      1    $outer       Lscala/Function22;

  Signature: length = 0x2
   00 1D 

public final java.lang.Object apply(java.lang.Object);
  Signature: (Ljava/lang/Object;)Ljava/lang/Object;
  Code:
   Stack=2, Locals=2, Args_size=2
	aload_0
	aload_1
	checkcast	class scala/Tuple22
	invokevirtual	Method apply:(Lscala/Tuple22;)Ljava/lang/Object;
	areturn
  Labels:
  LocalVariableTable: 
   Start  Length  Slot  Name   Signature
   0      9      0    this       Lscala/Function22$$anonfun$tuple$1;
   0      9      1    v1       Ljava/lang/Object;


public final java.lang.Object apply(scala.Tuple22);
  Signature: (Lscala/Tuple22;)Ljava/lang/Object;
  Code:
   Stack=23, Locals=24, Args_size=2
	aload_1
	ifnull	l1 // new
	aload_1
	invokevirtual	Method scala/Tuple22._1:()Ljava/lang/Object;
	astore_2
	aload_1
	invokevirtual	Method scala/Tuple22._2:()Ljava/lang/Object;
	astore_3
	aload_1
	invokevirtual	Method scala/Tuple22._3:()Ljava/lang/Object;
	astore	4
	aload_1
	invokevirtual	Method scala/Tuple22._4:()Ljava/lang/Object;
	astore	5
	aload_1
	invokevirtual	Method scala/Tuple22._5:()Ljava/lang/Object;
	astore	6
	aload_1
	invokevirtual	Method scala/Tuple22._6:()Ljava/lang/Object;
	astore	7
	aload_1
	invokevirtual	Method scala/Tuple22._7:()Ljava/lang/Object;
	astore	8
	aload_1
	invokevirtual	Method scala/Tuple22._8:()Ljava/lang/Object;
	astore	9
	aload_1
	invokevirtual	Method scala/Tuple22._9:()Ljava/lang/Object;
	astore	10
	aload_1
	invokevirtual	Method scala/Tuple22._10:()Ljava/lang/Object;
	astore	11
	aload_1
	invokevirtual	Method scala/Tuple22._11:()Ljava/lang/Object;
	astore	12
	aload_1
	invokevirtual	Method scala/Tuple22._12:()Ljava/lang/Object;
	astore	13
	aload_1
	invokevirtual	Method scala/Tuple22._13:()Ljava/lang/Object;
	astore	14
	aload_1
	invokevirtual	Method scala/Tuple22._14:()Ljava/lang/Object;
	astore	15
	aload_1
	invokevirtual	Method scala/Tuple22._15:()Ljava/lang/Object;
	astore	16
	aload_1
	invokevirtual	Method scala/Tuple22._16:()Ljava/lang/Object;
	astore	17
	aload_1
	invokevirtual	Method scala/Tuple22._17:()Ljava/lang/Object;
	astore	18
	aload_1
	invokevirtual	Method scala/Tuple22._18:()Ljava/lang/Object;
	astore	19
	aload_1
	invokevirtual	Method scala/Tuple22._19:()Ljava/lang/Object;
	astore	20
	aload_1
	invokevirtual	Method scala/Tuple22._20:()Ljava/lang/Object;
	astore	21
	aload_1
	invokevirtual	Method scala/Tuple22._21:()Ljava/lang/Object;
	astore	22
	aload_1
	invokevirtual	Method scala/Tuple22._22:()Ljava/lang/Object;
	astore	23
	aload_0
	getfield	Field $outer:Lscala/Function22;
	aload_2
	aload_3
	aload	4
	aload	5
	aload	6
	aload	7
	aload	8
	aload	9
	aload	10
	aload	11
	aload	12
	aload	13
	aload	14
	aload	15
	aload	16
	aload	17
	aload	18
	aload	19
	aload	20
	aload	21
	aload	22
	aload	23
	invokeinterface	InterfaceMethod scala/Function22.apply:(Ljava/lang/Object;Ljava/lang/Object;Ljava/lang/Object;Ljava/lang/Object;Ljava/lang/Object;Ljava/lang/Object;Ljava/lang/Object;Ljava/lang/Object;Ljava/lang/Object;Ljava/lang/Object;Ljava/lang/Object;Ljava/lang/Object;Ljava/lang/Object;Ljava/lang/Object;Ljava/lang/Object;Ljava/lang/Object;Ljava/lang/Object;Ljava/lang/Object;Ljava/lang/Object;Ljava/lang/Object;Ljava/lang/Object;Ljava/lang/Object;)Ljava/lang/Object;
	areturn
l1	new	class scala/MatchError
	dup
	aload_1
	invokevirtual	Method scala/Tuple22.toString:()Ljava/lang/String;
	invokespecial	Method scala/MatchError."<init>":(Ljava/lang/String;)V
	athrow
  Labels:
   	l1 = 186 // new
  LocalVariableTable: 
   Start  Length  Slot  Name   Signature
   0      198      0    this       Lscala/Function22$$anonfun$tuple$1;
   9      176      2    temp2       Ljava/lang/Object;
   14      171      3    temp3       Ljava/lang/Object;
   20      165      4    temp4       Ljava/lang/Object;
   26      159      5    temp5       Ljava/lang/Object;
   32      153      6    temp6       Ljava/lang/Object;
   38      147      7    temp7       Ljava/lang/Object;
   44      141      8    temp8       Ljava/lang/Object;
   50      135      9    temp9       Ljava/lang/Object;
   56      129      10    temp10       Ljava/lang/Object;
   62      123      11    temp11       Ljava/lang/Object;
   68      117      12    temp12       Ljava/lang/Object;
   74      111      13    temp13       Ljava/lang/Object;
   80      105      14    temp14       Ljava/lang/Object;
   86      99      15    temp15       Ljava/lang/Object;
   92      93      16    temp16       Ljava/lang/Object;
   98      87      17    temp17       Ljava/lang/Object;
   104      81      18    temp18       Ljava/lang/Object;
   110      75      19    temp19       Ljava/lang/Object;
   116      69      20    temp20       Ljava/lang/Object;
   122      63      21    temp21       Ljava/lang/Object;
   128      57      22    temp22       Ljava/lang/Object;
   134      51      23    temp23       Ljava/lang/Object;

  Signature: length = 0x2
   00 FFFFFF8F 

}

