Compiled from "Function2.scala"
public abstract class scala.Function2$class extends java.lang.Object
  SourceFile: "Function2.scala"
  Scala: length = 0x
   
  InnerClass: 
   public final $anonfun$tupled$1=class scala/Function2$$anonfun$tupled$1 of class scala/Function2
   public final $anonfun$curried$1=class scala/Function2$$anonfun$curried$1 of class scala/Function2
  minor version: 0
  major version: 49
  Constant pool:
Asciz	SourceFile;
Asciz	Function2.scala;
Asciz	toString;
Asciz	(Lscala/Function2;)Ljava/lang/String;;
Asciz	Code;
Asciz	<function2>;
String	<function2>
Asciz	LineNumberTable;
Asciz	$this;
Asciz	Lscala/Function2;;
Asciz	LocalVariableTable;
Asciz	curried;
Asciz	(Lscala/Function2;)Lscala/Function1;;
Asciz	scala/Function2$$anonfun$curried$1;
class	scala/Function2$$anonfun$curried$1
Asciz	<init>;
Asciz	(Lscala/Function2;)V;
NameAndType	"<init>":(Lscala/Function2;)V
Method	scala/Function2$$anonfun$curried$1."<init>":(Lscala/Function2;)V
Asciz	curry;
Asciz	scala/Function2;
class	scala/Function2
Asciz	()Lscala/Function1;;
NameAndType	curried:()Lscala/Function1;
InterfaceMethod	scala/Function2.curried:()Lscala/Function1;
Asciz	Deprecated;
Asciz	tupled;
Asciz	scala/Function2$$anonfun$tupled$1;
class	scala/Function2$$anonfun$tupled$1
Method	scala/Function2$$anonfun$tupled$1."<init>":(Lscala/Function2;)V
Asciz	apply$mcVII$sp;
Asciz	(Lscala/Function2;II)V;
Asciz	scala/runtime/BoxesRunTime;
class	scala/runtime/BoxesRunTime
Asciz	boxToInteger;
Asciz	(I)Ljava/lang/Integer;;
NameAndType	boxToInteger:(I)Ljava/lang/Integer;
Method	scala/runtime/BoxesRunTime.boxToInteger:(I)Ljava/lang/Integer;
Asciz	apply;
Asciz	(Ljava/lang/Object;Ljava/lang/Object;)Ljava/lang/Object;;
NameAndType	apply:(Ljava/lang/Object;Ljava/lang/Object;)Ljava/lang/Object;
InterfaceMethod	scala/Function2.apply:(Ljava/lang/Object;Ljava/lang/Object;)Ljava/lang/Object;
Asciz	v1;
Asciz	I;
Asciz	v2;
Asciz	apply$mcZII$sp;
Asciz	(Lscala/Function2;II)Z;
Asciz	unboxToBoolean;
Asciz	(Ljava/lang/Object;)Z;
NameAndType	unboxToBoolean:(Ljava/lang/Object;)Z
Method	scala/runtime/BoxesRunTime.unboxToBoolean:(Ljava/lang/Object;)Z
Asciz	apply$mcIII$sp;
Asciz	(Lscala/Function2;II)I;
Asciz	unboxToInt;
Asciz	(Ljava/lang/Object;)I;
NameAndType	unboxToInt:(Ljava/lang/Object;)I
Method	scala/runtime/BoxesRunTime.unboxToInt:(Ljava/lang/Object;)I
Asciz	apply$mcLII$sp;
Asciz	(Lscala/Function2;II)J;
Asciz	unboxToLong;
Asciz	(Ljava/lang/Object;)J;
NameAndType	unboxToLong:(Ljava/lang/Object;)J
Method	scala/runtime/BoxesRunTime.unboxToLong:(Ljava/lang/Object;)J
Asciz	apply$mcDII$sp;
Asciz	(Lscala/Function2;II)D;
Asciz	unboxToDouble;
Asciz	(Ljava/lang/Object;)D;
NameAndType	unboxToDouble:(Ljava/lang/Object;)D
Method	scala/runtime/BoxesRunTime.unboxToDouble:(Ljava/lang/Object;)D
Asciz	apply$mcVIL$sp;
Asciz	(Lscala/Function2;IJ)V;
Asciz	boxToLong;
Asciz	(J)Ljava/lang/Long;;
NameAndType	boxToLong:(J)Ljava/lang/Long;
Method	scala/runtime/BoxesRunTime.boxToLong:(J)Ljava/lang/Long;
Asciz	J;
Asciz	apply$mcZIL$sp;
Asciz	(Lscala/Function2;IJ)Z;
Asciz	apply$mcIIL$sp;
Asciz	(Lscala/Function2;IJ)I;
Asciz	apply$mcLIL$sp;
Asciz	(Lscala/Function2;IJ)J;
Asciz	apply$mcDIL$sp;
Asciz	(Lscala/Function2;IJ)D;
Asciz	apply$mcVID$sp;
Asciz	(Lscala/Function2;ID)V;
Asciz	boxToDouble;
Asciz	(D)Ljava/lang/Double;;
NameAndType	boxToDouble:(D)Ljava/lang/Double;
Method	scala/runtime/BoxesRunTime.boxToDouble:(D)Ljava/lang/Double;
Asciz	D;
Asciz	apply$mcZID$sp;
Asciz	(Lscala/Function2;ID)Z;
Asciz	apply$mcIID$sp;
Asciz	(Lscala/Function2;ID)I;
Asciz	apply$mcLID$sp;
Asciz	(Lscala/Function2;ID)J;
Asciz	apply$mcDID$sp;
Asciz	(Lscala/Function2;ID)D;
Asciz	apply$mcVLI$sp;
Asciz	(Lscala/Function2;JI)V;
Asciz	apply$mcZLI$sp;
Asciz	(Lscala/Function2;JI)Z;
Asciz	apply$mcILI$sp;
Asciz	(Lscala/Function2;JI)I;
Asciz	apply$mcLLI$sp;
Asciz	(Lscala/Function2;JI)J;
Asciz	apply$mcDLI$sp;
Asciz	(Lscala/Function2;JI)D;
Asciz	apply$mcVLL$sp;
Asciz	(Lscala/Function2;JJ)V;
Asciz	apply$mcZLL$sp;
Asciz	(Lscala/Function2;JJ)Z;
Asciz	apply$mcILL$sp;
Asciz	(Lscala/Function2;JJ)I;
Asciz	apply$mcLLL$sp;
Asciz	(Lscala/Function2;JJ)J;
Asciz	apply$mcDLL$sp;
Asciz	(Lscala/Function2;JJ)D;
Asciz	apply$mcVLD$sp;
Asciz	(Lscala/Function2;JD)V;
Asciz	apply$mcZLD$sp;
Asciz	(Lscala/Function2;JD)Z;
Asciz	apply$mcILD$sp;
Asciz	(Lscala/Function2;JD)I;
Asciz	apply$mcLLD$sp;
Asciz	(Lscala/Function2;JD)J;
Asciz	apply$mcDLD$sp;
Asciz	(Lscala/Function2;JD)D;
Asciz	apply$mcVDI$sp;
Asciz	(Lscala/Function2;DI)V;
Asciz	apply$mcZDI$sp;
Asciz	(Lscala/Function2;DI)Z;
Asciz	apply$mcIDI$sp;
Asciz	(Lscala/Function2;DI)I;
Asciz	apply$mcLDI$sp;
Asciz	(Lscala/Function2;DI)J;
Asciz	apply$mcDDI$sp;
Asciz	(Lscala/Function2;DI)D;
Asciz	apply$mcVDL$sp;
Asciz	(Lscala/Function2;DJ)V;
Asciz	apply$mcZDL$sp;
Asciz	(Lscala/Function2;DJ)Z;
Asciz	apply$mcIDL$sp;
Asciz	(Lscala/Function2;DJ)I;
Asciz	apply$mcLDL$sp;
Asciz	(Lscala/Function2;DJ)J;
Asciz	apply$mcDDL$sp;
Asciz	(Lscala/Function2;DJ)D;
Asciz	apply$mcVDD$sp;
Asciz	(Lscala/Function2;DD)V;
Asciz	apply$mcZDD$sp;
Asciz	(Lscala/Function2;DD)Z;
Asciz	apply$mcIDD$sp;
Asciz	(Lscala/Function2;DD)I;
Asciz	apply$mcLDD$sp;
Asciz	(Lscala/Function2;DD)J;
Asciz	apply$mcDDD$sp;
Asciz	(Lscala/Function2;DD)D;
Asciz	curried$mcVII$sp;
Asciz	curried$mcZII$sp;
Asciz	curried$mcIII$sp;
Asciz	curried$mcLII$sp;
Asciz	curried$mcDII$sp;
Asciz	curried$mcVIL$sp;
Asciz	curried$mcZIL$sp;
Asciz	curried$mcIIL$sp;
Asciz	curried$mcLIL$sp;
Asciz	curried$mcDIL$sp;
Asciz	curried$mcVID$sp;
Asciz	curried$mcZID$sp;
Asciz	curried$mcIID$sp;
Asciz	curried$mcLID$sp;
Asciz	curried$mcDID$sp;
Asciz	curried$mcVLI$sp;
Asciz	curried$mcZLI$sp;
Asciz	curried$mcILI$sp;
Asciz	curried$mcLLI$sp;
Asciz	curried$mcDLI$sp;
Asciz	curried$mcVLL$sp;
Asciz	curried$mcZLL$sp;
Asciz	curried$mcILL$sp;
Asciz	curried$mcLLL$sp;
Asciz	curried$mcDLL$sp;
Asciz	curried$mcVLD$sp;
Asciz	curried$mcZLD$sp;
Asciz	curried$mcILD$sp;
Asciz	curried$mcLLD$sp;
Asciz	curried$mcDLD$sp;
Asciz	curried$mcVDI$sp;
Asciz	curried$mcZDI$sp;
Asciz	curried$mcIDI$sp;
Asciz	curried$mcLDI$sp;
Asciz	curried$mcDDI$sp;
Asciz	curried$mcVDL$sp;
Asciz	curried$mcZDL$sp;
Asciz	curried$mcIDL$sp;
Asciz	curried$mcLDL$sp;
Asciz	curried$mcDDL$sp;
Asciz	curried$mcVDD$sp;
Asciz	curried$mcZDD$sp;
Asciz	curried$mcIDD$sp;
Asciz	curried$mcLDD$sp;
Asciz	curried$mcDDD$sp;
Asciz	curry$mcVII$sp;
NameAndType	curry:()Lscala/Function1;
InterfaceMethod	scala/Function2.curry:()Lscala/Function1;
Asciz	curry$mcZII$sp;
Asciz	curry$mcIII$sp;
Asciz	curry$mcLII$sp;
Asciz	curry$mcDII$sp;
Asciz	curry$mcVIL$sp;
Asciz	curry$mcZIL$sp;
Asciz	curry$mcIIL$sp;
Asciz	curry$mcLIL$sp;
Asciz	curry$mcDIL$sp;
Asciz	curry$mcVID$sp;
Asciz	curry$mcZID$sp;
Asciz	curry$mcIID$sp;
Asciz	curry$mcLID$sp;
Asciz	curry$mcDID$sp;
Asciz	curry$mcVLI$sp;
Asciz	curry$mcZLI$sp;
Asciz	curry$mcILI$sp;
Asciz	curry$mcLLI$sp;
Asciz	curry$mcDLI$sp;
Asciz	curry$mcVLL$sp;
Asciz	curry$mcZLL$sp;
Asciz	curry$mcILL$sp;
Asciz	curry$mcLLL$sp;
Asciz	curry$mcDLL$sp;
Asciz	curry$mcVLD$sp;
Asciz	curry$mcZLD$sp;
Asciz	curry$mcILD$sp;
Asciz	curry$mcLLD$sp;
Asciz	curry$mcDLD$sp;
Asciz	curry$mcVDI$sp;
Asciz	curry$mcZDI$sp;
Asciz	curry$mcIDI$sp;
Asciz	curry$mcLDI$sp;
Asciz	curry$mcDDI$sp;
Asciz	curry$mcVDL$sp;
Asciz	curry$mcZDL$sp;
Asciz	curry$mcIDL$sp;
Asciz	curry$mcLDL$sp;
Asciz	curry$mcDDL$sp;
Asciz	curry$mcVDD$sp;
Asciz	curry$mcZDD$sp;
Asciz	curry$mcIDD$sp;
Asciz	curry$mcLDD$sp;
Asciz	curry$mcDDD$sp;
Asciz	tupled$mcVII$sp;
NameAndType	tupled:()Lscala/Function1;
InterfaceMethod	scala/Function2.tupled:()Lscala/Function1;
Asciz	tupled$mcZII$sp;
Asciz	tupled$mcIII$sp;
Asciz	tupled$mcLII$sp;
Asciz	tupled$mcDII$sp;
Asciz	tupled$mcVIL$sp;
Asciz	tupled$mcZIL$sp;
Asciz	tupled$mcIIL$sp;
Asciz	tupled$mcLIL$sp;
Asciz	tupled$mcDIL$sp;
Asciz	tupled$mcVID$sp;
Asciz	tupled$mcZID$sp;
Asciz	tupled$mcIID$sp;
Asciz	tupled$mcLID$sp;
Asciz	tupled$mcDID$sp;
Asciz	tupled$mcVLI$sp;
Asciz	tupled$mcZLI$sp;
Asciz	tupled$mcILI$sp;
Asciz	tupled$mcLLI$sp;
Asciz	tupled$mcDLI$sp;
Asciz	tupled$mcVLL$sp;
Asciz	tupled$mcZLL$sp;
Asciz	tupled$mcILL$sp;
Asciz	tupled$mcLLL$sp;
Asciz	tupled$mcDLL$sp;
Asciz	tupled$mcVLD$sp;
Asciz	tupled$mcZLD$sp;
Asciz	tupled$mcILD$sp;
Asciz	tupled$mcLLD$sp;
Asciz	tupled$mcDLD$sp;
Asciz	tupled$mcVDI$sp;
Asciz	tupled$mcZDI$sp;
Asciz	tupled$mcIDI$sp;
Asciz	tupled$mcLDI$sp;
Asciz	tupled$mcDDI$sp;
Asciz	tupled$mcVDL$sp;
Asciz	tupled$mcZDL$sp;
Asciz	tupled$mcIDL$sp;
Asciz	tupled$mcLDL$sp;
Asciz	tupled$mcDDL$sp;
Asciz	tupled$mcVDD$sp;
Asciz	tupled$mcZDD$sp;
Asciz	tupled$mcIDD$sp;
Asciz	tupled$mcLDD$sp;
Asciz	tupled$mcDDD$sp;
Asciz	$init$;
Asciz	Scala;
Asciz	InnerClasses;
Asciz	$anonfun$tupled$1;
Asciz	$anonfun$curried$1;
Asciz	scala/Function2$class;
class	scala/Function2$class
Asciz	java/lang/Object;
class	java/lang/Object

{
public static java.lang.String toString(scala.Function2);
  Signature: (Lscala/Function2;)Ljava/lang/String;
  Code:
   Stack=1, Locals=1, Args_size=1
	ldc	String <function2>
	areturn
  Labels:
  LocalVariableTable: 
   Start  Length  Slot  Name   Signature
   0      3      0    $this       Lscala/Function2;


public static scala.Function1 curried(scala.Function2);
  Signature: (Lscala/Function2;)Lscala/Function1;
  Code:
   Stack=3, Locals=1, Args_size=1
	new	class scala/Function2$$anonfun$curried$1
	dup
	aload_0
	invokespecial	Method scala/Function2$$anonfun$curried$1."<init>":(Lscala/Function2;)V
	areturn
  Labels:
  LocalVariableTable: 
   Start  Length  Slot  Name   Signature
   0      9      0    $this       Lscala/Function2;


public static scala.Function1 curry(scala.Function2);
  Signature: (Lscala/Function2;)Lscala/Function1;
  Code:
   Stack=1, Locals=1, Args_size=1
	aload_0
	invokeinterface	InterfaceMethod scala/Function2.curried:()Lscala/Function1;
	areturn
  Labels:
  LocalVariableTable: 
   Start  Length  Slot  Name   Signature
   0      7      0    $this       Lscala/Function2;

  Deprecated: true

public static scala.Function1 tupled(scala.Function2);
  Signature: (Lscala/Function2;)Lscala/Function1;
  Code:
   Stack=3, Locals=1, Args_size=1
	new	class scala/Function2$$anonfun$tupled$1
	dup
	aload_0
	invokespecial	Method scala/Function2$$anonfun$tupled$1."<init>":(Lscala/Function2;)V
	areturn
  Labels:
  LocalVariableTable: 
   Start  Length  Slot  Name   Signature
   0      9      0    $this       Lscala/Function2;


public static void apply$mcVII$sp(scala.Function2, int, int);
  Signature: (Lscala/Function2;II)V
  Code:
   Stack=3, Locals=3, Args_size=3
	aload_0
	iload_1
	invokestatic	Method scala/runtime/BoxesRunTime.boxToInteger:(I)Ljava/lang/Integer;
	iload_2
	invokestatic	Method scala/runtime/BoxesRunTime.boxToInteger:(I)Ljava/lang/Integer;
	invokeinterface	InterfaceMethod scala/Function2.apply:(Ljava/lang/Object;Ljava/lang/Object;)Ljava/lang/Object;
	pop
	return
  Labels:
  LocalVariableTable: 
   Start  Length  Slot  Name   Signature
   0      16      0    $this       Lscala/Function2;
   0      16      1    v1       I
   0      16      2    v2       I


public static boolean apply$mcZII$sp(scala.Function2, int, int);
  Signature: (Lscala/Function2;II)Z
  Code:
   Stack=3, Locals=3, Args_size=3
	aload_0
	iload_1
	invokestatic	Method scala/runtime/BoxesRunTime.boxToInteger:(I)Ljava/lang/Integer;
	iload_2
	invokestatic	Method scala/runtime/BoxesRunTime.boxToInteger:(I)Ljava/lang/Integer;
	invokeinterface	InterfaceMethod scala/Function2.apply:(Ljava/lang/Object;Ljava/lang/Object;)Ljava/lang/Object;
	invokestatic	Method scala/runtime/BoxesRunTime.unboxToBoolean:(Ljava/lang/Object;)Z
	ireturn
  Labels:
  LocalVariableTable: 
   Start  Length  Slot  Name   Signature
   0      18      0    $this       Lscala/Function2;
   0      18      1    v1       I
   0      18      2    v2       I


public static int apply$mcIII$sp(scala.Function2, int, int);
  Signature: (Lscala/Function2;II)I
  Code:
   Stack=3, Locals=3, Args_size=3
	aload_0
	iload_1
	invokestatic	Method scala/runtime/BoxesRunTime.boxToInteger:(I)Ljava/lang/Integer;
	iload_2
	invokestatic	Method scala/runtime/BoxesRunTime.boxToInteger:(I)Ljava/lang/Integer;
	invokeinterface	InterfaceMethod scala/Function2.apply:(Ljava/lang/Object;Ljava/lang/Object;)Ljava/lang/Object;
	invokestatic	Method scala/runtime/BoxesRunTime.unboxToInt:(Ljava/lang/Object;)I
	ireturn
  Labels:
  LocalVariableTable: 
   Start  Length  Slot  Name   Signature
   0      18      0    $this       Lscala/Function2;
   0      18      1    v1       I
   0      18      2    v2       I


public static long apply$mcLII$sp(scala.Function2, int, int);
  Signature: (Lscala/Function2;II)J
  Code:
   Stack=3, Locals=3, Args_size=3
	aload_0
	iload_1
	invokestatic	Method scala/runtime/BoxesRunTime.boxToInteger:(I)Ljava/lang/Integer;
	iload_2
	invokestatic	Method scala/runtime/BoxesRunTime.boxToInteger:(I)Ljava/lang/Integer;
	invokeinterface	InterfaceMethod scala/Function2.apply:(Ljava/lang/Object;Ljava/lang/Object;)Ljava/lang/Object;
	invokestatic	Method scala/runtime/BoxesRunTime.unboxToLong:(Ljava/lang/Object;)J
	lreturn
  Labels:
  LocalVariableTable: 
   Start  Length  Slot  Name   Signature
   0      18      0    $this       Lscala/Function2;
   0      18      1    v1       I
   0      18      2    v2       I


public static double apply$mcDII$sp(scala.Function2, int, int);
  Signature: (Lscala/Function2;II)D
  Code:
   Stack=3, Locals=3, Args_size=3
	aload_0
	iload_1
	invokestatic	Method scala/runtime/BoxesRunTime.boxToInteger:(I)Ljava/lang/Integer;
	iload_2
	invokestatic	Method scala/runtime/BoxesRunTime.boxToInteger:(I)Ljava/lang/Integer;
	invokeinterface	InterfaceMethod scala/Function2.apply:(Ljava/lang/Object;Ljava/lang/Object;)Ljava/lang/Object;
	invokestatic	Method scala/runtime/BoxesRunTime.unboxToDouble:(Ljava/lang/Object;)D
	dreturn
  Labels:
  LocalVariableTable: 
   Start  Length  Slot  Name   Signature
   0      18      0    $this       Lscala/Function2;
   0      18      1    v1       I
   0      18      2    v2       I


public static void apply$mcVIL$sp(scala.Function2, int, long);
  Signature: (Lscala/Function2;IJ)V
  Code:
   Stack=4, Locals=4, Args_size=3
	aload_0
	iload_1
	invokestatic	Method scala/runtime/BoxesRunTime.boxToInteger:(I)Ljava/lang/Integer;
	lload_2
	invokestatic	Method scala/runtime/BoxesRunTime.boxToLong:(J)Ljava/lang/Long;
	invokeinterface	InterfaceMethod scala/Function2.apply:(Ljava/lang/Object;Ljava/lang/Object;)Ljava/lang/Object;
	pop
	return
  Labels:
  LocalVariableTable: 
   Start  Length  Slot  Name   Signature
   0      16      0    $this       Lscala/Function2;
   0      16      1    v1       I
   0      16      2    v2       J


public static boolean apply$mcZIL$sp(scala.Function2, int, long);
  Signature: (Lscala/Function2;IJ)Z
  Code:
   Stack=4, Locals=4, Args_size=3
	aload_0
	iload_1
	invokestatic	Method scala/runtime/BoxesRunTime.boxToInteger:(I)Ljava/lang/Integer;
	lload_2
	invokestatic	Method scala/runtime/BoxesRunTime.boxToLong:(J)Ljava/lang/Long;
	invokeinterface	InterfaceMethod scala/Function2.apply:(Ljava/lang/Object;Ljava/lang/Object;)Ljava/lang/Object;
	invokestatic	Method scala/runtime/BoxesRunTime.unboxToBoolean:(Ljava/lang/Object;)Z
	ireturn
  Labels:
  LocalVariableTable: 
   Start  Length  Slot  Name   Signature
   0      18      0    $this       Lscala/Function2;
   0      18      1    v1       I
   0      18      2    v2       J


public static int apply$mcIIL$sp(scala.Function2, int, long);
  Signature: (Lscala/Function2;IJ)I
  Code:
   Stack=4, Locals=4, Args_size=3
	aload_0
	iload_1
	invokestatic	Method scala/runtime/BoxesRunTime.boxToInteger:(I)Ljava/lang/Integer;
	lload_2
	invokestatic	Method scala/runtime/BoxesRunTime.boxToLong:(J)Ljava/lang/Long;
	invokeinterface	InterfaceMethod scala/Function2.apply:(Ljava/lang/Object;Ljava/lang/Object;)Ljava/lang/Object;
	invokestatic	Method scala/runtime/BoxesRunTime.unboxToInt:(Ljava/lang/Object;)I
	ireturn
  Labels:
  LocalVariableTable: 
   Start  Length  Slot  Name   Signature
   0      18      0    $this       Lscala/Function2;
   0      18      1    v1       I
   0      18      2    v2       J


public static long apply$mcLIL$sp(scala.Function2, int, long);
  Signature: (Lscala/Function2;IJ)J
  Code:
   Stack=4, Locals=4, Args_size=3
	aload_0
	iload_1
	invokestatic	Method scala/runtime/BoxesRunTime.boxToInteger:(I)Ljava/lang/Integer;
	lload_2
	invokestatic	Method scala/runtime/BoxesRunTime.boxToLong:(J)Ljava/lang/Long;
	invokeinterface	InterfaceMethod scala/Function2.apply:(Ljava/lang/Object;Ljava/lang/Object;)Ljava/lang/Object;
	invokestatic	Method scala/runtime/BoxesRunTime.unboxToLong:(Ljava/lang/Object;)J
	lreturn
  Labels:
  LocalVariableTable: 
   Start  Length  Slot  Name   Signature
   0      18      0    $this       Lscala/Function2;
   0      18      1    v1       I
   0      18      2    v2       J


public static double apply$mcDIL$sp(scala.Function2, int, long);
  Signature: (Lscala/Function2;IJ)D
  Code:
   Stack=4, Locals=4, Args_size=3
	aload_0
	iload_1
	invokestatic	Method scala/runtime/BoxesRunTime.boxToInteger:(I)Ljava/lang/Integer;
	lload_2
	invokestatic	Method scala/runtime/BoxesRunTime.boxToLong:(J)Ljava/lang/Long;
	invokeinterface	InterfaceMethod scala/Function2.apply:(Ljava/lang/Object;Ljava/lang/Object;)Ljava/lang/Object;
	invokestatic	Method scala/runtime/BoxesRunTime.unboxToDouble:(Ljava/lang/Object;)D
	dreturn
  Labels:
  LocalVariableTable: 
   Start  Length  Slot  Name   Signature
   0      18      0    $this       Lscala/Function2;
   0      18      1    v1       I
   0      18      2    v2       J


public static void apply$mcVID$sp(scala.Function2, int, double);
  Signature: (Lscala/Function2;ID)V
  Code:
   Stack=4, Locals=4, Args_size=3
	aload_0
	iload_1
	invokestatic	Method scala/runtime/BoxesRunTime.boxToInteger:(I)Ljava/lang/Integer;
	dload_2
	invokestatic	Method scala/runtime/BoxesRunTime.boxToDouble:(D)Ljava/lang/Double;
	invokeinterface	InterfaceMethod scala/Function2.apply:(Ljava/lang/Object;Ljava/lang/Object;)Ljava/lang/Object;
	pop
	return
  Labels:
  LocalVariableTable: 
   Start  Length  Slot  Name   Signature
   0      16      0    $this       Lscala/Function2;
   0      16      1    v1       I
   0      16      2    v2       D


public static boolean apply$mcZID$sp(scala.Function2, int, double);
  Signature: (Lscala/Function2;ID)Z
  Code:
   Stack=4, Locals=4, Args_size=3
	aload_0
	iload_1
	invokestatic	Method scala/runtime/BoxesRunTime.boxToInteger:(I)Ljava/lang/Integer;
	dload_2
	invokestatic	Method scala/runtime/BoxesRunTime.boxToDouble:(D)Ljava/lang/Double;
	invokeinterface	InterfaceMethod scala/Function2.apply:(Ljava/lang/Object;Ljava/lang/Object;)Ljava/lang/Object;
	invokestatic	Method scala/runtime/BoxesRunTime.unboxToBoolean:(Ljava/lang/Object;)Z
	ireturn
  Labels:
  LocalVariableTable: 
   Start  Length  Slot  Name   Signature
   0      18      0    $this       Lscala/Function2;
   0      18      1    v1       I
   0      18      2    v2       D


public static int apply$mcIID$sp(scala.Function2, int, double);
  Signature: (Lscala/Function2;ID)I
  Code:
   Stack=4, Locals=4, Args_size=3
	aload_0
	iload_1
	invokestatic	Method scala/runtime/BoxesRunTime.boxToInteger:(I)Ljava/lang/Integer;
	dload_2
	invokestatic	Method scala/runtime/BoxesRunTime.boxToDouble:(D)Ljava/lang/Double;
	invokeinterface	InterfaceMethod scala/Function2.apply:(Ljava/lang/Object;Ljava/lang/Object;)Ljava/lang/Object;
	invokestatic	Method scala/runtime/BoxesRunTime.unboxToInt:(Ljava/lang/Object;)I
	ireturn
  Labels:
  LocalVariableTable: 
   Start  Length  Slot  Name   Signature
   0      18      0    $this       Lscala/Function2;
   0      18      1    v1       I
   0      18      2    v2       D


public static long apply$mcLID$sp(scala.Function2, int, double);
  Signature: (Lscala/Function2;ID)J
  Code:
   Stack=4, Locals=4, Args_size=3
	aload_0
	iload_1
	invokestatic	Method scala/runtime/BoxesRunTime.boxToInteger:(I)Ljava/lang/Integer;
	dload_2
	invokestatic	Method scala/runtime/BoxesRunTime.boxToDouble:(D)Ljava/lang/Double;
	invokeinterface	InterfaceMethod scala/Function2.apply:(Ljava/lang/Object;Ljava/lang/Object;)Ljava/lang/Object;
	invokestatic	Method scala/runtime/BoxesRunTime.unboxToLong:(Ljava/lang/Object;)J
	lreturn
  Labels:
  LocalVariableTable: 
   Start  Length  Slot  Name   Signature
   0      18      0    $this       Lscala/Function2;
   0      18      1    v1       I
   0      18      2    v2       D


public static double apply$mcDID$sp(scala.Function2, int, double);
  Signature: (Lscala/Function2;ID)D
  Code:
   Stack=4, Locals=4, Args_size=3
	aload_0
	iload_1
	invokestatic	Method scala/runtime/BoxesRunTime.boxToInteger:(I)Ljava/lang/Integer;
	dload_2
	invokestatic	Method scala/runtime/BoxesRunTime.boxToDouble:(D)Ljava/lang/Double;
	invokeinterface	InterfaceMethod scala/Function2.apply:(Ljava/lang/Object;Ljava/lang/Object;)Ljava/lang/Object;
	invokestatic	Method scala/runtime/BoxesRunTime.unboxToDouble:(Ljava/lang/Object;)D
	dreturn
  Labels:
  LocalVariableTable: 
   Start  Length  Slot  Name   Signature
   0      18      0    $this       Lscala/Function2;
   0      18      1    v1       I
   0      18      2    v2       D


public static void apply$mcVLI$sp(scala.Function2, long, int);
  Signature: (Lscala/Function2;JI)V
  Code:
   Stack=3, Locals=4, Args_size=3
	aload_0
	lload_1
	invokestatic	Method scala/runtime/BoxesRunTime.boxToLong:(J)Ljava/lang/Long;
	iload_3
	invokestatic	Method scala/runtime/BoxesRunTime.boxToInteger:(I)Ljava/lang/Integer;
	invokeinterface	InterfaceMethod scala/Function2.apply:(Ljava/lang/Object;Ljava/lang/Object;)Ljava/lang/Object;
	pop
	return
  Labels:
  LocalVariableTable: 
   Start  Length  Slot  Name   Signature
   0      16      0    $this       Lscala/Function2;
   0      16      1    v1       J
   0      16      3    v2       I


public static boolean apply$mcZLI$sp(scala.Function2, long, int);
  Signature: (Lscala/Function2;JI)Z
  Code:
   Stack=3, Locals=4, Args_size=3
	aload_0
	lload_1
	invokestatic	Method scala/runtime/BoxesRunTime.boxToLong:(J)Ljava/lang/Long;
	iload_3
	invokestatic	Method scala/runtime/BoxesRunTime.boxToInteger:(I)Ljava/lang/Integer;
	invokeinterface	InterfaceMethod scala/Function2.apply:(Ljava/lang/Object;Ljava/lang/Object;)Ljava/lang/Object;
	invokestatic	Method scala/runtime/BoxesRunTime.unboxToBoolean:(Ljava/lang/Object;)Z
	ireturn
  Labels:
  LocalVariableTable: 
   Start  Length  Slot  Name   Signature
   0      18      0    $this       Lscala/Function2;
   0      18      1    v1       J
   0      18      3    v2       I


public static int apply$mcILI$sp(scala.Function2, long, int);
  Signature: (Lscala/Function2;JI)I
  Code:
   Stack=3, Locals=4, Args_size=3
	aload_0
	lload_1
	invokestatic	Method scala/runtime/BoxesRunTime.boxToLong:(J)Ljava/lang/Long;
	iload_3
	invokestatic	Method scala/runtime/BoxesRunTime.boxToInteger:(I)Ljava/lang/Integer;
	invokeinterface	InterfaceMethod scala/Function2.apply:(Ljava/lang/Object;Ljava/lang/Object;)Ljava/lang/Object;
	invokestatic	Method scala/runtime/BoxesRunTime.unboxToInt:(Ljava/lang/Object;)I
	ireturn
  Labels:
  LocalVariableTable: 
   Start  Length  Slot  Name   Signature
   0      18      0    $this       Lscala/Function2;
   0      18      1    v1       J
   0      18      3    v2       I


public static long apply$mcLLI$sp(scala.Function2, long, int);
  Signature: (Lscala/Function2;JI)J
  Code:
   Stack=3, Locals=4, Args_size=3
	aload_0
	lload_1
	invokestatic	Method scala/runtime/BoxesRunTime.boxToLong:(J)Ljava/lang/Long;
	iload_3
	invokestatic	Method scala/runtime/BoxesRunTime.boxToInteger:(I)Ljava/lang/Integer;
	invokeinterface	InterfaceMethod scala/Function2.apply:(Ljava/lang/Object;Ljava/lang/Object;)Ljava/lang/Object;
	invokestatic	Method scala/runtime/BoxesRunTime.unboxToLong:(Ljava/lang/Object;)J
	lreturn
  Labels:
  LocalVariableTable: 
   Start  Length  Slot  Name   Signature
   0      18      0    $this       Lscala/Function2;
   0      18      1    v1       J
   0      18      3    v2       I


public static double apply$mcDLI$sp(scala.Function2, long, int);
  Signature: (Lscala/Function2;JI)D
  Code:
   Stack=3, Locals=4, Args_size=3
	aload_0
	lload_1
	invokestatic	Method scala/runtime/BoxesRunTime.boxToLong:(J)Ljava/lang/Long;
	iload_3
	invokestatic	Method scala/runtime/BoxesRunTime.boxToInteger:(I)Ljava/lang/Integer;
	invokeinterface	InterfaceMethod scala/Function2.apply:(Ljava/lang/Object;Ljava/lang/Object;)Ljava/lang/Object;
	invokestatic	Method scala/runtime/BoxesRunTime.unboxToDouble:(Ljava/lang/Object;)D
	dreturn
  Labels:
  LocalVariableTable: 
   Start  Length  Slot  Name   Signature
   0      18      0    $this       Lscala/Function2;
   0      18      1    v1       J
   0      18      3    v2       I


public static void apply$mcVLL$sp(scala.Function2, long, long);
  Signature: (Lscala/Function2;JJ)V
  Code:
   Stack=4, Locals=5, Args_size=3
	aload_0
	lload_1
	invokestatic	Method scala/runtime/BoxesRunTime.boxToLong:(J)Ljava/lang/Long;
	lload_3
	invokestatic	Method scala/runtime/BoxesRunTime.boxToLong:(J)Ljava/lang/Long;
	invokeinterface	InterfaceMethod scala/Function2.apply:(Ljava/lang/Object;Ljava/lang/Object;)Ljava/lang/Object;
	pop
	return
  Labels:
  LocalVariableTable: 
   Start  Length  Slot  Name   Signature
   0      16      0    $this       Lscala/Function2;
   0      16      1    v1       J
   0      16      3    v2       J


public static boolean apply$mcZLL$sp(scala.Function2, long, long);
  Signature: (Lscala/Function2;JJ)Z
  Code:
   Stack=4, Locals=5, Args_size=3
	aload_0
	lload_1
	invokestatic	Method scala/runtime/BoxesRunTime.boxToLong:(J)Ljava/lang/Long;
	lload_3
	invokestatic	Method scala/runtime/BoxesRunTime.boxToLong:(J)Ljava/lang/Long;
	invokeinterface	InterfaceMethod scala/Function2.apply:(Ljava/lang/Object;Ljava/lang/Object;)Ljava/lang/Object;
	invokestatic	Method scala/runtime/BoxesRunTime.unboxToBoolean:(Ljava/lang/Object;)Z
	ireturn
  Labels:
  LocalVariableTable: 
   Start  Length  Slot  Name   Signature
   0      18      0    $this       Lscala/Function2;
   0      18      1    v1       J
   0      18      3    v2       J


public static int apply$mcILL$sp(scala.Function2, long, long);
  Signature: (Lscala/Function2;JJ)I
  Code:
   Stack=4, Locals=5, Args_size=3
	aload_0
	lload_1
	invokestatic	Method scala/runtime/BoxesRunTime.boxToLong:(J)Ljava/lang/Long;
	lload_3
	invokestatic	Method scala/runtime/BoxesRunTime.boxToLong:(J)Ljava/lang/Long;
	invokeinterface	InterfaceMethod scala/Function2.apply:(Ljava/lang/Object;Ljava/lang/Object;)Ljava/lang/Object;
	invokestatic	Method scala/runtime/BoxesRunTime.unboxToInt:(Ljava/lang/Object;)I
	ireturn
  Labels:
  LocalVariableTable: 
   Start  Length  Slot  Name   Signature
   0      18      0    $this       Lscala/Function2;
   0      18      1    v1       J
   0      18      3    v2       J


public static long apply$mcLLL$sp(scala.Function2, long, long);
  Signature: (Lscala/Function2;JJ)J
  Code:
   Stack=4, Locals=5, Args_size=3
	aload_0
	lload_1
	invokestatic	Method scala/runtime/BoxesRunTime.boxToLong:(J)Ljava/lang/Long;
	lload_3
	invokestatic	Method scala/runtime/BoxesRunTime.boxToLong:(J)Ljava/lang/Long;
	invokeinterface	InterfaceMethod scala/Function2.apply:(Ljava/lang/Object;Ljava/lang/Object;)Ljava/lang/Object;
	invokestatic	Method scala/runtime/BoxesRunTime.unboxToLong:(Ljava/lang/Object;)J
	lreturn
  Labels:
  LocalVariableTable: 
   Start  Length  Slot  Name   Signature
   0      18      0    $this       Lscala/Function2;
   0      18      1    v1       J
   0      18      3    v2       J


public static double apply$mcDLL$sp(scala.Function2, long, long);
  Signature: (Lscala/Function2;JJ)D
  Code:
   Stack=4, Locals=5, Args_size=3
	aload_0
	lload_1
	invokestatic	Method scala/runtime/BoxesRunTime.boxToLong:(J)Ljava/lang/Long;
	lload_3
	invokestatic	Method scala/runtime/BoxesRunTime.boxToLong:(J)Ljava/lang/Long;
	invokeinterface	InterfaceMethod scala/Function2.apply:(Ljava/lang/Object;Ljava/lang/Object;)Ljava/lang/Object;
	invokestatic	Method scala/runtime/BoxesRunTime.unboxToDouble:(Ljava/lang/Object;)D
	dreturn
  Labels:
  LocalVariableTable: 
   Start  Length  Slot  Name   Signature
   0      18      0    $this       Lscala/Function2;
   0      18      1    v1       J
   0      18      3    v2       J


public static void apply$mcVLD$sp(scala.Function2, long, double);
  Signature: (Lscala/Function2;JD)V
  Code:
   Stack=4, Locals=5, Args_size=3
	aload_0
	lload_1
	invokestatic	Method scala/runtime/BoxesRunTime.boxToLong:(J)Ljava/lang/Long;
	dload_3
	invokestatic	Method scala/runtime/BoxesRunTime.boxToDouble:(D)Ljava/lang/Double;
	invokeinterface	InterfaceMethod scala/Function2.apply:(Ljava/lang/Object;Ljava/lang/Object;)Ljava/lang/Object;
	pop
	return
  Labels:
  LocalVariableTable: 
   Start  Length  Slot  Name   Signature
   0      16      0    $this       Lscala/Function2;
   0      16      1    v1       J
   0      16      3    v2       D


public static boolean apply$mcZLD$sp(scala.Function2, long, double);
  Signature: (Lscala/Function2;JD)Z
  Code:
   Stack=4, Locals=5, Args_size=3
	aload_0
	lload_1
	invokestatic	Method scala/runtime/BoxesRunTime.boxToLong:(J)Ljava/lang/Long;
	dload_3
	invokestatic	Method scala/runtime/BoxesRunTime.boxToDouble:(D)Ljava/lang/Double;
	invokeinterface	InterfaceMethod scala/Function2.apply:(Ljava/lang/Object;Ljava/lang/Object;)Ljava/lang/Object;
	invokestatic	Method scala/runtime/BoxesRunTime.unboxToBoolean:(Ljava/lang/Object;)Z
	ireturn
  Labels:
  LocalVariableTable: 
   Start  Length  Slot  Name   Signature
   0      18      0    $this       Lscala/Function2;
   0      18      1    v1       J
   0      18      3    v2       D


public static int apply$mcILD$sp(scala.Function2, long, double);
  Signature: (Lscala/Function2;JD)I
  Code:
   Stack=4, Locals=5, Args_size=3
	aload_0
	lload_1
	invokestatic	Method scala/runtime/BoxesRunTime.boxToLong:(J)Ljava/lang/Long;
	dload_3
	invokestatic	Method scala/runtime/BoxesRunTime.boxToDouble:(D)Ljava/lang/Double;
	invokeinterface	InterfaceMethod scala/Function2.apply:(Ljava/lang/Object;Ljava/lang/Object;)Ljava/lang/Object;
	invokestatic	Method scala/runtime/BoxesRunTime.unboxToInt:(Ljava/lang/Object;)I
	ireturn
  Labels:
  LocalVariableTable: 
   Start  Length  Slot  Name   Signature
   0      18      0    $this       Lscala/Function2;
   0      18      1    v1       J
   0      18      3    v2       D


public static long apply$mcLLD$sp(scala.Function2, long, double);
  Signature: (Lscala/Function2;JD)J
  Code:
   Stack=4, Locals=5, Args_size=3
	aload_0
	lload_1
	invokestatic	Method scala/runtime/BoxesRunTime.boxToLong:(J)Ljava/lang/Long;
	dload_3
	invokestatic	Method scala/runtime/BoxesRunTime.boxToDouble:(D)Ljava/lang/Double;
	invokeinterface	InterfaceMethod scala/Function2.apply:(Ljava/lang/Object;Ljava/lang/Object;)Ljava/lang/Object;
	invokestatic	Method scala/runtime/BoxesRunTime.unboxToLong:(Ljava/lang/Object;)J
	lreturn
  Labels:
  LocalVariableTable: 
   Start  Length  Slot  Name   Signature
   0      18      0    $this       Lscala/Function2;
   0      18      1    v1       J
   0      18      3    v2       D


public static double apply$mcDLD$sp(scala.Function2, long, double);
  Signature: (Lscala/Function2;JD)D
  Code:
   Stack=4, Locals=5, Args_size=3
	aload_0
	lload_1
	invokestatic	Method scala/runtime/BoxesRunTime.boxToLong:(J)Ljava/lang/Long;
	dload_3
	invokestatic	Method scala/runtime/BoxesRunTime.boxToDouble:(D)Ljava/lang/Double;
	invokeinterface	InterfaceMethod scala/Function2.apply:(Ljava/lang/Object;Ljava/lang/Object;)Ljava/lang/Object;
	invokestatic	Method scala/runtime/BoxesRunTime.unboxToDouble:(Ljava/lang/Object;)D
	dreturn
  Labels:
  LocalVariableTable: 
   Start  Length  Slot  Name   Signature
   0      18      0    $this       Lscala/Function2;
   0      18      1    v1       J
   0      18      3    v2       D


public static void apply$mcVDI$sp(scala.Function2, double, int);
  Signature: (Lscala/Function2;DI)V
  Code:
   Stack=3, Locals=4, Args_size=3
	aload_0
	dload_1
	invokestatic	Method scala/runtime/BoxesRunTime.boxToDouble:(D)Ljava/lang/Double;
	iload_3
	invokestatic	Method scala/runtime/BoxesRunTime.boxToInteger:(I)Ljava/lang/Integer;
	invokeinterface	InterfaceMethod scala/Function2.apply:(Ljava/lang/Object;Ljava/lang/Object;)Ljava/lang/Object;
	pop
	return
  Labels:
  LocalVariableTable: 
   Start  Length  Slot  Name   Signature
   0      16      0    $this       Lscala/Function2;
   0      16      1    v1       D
   0      16      3    v2       I


public static boolean apply$mcZDI$sp(scala.Function2, double, int);
  Signature: (Lscala/Function2;DI)Z
  Code:
   Stack=3, Locals=4, Args_size=3
	aload_0
	dload_1
	invokestatic	Method scala/runtime/BoxesRunTime.boxToDouble:(D)Ljava/lang/Double;
	iload_3
	invokestatic	Method scala/runtime/BoxesRunTime.boxToInteger:(I)Ljava/lang/Integer;
	invokeinterface	InterfaceMethod scala/Function2.apply:(Ljava/lang/Object;Ljava/lang/Object;)Ljava/lang/Object;
	invokestatic	Method scala/runtime/BoxesRunTime.unboxToBoolean:(Ljava/lang/Object;)Z
	ireturn
  Labels:
  LocalVariableTable: 
   Start  Length  Slot  Name   Signature
   0      18      0    $this       Lscala/Function2;
   0      18      1    v1       D
   0      18      3    v2       I


public static int apply$mcIDI$sp(scala.Function2, double, int);
  Signature: (Lscala/Function2;DI)I
  Code:
   Stack=3, Locals=4, Args_size=3
	aload_0
	dload_1
	invokestatic	Method scala/runtime/BoxesRunTime.boxToDouble:(D)Ljava/lang/Double;
	iload_3
	invokestatic	Method scala/runtime/BoxesRunTime.boxToInteger:(I)Ljava/lang/Integer;
	invokeinterface	InterfaceMethod scala/Function2.apply:(Ljava/lang/Object;Ljava/lang/Object;)Ljava/lang/Object;
	invokestatic	Method scala/runtime/BoxesRunTime.unboxToInt:(Ljava/lang/Object;)I
	ireturn
  Labels:
  LocalVariableTable: 
   Start  Length  Slot  Name   Signature
   0      18      0    $this       Lscala/Function2;
   0      18      1    v1       D
   0      18      3    v2       I


public static long apply$mcLDI$sp(scala.Function2, double, int);
  Signature: (Lscala/Function2;DI)J
  Code:
   Stack=3, Locals=4, Args_size=3
	aload_0
	dload_1
	invokestatic	Method scala/runtime/BoxesRunTime.boxToDouble:(D)Ljava/lang/Double;
	iload_3
	invokestatic	Method scala/runtime/BoxesRunTime.boxToInteger:(I)Ljava/lang/Integer;
	invokeinterface	InterfaceMethod scala/Function2.apply:(Ljava/lang/Object;Ljava/lang/Object;)Ljava/lang/Object;
	invokestatic	Method scala/runtime/BoxesRunTime.unboxToLong:(Ljava/lang/Object;)J
	lreturn
  Labels:
  LocalVariableTable: 
   Start  Length  Slot  Name   Signature
   0      18      0    $this       Lscala/Function2;
   0      18      1    v1       D
   0      18      3    v2       I


public static double apply$mcDDI$sp(scala.Function2, double, int);
  Signature: (Lscala/Function2;DI)D
  Code:
   Stack=3, Locals=4, Args_size=3
	aload_0
	dload_1
	invokestatic	Method scala/runtime/BoxesRunTime.boxToDouble:(D)Ljava/lang/Double;
	iload_3
	invokestatic	Method scala/runtime/BoxesRunTime.boxToInteger:(I)Ljava/lang/Integer;
	invokeinterface	InterfaceMethod scala/Function2.apply:(Ljava/lang/Object;Ljava/lang/Object;)Ljava/lang/Object;
	invokestatic	Method scala/runtime/BoxesRunTime.unboxToDouble:(Ljava/lang/Object;)D
	dreturn
  Labels:
  LocalVariableTable: 
   Start  Length  Slot  Name   Signature
   0      18      0    $this       Lscala/Function2;
   0      18      1    v1       D
   0      18      3    v2       I


public static void apply$mcVDL$sp(scala.Function2, double, long);
  Signature: (Lscala/Function2;DJ)V
  Code:
   Stack=4, Locals=5, Args_size=3
	aload_0
	dload_1
	invokestatic	Method scala/runtime/BoxesRunTime.boxToDouble:(D)Ljava/lang/Double;
	lload_3
	invokestatic	Method scala/runtime/BoxesRunTime.boxToLong:(J)Ljava/lang/Long;
	invokeinterface	InterfaceMethod scala/Function2.apply:(Ljava/lang/Object;Ljava/lang/Object;)Ljava/lang/Object;
	pop
	return
  Labels:
  LocalVariableTable: 
   Start  Length  Slot  Name   Signature
   0      16      0    $this       Lscala/Function2;
   0      16      1    v1       D
   0      16      3    v2       J


public static boolean apply$mcZDL$sp(scala.Function2, double, long);
  Signature: (Lscala/Function2;DJ)Z
  Code:
   Stack=4, Locals=5, Args_size=3
	aload_0
	dload_1
	invokestatic	Method scala/runtime/BoxesRunTime.boxToDouble:(D)Ljava/lang/Double;
	lload_3
	invokestatic	Method scala/runtime/BoxesRunTime.boxToLong:(J)Ljava/lang/Long;
	invokeinterface	InterfaceMethod scala/Function2.apply:(Ljava/lang/Object;Ljava/lang/Object;)Ljava/lang/Object;
	invokestatic	Method scala/runtime/BoxesRunTime.unboxToBoolean:(Ljava/lang/Object;)Z
	ireturn
  Labels:
  LocalVariableTable: 
   Start  Length  Slot  Name   Signature
   0      18      0    $this       Lscala/Function2;
   0      18      1    v1       D
   0      18      3    v2       J


public static int apply$mcIDL$sp(scala.Function2, double, long);
  Signature: (Lscala/Function2;DJ)I
  Code:
   Stack=4, Locals=5, Args_size=3
	aload_0
	dload_1
	invokestatic	Method scala/runtime/BoxesRunTime.boxToDouble:(D)Ljava/lang/Double;
	lload_3
	invokestatic	Method scala/runtime/BoxesRunTime.boxToLong:(J)Ljava/lang/Long;
	invokeinterface	InterfaceMethod scala/Function2.apply:(Ljava/lang/Object;Ljava/lang/Object;)Ljava/lang/Object;
	invokestatic	Method scala/runtime/BoxesRunTime.unboxToInt:(Ljava/lang/Object;)I
	ireturn
  Labels:
  LocalVariableTable: 
   Start  Length  Slot  Name   Signature
   0      18      0    $this       Lscala/Function2;
   0      18      1    v1       D
   0      18      3    v2       J


public static long apply$mcLDL$sp(scala.Function2, double, long);
  Signature: (Lscala/Function2;DJ)J
  Code:
   Stack=4, Locals=5, Args_size=3
	aload_0
	dload_1
	invokestatic	Method scala/runtime/BoxesRunTime.boxToDouble:(D)Ljava/lang/Double;
	lload_3
	invokestatic	Method scala/runtime/BoxesRunTime.boxToLong:(J)Ljava/lang/Long;
	invokeinterface	InterfaceMethod scala/Function2.apply:(Ljava/lang/Object;Ljava/lang/Object;)Ljava/lang/Object;
	invokestatic	Method scala/runtime/BoxesRunTime.unboxToLong:(Ljava/lang/Object;)J
	lreturn
  Labels:
  LocalVariableTable: 
   Start  Length  Slot  Name   Signature
   0      18      0    $this       Lscala/Function2;
   0      18      1    v1       D
   0      18      3    v2       J


public static double apply$mcDDL$sp(scala.Function2, double, long);
  Signature: (Lscala/Function2;DJ)D
  Code:
   Stack=4, Locals=5, Args_size=3
	aload_0
	dload_1
	invokestatic	Method scala/runtime/BoxesRunTime.boxToDouble:(D)Ljava/lang/Double;
	lload_3
	invokestatic	Method scala/runtime/BoxesRunTime.boxToLong:(J)Ljava/lang/Long;
	invokeinterface	InterfaceMethod scala/Function2.apply:(Ljava/lang/Object;Ljava/lang/Object;)Ljava/lang/Object;
	invokestatic	Method scala/runtime/BoxesRunTime.unboxToDouble:(Ljava/lang/Object;)D
	dreturn
  Labels:
  LocalVariableTable: 
   Start  Length  Slot  Name   Signature
   0      18      0    $this       Lscala/Function2;
   0      18      1    v1       D
   0      18      3    v2       J


public static void apply$mcVDD$sp(scala.Function2, double, double);
  Signature: (Lscala/Function2;DD)V
  Code:
   Stack=4, Locals=5, Args_size=3
	aload_0
	dload_1
	invokestatic	Method scala/runtime/BoxesRunTime.boxToDouble:(D)Ljava/lang/Double;
	dload_3
	invokestatic	Method scala/runtime/BoxesRunTime.boxToDouble:(D)Ljava/lang/Double;
	invokeinterface	InterfaceMethod scala/Function2.apply:(Ljava/lang/Object;Ljava/lang/Object;)Ljava/lang/Object;
	pop
	return
  Labels:
  LocalVariableTable: 
   Start  Length  Slot  Name   Signature
   0      16      0    $this       Lscala/Function2;
   0      16      1    v1       D
   0      16      3    v2       D


public static boolean apply$mcZDD$sp(scala.Function2, double, double);
  Signature: (Lscala/Function2;DD)Z
  Code:
   Stack=4, Locals=5, Args_size=3
	aload_0
	dload_1
	invokestatic	Method scala/runtime/BoxesRunTime.boxToDouble:(D)Ljava/lang/Double;
	dload_3
	invokestatic	Method scala/runtime/BoxesRunTime.boxToDouble:(D)Ljava/lang/Double;
	invokeinterface	InterfaceMethod scala/Function2.apply:(Ljava/lang/Object;Ljava/lang/Object;)Ljava/lang/Object;
	invokestatic	Method scala/runtime/BoxesRunTime.unboxToBoolean:(Ljava/lang/Object;)Z
	ireturn
  Labels:
  LocalVariableTable: 
   Start  Length  Slot  Name   Signature
   0      18      0    $this       Lscala/Function2;
   0      18      1    v1       D
   0      18      3    v2       D


public static int apply$mcIDD$sp(scala.Function2, double, double);
  Signature: (Lscala/Function2;DD)I
  Code:
   Stack=4, Locals=5, Args_size=3
	aload_0
	dload_1
	invokestatic	Method scala/runtime/BoxesRunTime.boxToDouble:(D)Ljava/lang/Double;
	dload_3
	invokestatic	Method scala/runtime/BoxesRunTime.boxToDouble:(D)Ljava/lang/Double;
	invokeinterface	InterfaceMethod scala/Function2.apply:(Ljava/lang/Object;Ljava/lang/Object;)Ljava/lang/Object;
	invokestatic	Method scala/runtime/BoxesRunTime.unboxToInt:(Ljava/lang/Object;)I
	ireturn
  Labels:
  LocalVariableTable: 
   Start  Length  Slot  Name   Signature
   0      18      0    $this       Lscala/Function2;
   0      18      1    v1       D
   0      18      3    v2       D


public static long apply$mcLDD$sp(scala.Function2, double, double);
  Signature: (Lscala/Function2;DD)J
  Code:
   Stack=4, Locals=5, Args_size=3
	aload_0
	dload_1
	invokestatic	Method scala/runtime/BoxesRunTime.boxToDouble:(D)Ljava/lang/Double;
	dload_3
	invokestatic	Method scala/runtime/BoxesRunTime.boxToDouble:(D)Ljava/lang/Double;
	invokeinterface	InterfaceMethod scala/Function2.apply:(Ljava/lang/Object;Ljava/lang/Object;)Ljava/lang/Object;
	invokestatic	Method scala/runtime/BoxesRunTime.unboxToLong:(Ljava/lang/Object;)J
	lreturn
  Labels:
  LocalVariableTable: 
   Start  Length  Slot  Name   Signature
   0      18      0    $this       Lscala/Function2;
   0      18      1    v1       D
   0      18      3    v2       D


public static double apply$mcDDD$sp(scala.Function2, double, double);
  Signature: (Lscala/Function2;DD)D
  Code:
   Stack=4, Locals=5, Args_size=3
	aload_0
	dload_1
	invokestatic	Method scala/runtime/BoxesRunTime.boxToDouble:(D)Ljava/lang/Double;
	dload_3
	invokestatic	Method scala/runtime/BoxesRunTime.boxToDouble:(D)Ljava/lang/Double;
	invokeinterface	InterfaceMethod scala/Function2.apply:(Ljava/lang/Object;Ljava/lang/Object;)Ljava/lang/Object;
	invokestatic	Method scala/runtime/BoxesRunTime.unboxToDouble:(Ljava/lang/Object;)D
	dreturn
  Labels:
  LocalVariableTable: 
   Start  Length  Slot  Name   Signature
   0      18      0    $this       Lscala/Function2;
   0      18      1    v1       D
   0      18      3    v2       D


public static scala.Function1 curried$mcVII$sp(scala.Function2);
  Signature: (Lscala/Function2;)Lscala/Function1;
  Code:
   Stack=1, Locals=1, Args_size=1
	aload_0
	invokeinterface	InterfaceMethod scala/Function2.curried:()Lscala/Function1;
	areturn
  Labels:
  LocalVariableTable: 
   Start  Length  Slot  Name   Signature
   0      7      0    $this       Lscala/Function2;


public static scala.Function1 curried$mcZII$sp(scala.Function2);
  Signature: (Lscala/Function2;)Lscala/Function1;
  Code:
   Stack=1, Locals=1, Args_size=1
	aload_0
	invokeinterface	InterfaceMethod scala/Function2.curried:()Lscala/Function1;
	areturn
  Labels:
  LocalVariableTable: 
   Start  Length  Slot  Name   Signature
   0      7      0    $this       Lscala/Function2;


public static scala.Function1 curried$mcIII$sp(scala.Function2);
  Signature: (Lscala/Function2;)Lscala/Function1;
  Code:
   Stack=1, Locals=1, Args_size=1
	aload_0
	invokeinterface	InterfaceMethod scala/Function2.curried:()Lscala/Function1;
	areturn
  Labels:
  LocalVariableTable: 
   Start  Length  Slot  Name   Signature
   0      7      0    $this       Lscala/Function2;


public static scala.Function1 curried$mcLII$sp(scala.Function2);
  Signature: (Lscala/Function2;)Lscala/Function1;
  Code:
   Stack=1, Locals=1, Args_size=1
	aload_0
	invokeinterface	InterfaceMethod scala/Function2.curried:()Lscala/Function1;
	areturn
  Labels:
  LocalVariableTable: 
   Start  Length  Slot  Name   Signature
   0      7      0    $this       Lscala/Function2;


public static scala.Function1 curried$mcDII$sp(scala.Function2);
  Signature: (Lscala/Function2;)Lscala/Function1;
  Code:
   Stack=1, Locals=1, Args_size=1
	aload_0
	invokeinterface	InterfaceMethod scala/Function2.curried:()Lscala/Function1;
	areturn
  Labels:
  LocalVariableTable: 
   Start  Length  Slot  Name   Signature
   0      7      0    $this       Lscala/Function2;


public static scala.Function1 curried$mcVIL$sp(scala.Function2);
  Signature: (Lscala/Function2;)Lscala/Function1;
  Code:
   Stack=1, Locals=1, Args_size=1
	aload_0
	invokeinterface	InterfaceMethod scala/Function2.curried:()Lscala/Function1;
	areturn
  Labels:
  LocalVariableTable: 
   Start  Length  Slot  Name   Signature
   0      7      0    $this       Lscala/Function2;


public static scala.Function1 curried$mcZIL$sp(scala.Function2);
  Signature: (Lscala/Function2;)Lscala/Function1;
  Code:
   Stack=1, Locals=1, Args_size=1
	aload_0
	invokeinterface	InterfaceMethod scala/Function2.curried:()Lscala/Function1;
	areturn
  Labels:
  LocalVariableTable: 
   Start  Length  Slot  Name   Signature
   0      7      0    $this       Lscala/Function2;


public static scala.Function1 curried$mcIIL$sp(scala.Function2);
  Signature: (Lscala/Function2;)Lscala/Function1;
  Code:
   Stack=1, Locals=1, Args_size=1
	aload_0
	invokeinterface	InterfaceMethod scala/Function2.curried:()Lscala/Function1;
	areturn
  Labels:
  LocalVariableTable: 
   Start  Length  Slot  Name   Signature
   0      7      0    $this       Lscala/Function2;


public static scala.Function1 curried$mcLIL$sp(scala.Function2);
  Signature: (Lscala/Function2;)Lscala/Function1;
  Code:
   Stack=1, Locals=1, Args_size=1
	aload_0
	invokeinterface	InterfaceMethod scala/Function2.curried:()Lscala/Function1;
	areturn
  Labels:
  LocalVariableTable: 
   Start  Length  Slot  Name   Signature
   0      7      0    $this       Lscala/Function2;


public static scala.Function1 curried$mcDIL$sp(scala.Function2);
  Signature: (Lscala/Function2;)Lscala/Function1;
  Code:
   Stack=1, Locals=1, Args_size=1
	aload_0
	invokeinterface	InterfaceMethod scala/Function2.curried:()Lscala/Function1;
	areturn
  Labels:
  LocalVariableTable: 
   Start  Length  Slot  Name   Signature
   0      7      0    $this       Lscala/Function2;


public static scala.Function1 curried$mcVID$sp(scala.Function2);
  Signature: (Lscala/Function2;)Lscala/Function1;
  Code:
   Stack=1, Locals=1, Args_size=1
	aload_0
	invokeinterface	InterfaceMethod scala/Function2.curried:()Lscala/Function1;
	areturn
  Labels:
  LocalVariableTable: 
   Start  Length  Slot  Name   Signature
   0      7      0    $this       Lscala/Function2;


public static scala.Function1 curried$mcZID$sp(scala.Function2);
  Signature: (Lscala/Function2;)Lscala/Function1;
  Code:
   Stack=1, Locals=1, Args_size=1
	aload_0
	invokeinterface	InterfaceMethod scala/Function2.curried:()Lscala/Function1;
	areturn
  Labels:
  LocalVariableTable: 
   Start  Length  Slot  Name   Signature
   0      7      0    $this       Lscala/Function2;


public static scala.Function1 curried$mcIID$sp(scala.Function2);
  Signature: (Lscala/Function2;)Lscala/Function1;
  Code:
   Stack=1, Locals=1, Args_size=1
	aload_0
	invokeinterface	InterfaceMethod scala/Function2.curried:()Lscala/Function1;
	areturn
  Labels:
  LocalVariableTable: 
   Start  Length  Slot  Name   Signature
   0      7      0    $this       Lscala/Function2;


public static scala.Function1 curried$mcLID$sp(scala.Function2);
  Signature: (Lscala/Function2;)Lscala/Function1;
  Code:
   Stack=1, Locals=1, Args_size=1
	aload_0
	invokeinterface	InterfaceMethod scala/Function2.curried:()Lscala/Function1;
	areturn
  Labels:
  LocalVariableTable: 
   Start  Length  Slot  Name   Signature
   0      7      0    $this       Lscala/Function2;


public static scala.Function1 curried$mcDID$sp(scala.Function2);
  Signature: (Lscala/Function2;)Lscala/Function1;
  Code:
   Stack=1, Locals=1, Args_size=1
	aload_0
	invokeinterface	InterfaceMethod scala/Function2.curried:()Lscala/Function1;
	areturn
  Labels:
  LocalVariableTable: 
   Start  Length  Slot  Name   Signature
   0      7      0    $this       Lscala/Function2;


public static scala.Function1 curried$mcVLI$sp(scala.Function2);
  Signature: (Lscala/Function2;)Lscala/Function1;
  Code:
   Stack=1, Locals=1, Args_size=1
	aload_0
	invokeinterface	InterfaceMethod scala/Function2.curried:()Lscala/Function1;
	areturn
  Labels:
  LocalVariableTable: 
   Start  Length  Slot  Name   Signature
   0      7      0    $this       Lscala/Function2;


public static scala.Function1 curried$mcZLI$sp(scala.Function2);
  Signature: (Lscala/Function2;)Lscala/Function1;
  Code:
   Stack=1, Locals=1, Args_size=1
	aload_0
	invokeinterface	InterfaceMethod scala/Function2.curried:()Lscala/Function1;
	areturn
  Labels:
  LocalVariableTable: 
   Start  Length  Slot  Name   Signature
   0      7      0    $this       Lscala/Function2;


public static scala.Function1 curried$mcILI$sp(scala.Function2);
  Signature: (Lscala/Function2;)Lscala/Function1;
  Code:
   Stack=1, Locals=1, Args_size=1
	aload_0
	invokeinterface	InterfaceMethod scala/Function2.curried:()Lscala/Function1;
	areturn
  Labels:
  LocalVariableTable: 
   Start  Length  Slot  Name   Signature
   0      7      0    $this       Lscala/Function2;


public static scala.Function1 curried$mcLLI$sp(scala.Function2);
  Signature: (Lscala/Function2;)Lscala/Function1;
  Code:
   Stack=1, Locals=1, Args_size=1
	aload_0
	invokeinterface	InterfaceMethod scala/Function2.curried:()Lscala/Function1;
	areturn
  Labels:
  LocalVariableTable: 
   Start  Length  Slot  Name   Signature
   0      7      0    $this       Lscala/Function2;


public static scala.Function1 curried$mcDLI$sp(scala.Function2);
  Signature: (Lscala/Function2;)Lscala/Function1;
  Code:
   Stack=1, Locals=1, Args_size=1
	aload_0
	invokeinterface	InterfaceMethod scala/Function2.curried:()Lscala/Function1;
	areturn
  Labels:
  LocalVariableTable: 
   Start  Length  Slot  Name   Signature
   0      7      0    $this       Lscala/Function2;


public static scala.Function1 curried$mcVLL$sp(scala.Function2);
  Signature: (Lscala/Function2;)Lscala/Function1;
  Code:
   Stack=1, Locals=1, Args_size=1
	aload_0
	invokeinterface	InterfaceMethod scala/Function2.curried:()Lscala/Function1;
	areturn
  Labels:
  LocalVariableTable: 
   Start  Length  Slot  Name   Signature
   0      7      0    $this       Lscala/Function2;


public static scala.Function1 curried$mcZLL$sp(scala.Function2);
  Signature: (Lscala/Function2;)Lscala/Function1;
  Code:
   Stack=1, Locals=1, Args_size=1
	aload_0
	invokeinterface	InterfaceMethod scala/Function2.curried:()Lscala/Function1;
	areturn
  Labels:
  LocalVariableTable: 
   Start  Length  Slot  Name   Signature
   0      7      0    $this       Lscala/Function2;


public static scala.Function1 curried$mcILL$sp(scala.Function2);
  Signature: (Lscala/Function2;)Lscala/Function1;
  Code:
   Stack=1, Locals=1, Args_size=1
	aload_0
	invokeinterface	InterfaceMethod scala/Function2.curried:()Lscala/Function1;
	areturn
  Labels:
  LocalVariableTable: 
   Start  Length  Slot  Name   Signature
   0      7      0    $this       Lscala/Function2;


public static scala.Function1 curried$mcLLL$sp(scala.Function2);
  Signature: (Lscala/Function2;)Lscala/Function1;
  Code:
   Stack=1, Locals=1, Args_size=1
	aload_0
	invokeinterface	InterfaceMethod scala/Function2.curried:()Lscala/Function1;
	areturn
  Labels:
  LocalVariableTable: 
   Start  Length  Slot  Name   Signature
   0      7      0    $this       Lscala/Function2;


public static scala.Function1 curried$mcDLL$sp(scala.Function2);
  Signature: (Lscala/Function2;)Lscala/Function1;
  Code:
   Stack=1, Locals=1, Args_size=1
	aload_0
	invokeinterface	InterfaceMethod scala/Function2.curried:()Lscala/Function1;
	areturn
  Labels:
  LocalVariableTable: 
   Start  Length  Slot  Name   Signature
   0      7      0    $this       Lscala/Function2;


public static scala.Function1 curried$mcVLD$sp(scala.Function2);
  Signature: (Lscala/Function2;)Lscala/Function1;
  Code:
   Stack=1, Locals=1, Args_size=1
	aload_0
	invokeinterface	InterfaceMethod scala/Function2.curried:()Lscala/Function1;
	areturn
  Labels:
  LocalVariableTable: 
   Start  Length  Slot  Name   Signature
   0      7      0    $this       Lscala/Function2;


public static scala.Function1 curried$mcZLD$sp(scala.Function2);
  Signature: (Lscala/Function2;)Lscala/Function1;
  Code:
   Stack=1, Locals=1, Args_size=1
	aload_0
	invokeinterface	InterfaceMethod scala/Function2.curried:()Lscala/Function1;
	areturn
  Labels:
  LocalVariableTable: 
   Start  Length  Slot  Name   Signature
   0      7      0    $this       Lscala/Function2;


public static scala.Function1 curried$mcILD$sp(scala.Function2);
  Signature: (Lscala/Function2;)Lscala/Function1;
  Code:
   Stack=1, Locals=1, Args_size=1
	aload_0
	invokeinterface	InterfaceMethod scala/Function2.curried:()Lscala/Function1;
	areturn
  Labels:
  LocalVariableTable: 
   Start  Length  Slot  Name   Signature
   0      7      0    $this       Lscala/Function2;


public static scala.Function1 curried$mcLLD$sp(scala.Function2);
  Signature: (Lscala/Function2;)Lscala/Function1;
  Code:
   Stack=1, Locals=1, Args_size=1
	aload_0
	invokeinterface	InterfaceMethod scala/Function2.curried:()Lscala/Function1;
	areturn
  Labels:
  LocalVariableTable: 
   Start  Length  Slot  Name   Signature
   0      7      0    $this       Lscala/Function2;


public static scala.Function1 curried$mcDLD$sp(scala.Function2);
  Signature: (Lscala/Function2;)Lscala/Function1;
  Code:
   Stack=1, Locals=1, Args_size=1
	aload_0
	invokeinterface	InterfaceMethod scala/Function2.curried:()Lscala/Function1;
	areturn
  Labels:
  LocalVariableTable: 
   Start  Length  Slot  Name   Signature
   0      7      0    $this       Lscala/Function2;


public static scala.Function1 curried$mcVDI$sp(scala.Function2);
  Signature: (Lscala/Function2;)Lscala/Function1;
  Code:
   Stack=1, Locals=1, Args_size=1
	aload_0
	invokeinterface	InterfaceMethod scala/Function2.curried:()Lscala/Function1;
	areturn
  Labels:
  LocalVariableTable: 
   Start  Length  Slot  Name   Signature
   0      7      0    $this       Lscala/Function2;


public static scala.Function1 curried$mcZDI$sp(scala.Function2);
  Signature: (Lscala/Function2;)Lscala/Function1;
  Code:
   Stack=1, Locals=1, Args_size=1
	aload_0
	invokeinterface	InterfaceMethod scala/Function2.curried:()Lscala/Function1;
	areturn
  Labels:
  LocalVariableTable: 
   Start  Length  Slot  Name   Signature
   0      7      0    $this       Lscala/Function2;


public static scala.Function1 curried$mcIDI$sp(scala.Function2);
  Signature: (Lscala/Function2;)Lscala/Function1;
  Code:
   Stack=1, Locals=1, Args_size=1
	aload_0
	invokeinterface	InterfaceMethod scala/Function2.curried:()Lscala/Function1;
	areturn
  Labels:
  LocalVariableTable: 
   Start  Length  Slot  Name   Signature
   0      7      0    $this       Lscala/Function2;


public static scala.Function1 curried$mcLDI$sp(scala.Function2);
  Signature: (Lscala/Function2;)Lscala/Function1;
  Code:
   Stack=1, Locals=1, Args_size=1
	aload_0
	invokeinterface	InterfaceMethod scala/Function2.curried:()Lscala/Function1;
	areturn
  Labels:
  LocalVariableTable: 
   Start  Length  Slot  Name   Signature
   0      7      0    $this       Lscala/Function2;


public static scala.Function1 curried$mcDDI$sp(scala.Function2);
  Signature: (Lscala/Function2;)Lscala/Function1;
  Code:
   Stack=1, Locals=1, Args_size=1
	aload_0
	invokeinterface	InterfaceMethod scala/Function2.curried:()Lscala/Function1;
	areturn
  Labels:
  LocalVariableTable: 
   Start  Length  Slot  Name   Signature
   0      7      0    $this       Lscala/Function2;


public static scala.Function1 curried$mcVDL$sp(scala.Function2);
  Signature: (Lscala/Function2;)Lscala/Function1;
  Code:
   Stack=1, Locals=1, Args_size=1
	aload_0
	invokeinterface	InterfaceMethod scala/Function2.curried:()Lscala/Function1;
	areturn
  Labels:
  LocalVariableTable: 
   Start  Length  Slot  Name   Signature
   0      7      0    $this       Lscala/Function2;


public static scala.Function1 curried$mcZDL$sp(scala.Function2);
  Signature: (Lscala/Function2;)Lscala/Function1;
  Code:
   Stack=1, Locals=1, Args_size=1
	aload_0
	invokeinterface	InterfaceMethod scala/Function2.curried:()Lscala/Function1;
	areturn
  Labels:
  LocalVariableTable: 
   Start  Length  Slot  Name   Signature
   0      7      0    $this       Lscala/Function2;


public static scala.Function1 curried$mcIDL$sp(scala.Function2);
  Signature: (Lscala/Function2;)Lscala/Function1;
  Code:
   Stack=1, Locals=1, Args_size=1
	aload_0
	invokeinterface	InterfaceMethod scala/Function2.curried:()Lscala/Function1;
	areturn
  Labels:
  LocalVariableTable: 
   Start  Length  Slot  Name   Signature
   0      7      0    $this       Lscala/Function2;


public static scala.Function1 curried$mcLDL$sp(scala.Function2);
  Signature: (Lscala/Function2;)Lscala/Function1;
  Code:
   Stack=1, Locals=1, Args_size=1
	aload_0
	invokeinterface	InterfaceMethod scala/Function2.curried:()Lscala/Function1;
	areturn
  Labels:
  LocalVariableTable: 
   Start  Length  Slot  Name   Signature
   0      7      0    $this       Lscala/Function2;


public static scala.Function1 curried$mcDDL$sp(scala.Function2);
  Signature: (Lscala/Function2;)Lscala/Function1;
  Code:
   Stack=1, Locals=1, Args_size=1
	aload_0
	invokeinterface	InterfaceMethod scala/Function2.curried:()Lscala/Function1;
	areturn
  Labels:
  LocalVariableTable: 
   Start  Length  Slot  Name   Signature
   0      7      0    $this       Lscala/Function2;


public static scala.Function1 curried$mcVDD$sp(scala.Function2);
  Signature: (Lscala/Function2;)Lscala/Function1;
  Code:
   Stack=1, Locals=1, Args_size=1
	aload_0
	invokeinterface	InterfaceMethod scala/Function2.curried:()Lscala/Function1;
	areturn
  Labels:
  LocalVariableTable: 
   Start  Length  Slot  Name   Signature
   0      7      0    $this       Lscala/Function2;


public static scala.Function1 curried$mcZDD$sp(scala.Function2);
  Signature: (Lscala/Function2;)Lscala/Function1;
  Code:
   Stack=1, Locals=1, Args_size=1
	aload_0
	invokeinterface	InterfaceMethod scala/Function2.curried:()Lscala/Function1;
	areturn
  Labels:
  LocalVariableTable: 
   Start  Length  Slot  Name   Signature
   0      7      0    $this       Lscala/Function2;


public static scala.Function1 curried$mcIDD$sp(scala.Function2);
  Signature: (Lscala/Function2;)Lscala/Function1;
  Code:
   Stack=1, Locals=1, Args_size=1
	aload_0
	invokeinterface	InterfaceMethod scala/Function2.curried:()Lscala/Function1;
	areturn
  Labels:
  LocalVariableTable: 
   Start  Length  Slot  Name   Signature
   0      7      0    $this       Lscala/Function2;


public static scala.Function1 curried$mcLDD$sp(scala.Function2);
  Signature: (Lscala/Function2;)Lscala/Function1;
  Code:
   Stack=1, Locals=1, Args_size=1
	aload_0
	invokeinterface	InterfaceMethod scala/Function2.curried:()Lscala/Function1;
	areturn
  Labels:
  LocalVariableTable: 
   Start  Length  Slot  Name   Signature
   0      7      0    $this       Lscala/Function2;


public static scala.Function1 curried$mcDDD$sp(scala.Function2);
  Signature: (Lscala/Function2;)Lscala/Function1;
  Code:
   Stack=1, Locals=1, Args_size=1
	aload_0
	invokeinterface	InterfaceMethod scala/Function2.curried:()Lscala/Function1;
	areturn
  Labels:
  LocalVariableTable: 
   Start  Length  Slot  Name   Signature
   0      7      0    $this       Lscala/Function2;


public static scala.Function1 curry$mcVII$sp(scala.Function2);
  Signature: (Lscala/Function2;)Lscala/Function1;
  Code:
   Stack=1, Locals=1, Args_size=1
	aload_0
	invokeinterface	InterfaceMethod scala/Function2.curry:()Lscala/Function1;
	areturn
  Labels:
  LocalVariableTable: 
   Start  Length  Slot  Name   Signature
   0      7      0    $this       Lscala/Function2;

  Deprecated: true

public static scala.Function1 curry$mcZII$sp(scala.Function2);
  Signature: (Lscala/Function2;)Lscala/Function1;
  Code:
   Stack=1, Locals=1, Args_size=1
	aload_0
	invokeinterface	InterfaceMethod scala/Function2.curry:()Lscala/Function1;
	areturn
  Labels:
  LocalVariableTable: 
   Start  Length  Slot  Name   Signature
   0      7      0    $this       Lscala/Function2;

  Deprecated: true

public static scala.Function1 curry$mcIII$sp(scala.Function2);
  Signature: (Lscala/Function2;)Lscala/Function1;
  Code:
   Stack=1, Locals=1, Args_size=1
	aload_0
	invokeinterface	InterfaceMethod scala/Function2.curry:()Lscala/Function1;
	areturn
  Labels:
  LocalVariableTable: 
   Start  Length  Slot  Name   Signature
   0      7      0    $this       Lscala/Function2;

  Deprecated: true

public static scala.Function1 curry$mcLII$sp(scala.Function2);
  Signature: (Lscala/Function2;)Lscala/Function1;
  Code:
   Stack=1, Locals=1, Args_size=1
	aload_0
	invokeinterface	InterfaceMethod scala/Function2.curry:()Lscala/Function1;
	areturn
  Labels:
  LocalVariableTable: 
   Start  Length  Slot  Name   Signature
   0      7      0    $this       Lscala/Function2;

  Deprecated: true

public static scala.Function1 curry$mcDII$sp(scala.Function2);
  Signature: (Lscala/Function2;)Lscala/Function1;
  Code:
   Stack=1, Locals=1, Args_size=1
	aload_0
	invokeinterface	InterfaceMethod scala/Function2.curry:()Lscala/Function1;
	areturn
  Labels:
  LocalVariableTable: 
   Start  Length  Slot  Name   Signature
   0      7      0    $this       Lscala/Function2;

  Deprecated: true

public static scala.Function1 curry$mcVIL$sp(scala.Function2);
  Signature: (Lscala/Function2;)Lscala/Function1;
  Code:
   Stack=1, Locals=1, Args_size=1
	aload_0
	invokeinterface	InterfaceMethod scala/Function2.curry:()Lscala/Function1;
	areturn
  Labels:
  LocalVariableTable: 
   Start  Length  Slot  Name   Signature
   0      7      0    $this       Lscala/Function2;

  Deprecated: true

public static scala.Function1 curry$mcZIL$sp(scala.Function2);
  Signature: (Lscala/Function2;)Lscala/Function1;
  Code:
   Stack=1, Locals=1, Args_size=1
	aload_0
	invokeinterface	InterfaceMethod scala/Function2.curry:()Lscala/Function1;
	areturn
  Labels:
  LocalVariableTable: 
   Start  Length  Slot  Name   Signature
   0      7      0    $this       Lscala/Function2;

  Deprecated: true

public static scala.Function1 curry$mcIIL$sp(scala.Function2);
  Signature: (Lscala/Function2;)Lscala/Function1;
  Code:
   Stack=1, Locals=1, Args_size=1
	aload_0
	invokeinterface	InterfaceMethod scala/Function2.curry:()Lscala/Function1;
	areturn
  Labels:
  LocalVariableTable: 
   Start  Length  Slot  Name   Signature
   0      7      0    $this       Lscala/Function2;

  Deprecated: true

public static scala.Function1 curry$mcLIL$sp(scala.Function2);
  Signature: (Lscala/Function2;)Lscala/Function1;
  Code:
   Stack=1, Locals=1, Args_size=1
	aload_0
	invokeinterface	InterfaceMethod scala/Function2.curry:()Lscala/Function1;
	areturn
  Labels:
  LocalVariableTable: 
   Start  Length  Slot  Name   Signature
   0      7      0    $this       Lscala/Function2;

  Deprecated: true

public static scala.Function1 curry$mcDIL$sp(scala.Function2);
  Signature: (Lscala/Function2;)Lscala/Function1;
  Code:
   Stack=1, Locals=1, Args_size=1
	aload_0
	invokeinterface	InterfaceMethod scala/Function2.curry:()Lscala/Function1;
	areturn
  Labels:
  LocalVariableTable: 
   Start  Length  Slot  Name   Signature
   0      7      0    $this       Lscala/Function2;

  Deprecated: true

public static scala.Function1 curry$mcVID$sp(scala.Function2);
  Signature: (Lscala/Function2;)Lscala/Function1;
  Code:
   Stack=1, Locals=1, Args_size=1
	aload_0
	invokeinterface	InterfaceMethod scala/Function2.curry:()Lscala/Function1;
	areturn
  Labels:
  LocalVariableTable: 
   Start  Length  Slot  Name   Signature
   0      7      0    $this       Lscala/Function2;

  Deprecated: true

public static scala.Function1 curry$mcZID$sp(scala.Function2);
  Signature: (Lscala/Function2;)Lscala/Function1;
  Code:
   Stack=1, Locals=1, Args_size=1
	aload_0
	invokeinterface	InterfaceMethod scala/Function2.curry:()Lscala/Function1;
	areturn
  Labels:
  LocalVariableTable: 
   Start  Length  Slot  Name   Signature
   0      7      0    $this       Lscala/Function2;

  Deprecated: true

public static scala.Function1 curry$mcIID$sp(scala.Function2);
  Signature: (Lscala/Function2;)Lscala/Function1;
  Code:
   Stack=1, Locals=1, Args_size=1
	aload_0
	invokeinterface	InterfaceMethod scala/Function2.curry:()Lscala/Function1;
	areturn
  Labels:
  LocalVariableTable: 
   Start  Length  Slot  Name   Signature
   0      7      0    $this       Lscala/Function2;

  Deprecated: true

public static scala.Function1 curry$mcLID$sp(scala.Function2);
  Signature: (Lscala/Function2;)Lscala/Function1;
  Code:
   Stack=1, Locals=1, Args_size=1
	aload_0
	invokeinterface	InterfaceMethod scala/Function2.curry:()Lscala/Function1;
	areturn
  Labels:
  LocalVariableTable: 
   Start  Length  Slot  Name   Signature
   0      7      0    $this       Lscala/Function2;

  Deprecated: true

public static scala.Function1 curry$mcDID$sp(scala.Function2);
  Signature: (Lscala/Function2;)Lscala/Function1;
  Code:
   Stack=1, Locals=1, Args_size=1
	aload_0
	invokeinterface	InterfaceMethod scala/Function2.curry:()Lscala/Function1;
	areturn
  Labels:
  LocalVariableTable: 
   Start  Length  Slot  Name   Signature
   0      7      0    $this       Lscala/Function2;

  Deprecated: true

public static scala.Function1 curry$mcVLI$sp(scala.Function2);
  Signature: (Lscala/Function2;)Lscala/Function1;
  Code:
   Stack=1, Locals=1, Args_size=1
	aload_0
	invokeinterface	InterfaceMethod scala/Function2.curry:()Lscala/Function1;
	areturn
  Labels:
  LocalVariableTable: 
   Start  Length  Slot  Name   Signature
   0      7      0    $this       Lscala/Function2;

  Deprecated: true

public static scala.Function1 curry$mcZLI$sp(scala.Function2);
  Signature: (Lscala/Function2;)Lscala/Function1;
  Code:
   Stack=1, Locals=1, Args_size=1
	aload_0
	invokeinterface	InterfaceMethod scala/Function2.curry:()Lscala/Function1;
	areturn
  Labels:
  LocalVariableTable: 
   Start  Length  Slot  Name   Signature
   0      7      0    $this       Lscala/Function2;

  Deprecated: true

public static scala.Function1 curry$mcILI$sp(scala.Function2);
  Signature: (Lscala/Function2;)Lscala/Function1;
  Code:
   Stack=1, Locals=1, Args_size=1
	aload_0
	invokeinterface	InterfaceMethod scala/Function2.curry:()Lscala/Function1;
	areturn
  Labels:
  LocalVariableTable: 
   Start  Length  Slot  Name   Signature
   0      7      0    $this       Lscala/Function2;

  Deprecated: true

public static scala.Function1 curry$mcLLI$sp(scala.Function2);
  Signature: (Lscala/Function2;)Lscala/Function1;
  Code:
   Stack=1, Locals=1, Args_size=1
	aload_0
	invokeinterface	InterfaceMethod scala/Function2.curry:()Lscala/Function1;
	areturn
  Labels:
  LocalVariableTable: 
   Start  Length  Slot  Name   Signature
   0      7      0    $this       Lscala/Function2;

  Deprecated: true

public static scala.Function1 curry$mcDLI$sp(scala.Function2);
  Signature: (Lscala/Function2;)Lscala/Function1;
  Code:
   Stack=1, Locals=1, Args_size=1
	aload_0
	invokeinterface	InterfaceMethod scala/Function2.curry:()Lscala/Function1;
	areturn
  Labels:
  LocalVariableTable: 
   Start  Length  Slot  Name   Signature
   0      7      0    $this       Lscala/Function2;

  Deprecated: true

public static scala.Function1 curry$mcVLL$sp(scala.Function2);
  Signature: (Lscala/Function2;)Lscala/Function1;
  Code:
   Stack=1, Locals=1, Args_size=1
	aload_0
	invokeinterface	InterfaceMethod scala/Function2.curry:()Lscala/Function1;
	areturn
  Labels:
  LocalVariableTable: 
   Start  Length  Slot  Name   Signature
   0      7      0    $this       Lscala/Function2;

  Deprecated: true

public static scala.Function1 curry$mcZLL$sp(scala.Function2);
  Signature: (Lscala/Function2;)Lscala/Function1;
  Code:
   Stack=1, Locals=1, Args_size=1
	aload_0
	invokeinterface	InterfaceMethod scala/Function2.curry:()Lscala/Function1;
	areturn
  Labels:
  LocalVariableTable: 
   Start  Length  Slot  Name   Signature
   0      7      0    $this       Lscala/Function2;

  Deprecated: true

public static scala.Function1 curry$mcILL$sp(scala.Function2);
  Signature: (Lscala/Function2;)Lscala/Function1;
  Code:
   Stack=1, Locals=1, Args_size=1
	aload_0
	invokeinterface	InterfaceMethod scala/Function2.curry:()Lscala/Function1;
	areturn
  Labels:
  LocalVariableTable: 
   Start  Length  Slot  Name   Signature
   0      7      0    $this       Lscala/Function2;

  Deprecated: true

public static scala.Function1 curry$mcLLL$sp(scala.Function2);
  Signature: (Lscala/Function2;)Lscala/Function1;
  Code:
   Stack=1, Locals=1, Args_size=1
	aload_0
	invokeinterface	InterfaceMethod scala/Function2.curry:()Lscala/Function1;
	areturn
  Labels:
  LocalVariableTable: 
   Start  Length  Slot  Name   Signature
   0      7      0    $this       Lscala/Function2;

  Deprecated: true

public static scala.Function1 curry$mcDLL$sp(scala.Function2);
  Signature: (Lscala/Function2;)Lscala/Function1;
  Code:
   Stack=1, Locals=1, Args_size=1
	aload_0
	invokeinterface	InterfaceMethod scala/Function2.curry:()Lscala/Function1;
	areturn
  Labels:
  LocalVariableTable: 
   Start  Length  Slot  Name   Signature
   0      7      0    $this       Lscala/Function2;

  Deprecated: true

public static scala.Function1 curry$mcVLD$sp(scala.Function2);
  Signature: (Lscala/Function2;)Lscala/Function1;
  Code:
   Stack=1, Locals=1, Args_size=1
	aload_0
	invokeinterface	InterfaceMethod scala/Function2.curry:()Lscala/Function1;
	areturn
  Labels:
  LocalVariableTable: 
   Start  Length  Slot  Name   Signature
   0      7      0    $this       Lscala/Function2;

  Deprecated: true

public static scala.Function1 curry$mcZLD$sp(scala.Function2);
  Signature: (Lscala/Function2;)Lscala/Function1;
  Code:
   Stack=1, Locals=1, Args_size=1
	aload_0
	invokeinterface	InterfaceMethod scala/Function2.curry:()Lscala/Function1;
	areturn
  Labels:
  LocalVariableTable: 
   Start  Length  Slot  Name   Signature
   0      7      0    $this       Lscala/Function2;

  Deprecated: true

public static scala.Function1 curry$mcILD$sp(scala.Function2);
  Signature: (Lscala/Function2;)Lscala/Function1;
  Code:
   Stack=1, Locals=1, Args_size=1
	aload_0
	invokeinterface	InterfaceMethod scala/Function2.curry:()Lscala/Function1;
	areturn
  Labels:
  LocalVariableTable: 
   Start  Length  Slot  Name   Signature
   0      7      0    $this       Lscala/Function2;

  Deprecated: true

public static scala.Function1 curry$mcLLD$sp(scala.Function2);
  Signature: (Lscala/Function2;)Lscala/Function1;
  Code:
   Stack=1, Locals=1, Args_size=1
	aload_0
	invokeinterface	InterfaceMethod scala/Function2.curry:()Lscala/Function1;
	areturn
  Labels:
  LocalVariableTable: 
   Start  Length  Slot  Name   Signature
   0      7      0    $this       Lscala/Function2;

  Deprecated: true

public static scala.Function1 curry$mcDLD$sp(scala.Function2);
  Signature: (Lscala/Function2;)Lscala/Function1;
  Code:
   Stack=1, Locals=1, Args_size=1
	aload_0
	invokeinterface	InterfaceMethod scala/Function2.curry:()Lscala/Function1;
	areturn
  Labels:
  LocalVariableTable: 
   Start  Length  Slot  Name   Signature
   0      7      0    $this       Lscala/Function2;

  Deprecated: true

public static scala.Function1 curry$mcVDI$sp(scala.Function2);
  Signature: (Lscala/Function2;)Lscala/Function1;
  Code:
   Stack=1, Locals=1, Args_size=1
	aload_0
	invokeinterface	InterfaceMethod scala/Function2.curry:()Lscala/Function1;
	areturn
  Labels:
  LocalVariableTable: 
   Start  Length  Slot  Name   Signature
   0      7      0    $this       Lscala/Function2;

  Deprecated: true

public static scala.Function1 curry$mcZDI$sp(scala.Function2);
  Signature: (Lscala/Function2;)Lscala/Function1;
  Code:
   Stack=1, Locals=1, Args_size=1
	aload_0
	invokeinterface	InterfaceMethod scala/Function2.curry:()Lscala/Function1;
	areturn
  Labels:
  LocalVariableTable: 
   Start  Length  Slot  Name   Signature
   0      7      0    $this       Lscala/Function2;

  Deprecated: true

public static scala.Function1 curry$mcIDI$sp(scala.Function2);
  Signature: (Lscala/Function2;)Lscala/Function1;
  Code:
   Stack=1, Locals=1, Args_size=1
	aload_0
	invokeinterface	InterfaceMethod scala/Function2.curry:()Lscala/Function1;
	areturn
  Labels:
  LocalVariableTable: 
   Start  Length  Slot  Name   Signature
   0      7      0    $this       Lscala/Function2;

  Deprecated: true

public static scala.Function1 curry$mcLDI$sp(scala.Function2);
  Signature: (Lscala/Function2;)Lscala/Function1;
  Code:
   Stack=1, Locals=1, Args_size=1
	aload_0
	invokeinterface	InterfaceMethod scala/Function2.curry:()Lscala/Function1;
	areturn
  Labels:
  LocalVariableTable: 
   Start  Length  Slot  Name   Signature
   0      7      0    $this       Lscala/Function2;

  Deprecated: true

public static scala.Function1 curry$mcDDI$sp(scala.Function2);
  Signature: (Lscala/Function2;)Lscala/Function1;
  Code:
   Stack=1, Locals=1, Args_size=1
	aload_0
	invokeinterface	InterfaceMethod scala/Function2.curry:()Lscala/Function1;
	areturn
  Labels:
  LocalVariableTable: 
   Start  Length  Slot  Name   Signature
   0      7      0    $this       Lscala/Function2;

  Deprecated: true

public static scala.Function1 curry$mcVDL$sp(scala.Function2);
  Signature: (Lscala/Function2;)Lscala/Function1;
  Code:
   Stack=1, Locals=1, Args_size=1
	aload_0
	invokeinterface	InterfaceMethod scala/Function2.curry:()Lscala/Function1;
	areturn
  Labels:
  LocalVariableTable: 
   Start  Length  Slot  Name   Signature
   0      7      0    $this       Lscala/Function2;

  Deprecated: true

public static scala.Function1 curry$mcZDL$sp(scala.Function2);
  Signature: (Lscala/Function2;)Lscala/Function1;
  Code:
   Stack=1, Locals=1, Args_size=1
	aload_0
	invokeinterface	InterfaceMethod scala/Function2.curry:()Lscala/Function1;
	areturn
  Labels:
  LocalVariableTable: 
   Start  Length  Slot  Name   Signature
   0      7      0    $this       Lscala/Function2;

  Deprecated: true

public static scala.Function1 curry$mcIDL$sp(scala.Function2);
  Signature: (Lscala/Function2;)Lscala/Function1;
  Code:
   Stack=1, Locals=1, Args_size=1
	aload_0
	invokeinterface	InterfaceMethod scala/Function2.curry:()Lscala/Function1;
	areturn
  Labels:
  LocalVariableTable: 
   Start  Length  Slot  Name   Signature
   0      7      0    $this       Lscala/Function2;

  Deprecated: true

public static scala.Function1 curry$mcLDL$sp(scala.Function2);
  Signature: (Lscala/Function2;)Lscala/Function1;
  Code:
   Stack=1, Locals=1, Args_size=1
	aload_0
	invokeinterface	InterfaceMethod scala/Function2.curry:()Lscala/Function1;
	areturn
  Labels:
  LocalVariableTable: 
   Start  Length  Slot  Name   Signature
   0      7      0    $this       Lscala/Function2;

  Deprecated: true

public static scala.Function1 curry$mcDDL$sp(scala.Function2);
  Signature: (Lscala/Function2;)Lscala/Function1;
  Code:
   Stack=1, Locals=1, Args_size=1
	aload_0
	invokeinterface	InterfaceMethod scala/Function2.curry:()Lscala/Function1;
	areturn
  Labels:
  LocalVariableTable: 
   Start  Length  Slot  Name   Signature
   0      7      0    $this       Lscala/Function2;

  Deprecated: true

public static scala.Function1 curry$mcVDD$sp(scala.Function2);
  Signature: (Lscala/Function2;)Lscala/Function1;
  Code:
   Stack=1, Locals=1, Args_size=1
	aload_0
	invokeinterface	InterfaceMethod scala/Function2.curry:()Lscala/Function1;
	areturn
  Labels:
  LocalVariableTable: 
   Start  Length  Slot  Name   Signature
   0      7      0    $this       Lscala/Function2;

  Deprecated: true

public static scala.Function1 curry$mcZDD$sp(scala.Function2);
  Signature: (Lscala/Function2;)Lscala/Function1;
  Code:
   Stack=1, Locals=1, Args_size=1
	aload_0
	invokeinterface	InterfaceMethod scala/Function2.curry:()Lscala/Function1;
	areturn
  Labels:
  LocalVariableTable: 
   Start  Length  Slot  Name   Signature
   0      7      0    $this       Lscala/Function2;

  Deprecated: true

public static scala.Function1 curry$mcIDD$sp(scala.Function2);
  Signature: (Lscala/Function2;)Lscala/Function1;
  Code:
   Stack=1, Locals=1, Args_size=1
	aload_0
	invokeinterface	InterfaceMethod scala/Function2.curry:()Lscala/Function1;
	areturn
  Labels:
  LocalVariableTable: 
   Start  Length  Slot  Name   Signature
   0      7      0    $this       Lscala/Function2;

  Deprecated: true

public static scala.Function1 curry$mcLDD$sp(scala.Function2);
  Signature: (Lscala/Function2;)Lscala/Function1;
  Code:
   Stack=1, Locals=1, Args_size=1
	aload_0
	invokeinterface	InterfaceMethod scala/Function2.curry:()Lscala/Function1;
	areturn
  Labels:
  LocalVariableTable: 
   Start  Length  Slot  Name   Signature
   0      7      0    $this       Lscala/Function2;

  Deprecated: true

public static scala.Function1 curry$mcDDD$sp(scala.Function2);
  Signature: (Lscala/Function2;)Lscala/Function1;
  Code:
   Stack=1, Locals=1, Args_size=1
	aload_0
	invokeinterface	InterfaceMethod scala/Function2.curry:()Lscala/Function1;
	areturn
  Labels:
  LocalVariableTable: 
   Start  Length  Slot  Name   Signature
   0      7      0    $this       Lscala/Function2;

  Deprecated: true

public static scala.Function1 tupled$mcVII$sp(scala.Function2);
  Signature: (Lscala/Function2;)Lscala/Function1;
  Code:
   Stack=1, Locals=1, Args_size=1
	aload_0
	invokeinterface	InterfaceMethod scala/Function2.tupled:()Lscala/Function1;
	areturn
  Labels:
  LocalVariableTable: 
   Start  Length  Slot  Name   Signature
   0      7      0    $this       Lscala/Function2;


public static scala.Function1 tupled$mcZII$sp(scala.Function2);
  Signature: (Lscala/Function2;)Lscala/Function1;
  Code:
   Stack=1, Locals=1, Args_size=1
	aload_0
	invokeinterface	InterfaceMethod scala/Function2.tupled:()Lscala/Function1;
	areturn
  Labels:
  LocalVariableTable: 
   Start  Length  Slot  Name   Signature
   0      7      0    $this       Lscala/Function2;


public static scala.Function1 tupled$mcIII$sp(scala.Function2);
  Signature: (Lscala/Function2;)Lscala/Function1;
  Code:
   Stack=1, Locals=1, Args_size=1
	aload_0
	invokeinterface	InterfaceMethod scala/Function2.tupled:()Lscala/Function1;
	areturn
  Labels:
  LocalVariableTable: 
   Start  Length  Slot  Name   Signature
   0      7      0    $this       Lscala/Function2;


public static scala.Function1 tupled$mcLII$sp(scala.Function2);
  Signature: (Lscala/Function2;)Lscala/Function1;
  Code:
   Stack=1, Locals=1, Args_size=1
	aload_0
	invokeinterface	InterfaceMethod scala/Function2.tupled:()Lscala/Function1;
	areturn
  Labels:
  LocalVariableTable: 
   Start  Length  Slot  Name   Signature
   0      7      0    $this       Lscala/Function2;


public static scala.Function1 tupled$mcDII$sp(scala.Function2);
  Signature: (Lscala/Function2;)Lscala/Function1;
  Code:
   Stack=1, Locals=1, Args_size=1
	aload_0
	invokeinterface	InterfaceMethod scala/Function2.tupled:()Lscala/Function1;
	areturn
  Labels:
  LocalVariableTable: 
   Start  Length  Slot  Name   Signature
   0      7      0    $this       Lscala/Function2;


public static scala.Function1 tupled$mcVIL$sp(scala.Function2);
  Signature: (Lscala/Function2;)Lscala/Function1;
  Code:
   Stack=1, Locals=1, Args_size=1
	aload_0
	invokeinterface	InterfaceMethod scala/Function2.tupled:()Lscala/Function1;
	areturn
  Labels:
  LocalVariableTable: 
   Start  Length  Slot  Name   Signature
   0      7      0    $this       Lscala/Function2;


public static scala.Function1 tupled$mcZIL$sp(scala.Function2);
  Signature: (Lscala/Function2;)Lscala/Function1;
  Code:
   Stack=1, Locals=1, Args_size=1
	aload_0
	invokeinterface	InterfaceMethod scala/Function2.tupled:()Lscala/Function1;
	areturn
  Labels:
  LocalVariableTable: 
   Start  Length  Slot  Name   Signature
   0      7      0    $this       Lscala/Function2;


public static scala.Function1 tupled$mcIIL$sp(scala.Function2);
  Signature: (Lscala/Function2;)Lscala/Function1;
  Code:
   Stack=1, Locals=1, Args_size=1
	aload_0
	invokeinterface	InterfaceMethod scala/Function2.tupled:()Lscala/Function1;
	areturn
  Labels:
  LocalVariableTable: 
   Start  Length  Slot  Name   Signature
   0      7      0    $this       Lscala/Function2;


public static scala.Function1 tupled$mcLIL$sp(scala.Function2);
  Signature: (Lscala/Function2;)Lscala/Function1;
  Code:
   Stack=1, Locals=1, Args_size=1
	aload_0
	invokeinterface	InterfaceMethod scala/Function2.tupled:()Lscala/Function1;
	areturn
  Labels:
  LocalVariableTable: 
   Start  Length  Slot  Name   Signature
   0      7      0    $this       Lscala/Function2;


public static scala.Function1 tupled$mcDIL$sp(scala.Function2);
  Signature: (Lscala/Function2;)Lscala/Function1;
  Code:
   Stack=1, Locals=1, Args_size=1
	aload_0
	invokeinterface	InterfaceMethod scala/Function2.tupled:()Lscala/Function1;
	areturn
  Labels:
  LocalVariableTable: 
   Start  Length  Slot  Name   Signature
   0      7      0    $this       Lscala/Function2;


public static scala.Function1 tupled$mcVID$sp(scala.Function2);
  Signature: (Lscala/Function2;)Lscala/Function1;
  Code:
   Stack=1, Locals=1, Args_size=1
	aload_0
	invokeinterface	InterfaceMethod scala/Function2.tupled:()Lscala/Function1;
	areturn
  Labels:
  LocalVariableTable: 
   Start  Length  Slot  Name   Signature
   0      7      0    $this       Lscala/Function2;


public static scala.Function1 tupled$mcZID$sp(scala.Function2);
  Signature: (Lscala/Function2;)Lscala/Function1;
  Code:
   Stack=1, Locals=1, Args_size=1
	aload_0
	invokeinterface	InterfaceMethod scala/Function2.tupled:()Lscala/Function1;
	areturn
  Labels:
  LocalVariableTable: 
   Start  Length  Slot  Name   Signature
   0      7      0    $this       Lscala/Function2;


public static scala.Function1 tupled$mcIID$sp(scala.Function2);
  Signature: (Lscala/Function2;)Lscala/Function1;
  Code:
   Stack=1, Locals=1, Args_size=1
	aload_0
	invokeinterface	InterfaceMethod scala/Function2.tupled:()Lscala/Function1;
	areturn
  Labels:
  LocalVariableTable: 
   Start  Length  Slot  Name   Signature
   0      7      0    $this       Lscala/Function2;


public static scala.Function1 tupled$mcLID$sp(scala.Function2);
  Signature: (Lscala/Function2;)Lscala/Function1;
  Code:
   Stack=1, Locals=1, Args_size=1
	aload_0
	invokeinterface	InterfaceMethod scala/Function2.tupled:()Lscala/Function1;
	areturn
  Labels:
  LocalVariableTable: 
   Start  Length  Slot  Name   Signature
   0      7      0    $this       Lscala/Function2;


public static scala.Function1 tupled$mcDID$sp(scala.Function2);
  Signature: (Lscala/Function2;)Lscala/Function1;
  Code:
   Stack=1, Locals=1, Args_size=1
	aload_0
	invokeinterface	InterfaceMethod scala/Function2.tupled:()Lscala/Function1;
	areturn
  Labels:
  LocalVariableTable: 
   Start  Length  Slot  Name   Signature
   0      7      0    $this       Lscala/Function2;


public static scala.Function1 tupled$mcVLI$sp(scala.Function2);
  Signature: (Lscala/Function2;)Lscala/Function1;
  Code:
   Stack=1, Locals=1, Args_size=1
	aload_0
	invokeinterface	InterfaceMethod scala/Function2.tupled:()Lscala/Function1;
	areturn
  Labels:
  LocalVariableTable: 
   Start  Length  Slot  Name   Signature
   0      7      0    $this       Lscala/Function2;


public static scala.Function1 tupled$mcZLI$sp(scala.Function2);
  Signature: (Lscala/Function2;)Lscala/Function1;
  Code:
   Stack=1, Locals=1, Args_size=1
	aload_0
	invokeinterface	InterfaceMethod scala/Function2.tupled:()Lscala/Function1;
	areturn
  Labels:
  LocalVariableTable: 
   Start  Length  Slot  Name   Signature
   0      7      0    $this       Lscala/Function2;


public static scala.Function1 tupled$mcILI$sp(scala.Function2);
  Signature: (Lscala/Function2;)Lscala/Function1;
  Code:
   Stack=1, Locals=1, Args_size=1
	aload_0
	invokeinterface	InterfaceMethod scala/Function2.tupled:()Lscala/Function1;
	areturn
  Labels:
  LocalVariableTable: 
   Start  Length  Slot  Name   Signature
   0      7      0    $this       Lscala/Function2;


public static scala.Function1 tupled$mcLLI$sp(scala.Function2);
  Signature: (Lscala/Function2;)Lscala/Function1;
  Code:
   Stack=1, Locals=1, Args_size=1
	aload_0
	invokeinterface	InterfaceMethod scala/Function2.tupled:()Lscala/Function1;
	areturn
  Labels:
  LocalVariableTable: 
   Start  Length  Slot  Name   Signature
   0      7      0    $this       Lscala/Function2;


public static scala.Function1 tupled$mcDLI$sp(scala.Function2);
  Signature: (Lscala/Function2;)Lscala/Function1;
  Code:
   Stack=1, Locals=1, Args_size=1
	aload_0
	invokeinterface	InterfaceMethod scala/Function2.tupled:()Lscala/Function1;
	areturn
  Labels:
  LocalVariableTable: 
   Start  Length  Slot  Name   Signature
   0      7      0    $this       Lscala/Function2;


public static scala.Function1 tupled$mcVLL$sp(scala.Function2);
  Signature: (Lscala/Function2;)Lscala/Function1;
  Code:
   Stack=1, Locals=1, Args_size=1
	aload_0
	invokeinterface	InterfaceMethod scala/Function2.tupled:()Lscala/Function1;
	areturn
  Labels:
  LocalVariableTable: 
   Start  Length  Slot  Name   Signature
   0      7      0    $this       Lscala/Function2;


public static scala.Function1 tupled$mcZLL$sp(scala.Function2);
  Signature: (Lscala/Function2;)Lscala/Function1;
  Code:
   Stack=1, Locals=1, Args_size=1
	aload_0
	invokeinterface	InterfaceMethod scala/Function2.tupled:()Lscala/Function1;
	areturn
  Labels:
  LocalVariableTable: 
   Start  Length  Slot  Name   Signature
   0      7      0    $this       Lscala/Function2;


public static scala.Function1 tupled$mcILL$sp(scala.Function2);
  Signature: (Lscala/Function2;)Lscala/Function1;
  Code:
   Stack=1, Locals=1, Args_size=1
	aload_0
	invokeinterface	InterfaceMethod scala/Function2.tupled:()Lscala/Function1;
	areturn
  Labels:
  LocalVariableTable: 
   Start  Length  Slot  Name   Signature
   0      7      0    $this       Lscala/Function2;


public static scala.Function1 tupled$mcLLL$sp(scala.Function2);
  Signature: (Lscala/Function2;)Lscala/Function1;
  Code:
   Stack=1, Locals=1, Args_size=1
	aload_0
	invokeinterface	InterfaceMethod scala/Function2.tupled:()Lscala/Function1;
	areturn
  Labels:
  LocalVariableTable: 
   Start  Length  Slot  Name   Signature
   0      7      0    $this       Lscala/Function2;


public static scala.Function1 tupled$mcDLL$sp(scala.Function2);
  Signature: (Lscala/Function2;)Lscala/Function1;
  Code:
   Stack=1, Locals=1, Args_size=1
	aload_0
	invokeinterface	InterfaceMethod scala/Function2.tupled:()Lscala/Function1;
	areturn
  Labels:
  LocalVariableTable: 
   Start  Length  Slot  Name   Signature
   0      7      0    $this       Lscala/Function2;


public static scala.Function1 tupled$mcVLD$sp(scala.Function2);
  Signature: (Lscala/Function2;)Lscala/Function1;
  Code:
   Stack=1, Locals=1, Args_size=1
	aload_0
	invokeinterface	InterfaceMethod scala/Function2.tupled:()Lscala/Function1;
	areturn
  Labels:
  LocalVariableTable: 
   Start  Length  Slot  Name   Signature
   0      7      0    $this       Lscala/Function2;


public static scala.Function1 tupled$mcZLD$sp(scala.Function2);
  Signature: (Lscala/Function2;)Lscala/Function1;
  Code:
   Stack=1, Locals=1, Args_size=1
	aload_0
	invokeinterface	InterfaceMethod scala/Function2.tupled:()Lscala/Function1;
	areturn
  Labels:
  LocalVariableTable: 
   Start  Length  Slot  Name   Signature
   0      7      0    $this       Lscala/Function2;


public static scala.Function1 tupled$mcILD$sp(scala.Function2);
  Signature: (Lscala/Function2;)Lscala/Function1;
  Code:
   Stack=1, Locals=1, Args_size=1
	aload_0
	invokeinterface	InterfaceMethod scala/Function2.tupled:()Lscala/Function1;
	areturn
  Labels:
  LocalVariableTable: 
   Start  Length  Slot  Name   Signature
   0      7      0    $this       Lscala/Function2;


public static scala.Function1 tupled$mcLLD$sp(scala.Function2);
  Signature: (Lscala/Function2;)Lscala/Function1;
  Code:
   Stack=1, Locals=1, Args_size=1
	aload_0
	invokeinterface	InterfaceMethod scala/Function2.tupled:()Lscala/Function1;
	areturn
  Labels:
  LocalVariableTable: 
   Start  Length  Slot  Name   Signature
   0      7      0    $this       Lscala/Function2;


public static scala.Function1 tupled$mcDLD$sp(scala.Function2);
  Signature: (Lscala/Function2;)Lscala/Function1;
  Code:
   Stack=1, Locals=1, Args_size=1
	aload_0
	invokeinterface	InterfaceMethod scala/Function2.tupled:()Lscala/Function1;
	areturn
  Labels:
  LocalVariableTable: 
   Start  Length  Slot  Name   Signature
   0      7      0    $this       Lscala/Function2;


public static scala.Function1 tupled$mcVDI$sp(scala.Function2);
  Signature: (Lscala/Function2;)Lscala/Function1;
  Code:
   Stack=1, Locals=1, Args_size=1
	aload_0
	invokeinterface	InterfaceMethod scala/Function2.tupled:()Lscala/Function1;
	areturn
  Labels:
  LocalVariableTable: 
   Start  Length  Slot  Name   Signature
   0      7      0    $this       Lscala/Function2;


public static scala.Function1 tupled$mcZDI$sp(scala.Function2);
  Signature: (Lscala/Function2;)Lscala/Function1;
  Code:
   Stack=1, Locals=1, Args_size=1
	aload_0
	invokeinterface	InterfaceMethod scala/Function2.tupled:()Lscala/Function1;
	areturn
  Labels:
  LocalVariableTable: 
   Start  Length  Slot  Name   Signature
   0      7      0    $this       Lscala/Function2;


public static scala.Function1 tupled$mcIDI$sp(scala.Function2);
  Signature: (Lscala/Function2;)Lscala/Function1;
  Code:
   Stack=1, Locals=1, Args_size=1
	aload_0
	invokeinterface	InterfaceMethod scala/Function2.tupled:()Lscala/Function1;
	areturn
  Labels:
  LocalVariableTable: 
   Start  Length  Slot  Name   Signature
   0      7      0    $this       Lscala/Function2;


public static scala.Function1 tupled$mcLDI$sp(scala.Function2);
  Signature: (Lscala/Function2;)Lscala/Function1;
  Code:
   Stack=1, Locals=1, Args_size=1
	aload_0
	invokeinterface	InterfaceMethod scala/Function2.tupled:()Lscala/Function1;
	areturn
  Labels:
  LocalVariableTable: 
   Start  Length  Slot  Name   Signature
   0      7      0    $this       Lscala/Function2;


public static scala.Function1 tupled$mcDDI$sp(scala.Function2);
  Signature: (Lscala/Function2;)Lscala/Function1;
  Code:
   Stack=1, Locals=1, Args_size=1
	aload_0
	invokeinterface	InterfaceMethod scala/Function2.tupled:()Lscala/Function1;
	areturn
  Labels:
  LocalVariableTable: 
   Start  Length  Slot  Name   Signature
   0      7      0    $this       Lscala/Function2;


public static scala.Function1 tupled$mcVDL$sp(scala.Function2);
  Signature: (Lscala/Function2;)Lscala/Function1;
  Code:
   Stack=1, Locals=1, Args_size=1
	aload_0
	invokeinterface	InterfaceMethod scala/Function2.tupled:()Lscala/Function1;
	areturn
  Labels:
  LocalVariableTable: 
   Start  Length  Slot  Name   Signature
   0      7      0    $this       Lscala/Function2;


public static scala.Function1 tupled$mcZDL$sp(scala.Function2);
  Signature: (Lscala/Function2;)Lscala/Function1;
  Code:
   Stack=1, Locals=1, Args_size=1
	aload_0
	invokeinterface	InterfaceMethod scala/Function2.tupled:()Lscala/Function1;
	areturn
  Labels:
  LocalVariableTable: 
   Start  Length  Slot  Name   Signature
   0      7      0    $this       Lscala/Function2;


public static scala.Function1 tupled$mcIDL$sp(scala.Function2);
  Signature: (Lscala/Function2;)Lscala/Function1;
  Code:
   Stack=1, Locals=1, Args_size=1
	aload_0
	invokeinterface	InterfaceMethod scala/Function2.tupled:()Lscala/Function1;
	areturn
  Labels:
  LocalVariableTable: 
   Start  Length  Slot  Name   Signature
   0      7      0    $this       Lscala/Function2;


public static scala.Function1 tupled$mcLDL$sp(scala.Function2);
  Signature: (Lscala/Function2;)Lscala/Function1;
  Code:
   Stack=1, Locals=1, Args_size=1
	aload_0
	invokeinterface	InterfaceMethod scala/Function2.tupled:()Lscala/Function1;
	areturn
  Labels:
  LocalVariableTable: 
   Start  Length  Slot  Name   Signature
   0      7      0    $this       Lscala/Function2;


public static scala.Function1 tupled$mcDDL$sp(scala.Function2);
  Signature: (Lscala/Function2;)Lscala/Function1;
  Code:
   Stack=1, Locals=1, Args_size=1
	aload_0
	invokeinterface	InterfaceMethod scala/Function2.tupled:()Lscala/Function1;
	areturn
  Labels:
  LocalVariableTable: 
   Start  Length  Slot  Name   Signature
   0      7      0    $this       Lscala/Function2;


public static scala.Function1 tupled$mcVDD$sp(scala.Function2);
  Signature: (Lscala/Function2;)Lscala/Function1;
  Code:
   Stack=1, Locals=1, Args_size=1
	aload_0
	invokeinterface	InterfaceMethod scala/Function2.tupled:()Lscala/Function1;
	areturn
  Labels:
  LocalVariableTable: 
   Start  Length  Slot  Name   Signature
   0      7      0    $this       Lscala/Function2;


public static scala.Function1 tupled$mcZDD$sp(scala.Function2);
  Signature: (Lscala/Function2;)Lscala/Function1;
  Code:
   Stack=1, Locals=1, Args_size=1
	aload_0
	invokeinterface	InterfaceMethod scala/Function2.tupled:()Lscala/Function1;
	areturn
  Labels:
  LocalVariableTable: 
   Start  Length  Slot  Name   Signature
   0      7      0    $this       Lscala/Function2;


public static scala.Function1 tupled$mcIDD$sp(scala.Function2);
  Signature: (Lscala/Function2;)Lscala/Function1;
  Code:
   Stack=1, Locals=1, Args_size=1
	aload_0
	invokeinterface	InterfaceMethod scala/Function2.tupled:()Lscala/Function1;
	areturn
  Labels:
  LocalVariableTable: 
   Start  Length  Slot  Name   Signature
   0      7      0    $this       Lscala/Function2;


public static scala.Function1 tupled$mcLDD$sp(scala.Function2);
  Signature: (Lscala/Function2;)Lscala/Function1;
  Code:
   Stack=1, Locals=1, Args_size=1
	aload_0
	invokeinterface	InterfaceMethod scala/Function2.tupled:()Lscala/Function1;
	areturn
  Labels:
  LocalVariableTable: 
   Start  Length  Slot  Name   Signature
   0      7      0    $this       Lscala/Function2;


public static scala.Function1 tupled$mcDDD$sp(scala.Function2);
  Signature: (Lscala/Function2;)Lscala/Function1;
  Code:
   Stack=1, Locals=1, Args_size=1
	aload_0
	invokeinterface	InterfaceMethod scala/Function2.tupled:()Lscala/Function1;
	areturn
  Labels:
  LocalVariableTable: 
   Start  Length  Slot  Name   Signature
   0      7      0    $this       Lscala/Function2;


public static void $init$(scala.Function2);
  Signature: (Lscala/Function2;)V
  Code:
   Stack=0, Locals=1, Args_size=1
	return
  Labels:
  LocalVariableTable: 
   Start  Length  Slot  Name   Signature
   0      1      0    $this       Lscala/Function2;


}

