Compiled from "Function0.scala"
public abstract class scala.Function0$class extends java.lang.Object
  SourceFile: "Function0.scala"
  Scala: length = 0x
   
  minor version: 0
  major version: 49
  Constant pool:
Asciz	SourceFile;
Asciz	Function0.scala;
Asciz	toString;
Asciz	(Lscala/Function0;)Ljava/lang/String;;
Asciz	Code;
Asciz	<function0>;
String	<function0>
Asciz	LineNumberTable;
Asciz	$this;
Asciz	Lscala/Function0;;
Asciz	LocalVariableTable;
Asciz	apply$mcV$sp;
Asciz	(Lscala/Function0;)V;
Asciz	scala/Function0;
class	scala/Function0
Asciz	apply;
Asciz	()Ljava/lang/Object;;
NameAndType	apply:()Ljava/lang/Object;
InterfaceMethod	scala/Function0.apply:()Ljava/lang/Object;
Asciz	apply$mcZ$sp;
Asciz	(Lscala/Function0;)Z;
Asciz	scala/runtime/BoxesRunTime;
class	scala/runtime/BoxesRunTime
Asciz	unboxToBoolean;
Asciz	(Ljava/lang/Object;)Z;
NameAndType	unboxToBoolean:(Ljava/lang/Object;)Z
Method	scala/runtime/BoxesRunTime.unboxToBoolean:(Ljava/lang/Object;)Z
Asciz	apply$mcB$sp;
Asciz	(Lscala/Function0;)B;
Asciz	unboxToByte;
Asciz	(Ljava/lang/Object;)B;
NameAndType	unboxToByte:(Ljava/lang/Object;)B
Method	scala/runtime/BoxesRunTime.unboxToByte:(Ljava/lang/Object;)B
Asciz	apply$mcS$sp;
Asciz	(Lscala/Function0;)S;
Asciz	unboxToShort;
Asciz	(Ljava/lang/Object;)S;
NameAndType	unboxToShort:(Ljava/lang/Object;)S
Method	scala/runtime/BoxesRunTime.unboxToShort:(Ljava/lang/Object;)S
Asciz	apply$mcC$sp;
Asciz	(Lscala/Function0;)C;
Asciz	unboxToChar;
Asciz	(Ljava/lang/Object;)C;
NameAndType	unboxToChar:(Ljava/lang/Object;)C
Method	scala/runtime/BoxesRunTime.unboxToChar:(Ljava/lang/Object;)C
Asciz	apply$mcI$sp;
Asciz	(Lscala/Function0;)I;
Asciz	unboxToInt;
Asciz	(Ljava/lang/Object;)I;
NameAndType	unboxToInt:(Ljava/lang/Object;)I
Method	scala/runtime/BoxesRunTime.unboxToInt:(Ljava/lang/Object;)I
Asciz	apply$mcL$sp;
Asciz	(Lscala/Function0;)J;
Asciz	unboxToLong;
Asciz	(Ljava/lang/Object;)J;
NameAndType	unboxToLong:(Ljava/lang/Object;)J
Method	scala/runtime/BoxesRunTime.unboxToLong:(Ljava/lang/Object;)J
Asciz	apply$mcF$sp;
Asciz	(Lscala/Function0;)F;
Asciz	unboxToFloat;
Asciz	(Ljava/lang/Object;)F;
NameAndType	unboxToFloat:(Ljava/lang/Object;)F
Method	scala/runtime/BoxesRunTime.unboxToFloat:(Ljava/lang/Object;)F
Asciz	apply$mcD$sp;
Asciz	(Lscala/Function0;)D;
Asciz	unboxToDouble;
Asciz	(Ljava/lang/Object;)D;
NameAndType	unboxToDouble:(Ljava/lang/Object;)D
Method	scala/runtime/BoxesRunTime.unboxToDouble:(Ljava/lang/Object;)D
Asciz	$init$;
Asciz	Scala;
Asciz	scala/Function0$class;
class	scala/Function0$class
Asciz	java/lang/Object;
class	java/lang/Object

{
public static java.lang.String toString(scala.Function0);
  Signature: (Lscala/Function0;)Ljava/lang/String;
  Code:
   Stack=1, Locals=1, Args_size=1
	ldc	String <function0>
	areturn
  Labels:
  LocalVariableTable: 
   Start  Length  Slot  Name   Signature
   0      3      0    $this       Lscala/Function0;


public static void apply$mcV$sp(scala.Function0);
  Signature: (Lscala/Function0;)V
  Code:
   Stack=1, Locals=1, Args_size=1
	aload_0
	invokeinterface	InterfaceMethod scala/Function0.apply:()Ljava/lang/Object;
	pop
	return
  Labels:
  LocalVariableTable: 
   Start  Length  Slot  Name   Signature
   0      8      0    $this       Lscala/Function0;


public static boolean apply$mcZ$sp(scala.Function0);
  Signature: (Lscala/Function0;)Z
  Code:
   Stack=1, Locals=1, Args_size=1
	aload_0
	invokeinterface	InterfaceMethod scala/Function0.apply:()Ljava/lang/Object;
	invokestatic	Method scala/runtime/BoxesRunTime.unboxToBoolean:(Ljava/lang/Object;)Z
	ireturn
  Labels:
  LocalVariableTable: 
   Start  Length  Slot  Name   Signature
   0      10      0    $this       Lscala/Function0;


public static byte apply$mcB$sp(scala.Function0);
  Signature: (Lscala/Function0;)B
  Code:
   Stack=1, Locals=1, Args_size=1
	aload_0
	invokeinterface	InterfaceMethod scala/Function0.apply:()Ljava/lang/Object;
	invokestatic	Method scala/runtime/BoxesRunTime.unboxToByte:(Ljava/lang/Object;)B
	ireturn
  Labels:
  LocalVariableTable: 
   Start  Length  Slot  Name   Signature
   0      10      0    $this       Lscala/Function0;


public static short apply$mcS$sp(scala.Function0);
  Signature: (Lscala/Function0;)S
  Code:
   Stack=1, Locals=1, Args_size=1
	aload_0
	invokeinterface	InterfaceMethod scala/Function0.apply:()Ljava/lang/Object;
	invokestatic	Method scala/runtime/BoxesRunTime.unboxToShort:(Ljava/lang/Object;)S
	ireturn
  Labels:
  LocalVariableTable: 
   Start  Length  Slot  Name   Signature
   0      10      0    $this       Lscala/Function0;


public static char apply$mcC$sp(scala.Function0);
  Signature: (Lscala/Function0;)C
  Code:
   Stack=1, Locals=1, Args_size=1
	aload_0
	invokeinterface	InterfaceMethod scala/Function0.apply:()Ljava/lang/Object;
	invokestatic	Method scala/runtime/BoxesRunTime.unboxToChar:(Ljava/lang/Object;)C
	ireturn
  Labels:
  LocalVariableTable: 
   Start  Length  Slot  Name   Signature
   0      10      0    $this       Lscala/Function0;


public static int apply$mcI$sp(scala.Function0);
  Signature: (Lscala/Function0;)I
  Code:
   Stack=1, Locals=1, Args_size=1
	aload_0
	invokeinterface	InterfaceMethod scala/Function0.apply:()Ljava/lang/Object;
	invokestatic	Method scala/runtime/BoxesRunTime.unboxToInt:(Ljava/lang/Object;)I
	ireturn
  Labels:
  LocalVariableTable: 
   Start  Length  Slot  Name   Signature
   0      10      0    $this       Lscala/Function0;


public static long apply$mcL$sp(scala.Function0);
  Signature: (Lscala/Function0;)J
  Code:
   Stack=2, Locals=1, Args_size=1
	aload_0
	invokeinterface	InterfaceMethod scala/Function0.apply:()Ljava/lang/Object;
	invokestatic	Method scala/runtime/BoxesRunTime.unboxToLong:(Ljava/lang/Object;)J
	lreturn
  Labels:
  LocalVariableTable: 
   Start  Length  Slot  Name   Signature
   0      10      0    $this       Lscala/Function0;


public static float apply$mcF$sp(scala.Function0);
  Signature: (Lscala/Function0;)F
  Code:
   Stack=1, Locals=1, Args_size=1
	aload_0
	invokeinterface	InterfaceMethod scala/Function0.apply:()Ljava/lang/Object;
	invokestatic	Method scala/runtime/BoxesRunTime.unboxToFloat:(Ljava/lang/Object;)F
	freturn
  Labels:
  LocalVariableTable: 
   Start  Length  Slot  Name   Signature
   0      10      0    $this       Lscala/Function0;


public static double apply$mcD$sp(scala.Function0);
  Signature: (Lscala/Function0;)D
  Code:
   Stack=2, Locals=1, Args_size=1
	aload_0
	invokeinterface	InterfaceMethod scala/Function0.apply:()Ljava/lang/Object;
	invokestatic	Method scala/runtime/BoxesRunTime.unboxToDouble:(Ljava/lang/Object;)D
	dreturn
  Labels:
  LocalVariableTable: 
   Start  Length  Slot  Name   Signature
   0      10      0    $this       Lscala/Function0;


public static void $init$(scala.Function0);
  Signature: (Lscala/Function0;)V
  Code:
   Stack=0, Locals=1, Args_size=1
	return
  Labels:
  LocalVariableTable: 
   Start  Length  Slot  Name   Signature
   0      1      0    $this       Lscala/Function0;


}

