Compiled from "Function2.scala"
public abstract class scala.Function2$mcDII$sp$class extends java.lang.Object
  SourceFile: "Function2.scala"
  Scala: length = 0x
   
  InnerClass: 
   public final $anonfun$tupled$mcDII$sp$1=class scala/Function2$mcDII$sp$$anonfun$tupled$mcDII$sp$1 of class scala/Function2$mcDII$sp
   public final $anonfun$curried$mcDII$sp$1=class scala/Function2$mcDII$sp$$anonfun$curried$mcDII$sp$1 of class scala/Function2$mcDII$sp
  minor version: 0
  major version: 49
  Constant pool:
Asciz	SourceFile;
Asciz	Function2.scala;
Asciz	apply;
Asciz	(Lscala/Function2$mcDII$sp;II)D;
Asciz	Code;
Asciz	LineNumberTable;
Asciz	scala/Function2;
class	scala/Function2
Asciz	apply$mcDII$sp;
Asciz	(II)D;
NameAndType	apply$mcDII$sp:(II)D
InterfaceMethod	scala/Function2.apply$mcDII$sp:(II)D
Asciz	$this;
Asciz	Lscala/Function2$mcDII$sp;;
Asciz	v1;
Asciz	I;
Asciz	v2;
Asciz	LocalVariableTable;
Asciz	curried;
Asciz	(Lscala/Function2$mcDII$sp;)Lscala/Function1;;
Asciz	scala/Function2$mcDII$sp;
class	scala/Function2$mcDII$sp
Asciz	curried$mcDII$sp;
Asciz	()Lscala/Function1;;
NameAndType	curried$mcDII$sp:()Lscala/Function1;
InterfaceMethod	scala/Function2$mcDII$sp.curried$mcDII$sp:()Lscala/Function1;
Asciz	scala/Function2$mcDII$sp$$anonfun$curried$mcDII$sp$1;
class	scala/Function2$mcDII$sp$$anonfun$curried$mcDII$sp$1
Asciz	<init>;
Asciz	(Lscala/Function2$mcDII$sp;)V;
NameAndType	"<init>":(Lscala/Function2$mcDII$sp;)V
Method	scala/Function2$mcDII$sp$$anonfun$curried$mcDII$sp$1."<init>":(Lscala/Function2$mcDII$sp;)V
Asciz	curry;
Asciz	curry$mcDII$sp;
NameAndType	curry$mcDII$sp:()Lscala/Function1;
InterfaceMethod	scala/Function2$mcDII$sp.curry$mcDII$sp:()Lscala/Function1;
Asciz	Deprecated;
Asciz	tupled;
Asciz	tupled$mcDII$sp;
NameAndType	tupled$mcDII$sp:()Lscala/Function1;
InterfaceMethod	scala/Function2$mcDII$sp.tupled$mcDII$sp:()Lscala/Function1;
Asciz	scala/Function2$mcDII$sp$$anonfun$tupled$mcDII$sp$1;
class	scala/Function2$mcDII$sp$$anonfun$tupled$mcDII$sp$1
Method	scala/Function2$mcDII$sp$$anonfun$tupled$mcDII$sp$1."<init>":(Lscala/Function2$mcDII$sp;)V
Asciz	$init$;
Asciz	Scala;
Asciz	InnerClasses;
Asciz	$anonfun$tupled$mcDII$sp$1;
Asciz	$anonfun$curried$mcDII$sp$1;
Asciz	scala/Function2$mcDII$sp$class;
class	scala/Function2$mcDII$sp$class
Asciz	java/lang/Object;
class	java/lang/Object

{
public static double apply(scala.Function2$mcDII$sp, int, int);
  Signature: (Lscala/Function2$mcDII$sp;II)D
  Code:
   Stack=3, Locals=3, Args_size=3
	aload_0
	iload_1
	iload_2
	invokeinterface	InterfaceMethod scala/Function2.apply$mcDII$sp:(II)D
	dreturn
  Labels:
  LocalVariableTable: 
   Start  Length  Slot  Name   Signature
   0      9      0    $this       Lscala/Function2$mcDII$sp;
   0      9      1    v1       I
   0      9      2    v2       I


public static scala.Function1 curried(scala.Function2$mcDII$sp);
  Signature: (Lscala/Function2$mcDII$sp;)Lscala/Function1;
  Code:
   Stack=1, Locals=1, Args_size=1
	aload_0
	invokeinterface	InterfaceMethod scala/Function2$mcDII$sp.curried$mcDII$sp:()Lscala/Function1;
	areturn
  Labels:
  LocalVariableTable: 
   Start  Length  Slot  Name   Signature
   0      7      0    $this       Lscala/Function2$mcDII$sp;


public static scala.Function1 curried$mcDII$sp(scala.Function2$mcDII$sp);
  Signature: (Lscala/Function2$mcDII$sp;)Lscala/Function1;
  Code:
   Stack=3, Locals=1, Args_size=1
	new	class scala/Function2$mcDII$sp$$anonfun$curried$mcDII$sp$1
	dup
	aload_0
	invokespecial	Method scala/Function2$mcDII$sp$$anonfun$curried$mcDII$sp$1."<init>":(Lscala/Function2$mcDII$sp;)V
	areturn
  Labels:
  LocalVariableTable: 
   Start  Length  Slot  Name   Signature
   0      9      0    $this       Lscala/Function2$mcDII$sp;


public static scala.Function1 curry(scala.Function2$mcDII$sp);
  Signature: (Lscala/Function2$mcDII$sp;)Lscala/Function1;
  Code:
   Stack=1, Locals=1, Args_size=1
	aload_0
	invokeinterface	InterfaceMethod scala/Function2$mcDII$sp.curry$mcDII$sp:()Lscala/Function1;
	areturn
  Labels:
  LocalVariableTable: 
   Start  Length  Slot  Name   Signature
   0      7      0    $this       Lscala/Function2$mcDII$sp;

  Deprecated: true

public static scala.Function1 curry$mcDII$sp(scala.Function2$mcDII$sp);
  Signature: (Lscala/Function2$mcDII$sp;)Lscala/Function1;
  Code:
   Stack=1, Locals=1, Args_size=1
	aload_0
	invokeinterface	InterfaceMethod scala/Function2$mcDII$sp.curried$mcDII$sp:()Lscala/Function1;
	areturn
  Labels:
  LocalVariableTable: 
   Start  Length  Slot  Name   Signature
   0      7      0    $this       Lscala/Function2$mcDII$sp;

  Deprecated: true

public static scala.Function1 tupled(scala.Function2$mcDII$sp);
  Signature: (Lscala/Function2$mcDII$sp;)Lscala/Function1;
  Code:
   Stack=1, Locals=1, Args_size=1
	aload_0
	invokeinterface	InterfaceMethod scala/Function2$mcDII$sp.tupled$mcDII$sp:()Lscala/Function1;
	areturn
  Labels:
  LocalVariableTable: 
   Start  Length  Slot  Name   Signature
   0      7      0    $this       Lscala/Function2$mcDII$sp;


public static scala.Function1 tupled$mcDII$sp(scala.Function2$mcDII$sp);
  Signature: (Lscala/Function2$mcDII$sp;)Lscala/Function1;
  Code:
   Stack=3, Locals=1, Args_size=1
	new	class scala/Function2$mcDII$sp$$anonfun$tupled$mcDII$sp$1
	dup
	aload_0
	invokespecial	Method scala/Function2$mcDII$sp$$anonfun$tupled$mcDII$sp$1."<init>":(Lscala/Function2$mcDII$sp;)V
	areturn
  Labels:
  LocalVariableTable: 
   Start  Length  Slot  Name   Signature
   0      9      0    $this       Lscala/Function2$mcDII$sp;


public static void $init$(scala.Function2$mcDII$sp);
  Signature: (Lscala/Function2$mcDII$sp;)V
  Code:
   Stack=0, Locals=1, Args_size=1
	return
  Labels:
  LocalVariableTable: 
   Start  Length  Slot  Name   Signature
   0      1      0    $this       Lscala/Function2$mcDII$sp;


}

