Compiled from "Function2.scala"
public abstract class scala.Function2$mcZII$sp$class extends java.lang.Object
  SourceFile: "Function2.scala"
  Scala: length = 0x
   
  InnerClass: 
   public final $anonfun$tupled$mcZII$sp$1=class scala/Function2$mcZII$sp$$anonfun$tupled$mcZII$sp$1 of class scala/Function2$mcZII$sp
   public final $anonfun$curried$mcZII$sp$1=class scala/Function2$mcZII$sp$$anonfun$curried$mcZII$sp$1 of class scala/Function2$mcZII$sp
  minor version: 0
  major version: 49
  Constant pool:
Asciz	SourceFile;
Asciz	Function2.scala;
Asciz	apply;
Asciz	(Lscala/Function2$mcZII$sp;II)Z;
Asciz	Code;
Asciz	LineNumberTable;
Asciz	scala/Function2;
class	scala/Function2
Asciz	apply$mcZII$sp;
Asciz	(II)Z;
NameAndType	apply$mcZII$sp:(II)Z
InterfaceMethod	scala/Function2.apply$mcZII$sp:(II)Z
Asciz	$this;
Asciz	Lscala/Function2$mcZII$sp;;
Asciz	v1;
Asciz	I;
Asciz	v2;
Asciz	LocalVariableTable;
Asciz	curried;
Asciz	(Lscala/Function2$mcZII$sp;)Lscala/Function1;;
Asciz	scala/Function2$mcZII$sp;
class	scala/Function2$mcZII$sp
Asciz	curried$mcZII$sp;
Asciz	()Lscala/Function1;;
NameAndType	curried$mcZII$sp:()Lscala/Function1;
InterfaceMethod	scala/Function2$mcZII$sp.curried$mcZII$sp:()Lscala/Function1;
Asciz	scala/Function2$mcZII$sp$$anonfun$curried$mcZII$sp$1;
class	scala/Function2$mcZII$sp$$anonfun$curried$mcZII$sp$1
Asciz	<init>;
Asciz	(Lscala/Function2$mcZII$sp;)V;
NameAndType	"<init>":(Lscala/Function2$mcZII$sp;)V
Method	scala/Function2$mcZII$sp$$anonfun$curried$mcZII$sp$1."<init>":(Lscala/Function2$mcZII$sp;)V
Asciz	curry;
Asciz	curry$mcZII$sp;
NameAndType	curry$mcZII$sp:()Lscala/Function1;
InterfaceMethod	scala/Function2$mcZII$sp.curry$mcZII$sp:()Lscala/Function1;
Asciz	Deprecated;
Asciz	tupled;
Asciz	tupled$mcZII$sp;
NameAndType	tupled$mcZII$sp:()Lscala/Function1;
InterfaceMethod	scala/Function2$mcZII$sp.tupled$mcZII$sp:()Lscala/Function1;
Asciz	scala/Function2$mcZII$sp$$anonfun$tupled$mcZII$sp$1;
class	scala/Function2$mcZII$sp$$anonfun$tupled$mcZII$sp$1
Method	scala/Function2$mcZII$sp$$anonfun$tupled$mcZII$sp$1."<init>":(Lscala/Function2$mcZII$sp;)V
Asciz	$init$;
Asciz	Scala;
Asciz	InnerClasses;
Asciz	$anonfun$tupled$mcZII$sp$1;
Asciz	$anonfun$curried$mcZII$sp$1;
Asciz	scala/Function2$mcZII$sp$class;
class	scala/Function2$mcZII$sp$class
Asciz	java/lang/Object;
class	java/lang/Object

{
public static boolean apply(scala.Function2$mcZII$sp, int, int);
  Signature: (Lscala/Function2$mcZII$sp;II)Z
  Code:
   Stack=3, Locals=3, Args_size=3
	aload_0
	iload_1
	iload_2
	invokeinterface	InterfaceMethod scala/Function2.apply$mcZII$sp:(II)Z
	ireturn
  Labels:
  LocalVariableTable: 
   Start  Length  Slot  Name   Signature
   0      9      0    $this       Lscala/Function2$mcZII$sp;
   0      9      1    v1       I
   0      9      2    v2       I


public static scala.Function1 curried(scala.Function2$mcZII$sp);
  Signature: (Lscala/Function2$mcZII$sp;)Lscala/Function1;
  Code:
   Stack=1, Locals=1, Args_size=1
	aload_0
	invokeinterface	InterfaceMethod scala/Function2$mcZII$sp.curried$mcZII$sp:()Lscala/Function1;
	areturn
  Labels:
  LocalVariableTable: 
   Start  Length  Slot  Name   Signature
   0      7      0    $this       Lscala/Function2$mcZII$sp;


public static scala.Function1 curried$mcZII$sp(scala.Function2$mcZII$sp);
  Signature: (Lscala/Function2$mcZII$sp;)Lscala/Function1;
  Code:
   Stack=3, Locals=1, Args_size=1
	new	class scala/Function2$mcZII$sp$$anonfun$curried$mcZII$sp$1
	dup
	aload_0
	invokespecial	Method scala/Function2$mcZII$sp$$anonfun$curried$mcZII$sp$1."<init>":(Lscala/Function2$mcZII$sp;)V
	areturn
  Labels:
  LocalVariableTable: 
   Start  Length  Slot  Name   Signature
   0      9      0    $this       Lscala/Function2$mcZII$sp;


public static scala.Function1 curry(scala.Function2$mcZII$sp);
  Signature: (Lscala/Function2$mcZII$sp;)Lscala/Function1;
  Code:
   Stack=1, Locals=1, Args_size=1
	aload_0
	invokeinterface	InterfaceMethod scala/Function2$mcZII$sp.curry$mcZII$sp:()Lscala/Function1;
	areturn
  Labels:
  LocalVariableTable: 
   Start  Length  Slot  Name   Signature
   0      7      0    $this       Lscala/Function2$mcZII$sp;

  Deprecated: true

public static scala.Function1 curry$mcZII$sp(scala.Function2$mcZII$sp);
  Signature: (Lscala/Function2$mcZII$sp;)Lscala/Function1;
  Code:
   Stack=1, Locals=1, Args_size=1
	aload_0
	invokeinterface	InterfaceMethod scala/Function2$mcZII$sp.curried$mcZII$sp:()Lscala/Function1;
	areturn
  Labels:
  LocalVariableTable: 
   Start  Length  Slot  Name   Signature
   0      7      0    $this       Lscala/Function2$mcZII$sp;

  Deprecated: true

public static scala.Function1 tupled(scala.Function2$mcZII$sp);
  Signature: (Lscala/Function2$mcZII$sp;)Lscala/Function1;
  Code:
   Stack=1, Locals=1, Args_size=1
	aload_0
	invokeinterface	InterfaceMethod scala/Function2$mcZII$sp.tupled$mcZII$sp:()Lscala/Function1;
	areturn
  Labels:
  LocalVariableTable: 
   Start  Length  Slot  Name   Signature
   0      7      0    $this       Lscala/Function2$mcZII$sp;


public static scala.Function1 tupled$mcZII$sp(scala.Function2$mcZII$sp);
  Signature: (Lscala/Function2$mcZII$sp;)Lscala/Function1;
  Code:
   Stack=3, Locals=1, Args_size=1
	new	class scala/Function2$mcZII$sp$$anonfun$tupled$mcZII$sp$1
	dup
	aload_0
	invokespecial	Method scala/Function2$mcZII$sp$$anonfun$tupled$mcZII$sp$1."<init>":(Lscala/Function2$mcZII$sp;)V
	areturn
  Labels:
  LocalVariableTable: 
   Start  Length  Slot  Name   Signature
   0      9      0    $this       Lscala/Function2$mcZII$sp;


public static void $init$(scala.Function2$mcZII$sp);
  Signature: (Lscala/Function2$mcZII$sp;)V
  Code:
   Stack=0, Locals=1, Args_size=1
	return
  Labels:
  LocalVariableTable: 
   Start  Length  Slot  Name   Signature
   0      1      0    $this       Lscala/Function2$mcZII$sp;


}

