Compiled from "Function1.scala"
public abstract class scala.Function1$mcII$sp$class extends java.lang.Object
  SourceFile: "Function1.scala"
  Scala: length = 0x
   
  InnerClass: 
   public final $anonfun$andThen$mcII$sp$1=class scala/Function1$mcII$sp$$anonfun$andThen$mcII$sp$1 of class scala/Function1$mcII$sp
   public final $anonfun$compose$mcII$sp$1=class scala/Function1$mcII$sp$$anonfun$compose$mcII$sp$1 of class scala/Function1$mcII$sp
  minor version: 0
  major version: 49
  Constant pool:
Asciz	SourceFile;
Asciz	Function1.scala;
Asciz	apply;
Asciz	(Lscala/Function1$mcII$sp;I)I;
Asciz	Code;
Asciz	LineNumberTable;
Asciz	scala/Function1;
class	scala/Function1
Asciz	apply$mcII$sp;
Asciz	(I)I;
NameAndType	apply$mcII$sp:(I)I
InterfaceMethod	scala/Function1.apply$mcII$sp:(I)I
Asciz	$this;
Asciz	Lscala/Function1$mcII$sp;;
Asciz	v1;
Asciz	I;
Asciz	LocalVariableTable;
Asciz	compose;
Asciz	(Lscala/Function1$mcII$sp;Lscala/Function1;)Lscala/Function1;;
Asciz	scala/Function1$mcII$sp;
class	scala/Function1$mcII$sp
Asciz	compose$mcII$sp;
Asciz	(Lscala/Function1;)Lscala/Function1;;
NameAndType	compose$mcII$sp:(Lscala/Function1;)Lscala/Function1;
InterfaceMethod	scala/Function1$mcII$sp.compose$mcII$sp:(Lscala/Function1;)Lscala/Function1;
Asciz	g;
Asciz	Lscala/Function1;;
Asciz	scala/Function1$mcII$sp$$anonfun$compose$mcII$sp$1;
class	scala/Function1$mcII$sp$$anonfun$compose$mcII$sp$1
Asciz	<init>;
Asciz	(Lscala/Function1$mcII$sp;Lscala/Function1;)V;
NameAndType	"<init>":(Lscala/Function1$mcII$sp;Lscala/Function1;)V
Method	scala/Function1$mcII$sp$$anonfun$compose$mcII$sp$1."<init>":(Lscala/Function1$mcII$sp;Lscala/Function1;)V
Asciz	g$7;
Asciz	andThen;
Asciz	andThen$mcII$sp;
NameAndType	andThen$mcII$sp:(Lscala/Function1;)Lscala/Function1;
InterfaceMethod	scala/Function1$mcII$sp.andThen$mcII$sp:(Lscala/Function1;)Lscala/Function1;
Asciz	scala/Function1$mcII$sp$$anonfun$andThen$mcII$sp$1;
class	scala/Function1$mcII$sp$$anonfun$andThen$mcII$sp$1
Method	scala/Function1$mcII$sp$$anonfun$andThen$mcII$sp$1."<init>":(Lscala/Function1$mcII$sp;Lscala/Function1;)V
Asciz	g$8;
Asciz	$init$;
Asciz	(Lscala/Function1$mcII$sp;)V;
Asciz	Scala;
Asciz	InnerClasses;
Asciz	$anonfun$andThen$mcII$sp$1;
Asciz	$anonfun$compose$mcII$sp$1;
Asciz	scala/Function1$mcII$sp$class;
class	scala/Function1$mcII$sp$class
Asciz	java/lang/Object;
class	java/lang/Object

{
public static int apply(scala.Function1$mcII$sp, int);
  Signature: (Lscala/Function1$mcII$sp;I)I
  Code:
   Stack=2, Locals=2, Args_size=2
	aload_0
	iload_1
	invokeinterface	InterfaceMethod scala/Function1.apply$mcII$sp:(I)I
	ireturn
  Labels:
  LocalVariableTable: 
   Start  Length  Slot  Name   Signature
   0      8      0    $this       Lscala/Function1$mcII$sp;
   0      8      1    v1       I


public static scala.Function1 compose(scala.Function1$mcII$sp, scala.Function1);
  Signature: (Lscala/Function1$mcII$sp;Lscala/Function1;)Lscala/Function1;
  Code:
   Stack=2, Locals=2, Args_size=2
	aload_0
	aload_1
	invokeinterface	InterfaceMethod scala/Function1$mcII$sp.compose$mcII$sp:(Lscala/Function1;)Lscala/Function1;
	areturn
  Labels:
  LocalVariableTable: 
   Start  Length  Slot  Name   Signature
   0      8      0    $this       Lscala/Function1$mcII$sp;
   0      8      1    g       Lscala/Function1;


public static scala.Function1 compose$mcII$sp(scala.Function1$mcII$sp, scala.Function1);
  Signature: (Lscala/Function1$mcII$sp;Lscala/Function1;)Lscala/Function1;
  Code:
   Stack=4, Locals=2, Args_size=2
	new	class scala/Function1$mcII$sp$$anonfun$compose$mcII$sp$1
	dup
	aload_0
	aload_1
	invokespecial	Method scala/Function1$mcII$sp$$anonfun$compose$mcII$sp$1."<init>":(Lscala/Function1$mcII$sp;Lscala/Function1;)V
	areturn
  Labels:
  LocalVariableTable: 
   Start  Length  Slot  Name   Signature
   0      10      0    $this       Lscala/Function1$mcII$sp;
   0      10      1    g$7       Lscala/Function1;


public static scala.Function1 andThen(scala.Function1$mcII$sp, scala.Function1);
  Signature: (Lscala/Function1$mcII$sp;Lscala/Function1;)Lscala/Function1;
  Code:
   Stack=2, Locals=2, Args_size=2
	aload_0
	aload_1
	invokeinterface	InterfaceMethod scala/Function1$mcII$sp.andThen$mcII$sp:(Lscala/Function1;)Lscala/Function1;
	areturn
  Labels:
  LocalVariableTable: 
   Start  Length  Slot  Name   Signature
   0      8      0    $this       Lscala/Function1$mcII$sp;
   0      8      1    g       Lscala/Function1;


public static scala.Function1 andThen$mcII$sp(scala.Function1$mcII$sp, scala.Function1);
  Signature: (Lscala/Function1$mcII$sp;Lscala/Function1;)Lscala/Function1;
  Code:
   Stack=4, Locals=2, Args_size=2
	new	class scala/Function1$mcII$sp$$anonfun$andThen$mcII$sp$1
	dup
	aload_0
	aload_1
	invokespecial	Method scala/Function1$mcII$sp$$anonfun$andThen$mcII$sp$1."<init>":(Lscala/Function1$mcII$sp;Lscala/Function1;)V
	areturn
  Labels:
  LocalVariableTable: 
   Start  Length  Slot  Name   Signature
   0      10      0    $this       Lscala/Function1$mcII$sp;
   0      10      1    g$8       Lscala/Function1;


public static void $init$(scala.Function1$mcII$sp);
  Signature: (Lscala/Function1$mcII$sp;)V
  Code:
   Stack=0, Locals=1, Args_size=1
	return
  Labels:
  LocalVariableTable: 
   Start  Length  Slot  Name   Signature
   0      1      0    $this       Lscala/Function1$mcII$sp;


}

