Compiled from "Function2.scala"
public abstract class scala.Function2$mcZLI$sp$class extends java.lang.Object
  SourceFile: "Function2.scala"
  Scala: length = 0x
   
  InnerClass: 
   public final $anonfun$tupled$mcZLI$sp$1=class scala/Function2$mcZLI$sp$$anonfun$tupled$mcZLI$sp$1 of class scala/Function2$mcZLI$sp
   public final $anonfun$curried$mcZLI$sp$1=class scala/Function2$mcZLI$sp$$anonfun$curried$mcZLI$sp$1 of class scala/Function2$mcZLI$sp
  minor version: 0
  major version: 49
  Constant pool:
Asciz	SourceFile;
Asciz	Function2.scala;
Asciz	apply;
Asciz	(Lscala/Function2$mcZLI$sp;JI)Z;
Asciz	Code;
Asciz	LineNumberTable;
Asciz	scala/Function2;
class	scala/Function2
Asciz	apply$mcZLI$sp;
Asciz	(JI)Z;
NameAndType	apply$mcZLI$sp:(JI)Z
InterfaceMethod	scala/Function2.apply$mcZLI$sp:(JI)Z
Asciz	$this;
Asciz	Lscala/Function2$mcZLI$sp;;
Asciz	v1;
Asciz	J;
Asciz	v2;
Asciz	I;
Asciz	LocalVariableTable;
Asciz	curried;
Asciz	(Lscala/Function2$mcZLI$sp;)Lscala/Function1;;
Asciz	scala/Function2$mcZLI$sp;
class	scala/Function2$mcZLI$sp
Asciz	curried$mcZLI$sp;
Asciz	()Lscala/Function1;;
NameAndType	curried$mcZLI$sp:()Lscala/Function1;
InterfaceMethod	scala/Function2$mcZLI$sp.curried$mcZLI$sp:()Lscala/Function1;
Asciz	scala/Function2$mcZLI$sp$$anonfun$curried$mcZLI$sp$1;
class	scala/Function2$mcZLI$sp$$anonfun$curried$mcZLI$sp$1
Asciz	<init>;
Asciz	(Lscala/Function2$mcZLI$sp;)V;
NameAndType	"<init>":(Lscala/Function2$mcZLI$sp;)V
Method	scala/Function2$mcZLI$sp$$anonfun$curried$mcZLI$sp$1."<init>":(Lscala/Function2$mcZLI$sp;)V
Asciz	curry;
Asciz	curry$mcZLI$sp;
NameAndType	curry$mcZLI$sp:()Lscala/Function1;
InterfaceMethod	scala/Function2$mcZLI$sp.curry$mcZLI$sp:()Lscala/Function1;
Asciz	Deprecated;
Asciz	tupled;
Asciz	tupled$mcZLI$sp;
NameAndType	tupled$mcZLI$sp:()Lscala/Function1;
InterfaceMethod	scala/Function2$mcZLI$sp.tupled$mcZLI$sp:()Lscala/Function1;
Asciz	scala/Function2$mcZLI$sp$$anonfun$tupled$mcZLI$sp$1;
class	scala/Function2$mcZLI$sp$$anonfun$tupled$mcZLI$sp$1
Method	scala/Function2$mcZLI$sp$$anonfun$tupled$mcZLI$sp$1."<init>":(Lscala/Function2$mcZLI$sp;)V
Asciz	$init$;
Asciz	Scala;
Asciz	InnerClasses;
Asciz	$anonfun$tupled$mcZLI$sp$1;
Asciz	$anonfun$curried$mcZLI$sp$1;
Asciz	scala/Function2$mcZLI$sp$class;
class	scala/Function2$mcZLI$sp$class
Asciz	java/lang/Object;
class	java/lang/Object

{
public static boolean apply(scala.Function2$mcZLI$sp, long, int);
  Signature: (Lscala/Function2$mcZLI$sp;JI)Z
  Code:
   Stack=4, Locals=4, Args_size=3
	aload_0
	lload_1
	iload_3
	invokeinterface	InterfaceMethod scala/Function2.apply$mcZLI$sp:(JI)Z
	ireturn
  Labels:
  LocalVariableTable: 
   Start  Length  Slot  Name   Signature
   0      9      0    $this       Lscala/Function2$mcZLI$sp;
   0      9      1    v1       J
   0      9      3    v2       I


public static scala.Function1 curried(scala.Function2$mcZLI$sp);
  Signature: (Lscala/Function2$mcZLI$sp;)Lscala/Function1;
  Code:
   Stack=1, Locals=1, Args_size=1
	aload_0
	invokeinterface	InterfaceMethod scala/Function2$mcZLI$sp.curried$mcZLI$sp:()Lscala/Function1;
	areturn
  Labels:
  LocalVariableTable: 
   Start  Length  Slot  Name   Signature
   0      7      0    $this       Lscala/Function2$mcZLI$sp;


public static scala.Function1 curried$mcZLI$sp(scala.Function2$mcZLI$sp);
  Signature: (Lscala/Function2$mcZLI$sp;)Lscala/Function1;
  Code:
   Stack=3, Locals=1, Args_size=1
	new	class scala/Function2$mcZLI$sp$$anonfun$curried$mcZLI$sp$1
	dup
	aload_0
	invokespecial	Method scala/Function2$mcZLI$sp$$anonfun$curried$mcZLI$sp$1."<init>":(Lscala/Function2$mcZLI$sp;)V
	areturn
  Labels:
  LocalVariableTable: 
   Start  Length  Slot  Name   Signature
   0      9      0    $this       Lscala/Function2$mcZLI$sp;


public static scala.Function1 curry(scala.Function2$mcZLI$sp);
  Signature: (Lscala/Function2$mcZLI$sp;)Lscala/Function1;
  Code:
   Stack=1, Locals=1, Args_size=1
	aload_0
	invokeinterface	InterfaceMethod scala/Function2$mcZLI$sp.curry$mcZLI$sp:()Lscala/Function1;
	areturn
  Labels:
  LocalVariableTable: 
   Start  Length  Slot  Name   Signature
   0      7      0    $this       Lscala/Function2$mcZLI$sp;

  Deprecated: true

public static scala.Function1 curry$mcZLI$sp(scala.Function2$mcZLI$sp);
  Signature: (Lscala/Function2$mcZLI$sp;)Lscala/Function1;
  Code:
   Stack=1, Locals=1, Args_size=1
	aload_0
	invokeinterface	InterfaceMethod scala/Function2$mcZLI$sp.curried$mcZLI$sp:()Lscala/Function1;
	areturn
  Labels:
  LocalVariableTable: 
   Start  Length  Slot  Name   Signature
   0      7      0    $this       Lscala/Function2$mcZLI$sp;

  Deprecated: true

public static scala.Function1 tupled(scala.Function2$mcZLI$sp);
  Signature: (Lscala/Function2$mcZLI$sp;)Lscala/Function1;
  Code:
   Stack=1, Locals=1, Args_size=1
	aload_0
	invokeinterface	InterfaceMethod scala/Function2$mcZLI$sp.tupled$mcZLI$sp:()Lscala/Function1;
	areturn
  Labels:
  LocalVariableTable: 
   Start  Length  Slot  Name   Signature
   0      7      0    $this       Lscala/Function2$mcZLI$sp;


public static scala.Function1 tupled$mcZLI$sp(scala.Function2$mcZLI$sp);
  Signature: (Lscala/Function2$mcZLI$sp;)Lscala/Function1;
  Code:
   Stack=3, Locals=1, Args_size=1
	new	class scala/Function2$mcZLI$sp$$anonfun$tupled$mcZLI$sp$1
	dup
	aload_0
	invokespecial	Method scala/Function2$mcZLI$sp$$anonfun$tupled$mcZLI$sp$1."<init>":(Lscala/Function2$mcZLI$sp;)V
	areturn
  Labels:
  LocalVariableTable: 
   Start  Length  Slot  Name   Signature
   0      9      0    $this       Lscala/Function2$mcZLI$sp;


public static void $init$(scala.Function2$mcZLI$sp);
  Signature: (Lscala/Function2$mcZLI$sp;)V
  Code:
   Stack=0, Locals=1, Args_size=1
	return
  Labels:
  LocalVariableTable: 
   Start  Length  Slot  Name   Signature
   0      1      0    $this       Lscala/Function2$mcZLI$sp;


}

