Compiled from "Function2.scala"
public final class scala.Function2$mcVID$sp$$anonfun$curried$mcVID$sp$1$$anonfun$apply$12 extends scala.runtime.AbstractFunction1 implements java.io.Serializable
  SourceFile: "Function2.scala"
  Scala: length = 0x
   
  InnerClass: 
   public final $anonfun$curried$mcVID$sp$1=class scala/Function2$mcVID$sp$$anonfun$curried$mcVID$sp$1 of class scala/Function2$mcVID$sp
   public final $anonfun$apply$12=class scala/Function2$mcVID$sp$$anonfun$curried$mcVID$sp$1$$anonfun$apply$12 of class scala/Function2$mcVID$sp$$anonfun$curried$mcVID$sp$1
  minor version: 0
  major version: 49
  Constant pool:
Asciz	SourceFile;
Asciz	Function2.scala;
Asciz	<clinit>;
Asciz	()V;
Asciz	Code;
Asciz	serialVersionUID;
Asciz	J;
Asciz	scala/Function2$mcVID$sp$$anonfun$curried$mcVID$sp$1$$anonfun$apply$12;
class	scala/Function2$mcVID$sp$$anonfun$curried$mcVID$sp$1$$anonfun$apply$12
NameAndType	serialVersionUID:J
Field	scala/Function2$mcVID$sp$$anonfun$curried$mcVID$sp$1$$anonfun$apply$12.serialVersionUID:J
Asciz	$outer;
Asciz	Lscala/Function2$mcVID$sp$$anonfun$curried$mcVID$sp$1;;
Asciz	x1$12;
Asciz	I;
Asciz	apply;
Asciz	(D)V;
Asciz	LineNumberTable;
NameAndType	$outer:Lscala/Function2$mcVID$sp$$anonfun$curried$mcVID$sp$1;
Field	scala/Function2$mcVID$sp$$anonfun$curried$mcVID$sp$1$$anonfun$apply$12.$outer:Lscala/Function2$mcVID$sp$$anonfun$curried$mcVID$sp$1;
Asciz	scala/Function2$mcVID$sp$$anonfun$curried$mcVID$sp$1;
class	scala/Function2$mcVID$sp$$anonfun$curried$mcVID$sp$1
Asciz	Lscala/Function2$mcVID$sp;;
NameAndType	$outer:Lscala/Function2$mcVID$sp;
Field	scala/Function2$mcVID$sp$$anonfun$curried$mcVID$sp$1.$outer:Lscala/Function2$mcVID$sp;
NameAndType	x1$12:I
Field	scala/Function2$mcVID$sp$$anonfun$curried$mcVID$sp$1$$anonfun$apply$12.x1$12:I
Asciz	scala/Function2$mcVID$sp;
class	scala/Function2$mcVID$sp
Asciz	(ID)V;
NameAndType	apply:(ID)V
InterfaceMethod	scala/Function2$mcVID$sp.apply:(ID)V
Asciz	this;
Asciz	Lscala/Function2$mcVID$sp$$anonfun$curried$mcVID$sp$1$$anonfun$apply$12;;
Asciz	x2;
Asciz	D;
Asciz	LocalVariableTable;
Asciz	apply$mcVD$sp;
Asciz	v1;
Asciz	(Ljava/lang/Object;)Ljava/lang/Object;;
Asciz	scala/runtime/BoxesRunTime;
class	scala/runtime/BoxesRunTime
Asciz	unboxToDouble;
Asciz	(Ljava/lang/Object;)D;
NameAndType	unboxToDouble:(Ljava/lang/Object;)D
Method	scala/runtime/BoxesRunTime.unboxToDouble:(Ljava/lang/Object;)D
NameAndType	apply:(D)V
Method	scala/Function2$mcVID$sp$$anonfun$curried$mcVID$sp$1$$anonfun$apply$12.apply:(D)V
Asciz	scala/runtime/BoxedUnit;
class	scala/runtime/BoxedUnit
Asciz	UNIT;
Asciz	Lscala/runtime/BoxedUnit;;
NameAndType	UNIT:Lscala/runtime/BoxedUnit;
Field	scala/runtime/BoxedUnit.UNIT:Lscala/runtime/BoxedUnit;
Asciz	Ljava/lang/Object;;
Asciz	<init>;
Asciz	(Lscala/Function2$mcVID$sp$$anonfun$curried$mcVID$sp$1;I)V;
Asciz	java/lang/NullPointerException;
class	java/lang/NullPointerException
NameAndType	"<init>":()V
Method	java/lang/NullPointerException."<init>":()V
Asciz	scala/runtime/AbstractFunction1;
class	scala/runtime/AbstractFunction1
Method	scala/runtime/AbstractFunction1."<init>":()V
Asciz	Scala;
Asciz	InnerClasses;
Asciz	$anonfun$curried$mcVID$sp$1;
Asciz	$anonfun$apply$12;
Asciz	java/io/Serializable;
class	java/io/Serializable

{
public static final long serialVersionUID;
  Signature: J

public final scala.Function2$mcVID$sp$$anonfun$curried$mcVID$sp$1 $outer;
  Signature: Lscala/Function2$mcVID$sp$$anonfun$curried$mcVID$sp$1;

public final int x1$12;
  Signature: I

public static {};
  Signature: ()V
  Code:
   Stack=2, Locals=0, Args_size=0
	lconst_0
	putstatic	Field serialVersionUID:J
	return
  Labels:

public final void apply(double);
  Signature: (D)V
  Code:
   Stack=4, Locals=4, Args_size=2
	aload_0
	getfield	Field $outer:Lscala/Function2$mcVID$sp$$anonfun$curried$mcVID$sp$1;
	astore_3
	aload_3
	getfield	Field scala/Function2$mcVID$sp$$anonfun$curried$mcVID$sp$1.$outer:Lscala/Function2$mcVID$sp;
	aload_0
	getfield	Field x1$12:I
	dload_1
	invokeinterface	InterfaceMethod scala/Function2$mcVID$sp.apply:(ID)V
	return
  Labels:
  LocalVariableTable: 
   Start  Length  Slot  Name   Signature
   0      20      0    this       Lscala/Function2$mcVID$sp$$anonfun$curried$mcVID$sp$1$$anonfun$apply$12;
   0      20      1    x2       D


public void apply$mcVD$sp(double);
  Signature: (D)V
  Code:
   Stack=4, Locals=4, Args_size=2
	aload_0
	getfield	Field $outer:Lscala/Function2$mcVID$sp$$anonfun$curried$mcVID$sp$1;
	astore_3
	aload_3
	getfield	Field scala/Function2$mcVID$sp$$anonfun$curried$mcVID$sp$1.$outer:Lscala/Function2$mcVID$sp;
	aload_0
	getfield	Field x1$12:I
	dload_1
	invokeinterface	InterfaceMethod scala/Function2$mcVID$sp.apply:(ID)V
	return
  Labels:
  LocalVariableTable: 
   Start  Length  Slot  Name   Signature
   0      20      0    this       Lscala/Function2$mcVID$sp$$anonfun$curried$mcVID$sp$1$$anonfun$apply$12;
   0      20      1    v1       D


public final java.lang.Object apply(java.lang.Object);
  Signature: (Ljava/lang/Object;)Ljava/lang/Object;
  Code:
   Stack=3, Locals=2, Args_size=2
	aload_0
	aload_1
	invokestatic	Method scala/runtime/BoxesRunTime.unboxToDouble:(Ljava/lang/Object;)D
	invokevirtual	Method apply:(D)V
	getstatic	Field scala/runtime/BoxedUnit.UNIT:Lscala/runtime/BoxedUnit;
	areturn
  Labels:
  LocalVariableTable: 
   Start  Length  Slot  Name   Signature
   0      12      0    this       Lscala/Function2$mcVID$sp$$anonfun$curried$mcVID$sp$1$$anonfun$apply$12;
   0      12      1    v1       Ljava/lang/Object;


public scala.Function2$mcVID$sp$$anonfun$curried$mcVID$sp$1$$anonfun$apply$12(scala.Function2$mcVID$sp$$anonfun$curried$mcVID$sp$1, int);
  Signature: (Lscala/Function2$mcVID$sp$$anonfun$curried$mcVID$sp$1;I)V
  Code:
   Stack=2, Locals=3, Args_size=3
	aload_1
	ifnonnull	l1 // aload_0
	new	class java/lang/NullPointerException
	dup
	invokespecial	Method java/lang/NullPointerException."<init>":()V
	athrow
l1	aload_0
	aload_1
	putfield	Field $outer:Lscala/Function2$mcVID$sp$$anonfun$curried$mcVID$sp$1;
	aload_0
	iload_2
	putfield	Field x1$12:I
	aload_0
	invokespecial	Method scala/runtime/AbstractFunction1."<init>":()V
	return
  Labels:
   	l1 = 12 // aload_0
  LocalVariableTable: 
   Start  Length  Slot  Name   Signature
   0      27      0    this       Lscala/Function2$mcVID$sp$$anonfun$curried$mcVID$sp$1$$anonfun$apply$12;
   0      27      1    $outer       Lscala/Function2$mcVID$sp$$anonfun$curried$mcVID$sp$1;


}

