Compiled from "Function1.scala"
public final class scala.Function1$mcVD$sp$$anonfun$andThen$mcVD$sp$1 extends scala.runtime.AbstractFunction1 implements java.io.Serializable
  SourceFile: "Function1.scala"
  Scala: length = 0x
   
  InnerClass: 
   public final $anonfun$andThen$mcVD$sp$1=class scala/Function1$mcVD$sp$$anonfun$andThen$mcVD$sp$1 of class scala/Function1$mcVD$sp
  minor version: 0
  major version: 49
  Constant pool:
Asciz	SourceFile;
Asciz	Function1.scala;
Asciz	<clinit>;
Asciz	()V;
Asciz	Code;
Asciz	serialVersionUID;
Asciz	J;
Asciz	scala/Function1$mcVD$sp$$anonfun$andThen$mcVD$sp$1;
class	scala/Function1$mcVD$sp$$anonfun$andThen$mcVD$sp$1
NameAndType	serialVersionUID:J
Field	scala/Function1$mcVD$sp$$anonfun$andThen$mcVD$sp$1.serialVersionUID:J
Asciz	$outer;
Asciz	Lscala/Function1$mcVD$sp;;
Asciz	g$24;
Asciz	Lscala/Function1;;
Asciz	apply;
Asciz	(D)Ljava/lang/Object;;
Asciz	LineNumberTable;
NameAndType	g$24:Lscala/Function1;
Field	scala/Function1$mcVD$sp$$anonfun$andThen$mcVD$sp$1.g$24:Lscala/Function1;
NameAndType	$outer:Lscala/Function1$mcVD$sp;
Field	scala/Function1$mcVD$sp$$anonfun$andThen$mcVD$sp$1.$outer:Lscala/Function1$mcVD$sp;
Asciz	scala/Function1$mcVD$sp;
class	scala/Function1$mcVD$sp
Asciz	(D)V;
NameAndType	apply:(D)V
InterfaceMethod	scala/Function1$mcVD$sp.apply:(D)V
Asciz	scala/runtime/BoxedUnit;
class	scala/runtime/BoxedUnit
Asciz	UNIT;
Asciz	Lscala/runtime/BoxedUnit;;
NameAndType	UNIT:Lscala/runtime/BoxedUnit;
Field	scala/runtime/BoxedUnit.UNIT:Lscala/runtime/BoxedUnit;
Asciz	scala/Function1;
class	scala/Function1
Asciz	(Ljava/lang/Object;)Ljava/lang/Object;;
NameAndType	apply:(Ljava/lang/Object;)Ljava/lang/Object;
InterfaceMethod	scala/Function1.apply:(Ljava/lang/Object;)Ljava/lang/Object;
Asciz	this;
Asciz	Lscala/Function1$mcVD$sp$$anonfun$andThen$mcVD$sp$1;;
Asciz	x;
Asciz	D;
Asciz	LocalVariableTable;
Asciz	(D)TA;;
Asciz	Signature;
Asciz	scala/runtime/BoxesRunTime;
class	scala/runtime/BoxesRunTime
Asciz	unboxToDouble;
Asciz	(Ljava/lang/Object;)D;
NameAndType	unboxToDouble:(Ljava/lang/Object;)D
Method	scala/runtime/BoxesRunTime.unboxToDouble:(Ljava/lang/Object;)D
NameAndType	apply:(D)Ljava/lang/Object;
Method	scala/Function1$mcVD$sp$$anonfun$andThen$mcVD$sp$1.apply:(D)Ljava/lang/Object;
Asciz	v1;
Asciz	Ljava/lang/Object;;
Asciz	<init>;
Asciz	(Lscala/Function1$mcVD$sp;Lscala/Function1;)V;
Asciz	java/lang/NullPointerException;
class	java/lang/NullPointerException
NameAndType	"<init>":()V
Method	java/lang/NullPointerException."<init>":()V
Asciz	scala/runtime/AbstractFunction1;
class	scala/runtime/AbstractFunction1
Method	scala/runtime/AbstractFunction1."<init>":()V
Asciz	Scala;
Asciz	InnerClasses;
Asciz	$anonfun$andThen$mcVD$sp$1;
Asciz	java/io/Serializable;
class	java/io/Serializable

{
public static final long serialVersionUID;
  Signature: J

public final scala.Function1$mcVD$sp $outer;
  Signature: Lscala/Function1$mcVD$sp;

public final scala.Function1 g$24;
  Signature: Lscala/Function1;

public static {};
  Signature: ()V
  Code:
   Stack=2, Locals=0, Args_size=0
	lconst_0
	putstatic	Field serialVersionUID:J
	return
  Labels:

public final java.lang.Object apply(double);
  Signature: (D)Ljava/lang/Object;
  Code:
   Stack=4, Locals=3, Args_size=2
	aload_0
	getfield	Field g$24:Lscala/Function1;
	aload_0
	getfield	Field $outer:Lscala/Function1$mcVD$sp;
	dload_1
	invokeinterface	InterfaceMethod scala/Function1$mcVD$sp.apply:(D)V
	getstatic	Field scala/runtime/BoxedUnit.UNIT:Lscala/runtime/BoxedUnit;
	invokeinterface	InterfaceMethod scala/Function1.apply:(Ljava/lang/Object;)Ljava/lang/Object;
	areturn
  Labels:
  LocalVariableTable: 
   Start  Length  Slot  Name   Signature
   0      23      0    this       Lscala/Function1$mcVD$sp$$anonfun$andThen$mcVD$sp$1;
   0      23      1    x       D

  Signature: length = 0x2
   00 2C 

public final java.lang.Object apply(java.lang.Object);
  Signature: (Ljava/lang/Object;)Ljava/lang/Object;
  Code:
   Stack=3, Locals=2, Args_size=2
	aload_0
	aload_1
	invokestatic	Method scala/runtime/BoxesRunTime.unboxToDouble:(Ljava/lang/Object;)D
	invokevirtual	Method apply:(D)Ljava/lang/Object;
	areturn
  Labels:
  LocalVariableTable: 
   Start  Length  Slot  Name   Signature
   0      9      0    this       Lscala/Function1$mcVD$sp$$anonfun$andThen$mcVD$sp$1;
   0      9      1    v1       Ljava/lang/Object;


public scala.Function1$mcVD$sp$$anonfun$andThen$mcVD$sp$1(scala.Function1$mcVD$sp, scala.Function1);
  Signature: (Lscala/Function1$mcVD$sp;Lscala/Function1;)V
  Code:
   Stack=2, Locals=3, Args_size=3
	aload_1
	ifnonnull	l1 // aload_0
	new	class java/lang/NullPointerException
	dup
	invokespecial	Method java/lang/NullPointerException."<init>":()V
	athrow
l1	aload_0
	aload_1
	putfield	Field $outer:Lscala/Function1$mcVD$sp;
	aload_0
	aload_2
	putfield	Field g$24:Lscala/Function1;
	aload_0
	invokespecial	Method scala/runtime/AbstractFunction1."<init>":()V
	return
  Labels:
   	l1 = 12 // aload_0
  LocalVariableTable: 
   Start  Length  Slot  Name   Signature
   0      27      0    this       Lscala/Function1$mcVD$sp$$anonfun$andThen$mcVD$sp$1;
   0      27      1    $outer       Lscala/Function1$mcVD$sp;


}

