Compiled from "Function22.scala"
public final class scala.Function22$$anonfun$tuple$1 extends scala.runtime.AbstractFunction1 implements java.io.Serializable
  SourceFile: "Function22.scala"
  Scala: length = 0x
   
  InnerClass: 
   public final #146= #9 of #108; //$anonfun$tuple$1=class scala/Function22$$anonfun$tuple$1 of class scala/Function22
  minor version: 0
  major version: 49
  Constant pool:
const #1 = Asciz	SourceFile;
const #2 = Asciz	Function22.scala;
const #3 = Asciz	<clinit>;
const #4 = Asciz	()V;
const #5 = Asciz	Code;
const #6 = Asciz	serialVersionUID;
const #7 = Asciz	J;
const #8 = Asciz	scala/Function22$$anonfun$tuple$1;
const #9 = class	#8;	//  scala/Function22$$anonfun$tuple$1
const #10 = NameAndType	#6:#7;//  serialVersionUID:J
const #11 = Field	#9.#10;	//  scala/Function22$$anonfun$tuple$1.serialVersionUID:J
const #12 = Asciz	$outer;
const #13 = Asciz	Lscala/Function22;;
const #14 = Asciz	<init>;
const #15 = Asciz	(Lscala/Function22;)V;
const #16 = Asciz	LineNumberTable;
const #17 = Asciz	java/lang/NullPointerException;
const #18 = class	#17;	//  java/lang/NullPointerException
const #19 = NameAndType	#14:#4;//  "<init>":()V
const #20 = Method	#18.#19;	//  java/lang/NullPointerException."<init>":()V
const #21 = NameAndType	#12:#13;//  $outer:Lscala/Function22;
const #22 = Field	#9.#21;	//  scala/Function22$$anonfun$tuple$1.$outer:Lscala/Function22;
const #23 = Asciz	scala/runtime/AbstractFunction1;
const #24 = class	#23;	//  scala/runtime/AbstractFunction1
const #25 = Method	#24.#19;	//  scala/runtime/AbstractFunction1."<init>":()V
const #26 = Asciz	this;
const #27 = Asciz	Lscala/Function22$$anonfun$tuple$1;;
const #28 = Asciz	LocalVariableTable;
const #29 = Asciz	(Lscala/Function22<TT1;TT2;TT3;TT4;TT5;TT6;TT7;TT8;TT9;TT10;TT11;TT12;TT13;TT14;TT15;TT16;TT17;TT18;TT19;TT20;TT21;TT22;TR;>;)V;
const #30 = Asciz	Signature;
const #31 = Asciz	apply;
const #32 = Asciz	(Ljava/lang/Object;)Ljava/lang/Object;;
const #33 = Asciz	scala/Tuple22;
const #34 = class	#33;	//  scala/Tuple22
const #35 = Asciz	(Lscala/Tuple22;)Ljava/lang/Object;;
const #36 = NameAndType	#31:#35;//  apply:(Lscala/Tuple22;)Ljava/lang/Object;
const #37 = Method	#9.#36;	//  scala/Function22$$anonfun$tuple$1.apply:(Lscala/Tuple22;)Ljava/lang/Object;
const #38 = Asciz	v1;
const #39 = Asciz	Ljava/lang/Object;;
const #40 = Asciz	_1;
const #41 = Asciz	()Ljava/lang/Object;;
const #42 = NameAndType	#40:#41;//  _1:()Ljava/lang/Object;
const #43 = Method	#34.#42;	//  scala/Tuple22._1:()Ljava/lang/Object;
const #44 = Asciz	_2;
const #45 = NameAndType	#44:#41;//  _2:()Ljava/lang/Object;
const #46 = Method	#34.#45;	//  scala/Tuple22._2:()Ljava/lang/Object;
const #47 = Asciz	_3;
const #48 = NameAndType	#47:#41;//  _3:()Ljava/lang/Object;
const #49 = Method	#34.#48;	//  scala/Tuple22._3:()Ljava/lang/Object;
const #50 = Asciz	_4;
const #51 = NameAndType	#50:#41;//  _4:()Ljava/lang/Object;
const #52 = Method	#34.#51;	//  scala/Tuple22._4:()Ljava/lang/Object;
const #53 = Asciz	_5;
const #54 = NameAndType	#53:#41;//  _5:()Ljava/lang/Object;
const #55 = Method	#34.#54;	//  scala/Tuple22._5:()Ljava/lang/Object;
const #56 = Asciz	_6;
const #57 = NameAndType	#56:#41;//  _6:()Ljava/lang/Object;
const #58 = Method	#34.#57;	//  scala/Tuple22._6:()Ljava/lang/Object;
const #59 = Asciz	_7;
const #60 = NameAndType	#59:#41;//  _7:()Ljava/lang/Object;
const #61 = Method	#34.#60;	//  scala/Tuple22._7:()Ljava/lang/Object;
const #62 = Asciz	_8;
const #63 = NameAndType	#62:#41;//  _8:()Ljava/lang/Object;
const #64 = Method	#34.#63;	//  scala/Tuple22._8:()Ljava/lang/Object;
const #65 = Asciz	_9;
const #66 = NameAndType	#65:#41;//  _9:()Ljava/lang/Object;
const #67 = Method	#34.#66;	//  scala/Tuple22._9:()Ljava/lang/Object;
const #68 = Asciz	_10;
const #69 = NameAndType	#68:#41;//  _10:()Ljava/lang/Object;
const #70 = Method	#34.#69;	//  scala/Tuple22._10:()Ljava/lang/Object;
const #71 = Asciz	_11;
const #72 = NameAndType	#71:#41;//  _11:()Ljava/lang/Object;
const #73 = Method	#34.#72;	//  scala/Tuple22._11:()Ljava/lang/Object;
const #74 = Asciz	_12;
const #75 = NameAndType	#74:#41;//  _12:()Ljava/lang/Object;
const #76 = Method	#34.#75;	//  scala/Tuple22._12:()Ljava/lang/Object;
const #77 = Asciz	_13;
const #78 = NameAndType	#77:#41;//  _13:()Ljava/lang/Object;
const #79 = Method	#34.#78;	//  scala/Tuple22._13:()Ljava/lang/Object;
const #80 = Asciz	_14;
const #81 = NameAndType	#80:#41;//  _14:()Ljava/lang/Object;
const #82 = Method	#34.#81;	//  scala/Tuple22._14:()Ljava/lang/Object;
const #83 = Asciz	_15;
const #84 = NameAndType	#83:#41;//  _15:()Ljava/lang/Object;
const #85 = Method	#34.#84;	//  scala/Tuple22._15:()Ljava/lang/Object;
const #86 = Asciz	_16;
const #87 = NameAndType	#86:#41;//  _16:()Ljava/lang/Object;
const #88 = Method	#34.#87;	//  scala/Tuple22._16:()Ljava/lang/Object;
const #89 = Asciz	_17;
const #90 = NameAndType	#89:#41;//  _17:()Ljava/lang/Object;
const #91 = Method	#34.#90;	//  scala/Tuple22._17:()Ljava/lang/Object;
const #92 = Asciz	_18;
const #93 = NameAndType	#92:#41;//  _18:()Ljava/lang/Object;
const #94 = Method	#34.#93;	//  scala/Tuple22._18:()Ljava/lang/Object;
const #95 = Asciz	_19;
const #96 = NameAndType	#95:#41;//  _19:()Ljava/lang/Object;
const #97 = Method	#34.#96;	//  scala/Tuple22._19:()Ljava/lang/Object;
const #98 = Asciz	_20;
const #99 = NameAndType	#98:#41;//  _20:()Ljava/lang/Object;
const #100 = Method	#34.#99;	//  scala/Tuple22._20:()Ljava/lang/Object;
const #101 = Asciz	_21;
const #102 = NameAndType	#101:#41;//  _21:()Ljava/lang/Object;
const #103 = Method	#34.#102;	//  scala/Tuple22._21:()Ljava/lang/Object;
const #104 = Asciz	_22;
const #105 = NameAndType	#104:#41;//  _22:()Ljava/lang/Object;
const #106 = Method	#34.#105;	//  scala/Tuple22._22:()Ljava/lang/Object;
const #107 = Asciz	scala/Function22;
const #108 = class	#107;	//  scala/Function22
const #109 = Asciz	(Ljava/lang/Object;Ljava/lang/Object;Ljava/lang/Object;Ljava/lang/Object;Ljava/lang/Object;Ljava/lang/Object;Ljava/lang/Object;Ljava/lang/Object;Ljava/lang/Object;Ljava/lang/Object;Ljava/lang/Object;Ljava/lang/Object;Ljava/lang/Object;Ljava/lang/Object;Ljava/lang/Object;Ljava/lang/Object;Ljava/lang/Object;Ljava/lang/Object;Ljava/lang/Object;Ljava/lang/Object;Ljava/lang/Object;Ljava/lang/Object;)Ljava/lang/Object;;
const #110 = NameAndType	#31:#109;//  apply:(Ljava/lang/Object;Ljava/lang/Object;Ljava/lang/Object;Ljava/lang/Object;Ljava/lang/Object;Ljava/lang/Object;Ljava/lang/Object;Ljava/lang/Object;Ljava/lang/Object;Ljava/lang/Object;Ljava/lang/Object;Ljava/lang/Object;Ljava/lang/Object;Ljava/lang/Object;Ljava/lang/Object;Ljava/lang/Object;Ljava/lang/Object;Ljava/lang/Object;Ljava/lang/Object;Ljava/lang/Object;Ljava/lang/Object;Ljava/lang/Object;)Ljava/lang/Object;
const #111 = InterfaceMethod	#108.#110;	//  scala/Function22.apply:(Ljava/lang/Object;Ljava/lang/Object;Ljava/lang/Object;Ljava/lang/Object;Ljava/lang/Object;Ljava/lang/Object;Ljava/lang/Object;Ljava/lang/Object;Ljava/lang/Object;Ljava/lang/Object;Ljava/lang/Object;Ljava/lang/Object;Ljava/lang/Object;Ljava/lang/Object;Ljava/lang/Object;Ljava/lang/Object;Ljava/lang/Object;Ljava/lang/Object;Ljava/lang/Object;Ljava/lang/Object;Ljava/lang/Object;Ljava/lang/Object;)Ljava/lang/Object;
const #112 = Asciz	scala/MatchError;
const #113 = class	#112;	//  scala/MatchError
const #114 = Asciz	toString;
const #115 = Asciz	()Ljava/lang/String;;
const #116 = NameAndType	#114:#115;//  toString:()Ljava/lang/String;
const #117 = Method	#34.#116;	//  scala/Tuple22.toString:()Ljava/lang/String;
const #118 = Asciz	(Ljava/lang/String;)V;
const #119 = NameAndType	#14:#118;//  "<init>":(Ljava/lang/String;)V
const #120 = Method	#113.#119;	//  scala/MatchError."<init>":(Ljava/lang/String;)V
const #121 = Asciz	temp2;
const #122 = Asciz	temp3;
const #123 = Asciz	temp4;
const #124 = Asciz	temp5;
const #125 = Asciz	temp6;
const #126 = Asciz	temp7;
const #127 = Asciz	temp8;
const #128 = Asciz	temp9;
const #129 = Asciz	temp10;
const #130 = Asciz	temp11;
const #131 = Asciz	temp12;
const #132 = Asciz	temp13;
const #133 = Asciz	temp14;
const #134 = Asciz	temp15;
const #135 = Asciz	temp16;
const #136 = Asciz	temp17;
const #137 = Asciz	temp18;
const #138 = Asciz	temp19;
const #139 = Asciz	temp20;
const #140 = Asciz	temp21;
const #141 = Asciz	temp22;
const #142 = Asciz	temp23;
const #143 = Asciz	(Lscala/Tuple22<TT1;TT2;TT3;TT4;TT5;TT6;TT7;TT8;TT9;TT10;TT11;TT12;TT13;TT14;TT15;TT16;TT17;TT18;TT19;TT20;TT21;TT22;>;)TR;;
const #144 = Asciz	Scala;
const #145 = Asciz	InnerClasses;
const #146 = Asciz	$anonfun$tuple$1;
const #147 = Asciz	java/io/Serializable;
const #148 = class	#147;	//  java/io/Serializable

{
public static final long serialVersionUID;

public static {};
  Code:
   Stack=2, Locals=0, Args_size=0
   0:	lconst_0
   1:	putstatic	#11; //Field serialVersionUID:J
   4:	return

public scala.Function22$$anonfun$tuple$1(scala.Function22);
  Code:
   Stack=2, Locals=2, Args_size=2
   0:	aload_1
   1:	ifnonnull	12
   4:	new	#18; //class java/lang/NullPointerException
   7:	dup
   8:	invokespecial	#20; //Method java/lang/NullPointerException."<init>":()V
   11:	athrow
   12:	aload_0
   13:	aload_1
   14:	putfield	#22; //Field $outer:Lscala/Function22;
   17:	aload_0
   18:	invokespecial	#25; //Method scala/runtime/AbstractFunction1."<init>":()V
   21:	return
  LineNumberTable: 
   line 34: 0

  LocalVariableTable: 
   Start  Length  Slot  Name   Signature
   0      22      0    this       Lscala/Function22$$anonfun$tuple$1;
   0      22      1    $outer       Lscala/Function22;

  Signature: length = 0x2
   00 1D 

public final java.lang.Object apply(java.lang.Object);
  Code:
   Stack=2, Locals=2, Args_size=2
   0:	aload_0
   1:	aload_1
   2:	checkcast	#34; //class scala/Tuple22
   5:	invokevirtual	#37; //Method apply:(Lscala/Tuple22;)Ljava/lang/Object;
   8:	areturn
  LineNumberTable: 
   line 34: 0

  LocalVariableTable: 
   Start  Length  Slot  Name   Signature
   0      9      0    this       Lscala/Function22$$anonfun$tuple$1;
   0      9      1    v1       Ljava/lang/Object;


public final java.lang.Object apply(scala.Tuple22);
  Code:
   Stack=23, Locals=24, Args_size=2
   0:	aload_1
   1:	ifnull	202
   4:	aload_1
   5:	invokevirtual	#43; //Method scala/Tuple22._1:()Ljava/lang/Object;
   8:	astore_2
   9:	aload_1
   10:	invokevirtual	#46; //Method scala/Tuple22._2:()Ljava/lang/Object;
   13:	astore_3
   14:	aload_1
   15:	invokevirtual	#49; //Method scala/Tuple22._3:()Ljava/lang/Object;
   18:	astore	4
   20:	aload_1
   21:	invokevirtual	#52; //Method scala/Tuple22._4:()Ljava/lang/Object;
   24:	astore	5
   26:	aload_1
   27:	invokevirtual	#55; //Method scala/Tuple22._5:()Ljava/lang/Object;
   30:	astore	6
   32:	aload_1
   33:	invokevirtual	#58; //Method scala/Tuple22._6:()Ljava/lang/Object;
   36:	astore	7
   38:	aload_1
   39:	invokevirtual	#61; //Method scala/Tuple22._7:()Ljava/lang/Object;
   42:	astore	8
   44:	aload_1
   45:	invokevirtual	#64; //Method scala/Tuple22._8:()Ljava/lang/Object;
   48:	astore	9
   50:	aload_1
   51:	invokevirtual	#67; //Method scala/Tuple22._9:()Ljava/lang/Object;
   54:	astore	10
   56:	aload_1
   57:	invokevirtual	#70; //Method scala/Tuple22._10:()Ljava/lang/Object;
   60:	astore	11
   62:	aload_1
   63:	invokevirtual	#73; //Method scala/Tuple22._11:()Ljava/lang/Object;
   66:	astore	12
   68:	aload_1
   69:	invokevirtual	#76; //Method scala/Tuple22._12:()Ljava/lang/Object;
   72:	astore	13
   74:	aload_1
   75:	invokevirtual	#79; //Method scala/Tuple22._13:()Ljava/lang/Object;
   78:	astore	14
   80:	aload_1
   81:	invokevirtual	#82; //Method scala/Tuple22._14:()Ljava/lang/Object;
   84:	astore	15
   86:	aload_1
   87:	invokevirtual	#85; //Method scala/Tuple22._15:()Ljava/lang/Object;
   90:	astore	16
   92:	aload_1
   93:	invokevirtual	#88; //Method scala/Tuple22._16:()Ljava/lang/Object;
   96:	astore	17
   98:	aload_1
   99:	invokevirtual	#91; //Method scala/Tuple22._17:()Ljava/lang/Object;
   102:	astore	18
   104:	aload_1
   105:	invokevirtual	#94; //Method scala/Tuple22._18:()Ljava/lang/Object;
   108:	astore	19
   110:	aload_1
   111:	invokevirtual	#97; //Method scala/Tuple22._19:()Ljava/lang/Object;
   114:	astore	20
   116:	aload_1
   117:	invokevirtual	#100; //Method scala/Tuple22._20:()Ljava/lang/Object;
   120:	astore	21
   122:	aload_1
   123:	invokevirtual	#103; //Method scala/Tuple22._21:()Ljava/lang/Object;
   126:	astore	22
   128:	aload_1
   129:	invokevirtual	#106; //Method scala/Tuple22._22:()Ljava/lang/Object;
   132:	astore	23
   134:	iconst_1
   135:	ifeq	190
   138:	aload_0
   139:	getfield	#22; //Field $outer:Lscala/Function22;
   142:	aload_2
   143:	aload_3
   144:	aload	4
   146:	aload	5
   148:	aload	6
   150:	aload	7
   152:	aload	8
   154:	aload	9
   156:	aload	10
   158:	aload	11
   160:	aload	12
   162:	aload	13
   164:	aload	14
   166:	aload	15
   168:	aload	16
   170:	aload	17
   172:	aload	18
   174:	aload	19
   176:	aload	20
   178:	aload	21
   180:	aload	22
   182:	aload	23
   184:	invokeinterface	#111,  23; //InterfaceMethod scala/Function22.apply:(Ljava/lang/Object;Ljava/lang/Object;Ljava/lang/Object;Ljava/lang/Object;Ljava/lang/Object;Ljava/lang/Object;Ljava/lang/Object;Ljava/lang/Object;Ljava/lang/Object;Ljava/lang/Object;Ljava/lang/Object;Ljava/lang/Object;Ljava/lang/Object;Ljava/lang/Object;Ljava/lang/Object;Ljava/lang/Object;Ljava/lang/Object;Ljava/lang/Object;Ljava/lang/Object;Ljava/lang/Object;Ljava/lang/Object;Ljava/lang/Object;)Ljava/lang/Object;
   189:	areturn
   190:	new	#113; //class scala/MatchError
   193:	dup
   194:	aload_1
   195:	invokevirtual	#117; //Method scala/Tuple22.toString:()Ljava/lang/String;
   198:	invokespecial	#120; //Method scala/MatchError."<init>":(Ljava/lang/String;)V
   201:	athrow
   202:	new	#113; //class scala/MatchError
   205:	dup
   206:	aload_1
   207:	invokevirtual	#117; //Method scala/Tuple22.toString:()Ljava/lang/String;
   210:	invokespecial	#120; //Method scala/MatchError."<init>":(Ljava/lang/String;)V
   213:	athrow
  LineNumberTable: 
   line 34: 0
   line 21: 134
   line 35: 138
   line 34: 189

  LocalVariableTable: 
   Start  Length  Slot  Name   Signature
   0      214      0    this       Lscala/Function22$$anonfun$tuple$1;
   9      193      2    temp2       Ljava/lang/Object;
   14      188      3    temp3       Ljava/lang/Object;
   20      182      4    temp4       Ljava/lang/Object;
   26      176      5    temp5       Ljava/lang/Object;
   32      170      6    temp6       Ljava/lang/Object;
   38      164      7    temp7       Ljava/lang/Object;
   44      158      8    temp8       Ljava/lang/Object;
   50      152      9    temp9       Ljava/lang/Object;
   56      146      10    temp10       Ljava/lang/Object;
   62      140      11    temp11       Ljava/lang/Object;
   68      134      12    temp12       Ljava/lang/Object;
   74      128      13    temp13       Ljava/lang/Object;
   80      122      14    temp14       Ljava/lang/Object;
   86      116      15    temp15       Ljava/lang/Object;
   92      110      16    temp16       Ljava/lang/Object;
   98      104      17    temp17       Ljava/lang/Object;
   104      98      18    temp18       Ljava/lang/Object;
   110      92      19    temp19       Ljava/lang/Object;
   116      86      20    temp20       Ljava/lang/Object;
   122      80      21    temp21       Ljava/lang/Object;
   128      74      22    temp22       Ljava/lang/Object;
   134      68      23    temp23       Ljava/lang/Object;

  Signature: length = 0x2
   00 FFFFFF8F 

}

