Compiled from "Function2.scala"
public abstract class scala.Function2$mcZLL$sp$class extends java.lang.Object
  SourceFile: "Function2.scala"
  Scala: length = 0x
   
  InnerClass: 
   public final $anonfun$tupled$mcZLL$sp$1=class scala/Function2$mcZLL$sp$$anonfun$tupled$mcZLL$sp$1 of class scala/Function2$mcZLL$sp
   public final $anonfun$curried$mcZLL$sp$1=class scala/Function2$mcZLL$sp$$anonfun$curried$mcZLL$sp$1 of class scala/Function2$mcZLL$sp
  minor version: 0
  major version: 49
  Constant pool:
Asciz	SourceFile;
Asciz	Function2.scala;
Asciz	apply;
Asciz	(Lscala/Function2$mcZLL$sp;JJ)Z;
Asciz	Code;
Asciz	LineNumberTable;
Asciz	scala/Function2;
class	scala/Function2
Asciz	apply$mcZLL$sp;
Asciz	(JJ)Z;
NameAndType	apply$mcZLL$sp:(JJ)Z
InterfaceMethod	scala/Function2.apply$mcZLL$sp:(JJ)Z
Asciz	$this;
Asciz	Lscala/Function2$mcZLL$sp;;
Asciz	v1;
Asciz	J;
Asciz	v2;
Asciz	LocalVariableTable;
Asciz	curried;
Asciz	(Lscala/Function2$mcZLL$sp;)Lscala/Function1;;
Asciz	scala/Function2$mcZLL$sp;
class	scala/Function2$mcZLL$sp
Asciz	curried$mcZLL$sp;
Asciz	()Lscala/Function1;;
NameAndType	curried$mcZLL$sp:()Lscala/Function1;
InterfaceMethod	scala/Function2$mcZLL$sp.curried$mcZLL$sp:()Lscala/Function1;
Asciz	scala/Function2$mcZLL$sp$$anonfun$curried$mcZLL$sp$1;
class	scala/Function2$mcZLL$sp$$anonfun$curried$mcZLL$sp$1
Asciz	<init>;
Asciz	(Lscala/Function2$mcZLL$sp;)V;
NameAndType	"<init>":(Lscala/Function2$mcZLL$sp;)V
Method	scala/Function2$mcZLL$sp$$anonfun$curried$mcZLL$sp$1."<init>":(Lscala/Function2$mcZLL$sp;)V
Asciz	curry;
Asciz	curry$mcZLL$sp;
NameAndType	curry$mcZLL$sp:()Lscala/Function1;
InterfaceMethod	scala/Function2$mcZLL$sp.curry$mcZLL$sp:()Lscala/Function1;
Asciz	Deprecated;
Asciz	tupled;
Asciz	tupled$mcZLL$sp;
NameAndType	tupled$mcZLL$sp:()Lscala/Function1;
InterfaceMethod	scala/Function2$mcZLL$sp.tupled$mcZLL$sp:()Lscala/Function1;
Asciz	scala/Function2$mcZLL$sp$$anonfun$tupled$mcZLL$sp$1;
class	scala/Function2$mcZLL$sp$$anonfun$tupled$mcZLL$sp$1
Method	scala/Function2$mcZLL$sp$$anonfun$tupled$mcZLL$sp$1."<init>":(Lscala/Function2$mcZLL$sp;)V
Asciz	$init$;
Asciz	Scala;
Asciz	InnerClasses;
Asciz	$anonfun$tupled$mcZLL$sp$1;
Asciz	$anonfun$curried$mcZLL$sp$1;
Asciz	scala/Function2$mcZLL$sp$class;
class	scala/Function2$mcZLL$sp$class
Asciz	java/lang/Object;
class	java/lang/Object

{
public static boolean apply(scala.Function2$mcZLL$sp, long, long);
  Signature: (Lscala/Function2$mcZLL$sp;JJ)Z
  Code:
   Stack=5, Locals=5, Args_size=3
	aload_0
	lload_1
	lload_3
	invokeinterface	InterfaceMethod scala/Function2.apply$mcZLL$sp:(JJ)Z
	ireturn
  Labels:
  LocalVariableTable: 
   Start  Length  Slot  Name   Signature
   0      9      0    $this       Lscala/Function2$mcZLL$sp;
   0      9      1    v1       J
   0      9      3    v2       J


public static scala.Function1 curried(scala.Function2$mcZLL$sp);
  Signature: (Lscala/Function2$mcZLL$sp;)Lscala/Function1;
  Code:
   Stack=1, Locals=1, Args_size=1
	aload_0
	invokeinterface	InterfaceMethod scala/Function2$mcZLL$sp.curried$mcZLL$sp:()Lscala/Function1;
	areturn
  Labels:
  LocalVariableTable: 
   Start  Length  Slot  Name   Signature
   0      7      0    $this       Lscala/Function2$mcZLL$sp;


public static scala.Function1 curried$mcZLL$sp(scala.Function2$mcZLL$sp);
  Signature: (Lscala/Function2$mcZLL$sp;)Lscala/Function1;
  Code:
   Stack=3, Locals=1, Args_size=1
	new	class scala/Function2$mcZLL$sp$$anonfun$curried$mcZLL$sp$1
	dup
	aload_0
	invokespecial	Method scala/Function2$mcZLL$sp$$anonfun$curried$mcZLL$sp$1."<init>":(Lscala/Function2$mcZLL$sp;)V
	areturn
  Labels:
  LocalVariableTable: 
   Start  Length  Slot  Name   Signature
   0      9      0    $this       Lscala/Function2$mcZLL$sp;


public static scala.Function1 curry(scala.Function2$mcZLL$sp);
  Signature: (Lscala/Function2$mcZLL$sp;)Lscala/Function1;
  Code:
   Stack=1, Locals=1, Args_size=1
	aload_0
	invokeinterface	InterfaceMethod scala/Function2$mcZLL$sp.curry$mcZLL$sp:()Lscala/Function1;
	areturn
  Labels:
  LocalVariableTable: 
   Start  Length  Slot  Name   Signature
   0      7      0    $this       Lscala/Function2$mcZLL$sp;

  Deprecated: true

public static scala.Function1 curry$mcZLL$sp(scala.Function2$mcZLL$sp);
  Signature: (Lscala/Function2$mcZLL$sp;)Lscala/Function1;
  Code:
   Stack=1, Locals=1, Args_size=1
	aload_0
	invokeinterface	InterfaceMethod scala/Function2$mcZLL$sp.curried$mcZLL$sp:()Lscala/Function1;
	areturn
  Labels:
  LocalVariableTable: 
   Start  Length  Slot  Name   Signature
   0      7      0    $this       Lscala/Function2$mcZLL$sp;

  Deprecated: true

public static scala.Function1 tupled(scala.Function2$mcZLL$sp);
  Signature: (Lscala/Function2$mcZLL$sp;)Lscala/Function1;
  Code:
   Stack=1, Locals=1, Args_size=1
	aload_0
	invokeinterface	InterfaceMethod scala/Function2$mcZLL$sp.tupled$mcZLL$sp:()Lscala/Function1;
	areturn
  Labels:
  LocalVariableTable: 
   Start  Length  Slot  Name   Signature
   0      7      0    $this       Lscala/Function2$mcZLL$sp;


public static scala.Function1 tupled$mcZLL$sp(scala.Function2$mcZLL$sp);
  Signature: (Lscala/Function2$mcZLL$sp;)Lscala/Function1;
  Code:
   Stack=3, Locals=1, Args_size=1
	new	class scala/Function2$mcZLL$sp$$anonfun$tupled$mcZLL$sp$1
	dup
	aload_0
	invokespecial	Method scala/Function2$mcZLL$sp$$anonfun$tupled$mcZLL$sp$1."<init>":(Lscala/Function2$mcZLL$sp;)V
	areturn
  Labels:
  LocalVariableTable: 
   Start  Length  Slot  Name   Signature
   0      9      0    $this       Lscala/Function2$mcZLL$sp;


public static void $init$(scala.Function2$mcZLL$sp);
  Signature: (Lscala/Function2$mcZLL$sp;)V
  Code:
   Stack=0, Locals=1, Args_size=1
	return
  Labels:
  LocalVariableTable: 
   Start  Length  Slot  Name   Signature
   0      1      0    $this       Lscala/Function2$mcZLL$sp;


}

