Compiled from "Function.scala"
public final class scala.Function$$anonfun$untupled$2 extends scala.runtime.AbstractFunction3 implements java.io.Serializable
  SourceFile: "Function.scala"
  Scala: length = 0x
   
  InnerClass: 
   public final $anonfun$untupled$2=class scala/Function$$anonfun$untupled$2 of class scala/Function
  minor version: 0
  major version: 49
  Constant pool:
Asciz	SourceFile;
Asciz	Function.scala;
Asciz	<clinit>;
Asciz	()V;
Asciz	Code;
Asciz	serialVersionUID;
Asciz	J;
Asciz	scala/Function$$anonfun$untupled$2;
class	scala/Function$$anonfun$untupled$2
NameAndType	serialVersionUID:J
Field	scala/Function$$anonfun$untupled$2.serialVersionUID:J
Asciz	f$14;
Asciz	Lscala/Function1;;
Asciz	apply;
Asciz	(Ljava/lang/Object;Ljava/lang/Object;Ljava/lang/Object;)Ljava/lang/Object;;
Asciz	LineNumberTable;
NameAndType	f$14:Lscala/Function1;
Field	scala/Function$$anonfun$untupled$2.f$14:Lscala/Function1;
Asciz	scala/Tuple3;
class	scala/Tuple3
Asciz	<init>;
Asciz	(Ljava/lang/Object;Ljava/lang/Object;Ljava/lang/Object;)V;
NameAndType	"<init>":(Ljava/lang/Object;Ljava/lang/Object;Ljava/lang/Object;)V
Method	scala/Tuple3."<init>":(Ljava/lang/Object;Ljava/lang/Object;Ljava/lang/Object;)V
Asciz	scala/Function1;
class	scala/Function1
Asciz	(Ljava/lang/Object;)Ljava/lang/Object;;
NameAndType	apply:(Ljava/lang/Object;)Ljava/lang/Object;
InterfaceMethod	scala/Function1.apply:(Ljava/lang/Object;)Ljava/lang/Object;
Asciz	this;
Asciz	Lscala/Function$$anonfun$untupled$2;;
Asciz	x1;
Asciz	Ljava/lang/Object;;
Asciz	x2;
Asciz	x3;
Asciz	LocalVariableTable;
Asciz	(Ta1;Ta2;Ta3;)Tb;;
Asciz	Signature;
Asciz	(Lscala/Function1;)V;
Asciz	scala/runtime/AbstractFunction3;
class	scala/runtime/AbstractFunction3
NameAndType	"<init>":()V
Method	scala/runtime/AbstractFunction3."<init>":()V
Asciz	Scala;
Asciz	InnerClasses;
Asciz	scala/Function;
class	scala/Function
Asciz	$anonfun$untupled$2;
Asciz	java/io/Serializable;
class	java/io/Serializable

{
public static final long serialVersionUID;
  Signature: J

private final scala.Function1 f$14;
  Signature: Lscala/Function1;

public static {};
  Signature: ()V
  Code:
   Stack=2, Locals=0, Args_size=0
	lconst_0
	putstatic	Field serialVersionUID:J
	return
  Labels:

public final java.lang.Object apply(java.lang.Object, java.lang.Object, java.lang.Object);
  Signature: (Ljava/lang/Object;Ljava/lang/Object;Ljava/lang/Object;)Ljava/lang/Object;
  Code:
   Stack=6, Locals=4, Args_size=4
	aload_0
	getfield	Field f$14:Lscala/Function1;
	new	class scala/Tuple3
	dup
	aload_1
	aload_2
	aload_3
	invokespecial	Method scala/Tuple3."<init>":(Ljava/lang/Object;Ljava/lang/Object;Ljava/lang/Object;)V
	invokeinterface	InterfaceMethod scala/Function1.apply:(Ljava/lang/Object;)Ljava/lang/Object;
	areturn
  Labels:
  LocalVariableTable: 
   Start  Length  Slot  Name   Signature
   0      20      0    this       Lscala/Function$$anonfun$untupled$2;
   0      20      1    x1       Ljava/lang/Object;
   0      20      2    x2       Ljava/lang/Object;
   0      20      3    x3       Ljava/lang/Object;

  Signature: length = 0x2
   00 25 

public scala.Function$$anonfun$untupled$2(scala.Function1);
  Signature: (Lscala/Function1;)V
  Code:
   Stack=2, Locals=2, Args_size=2
	aload_0
	aload_1
	putfield	Field f$14:Lscala/Function1;
	aload_0
	invokespecial	Method scala/runtime/AbstractFunction3."<init>":()V
	return
  Labels:

}

