Compiled from "Function2.scala"
public abstract class scala.Function2$mcLLI$sp$class extends java.lang.Object
  SourceFile: "Function2.scala"
  Scala: length = 0x
   
  InnerClass: 
   public final $anonfun$tupled$mcLLI$sp$1=class scala/Function2$mcLLI$sp$$anonfun$tupled$mcLLI$sp$1 of class scala/Function2$mcLLI$sp
   public final $anonfun$curried$mcLLI$sp$1=class scala/Function2$mcLLI$sp$$anonfun$curried$mcLLI$sp$1 of class scala/Function2$mcLLI$sp
  minor version: 0
  major version: 49
  Constant pool:
Asciz	SourceFile;
Asciz	Function2.scala;
Asciz	apply;
Asciz	(Lscala/Function2$mcLLI$sp;JI)J;
Asciz	Code;
Asciz	LineNumberTable;
Asciz	scala/Function2;
class	scala/Function2
Asciz	apply$mcLLI$sp;
Asciz	(JI)J;
NameAndType	apply$mcLLI$sp:(JI)J
InterfaceMethod	scala/Function2.apply$mcLLI$sp:(JI)J
Asciz	$this;
Asciz	Lscala/Function2$mcLLI$sp;;
Asciz	v1;
Asciz	J;
Asciz	v2;
Asciz	I;
Asciz	LocalVariableTable;
Asciz	curried;
Asciz	(Lscala/Function2$mcLLI$sp;)Lscala/Function1;;
Asciz	scala/Function2$mcLLI$sp;
class	scala/Function2$mcLLI$sp
Asciz	curried$mcLLI$sp;
Asciz	()Lscala/Function1;;
NameAndType	curried$mcLLI$sp:()Lscala/Function1;
InterfaceMethod	scala/Function2$mcLLI$sp.curried$mcLLI$sp:()Lscala/Function1;
Asciz	scala/Function2$mcLLI$sp$$anonfun$curried$mcLLI$sp$1;
class	scala/Function2$mcLLI$sp$$anonfun$curried$mcLLI$sp$1
Asciz	<init>;
Asciz	(Lscala/Function2$mcLLI$sp;)V;
NameAndType	"<init>":(Lscala/Function2$mcLLI$sp;)V
Method	scala/Function2$mcLLI$sp$$anonfun$curried$mcLLI$sp$1."<init>":(Lscala/Function2$mcLLI$sp;)V
Asciz	curry;
Asciz	curry$mcLLI$sp;
NameAndType	curry$mcLLI$sp:()Lscala/Function1;
InterfaceMethod	scala/Function2$mcLLI$sp.curry$mcLLI$sp:()Lscala/Function1;
Asciz	Deprecated;
Asciz	tupled;
Asciz	tupled$mcLLI$sp;
NameAndType	tupled$mcLLI$sp:()Lscala/Function1;
InterfaceMethod	scala/Function2$mcLLI$sp.tupled$mcLLI$sp:()Lscala/Function1;
Asciz	scala/Function2$mcLLI$sp$$anonfun$tupled$mcLLI$sp$1;
class	scala/Function2$mcLLI$sp$$anonfun$tupled$mcLLI$sp$1
Method	scala/Function2$mcLLI$sp$$anonfun$tupled$mcLLI$sp$1."<init>":(Lscala/Function2$mcLLI$sp;)V
Asciz	$init$;
Asciz	Scala;
Asciz	InnerClasses;
Asciz	$anonfun$tupled$mcLLI$sp$1;
Asciz	$anonfun$curried$mcLLI$sp$1;
Asciz	scala/Function2$mcLLI$sp$class;
class	scala/Function2$mcLLI$sp$class
Asciz	java/lang/Object;
class	java/lang/Object

{
public static long apply(scala.Function2$mcLLI$sp, long, int);
  Signature: (Lscala/Function2$mcLLI$sp;JI)J
  Code:
   Stack=4, Locals=4, Args_size=3
	aload_0
	lload_1
	iload_3
	invokeinterface	InterfaceMethod scala/Function2.apply$mcLLI$sp:(JI)J
	lreturn
  Labels:
  LocalVariableTable: 
   Start  Length  Slot  Name   Signature
   0      9      0    $this       Lscala/Function2$mcLLI$sp;
   0      9      1    v1       J
   0      9      3    v2       I


public static scala.Function1 curried(scala.Function2$mcLLI$sp);
  Signature: (Lscala/Function2$mcLLI$sp;)Lscala/Function1;
  Code:
   Stack=1, Locals=1, Args_size=1
	aload_0
	invokeinterface	InterfaceMethod scala/Function2$mcLLI$sp.curried$mcLLI$sp:()Lscala/Function1;
	areturn
  Labels:
  LocalVariableTable: 
   Start  Length  Slot  Name   Signature
   0      7      0    $this       Lscala/Function2$mcLLI$sp;


public static scala.Function1 curried$mcLLI$sp(scala.Function2$mcLLI$sp);
  Signature: (Lscala/Function2$mcLLI$sp;)Lscala/Function1;
  Code:
   Stack=3, Locals=1, Args_size=1
	new	class scala/Function2$mcLLI$sp$$anonfun$curried$mcLLI$sp$1
	dup
	aload_0
	invokespecial	Method scala/Function2$mcLLI$sp$$anonfun$curried$mcLLI$sp$1."<init>":(Lscala/Function2$mcLLI$sp;)V
	areturn
  Labels:
  LocalVariableTable: 
   Start  Length  Slot  Name   Signature
   0      9      0    $this       Lscala/Function2$mcLLI$sp;


public static scala.Function1 curry(scala.Function2$mcLLI$sp);
  Signature: (Lscala/Function2$mcLLI$sp;)Lscala/Function1;
  Code:
   Stack=1, Locals=1, Args_size=1
	aload_0
	invokeinterface	InterfaceMethod scala/Function2$mcLLI$sp.curry$mcLLI$sp:()Lscala/Function1;
	areturn
  Labels:
  LocalVariableTable: 
   Start  Length  Slot  Name   Signature
   0      7      0    $this       Lscala/Function2$mcLLI$sp;

  Deprecated: true

public static scala.Function1 curry$mcLLI$sp(scala.Function2$mcLLI$sp);
  Signature: (Lscala/Function2$mcLLI$sp;)Lscala/Function1;
  Code:
   Stack=1, Locals=1, Args_size=1
	aload_0
	invokeinterface	InterfaceMethod scala/Function2$mcLLI$sp.curried$mcLLI$sp:()Lscala/Function1;
	areturn
  Labels:
  LocalVariableTable: 
   Start  Length  Slot  Name   Signature
   0      7      0    $this       Lscala/Function2$mcLLI$sp;

  Deprecated: true

public static scala.Function1 tupled(scala.Function2$mcLLI$sp);
  Signature: (Lscala/Function2$mcLLI$sp;)Lscala/Function1;
  Code:
   Stack=1, Locals=1, Args_size=1
	aload_0
	invokeinterface	InterfaceMethod scala/Function2$mcLLI$sp.tupled$mcLLI$sp:()Lscala/Function1;
	areturn
  Labels:
  LocalVariableTable: 
   Start  Length  Slot  Name   Signature
   0      7      0    $this       Lscala/Function2$mcLLI$sp;


public static scala.Function1 tupled$mcLLI$sp(scala.Function2$mcLLI$sp);
  Signature: (Lscala/Function2$mcLLI$sp;)Lscala/Function1;
  Code:
   Stack=3, Locals=1, Args_size=1
	new	class scala/Function2$mcLLI$sp$$anonfun$tupled$mcLLI$sp$1
	dup
	aload_0
	invokespecial	Method scala/Function2$mcLLI$sp$$anonfun$tupled$mcLLI$sp$1."<init>":(Lscala/Function2$mcLLI$sp;)V
	areturn
  Labels:
  LocalVariableTable: 
   Start  Length  Slot  Name   Signature
   0      9      0    $this       Lscala/Function2$mcLLI$sp;


public static void $init$(scala.Function2$mcLLI$sp);
  Signature: (Lscala/Function2$mcLLI$sp;)V
  Code:
   Stack=0, Locals=1, Args_size=1
	return
  Labels:
  LocalVariableTable: 
   Start  Length  Slot  Name   Signature
   0      1      0    $this       Lscala/Function2$mcLLI$sp;


}

