Compiled from "Function1.scala"
public abstract class scala.Function1$mcVD$sp$class extends java.lang.Object
  SourceFile: "Function1.scala"
  Scala: length = 0x
   
  InnerClass: 
   public final $anonfun$andThen$mcVD$sp$1=class scala/Function1$mcVD$sp$$anonfun$andThen$mcVD$sp$1 of class scala/Function1$mcVD$sp
   public final $anonfun$compose$mcVD$sp$1=class scala/Function1$mcVD$sp$$anonfun$compose$mcVD$sp$1 of class scala/Function1$mcVD$sp
  minor version: 0
  major version: 49
  Constant pool:
Asciz	SourceFile;
Asciz	Function1.scala;
Asciz	apply;
Asciz	(Lscala/Function1$mcVD$sp;D)V;
Asciz	Code;
Asciz	LineNumberTable;
Asciz	scala/Function1;
class	scala/Function1
Asciz	apply$mcVD$sp;
Asciz	(D)V;
NameAndType	apply$mcVD$sp:(D)V
InterfaceMethod	scala/Function1.apply$mcVD$sp:(D)V
Asciz	$this;
Asciz	Lscala/Function1$mcVD$sp;;
Asciz	v1;
Asciz	D;
Asciz	LocalVariableTable;
Asciz	compose;
Asciz	(Lscala/Function1$mcVD$sp;Lscala/Function1;)Lscala/Function1;;
Asciz	scala/Function1$mcVD$sp;
class	scala/Function1$mcVD$sp
Asciz	compose$mcVD$sp;
Asciz	(Lscala/Function1;)Lscala/Function1;;
NameAndType	compose$mcVD$sp:(Lscala/Function1;)Lscala/Function1;
InterfaceMethod	scala/Function1$mcVD$sp.compose$mcVD$sp:(Lscala/Function1;)Lscala/Function1;
Asciz	g;
Asciz	Lscala/Function1;;
Asciz	scala/Function1$mcVD$sp$$anonfun$compose$mcVD$sp$1;
class	scala/Function1$mcVD$sp$$anonfun$compose$mcVD$sp$1
Asciz	<init>;
Asciz	(Lscala/Function1$mcVD$sp;Lscala/Function1;)V;
NameAndType	"<init>":(Lscala/Function1$mcVD$sp;Lscala/Function1;)V
Method	scala/Function1$mcVD$sp$$anonfun$compose$mcVD$sp$1."<init>":(Lscala/Function1$mcVD$sp;Lscala/Function1;)V
Asciz	g$23;
Asciz	andThen;
Asciz	andThen$mcVD$sp;
NameAndType	andThen$mcVD$sp:(Lscala/Function1;)Lscala/Function1;
InterfaceMethod	scala/Function1$mcVD$sp.andThen$mcVD$sp:(Lscala/Function1;)Lscala/Function1;
Asciz	scala/Function1$mcVD$sp$$anonfun$andThen$mcVD$sp$1;
class	scala/Function1$mcVD$sp$$anonfun$andThen$mcVD$sp$1
Method	scala/Function1$mcVD$sp$$anonfun$andThen$mcVD$sp$1."<init>":(Lscala/Function1$mcVD$sp;Lscala/Function1;)V
Asciz	g$24;
Asciz	$init$;
Asciz	(Lscala/Function1$mcVD$sp;)V;
Asciz	Scala;
Asciz	InnerClasses;
Asciz	$anonfun$andThen$mcVD$sp$1;
Asciz	$anonfun$compose$mcVD$sp$1;
Asciz	scala/Function1$mcVD$sp$class;
class	scala/Function1$mcVD$sp$class
Asciz	java/lang/Object;
class	java/lang/Object

{
public static void apply(scala.Function1$mcVD$sp, double);
  Signature: (Lscala/Function1$mcVD$sp;D)V
  Code:
   Stack=3, Locals=3, Args_size=2
	aload_0
	dload_1
	invokeinterface	InterfaceMethod scala/Function1.apply$mcVD$sp:(D)V
	return
  Labels:
  LocalVariableTable: 
   Start  Length  Slot  Name   Signature
   0      8      0    $this       Lscala/Function1$mcVD$sp;
   0      8      1    v1       D


public static scala.Function1 compose(scala.Function1$mcVD$sp, scala.Function1);
  Signature: (Lscala/Function1$mcVD$sp;Lscala/Function1;)Lscala/Function1;
  Code:
   Stack=2, Locals=2, Args_size=2
	aload_0
	aload_1
	invokeinterface	InterfaceMethod scala/Function1$mcVD$sp.compose$mcVD$sp:(Lscala/Function1;)Lscala/Function1;
	areturn
  Labels:
  LocalVariableTable: 
   Start  Length  Slot  Name   Signature
   0      8      0    $this       Lscala/Function1$mcVD$sp;
   0      8      1    g       Lscala/Function1;


public static scala.Function1 compose$mcVD$sp(scala.Function1$mcVD$sp, scala.Function1);
  Signature: (Lscala/Function1$mcVD$sp;Lscala/Function1;)Lscala/Function1;
  Code:
   Stack=4, Locals=2, Args_size=2
	new	class scala/Function1$mcVD$sp$$anonfun$compose$mcVD$sp$1
	dup
	aload_0
	aload_1
	invokespecial	Method scala/Function1$mcVD$sp$$anonfun$compose$mcVD$sp$1."<init>":(Lscala/Function1$mcVD$sp;Lscala/Function1;)V
	areturn
  Labels:
  LocalVariableTable: 
   Start  Length  Slot  Name   Signature
   0      10      0    $this       Lscala/Function1$mcVD$sp;
   0      10      1    g$23       Lscala/Function1;


public static scala.Function1 andThen(scala.Function1$mcVD$sp, scala.Function1);
  Signature: (Lscala/Function1$mcVD$sp;Lscala/Function1;)Lscala/Function1;
  Code:
   Stack=2, Locals=2, Args_size=2
	aload_0
	aload_1
	invokeinterface	InterfaceMethod scala/Function1$mcVD$sp.andThen$mcVD$sp:(Lscala/Function1;)Lscala/Function1;
	areturn
  Labels:
  LocalVariableTable: 
   Start  Length  Slot  Name   Signature
   0      8      0    $this       Lscala/Function1$mcVD$sp;
   0      8      1    g       Lscala/Function1;


public static scala.Function1 andThen$mcVD$sp(scala.Function1$mcVD$sp, scala.Function1);
  Signature: (Lscala/Function1$mcVD$sp;Lscala/Function1;)Lscala/Function1;
  Code:
   Stack=4, Locals=2, Args_size=2
	new	class scala/Function1$mcVD$sp$$anonfun$andThen$mcVD$sp$1
	dup
	aload_0
	aload_1
	invokespecial	Method scala/Function1$mcVD$sp$$anonfun$andThen$mcVD$sp$1."<init>":(Lscala/Function1$mcVD$sp;Lscala/Function1;)V
	areturn
  Labels:
  LocalVariableTable: 
   Start  Length  Slot  Name   Signature
   0      10      0    $this       Lscala/Function1$mcVD$sp;
   0      10      1    g$24       Lscala/Function1;


public static void $init$(scala.Function1$mcVD$sp);
  Signature: (Lscala/Function1$mcVD$sp;)V
  Code:
   Stack=0, Locals=1, Args_size=1
	return
  Labels:
  LocalVariableTable: 
   Start  Length  Slot  Name   Signature
   0      1      0    $this       Lscala/Function1$mcVD$sp;


}

