Compiled from "Function22.scala"
public abstract class scala.Function22$class extends java.lang.Object
  SourceFile: "Function22.scala"
  Scala: length = 0x
   
  InnerClass: 
   public final #29= #19 of #28; //$anonfun$curry$1=class scala/Function22$$anonfun$curry$1 of class scala/Function22
   public final #30= #13 of #28; //$anonfun$tuple$1=class scala/Function22$$anonfun$tuple$1 of class scala/Function22
  minor version: 0
  major version: 49
  Constant pool:
const #1 = Asciz	SourceFile;
const #2 = Asciz	Function22.scala;
const #3 = Asciz	$init$;
const #4 = Asciz	(Lscala/Function22;)V;
const #5 = Asciz	Code;
const #6 = Asciz	LineNumberTable;
const #7 = Asciz	$this;
const #8 = Asciz	Lscala/Function22;;
const #9 = Asciz	LocalVariableTable;
const #10 = Asciz	tuple;
const #11 = Asciz	(Lscala/Function22;)Lscala/Function1;;
const #12 = Asciz	scala/Function22$$anonfun$tuple$1;
const #13 = class	#12;	//  scala/Function22$$anonfun$tuple$1
const #14 = Asciz	<init>;
const #15 = NameAndType	#14:#4;//  "<init>":(Lscala/Function22;)V
const #16 = Method	#13.#15;	//  scala/Function22$$anonfun$tuple$1."<init>":(Lscala/Function22;)V
const #17 = Asciz	curry;
const #18 = Asciz	scala/Function22$$anonfun$curry$1;
const #19 = class	#18;	//  scala/Function22$$anonfun$curry$1
const #20 = Method	#19.#15;	//  scala/Function22$$anonfun$curry$1."<init>":(Lscala/Function22;)V
const #21 = Asciz	toString;
const #22 = Asciz	(Lscala/Function22;)Ljava/lang/String;;
const #23 = Asciz	<function22>;
const #24 = String	#23;	//  <function22>
const #25 = Asciz	Scala;
const #26 = Asciz	InnerClasses;
const #27 = Asciz	scala/Function22;
const #28 = class	#27;	//  scala/Function22
const #29 = Asciz	$anonfun$curry$1;
const #30 = Asciz	$anonfun$tuple$1;
const #31 = Asciz	scala/Function22$class;
const #32 = class	#31;	//  scala/Function22$class
const #33 = Asciz	java/lang/Object;
const #34 = class	#33;	//  java/lang/Object

{
public static void $init$(scala.Function22);
  Code:
   Stack=0, Locals=1, Args_size=1
   0:	return
  LineNumberTable: 
   line 22: 0

  LocalVariableTable: 
   Start  Length  Slot  Name   Signature
   0      1      0    $this       Lscala/Function22;


public static scala.Function1 tuple(scala.Function22);
  Code:
   Stack=3, Locals=1, Args_size=1
   0:	new	#13; //class scala/Function22$$anonfun$tuple$1
   3:	dup
   4:	aload_0
   5:	invokespecial	#16; //Method scala/Function22$$anonfun$tuple$1."<init>":(Lscala/Function22;)V
   8:	areturn
  LineNumberTable: 
   line 34: 0

  LocalVariableTable: 
   Start  Length  Slot  Name   Signature
   0      9      0    $this       Lscala/Function22;


public static scala.Function1 curry(scala.Function22);
  Code:
   Stack=3, Locals=1, Args_size=1
   0:	new	#19; //class scala/Function22$$anonfun$curry$1
   3:	dup
   4:	aload_0
   5:	invokespecial	#20; //Method scala/Function22$$anonfun$curry$1."<init>":(Lscala/Function22;)V
   8:	areturn
  LineNumberTable: 
   line 29: 0

  LocalVariableTable: 
   Start  Length  Slot  Name   Signature
   0      9      0    $this       Lscala/Function22;


public static java.lang.String toString(scala.Function22);
  Code:
   Stack=1, Locals=1, Args_size=1
   0:	ldc	#24; //String <function22>
   2:	areturn
  LineNumberTable: 
   line 24: 0

  LocalVariableTable: 
   Start  Length  Slot  Name   Signature
   0      3      0    $this       Lscala/Function22;


}

