Compiled from "Function22.scala"
public final class scala.Function22$$anonfun$curried$1$$anonfun$apply$1 extends scala.runtime.AbstractFunction21 implements java.io.Serializable
  SourceFile: "Function22.scala"
  Scala: length = 0x
   
  InnerClass: 
   public final $anonfun$curried$1=class scala/Function22$$anonfun$curried$1 of class scala/Function22
   public final $anonfun$apply$1=class scala/Function22$$anonfun$curried$1$$anonfun$apply$1 of class scala/Function22$$anonfun$curried$1
  minor version: 0
  major version: 49
  Constant pool:
Asciz	SourceFile;
Asciz	Function22.scala;
Asciz	<clinit>;
Asciz	()V;
Asciz	Code;
Asciz	serialVersionUID;
Asciz	J;
Asciz	scala/Function22$$anonfun$curried$1$$anonfun$apply$1;
class	scala/Function22$$anonfun$curried$1$$anonfun$apply$1
NameAndType	serialVersionUID:J
Field	scala/Function22$$anonfun$curried$1$$anonfun$apply$1.serialVersionUID:J
Asciz	$outer;
Asciz	Lscala/Function22$$anonfun$curried$1;;
Asciz	x1$1;
Asciz	Ljava/lang/Object;;
Asciz	apply;
Asciz	(Ljava/lang/Object;Ljava/lang/Object;Ljava/lang/Object;Ljava/lang/Object;Ljava/lang/Object;Ljava/lang/Object;Ljava/lang/Object;Ljava/lang/Object;Ljava/lang/Object;Ljava/lang/Object;Ljava/lang/Object;Ljava/lang/Object;Ljava/lang/Object;Ljava/lang/Object;Ljava/lang/Object;Ljava/lang/Object;Ljava/lang/Object;Ljava/lang/Object;Ljava/lang/Object;Ljava/lang/Object;Ljava/lang/Object;)Ljava/lang/Object;;
Asciz	LineNumberTable;
NameAndType	$outer:Lscala/Function22$$anonfun$curried$1;
Field	scala/Function22$$anonfun$curried$1$$anonfun$apply$1.$outer:Lscala/Function22$$anonfun$curried$1;
Asciz	scala/Function22$$anonfun$curried$1;
class	scala/Function22$$anonfun$curried$1
Asciz	Lscala/Function22;;
NameAndType	$outer:Lscala/Function22;
Field	scala/Function22$$anonfun$curried$1.$outer:Lscala/Function22;
NameAndType	x1$1:Ljava/lang/Object;
Field	scala/Function22$$anonfun$curried$1$$anonfun$apply$1.x1$1:Ljava/lang/Object;
Asciz	scala/Function22;
class	scala/Function22
Asciz	(Ljava/lang/Object;Ljava/lang/Object;Ljava/lang/Object;Ljava/lang/Object;Ljava/lang/Object;Ljava/lang/Object;Ljava/lang/Object;Ljava/lang/Object;Ljava/lang/Object;Ljava/lang/Object;Ljava/lang/Object;Ljava/lang/Object;Ljava/lang/Object;Ljava/lang/Object;Ljava/lang/Object;Ljava/lang/Object;Ljava/lang/Object;Ljava/lang/Object;Ljava/lang/Object;Ljava/lang/Object;Ljava/lang/Object;Ljava/lang/Object;)Ljava/lang/Object;;
NameAndType	apply:(Ljava/lang/Object;Ljava/lang/Object;Ljava/lang/Object;Ljava/lang/Object;Ljava/lang/Object;Ljava/lang/Object;Ljava/lang/Object;Ljava/lang/Object;Ljava/lang/Object;Ljava/lang/Object;Ljava/lang/Object;Ljava/lang/Object;Ljava/lang/Object;Ljava/lang/Object;Ljava/lang/Object;Ljava/lang/Object;Ljava/lang/Object;Ljava/lang/Object;Ljava/lang/Object;Ljava/lang/Object;Ljava/lang/Object;Ljava/lang/Object;)Ljava/lang/Object;
InterfaceMethod	scala/Function22.apply:(Ljava/lang/Object;Ljava/lang/Object;Ljava/lang/Object;Ljava/lang/Object;Ljava/lang/Object;Ljava/lang/Object;Ljava/lang/Object;Ljava/lang/Object;Ljava/lang/Object;Ljava/lang/Object;Ljava/lang/Object;Ljava/lang/Object;Ljava/lang/Object;Ljava/lang/Object;Ljava/lang/Object;Ljava/lang/Object;Ljava/lang/Object;Ljava/lang/Object;Ljava/lang/Object;Ljava/lang/Object;Ljava/lang/Object;Ljava/lang/Object;)Ljava/lang/Object;
Asciz	this;
Asciz	Lscala/Function22$$anonfun$curried$1$$anonfun$apply$1;;
Asciz	x2;
Asciz	x3;
Asciz	x4;
Asciz	x5;
Asciz	x6;
Asciz	x7;
Asciz	x8;
Asciz	x9;
Asciz	x10;
Asciz	x11;
Asciz	x12;
Asciz	x13;
Asciz	x14;
Asciz	x15;
Asciz	x16;
Asciz	x17;
Asciz	x18;
Asciz	x19;
Asciz	x20;
Asciz	x21;
Asciz	x22;
Asciz	LocalVariableTable;
Asciz	(TT2;TT3;TT4;TT5;TT6;TT7;TT8;TT9;TT10;TT11;TT12;TT13;TT14;TT15;TT16;TT17;TT18;TT19;TT20;TT21;TT22;)TR;;
Asciz	Signature;
Asciz	<init>;
Asciz	(Lscala/Function22$$anonfun$curried$1;Ljava/lang/Object;)V;
Asciz	java/lang/NullPointerException;
class	java/lang/NullPointerException
NameAndType	"<init>":()V
Method	java/lang/NullPointerException."<init>":()V
Asciz	scala/runtime/AbstractFunction21;
class	scala/runtime/AbstractFunction21
Method	scala/runtime/AbstractFunction21."<init>":()V
Asciz	(Lscala/Function22<TT1;TT2;TT3;TT4;TT5;TT6;TT7;TT8;TT9;TT10;TT11;TT12;TT13;TT14;TT15;TT16;TT17;TT18;TT19;TT20;TT21;TT22;TR;>.$anonfun$curried$1;)V;
Asciz	Scala;
Asciz	InnerClasses;
Asciz	$anonfun$curried$1;
Asciz	$anonfun$apply$1;
Asciz	java/io/Serializable;
class	java/io/Serializable

{
public static final long serialVersionUID;
  Signature: J

private final scala.Function22$$anonfun$curried$1 $outer;
  Signature: Lscala/Function22$$anonfun$curried$1;

private final java.lang.Object x1$1;
  Signature: Ljava/lang/Object;

public static {};
  Signature: ()V
  Code:
   Stack=2, Locals=0, Args_size=0
	lconst_0
	putstatic	Field serialVersionUID:J
	return
  Labels:

public final java.lang.Object apply(java.lang.Object, java.lang.Object, java.lang.Object, java.lang.Object, java.lang.Object, java.lang.Object, java.lang.Object, java.lang.Object, java.lang.Object, java.lang.Object, java.lang.Object, java.lang.Object, java.lang.Object, java.lang.Object, java.lang.Object, java.lang.Object, java.lang.Object, java.lang.Object, java.lang.Object, java.lang.Object, java.lang.Object);
  Signature: (Ljava/lang/Object;Ljava/lang/Object;Ljava/lang/Object;Ljava/lang/Object;Ljava/lang/Object;Ljava/lang/Object;Ljava/lang/Object;Ljava/lang/Object;Ljava/lang/Object;Ljava/lang/Object;Ljava/lang/Object;Ljava/lang/Object;Ljava/lang/Object;Ljava/lang/Object;Ljava/lang/Object;Ljava/lang/Object;Ljava/lang/Object;Ljava/lang/Object;Ljava/lang/Object;Ljava/lang/Object;Ljava/lang/Object;)Ljava/lang/Object;
  Code:
   Stack=23, Locals=23, Args_size=22
	aload_0
	getfield	Field $outer:Lscala/Function22$$anonfun$curried$1;
	astore	22
	aload	22
	getfield	Field scala/Function22$$anonfun$curried$1.$outer:Lscala/Function22;
	aload_0
	getfield	Field x1$1:Ljava/lang/Object;
	aload_1
	aload_2
	aload_3
	aload	4
	aload	5
	aload	6
	aload	7
	aload	8
	aload	9
	aload	10
	aload	11
	aload	12
	aload	13
	aload	14
	aload	15
	aload	16
	aload	17
	aload	18
	aload	19
	aload	20
	aload	21
	invokeinterface	InterfaceMethod scala/Function22.apply:(Ljava/lang/Object;Ljava/lang/Object;Ljava/lang/Object;Ljava/lang/Object;Ljava/lang/Object;Ljava/lang/Object;Ljava/lang/Object;Ljava/lang/Object;Ljava/lang/Object;Ljava/lang/Object;Ljava/lang/Object;Ljava/lang/Object;Ljava/lang/Object;Ljava/lang/Object;Ljava/lang/Object;Ljava/lang/Object;Ljava/lang/Object;Ljava/lang/Object;Ljava/lang/Object;Ljava/lang/Object;Ljava/lang/Object;Ljava/lang/Object;)Ljava/lang/Object;
	areturn
  Labels:
  LocalVariableTable: 
   Start  Length  Slot  Name   Signature
   0      60      0    this       Lscala/Function22$$anonfun$curried$1$$anonfun$apply$1;
   0      60      1    x2       Ljava/lang/Object;
   0      60      2    x3       Ljava/lang/Object;
   0      60      3    x4       Ljava/lang/Object;
   0      60      4    x5       Ljava/lang/Object;
   0      60      5    x6       Ljava/lang/Object;
   0      60      6    x7       Ljava/lang/Object;
   0      60      7    x8       Ljava/lang/Object;
   0      60      8    x9       Ljava/lang/Object;
   0      60      9    x10       Ljava/lang/Object;
   0      60      10    x11       Ljava/lang/Object;
   0      60      11    x12       Ljava/lang/Object;
   0      60      12    x13       Ljava/lang/Object;
   0      60      13    x14       Ljava/lang/Object;
   0      60      14    x15       Ljava/lang/Object;
   0      60      15    x16       Ljava/lang/Object;
   0      60      16    x17       Ljava/lang/Object;
   0      60      17    x18       Ljava/lang/Object;
   0      60      18    x19       Ljava/lang/Object;
   0      60      19    x20       Ljava/lang/Object;
   0      60      20    x21       Ljava/lang/Object;
   0      60      21    x22       Ljava/lang/Object;

  Signature: length = 0x2
   00 39 

public scala.Function22$$anonfun$curried$1$$anonfun$apply$1(scala.Function22$$anonfun$curried$1, java.lang.Object);
  Signature: (Lscala/Function22$$anonfun$curried$1;Ljava/lang/Object;)V
  Code:
   Stack=2, Locals=3, Args_size=3
	aload_1
	ifnonnull	l1 // aload_0
	new	class java/lang/NullPointerException
	dup
	invokespecial	Method java/lang/NullPointerException."<init>":()V
	athrow
l1	aload_0
	aload_1
	putfield	Field $outer:Lscala/Function22$$anonfun$curried$1;
	aload_0
	aload_2
	putfield	Field x1$1:Ljava/lang/Object;
	aload_0
	invokespecial	Method scala/runtime/AbstractFunction21."<init>":()V
	return
  Labels:
   	l1 = 12 // aload_0
  LocalVariableTable: 
   Start  Length  Slot  Name   Signature
   0      27      0    this       Lscala/Function22$$anonfun$curried$1$$anonfun$apply$1;
   0      27      1    $outer       Lscala/Function22$$anonfun$curried$1;

  Signature: length = 0x2
   00 44 

}

