Compiled from "Function.scala"
public final class scala.Function$$anonfun$chain$1 extends java.lang.Object implements scala.Function1,scala.ScalaObject,java.io.Serializable
  SourceFile: "Function.scala"
  Scala: length = 0x
   
  InnerClass: 
   public final $anonfun$chain$1=class scala/Function$$anonfun$chain$1 of class scala/Function
   public final $anonfun$apply$1=class scala/Function$$anonfun$chain$1$$anonfun$apply$1 of class scala/Function$$anonfun$chain$1
  minor version: 0
  major version: 49
  Constant pool:
Asciz	SourceFile;
Asciz	Function.scala;
Asciz	<clinit>;
Asciz	()V;
Asciz	Code;
Asciz	serialVersionUID;
Asciz	J;
Asciz	scala/Function$$anonfun$chain$1;
class	scala/Function$$anonfun$chain$1
NameAndType	serialVersionUID:J
Field	scala/Function$$anonfun$chain$1.serialVersionUID:J
Asciz	fs$1;
Asciz	Lscala/collection/Seq;;
Asciz	<init>;
Asciz	(Lscala/collection/Seq;)V;
Asciz	LineNumberTable;
NameAndType	fs$1:Lscala/collection/Seq;
Field	scala/Function$$anonfun$chain$1.fs$1:Lscala/collection/Seq;
Asciz	java/lang/Object;
class	java/lang/Object
NameAndType	"<init>":()V
Method	java/lang/Object."<init>":()V
Asciz	scala/Function1$class;
class	scala/Function1$class
Asciz	$init$;
Asciz	(Lscala/Function1;)V;
NameAndType	$init$:(Lscala/Function1;)V
Method	scala/Function1$class.$init$:(Lscala/Function1;)V
Asciz	apply;
Asciz	(Ljava/lang/Object;)Ljava/lang/Object;;
Asciz	scala/Function$$anonfun$chain$1$$anonfun$apply$1;
class	scala/Function$$anonfun$chain$1$$anonfun$apply$1
Asciz	(Lscala/Function$$anonfun$chain$1;)V;
NameAndType	"<init>":(Lscala/Function$$anonfun$chain$1;)V
Method	scala/Function$$anonfun$chain$1$$anonfun$apply$1."<init>":(Lscala/Function$$anonfun$chain$1;)V
Asciz	scala/collection/TraversableLike;
class	scala/collection/TraversableLike
Asciz	$div$colon;
Asciz	(Ljava/lang/Object;Lscala/Function2;)Ljava/lang/Object;;
NameAndType	$div$colon:(Ljava/lang/Object;Lscala/Function2;)Ljava/lang/Object;
InterfaceMethod	scala/collection/TraversableLike.$div$colon:(Ljava/lang/Object;Lscala/Function2;)Ljava/lang/Object;
Asciz	this;
Asciz	Lscala/Function$$anonfun$chain$1;;
Asciz	x;
Asciz	Ljava/lang/Object;;
Asciz	LocalVariableTable;
Asciz	(Ta;)Ta;;
Asciz	Signature;
Asciz	andThen;
Asciz	(Lscala/Function1;)Lscala/Function1;;
Asciz	(Lscala/Function1;Lscala/Function1;)Lscala/Function1;;
NameAndType	andThen:(Lscala/Function1;Lscala/Function1;)Lscala/Function1;
Method	scala/Function1$class.andThen:(Lscala/Function1;Lscala/Function1;)Lscala/Function1;
Asciz	g;
Asciz	Lscala/Function1;;
Asciz	compose;
NameAndType	compose:(Lscala/Function1;Lscala/Function1;)Lscala/Function1;
Method	scala/Function1$class.compose:(Lscala/Function1;Lscala/Function1;)Lscala/Function1;
Asciz	toString;
Asciz	()Ljava/lang/String;;
Asciz	(Lscala/Function1;)Ljava/lang/String;;
NameAndType	toString:(Lscala/Function1;)Ljava/lang/String;
Method	scala/Function1$class.toString:(Lscala/Function1;)Ljava/lang/String;
Asciz	Scala;
Asciz	InnerClasses;
Asciz	scala/Function;
class	scala/Function
Asciz	$anonfun$chain$1;
Asciz	$anonfun$apply$1;
Asciz	scala/Function1;
class	scala/Function1
Asciz	scala/ScalaObject;
class	scala/ScalaObject
Asciz	java/io/Serializable;
class	java/io/Serializable

{
public static final long serialVersionUID;
  Signature: J

private final scala.collection.Seq fs$1;
  Signature: Lscala/collection/Seq;

public static {};
  Signature: ()V
  Code:
   Stack=2, Locals=0, Args_size=0
	lconst_0
	putstatic	Field serialVersionUID:J
	return
  Labels:

public scala.Function$$anonfun$chain$1(scala.collection.Seq);
  Signature: (Lscala/collection/Seq;)V
  Code:
   Stack=2, Locals=2, Args_size=2
	aload_0
	aload_1
	putfield	Field fs$1:Lscala/collection/Seq;
	aload_0
	invokespecial	Method java/lang/Object."<init>":()V
	aload_0
	invokestatic	Method scala/Function1$class.$init$:(Lscala/Function1;)V
	return
  Labels:

public final java.lang.Object apply(java.lang.Object);
  Signature: (Ljava/lang/Object;)Ljava/lang/Object;
  Code:
   Stack=5, Locals=2, Args_size=2
	aload_0
	getfield	Field fs$1:Lscala/collection/Seq;
	aload_1
	new	class scala/Function$$anonfun$chain$1$$anonfun$apply$1
	dup
	aload_0
	invokespecial	Method scala/Function$$anonfun$chain$1$$anonfun$apply$1."<init>":(Lscala/Function$$anonfun$chain$1;)V
	invokeinterface	InterfaceMethod scala/collection/TraversableLike.$div$colon:(Ljava/lang/Object;Lscala/Function2;)Ljava/lang/Object;
	areturn
  Labels:
  LocalVariableTable: 
   Start  Length  Slot  Name   Signature
   0      19      0    this       Lscala/Function$$anonfun$chain$1;
   0      19      1    x       Ljava/lang/Object;

  Signature: length = 0x2
   00 2F 

public scala.Function1 andThen(scala.Function1);
  Signature: (Lscala/Function1;)Lscala/Function1;
  Code:
   Stack=2, Locals=2, Args_size=2
	aload_0
	aload_1
	invokestatic	Method scala/Function1$class.andThen:(Lscala/Function1;Lscala/Function1;)Lscala/Function1;
	areturn
  Labels:
  LocalVariableTable: 
   Start  Length  Slot  Name   Signature
   0      6      0    this       Lscala/Function$$anonfun$chain$1;
   0      6      1    g       Lscala/Function1;


public scala.Function1 compose(scala.Function1);
  Signature: (Lscala/Function1;)Lscala/Function1;
  Code:
   Stack=2, Locals=2, Args_size=2
	aload_0
	aload_1
	invokestatic	Method scala/Function1$class.compose:(Lscala/Function1;Lscala/Function1;)Lscala/Function1;
	areturn
  Labels:
  LocalVariableTable: 
   Start  Length  Slot  Name   Signature
   0      6      0    this       Lscala/Function$$anonfun$chain$1;
   0      6      1    g       Lscala/Function1;


public java.lang.String toString();
  Signature: ()Ljava/lang/String;
  Code:
   Stack=1, Locals=1, Args_size=1
	aload_0
	invokestatic	Method scala/Function1$class.toString:(Lscala/Function1;)Ljava/lang/String;
	areturn
  Labels:

}

