Compiled from "Function2.scala"
public abstract class scala.Function2$mcVLD$sp$class extends java.lang.Object
  SourceFile: "Function2.scala"
  Scala: length = 0x
   
  InnerClass: 
   public final $anonfun$tupled$mcVLD$sp$1=class scala/Function2$mcVLD$sp$$anonfun$tupled$mcVLD$sp$1 of class scala/Function2$mcVLD$sp
   public final $anonfun$curried$mcVLD$sp$1=class scala/Function2$mcVLD$sp$$anonfun$curried$mcVLD$sp$1 of class scala/Function2$mcVLD$sp
  minor version: 0
  major version: 49
  Constant pool:
Asciz	SourceFile;
Asciz	Function2.scala;
Asciz	apply;
Asciz	(Lscala/Function2$mcVLD$sp;JD)V;
Asciz	Code;
Asciz	LineNumberTable;
Asciz	scala/Function2;
class	scala/Function2
Asciz	apply$mcVLD$sp;
Asciz	(JD)V;
NameAndType	apply$mcVLD$sp:(JD)V
InterfaceMethod	scala/Function2.apply$mcVLD$sp:(JD)V
Asciz	$this;
Asciz	Lscala/Function2$mcVLD$sp;;
Asciz	v1;
Asciz	J;
Asciz	v2;
Asciz	D;
Asciz	LocalVariableTable;
Asciz	curried;
Asciz	(Lscala/Function2$mcVLD$sp;)Lscala/Function1;;
Asciz	scala/Function2$mcVLD$sp;
class	scala/Function2$mcVLD$sp
Asciz	curried$mcVLD$sp;
Asciz	()Lscala/Function1;;
NameAndType	curried$mcVLD$sp:()Lscala/Function1;
InterfaceMethod	scala/Function2$mcVLD$sp.curried$mcVLD$sp:()Lscala/Function1;
Asciz	scala/Function2$mcVLD$sp$$anonfun$curried$mcVLD$sp$1;
class	scala/Function2$mcVLD$sp$$anonfun$curried$mcVLD$sp$1
Asciz	<init>;
Asciz	(Lscala/Function2$mcVLD$sp;)V;
NameAndType	"<init>":(Lscala/Function2$mcVLD$sp;)V
Method	scala/Function2$mcVLD$sp$$anonfun$curried$mcVLD$sp$1."<init>":(Lscala/Function2$mcVLD$sp;)V
Asciz	curry;
Asciz	curry$mcVLD$sp;
NameAndType	curry$mcVLD$sp:()Lscala/Function1;
InterfaceMethod	scala/Function2$mcVLD$sp.curry$mcVLD$sp:()Lscala/Function1;
Asciz	Deprecated;
Asciz	tupled;
Asciz	tupled$mcVLD$sp;
NameAndType	tupled$mcVLD$sp:()Lscala/Function1;
InterfaceMethod	scala/Function2$mcVLD$sp.tupled$mcVLD$sp:()Lscala/Function1;
Asciz	scala/Function2$mcVLD$sp$$anonfun$tupled$mcVLD$sp$1;
class	scala/Function2$mcVLD$sp$$anonfun$tupled$mcVLD$sp$1
Method	scala/Function2$mcVLD$sp$$anonfun$tupled$mcVLD$sp$1."<init>":(Lscala/Function2$mcVLD$sp;)V
Asciz	$init$;
Asciz	Scala;
Asciz	InnerClasses;
Asciz	$anonfun$tupled$mcVLD$sp$1;
Asciz	$anonfun$curried$mcVLD$sp$1;
Asciz	scala/Function2$mcVLD$sp$class;
class	scala/Function2$mcVLD$sp$class
Asciz	java/lang/Object;
class	java/lang/Object

{
public static void apply(scala.Function2$mcVLD$sp, long, double);
  Signature: (Lscala/Function2$mcVLD$sp;JD)V
  Code:
   Stack=5, Locals=5, Args_size=3
	aload_0
	lload_1
	dload_3
	invokeinterface	InterfaceMethod scala/Function2.apply$mcVLD$sp:(JD)V
	return
  Labels:
  LocalVariableTable: 
   Start  Length  Slot  Name   Signature
   0      9      0    $this       Lscala/Function2$mcVLD$sp;
   0      9      1    v1       J
   0      9      3    v2       D


public static scala.Function1 curried(scala.Function2$mcVLD$sp);
  Signature: (Lscala/Function2$mcVLD$sp;)Lscala/Function1;
  Code:
   Stack=1, Locals=1, Args_size=1
	aload_0
	invokeinterface	InterfaceMethod scala/Function2$mcVLD$sp.curried$mcVLD$sp:()Lscala/Function1;
	areturn
  Labels:
  LocalVariableTable: 
   Start  Length  Slot  Name   Signature
   0      7      0    $this       Lscala/Function2$mcVLD$sp;


public static scala.Function1 curried$mcVLD$sp(scala.Function2$mcVLD$sp);
  Signature: (Lscala/Function2$mcVLD$sp;)Lscala/Function1;
  Code:
   Stack=3, Locals=1, Args_size=1
	new	class scala/Function2$mcVLD$sp$$anonfun$curried$mcVLD$sp$1
	dup
	aload_0
	invokespecial	Method scala/Function2$mcVLD$sp$$anonfun$curried$mcVLD$sp$1."<init>":(Lscala/Function2$mcVLD$sp;)V
	areturn
  Labels:
  LocalVariableTable: 
   Start  Length  Slot  Name   Signature
   0      9      0    $this       Lscala/Function2$mcVLD$sp;


public static scala.Function1 curry(scala.Function2$mcVLD$sp);
  Signature: (Lscala/Function2$mcVLD$sp;)Lscala/Function1;
  Code:
   Stack=1, Locals=1, Args_size=1
	aload_0
	invokeinterface	InterfaceMethod scala/Function2$mcVLD$sp.curry$mcVLD$sp:()Lscala/Function1;
	areturn
  Labels:
  LocalVariableTable: 
   Start  Length  Slot  Name   Signature
   0      7      0    $this       Lscala/Function2$mcVLD$sp;

  Deprecated: true

public static scala.Function1 curry$mcVLD$sp(scala.Function2$mcVLD$sp);
  Signature: (Lscala/Function2$mcVLD$sp;)Lscala/Function1;
  Code:
   Stack=1, Locals=1, Args_size=1
	aload_0
	invokeinterface	InterfaceMethod scala/Function2$mcVLD$sp.curried$mcVLD$sp:()Lscala/Function1;
	areturn
  Labels:
  LocalVariableTable: 
   Start  Length  Slot  Name   Signature
   0      7      0    $this       Lscala/Function2$mcVLD$sp;

  Deprecated: true

public static scala.Function1 tupled(scala.Function2$mcVLD$sp);
  Signature: (Lscala/Function2$mcVLD$sp;)Lscala/Function1;
  Code:
   Stack=1, Locals=1, Args_size=1
	aload_0
	invokeinterface	InterfaceMethod scala/Function2$mcVLD$sp.tupled$mcVLD$sp:()Lscala/Function1;
	areturn
  Labels:
  LocalVariableTable: 
   Start  Length  Slot  Name   Signature
   0      7      0    $this       Lscala/Function2$mcVLD$sp;


public static scala.Function1 tupled$mcVLD$sp(scala.Function2$mcVLD$sp);
  Signature: (Lscala/Function2$mcVLD$sp;)Lscala/Function1;
  Code:
   Stack=3, Locals=1, Args_size=1
	new	class scala/Function2$mcVLD$sp$$anonfun$tupled$mcVLD$sp$1
	dup
	aload_0
	invokespecial	Method scala/Function2$mcVLD$sp$$anonfun$tupled$mcVLD$sp$1."<init>":(Lscala/Function2$mcVLD$sp;)V
	areturn
  Labels:
  LocalVariableTable: 
   Start  Length  Slot  Name   Signature
   0      9      0    $this       Lscala/Function2$mcVLD$sp;


public static void $init$(scala.Function2$mcVLD$sp);
  Signature: (Lscala/Function2$mcVLD$sp;)V
  Code:
   Stack=0, Locals=1, Args_size=1
	return
  Labels:
  LocalVariableTable: 
   Start  Length  Slot  Name   Signature
   0      1      0    $this       Lscala/Function2$mcVLD$sp;


}

