Compiled from "Function.scala"
public final class scala.Function$$anonfun$curried$4$$anonfun$apply$8$$anonfun$apply$9 extends scala.runtime.AbstractFunction1 implements java.io.Serializable
  SourceFile: "Function.scala"
  Scala: length = 0x
   
  InnerClass: 
   public final $anonfun$apply$8=class scala/Function$$anonfun$curried$4$$anonfun$apply$8 of class scala/Function$$anonfun$curried$4
   public final $anonfun$apply$9=class scala/Function$$anonfun$curried$4$$anonfun$apply$8$$anonfun$apply$9 of class scala/Function$$anonfun$curried$4$$anonfun$apply$8
   public final $anonfun$apply$10=class scala/Function$$anonfun$curried$4$$anonfun$apply$8$$anonfun$apply$9$$anonfun$apply$10 of class scala/Function$$anonfun$curried$4$$anonfun$apply$8$$anonfun$apply$9
  minor version: 0
  major version: 49
  Constant pool:
Asciz	SourceFile;
Asciz	Function.scala;
Asciz	<clinit>;
Asciz	()V;
Asciz	Code;
Asciz	serialVersionUID;
Asciz	J;
Asciz	scala/Function$$anonfun$curried$4$$anonfun$apply$8$$anonfun$apply$9;
class	scala/Function$$anonfun$curried$4$$anonfun$apply$8$$anonfun$apply$9
NameAndType	serialVersionUID:J
Field	scala/Function$$anonfun$curried$4$$anonfun$apply$8$$anonfun$apply$9.serialVersionUID:J
Asciz	x2$3;
Asciz	Ljava/lang/Object;;
Asciz	$outer;
Asciz	Lscala/Function$$anonfun$curried$4$$anonfun$apply$8;;
Asciz	apply;
Asciz	(Ljava/lang/Object;)Lscala/Function1;;
Asciz	scala/Function$$anonfun$curried$4$$anonfun$apply$8$$anonfun$apply$9$$anonfun$apply$10;
class	scala/Function$$anonfun$curried$4$$anonfun$apply$8$$anonfun$apply$9$$anonfun$apply$10
Asciz	LineNumberTable;
Asciz	<init>;
Asciz	(Lscala/Function$$anonfun$curried$4$$anonfun$apply$8$$anonfun$apply$9;Ljava/lang/Object;)V;
NameAndType	"<init>":(Lscala/Function$$anonfun$curried$4$$anonfun$apply$8$$anonfun$apply$9;Ljava/lang/Object;)V
Method	scala/Function$$anonfun$curried$4$$anonfun$apply$8$$anonfun$apply$9$$anonfun$apply$10."<init>":(Lscala/Function$$anonfun$curried$4$$anonfun$apply$8$$anonfun$apply$9;Ljava/lang/Object;)V
Asciz	this;
Asciz	Lscala/Function$$anonfun$curried$4$$anonfun$apply$8$$anonfun$apply$9;;
Asciz	x3$2;
Asciz	LocalVariableTable;
Asciz	(Ta3;)Lscala/Function1<Ta4;Lscala/Function1<Ta5;Tb;>;>;;
Asciz	Signature;
Asciz	scala$Function$$anonfun$$anonfun$$anonfun$$$outer;
Asciz	()Lscala/Function$$anonfun$curried$4$$anonfun$apply$8;;
NameAndType	$outer:Lscala/Function$$anonfun$curried$4$$anonfun$apply$8;
Field	scala/Function$$anonfun$curried$4$$anonfun$apply$8$$anonfun$apply$9.$outer:Lscala/Function$$anonfun$curried$4$$anonfun$apply$8;
Asciz	(Ljava/lang/Object;)Ljava/lang/Object;;
NameAndType	apply:(Ljava/lang/Object;)Lscala/Function1;
Method	scala/Function$$anonfun$curried$4$$anonfun$apply$8$$anonfun$apply$9.apply:(Ljava/lang/Object;)Lscala/Function1;
Asciz	v1;
Asciz	(Lscala/Function$$anonfun$curried$4$$anonfun$apply$8;Ljava/lang/Object;)V;
Asciz	java/lang/NullPointerException;
class	java/lang/NullPointerException
NameAndType	"<init>":()V
Method	java/lang/NullPointerException."<init>":()V
NameAndType	x2$3:Ljava/lang/Object;
Field	scala/Function$$anonfun$curried$4$$anonfun$apply$8$$anonfun$apply$9.x2$3:Ljava/lang/Object;
Asciz	scala/runtime/AbstractFunction1;
class	scala/runtime/AbstractFunction1
Method	scala/runtime/AbstractFunction1."<init>":()V
Asciz	Scala;
Asciz	InnerClasses;
Asciz	scala/Function$$anonfun$curried$4$$anonfun$apply$8;
class	scala/Function$$anonfun$curried$4$$anonfun$apply$8
Asciz	scala/Function$$anonfun$curried$4;
class	scala/Function$$anonfun$curried$4
Asciz	$anonfun$apply$8;
Asciz	$anonfun$apply$9;
Asciz	$anonfun$apply$10;
Asciz	java/io/Serializable;
class	java/io/Serializable

{
public static final long serialVersionUID;
  Signature: J

public final java.lang.Object x2$3;
  Signature: Ljava/lang/Object;

public final scala.Function$$anonfun$curried$4$$anonfun$apply$8 $outer;
  Signature: Lscala/Function$$anonfun$curried$4$$anonfun$apply$8;

public static {};
  Signature: ()V
  Code:
   Stack=2, Locals=0, Args_size=0
	lconst_0
	putstatic	Field serialVersionUID:J
	return
  Labels:

public final scala.Function1 apply(java.lang.Object);
  Signature: (Ljava/lang/Object;)Lscala/Function1;
  Code:
   Stack=4, Locals=2, Args_size=2
	new	class scala/Function$$anonfun$curried$4$$anonfun$apply$8$$anonfun$apply$9$$anonfun$apply$10
	dup
	aload_0
	aload_1
	invokespecial	Method scala/Function$$anonfun$curried$4$$anonfun$apply$8$$anonfun$apply$9$$anonfun$apply$10."<init>":(Lscala/Function$$anonfun$curried$4$$anonfun$apply$8$$anonfun$apply$9;Ljava/lang/Object;)V
	areturn
  Labels:
  LocalVariableTable: 
   Start  Length  Slot  Name   Signature
   0      10      0    this       Lscala/Function$$anonfun$curried$4$$anonfun$apply$8$$anonfun$apply$9;
   0      10      1    x3$2       Ljava/lang/Object;

  Signature: length = 0x2
   00 1D 

public scala.Function$$anonfun$curried$4$$anonfun$apply$8 scala$Function$$anonfun$$anonfun$$anonfun$$$outer();
  Signature: ()Lscala/Function$$anonfun$curried$4$$anonfun$apply$8;
  Code:
   Stack=1, Locals=1, Args_size=1
	aload_0
	getfield	Field $outer:Lscala/Function$$anonfun$curried$4$$anonfun$apply$8;
	areturn
  Labels:

public final java.lang.Object apply(java.lang.Object);
  Signature: (Ljava/lang/Object;)Ljava/lang/Object;
  Code:
   Stack=2, Locals=2, Args_size=2
	aload_0
	aload_1
	invokevirtual	Method apply:(Ljava/lang/Object;)Lscala/Function1;
	areturn
  Labels:
  LocalVariableTable: 
   Start  Length  Slot  Name   Signature
   0      6      0    this       Lscala/Function$$anonfun$curried$4$$anonfun$apply$8$$anonfun$apply$9;
   0      6      1    v1       Ljava/lang/Object;


public scala.Function$$anonfun$curried$4$$anonfun$apply$8$$anonfun$apply$9(scala.Function$$anonfun$curried$4$$anonfun$apply$8, java.lang.Object);
  Signature: (Lscala/Function$$anonfun$curried$4$$anonfun$apply$8;Ljava/lang/Object;)V
  Code:
   Stack=2, Locals=3, Args_size=3
	aload_1
	ifnonnull	l1 // aload_0
	new	class java/lang/NullPointerException
	dup
	invokespecial	Method java/lang/NullPointerException."<init>":()V
	athrow
l1	aload_0
	aload_1
	putfield	Field $outer:Lscala/Function$$anonfun$curried$4$$anonfun$apply$8;
	aload_0
	aload_2
	putfield	Field x2$3:Ljava/lang/Object;
	aload_0
	invokespecial	Method scala/runtime/AbstractFunction1."<init>":()V
	return
  Labels:
   	l1 = 12 // aload_0
  LocalVariableTable: 
   Start  Length  Slot  Name   Signature
   0      27      0    this       Lscala/Function$$anonfun$curried$4$$anonfun$apply$8$$anonfun$apply$9;
   0      27      1    $outer       Lscala/Function$$anonfun$curried$4$$anonfun$apply$8;


}

