Compiled from "Function2.scala"
public final class scala.Function2$mcDDI$sp$$anonfun$curried$mcDDI$sp$1 extends scala.runtime.AbstractFunction1 implements java.io.Serializable
  SourceFile: "Function2.scala"
  Scala: length = 0x
   
  InnerClass: 
   public final $anonfun$curried$mcDDI$sp$1=class scala/Function2$mcDDI$sp$$anonfun$curried$mcDDI$sp$1 of class scala/Function2$mcDDI$sp
   public final $anonfun$apply$36=class scala/Function2$mcDDI$sp$$anonfun$curried$mcDDI$sp$1$$anonfun$apply$36 of class scala/Function2$mcDDI$sp$$anonfun$curried$mcDDI$sp$1
  minor version: 0
  major version: 49
  Constant pool:
Asciz	SourceFile;
Asciz	Function2.scala;
Asciz	<clinit>;
Asciz	()V;
Asciz	Code;
Asciz	serialVersionUID;
Asciz	J;
Asciz	scala/Function2$mcDDI$sp$$anonfun$curried$mcDDI$sp$1;
class	scala/Function2$mcDDI$sp$$anonfun$curried$mcDDI$sp$1
NameAndType	serialVersionUID:J
Field	scala/Function2$mcDDI$sp$$anonfun$curried$mcDDI$sp$1.serialVersionUID:J
Asciz	$outer;
Asciz	Lscala/Function2$mcDDI$sp;;
Asciz	apply;
Asciz	(D)Lscala/Function1;;
Asciz	scala/Function2$mcDDI$sp$$anonfun$curried$mcDDI$sp$1$$anonfun$apply$36;
class	scala/Function2$mcDDI$sp$$anonfun$curried$mcDDI$sp$1$$anonfun$apply$36
Asciz	LineNumberTable;
Asciz	<init>;
Asciz	(Lscala/Function2$mcDDI$sp$$anonfun$curried$mcDDI$sp$1;D)V;
NameAndType	"<init>":(Lscala/Function2$mcDDI$sp$$anonfun$curried$mcDDI$sp$1;D)V
Method	scala/Function2$mcDDI$sp$$anonfun$curried$mcDDI$sp$1$$anonfun$apply$36."<init>":(Lscala/Function2$mcDDI$sp$$anonfun$curried$mcDDI$sp$1;D)V
Asciz	this;
Asciz	Lscala/Function2$mcDDI$sp$$anonfun$curried$mcDDI$sp$1;;
Asciz	x1$36;
Asciz	D;
Asciz	LocalVariableTable;
Asciz	(D)Lscala/Function1<Ljava/lang/Integer;Ljava/lang/Double;>;;
Asciz	Signature;
Asciz	scala$Function2$mcDDI$sp$$anonfun$$$outer;
Asciz	()Lscala/Function2$mcDDI$sp;;
NameAndType	$outer:Lscala/Function2$mcDDI$sp;
Field	scala/Function2$mcDDI$sp$$anonfun$curried$mcDDI$sp$1.$outer:Lscala/Function2$mcDDI$sp;
Asciz	(Ljava/lang/Object;)Ljava/lang/Object;;
Asciz	scala/runtime/BoxesRunTime;
class	scala/runtime/BoxesRunTime
Asciz	unboxToDouble;
Asciz	(Ljava/lang/Object;)D;
NameAndType	unboxToDouble:(Ljava/lang/Object;)D
Method	scala/runtime/BoxesRunTime.unboxToDouble:(Ljava/lang/Object;)D
NameAndType	apply:(D)Lscala/Function1;
Method	scala/Function2$mcDDI$sp$$anonfun$curried$mcDDI$sp$1.apply:(D)Lscala/Function1;
Asciz	v1;
Asciz	Ljava/lang/Object;;
Asciz	(Lscala/Function2$mcDDI$sp;)V;
Asciz	java/lang/NullPointerException;
class	java/lang/NullPointerException
NameAndType	"<init>":()V
Method	java/lang/NullPointerException."<init>":()V
Asciz	scala/runtime/AbstractFunction1;
class	scala/runtime/AbstractFunction1
Method	scala/runtime/AbstractFunction1."<init>":()V
Asciz	Scala;
Asciz	InnerClasses;
Asciz	scala/Function2$mcDDI$sp;
class	scala/Function2$mcDDI$sp
Asciz	$anonfun$curried$mcDDI$sp$1;
Asciz	$anonfun$apply$36;
Asciz	java/io/Serializable;
class	java/io/Serializable

{
public static final long serialVersionUID;
  Signature: J

public final scala.Function2$mcDDI$sp $outer;
  Signature: Lscala/Function2$mcDDI$sp;

public static {};
  Signature: ()V
  Code:
   Stack=2, Locals=0, Args_size=0
	lconst_0
	putstatic	Field serialVersionUID:J
	return
  Labels:

public final scala.Function1 apply(double);
  Signature: (D)Lscala/Function1;
  Code:
   Stack=5, Locals=3, Args_size=2
	new	class scala/Function2$mcDDI$sp$$anonfun$curried$mcDDI$sp$1$$anonfun$apply$36
	dup
	aload_0
	dload_1
	invokespecial	Method scala/Function2$mcDDI$sp$$anonfun$curried$mcDDI$sp$1$$anonfun$apply$36."<init>":(Lscala/Function2$mcDDI$sp$$anonfun$curried$mcDDI$sp$1;D)V
	areturn
  Labels:
  LocalVariableTable: 
   Start  Length  Slot  Name   Signature
   0      10      0    this       Lscala/Function2$mcDDI$sp$$anonfun$curried$mcDDI$sp$1;
   0      10      1    x1$36       D

  Signature: length = 0x2
   00 1C 

public scala.Function2$mcDDI$sp scala$Function2$mcDDI$sp$$anonfun$$$outer();
  Signature: ()Lscala/Function2$mcDDI$sp;
  Code:
   Stack=1, Locals=1, Args_size=1
	aload_0
	getfield	Field $outer:Lscala/Function2$mcDDI$sp;
	areturn
  Labels:

public final java.lang.Object apply(java.lang.Object);
  Signature: (Ljava/lang/Object;)Ljava/lang/Object;
  Code:
   Stack=3, Locals=2, Args_size=2
	aload_0
	aload_1
	invokestatic	Method scala/runtime/BoxesRunTime.unboxToDouble:(Ljava/lang/Object;)D
	invokevirtual	Method apply:(D)Lscala/Function1;
	areturn
  Labels:
  LocalVariableTable: 
   Start  Length  Slot  Name   Signature
   0      9      0    this       Lscala/Function2$mcDDI$sp$$anonfun$curried$mcDDI$sp$1;
   0      9      1    v1       Ljava/lang/Object;


public scala.Function2$mcDDI$sp$$anonfun$curried$mcDDI$sp$1(scala.Function2$mcDDI$sp);
  Signature: (Lscala/Function2$mcDDI$sp;)V
  Code:
   Stack=2, Locals=2, Args_size=2
	aload_1
	ifnonnull	l1 // aload_0
	new	class java/lang/NullPointerException
	dup
	invokespecial	Method java/lang/NullPointerException."<init>":()V
	athrow
l1	aload_0
	aload_1
	putfield	Field $outer:Lscala/Function2$mcDDI$sp;
	aload_0
	invokespecial	Method scala/runtime/AbstractFunction1."<init>":()V
	return
  Labels:
   	l1 = 12 // aload_0
  LocalVariableTable: 
   Start  Length  Slot  Name   Signature
   0      22      0    this       Lscala/Function2$mcDDI$sp$$anonfun$curried$mcDDI$sp$1;
   0      22      1    $outer       Lscala/Function2$mcDDI$sp;


}

