Compiled from "Function.scala"
public final class scala.Function$$anonfun$curried$4$$anonfun$apply$8$$anonfun$apply$9$$anonfun$apply$10$$anonfun$apply$11 extends java.lang.Object implements scala.Function1,scala.ScalaObject,java.io.Serializable
  SourceFile: "Function.scala"
  Scala: length = 0x
   
  InnerClass: 
   public final $anonfun$curried$4=class scala/Function$$anonfun$curried$4 of class scala/Function
   public final $anonfun$apply$8=class scala/Function$$anonfun$curried$4$$anonfun$apply$8 of class scala/Function$$anonfun$curried$4
   public final $anonfun$apply$9=class scala/Function$$anonfun$curried$4$$anonfun$apply$8$$anonfun$apply$9 of class scala/Function$$anonfun$curried$4$$anonfun$apply$8
   public final $anonfun$apply$10=class scala/Function$$anonfun$curried$4$$anonfun$apply$8$$anonfun$apply$9$$anonfun$apply$10 of class scala/Function$$anonfun$curried$4$$anonfun$apply$8$$anonfun$apply$9
   public final $anonfun$apply$11=class scala/Function$$anonfun$curried$4$$anonfun$apply$8$$anonfun$apply$9$$anonfun$apply$10$$anonfun$apply$11 of class scala/Function$$anonfun$curried$4$$anonfun$apply$8$$anonfun$apply$9$$anonfun$apply$10
  minor version: 0
  major version: 49
  Constant pool:
Asciz	SourceFile;
Asciz	Function.scala;
Asciz	<clinit>;
Asciz	()V;
Asciz	Code;
Asciz	serialVersionUID;
Asciz	J;
Asciz	scala/Function$$anonfun$curried$4$$anonfun$apply$8$$anonfun$apply$9$$anonfun$apply$10$$anonfun$apply$11;
class	scala/Function$$anonfun$curried$4$$anonfun$apply$8$$anonfun$apply$9$$anonfun$apply$10$$anonfun$apply$11
NameAndType	serialVersionUID:J
Field	scala/Function$$anonfun$curried$4$$anonfun$apply$8$$anonfun$apply$9$$anonfun$apply$10$$anonfun$apply$11.serialVersionUID:J
Asciz	x4$1;
Asciz	Ljava/lang/Object;;
Asciz	$outer;
Asciz	Lscala/Function$$anonfun$curried$4$$anonfun$apply$8$$anonfun$apply$9$$anonfun$apply$10;;
Asciz	<init>;
Asciz	(Lscala/Function$$anonfun$curried$4$$anonfun$apply$8$$anonfun$apply$9$$anonfun$apply$10;Ljava/lang/Object;)V;
Asciz	LineNumberTable;
Asciz	java/lang/NullPointerException;
class	java/lang/NullPointerException
NameAndType	"<init>":()V
Method	java/lang/NullPointerException."<init>":()V
NameAndType	$outer:Lscala/Function$$anonfun$curried$4$$anonfun$apply$8$$anonfun$apply$9$$anonfun$apply$10;
Field	scala/Function$$anonfun$curried$4$$anonfun$apply$8$$anonfun$apply$9$$anonfun$apply$10$$anonfun$apply$11.$outer:Lscala/Function$$anonfun$curried$4$$anonfun$apply$8$$anonfun$apply$9$$anonfun$apply$10;
NameAndType	x4$1:Ljava/lang/Object;
Field	scala/Function$$anonfun$curried$4$$anonfun$apply$8$$anonfun$apply$9$$anonfun$apply$10$$anonfun$apply$11.x4$1:Ljava/lang/Object;
Asciz	java/lang/Object;
class	java/lang/Object
Method	java/lang/Object."<init>":()V
Asciz	scala/Function1$class;
class	scala/Function1$class
Asciz	$init$;
Asciz	(Lscala/Function1;)V;
NameAndType	$init$:(Lscala/Function1;)V
Method	scala/Function1$class.$init$:(Lscala/Function1;)V
Asciz	this;
Asciz	Lscala/Function$$anonfun$curried$4$$anonfun$apply$8$$anonfun$apply$9$$anonfun$apply$10$$anonfun$apply$11;;
Asciz	LocalVariableTable;
Asciz	apply;
Asciz	(Ljava/lang/Object;)Ljava/lang/Object;;
Asciz	scala/Function$$anonfun$curried$4$$anonfun$apply$8$$anonfun$apply$9$$anonfun$apply$10;
class	scala/Function$$anonfun$curried$4$$anonfun$apply$8$$anonfun$apply$9$$anonfun$apply$10
Asciz	Lscala/Function$$anonfun$curried$4$$anonfun$apply$8$$anonfun$apply$9;;
NameAndType	$outer:Lscala/Function$$anonfun$curried$4$$anonfun$apply$8$$anonfun$apply$9;
Field	scala/Function$$anonfun$curried$4$$anonfun$apply$8$$anonfun$apply$9$$anonfun$apply$10.$outer:Lscala/Function$$anonfun$curried$4$$anonfun$apply$8$$anonfun$apply$9;
Asciz	scala/Function$$anonfun$curried$4$$anonfun$apply$8$$anonfun$apply$9;
class	scala/Function$$anonfun$curried$4$$anonfun$apply$8$$anonfun$apply$9
Asciz	Lscala/Function$$anonfun$curried$4$$anonfun$apply$8;;
NameAndType	$outer:Lscala/Function$$anonfun$curried$4$$anonfun$apply$8;
Field	scala/Function$$anonfun$curried$4$$anonfun$apply$8$$anonfun$apply$9.$outer:Lscala/Function$$anonfun$curried$4$$anonfun$apply$8;
Asciz	scala/Function$$anonfun$curried$4$$anonfun$apply$8;
class	scala/Function$$anonfun$curried$4$$anonfun$apply$8
Asciz	Lscala/Function$$anonfun$curried$4;;
NameAndType	$outer:Lscala/Function$$anonfun$curried$4;
Field	scala/Function$$anonfun$curried$4$$anonfun$apply$8.$outer:Lscala/Function$$anonfun$curried$4;
Asciz	scala/Function$$anonfun$curried$4;
class	scala/Function$$anonfun$curried$4
Asciz	f$4;
Asciz	Lscala/Function5;;
NameAndType	f$4:Lscala/Function5;
Field	scala/Function$$anonfun$curried$4.f$4:Lscala/Function5;
Asciz	x1$4;
NameAndType	x1$4:Ljava/lang/Object;
Field	scala/Function$$anonfun$curried$4$$anonfun$apply$8.x1$4:Ljava/lang/Object;
Asciz	x2$3;
NameAndType	x2$3:Ljava/lang/Object;
Field	scala/Function$$anonfun$curried$4$$anonfun$apply$8$$anonfun$apply$9.x2$3:Ljava/lang/Object;
Asciz	x3$2;
NameAndType	x3$2:Ljava/lang/Object;
Field	scala/Function$$anonfun$curried$4$$anonfun$apply$8$$anonfun$apply$9$$anonfun$apply$10.x3$2:Ljava/lang/Object;
Asciz	scala/Function5;
class	scala/Function5
Asciz	(Ljava/lang/Object;Ljava/lang/Object;Ljava/lang/Object;Ljava/lang/Object;Ljava/lang/Object;)Ljava/lang/Object;;
NameAndType	apply:(Ljava/lang/Object;Ljava/lang/Object;Ljava/lang/Object;Ljava/lang/Object;Ljava/lang/Object;)Ljava/lang/Object;
InterfaceMethod	scala/Function5.apply:(Ljava/lang/Object;Ljava/lang/Object;Ljava/lang/Object;Ljava/lang/Object;Ljava/lang/Object;)Ljava/lang/Object;
Asciz	x5;
Asciz	(Ta5;)Tb;;
Asciz	Signature;
Asciz	andThen;
Asciz	(Lscala/Function1;)Lscala/Function1;;
Asciz	(Lscala/Function1;Lscala/Function1;)Lscala/Function1;;
NameAndType	andThen:(Lscala/Function1;Lscala/Function1;)Lscala/Function1;
Method	scala/Function1$class.andThen:(Lscala/Function1;Lscala/Function1;)Lscala/Function1;
Asciz	g;
Asciz	Lscala/Function1;;
Asciz	compose;
NameAndType	compose:(Lscala/Function1;Lscala/Function1;)Lscala/Function1;
Method	scala/Function1$class.compose:(Lscala/Function1;Lscala/Function1;)Lscala/Function1;
Asciz	toString;
Asciz	()Ljava/lang/String;;
Asciz	(Lscala/Function1;)Ljava/lang/String;;
NameAndType	toString:(Lscala/Function1;)Ljava/lang/String;
Method	scala/Function1$class.toString:(Lscala/Function1;)Ljava/lang/String;
Asciz	Scala;
Asciz	InnerClasses;
Asciz	scala/Function;
class	scala/Function
Asciz	$anonfun$curried$4;
Asciz	$anonfun$apply$8;
Asciz	$anonfun$apply$9;
Asciz	$anonfun$apply$10;
Asciz	$anonfun$apply$11;
Asciz	scala/Function1;
class	scala/Function1
Asciz	scala/ScalaObject;
class	scala/ScalaObject
Asciz	java/io/Serializable;
class	java/io/Serializable

{
public static final long serialVersionUID;
  Signature: J

private final java.lang.Object x4$1;
  Signature: Ljava/lang/Object;

private final scala.Function$$anonfun$curried$4$$anonfun$apply$8$$anonfun$apply$9$$anonfun$apply$10 $outer;
  Signature: Lscala/Function$$anonfun$curried$4$$anonfun$apply$8$$anonfun$apply$9$$anonfun$apply$10;

public static {};
  Signature: ()V
  Code:
   Stack=2, Locals=0, Args_size=0
	lconst_0
	putstatic	Field serialVersionUID:J
	return
  Labels:

public scala.Function$$anonfun$curried$4$$anonfun$apply$8$$anonfun$apply$9$$anonfun$apply$10$$anonfun$apply$11(scala.Function$$anonfun$curried$4$$anonfun$apply$8$$anonfun$apply$9$$anonfun$apply$10, java.lang.Object);
  Signature: (Lscala/Function$$anonfun$curried$4$$anonfun$apply$8$$anonfun$apply$9$$anonfun$apply$10;Ljava/lang/Object;)V
  Code:
   Stack=2, Locals=3, Args_size=3
	aload_1
	ifnonnull	l1 // aload_0
	new	class java/lang/NullPointerException
	dup
	invokespecial	Method java/lang/NullPointerException."<init>":()V
	athrow
l1	aload_0
	aload_1
	putfield	Field $outer:Lscala/Function$$anonfun$curried$4$$anonfun$apply$8$$anonfun$apply$9$$anonfun$apply$10;
	aload_0
	aload_2
	putfield	Field x4$1:Ljava/lang/Object;
	aload_0
	invokespecial	Method java/lang/Object."<init>":()V
	aload_0
	invokestatic	Method scala/Function1$class.$init$:(Lscala/Function1;)V
	return
  Labels:
   	l1 = 12 // aload_0
  LocalVariableTable: 
   Start  Length  Slot  Name   Signature
   0      31      0    this       Lscala/Function$$anonfun$curried$4$$anonfun$apply$8$$anonfun$apply$9$$anonfun$apply$10$$anonfun$apply$11;
   0      31      1    $outer       Lscala/Function$$anonfun$curried$4$$anonfun$apply$8$$anonfun$apply$9$$anonfun$apply$10;


public final java.lang.Object apply(java.lang.Object);
  Signature: (Ljava/lang/Object;)Ljava/lang/Object;
  Code:
   Stack=6, Locals=9, Args_size=2
	aload_0
	getfield	Field $outer:Lscala/Function$$anonfun$curried$4$$anonfun$apply$8$$anonfun$apply$9$$anonfun$apply$10;
	astore	8
	aload_0
	getfield	Field $outer:Lscala/Function$$anonfun$curried$4$$anonfun$apply$8$$anonfun$apply$9$$anonfun$apply$10;
	astore_2
	aload_2
	getfield	Field scala/Function$$anonfun$curried$4$$anonfun$apply$8$$anonfun$apply$9$$anonfun$apply$10.$outer:Lscala/Function$$anonfun$curried$4$$anonfun$apply$8$$anonfun$apply$9;
	astore_3
	aload_3
	getfield	Field scala/Function$$anonfun$curried$4$$anonfun$apply$8$$anonfun$apply$9.$outer:Lscala/Function$$anonfun$curried$4$$anonfun$apply$8;
	astore	4
	aload	4
	getfield	Field scala/Function$$anonfun$curried$4$$anonfun$apply$8.$outer:Lscala/Function$$anonfun$curried$4;
	getfield	Field scala/Function$$anonfun$curried$4.f$4:Lscala/Function5;
	aload_0
	getfield	Field $outer:Lscala/Function$$anonfun$curried$4$$anonfun$apply$8$$anonfun$apply$9$$anonfun$apply$10;
	astore	5
	aload	5
	getfield	Field scala/Function$$anonfun$curried$4$$anonfun$apply$8$$anonfun$apply$9$$anonfun$apply$10.$outer:Lscala/Function$$anonfun$curried$4$$anonfun$apply$8$$anonfun$apply$9;
	astore	6
	aload	6
	getfield	Field scala/Function$$anonfun$curried$4$$anonfun$apply$8$$anonfun$apply$9.$outer:Lscala/Function$$anonfun$curried$4$$anonfun$apply$8;
	getfield	Field scala/Function$$anonfun$curried$4$$anonfun$apply$8.x1$4:Ljava/lang/Object;
	aload_0
	getfield	Field $outer:Lscala/Function$$anonfun$curried$4$$anonfun$apply$8$$anonfun$apply$9$$anonfun$apply$10;
	astore	7
	aload	7
	getfield	Field scala/Function$$anonfun$curried$4$$anonfun$apply$8$$anonfun$apply$9$$anonfun$apply$10.$outer:Lscala/Function$$anonfun$curried$4$$anonfun$apply$8$$anonfun$apply$9;
	getfield	Field scala/Function$$anonfun$curried$4$$anonfun$apply$8$$anonfun$apply$9.x2$3:Ljava/lang/Object;
	aload_0
	getfield	Field $outer:Lscala/Function$$anonfun$curried$4$$anonfun$apply$8$$anonfun$apply$9$$anonfun$apply$10;
	getfield	Field scala/Function$$anonfun$curried$4$$anonfun$apply$8$$anonfun$apply$9$$anonfun$apply$10.x3$2:Ljava/lang/Object;
	aload_0
	getfield	Field x4$1:Ljava/lang/Object;
	aload_1
	invokeinterface	InterfaceMethod scala/Function5.apply:(Ljava/lang/Object;Ljava/lang/Object;Ljava/lang/Object;Ljava/lang/Object;Ljava/lang/Object;)Ljava/lang/Object;
	areturn
  Labels:
  LocalVariableTable: 
   Start  Length  Slot  Name   Signature
   0      83      0    this       Lscala/Function$$anonfun$curried$4$$anonfun$apply$8$$anonfun$apply$9$$anonfun$apply$10$$anonfun$apply$11;
   6      77      1    x5       Ljava/lang/Object;

  Signature: length = 0x2
   00 4D 

public scala.Function1 andThen(scala.Function1);
  Signature: (Lscala/Function1;)Lscala/Function1;
  Code:
   Stack=2, Locals=2, Args_size=2
	aload_0
	aload_1
	invokestatic	Method scala/Function1$class.andThen:(Lscala/Function1;Lscala/Function1;)Lscala/Function1;
	areturn
  Labels:
  LocalVariableTable: 
   Start  Length  Slot  Name   Signature
   0      6      0    this       Lscala/Function$$anonfun$curried$4$$anonfun$apply$8$$anonfun$apply$9$$anonfun$apply$10$$anonfun$apply$11;
   0      6      1    g       Lscala/Function1;


public scala.Function1 compose(scala.Function1);
  Signature: (Lscala/Function1;)Lscala/Function1;
  Code:
   Stack=2, Locals=2, Args_size=2
	aload_0
	aload_1
	invokestatic	Method scala/Function1$class.compose:(Lscala/Function1;Lscala/Function1;)Lscala/Function1;
	areturn
  Labels:
  LocalVariableTable: 
   Start  Length  Slot  Name   Signature
   0      6      0    this       Lscala/Function$$anonfun$curried$4$$anonfun$apply$8$$anonfun$apply$9$$anonfun$apply$10$$anonfun$apply$11;
   0      6      1    g       Lscala/Function1;


public java.lang.String toString();
  Signature: ()Ljava/lang/String;
  Code:
   Stack=1, Locals=1, Args_size=1
	aload_0
	invokestatic	Method scala/Function1$class.toString:(Lscala/Function1;)Ljava/lang/String;
	areturn
  Labels:

}

