Compiled from "Function2.scala"
public abstract class scala.Function2$mcVID$sp$class extends java.lang.Object
  SourceFile: "Function2.scala"
  Scala: length = 0x
   
  InnerClass: 
   public final $anonfun$tupled$mcVID$sp$1=class scala/Function2$mcVID$sp$$anonfun$tupled$mcVID$sp$1 of class scala/Function2$mcVID$sp
   public final $anonfun$curried$mcVID$sp$1=class scala/Function2$mcVID$sp$$anonfun$curried$mcVID$sp$1 of class scala/Function2$mcVID$sp
  minor version: 0
  major version: 49
  Constant pool:
Asciz	SourceFile;
Asciz	Function2.scala;
Asciz	apply;
Asciz	(Lscala/Function2$mcVID$sp;ID)V;
Asciz	Code;
Asciz	LineNumberTable;
Asciz	scala/Function2;
class	scala/Function2
Asciz	apply$mcVID$sp;
Asciz	(ID)V;
NameAndType	apply$mcVID$sp:(ID)V
InterfaceMethod	scala/Function2.apply$mcVID$sp:(ID)V
Asciz	$this;
Asciz	Lscala/Function2$mcVID$sp;;
Asciz	v1;
Asciz	I;
Asciz	v2;
Asciz	D;
Asciz	LocalVariableTable;
Asciz	curried;
Asciz	(Lscala/Function2$mcVID$sp;)Lscala/Function1;;
Asciz	scala/Function2$mcVID$sp;
class	scala/Function2$mcVID$sp
Asciz	curried$mcVID$sp;
Asciz	()Lscala/Function1;;
NameAndType	curried$mcVID$sp:()Lscala/Function1;
InterfaceMethod	scala/Function2$mcVID$sp.curried$mcVID$sp:()Lscala/Function1;
Asciz	scala/Function2$mcVID$sp$$anonfun$curried$mcVID$sp$1;
class	scala/Function2$mcVID$sp$$anonfun$curried$mcVID$sp$1
Asciz	<init>;
Asciz	(Lscala/Function2$mcVID$sp;)V;
NameAndType	"<init>":(Lscala/Function2$mcVID$sp;)V
Method	scala/Function2$mcVID$sp$$anonfun$curried$mcVID$sp$1."<init>":(Lscala/Function2$mcVID$sp;)V
Asciz	curry;
Asciz	curry$mcVID$sp;
NameAndType	curry$mcVID$sp:()Lscala/Function1;
InterfaceMethod	scala/Function2$mcVID$sp.curry$mcVID$sp:()Lscala/Function1;
Asciz	Deprecated;
Asciz	tupled;
Asciz	tupled$mcVID$sp;
NameAndType	tupled$mcVID$sp:()Lscala/Function1;
InterfaceMethod	scala/Function2$mcVID$sp.tupled$mcVID$sp:()Lscala/Function1;
Asciz	scala/Function2$mcVID$sp$$anonfun$tupled$mcVID$sp$1;
class	scala/Function2$mcVID$sp$$anonfun$tupled$mcVID$sp$1
Method	scala/Function2$mcVID$sp$$anonfun$tupled$mcVID$sp$1."<init>":(Lscala/Function2$mcVID$sp;)V
Asciz	$init$;
Asciz	Scala;
Asciz	InnerClasses;
Asciz	$anonfun$tupled$mcVID$sp$1;
Asciz	$anonfun$curried$mcVID$sp$1;
Asciz	scala/Function2$mcVID$sp$class;
class	scala/Function2$mcVID$sp$class
Asciz	java/lang/Object;
class	java/lang/Object

{
public static void apply(scala.Function2$mcVID$sp, int, double);
  Signature: (Lscala/Function2$mcVID$sp;ID)V
  Code:
   Stack=4, Locals=4, Args_size=3
	aload_0
	iload_1
	dload_2
	invokeinterface	InterfaceMethod scala/Function2.apply$mcVID$sp:(ID)V
	return
  Labels:
  LocalVariableTable: 
   Start  Length  Slot  Name   Signature
   0      9      0    $this       Lscala/Function2$mcVID$sp;
   0      9      1    v1       I
   0      9      2    v2       D


public static scala.Function1 curried(scala.Function2$mcVID$sp);
  Signature: (Lscala/Function2$mcVID$sp;)Lscala/Function1;
  Code:
   Stack=1, Locals=1, Args_size=1
	aload_0
	invokeinterface	InterfaceMethod scala/Function2$mcVID$sp.curried$mcVID$sp:()Lscala/Function1;
	areturn
  Labels:
  LocalVariableTable: 
   Start  Length  Slot  Name   Signature
   0      7      0    $this       Lscala/Function2$mcVID$sp;


public static scala.Function1 curried$mcVID$sp(scala.Function2$mcVID$sp);
  Signature: (Lscala/Function2$mcVID$sp;)Lscala/Function1;
  Code:
   Stack=3, Locals=1, Args_size=1
	new	class scala/Function2$mcVID$sp$$anonfun$curried$mcVID$sp$1
	dup
	aload_0
	invokespecial	Method scala/Function2$mcVID$sp$$anonfun$curried$mcVID$sp$1."<init>":(Lscala/Function2$mcVID$sp;)V
	areturn
  Labels:
  LocalVariableTable: 
   Start  Length  Slot  Name   Signature
   0      9      0    $this       Lscala/Function2$mcVID$sp;


public static scala.Function1 curry(scala.Function2$mcVID$sp);
  Signature: (Lscala/Function2$mcVID$sp;)Lscala/Function1;
  Code:
   Stack=1, Locals=1, Args_size=1
	aload_0
	invokeinterface	InterfaceMethod scala/Function2$mcVID$sp.curry$mcVID$sp:()Lscala/Function1;
	areturn
  Labels:
  LocalVariableTable: 
   Start  Length  Slot  Name   Signature
   0      7      0    $this       Lscala/Function2$mcVID$sp;

  Deprecated: true

public static scala.Function1 curry$mcVID$sp(scala.Function2$mcVID$sp);
  Signature: (Lscala/Function2$mcVID$sp;)Lscala/Function1;
  Code:
   Stack=1, Locals=1, Args_size=1
	aload_0
	invokeinterface	InterfaceMethod scala/Function2$mcVID$sp.curried$mcVID$sp:()Lscala/Function1;
	areturn
  Labels:
  LocalVariableTable: 
   Start  Length  Slot  Name   Signature
   0      7      0    $this       Lscala/Function2$mcVID$sp;

  Deprecated: true

public static scala.Function1 tupled(scala.Function2$mcVID$sp);
  Signature: (Lscala/Function2$mcVID$sp;)Lscala/Function1;
  Code:
   Stack=1, Locals=1, Args_size=1
	aload_0
	invokeinterface	InterfaceMethod scala/Function2$mcVID$sp.tupled$mcVID$sp:()Lscala/Function1;
	areturn
  Labels:
  LocalVariableTable: 
   Start  Length  Slot  Name   Signature
   0      7      0    $this       Lscala/Function2$mcVID$sp;


public static scala.Function1 tupled$mcVID$sp(scala.Function2$mcVID$sp);
  Signature: (Lscala/Function2$mcVID$sp;)Lscala/Function1;
  Code:
   Stack=3, Locals=1, Args_size=1
	new	class scala/Function2$mcVID$sp$$anonfun$tupled$mcVID$sp$1
	dup
	aload_0
	invokespecial	Method scala/Function2$mcVID$sp$$anonfun$tupled$mcVID$sp$1."<init>":(Lscala/Function2$mcVID$sp;)V
	areturn
  Labels:
  LocalVariableTable: 
   Start  Length  Slot  Name   Signature
   0      9      0    $this       Lscala/Function2$mcVID$sp;


public static void $init$(scala.Function2$mcVID$sp);
  Signature: (Lscala/Function2$mcVID$sp;)V
  Code:
   Stack=0, Locals=1, Args_size=1
	return
  Labels:
  LocalVariableTable: 
   Start  Length  Slot  Name   Signature
   0      1      0    $this       Lscala/Function2$mcVID$sp;


}

