Compiled from "Function2.scala"
public abstract class scala.Function2$mcDDI$sp$class extends java.lang.Object
  SourceFile: "Function2.scala"
  Scala: length = 0x
   
  InnerClass: 
   public final $anonfun$tupled$mcDDI$sp$1=class scala/Function2$mcDDI$sp$$anonfun$tupled$mcDDI$sp$1 of class scala/Function2$mcDDI$sp
   public final $anonfun$curried$mcDDI$sp$1=class scala/Function2$mcDDI$sp$$anonfun$curried$mcDDI$sp$1 of class scala/Function2$mcDDI$sp
  minor version: 0
  major version: 49
  Constant pool:
Asciz	SourceFile;
Asciz	Function2.scala;
Asciz	apply;
Asciz	(Lscala/Function2$mcDDI$sp;DI)D;
Asciz	Code;
Asciz	LineNumberTable;
Asciz	scala/Function2;
class	scala/Function2
Asciz	apply$mcDDI$sp;
Asciz	(DI)D;
NameAndType	apply$mcDDI$sp:(DI)D
InterfaceMethod	scala/Function2.apply$mcDDI$sp:(DI)D
Asciz	$this;
Asciz	Lscala/Function2$mcDDI$sp;;
Asciz	v1;
Asciz	D;
Asciz	v2;
Asciz	I;
Asciz	LocalVariableTable;
Asciz	curried;
Asciz	(Lscala/Function2$mcDDI$sp;)Lscala/Function1;;
Asciz	scala/Function2$mcDDI$sp;
class	scala/Function2$mcDDI$sp
Asciz	curried$mcDDI$sp;
Asciz	()Lscala/Function1;;
NameAndType	curried$mcDDI$sp:()Lscala/Function1;
InterfaceMethod	scala/Function2$mcDDI$sp.curried$mcDDI$sp:()Lscala/Function1;
Asciz	scala/Function2$mcDDI$sp$$anonfun$curried$mcDDI$sp$1;
class	scala/Function2$mcDDI$sp$$anonfun$curried$mcDDI$sp$1
Asciz	<init>;
Asciz	(Lscala/Function2$mcDDI$sp;)V;
NameAndType	"<init>":(Lscala/Function2$mcDDI$sp;)V
Method	scala/Function2$mcDDI$sp$$anonfun$curried$mcDDI$sp$1."<init>":(Lscala/Function2$mcDDI$sp;)V
Asciz	curry;
Asciz	curry$mcDDI$sp;
NameAndType	curry$mcDDI$sp:()Lscala/Function1;
InterfaceMethod	scala/Function2$mcDDI$sp.curry$mcDDI$sp:()Lscala/Function1;
Asciz	Deprecated;
Asciz	tupled;
Asciz	tupled$mcDDI$sp;
NameAndType	tupled$mcDDI$sp:()Lscala/Function1;
InterfaceMethod	scala/Function2$mcDDI$sp.tupled$mcDDI$sp:()Lscala/Function1;
Asciz	scala/Function2$mcDDI$sp$$anonfun$tupled$mcDDI$sp$1;
class	scala/Function2$mcDDI$sp$$anonfun$tupled$mcDDI$sp$1
Method	scala/Function2$mcDDI$sp$$anonfun$tupled$mcDDI$sp$1."<init>":(Lscala/Function2$mcDDI$sp;)V
Asciz	$init$;
Asciz	Scala;
Asciz	InnerClasses;
Asciz	$anonfun$tupled$mcDDI$sp$1;
Asciz	$anonfun$curried$mcDDI$sp$1;
Asciz	scala/Function2$mcDDI$sp$class;
class	scala/Function2$mcDDI$sp$class
Asciz	java/lang/Object;
class	java/lang/Object

{
public static double apply(scala.Function2$mcDDI$sp, double, int);
  Signature: (Lscala/Function2$mcDDI$sp;DI)D
  Code:
   Stack=4, Locals=4, Args_size=3
	aload_0
	dload_1
	iload_3
	invokeinterface	InterfaceMethod scala/Function2.apply$mcDDI$sp:(DI)D
	dreturn
  Labels:
  LocalVariableTable: 
   Start  Length  Slot  Name   Signature
   0      9      0    $this       Lscala/Function2$mcDDI$sp;
   0      9      1    v1       D
   0      9      3    v2       I


public static scala.Function1 curried(scala.Function2$mcDDI$sp);
  Signature: (Lscala/Function2$mcDDI$sp;)Lscala/Function1;
  Code:
   Stack=1, Locals=1, Args_size=1
	aload_0
	invokeinterface	InterfaceMethod scala/Function2$mcDDI$sp.curried$mcDDI$sp:()Lscala/Function1;
	areturn
  Labels:
  LocalVariableTable: 
   Start  Length  Slot  Name   Signature
   0      7      0    $this       Lscala/Function2$mcDDI$sp;


public static scala.Function1 curried$mcDDI$sp(scala.Function2$mcDDI$sp);
  Signature: (Lscala/Function2$mcDDI$sp;)Lscala/Function1;
  Code:
   Stack=3, Locals=1, Args_size=1
	new	class scala/Function2$mcDDI$sp$$anonfun$curried$mcDDI$sp$1
	dup
	aload_0
	invokespecial	Method scala/Function2$mcDDI$sp$$anonfun$curried$mcDDI$sp$1."<init>":(Lscala/Function2$mcDDI$sp;)V
	areturn
  Labels:
  LocalVariableTable: 
   Start  Length  Slot  Name   Signature
   0      9      0    $this       Lscala/Function2$mcDDI$sp;


public static scala.Function1 curry(scala.Function2$mcDDI$sp);
  Signature: (Lscala/Function2$mcDDI$sp;)Lscala/Function1;
  Code:
   Stack=1, Locals=1, Args_size=1
	aload_0
	invokeinterface	InterfaceMethod scala/Function2$mcDDI$sp.curry$mcDDI$sp:()Lscala/Function1;
	areturn
  Labels:
  LocalVariableTable: 
   Start  Length  Slot  Name   Signature
   0      7      0    $this       Lscala/Function2$mcDDI$sp;

  Deprecated: true

public static scala.Function1 curry$mcDDI$sp(scala.Function2$mcDDI$sp);
  Signature: (Lscala/Function2$mcDDI$sp;)Lscala/Function1;
  Code:
   Stack=1, Locals=1, Args_size=1
	aload_0
	invokeinterface	InterfaceMethod scala/Function2$mcDDI$sp.curried$mcDDI$sp:()Lscala/Function1;
	areturn
  Labels:
  LocalVariableTable: 
   Start  Length  Slot  Name   Signature
   0      7      0    $this       Lscala/Function2$mcDDI$sp;

  Deprecated: true

public static scala.Function1 tupled(scala.Function2$mcDDI$sp);
  Signature: (Lscala/Function2$mcDDI$sp;)Lscala/Function1;
  Code:
   Stack=1, Locals=1, Args_size=1
	aload_0
	invokeinterface	InterfaceMethod scala/Function2$mcDDI$sp.tupled$mcDDI$sp:()Lscala/Function1;
	areturn
  Labels:
  LocalVariableTable: 
   Start  Length  Slot  Name   Signature
   0      7      0    $this       Lscala/Function2$mcDDI$sp;


public static scala.Function1 tupled$mcDDI$sp(scala.Function2$mcDDI$sp);
  Signature: (Lscala/Function2$mcDDI$sp;)Lscala/Function1;
  Code:
   Stack=3, Locals=1, Args_size=1
	new	class scala/Function2$mcDDI$sp$$anonfun$tupled$mcDDI$sp$1
	dup
	aload_0
	invokespecial	Method scala/Function2$mcDDI$sp$$anonfun$tupled$mcDDI$sp$1."<init>":(Lscala/Function2$mcDDI$sp;)V
	areturn
  Labels:
  LocalVariableTable: 
   Start  Length  Slot  Name   Signature
   0      9      0    $this       Lscala/Function2$mcDDI$sp;


public static void $init$(scala.Function2$mcDDI$sp);
  Signature: (Lscala/Function2$mcDDI$sp;)V
  Code:
   Stack=0, Locals=1, Args_size=1
	return
  Labels:
  LocalVariableTable: 
   Start  Length  Slot  Name   Signature
   0      1      0    $this       Lscala/Function2$mcDDI$sp;


}

