Compiled from "Function2.scala"
public final class scala.Function2$mcVDD$sp$$anonfun$tupled$mcVDD$sp$1 extends scala.runtime.AbstractFunction1 implements java.io.Serializable
  SourceFile: "Function2.scala"
  Scala: length = 0x
   
  InnerClass: 
   public final $anonfun$tupled$mcVDD$sp$1=class scala/Function2$mcVDD$sp$$anonfun$tupled$mcVDD$sp$1 of class scala/Function2$mcVDD$sp
  minor version: 0
  major version: 49
  Constant pool:
Asciz	SourceFile;
Asciz	Function2.scala;
Asciz	<clinit>;
Asciz	()V;
Asciz	Code;
Asciz	serialVersionUID;
Asciz	J;
Asciz	scala/Function2$mcVDD$sp$$anonfun$tupled$mcVDD$sp$1;
class	scala/Function2$mcVDD$sp$$anonfun$tupled$mcVDD$sp$1
NameAndType	serialVersionUID:J
Field	scala/Function2$mcVDD$sp$$anonfun$tupled$mcVDD$sp$1.serialVersionUID:J
Asciz	$outer;
Asciz	Lscala/Function2$mcVDD$sp;;
Asciz	apply;
Asciz	(Lscala/Tuple2;)V;
Asciz	LineNumberTable;
NameAndType	$outer:Lscala/Function2$mcVDD$sp;
Field	scala/Function2$mcVDD$sp$$anonfun$tupled$mcVDD$sp$1.$outer:Lscala/Function2$mcVDD$sp;
Asciz	scala/Tuple2;
class	scala/Tuple2
Asciz	_1;
Asciz	()Ljava/lang/Object;;
NameAndType	_1:()Ljava/lang/Object;
Method	scala/Tuple2._1:()Ljava/lang/Object;
Asciz	scala/runtime/BoxesRunTime;
class	scala/runtime/BoxesRunTime
Asciz	unboxToDouble;
Asciz	(Ljava/lang/Object;)D;
NameAndType	unboxToDouble:(Ljava/lang/Object;)D
Method	scala/runtime/BoxesRunTime.unboxToDouble:(Ljava/lang/Object;)D
Asciz	_2;
NameAndType	_2:()Ljava/lang/Object;
Method	scala/Tuple2._2:()Ljava/lang/Object;
Asciz	scala/Function2$mcVDD$sp;
class	scala/Function2$mcVDD$sp
Asciz	(DD)V;
NameAndType	apply:(DD)V
InterfaceMethod	scala/Function2$mcVDD$sp.apply:(DD)V
Asciz	scala/MatchError;
class	scala/MatchError
Asciz	<init>;
Asciz	(Ljava/lang/Object;)V;
NameAndType	"<init>":(Ljava/lang/Object;)V
Method	scala/MatchError."<init>":(Ljava/lang/Object;)V
Asciz	this;
Asciz	Lscala/Function2$mcVDD$sp$$anonfun$tupled$mcVDD$sp$1;;
Asciz	x0$1;
Asciz	Lscala/Tuple2;;
Asciz	LocalVariableTable;
Asciz	(Lscala/Tuple2<Ljava/lang/Double;Ljava/lang/Double;>;)V;
Asciz	Signature;
Asciz	(Ljava/lang/Object;)Ljava/lang/Object;;
NameAndType	apply:(Lscala/Tuple2;)V
Method	scala/Function2$mcVDD$sp$$anonfun$tupled$mcVDD$sp$1.apply:(Lscala/Tuple2;)V
Asciz	scala/runtime/BoxedUnit;
class	scala/runtime/BoxedUnit
Asciz	UNIT;
Asciz	Lscala/runtime/BoxedUnit;;
NameAndType	UNIT:Lscala/runtime/BoxedUnit;
Field	scala/runtime/BoxedUnit.UNIT:Lscala/runtime/BoxedUnit;
Asciz	v1;
Asciz	Ljava/lang/Object;;
Asciz	(Lscala/Function2$mcVDD$sp;)V;
Asciz	java/lang/NullPointerException;
class	java/lang/NullPointerException
NameAndType	"<init>":()V
Method	java/lang/NullPointerException."<init>":()V
Asciz	scala/runtime/AbstractFunction1;
class	scala/runtime/AbstractFunction1
Method	scala/runtime/AbstractFunction1."<init>":()V
Asciz	Scala;
Asciz	InnerClasses;
Asciz	$anonfun$tupled$mcVDD$sp$1;
Asciz	java/io/Serializable;
class	java/io/Serializable

{
public static final long serialVersionUID;
  Signature: J

public final scala.Function2$mcVDD$sp $outer;
  Signature: Lscala/Function2$mcVDD$sp;

public static {};
  Signature: ()V
  Code:
   Stack=2, Locals=0, Args_size=0
	lconst_0
	putstatic	Field serialVersionUID:J
	return
  Labels:

public final void apply(scala.Tuple2);
  Signature: (Lscala/Tuple2;)V
  Code:
   Stack=5, Locals=2, Args_size=2
	aload_1
	ifnull	l1 // new
	aload_0
	getfield	Field $outer:Lscala/Function2$mcVDD$sp;
	aload_1
	invokevirtual	Method scala/Tuple2._1:()Ljava/lang/Object;
	invokestatic	Method scala/runtime/BoxesRunTime.unboxToDouble:(Ljava/lang/Object;)D
	aload_1
	invokevirtual	Method scala/Tuple2._2:()Ljava/lang/Object;
	invokestatic	Method scala/runtime/BoxesRunTime.unboxToDouble:(Ljava/lang/Object;)D
	invokeinterface	InterfaceMethod scala/Function2$mcVDD$sp.apply:(DD)V
	return
l1	new	class scala/MatchError
	dup
	aload_1
	invokespecial	Method scala/MatchError."<init>":(Ljava/lang/Object;)V
	athrow
  Labels:
   	l1 = 28 // new
  LocalVariableTable: 
   Start  Length  Slot  Name   Signature
   0      37      0    this       Lscala/Function2$mcVDD$sp$$anonfun$tupled$mcVDD$sp$1;
   0      37      1    x0$1       Lscala/Tuple2;

  Signature: length = 0x2
   00 32 

public final java.lang.Object apply(java.lang.Object);
  Signature: (Ljava/lang/Object;)Ljava/lang/Object;
  Code:
   Stack=2, Locals=2, Args_size=2
	aload_0
	aload_1
	checkcast	class scala/Tuple2
	invokevirtual	Method apply:(Lscala/Tuple2;)V
	getstatic	Field scala/runtime/BoxedUnit.UNIT:Lscala/runtime/BoxedUnit;
	areturn
  Labels:
  LocalVariableTable: 
   Start  Length  Slot  Name   Signature
   0      12      0    this       Lscala/Function2$mcVDD$sp$$anonfun$tupled$mcVDD$sp$1;
   0      12      1    v1       Ljava/lang/Object;


public scala.Function2$mcVDD$sp$$anonfun$tupled$mcVDD$sp$1(scala.Function2$mcVDD$sp);
  Signature: (Lscala/Function2$mcVDD$sp;)V
  Code:
   Stack=2, Locals=2, Args_size=2
	aload_1
	ifnonnull	l1 // aload_0
	new	class java/lang/NullPointerException
	dup
	invokespecial	Method java/lang/NullPointerException."<init>":()V
	athrow
l1	aload_0
	aload_1
	putfield	Field $outer:Lscala/Function2$mcVDD$sp;
	aload_0
	invokespecial	Method scala/runtime/AbstractFunction1."<init>":()V
	return
  Labels:
   	l1 = 12 // aload_0
  LocalVariableTable: 
   Start  Length  Slot  Name   Signature
   0      22      0    this       Lscala/Function2$mcVDD$sp$$anonfun$tupled$mcVDD$sp$1;
   0      22      1    $outer       Lscala/Function2$mcVDD$sp;


}

