Compiled from "Function.scala"
public final class scala.Function$$anonfun$curried$4$$anonfun$apply$8$$anonfun$apply$9$$anonfun$apply$10$$anonfun$apply$11 extends java.lang.Object implements scala.Function1,scala.ScalaObject,java.io.Serializable
  SourceFile: "Function.scala"
  Scala: length = 0x
   
  InnerClass: 
   public final #96= #55 of #95; //$anonfun$curried$4=class scala/Function$$anonfun$curried$4 of class scala/Function
   public final #97= #49 of #55; //$anonfun$apply$8=class scala/Function$$anonfun$curried$4$$anonfun$apply$8 of class scala/Function$$anonfun$curried$4
   public final #98= #43 of #49; //$anonfun$apply$9=class scala/Function$$anonfun$curried$4$$anonfun$apply$8$$anonfun$apply$9 of class scala/Function$$anonfun$curried$4$$anonfun$apply$8
   public final #99= #37 of #43; //$anonfun$apply$10=class scala/Function$$anonfun$curried$4$$anonfun$apply$8$$anonfun$apply$9$$anonfun$apply$10 of class scala/Function$$anonfun$curried$4$$anonfun$apply$8$$anonfun$apply$9
   public final #100= #17 of #37; //$anonfun$apply$11=class scala/Function$$anonfun$curried$4$$anonfun$apply$8$$anonfun$apply$9$$anonfun$apply$10$$anonfun$apply$11 of class scala/Function$$anonfun$curried$4$$anonfun$apply$8$$anonfun$apply$9$$anonfun$apply$10
  minor version: 0
  major version: 49
  Constant pool:
const #1 = Asciz	SourceFile;
const #2 = Asciz	Function.scala;
const #3 = Asciz	x4$1;
const #4 = Asciz	Ljava/lang/Object;;
const #5 = Asciz	$outer;
const #6 = Asciz	Lscala/Function$$anonfun$curried$4$$anonfun$apply$8$$anonfun$apply$9$$anonfun$apply$10;;
const #7 = Asciz	<init>;
const #8 = Asciz	(Lscala/Function$$anonfun$curried$4$$anonfun$apply$8$$anonfun$apply$9$$anonfun$apply$10;Ljava/lang/Object;)V;
const #9 = Asciz	Code;
const #10 = Asciz	LineNumberTable;
const #11 = Asciz	java/lang/NullPointerException;
const #12 = class	#11;	//  java/lang/NullPointerException
const #13 = Asciz	()V;
const #14 = NameAndType	#7:#13;//  "<init>":()V
const #15 = Method	#12.#14;	//  java/lang/NullPointerException."<init>":()V
const #16 = Asciz	scala/Function$$anonfun$curried$4$$anonfun$apply$8$$anonfun$apply$9$$anonfun$apply$10$$anonfun$apply$11;
const #17 = class	#16;	//  scala/Function$$anonfun$curried$4$$anonfun$apply$8$$anonfun$apply$9$$anonfun$apply$10$$anonfun$apply$11
const #18 = NameAndType	#5:#6;//  $outer:Lscala/Function$$anonfun$curried$4$$anonfun$apply$8$$anonfun$apply$9$$anonfun$apply$10;
const #19 = Field	#17.#18;	//  scala/Function$$anonfun$curried$4$$anonfun$apply$8$$anonfun$apply$9$$anonfun$apply$10$$anonfun$apply$11.$outer:Lscala/Function$$anonfun$curried$4$$anonfun$apply$8$$anonfun$apply$9$$anonfun$apply$10;
const #20 = NameAndType	#3:#4;//  x4$1:Ljava/lang/Object;
const #21 = Field	#17.#20;	//  scala/Function$$anonfun$curried$4$$anonfun$apply$8$$anonfun$apply$9$$anonfun$apply$10$$anonfun$apply$11.x4$1:Ljava/lang/Object;
const #22 = Asciz	java/lang/Object;
const #23 = class	#22;	//  java/lang/Object
const #24 = Method	#23.#14;	//  java/lang/Object."<init>":()V
const #25 = Asciz	scala/Function1$class;
const #26 = class	#25;	//  scala/Function1$class
const #27 = Asciz	$init$;
const #28 = Asciz	(Lscala/Function1;)V;
const #29 = NameAndType	#27:#28;//  $init$:(Lscala/Function1;)V
const #30 = Method	#26.#29;	//  scala/Function1$class.$init$:(Lscala/Function1;)V
const #31 = Asciz	this;
const #32 = Asciz	Lscala/Function$$anonfun$curried$4$$anonfun$apply$8$$anonfun$apply$9$$anonfun$apply$10$$anonfun$apply$11;;
const #33 = Asciz	LocalVariableTable;
const #34 = Asciz	apply;
const #35 = Asciz	(Ljava/lang/Object;)Ljava/lang/Object;;
const #36 = Asciz	scala/Function$$anonfun$curried$4$$anonfun$apply$8$$anonfun$apply$9$$anonfun$apply$10;
const #37 = class	#36;	//  scala/Function$$anonfun$curried$4$$anonfun$apply$8$$anonfun$apply$9$$anonfun$apply$10
const #38 = Asciz	scala$Function$$anonfun$$anonfun$$anonfun$$anonfun$$$outer;
const #39 = Asciz	()Lscala/Function$$anonfun$curried$4$$anonfun$apply$8$$anonfun$apply$9;;
const #40 = NameAndType	#38:#39;//  scala$Function$$anonfun$$anonfun$$anonfun$$anonfun$$$outer:()Lscala/Function$$anonfun$curried$4$$anonfun$apply$8$$anonfun$apply$9;
const #41 = Method	#37.#40;	//  scala/Function$$anonfun$curried$4$$anonfun$apply$8$$anonfun$apply$9$$anonfun$apply$10.scala$Function$$anonfun$$anonfun$$anonfun$$anonfun$$$outer:()Lscala/Function$$anonfun$curried$4$$anonfun$apply$8$$anonfun$apply$9;
const #42 = Asciz	scala/Function$$anonfun$curried$4$$anonfun$apply$8$$anonfun$apply$9;
const #43 = class	#42;	//  scala/Function$$anonfun$curried$4$$anonfun$apply$8$$anonfun$apply$9
const #44 = Asciz	scala$Function$$anonfun$$anonfun$$anonfun$$$outer;
const #45 = Asciz	()Lscala/Function$$anonfun$curried$4$$anonfun$apply$8;;
const #46 = NameAndType	#44:#45;//  scala$Function$$anonfun$$anonfun$$anonfun$$$outer:()Lscala/Function$$anonfun$curried$4$$anonfun$apply$8;
const #47 = Method	#43.#46;	//  scala/Function$$anonfun$curried$4$$anonfun$apply$8$$anonfun$apply$9.scala$Function$$anonfun$$anonfun$$anonfun$$$outer:()Lscala/Function$$anonfun$curried$4$$anonfun$apply$8;
const #48 = Asciz	scala/Function$$anonfun$curried$4$$anonfun$apply$8;
const #49 = class	#48;	//  scala/Function$$anonfun$curried$4$$anonfun$apply$8
const #50 = Asciz	scala$Function$$anonfun$$anonfun$$$outer;
const #51 = Asciz	()Lscala/Function$$anonfun$curried$4;;
const #52 = NameAndType	#50:#51;//  scala$Function$$anonfun$$anonfun$$$outer:()Lscala/Function$$anonfun$curried$4;
const #53 = Method	#49.#52;	//  scala/Function$$anonfun$curried$4$$anonfun$apply$8.scala$Function$$anonfun$$anonfun$$$outer:()Lscala/Function$$anonfun$curried$4;
const #54 = Asciz	scala/Function$$anonfun$curried$4;
const #55 = class	#54;	//  scala/Function$$anonfun$curried$4
const #56 = Asciz	f$4;
const #57 = Asciz	Lscala/Function5;;
const #58 = NameAndType	#56:#57;//  f$4:Lscala/Function5;
const #59 = Field	#55.#58;	//  scala/Function$$anonfun$curried$4.f$4:Lscala/Function5;
const #60 = Asciz	x1$4;
const #61 = NameAndType	#60:#4;//  x1$4:Ljava/lang/Object;
const #62 = Field	#49.#61;	//  scala/Function$$anonfun$curried$4$$anonfun$apply$8.x1$4:Ljava/lang/Object;
const #63 = Asciz	x2$3;
const #64 = NameAndType	#63:#4;//  x2$3:Ljava/lang/Object;
const #65 = Field	#43.#64;	//  scala/Function$$anonfun$curried$4$$anonfun$apply$8$$anonfun$apply$9.x2$3:Ljava/lang/Object;
const #66 = Asciz	x3$2;
const #67 = NameAndType	#66:#4;//  x3$2:Ljava/lang/Object;
const #68 = Field	#37.#67;	//  scala/Function$$anonfun$curried$4$$anonfun$apply$8$$anonfun$apply$9$$anonfun$apply$10.x3$2:Ljava/lang/Object;
const #69 = Asciz	scala/Function5;
const #70 = class	#69;	//  scala/Function5
const #71 = Asciz	(Ljava/lang/Object;Ljava/lang/Object;Ljava/lang/Object;Ljava/lang/Object;Ljava/lang/Object;)Ljava/lang/Object;;
const #72 = NameAndType	#34:#71;//  apply:(Ljava/lang/Object;Ljava/lang/Object;Ljava/lang/Object;Ljava/lang/Object;Ljava/lang/Object;)Ljava/lang/Object;
const #73 = InterfaceMethod	#70.#72;	//  scala/Function5.apply:(Ljava/lang/Object;Ljava/lang/Object;Ljava/lang/Object;Ljava/lang/Object;Ljava/lang/Object;)Ljava/lang/Object;
const #74 = Asciz	x5;
const #75 = Asciz	(Ta5;)Tb;;
const #76 = Asciz	Signature;
const #77 = Asciz	andThen;
const #78 = Asciz	(Lscala/Function1;)Lscala/Function1;;
const #79 = Asciz	(Lscala/Function1;Lscala/Function1;)Lscala/Function1;;
const #80 = NameAndType	#77:#79;//  andThen:(Lscala/Function1;Lscala/Function1;)Lscala/Function1;
const #81 = Method	#26.#80;	//  scala/Function1$class.andThen:(Lscala/Function1;Lscala/Function1;)Lscala/Function1;
const #82 = Asciz	g;
const #83 = Asciz	Lscala/Function1;;
const #84 = Asciz	compose;
const #85 = NameAndType	#84:#79;//  compose:(Lscala/Function1;Lscala/Function1;)Lscala/Function1;
const #86 = Method	#26.#85;	//  scala/Function1$class.compose:(Lscala/Function1;Lscala/Function1;)Lscala/Function1;
const #87 = Asciz	toString;
const #88 = Asciz	()Ljava/lang/String;;
const #89 = Asciz	(Lscala/Function1;)Ljava/lang/String;;
const #90 = NameAndType	#87:#89;//  toString:(Lscala/Function1;)Ljava/lang/String;
const #91 = Method	#26.#90;	//  scala/Function1$class.toString:(Lscala/Function1;)Ljava/lang/String;
const #92 = Asciz	Scala;
const #93 = Asciz	InnerClasses;
const #94 = Asciz	scala/Function;
const #95 = class	#94;	//  scala/Function
const #96 = Asciz	$anonfun$curried$4;
const #97 = Asciz	$anonfun$apply$8;
const #98 = Asciz	$anonfun$apply$9;
const #99 = Asciz	$anonfun$apply$10;
const #100 = Asciz	$anonfun$apply$11;
const #101 = Asciz	scala/Function1;
const #102 = class	#101;	//  scala/Function1
const #103 = Asciz	scala/ScalaObject;
const #104 = class	#103;	//  scala/ScalaObject
const #105 = Asciz	java/io/Serializable;
const #106 = class	#105;	//  java/io/Serializable

{
public scala.Function$$anonfun$curried$4$$anonfun$apply$8$$anonfun$apply$9$$anonfun$apply$10$$anonfun$apply$11(scala.Function$$anonfun$curried$4$$anonfun$apply$8$$anonfun$apply$9$$anonfun$apply$10, java.lang.Object);
  Code:
   Stack=2, Locals=3, Args_size=3
   0:	aload_1
   1:	ifnonnull	12
   4:	new	#12; //class java/lang/NullPointerException
   7:	dup
   8:	invokespecial	#15; //Method java/lang/NullPointerException."<init>":()V
   11:	athrow
   12:	aload_0
   13:	aload_1
   14:	putfield	#19; //Field $outer:Lscala/Function$$anonfun$curried$4$$anonfun$apply$8$$anonfun$apply$9$$anonfun$apply$10;
   17:	aload_0
   18:	aload_2
   19:	putfield	#21; //Field x4$1:Ljava/lang/Object;
   22:	aload_0
   23:	invokespecial	#24; //Method java/lang/Object."<init>":()V
   26:	aload_0
   27:	invokestatic	#30; //Method scala/Function1$class.$init$:(Lscala/Function1;)V
   30:	return
  LineNumberTable: 
   line 61: 0

  LocalVariableTable: 
   Start  Length  Slot  Name   Signature
   0      31      0    this       Lscala/Function$$anonfun$curried$4$$anonfun$apply$8$$anonfun$apply$9$$anonfun$apply$10$$anonfun$apply$11;
   0      31      1    $outer       Lscala/Function$$anonfun$curried$4$$anonfun$apply$8$$anonfun$apply$9$$anonfun$apply$10;


public final java.lang.Object apply(java.lang.Object);
  Code:
   Stack=6, Locals=3, Args_size=2
   0:	aload_0
   1:	getfield	#19; //Field $outer:Lscala/Function$$anonfun$curried$4$$anonfun$apply$8$$anonfun$apply$9$$anonfun$apply$10;
   4:	astore_2
   5:	aload_0
   6:	getfield	#19; //Field $outer:Lscala/Function$$anonfun$curried$4$$anonfun$apply$8$$anonfun$apply$9$$anonfun$apply$10;
   9:	invokevirtual	#41; //Method scala/Function$$anonfun$curried$4$$anonfun$apply$8$$anonfun$apply$9$$anonfun$apply$10.scala$Function$$anonfun$$anonfun$$anonfun$$anonfun$$$outer:()Lscala/Function$$anonfun$curried$4$$anonfun$apply$8$$anonfun$apply$9;
   12:	invokevirtual	#47; //Method scala/Function$$anonfun$curried$4$$anonfun$apply$8$$anonfun$apply$9.scala$Function$$anonfun$$anonfun$$anonfun$$$outer:()Lscala/Function$$anonfun$curried$4$$anonfun$apply$8;
   15:	invokevirtual	#53; //Method scala/Function$$anonfun$curried$4$$anonfun$apply$8.scala$Function$$anonfun$$anonfun$$$outer:()Lscala/Function$$anonfun$curried$4;
   18:	getfield	#59; //Field scala/Function$$anonfun$curried$4.f$4:Lscala/Function5;
   21:	aload_0
   22:	getfield	#19; //Field $outer:Lscala/Function$$anonfun$curried$4$$anonfun$apply$8$$anonfun$apply$9$$anonfun$apply$10;
   25:	invokevirtual	#41; //Method scala/Function$$anonfun$curried$4$$anonfun$apply$8$$anonfun$apply$9$$anonfun$apply$10.scala$Function$$anonfun$$anonfun$$anonfun$$anonfun$$$outer:()Lscala/Function$$anonfun$curried$4$$anonfun$apply$8$$anonfun$apply$9;
   28:	invokevirtual	#47; //Method scala/Function$$anonfun$curried$4$$anonfun$apply$8$$anonfun$apply$9.scala$Function$$anonfun$$anonfun$$anonfun$$$outer:()Lscala/Function$$anonfun$curried$4$$anonfun$apply$8;
   31:	getfield	#62; //Field scala/Function$$anonfun$curried$4$$anonfun$apply$8.x1$4:Ljava/lang/Object;
   34:	aload_0
   35:	getfield	#19; //Field $outer:Lscala/Function$$anonfun$curried$4$$anonfun$apply$8$$anonfun$apply$9$$anonfun$apply$10;
   38:	invokevirtual	#41; //Method scala/Function$$anonfun$curried$4$$anonfun$apply$8$$anonfun$apply$9$$anonfun$apply$10.scala$Function$$anonfun$$anonfun$$anonfun$$anonfun$$$outer:()Lscala/Function$$anonfun$curried$4$$anonfun$apply$8$$anonfun$apply$9;
   41:	getfield	#65; //Field scala/Function$$anonfun$curried$4$$anonfun$apply$8$$anonfun$apply$9.x2$3:Ljava/lang/Object;
   44:	aload_0
   45:	getfield	#19; //Field $outer:Lscala/Function$$anonfun$curried$4$$anonfun$apply$8$$anonfun$apply$9$$anonfun$apply$10;
   48:	getfield	#68; //Field scala/Function$$anonfun$curried$4$$anonfun$apply$8$$anonfun$apply$9$$anonfun$apply$10.x3$2:Ljava/lang/Object;
   51:	aload_0
   52:	getfield	#21; //Field x4$1:Ljava/lang/Object;
   55:	aload_1
   56:	invokeinterface	#73,  6; //InterfaceMethod scala/Function5.apply:(Ljava/lang/Object;Ljava/lang/Object;Ljava/lang/Object;Ljava/lang/Object;Ljava/lang/Object;)Ljava/lang/Object;
   61:	areturn
  LineNumberTable: 
   line 61: 0

  LocalVariableTable: 
   Start  Length  Slot  Name   Signature
   0      62      0    this       Lscala/Function$$anonfun$curried$4$$anonfun$apply$8$$anonfun$apply$9$$anonfun$apply$10$$anonfun$apply$11;
   5      57      1    x5       Ljava/lang/Object;

  Signature: length = 0x2
   00 4B 

public scala.Function1 andThen(scala.Function1);
  Code:
   Stack=2, Locals=2, Args_size=2
   0:	aload_0
   1:	aload_1
   2:	invokestatic	#81; //Method scala/Function1$class.andThen:(Lscala/Function1;Lscala/Function1;)Lscala/Function1;
   5:	areturn
  LineNumberTable: 
   line 61: 0

  LocalVariableTable: 
   Start  Length  Slot  Name   Signature
   0      6      0    this       Lscala/Function$$anonfun$curried$4$$anonfun$apply$8$$anonfun$apply$9$$anonfun$apply$10$$anonfun$apply$11;
   0      6      1    g       Lscala/Function1;


public scala.Function1 compose(scala.Function1);
  Code:
   Stack=2, Locals=2, Args_size=2
   0:	aload_0
   1:	aload_1
   2:	invokestatic	#86; //Method scala/Function1$class.compose:(Lscala/Function1;Lscala/Function1;)Lscala/Function1;
   5:	areturn
  LineNumberTable: 
   line 61: 0

  LocalVariableTable: 
   Start  Length  Slot  Name   Signature
   0      6      0    this       Lscala/Function$$anonfun$curried$4$$anonfun$apply$8$$anonfun$apply$9$$anonfun$apply$10$$anonfun$apply$11;
   0      6      1    g       Lscala/Function1;


public java.lang.String toString();
  Code:
   Stack=1, Locals=1, Args_size=1
   0:	aload_0
   1:	invokestatic	#91; //Method scala/Function1$class.toString:(Lscala/Function1;)Ljava/lang/String;
   4:	areturn
  LineNumberTable: 
   line 61: 0


}

