Compiled from "Function1.scala"
public abstract class scala.Function1$mcDL$sp$class extends java.lang.Object
  SourceFile: "Function1.scala"
  Scala: length = 0x
   
  InnerClass: 
   public final $anonfun$andThen$mcDL$sp$1=class scala/Function1$mcDL$sp$$anonfun$andThen$mcDL$sp$1 of class scala/Function1$mcDL$sp
   public final $anonfun$compose$mcDL$sp$1=class scala/Function1$mcDL$sp$$anonfun$compose$mcDL$sp$1 of class scala/Function1$mcDL$sp
  minor version: 0
  major version: 49
  Constant pool:
Asciz	SourceFile;
Asciz	Function1.scala;
Asciz	apply;
Asciz	(Lscala/Function1$mcDL$sp;J)D;
Asciz	Code;
Asciz	LineNumberTable;
Asciz	scala/Function1;
class	scala/Function1
Asciz	apply$mcDL$sp;
Asciz	(J)D;
NameAndType	apply$mcDL$sp:(J)D
InterfaceMethod	scala/Function1.apply$mcDL$sp:(J)D
Asciz	$this;
Asciz	Lscala/Function1$mcDL$sp;;
Asciz	v1;
Asciz	J;
Asciz	LocalVariableTable;
Asciz	compose;
Asciz	(Lscala/Function1$mcDL$sp;Lscala/Function1;)Lscala/Function1;;
Asciz	scala/Function1$mcDL$sp;
class	scala/Function1$mcDL$sp
Asciz	compose$mcDL$sp;
Asciz	(Lscala/Function1;)Lscala/Function1;;
NameAndType	compose$mcDL$sp:(Lscala/Function1;)Lscala/Function1;
InterfaceMethod	scala/Function1$mcDL$sp.compose$mcDL$sp:(Lscala/Function1;)Lscala/Function1;
Asciz	g;
Asciz	Lscala/Function1;;
Asciz	scala/Function1$mcDL$sp$$anonfun$compose$mcDL$sp$1;
class	scala/Function1$mcDL$sp$$anonfun$compose$mcDL$sp$1
Asciz	<init>;
Asciz	(Lscala/Function1$mcDL$sp;Lscala/Function1;)V;
NameAndType	"<init>":(Lscala/Function1$mcDL$sp;Lscala/Function1;)V
Method	scala/Function1$mcDL$sp$$anonfun$compose$mcDL$sp$1."<init>":(Lscala/Function1$mcDL$sp;Lscala/Function1;)V
Asciz	g$21;
Asciz	andThen;
Asciz	andThen$mcDL$sp;
NameAndType	andThen$mcDL$sp:(Lscala/Function1;)Lscala/Function1;
InterfaceMethod	scala/Function1$mcDL$sp.andThen$mcDL$sp:(Lscala/Function1;)Lscala/Function1;
Asciz	scala/Function1$mcDL$sp$$anonfun$andThen$mcDL$sp$1;
class	scala/Function1$mcDL$sp$$anonfun$andThen$mcDL$sp$1
Method	scala/Function1$mcDL$sp$$anonfun$andThen$mcDL$sp$1."<init>":(Lscala/Function1$mcDL$sp;Lscala/Function1;)V
Asciz	g$22;
Asciz	$init$;
Asciz	(Lscala/Function1$mcDL$sp;)V;
Asciz	Scala;
Asciz	InnerClasses;
Asciz	$anonfun$andThen$mcDL$sp$1;
Asciz	$anonfun$compose$mcDL$sp$1;
Asciz	scala/Function1$mcDL$sp$class;
class	scala/Function1$mcDL$sp$class
Asciz	java/lang/Object;
class	java/lang/Object

{
public static double apply(scala.Function1$mcDL$sp, long);
  Signature: (Lscala/Function1$mcDL$sp;J)D
  Code:
   Stack=3, Locals=3, Args_size=2
	aload_0
	lload_1
	invokeinterface	InterfaceMethod scala/Function1.apply$mcDL$sp:(J)D
	dreturn
  Labels:
  LocalVariableTable: 
   Start  Length  Slot  Name   Signature
   0      8      0    $this       Lscala/Function1$mcDL$sp;
   0      8      1    v1       J


public static scala.Function1 compose(scala.Function1$mcDL$sp, scala.Function1);
  Signature: (Lscala/Function1$mcDL$sp;Lscala/Function1;)Lscala/Function1;
  Code:
   Stack=2, Locals=2, Args_size=2
	aload_0
	aload_1
	invokeinterface	InterfaceMethod scala/Function1$mcDL$sp.compose$mcDL$sp:(Lscala/Function1;)Lscala/Function1;
	areturn
  Labels:
  LocalVariableTable: 
   Start  Length  Slot  Name   Signature
   0      8      0    $this       Lscala/Function1$mcDL$sp;
   0      8      1    g       Lscala/Function1;


public static scala.Function1 compose$mcDL$sp(scala.Function1$mcDL$sp, scala.Function1);
  Signature: (Lscala/Function1$mcDL$sp;Lscala/Function1;)Lscala/Function1;
  Code:
   Stack=4, Locals=2, Args_size=2
	new	class scala/Function1$mcDL$sp$$anonfun$compose$mcDL$sp$1
	dup
	aload_0
	aload_1
	invokespecial	Method scala/Function1$mcDL$sp$$anonfun$compose$mcDL$sp$1."<init>":(Lscala/Function1$mcDL$sp;Lscala/Function1;)V
	areturn
  Labels:
  LocalVariableTable: 
   Start  Length  Slot  Name   Signature
   0      10      0    $this       Lscala/Function1$mcDL$sp;
   0      10      1    g$21       Lscala/Function1;


public static scala.Function1 andThen(scala.Function1$mcDL$sp, scala.Function1);
  Signature: (Lscala/Function1$mcDL$sp;Lscala/Function1;)Lscala/Function1;
  Code:
   Stack=2, Locals=2, Args_size=2
	aload_0
	aload_1
	invokeinterface	InterfaceMethod scala/Function1$mcDL$sp.andThen$mcDL$sp:(Lscala/Function1;)Lscala/Function1;
	areturn
  Labels:
  LocalVariableTable: 
   Start  Length  Slot  Name   Signature
   0      8      0    $this       Lscala/Function1$mcDL$sp;
   0      8      1    g       Lscala/Function1;


public static scala.Function1 andThen$mcDL$sp(scala.Function1$mcDL$sp, scala.Function1);
  Signature: (Lscala/Function1$mcDL$sp;Lscala/Function1;)Lscala/Function1;
  Code:
   Stack=4, Locals=2, Args_size=2
	new	class scala/Function1$mcDL$sp$$anonfun$andThen$mcDL$sp$1
	dup
	aload_0
	aload_1
	invokespecial	Method scala/Function1$mcDL$sp$$anonfun$andThen$mcDL$sp$1."<init>":(Lscala/Function1$mcDL$sp;Lscala/Function1;)V
	areturn
  Labels:
  LocalVariableTable: 
   Start  Length  Slot  Name   Signature
   0      10      0    $this       Lscala/Function1$mcDL$sp;
   0      10      1    g$22       Lscala/Function1;


public static void $init$(scala.Function1$mcDL$sp);
  Signature: (Lscala/Function1$mcDL$sp;)V
  Code:
   Stack=0, Locals=1, Args_size=1
	return
  Labels:
  LocalVariableTable: 
   Start  Length  Slot  Name   Signature
   0      1      0    $this       Lscala/Function1$mcDL$sp;


}

