Compiled from "Function1.scala"
public abstract class scala.Function1$mcDI$sp$class extends java.lang.Object
  SourceFile: "Function1.scala"
  Scala: length = 0x
   
  InnerClass: 
   public final $anonfun$andThen$mcDI$sp$1=class scala/Function1$mcDI$sp$$anonfun$andThen$mcDI$sp$1 of class scala/Function1$mcDI$sp
   public final $anonfun$compose$mcDI$sp$1=class scala/Function1$mcDI$sp$$anonfun$compose$mcDI$sp$1 of class scala/Function1$mcDI$sp
  minor version: 0
  major version: 49
  Constant pool:
Asciz	SourceFile;
Asciz	Function1.scala;
Asciz	apply;
Asciz	(Lscala/Function1$mcDI$sp;I)D;
Asciz	Code;
Asciz	LineNumberTable;
Asciz	scala/Function1;
class	scala/Function1
Asciz	apply$mcDI$sp;
Asciz	(I)D;
NameAndType	apply$mcDI$sp:(I)D
InterfaceMethod	scala/Function1.apply$mcDI$sp:(I)D
Asciz	$this;
Asciz	Lscala/Function1$mcDI$sp;;
Asciz	v1;
Asciz	I;
Asciz	LocalVariableTable;
Asciz	compose;
Asciz	(Lscala/Function1$mcDI$sp;Lscala/Function1;)Lscala/Function1;;
Asciz	scala/Function1$mcDI$sp;
class	scala/Function1$mcDI$sp
Asciz	compose$mcDI$sp;
Asciz	(Lscala/Function1;)Lscala/Function1;;
NameAndType	compose$mcDI$sp:(Lscala/Function1;)Lscala/Function1;
InterfaceMethod	scala/Function1$mcDI$sp.compose$mcDI$sp:(Lscala/Function1;)Lscala/Function1;
Asciz	g;
Asciz	Lscala/Function1;;
Asciz	scala/Function1$mcDI$sp$$anonfun$compose$mcDI$sp$1;
class	scala/Function1$mcDI$sp$$anonfun$compose$mcDI$sp$1
Asciz	<init>;
Asciz	(Lscala/Function1$mcDI$sp;Lscala/Function1;)V;
NameAndType	"<init>":(Lscala/Function1$mcDI$sp;Lscala/Function1;)V
Method	scala/Function1$mcDI$sp$$anonfun$compose$mcDI$sp$1."<init>":(Lscala/Function1$mcDI$sp;Lscala/Function1;)V
Asciz	g$11;
Asciz	andThen;
Asciz	andThen$mcDI$sp;
NameAndType	andThen$mcDI$sp:(Lscala/Function1;)Lscala/Function1;
InterfaceMethod	scala/Function1$mcDI$sp.andThen$mcDI$sp:(Lscala/Function1;)Lscala/Function1;
Asciz	scala/Function1$mcDI$sp$$anonfun$andThen$mcDI$sp$1;
class	scala/Function1$mcDI$sp$$anonfun$andThen$mcDI$sp$1
Method	scala/Function1$mcDI$sp$$anonfun$andThen$mcDI$sp$1."<init>":(Lscala/Function1$mcDI$sp;Lscala/Function1;)V
Asciz	g$12;
Asciz	$init$;
Asciz	(Lscala/Function1$mcDI$sp;)V;
Asciz	Scala;
Asciz	InnerClasses;
Asciz	$anonfun$andThen$mcDI$sp$1;
Asciz	$anonfun$compose$mcDI$sp$1;
Asciz	scala/Function1$mcDI$sp$class;
class	scala/Function1$mcDI$sp$class
Asciz	java/lang/Object;
class	java/lang/Object

{
public static double apply(scala.Function1$mcDI$sp, int);
  Signature: (Lscala/Function1$mcDI$sp;I)D
  Code:
   Stack=2, Locals=2, Args_size=2
	aload_0
	iload_1
	invokeinterface	InterfaceMethod scala/Function1.apply$mcDI$sp:(I)D
	dreturn
  Labels:
  LocalVariableTable: 
   Start  Length  Slot  Name   Signature
   0      8      0    $this       Lscala/Function1$mcDI$sp;
   0      8      1    v1       I


public static scala.Function1 compose(scala.Function1$mcDI$sp, scala.Function1);
  Signature: (Lscala/Function1$mcDI$sp;Lscala/Function1;)Lscala/Function1;
  Code:
   Stack=2, Locals=2, Args_size=2
	aload_0
	aload_1
	invokeinterface	InterfaceMethod scala/Function1$mcDI$sp.compose$mcDI$sp:(Lscala/Function1;)Lscala/Function1;
	areturn
  Labels:
  LocalVariableTable: 
   Start  Length  Slot  Name   Signature
   0      8      0    $this       Lscala/Function1$mcDI$sp;
   0      8      1    g       Lscala/Function1;


public static scala.Function1 compose$mcDI$sp(scala.Function1$mcDI$sp, scala.Function1);
  Signature: (Lscala/Function1$mcDI$sp;Lscala/Function1;)Lscala/Function1;
  Code:
   Stack=4, Locals=2, Args_size=2
	new	class scala/Function1$mcDI$sp$$anonfun$compose$mcDI$sp$1
	dup
	aload_0
	aload_1
	invokespecial	Method scala/Function1$mcDI$sp$$anonfun$compose$mcDI$sp$1."<init>":(Lscala/Function1$mcDI$sp;Lscala/Function1;)V
	areturn
  Labels:
  LocalVariableTable: 
   Start  Length  Slot  Name   Signature
   0      10      0    $this       Lscala/Function1$mcDI$sp;
   0      10      1    g$11       Lscala/Function1;


public static scala.Function1 andThen(scala.Function1$mcDI$sp, scala.Function1);
  Signature: (Lscala/Function1$mcDI$sp;Lscala/Function1;)Lscala/Function1;
  Code:
   Stack=2, Locals=2, Args_size=2
	aload_0
	aload_1
	invokeinterface	InterfaceMethod scala/Function1$mcDI$sp.andThen$mcDI$sp:(Lscala/Function1;)Lscala/Function1;
	areturn
  Labels:
  LocalVariableTable: 
   Start  Length  Slot  Name   Signature
   0      8      0    $this       Lscala/Function1$mcDI$sp;
   0      8      1    g       Lscala/Function1;


public static scala.Function1 andThen$mcDI$sp(scala.Function1$mcDI$sp, scala.Function1);
  Signature: (Lscala/Function1$mcDI$sp;Lscala/Function1;)Lscala/Function1;
  Code:
   Stack=4, Locals=2, Args_size=2
	new	class scala/Function1$mcDI$sp$$anonfun$andThen$mcDI$sp$1
	dup
	aload_0
	aload_1
	invokespecial	Method scala/Function1$mcDI$sp$$anonfun$andThen$mcDI$sp$1."<init>":(Lscala/Function1$mcDI$sp;Lscala/Function1;)V
	areturn
  Labels:
  LocalVariableTable: 
   Start  Length  Slot  Name   Signature
   0      10      0    $this       Lscala/Function1$mcDI$sp;
   0      10      1    g$12       Lscala/Function1;


public static void $init$(scala.Function1$mcDI$sp);
  Signature: (Lscala/Function1$mcDI$sp;)V
  Code:
   Stack=0, Locals=1, Args_size=1
	return
  Labels:
  LocalVariableTable: 
   Start  Length  Slot  Name   Signature
   0      1      0    $this       Lscala/Function1$mcDI$sp;


}

