Compiled from "Range.scala"
public abstract class scala.GenericRange extends java.lang.Object implements scala.collection.generic.VectorView,scala.RangeToString,scala.util.Hashable,scala.ScalaObject
  SourceFile: "Range.scala"
  Signature: length = 0x2
   04 46 
  ScalaSig: length = 0x843
   05 00 FFFFFF82 1C 06 05 01 02 FFFFFF81 00 05 02 0C 47 65 6E
   65 72 69 63 52 61 6E 67 65 0A 01 03 01 05 73 63
   61 6C 61 03 00 15 02 06 19 13 06 00 07 0F 29 2C
   32 10 02 08 0D 0D 01 09 0A 02 0A 0B 01 04 6C 61
   6E 67 0A 01 0C 01 04 6A 61 76 61 09 02 0E 09 02
   06 4F 62 6A 65 63 74 10 04 10 15 17 23 0D 01 11
   0A 02 12 13 01 07 67 65 6E 65 72 69 63 0A 02 14
   02 01 0A 63 6F 6C 6C 65 63 74 69 6F 6E 09 02 16
   11 02 0A 56 65 63 74 6F 72 56 69 65 77 10 02 18
   19 0C 00 04 08 1A 00 FFFFFF84 FFFFFF80 FFFFFF80 FFFFFFC2 00 1B 02 01 54
   11 02 1C 20 10 02 1D 1E 0D 01 02 09 02 1F 02 02
   07 4E 6F 74 68 69 6E 67 10 02 1D 21 09 02 22 02
   02 03 41 6E 79 10 03 24 27 17 0D 01 25 0A 02 26
   13 01 09 69 6D 6D 75 74 61 62 6C 65 09 02 28 25
   02 06 56 65 63 74 6F 72 10 03 1D 2A 17 09 02 2B
   02 02 0D 52 61 6E 67 65 54 6F 53 74 72 69 6E 67
   10 02 2D 30 0D 01 2E 0A 02 2F 02 01 04 75 74 69
   6C 09 02 31 2E 02 08 48 61 73 68 61 62 6C 65 10
   02 1D 33 09 02 34 02 02 0B 53 63 61 6C 61 4F 62
   6A 65 63 74 08 08 36 00 FFFFFF82 FFFFFFC2 FFFFFF80 FFFFFF84 00 37 01 05
   73 74 61 72 74 15 01 17 08 08 39 00 FFFFFF82 FFFFFF80 FFFFFFA0 FFFFFF80
   04 17 01 06 73 74 61 72 74 20 08 08 3B 00 FFFFFF82 FFFFFFC2
   FFFFFF80 FFFFFF84 00 37 01 03 65 6E 64 08 08 3D 00 FFFFFF82 FFFFFF80 FFFFFFA0
   FFFFFF80 04 17 01 04 65 6E 64 20 08 08 3F 00 FFFFFF82 FFFFFFC2 FFFFFF80
   FFFFFF84 00 37 01 04 73 74 65 70 08 08 41 00 FFFFFF82 FFFFFF80 FFFFFFA0
   FFFFFF80 04 17 01 05 73 74 65 70 20 08 08 43 00 FFFFFF82 FFFFFFC2
   FFFFFF80 FFFFFF84 00 44 01 0B 69 73 49 6E 63 6C 75 73 69 76
   65 15 01 45 10 02 1D 46 09 02 47 02 02 07 42 6F
   6F 6C 65 61 6E 08 08 49 00 FFFFFF82 FFFFFF80 FFFFFFA0 FFFFFF80 04 45 01
   0C 69 73 49 6E 63 6C 75 73 69 76 65 20 08 08 4B
   00 FFFFFF82 FFFFFF80 FFFFFFA0 FFFFFF80 05 4C 01 03 6E 75 6D 10 03 1D 4D
   17 09 02 4E 02 02 08 49 6E 74 65 67 72 61 6C 08
   05 50 00 FFFFFF84 00 51 01 06 3C 69 6E 69 74 3E 14 05
   52 55 56 57 58 16 02 53 54 10 03 1D 00 17 08 05
   4B 4F FFFFFFC0 01 4C 08 05 36 4F FFFFFFC0 00 17 08 05 3B 4F
   FFFFFFC0 00 17 08 05 3F 4F FFFFFFC0 00 17 08 08 59 43 4F FFFFFF90
   FFFFFF80 FFFFFFC0 00 45 08 08 5A 5B FFFFFF91 FFFFFF80 FFFFFF84 00 FFFFFF81 35 01 0E
   69 6E 69 74 24 64 65 66 61 75 6C 74 24 34 06 08
   01 02 FFFFFF84 FFFFFF80 FFFFFF80 FFFFFF88 02 5C 13 03 5B 07 32 08 05 50
   5B FFFFFF84 00 5E 14 01 5F 10 02 1D 5B 06 04 61 5B 00
   62 02 09 49 6E 63 6C 75 73 69 76 65 15 02 63 66
   13 03 60 64 32 10 03 1D 00 65 10 02 18 66 04 08
   1A 60 FFFFFF84 FFFFFF80 FFFFFF80 FFFFFFC2 00 1B 08 09 36 60 FFFFFF82 FFFFFF80 FFFFFFA0 FFFFFF80
   04 65 35 08 09 3B 60 FFFFFF82 FFFFFF80 FFFFFFA0 FFFFFF80 04 65 3A 08 09
   3F 60 FFFFFF82 FFFFFF80 FFFFFFA0 FFFFFF80 04 65 3E 08 08 4B 60 FFFFFF82 FFFFFF80 FFFFFFA0
   FFFFFF80 05 6B 10 03 1D 4D 65 08 05 50 60 FFFFFF84 00 6D 14
   04 6E 72 73 74 16 02 6F 71 10 03 70 60 65 0D 01
   5B 08 05 4B 6C FFFFFFC0 01 6B 08 05 36 6C FFFFFFC0 00 65 08
   05 3B 6C FFFFFFC0 00 65 08 05 3F 6C FFFFFFC0 00 65 08 05 76
   60 FFFFFF84 00 77 01 09 65 78 63 6C 75 73 69 76 65 15
   01 78 10 03 70 79 65 06 04 7A 5B 00 7B 02 09 45
   78 63 6C 75 73 69 76 65 15 02 7C 7F 13 03 79 7D
   32 10 03 1D 00 7E 10 02 18 7F 04 08 1A 79 FFFFFF84 FFFFFF80
   FFFFFF80 FFFFFFC2 00 1B 08 09 36 79 FFFFFF82 FFFFFF80 FFFFFFA0 FFFFFF80 04 7E 35 08
   09 3B 79 FFFFFF82 FFFFFF80 FFFFFFA0 FFFFFF80 04 7E 3A 08 09 3F 79 FFFFFF82 FFFFFF80
   FFFFFFA0 FFFFFF80 04 7E 3E 08 09 4B 79 FFFFFF82 FFFFFF80 FFFFFFA0 FFFFFF80 05 FFFFFF81 04
   10 03 1D 4D 7E 08 06 50 79 FFFFFF84 00 FFFFFF81 06 14 08 FFFFFF81
   07 FFFFFF81 0A FFFFFF81 0B FFFFFF81 0C 16 04 FFFFFF81 08 FFFFFF81 09 10 03 70
   79 7E 08 07 4B FFFFFF81 05 FFFFFFC0 01 FFFFFF81 04 08 06 36 FFFFFF81 05
   FFFFFFC0 00 7E 08 06 3B FFFFFF81 05 FFFFFFC0 00 7E 08 06 3F FFFFFF81 05
   FFFFFFC0 00 7E 08 07 FFFFFF81 0E 79 FFFFFF84 00 FFFFFF81 0F 01 09 69 6E
   63 6C 75 73 69 76 65 15 02 FFFFFF81 10 10 03 70 60 7E
   08 07 FFFFFF81 12 79 FFFFFF84 00 FFFFFF81 13 01 04 63 6F 70 79 14
   08 FFFFFF81 08 FFFFFF81 14 FFFFFF81 15 FFFFFF81 16 08 06 36 FFFFFF81 11 FFFFFFC0 00
   7E 08 06 3B FFFFFF81 11 FFFFFFC0 00 7E 08 06 3F FFFFFF81 11 FFFFFFC0 00
   7E 08 07 FFFFFF81 12 60 FFFFFF84 00 FFFFFF81 18 14 07 6F FFFFFF81 19 FFFFFF81
   1A FFFFFF81 1B 08 06 36 FFFFFF81 17 FFFFFFC0 00 65 08 06 3B FFFFFF81 17
   FFFFFFC0 00 65 08 06 3F FFFFFF81 17 FFFFFFC0 00 65 08 07 FFFFFF81 1D 5B
   FFFFFF84 00 FFFFFF81 1E 01 05 61 70 70 6C 79 15 04 FFFFFF81 1F FFFFFF81
   23 14 08 FFFFFF81 20 FFFFFF81 26 FFFFFF81 27 FFFFFF81 28 16 04 FFFFFF81 21 FFFFFF81
   24 10 04 70 79 FFFFFF81 22 10 03 18 FFFFFF81 23 04 09 1A FFFFFF81
   1C FFFFFF84 FFFFFF80 FFFFFF80 FFFFFFC2 00 1B 08 07 4B FFFFFF81 1C FFFFFFC0 01 FFFFFF81 25
   10 04 1D 4D FFFFFF81 22 08 07 36 FFFFFF81 1C FFFFFFC0 00 FFFFFF81 22 08
   07 3B FFFFFF81 1C FFFFFFC0 00 FFFFFF81 22 08 07 3F FFFFFF81 1C FFFFFFC0 00 FFFFFF81
   22 08 07 FFFFFF81 0E 5B FFFFFF84 00 FFFFFF81 2A 15 04 FFFFFF81 2B FFFFFF81 2F
   14 08 FFFFFF81 2C FFFFFF81 32 FFFFFF81 33 FFFFFF81 34 16 04 FFFFFF81 2D FFFFFF81 30
   10 04 70 60 FFFFFF81 2E 10 03 18 FFFFFF81 2F 04 09 1A FFFFFF81 29
   FFFFFF84 FFFFFF80 FFFFFF80 FFFFFFC2 00 1B 08 07 4B FFFFFF81 29 FFFFFFC0 01 FFFFFF81 31 10
   04 1D 4D FFFFFF81 2E 08 07 36 FFFFFF81 29 FFFFFFC0 00 FFFFFF81 2E 08 07
   3B FFFFFF81 29 FFFFFFC0 00 FFFFFF81 2E 08 07 3F FFFFFF81 29 FFFFFFC0 00 FFFFFF81 2E
   15 03 45 FFFFFF81 36 04 08 1A 59 FFFFFF84 FFFFFF80 FFFFFF80 FFFFFFC2 00 1B 08
   09 FFFFFF81 38 00 FFFFFF88 FFFFFFC2 FFFFFF80 FFFFFF84 04 37 01 07 74 72 75 65
   45 6E 64 08 09 FFFFFF81 3A 00 FFFFFF88 FFFFFF80 FFFFFFA0 FFFFFFA0 04 17 01 08
   74 72 75 65 45 6E 64 20 08 07 FFFFFF81 3C 00 FFFFFF84 08 FFFFFF81
   3D 01 0A 75 6E 64 65 72 6C 79 69 6E 67 15 01 23
   08 07 FFFFFF81 3F 00 FFFFFF84 00 FFFFFF81 40 01 02 62 79 14 03 53
   FFFFFF81 41 08 07 FFFFFF81 42 FFFFFF81 3E FFFFFFC0 00 17 01 07 6E 65 77
   53 74 65 70 08 07 FFFFFF81 12 00 FFFFFF86 00 FFFFFF81 44 14 07 53
   FFFFFF81 45 FFFFFF81 46 FFFFFF81 47 08 06 36 FFFFFF81 43 FFFFFFC0 00 17 08 06
   3B FFFFFF81 43 FFFFFFC0 00 17 08 06 3F FFFFFF81 43 FFFFFFC0 00 17 08 07
   FFFFFF81 49 00 FFFFFF84 00 FFFFFF81 4A 01 06 24 6D 69 6E 75 73 14
   03 53 FFFFFF81 4B 08 07 FFFFFF81 4C FFFFFF81 48 FFFFFFC0 00 17 01 05 73
   68 69 66 74 08 07 FFFFFF81 4E 00 FFFFFF84 00 FFFFFF81 4F 01 05 24
   70 6C 75 73 14 03 53 FFFFFF81 50 08 07 FFFFFF81 4C FFFFFF81 4D FFFFFFC0
   00 17 08 07 FFFFFF81 52 00 FFFFFF84 00 FFFFFF81 53 01 06 24 74 69
   6D 65 73 14 03 53 FFFFFF81 54 08 07 FFFFFF81 55 FFFFFF81 51 FFFFFFC0 00
   17 01 04 6D 75 6C 74 08 07 FFFFFF81 57 00 FFFFFF84 20 FFFFFF81 58
   01 07 66 6F 72 65 61 63 68 15 04 FFFFFF81 59 FFFFFF81 63 14
   04 FFFFFF81 5A FFFFFF81 5D 10 03 1D FFFFFF81 5B 09 03 FFFFFF81 5C 02 02
   04 55 6E 69 74 08 08 FFFFFF81 5E FFFFFF81 56 FFFFFFC0 00 FFFFFF81 5F 01
   01 66 10 06 1D FFFFFF81 60 17 FFFFFF81 62 09 03 FFFFFF81 61 02 02
   09 46 75 6E 63 74 69 6F 6E 31 10 03 18 FFFFFF81 63 04
   0A FFFFFF81 64 FFFFFF81 56 FFFFFF84 FFFFFF80 FFFFFF80 FFFFFFC2 00 1B 02 01 55 08 09
   FFFFFF81 66 00 FFFFFF88 FFFFFFC2 FFFFFF80 FFFFFF84 00 37 01 0D 67 65 6E 65 72
   69 63 4C 65 6E 67 74 68 08 09 FFFFFF81 68 00 FFFFFF88 FFFFFF80 FFFFFFA0
   FFFFFFA0 04 17 01 0E 67 65 6E 65 72 69 63 4C 65 6E 67
   74 68 20 08 0A FFFFFF81 6A 00 FFFFFF88 FFFFFFC2 FFFFFF80 FFFFFF84 00 FFFFFF81 6B 01
   06 6C 65 6E 67 74 68 15 02 FFFFFF81 6C 10 03 1D FFFFFF81 6D
   09 03 FFFFFF81 6E 02 02 03 49 6E 74 08 0A FFFFFF81 70 00 FFFFFF88
   FFFFFF80 FFFFFFA0 FFFFFFA0 04 FFFFFF81 6C 01 07 6C 65 6E 67 74 68 20 08
   07 FFFFFF81 1D 00 FFFFFF84 00 FFFFFF81 72 14 03 17 FFFFFF81 73 08 08 FFFFFF81
   74 FFFFFF81 71 FFFFFFC0 00 FFFFFF81 6C 01 03 69 64 78 08 07 FFFFFF81 76
   00 FFFFFF84 00 FFFFFF81 77 01 07 61 70 70 6C 79 41 74 14 03
   17 FFFFFF81 78 08 07 FFFFFF81 74 FFFFFF81 75 FFFFFFC0 00 17 08 07 FFFFFF81 7A
   00 FFFFFF84 20 FFFFFF81 7B 01 08 63 6F 6E 74 61 69 6E 73 14
   03 45 FFFFFF81 7C 08 07 FFFFFF81 7D FFFFFF81 79 FFFFFFC0 00 20 01 02 5F
   78 08 09 FFFFFF81 7F 00 FFFFFFC2 FFFFFF80 FFFFFF84 00 FFFFFF82 00 01 0A 68 61
   73 68 56 61 6C 75 65 73 15 02 FFFFFF82 01 10 04 24 FFFFFF82
   02 17 09 03 FFFFFF82 03 25 02 04 4C 69 73 74 08 08 FFFFFF82
   05 00 FFFFFFA0 FFFFFF80 04 FFFFFF82 01 01 0B 68 61 73 68 56 61 6C
   75 65 73 20 08 07 FFFFFF82 07 00 FFFFFF84 20 FFFFFF82 08 01 06 65
   71 75 61 6C 73 14 03 45 FFFFFF82 09 08 07 FFFFFF82 0A FFFFFF82 06
   FFFFFFC0 00 20 01 05 6F 74 68 65 72 08 0C FFFFFF82 0C 00 FFFFFF81
   FFFFFF80 FFFFFF80 FFFFFF84 04 FFFFFF82 0D FFFFFF82 10 01 0E 73 75 70 65 72 24
   63 6F 6E 74 61 69 6E 73 14 03 45 FFFFFF82 0E 08 07 FFFFFF82
   0F FFFFFF82 0B FFFFFFC0 00 20 01 04 65 6C 65 6D 09 04 FFFFFF81 7A
   FFFFFF82 11 09 03 FFFFFF82 12 11 02 10 53 65 71 75 65 6E 63
   65 54 65 6D 70 6C 61 74 65 28 03 00 FFFFFF82 14 10 04
   FFFFFF82 15 FFFFFF82 18 0D 02 FFFFFF82 16 0A 03 FFFFFF82 17 02 01 0A 61
   6E 6E 6F 74 61 74 69 6F 6E 09 04 FFFFFF82 19 FFFFFF82 16 02
   0C 65 78 70 65 72 69 6D 65 6E 74 61 6C 07 06 FFFFFF82
   1B 02 FFFFFF88 02 5F 01 0C 47 65 6E 65 72 69 63 52 61
   6E 67 65 
  InnerClass: 
   public #1099= #1098 of #142; //Ops=class scala/Numeric$Ops of class scala/Numeric
   public #1099= #148 of #136; //Ops=class scala/Ordering$Ops of class scala/Ordering
   public #1102= #446 of #1101; //Catch=class scala/util/control/Exception$Catch of class scala/util/control/Exception
   public #1103= #247 of #241; //IntegralOps=class scala/Integral$IntegralOps of class scala/Integral
   public #1106= #1105 of #27; //Inclusive=class scala/GenericRange$Inclusive of class scala/GenericRange
   public #1109= #1108 of #27; //Exclusive=class scala/GenericRange$Exclusive of class scala/GenericRange
   public final #1110= #176 of #27; //$anonfun$1=class scala/GenericRange$$anonfun$1 of class scala/GenericRange
   public abstract #1113= #1112 of #282; //Transformed=class scala/collection/generic/VectorViewTemplate$Transformed of class scala/collection/generic/VectorViewTemplate
   public final #1114= #441 of #27; //$anonfun$contains$1=class scala/GenericRange$$anonfun$contains$1 of class scala/GenericRange
   public abstract #1113= #1116 of #1118; //Transformed=class scala/collection/generic/IterableViewTemplate$Transformed of class scala/collection/generic/IterableViewTemplate
   public final #1119= #452 of #27; //$anonfun$contains$2=class scala/GenericRange$$anonfun$contains$2 of class scala/GenericRange
   public abstract #1113= #1121 of #342; //Transformed=class scala/collection/generic/SequenceViewTemplate$Transformed of class scala/collection/generic/SequenceViewTemplate
   public abstract #1113= #1123 of #352; //Transformed=class scala/collection/generic/TraversableViewTemplate$Transformed of class scala/collection/generic/TraversableViewTemplate
  minor version: 0
  major version: 49
  Constant pool:
const #1 = Asciz	SourceFile;
const #2 = Asciz	Range.scala;
const #3 = Asciz	bitmap$0;
const #4 = Asciz	I;
const #5 = Asciz	hashValues;
const #6 = Asciz	Lscala/collection/immutable/List;;
const #7 = Asciz	Lscala/collection/immutable/List<TT;>;;
const #8 = Asciz	Signature;
const #9 = Asciz	length;
const #10 = Asciz	genericLength;
const #11 = Asciz	Ljava/lang/Object;;
const #12 = Asciz	TT;;
const #13 = Asciz	trueEnd;
const #14 = Asciz	num;
const #15 = Asciz	Lscala/Integral;;
const #16 = Asciz	Lscala/Integral<TT;>;;
const #17 = Asciz	isInclusive;
const #18 = Asciz	Z;
const #19 = Asciz	step;
const #20 = Asciz	end;
const #21 = Asciz	start;
const #22 = Asciz	<init>;
const #23 = Asciz	(Ljava/lang/Object;Ljava/lang/Object;Ljava/lang/Object;ZLscala/Integral;)V;
const #24 = Asciz	Code;
const #25 = Asciz	LineNumberTable;
const #26 = Asciz	scala/GenericRange;
const #27 = class	#26;	//  scala/GenericRange
const #28 = NameAndType	#21:#11;//  start:Ljava/lang/Object;
const #29 = Field	#27.#28;	//  scala/GenericRange.start:Ljava/lang/Object;
const #30 = NameAndType	#20:#11;//  end:Ljava/lang/Object;
const #31 = Field	#27.#30;	//  scala/GenericRange.end:Ljava/lang/Object;
const #32 = NameAndType	#19:#11;//  step:Ljava/lang/Object;
const #33 = Field	#27.#32;	//  scala/GenericRange.step:Ljava/lang/Object;
const #34 = NameAndType	#17:#18;//  isInclusive:Z
const #35 = Field	#27.#34;	//  scala/GenericRange.isInclusive:Z
const #36 = NameAndType	#14:#15;//  num:Lscala/Integral;
const #37 = Field	#27.#36;	//  scala/GenericRange.num:Lscala/Integral;
const #38 = Asciz	java/lang/Object;
const #39 = class	#38;	//  java/lang/Object
const #40 = Asciz	()V;
const #41 = NameAndType	#22:#40;//  "<init>":()V
const #42 = Method	#39.#41;	//  java/lang/Object."<init>":()V
const #43 = Asciz	scala/Function1$class;
const #44 = class	#43;	//  scala/Function1$class
const #45 = Asciz	$init$;
const #46 = Asciz	(Lscala/Function1;)V;
const #47 = NameAndType	#45:#46;//  $init$:(Lscala/Function1;)V
const #48 = Method	#44.#47;	//  scala/Function1$class.$init$:(Lscala/Function1;)V
const #49 = Asciz	scala/PartialFunction$class;
const #50 = class	#49;	//  scala/PartialFunction$class
const #51 = Asciz	(Lscala/PartialFunction;)V;
const #52 = NameAndType	#45:#51;//  $init$:(Lscala/PartialFunction;)V
const #53 = Method	#50.#52;	//  scala/PartialFunction$class.$init$:(Lscala/PartialFunction;)V
const #54 = Asciz	scala/collection/generic/TraversableTemplate$class;
const #55 = class	#54;	//  scala/collection/generic/TraversableTemplate$class
const #56 = Asciz	(Lscala/collection/generic/TraversableTemplate;)V;
const #57 = NameAndType	#45:#56;//  $init$:(Lscala/collection/generic/TraversableTemplate;)V
const #58 = Method	#55.#57;	//  scala/collection/generic/TraversableTemplate$class.$init$:(Lscala/collection/generic/TraversableTemplate;)V
const #59 = Asciz	scala/collection/generic/TraversableClass$class;
const #60 = class	#59;	//  scala/collection/generic/TraversableClass$class
const #61 = Asciz	(Lscala/collection/generic/TraversableClass;)V;
const #62 = NameAndType	#45:#61;//  $init$:(Lscala/collection/generic/TraversableClass;)V
const #63 = Method	#60.#62;	//  scala/collection/generic/TraversableClass$class.$init$:(Lscala/collection/generic/TraversableClass;)V
const #64 = Asciz	scala/collection/Traversable$class;
const #65 = class	#64;	//  scala/collection/Traversable$class
const #66 = Asciz	(Lscala/collection/Traversable;)V;
const #67 = NameAndType	#45:#66;//  $init$:(Lscala/collection/Traversable;)V
const #68 = Method	#65.#67;	//  scala/collection/Traversable$class.$init$:(Lscala/collection/Traversable;)V
const #69 = Asciz	scala/collection/generic/IterableTemplate$class;
const #70 = class	#69;	//  scala/collection/generic/IterableTemplate$class
const #71 = Asciz	(Lscala/collection/generic/IterableTemplate;)V;
const #72 = NameAndType	#45:#71;//  $init$:(Lscala/collection/generic/IterableTemplate;)V
const #73 = Method	#70.#72;	//  scala/collection/generic/IterableTemplate$class.$init$:(Lscala/collection/generic/IterableTemplate;)V
const #74 = Asciz	scala/collection/Iterable$class;
const #75 = class	#74;	//  scala/collection/Iterable$class
const #76 = Asciz	(Lscala/collection/Iterable;)V;
const #77 = NameAndType	#45:#76;//  $init$:(Lscala/collection/Iterable;)V
const #78 = Method	#75.#77;	//  scala/collection/Iterable$class.$init$:(Lscala/collection/Iterable;)V
const #79 = Asciz	scala/collection/generic/SequenceTemplate$class;
const #80 = class	#79;	//  scala/collection/generic/SequenceTemplate$class
const #81 = Asciz	(Lscala/collection/generic/SequenceTemplate;)V;
const #82 = NameAndType	#45:#81;//  $init$:(Lscala/collection/generic/SequenceTemplate;)V
const #83 = Method	#80.#82;	//  scala/collection/generic/SequenceTemplate$class.$init$:(Lscala/collection/generic/SequenceTemplate;)V
const #84 = Asciz	scala/collection/Sequence$class;
const #85 = class	#84;	//  scala/collection/Sequence$class
const #86 = Asciz	(Lscala/collection/Sequence;)V;
const #87 = NameAndType	#45:#86;//  $init$:(Lscala/collection/Sequence;)V
const #88 = Method	#85.#87;	//  scala/collection/Sequence$class.$init$:(Lscala/collection/Sequence;)V
const #89 = Asciz	scala/collection/generic/VectorTemplate$class;
const #90 = class	#89;	//  scala/collection/generic/VectorTemplate$class
const #91 = Asciz	(Lscala/collection/generic/VectorTemplate;)V;
const #92 = NameAndType	#45:#91;//  $init$:(Lscala/collection/generic/VectorTemplate;)V
const #93 = Method	#90.#92;	//  scala/collection/generic/VectorTemplate$class.$init$:(Lscala/collection/generic/VectorTemplate;)V
const #94 = Asciz	scala/collection/Vector$class;
const #95 = class	#94;	//  scala/collection/Vector$class
const #96 = Asciz	(Lscala/collection/Vector;)V;
const #97 = NameAndType	#45:#96;//  $init$:(Lscala/collection/Vector;)V
const #98 = Method	#95.#97;	//  scala/collection/Vector$class.$init$:(Lscala/collection/Vector;)V
const #99 = Asciz	scala/collection/generic/TraversableViewTemplate$class;
const #100 = class	#99;	//  scala/collection/generic/TraversableViewTemplate$class
const #101 = Asciz	(Lscala/collection/generic/TraversableViewTemplate;)V;
const #102 = NameAndType	#45:#101;//  $init$:(Lscala/collection/generic/TraversableViewTemplate;)V
const #103 = Method	#100.#102;	//  scala/collection/generic/TraversableViewTemplate$class.$init$:(Lscala/collection/generic/TraversableViewTemplate;)V
const #104 = Asciz	scala/collection/generic/IterableViewTemplate$class;
const #105 = class	#104;	//  scala/collection/generic/IterableViewTemplate$class
const #106 = Asciz	(Lscala/collection/generic/IterableViewTemplate;)V;
const #107 = NameAndType	#45:#106;//  $init$:(Lscala/collection/generic/IterableViewTemplate;)V
const #108 = Method	#105.#107;	//  scala/collection/generic/IterableViewTemplate$class.$init$:(Lscala/collection/generic/IterableViewTemplate;)V
const #109 = Asciz	scala/collection/generic/SequenceViewTemplate$class;
const #110 = class	#109;	//  scala/collection/generic/SequenceViewTemplate$class
const #111 = Asciz	(Lscala/collection/generic/SequenceViewTemplate;)V;
const #112 = NameAndType	#45:#111;//  $init$:(Lscala/collection/generic/SequenceViewTemplate;)V
const #113 = Method	#110.#112;	//  scala/collection/generic/SequenceViewTemplate$class.$init$:(Lscala/collection/generic/SequenceViewTemplate;)V
const #114 = Asciz	scala/collection/generic/VectorViewTemplate$class;
const #115 = class	#114;	//  scala/collection/generic/VectorViewTemplate$class
const #116 = Asciz	(Lscala/collection/generic/VectorViewTemplate;)V;
const #117 = NameAndType	#45:#116;//  $init$:(Lscala/collection/generic/VectorViewTemplate;)V
const #118 = Method	#115.#117;	//  scala/collection/generic/VectorViewTemplate$class.$init$:(Lscala/collection/generic/VectorViewTemplate;)V
const #119 = Asciz	scala/RangeToString$class;
const #120 = class	#119;	//  scala/RangeToString$class
const #121 = Asciz	(Lscala/RangeToString;)V;
const #122 = NameAndType	#45:#121;//  $init$:(Lscala/RangeToString;)V
const #123 = Method	#120.#122;	//  scala/RangeToString$class.$init$:(Lscala/RangeToString;)V
const #124 = Asciz	scala/util/Hashable$class;
const #125 = class	#124;	//  scala/util/Hashable$class
const #126 = Asciz	(Lscala/util/Hashable;)V;
const #127 = NameAndType	#45:#126;//  $init$:(Lscala/util/Hashable;)V
const #128 = Method	#125.#127;	//  scala/util/Hashable$class.$init$:(Lscala/util/Hashable;)V
const #129 = Asciz	scala/Predef$;
const #130 = class	#129;	//  scala/Predef$
const #131 = Asciz	MODULE$;
const #132 = Asciz	Lscala/Predef$;;
const #133 = NameAndType	#131:#132;//  MODULE$:Lscala/Predef$;
const #134 = Field	#130.#133;	//  scala/Predef$.MODULE$:Lscala/Predef$;
const #135 = Asciz	scala/Ordering;
const #136 = class	#135;	//  scala/Ordering
const #137 = Asciz	mkOrderingOps;
const #138 = Asciz	(Ljava/lang/Object;)Lscala/Ordering$Ops;;
const #139 = NameAndType	#137:#138;//  mkOrderingOps:(Ljava/lang/Object;)Lscala/Ordering$Ops;
const #140 = InterfaceMethod	#136.#139;	//  scala/Ordering.mkOrderingOps:(Ljava/lang/Object;)Lscala/Ordering$Ops;
const #141 = Asciz	scala/Numeric;
const #142 = class	#141;	//  scala/Numeric
const #143 = Asciz	zero;
const #144 = Asciz	()Ljava/lang/Object;;
const #145 = NameAndType	#143:#144;//  zero:()Ljava/lang/Object;
const #146 = InterfaceMethod	#142.#145;	//  scala/Numeric.zero:()Ljava/lang/Object;
const #147 = Asciz	scala/Ordering$Ops;
const #148 = class	#147;	//  scala/Ordering$Ops
const #149 = Asciz	equiv;
const #150 = Asciz	(Ljava/lang/Object;)Z;
const #151 = NameAndType	#149:#150;//  equiv:(Ljava/lang/Object;)Z
const #152 = Method	#148.#151;	//  scala/Ordering$Ops.equiv:(Ljava/lang/Object;)Z
const #153 = Asciz	require;
const #154 = Asciz	(Z)V;
const #155 = NameAndType	#153:#154;//  require:(Z)V
const #156 = Method	#130.#155;	//  scala/Predef$.require:(Z)V
const #157 = NameAndType	#10:#144;//  genericLength:()Ljava/lang/Object;
const #158 = Method	#27.#157;	//  scala/GenericRange.genericLength:()Ljava/lang/Object;
const #159 = Asciz	scala/Math$;
const #160 = class	#159;	//  scala/Math$
const #161 = Asciz	Lscala/Math$;;
const #162 = NameAndType	#131:#161;//  MODULE$:Lscala/Math$;
const #163 = Field	#160.#162;	//  scala/Math$.MODULE$:Lscala/Math$;
const #164 = Asciz	MAX_INT;
const #165 = Asciz	()I;
const #166 = NameAndType	#164:#165;//  MAX_INT:()I
const #167 = Method	#160.#166;	//  scala/Math$.MAX_INT:()I
const #168 = Asciz	fromInt;
const #169 = Asciz	(I)Ljava/lang/Object;;
const #170 = NameAndType	#168:#169;//  fromInt:(I)Ljava/lang/Object;
const #171 = InterfaceMethod	#142.#170;	//  scala/Numeric.fromInt:(I)Ljava/lang/Object;
const #172 = Asciz	$less$eq;
const #173 = NameAndType	#172:#150;//  $less$eq:(Ljava/lang/Object;)Z
const #174 = Method	#148.#173;	//  scala/Ordering$Ops.$less$eq:(Ljava/lang/Object;)Z
const #175 = Asciz	scala/GenericRange$$anonfun$1;
const #176 = class	#175;	//  scala/GenericRange$$anonfun$1
const #177 = Asciz	(Lscala/GenericRange;)V;
const #178 = NameAndType	#22:#177;//  "<init>":(Lscala/GenericRange;)V
const #179 = Method	#176.#178;	//  scala/GenericRange$$anonfun$1."<init>":(Lscala/GenericRange;)V
const #180 = Asciz	(ZLscala/Function0;)V;
const #181 = NameAndType	#153:#180;//  require:(ZLscala/Function0;)V
const #182 = Method	#130.#181;	//  scala/Predef$.require:(ZLscala/Function0;)V
const #183 = Asciz	scala/collection/immutable/List$;
const #184 = class	#183;	//  scala/collection/immutable/List$
const #185 = Asciz	Lscala/collection/immutable/List$;;
const #186 = NameAndType	#131:#185;//  MODULE$:Lscala/collection/immutable/List$;
const #187 = Field	#184.#186;	//  scala/collection/immutable/List$.MODULE$:Lscala/collection/immutable/List$;
const #188 = Asciz	scala/runtime/ScalaRunTime$;
const #189 = class	#188;	//  scala/runtime/ScalaRunTime$
const #190 = Asciz	Lscala/runtime/ScalaRunTime$;;
const #191 = NameAndType	#131:#190;//  MODULE$:Lscala/runtime/ScalaRunTime$;
const #192 = Field	#189.#191;	//  scala/runtime/ScalaRunTime$.MODULE$:Lscala/runtime/ScalaRunTime$;
const #193 = NameAndType	#13:#144;//  trueEnd:()Ljava/lang/Object;
const #194 = Method	#27.#193;	//  scala/GenericRange.trueEnd:()Ljava/lang/Object;
const #195 = Asciz	boxArray;
const #196 = Asciz	(Ljava/lang/Object;)Lscala/runtime/BoxedArray;;
const #197 = NameAndType	#195:#196;//  boxArray:(Ljava/lang/Object;)Lscala/runtime/BoxedArray;
const #198 = Method	#189.#197;	//  scala/runtime/ScalaRunTime$.boxArray:(Ljava/lang/Object;)Lscala/runtime/BoxedArray;
const #199 = Asciz	apply;
const #200 = Asciz	(Lscala/collection/Sequence;)Lscala/collection/immutable/List;;
const #201 = NameAndType	#199:#200;//  apply:(Lscala/collection/Sequence;)Lscala/collection/immutable/List;
const #202 = Method	#184.#201;	//  scala/collection/immutable/List$.apply:(Lscala/collection/Sequence;)Lscala/collection/immutable/List;
const #203 = NameAndType	#5:#6;//  hashValues:Lscala/collection/immutable/List;
const #204 = Field	#27.#203;	//  scala/GenericRange.hashValues:Lscala/collection/immutable/List;
const #205 = Asciz	this;
const #206 = Asciz	Lscala/GenericRange;;
const #207 = Asciz	LocalVariableTable;
const #208 = Asciz	(TT;TT;TT;ZLscala/Integral<TT;>;)V;
const #209 = Asciz	doContains$1;
const #210 = Asciz	java/lang/Integer;
const #211 = class	#210;	//  java/lang/Integer
const #212 = Asciz	scala/runtime/BoxesRunTime;
const #213 = class	#212;	//  scala/runtime/BoxesRunTime
const #214 = Asciz	unboxToInt;
const #215 = Asciz	(Ljava/lang/Object;)I;
const #216 = NameAndType	#214:#215;//  unboxToInt:(Ljava/lang/Object;)I
const #217 = Method	#213.#216;	//  scala/runtime/BoxesRunTime.unboxToInt:(Ljava/lang/Object;)I
const #218 = Asciz	withinRange$1;
const #219 = NameAndType	#218:#150;//  withinRange$1:(Ljava/lang/Object;)Z
const #220 = Method	#27.#219;	//  scala/GenericRange.withinRange$1:(Ljava/lang/Object;)Z
const #221 = Asciz	matchesStep$1;
const #222 = NameAndType	#221:#150;//  matchesStep$1:(Ljava/lang/Object;)Z
const #223 = Method	#27.#222;	//  scala/GenericRange.matchesStep$1:(Ljava/lang/Object;)Z
const #224 = Asciz	x$1;
const #225 = Asciz	temp1;
const #226 = Asciz	temp2;
const #227 = NameAndType	#19:#144;//  step:()Ljava/lang/Object;
const #228 = Method	#27.#227;	//  scala/GenericRange.step:()Ljava/lang/Object;
const #229 = Asciz	$greater;
const #230 = NameAndType	#229:#150;//  $greater:(Ljava/lang/Object;)Z
const #231 = Method	#148.#230;	//  scala/Ordering$Ops.$greater:(Ljava/lang/Object;)Z
const #232 = NameAndType	#21:#144;//  start:()Ljava/lang/Object;
const #233 = Method	#27.#232;	//  scala/GenericRange.start:()Ljava/lang/Object;
const #234 = Asciz	$less;
const #235 = NameAndType	#234:#150;//  $less:(Ljava/lang/Object;)Z
const #236 = Method	#148.#235;	//  scala/Ordering$Ops.$less:(Ljava/lang/Object;)Z
const #237 = Asciz	$greater$eq;
const #238 = NameAndType	#237:#150;//  $greater$eq:(Ljava/lang/Object;)Z
const #239 = Method	#148.#238;	//  scala/Ordering$Ops.$greater$eq:(Ljava/lang/Object;)Z
const #240 = Asciz	scala/Integral;
const #241 = class	#240;	//  scala/Integral
const #242 = Asciz	mkNumericOps;
const #243 = Asciz	(Ljava/lang/Object;)Lscala/Integral$IntegralOps;;
const #244 = NameAndType	#242:#243;//  mkNumericOps:(Ljava/lang/Object;)Lscala/Integral$IntegralOps;
const #245 = InterfaceMethod	#241.#244;	//  scala/Integral.mkNumericOps:(Ljava/lang/Object;)Lscala/Integral$IntegralOps;
const #246 = Asciz	scala/Integral$IntegralOps;
const #247 = class	#246;	//  scala/Integral$IntegralOps
const #248 = Asciz	$minus;
const #249 = Asciz	(Ljava/lang/Object;)Ljava/lang/Object;;
const #250 = NameAndType	#248:#249;//  $minus:(Ljava/lang/Object;)Ljava/lang/Object;
const #251 = Method	#247.#250;	//  scala/Integral$IntegralOps.$minus:(Ljava/lang/Object;)Ljava/lang/Object;
const #252 = Asciz	$percent;
const #253 = NameAndType	#252:#249;//  $percent:(Ljava/lang/Object;)Ljava/lang/Object;
const #254 = Method	#247.#253;	//  scala/Integral$IntegralOps.$percent:(Ljava/lang/Object;)Ljava/lang/Object;
const #255 = Asciz	equals;
const #256 = Asciz	(Ljava/lang/Object;Ljava/lang/Object;)Z;
const #257 = NameAndType	#255:#256;//  equals:(Ljava/lang/Object;Ljava/lang/Object;)Z
const #258 = Method	#213.#257;	//  scala/runtime/BoxesRunTime.equals:(Ljava/lang/Object;Ljava/lang/Object;)Z
const #259 = Asciz	plen$1;
const #260 = Asciz	(Ljava/lang/Object;Ljava/lang/Object;Ljava/lang/Object;)Ljava/lang/Object;;
const #261 = Asciz	$div;
const #262 = NameAndType	#261:#249;//  $div:(Ljava/lang/Object;)Ljava/lang/Object;
const #263 = Method	#247.#262;	//  scala/Integral$IntegralOps.$div:(Ljava/lang/Object;)Ljava/lang/Object;
const #264 = Asciz	s;
const #265 = Asciz	e;
const #266 = Asciz	stp;
const #267 = Asciz	underlying;
const #268 = Asciz	()Lscala/collection/Traversable;;
const #269 = Asciz	()Lscala/collection/immutable/Vector;;
const #270 = NameAndType	#267:#269;//  underlying:()Lscala/collection/immutable/Vector;
const #271 = Method	#27.#270;	//  scala/GenericRange.underlying:()Lscala/collection/immutable/Vector;
const #272 = NameAndType	#199:#169;//  apply:(I)Ljava/lang/Object;
const #273 = Method	#27.#272;	//  scala/GenericRange.apply:(I)Ljava/lang/Object;
const #274 = Asciz	v1;
const #275 = Asciz	()Lscala/collection/Sequence;;
const #276 = Asciz	()Lscala/collection/immutable/List;;
const #277 = NameAndType	#5:#276;//  hashValues:()Lscala/collection/immutable/List;
const #278 = Method	#27.#277;	//  scala/GenericRange.hashValues:()Lscala/collection/immutable/List;
const #279 = Asciz	newAppended;
const #280 = Asciz	(Lscala/collection/Traversable;)Lscala/collection/generic/SequenceViewTemplate$Transformed;;
const #281 = Asciz	scala/collection/generic/VectorViewTemplate;
const #282 = class	#281;	//  scala/collection/generic/VectorViewTemplate
const #283 = Asciz	(Lscala/collection/Traversable;)Lscala/collection/generic/VectorViewTemplate$Transformed;;
const #284 = NameAndType	#279:#283;//  newAppended:(Lscala/collection/Traversable;)Lscala/collection/generic/VectorViewTemplate$Transformed;
const #285 = InterfaceMethod	#282.#284;	//  scala/collection/generic/VectorViewTemplate.newAppended:(Lscala/collection/Traversable;)Lscala/collection/generic/VectorViewTemplate$Transformed;
const #286 = Asciz	that;
const #287 = Asciz	Lscala/collection/Traversable;;
const #288 = Asciz	(Lscala/collection/Traversable;)Lscala/collection/generic/IterableViewTemplate$Transformed;;
const #289 = Asciz	(Lscala/collection/Traversable;)Lscala/collection/generic/TraversableViewTemplate$Transformed;;
const #290 = Asciz	newMapped;
const #291 = Asciz	(Lscala/Function1;)Lscala/collection/generic/SequenceViewTemplate$Transformed;;
const #292 = Asciz	(Lscala/Function1;)Lscala/collection/generic/VectorViewTemplate$Transformed;;
const #293 = NameAndType	#290:#292;//  newMapped:(Lscala/Function1;)Lscala/collection/generic/VectorViewTemplate$Transformed;
const #294 = InterfaceMethod	#282.#293;	//  scala/collection/generic/VectorViewTemplate.newMapped:(Lscala/Function1;)Lscala/collection/generic/VectorViewTemplate$Transformed;
const #295 = Asciz	f;
const #296 = Asciz	Lscala/Function1;;
const #297 = Asciz	(Lscala/Function1;)Lscala/collection/generic/IterableViewTemplate$Transformed;;
const #298 = Asciz	(Lscala/Function1;)Lscala/collection/generic/TraversableViewTemplate$Transformed;;
const #299 = Asciz	newFlatMapped;
const #300 = NameAndType	#299:#292;//  newFlatMapped:(Lscala/Function1;)Lscala/collection/generic/VectorViewTemplate$Transformed;
const #301 = InterfaceMethod	#282.#300;	//  scala/collection/generic/VectorViewTemplate.newFlatMapped:(Lscala/Function1;)Lscala/collection/generic/VectorViewTemplate$Transformed;
const #302 = Asciz	newFiltered;
const #303 = NameAndType	#302:#292;//  newFiltered:(Lscala/Function1;)Lscala/collection/generic/VectorViewTemplate$Transformed;
const #304 = InterfaceMethod	#282.#303;	//  scala/collection/generic/VectorViewTemplate.newFiltered:(Lscala/Function1;)Lscala/collection/generic/VectorViewTemplate$Transformed;
const #305 = Asciz	p;
const #306 = Asciz	newSliced;
const #307 = Asciz	(II)Lscala/collection/generic/SequenceViewTemplate$Transformed;;
const #308 = Asciz	(II)Lscala/collection/generic/VectorViewTemplate$Transformed;;
const #309 = NameAndType	#306:#308;//  newSliced:(II)Lscala/collection/generic/VectorViewTemplate$Transformed;
const #310 = InterfaceMethod	#282.#309;	//  scala/collection/generic/VectorViewTemplate.newSliced:(II)Lscala/collection/generic/VectorViewTemplate$Transformed;
const #311 = Asciz	_from;
const #312 = Asciz	_until;
const #313 = Asciz	(II)Lscala/collection/generic/IterableViewTemplate$Transformed;;
const #314 = Asciz	(II)Lscala/collection/generic/TraversableViewTemplate$Transformed;;
const #315 = Asciz	newDroppedWhile;
const #316 = NameAndType	#315:#292;//  newDroppedWhile:(Lscala/Function1;)Lscala/collection/generic/VectorViewTemplate$Transformed;
const #317 = InterfaceMethod	#282.#316;	//  scala/collection/generic/VectorViewTemplate.newDroppedWhile:(Lscala/Function1;)Lscala/collection/generic/VectorViewTemplate$Transformed;
const #318 = Asciz	newTakenWhile;
const #319 = NameAndType	#318:#292;//  newTakenWhile:(Lscala/Function1;)Lscala/collection/generic/VectorViewTemplate$Transformed;
const #320 = InterfaceMethod	#282.#319;	//  scala/collection/generic/VectorViewTemplate.newTakenWhile:(Lscala/Function1;)Lscala/collection/generic/VectorViewTemplate$Transformed;
const #321 = Asciz	newReversed;
const #322 = Asciz	()Lscala/collection/generic/SequenceViewTemplate$Transformed;;
const #323 = Asciz	()Lscala/collection/generic/VectorViewTemplate$Transformed;;
const #324 = NameAndType	#321:#323;//  newReversed:()Lscala/collection/generic/VectorViewTemplate$Transformed;
const #325 = InterfaceMethod	#282.#324;	//  scala/collection/generic/VectorViewTemplate.newReversed:()Lscala/collection/generic/VectorViewTemplate$Transformed;
const #326 = Asciz	newPatched;
const #327 = Asciz	(ILscala/collection/Sequence;I)Lscala/collection/generic/SequenceViewTemplate$Transformed;;
const #328 = Asciz	(ILscala/collection/Sequence;I)Lscala/collection/generic/VectorViewTemplate$Transformed;;
const #329 = NameAndType	#326:#328;//  newPatched:(ILscala/collection/Sequence;I)Lscala/collection/generic/VectorViewTemplate$Transformed;
const #330 = InterfaceMethod	#282.#329;	//  scala/collection/generic/VectorViewTemplate.newPatched:(ILscala/collection/Sequence;I)Lscala/collection/generic/VectorViewTemplate$Transformed;
const #331 = Asciz	_patch;
const #332 = Asciz	Lscala/collection/Sequence;;
const #333 = Asciz	_replaced;
const #334 = Asciz	newZipped;
const #335 = Asciz	(Lscala/collection/Sequence;)Lscala/collection/generic/SequenceViewTemplate$Transformed;;
const #336 = Asciz	(Lscala/collection/Sequence;)Lscala/collection/generic/VectorViewTemplate$Transformed;;
const #337 = NameAndType	#334:#336;//  newZipped:(Lscala/collection/Sequence;)Lscala/collection/generic/VectorViewTemplate$Transformed;
const #338 = InterfaceMethod	#282.#337;	//  scala/collection/generic/VectorViewTemplate.newZipped:(Lscala/collection/Sequence;)Lscala/collection/generic/VectorViewTemplate$Transformed;
const #339 = Asciz	reverse;
const #340 = Asciz	()Lscala/collection/generic/VectorTemplate;;
const #341 = Asciz	scala/collection/generic/SequenceViewTemplate;
const #342 = class	#341;	//  scala/collection/generic/SequenceViewTemplate
const #343 = Asciz	()Lscala/collection/generic/SequenceView;;
const #344 = NameAndType	#339:#343;//  reverse:()Lscala/collection/generic/SequenceView;
const #345 = InterfaceMethod	#342.#344;	//  scala/collection/generic/SequenceViewTemplate.reverse:()Lscala/collection/generic/SequenceView;
const #346 = Asciz	scala/collection/generic/VectorTemplate;
const #347 = class	#346;	//  scala/collection/generic/VectorTemplate
const #348 = Asciz	()Lscala/collection/generic/IterableTemplate;;
const #349 = Asciz	filter;
const #350 = Asciz	(Lscala/Function1;)Lscala/collection/generic/TraversableTemplate;;
const #351 = Asciz	scala/collection/generic/TraversableViewTemplate;
const #352 = class	#351;	//  scala/collection/generic/TraversableViewTemplate
const #353 = Asciz	(Lscala/Function1;)Lscala/collection/generic/TraversableView;;
const #354 = NameAndType	#349:#353;//  filter:(Lscala/Function1;)Lscala/collection/generic/TraversableView;
const #355 = InterfaceMethod	#352.#354;	//  scala/collection/generic/TraversableViewTemplate.filter:(Lscala/Function1;)Lscala/collection/generic/TraversableView;
const #356 = Asciz	init;
const #357 = Asciz	()Lscala/collection/generic/TraversableView;;
const #358 = NameAndType	#356:#357;//  init:()Lscala/collection/generic/TraversableView;
const #359 = InterfaceMethod	#352.#358;	//  scala/collection/generic/TraversableViewTemplate.init:()Lscala/collection/generic/TraversableView;
const #360 = Asciz	()Lscala/collection/generic/TraversableTemplate;;
const #361 = Asciz	drop;
const #362 = Asciz	(I)Lscala/collection/generic/VectorTemplate;;
const #363 = Asciz	(I)Lscala/collection/generic/TraversableView;;
const #364 = NameAndType	#361:#363;//  drop:(I)Lscala/collection/generic/TraversableView;
const #365 = InterfaceMethod	#352.#364;	//  scala/collection/generic/TraversableViewTemplate.drop:(I)Lscala/collection/generic/TraversableView;
const #366 = Asciz	n;
const #367 = Asciz	(I)Lscala/collection/generic/TraversableTemplate;;
const #368 = Asciz	take;
const #369 = NameAndType	#368:#363;//  take:(I)Lscala/collection/generic/TraversableView;
const #370 = InterfaceMethod	#352.#369;	//  scala/collection/generic/TraversableViewTemplate.take:(I)Lscala/collection/generic/TraversableView;
const #371 = Asciz	slice;
const #372 = Asciz	(II)Lscala/collection/generic/VectorTemplate;;
const #373 = Asciz	(II)Lscala/collection/generic/TraversableView;;
const #374 = NameAndType	#371:#373;//  slice:(II)Lscala/collection/generic/TraversableView;
const #375 = InterfaceMethod	#352.#374;	//  scala/collection/generic/TraversableViewTemplate.slice:(II)Lscala/collection/generic/TraversableView;
const #376 = Asciz	from;
const #377 = Asciz	until;
const #378 = Asciz	(II)Lscala/collection/generic/TraversableTemplate;;
const #379 = Asciz	dropWhile;
const #380 = Asciz	(Lscala/Function1;)Lscala/collection/generic/VectorTemplate;;
const #381 = NameAndType	#379:#353;//  dropWhile:(Lscala/Function1;)Lscala/collection/generic/TraversableView;
const #382 = InterfaceMethod	#352.#381;	//  scala/collection/generic/TraversableViewTemplate.dropWhile:(Lscala/Function1;)Lscala/collection/generic/TraversableView;
const #383 = Asciz	takeWhile;
const #384 = NameAndType	#383:#353;//  takeWhile:(Lscala/Function1;)Lscala/collection/generic/TraversableView;
const #385 = InterfaceMethod	#352.#384;	//  scala/collection/generic/TraversableViewTemplate.takeWhile:(Lscala/Function1;)Lscala/collection/generic/TraversableView;
const #386 = Asciz	tail;
const #387 = NameAndType	#386:#340;//  tail:()Lscala/collection/generic/VectorTemplate;
const #388 = InterfaceMethod	#347.#387;	//  scala/collection/generic/VectorTemplate.tail:()Lscala/collection/generic/VectorTemplate;
const #389 = Asciz	takeRight;
const #390 = Asciz	(I)Lscala/collection/generic/IterableTemplate;;
const #391 = NameAndType	#389:#362;//  takeRight:(I)Lscala/collection/generic/VectorTemplate;
const #392 = InterfaceMethod	#347.#391;	//  scala/collection/generic/VectorTemplate.takeRight:(I)Lscala/collection/generic/VectorTemplate;
const #393 = Asciz	dropRight;
const #394 = NameAndType	#393:#362;//  dropRight:(I)Lscala/collection/generic/VectorTemplate;
const #395 = InterfaceMethod	#347.#394;	//  scala/collection/generic/VectorTemplate.dropRight:(I)Lscala/collection/generic/VectorTemplate;
const #396 = Asciz	view;
const #397 = Asciz	(II)Lscala/collection/generic/SequenceView;;
const #398 = Asciz	(II)Lscala/collection/generic/VectorView;;
const #399 = NameAndType	#396:#398;//  view:(II)Lscala/collection/generic/VectorView;
const #400 = InterfaceMethod	#347.#399;	//  scala/collection/generic/VectorTemplate.view:(II)Lscala/collection/generic/VectorView;
const #401 = Asciz	(II)Lscala/collection/generic/IterableView;;
const #402 = Asciz	isDefinedAt;
const #403 = Asciz	scala/collection/generic/SequenceTemplate;
const #404 = class	#403;	//  scala/collection/generic/SequenceTemplate
const #405 = Asciz	(I)Z;
const #406 = NameAndType	#402:#405;//  isDefinedAt:(I)Z
const #407 = InterfaceMethod	#404.#406;	//  scala/collection/generic/SequenceTemplate.isDefinedAt:(I)Z
const #408 = Asciz	x;
const #409 = Asciz	andThen;
const #410 = Asciz	(Lscala/Function1;)Lscala/Function1;;
const #411 = Asciz	scala/PartialFunction;
const #412 = class	#411;	//  scala/PartialFunction
const #413 = Asciz	(Lscala/Function1;)Lscala/PartialFunction;;
const #414 = NameAndType	#409:#413;//  andThen:(Lscala/Function1;)Lscala/PartialFunction;
const #415 = InterfaceMethod	#412.#414;	//  scala/PartialFunction.andThen:(Lscala/Function1;)Lscala/PartialFunction;
const #416 = Asciz	g;
const #417 = Asciz	scala/util/Hashable;
const #418 = class	#417;	//  scala/util/Hashable
const #419 = Asciz	equalHashValues;
const #420 = NameAndType	#419:#150;//  equalHashValues:(Ljava/lang/Object;)Z
const #421 = InterfaceMethod	#418.#420;	//  scala/util/Hashable.equalHashValues:(Ljava/lang/Object;)Z
const #422 = Asciz	other;
const #423 = Asciz	temp3;
const #424 = Asciz	temp4;
const #425 = Asciz	()Lscala/collection/immutable/List<TT;>;;
const #426 = Asciz	contains;
const #427 = Asciz	scala/util/control/Exception$;
const #428 = class	#427;	//  scala/util/control/Exception$
const #429 = Asciz	Lscala/util/control/Exception$;;
const #430 = NameAndType	#131:#429;//  MODULE$:Lscala/util/control/Exception$;
const #431 = Field	#428.#430;	//  scala/util/control/Exception$.MODULE$:Lscala/util/control/Exception$;
const #432 = Asciz	java/lang/Class;
const #433 = class	#432;	//  java/lang/Class
const #434 = Asciz	java/lang/ClassCastException;
const #435 = class	#434;	//  java/lang/ClassCastException
const #436 = Asciz	catching;
const #437 = Asciz	(Lscala/collection/Sequence;)Lscala/util/control/Exception$Catch;;
const #438 = NameAndType	#436:#437;//  catching:(Lscala/collection/Sequence;)Lscala/util/control/Exception$Catch;
const #439 = Method	#428.#438;	//  scala/util/control/Exception$.catching:(Lscala/collection/Sequence;)Lscala/util/control/Exception$Catch;
const #440 = Asciz	scala/GenericRange$$anonfun$contains$1;
const #441 = class	#440;	//  scala/GenericRange$$anonfun$contains$1
const #442 = Asciz	(Lscala/GenericRange;Ljava/lang/Object;)V;
const #443 = NameAndType	#22:#442;//  "<init>":(Lscala/GenericRange;Ljava/lang/Object;)V
const #444 = Method	#441.#443;	//  scala/GenericRange$$anonfun$contains$1."<init>":(Lscala/GenericRange;Ljava/lang/Object;)V
const #445 = Asciz	scala/util/control/Exception$Catch;
const #446 = class	#445;	//  scala/util/control/Exception$Catch
const #447 = Asciz	opt;
const #448 = Asciz	(Lscala/Function0;)Lscala/Option;;
const #449 = NameAndType	#447:#448;//  opt:(Lscala/Function0;)Lscala/Option;
const #450 = Method	#446.#449;	//  scala/util/control/Exception$Catch.opt:(Lscala/Function0;)Lscala/Option;
const #451 = Asciz	scala/GenericRange$$anonfun$contains$2;
const #452 = class	#451;	//  scala/GenericRange$$anonfun$contains$2
const #453 = Method	#452.#443;	//  scala/GenericRange$$anonfun$contains$2."<init>":(Lscala/GenericRange;Ljava/lang/Object;)V
const #454 = Asciz	scala/Option;
const #455 = class	#454;	//  scala/Option
const #456 = Asciz	getOrElse;
const #457 = Asciz	(Lscala/Function0;)Ljava/lang/Object;;
const #458 = NameAndType	#456:#457;//  getOrElse:(Lscala/Function0;)Ljava/lang/Object;
const #459 = Method	#455.#458;	//  scala/Option.getOrElse:(Lscala/Function0;)Ljava/lang/Object;
const #460 = Asciz	unboxToBoolean;
const #461 = NameAndType	#460:#150;//  unboxToBoolean:(Ljava/lang/Object;)Z
const #462 = Method	#213.#461;	//  scala/runtime/BoxesRunTime.unboxToBoolean:(Ljava/lang/Object;)Z
const #463 = Asciz	_x$1;
const #464 = Asciz	applyAt;
const #465 = Asciz	java/lang/IndexOutOfBoundsException;
const #466 = class	#465;	//  java/lang/IndexOutOfBoundsException
const #467 = Asciz	toString;
const #468 = Asciz	()Ljava/lang/String;;
const #469 = NameAndType	#467:#468;//  toString:()Ljava/lang/String;
const #470 = Method	#39.#469;	//  java/lang/Object.toString:()Ljava/lang/String;
const #471 = Asciz	(Ljava/lang/String;)V;
const #472 = NameAndType	#22:#471;//  "<init>":(Ljava/lang/String;)V
const #473 = Method	#466.#472;	//  java/lang/IndexOutOfBoundsException."<init>":(Ljava/lang/String;)V
const #474 = Asciz	$times;
const #475 = NameAndType	#474:#249;//  $times:(Ljava/lang/Object;)Ljava/lang/Object;
const #476 = Method	#247.#475;	//  scala/Integral$IntegralOps.$times:(Ljava/lang/Object;)Ljava/lang/Object;
const #477 = Asciz	$plus;
const #478 = NameAndType	#477:#249;//  $plus:(Ljava/lang/Object;)Ljava/lang/Object;
const #479 = Method	#247.#478;	//  scala/Integral$IntegralOps.$plus:(Ljava/lang/Object;)Ljava/lang/Object;
const #480 = Asciz	idx;
const #481 = Asciz	(TT;)TT;;
const #482 = NameAndType	#464:#249;//  applyAt:(Ljava/lang/Object;)Ljava/lang/Object;
const #483 = Method	#27.#482;	//  scala/GenericRange.applyAt:(Ljava/lang/Object;)Ljava/lang/Object;
const #484 = Asciz	(I)TT;;
const #485 = NameAndType	#3:#4;//  bitmap$0:I
const #486 = Field	#27.#485;	//  scala/GenericRange.bitmap$0:I
const #487 = int	16;
const #488 = Asciz	toInt;
const #489 = NameAndType	#488:#215;//  toInt:(Ljava/lang/Object;)I
const #490 = InterfaceMethod	#142.#489;	//  scala/Numeric.toInt:(Ljava/lang/Object;)I
const #491 = NameAndType	#9:#4;//  length:I
const #492 = Field	#27.#491;	//  scala/GenericRange.length:I
const #493 = Asciz	scala/runtime/BoxedUnit;
const #494 = class	#493;	//  scala/runtime/BoxedUnit
const #495 = Asciz	UNIT;
const #496 = Asciz	Lscala/runtime/BoxedUnit;;
const #497 = NameAndType	#495:#496;//  UNIT:Lscala/runtime/BoxedUnit;
const #498 = Field	#494.#497;	//  scala/runtime/BoxedUnit.UNIT:Lscala/runtime/BoxedUnit;
const #499 = NameAndType	#259:#260;//  plen$1:(Ljava/lang/Object;Ljava/lang/Object;Ljava/lang/Object;)Ljava/lang/Object;
const #500 = Method	#27.#499;	//  scala/GenericRange.plen$1:(Ljava/lang/Object;Ljava/lang/Object;Ljava/lang/Object;)Ljava/lang/Object;
const #501 = Asciz	unary_$minus;
const #502 = NameAndType	#501:#144;//  unary_$minus:()Ljava/lang/Object;
const #503 = Method	#247.#502;	//  scala/Integral$IntegralOps.unary_$minus:()Ljava/lang/Object;
const #504 = NameAndType	#10:#11;//  genericLength:Ljava/lang/Object;
const #505 = Field	#27.#504;	//  scala/GenericRange.genericLength:Ljava/lang/Object;
const #506 = Asciz	()TT;;
const #507 = Asciz	foreach;
const #508 = Asciz	scala/Function1;
const #509 = class	#508;	//  scala/Function1
const #510 = NameAndType	#199:#249;//  apply:(Ljava/lang/Object;)Ljava/lang/Object;
const #511 = InterfaceMethod	#509.#510;	//  scala/Function1.apply:(Ljava/lang/Object;)Ljava/lang/Object;
const #512 = Asciz	i;
const #513 = Asciz	<U:Ljava/lang/Object;>(Lscala/Function1<TT;TU;>;)V;
const #514 = Asciz	(Ljava/lang/Object;)Lscala/GenericRange;;
const #515 = NameAndType	#20:#144;//  end:()Ljava/lang/Object;
const #516 = Method	#27.#515;	//  scala/GenericRange.end:()Ljava/lang/Object;
const #517 = Asciz	copy;
const #518 = Asciz	(Ljava/lang/Object;Ljava/lang/Object;Ljava/lang/Object;)Lscala/GenericRange;;
const #519 = NameAndType	#517:#518;//  copy:(Ljava/lang/Object;Ljava/lang/Object;Ljava/lang/Object;)Lscala/GenericRange;
const #520 = Method	#27.#519;	//  scala/GenericRange.copy:(Ljava/lang/Object;Ljava/lang/Object;Ljava/lang/Object;)Lscala/GenericRange;
const #521 = Asciz	mult;
const #522 = Asciz	(TT;)Lscala/GenericRange<TT;>;;
const #523 = Asciz	shift;
const #524 = Asciz	negate;
const #525 = NameAndType	#524:#249;//  negate:(Ljava/lang/Object;)Ljava/lang/Object;
const #526 = InterfaceMethod	#142.#525;	//  scala/Numeric.negate:(Ljava/lang/Object;)Ljava/lang/Object;
const #527 = NameAndType	#477:#514;//  $plus:(Ljava/lang/Object;)Lscala/GenericRange;
const #528 = Method	#27.#527;	//  scala/GenericRange.$plus:(Ljava/lang/Object;)Lscala/GenericRange;
const #529 = Asciz	(TT;TT;TT;)Lscala/GenericRange<TT;>;;
const #530 = Asciz	by;
const #531 = Asciz	newStep;
const #532 = Asciz	scala/collection/immutable/Vector$;
const #533 = class	#532;	//  scala/collection/immutable/Vector$
const #534 = Asciz	Lscala/collection/immutable/Vector$;;
const #535 = NameAndType	#131:#534;//  MODULE$:Lscala/collection/immutable/Vector$;
const #536 = Field	#533.#535;	//  scala/collection/immutable/Vector$.MODULE$:Lscala/collection/immutable/Vector$;
const #537 = Asciz	empty;
const #538 = NameAndType	#537:#268;//  empty:()Lscala/collection/Traversable;
const #539 = Method	#533.#538;	//  scala/collection/immutable/Vector$.empty:()Lscala/collection/Traversable;
const #540 = Asciz	scala/collection/immutable/Vector;
const #541 = class	#540;	//  scala/collection/immutable/Vector
const #542 = Asciz	()Lscala/collection/immutable/Vector<TT;>;;
const #543 = Asciz	()Z;
const #544 = NameAndType	#17:#543;//  isInclusive:()Z
const #545 = Method	#27.#544;	//  scala/GenericRange.isInclusive:()Z
const #546 = NameAndType	#13:#11;//  trueEnd:Ljava/lang/Object;
const #547 = Field	#27.#546;	//  scala/GenericRange.trueEnd:Ljava/lang/Object;
const #548 = Asciz	scala$GenericRange$$super$contains;
const #549 = Asciz	(Lscala/collection/generic/SequenceTemplate;Ljava/lang/Object;)Z;
const #550 = NameAndType	#426:#549;//  contains:(Lscala/collection/generic/SequenceTemplate;Ljava/lang/Object;)Z
const #551 = Method	#80.#550;	//  scala/collection/generic/SequenceTemplate$class.contains:(Lscala/collection/generic/SequenceTemplate;Ljava/lang/Object;)Z
const #552 = Asciz	elem;
const #553 = Asciz	compose;
const #554 = Asciz	(Lscala/Function1;Lscala/Function1;)Lscala/Function1;;
const #555 = NameAndType	#553:#554;//  compose:(Lscala/Function1;Lscala/Function1;)Lscala/Function1;
const #556 = Method	#44.#555;	//  scala/Function1$class.compose:(Lscala/Function1;Lscala/Function1;)Lscala/Function1;
const #557 = Asciz	(Lscala/PartialFunction;Lscala/Function1;)Lscala/PartialFunction;;
const #558 = NameAndType	#409:#557;//  andThen:(Lscala/PartialFunction;Lscala/Function1;)Lscala/PartialFunction;
const #559 = Method	#50.#558;	//  scala/PartialFunction$class.andThen:(Lscala/PartialFunction;Lscala/Function1;)Lscala/PartialFunction;
const #560 = Asciz	k;
const #561 = Asciz	orElse;
const #562 = Asciz	(Lscala/PartialFunction;)Lscala/PartialFunction;;
const #563 = Asciz	(Lscala/PartialFunction;Lscala/PartialFunction;)Lscala/PartialFunction;;
const #564 = NameAndType	#561:#563;//  orElse:(Lscala/PartialFunction;Lscala/PartialFunction;)Lscala/PartialFunction;
const #565 = Method	#50.#564;	//  scala/PartialFunction$class.orElse:(Lscala/PartialFunction;Lscala/PartialFunction;)Lscala/PartialFunction;
const #566 = Asciz	Lscala/PartialFunction;;
const #567 = Asciz	stringPrefix;
const #568 = Asciz	(Lscala/collection/generic/TraversableTemplate;)Ljava/lang/String;;
const #569 = NameAndType	#567:#568;//  stringPrefix:(Lscala/collection/generic/TraversableTemplate;)Ljava/lang/String;
const #570 = Method	#55.#569;	//  scala/collection/generic/TraversableTemplate$class.stringPrefix:(Lscala/collection/generic/TraversableTemplate;)Ljava/lang/String;
const #571 = Asciz	addString;
const #572 = Asciz	(Lscala/collection/mutable/StringBuilder;)Lscala/collection/mutable/StringBuilder;;
const #573 = Asciz	(Lscala/collection/generic/TraversableTemplate;Lscala/collection/mutable/StringBuilder;)Lscala/collection/mutable/StringBuilder;;
const #574 = NameAndType	#571:#573;//  addString:(Lscala/collection/generic/TraversableTemplate;Lscala/collection/mutable/StringBuilder;)Lscala/collection/mutable/StringBuilder;
const #575 = Method	#55.#574;	//  scala/collection/generic/TraversableTemplate$class.addString:(Lscala/collection/generic/TraversableTemplate;Lscala/collection/mutable/StringBuilder;)Lscala/collection/mutable/StringBuilder;
const #576 = Asciz	b;
const #577 = Asciz	Lscala/collection/mutable/StringBuilder;;
const #578 = Asciz	(Lscala/collection/mutable/StringBuilder;Ljava/lang/String;)Lscala/collection/mutable/StringBuilder;;
const #579 = Asciz	(Lscala/collection/generic/TraversableTemplate;Lscala/collection/mutable/StringBuilder;Ljava/lang/String;)Lscala/collection/mutable/StringBuilder;;
const #580 = NameAndType	#571:#579;//  addString:(Lscala/collection/generic/TraversableTemplate;Lscala/collection/mutable/StringBuilder;Ljava/lang/String;)Lscala/collection/mutable/StringBuilder;
const #581 = Method	#55.#580;	//  scala/collection/generic/TraversableTemplate$class.addString:(Lscala/collection/generic/TraversableTemplate;Lscala/collection/mutable/StringBuilder;Ljava/lang/String;)Lscala/collection/mutable/StringBuilder;
const #582 = Asciz	sep;
const #583 = Asciz	Ljava/lang/String;;
const #584 = Asciz	(Lscala/collection/mutable/StringBuilder;Ljava/lang/String;Ljava/lang/String;Ljava/lang/String;)Lscala/collection/mutable/StringBuilder;;
const #585 = Asciz	(Lscala/collection/generic/TraversableTemplate;Lscala/collection/mutable/StringBuilder;Ljava/lang/String;Ljava/lang/String;Ljava/lang/String;)Lscala/collection/mutable/StringBuilder;;
const #586 = NameAndType	#571:#585;//  addString:(Lscala/collection/generic/TraversableTemplate;Lscala/collection/mutable/StringBuilder;Ljava/lang/String;Ljava/lang/String;Ljava/lang/String;)Lscala/collection/mutable/StringBuilder;
const #587 = Method	#55.#586;	//  scala/collection/generic/TraversableTemplate$class.addString:(Lscala/collection/generic/TraversableTemplate;Lscala/collection/mutable/StringBuilder;Ljava/lang/String;Ljava/lang/String;Ljava/lang/String;)Lscala/collection/mutable/StringBuilder;
const #588 = Asciz	mkString;
const #589 = NameAndType	#588:#568;//  mkString:(Lscala/collection/generic/TraversableTemplate;)Ljava/lang/String;
const #590 = Method	#55.#589;	//  scala/collection/generic/TraversableTemplate$class.mkString:(Lscala/collection/generic/TraversableTemplate;)Ljava/lang/String;
const #591 = Asciz	(Ljava/lang/String;)Ljava/lang/String;;
const #592 = Asciz	(Lscala/collection/generic/TraversableTemplate;Ljava/lang/String;)Ljava/lang/String;;
const #593 = NameAndType	#588:#592;//  mkString:(Lscala/collection/generic/TraversableTemplate;Ljava/lang/String;)Ljava/lang/String;
const #594 = Method	#55.#593;	//  scala/collection/generic/TraversableTemplate$class.mkString:(Lscala/collection/generic/TraversableTemplate;Ljava/lang/String;)Ljava/lang/String;
const #595 = Asciz	(Ljava/lang/String;Ljava/lang/String;Ljava/lang/String;)Ljava/lang/String;;
const #596 = Asciz	(Lscala/collection/generic/TraversableTemplate;Ljava/lang/String;Ljava/lang/String;Ljava/lang/String;)Ljava/lang/String;;
const #597 = NameAndType	#588:#596;//  mkString:(Lscala/collection/generic/TraversableTemplate;Ljava/lang/String;Ljava/lang/String;Ljava/lang/String;)Ljava/lang/String;
const #598 = Method	#55.#597;	//  scala/collection/generic/TraversableTemplate$class.mkString:(Lscala/collection/generic/TraversableTemplate;Ljava/lang/String;Ljava/lang/String;Ljava/lang/String;)Ljava/lang/String;
const #599 = Asciz	toSet;
const #600 = Asciz	()Lscala/collection/immutable/Set;;
const #601 = Asciz	(Lscala/collection/generic/TraversableTemplate;)Lscala/collection/immutable/Set;;
const #602 = NameAndType	#599:#601;//  toSet:(Lscala/collection/generic/TraversableTemplate;)Lscala/collection/immutable/Set;
const #603 = Method	#55.#602;	//  scala/collection/generic/TraversableTemplate$class.toSet:(Lscala/collection/generic/TraversableTemplate;)Lscala/collection/immutable/Set;
const #604 = Asciz	toList;
const #605 = Asciz	(Lscala/collection/generic/TraversableTemplate;)Lscala/collection/immutable/List;;
const #606 = NameAndType	#604:#605;//  toList:(Lscala/collection/generic/TraversableTemplate;)Lscala/collection/immutable/List;
const #607 = Method	#55.#606;	//  scala/collection/generic/TraversableTemplate$class.toList:(Lscala/collection/generic/TraversableTemplate;)Lscala/collection/immutable/List;
const #608 = Asciz	toArray;
const #609 = Asciz	()Lscala/runtime/BoxedArray;;
const #610 = Asciz	(Lscala/collection/generic/TraversableTemplate;)Lscala/runtime/BoxedArray;;
const #611 = NameAndType	#608:#610;//  toArray:(Lscala/collection/generic/TraversableTemplate;)Lscala/runtime/BoxedArray;
const #612 = Method	#55.#611;	//  scala/collection/generic/TraversableTemplate$class.toArray:(Lscala/collection/generic/TraversableTemplate;)Lscala/runtime/BoxedArray;
const #613 = Asciz	copyToArray;
const #614 = Asciz	(Lscala/runtime/BoxedArray;I)V;
const #615 = Asciz	(Lscala/collection/generic/TraversableTemplate;Lscala/runtime/BoxedArray;I)V;
const #616 = NameAndType	#613:#615;//  copyToArray:(Lscala/collection/generic/TraversableTemplate;Lscala/runtime/BoxedArray;I)V
const #617 = Method	#55.#616;	//  scala/collection/generic/TraversableTemplate$class.copyToArray:(Lscala/collection/generic/TraversableTemplate;Lscala/runtime/BoxedArray;I)V
const #618 = Asciz	xs;
const #619 = Asciz	Lscala/runtime/BoxedArray;;
const #620 = Asciz	copyToBuffer;
const #621 = Asciz	(Lscala/collection/mutable/Buffer;)V;
const #622 = Asciz	(Lscala/collection/generic/TraversableTemplate;Lscala/collection/mutable/Buffer;)V;
const #623 = NameAndType	#620:#622;//  copyToBuffer:(Lscala/collection/generic/TraversableTemplate;Lscala/collection/mutable/Buffer;)V
const #624 = Method	#55.#623;	//  scala/collection/generic/TraversableTemplate$class.copyToBuffer:(Lscala/collection/generic/TraversableTemplate;Lscala/collection/mutable/Buffer;)V
const #625 = Asciz	dest;
const #626 = Asciz	Lscala/collection/mutable/Buffer;;
const #627 = Asciz	lastOption;
const #628 = Asciz	()Lscala/Option;;
const #629 = Asciz	(Lscala/collection/generic/TraversableTemplate;)Lscala/Option;;
const #630 = NameAndType	#627:#629;//  lastOption:(Lscala/collection/generic/TraversableTemplate;)Lscala/Option;
const #631 = Method	#55.#630;	//  scala/collection/generic/TraversableTemplate$class.lastOption:(Lscala/collection/generic/TraversableTemplate;)Lscala/Option;
const #632 = Asciz	headOption;
const #633 = NameAndType	#632:#629;//  headOption:(Lscala/collection/generic/TraversableTemplate;)Lscala/Option;
const #634 = Method	#55.#633;	//  scala/collection/generic/TraversableTemplate$class.headOption:(Lscala/collection/generic/TraversableTemplate;)Lscala/Option;
const #635 = Asciz	reduceRightOption;
const #636 = Asciz	(Lscala/Function2;)Lscala/Option;;
const #637 = Asciz	(Lscala/collection/generic/TraversableTemplate;Lscala/Function2;)Lscala/Option;;
const #638 = NameAndType	#635:#637;//  reduceRightOption:(Lscala/collection/generic/TraversableTemplate;Lscala/Function2;)Lscala/Option;
const #639 = Method	#55.#638;	//  scala/collection/generic/TraversableTemplate$class.reduceRightOption:(Lscala/collection/generic/TraversableTemplate;Lscala/Function2;)Lscala/Option;
const #640 = Asciz	op;
const #641 = Asciz	Lscala/Function2;;
const #642 = Asciz	reduceLeftOption;
const #643 = NameAndType	#642:#637;//  reduceLeftOption:(Lscala/collection/generic/TraversableTemplate;Lscala/Function2;)Lscala/Option;
const #644 = Method	#55.#643;	//  scala/collection/generic/TraversableTemplate$class.reduceLeftOption:(Lscala/collection/generic/TraversableTemplate;Lscala/Function2;)Lscala/Option;
const #645 = Asciz	$colon$bslash;
const #646 = Asciz	(Ljava/lang/Object;Lscala/Function2;)Ljava/lang/Object;;
const #647 = Asciz	(Lscala/collection/generic/TraversableTemplate;Ljava/lang/Object;Lscala/Function2;)Ljava/lang/Object;;
const #648 = NameAndType	#645:#647;//  $colon$bslash:(Lscala/collection/generic/TraversableTemplate;Ljava/lang/Object;Lscala/Function2;)Ljava/lang/Object;
const #649 = Method	#55.#648;	//  scala/collection/generic/TraversableTemplate$class.$colon$bslash:(Lscala/collection/generic/TraversableTemplate;Ljava/lang/Object;Lscala/Function2;)Ljava/lang/Object;
const #650 = Asciz	z;
const #651 = Asciz	$div$colon;
const #652 = NameAndType	#651:#647;//  $div$colon:(Lscala/collection/generic/TraversableTemplate;Ljava/lang/Object;Lscala/Function2;)Ljava/lang/Object;
const #653 = Method	#55.#652;	//  scala/collection/generic/TraversableTemplate$class.$div$colon:(Lscala/collection/generic/TraversableTemplate;Ljava/lang/Object;Lscala/Function2;)Ljava/lang/Object;
const #654 = Asciz	count;
const #655 = Asciz	(Lscala/Function1;)I;
const #656 = Asciz	(Lscala/collection/generic/TraversableTemplate;Lscala/Function1;)I;
const #657 = NameAndType	#654:#656;//  count:(Lscala/collection/generic/TraversableTemplate;Lscala/Function1;)I
const #658 = Method	#55.#657;	//  scala/collection/generic/TraversableTemplate$class.count:(Lscala/collection/generic/TraversableTemplate;Lscala/Function1;)I
const #659 = Asciz	groupBy;
const #660 = Asciz	(Lscala/Function1;)Lscala/collection/Map;;
const #661 = Asciz	(Lscala/collection/generic/TraversableTemplate;Lscala/Function1;)Lscala/collection/Map;;
const #662 = NameAndType	#659:#661;//  groupBy:(Lscala/collection/generic/TraversableTemplate;Lscala/Function1;)Lscala/collection/Map;
const #663 = Method	#55.#662;	//  scala/collection/generic/TraversableTemplate$class.groupBy:(Lscala/collection/generic/TraversableTemplate;Lscala/Function1;)Lscala/collection/Map;
const #664 = Asciz	partition;
const #665 = Asciz	(Lscala/Function1;)Lscala/Tuple2;;
const #666 = Asciz	(Lscala/collection/generic/TraversableTemplate;Lscala/Function1;)Lscala/Tuple2;;
const #667 = NameAndType	#664:#666;//  partition:(Lscala/collection/generic/TraversableTemplate;Lscala/Function1;)Lscala/Tuple2;
const #668 = Method	#55.#667;	//  scala/collection/generic/TraversableTemplate$class.partition:(Lscala/collection/generic/TraversableTemplate;Lscala/Function1;)Lscala/Tuple2;
const #669 = Asciz	remove;
const #670 = Asciz	(Lscala/collection/generic/TraversableTemplate;Lscala/Function1;)Lscala/collection/generic/TraversableTemplate;;
const #671 = NameAndType	#669:#670;//  remove:(Lscala/collection/generic/TraversableTemplate;Lscala/Function1;)Lscala/collection/generic/TraversableTemplate;
const #672 = Method	#55.#671;	//  scala/collection/generic/TraversableTemplate$class.remove:(Lscala/collection/generic/TraversableTemplate;Lscala/Function1;)Lscala/collection/generic/TraversableTemplate;
const #673 = Asciz	filterNot;
const #674 = NameAndType	#673:#670;//  filterNot:(Lscala/collection/generic/TraversableTemplate;Lscala/Function1;)Lscala/collection/generic/TraversableTemplate;
const #675 = Method	#55.#674;	//  scala/collection/generic/TraversableTemplate$class.filterNot:(Lscala/collection/generic/TraversableTemplate;Lscala/Function1;)Lscala/collection/generic/TraversableTemplate;
const #676 = Asciz	filterMap;
const #677 = Asciz	(Lscala/PartialFunction;Lscala/collection/generic/BuilderFactory;)Ljava/lang/Object;;
const #678 = Asciz	(Lscala/collection/generic/TraversableTemplate;Lscala/PartialFunction;Lscala/collection/generic/BuilderFactory;)Ljava/lang/Object;;
const #679 = NameAndType	#676:#678;//  filterMap:(Lscala/collection/generic/TraversableTemplate;Lscala/PartialFunction;Lscala/collection/generic/BuilderFactory;)Ljava/lang/Object;
const #680 = Method	#55.#679;	//  scala/collection/generic/TraversableTemplate$class.filterMap:(Lscala/collection/generic/TraversableTemplate;Lscala/PartialFunction;Lscala/collection/generic/BuilderFactory;)Ljava/lang/Object;
const #681 = Asciz	pf;
const #682 = Asciz	bf;
const #683 = Asciz	Lscala/collection/generic/BuilderFactory;;
const #684 = Asciz	hasDefiniteSize;
const #685 = Asciz	(Lscala/collection/generic/TraversableTemplate;)Z;
const #686 = NameAndType	#684:#685;//  hasDefiniteSize:(Lscala/collection/generic/TraversableTemplate;)Z
const #687 = Method	#55.#686;	//  scala/collection/generic/TraversableTemplate$class.hasDefiniteSize:(Lscala/collection/generic/TraversableTemplate;)Z
const #688 = Asciz	nonEmpty;
const #689 = NameAndType	#688:#685;//  nonEmpty:(Lscala/collection/generic/TraversableTemplate;)Z
const #690 = Method	#55.#689;	//  scala/collection/generic/TraversableTemplate$class.nonEmpty:(Lscala/collection/generic/TraversableTemplate;)Z
const #691 = Asciz	thisCollection;
const #692 = Asciz	(Lscala/collection/generic/TraversableTemplate;)Lscala/collection/generic/TraversableTemplate;;
const #693 = NameAndType	#691:#692;//  thisCollection:(Lscala/collection/generic/TraversableTemplate;)Lscala/collection/generic/TraversableTemplate;
const #694 = Method	#55.#693;	//  scala/collection/generic/TraversableTemplate$class.thisCollection:(Lscala/collection/generic/TraversableTemplate;)Lscala/collection/generic/TraversableTemplate;
const #695 = Asciz	transpose;
const #696 = Asciz	(Lscala/Function1;)Lscala/collection/Traversable;;
const #697 = Asciz	(Lscala/collection/generic/TraversableClass;Lscala/Function1;)Lscala/collection/Traversable;;
const #698 = NameAndType	#695:#697;//  transpose:(Lscala/collection/generic/TraversableClass;Lscala/Function1;)Lscala/collection/Traversable;
const #699 = Method	#60.#698;	//  scala/collection/generic/TraversableClass$class.transpose:(Lscala/collection/generic/TraversableClass;Lscala/Function1;)Lscala/collection/Traversable;
const #700 = Asciz	toTraversable;
const #701 = Asciz	flatten;
const #702 = NameAndType	#701:#697;//  flatten:(Lscala/collection/generic/TraversableClass;Lscala/Function1;)Lscala/collection/Traversable;
const #703 = Method	#60.#702;	//  scala/collection/generic/TraversableClass$class.flatten:(Lscala/collection/generic/TraversableClass;Lscala/Function1;)Lscala/collection/Traversable;
const #704 = Asciz	unzip;
const #705 = Asciz	(Lscala/collection/generic/TraversableClass;Lscala/Function1;)Lscala/Tuple2;;
const #706 = NameAndType	#704:#705;//  unzip:(Lscala/collection/generic/TraversableClass;Lscala/Function1;)Lscala/Tuple2;
const #707 = Method	#60.#706;	//  scala/collection/generic/TraversableClass$class.unzip:(Lscala/collection/generic/TraversableClass;Lscala/Function1;)Lscala/Tuple2;
const #708 = Asciz	toPair;
const #709 = Asciz	genericBuilder;
const #710 = Asciz	()Lscala/collection/generic/Builder;;
const #711 = Asciz	(Lscala/collection/generic/TraversableClass;)Lscala/collection/generic/Builder;;
const #712 = NameAndType	#709:#711;//  genericBuilder:(Lscala/collection/generic/TraversableClass;)Lscala/collection/generic/Builder;
const #713 = Method	#60.#712;	//  scala/collection/generic/TraversableClass$class.genericBuilder:(Lscala/collection/generic/TraversableClass;)Lscala/collection/generic/Builder;
const #714 = Asciz	toSeq;
const #715 = Asciz	(Lscala/collection/generic/IterableTemplate;)Lscala/collection/Sequence;;
const #716 = NameAndType	#714:#715;//  toSeq:(Lscala/collection/generic/IterableTemplate;)Lscala/collection/Sequence;
const #717 = Method	#70.#716;	//  scala/collection/generic/IterableTemplate$class.toSeq:(Lscala/collection/generic/IterableTemplate;)Lscala/collection/Sequence;
const #718 = Asciz	firstOption;
const #719 = Asciz	(Lscala/collection/generic/IterableTemplate;)Lscala/Option;;
const #720 = NameAndType	#718:#719;//  firstOption:(Lscala/collection/generic/IterableTemplate;)Lscala/Option;
const #721 = Method	#70.#720;	//  scala/collection/generic/IterableTemplate$class.firstOption:(Lscala/collection/generic/IterableTemplate;)Lscala/Option;
const #722 = Asciz	first;
const #723 = Asciz	(Lscala/collection/generic/IterableTemplate;)Ljava/lang/Object;;
const #724 = NameAndType	#722:#723;//  first:(Lscala/collection/generic/IterableTemplate;)Ljava/lang/Object;
const #725 = Method	#70.#724;	//  scala/collection/generic/IterableTemplate$class.first:(Lscala/collection/generic/IterableTemplate;)Ljava/lang/Object;
const #726 = Asciz	toStream;
const #727 = Asciz	()Lscala/collection/immutable/Stream;;
const #728 = Asciz	(Lscala/collection/generic/IterableTemplate;)Lscala/collection/immutable/Stream;;
const #729 = NameAndType	#726:#728;//  toStream:(Lscala/collection/generic/IterableTemplate;)Lscala/collection/immutable/Stream;
const #730 = Method	#70.#729;	//  scala/collection/generic/IterableTemplate$class.toStream:(Lscala/collection/generic/IterableTemplate;)Lscala/collection/immutable/Stream;
const #731 = Asciz	toIterable;
const #732 = Asciz	()Lscala/collection/Iterable;;
const #733 = Asciz	(Lscala/collection/generic/IterableTemplate;)Lscala/collection/Iterable;;
const #734 = NameAndType	#731:#733;//  toIterable:(Lscala/collection/generic/IterableTemplate;)Lscala/collection/Iterable;
const #735 = Method	#70.#734;	//  scala/collection/generic/IterableTemplate$class.toIterable:(Lscala/collection/generic/IterableTemplate;)Lscala/collection/Iterable;
const #736 = Asciz	elements;
const #737 = Asciz	()Lscala/collection/Iterator;;
const #738 = Asciz	(Lscala/collection/generic/IterableTemplate;)Lscala/collection/Iterator;;
const #739 = NameAndType	#736:#738;//  elements:(Lscala/collection/generic/IterableTemplate;)Lscala/collection/Iterator;
const #740 = Method	#70.#739;	//  scala/collection/generic/IterableTemplate$class.elements:(Lscala/collection/generic/IterableTemplate;)Lscala/collection/Iterator;
const #741 = Asciz	projection;
const #742 = Asciz	(Lscala/collection/generic/SequenceTemplate;)Ljava/lang/Object;;
const #743 = NameAndType	#741:#742;//  projection:(Lscala/collection/generic/SequenceTemplate;)Ljava/lang/Object;
const #744 = Method	#80.#743;	//  scala/collection/generic/SequenceTemplate$class.projection:(Lscala/collection/generic/SequenceTemplate;)Ljava/lang/Object;
const #745 = Asciz	containsSlice;
const #746 = Asciz	(Lscala/collection/Sequence;)Z;
const #747 = Asciz	(Lscala/collection/generic/SequenceTemplate;Lscala/collection/Sequence;)Z;
const #748 = NameAndType	#745:#747;//  containsSlice:(Lscala/collection/generic/SequenceTemplate;Lscala/collection/Sequence;)Z
const #749 = Method	#80.#748;	//  scala/collection/generic/SequenceTemplate$class.containsSlice:(Lscala/collection/generic/SequenceTemplate;Lscala/collection/Sequence;)Z
const #750 = Asciz	equalsWith;
const #751 = Asciz	(Lscala/collection/Sequence;Lscala/Function2;)Z;
const #752 = Asciz	(Lscala/collection/generic/SequenceTemplate;Lscala/collection/Sequence;Lscala/Function2;)Z;
const #753 = NameAndType	#750:#752;//  equalsWith:(Lscala/collection/generic/SequenceTemplate;Lscala/collection/Sequence;Lscala/Function2;)Z
const #754 = Method	#80.#753;	//  scala/collection/generic/SequenceTemplate$class.equalsWith:(Lscala/collection/generic/SequenceTemplate;Lscala/collection/Sequence;Lscala/Function2;)Z
const #755 = Asciz	(I)Lscala/collection/Sequence;;
const #756 = Asciz	(Lscala/collection/generic/SequenceTemplate;I)Lscala/collection/Sequence;;
const #757 = NameAndType	#371:#756;//  slice:(Lscala/collection/generic/SequenceTemplate;I)Lscala/collection/Sequence;
const #758 = Method	#80.#757;	//  scala/collection/generic/SequenceTemplate$class.slice:(Lscala/collection/generic/SequenceTemplate;I)Lscala/collection/Sequence;
const #759 = Asciz	findLastIndexOf;
const #760 = Asciz	(Lscala/collection/generic/SequenceTemplate;Lscala/Function1;)I;
const #761 = NameAndType	#759:#760;//  findLastIndexOf:(Lscala/collection/generic/SequenceTemplate;Lscala/Function1;)I
const #762 = Method	#80.#761;	//  scala/collection/generic/SequenceTemplate$class.findLastIndexOf:(Lscala/collection/generic/SequenceTemplate;Lscala/Function1;)I
const #763 = Asciz	indices;
const #764 = Asciz	()Lscala/Range;;
const #765 = Asciz	(Lscala/collection/generic/SequenceTemplate;)Lscala/Range;;
const #766 = NameAndType	#763:#765;//  indices:(Lscala/collection/generic/SequenceTemplate;)Lscala/Range;
const #767 = Method	#80.#766;	//  scala/collection/generic/SequenceTemplate$class.indices:(Lscala/collection/generic/SequenceTemplate;)Lscala/Range;
const #768 = Asciz	toSequence;
const #769 = Asciz	(Lscala/collection/generic/SequenceTemplate;)Lscala/collection/Sequence;;
const #770 = NameAndType	#768:#769;//  toSequence:(Lscala/collection/generic/SequenceTemplate;)Lscala/collection/Sequence;
const #771 = Method	#80.#770;	//  scala/collection/generic/SequenceTemplate$class.toSequence:(Lscala/collection/generic/SequenceTemplate;)Lscala/collection/Sequence;
const #772 = Asciz	removeDuplicates;
const #773 = Asciz	(Lscala/collection/generic/SequenceTemplate;)Lscala/collection/generic/IterableTemplate;;
const #774 = NameAndType	#772:#773;//  removeDuplicates:(Lscala/collection/generic/SequenceTemplate;)Lscala/collection/generic/IterableTemplate;
const #775 = Method	#80.#774;	//  scala/collection/generic/SequenceTemplate$class.removeDuplicates:(Lscala/collection/generic/SequenceTemplate;)Lscala/collection/generic/IterableTemplate;
const #776 = Asciz	intersect;
const #777 = Asciz	(Lscala/collection/Sequence;)Lscala/collection/generic/IterableTemplate;;
const #778 = Asciz	(Lscala/collection/generic/SequenceTemplate;Lscala/collection/Sequence;)Lscala/collection/generic/IterableTemplate;;
const #779 = NameAndType	#776:#778;//  intersect:(Lscala/collection/generic/SequenceTemplate;Lscala/collection/Sequence;)Lscala/collection/generic/IterableTemplate;
const #780 = Method	#80.#779;	//  scala/collection/generic/SequenceTemplate$class.intersect:(Lscala/collection/generic/SequenceTemplate;Lscala/collection/Sequence;)Lscala/collection/generic/IterableTemplate;
const #781 = Asciz	diff;
const #782 = NameAndType	#781:#778;//  diff:(Lscala/collection/generic/SequenceTemplate;Lscala/collection/Sequence;)Lscala/collection/generic/IterableTemplate;
const #783 = Method	#80.#782;	//  scala/collection/generic/SequenceTemplate$class.diff:(Lscala/collection/generic/SequenceTemplate;Lscala/collection/Sequence;)Lscala/collection/generic/IterableTemplate;
const #784 = Asciz	union;
const #785 = Asciz	(Lscala/collection/Sequence;Lscala/collection/generic/BuilderFactory;)Ljava/lang/Object;;
const #786 = Asciz	(Lscala/collection/generic/SequenceTemplate;Lscala/collection/Sequence;Lscala/collection/generic/BuilderFactory;)Ljava/lang/Object;;
const #787 = NameAndType	#784:#786;//  union:(Lscala/collection/generic/SequenceTemplate;Lscala/collection/Sequence;Lscala/collection/generic/BuilderFactory;)Ljava/lang/Object;
const #788 = Method	#80.#787;	//  scala/collection/generic/SequenceTemplate$class.union:(Lscala/collection/generic/SequenceTemplate;Lscala/collection/Sequence;Lscala/collection/generic/BuilderFactory;)Ljava/lang/Object;
const #789 = Asciz	lastIndexOfSeq;
const #790 = Asciz	(Lscala/collection/Sequence;I)I;
const #791 = Asciz	(Lscala/collection/generic/SequenceTemplate;Lscala/collection/Sequence;I)I;
const #792 = NameAndType	#789:#791;//  lastIndexOfSeq:(Lscala/collection/generic/SequenceTemplate;Lscala/collection/Sequence;I)I
const #793 = Method	#80.#792;	//  scala/collection/generic/SequenceTemplate$class.lastIndexOfSeq:(Lscala/collection/generic/SequenceTemplate;Lscala/collection/Sequence;I)I
const #794 = Asciz	fromIndex;
const #795 = Asciz	(Lscala/collection/Sequence;)I;
const #796 = Asciz	(Lscala/collection/generic/SequenceTemplate;Lscala/collection/Sequence;)I;
const #797 = NameAndType	#789:#796;//  lastIndexOfSeq:(Lscala/collection/generic/SequenceTemplate;Lscala/collection/Sequence;)I
const #798 = Method	#80.#797;	//  scala/collection/generic/SequenceTemplate$class.lastIndexOfSeq:(Lscala/collection/generic/SequenceTemplate;Lscala/collection/Sequence;)I
const #799 = Asciz	indexOfSeq;
const #800 = NameAndType	#799:#791;//  indexOfSeq:(Lscala/collection/generic/SequenceTemplate;Lscala/collection/Sequence;I)I
const #801 = Method	#80.#800;	//  scala/collection/generic/SequenceTemplate$class.indexOfSeq:(Lscala/collection/generic/SequenceTemplate;Lscala/collection/Sequence;I)I
const #802 = NameAndType	#799:#796;//  indexOfSeq:(Lscala/collection/generic/SequenceTemplate;Lscala/collection/Sequence;)I
const #803 = Method	#80.#802;	//  scala/collection/generic/SequenceTemplate$class.indexOfSeq:(Lscala/collection/generic/SequenceTemplate;Lscala/collection/Sequence;)I
const #804 = Asciz	startsWith;
const #805 = NameAndType	#804:#747;//  startsWith:(Lscala/collection/generic/SequenceTemplate;Lscala/collection/Sequence;)Z
const #806 = Method	#80.#805;	//  scala/collection/generic/SequenceTemplate$class.startsWith:(Lscala/collection/generic/SequenceTemplate;Lscala/collection/Sequence;)Z
const #807 = Asciz	reversedElements;
const #808 = Asciz	(Lscala/collection/generic/SequenceTemplate;)Lscala/collection/Iterator;;
const #809 = NameAndType	#807:#808;//  reversedElements:(Lscala/collection/generic/SequenceTemplate;)Lscala/collection/Iterator;
const #810 = Method	#80.#809;	//  scala/collection/generic/SequenceTemplate$class.reversedElements:(Lscala/collection/generic/SequenceTemplate;)Lscala/collection/Iterator;
const #811 = Asciz	lastIndexWhere;
const #812 = NameAndType	#811:#760;//  lastIndexWhere:(Lscala/collection/generic/SequenceTemplate;Lscala/Function1;)I
const #813 = Method	#80.#812;	//  scala/collection/generic/SequenceTemplate$class.lastIndexWhere:(Lscala/collection/generic/SequenceTemplate;Lscala/Function1;)I
const #814 = Asciz	lastIndexOf;
const #815 = Asciz	(Ljava/lang/Object;I)I;
const #816 = Asciz	(Lscala/collection/generic/SequenceTemplate;Ljava/lang/Object;I)I;
const #817 = NameAndType	#814:#816;//  lastIndexOf:(Lscala/collection/generic/SequenceTemplate;Ljava/lang/Object;I)I
const #818 = Method	#80.#817;	//  scala/collection/generic/SequenceTemplate$class.lastIndexOf:(Lscala/collection/generic/SequenceTemplate;Ljava/lang/Object;I)I
const #819 = Asciz	(Lscala/collection/generic/SequenceTemplate;Ljava/lang/Object;)I;
const #820 = NameAndType	#814:#819;//  lastIndexOf:(Lscala/collection/generic/SequenceTemplate;Ljava/lang/Object;)I
const #821 = Method	#80.#820;	//  scala/collection/generic/SequenceTemplate$class.lastIndexOf:(Lscala/collection/generic/SequenceTemplate;Ljava/lang/Object;)I
const #822 = Asciz	indexOf;
const #823 = NameAndType	#822:#816;//  indexOf:(Lscala/collection/generic/SequenceTemplate;Ljava/lang/Object;I)I
const #824 = Method	#80.#823;	//  scala/collection/generic/SequenceTemplate$class.indexOf:(Lscala/collection/generic/SequenceTemplate;Ljava/lang/Object;I)I
const #825 = NameAndType	#822:#819;//  indexOf:(Lscala/collection/generic/SequenceTemplate;Ljava/lang/Object;)I
const #826 = Method	#80.#825;	//  scala/collection/generic/SequenceTemplate$class.indexOf:(Lscala/collection/generic/SequenceTemplate;Ljava/lang/Object;)I
const #827 = Asciz	findIndexOf;
const #828 = NameAndType	#827:#760;//  findIndexOf:(Lscala/collection/generic/SequenceTemplate;Lscala/Function1;)I
const #829 = Method	#80.#828;	//  scala/collection/generic/SequenceTemplate$class.findIndexOf:(Lscala/collection/generic/SequenceTemplate;Lscala/Function1;)I
const #830 = Asciz	indexWhere;
const #831 = NameAndType	#830:#760;//  indexWhere:(Lscala/collection/generic/SequenceTemplate;Lscala/Function1;)I
const #832 = Method	#80.#831;	//  scala/collection/generic/SequenceTemplate$class.indexWhere:(Lscala/collection/generic/SequenceTemplate;Lscala/Function1;)I
const #833 = Asciz	prefixLength;
const #834 = NameAndType	#833:#760;//  prefixLength:(Lscala/collection/generic/SequenceTemplate;Lscala/Function1;)I
const #835 = Method	#80.#834;	//  scala/collection/generic/SequenceTemplate$class.prefixLength:(Lscala/collection/generic/SequenceTemplate;Lscala/Function1;)I
const #836 = Asciz	(Lscala/collection/generic/SequenceTemplate;I)Z;
const #837 = NameAndType	#402:#836;//  isDefinedAt:(Lscala/collection/generic/SequenceTemplate;I)Z
const #838 = Method	#80.#837;	//  scala/collection/generic/SequenceTemplate$class.isDefinedAt:(Lscala/collection/generic/SequenceTemplate;I)Z
const #839 = Asciz	size;
const #840 = Asciz	(Lscala/collection/generic/SequenceTemplate;)I;
const #841 = NameAndType	#839:#840;//  size:(Lscala/collection/generic/SequenceTemplate;)I
const #842 = Method	#80.#841;	//  scala/collection/generic/SequenceTemplate$class.size:(Lscala/collection/generic/SequenceTemplate;)I
const #843 = Asciz	(Lscala/collection/generic/VectorTemplate;II)Lscala/collection/generic/VectorView;;
const #844 = NameAndType	#396:#843;//  view:(Lscala/collection/generic/VectorTemplate;II)Lscala/collection/generic/VectorView;
const #845 = Method	#90.#844;	//  scala/collection/generic/VectorTemplate$class.view:(Lscala/collection/generic/VectorTemplate;II)Lscala/collection/generic/VectorView;
const #846 = Asciz	(Lscala/collection/generic/VectorTemplate;)Ljava/lang/Object;;
const #847 = NameAndType	#396:#846;//  view:(Lscala/collection/generic/VectorTemplate;)Ljava/lang/Object;
const #848 = Method	#90.#847;	//  scala/collection/generic/VectorTemplate$class.view:(Lscala/collection/generic/VectorTemplate;)Ljava/lang/Object;
const #849 = Asciz	endsWith;
const #850 = Asciz	(Lscala/collection/generic/VectorTemplate;Lscala/collection/Sequence;)Z;
const #851 = NameAndType	#849:#850;//  endsWith:(Lscala/collection/generic/VectorTemplate;Lscala/collection/Sequence;)Z
const #852 = Method	#90.#851;	//  scala/collection/generic/VectorTemplate$class.endsWith:(Lscala/collection/generic/VectorTemplate;Lscala/collection/Sequence;)Z
const #853 = Asciz	(Lscala/collection/Sequence;I)Z;
const #854 = Asciz	(Lscala/collection/generic/VectorTemplate;Lscala/collection/Sequence;I)Z;
const #855 = NameAndType	#804:#854;//  startsWith:(Lscala/collection/generic/VectorTemplate;Lscala/collection/Sequence;I)Z
const #856 = Method	#90.#855;	//  scala/collection/generic/VectorTemplate$class.startsWith:(Lscala/collection/generic/VectorTemplate;Lscala/collection/Sequence;I)Z
const #857 = Asciz	offset;
const #858 = Asciz	reverseIterator;
const #859 = Asciz	(Lscala/collection/generic/VectorTemplate;)Lscala/collection/Iterator;;
const #860 = NameAndType	#858:#859;//  reverseIterator:(Lscala/collection/generic/VectorTemplate;)Lscala/collection/Iterator;
const #861 = Method	#90.#860;	//  scala/collection/generic/VectorTemplate$class.reverseIterator:(Lscala/collection/generic/VectorTemplate;)Lscala/collection/Iterator;
const #862 = Asciz	(Lscala/Function1;I)I;
const #863 = Asciz	(Lscala/collection/generic/VectorTemplate;Lscala/Function1;I)I;
const #864 = NameAndType	#811:#863;//  lastIndexWhere:(Lscala/collection/generic/VectorTemplate;Lscala/Function1;I)I
const #865 = Method	#90.#864;	//  scala/collection/generic/VectorTemplate$class.lastIndexWhere:(Lscala/collection/generic/VectorTemplate;Lscala/Function1;I)I
const #866 = NameAndType	#830:#863;//  indexWhere:(Lscala/collection/generic/VectorTemplate;Lscala/Function1;I)I
const #867 = Method	#90.#866;	//  scala/collection/generic/VectorTemplate$class.indexWhere:(Lscala/collection/generic/VectorTemplate;Lscala/Function1;I)I
const #868 = Asciz	segmentLength;
const #869 = NameAndType	#868:#863;//  segmentLength:(Lscala/collection/generic/VectorTemplate;Lscala/Function1;I)I
const #870 = Method	#90.#869;	//  scala/collection/generic/VectorTemplate$class.segmentLength:(Lscala/collection/generic/VectorTemplate;Lscala/Function1;I)I
const #871 = Asciz	lengthCompare;
const #872 = Asciz	(I)I;
const #873 = Asciz	(Lscala/collection/generic/VectorTemplate;I)I;
const #874 = NameAndType	#871:#873;//  lengthCompare:(Lscala/collection/generic/VectorTemplate;I)I
const #875 = Method	#90.#874;	//  scala/collection/generic/VectorTemplate$class.lengthCompare:(Lscala/collection/generic/VectorTemplate;I)I
const #876 = Asciz	len;
const #877 = Asciz	(Lscala/runtime/BoxedArray;II)V;
const #878 = Asciz	(Lscala/collection/generic/VectorTemplate;Lscala/runtime/BoxedArray;II)V;
const #879 = NameAndType	#613:#878;//  copyToArray:(Lscala/collection/generic/VectorTemplate;Lscala/runtime/BoxedArray;II)V
const #880 = Method	#90.#879;	//  scala/collection/generic/VectorTemplate$class.copyToArray:(Lscala/collection/generic/VectorTemplate;Lscala/runtime/BoxedArray;II)V
const #881 = Asciz	sameElements;
const #882 = Asciz	(Lscala/collection/Iterable;)Z;
const #883 = Asciz	(Lscala/collection/generic/VectorTemplate;Lscala/collection/Iterable;)Z;
const #884 = NameAndType	#881:#883;//  sameElements:(Lscala/collection/generic/VectorTemplate;Lscala/collection/Iterable;)Z
const #885 = Method	#90.#884;	//  scala/collection/generic/VectorTemplate$class.sameElements:(Lscala/collection/generic/VectorTemplate;Lscala/collection/Iterable;)Z
const #886 = Asciz	Lscala/collection/Iterable;;
const #887 = Asciz	(Lscala/collection/generic/VectorTemplate;I)Lscala/collection/generic/VectorTemplate;;
const #888 = NameAndType	#393:#887;//  dropRight:(Lscala/collection/generic/VectorTemplate;I)Lscala/collection/generic/VectorTemplate;
const #889 = Method	#90.#888;	//  scala/collection/generic/VectorTemplate$class.dropRight:(Lscala/collection/generic/VectorTemplate;I)Lscala/collection/generic/VectorTemplate;
const #890 = NameAndType	#389:#887;//  takeRight:(Lscala/collection/generic/VectorTemplate;I)Lscala/collection/generic/VectorTemplate;
const #891 = Method	#90.#890;	//  scala/collection/generic/VectorTemplate$class.takeRight:(Lscala/collection/generic/VectorTemplate;I)Lscala/collection/generic/VectorTemplate;
const #892 = Asciz	last;
const #893 = NameAndType	#892:#846;//  last:(Lscala/collection/generic/VectorTemplate;)Ljava/lang/Object;
const #894 = Method	#90.#893;	//  scala/collection/generic/VectorTemplate$class.last:(Lscala/collection/generic/VectorTemplate;)Ljava/lang/Object;
const #895 = Asciz	(Lscala/collection/generic/VectorTemplate;)Lscala/collection/generic/VectorTemplate;;
const #896 = NameAndType	#386:#895;//  tail:(Lscala/collection/generic/VectorTemplate;)Lscala/collection/generic/VectorTemplate;
const #897 = Method	#90.#896;	//  scala/collection/generic/VectorTemplate$class.tail:(Lscala/collection/generic/VectorTemplate;)Lscala/collection/generic/VectorTemplate;
const #898 = Asciz	head;
const #899 = NameAndType	#898:#846;//  head:(Lscala/collection/generic/VectorTemplate;)Ljava/lang/Object;
const #900 = Method	#90.#899;	//  scala/collection/generic/VectorTemplate$class.head:(Lscala/collection/generic/VectorTemplate;)Ljava/lang/Object;
const #901 = Asciz	reduceRight;
const #902 = Asciz	(Lscala/Function2;)Ljava/lang/Object;;
const #903 = Asciz	(Lscala/collection/generic/VectorTemplate;Lscala/Function2;)Ljava/lang/Object;;
const #904 = NameAndType	#901:#903;//  reduceRight:(Lscala/collection/generic/VectorTemplate;Lscala/Function2;)Ljava/lang/Object;
const #905 = Method	#90.#904;	//  scala/collection/generic/VectorTemplate$class.reduceRight:(Lscala/collection/generic/VectorTemplate;Lscala/Function2;)Ljava/lang/Object;
const #906 = Asciz	reduceLeft;
const #907 = NameAndType	#906:#903;//  reduceLeft:(Lscala/collection/generic/VectorTemplate;Lscala/Function2;)Ljava/lang/Object;
const #908 = Method	#90.#907;	//  scala/collection/generic/VectorTemplate$class.reduceLeft:(Lscala/collection/generic/VectorTemplate;Lscala/Function2;)Ljava/lang/Object;
const #909 = Asciz	foldRight;
const #910 = Asciz	(Lscala/collection/generic/VectorTemplate;Ljava/lang/Object;Lscala/Function2;)Ljava/lang/Object;;
const #911 = NameAndType	#909:#910;//  foldRight:(Lscala/collection/generic/VectorTemplate;Ljava/lang/Object;Lscala/Function2;)Ljava/lang/Object;
const #912 = Method	#90.#911;	//  scala/collection/generic/VectorTemplate$class.foldRight:(Lscala/collection/generic/VectorTemplate;Ljava/lang/Object;Lscala/Function2;)Ljava/lang/Object;
const #913 = Asciz	foldLeft;
const #914 = NameAndType	#913:#910;//  foldLeft:(Lscala/collection/generic/VectorTemplate;Ljava/lang/Object;Lscala/Function2;)Ljava/lang/Object;
const #915 = Method	#90.#914;	//  scala/collection/generic/VectorTemplate$class.foldLeft:(Lscala/collection/generic/VectorTemplate;Ljava/lang/Object;Lscala/Function2;)Ljava/lang/Object;
const #916 = Asciz	find;
const #917 = Asciz	(Lscala/Function1;)Lscala/Option;;
const #918 = Asciz	(Lscala/collection/generic/VectorTemplate;Lscala/Function1;)Lscala/Option;;
const #919 = NameAndType	#916:#918;//  find:(Lscala/collection/generic/VectorTemplate;Lscala/Function1;)Lscala/Option;
const #920 = Method	#90.#919;	//  scala/collection/generic/VectorTemplate$class.find:(Lscala/collection/generic/VectorTemplate;Lscala/Function1;)Lscala/Option;
const #921 = Asciz	exists;
const #922 = Asciz	(Lscala/Function1;)Z;
const #923 = Asciz	(Lscala/collection/generic/VectorTemplate;Lscala/Function1;)Z;
const #924 = NameAndType	#921:#923;//  exists:(Lscala/collection/generic/VectorTemplate;Lscala/Function1;)Z
const #925 = Method	#90.#924;	//  scala/collection/generic/VectorTemplate$class.exists:(Lscala/collection/generic/VectorTemplate;Lscala/Function1;)Z
const #926 = Asciz	forall;
const #927 = NameAndType	#926:#923;//  forall:(Lscala/collection/generic/VectorTemplate;Lscala/Function1;)Z
const #928 = Method	#90.#927;	//  scala/collection/generic/VectorTemplate$class.forall:(Lscala/collection/generic/VectorTemplate;Lscala/Function1;)Z
const #929 = Asciz	isEmpty;
const #930 = Asciz	(Lscala/collection/generic/VectorTemplate;)Z;
const #931 = NameAndType	#929:#930;//  isEmpty:(Lscala/collection/generic/VectorTemplate;)Z
const #932 = Method	#90.#931;	//  scala/collection/generic/VectorTemplate$class.isEmpty:(Lscala/collection/generic/VectorTemplate;)Z
const #933 = Asciz	iterator;
const #934 = NameAndType	#933:#859;//  iterator:(Lscala/collection/generic/VectorTemplate;)Lscala/collection/Iterator;
const #935 = Method	#90.#934;	//  scala/collection/generic/VectorTemplate$class.iterator:(Lscala/collection/generic/VectorTemplate;)Lscala/collection/Iterator;
const #936 = Asciz	scala$collection$generic$VectorTemplate$$super$equals;
const #937 = NameAndType	#255:#549;//  equals:(Lscala/collection/generic/SequenceTemplate;Ljava/lang/Object;)Z
const #938 = Method	#80.#937;	//  scala/collection/generic/SequenceTemplate$class.equals:(Lscala/collection/generic/SequenceTemplate;Ljava/lang/Object;)Z
const #939 = Asciz	scala$collection$generic$VectorTemplate$$super$endsWith;
const #940 = NameAndType	#849:#747;//  endsWith:(Lscala/collection/generic/SequenceTemplate;Lscala/collection/Sequence;)Z
const #941 = Method	#80.#940;	//  scala/collection/generic/SequenceTemplate$class.endsWith:(Lscala/collection/generic/SequenceTemplate;Lscala/collection/Sequence;)Z
const #942 = Asciz	scala$collection$generic$VectorTemplate$$super$sameElements;
const #943 = Asciz	(Lscala/collection/generic/IterableTemplate;Lscala/collection/Iterable;)Z;
const #944 = NameAndType	#881:#943;//  sameElements:(Lscala/collection/generic/IterableTemplate;Lscala/collection/Iterable;)Z
const #945 = Method	#70.#944;	//  scala/collection/generic/IterableTemplate$class.sameElements:(Lscala/collection/generic/IterableTemplate;Lscala/collection/Iterable;)Z
const #946 = Asciz	scala$collection$generic$VectorTemplate$$super$init;
const #947 = NameAndType	#356:#692;//  init:(Lscala/collection/generic/TraversableTemplate;)Lscala/collection/generic/TraversableTemplate;
const #948 = Method	#55.#947;	//  scala/collection/generic/TraversableTemplate$class.init:(Lscala/collection/generic/TraversableTemplate;)Lscala/collection/generic/TraversableTemplate;
const #949 = Asciz	scala$collection$generic$VectorTemplate$$super$last;
const #950 = Asciz	(Lscala/collection/generic/TraversableTemplate;)Ljava/lang/Object;;
const #951 = NameAndType	#892:#950;//  last:(Lscala/collection/generic/TraversableTemplate;)Ljava/lang/Object;
const #952 = Method	#55.#951;	//  scala/collection/generic/TraversableTemplate$class.last:(Lscala/collection/generic/TraversableTemplate;)Ljava/lang/Object;
const #953 = Asciz	scala$collection$generic$VectorTemplate$$super$head;
const #954 = NameAndType	#898:#723;//  head:(Lscala/collection/generic/IterableTemplate;)Ljava/lang/Object;
const #955 = Method	#70.#954;	//  scala/collection/generic/IterableTemplate$class.head:(Lscala/collection/generic/IterableTemplate;)Ljava/lang/Object;
const #956 = Asciz	scala$collection$generic$VectorTemplate$$super$zip;
const #957 = Asciz	zip;
const #958 = NameAndType	#957:#786;//  zip:(Lscala/collection/generic/SequenceTemplate;Lscala/collection/Sequence;Lscala/collection/generic/BuilderFactory;)Ljava/lang/Object;
const #959 = Method	#80.#958;	//  scala/collection/generic/SequenceTemplate$class.zip:(Lscala/collection/generic/SequenceTemplate;Lscala/collection/Sequence;Lscala/collection/generic/BuilderFactory;)Ljava/lang/Object;
const #960 = Asciz	scala$collection$generic$VectorTemplate$$super$reduceRight;
const #961 = Asciz	(Lscala/collection/generic/IterableTemplate;Lscala/Function2;)Ljava/lang/Object;;
const #962 = NameAndType	#901:#961;//  reduceRight:(Lscala/collection/generic/IterableTemplate;Lscala/Function2;)Ljava/lang/Object;
const #963 = Method	#70.#962;	//  scala/collection/generic/IterableTemplate$class.reduceRight:(Lscala/collection/generic/IterableTemplate;Lscala/Function2;)Ljava/lang/Object;
const #964 = Asciz	scala$collection$generic$VectorTemplate$$super$reduceLeft;
const #965 = Asciz	(Lscala/collection/generic/TraversableTemplate;Lscala/Function2;)Ljava/lang/Object;;
const #966 = NameAndType	#906:#965;//  reduceLeft:(Lscala/collection/generic/TraversableTemplate;Lscala/Function2;)Ljava/lang/Object;
const #967 = Method	#55.#966;	//  scala/collection/generic/TraversableTemplate$class.reduceLeft:(Lscala/collection/generic/TraversableTemplate;Lscala/Function2;)Ljava/lang/Object;
const #968 = Asciz	companion;
const #969 = Asciz	()Lscala/collection/generic/Companion;;
const #970 = Asciz	(Lscala/collection/Vector;)Lscala/collection/generic/Companion;;
const #971 = NameAndType	#968:#970;//  companion:(Lscala/collection/Vector;)Lscala/collection/generic/Companion;
const #972 = Method	#95.#971;	//  scala/collection/Vector$class.companion:(Lscala/collection/Vector;)Lscala/collection/generic/Companion;
const #973 = Asciz	splitAt;
const #974 = Asciz	(I)Lscala/Tuple2;;
const #975 = Asciz	(Lscala/collection/generic/TraversableViewTemplate;I)Lscala/Tuple2;;
const #976 = NameAndType	#973:#975;//  splitAt:(Lscala/collection/generic/TraversableViewTemplate;I)Lscala/Tuple2;
const #977 = Method	#100.#976;	//  scala/collection/generic/TraversableViewTemplate$class.splitAt:(Lscala/collection/generic/TraversableViewTemplate;I)Lscala/Tuple2;
const #978 = Asciz	span;
const #979 = Asciz	(Lscala/collection/generic/TraversableViewTemplate;Lscala/Function1;)Lscala/Tuple2;;
const #980 = NameAndType	#978:#979;//  span:(Lscala/collection/generic/TraversableViewTemplate;Lscala/Function1;)Lscala/Tuple2;
const #981 = Method	#100.#980;	//  scala/collection/generic/TraversableViewTemplate$class.span:(Lscala/collection/generic/TraversableViewTemplate;Lscala/Function1;)Lscala/Tuple2;
const #982 = Asciz	(Lscala/collection/generic/TraversableViewTemplate;Lscala/Function1;)Lscala/collection/generic/TraversableView;;
const #983 = NameAndType	#383:#982;//  takeWhile:(Lscala/collection/generic/TraversableViewTemplate;Lscala/Function1;)Lscala/collection/generic/TraversableView;
const #984 = Method	#100.#983;	//  scala/collection/generic/TraversableViewTemplate$class.takeWhile:(Lscala/collection/generic/TraversableViewTemplate;Lscala/Function1;)Lscala/collection/generic/TraversableView;
const #985 = NameAndType	#379:#982;//  dropWhile:(Lscala/collection/generic/TraversableViewTemplate;Lscala/Function1;)Lscala/collection/generic/TraversableView;
const #986 = Method	#100.#985;	//  scala/collection/generic/TraversableViewTemplate$class.dropWhile:(Lscala/collection/generic/TraversableViewTemplate;Lscala/Function1;)Lscala/collection/generic/TraversableView;
const #987 = Asciz	(Lscala/collection/generic/TraversableViewTemplate;II)Lscala/collection/generic/TraversableView;;
const #988 = NameAndType	#371:#987;//  slice:(Lscala/collection/generic/TraversableViewTemplate;II)Lscala/collection/generic/TraversableView;
const #989 = Method	#100.#988;	//  scala/collection/generic/TraversableViewTemplate$class.slice:(Lscala/collection/generic/TraversableViewTemplate;II)Lscala/collection/generic/TraversableView;
const #990 = Asciz	(Lscala/collection/generic/TraversableViewTemplate;I)Lscala/collection/generic/TraversableView;;
const #991 = NameAndType	#368:#990;//  take:(Lscala/collection/generic/TraversableViewTemplate;I)Lscala/collection/generic/TraversableView;
const #992 = Method	#100.#991;	//  scala/collection/generic/TraversableViewTemplate$class.take:(Lscala/collection/generic/TraversableViewTemplate;I)Lscala/collection/generic/TraversableView;
const #993 = NameAndType	#361:#990;//  drop:(Lscala/collection/generic/TraversableViewTemplate;I)Lscala/collection/generic/TraversableView;
const #994 = Method	#100.#993;	//  scala/collection/generic/TraversableViewTemplate$class.drop:(Lscala/collection/generic/TraversableViewTemplate;I)Lscala/collection/generic/TraversableView;
const #995 = Asciz	(Lscala/collection/generic/TraversableViewTemplate;)Lscala/collection/generic/TraversableView;;
const #996 = NameAndType	#356:#995;//  init:(Lscala/collection/generic/TraversableViewTemplate;)Lscala/collection/generic/TraversableView;
const #997 = Method	#100.#996;	//  scala/collection/generic/TraversableViewTemplate$class.init:(Lscala/collection/generic/TraversableViewTemplate;)Lscala/collection/generic/TraversableView;
const #998 = NameAndType	#349:#982;//  filter:(Lscala/collection/generic/TraversableViewTemplate;Lscala/Function1;)Lscala/collection/generic/TraversableView;
const #999 = Method	#100.#998;	//  scala/collection/generic/TraversableViewTemplate$class.filter:(Lscala/collection/generic/TraversableViewTemplate;Lscala/Function1;)Lscala/collection/generic/TraversableView;
const #1000 = Asciz	flatMap;
const #1001 = Asciz	(Lscala/Function1;Lscala/collection/generic/BuilderFactory;)Ljava/lang/Object;;
const #1002 = Asciz	(Lscala/collection/generic/TraversableViewTemplate;Lscala/Function1;Lscala/collection/generic/BuilderFactory;)Ljava/lang/Object;;
const #1003 = NameAndType	#1000:#1002;//  flatMap:(Lscala/collection/generic/TraversableViewTemplate;Lscala/Function1;Lscala/collection/generic/BuilderFactory;)Ljava/lang/Object;
const #1004 = Method	#100.#1003;	//  scala/collection/generic/TraversableViewTemplate$class.flatMap:(Lscala/collection/generic/TraversableViewTemplate;Lscala/Function1;Lscala/collection/generic/BuilderFactory;)Ljava/lang/Object;
const #1005 = Asciz	map;
const #1006 = NameAndType	#1005:#1002;//  map:(Lscala/collection/generic/TraversableViewTemplate;Lscala/Function1;Lscala/collection/generic/BuilderFactory;)Ljava/lang/Object;
const #1007 = Method	#100.#1006;	//  scala/collection/generic/TraversableViewTemplate$class.map:(Lscala/collection/generic/TraversableViewTemplate;Lscala/Function1;Lscala/collection/generic/BuilderFactory;)Ljava/lang/Object;
const #1008 = Asciz	$plus$plus;
const #1009 = Asciz	(Lscala/collection/Iterator;Lscala/collection/generic/BuilderFactory;)Ljava/lang/Object;;
const #1010 = Asciz	(Lscala/collection/generic/TraversableViewTemplate;Lscala/collection/Iterator;Lscala/collection/generic/BuilderFactory;)Ljava/lang/Object;;
const #1011 = NameAndType	#1008:#1010;//  $plus$plus:(Lscala/collection/generic/TraversableViewTemplate;Lscala/collection/Iterator;Lscala/collection/generic/BuilderFactory;)Ljava/lang/Object;
const #1012 = Method	#100.#1011;	//  scala/collection/generic/TraversableViewTemplate$class.$plus$plus:(Lscala/collection/generic/TraversableViewTemplate;Lscala/collection/Iterator;Lscala/collection/generic/BuilderFactory;)Ljava/lang/Object;
const #1013 = Asciz	Lscala/collection/Iterator;;
const #1014 = Asciz	(Lscala/collection/Traversable;Lscala/collection/generic/BuilderFactory;)Ljava/lang/Object;;
const #1015 = Asciz	(Lscala/collection/generic/TraversableViewTemplate;Lscala/collection/Traversable;Lscala/collection/generic/BuilderFactory;)Ljava/lang/Object;;
const #1016 = NameAndType	#1008:#1015;//  $plus$plus:(Lscala/collection/generic/TraversableViewTemplate;Lscala/collection/Traversable;Lscala/collection/generic/BuilderFactory;)Ljava/lang/Object;
const #1017 = Method	#100.#1016;	//  scala/collection/generic/TraversableViewTemplate$class.$plus$plus:(Lscala/collection/generic/TraversableViewTemplate;Lscala/collection/Traversable;Lscala/collection/generic/BuilderFactory;)Ljava/lang/Object;
const #1018 = Asciz	force;
const #1019 = Asciz	(Lscala/collection/generic/BuilderFactory;)Ljava/lang/Object;;
const #1020 = Asciz	(Lscala/collection/generic/TraversableViewTemplate;Lscala/collection/generic/BuilderFactory;)Ljava/lang/Object;;
const #1021 = NameAndType	#1018:#1020;//  force:(Lscala/collection/generic/TraversableViewTemplate;Lscala/collection/generic/BuilderFactory;)Ljava/lang/Object;
const #1022 = Method	#100.#1021;	//  scala/collection/generic/TraversableViewTemplate$class.force:(Lscala/collection/generic/TraversableViewTemplate;Lscala/collection/generic/BuilderFactory;)Ljava/lang/Object;
const #1023 = Asciz	newBuilder;
const #1024 = Asciz	(Lscala/collection/generic/TraversableViewTemplate;)Lscala/collection/generic/Builder;;
const #1025 = NameAndType	#1023:#1024;//  newBuilder:(Lscala/collection/generic/TraversableViewTemplate;)Lscala/collection/generic/Builder;
const #1026 = Method	#100.#1025;	//  scala/collection/generic/TraversableViewTemplate$class.newBuilder:(Lscala/collection/generic/TraversableViewTemplate;)Lscala/collection/generic/Builder;
const #1027 = Asciz	zipAll;
const #1028 = Asciz	(Lscala/collection/Sequence;Ljava/lang/Object;Ljava/lang/Object;Lscala/collection/generic/BuilderFactory;)Ljava/lang/Object;;
const #1029 = Asciz	(Lscala/collection/generic/SequenceViewTemplate;Lscala/collection/Sequence;Ljava/lang/Object;Ljava/lang/Object;Lscala/collection/generic/BuilderFactory;)Ljava/lang/Object;;
const #1030 = NameAndType	#1027:#1029;//  zipAll:(Lscala/collection/generic/SequenceViewTemplate;Lscala/collection/Sequence;Ljava/lang/Object;Ljava/lang/Object;Lscala/collection/generic/BuilderFactory;)Ljava/lang/Object;
const #1031 = Method	#110.#1030;	//  scala/collection/generic/SequenceViewTemplate$class.zipAll:(Lscala/collection/generic/SequenceViewTemplate;Lscala/collection/Sequence;Ljava/lang/Object;Ljava/lang/Object;Lscala/collection/generic/BuilderFactory;)Ljava/lang/Object;
const #1032 = Asciz	thisElem;
const #1033 = Asciz	thatElem;
const #1034 = Asciz	zipWithIndex;
const #1035 = Asciz	(Lscala/collection/generic/SequenceViewTemplate;Lscala/collection/generic/BuilderFactory;)Ljava/lang/Object;;
const #1036 = NameAndType	#1034:#1035;//  zipWithIndex:(Lscala/collection/generic/SequenceViewTemplate;Lscala/collection/generic/BuilderFactory;)Ljava/lang/Object;
const #1037 = Method	#110.#1036;	//  scala/collection/generic/SequenceViewTemplate$class.zipWithIndex:(Lscala/collection/generic/SequenceViewTemplate;Lscala/collection/generic/BuilderFactory;)Ljava/lang/Object;
const #1038 = Asciz	(Lscala/collection/generic/SequenceViewTemplate;Lscala/collection/Sequence;Lscala/collection/generic/BuilderFactory;)Ljava/lang/Object;;
const #1039 = NameAndType	#957:#1038;//  zip:(Lscala/collection/generic/SequenceViewTemplate;Lscala/collection/Sequence;Lscala/collection/generic/BuilderFactory;)Ljava/lang/Object;
const #1040 = Method	#110.#1039;	//  scala/collection/generic/SequenceViewTemplate$class.zip:(Lscala/collection/generic/SequenceViewTemplate;Lscala/collection/Sequence;Lscala/collection/generic/BuilderFactory;)Ljava/lang/Object;
const #1041 = Asciz	padTo;
const #1042 = Asciz	(ILjava/lang/Object;Lscala/collection/generic/BuilderFactory;)Ljava/lang/Object;;
const #1043 = Asciz	(Lscala/collection/generic/SequenceViewTemplate;ILjava/lang/Object;Lscala/collection/generic/BuilderFactory;)Ljava/lang/Object;;
const #1044 = NameAndType	#1041:#1043;//  padTo:(Lscala/collection/generic/SequenceViewTemplate;ILjava/lang/Object;Lscala/collection/generic/BuilderFactory;)Ljava/lang/Object;
const #1045 = Method	#110.#1044;	//  scala/collection/generic/SequenceViewTemplate$class.padTo:(Lscala/collection/generic/SequenceViewTemplate;ILjava/lang/Object;Lscala/collection/generic/BuilderFactory;)Ljava/lang/Object;
const #1046 = Asciz	patch;
const #1047 = Asciz	(ILscala/collection/Sequence;ILscala/collection/generic/BuilderFactory;)Ljava/lang/Object;;
const #1048 = Asciz	(Lscala/collection/generic/SequenceViewTemplate;ILscala/collection/Sequence;ILscala/collection/generic/BuilderFactory;)Ljava/lang/Object;;
const #1049 = NameAndType	#1046:#1048;//  patch:(Lscala/collection/generic/SequenceViewTemplate;ILscala/collection/Sequence;ILscala/collection/generic/BuilderFactory;)Ljava/lang/Object;
const #1050 = Method	#110.#1049;	//  scala/collection/generic/SequenceViewTemplate$class.patch:(Lscala/collection/generic/SequenceViewTemplate;ILscala/collection/Sequence;ILscala/collection/generic/BuilderFactory;)Ljava/lang/Object;
const #1051 = Asciz	replaced;
const #1052 = Asciz	(Lscala/collection/generic/SequenceViewTemplate;)Lscala/collection/generic/SequenceView;;
const #1053 = NameAndType	#339:#1052;//  reverse:(Lscala/collection/generic/SequenceViewTemplate;)Lscala/collection/generic/SequenceView;
const #1054 = Method	#110.#1053;	//  scala/collection/generic/SequenceViewTemplate$class.reverse:(Lscala/collection/generic/SequenceViewTemplate;)Lscala/collection/generic/SequenceView;
const #1055 = Asciz	(Lscala/collection/generic/VectorViewTemplate;Lscala/collection/Sequence;)Lscala/collection/generic/VectorViewTemplate$Transformed;;
const #1056 = NameAndType	#334:#1055;//  newZipped:(Lscala/collection/generic/VectorViewTemplate;Lscala/collection/Sequence;)Lscala/collection/generic/VectorViewTemplate$Transformed;
const #1057 = Method	#115.#1056;	//  scala/collection/generic/VectorViewTemplate$class.newZipped:(Lscala/collection/generic/VectorViewTemplate;Lscala/collection/Sequence;)Lscala/collection/generic/VectorViewTemplate$Transformed;
const #1058 = Asciz	(Lscala/collection/generic/VectorViewTemplate;ILscala/collection/Sequence;I)Lscala/collection/generic/VectorViewTemplate$Transformed;;
const #1059 = NameAndType	#326:#1058;//  newPatched:(Lscala/collection/generic/VectorViewTemplate;ILscala/collection/Sequence;I)Lscala/collection/generic/VectorViewTemplate$Transformed;
const #1060 = Method	#115.#1059;	//  scala/collection/generic/VectorViewTemplate$class.newPatched:(Lscala/collection/generic/VectorViewTemplate;ILscala/collection/Sequence;I)Lscala/collection/generic/VectorViewTemplate$Transformed;
const #1061 = Asciz	(Lscala/collection/generic/VectorViewTemplate;)Lscala/collection/generic/VectorViewTemplate$Transformed;;
const #1062 = NameAndType	#321:#1061;//  newReversed:(Lscala/collection/generic/VectorViewTemplate;)Lscala/collection/generic/VectorViewTemplate$Transformed;
const #1063 = Method	#115.#1062;	//  scala/collection/generic/VectorViewTemplate$class.newReversed:(Lscala/collection/generic/VectorViewTemplate;)Lscala/collection/generic/VectorViewTemplate$Transformed;
const #1064 = Asciz	(Lscala/collection/generic/VectorViewTemplate;Lscala/Function1;)Lscala/collection/generic/VectorViewTemplate$Transformed;;
const #1065 = NameAndType	#318:#1064;//  newTakenWhile:(Lscala/collection/generic/VectorViewTemplate;Lscala/Function1;)Lscala/collection/generic/VectorViewTemplate$Transformed;
const #1066 = Method	#115.#1065;	//  scala/collection/generic/VectorViewTemplate$class.newTakenWhile:(Lscala/collection/generic/VectorViewTemplate;Lscala/Function1;)Lscala/collection/generic/VectorViewTemplate$Transformed;
const #1067 = NameAndType	#315:#1064;//  newDroppedWhile:(Lscala/collection/generic/VectorViewTemplate;Lscala/Function1;)Lscala/collection/generic/VectorViewTemplate$Transformed;
const #1068 = Method	#115.#1067;	//  scala/collection/generic/VectorViewTemplate$class.newDroppedWhile:(Lscala/collection/generic/VectorViewTemplate;Lscala/Function1;)Lscala/collection/generic/VectorViewTemplate$Transformed;
const #1069 = Asciz	(Lscala/collection/generic/VectorViewTemplate;II)Lscala/collection/generic/VectorViewTemplate$Transformed;;
const #1070 = NameAndType	#306:#1069;//  newSliced:(Lscala/collection/generic/VectorViewTemplate;II)Lscala/collection/generic/VectorViewTemplate$Transformed;
const #1071 = Method	#115.#1070;	//  scala/collection/generic/VectorViewTemplate$class.newSliced:(Lscala/collection/generic/VectorViewTemplate;II)Lscala/collection/generic/VectorViewTemplate$Transformed;
const #1072 = NameAndType	#302:#1064;//  newFiltered:(Lscala/collection/generic/VectorViewTemplate;Lscala/Function1;)Lscala/collection/generic/VectorViewTemplate$Transformed;
const #1073 = Method	#115.#1072;	//  scala/collection/generic/VectorViewTemplate$class.newFiltered:(Lscala/collection/generic/VectorViewTemplate;Lscala/Function1;)Lscala/collection/generic/VectorViewTemplate$Transformed;
const #1074 = NameAndType	#299:#1064;//  newFlatMapped:(Lscala/collection/generic/VectorViewTemplate;Lscala/Function1;)Lscala/collection/generic/VectorViewTemplate$Transformed;
const #1075 = Method	#115.#1074;	//  scala/collection/generic/VectorViewTemplate$class.newFlatMapped:(Lscala/collection/generic/VectorViewTemplate;Lscala/Function1;)Lscala/collection/generic/VectorViewTemplate$Transformed;
const #1076 = NameAndType	#290:#1064;//  newMapped:(Lscala/collection/generic/VectorViewTemplate;Lscala/Function1;)Lscala/collection/generic/VectorViewTemplate$Transformed;
const #1077 = Method	#115.#1076;	//  scala/collection/generic/VectorViewTemplate$class.newMapped:(Lscala/collection/generic/VectorViewTemplate;Lscala/Function1;)Lscala/collection/generic/VectorViewTemplate$Transformed;
const #1078 = Asciz	(Lscala/collection/generic/VectorViewTemplate;Lscala/collection/Traversable;)Lscala/collection/generic/VectorViewTemplate$Transformed;;
const #1079 = NameAndType	#279:#1078;//  newAppended:(Lscala/collection/generic/VectorViewTemplate;Lscala/collection/Traversable;)Lscala/collection/generic/VectorViewTemplate$Transformed;
const #1080 = Method	#115.#1079;	//  scala/collection/generic/VectorViewTemplate$class.newAppended:(Lscala/collection/generic/VectorViewTemplate;Lscala/collection/Traversable;)Lscala/collection/generic/VectorViewTemplate$Transformed;
const #1081 = Asciz	(Lscala/RangeToString;)Ljava/lang/String;;
const #1082 = NameAndType	#467:#1081;//  toString:(Lscala/RangeToString;)Ljava/lang/String;
const #1083 = Method	#120.#1082;	//  scala/RangeToString$class.toString:(Lscala/RangeToString;)Ljava/lang/String;
const #1084 = Asciz	(Lscala/util/Hashable;Ljava/lang/Object;)Z;
const #1085 = NameAndType	#419:#1084;//  equalHashValues:(Lscala/util/Hashable;Ljava/lang/Object;)Z
const #1086 = Method	#125.#1085;	//  scala/util/Hashable$class.equalHashValues:(Lscala/util/Hashable;Ljava/lang/Object;)Z
const #1087 = Asciz	hashCode;
const #1088 = Asciz	(Lscala/util/Hashable;)I;
const #1089 = NameAndType	#1087:#1088;//  hashCode:(Lscala/util/Hashable;)I
const #1090 = Method	#125.#1089;	//  scala/util/Hashable$class.hashCode:(Lscala/util/Hashable;)I
const #1091 = Asciz	hashSeed;
const #1092 = NameAndType	#1091:#1088;//  hashSeed:(Lscala/util/Hashable;)I
const #1093 = Method	#125.#1092;	//  scala/util/Hashable$class.hashSeed:(Lscala/util/Hashable;)I
const #1094 = Asciz	<T:Ljava/lang/Object;>Ljava/lang/Object;Lscala/collection/generic/VectorView<TT;Lscala/collection/immutable/Vector<TT;>;>;Lscala/RangeToString<TT;>;Lscala/util/Hashable;Lscala/ScalaObject;;
const #1095 = Asciz	ScalaSig;
const #1096 = Asciz	InnerClasses;
const #1097 = Asciz	scala/Numeric$Ops;
const #1098 = class	#1097;	//  scala/Numeric$Ops
const #1099 = Asciz	Ops;
const #1100 = Asciz	scala/util/control/Exception;
const #1101 = class	#1100;	//  scala/util/control/Exception
const #1102 = Asciz	Catch;
const #1103 = Asciz	IntegralOps;
const #1104 = Asciz	scala/GenericRange$Inclusive;
const #1105 = class	#1104;	//  scala/GenericRange$Inclusive
const #1106 = Asciz	Inclusive;
const #1107 = Asciz	scala/GenericRange$Exclusive;
const #1108 = class	#1107;	//  scala/GenericRange$Exclusive
const #1109 = Asciz	Exclusive;
const #1110 = Asciz	$anonfun$1;
const #1111 = Asciz	scala/collection/generic/VectorViewTemplate$Transformed;
const #1112 = class	#1111;	//  scala/collection/generic/VectorViewTemplate$Transformed
const #1113 = Asciz	Transformed;
const #1114 = Asciz	$anonfun$contains$1;
const #1115 = Asciz	scala/collection/generic/IterableViewTemplate$Transformed;
const #1116 = class	#1115;	//  scala/collection/generic/IterableViewTemplate$Transformed
const #1117 = Asciz	scala/collection/generic/IterableViewTemplate;
const #1118 = class	#1117;	//  scala/collection/generic/IterableViewTemplate
const #1119 = Asciz	$anonfun$contains$2;
const #1120 = Asciz	scala/collection/generic/SequenceViewTemplate$Transformed;
const #1121 = class	#1120;	//  scala/collection/generic/SequenceViewTemplate$Transformed
const #1122 = Asciz	scala/collection/generic/TraversableViewTemplate$Transformed;
const #1123 = class	#1122;	//  scala/collection/generic/TraversableViewTemplate$Transformed
const #1124 = Asciz	scala/collection/generic/VectorView;
const #1125 = class	#1124;	//  scala/collection/generic/VectorView
const #1126 = Asciz	scala/RangeToString;
const #1127 = class	#1126;	//  scala/RangeToString
const #1128 = Asciz	scala/ScalaObject;
const #1129 = class	#1128;	//  scala/ScalaObject

{
public volatile int bitmap$0;

public scala.GenericRange(java.lang.Object, java.lang.Object, java.lang.Object, boolean, scala.Integral);
  Code:
   Stack=7, Locals=6, Args_size=6
   0:	aload_0
   1:	aload_1
   2:	putfield	#29; //Field start:Ljava/lang/Object;
   5:	aload_0
   6:	aload_2
   7:	putfield	#31; //Field end:Ljava/lang/Object;
   10:	aload_0
   11:	aload_3
   12:	putfield	#33; //Field step:Ljava/lang/Object;
   15:	aload_0
   16:	iload	4
   18:	putfield	#35; //Field isInclusive:Z
   21:	aload_0
   22:	aload	5
   24:	putfield	#37; //Field num:Lscala/Integral;
   27:	aload_0
   28:	invokespecial	#42; //Method java/lang/Object."<init>":()V
   31:	aload_0
   32:	invokestatic	#48; //Method scala/Function1$class.$init$:(Lscala/Function1;)V
   35:	aload_0
   36:	invokestatic	#53; //Method scala/PartialFunction$class.$init$:(Lscala/PartialFunction;)V
   39:	aload_0
   40:	invokestatic	#58; //Method scala/collection/generic/TraversableTemplate$class.$init$:(Lscala/collection/generic/TraversableTemplate;)V
   43:	aload_0
   44:	invokestatic	#63; //Method scala/collection/generic/TraversableClass$class.$init$:(Lscala/collection/generic/TraversableClass;)V
   47:	aload_0
   48:	invokestatic	#68; //Method scala/collection/Traversable$class.$init$:(Lscala/collection/Traversable;)V
   51:	aload_0
   52:	invokestatic	#73; //Method scala/collection/generic/IterableTemplate$class.$init$:(Lscala/collection/generic/IterableTemplate;)V
   55:	aload_0
   56:	invokestatic	#78; //Method scala/collection/Iterable$class.$init$:(Lscala/collection/Iterable;)V
   59:	aload_0
   60:	invokestatic	#83; //Method scala/collection/generic/SequenceTemplate$class.$init$:(Lscala/collection/generic/SequenceTemplate;)V
   63:	aload_0
   64:	invokestatic	#88; //Method scala/collection/Sequence$class.$init$:(Lscala/collection/Sequence;)V
   67:	aload_0
   68:	invokestatic	#93; //Method scala/collection/generic/VectorTemplate$class.$init$:(Lscala/collection/generic/VectorTemplate;)V
   71:	aload_0
   72:	invokestatic	#98; //Method scala/collection/Vector$class.$init$:(Lscala/collection/Vector;)V
   75:	aload_0
   76:	invokestatic	#103; //Method scala/collection/generic/TraversableViewTemplate$class.$init$:(Lscala/collection/generic/TraversableViewTemplate;)V
   79:	aload_0
   80:	invokestatic	#108; //Method scala/collection/generic/IterableViewTemplate$class.$init$:(Lscala/collection/generic/IterableViewTemplate;)V
   83:	aload_0
   84:	invokestatic	#113; //Method scala/collection/generic/SequenceViewTemplate$class.$init$:(Lscala/collection/generic/SequenceViewTemplate;)V
   87:	aload_0
   88:	invokestatic	#118; //Method scala/collection/generic/VectorViewTemplate$class.$init$:(Lscala/collection/generic/VectorViewTemplate;)V
   91:	aload_0
   92:	invokestatic	#123; //Method scala/RangeToString$class.$init$:(Lscala/RangeToString;)V
   95:	aload_0
   96:	invokestatic	#128; //Method scala/util/Hashable$class.$init$:(Lscala/util/Hashable;)V
   99:	getstatic	#134; //Field scala/Predef$.MODULE$:Lscala/Predef$;
   102:	aload	5
   104:	aload_3
   105:	invokeinterface	#140,  2; //InterfaceMethod scala/Ordering.mkOrderingOps:(Ljava/lang/Object;)Lscala/Ordering$Ops;
   110:	aload	5
   112:	invokeinterface	#146,  1; //InterfaceMethod scala/Numeric.zero:()Ljava/lang/Object;
   117:	invokevirtual	#152; //Method scala/Ordering$Ops.equiv:(Ljava/lang/Object;)Z
   120:	ifeq	127
   123:	iconst_0
   124:	goto	128
   127:	iconst_1
   128:	invokevirtual	#156; //Method scala/Predef$.require:(Z)V
   131:	getstatic	#134; //Field scala/Predef$.MODULE$:Lscala/Predef$;
   134:	aload	5
   136:	aload_0
   137:	invokevirtual	#158; //Method genericLength:()Ljava/lang/Object;
   140:	invokeinterface	#140,  2; //InterfaceMethod scala/Ordering.mkOrderingOps:(Ljava/lang/Object;)Lscala/Ordering$Ops;
   145:	aload	5
   147:	getstatic	#163; //Field scala/Math$.MODULE$:Lscala/Math$;
   150:	invokevirtual	#167; //Method scala/Math$.MAX_INT:()I
   153:	invokeinterface	#171,  2; //InterfaceMethod scala/Numeric.fromInt:(I)Ljava/lang/Object;
   158:	invokevirtual	#174; //Method scala/Ordering$Ops.$less$eq:(Ljava/lang/Object;)Z
   161:	new	#176; //class scala/GenericRange$$anonfun$1
   164:	dup
   165:	aload_0
   166:	invokespecial	#179; //Method scala/GenericRange$$anonfun$1."<init>":(Lscala/GenericRange;)V
   169:	invokevirtual	#182; //Method scala/Predef$.require:(ZLscala/Function0;)V
   172:	aload_0
   173:	getstatic	#187; //Field scala/collection/immutable/List$.MODULE$:Lscala/collection/immutable/List$;
   176:	getstatic	#192; //Field scala/runtime/ScalaRunTime$.MODULE$:Lscala/runtime/ScalaRunTime$;
   179:	iconst_3
   180:	anewarray	#39; //class java/lang/Object
   183:	dup
   184:	iconst_0
   185:	aload_1
   186:	aastore
   187:	dup
   188:	iconst_1
   189:	aload_0
   190:	invokespecial	#194; //Method trueEnd:()Ljava/lang/Object;
   193:	aastore
   194:	dup
   195:	iconst_2
   196:	aload_3
   197:	aastore
   198:	invokevirtual	#198; //Method scala/runtime/ScalaRunTime$.boxArray:(Ljava/lang/Object;)Lscala/runtime/BoxedArray;
   201:	invokevirtual	#202; //Method scala/collection/immutable/List$.apply:(Lscala/collection/Sequence;)Lscala/collection/immutable/List;
   204:	putfield	#204; //Field hashValues:Lscala/collection/immutable/List;
   207:	return
  LineNumberTable: 
   line 40: 0
   line 41: 21
   line 40: 27
   line 48: 99
   line 49: 131
   line 125: 172

  LocalVariableTable: 
   Start  Length  Slot  Name   Signature
   0      208      0    this       Lscala/GenericRange;
   0      208      1    start       Ljava/lang/Object;
   0      208      2    end       Ljava/lang/Object;
   0      208      3    step       Ljava/lang/Object;
   0      208      4    isInclusive       Z
   0      208      5    num       Lscala/Integral;

  Signature: length = 0x2
   00 FFFFFFD0 

public final boolean doContains$1(java.lang.Object);
  Code:
   Stack=2, Locals=5, Args_size=2
   0:	aload_1
   1:	astore_3
   2:	aload_3
   3:	instanceof	#211; //class java/lang/Integer
   6:	ifeq	29
   9:	aload_3
   10:	invokestatic	#217; //Method scala/runtime/BoxesRunTime.unboxToInt:(Ljava/lang/Object;)I
   13:	istore	4
   15:	aload_0
   16:	getfield	#37; //Field num:Lscala/Integral;
   19:	iload	4
   21:	invokeinterface	#171,  2; //InterfaceMethod scala/Numeric.fromInt:(I)Ljava/lang/Object;
   26:	goto	30
   29:	aload_1
   30:	astore_2
   31:	aload_0
   32:	aload_2
   33:	invokespecial	#220; //Method withinRange$1:(Ljava/lang/Object;)Z
   36:	ifeq	51
   39:	aload_0
   40:	aload_2
   41:	invokespecial	#223; //Method matchesStep$1:(Ljava/lang/Object;)Z
   44:	ifeq	51
   47:	iconst_1
   48:	goto	52
   51:	iconst_0
   52:	ireturn
  LineNumberTable: 
   line 109: 0
   line 110: 15
   line 111: 29
   line 109: 30
   line 118: 31
   line 106: 52

  LocalVariableTable: 
   Start  Length  Slot  Name   Signature
   0      53      0    this       Lscala/GenericRange;
   31      22      2    x$1       Ljava/lang/Object;
   2      37      3    temp1       Ljava/lang/Object;
   15      11      4    temp2       I


public scala.collection.Traversable underlying();
  Code:
   Stack=1, Locals=1, Args_size=1
   0:	aload_0
   1:	invokevirtual	#271; //Method underlying:()Lscala/collection/immutable/Vector;
   4:	areturn
  LineNumberTable: 
   line 39: 0


public java.lang.Object apply(java.lang.Object);
  Code:
   Stack=2, Locals=2, Args_size=2
   0:	aload_0
   1:	aload_1
   2:	invokestatic	#217; //Method scala/runtime/BoxesRunTime.unboxToInt:(Ljava/lang/Object;)I
   5:	invokevirtual	#273; //Method apply:(I)Ljava/lang/Object;
   8:	areturn
  LineNumberTable: 
   line 39: 0

  LocalVariableTable: 
   Start  Length  Slot  Name   Signature
   0      9      0    this       Lscala/GenericRange;
   0      9      1    v1       Ljava/lang/Object;


public scala.collection.Sequence hashValues();
  Code:
   Stack=1, Locals=1, Args_size=1
   0:	aload_0
   1:	invokevirtual	#278; //Method hashValues:()Lscala/collection/immutable/List;
   4:	areturn
  LineNumberTable: 
   line 39: 0


public scala.collection.generic.SequenceViewTemplate$Transformed newAppended(scala.collection.Traversable);
  Code:
   Stack=2, Locals=2, Args_size=2
   0:	aload_0
   1:	aload_1
   2:	invokeinterface	#285,  2; //InterfaceMethod scala/collection/generic/VectorViewTemplate.newAppended:(Lscala/collection/Traversable;)Lscala/collection/generic/VectorViewTemplate$Transformed;
   7:	areturn
  LineNumberTable: 
   line 39: 0

  LocalVariableTable: 
   Start  Length  Slot  Name   Signature
   0      8      0    this       Lscala/GenericRange;
   0      8      1    that       Lscala/collection/Traversable;


public scala.collection.generic.IterableViewTemplate$Transformed newAppended(scala.collection.Traversable);
  Code:
   Stack=2, Locals=2, Args_size=2
   0:	aload_0
   1:	aload_1
   2:	invokeinterface	#285,  2; //InterfaceMethod scala/collection/generic/VectorViewTemplate.newAppended:(Lscala/collection/Traversable;)Lscala/collection/generic/VectorViewTemplate$Transformed;
   7:	areturn
  LineNumberTable: 
   line 39: 0

  LocalVariableTable: 
   Start  Length  Slot  Name   Signature
   0      8      0    this       Lscala/GenericRange;
   0      8      1    that       Lscala/collection/Traversable;


public scala.collection.generic.TraversableViewTemplate$Transformed newAppended(scala.collection.Traversable);
  Code:
   Stack=2, Locals=2, Args_size=2
   0:	aload_0
   1:	aload_1
   2:	invokeinterface	#285,  2; //InterfaceMethod scala/collection/generic/VectorViewTemplate.newAppended:(Lscala/collection/Traversable;)Lscala/collection/generic/VectorViewTemplate$Transformed;
   7:	areturn
  LineNumberTable: 
   line 39: 0

  LocalVariableTable: 
   Start  Length  Slot  Name   Signature
   0      8      0    this       Lscala/GenericRange;
   0      8      1    that       Lscala/collection/Traversable;


public scala.collection.generic.SequenceViewTemplate$Transformed newMapped(scala.Function1);
  Code:
   Stack=2, Locals=2, Args_size=2
   0:	aload_0
   1:	aload_1
   2:	invokeinterface	#294,  2; //InterfaceMethod scala/collection/generic/VectorViewTemplate.newMapped:(Lscala/Function1;)Lscala/collection/generic/VectorViewTemplate$Transformed;
   7:	areturn
  LineNumberTable: 
   line 39: 0

  LocalVariableTable: 
   Start  Length  Slot  Name   Signature
   0      8      0    this       Lscala/GenericRange;
   0      8      1    f       Lscala/Function1;


public scala.collection.generic.IterableViewTemplate$Transformed newMapped(scala.Function1);
  Code:
   Stack=2, Locals=2, Args_size=2
   0:	aload_0
   1:	aload_1
   2:	invokeinterface	#294,  2; //InterfaceMethod scala/collection/generic/VectorViewTemplate.newMapped:(Lscala/Function1;)Lscala/collection/generic/VectorViewTemplate$Transformed;
   7:	areturn
  LineNumberTable: 
   line 39: 0

  LocalVariableTable: 
   Start  Length  Slot  Name   Signature
   0      8      0    this       Lscala/GenericRange;
   0      8      1    f       Lscala/Function1;


public scala.collection.generic.TraversableViewTemplate$Transformed newMapped(scala.Function1);
  Code:
   Stack=2, Locals=2, Args_size=2
   0:	aload_0
   1:	aload_1
   2:	invokeinterface	#294,  2; //InterfaceMethod scala/collection/generic/VectorViewTemplate.newMapped:(Lscala/Function1;)Lscala/collection/generic/VectorViewTemplate$Transformed;
   7:	areturn
  LineNumberTable: 
   line 39: 0

  LocalVariableTable: 
   Start  Length  Slot  Name   Signature
   0      8      0    this       Lscala/GenericRange;
   0      8      1    f       Lscala/Function1;


public scala.collection.generic.SequenceViewTemplate$Transformed newFlatMapped(scala.Function1);
  Code:
   Stack=2, Locals=2, Args_size=2
   0:	aload_0
   1:	aload_1
   2:	invokeinterface	#301,  2; //InterfaceMethod scala/collection/generic/VectorViewTemplate.newFlatMapped:(Lscala/Function1;)Lscala/collection/generic/VectorViewTemplate$Transformed;
   7:	areturn
  LineNumberTable: 
   line 39: 0

  LocalVariableTable: 
   Start  Length  Slot  Name   Signature
   0      8      0    this       Lscala/GenericRange;
   0      8      1    f       Lscala/Function1;


public scala.collection.generic.IterableViewTemplate$Transformed newFlatMapped(scala.Function1);
  Code:
   Stack=2, Locals=2, Args_size=2
   0:	aload_0
   1:	aload_1
   2:	invokeinterface	#301,  2; //InterfaceMethod scala/collection/generic/VectorViewTemplate.newFlatMapped:(Lscala/Function1;)Lscala/collection/generic/VectorViewTemplate$Transformed;
   7:	areturn
  LineNumberTable: 
   line 39: 0

  LocalVariableTable: 
   Start  Length  Slot  Name   Signature
   0      8      0    this       Lscala/GenericRange;
   0      8      1    f       Lscala/Function1;


public scala.collection.generic.TraversableViewTemplate$Transformed newFlatMapped(scala.Function1);
  Code:
   Stack=2, Locals=2, Args_size=2
   0:	aload_0
   1:	aload_1
   2:	invokeinterface	#301,  2; //InterfaceMethod scala/collection/generic/VectorViewTemplate.newFlatMapped:(Lscala/Function1;)Lscala/collection/generic/VectorViewTemplate$Transformed;
   7:	areturn
  LineNumberTable: 
   line 39: 0

  LocalVariableTable: 
   Start  Length  Slot  Name   Signature
   0      8      0    this       Lscala/GenericRange;
   0      8      1    f       Lscala/Function1;


public scala.collection.generic.SequenceViewTemplate$Transformed newFiltered(scala.Function1);
  Code:
   Stack=2, Locals=2, Args_size=2
   0:	aload_0
   1:	aload_1
   2:	invokeinterface	#304,  2; //InterfaceMethod scala/collection/generic/VectorViewTemplate.newFiltered:(Lscala/Function1;)Lscala/collection/generic/VectorViewTemplate$Transformed;
   7:	areturn
  LineNumberTable: 
   line 39: 0

  LocalVariableTable: 
   Start  Length  Slot  Name   Signature
   0      8      0    this       Lscala/GenericRange;
   0      8      1    p       Lscala/Function1;


public scala.collection.generic.IterableViewTemplate$Transformed newFiltered(scala.Function1);
  Code:
   Stack=2, Locals=2, Args_size=2
   0:	aload_0
   1:	aload_1
   2:	invokeinterface	#304,  2; //InterfaceMethod scala/collection/generic/VectorViewTemplate.newFiltered:(Lscala/Function1;)Lscala/collection/generic/VectorViewTemplate$Transformed;
   7:	areturn
  LineNumberTable: 
   line 39: 0

  LocalVariableTable: 
   Start  Length  Slot  Name   Signature
   0      8      0    this       Lscala/GenericRange;
   0      8      1    p       Lscala/Function1;


public scala.collection.generic.TraversableViewTemplate$Transformed newFiltered(scala.Function1);
  Code:
   Stack=2, Locals=2, Args_size=2
   0:	aload_0
   1:	aload_1
   2:	invokeinterface	#304,  2; //InterfaceMethod scala/collection/generic/VectorViewTemplate.newFiltered:(Lscala/Function1;)Lscala/collection/generic/VectorViewTemplate$Transformed;
   7:	areturn
  LineNumberTable: 
   line 39: 0

  LocalVariableTable: 
   Start  Length  Slot  Name   Signature
   0      8      0    this       Lscala/GenericRange;
   0      8      1    p       Lscala/Function1;


public scala.collection.generic.SequenceViewTemplate$Transformed newSliced(int, int);
  Code:
   Stack=3, Locals=3, Args_size=3
   0:	aload_0
   1:	iload_1
   2:	iload_2
   3:	invokeinterface	#310,  3; //InterfaceMethod scala/collection/generic/VectorViewTemplate.newSliced:(II)Lscala/collection/generic/VectorViewTemplate$Transformed;
   8:	areturn
  LineNumberTable: 
   line 39: 0

  LocalVariableTable: 
   Start  Length  Slot  Name   Signature
   0      9      0    this       Lscala/GenericRange;
   0      9      1    _from       I
   0      9      2    _until       I


public scala.collection.generic.IterableViewTemplate$Transformed newSliced(int, int);
  Code:
   Stack=3, Locals=3, Args_size=3
   0:	aload_0
   1:	iload_1
   2:	iload_2
   3:	invokeinterface	#310,  3; //InterfaceMethod scala/collection/generic/VectorViewTemplate.newSliced:(II)Lscala/collection/generic/VectorViewTemplate$Transformed;
   8:	areturn
  LineNumberTable: 
   line 39: 0

  LocalVariableTable: 
   Start  Length  Slot  Name   Signature
   0      9      0    this       Lscala/GenericRange;
   0      9      1    _from       I
   0      9      2    _until       I


public scala.collection.generic.TraversableViewTemplate$Transformed newSliced(int, int);
  Code:
   Stack=3, Locals=3, Args_size=3
   0:	aload_0
   1:	iload_1
   2:	iload_2
   3:	invokeinterface	#310,  3; //InterfaceMethod scala/collection/generic/VectorViewTemplate.newSliced:(II)Lscala/collection/generic/VectorViewTemplate$Transformed;
   8:	areturn
  LineNumberTable: 
   line 39: 0

  LocalVariableTable: 
   Start  Length  Slot  Name   Signature
   0      9      0    this       Lscala/GenericRange;
   0      9      1    _from       I
   0      9      2    _until       I


public scala.collection.generic.SequenceViewTemplate$Transformed newDroppedWhile(scala.Function1);
  Code:
   Stack=2, Locals=2, Args_size=2
   0:	aload_0
   1:	aload_1
   2:	invokeinterface	#317,  2; //InterfaceMethod scala/collection/generic/VectorViewTemplate.newDroppedWhile:(Lscala/Function1;)Lscala/collection/generic/VectorViewTemplate$Transformed;
   7:	areturn
  LineNumberTable: 
   line 39: 0

  LocalVariableTable: 
   Start  Length  Slot  Name   Signature
   0      8      0    this       Lscala/GenericRange;
   0      8      1    p       Lscala/Function1;


public scala.collection.generic.IterableViewTemplate$Transformed newDroppedWhile(scala.Function1);
  Code:
   Stack=2, Locals=2, Args_size=2
   0:	aload_0
   1:	aload_1
   2:	invokeinterface	#317,  2; //InterfaceMethod scala/collection/generic/VectorViewTemplate.newDroppedWhile:(Lscala/Function1;)Lscala/collection/generic/VectorViewTemplate$Transformed;
   7:	areturn
  LineNumberTable: 
   line 39: 0

  LocalVariableTable: 
   Start  Length  Slot  Name   Signature
   0      8      0    this       Lscala/GenericRange;
   0      8      1    p       Lscala/Function1;


public scala.collection.generic.TraversableViewTemplate$Transformed newDroppedWhile(scala.Function1);
  Code:
   Stack=2, Locals=2, Args_size=2
   0:	aload_0
   1:	aload_1
   2:	invokeinterface	#317,  2; //InterfaceMethod scala/collection/generic/VectorViewTemplate.newDroppedWhile:(Lscala/Function1;)Lscala/collection/generic/VectorViewTemplate$Transformed;
   7:	areturn
  LineNumberTable: 
   line 39: 0

  LocalVariableTable: 
   Start  Length  Slot  Name   Signature
   0      8      0    this       Lscala/GenericRange;
   0      8      1    p       Lscala/Function1;


public scala.collection.generic.SequenceViewTemplate$Transformed newTakenWhile(scala.Function1);
  Code:
   Stack=2, Locals=2, Args_size=2
   0:	aload_0
   1:	aload_1
   2:	invokeinterface	#320,  2; //InterfaceMethod scala/collection/generic/VectorViewTemplate.newTakenWhile:(Lscala/Function1;)Lscala/collection/generic/VectorViewTemplate$Transformed;
   7:	areturn
  LineNumberTable: 
   line 39: 0

  LocalVariableTable: 
   Start  Length  Slot  Name   Signature
   0      8      0    this       Lscala/GenericRange;
   0      8      1    p       Lscala/Function1;


public scala.collection.generic.IterableViewTemplate$Transformed newTakenWhile(scala.Function1);
  Code:
   Stack=2, Locals=2, Args_size=2
   0:	aload_0
   1:	aload_1
   2:	invokeinterface	#320,  2; //InterfaceMethod scala/collection/generic/VectorViewTemplate.newTakenWhile:(Lscala/Function1;)Lscala/collection/generic/VectorViewTemplate$Transformed;
   7:	areturn
  LineNumberTable: 
   line 39: 0

  LocalVariableTable: 
   Start  Length  Slot  Name   Signature
   0      8      0    this       Lscala/GenericRange;
   0      8      1    p       Lscala/Function1;


public scala.collection.generic.TraversableViewTemplate$Transformed newTakenWhile(scala.Function1);
  Code:
   Stack=2, Locals=2, Args_size=2
   0:	aload_0
   1:	aload_1
   2:	invokeinterface	#320,  2; //InterfaceMethod scala/collection/generic/VectorViewTemplate.newTakenWhile:(Lscala/Function1;)Lscala/collection/generic/VectorViewTemplate$Transformed;
   7:	areturn
  LineNumberTable: 
   line 39: 0

  LocalVariableTable: 
   Start  Length  Slot  Name   Signature
   0      8      0    this       Lscala/GenericRange;
   0      8      1    p       Lscala/Function1;


public scala.collection.generic.SequenceViewTemplate$Transformed newReversed();
  Code:
   Stack=1, Locals=1, Args_size=1
   0:	aload_0
   1:	invokeinterface	#325,  1; //InterfaceMethod scala/collection/generic/VectorViewTemplate.newReversed:()Lscala/collection/generic/VectorViewTemplate$Transformed;
   6:	areturn
  LineNumberTable: 
   line 39: 0


public scala.collection.generic.SequenceViewTemplate$Transformed newPatched(int, scala.collection.Sequence, int);
  Code:
   Stack=4, Locals=4, Args_size=4
   0:	aload_0
   1:	iload_1
   2:	aload_2
   3:	iload_3
   4:	invokeinterface	#330,  4; //InterfaceMethod scala/collection/generic/VectorViewTemplate.newPatched:(ILscala/collection/Sequence;I)Lscala/collection/generic/VectorViewTemplate$Transformed;
   9:	areturn
  LineNumberTable: 
   line 39: 0

  LocalVariableTable: 
   Start  Length  Slot  Name   Signature
   0      10      0    this       Lscala/GenericRange;
   0      10      1    _from       I
   0      10      2    _patch       Lscala/collection/Sequence;
   0      10      3    _replaced       I


public scala.collection.generic.SequenceViewTemplate$Transformed newZipped(scala.collection.Sequence);
  Code:
   Stack=2, Locals=2, Args_size=2
   0:	aload_0
   1:	aload_1
   2:	invokeinterface	#338,  2; //InterfaceMethod scala/collection/generic/VectorViewTemplate.newZipped:(Lscala/collection/Sequence;)Lscala/collection/generic/VectorViewTemplate$Transformed;
   7:	areturn
  LineNumberTable: 
   line 39: 0

  LocalVariableTable: 
   Start  Length  Slot  Name   Signature
   0      8      0    this       Lscala/GenericRange;
   0      8      1    that       Lscala/collection/Sequence;


public scala.collection.generic.VectorTemplate reverse();
  Code:
   Stack=1, Locals=1, Args_size=1
   0:	aload_0
   1:	invokeinterface	#345,  1; //InterfaceMethod scala/collection/generic/SequenceViewTemplate.reverse:()Lscala/collection/generic/SequenceView;
   6:	checkcast	#347; //class scala/collection/generic/VectorTemplate
   9:	areturn
  LineNumberTable: 
   line 39: 0


public scala.collection.generic.IterableTemplate reverse();
  Code:
   Stack=1, Locals=1, Args_size=1
   0:	aload_0
   1:	invokeinterface	#345,  1; //InterfaceMethod scala/collection/generic/SequenceViewTemplate.reverse:()Lscala/collection/generic/SequenceView;
   6:	areturn
  LineNumberTable: 
   line 39: 0


public scala.collection.generic.TraversableTemplate filter(scala.Function1);
  Code:
   Stack=2, Locals=2, Args_size=2
   0:	aload_0
   1:	aload_1
   2:	invokeinterface	#355,  2; //InterfaceMethod scala/collection/generic/TraversableViewTemplate.filter:(Lscala/Function1;)Lscala/collection/generic/TraversableView;
   7:	areturn
  LineNumberTable: 
   line 39: 0

  LocalVariableTable: 
   Start  Length  Slot  Name   Signature
   0      8      0    this       Lscala/GenericRange;
   0      8      1    p       Lscala/Function1;


public scala.collection.generic.VectorTemplate init();
  Code:
   Stack=1, Locals=1, Args_size=1
   0:	aload_0
   1:	invokeinterface	#359,  1; //InterfaceMethod scala/collection/generic/TraversableViewTemplate.init:()Lscala/collection/generic/TraversableView;
   6:	checkcast	#347; //class scala/collection/generic/VectorTemplate
   9:	areturn
  LineNumberTable: 
   line 39: 0


public scala.collection.generic.TraversableTemplate init();
  Code:
   Stack=1, Locals=1, Args_size=1
   0:	aload_0
   1:	invokeinterface	#359,  1; //InterfaceMethod scala/collection/generic/TraversableViewTemplate.init:()Lscala/collection/generic/TraversableView;
   6:	areturn
  LineNumberTable: 
   line 39: 0


public scala.collection.generic.VectorTemplate drop(int);
  Code:
   Stack=2, Locals=2, Args_size=2
   0:	aload_0
   1:	iload_1
   2:	invokeinterface	#365,  2; //InterfaceMethod scala/collection/generic/TraversableViewTemplate.drop:(I)Lscala/collection/generic/TraversableView;
   7:	checkcast	#347; //class scala/collection/generic/VectorTemplate
   10:	areturn
  LineNumberTable: 
   line 39: 0

  LocalVariableTable: 
   Start  Length  Slot  Name   Signature
   0      11      0    this       Lscala/GenericRange;
   0      11      1    n       I


public scala.collection.generic.TraversableTemplate drop(int);
  Code:
   Stack=2, Locals=2, Args_size=2
   0:	aload_0
   1:	iload_1
   2:	invokeinterface	#365,  2; //InterfaceMethod scala/collection/generic/TraversableViewTemplate.drop:(I)Lscala/collection/generic/TraversableView;
   7:	areturn
  LineNumberTable: 
   line 39: 0

  LocalVariableTable: 
   Start  Length  Slot  Name   Signature
   0      8      0    this       Lscala/GenericRange;
   0      8      1    n       I


public scala.collection.generic.VectorTemplate take(int);
  Code:
   Stack=2, Locals=2, Args_size=2
   0:	aload_0
   1:	iload_1
   2:	invokeinterface	#370,  2; //InterfaceMethod scala/collection/generic/TraversableViewTemplate.take:(I)Lscala/collection/generic/TraversableView;
   7:	checkcast	#347; //class scala/collection/generic/VectorTemplate
   10:	areturn
  LineNumberTable: 
   line 39: 0

  LocalVariableTable: 
   Start  Length  Slot  Name   Signature
   0      11      0    this       Lscala/GenericRange;
   0      11      1    n       I


public scala.collection.generic.TraversableTemplate take(int);
  Code:
   Stack=2, Locals=2, Args_size=2
   0:	aload_0
   1:	iload_1
   2:	invokeinterface	#370,  2; //InterfaceMethod scala/collection/generic/TraversableViewTemplate.take:(I)Lscala/collection/generic/TraversableView;
   7:	areturn
  LineNumberTable: 
   line 39: 0

  LocalVariableTable: 
   Start  Length  Slot  Name   Signature
   0      8      0    this       Lscala/GenericRange;
   0      8      1    n       I


public scala.collection.generic.VectorTemplate slice(int, int);
  Code:
   Stack=3, Locals=3, Args_size=3
   0:	aload_0
   1:	iload_1
   2:	iload_2
   3:	invokeinterface	#375,  3; //InterfaceMethod scala/collection/generic/TraversableViewTemplate.slice:(II)Lscala/collection/generic/TraversableView;
   8:	checkcast	#347; //class scala/collection/generic/VectorTemplate
   11:	areturn
  LineNumberTable: 
   line 39: 0

  LocalVariableTable: 
   Start  Length  Slot  Name   Signature
   0      12      0    this       Lscala/GenericRange;
   0      12      1    from       I
   0      12      2    until       I


public scala.collection.generic.TraversableTemplate slice(int, int);
  Code:
   Stack=3, Locals=3, Args_size=3
   0:	aload_0
   1:	iload_1
   2:	iload_2
   3:	invokeinterface	#375,  3; //InterfaceMethod scala/collection/generic/TraversableViewTemplate.slice:(II)Lscala/collection/generic/TraversableView;
   8:	areturn
  LineNumberTable: 
   line 39: 0

  LocalVariableTable: 
   Start  Length  Slot  Name   Signature
   0      9      0    this       Lscala/GenericRange;
   0      9      1    from       I
   0      9      2    until       I


public scala.collection.generic.VectorTemplate dropWhile(scala.Function1);
  Code:
   Stack=2, Locals=2, Args_size=2
   0:	aload_0
   1:	aload_1
   2:	invokeinterface	#382,  2; //InterfaceMethod scala/collection/generic/TraversableViewTemplate.dropWhile:(Lscala/Function1;)Lscala/collection/generic/TraversableView;
   7:	checkcast	#347; //class scala/collection/generic/VectorTemplate
   10:	areturn
  LineNumberTable: 
   line 39: 0

  LocalVariableTable: 
   Start  Length  Slot  Name   Signature
   0      11      0    this       Lscala/GenericRange;
   0      11      1    p       Lscala/Function1;


public scala.collection.generic.TraversableTemplate dropWhile(scala.Function1);
  Code:
   Stack=2, Locals=2, Args_size=2
   0:	aload_0
   1:	aload_1
   2:	invokeinterface	#382,  2; //InterfaceMethod scala/collection/generic/TraversableViewTemplate.dropWhile:(Lscala/Function1;)Lscala/collection/generic/TraversableView;
   7:	areturn
  LineNumberTable: 
   line 39: 0

  LocalVariableTable: 
   Start  Length  Slot  Name   Signature
   0      8      0    this       Lscala/GenericRange;
   0      8      1    p       Lscala/Function1;


public scala.collection.generic.VectorTemplate takeWhile(scala.Function1);
  Code:
   Stack=2, Locals=2, Args_size=2
   0:	aload_0
   1:	aload_1
   2:	invokeinterface	#385,  2; //InterfaceMethod scala/collection/generic/TraversableViewTemplate.takeWhile:(Lscala/Function1;)Lscala/collection/generic/TraversableView;
   7:	checkcast	#347; //class scala/collection/generic/VectorTemplate
   10:	areturn
  LineNumberTable: 
   line 39: 0

  LocalVariableTable: 
   Start  Length  Slot  Name   Signature
   0      11      0    this       Lscala/GenericRange;
   0      11      1    p       Lscala/Function1;


public scala.collection.generic.TraversableTemplate takeWhile(scala.Function1);
  Code:
   Stack=2, Locals=2, Args_size=2
   0:	aload_0
   1:	aload_1
   2:	invokeinterface	#385,  2; //InterfaceMethod scala/collection/generic/TraversableViewTemplate.takeWhile:(Lscala/Function1;)Lscala/collection/generic/TraversableView;
   7:	areturn
  LineNumberTable: 
   line 39: 0

  LocalVariableTable: 
   Start  Length  Slot  Name   Signature
   0      8      0    this       Lscala/GenericRange;
   0      8      1    p       Lscala/Function1;


public scala.collection.generic.TraversableTemplate tail();
  Code:
   Stack=1, Locals=1, Args_size=1
   0:	aload_0
   1:	invokeinterface	#388,  1; //InterfaceMethod scala/collection/generic/VectorTemplate.tail:()Lscala/collection/generic/VectorTemplate;
   6:	areturn
  LineNumberTable: 
   line 39: 0


public scala.collection.generic.IterableTemplate takeRight(int);
  Code:
   Stack=2, Locals=2, Args_size=2
   0:	aload_0
   1:	iload_1
   2:	invokeinterface	#392,  2; //InterfaceMethod scala/collection/generic/VectorTemplate.takeRight:(I)Lscala/collection/generic/VectorTemplate;
   7:	areturn
  LineNumberTable: 
   line 39: 0

  LocalVariableTable: 
   Start  Length  Slot  Name   Signature
   0      8      0    this       Lscala/GenericRange;
   0      8      1    n       I


public scala.collection.generic.IterableTemplate dropRight(int);
  Code:
   Stack=2, Locals=2, Args_size=2
   0:	aload_0
   1:	iload_1
   2:	invokeinterface	#395,  2; //InterfaceMethod scala/collection/generic/VectorTemplate.dropRight:(I)Lscala/collection/generic/VectorTemplate;
   7:	areturn
  LineNumberTable: 
   line 39: 0

  LocalVariableTable: 
   Start  Length  Slot  Name   Signature
   0      8      0    this       Lscala/GenericRange;
   0      8      1    n       I


public scala.collection.generic.SequenceView view(int, int);
  Code:
   Stack=3, Locals=3, Args_size=3
   0:	aload_0
   1:	iload_1
   2:	iload_2
   3:	invokeinterface	#400,  3; //InterfaceMethod scala/collection/generic/VectorTemplate.view:(II)Lscala/collection/generic/VectorView;
   8:	areturn
  LineNumberTable: 
   line 39: 0

  LocalVariableTable: 
   Start  Length  Slot  Name   Signature
   0      9      0    this       Lscala/GenericRange;
   0      9      1    from       I
   0      9      2    until       I


public scala.collection.generic.IterableView view(int, int);
  Code:
   Stack=3, Locals=3, Args_size=3
   0:	aload_0
   1:	iload_1
   2:	iload_2
   3:	invokeinterface	#400,  3; //InterfaceMethod scala/collection/generic/VectorTemplate.view:(II)Lscala/collection/generic/VectorView;
   8:	areturn
  LineNumberTable: 
   line 39: 0

  LocalVariableTable: 
   Start  Length  Slot  Name   Signature
   0      9      0    this       Lscala/GenericRange;
   0      9      1    from       I
   0      9      2    until       I


public scala.collection.generic.TraversableView view(int, int);
  Code:
   Stack=3, Locals=3, Args_size=3
   0:	aload_0
   1:	iload_1
   2:	iload_2
   3:	invokeinterface	#400,  3; //InterfaceMethod scala/collection/generic/VectorTemplate.view:(II)Lscala/collection/generic/VectorView;
   8:	areturn
  LineNumberTable: 
   line 39: 0

  LocalVariableTable: 
   Start  Length  Slot  Name   Signature
   0      9      0    this       Lscala/GenericRange;
   0      9      1    from       I
   0      9      2    until       I


public boolean isDefinedAt(java.lang.Object);
  Code:
   Stack=2, Locals=2, Args_size=2
   0:	aload_0
   1:	aload_1
   2:	invokestatic	#217; //Method scala/runtime/BoxesRunTime.unboxToInt:(Ljava/lang/Object;)I
   5:	invokeinterface	#407,  2; //InterfaceMethod scala/collection/generic/SequenceTemplate.isDefinedAt:(I)Z
   10:	ireturn
  LineNumberTable: 
   line 39: 0

  LocalVariableTable: 
   Start  Length  Slot  Name   Signature
   0      11      0    this       Lscala/GenericRange;
   0      11      1    x       Ljava/lang/Object;


public scala.Function1 andThen(scala.Function1);
  Code:
   Stack=2, Locals=2, Args_size=2
   0:	aload_0
   1:	aload_1
   2:	invokeinterface	#415,  2; //InterfaceMethod scala/PartialFunction.andThen:(Lscala/Function1;)Lscala/PartialFunction;
   7:	areturn
  LineNumberTable: 
   line 39: 0

  LocalVariableTable: 
   Start  Length  Slot  Name   Signature
   0      8      0    this       Lscala/GenericRange;
   0      8      1    g       Lscala/Function1;


public boolean equals(java.lang.Object);
  Code:
   Stack=2, Locals=4, Args_size=2
   0:	aload_1
   1:	astore_2
   2:	aload_2
   3:	instanceof	#27; //class scala/GenericRange
   6:	ifeq	24
   9:	aload_2
   10:	checkcast	#27; //class scala/GenericRange
   13:	astore_3
   14:	aload_0
   15:	aload_3
   16:	invokeinterface	#421,  2; //InterfaceMethod scala/util/Hashable.equalHashValues:(Ljava/lang/Object;)Z
   21:	goto	25
   24:	iconst_0
   25:	ireturn
  LineNumberTable: 
   line 126: 0
   line 127: 14
   line 128: 24
   line 126: 25

  LocalVariableTable: 
   Start  Length  Slot  Name   Signature
   0      26      0    this       Lscala/GenericRange;
   0      26      1    other       Ljava/lang/Object;
   2      24      2    temp3       Ljava/lang/Object;
   14      7      3    temp4       Lscala/GenericRange;


public scala.collection.immutable.List hashValues();
  Code:
   Stack=1, Locals=1, Args_size=1
   0:	aload_0
   1:	getfield	#204; //Field hashValues:Lscala/collection/immutable/List;
   4:	areturn
  LineNumberTable: 
   line 125: 0

  Signature: length = 0x2
   01 FFFFFFA9 

public boolean contains(java.lang.Object);
  Code:
   Stack=6, Locals=2, Args_size=2
   0:	getstatic	#431; //Field scala/util/control/Exception$.MODULE$:Lscala/util/control/Exception$;
   3:	getstatic	#192; //Field scala/runtime/ScalaRunTime$.MODULE$:Lscala/runtime/ScalaRunTime$;
   6:	iconst_1
   7:	anewarray	#433; //class java/lang/Class
   10:	dup
   11:	iconst_0
   12:	ldc_w	#435; //class java/lang/ClassCastException
   15:	aastore
   16:	invokevirtual	#198; //Method scala/runtime/ScalaRunTime$.boxArray:(Ljava/lang/Object;)Lscala/runtime/BoxedArray;
   19:	invokevirtual	#439; //Method scala/util/control/Exception$.catching:(Lscala/collection/Sequence;)Lscala/util/control/Exception$Catch;
   22:	new	#441; //class scala/GenericRange$$anonfun$contains$1
   25:	dup
   26:	aload_0
   27:	aload_1
   28:	invokespecial	#444; //Method scala/GenericRange$$anonfun$contains$1."<init>":(Lscala/GenericRange;Ljava/lang/Object;)V
   31:	invokevirtual	#450; //Method scala/util/control/Exception$Catch.opt:(Lscala/Function0;)Lscala/Option;
   34:	new	#452; //class scala/GenericRange$$anonfun$contains$2
   37:	dup
   38:	aload_0
   39:	aload_1
   40:	invokespecial	#453; //Method scala/GenericRange$$anonfun$contains$2."<init>":(Lscala/GenericRange;Ljava/lang/Object;)V
   43:	invokevirtual	#459; //Method scala/Option.getOrElse:(Lscala/Function0;)Ljava/lang/Object;
   46:	invokestatic	#462; //Method scala/runtime/BoxesRunTime.unboxToBoolean:(Ljava/lang/Object;)Z
   49:	ireturn
  LineNumberTable: 
   line 121: 0

  LocalVariableTable: 
   Start  Length  Slot  Name   Signature
   0      50      0    this       Lscala/GenericRange;
   0      50      1    _x$1       Ljava/lang/Object;


public java.lang.Object applyAt(java.lang.Object);
  Code:
   Stack=3, Locals=2, Args_size=2
   0:	aload_0
   1:	getfield	#37; //Field num:Lscala/Integral;
   4:	aload_1
   5:	invokeinterface	#140,  2; //InterfaceMethod scala/Ordering.mkOrderingOps:(Ljava/lang/Object;)Lscala/Ordering$Ops;
   10:	aload_0
   11:	getfield	#37; //Field num:Lscala/Integral;
   14:	invokeinterface	#146,  1; //InterfaceMethod scala/Numeric.zero:()Ljava/lang/Object;
   19:	invokevirtual	#236; //Method scala/Ordering$Ops.$less:(Ljava/lang/Object;)Z
   22:	ifne	45
   25:	aload_0
   26:	getfield	#37; //Field num:Lscala/Integral;
   29:	aload_1
   30:	invokeinterface	#140,  2; //InterfaceMethod scala/Ordering.mkOrderingOps:(Ljava/lang/Object;)Lscala/Ordering$Ops;
   35:	aload_0
   36:	invokevirtual	#158; //Method genericLength:()Ljava/lang/Object;
   39:	invokevirtual	#239; //Method scala/Ordering$Ops.$greater$eq:(Ljava/lang/Object;)Z
   42:	ifeq	57
   45:	new	#466; //class java/lang/IndexOutOfBoundsException
   48:	dup
   49:	aload_1
   50:	invokevirtual	#470; //Method java/lang/Object.toString:()Ljava/lang/String;
   53:	invokespecial	#473; //Method java/lang/IndexOutOfBoundsException."<init>":(Ljava/lang/String;)V
   56:	athrow
   57:	aload_0
   58:	getfield	#37; //Field num:Lscala/Integral;
   61:	aload_0
   62:	invokevirtual	#233; //Method start:()Ljava/lang/Object;
   65:	invokeinterface	#245,  2; //InterfaceMethod scala/Integral.mkNumericOps:(Ljava/lang/Object;)Lscala/Integral$IntegralOps;
   70:	aload_0
   71:	getfield	#37; //Field num:Lscala/Integral;
   74:	aload_1
   75:	invokeinterface	#245,  2; //InterfaceMethod scala/Integral.mkNumericOps:(Ljava/lang/Object;)Lscala/Integral$IntegralOps;
   80:	aload_0
   81:	invokevirtual	#228; //Method step:()Ljava/lang/Object;
   84:	invokevirtual	#476; //Method scala/Integral$IntegralOps.$times:(Ljava/lang/Object;)Ljava/lang/Object;
   87:	invokevirtual	#479; //Method scala/Integral$IntegralOps.$plus:(Ljava/lang/Object;)Ljava/lang/Object;
   90:	areturn
  LineNumberTable: 
   line 98: 0
   line 99: 57

  LocalVariableTable: 
   Start  Length  Slot  Name   Signature
   0      91      0    this       Lscala/GenericRange;
   0      91      1    idx       Ljava/lang/Object;

  Signature: length = 0x2
   01 FFFFFFE1 

public java.lang.Object apply(int);
  Code:
   Stack=3, Locals=2, Args_size=2
   0:	aload_0
   1:	aload_0
   2:	getfield	#37; //Field num:Lscala/Integral;
   5:	iload_1
   6:	invokeinterface	#171,  2; //InterfaceMethod scala/Numeric.fromInt:(I)Ljava/lang/Object;
   11:	invokevirtual	#483; //Method applyAt:(Ljava/lang/Object;)Ljava/lang/Object;
   14:	areturn
  LineNumberTable: 
   line 96: 0

  LocalVariableTable: 
   Start  Length  Slot  Name   Signature
   0      15      0    this       Lscala/GenericRange;
   0      15      1    idx       I

  Signature: length = 0x2
   01 FFFFFFE4 

public int length();
  Code:
   Stack=3, Locals=2, Args_size=1
   0:	aload_0
   1:	getfield	#486; //Field bitmap$0:I
   4:	ldc_w	#487; //int 16
   7:	iand
   8:	iconst_0
   9:	if_icmpne	63
   12:	aload_0
   13:	dup
   14:	astore_1
   15:	monitorenter
   16:	aload_0
   17:	getfield	#486; //Field bitmap$0:I
   20:	ldc_w	#487; //int 16
   23:	iand
   24:	iconst_0
   25:	if_icmpne	57
   28:	aload_0
   29:	aload_0
   30:	getfield	#37; //Field num:Lscala/Integral;
   33:	aload_0
   34:	invokevirtual	#158; //Method genericLength:()Ljava/lang/Object;
   37:	invokeinterface	#490,  2; //InterfaceMethod scala/Numeric.toInt:(Ljava/lang/Object;)I
   42:	putfield	#492; //Field length:I
   45:	aload_0
   46:	aload_0
   47:	getfield	#486; //Field bitmap$0:I
   50:	ldc_w	#487; //int 16
   53:	ior
   54:	putfield	#486; //Field bitmap$0:I
   57:	getstatic	#498; //Field scala/runtime/BoxedUnit.UNIT:Lscala/runtime/BoxedUnit;
   60:	pop
   61:	aload_1
   62:	monitorexit
   63:	aload_0
   64:	getfield	#492; //Field length:I
   67:	ireturn
   68:	aload_1
   69:	monitorexit
   70:	athrow
  Exception table:
   from   to  target type
    16    63    68   any
  LineNumberTable: 
   line 92: 0
   line 492: 8
   line 92: 12
   line 492: 24
   line 92: 28


public java.lang.Object genericLength();
  Code:
   Stack=6, Locals=2, Args_size=1
   0:	aload_0
   1:	getfield	#486; //Field bitmap$0:I
   4:	iconst_4
   5:	iand
   6:	iconst_0
   7:	if_icmpne	119
   10:	aload_0
   11:	dup
   12:	astore_1
   13:	monitorenter
   14:	aload_0
   15:	getfield	#486; //Field bitmap$0:I
   18:	iconst_4
   19:	iand
   20:	iconst_0
   21:	if_icmpne	113
   24:	aload_0
   25:	aload_0
   26:	getfield	#37; //Field num:Lscala/Integral;
   29:	aload_0
   30:	invokevirtual	#228; //Method step:()Ljava/lang/Object;
   33:	invokeinterface	#140,  2; //InterfaceMethod scala/Ordering.mkOrderingOps:(Ljava/lang/Object;)Lscala/Ordering$Ops;
   38:	aload_0
   39:	getfield	#37; //Field num:Lscala/Integral;
   42:	invokeinterface	#146,  1; //InterfaceMethod scala/Numeric.zero:()Ljava/lang/Object;
   47:	invokevirtual	#231; //Method scala/Ordering$Ops.$greater:(Ljava/lang/Object;)Z
   50:	ifeq	72
   53:	aload_0
   54:	aload_0
   55:	invokevirtual	#233; //Method start:()Ljava/lang/Object;
   58:	aload_0
   59:	invokespecial	#194; //Method trueEnd:()Ljava/lang/Object;
   62:	aload_0
   63:	invokevirtual	#228; //Method step:()Ljava/lang/Object;
   66:	invokespecial	#500; //Method plen$1:(Ljava/lang/Object;Ljava/lang/Object;Ljava/lang/Object;)Ljava/lang/Object;
   69:	goto	100
   72:	aload_0
   73:	aload_0
   74:	invokespecial	#194; //Method trueEnd:()Ljava/lang/Object;
   77:	aload_0
   78:	invokevirtual	#233; //Method start:()Ljava/lang/Object;
   81:	aload_0
   82:	getfield	#37; //Field num:Lscala/Integral;
   85:	aload_0
   86:	invokevirtual	#228; //Method step:()Ljava/lang/Object;
   89:	invokeinterface	#245,  2; //InterfaceMethod scala/Integral.mkNumericOps:(Ljava/lang/Object;)Lscala/Integral$IntegralOps;
   94:	invokevirtual	#503; //Method scala/Integral$IntegralOps.unary_$minus:()Ljava/lang/Object;
   97:	invokespecial	#500; //Method plen$1:(Ljava/lang/Object;Ljava/lang/Object;Ljava/lang/Object;)Ljava/lang/Object;
   100:	putfield	#505; //Field genericLength:Ljava/lang/Object;
   103:	aload_0
   104:	aload_0
   105:	getfield	#486; //Field bitmap$0:I
   108:	iconst_4
   109:	ior
   110:	putfield	#486; //Field bitmap$0:I
   113:	getstatic	#498; //Field scala/runtime/BoxedUnit.UNIT:Lscala/runtime/BoxedUnit;
   116:	pop
   117:	aload_1
   118:	monitorexit
   119:	aload_0
   120:	getfield	#505; //Field genericLength:Ljava/lang/Object;
   123:	areturn
   124:	aload_1
   125:	monitorexit
   126:	athrow
  Exception table:
   from   to  target type
    14   119   124   any
  LineNumberTable: 
   line 85: 0
   line 492: 6
   line 85: 10
   line 492: 20
   line 85: 24
   line 89: 25
   line 90: 72
   line 85: 100

  Signature: length = 0x2
   01 FFFFFFFA 

public void foreach(scala.Function1);
  Code:
   Stack=2, Locals=3, Args_size=2
   0:	aload_0
   1:	invokevirtual	#233; //Method start:()Ljava/lang/Object;
   4:	astore_2
   5:	aload_0
   6:	getfield	#37; //Field num:Lscala/Integral;
   9:	aload_0
   10:	invokevirtual	#228; //Method step:()Ljava/lang/Object;
   13:	invokeinterface	#140,  2; //InterfaceMethod scala/Ordering.mkOrderingOps:(Ljava/lang/Object;)Lscala/Ordering$Ops;
   18:	aload_0
   19:	getfield	#37; //Field num:Lscala/Integral;
   22:	invokeinterface	#146,  1; //InterfaceMethod scala/Numeric.zero:()Ljava/lang/Object;
   27:	invokevirtual	#231; //Method scala/Ordering$Ops.$greater:(Ljava/lang/Object;)Z
   30:	ifeq	82
   33:	aload_0
   34:	getfield	#37; //Field num:Lscala/Integral;
   37:	aload_2
   38:	invokeinterface	#140,  2; //InterfaceMethod scala/Ordering.mkOrderingOps:(Ljava/lang/Object;)Lscala/Ordering$Ops;
   43:	aload_0
   44:	invokespecial	#194; //Method trueEnd:()Ljava/lang/Object;
   47:	invokevirtual	#236; //Method scala/Ordering$Ops.$less:(Ljava/lang/Object;)Z
   50:	ifeq	131
   53:	aload_1
   54:	aload_2
   55:	invokeinterface	#511,  2; //InterfaceMethod scala/Function1.apply:(Ljava/lang/Object;)Ljava/lang/Object;
   60:	pop
   61:	aload_0
   62:	getfield	#37; //Field num:Lscala/Integral;
   65:	aload_2
   66:	invokeinterface	#245,  2; //InterfaceMethod scala/Integral.mkNumericOps:(Ljava/lang/Object;)Lscala/Integral$IntegralOps;
   71:	aload_0
   72:	invokevirtual	#228; //Method step:()Ljava/lang/Object;
   75:	invokevirtual	#479; //Method scala/Integral$IntegralOps.$plus:(Ljava/lang/Object;)Ljava/lang/Object;
   78:	astore_2
   79:	goto	33
   82:	aload_0
   83:	getfield	#37; //Field num:Lscala/Integral;
   86:	aload_2
   87:	invokeinterface	#140,  2; //InterfaceMethod scala/Ordering.mkOrderingOps:(Ljava/lang/Object;)Lscala/Ordering$Ops;
   92:	aload_0
   93:	invokespecial	#194; //Method trueEnd:()Ljava/lang/Object;
   96:	invokevirtual	#231; //Method scala/Ordering$Ops.$greater:(Ljava/lang/Object;)Z
   99:	ifeq	131
   102:	aload_1
   103:	aload_2
   104:	invokeinterface	#511,  2; //InterfaceMethod scala/Function1.apply:(Ljava/lang/Object;)Ljava/lang/Object;
   109:	pop
   110:	aload_0
   111:	getfield	#37; //Field num:Lscala/Integral;
   114:	aload_2
   115:	invokeinterface	#245,  2; //InterfaceMethod scala/Integral.mkNumericOps:(Ljava/lang/Object;)Lscala/Integral$IntegralOps;
   120:	aload_0
   121:	invokevirtual	#228; //Method step:()Ljava/lang/Object;
   124:	invokevirtual	#479; //Method scala/Integral$IntegralOps.$plus:(Ljava/lang/Object;)Ljava/lang/Object;
   127:	astore_2
   128:	goto	82
   131:	return
  LineNumberTable: 
   line 71: 0
   line 72: 5
   line 73: 33
   line 74: 53
   line 75: 61
   line 73: 79
   line 78: 82
   line 79: 102
   line 80: 110
   line 78: 128
   line 70: 131

  LocalVariableTable: 
   Start  Length  Slot  Name   Signature
   0      132      0    this       Lscala/GenericRange;
   0      132      1    f       Lscala/Function1;
   5      127      2    i       Ljava/lang/Object;

  Signature: length = 0x2
   02 01 

public scala.GenericRange $times(java.lang.Object);
  Code:
   Stack=5, Locals=2, Args_size=2
   0:	aload_0
   1:	aload_0
   2:	getfield	#37; //Field num:Lscala/Integral;
   5:	aload_0
   6:	invokevirtual	#233; //Method start:()Ljava/lang/Object;
   9:	invokeinterface	#245,  2; //InterfaceMethod scala/Integral.mkNumericOps:(Ljava/lang/Object;)Lscala/Integral$IntegralOps;
   14:	aload_1
   15:	invokevirtual	#476; //Method scala/Integral$IntegralOps.$times:(Ljava/lang/Object;)Ljava/lang/Object;
   18:	aload_0
   19:	getfield	#37; //Field num:Lscala/Integral;
   22:	aload_0
   23:	invokevirtual	#516; //Method end:()Ljava/lang/Object;
   26:	invokeinterface	#245,  2; //InterfaceMethod scala/Integral.mkNumericOps:(Ljava/lang/Object;)Lscala/Integral$IntegralOps;
   31:	aload_1
   32:	invokevirtual	#476; //Method scala/Integral$IntegralOps.$times:(Ljava/lang/Object;)Ljava/lang/Object;
   35:	aload_0
   36:	getfield	#37; //Field num:Lscala/Integral;
   39:	aload_0
   40:	invokevirtual	#228; //Method step:()Ljava/lang/Object;
   43:	invokeinterface	#245,  2; //InterfaceMethod scala/Integral.mkNumericOps:(Ljava/lang/Object;)Lscala/Integral$IntegralOps;
   48:	aload_1
   49:	invokevirtual	#476; //Method scala/Integral$IntegralOps.$times:(Ljava/lang/Object;)Ljava/lang/Object;
   52:	invokevirtual	#520; //Method copy:(Ljava/lang/Object;Ljava/lang/Object;Ljava/lang/Object;)Lscala/GenericRange;
   55:	areturn
  LineNumberTable: 
   line 68: 0

  LocalVariableTable: 
   Start  Length  Slot  Name   Signature
   0      56      0    this       Lscala/GenericRange;
   0      56      1    mult       Ljava/lang/Object;

  Signature: length = 0x2
   02 0A 

public scala.GenericRange $plus(java.lang.Object);
  Code:
   Stack=4, Locals=2, Args_size=2
   0:	aload_0
   1:	aload_0
   2:	getfield	#37; //Field num:Lscala/Integral;
   5:	aload_0
   6:	invokevirtual	#233; //Method start:()Ljava/lang/Object;
   9:	invokeinterface	#245,  2; //InterfaceMethod scala/Integral.mkNumericOps:(Ljava/lang/Object;)Lscala/Integral$IntegralOps;
   14:	aload_1
   15:	invokevirtual	#479; //Method scala/Integral$IntegralOps.$plus:(Ljava/lang/Object;)Ljava/lang/Object;
   18:	aload_0
   19:	getfield	#37; //Field num:Lscala/Integral;
   22:	aload_0
   23:	invokevirtual	#516; //Method end:()Ljava/lang/Object;
   26:	invokeinterface	#245,  2; //InterfaceMethod scala/Integral.mkNumericOps:(Ljava/lang/Object;)Lscala/Integral$IntegralOps;
   31:	aload_1
   32:	invokevirtual	#479; //Method scala/Integral$IntegralOps.$plus:(Ljava/lang/Object;)Ljava/lang/Object;
   35:	aload_0
   36:	invokevirtual	#228; //Method step:()Ljava/lang/Object;
   39:	invokevirtual	#520; //Method copy:(Ljava/lang/Object;Ljava/lang/Object;Ljava/lang/Object;)Lscala/GenericRange;
   42:	areturn
  LineNumberTable: 
   line 67: 0

  LocalVariableTable: 
   Start  Length  Slot  Name   Signature
   0      43      0    this       Lscala/GenericRange;
   0      43      1    shift       Ljava/lang/Object;

  Signature: length = 0x2
   02 0A 

public scala.GenericRange $minus(java.lang.Object);
  Code:
   Stack=3, Locals=2, Args_size=2
   0:	aload_0
   1:	aload_0
   2:	getfield	#37; //Field num:Lscala/Integral;
   5:	aload_1
   6:	invokeinterface	#526,  2; //InterfaceMethod scala/Numeric.negate:(Ljava/lang/Object;)Ljava/lang/Object;
   11:	invokevirtual	#528; //Method $plus:(Ljava/lang/Object;)Lscala/GenericRange;
   14:	areturn
  LineNumberTable: 
   line 66: 0

  LocalVariableTable: 
   Start  Length  Slot  Name   Signature
   0      15      0    this       Lscala/GenericRange;
   0      15      1    shift       Ljava/lang/Object;

  Signature: length = 0x2
   02 0A 

public abstract scala.GenericRange copy(java.lang.Object, java.lang.Object, java.lang.Object);
  Signature: length = 0x2
   02 11 

public scala.GenericRange by(java.lang.Object);
  Code:
   Stack=4, Locals=2, Args_size=2
   0:	aload_0
   1:	aload_0
   2:	invokevirtual	#233; //Method start:()Ljava/lang/Object;
   5:	aload_0
   6:	invokevirtual	#516; //Method end:()Ljava/lang/Object;
   9:	aload_1
   10:	invokevirtual	#520; //Method copy:(Ljava/lang/Object;Ljava/lang/Object;Ljava/lang/Object;)Lscala/GenericRange;
   13:	areturn
  LineNumberTable: 
   line 58: 0

  LocalVariableTable: 
   Start  Length  Slot  Name   Signature
   0      14      0    this       Lscala/GenericRange;
   0      14      1    newStep       Ljava/lang/Object;

  Signature: length = 0x2
   02 0A 

public scala.collection.immutable.Vector underlying();
  Code:
   Stack=1, Locals=1, Args_size=1
   0:	getstatic	#536; //Field scala/collection/immutable/Vector$.MODULE$:Lscala/collection/immutable/Vector$;
   3:	invokevirtual	#539; //Method scala/collection/immutable/Vector$.empty:()Lscala/collection/Traversable;
   6:	checkcast	#541; //class scala/collection/immutable/Vector
   9:	areturn
  LineNumberTable: 
   line 53: 0

  Signature: length = 0x2
   02 1E 

public boolean isInclusive();
  Code:
   Stack=1, Locals=1, Args_size=1
   0:	aload_0
   1:	getfield	#35; //Field isInclusive:Z
   4:	ireturn
  LineNumberTable: 
   line 40: 0


public java.lang.Object step();
  Code:
   Stack=1, Locals=1, Args_size=1
   0:	aload_0
   1:	getfield	#33; //Field step:Ljava/lang/Object;
   4:	areturn
  LineNumberTable: 
   line 40: 0

  Signature: length = 0x2
   01 FFFFFFFA 

public java.lang.Object end();
  Code:
   Stack=1, Locals=1, Args_size=1
   0:	aload_0
   1:	getfield	#31; //Field end:Ljava/lang/Object;
   4:	areturn
  LineNumberTable: 
   line 40: 0

  Signature: length = 0x2
   01 FFFFFFFA 

public java.lang.Object start();
  Code:
   Stack=1, Locals=1, Args_size=1
   0:	aload_0
   1:	getfield	#29; //Field start:Ljava/lang/Object;
   4:	areturn
  LineNumberTable: 
   line 40: 0

  Signature: length = 0x2
   01 FFFFFFFA 

public final boolean scala$GenericRange$$super$contains(java.lang.Object);
  Code:
   Stack=2, Locals=2, Args_size=2
   0:	aload_0
   1:	aload_1
   2:	invokestatic	#551; //Method scala/collection/generic/SequenceTemplate$class.contains:(Lscala/collection/generic/SequenceTemplate;Ljava/lang/Object;)Z
   5:	ireturn
  LineNumberTable: 
   line 121: 0

  LocalVariableTable: 
   Start  Length  Slot  Name   Signature
   0      6      0    this       Lscala/GenericRange;
   0      6      1    elem       Ljava/lang/Object;


public scala.Function1 compose(scala.Function1);
  Code:
   Stack=2, Locals=2, Args_size=2
   0:	aload_0
   1:	aload_1
   2:	invokestatic	#556; //Method scala/Function1$class.compose:(Lscala/Function1;Lscala/Function1;)Lscala/Function1;
   5:	areturn
  LineNumberTable: 
   line 39: 0

  LocalVariableTable: 
   Start  Length  Slot  Name   Signature
   0      6      0    this       Lscala/GenericRange;
   0      6      1    g       Lscala/Function1;


public scala.PartialFunction andThen(scala.Function1);
  Code:
   Stack=2, Locals=2, Args_size=2
   0:	aload_0
   1:	aload_1
   2:	invokestatic	#559; //Method scala/PartialFunction$class.andThen:(Lscala/PartialFunction;Lscala/Function1;)Lscala/PartialFunction;
   5:	areturn
  LineNumberTable: 
   line 39: 0

  LocalVariableTable: 
   Start  Length  Slot  Name   Signature
   0      6      0    this       Lscala/GenericRange;
   0      6      1    k       Lscala/Function1;


public scala.PartialFunction orElse(scala.PartialFunction);
  Code:
   Stack=2, Locals=2, Args_size=2
   0:	aload_0
   1:	aload_1
   2:	invokestatic	#565; //Method scala/PartialFunction$class.orElse:(Lscala/PartialFunction;Lscala/PartialFunction;)Lscala/PartialFunction;
   5:	areturn
  LineNumberTable: 
   line 39: 0

  LocalVariableTable: 
   Start  Length  Slot  Name   Signature
   0      6      0    this       Lscala/GenericRange;
   0      6      1    that       Lscala/PartialFunction;


public java.lang.String stringPrefix();
  Code:
   Stack=1, Locals=1, Args_size=1
   0:	aload_0
   1:	invokestatic	#570; //Method scala/collection/generic/TraversableTemplate$class.stringPrefix:(Lscala/collection/generic/TraversableTemplate;)Ljava/lang/String;
   4:	areturn
  LineNumberTable: 
   line 39: 0


public scala.collection.mutable.StringBuilder addString(scala.collection.mutable.StringBuilder);
  Code:
   Stack=2, Locals=2, Args_size=2
   0:	aload_0
   1:	aload_1
   2:	invokestatic	#575; //Method scala/collection/generic/TraversableTemplate$class.addString:(Lscala/collection/generic/TraversableTemplate;Lscala/collection/mutable/StringBuilder;)Lscala/collection/mutable/StringBuilder;
   5:	areturn
  LineNumberTable: 
   line 39: 0

  LocalVariableTable: 
   Start  Length  Slot  Name   Signature
   0      6      0    this       Lscala/GenericRange;
   0      6      1    b       Lscala/collection/mutable/StringBuilder;


public scala.collection.mutable.StringBuilder addString(scala.collection.mutable.StringBuilder, java.lang.String);
  Code:
   Stack=3, Locals=3, Args_size=3
   0:	aload_0
   1:	aload_1
   2:	aload_2
   3:	invokestatic	#581; //Method scala/collection/generic/TraversableTemplate$class.addString:(Lscala/collection/generic/TraversableTemplate;Lscala/collection/mutable/StringBuilder;Ljava/lang/String;)Lscala/collection/mutable/StringBuilder;
   6:	areturn
  LineNumberTable: 
   line 39: 0

  LocalVariableTable: 
   Start  Length  Slot  Name   Signature
   0      7      0    this       Lscala/GenericRange;
   0      7      1    b       Lscala/collection/mutable/StringBuilder;
   0      7      2    sep       Ljava/lang/String;


public scala.collection.mutable.StringBuilder addString(scala.collection.mutable.StringBuilder, java.lang.String, java.lang.String, java.lang.String);
  Code:
   Stack=5, Locals=5, Args_size=5
   0:	aload_0
   1:	aload_1
   2:	aload_2
   3:	aload_3
   4:	aload	4
   6:	invokestatic	#587; //Method scala/collection/generic/TraversableTemplate$class.addString:(Lscala/collection/generic/TraversableTemplate;Lscala/collection/mutable/StringBuilder;Ljava/lang/String;Ljava/lang/String;Ljava/lang/String;)Lscala/collection/mutable/StringBuilder;
   9:	areturn
  LineNumberTable: 
   line 39: 0

  LocalVariableTable: 
   Start  Length  Slot  Name   Signature
   0      10      0    this       Lscala/GenericRange;
   0      10      1    b       Lscala/collection/mutable/StringBuilder;
   0      10      2    start       Ljava/lang/String;
   0      10      3    sep       Ljava/lang/String;
   0      10      4    end       Ljava/lang/String;


public java.lang.String mkString();
  Code:
   Stack=1, Locals=1, Args_size=1
   0:	aload_0
   1:	invokestatic	#590; //Method scala/collection/generic/TraversableTemplate$class.mkString:(Lscala/collection/generic/TraversableTemplate;)Ljava/lang/String;
   4:	areturn
  LineNumberTable: 
   line 39: 0


public java.lang.String mkString(java.lang.String);
  Code:
   Stack=2, Locals=2, Args_size=2
   0:	aload_0
   1:	aload_1
   2:	invokestatic	#594; //Method scala/collection/generic/TraversableTemplate$class.mkString:(Lscala/collection/generic/TraversableTemplate;Ljava/lang/String;)Ljava/lang/String;
   5:	areturn
  LineNumberTable: 
   line 39: 0

  LocalVariableTable: 
   Start  Length  Slot  Name   Signature
   0      6      0    this       Lscala/GenericRange;
   0      6      1    sep       Ljava/lang/String;


public java.lang.String mkString(java.lang.String, java.lang.String, java.lang.String);
  Code:
   Stack=4, Locals=4, Args_size=4
   0:	aload_0
   1:	aload_1
   2:	aload_2
   3:	aload_3
   4:	invokestatic	#598; //Method scala/collection/generic/TraversableTemplate$class.mkString:(Lscala/collection/generic/TraversableTemplate;Ljava/lang/String;Ljava/lang/String;Ljava/lang/String;)Ljava/lang/String;
   7:	areturn
  LineNumberTable: 
   line 39: 0

  LocalVariableTable: 
   Start  Length  Slot  Name   Signature
   0      8      0    this       Lscala/GenericRange;
   0      8      1    start       Ljava/lang/String;
   0      8      2    sep       Ljava/lang/String;
   0      8      3    end       Ljava/lang/String;


public scala.collection.immutable.Set toSet();
  Code:
   Stack=1, Locals=1, Args_size=1
   0:	aload_0
   1:	invokestatic	#603; //Method scala/collection/generic/TraversableTemplate$class.toSet:(Lscala/collection/generic/TraversableTemplate;)Lscala/collection/immutable/Set;
   4:	areturn
  LineNumberTable: 
   line 39: 0


public scala.collection.immutable.List toList();
  Code:
   Stack=1, Locals=1, Args_size=1
   0:	aload_0
   1:	invokestatic	#607; //Method scala/collection/generic/TraversableTemplate$class.toList:(Lscala/collection/generic/TraversableTemplate;)Lscala/collection/immutable/List;
   4:	areturn
  LineNumberTable: 
   line 39: 0


public scala.runtime.BoxedArray toArray();
  Code:
   Stack=1, Locals=1, Args_size=1
   0:	aload_0
   1:	invokestatic	#612; //Method scala/collection/generic/TraversableTemplate$class.toArray:(Lscala/collection/generic/TraversableTemplate;)Lscala/runtime/BoxedArray;
   4:	areturn
  LineNumberTable: 
   line 39: 0


public void copyToArray(scala.runtime.BoxedArray, int);
  Code:
   Stack=3, Locals=3, Args_size=3
   0:	aload_0
   1:	aload_1
   2:	iload_2
   3:	invokestatic	#617; //Method scala/collection/generic/TraversableTemplate$class.copyToArray:(Lscala/collection/generic/TraversableTemplate;Lscala/runtime/BoxedArray;I)V
   6:	return
  LineNumberTable: 
   line 39: 0

  LocalVariableTable: 
   Start  Length  Slot  Name   Signature
   0      7      0    this       Lscala/GenericRange;
   0      7      1    xs       Lscala/runtime/BoxedArray;
   0      7      2    start       I


public void copyToBuffer(scala.collection.mutable.Buffer);
  Code:
   Stack=2, Locals=2, Args_size=2
   0:	aload_0
   1:	aload_1
   2:	invokestatic	#624; //Method scala/collection/generic/TraversableTemplate$class.copyToBuffer:(Lscala/collection/generic/TraversableTemplate;Lscala/collection/mutable/Buffer;)V
   5:	return
  LineNumberTable: 
   line 39: 0

  LocalVariableTable: 
   Start  Length  Slot  Name   Signature
   0      6      0    this       Lscala/GenericRange;
   0      6      1    dest       Lscala/collection/mutable/Buffer;


public scala.Option lastOption();
  Code:
   Stack=1, Locals=1, Args_size=1
   0:	aload_0
   1:	invokestatic	#631; //Method scala/collection/generic/TraversableTemplate$class.lastOption:(Lscala/collection/generic/TraversableTemplate;)Lscala/Option;
   4:	areturn
  LineNumberTable: 
   line 39: 0


public scala.Option headOption();
  Code:
   Stack=1, Locals=1, Args_size=1
   0:	aload_0
   1:	invokestatic	#634; //Method scala/collection/generic/TraversableTemplate$class.headOption:(Lscala/collection/generic/TraversableTemplate;)Lscala/Option;
   4:	areturn
  LineNumberTable: 
   line 39: 0


public scala.Option reduceRightOption(scala.Function2);
  Code:
   Stack=2, Locals=2, Args_size=2
   0:	aload_0
   1:	aload_1
   2:	invokestatic	#639; //Method scala/collection/generic/TraversableTemplate$class.reduceRightOption:(Lscala/collection/generic/TraversableTemplate;Lscala/Function2;)Lscala/Option;
   5:	areturn
  LineNumberTable: 
   line 39: 0

  LocalVariableTable: 
   Start  Length  Slot  Name   Signature
   0      6      0    this       Lscala/GenericRange;
   0      6      1    op       Lscala/Function2;


public scala.Option reduceLeftOption(scala.Function2);
  Code:
   Stack=2, Locals=2, Args_size=2
   0:	aload_0
   1:	aload_1
   2:	invokestatic	#644; //Method scala/collection/generic/TraversableTemplate$class.reduceLeftOption:(Lscala/collection/generic/TraversableTemplate;Lscala/Function2;)Lscala/Option;
   5:	areturn
  LineNumberTable: 
   line 39: 0

  LocalVariableTable: 
   Start  Length  Slot  Name   Signature
   0      6      0    this       Lscala/GenericRange;
   0      6      1    op       Lscala/Function2;


public java.lang.Object $colon$bslash(java.lang.Object, scala.Function2);
  Code:
   Stack=3, Locals=3, Args_size=3
   0:	aload_0
   1:	aload_1
   2:	aload_2
   3:	invokestatic	#649; //Method scala/collection/generic/TraversableTemplate$class.$colon$bslash:(Lscala/collection/generic/TraversableTemplate;Ljava/lang/Object;Lscala/Function2;)Ljava/lang/Object;
   6:	areturn
  LineNumberTable: 
   line 39: 0

  LocalVariableTable: 
   Start  Length  Slot  Name   Signature
   0      7      0    this       Lscala/GenericRange;
   0      7      1    z       Ljava/lang/Object;
   0      7      2    op       Lscala/Function2;


public java.lang.Object $div$colon(java.lang.Object, scala.Function2);
  Code:
   Stack=3, Locals=3, Args_size=3
   0:	aload_0
   1:	aload_1
   2:	aload_2
   3:	invokestatic	#653; //Method scala/collection/generic/TraversableTemplate$class.$div$colon:(Lscala/collection/generic/TraversableTemplate;Ljava/lang/Object;Lscala/Function2;)Ljava/lang/Object;
   6:	areturn
  LineNumberTable: 
   line 39: 0

  LocalVariableTable: 
   Start  Length  Slot  Name   Signature
   0      7      0    this       Lscala/GenericRange;
   0      7      1    z       Ljava/lang/Object;
   0      7      2    op       Lscala/Function2;


public int count(scala.Function1);
  Code:
   Stack=2, Locals=2, Args_size=2
   0:	aload_0
   1:	aload_1
   2:	invokestatic	#658; //Method scala/collection/generic/TraversableTemplate$class.count:(Lscala/collection/generic/TraversableTemplate;Lscala/Function1;)I
   5:	ireturn
  LineNumberTable: 
   line 39: 0

  LocalVariableTable: 
   Start  Length  Slot  Name   Signature
   0      6      0    this       Lscala/GenericRange;
   0      6      1    p       Lscala/Function1;


public scala.collection.Map groupBy(scala.Function1);
  Code:
   Stack=2, Locals=2, Args_size=2
   0:	aload_0
   1:	aload_1
   2:	invokestatic	#663; //Method scala/collection/generic/TraversableTemplate$class.groupBy:(Lscala/collection/generic/TraversableTemplate;Lscala/Function1;)Lscala/collection/Map;
   5:	areturn
  LineNumberTable: 
   line 39: 0

  LocalVariableTable: 
   Start  Length  Slot  Name   Signature
   0      6      0    this       Lscala/GenericRange;
   0      6      1    f       Lscala/Function1;


public scala.Tuple2 partition(scala.Function1);
  Code:
   Stack=2, Locals=2, Args_size=2
   0:	aload_0
   1:	aload_1
   2:	invokestatic	#668; //Method scala/collection/generic/TraversableTemplate$class.partition:(Lscala/collection/generic/TraversableTemplate;Lscala/Function1;)Lscala/Tuple2;
   5:	areturn
  LineNumberTable: 
   line 39: 0

  LocalVariableTable: 
   Start  Length  Slot  Name   Signature
   0      6      0    this       Lscala/GenericRange;
   0      6      1    p       Lscala/Function1;


public scala.collection.generic.TraversableTemplate remove(scala.Function1);
  Code:
   Stack=2, Locals=2, Args_size=2
   0:	aload_0
   1:	aload_1
   2:	invokestatic	#672; //Method scala/collection/generic/TraversableTemplate$class.remove:(Lscala/collection/generic/TraversableTemplate;Lscala/Function1;)Lscala/collection/generic/TraversableTemplate;
   5:	areturn
  LineNumberTable: 
   line 39: 0

  LocalVariableTable: 
   Start  Length  Slot  Name   Signature
   0      6      0    this       Lscala/GenericRange;
   0      6      1    p       Lscala/Function1;


public scala.collection.generic.TraversableTemplate filterNot(scala.Function1);
  Code:
   Stack=2, Locals=2, Args_size=2
   0:	aload_0
   1:	aload_1
   2:	invokestatic	#675; //Method scala/collection/generic/TraversableTemplate$class.filterNot:(Lscala/collection/generic/TraversableTemplate;Lscala/Function1;)Lscala/collection/generic/TraversableTemplate;
   5:	areturn
  LineNumberTable: 
   line 39: 0

  LocalVariableTable: 
   Start  Length  Slot  Name   Signature
   0      6      0    this       Lscala/GenericRange;
   0      6      1    p       Lscala/Function1;


public java.lang.Object filterMap(scala.PartialFunction, scala.collection.generic.BuilderFactory);
  Code:
   Stack=3, Locals=3, Args_size=3
   0:	aload_0
   1:	aload_1
   2:	aload_2
   3:	invokestatic	#680; //Method scala/collection/generic/TraversableTemplate$class.filterMap:(Lscala/collection/generic/TraversableTemplate;Lscala/PartialFunction;Lscala/collection/generic/BuilderFactory;)Ljava/lang/Object;
   6:	areturn
  LineNumberTable: 
   line 39: 0

  LocalVariableTable: 
   Start  Length  Slot  Name   Signature
   0      7      0    this       Lscala/GenericRange;
   0      7      1    pf       Lscala/PartialFunction;
   0      7      2    bf       Lscala/collection/generic/BuilderFactory;


public boolean hasDefiniteSize();
  Code:
   Stack=1, Locals=1, Args_size=1
   0:	aload_0
   1:	invokestatic	#687; //Method scala/collection/generic/TraversableTemplate$class.hasDefiniteSize:(Lscala/collection/generic/TraversableTemplate;)Z
   4:	ireturn
  LineNumberTable: 
   line 39: 0


public boolean nonEmpty();
  Code:
   Stack=1, Locals=1, Args_size=1
   0:	aload_0
   1:	invokestatic	#690; //Method scala/collection/generic/TraversableTemplate$class.nonEmpty:(Lscala/collection/generic/TraversableTemplate;)Z
   4:	ireturn
  LineNumberTable: 
   line 39: 0


public scala.collection.generic.TraversableTemplate thisCollection();
  Code:
   Stack=1, Locals=1, Args_size=1
   0:	aload_0
   1:	invokestatic	#694; //Method scala/collection/generic/TraversableTemplate$class.thisCollection:(Lscala/collection/generic/TraversableTemplate;)Lscala/collection/generic/TraversableTemplate;
   4:	areturn
  LineNumberTable: 
   line 39: 0


public scala.collection.Traversable transpose(scala.Function1);
  Code:
   Stack=2, Locals=2, Args_size=2
   0:	aload_0
   1:	aload_1
   2:	invokestatic	#699; //Method scala/collection/generic/TraversableClass$class.transpose:(Lscala/collection/generic/TraversableClass;Lscala/Function1;)Lscala/collection/Traversable;
   5:	areturn
  LineNumberTable: 
   line 39: 0

  LocalVariableTable: 
   Start  Length  Slot  Name   Signature
   0      6      0    this       Lscala/GenericRange;
   0      6      1    toTraversable       Lscala/Function1;


public scala.collection.Traversable flatten(scala.Function1);
  Code:
   Stack=2, Locals=2, Args_size=2
   0:	aload_0
   1:	aload_1
   2:	invokestatic	#703; //Method scala/collection/generic/TraversableClass$class.flatten:(Lscala/collection/generic/TraversableClass;Lscala/Function1;)Lscala/collection/Traversable;
   5:	areturn
  LineNumberTable: 
   line 39: 0

  LocalVariableTable: 
   Start  Length  Slot  Name   Signature
   0      6      0    this       Lscala/GenericRange;
   0      6      1    toTraversable       Lscala/Function1;


public scala.Tuple2 unzip(scala.Function1);
  Code:
   Stack=2, Locals=2, Args_size=2
   0:	aload_0
   1:	aload_1
   2:	invokestatic	#707; //Method scala/collection/generic/TraversableClass$class.unzip:(Lscala/collection/generic/TraversableClass;Lscala/Function1;)Lscala/Tuple2;
   5:	areturn
  LineNumberTable: 
   line 39: 0

  LocalVariableTable: 
   Start  Length  Slot  Name   Signature
   0      6      0    this       Lscala/GenericRange;
   0      6      1    toPair       Lscala/Function1;


public scala.collection.generic.Builder genericBuilder();
  Code:
   Stack=1, Locals=1, Args_size=1
   0:	aload_0
   1:	invokestatic	#713; //Method scala/collection/generic/TraversableClass$class.genericBuilder:(Lscala/collection/generic/TraversableClass;)Lscala/collection/generic/Builder;
   4:	areturn
  LineNumberTable: 
   line 39: 0


public scala.collection.Sequence toSeq();
  Code:
   Stack=1, Locals=1, Args_size=1
   0:	aload_0
   1:	invokestatic	#717; //Method scala/collection/generic/IterableTemplate$class.toSeq:(Lscala/collection/generic/IterableTemplate;)Lscala/collection/Sequence;
   4:	areturn
  LineNumberTable: 
   line 39: 0


public scala.Option firstOption();
  Code:
   Stack=1, Locals=1, Args_size=1
   0:	aload_0
   1:	invokestatic	#721; //Method scala/collection/generic/IterableTemplate$class.firstOption:(Lscala/collection/generic/IterableTemplate;)Lscala/Option;
   4:	areturn
  LineNumberTable: 
   line 39: 0


public java.lang.Object first();
  Code:
   Stack=1, Locals=1, Args_size=1
   0:	aload_0
   1:	invokestatic	#725; //Method scala/collection/generic/IterableTemplate$class.first:(Lscala/collection/generic/IterableTemplate;)Ljava/lang/Object;
   4:	areturn
  LineNumberTable: 
   line 39: 0


public scala.collection.immutable.Stream toStream();
  Code:
   Stack=1, Locals=1, Args_size=1
   0:	aload_0
   1:	invokestatic	#730; //Method scala/collection/generic/IterableTemplate$class.toStream:(Lscala/collection/generic/IterableTemplate;)Lscala/collection/immutable/Stream;
   4:	areturn
  LineNumberTable: 
   line 39: 0


public scala.collection.Iterable toIterable();
  Code:
   Stack=1, Locals=1, Args_size=1
   0:	aload_0
   1:	invokestatic	#735; //Method scala/collection/generic/IterableTemplate$class.toIterable:(Lscala/collection/generic/IterableTemplate;)Lscala/collection/Iterable;
   4:	areturn
  LineNumberTable: 
   line 39: 0


public scala.collection.Iterator elements();
  Code:
   Stack=1, Locals=1, Args_size=1
   0:	aload_0
   1:	invokestatic	#740; //Method scala/collection/generic/IterableTemplate$class.elements:(Lscala/collection/generic/IterableTemplate;)Lscala/collection/Iterator;
   4:	areturn
  LineNumberTable: 
   line 39: 0


public java.lang.Object projection();
  Code:
   Stack=1, Locals=1, Args_size=1
   0:	aload_0
   1:	invokestatic	#744; //Method scala/collection/generic/SequenceTemplate$class.projection:(Lscala/collection/generic/SequenceTemplate;)Ljava/lang/Object;
   4:	areturn
  LineNumberTable: 
   line 39: 0


public boolean containsSlice(scala.collection.Sequence);
  Code:
   Stack=2, Locals=2, Args_size=2
   0:	aload_0
   1:	aload_1
   2:	invokestatic	#749; //Method scala/collection/generic/SequenceTemplate$class.containsSlice:(Lscala/collection/generic/SequenceTemplate;Lscala/collection/Sequence;)Z
   5:	ireturn
  LineNumberTable: 
   line 39: 0

  LocalVariableTable: 
   Start  Length  Slot  Name   Signature
   0      6      0    this       Lscala/GenericRange;
   0      6      1    that       Lscala/collection/Sequence;


public boolean equalsWith(scala.collection.Sequence, scala.Function2);
  Code:
   Stack=3, Locals=3, Args_size=3
   0:	aload_0
   1:	aload_1
   2:	aload_2
   3:	invokestatic	#754; //Method scala/collection/generic/SequenceTemplate$class.equalsWith:(Lscala/collection/generic/SequenceTemplate;Lscala/collection/Sequence;Lscala/Function2;)Z
   6:	ireturn
  LineNumberTable: 
   line 39: 0

  LocalVariableTable: 
   Start  Length  Slot  Name   Signature
   0      7      0    this       Lscala/GenericRange;
   0      7      1    that       Lscala/collection/Sequence;
   0      7      2    f       Lscala/Function2;


public scala.collection.Sequence slice(int);
  Code:
   Stack=2, Locals=2, Args_size=2
   0:	aload_0
   1:	iload_1
   2:	invokestatic	#758; //Method scala/collection/generic/SequenceTemplate$class.slice:(Lscala/collection/generic/SequenceTemplate;I)Lscala/collection/Sequence;
   5:	areturn
  LineNumberTable: 
   line 39: 0

  LocalVariableTable: 
   Start  Length  Slot  Name   Signature
   0      6      0    this       Lscala/GenericRange;
   0      6      1    from       I


public int findLastIndexOf(scala.Function1);
  Code:
   Stack=2, Locals=2, Args_size=2
   0:	aload_0
   1:	aload_1
   2:	invokestatic	#762; //Method scala/collection/generic/SequenceTemplate$class.findLastIndexOf:(Lscala/collection/generic/SequenceTemplate;Lscala/Function1;)I
   5:	ireturn
  LineNumberTable: 
   line 39: 0

  LocalVariableTable: 
   Start  Length  Slot  Name   Signature
   0      6      0    this       Lscala/GenericRange;
   0      6      1    p       Lscala/Function1;


public scala.Range indices();
  Code:
   Stack=1, Locals=1, Args_size=1
   0:	aload_0
   1:	invokestatic	#767; //Method scala/collection/generic/SequenceTemplate$class.indices:(Lscala/collection/generic/SequenceTemplate;)Lscala/Range;
   4:	areturn
  LineNumberTable: 
   line 39: 0


public scala.collection.Sequence toSequence();
  Code:
   Stack=1, Locals=1, Args_size=1
   0:	aload_0
   1:	invokestatic	#771; //Method scala/collection/generic/SequenceTemplate$class.toSequence:(Lscala/collection/generic/SequenceTemplate;)Lscala/collection/Sequence;
   4:	areturn
  LineNumberTable: 
   line 39: 0


public scala.collection.generic.IterableTemplate removeDuplicates();
  Code:
   Stack=1, Locals=1, Args_size=1
   0:	aload_0
   1:	invokestatic	#775; //Method scala/collection/generic/SequenceTemplate$class.removeDuplicates:(Lscala/collection/generic/SequenceTemplate;)Lscala/collection/generic/IterableTemplate;
   4:	areturn
  LineNumberTable: 
   line 39: 0


public scala.collection.generic.IterableTemplate intersect(scala.collection.Sequence);
  Code:
   Stack=2, Locals=2, Args_size=2
   0:	aload_0
   1:	aload_1
   2:	invokestatic	#780; //Method scala/collection/generic/SequenceTemplate$class.intersect:(Lscala/collection/generic/SequenceTemplate;Lscala/collection/Sequence;)Lscala/collection/generic/IterableTemplate;
   5:	areturn
  LineNumberTable: 
   line 39: 0

  LocalVariableTable: 
   Start  Length  Slot  Name   Signature
   0      6      0    this       Lscala/GenericRange;
   0      6      1    that       Lscala/collection/Sequence;


public scala.collection.generic.IterableTemplate diff(scala.collection.Sequence);
  Code:
   Stack=2, Locals=2, Args_size=2
   0:	aload_0
   1:	aload_1
   2:	invokestatic	#783; //Method scala/collection/generic/SequenceTemplate$class.diff:(Lscala/collection/generic/SequenceTemplate;Lscala/collection/Sequence;)Lscala/collection/generic/IterableTemplate;
   5:	areturn
  LineNumberTable: 
   line 39: 0

  LocalVariableTable: 
   Start  Length  Slot  Name   Signature
   0      6      0    this       Lscala/GenericRange;
   0      6      1    that       Lscala/collection/Sequence;


public java.lang.Object union(scala.collection.Sequence, scala.collection.generic.BuilderFactory);
  Code:
   Stack=3, Locals=3, Args_size=3
   0:	aload_0
   1:	aload_1
   2:	aload_2
   3:	invokestatic	#788; //Method scala/collection/generic/SequenceTemplate$class.union:(Lscala/collection/generic/SequenceTemplate;Lscala/collection/Sequence;Lscala/collection/generic/BuilderFactory;)Ljava/lang/Object;
   6:	areturn
  LineNumberTable: 
   line 39: 0

  LocalVariableTable: 
   Start  Length  Slot  Name   Signature
   0      7      0    this       Lscala/GenericRange;
   0      7      1    that       Lscala/collection/Sequence;
   0      7      2    bf       Lscala/collection/generic/BuilderFactory;


public int lastIndexOfSeq(scala.collection.Sequence, int);
  Code:
   Stack=3, Locals=3, Args_size=3
   0:	aload_0
   1:	aload_1
   2:	iload_2
   3:	invokestatic	#793; //Method scala/collection/generic/SequenceTemplate$class.lastIndexOfSeq:(Lscala/collection/generic/SequenceTemplate;Lscala/collection/Sequence;I)I
   6:	ireturn
  LineNumberTable: 
   line 39: 0

  LocalVariableTable: 
   Start  Length  Slot  Name   Signature
   0      7      0    this       Lscala/GenericRange;
   0      7      1    that       Lscala/collection/Sequence;
   0      7      2    fromIndex       I


public int lastIndexOfSeq(scala.collection.Sequence);
  Code:
   Stack=2, Locals=2, Args_size=2
   0:	aload_0
   1:	aload_1
   2:	invokestatic	#798; //Method scala/collection/generic/SequenceTemplate$class.lastIndexOfSeq:(Lscala/collection/generic/SequenceTemplate;Lscala/collection/Sequence;)I
   5:	ireturn
  LineNumberTable: 
   line 39: 0

  LocalVariableTable: 
   Start  Length  Slot  Name   Signature
   0      6      0    this       Lscala/GenericRange;
   0      6      1    that       Lscala/collection/Sequence;


public int indexOfSeq(scala.collection.Sequence, int);
  Code:
   Stack=3, Locals=3, Args_size=3
   0:	aload_0
   1:	aload_1
   2:	iload_2
   3:	invokestatic	#801; //Method scala/collection/generic/SequenceTemplate$class.indexOfSeq:(Lscala/collection/generic/SequenceTemplate;Lscala/collection/Sequence;I)I
   6:	ireturn
  LineNumberTable: 
   line 39: 0

  LocalVariableTable: 
   Start  Length  Slot  Name   Signature
   0      7      0    this       Lscala/GenericRange;
   0      7      1    that       Lscala/collection/Sequence;
   0      7      2    fromIndex       I


public int indexOfSeq(scala.collection.Sequence);
  Code:
   Stack=2, Locals=2, Args_size=2
   0:	aload_0
   1:	aload_1
   2:	invokestatic	#803; //Method scala/collection/generic/SequenceTemplate$class.indexOfSeq:(Lscala/collection/generic/SequenceTemplate;Lscala/collection/Sequence;)I
   5:	ireturn
  LineNumberTable: 
   line 39: 0

  LocalVariableTable: 
   Start  Length  Slot  Name   Signature
   0      6      0    this       Lscala/GenericRange;
   0      6      1    that       Lscala/collection/Sequence;


public boolean startsWith(scala.collection.Sequence);
  Code:
   Stack=2, Locals=2, Args_size=2
   0:	aload_0
   1:	aload_1
   2:	invokestatic	#806; //Method scala/collection/generic/SequenceTemplate$class.startsWith:(Lscala/collection/generic/SequenceTemplate;Lscala/collection/Sequence;)Z
   5:	ireturn
  LineNumberTable: 
   line 39: 0

  LocalVariableTable: 
   Start  Length  Slot  Name   Signature
   0      6      0    this       Lscala/GenericRange;
   0      6      1    that       Lscala/collection/Sequence;


public scala.collection.Iterator reversedElements();
  Code:
   Stack=1, Locals=1, Args_size=1
   0:	aload_0
   1:	invokestatic	#810; //Method scala/collection/generic/SequenceTemplate$class.reversedElements:(Lscala/collection/generic/SequenceTemplate;)Lscala/collection/Iterator;
   4:	areturn
  LineNumberTable: 
   line 39: 0


public int lastIndexWhere(scala.Function1);
  Code:
   Stack=2, Locals=2, Args_size=2
   0:	aload_0
   1:	aload_1
   2:	invokestatic	#813; //Method scala/collection/generic/SequenceTemplate$class.lastIndexWhere:(Lscala/collection/generic/SequenceTemplate;Lscala/Function1;)I
   5:	ireturn
  LineNumberTable: 
   line 39: 0

  LocalVariableTable: 
   Start  Length  Slot  Name   Signature
   0      6      0    this       Lscala/GenericRange;
   0      6      1    p       Lscala/Function1;


public int lastIndexOf(java.lang.Object, int);
  Code:
   Stack=3, Locals=3, Args_size=3
   0:	aload_0
   1:	aload_1
   2:	iload_2
   3:	invokestatic	#818; //Method scala/collection/generic/SequenceTemplate$class.lastIndexOf:(Lscala/collection/generic/SequenceTemplate;Ljava/lang/Object;I)I
   6:	ireturn
  LineNumberTable: 
   line 39: 0

  LocalVariableTable: 
   Start  Length  Slot  Name   Signature
   0      7      0    this       Lscala/GenericRange;
   0      7      1    elem       Ljava/lang/Object;
   0      7      2    end       I


public int lastIndexOf(java.lang.Object);
  Code:
   Stack=2, Locals=2, Args_size=2
   0:	aload_0
   1:	aload_1
   2:	invokestatic	#821; //Method scala/collection/generic/SequenceTemplate$class.lastIndexOf:(Lscala/collection/generic/SequenceTemplate;Ljava/lang/Object;)I
   5:	ireturn
  LineNumberTable: 
   line 39: 0

  LocalVariableTable: 
   Start  Length  Slot  Name   Signature
   0      6      0    this       Lscala/GenericRange;
   0      6      1    elem       Ljava/lang/Object;


public int indexOf(java.lang.Object, int);
  Code:
   Stack=3, Locals=3, Args_size=3
   0:	aload_0
   1:	aload_1
   2:	iload_2
   3:	invokestatic	#824; //Method scala/collection/generic/SequenceTemplate$class.indexOf:(Lscala/collection/generic/SequenceTemplate;Ljava/lang/Object;I)I
   6:	ireturn
  LineNumberTable: 
   line 39: 0

  LocalVariableTable: 
   Start  Length  Slot  Name   Signature
   0      7      0    this       Lscala/GenericRange;
   0      7      1    elem       Ljava/lang/Object;
   0      7      2    from       I


public int indexOf(java.lang.Object);
  Code:
   Stack=2, Locals=2, Args_size=2
   0:	aload_0
   1:	aload_1
   2:	invokestatic	#826; //Method scala/collection/generic/SequenceTemplate$class.indexOf:(Lscala/collection/generic/SequenceTemplate;Ljava/lang/Object;)I
   5:	ireturn
  LineNumberTable: 
   line 39: 0

  LocalVariableTable: 
   Start  Length  Slot  Name   Signature
   0      6      0    this       Lscala/GenericRange;
   0      6      1    elem       Ljava/lang/Object;


public int findIndexOf(scala.Function1);
  Code:
   Stack=2, Locals=2, Args_size=2
   0:	aload_0
   1:	aload_1
   2:	invokestatic	#829; //Method scala/collection/generic/SequenceTemplate$class.findIndexOf:(Lscala/collection/generic/SequenceTemplate;Lscala/Function1;)I
   5:	ireturn
  LineNumberTable: 
   line 39: 0

  LocalVariableTable: 
   Start  Length  Slot  Name   Signature
   0      6      0    this       Lscala/GenericRange;
   0      6      1    p       Lscala/Function1;


public int indexWhere(scala.Function1);
  Code:
   Stack=2, Locals=2, Args_size=2
   0:	aload_0
   1:	aload_1
   2:	invokestatic	#832; //Method scala/collection/generic/SequenceTemplate$class.indexWhere:(Lscala/collection/generic/SequenceTemplate;Lscala/Function1;)I
   5:	ireturn
  LineNumberTable: 
   line 39: 0

  LocalVariableTable: 
   Start  Length  Slot  Name   Signature
   0      6      0    this       Lscala/GenericRange;
   0      6      1    p       Lscala/Function1;


public int prefixLength(scala.Function1);
  Code:
   Stack=2, Locals=2, Args_size=2
   0:	aload_0
   1:	aload_1
   2:	invokestatic	#835; //Method scala/collection/generic/SequenceTemplate$class.prefixLength:(Lscala/collection/generic/SequenceTemplate;Lscala/Function1;)I
   5:	ireturn
  LineNumberTable: 
   line 39: 0

  LocalVariableTable: 
   Start  Length  Slot  Name   Signature
   0      6      0    this       Lscala/GenericRange;
   0      6      1    p       Lscala/Function1;


public boolean isDefinedAt(int);
  Code:
   Stack=2, Locals=2, Args_size=2
   0:	aload_0
   1:	iload_1
   2:	invokestatic	#838; //Method scala/collection/generic/SequenceTemplate$class.isDefinedAt:(Lscala/collection/generic/SequenceTemplate;I)Z
   5:	ireturn
  LineNumberTable: 
   line 39: 0

  LocalVariableTable: 
   Start  Length  Slot  Name   Signature
   0      6      0    this       Lscala/GenericRange;
   0      6      1    x       I


public int size();
  Code:
   Stack=1, Locals=1, Args_size=1
   0:	aload_0
   1:	invokestatic	#842; //Method scala/collection/generic/SequenceTemplate$class.size:(Lscala/collection/generic/SequenceTemplate;)I
   4:	ireturn
  LineNumberTable: 
   line 39: 0


public scala.collection.generic.VectorView view(int, int);
  Code:
   Stack=3, Locals=3, Args_size=3
   0:	aload_0
   1:	iload_1
   2:	iload_2
   3:	invokestatic	#845; //Method scala/collection/generic/VectorTemplate$class.view:(Lscala/collection/generic/VectorTemplate;II)Lscala/collection/generic/VectorView;
   6:	areturn
  LineNumberTable: 
   line 39: 0

  LocalVariableTable: 
   Start  Length  Slot  Name   Signature
   0      7      0    this       Lscala/GenericRange;
   0      7      1    from       I
   0      7      2    until       I


public java.lang.Object view();
  Code:
   Stack=1, Locals=1, Args_size=1
   0:	aload_0
   1:	invokestatic	#848; //Method scala/collection/generic/VectorTemplate$class.view:(Lscala/collection/generic/VectorTemplate;)Ljava/lang/Object;
   4:	areturn
  LineNumberTable: 
   line 39: 0


public boolean endsWith(scala.collection.Sequence);
  Code:
   Stack=2, Locals=2, Args_size=2
   0:	aload_0
   1:	aload_1
   2:	invokestatic	#852; //Method scala/collection/generic/VectorTemplate$class.endsWith:(Lscala/collection/generic/VectorTemplate;Lscala/collection/Sequence;)Z
   5:	ireturn
  LineNumberTable: 
   line 39: 0

  LocalVariableTable: 
   Start  Length  Slot  Name   Signature
   0      6      0    this       Lscala/GenericRange;
   0      6      1    that       Lscala/collection/Sequence;


public boolean startsWith(scala.collection.Sequence, int);
  Code:
   Stack=3, Locals=3, Args_size=3
   0:	aload_0
   1:	aload_1
   2:	iload_2
   3:	invokestatic	#856; //Method scala/collection/generic/VectorTemplate$class.startsWith:(Lscala/collection/generic/VectorTemplate;Lscala/collection/Sequence;I)Z
   6:	ireturn
  LineNumberTable: 
   line 39: 0

  LocalVariableTable: 
   Start  Length  Slot  Name   Signature
   0      7      0    this       Lscala/GenericRange;
   0      7      1    that       Lscala/collection/Sequence;
   0      7      2    offset       I


public scala.collection.Iterator reverseIterator();
  Code:
   Stack=1, Locals=1, Args_size=1
   0:	aload_0
   1:	invokestatic	#861; //Method scala/collection/generic/VectorTemplate$class.reverseIterator:(Lscala/collection/generic/VectorTemplate;)Lscala/collection/Iterator;
   4:	areturn
  LineNumberTable: 
   line 39: 0


public int lastIndexWhere(scala.Function1, int);
  Code:
   Stack=3, Locals=3, Args_size=3
   0:	aload_0
   1:	aload_1
   2:	iload_2
   3:	invokestatic	#865; //Method scala/collection/generic/VectorTemplate$class.lastIndexWhere:(Lscala/collection/generic/VectorTemplate;Lscala/Function1;I)I
   6:	ireturn
  LineNumberTable: 
   line 39: 0

  LocalVariableTable: 
   Start  Length  Slot  Name   Signature
   0      7      0    this       Lscala/GenericRange;
   0      7      1    p       Lscala/Function1;
   0      7      2    end       I


public int indexWhere(scala.Function1, int);
  Code:
   Stack=3, Locals=3, Args_size=3
   0:	aload_0
   1:	aload_1
   2:	iload_2
   3:	invokestatic	#867; //Method scala/collection/generic/VectorTemplate$class.indexWhere:(Lscala/collection/generic/VectorTemplate;Lscala/Function1;I)I
   6:	ireturn
  LineNumberTable: 
   line 39: 0

  LocalVariableTable: 
   Start  Length  Slot  Name   Signature
   0      7      0    this       Lscala/GenericRange;
   0      7      1    p       Lscala/Function1;
   0      7      2    from       I


public int segmentLength(scala.Function1, int);
  Code:
   Stack=3, Locals=3, Args_size=3
   0:	aload_0
   1:	aload_1
   2:	iload_2
   3:	invokestatic	#870; //Method scala/collection/generic/VectorTemplate$class.segmentLength:(Lscala/collection/generic/VectorTemplate;Lscala/Function1;I)I
   6:	ireturn
  LineNumberTable: 
   line 39: 0

  LocalVariableTable: 
   Start  Length  Slot  Name   Signature
   0      7      0    this       Lscala/GenericRange;
   0      7      1    p       Lscala/Function1;
   0      7      2    from       I


public int lengthCompare(int);
  Code:
   Stack=2, Locals=2, Args_size=2
   0:	aload_0
   1:	iload_1
   2:	invokestatic	#875; //Method scala/collection/generic/VectorTemplate$class.lengthCompare:(Lscala/collection/generic/VectorTemplate;I)I
   5:	ireturn
  LineNumberTable: 
   line 39: 0

  LocalVariableTable: 
   Start  Length  Slot  Name   Signature
   0      6      0    this       Lscala/GenericRange;
   0      6      1    len       I


public void copyToArray(scala.runtime.BoxedArray, int, int);
  Code:
   Stack=4, Locals=4, Args_size=4
   0:	aload_0
   1:	aload_1
   2:	iload_2
   3:	iload_3
   4:	invokestatic	#880; //Method scala/collection/generic/VectorTemplate$class.copyToArray:(Lscala/collection/generic/VectorTemplate;Lscala/runtime/BoxedArray;II)V
   7:	return
  LineNumberTable: 
   line 39: 0

  LocalVariableTable: 
   Start  Length  Slot  Name   Signature
   0      8      0    this       Lscala/GenericRange;
   0      8      1    xs       Lscala/runtime/BoxedArray;
   0      8      2    start       I
   0      8      3    len       I


public boolean sameElements(scala.collection.Iterable);
  Code:
   Stack=2, Locals=2, Args_size=2
   0:	aload_0
   1:	aload_1
   2:	invokestatic	#885; //Method scala/collection/generic/VectorTemplate$class.sameElements:(Lscala/collection/generic/VectorTemplate;Lscala/collection/Iterable;)Z
   5:	ireturn
  LineNumberTable: 
   line 39: 0

  LocalVariableTable: 
   Start  Length  Slot  Name   Signature
   0      6      0    this       Lscala/GenericRange;
   0      6      1    that       Lscala/collection/Iterable;


public scala.collection.generic.VectorTemplate dropRight(int);
  Code:
   Stack=2, Locals=2, Args_size=2
   0:	aload_0
   1:	iload_1
   2:	invokestatic	#889; //Method scala/collection/generic/VectorTemplate$class.dropRight:(Lscala/collection/generic/VectorTemplate;I)Lscala/collection/generic/VectorTemplate;
   5:	areturn
  LineNumberTable: 
   line 39: 0

  LocalVariableTable: 
   Start  Length  Slot  Name   Signature
   0      6      0    this       Lscala/GenericRange;
   0      6      1    n       I


public scala.collection.generic.VectorTemplate takeRight(int);
  Code:
   Stack=2, Locals=2, Args_size=2
   0:	aload_0
   1:	iload_1
   2:	invokestatic	#891; //Method scala/collection/generic/VectorTemplate$class.takeRight:(Lscala/collection/generic/VectorTemplate;I)Lscala/collection/generic/VectorTemplate;
   5:	areturn
  LineNumberTable: 
   line 39: 0

  LocalVariableTable: 
   Start  Length  Slot  Name   Signature
   0      6      0    this       Lscala/GenericRange;
   0      6      1    n       I


public java.lang.Object last();
  Code:
   Stack=1, Locals=1, Args_size=1
   0:	aload_0
   1:	invokestatic	#894; //Method scala/collection/generic/VectorTemplate$class.last:(Lscala/collection/generic/VectorTemplate;)Ljava/lang/Object;
   4:	areturn
  LineNumberTable: 
   line 39: 0


public scala.collection.generic.VectorTemplate tail();
  Code:
   Stack=1, Locals=1, Args_size=1
   0:	aload_0
   1:	invokestatic	#897; //Method scala/collection/generic/VectorTemplate$class.tail:(Lscala/collection/generic/VectorTemplate;)Lscala/collection/generic/VectorTemplate;
   4:	areturn
  LineNumberTable: 
   line 39: 0


public java.lang.Object head();
  Code:
   Stack=1, Locals=1, Args_size=1
   0:	aload_0
   1:	invokestatic	#900; //Method scala/collection/generic/VectorTemplate$class.head:(Lscala/collection/generic/VectorTemplate;)Ljava/lang/Object;
   4:	areturn
  LineNumberTable: 
   line 39: 0


public java.lang.Object reduceRight(scala.Function2);
  Code:
   Stack=2, Locals=2, Args_size=2
   0:	aload_0
   1:	aload_1
   2:	invokestatic	#905; //Method scala/collection/generic/VectorTemplate$class.reduceRight:(Lscala/collection/generic/VectorTemplate;Lscala/Function2;)Ljava/lang/Object;
   5:	areturn
  LineNumberTable: 
   line 39: 0

  LocalVariableTable: 
   Start  Length  Slot  Name   Signature
   0      6      0    this       Lscala/GenericRange;
   0      6      1    op       Lscala/Function2;


public java.lang.Object reduceLeft(scala.Function2);
  Code:
   Stack=2, Locals=2, Args_size=2
   0:	aload_0
   1:	aload_1
   2:	invokestatic	#908; //Method scala/collection/generic/VectorTemplate$class.reduceLeft:(Lscala/collection/generic/VectorTemplate;Lscala/Function2;)Ljava/lang/Object;
   5:	areturn
  LineNumberTable: 
   line 39: 0

  LocalVariableTable: 
   Start  Length  Slot  Name   Signature
   0      6      0    this       Lscala/GenericRange;
   0      6      1    op       Lscala/Function2;


public java.lang.Object foldRight(java.lang.Object, scala.Function2);
  Code:
   Stack=3, Locals=3, Args_size=3
   0:	aload_0
   1:	aload_1
   2:	aload_2
   3:	invokestatic	#912; //Method scala/collection/generic/VectorTemplate$class.foldRight:(Lscala/collection/generic/VectorTemplate;Ljava/lang/Object;Lscala/Function2;)Ljava/lang/Object;
   6:	areturn
  LineNumberTable: 
   line 39: 0

  LocalVariableTable: 
   Start  Length  Slot  Name   Signature
   0      7      0    this       Lscala/GenericRange;
   0      7      1    z       Ljava/lang/Object;
   0      7      2    op       Lscala/Function2;


public java.lang.Object foldLeft(java.lang.Object, scala.Function2);
  Code:
   Stack=3, Locals=3, Args_size=3
   0:	aload_0
   1:	aload_1
   2:	aload_2
   3:	invokestatic	#915; //Method scala/collection/generic/VectorTemplate$class.foldLeft:(Lscala/collection/generic/VectorTemplate;Ljava/lang/Object;Lscala/Function2;)Ljava/lang/Object;
   6:	areturn
  LineNumberTable: 
   line 39: 0

  LocalVariableTable: 
   Start  Length  Slot  Name   Signature
   0      7      0    this       Lscala/GenericRange;
   0      7      1    z       Ljava/lang/Object;
   0      7      2    op       Lscala/Function2;


public scala.Option find(scala.Function1);
  Code:
   Stack=2, Locals=2, Args_size=2
   0:	aload_0
   1:	aload_1
   2:	invokestatic	#920; //Method scala/collection/generic/VectorTemplate$class.find:(Lscala/collection/generic/VectorTemplate;Lscala/Function1;)Lscala/Option;
   5:	areturn
  LineNumberTable: 
   line 39: 0

  LocalVariableTable: 
   Start  Length  Slot  Name   Signature
   0      6      0    this       Lscala/GenericRange;
   0      6      1    p       Lscala/Function1;


public boolean exists(scala.Function1);
  Code:
   Stack=2, Locals=2, Args_size=2
   0:	aload_0
   1:	aload_1
   2:	invokestatic	#925; //Method scala/collection/generic/VectorTemplate$class.exists:(Lscala/collection/generic/VectorTemplate;Lscala/Function1;)Z
   5:	ireturn
  LineNumberTable: 
   line 39: 0

  LocalVariableTable: 
   Start  Length  Slot  Name   Signature
   0      6      0    this       Lscala/GenericRange;
   0      6      1    p       Lscala/Function1;


public boolean forall(scala.Function1);
  Code:
   Stack=2, Locals=2, Args_size=2
   0:	aload_0
   1:	aload_1
   2:	invokestatic	#928; //Method scala/collection/generic/VectorTemplate$class.forall:(Lscala/collection/generic/VectorTemplate;Lscala/Function1;)Z
   5:	ireturn
  LineNumberTable: 
   line 39: 0

  LocalVariableTable: 
   Start  Length  Slot  Name   Signature
   0      6      0    this       Lscala/GenericRange;
   0      6      1    p       Lscala/Function1;


public boolean isEmpty();
  Code:
   Stack=1, Locals=1, Args_size=1
   0:	aload_0
   1:	invokestatic	#932; //Method scala/collection/generic/VectorTemplate$class.isEmpty:(Lscala/collection/generic/VectorTemplate;)Z
   4:	ireturn
  LineNumberTable: 
   line 39: 0


public scala.collection.Iterator iterator();
  Code:
   Stack=1, Locals=1, Args_size=1
   0:	aload_0
   1:	invokestatic	#935; //Method scala/collection/generic/VectorTemplate$class.iterator:(Lscala/collection/generic/VectorTemplate;)Lscala/collection/Iterator;
   4:	areturn
  LineNumberTable: 
   line 39: 0


public final boolean scala$collection$generic$VectorTemplate$$super$equals(java.lang.Object);
  Code:
   Stack=2, Locals=2, Args_size=2
   0:	aload_0
   1:	aload_1
   2:	invokestatic	#938; //Method scala/collection/generic/SequenceTemplate$class.equals:(Lscala/collection/generic/SequenceTemplate;Ljava/lang/Object;)Z
   5:	ireturn
  LineNumberTable: 
   line 39: 0

  LocalVariableTable: 
   Start  Length  Slot  Name   Signature
   0      6      0    this       Lscala/GenericRange;
   0      6      1    that       Ljava/lang/Object;


public final boolean scala$collection$generic$VectorTemplate$$super$endsWith(scala.collection.Sequence);
  Code:
   Stack=2, Locals=2, Args_size=2
   0:	aload_0
   1:	aload_1
   2:	invokestatic	#941; //Method scala/collection/generic/SequenceTemplate$class.endsWith:(Lscala/collection/generic/SequenceTemplate;Lscala/collection/Sequence;)Z
   5:	ireturn
  LineNumberTable: 
   line 39: 0

  LocalVariableTable: 
   Start  Length  Slot  Name   Signature
   0      6      0    this       Lscala/GenericRange;
   0      6      1    that       Lscala/collection/Sequence;


public final boolean scala$collection$generic$VectorTemplate$$super$sameElements(scala.collection.Iterable);
  Code:
   Stack=2, Locals=2, Args_size=2
   0:	aload_0
   1:	aload_1
   2:	invokestatic	#945; //Method scala/collection/generic/IterableTemplate$class.sameElements:(Lscala/collection/generic/IterableTemplate;Lscala/collection/Iterable;)Z
   5:	ireturn
  LineNumberTable: 
   line 39: 0

  LocalVariableTable: 
   Start  Length  Slot  Name   Signature
   0      6      0    this       Lscala/GenericRange;
   0      6      1    that       Lscala/collection/Iterable;


public final scala.collection.generic.VectorTemplate scala$collection$generic$VectorTemplate$$super$init();
  Code:
   Stack=1, Locals=1, Args_size=1
   0:	aload_0
   1:	invokestatic	#948; //Method scala/collection/generic/TraversableTemplate$class.init:(Lscala/collection/generic/TraversableTemplate;)Lscala/collection/generic/TraversableTemplate;
   4:	checkcast	#347; //class scala/collection/generic/VectorTemplate
   7:	areturn
  LineNumberTable: 
   line 39: 0


public final java.lang.Object scala$collection$generic$VectorTemplate$$super$last();
  Code:
   Stack=1, Locals=1, Args_size=1
   0:	aload_0
   1:	invokestatic	#952; //Method scala/collection/generic/TraversableTemplate$class.last:(Lscala/collection/generic/TraversableTemplate;)Ljava/lang/Object;
   4:	areturn
  LineNumberTable: 
   line 39: 0


public final java.lang.Object scala$collection$generic$VectorTemplate$$super$head();
  Code:
   Stack=1, Locals=1, Args_size=1
   0:	aload_0
   1:	invokestatic	#955; //Method scala/collection/generic/IterableTemplate$class.head:(Lscala/collection/generic/IterableTemplate;)Ljava/lang/Object;
   4:	areturn
  LineNumberTable: 
   line 39: 0


public final java.lang.Object scala$collection$generic$VectorTemplate$$super$zip(scala.collection.Sequence, scala.collection.generic.BuilderFactory);
  Code:
   Stack=3, Locals=3, Args_size=3
   0:	aload_0
   1:	aload_1
   2:	aload_2
   3:	invokestatic	#959; //Method scala/collection/generic/SequenceTemplate$class.zip:(Lscala/collection/generic/SequenceTemplate;Lscala/collection/Sequence;Lscala/collection/generic/BuilderFactory;)Ljava/lang/Object;
   6:	areturn
  LineNumberTable: 
   line 39: 0

  LocalVariableTable: 
   Start  Length  Slot  Name   Signature
   0      7      0    this       Lscala/GenericRange;
   0      7      1    that       Lscala/collection/Sequence;
   0      7      2    bf       Lscala/collection/generic/BuilderFactory;


public final java.lang.Object scala$collection$generic$VectorTemplate$$super$reduceRight(scala.Function2);
  Code:
   Stack=2, Locals=2, Args_size=2
   0:	aload_0
   1:	aload_1
   2:	invokestatic	#963; //Method scala/collection/generic/IterableTemplate$class.reduceRight:(Lscala/collection/generic/IterableTemplate;Lscala/Function2;)Ljava/lang/Object;
   5:	areturn
  LineNumberTable: 
   line 39: 0

  LocalVariableTable: 
   Start  Length  Slot  Name   Signature
   0      6      0    this       Lscala/GenericRange;
   0      6      1    op       Lscala/Function2;


public final java.lang.Object scala$collection$generic$VectorTemplate$$super$reduceLeft(scala.Function2);
  Code:
   Stack=2, Locals=2, Args_size=2
   0:	aload_0
   1:	aload_1
   2:	invokestatic	#967; //Method scala/collection/generic/TraversableTemplate$class.reduceLeft:(Lscala/collection/generic/TraversableTemplate;Lscala/Function2;)Ljava/lang/Object;
   5:	areturn
  LineNumberTable: 
   line 39: 0

  LocalVariableTable: 
   Start  Length  Slot  Name   Signature
   0      6      0    this       Lscala/GenericRange;
   0      6      1    op       Lscala/Function2;


public scala.collection.generic.Companion companion();
  Code:
   Stack=1, Locals=1, Args_size=1
   0:	aload_0
   1:	invokestatic	#972; //Method scala/collection/Vector$class.companion:(Lscala/collection/Vector;)Lscala/collection/generic/Companion;
   4:	areturn
  LineNumberTable: 
   line 39: 0


public scala.Tuple2 splitAt(int);
  Code:
   Stack=2, Locals=2, Args_size=2
   0:	aload_0
   1:	iload_1
   2:	invokestatic	#977; //Method scala/collection/generic/TraversableViewTemplate$class.splitAt:(Lscala/collection/generic/TraversableViewTemplate;I)Lscala/Tuple2;
   5:	areturn
  LineNumberTable: 
   line 39: 0

  LocalVariableTable: 
   Start  Length  Slot  Name   Signature
   0      6      0    this       Lscala/GenericRange;
   0      6      1    n       I


public scala.Tuple2 span(scala.Function1);
  Code:
   Stack=2, Locals=2, Args_size=2
   0:	aload_0
   1:	aload_1
   2:	invokestatic	#981; //Method scala/collection/generic/TraversableViewTemplate$class.span:(Lscala/collection/generic/TraversableViewTemplate;Lscala/Function1;)Lscala/Tuple2;
   5:	areturn
  LineNumberTable: 
   line 39: 0

  LocalVariableTable: 
   Start  Length  Slot  Name   Signature
   0      6      0    this       Lscala/GenericRange;
   0      6      1    p       Lscala/Function1;


public scala.collection.generic.TraversableView takeWhile(scala.Function1);
  Code:
   Stack=2, Locals=2, Args_size=2
   0:	aload_0
   1:	aload_1
   2:	invokestatic	#984; //Method scala/collection/generic/TraversableViewTemplate$class.takeWhile:(Lscala/collection/generic/TraversableViewTemplate;Lscala/Function1;)Lscala/collection/generic/TraversableView;
   5:	areturn
  LineNumberTable: 
   line 39: 0

  LocalVariableTable: 
   Start  Length  Slot  Name   Signature
   0      6      0    this       Lscala/GenericRange;
   0      6      1    p       Lscala/Function1;


public scala.collection.generic.TraversableView dropWhile(scala.Function1);
  Code:
   Stack=2, Locals=2, Args_size=2
   0:	aload_0
   1:	aload_1
   2:	invokestatic	#986; //Method scala/collection/generic/TraversableViewTemplate$class.dropWhile:(Lscala/collection/generic/TraversableViewTemplate;Lscala/Function1;)Lscala/collection/generic/TraversableView;
   5:	areturn
  LineNumberTable: 
   line 39: 0

  LocalVariableTable: 
   Start  Length  Slot  Name   Signature
   0      6      0    this       Lscala/GenericRange;
   0      6      1    p       Lscala/Function1;


public scala.collection.generic.TraversableView slice(int, int);
  Code:
   Stack=3, Locals=3, Args_size=3
   0:	aload_0
   1:	iload_1
   2:	iload_2
   3:	invokestatic	#989; //Method scala/collection/generic/TraversableViewTemplate$class.slice:(Lscala/collection/generic/TraversableViewTemplate;II)Lscala/collection/generic/TraversableView;
   6:	areturn
  LineNumberTable: 
   line 39: 0

  LocalVariableTable: 
   Start  Length  Slot  Name   Signature
   0      7      0    this       Lscala/GenericRange;
   0      7      1    from       I
   0      7      2    until       I


public scala.collection.generic.TraversableView take(int);
  Code:
   Stack=2, Locals=2, Args_size=2
   0:	aload_0
   1:	iload_1
   2:	invokestatic	#992; //Method scala/collection/generic/TraversableViewTemplate$class.take:(Lscala/collection/generic/TraversableViewTemplate;I)Lscala/collection/generic/TraversableView;
   5:	areturn
  LineNumberTable: 
   line 39: 0

  LocalVariableTable: 
   Start  Length  Slot  Name   Signature
   0      6      0    this       Lscala/GenericRange;
   0      6      1    n       I


public scala.collection.generic.TraversableView drop(int);
  Code:
   Stack=2, Locals=2, Args_size=2
   0:	aload_0
   1:	iload_1
   2:	invokestatic	#994; //Method scala/collection/generic/TraversableViewTemplate$class.drop:(Lscala/collection/generic/TraversableViewTemplate;I)Lscala/collection/generic/TraversableView;
   5:	areturn
  LineNumberTable: 
   line 39: 0

  LocalVariableTable: 
   Start  Length  Slot  Name   Signature
   0      6      0    this       Lscala/GenericRange;
   0      6      1    n       I


public scala.collection.generic.TraversableView init();
  Code:
   Stack=1, Locals=1, Args_size=1
   0:	aload_0
   1:	invokestatic	#997; //Method scala/collection/generic/TraversableViewTemplate$class.init:(Lscala/collection/generic/TraversableViewTemplate;)Lscala/collection/generic/TraversableView;
   4:	areturn
  LineNumberTable: 
   line 39: 0


public scala.collection.generic.TraversableView filter(scala.Function1);
  Code:
   Stack=2, Locals=2, Args_size=2
   0:	aload_0
   1:	aload_1
   2:	invokestatic	#999; //Method scala/collection/generic/TraversableViewTemplate$class.filter:(Lscala/collection/generic/TraversableViewTemplate;Lscala/Function1;)Lscala/collection/generic/TraversableView;
   5:	areturn
  LineNumberTable: 
   line 39: 0

  LocalVariableTable: 
   Start  Length  Slot  Name   Signature
   0      6      0    this       Lscala/GenericRange;
   0      6      1    p       Lscala/Function1;


public java.lang.Object flatMap(scala.Function1, scala.collection.generic.BuilderFactory);
  Code:
   Stack=3, Locals=3, Args_size=3
   0:	aload_0
   1:	aload_1
   2:	aload_2
   3:	invokestatic	#1004; //Method scala/collection/generic/TraversableViewTemplate$class.flatMap:(Lscala/collection/generic/TraversableViewTemplate;Lscala/Function1;Lscala/collection/generic/BuilderFactory;)Ljava/lang/Object;
   6:	areturn
  LineNumberTable: 
   line 39: 0

  LocalVariableTable: 
   Start  Length  Slot  Name   Signature
   0      7      0    this       Lscala/GenericRange;
   0      7      1    f       Lscala/Function1;
   0      7      2    bf       Lscala/collection/generic/BuilderFactory;


public java.lang.Object map(scala.Function1, scala.collection.generic.BuilderFactory);
  Code:
   Stack=3, Locals=3, Args_size=3
   0:	aload_0
   1:	aload_1
   2:	aload_2
   3:	invokestatic	#1007; //Method scala/collection/generic/TraversableViewTemplate$class.map:(Lscala/collection/generic/TraversableViewTemplate;Lscala/Function1;Lscala/collection/generic/BuilderFactory;)Ljava/lang/Object;
   6:	areturn
  LineNumberTable: 
   line 39: 0

  LocalVariableTable: 
   Start  Length  Slot  Name   Signature
   0      7      0    this       Lscala/GenericRange;
   0      7      1    f       Lscala/Function1;
   0      7      2    bf       Lscala/collection/generic/BuilderFactory;


public java.lang.Object $plus$plus(scala.collection.Iterator, scala.collection.generic.BuilderFactory);
  Code:
   Stack=3, Locals=3, Args_size=3
   0:	aload_0
   1:	aload_1
   2:	aload_2
   3:	invokestatic	#1012; //Method scala/collection/generic/TraversableViewTemplate$class.$plus$plus:(Lscala/collection/generic/TraversableViewTemplate;Lscala/collection/Iterator;Lscala/collection/generic/BuilderFactory;)Ljava/lang/Object;
   6:	areturn
  LineNumberTable: 
   line 39: 0

  LocalVariableTable: 
   Start  Length  Slot  Name   Signature
   0      7      0    this       Lscala/GenericRange;
   0      7      1    that       Lscala/collection/Iterator;
   0      7      2    bf       Lscala/collection/generic/BuilderFactory;


public java.lang.Object $plus$plus(scala.collection.Traversable, scala.collection.generic.BuilderFactory);
  Code:
   Stack=3, Locals=3, Args_size=3
   0:	aload_0
   1:	aload_1
   2:	aload_2
   3:	invokestatic	#1017; //Method scala/collection/generic/TraversableViewTemplate$class.$plus$plus:(Lscala/collection/generic/TraversableViewTemplate;Lscala/collection/Traversable;Lscala/collection/generic/BuilderFactory;)Ljava/lang/Object;
   6:	areturn
  LineNumberTable: 
   line 39: 0

  LocalVariableTable: 
   Start  Length  Slot  Name   Signature
   0      7      0    this       Lscala/GenericRange;
   0      7      1    that       Lscala/collection/Traversable;
   0      7      2    bf       Lscala/collection/generic/BuilderFactory;


public java.lang.Object force(scala.collection.generic.BuilderFactory);
  Code:
   Stack=2, Locals=2, Args_size=2
   0:	aload_0
   1:	aload_1
   2:	invokestatic	#1022; //Method scala/collection/generic/TraversableViewTemplate$class.force:(Lscala/collection/generic/TraversableViewTemplate;Lscala/collection/generic/BuilderFactory;)Ljava/lang/Object;
   5:	areturn
  LineNumberTable: 
   line 39: 0

  LocalVariableTable: 
   Start  Length  Slot  Name   Signature
   0      6      0    this       Lscala/GenericRange;
   0      6      1    bf       Lscala/collection/generic/BuilderFactory;


public scala.collection.generic.Builder newBuilder();
  Code:
   Stack=1, Locals=1, Args_size=1
   0:	aload_0
   1:	invokestatic	#1026; //Method scala/collection/generic/TraversableViewTemplate$class.newBuilder:(Lscala/collection/generic/TraversableViewTemplate;)Lscala/collection/generic/Builder;
   4:	areturn
  LineNumberTable: 
   line 39: 0


public java.lang.Object zipAll(scala.collection.Sequence, java.lang.Object, java.lang.Object, scala.collection.generic.BuilderFactory);
  Code:
   Stack=5, Locals=5, Args_size=5
   0:	aload_0
   1:	aload_1
   2:	aload_2
   3:	aload_3
   4:	aload	4
   6:	invokestatic	#1031; //Method scala/collection/generic/SequenceViewTemplate$class.zipAll:(Lscala/collection/generic/SequenceViewTemplate;Lscala/collection/Sequence;Ljava/lang/Object;Ljava/lang/Object;Lscala/collection/generic/BuilderFactory;)Ljava/lang/Object;
   9:	areturn
  LineNumberTable: 
   line 39: 0

  LocalVariableTable: 
   Start  Length  Slot  Name   Signature
   0      10      0    this       Lscala/GenericRange;
   0      10      1    that       Lscala/collection/Sequence;
   0      10      2    thisElem       Ljava/lang/Object;
   0      10      3    thatElem       Ljava/lang/Object;
   0      10      4    bf       Lscala/collection/generic/BuilderFactory;


public java.lang.Object zipWithIndex(scala.collection.generic.BuilderFactory);
  Code:
   Stack=2, Locals=2, Args_size=2
   0:	aload_0
   1:	aload_1
   2:	invokestatic	#1037; //Method scala/collection/generic/SequenceViewTemplate$class.zipWithIndex:(Lscala/collection/generic/SequenceViewTemplate;Lscala/collection/generic/BuilderFactory;)Ljava/lang/Object;
   5:	areturn
  LineNumberTable: 
   line 39: 0

  LocalVariableTable: 
   Start  Length  Slot  Name   Signature
   0      6      0    this       Lscala/GenericRange;
   0      6      1    bf       Lscala/collection/generic/BuilderFactory;


public java.lang.Object zip(scala.collection.Sequence, scala.collection.generic.BuilderFactory);
  Code:
   Stack=3, Locals=3, Args_size=3
   0:	aload_0
   1:	aload_1
   2:	aload_2
   3:	invokestatic	#1040; //Method scala/collection/generic/SequenceViewTemplate$class.zip:(Lscala/collection/generic/SequenceViewTemplate;Lscala/collection/Sequence;Lscala/collection/generic/BuilderFactory;)Ljava/lang/Object;
   6:	areturn
  LineNumberTable: 
   line 39: 0

  LocalVariableTable: 
   Start  Length  Slot  Name   Signature
   0      7      0    this       Lscala/GenericRange;
   0      7      1    that       Lscala/collection/Sequence;
   0      7      2    bf       Lscala/collection/generic/BuilderFactory;


public java.lang.Object padTo(int, java.lang.Object, scala.collection.generic.BuilderFactory);
  Code:
   Stack=4, Locals=4, Args_size=4
   0:	aload_0
   1:	iload_1
   2:	aload_2
   3:	aload_3
   4:	invokestatic	#1045; //Method scala/collection/generic/SequenceViewTemplate$class.padTo:(Lscala/collection/generic/SequenceViewTemplate;ILjava/lang/Object;Lscala/collection/generic/BuilderFactory;)Ljava/lang/Object;
   7:	areturn
  LineNumberTable: 
   line 39: 0

  LocalVariableTable: 
   Start  Length  Slot  Name   Signature
   0      8      0    this       Lscala/GenericRange;
   0      8      1    len       I
   0      8      2    elem       Ljava/lang/Object;
   0      8      3    bf       Lscala/collection/generic/BuilderFactory;


public java.lang.Object patch(int, scala.collection.Sequence, int, scala.collection.generic.BuilderFactory);
  Code:
   Stack=5, Locals=5, Args_size=5
   0:	aload_0
   1:	iload_1
   2:	aload_2
   3:	iload_3
   4:	aload	4
   6:	invokestatic	#1050; //Method scala/collection/generic/SequenceViewTemplate$class.patch:(Lscala/collection/generic/SequenceViewTemplate;ILscala/collection/Sequence;ILscala/collection/generic/BuilderFactory;)Ljava/lang/Object;
   9:	areturn
  LineNumberTable: 
   line 39: 0

  LocalVariableTable: 
   Start  Length  Slot  Name   Signature
   0      10      0    this       Lscala/GenericRange;
   0      10      1    from       I
   0      10      2    patch       Lscala/collection/Sequence;
   0      10      3    replaced       I
   0      10      4    bf       Lscala/collection/generic/BuilderFactory;


public scala.collection.generic.SequenceView reverse();
  Code:
   Stack=1, Locals=1, Args_size=1
   0:	aload_0
   1:	invokestatic	#1054; //Method scala/collection/generic/SequenceViewTemplate$class.reverse:(Lscala/collection/generic/SequenceViewTemplate;)Lscala/collection/generic/SequenceView;
   4:	areturn
  LineNumberTable: 
   line 39: 0


public scala.collection.generic.VectorViewTemplate$Transformed newZipped(scala.collection.Sequence);
  Code:
   Stack=2, Locals=2, Args_size=2
   0:	aload_0
   1:	aload_1
   2:	invokestatic	#1057; //Method scala/collection/generic/VectorViewTemplate$class.newZipped:(Lscala/collection/generic/VectorViewTemplate;Lscala/collection/Sequence;)Lscala/collection/generic/VectorViewTemplate$Transformed;
   5:	areturn
  LineNumberTable: 
   line 39: 0

  LocalVariableTable: 
   Start  Length  Slot  Name   Signature
   0      6      0    this       Lscala/GenericRange;
   0      6      1    that       Lscala/collection/Sequence;


public scala.collection.generic.VectorViewTemplate$Transformed newPatched(int, scala.collection.Sequence, int);
  Code:
   Stack=4, Locals=4, Args_size=4
   0:	aload_0
   1:	iload_1
   2:	aload_2
   3:	iload_3
   4:	invokestatic	#1060; //Method scala/collection/generic/VectorViewTemplate$class.newPatched:(Lscala/collection/generic/VectorViewTemplate;ILscala/collection/Sequence;I)Lscala/collection/generic/VectorViewTemplate$Transformed;
   7:	areturn
  LineNumberTable: 
   line 39: 0

  LocalVariableTable: 
   Start  Length  Slot  Name   Signature
   0      8      0    this       Lscala/GenericRange;
   0      8      1    _from       I
   0      8      2    _patch       Lscala/collection/Sequence;
   0      8      3    _replaced       I


public scala.collection.generic.VectorViewTemplate$Transformed newReversed();
  Code:
   Stack=1, Locals=1, Args_size=1
   0:	aload_0
   1:	invokestatic	#1063; //Method scala/collection/generic/VectorViewTemplate$class.newReversed:(Lscala/collection/generic/VectorViewTemplate;)Lscala/collection/generic/VectorViewTemplate$Transformed;
   4:	areturn
  LineNumberTable: 
   line 39: 0


public scala.collection.generic.VectorViewTemplate$Transformed newTakenWhile(scala.Function1);
  Code:
   Stack=2, Locals=2, Args_size=2
   0:	aload_0
   1:	aload_1
   2:	invokestatic	#1066; //Method scala/collection/generic/VectorViewTemplate$class.newTakenWhile:(Lscala/collection/generic/VectorViewTemplate;Lscala/Function1;)Lscala/collection/generic/VectorViewTemplate$Transformed;
   5:	areturn
  LineNumberTable: 
   line 39: 0

  LocalVariableTable: 
   Start  Length  Slot  Name   Signature
   0      6      0    this       Lscala/GenericRange;
   0      6      1    p       Lscala/Function1;


public scala.collection.generic.VectorViewTemplate$Transformed newDroppedWhile(scala.Function1);
  Code:
   Stack=2, Locals=2, Args_size=2
   0:	aload_0
   1:	aload_1
   2:	invokestatic	#1068; //Method scala/collection/generic/VectorViewTemplate$class.newDroppedWhile:(Lscala/collection/generic/VectorViewTemplate;Lscala/Function1;)Lscala/collection/generic/VectorViewTemplate$Transformed;
   5:	areturn
  LineNumberTable: 
   line 39: 0

  LocalVariableTable: 
   Start  Length  Slot  Name   Signature
   0      6      0    this       Lscala/GenericRange;
   0      6      1    p       Lscala/Function1;


public scala.collection.generic.VectorViewTemplate$Transformed newSliced(int, int);
  Code:
   Stack=3, Locals=3, Args_size=3
   0:	aload_0
   1:	iload_1
   2:	iload_2
   3:	invokestatic	#1071; //Method scala/collection/generic/VectorViewTemplate$class.newSliced:(Lscala/collection/generic/VectorViewTemplate;II)Lscala/collection/generic/VectorViewTemplate$Transformed;
   6:	areturn
  LineNumberTable: 
   line 39: 0

  LocalVariableTable: 
   Start  Length  Slot  Name   Signature
   0      7      0    this       Lscala/GenericRange;
   0      7      1    _from       I
   0      7      2    _until       I


public scala.collection.generic.VectorViewTemplate$Transformed newFiltered(scala.Function1);
  Code:
   Stack=2, Locals=2, Args_size=2
   0:	aload_0
   1:	aload_1
   2:	invokestatic	#1073; //Method scala/collection/generic/VectorViewTemplate$class.newFiltered:(Lscala/collection/generic/VectorViewTemplate;Lscala/Function1;)Lscala/collection/generic/VectorViewTemplate$Transformed;
   5:	areturn
  LineNumberTable: 
   line 39: 0

  LocalVariableTable: 
   Start  Length  Slot  Name   Signature
   0      6      0    this       Lscala/GenericRange;
   0      6      1    p       Lscala/Function1;


public scala.collection.generic.VectorViewTemplate$Transformed newFlatMapped(scala.Function1);
  Code:
   Stack=2, Locals=2, Args_size=2
   0:	aload_0
   1:	aload_1
   2:	invokestatic	#1075; //Method scala/collection/generic/VectorViewTemplate$class.newFlatMapped:(Lscala/collection/generic/VectorViewTemplate;Lscala/Function1;)Lscala/collection/generic/VectorViewTemplate$Transformed;
   5:	areturn
  LineNumberTable: 
   line 39: 0

  LocalVariableTable: 
   Start  Length  Slot  Name   Signature
   0      6      0    this       Lscala/GenericRange;
   0      6      1    f       Lscala/Function1;


public scala.collection.generic.VectorViewTemplate$Transformed newMapped(scala.Function1);
  Code:
   Stack=2, Locals=2, Args_size=2
   0:	aload_0
   1:	aload_1
   2:	invokestatic	#1077; //Method scala/collection/generic/VectorViewTemplate$class.newMapped:(Lscala/collection/generic/VectorViewTemplate;Lscala/Function1;)Lscala/collection/generic/VectorViewTemplate$Transformed;
   5:	areturn
  LineNumberTable: 
   line 39: 0

  LocalVariableTable: 
   Start  Length  Slot  Name   Signature
   0      6      0    this       Lscala/GenericRange;
   0      6      1    f       Lscala/Function1;


public scala.collection.generic.VectorViewTemplate$Transformed newAppended(scala.collection.Traversable);
  Code:
   Stack=2, Locals=2, Args_size=2
   0:	aload_0
   1:	aload_1
   2:	invokestatic	#1080; //Method scala/collection/generic/VectorViewTemplate$class.newAppended:(Lscala/collection/generic/VectorViewTemplate;Lscala/collection/Traversable;)Lscala/collection/generic/VectorViewTemplate$Transformed;
   5:	areturn
  LineNumberTable: 
   line 39: 0

  LocalVariableTable: 
   Start  Length  Slot  Name   Signature
   0      6      0    this       Lscala/GenericRange;
   0      6      1    that       Lscala/collection/Traversable;


public java.lang.String toString();
  Code:
   Stack=1, Locals=1, Args_size=1
   0:	aload_0
   1:	invokestatic	#1083; //Method scala/RangeToString$class.toString:(Lscala/RangeToString;)Ljava/lang/String;
   4:	areturn
  LineNumberTable: 
   line 39: 0


public boolean equalHashValues(java.lang.Object);
  Code:
   Stack=2, Locals=2, Args_size=2
   0:	aload_0
   1:	aload_1
   2:	invokestatic	#1086; //Method scala/util/Hashable$class.equalHashValues:(Lscala/util/Hashable;Ljava/lang/Object;)Z
   5:	ireturn
  LineNumberTable: 
   line 39: 0

  LocalVariableTable: 
   Start  Length  Slot  Name   Signature
   0      6      0    this       Lscala/GenericRange;
   0      6      1    other       Ljava/lang/Object;


public int hashCode();
  Code:
   Stack=1, Locals=1, Args_size=1
   0:	aload_0
   1:	invokestatic	#1090; //Method scala/util/Hashable$class.hashCode:(Lscala/util/Hashable;)I
   4:	ireturn
  LineNumberTable: 
   line 39: 0


public int hashSeed();
  Code:
   Stack=1, Locals=1, Args_size=1
   0:	aload_0
   1:	invokestatic	#1093; //Method scala/util/Hashable$class.hashSeed:(Lscala/util/Hashable;)I
   4:	ireturn
  LineNumberTable: 
   line 39: 0


}

