Compiled from "Range.scala"
public final class scala.GenericRange$ extends java.lang.Object implements scala.ScalaObject
  SourceFile: "Range.scala"
  Scala: length = 0x
   
  InnerClass: 
   public #48= #42 of #47; //Exclusive=class scala/GenericRange$Exclusive of class scala/GenericRange
   public #49= #25 of #47; //Inclusive=class scala/GenericRange$Inclusive of class scala/GenericRange
   public final #52= #51 of #47; //$anonfun$1=class scala/GenericRange$$anonfun$1 of class scala/GenericRange
   public final #55= #54 of #47; //$anonfun$contains$1=class scala/GenericRange$$anonfun$contains$1 of class scala/GenericRange
   public final #58= #57 of #47; //$anonfun$contains$2=class scala/GenericRange$$anonfun$contains$2 of class scala/GenericRange
  minor version: 0
  major version: 49
  Constant pool:
const #1 = Asciz	SourceFile;
const #2 = Asciz	Range.scala;
const #3 = Asciz	Scala;
const #4 = Asciz	MODULE$;
const #5 = Asciz	Lscala/GenericRange$;;
const #6 = Asciz	<clinit>;
const #7 = Asciz	()V;
const #8 = Asciz	Code;
const #9 = Asciz	scala/GenericRange$;
const #10 = class	#9;	//  scala/GenericRange$
const #11 = Asciz	<init>;
const #12 = NameAndType	#11:#7;//  "<init>":()V
const #13 = Method	#10.#12;	//  scala/GenericRange$."<init>":()V
const #14 = Asciz	LineNumberTable;
const #15 = Asciz	java/lang/Object;
const #16 = class	#15;	//  java/lang/Object
const #17 = Method	#16.#12;	//  java/lang/Object."<init>":()V
const #18 = NameAndType	#4:#5;//  MODULE$:Lscala/GenericRange$;
const #19 = Field	#10.#18;	//  scala/GenericRange$.MODULE$:Lscala/GenericRange$;
const #20 = Asciz	init$default$4;
const #21 = Asciz	()Z;
const #22 = Asciz	inclusive;
const #23 = Asciz	(Ljava/lang/Object;Ljava/lang/Object;Ljava/lang/Object;Lscala/Integral;)Lscala/GenericRange$Inclusive;;
const #24 = Asciz	scala/GenericRange$Inclusive;
const #25 = class	#24;	//  scala/GenericRange$Inclusive
const #26 = Asciz	(Ljava/lang/Object;Ljava/lang/Object;Ljava/lang/Object;Lscala/Integral;)V;
const #27 = NameAndType	#11:#26;//  "<init>":(Ljava/lang/Object;Ljava/lang/Object;Ljava/lang/Object;Lscala/Integral;)V
const #28 = Method	#25.#27;	//  scala/GenericRange$Inclusive."<init>":(Ljava/lang/Object;Ljava/lang/Object;Ljava/lang/Object;Lscala/Integral;)V
const #29 = Asciz	this;
const #30 = Asciz	start;
const #31 = Asciz	Ljava/lang/Object;;
const #32 = Asciz	end;
const #33 = Asciz	step;
const #34 = Asciz	num;
const #35 = Asciz	Lscala/Integral;;
const #36 = Asciz	LocalVariableTable;
const #37 = Asciz	<T:Ljava/lang/Object;>(TT;TT;TT;Lscala/Integral<TT;>;)Lscala/GenericRange$Inclusive<TT;>;;
const #38 = Asciz	Signature;
const #39 = Asciz	apply;
const #40 = Asciz	(Ljava/lang/Object;Ljava/lang/Object;Ljava/lang/Object;Lscala/Integral;)Lscala/GenericRange$Exclusive;;
const #41 = Asciz	scala/GenericRange$Exclusive;
const #42 = class	#41;	//  scala/GenericRange$Exclusive
const #43 = Method	#42.#27;	//  scala/GenericRange$Exclusive."<init>":(Ljava/lang/Object;Ljava/lang/Object;Ljava/lang/Object;Lscala/Integral;)V
const #44 = Asciz	<T:Ljava/lang/Object;>(TT;TT;TT;Lscala/Integral<TT;>;)Lscala/GenericRange$Exclusive<TT;>;;
const #45 = Asciz	InnerClasses;
const #46 = Asciz	scala/GenericRange;
const #47 = class	#46;	//  scala/GenericRange
const #48 = Asciz	Exclusive;
const #49 = Asciz	Inclusive;
const #50 = Asciz	scala/GenericRange$$anonfun$1;
const #51 = class	#50;	//  scala/GenericRange$$anonfun$1
const #52 = Asciz	$anonfun$1;
const #53 = Asciz	scala/GenericRange$$anonfun$contains$1;
const #54 = class	#53;	//  scala/GenericRange$$anonfun$contains$1
const #55 = Asciz	$anonfun$contains$1;
const #56 = Asciz	scala/GenericRange$$anonfun$contains$2;
const #57 = class	#56;	//  scala/GenericRange$$anonfun$contains$2
const #58 = Asciz	$anonfun$contains$2;
const #59 = Asciz	scala/ScalaObject;
const #60 = class	#59;	//  scala/ScalaObject

{
public static final scala.GenericRange$ MODULE$;

public static {};
  Code:
   Stack=1, Locals=0, Args_size=0
   0:	new	#10; //class scala/GenericRange$
   3:	invokespecial	#13; //Method "<init>":()V
   6:	return

public boolean init$default$4();
  Code:
   Stack=1, Locals=1, Args_size=1
   0:	iconst_0
   1:	ireturn
  LineNumberTable: 
   line 40: 0


public scala.GenericRange$Inclusive inclusive(java.lang.Object, java.lang.Object, java.lang.Object, scala.Integral);
  Code:
   Stack=6, Locals=5, Args_size=5
   0:	new	#25; //class scala/GenericRange$Inclusive
   3:	dup
   4:	aload_1
   5:	aload_2
   6:	aload_3
   7:	aload	4
   9:	invokespecial	#28; //Method scala/GenericRange$Inclusive."<init>":(Ljava/lang/Object;Ljava/lang/Object;Ljava/lang/Object;Lscala/Integral;)V
   12:	areturn
  LineNumberTable: 
   line 162: 0

  LocalVariableTable: 
   Start  Length  Slot  Name   Signature
   0      13      0    this       Lscala/GenericRange$;
   0      13      1    start       Ljava/lang/Object;
   0      13      2    end       Ljava/lang/Object;
   0      13      3    step       Ljava/lang/Object;
   0      13      4    num       Lscala/Integral;

  Signature: length = 0x2
   00 25 

public scala.GenericRange$Exclusive apply(java.lang.Object, java.lang.Object, java.lang.Object, scala.Integral);
  Code:
   Stack=6, Locals=5, Args_size=5
   0:	new	#42; //class scala/GenericRange$Exclusive
   3:	dup
   4:	aload_1
   5:	aload_2
   6:	aload_3
   7:	aload	4
   9:	invokespecial	#43; //Method scala/GenericRange$Exclusive."<init>":(Ljava/lang/Object;Ljava/lang/Object;Ljava/lang/Object;Lscala/Integral;)V
   12:	areturn
  LineNumberTable: 
   line 160: 0

  LocalVariableTable: 
   Start  Length  Slot  Name   Signature
   0      13      0    this       Lscala/GenericRange$;
   0      13      1    start       Ljava/lang/Object;
   0      13      2    end       Ljava/lang/Object;
   0      13      3    step       Ljava/lang/Object;
   0      13      4    num       Lscala/Integral;

  Signature: length = 0x2
   00 2C 

}

