Compiled from "Range.scala"
public class scala.GenericRange$Inclusive extends scala.GenericRange implements scala.ScalaObject
  SourceFile: "Range.scala"
  Signature: length = 0x2
   00 3A 
  Scala: length = 0x
   
  InnerClass: 
   public #61= #12 of #16; //Inclusive=class scala/GenericRange$Inclusive of class scala/GenericRange
   public #64= #63 of #16; //Exclusive=class scala/GenericRange$Exclusive of class scala/GenericRange
  minor version: 0
  major version: 49
  Constant pool:
const #1 = Asciz	SourceFile;
const #2 = Asciz	Range.scala;
const #3 = Asciz	num;
const #4 = Asciz	Lscala/Integral;;
const #5 = Asciz	Lscala/Integral<TT;>;;
const #6 = Asciz	Signature;
const #7 = Asciz	<init>;
const #8 = Asciz	(Ljava/lang/Object;Ljava/lang/Object;Ljava/lang/Object;Lscala/Integral;)V;
const #9 = Asciz	Code;
const #10 = Asciz	LineNumberTable;
const #11 = Asciz	scala/GenericRange$Inclusive;
const #12 = class	#11;	//  scala/GenericRange$Inclusive
const #13 = NameAndType	#3:#4;//  num:Lscala/Integral;
const #14 = Field	#12.#13;	//  scala/GenericRange$Inclusive.num:Lscala/Integral;
const #15 = Asciz	scala/GenericRange;
const #16 = class	#15;	//  scala/GenericRange
const #17 = Asciz	(Ljava/lang/Object;Ljava/lang/Object;Ljava/lang/Object;ZLscala/Integral;)V;
const #18 = NameAndType	#7:#17;//  "<init>":(Ljava/lang/Object;Ljava/lang/Object;Ljava/lang/Object;ZLscala/Integral;)V
const #19 = Method	#16.#18;	//  scala/GenericRange."<init>":(Ljava/lang/Object;Ljava/lang/Object;Ljava/lang/Object;ZLscala/Integral;)V
const #20 = Asciz	this;
const #21 = Asciz	Lscala/GenericRange$Inclusive;;
const #22 = Asciz	start;
const #23 = Asciz	Ljava/lang/Object;;
const #24 = Asciz	end;
const #25 = Asciz	step;
const #26 = Asciz	LocalVariableTable;
const #27 = Asciz	(TT;TT;TT;Lscala/Integral<TT;>;)V;
const #28 = Asciz	copy;
const #29 = Asciz	(Ljava/lang/Object;Ljava/lang/Object;Ljava/lang/Object;)Lscala/GenericRange;;
const #30 = Asciz	(Ljava/lang/Object;Ljava/lang/Object;Ljava/lang/Object;)Lscala/GenericRange$Inclusive;;
const #31 = NameAndType	#28:#30;//  copy:(Ljava/lang/Object;Ljava/lang/Object;Ljava/lang/Object;)Lscala/GenericRange$Inclusive;
const #32 = Method	#12.#31;	//  scala/GenericRange$Inclusive.copy:(Ljava/lang/Object;Ljava/lang/Object;Ljava/lang/Object;)Lscala/GenericRange$Inclusive;
const #33 = Asciz	scala/GenericRange$;
const #34 = class	#33;	//  scala/GenericRange$
const #35 = Asciz	MODULE$;
const #36 = Asciz	Lscala/GenericRange$;;
const #37 = NameAndType	#35:#36;//  MODULE$:Lscala/GenericRange$;
const #38 = Field	#34.#37;	//  scala/GenericRange$.MODULE$:Lscala/GenericRange$;
const #39 = Asciz	inclusive;
const #40 = Asciz	(Ljava/lang/Object;Ljava/lang/Object;Ljava/lang/Object;Lscala/Integral;)Lscala/GenericRange$Inclusive;;
const #41 = NameAndType	#39:#40;//  inclusive:(Ljava/lang/Object;Ljava/lang/Object;Ljava/lang/Object;Lscala/Integral;)Lscala/GenericRange$Inclusive;
const #42 = Method	#34.#41;	//  scala/GenericRange$.inclusive:(Ljava/lang/Object;Ljava/lang/Object;Ljava/lang/Object;Lscala/Integral;)Lscala/GenericRange$Inclusive;
const #43 = Asciz	(TT;TT;TT;)Lscala/GenericRange$Inclusive<TT;>;;
const #44 = Asciz	exclusive;
const #45 = Asciz	()Lscala/GenericRange$Exclusive;;
const #46 = Asciz	()Ljava/lang/Object;;
const #47 = NameAndType	#22:#46;//  start:()Ljava/lang/Object;
const #48 = Method	#16.#47;	//  scala/GenericRange.start:()Ljava/lang/Object;
const #49 = NameAndType	#24:#46;//  end:()Ljava/lang/Object;
const #50 = Method	#16.#49;	//  scala/GenericRange.end:()Ljava/lang/Object;
const #51 = NameAndType	#25:#46;//  step:()Ljava/lang/Object;
const #52 = Method	#16.#51;	//  scala/GenericRange.step:()Ljava/lang/Object;
const #53 = Asciz	apply;
const #54 = Asciz	(Ljava/lang/Object;Ljava/lang/Object;Ljava/lang/Object;Lscala/Integral;)Lscala/GenericRange$Exclusive;;
const #55 = NameAndType	#53:#54;//  apply:(Ljava/lang/Object;Ljava/lang/Object;Ljava/lang/Object;Lscala/Integral;)Lscala/GenericRange$Exclusive;
const #56 = Method	#34.#55;	//  scala/GenericRange$.apply:(Ljava/lang/Object;Ljava/lang/Object;Ljava/lang/Object;Lscala/Integral;)Lscala/GenericRange$Exclusive;
const #57 = Asciz	()Lscala/GenericRange$Exclusive<TT;>;;
const #58 = Asciz	<T:Ljava/lang/Object;>Lscala/GenericRange<TT;>;Lscala/ScalaObject;;
const #59 = Asciz	Scala;
const #60 = Asciz	InnerClasses;
const #61 = Asciz	Inclusive;
const #62 = Asciz	scala/GenericRange$Exclusive;
const #63 = class	#62;	//  scala/GenericRange$Exclusive
const #64 = Asciz	Exclusive;
const #65 = Asciz	scala/ScalaObject;
const #66 = class	#65;	//  scala/ScalaObject

{
public scala.GenericRange$Inclusive(java.lang.Object, java.lang.Object, java.lang.Object, scala.Integral);
  Code:
   Stack=6, Locals=5, Args_size=5
   0:	aload_0
   1:	aload	4
   3:	putfield	#14; //Field num:Lscala/Integral;
   6:	aload_0
   7:	aload_1
   8:	aload_2
   9:	aload_3
   10:	iconst_1
   11:	aload	4
   13:	invokespecial	#19; //Method scala/GenericRange."<init>":(Ljava/lang/Object;Ljava/lang/Object;Ljava/lang/Object;ZLscala/Integral;)V
   16:	return
  LineNumberTable: 
   line 147: 0
   line 148: 7
   line 147: 11

  LocalVariableTable: 
   Start  Length  Slot  Name   Signature
   0      17      0    this       Lscala/GenericRange$Inclusive;
   0      17      1    start       Ljava/lang/Object;
   0      17      2    end       Ljava/lang/Object;
   0      17      3    step       Ljava/lang/Object;
   0      17      4    num       Lscala/Integral;

  Signature: length = 0x2
   00 1B 

public scala.GenericRange copy(java.lang.Object, java.lang.Object, java.lang.Object);
  Code:
   Stack=4, Locals=4, Args_size=4
   0:	aload_0
   1:	aload_1
   2:	aload_2
   3:	aload_3
   4:	invokevirtual	#32; //Method copy:(Ljava/lang/Object;Ljava/lang/Object;Ljava/lang/Object;)Lscala/GenericRange$Inclusive;
   7:	areturn
  LineNumberTable: 
   line 147: 0

  LocalVariableTable: 
   Start  Length  Slot  Name   Signature
   0      8      0    this       Lscala/GenericRange$Inclusive;
   0      8      1    start       Ljava/lang/Object;
   0      8      2    end       Ljava/lang/Object;
   0      8      3    step       Ljava/lang/Object;


public scala.GenericRange$Inclusive copy(java.lang.Object, java.lang.Object, java.lang.Object);
  Code:
   Stack=5, Locals=4, Args_size=4
   0:	getstatic	#38; //Field scala/GenericRange$.MODULE$:Lscala/GenericRange$;
   3:	aload_1
   4:	aload_2
   5:	aload_3
   6:	aload_0
   7:	getfield	#14; //Field num:Lscala/Integral;
   10:	invokevirtual	#42; //Method scala/GenericRange$.inclusive:(Ljava/lang/Object;Ljava/lang/Object;Ljava/lang/Object;Lscala/Integral;)Lscala/GenericRange$Inclusive;
   13:	areturn
  LineNumberTable: 
   line 150: 0

  LocalVariableTable: 
   Start  Length  Slot  Name   Signature
   0      14      0    this       Lscala/GenericRange$Inclusive;
   0      14      1    start       Ljava/lang/Object;
   0      14      2    end       Ljava/lang/Object;
   0      14      3    step       Ljava/lang/Object;

  Signature: length = 0x2
   00 2B 

public scala.GenericRange$Exclusive exclusive();
  Code:
   Stack=5, Locals=1, Args_size=1
   0:	getstatic	#38; //Field scala/GenericRange$.MODULE$:Lscala/GenericRange$;
   3:	aload_0
   4:	invokespecial	#48; //Method scala/GenericRange.start:()Ljava/lang/Object;
   7:	aload_0
   8:	invokespecial	#50; //Method scala/GenericRange.end:()Ljava/lang/Object;
   11:	aload_0
   12:	invokespecial	#52; //Method scala/GenericRange.step:()Ljava/lang/Object;
   15:	aload_0
   16:	getfield	#14; //Field num:Lscala/Integral;
   19:	invokevirtual	#56; //Method scala/GenericRange$.apply:(Ljava/lang/Object;Ljava/lang/Object;Ljava/lang/Object;Lscala/Integral;)Lscala/GenericRange$Exclusive;
   22:	areturn
  LineNumberTable: 
   line 149: 0

  Signature: length = 0x2
   00 39 

}

