Compiled from "Integral.scala"
public class scala.Integral$IntegralOps extends scala.Numeric$Ops implements scala.ScalaObject
  SourceFile: "Integral.scala"
  Signature: length = 0x2
   00 33 
  Scala: length = 0x
   
  InnerClass: 
   public #56= #25 of #55; //Ops=class scala/Numeric$Ops of class scala/Numeric
   public #57= #14 of #40; //IntegralOps=class scala/Integral$IntegralOps of class scala/Integral
  minor version: 0
  major version: 49
  Constant pool:
const #1 = Asciz	SourceFile;
const #2 = Asciz	Integral.scala;
const #3 = Asciz	$outer;
const #4 = Asciz	Lscala/Integral;;
const #5 = Asciz	lhs;
const #6 = Asciz	Ljava/lang/Object;;
const #7 = Asciz	TT;;
const #8 = Asciz	Signature;
const #9 = Asciz	<init>;
const #10 = Asciz	(Lscala/Integral;Ljava/lang/Object;)V;
const #11 = Asciz	Code;
const #12 = Asciz	LineNumberTable;
const #13 = Asciz	scala/Integral$IntegralOps;
const #14 = class	#13;	//  scala/Integral$IntegralOps
const #15 = NameAndType	#5:#6;//  lhs:Ljava/lang/Object;
const #16 = Field	#14.#15;	//  scala/Integral$IntegralOps.lhs:Ljava/lang/Object;
const #17 = Asciz	java/lang/NullPointerException;
const #18 = class	#17;	//  java/lang/NullPointerException
const #19 = Asciz	()V;
const #20 = NameAndType	#9:#19;//  "<init>":()V
const #21 = Method	#18.#20;	//  java/lang/NullPointerException."<init>":()V
const #22 = NameAndType	#3:#4;//  $outer:Lscala/Integral;
const #23 = Field	#14.#22;	//  scala/Integral$IntegralOps.$outer:Lscala/Integral;
const #24 = Asciz	scala/Numeric$Ops;
const #25 = class	#24;	//  scala/Numeric$Ops
const #26 = Asciz	(Lscala/Numeric;Ljava/lang/Object;)V;
const #27 = NameAndType	#9:#26;//  "<init>":(Lscala/Numeric;Ljava/lang/Object;)V
const #28 = Method	#25.#27;	//  scala/Numeric$Ops."<init>":(Lscala/Numeric;Ljava/lang/Object;)V
const #29 = Asciz	this;
const #30 = Asciz	Lscala/Integral$IntegralOps;;
const #31 = Asciz	LocalVariableTable;
const #32 = Asciz	(Lscala/Integral<TT;>;TT;)V;
const #33 = Asciz	scala$Integral$IntegralOps$$$outer;
const #34 = Asciz	()Lscala/Integral;;
const #35 = Asciz	$percent;
const #36 = Asciz	(Ljava/lang/Object;)Ljava/lang/Object;;
const #37 = NameAndType	#33:#34;//  scala$Integral$IntegralOps$$$outer:()Lscala/Integral;
const #38 = Method	#14.#37;	//  scala/Integral$IntegralOps.scala$Integral$IntegralOps$$$outer:()Lscala/Integral;
const #39 = Asciz	scala/Integral;
const #40 = class	#39;	//  scala/Integral
const #41 = Asciz	rem;
const #42 = Asciz	(Ljava/lang/Object;Ljava/lang/Object;)Ljava/lang/Object;;
const #43 = NameAndType	#41:#42;//  rem:(Ljava/lang/Object;Ljava/lang/Object;)Ljava/lang/Object;
const #44 = InterfaceMethod	#40.#43;	//  scala/Integral.rem:(Ljava/lang/Object;Ljava/lang/Object;)Ljava/lang/Object;
const #45 = Asciz	rhs;
const #46 = Asciz	(TT;)TT;;
const #47 = Asciz	$div;
const #48 = Asciz	quot;
const #49 = NameAndType	#48:#42;//  quot:(Ljava/lang/Object;Ljava/lang/Object;)Ljava/lang/Object;
const #50 = InterfaceMethod	#40.#49;	//  scala/Integral.quot:(Ljava/lang/Object;Ljava/lang/Object;)Ljava/lang/Object;
const #51 = Asciz	Lscala/Integral<TT;>.Ops;Lscala/ScalaObject;;
const #52 = Asciz	Scala;
const #53 = Asciz	InnerClasses;
const #54 = Asciz	scala/Numeric;
const #55 = class	#54;	//  scala/Numeric
const #56 = Asciz	Ops;
const #57 = Asciz	IntegralOps;
const #58 = Asciz	scala/ScalaObject;
const #59 = class	#58;	//  scala/ScalaObject

{
public final scala.Integral $outer;

public scala.Integral$IntegralOps(scala.Integral, java.lang.Object);
  Code:
   Stack=3, Locals=3, Args_size=3
   0:	aload_0
   1:	aload_2
   2:	putfield	#16; //Field lhs:Ljava/lang/Object;
   5:	aload_1
   6:	ifnonnull	17
   9:	new	#18; //class java/lang/NullPointerException
   12:	dup
   13:	invokespecial	#21; //Method java/lang/NullPointerException."<init>":()V
   16:	athrow
   17:	aload_0
   18:	aload_1
   19:	putfield	#23; //Field $outer:Lscala/Integral;
   22:	aload_0
   23:	aload_1
   24:	aload_2
   25:	invokespecial	#28; //Method scala/Numeric$Ops."<init>":(Lscala/Numeric;Ljava/lang/Object;)V
   28:	return
  LineNumberTable: 
   line 7: 0

  LocalVariableTable: 
   Start  Length  Slot  Name   Signature
   0      29      0    this       Lscala/Integral$IntegralOps;
   0      29      1    $outer       Lscala/Integral;
   0      29      2    lhs       Ljava/lang/Object;

  Signature: length = 0x2
   00 20 

public scala.Integral scala$Integral$IntegralOps$$$outer();
  Code:
   Stack=1, Locals=1, Args_size=1
   0:	aload_0
   1:	getfield	#23; //Field $outer:Lscala/Integral;
   4:	areturn
  LineNumberTable: 
   line 7: 0


public java.lang.Object $percent(java.lang.Object);
  Code:
   Stack=3, Locals=2, Args_size=2
   0:	aload_0
   1:	invokevirtual	#38; //Method scala$Integral$IntegralOps$$$outer:()Lscala/Integral;
   4:	aload_0
   5:	getfield	#16; //Field lhs:Ljava/lang/Object;
   8:	aload_1
   9:	invokeinterface	#44,  3; //InterfaceMethod scala/Integral.rem:(Ljava/lang/Object;Ljava/lang/Object;)Ljava/lang/Object;
   14:	areturn
  LineNumberTable: 
   line 9: 0

  LocalVariableTable: 
   Start  Length  Slot  Name   Signature
   0      15      0    this       Lscala/Integral$IntegralOps;
   0      15      1    rhs       Ljava/lang/Object;

  Signature: length = 0x2
   00 2E 

public java.lang.Object $div(java.lang.Object);
  Code:
   Stack=3, Locals=2, Args_size=2
   0:	aload_0
   1:	invokevirtual	#38; //Method scala$Integral$IntegralOps$$$outer:()Lscala/Integral;
   4:	aload_0
   5:	getfield	#16; //Field lhs:Ljava/lang/Object;
   8:	aload_1
   9:	invokeinterface	#50,  3; //InterfaceMethod scala/Integral.quot:(Ljava/lang/Object;Ljava/lang/Object;)Ljava/lang/Object;
   14:	areturn
  LineNumberTable: 
   line 8: 0

  LocalVariableTable: 
   Start  Length  Slot  Name   Signature
   0      15      0    this       Lscala/Integral$IntegralOps;
   0      15      1    rhs       Ljava/lang/Object;

  Signature: length = 0x2
   00 2E 

}

