Compiled from "Iterator.scala"
public abstract class scala.Iterator$class extends java.lang.Object
  InnerClass: 
   public final $anon$17=class scala/Iterator$$anon$17 of class scala/Iterator
   public abstract Mutable=class scala/RandomAccessSeq$Mutable of class scala/RandomAccessSeq
  Scala: length = 0x
   
  SourceFile: "Iterator.scala"
  minor version: 0
  major version: 49
  Constant pool:
String	 iterator
String	empty
String	non-empty
class	java/lang/Object
class	scala/Function1
class	scala/Iterator
class	scala/Iterator$$anon$17
class	scala/Iterator$class
class	scala/RandomAccessSeq
class	scala/RandomAccessSeq$Mutable
class	scala/StringBuilder
class	scala/runtime/BoxesRunTime
Method	scala/Iterator$$anon$17."<init>":(Lscala/Iterator;Lscala/Iterator;)V
Method	scala/StringBuilder."<init>":()V
Method	scala/StringBuilder.append:(Ljava/lang/Object;)Lscala/StringBuilder;
Method	scala/StringBuilder.toString:()Ljava/lang/String;
Method	scala/runtime/BoxesRunTime.unboxToBoolean:(Ljava/lang/Object;)Z
InterfaceMethod	scala/Function1.apply:(Ljava/lang/Object;)Ljava/lang/Object;
InterfaceMethod	scala/Iterator.hasNext:()Z
InterfaceMethod	scala/Iterator.next:()Ljava/lang/Object;
NameAndType	"<init>":()V
NameAndType	"<init>":(Lscala/Iterator;Lscala/Iterator;)V
NameAndType	append:(Ljava/lang/Object;)Lscala/StringBuilder;
NameAndType	apply:(Ljava/lang/Object;)Ljava/lang/Object;
NameAndType	hasNext:()Z
NameAndType	next:()Ljava/lang/Object;
NameAndType	toString:()Ljava/lang/String;
NameAndType	unboxToBoolean:(Ljava/lang/Object;)Z
Asciz	 iterator;
Asciz	$anon$17;
Asciz	$init$;
Asciz	$this;
Asciz	()Ljava/lang/Object;;
Asciz	()Ljava/lang/String;;
Asciz	()V;
Asciz	()Z;
Asciz	(Ljava/lang/Object;)Ljava/lang/Object;;
Asciz	(Ljava/lang/Object;)Lscala/StringBuilder;;
Asciz	(Ljava/lang/Object;)Z;
Asciz	(Lscala/Iterator;)Ljava/lang/String;;
Asciz	(Lscala/Iterator;)V;
Asciz	(Lscala/Iterator;Lscala/Function1;)V;
Asciz	(Lscala/Iterator;Lscala/Function1;)Z;
Asciz	(Lscala/Iterator;Lscala/Iterator;)Ljava/lang/Object;;
Asciz	(Lscala/Iterator;Lscala/Iterator;)V;
Asciz	<init>;
Asciz	Code;
Asciz	InnerClasses;
Asciz	Iterator.scala;
Asciz	LineNumberTable;
Asciz	LocalVariableTable;
Asciz	Lscala/Function1;;
Asciz	Lscala/Iterator;;
Asciz	Mutable;
Asciz	Scala;
Asciz	SourceFile;
Asciz	Z;
Asciz	append;
Asciz	apply;
Asciz	empty;
Asciz	f;
Asciz	forall;
Asciz	foreach;
Asciz	hasNext;
Asciz	java/lang/Object;
Asciz	next;
Asciz	non-empty;
Asciz	p;
Asciz	res;
Asciz	scala/Function1;
Asciz	scala/Iterator;
Asciz	scala/Iterator$$anon$17;
Asciz	scala/Iterator$class;
Asciz	scala/RandomAccessSeq;
Asciz	scala/RandomAccessSeq$Mutable;
Asciz	scala/StringBuilder;
Asciz	scala/runtime/BoxesRunTime;
Asciz	that$3;
Asciz	toString;
Asciz	unboxToBoolean;
Asciz	zip;

{
public static void $init$(scala.Iterator);
  Signature: (Lscala/Iterator;)V
  Code:
   Stack=0, Locals=1, Args_size=1
	return
  Labels:
  LocalVariableTable: 
   Start  Length  Slot  Name   Signature
   0      1      0    $this       Lscala/Iterator;


public static java.lang.String toString(scala.Iterator);
  Signature: (Lscala/Iterator;)Ljava/lang/String;
  Code:
   Stack=2, Locals=1, Args_size=1
	new	class scala/StringBuilder
	dup
	invokespecial	Method scala/StringBuilder."<init>":()V
	aload_0
	invokeinterface	InterfaceMethod scala/Iterator.hasNext:()Z
	ifeq	l1 // ldc
	ldc	String non-empty
	goto	l2 // invokevirtual
l1	ldc	String empty
l2	invokevirtual	Method scala/StringBuilder.append:(Ljava/lang/Object;)Lscala/StringBuilder;
	ldc	String  iterator
	invokevirtual	Method scala/StringBuilder.append:(Ljava/lang/Object;)Lscala/StringBuilder;
	invokevirtual	Method scala/StringBuilder.toString:()Ljava/lang/String;
	areturn
  Labels:
   	l1 = 21 // ldc
   	l2 = 23 // invokevirtual
  LocalVariableTable: 
   Start  Length  Slot  Name   Signature
   0      35      0    $this       Lscala/Iterator;


public static boolean forall(scala.Iterator, scala.Function1);
  Signature: (Lscala/Iterator;Lscala/Function1;)Z
  Code:
   Stack=2, Locals=3, Args_size=2
	iconst_1
	istore_2
l2	iload_2
	ifeq	l1 // iload_2
	aload_0
	invokeinterface	InterfaceMethod scala/Iterator.hasNext:()Z
	ifeq	l1 // iload_2
	aload_1
	aload_0
	invokeinterface	InterfaceMethod scala/Iterator.next:()Ljava/lang/Object;
	invokeinterface	InterfaceMethod scala/Function1.apply:(Ljava/lang/Object;)Ljava/lang/Object;
	invokestatic	Method scala/runtime/BoxesRunTime.unboxToBoolean:(Ljava/lang/Object;)Z
	istore_2
	goto	l2 // iload_2
l1	iload_2
	ireturn
  Labels:
   	l2 = 2 // iload_2
   	l1 = 34 // iload_2
  LocalVariableTable: 
   Start  Length  Slot  Name   Signature
   0      36      0    $this       Lscala/Iterator;
   0      36      1    p       Lscala/Function1;
   0      35      2    res       Z


public static void foreach(scala.Iterator, scala.Function1);
  Signature: (Lscala/Iterator;Lscala/Function1;)V
  Code:
   Stack=2, Locals=2, Args_size=2
l2	aload_0
	invokeinterface	InterfaceMethod scala/Iterator.hasNext:()Z
	ifeq	l1 // return
	aload_1
	aload_0
	invokeinterface	InterfaceMethod scala/Iterator.next:()Ljava/lang/Object;
	invokeinterface	InterfaceMethod scala/Function1.apply:(Ljava/lang/Object;)Ljava/lang/Object;
	pop
	goto	l2 // aload_0
l1	return
  Labels:
   	l2 = 0 // aload_0
   	l1 = 25 // return
  LocalVariableTable: 
   Start  Length  Slot  Name   Signature
   0      26      0    $this       Lscala/Iterator;
   0      26      1    f       Lscala/Function1;


public static java.lang.Object zip(scala.Iterator, scala.Iterator);
  Signature: (Lscala/Iterator;Lscala/Iterator;)Ljava/lang/Object;
  Code:
   Stack=4, Locals=2, Args_size=2
	new	class scala/Iterator$$anon$17
	dup
	aload_0
	aload_1
	invokespecial	Method scala/Iterator$$anon$17."<init>":(Lscala/Iterator;Lscala/Iterator;)V
	areturn
  Labels:
  LocalVariableTable: 
   Start  Length  Slot  Name   Signature
   0      10      0    $this       Lscala/Iterator;
   0      10      1    that$3       Lscala/Iterator;


}

