Compiled from "Iterator.scala"
public final class scala.Iterator$$anon$17 extends java.lang.Object implements scala.Iterator
  InnerClass: 
   public final $anon$17=class scala/Iterator$$anon$17 of class scala/Iterator
  Scala: length = 0x
   
  Signature: length = 0x2
   00 39 
  SourceFile: "Iterator.scala"
  minor version: 0
  major version: 49
  Constant pool:
class	java/lang/NullPointerException
class	java/lang/Object
class	scala/Iterator
class	scala/Iterator$$anon$17
class	scala/Iterator$class
class	scala/Tuple2
Field	scala/Iterator$$anon$17.$outer:Lscala/Iterator;
Field	scala/Iterator$$anon$17.that$3:Lscala/Iterator;
Method	java/lang/NullPointerException."<init>":()V
Method	java/lang/Object."<init>":()V
Method	scala/Iterator$$anon$17.next:()Lscala/Tuple2;
Method	scala/Iterator$class.$init$:(Lscala/Iterator;)V
Method	scala/Iterator$class.forall:(Lscala/Iterator;Lscala/Function1;)Z
Method	scala/Iterator$class.foreach:(Lscala/Iterator;Lscala/Function1;)V
Method	scala/Iterator$class.toString:(Lscala/Iterator;)Ljava/lang/String;
Method	scala/Iterator$class.zip:(Lscala/Iterator;Lscala/Iterator;)Ljava/lang/Object;
Method	scala/Tuple2."<init>":(Ljava/lang/Object;Ljava/lang/Object;)V
InterfaceMethod	scala/Iterator.hasNext:()Z
InterfaceMethod	scala/Iterator.next:()Ljava/lang/Object;
NameAndType	$init$:(Lscala/Iterator;)V
NameAndType	$outer:Lscala/Iterator;
NameAndType	"<init>":()V
NameAndType	"<init>":(Ljava/lang/Object;Ljava/lang/Object;)V
NameAndType	forall:(Lscala/Iterator;Lscala/Function1;)Z
NameAndType	foreach:(Lscala/Iterator;Lscala/Function1;)V
NameAndType	hasNext:()Z
NameAndType	next:()Ljava/lang/Object;
NameAndType	next:()Lscala/Tuple2;
NameAndType	that$3:Lscala/Iterator;
NameAndType	toString:(Lscala/Iterator;)Ljava/lang/String;
NameAndType	zip:(Lscala/Iterator;Lscala/Iterator;)Ljava/lang/Object;
Asciz	$anon$17;
Asciz	$init$;
Asciz	$outer;
Asciz	()Ljava/lang/Object;;
Asciz	()Ljava/lang/String;;
Asciz	()Lscala/Tuple2;;
Asciz	()Lscala/Tuple2<TA;TB;>;;
Asciz	()V;
Asciz	()Z;
Asciz	(Ljava/lang/Object;Ljava/lang/Object;)V;
Asciz	(Lscala/Function1;)V;
Asciz	(Lscala/Function1;)Z;
Asciz	(Lscala/Iterator;)Ljava/lang/Object;;
Asciz	(Lscala/Iterator;)Ljava/lang/String;;
Asciz	(Lscala/Iterator;)V;
Asciz	(Lscala/Iterator;Lscala/Function1;)V;
Asciz	(Lscala/Iterator;Lscala/Function1;)Z;
Asciz	(Lscala/Iterator;Lscala/Iterator;)Ljava/lang/Object;;
Asciz	(Lscala/Iterator;Lscala/Iterator;)V;
Asciz	(Lscala/Iterator<TA;>;)V;
Asciz	<init>;
Asciz	Code;
Asciz	InnerClasses;
Asciz	Iterator.scala;
Asciz	LineNumberTable;
Asciz	Ljava/lang/Object;Lscala/Iterator<Lscala/Tuple2<TA;TB;>;>;;
Asciz	LocalVariableTable;
Asciz	Lscala/Function1;;
Asciz	Lscala/Iterator$$anon$17;;
Asciz	Lscala/Iterator;;
Asciz	Scala;
Asciz	Signature;
Asciz	SourceFile;
Asciz	forall;
Asciz	foreach;
Asciz	hasNext;
Asciz	java/lang/NullPointerException;
Asciz	java/lang/Object;
Asciz	next;
Asciz	scala/Iterator;
Asciz	scala/Iterator$$anon$17;
Asciz	scala/Iterator$class;
Asciz	scala/Tuple2;
Asciz	that$3;
Asciz	this;
Asciz	toString;
Asciz	x$1;
Asciz	zip;

{
private final scala.Iterator that$3;
  Signature: Lscala/Iterator;

private final scala.Iterator $outer;
  Signature: Lscala/Iterator;

public scala.Iterator$$anon$17(scala.Iterator, scala.Iterator);
  Signature: (Lscala/Iterator;Lscala/Iterator;)V
  Code:
   Stack=2, Locals=3, Args_size=3
	aload_1
	ifnonnull	l1 // aload_0
	new	class java/lang/NullPointerException
	dup
	invokespecial	Method java/lang/NullPointerException."<init>":()V
	athrow
l1	aload_0
	aload_1
	putfield	Field $outer:Lscala/Iterator;
	aload_0
	aload_2
	putfield	Field that$3:Lscala/Iterator;
	aload_0
	invokespecial	Method java/lang/Object."<init>":()V
	aload_0
	invokestatic	Method scala/Iterator$class.$init$:(Lscala/Iterator;)V
	return
  Labels:
   	l1 = 12 // aload_0
  LocalVariableTable: 
   Start  Length  Slot  Name   Signature
   0      31      0    this       Lscala/Iterator$$anon$17;
   0      31      1    $outer       Lscala/Iterator;

  Signature: length = 0x2
   00 33 

public java.lang.Object next();
  Signature: ()Ljava/lang/Object;
  Code:
   Stack=1, Locals=1, Args_size=1
	aload_0
	invokevirtual	Method next:()Lscala/Tuple2;
	areturn
  Labels:

public scala.Tuple2 next();
  Signature: ()Lscala/Tuple2;
  Code:
   Stack=4, Locals=1, Args_size=1
	new	class scala/Tuple2
	dup
	aload_0
	getfield	Field $outer:Lscala/Iterator;
	invokeinterface	InterfaceMethod scala/Iterator.next:()Ljava/lang/Object;
	aload_0
	getfield	Field that$3:Lscala/Iterator;
	invokeinterface	InterfaceMethod scala/Iterator.next:()Ljava/lang/Object;
	invokespecial	Method scala/Tuple2."<init>":(Ljava/lang/Object;Ljava/lang/Object;)V
	areturn
  Labels:
  Signature: length = 0x2
   00 26 

public boolean hasNext();
  Signature: ()Z
  Code:
   Stack=1, Locals=1, Args_size=1
	aload_0
	getfield	Field $outer:Lscala/Iterator;
	invokeinterface	InterfaceMethod scala/Iterator.hasNext:()Z
	ifeq	l1 // iconst_0
	aload_0
	getfield	Field that$3:Lscala/Iterator;
	invokeinterface	InterfaceMethod scala/Iterator.hasNext:()Z
	ifeq	l1 // iconst_0
	iconst_1
	goto	l2 // ireturn
l1	iconst_0
l2	ireturn
  Labels:
   	l1 = 28 // iconst_0
   	l2 = 29 // ireturn

public java.lang.String toString();
  Signature: ()Ljava/lang/String;
  Code:
   Stack=1, Locals=1, Args_size=1
	aload_0
	invokestatic	Method scala/Iterator$class.toString:(Lscala/Iterator;)Ljava/lang/String;
	areturn
  Labels:

public boolean forall(scala.Function1);
  Signature: (Lscala/Function1;)Z
  Code:
   Stack=2, Locals=2, Args_size=2
	aload_0
	aload_1
	invokestatic	Method scala/Iterator$class.forall:(Lscala/Iterator;Lscala/Function1;)Z
	ireturn
  Labels:
  LocalVariableTable: 
   Start  Length  Slot  Name   Signature
   0      6      0    this       Lscala/Iterator$$anon$17;
   0      6      1    x$1       Lscala/Function1;


public void foreach(scala.Function1);
  Signature: (Lscala/Function1;)V
  Code:
   Stack=2, Locals=2, Args_size=2
	aload_0
	aload_1
	invokestatic	Method scala/Iterator$class.foreach:(Lscala/Iterator;Lscala/Function1;)V
	return
  Labels:
  LocalVariableTable: 
   Start  Length  Slot  Name   Signature
   0      6      0    this       Lscala/Iterator$$anon$17;
   0      6      1    x$1       Lscala/Function1;


public java.lang.Object zip(scala.Iterator);
  Signature: (Lscala/Iterator;)Ljava/lang/Object;
  Code:
   Stack=2, Locals=2, Args_size=2
	aload_0
	aload_1
	invokestatic	Method scala/Iterator$class.zip:(Lscala/Iterator;Lscala/Iterator;)Ljava/lang/Object;
	areturn
  Labels:
  LocalVariableTable: 
   Start  Length  Slot  Name   Signature
   0      6      0    this       Lscala/Iterator$$anon$17;
   0      6      1    x$1       Lscala/Iterator;


}

