Compiled from "Iterable.scala"
public abstract class scala.Iterable$class extends java.lang.Object
  Scala: length = 0x
   
  SourceFile: "Iterable.scala"
  minor version: 0
  major version: 49
  Constant pool:
class	java/lang/Object
class	scala/Iterable
class	scala/Iterable$class
class	scala/Iterator
class	scala/StringBuilder
Method	scala/StringBuilder."<init>":()V
Method	scala/StringBuilder.append:(Ljava/lang/Object;)Lscala/StringBuilder;
Method	scala/StringBuilder.append:(Ljava/lang/String;)Lscala/StringBuilder;
Method	scala/StringBuilder.toString:()Ljava/lang/String;
InterfaceMethod	scala/Iterable.addString:(Lscala/StringBuilder;Ljava/lang/String;Ljava/lang/String;Ljava/lang/String;)Lscala/StringBuilder;
InterfaceMethod	scala/Iterable.elements:()Lscala/Iterator;
InterfaceMethod	scala/Iterator.hasNext:()Z
InterfaceMethod	scala/Iterator.next:()Ljava/lang/Object;
NameAndType	"<init>":()V
NameAndType	addString:(Lscala/StringBuilder;Ljava/lang/String;Ljava/lang/String;Ljava/lang/String;)Lscala/StringBuilder;
NameAndType	append:(Ljava/lang/Object;)Lscala/StringBuilder;
NameAndType	append:(Ljava/lang/String;)Lscala/StringBuilder;
NameAndType	elements:()Lscala/Iterator;
NameAndType	hasNext:()Z
NameAndType	next:()Ljava/lang/Object;
NameAndType	toString:()Ljava/lang/String;
Asciz	$init$;
Asciz	$this;
Asciz	()Ljava/lang/Object;;
Asciz	()Ljava/lang/String;;
Asciz	()Lscala/Iterator;;
Asciz	()V;
Asciz	()Z;
Asciz	(Ljava/lang/Object;)Lscala/StringBuilder;;
Asciz	(Ljava/lang/String;)Lscala/StringBuilder;;
Asciz	(Lscala/Iterable;)V;
Asciz	(Lscala/Iterable;Ljava/lang/String;Ljava/lang/String;Ljava/lang/String;)Ljava/lang/String;;
Asciz	(Lscala/Iterable;Lscala/StringBuilder;Ljava/lang/String;Ljava/lang/String;Ljava/lang/String;)Lscala/StringBuilder;;
Asciz	(Lscala/StringBuilder;Ljava/lang/String;Ljava/lang/String;Ljava/lang/String;)Lscala/StringBuilder;;
Asciz	<init>;
Asciz	Code;
Asciz	Iterable.scala;
Asciz	LineNumberTable;
Asciz	Ljava/lang/String;;
Asciz	LocalVariableTable;
Asciz	Lscala/Iterable;;
Asciz	Lscala/Iterator;;
Asciz	Lscala/StringBuilder;;
Asciz	Scala;
Asciz	SourceFile;
Asciz	addString;
Asciz	append;
Asciz	buf;
Asciz	elements;
Asciz	elems;
Asciz	end;
Asciz	hasNext;
Asciz	java/lang/Object;
Asciz	mkString;
Asciz	next;
Asciz	scala/Iterable;
Asciz	scala/Iterable$class;
Asciz	scala/Iterator;
Asciz	scala/StringBuilder;
Asciz	sep;
Asciz	start;
Asciz	toString;

{
public static void $init$(scala.Iterable);
  Signature: (Lscala/Iterable;)V
  Code:
   Stack=0, Locals=1, Args_size=1
	return
  Labels:
  LocalVariableTable: 
   Start  Length  Slot  Name   Signature
   0      1      0    $this       Lscala/Iterable;


public static scala.StringBuilder addString(scala.Iterable, scala.StringBuilder, java.lang.String, java.lang.String, java.lang.String);
  Signature: (Lscala/Iterable;Lscala/StringBuilder;Ljava/lang/String;Ljava/lang/String;Ljava/lang/String;)Lscala/StringBuilder;
  Code:
   Stack=2, Locals=6, Args_size=5
	aload_1
	aload_2
	invokevirtual	Method scala/StringBuilder.append:(Ljava/lang/String;)Lscala/StringBuilder;
	pop
	aload_0
	invokeinterface	InterfaceMethod scala/Iterable.elements:()Lscala/Iterator;
	astore	5
	aload	5
	invokeinterface	InterfaceMethod scala/Iterator.hasNext:()Z
	ifeq	l1 // aload
	aload_1
	aload	5
	invokeinterface	InterfaceMethod scala/Iterator.next:()Ljava/lang/Object;
	invokevirtual	Method scala/StringBuilder.append:(Ljava/lang/Object;)Lscala/StringBuilder;
	pop
l1	aload	5
	invokeinterface	InterfaceMethod scala/Iterator.hasNext:()Z
	ifeq	l2 // aload_1
	aload_1
	aload_3
	invokevirtual	Method scala/StringBuilder.append:(Ljava/lang/String;)Lscala/StringBuilder;
	pop
	aload_1
	aload	5
	invokeinterface	InterfaceMethod scala/Iterator.next:()Ljava/lang/Object;
	invokevirtual	Method scala/StringBuilder.append:(Ljava/lang/Object;)Lscala/StringBuilder;
	pop
	goto	l1 // aload
l2	aload_1
	aload	4
	invokevirtual	Method scala/StringBuilder.append:(Ljava/lang/String;)Lscala/StringBuilder;
	areturn
  Labels:
   	l1 = 36 // aload
   	l2 = 67 // aload_1
  LocalVariableTable: 
   Start  Length  Slot  Name   Signature
   0      74      0    $this       Lscala/Iterable;
   0      74      1    buf       Lscala/StringBuilder;
   0      74      2    start       Ljava/lang/String;
   0      74      3    sep       Ljava/lang/String;
   0      74      4    end       Ljava/lang/String;
   6      67      5    elems       Lscala/Iterator;


public static java.lang.String mkString(scala.Iterable, java.lang.String, java.lang.String, java.lang.String);
  Signature: (Lscala/Iterable;Ljava/lang/String;Ljava/lang/String;Ljava/lang/String;)Ljava/lang/String;
  Code:
   Stack=5, Locals=5, Args_size=4
	new	class scala/StringBuilder
	dup
	invokespecial	Method scala/StringBuilder."<init>":()V
	astore	4
	aload_0
	aload	4
	aload_1
	aload_2
	aload_3
	invokeinterface	InterfaceMethod scala/Iterable.addString:(Lscala/StringBuilder;Ljava/lang/String;Ljava/lang/String;Ljava/lang/String;)Lscala/StringBuilder;
	invokevirtual	Method scala/StringBuilder.toString:()Ljava/lang/String;
	areturn
  Labels:
  LocalVariableTable: 
   Start  Length  Slot  Name   Signature
   0      24      0    $this       Lscala/Iterable;
   0      24      1    start       Ljava/lang/String;
   0      24      2    sep       Ljava/lang/String;
   0      24      3    end       Ljava/lang/String;
   0      23      4    buf       Lscala/StringBuilder;


}

