Compiled from "Either.scala"
public final class scala.Left extends scala.Either implements scala.ScalaObject,scala.Product,java.io.Serializable
  SourceFile: "Either.scala"
  ScalaSig: length = 0x3
   05 00 00 
  Signature: length = 0x2
   00 79 
  RuntimeVisibleAnnotations: length = 0xB
   00 01 00 7A 00 01 00 7B 73 00 7C 
  minor version: 0
  major version: 49
  Constant pool:
Asciz	SourceFile;
Asciz	Either.scala;
Asciz	a;
Asciz	Ljava/lang/Object;;
Asciz	TA;;
Asciz	Signature;
Asciz	productElementName;
Asciz	(I)Ljava/lang/String;;
Asciz	Code;
Asciz	LineNumberTable;
Asciz	scala/Product$class;
class	scala/Product$class
Asciz	(Lscala/Product;I)Ljava/lang/String;;
NameAndType	productElementName:(Lscala/Product;I)Ljava/lang/String;
Method	scala/Product$class.productElementName:(Lscala/Product;I)Ljava/lang/String;
Asciz	this;
Asciz	Lscala/Left;;
Asciz	n;
Asciz	I;
Asciz	LocalVariableTable;
Asciz	productIterator;
Asciz	()Lscala/collection/Iterator;;
Asciz	(Lscala/Product;)Lscala/collection/Iterator;;
NameAndType	productIterator:(Lscala/Product;)Lscala/collection/Iterator;
Method	scala/Product$class.productIterator:(Lscala/Product;)Lscala/collection/Iterator;
Asciz	productElements;
NameAndType	productElements:(Lscala/Product;)Lscala/collection/Iterator;
Method	scala/Product$class.productElements:(Lscala/Product;)Lscala/collection/Iterator;
Asciz	Deprecated;
Asciz	copy$default$1;
Asciz	()Ljava/lang/Object;;
Asciz	scala/Left;
class	scala/Left
NameAndType	a:()Ljava/lang/Object;
Method	scala/Left.a:()Ljava/lang/Object;
NameAndType	a:Ljava/lang/Object;
Field	scala/Left.a:Ljava/lang/Object;
Asciz	()TA;;
Asciz	isLeft;
Asciz	()Z;
Asciz	isRight;
Asciz	copy;
Asciz	(Ljava/lang/Object;)Lscala/Left;;
Asciz	<init>;
Asciz	(Ljava/lang/Object;)V;
NameAndType	"<init>":(Ljava/lang/Object;)V
Method	scala/Left."<init>":(Ljava/lang/Object;)V
Asciz	hashCode;
Asciz	()I;
Asciz	scala/runtime/ScalaRunTime$;
class	scala/runtime/ScalaRunTime$
Asciz	MODULE$;
Asciz	Lscala/runtime/ScalaRunTime$;;
NameAndType	MODULE$:Lscala/runtime/ScalaRunTime$;
Field	scala/runtime/ScalaRunTime$.MODULE$:Lscala/runtime/ScalaRunTime$;
Asciz	_hashCode;
Asciz	(Lscala/Product;)I;
NameAndType	_hashCode:(Lscala/Product;)I
Method	scala/runtime/ScalaRunTime$._hashCode:(Lscala/Product;)I
Asciz	toString;
Asciz	()Ljava/lang/String;;
Asciz	_toString;
Asciz	(Lscala/Product;)Ljava/lang/String;;
NameAndType	_toString:(Lscala/Product;)Ljava/lang/String;
Method	scala/runtime/ScalaRunTime$._toString:(Lscala/Product;)Ljava/lang/String;
Asciz	equals;
Asciz	(Ljava/lang/Object;)Z;
Asciz	gd1$1;
NameAndType	gd1$1:(Ljava/lang/Object;)Z
Method	scala/Left.gd1$1:(Ljava/lang/Object;)Z
Asciz	temp22;
Asciz	temp23;
Asciz	productPrefix;
Asciz	Left;
String	Left
Asciz	productArity;
Asciz	productElement;
Asciz	(I)Ljava/lang/Object;;
Asciz	java/lang/IndexOutOfBoundsException;
class	java/lang/IndexOutOfBoundsException
Asciz	scala/runtime/BoxesRunTime;
class	scala/runtime/BoxesRunTime
Asciz	boxToInteger;
Asciz	(I)Ljava/lang/Integer;;
NameAndType	boxToInteger:(I)Ljava/lang/Integer;
Method	scala/runtime/BoxesRunTime.boxToInteger:(I)Ljava/lang/Integer;
Asciz	java/lang/Object;
class	java/lang/Object
NameAndType	toString:()Ljava/lang/String;
Method	java/lang/Object.toString:()Ljava/lang/String;
Asciz	(Ljava/lang/String;)V;
NameAndType	"<init>":(Ljava/lang/String;)V
Method	java/lang/IndexOutOfBoundsException."<init>":(Ljava/lang/String;)V
Asciz	canEqual;
Asciz	java/lang/Number;
class	java/lang/Number
Asciz	equalsNumObject;
Asciz	(Ljava/lang/Number;Ljava/lang/Object;)Z;
NameAndType	equalsNumObject:(Ljava/lang/Number;Ljava/lang/Object;)Z
Method	scala/runtime/BoxesRunTime.equalsNumObject:(Ljava/lang/Number;Ljava/lang/Object;)Z
Asciz	java/lang/Character;
class	java/lang/Character
Asciz	equalsCharObject;
Asciz	(Ljava/lang/Character;Ljava/lang/Object;)Z;
NameAndType	equalsCharObject:(Ljava/lang/Character;Ljava/lang/Object;)Z
Method	scala/runtime/BoxesRunTime.equalsCharObject:(Ljava/lang/Character;Ljava/lang/Object;)Z
NameAndType	equals:(Ljava/lang/Object;)Z
Method	java/lang/Object.equals:(Ljava/lang/Object;)Z
Asciz	y0;
Asciz	scala/Either;
class	scala/Either
Asciz	()V;
NameAndType	"<init>":()V
Method	scala/Either."<init>":()V
Asciz	$init$;
Asciz	(Lscala/Product;)V;
NameAndType	$init$:(Lscala/Product;)V
Method	scala/Product$class.$init$:(Lscala/Product;)V
Asciz	(TA;)V;
Asciz	ScalaSig;
Asciz	<A:Ljava/lang/Object;B:Ljava/lang/Object;>Lscala/Either<TA;TB;>;Lscala/ScalaObject;Lscala/Product;;
Asciz	Lscala/reflect/ScalaSignature;;
Asciz	bytes;
Asciz	UbBAT3gi*\t1!AtGdmiqcea\nYiAA\ta!R5uQC!B\raFc\tEI!A9{G[5oOBF+\t1!8z!\taqIQ1C\tY\"AATGdm2kK$C\tq\"AAQe>$Wo;\t!Q3A\n!Y!A1B\tB%1\"bA!)QCM1A(8jiz\"\"a\n\t!1BA\raU!\taKSNdUM;1\"C\n9!a\"p_2,Ma!\taKSNn5u!!AM\nAaY8qsVAgNURma\"D9\tD!AC=\"Da\tD!AC=AqIaC=EIA\r|/eKW;%cUaS%+-y4&!3U\"\"\r#!C;oG\",7m[3e\t)%!b]:|G/;j_:L!a\"#Ut7\r[3dW$g+:jC:W\rw\tQ1\t!A2\"AyC&\tI\t'!7[\"pI$!\t9K!a%sGR\t\"S!!xn;sS:<G#A*Q;fBV\t1&!Qe$WMZ1faa;sS:<'B,!Y\"A\nbAB3rkd7-;\"9aLWAa=%c!A\rC-Aqe>$Wo;Qe4_EB1\r[I*QMZYtwMChQM^1\na#6\tII6AxZ;di^=5C\"%\tE\aJ|G-^2u2,W.8u)\trC_Y\tA'\tEA!ABIbY1oF,\rYMDqA91kBB^o\nAb]3sSdN_1cY<q!#!0MK$C|\r!\t!bAa8cA>~3A1M`aa2kK$BB|\t\tF{%\t9a_A\nI!AbaBd0EQ\t9\t=1\tEA!\tQ1!\raQ\n1A!AC=AqIA\tyCm\t\"!9QO\1qa2LXCBAS\t\"-#$bAA\t1q\n;j_:2DA\t%qCq.eAA\rAH\r\t\t9#!\r1\tB3!\t!b;
Asciz	RuntimeVisibleAnnotations;
Asciz	scala/ScalaObject;
class	scala/ScalaObject
Asciz	scala/Product;
class	scala/Product
Asciz	java/io/Serializable;
class	java/io/Serializable

{
public final java.lang.Object a;
  Signature: Ljava/lang/Object;
  Signature: length = 0x2
   00 05 

public java.lang.String productElementName(int);
  Signature: (I)Ljava/lang/String;
  Code:
   Stack=2, Locals=2, Args_size=2
	aload_0
	iload_1
	invokestatic	Method scala/Product$class.productElementName:(Lscala/Product;I)Ljava/lang/String;
	areturn
  Labels:
  LocalVariableTable: 
   Start  Length  Slot  Name   Signature
   0      6      0    this       Lscala/Left;
   0      6      1    n       I


public scala.collection.Iterator productIterator();
  Signature: ()Lscala/collection/Iterator;
  Code:
   Stack=1, Locals=1, Args_size=1
	aload_0
	invokestatic	Method scala/Product$class.productIterator:(Lscala/Product;)Lscala/collection/Iterator;
	areturn
  Labels:

public scala.collection.Iterator productElements();
  Signature: ()Lscala/collection/Iterator;
  Code:
   Stack=1, Locals=1, Args_size=1
	aload_0
	invokestatic	Method scala/Product$class.productElements:(Lscala/Product;)Lscala/collection/Iterator;
	areturn
  Labels:
  Deprecated: true

public java.lang.Object copy$default$1();
  Signature: ()Ljava/lang/Object;
  Code:
   Stack=1, Locals=1, Args_size=1
	aload_0
	invokevirtual	Method a:()Ljava/lang/Object;
	areturn
  Labels:

public java.lang.Object a();
  Signature: ()Ljava/lang/Object;
  Code:
   Stack=1, Locals=1, Args_size=1
	aload_0
	getfield	Field a:Ljava/lang/Object;
	areturn
  Labels:
  Signature: length = 0x2
   00 26 

public boolean isLeft();
  Signature: ()Z
  Code:
   Stack=1, Locals=1, Args_size=1
	iconst_1
	ireturn
  Labels:

public boolean isRight();
  Signature: ()Z
  Code:
   Stack=1, Locals=1, Args_size=1
	iconst_0
	ireturn
  Labels:

public scala.Left copy(java.lang.Object);
  Signature: (Ljava/lang/Object;)Lscala/Left;
  Code:
   Stack=3, Locals=2, Args_size=2
	new	class scala/Left
	dup
	aload_1
	invokespecial	Method "<init>":(Ljava/lang/Object;)V
	areturn
  Labels:
  LocalVariableTable: 
   Start  Length  Slot  Name   Signature
   0      9      0    this       Lscala/Left;
   0      9      1    a       Ljava/lang/Object;


public int hashCode();
  Signature: ()I
  Code:
   Stack=2, Locals=1, Args_size=1
	getstatic	Field scala/runtime/ScalaRunTime$.MODULE$:Lscala/runtime/ScalaRunTime$;
	aload_0
	invokevirtual	Method scala/runtime/ScalaRunTime$._hashCode:(Lscala/Product;)I
	ireturn
  Labels:

public java.lang.String toString();
  Signature: ()Ljava/lang/String;
  Code:
   Stack=2, Locals=1, Args_size=1
	getstatic	Field scala/runtime/ScalaRunTime$.MODULE$:Lscala/runtime/ScalaRunTime$;
	aload_0
	invokevirtual	Method scala/runtime/ScalaRunTime$._toString:(Lscala/Product;)Ljava/lang/String;
	areturn
  Labels:

public boolean equals(java.lang.Object);
  Signature: (Ljava/lang/Object;)Z
  Code:
   Stack=2, Locals=4, Args_size=2
	aload_0
	aload_1
	if_acmpeq	l1 // iconst_1
	aload_1
	instanceof	class scala/Left
	ifeq	l2 // iconst_0
	aload_1
	checkcast	class scala/Left
	astore_2
	aload_2
	getfield	Field a:Ljava/lang/Object;
	astore_3
	aload_0
	aload_3
	invokespecial	Method gd1$1:(Ljava/lang/Object;)Z
	ifeq	l3 // iconst_0
	aload_0
	instanceof	class scala/Left
	goto	l4 // ifeq
l3	iconst_0
	goto	l4 // ifeq
l2	iconst_0
l4	ifeq	l5 // iconst_0
l1	iconst_1
	goto	l6 // ireturn
l5	iconst_0
l6	ireturn
  Labels:
   	l3 = 37 // iconst_0
   	l2 = 41 // iconst_0
   	l4 = 42 // ifeq
   	l1 = 45 // iconst_1
   	l5 = 49 // iconst_0
   	l6 = 50 // ireturn
  LocalVariableTable: 
   Start  Length  Slot  Name   Signature
   0      51      0    this       Lscala/Left;
   17      24      2    temp22       Lscala/Left;
   22      19      3    temp23       Ljava/lang/Object;


public java.lang.String productPrefix();
  Signature: ()Ljava/lang/String;
  Code:
   Stack=1, Locals=1, Args_size=1
	ldc	String Left
	areturn
  Labels:

public int productArity();
  Signature: ()I
  Code:
   Stack=1, Locals=1, Args_size=1
	iconst_1
	ireturn
  Labels:

public java.lang.Object productElement(int);
  Signature: (I)Ljava/lang/Object;
  Code:
   Stack=3, Locals=2, Args_size=2
	iload_1
	iconst_0
	if_icmpne	l1 // new
	aload_0
	getfield	Field a:Ljava/lang/Object;
	areturn
l1	new	class java/lang/IndexOutOfBoundsException
	dup
	iload_1
	invokestatic	Method scala/runtime/BoxesRunTime.boxToInteger:(I)Ljava/lang/Integer;
	invokevirtual	Method java/lang/Object.toString:()Ljava/lang/String;
	invokespecial	Method java/lang/IndexOutOfBoundsException."<init>":(Ljava/lang/String;)V
	athrow
  Labels:
   	l1 = 10 // new

public boolean canEqual(java.lang.Object);
  Signature: (Ljava/lang/Object;)Z
  Code:
   Stack=1, Locals=2, Args_size=2
	aload_1
	instanceof	class scala/Left
	ireturn
  Labels:

private final boolean gd1$1(java.lang.Object);
  Signature: (Ljava/lang/Object;)Z
  Code:
   Stack=2, Locals=3, Args_size=2
	aload_0
	getfield	Field a:Ljava/lang/Object;
	astore_2
	aload_1
	aload_2
	if_acmpne	l1 // aload_1
	iconst_1
	goto	l2 // ifeq
l1	aload_1
	ifnonnull	l3 // aload_1
	iconst_0
	goto	l2 // ifeq
l3	aload_1
	instanceof	class java/lang/Number
	ifeq	l4 // aload_1
	aload_1
	checkcast	class java/lang/Number
	aload_2
	invokestatic	Method scala/runtime/BoxesRunTime.equalsNumObject:(Ljava/lang/Number;Ljava/lang/Object;)Z
	goto	l2 // ifeq
l4	aload_1
	instanceof	class java/lang/Character
	ifeq	l5 // aload_1
	aload_1
	checkcast	class java/lang/Character
	aload_2
	invokestatic	Method scala/runtime/BoxesRunTime.equalsCharObject:(Ljava/lang/Character;Ljava/lang/Object;)Z
	goto	l2 // ifeq
l5	aload_1
	aload_2
	invokevirtual	Method java/lang/Object.equals:(Ljava/lang/Object;)Z
l2	ifeq	l6 // iconst_0
	iconst_1
	goto	l7 // ireturn
l6	iconst_0
l7	ireturn
  Labels:
   	l1 = 14 // aload_1
   	l3 = 22 // aload_1
   	l4 = 40 // aload_1
   	l5 = 58 // aload_1
   	l2 = 63 // ifeq
   	l6 = 70 // iconst_0
   	l7 = 71 // ireturn
  LocalVariableTable: 
   Start  Length  Slot  Name   Signature
   0      72      0    this       Lscala/Left;
   10      56      2    y0       Ljava/lang/Object;


public scala.Left(java.lang.Object);
  Signature: (Ljava/lang/Object;)V
  Code:
   Stack=2, Locals=2, Args_size=2
	aload_0
	aload_1
	putfield	Field a:Ljava/lang/Object;
	aload_0
	invokespecial	Method scala/Either."<init>":()V
	aload_0
	invokestatic	Method scala/Product$class.$init$:(Lscala/Product;)V
	return
  Labels:
  LocalVariableTable: 
   Start  Length  Slot  Name   Signature
   0      14      0    this       Lscala/Left;
   0      14      1    a       Ljava/lang/Object;

  Signature: length = 0x2
   00 77 

}

