Compiled from "List.scala"
public final class scala.List$$anon$2 extends java.lang.Object implements scala.Iterator
  InnerClass: 
   public final $anon$2=class scala/List$$anon$2 of class scala/List
  Scala: length = 0x
   
  Signature: length = 0x2
   00 40 
  SourceFile: "List.scala"
  minor version: 0
  major version: 49
  Constant pool:
String	next on empty Iterator
class	java/lang/Object
class	java/util/NoSuchElementException
class	scala/Iterator
class	scala/Iterator$class
class	scala/List
class	scala/List$$anon$2
class	scala/Seq
Field	scala/List$$anon$2.these:Lscala/List;
Method	java/lang/Object."<init>":()V
Method	java/util/NoSuchElementException."<init>":(Ljava/lang/String;)V
Method	scala/Iterator$class.$init$:(Lscala/Iterator;)V
Method	scala/Iterator$class.forall:(Lscala/Iterator;Lscala/Function1;)Z
Method	scala/Iterator$class.foreach:(Lscala/Iterator;Lscala/Function1;)V
Method	scala/Iterator$class.toString:(Lscala/Iterator;)Ljava/lang/String;
Method	scala/Iterator$class.zip:(Lscala/Iterator;Lscala/Iterator;)Ljava/lang/Object;
Method	scala/List.head:()Ljava/lang/Object;
Method	scala/List.tail:()Lscala/List;
Method	scala/List$$anon$2.hasNext:()Z
Method	scala/List$$anon$2.these:()Lscala/List;
Method	scala/List$$anon$2.these_$eq:(Lscala/List;)V
InterfaceMethod	scala/Seq.isEmpty:()Z
NameAndType	$init$:(Lscala/Iterator;)V
NameAndType	"<init>":()V
NameAndType	"<init>":(Ljava/lang/String;)V
NameAndType	forall:(Lscala/Iterator;Lscala/Function1;)Z
NameAndType	foreach:(Lscala/Iterator;Lscala/Function1;)V
NameAndType	hasNext:()Z
NameAndType	head:()Ljava/lang/Object;
NameAndType	isEmpty:()Z
NameAndType	tail:()Lscala/List;
NameAndType	these:()Lscala/List;
NameAndType	these:Lscala/List;
NameAndType	these_$eq:(Lscala/List;)V
NameAndType	toString:(Lscala/Iterator;)Ljava/lang/String;
NameAndType	zip:(Lscala/Iterator;Lscala/Iterator;)Ljava/lang/Object;
Asciz	$anon$2;
Asciz	$init$;
Asciz	$outer;
Asciz	()Ljava/lang/Object;;
Asciz	()Ljava/lang/String;;
Asciz	()Lscala/List;;
Asciz	()Lscala/List<TA;>;;
Asciz	()TA;;
Asciz	()V;
Asciz	()Z;
Asciz	(Ljava/lang/String;)V;
Asciz	(Lscala/Function1;)V;
Asciz	(Lscala/Function1;)Z;
Asciz	(Lscala/Iterator;)Ljava/lang/Object;;
Asciz	(Lscala/Iterator;)Ljava/lang/String;;
Asciz	(Lscala/Iterator;)V;
Asciz	(Lscala/Iterator;Lscala/Function1;)V;
Asciz	(Lscala/Iterator;Lscala/Function1;)Z;
Asciz	(Lscala/Iterator;Lscala/Iterator;)Ljava/lang/Object;;
Asciz	(Lscala/List;)V;
Asciz	(Lscala/List<TA;>;)V;
Asciz	<init>;
Asciz	Code;
Asciz	InnerClasses;
Asciz	LineNumberTable;
Asciz	List.scala;
Asciz	Ljava/lang/Object;;
Asciz	Ljava/lang/Object;Lscala/Iterator<TA;>;;
Asciz	LocalVariableTable;
Asciz	Lscala/Function1;;
Asciz	Lscala/Iterator;;
Asciz	Lscala/List$$anon$2;;
Asciz	Lscala/List;;
Asciz	Lscala/List<TA;>;;
Asciz	Scala;
Asciz	Signature;
Asciz	SourceFile;
Asciz	forall;
Asciz	foreach;
Asciz	hasNext;
Asciz	head;
Asciz	isEmpty;
Asciz	java/lang/Object;
Asciz	java/util/NoSuchElementException;
Asciz	next;
Asciz	next on empty Iterator;
Asciz	result;
Asciz	scala/Iterator;
Asciz	scala/Iterator$class;
Asciz	scala/List;
Asciz	scala/List$$anon$2;
Asciz	scala/Seq;
Asciz	tail;
Asciz	these;
Asciz	these_$eq;
Asciz	this;
Asciz	toString;
Asciz	x$1;
Asciz	zip;

{
private scala.List these;
  Signature: Lscala/List;
  Signature: length = 0x2
   00 46 

public scala.List$$anon$2(scala.List);
  Signature: (Lscala/List;)V
  Code:
   Stack=2, Locals=2, Args_size=2
	aload_0
	aload_1
	putfield	Field these:Lscala/List;
	aload_0
	invokespecial	Method java/lang/Object."<init>":()V
	aload_0
	invokestatic	Method scala/Iterator$class.$init$:(Lscala/Iterator;)V
	return
  Labels:
  LocalVariableTable: 
   Start  Length  Slot  Name   Signature
   0      14      0    this       Lscala/List$$anon$2;
   0      14      1    $outer       Lscala/List;

  Signature: length = 0x2
   00 39 

public java.lang.Object next();
  Signature: ()Ljava/lang/Object;
  Code:
   Stack=3, Locals=2, Args_size=1
	aload_0
	invokevirtual	Method hasNext:()Z
	ifeq	l1 // new
	aload_0
	invokevirtual	Method these:()Lscala/List;
	invokevirtual	Method scala/List.head:()Ljava/lang/Object;
	astore_1
	aload_0
	aload_0
	invokevirtual	Method these:()Lscala/List;
	invokevirtual	Method scala/List.tail:()Lscala/List;
	invokevirtual	Method these_$eq:(Lscala/List;)V
	aload_1
	areturn
l1	new	class java/util/NoSuchElementException
	dup
	ldc	String next on empty Iterator
	invokespecial	Method java/util/NoSuchElementException."<init>":(Ljava/lang/String;)V
	athrow
  Labels:
   	l1 = 28 // new
  LocalVariableTable: 
   Start  Length  Slot  Name   Signature
   0      38      0    this       Lscala/List$$anon$2;
   7      20      1    result       Ljava/lang/Object;

  Signature: length = 0x2
   00 2C 

public boolean hasNext();
  Signature: ()Z
  Code:
   Stack=1, Locals=1, Args_size=1
	aload_0
	invokevirtual	Method these:()Lscala/List;
	invokeinterface	InterfaceMethod scala/Seq.isEmpty:()Z
	ifeq	l1 // iconst_1
	iconst_0
	goto	l2 // ireturn
l1	iconst_1
l2	ireturn
  Labels:
   	l1 = 16 // iconst_1
   	l2 = 17 // ireturn

public void these_$eq(scala.List);
  Signature: (Lscala/List;)V
  Code:
   Stack=2, Locals=2, Args_size=2
	aload_0
	aload_1
	putfield	Field these:Lscala/List;
	return
  Labels:
  LocalVariableTable: 
   Start  Length  Slot  Name   Signature
   0      6      0    this       Lscala/List$$anon$2;
   0      6      1    x$1       Lscala/List;

  Signature: length = 0x2
   00 39 

public scala.List these();
  Signature: ()Lscala/List;
  Code:
   Stack=1, Locals=1, Args_size=1
	aload_0
	getfield	Field these:Lscala/List;
	areturn
  Labels:
  Signature: length = 0x2
   00 2B 

public java.lang.String toString();
  Signature: ()Ljava/lang/String;
  Code:
   Stack=1, Locals=1, Args_size=1
	aload_0
	invokestatic	Method scala/Iterator$class.toString:(Lscala/Iterator;)Ljava/lang/String;
	areturn
  Labels:

public boolean forall(scala.Function1);
  Signature: (Lscala/Function1;)Z
  Code:
   Stack=2, Locals=2, Args_size=2
	aload_0
	aload_1
	invokestatic	Method scala/Iterator$class.forall:(Lscala/Iterator;Lscala/Function1;)Z
	ireturn
  Labels:
  LocalVariableTable: 
   Start  Length  Slot  Name   Signature
   0      6      0    this       Lscala/List$$anon$2;
   0      6      1    x$1       Lscala/Function1;


public void foreach(scala.Function1);
  Signature: (Lscala/Function1;)V
  Code:
   Stack=2, Locals=2, Args_size=2
	aload_0
	aload_1
	invokestatic	Method scala/Iterator$class.foreach:(Lscala/Iterator;Lscala/Function1;)V
	return
  Labels:
  LocalVariableTable: 
   Start  Length  Slot  Name   Signature
   0      6      0    this       Lscala/List$$anon$2;
   0      6      1    x$1       Lscala/Function1;


public java.lang.Object zip(scala.Iterator);
  Signature: (Lscala/Iterator;)Ljava/lang/Object;
  Code:
   Stack=2, Locals=2, Args_size=2
	aload_0
	aload_1
	invokestatic	Method scala/Iterator$class.zip:(Lscala/Iterator;Lscala/Iterator;)Ljava/lang/Object;
	areturn
  Labels:
  LocalVariableTable: 
   Start  Length  Slot  Name   Signature
   0      6      0    this       Lscala/List$$anon$2;
   0      6      1    x$1       Lscala/Iterator;


}

