Compiled from "List.scala"
public abstract class scala.List extends java.lang.Object implements scala.Product,scala.Seq
  InnerClass: 
   public final $anon$2=class scala/List$$anon$2 of class scala/List
  ScalaSig: length = 0x10C4
   04 01 FFFFFF84 50 07 05 01 02 FFFFFF88 02 05 01 04 4C 69 73
   74 0A 01 03 01 05 73 63 61 6C 61 03 00 10 02 06
   07 0D 01 02 06 08 08 02 FFFFFF84 FFFFFF80 FFFFFF80 FFFFFF88 02 09 02 04
   4C 69 73 74 13 03 07 0A 12 10 02 0B 10 0D 01 0C
   0A 02 0D 0E 01 04 6C 61 6E 67 0A 01 0F 01 04 6A
   61 76 61 09 02 11 0C 02 06 4F 62 6A 65 63 74 10
   02 06 13 09 02 14 02 02 0B 53 63 61 6C 61 4F 62
   6A 65 63 74 08 05 16 07 FFFFFF84 00 17 01 06 3C 69 6E
   69 74 3E 14 01 05 08 05 19 07 FFFFFF84 00 1A 01 05 61
   70 70 6C 79 15 03 1B FFFFFF82 61 14 03 1C FFFFFF82 62 10 04
   06 1D FFFFFF82 60 06 05 08 02 FFFFFF81 10 1E 15 02 1F 25 13
   05 1D 0A 20 2E 12 10 03 06 21 23 09 02 22 02 02
   03 53 65 71 10 02 24 25 0C 00 04 08 26 1D FFFFFF84 FFFFFF80
   FFFFFF84 FFFFFFC2 00 27 02 01 41 11 02 28 2B 10 02 06 29 09
   02 2A 02 02 07 4E 6F 74 68 69 6E 67 10 02 06 2C
   09 02 2D 02 02 03 41 6E 79 10 02 06 2F 09 02 30
   02 02 07 50 72 6F 64 75 63 74 08 05 16 1D FFFFFF84 00
   32 14 01 33 10 03 06 1D 23 08 05 35 1D FFFFFF86 20 36
   01 07 69 73 45 6D 70 74 79 15 01 37 10 02 06 38
   09 02 39 02 02 07 42 6F 6F 6C 65 61 6E 08 05 3B
   1D FFFFFF86 00 3C 01 04 68 65 61 64 15 01 23 08 05 3E
   1D FFFFFF84 20 3F 01 0D 6C 65 6E 67 74 68 43 6F 6D 70
   61 72 65 14 02 40 40 10 02 06 41 09 02 42 02 02
   03 49 6E 74 08 05 44 1D FFFFFF86 00 45 01 04 74 61 69
   6C 15 01 33 08 05 47 1D FFFFFF84 00 48 01 0C 24 63 6F
   6C 6F 6E 24 63 6F 6C 6F 6E 15 02 49 4C 14 02 4A
   4B 10 03 06 1D 4B 10 02 24 4C 04 08 4D 46 FFFFFF84 FFFFFF80
   FFFFFF80 FFFFFFC2 00 4E 02 01 42 11 02 23 2B 08 05 50 1D FFFFFF84
   00 51 01 05 24 70 6C 75 73 15 02 52 55 14 02 53
   54 10 03 06 1D 54 10 02 24 55 04 08 4D 4F FFFFFF84 FFFFFF80
   FFFFFF80 FFFFFFC2 00 4E 28 02 4F 57 10 02 06 58 09 02 59 02
   02 0A 64 65 70 72 65 63 61 74 65 64 08 05 5B 1D
   FFFFFF84 00 5C 01 12 24 63 6F 6C 6F 6E 24 63 6F 6C 6F
   6E 24 63 6F 6C 6F 6E 15 02 5D 60 14 02 5E 5E 10
   03 06 1D 5F 10 02 24 60 04 08 4D 5A FFFFFF84 FFFFFF80 FFFFFF80 FFFFFFC2
   00 4E 08 05 62 1D FFFFFF84 20 63 01 0A 24 70 6C 75 73
   24 70 6C 75 73 15 02 64 67 14 02 65 68 10 03 06
   1D 66 10 02 24 67 04 08 4D 61 FFFFFF84 FFFFFF80 FFFFFF80 FFFFFFC2 00 4E
   10 03 06 69 66 09 02 6A 02 02 08 49 74 65 72 61
   62 6C 65 08 05 6C 1D FFFFFF84 00 6D 01 1A 72 65 76 65
   72 73 65 5F 24 63 6F 6C 6F 6E 24 63 6F 6C 6F 6E
   24 63 6F 6C 6F 6E 15 02 6E 71 14 02 6F 6F 10 03
   06 1D 70 10 02 24 71 04 08 4D 6B FFFFFF84 FFFFFF80 FFFFFF80 FFFFFFC2 00
   4E 08 05 73 1D FFFFFF84 00 74 01 06 6C 65 6E 67 74 68
   15 01 40 08 05 76 1D FFFFFF84 00 77 01 07 69 6E 64 69
   63 65 73 15 01 78 10 03 06 1D 40 08 05 7A 1D FFFFFF84
   20 7B 01 08 65 6C 65 6D 65 6E 74 73 15 01 7C 10
   03 06 7D 23 09 02 7E 02 02 08 49 74 65 72 61 74
   6F 72 08 06 FFFFFF81 00 1D FFFFFF84 20 45 01 06 74 6F 4C 69
   73 74 08 06 FFFFFF81 02 1D FFFFFF84 00 45 01 04 69 6E 69 74
   08 06 FFFFFF81 04 1D FFFFFF84 20 3C 01 04 6C 61 73 74 08 07
   FFFFFF81 06 1D FFFFFF84 20 FFFFFF81 07 01 04 74 61 6B 65 14 02 33
   40 08 07 FFFFFF81 09 1D FFFFFF84 20 FFFFFF81 0A 01 05 73 6C 69 63
   65 14 03 33 40 40 08 07 FFFFFF81 0C 1D FFFFFF84 20 FFFFFF81 07 01
   04 64 72 6F 70 08 07 FFFFFF81 0E 1D FFFFFF84 00 FFFFFF81 07 01 09
   74 61 6B 65 52 69 67 68 74 08 07 FFFFFF81 10 1D FFFFFF84 00
   FFFFFF81 07 01 09 64 72 6F 70 52 69 67 68 74 08 07 FFFFFF81
   12 1D FFFFFF84 00 FFFFFF81 13 01 07 73 70 6C 69 74 41 74 14
   03 FFFFFF81 14 40 10 05 06 FFFFFF81 15 33 33 09 03 FFFFFF81 16 02
   02 06 54 75 70 6C 65 32 08 07 FFFFFF81 18 1D FFFFFF84 20 FFFFFF81
   19 01 09 74 61 6B 65 57 68 69 6C 65 14 03 33 FFFFFF81
   1A 10 05 06 FFFFFF81 1B 23 37 09 03 FFFFFF81 1C 02 02 09 46
   75 6E 63 74 69 6F 6E 31 08 07 FFFFFF81 1E 1D FFFFFF84 20 FFFFFF81
   19 01 09 64 72 6F 70 57 68 69 6C 65 08 07 FFFFFF81 20
   1D FFFFFF84 00 FFFFFF81 21 01 04 73 70 61 6E 14 04 FFFFFF81 14 FFFFFF81
   1A 08 07 FFFFFF81 23 1D FFFFFF84 00 FFFFFF81 21 01 05 62 72 65 61
   6B 08 06 19 1D FFFFFF84 00 FFFFFF81 25 14 02 23 40 08 07 FFFFFF81
   27 1D FFFFFF84 22 FFFFFF81 28 01 03 6D 61 70 15 04 FFFFFF81 29 FFFFFF81
   2C 14 04 FFFFFF81 2A FFFFFF81 2D 10 04 06 1D FFFFFF81 2B 10 03 24
   FFFFFF81 2C 04 09 4D FFFFFF81 26 FFFFFF84 FFFFFF80 FFFFFF80 FFFFFFC2 00 27 10 06 06
   FFFFFF81 1B 23 FFFFFF81 2B 08 07 FFFFFF81 2F 1D FFFFFF84 00 FFFFFF81 30 01 0A
   72 65 76 65 72 73 65 4D 61 70 15 04 FFFFFF81 31 FFFFFF81 34
   14 04 FFFFFF81 32 FFFFFF81 35 10 04 06 1D FFFFFF81 33 10 03 24 FFFFFF81
   34 04 09 4D FFFFFF81 2E FFFFFF84 FFFFFF80 FFFFFF80 FFFFFFC2 00 27 10 06 06 FFFFFF81
   1B 23 FFFFFF81 33 08 07 FFFFFF81 37 1D FFFFFF84 22 FFFFFF81 38 01 07 66
   6F 72 65 61 63 68 14 04 FFFFFF81 39 FFFFFF81 3C 10 03 06 FFFFFF81
   3A 09 03 FFFFFF81 3B 02 02 04 55 6E 69 74 10 06 06 FFFFFF81
   1B 23 FFFFFF81 39 08 07 FFFFFF81 3E 1D FFFFFF84 22 FFFFFF81 19 01 06 66
   69 6C 74 65 72 08 07 FFFFFF81 40 1D FFFFFF84 00 FFFFFF81 19 01 06
   72 65 6D 6F 76 65 08 07 FFFFFF81 42 1D FFFFFF84 20 FFFFFF81 21 01
   09 70 61 72 74 69 74 69 6F 6E 08 07 FFFFFF81 44 1D FFFFFF84
   00 FFFFFF81 45 01 04 73 6F 72 74 14 03 33 FFFFFF81 46 10 06
   06 FFFFFF81 47 23 23 37 09 03 FFFFFF81 48 02 02 09 46 75 6E
   63 74 69 6F 6E 32 08 07 FFFFFF81 4A 1D FFFFFF84 00 FFFFFF81 4B 01
   05 63 6F 75 6E 74 14 03 40 FFFFFF81 1A 08 07 FFFFFF81 4D 1D
   FFFFFF84 20 FFFFFF81 4E 01 06 66 6F 72 61 6C 6C 14 03 37 FFFFFF81
   1A 08 07 FFFFFF81 50 1D FFFFFF84 20 FFFFFF81 4E 01 06 65 78 69 73
   74 73 08 07 FFFFFF81 52 1D FFFFFF84 20 FFFFFF81 53 01 04 66 69 6E
   64 14 04 FFFFFF81 54 FFFFFF81 1A 10 04 06 FFFFFF81 55 23 09 03 FFFFFF81
   56 02 02 06 4F 70 74 69 6F 6E 08 07 FFFFFF81 58 1D FFFFFF84
   20 FFFFFF81 59 01 08 66 6F 6C 64 4C 65 66 74 15 04 FFFFFF81
   5A FFFFFF81 5D 14 04 FFFFFF81 5B FFFFFF81 5C 14 04 FFFFFF81 5C FFFFFF81 5E 10
   03 24 FFFFFF81 5D 04 09 4D FFFFFF81 57 FFFFFF84 FFFFFF80 FFFFFF80 FFFFFFC2 00 27 10
   08 06 FFFFFF81 47 FFFFFF81 5C 23 FFFFFF81 5C 08 07 FFFFFF81 60 1D FFFFFF84 20
   FFFFFF81 61 01 09 66 6F 6C 64 52 69 67 68 74 15 04 FFFFFF81
   62 FFFFFF81 65 14 04 FFFFFF81 63 FFFFFF81 64 14 04 FFFFFF81 64 FFFFFF81 66 10
   03 24 FFFFFF81 65 04 09 4D FFFFFF81 5F FFFFFF84 FFFFFF80 FFFFFF80 FFFFFFC2 00 27 10
   08 06 FFFFFF81 47 23 FFFFFF81 64 FFFFFF81 64 08 07 FFFFFF81 68 1D FFFFFF84 20
   FFFFFF81 69 01 0A 72 65 64 75 63 65 4C 65 66 74 15 04
   FFFFFF81 6A FFFFFF81 6C 14 04 FFFFFF81 6B FFFFFF81 6D 10 03 24 FFFFFF81 6C 04
   09 4D FFFFFF81 67 FFFFFF84 FFFFFF80 FFFFFF80 FFFFFFC2 00 4E 10 08 06 FFFFFF81 47 FFFFFF81
   6B 23 FFFFFF81 6B 08 07 FFFFFF81 6F 1D FFFFFF84 20 FFFFFF81 70 01 0B 72
   65 64 75 63 65 52 69 67 68 74 15 04 FFFFFF81 71 FFFFFF81 73
   14 04 FFFFFF81 72 FFFFFF81 74 10 03 24 FFFFFF81 73 04 09 4D FFFFFF81 6E
   FFFFFF84 FFFFFF80 FFFFFF80 FFFFFFC2 00 4E 10 08 06 FFFFFF81 47 23 FFFFFF81 72 FFFFFF81 72
   08 07 FFFFFF81 76 1D FFFFFF84 22 FFFFFF81 77 01 07 66 6C 61 74 4D
   61 70 15 04 FFFFFF81 78 FFFFFF81 7B 14 04 FFFFFF81 79 FFFFFF81 7C 10 04
   06 1D FFFFFF81 7A 10 03 24 FFFFFF81 7B 04 09 4D FFFFFF81 75 FFFFFF84 FFFFFF80
   FFFFFF80 FFFFFFC2 00 27 10 06 06 FFFFFF81 1B 23 FFFFFF81 7D 10 04 06 69
   FFFFFF81 7A 08 06 FFFFFF81 7F 1D FFFFFF84 20 45 01 07 72 65 76 65
   72 73 65 08 07 FFFFFF82 01 1D FFFFFF84 00 FFFFFF82 02 01 03 7A 69
   70 15 04 FFFFFF82 03 FFFFFF82 07 14 04 FFFFFF82 04 FFFFFF82 08 10 04 06
   1D FFFFFF82 05 10 06 06 FFFFFF81 15 23 FFFFFF82 06 10 03 24 FFFFFF82 07
   04 09 4D FFFFFF82 00 FFFFFF84 FFFFFF80 FFFFFF80 FFFFFFC2 00 27 10 04 06 1D FFFFFF82
   06 08 07 FFFFFF82 0A 1D FFFFFF84 00 FFFFFF82 0B 01 0C 7A 69 70 57
   69 74 68 49 6E 64 65 78 15 02 FFFFFF82 0C 10 04 06 1D
   FFFFFF82 0D 10 05 06 FFFFFF81 15 23 40 08 07 FFFFFF82 0F 1D FFFFFF84 00
   FFFFFF82 10 01 06 7A 69 70 41 6C 6C 15 08 FFFFFF82 11 FFFFFF82 1C
   FFFFFF82 15 FFFFFF82 18 14 08 FFFFFF82 12 FFFFFF82 1D FFFFFF82 14 FFFFFF82 17 10 04
   06 1D FFFFFF82 13 10 07 06 FFFFFF81 15 FFFFFF82 14 FFFFFF82 17 10 03 24
   FFFFFF82 15 04 0A FFFFFF82 16 FFFFFF82 0E FFFFFF84 FFFFFF80 FFFFFF80 FFFFFFC2 00 4E 02 01
   43 10 03 24 FFFFFF82 18 04 0B FFFFFF82 19 FFFFFF82 0E FFFFFF84 FFFFFF80 FFFFFF80 FFFFFFC2
   00 FFFFFF82 1A 02 01 44 11 03 FFFFFF82 1B 2B 10 03 24 FFFFFF82 1C
   04 09 4D FFFFFF82 0E FFFFFF84 FFFFFF80 FFFFFF80 FFFFFFC2 00 27 10 04 06 1D FFFFFF82
   1B 08 07 FFFFFF82 1F 1D FFFFFF84 00 FFFFFF82 20 01 05 75 6E 69 6F
   6E 15 04 FFFFFF82 21 FFFFFF82 24 14 04 FFFFFF82 22 FFFFFF82 22 10 04 06
   1D FFFFFF82 23 10 03 24 FFFFFF82 24 04 09 4D FFFFFF82 1E FFFFFF84 FFFFFF80 FFFFFF80
   FFFFFFC2 00 4E 08 07 FFFFFF82 26 1D FFFFFF84 00 FFFFFF82 27 01 04 64 69
   66 66 15 04 FFFFFF82 28 FFFFFF82 2B 14 04 FFFFFF82 29 FFFFFF82 29 10 04
   06 1D FFFFFF82 2A 10 03 24 FFFFFF82 2B 04 09 4D FFFFFF82 25 FFFFFF84 FFFFFF80
   FFFFFF80 FFFFFFC2 00 4E 28 03 FFFFFF82 25 57 08 07 FFFFFF82 2E 1D FFFFFF84 00
   FFFFFF82 2F 01 0C 24 6D 69 6E 75 73 24 6D 69 6E 75 73
   15 04 FFFFFF82 30 FFFFFF82 33 14 04 FFFFFF82 31 FFFFFF82 31 10 04 06 1D
   FFFFFF82 32 10 03 24 FFFFFF82 33 04 09 4D FFFFFF82 2D FFFFFF84 FFFFFF80 FFFFFF80 FFFFFFC2
   00 4E 08 07 FFFFFF82 35 1D FFFFFF84 00 FFFFFF82 36 01 06 24 6D 69
   6E 75 73 15 04 FFFFFF82 37 FFFFFF82 3A 14 04 FFFFFF82 38 FFFFFF82 39 10
   04 06 1D FFFFFF82 39 10 03 24 FFFFFF82 3A 04 09 4D FFFFFF82 34 FFFFFF84
   FFFFFF80 FFFFFF80 FFFFFFC2 00 4E 08 07 FFFFFF82 3C 1D FFFFFF84 00 FFFFFF82 3D 01 07
   66 6C 61 74 74 65 6E 15 04 FFFFFF82 3E FFFFFF82 41 16 04 FFFFFF82
   3F FFFFFF82 42 10 04 06 1D FFFFFF82 40 10 03 24 FFFFFF82 41 04 09
   4D FFFFFF82 3B FFFFFF84 FFFFFF80 FFFFFF80 FFFFFFC2 00 27 10 06 06 FFFFFF81 1B 23 FFFFFF82
   43 10 04 06 69 FFFFFF82 40 08 07 FFFFFF82 45 1D FFFFFF84 00 FFFFFF82 46
   01 09 69 6E 74 65 72 73 65 63 74 15 04 FFFFFF82 47 FFFFFF82
   4A 14 04 FFFFFF82 48 FFFFFF82 48 10 04 06 1D FFFFFF82 49 10 03 24
   FFFFFF82 4A 04 09 4D FFFFFF82 44 FFFFFF84 FFFFFF80 FFFFFF80 FFFFFFC2 00 4E 08 06 FFFFFF82
   4C 1D FFFFFF84 00 45 01 10 72 65 6D 6F 76 65 44 75 70
   6C 69 63 61 74 65 73 08 07 FFFFFF82 4E 1D FFFFFF84 28 FFFFFF82 4F
   01 0C 73 74 72 69 6E 67 50 72 65 66 69 78 15 02
   FFFFFF82 50 10 03 0B FFFFFF82 51 09 03 FFFFFF82 52 0C 02 06 53 74
   72 69 6E 67 08 07 FFFFFF82 54 1D FFFFFF84 20 FFFFFF82 55 01 0A 70
   72 6F 6A 65 63 74 69 6F 6E 15 02 FFFFFF82 56 10 04 06
   FFFFFF82 57 23 09 03 FFFFFF82 58 02 02 06 53 74 72 65 61 6D
   08 07 FFFFFF82 5A 1D FFFFFF84 20 FFFFFF82 55 01 08 74 6F 53 74 72
   65 61 6D 29 05 1D FFFFFF82 5C FFFFFF82 5E 0A 03 FFFFFF82 5D 02 01
   03 4E 69 6C 09 03 FFFFFF82 5F 02 02 0C 24 63 6F 6C 6F
   6E 24 63 6F 6C 6F 6E 10 03 24 FFFFFF82 61 04 08 26 18
   FFFFFF84 FFFFFF80 FFFFFF80 FFFFFFC2 00 27 10 05 06 FFFFFF82 63 FFFFFF82 60 09 03 FFFFFF82
   64 02 02 0A 3C 72 65 70 65 61 74 65 64 3E 08 07
   FFFFFF82 66 07 FFFFFF84 00 FFFFFF82 67 01 0A 75 6E 61 70 70 6C 79
   53 65 71 15 04 FFFFFF82 68 FFFFFF82 6E 14 04 FFFFFF82 69 FFFFFF82 6C 10
   05 06 FFFFFF82 6A FFFFFF82 6C 09 03 FFFFFF82 6B 02 02 04 53 6F 6D
   65 10 04 06 1D FFFFFF82 6D 10 03 24 FFFFFF82 6E 04 09 26 FFFFFF82
   65 FFFFFF84 FFFFFF80 FFFFFF80 FFFFFFC2 00 27 08 07 FFFFFF82 70 07 FFFFFF84 00 FFFFFF82 71
   01 05 72 61 6E 67 65 14 03 78 40 40 08 07 FFFFFF82 70
   07 FFFFFF84 00 FFFFFF82 73 14 04 78 40 40 40 08 07 FFFFFF82 70 07
   FFFFFF84 00 FFFFFF82 75 14 05 78 40 40 FFFFFF82 76 10 05 06 FFFFFF81 1B
   40 40 08 07 FFFFFF82 78 07 FFFFFF84 00 FFFFFF82 79 01 04 6D 61 6B
   65 15 04 FFFFFF82 7A FFFFFF82 7D 14 05 FFFFFF82 7B 40 FFFFFF82 7C 10 04
   06 1D FFFFFF82 7C 10 03 24 FFFFFF82 7D 04 09 26 FFFFFF82 77 FFFFFF84 FFFFFF80
   FFFFFF80 FFFFFFC2 00 27 08 07 FFFFFF82 7F 07 FFFFFF84 00 FFFFFF83 00 01 08 74
   61 62 75 6C 61 74 65 15 04 FFFFFF83 01 FFFFFF83 04 14 05 FFFFFF83
   02 40 FFFFFF83 05 10 04 06 1D FFFFFF83 03 10 03 24 FFFFFF83 04 04
   09 26 FFFFFF82 7E FFFFFF84 FFFFFF80 FFFFFF80 FFFFFFC2 00 27 10 06 06 FFFFFF81 1B 40
   FFFFFF83 03 08 07 FFFFFF82 3C 07 FFFFFF84 00 FFFFFF83 07 15 04 FFFFFF83 08 FFFFFF83
   0B 14 04 FFFFFF83 09 FFFFFF83 0C 10 04 06 1D FFFFFF83 0A 10 03 24
   FFFFFF83 0B 04 09 26 FFFFFF83 06 FFFFFF84 FFFFFF80 FFFFFF80 FFFFFFC2 00 27 10 04 06
   1D FFFFFF83 09 08 07 FFFFFF83 0E 07 FFFFFF84 00 FFFFFF83 0F 01 06 63 6F
   6E 63 61 74 15 04 FFFFFF83 10 FFFFFF83 13 14 04 FFFFFF83 11 FFFFFF83 14
   10 04 06 1D FFFFFF83 12 10 03 24 FFFFFF83 13 04 09 26 FFFFFF83 0D
   FFFFFF84 FFFFFF80 FFFFFF80 FFFFFFC2 00 27 10 05 06 FFFFFF82 63 FFFFFF83 11 08 07 FFFFFF83
   16 07 FFFFFF84 00 FFFFFF83 17 01 05 75 6E 7A 69 70 15 06 FFFFFF83
   18 FFFFFF83 1C FFFFFF83 1F 14 04 FFFFFF83 19 FFFFFF83 20 10 07 06 FFFFFF81 15
   FFFFFF83 1A FFFFFF83 1D 10 04 06 1D FFFFFF83 1B 10 03 24 FFFFFF83 1C 04
   09 26 FFFFFF83 15 FFFFFF84 FFFFFF80 FFFFFF80 FFFFFFC2 00 27 10 04 06 1D FFFFFF83 1E
   10 03 24 FFFFFF83 1F 04 09 4D FFFFFF83 15 FFFFFF84 FFFFFF80 FFFFFF80 FFFFFFC2 00 27
   10 04 06 1D FFFFFF83 21 10 07 06 FFFFFF81 15 FFFFFF83 1B FFFFFF83 1E 08
   07 FFFFFF83 16 07 FFFFFF84 00 FFFFFF83 23 15 06 FFFFFF83 24 FFFFFF83 28 FFFFFF83 2B
   14 04 FFFFFF83 25 FFFFFF83 2C 10 07 06 FFFFFF81 15 FFFFFF83 26 FFFFFF83 29 10
   04 06 1D FFFFFF83 27 10 03 24 FFFFFF83 28 04 09 26 FFFFFF83 22 FFFFFF84
   FFFFFF80 FFFFFF80 FFFFFFC2 00 27 10 04 06 1D FFFFFF83 2A 10 03 24 FFFFFF83 2B
   04 09 4D FFFFFF83 22 FFFFFF84 FFFFFF80 FFFFFF80 FFFFFFC2 00 27 10 04 06 69 FFFFFF83
   2D 10 07 06 FFFFFF81 15 FFFFFF83 27 FFFFFF83 2A 08 07 FFFFFF83 2F 07 FFFFFF84
   00 FFFFFF83 30 01 05 6C 65 66 74 73 15 06 FFFFFF83 31 FFFFFF83 34
   FFFFFF83 3A 14 04 FFFFFF83 32 FFFFFF83 35 10 04 06 1D FFFFFF83 33 10 03
   24 FFFFFF83 34 04 09 26 FFFFFF83 2E FFFFFF84 FFFFFF80 FFFFFF80 FFFFFFC2 00 27 10 04
   06 69 FFFFFF83 36 10 07 06 FFFFFF83 37 FFFFFF83 33 FFFFFF83 39 09 03 FFFFFF83
   38 02 02 06 45 69 74 68 65 72 10 03 24 FFFFFF83 3A 04
   09 4D FFFFFF83 2E FFFFFF84 FFFFFF80 FFFFFF80 FFFFFFC2 00 27 08 07 FFFFFF83 3C 07 FFFFFF84
   00 FFFFFF83 3D 01 06 72 69 67 68 74 73 15 06 FFFFFF83 3E FFFFFF83
   45 FFFFFF83 41 14 04 FFFFFF83 3F FFFFFF83 42 10 04 06 1D FFFFFF83 40 10
   03 24 FFFFFF83 41 04 09 4D FFFFFF83 3B FFFFFF84 FFFFFF80 FFFFFF80 FFFFFFC2 00 27 10
   04 06 69 FFFFFF83 43 10 07 06 FFFFFF83 37 FFFFFF83 44 FFFFFF83 40 10 03
   24 FFFFFF83 45 04 09 26 FFFFFF83 3B FFFFFF84 FFFFFF80 FFFFFF80 FFFFFFC2 00 27 08 07
   FFFFFF83 47 07 FFFFFF84 00 FFFFFF83 48 01 08 73 65 70 61 72 61 74
   65 15 06 FFFFFF83 49 FFFFFF83 4D FFFFFF83 50 14 04 FFFFFF83 4A FFFFFF83 51 10
   07 06 FFFFFF81 15 FFFFFF83 4B FFFFFF83 4E 10 04 06 1D FFFFFF83 4C 10 03
   24 FFFFFF83 4D 04 09 26 FFFFFF83 46 FFFFFF84 FFFFFF80 FFFFFF80 FFFFFFC2 00 27 10 04
   06 1D FFFFFF83 4F 10 03 24 FFFFFF83 50 04 09 4D FFFFFF83 46 FFFFFF84 FFFFFF80
   FFFFFF80 FFFFFFC2 00 27 10 04 06 69 FFFFFF83 52 10 07 06 FFFFFF83 37 FFFFFF83
   4C FFFFFF83 4F 08 07 FFFFFF83 54 07 FFFFFF84 00 FFFFFF83 55 01 0C 66 72
   6F 6D 49 74 65 72 61 74 6F 72 15 04 FFFFFF83 56 FFFFFF83 59
   14 04 FFFFFF83 57 FFFFFF83 5A 10 04 06 1D FFFFFF83 58 10 03 24 FFFFFF83
   59 04 09 26 FFFFFF83 53 FFFFFF84 FFFFFF80 FFFFFF80 FFFFFFC2 00 27 10 04 06 7D
   FFFFFF83 58 08 07 FFFFFF83 5C 07 FFFFFF84 00 FFFFFF83 5D 01 09 66 72 6F
   6D 41 72 72 61 79 15 04 FFFFFF83 5E FFFFFF83 61 14 04 FFFFFF83 5F
   FFFFFF83 62 10 04 06 1D FFFFFF83 60 10 03 24 FFFFFF83 61 04 09 26
   FFFFFF83 5B FFFFFF84 FFFFFF80 FFFFFF80 FFFFFFC2 00 27 10 05 06 FFFFFF83 63 FFFFFF83 60 09
   03 FFFFFF83 64 02 02 05 41 72 72 61 79 08 07 FFFFFF83 5C 07
   FFFFFF84 00 FFFFFF83 66 15 04 FFFFFF83 67 FFFFFF83 6A 14 06 FFFFFF83 68 FFFFFF83 6B
   40 40 10 04 06 1D FFFFFF83 69 10 03 24 FFFFFF83 6A 04 09 26
   FFFFFF83 65 FFFFFF84 FFFFFF80 FFFFFF80 FFFFFFC2 00 27 10 05 06 FFFFFF83 63 FFFFFF83 69 08
   07 FFFFFF83 6D 07 FFFFFF84 00 FFFFFF83 6E 01 0A 66 72 6F 6D 53 74
   72 69 6E 67 14 06 FFFFFF83 6F FFFFFF83 70 FFFFFF83 76 10 04 06 1D
   FFFFFF83 70 10 04 FFFFFF83 71 FFFFFF83 74 0E 03 06 FFFFFF83 72 09 03 FFFFFF83
   73 02 01 06 50 72 65 64 65 66 09 04 FFFFFF82 52 FFFFFF83 75
   0A 03 FFFFFF83 73 02 10 03 06 FFFFFF83 77 09 03 FFFFFF83 78 02 02
   04 43 68 61 72 08 07 FFFFFF83 6D 07 FFFFFF84 00 FFFFFF83 7A 14 04
   FFFFFF83 7B FFFFFF83 70 10 04 06 1D FFFFFF83 76 28 03 FFFFFF83 79 57 08
   07 FFFFFF83 7E 07 FFFFFF84 00 FFFFFF83 7F 01 08 74 6F 53 74 72 69
   6E 67 14 04 FFFFFF83 70 FFFFFF83 7B 08 07 FFFFFF84 01 07 FFFFFF84 00 FFFFFF84
   02 01 0B 6D 61 70 43 6F 6E 73 65 72 76 65 15 04
   FFFFFF84 03 FFFFFF84 07 14 04 FFFFFF84 04 FFFFFF84 05 14 04 FFFFFF84 05 FFFFFF84 0C
   10 04 06 1D FFFFFF84 06 10 03 24 FFFFFF84 07 04 0A 26 FFFFFF84 00
   FFFFFF84 FFFFFF80 FFFFFF80 FFFFFFC2 00 FFFFFF84 08 11 03 28 FFFFFF84 09 10 03 06 FFFFFF84
   0A 09 03 FFFFFF84 0B 02 02 06 41 6E 79 52 65 66 10 07
   06 FFFFFF81 1B FFFFFF84 06 FFFFFF84 06 08 07 FFFFFF84 0E 07 FFFFFF84 00 FFFFFF84 0F
   01 04 6D 61 70 32 15 08 FFFFFF84 10 FFFFFF84 17 FFFFFF84 19 FFFFFF84 14
   14 06 FFFFFF84 11 FFFFFF84 1A FFFFFF84 1B 14 04 FFFFFF84 12 FFFFFF84 15 10 04
   06 1D FFFFFF84 13 10 03 24 FFFFFF84 14 04 0A FFFFFF82 16 FFFFFF84 0D FFFFFF84
   FFFFFF80 FFFFFF80 FFFFFFC2 00 27 10 09 06 FFFFFF81 47 FFFFFF84 16 FFFFFF84 18 FFFFFF84 13
   10 03 24 FFFFFF84 17 04 09 26 FFFFFF84 0D FFFFFF84 FFFFFF80 FFFFFF80 FFFFFFC2 00 27
   10 03 24 FFFFFF84 19 04 09 4D FFFFFF84 0D FFFFFF84 FFFFFF80 FFFFFF80 FFFFFFC2 00 27
   10 04 06 1D FFFFFF84 16 10 04 06 1D FFFFFF84 18 08 07 FFFFFF84 1D
   07 FFFFFF84 00 FFFFFF84 1E 01 04 6D 61 70 33 15 0A FFFFFF84 1F FFFFFF84
   28 FFFFFF84 2A FFFFFF84 2C FFFFFF84 23 14 08 FFFFFF84 20 FFFFFF84 2D FFFFFF84 2E FFFFFF84
   2F 14 04 FFFFFF84 21 FFFFFF84 24 10 04 06 1D FFFFFF84 22 10 03 24
   FFFFFF84 23 04 0A FFFFFF82 19 FFFFFF84 1C FFFFFF84 FFFFFF80 FFFFFF80 FFFFFFC2 00 27 10 0B
   06 FFFFFF84 25 FFFFFF84 27 FFFFFF84 29 FFFFFF84 2B FFFFFF84 22 09 03 FFFFFF84 26 02
   02 09 46 75 6E 63 74 69 6F 6E 33 10 03 24 FFFFFF84 28
   04 09 26 FFFFFF84 1C FFFFFF84 FFFFFF80 FFFFFF80 FFFFFFC2 00 27 10 03 24 FFFFFF84 2A
   04 09 4D FFFFFF84 1C FFFFFF84 FFFFFF80 FFFFFF80 FFFFFFC2 00 27 10 03 24 FFFFFF84 2C
   04 0A FFFFFF82 16 FFFFFF84 1C FFFFFF84 FFFFFF80 FFFFFF80 FFFFFFC2 00 27 10 04 06 1D
   FFFFFF84 27 10 04 06 1D FFFFFF84 29 10 04 06 1D FFFFFF84 2B 08 07
   FFFFFF84 31 07 FFFFFF84 00 FFFFFF84 32 01 07 66 6F 72 61 6C 6C 32
   15 06 FFFFFF84 33 FFFFFF84 37 FFFFFF84 39 14 06 FFFFFF84 34 FFFFFF84 3A FFFFFF84 3B
   14 03 37 FFFFFF84 35 10 08 06 FFFFFF81 47 FFFFFF84 36 FFFFFF84 38 37 10
   03 24 FFFFFF84 37 04 09 26 FFFFFF84 30 FFFFFF84 FFFFFF80 FFFFFF80 FFFFFFC2 00 27 10
   03 24 FFFFFF84 39 04 09 4D FFFFFF84 30 FFFFFF84 FFFFFF80 FFFFFF80 FFFFFFC2 00 27 10
   04 06 1D FFFFFF84 36 10 04 06 1D FFFFFF84 38 08 07 FFFFFF84 3D 07
   FFFFFF84 00 FFFFFF84 3E 01 07 65 78 69 73 74 73 32 15 06 FFFFFF84
   3F FFFFFF84 43 FFFFFF84 45 14 06 FFFFFF84 40 FFFFFF84 46 FFFFFF84 47 14 03 37
   FFFFFF84 41 10 08 06 FFFFFF81 47 FFFFFF84 42 FFFFFF84 44 37 10 03 24 FFFFFF84
   43 04 09 26 FFFFFF84 3C FFFFFF84 FFFFFF80 FFFFFF80 FFFFFFC2 00 27 10 03 24 FFFFFF84
   45 04 09 4D FFFFFF84 3C FFFFFF84 FFFFFF80 FFFFFF80 FFFFFFC2 00 27 10 04 06 1D
   FFFFFF84 42 10 04 06 1D FFFFFF84 44 08 07 FFFFFF84 49 07 FFFFFF84 00 FFFFFF84
   4A 01 09 74 72 61 6E 73 70 6F 73 65 15 04 FFFFFF84 4B
   FFFFFF84 4F 14 04 FFFFFF84 4C FFFFFF84 4C 10 04 06 1D FFFFFF84 4D 10 04
   06 1D FFFFFF84 4E 10 03 24 FFFFFF84 4F 04 09 26 FFFFFF84 48 FFFFFF84 FFFFFF80
   FFFFFF80 FFFFFFC2 00 27 
  Signature: length = 0x2
   00 6A 
  SourceFile: "List.scala"
  minor version: 0
  major version: 49
  Constant pool:
String	List
class	java/lang/Object
class	scala/$colon$colon
class	scala/Collection$class
class	scala/Function1
class	scala/Function1$class
class	scala/Iterable
class	scala/Iterable$class
class	scala/List
class	scala/List$$anon$2
class	scala/PartialFunction$class
class	scala/Product
class	scala/Product$class
class	scala/Seq
class	scala/Seq$class
class	scala/collection/mutable/ListBuffer
class	scala/runtime/BoxesRunTime
Method	java/lang/Object."<init>":()V
Method	scala/$colon$colon."<init>":(Ljava/lang/Object;Lscala/List;)V
Method	scala/Collection$class.$init$:(Lscala/Collection;)V
Method	scala/Collection$class.toString:(Lscala/Collection;)Ljava/lang/String;
Method	scala/Function1$class.$init$:(Lscala/Function1;)V
Method	scala/Iterable$class.$init$:(Lscala/Iterable;)V
Method	scala/Iterable$class.addString:(Lscala/Iterable;Lscala/StringBuilder;Ljava/lang/String;Ljava/lang/String;Ljava/lang/String;)Lscala/StringBuilder;
Method	scala/Iterable$class.mkString:(Lscala/Iterable;Ljava/lang/String;Ljava/lang/String;Ljava/lang/String;)Ljava/lang/String;
Method	scala/List.apply:(I)Ljava/lang/Object;
Method	scala/List.drop:(I)Lscala/List;
Method	scala/List.head:()Ljava/lang/Object;
Method	scala/List.tail:()Lscala/List;
Method	scala/List$$anon$2."<init>":(Lscala/List;)V
Method	scala/PartialFunction$class.$init$:(Lscala/PartialFunction;)V
Method	scala/Product$class.$init$:(Lscala/Product;)V
Method	scala/Product$class.productPrefix:(Lscala/Product;)Ljava/lang/String;
Method	scala/Seq$class.$init$:(Lscala/Seq;)V
Method	scala/collection/mutable/ListBuffer.$plus$eq:(Ljava/lang/Object;)V
Method	scala/collection/mutable/ListBuffer."<init>":()V
Method	scala/collection/mutable/ListBuffer.toList:()Lscala/List;
Method	scala/runtime/BoxesRunTime.unboxToBoolean:(Ljava/lang/Object;)Z
Method	scala/runtime/BoxesRunTime.unboxToInt:(Ljava/lang/Object;)I
InterfaceMethod	scala/Function1.apply:(Ljava/lang/Object;)Ljava/lang/Object;
InterfaceMethod	scala/Seq.isEmpty:()Z
NameAndType	$init$:(Lscala/Collection;)V
NameAndType	$init$:(Lscala/Function1;)V
NameAndType	$init$:(Lscala/Iterable;)V
NameAndType	$init$:(Lscala/PartialFunction;)V
NameAndType	$init$:(Lscala/Product;)V
NameAndType	$init$:(Lscala/Seq;)V
NameAndType	$plus$eq:(Ljava/lang/Object;)V
NameAndType	"<init>":()V
NameAndType	"<init>":(Ljava/lang/Object;Lscala/List;)V
NameAndType	"<init>":(Lscala/List;)V
NameAndType	addString:(Lscala/Iterable;Lscala/StringBuilder;Ljava/lang/String;Ljava/lang/String;Ljava/lang/String;)Lscala/StringBuilder;
NameAndType	apply:(I)Ljava/lang/Object;
NameAndType	apply:(Ljava/lang/Object;)Ljava/lang/Object;
NameAndType	drop:(I)Lscala/List;
NameAndType	head:()Ljava/lang/Object;
NameAndType	isEmpty:()Z
NameAndType	mkString:(Lscala/Iterable;Ljava/lang/String;Ljava/lang/String;Ljava/lang/String;)Ljava/lang/String;
NameAndType	productPrefix:(Lscala/Product;)Ljava/lang/String;
NameAndType	tail:()Lscala/List;
NameAndType	toList:()Lscala/List;
NameAndType	toString:(Lscala/Collection;)Ljava/lang/String;
NameAndType	unboxToBoolean:(Ljava/lang/Object;)Z
NameAndType	unboxToInt:(Ljava/lang/Object;)I
Asciz	$anon$2;
Asciz	$colon$colon;
Asciz	$init$;
Asciz	$plus$eq;
Asciz	()I;
Asciz	()Ljava/lang/Object;;
Asciz	()Ljava/lang/String;;
Asciz	()Lscala/Iterator;;
Asciz	()Lscala/Iterator<TA;>;;
Asciz	()Lscala/List;;
Asciz	()Lscala/List<TA;>;;
Asciz	()TA;;
Asciz	()V;
Asciz	()Z;
Asciz	(I)Ljava/lang/Object;;
Asciz	(I)Lscala/List;;
Asciz	(I)Lscala/List<TA;>;;
Asciz	(I)TA;;
Asciz	(Ljava/lang/Object;)I;
Asciz	(Ljava/lang/Object;)Ljava/lang/Object;;
Asciz	(Ljava/lang/Object;)Lscala/List;;
Asciz	(Ljava/lang/Object;)V;
Asciz	(Ljava/lang/Object;)Z;
Asciz	(Ljava/lang/Object;Lscala/List;)V;
Asciz	(Ljava/lang/String;Ljava/lang/String;Ljava/lang/String;)Ljava/lang/String;;
Asciz	(Lscala/Collection;)Ljava/lang/String;;
Asciz	(Lscala/Collection;)V;
Asciz	(Lscala/Function1;)I;
Asciz	(Lscala/Function1;)Lscala/List;;
Asciz	(Lscala/Function1;)V;
Asciz	(Lscala/Function1<TA;Ljava/lang/Boolean;>;)I;
Asciz	(Lscala/Function1<TA;Ljava/lang/Boolean;>;)Lscala/List<TA;>;;
Asciz	(Lscala/Iterable;)V;
Asciz	(Lscala/Iterable;Ljava/lang/String;Ljava/lang/String;Ljava/lang/String;)Ljava/lang/String;;
Asciz	(Lscala/Iterable;Lscala/StringBuilder;Ljava/lang/String;Ljava/lang/String;Ljava/lang/String;)Lscala/StringBuilder;;
Asciz	(Lscala/List;)V;
Asciz	(Lscala/PartialFunction;)V;
Asciz	(Lscala/Product;)Ljava/lang/String;;
Asciz	(Lscala/Product;)V;
Asciz	(Lscala/Seq;)V;
Asciz	(Lscala/StringBuilder;Ljava/lang/String;Ljava/lang/String;Ljava/lang/String;)Lscala/StringBuilder;;
Asciz	<A:Ljava/lang/Object;>Ljava/lang/Object;Lscala/Seq<TA;>;Lscala/Product;;
Asciz	<B:Ljava/lang/Object;>(TB;)Lscala/List<TB;>;;
Asciz	<init>;
Asciz	Code;
Asciz	I;
Asciz	InnerClasses;
Asciz	LineNumberTable;
Asciz	List;
Asciz	List.scala;
Asciz	Ljava/lang/Object;;
Asciz	Ljava/lang/String;;
Asciz	LocalVariableTable;
Asciz	Lscala/Function1;;
Asciz	Lscala/List;;
Asciz	Lscala/StringBuilder;;
Asciz	Lscala/collection/mutable/ListBuffer;;
Asciz	ScalaSig;
Asciz	Signature;
Asciz	SourceFile;
Asciz	addString;
Asciz	apply;
Asciz	b;
Asciz	cnt;
Asciz	count;
Asciz	drop;
Asciz	elements;
Asciz	filter;
Asciz	head;
Asciz	isEmpty;
Asciz	java/lang/Object;
Asciz	len;
Asciz	length;
Asciz	mkString;
Asciz	n;
Asciz	p;
Asciz	productPrefix;
Asciz	scala/$colon$colon;
Asciz	scala/Collection$class;
Asciz	scala/Function1;
Asciz	scala/Function1$class;
Asciz	scala/Iterable;
Asciz	scala/Iterable$class;
Asciz	scala/List;
Asciz	scala/List$$anon$2;
Asciz	scala/PartialFunction$class;
Asciz	scala/Product;
Asciz	scala/Product$class;
Asciz	scala/Seq;
Asciz	scala/Seq$class;
Asciz	scala/collection/mutable/ListBuffer;
Asciz	scala/runtime/BoxesRunTime;
Asciz	stringPrefix;
Asciz	tail;
Asciz	these;
Asciz	these1;
Asciz	this;
Asciz	toList;
Asciz	toString;
Asciz	unboxToBoolean;
Asciz	unboxToInt;
Asciz	x;
Asciz	x$1;
Asciz	x$2;
Asciz	x$3;
Asciz	x$4;

{
public scala.List();
  Signature: ()V
  Code:
   Stack=1, Locals=1, Args_size=1
	aload_0
	invokespecial	Method java/lang/Object."<init>":()V
	aload_0
	invokestatic	Method scala/Function1$class.$init$:(Lscala/Function1;)V
	aload_0
	invokestatic	Method scala/PartialFunction$class.$init$:(Lscala/PartialFunction;)V
	aload_0
	invokestatic	Method scala/Iterable$class.$init$:(Lscala/Iterable;)V
	aload_0
	invokestatic	Method scala/Collection$class.$init$:(Lscala/Collection;)V
	aload_0
	invokestatic	Method scala/Seq$class.$init$:(Lscala/Seq;)V
	aload_0
	invokestatic	Method scala/Product$class.$init$:(Lscala/Product;)V
	return
  Labels:
  Signature: length = 0x2
   00 4D 

public java.lang.Object apply(java.lang.Object);
  Signature: (Ljava/lang/Object;)Ljava/lang/Object;
  Code:
   Stack=2, Locals=2, Args_size=2
	aload_0
	aload_1
	invokestatic	Method scala/runtime/BoxesRunTime.unboxToInt:(Ljava/lang/Object;)I
	invokevirtual	Method apply:(I)Ljava/lang/Object;
	areturn
  Labels:
  LocalVariableTable: 
   Start  Length  Slot  Name   Signature
   0      9      0    this       Lscala/List;
   0      9      1    x$1       Ljava/lang/Object;


public java.lang.String stringPrefix();
  Signature: ()Ljava/lang/String;
  Code:
   Stack=1, Locals=1, Args_size=1
	ldc	String List
	areturn
  Labels:

public int count(scala.Function1);
  Signature: (Lscala/Function1;)I
  Code:
   Stack=2, Locals=4, Args_size=2
	iconst_0
	istore_2
	aload_0
	astore_3
l3	aload_3
	invokeinterface	InterfaceMethod scala/Seq.isEmpty:()Z
	ifeq	l1 // aload_1
	iload_2
	ireturn
l1	aload_1
	aload_3
	invokevirtual	Method head:()Ljava/lang/Object;
	invokeinterface	InterfaceMethod scala/Function1.apply:(Ljava/lang/Object;)Ljava/lang/Object;
	invokestatic	Method scala/runtime/BoxesRunTime.unboxToBoolean:(Ljava/lang/Object;)Z
	ifeq	l2 // aload_3
	iload_2
	iconst_1
	iadd
	istore_2
l2	aload_3
	invokevirtual	Method tail:()Lscala/List;
	astore_3
	goto	l3 // aload_3
  Labels:
   	l3 = 4 // aload_3
   	l1 = 15 // aload_1
   	l2 = 35 // aload_3
  LocalVariableTable: 
   Start  Length  Slot  Name   Signature
   0      43      0    this       Lscala/List;
   0      43      1    p       Lscala/Function1;
   0      14      2    cnt       I
   15      28      2    cnt       I
   2      12      3    these       Lscala/List;
   15      28      3    these       Lscala/List;

  Signature: length = 0x2
   00 5F 

public final scala.List filter(scala.Function1);
  Signature: (Lscala/Function1;)Lscala/List;
  Code:
   Stack=2, Locals=5, Args_size=2
	aload_0
	astore_2
l2	aload_2
	invokeinterface	InterfaceMethod scala/Seq.isEmpty:()Z
	ifne	l1 // aload_2
	aload_1
	aload_2
	invokevirtual	Method head:()Ljava/lang/Object;
	invokeinterface	InterfaceMethod scala/Function1.apply:(Ljava/lang/Object;)Ljava/lang/Object;
	invokestatic	Method scala/runtime/BoxesRunTime.unboxToBoolean:(Ljava/lang/Object;)Z
	ifeq	l1 // aload_2
	aload_2
	invokevirtual	Method tail:()Lscala/List;
	astore_2
	goto	l2 // aload_2
l1	aload_2
	invokeinterface	InterfaceMethod scala/Seq.isEmpty:()Z
	ifeq	l3 // new
	aload_0
	goto	l4 // areturn
l3	new	class scala/collection/mutable/ListBuffer
	dup
	invokespecial	Method scala/collection/mutable/ListBuffer."<init>":()V
	astore_3
	aload_0
	astore	4
l6	aload	4
	aload_2
	if_acmpeq	l5 // aload_2
	aload_3
	aload	4
	invokevirtual	Method head:()Ljava/lang/Object;
	invokevirtual	Method scala/collection/mutable/ListBuffer.$plus$eq:(Ljava/lang/Object;)V
	aload	4
	invokevirtual	Method tail:()Lscala/List;
	astore	4
	goto	l6 // aload
l5	aload_2
	invokevirtual	Method tail:()Lscala/List;
	astore_2
l9	aload_2
	invokeinterface	InterfaceMethod scala/Seq.isEmpty:()Z
	ifeq	l7 // aload_1
	aload_3
	invokevirtual	Method scala/collection/mutable/ListBuffer.toList:()Lscala/List;
l4	areturn
l7	aload_1
	aload_2
	invokevirtual	Method head:()Ljava/lang/Object;
	invokeinterface	InterfaceMethod scala/Function1.apply:(Ljava/lang/Object;)Ljava/lang/Object;
	invokestatic	Method scala/runtime/BoxesRunTime.unboxToBoolean:(Ljava/lang/Object;)Z
	ifeq	l8 // aload_2
	aload_3
	aload_2
	invokevirtual	Method head:()Ljava/lang/Object;
	invokevirtual	Method scala/collection/mutable/ListBuffer.$plus$eq:(Ljava/lang/Object;)V
l8	aload_2
	invokevirtual	Method tail:()Lscala/List;
	astore_2
	goto	l9 // aload_2
  Labels:
   	l2 = 2 // aload_2
   	l1 = 35 // aload_2
   	l3 = 48 // new
   	l6 = 59 // aload
   	l5 = 84 // aload_2
   	l9 = 89 // aload_2
   	l4 = 102 // areturn
   	l7 = 103 // aload_1
   	l8 = 127 // aload_2
  LocalVariableTable: 
   Start  Length  Slot  Name   Signature
   0      135      0    this       Lscala/List;
   0      135      1    p       Lscala/Function1;
   0      135      2    these       Lscala/List;
   48      54      3    b       Lscala/collection/mutable/ListBuffer;
   103      32      3    b       Lscala/collection/mutable/ListBuffer;
   56      46      4    these1       Lscala/List;
   103      32      4    these1       Lscala/List;

  Signature: length = 0x2
   00 60 

public java.lang.Object apply(int);
  Signature: (I)Ljava/lang/Object;
  Code:
   Stack=2, Locals=2, Args_size=2
	aload_0
	iload_1
	invokevirtual	Method drop:(I)Lscala/List;
	invokevirtual	Method head:()Ljava/lang/Object;
	areturn
  Labels:
  LocalVariableTable: 
   Start  Length  Slot  Name   Signature
   0      9      0    this       Lscala/List;
   0      9      1    n       I

  Signature: length = 0x2
   00 52 

public scala.List drop(int);
  Signature: (I)Lscala/List;
  Code:
   Stack=2, Locals=4, Args_size=2
	aload_0
	astore_2
	iload_1
	istore_3
l2	aload_2
	invokeinterface	InterfaceMethod scala/Seq.isEmpty:()Z
	ifne	l1 // aload_2
	iload_3
	iconst_0
	if_icmple	l1 // aload_2
	aload_2
	invokevirtual	Method tail:()Lscala/List;
	astore_2
	iload_3
	iconst_1
	isub
	istore_3
	goto	l2 // aload_2
l1	aload_2
	areturn
  Labels:
   	l2 = 4 // aload_2
   	l1 = 30 // aload_2
  LocalVariableTable: 
   Start  Length  Slot  Name   Signature
   0      32      0    this       Lscala/List;
   0      32      1    n       I
   0      31      2    these       Lscala/List;
   2      29      3    count       I

  Signature: length = 0x2
   00 51 

public scala.Iterator elements();
  Signature: ()Lscala/Iterator;
  Code:
   Stack=3, Locals=1, Args_size=1
	new	class scala/List$$anon$2
	dup
	aload_0
	invokespecial	Method scala/List$$anon$2."<init>":(Lscala/List;)V
	areturn
  Labels:
  Signature: length = 0x2
   00 49 

public int length();
  Signature: ()I
  Code:
   Stack=2, Locals=3, Args_size=1
	aload_0
	astore_1
	iconst_0
	istore_2
l2	aload_1
	invokeinterface	InterfaceMethod scala/Seq.isEmpty:()Z
	ifeq	l1 // iload_2
	iload_2
	ireturn
l1	iload_2
	iconst_1
	iadd
	istore_2
	aload_1
	invokevirtual	Method tail:()Lscala/List;
	astore_1
	goto	l2 // aload_1
  Labels:
   	l2 = 4 // aload_1
   	l1 = 15 // iload_2
  LocalVariableTable: 
   Start  Length  Slot  Name   Signature
   0      27      0    this       Lscala/List;
   0      14      1    these       Lscala/List;
   15      12      1    these       Lscala/List;
   2      12      2    len       I
   15      12      2    len       I


public scala.List $colon$colon(java.lang.Object);
  Signature: (Ljava/lang/Object;)Lscala/List;
  Code:
   Stack=4, Locals=2, Args_size=2
	new	class scala/$colon$colon
	dup
	aload_1
	aload_0
	invokespecial	Method scala/$colon$colon."<init>":(Ljava/lang/Object;Lscala/List;)V
	areturn
  Labels:
  LocalVariableTable: 
   Start  Length  Slot  Name   Signature
   0      10      0    this       Lscala/List;
   0      10      1    x       Ljava/lang/Object;

  Signature: length = 0x2
   00 6B 

public abstract scala.List tail();
  Signature: ()Lscala/List;
  Signature: length = 0x2
   00 4B 

public abstract java.lang.Object head();
  Signature: ()Ljava/lang/Object;
  Signature: length = 0x2
   00 4C 

public scala.StringBuilder addString(scala.StringBuilder, java.lang.String, java.lang.String, java.lang.String);
  Signature: (Lscala/StringBuilder;Ljava/lang/String;Ljava/lang/String;Ljava/lang/String;)Lscala/StringBuilder;
  Code:
   Stack=5, Locals=5, Args_size=5
	aload_0
	aload_1
	aload_2
	aload_3
	aload	4
	invokestatic	Method scala/Iterable$class.addString:(Lscala/Iterable;Lscala/StringBuilder;Ljava/lang/String;Ljava/lang/String;Ljava/lang/String;)Lscala/StringBuilder;
	areturn
  Labels:
  LocalVariableTable: 
   Start  Length  Slot  Name   Signature
   0      10      0    this       Lscala/List;
   0      10      1    x$1       Lscala/StringBuilder;
   0      10      2    x$2       Ljava/lang/String;
   0      10      3    x$3       Ljava/lang/String;
   0      10      4    x$4       Ljava/lang/String;


public java.lang.String mkString(java.lang.String, java.lang.String, java.lang.String);
  Signature: (Ljava/lang/String;Ljava/lang/String;Ljava/lang/String;)Ljava/lang/String;
  Code:
   Stack=4, Locals=4, Args_size=4
	aload_0
	aload_1
	aload_2
	aload_3
	invokestatic	Method scala/Iterable$class.mkString:(Lscala/Iterable;Ljava/lang/String;Ljava/lang/String;Ljava/lang/String;)Ljava/lang/String;
	areturn
  Labels:
  LocalVariableTable: 
   Start  Length  Slot  Name   Signature
   0      8      0    this       Lscala/List;
   0      8      1    x$1       Ljava/lang/String;
   0      8      2    x$2       Ljava/lang/String;
   0      8      3    x$3       Ljava/lang/String;


public java.lang.String toString();
  Signature: ()Ljava/lang/String;
  Code:
   Stack=1, Locals=1, Args_size=1
	aload_0
	invokestatic	Method scala/Collection$class.toString:(Lscala/Collection;)Ljava/lang/String;
	areturn
  Labels:

public java.lang.String productPrefix();
  Signature: ()Ljava/lang/String;
  Code:
   Stack=1, Locals=1, Args_size=1
	aload_0
	invokestatic	Method scala/Product$class.productPrefix:(Lscala/Product;)Ljava/lang/String;
	areturn
  Labels:

}

