Compiled from "LowPriorityImplicits.scala"
public final class scala.LowPriorityImplicits$$anon$1 extends java.lang.Object implements scala.collection.generic.CanBuildFrom
  SourceFile: "LowPriorityImplicits.scala"
  Signature: length = 0x2
   00 2A 
  Scala: length = 0x
   
  InnerClass: 
   public final #47= #22 of #46; //$anon$1=class scala/LowPriorityImplicits$$anon$1 of class scala/LowPriorityImplicits
  minor version: 0
  major version: 49
  Constant pool:
const #1 = Asciz	SourceFile;
const #2 = Asciz	LowPriorityImplicits.scala;
const #3 = Asciz	<init>;
const #4 = Asciz	(Lscala/LowPriorityImplicits;)V;
const #5 = Asciz	Code;
const #6 = Asciz	LineNumberTable;
const #7 = Asciz	java/lang/Object;
const #8 = class	#7;	//  java/lang/Object
const #9 = Asciz	()V;
const #10 = NameAndType	#3:#9;//  "<init>":()V
const #11 = Method	#8.#10;	//  java/lang/Object."<init>":()V
const #12 = Asciz	this;
const #13 = Asciz	Lscala/LowPriorityImplicits$$anon$1;;
const #14 = Asciz	$outer;
const #15 = Asciz	Lscala/LowPriorityImplicits;;
const #16 = Asciz	LocalVariableTable;
const #17 = Asciz	apply;
const #18 = Asciz	(Ljava/lang/Object;)Lscala/collection/mutable/Builder;;
const #19 = Asciz	java/lang/String;
const #20 = class	#19;	//  java/lang/String
const #21 = Asciz	scala/LowPriorityImplicits$$anon$1;
const #22 = class	#21;	//  scala/LowPriorityImplicits$$anon$1
const #23 = Asciz	(Ljava/lang/String;)Lscala/collection/mutable/Builder;;
const #24 = NameAndType	#17:#23;//  apply:(Ljava/lang/String;)Lscala/collection/mutable/Builder;
const #25 = Method	#22.#24;	//  scala/LowPriorityImplicits$$anon$1.apply:(Ljava/lang/String;)Lscala/collection/mutable/Builder;
const #26 = Asciz	from;
const #27 = Asciz	Ljava/lang/Object;;
const #28 = Asciz	()Lscala/collection/mutable/Builder;;
const #29 = Asciz	scala/collection/immutable/IndexedSeq$;
const #30 = class	#29;	//  scala/collection/immutable/IndexedSeq$
const #31 = Asciz	MODULE$;
const #32 = Asciz	Lscala/collection/immutable/IndexedSeq$;;
const #33 = NameAndType	#31:#32;//  MODULE$:Lscala/collection/immutable/IndexedSeq$;
const #34 = Field	#30.#33;	//  scala/collection/immutable/IndexedSeq$.MODULE$:Lscala/collection/immutable/IndexedSeq$;
const #35 = Asciz	newBuilder;
const #36 = NameAndType	#35:#28;//  newBuilder:()Lscala/collection/mutable/Builder;
const #37 = Method	#30.#36;	//  scala/collection/immutable/IndexedSeq$.newBuilder:()Lscala/collection/mutable/Builder;
const #38 = Asciz	()Lscala/collection/mutable/Builder<TT;Lscala/collection/immutable/IndexedSeq<TT;>;>;;
const #39 = Asciz	Signature;
const #40 = Asciz	Ljava/lang/String;;
const #41 = Asciz	(Ljava/lang/String;)Lscala/collection/mutable/Builder<TT;Lscala/collection/immutable/IndexedSeq<TT;>;>;;
const #42 = Asciz	Ljava/lang/Object;Lscala/collection/generic/CanBuildFrom<Ljava/lang/String;TT;Lscala/collection/immutable/IndexedSeq<TT;>;>;;
const #43 = Asciz	Scala;
const #44 = Asciz	InnerClasses;
const #45 = Asciz	scala/LowPriorityImplicits;
const #46 = class	#45;	//  scala/LowPriorityImplicits
const #47 = Asciz	$anon$1;
const #48 = Asciz	scala/collection/generic/CanBuildFrom;
const #49 = class	#48;	//  scala/collection/generic/CanBuildFrom

{
public scala.LowPriorityImplicits$$anon$1(scala.LowPriorityImplicits);
  Code:
   Stack=1, Locals=2, Args_size=2
   0:	aload_0
   1:	invokespecial	#11; //Method java/lang/Object."<init>":()V
   4:	return
  LineNumberTable: 
   line 46: 0

  LocalVariableTable: 
   Start  Length  Slot  Name   Signature
   0      5      0    this       Lscala/LowPriorityImplicits$$anon$1;
   0      5      1    $outer       Lscala/LowPriorityImplicits;


public scala.collection.mutable.Builder apply(java.lang.Object);
  Code:
   Stack=2, Locals=2, Args_size=2
   0:	aload_0
   1:	aload_1
   2:	checkcast	#20; //class java/lang/String
   5:	invokevirtual	#25; //Method apply:(Ljava/lang/String;)Lscala/collection/mutable/Builder;
   8:	areturn
  LineNumberTable: 
   line 46: 0

  LocalVariableTable: 
   Start  Length  Slot  Name   Signature
   0      9      0    this       Lscala/LowPriorityImplicits$$anon$1;
   0      9      1    from       Ljava/lang/Object;


public scala.collection.mutable.Builder apply();
  Code:
   Stack=1, Locals=1, Args_size=1
   0:	getstatic	#34; //Field scala/collection/immutable/IndexedSeq$.MODULE$:Lscala/collection/immutable/IndexedSeq$;
   3:	invokevirtual	#37; //Method scala/collection/immutable/IndexedSeq$.newBuilder:()Lscala/collection/mutable/Builder;
   6:	areturn
  LineNumberTable: 
   line 48: 0

  Signature: length = 0x2
   00 26 

public scala.collection.mutable.Builder apply(java.lang.String);
  Code:
   Stack=1, Locals=2, Args_size=2
   0:	getstatic	#34; //Field scala/collection/immutable/IndexedSeq$.MODULE$:Lscala/collection/immutable/IndexedSeq$;
   3:	invokevirtual	#37; //Method scala/collection/immutable/IndexedSeq$.newBuilder:()Lscala/collection/mutable/Builder;
   6:	areturn
  LineNumberTable: 
   line 47: 0

  LocalVariableTable: 
   Start  Length  Slot  Name   Signature
   0      7      0    this       Lscala/LowPriorityImplicits$$anon$1;
   0      7      1    from       Ljava/lang/String;

  Signature: length = 0x2
   00 29 

}

