Compiled from "LowPriorityImplicits.scala"
public class scala.LowPriorityImplicits extends java.lang.Object implements scala.ScalaObject
  SourceFile: "LowPriorityImplicits.scala"
  ScalaSig: length = 0x5E3
   05 00 FFFFFF81 59 06 08 01 02 FFFFFF84 FFFFFF80 FFFFFF80 FFFFFF80 00 05 02 14
   4C 6F 77 50 72 69 6F 72 69 74 79 49 6D 70 6C 69
   63 69 74 73 0A 01 03 01 05 73 63 61 6C 61 03 00
   13 03 00 06 0E 10 02 07 0C 0D 01 08 0A 02 09 0A
   01 04 6C 61 6E 67 0A 01 0B 01 04 6A 61 76 61 09
   02 0D 08 02 06 4F 62 6A 65 63 74 10 02 0F 10 0D
   01 02 09 02 11 02 02 0B 53 63 61 6C 61 4F 62 6A
   65 63 74 08 05 13 00 FFFFFF84 00 14 01 06 3C 69 6E 69
   74 3E 14 01 15 10 02 0F 00 08 05 17 00 FFFFFF84 01 18
   01 10 67 65 6E 65 72 69 63 57 72 61 70 41 72 72
   61 79 15 02 19 24 14 02 1A 2D 10 03 1B 20 22 0D
   01 1C 0A 02 1D 1E 01 07 6D 75 74 61 62 6C 65 0A
   02 1F 02 01 0A 63 6F 6C 6C 65 63 74 69 6F 6E 09
   02 21 1C 02 0C 57 72 61 70 70 65 64 41 72 72 61
   79 10 02 23 24 0C 00 04 08 25 16 FFFFFF84 FFFFFF80 FFFFFF80 FFFFFFC2 00
   26 02 01 54 11 02 27 2A 10 02 0F 28 09 02 29 02
   02 07 4E 6F 74 68 69 6E 67 10 02 0F 2B 09 02 2C
   02 02 03 41 6E 79 08 05 2E 16 FFFFFFC0 00 2F 01 02 78
   73 10 03 0F 30 22 09 02 31 02 02 05 41 72 72 61
   79 08 05 33 00 FFFFFF84 01 34 01 0C 77 72 61 70 52 65
   66 41 72 72 61 79 15 02 35 38 14 02 36 3D 10 03
   1B 20 37 10 02 23 38 04 08 25 32 FFFFFF84 FFFFFF80 FFFFFF80 FFFFFFC2 00
   39 11 02 27 3A 10 02 0F 3B 09 02 3C 02 02 06 41
   6E 79 52 65 66 08 05 2E 32 FFFFFFC0 00 3E 10 03 0F 30
   37 08 05 40 00 FFFFFF84 01 41 01 0C 77 72 61 70 49 6E
   74 41 72 72 61 79 14 02 42 46 10 03 1B 20 43 10
   02 0F 44 09 02 45 02 02 03 49 6E 74 08 05 2E 3F
   FFFFFFC0 00 47 10 03 0F 30 43 08 05 49 00 FFFFFF84 01 4A 01
   0F 77 72 61 70 44 6F 75 62 6C 65 41 72 72 61 79
   14 02 4B 4F 10 03 1B 20 4C 10 02 0F 4D 09 02 4E
   02 02 06 44 6F 75 62 6C 65 08 05 2E 48 FFFFFFC0 00 50
   10 03 0F 30 4C 08 05 52 00 FFFFFF84 01 53 01 0D 77 72
   61 70 4C 6F 6E 67 41 72 72 61 79 14 02 54 58 10
   03 1B 20 55 10 02 0F 56 09 02 57 02 02 04 4C 6F
   6E 67 08 05 2E 51 FFFFFFC0 00 59 10 03 0F 30 55 08 05
   5B 00 FFFFFF84 01 5C 01 0E 77 72 61 70 46 6C 6F 61 74
   41 72 72 61 79 14 02 5D 61 10 03 1B 20 5E 10 02
   0F 5F 09 02 60 02 02 05 46 6C 6F 61 74 08 05 2E
   5A FFFFFFC0 00 62 10 03 0F 30 5E 08 05 64 00 FFFFFF84 01 65
   01 0D 77 72 61 70 43 68 61 72 41 72 72 61 79 14
   02 66 6A 10 03 1B 20 67 10 02 0F 68 09 02 69 02
   02 04 43 68 61 72 08 05 2E 63 FFFFFFC0 00 6B 10 03 0F
   30 67 08 05 6D 00 FFFFFF84 01 6E 01 0D 77 72 61 70 42
   79 74 65 41 72 72 61 79 14 02 6F 73 10 03 1B 20
   70 10 02 0F 71 09 02 72 02 02 04 42 79 74 65 08
   05 2E 6C FFFFFFC0 00 74 10 03 0F 30 70 08 05 76 00 FFFFFF84
   01 77 01 0E 77 72 61 70 53 68 6F 72 74 41 72 72
   61 79 14 02 78 7C 10 03 1B 20 79 10 02 0F 7A 09
   02 7B 02 02 05 53 68 6F 72 74 08 05 2E 75 FFFFFFC0 00
   7D 10 03 0F 30 79 08 06 7F 00 FFFFFF84 01 FFFFFF81 00 01 10
   77 72 61 70 42 6F 6F 6C 65 61 6E 41 72 72 61 79
   14 04 FFFFFF81 01 FFFFFF81 05 10 04 1B 20 FFFFFF81 02 10 03 0F FFFFFF81
   03 09 03 FFFFFF81 04 02 02 07 42 6F 6F 6C 65 61 6E 08
   06 2E 7E FFFFFFC0 00 FFFFFF81 06 10 04 0F 30 FFFFFF81 02 08 07 FFFFFF81
   08 00 FFFFFF84 01 FFFFFF81 09 01 0D 77 72 61 70 55 6E 69 74
   41 72 72 61 79 14 04 FFFFFF81 0A FFFFFF81 0E 10 04 1B 20 FFFFFF81
   0B 10 03 0F FFFFFF81 0C 09 03 FFFFFF81 0D 02 02 04 55 6E 69
   74 08 07 2E FFFFFF81 07 FFFFFFC0 00 FFFFFF81 0F 10 04 0F 30 FFFFFF81 0B
   08 07 FFFFFF81 11 00 FFFFFF84 01 FFFFFF81 12 01 0A 77 72 61 70 53
   74 72 69 6E 67 14 04 FFFFFF81 13 FFFFFF81 19 10 04 FFFFFF81 14 FFFFFF81
   17 0D 02 FFFFFF81 15 0A 03 FFFFFF81 16 1E 01 09 69 6D 6D 75
   74 61 62 6C 65 09 04 FFFFFF81 18 FFFFFF81 15 02 0D 57 72 61
   70 70 65 64 53 74 72 69 6E 67 08 08 FFFFFF81 1A FFFFFF81 10
   FFFFFFC0 00 FFFFFF81 1B 01 01 73 10 04 FFFFFF81 1C FFFFFF81 1F 0E 03 0F
   FFFFFF81 1D 09 03 FFFFFF81 1E 02 01 06 50 72 65 64 65 66 09
   04 FFFFFF81 20 FFFFFF81 21 02 06 53 74 72 69 6E 67 0A 03 FFFFFF81
   1E 02 08 07 FFFFFF81 23 00 FFFFFF84 01 FFFFFF81 24 01 0C 75 6E 77
   72 61 70 53 74 72 69 6E 67 14 04 FFFFFF81 1B FFFFFF81 25 08
   08 FFFFFF81 26 FFFFFF81 22 FFFFFFC0 00 FFFFFF81 13 01 02 77 73 08 07 FFFFFF81
   28 00 FFFFFF84 01 FFFFFF81 29 01 1A 66 61 6C 6C 62 61 63 6B
   53 74 72 69 6E 67 43 61 6E 42 75 69 6C 64 46 72
   6F 6D 15 04 FFFFFF81 2A FFFFFF81 31 10 0A FFFFFF81 2B FFFFFF81 2E FFFFFF81 1B
   FFFFFF81 30 FFFFFF81 32 0D 02 FFFFFF81 2C 0A 03 FFFFFF81 2D 1E 01 07 67
   65 6E 65 72 69 63 09 04 FFFFFF81 2F FFFFFF81 2C 02 0C 43 61
   6E 42 75 69 6C 64 46 72 6F 6D 10 03 23 FFFFFF81 31 04
   09 25 FFFFFF81 27 FFFFFF84 FFFFFF80 FFFFFF80 FFFFFFC2 00 26 10 06 FFFFFF81 14 FFFFFF81 33
   FFFFFF81 30 09 04 FFFFFF81 34 FFFFFF81 15 02 0A 49 6E 64 65 78 65
   64 53 65 71 08 07 FFFFFF81 36 00 FFFFFF84 00 FFFFFF81 37 01 09 77
   72 61 70 41 72 72 61 79 15 04 FFFFFF81 38 FFFFFF81 3B 14 04
   FFFFFF81 39 FFFFFF81 3C 10 04 1B 20 FFFFFF81 3A 10 03 23 FFFFFF81 3B 04
   09 25 FFFFFF81 35 FFFFFF84 FFFFFF80 FFFFFF80 FFFFFFC2 00 39 08 07 2E FFFFFF81 35 FFFFFFC0
   00 FFFFFF81 3D 10 04 0F 30 FFFFFF81 3A 08 07 FFFFFF81 36 00 FFFFFF84 00
   FFFFFF81 3F 14 03 42 FFFFFF81 40 08 06 2E FFFFFF81 3E FFFFFFC0 00 47 08
   07 FFFFFF81 36 00 FFFFFF84 00 FFFFFF81 42 14 03 4B FFFFFF81 43 08 06 2E
   FFFFFF81 41 FFFFFFC0 00 50 08 07 FFFFFF81 36 00 FFFFFF84 00 FFFFFF81 45 14 03
   54 FFFFFF81 46 08 06 2E FFFFFF81 44 FFFFFFC0 00 59 08 07 FFFFFF81 36 00
   FFFFFF84 00 FFFFFF81 48 14 03 5D FFFFFF81 49 08 06 2E FFFFFF81 47 FFFFFFC0 00
   62 08 07 FFFFFF81 36 00 FFFFFF84 00 FFFFFF81 4B 14 03 66 FFFFFF81 4C 08
   06 2E FFFFFF81 4A FFFFFFC0 00 6B 08 07 FFFFFF81 36 00 FFFFFF84 00 FFFFFF81 4E
   14 03 6F FFFFFF81 4F 08 06 2E FFFFFF81 4D FFFFFFC0 00 74 08 07 FFFFFF81
   36 00 FFFFFF84 00 FFFFFF81 51 14 03 78 FFFFFF81 52 08 06 2E FFFFFF81 50
   FFFFFFC0 00 7D 08 07 FFFFFF81 36 00 FFFFFF84 00 FFFFFF81 54 14 04 FFFFFF81 01
   FFFFFF81 55 08 07 2E FFFFFF81 53 FFFFFFC0 00 FFFFFF81 06 08 07 FFFFFF81 36 00
   FFFFFF84 00 FFFFFF81 57 14 04 FFFFFF81 0A FFFFFF81 58 08 07 2E FFFFFF81 56 FFFFFFC0
   00 FFFFFF81 0F 
  InnerClass: 
   public final #148= #91 of #147; //ofRef=class scala/collection/mutable/WrappedArray$ofRef of class scala/collection/mutable/WrappedArray
   public final #149= #83 of #147; //ofInt=class scala/collection/mutable/WrappedArray$ofInt of class scala/collection/mutable/WrappedArray
   public final #150= #67 of #147; //ofLong=class scala/collection/mutable/WrappedArray$ofLong of class scala/collection/mutable/WrappedArray
   public final #151= #51 of #147; //ofChar=class scala/collection/mutable/WrappedArray$ofChar of class scala/collection/mutable/WrappedArray
   public final #152= #43 of #147; //ofByte=class scala/collection/mutable/WrappedArray$ofByte of class scala/collection/mutable/WrappedArray
   public final #153= #14 of #147; //ofUnit=class scala/collection/mutable/WrappedArray$ofUnit of class scala/collection/mutable/WrappedArray
   public final #154= #59 of #147; //ofFloat=class scala/collection/mutable/WrappedArray$ofFloat of class scala/collection/mutable/WrappedArray
   public final #155= #35 of #147; //ofShort=class scala/collection/mutable/WrappedArray$ofShort of class scala/collection/mutable/WrappedArray
   public final #156= #75 of #147; //ofDouble=class scala/collection/mutable/WrappedArray$ofDouble of class scala/collection/mutable/WrappedArray
   public final #157= #27 of #147; //ofBoolean=class scala/collection/mutable/WrappedArray$ofBoolean of class scala/collection/mutable/WrappedArray
   public final #160= #100 of #159; //$anon$1=class scala/LowPriorityImplicits$$anon$1 of class scala/LowPriorityImplicits
  minor version: 0
  major version: 49
  Constant pool:
const #1 = Asciz	SourceFile;
const #2 = Asciz	LowPriorityImplicits.scala;
const #3 = Asciz	<init>;
const #4 = Asciz	()V;
const #5 = Asciz	Code;
const #6 = Asciz	LineNumberTable;
const #7 = Asciz	java/lang/Object;
const #8 = class	#7;	//  java/lang/Object
const #9 = NameAndType	#3:#4;//  "<init>":()V
const #10 = Method	#8.#9;	//  java/lang/Object."<init>":()V
const #11 = Asciz	wrapArray;
const #12 = Asciz	([Lscala/runtime/BoxedUnit;)Lscala/collection/mutable/WrappedArray;;
const #13 = Asciz	scala/collection/mutable/WrappedArray$ofUnit;
const #14 = class	#13;	//  scala/collection/mutable/WrappedArray$ofUnit
const #15 = Asciz	([Lscala/runtime/BoxedUnit;)V;
const #16 = NameAndType	#3:#15;//  "<init>":([Lscala/runtime/BoxedUnit;)V
const #17 = Method	#14.#16;	//  scala/collection/mutable/WrappedArray$ofUnit."<init>":([Lscala/runtime/BoxedUnit;)V
const #18 = Asciz	this;
const #19 = Asciz	Lscala/LowPriorityImplicits;;
const #20 = Asciz	xs;
const #21 = Asciz	[Lscala/runtime/BoxedUnit;;
const #22 = Asciz	LocalVariableTable;
const #23 = Asciz	([Lscala/runtime/BoxedUnit;)Lscala/collection/mutable/WrappedArray<Ljava/lang/Object;>;;
const #24 = Asciz	Signature;
const #25 = Asciz	([Z)Lscala/collection/mutable/WrappedArray;;
const #26 = Asciz	scala/collection/mutable/WrappedArray$ofBoolean;
const #27 = class	#26;	//  scala/collection/mutable/WrappedArray$ofBoolean
const #28 = Asciz	([Z)V;
const #29 = NameAndType	#3:#28;//  "<init>":([Z)V
const #30 = Method	#27.#29;	//  scala/collection/mutable/WrappedArray$ofBoolean."<init>":([Z)V
const #31 = Asciz	[Z;
const #32 = Asciz	([Z)Lscala/collection/mutable/WrappedArray<Ljava/lang/Boolean;>;;
const #33 = Asciz	([S)Lscala/collection/mutable/WrappedArray;;
const #34 = Asciz	scala/collection/mutable/WrappedArray$ofShort;
const #35 = class	#34;	//  scala/collection/mutable/WrappedArray$ofShort
const #36 = Asciz	([S)V;
const #37 = NameAndType	#3:#36;//  "<init>":([S)V
const #38 = Method	#35.#37;	//  scala/collection/mutable/WrappedArray$ofShort."<init>":([S)V
const #39 = Asciz	[S;
const #40 = Asciz	([S)Lscala/collection/mutable/WrappedArray<Ljava/lang/Short;>;;
const #41 = Asciz	([B)Lscala/collection/mutable/WrappedArray;;
const #42 = Asciz	scala/collection/mutable/WrappedArray$ofByte;
const #43 = class	#42;	//  scala/collection/mutable/WrappedArray$ofByte
const #44 = Asciz	([B)V;
const #45 = NameAndType	#3:#44;//  "<init>":([B)V
const #46 = Method	#43.#45;	//  scala/collection/mutable/WrappedArray$ofByte."<init>":([B)V
const #47 = Asciz	[B;
const #48 = Asciz	([B)Lscala/collection/mutable/WrappedArray<Ljava/lang/Byte;>;;
const #49 = Asciz	([C)Lscala/collection/mutable/WrappedArray;;
const #50 = Asciz	scala/collection/mutable/WrappedArray$ofChar;
const #51 = class	#50;	//  scala/collection/mutable/WrappedArray$ofChar
const #52 = Asciz	([C)V;
const #53 = NameAndType	#3:#52;//  "<init>":([C)V
const #54 = Method	#51.#53;	//  scala/collection/mutable/WrappedArray$ofChar."<init>":([C)V
const #55 = Asciz	[C;
const #56 = Asciz	([C)Lscala/collection/mutable/WrappedArray<Ljava/lang/Character;>;;
const #57 = Asciz	([F)Lscala/collection/mutable/WrappedArray;;
const #58 = Asciz	scala/collection/mutable/WrappedArray$ofFloat;
const #59 = class	#58;	//  scala/collection/mutable/WrappedArray$ofFloat
const #60 = Asciz	([F)V;
const #61 = NameAndType	#3:#60;//  "<init>":([F)V
const #62 = Method	#59.#61;	//  scala/collection/mutable/WrappedArray$ofFloat."<init>":([F)V
const #63 = Asciz	[F;
const #64 = Asciz	([F)Lscala/collection/mutable/WrappedArray<Ljava/lang/Float;>;;
const #65 = Asciz	([J)Lscala/collection/mutable/WrappedArray;;
const #66 = Asciz	scala/collection/mutable/WrappedArray$ofLong;
const #67 = class	#66;	//  scala/collection/mutable/WrappedArray$ofLong
const #68 = Asciz	([J)V;
const #69 = NameAndType	#3:#68;//  "<init>":([J)V
const #70 = Method	#67.#69;	//  scala/collection/mutable/WrappedArray$ofLong."<init>":([J)V
const #71 = Asciz	[J;
const #72 = Asciz	([J)Lscala/collection/mutable/WrappedArray<Ljava/lang/Long;>;;
const #73 = Asciz	([D)Lscala/collection/mutable/WrappedArray;;
const #74 = Asciz	scala/collection/mutable/WrappedArray$ofDouble;
const #75 = class	#74;	//  scala/collection/mutable/WrappedArray$ofDouble
const #76 = Asciz	([D)V;
const #77 = NameAndType	#3:#76;//  "<init>":([D)V
const #78 = Method	#75.#77;	//  scala/collection/mutable/WrappedArray$ofDouble."<init>":([D)V
const #79 = Asciz	[D;
const #80 = Asciz	([D)Lscala/collection/mutable/WrappedArray<Ljava/lang/Double;>;;
const #81 = Asciz	([I)Lscala/collection/mutable/WrappedArray;;
const #82 = Asciz	scala/collection/mutable/WrappedArray$ofInt;
const #83 = class	#82;	//  scala/collection/mutable/WrappedArray$ofInt
const #84 = Asciz	([I)V;
const #85 = NameAndType	#3:#84;//  "<init>":([I)V
const #86 = Method	#83.#85;	//  scala/collection/mutable/WrappedArray$ofInt."<init>":([I)V
const #87 = Asciz	[I;
const #88 = Asciz	([I)Lscala/collection/mutable/WrappedArray<Ljava/lang/Integer;>;;
const #89 = Asciz	([Ljava/lang/Object;)Lscala/collection/mutable/WrappedArray;;
const #90 = Asciz	scala/collection/mutable/WrappedArray$ofRef;
const #91 = class	#90;	//  scala/collection/mutable/WrappedArray$ofRef
const #92 = Asciz	([Ljava/lang/Object;)V;
const #93 = NameAndType	#3:#92;//  "<init>":([Ljava/lang/Object;)V
const #94 = Method	#91.#93;	//  scala/collection/mutable/WrappedArray$ofRef."<init>":([Ljava/lang/Object;)V
const #95 = Asciz	[Ljava/lang/Object;;
const #96 = Asciz	<T:Ljava/lang/Object;>([TT;)Lscala/collection/mutable/WrappedArray<TT;>;;
const #97 = Asciz	fallbackStringCanBuildFrom;
const #98 = Asciz	()Lscala/collection/generic/CanBuildFrom;;
const #99 = Asciz	scala/LowPriorityImplicits$$anon$1;
const #100 = class	#99;	//  scala/LowPriorityImplicits$$anon$1
const #101 = Asciz	(Lscala/LowPriorityImplicits;)V;
const #102 = NameAndType	#3:#101;//  "<init>":(Lscala/LowPriorityImplicits;)V
const #103 = Method	#100.#102;	//  scala/LowPriorityImplicits$$anon$1."<init>":(Lscala/LowPriorityImplicits;)V
const #104 = Asciz	<T:Ljava/lang/Object;>()Lscala/collection/generic/CanBuildFrom<Ljava/lang/String;TT;Lscala/collection/immutable/IndexedSeq<TT;>;>;;
const #105 = Asciz	unwrapString;
const #106 = Asciz	(Lscala/collection/immutable/WrappedString;)Ljava/lang/String;;
const #107 = Asciz	scala/collection/immutable/WrappedString;
const #108 = class	#107;	//  scala/collection/immutable/WrappedString
const #109 = Asciz	self;
const #110 = Asciz	()Ljava/lang/String;;
const #111 = NameAndType	#109:#110;//  self:()Ljava/lang/String;
const #112 = Method	#108.#111;	//  scala/collection/immutable/WrappedString.self:()Ljava/lang/String;
const #113 = Asciz	ws;
const #114 = Asciz	Lscala/collection/immutable/WrappedString;;
const #115 = Asciz	wrapString;
const #116 = Asciz	(Ljava/lang/String;)Lscala/collection/immutable/WrappedString;;
const #117 = Asciz	(Ljava/lang/String;)V;
const #118 = NameAndType	#3:#117;//  "<init>":(Ljava/lang/String;)V
const #119 = Method	#108.#118;	//  scala/collection/immutable/WrappedString."<init>":(Ljava/lang/String;)V
const #120 = Asciz	s;
const #121 = Asciz	Ljava/lang/String;;
const #122 = Asciz	wrapUnitArray;
const #123 = Asciz	wrapBooleanArray;
const #124 = Asciz	wrapShortArray;
const #125 = Asciz	wrapByteArray;
const #126 = Asciz	wrapCharArray;
const #127 = Asciz	wrapFloatArray;
const #128 = Asciz	wrapLongArray;
const #129 = Asciz	wrapDoubleArray;
const #130 = Asciz	wrapIntArray;
const #131 = Asciz	wrapRefArray;
const #132 = Asciz	genericWrapArray;
const #133 = Asciz	(Ljava/lang/Object;)Lscala/collection/mutable/WrappedArray;;
const #134 = Asciz	scala/collection/mutable/WrappedArray$;
const #135 = class	#134;	//  scala/collection/mutable/WrappedArray$
const #136 = Asciz	MODULE$;
const #137 = Asciz	Lscala/collection/mutable/WrappedArray$;;
const #138 = NameAndType	#136:#137;//  MODULE$:Lscala/collection/mutable/WrappedArray$;
const #139 = Field	#135.#138;	//  scala/collection/mutable/WrappedArray$.MODULE$:Lscala/collection/mutable/WrappedArray$;
const #140 = Asciz	make;
const #141 = NameAndType	#140:#133;//  make:(Ljava/lang/Object;)Lscala/collection/mutable/WrappedArray;
const #142 = Method	#135.#141;	//  scala/collection/mutable/WrappedArray$.make:(Ljava/lang/Object;)Lscala/collection/mutable/WrappedArray;
const #143 = Asciz	Ljava/lang/Object;;
const #144 = Asciz	ScalaSig;
const #145 = Asciz	InnerClasses;
const #146 = Asciz	scala/collection/mutable/WrappedArray;
const #147 = class	#146;	//  scala/collection/mutable/WrappedArray
const #148 = Asciz	ofRef;
const #149 = Asciz	ofInt;
const #150 = Asciz	ofLong;
const #151 = Asciz	ofChar;
const #152 = Asciz	ofByte;
const #153 = Asciz	ofUnit;
const #154 = Asciz	ofFloat;
const #155 = Asciz	ofShort;
const #156 = Asciz	ofDouble;
const #157 = Asciz	ofBoolean;
const #158 = Asciz	scala/LowPriorityImplicits;
const #159 = class	#158;	//  scala/LowPriorityImplicits
const #160 = Asciz	$anon$1;
const #161 = Asciz	scala/ScalaObject;
const #162 = class	#161;	//  scala/ScalaObject

{
public scala.LowPriorityImplicits();
  Code:
   Stack=1, Locals=1, Args_size=1
   0:	aload_0
   1:	invokespecial	#10; //Method java/lang/Object."<init>":()V
   4:	return
  LineNumberTable: 
   line 26: 0


public scala.collection.mutable.WrappedArray wrapArray(scala.runtime.BoxedUnit[]);
  Code:
   Stack=3, Locals=2, Args_size=2
   0:	new	#14; //class scala/collection/mutable/WrappedArray$ofUnit
   3:	dup
   4:	aload_1
   5:	invokespecial	#17; //Method scala/collection/mutable/WrappedArray$ofUnit."<init>":([Lscala/runtime/BoxedUnit;)V
   8:	areturn
  LineNumberTable: 
   line 61: 0

  LocalVariableTable: 
   Start  Length  Slot  Name   Signature
   0      9      0    this       Lscala/LowPriorityImplicits;
   0      9      1    xs       [Lscala/runtime/BoxedUnit;

  Signature: length = 0x2
   00 17 

public scala.collection.mutable.WrappedArray wrapArray(boolean[]);
  Code:
   Stack=3, Locals=2, Args_size=2
   0:	new	#27; //class scala/collection/mutable/WrappedArray$ofBoolean
   3:	dup
   4:	aload_1
   5:	invokespecial	#30; //Method scala/collection/mutable/WrappedArray$ofBoolean."<init>":([Z)V
   8:	areturn
  LineNumberTable: 
   line 60: 0

  LocalVariableTable: 
   Start  Length  Slot  Name   Signature
   0      9      0    this       Lscala/LowPriorityImplicits;
   0      9      1    xs       [Z

  Signature: length = 0x2
   00 20 

public scala.collection.mutable.WrappedArray wrapArray(short[]);
  Code:
   Stack=3, Locals=2, Args_size=2
   0:	new	#35; //class scala/collection/mutable/WrappedArray$ofShort
   3:	dup
   4:	aload_1
   5:	invokespecial	#38; //Method scala/collection/mutable/WrappedArray$ofShort."<init>":([S)V
   8:	areturn
  LineNumberTable: 
   line 59: 0

  LocalVariableTable: 
   Start  Length  Slot  Name   Signature
   0      9      0    this       Lscala/LowPriorityImplicits;
   0      9      1    xs       [S

  Signature: length = 0x2
   00 28 

public scala.collection.mutable.WrappedArray wrapArray(byte[]);
  Code:
   Stack=3, Locals=2, Args_size=2
   0:	new	#43; //class scala/collection/mutable/WrappedArray$ofByte
   3:	dup
   4:	aload_1
   5:	invokespecial	#46; //Method scala/collection/mutable/WrappedArray$ofByte."<init>":([B)V
   8:	areturn
  LineNumberTable: 
   line 58: 0

  LocalVariableTable: 
   Start  Length  Slot  Name   Signature
   0      9      0    this       Lscala/LowPriorityImplicits;
   0      9      1    xs       [B

  Signature: length = 0x2
   00 30 

public scala.collection.mutable.WrappedArray wrapArray(char[]);
  Code:
   Stack=3, Locals=2, Args_size=2
   0:	new	#51; //class scala/collection/mutable/WrappedArray$ofChar
   3:	dup
   4:	aload_1
   5:	invokespecial	#54; //Method scala/collection/mutable/WrappedArray$ofChar."<init>":([C)V
   8:	areturn
  LineNumberTable: 
   line 57: 0

  LocalVariableTable: 
   Start  Length  Slot  Name   Signature
   0      9      0    this       Lscala/LowPriorityImplicits;
   0      9      1    xs       [C

  Signature: length = 0x2
   00 38 

public scala.collection.mutable.WrappedArray wrapArray(float[]);
  Code:
   Stack=3, Locals=2, Args_size=2
   0:	new	#59; //class scala/collection/mutable/WrappedArray$ofFloat
   3:	dup
   4:	aload_1
   5:	invokespecial	#62; //Method scala/collection/mutable/WrappedArray$ofFloat."<init>":([F)V
   8:	areturn
  LineNumberTable: 
   line 56: 0

  LocalVariableTable: 
   Start  Length  Slot  Name   Signature
   0      9      0    this       Lscala/LowPriorityImplicits;
   0      9      1    xs       [F

  Signature: length = 0x2
   00 40 

public scala.collection.mutable.WrappedArray wrapArray(long[]);
  Code:
   Stack=3, Locals=2, Args_size=2
   0:	new	#67; //class scala/collection/mutable/WrappedArray$ofLong
   3:	dup
   4:	aload_1
   5:	invokespecial	#70; //Method scala/collection/mutable/WrappedArray$ofLong."<init>":([J)V
   8:	areturn
  LineNumberTable: 
   line 55: 0

  LocalVariableTable: 
   Start  Length  Slot  Name   Signature
   0      9      0    this       Lscala/LowPriorityImplicits;
   0      9      1    xs       [J

  Signature: length = 0x2
   00 48 

public scala.collection.mutable.WrappedArray wrapArray(double[]);
  Code:
   Stack=3, Locals=2, Args_size=2
   0:	new	#75; //class scala/collection/mutable/WrappedArray$ofDouble
   3:	dup
   4:	aload_1
   5:	invokespecial	#78; //Method scala/collection/mutable/WrappedArray$ofDouble."<init>":([D)V
   8:	areturn
  LineNumberTable: 
   line 54: 0

  LocalVariableTable: 
   Start  Length  Slot  Name   Signature
   0      9      0    this       Lscala/LowPriorityImplicits;
   0      9      1    xs       [D

  Signature: length = 0x2
   00 50 

public scala.collection.mutable.WrappedArray wrapArray(int[]);
  Code:
   Stack=3, Locals=2, Args_size=2
   0:	new	#83; //class scala/collection/mutable/WrappedArray$ofInt
   3:	dup
   4:	aload_1
   5:	invokespecial	#86; //Method scala/collection/mutable/WrappedArray$ofInt."<init>":([I)V
   8:	areturn
  LineNumberTable: 
   line 53: 0

  LocalVariableTable: 
   Start  Length  Slot  Name   Signature
   0      9      0    this       Lscala/LowPriorityImplicits;
   0      9      1    xs       [I

  Signature: length = 0x2
   00 58 

public scala.collection.mutable.WrappedArray wrapArray(java.lang.Object[]);
  Code:
   Stack=3, Locals=2, Args_size=2
   0:	new	#91; //class scala/collection/mutable/WrappedArray$ofRef
   3:	dup
   4:	aload_1
   5:	invokespecial	#94; //Method scala/collection/mutable/WrappedArray$ofRef."<init>":([Ljava/lang/Object;)V
   8:	areturn
  LineNumberTable: 
   line 52: 0

  LocalVariableTable: 
   Start  Length  Slot  Name   Signature
   0      9      0    this       Lscala/LowPriorityImplicits;
   0      9      1    xs       [Ljava/lang/Object;

  Signature: length = 0x2
   00 60 

public scala.collection.generic.CanBuildFrom fallbackStringCanBuildFrom();
  Code:
   Stack=3, Locals=1, Args_size=1
   0:	new	#100; //class scala/LowPriorityImplicits$$anon$1
   3:	dup
   4:	aload_0
   5:	invokespecial	#103; //Method scala/LowPriorityImplicits$$anon$1."<init>":(Lscala/LowPriorityImplicits;)V
   8:	areturn
  LineNumberTable: 
   line 46: 0

  Signature: length = 0x2
   00 68 

public java.lang.String unwrapString(scala.collection.immutable.WrappedString);
  Code:
   Stack=1, Locals=2, Args_size=2
   0:	aload_1
   1:	invokevirtual	#112; //Method scala/collection/immutable/WrappedString.self:()Ljava/lang/String;
   4:	areturn
  LineNumberTable: 
   line 43: 0

  LocalVariableTable: 
   Start  Length  Slot  Name   Signature
   0      5      0    this       Lscala/LowPriorityImplicits;
   0      5      1    ws       Lscala/collection/immutable/WrappedString;


public scala.collection.immutable.WrappedString wrapString(java.lang.String);
  Code:
   Stack=3, Locals=2, Args_size=2
   0:	new	#108; //class scala/collection/immutable/WrappedString
   3:	dup
   4:	aload_1
   5:	invokespecial	#119; //Method scala/collection/immutable/WrappedString."<init>":(Ljava/lang/String;)V
   8:	areturn
  LineNumberTable: 
   line 42: 0

  LocalVariableTable: 
   Start  Length  Slot  Name   Signature
   0      9      0    this       Lscala/LowPriorityImplicits;
   0      9      1    s       Ljava/lang/String;


public scala.collection.mutable.WrappedArray wrapUnitArray(scala.runtime.BoxedUnit[]);
  Code:
   Stack=3, Locals=2, Args_size=2
   0:	new	#14; //class scala/collection/mutable/WrappedArray$ofUnit
   3:	dup
   4:	aload_1
   5:	invokespecial	#17; //Method scala/collection/mutable/WrappedArray$ofUnit."<init>":([Lscala/runtime/BoxedUnit;)V
   8:	areturn
  LineNumberTable: 
   line 40: 0

  LocalVariableTable: 
   Start  Length  Slot  Name   Signature
   0      9      0    this       Lscala/LowPriorityImplicits;
   0      9      1    xs       [Lscala/runtime/BoxedUnit;

  Signature: length = 0x2
   00 17 

public scala.collection.mutable.WrappedArray wrapBooleanArray(boolean[]);
  Code:
   Stack=3, Locals=2, Args_size=2
   0:	new	#27; //class scala/collection/mutable/WrappedArray$ofBoolean
   3:	dup
   4:	aload_1
   5:	invokespecial	#30; //Method scala/collection/mutable/WrappedArray$ofBoolean."<init>":([Z)V
   8:	areturn
  LineNumberTable: 
   line 39: 0

  LocalVariableTable: 
   Start  Length  Slot  Name   Signature
   0      9      0    this       Lscala/LowPriorityImplicits;
   0      9      1    xs       [Z

  Signature: length = 0x2
   00 20 

public scala.collection.mutable.WrappedArray wrapShortArray(short[]);
  Code:
   Stack=3, Locals=2, Args_size=2
   0:	new	#35; //class scala/collection/mutable/WrappedArray$ofShort
   3:	dup
   4:	aload_1
   5:	invokespecial	#38; //Method scala/collection/mutable/WrappedArray$ofShort."<init>":([S)V
   8:	areturn
  LineNumberTable: 
   line 38: 0

  LocalVariableTable: 
   Start  Length  Slot  Name   Signature
   0      9      0    this       Lscala/LowPriorityImplicits;
   0      9      1    xs       [S

  Signature: length = 0x2
   00 28 

public scala.collection.mutable.WrappedArray wrapByteArray(byte[]);
  Code:
   Stack=3, Locals=2, Args_size=2
   0:	new	#43; //class scala/collection/mutable/WrappedArray$ofByte
   3:	dup
   4:	aload_1
   5:	invokespecial	#46; //Method scala/collection/mutable/WrappedArray$ofByte."<init>":([B)V
   8:	areturn
  LineNumberTable: 
   line 37: 0

  LocalVariableTable: 
   Start  Length  Slot  Name   Signature
   0      9      0    this       Lscala/LowPriorityImplicits;
   0      9      1    xs       [B

  Signature: length = 0x2
   00 30 

public scala.collection.mutable.WrappedArray wrapCharArray(char[]);
  Code:
   Stack=3, Locals=2, Args_size=2
   0:	new	#51; //class scala/collection/mutable/WrappedArray$ofChar
   3:	dup
   4:	aload_1
   5:	invokespecial	#54; //Method scala/collection/mutable/WrappedArray$ofChar."<init>":([C)V
   8:	areturn
  LineNumberTable: 
   line 36: 0

  LocalVariableTable: 
   Start  Length  Slot  Name   Signature
   0      9      0    this       Lscala/LowPriorityImplicits;
   0      9      1    xs       [C

  Signature: length = 0x2
   00 38 

public scala.collection.mutable.WrappedArray wrapFloatArray(float[]);
  Code:
   Stack=3, Locals=2, Args_size=2
   0:	new	#59; //class scala/collection/mutable/WrappedArray$ofFloat
   3:	dup
   4:	aload_1
   5:	invokespecial	#62; //Method scala/collection/mutable/WrappedArray$ofFloat."<init>":([F)V
   8:	areturn
  LineNumberTable: 
   line 35: 0

  LocalVariableTable: 
   Start  Length  Slot  Name   Signature
   0      9      0    this       Lscala/LowPriorityImplicits;
   0      9      1    xs       [F

  Signature: length = 0x2
   00 40 

public scala.collection.mutable.WrappedArray wrapLongArray(long[]);
  Code:
   Stack=3, Locals=2, Args_size=2
   0:	new	#67; //class scala/collection/mutable/WrappedArray$ofLong
   3:	dup
   4:	aload_1
   5:	invokespecial	#70; //Method scala/collection/mutable/WrappedArray$ofLong."<init>":([J)V
   8:	areturn
  LineNumberTable: 
   line 34: 0

  LocalVariableTable: 
   Start  Length  Slot  Name   Signature
   0      9      0    this       Lscala/LowPriorityImplicits;
   0      9      1    xs       [J

  Signature: length = 0x2
   00 48 

public scala.collection.mutable.WrappedArray wrapDoubleArray(double[]);
  Code:
   Stack=3, Locals=2, Args_size=2
   0:	new	#75; //class scala/collection/mutable/WrappedArray$ofDouble
   3:	dup
   4:	aload_1
   5:	invokespecial	#78; //Method scala/collection/mutable/WrappedArray$ofDouble."<init>":([D)V
   8:	areturn
  LineNumberTable: 
   line 33: 0

  LocalVariableTable: 
   Start  Length  Slot  Name   Signature
   0      9      0    this       Lscala/LowPriorityImplicits;
   0      9      1    xs       [D

  Signature: length = 0x2
   00 50 

public scala.collection.mutable.WrappedArray wrapIntArray(int[]);
  Code:
   Stack=3, Locals=2, Args_size=2
   0:	new	#83; //class scala/collection/mutable/WrappedArray$ofInt
   3:	dup
   4:	aload_1
   5:	invokespecial	#86; //Method scala/collection/mutable/WrappedArray$ofInt."<init>":([I)V
   8:	areturn
  LineNumberTable: 
   line 32: 0

  LocalVariableTable: 
   Start  Length  Slot  Name   Signature
   0      9      0    this       Lscala/LowPriorityImplicits;
   0      9      1    xs       [I

  Signature: length = 0x2
   00 58 

public scala.collection.mutable.WrappedArray wrapRefArray(java.lang.Object[]);
  Code:
   Stack=3, Locals=2, Args_size=2
   0:	new	#91; //class scala/collection/mutable/WrappedArray$ofRef
   3:	dup
   4:	aload_1
   5:	invokespecial	#94; //Method scala/collection/mutable/WrappedArray$ofRef."<init>":([Ljava/lang/Object;)V
   8:	areturn
  LineNumberTable: 
   line 31: 0

  LocalVariableTable: 
   Start  Length  Slot  Name   Signature
   0      9      0    this       Lscala/LowPriorityImplicits;
   0      9      1    xs       [Ljava/lang/Object;

  Signature: length = 0x2
   00 60 

public scala.collection.mutable.WrappedArray genericWrapArray(java.lang.Object);
  Code:
   Stack=2, Locals=2, Args_size=2
   0:	getstatic	#139; //Field scala/collection/mutable/WrappedArray$.MODULE$:Lscala/collection/mutable/WrappedArray$;
   3:	aload_1
   4:	invokevirtual	#142; //Method scala/collection/mutable/WrappedArray$.make:(Ljava/lang/Object;)Lscala/collection/mutable/WrappedArray;
   7:	areturn
  LineNumberTable: 
   line 29: 0

  LocalVariableTable: 
   Start  Length  Slot  Name   Signature
   0      8      0    this       Lscala/LowPriorityImplicits;
   0      8      1    xs       Ljava/lang/Object;

  Signature: length = 0x2
   00 60 

}

