Compiled from "LowPriorityImplicits.scala"
public class scala.LowPriorityImplicits extends java.lang.Object implements scala.ScalaObject
  SourceFile: "LowPriorityImplicits.scala"
  ScalaSig: length = 0x5E3
   05 00 FFFFFF81 59 06 08 01 02 FFFFFF84 FFFFFF80 FFFFFF80 FFFFFF80 00 05 02 14
   4C 6F 77 50 72 69 6F 72 69 74 79 49 6D 70 6C 69
   63 69 74 73 0A 01 03 01 05 73 63 61 6C 61 03 00
   13 03 00 06 0E 10 02 07 0C 0D 01 08 0A 02 09 0A
   01 04 6C 61 6E 67 0A 01 0B 01 04 6A 61 76 61 09
   02 0D 08 02 06 4F 62 6A 65 63 74 10 02 0F 10 0D
   01 02 09 02 11 02 02 0B 53 63 61 6C 61 4F 62 6A
   65 63 74 08 05 13 00 FFFFFF84 00 14 01 06 3C 69 6E 69
   74 3E 14 01 15 10 02 0F 00 08 05 17 00 FFFFFF84 01 18
   01 10 67 65 6E 65 72 69 63 57 72 61 70 41 72 72
   61 79 15 02 19 24 14 02 1A 2D 10 03 1B 20 22 0D
   01 1C 0A 02 1D 1E 01 07 6D 75 74 61 62 6C 65 0A
   02 1F 02 01 0A 63 6F 6C 6C 65 63 74 69 6F 6E 09
   02 21 1C 02 0C 57 72 61 70 70 65 64 41 72 72 61
   79 10 02 23 24 0C 00 04 08 25 16 FFFFFF84 FFFFFF80 FFFFFF80 FFFFFFC2 00
   26 02 01 54 11 02 27 2A 10 02 0F 28 09 02 29 02
   02 07 4E 6F 74 68 69 6E 67 10 02 0F 2B 09 02 2C
   02 02 03 41 6E 79 08 05 2E 16 FFFFFFC0 00 2F 01 02 78
   73 10 03 0F 30 22 09 02 31 02 02 05 41 72 72 61
   79 08 05 33 00 FFFFFF84 01 34 01 0C 77 72 61 70 52 65
   66 41 72 72 61 79 15 02 35 38 14 02 36 3D 10 03
   1B 20 37 10 02 23 38 04 08 25 32 FFFFFF84 FFFFFF80 FFFFFF80 FFFFFFC2 00
   39 11 02 27 3A 10 02 0F 3B 09 02 3C 02 02 06 41
   6E 79 52 65 66 08 05 2E 32 FFFFFFC0 00 3E 10 03 0F 30
   37 08 05 40 00 FFFFFF84 01 41 01 0C 77 72 61 70 49 6E
   74 41 72 72 61 79 14 02 42 46 10 03 1B 20 43 10
   02 0F 44 09 02 45 02 02 03 49 6E 74 08 05 2E 3F
   FFFFFFC0 00 47 10 03 0F 30 43 08 05 49 00 FFFFFF84 01 4A 01
   0F 77 72 61 70 44 6F 75 62 6C 65 41 72 72 61 79
   14 02 4B 4F 10 03 1B 20 4C 10 02 0F 4D 09 02 4E
   02 02 06 44 6F 75 62 6C 65 08 05 2E 48 FFFFFFC0 00 50
   10 03 0F 30 4C 08 05 52 00 FFFFFF84 01 53 01 0D 77 72
   61 70 4C 6F 6E 67 41 72 72 61 79 14 02 54 58 10
   03 1B 20 55 10 02 0F 56 09 02 57 02 02 04 4C 6F
   6E 67 08 05 2E 51 FFFFFFC0 00 59 10 03 0F 30 55 08 05
   5B 00 FFFFFF84 01 5C 01 0E 77 72 61 70 46 6C 6F 61 74
   41 72 72 61 79 14 02 5D 61 10 03 1B 20 5E 10 02
   0F 5F 09 02 60 02 02 05 46 6C 6F 61 74 08 05 2E
   5A FFFFFFC0 00 62 10 03 0F 30 5E 08 05 64 00 FFFFFF84 01 65
   01 0D 77 72 61 70 43 68 61 72 41 72 72 61 79 14
   02 66 6A 10 03 1B 20 67 10 02 0F 68 09 02 69 02
   02 04 43 68 61 72 08 05 2E 63 FFFFFFC0 00 6B 10 03 0F
   30 67 08 05 6D 00 FFFFFF84 01 6E 01 0D 77 72 61 70 42
   79 74 65 41 72 72 61 79 14 02 6F 73 10 03 1B 20
   70 10 02 0F 71 09 02 72 02 02 04 42 79 74 65 08
   05 2E 6C FFFFFFC0 00 74 10 03 0F 30 70 08 05 76 00 FFFFFF84
   01 77 01 0E 77 72 61 70 53 68 6F 72 74 41 72 72
   61 79 14 02 78 7C 10 03 1B 20 79 10 02 0F 7A 09
   02 7B 02 02 05 53 68 6F 72 74 08 05 2E 75 FFFFFFC0 00
   7D 10 03 0F 30 79 08 06 7F 00 FFFFFF84 01 FFFFFF81 00 01 10
   77 72 61 70 42 6F 6F 6C 65 61 6E 41 72 72 61 79
   14 04 FFFFFF81 01 FFFFFF81 05 10 04 1B 20 FFFFFF81 02 10 03 0F FFFFFF81
   03 09 03 FFFFFF81 04 02 02 07 42 6F 6F 6C 65 61 6E 08
   06 2E 7E FFFFFFC0 00 FFFFFF81 06 10 04 0F 30 FFFFFF81 02 08 07 FFFFFF81
   08 00 FFFFFF84 01 FFFFFF81 09 01 0D 77 72 61 70 55 6E 69 74
   41 72 72 61 79 14 04 FFFFFF81 0A FFFFFF81 0E 10 04 1B 20 FFFFFF81
   0B 10 03 0F FFFFFF81 0C 09 03 FFFFFF81 0D 02 02 04 55 6E 69
   74 08 07 2E FFFFFF81 07 FFFFFFC0 00 FFFFFF81 0F 10 04 0F 30 FFFFFF81 0B
   08 07 FFFFFF81 11 00 FFFFFF84 01 FFFFFF81 12 01 0A 77 72 61 70 53
   74 72 69 6E 67 14 04 FFFFFF81 13 FFFFFF81 19 10 04 FFFFFF81 14 FFFFFF81
   17 0D 02 FFFFFF81 15 0A 03 FFFFFF81 16 1E 01 09 69 6D 6D 75
   74 61 62 6C 65 09 04 FFFFFF81 18 FFFFFF81 15 02 0D 57 72 61
   70 70 65 64 53 74 72 69 6E 67 08 08 FFFFFF81 1A FFFFFF81 10
   FFFFFFC0 00 FFFFFF81 1B 01 01 73 10 04 FFFFFF81 1C FFFFFF81 1F 0E 03 0F
   FFFFFF81 1D 09 03 FFFFFF81 1E 02 01 06 50 72 65 64 65 66 09
   04 FFFFFF81 20 FFFFFF81 21 02 06 53 74 72 69 6E 67 0A 03 FFFFFF81
   1E 02 08 07 FFFFFF81 23 00 FFFFFF84 01 FFFFFF81 24 01 0C 75 6E 77
   72 61 70 53 74 72 69 6E 67 14 04 FFFFFF81 1B FFFFFF81 25 08
   08 FFFFFF81 26 FFFFFF81 22 FFFFFFC0 00 FFFFFF81 13 01 02 77 73 08 07 FFFFFF81
   28 00 FFFFFF84 01 FFFFFF81 29 01 1A 66 61 6C 6C 62 61 63 6B
   53 74 72 69 6E 67 43 61 6E 42 75 69 6C 64 46 72
   6F 6D 15 04 FFFFFF81 2A FFFFFF81 31 10 0A FFFFFF81 2B FFFFFF81 2E FFFFFF81 1B
   FFFFFF81 30 FFFFFF81 32 0D 02 FFFFFF81 2C 0A 03 FFFFFF81 2D 1E 01 07 67
   65 6E 65 72 69 63 09 04 FFFFFF81 2F FFFFFF81 2C 02 0C 43 61
   6E 42 75 69 6C 64 46 72 6F 6D 10 03 23 FFFFFF81 31 04
   09 25 FFFFFF81 27 FFFFFF84 FFFFFF80 FFFFFF80 FFFFFFC2 00 26 10 06 FFFFFF81 14 FFFFFF81 33
   FFFFFF81 30 09 04 FFFFFF81 34 FFFFFF81 15 02 0A 49 6E 64 65 78 65
   64 53 65 71 08 07 FFFFFF81 36 00 FFFFFF84 00 FFFFFF81 37 01 09 77
   72 61 70 41 72 72 61 79 15 04 FFFFFF81 38 FFFFFF81 3B 14 04
   FFFFFF81 39 FFFFFF81 3C 10 04 1B 20 FFFFFF81 3A 10 03 23 FFFFFF81 3B 04
   09 25 FFFFFF81 35 FFFFFF84 FFFFFF80 FFFFFF80 FFFFFFC2 00 39 08 07 2E FFFFFF81 35 FFFFFFC0
   00 FFFFFF81 3D 10 04 0F 30 FFFFFF81 3A 08 07 FFFFFF81 36 00 FFFFFF84 00
   FFFFFF81 3F 14 03 42 FFFFFF81 40 08 06 2E FFFFFF81 3E FFFFFFC0 00 47 08
   07 FFFFFF81 36 00 FFFFFF84 00 FFFFFF81 42 14 03 4B FFFFFF81 43 08 06 2E
   FFFFFF81 41 FFFFFFC0 00 50 08 07 FFFFFF81 36 00 FFFFFF84 00 FFFFFF81 45 14 03
   54 FFFFFF81 46 08 06 2E FFFFFF81 44 FFFFFFC0 00 59 08 07 FFFFFF81 36 00
   FFFFFF84 00 FFFFFF81 48 14 03 5D FFFFFF81 49 08 06 2E FFFFFF81 47 FFFFFFC0 00
   62 08 07 FFFFFF81 36 00 FFFFFF84 00 FFFFFF81 4B 14 03 66 FFFFFF81 4C 08
   06 2E FFFFFF81 4A FFFFFFC0 00 6B 08 07 FFFFFF81 36 00 FFFFFF84 00 FFFFFF81 4E
   14 03 6F FFFFFF81 4F 08 06 2E FFFFFF81 4D FFFFFFC0 00 74 08 07 FFFFFF81
   36 00 FFFFFF84 00 FFFFFF81 51 14 03 78 FFFFFF81 52 08 06 2E FFFFFF81 50
   FFFFFFC0 00 7D 08 07 FFFFFF81 36 00 FFFFFF84 00 FFFFFF81 54 14 04 FFFFFF81 01
   FFFFFF81 55 08 07 2E FFFFFF81 53 FFFFFFC0 00 FFFFFF81 06 08 07 FFFFFF81 36 00
   FFFFFF84 00 FFFFFF81 57 14 04 FFFFFF81 0A FFFFFF81 58 08 07 2E FFFFFF81 56 FFFFFFC0
   00 FFFFFF81 0F 
  InnerClass: 
   public final ofInt=class scala/collection/mutable/WrappedArray$ofInt of class scala/collection/mutable/WrappedArray
   public final ofRef=class scala/collection/mutable/WrappedArray$ofRef of class scala/collection/mutable/WrappedArray
   public final ofUnit=class scala/collection/mutable/WrappedArray$ofUnit of class scala/collection/mutable/WrappedArray
   public final ofByte=class scala/collection/mutable/WrappedArray$ofByte of class scala/collection/mutable/WrappedArray
   public final ofChar=class scala/collection/mutable/WrappedArray$ofChar of class scala/collection/mutable/WrappedArray
   public final ofLong=class scala/collection/mutable/WrappedArray$ofLong of class scala/collection/mutable/WrappedArray
   public final ofShort=class scala/collection/mutable/WrappedArray$ofShort of class scala/collection/mutable/WrappedArray
   public final ofFloat=class scala/collection/mutable/WrappedArray$ofFloat of class scala/collection/mutable/WrappedArray
   public final ofDouble=class scala/collection/mutable/WrappedArray$ofDouble of class scala/collection/mutable/WrappedArray
   public final ofBoolean=class scala/collection/mutable/WrappedArray$ofBoolean of class scala/collection/mutable/WrappedArray
   public final $anon$1=class scala/LowPriorityImplicits$$anon$1 of class scala/LowPriorityImplicits
  minor version: 0
  major version: 49
  Constant pool:
Asciz	SourceFile;
Asciz	LowPriorityImplicits.scala;
Asciz	genericWrapArray;
Asciz	(Ljava/lang/Object;)Lscala/collection/mutable/WrappedArray;;
Asciz	Code;
Asciz	LineNumberTable;
Asciz	java/lang/Object;
class	java/lang/Object
Asciz	equals;
Asciz	(Ljava/lang/Object;)Z;
NameAndType	equals:(Ljava/lang/Object;)Z
Method	java/lang/Object.equals:(Ljava/lang/Object;)Z
Asciz	scala/collection/mutable/WrappedArray$;
class	scala/collection/mutable/WrappedArray$
Asciz	MODULE$;
Asciz	Lscala/collection/mutable/WrappedArray$;;
NameAndType	MODULE$:Lscala/collection/mutable/WrappedArray$;
Field	scala/collection/mutable/WrappedArray$.MODULE$:Lscala/collection/mutable/WrappedArray$;
Asciz	make;
NameAndType	make:(Ljava/lang/Object;)Lscala/collection/mutable/WrappedArray;
Method	scala/collection/mutable/WrappedArray$.make:(Ljava/lang/Object;)Lscala/collection/mutable/WrappedArray;
Asciz	this;
Asciz	Lscala/LowPriorityImplicits;;
Asciz	xs;
Asciz	Ljava/lang/Object;;
Asciz	LocalVariableTable;
Asciz	<T:Ljava/lang/Object;>([TT;)Lscala/collection/mutable/WrappedArray<TT;>;;
Asciz	Signature;
Asciz	wrapRefArray;
Asciz	([Ljava/lang/Object;)Lscala/collection/mutable/WrappedArray;;
Asciz	scala/collection/mutable/WrappedArray$ofRef;
class	scala/collection/mutable/WrappedArray$ofRef
Asciz	<init>;
Asciz	([Ljava/lang/Object;)V;
NameAndType	"<init>":([Ljava/lang/Object;)V
Method	scala/collection/mutable/WrappedArray$ofRef."<init>":([Ljava/lang/Object;)V
Asciz	[Ljava/lang/Object;;
Asciz	wrapIntArray;
Asciz	([I)Lscala/collection/mutable/WrappedArray;;
Asciz	scala/collection/mutable/WrappedArray$ofInt;
class	scala/collection/mutable/WrappedArray$ofInt
Asciz	([I)V;
NameAndType	"<init>":([I)V
Method	scala/collection/mutable/WrappedArray$ofInt."<init>":([I)V
Asciz	[I;
Asciz	([I)Lscala/collection/mutable/WrappedArray<Ljava/lang/Integer;>;;
Asciz	wrapDoubleArray;
Asciz	([D)Lscala/collection/mutable/WrappedArray;;
Asciz	scala/collection/mutable/WrappedArray$ofDouble;
class	scala/collection/mutable/WrappedArray$ofDouble
Asciz	([D)V;
NameAndType	"<init>":([D)V
Method	scala/collection/mutable/WrappedArray$ofDouble."<init>":([D)V
Asciz	[D;
Asciz	([D)Lscala/collection/mutable/WrappedArray<Ljava/lang/Double;>;;
Asciz	wrapLongArray;
Asciz	([J)Lscala/collection/mutable/WrappedArray;;
Asciz	scala/collection/mutable/WrappedArray$ofLong;
class	scala/collection/mutable/WrappedArray$ofLong
Asciz	([J)V;
NameAndType	"<init>":([J)V
Method	scala/collection/mutable/WrappedArray$ofLong."<init>":([J)V
Asciz	[J;
Asciz	([J)Lscala/collection/mutable/WrappedArray<Ljava/lang/Long;>;;
Asciz	wrapFloatArray;
Asciz	([F)Lscala/collection/mutable/WrappedArray;;
Asciz	scala/collection/mutable/WrappedArray$ofFloat;
class	scala/collection/mutable/WrappedArray$ofFloat
Asciz	([F)V;
NameAndType	"<init>":([F)V
Method	scala/collection/mutable/WrappedArray$ofFloat."<init>":([F)V
Asciz	[F;
Asciz	([F)Lscala/collection/mutable/WrappedArray<Ljava/lang/Float;>;;
Asciz	wrapCharArray;
Asciz	([C)Lscala/collection/mutable/WrappedArray;;
Asciz	scala/collection/mutable/WrappedArray$ofChar;
class	scala/collection/mutable/WrappedArray$ofChar
Asciz	([C)V;
NameAndType	"<init>":([C)V
Method	scala/collection/mutable/WrappedArray$ofChar."<init>":([C)V
Asciz	[C;
Asciz	([C)Lscala/collection/mutable/WrappedArray<Ljava/lang/Character;>;;
Asciz	wrapByteArray;
Asciz	([B)Lscala/collection/mutable/WrappedArray;;
Asciz	scala/collection/mutable/WrappedArray$ofByte;
class	scala/collection/mutable/WrappedArray$ofByte
Asciz	([B)V;
NameAndType	"<init>":([B)V
Method	scala/collection/mutable/WrappedArray$ofByte."<init>":([B)V
Asciz	[B;
Asciz	([B)Lscala/collection/mutable/WrappedArray<Ljava/lang/Byte;>;;
Asciz	wrapShortArray;
Asciz	([S)Lscala/collection/mutable/WrappedArray;;
Asciz	scala/collection/mutable/WrappedArray$ofShort;
class	scala/collection/mutable/WrappedArray$ofShort
Asciz	([S)V;
NameAndType	"<init>":([S)V
Method	scala/collection/mutable/WrappedArray$ofShort."<init>":([S)V
Asciz	[S;
Asciz	([S)Lscala/collection/mutable/WrappedArray<Ljava/lang/Short;>;;
Asciz	wrapBooleanArray;
Asciz	([Z)Lscala/collection/mutable/WrappedArray;;
Asciz	scala/collection/mutable/WrappedArray$ofBoolean;
class	scala/collection/mutable/WrappedArray$ofBoolean
Asciz	([Z)V;
NameAndType	"<init>":([Z)V
Method	scala/collection/mutable/WrappedArray$ofBoolean."<init>":([Z)V
Asciz	[Z;
Asciz	([Z)Lscala/collection/mutable/WrappedArray<Ljava/lang/Boolean;>;;
Asciz	wrapUnitArray;
Asciz	([Lscala/runtime/BoxedUnit;)Lscala/collection/mutable/WrappedArray;;
Asciz	scala/collection/mutable/WrappedArray$ofUnit;
class	scala/collection/mutable/WrappedArray$ofUnit
Asciz	([Lscala/runtime/BoxedUnit;)V;
NameAndType	"<init>":([Lscala/runtime/BoxedUnit;)V
Method	scala/collection/mutable/WrappedArray$ofUnit."<init>":([Lscala/runtime/BoxedUnit;)V
Asciz	[Lscala/runtime/BoxedUnit;;
Asciz	([Lscala/runtime/BoxedUnit;)Lscala/collection/mutable/WrappedArray<Ljava/lang/Object;>;;
Asciz	wrapString;
Asciz	(Ljava/lang/String;)Lscala/collection/immutable/WrappedString;;
Asciz	scala/collection/immutable/WrappedString;
class	scala/collection/immutable/WrappedString
Asciz	(Ljava/lang/String;)V;
NameAndType	"<init>":(Ljava/lang/String;)V
Method	scala/collection/immutable/WrappedString."<init>":(Ljava/lang/String;)V
Asciz	s;
Asciz	Ljava/lang/String;;
Asciz	unwrapString;
Asciz	(Lscala/collection/immutable/WrappedString;)Ljava/lang/String;;
Asciz	self;
Asciz	()Ljava/lang/String;;
NameAndType	self:()Ljava/lang/String;
Method	scala/collection/immutable/WrappedString.self:()Ljava/lang/String;
Asciz	ws;
Asciz	Lscala/collection/immutable/WrappedString;;
Asciz	fallbackStringCanBuildFrom;
Asciz	()Lscala/collection/generic/CanBuildFrom;;
Asciz	scala/LowPriorityImplicits$$anon$1;
class	scala/LowPriorityImplicits$$anon$1
Asciz	(Lscala/LowPriorityImplicits;)V;
NameAndType	"<init>":(Lscala/LowPriorityImplicits;)V
Method	scala/LowPriorityImplicits$$anon$1."<init>":(Lscala/LowPriorityImplicits;)V
Asciz	<T:Ljava/lang/Object;>()Lscala/collection/generic/CanBuildFrom<Ljava/lang/String;TT;Lscala/collection/immutable/IndexedSeq<TT;>;>;;
Asciz	wrapArray;
Asciz	()V;
NameAndType	"<init>":()V
Method	java/lang/Object."<init>":()V
Asciz	ScalaSig;
Asciz	InnerClasses;
Asciz	scala/collection/mutable/WrappedArray;
class	scala/collection/mutable/WrappedArray
Asciz	ofInt;
Asciz	ofRef;
Asciz	ofUnit;
Asciz	ofByte;
Asciz	ofChar;
Asciz	ofLong;
Asciz	ofShort;
Asciz	ofFloat;
Asciz	ofDouble;
Asciz	ofBoolean;
Asciz	scala/LowPriorityImplicits;
class	scala/LowPriorityImplicits
Asciz	$anon$1;
Asciz	scala/ScalaObject;
class	scala/ScalaObject

{
public scala.collection.mutable.WrappedArray genericWrapArray(java.lang.Object);
  Signature: (Ljava/lang/Object;)Lscala/collection/mutable/WrappedArray;
  Code:
   Stack=2, Locals=2, Args_size=2
	aload_1
	dup
	pop
	ifnull	l1 // aconst_null
	aload_1
	aconst_null
	invokevirtual	Method java/lang/Object.equals:(Ljava/lang/Object;)Z
	ifeq	l2 // getstatic
l1	aconst_null
	goto	l3 // areturn
l2	getstatic	Field scala/collection/mutable/WrappedArray$.MODULE$:Lscala/collection/mutable/WrappedArray$;
	aload_1
	invokevirtual	Method scala/collection/mutable/WrappedArray$.make:(Ljava/lang/Object;)Lscala/collection/mutable/WrappedArray;
l3	areturn
  Labels:
   	l1 = 14 // aconst_null
   	l2 = 18 // getstatic
   	l3 = 25 // areturn
  LocalVariableTable: 
   Start  Length  Slot  Name   Signature
   0      26      0    this       Lscala/LowPriorityImplicits;
   0      26      1    xs       Ljava/lang/Object;

  Signature: length = 0x2
   00 1B 

public scala.collection.mutable.WrappedArray wrapRefArray(java.lang.Object[]);
  Signature: ([Ljava/lang/Object;)Lscala/collection/mutable/WrappedArray;
  Code:
   Stack=3, Locals=2, Args_size=2
	aload_1
	aconst_null
	if_acmpeq	l1 // aconst_null
	new	class scala/collection/mutable/WrappedArray$ofRef
	dup
	aload_1
	invokespecial	Method scala/collection/mutable/WrappedArray$ofRef."<init>":([Ljava/lang/Object;)V
	goto	l2 // areturn
l1	aconst_null
l2	areturn
  Labels:
   	l1 = 16 // aconst_null
   	l2 = 17 // areturn
  LocalVariableTable: 
   Start  Length  Slot  Name   Signature
   0      18      0    this       Lscala/LowPriorityImplicits;
   0      18      1    xs       [Ljava/lang/Object;

  Signature: length = 0x2
   00 1B 

public scala.collection.mutable.WrappedArray wrapIntArray(int[]);
  Signature: ([I)Lscala/collection/mutable/WrappedArray;
  Code:
   Stack=3, Locals=2, Args_size=2
	aload_1
	aconst_null
	if_acmpeq	l1 // aconst_null
	new	class scala/collection/mutable/WrappedArray$ofInt
	dup
	aload_1
	invokespecial	Method scala/collection/mutable/WrappedArray$ofInt."<init>":([I)V
	goto	l2 // areturn
l1	aconst_null
l2	areturn
  Labels:
   	l1 = 16 // aconst_null
   	l2 = 17 // areturn
  LocalVariableTable: 
   Start  Length  Slot  Name   Signature
   0      18      0    this       Lscala/LowPriorityImplicits;
   0      18      1    xs       [I

  Signature: length = 0x2
   00 2E 

public scala.collection.mutable.WrappedArray wrapDoubleArray(double[]);
  Signature: ([D)Lscala/collection/mutable/WrappedArray;
  Code:
   Stack=3, Locals=2, Args_size=2
	aload_1
	aconst_null
	if_acmpeq	l1 // aconst_null
	new	class scala/collection/mutable/WrappedArray$ofDouble
	dup
	aload_1
	invokespecial	Method scala/collection/mutable/WrappedArray$ofDouble."<init>":([D)V
	goto	l2 // areturn
l1	aconst_null
l2	areturn
  Labels:
   	l1 = 16 // aconst_null
   	l2 = 17 // areturn
  LocalVariableTable: 
   Start  Length  Slot  Name   Signature
   0      18      0    this       Lscala/LowPriorityImplicits;
   0      18      1    xs       [D

  Signature: length = 0x2
   00 37 

public scala.collection.mutable.WrappedArray wrapLongArray(long[]);
  Signature: ([J)Lscala/collection/mutable/WrappedArray;
  Code:
   Stack=3, Locals=2, Args_size=2
	aload_1
	aconst_null
	if_acmpeq	l1 // aconst_null
	new	class scala/collection/mutable/WrappedArray$ofLong
	dup
	aload_1
	invokespecial	Method scala/collection/mutable/WrappedArray$ofLong."<init>":([J)V
	goto	l2 // areturn
l1	aconst_null
l2	areturn
  Labels:
   	l1 = 16 // aconst_null
   	l2 = 17 // areturn
  LocalVariableTable: 
   Start  Length  Slot  Name   Signature
   0      18      0    this       Lscala/LowPriorityImplicits;
   0      18      1    xs       [J

  Signature: length = 0x2
   00 40 

public scala.collection.mutable.WrappedArray wrapFloatArray(float[]);
  Signature: ([F)Lscala/collection/mutable/WrappedArray;
  Code:
   Stack=3, Locals=2, Args_size=2
	aload_1
	aconst_null
	if_acmpeq	l1 // aconst_null
	new	class scala/collection/mutable/WrappedArray$ofFloat
	dup
	aload_1
	invokespecial	Method scala/collection/mutable/WrappedArray$ofFloat."<init>":([F)V
	goto	l2 // areturn
l1	aconst_null
l2	areturn
  Labels:
   	l1 = 16 // aconst_null
   	l2 = 17 // areturn
  LocalVariableTable: 
   Start  Length  Slot  Name   Signature
   0      18      0    this       Lscala/LowPriorityImplicits;
   0      18      1    xs       [F

  Signature: length = 0x2
   00 49 

public scala.collection.mutable.WrappedArray wrapCharArray(char[]);
  Signature: ([C)Lscala/collection/mutable/WrappedArray;
  Code:
   Stack=3, Locals=2, Args_size=2
	aload_1
	aconst_null
	if_acmpeq	l1 // aconst_null
	new	class scala/collection/mutable/WrappedArray$ofChar
	dup
	aload_1
	invokespecial	Method scala/collection/mutable/WrappedArray$ofChar."<init>":([C)V
	goto	l2 // areturn
l1	aconst_null
l2	areturn
  Labels:
   	l1 = 16 // aconst_null
   	l2 = 17 // areturn
  LocalVariableTable: 
   Start  Length  Slot  Name   Signature
   0      18      0    this       Lscala/LowPriorityImplicits;
   0      18      1    xs       [C

  Signature: length = 0x2
   00 52 

public scala.collection.mutable.WrappedArray wrapByteArray(byte[]);
  Signature: ([B)Lscala/collection/mutable/WrappedArray;
  Code:
   Stack=3, Locals=2, Args_size=2
	aload_1
	aconst_null
	if_acmpeq	l1 // aconst_null
	new	class scala/collection/mutable/WrappedArray$ofByte
	dup
	aload_1
	invokespecial	Method scala/collection/mutable/WrappedArray$ofByte."<init>":([B)V
	goto	l2 // areturn
l1	aconst_null
l2	areturn
  Labels:
   	l1 = 16 // aconst_null
   	l2 = 17 // areturn
  LocalVariableTable: 
   Start  Length  Slot  Name   Signature
   0      18      0    this       Lscala/LowPriorityImplicits;
   0      18      1    xs       [B

  Signature: length = 0x2
   00 5B 

public scala.collection.mutable.WrappedArray wrapShortArray(short[]);
  Signature: ([S)Lscala/collection/mutable/WrappedArray;
  Code:
   Stack=3, Locals=2, Args_size=2
	aload_1
	aconst_null
	if_acmpeq	l1 // aconst_null
	new	class scala/collection/mutable/WrappedArray$ofShort
	dup
	aload_1
	invokespecial	Method scala/collection/mutable/WrappedArray$ofShort."<init>":([S)V
	goto	l2 // areturn
l1	aconst_null
l2	areturn
  Labels:
   	l1 = 16 // aconst_null
   	l2 = 17 // areturn
  LocalVariableTable: 
   Start  Length  Slot  Name   Signature
   0      18      0    this       Lscala/LowPriorityImplicits;
   0      18      1    xs       [S

  Signature: length = 0x2
   00 64 

public scala.collection.mutable.WrappedArray wrapBooleanArray(boolean[]);
  Signature: ([Z)Lscala/collection/mutable/WrappedArray;
  Code:
   Stack=3, Locals=2, Args_size=2
	aload_1
	aconst_null
	if_acmpeq	l1 // aconst_null
	new	class scala/collection/mutable/WrappedArray$ofBoolean
	dup
	aload_1
	invokespecial	Method scala/collection/mutable/WrappedArray$ofBoolean."<init>":([Z)V
	goto	l2 // areturn
l1	aconst_null
l2	areturn
  Labels:
   	l1 = 16 // aconst_null
   	l2 = 17 // areturn
  LocalVariableTable: 
   Start  Length  Slot  Name   Signature
   0      18      0    this       Lscala/LowPriorityImplicits;
   0      18      1    xs       [Z

  Signature: length = 0x2
   00 6D 

public scala.collection.mutable.WrappedArray wrapUnitArray(scala.runtime.BoxedUnit[]);
  Signature: ([Lscala/runtime/BoxedUnit;)Lscala/collection/mutable/WrappedArray;
  Code:
   Stack=3, Locals=2, Args_size=2
	aload_1
	aconst_null
	if_acmpeq	l1 // aconst_null
	new	class scala/collection/mutable/WrappedArray$ofUnit
	dup
	aload_1
	invokespecial	Method scala/collection/mutable/WrappedArray$ofUnit."<init>":([Lscala/runtime/BoxedUnit;)V
	goto	l2 // areturn
l1	aconst_null
l2	areturn
  Labels:
   	l1 = 16 // aconst_null
   	l2 = 17 // areturn
  LocalVariableTable: 
   Start  Length  Slot  Name   Signature
   0      18      0    this       Lscala/LowPriorityImplicits;
   0      18      1    xs       [Lscala/runtime/BoxedUnit;

  Signature: length = 0x2
   00 76 

public scala.collection.immutable.WrappedString wrapString(java.lang.String);
  Signature: (Ljava/lang/String;)Lscala/collection/immutable/WrappedString;
  Code:
   Stack=3, Locals=2, Args_size=2
	aload_1
	dup
	pop
	ifnull	l1 // aconst_null
	aload_1
	aconst_null
	invokevirtual	Method java/lang/Object.equals:(Ljava/lang/Object;)Z
	ifeq	l2 // new
l1	aconst_null
	goto	l3 // areturn
l2	new	class scala/collection/immutable/WrappedString
	dup
	aload_1
	invokespecial	Method scala/collection/immutable/WrappedString."<init>":(Ljava/lang/String;)V
l3	areturn
  Labels:
   	l1 = 14 // aconst_null
   	l2 = 18 // new
   	l3 = 26 // areturn
  LocalVariableTable: 
   Start  Length  Slot  Name   Signature
   0      27      0    this       Lscala/LowPriorityImplicits;
   0      27      1    s       Ljava/lang/String;


public java.lang.String unwrapString(scala.collection.immutable.WrappedString);
  Signature: (Lscala/collection/immutable/WrappedString;)Ljava/lang/String;
  Code:
   Stack=2, Locals=2, Args_size=2
	aload_1
	dup
	pop
	ifnull	l1 // aconst_null
	aload_1
	aconst_null
	invokevirtual	Method java/lang/Object.equals:(Ljava/lang/Object;)Z
	ifeq	l2 // aload_1
l1	aconst_null
	goto	l3 // areturn
l2	aload_1
	invokevirtual	Method scala/collection/immutable/WrappedString.self:()Ljava/lang/String;
l3	areturn
  Labels:
   	l1 = 14 // aconst_null
   	l2 = 18 // aload_1
   	l3 = 22 // areturn
  LocalVariableTable: 
   Start  Length  Slot  Name   Signature
   0      23      0    this       Lscala/LowPriorityImplicits;
   0      23      1    ws       Lscala/collection/immutable/WrappedString;


public scala.collection.generic.CanBuildFrom fallbackStringCanBuildFrom();
  Signature: ()Lscala/collection/generic/CanBuildFrom;
  Code:
   Stack=3, Locals=1, Args_size=1
	new	class scala/LowPriorityImplicits$$anon$1
	dup
	aload_0
	invokespecial	Method scala/LowPriorityImplicits$$anon$1."<init>":(Lscala/LowPriorityImplicits;)V
	areturn
  Labels:
  Signature: length = 0x2
   00 FFFFFF8F 

public scala.collection.mutable.WrappedArray wrapArray(java.lang.Object[]);
  Signature: ([Ljava/lang/Object;)Lscala/collection/mutable/WrappedArray;
  Code:
   Stack=3, Locals=2, Args_size=2
	new	class scala/collection/mutable/WrappedArray$ofRef
	dup
	aload_1
	invokespecial	Method scala/collection/mutable/WrappedArray$ofRef."<init>":([Ljava/lang/Object;)V
	areturn
  Labels:
  LocalVariableTable: 
   Start  Length  Slot  Name   Signature
   0      9      0    this       Lscala/LowPriorityImplicits;
   0      9      1    xs       [Ljava/lang/Object;

  Signature: length = 0x2
   00 1B 

public scala.collection.mutable.WrappedArray wrapArray(int[]);
  Signature: ([I)Lscala/collection/mutable/WrappedArray;
  Code:
   Stack=3, Locals=2, Args_size=2
	new	class scala/collection/mutable/WrappedArray$ofInt
	dup
	aload_1
	invokespecial	Method scala/collection/mutable/WrappedArray$ofInt."<init>":([I)V
	areturn
  Labels:
  LocalVariableTable: 
   Start  Length  Slot  Name   Signature
   0      9      0    this       Lscala/LowPriorityImplicits;
   0      9      1    xs       [I

  Signature: length = 0x2
   00 2E 

public scala.collection.mutable.WrappedArray wrapArray(double[]);
  Signature: ([D)Lscala/collection/mutable/WrappedArray;
  Code:
   Stack=3, Locals=2, Args_size=2
	new	class scala/collection/mutable/WrappedArray$ofDouble
	dup
	aload_1
	invokespecial	Method scala/collection/mutable/WrappedArray$ofDouble."<init>":([D)V
	areturn
  Labels:
  LocalVariableTable: 
   Start  Length  Slot  Name   Signature
   0      9      0    this       Lscala/LowPriorityImplicits;
   0      9      1    xs       [D

  Signature: length = 0x2
   00 37 

public scala.collection.mutable.WrappedArray wrapArray(long[]);
  Signature: ([J)Lscala/collection/mutable/WrappedArray;
  Code:
   Stack=3, Locals=2, Args_size=2
	new	class scala/collection/mutable/WrappedArray$ofLong
	dup
	aload_1
	invokespecial	Method scala/collection/mutable/WrappedArray$ofLong."<init>":([J)V
	areturn
  Labels:
  LocalVariableTable: 
   Start  Length  Slot  Name   Signature
   0      9      0    this       Lscala/LowPriorityImplicits;
   0      9      1    xs       [J

  Signature: length = 0x2
   00 40 

public scala.collection.mutable.WrappedArray wrapArray(float[]);
  Signature: ([F)Lscala/collection/mutable/WrappedArray;
  Code:
   Stack=3, Locals=2, Args_size=2
	new	class scala/collection/mutable/WrappedArray$ofFloat
	dup
	aload_1
	invokespecial	Method scala/collection/mutable/WrappedArray$ofFloat."<init>":([F)V
	areturn
  Labels:
  LocalVariableTable: 
   Start  Length  Slot  Name   Signature
   0      9      0    this       Lscala/LowPriorityImplicits;
   0      9      1    xs       [F

  Signature: length = 0x2
   00 49 

public scala.collection.mutable.WrappedArray wrapArray(char[]);
  Signature: ([C)Lscala/collection/mutable/WrappedArray;
  Code:
   Stack=3, Locals=2, Args_size=2
	new	class scala/collection/mutable/WrappedArray$ofChar
	dup
	aload_1
	invokespecial	Method scala/collection/mutable/WrappedArray$ofChar."<init>":([C)V
	areturn
  Labels:
  LocalVariableTable: 
   Start  Length  Slot  Name   Signature
   0      9      0    this       Lscala/LowPriorityImplicits;
   0      9      1    xs       [C

  Signature: length = 0x2
   00 52 

public scala.collection.mutable.WrappedArray wrapArray(byte[]);
  Signature: ([B)Lscala/collection/mutable/WrappedArray;
  Code:
   Stack=3, Locals=2, Args_size=2
	new	class scala/collection/mutable/WrappedArray$ofByte
	dup
	aload_1
	invokespecial	Method scala/collection/mutable/WrappedArray$ofByte."<init>":([B)V
	areturn
  Labels:
  LocalVariableTable: 
   Start  Length  Slot  Name   Signature
   0      9      0    this       Lscala/LowPriorityImplicits;
   0      9      1    xs       [B

  Signature: length = 0x2
   00 5B 

public scala.collection.mutable.WrappedArray wrapArray(short[]);
  Signature: ([S)Lscala/collection/mutable/WrappedArray;
  Code:
   Stack=3, Locals=2, Args_size=2
	new	class scala/collection/mutable/WrappedArray$ofShort
	dup
	aload_1
	invokespecial	Method scala/collection/mutable/WrappedArray$ofShort."<init>":([S)V
	areturn
  Labels:
  LocalVariableTable: 
   Start  Length  Slot  Name   Signature
   0      9      0    this       Lscala/LowPriorityImplicits;
   0      9      1    xs       [S

  Signature: length = 0x2
   00 64 

public scala.collection.mutable.WrappedArray wrapArray(boolean[]);
  Signature: ([Z)Lscala/collection/mutable/WrappedArray;
  Code:
   Stack=3, Locals=2, Args_size=2
	new	class scala/collection/mutable/WrappedArray$ofBoolean
	dup
	aload_1
	invokespecial	Method scala/collection/mutable/WrappedArray$ofBoolean."<init>":([Z)V
	areturn
  Labels:
  LocalVariableTable: 
   Start  Length  Slot  Name   Signature
   0      9      0    this       Lscala/LowPriorityImplicits;
   0      9      1    xs       [Z

  Signature: length = 0x2
   00 6D 

public scala.collection.mutable.WrappedArray wrapArray(scala.runtime.BoxedUnit[]);
  Signature: ([Lscala/runtime/BoxedUnit;)Lscala/collection/mutable/WrappedArray;
  Code:
   Stack=3, Locals=2, Args_size=2
	new	class scala/collection/mutable/WrappedArray$ofUnit
	dup
	aload_1
	invokespecial	Method scala/collection/mutable/WrappedArray$ofUnit."<init>":([Lscala/runtime/BoxedUnit;)V
	areturn
  Labels:
  LocalVariableTable: 
   Start  Length  Slot  Name   Signature
   0      9      0    this       Lscala/LowPriorityImplicits;
   0      9      1    xs       [Lscala/runtime/BoxedUnit;

  Signature: length = 0x2
   00 76 

public scala.LowPriorityImplicits();
  Signature: ()V
  Code:
   Stack=1, Locals=1, Args_size=1
	aload_0
	invokespecial	Method java/lang/Object."<init>":()V
	return
  Labels:

}

