Compiled from "MathCommon.scala"
public abstract class scala.MathCommon$class extends java.lang.Object
  SourceFile: "MathCommon.scala"
  Scala: length = 0x
   
  minor version: 0
  major version: 49
  Constant pool:
Asciz	SourceFile;
Asciz	MathCommon.scala;
Asciz	random;
Asciz	(Lscala/MathCommon;)D;
Asciz	Code;
Asciz	java/lang/Math;
class	java/lang/Math
Asciz	()D;
NameAndType	random:()D
Method	java/lang/Math.random:()D
Asciz	LineNumberTable;
Asciz	$this;
Asciz	Lscala/MathCommon;;
Asciz	LocalVariableTable;
Asciz	sin;
Asciz	(Lscala/MathCommon;D)D;
Asciz	(D)D;
NameAndType	sin:(D)D
Method	java/lang/Math.sin:(D)D
Asciz	x;
Asciz	D;
Asciz	cos;
NameAndType	cos:(D)D
Method	java/lang/Math.cos:(D)D
Asciz	tan;
NameAndType	tan:(D)D
Method	java/lang/Math.tan:(D)D
Asciz	asin;
NameAndType	asin:(D)D
Method	java/lang/Math.asin:(D)D
Asciz	acos;
NameAndType	acos:(D)D
Method	java/lang/Math.acos:(D)D
Asciz	atan;
NameAndType	atan:(D)D
Method	java/lang/Math.atan:(D)D
Asciz	toRadians;
NameAndType	toRadians:(D)D
Method	java/lang/Math.toRadians:(D)D
Asciz	toDegrees;
NameAndType	toDegrees:(D)D
Method	java/lang/Math.toDegrees:(D)D
Asciz	exp;
NameAndType	exp:(D)D
Method	java/lang/Math.exp:(D)D
Asciz	log;
NameAndType	log:(D)D
Method	java/lang/Math.log:(D)D
Asciz	sqrt;
NameAndType	sqrt:(D)D
Method	java/lang/Math.sqrt:(D)D
Asciz	IEEEremainder;
Asciz	(Lscala/MathCommon;DD)D;
Asciz	(DD)D;
NameAndType	IEEEremainder:(DD)D
Method	java/lang/Math.IEEEremainder:(DD)D
Asciz	y;
Asciz	ceil;
NameAndType	ceil:(D)D
Method	java/lang/Math.ceil:(D)D
Asciz	floor;
NameAndType	floor:(D)D
Method	java/lang/Math.floor:(D)D
Asciz	rint;
NameAndType	rint:(D)D
Method	java/lang/Math.rint:(D)D
Asciz	atan2;
NameAndType	atan2:(DD)D
Method	java/lang/Math.atan2:(DD)D
Asciz	pow;
NameAndType	pow:(DD)D
Method	java/lang/Math.pow:(DD)D
Asciz	round;
Asciz	(Lscala/MathCommon;F)I;
Asciz	(F)I;
NameAndType	round:(F)I
Method	java/lang/Math.round:(F)I
Asciz	F;
Asciz	(Lscala/MathCommon;D)J;
Asciz	(D)J;
NameAndType	round:(D)J
Method	java/lang/Math.round:(D)J
Asciz	abs;
Asciz	(Lscala/MathCommon;I)I;
Asciz	(I)I;
NameAndType	abs:(I)I
Method	java/lang/Math.abs:(I)I
Asciz	I;
Asciz	(Lscala/MathCommon;J)J;
Asciz	(J)J;
NameAndType	abs:(J)J
Method	java/lang/Math.abs:(J)J
Asciz	J;
Asciz	(Lscala/MathCommon;F)F;
Asciz	(F)F;
NameAndType	abs:(F)F
Method	java/lang/Math.abs:(F)F
NameAndType	abs:(D)D
Method	java/lang/Math.abs:(D)D
Asciz	max;
Asciz	(Lscala/MathCommon;II)I;
Asciz	(II)I;
NameAndType	max:(II)I
Method	java/lang/Math.max:(II)I
Asciz	(Lscala/MathCommon;JJ)J;
Asciz	(JJ)J;
NameAndType	max:(JJ)J
Method	java/lang/Math.max:(JJ)J
Asciz	(Lscala/MathCommon;FF)F;
Asciz	(FF)F;
NameAndType	max:(FF)F
Method	java/lang/Math.max:(FF)F
NameAndType	max:(DD)D
Method	java/lang/Math.max:(DD)D
Asciz	min;
NameAndType	min:(II)I
Method	java/lang/Math.min:(II)I
NameAndType	min:(JJ)J
Method	java/lang/Math.min:(JJ)J
NameAndType	min:(FF)F
Method	java/lang/Math.min:(FF)F
NameAndType	min:(DD)D
Method	java/lang/Math.min:(DD)D
Asciz	signum;
long	-1l;
Asciz	$init$;
Asciz	(Lscala/MathCommon;)V;
double	2.718281828459045d;
Asciz	scala/MathCommon;
class	scala/MathCommon
Asciz	scala$MathCommon$_setter_$E_$eq;
Asciz	(D)V;
NameAndType	scala$MathCommon$_setter_$E_$eq:(D)V
InterfaceMethod	scala/MathCommon.scala$MathCommon$_setter_$E_$eq:(D)V
double	3.141592653589793d;
Asciz	scala$MathCommon$_setter_$Pi_$eq;
NameAndType	scala$MathCommon$_setter_$Pi_$eq:(D)V
InterfaceMethod	scala/MathCommon.scala$MathCommon$_setter_$Pi_$eq:(D)V
Asciz	Scala;
Asciz	scala/MathCommon$class;
class	scala/MathCommon$class
Asciz	java/lang/Object;
class	java/lang/Object

{
public static double random(scala.MathCommon);
  Signature: (Lscala/MathCommon;)D
  Code:
   Stack=2, Locals=1, Args_size=1
	invokestatic	Method java/lang/Math.random:()D
	dreturn
  Labels:
  LocalVariableTable: 
   Start  Length  Slot  Name   Signature
   0      4      0    $this       Lscala/MathCommon;


public static double sin(scala.MathCommon, double);
  Signature: (Lscala/MathCommon;D)D
  Code:
   Stack=2, Locals=3, Args_size=2
	dload_1
	invokestatic	Method java/lang/Math.sin:(D)D
	dreturn
  Labels:
  LocalVariableTable: 
   Start  Length  Slot  Name   Signature
   0      5      0    $this       Lscala/MathCommon;
   0      5      1    x       D


public static double cos(scala.MathCommon, double);
  Signature: (Lscala/MathCommon;D)D
  Code:
   Stack=2, Locals=3, Args_size=2
	dload_1
	invokestatic	Method java/lang/Math.cos:(D)D
	dreturn
  Labels:
  LocalVariableTable: 
   Start  Length  Slot  Name   Signature
   0      5      0    $this       Lscala/MathCommon;
   0      5      1    x       D


public static double tan(scala.MathCommon, double);
  Signature: (Lscala/MathCommon;D)D
  Code:
   Stack=2, Locals=3, Args_size=2
	dload_1
	invokestatic	Method java/lang/Math.tan:(D)D
	dreturn
  Labels:
  LocalVariableTable: 
   Start  Length  Slot  Name   Signature
   0      5      0    $this       Lscala/MathCommon;
   0      5      1    x       D


public static double asin(scala.MathCommon, double);
  Signature: (Lscala/MathCommon;D)D
  Code:
   Stack=2, Locals=3, Args_size=2
	dload_1
	invokestatic	Method java/lang/Math.asin:(D)D
	dreturn
  Labels:
  LocalVariableTable: 
   Start  Length  Slot  Name   Signature
   0      5      0    $this       Lscala/MathCommon;
   0      5      1    x       D


public static double acos(scala.MathCommon, double);
  Signature: (Lscala/MathCommon;D)D
  Code:
   Stack=2, Locals=3, Args_size=2
	dload_1
	invokestatic	Method java/lang/Math.acos:(D)D
	dreturn
  Labels:
  LocalVariableTable: 
   Start  Length  Slot  Name   Signature
   0      5      0    $this       Lscala/MathCommon;
   0      5      1    x       D


public static double atan(scala.MathCommon, double);
  Signature: (Lscala/MathCommon;D)D
  Code:
   Stack=2, Locals=3, Args_size=2
	dload_1
	invokestatic	Method java/lang/Math.atan:(D)D
	dreturn
  Labels:
  LocalVariableTable: 
   Start  Length  Slot  Name   Signature
   0      5      0    $this       Lscala/MathCommon;
   0      5      1    x       D


public static double toRadians(scala.MathCommon, double);
  Signature: (Lscala/MathCommon;D)D
  Code:
   Stack=2, Locals=3, Args_size=2
	dload_1
	invokestatic	Method java/lang/Math.toRadians:(D)D
	dreturn
  Labels:
  LocalVariableTable: 
   Start  Length  Slot  Name   Signature
   0      5      0    $this       Lscala/MathCommon;
   0      5      1    x       D


public static double toDegrees(scala.MathCommon, double);
  Signature: (Lscala/MathCommon;D)D
  Code:
   Stack=2, Locals=3, Args_size=2
	dload_1
	invokestatic	Method java/lang/Math.toDegrees:(D)D
	dreturn
  Labels:
  LocalVariableTable: 
   Start  Length  Slot  Name   Signature
   0      5      0    $this       Lscala/MathCommon;
   0      5      1    x       D


public static double exp(scala.MathCommon, double);
  Signature: (Lscala/MathCommon;D)D
  Code:
   Stack=2, Locals=3, Args_size=2
	dload_1
	invokestatic	Method java/lang/Math.exp:(D)D
	dreturn
  Labels:
  LocalVariableTable: 
   Start  Length  Slot  Name   Signature
   0      5      0    $this       Lscala/MathCommon;
   0      5      1    x       D


public static double log(scala.MathCommon, double);
  Signature: (Lscala/MathCommon;D)D
  Code:
   Stack=2, Locals=3, Args_size=2
	dload_1
	invokestatic	Method java/lang/Math.log:(D)D
	dreturn
  Labels:
  LocalVariableTable: 
   Start  Length  Slot  Name   Signature
   0      5      0    $this       Lscala/MathCommon;
   0      5      1    x       D


public static double sqrt(scala.MathCommon, double);
  Signature: (Lscala/MathCommon;D)D
  Code:
   Stack=2, Locals=3, Args_size=2
	dload_1
	invokestatic	Method java/lang/Math.sqrt:(D)D
	dreturn
  Labels:
  LocalVariableTable: 
   Start  Length  Slot  Name   Signature
   0      5      0    $this       Lscala/MathCommon;
   0      5      1    x       D


public static double IEEEremainder(scala.MathCommon, double, double);
  Signature: (Lscala/MathCommon;DD)D
  Code:
   Stack=4, Locals=5, Args_size=3
	dload_1
	dload_3
	invokestatic	Method java/lang/Math.IEEEremainder:(DD)D
	dreturn
  Labels:
  LocalVariableTable: 
   Start  Length  Slot  Name   Signature
   0      6      0    $this       Lscala/MathCommon;
   0      6      1    x       D
   0      6      3    y       D


public static double ceil(scala.MathCommon, double);
  Signature: (Lscala/MathCommon;D)D
  Code:
   Stack=2, Locals=3, Args_size=2
	dload_1
	invokestatic	Method java/lang/Math.ceil:(D)D
	dreturn
  Labels:
  LocalVariableTable: 
   Start  Length  Slot  Name   Signature
   0      5      0    $this       Lscala/MathCommon;
   0      5      1    x       D


public static double floor(scala.MathCommon, double);
  Signature: (Lscala/MathCommon;D)D
  Code:
   Stack=2, Locals=3, Args_size=2
	dload_1
	invokestatic	Method java/lang/Math.floor:(D)D
	dreturn
  Labels:
  LocalVariableTable: 
   Start  Length  Slot  Name   Signature
   0      5      0    $this       Lscala/MathCommon;
   0      5      1    x       D


public static double rint(scala.MathCommon, double);
  Signature: (Lscala/MathCommon;D)D
  Code:
   Stack=2, Locals=3, Args_size=2
	dload_1
	invokestatic	Method java/lang/Math.rint:(D)D
	dreturn
  Labels:
  LocalVariableTable: 
   Start  Length  Slot  Name   Signature
   0      5      0    $this       Lscala/MathCommon;
   0      5      1    x       D


public static double atan2(scala.MathCommon, double, double);
  Signature: (Lscala/MathCommon;DD)D
  Code:
   Stack=4, Locals=5, Args_size=3
	dload_1
	dload_3
	invokestatic	Method java/lang/Math.atan2:(DD)D
	dreturn
  Labels:
  LocalVariableTable: 
   Start  Length  Slot  Name   Signature
   0      6      0    $this       Lscala/MathCommon;
   0      6      1    y       D
   0      6      3    x       D


public static double pow(scala.MathCommon, double, double);
  Signature: (Lscala/MathCommon;DD)D
  Code:
   Stack=4, Locals=5, Args_size=3
	dload_1
	dload_3
	invokestatic	Method java/lang/Math.pow:(DD)D
	dreturn
  Labels:
  LocalVariableTable: 
   Start  Length  Slot  Name   Signature
   0      6      0    $this       Lscala/MathCommon;
   0      6      1    x       D
   0      6      3    y       D


public static int round(scala.MathCommon, float);
  Signature: (Lscala/MathCommon;F)I
  Code:
   Stack=1, Locals=2, Args_size=2
	fload_1
	invokestatic	Method java/lang/Math.round:(F)I
	ireturn
  Labels:
  LocalVariableTable: 
   Start  Length  Slot  Name   Signature
   0      5      0    $this       Lscala/MathCommon;
   0      5      1    x       F


public static long round(scala.MathCommon, double);
  Signature: (Lscala/MathCommon;D)J
  Code:
   Stack=2, Locals=3, Args_size=2
	dload_1
	invokestatic	Method java/lang/Math.round:(D)J
	lreturn
  Labels:
  LocalVariableTable: 
   Start  Length  Slot  Name   Signature
   0      5      0    $this       Lscala/MathCommon;
   0      5      1    x       D


public static int abs(scala.MathCommon, int);
  Signature: (Lscala/MathCommon;I)I
  Code:
   Stack=1, Locals=2, Args_size=2
	iload_1
	invokestatic	Method java/lang/Math.abs:(I)I
	ireturn
  Labels:
  LocalVariableTable: 
   Start  Length  Slot  Name   Signature
   0      5      0    $this       Lscala/MathCommon;
   0      5      1    x       I


public static long abs(scala.MathCommon, long);
  Signature: (Lscala/MathCommon;J)J
  Code:
   Stack=2, Locals=3, Args_size=2
	lload_1
	invokestatic	Method java/lang/Math.abs:(J)J
	lreturn
  Labels:
  LocalVariableTable: 
   Start  Length  Slot  Name   Signature
   0      5      0    $this       Lscala/MathCommon;
   0      5      1    x       J


public static float abs(scala.MathCommon, float);
  Signature: (Lscala/MathCommon;F)F
  Code:
   Stack=1, Locals=2, Args_size=2
	fload_1
	invokestatic	Method java/lang/Math.abs:(F)F
	freturn
  Labels:
  LocalVariableTable: 
   Start  Length  Slot  Name   Signature
   0      5      0    $this       Lscala/MathCommon;
   0      5      1    x       F


public static double abs(scala.MathCommon, double);
  Signature: (Lscala/MathCommon;D)D
  Code:
   Stack=2, Locals=3, Args_size=2
	dload_1
	invokestatic	Method java/lang/Math.abs:(D)D
	dreturn
  Labels:
  LocalVariableTable: 
   Start  Length  Slot  Name   Signature
   0      5      0    $this       Lscala/MathCommon;
   0      5      1    x       D


public static int max(scala.MathCommon, int, int);
  Signature: (Lscala/MathCommon;II)I
  Code:
   Stack=2, Locals=3, Args_size=3
	iload_1
	iload_2
	invokestatic	Method java/lang/Math.max:(II)I
	ireturn
  Labels:
  LocalVariableTable: 
   Start  Length  Slot  Name   Signature
   0      6      0    $this       Lscala/MathCommon;
   0      6      1    x       I
   0      6      2    y       I


public static long max(scala.MathCommon, long, long);
  Signature: (Lscala/MathCommon;JJ)J
  Code:
   Stack=4, Locals=5, Args_size=3
	lload_1
	lload_3
	invokestatic	Method java/lang/Math.max:(JJ)J
	lreturn
  Labels:
  LocalVariableTable: 
   Start  Length  Slot  Name   Signature
   0      6      0    $this       Lscala/MathCommon;
   0      6      1    x       J
   0      6      3    y       J


public static float max(scala.MathCommon, float, float);
  Signature: (Lscala/MathCommon;FF)F
  Code:
   Stack=2, Locals=3, Args_size=3
	fload_1
	fload_2
	invokestatic	Method java/lang/Math.max:(FF)F
	freturn
  Labels:
  LocalVariableTable: 
   Start  Length  Slot  Name   Signature
   0      6      0    $this       Lscala/MathCommon;
   0      6      1    x       F
   0      6      2    y       F


public static double max(scala.MathCommon, double, double);
  Signature: (Lscala/MathCommon;DD)D
  Code:
   Stack=4, Locals=5, Args_size=3
	dload_1
	dload_3
	invokestatic	Method java/lang/Math.max:(DD)D
	dreturn
  Labels:
  LocalVariableTable: 
   Start  Length  Slot  Name   Signature
   0      6      0    $this       Lscala/MathCommon;
   0      6      1    x       D
   0      6      3    y       D


public static int min(scala.MathCommon, int, int);
  Signature: (Lscala/MathCommon;II)I
  Code:
   Stack=2, Locals=3, Args_size=3
	iload_1
	iload_2
	invokestatic	Method java/lang/Math.min:(II)I
	ireturn
  Labels:
  LocalVariableTable: 
   Start  Length  Slot  Name   Signature
   0      6      0    $this       Lscala/MathCommon;
   0      6      1    x       I
   0      6      2    y       I


public static long min(scala.MathCommon, long, long);
  Signature: (Lscala/MathCommon;JJ)J
  Code:
   Stack=4, Locals=5, Args_size=3
	lload_1
	lload_3
	invokestatic	Method java/lang/Math.min:(JJ)J
	lreturn
  Labels:
  LocalVariableTable: 
   Start  Length  Slot  Name   Signature
   0      6      0    $this       Lscala/MathCommon;
   0      6      1    x       J
   0      6      3    y       J


public static float min(scala.MathCommon, float, float);
  Signature: (Lscala/MathCommon;FF)F
  Code:
   Stack=2, Locals=3, Args_size=3
	fload_1
	fload_2
	invokestatic	Method java/lang/Math.min:(FF)F
	freturn
  Labels:
  LocalVariableTable: 
   Start  Length  Slot  Name   Signature
   0      6      0    $this       Lscala/MathCommon;
   0      6      1    x       F
   0      6      2    y       F


public static double min(scala.MathCommon, double, double);
  Signature: (Lscala/MathCommon;DD)D
  Code:
   Stack=4, Locals=5, Args_size=3
	dload_1
	dload_3
	invokestatic	Method java/lang/Math.min:(DD)D
	dreturn
  Labels:
  LocalVariableTable: 
   Start  Length  Slot  Name   Signature
   0      6      0    $this       Lscala/MathCommon;
   0      6      1    x       D
   0      6      3    y       D


public static double signum(scala.MathCommon, double);
  Signature: (Lscala/MathCommon;D)D
  Code:
   Stack=4, Locals=3, Args_size=2
	dload_1
	dconst_0
	dcmpl
	ifne	l1 // dload_1
	dconst_0
	goto	l2 // dreturn
l1	dload_1
	iconst_0
	i2d
	dcmpg
	ifge	l3 // dload_1
	dconst_1
	dneg
	goto	l2 // dreturn
l3	dload_1
	iconst_0
	i2d
	dcmpl
	ifle	l4 // dload_1
	dconst_1
	goto	l2 // dreturn
l4	dload_1
l2	dreturn
  Labels:
   	l1 = 10 // dload_1
   	l3 = 22 // dload_1
   	l4 = 33 // dload_1
   	l2 = 34 // dreturn
  LocalVariableTable: 
   Start  Length  Slot  Name   Signature
   0      35      0    $this       Lscala/MathCommon;
   0      35      1    x       D


public static float signum(scala.MathCommon, float);
  Signature: (Lscala/MathCommon;F)F
  Code:
   Stack=2, Locals=2, Args_size=2
	fload_1
	fconst_0
	fcmpl
	ifne	l1 // fload_1
	fconst_0
	goto	l2 // freturn
l1	fload_1
	iconst_0
	i2f
	fcmpg
	ifge	l3 // fload_1
	fconst_1
	fneg
	goto	l2 // freturn
l3	fload_1
	iconst_0
	i2f
	fcmpl
	ifle	l4 // fload_1
	fconst_1
	goto	l2 // freturn
l4	fload_1
l2	freturn
  Labels:
   	l1 = 10 // fload_1
   	l3 = 22 // fload_1
   	l4 = 33 // fload_1
   	l2 = 34 // freturn
  LocalVariableTable: 
   Start  Length  Slot  Name   Signature
   0      35      0    $this       Lscala/MathCommon;
   0      35      1    x       F


public static long signum(scala.MathCommon, long);
  Signature: (Lscala/MathCommon;J)J
  Code:
   Stack=4, Locals=3, Args_size=2
	lload_1
	lconst_0
	lcmp
	ifne	l1 // lload_1
	lconst_0
	goto	l2 // lreturn
l1	lload_1
	lconst_0
	lcmp
	ifge	l3 // lconst_1
	ldc2_w	long -1l
	goto	l2 // lreturn
l3	lconst_1
l2	lreturn
  Labels:
   	l1 = 10 // lload_1
   	l3 = 22 // lconst_1
   	l2 = 23 // lreturn
  LocalVariableTable: 
   Start  Length  Slot  Name   Signature
   0      24      0    $this       Lscala/MathCommon;
   0      24      1    x       J


public static int signum(scala.MathCommon, int);
  Signature: (Lscala/MathCommon;I)I
  Code:
   Stack=2, Locals=2, Args_size=2
	iload_1
	iconst_0
	if_icmpne	l1 // iload_1
	iconst_0
	goto	l2 // ireturn
l1	iload_1
	iconst_0
	if_icmpge	l3 // iconst_1
	iconst_m1
	goto	l2 // ireturn
l3	iconst_1
l2	ireturn
  Labels:
   	l1 = 9 // iload_1
   	l3 = 18 // iconst_1
   	l2 = 19 // ireturn
  LocalVariableTable: 
   Start  Length  Slot  Name   Signature
   0      20      0    $this       Lscala/MathCommon;
   0      20      1    x       I


public static void $init$(scala.MathCommon);
  Signature: (Lscala/MathCommon;)V
  Code:
   Stack=3, Locals=1, Args_size=1
	aload_0
	ldc2_w	double 2.718281828459045d
	invokeinterface	InterfaceMethod scala/MathCommon.scala$MathCommon$_setter_$E_$eq:(D)V
	aload_0
	ldc2_w	double 3.141592653589793d
	invokeinterface	InterfaceMethod scala/MathCommon.scala$MathCommon$_setter_$Pi_$eq:(D)V
	return
  Labels:
  LocalVariableTable: 
   Start  Length  Slot  Name   Signature
   0      19      0    $this       Lscala/MathCommon;


}

