Compiled from "MathCommon.scala"
public abstract class scala.MathCommon$class extends java.lang.Object
  SourceFile: "MathCommon.scala"
  Scala: length = 0x
   
  minor version: 0
  major version: 49
  Constant pool:
const #1 = Asciz	SourceFile;
const #2 = Asciz	MathCommon.scala;
const #3 = Asciz	$init$;
const #4 = Asciz	(Lscala/MathCommon;)V;
const #5 = Asciz	Code;
const #6 = Asciz	LineNumberTable;
const #7 = double	2.718281828459045d;
const #9 = Asciz	scala/MathCommon;
const #10 = class	#9;	//  scala/MathCommon
const #11 = Asciz	scala$MathCommon$_setter_$E_$eq;
const #12 = Asciz	(D)V;
const #13 = NameAndType	#11:#12;//  scala$MathCommon$_setter_$E_$eq:(D)V
const #14 = InterfaceMethod	#10.#13;	//  scala/MathCommon.scala$MathCommon$_setter_$E_$eq:(D)V
const #15 = double	3.141592653589793d;
const #17 = Asciz	scala$MathCommon$_setter_$Pi_$eq;
const #18 = NameAndType	#17:#12;//  scala$MathCommon$_setter_$Pi_$eq:(D)V
const #19 = InterfaceMethod	#10.#18;	//  scala/MathCommon.scala$MathCommon$_setter_$Pi_$eq:(D)V
const #20 = Asciz	$this;
const #21 = Asciz	Lscala/MathCommon;;
const #22 = Asciz	LocalVariableTable;
const #23 = Asciz	signum;
const #24 = Asciz	(Lscala/MathCommon;I)I;
const #25 = Asciz	x;
const #26 = Asciz	I;
const #27 = Asciz	(Lscala/MathCommon;J)J;
const #28 = long	-1l;
const #30 = Asciz	J;
const #31 = Asciz	(Lscala/MathCommon;F)F;
const #32 = Asciz	F;
const #33 = Asciz	(Lscala/MathCommon;D)D;
const #34 = Asciz	D;
const #35 = Asciz	min;
const #36 = Asciz	(Lscala/MathCommon;DD)D;
const #37 = Asciz	java/lang/Math;
const #38 = class	#37;	//  java/lang/Math
const #39 = Asciz	(DD)D;
const #40 = NameAndType	#35:#39;//  min:(DD)D
const #41 = Method	#38.#40;	//  java/lang/Math.min:(DD)D
const #42 = Asciz	y;
const #43 = Asciz	(Lscala/MathCommon;FF)F;
const #44 = Asciz	(FF)F;
const #45 = NameAndType	#35:#44;//  min:(FF)F
const #46 = Method	#38.#45;	//  java/lang/Math.min:(FF)F
const #47 = Asciz	(Lscala/MathCommon;JJ)J;
const #48 = Asciz	(JJ)J;
const #49 = NameAndType	#35:#48;//  min:(JJ)J
const #50 = Method	#38.#49;	//  java/lang/Math.min:(JJ)J
const #51 = Asciz	(Lscala/MathCommon;II)I;
const #52 = Asciz	(II)I;
const #53 = NameAndType	#35:#52;//  min:(II)I
const #54 = Method	#38.#53;	//  java/lang/Math.min:(II)I
const #55 = Asciz	max;
const #56 = NameAndType	#55:#39;//  max:(DD)D
const #57 = Method	#38.#56;	//  java/lang/Math.max:(DD)D
const #58 = NameAndType	#55:#44;//  max:(FF)F
const #59 = Method	#38.#58;	//  java/lang/Math.max:(FF)F
const #60 = NameAndType	#55:#48;//  max:(JJ)J
const #61 = Method	#38.#60;	//  java/lang/Math.max:(JJ)J
const #62 = NameAndType	#55:#52;//  max:(II)I
const #63 = Method	#38.#62;	//  java/lang/Math.max:(II)I
const #64 = Asciz	abs;
const #65 = Asciz	(D)D;
const #66 = NameAndType	#64:#65;//  abs:(D)D
const #67 = Method	#38.#66;	//  java/lang/Math.abs:(D)D
const #68 = Asciz	(F)F;
const #69 = NameAndType	#64:#68;//  abs:(F)F
const #70 = Method	#38.#69;	//  java/lang/Math.abs:(F)F
const #71 = Asciz	(J)J;
const #72 = NameAndType	#64:#71;//  abs:(J)J
const #73 = Method	#38.#72;	//  java/lang/Math.abs:(J)J
const #74 = Asciz	(I)I;
const #75 = NameAndType	#64:#74;//  abs:(I)I
const #76 = Method	#38.#75;	//  java/lang/Math.abs:(I)I
const #77 = Asciz	round;
const #78 = Asciz	(Lscala/MathCommon;D)J;
const #79 = Asciz	(D)J;
const #80 = NameAndType	#77:#79;//  round:(D)J
const #81 = Method	#38.#80;	//  java/lang/Math.round:(D)J
const #82 = Asciz	(Lscala/MathCommon;F)I;
const #83 = Asciz	(F)I;
const #84 = NameAndType	#77:#83;//  round:(F)I
const #85 = Method	#38.#84;	//  java/lang/Math.round:(F)I
const #86 = Asciz	pow;
const #87 = NameAndType	#86:#39;//  pow:(DD)D
const #88 = Method	#38.#87;	//  java/lang/Math.pow:(DD)D
const #89 = Asciz	atan2;
const #90 = NameAndType	#89:#39;//  atan2:(DD)D
const #91 = Method	#38.#90;	//  java/lang/Math.atan2:(DD)D
const #92 = Asciz	rint;
const #93 = NameAndType	#92:#65;//  rint:(D)D
const #94 = Method	#38.#93;	//  java/lang/Math.rint:(D)D
const #95 = Asciz	floor;
const #96 = NameAndType	#95:#65;//  floor:(D)D
const #97 = Method	#38.#96;	//  java/lang/Math.floor:(D)D
const #98 = Asciz	ceil;
const #99 = NameAndType	#98:#65;//  ceil:(D)D
const #100 = Method	#38.#99;	//  java/lang/Math.ceil:(D)D
const #101 = Asciz	IEEEremainder;
const #102 = NameAndType	#101:#39;//  IEEEremainder:(DD)D
const #103 = Method	#38.#102;	//  java/lang/Math.IEEEremainder:(DD)D
const #104 = Asciz	sqrt;
const #105 = NameAndType	#104:#65;//  sqrt:(D)D
const #106 = Method	#38.#105;	//  java/lang/Math.sqrt:(D)D
const #107 = Asciz	log;
const #108 = NameAndType	#107:#65;//  log:(D)D
const #109 = Method	#38.#108;	//  java/lang/Math.log:(D)D
const #110 = Asciz	exp;
const #111 = NameAndType	#110:#65;//  exp:(D)D
const #112 = Method	#38.#111;	//  java/lang/Math.exp:(D)D
const #113 = Asciz	toDegrees;
const #114 = NameAndType	#113:#65;//  toDegrees:(D)D
const #115 = Method	#38.#114;	//  java/lang/Math.toDegrees:(D)D
const #116 = Asciz	toRadians;
const #117 = NameAndType	#116:#65;//  toRadians:(D)D
const #118 = Method	#38.#117;	//  java/lang/Math.toRadians:(D)D
const #119 = Asciz	atan;
const #120 = NameAndType	#119:#65;//  atan:(D)D
const #121 = Method	#38.#120;	//  java/lang/Math.atan:(D)D
const #122 = Asciz	acos;
const #123 = NameAndType	#122:#65;//  acos:(D)D
const #124 = Method	#38.#123;	//  java/lang/Math.acos:(D)D
const #125 = Asciz	asin;
const #126 = NameAndType	#125:#65;//  asin:(D)D
const #127 = Method	#38.#126;	//  java/lang/Math.asin:(D)D
const #128 = Asciz	tan;
const #129 = NameAndType	#128:#65;//  tan:(D)D
const #130 = Method	#38.#129;	//  java/lang/Math.tan:(D)D
const #131 = Asciz	cos;
const #132 = NameAndType	#131:#65;//  cos:(D)D
const #133 = Method	#38.#132;	//  java/lang/Math.cos:(D)D
const #134 = Asciz	sin;
const #135 = NameAndType	#134:#65;//  sin:(D)D
const #136 = Method	#38.#135;	//  java/lang/Math.sin:(D)D
const #137 = Asciz	random;
const #138 = Asciz	(Lscala/MathCommon;)D;
const #139 = Asciz	()D;
const #140 = NameAndType	#137:#139;//  random:()D
const #141 = Method	#38.#140;	//  java/lang/Math.random:()D
const #142 = Asciz	Scala;
const #143 = Asciz	scala/MathCommon$class;
const #144 = class	#143;	//  scala/MathCommon$class
const #145 = Asciz	java/lang/Object;
const #146 = class	#145;	//  java/lang/Object

{
public static void $init$(scala.MathCommon);
  Code:
   Stack=3, Locals=1, Args_size=1
   0:	aload_0
   1:	ldc2_w	#7; //double 2.718281828459045d
   4:	invokeinterface	#14,  3; //InterfaceMethod scala/MathCommon.scala$MathCommon$_setter_$E_$eq:(D)V
   9:	aload_0
   10:	ldc2_w	#15; //double 3.141592653589793d
   13:	invokeinterface	#19,  3; //InterfaceMethod scala/MathCommon.scala$MathCommon$_setter_$Pi_$eq:(D)V
   18:	return
  LineNumberTable: 
   line 20: 0
   line 26: 9

  LocalVariableTable: 
   Start  Length  Slot  Name   Signature
   0      19      0    $this       Lscala/MathCommon;


public static int signum(scala.MathCommon, int);
  Code:
   Stack=2, Locals=2, Args_size=2
   0:	iload_1
   1:	iconst_0
   2:	if_icmpne	9
   5:	iconst_0
   6:	goto	19
   9:	iload_1
   10:	iconst_0
   11:	if_icmpge	18
   14:	iconst_m1
   15:	goto	19
   18:	iconst_1
   19:	ireturn
  LineNumberTable: 
   line 141: 0
   line 142: 9
   line 143: 18
   line 141: 19

  LocalVariableTable: 
   Start  Length  Slot  Name   Signature
   0      20      0    $this       Lscala/MathCommon;
   0      20      1    x       I


public static long signum(scala.MathCommon, long);
  Code:
   Stack=4, Locals=3, Args_size=2
   0:	lload_1
   1:	lconst_0
   2:	lcmp
   3:	ifne	10
   6:	lconst_0
   7:	goto	23
   10:	lload_1
   11:	lconst_0
   12:	lcmp
   13:	ifge	22
   16:	ldc2_w	#28; //long -1l
   19:	goto	23
   22:	lconst_1
   23:	lreturn
  LineNumberTable: 
   line 136: 0
   line 137: 10
   line 138: 22
   line 136: 23

  LocalVariableTable: 
   Start  Length  Slot  Name   Signature
   0      24      0    $this       Lscala/MathCommon;
   0      24      1    x       J


public static float signum(scala.MathCommon, float);
  Code:
   Stack=2, Locals=2, Args_size=2
   0:	fload_1
   1:	fconst_0
   2:	fcmpl
   3:	ifne	10
   6:	fconst_0
   7:	goto	34
   10:	fload_1
   11:	iconst_0
   12:	i2f
   13:	fcmpg
   14:	ifge	22
   17:	fconst_1
   18:	fneg
   19:	goto	34
   22:	fload_1
   23:	iconst_0
   24:	i2f
   25:	fcmpl
   26:	ifle	33
   29:	fconst_1
   30:	goto	34
   33:	fload_1
   34:	freturn
  LineNumberTable: 
   line 130: 0
   line 131: 10
   line 132: 22
   line 133: 33
   line 130: 34

  LocalVariableTable: 
   Start  Length  Slot  Name   Signature
   0      35      0    $this       Lscala/MathCommon;
   0      35      1    x       F


public static double signum(scala.MathCommon, double);
  Code:
   Stack=4, Locals=3, Args_size=2
   0:	dload_1
   1:	dconst_0
   2:	dcmpl
   3:	ifne	10
   6:	dconst_0
   7:	goto	34
   10:	dload_1
   11:	iconst_0
   12:	i2d
   13:	dcmpg
   14:	ifge	22
   17:	dconst_1
   18:	dneg
   19:	goto	34
   22:	dload_1
   23:	iconst_0
   24:	i2d
   25:	dcmpl
   26:	ifle	33
   29:	dconst_1
   30:	goto	34
   33:	dload_1
   34:	dreturn
  LineNumberTable: 
   line 124: 0
   line 125: 10
   line 126: 22
   line 127: 33
   line 124: 34

  LocalVariableTable: 
   Start  Length  Slot  Name   Signature
   0      35      0    $this       Lscala/MathCommon;
   0      35      1    x       D


public static double min(scala.MathCommon, double, double);
  Code:
   Stack=4, Locals=5, Args_size=3
   0:	dload_1
   1:	dload_3
   2:	invokestatic	#41; //Method java/lang/Math.min:(DD)D
   5:	dreturn
  LineNumberTable: 
   line 121: 0

  LocalVariableTable: 
   Start  Length  Slot  Name   Signature
   0      6      0    $this       Lscala/MathCommon;
   0      6      1    x       D
   0      6      3    y       D


public static float min(scala.MathCommon, float, float);
  Code:
   Stack=2, Locals=3, Args_size=3
   0:	fload_1
   1:	fload_2
   2:	invokestatic	#46; //Method java/lang/Math.min:(FF)F
   5:	freturn
  LineNumberTable: 
   line 120: 0

  LocalVariableTable: 
   Start  Length  Slot  Name   Signature
   0      6      0    $this       Lscala/MathCommon;
   0      6      1    x       F
   0      6      2    y       F


public static long min(scala.MathCommon, long, long);
  Code:
   Stack=4, Locals=5, Args_size=3
   0:	lload_1
   1:	lload_3
   2:	invokestatic	#50; //Method java/lang/Math.min:(JJ)J
   5:	lreturn
  LineNumberTable: 
   line 119: 0

  LocalVariableTable: 
   Start  Length  Slot  Name   Signature
   0      6      0    $this       Lscala/MathCommon;
   0      6      1    x       J
   0      6      3    y       J


public static int min(scala.MathCommon, int, int);
  Code:
   Stack=2, Locals=3, Args_size=3
   0:	iload_1
   1:	iload_2
   2:	invokestatic	#54; //Method java/lang/Math.min:(II)I
   5:	ireturn
  LineNumberTable: 
   line 118: 0

  LocalVariableTable: 
   Start  Length  Slot  Name   Signature
   0      6      0    $this       Lscala/MathCommon;
   0      6      1    x       I
   0      6      2    y       I


public static double max(scala.MathCommon, double, double);
  Code:
   Stack=4, Locals=5, Args_size=3
   0:	dload_1
   1:	dload_3
   2:	invokestatic	#57; //Method java/lang/Math.max:(DD)D
   5:	dreturn
  LineNumberTable: 
   line 116: 0

  LocalVariableTable: 
   Start  Length  Slot  Name   Signature
   0      6      0    $this       Lscala/MathCommon;
   0      6      1    x       D
   0      6      3    y       D


public static float max(scala.MathCommon, float, float);
  Code:
   Stack=2, Locals=3, Args_size=3
   0:	fload_1
   1:	fload_2
   2:	invokestatic	#59; //Method java/lang/Math.max:(FF)F
   5:	freturn
  LineNumberTable: 
   line 115: 0

  LocalVariableTable: 
   Start  Length  Slot  Name   Signature
   0      6      0    $this       Lscala/MathCommon;
   0      6      1    x       F
   0      6      2    y       F


public static long max(scala.MathCommon, long, long);
  Code:
   Stack=4, Locals=5, Args_size=3
   0:	lload_1
   1:	lload_3
   2:	invokestatic	#61; //Method java/lang/Math.max:(JJ)J
   5:	lreturn
  LineNumberTable: 
   line 114: 0

  LocalVariableTable: 
   Start  Length  Slot  Name   Signature
   0      6      0    $this       Lscala/MathCommon;
   0      6      1    x       J
   0      6      3    y       J


public static int max(scala.MathCommon, int, int);
  Code:
   Stack=2, Locals=3, Args_size=3
   0:	iload_1
   1:	iload_2
   2:	invokestatic	#63; //Method java/lang/Math.max:(II)I
   5:	ireturn
  LineNumberTable: 
   line 113: 0

  LocalVariableTable: 
   Start  Length  Slot  Name   Signature
   0      6      0    $this       Lscala/MathCommon;
   0      6      1    x       I
   0      6      2    y       I


public static double abs(scala.MathCommon, double);
  Code:
   Stack=2, Locals=3, Args_size=2
   0:	dload_1
   1:	invokestatic	#67; //Method java/lang/Math.abs:(D)D
   4:	dreturn
  LineNumberTable: 
   line 111: 0

  LocalVariableTable: 
   Start  Length  Slot  Name   Signature
   0      5      0    $this       Lscala/MathCommon;
   0      5      1    x       D


public static float abs(scala.MathCommon, float);
  Code:
   Stack=1, Locals=2, Args_size=2
   0:	fload_1
   1:	invokestatic	#70; //Method java/lang/Math.abs:(F)F
   4:	freturn
  LineNumberTable: 
   line 110: 0

  LocalVariableTable: 
   Start  Length  Slot  Name   Signature
   0      5      0    $this       Lscala/MathCommon;
   0      5      1    x       F


public static long abs(scala.MathCommon, long);
  Code:
   Stack=2, Locals=3, Args_size=2
   0:	lload_1
   1:	invokestatic	#73; //Method java/lang/Math.abs:(J)J
   4:	lreturn
  LineNumberTable: 
   line 109: 0

  LocalVariableTable: 
   Start  Length  Slot  Name   Signature
   0      5      0    $this       Lscala/MathCommon;
   0      5      1    x       J


public static int abs(scala.MathCommon, int);
  Code:
   Stack=1, Locals=2, Args_size=2
   0:	iload_1
   1:	invokestatic	#76; //Method java/lang/Math.abs:(I)I
   4:	ireturn
  LineNumberTable: 
   line 108: 0

  LocalVariableTable: 
   Start  Length  Slot  Name   Signature
   0      5      0    $this       Lscala/MathCommon;
   0      5      1    x       I


public static long round(scala.MathCommon, double);
  Code:
   Stack=2, Locals=3, Args_size=2
   0:	dload_1
   1:	invokestatic	#81; //Method java/lang/Math.round:(D)J
   4:	lreturn
  LineNumberTable: 
   line 107: 0

  LocalVariableTable: 
   Start  Length  Slot  Name   Signature
   0      5      0    $this       Lscala/MathCommon;
   0      5      1    x       D


public static int round(scala.MathCommon, float);
  Code:
   Stack=1, Locals=2, Args_size=2
   0:	fload_1
   1:	invokestatic	#85; //Method java/lang/Math.round:(F)I
   4:	ireturn
  LineNumberTable: 
   line 106: 0

  LocalVariableTable: 
   Start  Length  Slot  Name   Signature
   0      5      0    $this       Lscala/MathCommon;
   0      5      1    x       F


public static double pow(scala.MathCommon, double, double);
  Code:
   Stack=4, Locals=5, Args_size=3
   0:	dload_1
   1:	dload_3
   2:	invokestatic	#88; //Method java/lang/Math.pow:(DD)D
   5:	dreturn
  LineNumberTable: 
   line 98: 0

  LocalVariableTable: 
   Start  Length  Slot  Name   Signature
   0      6      0    $this       Lscala/MathCommon;
   0      6      1    x       D
   0      6      3    y       D


public static double atan2(scala.MathCommon, double, double);
  Code:
   Stack=4, Locals=5, Args_size=3
   0:	dload_1
   1:	dload_3
   2:	invokestatic	#91; //Method java/lang/Math.atan2:(DD)D
   5:	dreturn
  LineNumberTable: 
   line 89: 0

  LocalVariableTable: 
   Start  Length  Slot  Name   Signature
   0      6      0    $this       Lscala/MathCommon;
   0      6      1    y       D
   0      6      3    x       D


public static double rint(scala.MathCommon, double);
  Code:
   Stack=2, Locals=3, Args_size=2
   0:	dload_1
   1:	invokestatic	#94; //Method java/lang/Math.rint:(D)D
   4:	dreturn
  LineNumberTable: 
   line 78: 0

  LocalVariableTable: 
   Start  Length  Slot  Name   Signature
   0      5      0    $this       Lscala/MathCommon;
   0      5      1    x       D


public static double floor(scala.MathCommon, double);
  Code:
   Stack=2, Locals=3, Args_size=2
   0:	dload_1
   1:	invokestatic	#97; //Method java/lang/Math.floor:(D)D
   4:	dreturn
  LineNumberTable: 
   line 69: 0

  LocalVariableTable: 
   Start  Length  Slot  Name   Signature
   0      5      0    $this       Lscala/MathCommon;
   0      5      1    x       D


public static double ceil(scala.MathCommon, double);
  Code:
   Stack=2, Locals=3, Args_size=2
   0:	dload_1
   1:	invokestatic	#100; //Method java/lang/Math.ceil:(D)D
   4:	dreturn
  LineNumberTable: 
   line 68: 0

  LocalVariableTable: 
   Start  Length  Slot  Name   Signature
   0      5      0    $this       Lscala/MathCommon;
   0      5      1    x       D


public static double IEEEremainder(scala.MathCommon, double, double);
  Code:
   Stack=4, Locals=5, Args_size=3
   0:	dload_1
   1:	dload_3
   2:	invokestatic	#103; //Method java/lang/Math.IEEEremainder:(DD)D
   5:	dreturn
  LineNumberTable: 
   line 66: 0

  LocalVariableTable: 
   Start  Length  Slot  Name   Signature
   0      6      0    $this       Lscala/MathCommon;
   0      6      1    x       D
   0      6      3    y       D


public static double sqrt(scala.MathCommon, double);
  Code:
   Stack=2, Locals=3, Args_size=2
   0:	dload_1
   1:	invokestatic	#106; //Method java/lang/Math.sqrt:(D)D
   4:	dreturn
  LineNumberTable: 
   line 65: 0

  LocalVariableTable: 
   Start  Length  Slot  Name   Signature
   0      5      0    $this       Lscala/MathCommon;
   0      5      1    x       D


public static double log(scala.MathCommon, double);
  Code:
   Stack=2, Locals=3, Args_size=2
   0:	dload_1
   1:	invokestatic	#109; //Method java/lang/Math.log:(D)D
   4:	dreturn
  LineNumberTable: 
   line 64: 0

  LocalVariableTable: 
   Start  Length  Slot  Name   Signature
   0      5      0    $this       Lscala/MathCommon;
   0      5      1    x       D


public static double exp(scala.MathCommon, double);
  Code:
   Stack=2, Locals=3, Args_size=2
   0:	dload_1
   1:	invokestatic	#112; //Method java/lang/Math.exp:(D)D
   4:	dreturn
  LineNumberTable: 
   line 63: 0

  LocalVariableTable: 
   Start  Length  Slot  Name   Signature
   0      5      0    $this       Lscala/MathCommon;
   0      5      1    x       D


public static double toDegrees(scala.MathCommon, double);
  Code:
   Stack=2, Locals=3, Args_size=2
   0:	dload_1
   1:	invokestatic	#115; //Method java/lang/Math.toDegrees:(D)D
   4:	dreturn
  LineNumberTable: 
   line 54: 0

  LocalVariableTable: 
   Start  Length  Slot  Name   Signature
   0      5      0    $this       Lscala/MathCommon;
   0      5      1    x       D


public static double toRadians(scala.MathCommon, double);
  Code:
   Stack=2, Locals=3, Args_size=2
   0:	dload_1
   1:	invokestatic	#118; //Method java/lang/Math.toRadians:(D)D
   4:	dreturn
  LineNumberTable: 
   line 46: 0

  LocalVariableTable: 
   Start  Length  Slot  Name   Signature
   0      5      0    $this       Lscala/MathCommon;
   0      5      1    x       D


public static double atan(scala.MathCommon, double);
  Code:
   Stack=2, Locals=3, Args_size=2
   0:	dload_1
   1:	invokestatic	#121; //Method java/lang/Math.atan:(D)D
   4:	dreturn
  LineNumberTable: 
   line 38: 0

  LocalVariableTable: 
   Start  Length  Slot  Name   Signature
   0      5      0    $this       Lscala/MathCommon;
   0      5      1    x       D


public static double acos(scala.MathCommon, double);
  Code:
   Stack=2, Locals=3, Args_size=2
   0:	dload_1
   1:	invokestatic	#124; //Method java/lang/Math.acos:(D)D
   4:	dreturn
  LineNumberTable: 
   line 37: 0

  LocalVariableTable: 
   Start  Length  Slot  Name   Signature
   0      5      0    $this       Lscala/MathCommon;
   0      5      1    x       D


public static double asin(scala.MathCommon, double);
  Code:
   Stack=2, Locals=3, Args_size=2
   0:	dload_1
   1:	invokestatic	#127; //Method java/lang/Math.asin:(D)D
   4:	dreturn
  LineNumberTable: 
   line 36: 0

  LocalVariableTable: 
   Start  Length  Slot  Name   Signature
   0      5      0    $this       Lscala/MathCommon;
   0      5      1    x       D


public static double tan(scala.MathCommon, double);
  Code:
   Stack=2, Locals=3, Args_size=2
   0:	dload_1
   1:	invokestatic	#130; //Method java/lang/Math.tan:(D)D
   4:	dreturn
  LineNumberTable: 
   line 35: 0

  LocalVariableTable: 
   Start  Length  Slot  Name   Signature
   0      5      0    $this       Lscala/MathCommon;
   0      5      1    x       D


public static double cos(scala.MathCommon, double);
  Code:
   Stack=2, Locals=3, Args_size=2
   0:	dload_1
   1:	invokestatic	#133; //Method java/lang/Math.cos:(D)D
   4:	dreturn
  LineNumberTable: 
   line 34: 0

  LocalVariableTable: 
   Start  Length  Slot  Name   Signature
   0      5      0    $this       Lscala/MathCommon;
   0      5      1    x       D


public static double sin(scala.MathCommon, double);
  Code:
   Stack=2, Locals=3, Args_size=2
   0:	dload_1
   1:	invokestatic	#136; //Method java/lang/Math.sin:(D)D
   4:	dreturn
  LineNumberTable: 
   line 33: 0

  LocalVariableTable: 
   Start  Length  Slot  Name   Signature
   0      5      0    $this       Lscala/MathCommon;
   0      5      1    x       D


public static double random(scala.MathCommon);
  Code:
   Stack=2, Locals=1, Args_size=1
   0:	invokestatic	#141; //Method java/lang/Math.random:()D
   3:	dreturn
  LineNumberTable: 
   line 31: 0

  LocalVariableTable: 
   Start  Length  Slot  Name   Signature
   0      4      0    $this       Lscala/MathCommon;


}

