Compiled from "Math.scala"
public final class scala.Math extends java.lang.Object
  SourceFile: "Math.scala"
  ScalaSig: length = 0xD6A
   05 00 FFFFFF82 6A 07 05 01 02 FFFFFF88 02 05 01 04 4D 61 74
   68 0A 01 03 01 05 73 63 61 6C 61 03 00 10 02 06
   07 0D 01 02 06 08 08 02 FFFFFF84 FFFFFF80 FFFFFF80 FFFFFF88 02 09 02 04
   4D 61 74 68 13 03 07 0A 12 10 02 0B 10 0D 01 0C
   0A 02 0D 0E 01 04 6C 61 6E 67 0A 01 0F 01 04 6A
   61 76 61 09 02 11 0C 02 06 4F 62 6A 65 63 74 10
   02 06 13 09 02 14 02 02 0B 53 63 61 6C 61 4F 62
   6A 65 63 74 08 05 16 07 FFFFFF84 00 17 01 06 3C 69 6E
   69 74 3E 14 01 05 08 07 19 07 FFFFFFC2 FFFFFF80 FFFFFF84 00 1A 01
   08 4D 49 4E 5F 42 59 54 45 15 01 1B 10 02 06 1C
   09 02 1D 02 02 04 42 79 74 65 28 03 18 1F 22 10
   02 06 20 09 02 21 02 02 0A 64 65 70 72 65 63 61
   74 65 64 21 01 23 01 1F 55 73 65 20 73 63 61 6C
   61 2E 42 79 74 65 2E 4D 69 6E 56 61 6C 75 65 20
   69 6E 73 74 65 61 64 08 06 25 07 FFFFFFA0 FFFFFF80 04 1B 01
   09 4D 49 4E 5F 42 59 54 45 20 08 07 27 07 FFFFFFC2 FFFFFF80
   FFFFFF84 00 1A 01 08 4D 41 58 5F 42 59 54 45 28 03 26
   1F 29 21 01 2A 01 1F 55 73 65 20 73 63 61 6C 61
   2E 42 79 74 65 2E 4D 61 78 56 61 6C 75 65 20 69
   6E 73 74 65 61 64 08 06 2C 07 FFFFFFA0 FFFFFF80 04 1B 01 09
   4D 41 58 5F 42 59 54 45 20 08 07 2E 07 FFFFFFC2 FFFFFF80 FFFFFF84
   00 2F 01 09 4D 49 4E 5F 53 48 4F 52 54 15 01 30
   10 02 06 31 09 02 32 02 02 05 53 68 6F 72 74 28
   03 2D 1F 34 21 01 35 01 20 55 73 65 20 73 63 61
   6C 61 2E 53 68 6F 72 74 2E 4D 69 6E 56 61 6C 75
   65 20 69 6E 73 74 65 61 64 08 06 37 07 FFFFFFA0 FFFFFF80 04
   30 01 0A 4D 49 4E 5F 53 48 4F 52 54 20 08 07 39
   07 FFFFFFC2 FFFFFF80 FFFFFF84 00 2F 01 09 4D 41 58 5F 53 48 4F 52
   54 28 03 38 1F 3B 21 01 3C 01 20 55 73 65 20 73
   63 61 6C 61 2E 53 68 6F 72 74 2E 4D 61 78 56 61
   6C 75 65 20 69 6E 73 74 65 61 64 08 06 3E 07 FFFFFFA0
   FFFFFF80 04 30 01 0A 4D 41 58 5F 53 48 4F 52 54 20 08
   07 40 07 FFFFFFC2 FFFFFF80 FFFFFF84 00 41 01 08 4D 49 4E 5F 43 48
   41 52 15 01 42 10 02 06 43 09 02 44 02 02 04 43
   68 61 72 28 03 3F 1F 46 21 01 47 01 1F 55 73 65
   20 73 63 61 6C 61 2E 43 68 61 72 2E 4D 69 6E 56
   61 6C 75 65 20 69 6E 73 74 65 61 64 08 06 49 07
   FFFFFFA0 FFFFFF80 04 42 01 09 4D 49 4E 5F 43 48 41 52 20 08
   07 4B 07 FFFFFFC2 FFFFFF80 FFFFFF84 00 41 01 08 4D 41 58 5F 43 48
   41 52 28 03 4A 1F 4D 21 01 4E 01 1F 55 73 65 20
   73 63 61 6C 61 2E 43 68 61 72 2E 4D 61 78 56 61
   6C 75 65 20 69 6E 73 74 65 61 64 08 06 50 07 FFFFFFA0
   FFFFFF80 04 42 01 09 4D 41 58 5F 43 48 41 52 20 08 07
   52 07 FFFFFFC2 FFFFFF80 FFFFFF84 00 53 01 07 4D 49 4E 5F 49 4E 54
   15 01 54 10 02 06 55 09 02 56 02 02 03 49 6E 74
   28 03 51 1F 58 21 01 59 01 1E 55 73 65 20 73 63
   61 6C 61 2E 49 6E 74 2E 4D 69 6E 56 61 6C 75 65
   20 69 6E 73 74 65 61 64 08 06 5B 07 FFFFFFA0 FFFFFF80 04 54
   01 08 4D 49 4E 5F 49 4E 54 20 08 07 5D 07 FFFFFFC2 FFFFFF80
   FFFFFF84 00 53 01 07 4D 41 58 5F 49 4E 54 28 03 5C 1F
   5F 21 01 60 01 1E 55 73 65 20 73 63 61 6C 61 2E
   49 6E 74 2E 4D 61 78 56 61 6C 75 65 20 69 6E 73
   74 65 61 64 08 06 62 07 FFFFFFA0 FFFFFF80 04 54 01 08 4D 41
   58 5F 49 4E 54 20 08 07 64 07 FFFFFFC2 FFFFFF80 FFFFFF84 00 65 01
   08 4D 49 4E 5F 4C 4F 4E 47 15 01 66 10 02 06 67
   09 02 68 02 02 04 4C 6F 6E 67 28 03 63 1F 6A 21
   01 6B 01 1F 55 73 65 20 73 63 61 6C 61 2E 4C 6F
   6E 67 2E 4D 69 6E 56 61 6C 75 65 20 69 6E 73 74
   65 61 64 08 06 6D 07 FFFFFFA0 FFFFFF80 04 66 01 09 4D 49 4E
   5F 4C 4F 4E 47 20 08 07 6F 07 FFFFFFC2 FFFFFF80 FFFFFF84 00 65 01
   08 4D 41 58 5F 4C 4F 4E 47 28 03 6E 1F 71 21 01
   72 01 1F 55 73 65 20 73 63 61 6C 61 2E 4C 6F 6E
   67 2E 4D 61 78 56 61 6C 75 65 20 69 6E 73 74 65
   61 64 08 06 74 07 FFFFFFA0 FFFFFF80 04 66 01 09 4D 41 58 5F
   4C 4F 4E 47 20 08 07 76 07 FFFFFFC2 FFFFFF80 FFFFFF84 00 77 01 09
   4D 49 4E 5F 46 4C 4F 41 54 15 01 78 10 02 06 79
   09 02 7A 02 02 05 46 6C 6F 61 74 28 03 75 1F 7C
   21 01 7D 01 20 55 73 65 20 73 63 61 6C 61 2E 46
   6C 6F 61 74 2E 4D 69 6E 56 61 6C 75 65 20 69 6E
   73 74 65 61 64 08 06 7F 07 FFFFFFA0 FFFFFF80 04 78 01 0A 4D
   49 4E 5F 46 4C 4F 41 54 20 08 08 FFFFFF81 01 07 FFFFFFC2 FFFFFF80
   FFFFFF84 00 77 01 09 45 50 53 5F 46 4C 4F 41 54 28 05
   FFFFFF81 00 1F FFFFFF81 03 21 02 FFFFFF81 04 01 1F 55 73 65 20 73
   63 61 6C 61 2E 46 6C 6F 61 74 2E 45 70 73 69 6C
   6F 6E 20 69 6E 73 74 65 61 64 08 07 FFFFFF81 06 07 FFFFFFA0
   FFFFFF80 04 78 01 0A 45 50 53 5F 46 4C 4F 41 54 20 08
   08 FFFFFF81 08 07 FFFFFFC2 FFFFFF80 FFFFFF84 00 77 01 09 4D 41 58 5F 46
   4C 4F 41 54 28 05 FFFFFF81 07 1F FFFFFF81 0A 21 02 FFFFFF81 0B 01
   20 55 73 65 20 73 63 61 6C 61 2E 46 6C 6F 61 74
   2E 4D 61 78 56 61 6C 75 65 20 69 6E 73 74 65 61
   64 08 07 FFFFFF81 0D 07 FFFFFFA0 FFFFFF80 04 78 01 0A 4D 41 58 5F
   46 4C 4F 41 54 20 08 08 FFFFFF81 0F 07 FFFFFFC2 FFFFFF80 FFFFFF84 00 77
   01 09 4E 61 4E 5F 46 4C 4F 41 54 28 05 FFFFFF81 0E 1F
   FFFFFF81 11 21 02 FFFFFF81 12 01 1B 55 73 65 20 73 63 61 6C
   61 2E 46 6C 6F 61 74 2E 4E 61 4E 20 69 6E 73 74
   65 61 64 08 07 FFFFFF81 14 07 FFFFFFA0 FFFFFF80 04 78 01 0A 4E 61
   4E 5F 46 4C 4F 41 54 20 08 08 FFFFFF81 16 07 FFFFFFC2 FFFFFF80 FFFFFF84
   00 77 01 0D 4E 45 47 5F 49 4E 46 5F 46 4C 4F 41
   54 28 05 FFFFFF81 15 1F FFFFFF81 18 21 02 FFFFFF81 19 01 28 55 73
   65 20 73 63 61 6C 61 2E 46 6C 6F 61 74 2E 4E 65
   67 61 74 69 76 65 49 6E 66 69 6E 69 74 79 20 69
   6E 73 74 65 61 64 08 07 FFFFFF81 1B 07 FFFFFFA0 FFFFFF80 04 78 01
   0E 4E 45 47 5F 49 4E 46 5F 46 4C 4F 41 54 20 08
   08 FFFFFF81 1D 07 FFFFFFC2 FFFFFF80 FFFFFF84 00 77 01 0D 50 4F 53 5F 49
   4E 46 5F 46 4C 4F 41 54 28 05 FFFFFF81 1C 1F FFFFFF81 1F 21
   02 FFFFFF81 20 01 28 55 73 65 20 73 63 61 6C 61 2E 46
   6C 6F 61 74 2E 50 6F 73 69 74 69 76 65 49 6E 66
   69 6E 69 74 79 20 69 6E 73 74 65 61 64 08 07 FFFFFF81
   22 07 FFFFFFA0 FFFFFF80 04 78 01 0E 50 4F 53 5F 49 4E 46 5F
   46 4C 4F 41 54 20 08 09 FFFFFF81 24 07 FFFFFFC2 FFFFFF80 FFFFFF84 00 FFFFFF81
   25 01 0A 4D 49 4E 5F 44 4F 55 42 4C 45 15 02 FFFFFF81
   26 10 03 06 FFFFFF81 27 09 03 FFFFFF81 28 02 02 06 44 6F 75
   62 6C 65 28 05 FFFFFF81 23 1F FFFFFF81 2A 21 02 FFFFFF81 2B 01 21
   55 73 65 20 73 63 61 6C 61 2E 44 6F 75 62 6C 65
   2E 4D 69 6E 56 61 6C 75 65 20 69 6E 73 74 65 61
   64 08 08 FFFFFF81 2D 07 FFFFFFA0 FFFFFF80 04 FFFFFF81 26 01 0B 4D 49 4E
   5F 44 4F 55 42 4C 45 20 08 09 FFFFFF81 2F 07 FFFFFFC2 FFFFFF80 FFFFFF84
   00 FFFFFF81 25 01 0A 45 50 53 5F 44 4F 55 42 4C 45 28
   05 FFFFFF81 2E 1F FFFFFF81 31 21 02 FFFFFF81 32 01 20 55 73 65 20
   73 63 61 6C 61 2E 44 6F 75 62 6C 65 2E 45 70 73
   69 6C 6F 6E 20 69 6E 73 74 65 61 64 08 08 FFFFFF81 34
   07 FFFFFFA0 FFFFFF80 04 FFFFFF81 26 01 0B 45 50 53 5F 44 4F 55 42
   4C 45 20 08 09 FFFFFF81 36 07 FFFFFFC2 FFFFFF80 FFFFFF84 00 FFFFFF81 25 01 0A
   4D 41 58 5F 44 4F 55 42 4C 45 28 05 FFFFFF81 35 1F FFFFFF81
   38 21 02 FFFFFF81 39 01 21 55 73 65 20 73 63 61 6C 61
   2E 44 6F 75 62 6C 65 2E 4D 61 78 56 61 6C 75 65
   20 69 6E 73 74 65 61 64 08 08 FFFFFF81 3B 07 FFFFFFA0 FFFFFF80 04
   FFFFFF81 26 01 0B 4D 41 58 5F 44 4F 55 42 4C 45 20 08
   09 FFFFFF81 3D 07 FFFFFFC2 FFFFFF80 FFFFFF84 00 FFFFFF81 25 01 0A 4E 61 4E 5F
   44 4F 55 42 4C 45 28 05 FFFFFF81 3C 1F FFFFFF81 3F 21 02 FFFFFF81
   40 01 1C 55 73 65 20 73 63 61 6C 61 2E 44 6F 75
   62 6C 65 2E 4E 61 4E 20 69 6E 73 74 65 61 64 08
   08 FFFFFF81 42 07 FFFFFFA0 FFFFFF80 04 FFFFFF81 26 01 0B 4E 61 4E 5F 44
   4F 55 42 4C 45 20 08 09 FFFFFF81 44 07 FFFFFFC2 FFFFFF80 FFFFFF84 00 FFFFFF81
   25 01 0E 4E 45 47 5F 49 4E 46 5F 44 4F 55 42 4C
   45 28 05 FFFFFF81 43 1F FFFFFF81 46 21 02 FFFFFF81 47 01 29 55 73
   65 20 73 63 61 6C 61 2E 44 6F 75 62 6C 65 2E 4E
   65 67 61 74 69 76 65 49 6E 66 69 6E 69 74 79 20
   69 6E 73 74 65 61 64 08 08 FFFFFF81 49 07 FFFFFFA0 FFFFFF80 04 FFFFFF81
   26 01 0F 4E 45 47 5F 49 4E 46 5F 44 4F 55 42 4C
   45 20 08 09 FFFFFF81 4B 07 FFFFFFC2 FFFFFF80 FFFFFF84 00 FFFFFF81 25 01 0E 50
   4F 53 5F 49 4E 46 5F 44 4F 55 42 4C 45 28 05 FFFFFF81
   4A 1F FFFFFF81 4D 21 02 FFFFFF81 4E 01 29 55 73 65 20 73 63
   61 6C 61 2E 44 6F 75 62 6C 65 2E 50 6F 73 69 74
   69 76 65 49 6E 66 69 6E 69 74 79 20 69 6E 73 74
   65 61 64 08 08 FFFFFF81 50 07 FFFFFFA0 FFFFFF80 04 FFFFFF81 26 01 0F 50
   4F 53 5F 49 4E 46 5F 44 4F 55 42 4C 45 20 08 09
   FFFFFF81 52 07 FFFFFFC2 FFFFFF80 FFFFFF84 00 FFFFFF81 25 01 01 45 08 08 FFFFFF81 54
   07 FFFFFFA0 FFFFFF80 04 FFFFFF81 26 01 02 45 20 08 09 FFFFFF81 56 07 FFFFFFC2
   FFFFFF80 FFFFFF84 00 FFFFFF81 25 01 02 50 69 08 08 FFFFFF81 58 07 FFFFFFA0 FFFFFF80
   04 FFFFFF81 26 01 03 50 69 20 08 07 FFFFFF81 5A 07 FFFFFF84 00 FFFFFF81
   25 01 06 72 61 6E 64 6F 6D 08 07 FFFFFF81 5C 07 FFFFFF84 00
   FFFFFF81 5D 01 03 73 69 6E 14 04 FFFFFF81 26 FFFFFF81 5E 08 08 FFFFFF81
   5F FFFFFF81 5B FFFFFFC0 00 FFFFFF81 26 01 01 78 08 07 FFFFFF81 61 07 FFFFFF84
   00 FFFFFF81 62 01 03 63 6F 73 14 04 FFFFFF81 26 FFFFFF81 63 08 08
   FFFFFF81 5F FFFFFF81 60 FFFFFFC0 00 FFFFFF81 26 08 07 FFFFFF81 65 07 FFFFFF84 00 FFFFFF81
   66 01 03 74 61 6E 14 04 FFFFFF81 26 FFFFFF81 67 08 08 FFFFFF81 5F
   FFFFFF81 64 FFFFFFC0 00 FFFFFF81 26 08 07 FFFFFF81 69 07 FFFFFF84 00 FFFFFF81 6A 01
   04 61 73 69 6E 14 04 FFFFFF81 26 FFFFFF81 6B 08 08 FFFFFF81 5F FFFFFF81
   68 FFFFFFC0 00 FFFFFF81 26 08 07 FFFFFF81 6D 07 FFFFFF84 00 FFFFFF81 6E 01 04
   61 63 6F 73 14 04 FFFFFF81 26 FFFFFF81 6F 08 08 FFFFFF81 5F FFFFFF81 6C
   FFFFFFC0 00 FFFFFF81 26 08 07 FFFFFF81 71 07 FFFFFF84 00 FFFFFF81 72 01 04 61
   74 61 6E 14 04 FFFFFF81 26 FFFFFF81 73 08 08 FFFFFF81 5F FFFFFF81 70 FFFFFFC0
   00 FFFFFF81 26 08 07 FFFFFF81 75 07 FFFFFF84 00 FFFFFF81 76 01 09 74 6F
   52 61 64 69 61 6E 73 14 04 FFFFFF81 26 FFFFFF81 77 08 08 FFFFFF81
   5F FFFFFF81 74 FFFFFFC0 00 FFFFFF81 26 08 07 FFFFFF81 79 07 FFFFFF84 00 FFFFFF81 7A
   01 09 74 6F 44 65 67 72 65 65 73 14 04 FFFFFF81 26 FFFFFF81
   7B 08 08 FFFFFF81 5F FFFFFF81 78 FFFFFFC0 00 FFFFFF81 26 08 07 FFFFFF81 7D 07
   FFFFFF84 00 FFFFFF81 7E 01 03 65 78 70 14 04 FFFFFF81 26 FFFFFF81 7F 08
   08 FFFFFF81 5F FFFFFF81 7C FFFFFFC0 00 FFFFFF81 26 08 07 FFFFFF82 01 07 FFFFFF84 00
   FFFFFF82 02 01 03 6C 6F 67 14 04 FFFFFF81 26 FFFFFF82 03 08 08 FFFFFF81
   5F FFFFFF82 00 FFFFFFC0 00 FFFFFF81 26 08 07 FFFFFF82 05 07 FFFFFF84 00 FFFFFF82 06
   01 04 73 71 72 74 14 04 FFFFFF81 26 FFFFFF82 07 08 08 FFFFFF81 5F
   FFFFFF82 04 FFFFFFC0 00 FFFFFF81 26 08 07 FFFFFF82 09 07 FFFFFF84 00 FFFFFF82 0A 01
   0D 49 45 45 45 72 65 6D 61 69 6E 64 65 72 14 06
   FFFFFF81 26 FFFFFF82 0B FFFFFF82 0C 08 08 FFFFFF81 5F FFFFFF82 08 FFFFFFC0 00 FFFFFF81 26
   08 08 FFFFFF82 0D FFFFFF82 08 FFFFFFC0 00 FFFFFF81 26 01 01 79 08 07 FFFFFF82
   0F 07 FFFFFF84 00 FFFFFF82 10 01 04 63 65 69 6C 14 04 FFFFFF81 26
   FFFFFF82 11 08 08 FFFFFF81 5F FFFFFF82 0E FFFFFFC0 00 FFFFFF81 26 08 07 FFFFFF82 13
   07 FFFFFF84 00 FFFFFF82 14 01 05 66 6C 6F 6F 72 14 04 FFFFFF81 26
   FFFFFF82 15 08 08 FFFFFF81 5F FFFFFF82 12 FFFFFFC0 00 FFFFFF81 26 08 07 FFFFFF82 17
   07 FFFFFF84 00 FFFFFF82 18 01 04 72 69 6E 74 14 04 FFFFFF81 26 FFFFFF82
   19 08 08 FFFFFF81 5F FFFFFF82 16 FFFFFFC0 00 FFFFFF81 26 08 07 FFFFFF82 1B 07
   FFFFFF84 00 FFFFFF82 1C 01 05 61 74 61 6E 32 14 06 FFFFFF81 26 FFFFFF82
   1D FFFFFF82 1E 08 08 FFFFFF82 0D FFFFFF82 1A FFFFFFC0 00 FFFFFF81 26 08 08 FFFFFF81
   5F FFFFFF82 1A FFFFFFC0 00 FFFFFF81 26 08 07 FFFFFF82 20 07 FFFFFF84 00 FFFFFF82 21
   01 03 70 6F 77 14 06 FFFFFF81 26 FFFFFF82 22 FFFFFF82 23 08 08 FFFFFF81
   5F FFFFFF82 1F FFFFFFC0 00 FFFFFF81 26 08 08 FFFFFF82 0D FFFFFF82 1F FFFFFFC0 00 FFFFFF81
   26 08 07 FFFFFF82 25 07 FFFFFF84 00 FFFFFF82 26 01 05 72 6F 75 6E
   64 14 03 54 FFFFFF82 27 08 07 FFFFFF81 5F FFFFFF82 24 FFFFFFC0 00 78 08
   07 FFFFFF82 25 07 FFFFFF84 00 FFFFFF82 29 14 03 66 FFFFFF82 2A 08 08 FFFFFF81
   5F FFFFFF82 28 FFFFFFC0 00 FFFFFF81 26 08 07 FFFFFF82 2C 07 FFFFFF84 00 FFFFFF82 2D
   01 03 61 62 73 14 03 54 FFFFFF82 2E 08 07 FFFFFF81 5F FFFFFF82 2B
   FFFFFFC0 00 54 08 07 FFFFFF82 2C 07 FFFFFF84 00 FFFFFF82 30 14 03 66 FFFFFF82
   31 08 07 FFFFFF81 5F FFFFFF82 2F FFFFFFC0 00 66 08 07 FFFFFF82 2C 07 FFFFFF84
   00 FFFFFF82 33 14 03 78 FFFFFF82 34 08 07 FFFFFF81 5F FFFFFF82 32 FFFFFFC0 00
   78 08 07 FFFFFF82 2C 07 FFFFFF84 00 FFFFFF82 36 14 04 FFFFFF81 26 FFFFFF82 37
   08 08 FFFFFF81 5F FFFFFF82 35 FFFFFFC0 00 FFFFFF81 26 08 07 FFFFFF82 39 07 FFFFFF84
   00 FFFFFF82 3A 01 03 6D 61 78 14 05 54 FFFFFF82 3B FFFFFF82 3C 08
   07 FFFFFF81 5F FFFFFF82 38 FFFFFFC0 00 54 08 07 FFFFFF82 0D FFFFFF82 38 FFFFFFC0 00
   54 08 07 FFFFFF82 39 07 FFFFFF84 00 FFFFFF82 3E 14 05 66 FFFFFF82 3F FFFFFF82
   40 08 07 FFFFFF81 5F FFFFFF82 3D FFFFFFC0 00 66 08 07 FFFFFF82 0D FFFFFF82 3D
   FFFFFFC0 00 66 08 07 FFFFFF82 39 07 FFFFFF84 00 FFFFFF82 42 14 05 78 FFFFFF82
   43 FFFFFF82 44 08 07 FFFFFF81 5F FFFFFF82 41 FFFFFFC0 00 78 08 07 FFFFFF82 0D
   FFFFFF82 41 FFFFFFC0 00 78 08 07 FFFFFF82 39 07 FFFFFF84 00 FFFFFF82 46 14 06
   FFFFFF81 26 FFFFFF82 47 FFFFFF82 48 08 08 FFFFFF81 5F FFFFFF82 45 FFFFFFC0 00 FFFFFF81 26
   08 08 FFFFFF82 0D FFFFFF82 45 FFFFFFC0 00 FFFFFF81 26 08 07 FFFFFF82 4A 07 FFFFFF84
   00 FFFFFF82 4B 01 03 6D 69 6E 14 05 54 FFFFFF82 4C FFFFFF82 4D 08
   07 FFFFFF81 5F FFFFFF82 49 FFFFFFC0 00 54 08 07 FFFFFF82 0D FFFFFF82 49 FFFFFFC0 00
   54 08 07 FFFFFF82 4A 07 FFFFFF84 00 FFFFFF82 4F 14 05 66 FFFFFF82 50 FFFFFF82
   51 08 07 FFFFFF81 5F FFFFFF82 4E FFFFFFC0 00 66 08 07 FFFFFF82 0D FFFFFF82 4E
   FFFFFFC0 00 66 08 07 FFFFFF82 4A 07 FFFFFF84 00 FFFFFF82 53 14 05 78 FFFFFF82
   54 FFFFFF82 55 08 07 FFFFFF81 5F FFFFFF82 52 FFFFFFC0 00 78 08 07 FFFFFF82 0D
   FFFFFF82 52 FFFFFFC0 00 78 08 07 FFFFFF82 4A 07 FFFFFF84 00 FFFFFF82 57 14 06
   FFFFFF81 26 FFFFFF82 58 FFFFFF82 59 08 08 FFFFFF81 5F FFFFFF82 56 FFFFFFC0 00 FFFFFF81 26
   08 08 FFFFFF82 0D FFFFFF82 56 FFFFFFC0 00 FFFFFF81 26 08 07 FFFFFF82 5B 07 FFFFFF84
   00 FFFFFF82 5C 01 06 73 69 67 6E 75 6D 14 04 FFFFFF81 26 FFFFFF82
   5D 08 08 FFFFFF81 5F FFFFFF82 5A FFFFFFC0 00 FFFFFF81 26 08 07 FFFFFF82 5B 07
   FFFFFF84 00 FFFFFF82 5F 14 03 78 FFFFFF82 60 08 07 FFFFFF81 5F FFFFFF82 5E FFFFFFC0
   00 78 08 07 FFFFFF82 5B 07 FFFFFF84 00 FFFFFF82 62 14 03 66 FFFFFF82 63
   08 07 FFFFFF81 5F FFFFFF82 61 FFFFFFC0 00 66 08 07 FFFFFF82 5B 07 FFFFFF84 00
   FFFFFF82 65 14 03 54 FFFFFF82 66 08 07 FFFFFF81 5F FFFFFF82 64 FFFFFFC0 00 54
   28 04 07 1F FFFFFF82 68 21 02 FFFFFF82 69 01 1E 75 73 65 20
   73 63 61 6C 61 2E 6D 61 74 68 20 70 61 63 6B 61
   67 65 20 69 6E 73 74 65 61 64 
  minor version: 0
  major version: 49
  Constant pool:
Asciz	SourceFile;
Asciz	Math.scala;
Asciz	signum;
Asciz	(I)I;
Asciz	Code;
Asciz	scala/Math$;
class	scala/Math$
Asciz	MODULE$;
Asciz	Lscala/Math$;;
NameAndType	MODULE$:Lscala/Math$;
Field	scala/Math$.MODULE$:Lscala/Math$;
NameAndType	signum:(I)I
Method	scala/Math$.signum:(I)I
Asciz	(J)J;
NameAndType	signum:(J)J
Method	scala/Math$.signum:(J)J
Asciz	(F)F;
NameAndType	signum:(F)F
Method	scala/Math$.signum:(F)F
Asciz	(D)D;
NameAndType	signum:(D)D
Method	scala/Math$.signum:(D)D
Asciz	min;
Asciz	(DD)D;
NameAndType	min:(DD)D
Method	scala/Math$.min:(DD)D
Asciz	(FF)F;
NameAndType	min:(FF)F
Method	scala/Math$.min:(FF)F
Asciz	(JJ)J;
NameAndType	min:(JJ)J
Method	scala/Math$.min:(JJ)J
Asciz	(II)I;
NameAndType	min:(II)I
Method	scala/Math$.min:(II)I
Asciz	max;
NameAndType	max:(DD)D
Method	scala/Math$.max:(DD)D
NameAndType	max:(FF)F
Method	scala/Math$.max:(FF)F
NameAndType	max:(JJ)J
Method	scala/Math$.max:(JJ)J
NameAndType	max:(II)I
Method	scala/Math$.max:(II)I
Asciz	abs;
NameAndType	abs:(D)D
Method	scala/Math$.abs:(D)D
NameAndType	abs:(F)F
Method	scala/Math$.abs:(F)F
NameAndType	abs:(J)J
Method	scala/Math$.abs:(J)J
NameAndType	abs:(I)I
Method	scala/Math$.abs:(I)I
Asciz	round;
Asciz	(D)J;
NameAndType	round:(D)J
Method	scala/Math$.round:(D)J
Asciz	(F)I;
NameAndType	round:(F)I
Method	scala/Math$.round:(F)I
Asciz	pow;
NameAndType	pow:(DD)D
Method	scala/Math$.pow:(DD)D
Asciz	atan2;
NameAndType	atan2:(DD)D
Method	scala/Math$.atan2:(DD)D
Asciz	rint;
NameAndType	rint:(D)D
Method	scala/Math$.rint:(D)D
Asciz	floor;
NameAndType	floor:(D)D
Method	scala/Math$.floor:(D)D
Asciz	ceil;
NameAndType	ceil:(D)D
Method	scala/Math$.ceil:(D)D
Asciz	IEEEremainder;
NameAndType	IEEEremainder:(DD)D
Method	scala/Math$.IEEEremainder:(DD)D
Asciz	sqrt;
NameAndType	sqrt:(D)D
Method	scala/Math$.sqrt:(D)D
Asciz	log;
NameAndType	log:(D)D
Method	scala/Math$.log:(D)D
Asciz	exp;
NameAndType	exp:(D)D
Method	scala/Math$.exp:(D)D
Asciz	toDegrees;
NameAndType	toDegrees:(D)D
Method	scala/Math$.toDegrees:(D)D
Asciz	toRadians;
NameAndType	toRadians:(D)D
Method	scala/Math$.toRadians:(D)D
Asciz	atan;
NameAndType	atan:(D)D
Method	scala/Math$.atan:(D)D
Asciz	acos;
NameAndType	acos:(D)D
Method	scala/Math$.acos:(D)D
Asciz	asin;
NameAndType	asin:(D)D
Method	scala/Math$.asin:(D)D
Asciz	tan;
NameAndType	tan:(D)D
Method	scala/Math$.tan:(D)D
Asciz	cos;
NameAndType	cos:(D)D
Method	scala/Math$.cos:(D)D
Asciz	sin;
NameAndType	sin:(D)D
Method	scala/Math$.sin:(D)D
Asciz	random;
Asciz	()D;
NameAndType	random:()D
Method	scala/Math$.random:()D
Asciz	Pi;
NameAndType	Pi:()D
Method	scala/Math$.Pi:()D
Asciz	E;
NameAndType	E:()D
Method	scala/Math$.E:()D
Asciz	POS_INF_DOUBLE;
NameAndType	POS_INF_DOUBLE:()D
Method	scala/Math$.POS_INF_DOUBLE:()D
Asciz	NEG_INF_DOUBLE;
NameAndType	NEG_INF_DOUBLE:()D
Method	scala/Math$.NEG_INF_DOUBLE:()D
Asciz	NaN_DOUBLE;
NameAndType	NaN_DOUBLE:()D
Method	scala/Math$.NaN_DOUBLE:()D
Asciz	MAX_DOUBLE;
NameAndType	MAX_DOUBLE:()D
Method	scala/Math$.MAX_DOUBLE:()D
Asciz	EPS_DOUBLE;
NameAndType	EPS_DOUBLE:()D
Method	scala/Math$.EPS_DOUBLE:()D
Asciz	MIN_DOUBLE;
NameAndType	MIN_DOUBLE:()D
Method	scala/Math$.MIN_DOUBLE:()D
Asciz	POS_INF_FLOAT;
Asciz	()F;
NameAndType	POS_INF_FLOAT:()F
Method	scala/Math$.POS_INF_FLOAT:()F
Asciz	NEG_INF_FLOAT;
NameAndType	NEG_INF_FLOAT:()F
Method	scala/Math$.NEG_INF_FLOAT:()F
Asciz	NaN_FLOAT;
NameAndType	NaN_FLOAT:()F
Method	scala/Math$.NaN_FLOAT:()F
Asciz	MAX_FLOAT;
NameAndType	MAX_FLOAT:()F
Method	scala/Math$.MAX_FLOAT:()F
Asciz	EPS_FLOAT;
NameAndType	EPS_FLOAT:()F
Method	scala/Math$.EPS_FLOAT:()F
Asciz	MIN_FLOAT;
NameAndType	MIN_FLOAT:()F
Method	scala/Math$.MIN_FLOAT:()F
Asciz	MAX_LONG;
Asciz	()J;
NameAndType	MAX_LONG:()J
Method	scala/Math$.MAX_LONG:()J
Asciz	MIN_LONG;
NameAndType	MIN_LONG:()J
Method	scala/Math$.MIN_LONG:()J
Asciz	MAX_INT;
Asciz	()I;
NameAndType	MAX_INT:()I
Method	scala/Math$.MAX_INT:()I
Asciz	MIN_INT;
NameAndType	MIN_INT:()I
Method	scala/Math$.MIN_INT:()I
Asciz	MAX_CHAR;
Asciz	()C;
NameAndType	MAX_CHAR:()C
Method	scala/Math$.MAX_CHAR:()C
Asciz	MIN_CHAR;
NameAndType	MIN_CHAR:()C
Method	scala/Math$.MIN_CHAR:()C
Asciz	MAX_SHORT;
Asciz	()S;
NameAndType	MAX_SHORT:()S
Method	scala/Math$.MAX_SHORT:()S
Asciz	MIN_SHORT;
NameAndType	MIN_SHORT:()S
Method	scala/Math$.MIN_SHORT:()S
Asciz	MAX_BYTE;
Asciz	()B;
NameAndType	MAX_BYTE:()B
Method	scala/Math$.MAX_BYTE:()B
Asciz	MIN_BYTE;
NameAndType	MIN_BYTE:()B
Method	scala/Math$.MIN_BYTE:()B
Asciz	ScalaSig;
Asciz	scala/Math;
class	scala/Math
Asciz	java/lang/Object;
class	java/lang/Object

{
public static final int signum(int);
  Signature: (I)I
  Code:
   Stack=2, Locals=1, Args_size=1
	getstatic	Field scala/Math$.MODULE$:Lscala/Math$;
	iload_0
	invokevirtual	Method scala/Math$.signum:(I)I
	ireturn
  Labels:

public static final long signum(long);
  Signature: (J)J
  Code:
   Stack=3, Locals=2, Args_size=1
	getstatic	Field scala/Math$.MODULE$:Lscala/Math$;
	lload_0
	invokevirtual	Method scala/Math$.signum:(J)J
	lreturn
  Labels:

public static final float signum(float);
  Signature: (F)F
  Code:
   Stack=2, Locals=1, Args_size=1
	getstatic	Field scala/Math$.MODULE$:Lscala/Math$;
	fload_0
	invokevirtual	Method scala/Math$.signum:(F)F
	freturn
  Labels:

public static final double signum(double);
  Signature: (D)D
  Code:
   Stack=3, Locals=2, Args_size=1
	getstatic	Field scala/Math$.MODULE$:Lscala/Math$;
	dload_0
	invokevirtual	Method scala/Math$.signum:(D)D
	dreturn
  Labels:

public static final double min(double, double);
  Signature: (DD)D
  Code:
   Stack=5, Locals=4, Args_size=2
	getstatic	Field scala/Math$.MODULE$:Lscala/Math$;
	dload_0
	dload_2
	invokevirtual	Method scala/Math$.min:(DD)D
	dreturn
  Labels:

public static final float min(float, float);
  Signature: (FF)F
  Code:
   Stack=3, Locals=2, Args_size=2
	getstatic	Field scala/Math$.MODULE$:Lscala/Math$;
	fload_0
	fload_1
	invokevirtual	Method scala/Math$.min:(FF)F
	freturn
  Labels:

public static final long min(long, long);
  Signature: (JJ)J
  Code:
   Stack=5, Locals=4, Args_size=2
	getstatic	Field scala/Math$.MODULE$:Lscala/Math$;
	lload_0
	lload_2
	invokevirtual	Method scala/Math$.min:(JJ)J
	lreturn
  Labels:

public static final int min(int, int);
  Signature: (II)I
  Code:
   Stack=3, Locals=2, Args_size=2
	getstatic	Field scala/Math$.MODULE$:Lscala/Math$;
	iload_0
	iload_1
	invokevirtual	Method scala/Math$.min:(II)I
	ireturn
  Labels:

public static final double max(double, double);
  Signature: (DD)D
  Code:
   Stack=5, Locals=4, Args_size=2
	getstatic	Field scala/Math$.MODULE$:Lscala/Math$;
	dload_0
	dload_2
	invokevirtual	Method scala/Math$.max:(DD)D
	dreturn
  Labels:

public static final float max(float, float);
  Signature: (FF)F
  Code:
   Stack=3, Locals=2, Args_size=2
	getstatic	Field scala/Math$.MODULE$:Lscala/Math$;
	fload_0
	fload_1
	invokevirtual	Method scala/Math$.max:(FF)F
	freturn
  Labels:

public static final long max(long, long);
  Signature: (JJ)J
  Code:
   Stack=5, Locals=4, Args_size=2
	getstatic	Field scala/Math$.MODULE$:Lscala/Math$;
	lload_0
	lload_2
	invokevirtual	Method scala/Math$.max:(JJ)J
	lreturn
  Labels:

public static final int max(int, int);
  Signature: (II)I
  Code:
   Stack=3, Locals=2, Args_size=2
	getstatic	Field scala/Math$.MODULE$:Lscala/Math$;
	iload_0
	iload_1
	invokevirtual	Method scala/Math$.max:(II)I
	ireturn
  Labels:

public static final double abs(double);
  Signature: (D)D
  Code:
   Stack=3, Locals=2, Args_size=1
	getstatic	Field scala/Math$.MODULE$:Lscala/Math$;
	dload_0
	invokevirtual	Method scala/Math$.abs:(D)D
	dreturn
  Labels:

public static final float abs(float);
  Signature: (F)F
  Code:
   Stack=2, Locals=1, Args_size=1
	getstatic	Field scala/Math$.MODULE$:Lscala/Math$;
	fload_0
	invokevirtual	Method scala/Math$.abs:(F)F
	freturn
  Labels:

public static final long abs(long);
  Signature: (J)J
  Code:
   Stack=3, Locals=2, Args_size=1
	getstatic	Field scala/Math$.MODULE$:Lscala/Math$;
	lload_0
	invokevirtual	Method scala/Math$.abs:(J)J
	lreturn
  Labels:

public static final int abs(int);
  Signature: (I)I
  Code:
   Stack=2, Locals=1, Args_size=1
	getstatic	Field scala/Math$.MODULE$:Lscala/Math$;
	iload_0
	invokevirtual	Method scala/Math$.abs:(I)I
	ireturn
  Labels:

public static final long round(double);
  Signature: (D)J
  Code:
   Stack=3, Locals=2, Args_size=1
	getstatic	Field scala/Math$.MODULE$:Lscala/Math$;
	dload_0
	invokevirtual	Method scala/Math$.round:(D)J
	lreturn
  Labels:

public static final int round(float);
  Signature: (F)I
  Code:
   Stack=2, Locals=1, Args_size=1
	getstatic	Field scala/Math$.MODULE$:Lscala/Math$;
	fload_0
	invokevirtual	Method scala/Math$.round:(F)I
	ireturn
  Labels:

public static final double pow(double, double);
  Signature: (DD)D
  Code:
   Stack=5, Locals=4, Args_size=2
	getstatic	Field scala/Math$.MODULE$:Lscala/Math$;
	dload_0
	dload_2
	invokevirtual	Method scala/Math$.pow:(DD)D
	dreturn
  Labels:

public static final double atan2(double, double);
  Signature: (DD)D
  Code:
   Stack=5, Locals=4, Args_size=2
	getstatic	Field scala/Math$.MODULE$:Lscala/Math$;
	dload_0
	dload_2
	invokevirtual	Method scala/Math$.atan2:(DD)D
	dreturn
  Labels:

public static final double rint(double);
  Signature: (D)D
  Code:
   Stack=3, Locals=2, Args_size=1
	getstatic	Field scala/Math$.MODULE$:Lscala/Math$;
	dload_0
	invokevirtual	Method scala/Math$.rint:(D)D
	dreturn
  Labels:

public static final double floor(double);
  Signature: (D)D
  Code:
   Stack=3, Locals=2, Args_size=1
	getstatic	Field scala/Math$.MODULE$:Lscala/Math$;
	dload_0
	invokevirtual	Method scala/Math$.floor:(D)D
	dreturn
  Labels:

public static final double ceil(double);
  Signature: (D)D
  Code:
   Stack=3, Locals=2, Args_size=1
	getstatic	Field scala/Math$.MODULE$:Lscala/Math$;
	dload_0
	invokevirtual	Method scala/Math$.ceil:(D)D
	dreturn
  Labels:

public static final double IEEEremainder(double, double);
  Signature: (DD)D
  Code:
   Stack=5, Locals=4, Args_size=2
	getstatic	Field scala/Math$.MODULE$:Lscala/Math$;
	dload_0
	dload_2
	invokevirtual	Method scala/Math$.IEEEremainder:(DD)D
	dreturn
  Labels:

public static final double sqrt(double);
  Signature: (D)D
  Code:
   Stack=3, Locals=2, Args_size=1
	getstatic	Field scala/Math$.MODULE$:Lscala/Math$;
	dload_0
	invokevirtual	Method scala/Math$.sqrt:(D)D
	dreturn
  Labels:

public static final double log(double);
  Signature: (D)D
  Code:
   Stack=3, Locals=2, Args_size=1
	getstatic	Field scala/Math$.MODULE$:Lscala/Math$;
	dload_0
	invokevirtual	Method scala/Math$.log:(D)D
	dreturn
  Labels:

public static final double exp(double);
  Signature: (D)D
  Code:
   Stack=3, Locals=2, Args_size=1
	getstatic	Field scala/Math$.MODULE$:Lscala/Math$;
	dload_0
	invokevirtual	Method scala/Math$.exp:(D)D
	dreturn
  Labels:

public static final double toDegrees(double);
  Signature: (D)D
  Code:
   Stack=3, Locals=2, Args_size=1
	getstatic	Field scala/Math$.MODULE$:Lscala/Math$;
	dload_0
	invokevirtual	Method scala/Math$.toDegrees:(D)D
	dreturn
  Labels:

public static final double toRadians(double);
  Signature: (D)D
  Code:
   Stack=3, Locals=2, Args_size=1
	getstatic	Field scala/Math$.MODULE$:Lscala/Math$;
	dload_0
	invokevirtual	Method scala/Math$.toRadians:(D)D
	dreturn
  Labels:

public static final double atan(double);
  Signature: (D)D
  Code:
   Stack=3, Locals=2, Args_size=1
	getstatic	Field scala/Math$.MODULE$:Lscala/Math$;
	dload_0
	invokevirtual	Method scala/Math$.atan:(D)D
	dreturn
  Labels:

public static final double acos(double);
  Signature: (D)D
  Code:
   Stack=3, Locals=2, Args_size=1
	getstatic	Field scala/Math$.MODULE$:Lscala/Math$;
	dload_0
	invokevirtual	Method scala/Math$.acos:(D)D
	dreturn
  Labels:

public static final double asin(double);
  Signature: (D)D
  Code:
   Stack=3, Locals=2, Args_size=1
	getstatic	Field scala/Math$.MODULE$:Lscala/Math$;
	dload_0
	invokevirtual	Method scala/Math$.asin:(D)D
	dreturn
  Labels:

public static final double tan(double);
  Signature: (D)D
  Code:
   Stack=3, Locals=2, Args_size=1
	getstatic	Field scala/Math$.MODULE$:Lscala/Math$;
	dload_0
	invokevirtual	Method scala/Math$.tan:(D)D
	dreturn
  Labels:

public static final double cos(double);
  Signature: (D)D
  Code:
   Stack=3, Locals=2, Args_size=1
	getstatic	Field scala/Math$.MODULE$:Lscala/Math$;
	dload_0
	invokevirtual	Method scala/Math$.cos:(D)D
	dreturn
  Labels:

public static final double sin(double);
  Signature: (D)D
  Code:
   Stack=3, Locals=2, Args_size=1
	getstatic	Field scala/Math$.MODULE$:Lscala/Math$;
	dload_0
	invokevirtual	Method scala/Math$.sin:(D)D
	dreturn
  Labels:

public static final double random();
  Signature: ()D
  Code:
   Stack=2, Locals=0, Args_size=0
	getstatic	Field scala/Math$.MODULE$:Lscala/Math$;
	invokevirtual	Method scala/Math$.random:()D
	dreturn
  Labels:

public static final double Pi();
  Signature: ()D
  Code:
   Stack=2, Locals=0, Args_size=0
	getstatic	Field scala/Math$.MODULE$:Lscala/Math$;
	invokevirtual	Method scala/Math$.Pi:()D
	dreturn
  Labels:

public static final double E();
  Signature: ()D
  Code:
   Stack=2, Locals=0, Args_size=0
	getstatic	Field scala/Math$.MODULE$:Lscala/Math$;
	invokevirtual	Method scala/Math$.E:()D
	dreturn
  Labels:

public static final double POS_INF_DOUBLE();
  Signature: ()D
  Code:
   Stack=2, Locals=0, Args_size=0
	getstatic	Field scala/Math$.MODULE$:Lscala/Math$;
	invokevirtual	Method scala/Math$.POS_INF_DOUBLE:()D
	dreturn
  Labels:

public static final double NEG_INF_DOUBLE();
  Signature: ()D
  Code:
   Stack=2, Locals=0, Args_size=0
	getstatic	Field scala/Math$.MODULE$:Lscala/Math$;
	invokevirtual	Method scala/Math$.NEG_INF_DOUBLE:()D
	dreturn
  Labels:

public static final double NaN_DOUBLE();
  Signature: ()D
  Code:
   Stack=2, Locals=0, Args_size=0
	getstatic	Field scala/Math$.MODULE$:Lscala/Math$;
	invokevirtual	Method scala/Math$.NaN_DOUBLE:()D
	dreturn
  Labels:

public static final double MAX_DOUBLE();
  Signature: ()D
  Code:
   Stack=2, Locals=0, Args_size=0
	getstatic	Field scala/Math$.MODULE$:Lscala/Math$;
	invokevirtual	Method scala/Math$.MAX_DOUBLE:()D
	dreturn
  Labels:

public static final double EPS_DOUBLE();
  Signature: ()D
  Code:
   Stack=2, Locals=0, Args_size=0
	getstatic	Field scala/Math$.MODULE$:Lscala/Math$;
	invokevirtual	Method scala/Math$.EPS_DOUBLE:()D
	dreturn
  Labels:

public static final double MIN_DOUBLE();
  Signature: ()D
  Code:
   Stack=2, Locals=0, Args_size=0
	getstatic	Field scala/Math$.MODULE$:Lscala/Math$;
	invokevirtual	Method scala/Math$.MIN_DOUBLE:()D
	dreturn
  Labels:

public static final float POS_INF_FLOAT();
  Signature: ()F
  Code:
   Stack=1, Locals=0, Args_size=0
	getstatic	Field scala/Math$.MODULE$:Lscala/Math$;
	invokevirtual	Method scala/Math$.POS_INF_FLOAT:()F
	freturn
  Labels:

public static final float NEG_INF_FLOAT();
  Signature: ()F
  Code:
   Stack=1, Locals=0, Args_size=0
	getstatic	Field scala/Math$.MODULE$:Lscala/Math$;
	invokevirtual	Method scala/Math$.NEG_INF_FLOAT:()F
	freturn
  Labels:

public static final float NaN_FLOAT();
  Signature: ()F
  Code:
   Stack=1, Locals=0, Args_size=0
	getstatic	Field scala/Math$.MODULE$:Lscala/Math$;
	invokevirtual	Method scala/Math$.NaN_FLOAT:()F
	freturn
  Labels:

public static final float MAX_FLOAT();
  Signature: ()F
  Code:
   Stack=1, Locals=0, Args_size=0
	getstatic	Field scala/Math$.MODULE$:Lscala/Math$;
	invokevirtual	Method scala/Math$.MAX_FLOAT:()F
	freturn
  Labels:

public static final float EPS_FLOAT();
  Signature: ()F
  Code:
   Stack=1, Locals=0, Args_size=0
	getstatic	Field scala/Math$.MODULE$:Lscala/Math$;
	invokevirtual	Method scala/Math$.EPS_FLOAT:()F
	freturn
  Labels:

public static final float MIN_FLOAT();
  Signature: ()F
  Code:
   Stack=1, Locals=0, Args_size=0
	getstatic	Field scala/Math$.MODULE$:Lscala/Math$;
	invokevirtual	Method scala/Math$.MIN_FLOAT:()F
	freturn
  Labels:

public static final long MAX_LONG();
  Signature: ()J
  Code:
   Stack=2, Locals=0, Args_size=0
	getstatic	Field scala/Math$.MODULE$:Lscala/Math$;
	invokevirtual	Method scala/Math$.MAX_LONG:()J
	lreturn
  Labels:

public static final long MIN_LONG();
  Signature: ()J
  Code:
   Stack=2, Locals=0, Args_size=0
	getstatic	Field scala/Math$.MODULE$:Lscala/Math$;
	invokevirtual	Method scala/Math$.MIN_LONG:()J
	lreturn
  Labels:

public static final int MAX_INT();
  Signature: ()I
  Code:
   Stack=1, Locals=0, Args_size=0
	getstatic	Field scala/Math$.MODULE$:Lscala/Math$;
	invokevirtual	Method scala/Math$.MAX_INT:()I
	ireturn
  Labels:

public static final int MIN_INT();
  Signature: ()I
  Code:
   Stack=1, Locals=0, Args_size=0
	getstatic	Field scala/Math$.MODULE$:Lscala/Math$;
	invokevirtual	Method scala/Math$.MIN_INT:()I
	ireturn
  Labels:

public static final char MAX_CHAR();
  Signature: ()C
  Code:
   Stack=1, Locals=0, Args_size=0
	getstatic	Field scala/Math$.MODULE$:Lscala/Math$;
	invokevirtual	Method scala/Math$.MAX_CHAR:()C
	ireturn
  Labels:

public static final char MIN_CHAR();
  Signature: ()C
  Code:
   Stack=1, Locals=0, Args_size=0
	getstatic	Field scala/Math$.MODULE$:Lscala/Math$;
	invokevirtual	Method scala/Math$.MIN_CHAR:()C
	ireturn
  Labels:

public static final short MAX_SHORT();
  Signature: ()S
  Code:
   Stack=1, Locals=0, Args_size=0
	getstatic	Field scala/Math$.MODULE$:Lscala/Math$;
	invokevirtual	Method scala/Math$.MAX_SHORT:()S
	ireturn
  Labels:

public static final short MIN_SHORT();
  Signature: ()S
  Code:
   Stack=1, Locals=0, Args_size=0
	getstatic	Field scala/Math$.MODULE$:Lscala/Math$;
	invokevirtual	Method scala/Math$.MIN_SHORT:()S
	ireturn
  Labels:

public static final byte MAX_BYTE();
  Signature: ()B
  Code:
   Stack=1, Locals=0, Args_size=0
	getstatic	Field scala/Math$.MODULE$:Lscala/Math$;
	invokevirtual	Method scala/Math$.MAX_BYTE:()B
	ireturn
  Labels:

public static final byte MIN_BYTE();
  Signature: ()B
  Code:
   Stack=1, Locals=0, Args_size=0
	getstatic	Field scala/Math$.MODULE$:Lscala/Math$;
	invokevirtual	Method scala/Math$.MIN_BYTE:()B
	ireturn
  Labels:

}

