Compiled from "List.scala"
public final class scala.Nil$ extends scala.List implements java.io.Serializable,scala.Product
  Scala: length = 0x
   
  Signature: length = 0x2
   00 31 
  SourceFile: "List.scala"
  minor version: 0
  major version: 49
  Constant pool:
String	Nil
String	head of empty list
String	tail of empty list
class	java/io/Serializable
class	java/lang/IndexOutOfBoundsException
class	java/lang/Object
class	java/util/NoSuchElementException
class	scala/List
class	scala/Nil$
class	scala/Product
class	scala/runtime/BoxesRunTime
long	-8256821097970055419l;
Field	scala/Nil$.MODULE$:Lscala/Nil$;
Field	scala/Nil$.serialVersionUID:J
Method	java/lang/IndexOutOfBoundsException."<init>":(Ljava/lang/String;)V
Method	java/lang/Object.toString:()Ljava/lang/String;
Method	java/util/NoSuchElementException."<init>":(Ljava/lang/String;)V
Method	scala/List."<init>":()V
Method	scala/Nil$."<init>":()V
Method	scala/Nil$.head:()Lscala/runtime/Nothing$;
Method	scala/runtime/BoxesRunTime.boxToInteger:(I)Ljava/lang/Integer;
NameAndType	"<init>":()V
NameAndType	"<init>":(Ljava/lang/String;)V
NameAndType	MODULE$:Lscala/Nil$;
NameAndType	boxToInteger:(I)Ljava/lang/Integer;
NameAndType	head:()Lscala/runtime/Nothing$;
NameAndType	serialVersionUID:J
NameAndType	toString:()Ljava/lang/String;
Asciz	()I;
Asciz	()Ljava/lang/Object;;
Asciz	()Ljava/lang/String;;
Asciz	()Lscala/List;;
Asciz	()Lscala/List<Lscala/Nothing;>;;
Asciz	()Lscala/runtime/Nothing$;;
Asciz	()V;
Asciz	()Z;
Asciz	(I)Ljava/lang/Integer;;
Asciz	(I)Ljava/lang/Object;;
Asciz	(Ljava/lang/String;)V;
Asciz	<clinit>;
Asciz	<init>;
Asciz	Code;
Asciz	I;
Asciz	J;
Asciz	LineNumberTable;
Asciz	List.scala;
Asciz	LocalVariableTable;
Asciz	Lscala/List<Lscala/Nothing;>;Lscala/Product;;
Asciz	Lscala/Nil$;;
Asciz	MODULE$;
Asciz	Nil;
Asciz	Scala;
Asciz	Signature;
Asciz	SourceFile;
Asciz	boxToInteger;
Asciz	head;
Asciz	head of empty list;
Asciz	isEmpty;
Asciz	java/io/Serializable;
Asciz	java/lang/IndexOutOfBoundsException;
Asciz	java/lang/Object;
Asciz	java/util/NoSuchElementException;
Asciz	productArity;
Asciz	productElement;
Asciz	productPrefix;
Asciz	scala/List;
Asciz	scala/Nil$;
Asciz	scala/Product;
Asciz	scala/runtime/BoxesRunTime;
Asciz	serialVersionUID;
Asciz	tail;
Asciz	tail of empty list;
Asciz	this;
Asciz	toString;
Asciz	x$1;

{
public static final scala.Nil$ MODULE$;
  Signature: Lscala/Nil$;

public static final long serialVersionUID;
  Signature: J

public static {};
  Signature: ()V
  Code:
   Stack=2, Locals=0, Args_size=0
	new	class scala/Nil$
	invokespecial	Method "<init>":()V
	ldc2_w	long -8256821097970055419l
	putstatic	Field serialVersionUID:J
	return
  Labels:

public scala.Nil$();
  Signature: ()V
  Code:
   Stack=1, Locals=1, Args_size=1
	aload_0
	invokespecial	Method scala/List."<init>":()V
	aload_0
	putstatic	Field MODULE$:Lscala/Nil$;
	return
  Labels:

public java.lang.Object head();
  Signature: ()Ljava/lang/Object;
  Code:
   Stack=1, Locals=1, Args_size=1
	aload_0
	invokevirtual	Method head:()Lscala/runtime/Nothing$;
	athrow
  Labels:

public java.lang.Object productElement(int);
  Signature: (I)Ljava/lang/Object;
  Code:
   Stack=3, Locals=3, Args_size=2
	iload_1
	istore_2
	new	class java/lang/IndexOutOfBoundsException
	dup
	iload_1
	invokestatic	Method scala/runtime/BoxesRunTime.boxToInteger:(I)Ljava/lang/Integer;
	invokevirtual	Method java/lang/Object.toString:()Ljava/lang/String;
	invokespecial	Method java/lang/IndexOutOfBoundsException."<init>":(Ljava/lang/String;)V
	athrow
  Labels:
  LocalVariableTable: 
   Start  Length  Slot  Name   Signature
   0      17      0    this       Lscala/Nil$;
   0      17      1    x$1       I


public int productArity();
  Signature: ()I
  Code:
   Stack=1, Locals=1, Args_size=1
	iconst_0
	ireturn
  Labels:

public java.lang.String productPrefix();
  Signature: ()Ljava/lang/String;
  Code:
   Stack=1, Locals=1, Args_size=1
	ldc	String Nil
	areturn
  Labels:

public scala.List tail();
  Signature: ()Lscala/List;
  Code:
   Stack=3, Locals=1, Args_size=1
	new	class java/util/NoSuchElementException
	dup
	ldc	String tail of empty list
	invokespecial	Method java/util/NoSuchElementException."<init>":(Ljava/lang/String;)V
	athrow
  Labels:
  Signature: length = 0x2
   00 22 

public scala.runtime.Nothing$ head();
  Signature: ()Lscala/runtime/Nothing$;
  Code:
   Stack=3, Locals=1, Args_size=1
	new	class java/util/NoSuchElementException
	dup
	ldc	String head of empty list
	invokespecial	Method java/util/NoSuchElementException."<init>":(Ljava/lang/String;)V
	athrow
  Labels:

public boolean isEmpty();
  Signature: ()Z
  Code:
   Stack=1, Locals=1, Args_size=1
	iconst_1
	ireturn
  Labels:

}

