Compiled from "NotDefinedError.scala"
public final class scala.NotDefinedError extends java.lang.Error implements scala.ScalaObject
  SourceFile: "NotDefinedError.scala"
  ScalaSig: length = 0xBD
   05 00 20 06 08 01 02 FFFFFF84 FFFFFF80 FFFFFF80 FFFFFF80 02 05 02 0F 4E
   6F 74 44 65 66 69 6E 65 64 45 72 72 6F 72 0A 01
   03 01 05 73 63 61 6C 61 03 00 13 03 00 06 0E 10
   02 07 0C 0D 01 08 0A 02 09 0A 01 04 6C 61 6E 67
   0A 01 0B 01 04 6A 61 76 61 09 02 0D 08 02 05 45
   72 72 6F 72 10 02 0F 10 0D 01 02 09 02 11 02 02
   0B 53 63 61 6C 61 4F 62 6A 65 63 74 08 08 13 00
   FFFFFF82 FFFFFF80 FFFFFFA0 FFFFFF80 04 14 01 03 6D 73 67 10 02 15 18 0E
   02 0F 16 09 02 17 02 01 06 50 72 65 64 65 66 09
   02 19 1A 02 06 53 74 72 69 6E 67 0A 02 17 02 08
   05 1C 00 FFFFFF84 00 1D 01 06 3C 69 6E 69 74 3E 14 02
   1E 1F 10 02 0F 00 08 05 13 1B FFFFFFC0 00 14 
  minor version: 0
  major version: 49
  Constant pool:
const #1 = Asciz	SourceFile;
const #2 = Asciz	NotDefinedError.scala;
const #3 = Asciz	<init>;
const #4 = Asciz	(Ljava/lang/String;)V;
const #5 = Asciz	Code;
const #6 = Asciz	LineNumberTable;
const #7 = Asciz	scala/collection/mutable/StringBuilder;
const #8 = class	#7;	//  scala/collection/mutable/StringBuilder
const #9 = Asciz	()V;
const #10 = NameAndType	#3:#9;//  "<init>":()V
const #11 = Method	#8.#10;	//  scala/collection/mutable/StringBuilder."<init>":()V
const #12 = Asciz	not defined: ;
const #13 = String	#12;	//  not defined: 
const #14 = Asciz	append;
const #15 = Asciz	(Ljava/lang/Object;)Lscala/collection/mutable/StringBuilder;;
const #16 = NameAndType	#14:#15;//  append:(Ljava/lang/Object;)Lscala/collection/mutable/StringBuilder;
const #17 = Method	#8.#16;	//  scala/collection/mutable/StringBuilder.append:(Ljava/lang/Object;)Lscala/collection/mutable/StringBuilder;
const #18 = Asciz	toString;
const #19 = Asciz	()Ljava/lang/String;;
const #20 = NameAndType	#18:#19;//  toString:()Ljava/lang/String;
const #21 = Method	#8.#20;	//  scala/collection/mutable/StringBuilder.toString:()Ljava/lang/String;
const #22 = Asciz	java/lang/Error;
const #23 = class	#22;	//  java/lang/Error
const #24 = NameAndType	#3:#4;//  "<init>":(Ljava/lang/String;)V
const #25 = Method	#23.#24;	//  java/lang/Error."<init>":(Ljava/lang/String;)V
const #26 = Asciz	this;
const #27 = Asciz	Lscala/NotDefinedError;;
const #28 = Asciz	msg;
const #29 = Asciz	Ljava/lang/String;;
const #30 = Asciz	LocalVariableTable;
const #31 = Asciz	ScalaSig;
const #32 = Asciz	scala/NotDefinedError;
const #33 = class	#32;	//  scala/NotDefinedError
const #34 = Asciz	scala/ScalaObject;
const #35 = class	#34;	//  scala/ScalaObject

{
public scala.NotDefinedError(java.lang.String);
  Code:
   Stack=3, Locals=2, Args_size=2
   0:	aload_0
   1:	new	#8; //class scala/collection/mutable/StringBuilder
   4:	dup
   5:	invokespecial	#11; //Method scala/collection/mutable/StringBuilder."<init>":()V
   8:	ldc	#13; //String not defined: 
   10:	invokevirtual	#17; //Method scala/collection/mutable/StringBuilder.append:(Ljava/lang/Object;)Lscala/collection/mutable/StringBuilder;
   13:	aload_1
   14:	invokevirtual	#17; //Method scala/collection/mutable/StringBuilder.append:(Ljava/lang/Object;)Lscala/collection/mutable/StringBuilder;
   17:	invokevirtual	#21; //Method scala/collection/mutable/StringBuilder.toString:()Ljava/lang/String;
   20:	invokespecial	#25; //Method java/lang/Error."<init>":(Ljava/lang/String;)V
   23:	return
  LineNumberTable: 
   line 17: 0

  LocalVariableTable: 
   Start  Length  Slot  Name   Signature
   0      24      0    this       Lscala/NotDefinedError;
   0      24      1    msg       Ljava/lang/String;


}

