Compiled from "Numeric.scala"
public abstract class scala.Numeric$BigDecimalAsIfIntegral$class extends java.lang.Object
  SourceFile: "Numeric.scala"
  Scala: length = 0x
   
  InnerClass: 
   public abstract #42= #39 of #41; //BigDecimalAsIfIntegral=class scala/Numeric$BigDecimalAsIfIntegral of class scala/Numeric
  minor version: 0
  major version: 49
  Constant pool:
const #1 = Asciz	SourceFile;
const #2 = Asciz	Numeric.scala;
const #3 = Asciz	$init$;
const #4 = Asciz	(Lscala/Numeric$BigDecimalAsIfIntegral;)V;
const #5 = Asciz	Code;
const #6 = Asciz	LineNumberTable;
const #7 = Asciz	$this;
const #8 = Asciz	Lscala/Numeric$BigDecimalAsIfIntegral;;
const #9 = Asciz	LocalVariableTable;
const #10 = Asciz	rem;
const #11 = Asciz	(Lscala/Numeric$BigDecimalAsIfIntegral;Lscala/BigDecimal;Lscala/BigDecimal;)Lscala/BigDecimal;;
const #12 = Asciz	scala/BigDecimal;
const #13 = class	#12;	//  scala/BigDecimal
const #14 = Asciz	bigDecimal;
const #15 = Asciz	()Ljava/math/BigDecimal;;
const #16 = NameAndType	#14:#15;//  bigDecimal:()Ljava/math/BigDecimal;
const #17 = Method	#13.#16;	//  scala/BigDecimal.bigDecimal:()Ljava/math/BigDecimal;
const #18 = Asciz	java/math/BigDecimal;
const #19 = class	#18;	//  java/math/BigDecimal
const #20 = Asciz	remainder;
const #21 = Asciz	(Ljava/math/BigDecimal;)Ljava/math/BigDecimal;;
const #22 = NameAndType	#20:#21;//  remainder:(Ljava/math/BigDecimal;)Ljava/math/BigDecimal;
const #23 = Method	#19.#22;	//  java/math/BigDecimal.remainder:(Ljava/math/BigDecimal;)Ljava/math/BigDecimal;
const #24 = Asciz	<init>;
const #25 = Asciz	(Ljava/math/BigDecimal;)V;
const #26 = NameAndType	#24:#25;//  "<init>":(Ljava/math/BigDecimal;)V
const #27 = Method	#13.#26;	//  scala/BigDecimal."<init>":(Ljava/math/BigDecimal;)V
const #28 = Asciz	x;
const #29 = Asciz	Lscala/BigDecimal;;
const #30 = Asciz	y;
const #31 = Asciz	quot;
const #32 = Asciz	$div;
const #33 = Asciz	(Lscala/BigDecimal;)Lscala/BigDecimal;;
const #34 = NameAndType	#32:#33;//  $div:(Lscala/BigDecimal;)Lscala/BigDecimal;
const #35 = Method	#13.#34;	//  scala/BigDecimal.$div:(Lscala/BigDecimal;)Lscala/BigDecimal;
const #36 = Asciz	Scala;
const #37 = Asciz	InnerClasses;
const #38 = Asciz	scala/Numeric$BigDecimalAsIfIntegral;
const #39 = class	#38;	//  scala/Numeric$BigDecimalAsIfIntegral
const #40 = Asciz	scala/Numeric;
const #41 = class	#40;	//  scala/Numeric
const #42 = Asciz	BigDecimalAsIfIntegral;
const #43 = Asciz	scala/Numeric$BigDecimalAsIfIntegral$class;
const #44 = class	#43;	//  scala/Numeric$BigDecimalAsIfIntegral$class
const #45 = Asciz	java/lang/Object;
const #46 = class	#45;	//  java/lang/Object

{
public static void $init$(scala.Numeric$BigDecimalAsIfIntegral);
  Code:
   Stack=0, Locals=1, Args_size=1
   0:	return
  LineNumberTable: 
   line 92: 0

  LocalVariableTable: 
   Start  Length  Slot  Name   Signature
   0      1      0    $this       Lscala/Numeric$BigDecimalAsIfIntegral;


public static scala.BigDecimal rem(scala.Numeric$BigDecimalAsIfIntegral, scala.BigDecimal, scala.BigDecimal);
  Code:
   Stack=4, Locals=3, Args_size=3
   0:	new	#13; //class scala/BigDecimal
   3:	dup
   4:	aload_1
   5:	invokevirtual	#17; //Method scala/BigDecimal.bigDecimal:()Ljava/math/BigDecimal;
   8:	aload_2
   9:	invokevirtual	#17; //Method scala/BigDecimal.bigDecimal:()Ljava/math/BigDecimal;
   12:	invokevirtual	#23; //Method java/math/BigDecimal.remainder:(Ljava/math/BigDecimal;)Ljava/math/BigDecimal;
   15:	invokespecial	#27; //Method scala/BigDecimal."<init>":(Ljava/math/BigDecimal;)V
   18:	areturn
  LineNumberTable: 
   line 96: 0

  LocalVariableTable: 
   Start  Length  Slot  Name   Signature
   0      19      0    $this       Lscala/Numeric$BigDecimalAsIfIntegral;
   0      19      1    x       Lscala/BigDecimal;
   0      19      2    y       Lscala/BigDecimal;


public static scala.BigDecimal quot(scala.Numeric$BigDecimalAsIfIntegral, scala.BigDecimal, scala.BigDecimal);
  Code:
   Stack=2, Locals=3, Args_size=3
   0:	aload_1
   1:	aload_2
   2:	invokevirtual	#35; //Method scala/BigDecimal.$div:(Lscala/BigDecimal;)Lscala/BigDecimal;
   5:	areturn
  LineNumberTable: 
   line 93: 0

  LocalVariableTable: 
   Start  Length  Slot  Name   Signature
   0      6      0    $this       Lscala/Numeric$BigDecimalAsIfIntegral;
   0      6      1    x       Lscala/BigDecimal;
   0      6      2    y       Lscala/BigDecimal;


}

