Compiled from "Numeric.scala"
public final class scala.Numeric$IntIsIntegral$ extends java.lang.Object implements scala.Numeric$IntIsIntegral,scala.Ordering$IntOrdering,scala.ScalaObject
  SourceFile: "Numeric.scala"
  Scala: length = 0x
   
  InnerClass: 
   public #220= #217 of #219; //Ops=class scala/Numeric$Ops of class scala/Numeric
   public #220= #222 of #130; //Ops=class scala/Ordering$Ops of class scala/Ordering
   public abstract #223= #60 of #130; //IntOrdering=class scala/Ordering$IntOrdering of class scala/Ordering
   public #226= #225 of #122; //IntegralOps=class scala/Integral$IntegralOps of class scala/Integral
   public abstract #227= #72 of #219; //IntIsIntegral=class scala/Numeric$IntIsIntegral of class scala/Numeric
  minor version: 0
  major version: 49
  Constant pool:
const #1 = Asciz	SourceFile;
const #2 = Asciz	Numeric.scala;
const #3 = Asciz	Scala;
const #4 = Asciz	MODULE$;
const #5 = Asciz	Lscala/Numeric$IntIsIntegral$;;
const #6 = Asciz	<clinit>;
const #7 = Asciz	()V;
const #8 = Asciz	Code;
const #9 = Asciz	scala/Numeric$IntIsIntegral$;
const #10 = class	#9;	//  scala/Numeric$IntIsIntegral$
const #11 = Asciz	<init>;
const #12 = NameAndType	#11:#7;//  "<init>":()V
const #13 = Method	#10.#12;	//  scala/Numeric$IntIsIntegral$."<init>":()V
const #14 = Asciz	LineNumberTable;
const #15 = Asciz	java/lang/Object;
const #16 = class	#15;	//  java/lang/Object
const #17 = Method	#16.#12;	//  java/lang/Object."<init>":()V
const #18 = NameAndType	#4:#5;//  MODULE$:Lscala/Numeric$IntIsIntegral$;
const #19 = Field	#10.#18;	//  scala/Numeric$IntIsIntegral$.MODULE$:Lscala/Numeric$IntIsIntegral$;
const #20 = Asciz	scala/PartialOrdering$class;
const #21 = class	#20;	//  scala/PartialOrdering$class
const #22 = Asciz	$init$;
const #23 = Asciz	(Lscala/PartialOrdering;)V;
const #24 = NameAndType	#22:#23;//  $init$:(Lscala/PartialOrdering;)V
const #25 = Method	#21.#24;	//  scala/PartialOrdering$class.$init$:(Lscala/PartialOrdering;)V
const #26 = Asciz	scala/Ordering$class;
const #27 = class	#26;	//  scala/Ordering$class
const #28 = Asciz	(Lscala/Ordering;)V;
const #29 = NameAndType	#22:#28;//  $init$:(Lscala/Ordering;)V
const #30 = Method	#27.#29;	//  scala/Ordering$class.$init$:(Lscala/Ordering;)V
const #31 = Asciz	scala/Numeric$class;
const #32 = class	#31;	//  scala/Numeric$class
const #33 = Asciz	(Lscala/Numeric;)V;
const #34 = NameAndType	#22:#33;//  $init$:(Lscala/Numeric;)V
const #35 = Method	#32.#34;	//  scala/Numeric$class.$init$:(Lscala/Numeric;)V
const #36 = Asciz	scala/Integral$class;
const #37 = class	#36;	//  scala/Integral$class
const #38 = Asciz	(Lscala/Integral;)V;
const #39 = NameAndType	#22:#38;//  $init$:(Lscala/Integral;)V
const #40 = Method	#37.#39;	//  scala/Integral$class.$init$:(Lscala/Integral;)V
const #41 = Asciz	scala/Numeric$IntIsIntegral$class;
const #42 = class	#41;	//  scala/Numeric$IntIsIntegral$class
const #43 = Asciz	(Lscala/Numeric$IntIsIntegral;)V;
const #44 = NameAndType	#22:#43;//  $init$:(Lscala/Numeric$IntIsIntegral;)V
const #45 = Method	#42.#44;	//  scala/Numeric$IntIsIntegral$class.$init$:(Lscala/Numeric$IntIsIntegral;)V
const #46 = Asciz	scala/Ordering$IntOrdering$class;
const #47 = class	#46;	//  scala/Ordering$IntOrdering$class
const #48 = Asciz	(Lscala/Ordering$IntOrdering;)V;
const #49 = NameAndType	#22:#48;//  $init$:(Lscala/Ordering$IntOrdering;)V
const #50 = Method	#47.#49;	//  scala/Ordering$IntOrdering$class.$init$:(Lscala/Ordering$IntOrdering;)V
const #51 = Asciz	compare;
const #52 = Asciz	(Ljava/lang/Object;Ljava/lang/Object;)I;
const #53 = Asciz	scala/runtime/BoxesRunTime;
const #54 = class	#53;	//  scala/runtime/BoxesRunTime
const #55 = Asciz	unboxToInt;
const #56 = Asciz	(Ljava/lang/Object;)I;
const #57 = NameAndType	#55:#56;//  unboxToInt:(Ljava/lang/Object;)I
const #58 = Method	#54.#57;	//  scala/runtime/BoxesRunTime.unboxToInt:(Ljava/lang/Object;)I
const #59 = Asciz	scala/Ordering$IntOrdering;
const #60 = class	#59;	//  scala/Ordering$IntOrdering
const #61 = Asciz	(II)I;
const #62 = NameAndType	#51:#61;//  compare:(II)I
const #63 = InterfaceMethod	#60.#62;	//  scala/Ordering$IntOrdering.compare:(II)I
const #64 = Asciz	this;
const #65 = Asciz	x;
const #66 = Asciz	Ljava/lang/Object;;
const #67 = Asciz	y;
const #68 = Asciz	LocalVariableTable;
const #69 = Asciz	plus;
const #70 = Asciz	(Ljava/lang/Object;Ljava/lang/Object;)Ljava/lang/Object;;
const #71 = Asciz	scala/Numeric$IntIsIntegral;
const #72 = class	#71;	//  scala/Numeric$IntIsIntegral
const #73 = NameAndType	#69:#61;//  plus:(II)I
const #74 = InterfaceMethod	#72.#73;	//  scala/Numeric$IntIsIntegral.plus:(II)I
const #75 = Asciz	boxToInteger;
const #76 = Asciz	(I)Ljava/lang/Integer;;
const #77 = NameAndType	#75:#76;//  boxToInteger:(I)Ljava/lang/Integer;
const #78 = Method	#54.#77;	//  scala/runtime/BoxesRunTime.boxToInteger:(I)Ljava/lang/Integer;
const #79 = Asciz	minus;
const #80 = NameAndType	#79:#61;//  minus:(II)I
const #81 = InterfaceMethod	#72.#80;	//  scala/Numeric$IntIsIntegral.minus:(II)I
const #82 = Asciz	times;
const #83 = NameAndType	#82:#61;//  times:(II)I
const #84 = InterfaceMethod	#72.#83;	//  scala/Numeric$IntIsIntegral.times:(II)I
const #85 = Asciz	quot;
const #86 = NameAndType	#85:#61;//  quot:(II)I
const #87 = InterfaceMethod	#72.#86;	//  scala/Numeric$IntIsIntegral.quot:(II)I
const #88 = Asciz	rem;
const #89 = NameAndType	#88:#61;//  rem:(II)I
const #90 = InterfaceMethod	#72.#89;	//  scala/Numeric$IntIsIntegral.rem:(II)I
const #91 = Asciz	negate;
const #92 = Asciz	(Ljava/lang/Object;)Ljava/lang/Object;;
const #93 = Asciz	(I)I;
const #94 = NameAndType	#91:#93;//  negate:(I)I
const #95 = InterfaceMethod	#72.#94;	//  scala/Numeric$IntIsIntegral.negate:(I)I
const #96 = Asciz	fromInt;
const #97 = Asciz	(I)Ljava/lang/Object;;
const #98 = NameAndType	#96:#93;//  fromInt:(I)I
const #99 = InterfaceMethod	#72.#98;	//  scala/Numeric$IntIsIntegral.fromInt:(I)I
const #100 = Asciz	I;
const #101 = Asciz	toInt;
const #102 = NameAndType	#101:#93;//  toInt:(I)I
const #103 = InterfaceMethod	#72.#102;	//  scala/Numeric$IntIsIntegral.toInt:(I)I
const #104 = Asciz	toLong;
const #105 = Asciz	(Ljava/lang/Object;)J;
const #106 = Asciz	(I)J;
const #107 = NameAndType	#104:#106;//  toLong:(I)J
const #108 = InterfaceMethod	#72.#107;	//  scala/Numeric$IntIsIntegral.toLong:(I)J
const #109 = Asciz	toFloat;
const #110 = Asciz	(Ljava/lang/Object;)F;
const #111 = Asciz	(I)F;
const #112 = NameAndType	#109:#111;//  toFloat:(I)F
const #113 = InterfaceMethod	#72.#112;	//  scala/Numeric$IntIsIntegral.toFloat:(I)F
const #114 = Asciz	toDouble;
const #115 = Asciz	(Ljava/lang/Object;)D;
const #116 = Asciz	(I)D;
const #117 = NameAndType	#114:#116;//  toDouble:(I)D
const #118 = InterfaceMethod	#72.#117;	//  scala/Numeric$IntIsIntegral.toDouble:(I)D
const #119 = Asciz	mkNumericOps;
const #120 = Asciz	(Ljava/lang/Object;)Lscala/Numeric$Ops;;
const #121 = Asciz	scala/Integral;
const #122 = class	#121;	//  scala/Integral
const #123 = Asciz	(Ljava/lang/Object;)Lscala/Integral$IntegralOps;;
const #124 = NameAndType	#119:#123;//  mkNumericOps:(Ljava/lang/Object;)Lscala/Integral$IntegralOps;
const #125 = InterfaceMethod	#122.#124;	//  scala/Integral.mkNumericOps:(Ljava/lang/Object;)Lscala/Integral$IntegralOps;
const #126 = Asciz	lhs;
const #127 = Asciz	reverse;
const #128 = Asciz	()Lscala/PartialOrdering;;
const #129 = Asciz	scala/Ordering;
const #130 = class	#129;	//  scala/Ordering
const #131 = Asciz	()Lscala/Ordering;;
const #132 = NameAndType	#127:#131;//  reverse:()Lscala/Ordering;
const #133 = InterfaceMethod	#130.#132;	//  scala/Ordering.reverse:()Lscala/Ordering;
const #134 = Asciz	mkOrderingOps;
const #135 = Asciz	(Ljava/lang/Object;)Lscala/Ordering$Ops;;
const #136 = Asciz	(Lscala/Ordering;Ljava/lang/Object;)Lscala/Ordering$Ops;;
const #137 = NameAndType	#134:#136;//  mkOrderingOps:(Lscala/Ordering;Ljava/lang/Object;)Lscala/Ordering$Ops;
const #138 = Method	#27.#137;	//  scala/Ordering$class.mkOrderingOps:(Lscala/Ordering;Ljava/lang/Object;)Lscala/Ordering$Ops;
const #139 = Asciz	(Lscala/Ordering;)Lscala/Ordering;;
const #140 = NameAndType	#127:#139;//  reverse:(Lscala/Ordering;)Lscala/Ordering;
const #141 = Method	#27.#140;	//  scala/Ordering$class.reverse:(Lscala/Ordering;)Lscala/Ordering;
const #142 = Asciz	min;
const #143 = Asciz	(Lscala/Ordering;Ljava/lang/Object;Ljava/lang/Object;)Ljava/lang/Object;;
const #144 = NameAndType	#142:#143;//  min:(Lscala/Ordering;Ljava/lang/Object;Ljava/lang/Object;)Ljava/lang/Object;
const #145 = Method	#27.#144;	//  scala/Ordering$class.min:(Lscala/Ordering;Ljava/lang/Object;Ljava/lang/Object;)Ljava/lang/Object;
const #146 = Asciz	max;
const #147 = NameAndType	#146:#143;//  max:(Lscala/Ordering;Ljava/lang/Object;Ljava/lang/Object;)Ljava/lang/Object;
const #148 = Method	#27.#147;	//  scala/Ordering$class.max:(Lscala/Ordering;Ljava/lang/Object;Ljava/lang/Object;)Ljava/lang/Object;
const #149 = Asciz	equiv;
const #150 = Asciz	(Ljava/lang/Object;Ljava/lang/Object;)Z;
const #151 = Asciz	(Lscala/Ordering;Ljava/lang/Object;Ljava/lang/Object;)Z;
const #152 = NameAndType	#149:#151;//  equiv:(Lscala/Ordering;Ljava/lang/Object;Ljava/lang/Object;)Z
const #153 = Method	#27.#152;	//  scala/Ordering$class.equiv:(Lscala/Ordering;Ljava/lang/Object;Ljava/lang/Object;)Z
const #154 = Asciz	gt;
const #155 = NameAndType	#154:#151;//  gt:(Lscala/Ordering;Ljava/lang/Object;Ljava/lang/Object;)Z
const #156 = Method	#27.#155;	//  scala/Ordering$class.gt:(Lscala/Ordering;Ljava/lang/Object;Ljava/lang/Object;)Z
const #157 = Asciz	lt;
const #158 = NameAndType	#157:#151;//  lt:(Lscala/Ordering;Ljava/lang/Object;Ljava/lang/Object;)Z
const #159 = Method	#27.#158;	//  scala/Ordering$class.lt:(Lscala/Ordering;Ljava/lang/Object;Ljava/lang/Object;)Z
const #160 = Asciz	gteq;
const #161 = NameAndType	#160:#151;//  gteq:(Lscala/Ordering;Ljava/lang/Object;Ljava/lang/Object;)Z
const #162 = Method	#27.#161;	//  scala/Ordering$class.gteq:(Lscala/Ordering;Ljava/lang/Object;Ljava/lang/Object;)Z
const #163 = Asciz	lteq;
const #164 = NameAndType	#163:#151;//  lteq:(Lscala/Ordering;Ljava/lang/Object;Ljava/lang/Object;)Z
const #165 = Method	#27.#164;	//  scala/Ordering$class.lteq:(Lscala/Ordering;Ljava/lang/Object;Ljava/lang/Object;)Z
const #166 = Asciz	signum;
const #167 = Asciz	(Lscala/Numeric;Ljava/lang/Object;)I;
const #168 = NameAndType	#166:#167;//  signum:(Lscala/Numeric;Ljava/lang/Object;)I
const #169 = Method	#32.#168;	//  scala/Numeric$class.signum:(Lscala/Numeric;Ljava/lang/Object;)I
const #170 = Asciz	abs;
const #171 = Asciz	(Lscala/Numeric;Ljava/lang/Object;)Ljava/lang/Object;;
const #172 = NameAndType	#170:#171;//  abs:(Lscala/Numeric;Ljava/lang/Object;)Ljava/lang/Object;
const #173 = Method	#32.#172;	//  scala/Numeric$class.abs:(Lscala/Numeric;Ljava/lang/Object;)Ljava/lang/Object;
const #174 = Asciz	one;
const #175 = Asciz	()Ljava/lang/Object;;
const #176 = Asciz	(Lscala/Numeric;)Ljava/lang/Object;;
const #177 = NameAndType	#174:#176;//  one:(Lscala/Numeric;)Ljava/lang/Object;
const #178 = Method	#32.#177;	//  scala/Numeric$class.one:(Lscala/Numeric;)Ljava/lang/Object;
const #179 = Asciz	zero;
const #180 = NameAndType	#179:#176;//  zero:(Lscala/Numeric;)Ljava/lang/Object;
const #181 = Method	#32.#180;	//  scala/Numeric$class.zero:(Lscala/Numeric;)Ljava/lang/Object;
const #182 = Asciz	(Lscala/Integral;Ljava/lang/Object;)Lscala/Integral$IntegralOps;;
const #183 = NameAndType	#119:#182;//  mkNumericOps:(Lscala/Integral;Ljava/lang/Object;)Lscala/Integral$IntegralOps;
const #184 = Method	#37.#183;	//  scala/Integral$class.mkNumericOps:(Lscala/Integral;Ljava/lang/Object;)Lscala/Integral$IntegralOps;
const #185 = Asciz	(Lscala/Numeric$IntIsIntegral;I)D;
const #186 = NameAndType	#114:#185;//  toDouble:(Lscala/Numeric$IntIsIntegral;I)D
const #187 = Method	#42.#186;	//  scala/Numeric$IntIsIntegral$class.toDouble:(Lscala/Numeric$IntIsIntegral;I)D
const #188 = Asciz	(Lscala/Numeric$IntIsIntegral;I)F;
const #189 = NameAndType	#109:#188;//  toFloat:(Lscala/Numeric$IntIsIntegral;I)F
const #190 = Method	#42.#189;	//  scala/Numeric$IntIsIntegral$class.toFloat:(Lscala/Numeric$IntIsIntegral;I)F
const #191 = Asciz	(Lscala/Numeric$IntIsIntegral;I)J;
const #192 = NameAndType	#104:#191;//  toLong:(Lscala/Numeric$IntIsIntegral;I)J
const #193 = Method	#42.#192;	//  scala/Numeric$IntIsIntegral$class.toLong:(Lscala/Numeric$IntIsIntegral;I)J
const #194 = Asciz	(Lscala/Numeric$IntIsIntegral;I)I;
const #195 = NameAndType	#101:#194;//  toInt:(Lscala/Numeric$IntIsIntegral;I)I
const #196 = Method	#42.#195;	//  scala/Numeric$IntIsIntegral$class.toInt:(Lscala/Numeric$IntIsIntegral;I)I
const #197 = NameAndType	#96:#194;//  fromInt:(Lscala/Numeric$IntIsIntegral;I)I
const #198 = Method	#42.#197;	//  scala/Numeric$IntIsIntegral$class.fromInt:(Lscala/Numeric$IntIsIntegral;I)I
const #199 = NameAndType	#91:#194;//  negate:(Lscala/Numeric$IntIsIntegral;I)I
const #200 = Method	#42.#199;	//  scala/Numeric$IntIsIntegral$class.negate:(Lscala/Numeric$IntIsIntegral;I)I
const #201 = Asciz	(Lscala/Numeric$IntIsIntegral;II)I;
const #202 = NameAndType	#88:#201;//  rem:(Lscala/Numeric$IntIsIntegral;II)I
const #203 = Method	#42.#202;	//  scala/Numeric$IntIsIntegral$class.rem:(Lscala/Numeric$IntIsIntegral;II)I
const #204 = NameAndType	#85:#201;//  quot:(Lscala/Numeric$IntIsIntegral;II)I
const #205 = Method	#42.#204;	//  scala/Numeric$IntIsIntegral$class.quot:(Lscala/Numeric$IntIsIntegral;II)I
const #206 = NameAndType	#82:#201;//  times:(Lscala/Numeric$IntIsIntegral;II)I
const #207 = Method	#42.#206;	//  scala/Numeric$IntIsIntegral$class.times:(Lscala/Numeric$IntIsIntegral;II)I
const #208 = NameAndType	#79:#201;//  minus:(Lscala/Numeric$IntIsIntegral;II)I
const #209 = Method	#42.#208;	//  scala/Numeric$IntIsIntegral$class.minus:(Lscala/Numeric$IntIsIntegral;II)I
const #210 = NameAndType	#69:#201;//  plus:(Lscala/Numeric$IntIsIntegral;II)I
const #211 = Method	#42.#210;	//  scala/Numeric$IntIsIntegral$class.plus:(Lscala/Numeric$IntIsIntegral;II)I
const #212 = Asciz	(Lscala/Ordering$IntOrdering;II)I;
const #213 = NameAndType	#51:#212;//  compare:(Lscala/Ordering$IntOrdering;II)I
const #214 = Method	#47.#213;	//  scala/Ordering$IntOrdering$class.compare:(Lscala/Ordering$IntOrdering;II)I
const #215 = Asciz	InnerClasses;
const #216 = Asciz	scala/Numeric$Ops;
const #217 = class	#216;	//  scala/Numeric$Ops
const #218 = Asciz	scala/Numeric;
const #219 = class	#218;	//  scala/Numeric
const #220 = Asciz	Ops;
const #221 = Asciz	scala/Ordering$Ops;
const #222 = class	#221;	//  scala/Ordering$Ops
const #223 = Asciz	IntOrdering;
const #224 = Asciz	scala/Integral$IntegralOps;
const #225 = class	#224;	//  scala/Integral$IntegralOps
const #226 = Asciz	IntegralOps;
const #227 = Asciz	IntIsIntegral;
const #228 = Asciz	scala/ScalaObject;
const #229 = class	#228;	//  scala/ScalaObject

{
public static final scala.Numeric$IntIsIntegral$ MODULE$;

public static {};
  Code:
   Stack=1, Locals=0, Args_size=0
   0:	new	#10; //class scala/Numeric$IntIsIntegral$
   3:	invokespecial	#13; //Method "<init>":()V
   6:	return

public scala.Numeric$IntIsIntegral$();
  Code:
   Stack=1, Locals=1, Args_size=1
   0:	aload_0
   1:	invokespecial	#17; //Method java/lang/Object."<init>":()V
   4:	aload_0
   5:	putstatic	#19; //Field MODULE$:Lscala/Numeric$IntIsIntegral$;
   8:	aload_0
   9:	invokestatic	#25; //Method scala/PartialOrdering$class.$init$:(Lscala/PartialOrdering;)V
   12:	aload_0
   13:	invokestatic	#30; //Method scala/Ordering$class.$init$:(Lscala/Ordering;)V
   16:	aload_0
   17:	invokestatic	#35; //Method scala/Numeric$class.$init$:(Lscala/Numeric;)V
   20:	aload_0
   21:	invokestatic	#40; //Method scala/Integral$class.$init$:(Lscala/Integral;)V
   24:	aload_0
   25:	invokestatic	#45; //Method scala/Numeric$IntIsIntegral$class.$init$:(Lscala/Numeric$IntIsIntegral;)V
   28:	aload_0
   29:	invokestatic	#50; //Method scala/Ordering$IntOrdering$class.$init$:(Lscala/Ordering$IntOrdering;)V
   32:	return
  LineNumberTable: 
   line 32: 0


public int compare(java.lang.Object, java.lang.Object);
  Code:
   Stack=3, Locals=3, Args_size=3
   0:	aload_0
   1:	aload_1
   2:	invokestatic	#58; //Method scala/runtime/BoxesRunTime.unboxToInt:(Ljava/lang/Object;)I
   5:	aload_2
   6:	invokestatic	#58; //Method scala/runtime/BoxesRunTime.unboxToInt:(Ljava/lang/Object;)I
   9:	invokeinterface	#63,  3; //InterfaceMethod scala/Ordering$IntOrdering.compare:(II)I
   14:	ireturn
  LineNumberTable: 
   line 32: 0

  LocalVariableTable: 
   Start  Length  Slot  Name   Signature
   0      15      0    this       Lscala/Numeric$IntIsIntegral$;
   0      15      1    x       Ljava/lang/Object;
   0      15      2    y       Ljava/lang/Object;


public java.lang.Object plus(java.lang.Object, java.lang.Object);
  Code:
   Stack=3, Locals=3, Args_size=3
   0:	aload_0
   1:	aload_1
   2:	invokestatic	#58; //Method scala/runtime/BoxesRunTime.unboxToInt:(Ljava/lang/Object;)I
   5:	aload_2
   6:	invokestatic	#58; //Method scala/runtime/BoxesRunTime.unboxToInt:(Ljava/lang/Object;)I
   9:	invokeinterface	#74,  3; //InterfaceMethod scala/Numeric$IntIsIntegral.plus:(II)I
   14:	invokestatic	#78; //Method scala/runtime/BoxesRunTime.boxToInteger:(I)Ljava/lang/Integer;
   17:	areturn
  LineNumberTable: 
   line 32: 0

  LocalVariableTable: 
   Start  Length  Slot  Name   Signature
   0      18      0    this       Lscala/Numeric$IntIsIntegral$;
   0      18      1    x       Ljava/lang/Object;
   0      18      2    y       Ljava/lang/Object;


public java.lang.Object minus(java.lang.Object, java.lang.Object);
  Code:
   Stack=3, Locals=3, Args_size=3
   0:	aload_0
   1:	aload_1
   2:	invokestatic	#58; //Method scala/runtime/BoxesRunTime.unboxToInt:(Ljava/lang/Object;)I
   5:	aload_2
   6:	invokestatic	#58; //Method scala/runtime/BoxesRunTime.unboxToInt:(Ljava/lang/Object;)I
   9:	invokeinterface	#81,  3; //InterfaceMethod scala/Numeric$IntIsIntegral.minus:(II)I
   14:	invokestatic	#78; //Method scala/runtime/BoxesRunTime.boxToInteger:(I)Ljava/lang/Integer;
   17:	areturn
  LineNumberTable: 
   line 32: 0

  LocalVariableTable: 
   Start  Length  Slot  Name   Signature
   0      18      0    this       Lscala/Numeric$IntIsIntegral$;
   0      18      1    x       Ljava/lang/Object;
   0      18      2    y       Ljava/lang/Object;


public java.lang.Object times(java.lang.Object, java.lang.Object);
  Code:
   Stack=3, Locals=3, Args_size=3
   0:	aload_0
   1:	aload_1
   2:	invokestatic	#58; //Method scala/runtime/BoxesRunTime.unboxToInt:(Ljava/lang/Object;)I
   5:	aload_2
   6:	invokestatic	#58; //Method scala/runtime/BoxesRunTime.unboxToInt:(Ljava/lang/Object;)I
   9:	invokeinterface	#84,  3; //InterfaceMethod scala/Numeric$IntIsIntegral.times:(II)I
   14:	invokestatic	#78; //Method scala/runtime/BoxesRunTime.boxToInteger:(I)Ljava/lang/Integer;
   17:	areturn
  LineNumberTable: 
   line 32: 0

  LocalVariableTable: 
   Start  Length  Slot  Name   Signature
   0      18      0    this       Lscala/Numeric$IntIsIntegral$;
   0      18      1    x       Ljava/lang/Object;
   0      18      2    y       Ljava/lang/Object;


public java.lang.Object quot(java.lang.Object, java.lang.Object);
  Code:
   Stack=3, Locals=3, Args_size=3
   0:	aload_0
   1:	aload_1
   2:	invokestatic	#58; //Method scala/runtime/BoxesRunTime.unboxToInt:(Ljava/lang/Object;)I
   5:	aload_2
   6:	invokestatic	#58; //Method scala/runtime/BoxesRunTime.unboxToInt:(Ljava/lang/Object;)I
   9:	invokeinterface	#87,  3; //InterfaceMethod scala/Numeric$IntIsIntegral.quot:(II)I
   14:	invokestatic	#78; //Method scala/runtime/BoxesRunTime.boxToInteger:(I)Ljava/lang/Integer;
   17:	areturn
  LineNumberTable: 
   line 32: 0

  LocalVariableTable: 
   Start  Length  Slot  Name   Signature
   0      18      0    this       Lscala/Numeric$IntIsIntegral$;
   0      18      1    x       Ljava/lang/Object;
   0      18      2    y       Ljava/lang/Object;


public java.lang.Object rem(java.lang.Object, java.lang.Object);
  Code:
   Stack=3, Locals=3, Args_size=3
   0:	aload_0
   1:	aload_1
   2:	invokestatic	#58; //Method scala/runtime/BoxesRunTime.unboxToInt:(Ljava/lang/Object;)I
   5:	aload_2
   6:	invokestatic	#58; //Method scala/runtime/BoxesRunTime.unboxToInt:(Ljava/lang/Object;)I
   9:	invokeinterface	#90,  3; //InterfaceMethod scala/Numeric$IntIsIntegral.rem:(II)I
   14:	invokestatic	#78; //Method scala/runtime/BoxesRunTime.boxToInteger:(I)Ljava/lang/Integer;
   17:	areturn
  LineNumberTable: 
   line 32: 0

  LocalVariableTable: 
   Start  Length  Slot  Name   Signature
   0      18      0    this       Lscala/Numeric$IntIsIntegral$;
   0      18      1    x       Ljava/lang/Object;
   0      18      2    y       Ljava/lang/Object;


public java.lang.Object negate(java.lang.Object);
  Code:
   Stack=2, Locals=2, Args_size=2
   0:	aload_0
   1:	aload_1
   2:	invokestatic	#58; //Method scala/runtime/BoxesRunTime.unboxToInt:(Ljava/lang/Object;)I
   5:	invokeinterface	#95,  2; //InterfaceMethod scala/Numeric$IntIsIntegral.negate:(I)I
   10:	invokestatic	#78; //Method scala/runtime/BoxesRunTime.boxToInteger:(I)Ljava/lang/Integer;
   13:	areturn
  LineNumberTable: 
   line 32: 0

  LocalVariableTable: 
   Start  Length  Slot  Name   Signature
   0      14      0    this       Lscala/Numeric$IntIsIntegral$;
   0      14      1    x       Ljava/lang/Object;


public java.lang.Object fromInt(int);
  Code:
   Stack=2, Locals=2, Args_size=2
   0:	aload_0
   1:	iload_1
   2:	invokeinterface	#99,  2; //InterfaceMethod scala/Numeric$IntIsIntegral.fromInt:(I)I
   7:	invokestatic	#78; //Method scala/runtime/BoxesRunTime.boxToInteger:(I)Ljava/lang/Integer;
   10:	areturn
  LineNumberTable: 
   line 32: 0

  LocalVariableTable: 
   Start  Length  Slot  Name   Signature
   0      11      0    this       Lscala/Numeric$IntIsIntegral$;
   0      11      1    x       I


public int toInt(java.lang.Object);
  Code:
   Stack=2, Locals=2, Args_size=2
   0:	aload_0
   1:	aload_1
   2:	invokestatic	#58; //Method scala/runtime/BoxesRunTime.unboxToInt:(Ljava/lang/Object;)I
   5:	invokeinterface	#103,  2; //InterfaceMethod scala/Numeric$IntIsIntegral.toInt:(I)I
   10:	ireturn
  LineNumberTable: 
   line 32: 0

  LocalVariableTable: 
   Start  Length  Slot  Name   Signature
   0      11      0    this       Lscala/Numeric$IntIsIntegral$;
   0      11      1    x       Ljava/lang/Object;


public long toLong(java.lang.Object);
  Code:
   Stack=2, Locals=2, Args_size=2
   0:	aload_0
   1:	aload_1
   2:	invokestatic	#58; //Method scala/runtime/BoxesRunTime.unboxToInt:(Ljava/lang/Object;)I
   5:	invokeinterface	#108,  2; //InterfaceMethod scala/Numeric$IntIsIntegral.toLong:(I)J
   10:	lreturn
  LineNumberTable: 
   line 32: 0

  LocalVariableTable: 
   Start  Length  Slot  Name   Signature
   0      11      0    this       Lscala/Numeric$IntIsIntegral$;
   0      11      1    x       Ljava/lang/Object;


public float toFloat(java.lang.Object);
  Code:
   Stack=2, Locals=2, Args_size=2
   0:	aload_0
   1:	aload_1
   2:	invokestatic	#58; //Method scala/runtime/BoxesRunTime.unboxToInt:(Ljava/lang/Object;)I
   5:	invokeinterface	#113,  2; //InterfaceMethod scala/Numeric$IntIsIntegral.toFloat:(I)F
   10:	freturn
  LineNumberTable: 
   line 32: 0

  LocalVariableTable: 
   Start  Length  Slot  Name   Signature
   0      11      0    this       Lscala/Numeric$IntIsIntegral$;
   0      11      1    x       Ljava/lang/Object;


public double toDouble(java.lang.Object);
  Code:
   Stack=2, Locals=2, Args_size=2
   0:	aload_0
   1:	aload_1
   2:	invokestatic	#58; //Method scala/runtime/BoxesRunTime.unboxToInt:(Ljava/lang/Object;)I
   5:	invokeinterface	#118,  2; //InterfaceMethod scala/Numeric$IntIsIntegral.toDouble:(I)D
   10:	dreturn
  LineNumberTable: 
   line 32: 0

  LocalVariableTable: 
   Start  Length  Slot  Name   Signature
   0      11      0    this       Lscala/Numeric$IntIsIntegral$;
   0      11      1    x       Ljava/lang/Object;


public scala.Numeric$Ops mkNumericOps(java.lang.Object);
  Code:
   Stack=2, Locals=2, Args_size=2
   0:	aload_0
   1:	aload_1
   2:	invokeinterface	#125,  2; //InterfaceMethod scala/Integral.mkNumericOps:(Ljava/lang/Object;)Lscala/Integral$IntegralOps;
   7:	areturn
  LineNumberTable: 
   line 32: 0

  LocalVariableTable: 
   Start  Length  Slot  Name   Signature
   0      8      0    this       Lscala/Numeric$IntIsIntegral$;
   0      8      1    lhs       Ljava/lang/Object;


public scala.PartialOrdering reverse();
  Code:
   Stack=1, Locals=1, Args_size=1
   0:	aload_0
   1:	invokeinterface	#133,  1; //InterfaceMethod scala/Ordering.reverse:()Lscala/Ordering;
   6:	areturn
  LineNumberTable: 
   line 32: 0


public scala.Ordering$Ops mkOrderingOps(java.lang.Object);
  Code:
   Stack=2, Locals=2, Args_size=2
   0:	aload_0
   1:	aload_1
   2:	invokestatic	#138; //Method scala/Ordering$class.mkOrderingOps:(Lscala/Ordering;Ljava/lang/Object;)Lscala/Ordering$Ops;
   5:	areturn
  LineNumberTable: 
   line 32: 0

  LocalVariableTable: 
   Start  Length  Slot  Name   Signature
   0      6      0    this       Lscala/Numeric$IntIsIntegral$;
   0      6      1    lhs       Ljava/lang/Object;


public scala.Ordering reverse();
  Code:
   Stack=1, Locals=1, Args_size=1
   0:	aload_0
   1:	invokestatic	#141; //Method scala/Ordering$class.reverse:(Lscala/Ordering;)Lscala/Ordering;
   4:	areturn
  LineNumberTable: 
   line 32: 0


public java.lang.Object min(java.lang.Object, java.lang.Object);
  Code:
   Stack=3, Locals=3, Args_size=3
   0:	aload_0
   1:	aload_1
   2:	aload_2
   3:	invokestatic	#145; //Method scala/Ordering$class.min:(Lscala/Ordering;Ljava/lang/Object;Ljava/lang/Object;)Ljava/lang/Object;
   6:	areturn
  LineNumberTable: 
   line 32: 0

  LocalVariableTable: 
   Start  Length  Slot  Name   Signature
   0      7      0    this       Lscala/Numeric$IntIsIntegral$;
   0      7      1    x       Ljava/lang/Object;
   0      7      2    y       Ljava/lang/Object;


public java.lang.Object max(java.lang.Object, java.lang.Object);
  Code:
   Stack=3, Locals=3, Args_size=3
   0:	aload_0
   1:	aload_1
   2:	aload_2
   3:	invokestatic	#148; //Method scala/Ordering$class.max:(Lscala/Ordering;Ljava/lang/Object;Ljava/lang/Object;)Ljava/lang/Object;
   6:	areturn
  LineNumberTable: 
   line 32: 0

  LocalVariableTable: 
   Start  Length  Slot  Name   Signature
   0      7      0    this       Lscala/Numeric$IntIsIntegral$;
   0      7      1    x       Ljava/lang/Object;
   0      7      2    y       Ljava/lang/Object;


public boolean equiv(java.lang.Object, java.lang.Object);
  Code:
   Stack=3, Locals=3, Args_size=3
   0:	aload_0
   1:	aload_1
   2:	aload_2
   3:	invokestatic	#153; //Method scala/Ordering$class.equiv:(Lscala/Ordering;Ljava/lang/Object;Ljava/lang/Object;)Z
   6:	ireturn
  LineNumberTable: 
   line 32: 0

  LocalVariableTable: 
   Start  Length  Slot  Name   Signature
   0      7      0    this       Lscala/Numeric$IntIsIntegral$;
   0      7      1    x       Ljava/lang/Object;
   0      7      2    y       Ljava/lang/Object;


public boolean gt(java.lang.Object, java.lang.Object);
  Code:
   Stack=3, Locals=3, Args_size=3
   0:	aload_0
   1:	aload_1
   2:	aload_2
   3:	invokestatic	#156; //Method scala/Ordering$class.gt:(Lscala/Ordering;Ljava/lang/Object;Ljava/lang/Object;)Z
   6:	ireturn
  LineNumberTable: 
   line 32: 0

  LocalVariableTable: 
   Start  Length  Slot  Name   Signature
   0      7      0    this       Lscala/Numeric$IntIsIntegral$;
   0      7      1    x       Ljava/lang/Object;
   0      7      2    y       Ljava/lang/Object;


public boolean lt(java.lang.Object, java.lang.Object);
  Code:
   Stack=3, Locals=3, Args_size=3
   0:	aload_0
   1:	aload_1
   2:	aload_2
   3:	invokestatic	#159; //Method scala/Ordering$class.lt:(Lscala/Ordering;Ljava/lang/Object;Ljava/lang/Object;)Z
   6:	ireturn
  LineNumberTable: 
   line 32: 0

  LocalVariableTable: 
   Start  Length  Slot  Name   Signature
   0      7      0    this       Lscala/Numeric$IntIsIntegral$;
   0      7      1    x       Ljava/lang/Object;
   0      7      2    y       Ljava/lang/Object;


public boolean gteq(java.lang.Object, java.lang.Object);
  Code:
   Stack=3, Locals=3, Args_size=3
   0:	aload_0
   1:	aload_1
   2:	aload_2
   3:	invokestatic	#162; //Method scala/Ordering$class.gteq:(Lscala/Ordering;Ljava/lang/Object;Ljava/lang/Object;)Z
   6:	ireturn
  LineNumberTable: 
   line 32: 0

  LocalVariableTable: 
   Start  Length  Slot  Name   Signature
   0      7      0    this       Lscala/Numeric$IntIsIntegral$;
   0      7      1    x       Ljava/lang/Object;
   0      7      2    y       Ljava/lang/Object;


public boolean lteq(java.lang.Object, java.lang.Object);
  Code:
   Stack=3, Locals=3, Args_size=3
   0:	aload_0
   1:	aload_1
   2:	aload_2
   3:	invokestatic	#165; //Method scala/Ordering$class.lteq:(Lscala/Ordering;Ljava/lang/Object;Ljava/lang/Object;)Z
   6:	ireturn
  LineNumberTable: 
   line 32: 0

  LocalVariableTable: 
   Start  Length  Slot  Name   Signature
   0      7      0    this       Lscala/Numeric$IntIsIntegral$;
   0      7      1    x       Ljava/lang/Object;
   0      7      2    y       Ljava/lang/Object;


public int signum(java.lang.Object);
  Code:
   Stack=2, Locals=2, Args_size=2
   0:	aload_0
   1:	aload_1
   2:	invokestatic	#169; //Method scala/Numeric$class.signum:(Lscala/Numeric;Ljava/lang/Object;)I
   5:	ireturn
  LineNumberTable: 
   line 32: 0

  LocalVariableTable: 
   Start  Length  Slot  Name   Signature
   0      6      0    this       Lscala/Numeric$IntIsIntegral$;
   0      6      1    x       Ljava/lang/Object;


public java.lang.Object abs(java.lang.Object);
  Code:
   Stack=2, Locals=2, Args_size=2
   0:	aload_0
   1:	aload_1
   2:	invokestatic	#173; //Method scala/Numeric$class.abs:(Lscala/Numeric;Ljava/lang/Object;)Ljava/lang/Object;
   5:	areturn
  LineNumberTable: 
   line 32: 0

  LocalVariableTable: 
   Start  Length  Slot  Name   Signature
   0      6      0    this       Lscala/Numeric$IntIsIntegral$;
   0      6      1    x       Ljava/lang/Object;


public java.lang.Object one();
  Code:
   Stack=1, Locals=1, Args_size=1
   0:	aload_0
   1:	invokestatic	#178; //Method scala/Numeric$class.one:(Lscala/Numeric;)Ljava/lang/Object;
   4:	areturn
  LineNumberTable: 
   line 32: 0


public java.lang.Object zero();
  Code:
   Stack=1, Locals=1, Args_size=1
   0:	aload_0
   1:	invokestatic	#181; //Method scala/Numeric$class.zero:(Lscala/Numeric;)Ljava/lang/Object;
   4:	areturn
  LineNumberTable: 
   line 32: 0


public scala.Integral$IntegralOps mkNumericOps(java.lang.Object);
  Code:
   Stack=2, Locals=2, Args_size=2
   0:	aload_0
   1:	aload_1
   2:	invokestatic	#184; //Method scala/Integral$class.mkNumericOps:(Lscala/Integral;Ljava/lang/Object;)Lscala/Integral$IntegralOps;
   5:	areturn
  LineNumberTable: 
   line 32: 0

  LocalVariableTable: 
   Start  Length  Slot  Name   Signature
   0      6      0    this       Lscala/Numeric$IntIsIntegral$;
   0      6      1    lhs       Ljava/lang/Object;


public double toDouble(int);
  Code:
   Stack=2, Locals=2, Args_size=2
   0:	aload_0
   1:	iload_1
   2:	invokestatic	#187; //Method scala/Numeric$IntIsIntegral$class.toDouble:(Lscala/Numeric$IntIsIntegral;I)D
   5:	dreturn
  LineNumberTable: 
   line 32: 0

  LocalVariableTable: 
   Start  Length  Slot  Name   Signature
   0      6      0    this       Lscala/Numeric$IntIsIntegral$;
   0      6      1    x       I


public float toFloat(int);
  Code:
   Stack=2, Locals=2, Args_size=2
   0:	aload_0
   1:	iload_1
   2:	invokestatic	#190; //Method scala/Numeric$IntIsIntegral$class.toFloat:(Lscala/Numeric$IntIsIntegral;I)F
   5:	freturn
  LineNumberTable: 
   line 32: 0

  LocalVariableTable: 
   Start  Length  Slot  Name   Signature
   0      6      0    this       Lscala/Numeric$IntIsIntegral$;
   0      6      1    x       I


public long toLong(int);
  Code:
   Stack=2, Locals=2, Args_size=2
   0:	aload_0
   1:	iload_1
   2:	invokestatic	#193; //Method scala/Numeric$IntIsIntegral$class.toLong:(Lscala/Numeric$IntIsIntegral;I)J
   5:	lreturn
  LineNumberTable: 
   line 32: 0

  LocalVariableTable: 
   Start  Length  Slot  Name   Signature
   0      6      0    this       Lscala/Numeric$IntIsIntegral$;
   0      6      1    x       I


public int toInt(int);
  Code:
   Stack=2, Locals=2, Args_size=2
   0:	aload_0
   1:	iload_1
   2:	invokestatic	#196; //Method scala/Numeric$IntIsIntegral$class.toInt:(Lscala/Numeric$IntIsIntegral;I)I
   5:	ireturn
  LineNumberTable: 
   line 32: 0

  LocalVariableTable: 
   Start  Length  Slot  Name   Signature
   0      6      0    this       Lscala/Numeric$IntIsIntegral$;
   0      6      1    x       I


public int fromInt(int);
  Code:
   Stack=2, Locals=2, Args_size=2
   0:	aload_0
   1:	iload_1
   2:	invokestatic	#198; //Method scala/Numeric$IntIsIntegral$class.fromInt:(Lscala/Numeric$IntIsIntegral;I)I
   5:	ireturn
  LineNumberTable: 
   line 32: 0

  LocalVariableTable: 
   Start  Length  Slot  Name   Signature
   0      6      0    this       Lscala/Numeric$IntIsIntegral$;
   0      6      1    x       I


public int negate(int);
  Code:
   Stack=2, Locals=2, Args_size=2
   0:	aload_0
   1:	iload_1
   2:	invokestatic	#200; //Method scala/Numeric$IntIsIntegral$class.negate:(Lscala/Numeric$IntIsIntegral;I)I
   5:	ireturn
  LineNumberTable: 
   line 32: 0

  LocalVariableTable: 
   Start  Length  Slot  Name   Signature
   0      6      0    this       Lscala/Numeric$IntIsIntegral$;
   0      6      1    x       I


public int rem(int, int);
  Code:
   Stack=3, Locals=3, Args_size=3
   0:	aload_0
   1:	iload_1
   2:	iload_2
   3:	invokestatic	#203; //Method scala/Numeric$IntIsIntegral$class.rem:(Lscala/Numeric$IntIsIntegral;II)I
   6:	ireturn
  LineNumberTable: 
   line 32: 0

  LocalVariableTable: 
   Start  Length  Slot  Name   Signature
   0      7      0    this       Lscala/Numeric$IntIsIntegral$;
   0      7      1    x       I
   0      7      2    y       I


public int quot(int, int);
  Code:
   Stack=3, Locals=3, Args_size=3
   0:	aload_0
   1:	iload_1
   2:	iload_2
   3:	invokestatic	#205; //Method scala/Numeric$IntIsIntegral$class.quot:(Lscala/Numeric$IntIsIntegral;II)I
   6:	ireturn
  LineNumberTable: 
   line 32: 0

  LocalVariableTable: 
   Start  Length  Slot  Name   Signature
   0      7      0    this       Lscala/Numeric$IntIsIntegral$;
   0      7      1    x       I
   0      7      2    y       I


public int times(int, int);
  Code:
   Stack=3, Locals=3, Args_size=3
   0:	aload_0
   1:	iload_1
   2:	iload_2
   3:	invokestatic	#207; //Method scala/Numeric$IntIsIntegral$class.times:(Lscala/Numeric$IntIsIntegral;II)I
   6:	ireturn
  LineNumberTable: 
   line 32: 0

  LocalVariableTable: 
   Start  Length  Slot  Name   Signature
   0      7      0    this       Lscala/Numeric$IntIsIntegral$;
   0      7      1    x       I
   0      7      2    y       I


public int minus(int, int);
  Code:
   Stack=3, Locals=3, Args_size=3
   0:	aload_0
   1:	iload_1
   2:	iload_2
   3:	invokestatic	#209; //Method scala/Numeric$IntIsIntegral$class.minus:(Lscala/Numeric$IntIsIntegral;II)I
   6:	ireturn
  LineNumberTable: 
   line 32: 0

  LocalVariableTable: 
   Start  Length  Slot  Name   Signature
   0      7      0    this       Lscala/Numeric$IntIsIntegral$;
   0      7      1    x       I
   0      7      2    y       I


public int plus(int, int);
  Code:
   Stack=3, Locals=3, Args_size=3
   0:	aload_0
   1:	iload_1
   2:	iload_2
   3:	invokestatic	#211; //Method scala/Numeric$IntIsIntegral$class.plus:(Lscala/Numeric$IntIsIntegral;II)I
   6:	ireturn
  LineNumberTable: 
   line 32: 0

  LocalVariableTable: 
   Start  Length  Slot  Name   Signature
   0      7      0    this       Lscala/Numeric$IntIsIntegral$;
   0      7      1    x       I
   0      7      2    y       I


public int compare(int, int);
  Code:
   Stack=3, Locals=3, Args_size=3
   0:	aload_0
   1:	iload_1
   2:	iload_2
   3:	invokestatic	#214; //Method scala/Ordering$IntOrdering$class.compare:(Lscala/Ordering$IntOrdering;II)I
   6:	ireturn
  LineNumberTable: 
   line 32: 0

  LocalVariableTable: 
   Start  Length  Slot  Name   Signature
   0      7      0    this       Lscala/Numeric$IntIsIntegral$;
   0      7      1    x       I
   0      7      2    y       I


}

