Compiled from "Numeric.scala"
public final class scala.Numeric$LongIsIntegral$ extends java.lang.Object implements scala.Numeric$LongIsIntegral,scala.Ordering$LongOrdering,scala.ScalaObject
  SourceFile: "Numeric.scala"
  Scala: length = 0x
   
  InnerClass: 
   public #224= #221 of #223; //Ops=class scala/Numeric$Ops of class scala/Numeric
   public #224= #226 of #132; //Ops=class scala/Ordering$Ops of class scala/Ordering
   public #229= #228 of #124; //IntegralOps=class scala/Integral$IntegralOps of class scala/Integral
   public abstract #230= #60 of #132; //LongOrdering=class scala/Ordering$LongOrdering of class scala/Ordering
   public abstract #231= #72 of #223; //LongIsIntegral=class scala/Numeric$LongIsIntegral of class scala/Numeric
  minor version: 0
  major version: 49
  Constant pool:
const #1 = Asciz	SourceFile;
const #2 = Asciz	Numeric.scala;
const #3 = Asciz	Scala;
const #4 = Asciz	MODULE$;
const #5 = Asciz	Lscala/Numeric$LongIsIntegral$;;
const #6 = Asciz	<clinit>;
const #7 = Asciz	()V;
const #8 = Asciz	Code;
const #9 = Asciz	scala/Numeric$LongIsIntegral$;
const #10 = class	#9;	//  scala/Numeric$LongIsIntegral$
const #11 = Asciz	<init>;
const #12 = NameAndType	#11:#7;//  "<init>":()V
const #13 = Method	#10.#12;	//  scala/Numeric$LongIsIntegral$."<init>":()V
const #14 = Asciz	LineNumberTable;
const #15 = Asciz	java/lang/Object;
const #16 = class	#15;	//  java/lang/Object
const #17 = Method	#16.#12;	//  java/lang/Object."<init>":()V
const #18 = NameAndType	#4:#5;//  MODULE$:Lscala/Numeric$LongIsIntegral$;
const #19 = Field	#10.#18;	//  scala/Numeric$LongIsIntegral$.MODULE$:Lscala/Numeric$LongIsIntegral$;
const #20 = Asciz	scala/PartialOrdering$class;
const #21 = class	#20;	//  scala/PartialOrdering$class
const #22 = Asciz	$init$;
const #23 = Asciz	(Lscala/PartialOrdering;)V;
const #24 = NameAndType	#22:#23;//  $init$:(Lscala/PartialOrdering;)V
const #25 = Method	#21.#24;	//  scala/PartialOrdering$class.$init$:(Lscala/PartialOrdering;)V
const #26 = Asciz	scala/Ordering$class;
const #27 = class	#26;	//  scala/Ordering$class
const #28 = Asciz	(Lscala/Ordering;)V;
const #29 = NameAndType	#22:#28;//  $init$:(Lscala/Ordering;)V
const #30 = Method	#27.#29;	//  scala/Ordering$class.$init$:(Lscala/Ordering;)V
const #31 = Asciz	scala/Numeric$class;
const #32 = class	#31;	//  scala/Numeric$class
const #33 = Asciz	(Lscala/Numeric;)V;
const #34 = NameAndType	#22:#33;//  $init$:(Lscala/Numeric;)V
const #35 = Method	#32.#34;	//  scala/Numeric$class.$init$:(Lscala/Numeric;)V
const #36 = Asciz	scala/Integral$class;
const #37 = class	#36;	//  scala/Integral$class
const #38 = Asciz	(Lscala/Integral;)V;
const #39 = NameAndType	#22:#38;//  $init$:(Lscala/Integral;)V
const #40 = Method	#37.#39;	//  scala/Integral$class.$init$:(Lscala/Integral;)V
const #41 = Asciz	scala/Numeric$LongIsIntegral$class;
const #42 = class	#41;	//  scala/Numeric$LongIsIntegral$class
const #43 = Asciz	(Lscala/Numeric$LongIsIntegral;)V;
const #44 = NameAndType	#22:#43;//  $init$:(Lscala/Numeric$LongIsIntegral;)V
const #45 = Method	#42.#44;	//  scala/Numeric$LongIsIntegral$class.$init$:(Lscala/Numeric$LongIsIntegral;)V
const #46 = Asciz	scala/Ordering$LongOrdering$class;
const #47 = class	#46;	//  scala/Ordering$LongOrdering$class
const #48 = Asciz	(Lscala/Ordering$LongOrdering;)V;
const #49 = NameAndType	#22:#48;//  $init$:(Lscala/Ordering$LongOrdering;)V
const #50 = Method	#47.#49;	//  scala/Ordering$LongOrdering$class.$init$:(Lscala/Ordering$LongOrdering;)V
const #51 = Asciz	compare;
const #52 = Asciz	(Ljava/lang/Object;Ljava/lang/Object;)I;
const #53 = Asciz	scala/runtime/BoxesRunTime;
const #54 = class	#53;	//  scala/runtime/BoxesRunTime
const #55 = Asciz	unboxToLong;
const #56 = Asciz	(Ljava/lang/Object;)J;
const #57 = NameAndType	#55:#56;//  unboxToLong:(Ljava/lang/Object;)J
const #58 = Method	#54.#57;	//  scala/runtime/BoxesRunTime.unboxToLong:(Ljava/lang/Object;)J
const #59 = Asciz	scala/Ordering$LongOrdering;
const #60 = class	#59;	//  scala/Ordering$LongOrdering
const #61 = Asciz	(JJ)I;
const #62 = NameAndType	#51:#61;//  compare:(JJ)I
const #63 = InterfaceMethod	#60.#62;	//  scala/Ordering$LongOrdering.compare:(JJ)I
const #64 = Asciz	this;
const #65 = Asciz	x;
const #66 = Asciz	Ljava/lang/Object;;
const #67 = Asciz	y;
const #68 = Asciz	LocalVariableTable;
const #69 = Asciz	plus;
const #70 = Asciz	(Ljava/lang/Object;Ljava/lang/Object;)Ljava/lang/Object;;
const #71 = Asciz	scala/Numeric$LongIsIntegral;
const #72 = class	#71;	//  scala/Numeric$LongIsIntegral
const #73 = Asciz	(JJ)J;
const #74 = NameAndType	#69:#73;//  plus:(JJ)J
const #75 = InterfaceMethod	#72.#74;	//  scala/Numeric$LongIsIntegral.plus:(JJ)J
const #76 = Asciz	boxToLong;
const #77 = Asciz	(J)Ljava/lang/Long;;
const #78 = NameAndType	#76:#77;//  boxToLong:(J)Ljava/lang/Long;
const #79 = Method	#54.#78;	//  scala/runtime/BoxesRunTime.boxToLong:(J)Ljava/lang/Long;
const #80 = Asciz	minus;
const #81 = NameAndType	#80:#73;//  minus:(JJ)J
const #82 = InterfaceMethod	#72.#81;	//  scala/Numeric$LongIsIntegral.minus:(JJ)J
const #83 = Asciz	times;
const #84 = NameAndType	#83:#73;//  times:(JJ)J
const #85 = InterfaceMethod	#72.#84;	//  scala/Numeric$LongIsIntegral.times:(JJ)J
const #86 = Asciz	quot;
const #87 = NameAndType	#86:#73;//  quot:(JJ)J
const #88 = InterfaceMethod	#72.#87;	//  scala/Numeric$LongIsIntegral.quot:(JJ)J
const #89 = Asciz	rem;
const #90 = NameAndType	#89:#73;//  rem:(JJ)J
const #91 = InterfaceMethod	#72.#90;	//  scala/Numeric$LongIsIntegral.rem:(JJ)J
const #92 = Asciz	negate;
const #93 = Asciz	(Ljava/lang/Object;)Ljava/lang/Object;;
const #94 = Asciz	(J)J;
const #95 = NameAndType	#92:#94;//  negate:(J)J
const #96 = InterfaceMethod	#72.#95;	//  scala/Numeric$LongIsIntegral.negate:(J)J
const #97 = Asciz	fromInt;
const #98 = Asciz	(I)Ljava/lang/Object;;
const #99 = Asciz	(I)J;
const #100 = NameAndType	#97:#99;//  fromInt:(I)J
const #101 = InterfaceMethod	#72.#100;	//  scala/Numeric$LongIsIntegral.fromInt:(I)J
const #102 = Asciz	I;
const #103 = Asciz	toInt;
const #104 = Asciz	(Ljava/lang/Object;)I;
const #105 = Asciz	(J)I;
const #106 = NameAndType	#103:#105;//  toInt:(J)I
const #107 = InterfaceMethod	#72.#106;	//  scala/Numeric$LongIsIntegral.toInt:(J)I
const #108 = Asciz	toLong;
const #109 = NameAndType	#108:#94;//  toLong:(J)J
const #110 = InterfaceMethod	#72.#109;	//  scala/Numeric$LongIsIntegral.toLong:(J)J
const #111 = Asciz	toFloat;
const #112 = Asciz	(Ljava/lang/Object;)F;
const #113 = Asciz	(J)F;
const #114 = NameAndType	#111:#113;//  toFloat:(J)F
const #115 = InterfaceMethod	#72.#114;	//  scala/Numeric$LongIsIntegral.toFloat:(J)F
const #116 = Asciz	toDouble;
const #117 = Asciz	(Ljava/lang/Object;)D;
const #118 = Asciz	(J)D;
const #119 = NameAndType	#116:#118;//  toDouble:(J)D
const #120 = InterfaceMethod	#72.#119;	//  scala/Numeric$LongIsIntegral.toDouble:(J)D
const #121 = Asciz	mkNumericOps;
const #122 = Asciz	(Ljava/lang/Object;)Lscala/Numeric$Ops;;
const #123 = Asciz	scala/Integral;
const #124 = class	#123;	//  scala/Integral
const #125 = Asciz	(Ljava/lang/Object;)Lscala/Integral$IntegralOps;;
const #126 = NameAndType	#121:#125;//  mkNumericOps:(Ljava/lang/Object;)Lscala/Integral$IntegralOps;
const #127 = InterfaceMethod	#124.#126;	//  scala/Integral.mkNumericOps:(Ljava/lang/Object;)Lscala/Integral$IntegralOps;
const #128 = Asciz	lhs;
const #129 = Asciz	reverse;
const #130 = Asciz	()Lscala/PartialOrdering;;
const #131 = Asciz	scala/Ordering;
const #132 = class	#131;	//  scala/Ordering
const #133 = Asciz	()Lscala/Ordering;;
const #134 = NameAndType	#129:#133;//  reverse:()Lscala/Ordering;
const #135 = InterfaceMethod	#132.#134;	//  scala/Ordering.reverse:()Lscala/Ordering;
const #136 = Asciz	mkOrderingOps;
const #137 = Asciz	(Ljava/lang/Object;)Lscala/Ordering$Ops;;
const #138 = Asciz	(Lscala/Ordering;Ljava/lang/Object;)Lscala/Ordering$Ops;;
const #139 = NameAndType	#136:#138;//  mkOrderingOps:(Lscala/Ordering;Ljava/lang/Object;)Lscala/Ordering$Ops;
const #140 = Method	#27.#139;	//  scala/Ordering$class.mkOrderingOps:(Lscala/Ordering;Ljava/lang/Object;)Lscala/Ordering$Ops;
const #141 = Asciz	(Lscala/Ordering;)Lscala/Ordering;;
const #142 = NameAndType	#129:#141;//  reverse:(Lscala/Ordering;)Lscala/Ordering;
const #143 = Method	#27.#142;	//  scala/Ordering$class.reverse:(Lscala/Ordering;)Lscala/Ordering;
const #144 = Asciz	min;
const #145 = Asciz	(Lscala/Ordering;Ljava/lang/Object;Ljava/lang/Object;)Ljava/lang/Object;;
const #146 = NameAndType	#144:#145;//  min:(Lscala/Ordering;Ljava/lang/Object;Ljava/lang/Object;)Ljava/lang/Object;
const #147 = Method	#27.#146;	//  scala/Ordering$class.min:(Lscala/Ordering;Ljava/lang/Object;Ljava/lang/Object;)Ljava/lang/Object;
const #148 = Asciz	max;
const #149 = NameAndType	#148:#145;//  max:(Lscala/Ordering;Ljava/lang/Object;Ljava/lang/Object;)Ljava/lang/Object;
const #150 = Method	#27.#149;	//  scala/Ordering$class.max:(Lscala/Ordering;Ljava/lang/Object;Ljava/lang/Object;)Ljava/lang/Object;
const #151 = Asciz	equiv;
const #152 = Asciz	(Ljava/lang/Object;Ljava/lang/Object;)Z;
const #153 = Asciz	(Lscala/Ordering;Ljava/lang/Object;Ljava/lang/Object;)Z;
const #154 = NameAndType	#151:#153;//  equiv:(Lscala/Ordering;Ljava/lang/Object;Ljava/lang/Object;)Z
const #155 = Method	#27.#154;	//  scala/Ordering$class.equiv:(Lscala/Ordering;Ljava/lang/Object;Ljava/lang/Object;)Z
const #156 = Asciz	gt;
const #157 = NameAndType	#156:#153;//  gt:(Lscala/Ordering;Ljava/lang/Object;Ljava/lang/Object;)Z
const #158 = Method	#27.#157;	//  scala/Ordering$class.gt:(Lscala/Ordering;Ljava/lang/Object;Ljava/lang/Object;)Z
const #159 = Asciz	lt;
const #160 = NameAndType	#159:#153;//  lt:(Lscala/Ordering;Ljava/lang/Object;Ljava/lang/Object;)Z
const #161 = Method	#27.#160;	//  scala/Ordering$class.lt:(Lscala/Ordering;Ljava/lang/Object;Ljava/lang/Object;)Z
const #162 = Asciz	gteq;
const #163 = NameAndType	#162:#153;//  gteq:(Lscala/Ordering;Ljava/lang/Object;Ljava/lang/Object;)Z
const #164 = Method	#27.#163;	//  scala/Ordering$class.gteq:(Lscala/Ordering;Ljava/lang/Object;Ljava/lang/Object;)Z
const #165 = Asciz	lteq;
const #166 = NameAndType	#165:#153;//  lteq:(Lscala/Ordering;Ljava/lang/Object;Ljava/lang/Object;)Z
const #167 = Method	#27.#166;	//  scala/Ordering$class.lteq:(Lscala/Ordering;Ljava/lang/Object;Ljava/lang/Object;)Z
const #168 = Asciz	signum;
const #169 = Asciz	(Lscala/Numeric;Ljava/lang/Object;)I;
const #170 = NameAndType	#168:#169;//  signum:(Lscala/Numeric;Ljava/lang/Object;)I
const #171 = Method	#32.#170;	//  scala/Numeric$class.signum:(Lscala/Numeric;Ljava/lang/Object;)I
const #172 = Asciz	abs;
const #173 = Asciz	(Lscala/Numeric;Ljava/lang/Object;)Ljava/lang/Object;;
const #174 = NameAndType	#172:#173;//  abs:(Lscala/Numeric;Ljava/lang/Object;)Ljava/lang/Object;
const #175 = Method	#32.#174;	//  scala/Numeric$class.abs:(Lscala/Numeric;Ljava/lang/Object;)Ljava/lang/Object;
const #176 = Asciz	one;
const #177 = Asciz	()Ljava/lang/Object;;
const #178 = Asciz	(Lscala/Numeric;)Ljava/lang/Object;;
const #179 = NameAndType	#176:#178;//  one:(Lscala/Numeric;)Ljava/lang/Object;
const #180 = Method	#32.#179;	//  scala/Numeric$class.one:(Lscala/Numeric;)Ljava/lang/Object;
const #181 = Asciz	zero;
const #182 = NameAndType	#181:#178;//  zero:(Lscala/Numeric;)Ljava/lang/Object;
const #183 = Method	#32.#182;	//  scala/Numeric$class.zero:(Lscala/Numeric;)Ljava/lang/Object;
const #184 = Asciz	(Lscala/Integral;Ljava/lang/Object;)Lscala/Integral$IntegralOps;;
const #185 = NameAndType	#121:#184;//  mkNumericOps:(Lscala/Integral;Ljava/lang/Object;)Lscala/Integral$IntegralOps;
const #186 = Method	#37.#185;	//  scala/Integral$class.mkNumericOps:(Lscala/Integral;Ljava/lang/Object;)Lscala/Integral$IntegralOps;
const #187 = Asciz	(Lscala/Numeric$LongIsIntegral;J)D;
const #188 = NameAndType	#116:#187;//  toDouble:(Lscala/Numeric$LongIsIntegral;J)D
const #189 = Method	#42.#188;	//  scala/Numeric$LongIsIntegral$class.toDouble:(Lscala/Numeric$LongIsIntegral;J)D
const #190 = Asciz	J;
const #191 = Asciz	(Lscala/Numeric$LongIsIntegral;J)F;
const #192 = NameAndType	#111:#191;//  toFloat:(Lscala/Numeric$LongIsIntegral;J)F
const #193 = Method	#42.#192;	//  scala/Numeric$LongIsIntegral$class.toFloat:(Lscala/Numeric$LongIsIntegral;J)F
const #194 = Asciz	(Lscala/Numeric$LongIsIntegral;J)J;
const #195 = NameAndType	#108:#194;//  toLong:(Lscala/Numeric$LongIsIntegral;J)J
const #196 = Method	#42.#195;	//  scala/Numeric$LongIsIntegral$class.toLong:(Lscala/Numeric$LongIsIntegral;J)J
const #197 = Asciz	(Lscala/Numeric$LongIsIntegral;J)I;
const #198 = NameAndType	#103:#197;//  toInt:(Lscala/Numeric$LongIsIntegral;J)I
const #199 = Method	#42.#198;	//  scala/Numeric$LongIsIntegral$class.toInt:(Lscala/Numeric$LongIsIntegral;J)I
const #200 = Asciz	(Lscala/Numeric$LongIsIntegral;I)J;
const #201 = NameAndType	#97:#200;//  fromInt:(Lscala/Numeric$LongIsIntegral;I)J
const #202 = Method	#42.#201;	//  scala/Numeric$LongIsIntegral$class.fromInt:(Lscala/Numeric$LongIsIntegral;I)J
const #203 = NameAndType	#92:#194;//  negate:(Lscala/Numeric$LongIsIntegral;J)J
const #204 = Method	#42.#203;	//  scala/Numeric$LongIsIntegral$class.negate:(Lscala/Numeric$LongIsIntegral;J)J
const #205 = Asciz	(Lscala/Numeric$LongIsIntegral;JJ)J;
const #206 = NameAndType	#89:#205;//  rem:(Lscala/Numeric$LongIsIntegral;JJ)J
const #207 = Method	#42.#206;	//  scala/Numeric$LongIsIntegral$class.rem:(Lscala/Numeric$LongIsIntegral;JJ)J
const #208 = NameAndType	#86:#205;//  quot:(Lscala/Numeric$LongIsIntegral;JJ)J
const #209 = Method	#42.#208;	//  scala/Numeric$LongIsIntegral$class.quot:(Lscala/Numeric$LongIsIntegral;JJ)J
const #210 = NameAndType	#83:#205;//  times:(Lscala/Numeric$LongIsIntegral;JJ)J
const #211 = Method	#42.#210;	//  scala/Numeric$LongIsIntegral$class.times:(Lscala/Numeric$LongIsIntegral;JJ)J
const #212 = NameAndType	#80:#205;//  minus:(Lscala/Numeric$LongIsIntegral;JJ)J
const #213 = Method	#42.#212;	//  scala/Numeric$LongIsIntegral$class.minus:(Lscala/Numeric$LongIsIntegral;JJ)J
const #214 = NameAndType	#69:#205;//  plus:(Lscala/Numeric$LongIsIntegral;JJ)J
const #215 = Method	#42.#214;	//  scala/Numeric$LongIsIntegral$class.plus:(Lscala/Numeric$LongIsIntegral;JJ)J
const #216 = Asciz	(Lscala/Ordering$LongOrdering;JJ)I;
const #217 = NameAndType	#51:#216;//  compare:(Lscala/Ordering$LongOrdering;JJ)I
const #218 = Method	#47.#217;	//  scala/Ordering$LongOrdering$class.compare:(Lscala/Ordering$LongOrdering;JJ)I
const #219 = Asciz	InnerClasses;
const #220 = Asciz	scala/Numeric$Ops;
const #221 = class	#220;	//  scala/Numeric$Ops
const #222 = Asciz	scala/Numeric;
const #223 = class	#222;	//  scala/Numeric
const #224 = Asciz	Ops;
const #225 = Asciz	scala/Ordering$Ops;
const #226 = class	#225;	//  scala/Ordering$Ops
const #227 = Asciz	scala/Integral$IntegralOps;
const #228 = class	#227;	//  scala/Integral$IntegralOps
const #229 = Asciz	IntegralOps;
const #230 = Asciz	LongOrdering;
const #231 = Asciz	LongIsIntegral;
const #232 = Asciz	scala/ScalaObject;
const #233 = class	#232;	//  scala/ScalaObject

{
public static final scala.Numeric$LongIsIntegral$ MODULE$;

public static {};
  Code:
   Stack=1, Locals=0, Args_size=0
   0:	new	#10; //class scala/Numeric$LongIsIntegral$
   3:	invokespecial	#13; //Method "<init>":()V
   6:	return

public scala.Numeric$LongIsIntegral$();
  Code:
   Stack=1, Locals=1, Args_size=1
   0:	aload_0
   1:	invokespecial	#17; //Method java/lang/Object."<init>":()V
   4:	aload_0
   5:	putstatic	#19; //Field MODULE$:Lscala/Numeric$LongIsIntegral$;
   8:	aload_0
   9:	invokestatic	#25; //Method scala/PartialOrdering$class.$init$:(Lscala/PartialOrdering;)V
   12:	aload_0
   13:	invokestatic	#30; //Method scala/Ordering$class.$init$:(Lscala/Ordering;)V
   16:	aload_0
   17:	invokestatic	#35; //Method scala/Numeric$class.$init$:(Lscala/Numeric;)V
   20:	aload_0
   21:	invokestatic	#40; //Method scala/Integral$class.$init$:(Lscala/Integral;)V
   24:	aload_0
   25:	invokestatic	#45; //Method scala/Numeric$LongIsIntegral$class.$init$:(Lscala/Numeric$LongIsIntegral;)V
   28:	aload_0
   29:	invokestatic	#50; //Method scala/Ordering$LongOrdering$class.$init$:(Lscala/Ordering$LongOrdering;)V
   32:	return
  LineNumberTable: 
   line 47: 0


public int compare(java.lang.Object, java.lang.Object);
  Code:
   Stack=5, Locals=3, Args_size=3
   0:	aload_0
   1:	aload_1
   2:	invokestatic	#58; //Method scala/runtime/BoxesRunTime.unboxToLong:(Ljava/lang/Object;)J
   5:	aload_2
   6:	invokestatic	#58; //Method scala/runtime/BoxesRunTime.unboxToLong:(Ljava/lang/Object;)J
   9:	invokeinterface	#63,  5; //InterfaceMethod scala/Ordering$LongOrdering.compare:(JJ)I
   14:	ireturn
  LineNumberTable: 
   line 47: 0

  LocalVariableTable: 
   Start  Length  Slot  Name   Signature
   0      15      0    this       Lscala/Numeric$LongIsIntegral$;
   0      15      1    x       Ljava/lang/Object;
   0      15      2    y       Ljava/lang/Object;


public java.lang.Object plus(java.lang.Object, java.lang.Object);
  Code:
   Stack=5, Locals=3, Args_size=3
   0:	aload_0
   1:	aload_1
   2:	invokestatic	#58; //Method scala/runtime/BoxesRunTime.unboxToLong:(Ljava/lang/Object;)J
   5:	aload_2
   6:	invokestatic	#58; //Method scala/runtime/BoxesRunTime.unboxToLong:(Ljava/lang/Object;)J
   9:	invokeinterface	#75,  5; //InterfaceMethod scala/Numeric$LongIsIntegral.plus:(JJ)J
   14:	invokestatic	#79; //Method scala/runtime/BoxesRunTime.boxToLong:(J)Ljava/lang/Long;
   17:	areturn
  LineNumberTable: 
   line 47: 0

  LocalVariableTable: 
   Start  Length  Slot  Name   Signature
   0      18      0    this       Lscala/Numeric$LongIsIntegral$;
   0      18      1    x       Ljava/lang/Object;
   0      18      2    y       Ljava/lang/Object;


public java.lang.Object minus(java.lang.Object, java.lang.Object);
  Code:
   Stack=5, Locals=3, Args_size=3
   0:	aload_0
   1:	aload_1
   2:	invokestatic	#58; //Method scala/runtime/BoxesRunTime.unboxToLong:(Ljava/lang/Object;)J
   5:	aload_2
   6:	invokestatic	#58; //Method scala/runtime/BoxesRunTime.unboxToLong:(Ljava/lang/Object;)J
   9:	invokeinterface	#82,  5; //InterfaceMethod scala/Numeric$LongIsIntegral.minus:(JJ)J
   14:	invokestatic	#79; //Method scala/runtime/BoxesRunTime.boxToLong:(J)Ljava/lang/Long;
   17:	areturn
  LineNumberTable: 
   line 47: 0

  LocalVariableTable: 
   Start  Length  Slot  Name   Signature
   0      18      0    this       Lscala/Numeric$LongIsIntegral$;
   0      18      1    x       Ljava/lang/Object;
   0      18      2    y       Ljava/lang/Object;


public java.lang.Object times(java.lang.Object, java.lang.Object);
  Code:
   Stack=5, Locals=3, Args_size=3
   0:	aload_0
   1:	aload_1
   2:	invokestatic	#58; //Method scala/runtime/BoxesRunTime.unboxToLong:(Ljava/lang/Object;)J
   5:	aload_2
   6:	invokestatic	#58; //Method scala/runtime/BoxesRunTime.unboxToLong:(Ljava/lang/Object;)J
   9:	invokeinterface	#85,  5; //InterfaceMethod scala/Numeric$LongIsIntegral.times:(JJ)J
   14:	invokestatic	#79; //Method scala/runtime/BoxesRunTime.boxToLong:(J)Ljava/lang/Long;
   17:	areturn
  LineNumberTable: 
   line 47: 0

  LocalVariableTable: 
   Start  Length  Slot  Name   Signature
   0      18      0    this       Lscala/Numeric$LongIsIntegral$;
   0      18      1    x       Ljava/lang/Object;
   0      18      2    y       Ljava/lang/Object;


public java.lang.Object quot(java.lang.Object, java.lang.Object);
  Code:
   Stack=5, Locals=3, Args_size=3
   0:	aload_0
   1:	aload_1
   2:	invokestatic	#58; //Method scala/runtime/BoxesRunTime.unboxToLong:(Ljava/lang/Object;)J
   5:	aload_2
   6:	invokestatic	#58; //Method scala/runtime/BoxesRunTime.unboxToLong:(Ljava/lang/Object;)J
   9:	invokeinterface	#88,  5; //InterfaceMethod scala/Numeric$LongIsIntegral.quot:(JJ)J
   14:	invokestatic	#79; //Method scala/runtime/BoxesRunTime.boxToLong:(J)Ljava/lang/Long;
   17:	areturn
  LineNumberTable: 
   line 47: 0

  LocalVariableTable: 
   Start  Length  Slot  Name   Signature
   0      18      0    this       Lscala/Numeric$LongIsIntegral$;
   0      18      1    x       Ljava/lang/Object;
   0      18      2    y       Ljava/lang/Object;


public java.lang.Object rem(java.lang.Object, java.lang.Object);
  Code:
   Stack=5, Locals=3, Args_size=3
   0:	aload_0
   1:	aload_1
   2:	invokestatic	#58; //Method scala/runtime/BoxesRunTime.unboxToLong:(Ljava/lang/Object;)J
   5:	aload_2
   6:	invokestatic	#58; //Method scala/runtime/BoxesRunTime.unboxToLong:(Ljava/lang/Object;)J
   9:	invokeinterface	#91,  5; //InterfaceMethod scala/Numeric$LongIsIntegral.rem:(JJ)J
   14:	invokestatic	#79; //Method scala/runtime/BoxesRunTime.boxToLong:(J)Ljava/lang/Long;
   17:	areturn
  LineNumberTable: 
   line 47: 0

  LocalVariableTable: 
   Start  Length  Slot  Name   Signature
   0      18      0    this       Lscala/Numeric$LongIsIntegral$;
   0      18      1    x       Ljava/lang/Object;
   0      18      2    y       Ljava/lang/Object;


public java.lang.Object negate(java.lang.Object);
  Code:
   Stack=3, Locals=2, Args_size=2
   0:	aload_0
   1:	aload_1
   2:	invokestatic	#58; //Method scala/runtime/BoxesRunTime.unboxToLong:(Ljava/lang/Object;)J
   5:	invokeinterface	#96,  3; //InterfaceMethod scala/Numeric$LongIsIntegral.negate:(J)J
   10:	invokestatic	#79; //Method scala/runtime/BoxesRunTime.boxToLong:(J)Ljava/lang/Long;
   13:	areturn
  LineNumberTable: 
   line 47: 0

  LocalVariableTable: 
   Start  Length  Slot  Name   Signature
   0      14      0    this       Lscala/Numeric$LongIsIntegral$;
   0      14      1    x       Ljava/lang/Object;


public java.lang.Object fromInt(int);
  Code:
   Stack=2, Locals=2, Args_size=2
   0:	aload_0
   1:	iload_1
   2:	invokeinterface	#101,  2; //InterfaceMethod scala/Numeric$LongIsIntegral.fromInt:(I)J
   7:	invokestatic	#79; //Method scala/runtime/BoxesRunTime.boxToLong:(J)Ljava/lang/Long;
   10:	areturn
  LineNumberTable: 
   line 47: 0

  LocalVariableTable: 
   Start  Length  Slot  Name   Signature
   0      11      0    this       Lscala/Numeric$LongIsIntegral$;
   0      11      1    x       I


public int toInt(java.lang.Object);
  Code:
   Stack=3, Locals=2, Args_size=2
   0:	aload_0
   1:	aload_1
   2:	invokestatic	#58; //Method scala/runtime/BoxesRunTime.unboxToLong:(Ljava/lang/Object;)J
   5:	invokeinterface	#107,  3; //InterfaceMethod scala/Numeric$LongIsIntegral.toInt:(J)I
   10:	ireturn
  LineNumberTable: 
   line 47: 0

  LocalVariableTable: 
   Start  Length  Slot  Name   Signature
   0      11      0    this       Lscala/Numeric$LongIsIntegral$;
   0      11      1    x       Ljava/lang/Object;


public long toLong(java.lang.Object);
  Code:
   Stack=3, Locals=2, Args_size=2
   0:	aload_0
   1:	aload_1
   2:	invokestatic	#58; //Method scala/runtime/BoxesRunTime.unboxToLong:(Ljava/lang/Object;)J
   5:	invokeinterface	#110,  3; //InterfaceMethod scala/Numeric$LongIsIntegral.toLong:(J)J
   10:	lreturn
  LineNumberTable: 
   line 47: 0

  LocalVariableTable: 
   Start  Length  Slot  Name   Signature
   0      11      0    this       Lscala/Numeric$LongIsIntegral$;
   0      11      1    x       Ljava/lang/Object;


public float toFloat(java.lang.Object);
  Code:
   Stack=3, Locals=2, Args_size=2
   0:	aload_0
   1:	aload_1
   2:	invokestatic	#58; //Method scala/runtime/BoxesRunTime.unboxToLong:(Ljava/lang/Object;)J
   5:	invokeinterface	#115,  3; //InterfaceMethod scala/Numeric$LongIsIntegral.toFloat:(J)F
   10:	freturn
  LineNumberTable: 
   line 47: 0

  LocalVariableTable: 
   Start  Length  Slot  Name   Signature
   0      11      0    this       Lscala/Numeric$LongIsIntegral$;
   0      11      1    x       Ljava/lang/Object;


public double toDouble(java.lang.Object);
  Code:
   Stack=3, Locals=2, Args_size=2
   0:	aload_0
   1:	aload_1
   2:	invokestatic	#58; //Method scala/runtime/BoxesRunTime.unboxToLong:(Ljava/lang/Object;)J
   5:	invokeinterface	#120,  3; //InterfaceMethod scala/Numeric$LongIsIntegral.toDouble:(J)D
   10:	dreturn
  LineNumberTable: 
   line 47: 0

  LocalVariableTable: 
   Start  Length  Slot  Name   Signature
   0      11      0    this       Lscala/Numeric$LongIsIntegral$;
   0      11      1    x       Ljava/lang/Object;


public scala.Numeric$Ops mkNumericOps(java.lang.Object);
  Code:
   Stack=2, Locals=2, Args_size=2
   0:	aload_0
   1:	aload_1
   2:	invokeinterface	#127,  2; //InterfaceMethod scala/Integral.mkNumericOps:(Ljava/lang/Object;)Lscala/Integral$IntegralOps;
   7:	areturn
  LineNumberTable: 
   line 47: 0

  LocalVariableTable: 
   Start  Length  Slot  Name   Signature
   0      8      0    this       Lscala/Numeric$LongIsIntegral$;
   0      8      1    lhs       Ljava/lang/Object;


public scala.PartialOrdering reverse();
  Code:
   Stack=1, Locals=1, Args_size=1
   0:	aload_0
   1:	invokeinterface	#135,  1; //InterfaceMethod scala/Ordering.reverse:()Lscala/Ordering;
   6:	areturn
  LineNumberTable: 
   line 47: 0


public scala.Ordering$Ops mkOrderingOps(java.lang.Object);
  Code:
   Stack=2, Locals=2, Args_size=2
   0:	aload_0
   1:	aload_1
   2:	invokestatic	#140; //Method scala/Ordering$class.mkOrderingOps:(Lscala/Ordering;Ljava/lang/Object;)Lscala/Ordering$Ops;
   5:	areturn
  LineNumberTable: 
   line 47: 0

  LocalVariableTable: 
   Start  Length  Slot  Name   Signature
   0      6      0    this       Lscala/Numeric$LongIsIntegral$;
   0      6      1    lhs       Ljava/lang/Object;


public scala.Ordering reverse();
  Code:
   Stack=1, Locals=1, Args_size=1
   0:	aload_0
   1:	invokestatic	#143; //Method scala/Ordering$class.reverse:(Lscala/Ordering;)Lscala/Ordering;
   4:	areturn
  LineNumberTable: 
   line 47: 0


public java.lang.Object min(java.lang.Object, java.lang.Object);
  Code:
   Stack=3, Locals=3, Args_size=3
   0:	aload_0
   1:	aload_1
   2:	aload_2
   3:	invokestatic	#147; //Method scala/Ordering$class.min:(Lscala/Ordering;Ljava/lang/Object;Ljava/lang/Object;)Ljava/lang/Object;
   6:	areturn
  LineNumberTable: 
   line 47: 0

  LocalVariableTable: 
   Start  Length  Slot  Name   Signature
   0      7      0    this       Lscala/Numeric$LongIsIntegral$;
   0      7      1    x       Ljava/lang/Object;
   0      7      2    y       Ljava/lang/Object;


public java.lang.Object max(java.lang.Object, java.lang.Object);
  Code:
   Stack=3, Locals=3, Args_size=3
   0:	aload_0
   1:	aload_1
   2:	aload_2
   3:	invokestatic	#150; //Method scala/Ordering$class.max:(Lscala/Ordering;Ljava/lang/Object;Ljava/lang/Object;)Ljava/lang/Object;
   6:	areturn
  LineNumberTable: 
   line 47: 0

  LocalVariableTable: 
   Start  Length  Slot  Name   Signature
   0      7      0    this       Lscala/Numeric$LongIsIntegral$;
   0      7      1    x       Ljava/lang/Object;
   0      7      2    y       Ljava/lang/Object;


public boolean equiv(java.lang.Object, java.lang.Object);
  Code:
   Stack=3, Locals=3, Args_size=3
   0:	aload_0
   1:	aload_1
   2:	aload_2
   3:	invokestatic	#155; //Method scala/Ordering$class.equiv:(Lscala/Ordering;Ljava/lang/Object;Ljava/lang/Object;)Z
   6:	ireturn
  LineNumberTable: 
   line 47: 0

  LocalVariableTable: 
   Start  Length  Slot  Name   Signature
   0      7      0    this       Lscala/Numeric$LongIsIntegral$;
   0      7      1    x       Ljava/lang/Object;
   0      7      2    y       Ljava/lang/Object;


public boolean gt(java.lang.Object, java.lang.Object);
  Code:
   Stack=3, Locals=3, Args_size=3
   0:	aload_0
   1:	aload_1
   2:	aload_2
   3:	invokestatic	#158; //Method scala/Ordering$class.gt:(Lscala/Ordering;Ljava/lang/Object;Ljava/lang/Object;)Z
   6:	ireturn
  LineNumberTable: 
   line 47: 0

  LocalVariableTable: 
   Start  Length  Slot  Name   Signature
   0      7      0    this       Lscala/Numeric$LongIsIntegral$;
   0      7      1    x       Ljava/lang/Object;
   0      7      2    y       Ljava/lang/Object;


public boolean lt(java.lang.Object, java.lang.Object);
  Code:
   Stack=3, Locals=3, Args_size=3
   0:	aload_0
   1:	aload_1
   2:	aload_2
   3:	invokestatic	#161; //Method scala/Ordering$class.lt:(Lscala/Ordering;Ljava/lang/Object;Ljava/lang/Object;)Z
   6:	ireturn
  LineNumberTable: 
   line 47: 0

  LocalVariableTable: 
   Start  Length  Slot  Name   Signature
   0      7      0    this       Lscala/Numeric$LongIsIntegral$;
   0      7      1    x       Ljava/lang/Object;
   0      7      2    y       Ljava/lang/Object;


public boolean gteq(java.lang.Object, java.lang.Object);
  Code:
   Stack=3, Locals=3, Args_size=3
   0:	aload_0
   1:	aload_1
   2:	aload_2
   3:	invokestatic	#164; //Method scala/Ordering$class.gteq:(Lscala/Ordering;Ljava/lang/Object;Ljava/lang/Object;)Z
   6:	ireturn
  LineNumberTable: 
   line 47: 0

  LocalVariableTable: 
   Start  Length  Slot  Name   Signature
   0      7      0    this       Lscala/Numeric$LongIsIntegral$;
   0      7      1    x       Ljava/lang/Object;
   0      7      2    y       Ljava/lang/Object;


public boolean lteq(java.lang.Object, java.lang.Object);
  Code:
   Stack=3, Locals=3, Args_size=3
   0:	aload_0
   1:	aload_1
   2:	aload_2
   3:	invokestatic	#167; //Method scala/Ordering$class.lteq:(Lscala/Ordering;Ljava/lang/Object;Ljava/lang/Object;)Z
   6:	ireturn
  LineNumberTable: 
   line 47: 0

  LocalVariableTable: 
   Start  Length  Slot  Name   Signature
   0      7      0    this       Lscala/Numeric$LongIsIntegral$;
   0      7      1    x       Ljava/lang/Object;
   0      7      2    y       Ljava/lang/Object;


public int signum(java.lang.Object);
  Code:
   Stack=2, Locals=2, Args_size=2
   0:	aload_0
   1:	aload_1
   2:	invokestatic	#171; //Method scala/Numeric$class.signum:(Lscala/Numeric;Ljava/lang/Object;)I
   5:	ireturn
  LineNumberTable: 
   line 47: 0

  LocalVariableTable: 
   Start  Length  Slot  Name   Signature
   0      6      0    this       Lscala/Numeric$LongIsIntegral$;
   0      6      1    x       Ljava/lang/Object;


public java.lang.Object abs(java.lang.Object);
  Code:
   Stack=2, Locals=2, Args_size=2
   0:	aload_0
   1:	aload_1
   2:	invokestatic	#175; //Method scala/Numeric$class.abs:(Lscala/Numeric;Ljava/lang/Object;)Ljava/lang/Object;
   5:	areturn
  LineNumberTable: 
   line 47: 0

  LocalVariableTable: 
   Start  Length  Slot  Name   Signature
   0      6      0    this       Lscala/Numeric$LongIsIntegral$;
   0      6      1    x       Ljava/lang/Object;


public java.lang.Object one();
  Code:
   Stack=1, Locals=1, Args_size=1
   0:	aload_0
   1:	invokestatic	#180; //Method scala/Numeric$class.one:(Lscala/Numeric;)Ljava/lang/Object;
   4:	areturn
  LineNumberTable: 
   line 47: 0


public java.lang.Object zero();
  Code:
   Stack=1, Locals=1, Args_size=1
   0:	aload_0
   1:	invokestatic	#183; //Method scala/Numeric$class.zero:(Lscala/Numeric;)Ljava/lang/Object;
   4:	areturn
  LineNumberTable: 
   line 47: 0


public scala.Integral$IntegralOps mkNumericOps(java.lang.Object);
  Code:
   Stack=2, Locals=2, Args_size=2
   0:	aload_0
   1:	aload_1
   2:	invokestatic	#186; //Method scala/Integral$class.mkNumericOps:(Lscala/Integral;Ljava/lang/Object;)Lscala/Integral$IntegralOps;
   5:	areturn
  LineNumberTable: 
   line 47: 0

  LocalVariableTable: 
   Start  Length  Slot  Name   Signature
   0      6      0    this       Lscala/Numeric$LongIsIntegral$;
   0      6      1    lhs       Ljava/lang/Object;


public double toDouble(long);
  Code:
   Stack=3, Locals=3, Args_size=2
   0:	aload_0
   1:	lload_1
   2:	invokestatic	#189; //Method scala/Numeric$LongIsIntegral$class.toDouble:(Lscala/Numeric$LongIsIntegral;J)D
   5:	dreturn
  LineNumberTable: 
   line 47: 0

  LocalVariableTable: 
   Start  Length  Slot  Name   Signature
   0      6      0    this       Lscala/Numeric$LongIsIntegral$;
   0      6      1    x       J


public float toFloat(long);
  Code:
   Stack=3, Locals=3, Args_size=2
   0:	aload_0
   1:	lload_1
   2:	invokestatic	#193; //Method scala/Numeric$LongIsIntegral$class.toFloat:(Lscala/Numeric$LongIsIntegral;J)F
   5:	freturn
  LineNumberTable: 
   line 47: 0

  LocalVariableTable: 
   Start  Length  Slot  Name   Signature
   0      6      0    this       Lscala/Numeric$LongIsIntegral$;
   0      6      1    x       J


public long toLong(long);
  Code:
   Stack=3, Locals=3, Args_size=2
   0:	aload_0
   1:	lload_1
   2:	invokestatic	#196; //Method scala/Numeric$LongIsIntegral$class.toLong:(Lscala/Numeric$LongIsIntegral;J)J
   5:	lreturn
  LineNumberTable: 
   line 47: 0

  LocalVariableTable: 
   Start  Length  Slot  Name   Signature
   0      6      0    this       Lscala/Numeric$LongIsIntegral$;
   0      6      1    x       J


public int toInt(long);
  Code:
   Stack=3, Locals=3, Args_size=2
   0:	aload_0
   1:	lload_1
   2:	invokestatic	#199; //Method scala/Numeric$LongIsIntegral$class.toInt:(Lscala/Numeric$LongIsIntegral;J)I
   5:	ireturn
  LineNumberTable: 
   line 47: 0

  LocalVariableTable: 
   Start  Length  Slot  Name   Signature
   0      6      0    this       Lscala/Numeric$LongIsIntegral$;
   0      6      1    x       J


public long fromInt(int);
  Code:
   Stack=2, Locals=2, Args_size=2
   0:	aload_0
   1:	iload_1
   2:	invokestatic	#202; //Method scala/Numeric$LongIsIntegral$class.fromInt:(Lscala/Numeric$LongIsIntegral;I)J
   5:	lreturn
  LineNumberTable: 
   line 47: 0

  LocalVariableTable: 
   Start  Length  Slot  Name   Signature
   0      6      0    this       Lscala/Numeric$LongIsIntegral$;
   0      6      1    x       I


public long negate(long);
  Code:
   Stack=3, Locals=3, Args_size=2
   0:	aload_0
   1:	lload_1
   2:	invokestatic	#204; //Method scala/Numeric$LongIsIntegral$class.negate:(Lscala/Numeric$LongIsIntegral;J)J
   5:	lreturn
  LineNumberTable: 
   line 47: 0

  LocalVariableTable: 
   Start  Length  Slot  Name   Signature
   0      6      0    this       Lscala/Numeric$LongIsIntegral$;
   0      6      1    x       J


public long rem(long, long);
  Code:
   Stack=5, Locals=5, Args_size=3
   0:	aload_0
   1:	lload_1
   2:	lload_3
   3:	invokestatic	#207; //Method scala/Numeric$LongIsIntegral$class.rem:(Lscala/Numeric$LongIsIntegral;JJ)J
   6:	lreturn
  LineNumberTable: 
   line 47: 0

  LocalVariableTable: 
   Start  Length  Slot  Name   Signature
   0      7      0    this       Lscala/Numeric$LongIsIntegral$;
   0      7      1    x       J
   0      7      3    y       J


public long quot(long, long);
  Code:
   Stack=5, Locals=5, Args_size=3
   0:	aload_0
   1:	lload_1
   2:	lload_3
   3:	invokestatic	#209; //Method scala/Numeric$LongIsIntegral$class.quot:(Lscala/Numeric$LongIsIntegral;JJ)J
   6:	lreturn
  LineNumberTable: 
   line 47: 0

  LocalVariableTable: 
   Start  Length  Slot  Name   Signature
   0      7      0    this       Lscala/Numeric$LongIsIntegral$;
   0      7      1    x       J
   0      7      3    y       J


public long times(long, long);
  Code:
   Stack=5, Locals=5, Args_size=3
   0:	aload_0
   1:	lload_1
   2:	lload_3
   3:	invokestatic	#211; //Method scala/Numeric$LongIsIntegral$class.times:(Lscala/Numeric$LongIsIntegral;JJ)J
   6:	lreturn
  LineNumberTable: 
   line 47: 0

  LocalVariableTable: 
   Start  Length  Slot  Name   Signature
   0      7      0    this       Lscala/Numeric$LongIsIntegral$;
   0      7      1    x       J
   0      7      3    y       J


public long minus(long, long);
  Code:
   Stack=5, Locals=5, Args_size=3
   0:	aload_0
   1:	lload_1
   2:	lload_3
   3:	invokestatic	#213; //Method scala/Numeric$LongIsIntegral$class.minus:(Lscala/Numeric$LongIsIntegral;JJ)J
   6:	lreturn
  LineNumberTable: 
   line 47: 0

  LocalVariableTable: 
   Start  Length  Slot  Name   Signature
   0      7      0    this       Lscala/Numeric$LongIsIntegral$;
   0      7      1    x       J
   0      7      3    y       J


public long plus(long, long);
  Code:
   Stack=5, Locals=5, Args_size=3
   0:	aload_0
   1:	lload_1
   2:	lload_3
   3:	invokestatic	#215; //Method scala/Numeric$LongIsIntegral$class.plus:(Lscala/Numeric$LongIsIntegral;JJ)J
   6:	lreturn
  LineNumberTable: 
   line 47: 0

  LocalVariableTable: 
   Start  Length  Slot  Name   Signature
   0      7      0    this       Lscala/Numeric$LongIsIntegral$;
   0      7      1    x       J
   0      7      3    y       J


public int compare(long, long);
  Code:
   Stack=5, Locals=5, Args_size=3
   0:	aload_0
   1:	lload_1
   2:	lload_3
   3:	invokestatic	#218; //Method scala/Ordering$LongOrdering$class.compare:(Lscala/Ordering$LongOrdering;JJ)I
   6:	ireturn
  LineNumberTable: 
   line 47: 0

  LocalVariableTable: 
   Start  Length  Slot  Name   Signature
   0      7      0    this       Lscala/Numeric$LongIsIntegral$;
   0      7      1    x       J
   0      7      3    y       J


}

