Compiled from "Numeric.scala"
public final class scala.Numeric$DoubleIsFractional$ extends java.lang.Object implements scala.Numeric$DoubleIsFractional,scala.Ordering$DoubleOrdering,scala.ScalaObject
  SourceFile: "Numeric.scala"
  Scala: length = 0x
   
  InnerClass: 
   public #219= #216 of #218; //Ops=class scala/Numeric$Ops of class scala/Numeric
   public #219= #221 of #129; //Ops=class scala/Ordering$Ops of class scala/Ordering
   public abstract #222= #60 of #129; //DoubleOrdering=class scala/Ordering$DoubleOrdering of class scala/Ordering
   public #225= #224 of #121; //FractionalOps=class scala/Fractional$FractionalOps of class scala/Fractional
   public abstract #226= #72 of #218; //DoubleIsFractional=class scala/Numeric$DoubleIsFractional of class scala/Numeric
  minor version: 0
  major version: 49
  Constant pool:
const #1 = Asciz	SourceFile;
const #2 = Asciz	Numeric.scala;
const #3 = Asciz	Scala;
const #4 = Asciz	MODULE$;
const #5 = Asciz	Lscala/Numeric$DoubleIsFractional$;;
const #6 = Asciz	<clinit>;
const #7 = Asciz	()V;
const #8 = Asciz	Code;
const #9 = Asciz	scala/Numeric$DoubleIsFractional$;
const #10 = class	#9;	//  scala/Numeric$DoubleIsFractional$
const #11 = Asciz	<init>;
const #12 = NameAndType	#11:#7;//  "<init>":()V
const #13 = Method	#10.#12;	//  scala/Numeric$DoubleIsFractional$."<init>":()V
const #14 = Asciz	LineNumberTable;
const #15 = Asciz	java/lang/Object;
const #16 = class	#15;	//  java/lang/Object
const #17 = Method	#16.#12;	//  java/lang/Object."<init>":()V
const #18 = NameAndType	#4:#5;//  MODULE$:Lscala/Numeric$DoubleIsFractional$;
const #19 = Field	#10.#18;	//  scala/Numeric$DoubleIsFractional$.MODULE$:Lscala/Numeric$DoubleIsFractional$;
const #20 = Asciz	scala/PartialOrdering$class;
const #21 = class	#20;	//  scala/PartialOrdering$class
const #22 = Asciz	$init$;
const #23 = Asciz	(Lscala/PartialOrdering;)V;
const #24 = NameAndType	#22:#23;//  $init$:(Lscala/PartialOrdering;)V
const #25 = Method	#21.#24;	//  scala/PartialOrdering$class.$init$:(Lscala/PartialOrdering;)V
const #26 = Asciz	scala/Ordering$class;
const #27 = class	#26;	//  scala/Ordering$class
const #28 = Asciz	(Lscala/Ordering;)V;
const #29 = NameAndType	#22:#28;//  $init$:(Lscala/Ordering;)V
const #30 = Method	#27.#29;	//  scala/Ordering$class.$init$:(Lscala/Ordering;)V
const #31 = Asciz	scala/Numeric$class;
const #32 = class	#31;	//  scala/Numeric$class
const #33 = Asciz	(Lscala/Numeric;)V;
const #34 = NameAndType	#22:#33;//  $init$:(Lscala/Numeric;)V
const #35 = Method	#32.#34;	//  scala/Numeric$class.$init$:(Lscala/Numeric;)V
const #36 = Asciz	scala/Fractional$class;
const #37 = class	#36;	//  scala/Fractional$class
const #38 = Asciz	(Lscala/Fractional;)V;
const #39 = NameAndType	#22:#38;//  $init$:(Lscala/Fractional;)V
const #40 = Method	#37.#39;	//  scala/Fractional$class.$init$:(Lscala/Fractional;)V
const #41 = Asciz	scala/Numeric$DoubleIsFractional$class;
const #42 = class	#41;	//  scala/Numeric$DoubleIsFractional$class
const #43 = Asciz	(Lscala/Numeric$DoubleIsFractional;)V;
const #44 = NameAndType	#22:#43;//  $init$:(Lscala/Numeric$DoubleIsFractional;)V
const #45 = Method	#42.#44;	//  scala/Numeric$DoubleIsFractional$class.$init$:(Lscala/Numeric$DoubleIsFractional;)V
const #46 = Asciz	scala/Ordering$DoubleOrdering$class;
const #47 = class	#46;	//  scala/Ordering$DoubleOrdering$class
const #48 = Asciz	(Lscala/Ordering$DoubleOrdering;)V;
const #49 = NameAndType	#22:#48;//  $init$:(Lscala/Ordering$DoubleOrdering;)V
const #50 = Method	#47.#49;	//  scala/Ordering$DoubleOrdering$class.$init$:(Lscala/Ordering$DoubleOrdering;)V
const #51 = Asciz	compare;
const #52 = Asciz	(Ljava/lang/Object;Ljava/lang/Object;)I;
const #53 = Asciz	scala/runtime/BoxesRunTime;
const #54 = class	#53;	//  scala/runtime/BoxesRunTime
const #55 = Asciz	unboxToDouble;
const #56 = Asciz	(Ljava/lang/Object;)D;
const #57 = NameAndType	#55:#56;//  unboxToDouble:(Ljava/lang/Object;)D
const #58 = Method	#54.#57;	//  scala/runtime/BoxesRunTime.unboxToDouble:(Ljava/lang/Object;)D
const #59 = Asciz	scala/Ordering$DoubleOrdering;
const #60 = class	#59;	//  scala/Ordering$DoubleOrdering
const #61 = Asciz	(DD)I;
const #62 = NameAndType	#51:#61;//  compare:(DD)I
const #63 = InterfaceMethod	#60.#62;	//  scala/Ordering$DoubleOrdering.compare:(DD)I
const #64 = Asciz	this;
const #65 = Asciz	x;
const #66 = Asciz	Ljava/lang/Object;;
const #67 = Asciz	y;
const #68 = Asciz	LocalVariableTable;
const #69 = Asciz	plus;
const #70 = Asciz	(Ljava/lang/Object;Ljava/lang/Object;)Ljava/lang/Object;;
const #71 = Asciz	scala/Numeric$DoubleIsFractional;
const #72 = class	#71;	//  scala/Numeric$DoubleIsFractional
const #73 = Asciz	(DD)D;
const #74 = NameAndType	#69:#73;//  plus:(DD)D
const #75 = InterfaceMethod	#72.#74;	//  scala/Numeric$DoubleIsFractional.plus:(DD)D
const #76 = Asciz	boxToDouble;
const #77 = Asciz	(D)Ljava/lang/Double;;
const #78 = NameAndType	#76:#77;//  boxToDouble:(D)Ljava/lang/Double;
const #79 = Method	#54.#78;	//  scala/runtime/BoxesRunTime.boxToDouble:(D)Ljava/lang/Double;
const #80 = Asciz	minus;
const #81 = NameAndType	#80:#73;//  minus:(DD)D
const #82 = InterfaceMethod	#72.#81;	//  scala/Numeric$DoubleIsFractional.minus:(DD)D
const #83 = Asciz	times;
const #84 = NameAndType	#83:#73;//  times:(DD)D
const #85 = InterfaceMethod	#72.#84;	//  scala/Numeric$DoubleIsFractional.times:(DD)D
const #86 = Asciz	div;
const #87 = NameAndType	#86:#73;//  div:(DD)D
const #88 = InterfaceMethod	#72.#87;	//  scala/Numeric$DoubleIsFractional.div:(DD)D
const #89 = Asciz	negate;
const #90 = Asciz	(Ljava/lang/Object;)Ljava/lang/Object;;
const #91 = Asciz	(D)D;
const #92 = NameAndType	#89:#91;//  negate:(D)D
const #93 = InterfaceMethod	#72.#92;	//  scala/Numeric$DoubleIsFractional.negate:(D)D
const #94 = Asciz	fromInt;
const #95 = Asciz	(I)Ljava/lang/Object;;
const #96 = Asciz	(I)D;
const #97 = NameAndType	#94:#96;//  fromInt:(I)D
const #98 = InterfaceMethod	#72.#97;	//  scala/Numeric$DoubleIsFractional.fromInt:(I)D
const #99 = Asciz	I;
const #100 = Asciz	toInt;
const #101 = Asciz	(Ljava/lang/Object;)I;
const #102 = Asciz	(D)I;
const #103 = NameAndType	#100:#102;//  toInt:(D)I
const #104 = InterfaceMethod	#72.#103;	//  scala/Numeric$DoubleIsFractional.toInt:(D)I
const #105 = Asciz	toLong;
const #106 = Asciz	(Ljava/lang/Object;)J;
const #107 = Asciz	(D)J;
const #108 = NameAndType	#105:#107;//  toLong:(D)J
const #109 = InterfaceMethod	#72.#108;	//  scala/Numeric$DoubleIsFractional.toLong:(D)J
const #110 = Asciz	toFloat;
const #111 = Asciz	(Ljava/lang/Object;)F;
const #112 = Asciz	(D)F;
const #113 = NameAndType	#110:#112;//  toFloat:(D)F
const #114 = InterfaceMethod	#72.#113;	//  scala/Numeric$DoubleIsFractional.toFloat:(D)F
const #115 = Asciz	toDouble;
const #116 = NameAndType	#115:#91;//  toDouble:(D)D
const #117 = InterfaceMethod	#72.#116;	//  scala/Numeric$DoubleIsFractional.toDouble:(D)D
const #118 = Asciz	mkNumericOps;
const #119 = Asciz	(Ljava/lang/Object;)Lscala/Numeric$Ops;;
const #120 = Asciz	scala/Fractional;
const #121 = class	#120;	//  scala/Fractional
const #122 = Asciz	(Ljava/lang/Object;)Lscala/Fractional$FractionalOps;;
const #123 = NameAndType	#118:#122;//  mkNumericOps:(Ljava/lang/Object;)Lscala/Fractional$FractionalOps;
const #124 = InterfaceMethod	#121.#123;	//  scala/Fractional.mkNumericOps:(Ljava/lang/Object;)Lscala/Fractional$FractionalOps;
const #125 = Asciz	lhs;
const #126 = Asciz	reverse;
const #127 = Asciz	()Lscala/PartialOrdering;;
const #128 = Asciz	scala/Ordering;
const #129 = class	#128;	//  scala/Ordering
const #130 = Asciz	()Lscala/Ordering;;
const #131 = NameAndType	#126:#130;//  reverse:()Lscala/Ordering;
const #132 = InterfaceMethod	#129.#131;	//  scala/Ordering.reverse:()Lscala/Ordering;
const #133 = Asciz	mkOrderingOps;
const #134 = Asciz	(Ljava/lang/Object;)Lscala/Ordering$Ops;;
const #135 = Asciz	(Lscala/Ordering;Ljava/lang/Object;)Lscala/Ordering$Ops;;
const #136 = NameAndType	#133:#135;//  mkOrderingOps:(Lscala/Ordering;Ljava/lang/Object;)Lscala/Ordering$Ops;
const #137 = Method	#27.#136;	//  scala/Ordering$class.mkOrderingOps:(Lscala/Ordering;Ljava/lang/Object;)Lscala/Ordering$Ops;
const #138 = Asciz	(Lscala/Ordering;)Lscala/Ordering;;
const #139 = NameAndType	#126:#138;//  reverse:(Lscala/Ordering;)Lscala/Ordering;
const #140 = Method	#27.#139;	//  scala/Ordering$class.reverse:(Lscala/Ordering;)Lscala/Ordering;
const #141 = Asciz	min;
const #142 = Asciz	(Lscala/Ordering;Ljava/lang/Object;Ljava/lang/Object;)Ljava/lang/Object;;
const #143 = NameAndType	#141:#142;//  min:(Lscala/Ordering;Ljava/lang/Object;Ljava/lang/Object;)Ljava/lang/Object;
const #144 = Method	#27.#143;	//  scala/Ordering$class.min:(Lscala/Ordering;Ljava/lang/Object;Ljava/lang/Object;)Ljava/lang/Object;
const #145 = Asciz	max;
const #146 = NameAndType	#145:#142;//  max:(Lscala/Ordering;Ljava/lang/Object;Ljava/lang/Object;)Ljava/lang/Object;
const #147 = Method	#27.#146;	//  scala/Ordering$class.max:(Lscala/Ordering;Ljava/lang/Object;Ljava/lang/Object;)Ljava/lang/Object;
const #148 = Asciz	equiv;
const #149 = Asciz	(Ljava/lang/Object;Ljava/lang/Object;)Z;
const #150 = Asciz	(Lscala/Ordering;Ljava/lang/Object;Ljava/lang/Object;)Z;
const #151 = NameAndType	#148:#150;//  equiv:(Lscala/Ordering;Ljava/lang/Object;Ljava/lang/Object;)Z
const #152 = Method	#27.#151;	//  scala/Ordering$class.equiv:(Lscala/Ordering;Ljava/lang/Object;Ljava/lang/Object;)Z
const #153 = Asciz	gt;
const #154 = NameAndType	#153:#150;//  gt:(Lscala/Ordering;Ljava/lang/Object;Ljava/lang/Object;)Z
const #155 = Method	#27.#154;	//  scala/Ordering$class.gt:(Lscala/Ordering;Ljava/lang/Object;Ljava/lang/Object;)Z
const #156 = Asciz	lt;
const #157 = NameAndType	#156:#150;//  lt:(Lscala/Ordering;Ljava/lang/Object;Ljava/lang/Object;)Z
const #158 = Method	#27.#157;	//  scala/Ordering$class.lt:(Lscala/Ordering;Ljava/lang/Object;Ljava/lang/Object;)Z
const #159 = Asciz	gteq;
const #160 = NameAndType	#159:#150;//  gteq:(Lscala/Ordering;Ljava/lang/Object;Ljava/lang/Object;)Z
const #161 = Method	#27.#160;	//  scala/Ordering$class.gteq:(Lscala/Ordering;Ljava/lang/Object;Ljava/lang/Object;)Z
const #162 = Asciz	lteq;
const #163 = NameAndType	#162:#150;//  lteq:(Lscala/Ordering;Ljava/lang/Object;Ljava/lang/Object;)Z
const #164 = Method	#27.#163;	//  scala/Ordering$class.lteq:(Lscala/Ordering;Ljava/lang/Object;Ljava/lang/Object;)Z
const #165 = Asciz	signum;
const #166 = Asciz	(Lscala/Numeric;Ljava/lang/Object;)I;
const #167 = NameAndType	#165:#166;//  signum:(Lscala/Numeric;Ljava/lang/Object;)I
const #168 = Method	#32.#167;	//  scala/Numeric$class.signum:(Lscala/Numeric;Ljava/lang/Object;)I
const #169 = Asciz	abs;
const #170 = Asciz	(Lscala/Numeric;Ljava/lang/Object;)Ljava/lang/Object;;
const #171 = NameAndType	#169:#170;//  abs:(Lscala/Numeric;Ljava/lang/Object;)Ljava/lang/Object;
const #172 = Method	#32.#171;	//  scala/Numeric$class.abs:(Lscala/Numeric;Ljava/lang/Object;)Ljava/lang/Object;
const #173 = Asciz	one;
const #174 = Asciz	()Ljava/lang/Object;;
const #175 = Asciz	(Lscala/Numeric;)Ljava/lang/Object;;
const #176 = NameAndType	#173:#175;//  one:(Lscala/Numeric;)Ljava/lang/Object;
const #177 = Method	#32.#176;	//  scala/Numeric$class.one:(Lscala/Numeric;)Ljava/lang/Object;
const #178 = Asciz	zero;
const #179 = NameAndType	#178:#175;//  zero:(Lscala/Numeric;)Ljava/lang/Object;
const #180 = Method	#32.#179;	//  scala/Numeric$class.zero:(Lscala/Numeric;)Ljava/lang/Object;
const #181 = Asciz	(Lscala/Fractional;Ljava/lang/Object;)Lscala/Fractional$FractionalOps;;
const #182 = NameAndType	#118:#181;//  mkNumericOps:(Lscala/Fractional;Ljava/lang/Object;)Lscala/Fractional$FractionalOps;
const #183 = Method	#37.#182;	//  scala/Fractional$class.mkNumericOps:(Lscala/Fractional;Ljava/lang/Object;)Lscala/Fractional$FractionalOps;
const #184 = Asciz	(Lscala/Numeric$DoubleIsFractional;D)D;
const #185 = NameAndType	#115:#184;//  toDouble:(Lscala/Numeric$DoubleIsFractional;D)D
const #186 = Method	#42.#185;	//  scala/Numeric$DoubleIsFractional$class.toDouble:(Lscala/Numeric$DoubleIsFractional;D)D
const #187 = Asciz	D;
const #188 = Asciz	(Lscala/Numeric$DoubleIsFractional;D)F;
const #189 = NameAndType	#110:#188;//  toFloat:(Lscala/Numeric$DoubleIsFractional;D)F
const #190 = Method	#42.#189;	//  scala/Numeric$DoubleIsFractional$class.toFloat:(Lscala/Numeric$DoubleIsFractional;D)F
const #191 = Asciz	(Lscala/Numeric$DoubleIsFractional;D)J;
const #192 = NameAndType	#105:#191;//  toLong:(Lscala/Numeric$DoubleIsFractional;D)J
const #193 = Method	#42.#192;	//  scala/Numeric$DoubleIsFractional$class.toLong:(Lscala/Numeric$DoubleIsFractional;D)J
const #194 = Asciz	(Lscala/Numeric$DoubleIsFractional;D)I;
const #195 = NameAndType	#100:#194;//  toInt:(Lscala/Numeric$DoubleIsFractional;D)I
const #196 = Method	#42.#195;	//  scala/Numeric$DoubleIsFractional$class.toInt:(Lscala/Numeric$DoubleIsFractional;D)I
const #197 = Asciz	(Lscala/Numeric$DoubleIsFractional;I)D;
const #198 = NameAndType	#94:#197;//  fromInt:(Lscala/Numeric$DoubleIsFractional;I)D
const #199 = Method	#42.#198;	//  scala/Numeric$DoubleIsFractional$class.fromInt:(Lscala/Numeric$DoubleIsFractional;I)D
const #200 = NameAndType	#89:#184;//  negate:(Lscala/Numeric$DoubleIsFractional;D)D
const #201 = Method	#42.#200;	//  scala/Numeric$DoubleIsFractional$class.negate:(Lscala/Numeric$DoubleIsFractional;D)D
const #202 = Asciz	(Lscala/Numeric$DoubleIsFractional;DD)D;
const #203 = NameAndType	#86:#202;//  div:(Lscala/Numeric$DoubleIsFractional;DD)D
const #204 = Method	#42.#203;	//  scala/Numeric$DoubleIsFractional$class.div:(Lscala/Numeric$DoubleIsFractional;DD)D
const #205 = NameAndType	#83:#202;//  times:(Lscala/Numeric$DoubleIsFractional;DD)D
const #206 = Method	#42.#205;	//  scala/Numeric$DoubleIsFractional$class.times:(Lscala/Numeric$DoubleIsFractional;DD)D
const #207 = NameAndType	#80:#202;//  minus:(Lscala/Numeric$DoubleIsFractional;DD)D
const #208 = Method	#42.#207;	//  scala/Numeric$DoubleIsFractional$class.minus:(Lscala/Numeric$DoubleIsFractional;DD)D
const #209 = NameAndType	#69:#202;//  plus:(Lscala/Numeric$DoubleIsFractional;DD)D
const #210 = Method	#42.#209;	//  scala/Numeric$DoubleIsFractional$class.plus:(Lscala/Numeric$DoubleIsFractional;DD)D
const #211 = Asciz	(Lscala/Ordering$DoubleOrdering;DD)I;
const #212 = NameAndType	#51:#211;//  compare:(Lscala/Ordering$DoubleOrdering;DD)I
const #213 = Method	#47.#212;	//  scala/Ordering$DoubleOrdering$class.compare:(Lscala/Ordering$DoubleOrdering;DD)I
const #214 = Asciz	InnerClasses;
const #215 = Asciz	scala/Numeric$Ops;
const #216 = class	#215;	//  scala/Numeric$Ops
const #217 = Asciz	scala/Numeric;
const #218 = class	#217;	//  scala/Numeric
const #219 = Asciz	Ops;
const #220 = Asciz	scala/Ordering$Ops;
const #221 = class	#220;	//  scala/Ordering$Ops
const #222 = Asciz	DoubleOrdering;
const #223 = Asciz	scala/Fractional$FractionalOps;
const #224 = class	#223;	//  scala/Fractional$FractionalOps
const #225 = Asciz	FractionalOps;
const #226 = Asciz	DoubleIsFractional;
const #227 = Asciz	scala/ScalaObject;
const #228 = class	#227;	//  scala/ScalaObject

{
public static final scala.Numeric$DoubleIsFractional$ MODULE$;

public static {};
  Code:
   Stack=1, Locals=0, Args_size=0
   0:	new	#10; //class scala/Numeric$DoubleIsFractional$
   3:	invokespecial	#13; //Method "<init>":()V
   6:	return

public scala.Numeric$DoubleIsFractional$();
  Code:
   Stack=1, Locals=1, Args_size=1
   0:	aload_0
   1:	invokespecial	#17; //Method java/lang/Object."<init>":()V
   4:	aload_0
   5:	putstatic	#19; //Field MODULE$:Lscala/Numeric$DoubleIsFractional$;
   8:	aload_0
   9:	invokestatic	#25; //Method scala/PartialOrdering$class.$init$:(Lscala/PartialOrdering;)V
   12:	aload_0
   13:	invokestatic	#30; //Method scala/Ordering$class.$init$:(Lscala/Ordering;)V
   16:	aload_0
   17:	invokestatic	#35; //Method scala/Numeric$class.$init$:(Lscala/Numeric;)V
   20:	aload_0
   21:	invokestatic	#40; //Method scala/Fractional$class.$init$:(Lscala/Fractional;)V
   24:	aload_0
   25:	invokestatic	#45; //Method scala/Numeric$DoubleIsFractional$class.$init$:(Lscala/Numeric$DoubleIsFractional;)V
   28:	aload_0
   29:	invokestatic	#50; //Method scala/Ordering$DoubleOrdering$class.$init$:(Lscala/Ordering$DoubleOrdering;)V
   32:	return
  LineNumberTable: 
   line 75: 0


public int compare(java.lang.Object, java.lang.Object);
  Code:
   Stack=5, Locals=3, Args_size=3
   0:	aload_0
   1:	aload_1
   2:	invokestatic	#58; //Method scala/runtime/BoxesRunTime.unboxToDouble:(Ljava/lang/Object;)D
   5:	aload_2
   6:	invokestatic	#58; //Method scala/runtime/BoxesRunTime.unboxToDouble:(Ljava/lang/Object;)D
   9:	invokeinterface	#63,  5; //InterfaceMethod scala/Ordering$DoubleOrdering.compare:(DD)I
   14:	ireturn
  LineNumberTable: 
   line 75: 0

  LocalVariableTable: 
   Start  Length  Slot  Name   Signature
   0      15      0    this       Lscala/Numeric$DoubleIsFractional$;
   0      15      1    x       Ljava/lang/Object;
   0      15      2    y       Ljava/lang/Object;


public java.lang.Object plus(java.lang.Object, java.lang.Object);
  Code:
   Stack=5, Locals=3, Args_size=3
   0:	aload_0
   1:	aload_1
   2:	invokestatic	#58; //Method scala/runtime/BoxesRunTime.unboxToDouble:(Ljava/lang/Object;)D
   5:	aload_2
   6:	invokestatic	#58; //Method scala/runtime/BoxesRunTime.unboxToDouble:(Ljava/lang/Object;)D
   9:	invokeinterface	#75,  5; //InterfaceMethod scala/Numeric$DoubleIsFractional.plus:(DD)D
   14:	invokestatic	#79; //Method scala/runtime/BoxesRunTime.boxToDouble:(D)Ljava/lang/Double;
   17:	areturn
  LineNumberTable: 
   line 75: 0

  LocalVariableTable: 
   Start  Length  Slot  Name   Signature
   0      18      0    this       Lscala/Numeric$DoubleIsFractional$;
   0      18      1    x       Ljava/lang/Object;
   0      18      2    y       Ljava/lang/Object;


public java.lang.Object minus(java.lang.Object, java.lang.Object);
  Code:
   Stack=5, Locals=3, Args_size=3
   0:	aload_0
   1:	aload_1
   2:	invokestatic	#58; //Method scala/runtime/BoxesRunTime.unboxToDouble:(Ljava/lang/Object;)D
   5:	aload_2
   6:	invokestatic	#58; //Method scala/runtime/BoxesRunTime.unboxToDouble:(Ljava/lang/Object;)D
   9:	invokeinterface	#82,  5; //InterfaceMethod scala/Numeric$DoubleIsFractional.minus:(DD)D
   14:	invokestatic	#79; //Method scala/runtime/BoxesRunTime.boxToDouble:(D)Ljava/lang/Double;
   17:	areturn
  LineNumberTable: 
   line 75: 0

  LocalVariableTable: 
   Start  Length  Slot  Name   Signature
   0      18      0    this       Lscala/Numeric$DoubleIsFractional$;
   0      18      1    x       Ljava/lang/Object;
   0      18      2    y       Ljava/lang/Object;


public java.lang.Object times(java.lang.Object, java.lang.Object);
  Code:
   Stack=5, Locals=3, Args_size=3
   0:	aload_0
   1:	aload_1
   2:	invokestatic	#58; //Method scala/runtime/BoxesRunTime.unboxToDouble:(Ljava/lang/Object;)D
   5:	aload_2
   6:	invokestatic	#58; //Method scala/runtime/BoxesRunTime.unboxToDouble:(Ljava/lang/Object;)D
   9:	invokeinterface	#85,  5; //InterfaceMethod scala/Numeric$DoubleIsFractional.times:(DD)D
   14:	invokestatic	#79; //Method scala/runtime/BoxesRunTime.boxToDouble:(D)Ljava/lang/Double;
   17:	areturn
  LineNumberTable: 
   line 75: 0

  LocalVariableTable: 
   Start  Length  Slot  Name   Signature
   0      18      0    this       Lscala/Numeric$DoubleIsFractional$;
   0      18      1    x       Ljava/lang/Object;
   0      18      2    y       Ljava/lang/Object;


public java.lang.Object div(java.lang.Object, java.lang.Object);
  Code:
   Stack=5, Locals=3, Args_size=3
   0:	aload_0
   1:	aload_1
   2:	invokestatic	#58; //Method scala/runtime/BoxesRunTime.unboxToDouble:(Ljava/lang/Object;)D
   5:	aload_2
   6:	invokestatic	#58; //Method scala/runtime/BoxesRunTime.unboxToDouble:(Ljava/lang/Object;)D
   9:	invokeinterface	#88,  5; //InterfaceMethod scala/Numeric$DoubleIsFractional.div:(DD)D
   14:	invokestatic	#79; //Method scala/runtime/BoxesRunTime.boxToDouble:(D)Ljava/lang/Double;
   17:	areturn
  LineNumberTable: 
   line 75: 0

  LocalVariableTable: 
   Start  Length  Slot  Name   Signature
   0      18      0    this       Lscala/Numeric$DoubleIsFractional$;
   0      18      1    x       Ljava/lang/Object;
   0      18      2    y       Ljava/lang/Object;


public java.lang.Object negate(java.lang.Object);
  Code:
   Stack=3, Locals=2, Args_size=2
   0:	aload_0
   1:	aload_1
   2:	invokestatic	#58; //Method scala/runtime/BoxesRunTime.unboxToDouble:(Ljava/lang/Object;)D
   5:	invokeinterface	#93,  3; //InterfaceMethod scala/Numeric$DoubleIsFractional.negate:(D)D
   10:	invokestatic	#79; //Method scala/runtime/BoxesRunTime.boxToDouble:(D)Ljava/lang/Double;
   13:	areturn
  LineNumberTable: 
   line 75: 0

  LocalVariableTable: 
   Start  Length  Slot  Name   Signature
   0      14      0    this       Lscala/Numeric$DoubleIsFractional$;
   0      14      1    x       Ljava/lang/Object;


public java.lang.Object fromInt(int);
  Code:
   Stack=2, Locals=2, Args_size=2
   0:	aload_0
   1:	iload_1
   2:	invokeinterface	#98,  2; //InterfaceMethod scala/Numeric$DoubleIsFractional.fromInt:(I)D
   7:	invokestatic	#79; //Method scala/runtime/BoxesRunTime.boxToDouble:(D)Ljava/lang/Double;
   10:	areturn
  LineNumberTable: 
   line 75: 0

  LocalVariableTable: 
   Start  Length  Slot  Name   Signature
   0      11      0    this       Lscala/Numeric$DoubleIsFractional$;
   0      11      1    x       I


public int toInt(java.lang.Object);
  Code:
   Stack=3, Locals=2, Args_size=2
   0:	aload_0
   1:	aload_1
   2:	invokestatic	#58; //Method scala/runtime/BoxesRunTime.unboxToDouble:(Ljava/lang/Object;)D
   5:	invokeinterface	#104,  3; //InterfaceMethod scala/Numeric$DoubleIsFractional.toInt:(D)I
   10:	ireturn
  LineNumberTable: 
   line 75: 0

  LocalVariableTable: 
   Start  Length  Slot  Name   Signature
   0      11      0    this       Lscala/Numeric$DoubleIsFractional$;
   0      11      1    x       Ljava/lang/Object;


public long toLong(java.lang.Object);
  Code:
   Stack=3, Locals=2, Args_size=2
   0:	aload_0
   1:	aload_1
   2:	invokestatic	#58; //Method scala/runtime/BoxesRunTime.unboxToDouble:(Ljava/lang/Object;)D
   5:	invokeinterface	#109,  3; //InterfaceMethod scala/Numeric$DoubleIsFractional.toLong:(D)J
   10:	lreturn
  LineNumberTable: 
   line 75: 0

  LocalVariableTable: 
   Start  Length  Slot  Name   Signature
   0      11      0    this       Lscala/Numeric$DoubleIsFractional$;
   0      11      1    x       Ljava/lang/Object;


public float toFloat(java.lang.Object);
  Code:
   Stack=3, Locals=2, Args_size=2
   0:	aload_0
   1:	aload_1
   2:	invokestatic	#58; //Method scala/runtime/BoxesRunTime.unboxToDouble:(Ljava/lang/Object;)D
   5:	invokeinterface	#114,  3; //InterfaceMethod scala/Numeric$DoubleIsFractional.toFloat:(D)F
   10:	freturn
  LineNumberTable: 
   line 75: 0

  LocalVariableTable: 
   Start  Length  Slot  Name   Signature
   0      11      0    this       Lscala/Numeric$DoubleIsFractional$;
   0      11      1    x       Ljava/lang/Object;


public double toDouble(java.lang.Object);
  Code:
   Stack=3, Locals=2, Args_size=2
   0:	aload_0
   1:	aload_1
   2:	invokestatic	#58; //Method scala/runtime/BoxesRunTime.unboxToDouble:(Ljava/lang/Object;)D
   5:	invokeinterface	#117,  3; //InterfaceMethod scala/Numeric$DoubleIsFractional.toDouble:(D)D
   10:	dreturn
  LineNumberTable: 
   line 75: 0

  LocalVariableTable: 
   Start  Length  Slot  Name   Signature
   0      11      0    this       Lscala/Numeric$DoubleIsFractional$;
   0      11      1    x       Ljava/lang/Object;


public scala.Numeric$Ops mkNumericOps(java.lang.Object);
  Code:
   Stack=2, Locals=2, Args_size=2
   0:	aload_0
   1:	aload_1
   2:	invokeinterface	#124,  2; //InterfaceMethod scala/Fractional.mkNumericOps:(Ljava/lang/Object;)Lscala/Fractional$FractionalOps;
   7:	areturn
  LineNumberTable: 
   line 75: 0

  LocalVariableTable: 
   Start  Length  Slot  Name   Signature
   0      8      0    this       Lscala/Numeric$DoubleIsFractional$;
   0      8      1    lhs       Ljava/lang/Object;


public scala.PartialOrdering reverse();
  Code:
   Stack=1, Locals=1, Args_size=1
   0:	aload_0
   1:	invokeinterface	#132,  1; //InterfaceMethod scala/Ordering.reverse:()Lscala/Ordering;
   6:	areturn
  LineNumberTable: 
   line 75: 0


public scala.Ordering$Ops mkOrderingOps(java.lang.Object);
  Code:
   Stack=2, Locals=2, Args_size=2
   0:	aload_0
   1:	aload_1
   2:	invokestatic	#137; //Method scala/Ordering$class.mkOrderingOps:(Lscala/Ordering;Ljava/lang/Object;)Lscala/Ordering$Ops;
   5:	areturn
  LineNumberTable: 
   line 75: 0

  LocalVariableTable: 
   Start  Length  Slot  Name   Signature
   0      6      0    this       Lscala/Numeric$DoubleIsFractional$;
   0      6      1    lhs       Ljava/lang/Object;


public scala.Ordering reverse();
  Code:
   Stack=1, Locals=1, Args_size=1
   0:	aload_0
   1:	invokestatic	#140; //Method scala/Ordering$class.reverse:(Lscala/Ordering;)Lscala/Ordering;
   4:	areturn
  LineNumberTable: 
   line 75: 0


public java.lang.Object min(java.lang.Object, java.lang.Object);
  Code:
   Stack=3, Locals=3, Args_size=3
   0:	aload_0
   1:	aload_1
   2:	aload_2
   3:	invokestatic	#144; //Method scala/Ordering$class.min:(Lscala/Ordering;Ljava/lang/Object;Ljava/lang/Object;)Ljava/lang/Object;
   6:	areturn
  LineNumberTable: 
   line 75: 0

  LocalVariableTable: 
   Start  Length  Slot  Name   Signature
   0      7      0    this       Lscala/Numeric$DoubleIsFractional$;
   0      7      1    x       Ljava/lang/Object;
   0      7      2    y       Ljava/lang/Object;


public java.lang.Object max(java.lang.Object, java.lang.Object);
  Code:
   Stack=3, Locals=3, Args_size=3
   0:	aload_0
   1:	aload_1
   2:	aload_2
   3:	invokestatic	#147; //Method scala/Ordering$class.max:(Lscala/Ordering;Ljava/lang/Object;Ljava/lang/Object;)Ljava/lang/Object;
   6:	areturn
  LineNumberTable: 
   line 75: 0

  LocalVariableTable: 
   Start  Length  Slot  Name   Signature
   0      7      0    this       Lscala/Numeric$DoubleIsFractional$;
   0      7      1    x       Ljava/lang/Object;
   0      7      2    y       Ljava/lang/Object;


public boolean equiv(java.lang.Object, java.lang.Object);
  Code:
   Stack=3, Locals=3, Args_size=3
   0:	aload_0
   1:	aload_1
   2:	aload_2
   3:	invokestatic	#152; //Method scala/Ordering$class.equiv:(Lscala/Ordering;Ljava/lang/Object;Ljava/lang/Object;)Z
   6:	ireturn
  LineNumberTable: 
   line 75: 0

  LocalVariableTable: 
   Start  Length  Slot  Name   Signature
   0      7      0    this       Lscala/Numeric$DoubleIsFractional$;
   0      7      1    x       Ljava/lang/Object;
   0      7      2    y       Ljava/lang/Object;


public boolean gt(java.lang.Object, java.lang.Object);
  Code:
   Stack=3, Locals=3, Args_size=3
   0:	aload_0
   1:	aload_1
   2:	aload_2
   3:	invokestatic	#155; //Method scala/Ordering$class.gt:(Lscala/Ordering;Ljava/lang/Object;Ljava/lang/Object;)Z
   6:	ireturn
  LineNumberTable: 
   line 75: 0

  LocalVariableTable: 
   Start  Length  Slot  Name   Signature
   0      7      0    this       Lscala/Numeric$DoubleIsFractional$;
   0      7      1    x       Ljava/lang/Object;
   0      7      2    y       Ljava/lang/Object;


public boolean lt(java.lang.Object, java.lang.Object);
  Code:
   Stack=3, Locals=3, Args_size=3
   0:	aload_0
   1:	aload_1
   2:	aload_2
   3:	invokestatic	#158; //Method scala/Ordering$class.lt:(Lscala/Ordering;Ljava/lang/Object;Ljava/lang/Object;)Z
   6:	ireturn
  LineNumberTable: 
   line 75: 0

  LocalVariableTable: 
   Start  Length  Slot  Name   Signature
   0      7      0    this       Lscala/Numeric$DoubleIsFractional$;
   0      7      1    x       Ljava/lang/Object;
   0      7      2    y       Ljava/lang/Object;


public boolean gteq(java.lang.Object, java.lang.Object);
  Code:
   Stack=3, Locals=3, Args_size=3
   0:	aload_0
   1:	aload_1
   2:	aload_2
   3:	invokestatic	#161; //Method scala/Ordering$class.gteq:(Lscala/Ordering;Ljava/lang/Object;Ljava/lang/Object;)Z
   6:	ireturn
  LineNumberTable: 
   line 75: 0

  LocalVariableTable: 
   Start  Length  Slot  Name   Signature
   0      7      0    this       Lscala/Numeric$DoubleIsFractional$;
   0      7      1    x       Ljava/lang/Object;
   0      7      2    y       Ljava/lang/Object;


public boolean lteq(java.lang.Object, java.lang.Object);
  Code:
   Stack=3, Locals=3, Args_size=3
   0:	aload_0
   1:	aload_1
   2:	aload_2
   3:	invokestatic	#164; //Method scala/Ordering$class.lteq:(Lscala/Ordering;Ljava/lang/Object;Ljava/lang/Object;)Z
   6:	ireturn
  LineNumberTable: 
   line 75: 0

  LocalVariableTable: 
   Start  Length  Slot  Name   Signature
   0      7      0    this       Lscala/Numeric$DoubleIsFractional$;
   0      7      1    x       Ljava/lang/Object;
   0      7      2    y       Ljava/lang/Object;


public int signum(java.lang.Object);
  Code:
   Stack=2, Locals=2, Args_size=2
   0:	aload_0
   1:	aload_1
   2:	invokestatic	#168; //Method scala/Numeric$class.signum:(Lscala/Numeric;Ljava/lang/Object;)I
   5:	ireturn
  LineNumberTable: 
   line 75: 0

  LocalVariableTable: 
   Start  Length  Slot  Name   Signature
   0      6      0    this       Lscala/Numeric$DoubleIsFractional$;
   0      6      1    x       Ljava/lang/Object;


public java.lang.Object abs(java.lang.Object);
  Code:
   Stack=2, Locals=2, Args_size=2
   0:	aload_0
   1:	aload_1
   2:	invokestatic	#172; //Method scala/Numeric$class.abs:(Lscala/Numeric;Ljava/lang/Object;)Ljava/lang/Object;
   5:	areturn
  LineNumberTable: 
   line 75: 0

  LocalVariableTable: 
   Start  Length  Slot  Name   Signature
   0      6      0    this       Lscala/Numeric$DoubleIsFractional$;
   0      6      1    x       Ljava/lang/Object;


public java.lang.Object one();
  Code:
   Stack=1, Locals=1, Args_size=1
   0:	aload_0
   1:	invokestatic	#177; //Method scala/Numeric$class.one:(Lscala/Numeric;)Ljava/lang/Object;
   4:	areturn
  LineNumberTable: 
   line 75: 0


public java.lang.Object zero();
  Code:
   Stack=1, Locals=1, Args_size=1
   0:	aload_0
   1:	invokestatic	#180; //Method scala/Numeric$class.zero:(Lscala/Numeric;)Ljava/lang/Object;
   4:	areturn
  LineNumberTable: 
   line 75: 0


public scala.Fractional$FractionalOps mkNumericOps(java.lang.Object);
  Code:
   Stack=2, Locals=2, Args_size=2
   0:	aload_0
   1:	aload_1
   2:	invokestatic	#183; //Method scala/Fractional$class.mkNumericOps:(Lscala/Fractional;Ljava/lang/Object;)Lscala/Fractional$FractionalOps;
   5:	areturn
  LineNumberTable: 
   line 75: 0

  LocalVariableTable: 
   Start  Length  Slot  Name   Signature
   0      6      0    this       Lscala/Numeric$DoubleIsFractional$;
   0      6      1    lhs       Ljava/lang/Object;


public double toDouble(double);
  Code:
   Stack=3, Locals=3, Args_size=2
   0:	aload_0
   1:	dload_1
   2:	invokestatic	#186; //Method scala/Numeric$DoubleIsFractional$class.toDouble:(Lscala/Numeric$DoubleIsFractional;D)D
   5:	dreturn
  LineNumberTable: 
   line 75: 0

  LocalVariableTable: 
   Start  Length  Slot  Name   Signature
   0      6      0    this       Lscala/Numeric$DoubleIsFractional$;
   0      6      1    x       D


public float toFloat(double);
  Code:
   Stack=3, Locals=3, Args_size=2
   0:	aload_0
   1:	dload_1
   2:	invokestatic	#190; //Method scala/Numeric$DoubleIsFractional$class.toFloat:(Lscala/Numeric$DoubleIsFractional;D)F
   5:	freturn
  LineNumberTable: 
   line 75: 0

  LocalVariableTable: 
   Start  Length  Slot  Name   Signature
   0      6      0    this       Lscala/Numeric$DoubleIsFractional$;
   0      6      1    x       D


public long toLong(double);
  Code:
   Stack=3, Locals=3, Args_size=2
   0:	aload_0
   1:	dload_1
   2:	invokestatic	#193; //Method scala/Numeric$DoubleIsFractional$class.toLong:(Lscala/Numeric$DoubleIsFractional;D)J
   5:	lreturn
  LineNumberTable: 
   line 75: 0

  LocalVariableTable: 
   Start  Length  Slot  Name   Signature
   0      6      0    this       Lscala/Numeric$DoubleIsFractional$;
   0      6      1    x       D


public int toInt(double);
  Code:
   Stack=3, Locals=3, Args_size=2
   0:	aload_0
   1:	dload_1
   2:	invokestatic	#196; //Method scala/Numeric$DoubleIsFractional$class.toInt:(Lscala/Numeric$DoubleIsFractional;D)I
   5:	ireturn
  LineNumberTable: 
   line 75: 0

  LocalVariableTable: 
   Start  Length  Slot  Name   Signature
   0      6      0    this       Lscala/Numeric$DoubleIsFractional$;
   0      6      1    x       D


public double fromInt(int);
  Code:
   Stack=2, Locals=2, Args_size=2
   0:	aload_0
   1:	iload_1
   2:	invokestatic	#199; //Method scala/Numeric$DoubleIsFractional$class.fromInt:(Lscala/Numeric$DoubleIsFractional;I)D
   5:	dreturn
  LineNumberTable: 
   line 75: 0

  LocalVariableTable: 
   Start  Length  Slot  Name   Signature
   0      6      0    this       Lscala/Numeric$DoubleIsFractional$;
   0      6      1    x       I


public double negate(double);
  Code:
   Stack=3, Locals=3, Args_size=2
   0:	aload_0
   1:	dload_1
   2:	invokestatic	#201; //Method scala/Numeric$DoubleIsFractional$class.negate:(Lscala/Numeric$DoubleIsFractional;D)D
   5:	dreturn
  LineNumberTable: 
   line 75: 0

  LocalVariableTable: 
   Start  Length  Slot  Name   Signature
   0      6      0    this       Lscala/Numeric$DoubleIsFractional$;
   0      6      1    x       D


public double div(double, double);
  Code:
   Stack=5, Locals=5, Args_size=3
   0:	aload_0
   1:	dload_1
   2:	dload_3
   3:	invokestatic	#204; //Method scala/Numeric$DoubleIsFractional$class.div:(Lscala/Numeric$DoubleIsFractional;DD)D
   6:	dreturn
  LineNumberTable: 
   line 75: 0

  LocalVariableTable: 
   Start  Length  Slot  Name   Signature
   0      7      0    this       Lscala/Numeric$DoubleIsFractional$;
   0      7      1    x       D
   0      7      3    y       D


public double times(double, double);
  Code:
   Stack=5, Locals=5, Args_size=3
   0:	aload_0
   1:	dload_1
   2:	dload_3
   3:	invokestatic	#206; //Method scala/Numeric$DoubleIsFractional$class.times:(Lscala/Numeric$DoubleIsFractional;DD)D
   6:	dreturn
  LineNumberTable: 
   line 75: 0

  LocalVariableTable: 
   Start  Length  Slot  Name   Signature
   0      7      0    this       Lscala/Numeric$DoubleIsFractional$;
   0      7      1    x       D
   0      7      3    y       D


public double minus(double, double);
  Code:
   Stack=5, Locals=5, Args_size=3
   0:	aload_0
   1:	dload_1
   2:	dload_3
   3:	invokestatic	#208; //Method scala/Numeric$DoubleIsFractional$class.minus:(Lscala/Numeric$DoubleIsFractional;DD)D
   6:	dreturn
  LineNumberTable: 
   line 75: 0

  LocalVariableTable: 
   Start  Length  Slot  Name   Signature
   0      7      0    this       Lscala/Numeric$DoubleIsFractional$;
   0      7      1    x       D
   0      7      3    y       D


public double plus(double, double);
  Code:
   Stack=5, Locals=5, Args_size=3
   0:	aload_0
   1:	dload_1
   2:	dload_3
   3:	invokestatic	#210; //Method scala/Numeric$DoubleIsFractional$class.plus:(Lscala/Numeric$DoubleIsFractional;DD)D
   6:	dreturn
  LineNumberTable: 
   line 75: 0

  LocalVariableTable: 
   Start  Length  Slot  Name   Signature
   0      7      0    this       Lscala/Numeric$DoubleIsFractional$;
   0      7      1    x       D
   0      7      3    y       D


public int compare(double, double);
  Code:
   Stack=5, Locals=5, Args_size=3
   0:	aload_0
   1:	dload_1
   2:	dload_3
   3:	invokestatic	#213; //Method scala/Ordering$DoubleOrdering$class.compare:(Lscala/Ordering$DoubleOrdering;DD)I
   6:	ireturn
  LineNumberTable: 
   line 75: 0

  LocalVariableTable: 
   Start  Length  Slot  Name   Signature
   0      7      0    this       Lscala/Numeric$DoubleIsFractional$;
   0      7      1    x       D
   0      7      3    y       D


}

