Compiled from "Option.scala"
public final class scala.Option$WithFilter$$anonfun$withFilter$1 extends scala.runtime.AbstractFunction1 implements java.io.Serializable
  SourceFile: "Option.scala"
  Scala: length = 0x
   
  InnerClass: 
   public WithFilter=class scala/Option$WithFilter of class scala/Option
   public final $anonfun$withFilter$1=class scala/Option$WithFilter$$anonfun$withFilter$1 of class scala/Option$WithFilter
  minor version: 0
  major version: 49
  Constant pool:
Asciz	SourceFile;
Asciz	Option.scala;
Asciz	<clinit>;
Asciz	()V;
Asciz	Code;
Asciz	serialVersionUID;
Asciz	J;
Asciz	scala/Option$WithFilter$$anonfun$withFilter$1;
class	scala/Option$WithFilter$$anonfun$withFilter$1
NameAndType	serialVersionUID:J
Field	scala/Option$WithFilter$$anonfun$withFilter$1.serialVersionUID:J
Asciz	q$1;
Asciz	Lscala/Function1;;
Asciz	$outer;
Asciz	Lscala/Option$WithFilter;;
Asciz	apply;
Asciz	(Ljava/lang/Object;)Z;
Asciz	LineNumberTable;
NameAndType	$outer:Lscala/Option$WithFilter;
Field	scala/Option$WithFilter$$anonfun$withFilter$1.$outer:Lscala/Option$WithFilter;
Asciz	scala/Option$WithFilter;
class	scala/Option$WithFilter
Asciz	scala$Option$WithFilter$$p;
NameAndType	scala$Option$WithFilter$$p:Lscala/Function1;
Field	scala/Option$WithFilter.scala$Option$WithFilter$$p:Lscala/Function1;
Asciz	scala/Function1;
class	scala/Function1
Asciz	(Ljava/lang/Object;)Ljava/lang/Object;;
NameAndType	apply:(Ljava/lang/Object;)Ljava/lang/Object;
InterfaceMethod	scala/Function1.apply:(Ljava/lang/Object;)Ljava/lang/Object;
Asciz	scala/runtime/BoxesRunTime;
class	scala/runtime/BoxesRunTime
Asciz	unboxToBoolean;
NameAndType	unboxToBoolean:(Ljava/lang/Object;)Z
Method	scala/runtime/BoxesRunTime.unboxToBoolean:(Ljava/lang/Object;)Z
NameAndType	q$1:Lscala/Function1;
Field	scala/Option$WithFilter$$anonfun$withFilter$1.q$1:Lscala/Function1;
Asciz	this;
Asciz	Lscala/Option$WithFilter$$anonfun$withFilter$1;;
Asciz	x;
Asciz	Ljava/lang/Object;;
Asciz	LocalVariableTable;
Asciz	(TA;)Z;
Asciz	Signature;
NameAndType	apply:(Ljava/lang/Object;)Z
Method	scala/Option$WithFilter$$anonfun$withFilter$1.apply:(Ljava/lang/Object;)Z
Asciz	boxToBoolean;
Asciz	(Z)Ljava/lang/Boolean;;
NameAndType	boxToBoolean:(Z)Ljava/lang/Boolean;
Method	scala/runtime/BoxesRunTime.boxToBoolean:(Z)Ljava/lang/Boolean;
Asciz	v1;
Asciz	<init>;
Asciz	(Lscala/Option$WithFilter;Lscala/Function1;)V;
Asciz	java/lang/NullPointerException;
class	java/lang/NullPointerException
NameAndType	"<init>":()V
Method	java/lang/NullPointerException."<init>":()V
Asciz	scala/runtime/AbstractFunction1;
class	scala/runtime/AbstractFunction1
Method	scala/runtime/AbstractFunction1."<init>":()V
Asciz	(Lscala/Option<TA;>.WithFilter;)V;
Asciz	Scala;
Asciz	InnerClasses;
Asciz	scala/Option;
class	scala/Option
Asciz	WithFilter;
Asciz	$anonfun$withFilter$1;
Asciz	java/io/Serializable;
class	java/io/Serializable

{
public static final long serialVersionUID;
  Signature: J

private final scala.Function1 q$1;
  Signature: Lscala/Function1;

private final scala.Option$WithFilter $outer;
  Signature: Lscala/Option$WithFilter;

public static {};
  Signature: ()V
  Code:
   Stack=2, Locals=0, Args_size=0
	lconst_0
	putstatic	Field serialVersionUID:J
	return
  Labels:

public final boolean apply(java.lang.Object);
  Signature: (Ljava/lang/Object;)Z
  Code:
   Stack=2, Locals=2, Args_size=2
	aload_0
	getfield	Field $outer:Lscala/Option$WithFilter;
	getfield	Field scala/Option$WithFilter.scala$Option$WithFilter$$p:Lscala/Function1;
	aload_1
	invokeinterface	InterfaceMethod scala/Function1.apply:(Ljava/lang/Object;)Ljava/lang/Object;
	invokestatic	Method scala/runtime/BoxesRunTime.unboxToBoolean:(Ljava/lang/Object;)Z
	ifeq	l1 // iconst_0
	aload_0
	getfield	Field q$1:Lscala/Function1;
	aload_1
	invokeinterface	InterfaceMethod scala/Function1.apply:(Ljava/lang/Object;)Ljava/lang/Object;
	invokestatic	Method scala/runtime/BoxesRunTime.unboxToBoolean:(Ljava/lang/Object;)Z
	ifeq	l1 // iconst_0
	iconst_1
	goto	l2 // ireturn
l1	iconst_0
l2	ireturn
  Labels:
   	l1 = 39 // iconst_0
   	l2 = 40 // ireturn
  LocalVariableTable: 
   Start  Length  Slot  Name   Signature
   0      41      0    this       Lscala/Option$WithFilter$$anonfun$withFilter$1;
   0      41      1    x       Ljava/lang/Object;

  Signature: length = 0x2
   00 2B 

public final java.lang.Object apply(java.lang.Object);
  Signature: (Ljava/lang/Object;)Ljava/lang/Object;
  Code:
   Stack=2, Locals=2, Args_size=2
	aload_0
	aload_1
	invokevirtual	Method apply:(Ljava/lang/Object;)Z
	invokestatic	Method scala/runtime/BoxesRunTime.boxToBoolean:(Z)Ljava/lang/Boolean;
	areturn
  Labels:
  LocalVariableTable: 
   Start  Length  Slot  Name   Signature
   0      9      0    this       Lscala/Option$WithFilter$$anonfun$withFilter$1;
   0      9      1    v1       Ljava/lang/Object;


public scala.Option$WithFilter$$anonfun$withFilter$1(scala.Option$WithFilter, scala.Function1);
  Signature: (Lscala/Option$WithFilter;Lscala/Function1;)V
  Code:
   Stack=2, Locals=3, Args_size=3
	aload_1
	ifnonnull	l1 // aload_0
	new	class java/lang/NullPointerException
	dup
	invokespecial	Method java/lang/NullPointerException."<init>":()V
	athrow
l1	aload_0
	aload_1
	putfield	Field $outer:Lscala/Option$WithFilter;
	aload_0
	aload_2
	putfield	Field q$1:Lscala/Function1;
	aload_0
	invokespecial	Method scala/runtime/AbstractFunction1."<init>":()V
	return
  Labels:
   	l1 = 12 // aload_0
  LocalVariableTable: 
   Start  Length  Slot  Name   Signature
   0      27      0    this       Lscala/Option$WithFilter$$anonfun$withFilter$1;
   0      27      1    $outer       Lscala/Option$WithFilter;

  Signature: length = 0x2
   00 3D 

}

