Compiled from "Option.scala"
public class scala.Option$NullableOption extends java.lang.Object implements scala.ScalaObject
  SourceFile: "Option.scala"
  Signature: length = 0x2
   00 24 
  Scala: length = 0x
   
  InnerClass: 
   public #39= #12 of #27; //NullableOption=class scala/Option$NullableOption of class scala/Option
  minor version: 0
  major version: 49
  Constant pool:
const #1 = Asciz	SourceFile;
const #2 = Asciz	Option.scala;
const #3 = Asciz	x;
const #4 = Asciz	Lscala/Option;;
const #5 = Asciz	Lscala/Option<TA;>;;
const #6 = Asciz	Signature;
const #7 = Asciz	<init>;
const #8 = Asciz	(Lscala/Option;)V;
const #9 = Asciz	Code;
const #10 = Asciz	LineNumberTable;
const #11 = Asciz	scala/Option$NullableOption;
const #12 = class	#11;	//  scala/Option$NullableOption
const #13 = NameAndType	#3:#4;//  x:Lscala/Option;
const #14 = Field	#12.#13;	//  scala/Option$NullableOption.x:Lscala/Option;
const #15 = Asciz	java/lang/Object;
const #16 = class	#15;	//  java/lang/Object
const #17 = Asciz	()V;
const #18 = NameAndType	#7:#17;//  "<init>":()V
const #19 = Method	#16.#18;	//  java/lang/Object."<init>":()V
const #20 = Asciz	this;
const #21 = Asciz	Lscala/Option$NullableOption;;
const #22 = Asciz	LocalVariableTable;
const #23 = Asciz	(Lscala/Option<TA;>;)V;
const #24 = Asciz	orNull;
const #25 = Asciz	()Ljava/lang/Object;;
const #26 = Asciz	scala/Option;
const #27 = class	#26;	//  scala/Option
const #28 = Asciz	isEmpty;
const #29 = Asciz	()Z;
const #30 = NameAndType	#28:#29;//  isEmpty:()Z
const #31 = Method	#27.#30;	//  scala/Option.isEmpty:()Z
const #32 = Asciz	get;
const #33 = NameAndType	#32:#25;//  get:()Ljava/lang/Object;
const #34 = Method	#27.#33;	//  scala/Option.get:()Ljava/lang/Object;
const #35 = Asciz	()TA;;
const #36 = Asciz	<A:Ljava/lang/Object;>Ljava/lang/Object;Lscala/ScalaObject;;
const #37 = Asciz	Scala;
const #38 = Asciz	InnerClasses;
const #39 = Asciz	NullableOption;
const #40 = Asciz	scala/ScalaObject;
const #41 = class	#40;	//  scala/ScalaObject

{
public scala.Option$NullableOption(scala.Option);
  Code:
   Stack=2, Locals=2, Args_size=2
   0:	aload_0
   1:	aload_1
   2:	putfield	#14; //Field x:Lscala/Option;
   5:	aload_0
   6:	invokespecial	#19; //Method java/lang/Object."<init>":()V
   9:	return
  LineNumberTable: 
   line 32: 0

  LocalVariableTable: 
   Start  Length  Slot  Name   Signature
   0      10      0    this       Lscala/Option$NullableOption;
   0      10      1    x       Lscala/Option;

  Signature: length = 0x2
   00 17 

public java.lang.Object orNull();
  Code:
   Stack=1, Locals=1, Args_size=1
   0:	aload_0
   1:	getfield	#14; //Field x:Lscala/Option;
   4:	invokevirtual	#31; //Method scala/Option.isEmpty:()Z
   7:	ifeq	16
   10:	aconst_null
   11:	pop
   12:	aconst_null
   13:	goto	23
   16:	aload_0
   17:	getfield	#14; //Field x:Lscala/Option;
   20:	invokevirtual	#34; //Method scala/Option.get:()Ljava/lang/Object;
   23:	areturn
  LineNumberTable: 
   line 38: 0

  Signature: length = 0x2
   00 23 

}

