Compiled from "Option.scala"
public final class scala.Option$ extends java.lang.Object implements scala.ScalaObject
  SourceFile: "Option.scala"
  Scala: length = 0x
   
  InnerClass: 
   public WithFilter=class scala/Option$WithFilter of class scala/Option
   public final $anonfun$orNull$1=class scala/Option$$anonfun$orNull$1 of class scala/Option
  minor version: 0
  major version: 49
  Constant pool:
Asciz	SourceFile;
Asciz	Option.scala;
Asciz	Scala;
Asciz	MODULE$;
Asciz	Lscala/Option$;;
Asciz	<clinit>;
Asciz	()V;
Asciz	Code;
Asciz	scala/Option$;
class	scala/Option$
Asciz	<init>;
NameAndType	"<init>":()V
Method	scala/Option$."<init>":()V
Asciz	option2Iterable;
Asciz	(Lscala/Option;)Lscala/collection/Iterable;;
Asciz	LineNumberTable;
Asciz	scala/Option;
class	scala/Option
Asciz	toList;
Asciz	()Lscala/collection/immutable/List;;
NameAndType	toList:()Lscala/collection/immutable/List;
Method	scala/Option.toList:()Lscala/collection/immutable/List;
Asciz	this;
Asciz	xo;
Asciz	Lscala/Option;;
Asciz	LocalVariableTable;
Asciz	<A:Ljava/lang/Object;>(Lscala/Option<TA;>;)Lscala/collection/Iterable<TA;>;;
Asciz	Signature;
Asciz	apply;
Asciz	(Ljava/lang/Object;)Lscala/Option;;
Asciz	java/lang/Object;
class	java/lang/Object
Asciz	equals;
Asciz	(Ljava/lang/Object;)Z;
NameAndType	equals:(Ljava/lang/Object;)Z
Method	java/lang/Object.equals:(Ljava/lang/Object;)Z
Asciz	scala/None$;
class	scala/None$
Asciz	Lscala/None$;;
NameAndType	MODULE$:Lscala/None$;
Field	scala/None$.MODULE$:Lscala/None$;
Asciz	scala/Some;
class	scala/Some
Asciz	(Ljava/lang/Object;)V;
NameAndType	"<init>":(Ljava/lang/Object;)V
Method	scala/Some."<init>":(Ljava/lang/Object;)V
Asciz	x;
Asciz	Ljava/lang/Object;;
Asciz	<A:Ljava/lang/Object;>(TA;)Lscala/Option<TA;>;;
Method	java/lang/Object."<init>":()V
NameAndType	MODULE$:Lscala/Option$;
Field	scala/Option$.MODULE$:Lscala/Option$;
Asciz	InnerClasses;
Asciz	scala/Option$WithFilter;
class	scala/Option$WithFilter
Asciz	WithFilter;
Asciz	scala/Option$$anonfun$orNull$1;
class	scala/Option$$anonfun$orNull$1
Asciz	$anonfun$orNull$1;
Asciz	scala/ScalaObject;
class	scala/ScalaObject

{
public static final scala.Option$ MODULE$;
  Signature: Lscala/Option$;

public static {};
  Signature: ()V
  Code:
   Stack=1, Locals=0, Args_size=0
	new	class scala/Option$
	invokespecial	Method "<init>":()V
	return
  Labels:

public scala.collection.Iterable option2Iterable(scala.Option);
  Signature: (Lscala/Option;)Lscala/collection/Iterable;
  Code:
   Stack=1, Locals=2, Args_size=2
	aload_1
	invokevirtual	Method scala/Option.toList:()Lscala/collection/immutable/List;
	areturn
  Labels:
  LocalVariableTable: 
   Start  Length  Slot  Name   Signature
   0      5      0    this       Lscala/Option$;
   0      5      1    xo       Lscala/Option;

  Signature: length = 0x2
   00 1B 

public scala.Option apply(java.lang.Object);
  Signature: (Ljava/lang/Object;)Lscala/Option;
  Code:
   Stack=3, Locals=2, Args_size=2
	aload_1
	dup
	pop
	ifnull	l1 // getstatic
	aload_1
	aconst_null
	invokevirtual	Method java/lang/Object.equals:(Ljava/lang/Object;)Z
	ifeq	l2 // new
l1	getstatic	Field scala/None$.MODULE$:Lscala/None$;
	goto	l3 // areturn
l2	new	class scala/Some
	dup
	aload_1
	invokespecial	Method scala/Some."<init>":(Ljava/lang/Object;)V
l3	areturn
  Labels:
   	l1 = 14 // getstatic
   	l2 = 20 // new
   	l3 = 28 // areturn
  LocalVariableTable: 
   Start  Length  Slot  Name   Signature
   0      29      0    this       Lscala/Option$;
   0      29      1    x       Ljava/lang/Object;

  Signature: length = 0x2
   00 31 

private scala.Option$();
  Signature: ()V
  Code:
   Stack=1, Locals=1, Args_size=1
	aload_0
	invokespecial	Method java/lang/Object."<init>":()V
	aload_0
	putstatic	Field MODULE$:Lscala/Option$;
	return
  Labels:

}

