Compiled from "Ordering.scala"
public final class scala.Ordering$$anon$12 extends java.lang.Object implements scala.Ordering
  SourceFile: "Ordering.scala"
  Signature: length = 0x2
   00 FFFFFF96 
  Scala: length = 0x
   
  InnerClass: 
   public #155= #154 of #69; //Ops=class scala/Ordering$Ops of class scala/Ordering
   public final #156= #18 of #69; //$anon$12=class scala/Ordering$$anon$12 of class scala/Ordering
  minor version: 0
  major version: 49
  Constant pool:
const #1 = Asciz	SourceFile;
const #2 = Asciz	Ordering.scala;
const #3 = Asciz	ord9$1;
const #4 = Asciz	Lscala/Ordering;;
const #5 = Asciz	ord8$2;
const #6 = Asciz	ord7$3;
const #7 = Asciz	ord6$4;
const #8 = Asciz	ord5$5;
const #9 = Asciz	ord4$6;
const #10 = Asciz	ord3$7;
const #11 = Asciz	ord2$8;
const #12 = Asciz	ord1$8;
const #13 = Asciz	<init>;
const #14 = Asciz	(Lscala/Ordering;Lscala/Ordering;Lscala/Ordering;Lscala/Ordering;Lscala/Ordering;Lscala/Ordering;Lscala/Ordering;Lscala/Ordering;Lscala/Ordering;)V;
const #15 = Asciz	Code;
const #16 = Asciz	LineNumberTable;
const #17 = Asciz	scala/Ordering$$anon$12;
const #18 = class	#17;	//  scala/Ordering$$anon$12
const #19 = NameAndType	#12:#4;//  ord1$8:Lscala/Ordering;
const #20 = Field	#18.#19;	//  scala/Ordering$$anon$12.ord1$8:Lscala/Ordering;
const #21 = NameAndType	#11:#4;//  ord2$8:Lscala/Ordering;
const #22 = Field	#18.#21;	//  scala/Ordering$$anon$12.ord2$8:Lscala/Ordering;
const #23 = NameAndType	#10:#4;//  ord3$7:Lscala/Ordering;
const #24 = Field	#18.#23;	//  scala/Ordering$$anon$12.ord3$7:Lscala/Ordering;
const #25 = NameAndType	#9:#4;//  ord4$6:Lscala/Ordering;
const #26 = Field	#18.#25;	//  scala/Ordering$$anon$12.ord4$6:Lscala/Ordering;
const #27 = NameAndType	#8:#4;//  ord5$5:Lscala/Ordering;
const #28 = Field	#18.#27;	//  scala/Ordering$$anon$12.ord5$5:Lscala/Ordering;
const #29 = NameAndType	#7:#4;//  ord6$4:Lscala/Ordering;
const #30 = Field	#18.#29;	//  scala/Ordering$$anon$12.ord6$4:Lscala/Ordering;
const #31 = NameAndType	#6:#4;//  ord7$3:Lscala/Ordering;
const #32 = Field	#18.#31;	//  scala/Ordering$$anon$12.ord7$3:Lscala/Ordering;
const #33 = NameAndType	#5:#4;//  ord8$2:Lscala/Ordering;
const #34 = Field	#18.#33;	//  scala/Ordering$$anon$12.ord8$2:Lscala/Ordering;
const #35 = NameAndType	#3:#4;//  ord9$1:Lscala/Ordering;
const #36 = Field	#18.#35;	//  scala/Ordering$$anon$12.ord9$1:Lscala/Ordering;
const #37 = Asciz	java/lang/Object;
const #38 = class	#37;	//  java/lang/Object
const #39 = Asciz	()V;
const #40 = NameAndType	#13:#39;//  "<init>":()V
const #41 = Method	#38.#40;	//  java/lang/Object."<init>":()V
const #42 = Asciz	scala/PartialOrdering$class;
const #43 = class	#42;	//  scala/PartialOrdering$class
const #44 = Asciz	$init$;
const #45 = Asciz	(Lscala/PartialOrdering;)V;
const #46 = NameAndType	#44:#45;//  $init$:(Lscala/PartialOrdering;)V
const #47 = Method	#43.#46;	//  scala/PartialOrdering$class.$init$:(Lscala/PartialOrdering;)V
const #48 = Asciz	scala/Ordering$class;
const #49 = class	#48;	//  scala/Ordering$class
const #50 = Asciz	(Lscala/Ordering;)V;
const #51 = NameAndType	#44:#50;//  $init$:(Lscala/Ordering;)V
const #52 = Method	#49.#51;	//  scala/Ordering$class.$init$:(Lscala/Ordering;)V
const #53 = Asciz	compare;
const #54 = Asciz	(Ljava/lang/Object;Ljava/lang/Object;)I;
const #55 = Asciz	scala/Tuple9;
const #56 = class	#55;	//  scala/Tuple9
const #57 = Asciz	(Lscala/Tuple9;Lscala/Tuple9;)I;
const #58 = NameAndType	#53:#57;//  compare:(Lscala/Tuple9;Lscala/Tuple9;)I
const #59 = Method	#18.#58;	//  scala/Ordering$$anon$12.compare:(Lscala/Tuple9;Lscala/Tuple9;)I
const #60 = Asciz	this;
const #61 = Asciz	Lscala/Ordering$$anon$12;;
const #62 = Asciz	x;
const #63 = Asciz	Ljava/lang/Object;;
const #64 = Asciz	y;
const #65 = Asciz	LocalVariableTable;
const #66 = Asciz	reverse;
const #67 = Asciz	()Lscala/PartialOrdering;;
const #68 = Asciz	scala/Ordering;
const #69 = class	#68;	//  scala/Ordering
const #70 = Asciz	()Lscala/Ordering;;
const #71 = NameAndType	#66:#70;//  reverse:()Lscala/Ordering;
const #72 = InterfaceMethod	#69.#71;	//  scala/Ordering.reverse:()Lscala/Ordering;
const #73 = Asciz	_1;
const #74 = Asciz	()Ljava/lang/Object;;
const #75 = NameAndType	#73:#74;//  _1:()Ljava/lang/Object;
const #76 = Method	#56.#75;	//  scala/Tuple9._1:()Ljava/lang/Object;
const #77 = NameAndType	#53:#54;//  compare:(Ljava/lang/Object;Ljava/lang/Object;)I
const #78 = InterfaceMethod	#69.#77;	//  scala/Ordering.compare:(Ljava/lang/Object;Ljava/lang/Object;)I
const #79 = Asciz	_2;
const #80 = NameAndType	#79:#74;//  _2:()Ljava/lang/Object;
const #81 = Method	#56.#80;	//  scala/Tuple9._2:()Ljava/lang/Object;
const #82 = Asciz	_3;
const #83 = NameAndType	#82:#74;//  _3:()Ljava/lang/Object;
const #84 = Method	#56.#83;	//  scala/Tuple9._3:()Ljava/lang/Object;
const #85 = Asciz	_4;
const #86 = NameAndType	#85:#74;//  _4:()Ljava/lang/Object;
const #87 = Method	#56.#86;	//  scala/Tuple9._4:()Ljava/lang/Object;
const #88 = Asciz	_5;
const #89 = NameAndType	#88:#74;//  _5:()Ljava/lang/Object;
const #90 = Method	#56.#89;	//  scala/Tuple9._5:()Ljava/lang/Object;
const #91 = Asciz	_6;
const #92 = NameAndType	#91:#74;//  _6:()Ljava/lang/Object;
const #93 = Method	#56.#92;	//  scala/Tuple9._6:()Ljava/lang/Object;
const #94 = Asciz	_7;
const #95 = NameAndType	#94:#74;//  _7:()Ljava/lang/Object;
const #96 = Method	#56.#95;	//  scala/Tuple9._7:()Ljava/lang/Object;
const #97 = Asciz	_8;
const #98 = NameAndType	#97:#74;//  _8:()Ljava/lang/Object;
const #99 = Method	#56.#98;	//  scala/Tuple9._8:()Ljava/lang/Object;
const #100 = Asciz	_9;
const #101 = NameAndType	#100:#74;//  _9:()Ljava/lang/Object;
const #102 = Method	#56.#101;	//  scala/Tuple9._9:()Ljava/lang/Object;
const #103 = Asciz	Lscala/Tuple9;;
const #104 = Asciz	compare1;
const #105 = Asciz	I;
const #106 = Asciz	compare2;
const #107 = Asciz	compare3;
const #108 = Asciz	compare4;
const #109 = Asciz	compare5;
const #110 = Asciz	compare6;
const #111 = Asciz	compare7;
const #112 = Asciz	compare8;
const #113 = Asciz	compare9;
const #114 = Asciz	(Lscala/Tuple9<TT1;TT2;TT3;TT4;TT5;TT6;TT7;TT8;TT9;>;Lscala/Tuple9<TT1;TT2;TT3;TT4;TT5;TT6;TT7;TT8;TT9;>;)I;
const #115 = Asciz	Signature;
const #116 = Asciz	mkOrderingOps;
const #117 = Asciz	(Ljava/lang/Object;)Lscala/Ordering$Ops;;
const #118 = Asciz	(Lscala/Ordering;Ljava/lang/Object;)Lscala/Ordering$Ops;;
const #119 = NameAndType	#116:#118;//  mkOrderingOps:(Lscala/Ordering;Ljava/lang/Object;)Lscala/Ordering$Ops;
const #120 = Method	#49.#119;	//  scala/Ordering$class.mkOrderingOps:(Lscala/Ordering;Ljava/lang/Object;)Lscala/Ordering$Ops;
const #121 = Asciz	lhs;
const #122 = Asciz	(Lscala/Ordering;)Lscala/Ordering;;
const #123 = NameAndType	#66:#122;//  reverse:(Lscala/Ordering;)Lscala/Ordering;
const #124 = Method	#49.#123;	//  scala/Ordering$class.reverse:(Lscala/Ordering;)Lscala/Ordering;
const #125 = Asciz	min;
const #126 = Asciz	(Ljava/lang/Object;Ljava/lang/Object;)Ljava/lang/Object;;
const #127 = Asciz	(Lscala/Ordering;Ljava/lang/Object;Ljava/lang/Object;)Ljava/lang/Object;;
const #128 = NameAndType	#125:#127;//  min:(Lscala/Ordering;Ljava/lang/Object;Ljava/lang/Object;)Ljava/lang/Object;
const #129 = Method	#49.#128;	//  scala/Ordering$class.min:(Lscala/Ordering;Ljava/lang/Object;Ljava/lang/Object;)Ljava/lang/Object;
const #130 = Asciz	max;
const #131 = NameAndType	#130:#127;//  max:(Lscala/Ordering;Ljava/lang/Object;Ljava/lang/Object;)Ljava/lang/Object;
const #132 = Method	#49.#131;	//  scala/Ordering$class.max:(Lscala/Ordering;Ljava/lang/Object;Ljava/lang/Object;)Ljava/lang/Object;
const #133 = Asciz	equiv;
const #134 = Asciz	(Ljava/lang/Object;Ljava/lang/Object;)Z;
const #135 = Asciz	(Lscala/Ordering;Ljava/lang/Object;Ljava/lang/Object;)Z;
const #136 = NameAndType	#133:#135;//  equiv:(Lscala/Ordering;Ljava/lang/Object;Ljava/lang/Object;)Z
const #137 = Method	#49.#136;	//  scala/Ordering$class.equiv:(Lscala/Ordering;Ljava/lang/Object;Ljava/lang/Object;)Z
const #138 = Asciz	gt;
const #139 = NameAndType	#138:#135;//  gt:(Lscala/Ordering;Ljava/lang/Object;Ljava/lang/Object;)Z
const #140 = Method	#49.#139;	//  scala/Ordering$class.gt:(Lscala/Ordering;Ljava/lang/Object;Ljava/lang/Object;)Z
const #141 = Asciz	lt;
const #142 = NameAndType	#141:#135;//  lt:(Lscala/Ordering;Ljava/lang/Object;Ljava/lang/Object;)Z
const #143 = Method	#49.#142;	//  scala/Ordering$class.lt:(Lscala/Ordering;Ljava/lang/Object;Ljava/lang/Object;)Z
const #144 = Asciz	gteq;
const #145 = NameAndType	#144:#135;//  gteq:(Lscala/Ordering;Ljava/lang/Object;Ljava/lang/Object;)Z
const #146 = Method	#49.#145;	//  scala/Ordering$class.gteq:(Lscala/Ordering;Ljava/lang/Object;Ljava/lang/Object;)Z
const #147 = Asciz	lteq;
const #148 = NameAndType	#147:#135;//  lteq:(Lscala/Ordering;Ljava/lang/Object;Ljava/lang/Object;)Z
const #149 = Method	#49.#148;	//  scala/Ordering$class.lteq:(Lscala/Ordering;Ljava/lang/Object;Ljava/lang/Object;)Z
const #150 = Asciz	Ljava/lang/Object;Lscala/Ordering<Lscala/Tuple9<TT1;TT2;TT3;TT4;TT5;TT6;TT7;TT8;TT9;>;>;;
const #151 = Asciz	Scala;
const #152 = Asciz	InnerClasses;
const #153 = Asciz	scala/Ordering$Ops;
const #154 = class	#153;	//  scala/Ordering$Ops
const #155 = Asciz	Ops;
const #156 = Asciz	$anon$12;

{
public scala.Ordering$$anon$12(scala.Ordering, scala.Ordering, scala.Ordering, scala.Ordering, scala.Ordering, scala.Ordering, scala.Ordering, scala.Ordering, scala.Ordering);
  Code:
   Stack=2, Locals=10, Args_size=10
   0:	aload_0
   1:	aload_1
   2:	putfield	#20; //Field ord1$8:Lscala/Ordering;
   5:	aload_0
   6:	aload_2
   7:	putfield	#22; //Field ord2$8:Lscala/Ordering;
   10:	aload_0
   11:	aload_3
   12:	putfield	#24; //Field ord3$7:Lscala/Ordering;
   15:	aload_0
   16:	aload	4
   18:	putfield	#26; //Field ord4$6:Lscala/Ordering;
   21:	aload_0
   22:	aload	5
   24:	putfield	#28; //Field ord5$5:Lscala/Ordering;
   27:	aload_0
   28:	aload	6
   30:	putfield	#30; //Field ord6$4:Lscala/Ordering;
   33:	aload_0
   34:	aload	7
   36:	putfield	#32; //Field ord7$3:Lscala/Ordering;
   39:	aload_0
   40:	aload	8
   42:	putfield	#34; //Field ord8$2:Lscala/Ordering;
   45:	aload_0
   46:	aload	9
   48:	putfield	#36; //Field ord9$1:Lscala/Ordering;
   51:	aload_0
   52:	invokespecial	#41; //Method java/lang/Object."<init>":()V
   55:	aload_0
   56:	invokestatic	#47; //Method scala/PartialOrdering$class.$init$:(Lscala/PartialOrdering;)V
   59:	aload_0
   60:	invokestatic	#52; //Method scala/Ordering$class.$init$:(Lscala/Ordering;)V
   63:	return
  LineNumberTable: 
   line 330: 0


public int compare(java.lang.Object, java.lang.Object);
  Code:
   Stack=3, Locals=3, Args_size=3
   0:	aload_0
   1:	aload_1
   2:	checkcast	#56; //class scala/Tuple9
   5:	aload_2
   6:	checkcast	#56; //class scala/Tuple9
   9:	invokevirtual	#59; //Method compare:(Lscala/Tuple9;Lscala/Tuple9;)I
   12:	ireturn
  LineNumberTable: 
   line 330: 0

  LocalVariableTable: 
   Start  Length  Slot  Name   Signature
   0      13      0    this       Lscala/Ordering$$anon$12;
   0      13      1    x       Ljava/lang/Object;
   0      13      2    y       Ljava/lang/Object;


public scala.PartialOrdering reverse();
  Code:
   Stack=1, Locals=1, Args_size=1
   0:	aload_0
   1:	invokeinterface	#72,  1; //InterfaceMethod scala/Ordering.reverse:()Lscala/Ordering;
   6:	areturn
  LineNumberTable: 
   line 330: 0


public int compare(scala.Tuple9, scala.Tuple9);
  Code:
   Stack=3, Locals=12, Args_size=3
   0:	aload_0
   1:	getfield	#20; //Field ord1$8:Lscala/Ordering;
   4:	aload_1
   5:	invokevirtual	#76; //Method scala/Tuple9._1:()Ljava/lang/Object;
   8:	aload_2
   9:	invokevirtual	#76; //Method scala/Tuple9._1:()Ljava/lang/Object;
   12:	invokeinterface	#78,  3; //InterfaceMethod scala/Ordering.compare:(Ljava/lang/Object;Ljava/lang/Object;)I
   17:	istore_3
   18:	iload_3
   19:	iconst_0
   20:	if_icmpeq	25
   23:	iload_3
   24:	ireturn
   25:	aload_0
   26:	getfield	#22; //Field ord2$8:Lscala/Ordering;
   29:	aload_1
   30:	invokevirtual	#81; //Method scala/Tuple9._2:()Ljava/lang/Object;
   33:	aload_2
   34:	invokevirtual	#81; //Method scala/Tuple9._2:()Ljava/lang/Object;
   37:	invokeinterface	#78,  3; //InterfaceMethod scala/Ordering.compare:(Ljava/lang/Object;Ljava/lang/Object;)I
   42:	istore	4
   44:	iload	4
   46:	iconst_0
   47:	if_icmpeq	53
   50:	iload	4
   52:	ireturn
   53:	aload_0
   54:	getfield	#24; //Field ord3$7:Lscala/Ordering;
   57:	aload_1
   58:	invokevirtual	#84; //Method scala/Tuple9._3:()Ljava/lang/Object;
   61:	aload_2
   62:	invokevirtual	#84; //Method scala/Tuple9._3:()Ljava/lang/Object;
   65:	invokeinterface	#78,  3; //InterfaceMethod scala/Ordering.compare:(Ljava/lang/Object;Ljava/lang/Object;)I
   70:	istore	5
   72:	iload	5
   74:	iconst_0
   75:	if_icmpeq	81
   78:	iload	5
   80:	ireturn
   81:	aload_0
   82:	getfield	#26; //Field ord4$6:Lscala/Ordering;
   85:	aload_1
   86:	invokevirtual	#87; //Method scala/Tuple9._4:()Ljava/lang/Object;
   89:	aload_2
   90:	invokevirtual	#87; //Method scala/Tuple9._4:()Ljava/lang/Object;
   93:	invokeinterface	#78,  3; //InterfaceMethod scala/Ordering.compare:(Ljava/lang/Object;Ljava/lang/Object;)I
   98:	istore	6
   100:	iload	6
   102:	iconst_0
   103:	if_icmpeq	109
   106:	iload	6
   108:	ireturn
   109:	aload_0
   110:	getfield	#28; //Field ord5$5:Lscala/Ordering;
   113:	aload_1
   114:	invokevirtual	#90; //Method scala/Tuple9._5:()Ljava/lang/Object;
   117:	aload_2
   118:	invokevirtual	#90; //Method scala/Tuple9._5:()Ljava/lang/Object;
   121:	invokeinterface	#78,  3; //InterfaceMethod scala/Ordering.compare:(Ljava/lang/Object;Ljava/lang/Object;)I
   126:	istore	7
   128:	iload	7
   130:	iconst_0
   131:	if_icmpeq	137
   134:	iload	7
   136:	ireturn
   137:	aload_0
   138:	getfield	#30; //Field ord6$4:Lscala/Ordering;
   141:	aload_1
   142:	invokevirtual	#93; //Method scala/Tuple9._6:()Ljava/lang/Object;
   145:	aload_2
   146:	invokevirtual	#93; //Method scala/Tuple9._6:()Ljava/lang/Object;
   149:	invokeinterface	#78,  3; //InterfaceMethod scala/Ordering.compare:(Ljava/lang/Object;Ljava/lang/Object;)I
   154:	istore	8
   156:	iload	8
   158:	iconst_0
   159:	if_icmpeq	165
   162:	iload	8
   164:	ireturn
   165:	aload_0
   166:	getfield	#32; //Field ord7$3:Lscala/Ordering;
   169:	aload_1
   170:	invokevirtual	#96; //Method scala/Tuple9._7:()Ljava/lang/Object;
   173:	aload_2
   174:	invokevirtual	#96; //Method scala/Tuple9._7:()Ljava/lang/Object;
   177:	invokeinterface	#78,  3; //InterfaceMethod scala/Ordering.compare:(Ljava/lang/Object;Ljava/lang/Object;)I
   182:	istore	9
   184:	iload	9
   186:	iconst_0
   187:	if_icmpeq	193
   190:	iload	9
   192:	ireturn
   193:	aload_0
   194:	getfield	#34; //Field ord8$2:Lscala/Ordering;
   197:	aload_1
   198:	invokevirtual	#99; //Method scala/Tuple9._8:()Ljava/lang/Object;
   201:	aload_2
   202:	invokevirtual	#99; //Method scala/Tuple9._8:()Ljava/lang/Object;
   205:	invokeinterface	#78,  3; //InterfaceMethod scala/Ordering.compare:(Ljava/lang/Object;Ljava/lang/Object;)I
   210:	istore	10
   212:	iload	10
   214:	iconst_0
   215:	if_icmpeq	221
   218:	iload	10
   220:	ireturn
   221:	aload_0
   222:	getfield	#36; //Field ord9$1:Lscala/Ordering;
   225:	aload_1
   226:	invokevirtual	#102; //Method scala/Tuple9._9:()Ljava/lang/Object;
   229:	aload_2
   230:	invokevirtual	#102; //Method scala/Tuple9._9:()Ljava/lang/Object;
   233:	invokeinterface	#78,  3; //InterfaceMethod scala/Ordering.compare:(Ljava/lang/Object;Ljava/lang/Object;)I
   238:	istore	11
   240:	iload	11
   242:	iconst_0
   243:	if_icmpeq	249
   246:	iload	11
   248:	ireturn
   249:	iconst_0
   250:	ireturn
  LineNumberTable: 
   line 332: 0
   line 333: 18
   line 334: 25
   line 335: 44
   line 336: 53
   line 337: 72
   line 338: 81
   line 339: 100
   line 340: 109
   line 341: 128
   line 342: 137
   line 343: 156
   line 344: 165
   line 345: 184
   line 346: 193
   line 347: 212
   line 348: 221
   line 349: 240
   line 350: 249

  LocalVariableTable: 
   Start  Length  Slot  Name   Signature
   0      251      0    this       Lscala/Ordering$$anon$12;
   0      251      1    x       Lscala/Tuple9;
   0      251      2    y       Lscala/Tuple9;
   18      232      3    compare1       I
   44      206      4    compare2       I
   72      178      5    compare3       I
   100      150      6    compare4       I
   128      122      7    compare5       I
   156      94      8    compare6       I
   184      66      9    compare7       I
   212      38      10    compare8       I
   240      10      11    compare9       I

  Signature: length = 0x2
   00 72 

public scala.Ordering$Ops mkOrderingOps(java.lang.Object);
  Code:
   Stack=2, Locals=2, Args_size=2
   0:	aload_0
   1:	aload_1
   2:	invokestatic	#120; //Method scala/Ordering$class.mkOrderingOps:(Lscala/Ordering;Ljava/lang/Object;)Lscala/Ordering$Ops;
   5:	areturn
  LineNumberTable: 
   line 330: 0

  LocalVariableTable: 
   Start  Length  Slot  Name   Signature
   0      6      0    this       Lscala/Ordering$$anon$12;
   0      6      1    lhs       Ljava/lang/Object;


public scala.Ordering reverse();
  Code:
   Stack=1, Locals=1, Args_size=1
   0:	aload_0
   1:	invokestatic	#124; //Method scala/Ordering$class.reverse:(Lscala/Ordering;)Lscala/Ordering;
   4:	areturn
  LineNumberTable: 
   line 330: 0


public java.lang.Object min(java.lang.Object, java.lang.Object);
  Code:
   Stack=3, Locals=3, Args_size=3
   0:	aload_0
   1:	aload_1
   2:	aload_2
   3:	invokestatic	#129; //Method scala/Ordering$class.min:(Lscala/Ordering;Ljava/lang/Object;Ljava/lang/Object;)Ljava/lang/Object;
   6:	areturn
  LineNumberTable: 
   line 330: 0

  LocalVariableTable: 
   Start  Length  Slot  Name   Signature
   0      7      0    this       Lscala/Ordering$$anon$12;
   0      7      1    x       Ljava/lang/Object;
   0      7      2    y       Ljava/lang/Object;


public java.lang.Object max(java.lang.Object, java.lang.Object);
  Code:
   Stack=3, Locals=3, Args_size=3
   0:	aload_0
   1:	aload_1
   2:	aload_2
   3:	invokestatic	#132; //Method scala/Ordering$class.max:(Lscala/Ordering;Ljava/lang/Object;Ljava/lang/Object;)Ljava/lang/Object;
   6:	areturn
  LineNumberTable: 
   line 330: 0

  LocalVariableTable: 
   Start  Length  Slot  Name   Signature
   0      7      0    this       Lscala/Ordering$$anon$12;
   0      7      1    x       Ljava/lang/Object;
   0      7      2    y       Ljava/lang/Object;


public boolean equiv(java.lang.Object, java.lang.Object);
  Code:
   Stack=3, Locals=3, Args_size=3
   0:	aload_0
   1:	aload_1
   2:	aload_2
   3:	invokestatic	#137; //Method scala/Ordering$class.equiv:(Lscala/Ordering;Ljava/lang/Object;Ljava/lang/Object;)Z
   6:	ireturn
  LineNumberTable: 
   line 330: 0

  LocalVariableTable: 
   Start  Length  Slot  Name   Signature
   0      7      0    this       Lscala/Ordering$$anon$12;
   0      7      1    x       Ljava/lang/Object;
   0      7      2    y       Ljava/lang/Object;


public boolean gt(java.lang.Object, java.lang.Object);
  Code:
   Stack=3, Locals=3, Args_size=3
   0:	aload_0
   1:	aload_1
   2:	aload_2
   3:	invokestatic	#140; //Method scala/Ordering$class.gt:(Lscala/Ordering;Ljava/lang/Object;Ljava/lang/Object;)Z
   6:	ireturn
  LineNumberTable: 
   line 330: 0

  LocalVariableTable: 
   Start  Length  Slot  Name   Signature
   0      7      0    this       Lscala/Ordering$$anon$12;
   0      7      1    x       Ljava/lang/Object;
   0      7      2    y       Ljava/lang/Object;


public boolean lt(java.lang.Object, java.lang.Object);
  Code:
   Stack=3, Locals=3, Args_size=3
   0:	aload_0
   1:	aload_1
   2:	aload_2
   3:	invokestatic	#143; //Method scala/Ordering$class.lt:(Lscala/Ordering;Ljava/lang/Object;Ljava/lang/Object;)Z
   6:	ireturn
  LineNumberTable: 
   line 330: 0

  LocalVariableTable: 
   Start  Length  Slot  Name   Signature
   0      7      0    this       Lscala/Ordering$$anon$12;
   0      7      1    x       Ljava/lang/Object;
   0      7      2    y       Ljava/lang/Object;


public boolean gteq(java.lang.Object, java.lang.Object);
  Code:
   Stack=3, Locals=3, Args_size=3
   0:	aload_0
   1:	aload_1
   2:	aload_2
   3:	invokestatic	#146; //Method scala/Ordering$class.gteq:(Lscala/Ordering;Ljava/lang/Object;Ljava/lang/Object;)Z
   6:	ireturn
  LineNumberTable: 
   line 330: 0

  LocalVariableTable: 
   Start  Length  Slot  Name   Signature
   0      7      0    this       Lscala/Ordering$$anon$12;
   0      7      1    x       Ljava/lang/Object;
   0      7      2    y       Ljava/lang/Object;


public boolean lteq(java.lang.Object, java.lang.Object);
  Code:
   Stack=3, Locals=3, Args_size=3
   0:	aload_0
   1:	aload_1
   2:	aload_2
   3:	invokestatic	#149; //Method scala/Ordering$class.lteq:(Lscala/Ordering;Ljava/lang/Object;Ljava/lang/Object;)Z
   6:	ireturn
  LineNumberTable: 
   line 330: 0

  LocalVariableTable: 
   Start  Length  Slot  Name   Signature
   0      7      0    this       Lscala/Ordering$$anon$12;
   0      7      1    x       Ljava/lang/Object;
   0      7      2    y       Ljava/lang/Object;


}

