Compiled from "Ordering.scala"
public final class scala.Ordering$ extends java.lang.Object implements scala.ScalaObject
  SourceFile: "Ordering.scala"
  Scala: length = 0x
   
  InnerClass: 
   public #161= #158 of #160; //Ops=class scala/Ordering$Ops of class scala/Ordering
   public final #162= #89 of #160; //$anon$8=class scala/Ordering$$anon$8 of class scala/Ordering
   public final #163= #135 of #160; //$anon$4=class scala/Ordering$$anon$4 of class scala/Ordering
   public final #164= #114 of #160; //$anon$6=class scala/Ordering$$anon$6 of class scala/Ordering
   public final #165= #150 of #160; //$anon$2=class scala/Ordering$$anon$2 of class scala/Ordering
   public final #166= #102 of #160; //$anon$7=class scala/Ordering$$anon$7 of class scala/Ordering
   public final #167= #143 of #160; //$anon$3=class scala/Ordering$$anon$3 of class scala/Ordering
   public final #168= #125 of #160; //$anon$5=class scala/Ordering$$anon$5 of class scala/Ordering
   public final #169= #75 of #160; //$anon$9=class scala/Ordering$$anon$9 of class scala/Ordering
   public final #170= #23 of #160; //$anon$12=class scala/Ordering$$anon$12 of class scala/Ordering
   public final #171= #60 of #160; //$anon$10=class scala/Ordering$$anon$10 of class scala/Ordering
   public final #172= #44 of #160; //$anon$11=class scala/Ordering$$anon$11 of class scala/Ordering
   public abstract #175= #174 of #160; //IntOrdering=class scala/Ordering$IntOrdering of class scala/Ordering
   public abstract #178= #177 of #160; //CharOrdering=class scala/Ordering$CharOrdering of class scala/Ordering
   public abstract #181= #180 of #160; //ByteOrdering=class scala/Ordering$ByteOrdering of class scala/Ordering
   public abstract #184= #183 of #160; //LongOrdering=class scala/Ordering$LongOrdering of class scala/Ordering
   public abstract #187= #186 of #160; //UnitOrdering=class scala/Ordering$UnitOrdering of class scala/Ordering
   public abstract #190= #189 of #160; //FloatOrdering=class scala/Ordering$FloatOrdering of class scala/Ordering
   public abstract #193= #192 of #160; //ShortOrdering=class scala/Ordering$ShortOrdering of class scala/Ordering
   public abstract #196= #195 of #160; //BigIntOrdering=class scala/Ordering$BigIntOrdering of class scala/Ordering
   public abstract #199= #198 of #160; //StringOrdering=class scala/Ordering$StringOrdering of class scala/Ordering
   public abstract #202= #201 of #160; //DoubleOrdering=class scala/Ordering$DoubleOrdering of class scala/Ordering
   public abstract #205= #204 of #160; //BooleanOrdering=class scala/Ordering$BooleanOrdering of class scala/Ordering
   public abstract #208= #207 of #160; //IntOrdering$class=class scala/Ordering$IntOrdering$class of class scala/Ordering
   public abstract #211= #210 of #160; //CharOrdering$class=class scala/Ordering$CharOrdering$class of class scala/Ordering
   public abstract #214= #213 of #160; //BigDecimalOrdering=class scala/Ordering$BigDecimalOrdering of class scala/Ordering
   public abstract #217= #216 of #160; //LongOrdering$class=class scala/Ordering$LongOrdering$class of class scala/Ordering
   public abstract #220= #219 of #160; //ByteOrdering$class=class scala/Ordering$ByteOrdering$class of class scala/Ordering
   public abstract #223= #222 of #160; //UnitOrdering$class=class scala/Ordering$UnitOrdering$class of class scala/Ordering
   public abstract #226= #225 of #160; //FloatOrdering$class=class scala/Ordering$FloatOrdering$class of class scala/Ordering
   public abstract #229= #228 of #160; //ShortOrdering$class=class scala/Ordering$ShortOrdering$class of class scala/Ordering
   public abstract #232= #231 of #160; //BigIntOrdering$class=class scala/Ordering$BigIntOrdering$class of class scala/Ordering
   public abstract #235= #234 of #160; //StringOrdering$class=class scala/Ordering$StringOrdering$class of class scala/Ordering
   public abstract #238= #237 of #160; //DoubleOrdering$class=class scala/Ordering$DoubleOrdering$class of class scala/Ordering
   public abstract #241= #240 of #160; //BooleanOrdering$class=class scala/Ordering$BooleanOrdering$class of class scala/Ordering
   public abstract #244= #243 of #160; //BigDecimalOrdering$class=class scala/Ordering$BigDecimalOrdering$class of class scala/Ordering
  minor version: 0
  major version: 49
  Constant pool:
const #1 = Asciz	SourceFile;
const #2 = Asciz	Ordering.scala;
const #3 = Asciz	Scala;
const #4 = Asciz	MODULE$;
const #5 = Asciz	Lscala/Ordering$;;
const #6 = Asciz	<clinit>;
const #7 = Asciz	()V;
const #8 = Asciz	Code;
const #9 = Asciz	scala/Ordering$;
const #10 = class	#9;	//  scala/Ordering$
const #11 = Asciz	<init>;
const #12 = NameAndType	#11:#7;//  "<init>":()V
const #13 = Method	#10.#12;	//  scala/Ordering$."<init>":()V
const #14 = Asciz	LineNumberTable;
const #15 = Asciz	java/lang/Object;
const #16 = class	#15;	//  java/lang/Object
const #17 = Method	#16.#12;	//  java/lang/Object."<init>":()V
const #18 = NameAndType	#4:#5;//  MODULE$:Lscala/Ordering$;
const #19 = Field	#10.#18;	//  scala/Ordering$.MODULE$:Lscala/Ordering$;
const #20 = Asciz	Tuple9;
const #21 = Asciz	(Lscala/Ordering;Lscala/Ordering;Lscala/Ordering;Lscala/Ordering;Lscala/Ordering;Lscala/Ordering;Lscala/Ordering;Lscala/Ordering;Lscala/Ordering;)Lscala/Ordering;;
const #22 = Asciz	scala/Ordering$$anon$12;
const #23 = class	#22;	//  scala/Ordering$$anon$12
const #24 = Asciz	(Lscala/Ordering;Lscala/Ordering;Lscala/Ordering;Lscala/Ordering;Lscala/Ordering;Lscala/Ordering;Lscala/Ordering;Lscala/Ordering;Lscala/Ordering;)V;
const #25 = NameAndType	#11:#24;//  "<init>":(Lscala/Ordering;Lscala/Ordering;Lscala/Ordering;Lscala/Ordering;Lscala/Ordering;Lscala/Ordering;Lscala/Ordering;Lscala/Ordering;Lscala/Ordering;)V
const #26 = Method	#23.#25;	//  scala/Ordering$$anon$12."<init>":(Lscala/Ordering;Lscala/Ordering;Lscala/Ordering;Lscala/Ordering;Lscala/Ordering;Lscala/Ordering;Lscala/Ordering;Lscala/Ordering;Lscala/Ordering;)V
const #27 = Asciz	this;
const #28 = Asciz	ord1$8;
const #29 = Asciz	Lscala/Ordering;;
const #30 = Asciz	ord2$8;
const #31 = Asciz	ord3$7;
const #32 = Asciz	ord4$6;
const #33 = Asciz	ord5$5;
const #34 = Asciz	ord6$4;
const #35 = Asciz	ord7$3;
const #36 = Asciz	ord8$2;
const #37 = Asciz	ord9$1;
const #38 = Asciz	LocalVariableTable;
const #39 = Asciz	<T1:Ljava/lang/Object;T2:Ljava/lang/Object;T3:Ljava/lang/Object;T4:Ljava/lang/Object;T5:Ljava/lang/Object;T6:Ljava/lang/Object;T7:Ljava/lang/Object;T8:Ljava/lang/Object;T9:Ljava/lang/Object;>(Lscala/Ordering<TT1;>;Lscala/Ordering<TT2;>;Lscala/Ordering<TT3;>;Lscala/Ordering<TT4;>;Lscala/Ordering<TT5;>;Lscala/Ordering<TT6;>;Lscala/Ordering<TT7;>;Lscala/Ordering<TT8;>;Lscala/Ordering<TT9;>;)Lscala/Ordering<Lscala/Tuple9<TT1;TT2;TT3;TT4;TT5;TT6;TT7;TT8;TT9;>;>;;
const #40 = Asciz	Signature;
const #41 = Asciz	Tuple8;
const #42 = Asciz	(Lscala/Ordering;Lscala/Ordering;Lscala/Ordering;Lscala/Ordering;Lscala/Ordering;Lscala/Ordering;Lscala/Ordering;Lscala/Ordering;)Lscala/Ordering;;
const #43 = Asciz	scala/Ordering$$anon$11;
const #44 = class	#43;	//  scala/Ordering$$anon$11
const #45 = Asciz	(Lscala/Ordering;Lscala/Ordering;Lscala/Ordering;Lscala/Ordering;Lscala/Ordering;Lscala/Ordering;Lscala/Ordering;Lscala/Ordering;)V;
const #46 = NameAndType	#11:#45;//  "<init>":(Lscala/Ordering;Lscala/Ordering;Lscala/Ordering;Lscala/Ordering;Lscala/Ordering;Lscala/Ordering;Lscala/Ordering;Lscala/Ordering;)V
const #47 = Method	#44.#46;	//  scala/Ordering$$anon$11."<init>":(Lscala/Ordering;Lscala/Ordering;Lscala/Ordering;Lscala/Ordering;Lscala/Ordering;Lscala/Ordering;Lscala/Ordering;Lscala/Ordering;)V
const #48 = Asciz	ord1$7;
const #49 = Asciz	ord2$7;
const #50 = Asciz	ord3$6;
const #51 = Asciz	ord4$5;
const #52 = Asciz	ord5$4;
const #53 = Asciz	ord6$3;
const #54 = Asciz	ord7$2;
const #55 = Asciz	ord8$1;
const #56 = Asciz	<T1:Ljava/lang/Object;T2:Ljava/lang/Object;T3:Ljava/lang/Object;T4:Ljava/lang/Object;T5:Ljava/lang/Object;T6:Ljava/lang/Object;T7:Ljava/lang/Object;T8:Ljava/lang/Object;>(Lscala/Ordering<TT1;>;Lscala/Ordering<TT2;>;Lscala/Ordering<TT3;>;Lscala/Ordering<TT4;>;Lscala/Ordering<TT5;>;Lscala/Ordering<TT6;>;Lscala/Ordering<TT7;>;Lscala/Ordering<TT8;>;)Lscala/Ordering<Lscala/Tuple8<TT1;TT2;TT3;TT4;TT5;TT6;TT7;TT8;>;>;;
const #57 = Asciz	Tuple7;
const #58 = Asciz	(Lscala/Ordering;Lscala/Ordering;Lscala/Ordering;Lscala/Ordering;Lscala/Ordering;Lscala/Ordering;Lscala/Ordering;)Lscala/Ordering;;
const #59 = Asciz	scala/Ordering$$anon$10;
const #60 = class	#59;	//  scala/Ordering$$anon$10
const #61 = Asciz	(Lscala/Ordering;Lscala/Ordering;Lscala/Ordering;Lscala/Ordering;Lscala/Ordering;Lscala/Ordering;Lscala/Ordering;)V;
const #62 = NameAndType	#11:#61;//  "<init>":(Lscala/Ordering;Lscala/Ordering;Lscala/Ordering;Lscala/Ordering;Lscala/Ordering;Lscala/Ordering;Lscala/Ordering;)V
const #63 = Method	#60.#62;	//  scala/Ordering$$anon$10."<init>":(Lscala/Ordering;Lscala/Ordering;Lscala/Ordering;Lscala/Ordering;Lscala/Ordering;Lscala/Ordering;Lscala/Ordering;)V
const #64 = Asciz	ord1$6;
const #65 = Asciz	ord2$6;
const #66 = Asciz	ord3$5;
const #67 = Asciz	ord4$4;
const #68 = Asciz	ord5$3;
const #69 = Asciz	ord6$2;
const #70 = Asciz	ord7$1;
const #71 = Asciz	<T1:Ljava/lang/Object;T2:Ljava/lang/Object;T3:Ljava/lang/Object;T4:Ljava/lang/Object;T5:Ljava/lang/Object;T6:Ljava/lang/Object;T7:Ljava/lang/Object;>(Lscala/Ordering<TT1;>;Lscala/Ordering<TT2;>;Lscala/Ordering<TT3;>;Lscala/Ordering<TT4;>;Lscala/Ordering<TT5;>;Lscala/Ordering<TT6;>;Lscala/Ordering<TT7;>;)Lscala/Ordering<Lscala/Tuple7<TT1;TT2;TT3;TT4;TT5;TT6;TT7;>;>;;
const #72 = Asciz	Tuple6;
const #73 = Asciz	(Lscala/Ordering;Lscala/Ordering;Lscala/Ordering;Lscala/Ordering;Lscala/Ordering;Lscala/Ordering;)Lscala/Ordering;;
const #74 = Asciz	scala/Ordering$$anon$9;
const #75 = class	#74;	//  scala/Ordering$$anon$9
const #76 = Asciz	(Lscala/Ordering;Lscala/Ordering;Lscala/Ordering;Lscala/Ordering;Lscala/Ordering;Lscala/Ordering;)V;
const #77 = NameAndType	#11:#76;//  "<init>":(Lscala/Ordering;Lscala/Ordering;Lscala/Ordering;Lscala/Ordering;Lscala/Ordering;Lscala/Ordering;)V
const #78 = Method	#75.#77;	//  scala/Ordering$$anon$9."<init>":(Lscala/Ordering;Lscala/Ordering;Lscala/Ordering;Lscala/Ordering;Lscala/Ordering;Lscala/Ordering;)V
const #79 = Asciz	ord1$5;
const #80 = Asciz	ord2$5;
const #81 = Asciz	ord3$4;
const #82 = Asciz	ord4$3;
const #83 = Asciz	ord5$2;
const #84 = Asciz	ord6$1;
const #85 = Asciz	<T1:Ljava/lang/Object;T2:Ljava/lang/Object;T3:Ljava/lang/Object;T4:Ljava/lang/Object;T5:Ljava/lang/Object;T6:Ljava/lang/Object;>(Lscala/Ordering<TT1;>;Lscala/Ordering<TT2;>;Lscala/Ordering<TT3;>;Lscala/Ordering<TT4;>;Lscala/Ordering<TT5;>;Lscala/Ordering<TT6;>;)Lscala/Ordering<Lscala/Tuple6<TT1;TT2;TT3;TT4;TT5;TT6;>;>;;
const #86 = Asciz	Tuple5;
const #87 = Asciz	(Lscala/Ordering;Lscala/Ordering;Lscala/Ordering;Lscala/Ordering;Lscala/Ordering;)Lscala/Ordering;;
const #88 = Asciz	scala/Ordering$$anon$8;
const #89 = class	#88;	//  scala/Ordering$$anon$8
const #90 = Asciz	(Lscala/Ordering;Lscala/Ordering;Lscala/Ordering;Lscala/Ordering;Lscala/Ordering;)V;
const #91 = NameAndType	#11:#90;//  "<init>":(Lscala/Ordering;Lscala/Ordering;Lscala/Ordering;Lscala/Ordering;Lscala/Ordering;)V
const #92 = Method	#89.#91;	//  scala/Ordering$$anon$8."<init>":(Lscala/Ordering;Lscala/Ordering;Lscala/Ordering;Lscala/Ordering;Lscala/Ordering;)V
const #93 = Asciz	ord1$4;
const #94 = Asciz	ord2$4;
const #95 = Asciz	ord3$3;
const #96 = Asciz	ord4$2;
const #97 = Asciz	ord5$1;
const #98 = Asciz	<T1:Ljava/lang/Object;T2:Ljava/lang/Object;T3:Ljava/lang/Object;T4:Ljava/lang/Object;T5:Ljava/lang/Object;>(Lscala/Ordering<TT1;>;Lscala/Ordering<TT2;>;Lscala/Ordering<TT3;>;Lscala/Ordering<TT4;>;Lscala/Ordering<TT5;>;)Lscala/Ordering<Lscala/Tuple5<TT1;TT2;TT3;TT4;TT5;>;>;;
const #99 = Asciz	Tuple4;
const #100 = Asciz	(Lscala/Ordering;Lscala/Ordering;Lscala/Ordering;Lscala/Ordering;)Lscala/Ordering;;
const #101 = Asciz	scala/Ordering$$anon$7;
const #102 = class	#101;	//  scala/Ordering$$anon$7
const #103 = Asciz	(Lscala/Ordering;Lscala/Ordering;Lscala/Ordering;Lscala/Ordering;)V;
const #104 = NameAndType	#11:#103;//  "<init>":(Lscala/Ordering;Lscala/Ordering;Lscala/Ordering;Lscala/Ordering;)V
const #105 = Method	#102.#104;	//  scala/Ordering$$anon$7."<init>":(Lscala/Ordering;Lscala/Ordering;Lscala/Ordering;Lscala/Ordering;)V
const #106 = Asciz	ord1$3;
const #107 = Asciz	ord2$3;
const #108 = Asciz	ord3$2;
const #109 = Asciz	ord4$1;
const #110 = Asciz	<T1:Ljava/lang/Object;T2:Ljava/lang/Object;T3:Ljava/lang/Object;T4:Ljava/lang/Object;>(Lscala/Ordering<TT1;>;Lscala/Ordering<TT2;>;Lscala/Ordering<TT3;>;Lscala/Ordering<TT4;>;)Lscala/Ordering<Lscala/Tuple4<TT1;TT2;TT3;TT4;>;>;;
const #111 = Asciz	Tuple3;
const #112 = Asciz	(Lscala/Ordering;Lscala/Ordering;Lscala/Ordering;)Lscala/Ordering;;
const #113 = Asciz	scala/Ordering$$anon$6;
const #114 = class	#113;	//  scala/Ordering$$anon$6
const #115 = Asciz	(Lscala/Ordering;Lscala/Ordering;Lscala/Ordering;)V;
const #116 = NameAndType	#11:#115;//  "<init>":(Lscala/Ordering;Lscala/Ordering;Lscala/Ordering;)V
const #117 = Method	#114.#116;	//  scala/Ordering$$anon$6."<init>":(Lscala/Ordering;Lscala/Ordering;Lscala/Ordering;)V
const #118 = Asciz	ord1$2;
const #119 = Asciz	ord2$2;
const #120 = Asciz	ord3$1;
const #121 = Asciz	<T1:Ljava/lang/Object;T2:Ljava/lang/Object;T3:Ljava/lang/Object;>(Lscala/Ordering<TT1;>;Lscala/Ordering<TT2;>;Lscala/Ordering<TT3;>;)Lscala/Ordering<Lscala/Tuple3<TT1;TT2;TT3;>;>;;
const #122 = Asciz	Tuple2;
const #123 = Asciz	(Lscala/Ordering;Lscala/Ordering;)Lscala/Ordering;;
const #124 = Asciz	scala/Ordering$$anon$5;
const #125 = class	#124;	//  scala/Ordering$$anon$5
const #126 = Asciz	(Lscala/Ordering;Lscala/Ordering;)V;
const #127 = NameAndType	#11:#126;//  "<init>":(Lscala/Ordering;Lscala/Ordering;)V
const #128 = Method	#125.#127;	//  scala/Ordering$$anon$5."<init>":(Lscala/Ordering;Lscala/Ordering;)V
const #129 = Asciz	ord1$1;
const #130 = Asciz	ord2$1;
const #131 = Asciz	<T1:Ljava/lang/Object;T2:Ljava/lang/Object;>(Lscala/Ordering<TT1;>;Lscala/Ordering<TT2;>;)Lscala/Ordering<Lscala/Tuple2<TT1;TT2;>;>;;
const #132 = Asciz	Iterable;
const #133 = Asciz	(Lscala/Ordering;)Lscala/Ordering;;
const #134 = Asciz	scala/Ordering$$anon$4;
const #135 = class	#134;	//  scala/Ordering$$anon$4
const #136 = Asciz	(Lscala/Ordering;)V;
const #137 = NameAndType	#11:#136;//  "<init>":(Lscala/Ordering;)V
const #138 = Method	#135.#137;	//  scala/Ordering$$anon$4."<init>":(Lscala/Ordering;)V
const #139 = Asciz	ord$2;
const #140 = Asciz	<T:Ljava/lang/Object;>(Lscala/Ordering<TT;>;)Lscala/Ordering<Lscala/collection/Iterable<TT;>;>;;
const #141 = Asciz	Option;
const #142 = Asciz	scala/Ordering$$anon$3;
const #143 = class	#142;	//  scala/Ordering$$anon$3
const #144 = Method	#143.#137;	//  scala/Ordering$$anon$3."<init>":(Lscala/Ordering;)V
const #145 = Asciz	ord$1;
const #146 = Asciz	<T:Ljava/lang/Object;>(Lscala/Ordering<TT;>;)Lscala/Ordering<Lscala/Option<TT;>;>;;
const #147 = Asciz	ordered;
const #148 = Asciz	()Lscala/Ordering;;
const #149 = Asciz	scala/Ordering$$anon$2;
const #150 = class	#149;	//  scala/Ordering$$anon$2
const #151 = Method	#150.#12;	//  scala/Ordering$$anon$2."<init>":()V
const #152 = Asciz	<A::Lscala/Ordered<TA;>;>()Lscala/Ordering<TA;>;;
const #153 = Asciz	apply;
const #154 = Asciz	ord;
const #155 = Asciz	<T:Ljava/lang/Object;>(Lscala/Ordering<TT;>;)Lscala/Ordering<TT;>;;
const #156 = Asciz	InnerClasses;
const #157 = Asciz	scala/Ordering$Ops;
const #158 = class	#157;	//  scala/Ordering$Ops
const #159 = Asciz	scala/Ordering;
const #160 = class	#159;	//  scala/Ordering
const #161 = Asciz	Ops;
const #162 = Asciz	$anon$8;
const #163 = Asciz	$anon$4;
const #164 = Asciz	$anon$6;
const #165 = Asciz	$anon$2;
const #166 = Asciz	$anon$7;
const #167 = Asciz	$anon$3;
const #168 = Asciz	$anon$5;
const #169 = Asciz	$anon$9;
const #170 = Asciz	$anon$12;
const #171 = Asciz	$anon$10;
const #172 = Asciz	$anon$11;
const #173 = Asciz	scala/Ordering$IntOrdering;
const #174 = class	#173;	//  scala/Ordering$IntOrdering
const #175 = Asciz	IntOrdering;
const #176 = Asciz	scala/Ordering$CharOrdering;
const #177 = class	#176;	//  scala/Ordering$CharOrdering
const #178 = Asciz	CharOrdering;
const #179 = Asciz	scala/Ordering$ByteOrdering;
const #180 = class	#179;	//  scala/Ordering$ByteOrdering
const #181 = Asciz	ByteOrdering;
const #182 = Asciz	scala/Ordering$LongOrdering;
const #183 = class	#182;	//  scala/Ordering$LongOrdering
const #184 = Asciz	LongOrdering;
const #185 = Asciz	scala/Ordering$UnitOrdering;
const #186 = class	#185;	//  scala/Ordering$UnitOrdering
const #187 = Asciz	UnitOrdering;
const #188 = Asciz	scala/Ordering$FloatOrdering;
const #189 = class	#188;	//  scala/Ordering$FloatOrdering
const #190 = Asciz	FloatOrdering;
const #191 = Asciz	scala/Ordering$ShortOrdering;
const #192 = class	#191;	//  scala/Ordering$ShortOrdering
const #193 = Asciz	ShortOrdering;
const #194 = Asciz	scala/Ordering$BigIntOrdering;
const #195 = class	#194;	//  scala/Ordering$BigIntOrdering
const #196 = Asciz	BigIntOrdering;
const #197 = Asciz	scala/Ordering$StringOrdering;
const #198 = class	#197;	//  scala/Ordering$StringOrdering
const #199 = Asciz	StringOrdering;
const #200 = Asciz	scala/Ordering$DoubleOrdering;
const #201 = class	#200;	//  scala/Ordering$DoubleOrdering
const #202 = Asciz	DoubleOrdering;
const #203 = Asciz	scala/Ordering$BooleanOrdering;
const #204 = class	#203;	//  scala/Ordering$BooleanOrdering
const #205 = Asciz	BooleanOrdering;
const #206 = Asciz	scala/Ordering$IntOrdering$class;
const #207 = class	#206;	//  scala/Ordering$IntOrdering$class
const #208 = Asciz	IntOrdering$class;
const #209 = Asciz	scala/Ordering$CharOrdering$class;
const #210 = class	#209;	//  scala/Ordering$CharOrdering$class
const #211 = Asciz	CharOrdering$class;
const #212 = Asciz	scala/Ordering$BigDecimalOrdering;
const #213 = class	#212;	//  scala/Ordering$BigDecimalOrdering
const #214 = Asciz	BigDecimalOrdering;
const #215 = Asciz	scala/Ordering$LongOrdering$class;
const #216 = class	#215;	//  scala/Ordering$LongOrdering$class
const #217 = Asciz	LongOrdering$class;
const #218 = Asciz	scala/Ordering$ByteOrdering$class;
const #219 = class	#218;	//  scala/Ordering$ByteOrdering$class
const #220 = Asciz	ByteOrdering$class;
const #221 = Asciz	scala/Ordering$UnitOrdering$class;
const #222 = class	#221;	//  scala/Ordering$UnitOrdering$class
const #223 = Asciz	UnitOrdering$class;
const #224 = Asciz	scala/Ordering$FloatOrdering$class;
const #225 = class	#224;	//  scala/Ordering$FloatOrdering$class
const #226 = Asciz	FloatOrdering$class;
const #227 = Asciz	scala/Ordering$ShortOrdering$class;
const #228 = class	#227;	//  scala/Ordering$ShortOrdering$class
const #229 = Asciz	ShortOrdering$class;
const #230 = Asciz	scala/Ordering$BigIntOrdering$class;
const #231 = class	#230;	//  scala/Ordering$BigIntOrdering$class
const #232 = Asciz	BigIntOrdering$class;
const #233 = Asciz	scala/Ordering$StringOrdering$class;
const #234 = class	#233;	//  scala/Ordering$StringOrdering$class
const #235 = Asciz	StringOrdering$class;
const #236 = Asciz	scala/Ordering$DoubleOrdering$class;
const #237 = class	#236;	//  scala/Ordering$DoubleOrdering$class
const #238 = Asciz	DoubleOrdering$class;
const #239 = Asciz	scala/Ordering$BooleanOrdering$class;
const #240 = class	#239;	//  scala/Ordering$BooleanOrdering$class
const #241 = Asciz	BooleanOrdering$class;
const #242 = Asciz	scala/Ordering$BigDecimalOrdering$class;
const #243 = class	#242;	//  scala/Ordering$BigDecimalOrdering$class
const #244 = Asciz	BigDecimalOrdering$class;
const #245 = Asciz	scala/ScalaObject;
const #246 = class	#245;	//  scala/ScalaObject

{
public static final scala.Ordering$ MODULE$;

public static {};
  Code:
   Stack=1, Locals=0, Args_size=0
   0:	new	#10; //class scala/Ordering$
   3:	invokespecial	#13; //Method "<init>":()V
   6:	return

public scala.Ordering Tuple9(scala.Ordering, scala.Ordering, scala.Ordering, scala.Ordering, scala.Ordering, scala.Ordering, scala.Ordering, scala.Ordering, scala.Ordering);
  Code:
   Stack=11, Locals=10, Args_size=10
   0:	new	#23; //class scala/Ordering$$anon$12
   3:	dup
   4:	aload_1
   5:	aload_2
   6:	aload_3
   7:	aload	4
   9:	aload	5
   11:	aload	6
   13:	aload	7
   15:	aload	8
   17:	aload	9
   19:	invokespecial	#26; //Method scala/Ordering$$anon$12."<init>":(Lscala/Ordering;Lscala/Ordering;Lscala/Ordering;Lscala/Ordering;Lscala/Ordering;Lscala/Ordering;Lscala/Ordering;Lscala/Ordering;Lscala/Ordering;)V
   22:	areturn
  LineNumberTable: 
   line 330: 0

  LocalVariableTable: 
   Start  Length  Slot  Name   Signature
   0      23      0    this       Lscala/Ordering$;
   0      23      1    ord1$8       Lscala/Ordering;
   0      23      2    ord2$8       Lscala/Ordering;
   0      23      3    ord3$7       Lscala/Ordering;
   0      23      4    ord4$6       Lscala/Ordering;
   0      23      5    ord5$5       Lscala/Ordering;
   0      23      6    ord6$4       Lscala/Ordering;
   0      23      7    ord7$3       Lscala/Ordering;
   0      23      8    ord8$2       Lscala/Ordering;
   0      23      9    ord9$1       Lscala/Ordering;

  Signature: length = 0x2
   00 27 

public scala.Ordering Tuple8(scala.Ordering, scala.Ordering, scala.Ordering, scala.Ordering, scala.Ordering, scala.Ordering, scala.Ordering, scala.Ordering);
  Code:
   Stack=10, Locals=9, Args_size=9
   0:	new	#44; //class scala/Ordering$$anon$11
   3:	dup
   4:	aload_1
   5:	aload_2
   6:	aload_3
   7:	aload	4
   9:	aload	5
   11:	aload	6
   13:	aload	7
   15:	aload	8
   17:	invokespecial	#47; //Method scala/Ordering$$anon$11."<init>":(Lscala/Ordering;Lscala/Ordering;Lscala/Ordering;Lscala/Ordering;Lscala/Ordering;Lscala/Ordering;Lscala/Ordering;Lscala/Ordering;)V
   20:	areturn
  LineNumberTable: 
   line 307: 0

  LocalVariableTable: 
   Start  Length  Slot  Name   Signature
   0      21      0    this       Lscala/Ordering$;
   0      21      1    ord1$7       Lscala/Ordering;
   0      21      2    ord2$7       Lscala/Ordering;
   0      21      3    ord3$6       Lscala/Ordering;
   0      21      4    ord4$5       Lscala/Ordering;
   0      21      5    ord5$4       Lscala/Ordering;
   0      21      6    ord6$3       Lscala/Ordering;
   0      21      7    ord7$2       Lscala/Ordering;
   0      21      8    ord8$1       Lscala/Ordering;

  Signature: length = 0x2
   00 38 

public scala.Ordering Tuple7(scala.Ordering, scala.Ordering, scala.Ordering, scala.Ordering, scala.Ordering, scala.Ordering, scala.Ordering);
  Code:
   Stack=9, Locals=8, Args_size=8
   0:	new	#60; //class scala/Ordering$$anon$10
   3:	dup
   4:	aload_1
   5:	aload_2
   6:	aload_3
   7:	aload	4
   9:	aload	5
   11:	aload	6
   13:	aload	7
   15:	invokespecial	#63; //Method scala/Ordering$$anon$10."<init>":(Lscala/Ordering;Lscala/Ordering;Lscala/Ordering;Lscala/Ordering;Lscala/Ordering;Lscala/Ordering;Lscala/Ordering;)V
   18:	areturn
  LineNumberTable: 
   line 286: 0

  LocalVariableTable: 
   Start  Length  Slot  Name   Signature
   0      19      0    this       Lscala/Ordering$;
   0      19      1    ord1$6       Lscala/Ordering;
   0      19      2    ord2$6       Lscala/Ordering;
   0      19      3    ord3$5       Lscala/Ordering;
   0      19      4    ord4$4       Lscala/Ordering;
   0      19      5    ord5$3       Lscala/Ordering;
   0      19      6    ord6$2       Lscala/Ordering;
   0      19      7    ord7$1       Lscala/Ordering;

  Signature: length = 0x2
   00 47 

public scala.Ordering Tuple6(scala.Ordering, scala.Ordering, scala.Ordering, scala.Ordering, scala.Ordering, scala.Ordering);
  Code:
   Stack=8, Locals=7, Args_size=7
   0:	new	#75; //class scala/Ordering$$anon$9
   3:	dup
   4:	aload_1
   5:	aload_2
   6:	aload_3
   7:	aload	4
   9:	aload	5
   11:	aload	6
   13:	invokespecial	#78; //Method scala/Ordering$$anon$9."<init>":(Lscala/Ordering;Lscala/Ordering;Lscala/Ordering;Lscala/Ordering;Lscala/Ordering;Lscala/Ordering;)V
   16:	areturn
  LineNumberTable: 
   line 267: 0

  LocalVariableTable: 
   Start  Length  Slot  Name   Signature
   0      17      0    this       Lscala/Ordering$;
   0      17      1    ord1$5       Lscala/Ordering;
   0      17      2    ord2$5       Lscala/Ordering;
   0      17      3    ord3$4       Lscala/Ordering;
   0      17      4    ord4$3       Lscala/Ordering;
   0      17      5    ord5$2       Lscala/Ordering;
   0      17      6    ord6$1       Lscala/Ordering;

  Signature: length = 0x2
   00 55 

public scala.Ordering Tuple5(scala.Ordering, scala.Ordering, scala.Ordering, scala.Ordering, scala.Ordering);
  Code:
   Stack=7, Locals=6, Args_size=6
   0:	new	#89; //class scala/Ordering$$anon$8
   3:	dup
   4:	aload_1
   5:	aload_2
   6:	aload_3
   7:	aload	4
   9:	aload	5
   11:	invokespecial	#92; //Method scala/Ordering$$anon$8."<init>":(Lscala/Ordering;Lscala/Ordering;Lscala/Ordering;Lscala/Ordering;Lscala/Ordering;)V
   14:	areturn
  LineNumberTable: 
   line 250: 0

  LocalVariableTable: 
   Start  Length  Slot  Name   Signature
   0      15      0    this       Lscala/Ordering$;
   0      15      1    ord1$4       Lscala/Ordering;
   0      15      2    ord2$4       Lscala/Ordering;
   0      15      3    ord3$3       Lscala/Ordering;
   0      15      4    ord4$2       Lscala/Ordering;
   0      15      5    ord5$1       Lscala/Ordering;

  Signature: length = 0x2
   00 62 

public scala.Ordering Tuple4(scala.Ordering, scala.Ordering, scala.Ordering, scala.Ordering);
  Code:
   Stack=6, Locals=5, Args_size=5
   0:	new	#102; //class scala/Ordering$$anon$7
   3:	dup
   4:	aload_1
   5:	aload_2
   6:	aload_3
   7:	aload	4
   9:	invokespecial	#105; //Method scala/Ordering$$anon$7."<init>":(Lscala/Ordering;Lscala/Ordering;Lscala/Ordering;Lscala/Ordering;)V
   12:	areturn
  LineNumberTable: 
   line 235: 0

  LocalVariableTable: 
   Start  Length  Slot  Name   Signature
   0      13      0    this       Lscala/Ordering$;
   0      13      1    ord1$3       Lscala/Ordering;
   0      13      2    ord2$3       Lscala/Ordering;
   0      13      3    ord3$2       Lscala/Ordering;
   0      13      4    ord4$1       Lscala/Ordering;

  Signature: length = 0x2
   00 6E 

public scala.Ordering Tuple3(scala.Ordering, scala.Ordering, scala.Ordering);
  Code:
   Stack=5, Locals=4, Args_size=4
   0:	new	#114; //class scala/Ordering$$anon$6
   3:	dup
   4:	aload_1
   5:	aload_2
   6:	aload_3
   7:	invokespecial	#117; //Method scala/Ordering$$anon$6."<init>":(Lscala/Ordering;Lscala/Ordering;Lscala/Ordering;)V
   10:	areturn
  LineNumberTable: 
   line 222: 0

  LocalVariableTable: 
   Start  Length  Slot  Name   Signature
   0      11      0    this       Lscala/Ordering$;
   0      11      1    ord1$2       Lscala/Ordering;
   0      11      2    ord2$2       Lscala/Ordering;
   0      11      3    ord3$1       Lscala/Ordering;

  Signature: length = 0x2
   00 79 

public scala.Ordering Tuple2(scala.Ordering, scala.Ordering);
  Code:
   Stack=4, Locals=3, Args_size=3
   0:	new	#125; //class scala/Ordering$$anon$5
   3:	dup
   4:	aload_1
   5:	aload_2
   6:	invokespecial	#128; //Method scala/Ordering$$anon$5."<init>":(Lscala/Ordering;Lscala/Ordering;)V
   9:	areturn
  LineNumberTable: 
   line 211: 0

  LocalVariableTable: 
   Start  Length  Slot  Name   Signature
   0      10      0    this       Lscala/Ordering$;
   0      10      1    ord1$1       Lscala/Ordering;
   0      10      2    ord2$1       Lscala/Ordering;

  Signature: length = 0x2
   00 FFFFFF83 

public scala.Ordering Iterable(scala.Ordering);
  Code:
   Stack=3, Locals=2, Args_size=2
   0:	new	#135; //class scala/Ordering$$anon$4
   3:	dup
   4:	aload_1
   5:	invokespecial	#138; //Method scala/Ordering$$anon$4."<init>":(Lscala/Ordering;)V
   8:	areturn
  LineNumberTable: 
   line 196: 0

  LocalVariableTable: 
   Start  Length  Slot  Name   Signature
   0      9      0    this       Lscala/Ordering$;
   0      9      1    ord$2       Lscala/Ordering;

  Signature: length = 0x2
   00 FFFFFF8C 

public scala.Ordering Option(scala.Ordering);
  Code:
   Stack=3, Locals=2, Args_size=2
   0:	new	#143; //class scala/Ordering$$anon$3
   3:	dup
   4:	aload_1
   5:	invokespecial	#144; //Method scala/Ordering$$anon$3."<init>":(Lscala/Ordering;)V
   8:	areturn
  LineNumberTable: 
   line 186: 0

  LocalVariableTable: 
   Start  Length  Slot  Name   Signature
   0      9      0    this       Lscala/Ordering$;
   0      9      1    ord$1       Lscala/Ordering;

  Signature: length = 0x2
   00 FFFFFF92 

public scala.Ordering ordered();
  Code:
   Stack=2, Locals=1, Args_size=1
   0:	new	#150; //class scala/Ordering$$anon$2
   3:	dup
   4:	invokespecial	#151; //Method scala/Ordering$$anon$2."<init>":()V
   7:	areturn
  LineNumberTable: 
   line 105: 0

  Signature: length = 0x2
   00 FFFFFF98 

public scala.Ordering apply(scala.Ordering);
  Code:
   Stack=1, Locals=2, Args_size=2
   0:	aload_1
   1:	areturn
  LineNumberTable: 
   line 103: 0

  LocalVariableTable: 
   Start  Length  Slot  Name   Signature
   0      2      0    this       Lscala/Ordering$;
   0      2      1    ord       Lscala/Ordering;

  Signature: length = 0x2
   00 FFFFFF9B 

}

