Compiled from "Ordering.scala"
public abstract class scala.Ordering$class extends java.lang.Object
  SourceFile: "Ordering.scala"
  Scala: length = 0x
   
  InnerClass: 
   public #50= #13 of #29; //Ops=class scala/Ordering$Ops of class scala/Ordering
   public final #51= #23 of #29; //$anon$1=class scala/Ordering$$anon$1 of class scala/Ordering
  minor version: 0
  major version: 49
  Constant pool:
const #1 = Asciz	SourceFile;
const #2 = Asciz	Ordering.scala;
const #3 = Asciz	$init$;
const #4 = Asciz	(Lscala/Ordering;)V;
const #5 = Asciz	Code;
const #6 = Asciz	LineNumberTable;
const #7 = Asciz	$this;
const #8 = Asciz	Lscala/Ordering;;
const #9 = Asciz	LocalVariableTable;
const #10 = Asciz	mkOrderingOps;
const #11 = Asciz	(Lscala/Ordering;Ljava/lang/Object;)Lscala/Ordering$Ops;;
const #12 = Asciz	scala/Ordering$Ops;
const #13 = class	#12;	//  scala/Ordering$Ops
const #14 = Asciz	<init>;
const #15 = Asciz	(Lscala/Ordering;Ljava/lang/Object;)V;
const #16 = NameAndType	#14:#15;//  "<init>":(Lscala/Ordering;Ljava/lang/Object;)V
const #17 = Method	#13.#16;	//  scala/Ordering$Ops."<init>":(Lscala/Ordering;Ljava/lang/Object;)V
const #18 = Asciz	lhs;
const #19 = Asciz	Ljava/lang/Object;;
const #20 = Asciz	reverse;
const #21 = Asciz	(Lscala/Ordering;)Lscala/Ordering;;
const #22 = Asciz	scala/Ordering$$anon$1;
const #23 = class	#22;	//  scala/Ordering$$anon$1
const #24 = NameAndType	#14:#4;//  "<init>":(Lscala/Ordering;)V
const #25 = Method	#23.#24;	//  scala/Ordering$$anon$1."<init>":(Lscala/Ordering;)V
const #26 = Asciz	min;
const #27 = Asciz	(Lscala/Ordering;Ljava/lang/Object;Ljava/lang/Object;)Ljava/lang/Object;;
const #28 = Asciz	scala/Ordering;
const #29 = class	#28;	//  scala/Ordering
const #30 = Asciz	lteq;
const #31 = Asciz	(Ljava/lang/Object;Ljava/lang/Object;)Z;
const #32 = NameAndType	#30:#31;//  lteq:(Ljava/lang/Object;Ljava/lang/Object;)Z
const #33 = InterfaceMethod	#29.#32;	//  scala/Ordering.lteq:(Ljava/lang/Object;Ljava/lang/Object;)Z
const #34 = Asciz	x;
const #35 = Asciz	y;
const #36 = Asciz	max;
const #37 = Asciz	gteq;
const #38 = NameAndType	#37:#31;//  gteq:(Ljava/lang/Object;Ljava/lang/Object;)Z
const #39 = InterfaceMethod	#29.#38;	//  scala/Ordering.gteq:(Ljava/lang/Object;Ljava/lang/Object;)Z
const #40 = Asciz	equiv;
const #41 = Asciz	(Lscala/Ordering;Ljava/lang/Object;Ljava/lang/Object;)Z;
const #42 = Asciz	compare;
const #43 = Asciz	(Ljava/lang/Object;Ljava/lang/Object;)I;
const #44 = NameAndType	#42:#43;//  compare:(Ljava/lang/Object;Ljava/lang/Object;)I
const #45 = InterfaceMethod	#29.#44;	//  scala/Ordering.compare:(Ljava/lang/Object;Ljava/lang/Object;)I
const #46 = Asciz	gt;
const #47 = Asciz	lt;
const #48 = Asciz	Scala;
const #49 = Asciz	InnerClasses;
const #50 = Asciz	Ops;
const #51 = Asciz	$anon$1;
const #52 = Asciz	scala/Ordering$class;
const #53 = class	#52;	//  scala/Ordering$class
const #54 = Asciz	java/lang/Object;
const #55 = class	#54;	//  java/lang/Object

{
public static void $init$(scala.Ordering);
  Code:
   Stack=0, Locals=1, Args_size=1
   0:	return
  LineNumberTable: 
   line 43: 0

  LocalVariableTable: 
   Start  Length  Slot  Name   Signature
   0      1      0    $this       Lscala/Ordering;


public static scala.Ordering$Ops mkOrderingOps(scala.Ordering, java.lang.Object);
  Code:
   Stack=4, Locals=2, Args_size=2
   0:	new	#13; //class scala/Ordering$Ops
   3:	dup
   4:	aload_0
   5:	aload_1
   6:	invokespecial	#17; //Method scala/Ordering$Ops."<init>":(Lscala/Ordering;Ljava/lang/Object;)V
   9:	areturn
  LineNumberTable: 
   line 98: 0

  LocalVariableTable: 
   Start  Length  Slot  Name   Signature
   0      10      0    $this       Lscala/Ordering;
   0      10      1    lhs       Ljava/lang/Object;


public static scala.Ordering reverse(scala.Ordering);
  Code:
   Stack=3, Locals=1, Args_size=1
   0:	new	#23; //class scala/Ordering$$anon$1
   3:	dup
   4:	aload_0
   5:	invokespecial	#25; //Method scala/Ordering$$anon$1."<init>":(Lscala/Ordering;)V
   8:	areturn
  LineNumberTable: 
   line 84: 0

  LocalVariableTable: 
   Start  Length  Slot  Name   Signature
   0      9      0    $this       Lscala/Ordering;


public static java.lang.Object min(scala.Ordering, java.lang.Object, java.lang.Object);
  Code:
   Stack=3, Locals=3, Args_size=3
   0:	aload_0
   1:	aload_1
   2:	aload_2
   3:	invokeinterface	#33,  3; //InterfaceMethod scala/Ordering.lteq:(Ljava/lang/Object;Ljava/lang/Object;)Z
   8:	ifeq	15
   11:	aload_1
   12:	goto	16
   15:	aload_2
   16:	areturn
  LineNumberTable: 
   line 82: 0

  LocalVariableTable: 
   Start  Length  Slot  Name   Signature
   0      17      0    $this       Lscala/Ordering;
   0      17      1    x       Ljava/lang/Object;
   0      17      2    y       Ljava/lang/Object;


public static java.lang.Object max(scala.Ordering, java.lang.Object, java.lang.Object);
  Code:
   Stack=3, Locals=3, Args_size=3
   0:	aload_0
   1:	aload_1
   2:	aload_2
   3:	invokeinterface	#39,  3; //InterfaceMethod scala/Ordering.gteq:(Ljava/lang/Object;Ljava/lang/Object;)Z
   8:	ifeq	15
   11:	aload_1
   12:	goto	16
   15:	aload_2
   16:	areturn
  LineNumberTable: 
   line 79: 0

  LocalVariableTable: 
   Start  Length  Slot  Name   Signature
   0      17      0    $this       Lscala/Ordering;
   0      17      1    x       Ljava/lang/Object;
   0      17      2    y       Ljava/lang/Object;


public static boolean equiv(scala.Ordering, java.lang.Object, java.lang.Object);
  Code:
   Stack=3, Locals=3, Args_size=3
   0:	aload_0
   1:	aload_1
   2:	aload_2
   3:	invokeinterface	#45,  3; //InterfaceMethod scala/Ordering.compare:(Ljava/lang/Object;Ljava/lang/Object;)I
   8:	iconst_0
   9:	if_icmpne	16
   12:	iconst_1
   13:	goto	17
   16:	iconst_0
   17:	ireturn
  LineNumberTable: 
   line 76: 0

  LocalVariableTable: 
   Start  Length  Slot  Name   Signature
   0      18      0    $this       Lscala/Ordering;
   0      18      1    x       Ljava/lang/Object;
   0      18      2    y       Ljava/lang/Object;


public static boolean gt(scala.Ordering, java.lang.Object, java.lang.Object);
  Code:
   Stack=3, Locals=3, Args_size=3
   0:	aload_0
   1:	aload_1
   2:	aload_2
   3:	invokeinterface	#45,  3; //InterfaceMethod scala/Ordering.compare:(Ljava/lang/Object;Ljava/lang/Object;)I
   8:	iconst_0
   9:	if_icmple	16
   12:	iconst_1
   13:	goto	17
   16:	iconst_0
   17:	ireturn
  LineNumberTable: 
   line 71: 0

  LocalVariableTable: 
   Start  Length  Slot  Name   Signature
   0      18      0    $this       Lscala/Ordering;
   0      18      1    x       Ljava/lang/Object;
   0      18      2    y       Ljava/lang/Object;


public static boolean lt(scala.Ordering, java.lang.Object, java.lang.Object);
  Code:
   Stack=3, Locals=3, Args_size=3
   0:	aload_0
   1:	aload_1
   2:	aload_2
   3:	invokeinterface	#45,  3; //InterfaceMethod scala/Ordering.compare:(Ljava/lang/Object;Ljava/lang/Object;)I
   8:	iconst_0
   9:	if_icmpge	16
   12:	iconst_1
   13:	goto	17
   16:	iconst_0
   17:	ireturn
  LineNumberTable: 
   line 66: 0

  LocalVariableTable: 
   Start  Length  Slot  Name   Signature
   0      18      0    $this       Lscala/Ordering;
   0      18      1    x       Ljava/lang/Object;
   0      18      2    y       Ljava/lang/Object;


public static boolean gteq(scala.Ordering, java.lang.Object, java.lang.Object);
  Code:
   Stack=3, Locals=3, Args_size=3
   0:	aload_0
   1:	aload_1
   2:	aload_2
   3:	invokeinterface	#45,  3; //InterfaceMethod scala/Ordering.compare:(Ljava/lang/Object;Ljava/lang/Object;)I
   8:	iconst_0
   9:	if_icmplt	16
   12:	iconst_1
   13:	goto	17
   16:	iconst_0
   17:	ireturn
  LineNumberTable: 
   line 61: 0

  LocalVariableTable: 
   Start  Length  Slot  Name   Signature
   0      18      0    $this       Lscala/Ordering;
   0      18      1    x       Ljava/lang/Object;
   0      18      2    y       Ljava/lang/Object;


public static boolean lteq(scala.Ordering, java.lang.Object, java.lang.Object);
  Code:
   Stack=3, Locals=3, Args_size=3
   0:	aload_0
   1:	aload_1
   2:	aload_2
   3:	invokeinterface	#45,  3; //InterfaceMethod scala/Ordering.compare:(Ljava/lang/Object;Ljava/lang/Object;)I
   8:	iconst_0
   9:	if_icmpgt	16
   12:	iconst_1
   13:	goto	17
   16:	iconst_0
   17:	ireturn
  LineNumberTable: 
   line 56: 0

  LocalVariableTable: 
   Start  Length  Slot  Name   Signature
   0      18      0    $this       Lscala/Ordering;
   0      18      1    x       Ljava/lang/Object;
   0      18      2    y       Ljava/lang/Object;


}

