Compiled from "Ordering.scala"
public final class scala.Ordering$BigDecimal$ extends java.lang.Object implements scala.Ordering$BigDecimalOrdering,scala.ScalaObject
  SourceFile: "Ordering.scala"
  Scala: length = 0x
   
  InnerClass: 
   public #98= #97 of #53; //Ops=class scala/Ordering$Ops of class scala/Ordering
   public abstract #99= #41 of #53; //BigDecimalOrdering=class scala/Ordering$BigDecimalOrdering of class scala/Ordering
  minor version: 0
  major version: 49
  Constant pool:
const #1 = Asciz	SourceFile;
const #2 = Asciz	Ordering.scala;
const #3 = Asciz	Scala;
const #4 = Asciz	MODULE$;
const #5 = Asciz	Lscala/Ordering$BigDecimal$;;
const #6 = Asciz	<clinit>;
const #7 = Asciz	()V;
const #8 = Asciz	Code;
const #9 = Asciz	scala/Ordering$BigDecimal$;
const #10 = class	#9;	//  scala/Ordering$BigDecimal$
const #11 = Asciz	<init>;
const #12 = NameAndType	#11:#7;//  "<init>":()V
const #13 = Method	#10.#12;	//  scala/Ordering$BigDecimal$."<init>":()V
const #14 = Asciz	LineNumberTable;
const #15 = Asciz	java/lang/Object;
const #16 = class	#15;	//  java/lang/Object
const #17 = Method	#16.#12;	//  java/lang/Object."<init>":()V
const #18 = NameAndType	#4:#5;//  MODULE$:Lscala/Ordering$BigDecimal$;
const #19 = Field	#10.#18;	//  scala/Ordering$BigDecimal$.MODULE$:Lscala/Ordering$BigDecimal$;
const #20 = Asciz	scala/PartialOrdering$class;
const #21 = class	#20;	//  scala/PartialOrdering$class
const #22 = Asciz	$init$;
const #23 = Asciz	(Lscala/PartialOrdering;)V;
const #24 = NameAndType	#22:#23;//  $init$:(Lscala/PartialOrdering;)V
const #25 = Method	#21.#24;	//  scala/PartialOrdering$class.$init$:(Lscala/PartialOrdering;)V
const #26 = Asciz	scala/Ordering$class;
const #27 = class	#26;	//  scala/Ordering$class
const #28 = Asciz	(Lscala/Ordering;)V;
const #29 = NameAndType	#22:#28;//  $init$:(Lscala/Ordering;)V
const #30 = Method	#27.#29;	//  scala/Ordering$class.$init$:(Lscala/Ordering;)V
const #31 = Asciz	scala/Ordering$BigDecimalOrdering$class;
const #32 = class	#31;	//  scala/Ordering$BigDecimalOrdering$class
const #33 = Asciz	(Lscala/Ordering$BigDecimalOrdering;)V;
const #34 = NameAndType	#22:#33;//  $init$:(Lscala/Ordering$BigDecimalOrdering;)V
const #35 = Method	#32.#34;	//  scala/Ordering$BigDecimalOrdering$class.$init$:(Lscala/Ordering$BigDecimalOrdering;)V
const #36 = Asciz	compare;
const #37 = Asciz	(Ljava/lang/Object;Ljava/lang/Object;)I;
const #38 = Asciz	scala/BigDecimal;
const #39 = class	#38;	//  scala/BigDecimal
const #40 = Asciz	scala/Ordering$BigDecimalOrdering;
const #41 = class	#40;	//  scala/Ordering$BigDecimalOrdering
const #42 = Asciz	(Lscala/BigDecimal;Lscala/BigDecimal;)I;
const #43 = NameAndType	#36:#42;//  compare:(Lscala/BigDecimal;Lscala/BigDecimal;)I
const #44 = InterfaceMethod	#41.#43;	//  scala/Ordering$BigDecimalOrdering.compare:(Lscala/BigDecimal;Lscala/BigDecimal;)I
const #45 = Asciz	this;
const #46 = Asciz	x;
const #47 = Asciz	Ljava/lang/Object;;
const #48 = Asciz	y;
const #49 = Asciz	LocalVariableTable;
const #50 = Asciz	reverse;
const #51 = Asciz	()Lscala/PartialOrdering;;
const #52 = Asciz	scala/Ordering;
const #53 = class	#52;	//  scala/Ordering
const #54 = Asciz	()Lscala/Ordering;;
const #55 = NameAndType	#50:#54;//  reverse:()Lscala/Ordering;
const #56 = InterfaceMethod	#53.#55;	//  scala/Ordering.reverse:()Lscala/Ordering;
const #57 = Asciz	mkOrderingOps;
const #58 = Asciz	(Ljava/lang/Object;)Lscala/Ordering$Ops;;
const #59 = Asciz	(Lscala/Ordering;Ljava/lang/Object;)Lscala/Ordering$Ops;;
const #60 = NameAndType	#57:#59;//  mkOrderingOps:(Lscala/Ordering;Ljava/lang/Object;)Lscala/Ordering$Ops;
const #61 = Method	#27.#60;	//  scala/Ordering$class.mkOrderingOps:(Lscala/Ordering;Ljava/lang/Object;)Lscala/Ordering$Ops;
const #62 = Asciz	lhs;
const #63 = Asciz	(Lscala/Ordering;)Lscala/Ordering;;
const #64 = NameAndType	#50:#63;//  reverse:(Lscala/Ordering;)Lscala/Ordering;
const #65 = Method	#27.#64;	//  scala/Ordering$class.reverse:(Lscala/Ordering;)Lscala/Ordering;
const #66 = Asciz	min;
const #67 = Asciz	(Ljava/lang/Object;Ljava/lang/Object;)Ljava/lang/Object;;
const #68 = Asciz	(Lscala/Ordering;Ljava/lang/Object;Ljava/lang/Object;)Ljava/lang/Object;;
const #69 = NameAndType	#66:#68;//  min:(Lscala/Ordering;Ljava/lang/Object;Ljava/lang/Object;)Ljava/lang/Object;
const #70 = Method	#27.#69;	//  scala/Ordering$class.min:(Lscala/Ordering;Ljava/lang/Object;Ljava/lang/Object;)Ljava/lang/Object;
const #71 = Asciz	max;
const #72 = NameAndType	#71:#68;//  max:(Lscala/Ordering;Ljava/lang/Object;Ljava/lang/Object;)Ljava/lang/Object;
const #73 = Method	#27.#72;	//  scala/Ordering$class.max:(Lscala/Ordering;Ljava/lang/Object;Ljava/lang/Object;)Ljava/lang/Object;
const #74 = Asciz	equiv;
const #75 = Asciz	(Ljava/lang/Object;Ljava/lang/Object;)Z;
const #76 = Asciz	(Lscala/Ordering;Ljava/lang/Object;Ljava/lang/Object;)Z;
const #77 = NameAndType	#74:#76;//  equiv:(Lscala/Ordering;Ljava/lang/Object;Ljava/lang/Object;)Z
const #78 = Method	#27.#77;	//  scala/Ordering$class.equiv:(Lscala/Ordering;Ljava/lang/Object;Ljava/lang/Object;)Z
const #79 = Asciz	gt;
const #80 = NameAndType	#79:#76;//  gt:(Lscala/Ordering;Ljava/lang/Object;Ljava/lang/Object;)Z
const #81 = Method	#27.#80;	//  scala/Ordering$class.gt:(Lscala/Ordering;Ljava/lang/Object;Ljava/lang/Object;)Z
const #82 = Asciz	lt;
const #83 = NameAndType	#82:#76;//  lt:(Lscala/Ordering;Ljava/lang/Object;Ljava/lang/Object;)Z
const #84 = Method	#27.#83;	//  scala/Ordering$class.lt:(Lscala/Ordering;Ljava/lang/Object;Ljava/lang/Object;)Z
const #85 = Asciz	gteq;
const #86 = NameAndType	#85:#76;//  gteq:(Lscala/Ordering;Ljava/lang/Object;Ljava/lang/Object;)Z
const #87 = Method	#27.#86;	//  scala/Ordering$class.gteq:(Lscala/Ordering;Ljava/lang/Object;Ljava/lang/Object;)Z
const #88 = Asciz	lteq;
const #89 = NameAndType	#88:#76;//  lteq:(Lscala/Ordering;Ljava/lang/Object;Ljava/lang/Object;)Z
const #90 = Method	#27.#89;	//  scala/Ordering$class.lteq:(Lscala/Ordering;Ljava/lang/Object;Ljava/lang/Object;)Z
const #91 = Asciz	(Lscala/Ordering$BigDecimalOrdering;Lscala/BigDecimal;Lscala/BigDecimal;)I;
const #92 = NameAndType	#36:#91;//  compare:(Lscala/Ordering$BigDecimalOrdering;Lscala/BigDecimal;Lscala/BigDecimal;)I
const #93 = Method	#32.#92;	//  scala/Ordering$BigDecimalOrdering$class.compare:(Lscala/Ordering$BigDecimalOrdering;Lscala/BigDecimal;Lscala/BigDecimal;)I
const #94 = Asciz	Lscala/BigDecimal;;
const #95 = Asciz	InnerClasses;
const #96 = Asciz	scala/Ordering$Ops;
const #97 = class	#96;	//  scala/Ordering$Ops
const #98 = Asciz	Ops;
const #99 = Asciz	BigDecimalOrdering;
const #100 = Asciz	scala/ScalaObject;
const #101 = class	#100;	//  scala/ScalaObject

{
public static final scala.Ordering$BigDecimal$ MODULE$;

public static {};
  Code:
   Stack=1, Locals=0, Args_size=0
   0:	new	#10; //class scala/Ordering$BigDecimal$
   3:	invokespecial	#13; //Method "<init>":()V
   6:	return

public scala.Ordering$BigDecimal$();
  Code:
   Stack=1, Locals=1, Args_size=1
   0:	aload_0
   1:	invokespecial	#17; //Method java/lang/Object."<init>":()V
   4:	aload_0
   5:	putstatic	#19; //Field MODULE$:Lscala/Ordering$BigDecimal$;
   8:	aload_0
   9:	invokestatic	#25; //Method scala/PartialOrdering$class.$init$:(Lscala/PartialOrdering;)V
   12:	aload_0
   13:	invokestatic	#30; //Method scala/Ordering$class.$init$:(Lscala/Ordering;)V
   16:	aload_0
   17:	invokestatic	#35; //Method scala/Ordering$BigDecimalOrdering$class.$init$:(Lscala/Ordering$BigDecimalOrdering;)V
   20:	return
  LineNumberTable: 
   line 178: 0


public int compare(java.lang.Object, java.lang.Object);
  Code:
   Stack=3, Locals=3, Args_size=3
   0:	aload_0
   1:	aload_1
   2:	checkcast	#39; //class scala/BigDecimal
   5:	aload_2
   6:	checkcast	#39; //class scala/BigDecimal
   9:	invokeinterface	#44,  3; //InterfaceMethod scala/Ordering$BigDecimalOrdering.compare:(Lscala/BigDecimal;Lscala/BigDecimal;)I
   14:	ireturn
  LineNumberTable: 
   line 178: 0

  LocalVariableTable: 
   Start  Length  Slot  Name   Signature
   0      15      0    this       Lscala/Ordering$BigDecimal$;
   0      15      1    x       Ljava/lang/Object;
   0      15      2    y       Ljava/lang/Object;


public scala.PartialOrdering reverse();
  Code:
   Stack=1, Locals=1, Args_size=1
   0:	aload_0
   1:	invokeinterface	#56,  1; //InterfaceMethod scala/Ordering.reverse:()Lscala/Ordering;
   6:	areturn
  LineNumberTable: 
   line 178: 0


public scala.Ordering$Ops mkOrderingOps(java.lang.Object);
  Code:
   Stack=2, Locals=2, Args_size=2
   0:	aload_0
   1:	aload_1
   2:	invokestatic	#61; //Method scala/Ordering$class.mkOrderingOps:(Lscala/Ordering;Ljava/lang/Object;)Lscala/Ordering$Ops;
   5:	areturn
  LineNumberTable: 
   line 178: 0

  LocalVariableTable: 
   Start  Length  Slot  Name   Signature
   0      6      0    this       Lscala/Ordering$BigDecimal$;
   0      6      1    lhs       Ljava/lang/Object;


public scala.Ordering reverse();
  Code:
   Stack=1, Locals=1, Args_size=1
   0:	aload_0
   1:	invokestatic	#65; //Method scala/Ordering$class.reverse:(Lscala/Ordering;)Lscala/Ordering;
   4:	areturn
  LineNumberTable: 
   line 178: 0


public java.lang.Object min(java.lang.Object, java.lang.Object);
  Code:
   Stack=3, Locals=3, Args_size=3
   0:	aload_0
   1:	aload_1
   2:	aload_2
   3:	invokestatic	#70; //Method scala/Ordering$class.min:(Lscala/Ordering;Ljava/lang/Object;Ljava/lang/Object;)Ljava/lang/Object;
   6:	areturn
  LineNumberTable: 
   line 178: 0

  LocalVariableTable: 
   Start  Length  Slot  Name   Signature
   0      7      0    this       Lscala/Ordering$BigDecimal$;
   0      7      1    x       Ljava/lang/Object;
   0      7      2    y       Ljava/lang/Object;


public java.lang.Object max(java.lang.Object, java.lang.Object);
  Code:
   Stack=3, Locals=3, Args_size=3
   0:	aload_0
   1:	aload_1
   2:	aload_2
   3:	invokestatic	#73; //Method scala/Ordering$class.max:(Lscala/Ordering;Ljava/lang/Object;Ljava/lang/Object;)Ljava/lang/Object;
   6:	areturn
  LineNumberTable: 
   line 178: 0

  LocalVariableTable: 
   Start  Length  Slot  Name   Signature
   0      7      0    this       Lscala/Ordering$BigDecimal$;
   0      7      1    x       Ljava/lang/Object;
   0      7      2    y       Ljava/lang/Object;


public boolean equiv(java.lang.Object, java.lang.Object);
  Code:
   Stack=3, Locals=3, Args_size=3
   0:	aload_0
   1:	aload_1
   2:	aload_2
   3:	invokestatic	#78; //Method scala/Ordering$class.equiv:(Lscala/Ordering;Ljava/lang/Object;Ljava/lang/Object;)Z
   6:	ireturn
  LineNumberTable: 
   line 178: 0

  LocalVariableTable: 
   Start  Length  Slot  Name   Signature
   0      7      0    this       Lscala/Ordering$BigDecimal$;
   0      7      1    x       Ljava/lang/Object;
   0      7      2    y       Ljava/lang/Object;


public boolean gt(java.lang.Object, java.lang.Object);
  Code:
   Stack=3, Locals=3, Args_size=3
   0:	aload_0
   1:	aload_1
   2:	aload_2
   3:	invokestatic	#81; //Method scala/Ordering$class.gt:(Lscala/Ordering;Ljava/lang/Object;Ljava/lang/Object;)Z
   6:	ireturn
  LineNumberTable: 
   line 178: 0

  LocalVariableTable: 
   Start  Length  Slot  Name   Signature
   0      7      0    this       Lscala/Ordering$BigDecimal$;
   0      7      1    x       Ljava/lang/Object;
   0      7      2    y       Ljava/lang/Object;


public boolean lt(java.lang.Object, java.lang.Object);
  Code:
   Stack=3, Locals=3, Args_size=3
   0:	aload_0
   1:	aload_1
   2:	aload_2
   3:	invokestatic	#84; //Method scala/Ordering$class.lt:(Lscala/Ordering;Ljava/lang/Object;Ljava/lang/Object;)Z
   6:	ireturn
  LineNumberTable: 
   line 178: 0

  LocalVariableTable: 
   Start  Length  Slot  Name   Signature
   0      7      0    this       Lscala/Ordering$BigDecimal$;
   0      7      1    x       Ljava/lang/Object;
   0      7      2    y       Ljava/lang/Object;


public boolean gteq(java.lang.Object, java.lang.Object);
  Code:
   Stack=3, Locals=3, Args_size=3
   0:	aload_0
   1:	aload_1
   2:	aload_2
   3:	invokestatic	#87; //Method scala/Ordering$class.gteq:(Lscala/Ordering;Ljava/lang/Object;Ljava/lang/Object;)Z
   6:	ireturn
  LineNumberTable: 
   line 178: 0

  LocalVariableTable: 
   Start  Length  Slot  Name   Signature
   0      7      0    this       Lscala/Ordering$BigDecimal$;
   0      7      1    x       Ljava/lang/Object;
   0      7      2    y       Ljava/lang/Object;


public boolean lteq(java.lang.Object, java.lang.Object);
  Code:
   Stack=3, Locals=3, Args_size=3
   0:	aload_0
   1:	aload_1
   2:	aload_2
   3:	invokestatic	#90; //Method scala/Ordering$class.lteq:(Lscala/Ordering;Ljava/lang/Object;Ljava/lang/Object;)Z
   6:	ireturn
  LineNumberTable: 
   line 178: 0

  LocalVariableTable: 
   Start  Length  Slot  Name   Signature
   0      7      0    this       Lscala/Ordering$BigDecimal$;
   0      7      1    x       Ljava/lang/Object;
   0      7      2    y       Ljava/lang/Object;


public int compare(scala.BigDecimal, scala.BigDecimal);
  Code:
   Stack=3, Locals=3, Args_size=3
   0:	aload_0
   1:	aload_1
   2:	aload_2
   3:	invokestatic	#93; //Method scala/Ordering$BigDecimalOrdering$class.compare:(Lscala/Ordering$BigDecimalOrdering;Lscala/BigDecimal;Lscala/BigDecimal;)I
   6:	ireturn
  LineNumberTable: 
   line 178: 0

  LocalVariableTable: 
   Start  Length  Slot  Name   Signature
   0      7      0    this       Lscala/Ordering$BigDecimal$;
   0      7      1    x       Lscala/BigDecimal;
   0      7      2    y       Lscala/BigDecimal;


}

