Compiled from "package.scala"
public final class scala.package$ extends java.lang.Object implements scala.ScalaObject
  SourceFile: "package.scala"
  Scala: length = 0x
   
  minor version: 0
  major version: 49
  Constant pool:
Asciz	SourceFile;
Asciz	package.scala;
Asciz	Scala;
Asciz	MODULE$;
Asciz	Lscala/package$;;
Asciz	<clinit>;
Asciz	()V;
Asciz	Code;
Asciz	scala/package$;
class	scala/package$
Asciz	<init>;
NameAndType	"<init>":()V
Method	scala/package$."<init>":()V
Asciz	RandomAccessSeq;
Asciz	Lscala/collection/IndexedSeq$;;
Asciz	Sequence;
Asciz	Lscala/collection/Seq$;;
Asciz	Collection;
Asciz	Lscala/collection/Iterable$;;
Asciz	Ordering;
Asciz	Lscala/math/Ordering$;;
Asciz	Ordered;
Asciz	Lscala/math/Ordered$;;
Asciz	Numeric;
Asciz	Lscala/math/Numeric$;;
Asciz	BigInt;
Asciz	Lscala/math/BigInt$;;
Asciz	BigDecimal;
Asciz	Lscala/math/BigDecimal$;;
Asciz	$scope;
Asciz	Lscala/xml/TopScope$;;
Asciz	Range;
Asciz	Lscala/collection/immutable/Range$;;
Asciz	StringBuilder;
Asciz	Lscala/collection/mutable/StringBuilder$;;
Asciz	Vector;
Asciz	Lscala/collection/immutable/Vector$;;
Asciz	$hash$colon$colon;
Asciz	Lscala/collection/immutable/Stream$$hash$colon$colon$;;
Asciz	Stream;
Asciz	Lscala/collection/immutable/Stream$;;
Asciz	$colon$colon;
Asciz	Lscala/collection/immutable/$colon$colon$;;
Asciz	Nil;
Asciz	Lscala/collection/immutable/Nil$;;
Asciz	List;
Asciz	Lscala/collection/immutable/List$;;
Asciz	Iterator;
Asciz	Lscala/collection/Iterator$;;
Asciz	IndexedSeq;
Asciz	Seq;
Asciz	Iterable;
Asciz	Traversable;
Asciz	Lscala/collection/Traversable$;;
Asciz	()Lscala/collection/Traversable$;;
Asciz	LineNumberTable;
NameAndType	Traversable:Lscala/collection/Traversable$;
Field	scala/package$.Traversable:Lscala/collection/Traversable$;
Asciz	()Lscala/collection/Iterable$;;
NameAndType	Iterable:Lscala/collection/Iterable$;
Field	scala/package$.Iterable:Lscala/collection/Iterable$;
Asciz	()Lscala/collection/Seq$;;
NameAndType	Seq:Lscala/collection/Seq$;
Field	scala/package$.Seq:Lscala/collection/Seq$;
Asciz	()Lscala/collection/IndexedSeq$;;
NameAndType	IndexedSeq:Lscala/collection/IndexedSeq$;
Field	scala/package$.IndexedSeq:Lscala/collection/IndexedSeq$;
Asciz	()Lscala/collection/Iterator$;;
NameAndType	Iterator:Lscala/collection/Iterator$;
Field	scala/package$.Iterator:Lscala/collection/Iterator$;
Asciz	()Lscala/collection/immutable/List$;;
NameAndType	List:Lscala/collection/immutable/List$;
Field	scala/package$.List:Lscala/collection/immutable/List$;
Asciz	()Lscala/collection/immutable/Nil$;;
NameAndType	Nil:Lscala/collection/immutable/Nil$;
Field	scala/package$.Nil:Lscala/collection/immutable/Nil$;
Asciz	()Lscala/collection/immutable/$colon$colon$;;
NameAndType	$colon$colon:Lscala/collection/immutable/$colon$colon$;
Field	scala/package$.$colon$colon:Lscala/collection/immutable/$colon$colon$;
Asciz	()Lscala/collection/immutable/Stream$;;
NameAndType	Stream:Lscala/collection/immutable/Stream$;
Field	scala/package$.Stream:Lscala/collection/immutable/Stream$;
Asciz	()Lscala/collection/immutable/Stream$$hash$colon$colon$;;
NameAndType	$hash$colon$colon:Lscala/collection/immutable/Stream$$hash$colon$colon$;
Field	scala/package$.$hash$colon$colon:Lscala/collection/immutable/Stream$$hash$colon$colon$;
Asciz	()Lscala/collection/immutable/Vector$;;
NameAndType	Vector:Lscala/collection/immutable/Vector$;
Field	scala/package$.Vector:Lscala/collection/immutable/Vector$;
Asciz	()Lscala/collection/mutable/StringBuilder$;;
NameAndType	StringBuilder:Lscala/collection/mutable/StringBuilder$;
Field	scala/package$.StringBuilder:Lscala/collection/mutable/StringBuilder$;
Asciz	()Lscala/collection/immutable/Range$;;
NameAndType	Range:Lscala/collection/immutable/Range$;
Field	scala/package$.Range:Lscala/collection/immutable/Range$;
Asciz	()Lscala/xml/TopScope$;;
NameAndType	$scope:Lscala/xml/TopScope$;
Field	scala/package$.$scope:Lscala/xml/TopScope$;
Asciz	currentThread;
Asciz	()Ljava/lang/Thread;;
Asciz	java/lang/Thread;
class	java/lang/Thread
NameAndType	currentThread:()Ljava/lang/Thread;
Method	java/lang/Thread.currentThread:()Ljava/lang/Thread;
Asciz	()Lscala/math/BigDecimal$;;
NameAndType	BigDecimal:Lscala/math/BigDecimal$;
Field	scala/package$.BigDecimal:Lscala/math/BigDecimal$;
Asciz	()Lscala/math/BigInt$;;
NameAndType	BigInt:Lscala/math/BigInt$;
Field	scala/package$.BigInt:Lscala/math/BigInt$;
Asciz	()Lscala/math/Numeric$;;
NameAndType	Numeric:Lscala/math/Numeric$;
Field	scala/package$.Numeric:Lscala/math/Numeric$;
Asciz	()Lscala/math/Ordered$;;
NameAndType	Ordered:Lscala/math/Ordered$;
Field	scala/package$.Ordered:Lscala/math/Ordered$;
Asciz	()Lscala/math/Ordering$;;
NameAndType	Ordering:Lscala/math/Ordering$;
Field	scala/package$.Ordering:Lscala/math/Ordering$;
Asciz	Tuple;
Asciz	(Ljava/lang/Object;)Lscala/Tuple1;;
Asciz	scala/Tuple1;
class	scala/Tuple1
Asciz	(Ljava/lang/Object;)V;
NameAndType	"<init>":(Ljava/lang/Object;)V
Method	scala/Tuple1."<init>":(Ljava/lang/Object;)V
Asciz	this;
Asciz	x1;
Asciz	Ljava/lang/Object;;
Asciz	LocalVariableTable;
Asciz	<A1:Ljava/lang/Object;>(TA1;)Lscala/Tuple1<TA1;>;;
Asciz	Signature;
Asciz	Deprecated;
Asciz	(Ljava/lang/Object;Ljava/lang/Object;)Lscala/Tuple2;;
Asciz	scala/Tuple2;
class	scala/Tuple2
Asciz	(Ljava/lang/Object;Ljava/lang/Object;)V;
NameAndType	"<init>":(Ljava/lang/Object;Ljava/lang/Object;)V
Method	scala/Tuple2."<init>":(Ljava/lang/Object;Ljava/lang/Object;)V
Asciz	x2;
Asciz	<A1:Ljava/lang/Object;A2:Ljava/lang/Object;>(TA1;TA2;)Lscala/Tuple2<TA1;TA2;>;;
Asciz	(Ljava/lang/Object;Ljava/lang/Object;Ljava/lang/Object;)Lscala/Tuple3;;
Asciz	scala/Tuple3;
class	scala/Tuple3
Asciz	(Ljava/lang/Object;Ljava/lang/Object;Ljava/lang/Object;)V;
NameAndType	"<init>":(Ljava/lang/Object;Ljava/lang/Object;Ljava/lang/Object;)V
Method	scala/Tuple3."<init>":(Ljava/lang/Object;Ljava/lang/Object;Ljava/lang/Object;)V
Asciz	x3;
Asciz	<A1:Ljava/lang/Object;A2:Ljava/lang/Object;A3:Ljava/lang/Object;>(TA1;TA2;TA3;)Lscala/Tuple3<TA1;TA2;TA3;>;;
Asciz	(Ljava/lang/Object;Ljava/lang/Object;Ljava/lang/Object;Ljava/lang/Object;)Lscala/Tuple4;;
Asciz	scala/Tuple4;
class	scala/Tuple4
Asciz	(Ljava/lang/Object;Ljava/lang/Object;Ljava/lang/Object;Ljava/lang/Object;)V;
NameAndType	"<init>":(Ljava/lang/Object;Ljava/lang/Object;Ljava/lang/Object;Ljava/lang/Object;)V
Method	scala/Tuple4."<init>":(Ljava/lang/Object;Ljava/lang/Object;Ljava/lang/Object;Ljava/lang/Object;)V
Asciz	x4;
Asciz	<A1:Ljava/lang/Object;A2:Ljava/lang/Object;A3:Ljava/lang/Object;A4:Ljava/lang/Object;>(TA1;TA2;TA3;TA4;)Lscala/Tuple4<TA1;TA2;TA3;TA4;>;;
Asciz	(Ljava/lang/Object;Ljava/lang/Object;Ljava/lang/Object;Ljava/lang/Object;Ljava/lang/Object;)Lscala/Tuple5;;
Asciz	scala/Tuple5;
class	scala/Tuple5
Asciz	(Ljava/lang/Object;Ljava/lang/Object;Ljava/lang/Object;Ljava/lang/Object;Ljava/lang/Object;)V;
NameAndType	"<init>":(Ljava/lang/Object;Ljava/lang/Object;Ljava/lang/Object;Ljava/lang/Object;Ljava/lang/Object;)V
Method	scala/Tuple5."<init>":(Ljava/lang/Object;Ljava/lang/Object;Ljava/lang/Object;Ljava/lang/Object;Ljava/lang/Object;)V
Asciz	x5;
Asciz	<A1:Ljava/lang/Object;A2:Ljava/lang/Object;A3:Ljava/lang/Object;A4:Ljava/lang/Object;A5:Ljava/lang/Object;>(TA1;TA2;TA3;TA4;TA5;)Lscala/Tuple5<TA1;TA2;TA3;TA4;TA5;>;;
Asciz	(Ljava/lang/Object;Ljava/lang/Object;Ljava/lang/Object;Ljava/lang/Object;Ljava/lang/Object;Ljava/lang/Object;)Lscala/Tuple6;;
Asciz	scala/Tuple6;
class	scala/Tuple6
Asciz	(Ljava/lang/Object;Ljava/lang/Object;Ljava/lang/Object;Ljava/lang/Object;Ljava/lang/Object;Ljava/lang/Object;)V;
NameAndType	"<init>":(Ljava/lang/Object;Ljava/lang/Object;Ljava/lang/Object;Ljava/lang/Object;Ljava/lang/Object;Ljava/lang/Object;)V
Method	scala/Tuple6."<init>":(Ljava/lang/Object;Ljava/lang/Object;Ljava/lang/Object;Ljava/lang/Object;Ljava/lang/Object;Ljava/lang/Object;)V
Asciz	x6;
Asciz	<A1:Ljava/lang/Object;A2:Ljava/lang/Object;A3:Ljava/lang/Object;A4:Ljava/lang/Object;A5:Ljava/lang/Object;A6:Ljava/lang/Object;>(TA1;TA2;TA3;TA4;TA5;TA6;)Lscala/Tuple6<TA1;TA2;TA3;TA4;TA5;TA6;>;;
Asciz	(Ljava/lang/Object;Ljava/lang/Object;Ljava/lang/Object;Ljava/lang/Object;Ljava/lang/Object;Ljava/lang/Object;Ljava/lang/Object;)Lscala/Tuple7;;
Asciz	scala/Tuple7;
class	scala/Tuple7
Asciz	(Ljava/lang/Object;Ljava/lang/Object;Ljava/lang/Object;Ljava/lang/Object;Ljava/lang/Object;Ljava/lang/Object;Ljava/lang/Object;)V;
NameAndType	"<init>":(Ljava/lang/Object;Ljava/lang/Object;Ljava/lang/Object;Ljava/lang/Object;Ljava/lang/Object;Ljava/lang/Object;Ljava/lang/Object;)V
Method	scala/Tuple7."<init>":(Ljava/lang/Object;Ljava/lang/Object;Ljava/lang/Object;Ljava/lang/Object;Ljava/lang/Object;Ljava/lang/Object;Ljava/lang/Object;)V
Asciz	x7;
Asciz	<A1:Ljava/lang/Object;A2:Ljava/lang/Object;A3:Ljava/lang/Object;A4:Ljava/lang/Object;A5:Ljava/lang/Object;A6:Ljava/lang/Object;A7:Ljava/lang/Object;>(TA1;TA2;TA3;TA4;TA5;TA6;TA7;)Lscala/Tuple7<TA1;TA2;TA3;TA4;TA5;TA6;TA7;>;;
Asciz	(Ljava/lang/Object;Ljava/lang/Object;Ljava/lang/Object;Ljava/lang/Object;Ljava/lang/Object;Ljava/lang/Object;Ljava/lang/Object;Ljava/lang/Object;)Lscala/Tuple8;;
Asciz	scala/Tuple8;
class	scala/Tuple8
Asciz	(Ljava/lang/Object;Ljava/lang/Object;Ljava/lang/Object;Ljava/lang/Object;Ljava/lang/Object;Ljava/lang/Object;Ljava/lang/Object;Ljava/lang/Object;)V;
NameAndType	"<init>":(Ljava/lang/Object;Ljava/lang/Object;Ljava/lang/Object;Ljava/lang/Object;Ljava/lang/Object;Ljava/lang/Object;Ljava/lang/Object;Ljava/lang/Object;)V
Method	scala/Tuple8."<init>":(Ljava/lang/Object;Ljava/lang/Object;Ljava/lang/Object;Ljava/lang/Object;Ljava/lang/Object;Ljava/lang/Object;Ljava/lang/Object;Ljava/lang/Object;)V
Asciz	x8;
Asciz	<A1:Ljava/lang/Object;A2:Ljava/lang/Object;A3:Ljava/lang/Object;A4:Ljava/lang/Object;A5:Ljava/lang/Object;A6:Ljava/lang/Object;A7:Ljava/lang/Object;A8:Ljava/lang/Object;>(TA1;TA2;TA3;TA4;TA5;TA6;TA7;TA8;)Lscala/Tuple8<TA1;TA2;TA3;TA4;TA5;TA6;TA7;TA8;>;;
Asciz	(Ljava/lang/Object;Ljava/lang/Object;Ljava/lang/Object;Ljava/lang/Object;Ljava/lang/Object;Ljava/lang/Object;Ljava/lang/Object;Ljava/lang/Object;Ljava/lang/Object;)Lscala/Tuple9;;
Asciz	scala/Tuple9;
class	scala/Tuple9
Asciz	(Ljava/lang/Object;Ljava/lang/Object;Ljava/lang/Object;Ljava/lang/Object;Ljava/lang/Object;Ljava/lang/Object;Ljava/lang/Object;Ljava/lang/Object;Ljava/lang/Object;)V;
NameAndType	"<init>":(Ljava/lang/Object;Ljava/lang/Object;Ljava/lang/Object;Ljava/lang/Object;Ljava/lang/Object;Ljava/lang/Object;Ljava/lang/Object;Ljava/lang/Object;Ljava/lang/Object;)V
Method	scala/Tuple9."<init>":(Ljava/lang/Object;Ljava/lang/Object;Ljava/lang/Object;Ljava/lang/Object;Ljava/lang/Object;Ljava/lang/Object;Ljava/lang/Object;Ljava/lang/Object;Ljava/lang/Object;)V
Asciz	x9;
Asciz	<A1:Ljava/lang/Object;A2:Ljava/lang/Object;A3:Ljava/lang/Object;A4:Ljava/lang/Object;A5:Ljava/lang/Object;A6:Ljava/lang/Object;A7:Ljava/lang/Object;A8:Ljava/lang/Object;A9:Ljava/lang/Object;>(TA1;TA2;TA3;TA4;TA5;TA6;TA7;TA8;TA9;)Lscala/Tuple9<TA1;TA2;TA3;TA4;TA5;TA6;TA7;TA8;TA9;>;;
Asciz	(Ljava/lang/Object;Ljava/lang/Object;Ljava/lang/Object;Ljava/lang/Object;Ljava/lang/Object;Ljava/lang/Object;Ljava/lang/Object;Ljava/lang/Object;Ljava/lang/Object;Ljava/lang/Object;)Lscala/Tuple10;;
Asciz	scala/Tuple10;
class	scala/Tuple10
Asciz	(Ljava/lang/Object;Ljava/lang/Object;Ljava/lang/Object;Ljava/lang/Object;Ljava/lang/Object;Ljava/lang/Object;Ljava/lang/Object;Ljava/lang/Object;Ljava/lang/Object;Ljava/lang/Object;)V;
NameAndType	"<init>":(Ljava/lang/Object;Ljava/lang/Object;Ljava/lang/Object;Ljava/lang/Object;Ljava/lang/Object;Ljava/lang/Object;Ljava/lang/Object;Ljava/lang/Object;Ljava/lang/Object;Ljava/lang/Object;)V
Method	scala/Tuple10."<init>":(Ljava/lang/Object;Ljava/lang/Object;Ljava/lang/Object;Ljava/lang/Object;Ljava/lang/Object;Ljava/lang/Object;Ljava/lang/Object;Ljava/lang/Object;Ljava/lang/Object;Ljava/lang/Object;)V
Asciz	x10;
Asciz	<A1:Ljava/lang/Object;A2:Ljava/lang/Object;A3:Ljava/lang/Object;A4:Ljava/lang/Object;A5:Ljava/lang/Object;A6:Ljava/lang/Object;A7:Ljava/lang/Object;A8:Ljava/lang/Object;A9:Ljava/lang/Object;A10:Ljava/lang/Object;>(TA1;TA2;TA3;TA4;TA5;TA6;TA7;TA8;TA9;TA10;)Lscala/Tuple10<TA1;TA2;TA3;TA4;TA5;TA6;TA7;TA8;TA9;TA10;>;;
Asciz	(Ljava/lang/Object;Ljava/lang/Object;Ljava/lang/Object;Ljava/lang/Object;Ljava/lang/Object;Ljava/lang/Object;Ljava/lang/Object;Ljava/lang/Object;Ljava/lang/Object;Ljava/lang/Object;Ljava/lang/Object;)Lscala/Tuple11;;
Asciz	scala/Tuple11;
class	scala/Tuple11
Asciz	(Ljava/lang/Object;Ljava/lang/Object;Ljava/lang/Object;Ljava/lang/Object;Ljava/lang/Object;Ljava/lang/Object;Ljava/lang/Object;Ljava/lang/Object;Ljava/lang/Object;Ljava/lang/Object;Ljava/lang/Object;)V;
NameAndType	"<init>":(Ljava/lang/Object;Ljava/lang/Object;Ljava/lang/Object;Ljava/lang/Object;Ljava/lang/Object;Ljava/lang/Object;Ljava/lang/Object;Ljava/lang/Object;Ljava/lang/Object;Ljava/lang/Object;Ljava/lang/Object;)V
Method	scala/Tuple11."<init>":(Ljava/lang/Object;Ljava/lang/Object;Ljava/lang/Object;Ljava/lang/Object;Ljava/lang/Object;Ljava/lang/Object;Ljava/lang/Object;Ljava/lang/Object;Ljava/lang/Object;Ljava/lang/Object;Ljava/lang/Object;)V
Asciz	x11;
Asciz	<A1:Ljava/lang/Object;A2:Ljava/lang/Object;A3:Ljava/lang/Object;A4:Ljava/lang/Object;A5:Ljava/lang/Object;A6:Ljava/lang/Object;A7:Ljava/lang/Object;A8:Ljava/lang/Object;A9:Ljava/lang/Object;A10:Ljava/lang/Object;A11:Ljava/lang/Object;>(TA1;TA2;TA3;TA4;TA5;TA6;TA7;TA8;TA9;TA10;TA11;)Lscala/Tuple11<TA1;TA2;TA3;TA4;TA5;TA6;TA7;TA8;TA9;TA10;TA11;>;;
Asciz	(Ljava/lang/Object;Ljava/lang/Object;Ljava/lang/Object;Ljava/lang/Object;Ljava/lang/Object;Ljava/lang/Object;Ljava/lang/Object;Ljava/lang/Object;Ljava/lang/Object;Ljava/lang/Object;Ljava/lang/Object;Ljava/lang/Object;)Lscala/Tuple12;;
Asciz	scala/Tuple12;
class	scala/Tuple12
Asciz	(Ljava/lang/Object;Ljava/lang/Object;Ljava/lang/Object;Ljava/lang/Object;Ljava/lang/Object;Ljava/lang/Object;Ljava/lang/Object;Ljava/lang/Object;Ljava/lang/Object;Ljava/lang/Object;Ljava/lang/Object;Ljava/lang/Object;)V;
NameAndType	"<init>":(Ljava/lang/Object;Ljava/lang/Object;Ljava/lang/Object;Ljava/lang/Object;Ljava/lang/Object;Ljava/lang/Object;Ljava/lang/Object;Ljava/lang/Object;Ljava/lang/Object;Ljava/lang/Object;Ljava/lang/Object;Ljava/lang/Object;)V
Method	scala/Tuple12."<init>":(Ljava/lang/Object;Ljava/lang/Object;Ljava/lang/Object;Ljava/lang/Object;Ljava/lang/Object;Ljava/lang/Object;Ljava/lang/Object;Ljava/lang/Object;Ljava/lang/Object;Ljava/lang/Object;Ljava/lang/Object;Ljava/lang/Object;)V
Asciz	x12;
Asciz	<A1:Ljava/lang/Object;A2:Ljava/lang/Object;A3:Ljava/lang/Object;A4:Ljava/lang/Object;A5:Ljava/lang/Object;A6:Ljava/lang/Object;A7:Ljava/lang/Object;A8:Ljava/lang/Object;A9:Ljava/lang/Object;A10:Ljava/lang/Object;A11:Ljava/lang/Object;A12:Ljava/lang/Object;>(TA1;TA2;TA3;TA4;TA5;TA6;TA7;TA8;TA9;TA10;TA11;TA12;)Lscala/Tuple12<TA1;TA2;TA3;TA4;TA5;TA6;TA7;TA8;TA9;TA10;TA11;TA12;>;;
Asciz	(Ljava/lang/Object;Ljava/lang/Object;Ljava/lang/Object;Ljava/lang/Object;Ljava/lang/Object;Ljava/lang/Object;Ljava/lang/Object;Ljava/lang/Object;Ljava/lang/Object;Ljava/lang/Object;Ljava/lang/Object;Ljava/lang/Object;Ljava/lang/Object;)Lscala/Tuple13;;
Asciz	scala/Tuple13;
class	scala/Tuple13
Asciz	(Ljava/lang/Object;Ljava/lang/Object;Ljava/lang/Object;Ljava/lang/Object;Ljava/lang/Object;Ljava/lang/Object;Ljava/lang/Object;Ljava/lang/Object;Ljava/lang/Object;Ljava/lang/Object;Ljava/lang/Object;Ljava/lang/Object;Ljava/lang/Object;)V;
NameAndType	"<init>":(Ljava/lang/Object;Ljava/lang/Object;Ljava/lang/Object;Ljava/lang/Object;Ljava/lang/Object;Ljava/lang/Object;Ljava/lang/Object;Ljava/lang/Object;Ljava/lang/Object;Ljava/lang/Object;Ljava/lang/Object;Ljava/lang/Object;Ljava/lang/Object;)V
Method	scala/Tuple13."<init>":(Ljava/lang/Object;Ljava/lang/Object;Ljava/lang/Object;Ljava/lang/Object;Ljava/lang/Object;Ljava/lang/Object;Ljava/lang/Object;Ljava/lang/Object;Ljava/lang/Object;Ljava/lang/Object;Ljava/lang/Object;Ljava/lang/Object;Ljava/lang/Object;)V
Asciz	x13;
Asciz	<A1:Ljava/lang/Object;A2:Ljava/lang/Object;A3:Ljava/lang/Object;A4:Ljava/lang/Object;A5:Ljava/lang/Object;A6:Ljava/lang/Object;A7:Ljava/lang/Object;A8:Ljava/lang/Object;A9:Ljava/lang/Object;A10:Ljava/lang/Object;A11:Ljava/lang/Object;A12:Ljava/lang/Object;A13:Ljava/lang/Object;>(TA1;TA2;TA3;TA4;TA5;TA6;TA7;TA8;TA9;TA10;TA11;TA12;TA13;)Lscala/Tuple13<TA1;TA2;TA3;TA4;TA5;TA6;TA7;TA8;TA9;TA10;TA11;TA12;TA13;>;;
Asciz	(Ljava/lang/Object;Ljava/lang/Object;Ljava/lang/Object;Ljava/lang/Object;Ljava/lang/Object;Ljava/lang/Object;Ljava/lang/Object;Ljava/lang/Object;Ljava/lang/Object;Ljava/lang/Object;Ljava/lang/Object;Ljava/lang/Object;Ljava/lang/Object;Ljava/lang/Object;)Lscala/Tuple14;;
Asciz	scala/Tuple14;
class	scala/Tuple14
Asciz	(Ljava/lang/Object;Ljava/lang/Object;Ljava/lang/Object;Ljava/lang/Object;Ljava/lang/Object;Ljava/lang/Object;Ljava/lang/Object;Ljava/lang/Object;Ljava/lang/Object;Ljava/lang/Object;Ljava/lang/Object;Ljava/lang/Object;Ljava/lang/Object;Ljava/lang/Object;)V;
NameAndType	"<init>":(Ljava/lang/Object;Ljava/lang/Object;Ljava/lang/Object;Ljava/lang/Object;Ljava/lang/Object;Ljava/lang/Object;Ljava/lang/Object;Ljava/lang/Object;Ljava/lang/Object;Ljava/lang/Object;Ljava/lang/Object;Ljava/lang/Object;Ljava/lang/Object;Ljava/lang/Object;)V
Method	scala/Tuple14."<init>":(Ljava/lang/Object;Ljava/lang/Object;Ljava/lang/Object;Ljava/lang/Object;Ljava/lang/Object;Ljava/lang/Object;Ljava/lang/Object;Ljava/lang/Object;Ljava/lang/Object;Ljava/lang/Object;Ljava/lang/Object;Ljava/lang/Object;Ljava/lang/Object;Ljava/lang/Object;)V
Asciz	x14;
Asciz	<A1:Ljava/lang/Object;A2:Ljava/lang/Object;A3:Ljava/lang/Object;A4:Ljava/lang/Object;A5:Ljava/lang/Object;A6:Ljava/lang/Object;A7:Ljava/lang/Object;A8:Ljava/lang/Object;A9:Ljava/lang/Object;A10:Ljava/lang/Object;A11:Ljava/lang/Object;A12:Ljava/lang/Object;A13:Ljava/lang/Object;A14:Ljava/lang/Object;>(TA1;TA2;TA3;TA4;TA5;TA6;TA7;TA8;TA9;TA10;TA11;TA12;TA13;TA14;)Lscala/Tuple14<TA1;TA2;TA3;TA4;TA5;TA6;TA7;TA8;TA9;TA10;TA11;TA12;TA13;TA14;>;;
Asciz	(Ljava/lang/Object;Ljava/lang/Object;Ljava/lang/Object;Ljava/lang/Object;Ljava/lang/Object;Ljava/lang/Object;Ljava/lang/Object;Ljava/lang/Object;Ljava/lang/Object;Ljava/lang/Object;Ljava/lang/Object;Ljava/lang/Object;Ljava/lang/Object;Ljava/lang/Object;Ljava/lang/Object;)Lscala/Tuple15;;
Asciz	scala/Tuple15;
class	scala/Tuple15
Asciz	(Ljava/lang/Object;Ljava/lang/Object;Ljava/lang/Object;Ljava/lang/Object;Ljava/lang/Object;Ljava/lang/Object;Ljava/lang/Object;Ljava/lang/Object;Ljava/lang/Object;Ljava/lang/Object;Ljava/lang/Object;Ljava/lang/Object;Ljava/lang/Object;Ljava/lang/Object;Ljava/lang/Object;)V;
NameAndType	"<init>":(Ljava/lang/Object;Ljava/lang/Object;Ljava/lang/Object;Ljava/lang/Object;Ljava/lang/Object;Ljava/lang/Object;Ljava/lang/Object;Ljava/lang/Object;Ljava/lang/Object;Ljava/lang/Object;Ljava/lang/Object;Ljava/lang/Object;Ljava/lang/Object;Ljava/lang/Object;Ljava/lang/Object;)V
Method	scala/Tuple15."<init>":(Ljava/lang/Object;Ljava/lang/Object;Ljava/lang/Object;Ljava/lang/Object;Ljava/lang/Object;Ljava/lang/Object;Ljava/lang/Object;Ljava/lang/Object;Ljava/lang/Object;Ljava/lang/Object;Ljava/lang/Object;Ljava/lang/Object;Ljava/lang/Object;Ljava/lang/Object;Ljava/lang/Object;)V
Asciz	x15;
Asciz	<A1:Ljava/lang/Object;A2:Ljava/lang/Object;A3:Ljava/lang/Object;A4:Ljava/lang/Object;A5:Ljava/lang/Object;A6:Ljava/lang/Object;A7:Ljava/lang/Object;A8:Ljava/lang/Object;A9:Ljava/lang/Object;A10:Ljava/lang/Object;A11:Ljava/lang/Object;A12:Ljava/lang/Object;A13:Ljava/lang/Object;A14:Ljava/lang/Object;A15:Ljava/lang/Object;>(TA1;TA2;TA3;TA4;TA5;TA6;TA7;TA8;TA9;TA10;TA11;TA12;TA13;TA14;TA15;)Lscala/Tuple15<TA1;TA2;TA3;TA4;TA5;TA6;TA7;TA8;TA9;TA10;TA11;TA12;TA13;TA14;TA15;>;;
Asciz	(Ljava/lang/Object;Ljava/lang/Object;Ljava/lang/Object;Ljava/lang/Object;Ljava/lang/Object;Ljava/lang/Object;Ljava/lang/Object;Ljava/lang/Object;Ljava/lang/Object;Ljava/lang/Object;Ljava/lang/Object;Ljava/lang/Object;Ljava/lang/Object;Ljava/lang/Object;Ljava/lang/Object;Ljava/lang/Object;)Lscala/Tuple16;;
Asciz	scala/Tuple16;
class	scala/Tuple16
Asciz	(Ljava/lang/Object;Ljava/lang/Object;Ljava/lang/Object;Ljava/lang/Object;Ljava/lang/Object;Ljava/lang/Object;Ljava/lang/Object;Ljava/lang/Object;Ljava/lang/Object;Ljava/lang/Object;Ljava/lang/Object;Ljava/lang/Object;Ljava/lang/Object;Ljava/lang/Object;Ljava/lang/Object;Ljava/lang/Object;)V;
NameAndType	"<init>":(Ljava/lang/Object;Ljava/lang/Object;Ljava/lang/Object;Ljava/lang/Object;Ljava/lang/Object;Ljava/lang/Object;Ljava/lang/Object;Ljava/lang/Object;Ljava/lang/Object;Ljava/lang/Object;Ljava/lang/Object;Ljava/lang/Object;Ljava/lang/Object;Ljava/lang/Object;Ljava/lang/Object;Ljava/lang/Object;)V
Method	scala/Tuple16."<init>":(Ljava/lang/Object;Ljava/lang/Object;Ljava/lang/Object;Ljava/lang/Object;Ljava/lang/Object;Ljava/lang/Object;Ljava/lang/Object;Ljava/lang/Object;Ljava/lang/Object;Ljava/lang/Object;Ljava/lang/Object;Ljava/lang/Object;Ljava/lang/Object;Ljava/lang/Object;Ljava/lang/Object;Ljava/lang/Object;)V
Asciz	x16;
Asciz	<A1:Ljava/lang/Object;A2:Ljava/lang/Object;A3:Ljava/lang/Object;A4:Ljava/lang/Object;A5:Ljava/lang/Object;A6:Ljava/lang/Object;A7:Ljava/lang/Object;A8:Ljava/lang/Object;A9:Ljava/lang/Object;A10:Ljava/lang/Object;A11:Ljava/lang/Object;A12:Ljava/lang/Object;A13:Ljava/lang/Object;A14:Ljava/lang/Object;A15:Ljava/lang/Object;A16:Ljava/lang/Object;>(TA1;TA2;TA3;TA4;TA5;TA6;TA7;TA8;TA9;TA10;TA11;TA12;TA13;TA14;TA15;TA16;)Lscala/Tuple16<TA1;TA2;TA3;TA4;TA5;TA6;TA7;TA8;TA9;TA10;TA11;TA12;TA13;TA14;TA15;TA16;>;;
Asciz	(Ljava/lang/Object;Ljava/lang/Object;Ljava/lang/Object;Ljava/lang/Object;Ljava/lang/Object;Ljava/lang/Object;Ljava/lang/Object;Ljava/lang/Object;Ljava/lang/Object;Ljava/lang/Object;Ljava/lang/Object;Ljava/lang/Object;Ljava/lang/Object;Ljava/lang/Object;Ljava/lang/Object;Ljava/lang/Object;Ljava/lang/Object;)Lscala/Tuple17;;
Asciz	scala/Tuple17;
class	scala/Tuple17
Asciz	(Ljava/lang/Object;Ljava/lang/Object;Ljava/lang/Object;Ljava/lang/Object;Ljava/lang/Object;Ljava/lang/Object;Ljava/lang/Object;Ljava/lang/Object;Ljava/lang/Object;Ljava/lang/Object;Ljava/lang/Object;Ljava/lang/Object;Ljava/lang/Object;Ljava/lang/Object;Ljava/lang/Object;Ljava/lang/Object;Ljava/lang/Object;)V;
NameAndType	"<init>":(Ljava/lang/Object;Ljava/lang/Object;Ljava/lang/Object;Ljava/lang/Object;Ljava/lang/Object;Ljava/lang/Object;Ljava/lang/Object;Ljava/lang/Object;Ljava/lang/Object;Ljava/lang/Object;Ljava/lang/Object;Ljava/lang/Object;Ljava/lang/Object;Ljava/lang/Object;Ljava/lang/Object;Ljava/lang/Object;Ljava/lang/Object;)V
Method	scala/Tuple17."<init>":(Ljava/lang/Object;Ljava/lang/Object;Ljava/lang/Object;Ljava/lang/Object;Ljava/lang/Object;Ljava/lang/Object;Ljava/lang/Object;Ljava/lang/Object;Ljava/lang/Object;Ljava/lang/Object;Ljava/lang/Object;Ljava/lang/Object;Ljava/lang/Object;Ljava/lang/Object;Ljava/lang/Object;Ljava/lang/Object;Ljava/lang/Object;)V
Asciz	x17;
Asciz	<A1:Ljava/lang/Object;A2:Ljava/lang/Object;A3:Ljava/lang/Object;A4:Ljava/lang/Object;A5:Ljava/lang/Object;A6:Ljava/lang/Object;A7:Ljava/lang/Object;A8:Ljava/lang/Object;A9:Ljava/lang/Object;A10:Ljava/lang/Object;A11:Ljava/lang/Object;A12:Ljava/lang/Object;A13:Ljava/lang/Object;A14:Ljava/lang/Object;A15:Ljava/lang/Object;A16:Ljava/lang/Object;A17:Ljava/lang/Object;>(TA1;TA2;TA3;TA4;TA5;TA6;TA7;TA8;TA9;TA10;TA11;TA12;TA13;TA14;TA15;TA16;TA17;)Lscala/Tuple17<TA1;TA2;TA3;TA4;TA5;TA6;TA7;TA8;TA9;TA10;TA11;TA12;TA13;TA14;TA15;TA16;TA17;>;;
Asciz	(Ljava/lang/Object;Ljava/lang/Object;Ljava/lang/Object;Ljava/lang/Object;Ljava/lang/Object;Ljava/lang/Object;Ljava/lang/Object;Ljava/lang/Object;Ljava/lang/Object;Ljava/lang/Object;Ljava/lang/Object;Ljava/lang/Object;Ljava/lang/Object;Ljava/lang/Object;Ljava/lang/Object;Ljava/lang/Object;Ljava/lang/Object;Ljava/lang/Object;)Lscala/Tuple18;;
Asciz	scala/Tuple18;
class	scala/Tuple18
Asciz	(Ljava/lang/Object;Ljava/lang/Object;Ljava/lang/Object;Ljava/lang/Object;Ljava/lang/Object;Ljava/lang/Object;Ljava/lang/Object;Ljava/lang/Object;Ljava/lang/Object;Ljava/lang/Object;Ljava/lang/Object;Ljava/lang/Object;Ljava/lang/Object;Ljava/lang/Object;Ljava/lang/Object;Ljava/lang/Object;Ljava/lang/Object;Ljava/lang/Object;)V;
NameAndType	"<init>":(Ljava/lang/Object;Ljava/lang/Object;Ljava/lang/Object;Ljava/lang/Object;Ljava/lang/Object;Ljava/lang/Object;Ljava/lang/Object;Ljava/lang/Object;Ljava/lang/Object;Ljava/lang/Object;Ljava/lang/Object;Ljava/lang/Object;Ljava/lang/Object;Ljava/lang/Object;Ljava/lang/Object;Ljava/lang/Object;Ljava/lang/Object;Ljava/lang/Object;)V
Method	scala/Tuple18."<init>":(Ljava/lang/Object;Ljava/lang/Object;Ljava/lang/Object;Ljava/lang/Object;Ljava/lang/Object;Ljava/lang/Object;Ljava/lang/Object;Ljava/lang/Object;Ljava/lang/Object;Ljava/lang/Object;Ljava/lang/Object;Ljava/lang/Object;Ljava/lang/Object;Ljava/lang/Object;Ljava/lang/Object;Ljava/lang/Object;Ljava/lang/Object;Ljava/lang/Object;)V
Asciz	x18;
Asciz	<A1:Ljava/lang/Object;A2:Ljava/lang/Object;A3:Ljava/lang/Object;A4:Ljava/lang/Object;A5:Ljava/lang/Object;A6:Ljava/lang/Object;A7:Ljava/lang/Object;A8:Ljava/lang/Object;A9:Ljava/lang/Object;A10:Ljava/lang/Object;A11:Ljava/lang/Object;A12:Ljava/lang/Object;A13:Ljava/lang/Object;A14:Ljava/lang/Object;A15:Ljava/lang/Object;A16:Ljava/lang/Object;A17:Ljava/lang/Object;A18:Ljava/lang/Object;>(TA1;TA2;TA3;TA4;TA5;TA6;TA7;TA8;TA9;TA10;TA11;TA12;TA13;TA14;TA15;TA16;TA17;TA18;)Lscala/Tuple18<TA1;TA2;TA3;TA4;TA5;TA6;TA7;TA8;TA9;TA10;TA11;TA12;TA13;TA14;TA15;TA16;TA17;TA18;>;;
Asciz	(Ljava/lang/Object;Ljava/lang/Object;Ljava/lang/Object;Ljava/lang/Object;Ljava/lang/Object;Ljava/lang/Object;Ljava/lang/Object;Ljava/lang/Object;Ljava/lang/Object;Ljava/lang/Object;Ljava/lang/Object;Ljava/lang/Object;Ljava/lang/Object;Ljava/lang/Object;Ljava/lang/Object;Ljava/lang/Object;Ljava/lang/Object;Ljava/lang/Object;Ljava/lang/Object;)Lscala/Tuple19;;
Asciz	scala/Tuple19;
class	scala/Tuple19
Asciz	(Ljava/lang/Object;Ljava/lang/Object;Ljava/lang/Object;Ljava/lang/Object;Ljava/lang/Object;Ljava/lang/Object;Ljava/lang/Object;Ljava/lang/Object;Ljava/lang/Object;Ljava/lang/Object;Ljava/lang/Object;Ljava/lang/Object;Ljava/lang/Object;Ljava/lang/Object;Ljava/lang/Object;Ljava/lang/Object;Ljava/lang/Object;Ljava/lang/Object;Ljava/lang/Object;)V;
NameAndType	"<init>":(Ljava/lang/Object;Ljava/lang/Object;Ljava/lang/Object;Ljava/lang/Object;Ljava/lang/Object;Ljava/lang/Object;Ljava/lang/Object;Ljava/lang/Object;Ljava/lang/Object;Ljava/lang/Object;Ljava/lang/Object;Ljava/lang/Object;Ljava/lang/Object;Ljava/lang/Object;Ljava/lang/Object;Ljava/lang/Object;Ljava/lang/Object;Ljava/lang/Object;Ljava/lang/Object;)V
Method	scala/Tuple19."<init>":(Ljava/lang/Object;Ljava/lang/Object;Ljava/lang/Object;Ljava/lang/Object;Ljava/lang/Object;Ljava/lang/Object;Ljava/lang/Object;Ljava/lang/Object;Ljava/lang/Object;Ljava/lang/Object;Ljava/lang/Object;Ljava/lang/Object;Ljava/lang/Object;Ljava/lang/Object;Ljava/lang/Object;Ljava/lang/Object;Ljava/lang/Object;Ljava/lang/Object;Ljava/lang/Object;)V
Asciz	x19;
Asciz	<A1:Ljava/lang/Object;A2:Ljava/lang/Object;A3:Ljava/lang/Object;A4:Ljava/lang/Object;A5:Ljava/lang/Object;A6:Ljava/lang/Object;A7:Ljava/lang/Object;A8:Ljava/lang/Object;A9:Ljava/lang/Object;A10:Ljava/lang/Object;A11:Ljava/lang/Object;A12:Ljava/lang/Object;A13:Ljava/lang/Object;A14:Ljava/lang/Object;A15:Ljava/lang/Object;A16:Ljava/lang/Object;A17:Ljava/lang/Object;A18:Ljava/lang/Object;A19:Ljava/lang/Object;>(TA1;TA2;TA3;TA4;TA5;TA6;TA7;TA8;TA9;TA10;TA11;TA12;TA13;TA14;TA15;TA16;TA17;TA18;TA19;)Lscala/Tuple19<TA1;TA2;TA3;TA4;TA5;TA6;TA7;TA8;TA9;TA10;TA11;TA12;TA13;TA14;TA15;TA16;TA17;TA18;TA19;>;;
Asciz	(Ljava/lang/Object;Ljava/lang/Object;Ljava/lang/Object;Ljava/lang/Object;Ljava/lang/Object;Ljava/lang/Object;Ljava/lang/Object;Ljava/lang/Object;Ljava/lang/Object;Ljava/lang/Object;Ljava/lang/Object;Ljava/lang/Object;Ljava/lang/Object;Ljava/lang/Object;Ljava/lang/Object;Ljava/lang/Object;Ljava/lang/Object;Ljava/lang/Object;Ljava/lang/Object;Ljava/lang/Object;)Lscala/Tuple20;;
Asciz	scala/Tuple20;
class	scala/Tuple20
Asciz	(Ljava/lang/Object;Ljava/lang/Object;Ljava/lang/Object;Ljava/lang/Object;Ljava/lang/Object;Ljava/lang/Object;Ljava/lang/Object;Ljava/lang/Object;Ljava/lang/Object;Ljava/lang/Object;Ljava/lang/Object;Ljava/lang/Object;Ljava/lang/Object;Ljava/lang/Object;Ljava/lang/Object;Ljava/lang/Object;Ljava/lang/Object;Ljava/lang/Object;Ljava/lang/Object;Ljava/lang/Object;)V;
NameAndType	"<init>":(Ljava/lang/Object;Ljava/lang/Object;Ljava/lang/Object;Ljava/lang/Object;Ljava/lang/Object;Ljava/lang/Object;Ljava/lang/Object;Ljava/lang/Object;Ljava/lang/Object;Ljava/lang/Object;Ljava/lang/Object;Ljava/lang/Object;Ljava/lang/Object;Ljava/lang/Object;Ljava/lang/Object;Ljava/lang/Object;Ljava/lang/Object;Ljava/lang/Object;Ljava/lang/Object;Ljava/lang/Object;)V
Method	scala/Tuple20."<init>":(Ljava/lang/Object;Ljava/lang/Object;Ljava/lang/Object;Ljava/lang/Object;Ljava/lang/Object;Ljava/lang/Object;Ljava/lang/Object;Ljava/lang/Object;Ljava/lang/Object;Ljava/lang/Object;Ljava/lang/Object;Ljava/lang/Object;Ljava/lang/Object;Ljava/lang/Object;Ljava/lang/Object;Ljava/lang/Object;Ljava/lang/Object;Ljava/lang/Object;Ljava/lang/Object;Ljava/lang/Object;)V
Asciz	x20;
Asciz	<A1:Ljava/lang/Object;A2:Ljava/lang/Object;A3:Ljava/lang/Object;A4:Ljava/lang/Object;A5:Ljava/lang/Object;A6:Ljava/lang/Object;A7:Ljava/lang/Object;A8:Ljava/lang/Object;A9:Ljava/lang/Object;A10:Ljava/lang/Object;A11:Ljava/lang/Object;A12:Ljava/lang/Object;A13:Ljava/lang/Object;A14:Ljava/lang/Object;A15:Ljava/lang/Object;A16:Ljava/lang/Object;A17:Ljava/lang/Object;A18:Ljava/lang/Object;A19:Ljava/lang/Object;A20:Ljava/lang/Object;>(TA1;TA2;TA3;TA4;TA5;TA6;TA7;TA8;TA9;TA10;TA11;TA12;TA13;TA14;TA15;TA16;TA17;TA18;TA19;TA20;)Lscala/Tuple20<TA1;TA2;TA3;TA4;TA5;TA6;TA7;TA8;TA9;TA10;TA11;TA12;TA13;TA14;TA15;TA16;TA17;TA18;TA19;TA20;>;;
Asciz	(Ljava/lang/Object;Ljava/lang/Object;Ljava/lang/Object;Ljava/lang/Object;Ljava/lang/Object;Ljava/lang/Object;Ljava/lang/Object;Ljava/lang/Object;Ljava/lang/Object;Ljava/lang/Object;Ljava/lang/Object;Ljava/lang/Object;Ljava/lang/Object;Ljava/lang/Object;Ljava/lang/Object;Ljava/lang/Object;Ljava/lang/Object;Ljava/lang/Object;Ljava/lang/Object;Ljava/lang/Object;Ljava/lang/Object;)Lscala/Tuple21;;
Asciz	scala/Tuple21;
class	scala/Tuple21
Asciz	(Ljava/lang/Object;Ljava/lang/Object;Ljava/lang/Object;Ljava/lang/Object;Ljava/lang/Object;Ljava/lang/Object;Ljava/lang/Object;Ljava/lang/Object;Ljava/lang/Object;Ljava/lang/Object;Ljava/lang/Object;Ljava/lang/Object;Ljava/lang/Object;Ljava/lang/Object;Ljava/lang/Object;Ljava/lang/Object;Ljava/lang/Object;Ljava/lang/Object;Ljava/lang/Object;Ljava/lang/Object;Ljava/lang/Object;)V;
NameAndType	"<init>":(Ljava/lang/Object;Ljava/lang/Object;Ljava/lang/Object;Ljava/lang/Object;Ljava/lang/Object;Ljava/lang/Object;Ljava/lang/Object;Ljava/lang/Object;Ljava/lang/Object;Ljava/lang/Object;Ljava/lang/Object;Ljava/lang/Object;Ljava/lang/Object;Ljava/lang/Object;Ljava/lang/Object;Ljava/lang/Object;Ljava/lang/Object;Ljava/lang/Object;Ljava/lang/Object;Ljava/lang/Object;Ljava/lang/Object;)V
Method	scala/Tuple21."<init>":(Ljava/lang/Object;Ljava/lang/Object;Ljava/lang/Object;Ljava/lang/Object;Ljava/lang/Object;Ljava/lang/Object;Ljava/lang/Object;Ljava/lang/Object;Ljava/lang/Object;Ljava/lang/Object;Ljava/lang/Object;Ljava/lang/Object;Ljava/lang/Object;Ljava/lang/Object;Ljava/lang/Object;Ljava/lang/Object;Ljava/lang/Object;Ljava/lang/Object;Ljava/lang/Object;Ljava/lang/Object;Ljava/lang/Object;)V
Asciz	x21;
Asciz	<A1:Ljava/lang/Object;A2:Ljava/lang/Object;A3:Ljava/lang/Object;A4:Ljava/lang/Object;A5:Ljava/lang/Object;A6:Ljava/lang/Object;A7:Ljava/lang/Object;A8:Ljava/lang/Object;A9:Ljava/lang/Object;A10:Ljava/lang/Object;A11:Ljava/lang/Object;A12:Ljava/lang/Object;A13:Ljava/lang/Object;A14:Ljava/lang/Object;A15:Ljava/lang/Object;A16:Ljava/lang/Object;A17:Ljava/lang/Object;A18:Ljava/lang/Object;A19:Ljava/lang/Object;A20:Ljava/lang/Object;A21:Ljava/lang/Object;>(TA1;TA2;TA3;TA4;TA5;TA6;TA7;TA8;TA9;TA10;TA11;TA12;TA13;TA14;TA15;TA16;TA17;TA18;TA19;TA20;TA21;)Lscala/Tuple21<TA1;TA2;TA3;TA4;TA5;TA6;TA7;TA8;TA9;TA10;TA11;TA12;TA13;TA14;TA15;TA16;TA17;TA18;TA19;TA20;TA21;>;;
Asciz	(Ljava/lang/Object;Ljava/lang/Object;Ljava/lang/Object;Ljava/lang/Object;Ljava/lang/Object;Ljava/lang/Object;Ljava/lang/Object;Ljava/lang/Object;Ljava/lang/Object;Ljava/lang/Object;Ljava/lang/Object;Ljava/lang/Object;Ljava/lang/Object;Ljava/lang/Object;Ljava/lang/Object;Ljava/lang/Object;Ljava/lang/Object;Ljava/lang/Object;Ljava/lang/Object;Ljava/lang/Object;Ljava/lang/Object;Ljava/lang/Object;)Lscala/Tuple22;;
Asciz	scala/Tuple22;
class	scala/Tuple22
Asciz	(Ljava/lang/Object;Ljava/lang/Object;Ljava/lang/Object;Ljava/lang/Object;Ljava/lang/Object;Ljava/lang/Object;Ljava/lang/Object;Ljava/lang/Object;Ljava/lang/Object;Ljava/lang/Object;Ljava/lang/Object;Ljava/lang/Object;Ljava/lang/Object;Ljava/lang/Object;Ljava/lang/Object;Ljava/lang/Object;Ljava/lang/Object;Ljava/lang/Object;Ljava/lang/Object;Ljava/lang/Object;Ljava/lang/Object;Ljava/lang/Object;)V;
NameAndType	"<init>":(Ljava/lang/Object;Ljava/lang/Object;Ljava/lang/Object;Ljava/lang/Object;Ljava/lang/Object;Ljava/lang/Object;Ljava/lang/Object;Ljava/lang/Object;Ljava/lang/Object;Ljava/lang/Object;Ljava/lang/Object;Ljava/lang/Object;Ljava/lang/Object;Ljava/lang/Object;Ljava/lang/Object;Ljava/lang/Object;Ljava/lang/Object;Ljava/lang/Object;Ljava/lang/Object;Ljava/lang/Object;Ljava/lang/Object;Ljava/lang/Object;)V
Method	scala/Tuple22."<init>":(Ljava/lang/Object;Ljava/lang/Object;Ljava/lang/Object;Ljava/lang/Object;Ljava/lang/Object;Ljava/lang/Object;Ljava/lang/Object;Ljava/lang/Object;Ljava/lang/Object;Ljava/lang/Object;Ljava/lang/Object;Ljava/lang/Object;Ljava/lang/Object;Ljava/lang/Object;Ljava/lang/Object;Ljava/lang/Object;Ljava/lang/Object;Ljava/lang/Object;Ljava/lang/Object;Ljava/lang/Object;Ljava/lang/Object;Ljava/lang/Object;)V
Asciz	x22;
Asciz	<A1:Ljava/lang/Object;A2:Ljava/lang/Object;A3:Ljava/lang/Object;A4:Ljava/lang/Object;A5:Ljava/lang/Object;A6:Ljava/lang/Object;A7:Ljava/lang/Object;A8:Ljava/lang/Object;A9:Ljava/lang/Object;A10:Ljava/lang/Object;A11:Ljava/lang/Object;A12:Ljava/lang/Object;A13:Ljava/lang/Object;A14:Ljava/lang/Object;A15:Ljava/lang/Object;A16:Ljava/lang/Object;A17:Ljava/lang/Object;A18:Ljava/lang/Object;A19:Ljava/lang/Object;A20:Ljava/lang/Object;A21:Ljava/lang/Object;A22:Ljava/lang/Object;>(TA1;TA2;TA3;TA4;TA5;TA6;TA7;TA8;TA9;TA10;TA11;TA12;TA13;TA14;TA15;TA16;TA17;TA18;TA19;TA20;TA21;TA22;)Lscala/Tuple22<TA1;TA2;TA3;TA4;TA5;TA6;TA7;TA8;TA9;TA10;TA11;TA12;TA13;TA14;TA15;TA16;TA17;TA18;TA19;TA20;TA21;TA22;>;;
NameAndType	Collection:Lscala/collection/Iterable$;
Field	scala/package$.Collection:Lscala/collection/Iterable$;
NameAndType	Sequence:Lscala/collection/Seq$;
Field	scala/package$.Sequence:Lscala/collection/Seq$;
NameAndType	RandomAccessSeq:Lscala/collection/IndexedSeq$;
Field	scala/package$.RandomAccessSeq:Lscala/collection/IndexedSeq$;
Asciz	java/lang/Object;
class	java/lang/Object
Method	java/lang/Object."<init>":()V
NameAndType	MODULE$:Lscala/package$;
Field	scala/package$.MODULE$:Lscala/package$;
Asciz	scala/collection/Traversable$;
class	scala/collection/Traversable$
NameAndType	MODULE$:Lscala/collection/Traversable$;
Field	scala/collection/Traversable$.MODULE$:Lscala/collection/Traversable$;
Asciz	scala/collection/Iterable$;
class	scala/collection/Iterable$
NameAndType	MODULE$:Lscala/collection/Iterable$;
Field	scala/collection/Iterable$.MODULE$:Lscala/collection/Iterable$;
Asciz	scala/collection/Seq$;
class	scala/collection/Seq$
NameAndType	MODULE$:Lscala/collection/Seq$;
Field	scala/collection/Seq$.MODULE$:Lscala/collection/Seq$;
Asciz	scala/collection/IndexedSeq$;
class	scala/collection/IndexedSeq$
NameAndType	MODULE$:Lscala/collection/IndexedSeq$;
Field	scala/collection/IndexedSeq$.MODULE$:Lscala/collection/IndexedSeq$;
Asciz	scala/collection/Iterator$;
class	scala/collection/Iterator$
NameAndType	MODULE$:Lscala/collection/Iterator$;
Field	scala/collection/Iterator$.MODULE$:Lscala/collection/Iterator$;
Asciz	scala/collection/immutable/List$;
class	scala/collection/immutable/List$
NameAndType	MODULE$:Lscala/collection/immutable/List$;
Field	scala/collection/immutable/List$.MODULE$:Lscala/collection/immutable/List$;
Asciz	scala/collection/immutable/Nil$;
class	scala/collection/immutable/Nil$
NameAndType	MODULE$:Lscala/collection/immutable/Nil$;
Field	scala/collection/immutable/Nil$.MODULE$:Lscala/collection/immutable/Nil$;
Asciz	scala/collection/immutable/$colon$colon$;
class	scala/collection/immutable/$colon$colon$
NameAndType	MODULE$:Lscala/collection/immutable/$colon$colon$;
Field	scala/collection/immutable/$colon$colon$.MODULE$:Lscala/collection/immutable/$colon$colon$;
Asciz	scala/collection/immutable/Stream$;
class	scala/collection/immutable/Stream$
NameAndType	MODULE$:Lscala/collection/immutable/Stream$;
Field	scala/collection/immutable/Stream$.MODULE$:Lscala/collection/immutable/Stream$;
Asciz	scala/collection/immutable/Stream$$hash$colon$colon$;
class	scala/collection/immutable/Stream$$hash$colon$colon$
NameAndType	MODULE$:Lscala/collection/immutable/Stream$$hash$colon$colon$;
Field	scala/collection/immutable/Stream$$hash$colon$colon$.MODULE$:Lscala/collection/immutable/Stream$$hash$colon$colon$;
Asciz	scala/collection/immutable/Vector$;
class	scala/collection/immutable/Vector$
NameAndType	MODULE$:Lscala/collection/immutable/Vector$;
Field	scala/collection/immutable/Vector$.MODULE$:Lscala/collection/immutable/Vector$;
Asciz	scala/collection/mutable/StringBuilder$;
class	scala/collection/mutable/StringBuilder$
NameAndType	MODULE$:Lscala/collection/mutable/StringBuilder$;
Field	scala/collection/mutable/StringBuilder$.MODULE$:Lscala/collection/mutable/StringBuilder$;
Asciz	scala/collection/immutable/Range$;
class	scala/collection/immutable/Range$
NameAndType	MODULE$:Lscala/collection/immutable/Range$;
Field	scala/collection/immutable/Range$.MODULE$:Lscala/collection/immutable/Range$;
Asciz	scala/xml/TopScope$;
class	scala/xml/TopScope$
NameAndType	MODULE$:Lscala/xml/TopScope$;
Field	scala/xml/TopScope$.MODULE$:Lscala/xml/TopScope$;
Asciz	scala/math/BigDecimal$;
class	scala/math/BigDecimal$
NameAndType	MODULE$:Lscala/math/BigDecimal$;
Field	scala/math/BigDecimal$.MODULE$:Lscala/math/BigDecimal$;
Asciz	scala/math/BigInt$;
class	scala/math/BigInt$
NameAndType	MODULE$:Lscala/math/BigInt$;
Field	scala/math/BigInt$.MODULE$:Lscala/math/BigInt$;
Asciz	scala/math/Numeric$;
class	scala/math/Numeric$
NameAndType	MODULE$:Lscala/math/Numeric$;
Field	scala/math/Numeric$.MODULE$:Lscala/math/Numeric$;
Asciz	scala/math/Ordered$;
class	scala/math/Ordered$
NameAndType	MODULE$:Lscala/math/Ordered$;
Field	scala/math/Ordered$.MODULE$:Lscala/math/Ordered$;
Asciz	scala/math/Ordering$;
class	scala/math/Ordering$
NameAndType	MODULE$:Lscala/math/Ordering$;
Field	scala/math/Ordering$.MODULE$:Lscala/math/Ordering$;
NameAndType	Iterable:()Lscala/collection/Iterable$;
Method	scala/package$.Iterable:()Lscala/collection/Iterable$;
Asciz	scala/ScalaObject;
class	scala/ScalaObject

{
public static final scala.package$ MODULE$;
  Signature: Lscala/package$;

private final scala.collection.IndexedSeq$ RandomAccessSeq;
  Signature: Lscala/collection/IndexedSeq$;

private final scala.collection.Seq$ Sequence;
  Signature: Lscala/collection/Seq$;

private final scala.collection.Iterable$ Collection;
  Signature: Lscala/collection/Iterable$;

private final scala.math.Ordering$ Ordering;
  Signature: Lscala/math/Ordering$;

private final scala.math.Ordered$ Ordered;
  Signature: Lscala/math/Ordered$;

private final scala.math.Numeric$ Numeric;
  Signature: Lscala/math/Numeric$;

private final scala.math.BigInt$ BigInt;
  Signature: Lscala/math/BigInt$;

private final scala.math.BigDecimal$ BigDecimal;
  Signature: Lscala/math/BigDecimal$;

private final scala.xml.TopScope$ $scope;
  Signature: Lscala/xml/TopScope$;

private final scala.collection.immutable.Range$ Range;
  Signature: Lscala/collection/immutable/Range$;

private final scala.collection.mutable.StringBuilder$ StringBuilder;
  Signature: Lscala/collection/mutable/StringBuilder$;

private final scala.collection.immutable.Vector$ Vector;
  Signature: Lscala/collection/immutable/Vector$;

private final scala.collection.immutable.Stream$$hash$colon$colon$ $hash$colon$colon;
  Signature: Lscala/collection/immutable/Stream$$hash$colon$colon$;

private final scala.collection.immutable.Stream$ Stream;
  Signature: Lscala/collection/immutable/Stream$;

private final scala.collection.immutable.$colon$colon$ $colon$colon;
  Signature: Lscala/collection/immutable/$colon$colon$;

private final scala.collection.immutable.Nil$ Nil;
  Signature: Lscala/collection/immutable/Nil$;

private final scala.collection.immutable.List$ List;
  Signature: Lscala/collection/immutable/List$;

private final scala.collection.Iterator$ Iterator;
  Signature: Lscala/collection/Iterator$;

private final scala.collection.IndexedSeq$ IndexedSeq;
  Signature: Lscala/collection/IndexedSeq$;

private final scala.collection.Seq$ Seq;
  Signature: Lscala/collection/Seq$;

private final scala.collection.Iterable$ Iterable;
  Signature: Lscala/collection/Iterable$;

private final scala.collection.Traversable$ Traversable;
  Signature: Lscala/collection/Traversable$;

public static {};
  Signature: ()V
  Code:
   Stack=1, Locals=0, Args_size=0
	new	class scala/package$
	invokespecial	Method "<init>":()V
	return
  Labels:

public scala.collection.Traversable$ Traversable();
  Signature: ()Lscala/collection/Traversable$;
  Code:
   Stack=1, Locals=1, Args_size=1
	aload_0
	getfield	Field Traversable:Lscala/collection/Traversable$;
	areturn
  Labels:

public scala.collection.Iterable$ Iterable();
  Signature: ()Lscala/collection/Iterable$;
  Code:
   Stack=1, Locals=1, Args_size=1
	aload_0
	getfield	Field Iterable:Lscala/collection/Iterable$;
	areturn
  Labels:

public scala.collection.Seq$ Seq();
  Signature: ()Lscala/collection/Seq$;
  Code:
   Stack=1, Locals=1, Args_size=1
	aload_0
	getfield	Field Seq:Lscala/collection/Seq$;
	areturn
  Labels:

public scala.collection.IndexedSeq$ IndexedSeq();
  Signature: ()Lscala/collection/IndexedSeq$;
  Code:
   Stack=1, Locals=1, Args_size=1
	aload_0
	getfield	Field IndexedSeq:Lscala/collection/IndexedSeq$;
	areturn
  Labels:

public scala.collection.Iterator$ Iterator();
  Signature: ()Lscala/collection/Iterator$;
  Code:
   Stack=1, Locals=1, Args_size=1
	aload_0
	getfield	Field Iterator:Lscala/collection/Iterator$;
	areturn
  Labels:

public scala.collection.immutable.List$ List();
  Signature: ()Lscala/collection/immutable/List$;
  Code:
   Stack=1, Locals=1, Args_size=1
	aload_0
	getfield	Field List:Lscala/collection/immutable/List$;
	areturn
  Labels:

public scala.collection.immutable.Nil$ Nil();
  Signature: ()Lscala/collection/immutable/Nil$;
  Code:
   Stack=1, Locals=1, Args_size=1
	aload_0
	getfield	Field Nil:Lscala/collection/immutable/Nil$;
	areturn
  Labels:

public scala.collection.immutable.$colon$colon$ $colon$colon();
  Signature: ()Lscala/collection/immutable/$colon$colon$;
  Code:
   Stack=1, Locals=1, Args_size=1
	aload_0
	getfield	Field $colon$colon:Lscala/collection/immutable/$colon$colon$;
	areturn
  Labels:

public scala.collection.immutable.Stream$ Stream();
  Signature: ()Lscala/collection/immutable/Stream$;
  Code:
   Stack=1, Locals=1, Args_size=1
	aload_0
	getfield	Field Stream:Lscala/collection/immutable/Stream$;
	areturn
  Labels:

public scala.collection.immutable.Stream$$hash$colon$colon$ $hash$colon$colon();
  Signature: ()Lscala/collection/immutable/Stream$$hash$colon$colon$;
  Code:
   Stack=1, Locals=1, Args_size=1
	aload_0
	getfield	Field $hash$colon$colon:Lscala/collection/immutable/Stream$$hash$colon$colon$;
	areturn
  Labels:

public scala.collection.immutable.Vector$ Vector();
  Signature: ()Lscala/collection/immutable/Vector$;
  Code:
   Stack=1, Locals=1, Args_size=1
	aload_0
	getfield	Field Vector:Lscala/collection/immutable/Vector$;
	areturn
  Labels:

public scala.collection.mutable.StringBuilder$ StringBuilder();
  Signature: ()Lscala/collection/mutable/StringBuilder$;
  Code:
   Stack=1, Locals=1, Args_size=1
	aload_0
	getfield	Field StringBuilder:Lscala/collection/mutable/StringBuilder$;
	areturn
  Labels:

public scala.collection.immutable.Range$ Range();
  Signature: ()Lscala/collection/immutable/Range$;
  Code:
   Stack=1, Locals=1, Args_size=1
	aload_0
	getfield	Field Range:Lscala/collection/immutable/Range$;
	areturn
  Labels:

public scala.xml.TopScope$ $scope();
  Signature: ()Lscala/xml/TopScope$;
  Code:
   Stack=1, Locals=1, Args_size=1
	aload_0
	getfield	Field $scope:Lscala/xml/TopScope$;
	areturn
  Labels:

public java.lang.Thread currentThread();
  Signature: ()Ljava/lang/Thread;
  Code:
   Stack=1, Locals=1, Args_size=1
	invokestatic	Method java/lang/Thread.currentThread:()Ljava/lang/Thread;
	areturn
  Labels:

public scala.math.BigDecimal$ BigDecimal();
  Signature: ()Lscala/math/BigDecimal$;
  Code:
   Stack=1, Locals=1, Args_size=1
	aload_0
	getfield	Field BigDecimal:Lscala/math/BigDecimal$;
	areturn
  Labels:

public scala.math.BigInt$ BigInt();
  Signature: ()Lscala/math/BigInt$;
  Code:
   Stack=1, Locals=1, Args_size=1
	aload_0
	getfield	Field BigInt:Lscala/math/BigInt$;
	areturn
  Labels:

public scala.math.Numeric$ Numeric();
  Signature: ()Lscala/math/Numeric$;
  Code:
   Stack=1, Locals=1, Args_size=1
	aload_0
	getfield	Field Numeric:Lscala/math/Numeric$;
	areturn
  Labels:

public scala.math.Ordered$ Ordered();
  Signature: ()Lscala/math/Ordered$;
  Code:
   Stack=1, Locals=1, Args_size=1
	aload_0
	getfield	Field Ordered:Lscala/math/Ordered$;
	areturn
  Labels:

public scala.math.Ordering$ Ordering();
  Signature: ()Lscala/math/Ordering$;
  Code:
   Stack=1, Locals=1, Args_size=1
	aload_0
	getfield	Field Ordering:Lscala/math/Ordering$;
	areturn
  Labels:

public scala.Tuple1 Tuple(java.lang.Object);
  Signature: (Ljava/lang/Object;)Lscala/Tuple1;
  Code:
   Stack=3, Locals=2, Args_size=2
	new	class scala/Tuple1
	dup
	aload_1
	invokespecial	Method scala/Tuple1."<init>":(Ljava/lang/Object;)V
	areturn
  Labels:
  LocalVariableTable: 
   Start  Length  Slot  Name   Signature
   0      9      0    this       Lscala/package$;
   0      9      1    x1       Ljava/lang/Object;

  Signature: length = 0x2
   00 FFFFFF82 
  Deprecated: true

public scala.Tuple2 Tuple(java.lang.Object, java.lang.Object);
  Signature: (Ljava/lang/Object;Ljava/lang/Object;)Lscala/Tuple2;
  Code:
   Stack=4, Locals=3, Args_size=3
	new	class scala/Tuple2
	dup
	aload_1
	aload_2
	invokespecial	Method scala/Tuple2."<init>":(Ljava/lang/Object;Ljava/lang/Object;)V
	areturn
  Labels:
  LocalVariableTable: 
   Start  Length  Slot  Name   Signature
   0      10      0    this       Lscala/package$;
   0      10      1    x1       Ljava/lang/Object;
   0      10      2    x2       Ljava/lang/Object;

  Signature: length = 0x2
   00 FFFFFF8C 
  Deprecated: true

public scala.Tuple3 Tuple(java.lang.Object, java.lang.Object, java.lang.Object);
  Signature: (Ljava/lang/Object;Ljava/lang/Object;Ljava/lang/Object;)Lscala/Tuple3;
  Code:
   Stack=5, Locals=4, Args_size=4
	new	class scala/Tuple3
	dup
	aload_1
	aload_2
	aload_3
	invokespecial	Method scala/Tuple3."<init>":(Ljava/lang/Object;Ljava/lang/Object;Ljava/lang/Object;)V
	areturn
  Labels:
  LocalVariableTable: 
   Start  Length  Slot  Name   Signature
   0      11      0    this       Lscala/package$;
   0      11      1    x1       Ljava/lang/Object;
   0      11      2    x2       Ljava/lang/Object;
   0      11      3    x3       Ljava/lang/Object;

  Signature: length = 0x2
   00 FFFFFF94 
  Deprecated: true

public scala.Tuple4 Tuple(java.lang.Object, java.lang.Object, java.lang.Object, java.lang.Object);
  Signature: (Ljava/lang/Object;Ljava/lang/Object;Ljava/lang/Object;Ljava/lang/Object;)Lscala/Tuple4;
  Code:
   Stack=6, Locals=5, Args_size=5
	new	class scala/Tuple4
	dup
	aload_1
	aload_2
	aload_3
	aload	4
	invokespecial	Method scala/Tuple4."<init>":(Ljava/lang/Object;Ljava/lang/Object;Ljava/lang/Object;Ljava/lang/Object;)V
	areturn
  Labels:
  LocalVariableTable: 
   Start  Length  Slot  Name   Signature
   0      13      0    this       Lscala/package$;
   0      13      1    x1       Ljava/lang/Object;
   0      13      2    x2       Ljava/lang/Object;
   0      13      3    x3       Ljava/lang/Object;
   0      13      4    x4       Ljava/lang/Object;

  Signature: length = 0x2
   00 FFFFFF9C 
  Deprecated: true

public scala.Tuple5 Tuple(java.lang.Object, java.lang.Object, java.lang.Object, java.lang.Object, java.lang.Object);
  Signature: (Ljava/lang/Object;Ljava/lang/Object;Ljava/lang/Object;Ljava/lang/Object;Ljava/lang/Object;)Lscala/Tuple5;
  Code:
   Stack=7, Locals=6, Args_size=6
	new	class scala/Tuple5
	dup
	aload_1
	aload_2
	aload_3
	aload	4
	aload	5
	invokespecial	Method scala/Tuple5."<init>":(Ljava/lang/Object;Ljava/lang/Object;Ljava/lang/Object;Ljava/lang/Object;Ljava/lang/Object;)V
	areturn
  Labels:
  LocalVariableTable: 
   Start  Length  Slot  Name   Signature
   0      15      0    this       Lscala/package$;
   0      15      1    x1       Ljava/lang/Object;
   0      15      2    x2       Ljava/lang/Object;
   0      15      3    x3       Ljava/lang/Object;
   0      15      4    x4       Ljava/lang/Object;
   0      15      5    x5       Ljava/lang/Object;

  Signature: length = 0x2
   00 FFFFFFA4 
  Deprecated: true

public scala.Tuple6 Tuple(java.lang.Object, java.lang.Object, java.lang.Object, java.lang.Object, java.lang.Object, java.lang.Object);
  Signature: (Ljava/lang/Object;Ljava/lang/Object;Ljava/lang/Object;Ljava/lang/Object;Ljava/lang/Object;Ljava/lang/Object;)Lscala/Tuple6;
  Code:
   Stack=8, Locals=7, Args_size=7
	new	class scala/Tuple6
	dup
	aload_1
	aload_2
	aload_3
	aload	4
	aload	5
	aload	6
	invokespecial	Method scala/Tuple6."<init>":(Ljava/lang/Object;Ljava/lang/Object;Ljava/lang/Object;Ljava/lang/Object;Ljava/lang/Object;Ljava/lang/Object;)V
	areturn
  Labels:
  LocalVariableTable: 
   Start  Length  Slot  Name   Signature
   0      17      0    this       Lscala/package$;
   0      17      1    x1       Ljava/lang/Object;
   0      17      2    x2       Ljava/lang/Object;
   0      17      3    x3       Ljava/lang/Object;
   0      17      4    x4       Ljava/lang/Object;
   0      17      5    x5       Ljava/lang/Object;
   0      17      6    x6       Ljava/lang/Object;

  Signature: length = 0x2
   00 FFFFFFAC 
  Deprecated: true

public scala.Tuple7 Tuple(java.lang.Object, java.lang.Object, java.lang.Object, java.lang.Object, java.lang.Object, java.lang.Object, java.lang.Object);
  Signature: (Ljava/lang/Object;Ljava/lang/Object;Ljava/lang/Object;Ljava/lang/Object;Ljava/lang/Object;Ljava/lang/Object;Ljava/lang/Object;)Lscala/Tuple7;
  Code:
   Stack=9, Locals=8, Args_size=8
	new	class scala/Tuple7
	dup
	aload_1
	aload_2
	aload_3
	aload	4
	aload	5
	aload	6
	aload	7
	invokespecial	Method scala/Tuple7."<init>":(Ljava/lang/Object;Ljava/lang/Object;Ljava/lang/Object;Ljava/lang/Object;Ljava/lang/Object;Ljava/lang/Object;Ljava/lang/Object;)V
	areturn
  Labels:
  LocalVariableTable: 
   Start  Length  Slot  Name   Signature
   0      19      0    this       Lscala/package$;
   0      19      1    x1       Ljava/lang/Object;
   0      19      2    x2       Ljava/lang/Object;
   0      19      3    x3       Ljava/lang/Object;
   0      19      4    x4       Ljava/lang/Object;
   0      19      5    x5       Ljava/lang/Object;
   0      19      6    x6       Ljava/lang/Object;
   0      19      7    x7       Ljava/lang/Object;

  Signature: length = 0x2
   00 FFFFFFB4 
  Deprecated: true

public scala.Tuple8 Tuple(java.lang.Object, java.lang.Object, java.lang.Object, java.lang.Object, java.lang.Object, java.lang.Object, java.lang.Object, java.lang.Object);
  Signature: (Ljava/lang/Object;Ljava/lang/Object;Ljava/lang/Object;Ljava/lang/Object;Ljava/lang/Object;Ljava/lang/Object;Ljava/lang/Object;Ljava/lang/Object;)Lscala/Tuple8;
  Code:
   Stack=10, Locals=9, Args_size=9
	new	class scala/Tuple8
	dup
	aload_1
	aload_2
	aload_3
	aload	4
	aload	5
	aload	6
	aload	7
	aload	8
	invokespecial	Method scala/Tuple8."<init>":(Ljava/lang/Object;Ljava/lang/Object;Ljava/lang/Object;Ljava/lang/Object;Ljava/lang/Object;Ljava/lang/Object;Ljava/lang/Object;Ljava/lang/Object;)V
	areturn
  Labels:
  LocalVariableTable: 
   Start  Length  Slot  Name   Signature
   0      21      0    this       Lscala/package$;
   0      21      1    x1       Ljava/lang/Object;
   0      21      2    x2       Ljava/lang/Object;
   0      21      3    x3       Ljava/lang/Object;
   0      21      4    x4       Ljava/lang/Object;
   0      21      5    x5       Ljava/lang/Object;
   0      21      6    x6       Ljava/lang/Object;
   0      21      7    x7       Ljava/lang/Object;
   0      21      8    x8       Ljava/lang/Object;

  Signature: length = 0x2
   00 FFFFFFBC 
  Deprecated: true

public scala.Tuple9 Tuple(java.lang.Object, java.lang.Object, java.lang.Object, java.lang.Object, java.lang.Object, java.lang.Object, java.lang.Object, java.lang.Object, java.lang.Object);
  Signature: (Ljava/lang/Object;Ljava/lang/Object;Ljava/lang/Object;Ljava/lang/Object;Ljava/lang/Object;Ljava/lang/Object;Ljava/lang/Object;Ljava/lang/Object;Ljava/lang/Object;)Lscala/Tuple9;
  Code:
   Stack=11, Locals=10, Args_size=10
	new	class scala/Tuple9
	dup
	aload_1
	aload_2
	aload_3
	aload	4
	aload	5
	aload	6
	aload	7
	aload	8
	aload	9
	invokespecial	Method scala/Tuple9."<init>":(Ljava/lang/Object;Ljava/lang/Object;Ljava/lang/Object;Ljava/lang/Object;Ljava/lang/Object;Ljava/lang/Object;Ljava/lang/Object;Ljava/lang/Object;Ljava/lang/Object;)V
	areturn
  Labels:
  LocalVariableTable: 
   Start  Length  Slot  Name   Signature
   0      23      0    this       Lscala/package$;
   0      23      1    x1       Ljava/lang/Object;
   0      23      2    x2       Ljava/lang/Object;
   0      23      3    x3       Ljava/lang/Object;
   0      23      4    x4       Ljava/lang/Object;
   0      23      5    x5       Ljava/lang/Object;
   0      23      6    x6       Ljava/lang/Object;
   0      23      7    x7       Ljava/lang/Object;
   0      23      8    x8       Ljava/lang/Object;
   0      23      9    x9       Ljava/lang/Object;

  Signature: length = 0x2
   00 FFFFFFC4 
  Deprecated: true

public scala.Tuple10 Tuple(java.lang.Object, java.lang.Object, java.lang.Object, java.lang.Object, java.lang.Object, java.lang.Object, java.lang.Object, java.lang.Object, java.lang.Object, java.lang.Object);
  Signature: (Ljava/lang/Object;Ljava/lang/Object;Ljava/lang/Object;Ljava/lang/Object;Ljava/lang/Object;Ljava/lang/Object;Ljava/lang/Object;Ljava/lang/Object;Ljava/lang/Object;Ljava/lang/Object;)Lscala/Tuple10;
  Code:
   Stack=12, Locals=11, Args_size=11
	new	class scala/Tuple10
	dup
	aload_1
	aload_2
	aload_3
	aload	4
	aload	5
	aload	6
	aload	7
	aload	8
	aload	9
	aload	10
	invokespecial	Method scala/Tuple10."<init>":(Ljava/lang/Object;Ljava/lang/Object;Ljava/lang/Object;Ljava/lang/Object;Ljava/lang/Object;Ljava/lang/Object;Ljava/lang/Object;Ljava/lang/Object;Ljava/lang/Object;Ljava/lang/Object;)V
	areturn
  Labels:
  LocalVariableTable: 
   Start  Length  Slot  Name   Signature
   0      25      0    this       Lscala/package$;
   0      25      1    x1       Ljava/lang/Object;
   0      25      2    x2       Ljava/lang/Object;
   0      25      3    x3       Ljava/lang/Object;
   0      25      4    x4       Ljava/lang/Object;
   0      25      5    x5       Ljava/lang/Object;
   0      25      6    x6       Ljava/lang/Object;
   0      25      7    x7       Ljava/lang/Object;
   0      25      8    x8       Ljava/lang/Object;
   0      25      9    x9       Ljava/lang/Object;
   0      25      10    x10       Ljava/lang/Object;

  Signature: length = 0x2
   00 FFFFFFCC 
  Deprecated: true

public scala.Tuple11 Tuple(java.lang.Object, java.lang.Object, java.lang.Object, java.lang.Object, java.lang.Object, java.lang.Object, java.lang.Object, java.lang.Object, java.lang.Object, java.lang.Object, java.lang.Object);
  Signature: (Ljava/lang/Object;Ljava/lang/Object;Ljava/lang/Object;Ljava/lang/Object;Ljava/lang/Object;Ljava/lang/Object;Ljava/lang/Object;Ljava/lang/Object;Ljava/lang/Object;Ljava/lang/Object;Ljava/lang/Object;)Lscala/Tuple11;
  Code:
   Stack=13, Locals=12, Args_size=12
	new	class scala/Tuple11
	dup
	aload_1
	aload_2
	aload_3
	aload	4
	aload	5
	aload	6
	aload	7
	aload	8
	aload	9
	aload	10
	aload	11
	invokespecial	Method scala/Tuple11."<init>":(Ljava/lang/Object;Ljava/lang/Object;Ljava/lang/Object;Ljava/lang/Object;Ljava/lang/Object;Ljava/lang/Object;Ljava/lang/Object;Ljava/lang/Object;Ljava/lang/Object;Ljava/lang/Object;Ljava/lang/Object;)V
	areturn
  Labels:
  LocalVariableTable: 
   Start  Length  Slot  Name   Signature
   0      27      0    this       Lscala/package$;
   0      27      1    x1       Ljava/lang/Object;
   0      27      2    x2       Ljava/lang/Object;
   0      27      3    x3       Ljava/lang/Object;
   0      27      4    x4       Ljava/lang/Object;
   0      27      5    x5       Ljava/lang/Object;
   0      27      6    x6       Ljava/lang/Object;
   0      27      7    x7       Ljava/lang/Object;
   0      27      8    x8       Ljava/lang/Object;
   0      27      9    x9       Ljava/lang/Object;
   0      27      10    x10       Ljava/lang/Object;
   0      27      11    x11       Ljava/lang/Object;

  Signature: length = 0x2
   00 FFFFFFD4 
  Deprecated: true

public scala.Tuple12 Tuple(java.lang.Object, java.lang.Object, java.lang.Object, java.lang.Object, java.lang.Object, java.lang.Object, java.lang.Object, java.lang.Object, java.lang.Object, java.lang.Object, java.lang.Object, java.lang.Object);
  Signature: (Ljava/lang/Object;Ljava/lang/Object;Ljava/lang/Object;Ljava/lang/Object;Ljava/lang/Object;Ljava/lang/Object;Ljava/lang/Object;Ljava/lang/Object;Ljava/lang/Object;Ljava/lang/Object;Ljava/lang/Object;Ljava/lang/Object;)Lscala/Tuple12;
  Code:
   Stack=14, Locals=13, Args_size=13
	new	class scala/Tuple12
	dup
	aload_1
	aload_2
	aload_3
	aload	4
	aload	5
	aload	6
	aload	7
	aload	8
	aload	9
	aload	10
	aload	11
	aload	12
	invokespecial	Method scala/Tuple12."<init>":(Ljava/lang/Object;Ljava/lang/Object;Ljava/lang/Object;Ljava/lang/Object;Ljava/lang/Object;Ljava/lang/Object;Ljava/lang/Object;Ljava/lang/Object;Ljava/lang/Object;Ljava/lang/Object;Ljava/lang/Object;Ljava/lang/Object;)V
	areturn
  Labels:
  LocalVariableTable: 
   Start  Length  Slot  Name   Signature
   0      29      0    this       Lscala/package$;
   0      29      1    x1       Ljava/lang/Object;
   0      29      2    x2       Ljava/lang/Object;
   0      29      3    x3       Ljava/lang/Object;
   0      29      4    x4       Ljava/lang/Object;
   0      29      5    x5       Ljava/lang/Object;
   0      29      6    x6       Ljava/lang/Object;
   0      29      7    x7       Ljava/lang/Object;
   0      29      8    x8       Ljava/lang/Object;
   0      29      9    x9       Ljava/lang/Object;
   0      29      10    x10       Ljava/lang/Object;
   0      29      11    x11       Ljava/lang/Object;
   0      29      12    x12       Ljava/lang/Object;

  Signature: length = 0x2
   00 FFFFFFDC 
  Deprecated: true

public scala.Tuple13 Tuple(java.lang.Object, java.lang.Object, java.lang.Object, java.lang.Object, java.lang.Object, java.lang.Object, java.lang.Object, java.lang.Object, java.lang.Object, java.lang.Object, java.lang.Object, java.lang.Object, java.lang.Object);
  Signature: (Ljava/lang/Object;Ljava/lang/Object;Ljava/lang/Object;Ljava/lang/Object;Ljava/lang/Object;Ljava/lang/Object;Ljava/lang/Object;Ljava/lang/Object;Ljava/lang/Object;Ljava/lang/Object;Ljava/lang/Object;Ljava/lang/Object;Ljava/lang/Object;)Lscala/Tuple13;
  Code:
   Stack=15, Locals=14, Args_size=14
	new	class scala/Tuple13
	dup
	aload_1
	aload_2
	aload_3
	aload	4
	aload	5
	aload	6
	aload	7
	aload	8
	aload	9
	aload	10
	aload	11
	aload	12
	aload	13
	invokespecial	Method scala/Tuple13."<init>":(Ljava/lang/Object;Ljava/lang/Object;Ljava/lang/Object;Ljava/lang/Object;Ljava/lang/Object;Ljava/lang/Object;Ljava/lang/Object;Ljava/lang/Object;Ljava/lang/Object;Ljava/lang/Object;Ljava/lang/Object;Ljava/lang/Object;Ljava/lang/Object;)V
	areturn
  Labels:
  LocalVariableTable: 
   Start  Length  Slot  Name   Signature
   0      31      0    this       Lscala/package$;
   0      31      1    x1       Ljava/lang/Object;
   0      31      2    x2       Ljava/lang/Object;
   0      31      3    x3       Ljava/lang/Object;
   0      31      4    x4       Ljava/lang/Object;
   0      31      5    x5       Ljava/lang/Object;
   0      31      6    x6       Ljava/lang/Object;
   0      31      7    x7       Ljava/lang/Object;
   0      31      8    x8       Ljava/lang/Object;
   0      31      9    x9       Ljava/lang/Object;
   0      31      10    x10       Ljava/lang/Object;
   0      31      11    x11       Ljava/lang/Object;
   0      31      12    x12       Ljava/lang/Object;
   0      31      13    x13       Ljava/lang/Object;

  Signature: length = 0x2
   00 FFFFFFE4 
  Deprecated: true

public scala.Tuple14 Tuple(java.lang.Object, java.lang.Object, java.lang.Object, java.lang.Object, java.lang.Object, java.lang.Object, java.lang.Object, java.lang.Object, java.lang.Object, java.lang.Object, java.lang.Object, java.lang.Object, java.lang.Object, java.lang.Object);
  Signature: (Ljava/lang/Object;Ljava/lang/Object;Ljava/lang/Object;Ljava/lang/Object;Ljava/lang/Object;Ljava/lang/Object;Ljava/lang/Object;Ljava/lang/Object;Ljava/lang/Object;Ljava/lang/Object;Ljava/lang/Object;Ljava/lang/Object;Ljava/lang/Object;Ljava/lang/Object;)Lscala/Tuple14;
  Code:
   Stack=16, Locals=15, Args_size=15
	new	class scala/Tuple14
	dup
	aload_1
	aload_2
	aload_3
	aload	4
	aload	5
	aload	6
	aload	7
	aload	8
	aload	9
	aload	10
	aload	11
	aload	12
	aload	13
	aload	14
	invokespecial	Method scala/Tuple14."<init>":(Ljava/lang/Object;Ljava/lang/Object;Ljava/lang/Object;Ljava/lang/Object;Ljava/lang/Object;Ljava/lang/Object;Ljava/lang/Object;Ljava/lang/Object;Ljava/lang/Object;Ljava/lang/Object;Ljava/lang/Object;Ljava/lang/Object;Ljava/lang/Object;Ljava/lang/Object;)V
	areturn
  Labels:
  LocalVariableTable: 
   Start  Length  Slot  Name   Signature
   0      33      0    this       Lscala/package$;
   0      33      1    x1       Ljava/lang/Object;
   0      33      2    x2       Ljava/lang/Object;
   0      33      3    x3       Ljava/lang/Object;
   0      33      4    x4       Ljava/lang/Object;
   0      33      5    x5       Ljava/lang/Object;
   0      33      6    x6       Ljava/lang/Object;
   0      33      7    x7       Ljava/lang/Object;
   0      33      8    x8       Ljava/lang/Object;
   0      33      9    x9       Ljava/lang/Object;
   0      33      10    x10       Ljava/lang/Object;
   0      33      11    x11       Ljava/lang/Object;
   0      33      12    x12       Ljava/lang/Object;
   0      33      13    x13       Ljava/lang/Object;
   0      33      14    x14       Ljava/lang/Object;

  Signature: length = 0x2
   00 FFFFFFEC 
  Deprecated: true

public scala.Tuple15 Tuple(java.lang.Object, java.lang.Object, java.lang.Object, java.lang.Object, java.lang.Object, java.lang.Object, java.lang.Object, java.lang.Object, java.lang.Object, java.lang.Object, java.lang.Object, java.lang.Object, java.lang.Object, java.lang.Object, java.lang.Object);
  Signature: (Ljava/lang/Object;Ljava/lang/Object;Ljava/lang/Object;Ljava/lang/Object;Ljava/lang/Object;Ljava/lang/Object;Ljava/lang/Object;Ljava/lang/Object;Ljava/lang/Object;Ljava/lang/Object;Ljava/lang/Object;Ljava/lang/Object;Ljava/lang/Object;Ljava/lang/Object;Ljava/lang/Object;)Lscala/Tuple15;
  Code:
   Stack=17, Locals=16, Args_size=16
	new	class scala/Tuple15
	dup
	aload_1
	aload_2
	aload_3
	aload	4
	aload	5
	aload	6
	aload	7
	aload	8
	aload	9
	aload	10
	aload	11
	aload	12
	aload	13
	aload	14
	aload	15
	invokespecial	Method scala/Tuple15."<init>":(Ljava/lang/Object;Ljava/lang/Object;Ljava/lang/Object;Ljava/lang/Object;Ljava/lang/Object;Ljava/lang/Object;Ljava/lang/Object;Ljava/lang/Object;Ljava/lang/Object;Ljava/lang/Object;Ljava/lang/Object;Ljava/lang/Object;Ljava/lang/Object;Ljava/lang/Object;Ljava/lang/Object;)V
	areturn
  Labels:
  LocalVariableTable: 
   Start  Length  Slot  Name   Signature
   0      35      0    this       Lscala/package$;
   0      35      1    x1       Ljava/lang/Object;
   0      35      2    x2       Ljava/lang/Object;
   0      35      3    x3       Ljava/lang/Object;
   0      35      4    x4       Ljava/lang/Object;
   0      35      5    x5       Ljava/lang/Object;
   0      35      6    x6       Ljava/lang/Object;
   0      35      7    x7       Ljava/lang/Object;
   0      35      8    x8       Ljava/lang/Object;
   0      35      9    x9       Ljava/lang/Object;
   0      35      10    x10       Ljava/lang/Object;
   0      35      11    x11       Ljava/lang/Object;
   0      35      12    x12       Ljava/lang/Object;
   0      35      13    x13       Ljava/lang/Object;
   0      35      14    x14       Ljava/lang/Object;
   0      35      15    x15       Ljava/lang/Object;

  Signature: length = 0x2
   00 FFFFFFF4 
  Deprecated: true

public scala.Tuple16 Tuple(java.lang.Object, java.lang.Object, java.lang.Object, java.lang.Object, java.lang.Object, java.lang.Object, java.lang.Object, java.lang.Object, java.lang.Object, java.lang.Object, java.lang.Object, java.lang.Object, java.lang.Object, java.lang.Object, java.lang.Object, java.lang.Object);
  Signature: (Ljava/lang/Object;Ljava/lang/Object;Ljava/lang/Object;Ljava/lang/Object;Ljava/lang/Object;Ljava/lang/Object;Ljava/lang/Object;Ljava/lang/Object;Ljava/lang/Object;Ljava/lang/Object;Ljava/lang/Object;Ljava/lang/Object;Ljava/lang/Object;Ljava/lang/Object;Ljava/lang/Object;Ljava/lang/Object;)Lscala/Tuple16;
  Code:
   Stack=18, Locals=17, Args_size=17
	new	class scala/Tuple16
	dup
	aload_1
	aload_2
	aload_3
	aload	4
	aload	5
	aload	6
	aload	7
	aload	8
	aload	9
	aload	10
	aload	11
	aload	12
	aload	13
	aload	14
	aload	15
	aload	16
	invokespecial	Method scala/Tuple16."<init>":(Ljava/lang/Object;Ljava/lang/Object;Ljava/lang/Object;Ljava/lang/Object;Ljava/lang/Object;Ljava/lang/Object;Ljava/lang/Object;Ljava/lang/Object;Ljava/lang/Object;Ljava/lang/Object;Ljava/lang/Object;Ljava/lang/Object;Ljava/lang/Object;Ljava/lang/Object;Ljava/lang/Object;Ljava/lang/Object;)V
	areturn
  Labels:
  LocalVariableTable: 
   Start  Length  Slot  Name   Signature
   0      37      0    this       Lscala/package$;
   0      37      1    x1       Ljava/lang/Object;
   0      37      2    x2       Ljava/lang/Object;
   0      37      3    x3       Ljava/lang/Object;
   0      37      4    x4       Ljava/lang/Object;
   0      37      5    x5       Ljava/lang/Object;
   0      37      6    x6       Ljava/lang/Object;
   0      37      7    x7       Ljava/lang/Object;
   0      37      8    x8       Ljava/lang/Object;
   0      37      9    x9       Ljava/lang/Object;
   0      37      10    x10       Ljava/lang/Object;
   0      37      11    x11       Ljava/lang/Object;
   0      37      12    x12       Ljava/lang/Object;
   0      37      13    x13       Ljava/lang/Object;
   0      37      14    x14       Ljava/lang/Object;
   0      37      15    x15       Ljava/lang/Object;
   0      37      16    x16       Ljava/lang/Object;

  Signature: length = 0x2
   00 FFFFFFFC 
  Deprecated: true

public scala.Tuple17 Tuple(java.lang.Object, java.lang.Object, java.lang.Object, java.lang.Object, java.lang.Object, java.lang.Object, java.lang.Object, java.lang.Object, java.lang.Object, java.lang.Object, java.lang.Object, java.lang.Object, java.lang.Object, java.lang.Object, java.lang.Object, java.lang.Object, java.lang.Object);
  Signature: (Ljava/lang/Object;Ljava/lang/Object;Ljava/lang/Object;Ljava/lang/Object;Ljava/lang/Object;Ljava/lang/Object;Ljava/lang/Object;Ljava/lang/Object;Ljava/lang/Object;Ljava/lang/Object;Ljava/lang/Object;Ljava/lang/Object;Ljava/lang/Object;Ljava/lang/Object;Ljava/lang/Object;Ljava/lang/Object;Ljava/lang/Object;)Lscala/Tuple17;
  Code:
   Stack=19, Locals=18, Args_size=18
	new	class scala/Tuple17
	dup
	aload_1
	aload_2
	aload_3
	aload	4
	aload	5
	aload	6
	aload	7
	aload	8
	aload	9
	aload	10
	aload	11
	aload	12
	aload	13
	aload	14
	aload	15
	aload	16
	aload	17
	invokespecial	Method scala/Tuple17."<init>":(Ljava/lang/Object;Ljava/lang/Object;Ljava/lang/Object;Ljava/lang/Object;Ljava/lang/Object;Ljava/lang/Object;Ljava/lang/Object;Ljava/lang/Object;Ljava/lang/Object;Ljava/lang/Object;Ljava/lang/Object;Ljava/lang/Object;Ljava/lang/Object;Ljava/lang/Object;Ljava/lang/Object;Ljava/lang/Object;Ljava/lang/Object;)V
	areturn
  Labels:
  LocalVariableTable: 
   Start  Length  Slot  Name   Signature
   0      39      0    this       Lscala/package$;
   0      39      1    x1       Ljava/lang/Object;
   0      39      2    x2       Ljava/lang/Object;
   0      39      3    x3       Ljava/lang/Object;
   0      39      4    x4       Ljava/lang/Object;
   0      39      5    x5       Ljava/lang/Object;
   0      39      6    x6       Ljava/lang/Object;
   0      39      7    x7       Ljava/lang/Object;
   0      39      8    x8       Ljava/lang/Object;
   0      39      9    x9       Ljava/lang/Object;
   0      39      10    x10       Ljava/lang/Object;
   0      39      11    x11       Ljava/lang/Object;
   0      39      12    x12       Ljava/lang/Object;
   0      39      13    x13       Ljava/lang/Object;
   0      39      14    x14       Ljava/lang/Object;
   0      39      15    x15       Ljava/lang/Object;
   0      39      16    x16       Ljava/lang/Object;
   0      39      17    x17       Ljava/lang/Object;

  Signature: length = 0x2
   01 04 
  Deprecated: true

public scala.Tuple18 Tuple(java.lang.Object, java.lang.Object, java.lang.Object, java.lang.Object, java.lang.Object, java.lang.Object, java.lang.Object, java.lang.Object, java.lang.Object, java.lang.Object, java.lang.Object, java.lang.Object, java.lang.Object, java.lang.Object, java.lang.Object, java.lang.Object, java.lang.Object, java.lang.Object);
  Signature: (Ljava/lang/Object;Ljava/lang/Object;Ljava/lang/Object;Ljava/lang/Object;Ljava/lang/Object;Ljava/lang/Object;Ljava/lang/Object;Ljava/lang/Object;Ljava/lang/Object;Ljava/lang/Object;Ljava/lang/Object;Ljava/lang/Object;Ljava/lang/Object;Ljava/lang/Object;Ljava/lang/Object;Ljava/lang/Object;Ljava/lang/Object;Ljava/lang/Object;)Lscala/Tuple18;
  Code:
   Stack=20, Locals=19, Args_size=19
	new	class scala/Tuple18
	dup
	aload_1
	aload_2
	aload_3
	aload	4
	aload	5
	aload	6
	aload	7
	aload	8
	aload	9
	aload	10
	aload	11
	aload	12
	aload	13
	aload	14
	aload	15
	aload	16
	aload	17
	aload	18
	invokespecial	Method scala/Tuple18."<init>":(Ljava/lang/Object;Ljava/lang/Object;Ljava/lang/Object;Ljava/lang/Object;Ljava/lang/Object;Ljava/lang/Object;Ljava/lang/Object;Ljava/lang/Object;Ljava/lang/Object;Ljava/lang/Object;Ljava/lang/Object;Ljava/lang/Object;Ljava/lang/Object;Ljava/lang/Object;Ljava/lang/Object;Ljava/lang/Object;Ljava/lang/Object;Ljava/lang/Object;)V
	areturn
  Labels:
  LocalVariableTable: 
   Start  Length  Slot  Name   Signature
   0      41      0    this       Lscala/package$;
   0      41      1    x1       Ljava/lang/Object;
   0      41      2    x2       Ljava/lang/Object;
   0      41      3    x3       Ljava/lang/Object;
   0      41      4    x4       Ljava/lang/Object;
   0      41      5    x5       Ljava/lang/Object;
   0      41      6    x6       Ljava/lang/Object;
   0      41      7    x7       Ljava/lang/Object;
   0      41      8    x8       Ljava/lang/Object;
   0      41      9    x9       Ljava/lang/Object;
   0      41      10    x10       Ljava/lang/Object;
   0      41      11    x11       Ljava/lang/Object;
   0      41      12    x12       Ljava/lang/Object;
   0      41      13    x13       Ljava/lang/Object;
   0      41      14    x14       Ljava/lang/Object;
   0      41      15    x15       Ljava/lang/Object;
   0      41      16    x16       Ljava/lang/Object;
   0      41      17    x17       Ljava/lang/Object;
   0      41      18    x18       Ljava/lang/Object;

  Signature: length = 0x2
   01 0C 
  Deprecated: true

public scala.Tuple19 Tuple(java.lang.Object, java.lang.Object, java.lang.Object, java.lang.Object, java.lang.Object, java.lang.Object, java.lang.Object, java.lang.Object, java.lang.Object, java.lang.Object, java.lang.Object, java.lang.Object, java.lang.Object, java.lang.Object, java.lang.Object, java.lang.Object, java.lang.Object, java.lang.Object, java.lang.Object);
  Signature: (Ljava/lang/Object;Ljava/lang/Object;Ljava/lang/Object;Ljava/lang/Object;Ljava/lang/Object;Ljava/lang/Object;Ljava/lang/Object;Ljava/lang/Object;Ljava/lang/Object;Ljava/lang/Object;Ljava/lang/Object;Ljava/lang/Object;Ljava/lang/Object;Ljava/lang/Object;Ljava/lang/Object;Ljava/lang/Object;Ljava/lang/Object;Ljava/lang/Object;Ljava/lang/Object;)Lscala/Tuple19;
  Code:
   Stack=21, Locals=20, Args_size=20
	new	class scala/Tuple19
	dup
	aload_1
	aload_2
	aload_3
	aload	4
	aload	5
	aload	6
	aload	7
	aload	8
	aload	9
	aload	10
	aload	11
	aload	12
	aload	13
	aload	14
	aload	15
	aload	16
	aload	17
	aload	18
	aload	19
	invokespecial	Method scala/Tuple19."<init>":(Ljava/lang/Object;Ljava/lang/Object;Ljava/lang/Object;Ljava/lang/Object;Ljava/lang/Object;Ljava/lang/Object;Ljava/lang/Object;Ljava/lang/Object;Ljava/lang/Object;Ljava/lang/Object;Ljava/lang/Object;Ljava/lang/Object;Ljava/lang/Object;Ljava/lang/Object;Ljava/lang/Object;Ljava/lang/Object;Ljava/lang/Object;Ljava/lang/Object;Ljava/lang/Object;)V
	areturn
  Labels:
  LocalVariableTable: 
   Start  Length  Slot  Name   Signature
   0      43      0    this       Lscala/package$;
   0      43      1    x1       Ljava/lang/Object;
   0      43      2    x2       Ljava/lang/Object;
   0      43      3    x3       Ljava/lang/Object;
   0      43      4    x4       Ljava/lang/Object;
   0      43      5    x5       Ljava/lang/Object;
   0      43      6    x6       Ljava/lang/Object;
   0      43      7    x7       Ljava/lang/Object;
   0      43      8    x8       Ljava/lang/Object;
   0      43      9    x9       Ljava/lang/Object;
   0      43      10    x10       Ljava/lang/Object;
   0      43      11    x11       Ljava/lang/Object;
   0      43      12    x12       Ljava/lang/Object;
   0      43      13    x13       Ljava/lang/Object;
   0      43      14    x14       Ljava/lang/Object;
   0      43      15    x15       Ljava/lang/Object;
   0      43      16    x16       Ljava/lang/Object;
   0      43      17    x17       Ljava/lang/Object;
   0      43      18    x18       Ljava/lang/Object;
   0      43      19    x19       Ljava/lang/Object;

  Signature: length = 0x2
   01 14 
  Deprecated: true

public scala.Tuple20 Tuple(java.lang.Object, java.lang.Object, java.lang.Object, java.lang.Object, java.lang.Object, java.lang.Object, java.lang.Object, java.lang.Object, java.lang.Object, java.lang.Object, java.lang.Object, java.lang.Object, java.lang.Object, java.lang.Object, java.lang.Object, java.lang.Object, java.lang.Object, java.lang.Object, java.lang.Object, java.lang.Object);
  Signature: (Ljava/lang/Object;Ljava/lang/Object;Ljava/lang/Object;Ljava/lang/Object;Ljava/lang/Object;Ljava/lang/Object;Ljava/lang/Object;Ljava/lang/Object;Ljava/lang/Object;Ljava/lang/Object;Ljava/lang/Object;Ljava/lang/Object;Ljava/lang/Object;Ljava/lang/Object;Ljava/lang/Object;Ljava/lang/Object;Ljava/lang/Object;Ljava/lang/Object;Ljava/lang/Object;Ljava/lang/Object;)Lscala/Tuple20;
  Code:
   Stack=22, Locals=21, Args_size=21
	new	class scala/Tuple20
	dup
	aload_1
	aload_2
	aload_3
	aload	4
	aload	5
	aload	6
	aload	7
	aload	8
	aload	9
	aload	10
	aload	11
	aload	12
	aload	13
	aload	14
	aload	15
	aload	16
	aload	17
	aload	18
	aload	19
	aload	20
	invokespecial	Method scala/Tuple20."<init>":(Ljava/lang/Object;Ljava/lang/Object;Ljava/lang/Object;Ljava/lang/Object;Ljava/lang/Object;Ljava/lang/Object;Ljava/lang/Object;Ljava/lang/Object;Ljava/lang/Object;Ljava/lang/Object;Ljava/lang/Object;Ljava/lang/Object;Ljava/lang/Object;Ljava/lang/Object;Ljava/lang/Object;Ljava/lang/Object;Ljava/lang/Object;Ljava/lang/Object;Ljava/lang/Object;Ljava/lang/Object;)V
	areturn
  Labels:
  LocalVariableTable: 
   Start  Length  Slot  Name   Signature
   0      45      0    this       Lscala/package$;
   0      45      1    x1       Ljava/lang/Object;
   0      45      2    x2       Ljava/lang/Object;
   0      45      3    x3       Ljava/lang/Object;
   0      45      4    x4       Ljava/lang/Object;
   0      45      5    x5       Ljava/lang/Object;
   0      45      6    x6       Ljava/lang/Object;
   0      45      7    x7       Ljava/lang/Object;
   0      45      8    x8       Ljava/lang/Object;
   0      45      9    x9       Ljava/lang/Object;
   0      45      10    x10       Ljava/lang/Object;
   0      45      11    x11       Ljava/lang/Object;
   0      45      12    x12       Ljava/lang/Object;
   0      45      13    x13       Ljava/lang/Object;
   0      45      14    x14       Ljava/lang/Object;
   0      45      15    x15       Ljava/lang/Object;
   0      45      16    x16       Ljava/lang/Object;
   0      45      17    x17       Ljava/lang/Object;
   0      45      18    x18       Ljava/lang/Object;
   0      45      19    x19       Ljava/lang/Object;
   0      45      20    x20       Ljava/lang/Object;

  Signature: length = 0x2
   01 1C 
  Deprecated: true

public scala.Tuple21 Tuple(java.lang.Object, java.lang.Object, java.lang.Object, java.lang.Object, java.lang.Object, java.lang.Object, java.lang.Object, java.lang.Object, java.lang.Object, java.lang.Object, java.lang.Object, java.lang.Object, java.lang.Object, java.lang.Object, java.lang.Object, java.lang.Object, java.lang.Object, java.lang.Object, java.lang.Object, java.lang.Object, java.lang.Object);
  Signature: (Ljava/lang/Object;Ljava/lang/Object;Ljava/lang/Object;Ljava/lang/Object;Ljava/lang/Object;Ljava/lang/Object;Ljava/lang/Object;Ljava/lang/Object;Ljava/lang/Object;Ljava/lang/Object;Ljava/lang/Object;Ljava/lang/Object;Ljava/lang/Object;Ljava/lang/Object;Ljava/lang/Object;Ljava/lang/Object;Ljava/lang/Object;Ljava/lang/Object;Ljava/lang/Object;Ljava/lang/Object;Ljava/lang/Object;)Lscala/Tuple21;
  Code:
   Stack=23, Locals=22, Args_size=22
	new	class scala/Tuple21
	dup
	aload_1
	aload_2
	aload_3
	aload	4
	aload	5
	aload	6
	aload	7
	aload	8
	aload	9
	aload	10
	aload	11
	aload	12
	aload	13
	aload	14
	aload	15
	aload	16
	aload	17
	aload	18
	aload	19
	aload	20
	aload	21
	invokespecial	Method scala/Tuple21."<init>":(Ljava/lang/Object;Ljava/lang/Object;Ljava/lang/Object;Ljava/lang/Object;Ljava/lang/Object;Ljava/lang/Object;Ljava/lang/Object;Ljava/lang/Object;Ljava/lang/Object;Ljava/lang/Object;Ljava/lang/Object;Ljava/lang/Object;Ljava/lang/Object;Ljava/lang/Object;Ljava/lang/Object;Ljava/lang/Object;Ljava/lang/Object;Ljava/lang/Object;Ljava/lang/Object;Ljava/lang/Object;Ljava/lang/Object;)V
	areturn
  Labels:
  LocalVariableTable: 
   Start  Length  Slot  Name   Signature
   0      47      0    this       Lscala/package$;
   0      47      1    x1       Ljava/lang/Object;
   0      47      2    x2       Ljava/lang/Object;
   0      47      3    x3       Ljava/lang/Object;
   0      47      4    x4       Ljava/lang/Object;
   0      47      5    x5       Ljava/lang/Object;
   0      47      6    x6       Ljava/lang/Object;
   0      47      7    x7       Ljava/lang/Object;
   0      47      8    x8       Ljava/lang/Object;
   0      47      9    x9       Ljava/lang/Object;
   0      47      10    x10       Ljava/lang/Object;
   0      47      11    x11       Ljava/lang/Object;
   0      47      12    x12       Ljava/lang/Object;
   0      47      13    x13       Ljava/lang/Object;
   0      47      14    x14       Ljava/lang/Object;
   0      47      15    x15       Ljava/lang/Object;
   0      47      16    x16       Ljava/lang/Object;
   0      47      17    x17       Ljava/lang/Object;
   0      47      18    x18       Ljava/lang/Object;
   0      47      19    x19       Ljava/lang/Object;
   0      47      20    x20       Ljava/lang/Object;
   0      47      21    x21       Ljava/lang/Object;

  Signature: length = 0x2
   01 24 
  Deprecated: true

public scala.Tuple22 Tuple(java.lang.Object, java.lang.Object, java.lang.Object, java.lang.Object, java.lang.Object, java.lang.Object, java.lang.Object, java.lang.Object, java.lang.Object, java.lang.Object, java.lang.Object, java.lang.Object, java.lang.Object, java.lang.Object, java.lang.Object, java.lang.Object, java.lang.Object, java.lang.Object, java.lang.Object, java.lang.Object, java.lang.Object, java.lang.Object);
  Signature: (Ljava/lang/Object;Ljava/lang/Object;Ljava/lang/Object;Ljava/lang/Object;Ljava/lang/Object;Ljava/lang/Object;Ljava/lang/Object;Ljava/lang/Object;Ljava/lang/Object;Ljava/lang/Object;Ljava/lang/Object;Ljava/lang/Object;Ljava/lang/Object;Ljava/lang/Object;Ljava/lang/Object;Ljava/lang/Object;Ljava/lang/Object;Ljava/lang/Object;Ljava/lang/Object;Ljava/lang/Object;Ljava/lang/Object;Ljava/lang/Object;)Lscala/Tuple22;
  Code:
   Stack=24, Locals=23, Args_size=23
	new	class scala/Tuple22
	dup
	aload_1
	aload_2
	aload_3
	aload	4
	aload	5
	aload	6
	aload	7
	aload	8
	aload	9
	aload	10
	aload	11
	aload	12
	aload	13
	aload	14
	aload	15
	aload	16
	aload	17
	aload	18
	aload	19
	aload	20
	aload	21
	aload	22
	invokespecial	Method scala/Tuple22."<init>":(Ljava/lang/Object;Ljava/lang/Object;Ljava/lang/Object;Ljava/lang/Object;Ljava/lang/Object;Ljava/lang/Object;Ljava/lang/Object;Ljava/lang/Object;Ljava/lang/Object;Ljava/lang/Object;Ljava/lang/Object;Ljava/lang/Object;Ljava/lang/Object;Ljava/lang/Object;Ljava/lang/Object;Ljava/lang/Object;Ljava/lang/Object;Ljava/lang/Object;Ljava/lang/Object;Ljava/lang/Object;Ljava/lang/Object;Ljava/lang/Object;)V
	areturn
  Labels:
  LocalVariableTable: 
   Start  Length  Slot  Name   Signature
   0      49      0    this       Lscala/package$;
   0      49      1    x1       Ljava/lang/Object;
   0      49      2    x2       Ljava/lang/Object;
   0      49      3    x3       Ljava/lang/Object;
   0      49      4    x4       Ljava/lang/Object;
   0      49      5    x5       Ljava/lang/Object;
   0      49      6    x6       Ljava/lang/Object;
   0      49      7    x7       Ljava/lang/Object;
   0      49      8    x8       Ljava/lang/Object;
   0      49      9    x9       Ljava/lang/Object;
   0      49      10    x10       Ljava/lang/Object;
   0      49      11    x11       Ljava/lang/Object;
   0      49      12    x12       Ljava/lang/Object;
   0      49      13    x13       Ljava/lang/Object;
   0      49      14    x14       Ljava/lang/Object;
   0      49      15    x15       Ljava/lang/Object;
   0      49      16    x16       Ljava/lang/Object;
   0      49      17    x17       Ljava/lang/Object;
   0      49      18    x18       Ljava/lang/Object;
   0      49      19    x19       Ljava/lang/Object;
   0      49      20    x20       Ljava/lang/Object;
   0      49      21    x21       Ljava/lang/Object;
   0      49      22    x22       Ljava/lang/Object;

  Signature: length = 0x2
   01 2C 
  Deprecated: true

public scala.collection.Iterable$ Collection();
  Signature: ()Lscala/collection/Iterable$;
  Code:
   Stack=1, Locals=1, Args_size=1
	aload_0
	getfield	Field Collection:Lscala/collection/Iterable$;
	areturn
  Labels:
  Deprecated: true

public scala.collection.Seq$ Sequence();
  Signature: ()Lscala/collection/Seq$;
  Code:
   Stack=1, Locals=1, Args_size=1
	aload_0
	getfield	Field Sequence:Lscala/collection/Seq$;
	areturn
  Labels:
  Deprecated: true

public scala.collection.IndexedSeq$ RandomAccessSeq();
  Signature: ()Lscala/collection/IndexedSeq$;
  Code:
   Stack=1, Locals=1, Args_size=1
	aload_0
	getfield	Field RandomAccessSeq:Lscala/collection/IndexedSeq$;
	areturn
  Labels:
  Deprecated: true

private scala.package$();
  Signature: ()V
  Code:
   Stack=2, Locals=1, Args_size=1
	aload_0
	invokespecial	Method java/lang/Object."<init>":()V
	aload_0
	putstatic	Field MODULE$:Lscala/package$;
	aload_0
	getstatic	Field scala/collection/Traversable$.MODULE$:Lscala/collection/Traversable$;
	putfield	Field Traversable:Lscala/collection/Traversable$;
	aload_0
	getstatic	Field scala/collection/Iterable$.MODULE$:Lscala/collection/Iterable$;
	putfield	Field Iterable:Lscala/collection/Iterable$;
	aload_0
	getstatic	Field scala/collection/Seq$.MODULE$:Lscala/collection/Seq$;
	putfield	Field Seq:Lscala/collection/Seq$;
	aload_0
	getstatic	Field scala/collection/IndexedSeq$.MODULE$:Lscala/collection/IndexedSeq$;
	putfield	Field IndexedSeq:Lscala/collection/IndexedSeq$;
	aload_0
	getstatic	Field scala/collection/Iterator$.MODULE$:Lscala/collection/Iterator$;
	putfield	Field Iterator:Lscala/collection/Iterator$;
	aload_0
	getstatic	Field scala/collection/immutable/List$.MODULE$:Lscala/collection/immutable/List$;
	putfield	Field List:Lscala/collection/immutable/List$;
	aload_0
	getstatic	Field scala/collection/immutable/Nil$.MODULE$:Lscala/collection/immutable/Nil$;
	putfield	Field Nil:Lscala/collection/immutable/Nil$;
	aload_0
	getstatic	Field scala/collection/immutable/$colon$colon$.MODULE$:Lscala/collection/immutable/$colon$colon$;
	putfield	Field $colon$colon:Lscala/collection/immutable/$colon$colon$;
	aload_0
	getstatic	Field scala/collection/immutable/Stream$.MODULE$:Lscala/collection/immutable/Stream$;
	putfield	Field Stream:Lscala/collection/immutable/Stream$;
	aload_0
	getstatic	Field scala/collection/immutable/Stream$$hash$colon$colon$.MODULE$:Lscala/collection/immutable/Stream$$hash$colon$colon$;
	putfield	Field $hash$colon$colon:Lscala/collection/immutable/Stream$$hash$colon$colon$;
	aload_0
	getstatic	Field scala/collection/immutable/Vector$.MODULE$:Lscala/collection/immutable/Vector$;
	putfield	Field Vector:Lscala/collection/immutable/Vector$;
	aload_0
	getstatic	Field scala/collection/mutable/StringBuilder$.MODULE$:Lscala/collection/mutable/StringBuilder$;
	putfield	Field StringBuilder:Lscala/collection/mutable/StringBuilder$;
	aload_0
	getstatic	Field scala/collection/immutable/Range$.MODULE$:Lscala/collection/immutable/Range$;
	putfield	Field Range:Lscala/collection/immutable/Range$;
	aload_0
	getstatic	Field scala/xml/TopScope$.MODULE$:Lscala/xml/TopScope$;
	putfield	Field $scope:Lscala/xml/TopScope$;
	aload_0
	getstatic	Field scala/math/BigDecimal$.MODULE$:Lscala/math/BigDecimal$;
	putfield	Field BigDecimal:Lscala/math/BigDecimal$;
	aload_0
	getstatic	Field scala/math/BigInt$.MODULE$:Lscala/math/BigInt$;
	putfield	Field BigInt:Lscala/math/BigInt$;
	aload_0
	getstatic	Field scala/math/Numeric$.MODULE$:Lscala/math/Numeric$;
	putfield	Field Numeric:Lscala/math/Numeric$;
	aload_0
	getstatic	Field scala/math/Ordered$.MODULE$:Lscala/math/Ordered$;
	putfield	Field Ordered:Lscala/math/Ordered$;
	aload_0
	getstatic	Field scala/math/Ordering$.MODULE$:Lscala/math/Ordering$;
	putfield	Field Ordering:Lscala/math/Ordering$;
	aload_0
	aload_0
	invokevirtual	Method Iterable:()Lscala/collection/Iterable$;
	putfield	Field Collection:Lscala/collection/Iterable$;
	aload_0
	getstatic	Field scala/collection/Seq$.MODULE$:Lscala/collection/Seq$;
	putfield	Field Sequence:Lscala/collection/Seq$;
	aload_0
	getstatic	Field scala/collection/IndexedSeq$.MODULE$:Lscala/collection/IndexedSeq$;
	putfield	Field RandomAccessSeq:Lscala/collection/IndexedSeq$;
	return
  Labels:

}

