Compiled from "package.scala"
public final class scala.package extends java.lang.Object
  SourceFile: "package.scala"
  ScalaSig: length = 0x343A
   05 00 FFFFFF8B 13 07 05 01 02 FFFFFF88 02 05 01 07 70 61 63
   6B 61 67 65 0A 01 03 01 05 73 63 61 6C 61 03 00
   10 02 06 07 0D 01 02 06 08 08 02 FFFFFF84 FFFFFF80 FFFFFF80 FFFFFF88 02
   09 02 07 70 61 63 6B 61 67 65 13 03 07 0A 12 10
   02 0B 10 0D 01 0C 0A 02 0D 0E 01 04 6C 61 6E 67
   0A 01 0F 01 04 6A 61 76 61 09 02 11 0C 02 06 4F
   62 6A 65 63 74 10 02 06 13 09 02 14 02 02 0B 53
   63 61 6C 61 4F 62 6A 65 63 74 08 05 16 07 FFFFFF84 00
   17 01 06 3C 69 6E 69 74 3E 14 01 05 05 08 19 07
   FFFFFF84 FFFFFF80 FFFFFF80 FFFFFF80 00 1A 02 09 54 68 72 6F 77 61 62 6C
   65 10 02 0B 1B 09 02 19 0C 05 08 1D 07 FFFFFF84 FFFFFF80 FFFFFF80
   FFFFFF80 00 1E 02 09 45 78 63 65 70 74 69 6F 6E 10 02
   0B 1F 09 02 1D 0C 05 08 21 07 FFFFFF84 FFFFFF80 FFFFFF80 FFFFFF80 00 22
   02 05 45 72 72 6F 72 10 02 0B 23 09 02 21 0C 05
   08 25 07 FFFFFF84 FFFFFF80 FFFFFF80 FFFFFF80 00 26 02 10 52 75 6E 74 69
   6D 65 45 78 63 65 70 74 69 6F 6E 10 02 0B 27 09
   02 25 0C 05 08 29 07 FFFFFF84 FFFFFF80 FFFFFF80 FFFFFF80 00 2A 02 14 4E
   75 6C 6C 50 6F 69 6E 74 65 72 45 78 63 65 70 74
   69 6F 6E 10 02 0B 2B 09 02 29 0C 05 08 2D 07 FFFFFF84
   FFFFFF80 FFFFFF80 FFFFFF80 00 2E 02 12 43 6C 61 73 73 43 61 73 74
   45 78 63 65 70 74 69 6F 6E 10 02 0B 2F 09 02 2D
   0C 05 08 31 07 FFFFFF84 FFFFFF80 FFFFFF80 FFFFFF80 00 32 02 19 49 6E 64
   65 78 4F 75 74 4F 66 42 6F 75 6E 64 73 45 78 63
   65 70 74 69 6F 6E 10 02 0B 33 09 02 31 0C 05 08
   35 07 FFFFFF84 FFFFFF80 FFFFFF80 FFFFFF80 00 36 02 1E 41 72 72 61 79 49
   6E 64 65 78 4F 75 74 4F 66 42 6F 75 6E 64 73 45
   78 63 65 70 74 69 6F 6E 10 02 0B 37 09 02 35 0C
   05 08 39 07 FFFFFF84 FFFFFF80 FFFFFF80 FFFFFF80 00 3A 02 1F 53 74 72 69
   6E 67 49 6E 64 65 78 4F 75 74 4F 66 42 6F 75 6E
   64 73 45 78 63 65 70 74 69 6F 6E 10 02 0B 3B 09
   02 39 0C 05 08 3D 07 FFFFFF84 FFFFFF80 FFFFFF80 FFFFFF80 00 3E 02 1D 55
   6E 73 75 70 70 6F 72 74 65 64 4F 70 65 72 61 74
   69 6F 6E 45 78 63 65 70 74 69 6F 6E 10 02 0B 3F
   09 02 3D 0C 05 08 41 07 FFFFFF84 FFFFFF80 FFFFFF80 FFFFFF80 00 42 02 18
   49 6C 6C 65 67 61 6C 41 72 67 75 6D 65 6E 74 45
   78 63 65 70 74 69 6F 6E 10 02 0B 43 09 02 41 0C
   05 08 45 07 FFFFFF84 FFFFFF80 FFFFFF80 FFFFFF80 00 46 02 16 4E 6F 53 75
   63 68 45 6C 65 6D 65 6E 74 45 78 63 65 70 74 69
   6F 6E 10 02 47 4A 0D 01 48 0A 02 49 0E 01 04 75
   74 69 6C 09 02 45 48 05 08 4C 07 FFFFFF84 FFFFFF80 FFFFFF80 FFFFFF80 00
   4D 02 15 4E 75 6D 62 65 72 46 6F 72 6D 61 74 45
   78 63 65 70 74 69 6F 6E 10 02 0B 4E 09 02 4C 0C
   05 08 50 07 FFFFFF84 FFFFFF80 FFFFFF80 FFFFFF80 00 51 02 13 41 62 73 74
   72 61 63 74 4D 65 74 68 6F 64 45 72 72 6F 72 10
   02 0B 52 09 02 50 0C 05 04 54 07 00 55 02 0B 54
   72 61 76 65 72 73 61 62 6C 65 15 02 56 5D 10 03
   57 5A 5B 0D 01 58 0A 02 59 02 01 0A 63 6F 6C 6C
   65 63 74 69 6F 6E 09 02 54 58 10 02 5C 5D 0C 00
   04 08 5E 53 FFFFFF84 FFFFFF80 FFFFFF84 FFFFFFC2 00 5F 02 01 41 11 02 60
   63 10 02 06 61 09 02 62 02 02 07 4E 6F 74 68 69
   6E 67 10 02 06 64 09 02 65 02 02 03 41 6E 79 08
   07 67 07 FFFFFFC2 FFFFFF80 FFFFFF84 00 68 01 0B 54 72 61 76 65 72
   73 61 62 6C 65 15 01 69 0E 02 6A 71 0E 02 6B 70
   0E 02 6C 6F 0D 01 6D 0A 02 6E 04 01 06 3C 72 6F
   6F 74 3E 09 01 03 09 02 59 02 09 02 67 58 08 06
   73 07 FFFFFFA0 FFFFFF80 04 69 01 0C 54 72 61 76 65 72 73 61
   62 6C 65 20 05 04 75 07 00 76 02 08 49 74 65 72
   61 62 6C 65 15 02 77 7A 10 03 57 78 79 09 02 75
   58 10 02 5C 7A 04 08 5E 74 FFFFFF84 FFFFFF80 FFFFFF84 FFFFFFC2 00 5F 08
   07 7C 07 FFFFFFC2 FFFFFF80 FFFFFF84 00 7D 01 08 49 74 65 72 61 62
   6C 65 15 01 7E 0E 02 6A 7F 09 02 7C 58 08 07 FFFFFF81
   01 07 FFFFFFA0 FFFFFF80 04 7E 01 09 49 74 65 72 61 62 6C 65
   20 05 06 FFFFFF81 03 07 00 FFFFFF81 04 02 03 53 65 71 15 04
   FFFFFF81 05 FFFFFF81 08 10 05 57 FFFFFF81 06 FFFFFF81 07 09 03 FFFFFF81 03 58
   10 03 5C FFFFFF81 08 04 09 5E FFFFFF81 02 FFFFFF84 FFFFFF80 FFFFFF84 FFFFFFC2 00 5F
   08 09 FFFFFF81 0A 07 FFFFFFC2 FFFFFF80 FFFFFF84 00 FFFFFF81 0B 01 03 53 65 71
   15 02 FFFFFF81 0C 0E 03 6A FFFFFF81 0D 09 03 FFFFFF81 0A 58 08 08
   FFFFFF81 0F 07 FFFFFFA0 FFFFFF80 04 FFFFFF81 0C 01 04 53 65 71 20 05 06
   FFFFFF81 11 07 00 FFFFFF81 12 02 0A 49 6E 64 65 78 65 64 53
   65 71 15 04 FFFFFF81 13 FFFFFF81 16 10 05 57 FFFFFF81 14 FFFFFF81 15 09
   03 FFFFFF81 11 58 10 03 5C FFFFFF81 16 04 09 5E FFFFFF81 10 FFFFFF84 FFFFFF80
   FFFFFF84 FFFFFFC2 00 5F 08 09 FFFFFF81 18 07 FFFFFFC2 FFFFFF80 FFFFFF84 00 FFFFFF81 19 01
   0A 49 6E 64 65 78 65 64 53 65 71 15 02 FFFFFF81 1A 0E
   03 6A FFFFFF81 1B 09 03 FFFFFF81 18 58 08 08 FFFFFF81 1D 07 FFFFFFA0 FFFFFF80
   04 FFFFFF81 1A 01 0B 49 6E 64 65 78 65 64 53 65 71 20
   05 06 FFFFFF81 1F 07 00 FFFFFF81 20 02 08 49 74 65 72 61 74
   6F 72 15 04 FFFFFF81 21 FFFFFF81 24 10 05 57 FFFFFF81 22 FFFFFF81 23 09
   03 FFFFFF81 1F 58 10 03 5C FFFFFF81 24 04 09 5E FFFFFF81 1E FFFFFF84 FFFFFF80
   FFFFFF84 FFFFFFC2 00 5F 08 09 FFFFFF81 26 07 FFFFFFC2 FFFFFF80 FFFFFF84 00 FFFFFF81 27 01
   08 49 74 65 72 61 74 6F 72 15 02 FFFFFF81 28 0E 03 6A
   FFFFFF81 29 09 03 FFFFFF81 26 58 08 08 FFFFFF81 2B 07 FFFFFFA0 FFFFFF80 04 FFFFFF81
   28 01 09 49 74 65 72 61 74 6F 72 20 05 06 FFFFFF81 2D
   07 00 FFFFFF81 2E 02 10 42 75 66 66 65 72 65 64 49 74
   65 72 61 74 6F 72 15 04 FFFFFF81 2F FFFFFF81 32 10 05 57 FFFFFF81
   30 FFFFFF81 31 09 03 FFFFFF81 2D 58 10 03 5C FFFFFF81 32 04 09 5E
   FFFFFF81 2C FFFFFF84 FFFFFF80 FFFFFF84 FFFFFFC2 00 5F 05 06 FFFFFF81 34 07 00 FFFFFF81 35
   02 04 4C 69 73 74 15 04 FFFFFF81 36 FFFFFF81 3C 10 06 FFFFFF81 37
   FFFFFF81 3A FFFFFF81 3B 0D 02 FFFFFF81 38 0A 03 FFFFFF81 39 58 01 09 69
   6D 6D 75 74 61 62 6C 65 09 04 FFFFFF81 34 FFFFFF81 38 10 03
   5C FFFFFF81 3C 04 09 5E FFFFFF81 33 FFFFFF84 FFFFFF80 FFFFFF84 FFFFFFC2 00 5F 08 09
   FFFFFF81 3E 07 FFFFFFC2 FFFFFF80 FFFFFF84 00 FFFFFF81 3F 01 04 4C 69 73 74 15
   02 FFFFFF81 40 0E 04 FFFFFF81 41 FFFFFF81 43 0E 03 6A FFFFFF81 42 09 03
   FFFFFF81 39 58 09 04 FFFFFF81 3E FFFFFF81 38 08 08 FFFFFF81 45 07 FFFFFFA0 FFFFFF80
   04 FFFFFF81 40 01 05 4C 69 73 74 20 08 09 FFFFFF81 47 07 FFFFFFC2
   FFFFFF80 FFFFFF84 00 FFFFFF81 48 01 03 4E 69 6C 15 02 FFFFFF81 49 0E 04
   FFFFFF81 41 FFFFFF81 4A 09 04 FFFFFF81 47 FFFFFF81 38 08 08 FFFFFF81 4C 07 FFFFFFA0
   FFFFFF80 04 FFFFFF81 49 01 04 4E 69 6C 20 05 06 FFFFFF81 4E 07 00
   FFFFFF81 4F 02 0C 24 63 6F 6C 6F 6E 24 63 6F 6C 6F 6E
   15 04 FFFFFF81 50 FFFFFF81 53 10 06 FFFFFF81 37 FFFFFF81 51 FFFFFF81 52 09 04
   FFFFFF81 4E FFFFFF81 38 10 03 5C FFFFFF81 53 04 09 5E FFFFFF81 4D FFFFFF84 FFFFFF80
   FFFFFF80 FFFFFFC2 00 5F 08 09 FFFFFF81 55 07 FFFFFFC2 FFFFFF80 FFFFFF84 00 FFFFFF81 56 01
   0C 24 63 6F 6C 6F 6E 24 63 6F 6C 6F 6E 15 02 FFFFFF81
   57 0E 04 FFFFFF81 41 FFFFFF81 58 09 04 FFFFFF81 55 FFFFFF81 38 08 08 FFFFFF81
   5A 07 FFFFFFA0 FFFFFF80 04 FFFFFF81 57 01 0D 24 63 6F 6C 6F 6E 24
   63 6F 6C 6F 6E 20 05 06 FFFFFF81 5C 07 00 FFFFFF81 5D 02 06
   53 74 72 65 61 6D 15 04 FFFFFF81 5E FFFFFF81 61 10 06 FFFFFF81 37
   FFFFFF81 5F FFFFFF81 60 09 04 FFFFFF81 5C FFFFFF81 38 10 03 5C FFFFFF81 61 04
   09 5E FFFFFF81 5B FFFFFF84 FFFFFF80 FFFFFF84 FFFFFFC2 00 5F 08 09 FFFFFF81 63 07 FFFFFFC2
   FFFFFF80 FFFFFF84 00 FFFFFF81 64 01 06 53 74 72 65 61 6D 15 02 FFFFFF81
   65 0E 04 FFFFFF81 41 FFFFFF81 66 09 04 FFFFFF81 63 FFFFFF81 38 08 08 FFFFFF81
   68 07 FFFFFFA0 FFFFFF80 04 FFFFFF81 65 01 07 53 74 72 65 61 6D 20
   08 09 FFFFFF81 6A 07 FFFFFFC2 FFFFFF80 FFFFFF84 00 FFFFFF81 6B 01 11 24 68 61
   73 68 24 63 6F 6C 6F 6E 24 63 6F 6C 6F 6E 15 02
   FFFFFF81 6C 0E 04 FFFFFF81 65 FFFFFF81 6D 09 04 FFFFFF81 6A FFFFFF81 6E 0A 04
   FFFFFF81 63 FFFFFF81 38 08 08 FFFFFF81 70 07 FFFFFFA0 FFFFFF80 04 FFFFFF81 6C 01 12
   24 68 61 73 68 24 63 6F 6C 6F 6E 24 63 6F 6C 6F
   6E 20 05 06 FFFFFF81 72 07 00 FFFFFF81 73 02 06 56 65 63 74
   6F 72 15 04 FFFFFF81 74 FFFFFF81 77 10 06 FFFFFF81 37 FFFFFF81 75 FFFFFF81 76
   09 04 FFFFFF81 72 FFFFFF81 38 10 03 5C FFFFFF81 77 04 09 5E FFFFFF81 71
   FFFFFF84 FFFFFF80 FFFFFF84 FFFFFFC2 00 5F 08 09 FFFFFF81 79 07 FFFFFFC2 FFFFFF80 FFFFFF84 00 FFFFFF81
   7A 01 06 56 65 63 74 6F 72 15 02 FFFFFF81 7B 0E 04 FFFFFF81
   41 FFFFFF81 7C 09 04 FFFFFF81 79 FFFFFF81 38 08 08 FFFFFF81 7E 07 FFFFFFA0 FFFFFF80
   04 FFFFFF81 7B 01 07 56 65 63 74 6F 72 20 05 0A FFFFFF82 00
   07 FFFFFF84 FFFFFF80 FFFFFF80 FFFFFF80 00 FFFFFF82 01 02 0D 53 74 72 69 6E 67
   42 75 69 6C 64 65 72 10 04 FFFFFF82 02 FFFFFF82 05 0D 02 FFFFFF82
   03 0A 03 FFFFFF82 04 58 01 07 6D 75 74 61 62 6C 65 09
   04 FFFFFF82 00 FFFFFF82 03 08 09 FFFFFF82 07 07 FFFFFFC2 FFFFFF80 FFFFFF84 00 FFFFFF82 08
   01 0D 53 74 72 69 6E 67 42 75 69 6C 64 65 72 15
   02 FFFFFF82 09 0E 04 FFFFFF82 0A FFFFFF82 0C 0E 03 6A FFFFFF82 0B 09 03
   FFFFFF82 04 58 09 04 FFFFFF82 07 FFFFFF82 03 08 08 FFFFFF82 0E 07 FFFFFFA0 FFFFFF80
   04 FFFFFF82 09 01 0E 53 74 72 69 6E 67 42 75 69 6C 64
   65 72 20 05 0A FFFFFF82 10 07 FFFFFF84 FFFFFF80 FFFFFF80 FFFFFF80 00 FFFFFF82 11 02
   05 52 61 6E 67 65 10 04 FFFFFF81 37 FFFFFF82 12 09 04 FFFFFF82 10
   FFFFFF81 38 08 09 FFFFFF82 14 07 FFFFFFC2 FFFFFF80 FFFFFF84 00 FFFFFF82 15 01 05 52
   61 6E 67 65 15 02 FFFFFF82 16 0E 04 FFFFFF81 41 FFFFFF82 17 09 04
   FFFFFF82 14 FFFFFF81 38 08 08 FFFFFF82 19 07 FFFFFFA0 FFFFFF80 04 FFFFFF82 16 01 06
   52 61 6E 67 65 20 08 09 FFFFFF82 1B 07 FFFFFFC2 FFFFFF80 FFFFFF84 00 FFFFFF82
   1C 01 06 24 73 63 6F 70 65 15 02 FFFFFF82 1D 0E 04 FFFFFF82
   1E FFFFFF82 21 0E 03 6B FFFFFF82 1F 09 03 FFFFFF82 20 02 01 03 78
   6D 6C 09 04 FFFFFF82 22 FFFFFF82 23 01 08 54 6F 70 53 63 6F
   70 65 0A 03 FFFFFF82 20 02 08 08 FFFFFF82 25 07 FFFFFFA0 FFFFFF80 04 FFFFFF82
   1D 01 07 24 73 63 6F 70 65 20 08 07 FFFFFF82 27 07 FFFFFF84
   00 FFFFFF82 28 01 0D 63 75 72 72 65 6E 74 54 68 72 65
   61 64 15 02 FFFFFF82 29 10 03 0B FFFFFF82 2A 09 03 FFFFFF82 2B 0C
   02 06 54 68 72 65 61 64 05 0A FFFFFF82 2D 07 FFFFFF84 FFFFFF80 FFFFFF80
   FFFFFF80 00 FFFFFF82 2E 02 0A 42 69 67 44 65 63 69 6D 61 6C
   10 04 FFFFFF82 2F FFFFFF82 32 0D 02 FFFFFF82 30 0A 03 FFFFFF82 31 02 01
   04 6D 61 74 68 09 04 FFFFFF82 2D FFFFFF82 30 08 09 FFFFFF82 34 07
   FFFFFFC2 FFFFFF80 FFFFFF84 00 FFFFFF82 35 01 0A 42 69 67 44 65 63 69 6D
   61 6C 15 02 FFFFFF82 36 0E 04 FFFFFF82 37 FFFFFF82 39 0E 03 6B FFFFFF82
   38 09 03 FFFFFF82 31 02 09 04 FFFFFF82 34 FFFFFF82 30 08 08 FFFFFF82 3B
   07 FFFFFFA0 FFFFFF80 04 FFFFFF82 36 01 0B 42 69 67 44 65 63 69 6D
   61 6C 20 05 0A FFFFFF82 3D 07 FFFFFF84 FFFFFF80 FFFFFF80 FFFFFF80 00 FFFFFF82 3E 02
   06 42 69 67 49 6E 74 10 04 FFFFFF82 2F FFFFFF82 3F 09 04 FFFFFF82
   3D FFFFFF82 30 08 09 FFFFFF82 41 07 FFFFFFC2 FFFFFF80 FFFFFF84 00 FFFFFF82 42 01 06
   42 69 67 49 6E 74 15 02 FFFFFF82 43 0E 04 FFFFFF82 37 FFFFFF82 44
   09 04 FFFFFF82 41 FFFFFF82 30 08 08 FFFFFF82 46 07 FFFFFFA0 FFFFFF80 04 FFFFFF82 43
   01 07 42 69 67 49 6E 74 20 05 06 FFFFFF82 48 07 00 FFFFFF82
   49 02 05 45 71 75 69 76 15 04 FFFFFF82 4A FFFFFF82 4D 10 06
   FFFFFF82 2F FFFFFF82 4B FFFFFF82 4C 09 04 FFFFFF82 48 FFFFFF82 30 10 03 5C FFFFFF82
   4D 04 0A FFFFFF82 4E FFFFFF82 47 FFFFFF84 FFFFFF80 FFFFFF80 FFFFFFC2 00 5F 02 01 54
   05 06 FFFFFF82 50 07 00 FFFFFF82 51 02 0A 46 72 61 63 74 69
   6F 6E 61 6C 15 04 FFFFFF82 52 FFFFFF82 55 10 06 FFFFFF82 2F FFFFFF82 53
   FFFFFF82 54 09 04 FFFFFF82 50 FFFFFF82 30 10 03 5C FFFFFF82 55 04 0A FFFFFF82
   4E FFFFFF82 4F FFFFFF84 FFFFFF80 FFFFFF80 FFFFFFC2 00 5F 05 06 FFFFFF82 57 07 00 FFFFFF82
   58 02 08 49 6E 74 65 67 72 61 6C 15 04 FFFFFF82 59 FFFFFF82
   5C 10 06 FFFFFF82 2F FFFFFF82 5A FFFFFF82 5B 09 04 FFFFFF82 57 FFFFFF82 30 10
   03 5C FFFFFF82 5C 04 0A FFFFFF82 4E FFFFFF82 56 FFFFFF84 FFFFFF80 FFFFFF80 FFFFFFC2 00 5F
   05 06 FFFFFF82 5E 07 00 FFFFFF82 5F 02 07 4E 75 6D 65 72 69
   63 15 04 FFFFFF82 60 FFFFFF82 63 10 06 FFFFFF82 2F FFFFFF82 61 FFFFFF82 62 09
   04 FFFFFF82 5E FFFFFF82 30 10 03 5C FFFFFF82 63 04 0A FFFFFF82 4E FFFFFF82 5D
   FFFFFF84 FFFFFF80 FFFFFF80 FFFFFFC2 00 5F 08 09 FFFFFF82 65 07 FFFFFFC2 FFFFFF80 FFFFFF84 00 FFFFFF82
   66 01 07 4E 75 6D 65 72 69 63 15 02 FFFFFF82 67 0E 04
   FFFFFF82 37 FFFFFF82 68 09 04 FFFFFF82 65 FFFFFF82 30 08 08 FFFFFF82 6A 07 FFFFFFA0
   FFFFFF80 04 FFFFFF82 67 01 08 4E 75 6D 65 72 69 63 20 05 06
   FFFFFF82 6C 07 00 FFFFFF82 6D 02 07 4F 72 64 65 72 65 64 15
   04 FFFFFF82 6E FFFFFF82 71 10 06 FFFFFF82 2F FFFFFF82 6F FFFFFF82 70 09 04 FFFFFF82
   6C FFFFFF82 30 10 03 5C FFFFFF82 71 04 0A FFFFFF82 4E FFFFFF82 6B FFFFFF84 FFFFFF80
   FFFFFF80 FFFFFFC2 00 5F 08 09 FFFFFF82 73 07 FFFFFFC2 FFFFFF80 FFFFFF84 00 FFFFFF82 74 01
   07 4F 72 64 65 72 65 64 15 02 FFFFFF82 75 0E 04 FFFFFF82 37
   FFFFFF82 76 09 04 FFFFFF82 73 FFFFFF82 30 08 08 FFFFFF82 78 07 FFFFFFA0 FFFFFF80 04
   FFFFFF82 75 01 08 4F 72 64 65 72 65 64 20 05 06 FFFFFF82 7A
   07 00 FFFFFF82 7B 02 08 4F 72 64 65 72 69 6E 67 15 04
   FFFFFF82 7C FFFFFF82 7F 10 06 FFFFFF82 2F FFFFFF82 7D FFFFFF82 7E 09 04 FFFFFF82 7A
   FFFFFF82 30 10 03 5C FFFFFF82 7F 04 0A FFFFFF82 4E FFFFFF82 79 FFFFFF84 FFFFFF80 FFFFFF80
   FFFFFFC2 00 5F 08 09 FFFFFF83 01 07 FFFFFFC2 FFFFFF80 FFFFFF84 00 FFFFFF83 02 01 08
   4F 72 64 65 72 69 6E 67 15 02 FFFFFF83 03 0E 04 FFFFFF82 37
   FFFFFF83 04 09 04 FFFFFF83 01 FFFFFF82 30 08 08 FFFFFF83 06 07 FFFFFFA0 FFFFFF80 04
   FFFFFF83 03 01 09 4F 72 64 65 72 69 6E 67 20 05 06 FFFFFF83
   08 07 00 FFFFFF83 09 02 0F 50 61 72 74 69 61 6C 4F 72
   64 65 72 69 6E 67 15 04 FFFFFF83 0A FFFFFF83 0D 10 06 FFFFFF82 2F
   FFFFFF83 0B FFFFFF83 0C 09 04 FFFFFF83 08 FFFFFF82 30 10 03 5C FFFFFF83 0D 04
   0A FFFFFF82 4E FFFFFF83 07 FFFFFF84 FFFFFF80 FFFFFF80 FFFFFFC2 00 5F 05 06 FFFFFF83 0F 07
   00 FFFFFF83 10 02 10 50 61 72 74 69 61 6C 6C 79 4F 72
   64 65 72 65 64 15 04 FFFFFF83 11 FFFFFF83 14 10 06 FFFFFF82 2F FFFFFF83
   12 FFFFFF83 13 09 04 FFFFFF83 0F FFFFFF82 30 10 03 5C FFFFFF83 14 04 0A
   FFFFFF82 4E FFFFFF83 0E FFFFFF84 FFFFFF80 FFFFFF80 FFFFFFC2 00 5F 08 07 FFFFFF83 16 07 FFFFFF84
   00 FFFFFF83 17 01 05 54 75 70 6C 65 15 04 FFFFFF83 18 FFFFFF83 1D
   14 04 FFFFFF83 19 FFFFFF83 1F 10 05 06 FFFFFF83 1A FFFFFF83 1C 09 03 FFFFFF83
   1B 02 02 06 54 75 70 6C 65 31 10 03 5C FFFFFF83 1D 04
   0A FFFFFF83 1E FFFFFF83 15 FFFFFF84 FFFFFF80 FFFFFF80 FFFFFFC2 00 5F 02 02 41 31 08
   08 FFFFFF83 20 FFFFFF83 15 FFFFFFC0 00 FFFFFF83 1C 01 02 78 31 28 06 FFFFFF83
   15 FFFFFF83 22 FFFFFF83 25 10 03 06 FFFFFF83 23 09 03 FFFFFF83 24 02 02
   0A 64 65 70 72 65 63 61 74 65 64 21 02 FFFFFF83 26 01
   22 55 73 65 20 54 75 70 6C 65 31 28 78 29 20 74
   6F 20 63 72 65 61 74 65 20 61 20 31 2D 74 75 70
   6C 65 2E 08 07 FFFFFF83 16 07 FFFFFF84 00 FFFFFF83 28 15 06 FFFFFF83 29
   FFFFFF83 2E FFFFFF83 30 14 06 FFFFFF83 2A FFFFFF83 32 FFFFFF83 33 10 07 06 FFFFFF83
   2B FFFFFF83 2D FFFFFF83 2F 09 03 FFFFFF83 2C 02 02 06 54 75 70 6C
   65 32 10 03 5C FFFFFF83 2E 04 0A FFFFFF83 1E FFFFFF83 27 FFFFFF84 FFFFFF80 FFFFFF80
   FFFFFFC2 00 5F 10 03 5C FFFFFF83 30 04 0A FFFFFF83 31 FFFFFF83 27 FFFFFF84 FFFFFF80
   FFFFFF80 FFFFFFC2 00 5F 02 02 41 32 08 08 FFFFFF83 20 FFFFFF83 27 FFFFFFC0 00
   FFFFFF83 2D 08 08 FFFFFF83 34 FFFFFF83 27 FFFFFFC0 00 FFFFFF83 2F 01 02 78 32
   28 06 FFFFFF83 27 FFFFFF83 22 FFFFFF83 36 21 02 FFFFFF83 37 01 2B 55 73
   65 20 28 28 78 31 2C 20 78 32 2C 20 2E 2E 2E 29
   29 20 73 79 6E 74 61 78 20 74 6F 20 63 72 65 61
   74 65 20 54 75 70 6C 65 73 08 07 FFFFFF83 16 07 FFFFFF84 00
   FFFFFF83 39 15 08 FFFFFF83 3A FFFFFF83 3F FFFFFF83 41 FFFFFF83 43 14 08 FFFFFF83 3B
   FFFFFF83 45 FFFFFF83 46 FFFFFF83 47 10 09 06 FFFFFF83 3C FFFFFF83 3E FFFFFF83 40 FFFFFF83
   42 09 03 FFFFFF83 3D 02 02 06 54 75 70 6C 65 33 10 03
   5C FFFFFF83 3F 04 0A FFFFFF83 1E FFFFFF83 38 FFFFFF84 FFFFFF80 FFFFFF80 FFFFFFC2 00 5F 10
   03 5C FFFFFF83 41 04 0A FFFFFF83 31 FFFFFF83 38 FFFFFF84 FFFFFF80 FFFFFF80 FFFFFFC2 00 5F
   10 03 5C FFFFFF83 43 04 0A FFFFFF83 44 FFFFFF83 38 FFFFFF84 FFFFFF80 FFFFFF80 FFFFFFC2 00
   5F 02 02 41 33 08 08 FFFFFF83 20 FFFFFF83 38 FFFFFFC0 00 FFFFFF83 3E 08
   08 FFFFFF83 34 FFFFFF83 38 FFFFFFC0 00 FFFFFF83 40 08 08 FFFFFF83 48 FFFFFF83 38 FFFFFFC0
   00 FFFFFF83 42 01 02 78 33 28 06 FFFFFF83 38 FFFFFF83 22 FFFFFF83 36 08
   07 FFFFFF83 16 07 FFFFFF84 00 FFFFFF83 4B 15 0A FFFFFF83 4C FFFFFF83 51 FFFFFF83 53
   FFFFFF83 55 FFFFFF83 57 14 0A FFFFFF83 4D FFFFFF83 59 FFFFFF83 5A FFFFFF83 5B FFFFFF83 5C
   10 0B 06 FFFFFF83 4E FFFFFF83 50 FFFFFF83 52 FFFFFF83 54 FFFFFF83 56 09 03 FFFFFF83
   4F 02 02 06 54 75 70 6C 65 34 10 03 5C FFFFFF83 51 04
   0A FFFFFF83 1E FFFFFF83 4A FFFFFF84 FFFFFF80 FFFFFF80 FFFFFFC2 00 5F 10 03 5C FFFFFF83 53
   04 0A FFFFFF83 31 FFFFFF83 4A FFFFFF84 FFFFFF80 FFFFFF80 FFFFFFC2 00 5F 10 03 5C FFFFFF83
   55 04 0A FFFFFF83 44 FFFFFF83 4A FFFFFF84 FFFFFF80 FFFFFF80 FFFFFFC2 00 5F 10 03 5C
   FFFFFF83 57 04 0A FFFFFF83 58 FFFFFF83 4A FFFFFF84 FFFFFF80 FFFFFF80 FFFFFFC2 00 5F 02 02
   41 34 08 08 FFFFFF83 20 FFFFFF83 4A FFFFFFC0 00 FFFFFF83 50 08 08 FFFFFF83 34
   FFFFFF83 4A FFFFFFC0 00 FFFFFF83 52 08 08 FFFFFF83 48 FFFFFF83 4A FFFFFFC0 00 FFFFFF83 54
   08 08 FFFFFF83 5D FFFFFF83 4A FFFFFFC0 00 FFFFFF83 56 01 02 78 34 28 06
   FFFFFF83 4A FFFFFF83 22 FFFFFF83 36 08 07 FFFFFF83 16 07 FFFFFF84 00 FFFFFF83 60 15
   0C FFFFFF83 61 FFFFFF83 66 FFFFFF83 68 FFFFFF83 6A FFFFFF83 6C FFFFFF83 6E 14 0C FFFFFF83
   62 FFFFFF83 70 FFFFFF83 71 FFFFFF83 72 FFFFFF83 73 FFFFFF83 74 10 0D 06 FFFFFF83 63
   FFFFFF83 65 FFFFFF83 67 FFFFFF83 69 FFFFFF83 6B FFFFFF83 6D 09 03 FFFFFF83 64 02 02
   06 54 75 70 6C 65 35 10 03 5C FFFFFF83 66 04 0A FFFFFF83 1E
   FFFFFF83 5F FFFFFF84 FFFFFF80 FFFFFF80 FFFFFFC2 00 5F 10 03 5C FFFFFF83 68 04 0A FFFFFF83
   31 FFFFFF83 5F FFFFFF84 FFFFFF80 FFFFFF80 FFFFFFC2 00 5F 10 03 5C FFFFFF83 6A 04 0A
   FFFFFF83 44 FFFFFF83 5F FFFFFF84 FFFFFF80 FFFFFF80 FFFFFFC2 00 5F 10 03 5C FFFFFF83 6C 04
   0A FFFFFF83 58 FFFFFF83 5F FFFFFF84 FFFFFF80 FFFFFF80 FFFFFFC2 00 5F 10 03 5C FFFFFF83 6E
   04 0A FFFFFF83 6F FFFFFF83 5F FFFFFF84 FFFFFF80 FFFFFF80 FFFFFFC2 00 5F 02 02 41 35
   08 08 FFFFFF83 20 FFFFFF83 5F FFFFFFC0 00 FFFFFF83 65 08 08 FFFFFF83 34 FFFFFF83 5F
   FFFFFFC0 00 FFFFFF83 67 08 08 FFFFFF83 48 FFFFFF83 5F FFFFFFC0 00 FFFFFF83 69 08 08
   FFFFFF83 5D FFFFFF83 5F FFFFFFC0 00 FFFFFF83 6B 08 08 FFFFFF83 75 FFFFFF83 5F FFFFFFC0 00
   FFFFFF83 6D 01 02 78 35 28 06 FFFFFF83 5F FFFFFF83 22 FFFFFF83 36 08 07
   FFFFFF83 16 07 FFFFFF84 00 FFFFFF83 78 15 0E FFFFFF83 79 FFFFFF83 7E FFFFFF84 00 FFFFFF84
   02 FFFFFF84 04 FFFFFF84 06 FFFFFF84 08 14 0E FFFFFF83 7A FFFFFF84 0A FFFFFF84 0B FFFFFF84
   0C FFFFFF84 0D FFFFFF84 0E FFFFFF84 0F 10 0F 06 FFFFFF83 7B FFFFFF83 7D FFFFFF83 7F
   FFFFFF84 01 FFFFFF84 03 FFFFFF84 05 FFFFFF84 07 09 03 FFFFFF83 7C 02 02 06 54
   75 70 6C 65 36 10 03 5C FFFFFF83 7E 04 0A FFFFFF83 1E FFFFFF83 77
   FFFFFF84 FFFFFF80 FFFFFF80 FFFFFFC2 00 5F 10 03 5C FFFFFF84 00 04 0A FFFFFF83 31 FFFFFF83
   77 FFFFFF84 FFFFFF80 FFFFFF80 FFFFFFC2 00 5F 10 03 5C FFFFFF84 02 04 0A FFFFFF83 44
   FFFFFF83 77 FFFFFF84 FFFFFF80 FFFFFF80 FFFFFFC2 00 5F 10 03 5C FFFFFF84 04 04 0A FFFFFF83
   58 FFFFFF83 77 FFFFFF84 FFFFFF80 FFFFFF80 FFFFFFC2 00 5F 10 03 5C FFFFFF84 06 04 0A
   FFFFFF83 6F FFFFFF83 77 FFFFFF84 FFFFFF80 FFFFFF80 FFFFFFC2 00 5F 10 03 5C FFFFFF84 08 04
   0A FFFFFF84 09 FFFFFF83 77 FFFFFF84 FFFFFF80 FFFFFF80 FFFFFFC2 00 5F 02 02 41 36 08
   08 FFFFFF83 20 FFFFFF83 77 FFFFFFC0 00 FFFFFF83 7D 08 08 FFFFFF83 34 FFFFFF83 77 FFFFFFC0
   00 FFFFFF83 7F 08 08 FFFFFF83 48 FFFFFF83 77 FFFFFFC0 00 FFFFFF84 01 08 08 FFFFFF83
   5D FFFFFF83 77 FFFFFFC0 00 FFFFFF84 03 08 08 FFFFFF83 75 FFFFFF83 77 FFFFFFC0 00 FFFFFF84
   05 08 08 FFFFFF84 10 FFFFFF83 77 FFFFFFC0 00 FFFFFF84 07 01 02 78 36 28
   06 FFFFFF83 77 FFFFFF83 22 FFFFFF83 36 08 07 FFFFFF83 16 07 FFFFFF84 00 FFFFFF84 13
   15 10 FFFFFF84 14 FFFFFF84 19 FFFFFF84 1B FFFFFF84 1D FFFFFF84 1F FFFFFF84 21 FFFFFF84 23
   FFFFFF84 25 14 10 FFFFFF84 15 FFFFFF84 27 FFFFFF84 28 FFFFFF84 29 FFFFFF84 2A FFFFFF84 2B
   FFFFFF84 2C FFFFFF84 2D 10 11 06 FFFFFF84 16 FFFFFF84 18 FFFFFF84 1A FFFFFF84 1C FFFFFF84
   1E FFFFFF84 20 FFFFFF84 22 FFFFFF84 24 09 03 FFFFFF84 17 02 02 06 54 75
   70 6C 65 37 10 03 5C FFFFFF84 19 04 0A FFFFFF83 1E FFFFFF84 12 FFFFFF84
   FFFFFF80 FFFFFF80 FFFFFFC2 00 5F 10 03 5C FFFFFF84 1B 04 0A FFFFFF83 31 FFFFFF84 12
   FFFFFF84 FFFFFF80 FFFFFF80 FFFFFFC2 00 5F 10 03 5C FFFFFF84 1D 04 0A FFFFFF83 44 FFFFFF84
   12 FFFFFF84 FFFFFF80 FFFFFF80 FFFFFFC2 00 5F 10 03 5C FFFFFF84 1F 04 0A FFFFFF83 58
   FFFFFF84 12 FFFFFF84 FFFFFF80 FFFFFF80 FFFFFFC2 00 5F 10 03 5C FFFFFF84 21 04 0A FFFFFF83
   6F FFFFFF84 12 FFFFFF84 FFFFFF80 FFFFFF80 FFFFFFC2 00 5F 10 03 5C FFFFFF84 23 04 0A
   FFFFFF84 09 FFFFFF84 12 FFFFFF84 FFFFFF80 FFFFFF80 FFFFFFC2 00 5F 10 03 5C FFFFFF84 25 04
   0A FFFFFF84 26 FFFFFF84 12 FFFFFF84 FFFFFF80 FFFFFF80 FFFFFFC2 00 5F 02 02 41 37 08
   08 FFFFFF83 20 FFFFFF84 12 FFFFFFC0 00 FFFFFF84 18 08 08 FFFFFF83 34 FFFFFF84 12 FFFFFFC0
   00 FFFFFF84 1A 08 08 FFFFFF83 48 FFFFFF84 12 FFFFFFC0 00 FFFFFF84 1C 08 08 FFFFFF83
   5D FFFFFF84 12 FFFFFFC0 00 FFFFFF84 1E 08 08 FFFFFF83 75 FFFFFF84 12 FFFFFFC0 00 FFFFFF84
   20 08 08 FFFFFF84 10 FFFFFF84 12 FFFFFFC0 00 FFFFFF84 22 08 08 FFFFFF84 2E FFFFFF84
   12 FFFFFFC0 00 FFFFFF84 24 01 02 78 37 28 06 FFFFFF84 12 FFFFFF83 22 FFFFFF83
   36 08 07 FFFFFF83 16 07 FFFFFF84 00 FFFFFF84 31 15 12 FFFFFF84 32 FFFFFF84 37
   FFFFFF84 39 FFFFFF84 3B FFFFFF84 3D FFFFFF84 3F FFFFFF84 41 FFFFFF84 43 FFFFFF84 45 14 12
   FFFFFF84 33 FFFFFF84 47 FFFFFF84 48 FFFFFF84 49 FFFFFF84 4A FFFFFF84 4B FFFFFF84 4C FFFFFF84 4D
   FFFFFF84 4E 10 13 06 FFFFFF84 34 FFFFFF84 36 FFFFFF84 38 FFFFFF84 3A FFFFFF84 3C FFFFFF84
   3E FFFFFF84 40 FFFFFF84 42 FFFFFF84 44 09 03 FFFFFF84 35 02 02 06 54 75
   70 6C 65 38 10 03 5C FFFFFF84 37 04 0A FFFFFF83 1E FFFFFF84 30 FFFFFF84
   FFFFFF80 FFFFFF80 FFFFFFC2 00 5F 10 03 5C FFFFFF84 39 04 0A FFFFFF83 31 FFFFFF84 30
   FFFFFF84 FFFFFF80 FFFFFF80 FFFFFFC2 00 5F 10 03 5C FFFFFF84 3B 04 0A FFFFFF83 44 FFFFFF84
   30 FFFFFF84 FFFFFF80 FFFFFF80 FFFFFFC2 00 5F 10 03 5C FFFFFF84 3D 04 0A FFFFFF83 58
   FFFFFF84 30 FFFFFF84 FFFFFF80 FFFFFF80 FFFFFFC2 00 5F 10 03 5C FFFFFF84 3F 04 0A FFFFFF83
   6F FFFFFF84 30 FFFFFF84 FFFFFF80 FFFFFF80 FFFFFFC2 00 5F 10 03 5C FFFFFF84 41 04 0A
   FFFFFF84 09 FFFFFF84 30 FFFFFF84 FFFFFF80 FFFFFF80 FFFFFFC2 00 5F 10 03 5C FFFFFF84 43 04
   0A FFFFFF84 26 FFFFFF84 30 FFFFFF84 FFFFFF80 FFFFFF80 FFFFFFC2 00 5F 10 03 5C FFFFFF84 45
   04 0A FFFFFF84 46 FFFFFF84 30 FFFFFF84 FFFFFF80 FFFFFF80 FFFFFFC2 00 5F 02 02 41 38
   08 08 FFFFFF83 20 FFFFFF84 30 FFFFFFC0 00 FFFFFF84 36 08 08 FFFFFF83 34 FFFFFF84 30
   FFFFFFC0 00 FFFFFF84 38 08 08 FFFFFF83 48 FFFFFF84 30 FFFFFFC0 00 FFFFFF84 3A 08 08
   FFFFFF83 5D FFFFFF84 30 FFFFFFC0 00 FFFFFF84 3C 08 08 FFFFFF83 75 FFFFFF84 30 FFFFFFC0 00
   FFFFFF84 3E 08 08 FFFFFF84 10 FFFFFF84 30 FFFFFFC0 00 FFFFFF84 40 08 08 FFFFFF84 2E
   FFFFFF84 30 FFFFFFC0 00 FFFFFF84 42 08 08 FFFFFF84 4F FFFFFF84 30 FFFFFFC0 00 FFFFFF84 44
   01 02 78 38 28 06 FFFFFF84 30 FFFFFF83 22 FFFFFF83 36 08 07 FFFFFF83 16
   07 FFFFFF84 00 FFFFFF84 52 15 14 FFFFFF84 53 FFFFFF84 58 FFFFFF84 5A FFFFFF84 5C FFFFFF84
   5E FFFFFF84 60 FFFFFF84 62 FFFFFF84 64 FFFFFF84 66 FFFFFF84 68 14 14 FFFFFF84 54 FFFFFF84
   6A FFFFFF84 6B FFFFFF84 6C FFFFFF84 6D FFFFFF84 6E FFFFFF84 6F FFFFFF84 70 FFFFFF84 71 FFFFFF84
   72 10 15 06 FFFFFF84 55 FFFFFF84 57 FFFFFF84 59 FFFFFF84 5B FFFFFF84 5D FFFFFF84 5F
   FFFFFF84 61 FFFFFF84 63 FFFFFF84 65 FFFFFF84 67 09 03 FFFFFF84 56 02 02 06 54
   75 70 6C 65 39 10 03 5C FFFFFF84 58 04 0A FFFFFF83 1E FFFFFF84 51
   FFFFFF84 FFFFFF80 FFFFFF80 FFFFFFC2 00 5F 10 03 5C FFFFFF84 5A 04 0A FFFFFF83 31 FFFFFF84
   51 FFFFFF84 FFFFFF80 FFFFFF80 FFFFFFC2 00 5F 10 03 5C FFFFFF84 5C 04 0A FFFFFF83 44
   FFFFFF84 51 FFFFFF84 FFFFFF80 FFFFFF80 FFFFFFC2 00 5F 10 03 5C FFFFFF84 5E 04 0A FFFFFF83
   58 FFFFFF84 51 FFFFFF84 FFFFFF80 FFFFFF80 FFFFFFC2 00 5F 10 03 5C FFFFFF84 60 04 0A
   FFFFFF83 6F FFFFFF84 51 FFFFFF84 FFFFFF80 FFFFFF80 FFFFFFC2 00 5F 10 03 5C FFFFFF84 62 04
   0A FFFFFF84 09 FFFFFF84 51 FFFFFF84 FFFFFF80 FFFFFF80 FFFFFFC2 00 5F 10 03 5C FFFFFF84 64
   04 0A FFFFFF84 26 FFFFFF84 51 FFFFFF84 FFFFFF80 FFFFFF80 FFFFFFC2 00 5F 10 03 5C FFFFFF84
   66 04 0A FFFFFF84 46 FFFFFF84 51 FFFFFF84 FFFFFF80 FFFFFF80 FFFFFFC2 00 5F 10 03 5C
   FFFFFF84 68 04 0A FFFFFF84 69 FFFFFF84 51 FFFFFF84 FFFFFF80 FFFFFF80 FFFFFFC2 00 5F 02 02
   41 39 08 08 FFFFFF83 20 FFFFFF84 51 FFFFFFC0 00 FFFFFF84 57 08 08 FFFFFF83 34
   FFFFFF84 51 FFFFFFC0 00 FFFFFF84 59 08 08 FFFFFF83 48 FFFFFF84 51 FFFFFFC0 00 FFFFFF84 5B
   08 08 FFFFFF83 5D FFFFFF84 51 FFFFFFC0 00 FFFFFF84 5D 08 08 FFFFFF83 75 FFFFFF84 51
   FFFFFFC0 00 FFFFFF84 5F 08 08 FFFFFF84 10 FFFFFF84 51 FFFFFFC0 00 FFFFFF84 61 08 08
   FFFFFF84 2E FFFFFF84 51 FFFFFFC0 00 FFFFFF84 63 08 08 FFFFFF84 4F FFFFFF84 51 FFFFFFC0 00
   FFFFFF84 65 08 08 FFFFFF84 73 FFFFFF84 51 FFFFFFC0 00 FFFFFF84 67 01 02 78 39
   28 06 FFFFFF84 51 FFFFFF83 22 FFFFFF83 36 08 07 FFFFFF83 16 07 FFFFFF84 00 FFFFFF84
   76 15 16 FFFFFF84 77 FFFFFF84 7C FFFFFF84 7E FFFFFF85 00 FFFFFF85 02 FFFFFF85 04 FFFFFF85
   06 FFFFFF85 08 FFFFFF85 0A FFFFFF85 0C FFFFFF85 0E 14 16 FFFFFF84 78 FFFFFF85 10 FFFFFF85
   11 FFFFFF85 12 FFFFFF85 13 FFFFFF85 14 FFFFFF85 15 FFFFFF85 16 FFFFFF85 17 FFFFFF85 18 FFFFFF85
   19 10 17 06 FFFFFF84 79 FFFFFF84 7B FFFFFF84 7D FFFFFF84 7F FFFFFF85 01 FFFFFF85 03
   FFFFFF85 05 FFFFFF85 07 FFFFFF85 09 FFFFFF85 0B FFFFFF85 0D 09 03 FFFFFF84 7A 02 02
   07 54 75 70 6C 65 31 30 10 03 5C FFFFFF84 7C 04 0A FFFFFF83
   1E FFFFFF84 75 FFFFFF84 FFFFFF80 FFFFFF80 FFFFFFC2 00 5F 10 03 5C FFFFFF84 7E 04 0A
   FFFFFF83 31 FFFFFF84 75 FFFFFF84 FFFFFF80 FFFFFF80 FFFFFFC2 00 5F 10 03 5C FFFFFF85 00 04
   0A FFFFFF83 44 FFFFFF84 75 FFFFFF84 FFFFFF80 FFFFFF80 FFFFFFC2 00 5F 10 03 5C FFFFFF85 02
   04 0A FFFFFF83 58 FFFFFF84 75 FFFFFF84 FFFFFF80 FFFFFF80 FFFFFFC2 00 5F 10 03 5C FFFFFF85
   04 04 0A FFFFFF83 6F FFFFFF84 75 FFFFFF84 FFFFFF80 FFFFFF80 FFFFFFC2 00 5F 10 03 5C
   FFFFFF85 06 04 0A FFFFFF84 09 FFFFFF84 75 FFFFFF84 FFFFFF80 FFFFFF80 FFFFFFC2 00 5F 10 03
   5C FFFFFF85 08 04 0A FFFFFF84 26 FFFFFF84 75 FFFFFF84 FFFFFF80 FFFFFF80 FFFFFFC2 00 5F 10
   03 5C FFFFFF85 0A 04 0A FFFFFF84 46 FFFFFF84 75 FFFFFF84 FFFFFF80 FFFFFF80 FFFFFFC2 00 5F
   10 03 5C FFFFFF85 0C 04 0A FFFFFF84 69 FFFFFF84 75 FFFFFF84 FFFFFF80 FFFFFF80 FFFFFFC2 00
   5F 10 03 5C FFFFFF85 0E 04 0A FFFFFF85 0F FFFFFF84 75 FFFFFF84 FFFFFF80 FFFFFF80 FFFFFFC2
   00 5F 02 03 41 31 30 08 08 FFFFFF83 20 FFFFFF84 75 FFFFFFC0 00 FFFFFF84
   7B 08 08 FFFFFF83 34 FFFFFF84 75 FFFFFFC0 00 FFFFFF84 7D 08 08 FFFFFF83 48 FFFFFF84
   75 FFFFFFC0 00 FFFFFF84 7F 08 08 FFFFFF83 5D FFFFFF84 75 FFFFFFC0 00 FFFFFF85 01 08
   08 FFFFFF83 75 FFFFFF84 75 FFFFFFC0 00 FFFFFF85 03 08 08 FFFFFF84 10 FFFFFF84 75 FFFFFFC0
   00 FFFFFF85 05 08 08 FFFFFF84 2E FFFFFF84 75 FFFFFFC0 00 FFFFFF85 07 08 08 FFFFFF84
   4F FFFFFF84 75 FFFFFFC0 00 FFFFFF85 09 08 08 FFFFFF84 73 FFFFFF84 75 FFFFFFC0 00 FFFFFF85
   0B 08 08 FFFFFF85 1A FFFFFF84 75 FFFFFFC0 00 FFFFFF85 0D 01 03 78 31 30
   28 06 FFFFFF84 75 FFFFFF83 22 FFFFFF83 36 08 07 FFFFFF83 16 07 FFFFFF84 00 FFFFFF85
   1D 15 18 FFFFFF85 1E FFFFFF85 23 FFFFFF85 25 FFFFFF85 27 FFFFFF85 29 FFFFFF85 2B FFFFFF85
   2D FFFFFF85 2F FFFFFF85 31 FFFFFF85 33 FFFFFF85 35 FFFFFF85 37 14 18 FFFFFF85 1F FFFFFF85
   39 FFFFFF85 3A FFFFFF85 3B FFFFFF85 3C FFFFFF85 3D FFFFFF85 3E FFFFFF85 3F FFFFFF85 40 FFFFFF85
   41 FFFFFF85 42 FFFFFF85 43 10 19 06 FFFFFF85 20 FFFFFF85 22 FFFFFF85 24 FFFFFF85 26
   FFFFFF85 28 FFFFFF85 2A FFFFFF85 2C FFFFFF85 2E FFFFFF85 30 FFFFFF85 32 FFFFFF85 34 FFFFFF85 36
   09 03 FFFFFF85 21 02 02 07 54 75 70 6C 65 31 31 10 03
   5C FFFFFF85 23 04 0A FFFFFF83 1E FFFFFF85 1C FFFFFF84 FFFFFF80 FFFFFF80 FFFFFFC2 00 5F 10
   03 5C FFFFFF85 25 04 0A FFFFFF83 31 FFFFFF85 1C FFFFFF84 FFFFFF80 FFFFFF80 FFFFFFC2 00 5F
   10 03 5C FFFFFF85 27 04 0A FFFFFF83 44 FFFFFF85 1C FFFFFF84 FFFFFF80 FFFFFF80 FFFFFFC2 00
   5F 10 03 5C FFFFFF85 29 04 0A FFFFFF83 58 FFFFFF85 1C FFFFFF84 FFFFFF80 FFFFFF80 FFFFFFC2
   00 5F 10 03 5C FFFFFF85 2B 04 0A FFFFFF83 6F FFFFFF85 1C FFFFFF84 FFFFFF80 FFFFFF80
   FFFFFFC2 00 5F 10 03 5C FFFFFF85 2D 04 0A FFFFFF84 09 FFFFFF85 1C FFFFFF84 FFFFFF80
   FFFFFF80 FFFFFFC2 00 5F 10 03 5C FFFFFF85 2F 04 0A FFFFFF84 26 FFFFFF85 1C FFFFFF84
   FFFFFF80 FFFFFF80 FFFFFFC2 00 5F 10 03 5C FFFFFF85 31 04 0A FFFFFF84 46 FFFFFF85 1C
   FFFFFF84 FFFFFF80 FFFFFF80 FFFFFFC2 00 5F 10 03 5C FFFFFF85 33 04 0A FFFFFF84 69 FFFFFF85
   1C FFFFFF84 FFFFFF80 FFFFFF80 FFFFFFC2 00 5F 10 03 5C FFFFFF85 35 04 0A FFFFFF85 0F
   FFFFFF85 1C FFFFFF84 FFFFFF80 FFFFFF80 FFFFFFC2 00 5F 10 03 5C FFFFFF85 37 04 0A FFFFFF85
   38 FFFFFF85 1C FFFFFF84 FFFFFF80 FFFFFF80 FFFFFFC2 00 5F 02 03 41 31 31 08 08
   FFFFFF83 20 FFFFFF85 1C FFFFFFC0 00 FFFFFF85 22 08 08 FFFFFF83 34 FFFFFF85 1C FFFFFFC0 00
   FFFFFF85 24 08 08 FFFFFF83 48 FFFFFF85 1C FFFFFFC0 00 FFFFFF85 26 08 08 FFFFFF83 5D
   FFFFFF85 1C FFFFFFC0 00 FFFFFF85 28 08 08 FFFFFF83 75 FFFFFF85 1C FFFFFFC0 00 FFFFFF85 2A
   08 08 FFFFFF84 10 FFFFFF85 1C FFFFFFC0 00 FFFFFF85 2C 08 08 FFFFFF84 2E FFFFFF85 1C
   FFFFFFC0 00 FFFFFF85 2E 08 08 FFFFFF84 4F FFFFFF85 1C FFFFFFC0 00 FFFFFF85 30 08 08
   FFFFFF84 73 FFFFFF85 1C FFFFFFC0 00 FFFFFF85 32 08 08 FFFFFF85 1A FFFFFF85 1C FFFFFFC0 00
   FFFFFF85 34 08 08 FFFFFF85 44 FFFFFF85 1C FFFFFFC0 00 FFFFFF85 36 01 03 78 31
   31 28 06 FFFFFF85 1C FFFFFF83 22 FFFFFF83 36 08 07 FFFFFF83 16 07 FFFFFF84 00
   FFFFFF85 47 15 1A FFFFFF85 48 FFFFFF85 4D FFFFFF85 4F FFFFFF85 51 FFFFFF85 53 FFFFFF85 55
   FFFFFF85 57 FFFFFF85 59 FFFFFF85 5B FFFFFF85 5D FFFFFF85 5F FFFFFF85 61 FFFFFF85 63 14 1A
   FFFFFF85 49 FFFFFF85 65 FFFFFF85 66 FFFFFF85 67 FFFFFF85 68 FFFFFF85 69 FFFFFF85 6A FFFFFF85 6B
   FFFFFF85 6C FFFFFF85 6D FFFFFF85 6E FFFFFF85 6F FFFFFF85 70 10 1B 06 FFFFFF85 4A FFFFFF85
   4C FFFFFF85 4E FFFFFF85 50 FFFFFF85 52 FFFFFF85 54 FFFFFF85 56 FFFFFF85 58 FFFFFF85 5A FFFFFF85
   5C FFFFFF85 5E FFFFFF85 60 FFFFFF85 62 09 03 FFFFFF85 4B 02 02 07 54 75
   70 6C 65 31 32 10 03 5C FFFFFF85 4D 04 0A FFFFFF83 1E FFFFFF85 46
   FFFFFF84 FFFFFF80 FFFFFF80 FFFFFFC2 00 5F 10 03 5C FFFFFF85 4F 04 0A FFFFFF83 31 FFFFFF85
   46 FFFFFF84 FFFFFF80 FFFFFF80 FFFFFFC2 00 5F 10 03 5C FFFFFF85 51 04 0A FFFFFF83 44
   FFFFFF85 46 FFFFFF84 FFFFFF80 FFFFFF80 FFFFFFC2 00 5F 10 03 5C FFFFFF85 53 04 0A FFFFFF83
   58 FFFFFF85 46 FFFFFF84 FFFFFF80 FFFFFF80 FFFFFFC2 00 5F 10 03 5C FFFFFF85 55 04 0A
   FFFFFF83 6F FFFFFF85 46 FFFFFF84 FFFFFF80 FFFFFF80 FFFFFFC2 00 5F 10 03 5C FFFFFF85 57 04
   0A FFFFFF84 09 FFFFFF85 46 FFFFFF84 FFFFFF80 FFFFFF80 FFFFFFC2 00 5F 10 03 5C FFFFFF85 59
   04 0A FFFFFF84 26 FFFFFF85 46 FFFFFF84 FFFFFF80 FFFFFF80 FFFFFFC2 00 5F 10 03 5C FFFFFF85
   5B 04 0A FFFFFF84 46 FFFFFF85 46 FFFFFF84 FFFFFF80 FFFFFF80 FFFFFFC2 00 5F 10 03 5C
   FFFFFF85 5D 04 0A FFFFFF84 69 FFFFFF85 46 FFFFFF84 FFFFFF80 FFFFFF80 FFFFFFC2 00 5F 10 03
   5C FFFFFF85 5F 04 0A FFFFFF85 0F FFFFFF85 46 FFFFFF84 FFFFFF80 FFFFFF80 FFFFFFC2 00 5F 10
   03 5C FFFFFF85 61 04 0A FFFFFF85 38 FFFFFF85 46 FFFFFF84 FFFFFF80 FFFFFF80 FFFFFFC2 00 5F
   10 03 5C FFFFFF85 63 04 0A FFFFFF85 64 FFFFFF85 46 FFFFFF84 FFFFFF80 FFFFFF80 FFFFFFC2 00
   5F 02 03 41 31 32 08 08 FFFFFF83 20 FFFFFF85 46 FFFFFFC0 00 FFFFFF85 4C
   08 08 FFFFFF83 34 FFFFFF85 46 FFFFFFC0 00 FFFFFF85 4E 08 08 FFFFFF83 48 FFFFFF85 46
   FFFFFFC0 00 FFFFFF85 50 08 08 FFFFFF83 5D FFFFFF85 46 FFFFFFC0 00 FFFFFF85 52 08 08
   FFFFFF83 75 FFFFFF85 46 FFFFFFC0 00 FFFFFF85 54 08 08 FFFFFF84 10 FFFFFF85 46 FFFFFFC0 00
   FFFFFF85 56 08 08 FFFFFF84 2E FFFFFF85 46 FFFFFFC0 00 FFFFFF85 58 08 08 FFFFFF84 4F
   FFFFFF85 46 FFFFFFC0 00 FFFFFF85 5A 08 08 FFFFFF84 73 FFFFFF85 46 FFFFFFC0 00 FFFFFF85 5C
   08 08 FFFFFF85 1A FFFFFF85 46 FFFFFFC0 00 FFFFFF85 5E 08 08 FFFFFF85 44 FFFFFF85 46
   FFFFFFC0 00 FFFFFF85 60 08 08 FFFFFF85 71 FFFFFF85 46 FFFFFFC0 00 FFFFFF85 62 01 03
   78 31 32 28 06 FFFFFF85 46 FFFFFF83 22 FFFFFF83 36 08 07 FFFFFF83 16 07
   FFFFFF84 00 FFFFFF85 74 15 1C FFFFFF85 75 FFFFFF85 7A FFFFFF85 7C FFFFFF85 7E FFFFFF86 00
   FFFFFF86 02 FFFFFF86 04 FFFFFF86 06 FFFFFF86 08 FFFFFF86 0A FFFFFF86 0C FFFFFF86 0E FFFFFF86 10
   FFFFFF86 12 14 1C FFFFFF85 76 FFFFFF86 14 FFFFFF86 15 FFFFFF86 16 FFFFFF86 17 FFFFFF86 18
   FFFFFF86 19 FFFFFF86 1A FFFFFF86 1B FFFFFF86 1C FFFFFF86 1D FFFFFF86 1E FFFFFF86 1F FFFFFF86 20
   10 1D 06 FFFFFF85 77 FFFFFF85 79 FFFFFF85 7B FFFFFF85 7D FFFFFF85 7F FFFFFF86 01 FFFFFF86
   03 FFFFFF86 05 FFFFFF86 07 FFFFFF86 09 FFFFFF86 0B FFFFFF86 0D FFFFFF86 0F FFFFFF86 11 09
   03 FFFFFF85 78 02 02 07 54 75 70 6C 65 31 33 10 03 5C
   FFFFFF85 7A 04 0A FFFFFF83 1E FFFFFF85 73 FFFFFF84 FFFFFF80 FFFFFF80 FFFFFFC2 00 5F 10 03
   5C FFFFFF85 7C 04 0A FFFFFF83 31 FFFFFF85 73 FFFFFF84 FFFFFF80 FFFFFF80 FFFFFFC2 00 5F 10
   03 5C FFFFFF85 7E 04 0A FFFFFF83 44 FFFFFF85 73 FFFFFF84 FFFFFF80 FFFFFF80 FFFFFFC2 00 5F
   10 03 5C FFFFFF86 00 04 0A FFFFFF83 58 FFFFFF85 73 FFFFFF84 FFFFFF80 FFFFFF80 FFFFFFC2 00
   5F 10 03 5C FFFFFF86 02 04 0A FFFFFF83 6F FFFFFF85 73 FFFFFF84 FFFFFF80 FFFFFF80 FFFFFFC2
   00 5F 10 03 5C FFFFFF86 04 04 0A FFFFFF84 09 FFFFFF85 73 FFFFFF84 FFFFFF80 FFFFFF80
   FFFFFFC2 00 5F 10 03 5C FFFFFF86 06 04 0A FFFFFF84 26 FFFFFF85 73 FFFFFF84 FFFFFF80
   FFFFFF80 FFFFFFC2 00 5F 10 03 5C FFFFFF86 08 04 0A FFFFFF84 46 FFFFFF85 73 FFFFFF84
   FFFFFF80 FFFFFF80 FFFFFFC2 00 5F 10 03 5C FFFFFF86 0A 04 0A FFFFFF84 69 FFFFFF85 73
   FFFFFF84 FFFFFF80 FFFFFF80 FFFFFFC2 00 5F 10 03 5C FFFFFF86 0C 04 0A FFFFFF85 0F FFFFFF85
   73 FFFFFF84 FFFFFF80 FFFFFF80 FFFFFFC2 00 5F 10 03 5C FFFFFF86 0E 04 0A FFFFFF85 38
   FFFFFF85 73 FFFFFF84 FFFFFF80 FFFFFF80 FFFFFFC2 00 5F 10 03 5C FFFFFF86 10 04 0A FFFFFF85
   64 FFFFFF85 73 FFFFFF84 FFFFFF80 FFFFFF80 FFFFFFC2 00 5F 10 03 5C FFFFFF86 12 04 0A
   FFFFFF86 13 FFFFFF85 73 FFFFFF84 FFFFFF80 FFFFFF80 FFFFFFC2 00 5F 02 03 41 31 33 08
   08 FFFFFF83 20 FFFFFF85 73 FFFFFFC0 00 FFFFFF85 79 08 08 FFFFFF83 34 FFFFFF85 73 FFFFFFC0
   00 FFFFFF85 7B 08 08 FFFFFF83 48 FFFFFF85 73 FFFFFFC0 00 FFFFFF85 7D 08 08 FFFFFF83
   5D FFFFFF85 73 FFFFFFC0 00 FFFFFF85 7F 08 08 FFFFFF83 75 FFFFFF85 73 FFFFFFC0 00 FFFFFF86
   01 08 08 FFFFFF84 10 FFFFFF85 73 FFFFFFC0 00 FFFFFF86 03 08 08 FFFFFF84 2E FFFFFF85
   73 FFFFFFC0 00 FFFFFF86 05 08 08 FFFFFF84 4F FFFFFF85 73 FFFFFFC0 00 FFFFFF86 07 08
   08 FFFFFF84 73 FFFFFF85 73 FFFFFFC0 00 FFFFFF86 09 08 08 FFFFFF85 1A FFFFFF85 73 FFFFFFC0
   00 FFFFFF86 0B 08 08 FFFFFF85 44 FFFFFF85 73 FFFFFFC0 00 FFFFFF86 0D 08 08 FFFFFF85
   71 FFFFFF85 73 FFFFFFC0 00 FFFFFF86 0F 08 08 FFFFFF86 21 FFFFFF85 73 FFFFFFC0 00 FFFFFF86
   11 01 03 78 31 33 28 06 FFFFFF85 73 FFFFFF83 22 FFFFFF83 36 08 07
   FFFFFF83 16 07 FFFFFF84 00 FFFFFF86 24 15 1E FFFFFF86 25 FFFFFF86 2A FFFFFF86 2C FFFFFF86
   2E FFFFFF86 30 FFFFFF86 32 FFFFFF86 34 FFFFFF86 36 FFFFFF86 38 FFFFFF86 3A FFFFFF86 3C FFFFFF86
   3E FFFFFF86 40 FFFFFF86 42 FFFFFF86 44 14 1E FFFFFF86 26 FFFFFF86 46 FFFFFF86 47 FFFFFF86
   48 FFFFFF86 49 FFFFFF86 4A FFFFFF86 4B FFFFFF86 4C FFFFFF86 4D FFFFFF86 4E FFFFFF86 4F FFFFFF86
   50 FFFFFF86 51 FFFFFF86 52 FFFFFF86 53 10 1F 06 FFFFFF86 27 FFFFFF86 29 FFFFFF86 2B
   FFFFFF86 2D FFFFFF86 2F FFFFFF86 31 FFFFFF86 33 FFFFFF86 35 FFFFFF86 37 FFFFFF86 39 FFFFFF86 3B
   FFFFFF86 3D FFFFFF86 3F FFFFFF86 41 FFFFFF86 43 09 03 FFFFFF86 28 02 02 07 54
   75 70 6C 65 31 34 10 03 5C FFFFFF86 2A 04 0A FFFFFF83 1E FFFFFF86
   23 FFFFFF84 FFFFFF80 FFFFFF80 FFFFFFC2 00 5F 10 03 5C FFFFFF86 2C 04 0A FFFFFF83 31
   FFFFFF86 23 FFFFFF84 FFFFFF80 FFFFFF80 FFFFFFC2 00 5F 10 03 5C FFFFFF86 2E 04 0A FFFFFF83
   44 FFFFFF86 23 FFFFFF84 FFFFFF80 FFFFFF80 FFFFFFC2 00 5F 10 03 5C FFFFFF86 30 04 0A
   FFFFFF83 58 FFFFFF86 23 FFFFFF84 FFFFFF80 FFFFFF80 FFFFFFC2 00 5F 10 03 5C FFFFFF86 32 04
   0A FFFFFF83 6F FFFFFF86 23 FFFFFF84 FFFFFF80 FFFFFF80 FFFFFFC2 00 5F 10 03 5C FFFFFF86 34
   04 0A FFFFFF84 09 FFFFFF86 23 FFFFFF84 FFFFFF80 FFFFFF80 FFFFFFC2 00 5F 10 03 5C FFFFFF86
   36 04 0A FFFFFF84 26 FFFFFF86 23 FFFFFF84 FFFFFF80 FFFFFF80 FFFFFFC2 00 5F 10 03 5C
   FFFFFF86 38 04 0A FFFFFF84 46 FFFFFF86 23 FFFFFF84 FFFFFF80 FFFFFF80 FFFFFFC2 00 5F 10 03
   5C FFFFFF86 3A 04 0A FFFFFF84 69 FFFFFF86 23 FFFFFF84 FFFFFF80 FFFFFF80 FFFFFFC2 00 5F 10
   03 5C FFFFFF86 3C 04 0A FFFFFF85 0F FFFFFF86 23 FFFFFF84 FFFFFF80 FFFFFF80 FFFFFFC2 00 5F
   10 03 5C FFFFFF86 3E 04 0A FFFFFF85 38 FFFFFF86 23 FFFFFF84 FFFFFF80 FFFFFF80 FFFFFFC2 00
   5F 10 03 5C FFFFFF86 40 04 0A FFFFFF85 64 FFFFFF86 23 FFFFFF84 FFFFFF80 FFFFFF80 FFFFFFC2
   00 5F 10 03 5C FFFFFF86 42 04 0A FFFFFF86 13 FFFFFF86 23 FFFFFF84 FFFFFF80 FFFFFF80
   FFFFFFC2 00 5F 10 03 5C FFFFFF86 44 04 0A FFFFFF86 45 FFFFFF86 23 FFFFFF84 FFFFFF80
   FFFFFF80 FFFFFFC2 00 5F 02 03 41 31 34 08 08 FFFFFF83 20 FFFFFF86 23 FFFFFFC0
   00 FFFFFF86 29 08 08 FFFFFF83 34 FFFFFF86 23 FFFFFFC0 00 FFFFFF86 2B 08 08 FFFFFF83
   48 FFFFFF86 23 FFFFFFC0 00 FFFFFF86 2D 08 08 FFFFFF83 5D FFFFFF86 23 FFFFFFC0 00 FFFFFF86
   2F 08 08 FFFFFF83 75 FFFFFF86 23 FFFFFFC0 00 FFFFFF86 31 08 08 FFFFFF84 10 FFFFFF86
   23 FFFFFFC0 00 FFFFFF86 33 08 08 FFFFFF84 2E FFFFFF86 23 FFFFFFC0 00 FFFFFF86 35 08
   08 FFFFFF84 4F FFFFFF86 23 FFFFFFC0 00 FFFFFF86 37 08 08 FFFFFF84 73 FFFFFF86 23 FFFFFFC0
   00 FFFFFF86 39 08 08 FFFFFF85 1A FFFFFF86 23 FFFFFFC0 00 FFFFFF86 3B 08 08 FFFFFF85
   44 FFFFFF86 23 FFFFFFC0 00 FFFFFF86 3D 08 08 FFFFFF85 71 FFFFFF86 23 FFFFFFC0 00 FFFFFF86
   3F 08 08 FFFFFF86 21 FFFFFF86 23 FFFFFFC0 00 FFFFFF86 41 08 08 FFFFFF86 54 FFFFFF86
   23 FFFFFFC0 00 FFFFFF86 43 01 03 78 31 34 28 06 FFFFFF86 23 FFFFFF83 22
   FFFFFF83 36 08 07 FFFFFF83 16 07 FFFFFF84 00 FFFFFF86 57 15 20 FFFFFF86 58 FFFFFF86
   5D FFFFFF86 5F FFFFFF86 61 FFFFFF86 63 FFFFFF86 65 FFFFFF86 67 FFFFFF86 69 FFFFFF86 6B FFFFFF86
   6D FFFFFF86 6F FFFFFF86 71 FFFFFF86 73 FFFFFF86 75 FFFFFF86 77 FFFFFF86 79 14 20 FFFFFF86
   59 FFFFFF86 7B FFFFFF86 7C FFFFFF86 7D FFFFFF86 7E FFFFFF86 7F FFFFFF87 00 FFFFFF87 01 FFFFFF87
   02 FFFFFF87 03 FFFFFF87 04 FFFFFF87 05 FFFFFF87 06 FFFFFF87 07 FFFFFF87 08 FFFFFF87 09 10
   21 06 FFFFFF86 5A FFFFFF86 5C FFFFFF86 5E FFFFFF86 60 FFFFFF86 62 FFFFFF86 64 FFFFFF86 66
   FFFFFF86 68 FFFFFF86 6A FFFFFF86 6C FFFFFF86 6E FFFFFF86 70 FFFFFF86 72 FFFFFF86 74 FFFFFF86 76
   FFFFFF86 78 09 03 FFFFFF86 5B 02 02 07 54 75 70 6C 65 31 35
   10 03 5C FFFFFF86 5D 04 0A FFFFFF83 1E FFFFFF86 56 FFFFFF84 FFFFFF80 FFFFFF80 FFFFFFC2 00
   5F 10 03 5C FFFFFF86 5F 04 0A FFFFFF83 31 FFFFFF86 56 FFFFFF84 FFFFFF80 FFFFFF80 FFFFFFC2
   00 5F 10 03 5C FFFFFF86 61 04 0A FFFFFF83 44 FFFFFF86 56 FFFFFF84 FFFFFF80 FFFFFF80
   FFFFFFC2 00 5F 10 03 5C FFFFFF86 63 04 0A FFFFFF83 58 FFFFFF86 56 FFFFFF84 FFFFFF80
   FFFFFF80 FFFFFFC2 00 5F 10 03 5C FFFFFF86 65 04 0A FFFFFF83 6F FFFFFF86 56 FFFFFF84
   FFFFFF80 FFFFFF80 FFFFFFC2 00 5F 10 03 5C FFFFFF86 67 04 0A FFFFFF84 09 FFFFFF86 56
   FFFFFF84 FFFFFF80 FFFFFF80 FFFFFFC2 00 5F 10 03 5C FFFFFF86 69 04 0A FFFFFF84 26 FFFFFF86
   56 FFFFFF84 FFFFFF80 FFFFFF80 FFFFFFC2 00 5F 10 03 5C FFFFFF86 6B 04 0A FFFFFF84 46
   FFFFFF86 56 FFFFFF84 FFFFFF80 FFFFFF80 FFFFFFC2 00 5F 10 03 5C FFFFFF86 6D 04 0A FFFFFF84
   69 FFFFFF86 56 FFFFFF84 FFFFFF80 FFFFFF80 FFFFFFC2 00 5F 10 03 5C FFFFFF86 6F 04 0A
   FFFFFF85 0F FFFFFF86 56 FFFFFF84 FFFFFF80 FFFFFF80 FFFFFFC2 00 5F 10 03 5C FFFFFF86 71 04
   0A FFFFFF85 38 FFFFFF86 56 FFFFFF84 FFFFFF80 FFFFFF80 FFFFFFC2 00 5F 10 03 5C FFFFFF86 73
   04 0A FFFFFF85 64 FFFFFF86 56 FFFFFF84 FFFFFF80 FFFFFF80 FFFFFFC2 00 5F 10 03 5C FFFFFF86
   75 04 0A FFFFFF86 13 FFFFFF86 56 FFFFFF84 FFFFFF80 FFFFFF80 FFFFFFC2 00 5F 10 03 5C
   FFFFFF86 77 04 0A FFFFFF86 45 FFFFFF86 56 FFFFFF84 FFFFFF80 FFFFFF80 FFFFFFC2 00 5F 10 03
   5C FFFFFF86 79 04 0A FFFFFF86 7A FFFFFF86 56 FFFFFF84 FFFFFF80 FFFFFF80 FFFFFFC2 00 5F 02
   03 41 31 35 08 08 FFFFFF83 20 FFFFFF86 56 FFFFFFC0 00 FFFFFF86 5C 08 08
   FFFFFF83 34 FFFFFF86 56 FFFFFFC0 00 FFFFFF86 5E 08 08 FFFFFF83 48 FFFFFF86 56 FFFFFFC0 00
   FFFFFF86 60 08 08 FFFFFF83 5D FFFFFF86 56 FFFFFFC0 00 FFFFFF86 62 08 08 FFFFFF83 75
   FFFFFF86 56 FFFFFFC0 00 FFFFFF86 64 08 08 FFFFFF84 10 FFFFFF86 56 FFFFFFC0 00 FFFFFF86 66
   08 08 FFFFFF84 2E FFFFFF86 56 FFFFFFC0 00 FFFFFF86 68 08 08 FFFFFF84 4F FFFFFF86 56
   FFFFFFC0 00 FFFFFF86 6A 08 08 FFFFFF84 73 FFFFFF86 56 FFFFFFC0 00 FFFFFF86 6C 08 08
   FFFFFF85 1A FFFFFF86 56 FFFFFFC0 00 FFFFFF86 6E 08 08 FFFFFF85 44 FFFFFF86 56 FFFFFFC0 00
   FFFFFF86 70 08 08 FFFFFF85 71 FFFFFF86 56 FFFFFFC0 00 FFFFFF86 72 08 08 FFFFFF86 21
   FFFFFF86 56 FFFFFFC0 00 FFFFFF86 74 08 08 FFFFFF86 54 FFFFFF86 56 FFFFFFC0 00 FFFFFF86 76
   08 08 FFFFFF87 0A FFFFFF86 56 FFFFFFC0 00 FFFFFF86 78 01 03 78 31 35 28
   06 FFFFFF86 56 FFFFFF83 22 FFFFFF83 36 08 07 FFFFFF83 16 07 FFFFFF84 00 FFFFFF87 0D
   15 22 FFFFFF87 0E FFFFFF87 13 FFFFFF87 15 FFFFFF87 17 FFFFFF87 19 FFFFFF87 1B FFFFFF87 1D
   FFFFFF87 1F FFFFFF87 21 FFFFFF87 23 FFFFFF87 25 FFFFFF87 27 FFFFFF87 29 FFFFFF87 2B FFFFFF87 2D
   FFFFFF87 2F FFFFFF87 31 14 22 FFFFFF87 0F FFFFFF87 33 FFFFFF87 34 FFFFFF87 35 FFFFFF87 36
   FFFFFF87 37 FFFFFF87 38 FFFFFF87 39 FFFFFF87 3A FFFFFF87 3B FFFFFF87 3C FFFFFF87 3D FFFFFF87 3E
   FFFFFF87 3F FFFFFF87 40 FFFFFF87 41 FFFFFF87 42 10 23 06 FFFFFF87 10 FFFFFF87 12 FFFFFF87
   14 FFFFFF87 16 FFFFFF87 18 FFFFFF87 1A FFFFFF87 1C FFFFFF87 1E FFFFFF87 20 FFFFFF87 22 FFFFFF87
   24 FFFFFF87 26 FFFFFF87 28 FFFFFF87 2A FFFFFF87 2C FFFFFF87 2E FFFFFF87 30 09 03 FFFFFF87
   11 02 02 07 54 75 70 6C 65 31 36 10 03 5C FFFFFF87 13
   04 0A FFFFFF83 1E FFFFFF87 0C FFFFFF84 FFFFFF80 FFFFFF80 FFFFFFC2 00 5F 10 03 5C FFFFFF87
   15 04 0A FFFFFF83 31 FFFFFF87 0C FFFFFF84 FFFFFF80 FFFFFF80 FFFFFFC2 00 5F 10 03 5C
   FFFFFF87 17 04 0A FFFFFF83 44 FFFFFF87 0C FFFFFF84 FFFFFF80 FFFFFF80 FFFFFFC2 00 5F 10 03
   5C FFFFFF87 19 04 0A FFFFFF83 58 FFFFFF87 0C FFFFFF84 FFFFFF80 FFFFFF80 FFFFFFC2 00 5F 10
   03 5C FFFFFF87 1B 04 0A FFFFFF83 6F FFFFFF87 0C FFFFFF84 FFFFFF80 FFFFFF80 FFFFFFC2 00 5F
   10 03 5C FFFFFF87 1D 04 0A FFFFFF84 09 FFFFFF87 0C FFFFFF84 FFFFFF80 FFFFFF80 FFFFFFC2 00
   5F 10 03 5C FFFFFF87 1F 04 0A FFFFFF84 26 FFFFFF87 0C FFFFFF84 FFFFFF80 FFFFFF80 FFFFFFC2
   00 5F 10 03 5C FFFFFF87 21 04 0A FFFFFF84 46 FFFFFF87 0C FFFFFF84 FFFFFF80 FFFFFF80
   FFFFFFC2 00 5F 10 03 5C FFFFFF87 23 04 0A FFFFFF84 69 FFFFFF87 0C FFFFFF84 FFFFFF80
   FFFFFF80 FFFFFFC2 00 5F 10 03 5C FFFFFF87 25 04 0A FFFFFF85 0F FFFFFF87 0C FFFFFF84
   FFFFFF80 FFFFFF80 FFFFFFC2 00 5F 10 03 5C FFFFFF87 27 04 0A FFFFFF85 38 FFFFFF87 0C
   FFFFFF84 FFFFFF80 FFFFFF80 FFFFFFC2 00 5F 10 03 5C FFFFFF87 29 04 0A FFFFFF85 64 FFFFFF87
   0C FFFFFF84 FFFFFF80 FFFFFF80 FFFFFFC2 00 5F 10 03 5C FFFFFF87 2B 04 0A FFFFFF86 13
   FFFFFF87 0C FFFFFF84 FFFFFF80 FFFFFF80 FFFFFFC2 00 5F 10 03 5C FFFFFF87 2D 04 0A FFFFFF86
   45 FFFFFF87 0C FFFFFF84 FFFFFF80 FFFFFF80 FFFFFFC2 00 5F 10 03 5C FFFFFF87 2F 04 0A
   FFFFFF86 7A FFFFFF87 0C FFFFFF84 FFFFFF80 FFFFFF80 FFFFFFC2 00 5F 10 03 5C FFFFFF87 31 04
   0A FFFFFF87 32 FFFFFF87 0C FFFFFF84 FFFFFF80 FFFFFF80 FFFFFFC2 00 5F 02 03 41 31 36
   08 08 FFFFFF83 20 FFFFFF87 0C FFFFFFC0 00 FFFFFF87 12 08 08 FFFFFF83 34 FFFFFF87 0C
   FFFFFFC0 00 FFFFFF87 14 08 08 FFFFFF83 48 FFFFFF87 0C FFFFFFC0 00 FFFFFF87 16 08 08
   FFFFFF83 5D FFFFFF87 0C FFFFFFC0 00 FFFFFF87 18 08 08 FFFFFF83 75 FFFFFF87 0C FFFFFFC0 00
   FFFFFF87 1A 08 08 FFFFFF84 10 FFFFFF87 0C FFFFFFC0 00 FFFFFF87 1C 08 08 FFFFFF84 2E
   FFFFFF87 0C FFFFFFC0 00 FFFFFF87 1E 08 08 FFFFFF84 4F FFFFFF87 0C FFFFFFC0 00 FFFFFF87 20
   08 08 FFFFFF84 73 FFFFFF87 0C FFFFFFC0 00 FFFFFF87 22 08 08 FFFFFF85 1A FFFFFF87 0C
   FFFFFFC0 00 FFFFFF87 24 08 08 FFFFFF85 44 FFFFFF87 0C FFFFFFC0 00 FFFFFF87 26 08 08
   FFFFFF85 71 FFFFFF87 0C FFFFFFC0 00 FFFFFF87 28 08 08 FFFFFF86 21 FFFFFF87 0C FFFFFFC0 00
   FFFFFF87 2A 08 08 FFFFFF86 54 FFFFFF87 0C FFFFFFC0 00 FFFFFF87 2C 08 08 FFFFFF87 0A
   FFFFFF87 0C FFFFFFC0 00 FFFFFF87 2E 08 08 FFFFFF87 43 FFFFFF87 0C FFFFFFC0 00 FFFFFF87 30
   01 03 78 31 36 28 06 FFFFFF87 0C FFFFFF83 22 FFFFFF83 36 08 07 FFFFFF83
   16 07 FFFFFF84 00 FFFFFF87 46 15 24 FFFFFF87 47 FFFFFF87 4C FFFFFF87 4E FFFFFF87 50
   FFFFFF87 52 FFFFFF87 54 FFFFFF87 56 FFFFFF87 58 FFFFFF87 5A FFFFFF87 5C FFFFFF87 5E FFFFFF87 60
   FFFFFF87 62 FFFFFF87 64 FFFFFF87 66 FFFFFF87 68 FFFFFF87 6A FFFFFF87 6C 14 24 FFFFFF87 48
   FFFFFF87 6E FFFFFF87 6F FFFFFF87 70 FFFFFF87 71 FFFFFF87 72 FFFFFF87 73 FFFFFF87 74 FFFFFF87 75
   FFFFFF87 76 FFFFFF87 77 FFFFFF87 78 FFFFFF87 79 FFFFFF87 7A FFFFFF87 7B FFFFFF87 7C FFFFFF87 7D
   FFFFFF87 7E 10 25 06 FFFFFF87 49 FFFFFF87 4B FFFFFF87 4D FFFFFF87 4F FFFFFF87 51 FFFFFF87
   53 FFFFFF87 55 FFFFFF87 57 FFFFFF87 59 FFFFFF87 5B FFFFFF87 5D FFFFFF87 5F FFFFFF87 61 FFFFFF87
   63 FFFFFF87 65 FFFFFF87 67 FFFFFF87 69 FFFFFF87 6B 09 03 FFFFFF87 4A 02 02 07
   54 75 70 6C 65 31 37 10 03 5C FFFFFF87 4C 04 0A FFFFFF83 1E
   FFFFFF87 45 FFFFFF84 FFFFFF80 FFFFFF80 FFFFFFC2 00 5F 10 03 5C FFFFFF87 4E 04 0A FFFFFF83
   31 FFFFFF87 45 FFFFFF84 FFFFFF80 FFFFFF80 FFFFFFC2 00 5F 10 03 5C FFFFFF87 50 04 0A
   FFFFFF83 44 FFFFFF87 45 FFFFFF84 FFFFFF80 FFFFFF80 FFFFFFC2 00 5F 10 03 5C FFFFFF87 52 04
   0A FFFFFF83 58 FFFFFF87 45 FFFFFF84 FFFFFF80 FFFFFF80 FFFFFFC2 00 5F 10 03 5C FFFFFF87 54
   04 0A FFFFFF83 6F FFFFFF87 45 FFFFFF84 FFFFFF80 FFFFFF80 FFFFFFC2 00 5F 10 03 5C FFFFFF87
   56 04 0A FFFFFF84 09 FFFFFF87 45 FFFFFF84 FFFFFF80 FFFFFF80 FFFFFFC2 00 5F 10 03 5C
   FFFFFF87 58 04 0A FFFFFF84 26 FFFFFF87 45 FFFFFF84 FFFFFF80 FFFFFF80 FFFFFFC2 00 5F 10 03
   5C FFFFFF87 5A 04 0A FFFFFF84 46 FFFFFF87 45 FFFFFF84 FFFFFF80 FFFFFF80 FFFFFFC2 00 5F 10
   03 5C FFFFFF87 5C 04 0A FFFFFF84 69 FFFFFF87 45 FFFFFF84 FFFFFF80 FFFFFF80 FFFFFFC2 00 5F
   10 03 5C FFFFFF87 5E 04 0A FFFFFF85 0F FFFFFF87 45 FFFFFF84 FFFFFF80 FFFFFF80 FFFFFFC2 00
   5F 10 03 5C FFFFFF87 60 04 0A FFFFFF85 38 FFFFFF87 45 FFFFFF84 FFFFFF80 FFFFFF80 FFFFFFC2
   00 5F 10 03 5C FFFFFF87 62 04 0A FFFFFF85 64 FFFFFF87 45 FFFFFF84 FFFFFF80 FFFFFF80
   FFFFFFC2 00 5F 10 03 5C FFFFFF87 64 04 0A FFFFFF86 13 FFFFFF87 45 FFFFFF84 FFFFFF80
   FFFFFF80 FFFFFFC2 00 5F 10 03 5C FFFFFF87 66 04 0A FFFFFF86 45 FFFFFF87 45 FFFFFF84
   FFFFFF80 FFFFFF80 FFFFFFC2 00 5F 10 03 5C FFFFFF87 68 04 0A FFFFFF86 7A FFFFFF87 45
   FFFFFF84 FFFFFF80 FFFFFF80 FFFFFFC2 00 5F 10 03 5C FFFFFF87 6A 04 0A FFFFFF87 32 FFFFFF87
   45 FFFFFF84 FFFFFF80 FFFFFF80 FFFFFFC2 00 5F 10 03 5C FFFFFF87 6C 04 0A FFFFFF87 6D
   FFFFFF87 45 FFFFFF84 FFFFFF80 FFFFFF80 FFFFFFC2 00 5F 02 03 41 31 37 08 08 FFFFFF83
   20 FFFFFF87 45 FFFFFFC0 00 FFFFFF87 4B 08 08 FFFFFF83 34 FFFFFF87 45 FFFFFFC0 00 FFFFFF87
   4D 08 08 FFFFFF83 48 FFFFFF87 45 FFFFFFC0 00 FFFFFF87 4F 08 08 FFFFFF83 5D FFFFFF87
   45 FFFFFFC0 00 FFFFFF87 51 08 08 FFFFFF83 75 FFFFFF87 45 FFFFFFC0 00 FFFFFF87 53 08
   08 FFFFFF84 10 FFFFFF87 45 FFFFFFC0 00 FFFFFF87 55 08 08 FFFFFF84 2E FFFFFF87 45 FFFFFFC0
   00 FFFFFF87 57 08 08 FFFFFF84 4F FFFFFF87 45 FFFFFFC0 00 FFFFFF87 59 08 08 FFFFFF84
   73 FFFFFF87 45 FFFFFFC0 00 FFFFFF87 5B 08 08 FFFFFF85 1A FFFFFF87 45 FFFFFFC0 00 FFFFFF87
   5D 08 08 FFFFFF85 44 FFFFFF87 45 FFFFFFC0 00 FFFFFF87 5F 08 08 FFFFFF85 71 FFFFFF87
   45 FFFFFFC0 00 FFFFFF87 61 08 08 FFFFFF86 21 FFFFFF87 45 FFFFFFC0 00 FFFFFF87 63 08
   08 FFFFFF86 54 FFFFFF87 45 FFFFFFC0 00 FFFFFF87 65 08 08 FFFFFF87 0A FFFFFF87 45 FFFFFFC0
   00 FFFFFF87 67 08 08 FFFFFF87 43 FFFFFF87 45 FFFFFFC0 00 FFFFFF87 69 08 08 FFFFFF87
   7F FFFFFF87 45 FFFFFFC0 00 FFFFFF87 6B 01 03 78 31 37 28 06 FFFFFF87 45
   FFFFFF83 22 FFFFFF83 36 08 07 FFFFFF83 16 07 FFFFFF84 00 FFFFFF88 02 15 26 FFFFFF88
   03 FFFFFF88 08 FFFFFF88 0A FFFFFF88 0C FFFFFF88 0E FFFFFF88 10 FFFFFF88 12 FFFFFF88 14 FFFFFF88
   16 FFFFFF88 18 FFFFFF88 1A FFFFFF88 1C FFFFFF88 1E FFFFFF88 20 FFFFFF88 22 FFFFFF88 24 FFFFFF88
   26 FFFFFF88 28 FFFFFF88 2A 14 26 FFFFFF88 04 FFFFFF88 2C FFFFFF88 2D FFFFFF88 2E FFFFFF88
   2F FFFFFF88 30 FFFFFF88 31 FFFFFF88 32 FFFFFF88 33 FFFFFF88 34 FFFFFF88 35 FFFFFF88 36 FFFFFF88
   37 FFFFFF88 38 FFFFFF88 39 FFFFFF88 3A FFFFFF88 3B FFFFFF88 3C FFFFFF88 3D 10 27 06
   FFFFFF88 05 FFFFFF88 07 FFFFFF88 09 FFFFFF88 0B FFFFFF88 0D FFFFFF88 0F FFFFFF88 11 FFFFFF88 13
   FFFFFF88 15 FFFFFF88 17 FFFFFF88 19 FFFFFF88 1B FFFFFF88 1D FFFFFF88 1F FFFFFF88 21 FFFFFF88 23
   FFFFFF88 25 FFFFFF88 27 FFFFFF88 29 09 03 FFFFFF88 06 02 02 07 54 75 70
   6C 65 31 38 10 03 5C FFFFFF88 08 04 0A FFFFFF83 1E FFFFFF88 01 FFFFFF84
   FFFFFF80 FFFFFF80 FFFFFFC2 00 5F 10 03 5C FFFFFF88 0A 04 0A FFFFFF83 31 FFFFFF88 01
   FFFFFF84 FFFFFF80 FFFFFF80 FFFFFFC2 00 5F 10 03 5C FFFFFF88 0C 04 0A FFFFFF83 44 FFFFFF88
   01 FFFFFF84 FFFFFF80 FFFFFF80 FFFFFFC2 00 5F 10 03 5C FFFFFF88 0E 04 0A FFFFFF83 58
   FFFFFF88 01 FFFFFF84 FFFFFF80 FFFFFF80 FFFFFFC2 00 5F 10 03 5C FFFFFF88 10 04 0A FFFFFF83
   6F FFFFFF88 01 FFFFFF84 FFFFFF80 FFFFFF80 FFFFFFC2 00 5F 10 03 5C FFFFFF88 12 04 0A
   FFFFFF84 09 FFFFFF88 01 FFFFFF84 FFFFFF80 FFFFFF80 FFFFFFC2 00 5F 10 03 5C FFFFFF88 14 04
   0A FFFFFF84 26 FFFFFF88 01 FFFFFF84 FFFFFF80 FFFFFF80 FFFFFFC2 00 5F 10 03 5C FFFFFF88 16
   04 0A FFFFFF84 46 FFFFFF88 01 FFFFFF84 FFFFFF80 FFFFFF80 FFFFFFC2 00 5F 10 03 5C FFFFFF88
   18 04 0A FFFFFF84 69 FFFFFF88 01 FFFFFF84 FFFFFF80 FFFFFF80 FFFFFFC2 00 5F 10 03 5C
   FFFFFF88 1A 04 0A FFFFFF85 0F FFFFFF88 01 FFFFFF84 FFFFFF80 FFFFFF80 FFFFFFC2 00 5F 10 03
   5C FFFFFF88 1C 04 0A FFFFFF85 38 FFFFFF88 01 FFFFFF84 FFFFFF80 FFFFFF80 FFFFFFC2 00 5F 10
   03 5C FFFFFF88 1E 04 0A FFFFFF85 64 FFFFFF88 01 FFFFFF84 FFFFFF80 FFFFFF80 FFFFFFC2 00 5F
   10 03 5C FFFFFF88 20 04 0A FFFFFF86 13 FFFFFF88 01 FFFFFF84 FFFFFF80 FFFFFF80 FFFFFFC2 00
   5F 10 03 5C FFFFFF88 22 04 0A FFFFFF86 45 FFFFFF88 01 FFFFFF84 FFFFFF80 FFFFFF80 FFFFFFC2
   00 5F 10 03 5C FFFFFF88 24 04 0A FFFFFF86 7A FFFFFF88 01 FFFFFF84 FFFFFF80 FFFFFF80
   FFFFFFC2 00 5F 10 03 5C FFFFFF88 26 04 0A FFFFFF87 32 FFFFFF88 01 FFFFFF84 FFFFFF80
   FFFFFF80 FFFFFFC2 00 5F 10 03 5C FFFFFF88 28 04 0A FFFFFF87 6D FFFFFF88 01 FFFFFF84
   FFFFFF80 FFFFFF80 FFFFFFC2 00 5F 10 03 5C FFFFFF88 2A 04 0A FFFFFF88 2B FFFFFF88 01
   FFFFFF84 FFFFFF80 FFFFFF80 FFFFFFC2 00 5F 02 03 41 31 38 08 08 FFFFFF83 20 FFFFFF88
   01 FFFFFFC0 00 FFFFFF88 07 08 08 FFFFFF83 34 FFFFFF88 01 FFFFFFC0 00 FFFFFF88 09 08
   08 FFFFFF83 48 FFFFFF88 01 FFFFFFC0 00 FFFFFF88 0B 08 08 FFFFFF83 5D FFFFFF88 01 FFFFFFC0
   00 FFFFFF88 0D 08 08 FFFFFF83 75 FFFFFF88 01 FFFFFFC0 00 FFFFFF88 0F 08 08 FFFFFF84
   10 FFFFFF88 01 FFFFFFC0 00 FFFFFF88 11 08 08 FFFFFF84 2E FFFFFF88 01 FFFFFFC0 00 FFFFFF88
   13 08 08 FFFFFF84 4F FFFFFF88 01 FFFFFFC0 00 FFFFFF88 15 08 08 FFFFFF84 73 FFFFFF88
   01 FFFFFFC0 00 FFFFFF88 17 08 08 FFFFFF85 1A FFFFFF88 01 FFFFFFC0 00 FFFFFF88 19 08
   08 FFFFFF85 44 FFFFFF88 01 FFFFFFC0 00 FFFFFF88 1B 08 08 FFFFFF85 71 FFFFFF88 01 FFFFFFC0
   00 FFFFFF88 1D 08 08 FFFFFF86 21 FFFFFF88 01 FFFFFFC0 00 FFFFFF88 1F 08 08 FFFFFF86
   54 FFFFFF88 01 FFFFFFC0 00 FFFFFF88 21 08 08 FFFFFF87 0A FFFFFF88 01 FFFFFFC0 00 FFFFFF88
   23 08 08 FFFFFF87 43 FFFFFF88 01 FFFFFFC0 00 FFFFFF88 25 08 08 FFFFFF87 7F FFFFFF88
   01 FFFFFFC0 00 FFFFFF88 27 08 08 FFFFFF88 3E FFFFFF88 01 FFFFFFC0 00 FFFFFF88 29 01
   03 78 31 38 28 06 FFFFFF88 01 FFFFFF83 22 FFFFFF83 36 08 07 FFFFFF83 16
   07 FFFFFF84 00 FFFFFF88 41 15 28 FFFFFF88 42 FFFFFF88 47 FFFFFF88 49 FFFFFF88 4B FFFFFF88
   4D FFFFFF88 4F FFFFFF88 51 FFFFFF88 53 FFFFFF88 55 FFFFFF88 57 FFFFFF88 59 FFFFFF88 5B FFFFFF88
   5D FFFFFF88 5F FFFFFF88 61 FFFFFF88 63 FFFFFF88 65 FFFFFF88 67 FFFFFF88 69 FFFFFF88 6B 14
   28 FFFFFF88 43 FFFFFF88 6D FFFFFF88 6E FFFFFF88 6F FFFFFF88 70 FFFFFF88 71 FFFFFF88 72 FFFFFF88
   73 FFFFFF88 74 FFFFFF88 75 FFFFFF88 76 FFFFFF88 77 FFFFFF88 78 FFFFFF88 79 FFFFFF88 7A FFFFFF88
   7B FFFFFF88 7C FFFFFF88 7D FFFFFF88 7E FFFFFF88 7F 10 29 06 FFFFFF88 44 FFFFFF88 46
   FFFFFF88 48 FFFFFF88 4A FFFFFF88 4C FFFFFF88 4E FFFFFF88 50 FFFFFF88 52 FFFFFF88 54 FFFFFF88 56
   FFFFFF88 58 FFFFFF88 5A FFFFFF88 5C FFFFFF88 5E FFFFFF88 60 FFFFFF88 62 FFFFFF88 64 FFFFFF88 66
   FFFFFF88 68 FFFFFF88 6A 09 03 FFFFFF88 45 02 02 07 54 75 70 6C 65
   31 39 10 03 5C FFFFFF88 47 04 0A FFFFFF83 1E FFFFFF88 40 FFFFFF84 FFFFFF80 FFFFFF80
   FFFFFFC2 00 5F 10 03 5C FFFFFF88 49 04 0A FFFFFF83 31 FFFFFF88 40 FFFFFF84 FFFFFF80
   FFFFFF80 FFFFFFC2 00 5F 10 03 5C FFFFFF88 4B 04 0A FFFFFF83 44 FFFFFF88 40 FFFFFF84
   FFFFFF80 FFFFFF80 FFFFFFC2 00 5F 10 03 5C FFFFFF88 4D 04 0A FFFFFF83 58 FFFFFF88 40
   FFFFFF84 FFFFFF80 FFFFFF80 FFFFFFC2 00 5F 10 03 5C FFFFFF88 4F 04 0A FFFFFF83 6F FFFFFF88
   40 FFFFFF84 FFFFFF80 FFFFFF80 FFFFFFC2 00 5F 10 03 5C FFFFFF88 51 04 0A FFFFFF84 09
   FFFFFF88 40 FFFFFF84 FFFFFF80 FFFFFF80 FFFFFFC2 00 5F 10 03 5C FFFFFF88 53 04 0A FFFFFF84
   26 FFFFFF88 40 FFFFFF84 FFFFFF80 FFFFFF80 FFFFFFC2 00 5F 10 03 5C FFFFFF88 55 04 0A
   FFFFFF84 46 FFFFFF88 40 FFFFFF84 FFFFFF80 FFFFFF80 FFFFFFC2 00 5F 10 03 5C FFFFFF88 57 04
   0A FFFFFF84 69 FFFFFF88 40 FFFFFF84 FFFFFF80 FFFFFF80 FFFFFFC2 00 5F 10 03 5C FFFFFF88 59
   04 0A FFFFFF85 0F FFFFFF88 40 FFFFFF84 FFFFFF80 FFFFFF80 FFFFFFC2 00 5F 10 03 5C FFFFFF88
   5B 04 0A FFFFFF85 38 FFFFFF88 40 FFFFFF84 FFFFFF80 FFFFFF80 FFFFFFC2 00 5F 10 03 5C
   FFFFFF88 5D 04 0A FFFFFF85 64 FFFFFF88 40 FFFFFF84 FFFFFF80 FFFFFF80 FFFFFFC2 00 5F 10 03
   5C FFFFFF88 5F 04 0A FFFFFF86 13 FFFFFF88 40 FFFFFF84 FFFFFF80 FFFFFF80 FFFFFFC2 00 5F 10
   03 5C FFFFFF88 61 04 0A FFFFFF86 45 FFFFFF88 40 FFFFFF84 FFFFFF80 FFFFFF80 FFFFFFC2 00 5F
   10 03 5C FFFFFF88 63 04 0A FFFFFF86 7A FFFFFF88 40 FFFFFF84 FFFFFF80 FFFFFF80 FFFFFFC2 00
   5F 10 03 5C FFFFFF88 65 04 0A FFFFFF87 32 FFFFFF88 40 FFFFFF84 FFFFFF80 FFFFFF80 FFFFFFC2
   00 5F 10 03 5C FFFFFF88 67 04 0A FFFFFF87 6D FFFFFF88 40 FFFFFF84 FFFFFF80 FFFFFF80
   FFFFFFC2 00 5F 10 03 5C FFFFFF88 69 04 0A FFFFFF88 2B FFFFFF88 40 FFFFFF84 FFFFFF80
   FFFFFF80 FFFFFFC2 00 5F 10 03 5C FFFFFF88 6B 04 0A FFFFFF88 6C FFFFFF88 40 FFFFFF84
   FFFFFF80 FFFFFF80 FFFFFFC2 00 5F 02 03 41 31 39 08 08 FFFFFF83 20 FFFFFF88 40
   FFFFFFC0 00 FFFFFF88 46 08 08 FFFFFF83 34 FFFFFF88 40 FFFFFFC0 00 FFFFFF88 48 08 08
   FFFFFF83 48 FFFFFF88 40 FFFFFFC0 00 FFFFFF88 4A 08 08 FFFFFF83 5D FFFFFF88 40 FFFFFFC0 00
   FFFFFF88 4C 08 08 FFFFFF83 75 FFFFFF88 40 FFFFFFC0 00 FFFFFF88 4E 08 08 FFFFFF84 10
   FFFFFF88 40 FFFFFFC0 00 FFFFFF88 50 08 08 FFFFFF84 2E FFFFFF88 40 FFFFFFC0 00 FFFFFF88 52
   08 08 FFFFFF84 4F FFFFFF88 40 FFFFFFC0 00 FFFFFF88 54 08 08 FFFFFF84 73 FFFFFF88 40
   FFFFFFC0 00 FFFFFF88 56 08 08 FFFFFF85 1A FFFFFF88 40 FFFFFFC0 00 FFFFFF88 58 08 08
   FFFFFF85 44 FFFFFF88 40 FFFFFFC0 00 FFFFFF88 5A 08 08 FFFFFF85 71 FFFFFF88 40 FFFFFFC0 00
   FFFFFF88 5C 08 08 FFFFFF86 21 FFFFFF88 40 FFFFFFC0 00 FFFFFF88 5E 08 08 FFFFFF86 54
   FFFFFF88 40 FFFFFFC0 00 FFFFFF88 60 08 08 FFFFFF87 0A FFFFFF88 40 FFFFFFC0 00 FFFFFF88 62
   08 08 FFFFFF87 43 FFFFFF88 40 FFFFFFC0 00 FFFFFF88 64 08 08 FFFFFF87 7F FFFFFF88 40
   FFFFFFC0 00 FFFFFF88 66 08 08 FFFFFF88 3E FFFFFF88 40 FFFFFFC0 00 FFFFFF88 68 08 08
   FFFFFF89 00 FFFFFF88 40 FFFFFFC0 00 FFFFFF88 6A 01 03 78 31 39 28 06 FFFFFF88
   40 FFFFFF83 22 FFFFFF83 36 08 07 FFFFFF83 16 07 FFFFFF84 00 FFFFFF89 03 15 2A
   FFFFFF89 04 FFFFFF89 09 FFFFFF89 0B FFFFFF89 0D FFFFFF89 0F FFFFFF89 11 FFFFFF89 13 FFFFFF89 15
   FFFFFF89 17 FFFFFF89 19 FFFFFF89 1B FFFFFF89 1D FFFFFF89 1F FFFFFF89 21 FFFFFF89 23 FFFFFF89 25
   FFFFFF89 27 FFFFFF89 29 FFFFFF89 2B FFFFFF89 2D FFFFFF89 2F 14 2A FFFFFF89 05 FFFFFF89 31
   FFFFFF89 32 FFFFFF89 33 FFFFFF89 34 FFFFFF89 35 FFFFFF89 36 FFFFFF89 37 FFFFFF89 38 FFFFFF89 39
   FFFFFF89 3A FFFFFF89 3B FFFFFF89 3C FFFFFF89 3D FFFFFF89 3E FFFFFF89 3F FFFFFF89 40 FFFFFF89 41
   FFFFFF89 42 FFFFFF89 43 FFFFFF89 44 10 2B 06 FFFFFF89 06 FFFFFF89 08 FFFFFF89 0A FFFFFF89
   0C FFFFFF89 0E FFFFFF89 10 FFFFFF89 12 FFFFFF89 14 FFFFFF89 16 FFFFFF89 18 FFFFFF89 1A FFFFFF89
   1C FFFFFF89 1E FFFFFF89 20 FFFFFF89 22 FFFFFF89 24 FFFFFF89 26 FFFFFF89 28 FFFFFF89 2A FFFFFF89
   2C FFFFFF89 2E 09 03 FFFFFF89 07 02 02 07 54 75 70 6C 65 32
   30 10 03 5C FFFFFF89 09 04 0A FFFFFF83 1E FFFFFF89 02 FFFFFF84 FFFFFF80 FFFFFF80 FFFFFFC2
   00 5F 10 03 5C FFFFFF89 0B 04 0A FFFFFF83 31 FFFFFF89 02 FFFFFF84 FFFFFF80 FFFFFF80
   FFFFFFC2 00 5F 10 03 5C FFFFFF89 0D 04 0A FFFFFF83 44 FFFFFF89 02 FFFFFF84 FFFFFF80
   FFFFFF80 FFFFFFC2 00 5F 10 03 5C FFFFFF89 0F 04 0A FFFFFF83 58 FFFFFF89 02 FFFFFF84
   FFFFFF80 FFFFFF80 FFFFFFC2 00 5F 10 03 5C FFFFFF89 11 04 0A FFFFFF83 6F FFFFFF89 02
   FFFFFF84 FFFFFF80 FFFFFF80 FFFFFFC2 00 5F 10 03 5C FFFFFF89 13 04 0A FFFFFF84 09 FFFFFF89
   02 FFFFFF84 FFFFFF80 FFFFFF80 FFFFFFC2 00 5F 10 03 5C FFFFFF89 15 04 0A FFFFFF84 26
   FFFFFF89 02 FFFFFF84 FFFFFF80 FFFFFF80 FFFFFFC2 00 5F 10 03 5C FFFFFF89 17 04 0A FFFFFF84
   46 FFFFFF89 02 FFFFFF84 FFFFFF80 FFFFFF80 FFFFFFC2 00 5F 10 03 5C FFFFFF89 19 04 0A
   FFFFFF84 69 FFFFFF89 02 FFFFFF84 FFFFFF80 FFFFFF80 FFFFFFC2 00 5F 10 03 5C FFFFFF89 1B 04
   0A FFFFFF85 0F FFFFFF89 02 FFFFFF84 FFFFFF80 FFFFFF80 FFFFFFC2 00 5F 10 03 5C FFFFFF89 1D
   04 0A FFFFFF85 38 FFFFFF89 02 FFFFFF84 FFFFFF80 FFFFFF80 FFFFFFC2 00 5F 10 03 5C FFFFFF89
   1F 04 0A FFFFFF85 64 FFFFFF89 02 FFFFFF84 FFFFFF80 FFFFFF80 FFFFFFC2 00 5F 10 03 5C
   FFFFFF89 21 04 0A FFFFFF86 13 FFFFFF89 02 FFFFFF84 FFFFFF80 FFFFFF80 FFFFFFC2 00 5F 10 03
   5C FFFFFF89 23 04 0A FFFFFF86 45 FFFFFF89 02 FFFFFF84 FFFFFF80 FFFFFF80 FFFFFFC2 00 5F 10
   03 5C FFFFFF89 25 04 0A FFFFFF86 7A FFFFFF89 02 FFFFFF84 FFFFFF80 FFFFFF80 FFFFFFC2 00 5F
   10 03 5C FFFFFF89 27 04 0A FFFFFF87 32 FFFFFF89 02 FFFFFF84 FFFFFF80 FFFFFF80 FFFFFFC2 00
   5F 10 03 5C FFFFFF89 29 04 0A FFFFFF87 6D FFFFFF89 02 FFFFFF84 FFFFFF80 FFFFFF80 FFFFFFC2
   00 5F 10 03 5C FFFFFF89 2B 04 0A FFFFFF88 2B FFFFFF89 02 FFFFFF84 FFFFFF80 FFFFFF80
   FFFFFFC2 00 5F 10 03 5C FFFFFF89 2D 04 0A FFFFFF88 6C FFFFFF89 02 FFFFFF84 FFFFFF80
   FFFFFF80 FFFFFFC2 00 5F 10 03 5C FFFFFF89 2F 04 0A FFFFFF89 30 FFFFFF89 02 FFFFFF84
   FFFFFF80 FFFFFF80 FFFFFFC2 00 5F 02 03 41 32 30 08 08 FFFFFF83 20 FFFFFF89 02
   FFFFFFC0 00 FFFFFF89 08 08 08 FFFFFF83 34 FFFFFF89 02 FFFFFFC0 00 FFFFFF89 0A 08 08
   FFFFFF83 48 FFFFFF89 02 FFFFFFC0 00 FFFFFF89 0C 08 08 FFFFFF83 5D FFFFFF89 02 FFFFFFC0 00
   FFFFFF89 0E 08 08 FFFFFF83 75 FFFFFF89 02 FFFFFFC0 00 FFFFFF89 10 08 08 FFFFFF84 10
   FFFFFF89 02 FFFFFFC0 00 FFFFFF89 12 08 08 FFFFFF84 2E FFFFFF89 02 FFFFFFC0 00 FFFFFF89 14
   08 08 FFFFFF84 4F FFFFFF89 02 FFFFFFC0 00 FFFFFF89 16 08 08 FFFFFF84 73 FFFFFF89 02
   FFFFFFC0 00 FFFFFF89 18 08 08 FFFFFF85 1A FFFFFF89 02 FFFFFFC0 00 FFFFFF89 1A 08 08
   FFFFFF85 44 FFFFFF89 02 FFFFFFC0 00 FFFFFF89 1C 08 08 FFFFFF85 71 FFFFFF89 02 FFFFFFC0 00
   FFFFFF89 1E 08 08 FFFFFF86 21 FFFFFF89 02 FFFFFFC0 00 FFFFFF89 20 08 08 FFFFFF86 54
   FFFFFF89 02 FFFFFFC0 00 FFFFFF89 22 08 08 FFFFFF87 0A FFFFFF89 02 FFFFFFC0 00 FFFFFF89 24
   08 08 FFFFFF87 43 FFFFFF89 02 FFFFFFC0 00 FFFFFF89 26 08 08 FFFFFF87 7F FFFFFF89 02
   FFFFFFC0 00 FFFFFF89 28 08 08 FFFFFF88 3E FFFFFF89 02 FFFFFFC0 00 FFFFFF89 2A 08 08
   FFFFFF89 00 FFFFFF89 02 FFFFFFC0 00 FFFFFF89 2C 08 08 FFFFFF89 45 FFFFFF89 02 FFFFFFC0 00
   FFFFFF89 2E 01 03 78 32 30 28 06 FFFFFF89 02 FFFFFF83 22 FFFFFF83 36 08
   07 FFFFFF83 16 07 FFFFFF84 00 FFFFFF89 48 15 2C FFFFFF89 49 FFFFFF89 4E FFFFFF89 50
   FFFFFF89 52 FFFFFF89 54 FFFFFF89 56 FFFFFF89 58 FFFFFF89 5A FFFFFF89 5C FFFFFF89 5E FFFFFF89 60
   FFFFFF89 62 FFFFFF89 64 FFFFFF89 66 FFFFFF89 68 FFFFFF89 6A FFFFFF89 6C FFFFFF89 6E FFFFFF89 70
   FFFFFF89 72 FFFFFF89 74 FFFFFF89 76 14 2C FFFFFF89 4A FFFFFF89 78 FFFFFF89 79 FFFFFF89 7A
   FFFFFF89 7B FFFFFF89 7C FFFFFF89 7D FFFFFF89 7E FFFFFF89 7F FFFFFF8A 00 FFFFFF8A 01 FFFFFF8A 02
   FFFFFF8A 03 FFFFFF8A 04 FFFFFF8A 05 FFFFFF8A 06 FFFFFF8A 07 FFFFFF8A 08 FFFFFF8A 09 FFFFFF8A 0A
   FFFFFF8A 0B FFFFFF8A 0C 10 2D 06 FFFFFF89 4B FFFFFF89 4D FFFFFF89 4F FFFFFF89 51 FFFFFF89
   53 FFFFFF89 55 FFFFFF89 57 FFFFFF89 59 FFFFFF89 5B FFFFFF89 5D FFFFFF89 5F FFFFFF89 61 FFFFFF89
   63 FFFFFF89 65 FFFFFF89 67 FFFFFF89 69 FFFFFF89 6B FFFFFF89 6D FFFFFF89 6F FFFFFF89 71 FFFFFF89
   73 FFFFFF89 75 09 03 FFFFFF89 4C 02 02 07 54 75 70 6C 65 32
   31 10 03 5C FFFFFF89 4E 04 0A FFFFFF83 1E FFFFFF89 47 FFFFFF84 FFFFFF80 FFFFFF80 FFFFFFC2
   00 5F 10 03 5C FFFFFF89 50 04 0A FFFFFF83 31 FFFFFF89 47 FFFFFF84 FFFFFF80 FFFFFF80
   FFFFFFC2 00 5F 10 03 5C FFFFFF89 52 04 0A FFFFFF83 44 FFFFFF89 47 FFFFFF84 FFFFFF80
   FFFFFF80 FFFFFFC2 00 5F 10 03 5C FFFFFF89 54 04 0A FFFFFF83 58 FFFFFF89 47 FFFFFF84
   FFFFFF80 FFFFFF80 FFFFFFC2 00 5F 10 03 5C FFFFFF89 56 04 0A FFFFFF83 6F FFFFFF89 47
   FFFFFF84 FFFFFF80 FFFFFF80 FFFFFFC2 00 5F 10 03 5C FFFFFF89 58 04 0A FFFFFF84 09 FFFFFF89
   47 FFFFFF84 FFFFFF80 FFFFFF80 FFFFFFC2 00 5F 10 03 5C FFFFFF89 5A 04 0A FFFFFF84 26
   FFFFFF89 47 FFFFFF84 FFFFFF80 FFFFFF80 FFFFFFC2 00 5F 10 03 5C FFFFFF89 5C 04 0A FFFFFF84
   46 FFFFFF89 47 FFFFFF84 FFFFFF80 FFFFFF80 FFFFFFC2 00 5F 10 03 5C FFFFFF89 5E 04 0A
   FFFFFF84 69 FFFFFF89 47 FFFFFF84 FFFFFF80 FFFFFF80 FFFFFFC2 00 5F 10 03 5C FFFFFF89 60 04
   0A FFFFFF85 0F FFFFFF89 47 FFFFFF84 FFFFFF80 FFFFFF80 FFFFFFC2 00 5F 10 03 5C FFFFFF89 62
   04 0A FFFFFF85 38 FFFFFF89 47 FFFFFF84 FFFFFF80 FFFFFF80 FFFFFFC2 00 5F 10 03 5C FFFFFF89
   64 04 0A FFFFFF85 64 FFFFFF89 47 FFFFFF84 FFFFFF80 FFFFFF80 FFFFFFC2 00 5F 10 03 5C
   FFFFFF89 66 04 0A FFFFFF86 13 FFFFFF89 47 FFFFFF84 FFFFFF80 FFFFFF80 FFFFFFC2 00 5F 10 03
   5C FFFFFF89 68 04 0A FFFFFF86 45 FFFFFF89 47 FFFFFF84 FFFFFF80 FFFFFF80 FFFFFFC2 00 5F 10
   03 5C FFFFFF89 6A 04 0A FFFFFF86 7A FFFFFF89 47 FFFFFF84 FFFFFF80 FFFFFF80 FFFFFFC2 00 5F
   10 03 5C FFFFFF89 6C 04 0A FFFFFF87 32 FFFFFF89 47 FFFFFF84 FFFFFF80 FFFFFF80 FFFFFFC2 00
   5F 10 03 5C FFFFFF89 6E 04 0A FFFFFF87 6D FFFFFF89 47 FFFFFF84 FFFFFF80 FFFFFF80 FFFFFFC2
   00 5F 10 03 5C FFFFFF89 70 04 0A FFFFFF88 2B FFFFFF89 47 FFFFFF84 FFFFFF80 FFFFFF80
   FFFFFFC2 00 5F 10 03 5C FFFFFF89 72 04 0A FFFFFF88 6C FFFFFF89 47 FFFFFF84 FFFFFF80
   FFFFFF80 FFFFFFC2 00 5F 10 03 5C FFFFFF89 74 04 0A FFFFFF89 30 FFFFFF89 47 FFFFFF84
   FFFFFF80 FFFFFF80 FFFFFFC2 00 5F 10 03 5C FFFFFF89 76 04 0A FFFFFF89 77 FFFFFF89 47
   FFFFFF84 FFFFFF80 FFFFFF80 FFFFFFC2 00 5F 02 03 41 32 31 08 08 FFFFFF83 20 FFFFFF89
   47 FFFFFFC0 00 FFFFFF89 4D 08 08 FFFFFF83 34 FFFFFF89 47 FFFFFFC0 00 FFFFFF89 4F 08
   08 FFFFFF83 48 FFFFFF89 47 FFFFFFC0 00 FFFFFF89 51 08 08 FFFFFF83 5D FFFFFF89 47 FFFFFFC0
   00 FFFFFF89 53 08 08 FFFFFF83 75 FFFFFF89 47 FFFFFFC0 00 FFFFFF89 55 08 08 FFFFFF84
   10 FFFFFF89 47 FFFFFFC0 00 FFFFFF89 57 08 08 FFFFFF84 2E FFFFFF89 47 FFFFFFC0 00 FFFFFF89
   59 08 08 FFFFFF84 4F FFFFFF89 47 FFFFFFC0 00 FFFFFF89 5B 08 08 FFFFFF84 73 FFFFFF89
   47 FFFFFFC0 00 FFFFFF89 5D 08 08 FFFFFF85 1A FFFFFF89 47 FFFFFFC0 00 FFFFFF89 5F 08
   08 FFFFFF85 44 FFFFFF89 47 FFFFFFC0 00 FFFFFF89 61 08 08 FFFFFF85 71 FFFFFF89 47 FFFFFFC0
   00 FFFFFF89 63 08 08 FFFFFF86 21 FFFFFF89 47 FFFFFFC0 00 FFFFFF89 65 08 08 FFFFFF86
   54 FFFFFF89 47 FFFFFFC0 00 FFFFFF89 67 08 08 FFFFFF87 0A FFFFFF89 47 FFFFFFC0 00 FFFFFF89
   69 08 08 FFFFFF87 43 FFFFFF89 47 FFFFFFC0 00 FFFFFF89 6B 08 08 FFFFFF87 7F FFFFFF89
   47 FFFFFFC0 00 FFFFFF89 6D 08 08 FFFFFF88 3E FFFFFF89 47 FFFFFFC0 00 FFFFFF89 6F 08
   08 FFFFFF89 00 FFFFFF89 47 FFFFFFC0 00 FFFFFF89 71 08 08 FFFFFF89 45 FFFFFF89 47 FFFFFFC0
   00 FFFFFF89 73 08 08 FFFFFF8A 0D FFFFFF89 47 FFFFFFC0 00 FFFFFF89 75 01 03 78
   32 31 28 06 FFFFFF89 47 FFFFFF83 22 FFFFFF83 36 08 07 FFFFFF83 16 07 FFFFFF84
   00 FFFFFF8A 10 15 2E FFFFFF8A 11 FFFFFF8A 16 FFFFFF8A 18 FFFFFF8A 1A FFFFFF8A 1C FFFFFF8A
   1E FFFFFF8A 20 FFFFFF8A 22 FFFFFF8A 24 FFFFFF8A 26 FFFFFF8A 28 FFFFFF8A 2A FFFFFF8A 2C FFFFFF8A
   2E FFFFFF8A 30 FFFFFF8A 32 FFFFFF8A 34 FFFFFF8A 36 FFFFFF8A 38 FFFFFF8A 3A FFFFFF8A 3C FFFFFF8A
   3E FFFFFF8A 40 14 2E FFFFFF8A 12 FFFFFF8A 42 FFFFFF8A 43 FFFFFF8A 44 FFFFFF8A 45 FFFFFF8A
   46 FFFFFF8A 47 FFFFFF8A 48 FFFFFF8A 49 FFFFFF8A 4A FFFFFF8A 4B FFFFFF8A 4C FFFFFF8A 4D FFFFFF8A
   4E FFFFFF8A 4F FFFFFF8A 50 FFFFFF8A 51 FFFFFF8A 52 FFFFFF8A 53 FFFFFF8A 54 FFFFFF8A 55 FFFFFF8A
   56 FFFFFF8A 57 10 2F 06 FFFFFF8A 13 FFFFFF8A 15 FFFFFF8A 17 FFFFFF8A 19 FFFFFF8A 1B
   FFFFFF8A 1D FFFFFF8A 1F FFFFFF8A 21 FFFFFF8A 23 FFFFFF8A 25 FFFFFF8A 27 FFFFFF8A 29 FFFFFF8A 2B
   FFFFFF8A 2D FFFFFF8A 2F FFFFFF8A 31 FFFFFF8A 33 FFFFFF8A 35 FFFFFF8A 37 FFFFFF8A 39 FFFFFF8A 3B
   FFFFFF8A 3D FFFFFF8A 3F 09 03 FFFFFF8A 14 02 02 07 54 75 70 6C 65
   32 32 10 03 5C FFFFFF8A 16 04 0A FFFFFF83 1E FFFFFF8A 0F FFFFFF84 FFFFFF80 FFFFFF80
   FFFFFFC2 00 5F 10 03 5C FFFFFF8A 18 04 0A FFFFFF83 31 FFFFFF8A 0F FFFFFF84 FFFFFF80
   FFFFFF80 FFFFFFC2 00 5F 10 03 5C FFFFFF8A 1A 04 0A FFFFFF83 44 FFFFFF8A 0F FFFFFF84
   FFFFFF80 FFFFFF80 FFFFFFC2 00 5F 10 03 5C FFFFFF8A 1C 04 0A FFFFFF83 58 FFFFFF8A 0F
   FFFFFF84 FFFFFF80 FFFFFF80 FFFFFFC2 00 5F 10 03 5C FFFFFF8A 1E 04 0A FFFFFF83 6F FFFFFF8A
   0F FFFFFF84 FFFFFF80 FFFFFF80 FFFFFFC2 00 5F 10 03 5C FFFFFF8A 20 04 0A FFFFFF84 09
   FFFFFF8A 0F FFFFFF84 FFFFFF80 FFFFFF80 FFFFFFC2 00 5F 10 03 5C FFFFFF8A 22 04 0A FFFFFF84
   26 FFFFFF8A 0F FFFFFF84 FFFFFF80 FFFFFF80 FFFFFFC2 00 5F 10 03 5C FFFFFF8A 24 04 0A
   FFFFFF84 46 FFFFFF8A 0F FFFFFF84 FFFFFF80 FFFFFF80 FFFFFFC2 00 5F 10 03 5C FFFFFF8A 26 04
   0A FFFFFF84 69 FFFFFF8A 0F FFFFFF84 FFFFFF80 FFFFFF80 FFFFFFC2 00 5F 10 03 5C FFFFFF8A 28
   04 0A FFFFFF85 0F FFFFFF8A 0F FFFFFF84 FFFFFF80 FFFFFF80 FFFFFFC2 00 5F 10 03 5C FFFFFF8A
   2A 04 0A FFFFFF85 38 FFFFFF8A 0F FFFFFF84 FFFFFF80 FFFFFF80 FFFFFFC2 00 5F 10 03 5C
   FFFFFF8A 2C 04 0A FFFFFF85 64 FFFFFF8A 0F FFFFFF84 FFFFFF80 FFFFFF80 FFFFFFC2 00 5F 10 03
   5C FFFFFF8A 2E 04 0A FFFFFF86 13 FFFFFF8A 0F FFFFFF84 FFFFFF80 FFFFFF80 FFFFFFC2 00 5F 10
   03 5C FFFFFF8A 30 04 0A FFFFFF86 45 FFFFFF8A 0F FFFFFF84 FFFFFF80 FFFFFF80 FFFFFFC2 00 5F
   10 03 5C FFFFFF8A 32 04 0A FFFFFF86 7A FFFFFF8A 0F FFFFFF84 FFFFFF80 FFFFFF80 FFFFFFC2 00
   5F 10 03 5C FFFFFF8A 34 04 0A FFFFFF87 32 FFFFFF8A 0F FFFFFF84 FFFFFF80 FFFFFF80 FFFFFFC2
   00 5F 10 03 5C FFFFFF8A 36 04 0A FFFFFF87 6D FFFFFF8A 0F FFFFFF84 FFFFFF80 FFFFFF80
   FFFFFFC2 00 5F 10 03 5C FFFFFF8A 38 04 0A FFFFFF88 2B FFFFFF8A 0F FFFFFF84 FFFFFF80
   FFFFFF80 FFFFFFC2 00 5F 10 03 5C FFFFFF8A 3A 04 0A FFFFFF88 6C FFFFFF8A 0F FFFFFF84
   FFFFFF80 FFFFFF80 FFFFFFC2 00 5F 10 03 5C FFFFFF8A 3C 04 0A FFFFFF89 30 FFFFFF8A 0F
   FFFFFF84 FFFFFF80 FFFFFF80 FFFFFFC2 00 5F 10 03 5C FFFFFF8A 3E 04 0A FFFFFF89 77 FFFFFF8A
   0F FFFFFF84 FFFFFF80 FFFFFF80 FFFFFFC2 00 5F 10 03 5C FFFFFF8A 40 04 0A FFFFFF8A 41
   FFFFFF8A 0F FFFFFF84 FFFFFF80 FFFFFF80 FFFFFFC2 00 5F 02 03 41 32 32 08 08 FFFFFF83
   20 FFFFFF8A 0F FFFFFFC0 00 FFFFFF8A 15 08 08 FFFFFF83 34 FFFFFF8A 0F FFFFFFC0 00 FFFFFF8A
   17 08 08 FFFFFF83 48 FFFFFF8A 0F FFFFFFC0 00 FFFFFF8A 19 08 08 FFFFFF83 5D FFFFFF8A
   0F FFFFFFC0 00 FFFFFF8A 1B 08 08 FFFFFF83 75 FFFFFF8A 0F FFFFFFC0 00 FFFFFF8A 1D 08
   08 FFFFFF84 10 FFFFFF8A 0F FFFFFFC0 00 FFFFFF8A 1F 08 08 FFFFFF84 2E FFFFFF8A 0F FFFFFFC0
   00 FFFFFF8A 21 08 08 FFFFFF84 4F FFFFFF8A 0F FFFFFFC0 00 FFFFFF8A 23 08 08 FFFFFF84
   73 FFFFFF8A 0F FFFFFFC0 00 FFFFFF8A 25 08 08 FFFFFF85 1A FFFFFF8A 0F FFFFFFC0 00 FFFFFF8A
   27 08 08 FFFFFF85 44 FFFFFF8A 0F FFFFFFC0 00 FFFFFF8A 29 08 08 FFFFFF85 71 FFFFFF8A
   0F FFFFFFC0 00 FFFFFF8A 2B 08 08 FFFFFF86 21 FFFFFF8A 0F FFFFFFC0 00 FFFFFF8A 2D 08
   08 FFFFFF86 54 FFFFFF8A 0F FFFFFFC0 00 FFFFFF8A 2F 08 08 FFFFFF87 0A FFFFFF8A 0F FFFFFFC0
   00 FFFFFF8A 31 08 08 FFFFFF87 43 FFFFFF8A 0F FFFFFFC0 00 FFFFFF8A 33 08 08 FFFFFF87
   7F FFFFFF8A 0F FFFFFFC0 00 FFFFFF8A 35 08 08 FFFFFF88 3E FFFFFF8A 0F FFFFFFC0 00 FFFFFF8A
   37 08 08 FFFFFF89 00 FFFFFF8A 0F FFFFFFC0 00 FFFFFF8A 39 08 08 FFFFFF89 45 FFFFFF8A
   0F FFFFFFC0 00 FFFFFF8A 3B 08 08 FFFFFF8A 0D FFFFFF8A 0F FFFFFFC0 00 FFFFFF8A 3D 08
   08 FFFFFF8A 58 FFFFFF8A 0F FFFFFFC0 00 FFFFFF8A 3F 01 03 78 32 32 28 06
   FFFFFF8A 0F FFFFFF83 22 FFFFFF83 36 05 0A FFFFFF8A 5B 07 FFFFFF84 FFFFFF80 FFFFFF80 FFFFFF80 00
   FFFFFF8A 5C 02 07 49 6E 74 65 67 65 72 10 03 0B FFFFFF8A 5D
   09 03 FFFFFF8A 5B 0C 28 06 FFFFFF8A 5A FFFFFF83 22 FFFFFF8A 5F 21 02 FFFFFF8A
   60 01 2A 75 73 65 20 3C 63 6F 64 65 3E 6A 61 76
   61 2E 6C 61 6E 67 2E 49 6E 74 65 67 65 72 3C 2F
   63 6F 64 65 3E 20 69 6E 73 74 65 61 64 05 0A FFFFFF8A
   62 07 FFFFFF84 FFFFFF80 FFFFFF80 FFFFFF80 00 FFFFFF8A 63 02 09 43 68 61 72 61
   63 74 65 72 10 03 0B FFFFFF8A 64 09 03 FFFFFF8A 62 0C 28 06
   FFFFFF8A 61 FFFFFF83 22 FFFFFF8A 66 21 02 FFFFFF8A 67 01 2C 75 73 65 20
   3C 63 6F 64 65 3E 6A 61 76 61 2E 6C 61 6E 67 2E
   43 68 61 72 61 63 74 65 72 3C 2F 63 6F 64 65 3E
   20 69 6E 73 74 65 61 64 05 06 FFFFFF8A 69 07 00 FFFFFF8A 6A
   02 0A 43 6F 6C 6C 65 63 74 69 6F 6E 15 04 FFFFFF8A 6B
   FFFFFF8A 6E 10 05 FFFFFF8A 6C 74 FFFFFF8A 6D 0D 01 07 10 03 5C FFFFFF8A
   6E 04 09 5E FFFFFF8A 68 FFFFFF84 FFFFFF80 FFFFFF84 FFFFFFC2 00 5F 28 06 FFFFFF8A 68
   FFFFFF83 22 FFFFFF8A 70 21 02 FFFFFF8A 71 01 14 75 73 65 20 49 74
   65 72 61 62 6C 65 20 69 6E 73 74 65 61 64 08 08
   FFFFFF8A 73 07 FFFFFFC2 FFFFFF80 FFFFFF84 00 7D 01 0A 43 6F 6C 6C 65 63
   74 69 6F 6E 28 06 FFFFFF8A 72 FFFFFF83 22 FFFFFF8A 70 08 07 FFFFFF8A 76
   07 FFFFFFA0 FFFFFF80 04 7E 01 0B 43 6F 6C 6C 65 63 74 69 6F
   6E 20 05 06 FFFFFF8A 78 07 00 FFFFFF8A 79 02 08 53 65 71 75
   65 6E 63 65 15 04 FFFFFF8A 7A FFFFFF8A 7C 10 05 57 FFFFFF81 06 FFFFFF8A
   7B 10 03 5C FFFFFF8A 7C 04 09 5E FFFFFF8A 77 FFFFFF84 FFFFFF80 FFFFFF84 FFFFFFC2 00
   5F 28 06 FFFFFF8A 77 FFFFFF83 22 FFFFFF8A 7E 21 02 FFFFFF8A 7F 01 0F 75
   73 65 20 53 65 71 20 69 6E 73 74 65 61 64 08 09
   FFFFFF8B 01 07 FFFFFFC2 FFFFFF80 FFFFFF84 00 FFFFFF81 0B 01 08 53 65 71 75 65
   6E 63 65 28 06 FFFFFF8B 00 FFFFFF83 22 FFFFFF8A 7E 08 08 FFFFFF8B 04 07
   FFFFFFA0 FFFFFF80 04 FFFFFF81 0C 01 09 53 65 71 75 65 6E 63 65 20
   05 06 FFFFFF8B 06 07 00 FFFFFF8B 07 02 0F 52 61 6E 64 6F 6D
   41 63 63 65 73 73 53 65 71 15 04 FFFFFF8B 08 FFFFFF8B 0A 10
   05 57 FFFFFF81 14 FFFFFF8B 09 10 03 5C FFFFFF8B 0A 04 09 5E FFFFFF8B 05
   FFFFFF84 FFFFFF80 FFFFFF84 FFFFFFC2 00 5F 28 06 FFFFFF8B 05 FFFFFF83 22 FFFFFF8B 0C 21 02
   FFFFFF8B 0D 01 16 75 73 65 20 49 6E 64 65 78 65 64 53
   65 71 20 69 6E 73 74 65 61 64 08 09 FFFFFF8B 0F 07 FFFFFFC2
   FFFFFF80 FFFFFF84 00 FFFFFF81 19 01 0F 52 61 6E 64 6F 6D 41 63 63
   65 73 73 53 65 71 28 06 FFFFFF8B 0E FFFFFF83 22 FFFFFF8B 0C 08 08
   FFFFFF8B 12 07 FFFFFFA0 FFFFFF80 04 FFFFFF81 1A 01 10 52 61 6E 64 6F 6D
   41 63 63 65 73 73 53 65 71 20 
  minor version: 0
  major version: 49
  Constant pool:
const #1 = Asciz	SourceFile;
const #2 = Asciz	package.scala;
const #3 = Asciz	RandomAccessSeq;
const #4 = Asciz	()Lscala/collection/IndexedSeq$;;
const #5 = Asciz	Code;
const #6 = Asciz	scala/package$;
const #7 = class	#6;	//  scala/package$
const #8 = Asciz	MODULE$;
const #9 = Asciz	Lscala/package$;;
const #10 = NameAndType	#8:#9;//  MODULE$:Lscala/package$;
const #11 = Field	#7.#10;	//  scala/package$.MODULE$:Lscala/package$;
const #12 = NameAndType	#3:#4;//  RandomAccessSeq:()Lscala/collection/IndexedSeq$;
const #13 = Method	#7.#12;	//  scala/package$.RandomAccessSeq:()Lscala/collection/IndexedSeq$;
const #14 = Asciz	Sequence;
const #15 = Asciz	()Lscala/collection/Seq$;;
const #16 = NameAndType	#14:#15;//  Sequence:()Lscala/collection/Seq$;
const #17 = Method	#7.#16;	//  scala/package$.Sequence:()Lscala/collection/Seq$;
const #18 = Asciz	Collection;
const #19 = Asciz	()Lscala/collection/Iterable$;;
const #20 = NameAndType	#18:#19;//  Collection:()Lscala/collection/Iterable$;
const #21 = Method	#7.#20;	//  scala/package$.Collection:()Lscala/collection/Iterable$;
const #22 = Asciz	Tuple;
const #23 = Asciz	(Ljava/lang/Object;Ljava/lang/Object;Ljava/lang/Object;Ljava/lang/Object;Ljava/lang/Object;Ljava/lang/Object;Ljava/lang/Object;Ljava/lang/Object;Ljava/lang/Object;Ljava/lang/Object;Ljava/lang/Object;Ljava/lang/Object;Ljava/lang/Object;Ljava/lang/Object;Ljava/lang/Object;Ljava/lang/Object;Ljava/lang/Object;Ljava/lang/Object;Ljava/lang/Object;Ljava/lang/Object;Ljava/lang/Object;Ljava/lang/Object;)Lscala/Tuple22;;
const #24 = NameAndType	#22:#23;//  Tuple:(Ljava/lang/Object;Ljava/lang/Object;Ljava/lang/Object;Ljava/lang/Object;Ljava/lang/Object;Ljava/lang/Object;Ljava/lang/Object;Ljava/lang/Object;Ljava/lang/Object;Ljava/lang/Object;Ljava/lang/Object;Ljava/lang/Object;Ljava/lang/Object;Ljava/lang/Object;Ljava/lang/Object;Ljava/lang/Object;Ljava/lang/Object;Ljava/lang/Object;Ljava/lang/Object;Ljava/lang/Object;Ljava/lang/Object;Ljava/lang/Object;)Lscala/Tuple22;
const #25 = Method	#7.#24;	//  scala/package$.Tuple:(Ljava/lang/Object;Ljava/lang/Object;Ljava/lang/Object;Ljava/lang/Object;Ljava/lang/Object;Ljava/lang/Object;Ljava/lang/Object;Ljava/lang/Object;Ljava/lang/Object;Ljava/lang/Object;Ljava/lang/Object;Ljava/lang/Object;Ljava/lang/Object;Ljava/lang/Object;Ljava/lang/Object;Ljava/lang/Object;Ljava/lang/Object;Ljava/lang/Object;Ljava/lang/Object;Ljava/lang/Object;Ljava/lang/Object;Ljava/lang/Object;)Lscala/Tuple22;
const #26 = Asciz	<A1:Ljava/lang/Object;A2:Ljava/lang/Object;A3:Ljava/lang/Object;A4:Ljava/lang/Object;A5:Ljava/lang/Object;A6:Ljava/lang/Object;A7:Ljava/lang/Object;A8:Ljava/lang/Object;A9:Ljava/lang/Object;A10:Ljava/lang/Object;A11:Ljava/lang/Object;A12:Ljava/lang/Object;A13:Ljava/lang/Object;A14:Ljava/lang/Object;A15:Ljava/lang/Object;A16:Ljava/lang/Object;A17:Ljava/lang/Object;A18:Ljava/lang/Object;A19:Ljava/lang/Object;A20:Ljava/lang/Object;A21:Ljava/lang/Object;A22:Ljava/lang/Object;>(TA1;TA2;TA3;TA4;TA5;TA6;TA7;TA8;TA9;TA10;TA11;TA12;TA13;TA14;TA15;TA16;TA17;TA18;TA19;TA20;TA21;TA22;)Lscala/Tuple22<TA1;TA2;TA3;TA4;TA5;TA6;TA7;TA8;TA9;TA10;TA11;TA12;TA13;TA14;TA15;TA16;TA17;TA18;TA19;TA20;TA21;TA22;>;;
const #27 = Asciz	Signature;
const #28 = Asciz	(Ljava/lang/Object;Ljava/lang/Object;Ljava/lang/Object;Ljava/lang/Object;Ljava/lang/Object;Ljava/lang/Object;Ljava/lang/Object;Ljava/lang/Object;Ljava/lang/Object;Ljava/lang/Object;Ljava/lang/Object;Ljava/lang/Object;Ljava/lang/Object;Ljava/lang/Object;Ljava/lang/Object;Ljava/lang/Object;Ljava/lang/Object;Ljava/lang/Object;Ljava/lang/Object;Ljava/lang/Object;Ljava/lang/Object;)Lscala/Tuple21;;
const #29 = NameAndType	#22:#28;//  Tuple:(Ljava/lang/Object;Ljava/lang/Object;Ljava/lang/Object;Ljava/lang/Object;Ljava/lang/Object;Ljava/lang/Object;Ljava/lang/Object;Ljava/lang/Object;Ljava/lang/Object;Ljava/lang/Object;Ljava/lang/Object;Ljava/lang/Object;Ljava/lang/Object;Ljava/lang/Object;Ljava/lang/Object;Ljava/lang/Object;Ljava/lang/Object;Ljava/lang/Object;Ljava/lang/Object;Ljava/lang/Object;Ljava/lang/Object;)Lscala/Tuple21;
const #30 = Method	#7.#29;	//  scala/package$.Tuple:(Ljava/lang/Object;Ljava/lang/Object;Ljava/lang/Object;Ljava/lang/Object;Ljava/lang/Object;Ljava/lang/Object;Ljava/lang/Object;Ljava/lang/Object;Ljava/lang/Object;Ljava/lang/Object;Ljava/lang/Object;Ljava/lang/Object;Ljava/lang/Object;Ljava/lang/Object;Ljava/lang/Object;Ljava/lang/Object;Ljava/lang/Object;Ljava/lang/Object;Ljava/lang/Object;Ljava/lang/Object;Ljava/lang/Object;)Lscala/Tuple21;
const #31 = Asciz	<A1:Ljava/lang/Object;A2:Ljava/lang/Object;A3:Ljava/lang/Object;A4:Ljava/lang/Object;A5:Ljava/lang/Object;A6:Ljava/lang/Object;A7:Ljava/lang/Object;A8:Ljava/lang/Object;A9:Ljava/lang/Object;A10:Ljava/lang/Object;A11:Ljava/lang/Object;A12:Ljava/lang/Object;A13:Ljava/lang/Object;A14:Ljava/lang/Object;A15:Ljava/lang/Object;A16:Ljava/lang/Object;A17:Ljava/lang/Object;A18:Ljava/lang/Object;A19:Ljava/lang/Object;A20:Ljava/lang/Object;A21:Ljava/lang/Object;>(TA1;TA2;TA3;TA4;TA5;TA6;TA7;TA8;TA9;TA10;TA11;TA12;TA13;TA14;TA15;TA16;TA17;TA18;TA19;TA20;TA21;)Lscala/Tuple21<TA1;TA2;TA3;TA4;TA5;TA6;TA7;TA8;TA9;TA10;TA11;TA12;TA13;TA14;TA15;TA16;TA17;TA18;TA19;TA20;TA21;>;;
const #32 = Asciz	(Ljava/lang/Object;Ljava/lang/Object;Ljava/lang/Object;Ljava/lang/Object;Ljava/lang/Object;Ljava/lang/Object;Ljava/lang/Object;Ljava/lang/Object;Ljava/lang/Object;Ljava/lang/Object;Ljava/lang/Object;Ljava/lang/Object;Ljava/lang/Object;Ljava/lang/Object;Ljava/lang/Object;Ljava/lang/Object;Ljava/lang/Object;Ljava/lang/Object;Ljava/lang/Object;Ljava/lang/Object;)Lscala/Tuple20;;
const #33 = NameAndType	#22:#32;//  Tuple:(Ljava/lang/Object;Ljava/lang/Object;Ljava/lang/Object;Ljava/lang/Object;Ljava/lang/Object;Ljava/lang/Object;Ljava/lang/Object;Ljava/lang/Object;Ljava/lang/Object;Ljava/lang/Object;Ljava/lang/Object;Ljava/lang/Object;Ljava/lang/Object;Ljava/lang/Object;Ljava/lang/Object;Ljava/lang/Object;Ljava/lang/Object;Ljava/lang/Object;Ljava/lang/Object;Ljava/lang/Object;)Lscala/Tuple20;
const #34 = Method	#7.#33;	//  scala/package$.Tuple:(Ljava/lang/Object;Ljava/lang/Object;Ljava/lang/Object;Ljava/lang/Object;Ljava/lang/Object;Ljava/lang/Object;Ljava/lang/Object;Ljava/lang/Object;Ljava/lang/Object;Ljava/lang/Object;Ljava/lang/Object;Ljava/lang/Object;Ljava/lang/Object;Ljava/lang/Object;Ljava/lang/Object;Ljava/lang/Object;Ljava/lang/Object;Ljava/lang/Object;Ljava/lang/Object;Ljava/lang/Object;)Lscala/Tuple20;
const #35 = Asciz	<A1:Ljava/lang/Object;A2:Ljava/lang/Object;A3:Ljava/lang/Object;A4:Ljava/lang/Object;A5:Ljava/lang/Object;A6:Ljava/lang/Object;A7:Ljava/lang/Object;A8:Ljava/lang/Object;A9:Ljava/lang/Object;A10:Ljava/lang/Object;A11:Ljava/lang/Object;A12:Ljava/lang/Object;A13:Ljava/lang/Object;A14:Ljava/lang/Object;A15:Ljava/lang/Object;A16:Ljava/lang/Object;A17:Ljava/lang/Object;A18:Ljava/lang/Object;A19:Ljava/lang/Object;A20:Ljava/lang/Object;>(TA1;TA2;TA3;TA4;TA5;TA6;TA7;TA8;TA9;TA10;TA11;TA12;TA13;TA14;TA15;TA16;TA17;TA18;TA19;TA20;)Lscala/Tuple20<TA1;TA2;TA3;TA4;TA5;TA6;TA7;TA8;TA9;TA10;TA11;TA12;TA13;TA14;TA15;TA16;TA17;TA18;TA19;TA20;>;;
const #36 = Asciz	(Ljava/lang/Object;Ljava/lang/Object;Ljava/lang/Object;Ljava/lang/Object;Ljava/lang/Object;Ljava/lang/Object;Ljava/lang/Object;Ljava/lang/Object;Ljava/lang/Object;Ljava/lang/Object;Ljava/lang/Object;Ljava/lang/Object;Ljava/lang/Object;Ljava/lang/Object;Ljava/lang/Object;Ljava/lang/Object;Ljava/lang/Object;Ljava/lang/Object;Ljava/lang/Object;)Lscala/Tuple19;;
const #37 = NameAndType	#22:#36;//  Tuple:(Ljava/lang/Object;Ljava/lang/Object;Ljava/lang/Object;Ljava/lang/Object;Ljava/lang/Object;Ljava/lang/Object;Ljava/lang/Object;Ljava/lang/Object;Ljava/lang/Object;Ljava/lang/Object;Ljava/lang/Object;Ljava/lang/Object;Ljava/lang/Object;Ljava/lang/Object;Ljava/lang/Object;Ljava/lang/Object;Ljava/lang/Object;Ljava/lang/Object;Ljava/lang/Object;)Lscala/Tuple19;
const #38 = Method	#7.#37;	//  scala/package$.Tuple:(Ljava/lang/Object;Ljava/lang/Object;Ljava/lang/Object;Ljava/lang/Object;Ljava/lang/Object;Ljava/lang/Object;Ljava/lang/Object;Ljava/lang/Object;Ljava/lang/Object;Ljava/lang/Object;Ljava/lang/Object;Ljava/lang/Object;Ljava/lang/Object;Ljava/lang/Object;Ljava/lang/Object;Ljava/lang/Object;Ljava/lang/Object;Ljava/lang/Object;Ljava/lang/Object;)Lscala/Tuple19;
const #39 = Asciz	<A1:Ljava/lang/Object;A2:Ljava/lang/Object;A3:Ljava/lang/Object;A4:Ljava/lang/Object;A5:Ljava/lang/Object;A6:Ljava/lang/Object;A7:Ljava/lang/Object;A8:Ljava/lang/Object;A9:Ljava/lang/Object;A10:Ljava/lang/Object;A11:Ljava/lang/Object;A12:Ljava/lang/Object;A13:Ljava/lang/Object;A14:Ljava/lang/Object;A15:Ljava/lang/Object;A16:Ljava/lang/Object;A17:Ljava/lang/Object;A18:Ljava/lang/Object;A19:Ljava/lang/Object;>(TA1;TA2;TA3;TA4;TA5;TA6;TA7;TA8;TA9;TA10;TA11;TA12;TA13;TA14;TA15;TA16;TA17;TA18;TA19;)Lscala/Tuple19<TA1;TA2;TA3;TA4;TA5;TA6;TA7;TA8;TA9;TA10;TA11;TA12;TA13;TA14;TA15;TA16;TA17;TA18;TA19;>;;
const #40 = Asciz	(Ljava/lang/Object;Ljava/lang/Object;Ljava/lang/Object;Ljava/lang/Object;Ljava/lang/Object;Ljava/lang/Object;Ljava/lang/Object;Ljava/lang/Object;Ljava/lang/Object;Ljava/lang/Object;Ljava/lang/Object;Ljava/lang/Object;Ljava/lang/Object;Ljava/lang/Object;Ljava/lang/Object;Ljava/lang/Object;Ljava/lang/Object;Ljava/lang/Object;)Lscala/Tuple18;;
const #41 = NameAndType	#22:#40;//  Tuple:(Ljava/lang/Object;Ljava/lang/Object;Ljava/lang/Object;Ljava/lang/Object;Ljava/lang/Object;Ljava/lang/Object;Ljava/lang/Object;Ljava/lang/Object;Ljava/lang/Object;Ljava/lang/Object;Ljava/lang/Object;Ljava/lang/Object;Ljava/lang/Object;Ljava/lang/Object;Ljava/lang/Object;Ljava/lang/Object;Ljava/lang/Object;Ljava/lang/Object;)Lscala/Tuple18;
const #42 = Method	#7.#41;	//  scala/package$.Tuple:(Ljava/lang/Object;Ljava/lang/Object;Ljava/lang/Object;Ljava/lang/Object;Ljava/lang/Object;Ljava/lang/Object;Ljava/lang/Object;Ljava/lang/Object;Ljava/lang/Object;Ljava/lang/Object;Ljava/lang/Object;Ljava/lang/Object;Ljava/lang/Object;Ljava/lang/Object;Ljava/lang/Object;Ljava/lang/Object;Ljava/lang/Object;Ljava/lang/Object;)Lscala/Tuple18;
const #43 = Asciz	<A1:Ljava/lang/Object;A2:Ljava/lang/Object;A3:Ljava/lang/Object;A4:Ljava/lang/Object;A5:Ljava/lang/Object;A6:Ljava/lang/Object;A7:Ljava/lang/Object;A8:Ljava/lang/Object;A9:Ljava/lang/Object;A10:Ljava/lang/Object;A11:Ljava/lang/Object;A12:Ljava/lang/Object;A13:Ljava/lang/Object;A14:Ljava/lang/Object;A15:Ljava/lang/Object;A16:Ljava/lang/Object;A17:Ljava/lang/Object;A18:Ljava/lang/Object;>(TA1;TA2;TA3;TA4;TA5;TA6;TA7;TA8;TA9;TA10;TA11;TA12;TA13;TA14;TA15;TA16;TA17;TA18;)Lscala/Tuple18<TA1;TA2;TA3;TA4;TA5;TA6;TA7;TA8;TA9;TA10;TA11;TA12;TA13;TA14;TA15;TA16;TA17;TA18;>;;
const #44 = Asciz	(Ljava/lang/Object;Ljava/lang/Object;Ljava/lang/Object;Ljava/lang/Object;Ljava/lang/Object;Ljava/lang/Object;Ljava/lang/Object;Ljava/lang/Object;Ljava/lang/Object;Ljava/lang/Object;Ljava/lang/Object;Ljava/lang/Object;Ljava/lang/Object;Ljava/lang/Object;Ljava/lang/Object;Ljava/lang/Object;Ljava/lang/Object;)Lscala/Tuple17;;
const #45 = NameAndType	#22:#44;//  Tuple:(Ljava/lang/Object;Ljava/lang/Object;Ljava/lang/Object;Ljava/lang/Object;Ljava/lang/Object;Ljava/lang/Object;Ljava/lang/Object;Ljava/lang/Object;Ljava/lang/Object;Ljava/lang/Object;Ljava/lang/Object;Ljava/lang/Object;Ljava/lang/Object;Ljava/lang/Object;Ljava/lang/Object;Ljava/lang/Object;Ljava/lang/Object;)Lscala/Tuple17;
const #46 = Method	#7.#45;	//  scala/package$.Tuple:(Ljava/lang/Object;Ljava/lang/Object;Ljava/lang/Object;Ljava/lang/Object;Ljava/lang/Object;Ljava/lang/Object;Ljava/lang/Object;Ljava/lang/Object;Ljava/lang/Object;Ljava/lang/Object;Ljava/lang/Object;Ljava/lang/Object;Ljava/lang/Object;Ljava/lang/Object;Ljava/lang/Object;Ljava/lang/Object;Ljava/lang/Object;)Lscala/Tuple17;
const #47 = Asciz	<A1:Ljava/lang/Object;A2:Ljava/lang/Object;A3:Ljava/lang/Object;A4:Ljava/lang/Object;A5:Ljava/lang/Object;A6:Ljava/lang/Object;A7:Ljava/lang/Object;A8:Ljava/lang/Object;A9:Ljava/lang/Object;A10:Ljava/lang/Object;A11:Ljava/lang/Object;A12:Ljava/lang/Object;A13:Ljava/lang/Object;A14:Ljava/lang/Object;A15:Ljava/lang/Object;A16:Ljava/lang/Object;A17:Ljava/lang/Object;>(TA1;TA2;TA3;TA4;TA5;TA6;TA7;TA8;TA9;TA10;TA11;TA12;TA13;TA14;TA15;TA16;TA17;)Lscala/Tuple17<TA1;TA2;TA3;TA4;TA5;TA6;TA7;TA8;TA9;TA10;TA11;TA12;TA13;TA14;TA15;TA16;TA17;>;;
const #48 = Asciz	(Ljava/lang/Object;Ljava/lang/Object;Ljava/lang/Object;Ljava/lang/Object;Ljava/lang/Object;Ljava/lang/Object;Ljava/lang/Object;Ljava/lang/Object;Ljava/lang/Object;Ljava/lang/Object;Ljava/lang/Object;Ljava/lang/Object;Ljava/lang/Object;Ljava/lang/Object;Ljava/lang/Object;Ljava/lang/Object;)Lscala/Tuple16;;
const #49 = NameAndType	#22:#48;//  Tuple:(Ljava/lang/Object;Ljava/lang/Object;Ljava/lang/Object;Ljava/lang/Object;Ljava/lang/Object;Ljava/lang/Object;Ljava/lang/Object;Ljava/lang/Object;Ljava/lang/Object;Ljava/lang/Object;Ljava/lang/Object;Ljava/lang/Object;Ljava/lang/Object;Ljava/lang/Object;Ljava/lang/Object;Ljava/lang/Object;)Lscala/Tuple16;
const #50 = Method	#7.#49;	//  scala/package$.Tuple:(Ljava/lang/Object;Ljava/lang/Object;Ljava/lang/Object;Ljava/lang/Object;Ljava/lang/Object;Ljava/lang/Object;Ljava/lang/Object;Ljava/lang/Object;Ljava/lang/Object;Ljava/lang/Object;Ljava/lang/Object;Ljava/lang/Object;Ljava/lang/Object;Ljava/lang/Object;Ljava/lang/Object;Ljava/lang/Object;)Lscala/Tuple16;
const #51 = Asciz	<A1:Ljava/lang/Object;A2:Ljava/lang/Object;A3:Ljava/lang/Object;A4:Ljava/lang/Object;A5:Ljava/lang/Object;A6:Ljava/lang/Object;A7:Ljava/lang/Object;A8:Ljava/lang/Object;A9:Ljava/lang/Object;A10:Ljava/lang/Object;A11:Ljava/lang/Object;A12:Ljava/lang/Object;A13:Ljava/lang/Object;A14:Ljava/lang/Object;A15:Ljava/lang/Object;A16:Ljava/lang/Object;>(TA1;TA2;TA3;TA4;TA5;TA6;TA7;TA8;TA9;TA10;TA11;TA12;TA13;TA14;TA15;TA16;)Lscala/Tuple16<TA1;TA2;TA3;TA4;TA5;TA6;TA7;TA8;TA9;TA10;TA11;TA12;TA13;TA14;TA15;TA16;>;;
const #52 = Asciz	(Ljava/lang/Object;Ljava/lang/Object;Ljava/lang/Object;Ljava/lang/Object;Ljava/lang/Object;Ljava/lang/Object;Ljava/lang/Object;Ljava/lang/Object;Ljava/lang/Object;Ljava/lang/Object;Ljava/lang/Object;Ljava/lang/Object;Ljava/lang/Object;Ljava/lang/Object;Ljava/lang/Object;)Lscala/Tuple15;;
const #53 = NameAndType	#22:#52;//  Tuple:(Ljava/lang/Object;Ljava/lang/Object;Ljava/lang/Object;Ljava/lang/Object;Ljava/lang/Object;Ljava/lang/Object;Ljava/lang/Object;Ljava/lang/Object;Ljava/lang/Object;Ljava/lang/Object;Ljava/lang/Object;Ljava/lang/Object;Ljava/lang/Object;Ljava/lang/Object;Ljava/lang/Object;)Lscala/Tuple15;
const #54 = Method	#7.#53;	//  scala/package$.Tuple:(Ljava/lang/Object;Ljava/lang/Object;Ljava/lang/Object;Ljava/lang/Object;Ljava/lang/Object;Ljava/lang/Object;Ljava/lang/Object;Ljava/lang/Object;Ljava/lang/Object;Ljava/lang/Object;Ljava/lang/Object;Ljava/lang/Object;Ljava/lang/Object;Ljava/lang/Object;Ljava/lang/Object;)Lscala/Tuple15;
const #55 = Asciz	<A1:Ljava/lang/Object;A2:Ljava/lang/Object;A3:Ljava/lang/Object;A4:Ljava/lang/Object;A5:Ljava/lang/Object;A6:Ljava/lang/Object;A7:Ljava/lang/Object;A8:Ljava/lang/Object;A9:Ljava/lang/Object;A10:Ljava/lang/Object;A11:Ljava/lang/Object;A12:Ljava/lang/Object;A13:Ljava/lang/Object;A14:Ljava/lang/Object;A15:Ljava/lang/Object;>(TA1;TA2;TA3;TA4;TA5;TA6;TA7;TA8;TA9;TA10;TA11;TA12;TA13;TA14;TA15;)Lscala/Tuple15<TA1;TA2;TA3;TA4;TA5;TA6;TA7;TA8;TA9;TA10;TA11;TA12;TA13;TA14;TA15;>;;
const #56 = Asciz	(Ljava/lang/Object;Ljava/lang/Object;Ljava/lang/Object;Ljava/lang/Object;Ljava/lang/Object;Ljava/lang/Object;Ljava/lang/Object;Ljava/lang/Object;Ljava/lang/Object;Ljava/lang/Object;Ljava/lang/Object;Ljava/lang/Object;Ljava/lang/Object;Ljava/lang/Object;)Lscala/Tuple14;;
const #57 = NameAndType	#22:#56;//  Tuple:(Ljava/lang/Object;Ljava/lang/Object;Ljava/lang/Object;Ljava/lang/Object;Ljava/lang/Object;Ljava/lang/Object;Ljava/lang/Object;Ljava/lang/Object;Ljava/lang/Object;Ljava/lang/Object;Ljava/lang/Object;Ljava/lang/Object;Ljava/lang/Object;Ljava/lang/Object;)Lscala/Tuple14;
const #58 = Method	#7.#57;	//  scala/package$.Tuple:(Ljava/lang/Object;Ljava/lang/Object;Ljava/lang/Object;Ljava/lang/Object;Ljava/lang/Object;Ljava/lang/Object;Ljava/lang/Object;Ljava/lang/Object;Ljava/lang/Object;Ljava/lang/Object;Ljava/lang/Object;Ljava/lang/Object;Ljava/lang/Object;Ljava/lang/Object;)Lscala/Tuple14;
const #59 = Asciz	<A1:Ljava/lang/Object;A2:Ljava/lang/Object;A3:Ljava/lang/Object;A4:Ljava/lang/Object;A5:Ljava/lang/Object;A6:Ljava/lang/Object;A7:Ljava/lang/Object;A8:Ljava/lang/Object;A9:Ljava/lang/Object;A10:Ljava/lang/Object;A11:Ljava/lang/Object;A12:Ljava/lang/Object;A13:Ljava/lang/Object;A14:Ljava/lang/Object;>(TA1;TA2;TA3;TA4;TA5;TA6;TA7;TA8;TA9;TA10;TA11;TA12;TA13;TA14;)Lscala/Tuple14<TA1;TA2;TA3;TA4;TA5;TA6;TA7;TA8;TA9;TA10;TA11;TA12;TA13;TA14;>;;
const #60 = Asciz	(Ljava/lang/Object;Ljava/lang/Object;Ljava/lang/Object;Ljava/lang/Object;Ljava/lang/Object;Ljava/lang/Object;Ljava/lang/Object;Ljava/lang/Object;Ljava/lang/Object;Ljava/lang/Object;Ljava/lang/Object;Ljava/lang/Object;Ljava/lang/Object;)Lscala/Tuple13;;
const #61 = NameAndType	#22:#60;//  Tuple:(Ljava/lang/Object;Ljava/lang/Object;Ljava/lang/Object;Ljava/lang/Object;Ljava/lang/Object;Ljava/lang/Object;Ljava/lang/Object;Ljava/lang/Object;Ljava/lang/Object;Ljava/lang/Object;Ljava/lang/Object;Ljava/lang/Object;Ljava/lang/Object;)Lscala/Tuple13;
const #62 = Method	#7.#61;	//  scala/package$.Tuple:(Ljava/lang/Object;Ljava/lang/Object;Ljava/lang/Object;Ljava/lang/Object;Ljava/lang/Object;Ljava/lang/Object;Ljava/lang/Object;Ljava/lang/Object;Ljava/lang/Object;Ljava/lang/Object;Ljava/lang/Object;Ljava/lang/Object;Ljava/lang/Object;)Lscala/Tuple13;
const #63 = Asciz	<A1:Ljava/lang/Object;A2:Ljava/lang/Object;A3:Ljava/lang/Object;A4:Ljava/lang/Object;A5:Ljava/lang/Object;A6:Ljava/lang/Object;A7:Ljava/lang/Object;A8:Ljava/lang/Object;A9:Ljava/lang/Object;A10:Ljava/lang/Object;A11:Ljava/lang/Object;A12:Ljava/lang/Object;A13:Ljava/lang/Object;>(TA1;TA2;TA3;TA4;TA5;TA6;TA7;TA8;TA9;TA10;TA11;TA12;TA13;)Lscala/Tuple13<TA1;TA2;TA3;TA4;TA5;TA6;TA7;TA8;TA9;TA10;TA11;TA12;TA13;>;;
const #64 = Asciz	(Ljava/lang/Object;Ljava/lang/Object;Ljava/lang/Object;Ljava/lang/Object;Ljava/lang/Object;Ljava/lang/Object;Ljava/lang/Object;Ljava/lang/Object;Ljava/lang/Object;Ljava/lang/Object;Ljava/lang/Object;Ljava/lang/Object;)Lscala/Tuple12;;
const #65 = NameAndType	#22:#64;//  Tuple:(Ljava/lang/Object;Ljava/lang/Object;Ljava/lang/Object;Ljava/lang/Object;Ljava/lang/Object;Ljava/lang/Object;Ljava/lang/Object;Ljava/lang/Object;Ljava/lang/Object;Ljava/lang/Object;Ljava/lang/Object;Ljava/lang/Object;)Lscala/Tuple12;
const #66 = Method	#7.#65;	//  scala/package$.Tuple:(Ljava/lang/Object;Ljava/lang/Object;Ljava/lang/Object;Ljava/lang/Object;Ljava/lang/Object;Ljava/lang/Object;Ljava/lang/Object;Ljava/lang/Object;Ljava/lang/Object;Ljava/lang/Object;Ljava/lang/Object;Ljava/lang/Object;)Lscala/Tuple12;
const #67 = Asciz	<A1:Ljava/lang/Object;A2:Ljava/lang/Object;A3:Ljava/lang/Object;A4:Ljava/lang/Object;A5:Ljava/lang/Object;A6:Ljava/lang/Object;A7:Ljava/lang/Object;A8:Ljava/lang/Object;A9:Ljava/lang/Object;A10:Ljava/lang/Object;A11:Ljava/lang/Object;A12:Ljava/lang/Object;>(TA1;TA2;TA3;TA4;TA5;TA6;TA7;TA8;TA9;TA10;TA11;TA12;)Lscala/Tuple12<TA1;TA2;TA3;TA4;TA5;TA6;TA7;TA8;TA9;TA10;TA11;TA12;>;;
const #68 = Asciz	(Ljava/lang/Object;Ljava/lang/Object;Ljava/lang/Object;Ljava/lang/Object;Ljava/lang/Object;Ljava/lang/Object;Ljava/lang/Object;Ljava/lang/Object;Ljava/lang/Object;Ljava/lang/Object;Ljava/lang/Object;)Lscala/Tuple11;;
const #69 = NameAndType	#22:#68;//  Tuple:(Ljava/lang/Object;Ljava/lang/Object;Ljava/lang/Object;Ljava/lang/Object;Ljava/lang/Object;Ljava/lang/Object;Ljava/lang/Object;Ljava/lang/Object;Ljava/lang/Object;Ljava/lang/Object;Ljava/lang/Object;)Lscala/Tuple11;
const #70 = Method	#7.#69;	//  scala/package$.Tuple:(Ljava/lang/Object;Ljava/lang/Object;Ljava/lang/Object;Ljava/lang/Object;Ljava/lang/Object;Ljava/lang/Object;Ljava/lang/Object;Ljava/lang/Object;Ljava/lang/Object;Ljava/lang/Object;Ljava/lang/Object;)Lscala/Tuple11;
const #71 = Asciz	<A1:Ljava/lang/Object;A2:Ljava/lang/Object;A3:Ljava/lang/Object;A4:Ljava/lang/Object;A5:Ljava/lang/Object;A6:Ljava/lang/Object;A7:Ljava/lang/Object;A8:Ljava/lang/Object;A9:Ljava/lang/Object;A10:Ljava/lang/Object;A11:Ljava/lang/Object;>(TA1;TA2;TA3;TA4;TA5;TA6;TA7;TA8;TA9;TA10;TA11;)Lscala/Tuple11<TA1;TA2;TA3;TA4;TA5;TA6;TA7;TA8;TA9;TA10;TA11;>;;
const #72 = Asciz	(Ljava/lang/Object;Ljava/lang/Object;Ljava/lang/Object;Ljava/lang/Object;Ljava/lang/Object;Ljava/lang/Object;Ljava/lang/Object;Ljava/lang/Object;Ljava/lang/Object;Ljava/lang/Object;)Lscala/Tuple10;;
const #73 = NameAndType	#22:#72;//  Tuple:(Ljava/lang/Object;Ljava/lang/Object;Ljava/lang/Object;Ljava/lang/Object;Ljava/lang/Object;Ljava/lang/Object;Ljava/lang/Object;Ljava/lang/Object;Ljava/lang/Object;Ljava/lang/Object;)Lscala/Tuple10;
const #74 = Method	#7.#73;	//  scala/package$.Tuple:(Ljava/lang/Object;Ljava/lang/Object;Ljava/lang/Object;Ljava/lang/Object;Ljava/lang/Object;Ljava/lang/Object;Ljava/lang/Object;Ljava/lang/Object;Ljava/lang/Object;Ljava/lang/Object;)Lscala/Tuple10;
const #75 = Asciz	<A1:Ljava/lang/Object;A2:Ljava/lang/Object;A3:Ljava/lang/Object;A4:Ljava/lang/Object;A5:Ljava/lang/Object;A6:Ljava/lang/Object;A7:Ljava/lang/Object;A8:Ljava/lang/Object;A9:Ljava/lang/Object;A10:Ljava/lang/Object;>(TA1;TA2;TA3;TA4;TA5;TA6;TA7;TA8;TA9;TA10;)Lscala/Tuple10<TA1;TA2;TA3;TA4;TA5;TA6;TA7;TA8;TA9;TA10;>;;
const #76 = Asciz	(Ljava/lang/Object;Ljava/lang/Object;Ljava/lang/Object;Ljava/lang/Object;Ljava/lang/Object;Ljava/lang/Object;Ljava/lang/Object;Ljava/lang/Object;Ljava/lang/Object;)Lscala/Tuple9;;
const #77 = NameAndType	#22:#76;//  Tuple:(Ljava/lang/Object;Ljava/lang/Object;Ljava/lang/Object;Ljava/lang/Object;Ljava/lang/Object;Ljava/lang/Object;Ljava/lang/Object;Ljava/lang/Object;Ljava/lang/Object;)Lscala/Tuple9;
const #78 = Method	#7.#77;	//  scala/package$.Tuple:(Ljava/lang/Object;Ljava/lang/Object;Ljava/lang/Object;Ljava/lang/Object;Ljava/lang/Object;Ljava/lang/Object;Ljava/lang/Object;Ljava/lang/Object;Ljava/lang/Object;)Lscala/Tuple9;
const #79 = Asciz	<A1:Ljava/lang/Object;A2:Ljava/lang/Object;A3:Ljava/lang/Object;A4:Ljava/lang/Object;A5:Ljava/lang/Object;A6:Ljava/lang/Object;A7:Ljava/lang/Object;A8:Ljava/lang/Object;A9:Ljava/lang/Object;>(TA1;TA2;TA3;TA4;TA5;TA6;TA7;TA8;TA9;)Lscala/Tuple9<TA1;TA2;TA3;TA4;TA5;TA6;TA7;TA8;TA9;>;;
const #80 = Asciz	(Ljava/lang/Object;Ljava/lang/Object;Ljava/lang/Object;Ljava/lang/Object;Ljava/lang/Object;Ljava/lang/Object;Ljava/lang/Object;Ljava/lang/Object;)Lscala/Tuple8;;
const #81 = NameAndType	#22:#80;//  Tuple:(Ljava/lang/Object;Ljava/lang/Object;Ljava/lang/Object;Ljava/lang/Object;Ljava/lang/Object;Ljava/lang/Object;Ljava/lang/Object;Ljava/lang/Object;)Lscala/Tuple8;
const #82 = Method	#7.#81;	//  scala/package$.Tuple:(Ljava/lang/Object;Ljava/lang/Object;Ljava/lang/Object;Ljava/lang/Object;Ljava/lang/Object;Ljava/lang/Object;Ljava/lang/Object;Ljava/lang/Object;)Lscala/Tuple8;
const #83 = Asciz	<A1:Ljava/lang/Object;A2:Ljava/lang/Object;A3:Ljava/lang/Object;A4:Ljava/lang/Object;A5:Ljava/lang/Object;A6:Ljava/lang/Object;A7:Ljava/lang/Object;A8:Ljava/lang/Object;>(TA1;TA2;TA3;TA4;TA5;TA6;TA7;TA8;)Lscala/Tuple8<TA1;TA2;TA3;TA4;TA5;TA6;TA7;TA8;>;;
const #84 = Asciz	(Ljava/lang/Object;Ljava/lang/Object;Ljava/lang/Object;Ljava/lang/Object;Ljava/lang/Object;Ljava/lang/Object;Ljava/lang/Object;)Lscala/Tuple7;;
const #85 = NameAndType	#22:#84;//  Tuple:(Ljava/lang/Object;Ljava/lang/Object;Ljava/lang/Object;Ljava/lang/Object;Ljava/lang/Object;Ljava/lang/Object;Ljava/lang/Object;)Lscala/Tuple7;
const #86 = Method	#7.#85;	//  scala/package$.Tuple:(Ljava/lang/Object;Ljava/lang/Object;Ljava/lang/Object;Ljava/lang/Object;Ljava/lang/Object;Ljava/lang/Object;Ljava/lang/Object;)Lscala/Tuple7;
const #87 = Asciz	<A1:Ljava/lang/Object;A2:Ljava/lang/Object;A3:Ljava/lang/Object;A4:Ljava/lang/Object;A5:Ljava/lang/Object;A6:Ljava/lang/Object;A7:Ljava/lang/Object;>(TA1;TA2;TA3;TA4;TA5;TA6;TA7;)Lscala/Tuple7<TA1;TA2;TA3;TA4;TA5;TA6;TA7;>;;
const #88 = Asciz	(Ljava/lang/Object;Ljava/lang/Object;Ljava/lang/Object;Ljava/lang/Object;Ljava/lang/Object;Ljava/lang/Object;)Lscala/Tuple6;;
const #89 = NameAndType	#22:#88;//  Tuple:(Ljava/lang/Object;Ljava/lang/Object;Ljava/lang/Object;Ljava/lang/Object;Ljava/lang/Object;Ljava/lang/Object;)Lscala/Tuple6;
const #90 = Method	#7.#89;	//  scala/package$.Tuple:(Ljava/lang/Object;Ljava/lang/Object;Ljava/lang/Object;Ljava/lang/Object;Ljava/lang/Object;Ljava/lang/Object;)Lscala/Tuple6;
const #91 = Asciz	<A1:Ljava/lang/Object;A2:Ljava/lang/Object;A3:Ljava/lang/Object;A4:Ljava/lang/Object;A5:Ljava/lang/Object;A6:Ljava/lang/Object;>(TA1;TA2;TA3;TA4;TA5;TA6;)Lscala/Tuple6<TA1;TA2;TA3;TA4;TA5;TA6;>;;
const #92 = Asciz	(Ljava/lang/Object;Ljava/lang/Object;Ljava/lang/Object;Ljava/lang/Object;Ljava/lang/Object;)Lscala/Tuple5;;
const #93 = NameAndType	#22:#92;//  Tuple:(Ljava/lang/Object;Ljava/lang/Object;Ljava/lang/Object;Ljava/lang/Object;Ljava/lang/Object;)Lscala/Tuple5;
const #94 = Method	#7.#93;	//  scala/package$.Tuple:(Ljava/lang/Object;Ljava/lang/Object;Ljava/lang/Object;Ljava/lang/Object;Ljava/lang/Object;)Lscala/Tuple5;
const #95 = Asciz	<A1:Ljava/lang/Object;A2:Ljava/lang/Object;A3:Ljava/lang/Object;A4:Ljava/lang/Object;A5:Ljava/lang/Object;>(TA1;TA2;TA3;TA4;TA5;)Lscala/Tuple5<TA1;TA2;TA3;TA4;TA5;>;;
const #96 = Asciz	(Ljava/lang/Object;Ljava/lang/Object;Ljava/lang/Object;Ljava/lang/Object;)Lscala/Tuple4;;
const #97 = NameAndType	#22:#96;//  Tuple:(Ljava/lang/Object;Ljava/lang/Object;Ljava/lang/Object;Ljava/lang/Object;)Lscala/Tuple4;
const #98 = Method	#7.#97;	//  scala/package$.Tuple:(Ljava/lang/Object;Ljava/lang/Object;Ljava/lang/Object;Ljava/lang/Object;)Lscala/Tuple4;
const #99 = Asciz	<A1:Ljava/lang/Object;A2:Ljava/lang/Object;A3:Ljava/lang/Object;A4:Ljava/lang/Object;>(TA1;TA2;TA3;TA4;)Lscala/Tuple4<TA1;TA2;TA3;TA4;>;;
const #100 = Asciz	(Ljava/lang/Object;Ljava/lang/Object;Ljava/lang/Object;)Lscala/Tuple3;;
const #101 = NameAndType	#22:#100;//  Tuple:(Ljava/lang/Object;Ljava/lang/Object;Ljava/lang/Object;)Lscala/Tuple3;
const #102 = Method	#7.#101;	//  scala/package$.Tuple:(Ljava/lang/Object;Ljava/lang/Object;Ljava/lang/Object;)Lscala/Tuple3;
const #103 = Asciz	<A1:Ljava/lang/Object;A2:Ljava/lang/Object;A3:Ljava/lang/Object;>(TA1;TA2;TA3;)Lscala/Tuple3<TA1;TA2;TA3;>;;
const #104 = Asciz	(Ljava/lang/Object;Ljava/lang/Object;)Lscala/Tuple2;;
const #105 = NameAndType	#22:#104;//  Tuple:(Ljava/lang/Object;Ljava/lang/Object;)Lscala/Tuple2;
const #106 = Method	#7.#105;	//  scala/package$.Tuple:(Ljava/lang/Object;Ljava/lang/Object;)Lscala/Tuple2;
const #107 = Asciz	<A1:Ljava/lang/Object;A2:Ljava/lang/Object;>(TA1;TA2;)Lscala/Tuple2<TA1;TA2;>;;
const #108 = Asciz	(Ljava/lang/Object;)Lscala/Tuple1;;
const #109 = NameAndType	#22:#108;//  Tuple:(Ljava/lang/Object;)Lscala/Tuple1;
const #110 = Method	#7.#109;	//  scala/package$.Tuple:(Ljava/lang/Object;)Lscala/Tuple1;
const #111 = Asciz	<A1:Ljava/lang/Object;>(TA1;)Lscala/Tuple1<TA1;>;;
const #112 = Asciz	Ordering;
const #113 = Asciz	()Lscala/math/Ordering$;;
const #114 = NameAndType	#112:#113;//  Ordering:()Lscala/math/Ordering$;
const #115 = Method	#7.#114;	//  scala/package$.Ordering:()Lscala/math/Ordering$;
const #116 = Asciz	Ordered;
const #117 = Asciz	()Lscala/math/Ordered$;;
const #118 = NameAndType	#116:#117;//  Ordered:()Lscala/math/Ordered$;
const #119 = Method	#7.#118;	//  scala/package$.Ordered:()Lscala/math/Ordered$;
const #120 = Asciz	Numeric;
const #121 = Asciz	()Lscala/math/Numeric$;;
const #122 = NameAndType	#120:#121;//  Numeric:()Lscala/math/Numeric$;
const #123 = Method	#7.#122;	//  scala/package$.Numeric:()Lscala/math/Numeric$;
const #124 = Asciz	BigInt;
const #125 = Asciz	()Lscala/math/BigInt$;;
const #126 = NameAndType	#124:#125;//  BigInt:()Lscala/math/BigInt$;
const #127 = Method	#7.#126;	//  scala/package$.BigInt:()Lscala/math/BigInt$;
const #128 = Asciz	BigDecimal;
const #129 = Asciz	()Lscala/math/BigDecimal$;;
const #130 = NameAndType	#128:#129;//  BigDecimal:()Lscala/math/BigDecimal$;
const #131 = Method	#7.#130;	//  scala/package$.BigDecimal:()Lscala/math/BigDecimal$;
const #132 = Asciz	currentThread;
const #133 = Asciz	()Ljava/lang/Thread;;
const #134 = NameAndType	#132:#133;//  currentThread:()Ljava/lang/Thread;
const #135 = Method	#7.#134;	//  scala/package$.currentThread:()Ljava/lang/Thread;
const #136 = Asciz	$scope;
const #137 = Asciz	()Lscala/xml/TopScope$;;
const #138 = NameAndType	#136:#137;//  $scope:()Lscala/xml/TopScope$;
const #139 = Method	#7.#138;	//  scala/package$.$scope:()Lscala/xml/TopScope$;
const #140 = Asciz	Range;
const #141 = Asciz	()Lscala/collection/immutable/Range$;;
const #142 = NameAndType	#140:#141;//  Range:()Lscala/collection/immutable/Range$;
const #143 = Method	#7.#142;	//  scala/package$.Range:()Lscala/collection/immutable/Range$;
const #144 = Asciz	StringBuilder;
const #145 = Asciz	()Lscala/collection/mutable/StringBuilder$;;
const #146 = NameAndType	#144:#145;//  StringBuilder:()Lscala/collection/mutable/StringBuilder$;
const #147 = Method	#7.#146;	//  scala/package$.StringBuilder:()Lscala/collection/mutable/StringBuilder$;
const #148 = Asciz	Vector;
const #149 = Asciz	()Lscala/collection/immutable/Vector$;;
const #150 = NameAndType	#148:#149;//  Vector:()Lscala/collection/immutable/Vector$;
const #151 = Method	#7.#150;	//  scala/package$.Vector:()Lscala/collection/immutable/Vector$;
const #152 = Asciz	$hash$colon$colon;
const #153 = Asciz	()Lscala/collection/immutable/Stream$$hash$colon$colon$;;
const #154 = NameAndType	#152:#153;//  $hash$colon$colon:()Lscala/collection/immutable/Stream$$hash$colon$colon$;
const #155 = Method	#7.#154;	//  scala/package$.$hash$colon$colon:()Lscala/collection/immutable/Stream$$hash$colon$colon$;
const #156 = Asciz	Stream;
const #157 = Asciz	()Lscala/collection/immutable/Stream$;;
const #158 = NameAndType	#156:#157;//  Stream:()Lscala/collection/immutable/Stream$;
const #159 = Method	#7.#158;	//  scala/package$.Stream:()Lscala/collection/immutable/Stream$;
const #160 = Asciz	$colon$colon;
const #161 = Asciz	()Lscala/collection/immutable/$colon$colon$;;
const #162 = NameAndType	#160:#161;//  $colon$colon:()Lscala/collection/immutable/$colon$colon$;
const #163 = Method	#7.#162;	//  scala/package$.$colon$colon:()Lscala/collection/immutable/$colon$colon$;
const #164 = Asciz	Nil;
const #165 = Asciz	()Lscala/collection/immutable/Nil$;;
const #166 = NameAndType	#164:#165;//  Nil:()Lscala/collection/immutable/Nil$;
const #167 = Method	#7.#166;	//  scala/package$.Nil:()Lscala/collection/immutable/Nil$;
const #168 = Asciz	List;
const #169 = Asciz	()Lscala/collection/immutable/List$;;
const #170 = NameAndType	#168:#169;//  List:()Lscala/collection/immutable/List$;
const #171 = Method	#7.#170;	//  scala/package$.List:()Lscala/collection/immutable/List$;
const #172 = Asciz	Iterator;
const #173 = Asciz	()Lscala/collection/Iterator$;;
const #174 = NameAndType	#172:#173;//  Iterator:()Lscala/collection/Iterator$;
const #175 = Method	#7.#174;	//  scala/package$.Iterator:()Lscala/collection/Iterator$;
const #176 = Asciz	IndexedSeq;
const #177 = NameAndType	#176:#4;//  IndexedSeq:()Lscala/collection/IndexedSeq$;
const #178 = Method	#7.#177;	//  scala/package$.IndexedSeq:()Lscala/collection/IndexedSeq$;
const #179 = Asciz	Seq;
const #180 = NameAndType	#179:#15;//  Seq:()Lscala/collection/Seq$;
const #181 = Method	#7.#180;	//  scala/package$.Seq:()Lscala/collection/Seq$;
const #182 = Asciz	Iterable;
const #183 = NameAndType	#182:#19;//  Iterable:()Lscala/collection/Iterable$;
const #184 = Method	#7.#183;	//  scala/package$.Iterable:()Lscala/collection/Iterable$;
const #185 = Asciz	Traversable;
const #186 = Asciz	()Lscala/collection/Traversable$;;
const #187 = NameAndType	#185:#186;//  Traversable:()Lscala/collection/Traversable$;
const #188 = Method	#7.#187;	//  scala/package$.Traversable:()Lscala/collection/Traversable$;
const #189 = Asciz	ScalaSig;
const #190 = Asciz	scala/package;
const #191 = class	#190;	//  scala/package
const #192 = Asciz	java/lang/Object;
const #193 = class	#192;	//  java/lang/Object

{
public static final scala.collection.IndexedSeq$ RandomAccessSeq();
  Code:
   Stack=1, Locals=0, Args_size=0
   0:	getstatic	#11; //Field scala/package$.MODULE$:Lscala/package$;
   3:	invokevirtual	#13; //Method scala/package$.RandomAccessSeq:()Lscala/collection/IndexedSeq$;
   6:	areturn

public static final scala.collection.Seq$ Sequence();
  Code:
   Stack=1, Locals=0, Args_size=0
   0:	getstatic	#11; //Field scala/package$.MODULE$:Lscala/package$;
   3:	invokevirtual	#17; //Method scala/package$.Sequence:()Lscala/collection/Seq$;
   6:	areturn

public static final scala.collection.Iterable$ Collection();
  Code:
   Stack=1, Locals=0, Args_size=0
   0:	getstatic	#11; //Field scala/package$.MODULE$:Lscala/package$;
   3:	invokevirtual	#21; //Method scala/package$.Collection:()Lscala/collection/Iterable$;
   6:	areturn

public static final scala.Tuple22 Tuple(java.lang.Object, java.lang.Object, java.lang.Object, java.lang.Object, java.lang.Object, java.lang.Object, java.lang.Object, java.lang.Object, java.lang.Object, java.lang.Object, java.lang.Object, java.lang.Object, java.lang.Object, java.lang.Object, java.lang.Object, java.lang.Object, java.lang.Object, java.lang.Object, java.lang.Object, java.lang.Object, java.lang.Object, java.lang.Object);
  Code:
   Stack=23, Locals=22, Args_size=22
   0:	getstatic	#11; //Field scala/package$.MODULE$:Lscala/package$;
   3:	aload_0
   4:	aload_1
   5:	aload_2
   6:	aload_3
   7:	aload	4
   9:	aload	5
   11:	aload	6
   13:	aload	7
   15:	aload	8
   17:	aload	9
   19:	aload	10
   21:	aload	11
   23:	aload	12
   25:	aload	13
   27:	aload	14
   29:	aload	15
   31:	aload	16
   33:	aload	17
   35:	aload	18
   37:	aload	19
   39:	aload	20
   41:	aload	21
   43:	invokevirtual	#25; //Method scala/package$.Tuple:(Ljava/lang/Object;Ljava/lang/Object;Ljava/lang/Object;Ljava/lang/Object;Ljava/lang/Object;Ljava/lang/Object;Ljava/lang/Object;Ljava/lang/Object;Ljava/lang/Object;Ljava/lang/Object;Ljava/lang/Object;Ljava/lang/Object;Ljava/lang/Object;Ljava/lang/Object;Ljava/lang/Object;Ljava/lang/Object;Ljava/lang/Object;Ljava/lang/Object;Ljava/lang/Object;Ljava/lang/Object;Ljava/lang/Object;Ljava/lang/Object;)Lscala/Tuple22;
   46:	areturn
  Signature: length = 0x2
   00 1A 

public static final scala.Tuple21 Tuple(java.lang.Object, java.lang.Object, java.lang.Object, java.lang.Object, java.lang.Object, java.lang.Object, java.lang.Object, java.lang.Object, java.lang.Object, java.lang.Object, java.lang.Object, java.lang.Object, java.lang.Object, java.lang.Object, java.lang.Object, java.lang.Object, java.lang.Object, java.lang.Object, java.lang.Object, java.lang.Object, java.lang.Object);
  Code:
   Stack=22, Locals=21, Args_size=21
   0:	getstatic	#11; //Field scala/package$.MODULE$:Lscala/package$;
   3:	aload_0
   4:	aload_1
   5:	aload_2
   6:	aload_3
   7:	aload	4
   9:	aload	5
   11:	aload	6
   13:	aload	7
   15:	aload	8
   17:	aload	9
   19:	aload	10
   21:	aload	11
   23:	aload	12
   25:	aload	13
   27:	aload	14
   29:	aload	15
   31:	aload	16
   33:	aload	17
   35:	aload	18
   37:	aload	19
   39:	aload	20
   41:	invokevirtual	#30; //Method scala/package$.Tuple:(Ljava/lang/Object;Ljava/lang/Object;Ljava/lang/Object;Ljava/lang/Object;Ljava/lang/Object;Ljava/lang/Object;Ljava/lang/Object;Ljava/lang/Object;Ljava/lang/Object;Ljava/lang/Object;Ljava/lang/Object;Ljava/lang/Object;Ljava/lang/Object;Ljava/lang/Object;Ljava/lang/Object;Ljava/lang/Object;Ljava/lang/Object;Ljava/lang/Object;Ljava/lang/Object;Ljava/lang/Object;Ljava/lang/Object;)Lscala/Tuple21;
   44:	areturn
  Signature: length = 0x2
   00 1F 

public static final scala.Tuple20 Tuple(java.lang.Object, java.lang.Object, java.lang.Object, java.lang.Object, java.lang.Object, java.lang.Object, java.lang.Object, java.lang.Object, java.lang.Object, java.lang.Object, java.lang.Object, java.lang.Object, java.lang.Object, java.lang.Object, java.lang.Object, java.lang.Object, java.lang.Object, java.lang.Object, java.lang.Object, java.lang.Object);
  Code:
   Stack=21, Locals=20, Args_size=20
   0:	getstatic	#11; //Field scala/package$.MODULE$:Lscala/package$;
   3:	aload_0
   4:	aload_1
   5:	aload_2
   6:	aload_3
   7:	aload	4
   9:	aload	5
   11:	aload	6
   13:	aload	7
   15:	aload	8
   17:	aload	9
   19:	aload	10
   21:	aload	11
   23:	aload	12
   25:	aload	13
   27:	aload	14
   29:	aload	15
   31:	aload	16
   33:	aload	17
   35:	aload	18
   37:	aload	19
   39:	invokevirtual	#34; //Method scala/package$.Tuple:(Ljava/lang/Object;Ljava/lang/Object;Ljava/lang/Object;Ljava/lang/Object;Ljava/lang/Object;Ljava/lang/Object;Ljava/lang/Object;Ljava/lang/Object;Ljava/lang/Object;Ljava/lang/Object;Ljava/lang/Object;Ljava/lang/Object;Ljava/lang/Object;Ljava/lang/Object;Ljava/lang/Object;Ljava/lang/Object;Ljava/lang/Object;Ljava/lang/Object;Ljava/lang/Object;Ljava/lang/Object;)Lscala/Tuple20;
   42:	areturn
  Signature: length = 0x2
   00 23 

public static final scala.Tuple19 Tuple(java.lang.Object, java.lang.Object, java.lang.Object, java.lang.Object, java.lang.Object, java.lang.Object, java.lang.Object, java.lang.Object, java.lang.Object, java.lang.Object, java.lang.Object, java.lang.Object, java.lang.Object, java.lang.Object, java.lang.Object, java.lang.Object, java.lang.Object, java.lang.Object, java.lang.Object);
  Code:
   Stack=20, Locals=19, Args_size=19
   0:	getstatic	#11; //Field scala/package$.MODULE$:Lscala/package$;
   3:	aload_0
   4:	aload_1
   5:	aload_2
   6:	aload_3
   7:	aload	4
   9:	aload	5
   11:	aload	6
   13:	aload	7
   15:	aload	8
   17:	aload	9
   19:	aload	10
   21:	aload	11
   23:	aload	12
   25:	aload	13
   27:	aload	14
   29:	aload	15
   31:	aload	16
   33:	aload	17
   35:	aload	18
   37:	invokevirtual	#38; //Method scala/package$.Tuple:(Ljava/lang/Object;Ljava/lang/Object;Ljava/lang/Object;Ljava/lang/Object;Ljava/lang/Object;Ljava/lang/Object;Ljava/lang/Object;Ljava/lang/Object;Ljava/lang/Object;Ljava/lang/Object;Ljava/lang/Object;Ljava/lang/Object;Ljava/lang/Object;Ljava/lang/Object;Ljava/lang/Object;Ljava/lang/Object;Ljava/lang/Object;Ljava/lang/Object;Ljava/lang/Object;)Lscala/Tuple19;
   40:	areturn
  Signature: length = 0x2
   00 27 

public static final scala.Tuple18 Tuple(java.lang.Object, java.lang.Object, java.lang.Object, java.lang.Object, java.lang.Object, java.lang.Object, java.lang.Object, java.lang.Object, java.lang.Object, java.lang.Object, java.lang.Object, java.lang.Object, java.lang.Object, java.lang.Object, java.lang.Object, java.lang.Object, java.lang.Object, java.lang.Object);
  Code:
   Stack=19, Locals=18, Args_size=18
   0:	getstatic	#11; //Field scala/package$.MODULE$:Lscala/package$;
   3:	aload_0
   4:	aload_1
   5:	aload_2
   6:	aload_3
   7:	aload	4
   9:	aload	5
   11:	aload	6
   13:	aload	7
   15:	aload	8
   17:	aload	9
   19:	aload	10
   21:	aload	11
   23:	aload	12
   25:	aload	13
   27:	aload	14
   29:	aload	15
   31:	aload	16
   33:	aload	17
   35:	invokevirtual	#42; //Method scala/package$.Tuple:(Ljava/lang/Object;Ljava/lang/Object;Ljava/lang/Object;Ljava/lang/Object;Ljava/lang/Object;Ljava/lang/Object;Ljava/lang/Object;Ljava/lang/Object;Ljava/lang/Object;Ljava/lang/Object;Ljava/lang/Object;Ljava/lang/Object;Ljava/lang/Object;Ljava/lang/Object;Ljava/lang/Object;Ljava/lang/Object;Ljava/lang/Object;Ljava/lang/Object;)Lscala/Tuple18;
   38:	areturn
  Signature: length = 0x2
   00 2B 

public static final scala.Tuple17 Tuple(java.lang.Object, java.lang.Object, java.lang.Object, java.lang.Object, java.lang.Object, java.lang.Object, java.lang.Object, java.lang.Object, java.lang.Object, java.lang.Object, java.lang.Object, java.lang.Object, java.lang.Object, java.lang.Object, java.lang.Object, java.lang.Object, java.lang.Object);
  Code:
   Stack=18, Locals=17, Args_size=17
   0:	getstatic	#11; //Field scala/package$.MODULE$:Lscala/package$;
   3:	aload_0
   4:	aload_1
   5:	aload_2
   6:	aload_3
   7:	aload	4
   9:	aload	5
   11:	aload	6
   13:	aload	7
   15:	aload	8
   17:	aload	9
   19:	aload	10
   21:	aload	11
   23:	aload	12
   25:	aload	13
   27:	aload	14
   29:	aload	15
   31:	aload	16
   33:	invokevirtual	#46; //Method scala/package$.Tuple:(Ljava/lang/Object;Ljava/lang/Object;Ljava/lang/Object;Ljava/lang/Object;Ljava/lang/Object;Ljava/lang/Object;Ljava/lang/Object;Ljava/lang/Object;Ljava/lang/Object;Ljava/lang/Object;Ljava/lang/Object;Ljava/lang/Object;Ljava/lang/Object;Ljava/lang/Object;Ljava/lang/Object;Ljava/lang/Object;Ljava/lang/Object;)Lscala/Tuple17;
   36:	areturn
  Signature: length = 0x2
   00 2F 

public static final scala.Tuple16 Tuple(java.lang.Object, java.lang.Object, java.lang.Object, java.lang.Object, java.lang.Object, java.lang.Object, java.lang.Object, java.lang.Object, java.lang.Object, java.lang.Object, java.lang.Object, java.lang.Object, java.lang.Object, java.lang.Object, java.lang.Object, java.lang.Object);
  Code:
   Stack=17, Locals=16, Args_size=16
   0:	getstatic	#11; //Field scala/package$.MODULE$:Lscala/package$;
   3:	aload_0
   4:	aload_1
   5:	aload_2
   6:	aload_3
   7:	aload	4
   9:	aload	5
   11:	aload	6
   13:	aload	7
   15:	aload	8
   17:	aload	9
   19:	aload	10
   21:	aload	11
   23:	aload	12
   25:	aload	13
   27:	aload	14
   29:	aload	15
   31:	invokevirtual	#50; //Method scala/package$.Tuple:(Ljava/lang/Object;Ljava/lang/Object;Ljava/lang/Object;Ljava/lang/Object;Ljava/lang/Object;Ljava/lang/Object;Ljava/lang/Object;Ljava/lang/Object;Ljava/lang/Object;Ljava/lang/Object;Ljava/lang/Object;Ljava/lang/Object;Ljava/lang/Object;Ljava/lang/Object;Ljava/lang/Object;Ljava/lang/Object;)Lscala/Tuple16;
   34:	areturn
  Signature: length = 0x2
   00 33 

public static final scala.Tuple15 Tuple(java.lang.Object, java.lang.Object, java.lang.Object, java.lang.Object, java.lang.Object, java.lang.Object, java.lang.Object, java.lang.Object, java.lang.Object, java.lang.Object, java.lang.Object, java.lang.Object, java.lang.Object, java.lang.Object, java.lang.Object);
  Code:
   Stack=16, Locals=15, Args_size=15
   0:	getstatic	#11; //Field scala/package$.MODULE$:Lscala/package$;
   3:	aload_0
   4:	aload_1
   5:	aload_2
   6:	aload_3
   7:	aload	4
   9:	aload	5
   11:	aload	6
   13:	aload	7
   15:	aload	8
   17:	aload	9
   19:	aload	10
   21:	aload	11
   23:	aload	12
   25:	aload	13
   27:	aload	14
   29:	invokevirtual	#54; //Method scala/package$.Tuple:(Ljava/lang/Object;Ljava/lang/Object;Ljava/lang/Object;Ljava/lang/Object;Ljava/lang/Object;Ljava/lang/Object;Ljava/lang/Object;Ljava/lang/Object;Ljava/lang/Object;Ljava/lang/Object;Ljava/lang/Object;Ljava/lang/Object;Ljava/lang/Object;Ljava/lang/Object;Ljava/lang/Object;)Lscala/Tuple15;
   32:	areturn
  Signature: length = 0x2
   00 37 

public static final scala.Tuple14 Tuple(java.lang.Object, java.lang.Object, java.lang.Object, java.lang.Object, java.lang.Object, java.lang.Object, java.lang.Object, java.lang.Object, java.lang.Object, java.lang.Object, java.lang.Object, java.lang.Object, java.lang.Object, java.lang.Object);
  Code:
   Stack=15, Locals=14, Args_size=14
   0:	getstatic	#11; //Field scala/package$.MODULE$:Lscala/package$;
   3:	aload_0
   4:	aload_1
   5:	aload_2
   6:	aload_3
   7:	aload	4
   9:	aload	5
   11:	aload	6
   13:	aload	7
   15:	aload	8
   17:	aload	9
   19:	aload	10
   21:	aload	11
   23:	aload	12
   25:	aload	13
   27:	invokevirtual	#58; //Method scala/package$.Tuple:(Ljava/lang/Object;Ljava/lang/Object;Ljava/lang/Object;Ljava/lang/Object;Ljava/lang/Object;Ljava/lang/Object;Ljava/lang/Object;Ljava/lang/Object;Ljava/lang/Object;Ljava/lang/Object;Ljava/lang/Object;Ljava/lang/Object;Ljava/lang/Object;Ljava/lang/Object;)Lscala/Tuple14;
   30:	areturn
  Signature: length = 0x2
   00 3B 

public static final scala.Tuple13 Tuple(java.lang.Object, java.lang.Object, java.lang.Object, java.lang.Object, java.lang.Object, java.lang.Object, java.lang.Object, java.lang.Object, java.lang.Object, java.lang.Object, java.lang.Object, java.lang.Object, java.lang.Object);
  Code:
   Stack=14, Locals=13, Args_size=13
   0:	getstatic	#11; //Field scala/package$.MODULE$:Lscala/package$;
   3:	aload_0
   4:	aload_1
   5:	aload_2
   6:	aload_3
   7:	aload	4
   9:	aload	5
   11:	aload	6
   13:	aload	7
   15:	aload	8
   17:	aload	9
   19:	aload	10
   21:	aload	11
   23:	aload	12
   25:	invokevirtual	#62; //Method scala/package$.Tuple:(Ljava/lang/Object;Ljava/lang/Object;Ljava/lang/Object;Ljava/lang/Object;Ljava/lang/Object;Ljava/lang/Object;Ljava/lang/Object;Ljava/lang/Object;Ljava/lang/Object;Ljava/lang/Object;Ljava/lang/Object;Ljava/lang/Object;Ljava/lang/Object;)Lscala/Tuple13;
   28:	areturn
  Signature: length = 0x2
   00 3F 

public static final scala.Tuple12 Tuple(java.lang.Object, java.lang.Object, java.lang.Object, java.lang.Object, java.lang.Object, java.lang.Object, java.lang.Object, java.lang.Object, java.lang.Object, java.lang.Object, java.lang.Object, java.lang.Object);
  Code:
   Stack=13, Locals=12, Args_size=12
   0:	getstatic	#11; //Field scala/package$.MODULE$:Lscala/package$;
   3:	aload_0
   4:	aload_1
   5:	aload_2
   6:	aload_3
   7:	aload	4
   9:	aload	5
   11:	aload	6
   13:	aload	7
   15:	aload	8
   17:	aload	9
   19:	aload	10
   21:	aload	11
   23:	invokevirtual	#66; //Method scala/package$.Tuple:(Ljava/lang/Object;Ljava/lang/Object;Ljava/lang/Object;Ljava/lang/Object;Ljava/lang/Object;Ljava/lang/Object;Ljava/lang/Object;Ljava/lang/Object;Ljava/lang/Object;Ljava/lang/Object;Ljava/lang/Object;Ljava/lang/Object;)Lscala/Tuple12;
   26:	areturn
  Signature: length = 0x2
   00 43 

public static final scala.Tuple11 Tuple(java.lang.Object, java.lang.Object, java.lang.Object, java.lang.Object, java.lang.Object, java.lang.Object, java.lang.Object, java.lang.Object, java.lang.Object, java.lang.Object, java.lang.Object);
  Code:
   Stack=12, Locals=11, Args_size=11
   0:	getstatic	#11; //Field scala/package$.MODULE$:Lscala/package$;
   3:	aload_0
   4:	aload_1
   5:	aload_2
   6:	aload_3
   7:	aload	4
   9:	aload	5
   11:	aload	6
   13:	aload	7
   15:	aload	8
   17:	aload	9
   19:	aload	10
   21:	invokevirtual	#70; //Method scala/package$.Tuple:(Ljava/lang/Object;Ljava/lang/Object;Ljava/lang/Object;Ljava/lang/Object;Ljava/lang/Object;Ljava/lang/Object;Ljava/lang/Object;Ljava/lang/Object;Ljava/lang/Object;Ljava/lang/Object;Ljava/lang/Object;)Lscala/Tuple11;
   24:	areturn
  Signature: length = 0x2
   00 47 

public static final scala.Tuple10 Tuple(java.lang.Object, java.lang.Object, java.lang.Object, java.lang.Object, java.lang.Object, java.lang.Object, java.lang.Object, java.lang.Object, java.lang.Object, java.lang.Object);
  Code:
   Stack=11, Locals=10, Args_size=10
   0:	getstatic	#11; //Field scala/package$.MODULE$:Lscala/package$;
   3:	aload_0
   4:	aload_1
   5:	aload_2
   6:	aload_3
   7:	aload	4
   9:	aload	5
   11:	aload	6
   13:	aload	7
   15:	aload	8
   17:	aload	9
   19:	invokevirtual	#74; //Method scala/package$.Tuple:(Ljava/lang/Object;Ljava/lang/Object;Ljava/lang/Object;Ljava/lang/Object;Ljava/lang/Object;Ljava/lang/Object;Ljava/lang/Object;Ljava/lang/Object;Ljava/lang/Object;Ljava/lang/Object;)Lscala/Tuple10;
   22:	areturn
  Signature: length = 0x2
   00 4B 

public static final scala.Tuple9 Tuple(java.lang.Object, java.lang.Object, java.lang.Object, java.lang.Object, java.lang.Object, java.lang.Object, java.lang.Object, java.lang.Object, java.lang.Object);
  Code:
   Stack=10, Locals=9, Args_size=9
   0:	getstatic	#11; //Field scala/package$.MODULE$:Lscala/package$;
   3:	aload_0
   4:	aload_1
   5:	aload_2
   6:	aload_3
   7:	aload	4
   9:	aload	5
   11:	aload	6
   13:	aload	7
   15:	aload	8
   17:	invokevirtual	#78; //Method scala/package$.Tuple:(Ljava/lang/Object;Ljava/lang/Object;Ljava/lang/Object;Ljava/lang/Object;Ljava/lang/Object;Ljava/lang/Object;Ljava/lang/Object;Ljava/lang/Object;Ljava/lang/Object;)Lscala/Tuple9;
   20:	areturn
  Signature: length = 0x2
   00 4F 

public static final scala.Tuple8 Tuple(java.lang.Object, java.lang.Object, java.lang.Object, java.lang.Object, java.lang.Object, java.lang.Object, java.lang.Object, java.lang.Object);
  Code:
   Stack=9, Locals=8, Args_size=8
   0:	getstatic	#11; //Field scala/package$.MODULE$:Lscala/package$;
   3:	aload_0
   4:	aload_1
   5:	aload_2
   6:	aload_3
   7:	aload	4
   9:	aload	5
   11:	aload	6
   13:	aload	7
   15:	invokevirtual	#82; //Method scala/package$.Tuple:(Ljava/lang/Object;Ljava/lang/Object;Ljava/lang/Object;Ljava/lang/Object;Ljava/lang/Object;Ljava/lang/Object;Ljava/lang/Object;Ljava/lang/Object;)Lscala/Tuple8;
   18:	areturn
  Signature: length = 0x2
   00 53 

public static final scala.Tuple7 Tuple(java.lang.Object, java.lang.Object, java.lang.Object, java.lang.Object, java.lang.Object, java.lang.Object, java.lang.Object);
  Code:
   Stack=8, Locals=7, Args_size=7
   0:	getstatic	#11; //Field scala/package$.MODULE$:Lscala/package$;
   3:	aload_0
   4:	aload_1
   5:	aload_2
   6:	aload_3
   7:	aload	4
   9:	aload	5
   11:	aload	6
   13:	invokevirtual	#86; //Method scala/package$.Tuple:(Ljava/lang/Object;Ljava/lang/Object;Ljava/lang/Object;Ljava/lang/Object;Ljava/lang/Object;Ljava/lang/Object;Ljava/lang/Object;)Lscala/Tuple7;
   16:	areturn
  Signature: length = 0x2
   00 57 

public static final scala.Tuple6 Tuple(java.lang.Object, java.lang.Object, java.lang.Object, java.lang.Object, java.lang.Object, java.lang.Object);
  Code:
   Stack=7, Locals=6, Args_size=6
   0:	getstatic	#11; //Field scala/package$.MODULE$:Lscala/package$;
   3:	aload_0
   4:	aload_1
   5:	aload_2
   6:	aload_3
   7:	aload	4
   9:	aload	5
   11:	invokevirtual	#90; //Method scala/package$.Tuple:(Ljava/lang/Object;Ljava/lang/Object;Ljava/lang/Object;Ljava/lang/Object;Ljava/lang/Object;Ljava/lang/Object;)Lscala/Tuple6;
   14:	areturn
  Signature: length = 0x2
   00 5B 

public static final scala.Tuple5 Tuple(java.lang.Object, java.lang.Object, java.lang.Object, java.lang.Object, java.lang.Object);
  Code:
   Stack=6, Locals=5, Args_size=5
   0:	getstatic	#11; //Field scala/package$.MODULE$:Lscala/package$;
   3:	aload_0
   4:	aload_1
   5:	aload_2
   6:	aload_3
   7:	aload	4
   9:	invokevirtual	#94; //Method scala/package$.Tuple:(Ljava/lang/Object;Ljava/lang/Object;Ljava/lang/Object;Ljava/lang/Object;Ljava/lang/Object;)Lscala/Tuple5;
   12:	areturn
  Signature: length = 0x2
   00 5F 

public static final scala.Tuple4 Tuple(java.lang.Object, java.lang.Object, java.lang.Object, java.lang.Object);
  Code:
   Stack=5, Locals=4, Args_size=4
   0:	getstatic	#11; //Field scala/package$.MODULE$:Lscala/package$;
   3:	aload_0
   4:	aload_1
   5:	aload_2
   6:	aload_3
   7:	invokevirtual	#98; //Method scala/package$.Tuple:(Ljava/lang/Object;Ljava/lang/Object;Ljava/lang/Object;Ljava/lang/Object;)Lscala/Tuple4;
   10:	areturn
  Signature: length = 0x2
   00 63 

public static final scala.Tuple3 Tuple(java.lang.Object, java.lang.Object, java.lang.Object);
  Code:
   Stack=4, Locals=3, Args_size=3
   0:	getstatic	#11; //Field scala/package$.MODULE$:Lscala/package$;
   3:	aload_0
   4:	aload_1
   5:	aload_2
   6:	invokevirtual	#102; //Method scala/package$.Tuple:(Ljava/lang/Object;Ljava/lang/Object;Ljava/lang/Object;)Lscala/Tuple3;
   9:	areturn
  Signature: length = 0x2
   00 67 

public static final scala.Tuple2 Tuple(java.lang.Object, java.lang.Object);
  Code:
   Stack=3, Locals=2, Args_size=2
   0:	getstatic	#11; //Field scala/package$.MODULE$:Lscala/package$;
   3:	aload_0
   4:	aload_1
   5:	invokevirtual	#106; //Method scala/package$.Tuple:(Ljava/lang/Object;Ljava/lang/Object;)Lscala/Tuple2;
   8:	areturn
  Signature: length = 0x2
   00 6B 

public static final scala.Tuple1 Tuple(java.lang.Object);
  Code:
   Stack=2, Locals=1, Args_size=1
   0:	getstatic	#11; //Field scala/package$.MODULE$:Lscala/package$;
   3:	aload_0
   4:	invokevirtual	#110; //Method scala/package$.Tuple:(Ljava/lang/Object;)Lscala/Tuple1;
   7:	areturn
  Signature: length = 0x2
   00 6F 

public static final scala.math.Ordering$ Ordering();
  Code:
   Stack=1, Locals=0, Args_size=0
   0:	getstatic	#11; //Field scala/package$.MODULE$:Lscala/package$;
   3:	invokevirtual	#115; //Method scala/package$.Ordering:()Lscala/math/Ordering$;
   6:	areturn

public static final scala.math.Ordered$ Ordered();
  Code:
   Stack=1, Locals=0, Args_size=0
   0:	getstatic	#11; //Field scala/package$.MODULE$:Lscala/package$;
   3:	invokevirtual	#119; //Method scala/package$.Ordered:()Lscala/math/Ordered$;
   6:	areturn

public static final scala.math.Numeric$ Numeric();
  Code:
   Stack=1, Locals=0, Args_size=0
   0:	getstatic	#11; //Field scala/package$.MODULE$:Lscala/package$;
   3:	invokevirtual	#123; //Method scala/package$.Numeric:()Lscala/math/Numeric$;
   6:	areturn

public static final scala.math.BigInt$ BigInt();
  Code:
   Stack=1, Locals=0, Args_size=0
   0:	getstatic	#11; //Field scala/package$.MODULE$:Lscala/package$;
   3:	invokevirtual	#127; //Method scala/package$.BigInt:()Lscala/math/BigInt$;
   6:	areturn

public static final scala.math.BigDecimal$ BigDecimal();
  Code:
   Stack=1, Locals=0, Args_size=0
   0:	getstatic	#11; //Field scala/package$.MODULE$:Lscala/package$;
   3:	invokevirtual	#131; //Method scala/package$.BigDecimal:()Lscala/math/BigDecimal$;
   6:	areturn

public static final java.lang.Thread currentThread();
  Code:
   Stack=1, Locals=0, Args_size=0
   0:	getstatic	#11; //Field scala/package$.MODULE$:Lscala/package$;
   3:	invokevirtual	#135; //Method scala/package$.currentThread:()Ljava/lang/Thread;
   6:	areturn

public static final scala.xml.TopScope$ $scope();
  Code:
   Stack=1, Locals=0, Args_size=0
   0:	getstatic	#11; //Field scala/package$.MODULE$:Lscala/package$;
   3:	invokevirtual	#139; //Method scala/package$.$scope:()Lscala/xml/TopScope$;
   6:	areturn

public static final scala.collection.immutable.Range$ Range();
  Code:
   Stack=1, Locals=0, Args_size=0
   0:	getstatic	#11; //Field scala/package$.MODULE$:Lscala/package$;
   3:	invokevirtual	#143; //Method scala/package$.Range:()Lscala/collection/immutable/Range$;
   6:	areturn

public static final scala.collection.mutable.StringBuilder$ StringBuilder();
  Code:
   Stack=1, Locals=0, Args_size=0
   0:	getstatic	#11; //Field scala/package$.MODULE$:Lscala/package$;
   3:	invokevirtual	#147; //Method scala/package$.StringBuilder:()Lscala/collection/mutable/StringBuilder$;
   6:	areturn

public static final scala.collection.immutable.Vector$ Vector();
  Code:
   Stack=1, Locals=0, Args_size=0
   0:	getstatic	#11; //Field scala/package$.MODULE$:Lscala/package$;
   3:	invokevirtual	#151; //Method scala/package$.Vector:()Lscala/collection/immutable/Vector$;
   6:	areturn

public static final scala.collection.immutable.Stream$$hash$colon$colon$ $hash$colon$colon();
  Code:
   Stack=1, Locals=0, Args_size=0
   0:	getstatic	#11; //Field scala/package$.MODULE$:Lscala/package$;
   3:	invokevirtual	#155; //Method scala/package$.$hash$colon$colon:()Lscala/collection/immutable/Stream$$hash$colon$colon$;
   6:	areturn

public static final scala.collection.immutable.Stream$ Stream();
  Code:
   Stack=1, Locals=0, Args_size=0
   0:	getstatic	#11; //Field scala/package$.MODULE$:Lscala/package$;
   3:	invokevirtual	#159; //Method scala/package$.Stream:()Lscala/collection/immutable/Stream$;
   6:	areturn

public static final scala.collection.immutable.$colon$colon$ $colon$colon();
  Code:
   Stack=1, Locals=0, Args_size=0
   0:	getstatic	#11; //Field scala/package$.MODULE$:Lscala/package$;
   3:	invokevirtual	#163; //Method scala/package$.$colon$colon:()Lscala/collection/immutable/$colon$colon$;
   6:	areturn

public static final scala.collection.immutable.Nil$ Nil();
  Code:
   Stack=1, Locals=0, Args_size=0
   0:	getstatic	#11; //Field scala/package$.MODULE$:Lscala/package$;
   3:	invokevirtual	#167; //Method scala/package$.Nil:()Lscala/collection/immutable/Nil$;
   6:	areturn

public static final scala.collection.immutable.List$ List();
  Code:
   Stack=1, Locals=0, Args_size=0
   0:	getstatic	#11; //Field scala/package$.MODULE$:Lscala/package$;
   3:	invokevirtual	#171; //Method scala/package$.List:()Lscala/collection/immutable/List$;
   6:	areturn

public static final scala.collection.Iterator$ Iterator();
  Code:
   Stack=1, Locals=0, Args_size=0
   0:	getstatic	#11; //Field scala/package$.MODULE$:Lscala/package$;
   3:	invokevirtual	#175; //Method scala/package$.Iterator:()Lscala/collection/Iterator$;
   6:	areturn

public static final scala.collection.IndexedSeq$ IndexedSeq();
  Code:
   Stack=1, Locals=0, Args_size=0
   0:	getstatic	#11; //Field scala/package$.MODULE$:Lscala/package$;
   3:	invokevirtual	#178; //Method scala/package$.IndexedSeq:()Lscala/collection/IndexedSeq$;
   6:	areturn

public static final scala.collection.Seq$ Seq();
  Code:
   Stack=1, Locals=0, Args_size=0
   0:	getstatic	#11; //Field scala/package$.MODULE$:Lscala/package$;
   3:	invokevirtual	#181; //Method scala/package$.Seq:()Lscala/collection/Seq$;
   6:	areturn

public static final scala.collection.Iterable$ Iterable();
  Code:
   Stack=1, Locals=0, Args_size=0
   0:	getstatic	#11; //Field scala/package$.MODULE$:Lscala/package$;
   3:	invokevirtual	#184; //Method scala/package$.Iterable:()Lscala/collection/Iterable$;
   6:	areturn

public static final scala.collection.Traversable$ Traversable();
  Code:
   Stack=1, Locals=0, Args_size=0
   0:	getstatic	#11; //Field scala/package$.MODULE$:Lscala/package$;
   3:	invokevirtual	#188; //Method scala/package$.Traversable:()Lscala/collection/Traversable$;
   6:	areturn

}

