Compiled from "package.scala"
public final class scala.package$ extends java.lang.Object implements scala.ScalaObject
  SourceFile: "package.scala"
  Scala: length = 0x
   
  minor version: 0
  major version: 49
  Constant pool:
const #1 = Asciz	SourceFile;
const #2 = Asciz	package.scala;
const #3 = Asciz	Scala;
const #4 = Asciz	MODULE$;
const #5 = Asciz	Lscala/package$;;
const #6 = Asciz	<clinit>;
const #7 = Asciz	()V;
const #8 = Asciz	Code;
const #9 = Asciz	scala/package$;
const #10 = class	#9;	//  scala/package$
const #11 = Asciz	<init>;
const #12 = NameAndType	#11:#7;//  "<init>":()V
const #13 = Method	#10.#12;	//  scala/package$."<init>":()V
const #14 = Asciz	RandomAccessSeq;
const #15 = Asciz	Lscala/collection/IndexedSeq$;;
const #16 = Asciz	Sequence;
const #17 = Asciz	Lscala/collection/Seq$;;
const #18 = Asciz	Collection;
const #19 = Asciz	Lscala/collection/Iterable$;;
const #20 = Asciz	Ordering;
const #21 = Asciz	Lscala/math/Ordering$;;
const #22 = Asciz	Ordered;
const #23 = Asciz	Lscala/math/Ordered$;;
const #24 = Asciz	Numeric;
const #25 = Asciz	Lscala/math/Numeric$;;
const #26 = Asciz	BigInt;
const #27 = Asciz	Lscala/math/BigInt$;;
const #28 = Asciz	BigDecimal;
const #29 = Asciz	Lscala/math/BigDecimal$;;
const #30 = Asciz	$scope;
const #31 = Asciz	Lscala/xml/TopScope$;;
const #32 = Asciz	Range;
const #33 = Asciz	Lscala/collection/immutable/Range$;;
const #34 = Asciz	StringBuilder;
const #35 = Asciz	Lscala/collection/mutable/StringBuilder$;;
const #36 = Asciz	Vector;
const #37 = Asciz	Lscala/collection/immutable/Vector$;;
const #38 = Asciz	$hash$colon$colon;
const #39 = Asciz	Lscala/collection/immutable/Stream$$hash$colon$colon$;;
const #40 = Asciz	Stream;
const #41 = Asciz	Lscala/collection/immutable/Stream$;;
const #42 = Asciz	$colon$colon;
const #43 = Asciz	Lscala/collection/immutable/$colon$colon$;;
const #44 = Asciz	Nil;
const #45 = Asciz	Lscala/collection/immutable/Nil$;;
const #46 = Asciz	List;
const #47 = Asciz	Lscala/collection/immutable/List$;;
const #48 = Asciz	Iterator;
const #49 = Asciz	Lscala/collection/Iterator$;;
const #50 = Asciz	IndexedSeq;
const #51 = Asciz	Seq;
const #52 = Asciz	Iterable;
const #53 = Asciz	Traversable;
const #54 = Asciz	Lscala/collection/Traversable$;;
const #55 = Asciz	LineNumberTable;
const #56 = Asciz	java/lang/Object;
const #57 = class	#56;	//  java/lang/Object
const #58 = Method	#57.#12;	//  java/lang/Object."<init>":()V
const #59 = NameAndType	#4:#5;//  MODULE$:Lscala/package$;
const #60 = Field	#10.#59;	//  scala/package$.MODULE$:Lscala/package$;
const #61 = Asciz	scala/collection/Traversable$;
const #62 = class	#61;	//  scala/collection/Traversable$
const #63 = NameAndType	#4:#54;//  MODULE$:Lscala/collection/Traversable$;
const #64 = Field	#62.#63;	//  scala/collection/Traversable$.MODULE$:Lscala/collection/Traversable$;
const #65 = NameAndType	#53:#54;//  Traversable:Lscala/collection/Traversable$;
const #66 = Field	#10.#65;	//  scala/package$.Traversable:Lscala/collection/Traversable$;
const #67 = Asciz	scala/collection/Iterable$;
const #68 = class	#67;	//  scala/collection/Iterable$
const #69 = NameAndType	#4:#19;//  MODULE$:Lscala/collection/Iterable$;
const #70 = Field	#68.#69;	//  scala/collection/Iterable$.MODULE$:Lscala/collection/Iterable$;
const #71 = NameAndType	#52:#19;//  Iterable:Lscala/collection/Iterable$;
const #72 = Field	#10.#71;	//  scala/package$.Iterable:Lscala/collection/Iterable$;
const #73 = Asciz	scala/collection/Seq$;
const #74 = class	#73;	//  scala/collection/Seq$
const #75 = NameAndType	#4:#17;//  MODULE$:Lscala/collection/Seq$;
const #76 = Field	#74.#75;	//  scala/collection/Seq$.MODULE$:Lscala/collection/Seq$;
const #77 = NameAndType	#51:#17;//  Seq:Lscala/collection/Seq$;
const #78 = Field	#10.#77;	//  scala/package$.Seq:Lscala/collection/Seq$;
const #79 = Asciz	scala/collection/IndexedSeq$;
const #80 = class	#79;	//  scala/collection/IndexedSeq$
const #81 = NameAndType	#4:#15;//  MODULE$:Lscala/collection/IndexedSeq$;
const #82 = Field	#80.#81;	//  scala/collection/IndexedSeq$.MODULE$:Lscala/collection/IndexedSeq$;
const #83 = NameAndType	#50:#15;//  IndexedSeq:Lscala/collection/IndexedSeq$;
const #84 = Field	#10.#83;	//  scala/package$.IndexedSeq:Lscala/collection/IndexedSeq$;
const #85 = Asciz	scala/collection/Iterator$;
const #86 = class	#85;	//  scala/collection/Iterator$
const #87 = NameAndType	#4:#49;//  MODULE$:Lscala/collection/Iterator$;
const #88 = Field	#86.#87;	//  scala/collection/Iterator$.MODULE$:Lscala/collection/Iterator$;
const #89 = NameAndType	#48:#49;//  Iterator:Lscala/collection/Iterator$;
const #90 = Field	#10.#89;	//  scala/package$.Iterator:Lscala/collection/Iterator$;
const #91 = Asciz	scala/collection/immutable/List$;
const #92 = class	#91;	//  scala/collection/immutable/List$
const #93 = NameAndType	#4:#47;//  MODULE$:Lscala/collection/immutable/List$;
const #94 = Field	#92.#93;	//  scala/collection/immutable/List$.MODULE$:Lscala/collection/immutable/List$;
const #95 = NameAndType	#46:#47;//  List:Lscala/collection/immutable/List$;
const #96 = Field	#10.#95;	//  scala/package$.List:Lscala/collection/immutable/List$;
const #97 = Asciz	scala/collection/immutable/Nil$;
const #98 = class	#97;	//  scala/collection/immutable/Nil$
const #99 = NameAndType	#4:#45;//  MODULE$:Lscala/collection/immutable/Nil$;
const #100 = Field	#98.#99;	//  scala/collection/immutable/Nil$.MODULE$:Lscala/collection/immutable/Nil$;
const #101 = NameAndType	#44:#45;//  Nil:Lscala/collection/immutable/Nil$;
const #102 = Field	#10.#101;	//  scala/package$.Nil:Lscala/collection/immutable/Nil$;
const #103 = Asciz	scala/collection/immutable/$colon$colon$;
const #104 = class	#103;	//  scala/collection/immutable/$colon$colon$
const #105 = NameAndType	#4:#43;//  MODULE$:Lscala/collection/immutable/$colon$colon$;
const #106 = Field	#104.#105;	//  scala/collection/immutable/$colon$colon$.MODULE$:Lscala/collection/immutable/$colon$colon$;
const #107 = NameAndType	#42:#43;//  $colon$colon:Lscala/collection/immutable/$colon$colon$;
const #108 = Field	#10.#107;	//  scala/package$.$colon$colon:Lscala/collection/immutable/$colon$colon$;
const #109 = Asciz	scala/collection/immutable/Stream$;
const #110 = class	#109;	//  scala/collection/immutable/Stream$
const #111 = NameAndType	#4:#41;//  MODULE$:Lscala/collection/immutable/Stream$;
const #112 = Field	#110.#111;	//  scala/collection/immutable/Stream$.MODULE$:Lscala/collection/immutable/Stream$;
const #113 = NameAndType	#40:#41;//  Stream:Lscala/collection/immutable/Stream$;
const #114 = Field	#10.#113;	//  scala/package$.Stream:Lscala/collection/immutable/Stream$;
const #115 = Asciz	scala/collection/immutable/Stream$$hash$colon$colon$;
const #116 = class	#115;	//  scala/collection/immutable/Stream$$hash$colon$colon$
const #117 = NameAndType	#4:#39;//  MODULE$:Lscala/collection/immutable/Stream$$hash$colon$colon$;
const #118 = Field	#116.#117;	//  scala/collection/immutable/Stream$$hash$colon$colon$.MODULE$:Lscala/collection/immutable/Stream$$hash$colon$colon$;
const #119 = NameAndType	#38:#39;//  $hash$colon$colon:Lscala/collection/immutable/Stream$$hash$colon$colon$;
const #120 = Field	#10.#119;	//  scala/package$.$hash$colon$colon:Lscala/collection/immutable/Stream$$hash$colon$colon$;
const #121 = Asciz	scala/collection/immutable/Vector$;
const #122 = class	#121;	//  scala/collection/immutable/Vector$
const #123 = NameAndType	#4:#37;//  MODULE$:Lscala/collection/immutable/Vector$;
const #124 = Field	#122.#123;	//  scala/collection/immutable/Vector$.MODULE$:Lscala/collection/immutable/Vector$;
const #125 = NameAndType	#36:#37;//  Vector:Lscala/collection/immutable/Vector$;
const #126 = Field	#10.#125;	//  scala/package$.Vector:Lscala/collection/immutable/Vector$;
const #127 = Asciz	scala/collection/mutable/StringBuilder$;
const #128 = class	#127;	//  scala/collection/mutable/StringBuilder$
const #129 = NameAndType	#4:#35;//  MODULE$:Lscala/collection/mutable/StringBuilder$;
const #130 = Field	#128.#129;	//  scala/collection/mutable/StringBuilder$.MODULE$:Lscala/collection/mutable/StringBuilder$;
const #131 = NameAndType	#34:#35;//  StringBuilder:Lscala/collection/mutable/StringBuilder$;
const #132 = Field	#10.#131;	//  scala/package$.StringBuilder:Lscala/collection/mutable/StringBuilder$;
const #133 = Asciz	scala/collection/immutable/Range$;
const #134 = class	#133;	//  scala/collection/immutable/Range$
const #135 = NameAndType	#4:#33;//  MODULE$:Lscala/collection/immutable/Range$;
const #136 = Field	#134.#135;	//  scala/collection/immutable/Range$.MODULE$:Lscala/collection/immutable/Range$;
const #137 = NameAndType	#32:#33;//  Range:Lscala/collection/immutable/Range$;
const #138 = Field	#10.#137;	//  scala/package$.Range:Lscala/collection/immutable/Range$;
const #139 = Asciz	scala/xml/TopScope$;
const #140 = class	#139;	//  scala/xml/TopScope$
const #141 = NameAndType	#4:#31;//  MODULE$:Lscala/xml/TopScope$;
const #142 = Field	#140.#141;	//  scala/xml/TopScope$.MODULE$:Lscala/xml/TopScope$;
const #143 = NameAndType	#30:#31;//  $scope:Lscala/xml/TopScope$;
const #144 = Field	#10.#143;	//  scala/package$.$scope:Lscala/xml/TopScope$;
const #145 = Asciz	scala/math/BigDecimal$;
const #146 = class	#145;	//  scala/math/BigDecimal$
const #147 = NameAndType	#4:#29;//  MODULE$:Lscala/math/BigDecimal$;
const #148 = Field	#146.#147;	//  scala/math/BigDecimal$.MODULE$:Lscala/math/BigDecimal$;
const #149 = NameAndType	#28:#29;//  BigDecimal:Lscala/math/BigDecimal$;
const #150 = Field	#10.#149;	//  scala/package$.BigDecimal:Lscala/math/BigDecimal$;
const #151 = Asciz	scala/math/BigInt$;
const #152 = class	#151;	//  scala/math/BigInt$
const #153 = NameAndType	#4:#27;//  MODULE$:Lscala/math/BigInt$;
const #154 = Field	#152.#153;	//  scala/math/BigInt$.MODULE$:Lscala/math/BigInt$;
const #155 = NameAndType	#26:#27;//  BigInt:Lscala/math/BigInt$;
const #156 = Field	#10.#155;	//  scala/package$.BigInt:Lscala/math/BigInt$;
const #157 = Asciz	scala/math/Numeric$;
const #158 = class	#157;	//  scala/math/Numeric$
const #159 = NameAndType	#4:#25;//  MODULE$:Lscala/math/Numeric$;
const #160 = Field	#158.#159;	//  scala/math/Numeric$.MODULE$:Lscala/math/Numeric$;
const #161 = NameAndType	#24:#25;//  Numeric:Lscala/math/Numeric$;
const #162 = Field	#10.#161;	//  scala/package$.Numeric:Lscala/math/Numeric$;
const #163 = Asciz	scala/math/Ordered$;
const #164 = class	#163;	//  scala/math/Ordered$
const #165 = NameAndType	#4:#23;//  MODULE$:Lscala/math/Ordered$;
const #166 = Field	#164.#165;	//  scala/math/Ordered$.MODULE$:Lscala/math/Ordered$;
const #167 = NameAndType	#22:#23;//  Ordered:Lscala/math/Ordered$;
const #168 = Field	#10.#167;	//  scala/package$.Ordered:Lscala/math/Ordered$;
const #169 = Asciz	scala/math/Ordering$;
const #170 = class	#169;	//  scala/math/Ordering$
const #171 = NameAndType	#4:#21;//  MODULE$:Lscala/math/Ordering$;
const #172 = Field	#170.#171;	//  scala/math/Ordering$.MODULE$:Lscala/math/Ordering$;
const #173 = NameAndType	#20:#21;//  Ordering:Lscala/math/Ordering$;
const #174 = Field	#10.#173;	//  scala/package$.Ordering:Lscala/math/Ordering$;
const #175 = Asciz	()Lscala/collection/Iterable$;;
const #176 = NameAndType	#52:#175;//  Iterable:()Lscala/collection/Iterable$;
const #177 = Method	#10.#176;	//  scala/package$.Iterable:()Lscala/collection/Iterable$;
const #178 = NameAndType	#18:#19;//  Collection:Lscala/collection/Iterable$;
const #179 = Field	#10.#178;	//  scala/package$.Collection:Lscala/collection/Iterable$;
const #180 = NameAndType	#16:#17;//  Sequence:Lscala/collection/Seq$;
const #181 = Field	#10.#180;	//  scala/package$.Sequence:Lscala/collection/Seq$;
const #182 = NameAndType	#14:#15;//  RandomAccessSeq:Lscala/collection/IndexedSeq$;
const #183 = Field	#10.#182;	//  scala/package$.RandomAccessSeq:Lscala/collection/IndexedSeq$;
const #184 = Asciz	()Lscala/collection/IndexedSeq$;;
const #185 = Asciz	()Lscala/collection/Seq$;;
const #186 = Asciz	Tuple;
const #187 = Asciz	(Ljava/lang/Object;Ljava/lang/Object;Ljava/lang/Object;Ljava/lang/Object;Ljava/lang/Object;Ljava/lang/Object;Ljava/lang/Object;Ljava/lang/Object;Ljava/lang/Object;Ljava/lang/Object;Ljava/lang/Object;Ljava/lang/Object;Ljava/lang/Object;Ljava/lang/Object;Ljava/lang/Object;Ljava/lang/Object;Ljava/lang/Object;Ljava/lang/Object;Ljava/lang/Object;Ljava/lang/Object;Ljava/lang/Object;Ljava/lang/Object;)Lscala/Tuple22;;
const #188 = Asciz	scala/Tuple22;
const #189 = class	#188;	//  scala/Tuple22
const #190 = Asciz	(Ljava/lang/Object;Ljava/lang/Object;Ljava/lang/Object;Ljava/lang/Object;Ljava/lang/Object;Ljava/lang/Object;Ljava/lang/Object;Ljava/lang/Object;Ljava/lang/Object;Ljava/lang/Object;Ljava/lang/Object;Ljava/lang/Object;Ljava/lang/Object;Ljava/lang/Object;Ljava/lang/Object;Ljava/lang/Object;Ljava/lang/Object;Ljava/lang/Object;Ljava/lang/Object;Ljava/lang/Object;Ljava/lang/Object;Ljava/lang/Object;)V;
const #191 = NameAndType	#11:#190;//  "<init>":(Ljava/lang/Object;Ljava/lang/Object;Ljava/lang/Object;Ljava/lang/Object;Ljava/lang/Object;Ljava/lang/Object;Ljava/lang/Object;Ljava/lang/Object;Ljava/lang/Object;Ljava/lang/Object;Ljava/lang/Object;Ljava/lang/Object;Ljava/lang/Object;Ljava/lang/Object;Ljava/lang/Object;Ljava/lang/Object;Ljava/lang/Object;Ljava/lang/Object;Ljava/lang/Object;Ljava/lang/Object;Ljava/lang/Object;Ljava/lang/Object;)V
const #192 = Method	#189.#191;	//  scala/Tuple22."<init>":(Ljava/lang/Object;Ljava/lang/Object;Ljava/lang/Object;Ljava/lang/Object;Ljava/lang/Object;Ljava/lang/Object;Ljava/lang/Object;Ljava/lang/Object;Ljava/lang/Object;Ljava/lang/Object;Ljava/lang/Object;Ljava/lang/Object;Ljava/lang/Object;Ljava/lang/Object;Ljava/lang/Object;Ljava/lang/Object;Ljava/lang/Object;Ljava/lang/Object;Ljava/lang/Object;Ljava/lang/Object;Ljava/lang/Object;Ljava/lang/Object;)V
const #193 = Asciz	this;
const #194 = Asciz	x1;
const #195 = Asciz	Ljava/lang/Object;;
const #196 = Asciz	x2;
const #197 = Asciz	x3;
const #198 = Asciz	x4;
const #199 = Asciz	x5;
const #200 = Asciz	x6;
const #201 = Asciz	x7;
const #202 = Asciz	x8;
const #203 = Asciz	x9;
const #204 = Asciz	x10;
const #205 = Asciz	x11;
const #206 = Asciz	x12;
const #207 = Asciz	x13;
const #208 = Asciz	x14;
const #209 = Asciz	x15;
const #210 = Asciz	x16;
const #211 = Asciz	x17;
const #212 = Asciz	x18;
const #213 = Asciz	x19;
const #214 = Asciz	x20;
const #215 = Asciz	x21;
const #216 = Asciz	x22;
const #217 = Asciz	LocalVariableTable;
const #218 = Asciz	<A1:Ljava/lang/Object;A2:Ljava/lang/Object;A3:Ljava/lang/Object;A4:Ljava/lang/Object;A5:Ljava/lang/Object;A6:Ljava/lang/Object;A7:Ljava/lang/Object;A8:Ljava/lang/Object;A9:Ljava/lang/Object;A10:Ljava/lang/Object;A11:Ljava/lang/Object;A12:Ljava/lang/Object;A13:Ljava/lang/Object;A14:Ljava/lang/Object;A15:Ljava/lang/Object;A16:Ljava/lang/Object;A17:Ljava/lang/Object;A18:Ljava/lang/Object;A19:Ljava/lang/Object;A20:Ljava/lang/Object;A21:Ljava/lang/Object;A22:Ljava/lang/Object;>(TA1;TA2;TA3;TA4;TA5;TA6;TA7;TA8;TA9;TA10;TA11;TA12;TA13;TA14;TA15;TA16;TA17;TA18;TA19;TA20;TA21;TA22;)Lscala/Tuple22<TA1;TA2;TA3;TA4;TA5;TA6;TA7;TA8;TA9;TA10;TA11;TA12;TA13;TA14;TA15;TA16;TA17;TA18;TA19;TA20;TA21;TA22;>;;
const #219 = Asciz	Signature;
const #220 = Asciz	(Ljava/lang/Object;Ljava/lang/Object;Ljava/lang/Object;Ljava/lang/Object;Ljava/lang/Object;Ljava/lang/Object;Ljava/lang/Object;Ljava/lang/Object;Ljava/lang/Object;Ljava/lang/Object;Ljava/lang/Object;Ljava/lang/Object;Ljava/lang/Object;Ljava/lang/Object;Ljava/lang/Object;Ljava/lang/Object;Ljava/lang/Object;Ljava/lang/Object;Ljava/lang/Object;Ljava/lang/Object;Ljava/lang/Object;)Lscala/Tuple21;;
const #221 = Asciz	scala/Tuple21;
const #222 = class	#221;	//  scala/Tuple21
const #223 = Asciz	(Ljava/lang/Object;Ljava/lang/Object;Ljava/lang/Object;Ljava/lang/Object;Ljava/lang/Object;Ljava/lang/Object;Ljava/lang/Object;Ljava/lang/Object;Ljava/lang/Object;Ljava/lang/Object;Ljava/lang/Object;Ljava/lang/Object;Ljava/lang/Object;Ljava/lang/Object;Ljava/lang/Object;Ljava/lang/Object;Ljava/lang/Object;Ljava/lang/Object;Ljava/lang/Object;Ljava/lang/Object;Ljava/lang/Object;)V;
const #224 = NameAndType	#11:#223;//  "<init>":(Ljava/lang/Object;Ljava/lang/Object;Ljava/lang/Object;Ljava/lang/Object;Ljava/lang/Object;Ljava/lang/Object;Ljava/lang/Object;Ljava/lang/Object;Ljava/lang/Object;Ljava/lang/Object;Ljava/lang/Object;Ljava/lang/Object;Ljava/lang/Object;Ljava/lang/Object;Ljava/lang/Object;Ljava/lang/Object;Ljava/lang/Object;Ljava/lang/Object;Ljava/lang/Object;Ljava/lang/Object;Ljava/lang/Object;)V
const #225 = Method	#222.#224;	//  scala/Tuple21."<init>":(Ljava/lang/Object;Ljava/lang/Object;Ljava/lang/Object;Ljava/lang/Object;Ljava/lang/Object;Ljava/lang/Object;Ljava/lang/Object;Ljava/lang/Object;Ljava/lang/Object;Ljava/lang/Object;Ljava/lang/Object;Ljava/lang/Object;Ljava/lang/Object;Ljava/lang/Object;Ljava/lang/Object;Ljava/lang/Object;Ljava/lang/Object;Ljava/lang/Object;Ljava/lang/Object;Ljava/lang/Object;Ljava/lang/Object;)V
const #226 = Asciz	<A1:Ljava/lang/Object;A2:Ljava/lang/Object;A3:Ljava/lang/Object;A4:Ljava/lang/Object;A5:Ljava/lang/Object;A6:Ljava/lang/Object;A7:Ljava/lang/Object;A8:Ljava/lang/Object;A9:Ljava/lang/Object;A10:Ljava/lang/Object;A11:Ljava/lang/Object;A12:Ljava/lang/Object;A13:Ljava/lang/Object;A14:Ljava/lang/Object;A15:Ljava/lang/Object;A16:Ljava/lang/Object;A17:Ljava/lang/Object;A18:Ljava/lang/Object;A19:Ljava/lang/Object;A20:Ljava/lang/Object;A21:Ljava/lang/Object;>(TA1;TA2;TA3;TA4;TA5;TA6;TA7;TA8;TA9;TA10;TA11;TA12;TA13;TA14;TA15;TA16;TA17;TA18;TA19;TA20;TA21;)Lscala/Tuple21<TA1;TA2;TA3;TA4;TA5;TA6;TA7;TA8;TA9;TA10;TA11;TA12;TA13;TA14;TA15;TA16;TA17;TA18;TA19;TA20;TA21;>;;
const #227 = Asciz	(Ljava/lang/Object;Ljava/lang/Object;Ljava/lang/Object;Ljava/lang/Object;Ljava/lang/Object;Ljava/lang/Object;Ljava/lang/Object;Ljava/lang/Object;Ljava/lang/Object;Ljava/lang/Object;Ljava/lang/Object;Ljava/lang/Object;Ljava/lang/Object;Ljava/lang/Object;Ljava/lang/Object;Ljava/lang/Object;Ljava/lang/Object;Ljava/lang/Object;Ljava/lang/Object;Ljava/lang/Object;)Lscala/Tuple20;;
const #228 = Asciz	scala/Tuple20;
const #229 = class	#228;	//  scala/Tuple20
const #230 = Asciz	(Ljava/lang/Object;Ljava/lang/Object;Ljava/lang/Object;Ljava/lang/Object;Ljava/lang/Object;Ljava/lang/Object;Ljava/lang/Object;Ljava/lang/Object;Ljava/lang/Object;Ljava/lang/Object;Ljava/lang/Object;Ljava/lang/Object;Ljava/lang/Object;Ljava/lang/Object;Ljava/lang/Object;Ljava/lang/Object;Ljava/lang/Object;Ljava/lang/Object;Ljava/lang/Object;Ljava/lang/Object;)V;
const #231 = NameAndType	#11:#230;//  "<init>":(Ljava/lang/Object;Ljava/lang/Object;Ljava/lang/Object;Ljava/lang/Object;Ljava/lang/Object;Ljava/lang/Object;Ljava/lang/Object;Ljava/lang/Object;Ljava/lang/Object;Ljava/lang/Object;Ljava/lang/Object;Ljava/lang/Object;Ljava/lang/Object;Ljava/lang/Object;Ljava/lang/Object;Ljava/lang/Object;Ljava/lang/Object;Ljava/lang/Object;Ljava/lang/Object;Ljava/lang/Object;)V
const #232 = Method	#229.#231;	//  scala/Tuple20."<init>":(Ljava/lang/Object;Ljava/lang/Object;Ljava/lang/Object;Ljava/lang/Object;Ljava/lang/Object;Ljava/lang/Object;Ljava/lang/Object;Ljava/lang/Object;Ljava/lang/Object;Ljava/lang/Object;Ljava/lang/Object;Ljava/lang/Object;Ljava/lang/Object;Ljava/lang/Object;Ljava/lang/Object;Ljava/lang/Object;Ljava/lang/Object;Ljava/lang/Object;Ljava/lang/Object;Ljava/lang/Object;)V
const #233 = Asciz	<A1:Ljava/lang/Object;A2:Ljava/lang/Object;A3:Ljava/lang/Object;A4:Ljava/lang/Object;A5:Ljava/lang/Object;A6:Ljava/lang/Object;A7:Ljava/lang/Object;A8:Ljava/lang/Object;A9:Ljava/lang/Object;A10:Ljava/lang/Object;A11:Ljava/lang/Object;A12:Ljava/lang/Object;A13:Ljava/lang/Object;A14:Ljava/lang/Object;A15:Ljava/lang/Object;A16:Ljava/lang/Object;A17:Ljava/lang/Object;A18:Ljava/lang/Object;A19:Ljava/lang/Object;A20:Ljava/lang/Object;>(TA1;TA2;TA3;TA4;TA5;TA6;TA7;TA8;TA9;TA10;TA11;TA12;TA13;TA14;TA15;TA16;TA17;TA18;TA19;TA20;)Lscala/Tuple20<TA1;TA2;TA3;TA4;TA5;TA6;TA7;TA8;TA9;TA10;TA11;TA12;TA13;TA14;TA15;TA16;TA17;TA18;TA19;TA20;>;;
const #234 = Asciz	(Ljava/lang/Object;Ljava/lang/Object;Ljava/lang/Object;Ljava/lang/Object;Ljava/lang/Object;Ljava/lang/Object;Ljava/lang/Object;Ljava/lang/Object;Ljava/lang/Object;Ljava/lang/Object;Ljava/lang/Object;Ljava/lang/Object;Ljava/lang/Object;Ljava/lang/Object;Ljava/lang/Object;Ljava/lang/Object;Ljava/lang/Object;Ljava/lang/Object;Ljava/lang/Object;)Lscala/Tuple19;;
const #235 = Asciz	scala/Tuple19;
const #236 = class	#235;	//  scala/Tuple19
const #237 = Asciz	(Ljava/lang/Object;Ljava/lang/Object;Ljava/lang/Object;Ljava/lang/Object;Ljava/lang/Object;Ljava/lang/Object;Ljava/lang/Object;Ljava/lang/Object;Ljava/lang/Object;Ljava/lang/Object;Ljava/lang/Object;Ljava/lang/Object;Ljava/lang/Object;Ljava/lang/Object;Ljava/lang/Object;Ljava/lang/Object;Ljava/lang/Object;Ljava/lang/Object;Ljava/lang/Object;)V;
const #238 = NameAndType	#11:#237;//  "<init>":(Ljava/lang/Object;Ljava/lang/Object;Ljava/lang/Object;Ljava/lang/Object;Ljava/lang/Object;Ljava/lang/Object;Ljava/lang/Object;Ljava/lang/Object;Ljava/lang/Object;Ljava/lang/Object;Ljava/lang/Object;Ljava/lang/Object;Ljava/lang/Object;Ljava/lang/Object;Ljava/lang/Object;Ljava/lang/Object;Ljava/lang/Object;Ljava/lang/Object;Ljava/lang/Object;)V
const #239 = Method	#236.#238;	//  scala/Tuple19."<init>":(Ljava/lang/Object;Ljava/lang/Object;Ljava/lang/Object;Ljava/lang/Object;Ljava/lang/Object;Ljava/lang/Object;Ljava/lang/Object;Ljava/lang/Object;Ljava/lang/Object;Ljava/lang/Object;Ljava/lang/Object;Ljava/lang/Object;Ljava/lang/Object;Ljava/lang/Object;Ljava/lang/Object;Ljava/lang/Object;Ljava/lang/Object;Ljava/lang/Object;Ljava/lang/Object;)V
const #240 = Asciz	<A1:Ljava/lang/Object;A2:Ljava/lang/Object;A3:Ljava/lang/Object;A4:Ljava/lang/Object;A5:Ljava/lang/Object;A6:Ljava/lang/Object;A7:Ljava/lang/Object;A8:Ljava/lang/Object;A9:Ljava/lang/Object;A10:Ljava/lang/Object;A11:Ljava/lang/Object;A12:Ljava/lang/Object;A13:Ljava/lang/Object;A14:Ljava/lang/Object;A15:Ljava/lang/Object;A16:Ljava/lang/Object;A17:Ljava/lang/Object;A18:Ljava/lang/Object;A19:Ljava/lang/Object;>(TA1;TA2;TA3;TA4;TA5;TA6;TA7;TA8;TA9;TA10;TA11;TA12;TA13;TA14;TA15;TA16;TA17;TA18;TA19;)Lscala/Tuple19<TA1;TA2;TA3;TA4;TA5;TA6;TA7;TA8;TA9;TA10;TA11;TA12;TA13;TA14;TA15;TA16;TA17;TA18;TA19;>;;
const #241 = Asciz	(Ljava/lang/Object;Ljava/lang/Object;Ljava/lang/Object;Ljava/lang/Object;Ljava/lang/Object;Ljava/lang/Object;Ljava/lang/Object;Ljava/lang/Object;Ljava/lang/Object;Ljava/lang/Object;Ljava/lang/Object;Ljava/lang/Object;Ljava/lang/Object;Ljava/lang/Object;Ljava/lang/Object;Ljava/lang/Object;Ljava/lang/Object;Ljava/lang/Object;)Lscala/Tuple18;;
const #242 = Asciz	scala/Tuple18;
const #243 = class	#242;	//  scala/Tuple18
const #244 = Asciz	(Ljava/lang/Object;Ljava/lang/Object;Ljava/lang/Object;Ljava/lang/Object;Ljava/lang/Object;Ljava/lang/Object;Ljava/lang/Object;Ljava/lang/Object;Ljava/lang/Object;Ljava/lang/Object;Ljava/lang/Object;Ljava/lang/Object;Ljava/lang/Object;Ljava/lang/Object;Ljava/lang/Object;Ljava/lang/Object;Ljava/lang/Object;Ljava/lang/Object;)V;
const #245 = NameAndType	#11:#244;//  "<init>":(Ljava/lang/Object;Ljava/lang/Object;Ljava/lang/Object;Ljava/lang/Object;Ljava/lang/Object;Ljava/lang/Object;Ljava/lang/Object;Ljava/lang/Object;Ljava/lang/Object;Ljava/lang/Object;Ljava/lang/Object;Ljava/lang/Object;Ljava/lang/Object;Ljava/lang/Object;Ljava/lang/Object;Ljava/lang/Object;Ljava/lang/Object;Ljava/lang/Object;)V
const #246 = Method	#243.#245;	//  scala/Tuple18."<init>":(Ljava/lang/Object;Ljava/lang/Object;Ljava/lang/Object;Ljava/lang/Object;Ljava/lang/Object;Ljava/lang/Object;Ljava/lang/Object;Ljava/lang/Object;Ljava/lang/Object;Ljava/lang/Object;Ljava/lang/Object;Ljava/lang/Object;Ljava/lang/Object;Ljava/lang/Object;Ljava/lang/Object;Ljava/lang/Object;Ljava/lang/Object;Ljava/lang/Object;)V
const #247 = Asciz	<A1:Ljava/lang/Object;A2:Ljava/lang/Object;A3:Ljava/lang/Object;A4:Ljava/lang/Object;A5:Ljava/lang/Object;A6:Ljava/lang/Object;A7:Ljava/lang/Object;A8:Ljava/lang/Object;A9:Ljava/lang/Object;A10:Ljava/lang/Object;A11:Ljava/lang/Object;A12:Ljava/lang/Object;A13:Ljava/lang/Object;A14:Ljava/lang/Object;A15:Ljava/lang/Object;A16:Ljava/lang/Object;A17:Ljava/lang/Object;A18:Ljava/lang/Object;>(TA1;TA2;TA3;TA4;TA5;TA6;TA7;TA8;TA9;TA10;TA11;TA12;TA13;TA14;TA15;TA16;TA17;TA18;)Lscala/Tuple18<TA1;TA2;TA3;TA4;TA5;TA6;TA7;TA8;TA9;TA10;TA11;TA12;TA13;TA14;TA15;TA16;TA17;TA18;>;;
const #248 = Asciz	(Ljava/lang/Object;Ljava/lang/Object;Ljava/lang/Object;Ljava/lang/Object;Ljava/lang/Object;Ljava/lang/Object;Ljava/lang/Object;Ljava/lang/Object;Ljava/lang/Object;Ljava/lang/Object;Ljava/lang/Object;Ljava/lang/Object;Ljava/lang/Object;Ljava/lang/Object;Ljava/lang/Object;Ljava/lang/Object;Ljava/lang/Object;)Lscala/Tuple17;;
const #249 = Asciz	scala/Tuple17;
const #250 = class	#249;	//  scala/Tuple17
const #251 = Asciz	(Ljava/lang/Object;Ljava/lang/Object;Ljava/lang/Object;Ljava/lang/Object;Ljava/lang/Object;Ljava/lang/Object;Ljava/lang/Object;Ljava/lang/Object;Ljava/lang/Object;Ljava/lang/Object;Ljava/lang/Object;Ljava/lang/Object;Ljava/lang/Object;Ljava/lang/Object;Ljava/lang/Object;Ljava/lang/Object;Ljava/lang/Object;)V;
const #252 = NameAndType	#11:#251;//  "<init>":(Ljava/lang/Object;Ljava/lang/Object;Ljava/lang/Object;Ljava/lang/Object;Ljava/lang/Object;Ljava/lang/Object;Ljava/lang/Object;Ljava/lang/Object;Ljava/lang/Object;Ljava/lang/Object;Ljava/lang/Object;Ljava/lang/Object;Ljava/lang/Object;Ljava/lang/Object;Ljava/lang/Object;Ljava/lang/Object;Ljava/lang/Object;)V
const #253 = Method	#250.#252;	//  scala/Tuple17."<init>":(Ljava/lang/Object;Ljava/lang/Object;Ljava/lang/Object;Ljava/lang/Object;Ljava/lang/Object;Ljava/lang/Object;Ljava/lang/Object;Ljava/lang/Object;Ljava/lang/Object;Ljava/lang/Object;Ljava/lang/Object;Ljava/lang/Object;Ljava/lang/Object;Ljava/lang/Object;Ljava/lang/Object;Ljava/lang/Object;Ljava/lang/Object;)V
const #254 = Asciz	<A1:Ljava/lang/Object;A2:Ljava/lang/Object;A3:Ljava/lang/Object;A4:Ljava/lang/Object;A5:Ljava/lang/Object;A6:Ljava/lang/Object;A7:Ljava/lang/Object;A8:Ljava/lang/Object;A9:Ljava/lang/Object;A10:Ljava/lang/Object;A11:Ljava/lang/Object;A12:Ljava/lang/Object;A13:Ljava/lang/Object;A14:Ljava/lang/Object;A15:Ljava/lang/Object;A16:Ljava/lang/Object;A17:Ljava/lang/Object;>(TA1;TA2;TA3;TA4;TA5;TA6;TA7;TA8;TA9;TA10;TA11;TA12;TA13;TA14;TA15;TA16;TA17;)Lscala/Tuple17<TA1;TA2;TA3;TA4;TA5;TA6;TA7;TA8;TA9;TA10;TA11;TA12;TA13;TA14;TA15;TA16;TA17;>;;
const #255 = Asciz	(Ljava/lang/Object;Ljava/lang/Object;Ljava/lang/Object;Ljava/lang/Object;Ljava/lang/Object;Ljava/lang/Object;Ljava/lang/Object;Ljava/lang/Object;Ljava/lang/Object;Ljava/lang/Object;Ljava/lang/Object;Ljava/lang/Object;Ljava/lang/Object;Ljava/lang/Object;Ljava/lang/Object;Ljava/lang/Object;)Lscala/Tuple16;;
const #256 = Asciz	scala/Tuple16;
const #257 = class	#256;	//  scala/Tuple16
const #258 = Asciz	(Ljava/lang/Object;Ljava/lang/Object;Ljava/lang/Object;Ljava/lang/Object;Ljava/lang/Object;Ljava/lang/Object;Ljava/lang/Object;Ljava/lang/Object;Ljava/lang/Object;Ljava/lang/Object;Ljava/lang/Object;Ljava/lang/Object;Ljava/lang/Object;Ljava/lang/Object;Ljava/lang/Object;Ljava/lang/Object;)V;
const #259 = NameAndType	#11:#258;//  "<init>":(Ljava/lang/Object;Ljava/lang/Object;Ljava/lang/Object;Ljava/lang/Object;Ljava/lang/Object;Ljava/lang/Object;Ljava/lang/Object;Ljava/lang/Object;Ljava/lang/Object;Ljava/lang/Object;Ljava/lang/Object;Ljava/lang/Object;Ljava/lang/Object;Ljava/lang/Object;Ljava/lang/Object;Ljava/lang/Object;)V
const #260 = Method	#257.#259;	//  scala/Tuple16."<init>":(Ljava/lang/Object;Ljava/lang/Object;Ljava/lang/Object;Ljava/lang/Object;Ljava/lang/Object;Ljava/lang/Object;Ljava/lang/Object;Ljava/lang/Object;Ljava/lang/Object;Ljava/lang/Object;Ljava/lang/Object;Ljava/lang/Object;Ljava/lang/Object;Ljava/lang/Object;Ljava/lang/Object;Ljava/lang/Object;)V
const #261 = Asciz	<A1:Ljava/lang/Object;A2:Ljava/lang/Object;A3:Ljava/lang/Object;A4:Ljava/lang/Object;A5:Ljava/lang/Object;A6:Ljava/lang/Object;A7:Ljava/lang/Object;A8:Ljava/lang/Object;A9:Ljava/lang/Object;A10:Ljava/lang/Object;A11:Ljava/lang/Object;A12:Ljava/lang/Object;A13:Ljava/lang/Object;A14:Ljava/lang/Object;A15:Ljava/lang/Object;A16:Ljava/lang/Object;>(TA1;TA2;TA3;TA4;TA5;TA6;TA7;TA8;TA9;TA10;TA11;TA12;TA13;TA14;TA15;TA16;)Lscala/Tuple16<TA1;TA2;TA3;TA4;TA5;TA6;TA7;TA8;TA9;TA10;TA11;TA12;TA13;TA14;TA15;TA16;>;;
const #262 = Asciz	(Ljava/lang/Object;Ljava/lang/Object;Ljava/lang/Object;Ljava/lang/Object;Ljava/lang/Object;Ljava/lang/Object;Ljava/lang/Object;Ljava/lang/Object;Ljava/lang/Object;Ljava/lang/Object;Ljava/lang/Object;Ljava/lang/Object;Ljava/lang/Object;Ljava/lang/Object;Ljava/lang/Object;)Lscala/Tuple15;;
const #263 = Asciz	scala/Tuple15;
const #264 = class	#263;	//  scala/Tuple15
const #265 = Asciz	(Ljava/lang/Object;Ljava/lang/Object;Ljava/lang/Object;Ljava/lang/Object;Ljava/lang/Object;Ljava/lang/Object;Ljava/lang/Object;Ljava/lang/Object;Ljava/lang/Object;Ljava/lang/Object;Ljava/lang/Object;Ljava/lang/Object;Ljava/lang/Object;Ljava/lang/Object;Ljava/lang/Object;)V;
const #266 = NameAndType	#11:#265;//  "<init>":(Ljava/lang/Object;Ljava/lang/Object;Ljava/lang/Object;Ljava/lang/Object;Ljava/lang/Object;Ljava/lang/Object;Ljava/lang/Object;Ljava/lang/Object;Ljava/lang/Object;Ljava/lang/Object;Ljava/lang/Object;Ljava/lang/Object;Ljava/lang/Object;Ljava/lang/Object;Ljava/lang/Object;)V
const #267 = Method	#264.#266;	//  scala/Tuple15."<init>":(Ljava/lang/Object;Ljava/lang/Object;Ljava/lang/Object;Ljava/lang/Object;Ljava/lang/Object;Ljava/lang/Object;Ljava/lang/Object;Ljava/lang/Object;Ljava/lang/Object;Ljava/lang/Object;Ljava/lang/Object;Ljava/lang/Object;Ljava/lang/Object;Ljava/lang/Object;Ljava/lang/Object;)V
const #268 = Asciz	<A1:Ljava/lang/Object;A2:Ljava/lang/Object;A3:Ljava/lang/Object;A4:Ljava/lang/Object;A5:Ljava/lang/Object;A6:Ljava/lang/Object;A7:Ljava/lang/Object;A8:Ljava/lang/Object;A9:Ljava/lang/Object;A10:Ljava/lang/Object;A11:Ljava/lang/Object;A12:Ljava/lang/Object;A13:Ljava/lang/Object;A14:Ljava/lang/Object;A15:Ljava/lang/Object;>(TA1;TA2;TA3;TA4;TA5;TA6;TA7;TA8;TA9;TA10;TA11;TA12;TA13;TA14;TA15;)Lscala/Tuple15<TA1;TA2;TA3;TA4;TA5;TA6;TA7;TA8;TA9;TA10;TA11;TA12;TA13;TA14;TA15;>;;
const #269 = Asciz	(Ljava/lang/Object;Ljava/lang/Object;Ljava/lang/Object;Ljava/lang/Object;Ljava/lang/Object;Ljava/lang/Object;Ljava/lang/Object;Ljava/lang/Object;Ljava/lang/Object;Ljava/lang/Object;Ljava/lang/Object;Ljava/lang/Object;Ljava/lang/Object;Ljava/lang/Object;)Lscala/Tuple14;;
const #270 = Asciz	scala/Tuple14;
const #271 = class	#270;	//  scala/Tuple14
const #272 = Asciz	(Ljava/lang/Object;Ljava/lang/Object;Ljava/lang/Object;Ljava/lang/Object;Ljava/lang/Object;Ljava/lang/Object;Ljava/lang/Object;Ljava/lang/Object;Ljava/lang/Object;Ljava/lang/Object;Ljava/lang/Object;Ljava/lang/Object;Ljava/lang/Object;Ljava/lang/Object;)V;
const #273 = NameAndType	#11:#272;//  "<init>":(Ljava/lang/Object;Ljava/lang/Object;Ljava/lang/Object;Ljava/lang/Object;Ljava/lang/Object;Ljava/lang/Object;Ljava/lang/Object;Ljava/lang/Object;Ljava/lang/Object;Ljava/lang/Object;Ljava/lang/Object;Ljava/lang/Object;Ljava/lang/Object;Ljava/lang/Object;)V
const #274 = Method	#271.#273;	//  scala/Tuple14."<init>":(Ljava/lang/Object;Ljava/lang/Object;Ljava/lang/Object;Ljava/lang/Object;Ljava/lang/Object;Ljava/lang/Object;Ljava/lang/Object;Ljava/lang/Object;Ljava/lang/Object;Ljava/lang/Object;Ljava/lang/Object;Ljava/lang/Object;Ljava/lang/Object;Ljava/lang/Object;)V
const #275 = Asciz	<A1:Ljava/lang/Object;A2:Ljava/lang/Object;A3:Ljava/lang/Object;A4:Ljava/lang/Object;A5:Ljava/lang/Object;A6:Ljava/lang/Object;A7:Ljava/lang/Object;A8:Ljava/lang/Object;A9:Ljava/lang/Object;A10:Ljava/lang/Object;A11:Ljava/lang/Object;A12:Ljava/lang/Object;A13:Ljava/lang/Object;A14:Ljava/lang/Object;>(TA1;TA2;TA3;TA4;TA5;TA6;TA7;TA8;TA9;TA10;TA11;TA12;TA13;TA14;)Lscala/Tuple14<TA1;TA2;TA3;TA4;TA5;TA6;TA7;TA8;TA9;TA10;TA11;TA12;TA13;TA14;>;;
const #276 = Asciz	(Ljava/lang/Object;Ljava/lang/Object;Ljava/lang/Object;Ljava/lang/Object;Ljava/lang/Object;Ljava/lang/Object;Ljava/lang/Object;Ljava/lang/Object;Ljava/lang/Object;Ljava/lang/Object;Ljava/lang/Object;Ljava/lang/Object;Ljava/lang/Object;)Lscala/Tuple13;;
const #277 = Asciz	scala/Tuple13;
const #278 = class	#277;	//  scala/Tuple13
const #279 = Asciz	(Ljava/lang/Object;Ljava/lang/Object;Ljava/lang/Object;Ljava/lang/Object;Ljava/lang/Object;Ljava/lang/Object;Ljava/lang/Object;Ljava/lang/Object;Ljava/lang/Object;Ljava/lang/Object;Ljava/lang/Object;Ljava/lang/Object;Ljava/lang/Object;)V;
const #280 = NameAndType	#11:#279;//  "<init>":(Ljava/lang/Object;Ljava/lang/Object;Ljava/lang/Object;Ljava/lang/Object;Ljava/lang/Object;Ljava/lang/Object;Ljava/lang/Object;Ljava/lang/Object;Ljava/lang/Object;Ljava/lang/Object;Ljava/lang/Object;Ljava/lang/Object;Ljava/lang/Object;)V
const #281 = Method	#278.#280;	//  scala/Tuple13."<init>":(Ljava/lang/Object;Ljava/lang/Object;Ljava/lang/Object;Ljava/lang/Object;Ljava/lang/Object;Ljava/lang/Object;Ljava/lang/Object;Ljava/lang/Object;Ljava/lang/Object;Ljava/lang/Object;Ljava/lang/Object;Ljava/lang/Object;Ljava/lang/Object;)V
const #282 = Asciz	<A1:Ljava/lang/Object;A2:Ljava/lang/Object;A3:Ljava/lang/Object;A4:Ljava/lang/Object;A5:Ljava/lang/Object;A6:Ljava/lang/Object;A7:Ljava/lang/Object;A8:Ljava/lang/Object;A9:Ljava/lang/Object;A10:Ljava/lang/Object;A11:Ljava/lang/Object;A12:Ljava/lang/Object;A13:Ljava/lang/Object;>(TA1;TA2;TA3;TA4;TA5;TA6;TA7;TA8;TA9;TA10;TA11;TA12;TA13;)Lscala/Tuple13<TA1;TA2;TA3;TA4;TA5;TA6;TA7;TA8;TA9;TA10;TA11;TA12;TA13;>;;
const #283 = Asciz	(Ljava/lang/Object;Ljava/lang/Object;Ljava/lang/Object;Ljava/lang/Object;Ljava/lang/Object;Ljava/lang/Object;Ljava/lang/Object;Ljava/lang/Object;Ljava/lang/Object;Ljava/lang/Object;Ljava/lang/Object;Ljava/lang/Object;)Lscala/Tuple12;;
const #284 = Asciz	scala/Tuple12;
const #285 = class	#284;	//  scala/Tuple12
const #286 = Asciz	(Ljava/lang/Object;Ljava/lang/Object;Ljava/lang/Object;Ljava/lang/Object;Ljava/lang/Object;Ljava/lang/Object;Ljava/lang/Object;Ljava/lang/Object;Ljava/lang/Object;Ljava/lang/Object;Ljava/lang/Object;Ljava/lang/Object;)V;
const #287 = NameAndType	#11:#286;//  "<init>":(Ljava/lang/Object;Ljava/lang/Object;Ljava/lang/Object;Ljava/lang/Object;Ljava/lang/Object;Ljava/lang/Object;Ljava/lang/Object;Ljava/lang/Object;Ljava/lang/Object;Ljava/lang/Object;Ljava/lang/Object;Ljava/lang/Object;)V
const #288 = Method	#285.#287;	//  scala/Tuple12."<init>":(Ljava/lang/Object;Ljava/lang/Object;Ljava/lang/Object;Ljava/lang/Object;Ljava/lang/Object;Ljava/lang/Object;Ljava/lang/Object;Ljava/lang/Object;Ljava/lang/Object;Ljava/lang/Object;Ljava/lang/Object;Ljava/lang/Object;)V
const #289 = Asciz	<A1:Ljava/lang/Object;A2:Ljava/lang/Object;A3:Ljava/lang/Object;A4:Ljava/lang/Object;A5:Ljava/lang/Object;A6:Ljava/lang/Object;A7:Ljava/lang/Object;A8:Ljava/lang/Object;A9:Ljava/lang/Object;A10:Ljava/lang/Object;A11:Ljava/lang/Object;A12:Ljava/lang/Object;>(TA1;TA2;TA3;TA4;TA5;TA6;TA7;TA8;TA9;TA10;TA11;TA12;)Lscala/Tuple12<TA1;TA2;TA3;TA4;TA5;TA6;TA7;TA8;TA9;TA10;TA11;TA12;>;;
const #290 = Asciz	(Ljava/lang/Object;Ljava/lang/Object;Ljava/lang/Object;Ljava/lang/Object;Ljava/lang/Object;Ljava/lang/Object;Ljava/lang/Object;Ljava/lang/Object;Ljava/lang/Object;Ljava/lang/Object;Ljava/lang/Object;)Lscala/Tuple11;;
const #291 = Asciz	scala/Tuple11;
const #292 = class	#291;	//  scala/Tuple11
const #293 = Asciz	(Ljava/lang/Object;Ljava/lang/Object;Ljava/lang/Object;Ljava/lang/Object;Ljava/lang/Object;Ljava/lang/Object;Ljava/lang/Object;Ljava/lang/Object;Ljava/lang/Object;Ljava/lang/Object;Ljava/lang/Object;)V;
const #294 = NameAndType	#11:#293;//  "<init>":(Ljava/lang/Object;Ljava/lang/Object;Ljava/lang/Object;Ljava/lang/Object;Ljava/lang/Object;Ljava/lang/Object;Ljava/lang/Object;Ljava/lang/Object;Ljava/lang/Object;Ljava/lang/Object;Ljava/lang/Object;)V
const #295 = Method	#292.#294;	//  scala/Tuple11."<init>":(Ljava/lang/Object;Ljava/lang/Object;Ljava/lang/Object;Ljava/lang/Object;Ljava/lang/Object;Ljava/lang/Object;Ljava/lang/Object;Ljava/lang/Object;Ljava/lang/Object;Ljava/lang/Object;Ljava/lang/Object;)V
const #296 = Asciz	<A1:Ljava/lang/Object;A2:Ljava/lang/Object;A3:Ljava/lang/Object;A4:Ljava/lang/Object;A5:Ljava/lang/Object;A6:Ljava/lang/Object;A7:Ljava/lang/Object;A8:Ljava/lang/Object;A9:Ljava/lang/Object;A10:Ljava/lang/Object;A11:Ljava/lang/Object;>(TA1;TA2;TA3;TA4;TA5;TA6;TA7;TA8;TA9;TA10;TA11;)Lscala/Tuple11<TA1;TA2;TA3;TA4;TA5;TA6;TA7;TA8;TA9;TA10;TA11;>;;
const #297 = Asciz	(Ljava/lang/Object;Ljava/lang/Object;Ljava/lang/Object;Ljava/lang/Object;Ljava/lang/Object;Ljava/lang/Object;Ljava/lang/Object;Ljava/lang/Object;Ljava/lang/Object;Ljava/lang/Object;)Lscala/Tuple10;;
const #298 = Asciz	scala/Tuple10;
const #299 = class	#298;	//  scala/Tuple10
const #300 = Asciz	(Ljava/lang/Object;Ljava/lang/Object;Ljava/lang/Object;Ljava/lang/Object;Ljava/lang/Object;Ljava/lang/Object;Ljava/lang/Object;Ljava/lang/Object;Ljava/lang/Object;Ljava/lang/Object;)V;
const #301 = NameAndType	#11:#300;//  "<init>":(Ljava/lang/Object;Ljava/lang/Object;Ljava/lang/Object;Ljava/lang/Object;Ljava/lang/Object;Ljava/lang/Object;Ljava/lang/Object;Ljava/lang/Object;Ljava/lang/Object;Ljava/lang/Object;)V
const #302 = Method	#299.#301;	//  scala/Tuple10."<init>":(Ljava/lang/Object;Ljava/lang/Object;Ljava/lang/Object;Ljava/lang/Object;Ljava/lang/Object;Ljava/lang/Object;Ljava/lang/Object;Ljava/lang/Object;Ljava/lang/Object;Ljava/lang/Object;)V
const #303 = Asciz	<A1:Ljava/lang/Object;A2:Ljava/lang/Object;A3:Ljava/lang/Object;A4:Ljava/lang/Object;A5:Ljava/lang/Object;A6:Ljava/lang/Object;A7:Ljava/lang/Object;A8:Ljava/lang/Object;A9:Ljava/lang/Object;A10:Ljava/lang/Object;>(TA1;TA2;TA3;TA4;TA5;TA6;TA7;TA8;TA9;TA10;)Lscala/Tuple10<TA1;TA2;TA3;TA4;TA5;TA6;TA7;TA8;TA9;TA10;>;;
const #304 = Asciz	(Ljava/lang/Object;Ljava/lang/Object;Ljava/lang/Object;Ljava/lang/Object;Ljava/lang/Object;Ljava/lang/Object;Ljava/lang/Object;Ljava/lang/Object;Ljava/lang/Object;)Lscala/Tuple9;;
const #305 = Asciz	scala/Tuple9;
const #306 = class	#305;	//  scala/Tuple9
const #307 = Asciz	(Ljava/lang/Object;Ljava/lang/Object;Ljava/lang/Object;Ljava/lang/Object;Ljava/lang/Object;Ljava/lang/Object;Ljava/lang/Object;Ljava/lang/Object;Ljava/lang/Object;)V;
const #308 = NameAndType	#11:#307;//  "<init>":(Ljava/lang/Object;Ljava/lang/Object;Ljava/lang/Object;Ljava/lang/Object;Ljava/lang/Object;Ljava/lang/Object;Ljava/lang/Object;Ljava/lang/Object;Ljava/lang/Object;)V
const #309 = Method	#306.#308;	//  scala/Tuple9."<init>":(Ljava/lang/Object;Ljava/lang/Object;Ljava/lang/Object;Ljava/lang/Object;Ljava/lang/Object;Ljava/lang/Object;Ljava/lang/Object;Ljava/lang/Object;Ljava/lang/Object;)V
const #310 = Asciz	<A1:Ljava/lang/Object;A2:Ljava/lang/Object;A3:Ljava/lang/Object;A4:Ljava/lang/Object;A5:Ljava/lang/Object;A6:Ljava/lang/Object;A7:Ljava/lang/Object;A8:Ljava/lang/Object;A9:Ljava/lang/Object;>(TA1;TA2;TA3;TA4;TA5;TA6;TA7;TA8;TA9;)Lscala/Tuple9<TA1;TA2;TA3;TA4;TA5;TA6;TA7;TA8;TA9;>;;
const #311 = Asciz	(Ljava/lang/Object;Ljava/lang/Object;Ljava/lang/Object;Ljava/lang/Object;Ljava/lang/Object;Ljava/lang/Object;Ljava/lang/Object;Ljava/lang/Object;)Lscala/Tuple8;;
const #312 = Asciz	scala/Tuple8;
const #313 = class	#312;	//  scala/Tuple8
const #314 = Asciz	(Ljava/lang/Object;Ljava/lang/Object;Ljava/lang/Object;Ljava/lang/Object;Ljava/lang/Object;Ljava/lang/Object;Ljava/lang/Object;Ljava/lang/Object;)V;
const #315 = NameAndType	#11:#314;//  "<init>":(Ljava/lang/Object;Ljava/lang/Object;Ljava/lang/Object;Ljava/lang/Object;Ljava/lang/Object;Ljava/lang/Object;Ljava/lang/Object;Ljava/lang/Object;)V
const #316 = Method	#313.#315;	//  scala/Tuple8."<init>":(Ljava/lang/Object;Ljava/lang/Object;Ljava/lang/Object;Ljava/lang/Object;Ljava/lang/Object;Ljava/lang/Object;Ljava/lang/Object;Ljava/lang/Object;)V
const #317 = Asciz	<A1:Ljava/lang/Object;A2:Ljava/lang/Object;A3:Ljava/lang/Object;A4:Ljava/lang/Object;A5:Ljava/lang/Object;A6:Ljava/lang/Object;A7:Ljava/lang/Object;A8:Ljava/lang/Object;>(TA1;TA2;TA3;TA4;TA5;TA6;TA7;TA8;)Lscala/Tuple8<TA1;TA2;TA3;TA4;TA5;TA6;TA7;TA8;>;;
const #318 = Asciz	(Ljava/lang/Object;Ljava/lang/Object;Ljava/lang/Object;Ljava/lang/Object;Ljava/lang/Object;Ljava/lang/Object;Ljava/lang/Object;)Lscala/Tuple7;;
const #319 = Asciz	scala/Tuple7;
const #320 = class	#319;	//  scala/Tuple7
const #321 = Asciz	(Ljava/lang/Object;Ljava/lang/Object;Ljava/lang/Object;Ljava/lang/Object;Ljava/lang/Object;Ljava/lang/Object;Ljava/lang/Object;)V;
const #322 = NameAndType	#11:#321;//  "<init>":(Ljava/lang/Object;Ljava/lang/Object;Ljava/lang/Object;Ljava/lang/Object;Ljava/lang/Object;Ljava/lang/Object;Ljava/lang/Object;)V
const #323 = Method	#320.#322;	//  scala/Tuple7."<init>":(Ljava/lang/Object;Ljava/lang/Object;Ljava/lang/Object;Ljava/lang/Object;Ljava/lang/Object;Ljava/lang/Object;Ljava/lang/Object;)V
const #324 = Asciz	<A1:Ljava/lang/Object;A2:Ljava/lang/Object;A3:Ljava/lang/Object;A4:Ljava/lang/Object;A5:Ljava/lang/Object;A6:Ljava/lang/Object;A7:Ljava/lang/Object;>(TA1;TA2;TA3;TA4;TA5;TA6;TA7;)Lscala/Tuple7<TA1;TA2;TA3;TA4;TA5;TA6;TA7;>;;
const #325 = Asciz	(Ljava/lang/Object;Ljava/lang/Object;Ljava/lang/Object;Ljava/lang/Object;Ljava/lang/Object;Ljava/lang/Object;)Lscala/Tuple6;;
const #326 = Asciz	scala/Tuple6;
const #327 = class	#326;	//  scala/Tuple6
const #328 = Asciz	(Ljava/lang/Object;Ljava/lang/Object;Ljava/lang/Object;Ljava/lang/Object;Ljava/lang/Object;Ljava/lang/Object;)V;
const #329 = NameAndType	#11:#328;//  "<init>":(Ljava/lang/Object;Ljava/lang/Object;Ljava/lang/Object;Ljava/lang/Object;Ljava/lang/Object;Ljava/lang/Object;)V
const #330 = Method	#327.#329;	//  scala/Tuple6."<init>":(Ljava/lang/Object;Ljava/lang/Object;Ljava/lang/Object;Ljava/lang/Object;Ljava/lang/Object;Ljava/lang/Object;)V
const #331 = Asciz	<A1:Ljava/lang/Object;A2:Ljava/lang/Object;A3:Ljava/lang/Object;A4:Ljava/lang/Object;A5:Ljava/lang/Object;A6:Ljava/lang/Object;>(TA1;TA2;TA3;TA4;TA5;TA6;)Lscala/Tuple6<TA1;TA2;TA3;TA4;TA5;TA6;>;;
const #332 = Asciz	(Ljava/lang/Object;Ljava/lang/Object;Ljava/lang/Object;Ljava/lang/Object;Ljava/lang/Object;)Lscala/Tuple5;;
const #333 = Asciz	scala/Tuple5;
const #334 = class	#333;	//  scala/Tuple5
const #335 = Asciz	(Ljava/lang/Object;Ljava/lang/Object;Ljava/lang/Object;Ljava/lang/Object;Ljava/lang/Object;)V;
const #336 = NameAndType	#11:#335;//  "<init>":(Ljava/lang/Object;Ljava/lang/Object;Ljava/lang/Object;Ljava/lang/Object;Ljava/lang/Object;)V
const #337 = Method	#334.#336;	//  scala/Tuple5."<init>":(Ljava/lang/Object;Ljava/lang/Object;Ljava/lang/Object;Ljava/lang/Object;Ljava/lang/Object;)V
const #338 = Asciz	<A1:Ljava/lang/Object;A2:Ljava/lang/Object;A3:Ljava/lang/Object;A4:Ljava/lang/Object;A5:Ljava/lang/Object;>(TA1;TA2;TA3;TA4;TA5;)Lscala/Tuple5<TA1;TA2;TA3;TA4;TA5;>;;
const #339 = Asciz	(Ljava/lang/Object;Ljava/lang/Object;Ljava/lang/Object;Ljava/lang/Object;)Lscala/Tuple4;;
const #340 = Asciz	scala/Tuple4;
const #341 = class	#340;	//  scala/Tuple4
const #342 = Asciz	(Ljava/lang/Object;Ljava/lang/Object;Ljava/lang/Object;Ljava/lang/Object;)V;
const #343 = NameAndType	#11:#342;//  "<init>":(Ljava/lang/Object;Ljava/lang/Object;Ljava/lang/Object;Ljava/lang/Object;)V
const #344 = Method	#341.#343;	//  scala/Tuple4."<init>":(Ljava/lang/Object;Ljava/lang/Object;Ljava/lang/Object;Ljava/lang/Object;)V
const #345 = Asciz	<A1:Ljava/lang/Object;A2:Ljava/lang/Object;A3:Ljava/lang/Object;A4:Ljava/lang/Object;>(TA1;TA2;TA3;TA4;)Lscala/Tuple4<TA1;TA2;TA3;TA4;>;;
const #346 = Asciz	(Ljava/lang/Object;Ljava/lang/Object;Ljava/lang/Object;)Lscala/Tuple3;;
const #347 = Asciz	scala/Tuple3;
const #348 = class	#347;	//  scala/Tuple3
const #349 = Asciz	(Ljava/lang/Object;Ljava/lang/Object;Ljava/lang/Object;)V;
const #350 = NameAndType	#11:#349;//  "<init>":(Ljava/lang/Object;Ljava/lang/Object;Ljava/lang/Object;)V
const #351 = Method	#348.#350;	//  scala/Tuple3."<init>":(Ljava/lang/Object;Ljava/lang/Object;Ljava/lang/Object;)V
const #352 = Asciz	<A1:Ljava/lang/Object;A2:Ljava/lang/Object;A3:Ljava/lang/Object;>(TA1;TA2;TA3;)Lscala/Tuple3<TA1;TA2;TA3;>;;
const #353 = Asciz	(Ljava/lang/Object;Ljava/lang/Object;)Lscala/Tuple2;;
const #354 = Asciz	scala/Tuple2;
const #355 = class	#354;	//  scala/Tuple2
const #356 = Asciz	(Ljava/lang/Object;Ljava/lang/Object;)V;
const #357 = NameAndType	#11:#356;//  "<init>":(Ljava/lang/Object;Ljava/lang/Object;)V
const #358 = Method	#355.#357;	//  scala/Tuple2."<init>":(Ljava/lang/Object;Ljava/lang/Object;)V
const #359 = Asciz	<A1:Ljava/lang/Object;A2:Ljava/lang/Object;>(TA1;TA2;)Lscala/Tuple2<TA1;TA2;>;;
const #360 = Asciz	(Ljava/lang/Object;)Lscala/Tuple1;;
const #361 = Asciz	scala/Tuple1;
const #362 = class	#361;	//  scala/Tuple1
const #363 = Asciz	(Ljava/lang/Object;)V;
const #364 = NameAndType	#11:#363;//  "<init>":(Ljava/lang/Object;)V
const #365 = Method	#362.#364;	//  scala/Tuple1."<init>":(Ljava/lang/Object;)V
const #366 = Asciz	<A1:Ljava/lang/Object;>(TA1;)Lscala/Tuple1<TA1;>;;
const #367 = Asciz	()Lscala/math/Ordering$;;
const #368 = Asciz	()Lscala/math/Ordered$;;
const #369 = Asciz	()Lscala/math/Numeric$;;
const #370 = Asciz	()Lscala/math/BigInt$;;
const #371 = Asciz	()Lscala/math/BigDecimal$;;
const #372 = Asciz	currentThread;
const #373 = Asciz	()Ljava/lang/Thread;;
const #374 = Asciz	java/lang/Thread;
const #375 = class	#374;	//  java/lang/Thread
const #376 = NameAndType	#372:#373;//  currentThread:()Ljava/lang/Thread;
const #377 = Method	#375.#376;	//  java/lang/Thread.currentThread:()Ljava/lang/Thread;
const #378 = Asciz	()Lscala/xml/TopScope$;;
const #379 = Asciz	()Lscala/collection/immutable/Range$;;
const #380 = Asciz	()Lscala/collection/mutable/StringBuilder$;;
const #381 = Asciz	()Lscala/collection/immutable/Vector$;;
const #382 = Asciz	()Lscala/collection/immutable/Stream$$hash$colon$colon$;;
const #383 = Asciz	()Lscala/collection/immutable/Stream$;;
const #384 = Asciz	()Lscala/collection/immutable/$colon$colon$;;
const #385 = Asciz	()Lscala/collection/immutable/Nil$;;
const #386 = Asciz	()Lscala/collection/immutable/List$;;
const #387 = Asciz	()Lscala/collection/Iterator$;;
const #388 = Asciz	()Lscala/collection/Traversable$;;
const #389 = Asciz	scala/ScalaObject;
const #390 = class	#389;	//  scala/ScalaObject

{
public static final scala.package$ MODULE$;

public static {};
  Code:
   Stack=1, Locals=0, Args_size=0
   0:	new	#10; //class scala/package$
   3:	invokespecial	#13; //Method "<init>":()V
   6:	return

public scala.collection.IndexedSeq$ RandomAccessSeq();
  Code:
   Stack=1, Locals=1, Args_size=1
   0:	aload_0
   1:	getfield	#183; //Field RandomAccessSeq:Lscala/collection/IndexedSeq$;
   4:	areturn
  LineNumberTable: 
   line 153: 0


public scala.collection.Seq$ Sequence();
  Code:
   Stack=1, Locals=1, Args_size=1
   0:	aload_0
   1:	getfield	#181; //Field Sequence:Lscala/collection/Seq$;
   4:	areturn
  LineNumberTable: 
   line 150: 0


public scala.collection.Iterable$ Collection();
  Code:
   Stack=1, Locals=1, Args_size=1
   0:	aload_0
   1:	getfield	#179; //Field Collection:Lscala/collection/Iterable$;
   4:	areturn
  LineNumberTable: 
   line 147: 0


public scala.Tuple22 Tuple(java.lang.Object, java.lang.Object, java.lang.Object, java.lang.Object, java.lang.Object, java.lang.Object, java.lang.Object, java.lang.Object, java.lang.Object, java.lang.Object, java.lang.Object, java.lang.Object, java.lang.Object, java.lang.Object, java.lang.Object, java.lang.Object, java.lang.Object, java.lang.Object, java.lang.Object, java.lang.Object, java.lang.Object, java.lang.Object);
  Code:
   Stack=24, Locals=23, Args_size=23
   0:	new	#189; //class scala/Tuple22
   3:	dup
   4:	aload_1
   5:	aload_2
   6:	aload_3
   7:	aload	4
   9:	aload	5
   11:	aload	6
   13:	aload	7
   15:	aload	8
   17:	aload	9
   19:	aload	10
   21:	aload	11
   23:	aload	12
   25:	aload	13
   27:	aload	14
   29:	aload	15
   31:	aload	16
   33:	aload	17
   35:	aload	18
   37:	aload	19
   39:	aload	20
   41:	aload	21
   43:	aload	22
   45:	invokespecial	#192; //Method scala/Tuple22."<init>":(Ljava/lang/Object;Ljava/lang/Object;Ljava/lang/Object;Ljava/lang/Object;Ljava/lang/Object;Ljava/lang/Object;Ljava/lang/Object;Ljava/lang/Object;Ljava/lang/Object;Ljava/lang/Object;Ljava/lang/Object;Ljava/lang/Object;Ljava/lang/Object;Ljava/lang/Object;Ljava/lang/Object;Ljava/lang/Object;Ljava/lang/Object;Ljava/lang/Object;Ljava/lang/Object;Ljava/lang/Object;Ljava/lang/Object;Ljava/lang/Object;)V
   48:	areturn
  LineNumberTable: 
   line 139: 0

  LocalVariableTable: 
   Start  Length  Slot  Name   Signature
   0      49      0    this       Lscala/package$;
   0      49      1    x1       Ljava/lang/Object;
   0      49      2    x2       Ljava/lang/Object;
   0      49      3    x3       Ljava/lang/Object;
   0      49      4    x4       Ljava/lang/Object;
   0      49      5    x5       Ljava/lang/Object;
   0      49      6    x6       Ljava/lang/Object;
   0      49      7    x7       Ljava/lang/Object;
   0      49      8    x8       Ljava/lang/Object;
   0      49      9    x9       Ljava/lang/Object;
   0      49      10    x10       Ljava/lang/Object;
   0      49      11    x11       Ljava/lang/Object;
   0      49      12    x12       Ljava/lang/Object;
   0      49      13    x13       Ljava/lang/Object;
   0      49      14    x14       Ljava/lang/Object;
   0      49      15    x15       Ljava/lang/Object;
   0      49      16    x16       Ljava/lang/Object;
   0      49      17    x17       Ljava/lang/Object;
   0      49      18    x18       Ljava/lang/Object;
   0      49      19    x19       Ljava/lang/Object;
   0      49      20    x20       Ljava/lang/Object;
   0      49      21    x21       Ljava/lang/Object;
   0      49      22    x22       Ljava/lang/Object;

  Signature: length = 0x2
   00 FFFFFFDA 

public scala.Tuple21 Tuple(java.lang.Object, java.lang.Object, java.lang.Object, java.lang.Object, java.lang.Object, java.lang.Object, java.lang.Object, java.lang.Object, java.lang.Object, java.lang.Object, java.lang.Object, java.lang.Object, java.lang.Object, java.lang.Object, java.lang.Object, java.lang.Object, java.lang.Object, java.lang.Object, java.lang.Object, java.lang.Object, java.lang.Object);
  Code:
   Stack=23, Locals=22, Args_size=22
   0:	new	#222; //class scala/Tuple21
   3:	dup
   4:	aload_1
   5:	aload_2
   6:	aload_3
   7:	aload	4
   9:	aload	5
   11:	aload	6
   13:	aload	7
   15:	aload	8
   17:	aload	9
   19:	aload	10
   21:	aload	11
   23:	aload	12
   25:	aload	13
   27:	aload	14
   29:	aload	15
   31:	aload	16
   33:	aload	17
   35:	aload	18
   37:	aload	19
   39:	aload	20
   41:	aload	21
   43:	invokespecial	#225; //Method scala/Tuple21."<init>":(Ljava/lang/Object;Ljava/lang/Object;Ljava/lang/Object;Ljava/lang/Object;Ljava/lang/Object;Ljava/lang/Object;Ljava/lang/Object;Ljava/lang/Object;Ljava/lang/Object;Ljava/lang/Object;Ljava/lang/Object;Ljava/lang/Object;Ljava/lang/Object;Ljava/lang/Object;Ljava/lang/Object;Ljava/lang/Object;Ljava/lang/Object;Ljava/lang/Object;Ljava/lang/Object;Ljava/lang/Object;Ljava/lang/Object;)V
   46:	areturn
  LineNumberTable: 
   line 137: 0

  LocalVariableTable: 
   Start  Length  Slot  Name   Signature
   0      47      0    this       Lscala/package$;
   0      47      1    x1       Ljava/lang/Object;
   0      47      2    x2       Ljava/lang/Object;
   0      47      3    x3       Ljava/lang/Object;
   0      47      4    x4       Ljava/lang/Object;
   0      47      5    x5       Ljava/lang/Object;
   0      47      6    x6       Ljava/lang/Object;
   0      47      7    x7       Ljava/lang/Object;
   0      47      8    x8       Ljava/lang/Object;
   0      47      9    x9       Ljava/lang/Object;
   0      47      10    x10       Ljava/lang/Object;
   0      47      11    x11       Ljava/lang/Object;
   0      47      12    x12       Ljava/lang/Object;
   0      47      13    x13       Ljava/lang/Object;
   0      47      14    x14       Ljava/lang/Object;
   0      47      15    x15       Ljava/lang/Object;
   0      47      16    x16       Ljava/lang/Object;
   0      47      17    x17       Ljava/lang/Object;
   0      47      18    x18       Ljava/lang/Object;
   0      47      19    x19       Ljava/lang/Object;
   0      47      20    x20       Ljava/lang/Object;
   0      47      21    x21       Ljava/lang/Object;

  Signature: length = 0x2
   00 FFFFFFE2 

public scala.Tuple20 Tuple(java.lang.Object, java.lang.Object, java.lang.Object, java.lang.Object, java.lang.Object, java.lang.Object, java.lang.Object, java.lang.Object, java.lang.Object, java.lang.Object, java.lang.Object, java.lang.Object, java.lang.Object, java.lang.Object, java.lang.Object, java.lang.Object, java.lang.Object, java.lang.Object, java.lang.Object, java.lang.Object);
  Code:
   Stack=22, Locals=21, Args_size=21
   0:	new	#229; //class scala/Tuple20
   3:	dup
   4:	aload_1
   5:	aload_2
   6:	aload_3
   7:	aload	4
   9:	aload	5
   11:	aload	6
   13:	aload	7
   15:	aload	8
   17:	aload	9
   19:	aload	10
   21:	aload	11
   23:	aload	12
   25:	aload	13
   27:	aload	14
   29:	aload	15
   31:	aload	16
   33:	aload	17
   35:	aload	18
   37:	aload	19
   39:	aload	20
   41:	invokespecial	#232; //Method scala/Tuple20."<init>":(Ljava/lang/Object;Ljava/lang/Object;Ljava/lang/Object;Ljava/lang/Object;Ljava/lang/Object;Ljava/lang/Object;Ljava/lang/Object;Ljava/lang/Object;Ljava/lang/Object;Ljava/lang/Object;Ljava/lang/Object;Ljava/lang/Object;Ljava/lang/Object;Ljava/lang/Object;Ljava/lang/Object;Ljava/lang/Object;Ljava/lang/Object;Ljava/lang/Object;Ljava/lang/Object;Ljava/lang/Object;)V
   44:	areturn
  LineNumberTable: 
   line 135: 0

  LocalVariableTable: 
   Start  Length  Slot  Name   Signature
   0      45      0    this       Lscala/package$;
   0      45      1    x1       Ljava/lang/Object;
   0      45      2    x2       Ljava/lang/Object;
   0      45      3    x3       Ljava/lang/Object;
   0      45      4    x4       Ljava/lang/Object;
   0      45      5    x5       Ljava/lang/Object;
   0      45      6    x6       Ljava/lang/Object;
   0      45      7    x7       Ljava/lang/Object;
   0      45      8    x8       Ljava/lang/Object;
   0      45      9    x9       Ljava/lang/Object;
   0      45      10    x10       Ljava/lang/Object;
   0      45      11    x11       Ljava/lang/Object;
   0      45      12    x12       Ljava/lang/Object;
   0      45      13    x13       Ljava/lang/Object;
   0      45      14    x14       Ljava/lang/Object;
   0      45      15    x15       Ljava/lang/Object;
   0      45      16    x16       Ljava/lang/Object;
   0      45      17    x17       Ljava/lang/Object;
   0      45      18    x18       Ljava/lang/Object;
   0      45      19    x19       Ljava/lang/Object;
   0      45      20    x20       Ljava/lang/Object;

  Signature: length = 0x2
   00 FFFFFFE9 

public scala.Tuple19 Tuple(java.lang.Object, java.lang.Object, java.lang.Object, java.lang.Object, java.lang.Object, java.lang.Object, java.lang.Object, java.lang.Object, java.lang.Object, java.lang.Object, java.lang.Object, java.lang.Object, java.lang.Object, java.lang.Object, java.lang.Object, java.lang.Object, java.lang.Object, java.lang.Object, java.lang.Object);
  Code:
   Stack=21, Locals=20, Args_size=20
   0:	new	#236; //class scala/Tuple19
   3:	dup
   4:	aload_1
   5:	aload_2
   6:	aload_3
   7:	aload	4
   9:	aload	5
   11:	aload	6
   13:	aload	7
   15:	aload	8
   17:	aload	9
   19:	aload	10
   21:	aload	11
   23:	aload	12
   25:	aload	13
   27:	aload	14
   29:	aload	15
   31:	aload	16
   33:	aload	17
   35:	aload	18
   37:	aload	19
   39:	invokespecial	#239; //Method scala/Tuple19."<init>":(Ljava/lang/Object;Ljava/lang/Object;Ljava/lang/Object;Ljava/lang/Object;Ljava/lang/Object;Ljava/lang/Object;Ljava/lang/Object;Ljava/lang/Object;Ljava/lang/Object;Ljava/lang/Object;Ljava/lang/Object;Ljava/lang/Object;Ljava/lang/Object;Ljava/lang/Object;Ljava/lang/Object;Ljava/lang/Object;Ljava/lang/Object;Ljava/lang/Object;Ljava/lang/Object;)V
   42:	areturn
  LineNumberTable: 
   line 133: 0

  LocalVariableTable: 
   Start  Length  Slot  Name   Signature
   0      43      0    this       Lscala/package$;
   0      43      1    x1       Ljava/lang/Object;
   0      43      2    x2       Ljava/lang/Object;
   0      43      3    x3       Ljava/lang/Object;
   0      43      4    x4       Ljava/lang/Object;
   0      43      5    x5       Ljava/lang/Object;
   0      43      6    x6       Ljava/lang/Object;
   0      43      7    x7       Ljava/lang/Object;
   0      43      8    x8       Ljava/lang/Object;
   0      43      9    x9       Ljava/lang/Object;
   0      43      10    x10       Ljava/lang/Object;
   0      43      11    x11       Ljava/lang/Object;
   0      43      12    x12       Ljava/lang/Object;
   0      43      13    x13       Ljava/lang/Object;
   0      43      14    x14       Ljava/lang/Object;
   0      43      15    x15       Ljava/lang/Object;
   0      43      16    x16       Ljava/lang/Object;
   0      43      17    x17       Ljava/lang/Object;
   0      43      18    x18       Ljava/lang/Object;
   0      43      19    x19       Ljava/lang/Object;

  Signature: length = 0x2
   00 FFFFFFF0 

public scala.Tuple18 Tuple(java.lang.Object, java.lang.Object, java.lang.Object, java.lang.Object, java.lang.Object, java.lang.Object, java.lang.Object, java.lang.Object, java.lang.Object, java.lang.Object, java.lang.Object, java.lang.Object, java.lang.Object, java.lang.Object, java.lang.Object, java.lang.Object, java.lang.Object, java.lang.Object);
  Code:
   Stack=20, Locals=19, Args_size=19
   0:	new	#243; //class scala/Tuple18
   3:	dup
   4:	aload_1
   5:	aload_2
   6:	aload_3
   7:	aload	4
   9:	aload	5
   11:	aload	6
   13:	aload	7
   15:	aload	8
   17:	aload	9
   19:	aload	10
   21:	aload	11
   23:	aload	12
   25:	aload	13
   27:	aload	14
   29:	aload	15
   31:	aload	16
   33:	aload	17
   35:	aload	18
   37:	invokespecial	#246; //Method scala/Tuple18."<init>":(Ljava/lang/Object;Ljava/lang/Object;Ljava/lang/Object;Ljava/lang/Object;Ljava/lang/Object;Ljava/lang/Object;Ljava/lang/Object;Ljava/lang/Object;Ljava/lang/Object;Ljava/lang/Object;Ljava/lang/Object;Ljava/lang/Object;Ljava/lang/Object;Ljava/lang/Object;Ljava/lang/Object;Ljava/lang/Object;Ljava/lang/Object;Ljava/lang/Object;)V
   40:	areturn
  LineNumberTable: 
   line 131: 0

  LocalVariableTable: 
   Start  Length  Slot  Name   Signature
   0      41      0    this       Lscala/package$;
   0      41      1    x1       Ljava/lang/Object;
   0      41      2    x2       Ljava/lang/Object;
   0      41      3    x3       Ljava/lang/Object;
   0      41      4    x4       Ljava/lang/Object;
   0      41      5    x5       Ljava/lang/Object;
   0      41      6    x6       Ljava/lang/Object;
   0      41      7    x7       Ljava/lang/Object;
   0      41      8    x8       Ljava/lang/Object;
   0      41      9    x9       Ljava/lang/Object;
   0      41      10    x10       Ljava/lang/Object;
   0      41      11    x11       Ljava/lang/Object;
   0      41      12    x12       Ljava/lang/Object;
   0      41      13    x13       Ljava/lang/Object;
   0      41      14    x14       Ljava/lang/Object;
   0      41      15    x15       Ljava/lang/Object;
   0      41      16    x16       Ljava/lang/Object;
   0      41      17    x17       Ljava/lang/Object;
   0      41      18    x18       Ljava/lang/Object;

  Signature: length = 0x2
   00 FFFFFFF7 

public scala.Tuple17 Tuple(java.lang.Object, java.lang.Object, java.lang.Object, java.lang.Object, java.lang.Object, java.lang.Object, java.lang.Object, java.lang.Object, java.lang.Object, java.lang.Object, java.lang.Object, java.lang.Object, java.lang.Object, java.lang.Object, java.lang.Object, java.lang.Object, java.lang.Object);
  Code:
   Stack=19, Locals=18, Args_size=18
   0:	new	#250; //class scala/Tuple17
   3:	dup
   4:	aload_1
   5:	aload_2
   6:	aload_3
   7:	aload	4
   9:	aload	5
   11:	aload	6
   13:	aload	7
   15:	aload	8
   17:	aload	9
   19:	aload	10
   21:	aload	11
   23:	aload	12
   25:	aload	13
   27:	aload	14
   29:	aload	15
   31:	aload	16
   33:	aload	17
   35:	invokespecial	#253; //Method scala/Tuple17."<init>":(Ljava/lang/Object;Ljava/lang/Object;Ljava/lang/Object;Ljava/lang/Object;Ljava/lang/Object;Ljava/lang/Object;Ljava/lang/Object;Ljava/lang/Object;Ljava/lang/Object;Ljava/lang/Object;Ljava/lang/Object;Ljava/lang/Object;Ljava/lang/Object;Ljava/lang/Object;Ljava/lang/Object;Ljava/lang/Object;Ljava/lang/Object;)V
   38:	areturn
  LineNumberTable: 
   line 129: 0

  LocalVariableTable: 
   Start  Length  Slot  Name   Signature
   0      39      0    this       Lscala/package$;
   0      39      1    x1       Ljava/lang/Object;
   0      39      2    x2       Ljava/lang/Object;
   0      39      3    x3       Ljava/lang/Object;
   0      39      4    x4       Ljava/lang/Object;
   0      39      5    x5       Ljava/lang/Object;
   0      39      6    x6       Ljava/lang/Object;
   0      39      7    x7       Ljava/lang/Object;
   0      39      8    x8       Ljava/lang/Object;
   0      39      9    x9       Ljava/lang/Object;
   0      39      10    x10       Ljava/lang/Object;
   0      39      11    x11       Ljava/lang/Object;
   0      39      12    x12       Ljava/lang/Object;
   0      39      13    x13       Ljava/lang/Object;
   0      39      14    x14       Ljava/lang/Object;
   0      39      15    x15       Ljava/lang/Object;
   0      39      16    x16       Ljava/lang/Object;
   0      39      17    x17       Ljava/lang/Object;

  Signature: length = 0x2
   00 FFFFFFFE 

public scala.Tuple16 Tuple(java.lang.Object, java.lang.Object, java.lang.Object, java.lang.Object, java.lang.Object, java.lang.Object, java.lang.Object, java.lang.Object, java.lang.Object, java.lang.Object, java.lang.Object, java.lang.Object, java.lang.Object, java.lang.Object, java.lang.Object, java.lang.Object);
  Code:
   Stack=18, Locals=17, Args_size=17
   0:	new	#257; //class scala/Tuple16
   3:	dup
   4:	aload_1
   5:	aload_2
   6:	aload_3
   7:	aload	4
   9:	aload	5
   11:	aload	6
   13:	aload	7
   15:	aload	8
   17:	aload	9
   19:	aload	10
   21:	aload	11
   23:	aload	12
   25:	aload	13
   27:	aload	14
   29:	aload	15
   31:	aload	16
   33:	invokespecial	#260; //Method scala/Tuple16."<init>":(Ljava/lang/Object;Ljava/lang/Object;Ljava/lang/Object;Ljava/lang/Object;Ljava/lang/Object;Ljava/lang/Object;Ljava/lang/Object;Ljava/lang/Object;Ljava/lang/Object;Ljava/lang/Object;Ljava/lang/Object;Ljava/lang/Object;Ljava/lang/Object;Ljava/lang/Object;Ljava/lang/Object;Ljava/lang/Object;)V
   36:	areturn
  LineNumberTable: 
   line 127: 0

  LocalVariableTable: 
   Start  Length  Slot  Name   Signature
   0      37      0    this       Lscala/package$;
   0      37      1    x1       Ljava/lang/Object;
   0      37      2    x2       Ljava/lang/Object;
   0      37      3    x3       Ljava/lang/Object;
   0      37      4    x4       Ljava/lang/Object;
   0      37      5    x5       Ljava/lang/Object;
   0      37      6    x6       Ljava/lang/Object;
   0      37      7    x7       Ljava/lang/Object;
   0      37      8    x8       Ljava/lang/Object;
   0      37      9    x9       Ljava/lang/Object;
   0      37      10    x10       Ljava/lang/Object;
   0      37      11    x11       Ljava/lang/Object;
   0      37      12    x12       Ljava/lang/Object;
   0      37      13    x13       Ljava/lang/Object;
   0      37      14    x14       Ljava/lang/Object;
   0      37      15    x15       Ljava/lang/Object;
   0      37      16    x16       Ljava/lang/Object;

  Signature: length = 0x2
   01 05 

public scala.Tuple15 Tuple(java.lang.Object, java.lang.Object, java.lang.Object, java.lang.Object, java.lang.Object, java.lang.Object, java.lang.Object, java.lang.Object, java.lang.Object, java.lang.Object, java.lang.Object, java.lang.Object, java.lang.Object, java.lang.Object, java.lang.Object);
  Code:
   Stack=17, Locals=16, Args_size=16
   0:	new	#264; //class scala/Tuple15
   3:	dup
   4:	aload_1
   5:	aload_2
   6:	aload_3
   7:	aload	4
   9:	aload	5
   11:	aload	6
   13:	aload	7
   15:	aload	8
   17:	aload	9
   19:	aload	10
   21:	aload	11
   23:	aload	12
   25:	aload	13
   27:	aload	14
   29:	aload	15
   31:	invokespecial	#267; //Method scala/Tuple15."<init>":(Ljava/lang/Object;Ljava/lang/Object;Ljava/lang/Object;Ljava/lang/Object;Ljava/lang/Object;Ljava/lang/Object;Ljava/lang/Object;Ljava/lang/Object;Ljava/lang/Object;Ljava/lang/Object;Ljava/lang/Object;Ljava/lang/Object;Ljava/lang/Object;Ljava/lang/Object;Ljava/lang/Object;)V
   34:	areturn
  LineNumberTable: 
   line 125: 0

  LocalVariableTable: 
   Start  Length  Slot  Name   Signature
   0      35      0    this       Lscala/package$;
   0      35      1    x1       Ljava/lang/Object;
   0      35      2    x2       Ljava/lang/Object;
   0      35      3    x3       Ljava/lang/Object;
   0      35      4    x4       Ljava/lang/Object;
   0      35      5    x5       Ljava/lang/Object;
   0      35      6    x6       Ljava/lang/Object;
   0      35      7    x7       Ljava/lang/Object;
   0      35      8    x8       Ljava/lang/Object;
   0      35      9    x9       Ljava/lang/Object;
   0      35      10    x10       Ljava/lang/Object;
   0      35      11    x11       Ljava/lang/Object;
   0      35      12    x12       Ljava/lang/Object;
   0      35      13    x13       Ljava/lang/Object;
   0      35      14    x14       Ljava/lang/Object;
   0      35      15    x15       Ljava/lang/Object;

  Signature: length = 0x2
   01 0C 

public scala.Tuple14 Tuple(java.lang.Object, java.lang.Object, java.lang.Object, java.lang.Object, java.lang.Object, java.lang.Object, java.lang.Object, java.lang.Object, java.lang.Object, java.lang.Object, java.lang.Object, java.lang.Object, java.lang.Object, java.lang.Object);
  Code:
   Stack=16, Locals=15, Args_size=15
   0:	new	#271; //class scala/Tuple14
   3:	dup
   4:	aload_1
   5:	aload_2
   6:	aload_3
   7:	aload	4
   9:	aload	5
   11:	aload	6
   13:	aload	7
   15:	aload	8
   17:	aload	9
   19:	aload	10
   21:	aload	11
   23:	aload	12
   25:	aload	13
   27:	aload	14
   29:	invokespecial	#274; //Method scala/Tuple14."<init>":(Ljava/lang/Object;Ljava/lang/Object;Ljava/lang/Object;Ljava/lang/Object;Ljava/lang/Object;Ljava/lang/Object;Ljava/lang/Object;Ljava/lang/Object;Ljava/lang/Object;Ljava/lang/Object;Ljava/lang/Object;Ljava/lang/Object;Ljava/lang/Object;Ljava/lang/Object;)V
   32:	areturn
  LineNumberTable: 
   line 123: 0

  LocalVariableTable: 
   Start  Length  Slot  Name   Signature
   0      33      0    this       Lscala/package$;
   0      33      1    x1       Ljava/lang/Object;
   0      33      2    x2       Ljava/lang/Object;
   0      33      3    x3       Ljava/lang/Object;
   0      33      4    x4       Ljava/lang/Object;
   0      33      5    x5       Ljava/lang/Object;
   0      33      6    x6       Ljava/lang/Object;
   0      33      7    x7       Ljava/lang/Object;
   0      33      8    x8       Ljava/lang/Object;
   0      33      9    x9       Ljava/lang/Object;
   0      33      10    x10       Ljava/lang/Object;
   0      33      11    x11       Ljava/lang/Object;
   0      33      12    x12       Ljava/lang/Object;
   0      33      13    x13       Ljava/lang/Object;
   0      33      14    x14       Ljava/lang/Object;

  Signature: length = 0x2
   01 13 

public scala.Tuple13 Tuple(java.lang.Object, java.lang.Object, java.lang.Object, java.lang.Object, java.lang.Object, java.lang.Object, java.lang.Object, java.lang.Object, java.lang.Object, java.lang.Object, java.lang.Object, java.lang.Object, java.lang.Object);
  Code:
   Stack=15, Locals=14, Args_size=14
   0:	new	#278; //class scala/Tuple13
   3:	dup
   4:	aload_1
   5:	aload_2
   6:	aload_3
   7:	aload	4
   9:	aload	5
   11:	aload	6
   13:	aload	7
   15:	aload	8
   17:	aload	9
   19:	aload	10
   21:	aload	11
   23:	aload	12
   25:	aload	13
   27:	invokespecial	#281; //Method scala/Tuple13."<init>":(Ljava/lang/Object;Ljava/lang/Object;Ljava/lang/Object;Ljava/lang/Object;Ljava/lang/Object;Ljava/lang/Object;Ljava/lang/Object;Ljava/lang/Object;Ljava/lang/Object;Ljava/lang/Object;Ljava/lang/Object;Ljava/lang/Object;Ljava/lang/Object;)V
   30:	areturn
  LineNumberTable: 
   line 121: 0

  LocalVariableTable: 
   Start  Length  Slot  Name   Signature
   0      31      0    this       Lscala/package$;
   0      31      1    x1       Ljava/lang/Object;
   0      31      2    x2       Ljava/lang/Object;
   0      31      3    x3       Ljava/lang/Object;
   0      31      4    x4       Ljava/lang/Object;
   0      31      5    x5       Ljava/lang/Object;
   0      31      6    x6       Ljava/lang/Object;
   0      31      7    x7       Ljava/lang/Object;
   0      31      8    x8       Ljava/lang/Object;
   0      31      9    x9       Ljava/lang/Object;
   0      31      10    x10       Ljava/lang/Object;
   0      31      11    x11       Ljava/lang/Object;
   0      31      12    x12       Ljava/lang/Object;
   0      31      13    x13       Ljava/lang/Object;

  Signature: length = 0x2
   01 1A 

public scala.Tuple12 Tuple(java.lang.Object, java.lang.Object, java.lang.Object, java.lang.Object, java.lang.Object, java.lang.Object, java.lang.Object, java.lang.Object, java.lang.Object, java.lang.Object, java.lang.Object, java.lang.Object);
  Code:
   Stack=14, Locals=13, Args_size=13
   0:	new	#285; //class scala/Tuple12
   3:	dup
   4:	aload_1
   5:	aload_2
   6:	aload_3
   7:	aload	4
   9:	aload	5
   11:	aload	6
   13:	aload	7
   15:	aload	8
   17:	aload	9
   19:	aload	10
   21:	aload	11
   23:	aload	12
   25:	invokespecial	#288; //Method scala/Tuple12."<init>":(Ljava/lang/Object;Ljava/lang/Object;Ljava/lang/Object;Ljava/lang/Object;Ljava/lang/Object;Ljava/lang/Object;Ljava/lang/Object;Ljava/lang/Object;Ljava/lang/Object;Ljava/lang/Object;Ljava/lang/Object;Ljava/lang/Object;)V
   28:	areturn
  LineNumberTable: 
   line 119: 0

  LocalVariableTable: 
   Start  Length  Slot  Name   Signature
   0      29      0    this       Lscala/package$;
   0      29      1    x1       Ljava/lang/Object;
   0      29      2    x2       Ljava/lang/Object;
   0      29      3    x3       Ljava/lang/Object;
   0      29      4    x4       Ljava/lang/Object;
   0      29      5    x5       Ljava/lang/Object;
   0      29      6    x6       Ljava/lang/Object;
   0      29      7    x7       Ljava/lang/Object;
   0      29      8    x8       Ljava/lang/Object;
   0      29      9    x9       Ljava/lang/Object;
   0      29      10    x10       Ljava/lang/Object;
   0      29      11    x11       Ljava/lang/Object;
   0      29      12    x12       Ljava/lang/Object;

  Signature: length = 0x2
   01 21 

public scala.Tuple11 Tuple(java.lang.Object, java.lang.Object, java.lang.Object, java.lang.Object, java.lang.Object, java.lang.Object, java.lang.Object, java.lang.Object, java.lang.Object, java.lang.Object, java.lang.Object);
  Code:
   Stack=13, Locals=12, Args_size=12
   0:	new	#292; //class scala/Tuple11
   3:	dup
   4:	aload_1
   5:	aload_2
   6:	aload_3
   7:	aload	4
   9:	aload	5
   11:	aload	6
   13:	aload	7
   15:	aload	8
   17:	aload	9
   19:	aload	10
   21:	aload	11
   23:	invokespecial	#295; //Method scala/Tuple11."<init>":(Ljava/lang/Object;Ljava/lang/Object;Ljava/lang/Object;Ljava/lang/Object;Ljava/lang/Object;Ljava/lang/Object;Ljava/lang/Object;Ljava/lang/Object;Ljava/lang/Object;Ljava/lang/Object;Ljava/lang/Object;)V
   26:	areturn
  LineNumberTable: 
   line 117: 0

  LocalVariableTable: 
   Start  Length  Slot  Name   Signature
   0      27      0    this       Lscala/package$;
   0      27      1    x1       Ljava/lang/Object;
   0      27      2    x2       Ljava/lang/Object;
   0      27      3    x3       Ljava/lang/Object;
   0      27      4    x4       Ljava/lang/Object;
   0      27      5    x5       Ljava/lang/Object;
   0      27      6    x6       Ljava/lang/Object;
   0      27      7    x7       Ljava/lang/Object;
   0      27      8    x8       Ljava/lang/Object;
   0      27      9    x9       Ljava/lang/Object;
   0      27      10    x10       Ljava/lang/Object;
   0      27      11    x11       Ljava/lang/Object;

  Signature: length = 0x2
   01 28 

public scala.Tuple10 Tuple(java.lang.Object, java.lang.Object, java.lang.Object, java.lang.Object, java.lang.Object, java.lang.Object, java.lang.Object, java.lang.Object, java.lang.Object, java.lang.Object);
  Code:
   Stack=12, Locals=11, Args_size=11
   0:	new	#299; //class scala/Tuple10
   3:	dup
   4:	aload_1
   5:	aload_2
   6:	aload_3
   7:	aload	4
   9:	aload	5
   11:	aload	6
   13:	aload	7
   15:	aload	8
   17:	aload	9
   19:	aload	10
   21:	invokespecial	#302; //Method scala/Tuple10."<init>":(Ljava/lang/Object;Ljava/lang/Object;Ljava/lang/Object;Ljava/lang/Object;Ljava/lang/Object;Ljava/lang/Object;Ljava/lang/Object;Ljava/lang/Object;Ljava/lang/Object;Ljava/lang/Object;)V
   24:	areturn
  LineNumberTable: 
   line 115: 0

  LocalVariableTable: 
   Start  Length  Slot  Name   Signature
   0      25      0    this       Lscala/package$;
   0      25      1    x1       Ljava/lang/Object;
   0      25      2    x2       Ljava/lang/Object;
   0      25      3    x3       Ljava/lang/Object;
   0      25      4    x4       Ljava/lang/Object;
   0      25      5    x5       Ljava/lang/Object;
   0      25      6    x6       Ljava/lang/Object;
   0      25      7    x7       Ljava/lang/Object;
   0      25      8    x8       Ljava/lang/Object;
   0      25      9    x9       Ljava/lang/Object;
   0      25      10    x10       Ljava/lang/Object;

  Signature: length = 0x2
   01 2F 

public scala.Tuple9 Tuple(java.lang.Object, java.lang.Object, java.lang.Object, java.lang.Object, java.lang.Object, java.lang.Object, java.lang.Object, java.lang.Object, java.lang.Object);
  Code:
   Stack=11, Locals=10, Args_size=10
   0:	new	#306; //class scala/Tuple9
   3:	dup
   4:	aload_1
   5:	aload_2
   6:	aload_3
   7:	aload	4
   9:	aload	5
   11:	aload	6
   13:	aload	7
   15:	aload	8
   17:	aload	9
   19:	invokespecial	#309; //Method scala/Tuple9."<init>":(Ljava/lang/Object;Ljava/lang/Object;Ljava/lang/Object;Ljava/lang/Object;Ljava/lang/Object;Ljava/lang/Object;Ljava/lang/Object;Ljava/lang/Object;Ljava/lang/Object;)V
   22:	areturn
  LineNumberTable: 
   line 113: 0

  LocalVariableTable: 
   Start  Length  Slot  Name   Signature
   0      23      0    this       Lscala/package$;
   0      23      1    x1       Ljava/lang/Object;
   0      23      2    x2       Ljava/lang/Object;
   0      23      3    x3       Ljava/lang/Object;
   0      23      4    x4       Ljava/lang/Object;
   0      23      5    x5       Ljava/lang/Object;
   0      23      6    x6       Ljava/lang/Object;
   0      23      7    x7       Ljava/lang/Object;
   0      23      8    x8       Ljava/lang/Object;
   0      23      9    x9       Ljava/lang/Object;

  Signature: length = 0x2
   01 36 

public scala.Tuple8 Tuple(java.lang.Object, java.lang.Object, java.lang.Object, java.lang.Object, java.lang.Object, java.lang.Object, java.lang.Object, java.lang.Object);
  Code:
   Stack=10, Locals=9, Args_size=9
   0:	new	#313; //class scala/Tuple8
   3:	dup
   4:	aload_1
   5:	aload_2
   6:	aload_3
   7:	aload	4
   9:	aload	5
   11:	aload	6
   13:	aload	7
   15:	aload	8
   17:	invokespecial	#316; //Method scala/Tuple8."<init>":(Ljava/lang/Object;Ljava/lang/Object;Ljava/lang/Object;Ljava/lang/Object;Ljava/lang/Object;Ljava/lang/Object;Ljava/lang/Object;Ljava/lang/Object;)V
   20:	areturn
  LineNumberTable: 
   line 111: 0

  LocalVariableTable: 
   Start  Length  Slot  Name   Signature
   0      21      0    this       Lscala/package$;
   0      21      1    x1       Ljava/lang/Object;
   0      21      2    x2       Ljava/lang/Object;
   0      21      3    x3       Ljava/lang/Object;
   0      21      4    x4       Ljava/lang/Object;
   0      21      5    x5       Ljava/lang/Object;
   0      21      6    x6       Ljava/lang/Object;
   0      21      7    x7       Ljava/lang/Object;
   0      21      8    x8       Ljava/lang/Object;

  Signature: length = 0x2
   01 3D 

public scala.Tuple7 Tuple(java.lang.Object, java.lang.Object, java.lang.Object, java.lang.Object, java.lang.Object, java.lang.Object, java.lang.Object);
  Code:
   Stack=9, Locals=8, Args_size=8
   0:	new	#320; //class scala/Tuple7
   3:	dup
   4:	aload_1
   5:	aload_2
   6:	aload_3
   7:	aload	4
   9:	aload	5
   11:	aload	6
   13:	aload	7
   15:	invokespecial	#323; //Method scala/Tuple7."<init>":(Ljava/lang/Object;Ljava/lang/Object;Ljava/lang/Object;Ljava/lang/Object;Ljava/lang/Object;Ljava/lang/Object;Ljava/lang/Object;)V
   18:	areturn
  LineNumberTable: 
   line 109: 0

  LocalVariableTable: 
   Start  Length  Slot  Name   Signature
   0      19      0    this       Lscala/package$;
   0      19      1    x1       Ljava/lang/Object;
   0      19      2    x2       Ljava/lang/Object;
   0      19      3    x3       Ljava/lang/Object;
   0      19      4    x4       Ljava/lang/Object;
   0      19      5    x5       Ljava/lang/Object;
   0      19      6    x6       Ljava/lang/Object;
   0      19      7    x7       Ljava/lang/Object;

  Signature: length = 0x2
   01 44 

public scala.Tuple6 Tuple(java.lang.Object, java.lang.Object, java.lang.Object, java.lang.Object, java.lang.Object, java.lang.Object);
  Code:
   Stack=8, Locals=7, Args_size=7
   0:	new	#327; //class scala/Tuple6
   3:	dup
   4:	aload_1
   5:	aload_2
   6:	aload_3
   7:	aload	4
   9:	aload	5
   11:	aload	6
   13:	invokespecial	#330; //Method scala/Tuple6."<init>":(Ljava/lang/Object;Ljava/lang/Object;Ljava/lang/Object;Ljava/lang/Object;Ljava/lang/Object;Ljava/lang/Object;)V
   16:	areturn
  LineNumberTable: 
   line 107: 0

  LocalVariableTable: 
   Start  Length  Slot  Name   Signature
   0      17      0    this       Lscala/package$;
   0      17      1    x1       Ljava/lang/Object;
   0      17      2    x2       Ljava/lang/Object;
   0      17      3    x3       Ljava/lang/Object;
   0      17      4    x4       Ljava/lang/Object;
   0      17      5    x5       Ljava/lang/Object;
   0      17      6    x6       Ljava/lang/Object;

  Signature: length = 0x2
   01 4B 

public scala.Tuple5 Tuple(java.lang.Object, java.lang.Object, java.lang.Object, java.lang.Object, java.lang.Object);
  Code:
   Stack=7, Locals=6, Args_size=6
   0:	new	#334; //class scala/Tuple5
   3:	dup
   4:	aload_1
   5:	aload_2
   6:	aload_3
   7:	aload	4
   9:	aload	5
   11:	invokespecial	#337; //Method scala/Tuple5."<init>":(Ljava/lang/Object;Ljava/lang/Object;Ljava/lang/Object;Ljava/lang/Object;Ljava/lang/Object;)V
   14:	areturn
  LineNumberTable: 
   line 105: 0

  LocalVariableTable: 
   Start  Length  Slot  Name   Signature
   0      15      0    this       Lscala/package$;
   0      15      1    x1       Ljava/lang/Object;
   0      15      2    x2       Ljava/lang/Object;
   0      15      3    x3       Ljava/lang/Object;
   0      15      4    x4       Ljava/lang/Object;
   0      15      5    x5       Ljava/lang/Object;

  Signature: length = 0x2
   01 52 

public scala.Tuple4 Tuple(java.lang.Object, java.lang.Object, java.lang.Object, java.lang.Object);
  Code:
   Stack=6, Locals=5, Args_size=5
   0:	new	#341; //class scala/Tuple4
   3:	dup
   4:	aload_1
   5:	aload_2
   6:	aload_3
   7:	aload	4
   9:	invokespecial	#344; //Method scala/Tuple4."<init>":(Ljava/lang/Object;Ljava/lang/Object;Ljava/lang/Object;Ljava/lang/Object;)V
   12:	areturn
  LineNumberTable: 
   line 103: 0

  LocalVariableTable: 
   Start  Length  Slot  Name   Signature
   0      13      0    this       Lscala/package$;
   0      13      1    x1       Ljava/lang/Object;
   0      13      2    x2       Ljava/lang/Object;
   0      13      3    x3       Ljava/lang/Object;
   0      13      4    x4       Ljava/lang/Object;

  Signature: length = 0x2
   01 59 

public scala.Tuple3 Tuple(java.lang.Object, java.lang.Object, java.lang.Object);
  Code:
   Stack=5, Locals=4, Args_size=4
   0:	new	#348; //class scala/Tuple3
   3:	dup
   4:	aload_1
   5:	aload_2
   6:	aload_3
   7:	invokespecial	#351; //Method scala/Tuple3."<init>":(Ljava/lang/Object;Ljava/lang/Object;Ljava/lang/Object;)V
   10:	areturn
  LineNumberTable: 
   line 101: 0

  LocalVariableTable: 
   Start  Length  Slot  Name   Signature
   0      11      0    this       Lscala/package$;
   0      11      1    x1       Ljava/lang/Object;
   0      11      2    x2       Ljava/lang/Object;
   0      11      3    x3       Ljava/lang/Object;

  Signature: length = 0x2
   01 60 

public scala.Tuple2 Tuple(java.lang.Object, java.lang.Object);
  Code:
   Stack=4, Locals=3, Args_size=3
   0:	new	#355; //class scala/Tuple2
   3:	dup
   4:	aload_1
   5:	aload_2
   6:	invokespecial	#358; //Method scala/Tuple2."<init>":(Ljava/lang/Object;Ljava/lang/Object;)V
   9:	areturn
  LineNumberTable: 
   line 99: 0

  LocalVariableTable: 
   Start  Length  Slot  Name   Signature
   0      10      0    this       Lscala/package$;
   0      10      1    x1       Ljava/lang/Object;
   0      10      2    x2       Ljava/lang/Object;

  Signature: length = 0x2
   01 67 

public scala.Tuple1 Tuple(java.lang.Object);
  Code:
   Stack=3, Locals=2, Args_size=2
   0:	new	#362; //class scala/Tuple1
   3:	dup
   4:	aload_1
   5:	invokespecial	#365; //Method scala/Tuple1."<init>":(Ljava/lang/Object;)V
   8:	areturn
  LineNumberTable: 
   line 97: 0

  LocalVariableTable: 
   Start  Length  Slot  Name   Signature
   0      9      0    this       Lscala/package$;
   0      9      1    x1       Ljava/lang/Object;

  Signature: length = 0x2
   01 6E 

public scala.math.Ordering$ Ordering();
  Code:
   Stack=1, Locals=1, Args_size=1
   0:	aload_0
   1:	getfield	#174; //Field Ordering:Lscala/math/Ordering$;
   4:	areturn
  LineNumberTable: 
   line 91: 0


public scala.math.Ordered$ Ordered();
  Code:
   Stack=1, Locals=1, Args_size=1
   0:	aload_0
   1:	getfield	#168; //Field Ordered:Lscala/math/Ordered$;
   4:	areturn
  LineNumberTable: 
   line 88: 0


public scala.math.Numeric$ Numeric();
  Code:
   Stack=1, Locals=1, Args_size=1
   0:	aload_0
   1:	getfield	#162; //Field Numeric:Lscala/math/Numeric$;
   4:	areturn
  LineNumberTable: 
   line 85: 0


public scala.math.BigInt$ BigInt();
  Code:
   Stack=1, Locals=1, Args_size=1
   0:	aload_0
   1:	getfield	#156; //Field BigInt:Lscala/math/BigInt$;
   4:	areturn
  LineNumberTable: 
   line 78: 0


public scala.math.BigDecimal$ BigDecimal();
  Code:
   Stack=1, Locals=1, Args_size=1
   0:	aload_0
   1:	getfield	#150; //Field BigDecimal:Lscala/math/BigDecimal$;
   4:	areturn
  LineNumberTable: 
   line 75: 0


public java.lang.Thread currentThread();
  Code:
   Stack=1, Locals=1, Args_size=1
   0:	invokestatic	#377; //Method java/lang/Thread.currentThread:()Ljava/lang/Thread;
   3:	areturn
  LineNumberTable: 
   line 70: 0


public scala.xml.TopScope$ $scope();
  Code:
   Stack=1, Locals=1, Args_size=1
   0:	aload_0
   1:	getfield	#144; //Field $scope:Lscala/xml/TopScope$;
   4:	areturn
  LineNumberTable: 
   line 69: 0


public scala.collection.immutable.Range$ Range();
  Code:
   Stack=1, Locals=1, Args_size=1
   0:	aload_0
   1:	getfield	#138; //Field Range:Lscala/collection/immutable/Range$;
   4:	areturn
  LineNumberTable: 
   line 65: 0


public scala.collection.mutable.StringBuilder$ StringBuilder();
  Code:
   Stack=1, Locals=1, Args_size=1
   0:	aload_0
   1:	getfield	#132; //Field StringBuilder:Lscala/collection/mutable/StringBuilder$;
   4:	areturn
  LineNumberTable: 
   line 62: 0


public scala.collection.immutable.Vector$ Vector();
  Code:
   Stack=1, Locals=1, Args_size=1
   0:	aload_0
   1:	getfield	#126; //Field Vector:Lscala/collection/immutable/Vector$;
   4:	areturn
  LineNumberTable: 
   line 59: 0


public scala.collection.immutable.Stream$$hash$colon$colon$ $hash$colon$colon();
  Code:
   Stack=1, Locals=1, Args_size=1
   0:	aload_0
   1:	getfield	#120; //Field $hash$colon$colon:Lscala/collection/immutable/Stream$$hash$colon$colon$;
   4:	areturn
  LineNumberTable: 
   line 56: 0


public scala.collection.immutable.Stream$ Stream();
  Code:
   Stack=1, Locals=1, Args_size=1
   0:	aload_0
   1:	getfield	#114; //Field Stream:Lscala/collection/immutable/Stream$;
   4:	areturn
  LineNumberTable: 
   line 55: 0


public scala.collection.immutable.$colon$colon$ $colon$colon();
  Code:
   Stack=1, Locals=1, Args_size=1
   0:	aload_0
   1:	getfield	#108; //Field $colon$colon:Lscala/collection/immutable/$colon$colon$;
   4:	areturn
  LineNumberTable: 
   line 52: 0


public scala.collection.immutable.Nil$ Nil();
  Code:
   Stack=1, Locals=1, Args_size=1
   0:	aload_0
   1:	getfield	#102; //Field Nil:Lscala/collection/immutable/Nil$;
   4:	areturn
  LineNumberTable: 
   line 49: 0


public scala.collection.immutable.List$ List();
  Code:
   Stack=1, Locals=1, Args_size=1
   0:	aload_0
   1:	getfield	#96; //Field List:Lscala/collection/immutable/List$;
   4:	areturn
  LineNumberTable: 
   line 47: 0


public scala.collection.Iterator$ Iterator();
  Code:
   Stack=1, Locals=1, Args_size=1
   0:	aload_0
   1:	getfield	#90; //Field Iterator:Lscala/collection/Iterator$;
   4:	areturn
  LineNumberTable: 
   line 42: 0


public scala.collection.IndexedSeq$ IndexedSeq();
  Code:
   Stack=1, Locals=1, Args_size=1
   0:	aload_0
   1:	getfield	#84; //Field IndexedSeq:Lscala/collection/IndexedSeq$;
   4:	areturn
  LineNumberTable: 
   line 39: 0


public scala.collection.Seq$ Seq();
  Code:
   Stack=1, Locals=1, Args_size=1
   0:	aload_0
   1:	getfield	#78; //Field Seq:Lscala/collection/Seq$;
   4:	areturn
  LineNumberTable: 
   line 36: 0


public scala.collection.Iterable$ Iterable();
  Code:
   Stack=1, Locals=1, Args_size=1
   0:	aload_0
   1:	getfield	#72; //Field Iterable:Lscala/collection/Iterable$;
   4:	areturn
  LineNumberTable: 
   line 33: 0


public scala.collection.Traversable$ Traversable();
  Code:
   Stack=1, Locals=1, Args_size=1
   0:	aload_0
   1:	getfield	#66; //Field Traversable:Lscala/collection/Traversable$;
   4:	areturn
  LineNumberTable: 
   line 30: 0


}

