Compiled from "PartialOrdering.scala"
public final class scala.PartialOrdering$$anon$1 extends java.lang.Object implements scala.PartialOrdering
  SourceFile: "PartialOrdering.scala"
  Signature: length = 0x2
   00 39 
  Scala: length = 0x
   
  InnerClass: 
   public final #60= #15 of #34; //$anon$1=class scala/PartialOrdering$$anon$1 of class scala/PartialOrdering
  minor version: 0
  major version: 49
  Constant pool:
const #1 = Asciz	SourceFile;
const #2 = Asciz	PartialOrdering.scala;
const #3 = Asciz	$outer;
const #4 = Asciz	Lscala/PartialOrdering;;
const #5 = Asciz	<init>;
const #6 = Asciz	(Lscala/PartialOrdering;)V;
const #7 = Asciz	Code;
const #8 = Asciz	LineNumberTable;
const #9 = Asciz	java/lang/NullPointerException;
const #10 = class	#9;	//  java/lang/NullPointerException
const #11 = Asciz	()V;
const #12 = NameAndType	#5:#11;//  "<init>":()V
const #13 = Method	#10.#12;	//  java/lang/NullPointerException."<init>":()V
const #14 = Asciz	scala/PartialOrdering$$anon$1;
const #15 = class	#14;	//  scala/PartialOrdering$$anon$1
const #16 = NameAndType	#3:#4;//  $outer:Lscala/PartialOrdering;
const #17 = Field	#15.#16;	//  scala/PartialOrdering$$anon$1.$outer:Lscala/PartialOrdering;
const #18 = Asciz	java/lang/Object;
const #19 = class	#18;	//  java/lang/Object
const #20 = Method	#19.#12;	//  java/lang/Object."<init>":()V
const #21 = Asciz	scala/PartialOrdering$class;
const #22 = class	#21;	//  scala/PartialOrdering$class
const #23 = Asciz	$init$;
const #24 = NameAndType	#23:#6;//  $init$:(Lscala/PartialOrdering;)V
const #25 = Method	#22.#24;	//  scala/PartialOrdering$class.$init$:(Lscala/PartialOrdering;)V
const #26 = Asciz	this;
const #27 = Asciz	Lscala/PartialOrdering$$anon$1;;
const #28 = Asciz	LocalVariableTable;
const #29 = Asciz	(Lscala/PartialOrdering<TT;>;)V;
const #30 = Asciz	Signature;
const #31 = Asciz	lteq;
const #32 = Asciz	(Ljava/lang/Object;Ljava/lang/Object;)Z;
const #33 = Asciz	scala/PartialOrdering;
const #34 = class	#33;	//  scala/PartialOrdering
const #35 = NameAndType	#31:#32;//  lteq:(Ljava/lang/Object;Ljava/lang/Object;)Z
const #36 = InterfaceMethod	#34.#35;	//  scala/PartialOrdering.lteq:(Ljava/lang/Object;Ljava/lang/Object;)Z
const #37 = Asciz	x;
const #38 = Asciz	Ljava/lang/Object;;
const #39 = Asciz	y;
const #40 = Asciz	(TT;TT;)Z;
const #41 = Asciz	reverse;
const #42 = Asciz	()Lscala/PartialOrdering;;
const #43 = Asciz	()Lscala/PartialOrdering<TT;>;;
const #44 = Asciz	equiv;
const #45 = Asciz	(Lscala/PartialOrdering;Ljava/lang/Object;Ljava/lang/Object;)Z;
const #46 = NameAndType	#44:#45;//  equiv:(Lscala/PartialOrdering;Ljava/lang/Object;Ljava/lang/Object;)Z
const #47 = Method	#22.#46;	//  scala/PartialOrdering$class.equiv:(Lscala/PartialOrdering;Ljava/lang/Object;Ljava/lang/Object;)Z
const #48 = Asciz	gt;
const #49 = NameAndType	#48:#45;//  gt:(Lscala/PartialOrdering;Ljava/lang/Object;Ljava/lang/Object;)Z
const #50 = Method	#22.#49;	//  scala/PartialOrdering$class.gt:(Lscala/PartialOrdering;Ljava/lang/Object;Ljava/lang/Object;)Z
const #51 = Asciz	lt;
const #52 = NameAndType	#51:#45;//  lt:(Lscala/PartialOrdering;Ljava/lang/Object;Ljava/lang/Object;)Z
const #53 = Method	#22.#52;	//  scala/PartialOrdering$class.lt:(Lscala/PartialOrdering;Ljava/lang/Object;Ljava/lang/Object;)Z
const #54 = Asciz	gteq;
const #55 = NameAndType	#54:#45;//  gteq:(Lscala/PartialOrdering;Ljava/lang/Object;Ljava/lang/Object;)Z
const #56 = Method	#22.#55;	//  scala/PartialOrdering$class.gteq:(Lscala/PartialOrdering;Ljava/lang/Object;Ljava/lang/Object;)Z
const #57 = Asciz	Ljava/lang/Object;Lscala/PartialOrdering<TT;>;;
const #58 = Asciz	Scala;
const #59 = Asciz	InnerClasses;
const #60 = Asciz	$anon$1;

{
public scala.PartialOrdering$$anon$1(scala.PartialOrdering);
  Code:
   Stack=2, Locals=2, Args_size=2
   0:	aload_1
   1:	ifnonnull	12
   4:	new	#10; //class java/lang/NullPointerException
   7:	dup
   8:	invokespecial	#13; //Method java/lang/NullPointerException."<init>":()V
   11:	athrow
   12:	aload_0
   13:	aload_1
   14:	putfield	#17; //Field $outer:Lscala/PartialOrdering;
   17:	aload_0
   18:	invokespecial	#20; //Method java/lang/Object."<init>":()V
   21:	aload_0
   22:	invokestatic	#25; //Method scala/PartialOrdering$class.$init$:(Lscala/PartialOrdering;)V
   25:	return
  LineNumberTable: 
   line 65: 0

  LocalVariableTable: 
   Start  Length  Slot  Name   Signature
   0      26      0    this       Lscala/PartialOrdering$$anon$1;
   0      26      1    $outer       Lscala/PartialOrdering;

  Signature: length = 0x2
   00 1D 

public boolean lteq(java.lang.Object, java.lang.Object);
  Code:
   Stack=3, Locals=3, Args_size=3
   0:	aload_0
   1:	getfield	#17; //Field $outer:Lscala/PartialOrdering;
   4:	aload_2
   5:	aload_1
   6:	invokeinterface	#36,  3; //InterfaceMethod scala/PartialOrdering.lteq:(Ljava/lang/Object;Ljava/lang/Object;)Z
   11:	ireturn
  LineNumberTable: 
   line 67: 0

  LocalVariableTable: 
   Start  Length  Slot  Name   Signature
   0      12      0    this       Lscala/PartialOrdering$$anon$1;
   0      12      1    x       Ljava/lang/Object;
   0      12      2    y       Ljava/lang/Object;

  Signature: length = 0x2
   00 28 

public scala.PartialOrdering reverse();
  Code:
   Stack=1, Locals=1, Args_size=1
   0:	aload_0
   1:	getfield	#17; //Field $outer:Lscala/PartialOrdering;
   4:	areturn
  LineNumberTable: 
   line 66: 0

  Signature: length = 0x2
   00 2B 

public boolean equiv(java.lang.Object, java.lang.Object);
  Code:
   Stack=3, Locals=3, Args_size=3
   0:	aload_0
   1:	aload_1
   2:	aload_2
   3:	invokestatic	#47; //Method scala/PartialOrdering$class.equiv:(Lscala/PartialOrdering;Ljava/lang/Object;Ljava/lang/Object;)Z
   6:	ireturn
  LineNumberTable: 
   line 65: 0

  LocalVariableTable: 
   Start  Length  Slot  Name   Signature
   0      7      0    this       Lscala/PartialOrdering$$anon$1;
   0      7      1    x       Ljava/lang/Object;
   0      7      2    y       Ljava/lang/Object;


public boolean gt(java.lang.Object, java.lang.Object);
  Code:
   Stack=3, Locals=3, Args_size=3
   0:	aload_0
   1:	aload_1
   2:	aload_2
   3:	invokestatic	#50; //Method scala/PartialOrdering$class.gt:(Lscala/PartialOrdering;Ljava/lang/Object;Ljava/lang/Object;)Z
   6:	ireturn
  LineNumberTable: 
   line 65: 0

  LocalVariableTable: 
   Start  Length  Slot  Name   Signature
   0      7      0    this       Lscala/PartialOrdering$$anon$1;
   0      7      1    x       Ljava/lang/Object;
   0      7      2    y       Ljava/lang/Object;


public boolean lt(java.lang.Object, java.lang.Object);
  Code:
   Stack=3, Locals=3, Args_size=3
   0:	aload_0
   1:	aload_1
   2:	aload_2
   3:	invokestatic	#53; //Method scala/PartialOrdering$class.lt:(Lscala/PartialOrdering;Ljava/lang/Object;Ljava/lang/Object;)Z
   6:	ireturn
  LineNumberTable: 
   line 65: 0

  LocalVariableTable: 
   Start  Length  Slot  Name   Signature
   0      7      0    this       Lscala/PartialOrdering$$anon$1;
   0      7      1    x       Ljava/lang/Object;
   0      7      2    y       Ljava/lang/Object;


public boolean gteq(java.lang.Object, java.lang.Object);
  Code:
   Stack=3, Locals=3, Args_size=3
   0:	aload_0
   1:	aload_1
   2:	aload_2
   3:	invokestatic	#56; //Method scala/PartialOrdering$class.gteq:(Lscala/PartialOrdering;Ljava/lang/Object;Ljava/lang/Object;)Z
   6:	ireturn
  LineNumberTable: 
   line 65: 0

  LocalVariableTable: 
   Start  Length  Slot  Name   Signature
   0      7      0    this       Lscala/PartialOrdering$$anon$1;
   0      7      1    x       Ljava/lang/Object;
   0      7      2    y       Ljava/lang/Object;


}

