Compiled from "PartialFunction.scala"
public final class scala.PartialFunction$$anonfun$lift$1 extends scala.runtime.AbstractFunction1 implements java.io.Serializable
  SourceFile: "PartialFunction.scala"
  Scala: length = 0x
   
  InnerClass: 
   public final #63= #9 of #39; //$anonfun$lift$1=class scala/PartialFunction$$anonfun$lift$1 of class scala/PartialFunction
  minor version: 0
  major version: 49
  Constant pool:
const #1 = Asciz	SourceFile;
const #2 = Asciz	PartialFunction.scala;
const #3 = Asciz	<clinit>;
const #4 = Asciz	()V;
const #5 = Asciz	Code;
const #6 = Asciz	serialVersionUID;
const #7 = Asciz	J;
const #8 = Asciz	scala/PartialFunction$$anonfun$lift$1;
const #9 = class	#8;	//  scala/PartialFunction$$anonfun$lift$1
const #10 = NameAndType	#6:#7;//  serialVersionUID:J
const #11 = Field	#9.#10;	//  scala/PartialFunction$$anonfun$lift$1.serialVersionUID:J
const #12 = Asciz	$outer;
const #13 = Asciz	Lscala/PartialFunction;;
const #14 = Asciz	<init>;
const #15 = Asciz	(Lscala/PartialFunction;)V;
const #16 = Asciz	LineNumberTable;
const #17 = Asciz	java/lang/NullPointerException;
const #18 = class	#17;	//  java/lang/NullPointerException
const #19 = NameAndType	#14:#4;//  "<init>":()V
const #20 = Method	#18.#19;	//  java/lang/NullPointerException."<init>":()V
const #21 = NameAndType	#12:#13;//  $outer:Lscala/PartialFunction;
const #22 = Field	#9.#21;	//  scala/PartialFunction$$anonfun$lift$1.$outer:Lscala/PartialFunction;
const #23 = Asciz	scala/runtime/AbstractFunction1;
const #24 = class	#23;	//  scala/runtime/AbstractFunction1
const #25 = Method	#24.#19;	//  scala/runtime/AbstractFunction1."<init>":()V
const #26 = Asciz	this;
const #27 = Asciz	Lscala/PartialFunction$$anonfun$lift$1;;
const #28 = Asciz	LocalVariableTable;
const #29 = Asciz	(Lscala/PartialFunction<TA;TB;>;)V;
const #30 = Asciz	Signature;
const #31 = Asciz	apply;
const #32 = Asciz	(Ljava/lang/Object;)Ljava/lang/Object;;
const #33 = Asciz	(Ljava/lang/Object;)Lscala/Option;;
const #34 = NameAndType	#31:#33;//  apply:(Ljava/lang/Object;)Lscala/Option;
const #35 = Method	#9.#34;	//  scala/PartialFunction$$anonfun$lift$1.apply:(Ljava/lang/Object;)Lscala/Option;
const #36 = Asciz	v1;
const #37 = Asciz	Ljava/lang/Object;;
const #38 = Asciz	scala/PartialFunction;
const #39 = class	#38;	//  scala/PartialFunction
const #40 = Asciz	isDefinedAt;
const #41 = Asciz	(Ljava/lang/Object;)Z;
const #42 = NameAndType	#40:#41;//  isDefinedAt:(Ljava/lang/Object;)Z
const #43 = InterfaceMethod	#39.#42;	//  scala/PartialFunction.isDefinedAt:(Ljava/lang/Object;)Z
const #44 = Asciz	scala/Some;
const #45 = class	#44;	//  scala/Some
const #46 = Asciz	scala/Function1;
const #47 = class	#46;	//  scala/Function1
const #48 = NameAndType	#31:#32;//  apply:(Ljava/lang/Object;)Ljava/lang/Object;
const #49 = InterfaceMethod	#47.#48;	//  scala/Function1.apply:(Ljava/lang/Object;)Ljava/lang/Object;
const #50 = Asciz	(Ljava/lang/Object;)V;
const #51 = NameAndType	#14:#50;//  "<init>":(Ljava/lang/Object;)V
const #52 = Method	#45.#51;	//  scala/Some."<init>":(Ljava/lang/Object;)V
const #53 = Asciz	scala/None$;
const #54 = class	#53;	//  scala/None$
const #55 = Asciz	MODULE$;
const #56 = Asciz	Lscala/None$;;
const #57 = NameAndType	#55:#56;//  MODULE$:Lscala/None$;
const #58 = Field	#54.#57;	//  scala/None$.MODULE$:Lscala/None$;
const #59 = Asciz	x;
const #60 = Asciz	(TA;)Lscala/Option<TB;>;;
const #61 = Asciz	Scala;
const #62 = Asciz	InnerClasses;
const #63 = Asciz	$anonfun$lift$1;
const #64 = Asciz	java/io/Serializable;
const #65 = class	#64;	//  java/io/Serializable

{
public static final long serialVersionUID;

public static {};
  Code:
   Stack=2, Locals=0, Args_size=0
   0:	lconst_0
   1:	putstatic	#11; //Field serialVersionUID:J
   4:	return

public scala.PartialFunction$$anonfun$lift$1(scala.PartialFunction);
  Code:
   Stack=2, Locals=2, Args_size=2
   0:	aload_1
   1:	ifnonnull	12
   4:	new	#18; //class java/lang/NullPointerException
   7:	dup
   8:	invokespecial	#20; //Method java/lang/NullPointerException."<init>":()V
   11:	athrow
   12:	aload_0
   13:	aload_1
   14:	putfield	#22; //Field $outer:Lscala/PartialFunction;
   17:	aload_0
   18:	invokespecial	#25; //Method scala/runtime/AbstractFunction1."<init>":()V
   21:	return
  LineNumberTable: 
   line 66: 0

  LocalVariableTable: 
   Start  Length  Slot  Name   Signature
   0      22      0    this       Lscala/PartialFunction$$anonfun$lift$1;
   0      22      1    $outer       Lscala/PartialFunction;

  Signature: length = 0x2
   00 1D 

public final java.lang.Object apply(java.lang.Object);
  Code:
   Stack=2, Locals=2, Args_size=2
   0:	aload_0
   1:	aload_1
   2:	invokevirtual	#35; //Method apply:(Ljava/lang/Object;)Lscala/Option;
   5:	areturn
  LineNumberTable: 
   line 66: 0

  LocalVariableTable: 
   Start  Length  Slot  Name   Signature
   0      6      0    this       Lscala/PartialFunction$$anonfun$lift$1;
   0      6      1    v1       Ljava/lang/Object;


public final scala.Option apply(java.lang.Object);
  Code:
   Stack=4, Locals=2, Args_size=2
   0:	aload_0
   1:	getfield	#22; //Field $outer:Lscala/PartialFunction;
   4:	aload_1
   5:	invokeinterface	#43,  2; //InterfaceMethod scala/PartialFunction.isDefinedAt:(Ljava/lang/Object;)Z
   10:	ifeq	33
   13:	new	#45; //class scala/Some
   16:	dup
   17:	aload_0
   18:	getfield	#22; //Field $outer:Lscala/PartialFunction;
   21:	aload_1
   22:	invokeinterface	#49,  2; //InterfaceMethod scala/Function1.apply:(Ljava/lang/Object;)Ljava/lang/Object;
   27:	invokespecial	#52; //Method scala/Some."<init>":(Ljava/lang/Object;)V
   30:	goto	36
   33:	getstatic	#58; //Field scala/None$.MODULE$:Lscala/None$;
   36:	areturn
  LineNumberTable: 
   line 66: 0

  LocalVariableTable: 
   Start  Length  Slot  Name   Signature
   0      37      0    this       Lscala/PartialFunction$$anonfun$lift$1;
   0      37      1    x       Ljava/lang/Object;

  Signature: length = 0x2
   00 3C 

}

