Compiled from "PartialFunction.scala"
public final class scala.PartialFunction$$anonfun$lift$1 extends scala.runtime.AbstractFunction1 implements java.io.Serializable
  SourceFile: "PartialFunction.scala"
  Scala: length = 0x
   
  InnerClass: 
   public final $anonfun$lift$1=class scala/PartialFunction$$anonfun$lift$1 of class scala/PartialFunction
  minor version: 0
  major version: 49
  Constant pool:
Asciz	SourceFile;
Asciz	PartialFunction.scala;
Asciz	<clinit>;
Asciz	()V;
Asciz	Code;
Asciz	serialVersionUID;
Asciz	J;
Asciz	scala/PartialFunction$$anonfun$lift$1;
class	scala/PartialFunction$$anonfun$lift$1
NameAndType	serialVersionUID:J
Field	scala/PartialFunction$$anonfun$lift$1.serialVersionUID:J
Asciz	$outer;
Asciz	Lscala/PartialFunction;;
Asciz	<init>;
Asciz	(Lscala/PartialFunction;)V;
Asciz	LineNumberTable;
Asciz	java/lang/NullPointerException;
class	java/lang/NullPointerException
NameAndType	"<init>":()V
Method	java/lang/NullPointerException."<init>":()V
NameAndType	$outer:Lscala/PartialFunction;
Field	scala/PartialFunction$$anonfun$lift$1.$outer:Lscala/PartialFunction;
Asciz	scala/runtime/AbstractFunction1;
class	scala/runtime/AbstractFunction1
Method	scala/runtime/AbstractFunction1."<init>":()V
Asciz	this;
Asciz	Lscala/PartialFunction$$anonfun$lift$1;;
Asciz	LocalVariableTable;
Asciz	(Lscala/PartialFunction<TA;TB;>;)V;
Asciz	Signature;
Asciz	apply;
Asciz	(Ljava/lang/Object;)Ljava/lang/Object;;
Asciz	(Ljava/lang/Object;)Lscala/Option;;
NameAndType	apply:(Ljava/lang/Object;)Lscala/Option;
Method	scala/PartialFunction$$anonfun$lift$1.apply:(Ljava/lang/Object;)Lscala/Option;
Asciz	v1;
Asciz	Ljava/lang/Object;;
Asciz	scala/PartialFunction;
class	scala/PartialFunction
Asciz	isDefinedAt;
Asciz	(Ljava/lang/Object;)Z;
NameAndType	isDefinedAt:(Ljava/lang/Object;)Z
InterfaceMethod	scala/PartialFunction.isDefinedAt:(Ljava/lang/Object;)Z
Asciz	scala/Some;
class	scala/Some
Asciz	scala/Function1;
class	scala/Function1
NameAndType	apply:(Ljava/lang/Object;)Ljava/lang/Object;
InterfaceMethod	scala/Function1.apply:(Ljava/lang/Object;)Ljava/lang/Object;
Asciz	(Ljava/lang/Object;)V;
NameAndType	"<init>":(Ljava/lang/Object;)V
Method	scala/Some."<init>":(Ljava/lang/Object;)V
Asciz	scala/None$;
class	scala/None$
Asciz	MODULE$;
Asciz	Lscala/None$;;
NameAndType	MODULE$:Lscala/None$;
Field	scala/None$.MODULE$:Lscala/None$;
Asciz	x;
Asciz	(TA;)Lscala/Option<TB;>;;
Asciz	Scala;
Asciz	InnerClasses;
Asciz	$anonfun$lift$1;
Asciz	java/io/Serializable;
class	java/io/Serializable

{
public static final long serialVersionUID;
  Signature: J

public final scala.PartialFunction $outer;
  Signature: Lscala/PartialFunction;

public static {};
  Signature: ()V
  Code:
   Stack=2, Locals=0, Args_size=0
	lconst_0
	putstatic	Field serialVersionUID:J
	return
  Labels:

public scala.PartialFunction$$anonfun$lift$1(scala.PartialFunction);
  Signature: (Lscala/PartialFunction;)V
  Code:
   Stack=2, Locals=2, Args_size=2
	aload_1
	ifnonnull	l1 // aload_0
	new	class java/lang/NullPointerException
	dup
	invokespecial	Method java/lang/NullPointerException."<init>":()V
	athrow
l1	aload_0
	aload_1
	putfield	Field $outer:Lscala/PartialFunction;
	aload_0
	invokespecial	Method scala/runtime/AbstractFunction1."<init>":()V
	return
  Labels:
   	l1 = 12 // aload_0
  LocalVariableTable: 
   Start  Length  Slot  Name   Signature
   0      22      0    this       Lscala/PartialFunction$$anonfun$lift$1;
   0      22      1    $outer       Lscala/PartialFunction;

  Signature: length = 0x2
   00 1D 

public final java.lang.Object apply(java.lang.Object);
  Signature: (Ljava/lang/Object;)Ljava/lang/Object;
  Code:
   Stack=2, Locals=2, Args_size=2
	aload_0
	aload_1
	invokevirtual	Method apply:(Ljava/lang/Object;)Lscala/Option;
	areturn
  Labels:
  LocalVariableTable: 
   Start  Length  Slot  Name   Signature
   0      6      0    this       Lscala/PartialFunction$$anonfun$lift$1;
   0      6      1    v1       Ljava/lang/Object;


public final scala.Option apply(java.lang.Object);
  Signature: (Ljava/lang/Object;)Lscala/Option;
  Code:
   Stack=4, Locals=2, Args_size=2
	aload_0
	getfield	Field $outer:Lscala/PartialFunction;
	aload_1
	invokeinterface	InterfaceMethod scala/PartialFunction.isDefinedAt:(Ljava/lang/Object;)Z
	ifeq	l1 // getstatic
	new	class scala/Some
	dup
	aload_0
	getfield	Field $outer:Lscala/PartialFunction;
	aload_1
	invokeinterface	InterfaceMethod scala/Function1.apply:(Ljava/lang/Object;)Ljava/lang/Object;
	invokespecial	Method scala/Some."<init>":(Ljava/lang/Object;)V
	goto	l2 // areturn
l1	getstatic	Field scala/None$.MODULE$:Lscala/None$;
l2	areturn
  Labels:
   	l1 = 33 // getstatic
   	l2 = 36 // areturn
  LocalVariableTable: 
   Start  Length  Slot  Name   Signature
   0      37      0    this       Lscala/PartialFunction$$anonfun$lift$1;
   0      37      1    x       Ljava/lang/Object;

  Signature: length = 0x2
   00 3C 

}

