Compiled from "Predef.scala"
public final class scala.Predef$DummyImplicit$ extends java.lang.Object implements scala.ScalaObject
  SourceFile: "Predef.scala"
  Scala: length = 0x
   
  InnerClass: 
   public #28= #23 of #27; //DummyImplicit=class scala/Predef$DummyImplicit of class scala/Predef
  minor version: 0
  major version: 49
  Constant pool:
const #1 = Asciz	SourceFile;
const #2 = Asciz	Predef.scala;
const #3 = Asciz	Scala;
const #4 = Asciz	MODULE$;
const #5 = Asciz	Lscala/Predef$DummyImplicit$;;
const #6 = Asciz	<clinit>;
const #7 = Asciz	()V;
const #8 = Asciz	Code;
const #9 = Asciz	scala/Predef$DummyImplicit$;
const #10 = class	#9;	//  scala/Predef$DummyImplicit$
const #11 = Asciz	<init>;
const #12 = NameAndType	#11:#7;//  "<init>":()V
const #13 = Method	#10.#12;	//  scala/Predef$DummyImplicit$."<init>":()V
const #14 = Asciz	LineNumberTable;
const #15 = Asciz	java/lang/Object;
const #16 = class	#15;	//  java/lang/Object
const #17 = Method	#16.#12;	//  java/lang/Object."<init>":()V
const #18 = NameAndType	#4:#5;//  MODULE$:Lscala/Predef$DummyImplicit$;
const #19 = Field	#10.#18;	//  scala/Predef$DummyImplicit$.MODULE$:Lscala/Predef$DummyImplicit$;
const #20 = Asciz	dummyImplicit;
const #21 = Asciz	()Lscala/Predef$DummyImplicit;;
const #22 = Asciz	scala/Predef$DummyImplicit;
const #23 = class	#22;	//  scala/Predef$DummyImplicit
const #24 = Method	#23.#12;	//  scala/Predef$DummyImplicit."<init>":()V
const #25 = Asciz	InnerClasses;
const #26 = Asciz	scala/Predef;
const #27 = class	#26;	//  scala/Predef
const #28 = Asciz	DummyImplicit;
const #29 = Asciz	scala/ScalaObject;
const #30 = class	#29;	//  scala/ScalaObject

{
public static final scala.Predef$DummyImplicit$ MODULE$;

public static {};
  Code:
   Stack=1, Locals=0, Args_size=0
   0:	new	#10; //class scala/Predef$DummyImplicit$
   3:	invokespecial	#13; //Method "<init>":()V
   6:	return

public scala.Predef$DummyImplicit$();
  Code:
   Stack=1, Locals=1, Args_size=1
   0:	aload_0
   1:	invokespecial	#17; //Method java/lang/Object."<init>":()V
   4:	aload_0
   5:	putstatic	#19; //Field MODULE$:Lscala/Predef$DummyImplicit$;
   8:	return
  LineNumberTable: 
   line 299: 0


public scala.Predef$DummyImplicit dummyImplicit();
  Code:
   Stack=2, Locals=1, Args_size=1
   0:	new	#23; //class scala/Predef$DummyImplicit
   3:	dup
   4:	invokespecial	#24; //Method scala/Predef$DummyImplicit."<init>":()V
   7:	areturn
  LineNumberTable: 
   line 304: 0


}

