Compiled from "Predef.scala"
public final class scala.Predef$$eq$colon$eq$ extends java.lang.Object implements scala.ScalaObject
  SourceFile: "Predef.scala"
  Scala: length = 0x
   
  InnerClass: 
   public abstract #32= #29 of #31; //$eq$colon$eq=class scala/Predef$$eq$colon$eq of class scala/Predef
   public final #33= #23 of #10; //$anon$2=class scala/Predef$$eq$colon$eq$$anon$2 of class scala/Predef$$eq$colon$eq$
  minor version: 0
  major version: 49
  Constant pool:
const #1 = Asciz	SourceFile;
const #2 = Asciz	Predef.scala;
const #3 = Asciz	Scala;
const #4 = Asciz	MODULE$;
const #5 = Asciz	Lscala/Predef$$eq$colon$eq$;;
const #6 = Asciz	<clinit>;
const #7 = Asciz	()V;
const #8 = Asciz	Code;
const #9 = Asciz	scala/Predef$$eq$colon$eq$;
const #10 = class	#9;	//  scala/Predef$$eq$colon$eq$
const #11 = Asciz	<init>;
const #12 = NameAndType	#11:#7;//  "<init>":()V
const #13 = Method	#10.#12;	//  scala/Predef$$eq$colon$eq$."<init>":()V
const #14 = Asciz	LineNumberTable;
const #15 = Asciz	java/lang/Object;
const #16 = class	#15;	//  java/lang/Object
const #17 = Method	#16.#12;	//  java/lang/Object."<init>":()V
const #18 = NameAndType	#4:#5;//  MODULE$:Lscala/Predef$$eq$colon$eq$;
const #19 = Field	#10.#18;	//  scala/Predef$$eq$colon$eq$.MODULE$:Lscala/Predef$$eq$colon$eq$;
const #20 = Asciz	tpEquals;
const #21 = Asciz	()Lscala/Predef$$eq$colon$eq;;
const #22 = Asciz	scala/Predef$$eq$colon$eq$$anon$2;
const #23 = class	#22;	//  scala/Predef$$eq$colon$eq$$anon$2
const #24 = Method	#23.#12;	//  scala/Predef$$eq$colon$eq$$anon$2."<init>":()V
const #25 = Asciz	<A:Ljava/lang/Object;>()Lscala/Predef$$eq$colon$eq<TA;TA;>;;
const #26 = Asciz	Signature;
const #27 = Asciz	InnerClasses;
const #28 = Asciz	scala/Predef$$eq$colon$eq;
const #29 = class	#28;	//  scala/Predef$$eq$colon$eq
const #30 = Asciz	scala/Predef;
const #31 = class	#30;	//  scala/Predef
const #32 = Asciz	$eq$colon$eq;
const #33 = Asciz	$anon$2;
const #34 = Asciz	scala/ScalaObject;
const #35 = class	#34;	//  scala/ScalaObject

{
public static final scala.Predef$$eq$colon$eq$ MODULE$;

public static {};
  Code:
   Stack=1, Locals=0, Args_size=0
   0:	new	#10; //class scala/Predef$$eq$colon$eq$
   3:	invokespecial	#13; //Method "<init>":()V
   6:	return

public scala.Predef$$eq$colon$eq$();
  Code:
   Stack=1, Locals=1, Args_size=1
   0:	aload_0
   1:	invokespecial	#17; //Method java/lang/Object."<init>":()V
   4:	aload_0
   5:	putstatic	#19; //Field MODULE$:Lscala/Predef$$eq$colon$eq$;
   8:	return
  LineNumberTable: 
   line 285: 0


public scala.Predef$$eq$colon$eq tpEquals();
  Code:
   Stack=2, Locals=1, Args_size=1
   0:	new	#23; //class scala/Predef$$eq$colon$eq$$anon$2
   3:	dup
   4:	invokespecial	#24; //Method scala/Predef$$eq$colon$eq$$anon$2."<init>":()V
   7:	areturn
  LineNumberTable: 
   line 286: 0

  Signature: length = 0x2
   00 19 

}

