Compiled from "Predef.scala"
public final class scala.Predef$$anon$6 extends java.lang.Object implements java.lang.CharSequence
  SourceFile: "Predef.scala"
  Scala: length = 0x
   
  InnerClass: 
   public final $anon$6=class scala/Predef$$anon$6 of class scala/Predef
  minor version: 0
  major version: 49
  Constant pool:
Asciz	SourceFile;
Asciz	Predef.scala;
Asciz	xs$1;
Asciz	[C;
Asciz	length;
Asciz	()I;
Asciz	Code;
Asciz	LineNumberTable;
Asciz	scala/Predef$$anon$6;
class	scala/Predef$$anon$6
NameAndType	xs$1:[C
Field	scala/Predef$$anon$6.xs$1:[C
Asciz	charAt;
Asciz	(I)C;
Asciz	this;
Asciz	Lscala/Predef$$anon$6;;
Asciz	index;
Asciz	I;
Asciz	LocalVariableTable;
Asciz	subSequence;
Asciz	(II)Ljava/lang/CharSequence;;
Asciz	scala/Predef$;
class	scala/Predef$
Asciz	MODULE$;
Asciz	Lscala/Predef$;;
NameAndType	MODULE$:Lscala/Predef$;
Field	scala/Predef$.MODULE$:Lscala/Predef$;
Asciz	charArrayOps;
Asciz	([C)Lscala/collection/mutable/ArrayOps;;
NameAndType	charArrayOps:([C)Lscala/collection/mutable/ArrayOps;
Method	scala/Predef$.charArrayOps:([C)Lscala/collection/mutable/ArrayOps;
Asciz	scala/collection/IndexedSeqLike;
class	scala/collection/IndexedSeqLike
Asciz	slice;
Asciz	(II)Ljava/lang/Object;;
NameAndType	slice:(II)Ljava/lang/Object;
InterfaceMethod	scala/collection/IndexedSeqLike.slice:(II)Ljava/lang/Object;
class	"[C"
Asciz	arrayToCharSequence;
Asciz	([C)Ljava/lang/CharSequence;;
NameAndType	arrayToCharSequence:([C)Ljava/lang/CharSequence;
Method	scala/Predef$.arrayToCharSequence:([C)Ljava/lang/CharSequence;
Asciz	start;
Asciz	end;
Asciz	toString;
Asciz	()Ljava/lang/String;;
Asciz	;
String	
Asciz	scala/collection/TraversableOnce;
class	scala/collection/TraversableOnce
Asciz	mkString;
Asciz	(Ljava/lang/String;)Ljava/lang/String;;
NameAndType	mkString:(Ljava/lang/String;)Ljava/lang/String;
InterfaceMethod	scala/collection/TraversableOnce.mkString:(Ljava/lang/String;)Ljava/lang/String;
Asciz	<init>;
Asciz	([C)V;
Asciz	java/lang/Object;
class	java/lang/Object
Asciz	()V;
NameAndType	"<init>":()V
Method	java/lang/Object."<init>":()V
Asciz	Scala;
Asciz	InnerClasses;
Asciz	scala/Predef;
class	scala/Predef
Asciz	$anon$6;
Asciz	java/lang/CharSequence;
class	java/lang/CharSequence

{
private final char[] xs$1;
  Signature: [C

public int length();
  Signature: ()I
  Code:
   Stack=1, Locals=1, Args_size=1
	aload_0
	getfield	Field xs$1:[C
	arraylength
	ireturn
  Labels:

public char charAt(int);
  Signature: (I)C
  Code:
   Stack=2, Locals=2, Args_size=2
	aload_0
	getfield	Field xs$1:[C
	iload_1
	caload
	ireturn
  Labels:
  LocalVariableTable: 
   Start  Length  Slot  Name   Signature
   0      7      0    this       Lscala/Predef$$anon$6;
   0      7      1    index       I


public java.lang.CharSequence subSequence(int, int);
  Signature: (II)Ljava/lang/CharSequence;
  Code:
   Stack=4, Locals=3, Args_size=3
	getstatic	Field scala/Predef$.MODULE$:Lscala/Predef$;
	getstatic	Field scala/Predef$.MODULE$:Lscala/Predef$;
	aload_0
	getfield	Field xs$1:[C
	invokevirtual	Method scala/Predef$.charArrayOps:([C)Lscala/collection/mutable/ArrayOps;
	iload_1
	iload_2
	invokeinterface	InterfaceMethod scala/collection/IndexedSeqLike.slice:(II)Ljava/lang/Object;
	checkcast	class "[C"
	invokevirtual	Method scala/Predef$.arrayToCharSequence:([C)Ljava/lang/CharSequence;
	areturn
  Labels:
  LocalVariableTable: 
   Start  Length  Slot  Name   Signature
   0      27      0    this       Lscala/Predef$$anon$6;
   0      27      1    start       I
   0      27      2    end       I


public java.lang.String toString();
  Signature: ()Ljava/lang/String;
  Code:
   Stack=2, Locals=1, Args_size=1
	getstatic	Field scala/Predef$.MODULE$:Lscala/Predef$;
	aload_0
	getfield	Field xs$1:[C
	invokevirtual	Method scala/Predef$.charArrayOps:([C)Lscala/collection/mutable/ArrayOps;
	ldc	String 
	invokeinterface	InterfaceMethod scala/collection/TraversableOnce.mkString:(Ljava/lang/String;)Ljava/lang/String;
	areturn
  Labels:

public scala.Predef$$anon$6(char[]);
  Signature: ([C)V
  Code:
   Stack=2, Locals=2, Args_size=2
	aload_0
	aload_1
	putfield	Field xs$1:[C
	aload_0
	invokespecial	Method java/lang/Object."<init>":()V
	return
  Labels:

}

