Compiled from "Predef.scala"
public final class scala.Predef$Ensuring$$anonfun$ensuring$2 extends scala.runtime.AbstractFunction0 implements java.io.Serializable
  SourceFile: "Predef.scala"
  Scala: length = 0x
   
  InnerClass: 
   public #38= #35 of #37; //Ensuring=class scala/Predef$Ensuring of class scala/Predef
   public final #39= #9 of #35; //$anonfun$ensuring$2=class scala/Predef$Ensuring$$anonfun$ensuring$2 of class scala/Predef$Ensuring
  minor version: 0
  major version: 49
  Constant pool:
const #1 = Asciz	SourceFile;
const #2 = Asciz	Predef.scala;
const #3 = Asciz	<clinit>;
const #4 = Asciz	()V;
const #5 = Asciz	Code;
const #6 = Asciz	serialVersionUID;
const #7 = Asciz	J;
const #8 = Asciz	scala/Predef$Ensuring$$anonfun$ensuring$2;
const #9 = class	#8;	//  scala/Predef$Ensuring$$anonfun$ensuring$2
const #10 = NameAndType	#6:#7;//  serialVersionUID:J
const #11 = Field	#9.#10;	//  scala/Predef$Ensuring$$anonfun$ensuring$2.serialVersionUID:J
const #12 = Asciz	msg$2;
const #13 = Asciz	Ljava/lang/Object;;
const #14 = Asciz	<init>;
const #15 = Asciz	(Lscala/Predef$Ensuring;Ljava/lang/Object;)V;
const #16 = Asciz	LineNumberTable;
const #17 = NameAndType	#12:#13;//  msg$2:Ljava/lang/Object;
const #18 = Field	#9.#17;	//  scala/Predef$Ensuring$$anonfun$ensuring$2.msg$2:Ljava/lang/Object;
const #19 = Asciz	scala/runtime/AbstractFunction0;
const #20 = class	#19;	//  scala/runtime/AbstractFunction0
const #21 = NameAndType	#14:#4;//  "<init>":()V
const #22 = Method	#20.#21;	//  scala/runtime/AbstractFunction0."<init>":()V
const #23 = Asciz	this;
const #24 = Asciz	Lscala/Predef$Ensuring$$anonfun$ensuring$2;;
const #25 = Asciz	$outer;
const #26 = Asciz	Lscala/Predef$Ensuring;;
const #27 = Asciz	LocalVariableTable;
const #28 = Asciz	(Lscala/Predef$Ensuring<TA;>;)V;
const #29 = Asciz	Signature;
const #30 = Asciz	apply;
const #31 = Asciz	()Ljava/lang/Object;;
const #32 = Asciz	Scala;
const #33 = Asciz	InnerClasses;
const #34 = Asciz	scala/Predef$Ensuring;
const #35 = class	#34;	//  scala/Predef$Ensuring
const #36 = Asciz	scala/Predef;
const #37 = class	#36;	//  scala/Predef
const #38 = Asciz	Ensuring;
const #39 = Asciz	$anonfun$ensuring$2;
const #40 = Asciz	java/io/Serializable;
const #41 = class	#40;	//  java/io/Serializable

{
public static final long serialVersionUID;

public static {};
  Code:
   Stack=2, Locals=0, Args_size=0
   0:	lconst_0
   1:	putstatic	#11; //Field serialVersionUID:J
   4:	return

public scala.Predef$Ensuring$$anonfun$ensuring$2(scala.Predef$Ensuring, java.lang.Object);
  Code:
   Stack=2, Locals=3, Args_size=3
   0:	aload_0
   1:	aload_2
   2:	putfield	#18; //Field msg$2:Ljava/lang/Object;
   5:	aload_0
   6:	invokespecial	#22; //Method scala/runtime/AbstractFunction0."<init>":()V
   9:	return
  LineNumberTable: 
   line 124: 0

  LocalVariableTable: 
   Start  Length  Slot  Name   Signature
   0      10      0    this       Lscala/Predef$Ensuring$$anonfun$ensuring$2;
   0      10      1    $outer       Lscala/Predef$Ensuring;

  Signature: length = 0x2
   00 1C 

public final java.lang.Object apply();
  Code:
   Stack=1, Locals=1, Args_size=1
   0:	aload_0
   1:	getfield	#18; //Field msg$2:Ljava/lang/Object;
   4:	areturn
  LineNumberTable: 
   line 124: 0


}

