Compiled from "Predef.scala"
public final class scala.Predef$Triple$ extends java.lang.Object implements scala.ScalaObject
  SourceFile: "Predef.scala"
  Scala: length = 0x
   
  minor version: 0
  major version: 49
  Constant pool:
const #1 = Asciz	SourceFile;
const #2 = Asciz	Predef.scala;
const #3 = Asciz	Scala;
const #4 = Asciz	MODULE$;
const #5 = Asciz	Lscala/Predef$Triple$;;
const #6 = Asciz	<clinit>;
const #7 = Asciz	()V;
const #8 = Asciz	Code;
const #9 = Asciz	scala/Predef$Triple$;
const #10 = class	#9;	//  scala/Predef$Triple$
const #11 = Asciz	<init>;
const #12 = NameAndType	#11:#7;//  "<init>":()V
const #13 = Method	#10.#12;	//  scala/Predef$Triple$."<init>":()V
const #14 = Asciz	LineNumberTable;
const #15 = Asciz	java/lang/Object;
const #16 = class	#15;	//  java/lang/Object
const #17 = Method	#16.#12;	//  java/lang/Object."<init>":()V
const #18 = NameAndType	#4:#5;//  MODULE$:Lscala/Predef$Triple$;
const #19 = Field	#10.#18;	//  scala/Predef$Triple$.MODULE$:Lscala/Predef$Triple$;
const #20 = Asciz	unapply;
const #21 = Asciz	(Lscala/Tuple3;)Lscala/Option;;
const #22 = Asciz	scala/Some;
const #23 = class	#22;	//  scala/Some
const #24 = Asciz	(Ljava/lang/Object;)V;
const #25 = NameAndType	#11:#24;//  "<init>":(Ljava/lang/Object;)V
const #26 = Method	#23.#25;	//  scala/Some."<init>":(Ljava/lang/Object;)V
const #27 = Asciz	this;
const #28 = Asciz	x;
const #29 = Asciz	Lscala/Tuple3;;
const #30 = Asciz	LocalVariableTable;
const #31 = Asciz	<A:Ljava/lang/Object;B:Ljava/lang/Object;C:Ljava/lang/Object;>(Lscala/Tuple3<TA;TB;TC;>;)Lscala/Option<Lscala/Tuple3<TA;TB;TC;>;>;;
const #32 = Asciz	Signature;
const #33 = Asciz	apply;
const #34 = Asciz	(Ljava/lang/Object;Ljava/lang/Object;Ljava/lang/Object;)Lscala/Tuple3;;
const #35 = Asciz	scala/Tuple3;
const #36 = class	#35;	//  scala/Tuple3
const #37 = Asciz	(Ljava/lang/Object;Ljava/lang/Object;Ljava/lang/Object;)V;
const #38 = NameAndType	#11:#37;//  "<init>":(Ljava/lang/Object;Ljava/lang/Object;Ljava/lang/Object;)V
const #39 = Method	#36.#38;	//  scala/Tuple3."<init>":(Ljava/lang/Object;Ljava/lang/Object;Ljava/lang/Object;)V
const #40 = Asciz	Ljava/lang/Object;;
const #41 = Asciz	y;
const #42 = Asciz	z;
const #43 = Asciz	<A:Ljava/lang/Object;B:Ljava/lang/Object;C:Ljava/lang/Object;>(TA;TB;TC;)Lscala/Tuple3<TA;TB;TC;>;;
const #44 = Asciz	scala/ScalaObject;
const #45 = class	#44;	//  scala/ScalaObject

{
public static final scala.Predef$Triple$ MODULE$;

public static {};
  Code:
   Stack=1, Locals=0, Args_size=0
   0:	new	#10; //class scala/Predef$Triple$
   3:	invokespecial	#13; //Method "<init>":()V
   6:	return

public scala.Predef$Triple$();
  Code:
   Stack=1, Locals=1, Args_size=1
   0:	aload_0
   1:	invokespecial	#17; //Method java/lang/Object."<init>":()V
   4:	aload_0
   5:	putstatic	#19; //Field MODULE$:Lscala/Predef$Triple$;
   8:	return
  LineNumberTable: 
   line 129: 0


public scala.Option unapply(scala.Tuple3);
  Code:
   Stack=3, Locals=2, Args_size=2
   0:	new	#23; //class scala/Some
   3:	dup
   4:	aload_1
   5:	invokespecial	#26; //Method scala/Some."<init>":(Ljava/lang/Object;)V
   8:	areturn
  LineNumberTable: 
   line 131: 0

  LocalVariableTable: 
   Start  Length  Slot  Name   Signature
   0      9      0    this       Lscala/Predef$Triple$;
   0      9      1    x       Lscala/Tuple3;

  Signature: length = 0x2
   00 1F 

public scala.Tuple3 apply(java.lang.Object, java.lang.Object, java.lang.Object);
  Code:
   Stack=5, Locals=4, Args_size=4
   0:	new	#36; //class scala/Tuple3
   3:	dup
   4:	aload_1
   5:	aload_2
   6:	aload_3
   7:	invokespecial	#39; //Method scala/Tuple3."<init>":(Ljava/lang/Object;Ljava/lang/Object;Ljava/lang/Object;)V
   10:	areturn
  LineNumberTable: 
   line 130: 0

  LocalVariableTable: 
   Start  Length  Slot  Name   Signature
   0      11      0    this       Lscala/Predef$Triple$;
   0      11      1    x       Ljava/lang/Object;
   0      11      2    y       Ljava/lang/Object;
   0      11      3    z       Ljava/lang/Object;

  Signature: length = 0x2
   00 2B 

}

