Compiled from "Predef.scala"
public final class scala.Predef$ extends scala.LowPriorityImplicits implements scala.ScalaObject
  SourceFile: "Predef.scala"
  Scala: length = 0x
   
  InnerClass: 
   public #608= #286 of #607; //ofRef=class scala/collection/mutable/ArrayOps$ofRef of class scala/collection/mutable/ArrayOps
   public #609= #277 of #607; //ofInt=class scala/collection/mutable/ArrayOps$ofInt of class scala/collection/mutable/ArrayOps
   public final #612= #54 of #611; //$anon$1=class scala/Predef$$anon$1 of class scala/Predef
   public final #613= #61 of #611; //$anon$6=class scala/Predef$$anon$6 of class scala/Predef
   public final #614= #72 of #611; //$anon$5=class scala/Predef$$anon$5 of class scala/Predef
   public final #615= #82 of #611; //$anon$4=class scala/Predef$$anon$4 of class scala/Predef
   public #616= #259 of #607; //ofLong=class scala/collection/mutable/ArrayOps$ofLong of class scala/collection/mutable/ArrayOps
   public #617= #244 of #607; //ofChar=class scala/collection/mutable/ArrayOps$ofChar of class scala/collection/mutable/ArrayOps
   public #618= #235 of #607; //ofByte=class scala/collection/mutable/ArrayOps$ofByte of class scala/collection/mutable/ArrayOps
   public #619= #207 of #607; //ofUnit=class scala/collection/mutable/ArrayOps$ofUnit of class scala/collection/mutable/ArrayOps
   public #620= #490 of #611; //Ensuring=class scala/Predef$Ensuring of class scala/Predef
   public #621= #250 of #607; //ofFloat=class scala/collection/mutable/ArrayOps$ofFloat of class scala/collection/mutable/ArrayOps
   public #622= #226 of #607; //ofShort=class scala/collection/mutable/ArrayOps$ofShort of class scala/collection/mutable/ArrayOps
   public #623= #268 of #607; //ofDouble=class scala/collection/mutable/ArrayOps$ofDouble of class scala/collection/mutable/ArrayOps
   public #624= #484 of #611; //ArrowAssoc=class scala/Predef$ArrowAssoc of class scala/Predef
   public #625= #217 of #607; //ofBoolean=class scala/collection/mutable/ArrayOps$ofBoolean of class scala/collection/mutable/ArrayOps
   public abstract #628= #627 of #611; //$eq$colon$eq=class scala/Predef$$eq$colon$eq of class scala/Predef
   public #631= #630 of #611; //DummyImplicit=class scala/Predef$DummyImplicit of class scala/Predef
   public abstract #634= #633 of #611; //$less$colon$less=class scala/Predef$$less$colon$less of class scala/Predef
   public abstract #637= #636 of #611; //$less$percent$less=class scala/Predef$$less$percent$less of class scala/Predef
  minor version: 0
  major version: 49
  Constant pool:
const #1 = Asciz	SourceFile;
const #2 = Asciz	Predef.scala;
const #3 = Asciz	Scala;
const #4 = Asciz	MODULE$;
const #5 = Asciz	Lscala/Predef$;;
const #6 = Asciz	<clinit>;
const #7 = Asciz	()V;
const #8 = Asciz	Code;
const #9 = Asciz	scala/Predef$;
const #10 = class	#9;	//  scala/Predef$
const #11 = Asciz	<init>;
const #12 = NameAndType	#11:#7;//  "<init>":()V
const #13 = Method	#10.#12;	//  scala/Predef$."<init>":()V
const #14 = Asciz	Set;
const #15 = Asciz	Lscala/collection/immutable/Set$;;
const #16 = Asciz	Map;
const #17 = Asciz	Lscala/collection/immutable/Map$;;
const #18 = Asciz	LineNumberTable;
const #19 = Asciz	scala/LowPriorityImplicits;
const #20 = class	#19;	//  scala/LowPriorityImplicits
const #21 = Method	#20.#12;	//  scala/LowPriorityImplicits."<init>":()V
const #22 = NameAndType	#4:#5;//  MODULE$:Lscala/Predef$;
const #23 = Field	#10.#22;	//  scala/Predef$.MODULE$:Lscala/Predef$;
const #24 = Asciz	scala/package$;
const #25 = class	#24;	//  scala/package$
const #26 = Asciz	Lscala/package$;;
const #27 = NameAndType	#4:#26;//  MODULE$:Lscala/package$;
const #28 = Field	#25.#27;	//  scala/package$.MODULE$:Lscala/package$;
const #29 = Asciz	scala/collection/immutable/List$;
const #30 = class	#29;	//  scala/collection/immutable/List$
const #31 = Asciz	Lscala/collection/immutable/List$;;
const #32 = NameAndType	#4:#31;//  MODULE$:Lscala/collection/immutable/List$;
const #33 = Field	#30.#32;	//  scala/collection/immutable/List$.MODULE$:Lscala/collection/immutable/List$;
const #34 = Asciz	scala/collection/mutable/StringBuilder$;
const #35 = class	#34;	//  scala/collection/mutable/StringBuilder$
const #36 = Asciz	Lscala/collection/mutable/StringBuilder$;;
const #37 = NameAndType	#4:#36;//  MODULE$:Lscala/collection/mutable/StringBuilder$;
const #38 = Field	#35.#37;	//  scala/collection/mutable/StringBuilder$.MODULE$:Lscala/collection/mutable/StringBuilder$;
const #39 = Asciz	scala/collection/immutable/Map$;
const #40 = class	#39;	//  scala/collection/immutable/Map$
const #41 = NameAndType	#4:#17;//  MODULE$:Lscala/collection/immutable/Map$;
const #42 = Field	#40.#41;	//  scala/collection/immutable/Map$.MODULE$:Lscala/collection/immutable/Map$;
const #43 = NameAndType	#16:#17;//  Map:Lscala/collection/immutable/Map$;
const #44 = Field	#10.#43;	//  scala/Predef$.Map:Lscala/collection/immutable/Map$;
const #45 = Asciz	scala/collection/immutable/Set$;
const #46 = class	#45;	//  scala/collection/immutable/Set$
const #47 = NameAndType	#4:#15;//  MODULE$:Lscala/collection/immutable/Set$;
const #48 = Field	#46.#47;	//  scala/collection/immutable/Set$.MODULE$:Lscala/collection/immutable/Set$;
const #49 = NameAndType	#14:#15;//  Set:Lscala/collection/immutable/Set$;
const #50 = Field	#10.#49;	//  scala/Predef$.Set:Lscala/collection/immutable/Set$;
const #51 = Asciz	conforms;
const #52 = Asciz	()Lscala/Predef$$less$colon$less;;
const #53 = Asciz	scala/Predef$$anon$1;
const #54 = class	#53;	//  scala/Predef$$anon$1
const #55 = Method	#54.#12;	//  scala/Predef$$anon$1."<init>":()V
const #56 = Asciz	<A:Ljava/lang/Object;>()Lscala/Predef$$less$colon$less<TA;TA;>;;
const #57 = Asciz	Signature;
const #58 = Asciz	arrayToCharSequence;
const #59 = Asciz	([C)Ljava/lang/CharSequence;;
const #60 = Asciz	scala/Predef$$anon$6;
const #61 = class	#60;	//  scala/Predef$$anon$6
const #62 = Asciz	([C)V;
const #63 = NameAndType	#11:#62;//  "<init>":([C)V
const #64 = Method	#61.#63;	//  scala/Predef$$anon$6."<init>":([C)V
const #65 = Asciz	this;
const #66 = Asciz	xs$1;
const #67 = Asciz	[C;
const #68 = Asciz	LocalVariableTable;
const #69 = Asciz	seqToCharSequence;
const #70 = Asciz	(Lscala/collection/IndexedSeq;)Ljava/lang/CharSequence;;
const #71 = Asciz	scala/Predef$$anon$5;
const #72 = class	#71;	//  scala/Predef$$anon$5
const #73 = Asciz	(Lscala/collection/IndexedSeq;)V;
const #74 = NameAndType	#11:#73;//  "<init>":(Lscala/collection/IndexedSeq;)V
const #75 = Method	#72.#74;	//  scala/Predef$$anon$5."<init>":(Lscala/collection/IndexedSeq;)V
const #76 = Asciz	xs$2;
const #77 = Asciz	Lscala/collection/IndexedSeq;;
const #78 = Asciz	(Lscala/collection/IndexedSeq<Ljava/lang/Character;>;)Ljava/lang/CharSequence;;
const #79 = Asciz	stringCanBuildFrom;
const #80 = Asciz	()Lscala/collection/generic/CanBuildFrom;;
const #81 = Asciz	scala/Predef$$anon$4;
const #82 = class	#81;	//  scala/Predef$$anon$4
const #83 = Method	#82.#12;	//  scala/Predef$$anon$4."<init>":()V
const #84 = Asciz	()Lscala/collection/generic/CanBuildFrom<Ljava/lang/String;Ljava/lang/Character;Ljava/lang/String;>;;
const #85 = Asciz	unaugmentString;
const #86 = Asciz	(Lscala/collection/immutable/StringOps;)Ljava/lang/String;;
const #87 = Asciz	scala/collection/immutable/StringOps;
const #88 = class	#87;	//  scala/collection/immutable/StringOps
const #89 = Asciz	repr;
const #90 = Asciz	()Ljava/lang/String;;
const #91 = NameAndType	#89:#90;//  repr:()Ljava/lang/String;
const #92 = Method	#88.#91;	//  scala/collection/immutable/StringOps.repr:()Ljava/lang/String;
const #93 = Asciz	x;
const #94 = Asciz	Lscala/collection/immutable/StringOps;;
const #95 = Asciz	augmentString;
const #96 = Asciz	(Ljava/lang/String;)Lscala/collection/immutable/StringOps;;
const #97 = Asciz	(Ljava/lang/String;)V;
const #98 = NameAndType	#11:#97;//  "<init>":(Ljava/lang/String;)V
const #99 = Method	#88.#98;	//  scala/collection/immutable/StringOps."<init>":(Ljava/lang/String;)V
const #100 = Asciz	Ljava/lang/String;;
const #101 = Asciz	any2stringadd;
const #102 = Asciz	(Ljava/lang/Object;)Lscala/runtime/StringAdd;;
const #103 = Asciz	scala/runtime/StringAdd;
const #104 = class	#103;	//  scala/runtime/StringAdd
const #105 = Asciz	(Ljava/lang/Object;)V;
const #106 = NameAndType	#11:#105;//  "<init>":(Ljava/lang/Object;)V
const #107 = Method	#104.#106;	//  scala/runtime/StringAdd."<init>":(Ljava/lang/Object;)V
const #108 = Asciz	Ljava/lang/Object;;
const #109 = Asciz	boolean2Boolean;
const #110 = Asciz	(Z)Ljava/lang/Boolean;;
const #111 = Asciz	java/lang/Boolean;
const #112 = class	#111;	//  java/lang/Boolean
const #113 = Asciz	valueOf;
const #114 = NameAndType	#113:#110;//  valueOf:(Z)Ljava/lang/Boolean;
const #115 = Method	#112.#114;	//  java/lang/Boolean.valueOf:(Z)Ljava/lang/Boolean;
const #116 = Asciz	Z;
const #117 = Asciz	double2Double;
const #118 = Asciz	(D)Ljava/lang/Double;;
const #119 = Asciz	java/lang/Double;
const #120 = class	#119;	//  java/lang/Double
const #121 = NameAndType	#113:#118;//  valueOf:(D)Ljava/lang/Double;
const #122 = Method	#120.#121;	//  java/lang/Double.valueOf:(D)Ljava/lang/Double;
const #123 = Asciz	D;
const #124 = Asciz	float2Float;
const #125 = Asciz	(F)Ljava/lang/Float;;
const #126 = Asciz	java/lang/Float;
const #127 = class	#126;	//  java/lang/Float
const #128 = NameAndType	#113:#125;//  valueOf:(F)Ljava/lang/Float;
const #129 = Method	#127.#128;	//  java/lang/Float.valueOf:(F)Ljava/lang/Float;
const #130 = Asciz	F;
const #131 = Asciz	long2Long;
const #132 = Asciz	(J)Ljava/lang/Long;;
const #133 = Asciz	java/lang/Long;
const #134 = class	#133;	//  java/lang/Long
const #135 = NameAndType	#113:#132;//  valueOf:(J)Ljava/lang/Long;
const #136 = Method	#134.#135;	//  java/lang/Long.valueOf:(J)Ljava/lang/Long;
const #137 = Asciz	J;
const #138 = Asciz	int2Integer;
const #139 = Asciz	(I)Ljava/lang/Integer;;
const #140 = Asciz	java/lang/Integer;
const #141 = class	#140;	//  java/lang/Integer
const #142 = NameAndType	#113:#139;//  valueOf:(I)Ljava/lang/Integer;
const #143 = Method	#141.#142;	//  java/lang/Integer.valueOf:(I)Ljava/lang/Integer;
const #144 = Asciz	I;
const #145 = Asciz	char2Character;
const #146 = Asciz	(C)Ljava/lang/Character;;
const #147 = Asciz	java/lang/Character;
const #148 = class	#147;	//  java/lang/Character
const #149 = NameAndType	#113:#146;//  valueOf:(C)Ljava/lang/Character;
const #150 = Method	#148.#149;	//  java/lang/Character.valueOf:(C)Ljava/lang/Character;
const #151 = Asciz	C;
const #152 = Asciz	short2Short;
const #153 = Asciz	(S)Ljava/lang/Short;;
const #154 = Asciz	java/lang/Short;
const #155 = class	#154;	//  java/lang/Short
const #156 = NameAndType	#113:#153;//  valueOf:(S)Ljava/lang/Short;
const #157 = Method	#155.#156;	//  java/lang/Short.valueOf:(S)Ljava/lang/Short;
const #158 = Asciz	S;
const #159 = Asciz	byte2Byte;
const #160 = Asciz	(B)Ljava/lang/Byte;;
const #161 = Asciz	java/lang/Byte;
const #162 = class	#161;	//  java/lang/Byte
const #163 = NameAndType	#113:#160;//  valueOf:(B)Ljava/lang/Byte;
const #164 = Method	#162.#163;	//  java/lang/Byte.valueOf:(B)Ljava/lang/Byte;
const #165 = Asciz	B;
const #166 = Asciz	float2double;
const #167 = Asciz	(F)D;
const #168 = Asciz	long2double;
const #169 = Asciz	(J)D;
const #170 = Asciz	long2float;
const #171 = Asciz	(J)F;
const #172 = Asciz	int2double;
const #173 = Asciz	(I)D;
const #174 = Asciz	int2float;
const #175 = Asciz	(I)F;
const #176 = Asciz	int2long;
const #177 = Asciz	(I)J;
const #178 = Asciz	char2double;
const #179 = Asciz	(C)D;
const #180 = Asciz	char2float;
const #181 = Asciz	(C)F;
const #182 = Asciz	char2long;
const #183 = Asciz	(C)J;
const #184 = Asciz	char2int;
const #185 = Asciz	(C)I;
const #186 = Asciz	short2double;
const #187 = Asciz	(S)D;
const #188 = Asciz	short2float;
const #189 = Asciz	(S)F;
const #190 = Asciz	short2long;
const #191 = Asciz	(S)J;
const #192 = Asciz	short2int;
const #193 = Asciz	(S)I;
const #194 = Asciz	byte2double;
const #195 = Asciz	(B)D;
const #196 = Asciz	byte2float;
const #197 = Asciz	(B)F;
const #198 = Asciz	byte2long;
const #199 = Asciz	(B)J;
const #200 = Asciz	byte2int;
const #201 = Asciz	(B)I;
const #202 = Asciz	byte2short;
const #203 = Asciz	(B)S;
const #204 = Asciz	unitArrayOps;
const #205 = Asciz	([Lscala/runtime/BoxedUnit;)Lscala/collection/mutable/ArrayOps;;
const #206 = Asciz	scala/collection/mutable/ArrayOps$ofUnit;
const #207 = class	#206;	//  scala/collection/mutable/ArrayOps$ofUnit
const #208 = Asciz	([Lscala/runtime/BoxedUnit;)V;
const #209 = NameAndType	#11:#208;//  "<init>":([Lscala/runtime/BoxedUnit;)V
const #210 = Method	#207.#209;	//  scala/collection/mutable/ArrayOps$ofUnit."<init>":([Lscala/runtime/BoxedUnit;)V
const #211 = Asciz	xs;
const #212 = Asciz	[Lscala/runtime/BoxedUnit;;
const #213 = Asciz	([Lscala/runtime/BoxedUnit;)Lscala/collection/mutable/ArrayOps<Ljava/lang/Object;>;;
const #214 = Asciz	booleanArrayOps;
const #215 = Asciz	([Z)Lscala/collection/mutable/ArrayOps;;
const #216 = Asciz	scala/collection/mutable/ArrayOps$ofBoolean;
const #217 = class	#216;	//  scala/collection/mutable/ArrayOps$ofBoolean
const #218 = Asciz	([Z)V;
const #219 = NameAndType	#11:#218;//  "<init>":([Z)V
const #220 = Method	#217.#219;	//  scala/collection/mutable/ArrayOps$ofBoolean."<init>":([Z)V
const #221 = Asciz	[Z;
const #222 = Asciz	([Z)Lscala/collection/mutable/ArrayOps<Ljava/lang/Boolean;>;;
const #223 = Asciz	shortArrayOps;
const #224 = Asciz	([S)Lscala/collection/mutable/ArrayOps;;
const #225 = Asciz	scala/collection/mutable/ArrayOps$ofShort;
const #226 = class	#225;	//  scala/collection/mutable/ArrayOps$ofShort
const #227 = Asciz	([S)V;
const #228 = NameAndType	#11:#227;//  "<init>":([S)V
const #229 = Method	#226.#228;	//  scala/collection/mutable/ArrayOps$ofShort."<init>":([S)V
const #230 = Asciz	[S;
const #231 = Asciz	([S)Lscala/collection/mutable/ArrayOps<Ljava/lang/Short;>;;
const #232 = Asciz	byteArrayOps;
const #233 = Asciz	([B)Lscala/collection/mutable/ArrayOps;;
const #234 = Asciz	scala/collection/mutable/ArrayOps$ofByte;
const #235 = class	#234;	//  scala/collection/mutable/ArrayOps$ofByte
const #236 = Asciz	([B)V;
const #237 = NameAndType	#11:#236;//  "<init>":([B)V
const #238 = Method	#235.#237;	//  scala/collection/mutable/ArrayOps$ofByte."<init>":([B)V
const #239 = Asciz	[B;
const #240 = Asciz	([B)Lscala/collection/mutable/ArrayOps<Ljava/lang/Byte;>;;
const #241 = Asciz	charArrayOps;
const #242 = Asciz	([C)Lscala/collection/mutable/ArrayOps;;
const #243 = Asciz	scala/collection/mutable/ArrayOps$ofChar;
const #244 = class	#243;	//  scala/collection/mutable/ArrayOps$ofChar
const #245 = Method	#244.#63;	//  scala/collection/mutable/ArrayOps$ofChar."<init>":([C)V
const #246 = Asciz	([C)Lscala/collection/mutable/ArrayOps<Ljava/lang/Character;>;;
const #247 = Asciz	floatArrayOps;
const #248 = Asciz	([F)Lscala/collection/mutable/ArrayOps;;
const #249 = Asciz	scala/collection/mutable/ArrayOps$ofFloat;
const #250 = class	#249;	//  scala/collection/mutable/ArrayOps$ofFloat
const #251 = Asciz	([F)V;
const #252 = NameAndType	#11:#251;//  "<init>":([F)V
const #253 = Method	#250.#252;	//  scala/collection/mutable/ArrayOps$ofFloat."<init>":([F)V
const #254 = Asciz	[F;
const #255 = Asciz	([F)Lscala/collection/mutable/ArrayOps<Ljava/lang/Float;>;;
const #256 = Asciz	longArrayOps;
const #257 = Asciz	([J)Lscala/collection/mutable/ArrayOps;;
const #258 = Asciz	scala/collection/mutable/ArrayOps$ofLong;
const #259 = class	#258;	//  scala/collection/mutable/ArrayOps$ofLong
const #260 = Asciz	([J)V;
const #261 = NameAndType	#11:#260;//  "<init>":([J)V
const #262 = Method	#259.#261;	//  scala/collection/mutable/ArrayOps$ofLong."<init>":([J)V
const #263 = Asciz	[J;
const #264 = Asciz	([J)Lscala/collection/mutable/ArrayOps<Ljava/lang/Long;>;;
const #265 = Asciz	doubleArrayOps;
const #266 = Asciz	([D)Lscala/collection/mutable/ArrayOps;;
const #267 = Asciz	scala/collection/mutable/ArrayOps$ofDouble;
const #268 = class	#267;	//  scala/collection/mutable/ArrayOps$ofDouble
const #269 = Asciz	([D)V;
const #270 = NameAndType	#11:#269;//  "<init>":([D)V
const #271 = Method	#268.#270;	//  scala/collection/mutable/ArrayOps$ofDouble."<init>":([D)V
const #272 = Asciz	[D;
const #273 = Asciz	([D)Lscala/collection/mutable/ArrayOps<Ljava/lang/Double;>;;
const #274 = Asciz	intArrayOps;
const #275 = Asciz	([I)Lscala/collection/mutable/ArrayOps;;
const #276 = Asciz	scala/collection/mutable/ArrayOps$ofInt;
const #277 = class	#276;	//  scala/collection/mutable/ArrayOps$ofInt
const #278 = Asciz	([I)V;
const #279 = NameAndType	#11:#278;//  "<init>":([I)V
const #280 = Method	#277.#279;	//  scala/collection/mutable/ArrayOps$ofInt."<init>":([I)V
const #281 = Asciz	[I;
const #282 = Asciz	([I)Lscala/collection/mutable/ArrayOps<Ljava/lang/Integer;>;;
const #283 = Asciz	refArrayOps;
const #284 = Asciz	([Ljava/lang/Object;)Lscala/collection/mutable/ArrayOps;;
const #285 = Asciz	scala/collection/mutable/ArrayOps$ofRef;
const #286 = class	#285;	//  scala/collection/mutable/ArrayOps$ofRef
const #287 = Asciz	([Ljava/lang/Object;)V;
const #288 = NameAndType	#11:#287;//  "<init>":([Ljava/lang/Object;)V
const #289 = Method	#286.#288;	//  scala/collection/mutable/ArrayOps$ofRef."<init>":([Ljava/lang/Object;)V
const #290 = Asciz	[Ljava/lang/Object;;
const #291 = Asciz	<T:Ljava/lang/Object;>([TT;)Lscala/collection/mutable/ArrayOps<TT;>;;
const #292 = Asciz	genericArrayOps;
const #293 = Asciz	(Ljava/lang/Object;)Lscala/collection/mutable/ArrayOps;;
const #294 = class	#290;	//  "[Ljava/lang/Object;"
const #295 = Asciz	scala/MatchError;
const #296 = class	#295;	//  scala/MatchError
const #297 = Asciz	java/lang/Object;
const #298 = class	#297;	//  java/lang/Object
const #299 = Asciz	toString;
const #300 = NameAndType	#299:#90;//  toString:()Ljava/lang/String;
const #301 = Method	#298.#300;	//  java/lang/Object.toString:()Ljava/lang/String;
const #302 = Method	#296.#98;	//  scala/MatchError."<init>":(Ljava/lang/String;)V
const #303 = class	#281;	//  "[I"
const #304 = class	#272;	//  "[D"
const #305 = class	#263;	//  "[J"
const #306 = class	#254;	//  "[F"
const #307 = class	#67;	//  "[C"
const #308 = class	#239;	//  "[B"
const #309 = class	#230;	//  "[S"
const #310 = class	#221;	//  "[Z"
const #311 = class	#212;	//  "[Lscala/runtime/BoxedUnit;"
const #312 = Asciz	temp2;
const #313 = Asciz	temp3;
const #314 = Asciz	temp4;
const #315 = Asciz	temp5;
const #316 = Asciz	temp6;
const #317 = Asciz	temp7;
const #318 = Asciz	temp8;
const #319 = Asciz	temp9;
const #320 = Asciz	temp10;
const #321 = Asciz	temp11;
const #322 = Asciz	exceptionWrapper;
const #323 = Asciz	(Ljava/lang/Throwable;)Lscala/runtime/RichException;;
const #324 = Asciz	scala/runtime/RichException;
const #325 = class	#324;	//  scala/runtime/RichException
const #326 = Asciz	(Ljava/lang/Throwable;)V;
const #327 = NameAndType	#11:#326;//  "<init>":(Ljava/lang/Throwable;)V
const #328 = Method	#325.#327;	//  scala/runtime/RichException."<init>":(Ljava/lang/Throwable;)V
const #329 = Asciz	exc;
const #330 = Asciz	Ljava/lang/Throwable;;
const #331 = Asciz	booleanWrapper;
const #332 = Asciz	(Z)Lscala/runtime/RichBoolean;;
const #333 = Asciz	scala/runtime/RichBoolean;
const #334 = class	#333;	//  scala/runtime/RichBoolean
const #335 = Asciz	(Z)V;
const #336 = NameAndType	#11:#335;//  "<init>":(Z)V
const #337 = Method	#334.#336;	//  scala/runtime/RichBoolean."<init>":(Z)V
const #338 = Asciz	doubleWrapper;
const #339 = Asciz	(D)Lscala/runtime/RichDouble;;
const #340 = Asciz	scala/runtime/RichDouble;
const #341 = class	#340;	//  scala/runtime/RichDouble
const #342 = Asciz	(D)V;
const #343 = NameAndType	#11:#342;//  "<init>":(D)V
const #344 = Method	#341.#343;	//  scala/runtime/RichDouble."<init>":(D)V
const #345 = Asciz	floatWrapper;
const #346 = Asciz	(F)Lscala/runtime/RichFloat;;
const #347 = Asciz	scala/runtime/RichFloat;
const #348 = class	#347;	//  scala/runtime/RichFloat
const #349 = Asciz	(F)V;
const #350 = NameAndType	#11:#349;//  "<init>":(F)V
const #351 = Method	#348.#350;	//  scala/runtime/RichFloat."<init>":(F)V
const #352 = Asciz	longWrapper;
const #353 = Asciz	(J)Lscala/runtime/RichLong;;
const #354 = Asciz	scala/runtime/RichLong;
const #355 = class	#354;	//  scala/runtime/RichLong
const #356 = Asciz	(J)V;
const #357 = NameAndType	#11:#356;//  "<init>":(J)V
const #358 = Method	#355.#357;	//  scala/runtime/RichLong."<init>":(J)V
const #359 = Asciz	charWrapper;
const #360 = Asciz	(C)Lscala/runtime/RichChar;;
const #361 = Asciz	scala/runtime/RichChar;
const #362 = class	#361;	//  scala/runtime/RichChar
const #363 = Asciz	(C)V;
const #364 = NameAndType	#11:#363;//  "<init>":(C)V
const #365 = Method	#362.#364;	//  scala/runtime/RichChar."<init>":(C)V
const #366 = Asciz	c;
const #367 = Asciz	intWrapper;
const #368 = Asciz	(I)Lscala/runtime/RichInt;;
const #369 = Asciz	scala/runtime/RichInt;
const #370 = class	#369;	//  scala/runtime/RichInt
const #371 = Asciz	(I)V;
const #372 = NameAndType	#11:#371;//  "<init>":(I)V
const #373 = Method	#370.#372;	//  scala/runtime/RichInt."<init>":(I)V
const #374 = Asciz	shortWrapper;
const #375 = Asciz	(S)Lscala/runtime/RichShort;;
const #376 = Asciz	scala/runtime/RichShort;
const #377 = class	#376;	//  scala/runtime/RichShort
const #378 = Asciz	(S)V;
const #379 = NameAndType	#11:#378;//  "<init>":(S)V
const #380 = Method	#377.#379;	//  scala/runtime/RichShort."<init>":(S)V
const #381 = Asciz	byteWrapper;
const #382 = Asciz	(B)Lscala/runtime/RichByte;;
const #383 = Asciz	scala/runtime/RichByte;
const #384 = class	#383;	//  scala/runtime/RichByte
const #385 = Asciz	(B)V;
const #386 = NameAndType	#11:#385;//  "<init>":(B)V
const #387 = Method	#384.#386;	//  scala/runtime/RichByte."<init>":(B)V
const #388 = Asciz	readf3;
const #389 = Asciz	(Ljava/lang/String;)Lscala/Tuple3;;
const #390 = Asciz	scala/Console$;
const #391 = class	#390;	//  scala/Console$
const #392 = Asciz	Lscala/Console$;;
const #393 = NameAndType	#4:#392;//  MODULE$:Lscala/Console$;
const #394 = Field	#391.#393;	//  scala/Console$.MODULE$:Lscala/Console$;
const #395 = NameAndType	#388:#389;//  readf3:(Ljava/lang/String;)Lscala/Tuple3;
const #396 = Method	#391.#395;	//  scala/Console$.readf3:(Ljava/lang/String;)Lscala/Tuple3;
const #397 = Asciz	format;
const #398 = Asciz	(Ljava/lang/String;)Lscala/Tuple3<Ljava/lang/Object;Ljava/lang/Object;Ljava/lang/Object;>;;
const #399 = Asciz	readf2;
const #400 = Asciz	(Ljava/lang/String;)Lscala/Tuple2;;
const #401 = NameAndType	#399:#400;//  readf2:(Ljava/lang/String;)Lscala/Tuple2;
const #402 = Method	#391.#401;	//  scala/Console$.readf2:(Ljava/lang/String;)Lscala/Tuple2;
const #403 = Asciz	(Ljava/lang/String;)Lscala/Tuple2<Ljava/lang/Object;Ljava/lang/Object;>;;
const #404 = Asciz	readf1;
const #405 = Asciz	(Ljava/lang/String;)Ljava/lang/Object;;
const #406 = NameAndType	#404:#405;//  readf1:(Ljava/lang/String;)Ljava/lang/Object;
const #407 = Method	#391.#406;	//  scala/Console$.readf1:(Ljava/lang/String;)Ljava/lang/Object;
const #408 = Asciz	readf;
const #409 = Asciz	(Ljava/lang/String;)Lscala/collection/immutable/List;;
const #410 = NameAndType	#408:#409;//  readf:(Ljava/lang/String;)Lscala/collection/immutable/List;
const #411 = Method	#391.#410;	//  scala/Console$.readf:(Ljava/lang/String;)Lscala/collection/immutable/List;
const #412 = Asciz	(Ljava/lang/String;)Lscala/collection/immutable/List<Ljava/lang/Object;>;;
const #413 = Asciz	readDouble;
const #414 = Asciz	()D;
const #415 = NameAndType	#413:#414;//  readDouble:()D
const #416 = Method	#391.#415;	//  scala/Console$.readDouble:()D
const #417 = Asciz	readFloat;
const #418 = Asciz	()F;
const #419 = NameAndType	#417:#418;//  readFloat:()F
const #420 = Method	#391.#419;	//  scala/Console$.readFloat:()F
const #421 = Asciz	readLong;
const #422 = Asciz	()J;
const #423 = NameAndType	#421:#422;//  readLong:()J
const #424 = Method	#391.#423;	//  scala/Console$.readLong:()J
const #425 = Asciz	readInt;
const #426 = Asciz	()I;
const #427 = NameAndType	#425:#426;//  readInt:()I
const #428 = Method	#391.#427;	//  scala/Console$.readInt:()I
const #429 = Asciz	readChar;
const #430 = Asciz	()C;
const #431 = NameAndType	#429:#430;//  readChar:()C
const #432 = Method	#391.#431;	//  scala/Console$.readChar:()C
const #433 = Asciz	readShort;
const #434 = Asciz	()S;
const #435 = NameAndType	#433:#434;//  readShort:()S
const #436 = Method	#391.#435;	//  scala/Console$.readShort:()S
const #437 = Asciz	readByte;
const #438 = Asciz	()B;
const #439 = NameAndType	#437:#438;//  readByte:()B
const #440 = Method	#391.#439;	//  scala/Console$.readByte:()B
const #441 = Asciz	readBoolean;
const #442 = Asciz	()Z;
const #443 = NameAndType	#441:#442;//  readBoolean:()Z
const #444 = Method	#391.#443;	//  scala/Console$.readBoolean:()Z
const #445 = Asciz	readLine;
const #446 = Asciz	(Ljava/lang/String;Lscala/collection/Seq;)Ljava/lang/String;;
const #447 = Asciz	genericWrapArray;
const #448 = Asciz	(Ljava/lang/Object;)Lscala/collection/mutable/WrappedArray;;
const #449 = NameAndType	#447:#448;//  genericWrapArray:(Ljava/lang/Object;)Lscala/collection/mutable/WrappedArray;
const #450 = Method	#10.#449;	//  scala/Predef$.genericWrapArray:(Ljava/lang/Object;)Lscala/collection/mutable/WrappedArray;
const #451 = NameAndType	#445:#446;//  readLine:(Ljava/lang/String;Lscala/collection/Seq;)Ljava/lang/String;
const #452 = Method	#391.#451;	//  scala/Console$.readLine:(Ljava/lang/String;Lscala/collection/Seq;)Ljava/lang/String;
const #453 = Asciz	text;
const #454 = Asciz	args;
const #455 = Asciz	Lscala/collection/Seq;;
const #456 = Asciz	(Ljava/lang/String;Lscala/collection/Seq<Ljava/lang/Object;>;)Ljava/lang/String;;
const #457 = NameAndType	#445:#90;//  readLine:()Ljava/lang/String;
const #458 = Method	#391.#457;	//  scala/Console$.readLine:()Ljava/lang/String;
const #459 = NameAndType	#95:#96;//  augmentString:(Ljava/lang/String;)Lscala/collection/immutable/StringOps;
const #460 = Method	#10.#459;	//  scala/Predef$.augmentString:(Ljava/lang/String;)Lscala/collection/immutable/StringOps;
const #461 = Asciz	scala/collection/immutable/StringLike;
const #462 = class	#461;	//  scala/collection/immutable/StringLike
const #463 = Asciz	(Lscala/collection/Seq;)Ljava/lang/String;;
const #464 = NameAndType	#397:#463;//  format:(Lscala/collection/Seq;)Ljava/lang/String;
const #465 = InterfaceMethod	#462.#464;	//  scala/collection/immutable/StringLike.format:(Lscala/collection/Seq;)Ljava/lang/String;
const #466 = Asciz	printf;
const #467 = Asciz	(Ljava/lang/String;Lscala/collection/Seq;)V;
const #468 = NameAndType	#397:#446;//  format:(Ljava/lang/String;Lscala/collection/Seq;)Ljava/lang/String;
const #469 = Method	#10.#468;	//  scala/Predef$.format:(Ljava/lang/String;Lscala/collection/Seq;)Ljava/lang/String;
const #470 = NameAndType	#466:#467;//  printf:(Ljava/lang/String;Lscala/collection/Seq;)V
const #471 = Method	#391.#470;	//  scala/Console$.printf:(Ljava/lang/String;Lscala/collection/Seq;)V
const #472 = Asciz	(Ljava/lang/String;Lscala/collection/Seq<Ljava/lang/Object;>;)V;
const #473 = Asciz	println;
const #474 = NameAndType	#473:#105;//  println:(Ljava/lang/Object;)V
const #475 = Method	#391.#474;	//  scala/Console$.println:(Ljava/lang/Object;)V
const #476 = NameAndType	#473:#7;//  println:()V
const #477 = Method	#391.#476;	//  scala/Console$.println:()V
const #478 = Asciz	print;
const #479 = NameAndType	#478:#105;//  print:(Ljava/lang/Object;)V
const #480 = Method	#391.#479;	//  scala/Console$.print:(Ljava/lang/Object;)V
const #481 = Asciz	any2ArrowAssoc;
const #482 = Asciz	(Ljava/lang/Object;)Lscala/Predef$ArrowAssoc;;
const #483 = Asciz	scala/Predef$ArrowAssoc;
const #484 = class	#483;	//  scala/Predef$ArrowAssoc
const #485 = Method	#484.#106;	//  scala/Predef$ArrowAssoc."<init>":(Ljava/lang/Object;)V
const #486 = Asciz	<A:Ljava/lang/Object;>(TA;)Lscala/Predef$ArrowAssoc<TA;>;;
const #487 = Asciz	any2Ensuring;
const #488 = Asciz	(Ljava/lang/Object;)Lscala/Predef$Ensuring;;
const #489 = Asciz	scala/Predef$Ensuring;
const #490 = class	#489;	//  scala/Predef$Ensuring
const #491 = Method	#490.#106;	//  scala/Predef$Ensuring."<init>":(Ljava/lang/Object;)V
const #492 = Asciz	<A:Ljava/lang/Object;>(TA;)Lscala/Predef$Ensuring<TA;>;;
const #493 = Asciz	require;
const #494 = Asciz	(ZLscala/Function0;)V;
const #495 = Asciz	java/lang/IllegalArgumentException;
const #496 = class	#495;	//  java/lang/IllegalArgumentException
const #497 = Asciz	scala/collection/mutable/StringBuilder;
const #498 = class	#497;	//  scala/collection/mutable/StringBuilder
const #499 = Method	#498.#12;	//  scala/collection/mutable/StringBuilder."<init>":()V
const #500 = Asciz	requirement failed: ;
const #501 = String	#500;	//  requirement failed: 
const #502 = Asciz	append;
const #503 = Asciz	(Ljava/lang/Object;)Lscala/collection/mutable/StringBuilder;;
const #504 = NameAndType	#502:#503;//  append:(Ljava/lang/Object;)Lscala/collection/mutable/StringBuilder;
const #505 = Method	#498.#504;	//  scala/collection/mutable/StringBuilder.append:(Ljava/lang/Object;)Lscala/collection/mutable/StringBuilder;
const #506 = Asciz	scala/Function0;
const #507 = class	#506;	//  scala/Function0
const #508 = Asciz	apply;
const #509 = Asciz	()Ljava/lang/Object;;
const #510 = NameAndType	#508:#509;//  apply:()Ljava/lang/Object;
const #511 = InterfaceMethod	#507.#510;	//  scala/Function0.apply:()Ljava/lang/Object;
const #512 = Method	#498.#300;	//  scala/collection/mutable/StringBuilder.toString:()Ljava/lang/String;
const #513 = Method	#496.#98;	//  java/lang/IllegalArgumentException."<init>":(Ljava/lang/String;)V
const #514 = Asciz	requirement;
const #515 = Asciz	message;
const #516 = Asciz	Lscala/Function0;;
const #517 = Asciz	(ZLscala/Function0<Ljava/lang/Object;>;)V;
const #518 = Asciz	requirement failed;
const #519 = String	#518;	//  requirement failed
const #520 = Asciz	assume;
const #521 = Asciz	java/lang/AssertionError;
const #522 = class	#521;	//  java/lang/AssertionError
const #523 = Asciz	assumption failed: ;
const #524 = String	#523;	//  assumption failed: 
const #525 = Method	#522.#106;	//  java/lang/AssertionError."<init>":(Ljava/lang/Object;)V
const #526 = Asciz	assumption;
const #527 = Asciz	assumption failed;
const #528 = String	#527;	//  assumption failed
const #529 = Asciz	assert;
const #530 = Asciz	assertion failed: ;
const #531 = String	#530;	//  assertion failed: 
const #532 = Asciz	assertion;
const #533 = Asciz	assertion failed;
const #534 = String	#533;	//  assertion failed
const #535 = Asciz	exit;
const #536 = Asciz	(I)Lscala/runtime/Nothing$;;
const #537 = Asciz	java/lang/System;
const #538 = class	#537;	//  java/lang/System
const #539 = NameAndType	#535:#371;//  exit:(I)V
const #540 = Method	#538.#539;	//  java/lang/System.exit:(I)V
const #541 = Asciz	java/lang/Throwable;
const #542 = class	#541;	//  java/lang/Throwable
const #543 = Method	#542.#12;	//  java/lang/Throwable."<init>":()V
const #544 = Asciz	status;
const #545 = Asciz	()Lscala/runtime/Nothing$;;
const #546 = NameAndType	#535:#536;//  exit:(I)Lscala/runtime/Nothing$;
const #547 = Method	#10.#546;	//  scala/Predef$.exit:(I)Lscala/runtime/Nothing$;
const #548 = Asciz	error;
const #549 = Asciz	(Ljava/lang/String;)Lscala/runtime/Nothing$;;
const #550 = Asciz	java/lang/RuntimeException;
const #551 = class	#550;	//  java/lang/RuntimeException
const #552 = Method	#551.#98;	//  java/lang/RuntimeException."<init>":(Ljava/lang/String;)V
const #553 = Asciz	hash;
const #554 = Asciz	(I)I;
const #555 = Asciz	(Ljava/lang/Long;)I;
const #556 = Asciz	intValue;
const #557 = NameAndType	#556:#426;//  intValue:()I
const #558 = Method	#134.#557;	//  java/lang/Long.intValue:()I
const #559 = Asciz	longValue;
const #560 = NameAndType	#559:#422;//  longValue:()J
const #561 = Method	#134.#560;	//  java/lang/Long.longValue:()J
const #562 = Asciz	hashCode;
const #563 = NameAndType	#562:#426;//  hashCode:()I
const #564 = Method	#134.#563;	//  java/lang/Long.hashCode:()I
const #565 = Asciz	Ljava/lang/Long;;
const #566 = Asciz	iv;
const #567 = Asciz	(Ljava/lang/Number;)I;
const #568 = Asciz	scala/runtime/BoxesRunTime;
const #569 = class	#568;	//  scala/runtime/BoxesRunTime
const #570 = Asciz	hashFromNumber;
const #571 = NameAndType	#570:#567;//  hashFromNumber:(Ljava/lang/Number;)I
const #572 = Method	#569.#571;	//  scala/runtime/BoxesRunTime.hashFromNumber:(Ljava/lang/Number;)I
const #573 = Asciz	Ljava/lang/Number;;
const #574 = Asciz	(Ljava/lang/Object;)I;
const #575 = Asciz	java/lang/Number;
const #576 = class	#575;	//  java/lang/Number
const #577 = Method	#298.#563;	//  java/lang/Object.hashCode:()I
const #578 = Asciz	locally;
const #579 = Asciz	(Ljava/lang/Object;)Ljava/lang/Object;;
const #580 = Asciz	<T:Ljava/lang/Object;>(TT;)TT;;
const #581 = Asciz	currentThread;
const #582 = Asciz	()Ljava/lang/Thread;;
const #583 = Asciz	java/lang/Thread;
const #584 = class	#583;	//  java/lang/Thread
const #585 = NameAndType	#581:#582;//  currentThread:()Ljava/lang/Thread;
const #586 = Method	#584.#585;	//  java/lang/Thread.currentThread:()Ljava/lang/Thread;
const #587 = Asciz	identity;
const #588 = Asciz	<A:Ljava/lang/Object;>(TA;)TA;;
const #589 = Asciz	classManifest;
const #590 = Asciz	(Lscala/reflect/ClassManifest;)Lscala/reflect/ClassManifest;;
const #591 = Asciz	m;
const #592 = Asciz	Lscala/reflect/ClassManifest;;
const #593 = Asciz	<T:Ljava/lang/Object;>(Lscala/reflect/ClassManifest<TT;>;)Lscala/reflect/ClassManifest<TT;>;;
const #594 = Asciz	manifest;
const #595 = Asciz	(Lscala/reflect/Manifest;)Lscala/reflect/Manifest;;
const #596 = Asciz	Lscala/reflect/Manifest;;
const #597 = Asciz	<T:Ljava/lang/Object;>(Lscala/reflect/Manifest<TT;>;)Lscala/reflect/Manifest<TT;>;;
const #598 = Asciz	implicitly;
const #599 = Asciz	e;
const #600 = Asciz	()Lscala/collection/immutable/Set$;;
const #601 = Asciz	()Lscala/collection/immutable/Map$;;
const #602 = Asciz	classOf;
const #603 = Asciz	()Ljava/lang/Class;;
const #604 = Asciz	<T:Ljava/lang/Object;>()Ljava/lang/Class<TT;>;;
const #605 = Asciz	InnerClasses;
const #606 = Asciz	scala/collection/mutable/ArrayOps;
const #607 = class	#606;	//  scala/collection/mutable/ArrayOps
const #608 = Asciz	ofRef;
const #609 = Asciz	ofInt;
const #610 = Asciz	scala/Predef;
const #611 = class	#610;	//  scala/Predef
const #612 = Asciz	$anon$1;
const #613 = Asciz	$anon$6;
const #614 = Asciz	$anon$5;
const #615 = Asciz	$anon$4;
const #616 = Asciz	ofLong;
const #617 = Asciz	ofChar;
const #618 = Asciz	ofByte;
const #619 = Asciz	ofUnit;
const #620 = Asciz	Ensuring;
const #621 = Asciz	ofFloat;
const #622 = Asciz	ofShort;
const #623 = Asciz	ofDouble;
const #624 = Asciz	ArrowAssoc;
const #625 = Asciz	ofBoolean;
const #626 = Asciz	scala/Predef$$eq$colon$eq;
const #627 = class	#626;	//  scala/Predef$$eq$colon$eq
const #628 = Asciz	$eq$colon$eq;
const #629 = Asciz	scala/Predef$DummyImplicit;
const #630 = class	#629;	//  scala/Predef$DummyImplicit
const #631 = Asciz	DummyImplicit;
const #632 = Asciz	scala/Predef$$less$colon$less;
const #633 = class	#632;	//  scala/Predef$$less$colon$less
const #634 = Asciz	$less$colon$less;
const #635 = Asciz	scala/Predef$$less$percent$less;
const #636 = class	#635;	//  scala/Predef$$less$percent$less
const #637 = Asciz	$less$percent$less;
const #638 = Asciz	scala/ScalaObject;
const #639 = class	#638;	//  scala/ScalaObject

{
public static final scala.Predef$ MODULE$;

public static {};
  Code:
   Stack=1, Locals=0, Args_size=0
   0:	new	#10; //class scala/Predef$
   3:	invokespecial	#13; //Method "<init>":()V
   6:	return

public scala.Predef$$less$colon$less conforms();
  Code:
   Stack=2, Locals=1, Args_size=1
   0:	new	#54; //class scala/Predef$$anon$1
   3:	dup
   4:	invokespecial	#55; //Method scala/Predef$$anon$1."<init>":()V
   7:	areturn
  LineNumberTable: 
   line 282: 0

  Signature: length = 0x2
   00 38 

public java.lang.CharSequence arrayToCharSequence(char[]);
  Code:
   Stack=3, Locals=2, Args_size=2
   0:	new	#61; //class scala/Predef$$anon$6
   3:	dup
   4:	aload_1
   5:	invokespecial	#64; //Method scala/Predef$$anon$6."<init>":([C)V
   8:	areturn
  LineNumberTable: 
   line 266: 0

  LocalVariableTable: 
   Start  Length  Slot  Name   Signature
   0      9      0    this       Lscala/Predef$;
   0      9      1    xs$1       [C


public java.lang.CharSequence seqToCharSequence(scala.collection.IndexedSeq);
  Code:
   Stack=3, Locals=2, Args_size=2
   0:	new	#72; //class scala/Predef$$anon$5
   3:	dup
   4:	aload_1
   5:	invokespecial	#75; //Method scala/Predef$$anon$5."<init>":(Lscala/collection/IndexedSeq;)V
   8:	areturn
  LineNumberTable: 
   line 259: 0

  LocalVariableTable: 
   Start  Length  Slot  Name   Signature
   0      9      0    this       Lscala/Predef$;
   0      9      1    xs$2       Lscala/collection/IndexedSeq;

  Signature: length = 0x2
   00 4E 

public scala.collection.generic.CanBuildFrom stringCanBuildFrom();
  Code:
   Stack=2, Locals=1, Args_size=1
   0:	new	#82; //class scala/Predef$$anon$4
   3:	dup
   4:	invokespecial	#83; //Method scala/Predef$$anon$4."<init>":()V
   7:	areturn
  LineNumberTable: 
   line 254: 0

  Signature: length = 0x2
   00 54 

public java.lang.String unaugmentString(scala.collection.immutable.StringOps);
  Code:
   Stack=1, Locals=2, Args_size=2
   0:	aload_1
   1:	invokevirtual	#92; //Method scala/collection/immutable/StringOps.repr:()Ljava/lang/String;
   4:	areturn
  LineNumberTable: 
   line 251: 0

  LocalVariableTable: 
   Start  Length  Slot  Name   Signature
   0      5      0    this       Lscala/Predef$;
   0      5      1    x       Lscala/collection/immutable/StringOps;


public scala.collection.immutable.StringOps augmentString(java.lang.String);
  Code:
   Stack=3, Locals=2, Args_size=2
   0:	new	#88; //class scala/collection/immutable/StringOps
   3:	dup
   4:	aload_1
   5:	invokespecial	#99; //Method scala/collection/immutable/StringOps."<init>":(Ljava/lang/String;)V
   8:	areturn
  LineNumberTable: 
   line 250: 0

  LocalVariableTable: 
   Start  Length  Slot  Name   Signature
   0      9      0    this       Lscala/Predef$;
   0      9      1    x       Ljava/lang/String;


public scala.runtime.StringAdd any2stringadd(java.lang.Object);
  Code:
   Stack=3, Locals=2, Args_size=2
   0:	new	#104; //class scala/runtime/StringAdd
   3:	dup
   4:	aload_1
   5:	invokespecial	#107; //Method scala/runtime/StringAdd."<init>":(Ljava/lang/Object;)V
   8:	areturn
  LineNumberTable: 
   line 249: 0

  LocalVariableTable: 
   Start  Length  Slot  Name   Signature
   0      9      0    this       Lscala/Predef$;
   0      9      1    x       Ljava/lang/Object;


public java.lang.Boolean boolean2Boolean(boolean);
  Code:
   Stack=1, Locals=2, Args_size=2
   0:	iload_1
   1:	invokestatic	#115; //Method java/lang/Boolean.valueOf:(Z)Ljava/lang/Boolean;
   4:	areturn
  LineNumberTable: 
   line 245: 0

  LocalVariableTable: 
   Start  Length  Slot  Name   Signature
   0      5      0    this       Lscala/Predef$;
   0      5      1    x       Z


public java.lang.Double double2Double(double);
  Code:
   Stack=2, Locals=3, Args_size=2
   0:	dload_1
   1:	invokestatic	#122; //Method java/lang/Double.valueOf:(D)Ljava/lang/Double;
   4:	areturn
  LineNumberTable: 
   line 244: 0

  LocalVariableTable: 
   Start  Length  Slot  Name   Signature
   0      5      0    this       Lscala/Predef$;
   0      5      1    x       D


public java.lang.Float float2Float(float);
  Code:
   Stack=1, Locals=2, Args_size=2
   0:	fload_1
   1:	invokestatic	#129; //Method java/lang/Float.valueOf:(F)Ljava/lang/Float;
   4:	areturn
  LineNumberTable: 
   line 243: 0

  LocalVariableTable: 
   Start  Length  Slot  Name   Signature
   0      5      0    this       Lscala/Predef$;
   0      5      1    x       F


public java.lang.Long long2Long(long);
  Code:
   Stack=2, Locals=3, Args_size=2
   0:	lload_1
   1:	invokestatic	#136; //Method java/lang/Long.valueOf:(J)Ljava/lang/Long;
   4:	areturn
  LineNumberTable: 
   line 242: 0

  LocalVariableTable: 
   Start  Length  Slot  Name   Signature
   0      5      0    this       Lscala/Predef$;
   0      5      1    x       J


public java.lang.Integer int2Integer(int);
  Code:
   Stack=1, Locals=2, Args_size=2
   0:	iload_1
   1:	invokestatic	#143; //Method java/lang/Integer.valueOf:(I)Ljava/lang/Integer;
   4:	areturn
  LineNumberTable: 
   line 241: 0

  LocalVariableTable: 
   Start  Length  Slot  Name   Signature
   0      5      0    this       Lscala/Predef$;
   0      5      1    x       I


public java.lang.Character char2Character(char);
  Code:
   Stack=1, Locals=2, Args_size=2
   0:	iload_1
   1:	invokestatic	#150; //Method java/lang/Character.valueOf:(C)Ljava/lang/Character;
   4:	areturn
  LineNumberTable: 
   line 240: 0

  LocalVariableTable: 
   Start  Length  Slot  Name   Signature
   0      5      0    this       Lscala/Predef$;
   0      5      1    x       C


public java.lang.Short short2Short(short);
  Code:
   Stack=1, Locals=2, Args_size=2
   0:	iload_1
   1:	invokestatic	#157; //Method java/lang/Short.valueOf:(S)Ljava/lang/Short;
   4:	areturn
  LineNumberTable: 
   line 239: 0

  LocalVariableTable: 
   Start  Length  Slot  Name   Signature
   0      5      0    this       Lscala/Predef$;
   0      5      1    x       S


public java.lang.Byte byte2Byte(byte);
  Code:
   Stack=1, Locals=2, Args_size=2
   0:	iload_1
   1:	invokestatic	#164; //Method java/lang/Byte.valueOf:(B)Ljava/lang/Byte;
   4:	areturn
  LineNumberTable: 
   line 238: 0

  LocalVariableTable: 
   Start  Length  Slot  Name   Signature
   0      5      0    this       Lscala/Predef$;
   0      5      1    x       B


public double float2double(float);
  Code:
   Stack=2, Locals=2, Args_size=2
   0:	fload_1
   1:	f2d
   2:	dreturn
  LineNumberTable: 
   line 234: 0

  LocalVariableTable: 
   Start  Length  Slot  Name   Signature
   0      3      0    this       Lscala/Predef$;
   0      3      1    x       F


public double long2double(long);
  Code:
   Stack=2, Locals=3, Args_size=2
   0:	lload_1
   1:	l2d
   2:	dreturn
  LineNumberTable: 
   line 232: 0

  LocalVariableTable: 
   Start  Length  Slot  Name   Signature
   0      3      0    this       Lscala/Predef$;
   0      3      1    x       J


public float long2float(long);
  Code:
   Stack=2, Locals=3, Args_size=2
   0:	lload_1
   1:	l2f
   2:	freturn
  LineNumberTable: 
   line 231: 0

  LocalVariableTable: 
   Start  Length  Slot  Name   Signature
   0      3      0    this       Lscala/Predef$;
   0      3      1    x       J


public double int2double(int);
  Code:
   Stack=2, Locals=2, Args_size=2
   0:	iload_1
   1:	i2d
   2:	dreturn
  LineNumberTable: 
   line 229: 0

  LocalVariableTable: 
   Start  Length  Slot  Name   Signature
   0      3      0    this       Lscala/Predef$;
   0      3      1    x       I


public float int2float(int);
  Code:
   Stack=1, Locals=2, Args_size=2
   0:	iload_1
   1:	i2f
   2:	freturn
  LineNumberTable: 
   line 228: 0

  LocalVariableTable: 
   Start  Length  Slot  Name   Signature
   0      3      0    this       Lscala/Predef$;
   0      3      1    x       I


public long int2long(int);
  Code:
   Stack=2, Locals=2, Args_size=2
   0:	iload_1
   1:	i2l
   2:	lreturn
  LineNumberTable: 
   line 227: 0

  LocalVariableTable: 
   Start  Length  Slot  Name   Signature
   0      3      0    this       Lscala/Predef$;
   0      3      1    x       I


public double char2double(char);
  Code:
   Stack=2, Locals=2, Args_size=2
   0:	iload_1
   1:	i2d
   2:	dreturn
  LineNumberTable: 
   line 225: 0

  LocalVariableTable: 
   Start  Length  Slot  Name   Signature
   0      3      0    this       Lscala/Predef$;
   0      3      1    x       C


public float char2float(char);
  Code:
   Stack=1, Locals=2, Args_size=2
   0:	iload_1
   1:	i2f
   2:	freturn
  LineNumberTable: 
   line 224: 0

  LocalVariableTable: 
   Start  Length  Slot  Name   Signature
   0      3      0    this       Lscala/Predef$;
   0      3      1    x       C


public long char2long(char);
  Code:
   Stack=2, Locals=2, Args_size=2
   0:	iload_1
   1:	i2l
   2:	lreturn
  LineNumberTable: 
   line 223: 0

  LocalVariableTable: 
   Start  Length  Slot  Name   Signature
   0      3      0    this       Lscala/Predef$;
   0      3      1    x       C


public int char2int(char);
  Code:
   Stack=1, Locals=2, Args_size=2
   0:	iload_1
   1:	ireturn
  LineNumberTable: 
   line 222: 0

  LocalVariableTable: 
   Start  Length  Slot  Name   Signature
   0      2      0    this       Lscala/Predef$;
   0      2      1    x       C


public double short2double(short);
  Code:
   Stack=2, Locals=2, Args_size=2
   0:	iload_1
   1:	i2d
   2:	dreturn
  LineNumberTable: 
   line 220: 0

  LocalVariableTable: 
   Start  Length  Slot  Name   Signature
   0      3      0    this       Lscala/Predef$;
   0      3      1    x       S


public float short2float(short);
  Code:
   Stack=1, Locals=2, Args_size=2
   0:	iload_1
   1:	i2f
   2:	freturn
  LineNumberTable: 
   line 219: 0

  LocalVariableTable: 
   Start  Length  Slot  Name   Signature
   0      3      0    this       Lscala/Predef$;
   0      3      1    x       S


public long short2long(short);
  Code:
   Stack=2, Locals=2, Args_size=2
   0:	iload_1
   1:	i2l
   2:	lreturn
  LineNumberTable: 
   line 218: 0

  LocalVariableTable: 
   Start  Length  Slot  Name   Signature
   0      3      0    this       Lscala/Predef$;
   0      3      1    x       S


public int short2int(short);
  Code:
   Stack=1, Locals=2, Args_size=2
   0:	iload_1
   1:	ireturn
  LineNumberTable: 
   line 217: 0

  LocalVariableTable: 
   Start  Length  Slot  Name   Signature
   0      2      0    this       Lscala/Predef$;
   0      2      1    x       S


public double byte2double(byte);
  Code:
   Stack=2, Locals=2, Args_size=2
   0:	iload_1
   1:	i2d
   2:	dreturn
  LineNumberTable: 
   line 215: 0

  LocalVariableTable: 
   Start  Length  Slot  Name   Signature
   0      3      0    this       Lscala/Predef$;
   0      3      1    x       B


public float byte2float(byte);
  Code:
   Stack=1, Locals=2, Args_size=2
   0:	iload_1
   1:	i2f
   2:	freturn
  LineNumberTable: 
   line 214: 0

  LocalVariableTable: 
   Start  Length  Slot  Name   Signature
   0      3      0    this       Lscala/Predef$;
   0      3      1    x       B


public long byte2long(byte);
  Code:
   Stack=2, Locals=2, Args_size=2
   0:	iload_1
   1:	i2l
   2:	lreturn
  LineNumberTable: 
   line 213: 0

  LocalVariableTable: 
   Start  Length  Slot  Name   Signature
   0      3      0    this       Lscala/Predef$;
   0      3      1    x       B


public int byte2int(byte);
  Code:
   Stack=1, Locals=2, Args_size=2
   0:	iload_1
   1:	ireturn
  LineNumberTable: 
   line 212: 0

  LocalVariableTable: 
   Start  Length  Slot  Name   Signature
   0      2      0    this       Lscala/Predef$;
   0      2      1    x       B


public short byte2short(byte);
  Code:
   Stack=1, Locals=2, Args_size=2
   0:	iload_1
   1:	ireturn
  LineNumberTable: 
   line 211: 0

  LocalVariableTable: 
   Start  Length  Slot  Name   Signature
   0      2      0    this       Lscala/Predef$;
   0      2      1    x       B


public scala.collection.mutable.ArrayOps unitArrayOps(scala.runtime.BoxedUnit[]);
  Code:
   Stack=3, Locals=2, Args_size=2
   0:	new	#207; //class scala/collection/mutable/ArrayOps$ofUnit
   3:	dup
   4:	aload_1
   5:	invokespecial	#210; //Method scala/collection/mutable/ArrayOps$ofUnit."<init>":([Lscala/runtime/BoxedUnit;)V
   8:	areturn
  LineNumberTable: 
   line 207: 0

  LocalVariableTable: 
   Start  Length  Slot  Name   Signature
   0      9      0    this       Lscala/Predef$;
   0      9      1    xs       [Lscala/runtime/BoxedUnit;

  Signature: length = 0x2
   00 FFFFFFD5 

public scala.collection.mutable.ArrayOps booleanArrayOps(boolean[]);
  Code:
   Stack=3, Locals=2, Args_size=2
   0:	new	#217; //class scala/collection/mutable/ArrayOps$ofBoolean
   3:	dup
   4:	aload_1
   5:	invokespecial	#220; //Method scala/collection/mutable/ArrayOps$ofBoolean."<init>":([Z)V
   8:	areturn
  LineNumberTable: 
   line 206: 0

  LocalVariableTable: 
   Start  Length  Slot  Name   Signature
   0      9      0    this       Lscala/Predef$;
   0      9      1    xs       [Z

  Signature: length = 0x2
   00 FFFFFFDE 

public scala.collection.mutable.ArrayOps shortArrayOps(short[]);
  Code:
   Stack=3, Locals=2, Args_size=2
   0:	new	#226; //class scala/collection/mutable/ArrayOps$ofShort
   3:	dup
   4:	aload_1
   5:	invokespecial	#229; //Method scala/collection/mutable/ArrayOps$ofShort."<init>":([S)V
   8:	areturn
  LineNumberTable: 
   line 205: 0

  LocalVariableTable: 
   Start  Length  Slot  Name   Signature
   0      9      0    this       Lscala/Predef$;
   0      9      1    xs       [S

  Signature: length = 0x2
   00 FFFFFFE7 

public scala.collection.mutable.ArrayOps byteArrayOps(byte[]);
  Code:
   Stack=3, Locals=2, Args_size=2
   0:	new	#235; //class scala/collection/mutable/ArrayOps$ofByte
   3:	dup
   4:	aload_1
   5:	invokespecial	#238; //Method scala/collection/mutable/ArrayOps$ofByte."<init>":([B)V
   8:	areturn
  LineNumberTable: 
   line 204: 0

  LocalVariableTable: 
   Start  Length  Slot  Name   Signature
   0      9      0    this       Lscala/Predef$;
   0      9      1    xs       [B

  Signature: length = 0x2
   00 FFFFFFF0 

public scala.collection.mutable.ArrayOps charArrayOps(char[]);
  Code:
   Stack=3, Locals=2, Args_size=2
   0:	new	#244; //class scala/collection/mutable/ArrayOps$ofChar
   3:	dup
   4:	aload_1
   5:	invokespecial	#245; //Method scala/collection/mutable/ArrayOps$ofChar."<init>":([C)V
   8:	areturn
  LineNumberTable: 
   line 203: 0

  LocalVariableTable: 
   Start  Length  Slot  Name   Signature
   0      9      0    this       Lscala/Predef$;
   0      9      1    xs       [C

  Signature: length = 0x2
   00 FFFFFFF6 

public scala.collection.mutable.ArrayOps floatArrayOps(float[]);
  Code:
   Stack=3, Locals=2, Args_size=2
   0:	new	#250; //class scala/collection/mutable/ArrayOps$ofFloat
   3:	dup
   4:	aload_1
   5:	invokespecial	#253; //Method scala/collection/mutable/ArrayOps$ofFloat."<init>":([F)V
   8:	areturn
  LineNumberTable: 
   line 202: 0

  LocalVariableTable: 
   Start  Length  Slot  Name   Signature
   0      9      0    this       Lscala/Predef$;
   0      9      1    xs       [F

  Signature: length = 0x2
   00 FFFFFFFF 

public scala.collection.mutable.ArrayOps longArrayOps(long[]);
  Code:
   Stack=3, Locals=2, Args_size=2
   0:	new	#259; //class scala/collection/mutable/ArrayOps$ofLong
   3:	dup
   4:	aload_1
   5:	invokespecial	#262; //Method scala/collection/mutable/ArrayOps$ofLong."<init>":([J)V
   8:	areturn
  LineNumberTable: 
   line 201: 0

  LocalVariableTable: 
   Start  Length  Slot  Name   Signature
   0      9      0    this       Lscala/Predef$;
   0      9      1    xs       [J

  Signature: length = 0x2
   01 08 

public scala.collection.mutable.ArrayOps doubleArrayOps(double[]);
  Code:
   Stack=3, Locals=2, Args_size=2
   0:	new	#268; //class scala/collection/mutable/ArrayOps$ofDouble
   3:	dup
   4:	aload_1
   5:	invokespecial	#271; //Method scala/collection/mutable/ArrayOps$ofDouble."<init>":([D)V
   8:	areturn
  LineNumberTable: 
   line 200: 0

  LocalVariableTable: 
   Start  Length  Slot  Name   Signature
   0      9      0    this       Lscala/Predef$;
   0      9      1    xs       [D

  Signature: length = 0x2
   01 11 

public scala.collection.mutable.ArrayOps intArrayOps(int[]);
  Code:
   Stack=3, Locals=2, Args_size=2
   0:	new	#277; //class scala/collection/mutable/ArrayOps$ofInt
   3:	dup
   4:	aload_1
   5:	invokespecial	#280; //Method scala/collection/mutable/ArrayOps$ofInt."<init>":([I)V
   8:	areturn
  LineNumberTable: 
   line 199: 0

  LocalVariableTable: 
   Start  Length  Slot  Name   Signature
   0      9      0    this       Lscala/Predef$;
   0      9      1    xs       [I

  Signature: length = 0x2
   01 1A 

public scala.collection.mutable.ArrayOps refArrayOps(java.lang.Object[]);
  Code:
   Stack=3, Locals=2, Args_size=2
   0:	new	#286; //class scala/collection/mutable/ArrayOps$ofRef
   3:	dup
   4:	aload_1
   5:	invokespecial	#289; //Method scala/collection/mutable/ArrayOps$ofRef."<init>":([Ljava/lang/Object;)V
   8:	areturn
  LineNumberTable: 
   line 198: 0

  LocalVariableTable: 
   Start  Length  Slot  Name   Signature
   0      9      0    this       Lscala/Predef$;
   0      9      1    xs       [Ljava/lang/Object;

  Signature: length = 0x2
   01 23 

public scala.collection.mutable.ArrayOps genericArrayOps(java.lang.Object);
  Code:
   Stack=3, Locals=12, Args_size=2
   0:	aload_1
   1:	instanceof	#294; //class "[Ljava/lang/Object;"
   4:	ifeq	39
   7:	aload_1
   8:	checkcast	#294; //class "[Ljava/lang/Object;"
   11:	astore_2
   12:	iconst_1
   13:	ifeq	27
   16:	new	#286; //class scala/collection/mutable/ArrayOps$ofRef
   19:	dup
   20:	aload_2
   21:	invokespecial	#289; //Method scala/collection/mutable/ArrayOps$ofRef."<init>":([Ljava/lang/Object;)V
   24:	goto	415
   27:	new	#296; //class scala/MatchError
   30:	dup
   31:	aload_1
   32:	invokevirtual	#301; //Method java/lang/Object.toString:()Ljava/lang/String;
   35:	invokespecial	#302; //Method scala/MatchError."<init>":(Ljava/lang/String;)V
   38:	athrow
   39:	aload_1
   40:	instanceof	#303; //class "[I"
   43:	ifeq	78
   46:	aload_1
   47:	checkcast	#303; //class "[I"
   50:	astore_3
   51:	iconst_1
   52:	ifeq	66
   55:	new	#277; //class scala/collection/mutable/ArrayOps$ofInt
   58:	dup
   59:	aload_3
   60:	invokespecial	#280; //Method scala/collection/mutable/ArrayOps$ofInt."<init>":([I)V
   63:	goto	415
   66:	new	#296; //class scala/MatchError
   69:	dup
   70:	aload_1
   71:	invokevirtual	#301; //Method java/lang/Object.toString:()Ljava/lang/String;
   74:	invokespecial	#302; //Method scala/MatchError."<init>":(Ljava/lang/String;)V
   77:	athrow
   78:	aload_1
   79:	instanceof	#304; //class "[D"
   82:	ifeq	119
   85:	aload_1
   86:	checkcast	#304; //class "[D"
   89:	astore	4
   91:	iconst_1
   92:	ifeq	107
   95:	new	#268; //class scala/collection/mutable/ArrayOps$ofDouble
   98:	dup
   99:	aload	4
   101:	invokespecial	#271; //Method scala/collection/mutable/ArrayOps$ofDouble."<init>":([D)V
   104:	goto	415
   107:	new	#296; //class scala/MatchError
   110:	dup
   111:	aload_1
   112:	invokevirtual	#301; //Method java/lang/Object.toString:()Ljava/lang/String;
   115:	invokespecial	#302; //Method scala/MatchError."<init>":(Ljava/lang/String;)V
   118:	athrow
   119:	aload_1
   120:	instanceof	#305; //class "[J"
   123:	ifeq	160
   126:	aload_1
   127:	checkcast	#305; //class "[J"
   130:	astore	5
   132:	iconst_1
   133:	ifeq	148
   136:	new	#259; //class scala/collection/mutable/ArrayOps$ofLong
   139:	dup
   140:	aload	5
   142:	invokespecial	#262; //Method scala/collection/mutable/ArrayOps$ofLong."<init>":([J)V
   145:	goto	415
   148:	new	#296; //class scala/MatchError
   151:	dup
   152:	aload_1
   153:	invokevirtual	#301; //Method java/lang/Object.toString:()Ljava/lang/String;
   156:	invokespecial	#302; //Method scala/MatchError."<init>":(Ljava/lang/String;)V
   159:	athrow
   160:	aload_1
   161:	instanceof	#306; //class "[F"
   164:	ifeq	201
   167:	aload_1
   168:	checkcast	#306; //class "[F"
   171:	astore	6
   173:	iconst_1
   174:	ifeq	189
   177:	new	#250; //class scala/collection/mutable/ArrayOps$ofFloat
   180:	dup
   181:	aload	6
   183:	invokespecial	#253; //Method scala/collection/mutable/ArrayOps$ofFloat."<init>":([F)V
   186:	goto	415
   189:	new	#296; //class scala/MatchError
   192:	dup
   193:	aload_1
   194:	invokevirtual	#301; //Method java/lang/Object.toString:()Ljava/lang/String;
   197:	invokespecial	#302; //Method scala/MatchError."<init>":(Ljava/lang/String;)V
   200:	athrow
   201:	aload_1
   202:	instanceof	#307; //class "[C"
   205:	ifeq	242
   208:	aload_1
   209:	checkcast	#307; //class "[C"
   212:	astore	7
   214:	iconst_1
   215:	ifeq	230
   218:	new	#244; //class scala/collection/mutable/ArrayOps$ofChar
   221:	dup
   222:	aload	7
   224:	invokespecial	#245; //Method scala/collection/mutable/ArrayOps$ofChar."<init>":([C)V
   227:	goto	415
   230:	new	#296; //class scala/MatchError
   233:	dup
   234:	aload_1
   235:	invokevirtual	#301; //Method java/lang/Object.toString:()Ljava/lang/String;
   238:	invokespecial	#302; //Method scala/MatchError."<init>":(Ljava/lang/String;)V
   241:	athrow
   242:	aload_1
   243:	instanceof	#308; //class "[B"
   246:	ifeq	283
   249:	aload_1
   250:	checkcast	#308; //class "[B"
   253:	astore	8
   255:	iconst_1
   256:	ifeq	271
   259:	new	#235; //class scala/collection/mutable/ArrayOps$ofByte
   262:	dup
   263:	aload	8
   265:	invokespecial	#238; //Method scala/collection/mutable/ArrayOps$ofByte."<init>":([B)V
   268:	goto	415
   271:	new	#296; //class scala/MatchError
   274:	dup
   275:	aload_1
   276:	invokevirtual	#301; //Method java/lang/Object.toString:()Ljava/lang/String;
   279:	invokespecial	#302; //Method scala/MatchError."<init>":(Ljava/lang/String;)V
   282:	athrow
   283:	aload_1
   284:	instanceof	#309; //class "[S"
   287:	ifeq	324
   290:	aload_1
   291:	checkcast	#309; //class "[S"
   294:	astore	9
   296:	iconst_1
   297:	ifeq	312
   300:	new	#226; //class scala/collection/mutable/ArrayOps$ofShort
   303:	dup
   304:	aload	9
   306:	invokespecial	#229; //Method scala/collection/mutable/ArrayOps$ofShort."<init>":([S)V
   309:	goto	415
   312:	new	#296; //class scala/MatchError
   315:	dup
   316:	aload_1
   317:	invokevirtual	#301; //Method java/lang/Object.toString:()Ljava/lang/String;
   320:	invokespecial	#302; //Method scala/MatchError."<init>":(Ljava/lang/String;)V
   323:	athrow
   324:	aload_1
   325:	instanceof	#310; //class "[Z"
   328:	ifeq	365
   331:	aload_1
   332:	checkcast	#310; //class "[Z"
   335:	astore	10
   337:	iconst_1
   338:	ifeq	353
   341:	new	#217; //class scala/collection/mutable/ArrayOps$ofBoolean
   344:	dup
   345:	aload	10
   347:	invokespecial	#220; //Method scala/collection/mutable/ArrayOps$ofBoolean."<init>":([Z)V
   350:	goto	415
   353:	new	#296; //class scala/MatchError
   356:	dup
   357:	aload_1
   358:	invokevirtual	#301; //Method java/lang/Object.toString:()Ljava/lang/String;
   361:	invokespecial	#302; //Method scala/MatchError."<init>":(Ljava/lang/String;)V
   364:	athrow
   365:	aload_1
   366:	instanceof	#311; //class "[Lscala/runtime/BoxedUnit;"
   369:	ifeq	406
   372:	aload_1
   373:	checkcast	#311; //class "[Lscala/runtime/BoxedUnit;"
   376:	astore	11
   378:	iconst_1
   379:	ifeq	394
   382:	new	#207; //class scala/collection/mutable/ArrayOps$ofUnit
   385:	dup
   386:	aload	11
   388:	invokespecial	#210; //Method scala/collection/mutable/ArrayOps$ofUnit."<init>":([Lscala/runtime/BoxedUnit;)V
   391:	goto	415
   394:	new	#296; //class scala/MatchError
   397:	dup
   398:	aload_1
   399:	invokevirtual	#301; //Method java/lang/Object.toString:()Ljava/lang/String;
   402:	invokespecial	#302; //Method scala/MatchError."<init>":(Ljava/lang/String;)V
   405:	athrow
   406:	aload_1
   407:	ifnonnull	428
   410:	iconst_1
   411:	ifeq	416
   414:	aconst_null
   415:	areturn
   416:	new	#296; //class scala/MatchError
   419:	dup
   420:	aload_1
   421:	invokevirtual	#301; //Method java/lang/Object.toString:()Ljava/lang/String;
   424:	invokespecial	#302; //Method scala/MatchError."<init>":(Ljava/lang/String;)V
   427:	athrow
   428:	new	#296; //class scala/MatchError
   431:	dup
   432:	aload_1
   433:	invokevirtual	#301; //Method java/lang/Object.toString:()Ljava/lang/String;
   436:	invokespecial	#302; //Method scala/MatchError."<init>":(Ljava/lang/String;)V
   439:	athrow
  LineNumberTable: 
   line 184: 0
   line 21: 12
   line 185: 16
   line 184: 27
   line 21: 51
   line 186: 55
   line 184: 66
   line 21: 91
   line 187: 95
   line 184: 107
   line 21: 132
   line 188: 136
   line 184: 148
   line 21: 173
   line 189: 177
   line 184: 189
   line 21: 214
   line 190: 218
   line 184: 230
   line 21: 255
   line 191: 259
   line 184: 271
   line 21: 296
   line 192: 300
   line 184: 312
   line 21: 337
   line 193: 341
   line 184: 353
   line 21: 378
   line 194: 382
   line 184: 394
   line 21: 410
   line 195: 414
   line 184: 415

  LocalVariableTable: 
   Start  Length  Slot  Name   Signature
   0      440      0    this       Lscala/Predef$;
   0      440      1    xs       Ljava/lang/Object;
   12      27      2    temp2       [Ljava/lang/Object;
   51      27      3    temp3       [I
   91      28      4    temp4       [D
   132      28      5    temp5       [J
   173      28      6    temp6       [F
   214      28      7    temp7       [C
   255      28      8    temp8       [B
   296      28      9    temp9       [S
   337      28      10    temp10       [Z
   378      28      11    temp11       [Lscala/runtime/BoxedUnit;

  Signature: length = 0x2
   01 23 

public scala.runtime.RichException exceptionWrapper(java.lang.Throwable);
  Code:
   Stack=3, Locals=2, Args_size=2
   0:	new	#325; //class scala/runtime/RichException
   3:	dup
   4:	aload_1
   5:	invokespecial	#328; //Method scala/runtime/RichException."<init>":(Ljava/lang/Throwable;)V
   8:	areturn
  LineNumberTable: 
   line 182: 0

  LocalVariableTable: 
   Start  Length  Slot  Name   Signature
   0      9      0    this       Lscala/Predef$;
   0      9      1    exc       Ljava/lang/Throwable;


public scala.runtime.RichBoolean booleanWrapper(boolean);
  Code:
   Stack=3, Locals=2, Args_size=2
   0:	new	#334; //class scala/runtime/RichBoolean
   3:	dup
   4:	iload_1
   5:	invokespecial	#337; //Method scala/runtime/RichBoolean."<init>":(Z)V
   8:	areturn
  LineNumberTable: 
   line 180: 0

  LocalVariableTable: 
   Start  Length  Slot  Name   Signature
   0      9      0    this       Lscala/Predef$;
   0      9      1    x       Z


public scala.runtime.RichDouble doubleWrapper(double);
  Code:
   Stack=4, Locals=3, Args_size=2
   0:	new	#341; //class scala/runtime/RichDouble
   3:	dup
   4:	dload_1
   5:	invokespecial	#344; //Method scala/runtime/RichDouble."<init>":(D)V
   8:	areturn
  LineNumberTable: 
   line 179: 0

  LocalVariableTable: 
   Start  Length  Slot  Name   Signature
   0      9      0    this       Lscala/Predef$;
   0      9      1    x       D


public scala.runtime.RichFloat floatWrapper(float);
  Code:
   Stack=3, Locals=2, Args_size=2
   0:	new	#348; //class scala/runtime/RichFloat
   3:	dup
   4:	fload_1
   5:	invokespecial	#351; //Method scala/runtime/RichFloat."<init>":(F)V
   8:	areturn
  LineNumberTable: 
   line 178: 0

  LocalVariableTable: 
   Start  Length  Slot  Name   Signature
   0      9      0    this       Lscala/Predef$;
   0      9      1    x       F


public scala.runtime.RichLong longWrapper(long);
  Code:
   Stack=4, Locals=3, Args_size=2
   0:	new	#355; //class scala/runtime/RichLong
   3:	dup
   4:	lload_1
   5:	invokespecial	#358; //Method scala/runtime/RichLong."<init>":(J)V
   8:	areturn
  LineNumberTable: 
   line 177: 0

  LocalVariableTable: 
   Start  Length  Slot  Name   Signature
   0      9      0    this       Lscala/Predef$;
   0      9      1    x       J


public scala.runtime.RichChar charWrapper(char);
  Code:
   Stack=3, Locals=2, Args_size=2
   0:	new	#362; //class scala/runtime/RichChar
   3:	dup
   4:	iload_1
   5:	invokespecial	#365; //Method scala/runtime/RichChar."<init>":(C)V
   8:	areturn
  LineNumberTable: 
   line 176: 0

  LocalVariableTable: 
   Start  Length  Slot  Name   Signature
   0      9      0    this       Lscala/Predef$;
   0      9      1    c       C


public scala.runtime.RichInt intWrapper(int);
  Code:
   Stack=3, Locals=2, Args_size=2
   0:	new	#370; //class scala/runtime/RichInt
   3:	dup
   4:	iload_1
   5:	invokespecial	#373; //Method scala/runtime/RichInt."<init>":(I)V
   8:	areturn
  LineNumberTable: 
   line 175: 0

  LocalVariableTable: 
   Start  Length  Slot  Name   Signature
   0      9      0    this       Lscala/Predef$;
   0      9      1    x       I


public scala.runtime.RichShort shortWrapper(short);
  Code:
   Stack=3, Locals=2, Args_size=2
   0:	new	#377; //class scala/runtime/RichShort
   3:	dup
   4:	iload_1
   5:	invokespecial	#380; //Method scala/runtime/RichShort."<init>":(S)V
   8:	areturn
  LineNumberTable: 
   line 174: 0

  LocalVariableTable: 
   Start  Length  Slot  Name   Signature
   0      9      0    this       Lscala/Predef$;
   0      9      1    x       S


public scala.runtime.RichByte byteWrapper(byte);
  Code:
   Stack=3, Locals=2, Args_size=2
   0:	new	#384; //class scala/runtime/RichByte
   3:	dup
   4:	iload_1
   5:	invokespecial	#387; //Method scala/runtime/RichByte."<init>":(B)V
   8:	areturn
  LineNumberTable: 
   line 173: 0

  LocalVariableTable: 
   Start  Length  Slot  Name   Signature
   0      9      0    this       Lscala/Predef$;
   0      9      1    x       B


public scala.Tuple3 readf3(java.lang.String);
  Code:
   Stack=2, Locals=2, Args_size=2
   0:	getstatic	#394; //Field scala/Console$.MODULE$:Lscala/Console$;
   3:	aload_1
   4:	invokevirtual	#396; //Method scala/Console$.readf3:(Ljava/lang/String;)Lscala/Tuple3;
   7:	areturn
  LineNumberTable: 
   line 169: 0

  LocalVariableTable: 
   Start  Length  Slot  Name   Signature
   0      8      0    this       Lscala/Predef$;
   0      8      1    format       Ljava/lang/String;

  Signature: length = 0x2
   01 FFFFFF8E 

public scala.Tuple2 readf2(java.lang.String);
  Code:
   Stack=2, Locals=2, Args_size=2
   0:	getstatic	#394; //Field scala/Console$.MODULE$:Lscala/Console$;
   3:	aload_1
   4:	invokevirtual	#402; //Method scala/Console$.readf2:(Ljava/lang/String;)Lscala/Tuple2;
   7:	areturn
  LineNumberTable: 
   line 168: 0

  LocalVariableTable: 
   Start  Length  Slot  Name   Signature
   0      8      0    this       Lscala/Predef$;
   0      8      1    format       Ljava/lang/String;

  Signature: length = 0x2
   01 FFFFFF93 

public java.lang.Object readf1(java.lang.String);
  Code:
   Stack=2, Locals=2, Args_size=2
   0:	getstatic	#394; //Field scala/Console$.MODULE$:Lscala/Console$;
   3:	aload_1
   4:	invokevirtual	#407; //Method scala/Console$.readf1:(Ljava/lang/String;)Ljava/lang/Object;
   7:	areturn
  LineNumberTable: 
   line 167: 0

  LocalVariableTable: 
   Start  Length  Slot  Name   Signature
   0      8      0    this       Lscala/Predef$;
   0      8      1    format       Ljava/lang/String;


public scala.collection.immutable.List readf(java.lang.String);
  Code:
   Stack=2, Locals=2, Args_size=2
   0:	getstatic	#394; //Field scala/Console$.MODULE$:Lscala/Console$;
   3:	aload_1
   4:	invokevirtual	#411; //Method scala/Console$.readf:(Ljava/lang/String;)Lscala/collection/immutable/List;
   7:	areturn
  LineNumberTable: 
   line 166: 0

  LocalVariableTable: 
   Start  Length  Slot  Name   Signature
   0      8      0    this       Lscala/Predef$;
   0      8      1    format       Ljava/lang/String;

  Signature: length = 0x2
   01 FFFFFF9C 

public double readDouble();
  Code:
   Stack=2, Locals=1, Args_size=1
   0:	getstatic	#394; //Field scala/Console$.MODULE$:Lscala/Console$;
   3:	invokevirtual	#416; //Method scala/Console$.readDouble:()D
   6:	dreturn
  LineNumberTable: 
   line 165: 0


public float readFloat();
  Code:
   Stack=1, Locals=1, Args_size=1
   0:	getstatic	#394; //Field scala/Console$.MODULE$:Lscala/Console$;
   3:	invokevirtual	#420; //Method scala/Console$.readFloat:()F
   6:	freturn
  LineNumberTable: 
   line 164: 0


public long readLong();
  Code:
   Stack=2, Locals=1, Args_size=1
   0:	getstatic	#394; //Field scala/Console$.MODULE$:Lscala/Console$;
   3:	invokevirtual	#424; //Method scala/Console$.readLong:()J
   6:	lreturn
  LineNumberTable: 
   line 163: 0


public int readInt();
  Code:
   Stack=1, Locals=1, Args_size=1
   0:	getstatic	#394; //Field scala/Console$.MODULE$:Lscala/Console$;
   3:	invokevirtual	#428; //Method scala/Console$.readInt:()I
   6:	ireturn
  LineNumberTable: 
   line 162: 0


public char readChar();
  Code:
   Stack=1, Locals=1, Args_size=1
   0:	getstatic	#394; //Field scala/Console$.MODULE$:Lscala/Console$;
   3:	invokevirtual	#432; //Method scala/Console$.readChar:()C
   6:	ireturn
  LineNumberTable: 
   line 161: 0


public short readShort();
  Code:
   Stack=1, Locals=1, Args_size=1
   0:	getstatic	#394; //Field scala/Console$.MODULE$:Lscala/Console$;
   3:	invokevirtual	#436; //Method scala/Console$.readShort:()S
   6:	ireturn
  LineNumberTable: 
   line 160: 0


public byte readByte();
  Code:
   Stack=1, Locals=1, Args_size=1
   0:	getstatic	#394; //Field scala/Console$.MODULE$:Lscala/Console$;
   3:	invokevirtual	#440; //Method scala/Console$.readByte:()B
   6:	ireturn
  LineNumberTable: 
   line 159: 0


public boolean readBoolean();
  Code:
   Stack=1, Locals=1, Args_size=1
   0:	getstatic	#394; //Field scala/Console$.MODULE$:Lscala/Console$;
   3:	invokevirtual	#444; //Method scala/Console$.readBoolean:()Z
   6:	ireturn
  LineNumberTable: 
   line 158: 0


public java.lang.String readLine(java.lang.String, scala.collection.Seq);
  Code:
   Stack=7, Locals=3, Args_size=3
   0:	getstatic	#394; //Field scala/Console$.MODULE$:Lscala/Console$;
   3:	aload_1
   4:	aload_0
   5:	iconst_1
   6:	anewarray	#298; //class java/lang/Object
   9:	dup
   10:	iconst_0
   11:	aload_2
   12:	aastore
   13:	invokevirtual	#450; //Method genericWrapArray:(Ljava/lang/Object;)Lscala/collection/mutable/WrappedArray;
   16:	invokevirtual	#452; //Method scala/Console$.readLine:(Ljava/lang/String;Lscala/collection/Seq;)Ljava/lang/String;
   19:	areturn
  LineNumberTable: 
   line 157: 0

  LocalVariableTable: 
   Start  Length  Slot  Name   Signature
   0      20      0    this       Lscala/Predef$;
   0      20      1    text       Ljava/lang/String;
   0      20      2    args       Lscala/collection/Seq;

  Signature: length = 0x2
   01 FFFFFFC8 

public java.lang.String readLine();
  Code:
   Stack=1, Locals=1, Args_size=1
   0:	getstatic	#394; //Field scala/Console$.MODULE$:Lscala/Console$;
   3:	invokevirtual	#458; //Method scala/Console$.readLine:()Ljava/lang/String;
   6:	areturn
  LineNumberTable: 
   line 156: 0


public java.lang.String format(java.lang.String, scala.collection.Seq);
  Code:
   Stack=2, Locals=3, Args_size=3
   0:	aload_0
   1:	aload_1
   2:	invokevirtual	#460; //Method augmentString:(Ljava/lang/String;)Lscala/collection/immutable/StringOps;
   5:	aload_2
   6:	invokeinterface	#465,  2; //InterfaceMethod scala/collection/immutable/StringLike.format:(Lscala/collection/Seq;)Ljava/lang/String;
   11:	areturn
  LineNumberTable: 
   line 154: 0

  LocalVariableTable: 
   Start  Length  Slot  Name   Signature
   0      12      0    this       Lscala/Predef$;
   0      12      1    text       Ljava/lang/String;
   0      12      2    xs       Lscala/collection/Seq;

  Signature: length = 0x2
   01 FFFFFFC8 

public void printf(java.lang.String, scala.collection.Seq);
  Code:
   Stack=4, Locals=3, Args_size=3
   0:	getstatic	#394; //Field scala/Console$.MODULE$:Lscala/Console$;
   3:	aload_0
   4:	aload_1
   5:	aload_2
   6:	invokevirtual	#469; //Method format:(Ljava/lang/String;Lscala/collection/Seq;)Ljava/lang/String;
   9:	aload_0
   10:	iconst_0
   11:	anewarray	#298; //class java/lang/Object
   14:	invokevirtual	#450; //Method genericWrapArray:(Ljava/lang/Object;)Lscala/collection/mutable/WrappedArray;
   17:	invokevirtual	#471; //Method scala/Console$.printf:(Ljava/lang/String;Lscala/collection/Seq;)V
   20:	return
  LineNumberTable: 
   line 153: 0

  LocalVariableTable: 
   Start  Length  Slot  Name   Signature
   0      21      0    this       Lscala/Predef$;
   0      21      1    text       Ljava/lang/String;
   0      21      2    xs       Lscala/collection/Seq;

  Signature: length = 0x2
   01 FFFFFFD8 

public void println(java.lang.Object);
  Code:
   Stack=2, Locals=2, Args_size=2
   0:	getstatic	#394; //Field scala/Console$.MODULE$:Lscala/Console$;
   3:	aload_1
   4:	invokevirtual	#475; //Method scala/Console$.println:(Ljava/lang/Object;)V
   7:	return
  LineNumberTable: 
   line 152: 0

  LocalVariableTable: 
   Start  Length  Slot  Name   Signature
   0      8      0    this       Lscala/Predef$;
   0      8      1    x       Ljava/lang/Object;


public void println();
  Code:
   Stack=1, Locals=1, Args_size=1
   0:	getstatic	#394; //Field scala/Console$.MODULE$:Lscala/Console$;
   3:	invokevirtual	#477; //Method scala/Console$.println:()V
   6:	return
  LineNumberTable: 
   line 151: 0


public void print(java.lang.Object);
  Code:
   Stack=2, Locals=2, Args_size=2
   0:	getstatic	#394; //Field scala/Console$.MODULE$:Lscala/Console$;
   3:	aload_1
   4:	invokevirtual	#480; //Method scala/Console$.print:(Ljava/lang/Object;)V
   7:	return
  LineNumberTable: 
   line 150: 0

  LocalVariableTable: 
   Start  Length  Slot  Name   Signature
   0      8      0    this       Lscala/Predef$;
   0      8      1    x       Ljava/lang/Object;


public scala.Predef$ArrowAssoc any2ArrowAssoc(java.lang.Object);
  Code:
   Stack=3, Locals=2, Args_size=2
   0:	new	#484; //class scala/Predef$ArrowAssoc
   3:	dup
   4:	aload_1
   5:	invokespecial	#485; //Method scala/Predef$ArrowAssoc."<init>":(Ljava/lang/Object;)V
   8:	areturn
  LineNumberTable: 
   line 146: 0

  LocalVariableTable: 
   Start  Length  Slot  Name   Signature
   0      9      0    this       Lscala/Predef$;
   0      9      1    x       Ljava/lang/Object;

  Signature: length = 0x2
   01 FFFFFFE6 

public scala.Predef$Ensuring any2Ensuring(java.lang.Object);
  Code:
   Stack=3, Locals=2, Args_size=2
   0:	new	#490; //class scala/Predef$Ensuring
   3:	dup
   4:	aload_1
   5:	invokespecial	#491; //Method scala/Predef$Ensuring."<init>":(Ljava/lang/Object;)V
   8:	areturn
  LineNumberTable: 
   line 126: 0

  LocalVariableTable: 
   Start  Length  Slot  Name   Signature
   0      9      0    this       Lscala/Predef$;
   0      9      1    x       Ljava/lang/Object;

  Signature: length = 0x2
   01 FFFFFFEC 

public void require(boolean, scala.Function0);
  Code:
   Stack=4, Locals=3, Args_size=3
   0:	iload_1
   1:	ifeq	5
   4:	return
   5:	new	#496; //class java/lang/IllegalArgumentException
   8:	dup
   9:	new	#498; //class scala/collection/mutable/StringBuilder
   12:	dup
   13:	invokespecial	#499; //Method scala/collection/mutable/StringBuilder."<init>":()V
   16:	ldc_w	#501; //String requirement failed: 
   19:	invokevirtual	#505; //Method scala/collection/mutable/StringBuilder.append:(Ljava/lang/Object;)Lscala/collection/mutable/StringBuilder;
   22:	aload_2
   23:	invokeinterface	#511,  1; //InterfaceMethod scala/Function0.apply:()Ljava/lang/Object;
   28:	invokevirtual	#505; //Method scala/collection/mutable/StringBuilder.append:(Ljava/lang/Object;)Lscala/collection/mutable/StringBuilder;
   31:	invokevirtual	#512; //Method scala/collection/mutable/StringBuilder.toString:()Ljava/lang/String;
   34:	invokespecial	#513; //Method java/lang/IllegalArgumentException."<init>":(Ljava/lang/String;)V
   37:	athrow
  LineNumberTable: 
   line 116: 0
   line 117: 5

  LocalVariableTable: 
   Start  Length  Slot  Name   Signature
   0      38      0    this       Lscala/Predef$;
   0      38      1    requirement       Z
   0      38      2    message       Lscala/Function0;

  Signature: length = 0x2
   02 05 

public void require(boolean);
  Code:
   Stack=3, Locals=2, Args_size=2
   0:	iload_1
   1:	ifeq	5
   4:	return
   5:	new	#496; //class java/lang/IllegalArgumentException
   8:	dup
   9:	ldc_w	#519; //String requirement failed
   12:	invokespecial	#513; //Method java/lang/IllegalArgumentException."<init>":(Ljava/lang/String;)V
   15:	athrow
  LineNumberTable: 
   line 111: 0
   line 112: 5

  LocalVariableTable: 
   Start  Length  Slot  Name   Signature
   0      16      0    this       Lscala/Predef$;
   0      16      1    requirement       Z


public void assume(boolean, scala.Function0);
  Code:
   Stack=4, Locals=3, Args_size=3
   0:	iload_1
   1:	ifeq	5
   4:	return
   5:	new	#522; //class java/lang/AssertionError
   8:	dup
   9:	new	#498; //class scala/collection/mutable/StringBuilder
   12:	dup
   13:	invokespecial	#499; //Method scala/collection/mutable/StringBuilder."<init>":()V
   16:	ldc_w	#524; //String assumption failed: 
   19:	invokevirtual	#505; //Method scala/collection/mutable/StringBuilder.append:(Ljava/lang/Object;)Lscala/collection/mutable/StringBuilder;
   22:	aload_2
   23:	invokeinterface	#511,  1; //InterfaceMethod scala/Function0.apply:()Ljava/lang/Object;
   28:	invokevirtual	#505; //Method scala/collection/mutable/StringBuilder.append:(Ljava/lang/Object;)Lscala/collection/mutable/StringBuilder;
   31:	invokevirtual	#512; //Method scala/collection/mutable/StringBuilder.toString:()Ljava/lang/String;
   34:	invokespecial	#525; //Method java/lang/AssertionError."<init>":(Ljava/lang/Object;)V
   37:	athrow
  LineNumberTable: 
   line 106: 0
   line 107: 5

  LocalVariableTable: 
   Start  Length  Slot  Name   Signature
   0      38      0    this       Lscala/Predef$;
   0      38      1    assumption       Z
   0      38      2    message       Lscala/Function0;

  Signature: length = 0x2
   02 05 

public void assume(boolean);
  Code:
   Stack=3, Locals=2, Args_size=2
   0:	iload_1
   1:	ifeq	5
   4:	return
   5:	new	#522; //class java/lang/AssertionError
   8:	dup
   9:	ldc_w	#528; //String assumption failed
   12:	invokespecial	#525; //Method java/lang/AssertionError."<init>":(Ljava/lang/Object;)V
   15:	athrow
  LineNumberTable: 
   line 100: 0
   line 101: 5

  LocalVariableTable: 
   Start  Length  Slot  Name   Signature
   0      16      0    this       Lscala/Predef$;
   0      16      1    assumption       Z


public void assert(boolean, scala.Function0);
  Code:
   Stack=4, Locals=3, Args_size=3
   0:	iload_1
   1:	ifeq	5
   4:	return
   5:	new	#522; //class java/lang/AssertionError
   8:	dup
   9:	new	#498; //class scala/collection/mutable/StringBuilder
   12:	dup
   13:	invokespecial	#499; //Method scala/collection/mutable/StringBuilder."<init>":()V
   16:	ldc_w	#531; //String assertion failed: 
   19:	invokevirtual	#505; //Method scala/collection/mutable/StringBuilder.append:(Ljava/lang/Object;)Lscala/collection/mutable/StringBuilder;
   22:	aload_2
   23:	invokeinterface	#511,  1; //InterfaceMethod scala/Function0.apply:()Ljava/lang/Object;
   28:	invokevirtual	#505; //Method scala/collection/mutable/StringBuilder.append:(Ljava/lang/Object;)Lscala/collection/mutable/StringBuilder;
   31:	invokevirtual	#512; //Method scala/collection/mutable/StringBuilder.toString:()Ljava/lang/String;
   34:	invokespecial	#525; //Method java/lang/AssertionError."<init>":(Ljava/lang/Object;)V
   37:	athrow
  LineNumberTable: 
   line 94: 0
   line 95: 5

  LocalVariableTable: 
   Start  Length  Slot  Name   Signature
   0      38      0    this       Lscala/Predef$;
   0      38      1    assertion       Z
   0      38      2    message       Lscala/Function0;

  Signature: length = 0x2
   02 05 

public void assert(boolean);
  Code:
   Stack=3, Locals=2, Args_size=2
   0:	iload_1
   1:	ifeq	5
   4:	return
   5:	new	#522; //class java/lang/AssertionError
   8:	dup
   9:	ldc_w	#534; //String assertion failed
   12:	invokespecial	#525; //Method java/lang/AssertionError."<init>":(Ljava/lang/Object;)V
   15:	athrow
  LineNumberTable: 
   line 88: 0
   line 89: 5

  LocalVariableTable: 
   Start  Length  Slot  Name   Signature
   0      16      0    this       Lscala/Predef$;
   0      16      1    assertion       Z


public scala.runtime.Nothing$ exit(int);
  Code:
   Stack=2, Locals=2, Args_size=2
   0:	iload_1
   1:	invokestatic	#540; //Method java/lang/System.exit:(I)V
   4:	new	#542; //class java/lang/Throwable
   7:	dup
   8:	invokespecial	#543; //Method java/lang/Throwable."<init>":()V
   11:	athrow
  LineNumberTable: 
   line 79: 0
   line 80: 4

  LocalVariableTable: 
   Start  Length  Slot  Name   Signature
   0      12      0    this       Lscala/Predef$;
   0      12      1    status       I


public scala.runtime.Nothing$ exit();
  Code:
   Stack=2, Locals=1, Args_size=1
   0:	aload_0
   1:	iconst_0
   2:	invokevirtual	#547; //Method exit:(I)Lscala/runtime/Nothing$;
   5:	areturn
  LineNumberTable: 
   line 76: 0


public scala.runtime.Nothing$ error(java.lang.String);
  Code:
   Stack=3, Locals=2, Args_size=2
   0:	new	#551; //class java/lang/RuntimeException
   3:	dup
   4:	aload_1
   5:	invokespecial	#552; //Method java/lang/RuntimeException."<init>":(Ljava/lang/String;)V
   8:	athrow
  LineNumberTable: 
   line 74: 0

  LocalVariableTable: 
   Start  Length  Slot  Name   Signature
   0      9      0    this       Lscala/Predef$;
   0      9      1    message       Ljava/lang/String;


public int hash(int);
  Code:
   Stack=1, Locals=2, Args_size=2
   0:	iload_1
   1:	ireturn
  LineNumberTable: 
   line 70: 0

  LocalVariableTable: 
   Start  Length  Slot  Name   Signature
   0      2      0    this       Lscala/Predef$;
   0      2      1    x       I


public int hash(java.lang.Long);
  Code:
   Stack=4, Locals=3, Args_size=2
   0:	aload_1
   1:	invokevirtual	#558; //Method java/lang/Long.intValue:()I
   4:	istore_2
   5:	iload_2
   6:	i2l
   7:	aload_1
   8:	invokevirtual	#561; //Method java/lang/Long.longValue:()J
   11:	lcmp
   12:	ifne	19
   15:	iload_2
   16:	goto	23
   19:	aload_1
   20:	invokevirtual	#564; //Method java/lang/Long.hashCode:()I
   23:	ireturn
  LineNumberTable: 
   line 66: 0
   line 67: 5
   line 65: 23

  LocalVariableTable: 
   Start  Length  Slot  Name   Signature
   0      24      0    this       Lscala/Predef$;
   0      24      1    x       Ljava/lang/Long;
   5      19      2    iv       I


public int hash(java.lang.Number);
  Code:
   Stack=1, Locals=2, Args_size=2
   0:	aload_1
   1:	invokestatic	#572; //Method scala/runtime/BoxesRunTime.hashFromNumber:(Ljava/lang/Number;)I
   4:	ireturn
  LineNumberTable: 
   line 63: 0

  LocalVariableTable: 
   Start  Length  Slot  Name   Signature
   0      5      0    this       Lscala/Predef$;
   0      5      1    x       Ljava/lang/Number;


public int hash(java.lang.Object);
  Code:
   Stack=1, Locals=2, Args_size=2
   0:	aload_1
   1:	instanceof	#576; //class java/lang/Number
   4:	ifeq	17
   7:	aload_1
   8:	checkcast	#576; //class java/lang/Number
   11:	invokestatic	#572; //Method scala/runtime/BoxesRunTime.hashFromNumber:(Ljava/lang/Number;)I
   14:	goto	21
   17:	aload_1
   18:	invokevirtual	#577; //Method java/lang/Object.hashCode:()I
   21:	ireturn
  LineNumberTable: 
   line 59: 0
   line 60: 17
   line 59: 21

  LocalVariableTable: 
   Start  Length  Slot  Name   Signature
   0      22      0    this       Lscala/Predef$;
   0      22      1    x       Ljava/lang/Object;


public java.lang.Object locally(java.lang.Object);
  Code:
   Stack=1, Locals=2, Args_size=2
   0:	aload_1
   1:	areturn
  LineNumberTable: 
   line 54: 0

  LocalVariableTable: 
   Start  Length  Slot  Name   Signature
   0      2      0    this       Lscala/Predef$;
   0      2      1    x       Ljava/lang/Object;

  Signature: length = 0x2
   02 44 

public java.lang.Thread currentThread();
  Code:
   Stack=1, Locals=1, Args_size=1
   0:	invokestatic	#586; //Method java/lang/Thread.currentThread:()Ljava/lang/Thread;
   3:	areturn
  LineNumberTable: 
   line 52: 0


public java.lang.Object identity(java.lang.Object);
  Code:
   Stack=1, Locals=2, Args_size=2
   0:	aload_1
   1:	areturn
  LineNumberTable: 
   line 50: 0

  LocalVariableTable: 
   Start  Length  Slot  Name   Signature
   0      2      0    this       Lscala/Predef$;
   0      2      1    x       Ljava/lang/Object;

  Signature: length = 0x2
   02 4C 

public scala.reflect.ClassManifest classManifest(scala.reflect.ClassManifest);
  Code:
   Stack=1, Locals=2, Args_size=2
   0:	aload_1
   1:	areturn
  LineNumberTable: 
   line 47: 0

  LocalVariableTable: 
   Start  Length  Slot  Name   Signature
   0      2      0    this       Lscala/Predef$;
   0      2      1    m       Lscala/reflect/ClassManifest;

  Signature: length = 0x2
   02 51 

public scala.reflect.Manifest manifest(scala.reflect.Manifest);
  Code:
   Stack=1, Locals=2, Args_size=2
   0:	aload_1
   1:	areturn
  LineNumberTable: 
   line 46: 0

  LocalVariableTable: 
   Start  Length  Slot  Name   Signature
   0      2      0    this       Lscala/Predef$;
   0      2      1    m       Lscala/reflect/Manifest;

  Signature: length = 0x2
   02 55 

public java.lang.Object implicitly(java.lang.Object);
  Code:
   Stack=1, Locals=2, Args_size=2
   0:	aload_1
   1:	areturn
  LineNumberTable: 
   line 45: 0

  LocalVariableTable: 
   Start  Length  Slot  Name   Signature
   0      2      0    this       Lscala/Predef$;
   0      2      1    e       Ljava/lang/Object;

  Signature: length = 0x2
   02 44 

public scala.collection.immutable.Set$ Set();
  Code:
   Stack=1, Locals=1, Args_size=1
   0:	aload_0
   1:	getfield	#50; //Field Set:Lscala/collection/immutable/Set$;
   4:	areturn
  LineNumberTable: 
   line 41: 0


public scala.collection.immutable.Map$ Map();
  Code:
   Stack=1, Locals=1, Args_size=1
   0:	aload_0
   1:	getfield	#44; //Field Map:Lscala/collection/immutable/Map$;
   4:	areturn
  LineNumberTable: 
   line 40: 0


public java.lang.Class classOf();
  Code:
   Stack=1, Locals=1, Args_size=1
   0:	aconst_null
   1:	areturn
  LineNumberTable: 
   line 26: 0

  Signature: length = 0x2
   02 5C 

}

