Compiled from "Predef.scala"
public final class scala.Predef$$anon$1 extends java.lang.Object implements scala.Ordered
  SourceFile: "Predef.scala"
  Signature: length = 0x2
   00 3B 
  Scala: length = 0x
   
  InnerClass: 
   public final #64= #12 of #63; //$anon$1=class scala/Predef$$anon$1 of class scala/Predef
  minor version: 0
  major version: 49
  Constant pool:
const #1 = Asciz	SourceFile;
const #2 = Asciz	Predef.scala;
const #3 = Asciz	ord$1;
const #4 = Asciz	Lscala/Ordering;;
const #5 = Asciz	x$1;
const #6 = Asciz	Ljava/lang/Object;;
const #7 = Asciz	<init>;
const #8 = Asciz	(Ljava/lang/Object;Lscala/Ordering;)V;
const #9 = Asciz	Code;
const #10 = Asciz	LineNumberTable;
const #11 = Asciz	scala/Predef$$anon$1;
const #12 = class	#11;	//  scala/Predef$$anon$1
const #13 = NameAndType	#5:#6;//  x$1:Ljava/lang/Object;
const #14 = Field	#12.#13;	//  scala/Predef$$anon$1.x$1:Ljava/lang/Object;
const #15 = NameAndType	#3:#4;//  ord$1:Lscala/Ordering;
const #16 = Field	#12.#15;	//  scala/Predef$$anon$1.ord$1:Lscala/Ordering;
const #17 = Asciz	java/lang/Object;
const #18 = class	#17;	//  java/lang/Object
const #19 = Asciz	()V;
const #20 = NameAndType	#7:#19;//  "<init>":()V
const #21 = Method	#18.#20;	//  java/lang/Object."<init>":()V
const #22 = Asciz	scala/Ordered$class;
const #23 = class	#22;	//  scala/Ordered$class
const #24 = Asciz	$init$;
const #25 = Asciz	(Lscala/Ordered;)V;
const #26 = NameAndType	#24:#25;//  $init$:(Lscala/Ordered;)V
const #27 = Method	#23.#26;	//  scala/Ordered$class.$init$:(Lscala/Ordered;)V
const #28 = Asciz	compare;
const #29 = Asciz	(Ljava/lang/Object;)I;
const #30 = Asciz	scala/Ordering;
const #31 = class	#30;	//  scala/Ordering
const #32 = Asciz	(Ljava/lang/Object;Ljava/lang/Object;)I;
const #33 = NameAndType	#28:#32;//  compare:(Ljava/lang/Object;Ljava/lang/Object;)I
const #34 = InterfaceMethod	#31.#33;	//  scala/Ordering.compare:(Ljava/lang/Object;Ljava/lang/Object;)I
const #35 = Asciz	this;
const #36 = Asciz	Lscala/Predef$$anon$1;;
const #37 = Asciz	that;
const #38 = Asciz	LocalVariableTable;
const #39 = Asciz	(TT;)I;
const #40 = Asciz	Signature;
const #41 = Asciz	compareTo;
const #42 = Asciz	(Lscala/Ordered;Ljava/lang/Object;)I;
const #43 = NameAndType	#41:#42;//  compareTo:(Lscala/Ordered;Ljava/lang/Object;)I
const #44 = Method	#23.#43;	//  scala/Ordered$class.compareTo:(Lscala/Ordered;Ljava/lang/Object;)I
const #45 = Asciz	$greater$eq;
const #46 = Asciz	(Ljava/lang/Object;)Z;
const #47 = Asciz	(Lscala/Ordered;Ljava/lang/Object;)Z;
const #48 = NameAndType	#45:#47;//  $greater$eq:(Lscala/Ordered;Ljava/lang/Object;)Z
const #49 = Method	#23.#48;	//  scala/Ordered$class.$greater$eq:(Lscala/Ordered;Ljava/lang/Object;)Z
const #50 = Asciz	$less$eq;
const #51 = NameAndType	#50:#47;//  $less$eq:(Lscala/Ordered;Ljava/lang/Object;)Z
const #52 = Method	#23.#51;	//  scala/Ordered$class.$less$eq:(Lscala/Ordered;Ljava/lang/Object;)Z
const #53 = Asciz	$greater;
const #54 = NameAndType	#53:#47;//  $greater:(Lscala/Ordered;Ljava/lang/Object;)Z
const #55 = Method	#23.#54;	//  scala/Ordered$class.$greater:(Lscala/Ordered;Ljava/lang/Object;)Z
const #56 = Asciz	$less;
const #57 = NameAndType	#56:#47;//  $less:(Lscala/Ordered;Ljava/lang/Object;)Z
const #58 = Method	#23.#57;	//  scala/Ordered$class.$less:(Lscala/Ordered;Ljava/lang/Object;)Z
const #59 = Asciz	Ljava/lang/Object;Lscala/Ordered<TT;>;;
const #60 = Asciz	Scala;
const #61 = Asciz	InnerClasses;
const #62 = Asciz	scala/Predef;
const #63 = class	#62;	//  scala/Predef
const #64 = Asciz	$anon$1;
const #65 = Asciz	scala/Ordered;
const #66 = class	#65;	//  scala/Ordered

{
public scala.Predef$$anon$1(java.lang.Object, scala.Ordering);
  Code:
   Stack=2, Locals=3, Args_size=3
   0:	aload_0
   1:	aload_1
   2:	putfield	#14; //Field x$1:Ljava/lang/Object;
   5:	aload_0
   6:	aload_2
   7:	putfield	#16; //Field ord$1:Lscala/Ordering;
   10:	aload_0
   11:	invokespecial	#21; //Method java/lang/Object."<init>":()V
   14:	aload_0
   15:	invokestatic	#27; //Method scala/Ordered$class.$init$:(Lscala/Ordered;)V
   18:	return
  LineNumberTable: 
   line 203: 0


public int compare(java.lang.Object);
  Code:
   Stack=3, Locals=2, Args_size=2
   0:	aload_0
   1:	getfield	#16; //Field ord$1:Lscala/Ordering;
   4:	aload_0
   5:	getfield	#14; //Field x$1:Ljava/lang/Object;
   8:	aload_1
   9:	invokeinterface	#34,  3; //InterfaceMethod scala/Ordering.compare:(Ljava/lang/Object;Ljava/lang/Object;)I
   14:	ireturn
  LineNumberTable: 
   line 203: 0

  LocalVariableTable: 
   Start  Length  Slot  Name   Signature
   0      15      0    this       Lscala/Predef$$anon$1;
   0      15      1    that       Ljava/lang/Object;

  Signature: length = 0x2
   00 27 

public int compareTo(java.lang.Object);
  Code:
   Stack=2, Locals=2, Args_size=2
   0:	aload_0
   1:	aload_1
   2:	invokestatic	#44; //Method scala/Ordered$class.compareTo:(Lscala/Ordered;Ljava/lang/Object;)I
   5:	ireturn
  LineNumberTable: 
   line 203: 0

  LocalVariableTable: 
   Start  Length  Slot  Name   Signature
   0      6      0    this       Lscala/Predef$$anon$1;
   0      6      1    that       Ljava/lang/Object;


public boolean $greater$eq(java.lang.Object);
  Code:
   Stack=2, Locals=2, Args_size=2
   0:	aload_0
   1:	aload_1
   2:	invokestatic	#49; //Method scala/Ordered$class.$greater$eq:(Lscala/Ordered;Ljava/lang/Object;)Z
   5:	ireturn
  LineNumberTable: 
   line 203: 0

  LocalVariableTable: 
   Start  Length  Slot  Name   Signature
   0      6      0    this       Lscala/Predef$$anon$1;
   0      6      1    that       Ljava/lang/Object;


public boolean $less$eq(java.lang.Object);
  Code:
   Stack=2, Locals=2, Args_size=2
   0:	aload_0
   1:	aload_1
   2:	invokestatic	#52; //Method scala/Ordered$class.$less$eq:(Lscala/Ordered;Ljava/lang/Object;)Z
   5:	ireturn
  LineNumberTable: 
   line 203: 0

  LocalVariableTable: 
   Start  Length  Slot  Name   Signature
   0      6      0    this       Lscala/Predef$$anon$1;
   0      6      1    that       Ljava/lang/Object;


public boolean $greater(java.lang.Object);
  Code:
   Stack=2, Locals=2, Args_size=2
   0:	aload_0
   1:	aload_1
   2:	invokestatic	#55; //Method scala/Ordered$class.$greater:(Lscala/Ordered;Ljava/lang/Object;)Z
   5:	ireturn
  LineNumberTable: 
   line 203: 0

  LocalVariableTable: 
   Start  Length  Slot  Name   Signature
   0      6      0    this       Lscala/Predef$$anon$1;
   0      6      1    that       Ljava/lang/Object;


public boolean $less(java.lang.Object);
  Code:
   Stack=2, Locals=2, Args_size=2
   0:	aload_0
   1:	aload_1
   2:	invokestatic	#58; //Method scala/Ordered$class.$less:(Lscala/Ordered;Ljava/lang/Object;)Z
   5:	ireturn
  LineNumberTable: 
   line 203: 0

  LocalVariableTable: 
   Start  Length  Slot  Name   Signature
   0      6      0    this       Lscala/Predef$$anon$1;
   0      6      1    that       Ljava/lang/Object;


}

