Compiled from "Predef.scala"
public final class scala.Predef$$anon$2 extends java.lang.Object implements java.lang.CharSequence
  SourceFile: "Predef.scala"
  Scala: length = 0x
   
  InnerClass: 
   public final #77= #10 of #76; //$anon$2=class scala/Predef$$anon$2 of class scala/Predef
  minor version: 0
  major version: 49
  Constant pool:
const #1 = Asciz	SourceFile;
const #2 = Asciz	Predef.scala;
const #3 = Asciz	xs$1;
const #4 = Asciz	Lscala/collection/Vector;;
const #5 = Asciz	<init>;
const #6 = Asciz	(Lscala/collection/Vector;)V;
const #7 = Asciz	Code;
const #8 = Asciz	LineNumberTable;
const #9 = Asciz	scala/Predef$$anon$2;
const #10 = class	#9;	//  scala/Predef$$anon$2
const #11 = NameAndType	#3:#4;//  xs$1:Lscala/collection/Vector;
const #12 = Field	#10.#11;	//  scala/Predef$$anon$2.xs$1:Lscala/collection/Vector;
const #13 = Asciz	java/lang/Object;
const #14 = class	#13;	//  java/lang/Object
const #15 = Asciz	()V;
const #16 = NameAndType	#5:#15;//  "<init>":()V
const #17 = Method	#14.#16;	//  java/lang/Object."<init>":()V
const #18 = Asciz	toString;
const #19 = Asciz	()Ljava/lang/String;;
const #20 = Asciz	;
const #21 = String	#20;	//  
const #22 = Asciz	scala/collection/generic/TraversableTemplate;
const #23 = class	#22;	//  scala/collection/generic/TraversableTemplate
const #24 = Asciz	mkString;
const #25 = Asciz	(Ljava/lang/String;)Ljava/lang/String;;
const #26 = NameAndType	#24:#25;//  mkString:(Ljava/lang/String;)Ljava/lang/String;
const #27 = InterfaceMethod	#23.#26;	//  scala/collection/generic/TraversableTemplate.mkString:(Ljava/lang/String;)Ljava/lang/String;
const #28 = Asciz	subSequence;
const #29 = Asciz	(II)Ljava/lang/CharSequence;;
const #30 = Asciz	scala/Predef$;
const #31 = class	#30;	//  scala/Predef$
const #32 = Asciz	MODULE$;
const #33 = Asciz	Lscala/Predef$;;
const #34 = NameAndType	#32:#33;//  MODULE$:Lscala/Predef$;
const #35 = Field	#31.#34;	//  scala/Predef$.MODULE$:Lscala/Predef$;
const #36 = Asciz	scala/collection/generic/VectorTemplate;
const #37 = class	#36;	//  scala/collection/generic/VectorTemplate
const #38 = Asciz	slice;
const #39 = Asciz	(II)Lscala/collection/generic/VectorTemplate;;
const #40 = NameAndType	#38:#39;//  slice:(II)Lscala/collection/generic/VectorTemplate;
const #41 = InterfaceMethod	#37.#40;	//  scala/collection/generic/VectorTemplate.slice:(II)Lscala/collection/generic/VectorTemplate;
const #42 = Asciz	scala/collection/Vector;
const #43 = class	#42;	//  scala/collection/Vector
const #44 = Asciz	seqToCharSequence;
const #45 = Asciz	(Lscala/collection/Vector;)Ljava/lang/CharSequence;;
const #46 = NameAndType	#44:#45;//  seqToCharSequence:(Lscala/collection/Vector;)Ljava/lang/CharSequence;
const #47 = Method	#31.#46;	//  scala/Predef$.seqToCharSequence:(Lscala/collection/Vector;)Ljava/lang/CharSequence;
const #48 = Asciz	this;
const #49 = Asciz	Lscala/Predef$$anon$2;;
const #50 = Asciz	start;
const #51 = Asciz	I;
const #52 = Asciz	end;
const #53 = Asciz	LocalVariableTable;
const #54 = Asciz	charAt;
const #55 = Asciz	(I)C;
const #56 = Asciz	scala/collection/generic/SequenceTemplate;
const #57 = class	#56;	//  scala/collection/generic/SequenceTemplate
const #58 = Asciz	apply;
const #59 = Asciz	(I)Ljava/lang/Object;;
const #60 = NameAndType	#58:#59;//  apply:(I)Ljava/lang/Object;
const #61 = InterfaceMethod	#57.#60;	//  scala/collection/generic/SequenceTemplate.apply:(I)Ljava/lang/Object;
const #62 = Asciz	scala/runtime/BoxesRunTime;
const #63 = class	#62;	//  scala/runtime/BoxesRunTime
const #64 = Asciz	unboxToChar;
const #65 = Asciz	(Ljava/lang/Object;)C;
const #66 = NameAndType	#64:#65;//  unboxToChar:(Ljava/lang/Object;)C
const #67 = Method	#63.#66;	//  scala/runtime/BoxesRunTime.unboxToChar:(Ljava/lang/Object;)C
const #68 = Asciz	index;
const #69 = Asciz	length;
const #70 = Asciz	()I;
const #71 = NameAndType	#69:#70;//  length:()I
const #72 = InterfaceMethod	#57.#71;	//  scala/collection/generic/SequenceTemplate.length:()I
const #73 = Asciz	Scala;
const #74 = Asciz	InnerClasses;
const #75 = Asciz	scala/Predef;
const #76 = class	#75;	//  scala/Predef
const #77 = Asciz	$anon$2;
const #78 = Asciz	java/lang/CharSequence;
const #79 = class	#78;	//  java/lang/CharSequence

{
public scala.Predef$$anon$2(scala.collection.Vector);
  Code:
   Stack=2, Locals=2, Args_size=2
   0:	aload_0
   1:	aload_1
   2:	putfield	#12; //Field xs$1:Lscala/collection/Vector;
   5:	aload_0
   6:	invokespecial	#17; //Method java/lang/Object."<init>":()V
   9:	return
  LineNumberTable: 
   line 245: 0


public java.lang.String toString();
  Code:
   Stack=2, Locals=1, Args_size=1
   0:	aload_0
   1:	getfield	#12; //Field xs$1:Lscala/collection/Vector;
   4:	ldc	#21; //String 
   6:	invokeinterface	#27,  2; //InterfaceMethod scala/collection/generic/TraversableTemplate.mkString:(Ljava/lang/String;)Ljava/lang/String;
   11:	areturn
  LineNumberTable: 
   line 249: 0


public java.lang.CharSequence subSequence(int, int);
  Code:
   Stack=4, Locals=3, Args_size=3
   0:	getstatic	#35; //Field scala/Predef$.MODULE$:Lscala/Predef$;
   3:	aload_0
   4:	getfield	#12; //Field xs$1:Lscala/collection/Vector;
   7:	iload_1
   8:	iload_2
   9:	invokeinterface	#41,  3; //InterfaceMethod scala/collection/generic/VectorTemplate.slice:(II)Lscala/collection/generic/VectorTemplate;
   14:	checkcast	#43; //class scala/collection/Vector
   17:	invokevirtual	#47; //Method scala/Predef$.seqToCharSequence:(Lscala/collection/Vector;)Ljava/lang/CharSequence;
   20:	areturn
  LineNumberTable: 
   line 248: 0

  LocalVariableTable: 
   Start  Length  Slot  Name   Signature
   0      21      0    this       Lscala/Predef$$anon$2;
   0      21      1    start       I
   0      21      2    end       I


public char charAt(int);
  Code:
   Stack=2, Locals=2, Args_size=2
   0:	aload_0
   1:	getfield	#12; //Field xs$1:Lscala/collection/Vector;
   4:	iload_1
   5:	invokeinterface	#61,  2; //InterfaceMethod scala/collection/generic/SequenceTemplate.apply:(I)Ljava/lang/Object;
   10:	invokestatic	#67; //Method scala/runtime/BoxesRunTime.unboxToChar:(Ljava/lang/Object;)C
   13:	ireturn
  LineNumberTable: 
   line 247: 0

  LocalVariableTable: 
   Start  Length  Slot  Name   Signature
   0      14      0    this       Lscala/Predef$$anon$2;
   0      14      1    index       I


public int length();
  Code:
   Stack=1, Locals=1, Args_size=1
   0:	aload_0
   1:	getfield	#12; //Field xs$1:Lscala/collection/Vector;
   4:	invokeinterface	#72,  1; //InterfaceMethod scala/collection/generic/SequenceTemplate.length:()I
   9:	ireturn
  LineNumberTable: 
   line 246: 0


}

