Compiled from "Predef.scala"
public final class scala.Predef$$less$percent$less$ extends java.lang.Object implements scala.ScalaObject
  SourceFile: "Predef.scala"
  Scala: length = 0x
   
  InnerClass: 
   public abstract #38= #35 of #37; //$less$percent$less=class scala/Predef$$less$percent$less of class scala/Predef
   public final #39= #23 of #10; //$anon$3=class scala/Predef$$less$percent$less$$anon$3 of class scala/Predef$$less$percent$less$
  minor version: 0
  major version: 49
  Constant pool:
const #1 = Asciz	SourceFile;
const #2 = Asciz	Predef.scala;
const #3 = Asciz	Scala;
const #4 = Asciz	MODULE$;
const #5 = Asciz	Lscala/Predef$$less$percent$less$;;
const #6 = Asciz	<clinit>;
const #7 = Asciz	()V;
const #8 = Asciz	Code;
const #9 = Asciz	scala/Predef$$less$percent$less$;
const #10 = class	#9;	//  scala/Predef$$less$percent$less$
const #11 = Asciz	<init>;
const #12 = NameAndType	#11:#7;//  "<init>":()V
const #13 = Method	#10.#12;	//  scala/Predef$$less$percent$less$."<init>":()V
const #14 = Asciz	LineNumberTable;
const #15 = Asciz	java/lang/Object;
const #16 = class	#15;	//  java/lang/Object
const #17 = Method	#16.#12;	//  java/lang/Object."<init>":()V
const #18 = NameAndType	#4:#5;//  MODULE$:Lscala/Predef$$less$percent$less$;
const #19 = Field	#10.#18;	//  scala/Predef$$less$percent$less$.MODULE$:Lscala/Predef$$less$percent$less$;
const #20 = Asciz	conformsOrViewsAs;
const #21 = Asciz	(Lscala/Function1;)Lscala/Predef$$less$percent$less;;
const #22 = Asciz	scala/Predef$$less$percent$less$$anon$3;
const #23 = class	#22;	//  scala/Predef$$less$percent$less$$anon$3
const #24 = Asciz	(Lscala/Function1;)V;
const #25 = NameAndType	#11:#24;//  "<init>":(Lscala/Function1;)V
const #26 = Method	#23.#25;	//  scala/Predef$$less$percent$less$$anon$3."<init>":(Lscala/Function1;)V
const #27 = Asciz	this;
const #28 = Asciz	evidence$1$1;
const #29 = Asciz	Lscala/Function1;;
const #30 = Asciz	LocalVariableTable;
const #31 = Asciz	<A:Ljava/lang/Object;B:Ljava/lang/Object;>(Lscala/Function1<TA;TB;>;)Lscala/Predef$$less$percent$less<TA;TB;>;;
const #32 = Asciz	Signature;
const #33 = Asciz	InnerClasses;
const #34 = Asciz	scala/Predef$$less$percent$less;
const #35 = class	#34;	//  scala/Predef$$less$percent$less
const #36 = Asciz	scala/Predef;
const #37 = class	#36;	//  scala/Predef
const #38 = Asciz	$less$percent$less;
const #39 = Asciz	$anon$3;
const #40 = Asciz	scala/ScalaObject;
const #41 = class	#40;	//  scala/ScalaObject

{
public static final scala.Predef$$less$percent$less$ MODULE$;

public static {};
  Code:
   Stack=1, Locals=0, Args_size=0
   0:	new	#10; //class scala/Predef$$less$percent$less$
   3:	invokespecial	#13; //Method "<init>":()V
   6:	return

public scala.Predef$$less$percent$less$();
  Code:
   Stack=1, Locals=1, Args_size=1
   0:	aload_0
   1:	invokespecial	#17; //Method java/lang/Object."<init>":()V
   4:	aload_0
   5:	putstatic	#19; //Field MODULE$:Lscala/Predef$$less$percent$less$;
   8:	return
  LineNumberTable: 
   line 290: 0


public scala.Predef$$less$percent$less conformsOrViewsAs(scala.Function1);
  Code:
   Stack=3, Locals=2, Args_size=2
   0:	new	#23; //class scala/Predef$$less$percent$less$$anon$3
   3:	dup
   4:	aload_1
   5:	invokespecial	#26; //Method scala/Predef$$less$percent$less$$anon$3."<init>":(Lscala/Function1;)V
   8:	areturn
  LineNumberTable: 
   line 291: 0

  LocalVariableTable: 
   Start  Length  Slot  Name   Signature
   0      9      0    this       Lscala/Predef$$less$percent$less$;
   0      9      1    evidence$1$1       Lscala/Function1;

  Signature: length = 0x2
   00 1F 

}

