Compiled from "Product.scala"
public abstract class scala.Product$class extends java.lang.Object
  SourceFile: "Product.scala"
  Scala: length = 0x
   
  InnerClass: 
   public final #33= #27 of #21; //$anon$1=class scala/Product$$anon$1 of class scala/Product
  minor version: 0
  major version: 49
  Constant pool:
const #1 = Asciz	SourceFile;
const #2 = Asciz	Product.scala;
const #3 = Asciz	$init$;
const #4 = Asciz	(Lscala/Product;)V;
const #5 = Asciz	Code;
const #6 = Asciz	LineNumberTable;
const #7 = Asciz	$this;
const #8 = Asciz	Lscala/Product;;
const #9 = Asciz	LocalVariableTable;
const #10 = Asciz	canEqual;
const #11 = Asciz	(Lscala/Product;Ljava/lang/Object;)Z;
const #12 = Asciz	other;
const #13 = Asciz	Ljava/lang/Object;;
const #14 = Asciz	productPrefix;
const #15 = Asciz	(Lscala/Product;)Ljava/lang/String;;
const #16 = Asciz	;
const #17 = String	#16;	//  
const #18 = Asciz	productElements;
const #19 = Asciz	(Lscala/Product;)Lscala/collection/Iterator;;
const #20 = Asciz	scala/Product;
const #21 = class	#20;	//  scala/Product
const #22 = Asciz	productIterator;
const #23 = Asciz	()Lscala/collection/Iterator;;
const #24 = NameAndType	#22:#23;//  productIterator:()Lscala/collection/Iterator;
const #25 = InterfaceMethod	#21.#24;	//  scala/Product.productIterator:()Lscala/collection/Iterator;
const #26 = Asciz	scala/Product$$anon$1;
const #27 = class	#26;	//  scala/Product$$anon$1
const #28 = Asciz	<init>;
const #29 = NameAndType	#28:#4;//  "<init>":(Lscala/Product;)V
const #30 = Method	#27.#29;	//  scala/Product$$anon$1."<init>":(Lscala/Product;)V
const #31 = Asciz	Scala;
const #32 = Asciz	InnerClasses;
const #33 = Asciz	$anon$1;
const #34 = Asciz	scala/Product$class;
const #35 = class	#34;	//  scala/Product$class
const #36 = Asciz	java/lang/Object;
const #37 = class	#36;	//  java/lang/Object

{
public static void $init$(scala.Product);
  Code:
   Stack=0, Locals=1, Args_size=1
   0:	return
  LineNumberTable: 
   line 20: 0

  LocalVariableTable: 
   Start  Length  Slot  Name   Signature
   0      1      0    $this       Lscala/Product;


public static boolean canEqual(scala.Product, java.lang.Object);
  Code:
   Stack=1, Locals=2, Args_size=2
   0:	iconst_1
   1:	ireturn
  LineNumberTable: 
   line 58: 0

  LocalVariableTable: 
   Start  Length  Slot  Name   Signature
   0      2      0    $this       Lscala/Product;
   0      2      1    other       Ljava/lang/Object;


public static java.lang.String productPrefix(scala.Product);
  Code:
   Stack=1, Locals=1, Args_size=1
   0:	ldc	#17; //String 
   2:	areturn
  LineNumberTable: 
   line 51: 0

  LocalVariableTable: 
   Start  Length  Slot  Name   Signature
   0      3      0    $this       Lscala/Product;


public static scala.collection.Iterator productElements(scala.Product);
  Code:
   Stack=1, Locals=1, Args_size=1
   0:	aload_0
   1:	invokeinterface	#25,  1; //InterfaceMethod scala/Product.productIterator:()Lscala/collection/Iterator;
   6:	areturn
  LineNumberTable: 
   line 44: 0

  LocalVariableTable: 
   Start  Length  Slot  Name   Signature
   0      7      0    $this       Lscala/Product;


public static scala.collection.Iterator productIterator(scala.Product);
  Code:
   Stack=3, Locals=1, Args_size=1
   0:	new	#27; //class scala/Product$$anon$1
   3:	dup
   4:	aload_0
   5:	invokespecial	#30; //Method scala/Product$$anon$1."<init>":(Lscala/Product;)V
   8:	areturn
  LineNumberTable: 
   line 36: 0

  LocalVariableTable: 
   Start  Length  Slot  Name   Signature
   0      9      0    $this       Lscala/Product;


}

