Compiled from "Product22.scala"
public abstract class scala.Product22$class extends java.lang.Object
  SourceFile: "Product22.scala"
  Scala: length = 0x
   
  minor version: 0
  major version: 49
  Constant pool:
Asciz	SourceFile;
Asciz	Product22.scala;
Asciz	$init$;
Asciz	(Lscala/Product22;)V;
Asciz	Code;
Asciz	LineNumberTable;
Asciz	$this;
Asciz	Lscala/Product22;;
Asciz	LocalVariableTable;
Asciz	productElement;
Asciz	(Lscala/Product22;I)Ljava/lang/Object;;
Asciz	java/lang/IndexOutOfBoundsException;
class	java/lang/IndexOutOfBoundsException
Asciz	scala/runtime/BoxesRunTime;
class	scala/runtime/BoxesRunTime
Asciz	boxToInteger;
Asciz	(I)Ljava/lang/Integer;;
NameAndType	boxToInteger:(I)Ljava/lang/Integer;
Method	scala/runtime/BoxesRunTime.boxToInteger:(I)Ljava/lang/Integer;
Asciz	java/lang/Object;
class	java/lang/Object
Asciz	toString;
Asciz	()Ljava/lang/String;;
NameAndType	toString:()Ljava/lang/String;
Method	java/lang/Object.toString:()Ljava/lang/String;
Asciz	<init>;
Asciz	(Ljava/lang/String;)V;
NameAndType	"<init>":(Ljava/lang/String;)V
Method	java/lang/IndexOutOfBoundsException."<init>":(Ljava/lang/String;)V
Asciz	scala/MatchError;
class	scala/MatchError
Method	scala/MatchError."<init>":(Ljava/lang/String;)V
Asciz	scala/Product22;
class	scala/Product22
Asciz	_22;
Asciz	()Ljava/lang/Object;;
NameAndType	_22:()Ljava/lang/Object;
InterfaceMethod	scala/Product22._22:()Ljava/lang/Object;
Asciz	_21;
NameAndType	_21:()Ljava/lang/Object;
InterfaceMethod	scala/Product22._21:()Ljava/lang/Object;
Asciz	_20;
NameAndType	_20:()Ljava/lang/Object;
InterfaceMethod	scala/Product22._20:()Ljava/lang/Object;
Asciz	_19;
NameAndType	_19:()Ljava/lang/Object;
InterfaceMethod	scala/Product22._19:()Ljava/lang/Object;
Asciz	_18;
NameAndType	_18:()Ljava/lang/Object;
InterfaceMethod	scala/Product22._18:()Ljava/lang/Object;
Asciz	_17;
NameAndType	_17:()Ljava/lang/Object;
InterfaceMethod	scala/Product22._17:()Ljava/lang/Object;
Asciz	_16;
NameAndType	_16:()Ljava/lang/Object;
InterfaceMethod	scala/Product22._16:()Ljava/lang/Object;
Asciz	_15;
NameAndType	_15:()Ljava/lang/Object;
InterfaceMethod	scala/Product22._15:()Ljava/lang/Object;
Asciz	_14;
NameAndType	_14:()Ljava/lang/Object;
InterfaceMethod	scala/Product22._14:()Ljava/lang/Object;
Asciz	_13;
NameAndType	_13:()Ljava/lang/Object;
InterfaceMethod	scala/Product22._13:()Ljava/lang/Object;
Asciz	_12;
NameAndType	_12:()Ljava/lang/Object;
InterfaceMethod	scala/Product22._12:()Ljava/lang/Object;
Asciz	_11;
NameAndType	_11:()Ljava/lang/Object;
InterfaceMethod	scala/Product22._11:()Ljava/lang/Object;
Asciz	_10;
NameAndType	_10:()Ljava/lang/Object;
InterfaceMethod	scala/Product22._10:()Ljava/lang/Object;
Asciz	_9;
NameAndType	_9:()Ljava/lang/Object;
InterfaceMethod	scala/Product22._9:()Ljava/lang/Object;
Asciz	_8;
NameAndType	_8:()Ljava/lang/Object;
InterfaceMethod	scala/Product22._8:()Ljava/lang/Object;
Asciz	_7;
NameAndType	_7:()Ljava/lang/Object;
InterfaceMethod	scala/Product22._7:()Ljava/lang/Object;
Asciz	_6;
NameAndType	_6:()Ljava/lang/Object;
InterfaceMethod	scala/Product22._6:()Ljava/lang/Object;
Asciz	_5;
NameAndType	_5:()Ljava/lang/Object;
InterfaceMethod	scala/Product22._5:()Ljava/lang/Object;
Asciz	_4;
NameAndType	_4:()Ljava/lang/Object;
InterfaceMethod	scala/Product22._4:()Ljava/lang/Object;
Asciz	_3;
NameAndType	_3:()Ljava/lang/Object;
InterfaceMethod	scala/Product22._3:()Ljava/lang/Object;
Asciz	_2;
NameAndType	_2:()Ljava/lang/Object;
InterfaceMethod	scala/Product22._2:()Ljava/lang/Object;
Asciz	_1;
NameAndType	_1:()Ljava/lang/Object;
InterfaceMethod	scala/Product22._1:()Ljava/lang/Object;
Asciz	n;
Asciz	I;
Asciz	Exceptions;
Asciz	productArity;
Asciz	(Lscala/Product22;)I;
int	22;
Asciz	Scala;
Asciz	scala/Product22$class;
class	scala/Product22$class

{
public static void $init$(scala.Product22);
  Signature: (Lscala/Product22;)V
  Code:
   Stack=0, Locals=1, Args_size=1
	return
  Labels:
  LocalVariableTable: 
   Start  Length  Slot  Name   Signature
   0      1      0    $this       Lscala/Product22;


public static java.lang.Object productElement(scala.Product22, int)   throws java.lang.IndexOutOfBoundsException;
  Signature: (Lscala/Product22;I)Ljava/lang/Object;
  Code:
   Stack=3, Locals=2, Args_size=2
	iload_1
	tableswitch{ //0 to 21
		0: 726;
		1: 698;
		2: 670;
		3: 642;
		4: 614;
		5: 586;
		6: 558;
		7: 530;
		8: 502;
		9: 474;
		10: 446;
		11: 418;
		12: 390;
		13: 362;
		14: 334;
		15: 306;
		16: 278;
		17: 250;
		18: 222;
		19: 194;
		20: 166;
		21: 138;
		default: 104 }
	iconst_1
	ifeq	l1 // new
	new	class java/lang/IndexOutOfBoundsException
	dup
	iload_1
	invokestatic	Method scala/runtime/BoxesRunTime.boxToInteger:(I)Ljava/lang/Integer;
	invokevirtual	Method java/lang/Object.toString:()Ljava/lang/String;
	invokespecial	Method java/lang/IndexOutOfBoundsException."<init>":(Ljava/lang/String;)V
	athrow
l1	new	class scala/MatchError
	dup
	iload_1
	invokestatic	Method scala/runtime/BoxesRunTime.boxToInteger:(I)Ljava/lang/Integer;
	invokevirtual	Method java/lang/Object.toString:()Ljava/lang/String;
	invokespecial	Method scala/MatchError."<init>":(Ljava/lang/String;)V
	athrow
	iconst_1
	ifeq	l2 // new
	aload_0
	invokeinterface	InterfaceMethod scala/Product22._22:()Ljava/lang/Object;
	goto	l3 // areturn
l2	new	class scala/MatchError
	dup
	iload_1
	invokestatic	Method scala/runtime/BoxesRunTime.boxToInteger:(I)Ljava/lang/Integer;
	invokevirtual	Method java/lang/Object.toString:()Ljava/lang/String;
	invokespecial	Method scala/MatchError."<init>":(Ljava/lang/String;)V
	athrow
	iconst_1
	ifeq	l4 // new
	aload_0
	invokeinterface	InterfaceMethod scala/Product22._21:()Ljava/lang/Object;
	goto	l3 // areturn
l4	new	class scala/MatchError
	dup
	iload_1
	invokestatic	Method scala/runtime/BoxesRunTime.boxToInteger:(I)Ljava/lang/Integer;
	invokevirtual	Method java/lang/Object.toString:()Ljava/lang/String;
	invokespecial	Method scala/MatchError."<init>":(Ljava/lang/String;)V
	athrow
	iconst_1
	ifeq	l5 // new
	aload_0
	invokeinterface	InterfaceMethod scala/Product22._20:()Ljava/lang/Object;
	goto	l3 // areturn
l5	new	class scala/MatchError
	dup
	iload_1
	invokestatic	Method scala/runtime/BoxesRunTime.boxToInteger:(I)Ljava/lang/Integer;
	invokevirtual	Method java/lang/Object.toString:()Ljava/lang/String;
	invokespecial	Method scala/MatchError."<init>":(Ljava/lang/String;)V
	athrow
	iconst_1
	ifeq	l6 // new
	aload_0
	invokeinterface	InterfaceMethod scala/Product22._19:()Ljava/lang/Object;
	goto	l3 // areturn
l6	new	class scala/MatchError
	dup
	iload_1
	invokestatic	Method scala/runtime/BoxesRunTime.boxToInteger:(I)Ljava/lang/Integer;
	invokevirtual	Method java/lang/Object.toString:()Ljava/lang/String;
	invokespecial	Method scala/MatchError."<init>":(Ljava/lang/String;)V
	athrow
	iconst_1
	ifeq	l7 // new
	aload_0
	invokeinterface	InterfaceMethod scala/Product22._18:()Ljava/lang/Object;
	goto	l3 // areturn
l7	new	class scala/MatchError
	dup
	iload_1
	invokestatic	Method scala/runtime/BoxesRunTime.boxToInteger:(I)Ljava/lang/Integer;
	invokevirtual	Method java/lang/Object.toString:()Ljava/lang/String;
	invokespecial	Method scala/MatchError."<init>":(Ljava/lang/String;)V
	athrow
	iconst_1
	ifeq	l8 // new
	aload_0
	invokeinterface	InterfaceMethod scala/Product22._17:()Ljava/lang/Object;
	goto	l3 // areturn
l8	new	class scala/MatchError
	dup
	iload_1
	invokestatic	Method scala/runtime/BoxesRunTime.boxToInteger:(I)Ljava/lang/Integer;
	invokevirtual	Method java/lang/Object.toString:()Ljava/lang/String;
	invokespecial	Method scala/MatchError."<init>":(Ljava/lang/String;)V
	athrow
	iconst_1
	ifeq	l9 // new
	aload_0
	invokeinterface	InterfaceMethod scala/Product22._16:()Ljava/lang/Object;
	goto	l3 // areturn
l9	new	class scala/MatchError
	dup
	iload_1
	invokestatic	Method scala/runtime/BoxesRunTime.boxToInteger:(I)Ljava/lang/Integer;
	invokevirtual	Method java/lang/Object.toString:()Ljava/lang/String;
	invokespecial	Method scala/MatchError."<init>":(Ljava/lang/String;)V
	athrow
	iconst_1
	ifeq	l10 // new
	aload_0
	invokeinterface	InterfaceMethod scala/Product22._15:()Ljava/lang/Object;
	goto	l3 // areturn
l10	new	class scala/MatchError
	dup
	iload_1
	invokestatic	Method scala/runtime/BoxesRunTime.boxToInteger:(I)Ljava/lang/Integer;
	invokevirtual	Method java/lang/Object.toString:()Ljava/lang/String;
	invokespecial	Method scala/MatchError."<init>":(Ljava/lang/String;)V
	athrow
	iconst_1
	ifeq	l11 // new
	aload_0
	invokeinterface	InterfaceMethod scala/Product22._14:()Ljava/lang/Object;
	goto	l3 // areturn
l11	new	class scala/MatchError
	dup
	iload_1
	invokestatic	Method scala/runtime/BoxesRunTime.boxToInteger:(I)Ljava/lang/Integer;
	invokevirtual	Method java/lang/Object.toString:()Ljava/lang/String;
	invokespecial	Method scala/MatchError."<init>":(Ljava/lang/String;)V
	athrow
	iconst_1
	ifeq	l12 // new
	aload_0
	invokeinterface	InterfaceMethod scala/Product22._13:()Ljava/lang/Object;
	goto	l3 // areturn
l12	new	class scala/MatchError
	dup
	iload_1
	invokestatic	Method scala/runtime/BoxesRunTime.boxToInteger:(I)Ljava/lang/Integer;
	invokevirtual	Method java/lang/Object.toString:()Ljava/lang/String;
	invokespecial	Method scala/MatchError."<init>":(Ljava/lang/String;)V
	athrow
	iconst_1
	ifeq	l13 // new
	aload_0
	invokeinterface	InterfaceMethod scala/Product22._12:()Ljava/lang/Object;
	goto	l3 // areturn
l13	new	class scala/MatchError
	dup
	iload_1
	invokestatic	Method scala/runtime/BoxesRunTime.boxToInteger:(I)Ljava/lang/Integer;
	invokevirtual	Method java/lang/Object.toString:()Ljava/lang/String;
	invokespecial	Method scala/MatchError."<init>":(Ljava/lang/String;)V
	athrow
	iconst_1
	ifeq	l14 // new
	aload_0
	invokeinterface	InterfaceMethod scala/Product22._11:()Ljava/lang/Object;
	goto	l3 // areturn
l14	new	class scala/MatchError
	dup
	iload_1
	invokestatic	Method scala/runtime/BoxesRunTime.boxToInteger:(I)Ljava/lang/Integer;
	invokevirtual	Method java/lang/Object.toString:()Ljava/lang/String;
	invokespecial	Method scala/MatchError."<init>":(Ljava/lang/String;)V
	athrow
	iconst_1
	ifeq	l15 // new
	aload_0
	invokeinterface	InterfaceMethod scala/Product22._10:()Ljava/lang/Object;
	goto	l3 // areturn
l15	new	class scala/MatchError
	dup
	iload_1
	invokestatic	Method scala/runtime/BoxesRunTime.boxToInteger:(I)Ljava/lang/Integer;
	invokevirtual	Method java/lang/Object.toString:()Ljava/lang/String;
	invokespecial	Method scala/MatchError."<init>":(Ljava/lang/String;)V
	athrow
	iconst_1
	ifeq	l16 // new
	aload_0
	invokeinterface	InterfaceMethod scala/Product22._9:()Ljava/lang/Object;
	goto	l3 // areturn
l16	new	class scala/MatchError
	dup
	iload_1
	invokestatic	Method scala/runtime/BoxesRunTime.boxToInteger:(I)Ljava/lang/Integer;
	invokevirtual	Method java/lang/Object.toString:()Ljava/lang/String;
	invokespecial	Method scala/MatchError."<init>":(Ljava/lang/String;)V
	athrow
	iconst_1
	ifeq	l17 // new
	aload_0
	invokeinterface	InterfaceMethod scala/Product22._8:()Ljava/lang/Object;
	goto	l3 // areturn
l17	new	class scala/MatchError
	dup
	iload_1
	invokestatic	Method scala/runtime/BoxesRunTime.boxToInteger:(I)Ljava/lang/Integer;
	invokevirtual	Method java/lang/Object.toString:()Ljava/lang/String;
	invokespecial	Method scala/MatchError."<init>":(Ljava/lang/String;)V
	athrow
	iconst_1
	ifeq	l18 // new
	aload_0
	invokeinterface	InterfaceMethod scala/Product22._7:()Ljava/lang/Object;
	goto	l3 // areturn
l18	new	class scala/MatchError
	dup
	iload_1
	invokestatic	Method scala/runtime/BoxesRunTime.boxToInteger:(I)Ljava/lang/Integer;
	invokevirtual	Method java/lang/Object.toString:()Ljava/lang/String;
	invokespecial	Method scala/MatchError."<init>":(Ljava/lang/String;)V
	athrow
	iconst_1
	ifeq	l19 // new
	aload_0
	invokeinterface	InterfaceMethod scala/Product22._6:()Ljava/lang/Object;
	goto	l3 // areturn
l19	new	class scala/MatchError
	dup
	iload_1
	invokestatic	Method scala/runtime/BoxesRunTime.boxToInteger:(I)Ljava/lang/Integer;
	invokevirtual	Method java/lang/Object.toString:()Ljava/lang/String;
	invokespecial	Method scala/MatchError."<init>":(Ljava/lang/String;)V
	athrow
	iconst_1
	ifeq	l20 // new
	aload_0
	invokeinterface	InterfaceMethod scala/Product22._5:()Ljava/lang/Object;
	goto	l3 // areturn
l20	new	class scala/MatchError
	dup
	iload_1
	invokestatic	Method scala/runtime/BoxesRunTime.boxToInteger:(I)Ljava/lang/Integer;
	invokevirtual	Method java/lang/Object.toString:()Ljava/lang/String;
	invokespecial	Method scala/MatchError."<init>":(Ljava/lang/String;)V
	athrow
	iconst_1
	ifeq	l21 // new
	aload_0
	invokeinterface	InterfaceMethod scala/Product22._4:()Ljava/lang/Object;
	goto	l3 // areturn
l21	new	class scala/MatchError
	dup
	iload_1
	invokestatic	Method scala/runtime/BoxesRunTime.boxToInteger:(I)Ljava/lang/Integer;
	invokevirtual	Method java/lang/Object.toString:()Ljava/lang/String;
	invokespecial	Method scala/MatchError."<init>":(Ljava/lang/String;)V
	athrow
	iconst_1
	ifeq	l22 // new
	aload_0
	invokeinterface	InterfaceMethod scala/Product22._3:()Ljava/lang/Object;
	goto	l3 // areturn
l22	new	class scala/MatchError
	dup
	iload_1
	invokestatic	Method scala/runtime/BoxesRunTime.boxToInteger:(I)Ljava/lang/Integer;
	invokevirtual	Method java/lang/Object.toString:()Ljava/lang/String;
	invokespecial	Method scala/MatchError."<init>":(Ljava/lang/String;)V
	athrow
	iconst_1
	ifeq	l23 // new
	aload_0
	invokeinterface	InterfaceMethod scala/Product22._2:()Ljava/lang/Object;
	goto	l3 // areturn
l23	new	class scala/MatchError
	dup
	iload_1
	invokestatic	Method scala/runtime/BoxesRunTime.boxToInteger:(I)Ljava/lang/Integer;
	invokevirtual	Method java/lang/Object.toString:()Ljava/lang/String;
	invokespecial	Method scala/MatchError."<init>":(Ljava/lang/String;)V
	athrow
	iconst_1
	ifeq	l24 // new
	aload_0
	invokeinterface	InterfaceMethod scala/Product22._1:()Ljava/lang/Object;
l3	areturn
l24	new	class scala/MatchError
	dup
	iload_1
	invokestatic	Method scala/runtime/BoxesRunTime.boxToInteger:(I)Ljava/lang/Integer;
	invokevirtual	Method java/lang/Object.toString:()Ljava/lang/String;
	invokespecial	Method scala/MatchError."<init>":(Ljava/lang/String;)V
	athrow
  Labels:
   	l1 = 123 // new
   	l2 = 151 // new
   	l4 = 179 // new
   	l5 = 207 // new
   	l6 = 235 // new
   	l7 = 263 // new
   	l8 = 291 // new
   	l9 = 319 // new
   	l10 = 347 // new
   	l11 = 375 // new
   	l12 = 403 // new
   	l13 = 431 // new
   	l14 = 459 // new
   	l15 = 487 // new
   	l16 = 515 // new
   	l17 = 543 // new
   	l18 = 571 // new
   	l19 = 599 // new
   	l20 = 627 // new
   	l21 = 655 // new
   	l22 = 683 // new
   	l23 = 711 // new
   	l3 = 736 // areturn
   	l24 = 737 // new
  LocalVariableTable: 
   Start  Length  Slot  Name   Signature
   0      752      0    $this       Lscala/Product22;
   0      752      1    n       I

  Exceptions: 
   throws java.lang.IndexOutOfBoundsException
public static int productArity(scala.Product22);
  Signature: (Lscala/Product22;)I
  Code:
   Stack=1, Locals=1, Args_size=1
	ldc	int 22
	ireturn
  Labels:
  LocalVariableTable: 
   Start  Length  Slot  Name   Signature
   0      3      0    $this       Lscala/Product22;


}

