Compiled from "Product22.scala"
public abstract class scala.Product22$class extends java.lang.Object
  SourceFile: "Product22.scala"
  Scala: length = 0x
   
  minor version: 0
  major version: 49
  Constant pool:
const #1 = Asciz	SourceFile;
const #2 = Asciz	Product22.scala;
const #3 = Asciz	$init$;
const #4 = Asciz	(Lscala/Product22;)V;
const #5 = Asciz	Code;
const #6 = Asciz	LineNumberTable;
const #7 = Asciz	$this;
const #8 = Asciz	Lscala/Product22;;
const #9 = Asciz	LocalVariableTable;
const #10 = Asciz	productElement;
const #11 = Asciz	(Lscala/Product22;I)Ljava/lang/Object;;
const #12 = Asciz	java/lang/IndexOutOfBoundsException;
const #13 = class	#12;	//  java/lang/IndexOutOfBoundsException
const #14 = Asciz	scala/runtime/BoxesRunTime;
const #15 = class	#14;	//  scala/runtime/BoxesRunTime
const #16 = Asciz	boxToInteger;
const #17 = Asciz	(I)Ljava/lang/Integer;;
const #18 = NameAndType	#16:#17;//  boxToInteger:(I)Ljava/lang/Integer;
const #19 = Method	#15.#18;	//  scala/runtime/BoxesRunTime.boxToInteger:(I)Ljava/lang/Integer;
const #20 = Asciz	java/lang/Object;
const #21 = class	#20;	//  java/lang/Object
const #22 = Asciz	toString;
const #23 = Asciz	()Ljava/lang/String;;
const #24 = NameAndType	#22:#23;//  toString:()Ljava/lang/String;
const #25 = Method	#21.#24;	//  java/lang/Object.toString:()Ljava/lang/String;
const #26 = Asciz	<init>;
const #27 = Asciz	(Ljava/lang/String;)V;
const #28 = NameAndType	#26:#27;//  "<init>":(Ljava/lang/String;)V
const #29 = Method	#13.#28;	//  java/lang/IndexOutOfBoundsException."<init>":(Ljava/lang/String;)V
const #30 = Asciz	scala/MatchError;
const #31 = class	#30;	//  scala/MatchError
const #32 = Method	#31.#28;	//  scala/MatchError."<init>":(Ljava/lang/String;)V
const #33 = Asciz	scala/Product22;
const #34 = class	#33;	//  scala/Product22
const #35 = Asciz	_22;
const #36 = Asciz	()Ljava/lang/Object;;
const #37 = NameAndType	#35:#36;//  _22:()Ljava/lang/Object;
const #38 = InterfaceMethod	#34.#37;	//  scala/Product22._22:()Ljava/lang/Object;
const #39 = Asciz	_21;
const #40 = NameAndType	#39:#36;//  _21:()Ljava/lang/Object;
const #41 = InterfaceMethod	#34.#40;	//  scala/Product22._21:()Ljava/lang/Object;
const #42 = Asciz	_20;
const #43 = NameAndType	#42:#36;//  _20:()Ljava/lang/Object;
const #44 = InterfaceMethod	#34.#43;	//  scala/Product22._20:()Ljava/lang/Object;
const #45 = Asciz	_19;
const #46 = NameAndType	#45:#36;//  _19:()Ljava/lang/Object;
const #47 = InterfaceMethod	#34.#46;	//  scala/Product22._19:()Ljava/lang/Object;
const #48 = Asciz	_18;
const #49 = NameAndType	#48:#36;//  _18:()Ljava/lang/Object;
const #50 = InterfaceMethod	#34.#49;	//  scala/Product22._18:()Ljava/lang/Object;
const #51 = Asciz	_17;
const #52 = NameAndType	#51:#36;//  _17:()Ljava/lang/Object;
const #53 = InterfaceMethod	#34.#52;	//  scala/Product22._17:()Ljava/lang/Object;
const #54 = Asciz	_16;
const #55 = NameAndType	#54:#36;//  _16:()Ljava/lang/Object;
const #56 = InterfaceMethod	#34.#55;	//  scala/Product22._16:()Ljava/lang/Object;
const #57 = Asciz	_15;
const #58 = NameAndType	#57:#36;//  _15:()Ljava/lang/Object;
const #59 = InterfaceMethod	#34.#58;	//  scala/Product22._15:()Ljava/lang/Object;
const #60 = Asciz	_14;
const #61 = NameAndType	#60:#36;//  _14:()Ljava/lang/Object;
const #62 = InterfaceMethod	#34.#61;	//  scala/Product22._14:()Ljava/lang/Object;
const #63 = Asciz	_13;
const #64 = NameAndType	#63:#36;//  _13:()Ljava/lang/Object;
const #65 = InterfaceMethod	#34.#64;	//  scala/Product22._13:()Ljava/lang/Object;
const #66 = Asciz	_12;
const #67 = NameAndType	#66:#36;//  _12:()Ljava/lang/Object;
const #68 = InterfaceMethod	#34.#67;	//  scala/Product22._12:()Ljava/lang/Object;
const #69 = Asciz	_11;
const #70 = NameAndType	#69:#36;//  _11:()Ljava/lang/Object;
const #71 = InterfaceMethod	#34.#70;	//  scala/Product22._11:()Ljava/lang/Object;
const #72 = Asciz	_10;
const #73 = NameAndType	#72:#36;//  _10:()Ljava/lang/Object;
const #74 = InterfaceMethod	#34.#73;	//  scala/Product22._10:()Ljava/lang/Object;
const #75 = Asciz	_9;
const #76 = NameAndType	#75:#36;//  _9:()Ljava/lang/Object;
const #77 = InterfaceMethod	#34.#76;	//  scala/Product22._9:()Ljava/lang/Object;
const #78 = Asciz	_8;
const #79 = NameAndType	#78:#36;//  _8:()Ljava/lang/Object;
const #80 = InterfaceMethod	#34.#79;	//  scala/Product22._8:()Ljava/lang/Object;
const #81 = Asciz	_7;
const #82 = NameAndType	#81:#36;//  _7:()Ljava/lang/Object;
const #83 = InterfaceMethod	#34.#82;	//  scala/Product22._7:()Ljava/lang/Object;
const #84 = Asciz	_6;
const #85 = NameAndType	#84:#36;//  _6:()Ljava/lang/Object;
const #86 = InterfaceMethod	#34.#85;	//  scala/Product22._6:()Ljava/lang/Object;
const #87 = Asciz	_5;
const #88 = NameAndType	#87:#36;//  _5:()Ljava/lang/Object;
const #89 = InterfaceMethod	#34.#88;	//  scala/Product22._5:()Ljava/lang/Object;
const #90 = Asciz	_4;
const #91 = NameAndType	#90:#36;//  _4:()Ljava/lang/Object;
const #92 = InterfaceMethod	#34.#91;	//  scala/Product22._4:()Ljava/lang/Object;
const #93 = Asciz	_3;
const #94 = NameAndType	#93:#36;//  _3:()Ljava/lang/Object;
const #95 = InterfaceMethod	#34.#94;	//  scala/Product22._3:()Ljava/lang/Object;
const #96 = Asciz	_2;
const #97 = NameAndType	#96:#36;//  _2:()Ljava/lang/Object;
const #98 = InterfaceMethod	#34.#97;	//  scala/Product22._2:()Ljava/lang/Object;
const #99 = Asciz	_1;
const #100 = NameAndType	#99:#36;//  _1:()Ljava/lang/Object;
const #101 = InterfaceMethod	#34.#100;	//  scala/Product22._1:()Ljava/lang/Object;
const #102 = Asciz	n;
const #103 = Asciz	I;
const #104 = Asciz	Exceptions;
const #105 = Asciz	productArity;
const #106 = Asciz	(Lscala/Product22;)I;
const #107 = int	22;
const #108 = Asciz	Scala;
const #109 = Asciz	scala/Product22$class;
const #110 = class	#109;	//  scala/Product22$class

{
public static void $init$(scala.Product22);
  Code:
   Stack=0, Locals=1, Args_size=1
   0:	return
  LineNumberTable: 
   line 25: 0

  LocalVariableTable: 
   Start  Length  Slot  Name   Signature
   0      1      0    $this       Lscala/Product22;


public static java.lang.Object productElement(scala.Product22, int)   throws java.lang.IndexOutOfBoundsException;
  Code:
   Stack=3, Locals=2, Args_size=2
   0:	iload_1
   1:	tableswitch{ //0 to 21
		0: 726;
		1: 698;
		2: 670;
		3: 642;
		4: 614;
		5: 586;
		6: 558;
		7: 530;
		8: 502;
		9: 474;
		10: 446;
		11: 418;
		12: 390;
		13: 362;
		14: 334;
		15: 306;
		16: 278;
		17: 250;
		18: 222;
		19: 194;
		20: 166;
		21: 138;
		default: 104 }
   104:	iconst_1
   105:	ifeq	123
   108:	new	#13; //class java/lang/IndexOutOfBoundsException
   111:	dup
   112:	iload_1
   113:	invokestatic	#19; //Method scala/runtime/BoxesRunTime.boxToInteger:(I)Ljava/lang/Integer;
   116:	invokevirtual	#25; //Method java/lang/Object.toString:()Ljava/lang/String;
   119:	invokespecial	#29; //Method java/lang/IndexOutOfBoundsException."<init>":(Ljava/lang/String;)V
   122:	athrow
   123:	new	#31; //class scala/MatchError
   126:	dup
   127:	iload_1
   128:	invokestatic	#19; //Method scala/runtime/BoxesRunTime.boxToInteger:(I)Ljava/lang/Integer;
   131:	invokevirtual	#25; //Method java/lang/Object.toString:()Ljava/lang/String;
   134:	invokespecial	#32; //Method scala/MatchError."<init>":(Ljava/lang/String;)V
   137:	athrow
   138:	iconst_1
   139:	ifeq	151
   142:	aload_0
   143:	invokeinterface	#38,  1; //InterfaceMethod scala/Product22._22:()Ljava/lang/Object;
   148:	goto	736
   151:	new	#31; //class scala/MatchError
   154:	dup
   155:	iload_1
   156:	invokestatic	#19; //Method scala/runtime/BoxesRunTime.boxToInteger:(I)Ljava/lang/Integer;
   159:	invokevirtual	#25; //Method java/lang/Object.toString:()Ljava/lang/String;
   162:	invokespecial	#32; //Method scala/MatchError."<init>":(Ljava/lang/String;)V
   165:	athrow
   166:	iconst_1
   167:	ifeq	179
   170:	aload_0
   171:	invokeinterface	#41,  1; //InterfaceMethod scala/Product22._21:()Ljava/lang/Object;
   176:	goto	736
   179:	new	#31; //class scala/MatchError
   182:	dup
   183:	iload_1
   184:	invokestatic	#19; //Method scala/runtime/BoxesRunTime.boxToInteger:(I)Ljava/lang/Integer;
   187:	invokevirtual	#25; //Method java/lang/Object.toString:()Ljava/lang/String;
   190:	invokespecial	#32; //Method scala/MatchError."<init>":(Ljava/lang/String;)V
   193:	athrow
   194:	iconst_1
   195:	ifeq	207
   198:	aload_0
   199:	invokeinterface	#44,  1; //InterfaceMethod scala/Product22._20:()Ljava/lang/Object;
   204:	goto	736
   207:	new	#31; //class scala/MatchError
   210:	dup
   211:	iload_1
   212:	invokestatic	#19; //Method scala/runtime/BoxesRunTime.boxToInteger:(I)Ljava/lang/Integer;
   215:	invokevirtual	#25; //Method java/lang/Object.toString:()Ljava/lang/String;
   218:	invokespecial	#32; //Method scala/MatchError."<init>":(Ljava/lang/String;)V
   221:	athrow
   222:	iconst_1
   223:	ifeq	235
   226:	aload_0
   227:	invokeinterface	#47,  1; //InterfaceMethod scala/Product22._19:()Ljava/lang/Object;
   232:	goto	736
   235:	new	#31; //class scala/MatchError
   238:	dup
   239:	iload_1
   240:	invokestatic	#19; //Method scala/runtime/BoxesRunTime.boxToInteger:(I)Ljava/lang/Integer;
   243:	invokevirtual	#25; //Method java/lang/Object.toString:()Ljava/lang/String;
   246:	invokespecial	#32; //Method scala/MatchError."<init>":(Ljava/lang/String;)V
   249:	athrow
   250:	iconst_1
   251:	ifeq	263
   254:	aload_0
   255:	invokeinterface	#50,  1; //InterfaceMethod scala/Product22._18:()Ljava/lang/Object;
   260:	goto	736
   263:	new	#31; //class scala/MatchError
   266:	dup
   267:	iload_1
   268:	invokestatic	#19; //Method scala/runtime/BoxesRunTime.boxToInteger:(I)Ljava/lang/Integer;
   271:	invokevirtual	#25; //Method java/lang/Object.toString:()Ljava/lang/String;
   274:	invokespecial	#32; //Method scala/MatchError."<init>":(Ljava/lang/String;)V
   277:	athrow
   278:	iconst_1
   279:	ifeq	291
   282:	aload_0
   283:	invokeinterface	#53,  1; //InterfaceMethod scala/Product22._17:()Ljava/lang/Object;
   288:	goto	736
   291:	new	#31; //class scala/MatchError
   294:	dup
   295:	iload_1
   296:	invokestatic	#19; //Method scala/runtime/BoxesRunTime.boxToInteger:(I)Ljava/lang/Integer;
   299:	invokevirtual	#25; //Method java/lang/Object.toString:()Ljava/lang/String;
   302:	invokespecial	#32; //Method scala/MatchError."<init>":(Ljava/lang/String;)V
   305:	athrow
   306:	iconst_1
   307:	ifeq	319
   310:	aload_0
   311:	invokeinterface	#56,  1; //InterfaceMethod scala/Product22._16:()Ljava/lang/Object;
   316:	goto	736
   319:	new	#31; //class scala/MatchError
   322:	dup
   323:	iload_1
   324:	invokestatic	#19; //Method scala/runtime/BoxesRunTime.boxToInteger:(I)Ljava/lang/Integer;
   327:	invokevirtual	#25; //Method java/lang/Object.toString:()Ljava/lang/String;
   330:	invokespecial	#32; //Method scala/MatchError."<init>":(Ljava/lang/String;)V
   333:	athrow
   334:	iconst_1
   335:	ifeq	347
   338:	aload_0
   339:	invokeinterface	#59,  1; //InterfaceMethod scala/Product22._15:()Ljava/lang/Object;
   344:	goto	736
   347:	new	#31; //class scala/MatchError
   350:	dup
   351:	iload_1
   352:	invokestatic	#19; //Method scala/runtime/BoxesRunTime.boxToInteger:(I)Ljava/lang/Integer;
   355:	invokevirtual	#25; //Method java/lang/Object.toString:()Ljava/lang/String;
   358:	invokespecial	#32; //Method scala/MatchError."<init>":(Ljava/lang/String;)V
   361:	athrow
   362:	iconst_1
   363:	ifeq	375
   366:	aload_0
   367:	invokeinterface	#62,  1; //InterfaceMethod scala/Product22._14:()Ljava/lang/Object;
   372:	goto	736
   375:	new	#31; //class scala/MatchError
   378:	dup
   379:	iload_1
   380:	invokestatic	#19; //Method scala/runtime/BoxesRunTime.boxToInteger:(I)Ljava/lang/Integer;
   383:	invokevirtual	#25; //Method java/lang/Object.toString:()Ljava/lang/String;
   386:	invokespecial	#32; //Method scala/MatchError."<init>":(Ljava/lang/String;)V
   389:	athrow
   390:	iconst_1
   391:	ifeq	403
   394:	aload_0
   395:	invokeinterface	#65,  1; //InterfaceMethod scala/Product22._13:()Ljava/lang/Object;
   400:	goto	736
   403:	new	#31; //class scala/MatchError
   406:	dup
   407:	iload_1
   408:	invokestatic	#19; //Method scala/runtime/BoxesRunTime.boxToInteger:(I)Ljava/lang/Integer;
   411:	invokevirtual	#25; //Method java/lang/Object.toString:()Ljava/lang/String;
   414:	invokespecial	#32; //Method scala/MatchError."<init>":(Ljava/lang/String;)V
   417:	athrow
   418:	iconst_1
   419:	ifeq	431
   422:	aload_0
   423:	invokeinterface	#68,  1; //InterfaceMethod scala/Product22._12:()Ljava/lang/Object;
   428:	goto	736
   431:	new	#31; //class scala/MatchError
   434:	dup
   435:	iload_1
   436:	invokestatic	#19; //Method scala/runtime/BoxesRunTime.boxToInteger:(I)Ljava/lang/Integer;
   439:	invokevirtual	#25; //Method java/lang/Object.toString:()Ljava/lang/String;
   442:	invokespecial	#32; //Method scala/MatchError."<init>":(Ljava/lang/String;)V
   445:	athrow
   446:	iconst_1
   447:	ifeq	459
   450:	aload_0
   451:	invokeinterface	#71,  1; //InterfaceMethod scala/Product22._11:()Ljava/lang/Object;
   456:	goto	736
   459:	new	#31; //class scala/MatchError
   462:	dup
   463:	iload_1
   464:	invokestatic	#19; //Method scala/runtime/BoxesRunTime.boxToInteger:(I)Ljava/lang/Integer;
   467:	invokevirtual	#25; //Method java/lang/Object.toString:()Ljava/lang/String;
   470:	invokespecial	#32; //Method scala/MatchError."<init>":(Ljava/lang/String;)V
   473:	athrow
   474:	iconst_1
   475:	ifeq	487
   478:	aload_0
   479:	invokeinterface	#74,  1; //InterfaceMethod scala/Product22._10:()Ljava/lang/Object;
   484:	goto	736
   487:	new	#31; //class scala/MatchError
   490:	dup
   491:	iload_1
   492:	invokestatic	#19; //Method scala/runtime/BoxesRunTime.boxToInteger:(I)Ljava/lang/Integer;
   495:	invokevirtual	#25; //Method java/lang/Object.toString:()Ljava/lang/String;
   498:	invokespecial	#32; //Method scala/MatchError."<init>":(Ljava/lang/String;)V
   501:	athrow
   502:	iconst_1
   503:	ifeq	515
   506:	aload_0
   507:	invokeinterface	#77,  1; //InterfaceMethod scala/Product22._9:()Ljava/lang/Object;
   512:	goto	736
   515:	new	#31; //class scala/MatchError
   518:	dup
   519:	iload_1
   520:	invokestatic	#19; //Method scala/runtime/BoxesRunTime.boxToInteger:(I)Ljava/lang/Integer;
   523:	invokevirtual	#25; //Method java/lang/Object.toString:()Ljava/lang/String;
   526:	invokespecial	#32; //Method scala/MatchError."<init>":(Ljava/lang/String;)V
   529:	athrow
   530:	iconst_1
   531:	ifeq	543
   534:	aload_0
   535:	invokeinterface	#80,  1; //InterfaceMethod scala/Product22._8:()Ljava/lang/Object;
   540:	goto	736
   543:	new	#31; //class scala/MatchError
   546:	dup
   547:	iload_1
   548:	invokestatic	#19; //Method scala/runtime/BoxesRunTime.boxToInteger:(I)Ljava/lang/Integer;
   551:	invokevirtual	#25; //Method java/lang/Object.toString:()Ljava/lang/String;
   554:	invokespecial	#32; //Method scala/MatchError."<init>":(Ljava/lang/String;)V
   557:	athrow
   558:	iconst_1
   559:	ifeq	571
   562:	aload_0
   563:	invokeinterface	#83,  1; //InterfaceMethod scala/Product22._7:()Ljava/lang/Object;
   568:	goto	736
   571:	new	#31; //class scala/MatchError
   574:	dup
   575:	iload_1
   576:	invokestatic	#19; //Method scala/runtime/BoxesRunTime.boxToInteger:(I)Ljava/lang/Integer;
   579:	invokevirtual	#25; //Method java/lang/Object.toString:()Ljava/lang/String;
   582:	invokespecial	#32; //Method scala/MatchError."<init>":(Ljava/lang/String;)V
   585:	athrow
   586:	iconst_1
   587:	ifeq	599
   590:	aload_0
   591:	invokeinterface	#86,  1; //InterfaceMethod scala/Product22._6:()Ljava/lang/Object;
   596:	goto	736
   599:	new	#31; //class scala/MatchError
   602:	dup
   603:	iload_1
   604:	invokestatic	#19; //Method scala/runtime/BoxesRunTime.boxToInteger:(I)Ljava/lang/Integer;
   607:	invokevirtual	#25; //Method java/lang/Object.toString:()Ljava/lang/String;
   610:	invokespecial	#32; //Method scala/MatchError."<init>":(Ljava/lang/String;)V
   613:	athrow
   614:	iconst_1
   615:	ifeq	627
   618:	aload_0
   619:	invokeinterface	#89,  1; //InterfaceMethod scala/Product22._5:()Ljava/lang/Object;
   624:	goto	736
   627:	new	#31; //class scala/MatchError
   630:	dup
   631:	iload_1
   632:	invokestatic	#19; //Method scala/runtime/BoxesRunTime.boxToInteger:(I)Ljava/lang/Integer;
   635:	invokevirtual	#25; //Method java/lang/Object.toString:()Ljava/lang/String;
   638:	invokespecial	#32; //Method scala/MatchError."<init>":(Ljava/lang/String;)V
   641:	athrow
   642:	iconst_1
   643:	ifeq	655
   646:	aload_0
   647:	invokeinterface	#92,  1; //InterfaceMethod scala/Product22._4:()Ljava/lang/Object;
   652:	goto	736
   655:	new	#31; //class scala/MatchError
   658:	dup
   659:	iload_1
   660:	invokestatic	#19; //Method scala/runtime/BoxesRunTime.boxToInteger:(I)Ljava/lang/Integer;
   663:	invokevirtual	#25; //Method java/lang/Object.toString:()Ljava/lang/String;
   666:	invokespecial	#32; //Method scala/MatchError."<init>":(Ljava/lang/String;)V
   669:	athrow
   670:	iconst_1
   671:	ifeq	683
   674:	aload_0
   675:	invokeinterface	#95,  1; //InterfaceMethod scala/Product22._3:()Ljava/lang/Object;
   680:	goto	736
   683:	new	#31; //class scala/MatchError
   686:	dup
   687:	iload_1
   688:	invokestatic	#19; //Method scala/runtime/BoxesRunTime.boxToInteger:(I)Ljava/lang/Integer;
   691:	invokevirtual	#25; //Method java/lang/Object.toString:()Ljava/lang/String;
   694:	invokespecial	#32; //Method scala/MatchError."<init>":(Ljava/lang/String;)V
   697:	athrow
   698:	iconst_1
   699:	ifeq	711
   702:	aload_0
   703:	invokeinterface	#98,  1; //InterfaceMethod scala/Product22._2:()Ljava/lang/Object;
   708:	goto	736
   711:	new	#31; //class scala/MatchError
   714:	dup
   715:	iload_1
   716:	invokestatic	#19; //Method scala/runtime/BoxesRunTime.boxToInteger:(I)Ljava/lang/Integer;
   719:	invokevirtual	#25; //Method java/lang/Object.toString:()Ljava/lang/String;
   722:	invokespecial	#32; //Method scala/MatchError."<init>":(Ljava/lang/String;)V
   725:	athrow
   726:	iconst_1
   727:	ifeq	737
   730:	aload_0
   731:	invokeinterface	#101,  1; //InterfaceMethod scala/Product22._1:()Ljava/lang/Object;
   736:	areturn
   737:	new	#31; //class scala/MatchError
   740:	dup
   741:	iload_1
   742:	invokestatic	#19; //Method scala/runtime/BoxesRunTime.boxToInteger:(I)Ljava/lang/Integer;
   745:	invokevirtual	#25; //Method java/lang/Object.toString:()Ljava/lang/String;
   748:	invokespecial	#32; //Method scala/MatchError."<init>":(Ljava/lang/String;)V
   751:	athrow
  LineNumberTable: 
   line 41: 0
   line 21: 104
   line 64: 108
   line 41: 123
   line 21: 138
   line 63: 142
   line 41: 151
   line 21: 166
   line 62: 170
   line 41: 179
   line 21: 194
   line 61: 198
   line 41: 207
   line 21: 222
   line 60: 226
   line 41: 235
   line 21: 250
   line 59: 254
   line 41: 263
   line 21: 278
   line 58: 282
   line 41: 291
   line 21: 306
   line 57: 310
   line 41: 319
   line 21: 334
   line 56: 338
   line 41: 347
   line 21: 362
   line 55: 366
   line 41: 375
   line 21: 390
   line 54: 394
   line 41: 403
   line 21: 418
   line 53: 422
   line 41: 431
   line 21: 446
   line 52: 450
   line 41: 459
   line 21: 474
   line 51: 478
   line 41: 487
   line 21: 502
   line 50: 506
   line 41: 515
   line 21: 530
   line 49: 534
   line 41: 543
   line 21: 558
   line 48: 562
   line 41: 571
   line 21: 586
   line 47: 590
   line 41: 599
   line 21: 614
   line 46: 618
   line 41: 627
   line 21: 642
   line 45: 646
   line 41: 655
   line 21: 670
   line 44: 674
   line 41: 683
   line 21: 698
   line 43: 702
   line 41: 711
   line 21: 726
   line 42: 730
   line 41: 736

  LocalVariableTable: 
   Start  Length  Slot  Name   Signature
   0      752      0    $this       Lscala/Product22;
   0      752      1    n       I

  Exceptions: 
   throws java.lang.IndexOutOfBoundsException
public static int productArity(scala.Product22);
  Code:
   Stack=1, Locals=1, Args_size=1
   0:	ldc	#107; //int 22
   2:	ireturn
  LineNumberTable: 
   line 30: 0

  LocalVariableTable: 
   Start  Length  Slot  Name   Signature
   0      3      0    $this       Lscala/Product22;


}

