Compiled from "RandomAccessSeq.scala"
public final class scala.RandomAccessSeq$$anon$13 extends java.lang.Object implements scala.BufferedIterator$Advanced
  InnerClass: 
   public final $anon$13=class scala/RandomAccessSeq$$anon$13 of class scala/RandomAccessSeq
   public abstract Advanced=class scala/BufferedIterator$Advanced of class scala/BufferedIterator
   public final $anon$12=class scala/RandomAccessSeq$$anon$13$$anon$12 of class scala/RandomAccessSeq$$anon$13
  Scala: length = 0x
   
  Signature: length = 0x2
   00 5F 
  SourceFile: "RandomAccessSeq.scala"
  minor version: 0
  major version: 49
  Constant pool:
class	java/lang/NullPointerException
class	java/lang/Object
class	java/util/NoSuchElementException
class	scala/BufferedIterator
class	scala/BufferedIterator$Advanced
class	scala/BufferedIterator$Advanced$class
class	scala/BufferedIterator$class
class	scala/Function1
class	scala/Iterator$class
class	scala/RandomAccessSeq
class	scala/RandomAccessSeq$$anon$13
class	scala/RandomAccessSeq$$anon$13$$anon$12
class	scala/Seq
class	scala/runtime/BoxesRunTime
class	scala/runtime/ScalaRunTime$
Field	scala/RandomAccessSeq$$anon$13.$outer:Lscala/RandomAccessSeq;
Field	scala/RandomAccessSeq$$anon$13.idx:I
Field	scala/runtime/ScalaRunTime$.MODULE$:Lscala/runtime/ScalaRunTime$;
Method	java/lang/NullPointerException."<init>":()V
Method	java/lang/Object."<init>":()V
Method	java/util/NoSuchElementException."<init>":()V
Method	scala/BufferedIterator$Advanced$class.$init$:(Lscala/BufferedIterator$Advanced;)V
Method	scala/BufferedIterator$Advanced$class.toString:(Lscala/BufferedIterator$Advanced;)Ljava/lang/String;
Method	scala/BufferedIterator$class.$init$:(Lscala/BufferedIterator;)V
Method	scala/Iterator$class.$init$:(Lscala/Iterator;)V
Method	scala/Iterator$class.forall:(Lscala/Iterator;Lscala/Function1;)Z
Method	scala/Iterator$class.foreach:(Lscala/Iterator;Lscala/Function1;)V
Method	scala/Iterator$class.zip:(Lscala/Iterator;Lscala/Iterator;)Ljava/lang/Object;
Method	scala/RandomAccessSeq$$anon$13.hasNext:()Z
Method	scala/RandomAccessSeq$$anon$13.idx:()I
Method	scala/RandomAccessSeq$$anon$13.idx_$eq:(I)V
Method	scala/RandomAccessSeq$$anon$13.peekList:(I)Ljava/lang/Object;
Method	scala/RandomAccessSeq$$anon$13$$anon$12."<init>":(Lscala/RandomAccessSeq$$anon$13;)V
Method	scala/runtime/BoxesRunTime.boxToInteger:(I)Ljava/lang/Integer;
Method	scala/runtime/ScalaRunTime$.boxArray:(Ljava/lang/Object;)Lscala/runtime/BoxedArray;
InterfaceMethod	scala/Function1.apply:(Ljava/lang/Object;)Ljava/lang/Object;
InterfaceMethod	scala/Seq.length:()I
NameAndType	$init$:(Lscala/BufferedIterator$Advanced;)V
NameAndType	$init$:(Lscala/BufferedIterator;)V
NameAndType	$init$:(Lscala/Iterator;)V
NameAndType	$outer:Lscala/RandomAccessSeq;
NameAndType	"<init>":()V
NameAndType	"<init>":(Lscala/RandomAccessSeq$$anon$13;)V
NameAndType	MODULE$:Lscala/runtime/ScalaRunTime$;
NameAndType	apply:(Ljava/lang/Object;)Ljava/lang/Object;
NameAndType	boxArray:(Ljava/lang/Object;)Lscala/runtime/BoxedArray;
NameAndType	boxToInteger:(I)Ljava/lang/Integer;
NameAndType	forall:(Lscala/Iterator;Lscala/Function1;)Z
NameAndType	foreach:(Lscala/Iterator;Lscala/Function1;)V
NameAndType	hasNext:()Z
NameAndType	idx:()I
NameAndType	idx:I
NameAndType	idx_$eq:(I)V
NameAndType	length:()I
NameAndType	peekList:(I)Ljava/lang/Object;
NameAndType	toString:(Lscala/BufferedIterator$Advanced;)Ljava/lang/String;
NameAndType	zip:(Lscala/Iterator;Lscala/Iterator;)Ljava/lang/Object;
Asciz	$anon$12;
Asciz	$anon$13;
Asciz	$init$;
Asciz	$outer;
Asciz	()I;
Asciz	()Ljava/lang/Object;;
Asciz	()Ljava/lang/String;;
Asciz	()Lscala/RandomAccessSeq;;
Asciz	()TA;;
Asciz	()V;
Asciz	()Z;
Asciz	(I)Ljava/lang/Integer;;
Asciz	(I)Ljava/lang/Object;;
Asciz	(I)Lscala/Seq;;
Asciz	(I)V;
Asciz	(Ljava/lang/Object;)Ljava/lang/Object;;
Asciz	(Ljava/lang/Object;)Lscala/runtime/BoxedArray;;
Asciz	(Lscala/BufferedIterator$Advanced;)Ljava/lang/String;;
Asciz	(Lscala/BufferedIterator$Advanced;)V;
Asciz	(Lscala/BufferedIterator;)V;
Asciz	(Lscala/Function1;)V;
Asciz	(Lscala/Function1;)Z;
Asciz	(Lscala/Iterator;)Ljava/lang/Object;;
Asciz	(Lscala/Iterator;)V;
Asciz	(Lscala/Iterator;Lscala/Function1;)V;
Asciz	(Lscala/Iterator;Lscala/Function1;)Z;
Asciz	(Lscala/Iterator;Lscala/Iterator;)Ljava/lang/Object;;
Asciz	(Lscala/RandomAccessSeq$$anon$13;)V;
Asciz	(Lscala/RandomAccessSeq;)V;
Asciz	(Lscala/RandomAccessSeq<TA;>;)V;
Asciz	<init>;
Asciz	Advanced;
Asciz	Code;
Asciz	I;
Asciz	InnerClasses;
Asciz	LineNumberTable;
Asciz	Ljava/lang/Object;;
Asciz	Ljava/lang/Object;Lscala/BufferedIterator$Advanced<TA;>;;
Asciz	LocalVariableTable;
Asciz	Lscala/Function1;;
Asciz	Lscala/Iterator;;
Asciz	Lscala/RandomAccessSeq$$anon$13;;
Asciz	Lscala/RandomAccessSeq;;
Asciz	Lscala/runtime/ScalaRunTime$;;
Asciz	MODULE$;
Asciz	RandomAccessSeq.scala;
Asciz	Scala;
Asciz	Signature;
Asciz	SourceFile;
Asciz	apply;
Asciz	boxArray;
Asciz	boxToInteger;
Asciz	forall;
Asciz	foreach;
Asciz	hasNext;
Asciz	idx;
Asciz	idx_$eq;
Asciz	java/lang/NullPointerException;
Asciz	java/lang/Object;
Asciz	java/util/NoSuchElementException;
Asciz	length;
Asciz	next;
Asciz	peekList;
Asciz	ret;
Asciz	scala$RandomAccessSeq$$anon$$$outer;
Asciz	scala/BufferedIterator;
Asciz	scala/BufferedIterator$Advanced;
Asciz	scala/BufferedIterator$Advanced$class;
Asciz	scala/BufferedIterator$class;
Asciz	scala/Function1;
Asciz	scala/Iterator$class;
Asciz	scala/RandomAccessSeq;
Asciz	scala/RandomAccessSeq$$anon$13;
Asciz	scala/RandomAccessSeq$$anon$13$$anon$12;
Asciz	scala/Seq;
Asciz	scala/runtime/BoxesRunTime;
Asciz	scala/runtime/ScalaRunTime$;
Asciz	sz;
Asciz	this;
Asciz	toString;
Asciz	x$1;
Asciz	zip;

{
private final scala.RandomAccessSeq $outer;
  Signature: Lscala/RandomAccessSeq;

private int idx;
  Signature: I

public scala.RandomAccessSeq$$anon$13(scala.RandomAccessSeq);
  Signature: (Lscala/RandomAccessSeq;)V
  Code:
   Stack=2, Locals=2, Args_size=2
	aload_1
	ifnonnull	l1 // aload_0
	new	class java/lang/NullPointerException
	dup
	invokespecial	Method java/lang/NullPointerException."<init>":()V
	athrow
l1	aload_0
	aload_1
	putfield	Field $outer:Lscala/RandomAccessSeq;
	aload_0
	iconst_0
	putfield	Field idx:I
	aload_0
	invokespecial	Method java/lang/Object."<init>":()V
	aload_0
	invokestatic	Method scala/Iterator$class.$init$:(Lscala/Iterator;)V
	aload_0
	invokestatic	Method scala/BufferedIterator$class.$init$:(Lscala/BufferedIterator;)V
	aload_0
	invokestatic	Method scala/BufferedIterator$Advanced$class.$init$:(Lscala/BufferedIterator$Advanced;)V
	return
  Labels:
   	l1 = 12 // aload_0
  LocalVariableTable: 
   Start  Length  Slot  Name   Signature
   0      39      0    this       Lscala/RandomAccessSeq$$anon$13;
   0      39      1    $outer       Lscala/RandomAccessSeq;

  Signature: length = 0x2
   00 57 

public scala.Seq peekList(int);
  Signature: (I)Lscala/Seq;
  Code:
   Stack=2, Locals=3, Args_size=2
	aload_0
	iload_1
	invokevirtual	Method peekList:(I)Ljava/lang/Object;
	astore_2
	aload_2
	instanceof	class scala/Seq
	ifeq	l1 // getstatic
	aload_2
	goto	l2 // checkcast
l1	getstatic	Field scala/runtime/ScalaRunTime$.MODULE$:Lscala/runtime/ScalaRunTime$;
	aload_2
	invokevirtual	Method scala/runtime/ScalaRunTime$.boxArray:(Ljava/lang/Object;)Lscala/runtime/BoxedArray;
l2	checkcast	class scala/Seq
	areturn
  Labels:
   	l1 = 17 // getstatic
   	l2 = 24 // checkcast
  LocalVariableTable: 
   Start  Length  Slot  Name   Signature
   0      28      0    this       Lscala/RandomAccessSeq$$anon$13;
   0      28      1    x$1       I


public scala.RandomAccessSeq scala$RandomAccessSeq$$anon$$$outer();
  Signature: ()Lscala/RandomAccessSeq;
  Code:
   Stack=1, Locals=1, Args_size=1
	aload_0
	getfield	Field $outer:Lscala/RandomAccessSeq;
	areturn
  Labels:

public java.lang.Object next();
  Signature: ()Ljava/lang/Object;
  Code:
   Stack=3, Locals=2, Args_size=1
	aload_0
	invokevirtual	Method hasNext:()Z
	ifeq	l1 // new
	aload_0
	getfield	Field $outer:Lscala/RandomAccessSeq;
	aload_0
	invokevirtual	Method idx:()I
	invokestatic	Method scala/runtime/BoxesRunTime.boxToInteger:(I)Ljava/lang/Integer;
	invokeinterface	InterfaceMethod scala/Function1.apply:(Ljava/lang/Object;)Ljava/lang/Object;
	astore_1
	aload_0
	aload_0
	invokevirtual	Method idx:()I
	iconst_1
	iadd
	invokevirtual	Method idx_$eq:(I)V
	aload_1
	areturn
l1	new	class java/util/NoSuchElementException
	dup
	invokespecial	Method java/util/NoSuchElementException."<init>":()V
	athrow
  Labels:
   	l1 = 36 // new
  LocalVariableTable: 
   Start  Length  Slot  Name   Signature
   0      44      0    this       Lscala/RandomAccessSeq$$anon$13;
   7      28      1    ret       Ljava/lang/Object;

  Signature: length = 0x2
   00 42 

public boolean hasNext();
  Signature: ()Z
  Code:
   Stack=2, Locals=1, Args_size=1
	aload_0
	invokevirtual	Method idx:()I
	aload_0
	getfield	Field $outer:Lscala/RandomAccessSeq;
	invokeinterface	InterfaceMethod scala/Seq.length:()I
	if_icmpge	l1 // iconst_0
	iconst_1
	goto	l2 // ireturn
l1	iconst_0
l2	ireturn
  Labels:
   	l1 = 20 // iconst_0
   	l2 = 21 // ireturn

public java.lang.Object peekList(int);
  Signature: (I)Ljava/lang/Object;
  Code:
   Stack=3, Locals=2, Args_size=2
	new	class scala/RandomAccessSeq$$anon$13$$anon$12
	dup
	aload_0
	invokespecial	Method scala/RandomAccessSeq$$anon$13$$anon$12."<init>":(Lscala/RandomAccessSeq$$anon$13;)V
	areturn
  Labels:
  LocalVariableTable: 
   Start  Length  Slot  Name   Signature
   0      9      0    this       Lscala/RandomAccessSeq$$anon$13;
   0      9      1    sz       I


public void idx_$eq(int);
  Signature: (I)V
  Code:
   Stack=2, Locals=2, Args_size=2
	aload_0
	iload_1
	putfield	Field idx:I
	return
  Labels:
  LocalVariableTable: 
   Start  Length  Slot  Name   Signature
   0      6      0    this       Lscala/RandomAccessSeq$$anon$13;
   0      6      1    x$1       I


public int idx();
  Signature: ()I
  Code:
   Stack=1, Locals=1, Args_size=1
	aload_0
	getfield	Field idx:I
	ireturn
  Labels:

public boolean forall(scala.Function1);
  Signature: (Lscala/Function1;)Z
  Code:
   Stack=2, Locals=2, Args_size=2
	aload_0
	aload_1
	invokestatic	Method scala/Iterator$class.forall:(Lscala/Iterator;Lscala/Function1;)Z
	ireturn
  Labels:
  LocalVariableTable: 
   Start  Length  Slot  Name   Signature
   0      6      0    this       Lscala/RandomAccessSeq$$anon$13;
   0      6      1    x$1       Lscala/Function1;


public void foreach(scala.Function1);
  Signature: (Lscala/Function1;)V
  Code:
   Stack=2, Locals=2, Args_size=2
	aload_0
	aload_1
	invokestatic	Method scala/Iterator$class.foreach:(Lscala/Iterator;Lscala/Function1;)V
	return
  Labels:
  LocalVariableTable: 
   Start  Length  Slot  Name   Signature
   0      6      0    this       Lscala/RandomAccessSeq$$anon$13;
   0      6      1    x$1       Lscala/Function1;


public java.lang.Object zip(scala.Iterator);
  Signature: (Lscala/Iterator;)Ljava/lang/Object;
  Code:
   Stack=2, Locals=2, Args_size=2
	aload_0
	aload_1
	invokestatic	Method scala/Iterator$class.zip:(Lscala/Iterator;Lscala/Iterator;)Ljava/lang/Object;
	areturn
  Labels:
  LocalVariableTable: 
   Start  Length  Slot  Name   Signature
   0      6      0    this       Lscala/RandomAccessSeq$$anon$13;
   0      6      1    x$1       Lscala/Iterator;


public java.lang.String toString();
  Signature: ()Ljava/lang/String;
  Code:
   Stack=1, Locals=1, Args_size=1
	aload_0
	invokestatic	Method scala/BufferedIterator$Advanced$class.toString:(Lscala/BufferedIterator$Advanced;)Ljava/lang/String;
	areturn
  Labels:

}

