Compiled from "RandomAccessSeq.scala"
public final class scala.RandomAccessSeq$$anon$13$$anon$12 extends java.lang.Object implements scala.RandomAccessSeq
  InnerClass: 
   public final $anon$13=class scala/RandomAccessSeq$$anon$13 of class scala/RandomAccessSeq
   public final $anon$12=class scala/RandomAccessSeq$$anon$13$$anon$12 of class scala/RandomAccessSeq$$anon$13
  Scala: length = 0x
   
  Signature: length = 0x2
   00 5F 
  SourceFile: "RandomAccessSeq.scala"
  minor version: 0
  major version: 49
  Constant pool:
class	java/lang/NullPointerException
class	java/lang/Object
class	scala/Collection$class
class	scala/Function1
class	scala/Function1$class
class	scala/Iterable
class	scala/Iterable$class
class	scala/PartialFunction$class
class	scala/RandomAccessSeq
class	scala/RandomAccessSeq$$anon$13
class	scala/RandomAccessSeq$$anon$13$$anon$12
class	scala/RandomAccessSeq$class
class	scala/Seq
class	scala/Seq$class
class	scala/runtime/BoxesRunTime
Field	scala/RandomAccessSeq$$anon$13$$anon$12.$outer:Lscala/RandomAccessSeq$$anon$13;
Method	java/lang/NullPointerException."<init>":()V
Method	java/lang/Object."<init>":()V
Method	scala/Collection$class.$init$:(Lscala/Collection;)V
Method	scala/Collection$class.stringPrefix:(Lscala/Collection;)Ljava/lang/String;
Method	scala/Collection$class.toString:(Lscala/Collection;)Ljava/lang/String;
Method	scala/Function1$class.$init$:(Lscala/Function1;)V
Method	scala/Iterable$class.$init$:(Lscala/Iterable;)V
Method	scala/Iterable$class.addString:(Lscala/Iterable;Lscala/StringBuilder;Ljava/lang/String;Ljava/lang/String;Ljava/lang/String;)Lscala/StringBuilder;
Method	scala/Iterable$class.mkString:(Lscala/Iterable;Ljava/lang/String;Ljava/lang/String;Ljava/lang/String;)Ljava/lang/String;
Method	scala/PartialFunction$class.$init$:(Lscala/PartialFunction;)V
Method	scala/RandomAccessSeq$$anon$13.idx:()I
Method	scala/RandomAccessSeq$$anon$13.scala$RandomAccessSeq$$anon$$$outer:()Lscala/RandomAccessSeq;
Method	scala/RandomAccessSeq$$anon$13$$anon$12.apply:(I)Ljava/lang/Object;
Method	scala/RandomAccessSeq$class.$init$:(Lscala/RandomAccessSeq;)V
Method	scala/RandomAccessSeq$class.elements:(Lscala/RandomAccessSeq;)Lscala/Iterator;
Method	scala/Seq$class.$init$:(Lscala/Seq;)V
Method	scala/Seq$class.isEmpty:(Lscala/Seq;)Z
Method	scala/runtime/BoxesRunTime.boxToInteger:(I)Ljava/lang/Integer;
Method	scala/runtime/BoxesRunTime.unboxToInt:(Ljava/lang/Object;)I
InterfaceMethod	scala/Function1.apply:(Ljava/lang/Object;)Ljava/lang/Object;
InterfaceMethod	scala/Seq.length:()I
NameAndType	$init$:(Lscala/Collection;)V
NameAndType	$init$:(Lscala/Function1;)V
NameAndType	$init$:(Lscala/Iterable;)V
NameAndType	$init$:(Lscala/PartialFunction;)V
NameAndType	$init$:(Lscala/RandomAccessSeq;)V
NameAndType	$init$:(Lscala/Seq;)V
NameAndType	$outer:Lscala/RandomAccessSeq$$anon$13;
NameAndType	"<init>":()V
NameAndType	addString:(Lscala/Iterable;Lscala/StringBuilder;Ljava/lang/String;Ljava/lang/String;Ljava/lang/String;)Lscala/StringBuilder;
NameAndType	apply:(I)Ljava/lang/Object;
NameAndType	apply:(Ljava/lang/Object;)Ljava/lang/Object;
NameAndType	boxToInteger:(I)Ljava/lang/Integer;
NameAndType	elements:(Lscala/RandomAccessSeq;)Lscala/Iterator;
NameAndType	idx:()I
NameAndType	isEmpty:(Lscala/Seq;)Z
NameAndType	length:()I
NameAndType	mkString:(Lscala/Iterable;Ljava/lang/String;Ljava/lang/String;Ljava/lang/String;)Ljava/lang/String;
NameAndType	scala$RandomAccessSeq$$anon$$$outer:()Lscala/RandomAccessSeq;
NameAndType	stringPrefix:(Lscala/Collection;)Ljava/lang/String;
NameAndType	toString:(Lscala/Collection;)Ljava/lang/String;
NameAndType	unboxToInt:(Ljava/lang/Object;)I
Asciz	$anon$12;
Asciz	$anon$13;
Asciz	$init$;
Asciz	$outer;
Asciz	()I;
Asciz	()Ljava/lang/String;;
Asciz	()Lscala/Iterator;;
Asciz	()Lscala/RandomAccessSeq;;
Asciz	()V;
Asciz	()Z;
Asciz	(I)Ljava/lang/Integer;;
Asciz	(I)Ljava/lang/Object;;
Asciz	(I)TA;;
Asciz	(Ljava/lang/Object;)I;
Asciz	(Ljava/lang/Object;)Ljava/lang/Object;;
Asciz	(Ljava/lang/String;Ljava/lang/String;Ljava/lang/String;)Ljava/lang/String;;
Asciz	(Lscala/Collection;)Ljava/lang/String;;
Asciz	(Lscala/Collection;)V;
Asciz	(Lscala/Function1;)V;
Asciz	(Lscala/Iterable;)V;
Asciz	(Lscala/Iterable;Ljava/lang/String;Ljava/lang/String;Ljava/lang/String;)Ljava/lang/String;;
Asciz	(Lscala/Iterable;Lscala/StringBuilder;Ljava/lang/String;Ljava/lang/String;Ljava/lang/String;)Lscala/StringBuilder;;
Asciz	(Lscala/PartialFunction;)V;
Asciz	(Lscala/RandomAccessSeq$$anon$13;)V;
Asciz	(Lscala/RandomAccessSeq;)Lscala/Iterator;;
Asciz	(Lscala/RandomAccessSeq;)V;
Asciz	(Lscala/RandomAccessSeq<TA;>.$anon$13;)V;
Asciz	(Lscala/Seq;)V;
Asciz	(Lscala/Seq;)Z;
Asciz	(Lscala/StringBuilder;Ljava/lang/String;Ljava/lang/String;Ljava/lang/String;)Lscala/StringBuilder;;
Asciz	<init>;
Asciz	Code;
Asciz	I;
Asciz	InnerClasses;
Asciz	LineNumberTable;
Asciz	Ljava/lang/Object;;
Asciz	Ljava/lang/Object;Lscala/RandomAccessSeq<TA;>;;
Asciz	Ljava/lang/String;;
Asciz	LocalVariableTable;
Asciz	Lscala/RandomAccessSeq$$anon$13$$anon$12;;
Asciz	Lscala/RandomAccessSeq$$anon$13;;
Asciz	Lscala/StringBuilder;;
Asciz	RandomAccessSeq.scala;
Asciz	Scala;
Asciz	Signature;
Asciz	SourceFile;
Asciz	addString;
Asciz	apply;
Asciz	boxToInteger;
Asciz	elements;
Asciz	idx;
Asciz	isEmpty;
Asciz	java/lang/NullPointerException;
Asciz	java/lang/Object;
Asciz	jdx;
Asciz	length;
Asciz	mkString;
Asciz	scala$RandomAccessSeq$$anon$$$outer;
Asciz	scala/Collection$class;
Asciz	scala/Function1;
Asciz	scala/Function1$class;
Asciz	scala/Iterable;
Asciz	scala/Iterable$class;
Asciz	scala/PartialFunction$class;
Asciz	scala/RandomAccessSeq;
Asciz	scala/RandomAccessSeq$$anon$13;
Asciz	scala/RandomAccessSeq$$anon$13$$anon$12;
Asciz	scala/RandomAccessSeq$class;
Asciz	scala/Seq;
Asciz	scala/Seq$class;
Asciz	scala/runtime/BoxesRunTime;
Asciz	stringPrefix;
Asciz	this;
Asciz	toString;
Asciz	unboxToInt;
Asciz	x$1;
Asciz	x$2;
Asciz	x$3;
Asciz	x$4;

{
private final scala.RandomAccessSeq$$anon$13 $outer;
  Signature: Lscala/RandomAccessSeq$$anon$13;

public scala.RandomAccessSeq$$anon$13$$anon$12(scala.RandomAccessSeq$$anon$13);
  Signature: (Lscala/RandomAccessSeq$$anon$13;)V
  Code:
   Stack=2, Locals=2, Args_size=2
	aload_1
	ifnonnull	l1 // aload_0
	new	class java/lang/NullPointerException
	dup
	invokespecial	Method java/lang/NullPointerException."<init>":()V
	athrow
l1	aload_0
	aload_1
	putfield	Field $outer:Lscala/RandomAccessSeq$$anon$13;
	aload_0
	invokespecial	Method java/lang/Object."<init>":()V
	aload_0
	invokestatic	Method scala/Function1$class.$init$:(Lscala/Function1;)V
	aload_0
	invokestatic	Method scala/PartialFunction$class.$init$:(Lscala/PartialFunction;)V
	aload_0
	invokestatic	Method scala/Iterable$class.$init$:(Lscala/Iterable;)V
	aload_0
	invokestatic	Method scala/Collection$class.$init$:(Lscala/Collection;)V
	aload_0
	invokestatic	Method scala/Seq$class.$init$:(Lscala/Seq;)V
	aload_0
	invokestatic	Method scala/RandomAccessSeq$class.$init$:(Lscala/RandomAccessSeq;)V
	return
  Labels:
   	l1 = 12 // aload_0
  LocalVariableTable: 
   Start  Length  Slot  Name   Signature
   0      46      0    this       Lscala/RandomAccessSeq$$anon$13$$anon$12;
   0      46      1    $outer       Lscala/RandomAccessSeq$$anon$13;

  Signature: length = 0x2
   00 55 

public java.lang.Object apply(java.lang.Object);
  Signature: (Ljava/lang/Object;)Ljava/lang/Object;
  Code:
   Stack=2, Locals=2, Args_size=2
	aload_0
	aload_1
	invokestatic	Method scala/runtime/BoxesRunTime.unboxToInt:(Ljava/lang/Object;)I
	invokevirtual	Method apply:(I)Ljava/lang/Object;
	areturn
  Labels:
  LocalVariableTable: 
   Start  Length  Slot  Name   Signature
   0      9      0    this       Lscala/RandomAccessSeq$$anon$13$$anon$12;
   0      9      1    x$1       Ljava/lang/Object;


public java.lang.Object apply(int);
  Signature: (I)Ljava/lang/Object;
  Code:
   Stack=3, Locals=2, Args_size=2
	aload_0
	getfield	Field $outer:Lscala/RandomAccessSeq$$anon$13;
	invokevirtual	Method scala/RandomAccessSeq$$anon$13.scala$RandomAccessSeq$$anon$$$outer:()Lscala/RandomAccessSeq;
	iload_1
	aload_0
	getfield	Field $outer:Lscala/RandomAccessSeq$$anon$13;
	invokevirtual	Method scala/RandomAccessSeq$$anon$13.idx:()I
	iadd
	invokestatic	Method scala/runtime/BoxesRunTime.boxToInteger:(I)Ljava/lang/Integer;
	invokeinterface	InterfaceMethod scala/Function1.apply:(Ljava/lang/Object;)Ljava/lang/Object;
	areturn
  Labels:
  LocalVariableTable: 
   Start  Length  Slot  Name   Signature
   0      25      0    this       Lscala/RandomAccessSeq$$anon$13$$anon$12;
   0      25      1    jdx       I

  Signature: length = 0x2
   00 47 

public int length();
  Signature: ()I
  Code:
   Stack=2, Locals=1, Args_size=1
	aload_0
	getfield	Field $outer:Lscala/RandomAccessSeq$$anon$13;
	invokevirtual	Method scala/RandomAccessSeq$$anon$13.scala$RandomAccessSeq$$anon$$$outer:()Lscala/RandomAccessSeq;
	invokeinterface	InterfaceMethod scala/Seq.length:()I
	aload_0
	getfield	Field $outer:Lscala/RandomAccessSeq$$anon$13;
	invokevirtual	Method scala/RandomAccessSeq$$anon$13.idx:()I
	isub
	ireturn
  Labels:

public scala.StringBuilder addString(scala.StringBuilder, java.lang.String, java.lang.String, java.lang.String);
  Signature: (Lscala/StringBuilder;Ljava/lang/String;Ljava/lang/String;Ljava/lang/String;)Lscala/StringBuilder;
  Code:
   Stack=5, Locals=5, Args_size=5
	aload_0
	aload_1
	aload_2
	aload_3
	aload	4
	invokestatic	Method scala/Iterable$class.addString:(Lscala/Iterable;Lscala/StringBuilder;Ljava/lang/String;Ljava/lang/String;Ljava/lang/String;)Lscala/StringBuilder;
	areturn
  Labels:
  LocalVariableTable: 
   Start  Length  Slot  Name   Signature
   0      10      0    this       Lscala/RandomAccessSeq$$anon$13$$anon$12;
   0      10      1    x$1       Lscala/StringBuilder;
   0      10      2    x$2       Ljava/lang/String;
   0      10      3    x$3       Ljava/lang/String;
   0      10      4    x$4       Ljava/lang/String;


public java.lang.String mkString(java.lang.String, java.lang.String, java.lang.String);
  Signature: (Ljava/lang/String;Ljava/lang/String;Ljava/lang/String;)Ljava/lang/String;
  Code:
   Stack=4, Locals=4, Args_size=4
	aload_0
	aload_1
	aload_2
	aload_3
	invokestatic	Method scala/Iterable$class.mkString:(Lscala/Iterable;Ljava/lang/String;Ljava/lang/String;Ljava/lang/String;)Ljava/lang/String;
	areturn
  Labels:
  LocalVariableTable: 
   Start  Length  Slot  Name   Signature
   0      8      0    this       Lscala/RandomAccessSeq$$anon$13$$anon$12;
   0      8      1    x$1       Ljava/lang/String;
   0      8      2    x$2       Ljava/lang/String;
   0      8      3    x$3       Ljava/lang/String;


public java.lang.String stringPrefix();
  Signature: ()Ljava/lang/String;
  Code:
   Stack=1, Locals=1, Args_size=1
	aload_0
	invokestatic	Method scala/Collection$class.stringPrefix:(Lscala/Collection;)Ljava/lang/String;
	areturn
  Labels:

public java.lang.String toString();
  Signature: ()Ljava/lang/String;
  Code:
   Stack=1, Locals=1, Args_size=1
	aload_0
	invokestatic	Method scala/Collection$class.toString:(Lscala/Collection;)Ljava/lang/String;
	areturn
  Labels:

public boolean isEmpty();
  Signature: ()Z
  Code:
   Stack=1, Locals=1, Args_size=1
	aload_0
	invokestatic	Method scala/Seq$class.isEmpty:(Lscala/Seq;)Z
	ireturn
  Labels:

public scala.Iterator elements();
  Signature: ()Lscala/Iterator;
  Code:
   Stack=1, Locals=1, Args_size=1
	aload_0
	invokestatic	Method scala/RandomAccessSeq$class.elements:(Lscala/RandomAccessSeq;)Lscala/Iterator;
	areturn
  Labels:

}

