Compiled from "Range.scala"
public abstract class scala.RangeToString$class extends java.lang.Object
  SourceFile: "Range.scala"
  Scala: length = 0x
   
  minor version: 0
  major version: 49
  Constant pool:
const #1 = Asciz	SourceFile;
const #2 = Asciz	Range.scala;
const #3 = Asciz	$init$;
const #4 = Asciz	(Lscala/RangeToString;)V;
const #5 = Asciz	Code;
const #6 = Asciz	LineNumberTable;
const #7 = Asciz	$this;
const #8 = Asciz	Lscala/RangeToString;;
const #9 = Asciz	LocalVariableTable;
const #10 = Asciz	toString;
const #11 = Asciz	(Lscala/RangeToString;)Ljava/lang/String;;
const #12 = int	512;
const #13 = Asciz	scala/collection/generic/TraversableViewTemplate;
const #14 = class	#13;	//  scala/collection/generic/TraversableViewTemplate
const #15 = Asciz	take;
const #16 = Asciz	(I)Lscala/collection/generic/TraversableView;;
const #17 = NameAndType	#15:#16;//  take:(I)Lscala/collection/generic/TraversableView;
const #18 = InterfaceMethod	#14.#17;	//  scala/collection/generic/TraversableViewTemplate.take:(I)Lscala/collection/generic/TraversableView;
const #19 = Asciz	, ;
const #20 = String	#19;	//  , 
const #21 = Asciz	scala/collection/generic/TraversableTemplate;
const #22 = class	#21;	//  scala/collection/generic/TraversableTemplate
const #23 = Asciz	mkString;
const #24 = Asciz	(Ljava/lang/String;)Ljava/lang/String;;
const #25 = NameAndType	#23:#24;//  mkString:(Ljava/lang/String;)Ljava/lang/String;
const #26 = InterfaceMethod	#22.#25;	//  scala/collection/generic/TraversableTemplate.mkString:(Ljava/lang/String;)Ljava/lang/String;
const #27 = Asciz	scala/collection/generic/SequenceTemplate;
const #28 = class	#27;	//  scala/collection/generic/SequenceTemplate
const #29 = Asciz	length;
const #30 = Asciz	()I;
const #31 = NameAndType	#29:#30;//  length:()I
const #32 = InterfaceMethod	#28.#31;	//  scala/collection/generic/SequenceTemplate.length:()I
const #33 = Asciz	\)$;
const #34 = String	#33;	//  \)$
const #35 = Asciz	, ...);
const #36 = String	#35;	//  , ...)
const #37 = Asciz	java/lang/String;
const #38 = class	#37;	//  java/lang/String
const #39 = Asciz	replaceAll;
const #40 = Asciz	(Ljava/lang/String;Ljava/lang/String;)Ljava/lang/String;;
const #41 = NameAndType	#39:#40;//  replaceAll:(Ljava/lang/String;Ljava/lang/String;)Ljava/lang/String;
const #42 = Method	#38.#41;	//  java/lang/String.replaceAll:(Ljava/lang/String;Ljava/lang/String;)Ljava/lang/String;
const #43 = Asciz	MAX_PRINT;
const #44 = Asciz	I;
const #45 = Asciz	str;
const #46 = Asciz	Ljava/lang/String;;
const #47 = Asciz	Scala;
const #48 = Asciz	scala/RangeToString$class;
const #49 = class	#48;	//  scala/RangeToString$class
const #50 = Asciz	java/lang/Object;
const #51 = class	#50;	//  java/lang/Object

{
public static void $init$(scala.RangeToString);
  Code:
   Stack=0, Locals=1, Args_size=1
   0:	return
  LineNumberTable: 
   line 132: 0

  LocalVariableTable: 
   Start  Length  Slot  Name   Signature
   0      1      0    $this       Lscala/RangeToString;


public static java.lang.String toString(scala.RangeToString);
  Code:
   Stack=3, Locals=3, Args_size=1
   0:	ldc	#12; //int 512
   2:	istore_1
   3:	aload_0
   4:	iload_1
   5:	invokeinterface	#18,  2; //InterfaceMethod scala/collection/generic/TraversableViewTemplate.take:(I)Lscala/collection/generic/TraversableView;
   10:	ldc	#20; //String , 
   12:	invokeinterface	#26,  2; //InterfaceMethod scala/collection/generic/TraversableTemplate.mkString:(Ljava/lang/String;)Ljava/lang/String;
   17:	astore_2
   18:	aload_0
   19:	invokeinterface	#32,  1; //InterfaceMethod scala/collection/generic/SequenceTemplate.length:()I
   24:	iload_1
   25:	if_icmple	39
   28:	aload_2
   29:	ldc	#34; //String \)$
   31:	ldc	#36; //String , ...)
   33:	invokevirtual	#42; //Method java/lang/String.replaceAll:(Ljava/lang/String;Ljava/lang/String;)Ljava/lang/String;
   36:	goto	40
   39:	aload_2
   40:	areturn
  LineNumberTable: 
   line 136: 0
   line 137: 3
   line 139: 18
   line 140: 39
   line 135: 40

  LocalVariableTable: 
   Start  Length  Slot  Name   Signature
   0      41      0    $this       Lscala/RangeToString;
   3      38      1    MAX_PRINT       I
   18      23      2    str       Ljava/lang/String;


}

