Compiled from "Range.scala"
public final class scala.Range$BigInt$ extends java.lang.Object implements scala.ScalaObject
  SourceFile: "Range.scala"
  Scala: length = 0x
   
  InnerClass: 
   public #54= #51 of #53; //Inclusive=class scala/GenericRange$Inclusive of class scala/GenericRange
   public #57= #56 of #53; //Exclusive=class scala/GenericRange$Exclusive of class scala/GenericRange
  minor version: 0
  major version: 49
  Constant pool:
const #1 = Asciz	SourceFile;
const #2 = Asciz	Range.scala;
const #3 = Asciz	Scala;
const #4 = Asciz	MODULE$;
const #5 = Asciz	Lscala/Range$BigInt$;;
const #6 = Asciz	<clinit>;
const #7 = Asciz	()V;
const #8 = Asciz	Code;
const #9 = Asciz	scala/Range$BigInt$;
const #10 = class	#9;	//  scala/Range$BigInt$
const #11 = Asciz	<init>;
const #12 = NameAndType	#11:#7;//  "<init>":()V
const #13 = Method	#10.#12;	//  scala/Range$BigInt$."<init>":()V
const #14 = Asciz	LineNumberTable;
const #15 = Asciz	java/lang/Object;
const #16 = class	#15;	//  java/lang/Object
const #17 = Method	#16.#12;	//  java/lang/Object."<init>":()V
const #18 = NameAndType	#4:#5;//  MODULE$:Lscala/Range$BigInt$;
const #19 = Field	#10.#18;	//  scala/Range$BigInt$.MODULE$:Lscala/Range$BigInt$;
const #20 = Asciz	inclusive;
const #21 = Asciz	(Lscala/BigInt;Lscala/BigInt;Lscala/BigInt;)Lscala/GenericRange$Inclusive;;
const #22 = Asciz	scala/GenericRange$;
const #23 = class	#22;	//  scala/GenericRange$
const #24 = Asciz	Lscala/GenericRange$;;
const #25 = NameAndType	#4:#24;//  MODULE$:Lscala/GenericRange$;
const #26 = Field	#23.#25;	//  scala/GenericRange$.MODULE$:Lscala/GenericRange$;
const #27 = Asciz	scala/Numeric$BigIntIsIntegral$;
const #28 = class	#27;	//  scala/Numeric$BigIntIsIntegral$
const #29 = Asciz	Lscala/Numeric$BigIntIsIntegral$;;
const #30 = NameAndType	#4:#29;//  MODULE$:Lscala/Numeric$BigIntIsIntegral$;
const #31 = Field	#28.#30;	//  scala/Numeric$BigIntIsIntegral$.MODULE$:Lscala/Numeric$BigIntIsIntegral$;
const #32 = Asciz	(Ljava/lang/Object;Ljava/lang/Object;Ljava/lang/Object;Lscala/Integral;)Lscala/GenericRange$Inclusive;;
const #33 = NameAndType	#20:#32;//  inclusive:(Ljava/lang/Object;Ljava/lang/Object;Ljava/lang/Object;Lscala/Integral;)Lscala/GenericRange$Inclusive;
const #34 = Method	#23.#33;	//  scala/GenericRange$.inclusive:(Ljava/lang/Object;Ljava/lang/Object;Ljava/lang/Object;Lscala/Integral;)Lscala/GenericRange$Inclusive;
const #35 = Asciz	this;
const #36 = Asciz	start;
const #37 = Asciz	Lscala/BigInt;;
const #38 = Asciz	end;
const #39 = Asciz	step;
const #40 = Asciz	LocalVariableTable;
const #41 = Asciz	(Lscala/BigInt;Lscala/BigInt;Lscala/BigInt;)Lscala/GenericRange$Inclusive<Lscala/BigInt;>;;
const #42 = Asciz	Signature;
const #43 = Asciz	apply;
const #44 = Asciz	(Lscala/BigInt;Lscala/BigInt;Lscala/BigInt;)Lscala/GenericRange$Exclusive;;
const #45 = Asciz	(Ljava/lang/Object;Ljava/lang/Object;Ljava/lang/Object;Lscala/Integral;)Lscala/GenericRange$Exclusive;;
const #46 = NameAndType	#43:#45;//  apply:(Ljava/lang/Object;Ljava/lang/Object;Ljava/lang/Object;Lscala/Integral;)Lscala/GenericRange$Exclusive;
const #47 = Method	#23.#46;	//  scala/GenericRange$.apply:(Ljava/lang/Object;Ljava/lang/Object;Ljava/lang/Object;Lscala/Integral;)Lscala/GenericRange$Exclusive;
const #48 = Asciz	(Lscala/BigInt;Lscala/BigInt;Lscala/BigInt;)Lscala/GenericRange$Exclusive<Lscala/BigInt;>;;
const #49 = Asciz	InnerClasses;
const #50 = Asciz	scala/GenericRange$Inclusive;
const #51 = class	#50;	//  scala/GenericRange$Inclusive
const #52 = Asciz	scala/GenericRange;
const #53 = class	#52;	//  scala/GenericRange
const #54 = Asciz	Inclusive;
const #55 = Asciz	scala/GenericRange$Exclusive;
const #56 = class	#55;	//  scala/GenericRange$Exclusive
const #57 = Asciz	Exclusive;
const #58 = Asciz	scala/ScalaObject;
const #59 = class	#58;	//  scala/ScalaObject

{
public static final scala.Range$BigInt$ MODULE$;

public static {};
  Code:
   Stack=1, Locals=0, Args_size=0
   0:	new	#10; //class scala/Range$BigInt$
   3:	invokespecial	#13; //Method "<init>":()V
   6:	return

public scala.Range$BigInt$();
  Code:
   Stack=1, Locals=1, Args_size=1
   0:	aload_0
   1:	invokespecial	#17; //Method java/lang/Object."<init>":()V
   4:	aload_0
   5:	putstatic	#19; //Field MODULE$:Lscala/Range$BigInt$;
   8:	return
  LineNumberTable: 
   line 247: 0


public scala.GenericRange$Inclusive inclusive(scala.BigInt, scala.BigInt, scala.BigInt);
  Code:
   Stack=5, Locals=4, Args_size=4
   0:	getstatic	#26; //Field scala/GenericRange$.MODULE$:Lscala/GenericRange$;
   3:	aload_1
   4:	aload_2
   5:	aload_3
   6:	getstatic	#31; //Field scala/Numeric$BigIntIsIntegral$.MODULE$:Lscala/Numeric$BigIntIsIntegral$;
   9:	invokevirtual	#34; //Method scala/GenericRange$.inclusive:(Ljava/lang/Object;Ljava/lang/Object;Ljava/lang/Object;Lscala/Integral;)Lscala/GenericRange$Inclusive;
   12:	areturn
  LineNumberTable: 
   line 249: 0

  LocalVariableTable: 
   Start  Length  Slot  Name   Signature
   0      13      0    this       Lscala/Range$BigInt$;
   0      13      1    start       Lscala/BigInt;
   0      13      2    end       Lscala/BigInt;
   0      13      3    step       Lscala/BigInt;

  Signature: length = 0x2
   00 29 

public scala.GenericRange$Exclusive apply(scala.BigInt, scala.BigInt, scala.BigInt);
  Code:
   Stack=5, Locals=4, Args_size=4
   0:	getstatic	#26; //Field scala/GenericRange$.MODULE$:Lscala/GenericRange$;
   3:	aload_1
   4:	aload_2
   5:	aload_3
   6:	getstatic	#31; //Field scala/Numeric$BigIntIsIntegral$.MODULE$:Lscala/Numeric$BigIntIsIntegral$;
   9:	invokevirtual	#47; //Method scala/GenericRange$.apply:(Ljava/lang/Object;Ljava/lang/Object;Ljava/lang/Object;Lscala/Integral;)Lscala/GenericRange$Exclusive;
   12:	areturn
  LineNumberTable: 
   line 248: 0

  LocalVariableTable: 
   Start  Length  Slot  Name   Signature
   0      13      0    this       Lscala/Range$BigInt$;
   0      13      1    start       Lscala/BigInt;
   0      13      2    end       Lscala/BigInt;
   0      13      3    step       Lscala/BigInt;

  Signature: length = 0x2
   00 30 

}

