Compiled from "Range.scala"
public final class scala.Range$Double$ extends java.lang.Object implements scala.ScalaObject
  SourceFile: "Range.scala"
  Scala: length = 0x
   
  InnerClass: 
   public #66= #41 of #65; //Partial=class scala/Range$Partial of class scala/Range
   public #69= #47 of #68; //Inclusive=class scala/GenericRange$Inclusive of class scala/GenericRange
   public #70= #61 of #68; //Exclusive=class scala/GenericRange$Exclusive of class scala/GenericRange
  minor version: 0
  major version: 49
  Constant pool:
const #1 = Asciz	SourceFile;
const #2 = Asciz	Range.scala;
const #3 = Asciz	Scala;
const #4 = Asciz	MODULE$;
const #5 = Asciz	Lscala/Range$Double$;;
const #6 = Asciz	<clinit>;
const #7 = Asciz	()V;
const #8 = Asciz	Code;
const #9 = Asciz	scala/Range$Double$;
const #10 = class	#9;	//  scala/Range$Double$
const #11 = Asciz	<init>;
const #12 = NameAndType	#11:#7;//  "<init>":()V
const #13 = Method	#10.#12;	//  scala/Range$Double$."<init>":()V
const #14 = Asciz	LineNumberTable;
const #15 = Asciz	java/lang/Object;
const #16 = class	#15;	//  java/lang/Object
const #17 = Method	#16.#12;	//  java/lang/Object."<init>":()V
const #18 = NameAndType	#4:#5;//  MODULE$:Lscala/Range$Double$;
const #19 = Field	#10.#18;	//  scala/Range$Double$.MODULE$:Lscala/Range$Double$;
const #20 = Asciz	inclusive;
const #21 = Asciz	(DDD)Lscala/GenericRange$Inclusive;;
const #22 = Asciz	scala/BigDecimal$;
const #23 = class	#22;	//  scala/BigDecimal$
const #24 = Asciz	Lscala/BigDecimal$;;
const #25 = NameAndType	#4:#24;//  MODULE$:Lscala/BigDecimal$;
const #26 = Field	#23.#25;	//  scala/BigDecimal$.MODULE$:Lscala/BigDecimal$;
const #27 = Asciz	apply;
const #28 = Asciz	(D)Lscala/BigDecimal;;
const #29 = NameAndType	#27:#28;//  apply:(D)Lscala/BigDecimal;
const #30 = Method	#23.#29;	//  scala/BigDecimal$.apply:(D)Lscala/BigDecimal;
const #31 = Asciz	double2bigDecimal;
const #32 = NameAndType	#31:#28;//  double2bigDecimal:(D)Lscala/BigDecimal;
const #33 = Method	#23.#32;	//  scala/BigDecimal$.double2bigDecimal:(D)Lscala/BigDecimal;
const #34 = Asciz	scala/BigDecimal;
const #35 = class	#34;	//  scala/BigDecimal
const #36 = Asciz	to;
const #37 = Asciz	(Lscala/BigDecimal;)Lscala/Range$Partial;;
const #38 = NameAndType	#36:#37;//  to:(Lscala/BigDecimal;)Lscala/Range$Partial;
const #39 = Method	#35.#38;	//  scala/BigDecimal.to:(Lscala/BigDecimal;)Lscala/Range$Partial;
const #40 = Asciz	scala/Range$Partial;
const #41 = class	#40;	//  scala/Range$Partial
const #42 = Asciz	by;
const #43 = Asciz	(Ljava/lang/Object;)Ljava/lang/Object;;
const #44 = NameAndType	#42:#43;//  by:(Ljava/lang/Object;)Ljava/lang/Object;
const #45 = Method	#41.#44;	//  scala/Range$Partial.by:(Ljava/lang/Object;)Ljava/lang/Object;
const #46 = Asciz	scala/GenericRange$Inclusive;
const #47 = class	#46;	//  scala/GenericRange$Inclusive
const #48 = Asciz	this;
const #49 = Asciz	start;
const #50 = Asciz	D;
const #51 = Asciz	end;
const #52 = Asciz	step;
const #53 = Asciz	LocalVariableTable;
const #54 = Asciz	(DDD)Lscala/GenericRange$Inclusive<Lscala/BigDecimal;>;;
const #55 = Asciz	Signature;
const #56 = Asciz	(DDD)Lscala/GenericRange$Exclusive;;
const #57 = Asciz	until;
const #58 = NameAndType	#57:#37;//  until:(Lscala/BigDecimal;)Lscala/Range$Partial;
const #59 = Method	#35.#58;	//  scala/BigDecimal.until:(Lscala/BigDecimal;)Lscala/Range$Partial;
const #60 = Asciz	scala/GenericRange$Exclusive;
const #61 = class	#60;	//  scala/GenericRange$Exclusive
const #62 = Asciz	(DDD)Lscala/GenericRange$Exclusive<Lscala/BigDecimal;>;;
const #63 = Asciz	InnerClasses;
const #64 = Asciz	scala/Range;
const #65 = class	#64;	//  scala/Range
const #66 = Asciz	Partial;
const #67 = Asciz	scala/GenericRange;
const #68 = class	#67;	//  scala/GenericRange
const #69 = Asciz	Inclusive;
const #70 = Asciz	Exclusive;
const #71 = Asciz	scala/ScalaObject;
const #72 = class	#71;	//  scala/ScalaObject

{
public static final scala.Range$Double$ MODULE$;

public static {};
  Code:
   Stack=1, Locals=0, Args_size=0
   0:	new	#10; //class scala/Range$Double$
   3:	invokespecial	#13; //Method "<init>":()V
   6:	return

public scala.Range$Double$();
  Code:
   Stack=1, Locals=1, Args_size=1
   0:	aload_0
   1:	invokespecial	#17; //Method java/lang/Object."<init>":()V
   4:	aload_0
   5:	putstatic	#19; //Field MODULE$:Lscala/Range$Double$;
   8:	return
  LineNumberTable: 
   line 270: 0


public scala.GenericRange$Inclusive inclusive(double, double, double);
  Code:
   Stack=4, Locals=7, Args_size=4
   0:	getstatic	#26; //Field scala/BigDecimal$.MODULE$:Lscala/BigDecimal$;
   3:	dload_1
   4:	invokevirtual	#30; //Method scala/BigDecimal$.apply:(D)Lscala/BigDecimal;
   7:	getstatic	#26; //Field scala/BigDecimal$.MODULE$:Lscala/BigDecimal$;
   10:	dload_3
   11:	invokevirtual	#33; //Method scala/BigDecimal$.double2bigDecimal:(D)Lscala/BigDecimal;
   14:	invokevirtual	#39; //Method scala/BigDecimal.to:(Lscala/BigDecimal;)Lscala/Range$Partial;
   17:	getstatic	#26; //Field scala/BigDecimal$.MODULE$:Lscala/BigDecimal$;
   20:	dload	5
   22:	invokevirtual	#33; //Method scala/BigDecimal$.double2bigDecimal:(D)Lscala/BigDecimal;
   25:	invokevirtual	#45; //Method scala/Range$Partial.by:(Ljava/lang/Object;)Ljava/lang/Object;
   28:	checkcast	#47; //class scala/GenericRange$Inclusive
   31:	areturn
  LineNumberTable: 
   line 272: 0

  LocalVariableTable: 
   Start  Length  Slot  Name   Signature
   0      32      0    this       Lscala/Range$Double$;
   0      32      1    start       D
   0      32      3    end       D
   0      32      5    step       D

  Signature: length = 0x2
   00 36 

public scala.GenericRange$Exclusive apply(double, double, double);
  Code:
   Stack=4, Locals=7, Args_size=4
   0:	getstatic	#26; //Field scala/BigDecimal$.MODULE$:Lscala/BigDecimal$;
   3:	dload_1
   4:	invokevirtual	#30; //Method scala/BigDecimal$.apply:(D)Lscala/BigDecimal;
   7:	getstatic	#26; //Field scala/BigDecimal$.MODULE$:Lscala/BigDecimal$;
   10:	dload_3
   11:	invokevirtual	#33; //Method scala/BigDecimal$.double2bigDecimal:(D)Lscala/BigDecimal;
   14:	invokevirtual	#59; //Method scala/BigDecimal.until:(Lscala/BigDecimal;)Lscala/Range$Partial;
   17:	getstatic	#26; //Field scala/BigDecimal$.MODULE$:Lscala/BigDecimal$;
   20:	dload	5
   22:	invokevirtual	#33; //Method scala/BigDecimal$.double2bigDecimal:(D)Lscala/BigDecimal;
   25:	invokevirtual	#45; //Method scala/Range$Partial.by:(Ljava/lang/Object;)Ljava/lang/Object;
   28:	checkcast	#61; //class scala/GenericRange$Exclusive
   31:	areturn
  LineNumberTable: 
   line 271: 0

  LocalVariableTable: 
   Start  Length  Slot  Name   Signature
   0      32      0    this       Lscala/Range$Double$;
   0      32      1    start       D
   0      32      3    end       D
   0      32      5    step       D

  Signature: length = 0x2
   00 3E 

}

