Compiled from "Range.scala"
public final class scala.Range$Inclusive extends scala.Range implements scala.ScalaObject
  SourceFile: "Range.scala"
  Scala: length = 0x
   
  InnerClass: 
   public final #30= #10 of #14; //Inclusive=class scala/Range$Inclusive of class scala/Range
  minor version: 0
  major version: 49
  Constant pool:
const #1 = Asciz	SourceFile;
const #2 = Asciz	Range.scala;
const #3 = Asciz	end0;
const #4 = Asciz	I;
const #5 = Asciz	<init>;
const #6 = Asciz	(III)V;
const #7 = Asciz	Code;
const #8 = Asciz	LineNumberTable;
const #9 = Asciz	scala/Range$Inclusive;
const #10 = class	#9;	//  scala/Range$Inclusive
const #11 = NameAndType	#3:#4;//  end0:I
const #12 = Field	#10.#11;	//  scala/Range$Inclusive.end0:I
const #13 = Asciz	scala/Range;
const #14 = class	#13;	//  scala/Range
const #15 = NameAndType	#5:#6;//  "<init>":(III)V
const #16 = Method	#14.#15;	//  scala/Range."<init>":(III)V
const #17 = Asciz	this;
const #18 = Asciz	Lscala/Range$Inclusive;;
const #19 = Asciz	start;
const #20 = Asciz	step;
const #21 = Asciz	LocalVariableTable;
const #22 = Asciz	by;
const #23 = Asciz	(I)Lscala/Range;;
const #24 = Asciz	()I;
const #25 = NameAndType	#19:#24;//  start:()I
const #26 = Method	#14.#25;	//  scala/Range.start:()I
const #27 = Method	#10.#15;	//  scala/Range$Inclusive."<init>":(III)V
const #28 = Asciz	Scala;
const #29 = Asciz	InnerClasses;
const #30 = Asciz	Inclusive;
const #31 = Asciz	scala/ScalaObject;
const #32 = class	#31;	//  scala/ScalaObject

{
public scala.Range$Inclusive(int, int, int);
  Code:
   Stack=4, Locals=4, Args_size=4
   0:	aload_0
   1:	iload_2
   2:	putfield	#12; //Field end0:I
   5:	aload_0
   6:	iload_1
   7:	iload_3
   8:	iconst_0
   9:	if_icmple	18
   12:	iload_2
   13:	iconst_1
   14:	iadd
   15:	goto	21
   18:	iload_2
   19:	iconst_1
   20:	isub
   21:	iload_3
   22:	invokespecial	#16; //Method scala/Range."<init>":(III)V
   25:	return
  LineNumberTable: 
   line 235: 0
   line 236: 6
   line 235: 22

  LocalVariableTable: 
   Start  Length  Slot  Name   Signature
   0      26      0    this       Lscala/Range$Inclusive;
   0      26      1    start       I
   0      26      2    end0       I
   0      26      3    step       I


public scala.Range by(int);
  Code:
   Stack=5, Locals=2, Args_size=2
   0:	new	#10; //class scala/Range$Inclusive
   3:	dup
   4:	aload_0
   5:	invokespecial	#26; //Method scala/Range.start:()I
   8:	aload_0
   9:	getfield	#12; //Field end0:I
   12:	iload_1
   13:	invokespecial	#27; //Method "<init>":(III)V
   16:	areturn
  LineNumberTable: 
   line 237: 0

  LocalVariableTable: 
   Start  Length  Slot  Name   Signature
   0      17      0    this       Lscala/Range$Inclusive;
   0      17      1    step       I


}

