Compiled from "Responder.scala"
public final class scala.Responder$ extends java.lang.Object implements scala.ScalaObject
  SourceFile: "Responder.scala"
  Scala: length = 0x
   
  InnerClass: 
   public final #113= #108 of #40; //$anon$1=class scala/Responder$$anon$1 of class scala/Responder
   public final #116= #115 of #40; //$anon$2=class scala/Responder$$anon$2 of class scala/Responder
   public final #119= #118 of #40; //$anon$3=class scala/Responder$$anon$3 of class scala/Responder
   public final #122= #121 of #40; //$anon$4=class scala/Responder$$anon$4 of class scala/Responder
   public final #123= #85 of #40; //$anonfun$run$1=class scala/Responder$$anonfun$run$1 of class scala/Responder
   public final #124= #66 of #40; //$anonfun$loop$1=class scala/Responder$$anonfun$loop$1 of class scala/Responder
   public final #125= #35 of #40; //$anonfun$loopWhile$1=class scala/Responder$$anonfun$loopWhile$1 of class scala/Responder
  minor version: 0
  major version: 49
  Constant pool:
const #1 = Asciz	SourceFile;
const #2 = Asciz	Responder.scala;
const #3 = Asciz	Scala;
const #4 = Asciz	MODULE$;
const #5 = Asciz	Lscala/Responder$;;
const #6 = Asciz	<clinit>;
const #7 = Asciz	()V;
const #8 = Asciz	Code;
const #9 = Asciz	scala/Responder$;
const #10 = class	#9;	//  scala/Responder$
const #11 = Asciz	<init>;
const #12 = NameAndType	#11:#7;//  "<init>":()V
const #13 = Method	#10.#12;	//  scala/Responder$."<init>":()V
const #14 = Asciz	LineNumberTable;
const #15 = Asciz	java/lang/Object;
const #16 = class	#15;	//  java/lang/Object
const #17 = Method	#16.#12;	//  java/lang/Object."<init>":()V
const #18 = NameAndType	#4:#5;//  MODULE$:Lscala/Responder$;
const #19 = Field	#10.#18;	//  scala/Responder$.MODULE$:Lscala/Responder$;
const #20 = Asciz	loopWhile;
const #21 = Asciz	(Lscala/Function0;Lscala/Responder;)Lscala/Responder;;
const #22 = Asciz	scala/Function0;
const #23 = class	#22;	//  scala/Function0
const #24 = Asciz	apply;
const #25 = Asciz	()Ljava/lang/Object;;
const #26 = NameAndType	#24:#25;//  apply:()Ljava/lang/Object;
const #27 = InterfaceMethod	#23.#26;	//  scala/Function0.apply:()Ljava/lang/Object;
const #28 = Asciz	scala/runtime/BoxesRunTime;
const #29 = class	#28;	//  scala/runtime/BoxesRunTime
const #30 = Asciz	unboxToBoolean;
const #31 = Asciz	(Ljava/lang/Object;)Z;
const #32 = NameAndType	#30:#31;//  unboxToBoolean:(Ljava/lang/Object;)Z
const #33 = Method	#29.#32;	//  scala/runtime/BoxesRunTime.unboxToBoolean:(Ljava/lang/Object;)Z
const #34 = Asciz	scala/Responder$$anonfun$loopWhile$1;
const #35 = class	#34;	//  scala/Responder$$anonfun$loopWhile$1
const #36 = Asciz	(Lscala/Function0;Lscala/Responder;)V;
const #37 = NameAndType	#11:#36;//  "<init>":(Lscala/Function0;Lscala/Responder;)V
const #38 = Method	#35.#37;	//  scala/Responder$$anonfun$loopWhile$1."<init>":(Lscala/Function0;Lscala/Responder;)V
const #39 = Asciz	scala/Responder;
const #40 = class	#39;	//  scala/Responder
const #41 = Asciz	flatMap;
const #42 = Asciz	(Lscala/Function1;)Lscala/Responder;;
const #43 = NameAndType	#41:#42;//  flatMap:(Lscala/Function1;)Lscala/Responder;
const #44 = Method	#40.#43;	//  scala/Responder.flatMap:(Lscala/Function1;)Lscala/Responder;
const #45 = Asciz	scala/runtime/BoxedUnit;
const #46 = class	#45;	//  scala/runtime/BoxedUnit
const #47 = Asciz	UNIT;
const #48 = Asciz	Lscala/runtime/BoxedUnit;;
const #49 = NameAndType	#47:#48;//  UNIT:Lscala/runtime/BoxedUnit;
const #50 = Field	#46.#49;	//  scala/runtime/BoxedUnit.UNIT:Lscala/runtime/BoxedUnit;
const #51 = Asciz	constant;
const #52 = Asciz	(Ljava/lang/Object;)Lscala/Responder;;
const #53 = NameAndType	#51:#52;//  constant:(Ljava/lang/Object;)Lscala/Responder;
const #54 = Method	#10.#53;	//  scala/Responder$.constant:(Ljava/lang/Object;)Lscala/Responder;
const #55 = Asciz	this;
const #56 = Asciz	cond$1;
const #57 = Asciz	Lscala/Function0;;
const #58 = Asciz	r$2;
const #59 = Asciz	Lscala/Responder;;
const #60 = Asciz	LocalVariableTable;
const #61 = Asciz	<A:Ljava/lang/Object;>(Lscala/Function0<Ljava/lang/Boolean;>;Lscala/Responder<Ljava/lang/Object;>;)Lscala/Responder<Ljava/lang/Object;>;;
const #62 = Asciz	Signature;
const #63 = Asciz	loop;
const #64 = Asciz	(Lscala/Responder;)Lscala/Responder;;
const #65 = Asciz	scala/Responder$$anonfun$loop$1;
const #66 = class	#65;	//  scala/Responder$$anonfun$loop$1
const #67 = Asciz	(Lscala/Responder;)V;
const #68 = NameAndType	#11:#67;//  "<init>":(Lscala/Responder;)V
const #69 = Method	#66.#68;	//  scala/Responder$$anonfun$loop$1."<init>":(Lscala/Responder;)V
const #70 = Asciz	r$1;
const #71 = Asciz	<A:Ljava/lang/Object;>(Lscala/Responder<Ljava/lang/Object;>;)Lscala/Responder<Lscala/runtime/Nothing$;>;;
const #72 = Asciz	run;
const #73 = Asciz	(Lscala/Responder;)Lscala/Option;;
const #74 = Asciz	scala/runtime/ObjectRef;
const #75 = class	#74;	//  scala/runtime/ObjectRef
const #76 = Asciz	scala/None$;
const #77 = class	#76;	//  scala/None$
const #78 = Asciz	Lscala/None$;;
const #79 = NameAndType	#4:#78;//  MODULE$:Lscala/None$;
const #80 = Field	#77.#79;	//  scala/None$.MODULE$:Lscala/None$;
const #81 = Asciz	(Ljava/lang/Object;)V;
const #82 = NameAndType	#11:#81;//  "<init>":(Ljava/lang/Object;)V
const #83 = Method	#75.#82;	//  scala/runtime/ObjectRef."<init>":(Ljava/lang/Object;)V
const #84 = Asciz	scala/Responder$$anonfun$run$1;
const #85 = class	#84;	//  scala/Responder$$anonfun$run$1
const #86 = Asciz	(Lscala/runtime/ObjectRef;)V;
const #87 = NameAndType	#11:#86;//  "<init>":(Lscala/runtime/ObjectRef;)V
const #88 = Method	#85.#87;	//  scala/Responder$$anonfun$run$1."<init>":(Lscala/runtime/ObjectRef;)V
const #89 = Asciz	foreach;
const #90 = Asciz	(Lscala/Function1;)V;
const #91 = NameAndType	#89:#90;//  foreach:(Lscala/Function1;)V
const #92 = Method	#40.#91;	//  scala/Responder.foreach:(Lscala/Function1;)V
const #93 = Asciz	elem;
const #94 = Asciz	Ljava/lang/Object;;
const #95 = NameAndType	#93:#94;//  elem:Ljava/lang/Object;
const #96 = Field	#75.#95;	//  scala/runtime/ObjectRef.elem:Ljava/lang/Object;
const #97 = Asciz	scala/Option;
const #98 = class	#97;	//  scala/Option
const #99 = Asciz	r;
const #100 = Asciz	result$1;
const #101 = Asciz	Lscala/runtime/ObjectRef;;
const #102 = Asciz	<A:Ljava/lang/Object;>(Lscala/Responder<TA;>;)Lscala/Option<TA;>;;
const #103 = Asciz	exec;
const #104 = Asciz	(Lscala/Function0;)Z;
const #105 = Asciz	x;
const #106 = Asciz	<A:Ljava/lang/Object;>(Lscala/Function0<Ljava/lang/Object;>;)Z;
const #107 = Asciz	scala/Responder$$anon$1;
const #108 = class	#107;	//  scala/Responder$$anon$1
const #109 = Method	#108.#82;	//  scala/Responder$$anon$1."<init>":(Ljava/lang/Object;)V
const #110 = Asciz	x$1;
const #111 = Asciz	<A:Ljava/lang/Object;>(TA;)Lscala/Responder<TA;>;;
const #112 = Asciz	InnerClasses;
const #113 = Asciz	$anon$1;
const #114 = Asciz	scala/Responder$$anon$2;
const #115 = class	#114;	//  scala/Responder$$anon$2
const #116 = Asciz	$anon$2;
const #117 = Asciz	scala/Responder$$anon$3;
const #118 = class	#117;	//  scala/Responder$$anon$3
const #119 = Asciz	$anon$3;
const #120 = Asciz	scala/Responder$$anon$4;
const #121 = class	#120;	//  scala/Responder$$anon$4
const #122 = Asciz	$anon$4;
const #123 = Asciz	$anonfun$run$1;
const #124 = Asciz	$anonfun$loop$1;
const #125 = Asciz	$anonfun$loopWhile$1;
const #126 = Asciz	scala/ScalaObject;
const #127 = class	#126;	//  scala/ScalaObject

{
public static final scala.Responder$ MODULE$;

public static {};
  Code:
   Stack=1, Locals=0, Args_size=0
   0:	new	#10; //class scala/Responder$
   3:	invokespecial	#13; //Method "<init>":()V
   6:	return

public scala.Responder loopWhile(scala.Function0, scala.Responder);
  Code:
   Stack=5, Locals=3, Args_size=3
   0:	aload_1
   1:	invokeinterface	#27,  1; //InterfaceMethod scala/Function0.apply:()Ljava/lang/Object;
   6:	invokestatic	#33; //Method scala/runtime/BoxesRunTime.unboxToBoolean:(Ljava/lang/Object;)Z
   9:	ifeq	28
   12:	aload_2
   13:	new	#35; //class scala/Responder$$anonfun$loopWhile$1
   16:	dup
   17:	aload_1
   18:	aload_2
   19:	invokespecial	#38; //Method scala/Responder$$anonfun$loopWhile$1."<init>":(Lscala/Function0;Lscala/Responder;)V
   22:	invokevirtual	#44; //Method scala/Responder.flatMap:(Lscala/Function1;)Lscala/Responder;
   25:	goto	35
   28:	aload_0
   29:	getstatic	#50; //Field scala/runtime/BoxedUnit.UNIT:Lscala/runtime/BoxedUnit;
   32:	invokevirtual	#54; //Method constant:(Ljava/lang/Object;)Lscala/Responder;
   35:	areturn
  LineNumberTable: 
   line 53: 0
   line 54: 28
   line 53: 35

  LocalVariableTable: 
   Start  Length  Slot  Name   Signature
   0      36      0    this       Lscala/Responder$;
   0      36      1    cond$1       Lscala/Function0;
   0      36      2    r$2       Lscala/Responder;

  Signature: length = 0x2
   00 3D 

public scala.Responder loop(scala.Responder);
  Code:
   Stack=4, Locals=2, Args_size=2
   0:	aload_1
   1:	new	#66; //class scala/Responder$$anonfun$loop$1
   4:	dup
   5:	aload_1
   6:	invokespecial	#69; //Method scala/Responder$$anonfun$loop$1."<init>":(Lscala/Responder;)V
   9:	invokevirtual	#44; //Method scala/Responder.flatMap:(Lscala/Function1;)Lscala/Responder;
   12:	areturn
  LineNumberTable: 
   line 50: 0

  LocalVariableTable: 
   Start  Length  Slot  Name   Signature
   0      13      0    this       Lscala/Responder$;
   0      13      1    r$1       Lscala/Responder;

  Signature: length = 0x2
   00 47 

public scala.Option run(scala.Responder);
  Code:
   Stack=4, Locals=3, Args_size=2
   0:	new	#75; //class scala/runtime/ObjectRef
   3:	dup
   4:	getstatic	#80; //Field scala/None$.MODULE$:Lscala/None$;
   7:	invokespecial	#83; //Method scala/runtime/ObjectRef."<init>":(Ljava/lang/Object;)V
   10:	astore_2
   11:	aload_1
   12:	new	#85; //class scala/Responder$$anonfun$run$1
   15:	dup
   16:	aload_2
   17:	invokespecial	#88; //Method scala/Responder$$anonfun$run$1."<init>":(Lscala/runtime/ObjectRef;)V
   20:	invokevirtual	#92; //Method scala/Responder.foreach:(Lscala/Function1;)V
   23:	aload_2
   24:	getfield	#96; //Field scala/runtime/ObjectRef.elem:Ljava/lang/Object;
   27:	checkcast	#98; //class scala/Option
   30:	areturn
  LineNumberTable: 
   line 44: 0
   line 45: 11
   line 46: 23

  LocalVariableTable: 
   Start  Length  Slot  Name   Signature
   0      31      0    this       Lscala/Responder$;
   0      31      1    r       Lscala/Responder;
   11      19      2    result$1       Lscala/runtime/ObjectRef;

  Signature: length = 0x2
   00 66 

public boolean exec(scala.Function0);
  Code:
   Stack=1, Locals=2, Args_size=2
   0:	aload_1
   1:	invokeinterface	#27,  1; //InterfaceMethod scala/Function0.apply:()Ljava/lang/Object;
   6:	pop
   7:	iconst_1
   8:	ireturn
  LineNumberTable: 
   line 39: 0

  LocalVariableTable: 
   Start  Length  Slot  Name   Signature
   0      9      0    this       Lscala/Responder$;
   0      9      1    x       Lscala/Function0;

  Signature: length = 0x2
   00 6A 

public scala.Responder constant(java.lang.Object);
  Code:
   Stack=3, Locals=2, Args_size=2
   0:	new	#108; //class scala/Responder$$anon$1
   3:	dup
   4:	aload_1
   5:	invokespecial	#109; //Method scala/Responder$$anon$1."<init>":(Ljava/lang/Object;)V
   8:	areturn
  LineNumberTable: 
   line 29: 0

  LocalVariableTable: 
   Start  Length  Slot  Name   Signature
   0      9      0    this       Lscala/Responder$;
   0      9      1    x$1       Ljava/lang/Object;

  Signature: length = 0x2
   00 6F 

}

