Compiled from "Responder.scala"
public abstract class scala.Responder extends java.lang.Object implements scala.ScalaObject,java.io.Serializable
  SourceFile: "Responder.scala"
  Signature: length = 0x2
   00 51 
  ScalaSig: length = 0x35B
   05 00 FFFFFF81 0F 07 05 01 02 FFFFFF88 02 05 01 09 52 65 73
   70 6F 6E 64 65 72 0A 01 03 01 05 73 63 61 6C 61
   03 00 10 02 06 07 0D 01 02 06 08 08 02 FFFFFF84 FFFFFF80 FFFFFF80
   FFFFFF88 02 09 02 09 52 65 73 70 6F 6E 64 65 72 13 03
   07 0A 12 10 02 0B 10 0D 01 0C 0A 02 0D 0E 01 04
   6C 61 6E 67 0A 01 0F 01 04 6A 61 76 61 09 02 11
   0C 02 06 4F 62 6A 65 63 74 10 02 06 13 09 02 14
   02 02 0B 53 63 61 6C 61 4F 62 6A 65 63 74 08 05
   16 07 FFFFFF84 00 17 01 06 3C 69 6E 69 74 3E 14 01 05
   08 05 19 07 FFFFFF84 00 1A 01 08 63 6F 6E 73 74 61 6E
   74 15 02 1B 65 14 02 1C 66 10 03 06 1D 64 06 05
   08 02 FFFFFF81 00 1E 15 02 1F 25 13 03 1D 0A 12 08 05
   16 1D FFFFFF84 00 21 14 01 22 10 03 06 1D 23 10 02 24
   25 0C 00 04 08 26 1D FFFFFF84 FFFFFF80 FFFFFF84 FFFFFFC2 00 27 02 01 41
   11 02 28 2B 10 02 06 29 09 02 2A 02 02 07 4E 6F
   74 68 69 6E 67 10 02 06 2C 09 02 2D 02 02 03 41
   6E 79 08 05 2F 1D FFFFFF86 00 30 01 07 72 65 73 70 6F
   6E 64 14 02 31 34 10 02 06 32 09 02 33 02 02 04
   55 6E 69 74 08 05 35 2E FFFFFFC0 00 36 01 01 6B 10 04
   06 37 23 31 09 02 38 02 02 09 46 75 6E 63 74 69
   6F 6E 31 08 05 3A 1D FFFFFF84 00 3B 01 07 66 6F 72 65
   61 63 68 14 02 31 3C 08 05 35 39 FFFFFFC0 00 36 08 05
   3E 1D FFFFFF84 00 3F 01 03 6D 61 70 15 02 40 43 14 02
   41 45 10 03 06 1D 42 10 02 24 43 04 08 44 3D FFFFFF84
   FFFFFF80 FFFFFF80 FFFFFFC2 00 27 02 01 42 08 05 46 3D FFFFFFC0 00 47 01
   01 66 10 04 06 37 23 42 08 05 49 1D FFFFFF84 00 4A 01
   07 66 6C 61 74 4D 61 70 15 02 4B 4E 14 02 4C 4F
   10 03 06 1D 4D 10 02 24 4E 04 08 44 48 FFFFFF84 FFFFFF80 FFFFFF80
   FFFFFFC2 00 27 08 05 46 48 FFFFFFC0 00 50 10 04 06 37 23 4C
   08 05 52 1D FFFFFF84 00 53 01 06 66 69 6C 74 65 72 14
   02 22 54 08 05 55 51 FFFFFFC0 00 56 01 01 70 10 04 06
   37 23 57 10 02 06 58 09 02 59 02 02 07 42 6F 6F
   6C 65 61 6E 08 05 5B 1D FFFFFF84 20 5C 01 08 74 6F 53
   74 72 69 6E 67 14 01 5D 10 02 0B 5E 09 02 5F 0C
   02 06 53 74 72 69 6E 67 28 02 1D 61 10 02 06 62
   09 02 63 02 02 0C 73 65 72 69 61 6C 69 7A 61 62
   6C 65 10 02 24 65 04 08 26 18 FFFFFF84 FFFFFF80 FFFFFF80 FFFFFFC2 00 27
   08 05 67 18 FFFFFFC0 00 64 01 01 78 08 05 69 07 FFFFFF84 00
   6A 01 04 65 78 65 63 15 02 6B 70 14 02 57 6C 08
   06 67 68 FFFFFF84 FFFFFFC0 00 6D 10 03 06 6E 31 09 02 6F 02
   02 08 3C 62 79 6E 61 6D 65 3E 04 08 26 68 FFFFFF84 FFFFFF80
   FFFFFF80 FFFFFFC2 00 27 08 05 72 07 FFFFFF84 00 73 01 03 72 75 6E
   15 02 74 79 14 02 75 7A 10 03 06 76 78 09 02 77
   02 02 06 4F 70 74 69 6F 6E 10 02 24 79 04 08 26
   71 FFFFFF84 FFFFFF80 FFFFFF80 FFFFFFC2 00 27 08 05 7B 71 FFFFFFC0 00 7C 01 01
   72 10 03 06 1D 78 08 05 7E 07 FFFFFF84 00 7F 01 04 6C
   6F 6F 70 15 04 FFFFFF81 00 FFFFFF81 04 14 04 FFFFFF81 01 FFFFFF81 02 10
   03 06 1D 28 08 06 7B 7D FFFFFFC0 00 FFFFFF81 03 10 03 06 1D
   31 04 08 26 7D FFFFFF84 FFFFFF80 FFFFFF80 FFFFFFC2 00 27 08 07 FFFFFF81 06 07
   FFFFFF84 00 FFFFFF81 07 01 09 6C 6F 6F 70 57 68 69 6C 65 15
   04 FFFFFF81 08 FFFFFF81 0E 14 04 FFFFFF81 09 FFFFFF81 0B 14 04 FFFFFF81 03 FFFFFF81
   0A 08 07 7B FFFFFF81 05 FFFFFFC0 00 FFFFFF81 03 08 09 FFFFFF81 0C FFFFFF81 05
   FFFFFF84 FFFFFFC0 00 FFFFFF81 0D 01 04 63 6F 6E 64 10 03 06 6E 57
   04 09 26 FFFFFF81 05 FFFFFF84 FFFFFF80 FFFFFF80 FFFFFFC2 00 27 
  InnerClass: 
   public final #86= #85 of #75; //$anon$1=class scala/Responder$$anon$1 of class scala/Responder
   public final #87= #68 of #75; //$anon$3=class scala/Responder$$anon$3 of class scala/Responder
   public final #88= #62 of #75; //$anon$2=class scala/Responder$$anon$2 of class scala/Responder
   public final #89= #50 of #75; //$anon$4=class scala/Responder$$anon$4 of class scala/Responder
   public final #92= #91 of #75; //$anonfun$run$1=class scala/Responder$$anonfun$run$1 of class scala/Responder
   public final #95= #94 of #75; //$anonfun$loop$1=class scala/Responder$$anonfun$loop$1 of class scala/Responder
   public final #98= #97 of #75; //$anonfun$loopWhile$1=class scala/Responder$$anonfun$loopWhile$1 of class scala/Responder
  minor version: 0
  major version: 49
  Constant pool:
const #1 = Asciz	SourceFile;
const #2 = Asciz	Responder.scala;
const #3 = Asciz	loopWhile;
const #4 = Asciz	(Lscala/Function0;Lscala/Responder;)Lscala/Responder;;
const #5 = Asciz	Code;
const #6 = Asciz	scala/Responder$;
const #7 = class	#6;	//  scala/Responder$
const #8 = Asciz	MODULE$;
const #9 = Asciz	Lscala/Responder$;;
const #10 = NameAndType	#8:#9;//  MODULE$:Lscala/Responder$;
const #11 = Field	#7.#10;	//  scala/Responder$.MODULE$:Lscala/Responder$;
const #12 = NameAndType	#3:#4;//  loopWhile:(Lscala/Function0;Lscala/Responder;)Lscala/Responder;
const #13 = Method	#7.#12;	//  scala/Responder$.loopWhile:(Lscala/Function0;Lscala/Responder;)Lscala/Responder;
const #14 = Asciz	<A:Ljava/lang/Object;>(Lscala/Function0<Ljava/lang/Boolean;>;Lscala/Responder<Ljava/lang/Object;>;)Lscala/Responder<Ljava/lang/Object;>;;
const #15 = Asciz	Signature;
const #16 = Asciz	loop;
const #17 = Asciz	(Lscala/Responder;)Lscala/Responder;;
const #18 = NameAndType	#16:#17;//  loop:(Lscala/Responder;)Lscala/Responder;
const #19 = Method	#7.#18;	//  scala/Responder$.loop:(Lscala/Responder;)Lscala/Responder;
const #20 = Asciz	<A:Ljava/lang/Object;>(Lscala/Responder<Ljava/lang/Object;>;)Lscala/Responder<Lscala/runtime/Nothing$;>;;
const #21 = Asciz	run;
const #22 = Asciz	(Lscala/Responder;)Lscala/Option;;
const #23 = NameAndType	#21:#22;//  run:(Lscala/Responder;)Lscala/Option;
const #24 = Method	#7.#23;	//  scala/Responder$.run:(Lscala/Responder;)Lscala/Option;
const #25 = Asciz	<A:Ljava/lang/Object;>(Lscala/Responder<TA;>;)Lscala/Option<TA;>;;
const #26 = Asciz	exec;
const #27 = Asciz	(Lscala/Function0;)Z;
const #28 = NameAndType	#26:#27;//  exec:(Lscala/Function0;)Z
const #29 = Method	#7.#28;	//  scala/Responder$.exec:(Lscala/Function0;)Z
const #30 = Asciz	<A:Ljava/lang/Object;>(Lscala/Function0<Ljava/lang/Object;>;)Z;
const #31 = Asciz	constant;
const #32 = Asciz	(Ljava/lang/Object;)Lscala/Responder;;
const #33 = NameAndType	#31:#32;//  constant:(Ljava/lang/Object;)Lscala/Responder;
const #34 = Method	#7.#33;	//  scala/Responder$.constant:(Ljava/lang/Object;)Lscala/Responder;
const #35 = Asciz	<A:Ljava/lang/Object;>(TA;)Lscala/Responder<TA;>;;
const #36 = Asciz	<init>;
const #37 = Asciz	()V;
const #38 = Asciz	LineNumberTable;
const #39 = Asciz	java/lang/Object;
const #40 = class	#39;	//  java/lang/Object
const #41 = NameAndType	#36:#37;//  "<init>":()V
const #42 = Method	#40.#41;	//  java/lang/Object."<init>":()V
const #43 = Asciz	toString;
const #44 = Asciz	()Ljava/lang/String;;
const #45 = Asciz	Responder;
const #46 = String	#45;	//  Responder
const #47 = Asciz	filter;
const #48 = Asciz	(Lscala/Function1;)Lscala/Responder;;
const #49 = Asciz	scala/Responder$$anon$4;
const #50 = class	#49;	//  scala/Responder$$anon$4
const #51 = Asciz	(Lscala/Responder;Lscala/Function1;)V;
const #52 = NameAndType	#36:#51;//  "<init>":(Lscala/Responder;Lscala/Function1;)V
const #53 = Method	#50.#52;	//  scala/Responder$$anon$4."<init>":(Lscala/Responder;Lscala/Function1;)V
const #54 = Asciz	this;
const #55 = Asciz	Lscala/Responder;;
const #56 = Asciz	p$1;
const #57 = Asciz	Lscala/Function1;;
const #58 = Asciz	LocalVariableTable;
const #59 = Asciz	(Lscala/Function1<TA;Ljava/lang/Boolean;>;)Lscala/Responder<TA;>;;
const #60 = Asciz	flatMap;
const #61 = Asciz	scala/Responder$$anon$2;
const #62 = class	#61;	//  scala/Responder$$anon$2
const #63 = Method	#62.#52;	//  scala/Responder$$anon$2."<init>":(Lscala/Responder;Lscala/Function1;)V
const #64 = Asciz	f$1;
const #65 = Asciz	<B:Ljava/lang/Object;>(Lscala/Function1<TA;Lscala/Responder<TB;>;>;)Lscala/Responder<TB;>;;
const #66 = Asciz	map;
const #67 = Asciz	scala/Responder$$anon$3;
const #68 = class	#67;	//  scala/Responder$$anon$3
const #69 = Method	#68.#52;	//  scala/Responder$$anon$3."<init>":(Lscala/Responder;Lscala/Function1;)V
const #70 = Asciz	f$2;
const #71 = Asciz	<B:Ljava/lang/Object;>(Lscala/Function1<TA;TB;>;)Lscala/Responder<TB;>;;
const #72 = Asciz	foreach;
const #73 = Asciz	(Lscala/Function1;)V;
const #74 = Asciz	scala/Responder;
const #75 = class	#74;	//  scala/Responder
const #76 = Asciz	respond;
const #77 = NameAndType	#76:#73;//  respond:(Lscala/Function1;)V
const #78 = Method	#75.#77;	//  scala/Responder.respond:(Lscala/Function1;)V
const #79 = Asciz	k;
const #80 = Asciz	(Lscala/Function1<TA;Ljava/lang/Object;>;)V;
const #81 = Asciz	<A:Ljava/lang/Object;>Ljava/lang/Object;Lscala/ScalaObject;;
const #82 = Asciz	ScalaSig;
const #83 = Asciz	InnerClasses;
const #84 = Asciz	scala/Responder$$anon$1;
const #85 = class	#84;	//  scala/Responder$$anon$1
const #86 = Asciz	$anon$1;
const #87 = Asciz	$anon$3;
const #88 = Asciz	$anon$2;
const #89 = Asciz	$anon$4;
const #90 = Asciz	scala/Responder$$anonfun$run$1;
const #91 = class	#90;	//  scala/Responder$$anonfun$run$1
const #92 = Asciz	$anonfun$run$1;
const #93 = Asciz	scala/Responder$$anonfun$loop$1;
const #94 = class	#93;	//  scala/Responder$$anonfun$loop$1
const #95 = Asciz	$anonfun$loop$1;
const #96 = Asciz	scala/Responder$$anonfun$loopWhile$1;
const #97 = class	#96;	//  scala/Responder$$anonfun$loopWhile$1
const #98 = Asciz	$anonfun$loopWhile$1;
const #99 = Asciz	scala/ScalaObject;
const #100 = class	#99;	//  scala/ScalaObject
const #101 = Asciz	java/io/Serializable;
const #102 = class	#101;	//  java/io/Serializable

{
public static final scala.Responder loopWhile(scala.Function0, scala.Responder);
  Code:
   Stack=3, Locals=2, Args_size=2
   0:	getstatic	#11; //Field scala/Responder$.MODULE$:Lscala/Responder$;
   3:	aload_0
   4:	aload_1
   5:	invokevirtual	#13; //Method scala/Responder$.loopWhile:(Lscala/Function0;Lscala/Responder;)Lscala/Responder;
   8:	areturn
  Signature: length = 0x2
   00 0E 

public static final scala.Responder loop(scala.Responder);
  Code:
   Stack=2, Locals=1, Args_size=1
   0:	getstatic	#11; //Field scala/Responder$.MODULE$:Lscala/Responder$;
   3:	aload_0
   4:	invokevirtual	#19; //Method scala/Responder$.loop:(Lscala/Responder;)Lscala/Responder;
   7:	areturn
  Signature: length = 0x2
   00 14 

public static final scala.Option run(scala.Responder);
  Code:
   Stack=2, Locals=1, Args_size=1
   0:	getstatic	#11; //Field scala/Responder$.MODULE$:Lscala/Responder$;
   3:	aload_0
   4:	invokevirtual	#24; //Method scala/Responder$.run:(Lscala/Responder;)Lscala/Option;
   7:	areturn
  Signature: length = 0x2
   00 19 

public static final boolean exec(scala.Function0);
  Code:
   Stack=2, Locals=1, Args_size=1
   0:	getstatic	#11; //Field scala/Responder$.MODULE$:Lscala/Responder$;
   3:	aload_0
   4:	invokevirtual	#29; //Method scala/Responder$.exec:(Lscala/Function0;)Z
   7:	ireturn
  Signature: length = 0x2
   00 1E 

public static final scala.Responder constant(java.lang.Object);
  Code:
   Stack=2, Locals=1, Args_size=1
   0:	getstatic	#11; //Field scala/Responder$.MODULE$:Lscala/Responder$;
   3:	aload_0
   4:	invokevirtual	#34; //Method scala/Responder$.constant:(Ljava/lang/Object;)Lscala/Responder;
   7:	areturn
  Signature: length = 0x2
   00 23 

public scala.Responder();
  Code:
   Stack=1, Locals=1, Args_size=1
   0:	aload_0
   1:	invokespecial	#42; //Method java/lang/Object."<init>":()V
   4:	return
  LineNumberTable: 
   line 71: 0

  Signature: length = 0x2
   00 25 

public java.lang.String toString();
  Code:
   Stack=1, Locals=1, Args_size=1
   0:	ldc	#46; //String Responder
   2:	areturn
  LineNumberTable: 
   line 95: 0


public scala.Responder filter(scala.Function1);
  Code:
   Stack=4, Locals=2, Args_size=2
   0:	new	#50; //class scala/Responder$$anon$4
   3:	dup
   4:	aload_0
   5:	aload_1
   6:	invokespecial	#53; //Method scala/Responder$$anon$4."<init>":(Lscala/Responder;Lscala/Function1;)V
   9:	areturn
  LineNumberTable: 
   line 89: 0

  LocalVariableTable: 
   Start  Length  Slot  Name   Signature
   0      10      0    this       Lscala/Responder;
   0      10      1    p$1       Lscala/Function1;

  Signature: length = 0x2
   00 3B 

public scala.Responder flatMap(scala.Function1);
  Code:
   Stack=4, Locals=2, Args_size=2
   0:	new	#62; //class scala/Responder$$anon$2
   3:	dup
   4:	aload_0
   5:	aload_1
   6:	invokespecial	#63; //Method scala/Responder$$anon$2."<init>":(Lscala/Responder;Lscala/Function1;)V
   9:	areturn
  LineNumberTable: 
   line 83: 0

  LocalVariableTable: 
   Start  Length  Slot  Name   Signature
   0      10      0    this       Lscala/Responder;
   0      10      1    f$1       Lscala/Function1;

  Signature: length = 0x2
   00 41 

public scala.Responder map(scala.Function1);
  Code:
   Stack=4, Locals=2, Args_size=2
   0:	new	#68; //class scala/Responder$$anon$3
   3:	dup
   4:	aload_0
   5:	aload_1
   6:	invokespecial	#69; //Method scala/Responder$$anon$3."<init>":(Lscala/Responder;Lscala/Function1;)V
   9:	areturn
  LineNumberTable: 
   line 77: 0

  LocalVariableTable: 
   Start  Length  Slot  Name   Signature
   0      10      0    this       Lscala/Responder;
   0      10      1    f$2       Lscala/Function1;

  Signature: length = 0x2
   00 47 

public void foreach(scala.Function1);
  Code:
   Stack=2, Locals=2, Args_size=2
   0:	aload_0
   1:	aload_1
   2:	invokevirtual	#78; //Method respond:(Lscala/Function1;)V
   5:	return
  LineNumberTable: 
   line 75: 0

  LocalVariableTable: 
   Start  Length  Slot  Name   Signature
   0      6      0    this       Lscala/Responder;
   0      6      1    k       Lscala/Function1;

  Signature: length = 0x2
   00 50 

public abstract void respond(scala.Function1);
  Signature: length = 0x2
   00 50 

}

