Compiled from "Responder.scala"
public final class scala.Responder$$anon$1 extends scala.Responder
  SourceFile: "Responder.scala"
  Signature: length = 0x2
   00 21 
  Scala: length = 0x
   
  InnerClass: 
   public final #36= #10 of #14; //$anon$1=class scala/Responder$$anon$1 of class scala/Responder
  minor version: 0
  major version: 49
  Constant pool:
const #1 = Asciz	SourceFile;
const #2 = Asciz	Responder.scala;
const #3 = Asciz	x$1;
const #4 = Asciz	Ljava/lang/Object;;
const #5 = Asciz	<init>;
const #6 = Asciz	(Ljava/lang/Object;)V;
const #7 = Asciz	Code;
const #8 = Asciz	LineNumberTable;
const #9 = Asciz	scala/Responder$$anon$1;
const #10 = class	#9;	//  scala/Responder$$anon$1
const #11 = NameAndType	#3:#4;//  x$1:Ljava/lang/Object;
const #12 = Field	#10.#11;	//  scala/Responder$$anon$1.x$1:Ljava/lang/Object;
const #13 = Asciz	scala/Responder;
const #14 = class	#13;	//  scala/Responder
const #15 = Asciz	()V;
const #16 = NameAndType	#5:#15;//  "<init>":()V
const #17 = Method	#14.#16;	//  scala/Responder."<init>":()V
const #18 = Asciz	respond;
const #19 = Asciz	(Lscala/Function1;)V;
const #20 = Asciz	scala/Function1;
const #21 = class	#20;	//  scala/Function1
const #22 = Asciz	apply;
const #23 = Asciz	(Ljava/lang/Object;)Ljava/lang/Object;;
const #24 = NameAndType	#22:#23;//  apply:(Ljava/lang/Object;)Ljava/lang/Object;
const #25 = InterfaceMethod	#21.#24;	//  scala/Function1.apply:(Ljava/lang/Object;)Ljava/lang/Object;
const #26 = Asciz	this;
const #27 = Asciz	Lscala/Responder$$anon$1;;
const #28 = Asciz	k;
const #29 = Asciz	Lscala/Function1;;
const #30 = Asciz	LocalVariableTable;
const #31 = Asciz	(Lscala/Function1<TA;Ljava/lang/Object;>;)V;
const #32 = Asciz	Signature;
const #33 = Asciz	Lscala/Responder<TA;>;;
const #34 = Asciz	Scala;
const #35 = Asciz	InnerClasses;
const #36 = Asciz	$anon$1;

{
public scala.Responder$$anon$1(java.lang.Object);
  Code:
   Stack=2, Locals=2, Args_size=2
   0:	aload_0
   1:	aload_1
   2:	putfield	#12; //Field x$1:Ljava/lang/Object;
   5:	aload_0
   6:	invokespecial	#17; //Method scala/Responder."<init>":()V
   9:	return
  LineNumberTable: 
   line 29: 0


public void respond(scala.Function1);
  Code:
   Stack=2, Locals=2, Args_size=2
   0:	aload_1
   1:	aload_0
   2:	getfield	#12; //Field x$1:Ljava/lang/Object;
   5:	invokeinterface	#25,  2; //InterfaceMethod scala/Function1.apply:(Ljava/lang/Object;)Ljava/lang/Object;
   10:	pop
   11:	return
  LineNumberTable: 
   line 30: 0

  LocalVariableTable: 
   Start  Length  Slot  Name   Signature
   0      12      0    this       Lscala/Responder$$anon$1;
   0      12      1    k       Lscala/Function1;

  Signature: length = 0x2
   00 1F 

}

