Compiled from "Responder.scala"
public final class scala.Responder$$anonfun$loop$1 extends java.lang.Object implements scala.Function1,scala.ScalaObject,java.io.Serializable
  SourceFile: "Responder.scala"
  Scala: length = 0x
   
  InnerClass: 
   public final #83= #9 of #57; //$anonfun$loop$1=class scala/Responder$$anonfun$loop$1 of class scala/Responder
   public final #84= #52 of #9; //$anonfun$apply$1=class scala/Responder$$anonfun$loop$1$$anonfun$apply$1 of class scala/Responder$$anonfun$loop$1
  minor version: 0
  major version: 49
  Constant pool:
const #1 = Asciz	SourceFile;
const #2 = Asciz	Responder.scala;
const #3 = Asciz	<clinit>;
const #4 = Asciz	()V;
const #5 = Asciz	Code;
const #6 = Asciz	serialVersionUID;
const #7 = Asciz	J;
const #8 = Asciz	scala/Responder$$anonfun$loop$1;
const #9 = class	#8;	//  scala/Responder$$anonfun$loop$1
const #10 = NameAndType	#6:#7;//  serialVersionUID:J
const #11 = Field	#9.#10;	//  scala/Responder$$anonfun$loop$1.serialVersionUID:J
const #12 = Asciz	r$1;
const #13 = Asciz	Lscala/Responder;;
const #14 = Asciz	<init>;
const #15 = Asciz	(Lscala/Responder;)V;
const #16 = Asciz	LineNumberTable;
const #17 = NameAndType	#12:#13;//  r$1:Lscala/Responder;
const #18 = Field	#9.#17;	//  scala/Responder$$anonfun$loop$1.r$1:Lscala/Responder;
const #19 = Asciz	java/lang/Object;
const #20 = class	#19;	//  java/lang/Object
const #21 = NameAndType	#14:#4;//  "<init>":()V
const #22 = Method	#20.#21;	//  java/lang/Object."<init>":()V
const #23 = Asciz	scala/Function1$class;
const #24 = class	#23;	//  scala/Function1$class
const #25 = Asciz	$init$;
const #26 = Asciz	(Lscala/Function1;)V;
const #27 = NameAndType	#25:#26;//  $init$:(Lscala/Function1;)V
const #28 = Method	#24.#27;	//  scala/Function1$class.$init$:(Lscala/Function1;)V
const #29 = Asciz	apply;
const #30 = Asciz	(Ljava/lang/Object;)Ljava/lang/Object;;
const #31 = Asciz	scala/runtime/BoxedUnit;
const #32 = class	#31;	//  scala/runtime/BoxedUnit
const #33 = Asciz	(Lscala/runtime/BoxedUnit;)Lscala/Responder;;
const #34 = NameAndType	#29:#33;//  apply:(Lscala/runtime/BoxedUnit;)Lscala/Responder;
const #35 = Method	#9.#34;	//  scala/Responder$$anonfun$loop$1.apply:(Lscala/runtime/BoxedUnit;)Lscala/Responder;
const #36 = Asciz	this;
const #37 = Asciz	Lscala/Responder$$anonfun$loop$1;;
const #38 = Asciz	v1;
const #39 = Asciz	Ljava/lang/Object;;
const #40 = Asciz	LocalVariableTable;
const #41 = Asciz	scala/Responder$;
const #42 = class	#41;	//  scala/Responder$
const #43 = Asciz	MODULE$;
const #44 = Asciz	Lscala/Responder$;;
const #45 = NameAndType	#43:#44;//  MODULE$:Lscala/Responder$;
const #46 = Field	#42.#45;	//  scala/Responder$.MODULE$:Lscala/Responder$;
const #47 = Asciz	loop;
const #48 = Asciz	(Lscala/Responder;)Lscala/Responder;;
const #49 = NameAndType	#47:#48;//  loop:(Lscala/Responder;)Lscala/Responder;
const #50 = Method	#42.#49;	//  scala/Responder$.loop:(Lscala/Responder;)Lscala/Responder;
const #51 = Asciz	scala/Responder$$anonfun$loop$1$$anonfun$apply$1;
const #52 = class	#51;	//  scala/Responder$$anonfun$loop$1$$anonfun$apply$1
const #53 = Asciz	(Lscala/Responder$$anonfun$loop$1;)V;
const #54 = NameAndType	#14:#53;//  "<init>":(Lscala/Responder$$anonfun$loop$1;)V
const #55 = Method	#52.#54;	//  scala/Responder$$anonfun$loop$1$$anonfun$apply$1."<init>":(Lscala/Responder$$anonfun$loop$1;)V
const #56 = Asciz	scala/Responder;
const #57 = class	#56;	//  scala/Responder
const #58 = Asciz	map;
const #59 = Asciz	(Lscala/Function1;)Lscala/Responder;;
const #60 = NameAndType	#58:#59;//  map:(Lscala/Function1;)Lscala/Responder;
const #61 = Method	#57.#60;	//  scala/Responder.map:(Lscala/Function1;)Lscala/Responder;
const #62 = Asciz	_;
const #63 = Asciz	Lscala/runtime/BoxedUnit;;
const #64 = Asciz	(Lscala/runtime/BoxedUnit;)Lscala/Responder<Lscala/runtime/Nothing$;>;;
const #65 = Asciz	Signature;
const #66 = Asciz	andThen;
const #67 = Asciz	(Lscala/Function1;)Lscala/Function1;;
const #68 = Asciz	(Lscala/Function1;Lscala/Function1;)Lscala/Function1;;
const #69 = NameAndType	#66:#68;//  andThen:(Lscala/Function1;Lscala/Function1;)Lscala/Function1;
const #70 = Method	#24.#69;	//  scala/Function1$class.andThen:(Lscala/Function1;Lscala/Function1;)Lscala/Function1;
const #71 = Asciz	g;
const #72 = Asciz	Lscala/Function1;;
const #73 = Asciz	compose;
const #74 = NameAndType	#73:#68;//  compose:(Lscala/Function1;Lscala/Function1;)Lscala/Function1;
const #75 = Method	#24.#74;	//  scala/Function1$class.compose:(Lscala/Function1;Lscala/Function1;)Lscala/Function1;
const #76 = Asciz	toString;
const #77 = Asciz	()Ljava/lang/String;;
const #78 = Asciz	(Lscala/Function1;)Ljava/lang/String;;
const #79 = NameAndType	#76:#78;//  toString:(Lscala/Function1;)Ljava/lang/String;
const #80 = Method	#24.#79;	//  scala/Function1$class.toString:(Lscala/Function1;)Ljava/lang/String;
const #81 = Asciz	Scala;
const #82 = Asciz	InnerClasses;
const #83 = Asciz	$anonfun$loop$1;
const #84 = Asciz	$anonfun$apply$1;
const #85 = Asciz	scala/Function1;
const #86 = class	#85;	//  scala/Function1
const #87 = Asciz	scala/ScalaObject;
const #88 = class	#87;	//  scala/ScalaObject
const #89 = Asciz	java/io/Serializable;
const #90 = class	#89;	//  java/io/Serializable

{
public static final long serialVersionUID;

public static {};
  Code:
   Stack=2, Locals=0, Args_size=0
   0:	lconst_0
   1:	putstatic	#11; //Field serialVersionUID:J
   4:	return

public scala.Responder$$anonfun$loop$1(scala.Responder);
  Code:
   Stack=2, Locals=2, Args_size=2
   0:	aload_0
   1:	aload_1
   2:	putfield	#18; //Field r$1:Lscala/Responder;
   5:	aload_0
   6:	invokespecial	#22; //Method java/lang/Object."<init>":()V
   9:	aload_0
   10:	invokestatic	#28; //Method scala/Function1$class.$init$:(Lscala/Function1;)V
   13:	return
  LineNumberTable: 
   line 51: 0


public final java.lang.Object apply(java.lang.Object);
  Code:
   Stack=2, Locals=2, Args_size=2
   0:	aload_0
   1:	aload_1
   2:	checkcast	#32; //class scala/runtime/BoxedUnit
   5:	invokevirtual	#35; //Method apply:(Lscala/runtime/BoxedUnit;)Lscala/Responder;
   8:	areturn
  LineNumberTable: 
   line 51: 0

  LocalVariableTable: 
   Start  Length  Slot  Name   Signature
   0      9      0    this       Lscala/Responder$$anonfun$loop$1;
   0      9      1    v1       Ljava/lang/Object;


public final scala.Responder apply(scala.runtime.BoxedUnit);
  Code:
   Stack=4, Locals=2, Args_size=2
   0:	getstatic	#46; //Field scala/Responder$.MODULE$:Lscala/Responder$;
   3:	aload_0
   4:	getfield	#18; //Field r$1:Lscala/Responder;
   7:	invokevirtual	#50; //Method scala/Responder$.loop:(Lscala/Responder;)Lscala/Responder;
   10:	new	#52; //class scala/Responder$$anonfun$loop$1$$anonfun$apply$1
   13:	dup
   14:	aload_0
   15:	invokespecial	#55; //Method scala/Responder$$anonfun$loop$1$$anonfun$apply$1."<init>":(Lscala/Responder$$anonfun$loop$1;)V
   18:	invokevirtual	#61; //Method scala/Responder.map:(Lscala/Function1;)Lscala/Responder;
   21:	areturn
  LineNumberTable: 
   line 51: 0

  LocalVariableTable: 
   Start  Length  Slot  Name   Signature
   0      22      0    this       Lscala/Responder$$anonfun$loop$1;
   0      22      1    _       Lscala/runtime/BoxedUnit;

  Signature: length = 0x2
   00 40 

public scala.Function1 andThen(scala.Function1);
  Code:
   Stack=2, Locals=2, Args_size=2
   0:	aload_0
   1:	aload_1
   2:	invokestatic	#70; //Method scala/Function1$class.andThen:(Lscala/Function1;Lscala/Function1;)Lscala/Function1;
   5:	areturn
  LineNumberTable: 
   line 51: 0

  LocalVariableTable: 
   Start  Length  Slot  Name   Signature
   0      6      0    this       Lscala/Responder$$anonfun$loop$1;
   0      6      1    g       Lscala/Function1;


public scala.Function1 compose(scala.Function1);
  Code:
   Stack=2, Locals=2, Args_size=2
   0:	aload_0
   1:	aload_1
   2:	invokestatic	#75; //Method scala/Function1$class.compose:(Lscala/Function1;Lscala/Function1;)Lscala/Function1;
   5:	areturn
  LineNumberTable: 
   line 51: 0

  LocalVariableTable: 
   Start  Length  Slot  Name   Signature
   0      6      0    this       Lscala/Responder$$anonfun$loop$1;
   0      6      1    g       Lscala/Function1;


public java.lang.String toString();
  Code:
   Stack=1, Locals=1, Args_size=1
   0:	aload_0
   1:	invokestatic	#80; //Method scala/Function1$class.toString:(Lscala/Function1;)Ljava/lang/String;
   4:	areturn
  LineNumberTable: 
   line 51: 0


}

