Compiled from "Responder.scala"
public final class scala.Responder$$anonfun$loopWhile$1$$anonfun$apply$2 extends java.lang.Object implements scala.Function1,scala.ScalaObject,java.io.Serializable
  SourceFile: "Responder.scala"
  Scala: length = 0x
   
  InnerClass: 
   public final $anonfun$loopWhile$1=class scala/Responder$$anonfun$loopWhile$1 of class scala/Responder
   public final $anonfun$apply$2=class scala/Responder$$anonfun$loopWhile$1$$anonfun$apply$2 of class scala/Responder$$anonfun$loopWhile$1
  minor version: 0
  major version: 49
  Constant pool:
Asciz	SourceFile;
Asciz	Responder.scala;
Asciz	<clinit>;
Asciz	()V;
Asciz	Code;
Asciz	serialVersionUID;
Asciz	J;
Asciz	scala/Responder$$anonfun$loopWhile$1$$anonfun$apply$2;
class	scala/Responder$$anonfun$loopWhile$1$$anonfun$apply$2
NameAndType	serialVersionUID:J
Field	scala/Responder$$anonfun$loopWhile$1$$anonfun$apply$2.serialVersionUID:J
Asciz	<init>;
Asciz	(Lscala/Responder$$anonfun$loopWhile$1;)V;
Asciz	LineNumberTable;
Asciz	java/lang/Object;
class	java/lang/Object
NameAndType	"<init>":()V
Method	java/lang/Object."<init>":()V
Asciz	scala/Function1$class;
class	scala/Function1$class
Asciz	$init$;
Asciz	(Lscala/Function1;)V;
NameAndType	$init$:(Lscala/Function1;)V
Method	scala/Function1$class.$init$:(Lscala/Function1;)V
Asciz	this;
Asciz	Lscala/Responder$$anonfun$loopWhile$1$$anonfun$apply$2;;
Asciz	$outer;
Asciz	Lscala/Responder$$anonfun$loopWhile$1;;
Asciz	LocalVariableTable;
Asciz	apply;
Asciz	(Ljava/lang/Object;)Ljava/lang/Object;;
Asciz	scala/runtime/BoxedUnit;
class	scala/runtime/BoxedUnit
Asciz	(Lscala/runtime/BoxedUnit;)V;
NameAndType	apply:(Lscala/runtime/BoxedUnit;)V
Method	scala/Responder$$anonfun$loopWhile$1$$anonfun$apply$2.apply:(Lscala/runtime/BoxedUnit;)V
Asciz	UNIT;
Asciz	Lscala/runtime/BoxedUnit;;
NameAndType	UNIT:Lscala/runtime/BoxedUnit;
Field	scala/runtime/BoxedUnit.UNIT:Lscala/runtime/BoxedUnit;
Asciz	v1;
Asciz	Ljava/lang/Object;;
Asciz	y;
Asciz	andThen;
Asciz	(Lscala/Function1;)Lscala/Function1;;
Asciz	(Lscala/Function1;Lscala/Function1;)Lscala/Function1;;
NameAndType	andThen:(Lscala/Function1;Lscala/Function1;)Lscala/Function1;
Method	scala/Function1$class.andThen:(Lscala/Function1;Lscala/Function1;)Lscala/Function1;
Asciz	g;
Asciz	Lscala/Function1;;
Asciz	compose;
NameAndType	compose:(Lscala/Function1;Lscala/Function1;)Lscala/Function1;
Method	scala/Function1$class.compose:(Lscala/Function1;Lscala/Function1;)Lscala/Function1;
Asciz	toString;
Asciz	()Ljava/lang/String;;
Asciz	(Lscala/Function1;)Ljava/lang/String;;
NameAndType	toString:(Lscala/Function1;)Ljava/lang/String;
Method	scala/Function1$class.toString:(Lscala/Function1;)Ljava/lang/String;
Asciz	Scala;
Asciz	InnerClasses;
Asciz	scala/Responder$$anonfun$loopWhile$1;
class	scala/Responder$$anonfun$loopWhile$1
Asciz	scala/Responder;
class	scala/Responder
Asciz	$anonfun$loopWhile$1;
Asciz	$anonfun$apply$2;
Asciz	scala/Function1;
class	scala/Function1
Asciz	scala/ScalaObject;
class	scala/ScalaObject
Asciz	java/io/Serializable;
class	java/io/Serializable

{
public static final long serialVersionUID;
  Signature: J

public static {};
  Signature: ()V
  Code:
   Stack=2, Locals=0, Args_size=0
	lconst_0
	putstatic	Field serialVersionUID:J
	return
  Labels:

public scala.Responder$$anonfun$loopWhile$1$$anonfun$apply$2(scala.Responder$$anonfun$loopWhile$1);
  Signature: (Lscala/Responder$$anonfun$loopWhile$1;)V
  Code:
   Stack=1, Locals=2, Args_size=2
	aload_0
	invokespecial	Method java/lang/Object."<init>":()V
	aload_0
	invokestatic	Method scala/Function1$class.$init$:(Lscala/Function1;)V
	return
  Labels:
  LocalVariableTable: 
   Start  Length  Slot  Name   Signature
   0      9      0    this       Lscala/Responder$$anonfun$loopWhile$1$$anonfun$apply$2;
   0      9      1    $outer       Lscala/Responder$$anonfun$loopWhile$1;


public final java.lang.Object apply(java.lang.Object);
  Signature: (Ljava/lang/Object;)Ljava/lang/Object;
  Code:
   Stack=2, Locals=2, Args_size=2
	aload_0
	aload_1
	checkcast	class scala/runtime/BoxedUnit
	invokevirtual	Method apply:(Lscala/runtime/BoxedUnit;)V
	getstatic	Field scala/runtime/BoxedUnit.UNIT:Lscala/runtime/BoxedUnit;
	areturn
  Labels:
  LocalVariableTable: 
   Start  Length  Slot  Name   Signature
   0      12      0    this       Lscala/Responder$$anonfun$loopWhile$1$$anonfun$apply$2;
   0      12      1    v1       Ljava/lang/Object;


public final void apply(scala.runtime.BoxedUnit);
  Signature: (Lscala/runtime/BoxedUnit;)V
  Code:
   Stack=0, Locals=2, Args_size=2
	return
  Labels:
  LocalVariableTable: 
   Start  Length  Slot  Name   Signature
   0      1      0    this       Lscala/Responder$$anonfun$loopWhile$1$$anonfun$apply$2;
   0      1      1    y       Lscala/runtime/BoxedUnit;


public scala.Function1 andThen(scala.Function1);
  Signature: (Lscala/Function1;)Lscala/Function1;
  Code:
   Stack=2, Locals=2, Args_size=2
	aload_0
	aload_1
	invokestatic	Method scala/Function1$class.andThen:(Lscala/Function1;Lscala/Function1;)Lscala/Function1;
	areturn
  Labels:
  LocalVariableTable: 
   Start  Length  Slot  Name   Signature
   0      6      0    this       Lscala/Responder$$anonfun$loopWhile$1$$anonfun$apply$2;
   0      6      1    g       Lscala/Function1;


public scala.Function1 compose(scala.Function1);
  Signature: (Lscala/Function1;)Lscala/Function1;
  Code:
   Stack=2, Locals=2, Args_size=2
	aload_0
	aload_1
	invokestatic	Method scala/Function1$class.compose:(Lscala/Function1;Lscala/Function1;)Lscala/Function1;
	areturn
  Labels:
  LocalVariableTable: 
   Start  Length  Slot  Name   Signature
   0      6      0    this       Lscala/Responder$$anonfun$loopWhile$1$$anonfun$apply$2;
   0      6      1    g       Lscala/Function1;


public java.lang.String toString();
  Signature: ()Ljava/lang/String;
  Code:
   Stack=1, Locals=1, Args_size=1
	aload_0
	invokestatic	Method scala/Function1$class.toString:(Lscala/Function1;)Ljava/lang/String;
	areturn
  Labels:

}

