Compiled from "Responder.scala"
public final class scala.Responder$$anon$2 extends scala.Responder
  SourceFile: "Responder.scala"
  Signature: length = 0x2
   00 29 
  Scala: length = 0x
   
  InnerClass: 
   public final $anon$2=class scala/Responder$$anon$2 of class scala/Responder
   public final $anonfun$respond$2=class scala/Responder$$anon$2$$anonfun$respond$2 of class scala/Responder$$anon$2
  minor version: 0
  major version: 49
  Constant pool:
Asciz	SourceFile;
Asciz	Responder.scala;
Asciz	f$1;
Asciz	Lscala/Function1;;
Asciz	$outer;
Asciz	Lscala/Responder;;
Asciz	respond;
Asciz	(Lscala/Function1;)V;
Asciz	Code;
Asciz	LineNumberTable;
Asciz	scala/Responder$$anon$2;
class	scala/Responder$$anon$2
NameAndType	$outer:Lscala/Responder;
Field	scala/Responder$$anon$2.$outer:Lscala/Responder;
Asciz	scala/Responder$$anon$2$$anonfun$respond$2;
class	scala/Responder$$anon$2$$anonfun$respond$2
Asciz	<init>;
Asciz	(Lscala/Responder$$anon$2;Lscala/Function1;)V;
NameAndType	"<init>":(Lscala/Responder$$anon$2;Lscala/Function1;)V
Method	scala/Responder$$anon$2$$anonfun$respond$2."<init>":(Lscala/Responder$$anon$2;Lscala/Function1;)V
Asciz	scala/Responder;
class	scala/Responder
NameAndType	respond:(Lscala/Function1;)V
Method	scala/Responder.respond:(Lscala/Function1;)V
Asciz	this;
Asciz	Lscala/Responder$$anon$2;;
Asciz	k$1;
Asciz	LocalVariableTable;
Asciz	(Lscala/Function1<TB;Ljava/lang/Object;>;)V;
Asciz	Signature;
Asciz	(Lscala/Responder;Lscala/Function1;)V;
Asciz	java/lang/NullPointerException;
class	java/lang/NullPointerException
Asciz	()V;
NameAndType	"<init>":()V
Method	java/lang/NullPointerException."<init>":()V
NameAndType	f$1:Lscala/Function1;
Field	scala/Responder$$anon$2.f$1:Lscala/Function1;
Method	scala/Responder."<init>":()V
Asciz	(Lscala/Responder<TA;>;)V;
Asciz	Lscala/Responder<TB;>;;
Asciz	Scala;
Asciz	InnerClasses;
Asciz	$anon$2;
Asciz	$anonfun$respond$2;

{
public final scala.Function1 f$1;
  Signature: Lscala/Function1;

private final scala.Responder $outer;
  Signature: Lscala/Responder;

public void respond(scala.Function1);
  Signature: (Lscala/Function1;)V
  Code:
   Stack=5, Locals=2, Args_size=2
	aload_0
	getfield	Field $outer:Lscala/Responder;
	new	class scala/Responder$$anon$2$$anonfun$respond$2
	dup
	aload_0
	aload_1
	invokespecial	Method scala/Responder$$anon$2$$anonfun$respond$2."<init>":(Lscala/Responder$$anon$2;Lscala/Function1;)V
	invokevirtual	Method scala/Responder.respond:(Lscala/Function1;)V
	return
  Labels:
  LocalVariableTable: 
   Start  Length  Slot  Name   Signature
   0      17      0    this       Lscala/Responder$$anon$2;
   0      17      1    k$1       Lscala/Function1;

  Signature: length = 0x2
   00 1D 

public scala.Responder$$anon$2(scala.Responder, scala.Function1);
  Signature: (Lscala/Responder;Lscala/Function1;)V
  Code:
   Stack=2, Locals=3, Args_size=3
	aload_1
	ifnonnull	l1 // aload_0
	new	class java/lang/NullPointerException
	dup
	invokespecial	Method java/lang/NullPointerException."<init>":()V
	athrow
l1	aload_0
	aload_1
	putfield	Field $outer:Lscala/Responder;
	aload_0
	aload_2
	putfield	Field f$1:Lscala/Function1;
	aload_0
	invokespecial	Method scala/Responder."<init>":()V
	return
  Labels:
   	l1 = 12 // aload_0
  LocalVariableTable: 
   Start  Length  Slot  Name   Signature
   0      27      0    this       Lscala/Responder$$anon$2;
   0      27      1    $outer       Lscala/Responder;

  Signature: length = 0x2
   00 28 

}

