Compiled from "Responder.scala"
public final class scala.Responder$$anon$2 extends scala.Responder
  SourceFile: "Responder.scala"
  Signature: length = 0x2
   00 29 
  Scala: length = 0x
   
  InnerClass: 
   public final #44= #17 of #23; //$anon$2=class scala/Responder$$anon$2 of class scala/Responder
   public final #45= #33 of #17; //$anonfun$respond$2=class scala/Responder$$anon$2$$anonfun$respond$2 of class scala/Responder$$anon$2
  minor version: 0
  major version: 49
  Constant pool:
const #1 = Asciz	SourceFile;
const #2 = Asciz	Responder.scala;
const #3 = Asciz	f$1;
const #4 = Asciz	Lscala/Function1;;
const #5 = Asciz	$outer;
const #6 = Asciz	Lscala/Responder;;
const #7 = Asciz	<init>;
const #8 = Asciz	(Lscala/Responder;Lscala/Function1;)V;
const #9 = Asciz	Code;
const #10 = Asciz	LineNumberTable;
const #11 = Asciz	java/lang/NullPointerException;
const #12 = class	#11;	//  java/lang/NullPointerException
const #13 = Asciz	()V;
const #14 = NameAndType	#7:#13;//  "<init>":()V
const #15 = Method	#12.#14;	//  java/lang/NullPointerException."<init>":()V
const #16 = Asciz	scala/Responder$$anon$2;
const #17 = class	#16;	//  scala/Responder$$anon$2
const #18 = NameAndType	#5:#6;//  $outer:Lscala/Responder;
const #19 = Field	#17.#18;	//  scala/Responder$$anon$2.$outer:Lscala/Responder;
const #20 = NameAndType	#3:#4;//  f$1:Lscala/Function1;
const #21 = Field	#17.#20;	//  scala/Responder$$anon$2.f$1:Lscala/Function1;
const #22 = Asciz	scala/Responder;
const #23 = class	#22;	//  scala/Responder
const #24 = Method	#23.#14;	//  scala/Responder."<init>":()V
const #25 = Asciz	this;
const #26 = Asciz	Lscala/Responder$$anon$2;;
const #27 = Asciz	LocalVariableTable;
const #28 = Asciz	(Lscala/Responder<TA;>;)V;
const #29 = Asciz	Signature;
const #30 = Asciz	respond;
const #31 = Asciz	(Lscala/Function1;)V;
const #32 = Asciz	scala/Responder$$anon$2$$anonfun$respond$2;
const #33 = class	#32;	//  scala/Responder$$anon$2$$anonfun$respond$2
const #34 = Asciz	(Lscala/Responder$$anon$2;Lscala/Function1;)V;
const #35 = NameAndType	#7:#34;//  "<init>":(Lscala/Responder$$anon$2;Lscala/Function1;)V
const #36 = Method	#33.#35;	//  scala/Responder$$anon$2$$anonfun$respond$2."<init>":(Lscala/Responder$$anon$2;Lscala/Function1;)V
const #37 = NameAndType	#30:#31;//  respond:(Lscala/Function1;)V
const #38 = Method	#23.#37;	//  scala/Responder.respond:(Lscala/Function1;)V
const #39 = Asciz	k$1;
const #40 = Asciz	(Lscala/Function1<TB;Ljava/lang/Object;>;)V;
const #41 = Asciz	Lscala/Responder<TB;>;;
const #42 = Asciz	Scala;
const #43 = Asciz	InnerClasses;
const #44 = Asciz	$anon$2;
const #45 = Asciz	$anonfun$respond$2;

{
public final scala.Function1 f$1;

public scala.Responder$$anon$2(scala.Responder, scala.Function1);
  Code:
   Stack=2, Locals=3, Args_size=3
   0:	aload_1
   1:	ifnonnull	12
   4:	new	#12; //class java/lang/NullPointerException
   7:	dup
   8:	invokespecial	#15; //Method java/lang/NullPointerException."<init>":()V
   11:	athrow
   12:	aload_0
   13:	aload_1
   14:	putfield	#19; //Field $outer:Lscala/Responder;
   17:	aload_0
   18:	aload_2
   19:	putfield	#21; //Field f$1:Lscala/Function1;
   22:	aload_0
   23:	invokespecial	#24; //Method scala/Responder."<init>":()V
   26:	return
  LineNumberTable: 
   line 80: 0

  LocalVariableTable: 
   Start  Length  Slot  Name   Signature
   0      27      0    this       Lscala/Responder$$anon$2;
   0      27      1    $outer       Lscala/Responder;

  Signature: length = 0x2
   00 1C 

public void respond(scala.Function1);
  Code:
   Stack=5, Locals=2, Args_size=2
   0:	aload_0
   1:	getfield	#19; //Field $outer:Lscala/Responder;
   4:	new	#33; //class scala/Responder$$anon$2$$anonfun$respond$2
   7:	dup
   8:	aload_0
   9:	aload_1
   10:	invokespecial	#36; //Method scala/Responder$$anon$2$$anonfun$respond$2."<init>":(Lscala/Responder$$anon$2;Lscala/Function1;)V
   13:	invokevirtual	#38; //Method scala/Responder.respond:(Lscala/Function1;)V
   16:	return
  LineNumberTable: 
   line 82: 0

  LocalVariableTable: 
   Start  Length  Slot  Name   Signature
   0      17      0    this       Lscala/Responder$$anon$2;
   0      17      1    k$1       Lscala/Function1;

  Signature: length = 0x2
   00 28 

}

