Compiled from "Either.scala"
public final class scala.Right$ extends java.lang.Object implements scala.ScalaObject
  SourceFile: "Either.scala"
  Scala: length = 0x
   
  minor version: 0
  major version: 49
  Constant pool:
const #1 = Asciz	SourceFile;
const #2 = Asciz	Either.scala;
const #3 = Asciz	Scala;
const #4 = Asciz	MODULE$;
const #5 = Asciz	Lscala/Right$;;
const #6 = Asciz	<clinit>;
const #7 = Asciz	()V;
const #8 = Asciz	Code;
const #9 = Asciz	scala/Right$;
const #10 = class	#9;	//  scala/Right$
const #11 = Asciz	<init>;
const #12 = NameAndType	#11:#7;//  "<init>":()V
const #13 = Method	#10.#12;	//  scala/Right$."<init>":()V
const #14 = Asciz	LineNumberTable;
const #15 = Asciz	java/lang/Object;
const #16 = class	#15;	//  java/lang/Object
const #17 = Method	#16.#12;	//  java/lang/Object."<init>":()V
const #18 = NameAndType	#4:#5;//  MODULE$:Lscala/Right$;
const #19 = Field	#10.#18;	//  scala/Right$.MODULE$:Lscala/Right$;
const #20 = Asciz	apply;
const #21 = Asciz	(Ljava/lang/Object;)Lscala/Right;;
const #22 = Asciz	scala/Right;
const #23 = class	#22;	//  scala/Right
const #24 = Asciz	(Ljava/lang/Object;)V;
const #25 = NameAndType	#11:#24;//  "<init>":(Ljava/lang/Object;)V
const #26 = Method	#23.#25;	//  scala/Right."<init>":(Ljava/lang/Object;)V
const #27 = Asciz	this;
const #28 = Asciz	b;
const #29 = Asciz	Ljava/lang/Object;;
const #30 = Asciz	LocalVariableTable;
const #31 = Asciz	unapply;
const #32 = Asciz	(Lscala/Right;)Lscala/Some;;
const #33 = Asciz	scala/Some;
const #34 = class	#33;	//  scala/Some
const #35 = Asciz	()Ljava/lang/Object;;
const #36 = NameAndType	#28:#35;//  b:()Ljava/lang/Object;
const #37 = Method	#23.#36;	//  scala/Right.b:()Ljava/lang/Object;
const #38 = Method	#34.#25;	//  scala/Some."<init>":(Ljava/lang/Object;)V
const #39 = Asciz	x$0;
const #40 = Asciz	Lscala/Right;;
const #41 = Asciz	scala/ScalaObject;
const #42 = class	#41;	//  scala/ScalaObject

{
public static final scala.Right$ MODULE$;

public static {};
  Code:
   Stack=1, Locals=0, Args_size=0
   0:	new	#10; //class scala/Right$
   3:	invokespecial	#13; //Method "<init>":()V
   6:	return

public scala.Right apply(java.lang.Object);
  Code:
   Stack=3, Locals=2, Args_size=2
   0:	new	#23; //class scala/Right
   3:	dup
   4:	aload_1
   5:	invokespecial	#26; //Method scala/Right."<init>":(Ljava/lang/Object;)V
   8:	areturn
  LineNumberTable: 
   line 65: 0

  LocalVariableTable: 
   Start  Length  Slot  Name   Signature
   0      9      0    this       Lscala/Right$;
   0      9      1    b       Ljava/lang/Object;


public scala.Some unapply(scala.Right);
  Code:
   Stack=3, Locals=2, Args_size=2
   0:	new	#34; //class scala/Some
   3:	dup
   4:	aload_1
   5:	invokevirtual	#37; //Method scala/Right.b:()Ljava/lang/Object;
   8:	invokespecial	#38; //Method scala/Some."<init>":(Ljava/lang/Object;)V
   11:	areturn
  LineNumberTable: 
   line 65: 0

  LocalVariableTable: 
   Start  Length  Slot  Name   Signature
   0      12      0    this       Lscala/Right$;
   0      12      1    x$0       Lscala/Right;


}

