Compiled from "Either.scala"
public final class scala.Right extends scala.Either implements scala.ScalaObject,scala.Product,java.io.Serializable
  SourceFile: "Either.scala"
  Signature: length = 0x2
   00 70 
  ScalaSig: length = 0x408
   05 00 FFFFFF81 1A 06 04 01 02 42 05 02 05 52 69 67 68
   74 0A 01 03 01 05 73 63 61 6C 61 03 00 15 03 06
   0D 17 13 04 00 07 19 1C 10 04 08 09 0B 16 0D 01
   02 09 02 0A 02 02 06 45 69 74 68 65 72 10 02 0C
   0D 0C 00 04 08 0E 00 FFFFFF84 FFFFFF80 FFFFFF84 FFFFFFC2 00 0F 02 01 41
   11 02 10 13 10 02 08 11 09 02 12 02 02 07 4E 6F
   74 68 69 6E 67 10 02 08 14 09 02 15 02 02 03 41
   6E 79 10 02 0C 17 04 08 18 00 FFFFFF84 FFFFFF80 FFFFFF84 FFFFFFC2 00 0F
   02 01 42 10 02 08 1A 09 02 1B 02 02 0B 53 63 61
   6C 61 4F 62 6A 65 63 74 10 02 08 1D 09 02 1E 02
   02 07 50 72 6F 64 75 63 74 08 08 20 00 FFFFFF82 FFFFFFCA FFFFFF80
   FFFFFF84 00 21 01 01 62 15 01 16 08 08 23 00 FFFFFF82 FFFFFF88 FFFFFFA0
   FFFFFF80 04 16 01 02 62 20 08 05 25 00 FFFFFF84 00 26 01 06
   3C 69 6E 69 74 3E 14 02 27 28 10 04 08 00 0B 16
   08 05 20 24 FFFFFFC0 00 16 08 05 2A 00 FFFFFF84 00 2B 01 06
   69 73 4C 65 66 74 15 01 2C 10 02 08 2D 09 02 2E
   02 02 07 42 6F 6F 6C 65 61 6E 08 05 30 00 FFFFFF84 00
   2B 01 07 69 73 52 69 67 68 74 08 07 32 00 FFFFFF81 FFFFFF80
   FFFFFF84 00 33 01 04 63 6F 70 79 15 03 34 37 39 14 02
   35 3A 10 04 08 00 36 38 10 02 0C 37 04 08 0E 31
   FFFFFF84 FFFFFF80 FFFFFF80 FFFFFFC2 00 0F 10 02 0C 39 04 08 18 31 FFFFFF84 FFFFFF80
   FFFFFF80 FFFFFFC2 00 0F 08 08 3B 20 31 FFFFFF90 FFFFFF80 FFFFFFC0 00 38 08 07
   3C 00 FFFFFF91 FFFFFF80 FFFFFF84 00 3D 01 0E 63 6F 70 79 24 64 65
   66 61 75 6C 74 24 31 15 03 3E 48 49 2A 02 16 3F
   2B 01 40 10 02 41 46 0D 01 42 0A 02 43 44 01 09
   75 6E 63 68 65 63 6B 65 64 0A 02 45 02 01 0A 61
   6E 6E 6F 74 61 74 69 6F 6E 09 02 47 42 02 11 75
   6E 63 68 65 63 6B 65 64 56 61 72 69 61 6E 63 65
   04 08 0E 3B FFFFFF84 FFFFFF80 FFFFFF80 FFFFFFC2 00 0F 04 08 18 3B FFFFFF84 FFFFFF80
   FFFFFF80 FFFFFFC2 00 0F 08 08 4B 00 FFFFFF84 FFFFFF80 FFFFFF80 FFFFFF84 20 4C 01 08
   68 61 73 68 43 6F 64 65 14 01 4D 10 02 08 4E 09
   02 4F 02 02 03 49 6E 74 08 08 51 00 FFFFFF84 FFFFFF80 FFFFFF80 FFFFFF84
   20 52 01 08 74 6F 53 74 72 69 6E 67 14 01 53 10
   02 54 57 0E 02 08 55 09 02 56 02 01 06 50 72 65
   64 65 66 09 02 58 59 02 06 53 74 72 69 6E 67 0A
   02 56 02 08 08 5B 00 FFFFFF84 FFFFFF80 FFFFFF80 FFFFFF84 20 5C 01 06 65
   71 75 61 6C 73 14 02 2C 5D 08 07 5E 5A FFFFFF81 FFFFFF80 FFFFFFC0
   00 13 01 03 78 24 31 08 08 60 00 FFFFFF84 FFFFFF80 FFFFFF80 FFFFFF84 20
   61 01 0D 70 72 6F 64 75 63 74 50 72 65 66 69 78
   15 01 62 10 02 63 68 0D 01 64 0A 02 65 66 01 04
   6C 61 6E 67 0A 01 67 01 04 6A 61 76 61 09 02 58
   64 08 08 6A 00 FFFFFF84 FFFFFF80 FFFFFF80 FFFFFF84 20 6B 01 0C 70 72 6F
   64 75 63 74 41 72 69 74 79 15 01 4D 08 08 6D 00
   FFFFFF84 FFFFFF80 FFFFFF80 FFFFFF84 20 6E 01 0E 70 72 6F 64 75 63 74 45
   6C 65 6D 65 6E 74 14 02 13 6F 08 07 5E 6C FFFFFF81 FFFFFF80
   FFFFFFC0 00 4D 08 08 71 00 FFFFFF84 FFFFFF80 FFFFFF80 FFFFFF84 20 72 01 08 63
   61 6E 45 71 75 61 6C 14 02 2C 73 08 07 5E 70 FFFFFF81
   FFFFFF80 FFFFFFC0 00 13 28 02 00 75 10 02 08 76 09 02 77 02
   02 0C 73 65 72 69 61 6C 69 7A 61 62 6C 65 07 07
   79 02 FFFFFF81 FFFFFF80 FFFFFF88 02 7A 01 05 52 69 67 68 74 10 02
   08 7B 06 08 01 02 FFFFFF84 FFFFFF81 FFFFFF80 FFFFFF88 02 7C 13 03 7B 7D
   19 10 02 63 7E 09 02 7F 64 02 06 4F 62 6A 65 63
   74 08 06 25 7B FFFFFF84 00 FFFFFF81 01 14 01 7A 08 09 FFFFFF81 03
   7B FFFFFF81 FFFFFF80 FFFFFF84 40 FFFFFF81 04 01 05 61 70 70 6C 79 15 06
   FFFFFF81 05 FFFFFF81 08 FFFFFF81 0A 14 04 FFFFFF81 06 FFFFFF81 0B 10 06 08 00
   FFFFFF81 07 FFFFFF81 09 10 03 0C FFFFFF81 08 04 09 0E FFFFFF81 02 FFFFFF84 FFFFFF80
   FFFFFF80 FFFFFFC2 00 0F 10 03 0C FFFFFF81 0A 04 09 18 FFFFFF81 02 FFFFFF84 FFFFFF80
   FFFFFF80 FFFFFFC2 00 0F 08 07 20 FFFFFF81 02 FFFFFFC0 00 FFFFFF81 09 08 09 FFFFFF81
   0D 7B FFFFFF81 FFFFFF80 FFFFFF84 40 FFFFFF81 0E 01 07 75 6E 61 70 70 6C
   79 15 06 FFFFFF81 0F FFFFFF81 19 FFFFFF81 14 14 04 FFFFFF81 10 FFFFFF81 15 10
   05 08 FFFFFF81 11 FFFFFF81 13 09 03 FFFFFF81 12 02 02 04 53 6F 6D
   65 10 03 0C FFFFFF81 14 04 09 18 FFFFFF81 0C FFFFFF84 FFFFFF80 FFFFFF80 FFFFFFC2 00
   0F 08 08 FFFFFF81 16 FFFFFF81 0C FFFFFFC0 00 FFFFFF81 17 01 03 78 24 30
   10 06 08 00 FFFFFF81 18 FFFFFF81 13 10 03 0C FFFFFF81 19 04 09 0E
   FFFFFF81 0C FFFFFF84 FFFFFF80 FFFFFF80 FFFFFFC2 00 0F 
  minor version: 0
  major version: 49
  Constant pool:
Asciz	SourceFile;
Asciz	Either.scala;
Asciz	b;
Asciz	Ljava/lang/Object;;
Asciz	TB;;
Asciz	Signature;
Asciz	<init>;
Asciz	(Ljava/lang/Object;)V;
Asciz	Code;
Asciz	LineNumberTable;
Asciz	scala/Right;
class	scala/Right
NameAndType	b:Ljava/lang/Object;
Field	scala/Right.b:Ljava/lang/Object;
Asciz	scala/Either;
class	scala/Either
Asciz	()V;
NameAndType	"<init>":()V
Method	scala/Either."<init>":()V
Asciz	scala/Product$class;
class	scala/Product$class
Asciz	$init$;
Asciz	(Lscala/Product;)V;
NameAndType	$init$:(Lscala/Product;)V
Method	scala/Product$class.$init$:(Lscala/Product;)V
Asciz	this;
Asciz	Lscala/Right;;
Asciz	LocalVariableTable;
Asciz	(TB;)V;
Asciz	gd2$1;
Asciz	(Ljava/lang/Object;)Z;
Asciz	java/lang/Number;
class	java/lang/Number
Asciz	java/lang/Character;
class	java/lang/Character
Asciz	scala/runtime/BoxesRunTime;
class	scala/runtime/BoxesRunTime
Asciz	equals2;
Asciz	(Ljava/lang/Object;Ljava/lang/Object;)Z;
NameAndType	equals2:(Ljava/lang/Object;Ljava/lang/Object;)Z
Method	scala/runtime/BoxesRunTime.equals2:(Ljava/lang/Object;Ljava/lang/Object;)Z
Asciz	java/lang/Object;
class	java/lang/Object
Asciz	equals;
NameAndType	equals:(Ljava/lang/Object;)Z
Method	java/lang/Object.equals:(Ljava/lang/Object;)Z
Asciz	y0;
Asciz	canEqual;
Asciz	productElement;
Asciz	(I)Ljava/lang/Object;;
Asciz	scala/MatchError;
class	scala/MatchError
Asciz	boxToInteger;
Asciz	(I)Ljava/lang/Integer;;
NameAndType	boxToInteger:(I)Ljava/lang/Integer;
Method	scala/runtime/BoxesRunTime.boxToInteger:(I)Ljava/lang/Integer;
Asciz	toString;
Asciz	()Ljava/lang/String;;
NameAndType	toString:()Ljava/lang/String;
Method	java/lang/Object.toString:()Ljava/lang/String;
Asciz	(Ljava/lang/String;)V;
NameAndType	"<init>":(Ljava/lang/String;)V
Method	scala/MatchError."<init>":(Ljava/lang/String;)V
Asciz	java/lang/IndexOutOfBoundsException;
class	java/lang/IndexOutOfBoundsException
Method	java/lang/IndexOutOfBoundsException."<init>":(Ljava/lang/String;)V
Asciz	productArity;
Asciz	()I;
Asciz	productPrefix;
Asciz	Right;
String	Right
NameAndType	gd2$1:(Ljava/lang/Object;)Z
Method	scala/Right.gd2$1:(Ljava/lang/Object;)Z
Asciz	temp26;
Asciz	temp27;
Asciz	scala/runtime/ScalaRunTime$;
class	scala/runtime/ScalaRunTime$
Asciz	MODULE$;
Asciz	Lscala/runtime/ScalaRunTime$;;
NameAndType	MODULE$:Lscala/runtime/ScalaRunTime$;
Field	scala/runtime/ScalaRunTime$.MODULE$:Lscala/runtime/ScalaRunTime$;
Asciz	_toString;
Asciz	(Lscala/Product;)Ljava/lang/String;;
NameAndType	_toString:(Lscala/Product;)Ljava/lang/String;
Method	scala/runtime/ScalaRunTime$._toString:(Lscala/Product;)Ljava/lang/String;
Asciz	hashCode;
Asciz	_hashCode;
Asciz	(Lscala/Product;)I;
NameAndType	_hashCode:(Lscala/Product;)I
Method	scala/runtime/ScalaRunTime$._hashCode:(Lscala/Product;)I
Asciz	copy;
Asciz	(Ljava/lang/Object;)Lscala/Right;;
NameAndType	"<init>":(Ljava/lang/Object;)V
Method	scala/Right."<init>":(Ljava/lang/Object;)V
Asciz	isRight;
Asciz	()Z;
Asciz	isLeft;
Asciz	()Ljava/lang/Object;;
Asciz	()TB;;
Asciz	copy$default$1;
NameAndType	b:()Ljava/lang/Object;
Method	scala/Right.b:()Ljava/lang/Object;
Asciz	productElements;
Asciz	()Lscala/collection/Iterator;;
Asciz	(Lscala/Product;)Lscala/collection/Iterator;;
NameAndType	productElements:(Lscala/Product;)Lscala/collection/Iterator;
Method	scala/Product$class.productElements:(Lscala/Product;)Lscala/collection/Iterator;
Asciz	Deprecated;
Asciz	productIterator;
NameAndType	productIterator:(Lscala/Product;)Lscala/collection/Iterator;
Method	scala/Product$class.productIterator:(Lscala/Product;)Lscala/collection/Iterator;
Asciz	<A:Ljava/lang/Object;B:Ljava/lang/Object;>Lscala/Either<TA;TB;>;Lscala/ScalaObject;Lscala/Product;;
Asciz	ScalaSig;
Asciz	scala/ScalaObject;
class	scala/ScalaObject
Asciz	scala/Product;
class	scala/Product
Asciz	java/io/Serializable;
class	java/io/Serializable

{
public final java.lang.Object b;
  Signature: Ljava/lang/Object;
  Signature: length = 0x2
   00 05 

public scala.Right(java.lang.Object);
  Signature: (Ljava/lang/Object;)V
  Code:
   Stack=2, Locals=2, Args_size=2
	aload_0
	aload_1
	putfield	Field b:Ljava/lang/Object;
	aload_0
	invokespecial	Method scala/Either."<init>":()V
	aload_0
	invokestatic	Method scala/Product$class.$init$:(Lscala/Product;)V
	return
  Labels:
  LocalVariableTable: 
   Start  Length  Slot  Name   Signature
   0      14      0    this       Lscala/Right;
   0      14      1    b       Ljava/lang/Object;

  Signature: length = 0x2
   00 1D 

private final boolean gd2$1(java.lang.Object);
  Signature: (Ljava/lang/Object;)Z
  Code:
   Stack=2, Locals=3, Args_size=2
	aload_0
	getfield	Field b:Ljava/lang/Object;
	astore_2
	aload_1
	aload_2
	if_acmpne	l1 // aload_1
	iconst_1
	goto	l2 // ifeq
l1	aload_1
	ifnonnull	l3 // aload_1
	iconst_0
	goto	l2 // ifeq
l3	aload_1
	instanceof	class java/lang/Number
	ifne	l4 // aload_1
	aload_1
	instanceof	class java/lang/Character
	ifeq	l5 // aload_1
l4	aload_1
	aload_2
	invokestatic	Method scala/runtime/BoxesRunTime.equals2:(Ljava/lang/Object;Ljava/lang/Object;)Z
	goto	l2 // ifeq
l5	aload_1
	aload_2
	invokevirtual	Method java/lang/Object.equals:(Ljava/lang/Object;)Z
l2	ifeq	l6 // iconst_0
	iconst_1
	goto	l7 // ireturn
l6	iconst_0
l7	ireturn
  Labels:
   	l1 = 14 // aload_1
   	l3 = 22 // aload_1
   	l4 = 36 // aload_1
   	l5 = 44 // aload_1
   	l2 = 49 // ifeq
   	l6 = 56 // iconst_0
   	l7 = 57 // ireturn
  LocalVariableTable: 
   Start  Length  Slot  Name   Signature
   0      58      0    this       Lscala/Right;
   10      42      2    y0       Ljava/lang/Object;


public boolean canEqual(java.lang.Object);
  Signature: (Ljava/lang/Object;)Z
  Code:
   Stack=1, Locals=2, Args_size=2
	aload_1
	instanceof	class scala/Right
	ireturn
  Labels:

public java.lang.Object productElement(int);
  Signature: (I)Ljava/lang/Object;
  Code:
   Stack=3, Locals=2, Args_size=2
	iload_1
	iconst_0
	if_icmpne	l1 // iconst_1
	iconst_1
	ifeq	l2 // new
	aload_0
	getfield	Field b:Ljava/lang/Object;
	areturn
l2	new	class scala/MatchError
	dup
	iload_1
	invokestatic	Method scala/runtime/BoxesRunTime.boxToInteger:(I)Ljava/lang/Integer;
	invokevirtual	Method java/lang/Object.toString:()Ljava/lang/String;
	invokespecial	Method scala/MatchError."<init>":(Ljava/lang/String;)V
	athrow
l1	iconst_1
	ifeq	l3 // new
	new	class java/lang/IndexOutOfBoundsException
	dup
	iload_1
	invokestatic	Method scala/runtime/BoxesRunTime.boxToInteger:(I)Ljava/lang/Integer;
	invokevirtual	Method java/lang/Object.toString:()Ljava/lang/String;
	invokespecial	Method java/lang/IndexOutOfBoundsException."<init>":(Ljava/lang/String;)V
	athrow
l3	new	class scala/MatchError
	dup
	iload_1
	invokestatic	Method scala/runtime/BoxesRunTime.boxToInteger:(I)Ljava/lang/Integer;
	invokevirtual	Method java/lang/Object.toString:()Ljava/lang/String;
	invokespecial	Method scala/MatchError."<init>":(Ljava/lang/String;)V
	athrow
  Labels:
   	l2 = 14 // new
   	l1 = 29 // iconst_1
   	l3 = 48 // new

public int productArity();
  Signature: ()I
  Code:
   Stack=1, Locals=1, Args_size=1
	iconst_1
	ireturn
  Labels:

public java.lang.String productPrefix();
  Signature: ()Ljava/lang/String;
  Code:
   Stack=1, Locals=1, Args_size=1
	ldc	String Right
	areturn
  Labels:

public boolean equals(java.lang.Object);
  Signature: (Ljava/lang/Object;)Z
  Code:
   Stack=3, Locals=4, Args_size=2
	aload_0
	aload_1
	if_acmpeq	l1 // iconst_1
	aload_1
	instanceof	class scala/Right
	ifeq	l2 // iconst_1
	aload_1
	checkcast	class scala/Right
	astore_2
	aload_2
	getfield	Field b:Ljava/lang/Object;
	astore_3
	aload_0
	aload_3
	invokespecial	Method gd2$1:(Ljava/lang/Object;)Z
	ifeq	l3 // iconst_1
	aload_0
	instanceof	class scala/Right
	goto	l4 // ifeq
l3	iconst_1
	ifeq	l5 // new
	iconst_0
	goto	l4 // ifeq
l5	new	class scala/MatchError
	dup
	aload_1
	invokevirtual	Method java/lang/Object.toString:()Ljava/lang/String;
	invokespecial	Method scala/MatchError."<init>":(Ljava/lang/String;)V
	athrow
l2	iconst_1
	ifeq	l6 // new
	iconst_0
l4	ifeq	l7 // iconst_0
l1	iconst_1
	goto	l8 // ireturn
l7	iconst_0
l8	ireturn
l6	new	class scala/MatchError
	dup
	aload_1
	invokevirtual	Method java/lang/Object.toString:()Ljava/lang/String;
	invokespecial	Method scala/MatchError."<init>":(Ljava/lang/String;)V
	athrow
  Labels:
   	l3 = 37 // iconst_1
   	l5 = 45 // new
   	l2 = 57 // iconst_1
   	l4 = 62 // ifeq
   	l1 = 65 // iconst_1
   	l7 = 69 // iconst_0
   	l8 = 70 // ireturn
   	l6 = 71 // new
  LocalVariableTable: 
   Start  Length  Slot  Name   Signature
   0      83      0    this       Lscala/Right;
   17      40      2    temp26       Lscala/Right;
   22      35      3    temp27       Ljava/lang/Object;


public java.lang.String toString();
  Signature: ()Ljava/lang/String;
  Code:
   Stack=2, Locals=1, Args_size=1
	getstatic	Field scala/runtime/ScalaRunTime$.MODULE$:Lscala/runtime/ScalaRunTime$;
	aload_0
	invokevirtual	Method scala/runtime/ScalaRunTime$._toString:(Lscala/Product;)Ljava/lang/String;
	areturn
  Labels:

public int hashCode();
  Signature: ()I
  Code:
   Stack=2, Locals=1, Args_size=1
	getstatic	Field scala/runtime/ScalaRunTime$.MODULE$:Lscala/runtime/ScalaRunTime$;
	aload_0
	invokevirtual	Method scala/runtime/ScalaRunTime$._hashCode:(Lscala/Product;)I
	ireturn
  Labels:

public scala.Right copy(java.lang.Object);
  Signature: (Ljava/lang/Object;)Lscala/Right;
  Code:
   Stack=3, Locals=2, Args_size=2
	new	class scala/Right
	dup
	aload_1
	invokespecial	Method "<init>":(Ljava/lang/Object;)V
	areturn
  Labels:
  LocalVariableTable: 
   Start  Length  Slot  Name   Signature
   0      9      0    this       Lscala/Right;
   0      9      1    b       Ljava/lang/Object;


public boolean isRight();
  Signature: ()Z
  Code:
   Stack=1, Locals=1, Args_size=1
	iconst_1
	ireturn
  Labels:

public boolean isLeft();
  Signature: ()Z
  Code:
   Stack=1, Locals=1, Args_size=1
	iconst_0
	ireturn
  Labels:

public java.lang.Object b();
  Signature: ()Ljava/lang/Object;
  Code:
   Stack=1, Locals=1, Args_size=1
	aload_0
	getfield	Field b:Ljava/lang/Object;
	areturn
  Labels:
  Signature: length = 0x2
   00 63 

public java.lang.Object copy$default$1();
  Signature: ()Ljava/lang/Object;
  Code:
   Stack=1, Locals=1, Args_size=1
	aload_0
	invokevirtual	Method b:()Ljava/lang/Object;
	areturn
  Labels:

public scala.collection.Iterator productElements();
  Signature: ()Lscala/collection/Iterator;
  Code:
   Stack=1, Locals=1, Args_size=1
	aload_0
	invokestatic	Method scala/Product$class.productElements:(Lscala/Product;)Lscala/collection/Iterator;
	areturn
  Labels:
  Deprecated: true

public scala.collection.Iterator productIterator();
  Signature: ()Lscala/collection/Iterator;
  Code:
   Stack=1, Locals=1, Args_size=1
	aload_0
	invokestatic	Method scala/Product$class.productIterator:(Lscala/Product;)Lscala/collection/Iterator;
	areturn
  Labels:

}

