Compiled from "Either.scala"
public final class scala.Right$ extends java.lang.Object implements scala.ScalaObject
  SourceFile: "Either.scala"
  Scala: length = 0x
   
  minor version: 0
  major version: 49
  Constant pool:
Asciz	SourceFile;
Asciz	Either.scala;
Asciz	Scala;
Asciz	MODULE$;
Asciz	Lscala/Right$;;
Asciz	<clinit>;
Asciz	()V;
Asciz	Code;
Asciz	scala/Right$;
class	scala/Right$
Asciz	<init>;
NameAndType	"<init>":()V
Method	scala/Right$."<init>":()V
Asciz	unapply;
Asciz	(Lscala/Right;)Lscala/Option;;
Asciz	LineNumberTable;
Asciz	java/lang/Object;
class	java/lang/Object
Asciz	equals;
Asciz	(Ljava/lang/Object;)Z;
NameAndType	equals:(Ljava/lang/Object;)Z
Method	java/lang/Object.equals:(Ljava/lang/Object;)Z
Asciz	scala/None$;
class	scala/None$
Asciz	Lscala/None$;;
NameAndType	MODULE$:Lscala/None$;
Field	scala/None$.MODULE$:Lscala/None$;
Asciz	scala/Some;
class	scala/Some
Asciz	scala/Right;
class	scala/Right
Asciz	b;
Asciz	Ljava/lang/Object;;
NameAndType	b:Ljava/lang/Object;
Field	scala/Right.b:Ljava/lang/Object;
Asciz	(Ljava/lang/Object;)V;
NameAndType	"<init>":(Ljava/lang/Object;)V
Method	scala/Some."<init>":(Ljava/lang/Object;)V
Asciz	this;
Asciz	x$0;
Asciz	Lscala/Right;;
Asciz	LocalVariableTable;
Asciz	apply;
Asciz	(Ljava/lang/Object;)Lscala/Right;;
Method	scala/Right."<init>":(Ljava/lang/Object;)V
Method	java/lang/Object."<init>":()V
NameAndType	MODULE$:Lscala/Right$;
Field	scala/Right$.MODULE$:Lscala/Right$;
Asciz	scala/ScalaObject;
class	scala/ScalaObject

{
public static final scala.Right$ MODULE$;
  Signature: Lscala/Right$;

public static {};
  Signature: ()V
  Code:
   Stack=1, Locals=0, Args_size=0
	new	class scala/Right$
	invokespecial	Method "<init>":()V
	return
  Labels:

public scala.Option unapply(scala.Right);
  Signature: (Lscala/Right;)Lscala/Option;
  Code:
   Stack=3, Locals=2, Args_size=2
	aload_1
	dup
	pop
	ifnull	l1 // getstatic
	aload_1
	aconst_null
	invokevirtual	Method java/lang/Object.equals:(Ljava/lang/Object;)Z
	ifeq	l2 // new
l1	getstatic	Field scala/None$.MODULE$:Lscala/None$;
	goto	l3 // areturn
l2	new	class scala/Some
	dup
	aload_1
	getfield	Field scala/Right.b:Ljava/lang/Object;
	invokespecial	Method scala/Some."<init>":(Ljava/lang/Object;)V
l3	areturn
  Labels:
   	l1 = 14 // getstatic
   	l2 = 20 // new
   	l3 = 31 // areturn
  LocalVariableTable: 
   Start  Length  Slot  Name   Signature
   0      32      0    this       Lscala/Right$;
   0      32      1    x$0       Lscala/Right;


public scala.Right apply(java.lang.Object);
  Signature: (Ljava/lang/Object;)Lscala/Right;
  Code:
   Stack=3, Locals=2, Args_size=2
	new	class scala/Right
	dup
	aload_1
	invokespecial	Method scala/Right."<init>":(Ljava/lang/Object;)V
	areturn
  Labels:
  LocalVariableTable: 
   Start  Length  Slot  Name   Signature
   0      9      0    this       Lscala/Right$;
   0      9      1    b       Ljava/lang/Object;


private scala.Right$();
  Signature: ()V
  Code:
   Stack=1, Locals=1, Args_size=1
	aload_0
	invokespecial	Method java/lang/Object."<init>":()V
	aload_0
	putstatic	Field MODULE$:Lscala/Right$;
	return
  Labels:

}

