Compiled from "StringBuilder.scala"
public final class scala.StringBuilder$ extends java.lang.Object
  Scala: length = 0x
   
  SourceFile: "StringBuilder.scala"
  minor version: 0
  major version: 49
  Constant pool:
int	55296;
int	56319;
int	56320;
int	57343;
class	java/lang/Object
class	scala/Math$
class	scala/StringBuilder
class	scala/StringBuilder$
class	scala/compat/Platform$
Field	scala/Math$.MODULE$:Lscala/Math$;
Field	scala/StringBuilder$.MAX_HIGH_SURROGATE:C
Field	scala/StringBuilder$.MAX_LOW_SURROGATE:C
Field	scala/StringBuilder$.MIN_HIGH_SURROGATE:C
Field	scala/StringBuilder$.MIN_LOW_SURROGATE:C
Field	scala/StringBuilder$.MODULE$:Lscala/StringBuilder$;
Field	scala/StringBuilder$.scala$StringBuilder$$MAX_SURROGATE:C
Field	scala/StringBuilder$.scala$StringBuilder$$MIN_SURROGATE:C
Field	scala/compat/Platform$.MODULE$:Lscala/compat/Platform$;
Method	java/lang/Object."<init>":()V
Method	scala/Math$.min:(II)I
Method	scala/StringBuilder$."<init>":()V
Method	scala/StringBuilder$.MAX_LOW_SURROGATE:()C
Method	scala/StringBuilder$.MIN_HIGH_SURROGATE:()C
Method	scala/compat/Platform$.arraycopy:(Ljava/lang/Object;ILjava/lang/Object;II)V
NameAndType	"<init>":()V
NameAndType	MAX_HIGH_SURROGATE:C
NameAndType	MAX_LOW_SURROGATE:()C
NameAndType	MAX_LOW_SURROGATE:C
NameAndType	MIN_HIGH_SURROGATE:()C
NameAndType	MIN_HIGH_SURROGATE:C
NameAndType	MIN_LOW_SURROGATE:C
NameAndType	MODULE$:Lscala/Math$;
NameAndType	MODULE$:Lscala/StringBuilder$;
NameAndType	MODULE$:Lscala/compat/Platform$;
NameAndType	arraycopy:(Ljava/lang/Object;ILjava/lang/Object;II)V
NameAndType	min:(II)I
NameAndType	scala$StringBuilder$$MAX_SURROGATE:C
NameAndType	scala$StringBuilder$$MIN_SURROGATE:C
Asciz	()C;
Asciz	()V;
Asciz	(II)I;
Asciz	(Ljava/lang/Object;ILjava/lang/Object;II)V;
Asciz	([CI)[C;
Asciz	<clinit>;
Asciz	<init>;
Asciz	C;
Asciz	Code;
Asciz	I;
Asciz	LineNumberTable;
Asciz	LocalVariableTable;
Asciz	Lscala/Math$;;
Asciz	Lscala/StringBuilder$;;
Asciz	Lscala/compat/Platform$;;
Asciz	MAX_HIGH_SURROGATE;
Asciz	MAX_LOW_SURROGATE;
Asciz	MIN_HIGH_SURROGATE;
Asciz	MIN_LOW_SURROGATE;
Asciz	MODULE$;
Asciz	Scala;
Asciz	SourceFile;
Asciz	StringBuilder.scala;
Asciz	[C;
Asciz	arraycopy;
Asciz	dest;
Asciz	java/lang/Object;
Asciz	min;
Asciz	newLength;
Asciz	scala$StringBuilder$$MAX_SURROGATE;
Asciz	scala$StringBuilder$$MIN_SURROGATE;
Asciz	scala$StringBuilder$$copyOf;
Asciz	scala/Math$;
Asciz	scala/StringBuilder;
Asciz	scala/StringBuilder$;
Asciz	scala/compat/Platform$;
Asciz	src;
Asciz	this;

{
public static final scala.StringBuilder$ MODULE$;
  Signature: Lscala/StringBuilder$;

private final char scala$StringBuilder$$MAX_SURROGATE;
  Signature: C

private final char scala$StringBuilder$$MIN_SURROGATE;
  Signature: C

private final char MAX_LOW_SURROGATE;
  Signature: C

private final char MIN_LOW_SURROGATE;
  Signature: C

private final char MAX_HIGH_SURROGATE;
  Signature: C

private final char MIN_HIGH_SURROGATE;
  Signature: C

public static {};
  Signature: ()V
  Code:
   Stack=1, Locals=0, Args_size=0
	new	class scala/StringBuilder$
	invokespecial	Method "<init>":()V
	return
  Labels:

public scala.StringBuilder$();
  Signature: ()V
  Code:
   Stack=2, Locals=1, Args_size=1
	aload_0
	ldc	int 55296
	putfield	Field MIN_HIGH_SURROGATE:C
	aload_0
	ldc	int 56319
	putfield	Field MAX_HIGH_SURROGATE:C
	aload_0
	ldc	int 56320
	putfield	Field MIN_LOW_SURROGATE:C
	aload_0
	ldc	int 57343
	putfield	Field MAX_LOW_SURROGATE:C
	aload_0
	invokespecial	Method java/lang/Object."<init>":()V
	aload_0
	putstatic	Field MODULE$:Lscala/StringBuilder$;
	aload_0
	aload_0
	invokespecial	Method MIN_HIGH_SURROGATE:()C
	putfield	Field scala$StringBuilder$$MIN_SURROGATE:C
	aload_0
	aload_0
	invokespecial	Method MAX_LOW_SURROGATE:()C
	putfield	Field scala$StringBuilder$$MAX_SURROGATE:C
	return
  Labels:

public final char[] scala$StringBuilder$$copyOf(char[], int);
  Signature: ([CI)[C
  Code:
   Stack=8, Locals=4, Args_size=3
	iload_2
	newarray char
	astore_3
	getstatic	Field scala/compat/Platform$.MODULE$:Lscala/compat/Platform$;
	aload_1
	iconst_0
	aload_3
	iconst_0
	getstatic	Field scala/Math$.MODULE$:Lscala/Math$;
	aload_1
	arraylength
	iload_2
	invokevirtual	Method scala/Math$.min:(II)I
	invokevirtual	Method scala/compat/Platform$.arraycopy:(Ljava/lang/Object;ILjava/lang/Object;II)V
	aload_3
	areturn
  Labels:
  LocalVariableTable: 
   Start  Length  Slot  Name   Signature
   0      25      0    this       Lscala/StringBuilder$;
   0      25      1    src       [C
   0      25      2    newLength       I
   0      24      3    dest       [C


private char MAX_LOW_SURROGATE();
  Signature: ()C
  Code:
   Stack=1, Locals=1, Args_size=1
	aload_0
	getfield	Field MAX_LOW_SURROGATE:C
	ireturn
  Labels:

private char MIN_HIGH_SURROGATE();
  Signature: ()C
  Code:
   Stack=1, Locals=1, Args_size=1
	aload_0
	getfield	Field MIN_HIGH_SURROGATE:C
	ireturn
  Labels:

}

