Compiled from "StringBuilder.scala"
public final class scala.StringBuilder extends java.lang.Object implements java.io.Serializable,scala.Function1
  ScalaSig: length = 0x8C4
   04 01 FFFFFF82 1E 06 08 01 02 FFFFFF84 FFFFFF80 FFFFFF80 FFFFFF80 02 05 02 0D
   53 74 72 69 6E 67 42 75 69 6C 64 65 72 0A 01 03
   01 05 73 63 61 6C 61 03 00 13 04 00 06 0E 18 10
   02 07 0C 0D 01 08 0A 02 09 0A 01 04 6C 61 6E 67
   0A 01 0B 01 04 6A 61 76 61 09 02 0D 08 02 06 4F
   62 6A 65 63 74 10 04 0F 10 12 15 0D 01 02 09 02
   11 02 02 09 46 75 6E 63 74 69 6F 6E 31 10 02 0F
   13 09 02 14 02 02 03 49 6E 74 10 02 0F 16 09 02
   17 02 02 04 43 68 61 72 10 02 0F 19 09 02 1A 02
   02 0B 53 63 61 6C 61 4F 62 6A 65 63 74 08 08 1C
   00 FFFFFF82 FFFFFF80 FFFFFFA0 FFFFFF80 04 12 01 0C 69 6E 69 74 43 61 70
   61 63 69 74 79 08 08 1E 00 FFFFFF82 FFFFFFC2 FFFFFF80 FFFFFF84 04 1F 01
   09 69 6E 69 74 56 61 6C 75 65 15 01 20 10 02 21
   24 0E 02 0F 22 09 02 23 02 01 06 50 72 65 64 65
   66 09 02 25 26 02 06 53 74 72 69 6E 67 0A 02 23
   02 08 08 28 00 FFFFFF82 FFFFFF80 FFFFFFA0 FFFFFF80 04 20 01 0A 69 6E 69
   74 56 61 6C 75 65 20 08 05 2A 00 FFFFFF84 00 2B 01 06
   3C 69 6E 69 74 3E 14 03 2C 12 20 10 02 0F 00 08
   07 2E 00 FFFFFFC0 FFFFFF80 FFFFFF84 04 2F 01 05 76 61 6C 75 65 15
   01 30 10 03 0F 31 15 09 02 32 02 02 05 41 72 72
   61 79 08 07 34 00 FFFFFFC0 FFFFFF80 FFFFFF84 04 35 01 09 76 61 6C
   75 65 5F 24 65 71 14 02 36 30 10 02 0F 37 09 02
   38 02 02 04 55 6E 69 74 08 06 3A 00 FFFFFFA0 FFFFFFA0 04 30
   01 06 76 61 6C 75 65 20 08 07 3C 00 FFFFFFC0 FFFFFF80 FFFFFF84 04
   3D 01 05 63 6F 75 6E 74 15 01 12 08 07 3F 00 FFFFFFC0
   FFFFFF80 FFFFFF84 04 40 01 09 63 6F 75 6E 74 5F 24 65 71 14
   02 36 12 08 06 42 00 FFFFFFA0 FFFFFFA0 04 12 01 06 63 6F 75
   6E 74 20 08 05 2A 00 FFFFFF84 00 44 14 01 2C 08 05 2A
   00 FFFFFF84 00 46 14 02 2C 12 08 05 2A 00 FFFFFF84 00 48 14
   02 2C 20 08 05 4A 00 FFFFFF84 00 2F 01 07 74 6F 41 72
   72 61 79 08 05 4C 00 FFFFFF84 00 3D 01 06 6C 65 6E 67
   74 68 08 05 4E 00 FFFFFF84 00 40 01 0A 6C 65 6E 67 74
   68 5F 24 65 71 08 05 50 00 FFFFFF84 00 40 01 09 73 65
   74 4C 65 6E 67 74 68 08 05 52 00 FFFFFF84 00 3D 01 08
   63 61 70 61 63 69 74 79 08 05 54 00 FFFFFF84 00 40 01
   0C 63 61 70 61 63 69 74 79 5F 24 65 71 08 05 56
   00 FFFFFF84 00 40 01 0E 65 6E 73 75 72 65 43 61 70 61
   63 69 74 79 08 05 58 00 FFFFFF84 04 40 01 0E 65 78 70
   61 6E 64 43 61 70 61 63 69 74 79 08 05 5A 00 FFFFFF84
   00 5B 01 06 63 68 61 72 41 74 14 02 15 12 08 05
   5D 00 FFFFFF84 00 5B 01 05 61 70 70 6C 79 08 05 5F 00
   FFFFFF84 00 46 01 0C 64 65 6C 65 74 65 43 68 61 72 41
   74 08 05 61 00 FFFFFF84 00 62 01 09 73 65 74 43 68 61
   72 41 74 14 03 36 12 15 08 05 64 00 FFFFFF84 00 62 01
   06 75 70 64 61 74 65 08 05 66 00 FFFFFF84 00 67 01 09
   73 75 62 73 74 72 69 6E 67 14 02 20 12 08 05 66
   00 FFFFFF84 00 69 14 03 20 12 12 08 05 6B 00 FFFFFF84 00 6C
   01 06 61 70 70 65 6E 64 14 02 2C 6D 10 02 0F 6E
   09 02 6F 02 02 03 41 6E 79 08 05 6B 00 FFFFFF84 00 48
   08 05 6B 00 FFFFFF84 00 72 14 02 2C 2C 08 05 6B 00 FFFFFF84
   00 74 14 02 2C 75 10 03 0F 76 15 09 02 77 02 02
   03 53 65 71 08 05 6B 00 FFFFFF84 00 79 14 02 2C 30 08
   05 6B 00 FFFFFF84 00 7B 14 04 2C 30 12 12 08 05 6B 00
   FFFFFF84 00 7D 14 02 2C 7E 10 02 0F 7F 09 03 FFFFFF81 00 02
   02 07 42 6F 6F 6C 65 61 6E 08 06 6B 00 FFFFFF84 00 FFFFFF81
   02 14 03 2C FFFFFF81 03 10 03 0F FFFFFF81 04 09 03 FFFFFF81 05 02
   02 04 42 79 74 65 08 06 6B 00 FFFFFF84 00 FFFFFF81 07 14 02
   2C 15 08 06 6B 00 FFFFFF84 00 FFFFFF81 09 14 03 2C FFFFFF81 0A 10
   03 0F FFFFFF81 0B 09 03 FFFFFF81 0C 02 02 05 53 68 6F 72 74
   08 05 6B 00 FFFFFF84 00 46 08 06 6B 00 FFFFFF84 00 FFFFFF81 0F 14
   03 2C FFFFFF81 10 10 03 0F FFFFFF81 11 09 03 FFFFFF81 12 02 02 04
   4C 6F 6E 67 08 06 6B 00 FFFFFF84 00 FFFFFF81 14 14 03 2C FFFFFF81
   15 10 03 0F FFFFFF81 16 09 03 FFFFFF81 17 02 02 05 46 6C 6F
   61 74 08 06 6B 00 FFFFFF84 00 FFFFFF81 19 14 03 2C FFFFFF81 1A 10
   03 0F FFFFFF81 1B 09 03 FFFFFF81 1C 02 02 06 44 6F 75 62 6C
   65 08 07 FFFFFF81 1E 00 FFFFFF84 00 FFFFFF81 1F 01 06 64 65 6C 65
   74 65 14 03 2C 12 12 08 07 FFFFFF81 21 00 FFFFFF84 00 FFFFFF81 22
   01 07 72 65 70 6C 61 63 65 14 04 36 12 12 20 08
   07 FFFFFF81 24 00 FFFFFF84 00 FFFFFF81 25 01 06 69 6E 73 65 72 74
   14 05 2C 12 30 12 12 08 07 FFFFFF81 24 00 FFFFFF84 00 FFFFFF81 27
   14 03 2C 12 6D 08 06 FFFFFF81 24 00 FFFFFF84 00 2B 08 07 FFFFFF81
   24 00 FFFFFF84 00 FFFFFF81 2A 14 03 2C 12 75 08 07 FFFFFF81 24 00
   FFFFFF84 00 FFFFFF81 2C 14 03 2C 12 30 08 07 FFFFFF81 24 00 FFFFFF84 00
   FFFFFF81 2E 14 03 2C 12 7E 08 07 FFFFFF81 24 00 FFFFFF84 00 FFFFFF81 30
   14 04 2C 12 FFFFFF81 03 08 07 FFFFFF81 24 00 FFFFFF84 00 FFFFFF81 32 14
   03 2C 12 15 08 07 FFFFFF81 24 00 FFFFFF84 00 FFFFFF81 34 14 04 2C
   12 FFFFFF81 0A 08 07 FFFFFF81 24 00 FFFFFF84 00 FFFFFF81 1F 08 07 FFFFFF81 24
   00 FFFFFF84 00 FFFFFF81 37 14 04 2C 12 FFFFFF81 10 08 07 FFFFFF81 24 00
   FFFFFF84 00 FFFFFF81 39 14 04 2C 12 FFFFFF81 15 08 07 FFFFFF81 24 00 FFFFFF84
   00 FFFFFF81 3B 14 04 2C 12 FFFFFF81 1A 08 07 FFFFFF81 3D 00 FFFFFF84 00
   FFFFFF81 3E 01 07 69 6E 64 65 78 4F 66 14 02 12 20 08
   07 FFFFFF81 3D 00 FFFFFF84 00 FFFFFF81 40 14 03 12 20 12 08 07 FFFFFF81
   42 00 FFFFFF84 00 FFFFFF81 3E 01 0B 6C 61 73 74 49 6E 64 65
   78 4F 66 08 07 FFFFFF81 42 00 FFFFFF84 00 FFFFFF81 40 08 06 FFFFFF81 45
   00 FFFFFF84 00 44 01 07 72 65 76 65 72 73 65 08 07 FFFFFF81
   47 00 FFFFFF84 20 FFFFFF81 48 01 08 74 6F 53 74 72 69 6E 67
   14 01 20 08 07 FFFFFF81 4A 00 FFFFFF84 04 FFFFFF81 4B 01 0B 77 72
   69 74 65 4F 62 6A 65 63 74 14 03 36 FFFFFF81 4C 10 04
   FFFFFF81 4D FFFFFF81 50 0D 02 FFFFFF81 4E 0A 03 FFFFFF81 4F 0A 01 02 69
   6F 09 04 FFFFFF81 51 FFFFFF81 4E 02 12 4F 62 6A 65 63 74 4F
   75 74 70 75 74 53 74 72 65 61 6D 28 06 FFFFFF81 49 FFFFFF81
   53 FFFFFF81 56 10 03 0F FFFFFF81 54 09 03 FFFFFF81 55 02 02 06 74
   68 72 6F 77 73 23 02 FFFFFF81 58 23 02 FFFFFF81 58 10 04 FFFFFF81
   4D FFFFFF81 59 09 04 FFFFFF81 5A FFFFFF81 4E 02 0B 49 4F 45 78 63
   65 70 74 69 6F 6E 08 07 FFFFFF81 5C 00 FFFFFF84 04 FFFFFF81 5D 01
   0A 72 65 61 64 4F 62 6A 65 63 74 14 03 36 FFFFFF81 5E
   10 04 FFFFFF81 4D FFFFFF81 5F 09 04 FFFFFF81 60 FFFFFF81 4E 02 11 4F 62
   6A 65 63 74 49 6E 70 75 74 53 74 72 65 61 6D 28
   06 FFFFFF81 5B FFFFFF81 53 FFFFFF81 62 23 02 FFFFFF81 58 28 05 00 FFFFFF81 64
   FFFFFF81 67 10 03 0F FFFFFF81 65 09 03 FFFFFF81 66 02 02 10 53 65
   72 69 61 6C 56 65 72 73 69 6F 6E 55 49 44 1E 08
   FFFFFF89 FFFFFFAF FFFFFFAA 01 FFFFFFAF FFFFFFD6 FFFFFFD4 FFFFFFF1 1E 08 FFFFFF89 FFFFFFAF FFFFFFAA 01 FFFFFFAF FFFFFFD6
   FFFFFFD4 FFFFFFF1 28 03 00 FFFFFF81 6A 10 03 0F FFFFFF81 6B 09 03 FFFFFF81 6C
   02 02 0C 73 65 72 69 61 6C 69 7A 61 62 6C 65 07
   07 FFFFFF81 6E 02 FFFFFF88 02 FFFFFF81 6F 01 0D 53 74 72 69 6E 67
   42 75 69 6C 64 65 72 10 03 0F FFFFFF81 70 06 09 01 02
   FFFFFF84 FFFFFF80 FFFFFF80 FFFFFF88 02 FFFFFF81 71 13 04 FFFFFF81 70 06 18 08 07 2A
   FFFFFF81 70 FFFFFF84 00 FFFFFF81 73 14 02 FFFFFF81 6F 08 0A FFFFFF81 75 FFFFFF81 70
   FFFFFFC2 FFFFFF80 FFFFFF84 04 FFFFFF81 76 01 12 4D 49 4E 5F 48 49 47 48
   5F 53 55 52 52 4F 47 41 54 45 15 01 15 08 08 FFFFFF81
   78 FFFFFF81 70 FFFFFFA0 FFFFFF80 04 15 01 13 4D 49 4E 5F 48 49 47
   48 5F 53 55 52 52 4F 47 41 54 45 20 08 0A FFFFFF81 7A
   FFFFFF81 70 FFFFFFC2 FFFFFF80 FFFFFF84 04 FFFFFF81 76 01 12 4D 41 58 5F 48 49
   47 48 5F 53 55 52 52 4F 47 41 54 45 08 08 FFFFFF81 7C
   FFFFFF81 70 FFFFFFA0 FFFFFF80 04 15 01 13 4D 41 58 5F 48 49 47 48
   5F 53 55 52 52 4F 47 41 54 45 20 08 0A FFFFFF81 7E FFFFFF81
   70 FFFFFFC2 FFFFFF80 FFFFFF84 04 FFFFFF81 76 01 11 4D 49 4E 5F 4C 4F 57
   5F 53 55 52 52 4F 47 41 54 45 08 08 FFFFFF82 00 FFFFFF81 70
   FFFFFFA0 FFFFFF80 04 15 01 12 4D 49 4E 5F 4C 4F 57 5F 53 55
   52 52 4F 47 41 54 45 20 08 0A FFFFFF82 02 FFFFFF81 70 FFFFFFC2 FFFFFF80
   FFFFFF84 04 FFFFFF81 76 01 11 4D 41 58 5F 4C 4F 57 5F 53 55
   52 52 4F 47 41 54 45 08 08 FFFFFF82 04 FFFFFF81 70 FFFFFFA0 FFFFFF80 04
   15 01 12 4D 41 58 5F 4C 4F 57 5F 53 55 52 52 4F
   47 41 54 45 20 08 0A FFFFFF82 06 FFFFFF81 70 FFFFFFC2 FFFFFF80 FFFFFF84 04 FFFFFF81
   76 01 0D 4D 49 4E 5F 53 55 52 52 4F 47 41 54 45
   08 08 FFFFFF82 08 FFFFFF81 70 FFFFFFA0 FFFFFF80 04 15 01 0E 4D 49 4E 5F
   53 55 52 52 4F 47 41 54 45 20 08 0A FFFFFF82 0A FFFFFF81 70
   FFFFFFC2 FFFFFF80 FFFFFF84 04 FFFFFF81 76 01 0D 4D 41 58 5F 53 55 52 52
   4F 47 41 54 45 08 08 FFFFFF82 0C FFFFFF81 70 FFFFFFA0 FFFFFF80 04 15 01
   0E 4D 41 58 5F 53 55 52 52 4F 47 41 54 45 20 08
   08 FFFFFF82 0E FFFFFF81 70 FFFFFF84 04 FFFFFF82 0F 01 0E 69 73 4C 6F 77
   53 75 72 72 6F 67 61 74 65 14 02 7E 15 08 08 FFFFFF82
   11 FFFFFF81 70 FFFFFF84 04 FFFFFF82 0F 01 0F 69 73 48 69 67 68 53
   75 72 72 6F 67 61 74 65 08 08 FFFFFF82 13 FFFFFF81 70 FFFFFF84 04
   FFFFFF82 14 01 06 63 6F 70 79 4F 66 14 03 30 30 12 08
   08 FFFFFF81 3D FFFFFF81 70 FFFFFF84 04 FFFFFF82 16 14 08 12 30 12 12 30
   12 12 12 08 08 FFFFFF81 42 FFFFFF81 70 FFFFFF84 04 FFFFFF82 16 08 08 FFFFFF82
   19 FFFFFF81 70 FFFFFF84 01 FFFFFF82 1A 01 0E 74 6F 43 68 61 72 53
   65 71 75 65 6E 63 65 14 03 FFFFFF82 1B 2C 10 03 07 FFFFFF82
   1C 09 03 FFFFFF82 1D 08 02 0C 43 68 61 72 53 65 71 75
   65 6E 63 65 
  Signature: length = 0x2
   00 68 
  SourceFile: "StringBuilder.scala"
  minor version: 0
  major version: 49
  Constant pool:
int	16;
String	
String	null
class	java/io/Serializable
class	java/lang/IllegalArgumentException
class	java/lang/NullPointerException
class	java/lang/Object
class	java/lang/String
class	java/lang/StringIndexOutOfBoundsException
class	scala/Function1
class	scala/Function1$class
class	scala/Math$
class	scala/StringBuilder
class	scala/StringBuilder$
class	scala/runtime/BoxesRunTime
long	-8525408645367278351l;
Field	scala/Math$.MODULE$:Lscala/Math$;
Field	scala/StringBuilder.count:I
Field	scala/StringBuilder.initValue:Ljava/lang/String;
Field	scala/StringBuilder.serialVersionUID:J
Field	scala/StringBuilder.value:[C
Field	scala/StringBuilder$.MODULE$:Lscala/StringBuilder$;
Method	java/lang/IllegalArgumentException."<init>":()V
Method	java/lang/NullPointerException."<init>":()V
Method	java/lang/Object."<init>":()V
Method	java/lang/Object.equals:(Ljava/lang/Object;)Z
Method	java/lang/String."<init>":([CII)V
Method	java/lang/String.getChars:(II[CI)V
Method	java/lang/String.length:()I
Method	java/lang/String.valueOf:(Ljava/lang/Object;)Ljava/lang/String;
Method	java/lang/StringIndexOutOfBoundsException."<init>":(I)V
Method	scala/Function1$class.$init$:(Lscala/Function1;)V
Method	scala/Math$.MAX_INT:()I
Method	scala/StringBuilder."<init>":(ILjava/lang/String;)V
Method	scala/StringBuilder.append:(Ljava/lang/String;)Lscala/StringBuilder;
Method	scala/StringBuilder.apply:(I)C
Method	scala/StringBuilder.charAt:(I)C
Method	scala/StringBuilder.count:()I
Method	scala/StringBuilder.count_$eq:(I)V
Method	scala/StringBuilder.expandCapacity:(I)V
Method	scala/StringBuilder.value:()[C
Method	scala/StringBuilder.value_$eq:([C)V
Method	scala/StringBuilder$.scala$StringBuilder$$copyOf:([CI)[C
Method	scala/runtime/BoxesRunTime.boxToCharacter:(C)Ljava/lang/Character;
Method	scala/runtime/BoxesRunTime.unboxToInt:(Ljava/lang/Object;)I
NameAndType	$init$:(Lscala/Function1;)V
NameAndType	"<init>":()V
NameAndType	"<init>":(I)V
NameAndType	"<init>":(ILjava/lang/String;)V
NameAndType	"<init>":([CII)V
NameAndType	MAX_INT:()I
NameAndType	MODULE$:Lscala/Math$;
NameAndType	MODULE$:Lscala/StringBuilder$;
NameAndType	append:(Ljava/lang/String;)Lscala/StringBuilder;
NameAndType	apply:(I)C
NameAndType	boxToCharacter:(C)Ljava/lang/Character;
NameAndType	charAt:(I)C
NameAndType	count:()I
NameAndType	count:I
NameAndType	count_$eq:(I)V
NameAndType	equals:(Ljava/lang/Object;)Z
NameAndType	expandCapacity:(I)V
NameAndType	getChars:(II[CI)V
NameAndType	initValue:Ljava/lang/String;
NameAndType	length:()I
NameAndType	scala$StringBuilder$$copyOf:([CI)[C
NameAndType	serialVersionUID:J
NameAndType	unboxToInt:(Ljava/lang/Object;)I
NameAndType	value:()[C
NameAndType	value:[C
NameAndType	valueOf:(Ljava/lang/Object;)Ljava/lang/String;
NameAndType	value_$eq:([C)V
Asciz	;
Asciz	$init$;
Asciz	()I;
Asciz	()Ljava/lang/String;;
Asciz	()V;
Asciz	()[C;
Asciz	(C)Ljava/lang/Character;;
Asciz	(C)Lscala/StringBuilder;;
Asciz	(I)C;
Asciz	(I)V;
Asciz	(II[CI)V;
Asciz	(ILjava/lang/String;)V;
Asciz	(Ljava/lang/Object;)I;
Asciz	(Ljava/lang/Object;)Ljava/lang/Object;;
Asciz	(Ljava/lang/Object;)Ljava/lang/String;;
Asciz	(Ljava/lang/Object;)Lscala/StringBuilder;;
Asciz	(Ljava/lang/Object;)Z;
Asciz	(Ljava/lang/String;)Lscala/StringBuilder;;
Asciz	(Lscala/Function1;)V;
Asciz	([C)V;
Asciz	([CI)[C;
Asciz	([CII)V;
Asciz	<clinit>;
Asciz	<init>;
Asciz	C;
Asciz	Code;
Asciz	I;
Asciz	J;
Asciz	LineNumberTable;
Asciz	Ljava/lang/Object;;
Asciz	Ljava/lang/Object;Lscala/Function1<Ljava/lang/Integer;Ljava/lang/Character;>;;
Asciz	Ljava/lang/String;;
Asciz	LocalVariableTable;
Asciz	Lscala/Math$;;
Asciz	Lscala/StringBuilder$;;
Asciz	Lscala/StringBuilder;;
Asciz	MAX_INT;
Asciz	MODULE$;
Asciz	ScalaSig;
Asciz	Signature;
Asciz	SourceFile;
Asciz	StringBuilder.scala;
Asciz	[C;
Asciz	append;
Asciz	apply;
Asciz	boxToCharacter;
Asciz	charAt;
Asciz	count;
Asciz	count_$eq;
Asciz	equals;
Asciz	expandCapacity;
Asciz	getChars;
Asciz	i;
Asciz	index;
Asciz	initCapacity;
Asciz	initValue;
Asciz	java/io/Serializable;
Asciz	java/lang/IllegalArgumentException;
Asciz	java/lang/NullPointerException;
Asciz	java/lang/Object;
Asciz	java/lang/String;
Asciz	java/lang/StringIndexOutOfBoundsException;
Asciz	len;
Asciz	length;
Asciz	n;
Asciz	newCapacity;
Asciz	newCount;
Asciz	null;
Asciz	s;
Asciz	scala$StringBuilder$$copyOf;
Asciz	scala/Function1;
Asciz	scala/Function1$class;
Asciz	scala/Math$;
Asciz	scala/StringBuilder;
Asciz	scala/StringBuilder$;
Asciz	scala/runtime/BoxesRunTime;
Asciz	serialVersionUID;
Asciz	str;
Asciz	this;
Asciz	toString;
Asciz	unboxToInt;
Asciz	value;
Asciz	valueOf;
Asciz	value_$eq;
Asciz	x;
Asciz	x$1;

{
public static final long serialVersionUID;
  Signature: J

private int count;
  Signature: I

private char[] value;
  Signature: [C

private final java.lang.String initValue;
  Signature: Ljava/lang/String;

public static {};
  Signature: ()V
  Code:
   Stack=2, Locals=0, Args_size=0
	ldc2_w	long -8525408645367278351l
	putstatic	Field serialVersionUID:J
	return
  Labels:

public scala.StringBuilder(int, java.lang.String);
  Signature: (ILjava/lang/String;)V
  Code:
   Stack=3, Locals=3, Args_size=3
	aload_0
	aload_2
	putfield	Field initValue:Ljava/lang/String;
	aload_0
	invokespecial	Method java/lang/Object."<init>":()V
	aload_0
	invokestatic	Method scala/Function1$class.$init$:(Lscala/Function1;)V
	iload_1
	iconst_0
	if_icmpge	l1 // aload_2
	new	class java/lang/IllegalArgumentException
	dup
	invokespecial	Method java/lang/IllegalArgumentException."<init>":()V
	athrow
l1	aload_2
	ifnonnull	l2 // aload_0
	new	class java/lang/NullPointerException
	dup
	invokespecial	Method java/lang/NullPointerException."<init>":()V
	athrow
l2	aload_0
	iload_1
	aload_2
	invokevirtual	Method java/lang/String.length:()I
	iadd
	newarray char
	putfield	Field value:[C
	aload_0
	iconst_0
	putfield	Field count:I
	aload_0
	aload_2
	invokevirtual	Method append:(Ljava/lang/String;)Lscala/StringBuilder;
	pop
	return
  Labels:
   	l1 = 26 // aload_2
   	l2 = 38 // aload_0
  LocalVariableTable: 
   Start  Length  Slot  Name   Signature
   0      62      0    this       Lscala/StringBuilder;
   0      62      1    initCapacity       I
   0      62      2    initValue       Ljava/lang/String;


public java.lang.Object apply(java.lang.Object);
  Signature: (Ljava/lang/Object;)Ljava/lang/Object;
  Code:
   Stack=2, Locals=2, Args_size=2
	aload_0
	aload_1
	invokestatic	Method scala/runtime/BoxesRunTime.unboxToInt:(Ljava/lang/Object;)I
	invokevirtual	Method apply:(I)C
	invokestatic	Method scala/runtime/BoxesRunTime.boxToCharacter:(C)Ljava/lang/Character;
	areturn
  Labels:
  LocalVariableTable: 
   Start  Length  Slot  Name   Signature
   0      12      0    this       Lscala/StringBuilder;
   0      12      1    x$1       Ljava/lang/Object;


public java.lang.String toString();
  Signature: ()Ljava/lang/String;
  Code:
   Stack=5, Locals=1, Args_size=1
	new	class java/lang/String
	dup
	aload_0
	invokespecial	Method value:()[C
	iconst_0
	aload_0
	invokespecial	Method count:()I
	invokespecial	Method java/lang/String."<init>":([CII)V
	areturn
  Labels:

public scala.StringBuilder append(char);
  Signature: (C)Lscala/StringBuilder;
  Code:
   Stack=3, Locals=3, Args_size=2
	aload_0
	invokespecial	Method count:()I
	iconst_1
	iadd
	istore_2
	iload_2
	aload_0
	invokespecial	Method value:()[C
	arraylength
	if_icmple	l1 // aload_0
	aload_0
	iload_2
	invokespecial	Method expandCapacity:(I)V
l1	aload_0
	invokespecial	Method value:()[C
	aload_0
	invokespecial	Method count:()I
	iload_1
	castore
	aload_0
	aload_0
	invokespecial	Method count:()I
	iconst_1
	iadd
	invokespecial	Method count_$eq:(I)V
	aload_0
	areturn
  Labels:
   	l1 = 21 // aload_0
  LocalVariableTable: 
   Start  Length  Slot  Name   Signature
   0      43      0    this       Lscala/StringBuilder;
   0      43      1    x       C
   0      42      2    newCount       I


public scala.StringBuilder append(java.lang.String);
  Signature: (Ljava/lang/String;)Lscala/StringBuilder;
  Code:
   Stack=5, Locals=6, Args_size=2
	aload_1
	dup
	astore_3
	ifnull	l1 // ldc
	aload_3
	aconst_null
	invokevirtual	Method java/lang/Object.equals:(Ljava/lang/Object;)Z
	ifeq	l2 // aload_1
l1	ldc	String null
	goto	l3 // astore_2
l2	aload_1
l3	astore_2
	aload_2
	invokevirtual	Method java/lang/String.length:()I
	istore	4
	iload	4
	iconst_0
	if_icmple	l4 // aload_0
	aload_0
	invokespecial	Method count:()I
	iload	4
	iadd
	istore	5
	iload	5
	aload_0
	invokespecial	Method value:()[C
	arraylength
	if_icmple	l5 // aload_2
	aload_0
	iload	5
	invokespecial	Method expandCapacity:(I)V
l5	aload_2
	iconst_0
	iload	4
	aload_0
	invokespecial	Method value:()[C
	aload_0
	invokespecial	Method count:()I
	invokevirtual	Method java/lang/String.getChars:(II[CI)V
	aload_0
	iload	5
	invokespecial	Method count_$eq:(I)V
l4	aload_0
	areturn
  Labels:
   	l1 = 14 // ldc
   	l2 = 19 // aload_1
   	l3 = 20 // astore_2
   	l5 = 58 // aload_2
   	l4 = 79 // aload_0


public scala.StringBuilder append(java.lang.Object);
  Signature: (Ljava/lang/Object;)Lscala/StringBuilder;
  Code:
   Stack=2, Locals=2, Args_size=2
	aload_0
	aload_1
	invokestatic	Method java/lang/String.valueOf:(Ljava/lang/Object;)Ljava/lang/String;
	invokevirtual	Method append:(Ljava/lang/String;)Lscala/StringBuilder;
	areturn
  Labels:
  LocalVariableTable: 
   Start  Length  Slot  Name   Signature
   0      9      0    this       Lscala/StringBuilder;
   0      9      1    x       Ljava/lang/Object;


public char apply(int);
  Signature: (I)C
  Code:
   Stack=2, Locals=2, Args_size=2
	aload_0
	iload_1
	invokevirtual	Method charAt:(I)C
	ireturn
  Labels:
  LocalVariableTable: 
   Start  Length  Slot  Name   Signature
   0      6      0    this       Lscala/StringBuilder;
   0      6      1    i       I


public char charAt(int);
  Signature: (I)C
  Code:
   Stack=3, Locals=2, Args_size=2
	iload_1
	iconst_0
	if_icmplt	l1 // new
	iload_1
	aload_0
	invokespecial	Method count:()I
	if_icmplt	l2 // aload_0
l1	new	class java/lang/StringIndexOutOfBoundsException
	dup
	iload_1
	invokespecial	Method java/lang/StringIndexOutOfBoundsException."<init>":(I)V
	athrow
l2	aload_0
	invokespecial	Method value:()[C
	iload_1
	caload
	ireturn
  Labels:
   	l1 = 13 // new
   	l2 = 22 // aload_0
  LocalVariableTable: 
   Start  Length  Slot  Name   Signature
   0      29      0    this       Lscala/StringBuilder;
   0      29      1    index       I


private void expandCapacity(int);
  Signature: (I)V
  Code:
   Stack=5, Locals=3, Args_size=2
	aload_0
	invokespecial	Method value:()[C
	arraylength
	iconst_1
	iadd
	iconst_2
	imul
	istore_2
	aload_0
	getstatic	Field scala/StringBuilder$.MODULE$:Lscala/StringBuilder$;
	aload_0
	invokespecial	Method value:()[C
	iload_2
	iconst_0
	if_icmpge	l1 // iload_1
	getstatic	Field scala/Math$.MODULE$:Lscala/Math$;
	invokevirtual	Method scala/Math$.MAX_INT:()I
	goto	l2 // invokevirtual
l1	iload_1
	iload_2
	if_icmple	l3 // iload_2
	iload_1
	goto	l2 // invokevirtual
l3	iload_2
l2	invokevirtual	Method scala/StringBuilder$.scala$StringBuilder$$copyOf:([CI)[C
	invokespecial	Method value_$eq:([C)V
	return
  Labels:
   	l1 = 32 // iload_1
   	l3 = 41 // iload_2
   	l2 = 42 // invokevirtual
  LocalVariableTable: 
   Start  Length  Slot  Name   Signature
   0      49      0    this       Lscala/StringBuilder;
   0      49      1    n       I
   0      48      2    newCapacity       I


public scala.StringBuilder();
  Signature: ()V
  Code:
   Stack=3, Locals=1, Args_size=1
	aload_0
	ldc	int 16
	ldc	String 
	invokespecial	Method "<init>":(ILjava/lang/String;)V
	return
  Labels:

private void count_$eq(int);
  Signature: (I)V
  Code:
   Stack=2, Locals=2, Args_size=2
	aload_0
	iload_1
	putfield	Field count:I
	return
  Labels:
  LocalVariableTable: 
   Start  Length  Slot  Name   Signature
   0      6      0    this       Lscala/StringBuilder;
   0      6      1    x$1       I


private int count();
  Signature: ()I
  Code:
   Stack=1, Locals=1, Args_size=1
	aload_0
	getfield	Field count:I
	ireturn
  Labels:

private void value_$eq(char[]);
  Signature: ([C)V
  Code:
   Stack=2, Locals=2, Args_size=2
	aload_0
	aload_1
	putfield	Field value:[C
	return
  Labels:
  LocalVariableTable: 
   Start  Length  Slot  Name   Signature
   0      6      0    this       Lscala/StringBuilder;
   0      6      1    x$1       [C


private char[] value();
  Signature: ()[C
  Code:
   Stack=1, Locals=1, Args_size=1
	aload_0
	getfield	Field value:[C
	areturn
  Labels:

}

