Compiled from "Tuple22.scala"
public class scala.Tuple22 extends java.lang.Object implements scala.Product22,scala.ScalaObject,scala.Product,java.io.Serializable
  SourceFile: "Tuple22.scala"
  ScalaSig: length = 0x3
   05 00 00 
  Signature: length = 0x2
   01 56 
  RuntimeVisibleAnnotations: length = 0xB
   00 01 01 57 00 01 01 58 73 01 59 
  minor version: 0
  major version: 49
  Constant pool:
Asciz	SourceFile;
Asciz	Tuple22.scala;
Asciz	_1;
Asciz	Ljava/lang/Object;;
Asciz	TT1;;
Asciz	Signature;
Asciz	_2;
Asciz	TT2;;
Asciz	_3;
Asciz	TT3;;
Asciz	_4;
Asciz	TT4;;
Asciz	_5;
Asciz	TT5;;
Asciz	_6;
Asciz	TT6;;
Asciz	_7;
Asciz	TT7;;
Asciz	_8;
Asciz	TT8;;
Asciz	_9;
Asciz	TT9;;
Asciz	_10;
Asciz	TT10;;
Asciz	_11;
Asciz	TT11;;
Asciz	_12;
Asciz	TT12;;
Asciz	_13;
Asciz	TT13;;
Asciz	_14;
Asciz	TT14;;
Asciz	_15;
Asciz	TT15;;
Asciz	_16;
Asciz	TT16;;
Asciz	_17;
Asciz	TT17;;
Asciz	_18;
Asciz	TT18;;
Asciz	_19;
Asciz	TT19;;
Asciz	_20;
Asciz	TT20;;
Asciz	_21;
Asciz	TT21;;
Asciz	_22;
Asciz	TT22;;
Asciz	productArity;
Asciz	()I;
Asciz	Code;
Asciz	LineNumberTable;
Asciz	scala/Product22$class;
class	scala/Product22$class
Asciz	(Lscala/Product22;)I;
NameAndType	productArity:(Lscala/Product22;)I
Method	scala/Product22$class.productArity:(Lscala/Product22;)I
Asciz	productElement;
Asciz	(I)Ljava/lang/Object;;
Asciz	(Lscala/Product22;I)Ljava/lang/Object;;
NameAndType	productElement:(Lscala/Product22;I)Ljava/lang/Object;
Method	scala/Product22$class.productElement:(Lscala/Product22;I)Ljava/lang/Object;
Asciz	this;
Asciz	Lscala/Tuple22;;
Asciz	n;
Asciz	I;
Asciz	LocalVariableTable;
Asciz	java/lang/IndexOutOfBoundsException;
class	java/lang/IndexOutOfBoundsException
Asciz	Exceptions;
Asciz	productElementName;
Asciz	(I)Ljava/lang/String;;
Asciz	scala/Product$class;
class	scala/Product$class
Asciz	(Lscala/Product;I)Ljava/lang/String;;
NameAndType	productElementName:(Lscala/Product;I)Ljava/lang/String;
Method	scala/Product$class.productElementName:(Lscala/Product;I)Ljava/lang/String;
Asciz	productIterator;
Asciz	()Lscala/collection/Iterator;;
Asciz	(Lscala/Product;)Lscala/collection/Iterator;;
NameAndType	productIterator:(Lscala/Product;)Lscala/collection/Iterator;
Method	scala/Product$class.productIterator:(Lscala/Product;)Lscala/collection/Iterator;
Asciz	productElements;
NameAndType	productElements:(Lscala/Product;)Lscala/collection/Iterator;
Method	scala/Product$class.productElements:(Lscala/Product;)Lscala/collection/Iterator;
Asciz	Deprecated;
Asciz	copy$default$22;
Asciz	()Ljava/lang/Object;;
Asciz	scala/Tuple22;
class	scala/Tuple22
NameAndType	_22:()Ljava/lang/Object;
Method	scala/Tuple22._22:()Ljava/lang/Object;
Asciz	copy$default$21;
NameAndType	_21:()Ljava/lang/Object;
Method	scala/Tuple22._21:()Ljava/lang/Object;
Asciz	copy$default$20;
NameAndType	_20:()Ljava/lang/Object;
Method	scala/Tuple22._20:()Ljava/lang/Object;
Asciz	copy$default$19;
NameAndType	_19:()Ljava/lang/Object;
Method	scala/Tuple22._19:()Ljava/lang/Object;
Asciz	copy$default$18;
NameAndType	_18:()Ljava/lang/Object;
Method	scala/Tuple22._18:()Ljava/lang/Object;
Asciz	copy$default$17;
NameAndType	_17:()Ljava/lang/Object;
Method	scala/Tuple22._17:()Ljava/lang/Object;
Asciz	copy$default$16;
NameAndType	_16:()Ljava/lang/Object;
Method	scala/Tuple22._16:()Ljava/lang/Object;
Asciz	copy$default$15;
NameAndType	_15:()Ljava/lang/Object;
Method	scala/Tuple22._15:()Ljava/lang/Object;
Asciz	copy$default$14;
NameAndType	_14:()Ljava/lang/Object;
Method	scala/Tuple22._14:()Ljava/lang/Object;
Asciz	copy$default$13;
NameAndType	_13:()Ljava/lang/Object;
Method	scala/Tuple22._13:()Ljava/lang/Object;
Asciz	copy$default$12;
NameAndType	_12:()Ljava/lang/Object;
Method	scala/Tuple22._12:()Ljava/lang/Object;
Asciz	copy$default$11;
NameAndType	_11:()Ljava/lang/Object;
Method	scala/Tuple22._11:()Ljava/lang/Object;
Asciz	copy$default$10;
NameAndType	_10:()Ljava/lang/Object;
Method	scala/Tuple22._10:()Ljava/lang/Object;
Asciz	copy$default$9;
NameAndType	_9:()Ljava/lang/Object;
Method	scala/Tuple22._9:()Ljava/lang/Object;
Asciz	copy$default$8;
NameAndType	_8:()Ljava/lang/Object;
Method	scala/Tuple22._8:()Ljava/lang/Object;
Asciz	copy$default$7;
NameAndType	_7:()Ljava/lang/Object;
Method	scala/Tuple22._7:()Ljava/lang/Object;
Asciz	copy$default$6;
NameAndType	_6:()Ljava/lang/Object;
Method	scala/Tuple22._6:()Ljava/lang/Object;
Asciz	copy$default$5;
NameAndType	_5:()Ljava/lang/Object;
Method	scala/Tuple22._5:()Ljava/lang/Object;
Asciz	copy$default$4;
NameAndType	_4:()Ljava/lang/Object;
Method	scala/Tuple22._4:()Ljava/lang/Object;
Asciz	copy$default$3;
NameAndType	_3:()Ljava/lang/Object;
Method	scala/Tuple22._3:()Ljava/lang/Object;
Asciz	copy$default$2;
NameAndType	_2:()Ljava/lang/Object;
Method	scala/Tuple22._2:()Ljava/lang/Object;
Asciz	copy$default$1;
NameAndType	_1:()Ljava/lang/Object;
Method	scala/Tuple22._1:()Ljava/lang/Object;
NameAndType	_1:Ljava/lang/Object;
Field	scala/Tuple22._1:Ljava/lang/Object;
Asciz	()TT1;;
NameAndType	_2:Ljava/lang/Object;
Field	scala/Tuple22._2:Ljava/lang/Object;
Asciz	()TT2;;
NameAndType	_3:Ljava/lang/Object;
Field	scala/Tuple22._3:Ljava/lang/Object;
Asciz	()TT3;;
NameAndType	_4:Ljava/lang/Object;
Field	scala/Tuple22._4:Ljava/lang/Object;
Asciz	()TT4;;
NameAndType	_5:Ljava/lang/Object;
Field	scala/Tuple22._5:Ljava/lang/Object;
Asciz	()TT5;;
NameAndType	_6:Ljava/lang/Object;
Field	scala/Tuple22._6:Ljava/lang/Object;
Asciz	()TT6;;
NameAndType	_7:Ljava/lang/Object;
Field	scala/Tuple22._7:Ljava/lang/Object;
Asciz	()TT7;;
NameAndType	_8:Ljava/lang/Object;
Field	scala/Tuple22._8:Ljava/lang/Object;
Asciz	()TT8;;
NameAndType	_9:Ljava/lang/Object;
Field	scala/Tuple22._9:Ljava/lang/Object;
Asciz	()TT9;;
NameAndType	_10:Ljava/lang/Object;
Field	scala/Tuple22._10:Ljava/lang/Object;
Asciz	()TT10;;
NameAndType	_11:Ljava/lang/Object;
Field	scala/Tuple22._11:Ljava/lang/Object;
Asciz	()TT11;;
NameAndType	_12:Ljava/lang/Object;
Field	scala/Tuple22._12:Ljava/lang/Object;
Asciz	()TT12;;
NameAndType	_13:Ljava/lang/Object;
Field	scala/Tuple22._13:Ljava/lang/Object;
Asciz	()TT13;;
NameAndType	_14:Ljava/lang/Object;
Field	scala/Tuple22._14:Ljava/lang/Object;
Asciz	()TT14;;
NameAndType	_15:Ljava/lang/Object;
Field	scala/Tuple22._15:Ljava/lang/Object;
Asciz	()TT15;;
NameAndType	_16:Ljava/lang/Object;
Field	scala/Tuple22._16:Ljava/lang/Object;
Asciz	()TT16;;
NameAndType	_17:Ljava/lang/Object;
Field	scala/Tuple22._17:Ljava/lang/Object;
Asciz	()TT17;;
NameAndType	_18:Ljava/lang/Object;
Field	scala/Tuple22._18:Ljava/lang/Object;
Asciz	()TT18;;
NameAndType	_19:Ljava/lang/Object;
Field	scala/Tuple22._19:Ljava/lang/Object;
Asciz	()TT19;;
NameAndType	_20:Ljava/lang/Object;
Field	scala/Tuple22._20:Ljava/lang/Object;
Asciz	()TT20;;
NameAndType	_21:Ljava/lang/Object;
Field	scala/Tuple22._21:Ljava/lang/Object;
Asciz	()TT21;;
NameAndType	_22:Ljava/lang/Object;
Field	scala/Tuple22._22:Ljava/lang/Object;
Asciz	()TT22;;
Asciz	toString;
Asciz	()Ljava/lang/String;;
Asciz	scala/collection/mutable/StringBuilder;
class	scala/collection/mutable/StringBuilder
Asciz	<init>;
Asciz	()V;
NameAndType	"<init>":()V
Method	scala/collection/mutable/StringBuilder."<init>":()V
Asciz	(;
String	(
Asciz	append;
Asciz	(Ljava/lang/Object;)Lscala/collection/mutable/StringBuilder;;
NameAndType	append:(Ljava/lang/Object;)Lscala/collection/mutable/StringBuilder;
Method	scala/collection/mutable/StringBuilder.append:(Ljava/lang/Object;)Lscala/collection/mutable/StringBuilder;
Asciz	,;
String	,
Asciz	);
String	)
NameAndType	toString:()Ljava/lang/String;
Method	scala/collection/mutable/StringBuilder.toString:()Ljava/lang/String;
Asciz	copy;
Asciz	(Ljava/lang/Object;Ljava/lang/Object;Ljava/lang/Object;Ljava/lang/Object;Ljava/lang/Object;Ljava/lang/Object;Ljava/lang/Object;Ljava/lang/Object;Ljava/lang/Object;Ljava/lang/Object;Ljava/lang/Object;Ljava/lang/Object;Ljava/lang/Object;Ljava/lang/Object;Ljava/lang/Object;Ljava/lang/Object;Ljava/lang/Object;Ljava/lang/Object;Ljava/lang/Object;Ljava/lang/Object;Ljava/lang/Object;Ljava/lang/Object;)Lscala/Tuple22;;
Asciz	(Ljava/lang/Object;Ljava/lang/Object;Ljava/lang/Object;Ljava/lang/Object;Ljava/lang/Object;Ljava/lang/Object;Ljava/lang/Object;Ljava/lang/Object;Ljava/lang/Object;Ljava/lang/Object;Ljava/lang/Object;Ljava/lang/Object;Ljava/lang/Object;Ljava/lang/Object;Ljava/lang/Object;Ljava/lang/Object;Ljava/lang/Object;Ljava/lang/Object;Ljava/lang/Object;Ljava/lang/Object;Ljava/lang/Object;Ljava/lang/Object;)V;
NameAndType	"<init>":(Ljava/lang/Object;Ljava/lang/Object;Ljava/lang/Object;Ljava/lang/Object;Ljava/lang/Object;Ljava/lang/Object;Ljava/lang/Object;Ljava/lang/Object;Ljava/lang/Object;Ljava/lang/Object;Ljava/lang/Object;Ljava/lang/Object;Ljava/lang/Object;Ljava/lang/Object;Ljava/lang/Object;Ljava/lang/Object;Ljava/lang/Object;Ljava/lang/Object;Ljava/lang/Object;Ljava/lang/Object;Ljava/lang/Object;Ljava/lang/Object;)V
Method	scala/Tuple22."<init>":(Ljava/lang/Object;Ljava/lang/Object;Ljava/lang/Object;Ljava/lang/Object;Ljava/lang/Object;Ljava/lang/Object;Ljava/lang/Object;Ljava/lang/Object;Ljava/lang/Object;Ljava/lang/Object;Ljava/lang/Object;Ljava/lang/Object;Ljava/lang/Object;Ljava/lang/Object;Ljava/lang/Object;Ljava/lang/Object;Ljava/lang/Object;Ljava/lang/Object;Ljava/lang/Object;Ljava/lang/Object;Ljava/lang/Object;Ljava/lang/Object;)V
Asciz	hashCode;
Asciz	scala/runtime/ScalaRunTime$;
class	scala/runtime/ScalaRunTime$
Asciz	MODULE$;
Asciz	Lscala/runtime/ScalaRunTime$;;
NameAndType	MODULE$:Lscala/runtime/ScalaRunTime$;
Field	scala/runtime/ScalaRunTime$.MODULE$:Lscala/runtime/ScalaRunTime$;
Asciz	_hashCode;
Asciz	(Lscala/Product;)I;
NameAndType	_hashCode:(Lscala/Product;)I
Method	scala/runtime/ScalaRunTime$._hashCode:(Lscala/Product;)I
Asciz	equals;
Asciz	(Ljava/lang/Object;)Z;
Asciz	gd1$1;
Asciz	(Ljava/lang/Object;Ljava/lang/Object;Ljava/lang/Object;Ljava/lang/Object;Ljava/lang/Object;Ljava/lang/Object;Ljava/lang/Object;Ljava/lang/Object;Ljava/lang/Object;Ljava/lang/Object;Ljava/lang/Object;Ljava/lang/Object;Ljava/lang/Object;Ljava/lang/Object;Ljava/lang/Object;Ljava/lang/Object;Ljava/lang/Object;Ljava/lang/Object;Ljava/lang/Object;Ljava/lang/Object;Ljava/lang/Object;Ljava/lang/Object;)Z;
NameAndType	gd1$1:(Ljava/lang/Object;Ljava/lang/Object;Ljava/lang/Object;Ljava/lang/Object;Ljava/lang/Object;Ljava/lang/Object;Ljava/lang/Object;Ljava/lang/Object;Ljava/lang/Object;Ljava/lang/Object;Ljava/lang/Object;Ljava/lang/Object;Ljava/lang/Object;Ljava/lang/Object;Ljava/lang/Object;Ljava/lang/Object;Ljava/lang/Object;Ljava/lang/Object;Ljava/lang/Object;Ljava/lang/Object;Ljava/lang/Object;Ljava/lang/Object;)Z
Method	scala/Tuple22.gd1$1:(Ljava/lang/Object;Ljava/lang/Object;Ljava/lang/Object;Ljava/lang/Object;Ljava/lang/Object;Ljava/lang/Object;Ljava/lang/Object;Ljava/lang/Object;Ljava/lang/Object;Ljava/lang/Object;Ljava/lang/Object;Ljava/lang/Object;Ljava/lang/Object;Ljava/lang/Object;Ljava/lang/Object;Ljava/lang/Object;Ljava/lang/Object;Ljava/lang/Object;Ljava/lang/Object;Ljava/lang/Object;Ljava/lang/Object;Ljava/lang/Object;)Z
Asciz	scala/Equals;
class	scala/Equals
Asciz	canEqual;
NameAndType	canEqual:(Ljava/lang/Object;)Z
InterfaceMethod	scala/Equals.canEqual:(Ljava/lang/Object;)Z
Asciz	temp2;
Asciz	temp3;
Asciz	temp4;
Asciz	temp5;
Asciz	temp6;
Asciz	temp7;
Asciz	temp8;
Asciz	temp9;
Asciz	temp10;
Asciz	temp11;
Asciz	temp12;
Asciz	temp13;
Asciz	temp14;
Asciz	temp15;
Asciz	temp16;
Asciz	temp17;
Asciz	temp18;
Asciz	temp19;
Asciz	temp20;
Asciz	temp21;
Asciz	temp22;
Asciz	temp23;
Asciz	temp24;
Asciz	productPrefix;
Asciz	Tuple22;
String	Tuple22
Asciz	java/lang/Number;
class	java/lang/Number
Asciz	scala/runtime/BoxesRunTime;
class	scala/runtime/BoxesRunTime
Asciz	equalsNumObject;
Asciz	(Ljava/lang/Number;Ljava/lang/Object;)Z;
NameAndType	equalsNumObject:(Ljava/lang/Number;Ljava/lang/Object;)Z
Method	scala/runtime/BoxesRunTime.equalsNumObject:(Ljava/lang/Number;Ljava/lang/Object;)Z
Asciz	java/lang/Character;
class	java/lang/Character
Asciz	equalsCharObject;
Asciz	(Ljava/lang/Character;Ljava/lang/Object;)Z;
NameAndType	equalsCharObject:(Ljava/lang/Character;Ljava/lang/Object;)Z
Method	scala/runtime/BoxesRunTime.equalsCharObject:(Ljava/lang/Character;Ljava/lang/Object;)Z
Asciz	java/lang/Object;
class	java/lang/Object
NameAndType	equals:(Ljava/lang/Object;)Z
Method	java/lang/Object.equals:(Ljava/lang/Object;)Z
Asciz	inlinedEquals;
Asciz	(Ljava/lang/Object;Ljava/lang/Object;)Z;
NameAndType	inlinedEquals:(Ljava/lang/Object;Ljava/lang/Object;)Z
Method	scala/runtime/ScalaRunTime$.inlinedEquals:(Ljava/lang/Object;Ljava/lang/Object;)Z
Asciz	y0;
Asciz	y1;
Asciz	y2;
Asciz	y3;
Asciz	y4;
Asciz	y5;
Asciz	y6;
Asciz	y7;
Asciz	y8;
Asciz	y9;
Asciz	y10;
Asciz	y11;
Asciz	y12;
Asciz	y13;
Asciz	y14;
Method	java/lang/Object."<init>":()V
Asciz	$init$;
Asciz	(Lscala/Product;)V;
NameAndType	$init$:(Lscala/Product;)V
Method	scala/Product$class.$init$:(Lscala/Product;)V
Asciz	(Lscala/Product22;)V;
NameAndType	$init$:(Lscala/Product22;)V
Method	scala/Product22$class.$init$:(Lscala/Product22;)V
Asciz	(TT1;TT2;TT3;TT4;TT5;TT6;TT7;TT8;TT9;TT10;TT11;TT12;TT13;TT14;TT15;TT16;TT17;TT18;TT19;TT20;TT21;TT22;)V;
Asciz	ScalaSig;
Asciz	<T1:Ljava/lang/Object;T2:Ljava/lang/Object;T3:Ljava/lang/Object;T4:Ljava/lang/Object;T5:Ljava/lang/Object;T6:Ljava/lang/Object;T7:Ljava/lang/Object;T8:Ljava/lang/Object;T9:Ljava/lang/Object;T10:Ljava/lang/Object;T11:Ljava/lang/Object;T12:Ljava/lang/Object;T13:Ljava/lang/Object;T14:Ljava/lang/Object;T15:Ljava/lang/Object;T16:Ljava/lang/Object;T17:Ljava/lang/Object;T18:Ljava/lang/Object;T19:Ljava/lang/Object;T20:Ljava/lang/Object;T21:Ljava/lang/Object;T22:Ljava/lang/Object;>Ljava/lang/Object;Lscala/Product22<TT1;TT2;TT3;TT4;TT5;TT6;TT7;TT8;TT9;TT10;TT11;TT12;TT13;TT14;TT15;TT16;TT17;TT18;TT19;TT20;TT21;TT22;>;Lscala/ScalaObject;Lscala/Product;;
Asciz	Lscala/reflect/ScalaSignature;;
Asciz	bytes;
Asciz	!UbBqV;qY$GC8-7b)rCB EB3FL5oiji$J>VW.9q\"1!iQ\"A)Y7b]TDU4-\t1qJ6fGRE\t=\"sEK1gYJDh\"F.sV,[B\n%&o3vGR$+1A\t%)AQC\r!\t$\t9aj;iS:<C\t\ti\"AAB]f\"FA!CC]!QCC\t%)AQC&\t!1\"A9\"A+5!\t!*IQ1\t!VWAAC\nqCUmAAC\t_!\t\"b/\tAk\t)E\"B\r\ra)b\"UA!CC]!VQ9D\t%)AQuA1C\nqCAUcE\"FyA!CC]1V3!\t!\tBIQ1\r!g\r\t)\r#\ra)F\"CG\t!9\"A9\"a+2kAA#\t!\t\"b/\tA+\rQaEC'\t%)AQtAC\nqCAUca\"*MA!CC]1V:!\t!RWIQ1\r!&\r\t)a#\"\ra)J\nC\\t!a\"A9\"a+3eACX?\n1bU2bY|%M[3diB#YE\nq:pIVGe\tU\r\"f\ty'F!9A!E!aA02A!ABK!.`eU\tam\tE\t!\ry&\t\t])!C_qlMC!AB\tB%%A`gBb%\t^?R*\n\tm\t)AIq\ta!Q3Ae!aXBbIaJ?VC?+I@}3T#\tA!E!QaA07A!QQ%\t!a};T#A\t-A!E!iaA08A!Qq%\t!!}CT#\tUA!E!aA09A!Q%\t!a}KT#A\t}A!E!aA0:A!Q1%\t!!\n}'F7%\tIB\tB%a'`cABCA\tU\r\"0q,MeB\"a\r#B\t}\to!Q3AeaA02eU\tAC>\t)Ay!q,\r!)\t\tBK1I?FT#A \tA!E!yB02gB!\"a+IAA'\ryN\"IIAQ?F\"V)!C/\n1aX6+)\"CA.\tE\t!Fy'\t}A!f\n\t\t'A`cY*\nK!#Q\n!AaX7A!Q%\t!a}t'FL%\tyB\tB%1*`c]BCA:\tU\r\"vq,\r9C\"!#(\t}\t{!Q3A}aA02sU\tC\t)A#!q,M!)\t9\tBKR?JT#+\t5A!E!!B03aB!\"!%+IAAJ\ry&'M/\"IqIaV?J\n)!C;1a3+Q\"CAQ\tE\t![y&G\r\t\"(1A(8jiz\"b&!+,5qVAYg),a.:mQXA`-!2H%1ZAg\t.a5VBAA\nC:#&4mebtHQ#I:Fk.\t\r1I1a=!1a.a)ABaa]AR!B=$q~G\rA\t1.\ty!a)AABq!!$1C$\r\t51as!9qGARabBA!G\ra\n1C\t)&a)ACq!a$\nCj\rA&\tM1a\"9QPAR\tbBADG\r#1X\tY*a)AiCq!!7\t\nY.u_N#(/8h)\t\tiE\t?L1!!9\nFO]5oO\"IQq]G>0j=1_A|wyPa\t-!qB\n/YBa$\t\"1Bg9Da@\t\rCCLAv9E!L\t5#q\nB)')FaZ\tm#QB0CG!h\t%$1B7_bnEQ_A}{\tA!\n\t5!B3iB!\t&\t%\"QBkID!BAA#a<Y\t\"A9ctI%a9\ra\t)]H!Cd\tQ1!\r!1 \nM\rH!AC]2FA \t%I1CqE!LAr\t)AQ9B0G$\t!b/AACaI\n\"A9cIQ'a9\ra\t)\tMA!d\tQ1!\r!\"q\nw\rH!AC]2B\t%q1CqE?!\"QAr\t)AQBEG$\t!b/AACa\n\"A9c,I!*a9\ra\t)\t=B!C'd\tQ1!\r!\"1\n!\rH!AC]2B\t%1CqEw!BVAr\t)AQyBZG$\t!b/AACaq\"A9\"3dB\tAAw%I1I\t\tCoG\n1v\"I1/a9 \nq\r!a{D\"`Ar!\rA!\t1I)\r!aA!\"!dB\tB)\t#a9![\t%AA\tUBCAG\n1!QIAr!\rA!\t-1I\tV\r!aKA!\"adB\tB)\tI'a9!Qg\n%AA\tEBCA?G\n16!QqQAr!\rA!\tE1Ii\r!aBBa#%\tA!\r|/eKW;%cUq#qBFyI!%\nU%qBM7iJa(\"\n\r&QBTSYK!,0\nE&1B[U\r\"PwBA! 6!q)Av]DWmY6fI*!Qtgn;bi&|g.\n\n}$!E;oG\",7m[3e-.8dKIaC!\ra\nA\tED!AC]!b\tB9\t)A\t\"A9B!Cr\tQ1\t%a#CqB0c\"\t!b/I!G!\ra\nk\tED!AC]!B9\t)Am\t\"A9B! r\tQ1\t%\t%CqBEc\"\t!b/IqI!\ra\n\nED!AC]!\"B9\t)AA\t\"A9B!C*r\tQ1\t%1&CqBZc\"\t!b/IAL!\ra\ns!CwabY8qs\"WMZ1vYR$#'>\n}&Bb9M!3L\n5'qBi')Na6Z\nm'QBpCO!:h\n%(fzIaCa.\ra\nA\t]F!AC]!b\tB\\t)A9\"A9B!C8\tQ1\t%a#qCqB0o#\t!b/I!Ga.\ra\nk\t]F!AC]!B\\t)Am9\"A9B! 8\tQ1\t%\t%qCqBEo#\t!b/IqIa.\ra\n\n]F!AC]!\"B\\t)AA9\"A9B!C*8\tQ1\t%1&qCqBZo#\t!b/IALa.\ra\n[!C_abY8qs\"WMZ1vYR$3'r\nM(QB|sYP!@ 11ABIaa\r=1CB\n+9b!\ru!fAzIaCa;\ra\nA\t-H!AC]!b\tBv\t)AY\"A9B!Cl\tQ1\t%a#1CqB0W$\t!b/I!Ga;\ra\nk\t-H!AC]!Bv\t)AmY\"A9B! l\tQ1\t%\t%1CqBEW$\t!b/IqIa;\ra\n\n-H!AC]!\"Bv\t)AAY\"A9B!C*l\tQ1\t%1&1CqBZW$\t!b/IALa;\ra\nC!CG\tabY8qs\"WMZ1vYR$C'&\r2FB[yc!\r4\rU2qGBwidaB\r\r3QIB$Ye!P\rE#fzIaca\ra\nA\r}A!AC]!bIB\t)Ay\"A9B!C \tQ1\t%a3qCqB0?!\t!b/I!ga\ra\nk\r}A!AC]!OB\t)Amy\"A9B!  \tQ1\t%\t5qCqBE?!\t!b/Iqia\ra\n}A!AC]!\"TB\t)AAy\"A9B!C* \tQ1\t%16qCqBZ?!\t!b/IAla\ra\n+!C/\nabY8qs\"WMZ1vYR$S'Z\rm3QLB0Cg!h\r%41NB7_\thav\r]4PB>{yh!!%fAzIaca\ra\nA\rMC!AC]!bIB*\t)A\"A9B!CT\tQ1\t%a31CqB0'\"\t!b/I!ga\ra\nk\rMC!AC]!OB*\t)Am\"A9B! T\tQ1\t%\t51CqBE'\"\t!b/Iqia\ra\nMC!AC]!\"TB*\t)AA\"A9B!C*T\tQ1\t%161CqBZ'\"\t!b/IAla\ra\n!CabY8qs\"WMZ1vYR$c'=5SBJ+9j!'u5qTBQG)ka**-6QVBXcl!.8e&fzIaca\"\ra\nA\rE!AC]!bIBD\t)A9\t\"A9B!C\tQ1\t%a3qCqB0#\t!b/I!ga\"\ra\nk\rE!AC]!OBD\t)Am9\t\"A9B! \tQ1\t%\t5qCqBE#\t!b/Iqia\"\ra\nE!AC]!\"TBD\t)AA9\t\"A9B!C*\tQ1\t%16qCqBZ#\t!b/IAla\"\ra\n{!CabY8qs\"WMZ1vYR$s'B\r7QYBdYm!4PE71[Bk/Ina7^}7]BrK9o!;l5(fAzIaca/\ra\nA\rmF!AC]!bIB^\t)AY\"A9B!C<\tQ1\t%a31CqB0w#\t!b/I!ga/\ra\nk\rmF!AC]!OB^\t)AmY\"A9B! <\tQ1\t%\t51CqBEw#\t!b/Iqia/\ra\nmF!AC]!\"TB^\t)AAY\"A9B!C*<\tQ1\t%161CqBZw#\t!b/IAla/\ra\nc!CgabY8qs\"WMZ1vYR$(v]8`B~{y\"AqC\t!ibMAQC\t3!Y\" \"fzIaca<\ra\nA\r=H!AC]!bIBx\t)Ay\"A9B!Cp\tQ1\t%a3qCqB0_$\t!b/I!ga<\ra\nk\r=H!AC]!OBx\t)Amy\"A9B! p\tQ1\t%\t5qCqBE_$\t!b/Iqia<\ra\n=H!AC]!\"TBx\t)AAy\"A9B!C*p\tQ1\t%16qCqBZ_$\t!b/IAla<\ra\n\tK!C\tO\tabY8qs\"WMZ1vYR$(*-BQC\tc!\"8eB1C\t!\tbFC\nC&\t\"y\"TU#fAzIab\t\ra\nA\rB!AC]!b\tC\t)A\"\"A9B!C$\tQ1\t%aC1CqB0\tG!\t!b/I!b\t\ra\nk\rB!AC]!C\t)Am\"\"A9B! $\tQ1\t%\tE1CqBE\tG!\t!b/Iq\tb\t\ra\n\rB!AC]!\"C\t)AA#\"A9B!C*$\tQ1\t%1F1CqBZ\tG!\t!b/IAb\t\ra\n\t3!C\t7\nqbY8qs\"WMZ1vYR$M/\t;\"y\"dDq\rC5\tW\"ibrMDQC<\ts\"Y\"  E1CC\t#IIK7s\"BC,\t)A\"9\"A9B!CX\tQ1\t%1CqCqB*\t/\"\t!b/IAb\ra\n_]C!AC]!B\rC,\t)AU\"9\"A9B!X\tQ1\t%YDqCqB?\t/\"\t!b/I\tb\ra\n\t]C!AC]!bC,\t)A)#9\"A9B!C'X\tQ1\t%FqCqBT\t/\"\t!b/Iab\ra\n3]C!AC]!C,\t)A\t5!%A=aD2paf$C-4bk2$H%M]EE1CK\t/#I\nb'}ECR\tK#9\"+,5FqCY\tg#)b.:mFQs\teD!\tQ1\t%C1CqB$\t#\t!b/Iab#\ra\nS-E!AC]!CF\t)A=\"Y\t\"A9B!\tQ1\t%)D1CqB9\t#\t!b/I1b#\ra\n}-E!AC]!\"CF\t)A#Y\t\"A9B!C$\tQ1\t%QE1CqBN\t#\t!b/Ib#\ra\n'-E!AC]!BCF\t)Ae#Y\t\"A9B!/\tQ1%!\t\rAI\n!-Ad_BLHZ3gCVdGJ3+9\")\rb2J-GQCh\t#$\"6XeG1Co\t?$\tb9fHCv\t[$y\"=+qIB\t#\t!b/Ib0\ra\nG}F!AC]!B\nC`\t)A%\"y\"A9B!@\tQ1\t%yCqCqB3\t#\t!b/IQb0\ra\nq}F!AC]!bC`\t)Ay\"y\"A9B!C!@\tQ1\t%!EqCqBH\t#\t!b/I!\nb0\ra\n}F!AC]!C`\t)AM#y\"A9B!,@\tQ1\t%IFqCqB]\t#\t!b/!IAQAq_G>\n3fM,H2gUqC C~\t{$y0\"QqAC)i!bMQQCC3)Y\"\" R1ECU\ry$\n-MH!AC]!\tCz\t)A\r\"\"A9B!t\tQ1\t%IC1CqB-\tg$\t!b/Iqb=\ra\neMH!AC]!\"Cz\t)Aa\"\"A9B!Ct\tQ1\t%qD1CqBB\tg$\t!b/IA\tb=\ra\nMH!AC]!BCz\t)A5#\"A9B!)t\tQ1\t%F1CqBW\tg$\t!b/Ib=\ra\n9MH!AC]A\"\"#%\t!b\r|/eKW;%cQ*b&\"0ER1GCo)I$b>}RIC\"*9%\"L5SqJC)'*)&bZ)!I!Y)9\"A9B!(\tQ1\t%SqCqB'O!\t!b/I&b\n\ra\nYB!AC]!bLC\t)AI*9\"A9B!C(\tQ1\t%ATqCqB<O!\t!b/Ia(b\n\ra\nB!AC]!RC\t)A+9\"A9B!&(\tQ1\t%iUqCqBQO!\t!b/I1+b\n\ra\n-B!AC]!\"WC\t)Aq+9\"A9\"CC/EIAC0=w]=%I4-7uIE*TCLC1G*)'bj-TQNC8c*(\"xeT1PC?*\t)b!URCFS3!B=\t%1R1CqB!7\"\t!b/I1%b\ra\nMmC!AC]!\"KC.\t)A1*Y\"A9B!C\\tQ1\t%T1CqB67\"\t!b/I(b\ra\nwmC!AC]!BPC.\t)A+Y\"A9B!#\\tQ1\t%9U1CqBK7\"\t!b/IQ*b\ra\n!mC!AC]!bUC.\t)AY+Y\"A9B!C-\\tQ1\t%aV1CqC\t\n\"y1m9zI,g-Y;mi\nd']UTCN;+y*\")$VqUCUW+i+b,2MVQWC\s+Y,\"0@'f%zIa#b$\ra\nA=E!AC]!bICH\t)A*y\t\"A9B!C\tQ1\t%aSqCqB0#\t!b/I!'b$\ra\nk=E!AC]!OCH\t)Am*y\t\"A9B! \tQ1\t%\tUqCqBE#\t!b/Iq)b$\ra\n=E!AC]!\"TCH\t)AA+y\t\"A9B!C*\tQ1\t%1VqCqBZ#\t!b/IA,b$\ra\n!CqbY8qs\"WMZ1vYR$gN/,Y-\"4PEW1[Ck/,I.b7^}W]CrK,9/\";l5Xq^Cyg,)PKLs\"BFCb\t)A*\r\"A9B!CD\tQ1\t%1S1CqB*$\t!b/IA&b1\ra\n_\rG!AC]!BMCb\t)AU*\r\"A9B!D\tQ1\t%YT1CqB?$\t!b/I)b1\ra\n\t\rG!AC]!bRCb\t)A)+\r\"A9B!C'D\tQ1\t%V1CqBT$\t!b/Ia+b1\ra\n3\rG!AC]!XCb\t)A\te!%AmaD2paf$C-4bk2$H%\r]uXq D\r1)Ab\n-aQD\r#1B\"ea1D\r?1\tCb\t&b\neD!x\tQ1\t%SqCqB$o$\t!b/Ia%b>\ra\nS]H!AC]!LC|\t)A=*9\"A9B!x\tQ1\t%)TqCqB9o$\t!b/I1(b>\ra\n}]H!AC]!\"QC|\t)A+9\"A9B!C$x\tQ1\t%QUqCqBNo$\t!b/I+b>\ra\n']H!AC]!BVC|\t)Ae+9\"A9B!/x\tQ1%1iAI\n1y#Ad_BLHZ3gCVdGJ:+92\tDb\r6]bD\r{1yD\"Dcq\tD%\r2iEbRMcQD,\r32YF\"+EIB\rW!\t!b/IEb\ra\nG-B!AC]!B\nD\t)A%2Y\"A9B!,\tQ1\t%yc1CqB3\rW!\t!b/IQGb\ra\nq-B!AC]!bD\t)Ay2Y\"A9B!C!,\tQ1\t%!e1CqBH\rW!\t!b/I!Jb\ra\n-B!AC]!D\t)AM3Y\"A9B!,,\tQ1\t%If1CqB]\rW!\t!b/!Ia\ra1MG>\n3fM,H3aUqcQ\rD4\rS2YG\"pEd1D;\ro2IHb~}dDB\r39I\"#5eqDIU\r!&\n-}C!AC]!\tD0\t)A\r2y\"A9B!`\tQ1\t%IcqCqB-\r?\"\t!b/IqFb\ra\ne}C!AC]!\"D0\t)Aa2y\"A9B!C`\tQ1\t%qdqCqBB\r?\"\t!b/IAIb\ra\n}C!AC]!BD0\t)A53y\"A9B!)`\tQ1\t%fqCqBW\r?\"\t!b/ILb\ra\n9}C!AC]AB\"&#%\tAb&\r|/eKW;%eE*bF\"'ueqDQ\rG3)Kb**-fQDX\rc3L\".8ef1D_\r3\tMb1F*qK!Y1\n\"A9B!\tQ1\t%c1CqB'\r'#\t!b/IFb%\ra\nYME!AC]!bDJ\t)AI2\n\"A9B!C\tQ1\t%Ad1CqB<\r'#\t!b/IaHb%\ra\nME!AC]!DJ\t)A3\n\"A9B!&\tQ1\t%ie1CqBQ\r'#\t!b/I1Kb%\ra\n-ME!AC]!\"DJ\t)Aq3\n\"A9\"DeEIDf=w]=%I4-7uIITCDg\r4\tNb5V]gDn\r;4yN\"9dhqDu\rW4iOb<rMhQD|\rsT3AB=\t%1bqCqB!\r$\t!b/I1Eb2\ra\nMG!AC]!\"Dd\t)A129\r\"A9B!CH\tQ1\t%dqCqB6\r$\t!b/IHb2\ra\nwG!AC]!BDd\t)A39\r\"A9B!#H\tQ1\t%9eqCqBK\r$\t!b/IQJb2\ra\n!G!AC]!bDd\t)AY39\r\"A9B!C-H\tQ1\t%afqCq~!\t!C!\r[1tQ{G-2ED\r9)A:$BCD\t\"1Q-];bYN$Ba\"Acb\nE!AAC_>dW-8\tUqqAAYa=%c!Qq%\tebAxZ;diBXMZ5y+\t\ti !\t!C!C\tbY1oF,\r9Cu!a7!ab\nA9I#C,\tAb]3sSdN_1cY<bbE)a\"\rQ+\33eAcb\rA1!A\tU2BDuC\"!*4qcA!b\"4IQD \t7z+9:\tebL=s1KD,7:yfbh-tqND:o:Yhb u1RDH';9jb']\rsQTDPC;k\"*(%v1VDW_;\tlb-6]vXD^{;yl\"1Dwq\t/!9)e\"NEsQKD-;:\tg\"j5tOD;s:ih\"!%uQRDI+;I\nE\"BFD\t)AQ9YB!w!\t!b/AAcb\r:Y\"A9cTIaeb\ra\t)]C!C<\tQ1!\r!r1\nYmB!AC]2FD0\t%ys1CqEG\"BMD\t)AQ99B6w!\t!b/AAcba:Y\"A9cpI1hb\ra\t)MD! <\tQ1!\r!rq\nmB!AC]2FD>\t%!u1CqE\"bRD\t)AQ9\tBKw!\t!b/AAcb\"5;Y\"A9cIkb\ra\t)=E!C*<\tQ1!\r!r1\n-mB!AC]2FDL\t%Iv1CqE7#XD\t)A\t<Y1F!9nbA%b8<qQ\ngmAD)Ax1a+Bq!`D9ImAD/!\tyabACA\rw\ra\"\t\rr1aSB\"!<qQ\to9Y1r!AID9)LmAD=!\t)fbAuCA0w\ra\"!\t%t1aC\"a<q\t{:Y1\"AqQD9\t\nmADK!\tYjbAeBCDfg\t\t\"!N9QO\1qa2LXCLDh7<ynb9h-xq^Dzo<Ypb@\t!2E'A9c\t !\rrE_!Ba\"5\t2A)cb5X&qQ\r=H/[8o!9a\"7^xQ]Du[<\tp\">zuEAi#\t!eREKAI#Q9YB$\t!b/AAcb8:I\r\"A9cdI1e\"3\ra\t)H!J\tQ1!\r!r1\nS%G!AC]2FDx\t%asCqEg$bLDe\t)AQ99B3$\t!b/AAcb?U:I\r\"A9c Ih\"3\ra\t)!\rA!CJ\tQ1!\r!r\n}%G!AC]2E\t%\tuCqE!RDe\t)AQABH$\t!b/AAc);I\r\"A9c\tIQj\"3\ra\t)!}A!)J\tQ1!\r!2\n'%G!AC]2E\t%1vCqEW!\"WDe\t)AQAyB]$\t!b/!A2GDe99.AyIA;
Asciz	RuntimeVisibleAnnotations;
Asciz	scala/Product22;
class	scala/Product22
Asciz	scala/ScalaObject;
class	scala/ScalaObject
Asciz	scala/Product;
class	scala/Product
Asciz	java/io/Serializable;
class	java/io/Serializable

{
private final java.lang.Object _1;
  Signature: Ljava/lang/Object;
  Signature: length = 0x2
   00 05 

private final java.lang.Object _2;
  Signature: Ljava/lang/Object;
  Signature: length = 0x2
   00 08 

private final java.lang.Object _3;
  Signature: Ljava/lang/Object;
  Signature: length = 0x2
   00 0A 

private final java.lang.Object _4;
  Signature: Ljava/lang/Object;
  Signature: length = 0x2
   00 0C 

private final java.lang.Object _5;
  Signature: Ljava/lang/Object;
  Signature: length = 0x2
   00 0E 

private final java.lang.Object _6;
  Signature: Ljava/lang/Object;
  Signature: length = 0x2
   00 10 

private final java.lang.Object _7;
  Signature: Ljava/lang/Object;
  Signature: length = 0x2
   00 12 

private final java.lang.Object _8;
  Signature: Ljava/lang/Object;
  Signature: length = 0x2
   00 14 

private final java.lang.Object _9;
  Signature: Ljava/lang/Object;
  Signature: length = 0x2
   00 16 

private final java.lang.Object _10;
  Signature: Ljava/lang/Object;
  Signature: length = 0x2
   00 18 

private final java.lang.Object _11;
  Signature: Ljava/lang/Object;
  Signature: length = 0x2
   00 1A 

private final java.lang.Object _12;
  Signature: Ljava/lang/Object;
  Signature: length = 0x2
   00 1C 

private final java.lang.Object _13;
  Signature: Ljava/lang/Object;
  Signature: length = 0x2
   00 1E 

private final java.lang.Object _14;
  Signature: Ljava/lang/Object;
  Signature: length = 0x2
   00 20 

private final java.lang.Object _15;
  Signature: Ljava/lang/Object;
  Signature: length = 0x2
   00 22 

private final java.lang.Object _16;
  Signature: Ljava/lang/Object;
  Signature: length = 0x2
   00 24 

private final java.lang.Object _17;
  Signature: Ljava/lang/Object;
  Signature: length = 0x2
   00 26 

private final java.lang.Object _18;
  Signature: Ljava/lang/Object;
  Signature: length = 0x2
   00 28 

private final java.lang.Object _19;
  Signature: Ljava/lang/Object;
  Signature: length = 0x2
   00 2A 

private final java.lang.Object _20;
  Signature: Ljava/lang/Object;
  Signature: length = 0x2
   00 2C 

private final java.lang.Object _21;
  Signature: Ljava/lang/Object;
  Signature: length = 0x2
   00 2E 

private final java.lang.Object _22;
  Signature: Ljava/lang/Object;
  Signature: length = 0x2
   00 30 

public int productArity();
  Signature: ()I
  Code:
   Stack=1, Locals=1, Args_size=1
	aload_0
	invokestatic	Method scala/Product22$class.productArity:(Lscala/Product22;)I
	ireturn
  Labels:

public java.lang.Object productElement(int)   throws java.lang.IndexOutOfBoundsException;
  Signature: (I)Ljava/lang/Object;
  Code:
   Stack=2, Locals=2, Args_size=2
	aload_0
	iload_1
	invokestatic	Method scala/Product22$class.productElement:(Lscala/Product22;I)Ljava/lang/Object;
	areturn
  Labels:
  LocalVariableTable: 
   Start  Length  Slot  Name   Signature
   0      6      0    this       Lscala/Tuple22;
   0      6      1    n       I

  Exceptions: 
   throws java.lang.IndexOutOfBoundsException
public java.lang.String productElementName(int);
  Signature: (I)Ljava/lang/String;
  Code:
   Stack=2, Locals=2, Args_size=2
	aload_0
	iload_1
	invokestatic	Method scala/Product$class.productElementName:(Lscala/Product;I)Ljava/lang/String;
	areturn
  Labels:
  LocalVariableTable: 
   Start  Length  Slot  Name   Signature
   0      6      0    this       Lscala/Tuple22;
   0      6      1    n       I


public scala.collection.Iterator productIterator();
  Signature: ()Lscala/collection/Iterator;
  Code:
   Stack=1, Locals=1, Args_size=1
	aload_0
	invokestatic	Method scala/Product$class.productIterator:(Lscala/Product;)Lscala/collection/Iterator;
	areturn
  Labels:

public scala.collection.Iterator productElements();
  Signature: ()Lscala/collection/Iterator;
  Code:
   Stack=1, Locals=1, Args_size=1
	aload_0
	invokestatic	Method scala/Product$class.productElements:(Lscala/Product;)Lscala/collection/Iterator;
	areturn
  Labels:
  Deprecated: true

public java.lang.Object copy$default$22();
  Signature: ()Ljava/lang/Object;
  Code:
   Stack=1, Locals=1, Args_size=1
	aload_0
	invokevirtual	Method _22:()Ljava/lang/Object;
	areturn
  Labels:

public java.lang.Object copy$default$21();
  Signature: ()Ljava/lang/Object;
  Code:
   Stack=1, Locals=1, Args_size=1
	aload_0
	invokevirtual	Method _21:()Ljava/lang/Object;
	areturn
  Labels:

public java.lang.Object copy$default$20();
  Signature: ()Ljava/lang/Object;
  Code:
   Stack=1, Locals=1, Args_size=1
	aload_0
	invokevirtual	Method _20:()Ljava/lang/Object;
	areturn
  Labels:

public java.lang.Object copy$default$19();
  Signature: ()Ljava/lang/Object;
  Code:
   Stack=1, Locals=1, Args_size=1
	aload_0
	invokevirtual	Method _19:()Ljava/lang/Object;
	areturn
  Labels:

public java.lang.Object copy$default$18();
  Signature: ()Ljava/lang/Object;
  Code:
   Stack=1, Locals=1, Args_size=1
	aload_0
	invokevirtual	Method _18:()Ljava/lang/Object;
	areturn
  Labels:

public java.lang.Object copy$default$17();
  Signature: ()Ljava/lang/Object;
  Code:
   Stack=1, Locals=1, Args_size=1
	aload_0
	invokevirtual	Method _17:()Ljava/lang/Object;
	areturn
  Labels:

public java.lang.Object copy$default$16();
  Signature: ()Ljava/lang/Object;
  Code:
   Stack=1, Locals=1, Args_size=1
	aload_0
	invokevirtual	Method _16:()Ljava/lang/Object;
	areturn
  Labels:

public java.lang.Object copy$default$15();
  Signature: ()Ljava/lang/Object;
  Code:
   Stack=1, Locals=1, Args_size=1
	aload_0
	invokevirtual	Method _15:()Ljava/lang/Object;
	areturn
  Labels:

public java.lang.Object copy$default$14();
  Signature: ()Ljava/lang/Object;
  Code:
   Stack=1, Locals=1, Args_size=1
	aload_0
	invokevirtual	Method _14:()Ljava/lang/Object;
	areturn
  Labels:

public java.lang.Object copy$default$13();
  Signature: ()Ljava/lang/Object;
  Code:
   Stack=1, Locals=1, Args_size=1
	aload_0
	invokevirtual	Method _13:()Ljava/lang/Object;
	areturn
  Labels:

public java.lang.Object copy$default$12();
  Signature: ()Ljava/lang/Object;
  Code:
   Stack=1, Locals=1, Args_size=1
	aload_0
	invokevirtual	Method _12:()Ljava/lang/Object;
	areturn
  Labels:

public java.lang.Object copy$default$11();
  Signature: ()Ljava/lang/Object;
  Code:
   Stack=1, Locals=1, Args_size=1
	aload_0
	invokevirtual	Method _11:()Ljava/lang/Object;
	areturn
  Labels:

public java.lang.Object copy$default$10();
  Signature: ()Ljava/lang/Object;
  Code:
   Stack=1, Locals=1, Args_size=1
	aload_0
	invokevirtual	Method _10:()Ljava/lang/Object;
	areturn
  Labels:

public java.lang.Object copy$default$9();
  Signature: ()Ljava/lang/Object;
  Code:
   Stack=1, Locals=1, Args_size=1
	aload_0
	invokevirtual	Method _9:()Ljava/lang/Object;
	areturn
  Labels:

public java.lang.Object copy$default$8();
  Signature: ()Ljava/lang/Object;
  Code:
   Stack=1, Locals=1, Args_size=1
	aload_0
	invokevirtual	Method _8:()Ljava/lang/Object;
	areturn
  Labels:

public java.lang.Object copy$default$7();
  Signature: ()Ljava/lang/Object;
  Code:
   Stack=1, Locals=1, Args_size=1
	aload_0
	invokevirtual	Method _7:()Ljava/lang/Object;
	areturn
  Labels:

public java.lang.Object copy$default$6();
  Signature: ()Ljava/lang/Object;
  Code:
   Stack=1, Locals=1, Args_size=1
	aload_0
	invokevirtual	Method _6:()Ljava/lang/Object;
	areturn
  Labels:

public java.lang.Object copy$default$5();
  Signature: ()Ljava/lang/Object;
  Code:
   Stack=1, Locals=1, Args_size=1
	aload_0
	invokevirtual	Method _5:()Ljava/lang/Object;
	areturn
  Labels:

public java.lang.Object copy$default$4();
  Signature: ()Ljava/lang/Object;
  Code:
   Stack=1, Locals=1, Args_size=1
	aload_0
	invokevirtual	Method _4:()Ljava/lang/Object;
	areturn
  Labels:

public java.lang.Object copy$default$3();
  Signature: ()Ljava/lang/Object;
  Code:
   Stack=1, Locals=1, Args_size=1
	aload_0
	invokevirtual	Method _3:()Ljava/lang/Object;
	areturn
  Labels:

public java.lang.Object copy$default$2();
  Signature: ()Ljava/lang/Object;
  Code:
   Stack=1, Locals=1, Args_size=1
	aload_0
	invokevirtual	Method _2:()Ljava/lang/Object;
	areturn
  Labels:

public java.lang.Object copy$default$1();
  Signature: ()Ljava/lang/Object;
  Code:
   Stack=1, Locals=1, Args_size=1
	aload_0
	invokevirtual	Method _1:()Ljava/lang/Object;
	areturn
  Labels:

public java.lang.Object _1();
  Signature: ()Ljava/lang/Object;
  Code:
   Stack=1, Locals=1, Args_size=1
	aload_0
	getfield	Field _1:Ljava/lang/Object;
	areturn
  Labels:
  Signature: length = 0x2
   00 FFFFFF9E 

public java.lang.Object _2();
  Signature: ()Ljava/lang/Object;
  Code:
   Stack=1, Locals=1, Args_size=1
	aload_0
	getfield	Field _2:Ljava/lang/Object;
	areturn
  Labels:
  Signature: length = 0x2
   00 FFFFFFA1 

public java.lang.Object _3();
  Signature: ()Ljava/lang/Object;
  Code:
   Stack=1, Locals=1, Args_size=1
	aload_0
	getfield	Field _3:Ljava/lang/Object;
	areturn
  Labels:
  Signature: length = 0x2
   00 FFFFFFA4 

public java.lang.Object _4();
  Signature: ()Ljava/lang/Object;
  Code:
   Stack=1, Locals=1, Args_size=1
	aload_0
	getfield	Field _4:Ljava/lang/Object;
	areturn
  Labels:
  Signature: length = 0x2
   00 FFFFFFA7 

public java.lang.Object _5();
  Signature: ()Ljava/lang/Object;
  Code:
   Stack=1, Locals=1, Args_size=1
	aload_0
	getfield	Field _5:Ljava/lang/Object;
	areturn
  Labels:
  Signature: length = 0x2
   00 FFFFFFAA 

public java.lang.Object _6();
  Signature: ()Ljava/lang/Object;
  Code:
   Stack=1, Locals=1, Args_size=1
	aload_0
	getfield	Field _6:Ljava/lang/Object;
	areturn
  Labels:
  Signature: length = 0x2
   00 FFFFFFAD 

public java.lang.Object _7();
  Signature: ()Ljava/lang/Object;
  Code:
   Stack=1, Locals=1, Args_size=1
	aload_0
	getfield	Field _7:Ljava/lang/Object;
	areturn
  Labels:
  Signature: length = 0x2
   00 FFFFFFB0 

public java.lang.Object _8();
  Signature: ()Ljava/lang/Object;
  Code:
   Stack=1, Locals=1, Args_size=1
	aload_0
	getfield	Field _8:Ljava/lang/Object;
	areturn
  Labels:
  Signature: length = 0x2
   00 FFFFFFB3 

public java.lang.Object _9();
  Signature: ()Ljava/lang/Object;
  Code:
   Stack=1, Locals=1, Args_size=1
	aload_0
	getfield	Field _9:Ljava/lang/Object;
	areturn
  Labels:
  Signature: length = 0x2
   00 FFFFFFB6 

public java.lang.Object _10();
  Signature: ()Ljava/lang/Object;
  Code:
   Stack=1, Locals=1, Args_size=1
	aload_0
	getfield	Field _10:Ljava/lang/Object;
	areturn
  Labels:
  Signature: length = 0x2
   00 FFFFFFB9 

public java.lang.Object _11();
  Signature: ()Ljava/lang/Object;
  Code:
   Stack=1, Locals=1, Args_size=1
	aload_0
	getfield	Field _11:Ljava/lang/Object;
	areturn
  Labels:
  Signature: length = 0x2
   00 FFFFFFBC 

public java.lang.Object _12();
  Signature: ()Ljava/lang/Object;
  Code:
   Stack=1, Locals=1, Args_size=1
	aload_0
	getfield	Field _12:Ljava/lang/Object;
	areturn
  Labels:
  Signature: length = 0x2
   00 FFFFFFBF 

public java.lang.Object _13();
  Signature: ()Ljava/lang/Object;
  Code:
   Stack=1, Locals=1, Args_size=1
	aload_0
	getfield	Field _13:Ljava/lang/Object;
	areturn
  Labels:
  Signature: length = 0x2
   00 FFFFFFC2 

public java.lang.Object _14();
  Signature: ()Ljava/lang/Object;
  Code:
   Stack=1, Locals=1, Args_size=1
	aload_0
	getfield	Field _14:Ljava/lang/Object;
	areturn
  Labels:
  Signature: length = 0x2
   00 FFFFFFC5 

public java.lang.Object _15();
  Signature: ()Ljava/lang/Object;
  Code:
   Stack=1, Locals=1, Args_size=1
	aload_0
	getfield	Field _15:Ljava/lang/Object;
	areturn
  Labels:
  Signature: length = 0x2
   00 FFFFFFC8 

public java.lang.Object _16();
  Signature: ()Ljava/lang/Object;
  Code:
   Stack=1, Locals=1, Args_size=1
	aload_0
	getfield	Field _16:Ljava/lang/Object;
	areturn
  Labels:
  Signature: length = 0x2
   00 FFFFFFCB 

public java.lang.Object _17();
  Signature: ()Ljava/lang/Object;
  Code:
   Stack=1, Locals=1, Args_size=1
	aload_0
	getfield	Field _17:Ljava/lang/Object;
	areturn
  Labels:
  Signature: length = 0x2
   00 FFFFFFCE 

public java.lang.Object _18();
  Signature: ()Ljava/lang/Object;
  Code:
   Stack=1, Locals=1, Args_size=1
	aload_0
	getfield	Field _18:Ljava/lang/Object;
	areturn
  Labels:
  Signature: length = 0x2
   00 FFFFFFD1 

public java.lang.Object _19();
  Signature: ()Ljava/lang/Object;
  Code:
   Stack=1, Locals=1, Args_size=1
	aload_0
	getfield	Field _19:Ljava/lang/Object;
	areturn
  Labels:
  Signature: length = 0x2
   00 FFFFFFD4 

public java.lang.Object _20();
  Signature: ()Ljava/lang/Object;
  Code:
   Stack=1, Locals=1, Args_size=1
	aload_0
	getfield	Field _20:Ljava/lang/Object;
	areturn
  Labels:
  Signature: length = 0x2
   00 FFFFFFD7 

public java.lang.Object _21();
  Signature: ()Ljava/lang/Object;
  Code:
   Stack=1, Locals=1, Args_size=1
	aload_0
	getfield	Field _21:Ljava/lang/Object;
	areturn
  Labels:
  Signature: length = 0x2
   00 FFFFFFDA 

public java.lang.Object _22();
  Signature: ()Ljava/lang/Object;
  Code:
   Stack=1, Locals=1, Args_size=1
	aload_0
	getfield	Field _22:Ljava/lang/Object;
	areturn
  Labels:
  Signature: length = 0x2
   00 FFFFFFDD 

public java.lang.String toString();
  Signature: ()Ljava/lang/String;
  Code:
   Stack=2, Locals=1, Args_size=1
	new	class scala/collection/mutable/StringBuilder
	dup
	invokespecial	Method scala/collection/mutable/StringBuilder."<init>":()V
	ldc	String (
	invokevirtual	Method scala/collection/mutable/StringBuilder.append:(Ljava/lang/Object;)Lscala/collection/mutable/StringBuilder;
	aload_0
	invokevirtual	Method _1:()Ljava/lang/Object;
	invokevirtual	Method scala/collection/mutable/StringBuilder.append:(Ljava/lang/Object;)Lscala/collection/mutable/StringBuilder;
	ldc	String ,
	invokevirtual	Method scala/collection/mutable/StringBuilder.append:(Ljava/lang/Object;)Lscala/collection/mutable/StringBuilder;
	aload_0
	invokevirtual	Method _2:()Ljava/lang/Object;
	invokevirtual	Method scala/collection/mutable/StringBuilder.append:(Ljava/lang/Object;)Lscala/collection/mutable/StringBuilder;
	ldc	String ,
	invokevirtual	Method scala/collection/mutable/StringBuilder.append:(Ljava/lang/Object;)Lscala/collection/mutable/StringBuilder;
	aload_0
	invokevirtual	Method _3:()Ljava/lang/Object;
	invokevirtual	Method scala/collection/mutable/StringBuilder.append:(Ljava/lang/Object;)Lscala/collection/mutable/StringBuilder;
	ldc	String ,
	invokevirtual	Method scala/collection/mutable/StringBuilder.append:(Ljava/lang/Object;)Lscala/collection/mutable/StringBuilder;
	aload_0
	invokevirtual	Method _4:()Ljava/lang/Object;
	invokevirtual	Method scala/collection/mutable/StringBuilder.append:(Ljava/lang/Object;)Lscala/collection/mutable/StringBuilder;
	ldc	String ,
	invokevirtual	Method scala/collection/mutable/StringBuilder.append:(Ljava/lang/Object;)Lscala/collection/mutable/StringBuilder;
	aload_0
	invokevirtual	Method _5:()Ljava/lang/Object;
	invokevirtual	Method scala/collection/mutable/StringBuilder.append:(Ljava/lang/Object;)Lscala/collection/mutable/StringBuilder;
	ldc	String ,
	invokevirtual	Method scala/collection/mutable/StringBuilder.append:(Ljava/lang/Object;)Lscala/collection/mutable/StringBuilder;
	aload_0
	invokevirtual	Method _6:()Ljava/lang/Object;
	invokevirtual	Method scala/collection/mutable/StringBuilder.append:(Ljava/lang/Object;)Lscala/collection/mutable/StringBuilder;
	ldc	String ,
	invokevirtual	Method scala/collection/mutable/StringBuilder.append:(Ljava/lang/Object;)Lscala/collection/mutable/StringBuilder;
	aload_0
	invokevirtual	Method _7:()Ljava/lang/Object;
	invokevirtual	Method scala/collection/mutable/StringBuilder.append:(Ljava/lang/Object;)Lscala/collection/mutable/StringBuilder;
	ldc	String ,
	invokevirtual	Method scala/collection/mutable/StringBuilder.append:(Ljava/lang/Object;)Lscala/collection/mutable/StringBuilder;
	aload_0
	invokevirtual	Method _8:()Ljava/lang/Object;
	invokevirtual	Method scala/collection/mutable/StringBuilder.append:(Ljava/lang/Object;)Lscala/collection/mutable/StringBuilder;
	ldc	String ,
	invokevirtual	Method scala/collection/mutable/StringBuilder.append:(Ljava/lang/Object;)Lscala/collection/mutable/StringBuilder;
	aload_0
	invokevirtual	Method _9:()Ljava/lang/Object;
	invokevirtual	Method scala/collection/mutable/StringBuilder.append:(Ljava/lang/Object;)Lscala/collection/mutable/StringBuilder;
	ldc	String ,
	invokevirtual	Method scala/collection/mutable/StringBuilder.append:(Ljava/lang/Object;)Lscala/collection/mutable/StringBuilder;
	aload_0
	invokevirtual	Method _10:()Ljava/lang/Object;
	invokevirtual	Method scala/collection/mutable/StringBuilder.append:(Ljava/lang/Object;)Lscala/collection/mutable/StringBuilder;
	ldc	String ,
	invokevirtual	Method scala/collection/mutable/StringBuilder.append:(Ljava/lang/Object;)Lscala/collection/mutable/StringBuilder;
	aload_0
	invokevirtual	Method _11:()Ljava/lang/Object;
	invokevirtual	Method scala/collection/mutable/StringBuilder.append:(Ljava/lang/Object;)Lscala/collection/mutable/StringBuilder;
	ldc	String ,
	invokevirtual	Method scala/collection/mutable/StringBuilder.append:(Ljava/lang/Object;)Lscala/collection/mutable/StringBuilder;
	aload_0
	invokevirtual	Method _12:()Ljava/lang/Object;
	invokevirtual	Method scala/collection/mutable/StringBuilder.append:(Ljava/lang/Object;)Lscala/collection/mutable/StringBuilder;
	ldc	String ,
	invokevirtual	Method scala/collection/mutable/StringBuilder.append:(Ljava/lang/Object;)Lscala/collection/mutable/StringBuilder;
	aload_0
	invokevirtual	Method _13:()Ljava/lang/Object;
	invokevirtual	Method scala/collection/mutable/StringBuilder.append:(Ljava/lang/Object;)Lscala/collection/mutable/StringBuilder;
	ldc	String ,
	invokevirtual	Method scala/collection/mutable/StringBuilder.append:(Ljava/lang/Object;)Lscala/collection/mutable/StringBuilder;
	aload_0
	invokevirtual	Method _14:()Ljava/lang/Object;
	invokevirtual	Method scala/collection/mutable/StringBuilder.append:(Ljava/lang/Object;)Lscala/collection/mutable/StringBuilder;
	ldc	String ,
	invokevirtual	Method scala/collection/mutable/StringBuilder.append:(Ljava/lang/Object;)Lscala/collection/mutable/StringBuilder;
	aload_0
	invokevirtual	Method _15:()Ljava/lang/Object;
	invokevirtual	Method scala/collection/mutable/StringBuilder.append:(Ljava/lang/Object;)Lscala/collection/mutable/StringBuilder;
	ldc	String ,
	invokevirtual	Method scala/collection/mutable/StringBuilder.append:(Ljava/lang/Object;)Lscala/collection/mutable/StringBuilder;
	aload_0
	invokevirtual	Method _16:()Ljava/lang/Object;
	invokevirtual	Method scala/collection/mutable/StringBuilder.append:(Ljava/lang/Object;)Lscala/collection/mutable/StringBuilder;
	ldc	String ,
	invokevirtual	Method scala/collection/mutable/StringBuilder.append:(Ljava/lang/Object;)Lscala/collection/mutable/StringBuilder;
	aload_0
	invokevirtual	Method _17:()Ljava/lang/Object;
	invokevirtual	Method scala/collection/mutable/StringBuilder.append:(Ljava/lang/Object;)Lscala/collection/mutable/StringBuilder;
	ldc	String ,
	invokevirtual	Method scala/collection/mutable/StringBuilder.append:(Ljava/lang/Object;)Lscala/collection/mutable/StringBuilder;
	aload_0
	invokevirtual	Method _18:()Ljava/lang/Object;
	invokevirtual	Method scala/collection/mutable/StringBuilder.append:(Ljava/lang/Object;)Lscala/collection/mutable/StringBuilder;
	ldc	String ,
	invokevirtual	Method scala/collection/mutable/StringBuilder.append:(Ljava/lang/Object;)Lscala/collection/mutable/StringBuilder;
	aload_0
	invokevirtual	Method _19:()Ljava/lang/Object;
	invokevirtual	Method scala/collection/mutable/StringBuilder.append:(Ljava/lang/Object;)Lscala/collection/mutable/StringBuilder;
	ldc	String ,
	invokevirtual	Method scala/collection/mutable/StringBuilder.append:(Ljava/lang/Object;)Lscala/collection/mutable/StringBuilder;
	aload_0
	invokevirtual	Method _20:()Ljava/lang/Object;
	invokevirtual	Method scala/collection/mutable/StringBuilder.append:(Ljava/lang/Object;)Lscala/collection/mutable/StringBuilder;
	ldc	String ,
	invokevirtual	Method scala/collection/mutable/StringBuilder.append:(Ljava/lang/Object;)Lscala/collection/mutable/StringBuilder;
	aload_0
	invokevirtual	Method _21:()Ljava/lang/Object;
	invokevirtual	Method scala/collection/mutable/StringBuilder.append:(Ljava/lang/Object;)Lscala/collection/mutable/StringBuilder;
	ldc	String ,
	invokevirtual	Method scala/collection/mutable/StringBuilder.append:(Ljava/lang/Object;)Lscala/collection/mutable/StringBuilder;
	aload_0
	invokevirtual	Method _22:()Ljava/lang/Object;
	invokevirtual	Method scala/collection/mutable/StringBuilder.append:(Ljava/lang/Object;)Lscala/collection/mutable/StringBuilder;
	ldc	String )
	invokevirtual	Method scala/collection/mutable/StringBuilder.append:(Ljava/lang/Object;)Lscala/collection/mutable/StringBuilder;
	invokevirtual	Method scala/collection/mutable/StringBuilder.toString:()Ljava/lang/String;
	areturn
  Labels:

public scala.Tuple22 copy(java.lang.Object, java.lang.Object, java.lang.Object, java.lang.Object, java.lang.Object, java.lang.Object, java.lang.Object, java.lang.Object, java.lang.Object, java.lang.Object, java.lang.Object, java.lang.Object, java.lang.Object, java.lang.Object, java.lang.Object, java.lang.Object, java.lang.Object, java.lang.Object, java.lang.Object, java.lang.Object, java.lang.Object, java.lang.Object);
  Signature: (Ljava/lang/Object;Ljava/lang/Object;Ljava/lang/Object;Ljava/lang/Object;Ljava/lang/Object;Ljava/lang/Object;Ljava/lang/Object;Ljava/lang/Object;Ljava/lang/Object;Ljava/lang/Object;Ljava/lang/Object;Ljava/lang/Object;Ljava/lang/Object;Ljava/lang/Object;Ljava/lang/Object;Ljava/lang/Object;Ljava/lang/Object;Ljava/lang/Object;Ljava/lang/Object;Ljava/lang/Object;Ljava/lang/Object;Ljava/lang/Object;)Lscala/Tuple22;
  Code:
   Stack=24, Locals=23, Args_size=23
	new	class scala/Tuple22
	dup
	aload_1
	aload_2
	aload_3
	aload	4
	aload	5
	aload	6
	aload	7
	aload	8
	aload	9
	aload	10
	aload	11
	aload	12
	aload	13
	aload	14
	aload	15
	aload	16
	aload	17
	aload	18
	aload	19
	aload	20
	aload	21
	aload	22
	invokespecial	Method "<init>":(Ljava/lang/Object;Ljava/lang/Object;Ljava/lang/Object;Ljava/lang/Object;Ljava/lang/Object;Ljava/lang/Object;Ljava/lang/Object;Ljava/lang/Object;Ljava/lang/Object;Ljava/lang/Object;Ljava/lang/Object;Ljava/lang/Object;Ljava/lang/Object;Ljava/lang/Object;Ljava/lang/Object;Ljava/lang/Object;Ljava/lang/Object;Ljava/lang/Object;Ljava/lang/Object;Ljava/lang/Object;Ljava/lang/Object;Ljava/lang/Object;)V
	areturn
  Labels:
  LocalVariableTable: 
   Start  Length  Slot  Name   Signature
   0      49      0    this       Lscala/Tuple22;
   0      49      1    _1       Ljava/lang/Object;
   0      49      2    _2       Ljava/lang/Object;
   0      49      3    _3       Ljava/lang/Object;
   0      49      4    _4       Ljava/lang/Object;
   0      49      5    _5       Ljava/lang/Object;
   0      49      6    _6       Ljava/lang/Object;
   0      49      7    _7       Ljava/lang/Object;
   0      49      8    _8       Ljava/lang/Object;
   0      49      9    _9       Ljava/lang/Object;
   0      49      10    _10       Ljava/lang/Object;
   0      49      11    _11       Ljava/lang/Object;
   0      49      12    _12       Ljava/lang/Object;
   0      49      13    _13       Ljava/lang/Object;
   0      49      14    _14       Ljava/lang/Object;
   0      49      15    _15       Ljava/lang/Object;
   0      49      16    _16       Ljava/lang/Object;
   0      49      17    _17       Ljava/lang/Object;
   0      49      18    _18       Ljava/lang/Object;
   0      49      19    _19       Ljava/lang/Object;
   0      49      20    _20       Ljava/lang/Object;
   0      49      21    _21       Ljava/lang/Object;
   0      49      22    _22       Ljava/lang/Object;


public int hashCode();
  Signature: ()I
  Code:
   Stack=2, Locals=1, Args_size=1
	getstatic	Field scala/runtime/ScalaRunTime$.MODULE$:Lscala/runtime/ScalaRunTime$;
	aload_0
	invokevirtual	Method scala/runtime/ScalaRunTime$._hashCode:(Lscala/Product;)I
	ireturn
  Labels:

public boolean equals(java.lang.Object);
  Signature: (Ljava/lang/Object;)Z
  Code:
   Stack=23, Locals=25, Args_size=2
	aload_0
	aload_1
	if_acmpeq	l1 // iconst_1
	aload_1
	instanceof	class scala/Tuple22
	ifeq	l2 // iconst_0
	aload_1
	checkcast	class scala/Tuple22
	astore_2
	aload_2
	invokevirtual	Method _1:()Ljava/lang/Object;
	astore_3
	aload_2
	invokevirtual	Method _2:()Ljava/lang/Object;
	astore	4
	aload_2
	invokevirtual	Method _3:()Ljava/lang/Object;
	astore	5
	aload_2
	invokevirtual	Method _4:()Ljava/lang/Object;
	astore	6
	aload_2
	invokevirtual	Method _5:()Ljava/lang/Object;
	astore	7
	aload_2
	invokevirtual	Method _6:()Ljava/lang/Object;
	astore	8
	aload_2
	invokevirtual	Method _7:()Ljava/lang/Object;
	astore	9
	aload_2
	invokevirtual	Method _8:()Ljava/lang/Object;
	astore	10
	aload_2
	invokevirtual	Method _9:()Ljava/lang/Object;
	astore	11
	aload_2
	invokevirtual	Method _10:()Ljava/lang/Object;
	astore	12
	aload_2
	invokevirtual	Method _11:()Ljava/lang/Object;
	astore	13
	aload_2
	invokevirtual	Method _12:()Ljava/lang/Object;
	astore	14
	aload_2
	invokevirtual	Method _13:()Ljava/lang/Object;
	astore	15
	aload_2
	invokevirtual	Method _14:()Ljava/lang/Object;
	astore	16
	aload_2
	invokevirtual	Method _15:()Ljava/lang/Object;
	astore	17
	aload_2
	invokevirtual	Method _16:()Ljava/lang/Object;
	astore	18
	aload_2
	invokevirtual	Method _17:()Ljava/lang/Object;
	astore	19
	aload_2
	invokevirtual	Method _18:()Ljava/lang/Object;
	astore	20
	aload_2
	invokevirtual	Method _19:()Ljava/lang/Object;
	astore	21
	aload_2
	invokevirtual	Method _20:()Ljava/lang/Object;
	astore	22
	aload_2
	invokevirtual	Method _21:()Ljava/lang/Object;
	astore	23
	aload_2
	invokevirtual	Method _22:()Ljava/lang/Object;
	astore	24
	aload_0
	aload_3
	aload	4
	aload	5
	aload	6
	aload	7
	aload	8
	aload	9
	aload	10
	aload	11
	aload	12
	aload	13
	aload	14
	aload	15
	aload	16
	aload	17
	aload	18
	aload	19
	aload	20
	aload	21
	aload	22
	aload	23
	aload	24
	invokespecial	Method gd1$1:(Ljava/lang/Object;Ljava/lang/Object;Ljava/lang/Object;Ljava/lang/Object;Ljava/lang/Object;Ljava/lang/Object;Ljava/lang/Object;Ljava/lang/Object;Ljava/lang/Object;Ljava/lang/Object;Ljava/lang/Object;Ljava/lang/Object;Ljava/lang/Object;Ljava/lang/Object;Ljava/lang/Object;Ljava/lang/Object;Ljava/lang/Object;Ljava/lang/Object;Ljava/lang/Object;Ljava/lang/Object;Ljava/lang/Object;Ljava/lang/Object;)Z
	ifeq	l3 // iconst_0
	aload_1
	checkcast	class scala/Tuple22
	aload_0
	invokeinterface	InterfaceMethod scala/Equals.canEqual:(Ljava/lang/Object;)Z
	goto	l4 // ifeq
l3	iconst_0
	goto	l4 // ifeq
l2	iconst_0
l4	ifeq	l5 // iconst_0
l1	iconst_1
	goto	l6 // ireturn
l5	iconst_0
l6	ireturn
  Labels:
   	l3 = 211 // iconst_0
   	l2 = 215 // iconst_0
   	l4 = 216 // ifeq
   	l1 = 219 // iconst_1
   	l5 = 223 // iconst_0
   	l6 = 224 // ireturn
  LocalVariableTable: 
   Start  Length  Slot  Name   Signature
   0      225      0    this       Lscala/Tuple22;
   17      198      2    temp2       Lscala/Tuple22;
   22      193      3    temp3       Ljava/lang/Object;
   28      187      4    temp4       Ljava/lang/Object;
   34      181      5    temp5       Ljava/lang/Object;
   40      175      6    temp6       Ljava/lang/Object;
   46      169      7    temp7       Ljava/lang/Object;
   52      163      8    temp8       Ljava/lang/Object;
   58      157      9    temp9       Ljava/lang/Object;
   64      151      10    temp10       Ljava/lang/Object;
   70      145      11    temp11       Ljava/lang/Object;
   76      139      12    temp12       Ljava/lang/Object;
   82      133      13    temp13       Ljava/lang/Object;
   88      127      14    temp14       Ljava/lang/Object;
   94      121      15    temp15       Ljava/lang/Object;
   100      115      16    temp16       Ljava/lang/Object;
   106      109      17    temp17       Ljava/lang/Object;
   112      103      18    temp18       Ljava/lang/Object;
   118      97      19    temp19       Ljava/lang/Object;
   124      91      20    temp20       Ljava/lang/Object;
   130      85      21    temp21       Ljava/lang/Object;
   136      79      22    temp22       Ljava/lang/Object;
   142      73      23    temp23       Ljava/lang/Object;
   148      67      24    temp24       Ljava/lang/Object;


public java.lang.String productPrefix();
  Signature: ()Ljava/lang/String;
  Code:
   Stack=1, Locals=1, Args_size=1
	ldc_w	String Tuple22
	areturn
  Labels:

public boolean canEqual(java.lang.Object);
  Signature: (Ljava/lang/Object;)Z
  Code:
   Stack=1, Locals=2, Args_size=2
	aload_1
	instanceof	class scala/Tuple22
	ireturn
  Labels:

private final boolean gd1$1(java.lang.Object, java.lang.Object, java.lang.Object, java.lang.Object, java.lang.Object, java.lang.Object, java.lang.Object, java.lang.Object, java.lang.Object, java.lang.Object, java.lang.Object, java.lang.Object, java.lang.Object, java.lang.Object, java.lang.Object, java.lang.Object, java.lang.Object, java.lang.Object, java.lang.Object, java.lang.Object, java.lang.Object, java.lang.Object);
  Signature: (Ljava/lang/Object;Ljava/lang/Object;Ljava/lang/Object;Ljava/lang/Object;Ljava/lang/Object;Ljava/lang/Object;Ljava/lang/Object;Ljava/lang/Object;Ljava/lang/Object;Ljava/lang/Object;Ljava/lang/Object;Ljava/lang/Object;Ljava/lang/Object;Ljava/lang/Object;Ljava/lang/Object;Ljava/lang/Object;Ljava/lang/Object;Ljava/lang/Object;Ljava/lang/Object;Ljava/lang/Object;Ljava/lang/Object;Ljava/lang/Object;)Z
  Code:
   Stack=3, Locals=38, Args_size=23
	aload_0
	invokevirtual	Method _1:()Ljava/lang/Object;
	astore	23
	aload_1
	aload	23
	if_acmpne	l1 // aload_1
	iconst_1
	goto	l2 // ifeq
l1	aload_1
	ifnonnull	l3 // aload_1
	iconst_0
	goto	l2 // ifeq
l3	aload_1
	instanceof	class java/lang/Number
	ifeq	l4 // aload_1
	aload_1
	checkcast	class java/lang/Number
	aload	23
	invokestatic	Method scala/runtime/BoxesRunTime.equalsNumObject:(Ljava/lang/Number;Ljava/lang/Object;)Z
	goto	l2 // ifeq
l4	aload_1
	instanceof	class java/lang/Character
	ifeq	l5 // aload_1
	aload_1
	checkcast	class java/lang/Character
	aload	23
	invokestatic	Method scala/runtime/BoxesRunTime.equalsCharObject:(Ljava/lang/Character;Ljava/lang/Object;)Z
	goto	l2 // ifeq
l5	aload_1
	aload	23
	invokevirtual	Method java/lang/Object.equals:(Ljava/lang/Object;)Z
l2	ifeq	l6 // iconst_0
	aload_0
	invokevirtual	Method _2:()Ljava/lang/Object;
	astore	24
	aload_2
	aload	24
	if_acmpne	l7 // aload_2
	iconst_1
	goto	l8 // ifeq
l7	aload_2
	ifnonnull	l9 // aload_2
	iconst_0
	goto	l8 // ifeq
l9	aload_2
	instanceof	class java/lang/Number
	ifeq	l10 // aload_2
	aload_2
	checkcast	class java/lang/Number
	aload	24
	invokestatic	Method scala/runtime/BoxesRunTime.equalsNumObject:(Ljava/lang/Number;Ljava/lang/Object;)Z
	goto	l8 // ifeq
l10	aload_2
	instanceof	class java/lang/Character
	ifeq	l11 // aload_2
	aload_2
	checkcast	class java/lang/Character
	aload	24
	invokestatic	Method scala/runtime/BoxesRunTime.equalsCharObject:(Ljava/lang/Character;Ljava/lang/Object;)Z
	goto	l8 // ifeq
l11	aload_2
	aload	24
	invokevirtual	Method java/lang/Object.equals:(Ljava/lang/Object;)Z
l8	ifeq	l6 // iconst_0
	aload_0
	invokevirtual	Method _3:()Ljava/lang/Object;
	astore	25
	aload_3
	aload	25
	if_acmpne	l12 // aload_3
	iconst_1
	goto	l13 // ifeq
l12	aload_3
	ifnonnull	l14 // aload_3
	iconst_0
	goto	l13 // ifeq
l14	aload_3
	instanceof	class java/lang/Number
	ifeq	l15 // aload_3
	aload_3
	checkcast	class java/lang/Number
	aload	25
	invokestatic	Method scala/runtime/BoxesRunTime.equalsNumObject:(Ljava/lang/Number;Ljava/lang/Object;)Z
	goto	l13 // ifeq
l15	aload_3
	instanceof	class java/lang/Character
	ifeq	l16 // aload_3
	aload_3
	checkcast	class java/lang/Character
	aload	25
	invokestatic	Method scala/runtime/BoxesRunTime.equalsCharObject:(Ljava/lang/Character;Ljava/lang/Object;)Z
	goto	l13 // ifeq
l16	aload_3
	aload	25
	invokevirtual	Method java/lang/Object.equals:(Ljava/lang/Object;)Z
l13	ifeq	l6 // iconst_0
	aload_0
	invokevirtual	Method _4:()Ljava/lang/Object;
	astore	26
	aload	4
	aload	26
	if_acmpne	l17 // aload
	iconst_1
	goto	l18 // ifeq
l17	aload	4
	ifnonnull	l19 // aload
	iconst_0
	goto	l18 // ifeq
l19	aload	4
	instanceof	class java/lang/Number
	ifeq	l20 // aload
	aload	4
	checkcast	class java/lang/Number
	aload	26
	invokestatic	Method scala/runtime/BoxesRunTime.equalsNumObject:(Ljava/lang/Number;Ljava/lang/Object;)Z
	goto	l18 // ifeq
l20	aload	4
	instanceof	class java/lang/Character
	ifeq	l21 // aload
	aload	4
	checkcast	class java/lang/Character
	aload	26
	invokestatic	Method scala/runtime/BoxesRunTime.equalsCharObject:(Ljava/lang/Character;Ljava/lang/Object;)Z
	goto	l18 // ifeq
l21	aload	4
	aload	26
	invokevirtual	Method java/lang/Object.equals:(Ljava/lang/Object;)Z
l18	ifeq	l6 // iconst_0
	aload_0
	invokevirtual	Method _5:()Ljava/lang/Object;
	astore	27
	aload	5
	aload	27
	if_acmpne	l22 // aload
	iconst_1
	goto	l23 // ifeq
l22	aload	5
	ifnonnull	l24 // aload
	iconst_0
	goto	l23 // ifeq
l24	aload	5
	instanceof	class java/lang/Number
	ifeq	l25 // aload
	aload	5
	checkcast	class java/lang/Number
	aload	27
	invokestatic	Method scala/runtime/BoxesRunTime.equalsNumObject:(Ljava/lang/Number;Ljava/lang/Object;)Z
	goto	l23 // ifeq
l25	aload	5
	instanceof	class java/lang/Character
	ifeq	l26 // aload
	aload	5
	checkcast	class java/lang/Character
	aload	27
	invokestatic	Method scala/runtime/BoxesRunTime.equalsCharObject:(Ljava/lang/Character;Ljava/lang/Object;)Z
	goto	l23 // ifeq
l26	aload	5
	aload	27
	invokevirtual	Method java/lang/Object.equals:(Ljava/lang/Object;)Z
l23	ifeq	l6 // iconst_0
	aload_0
	invokevirtual	Method _6:()Ljava/lang/Object;
	astore	28
	aload	6
	aload	28
	if_acmpne	l27 // aload
	iconst_1
	goto	l28 // ifeq
l27	aload	6
	ifnonnull	l29 // aload
	iconst_0
	goto	l28 // ifeq
l29	aload	6
	instanceof	class java/lang/Number
	ifeq	l30 // aload
	aload	6
	checkcast	class java/lang/Number
	aload	28
	invokestatic	Method scala/runtime/BoxesRunTime.equalsNumObject:(Ljava/lang/Number;Ljava/lang/Object;)Z
	goto	l28 // ifeq
l30	aload	6
	instanceof	class java/lang/Character
	ifeq	l31 // aload
	aload	6
	checkcast	class java/lang/Character
	aload	28
	invokestatic	Method scala/runtime/BoxesRunTime.equalsCharObject:(Ljava/lang/Character;Ljava/lang/Object;)Z
	goto	l28 // ifeq
l31	aload	6
	aload	28
	invokevirtual	Method java/lang/Object.equals:(Ljava/lang/Object;)Z
l28	ifeq	l6 // iconst_0
	aload_0
	invokevirtual	Method _7:()Ljava/lang/Object;
	astore	29
	aload	7
	aload	29
	if_acmpne	l32 // aload
	iconst_1
	goto	l33 // ifeq
l32	aload	7
	ifnonnull	l34 // aload
	iconst_0
	goto	l33 // ifeq
l34	aload	7
	instanceof	class java/lang/Number
	ifeq	l35 // aload
	aload	7
	checkcast	class java/lang/Number
	aload	29
	invokestatic	Method scala/runtime/BoxesRunTime.equalsNumObject:(Ljava/lang/Number;Ljava/lang/Object;)Z
	goto	l33 // ifeq
l35	aload	7
	instanceof	class java/lang/Character
	ifeq	l36 // aload
	aload	7
	checkcast	class java/lang/Character
	aload	29
	invokestatic	Method scala/runtime/BoxesRunTime.equalsCharObject:(Ljava/lang/Character;Ljava/lang/Object;)Z
	goto	l33 // ifeq
l36	aload	7
	aload	29
	invokevirtual	Method java/lang/Object.equals:(Ljava/lang/Object;)Z
l33	ifeq	l6 // iconst_0
	aload_0
	invokevirtual	Method _8:()Ljava/lang/Object;
	astore	30
	aload	8
	aload	30
	if_acmpne	l37 // aload
	iconst_1
	goto	l38 // ifeq
l37	aload	8
	ifnonnull	l39 // aload
	iconst_0
	goto	l38 // ifeq
l39	aload	8
	instanceof	class java/lang/Number
	ifeq	l40 // aload
	aload	8
	checkcast	class java/lang/Number
	aload	30
	invokestatic	Method scala/runtime/BoxesRunTime.equalsNumObject:(Ljava/lang/Number;Ljava/lang/Object;)Z
	goto	l38 // ifeq
l40	aload	8
	instanceof	class java/lang/Character
	ifeq	l41 // aload
	aload	8
	checkcast	class java/lang/Character
	aload	30
	invokestatic	Method scala/runtime/BoxesRunTime.equalsCharObject:(Ljava/lang/Character;Ljava/lang/Object;)Z
	goto	l38 // ifeq
l41	aload	8
	aload	30
	invokevirtual	Method java/lang/Object.equals:(Ljava/lang/Object;)Z
l38	ifeq	l6 // iconst_0
	aload_0
	invokevirtual	Method _9:()Ljava/lang/Object;
	astore	31
	aload	9
	aload	31
	if_acmpne	l42 // aload
	iconst_1
	goto	l43 // ifeq
l42	aload	9
	ifnonnull	l44 // aload
	iconst_0
	goto	l43 // ifeq
l44	aload	9
	instanceof	class java/lang/Number
	ifeq	l45 // aload
	aload	9
	checkcast	class java/lang/Number
	aload	31
	invokestatic	Method scala/runtime/BoxesRunTime.equalsNumObject:(Ljava/lang/Number;Ljava/lang/Object;)Z
	goto	l43 // ifeq
l45	aload	9
	instanceof	class java/lang/Character
	ifeq	l46 // aload
	aload	9
	checkcast	class java/lang/Character
	aload	31
	invokestatic	Method scala/runtime/BoxesRunTime.equalsCharObject:(Ljava/lang/Character;Ljava/lang/Object;)Z
	goto	l43 // ifeq
l46	aload	9
	aload	31
	invokevirtual	Method java/lang/Object.equals:(Ljava/lang/Object;)Z
l43	ifeq	l6 // iconst_0
	aload_0
	invokevirtual	Method _10:()Ljava/lang/Object;
	astore	32
	aload	10
	aload	32
	if_acmpne	l47 // aload
	iconst_1
	goto	l48 // ifeq
l47	aload	10
	ifnonnull	l49 // aload
	iconst_0
	goto	l48 // ifeq
l49	aload	10
	instanceof	class java/lang/Number
	ifeq	l50 // aload
	aload	10
	checkcast	class java/lang/Number
	aload	32
	invokestatic	Method scala/runtime/BoxesRunTime.equalsNumObject:(Ljava/lang/Number;Ljava/lang/Object;)Z
	goto	l48 // ifeq
l50	aload	10
	instanceof	class java/lang/Character
	ifeq	l51 // aload
	aload	10
	checkcast	class java/lang/Character
	aload	32
	invokestatic	Method scala/runtime/BoxesRunTime.equalsCharObject:(Ljava/lang/Character;Ljava/lang/Object;)Z
	goto	l48 // ifeq
l51	aload	10
	aload	32
	invokevirtual	Method java/lang/Object.equals:(Ljava/lang/Object;)Z
l48	ifeq	l6 // iconst_0
	aload_0
	invokevirtual	Method _11:()Ljava/lang/Object;
	astore	33
	aload	11
	aload	33
	if_acmpne	l52 // aload
	iconst_1
	goto	l53 // ifeq
l52	aload	11
	ifnonnull	l54 // aload
	iconst_0
	goto	l53 // ifeq
l54	aload	11
	instanceof	class java/lang/Number
	ifeq	l55 // aload
	aload	11
	checkcast	class java/lang/Number
	aload	33
	invokestatic	Method scala/runtime/BoxesRunTime.equalsNumObject:(Ljava/lang/Number;Ljava/lang/Object;)Z
	goto	l53 // ifeq
l55	aload	11
	instanceof	class java/lang/Character
	ifeq	l56 // aload
	aload	11
	checkcast	class java/lang/Character
	aload	33
	invokestatic	Method scala/runtime/BoxesRunTime.equalsCharObject:(Ljava/lang/Character;Ljava/lang/Object;)Z
	goto	l53 // ifeq
l56	aload	11
	aload	33
	invokevirtual	Method java/lang/Object.equals:(Ljava/lang/Object;)Z
l53	ifeq	l6 // iconst_0
	aload_0
	invokevirtual	Method _12:()Ljava/lang/Object;
	astore	34
	aload	12
	aload	34
	if_acmpne	l57 // aload
	iconst_1
	goto	l58 // ifeq
l57	aload	12
	ifnonnull	l59 // aload
	iconst_0
	goto	l58 // ifeq
l59	aload	12
	instanceof	class java/lang/Number
	ifeq	l60 // aload
	aload	12
	checkcast	class java/lang/Number
	aload	34
	invokestatic	Method scala/runtime/BoxesRunTime.equalsNumObject:(Ljava/lang/Number;Ljava/lang/Object;)Z
	goto	l58 // ifeq
l60	aload	12
	instanceof	class java/lang/Character
	ifeq	l61 // aload
	aload	12
	checkcast	class java/lang/Character
	aload	34
	invokestatic	Method scala/runtime/BoxesRunTime.equalsCharObject:(Ljava/lang/Character;Ljava/lang/Object;)Z
	goto	l58 // ifeq
l61	aload	12
	aload	34
	invokevirtual	Method java/lang/Object.equals:(Ljava/lang/Object;)Z
l58	ifeq	l6 // iconst_0
	aload_0
	invokevirtual	Method _13:()Ljava/lang/Object;
	astore	35
	aload	13
	aload	35
	if_acmpne	l62 // aload
	iconst_1
	goto	l63 // ifeq
l62	aload	13
	ifnonnull	l64 // aload
	iconst_0
	goto	l63 // ifeq
l64	aload	13
	instanceof	class java/lang/Number
	ifeq	l65 // aload
	aload	13
	checkcast	class java/lang/Number
	aload	35
	invokestatic	Method scala/runtime/BoxesRunTime.equalsNumObject:(Ljava/lang/Number;Ljava/lang/Object;)Z
	goto	l63 // ifeq
l65	aload	13
	instanceof	class java/lang/Character
	ifeq	l66 // aload
	aload	13
	checkcast	class java/lang/Character
	aload	35
	invokestatic	Method scala/runtime/BoxesRunTime.equalsCharObject:(Ljava/lang/Character;Ljava/lang/Object;)Z
	goto	l63 // ifeq
l66	aload	13
	aload	35
	invokevirtual	Method java/lang/Object.equals:(Ljava/lang/Object;)Z
l63	ifeq	l6 // iconst_0
	aload_0
	invokevirtual	Method _14:()Ljava/lang/Object;
	astore	36
	aload	14
	aload	36
	if_acmpne	l67 // aload
	iconst_1
	goto	l68 // ifeq
l67	aload	14
	ifnonnull	l69 // aload
	iconst_0
	goto	l68 // ifeq
l69	aload	14
	instanceof	class java/lang/Number
	ifeq	l70 // aload
	aload	14
	checkcast	class java/lang/Number
	aload	36
	invokestatic	Method scala/runtime/BoxesRunTime.equalsNumObject:(Ljava/lang/Number;Ljava/lang/Object;)Z
	goto	l68 // ifeq
l70	aload	14
	instanceof	class java/lang/Character
	ifeq	l71 // aload
	aload	14
	checkcast	class java/lang/Character
	aload	36
	invokestatic	Method scala/runtime/BoxesRunTime.equalsCharObject:(Ljava/lang/Character;Ljava/lang/Object;)Z
	goto	l68 // ifeq
l71	aload	14
	aload	36
	invokevirtual	Method java/lang/Object.equals:(Ljava/lang/Object;)Z
l68	ifeq	l6 // iconst_0
	aload_0
	invokevirtual	Method _15:()Ljava/lang/Object;
	astore	37
	aload	15
	aload	37
	if_acmpne	l72 // aload
	iconst_1
	goto	l73 // ifeq
l72	aload	15
	ifnonnull	l74 // aload
	iconst_0
	goto	l73 // ifeq
l74	aload	15
	instanceof	class java/lang/Number
	ifeq	l75 // aload
	aload	15
	checkcast	class java/lang/Number
	aload	37
	invokestatic	Method scala/runtime/BoxesRunTime.equalsNumObject:(Ljava/lang/Number;Ljava/lang/Object;)Z
	goto	l73 // ifeq
l75	aload	15
	instanceof	class java/lang/Character
	ifeq	l76 // aload
	aload	15
	checkcast	class java/lang/Character
	aload	37
	invokestatic	Method scala/runtime/BoxesRunTime.equalsCharObject:(Ljava/lang/Character;Ljava/lang/Object;)Z
	goto	l73 // ifeq
l76	aload	15
	aload	37
	invokevirtual	Method java/lang/Object.equals:(Ljava/lang/Object;)Z
l73	ifeq	l6 // iconst_0
	getstatic	Field scala/runtime/ScalaRunTime$.MODULE$:Lscala/runtime/ScalaRunTime$;
	aload	16
	aload_0
	invokevirtual	Method _16:()Ljava/lang/Object;
	invokevirtual	Method scala/runtime/ScalaRunTime$.inlinedEquals:(Ljava/lang/Object;Ljava/lang/Object;)Z
	ifeq	l6 // iconst_0
	getstatic	Field scala/runtime/ScalaRunTime$.MODULE$:Lscala/runtime/ScalaRunTime$;
	aload	17
	aload_0
	invokevirtual	Method _17:()Ljava/lang/Object;
	invokevirtual	Method scala/runtime/ScalaRunTime$.inlinedEquals:(Ljava/lang/Object;Ljava/lang/Object;)Z
	ifeq	l6 // iconst_0
	getstatic	Field scala/runtime/ScalaRunTime$.MODULE$:Lscala/runtime/ScalaRunTime$;
	aload	18
	aload_0
	invokevirtual	Method _18:()Ljava/lang/Object;
	invokevirtual	Method scala/runtime/ScalaRunTime$.inlinedEquals:(Ljava/lang/Object;Ljava/lang/Object;)Z
	ifeq	l6 // iconst_0
	getstatic	Field scala/runtime/ScalaRunTime$.MODULE$:Lscala/runtime/ScalaRunTime$;
	aload	19
	aload_0
	invokevirtual	Method _19:()Ljava/lang/Object;
	invokevirtual	Method scala/runtime/ScalaRunTime$.inlinedEquals:(Ljava/lang/Object;Ljava/lang/Object;)Z
	ifeq	l6 // iconst_0
	getstatic	Field scala/runtime/ScalaRunTime$.MODULE$:Lscala/runtime/ScalaRunTime$;
	aload	20
	aload_0
	invokevirtual	Method _20:()Ljava/lang/Object;
	invokevirtual	Method scala/runtime/ScalaRunTime$.inlinedEquals:(Ljava/lang/Object;Ljava/lang/Object;)Z
	ifeq	l6 // iconst_0
	getstatic	Field scala/runtime/ScalaRunTime$.MODULE$:Lscala/runtime/ScalaRunTime$;
	aload	21
	aload_0
	invokevirtual	Method _21:()Ljava/lang/Object;
	invokevirtual	Method scala/runtime/ScalaRunTime$.inlinedEquals:(Ljava/lang/Object;Ljava/lang/Object;)Z
	ifeq	l6 // iconst_0
	getstatic	Field scala/runtime/ScalaRunTime$.MODULE$:Lscala/runtime/ScalaRunTime$;
	aload	22
	aload_0
	invokevirtual	Method _22:()Ljava/lang/Object;
	invokevirtual	Method scala/runtime/ScalaRunTime$.inlinedEquals:(Ljava/lang/Object;Ljava/lang/Object;)Z
	ifeq	l6 // iconst_0
	iconst_1
	goto	l77 // ireturn
l6	iconst_0
l77	ireturn
  Labels:
   	l1 = 16 // aload_1
   	l3 = 24 // aload_1
   	l4 = 43 // aload_1
   	l5 = 62 // aload_1
   	l2 = 68 // ifeq
   	l7 = 87 // aload_2
   	l9 = 95 // aload_2
   	l10 = 114 // aload_2
   	l11 = 133 // aload_2
   	l8 = 139 // ifeq
   	l12 = 158 // aload_3
   	l14 = 166 // aload_3
   	l15 = 185 // aload_3
   	l16 = 204 // aload_3
   	l13 = 210 // ifeq
   	l17 = 230 // aload
   	l19 = 239 // aload
   	l20 = 260 // aload
   	l21 = 281 // aload
   	l18 = 288 // ifeq
   	l22 = 308 // aload
   	l24 = 317 // aload
   	l25 = 338 // aload
   	l26 = 359 // aload
   	l23 = 366 // ifeq
   	l27 = 386 // aload
   	l29 = 395 // aload
   	l30 = 416 // aload
   	l31 = 437 // aload
   	l28 = 444 // ifeq
   	l32 = 464 // aload
   	l34 = 473 // aload
   	l35 = 494 // aload
   	l36 = 515 // aload
   	l33 = 522 // ifeq
   	l37 = 542 // aload
   	l39 = 551 // aload
   	l40 = 572 // aload
   	l41 = 593 // aload
   	l38 = 600 // ifeq
   	l42 = 620 // aload
   	l44 = 629 // aload
   	l45 = 650 // aload
   	l46 = 671 // aload
   	l43 = 678 // ifeq
   	l47 = 698 // aload
   	l49 = 707 // aload
   	l50 = 728 // aload
   	l51 = 749 // aload
   	l48 = 756 // ifeq
   	l52 = 776 // aload
   	l54 = 785 // aload
   	l55 = 806 // aload
   	l56 = 827 // aload
   	l53 = 834 // ifeq
   	l57 = 854 // aload
   	l59 = 863 // aload
   	l60 = 884 // aload
   	l61 = 905 // aload
   	l58 = 912 // ifeq
   	l62 = 932 // aload
   	l64 = 941 // aload
   	l65 = 962 // aload
   	l66 = 983 // aload
   	l63 = 990 // ifeq
   	l67 = 1010 // aload
   	l69 = 1019 // aload
   	l70 = 1040 // aload
   	l71 = 1061 // aload
   	l68 = 1068 // ifeq
   	l72 = 1088 // aload
   	l74 = 1097 // aload
   	l75 = 1118 // aload
   	l76 = 1139 // aload
   	l73 = 1146 // ifeq
   	l6 = 1258 // iconst_0
   	l77 = 1259 // ireturn
  LocalVariableTable: 
   Start  Length  Slot  Name   Signature
   0      1260      0    this       Lscala/Tuple22;
   12      59      23    y0       Ljava/lang/Object;
   83      59      24    y1       Ljava/lang/Object;
   154      59      25    y2       Ljava/lang/Object;
   226      65      26    y3       Ljava/lang/Object;
   304      65      27    y4       Ljava/lang/Object;
   382      65      28    y5       Ljava/lang/Object;
   460      65      29    y6       Ljava/lang/Object;
   538      65      30    y7       Ljava/lang/Object;
   616      65      31    y8       Ljava/lang/Object;
   694      65      32    y9       Ljava/lang/Object;
   772      65      33    y10       Ljava/lang/Object;
   850      65      34    y11       Ljava/lang/Object;
   928      65      35    y12       Ljava/lang/Object;
   1006      65      36    y13       Ljava/lang/Object;
   1084      65      37    y14       Ljava/lang/Object;


public scala.Tuple22(java.lang.Object, java.lang.Object, java.lang.Object, java.lang.Object, java.lang.Object, java.lang.Object, java.lang.Object, java.lang.Object, java.lang.Object, java.lang.Object, java.lang.Object, java.lang.Object, java.lang.Object, java.lang.Object, java.lang.Object, java.lang.Object, java.lang.Object, java.lang.Object, java.lang.Object, java.lang.Object, java.lang.Object, java.lang.Object);
  Signature: (Ljava/lang/Object;Ljava/lang/Object;Ljava/lang/Object;Ljava/lang/Object;Ljava/lang/Object;Ljava/lang/Object;Ljava/lang/Object;Ljava/lang/Object;Ljava/lang/Object;Ljava/lang/Object;Ljava/lang/Object;Ljava/lang/Object;Ljava/lang/Object;Ljava/lang/Object;Ljava/lang/Object;Ljava/lang/Object;Ljava/lang/Object;Ljava/lang/Object;Ljava/lang/Object;Ljava/lang/Object;Ljava/lang/Object;Ljava/lang/Object;)V
  Code:
   Stack=2, Locals=23, Args_size=23
	aload_0
	aload_1
	putfield	Field _1:Ljava/lang/Object;
	aload_0
	aload_2
	putfield	Field _2:Ljava/lang/Object;
	aload_0
	aload_3
	putfield	Field _3:Ljava/lang/Object;
	aload_0
	aload	4
	putfield	Field _4:Ljava/lang/Object;
	aload_0
	aload	5
	putfield	Field _5:Ljava/lang/Object;
	aload_0
	aload	6
	putfield	Field _6:Ljava/lang/Object;
	aload_0
	aload	7
	putfield	Field _7:Ljava/lang/Object;
	aload_0
	aload	8
	putfield	Field _8:Ljava/lang/Object;
	aload_0
	aload	9
	putfield	Field _9:Ljava/lang/Object;
	aload_0
	aload	10
	putfield	Field _10:Ljava/lang/Object;
	aload_0
	aload	11
	putfield	Field _11:Ljava/lang/Object;
	aload_0
	aload	12
	putfield	Field _12:Ljava/lang/Object;
	aload_0
	aload	13
	putfield	Field _13:Ljava/lang/Object;
	aload_0
	aload	14
	putfield	Field _14:Ljava/lang/Object;
	aload_0
	aload	15
	putfield	Field _15:Ljava/lang/Object;
	aload_0
	aload	16
	putfield	Field _16:Ljava/lang/Object;
	aload_0
	aload	17
	putfield	Field _17:Ljava/lang/Object;
	aload_0
	aload	18
	putfield	Field _18:Ljava/lang/Object;
	aload_0
	aload	19
	putfield	Field _19:Ljava/lang/Object;
	aload_0
	aload	20
	putfield	Field _20:Ljava/lang/Object;
	aload_0
	aload	21
	putfield	Field _21:Ljava/lang/Object;
	aload_0
	aload	22
	putfield	Field _22:Ljava/lang/Object;
	aload_0
	invokespecial	Method java/lang/Object."<init>":()V
	aload_0
	invokestatic	Method scala/Product$class.$init$:(Lscala/Product;)V
	aload_0
	invokestatic	Method scala/Product22$class.$init$:(Lscala/Product22;)V
	return
  Labels:
  LocalVariableTable: 
   Start  Length  Slot  Name   Signature
   0      142      0    this       Lscala/Tuple22;
   0      142      1    _1       Ljava/lang/Object;
   0      142      2    _2       Ljava/lang/Object;
   0      142      3    _3       Ljava/lang/Object;
   0      142      4    _4       Ljava/lang/Object;
   0      142      5    _5       Ljava/lang/Object;
   0      142      6    _6       Ljava/lang/Object;
   0      142      7    _7       Ljava/lang/Object;
   0      142      8    _8       Ljava/lang/Object;
   0      142      9    _9       Ljava/lang/Object;
   0      142      10    _10       Ljava/lang/Object;
   0      142      11    _11       Ljava/lang/Object;
   0      142      12    _12       Ljava/lang/Object;
   0      142      13    _13       Ljava/lang/Object;
   0      142      14    _14       Ljava/lang/Object;
   0      142      15    _15       Ljava/lang/Object;
   0      142      16    _16       Ljava/lang/Object;
   0      142      17    _17       Ljava/lang/Object;
   0      142      18    _18       Ljava/lang/Object;
   0      142      19    _19       Ljava/lang/Object;
   0      142      20    _20       Ljava/lang/Object;
   0      142      21    _21       Ljava/lang/Object;
   0      142      22    _22       Ljava/lang/Object;

  Signature: length = 0x2
   01 54 

}

