Compiled from "Tuple2.scala"
public final class scala.Tuple2$mcLD$sp$$anonfun$zip$mcLD$sp$1 extends scala.runtime.AbstractFunction1 implements java.io.Serializable
  SourceFile: "Tuple2.scala"
  Scala: length = 0x
   
  InnerClass: 
   public final $anonfun$zip$mcLD$sp$1=class scala/Tuple2$mcLD$sp$$anonfun$zip$mcLD$sp$1 of class scala/Tuple2$mcLD$sp
  minor version: 0
  major version: 49
  Constant pool:
Asciz	SourceFile;
Asciz	Tuple2.scala;
Asciz	<clinit>;
Asciz	()V;
Asciz	Code;
Asciz	serialVersionUID;
Asciz	J;
Asciz	scala/Tuple2$mcLD$sp$$anonfun$zip$mcLD$sp$1;
class	scala/Tuple2$mcLD$sp$$anonfun$zip$mcLD$sp$1
NameAndType	serialVersionUID:J
Field	scala/Tuple2$mcLD$sp$$anonfun$zip$mcLD$sp$1.serialVersionUID:J
Asciz	b1$8;
Asciz	Lscala/collection/mutable/Builder;;
Asciz	elems2$13;
Asciz	Lscala/collection/Iterator;;
Asciz	apply;
Asciz	(Ljava/lang/Object;)Ljava/lang/Object;;
Asciz	LineNumberTable;
NameAndType	elems2$13:Lscala/collection/Iterator;
Field	scala/Tuple2$mcLD$sp$$anonfun$zip$mcLD$sp$1.elems2$13:Lscala/collection/Iterator;
Asciz	scala/collection/Iterator;
class	scala/collection/Iterator
Asciz	hasNext;
Asciz	()Z;
NameAndType	hasNext:()Z
InterfaceMethod	scala/collection/Iterator.hasNext:()Z
NameAndType	b1$8:Lscala/collection/mutable/Builder;
Field	scala/Tuple2$mcLD$sp$$anonfun$zip$mcLD$sp$1.b1$8:Lscala/collection/mutable/Builder;
Asciz	scala/Tuple2;
class	scala/Tuple2
Asciz	next;
Asciz	()Ljava/lang/Object;;
NameAndType	next:()Ljava/lang/Object;
InterfaceMethod	scala/collection/Iterator.next:()Ljava/lang/Object;
Asciz	<init>;
Asciz	(Ljava/lang/Object;Ljava/lang/Object;)V;
NameAndType	"<init>":(Ljava/lang/Object;Ljava/lang/Object;)V
Method	scala/Tuple2."<init>":(Ljava/lang/Object;Ljava/lang/Object;)V
Asciz	scala/collection/mutable/Builder;
class	scala/collection/mutable/Builder
Asciz	$plus$eq;
Asciz	(Ljava/lang/Object;)Lscala/collection/mutable/Builder;;
NameAndType	$plus$eq:(Ljava/lang/Object;)Lscala/collection/mutable/Builder;
InterfaceMethod	scala/collection/mutable/Builder.$plus$eq:(Ljava/lang/Object;)Lscala/collection/mutable/Builder;
Asciz	scala/runtime/BoxedUnit;
class	scala/runtime/BoxedUnit
Asciz	UNIT;
Asciz	Lscala/runtime/BoxedUnit;;
NameAndType	UNIT:Lscala/runtime/BoxedUnit;
Field	scala/runtime/BoxedUnit.UNIT:Lscala/runtime/BoxedUnit;
Asciz	this;
Asciz	Lscala/Tuple2$mcLD$sp$$anonfun$zip$mcLD$sp$1;;
Asciz	el1;
Asciz	Ljava/lang/Object;;
Asciz	LocalVariableTable;
Asciz	(TEl1;)Ljava/lang/Object;;
Asciz	Signature;
Asciz	(Lscala/Tuple2$mcLD$sp;Lscala/collection/mutable/Builder;Lscala/collection/Iterator;)V;
Asciz	scala/runtime/AbstractFunction1;
class	scala/runtime/AbstractFunction1
NameAndType	"<init>":()V
Method	scala/runtime/AbstractFunction1."<init>":()V
Asciz	$outer;
Asciz	Lscala/Tuple2$mcLD$sp;;
Asciz	Scala;
Asciz	InnerClasses;
Asciz	scala/Tuple2$mcLD$sp;
class	scala/Tuple2$mcLD$sp
Asciz	$anonfun$zip$mcLD$sp$1;
Asciz	java/io/Serializable;
class	java/io/Serializable

{
public static final long serialVersionUID;
  Signature: J

private final scala.collection.mutable.Builder b1$8;
  Signature: Lscala/collection/mutable/Builder;

private final scala.collection.Iterator elems2$13;
  Signature: Lscala/collection/Iterator;

public static {};
  Signature: ()V
  Code:
   Stack=2, Locals=0, Args_size=0
	lconst_0
	putstatic	Field serialVersionUID:J
	return
  Labels:

public final java.lang.Object apply(java.lang.Object);
  Signature: (Ljava/lang/Object;)Ljava/lang/Object;
  Code:
   Stack=5, Locals=2, Args_size=2
	aload_0
	getfield	Field elems2$13:Lscala/collection/Iterator;
	invokeinterface	InterfaceMethod scala/collection/Iterator.hasNext:()Z
	ifeq	l1 // getstatic
	aload_0
	getfield	Field b1$8:Lscala/collection/mutable/Builder;
	new	class scala/Tuple2
	dup
	aload_1
	aload_0
	getfield	Field elems2$13:Lscala/collection/Iterator;
	invokeinterface	InterfaceMethod scala/collection/Iterator.next:()Ljava/lang/Object;
	invokespecial	Method scala/Tuple2."<init>":(Ljava/lang/Object;Ljava/lang/Object;)V
	invokeinterface	InterfaceMethod scala/collection/mutable/Builder.$plus$eq:(Ljava/lang/Object;)Lscala/collection/mutable/Builder;
	goto	l2 // areturn
l1	getstatic	Field scala/runtime/BoxedUnit.UNIT:Lscala/runtime/BoxedUnit;
l2	areturn
  Labels:
   	l1 = 41 // getstatic
   	l2 = 44 // areturn
  LocalVariableTable: 
   Start  Length  Slot  Name   Signature
   0      45      0    this       Lscala/Tuple2$mcLD$sp$$anonfun$zip$mcLD$sp$1;
   0      45      1    el1       Ljava/lang/Object;

  Signature: length = 0x2
   00 38 

public scala.Tuple2$mcLD$sp$$anonfun$zip$mcLD$sp$1(scala.Tuple2$mcLD$sp, scala.collection.mutable.Builder, scala.collection.Iterator);
  Signature: (Lscala/Tuple2$mcLD$sp;Lscala/collection/mutable/Builder;Lscala/collection/Iterator;)V
  Code:
   Stack=2, Locals=4, Args_size=4
	aload_0
	aload_2
	putfield	Field b1$8:Lscala/collection/mutable/Builder;
	aload_0
	aload_3
	putfield	Field elems2$13:Lscala/collection/Iterator;
	aload_0
	invokespecial	Method scala/runtime/AbstractFunction1."<init>":()V
	return
  Labels:
  LocalVariableTable: 
   Start  Length  Slot  Name   Signature
   0      15      0    this       Lscala/Tuple2$mcLD$sp$$anonfun$zip$mcLD$sp$1;
   0      15      1    $outer       Lscala/Tuple2$mcLD$sp;


}

