Compiled from "Tuple3.scala"
public final class scala.Tuple3$Zipped$$anonfun$filter$1 extends java.lang.Object implements scala.Function1,scala.ScalaObject,java.io.Serializable
  SourceFile: "Tuple3.scala"
  Scala: length = 0x
   
  InnerClass: 
   public #114= #111 of #113; //Zipped=class scala/Tuple3$Zipped of class scala/Tuple3
   public final #115= #9 of #111; //$anonfun$filter$1=class scala/Tuple3$Zipped$$anonfun$filter$1 of class scala/Tuple3$Zipped
  minor version: 0
  major version: 49
  Constant pool:
const #1 = Asciz	SourceFile;
const #2 = Asciz	Tuple3.scala;
const #3 = Asciz	<clinit>;
const #4 = Asciz	()V;
const #5 = Asciz	Code;
const #6 = Asciz	serialVersionUID;
const #7 = Asciz	J;
const #8 = Asciz	scala/Tuple3$Zipped$$anonfun$filter$1;
const #9 = class	#8;	//  scala/Tuple3$Zipped$$anonfun$filter$1
const #10 = NameAndType	#6:#7;//  serialVersionUID:J
const #11 = Field	#9.#10;	//  scala/Tuple3$Zipped$$anonfun$filter$1.serialVersionUID:J
const #12 = Asciz	elems3$4;
const #13 = Asciz	Lscala/collection/Iterator;;
const #14 = Asciz	elems2$4;
const #15 = Asciz	b3$1;
const #16 = Asciz	Lscala/collection/mutable/Builder;;
const #17 = Asciz	b2$1;
const #18 = Asciz	b1$2;
const #19 = Asciz	f$3;
const #20 = Asciz	Lscala/Function3;;
const #21 = Asciz	<init>;
const #22 = Asciz	(Lscala/Tuple3$Zipped;Lscala/Function3;Lscala/collection/mutable/Builder;Lscala/collection/mutable/Builder;Lscala/collection/mutable/Builder;Lscala/collection/Iterator;Lscala/collection/Iterator;)V;
const #23 = Asciz	LineNumberTable;
const #24 = NameAndType	#19:#20;//  f$3:Lscala/Function3;
const #25 = Field	#9.#24;	//  scala/Tuple3$Zipped$$anonfun$filter$1.f$3:Lscala/Function3;
const #26 = NameAndType	#18:#16;//  b1$2:Lscala/collection/mutable/Builder;
const #27 = Field	#9.#26;	//  scala/Tuple3$Zipped$$anonfun$filter$1.b1$2:Lscala/collection/mutable/Builder;
const #28 = NameAndType	#17:#16;//  b2$1:Lscala/collection/mutable/Builder;
const #29 = Field	#9.#28;	//  scala/Tuple3$Zipped$$anonfun$filter$1.b2$1:Lscala/collection/mutable/Builder;
const #30 = NameAndType	#15:#16;//  b3$1:Lscala/collection/mutable/Builder;
const #31 = Field	#9.#30;	//  scala/Tuple3$Zipped$$anonfun$filter$1.b3$1:Lscala/collection/mutable/Builder;
const #32 = NameAndType	#14:#13;//  elems2$4:Lscala/collection/Iterator;
const #33 = Field	#9.#32;	//  scala/Tuple3$Zipped$$anonfun$filter$1.elems2$4:Lscala/collection/Iterator;
const #34 = NameAndType	#12:#13;//  elems3$4:Lscala/collection/Iterator;
const #35 = Field	#9.#34;	//  scala/Tuple3$Zipped$$anonfun$filter$1.elems3$4:Lscala/collection/Iterator;
const #36 = Asciz	java/lang/Object;
const #37 = class	#36;	//  java/lang/Object
const #38 = NameAndType	#21:#4;//  "<init>":()V
const #39 = Method	#37.#38;	//  java/lang/Object."<init>":()V
const #40 = Asciz	scala/Function1$class;
const #41 = class	#40;	//  scala/Function1$class
const #42 = Asciz	$init$;
const #43 = Asciz	(Lscala/Function1;)V;
const #44 = NameAndType	#42:#43;//  $init$:(Lscala/Function1;)V
const #45 = Method	#41.#44;	//  scala/Function1$class.$init$:(Lscala/Function1;)V
const #46 = Asciz	this;
const #47 = Asciz	Lscala/Tuple3$Zipped$$anonfun$filter$1;;
const #48 = Asciz	$outer;
const #49 = Asciz	Lscala/Tuple3$Zipped;;
const #50 = Asciz	LocalVariableTable;
const #51 = Asciz	(Lscala/Tuple3<TT1;TT2;TT3;>.Zipped<TRepr1;TEl1;TRepr2;TEl2;TRepr3;TEl3;>;)V;
const #52 = Asciz	Signature;
const #53 = Asciz	apply;
const #54 = Asciz	(Ljava/lang/Object;)Ljava/lang/Object;;
const #55 = Asciz	scala/collection/Iterator;
const #56 = class	#55;	//  scala/collection/Iterator
const #57 = Asciz	hasNext;
const #58 = Asciz	()Z;
const #59 = NameAndType	#57:#58;//  hasNext:()Z
const #60 = InterfaceMethod	#56.#59;	//  scala/collection/Iterator.hasNext:()Z
const #61 = Asciz	next;
const #62 = Asciz	()Ljava/lang/Object;;
const #63 = NameAndType	#61:#62;//  next:()Ljava/lang/Object;
const #64 = InterfaceMethod	#56.#63;	//  scala/collection/Iterator.next:()Ljava/lang/Object;
const #65 = Asciz	scala/Function3;
const #66 = class	#65;	//  scala/Function3
const #67 = Asciz	(Ljava/lang/Object;Ljava/lang/Object;Ljava/lang/Object;)Ljava/lang/Object;;
const #68 = NameAndType	#53:#67;//  apply:(Ljava/lang/Object;Ljava/lang/Object;Ljava/lang/Object;)Ljava/lang/Object;
const #69 = InterfaceMethod	#66.#68;	//  scala/Function3.apply:(Ljava/lang/Object;Ljava/lang/Object;Ljava/lang/Object;)Ljava/lang/Object;
const #70 = Asciz	scala/runtime/BoxesRunTime;
const #71 = class	#70;	//  scala/runtime/BoxesRunTime
const #72 = Asciz	unboxToBoolean;
const #73 = Asciz	(Ljava/lang/Object;)Z;
const #74 = NameAndType	#72:#73;//  unboxToBoolean:(Ljava/lang/Object;)Z
const #75 = Method	#71.#74;	//  scala/runtime/BoxesRunTime.unboxToBoolean:(Ljava/lang/Object;)Z
const #76 = Asciz	scala/collection/mutable/Builder;
const #77 = class	#76;	//  scala/collection/mutable/Builder
const #78 = Asciz	$plus$eq;
const #79 = Asciz	(Ljava/lang/Object;)Lscala/collection/mutable/Builder;;
const #80 = NameAndType	#78:#79;//  $plus$eq:(Ljava/lang/Object;)Lscala/collection/mutable/Builder;
const #81 = InterfaceMethod	#77.#80;	//  scala/collection/mutable/Builder.$plus$eq:(Ljava/lang/Object;)Lscala/collection/mutable/Builder;
const #82 = Asciz	scala/runtime/BoxedUnit;
const #83 = class	#82;	//  scala/runtime/BoxedUnit
const #84 = Asciz	UNIT;
const #85 = Asciz	Lscala/runtime/BoxedUnit;;
const #86 = NameAndType	#84:#85;//  UNIT:Lscala/runtime/BoxedUnit;
const #87 = Field	#83.#86;	//  scala/runtime/BoxedUnit.UNIT:Lscala/runtime/BoxedUnit;
const #88 = Asciz	el1;
const #89 = Asciz	Ljava/lang/Object;;
const #90 = Asciz	el2;
const #91 = Asciz	el3;
const #92 = Asciz	(TEl1;)Ljava/lang/Object;;
const #93 = Asciz	andThen;
const #94 = Asciz	(Lscala/Function1;)Lscala/Function1;;
const #95 = Asciz	(Lscala/Function1;Lscala/Function1;)Lscala/Function1;;
const #96 = NameAndType	#93:#95;//  andThen:(Lscala/Function1;Lscala/Function1;)Lscala/Function1;
const #97 = Method	#41.#96;	//  scala/Function1$class.andThen:(Lscala/Function1;Lscala/Function1;)Lscala/Function1;
const #98 = Asciz	g;
const #99 = Asciz	Lscala/Function1;;
const #100 = Asciz	compose;
const #101 = NameAndType	#100:#95;//  compose:(Lscala/Function1;Lscala/Function1;)Lscala/Function1;
const #102 = Method	#41.#101;	//  scala/Function1$class.compose:(Lscala/Function1;Lscala/Function1;)Lscala/Function1;
const #103 = Asciz	toString;
const #104 = Asciz	()Ljava/lang/String;;
const #105 = Asciz	(Lscala/Function1;)Ljava/lang/String;;
const #106 = NameAndType	#103:#105;//  toString:(Lscala/Function1;)Ljava/lang/String;
const #107 = Method	#41.#106;	//  scala/Function1$class.toString:(Lscala/Function1;)Ljava/lang/String;
const #108 = Asciz	Scala;
const #109 = Asciz	InnerClasses;
const #110 = Asciz	scala/Tuple3$Zipped;
const #111 = class	#110;	//  scala/Tuple3$Zipped
const #112 = Asciz	scala/Tuple3;
const #113 = class	#112;	//  scala/Tuple3
const #114 = Asciz	Zipped;
const #115 = Asciz	$anonfun$filter$1;
const #116 = Asciz	scala/Function1;
const #117 = class	#116;	//  scala/Function1
const #118 = Asciz	scala/ScalaObject;
const #119 = class	#118;	//  scala/ScalaObject
const #120 = Asciz	java/io/Serializable;
const #121 = class	#120;	//  java/io/Serializable

{
public static final long serialVersionUID;

public static {};
  Code:
   Stack=2, Locals=0, Args_size=0
   0:	lconst_0
   1:	putstatic	#11; //Field serialVersionUID:J
   4:	return

public scala.Tuple3$Zipped$$anonfun$filter$1(scala.Tuple3$Zipped, scala.Function3, scala.collection.mutable.Builder, scala.collection.mutable.Builder, scala.collection.mutable.Builder, scala.collection.Iterator, scala.collection.Iterator);
  Code:
   Stack=2, Locals=8, Args_size=8
   0:	aload_0
   1:	aload_2
   2:	putfield	#25; //Field f$3:Lscala/Function3;
   5:	aload_0
   6:	aload_3
   7:	putfield	#27; //Field b1$2:Lscala/collection/mutable/Builder;
   10:	aload_0
   11:	aload	4
   13:	putfield	#29; //Field b2$1:Lscala/collection/mutable/Builder;
   16:	aload_0
   17:	aload	5
   19:	putfield	#31; //Field b3$1:Lscala/collection/mutable/Builder;
   22:	aload_0
   23:	aload	6
   25:	putfield	#33; //Field elems2$4:Lscala/collection/Iterator;
   28:	aload_0
   29:	aload	7
   31:	putfield	#35; //Field elems3$4:Lscala/collection/Iterator;
   34:	aload_0
   35:	invokespecial	#39; //Method java/lang/Object."<init>":()V
   38:	aload_0
   39:	invokestatic	#45; //Method scala/Function1$class.$init$:(Lscala/Function1;)V
   42:	return
  LineNumberTable: 
   line 87: 0

  LocalVariableTable: 
   Start  Length  Slot  Name   Signature
   0      43      0    this       Lscala/Tuple3$Zipped$$anonfun$filter$1;
   0      43      1    $outer       Lscala/Tuple3$Zipped;

  Signature: length = 0x2
   00 33 

public final java.lang.Object apply(java.lang.Object);
  Code:
   Stack=4, Locals=4, Args_size=2
   0:	aload_0
   1:	getfield	#33; //Field elems2$4:Lscala/collection/Iterator;
   4:	invokeinterface	#60,  1; //InterfaceMethod scala/collection/Iterator.hasNext:()Z
   9:	ifeq	103
   12:	aload_0
   13:	getfield	#35; //Field elems3$4:Lscala/collection/Iterator;
   16:	invokeinterface	#60,  1; //InterfaceMethod scala/collection/Iterator.hasNext:()Z
   21:	ifeq	103
   24:	aload_0
   25:	getfield	#33; //Field elems2$4:Lscala/collection/Iterator;
   28:	invokeinterface	#64,  1; //InterfaceMethod scala/collection/Iterator.next:()Ljava/lang/Object;
   33:	astore_2
   34:	aload_0
   35:	getfield	#35; //Field elems3$4:Lscala/collection/Iterator;
   38:	invokeinterface	#64,  1; //InterfaceMethod scala/collection/Iterator.next:()Ljava/lang/Object;
   43:	astore_3
   44:	aload_0
   45:	getfield	#25; //Field f$3:Lscala/Function3;
   48:	aload_1
   49:	aload_2
   50:	aload_3
   51:	invokeinterface	#69,  4; //InterfaceMethod scala/Function3.apply:(Ljava/lang/Object;Ljava/lang/Object;Ljava/lang/Object;)Ljava/lang/Object;
   56:	invokestatic	#75; //Method scala/runtime/BoxesRunTime.unboxToBoolean:(Ljava/lang/Object;)Z
   59:	ifeq	97
   62:	aload_0
   63:	getfield	#27; //Field b1$2:Lscala/collection/mutable/Builder;
   66:	aload_1
   67:	invokeinterface	#81,  2; //InterfaceMethod scala/collection/mutable/Builder.$plus$eq:(Ljava/lang/Object;)Lscala/collection/mutable/Builder;
   72:	pop
   73:	aload_0
   74:	getfield	#29; //Field b2$1:Lscala/collection/mutable/Builder;
   77:	aload_2
   78:	invokeinterface	#81,  2; //InterfaceMethod scala/collection/mutable/Builder.$plus$eq:(Ljava/lang/Object;)Lscala/collection/mutable/Builder;
   83:	pop
   84:	aload_0
   85:	getfield	#31; //Field b3$1:Lscala/collection/mutable/Builder;
   88:	aload_3
   89:	invokeinterface	#81,  2; //InterfaceMethod scala/collection/mutable/Builder.$plus$eq:(Ljava/lang/Object;)Lscala/collection/mutable/Builder;
   94:	goto	106
   97:	getstatic	#87; //Field scala/runtime/BoxedUnit.UNIT:Lscala/runtime/BoxedUnit;
   100:	goto	106
   103:	getstatic	#87; //Field scala/runtime/BoxedUnit.UNIT:Lscala/runtime/BoxedUnit;
   106:	areturn
  LineNumberTable: 
   line 88: 0
   line 89: 24
   line 90: 34
   line 91: 44
   line 92: 62
   line 93: 73
   line 94: 84
   line 91: 97
   line 88: 103

  LocalVariableTable: 
   Start  Length  Slot  Name   Signature
   0      107      0    this       Lscala/Tuple3$Zipped$$anonfun$filter$1;
   0      107      1    el1       Ljava/lang/Object;
   34      69      2    el2       Ljava/lang/Object;
   44      59      3    el3       Ljava/lang/Object;

  Signature: length = 0x2
   00 5C 

public scala.Function1 andThen(scala.Function1);
  Code:
   Stack=2, Locals=2, Args_size=2
   0:	aload_0
   1:	aload_1
   2:	invokestatic	#97; //Method scala/Function1$class.andThen:(Lscala/Function1;Lscala/Function1;)Lscala/Function1;
   5:	areturn
  LineNumberTable: 
   line 87: 0

  LocalVariableTable: 
   Start  Length  Slot  Name   Signature
   0      6      0    this       Lscala/Tuple3$Zipped$$anonfun$filter$1;
   0      6      1    g       Lscala/Function1;


public scala.Function1 compose(scala.Function1);
  Code:
   Stack=2, Locals=2, Args_size=2
   0:	aload_0
   1:	aload_1
   2:	invokestatic	#102; //Method scala/Function1$class.compose:(Lscala/Function1;Lscala/Function1;)Lscala/Function1;
   5:	areturn
  LineNumberTable: 
   line 87: 0

  LocalVariableTable: 
   Start  Length  Slot  Name   Signature
   0      6      0    this       Lscala/Tuple3$Zipped$$anonfun$filter$1;
   0      6      1    g       Lscala/Function1;


public java.lang.String toString();
  Code:
   Stack=1, Locals=1, Args_size=1
   0:	aload_0
   1:	invokestatic	#107; //Method scala/Function1$class.toString:(Lscala/Function1;)Ljava/lang/String;
   4:	areturn
  LineNumberTable: 
   line 87: 0


}

