Compiled from "Tuple3.scala"
public class scala.Tuple3$Zipped extends java.lang.Object implements scala.ScalaObject
  SourceFile: "Tuple3.scala"
  Signature: length = 0x2
   00 FFFFFF9D 
  Scala: length = 0x
   
  InnerClass: 
   public #160= #19 of #114; //Zipped=class scala/Tuple3$Zipped of class scala/Tuple3
   public final #161= #150 of #19; //$anonfun$map$1=class scala/Tuple3$Zipped$$anonfun$map$1 of class scala/Tuple3$Zipped
   public final #162= #109 of #19; //$anonfun$filter$1=class scala/Tuple3$Zipped$$anonfun$filter$1 of class scala/Tuple3$Zipped
   public final #163= #90 of #19; //$anonfun$exists$1=class scala/Tuple3$Zipped$$anonfun$exists$1 of class scala/Tuple3$Zipped
   public final #164= #74 of #19; //$anonfun$forall$1=class scala/Tuple3$Zipped$$anonfun$forall$1 of class scala/Tuple3$Zipped
   public final #165= #138 of #19; //$anonfun$flatMap$1=class scala/Tuple3$Zipped$$anonfun$flatMap$1 of class scala/Tuple3$Zipped
   public final #166= #51 of #19; //$anonfun$foreach$1=class scala/Tuple3$Zipped$$anonfun$foreach$1 of class scala/Tuple3$Zipped
  minor version: 0
  major version: 49
  Constant pool:
const #1 = Asciz	SourceFile;
const #2 = Asciz	Tuple3.scala;
const #3 = Asciz	$outer;
const #4 = Asciz	Lscala/Tuple3;;
const #5 = Asciz	coll3;
const #6 = Asciz	Lscala/collection/IterableLike;;
const #7 = Asciz	Lscala/collection/IterableLike<TEl3;TRepr3;>;;
const #8 = Asciz	Signature;
const #9 = Asciz	coll2;
const #10 = Asciz	Lscala/collection/IterableLike<TEl2;TRepr2;>;;
const #11 = Asciz	coll1;
const #12 = Asciz	Lscala/collection/TraversableLike;;
const #13 = Asciz	Lscala/collection/TraversableLike<TEl1;TRepr1;>;;
const #14 = Asciz	<init>;
const #15 = Asciz	(Lscala/Tuple3;Lscala/collection/TraversableLike;Lscala/collection/IterableLike;Lscala/collection/IterableLike;)V;
const #16 = Asciz	Code;
const #17 = Asciz	LineNumberTable;
const #18 = Asciz	scala/Tuple3$Zipped;
const #19 = class	#18;	//  scala/Tuple3$Zipped
const #20 = NameAndType	#11:#12;//  coll1:Lscala/collection/TraversableLike;
const #21 = Field	#19.#20;	//  scala/Tuple3$Zipped.coll1:Lscala/collection/TraversableLike;
const #22 = NameAndType	#9:#6;//  coll2:Lscala/collection/IterableLike;
const #23 = Field	#19.#22;	//  scala/Tuple3$Zipped.coll2:Lscala/collection/IterableLike;
const #24 = NameAndType	#5:#6;//  coll3:Lscala/collection/IterableLike;
const #25 = Field	#19.#24;	//  scala/Tuple3$Zipped.coll3:Lscala/collection/IterableLike;
const #26 = Asciz	java/lang/NullPointerException;
const #27 = class	#26;	//  java/lang/NullPointerException
const #28 = Asciz	()V;
const #29 = NameAndType	#14:#28;//  "<init>":()V
const #30 = Method	#27.#29;	//  java/lang/NullPointerException."<init>":()V
const #31 = NameAndType	#3:#4;//  $outer:Lscala/Tuple3;
const #32 = Field	#19.#31;	//  scala/Tuple3$Zipped.$outer:Lscala/Tuple3;
const #33 = Asciz	java/lang/Object;
const #34 = class	#33;	//  java/lang/Object
const #35 = Method	#34.#29;	//  java/lang/Object."<init>":()V
const #36 = Asciz	this;
const #37 = Asciz	Lscala/Tuple3$Zipped;;
const #38 = Asciz	LocalVariableTable;
const #39 = Asciz	(Lscala/Tuple3<TT1;TT2;TT3;>;Lscala/collection/TraversableLike<TEl1;TRepr1;>;Lscala/collection/IterableLike<TEl2;TRepr2;>;Lscala/collection/IterableLike<TEl3;TRepr3;>;)V;
const #40 = Asciz	scala$Tuple3$Zipped$$$outer;
const #41 = Asciz	()Lscala/Tuple3;;
const #42 = Asciz	foreach;
const #43 = Asciz	(Lscala/Function3;)V;
const #44 = Asciz	scala/collection/IterableLike;
const #45 = class	#44;	//  scala/collection/IterableLike
const #46 = Asciz	iterator;
const #47 = Asciz	()Lscala/collection/Iterator;;
const #48 = NameAndType	#46:#47;//  iterator:()Lscala/collection/Iterator;
const #49 = InterfaceMethod	#45.#48;	//  scala/collection/IterableLike.iterator:()Lscala/collection/Iterator;
const #50 = Asciz	scala/Tuple3$Zipped$$anonfun$foreach$1;
const #51 = class	#50;	//  scala/Tuple3$Zipped$$anonfun$foreach$1
const #52 = Asciz	(Lscala/Tuple3$Zipped;Lscala/Function3;Lscala/collection/Iterator;Lscala/collection/Iterator;)V;
const #53 = NameAndType	#14:#52;//  "<init>":(Lscala/Tuple3$Zipped;Lscala/Function3;Lscala/collection/Iterator;Lscala/collection/Iterator;)V
const #54 = Method	#51.#53;	//  scala/Tuple3$Zipped$$anonfun$foreach$1."<init>":(Lscala/Tuple3$Zipped;Lscala/Function3;Lscala/collection/Iterator;Lscala/collection/Iterator;)V
const #55 = Asciz	scala/collection/TraversableLike;
const #56 = class	#55;	//  scala/collection/TraversableLike
const #57 = Asciz	(Lscala/Function1;)V;
const #58 = NameAndType	#42:#57;//  foreach:(Lscala/Function1;)V
const #59 = InterfaceMethod	#56.#58;	//  scala/collection/TraversableLike.foreach:(Lscala/Function1;)V
const #60 = Asciz	f$6;
const #61 = Asciz	Lscala/Function3;;
const #62 = Asciz	elems2$7;
const #63 = Asciz	Lscala/collection/Iterator;;
const #64 = Asciz	elems3$7;
const #65 = Asciz	<U:Ljava/lang/Object;>(Lscala/Function3<TEl1;TEl2;TEl3;TU;>;)V;
const #66 = Asciz	forall;
const #67 = Asciz	(Lscala/Function3;)Z;
const #68 = Asciz	scala/runtime/BooleanRef;
const #69 = class	#68;	//  scala/runtime/BooleanRef
const #70 = Asciz	(Z)V;
const #71 = NameAndType	#14:#70;//  "<init>":(Z)V
const #72 = Method	#69.#71;	//  scala/runtime/BooleanRef."<init>":(Z)V
const #73 = Asciz	scala/Tuple3$Zipped$$anonfun$forall$1;
const #74 = class	#73;	//  scala/Tuple3$Zipped$$anonfun$forall$1
const #75 = Asciz	(Lscala/Tuple3$Zipped;Lscala/Function3;Lscala/runtime/BooleanRef;Lscala/collection/Iterator;Lscala/collection/Iterator;)V;
const #76 = NameAndType	#14:#75;//  "<init>":(Lscala/Tuple3$Zipped;Lscala/Function3;Lscala/runtime/BooleanRef;Lscala/collection/Iterator;Lscala/collection/Iterator;)V
const #77 = Method	#74.#76;	//  scala/Tuple3$Zipped$$anonfun$forall$1."<init>":(Lscala/Tuple3$Zipped;Lscala/Function3;Lscala/runtime/BooleanRef;Lscala/collection/Iterator;Lscala/collection/Iterator;)V
const #78 = Asciz	elem;
const #79 = Asciz	Z;
const #80 = NameAndType	#78:#79;//  elem:Z
const #81 = Field	#69.#80;	//  scala/runtime/BooleanRef.elem:Z
const #82 = Asciz	f$5;
const #83 = Asciz	acc$2;
const #84 = Asciz	Lscala/runtime/BooleanRef;;
const #85 = Asciz	elems2$6;
const #86 = Asciz	elems3$6;
const #87 = Asciz	(Lscala/Function3<TEl1;TEl2;TEl3;Ljava/lang/Boolean;>;)Z;
const #88 = Asciz	exists;
const #89 = Asciz	scala/Tuple3$Zipped$$anonfun$exists$1;
const #90 = class	#89;	//  scala/Tuple3$Zipped$$anonfun$exists$1
const #91 = Method	#90.#76;	//  scala/Tuple3$Zipped$$anonfun$exists$1."<init>":(Lscala/Tuple3$Zipped;Lscala/Function3;Lscala/runtime/BooleanRef;Lscala/collection/Iterator;Lscala/collection/Iterator;)V
const #92 = Asciz	f$4;
const #93 = Asciz	acc$1;
const #94 = Asciz	elems2$5;
const #95 = Asciz	elems3$5;
const #96 = Asciz	filter;
const #97 = Asciz	(Lscala/Function3;Lscala/collection/generic/CanBuildFrom;Lscala/collection/generic/CanBuildFrom;Lscala/collection/generic/CanBuildFrom;)Lscala/Tuple3;;
const #98 = Asciz	repr;
const #99 = Asciz	()Ljava/lang/Object;;
const #100 = NameAndType	#98:#99;//  repr:()Ljava/lang/Object;
const #101 = InterfaceMethod	#56.#100;	//  scala/collection/TraversableLike.repr:()Ljava/lang/Object;
const #102 = Asciz	scala/collection/generic/CanBuildFrom;
const #103 = class	#102;	//  scala/collection/generic/CanBuildFrom
const #104 = Asciz	apply;
const #105 = Asciz	(Ljava/lang/Object;)Lscala/collection/mutable/Builder;;
const #106 = NameAndType	#104:#105;//  apply:(Ljava/lang/Object;)Lscala/collection/mutable/Builder;
const #107 = InterfaceMethod	#103.#106;	//  scala/collection/generic/CanBuildFrom.apply:(Ljava/lang/Object;)Lscala/collection/mutable/Builder;
const #108 = Asciz	scala/Tuple3$Zipped$$anonfun$filter$1;
const #109 = class	#108;	//  scala/Tuple3$Zipped$$anonfun$filter$1
const #110 = Asciz	(Lscala/Tuple3$Zipped;Lscala/Function3;Lscala/collection/mutable/Builder;Lscala/collection/mutable/Builder;Lscala/collection/mutable/Builder;Lscala/collection/Iterator;Lscala/collection/Iterator;)V;
const #111 = NameAndType	#14:#110;//  "<init>":(Lscala/Tuple3$Zipped;Lscala/Function3;Lscala/collection/mutable/Builder;Lscala/collection/mutable/Builder;Lscala/collection/mutable/Builder;Lscala/collection/Iterator;Lscala/collection/Iterator;)V
const #112 = Method	#109.#111;	//  scala/Tuple3$Zipped$$anonfun$filter$1."<init>":(Lscala/Tuple3$Zipped;Lscala/Function3;Lscala/collection/mutable/Builder;Lscala/collection/mutable/Builder;Lscala/collection/mutable/Builder;Lscala/collection/Iterator;Lscala/collection/Iterator;)V
const #113 = Asciz	scala/Tuple3;
const #114 = class	#113;	//  scala/Tuple3
const #115 = Asciz	scala/collection/mutable/Builder;
const #116 = class	#115;	//  scala/collection/mutable/Builder
const #117 = Asciz	result;
const #118 = NameAndType	#117:#99;//  result:()Ljava/lang/Object;
const #119 = InterfaceMethod	#116.#118;	//  scala/collection/mutable/Builder.result:()Ljava/lang/Object;
const #120 = Asciz	(Ljava/lang/Object;Ljava/lang/Object;Ljava/lang/Object;)V;
const #121 = NameAndType	#14:#120;//  "<init>":(Ljava/lang/Object;Ljava/lang/Object;Ljava/lang/Object;)V
const #122 = Method	#114.#121;	//  scala/Tuple3."<init>":(Ljava/lang/Object;Ljava/lang/Object;Ljava/lang/Object;)V
const #123 = Asciz	f$3;
const #124 = Asciz	cbf1;
const #125 = Asciz	Lscala/collection/generic/CanBuildFrom;;
const #126 = Asciz	cbf2;
const #127 = Asciz	cbf3;
const #128 = Asciz	b1$2;
const #129 = Asciz	Lscala/collection/mutable/Builder;;
const #130 = Asciz	b2$1;
const #131 = Asciz	b3$1;
const #132 = Asciz	elems2$4;
const #133 = Asciz	elems3$4;
const #134 = Asciz	<To1:Ljava/lang/Object;To2:Ljava/lang/Object;To3:Ljava/lang/Object;>(Lscala/Function3<TEl1;TEl2;TEl3;Ljava/lang/Boolean;>;Lscala/collection/generic/CanBuildFrom<TRepr1;TEl1;TTo1;>;Lscala/collection/generic/CanBuildFrom<TRepr2;TEl2;TTo2;>;Lscala/collection/generic/CanBuildFrom<TRepr3;TEl3;TTo3;>;)Lscala/Tuple3<TTo1;TTo2;TTo3;>;;
const #135 = Asciz	flatMap;
const #136 = Asciz	(Lscala/Function3;Lscala/collection/generic/CanBuildFrom;)Ljava/lang/Object;;
const #137 = Asciz	scala/Tuple3$Zipped$$anonfun$flatMap$1;
const #138 = class	#137;	//  scala/Tuple3$Zipped$$anonfun$flatMap$1
const #139 = Asciz	(Lscala/Tuple3$Zipped;Lscala/Function3;Lscala/collection/mutable/Builder;Lscala/collection/Iterator;Lscala/collection/Iterator;)V;
const #140 = NameAndType	#14:#139;//  "<init>":(Lscala/Tuple3$Zipped;Lscala/Function3;Lscala/collection/mutable/Builder;Lscala/collection/Iterator;Lscala/collection/Iterator;)V
const #141 = Method	#138.#140;	//  scala/Tuple3$Zipped$$anonfun$flatMap$1."<init>":(Lscala/Tuple3$Zipped;Lscala/Function3;Lscala/collection/mutable/Builder;Lscala/collection/Iterator;Lscala/collection/Iterator;)V
const #142 = Asciz	f$2;
const #143 = Asciz	cbf;
const #144 = Asciz	b$2;
const #145 = Asciz	elems2$3;
const #146 = Asciz	elems3$3;
const #147 = Asciz	<B:Ljava/lang/Object;To:Ljava/lang/Object;>(Lscala/Function3<TEl1;TEl2;TEl3;Lscala/collection/Traversable<TB;>;>;Lscala/collection/generic/CanBuildFrom<TRepr1;TB;TTo;>;)TTo;;
const #148 = Asciz	map;
const #149 = Asciz	scala/Tuple3$Zipped$$anonfun$map$1;
const #150 = class	#149;	//  scala/Tuple3$Zipped$$anonfun$map$1
const #151 = Method	#150.#140;	//  scala/Tuple3$Zipped$$anonfun$map$1."<init>":(Lscala/Tuple3$Zipped;Lscala/Function3;Lscala/collection/mutable/Builder;Lscala/collection/Iterator;Lscala/collection/Iterator;)V
const #152 = Asciz	f$1;
const #153 = Asciz	b$1;
const #154 = Asciz	elems2$2;
const #155 = Asciz	elems3$2;
const #156 = Asciz	<B:Ljava/lang/Object;To:Ljava/lang/Object;>(Lscala/Function3<TEl1;TEl2;TEl3;TB;>;Lscala/collection/generic/CanBuildFrom<TRepr1;TB;TTo;>;)TTo;;
const #157 = Asciz	<Repr1:Ljava/lang/Object;El1:Ljava/lang/Object;Repr2:Ljava/lang/Object;El2:Ljava/lang/Object;Repr3:Ljava/lang/Object;El3:Ljava/lang/Object;>Ljava/lang/Object;Lscala/ScalaObject;;
const #158 = Asciz	Scala;
const #159 = Asciz	InnerClasses;
const #160 = Asciz	Zipped;
const #161 = Asciz	$anonfun$map$1;
const #162 = Asciz	$anonfun$filter$1;
const #163 = Asciz	$anonfun$exists$1;
const #164 = Asciz	$anonfun$forall$1;
const #165 = Asciz	$anonfun$flatMap$1;
const #166 = Asciz	$anonfun$foreach$1;
const #167 = Asciz	scala/ScalaObject;
const #168 = class	#167;	//  scala/ScalaObject

{
public final scala.Tuple3 $outer;

public scala.Tuple3$Zipped(scala.Tuple3, scala.collection.TraversableLike, scala.collection.IterableLike, scala.collection.IterableLike);
  Code:
   Stack=2, Locals=5, Args_size=5
   0:	aload_0
   1:	aload_2
   2:	putfield	#21; //Field coll1:Lscala/collection/TraversableLike;
   5:	aload_0
   6:	aload_3
   7:	putfield	#23; //Field coll2:Lscala/collection/IterableLike;
   10:	aload_0
   11:	aload	4
   13:	putfield	#25; //Field coll3:Lscala/collection/IterableLike;
   16:	aload_1
   17:	ifnonnull	28
   20:	new	#27; //class java/lang/NullPointerException
   23:	dup
   24:	invokespecial	#30; //Method java/lang/NullPointerException."<init>":()V
   27:	athrow
   28:	aload_0
   29:	aload_1
   30:	putfield	#32; //Field $outer:Lscala/Tuple3;
   33:	aload_0
   34:	invokespecial	#35; //Method java/lang/Object."<init>":()V
   37:	return
  LineNumberTable: 
   line 50: 0
   line 51: 5
   line 52: 10
   line 50: 16

  LocalVariableTable: 
   Start  Length  Slot  Name   Signature
   0      38      0    this       Lscala/Tuple3$Zipped;
   0      38      1    $outer       Lscala/Tuple3;
   0      38      2    coll1       Lscala/collection/TraversableLike;
   0      38      3    coll2       Lscala/collection/IterableLike;
   0      38      4    coll3       Lscala/collection/IterableLike;

  Signature: length = 0x2
   00 27 

public scala.Tuple3 scala$Tuple3$Zipped$$$outer();
  Code:
   Stack=1, Locals=1, Args_size=1
   0:	aload_0
   1:	getfield	#32; //Field $outer:Lscala/Tuple3;
   4:	areturn
  LineNumberTable: 
   line 50: 0


public void foreach(scala.Function3);
  Code:
   Stack=7, Locals=4, Args_size=2
   0:	aload_0
   1:	getfield	#23; //Field coll2:Lscala/collection/IterableLike;
   4:	invokeinterface	#49,  1; //InterfaceMethod scala/collection/IterableLike.iterator:()Lscala/collection/Iterator;
   9:	astore_2
   10:	aload_0
   11:	getfield	#25; //Field coll3:Lscala/collection/IterableLike;
   14:	invokeinterface	#49,  1; //InterfaceMethod scala/collection/IterableLike.iterator:()Lscala/collection/Iterator;
   19:	astore_3
   20:	aload_0
   21:	getfield	#21; //Field coll1:Lscala/collection/TraversableLike;
   24:	new	#51; //class scala/Tuple3$Zipped$$anonfun$foreach$1
   27:	dup
   28:	aload_0
   29:	aload_1
   30:	aload_2
   31:	aload_3
   32:	invokespecial	#54; //Method scala/Tuple3$Zipped$$anonfun$foreach$1."<init>":(Lscala/Tuple3$Zipped;Lscala/Function3;Lscala/collection/Iterator;Lscala/collection/Iterator;)V
   35:	invokeinterface	#59,  2; //InterfaceMethod scala/collection/TraversableLike.foreach:(Lscala/Function1;)V
   40:	return
  LineNumberTable: 
   line 127: 0
   line 128: 10
   line 130: 20

  LocalVariableTable: 
   Start  Length  Slot  Name   Signature
   0      41      0    this       Lscala/Tuple3$Zipped;
   0      41      1    f$6       Lscala/Function3;
   10      30      2    elems2$7       Lscala/collection/Iterator;
   20      20      3    elems3$7       Lscala/collection/Iterator;

  Signature: length = 0x2
   00 41 

public boolean forall(scala.Function3);
  Code:
   Stack=8, Locals=5, Args_size=2
   0:	new	#69; //class scala/runtime/BooleanRef
   3:	dup
   4:	iconst_1
   5:	invokespecial	#72; //Method scala/runtime/BooleanRef."<init>":(Z)V
   8:	astore_2
   9:	aload_0
   10:	getfield	#23; //Field coll2:Lscala/collection/IterableLike;
   13:	invokeinterface	#49,  1; //InterfaceMethod scala/collection/IterableLike.iterator:()Lscala/collection/Iterator;
   18:	astore_3
   19:	aload_0
   20:	getfield	#25; //Field coll3:Lscala/collection/IterableLike;
   23:	invokeinterface	#49,  1; //InterfaceMethod scala/collection/IterableLike.iterator:()Lscala/collection/Iterator;
   28:	astore	4
   30:	aload_0
   31:	getfield	#21; //Field coll1:Lscala/collection/TraversableLike;
   34:	new	#74; //class scala/Tuple3$Zipped$$anonfun$forall$1
   37:	dup
   38:	aload_0
   39:	aload_1
   40:	aload_2
   41:	aload_3
   42:	aload	4
   44:	invokespecial	#77; //Method scala/Tuple3$Zipped$$anonfun$forall$1."<init>":(Lscala/Tuple3$Zipped;Lscala/Function3;Lscala/runtime/BooleanRef;Lscala/collection/Iterator;Lscala/collection/Iterator;)V
   47:	invokeinterface	#59,  2; //InterfaceMethod scala/collection/TraversableLike.foreach:(Lscala/Function1;)V
   52:	aload_2
   53:	getfield	#81; //Field scala/runtime/BooleanRef.elem:Z
   56:	ireturn
  LineNumberTable: 
   line 115: 0
   line 116: 9
   line 117: 19
   line 119: 30
   line 123: 40
   line 119: 41
   line 123: 52

  LocalVariableTable: 
   Start  Length  Slot  Name   Signature
   0      57      0    this       Lscala/Tuple3$Zipped;
   0      57      1    f$5       Lscala/Function3;
   9      47      2    acc$2       Lscala/runtime/BooleanRef;
   19      37      3    elems2$6       Lscala/collection/Iterator;
   30      26      4    elems3$6       Lscala/collection/Iterator;

  Signature: length = 0x2
   00 57 

public boolean exists(scala.Function3);
  Code:
   Stack=8, Locals=5, Args_size=2
   0:	new	#69; //class scala/runtime/BooleanRef
   3:	dup
   4:	iconst_0
   5:	invokespecial	#72; //Method scala/runtime/BooleanRef."<init>":(Z)V
   8:	astore_2
   9:	aload_0
   10:	getfield	#23; //Field coll2:Lscala/collection/IterableLike;
   13:	invokeinterface	#49,  1; //InterfaceMethod scala/collection/IterableLike.iterator:()Lscala/collection/Iterator;
   18:	astore_3
   19:	aload_0
   20:	getfield	#25; //Field coll3:Lscala/collection/IterableLike;
   23:	invokeinterface	#49,  1; //InterfaceMethod scala/collection/IterableLike.iterator:()Lscala/collection/Iterator;
   28:	astore	4
   30:	aload_0
   31:	getfield	#21; //Field coll1:Lscala/collection/TraversableLike;
   34:	new	#90; //class scala/Tuple3$Zipped$$anonfun$exists$1
   37:	dup
   38:	aload_0
   39:	aload_1
   40:	aload_2
   41:	aload_3
   42:	aload	4
   44:	invokespecial	#91; //Method scala/Tuple3$Zipped$$anonfun$exists$1."<init>":(Lscala/Tuple3$Zipped;Lscala/Function3;Lscala/runtime/BooleanRef;Lscala/collection/Iterator;Lscala/collection/Iterator;)V
   47:	invokeinterface	#59,  2; //InterfaceMethod scala/collection/TraversableLike.foreach:(Lscala/Function1;)V
   52:	aload_2
   53:	getfield	#81; //Field scala/runtime/BooleanRef.elem:Z
   56:	ireturn
  LineNumberTable: 
   line 103: 0
   line 104: 9
   line 105: 19
   line 107: 30
   line 111: 40
   line 107: 41
   line 111: 52

  LocalVariableTable: 
   Start  Length  Slot  Name   Signature
   0      57      0    this       Lscala/Tuple3$Zipped;
   0      57      1    f$4       Lscala/Function3;
   9      47      2    acc$1       Lscala/runtime/BooleanRef;
   19      37      3    elems2$5       Lscala/collection/Iterator;
   30      26      4    elems3$5       Lscala/collection/Iterator;

  Signature: length = 0x2
   00 57 

public scala.Tuple3 filter(scala.Function3, scala.collection.generic.CanBuildFrom, scala.collection.generic.CanBuildFrom, scala.collection.generic.CanBuildFrom);
  Code:
   Stack=10, Locals=10, Args_size=5
   0:	aload_2
   1:	aload_0
   2:	getfield	#21; //Field coll1:Lscala/collection/TraversableLike;
   5:	invokeinterface	#101,  1; //InterfaceMethod scala/collection/TraversableLike.repr:()Ljava/lang/Object;
   10:	invokeinterface	#107,  2; //InterfaceMethod scala/collection/generic/CanBuildFrom.apply:(Ljava/lang/Object;)Lscala/collection/mutable/Builder;
   15:	astore	5
   17:	aload_3
   18:	aload_0
   19:	getfield	#23; //Field coll2:Lscala/collection/IterableLike;
   22:	invokeinterface	#101,  1; //InterfaceMethod scala/collection/TraversableLike.repr:()Ljava/lang/Object;
   27:	invokeinterface	#107,  2; //InterfaceMethod scala/collection/generic/CanBuildFrom.apply:(Ljava/lang/Object;)Lscala/collection/mutable/Builder;
   32:	astore	6
   34:	aload	4
   36:	aload_0
   37:	getfield	#25; //Field coll3:Lscala/collection/IterableLike;
   40:	invokeinterface	#101,  1; //InterfaceMethod scala/collection/TraversableLike.repr:()Ljava/lang/Object;
   45:	invokeinterface	#107,  2; //InterfaceMethod scala/collection/generic/CanBuildFrom.apply:(Ljava/lang/Object;)Lscala/collection/mutable/Builder;
   50:	astore	7
   52:	aload_0
   53:	getfield	#23; //Field coll2:Lscala/collection/IterableLike;
   56:	invokeinterface	#49,  1; //InterfaceMethod scala/collection/IterableLike.iterator:()Lscala/collection/Iterator;
   61:	astore	8
   63:	aload_0
   64:	getfield	#25; //Field coll3:Lscala/collection/IterableLike;
   67:	invokeinterface	#49,  1; //InterfaceMethod scala/collection/IterableLike.iterator:()Lscala/collection/Iterator;
   72:	astore	9
   74:	aload_0
   75:	getfield	#21; //Field coll1:Lscala/collection/TraversableLike;
   78:	new	#109; //class scala/Tuple3$Zipped$$anonfun$filter$1
   81:	dup
   82:	aload_0
   83:	aload_1
   84:	aload	5
   86:	aload	6
   88:	aload	7
   90:	aload	8
   92:	aload	9
   94:	invokespecial	#112; //Method scala/Tuple3$Zipped$$anonfun$filter$1."<init>":(Lscala/Tuple3$Zipped;Lscala/Function3;Lscala/collection/mutable/Builder;Lscala/collection/mutable/Builder;Lscala/collection/mutable/Builder;Lscala/collection/Iterator;Lscala/collection/Iterator;)V
   97:	invokeinterface	#59,  2; //InterfaceMethod scala/collection/TraversableLike.foreach:(Lscala/Function1;)V
   102:	new	#114; //class scala/Tuple3
   105:	dup
   106:	aload	5
   108:	invokeinterface	#119,  1; //InterfaceMethod scala/collection/mutable/Builder.result:()Ljava/lang/Object;
   113:	aload	6
   115:	invokeinterface	#119,  1; //InterfaceMethod scala/collection/mutable/Builder.result:()Ljava/lang/Object;
   120:	aload	7
   122:	invokeinterface	#119,  1; //InterfaceMethod scala/collection/mutable/Builder.result:()Ljava/lang/Object;
   127:	invokespecial	#122; //Method scala/Tuple3."<init>":(Ljava/lang/Object;Ljava/lang/Object;Ljava/lang/Object;)V
   130:	areturn
  LineNumberTable: 
   line 81: 0
   line 82: 17
   line 83: 34
   line 84: 52
   line 85: 63
   line 87: 74
   line 99: 102

  LocalVariableTable: 
   Start  Length  Slot  Name   Signature
   0      131      0    this       Lscala/Tuple3$Zipped;
   0      131      1    f$3       Lscala/Function3;
   0      131      2    cbf1       Lscala/collection/generic/CanBuildFrom;
   0      131      3    cbf2       Lscala/collection/generic/CanBuildFrom;
   0      131      4    cbf3       Lscala/collection/generic/CanBuildFrom;
   17      113      5    b1$2       Lscala/collection/mutable/Builder;
   34      96      6    b2$1       Lscala/collection/mutable/Builder;
   52      78      7    b3$1       Lscala/collection/mutable/Builder;
   63      67      8    elems2$4       Lscala/collection/Iterator;
   74      56      9    elems3$4       Lscala/collection/Iterator;

  Signature: length = 0x2
   00 FFFFFF86 

public java.lang.Object flatMap(scala.Function3, scala.collection.generic.CanBuildFrom);
  Code:
   Stack=8, Locals=6, Args_size=3
   0:	aload_2
   1:	aload_0
   2:	getfield	#21; //Field coll1:Lscala/collection/TraversableLike;
   5:	invokeinterface	#101,  1; //InterfaceMethod scala/collection/TraversableLike.repr:()Ljava/lang/Object;
   10:	invokeinterface	#107,  2; //InterfaceMethod scala/collection/generic/CanBuildFrom.apply:(Ljava/lang/Object;)Lscala/collection/mutable/Builder;
   15:	astore_3
   16:	aload_0
   17:	getfield	#23; //Field coll2:Lscala/collection/IterableLike;
   20:	invokeinterface	#49,  1; //InterfaceMethod scala/collection/IterableLike.iterator:()Lscala/collection/Iterator;
   25:	astore	4
   27:	aload_0
   28:	getfield	#25; //Field coll3:Lscala/collection/IterableLike;
   31:	invokeinterface	#49,  1; //InterfaceMethod scala/collection/IterableLike.iterator:()Lscala/collection/Iterator;
   36:	astore	5
   38:	aload_0
   39:	getfield	#21; //Field coll1:Lscala/collection/TraversableLike;
   42:	new	#138; //class scala/Tuple3$Zipped$$anonfun$flatMap$1
   45:	dup
   46:	aload_0
   47:	aload_1
   48:	aload_3
   49:	aload	4
   51:	aload	5
   53:	invokespecial	#141; //Method scala/Tuple3$Zipped$$anonfun$flatMap$1."<init>":(Lscala/Tuple3$Zipped;Lscala/Function3;Lscala/collection/mutable/Builder;Lscala/collection/Iterator;Lscala/collection/Iterator;)V
   56:	invokeinterface	#59,  2; //InterfaceMethod scala/collection/TraversableLike.foreach:(Lscala/Function1;)V
   61:	aload_3
   62:	invokeinterface	#119,  1; //InterfaceMethod scala/collection/mutable/Builder.result:()Ljava/lang/Object;
   67:	areturn
  LineNumberTable: 
   line 66: 0
   line 67: 16
   line 68: 27
   line 70: 38
   line 74: 61

  LocalVariableTable: 
   Start  Length  Slot  Name   Signature
   0      68      0    this       Lscala/Tuple3$Zipped;
   0      68      1    f$2       Lscala/Function3;
   0      68      2    cbf       Lscala/collection/generic/CanBuildFrom;
   16      51      3    b$2       Lscala/collection/mutable/Builder;
   27      40      4    elems2$3       Lscala/collection/Iterator;
   38      29      5    elems3$3       Lscala/collection/Iterator;

  Signature: length = 0x2
   00 FFFFFF93 

public java.lang.Object map(scala.Function3, scala.collection.generic.CanBuildFrom);
  Code:
   Stack=8, Locals=6, Args_size=3
   0:	aload_2
   1:	aload_0
   2:	getfield	#21; //Field coll1:Lscala/collection/TraversableLike;
   5:	invokeinterface	#101,  1; //InterfaceMethod scala/collection/TraversableLike.repr:()Ljava/lang/Object;
   10:	invokeinterface	#107,  2; //InterfaceMethod scala/collection/generic/CanBuildFrom.apply:(Ljava/lang/Object;)Lscala/collection/mutable/Builder;
   15:	astore_3
   16:	aload_0
   17:	getfield	#23; //Field coll2:Lscala/collection/IterableLike;
   20:	invokeinterface	#49,  1; //InterfaceMethod scala/collection/IterableLike.iterator:()Lscala/collection/Iterator;
   25:	astore	4
   27:	aload_0
   28:	getfield	#25; //Field coll3:Lscala/collection/IterableLike;
   31:	invokeinterface	#49,  1; //InterfaceMethod scala/collection/IterableLike.iterator:()Lscala/collection/Iterator;
   36:	astore	5
   38:	aload_0
   39:	getfield	#21; //Field coll1:Lscala/collection/TraversableLike;
   42:	new	#150; //class scala/Tuple3$Zipped$$anonfun$map$1
   45:	dup
   46:	aload_0
   47:	aload_1
   48:	aload_3
   49:	aload	4
   51:	aload	5
   53:	invokespecial	#151; //Method scala/Tuple3$Zipped$$anonfun$map$1."<init>":(Lscala/Tuple3$Zipped;Lscala/Function3;Lscala/collection/mutable/Builder;Lscala/collection/Iterator;Lscala/collection/Iterator;)V
   56:	invokeinterface	#59,  2; //InterfaceMethod scala/collection/TraversableLike.foreach:(Lscala/Function1;)V
   61:	aload_3
   62:	invokeinterface	#119,  1; //InterfaceMethod scala/collection/mutable/Builder.result:()Ljava/lang/Object;
   67:	areturn
  LineNumberTable: 
   line 54: 0
   line 55: 16
   line 56: 27
   line 58: 38
   line 62: 61

  LocalVariableTable: 
   Start  Length  Slot  Name   Signature
   0      68      0    this       Lscala/Tuple3$Zipped;
   0      68      1    f$1       Lscala/Function3;
   0      68      2    cbf       Lscala/collection/generic/CanBuildFrom;
   16      51      3    b$1       Lscala/collection/mutable/Builder;
   27      40      4    elems2$2       Lscala/collection/Iterator;
   38      29      5    elems3$2       Lscala/collection/Iterator;

  Signature: length = 0x2
   00 FFFFFF9C 

}

