Compiled from "Tuple21.scala"
public class scala.Tuple21 extends java.lang.Object implements scala.Product21,scala.ScalaObject,scala.Product,java.io.Serializable
  SourceFile: "Tuple21.scala"
  Signature: length = 0x2
   01 48 
  ScalaSig: length = 0x28D3
   05 00 FFFFFF87 5A 06 04 01 02 40 05 02 07 54 75 70 6C
   65 32 31 0A 01 03 01 05 73 63 61 6C 61 03 00 15
   16 06 15 1F 22 25 28 2B 2E 31 34 37 3A 3D 40 43
   46 49 4C 4F 52 55 58 13 05 00 07 0F 5A 5D 10 02
   08 0D 0D 01 09 0A 02 0A 0B 01 04 6C 61 6E 67 0A
   01 0C 01 04 6A 61 76 61 09 02 0E 09 02 06 4F 62
   6A 65 63 74 10 17 10 11 13 1E 21 24 27 2A 2D 30
   33 36 39 3C 3F 42 45 48 4B 4E 51 54 57 0D 01 02
   09 02 12 02 02 09 50 72 6F 64 75 63 74 32 31 10
   02 14 15 0C 00 04 08 16 00 FFFFFF84 FFFFFF80 FFFFFF84 FFFFFFC2 00 17 02
   02 54 31 11 02 18 1B 10 02 10 19 09 02 1A 02 02
   07 4E 6F 74 68 69 6E 67 10 02 10 1C 09 02 1D 02
   02 03 41 6E 79 10 02 14 1F 04 08 20 00 FFFFFF84 FFFFFF80 FFFFFF84
   FFFFFFC2 00 17 02 02 54 32 10 02 14 22 04 08 23 00 FFFFFF84
   FFFFFF80 FFFFFF84 FFFFFFC2 00 17 02 02 54 33 10 02 14 25 04 08 26
   00 FFFFFF84 FFFFFF80 FFFFFF84 FFFFFFC2 00 17 02 02 54 34 10 02 14 28 04
   08 29 00 FFFFFF84 FFFFFF80 FFFFFF84 FFFFFFC2 00 17 02 02 54 35 10 02 14
   2B 04 08 2C 00 FFFFFF84 FFFFFF80 FFFFFF84 FFFFFFC2 00 17 02 02 54 36 10
   02 14 2E 04 08 2F 00 FFFFFF84 FFFFFF80 FFFFFF84 FFFFFFC2 00 17 02 02 54
   37 10 02 14 31 04 08 32 00 FFFFFF84 FFFFFF80 FFFFFF84 FFFFFFC2 00 17 02
   02 54 38 10 02 14 34 04 08 35 00 FFFFFF84 FFFFFF80 FFFFFF84 FFFFFFC2 00
   17 02 02 54 39 10 02 14 37 04 08 38 00 FFFFFF84 FFFFFF80 FFFFFF84
   FFFFFFC2 00 17 02 03 54 31 30 10 02 14 3A 04 08 3B 00
   FFFFFF84 FFFFFF80 FFFFFF84 FFFFFFC2 00 17 02 03 54 31 31 10 02 14 3D 04
   08 3E 00 FFFFFF84 FFFFFF80 FFFFFF84 FFFFFFC2 00 17 02 03 54 31 32 10 02
   14 40 04 08 41 00 FFFFFF84 FFFFFF80 FFFFFF84 FFFFFFC2 00 17 02 03 54 31
   33 10 02 14 43 04 08 44 00 FFFFFF84 FFFFFF80 FFFFFF84 FFFFFFC2 00 17 02
   03 54 31 34 10 02 14 46 04 08 47 00 FFFFFF84 FFFFFF80 FFFFFF84 FFFFFFC2
   00 17 02 03 54 31 35 10 02 14 49 04 08 4A 00 FFFFFF84
   FFFFFF80 FFFFFF84 FFFFFFC2 00 17 02 03 54 31 36 10 02 14 4C 04 08
   4D 00 FFFFFF84 FFFFFF80 FFFFFF84 FFFFFFC2 00 17 02 03 54 31 37 10 02 14
   4F 04 08 50 00 FFFFFF84 FFFFFF80 FFFFFF84 FFFFFFC2 00 17 02 03 54 31 38
   10 02 14 52 04 08 53 00 FFFFFF84 FFFFFF80 FFFFFF84 FFFFFFC2 00 17 02 03
   54 31 39 10 02 14 55 04 08 56 00 FFFFFF84 FFFFFF80 FFFFFF84 FFFFFFC2 00
   17 02 03 54 32 30 10 02 14 58 04 08 59 00 FFFFFF84 FFFFFF80
   FFFFFF84 FFFFFFC2 00 17 02 03 54 32 31 10 02 10 5B 09 02 5C
   02 02 0B 53 63 61 6C 61 4F 62 6A 65 63 74 10 02
   10 5E 09 02 5F 02 02 07 50 72 6F 64 75 63 74 08
   08 61 00 FFFFFF82 FFFFFFCA FFFFFF80 FFFFFF84 00 62 01 02 5F 31 15 01 13
   08 08 64 00 FFFFFF82 FFFFFF88 FFFFFFA0 FFFFFF80 04 13 01 03 5F 31 20 08
   08 66 00 FFFFFF82 FFFFFFCA FFFFFF80 FFFFFF84 00 67 01 02 5F 32 15 01 1E
   08 08 69 00 FFFFFF82 FFFFFF88 FFFFFFA0 FFFFFF80 04 1E 01 03 5F 32 20 08
   08 6B 00 FFFFFF82 FFFFFFCA FFFFFF80 FFFFFF84 00 6C 01 02 5F 33 15 01 21
   08 08 6E 00 FFFFFF82 FFFFFF88 FFFFFFA0 FFFFFF80 04 21 01 03 5F 33 20 08
   08 70 00 FFFFFF82 FFFFFFCA FFFFFF80 FFFFFF84 00 71 01 02 5F 34 15 01 24
   08 08 73 00 FFFFFF82 FFFFFF88 FFFFFFA0 FFFFFF80 04 24 01 03 5F 34 20 08
   08 75 00 FFFFFF82 FFFFFFCA FFFFFF80 FFFFFF84 00 76 01 02 5F 35 15 01 27
   08 08 78 00 FFFFFF82 FFFFFF88 FFFFFFA0 FFFFFF80 04 27 01 03 5F 35 20 08
   08 7A 00 FFFFFF82 FFFFFFCA FFFFFF80 FFFFFF84 00 7B 01 02 5F 36 15 01 2A
   08 08 7D 00 FFFFFF82 FFFFFF88 FFFFFFA0 FFFFFF80 04 2A 01 03 5F 36 20 08
   09 7F 00 FFFFFF82 FFFFFFCA FFFFFF80 FFFFFF84 00 FFFFFF81 00 01 02 5F 37 15 01
   2D 08 09 FFFFFF81 02 00 FFFFFF82 FFFFFF88 FFFFFFA0 FFFFFF80 04 2D 01 03 5F 37
   20 08 0A FFFFFF81 04 00 FFFFFF82 FFFFFFCA FFFFFF80 FFFFFF84 00 FFFFFF81 05 01 02 5F
   38 15 01 30 08 09 FFFFFF81 07 00 FFFFFF82 FFFFFF88 FFFFFFA0 FFFFFF80 04 30 01
   03 5F 38 20 08 0A FFFFFF81 09 00 FFFFFF82 FFFFFFCA FFFFFF80 FFFFFF84 00 FFFFFF81 0A
   01 02 5F 39 15 01 33 08 09 FFFFFF81 0C 00 FFFFFF82 FFFFFF88 FFFFFFA0 FFFFFF80
   04 33 01 03 5F 39 20 08 0A FFFFFF81 0E 00 FFFFFF82 FFFFFFCA FFFFFF80 FFFFFF84
   00 FFFFFF81 0F 01 03 5F 31 30 15 01 36 08 09 FFFFFF81 11 00
   FFFFFF82 FFFFFF88 FFFFFFA0 FFFFFF80 04 36 01 04 5F 31 30 20 08 0A FFFFFF81 13
   00 FFFFFF82 FFFFFFCA FFFFFF80 FFFFFF84 00 FFFFFF81 14 01 03 5F 31 31 15 01 39
   08 09 FFFFFF81 16 00 FFFFFF82 FFFFFF88 FFFFFFA0 FFFFFF80 04 39 01 04 5F 31 31
   20 08 0A FFFFFF81 18 00 FFFFFF82 FFFFFFCA FFFFFF80 FFFFFF84 00 FFFFFF81 19 01 03 5F
   31 32 15 01 3C 08 09 FFFFFF81 1B 00 FFFFFF82 FFFFFF88 FFFFFFA0 FFFFFF80 04 3C
   01 04 5F 31 32 20 08 0A FFFFFF81 1D 00 FFFFFF82 FFFFFFCA FFFFFF80 FFFFFF84 00
   FFFFFF81 1E 01 03 5F 31 33 15 01 3F 08 09 FFFFFF81 20 00 FFFFFF82
   FFFFFF88 FFFFFFA0 FFFFFF80 04 3F 01 04 5F 31 33 20 08 0A FFFFFF81 22 00
   FFFFFF82 FFFFFFCA FFFFFF80 FFFFFF84 00 FFFFFF81 23 01 03 5F 31 34 15 01 42 08
   09 FFFFFF81 25 00 FFFFFF82 FFFFFF88 FFFFFFA0 FFFFFF80 04 42 01 04 5F 31 34 20
   08 0A FFFFFF81 27 00 FFFFFF82 FFFFFFCA FFFFFF80 FFFFFF84 00 FFFFFF81 28 01 03 5F 31
   35 15 01 45 08 09 FFFFFF81 2A 00 FFFFFF82 FFFFFF88 FFFFFFA0 FFFFFF80 04 45 01
   04 5F 31 35 20 08 0A FFFFFF81 2C 00 FFFFFF82 FFFFFFCA FFFFFF80 FFFFFF84 00 FFFFFF81
   2D 01 03 5F 31 36 15 01 48 08 09 FFFFFF81 2F 00 FFFFFF82 FFFFFF88
   FFFFFFA0 FFFFFF80 04 48 01 04 5F 31 36 20 08 0A FFFFFF81 31 00 FFFFFF82
   FFFFFFCA FFFFFF80 FFFFFF84 00 FFFFFF81 32 01 03 5F 31 37 15 01 4B 08 09
   FFFFFF81 34 00 FFFFFF82 FFFFFF88 FFFFFFA0 FFFFFF80 04 4B 01 04 5F 31 37 20 08
   0A FFFFFF81 36 00 FFFFFF82 FFFFFFCA FFFFFF80 FFFFFF84 00 FFFFFF81 37 01 03 5F 31 38
   15 01 4E 08 09 FFFFFF81 39 00 FFFFFF82 FFFFFF88 FFFFFFA0 FFFFFF80 04 4E 01 04
   5F 31 38 20 08 0A FFFFFF81 3B 00 FFFFFF82 FFFFFFCA FFFFFF80 FFFFFF84 00 FFFFFF81 3C
   01 03 5F 31 39 15 01 51 08 09 FFFFFF81 3E 00 FFFFFF82 FFFFFF88 FFFFFFA0
   FFFFFF80 04 51 01 04 5F 31 39 20 08 0A FFFFFF81 40 00 FFFFFF82 FFFFFFCA
   FFFFFF80 FFFFFF84 00 FFFFFF81 41 01 03 5F 32 30 15 01 54 08 09 FFFFFF81
   43 00 FFFFFF82 FFFFFF88 FFFFFFA0 FFFFFF80 04 54 01 04 5F 32 30 20 08 0A
   FFFFFF81 45 00 FFFFFF82 FFFFFFCA FFFFFF80 FFFFFF84 00 FFFFFF81 46 01 03 5F 32 31 15
   01 57 08 09 FFFFFF81 48 00 FFFFFF82 FFFFFF88 FFFFFFA0 FFFFFF80 04 57 01 04 5F
   32 31 20 08 07 FFFFFF81 4A 00 FFFFFF84 00 FFFFFF81 4B 01 06 3C 69
   6E 69 74 3E 14 2C FFFFFF81 4C FFFFFF81 4D FFFFFF81 4E FFFFFF81 4F FFFFFF81 50
   FFFFFF81 51 FFFFFF81 52 FFFFFF81 53 FFFFFF81 54 FFFFFF81 55 FFFFFF81 56 FFFFFF81 57 FFFFFF81 58
   FFFFFF81 59 FFFFFF81 5A FFFFFF81 5B FFFFFF81 5C FFFFFF81 5D FFFFFF81 5E FFFFFF81 5F FFFFFF81 60
   FFFFFF81 61 10 17 10 00 13 1E 21 24 27 2A 2D 30 33 36
   39 3C 3F 42 45 48 4B 4E 51 54 57 08 06 61 FFFFFF81 49
   FFFFFFC0 00 13 08 06 66 FFFFFF81 49 FFFFFFC0 00 1E 08 06 6B FFFFFF81 49
   FFFFFFC0 00 21 08 06 70 FFFFFF81 49 FFFFFFC0 00 24 08 06 75 FFFFFF81 49
   FFFFFFC0 00 27 08 06 7A FFFFFF81 49 FFFFFFC0 00 2A 08 06 7F FFFFFF81 49
   FFFFFFC0 00 2D 08 07 FFFFFF81 04 FFFFFF81 49 FFFFFFC0 00 30 08 07 FFFFFF81 09
   FFFFFF81 49 FFFFFFC0 00 33 08 07 FFFFFF81 0E FFFFFF81 49 FFFFFFC0 00 36 08 07
   FFFFFF81 13 FFFFFF81 49 FFFFFFC0 00 39 08 07 FFFFFF81 18 FFFFFF81 49 FFFFFFC0 00 3C
   08 07 FFFFFF81 1D FFFFFF81 49 FFFFFFC0 00 3F 08 07 FFFFFF81 22 FFFFFF81 49 FFFFFFC0
   00 42 08 07 FFFFFF81 27 FFFFFF81 49 FFFFFFC0 00 45 08 07 FFFFFF81 2C FFFFFF81
   49 FFFFFFC0 00 48 08 07 FFFFFF81 31 FFFFFF81 49 FFFFFFC0 00 4B 08 07 FFFFFF81
   36 FFFFFF81 49 FFFFFFC0 00 4E 08 07 FFFFFF81 3B FFFFFF81 49 FFFFFFC0 00 51 08
   07 FFFFFF81 40 FFFFFF81 49 FFFFFFC0 00 54 08 07 FFFFFF81 45 FFFFFF81 49 FFFFFFC0 00
   57 08 07 FFFFFF81 63 00 FFFFFF84 20 FFFFFF81 64 01 08 74 6F 53 74
   72 69 6E 67 14 02 FFFFFF81 65 10 03 08 FFFFFF81 66 09 03 FFFFFF81
   67 09 02 06 53 74 72 69 6E 67 08 09 FFFFFF81 69 00 FFFFFF81
   FFFFFF80 FFFFFF84 00 FFFFFF81 6A 01 04 63 6F 70 79 15 2C FFFFFF81 6B FFFFFF81
   6E FFFFFF81 70 FFFFFF81 72 FFFFFF81 74 FFFFFF81 76 FFFFFF81 78 FFFFFF81 7A FFFFFF81 7C FFFFFF81
   7E FFFFFF82 00 FFFFFF82 02 FFFFFF82 04 FFFFFF82 06 FFFFFF82 08 FFFFFF82 0A FFFFFF82 0C FFFFFF82
   0E FFFFFF82 10 FFFFFF82 12 FFFFFF82 14 FFFFFF82 16 14 2C FFFFFF81 6C FFFFFF82 17 FFFFFF82
   3A FFFFFF82 54 FFFFFF82 6E FFFFFF83 08 FFFFFF83 22 FFFFFF83 3C FFFFFF83 56 FFFFFF83 70 FFFFFF84
   0A FFFFFF84 24 FFFFFF84 3E FFFFFF84 58 FFFFFF84 72 FFFFFF85 0C FFFFFF85 26 FFFFFF85 40 FFFFFF85
   5A FFFFFF85 74 FFFFFF86 0E FFFFFF86 28 10 2C 10 00 FFFFFF81 6D FFFFFF81 6F FFFFFF81
   71 FFFFFF81 73 FFFFFF81 75 FFFFFF81 77 FFFFFF81 79 FFFFFF81 7B FFFFFF81 7D FFFFFF81 7F FFFFFF82
   01 FFFFFF82 03 FFFFFF82 05 FFFFFF82 07 FFFFFF82 09 FFFFFF82 0B FFFFFF82 0D FFFFFF82 0F FFFFFF82
   11 FFFFFF82 13 FFFFFF82 15 10 03 14 FFFFFF81 6E 04 09 16 FFFFFF81 68 FFFFFF84
   FFFFFF80 FFFFFF80 FFFFFFC2 00 17 10 03 14 FFFFFF81 70 04 09 20 FFFFFF81 68 FFFFFF84
   FFFFFF80 FFFFFF80 FFFFFFC2 00 17 10 03 14 FFFFFF81 72 04 09 23 FFFFFF81 68 FFFFFF84
   FFFFFF80 FFFFFF80 FFFFFFC2 00 17 10 03 14 FFFFFF81 74 04 09 26 FFFFFF81 68 FFFFFF84
   FFFFFF80 FFFFFF80 FFFFFFC2 00 17 10 03 14 FFFFFF81 76 04 09 29 FFFFFF81 68 FFFFFF84
   FFFFFF80 FFFFFF80 FFFFFFC2 00 17 10 03 14 FFFFFF81 78 04 09 2C FFFFFF81 68 FFFFFF84
   FFFFFF80 FFFFFF80 FFFFFFC2 00 17 10 03 14 FFFFFF81 7A 04 09 2F FFFFFF81 68 FFFFFF84
   FFFFFF80 FFFFFF80 FFFFFFC2 00 17 10 03 14 FFFFFF81 7C 04 09 32 FFFFFF81 68 FFFFFF84
   FFFFFF80 FFFFFF80 FFFFFFC2 00 17 10 03 14 FFFFFF81 7E 04 09 35 FFFFFF81 68 FFFFFF84
   FFFFFF80 FFFFFF80 FFFFFFC2 00 17 10 03 14 FFFFFF82 00 04 09 38 FFFFFF81 68 FFFFFF84
   FFFFFF80 FFFFFF80 FFFFFFC2 00 17 10 03 14 FFFFFF82 02 04 09 3B FFFFFF81 68 FFFFFF84
   FFFFFF80 FFFFFF80 FFFFFFC2 00 17 10 03 14 FFFFFF82 04 04 09 3E FFFFFF81 68 FFFFFF84
   FFFFFF80 FFFFFF80 FFFFFFC2 00 17 10 03 14 FFFFFF82 06 04 09 41 FFFFFF81 68 FFFFFF84
   FFFFFF80 FFFFFF80 FFFFFFC2 00 17 10 03 14 FFFFFF82 08 04 09 44 FFFFFF81 68 FFFFFF84
   FFFFFF80 FFFFFF80 FFFFFFC2 00 17 10 03 14 FFFFFF82 0A 04 09 47 FFFFFF81 68 FFFFFF84
   FFFFFF80 FFFFFF80 FFFFFFC2 00 17 10 03 14 FFFFFF82 0C 04 09 4A FFFFFF81 68 FFFFFF84
   FFFFFF80 FFFFFF80 FFFFFFC2 00 17 10 03 14 FFFFFF82 0E 04 09 4D FFFFFF81 68 FFFFFF84
   FFFFFF80 FFFFFF80 FFFFFFC2 00 17 10 03 14 FFFFFF82 10 04 09 50 FFFFFF81 68 FFFFFF84
   FFFFFF80 FFFFFF80 FFFFFFC2 00 17 10 03 14 FFFFFF82 12 04 09 53 FFFFFF81 68 FFFFFF84
   FFFFFF80 FFFFFF80 FFFFFFC2 00 17 10 03 14 FFFFFF82 14 04 09 56 FFFFFF81 68 FFFFFF84
   FFFFFF80 FFFFFF80 FFFFFFC2 00 17 10 03 14 FFFFFF82 16 04 09 59 FFFFFF81 68 FFFFFF84
   FFFFFF80 FFFFFF80 FFFFFFC2 00 17 08 0B FFFFFF82 18 61 FFFFFF81 68 FFFFFF90 FFFFFF80 FFFFFFC0 00
   FFFFFF81 6D 08 09 FFFFFF82 19 00 FFFFFF91 FFFFFF80 FFFFFF84 00 FFFFFF82 1A 01 0E 63
   6F 70 79 24 64 65 66 61 75 6C 74 24 31 15 2C FFFFFF82
   1B FFFFFF82 25 FFFFFF82 26 FFFFFF82 27 FFFFFF82 28 FFFFFF82 29 FFFFFF82 2A FFFFFF82 2B FFFFFF82
   2C FFFFFF82 2D FFFFFF82 2E FFFFFF82 2F FFFFFF82 30 FFFFFF82 31 FFFFFF82 32 FFFFFF82 33 FFFFFF82
   34 FFFFFF82 35 FFFFFF82 36 FFFFFF82 37 FFFFFF82 38 FFFFFF82 39 2A 03 13 FFFFFF82 1C
   2B 02 FFFFFF82 1D 10 04 FFFFFF82 1E FFFFFF82 23 0D 02 FFFFFF82 1F 0A 04
   FFFFFF82 20 FFFFFF82 21 01 09 75 6E 63 68 65 63 6B 65 64 0A
   03 FFFFFF82 22 02 01 0A 61 6E 6E 6F 74 61 74 69 6F 6E
   09 04 FFFFFF82 24 FFFFFF82 1F 02 11 75 6E 63 68 65 63 6B 65
   64 56 61 72 69 61 6E 63 65 04 09 16 FFFFFF82 18 FFFFFF84 FFFFFF80
   FFFFFF80 FFFFFFC2 00 17 04 09 20 FFFFFF82 18 FFFFFF84 FFFFFF80 FFFFFF80 FFFFFFC2 00 17 04
   09 23 FFFFFF82 18 FFFFFF84 FFFFFF80 FFFFFF80 FFFFFFC2 00 17 04 09 26 FFFFFF82 18 FFFFFF84
   FFFFFF80 FFFFFF80 FFFFFFC2 00 17 04 09 29 FFFFFF82 18 FFFFFF84 FFFFFF80 FFFFFF80 FFFFFFC2 00 17
   04 09 2C FFFFFF82 18 FFFFFF84 FFFFFF80 FFFFFF80 FFFFFFC2 00 17 04 09 2F FFFFFF82 18
   FFFFFF84 FFFFFF80 FFFFFF80 FFFFFFC2 00 17 04 09 32 FFFFFF82 18 FFFFFF84 FFFFFF80 FFFFFF80 FFFFFFC2 00
   17 04 09 35 FFFFFF82 18 FFFFFF84 FFFFFF80 FFFFFF80 FFFFFFC2 00 17 04 09 38 FFFFFF82
   18 FFFFFF84 FFFFFF80 FFFFFF80 FFFFFFC2 00 17 04 09 3B FFFFFF82 18 FFFFFF84 FFFFFF80 FFFFFF80 FFFFFFC2
   00 17 04 09 3E FFFFFF82 18 FFFFFF84 FFFFFF80 FFFFFF80 FFFFFFC2 00 17 04 09 41
   FFFFFF82 18 FFFFFF84 FFFFFF80 FFFFFF80 FFFFFFC2 00 17 04 09 44 FFFFFF82 18 FFFFFF84 FFFFFF80 FFFFFF80
   FFFFFFC2 00 17 04 09 47 FFFFFF82 18 FFFFFF84 FFFFFF80 FFFFFF80 FFFFFFC2 00 17 04 09
   4A FFFFFF82 18 FFFFFF84 FFFFFF80 FFFFFF80 FFFFFFC2 00 17 04 09 4D FFFFFF82 18 FFFFFF84 FFFFFF80
   FFFFFF80 FFFFFFC2 00 17 04 09 50 FFFFFF82 18 FFFFFF84 FFFFFF80 FFFFFF80 FFFFFFC2 00 17 04
   09 53 FFFFFF82 18 FFFFFF84 FFFFFF80 FFFFFF80 FFFFFFC2 00 17 04 09 56 FFFFFF82 18 FFFFFF84
   FFFFFF80 FFFFFF80 FFFFFFC2 00 17 04 09 59 FFFFFF82 18 FFFFFF84 FFFFFF80 FFFFFF80 FFFFFFC2 00 17
   08 0B FFFFFF82 3B 66 FFFFFF81 68 FFFFFF90 FFFFFF80 FFFFFFC0 00 FFFFFF81 6F 08 09 FFFFFF82
   3C 00 FFFFFF91 FFFFFF80 FFFFFF84 00 FFFFFF82 3D 01 0E 63 6F 70 79 24 64
   65 66 61 75 6C 74 24 32 15 2C FFFFFF82 3E FFFFFF82 3F FFFFFF82 40
   FFFFFF82 41 FFFFFF82 42 FFFFFF82 43 FFFFFF82 44 FFFFFF82 45 FFFFFF82 46 FFFFFF82 47 FFFFFF82 48
   FFFFFF82 49 FFFFFF82 4A FFFFFF82 4B FFFFFF82 4C FFFFFF82 4D FFFFFF82 4E FFFFFF82 4F FFFFFF82 50
   FFFFFF82 51 FFFFFF82 52 FFFFFF82 53 2A 03 1E FFFFFF82 1C 04 09 16 FFFFFF82 3B
   FFFFFF84 FFFFFF80 FFFFFF80 FFFFFFC2 00 17 04 09 20 FFFFFF82 3B FFFFFF84 FFFFFF80 FFFFFF80 FFFFFFC2 00
   17 04 09 23 FFFFFF82 3B FFFFFF84 FFFFFF80 FFFFFF80 FFFFFFC2 00 17 04 09 26 FFFFFF82
   3B FFFFFF84 FFFFFF80 FFFFFF80 FFFFFFC2 00 17 04 09 29 FFFFFF82 3B FFFFFF84 FFFFFF80 FFFFFF80 FFFFFFC2
   00 17 04 09 2C FFFFFF82 3B FFFFFF84 FFFFFF80 FFFFFF80 FFFFFFC2 00 17 04 09 2F
   FFFFFF82 3B FFFFFF84 FFFFFF80 FFFFFF80 FFFFFFC2 00 17 04 09 32 FFFFFF82 3B FFFFFF84 FFFFFF80 FFFFFF80
   FFFFFFC2 00 17 04 09 35 FFFFFF82 3B FFFFFF84 FFFFFF80 FFFFFF80 FFFFFFC2 00 17 04 09
   38 FFFFFF82 3B FFFFFF84 FFFFFF80 FFFFFF80 FFFFFFC2 00 17 04 09 3B FFFFFF82 3B FFFFFF84 FFFFFF80
   FFFFFF80 FFFFFFC2 00 17 04 09 3E FFFFFF82 3B FFFFFF84 FFFFFF80 FFFFFF80 FFFFFFC2 00 17 04
   09 41 FFFFFF82 3B FFFFFF84 FFFFFF80 FFFFFF80 FFFFFFC2 00 17 04 09 44 FFFFFF82 3B FFFFFF84
   FFFFFF80 FFFFFF80 FFFFFFC2 00 17 04 09 47 FFFFFF82 3B FFFFFF84 FFFFFF80 FFFFFF80 FFFFFFC2 00 17
   04 09 4A FFFFFF82 3B FFFFFF84 FFFFFF80 FFFFFF80 FFFFFFC2 00 17 04 09 4D FFFFFF82 3B
   FFFFFF84 FFFFFF80 FFFFFF80 FFFFFFC2 00 17 04 09 50 FFFFFF82 3B FFFFFF84 FFFFFF80 FFFFFF80 FFFFFFC2 00
   17 04 09 53 FFFFFF82 3B FFFFFF84 FFFFFF80 FFFFFF80 FFFFFFC2 00 17 04 09 56 FFFFFF82
   3B FFFFFF84 FFFFFF80 FFFFFF80 FFFFFFC2 00 17 04 09 59 FFFFFF82 3B FFFFFF84 FFFFFF80 FFFFFF80 FFFFFFC2
   00 17 08 0B FFFFFF82 55 6B FFFFFF81 68 FFFFFF90 FFFFFF80 FFFFFFC0 00 FFFFFF81 71 08
   09 FFFFFF82 56 00 FFFFFF91 FFFFFF80 FFFFFF84 00 FFFFFF82 57 01 0E 63 6F 70 79
   24 64 65 66 61 75 6C 74 24 33 15 2C FFFFFF82 58 FFFFFF82 59
   FFFFFF82 5A FFFFFF82 5B FFFFFF82 5C FFFFFF82 5D FFFFFF82 5E FFFFFF82 5F FFFFFF82 60 FFFFFF82 61
   FFFFFF82 62 FFFFFF82 63 FFFFFF82 64 FFFFFF82 65 FFFFFF82 66 FFFFFF82 67 FFFFFF82 68 FFFFFF82 69
   FFFFFF82 6A FFFFFF82 6B FFFFFF82 6C FFFFFF82 6D 2A 03 21 FFFFFF82 1C 04 09 16
   FFFFFF82 55 FFFFFF84 FFFFFF80 FFFFFF80 FFFFFFC2 00 17 04 09 20 FFFFFF82 55 FFFFFF84 FFFFFF80 FFFFFF80
   FFFFFFC2 00 17 04 09 23 FFFFFF82 55 FFFFFF84 FFFFFF80 FFFFFF80 FFFFFFC2 00 17 04 09
   26 FFFFFF82 55 FFFFFF84 FFFFFF80 FFFFFF80 FFFFFFC2 00 17 04 09 29 FFFFFF82 55 FFFFFF84 FFFFFF80
   FFFFFF80 FFFFFFC2 00 17 04 09 2C FFFFFF82 55 FFFFFF84 FFFFFF80 FFFFFF80 FFFFFFC2 00 17 04
   09 2F FFFFFF82 55 FFFFFF84 FFFFFF80 FFFFFF80 FFFFFFC2 00 17 04 09 32 FFFFFF82 55 FFFFFF84
   FFFFFF80 FFFFFF80 FFFFFFC2 00 17 04 09 35 FFFFFF82 55 FFFFFF84 FFFFFF80 FFFFFF80 FFFFFFC2 00 17
   04 09 38 FFFFFF82 55 FFFFFF84 FFFFFF80 FFFFFF80 FFFFFFC2 00 17 04 09 3B FFFFFF82 55
   FFFFFF84 FFFFFF80 FFFFFF80 FFFFFFC2 00 17 04 09 3E FFFFFF82 55 FFFFFF84 FFFFFF80 FFFFFF80 FFFFFFC2 00
   17 04 09 41 FFFFFF82 55 FFFFFF84 FFFFFF80 FFFFFF80 FFFFFFC2 00 17 04 09 44 FFFFFF82
   55 FFFFFF84 FFFFFF80 FFFFFF80 FFFFFFC2 00 17 04 09 47 FFFFFF82 55 FFFFFF84 FFFFFF80 FFFFFF80 FFFFFFC2
   00 17 04 09 4A FFFFFF82 55 FFFFFF84 FFFFFF80 FFFFFF80 FFFFFFC2 00 17 04 09 4D
   FFFFFF82 55 FFFFFF84 FFFFFF80 FFFFFF80 FFFFFFC2 00 17 04 09 50 FFFFFF82 55 FFFFFF84 FFFFFF80 FFFFFF80
   FFFFFFC2 00 17 04 09 53 FFFFFF82 55 FFFFFF84 FFFFFF80 FFFFFF80 FFFFFFC2 00 17 04 09
   56 FFFFFF82 55 FFFFFF84 FFFFFF80 FFFFFF80 FFFFFFC2 00 17 04 09 59 FFFFFF82 55 FFFFFF84 FFFFFF80
   FFFFFF80 FFFFFFC2 00 17 08 0B FFFFFF82 6F 70 FFFFFF81 68 FFFFFF90 FFFFFF80 FFFFFFC0 00 FFFFFF81
   73 08 09 FFFFFF82 70 00 FFFFFF91 FFFFFF80 FFFFFF84 00 FFFFFF82 71 01 0E 63 6F
   70 79 24 64 65 66 61 75 6C 74 24 34 15 2C FFFFFF82 72
   FFFFFF82 73 FFFFFF82 74 FFFFFF82 75 FFFFFF82 76 FFFFFF82 77 FFFFFF82 78 FFFFFF82 79 FFFFFF82 7A
   FFFFFF82 7B FFFFFF82 7C FFFFFF82 7D FFFFFF82 7E FFFFFF82 7F FFFFFF83 00 FFFFFF83 01 FFFFFF83 02
   FFFFFF83 03 FFFFFF83 04 FFFFFF83 05 FFFFFF83 06 FFFFFF83 07 2A 03 24 FFFFFF82 1C 04
   09 16 FFFFFF82 6F FFFFFF84 FFFFFF80 FFFFFF80 FFFFFFC2 00 17 04 09 20 FFFFFF82 6F FFFFFF84
   FFFFFF80 FFFFFF80 FFFFFFC2 00 17 04 09 23 FFFFFF82 6F FFFFFF84 FFFFFF80 FFFFFF80 FFFFFFC2 00 17
   04 09 26 FFFFFF82 6F FFFFFF84 FFFFFF80 FFFFFF80 FFFFFFC2 00 17 04 09 29 FFFFFF82 6F
   FFFFFF84 FFFFFF80 FFFFFF80 FFFFFFC2 00 17 04 09 2C FFFFFF82 6F FFFFFF84 FFFFFF80 FFFFFF80 FFFFFFC2 00
   17 04 09 2F FFFFFF82 6F FFFFFF84 FFFFFF80 FFFFFF80 FFFFFFC2 00 17 04 09 32 FFFFFF82
   6F FFFFFF84 FFFFFF80 FFFFFF80 FFFFFFC2 00 17 04 09 35 FFFFFF82 6F FFFFFF84 FFFFFF80 FFFFFF80 FFFFFFC2
   00 17 04 09 38 FFFFFF82 6F FFFFFF84 FFFFFF80 FFFFFF80 FFFFFFC2 00 17 04 09 3B
   FFFFFF82 6F FFFFFF84 FFFFFF80 FFFFFF80 FFFFFFC2 00 17 04 09 3E FFFFFF82 6F FFFFFF84 FFFFFF80 FFFFFF80
   FFFFFFC2 00 17 04 09 41 FFFFFF82 6F FFFFFF84 FFFFFF80 FFFFFF80 FFFFFFC2 00 17 04 09
   44 FFFFFF82 6F FFFFFF84 FFFFFF80 FFFFFF80 FFFFFFC2 00 17 04 09 47 FFFFFF82 6F FFFFFF84 FFFFFF80
   FFFFFF80 FFFFFFC2 00 17 04 09 4A FFFFFF82 6F FFFFFF84 FFFFFF80 FFFFFF80 FFFFFFC2 00 17 04
   09 4D FFFFFF82 6F FFFFFF84 FFFFFF80 FFFFFF80 FFFFFFC2 00 17 04 09 50 FFFFFF82 6F FFFFFF84
   FFFFFF80 FFFFFF80 FFFFFFC2 00 17 04 09 53 FFFFFF82 6F FFFFFF84 FFFFFF80 FFFFFF80 FFFFFFC2 00 17
   04 09 56 FFFFFF82 6F FFFFFF84 FFFFFF80 FFFFFF80 FFFFFFC2 00 17 04 09 59 FFFFFF82 6F
   FFFFFF84 FFFFFF80 FFFFFF80 FFFFFFC2 00 17 08 0B FFFFFF83 09 75 FFFFFF81 68 FFFFFF90 FFFFFF80 FFFFFFC0
   00 FFFFFF81 75 08 09 FFFFFF83 0A 00 FFFFFF91 FFFFFF80 FFFFFF84 00 FFFFFF83 0B 01 0E
   63 6F 70 79 24 64 65 66 61 75 6C 74 24 35 15 2C
   FFFFFF83 0C FFFFFF83 0D FFFFFF83 0E FFFFFF83 0F FFFFFF83 10 FFFFFF83 11 FFFFFF83 12 FFFFFF83 13
   FFFFFF83 14 FFFFFF83 15 FFFFFF83 16 FFFFFF83 17 FFFFFF83 18 FFFFFF83 19 FFFFFF83 1A FFFFFF83 1B
   FFFFFF83 1C FFFFFF83 1D FFFFFF83 1E FFFFFF83 1F FFFFFF83 20 FFFFFF83 21 2A 03 27 FFFFFF82
   1C 04 09 16 FFFFFF83 09 FFFFFF84 FFFFFF80 FFFFFF80 FFFFFFC2 00 17 04 09 20 FFFFFF83
   09 FFFFFF84 FFFFFF80 FFFFFF80 FFFFFFC2 00 17 04 09 23 FFFFFF83 09 FFFFFF84 FFFFFF80 FFFFFF80 FFFFFFC2
   00 17 04 09 26 FFFFFF83 09 FFFFFF84 FFFFFF80 FFFFFF80 FFFFFFC2 00 17 04 09 29
   FFFFFF83 09 FFFFFF84 FFFFFF80 FFFFFF80 FFFFFFC2 00 17 04 09 2C FFFFFF83 09 FFFFFF84 FFFFFF80 FFFFFF80
   FFFFFFC2 00 17 04 09 2F FFFFFF83 09 FFFFFF84 FFFFFF80 FFFFFF80 FFFFFFC2 00 17 04 09
   32 FFFFFF83 09 FFFFFF84 FFFFFF80 FFFFFF80 FFFFFFC2 00 17 04 09 35 FFFFFF83 09 FFFFFF84 FFFFFF80
   FFFFFF80 FFFFFFC2 00 17 04 09 38 FFFFFF83 09 FFFFFF84 FFFFFF80 FFFFFF80 FFFFFFC2 00 17 04
   09 3B FFFFFF83 09 FFFFFF84 FFFFFF80 FFFFFF80 FFFFFFC2 00 17 04 09 3E FFFFFF83 09 FFFFFF84
   FFFFFF80 FFFFFF80 FFFFFFC2 00 17 04 09 41 FFFFFF83 09 FFFFFF84 FFFFFF80 FFFFFF80 FFFFFFC2 00 17
   04 09 44 FFFFFF83 09 FFFFFF84 FFFFFF80 FFFFFF80 FFFFFFC2 00 17 04 09 47 FFFFFF83 09
   FFFFFF84 FFFFFF80 FFFFFF80 FFFFFFC2 00 17 04 09 4A FFFFFF83 09 FFFFFF84 FFFFFF80 FFFFFF80 FFFFFFC2 00
   17 04 09 4D FFFFFF83 09 FFFFFF84 FFFFFF80 FFFFFF80 FFFFFFC2 00 17 04 09 50 FFFFFF83
   09 FFFFFF84 FFFFFF80 FFFFFF80 FFFFFFC2 00 17 04 09 53 FFFFFF83 09 FFFFFF84 FFFFFF80 FFFFFF80 FFFFFFC2
   00 17 04 09 56 FFFFFF83 09 FFFFFF84 FFFFFF80 FFFFFF80 FFFFFFC2 00 17 04 09 59
   FFFFFF83 09 FFFFFF84 FFFFFF80 FFFFFF80 FFFFFFC2 00 17 08 0B FFFFFF83 23 7A FFFFFF81 68 FFFFFF90
   FFFFFF80 FFFFFFC0 00 FFFFFF81 77 08 09 FFFFFF83 24 00 FFFFFF91 FFFFFF80 FFFFFF84 00 FFFFFF83 25
   01 0E 63 6F 70 79 24 64 65 66 61 75 6C 74 24 36
   15 2C FFFFFF83 26 FFFFFF83 27 FFFFFF83 28 FFFFFF83 29 FFFFFF83 2A FFFFFF83 2B FFFFFF83 2C
   FFFFFF83 2D FFFFFF83 2E FFFFFF83 2F FFFFFF83 30 FFFFFF83 31 FFFFFF83 32 FFFFFF83 33 FFFFFF83 34
   FFFFFF83 35 FFFFFF83 36 FFFFFF83 37 FFFFFF83 38 FFFFFF83 39 FFFFFF83 3A FFFFFF83 3B 2A 03
   2A FFFFFF82 1C 04 09 16 FFFFFF83 23 FFFFFF84 FFFFFF80 FFFFFF80 FFFFFFC2 00 17 04 09
   20 FFFFFF83 23 FFFFFF84 FFFFFF80 FFFFFF80 FFFFFFC2 00 17 04 09 23 FFFFFF83 23 FFFFFF84 FFFFFF80
   FFFFFF80 FFFFFFC2 00 17 04 09 26 FFFFFF83 23 FFFFFF84 FFFFFF80 FFFFFF80 FFFFFFC2 00 17 04
   09 29 FFFFFF83 23 FFFFFF84 FFFFFF80 FFFFFF80 FFFFFFC2 00 17 04 09 2C FFFFFF83 23 FFFFFF84
   FFFFFF80 FFFFFF80 FFFFFFC2 00 17 04 09 2F FFFFFF83 23 FFFFFF84 FFFFFF80 FFFFFF80 FFFFFFC2 00 17
   04 09 32 FFFFFF83 23 FFFFFF84 FFFFFF80 FFFFFF80 FFFFFFC2 00 17 04 09 35 FFFFFF83 23
   FFFFFF84 FFFFFF80 FFFFFF80 FFFFFFC2 00 17 04 09 38 FFFFFF83 23 FFFFFF84 FFFFFF80 FFFFFF80 FFFFFFC2 00
   17 04 09 3B FFFFFF83 23 FFFFFF84 FFFFFF80 FFFFFF80 FFFFFFC2 00 17 04 09 3E FFFFFF83
   23 FFFFFF84 FFFFFF80 FFFFFF80 FFFFFFC2 00 17 04 09 41 FFFFFF83 23 FFFFFF84 FFFFFF80 FFFFFF80 FFFFFFC2
   00 17 04 09 44 FFFFFF83 23 FFFFFF84 FFFFFF80 FFFFFF80 FFFFFFC2 00 17 04 09 47
   FFFFFF83 23 FFFFFF84 FFFFFF80 FFFFFF80 FFFFFFC2 00 17 04 09 4A FFFFFF83 23 FFFFFF84 FFFFFF80 FFFFFF80
   FFFFFFC2 00 17 04 09 4D FFFFFF83 23 FFFFFF84 FFFFFF80 FFFFFF80 FFFFFFC2 00 17 04 09
   50 FFFFFF83 23 FFFFFF84 FFFFFF80 FFFFFF80 FFFFFFC2 00 17 04 09 53 FFFFFF83 23 FFFFFF84 FFFFFF80
   FFFFFF80 FFFFFFC2 00 17 04 09 56 FFFFFF83 23 FFFFFF84 FFFFFF80 FFFFFF80 FFFFFFC2 00 17 04
   09 59 FFFFFF83 23 FFFFFF84 FFFFFF80 FFFFFF80 FFFFFFC2 00 17 08 0B FFFFFF83 3D 7F FFFFFF81
   68 FFFFFF90 FFFFFF80 FFFFFFC0 00 FFFFFF81 79 08 09 FFFFFF83 3E 00 FFFFFF91 FFFFFF80 FFFFFF84 00
   FFFFFF83 3F 01 0E 63 6F 70 79 24 64 65 66 61 75 6C 74
   24 37 15 2C FFFFFF83 40 FFFFFF83 41 FFFFFF83 42 FFFFFF83 43 FFFFFF83 44 FFFFFF83 45
   FFFFFF83 46 FFFFFF83 47 FFFFFF83 48 FFFFFF83 49 FFFFFF83 4A FFFFFF83 4B FFFFFF83 4C FFFFFF83 4D
   FFFFFF83 4E FFFFFF83 4F FFFFFF83 50 FFFFFF83 51 FFFFFF83 52 FFFFFF83 53 FFFFFF83 54 FFFFFF83 55
   2A 03 2D FFFFFF82 1C 04 09 16 FFFFFF83 3D FFFFFF84 FFFFFF80 FFFFFF80 FFFFFFC2 00 17
   04 09 20 FFFFFF83 3D FFFFFF84 FFFFFF80 FFFFFF80 FFFFFFC2 00 17 04 09 23 FFFFFF83 3D
   FFFFFF84 FFFFFF80 FFFFFF80 FFFFFFC2 00 17 04 09 26 FFFFFF83 3D FFFFFF84 FFFFFF80 FFFFFF80 FFFFFFC2 00
   17 04 09 29 FFFFFF83 3D FFFFFF84 FFFFFF80 FFFFFF80 FFFFFFC2 00 17 04 09 2C FFFFFF83
   3D FFFFFF84 FFFFFF80 FFFFFF80 FFFFFFC2 00 17 04 09 2F FFFFFF83 3D FFFFFF84 FFFFFF80 FFFFFF80 FFFFFFC2
   00 17 04 09 32 FFFFFF83 3D FFFFFF84 FFFFFF80 FFFFFF80 FFFFFFC2 00 17 04 09 35
   FFFFFF83 3D FFFFFF84 FFFFFF80 FFFFFF80 FFFFFFC2 00 17 04 09 38 FFFFFF83 3D FFFFFF84 FFFFFF80 FFFFFF80
   FFFFFFC2 00 17 04 09 3B FFFFFF83 3D FFFFFF84 FFFFFF80 FFFFFF80 FFFFFFC2 00 17 04 09
   3E FFFFFF83 3D FFFFFF84 FFFFFF80 FFFFFF80 FFFFFFC2 00 17 04 09 41 FFFFFF83 3D FFFFFF84 FFFFFF80
   FFFFFF80 FFFFFFC2 00 17 04 09 44 FFFFFF83 3D FFFFFF84 FFFFFF80 FFFFFF80 FFFFFFC2 00 17 04
   09 47 FFFFFF83 3D FFFFFF84 FFFFFF80 FFFFFF80 FFFFFFC2 00 17 04 09 4A FFFFFF83 3D FFFFFF84
   FFFFFF80 FFFFFF80 FFFFFFC2 00 17 04 09 4D FFFFFF83 3D FFFFFF84 FFFFFF80 FFFFFF80 FFFFFFC2 00 17
   04 09 50 FFFFFF83 3D FFFFFF84 FFFFFF80 FFFFFF80 FFFFFFC2 00 17 04 09 53 FFFFFF83 3D
   FFFFFF84 FFFFFF80 FFFFFF80 FFFFFFC2 00 17 04 09 56 FFFFFF83 3D FFFFFF84 FFFFFF80 FFFFFF80 FFFFFFC2 00
   17 04 09 59 FFFFFF83 3D FFFFFF84 FFFFFF80 FFFFFF80 FFFFFFC2 00 17 08 0C FFFFFF83 57
   FFFFFF81 04 FFFFFF81 68 FFFFFF90 FFFFFF80 FFFFFFC0 00 FFFFFF81 7B 08 09 FFFFFF83 58 00 FFFFFF91
   FFFFFF80 FFFFFF84 00 FFFFFF83 59 01 0E 63 6F 70 79 24 64 65 66 61
   75 6C 74 24 38 15 2C FFFFFF83 5A FFFFFF83 5B FFFFFF83 5C FFFFFF83 5D FFFFFF83
   5E FFFFFF83 5F FFFFFF83 60 FFFFFF83 61 FFFFFF83 62 FFFFFF83 63 FFFFFF83 64 FFFFFF83 65 FFFFFF83
   66 FFFFFF83 67 FFFFFF83 68 FFFFFF83 69 FFFFFF83 6A FFFFFF83 6B FFFFFF83 6C FFFFFF83 6D FFFFFF83
   6E FFFFFF83 6F 2A 03 30 FFFFFF82 1C 04 09 16 FFFFFF83 57 FFFFFF84 FFFFFF80 FFFFFF80
   FFFFFFC2 00 17 04 09 20 FFFFFF83 57 FFFFFF84 FFFFFF80 FFFFFF80 FFFFFFC2 00 17 04 09
   23 FFFFFF83 57 FFFFFF84 FFFFFF80 FFFFFF80 FFFFFFC2 00 17 04 09 26 FFFFFF83 57 FFFFFF84 FFFFFF80
   FFFFFF80 FFFFFFC2 00 17 04 09 29 FFFFFF83 57 FFFFFF84 FFFFFF80 FFFFFF80 FFFFFFC2 00 17 04
   09 2C FFFFFF83 57 FFFFFF84 FFFFFF80 FFFFFF80 FFFFFFC2 00 17 04 09 2F FFFFFF83 57 FFFFFF84
   FFFFFF80 FFFFFF80 FFFFFFC2 00 17 04 09 32 FFFFFF83 57 FFFFFF84 FFFFFF80 FFFFFF80 FFFFFFC2 00 17
   04 09 35 FFFFFF83 57 FFFFFF84 FFFFFF80 FFFFFF80 FFFFFFC2 00 17 04 09 38 FFFFFF83 57
   FFFFFF84 FFFFFF80 FFFFFF80 FFFFFFC2 00 17 04 09 3B FFFFFF83 57 FFFFFF84 FFFFFF80 FFFFFF80 FFFFFFC2 00
   17 04 09 3E FFFFFF83 57 FFFFFF84 FFFFFF80 FFFFFF80 FFFFFFC2 00 17 04 09 41 FFFFFF83
   57 FFFFFF84 FFFFFF80 FFFFFF80 FFFFFFC2 00 17 04 09 44 FFFFFF83 57 FFFFFF84 FFFFFF80 FFFFFF80 FFFFFFC2
   00 17 04 09 47 FFFFFF83 57 FFFFFF84 FFFFFF80 FFFFFF80 FFFFFFC2 00 17 04 09 4A
   FFFFFF83 57 FFFFFF84 FFFFFF80 FFFFFF80 FFFFFFC2 00 17 04 09 4D FFFFFF83 57 FFFFFF84 FFFFFF80 FFFFFF80
   FFFFFFC2 00 17 04 09 50 FFFFFF83 57 FFFFFF84 FFFFFF80 FFFFFF80 FFFFFFC2 00 17 04 09
   53 FFFFFF83 57 FFFFFF84 FFFFFF80 FFFFFF80 FFFFFFC2 00 17 04 09 56 FFFFFF83 57 FFFFFF84 FFFFFF80
   FFFFFF80 FFFFFFC2 00 17 04 09 59 FFFFFF83 57 FFFFFF84 FFFFFF80 FFFFFF80 FFFFFFC2 00 17 08
   0C FFFFFF83 71 FFFFFF81 09 FFFFFF81 68 FFFFFF90 FFFFFF80 FFFFFFC0 00 FFFFFF81 7D 08 09 FFFFFF83
   72 00 FFFFFF91 FFFFFF80 FFFFFF84 00 FFFFFF83 73 01 0E 63 6F 70 79 24 64
   65 66 61 75 6C 74 24 39 15 2C FFFFFF83 74 FFFFFF83 75 FFFFFF83 76
   FFFFFF83 77 FFFFFF83 78 FFFFFF83 79 FFFFFF83 7A FFFFFF83 7B FFFFFF83 7C FFFFFF83 7D FFFFFF83 7E
   FFFFFF83 7F FFFFFF84 00 FFFFFF84 01 FFFFFF84 02 FFFFFF84 03 FFFFFF84 04 FFFFFF84 05 FFFFFF84 06
   FFFFFF84 07 FFFFFF84 08 FFFFFF84 09 2A 03 33 FFFFFF82 1C 04 09 16 FFFFFF83 71
   FFFFFF84 FFFFFF80 FFFFFF80 FFFFFFC2 00 17 04 09 20 FFFFFF83 71 FFFFFF84 FFFFFF80 FFFFFF80 FFFFFFC2 00
   17 04 09 23 FFFFFF83 71 FFFFFF84 FFFFFF80 FFFFFF80 FFFFFFC2 00 17 04 09 26 FFFFFF83
   71 FFFFFF84 FFFFFF80 FFFFFF80 FFFFFFC2 00 17 04 09 29 FFFFFF83 71 FFFFFF84 FFFFFF80 FFFFFF80 FFFFFFC2
   00 17 04 09 2C FFFFFF83 71 FFFFFF84 FFFFFF80 FFFFFF80 FFFFFFC2 00 17 04 09 2F
   FFFFFF83 71 FFFFFF84 FFFFFF80 FFFFFF80 FFFFFFC2 00 17 04 09 32 FFFFFF83 71 FFFFFF84 FFFFFF80 FFFFFF80
   FFFFFFC2 00 17 04 09 35 FFFFFF83 71 FFFFFF84 FFFFFF80 FFFFFF80 FFFFFFC2 00 17 04 09
   38 FFFFFF83 71 FFFFFF84 FFFFFF80 FFFFFF80 FFFFFFC2 00 17 04 09 3B FFFFFF83 71 FFFFFF84 FFFFFF80
   FFFFFF80 FFFFFFC2 00 17 04 09 3E FFFFFF83 71 FFFFFF84 FFFFFF80 FFFFFF80 FFFFFFC2 00 17 04
   09 41 FFFFFF83 71 FFFFFF84 FFFFFF80 FFFFFF80 FFFFFFC2 00 17 04 09 44 FFFFFF83 71 FFFFFF84
   FFFFFF80 FFFFFF80 FFFFFFC2 00 17 04 09 47 FFFFFF83 71 FFFFFF84 FFFFFF80 FFFFFF80 FFFFFFC2 00 17
   04 09 4A FFFFFF83 71 FFFFFF84 FFFFFF80 FFFFFF80 FFFFFFC2 00 17 04 09 4D FFFFFF83 71
   FFFFFF84 FFFFFF80 FFFFFF80 FFFFFFC2 00 17 04 09 50 FFFFFF83 71 FFFFFF84 FFFFFF80 FFFFFF80 FFFFFFC2 00
   17 04 09 53 FFFFFF83 71 FFFFFF84 FFFFFF80 FFFFFF80 FFFFFFC2 00 17 04 09 56 FFFFFF83
   71 FFFFFF84 FFFFFF80 FFFFFF80 FFFFFFC2 00 17 04 09 59 FFFFFF83 71 FFFFFF84 FFFFFF80 FFFFFF80 FFFFFFC2
   00 17 08 0C FFFFFF84 0B FFFFFF81 0E FFFFFF81 68 FFFFFF90 FFFFFF80 FFFFFFC0 00 FFFFFF81 7F
   08 09 FFFFFF84 0C 00 FFFFFF91 FFFFFF80 FFFFFF84 00 FFFFFF84 0D 01 0F 63 6F 70
   79 24 64 65 66 61 75 6C 74 24 31 30 15 2C FFFFFF84 0E
   FFFFFF84 0F FFFFFF84 10 FFFFFF84 11 FFFFFF84 12 FFFFFF84 13 FFFFFF84 14 FFFFFF84 15 FFFFFF84 16
   FFFFFF84 17 FFFFFF84 18 FFFFFF84 19 FFFFFF84 1A FFFFFF84 1B FFFFFF84 1C FFFFFF84 1D FFFFFF84 1E
   FFFFFF84 1F FFFFFF84 20 FFFFFF84 21 FFFFFF84 22 FFFFFF84 23 2A 03 36 FFFFFF82 1C 04
   09 16 FFFFFF84 0B FFFFFF84 FFFFFF80 FFFFFF80 FFFFFFC2 00 17 04 09 20 FFFFFF84 0B FFFFFF84
   FFFFFF80 FFFFFF80 FFFFFFC2 00 17 04 09 23 FFFFFF84 0B FFFFFF84 FFFFFF80 FFFFFF80 FFFFFFC2 00 17
   04 09 26 FFFFFF84 0B FFFFFF84 FFFFFF80 FFFFFF80 FFFFFFC2 00 17 04 09 29 FFFFFF84 0B
   FFFFFF84 FFFFFF80 FFFFFF80 FFFFFFC2 00 17 04 09 2C FFFFFF84 0B FFFFFF84 FFFFFF80 FFFFFF80 FFFFFFC2 00
   17 04 09 2F FFFFFF84 0B FFFFFF84 FFFFFF80 FFFFFF80 FFFFFFC2 00 17 04 09 32 FFFFFF84
   0B FFFFFF84 FFFFFF80 FFFFFF80 FFFFFFC2 00 17 04 09 35 FFFFFF84 0B FFFFFF84 FFFFFF80 FFFFFF80 FFFFFFC2
   00 17 04 09 38 FFFFFF84 0B FFFFFF84 FFFFFF80 FFFFFF80 FFFFFFC2 00 17 04 09 3B
   FFFFFF84 0B FFFFFF84 FFFFFF80 FFFFFF80 FFFFFFC2 00 17 04 09 3E FFFFFF84 0B FFFFFF84 FFFFFF80 FFFFFF80
   FFFFFFC2 00 17 04 09 41 FFFFFF84 0B FFFFFF84 FFFFFF80 FFFFFF80 FFFFFFC2 00 17 04 09
   44 FFFFFF84 0B FFFFFF84 FFFFFF80 FFFFFF80 FFFFFFC2 00 17 04 09 47 FFFFFF84 0B FFFFFF84 FFFFFF80
   FFFFFF80 FFFFFFC2 00 17 04 09 4A FFFFFF84 0B FFFFFF84 FFFFFF80 FFFFFF80 FFFFFFC2 00 17 04
   09 4D FFFFFF84 0B FFFFFF84 FFFFFF80 FFFFFF80 FFFFFFC2 00 17 04 09 50 FFFFFF84 0B FFFFFF84
   FFFFFF80 FFFFFF80 FFFFFFC2 00 17 04 09 53 FFFFFF84 0B FFFFFF84 FFFFFF80 FFFFFF80 FFFFFFC2 00 17
   04 09 56 FFFFFF84 0B FFFFFF84 FFFFFF80 FFFFFF80 FFFFFFC2 00 17 04 09 59 FFFFFF84 0B
   FFFFFF84 FFFFFF80 FFFFFF80 FFFFFFC2 00 17 08 0C FFFFFF84 25 FFFFFF81 13 FFFFFF81 68 FFFFFF90 FFFFFF80
   FFFFFFC0 00 FFFFFF82 01 08 09 FFFFFF84 26 00 FFFFFF91 FFFFFF80 FFFFFF84 00 FFFFFF84 27 01
   0F 63 6F 70 79 24 64 65 66 61 75 6C 74 24 31 31
   15 2C FFFFFF84 28 FFFFFF84 29 FFFFFF84 2A FFFFFF84 2B FFFFFF84 2C FFFFFF84 2D FFFFFF84 2E
   FFFFFF84 2F FFFFFF84 30 FFFFFF84 31 FFFFFF84 32 FFFFFF84 33 FFFFFF84 34 FFFFFF84 35 FFFFFF84 36
   FFFFFF84 37 FFFFFF84 38 FFFFFF84 39 FFFFFF84 3A FFFFFF84 3B FFFFFF84 3C FFFFFF84 3D 2A 03
   39 FFFFFF82 1C 04 09 16 FFFFFF84 25 FFFFFF84 FFFFFF80 FFFFFF80 FFFFFFC2 00 17 04 09
   20 FFFFFF84 25 FFFFFF84 FFFFFF80 FFFFFF80 FFFFFFC2 00 17 04 09 23 FFFFFF84 25 FFFFFF84 FFFFFF80
   FFFFFF80 FFFFFFC2 00 17 04 09 26 FFFFFF84 25 FFFFFF84 FFFFFF80 FFFFFF80 FFFFFFC2 00 17 04
   09 29 FFFFFF84 25 FFFFFF84 FFFFFF80 FFFFFF80 FFFFFFC2 00 17 04 09 2C FFFFFF84 25 FFFFFF84
   FFFFFF80 FFFFFF80 FFFFFFC2 00 17 04 09 2F FFFFFF84 25 FFFFFF84 FFFFFF80 FFFFFF80 FFFFFFC2 00 17
   04 09 32 FFFFFF84 25 FFFFFF84 FFFFFF80 FFFFFF80 FFFFFFC2 00 17 04 09 35 FFFFFF84 25
   FFFFFF84 FFFFFF80 FFFFFF80 FFFFFFC2 00 17 04 09 38 FFFFFF84 25 FFFFFF84 FFFFFF80 FFFFFF80 FFFFFFC2 00
   17 04 09 3B FFFFFF84 25 FFFFFF84 FFFFFF80 FFFFFF80 FFFFFFC2 00 17 04 09 3E FFFFFF84
   25 FFFFFF84 FFFFFF80 FFFFFF80 FFFFFFC2 00 17 04 09 41 FFFFFF84 25 FFFFFF84 FFFFFF80 FFFFFF80 FFFFFFC2
   00 17 04 09 44 FFFFFF84 25 FFFFFF84 FFFFFF80 FFFFFF80 FFFFFFC2 00 17 04 09 47
   FFFFFF84 25 FFFFFF84 FFFFFF80 FFFFFF80 FFFFFFC2 00 17 04 09 4A FFFFFF84 25 FFFFFF84 FFFFFF80 FFFFFF80
   FFFFFFC2 00 17 04 09 4D FFFFFF84 25 FFFFFF84 FFFFFF80 FFFFFF80 FFFFFFC2 00 17 04 09
   50 FFFFFF84 25 FFFFFF84 FFFFFF80 FFFFFF80 FFFFFFC2 00 17 04 09 53 FFFFFF84 25 FFFFFF84 FFFFFF80
   FFFFFF80 FFFFFFC2 00 17 04 09 56 FFFFFF84 25 FFFFFF84 FFFFFF80 FFFFFF80 FFFFFFC2 00 17 04
   09 59 FFFFFF84 25 FFFFFF84 FFFFFF80 FFFFFF80 FFFFFFC2 00 17 08 0C FFFFFF84 3F FFFFFF81 18
   FFFFFF81 68 FFFFFF90 FFFFFF80 FFFFFFC0 00 FFFFFF82 03 08 09 FFFFFF84 40 00 FFFFFF91 FFFFFF80 FFFFFF84
   00 FFFFFF84 41 01 0F 63 6F 70 79 24 64 65 66 61 75 6C
   74 24 31 32 15 2C FFFFFF84 42 FFFFFF84 43 FFFFFF84 44 FFFFFF84 45 FFFFFF84 46
   FFFFFF84 47 FFFFFF84 48 FFFFFF84 49 FFFFFF84 4A FFFFFF84 4B FFFFFF84 4C FFFFFF84 4D FFFFFF84 4E
   FFFFFF84 4F FFFFFF84 50 FFFFFF84 51 FFFFFF84 52 FFFFFF84 53 FFFFFF84 54 FFFFFF84 55 FFFFFF84 56
   FFFFFF84 57 2A 03 3C FFFFFF82 1C 04 09 16 FFFFFF84 3F FFFFFF84 FFFFFF80 FFFFFF80 FFFFFFC2
   00 17 04 09 20 FFFFFF84 3F FFFFFF84 FFFFFF80 FFFFFF80 FFFFFFC2 00 17 04 09 23
   FFFFFF84 3F FFFFFF84 FFFFFF80 FFFFFF80 FFFFFFC2 00 17 04 09 26 FFFFFF84 3F FFFFFF84 FFFFFF80 FFFFFF80
   FFFFFFC2 00 17 04 09 29 FFFFFF84 3F FFFFFF84 FFFFFF80 FFFFFF80 FFFFFFC2 00 17 04 09
   2C FFFFFF84 3F FFFFFF84 FFFFFF80 FFFFFF80 FFFFFFC2 00 17 04 09 2F FFFFFF84 3F FFFFFF84 FFFFFF80
   FFFFFF80 FFFFFFC2 00 17 04 09 32 FFFFFF84 3F FFFFFF84 FFFFFF80 FFFFFF80 FFFFFFC2 00 17 04
   09 35 FFFFFF84 3F FFFFFF84 FFFFFF80 FFFFFF80 FFFFFFC2 00 17 04 09 38 FFFFFF84 3F FFFFFF84
   FFFFFF80 FFFFFF80 FFFFFFC2 00 17 04 09 3B FFFFFF84 3F FFFFFF84 FFFFFF80 FFFFFF80 FFFFFFC2 00 17
   04 09 3E FFFFFF84 3F FFFFFF84 FFFFFF80 FFFFFF80 FFFFFFC2 00 17 04 09 41 FFFFFF84 3F
   FFFFFF84 FFFFFF80 FFFFFF80 FFFFFFC2 00 17 04 09 44 FFFFFF84 3F FFFFFF84 FFFFFF80 FFFFFF80 FFFFFFC2 00
   17 04 09 47 FFFFFF84 3F FFFFFF84 FFFFFF80 FFFFFF80 FFFFFFC2 00 17 04 09 4A FFFFFF84
   3F FFFFFF84 FFFFFF80 FFFFFF80 FFFFFFC2 00 17 04 09 4D FFFFFF84 3F FFFFFF84 FFFFFF80 FFFFFF80 FFFFFFC2
   00 17 04 09 50 FFFFFF84 3F FFFFFF84 FFFFFF80 FFFFFF80 FFFFFFC2 00 17 04 09 53
   FFFFFF84 3F FFFFFF84 FFFFFF80 FFFFFF80 FFFFFFC2 00 17 04 09 56 FFFFFF84 3F FFFFFF84 FFFFFF80 FFFFFF80
   FFFFFFC2 00 17 04 09 59 FFFFFF84 3F FFFFFF84 FFFFFF80 FFFFFF80 FFFFFFC2 00 17 08 0C
   FFFFFF84 59 FFFFFF81 1D FFFFFF81 68 FFFFFF90 FFFFFF80 FFFFFFC0 00 FFFFFF82 05 08 09 FFFFFF84 5A
   00 FFFFFF91 FFFFFF80 FFFFFF84 00 FFFFFF84 5B 01 0F 63 6F 70 79 24 64 65
   66 61 75 6C 74 24 31 33 15 2C FFFFFF84 5C FFFFFF84 5D FFFFFF84 5E
   FFFFFF84 5F FFFFFF84 60 FFFFFF84 61 FFFFFF84 62 FFFFFF84 63 FFFFFF84 64 FFFFFF84 65 FFFFFF84 66
   FFFFFF84 67 FFFFFF84 68 FFFFFF84 69 FFFFFF84 6A FFFFFF84 6B FFFFFF84 6C FFFFFF84 6D FFFFFF84 6E
   FFFFFF84 6F FFFFFF84 70 FFFFFF84 71 2A 03 3F FFFFFF82 1C 04 09 16 FFFFFF84 59
   FFFFFF84 FFFFFF80 FFFFFF80 FFFFFFC2 00 17 04 09 20 FFFFFF84 59 FFFFFF84 FFFFFF80 FFFFFF80 FFFFFFC2 00
   17 04 09 23 FFFFFF84 59 FFFFFF84 FFFFFF80 FFFFFF80 FFFFFFC2 00 17 04 09 26 FFFFFF84
   59 FFFFFF84 FFFFFF80 FFFFFF80 FFFFFFC2 00 17 04 09 29 FFFFFF84 59 FFFFFF84 FFFFFF80 FFFFFF80 FFFFFFC2
   00 17 04 09 2C FFFFFF84 59 FFFFFF84 FFFFFF80 FFFFFF80 FFFFFFC2 00 17 04 09 2F
   FFFFFF84 59 FFFFFF84 FFFFFF80 FFFFFF80 FFFFFFC2 00 17 04 09 32 FFFFFF84 59 FFFFFF84 FFFFFF80 FFFFFF80
   FFFFFFC2 00 17 04 09 35 FFFFFF84 59 FFFFFF84 FFFFFF80 FFFFFF80 FFFFFFC2 00 17 04 09
   38 FFFFFF84 59 FFFFFF84 FFFFFF80 FFFFFF80 FFFFFFC2 00 17 04 09 3B FFFFFF84 59 FFFFFF84 FFFFFF80
   FFFFFF80 FFFFFFC2 00 17 04 09 3E FFFFFF84 59 FFFFFF84 FFFFFF80 FFFFFF80 FFFFFFC2 00 17 04
   09 41 FFFFFF84 59 FFFFFF84 FFFFFF80 FFFFFF80 FFFFFFC2 00 17 04 09 44 FFFFFF84 59 FFFFFF84
   FFFFFF80 FFFFFF80 FFFFFFC2 00 17 04 09 47 FFFFFF84 59 FFFFFF84 FFFFFF80 FFFFFF80 FFFFFFC2 00 17
   04 09 4A FFFFFF84 59 FFFFFF84 FFFFFF80 FFFFFF80 FFFFFFC2 00 17 04 09 4D FFFFFF84 59
   FFFFFF84 FFFFFF80 FFFFFF80 FFFFFFC2 00 17 04 09 50 FFFFFF84 59 FFFFFF84 FFFFFF80 FFFFFF80 FFFFFFC2 00
   17 04 09 53 FFFFFF84 59 FFFFFF84 FFFFFF80 FFFFFF80 FFFFFFC2 00 17 04 09 56 FFFFFF84
   59 FFFFFF84 FFFFFF80 FFFFFF80 FFFFFFC2 00 17 04 09 59 FFFFFF84 59 FFFFFF84 FFFFFF80 FFFFFF80 FFFFFFC2
   00 17 08 0C FFFFFF84 73 FFFFFF81 22 FFFFFF81 68 FFFFFF90 FFFFFF80 FFFFFFC0 00 FFFFFF82 07
   08 09 FFFFFF84 74 00 FFFFFF91 FFFFFF80 FFFFFF84 00 FFFFFF84 75 01 0F 63 6F 70
   79 24 64 65 66 61 75 6C 74 24 31 34 15 2C FFFFFF84 76
   FFFFFF84 77 FFFFFF84 78 FFFFFF84 79 FFFFFF84 7A FFFFFF84 7B FFFFFF84 7C FFFFFF84 7D FFFFFF84 7E
   FFFFFF84 7F FFFFFF85 00 FFFFFF85 01 FFFFFF85 02 FFFFFF85 03 FFFFFF85 04 FFFFFF85 05 FFFFFF85 06
   FFFFFF85 07 FFFFFF85 08 FFFFFF85 09 FFFFFF85 0A FFFFFF85 0B 2A 03 42 FFFFFF82 1C 04
   09 16 FFFFFF84 73 FFFFFF84 FFFFFF80 FFFFFF80 FFFFFFC2 00 17 04 09 20 FFFFFF84 73 FFFFFF84
   FFFFFF80 FFFFFF80 FFFFFFC2 00 17 04 09 23 FFFFFF84 73 FFFFFF84 FFFFFF80 FFFFFF80 FFFFFFC2 00 17
   04 09 26 FFFFFF84 73 FFFFFF84 FFFFFF80 FFFFFF80 FFFFFFC2 00 17 04 09 29 FFFFFF84 73
   FFFFFF84 FFFFFF80 FFFFFF80 FFFFFFC2 00 17 04 09 2C FFFFFF84 73 FFFFFF84 FFFFFF80 FFFFFF80 FFFFFFC2 00
   17 04 09 2F FFFFFF84 73 FFFFFF84 FFFFFF80 FFFFFF80 FFFFFFC2 00 17 04 09 32 FFFFFF84
   73 FFFFFF84 FFFFFF80 FFFFFF80 FFFFFFC2 00 17 04 09 35 FFFFFF84 73 FFFFFF84 FFFFFF80 FFFFFF80 FFFFFFC2
   00 17 04 09 38 FFFFFF84 73 FFFFFF84 FFFFFF80 FFFFFF80 FFFFFFC2 00 17 04 09 3B
   FFFFFF84 73 FFFFFF84 FFFFFF80 FFFFFF80 FFFFFFC2 00 17 04 09 3E FFFFFF84 73 FFFFFF84 FFFFFF80 FFFFFF80
   FFFFFFC2 00 17 04 09 41 FFFFFF84 73 FFFFFF84 FFFFFF80 FFFFFF80 FFFFFFC2 00 17 04 09
   44 FFFFFF84 73 FFFFFF84 FFFFFF80 FFFFFF80 FFFFFFC2 00 17 04 09 47 FFFFFF84 73 FFFFFF84 FFFFFF80
   FFFFFF80 FFFFFFC2 00 17 04 09 4A FFFFFF84 73 FFFFFF84 FFFFFF80 FFFFFF80 FFFFFFC2 00 17 04
   09 4D FFFFFF84 73 FFFFFF84 FFFFFF80 FFFFFF80 FFFFFFC2 00 17 04 09 50 FFFFFF84 73 FFFFFF84
   FFFFFF80 FFFFFF80 FFFFFFC2 00 17 04 09 53 FFFFFF84 73 FFFFFF84 FFFFFF80 FFFFFF80 FFFFFFC2 00 17
   04 09 56 FFFFFF84 73 FFFFFF84 FFFFFF80 FFFFFF80 FFFFFFC2 00 17 04 09 59 FFFFFF84 73
   FFFFFF84 FFFFFF80 FFFFFF80 FFFFFFC2 00 17 08 0C FFFFFF85 0D FFFFFF81 27 FFFFFF81 68 FFFFFF90 FFFFFF80
   FFFFFFC0 00 FFFFFF82 09 08 09 FFFFFF85 0E 00 FFFFFF91 FFFFFF80 FFFFFF84 00 FFFFFF85 0F 01
   0F 63 6F 70 79 24 64 65 66 61 75 6C 74 24 31 35
   15 2C FFFFFF85 10 FFFFFF85 11 FFFFFF85 12 FFFFFF85 13 FFFFFF85 14 FFFFFF85 15 FFFFFF85 16
   FFFFFF85 17 FFFFFF85 18 FFFFFF85 19 FFFFFF85 1A FFFFFF85 1B FFFFFF85 1C FFFFFF85 1D FFFFFF85 1E
   FFFFFF85 1F FFFFFF85 20 FFFFFF85 21 FFFFFF85 22 FFFFFF85 23 FFFFFF85 24 FFFFFF85 25 2A 03
   45 FFFFFF82 1C 04 09 16 FFFFFF85 0D FFFFFF84 FFFFFF80 FFFFFF80 FFFFFFC2 00 17 04 09
   20 FFFFFF85 0D FFFFFF84 FFFFFF80 FFFFFF80 FFFFFFC2 00 17 04 09 23 FFFFFF85 0D FFFFFF84 FFFFFF80
   FFFFFF80 FFFFFFC2 00 17 04 09 26 FFFFFF85 0D FFFFFF84 FFFFFF80 FFFFFF80 FFFFFFC2 00 17 04
   09 29 FFFFFF85 0D FFFFFF84 FFFFFF80 FFFFFF80 FFFFFFC2 00 17 04 09 2C FFFFFF85 0D FFFFFF84
   FFFFFF80 FFFFFF80 FFFFFFC2 00 17 04 09 2F FFFFFF85 0D FFFFFF84 FFFFFF80 FFFFFF80 FFFFFFC2 00 17
   04 09 32 FFFFFF85 0D FFFFFF84 FFFFFF80 FFFFFF80 FFFFFFC2 00 17 04 09 35 FFFFFF85 0D
   FFFFFF84 FFFFFF80 FFFFFF80 FFFFFFC2 00 17 04 09 38 FFFFFF85 0D FFFFFF84 FFFFFF80 FFFFFF80 FFFFFFC2 00
   17 04 09 3B FFFFFF85 0D FFFFFF84 FFFFFF80 FFFFFF80 FFFFFFC2 00 17 04 09 3E FFFFFF85
   0D FFFFFF84 FFFFFF80 FFFFFF80 FFFFFFC2 00 17 04 09 41 FFFFFF85 0D FFFFFF84 FFFFFF80 FFFFFF80 FFFFFFC2
   00 17 04 09 44 FFFFFF85 0D FFFFFF84 FFFFFF80 FFFFFF80 FFFFFFC2 00 17 04 09 47
   FFFFFF85 0D FFFFFF84 FFFFFF80 FFFFFF80 FFFFFFC2 00 17 04 09 4A FFFFFF85 0D FFFFFF84 FFFFFF80 FFFFFF80
   FFFFFFC2 00 17 04 09 4D FFFFFF85 0D FFFFFF84 FFFFFF80 FFFFFF80 FFFFFFC2 00 17 04 09
   50 FFFFFF85 0D FFFFFF84 FFFFFF80 FFFFFF80 FFFFFFC2 00 17 04 09 53 FFFFFF85 0D FFFFFF84 FFFFFF80
   FFFFFF80 FFFFFFC2 00 17 04 09 56 FFFFFF85 0D FFFFFF84 FFFFFF80 FFFFFF80 FFFFFFC2 00 17 04
   09 59 FFFFFF85 0D FFFFFF84 FFFFFF80 FFFFFF80 FFFFFFC2 00 17 08 0C FFFFFF85 27 FFFFFF81 2C
   FFFFFF81 68 FFFFFF90 FFFFFF80 FFFFFFC0 00 FFFFFF82 0B 08 09 FFFFFF85 28 00 FFFFFF91 FFFFFF80 FFFFFF84
   00 FFFFFF85 29 01 0F 63 6F 70 79 24 64 65 66 61 75 6C
   74 24 31 36 15 2C FFFFFF85 2A FFFFFF85 2B FFFFFF85 2C FFFFFF85 2D FFFFFF85 2E
   FFFFFF85 2F FFFFFF85 30 FFFFFF85 31 FFFFFF85 32 FFFFFF85 33 FFFFFF85 34 FFFFFF85 35 FFFFFF85 36
   FFFFFF85 37 FFFFFF85 38 FFFFFF85 39 FFFFFF85 3A FFFFFF85 3B FFFFFF85 3C FFFFFF85 3D FFFFFF85 3E
   FFFFFF85 3F 2A 03 48 FFFFFF82 1C 04 09 16 FFFFFF85 27 FFFFFF84 FFFFFF80 FFFFFF80 FFFFFFC2
   00 17 04 09 20 FFFFFF85 27 FFFFFF84 FFFFFF80 FFFFFF80 FFFFFFC2 00 17 04 09 23
   FFFFFF85 27 FFFFFF84 FFFFFF80 FFFFFF80 FFFFFFC2 00 17 04 09 26 FFFFFF85 27 FFFFFF84 FFFFFF80 FFFFFF80
   FFFFFFC2 00 17 04 09 29 FFFFFF85 27 FFFFFF84 FFFFFF80 FFFFFF80 FFFFFFC2 00 17 04 09
   2C FFFFFF85 27 FFFFFF84 FFFFFF80 FFFFFF80 FFFFFFC2 00 17 04 09 2F FFFFFF85 27 FFFFFF84 FFFFFF80
   FFFFFF80 FFFFFFC2 00 17 04 09 32 FFFFFF85 27 FFFFFF84 FFFFFF80 FFFFFF80 FFFFFFC2 00 17 04
   09 35 FFFFFF85 27 FFFFFF84 FFFFFF80 FFFFFF80 FFFFFFC2 00 17 04 09 38 FFFFFF85 27 FFFFFF84
   FFFFFF80 FFFFFF80 FFFFFFC2 00 17 04 09 3B FFFFFF85 27 FFFFFF84 FFFFFF80 FFFFFF80 FFFFFFC2 00 17
   04 09 3E FFFFFF85 27 FFFFFF84 FFFFFF80 FFFFFF80 FFFFFFC2 00 17 04 09 41 FFFFFF85 27
   FFFFFF84 FFFFFF80 FFFFFF80 FFFFFFC2 00 17 04 09 44 FFFFFF85 27 FFFFFF84 FFFFFF80 FFFFFF80 FFFFFFC2 00
   17 04 09 47 FFFFFF85 27 FFFFFF84 FFFFFF80 FFFFFF80 FFFFFFC2 00 17 04 09 4A FFFFFF85
   27 FFFFFF84 FFFFFF80 FFFFFF80 FFFFFFC2 00 17 04 09 4D FFFFFF85 27 FFFFFF84 FFFFFF80 FFFFFF80 FFFFFFC2
   00 17 04 09 50 FFFFFF85 27 FFFFFF84 FFFFFF80 FFFFFF80 FFFFFFC2 00 17 04 09 53
   FFFFFF85 27 FFFFFF84 FFFFFF80 FFFFFF80 FFFFFFC2 00 17 04 09 56 FFFFFF85 27 FFFFFF84 FFFFFF80 FFFFFF80
   FFFFFFC2 00 17 04 09 59 FFFFFF85 27 FFFFFF84 FFFFFF80 FFFFFF80 FFFFFFC2 00 17 08 0C
   FFFFFF85 41 FFFFFF81 31 FFFFFF81 68 FFFFFF90 FFFFFF80 FFFFFFC0 00 FFFFFF82 0D 08 09 FFFFFF85 42
   00 FFFFFF91 FFFFFF80 FFFFFF84 00 FFFFFF85 43 01 0F 63 6F 70 79 24 64 65
   66 61 75 6C 74 24 31 37 15 2C FFFFFF85 44 FFFFFF85 45 FFFFFF85 46
   FFFFFF85 47 FFFFFF85 48 FFFFFF85 49 FFFFFF85 4A FFFFFF85 4B FFFFFF85 4C FFFFFF85 4D FFFFFF85 4E
   FFFFFF85 4F FFFFFF85 50 FFFFFF85 51 FFFFFF85 52 FFFFFF85 53 FFFFFF85 54 FFFFFF85 55 FFFFFF85 56
   FFFFFF85 57 FFFFFF85 58 FFFFFF85 59 2A 03 4B FFFFFF82 1C 04 09 16 FFFFFF85 41
   FFFFFF84 FFFFFF80 FFFFFF80 FFFFFFC2 00 17 04 09 20 FFFFFF85 41 FFFFFF84 FFFFFF80 FFFFFF80 FFFFFFC2 00
   17 04 09 23 FFFFFF85 41 FFFFFF84 FFFFFF80 FFFFFF80 FFFFFFC2 00 17 04 09 26 FFFFFF85
   41 FFFFFF84 FFFFFF80 FFFFFF80 FFFFFFC2 00 17 04 09 29 FFFFFF85 41 FFFFFF84 FFFFFF80 FFFFFF80 FFFFFFC2
   00 17 04 09 2C FFFFFF85 41 FFFFFF84 FFFFFF80 FFFFFF80 FFFFFFC2 00 17 04 09 2F
   FFFFFF85 41 FFFFFF84 FFFFFF80 FFFFFF80 FFFFFFC2 00 17 04 09 32 FFFFFF85 41 FFFFFF84 FFFFFF80 FFFFFF80
   FFFFFFC2 00 17 04 09 35 FFFFFF85 41 FFFFFF84 FFFFFF80 FFFFFF80 FFFFFFC2 00 17 04 09
   38 FFFFFF85 41 FFFFFF84 FFFFFF80 FFFFFF80 FFFFFFC2 00 17 04 09 3B FFFFFF85 41 FFFFFF84 FFFFFF80
   FFFFFF80 FFFFFFC2 00 17 04 09 3E FFFFFF85 41 FFFFFF84 FFFFFF80 FFFFFF80 FFFFFFC2 00 17 04
   09 41 FFFFFF85 41 FFFFFF84 FFFFFF80 FFFFFF80 FFFFFFC2 00 17 04 09 44 FFFFFF85 41 FFFFFF84
   FFFFFF80 FFFFFF80 FFFFFFC2 00 17 04 09 47 FFFFFF85 41 FFFFFF84 FFFFFF80 FFFFFF80 FFFFFFC2 00 17
   04 09 4A FFFFFF85 41 FFFFFF84 FFFFFF80 FFFFFF80 FFFFFFC2 00 17 04 09 4D FFFFFF85 41
   FFFFFF84 FFFFFF80 FFFFFF80 FFFFFFC2 00 17 04 09 50 FFFFFF85 41 FFFFFF84 FFFFFF80 FFFFFF80 FFFFFFC2 00
   17 04 09 53 FFFFFF85 41 FFFFFF84 FFFFFF80 FFFFFF80 FFFFFFC2 00 17 04 09 56 FFFFFF85
   41 FFFFFF84 FFFFFF80 FFFFFF80 FFFFFFC2 00 17 04 09 59 FFFFFF85 41 FFFFFF84 FFFFFF80 FFFFFF80 FFFFFFC2
   00 17 08 0C FFFFFF85 5B FFFFFF81 36 FFFFFF81 68 FFFFFF90 FFFFFF80 FFFFFFC0 00 FFFFFF82 0F
   08 09 FFFFFF85 5C 00 FFFFFF91 FFFFFF80 FFFFFF84 00 FFFFFF85 5D 01 0F 63 6F 70
   79 24 64 65 66 61 75 6C 74 24 31 38 15 2C FFFFFF85 5E
   FFFFFF85 5F FFFFFF85 60 FFFFFF85 61 FFFFFF85 62 FFFFFF85 63 FFFFFF85 64 FFFFFF85 65 FFFFFF85 66
   FFFFFF85 67 FFFFFF85 68 FFFFFF85 69 FFFFFF85 6A FFFFFF85 6B FFFFFF85 6C FFFFFF85 6D FFFFFF85 6E
   FFFFFF85 6F FFFFFF85 70 FFFFFF85 71 FFFFFF85 72 FFFFFF85 73 2A 03 4E FFFFFF82 1C 04
   09 16 FFFFFF85 5B FFFFFF84 FFFFFF80 FFFFFF80 FFFFFFC2 00 17 04 09 20 FFFFFF85 5B FFFFFF84
   FFFFFF80 FFFFFF80 FFFFFFC2 00 17 04 09 23 FFFFFF85 5B FFFFFF84 FFFFFF80 FFFFFF80 FFFFFFC2 00 17
   04 09 26 FFFFFF85 5B FFFFFF84 FFFFFF80 FFFFFF80 FFFFFFC2 00 17 04 09 29 FFFFFF85 5B
   FFFFFF84 FFFFFF80 FFFFFF80 FFFFFFC2 00 17 04 09 2C FFFFFF85 5B FFFFFF84 FFFFFF80 FFFFFF80 FFFFFFC2 00
   17 04 09 2F FFFFFF85 5B FFFFFF84 FFFFFF80 FFFFFF80 FFFFFFC2 00 17 04 09 32 FFFFFF85
   5B FFFFFF84 FFFFFF80 FFFFFF80 FFFFFFC2 00 17 04 09 35 FFFFFF85 5B FFFFFF84 FFFFFF80 FFFFFF80 FFFFFFC2
   00 17 04 09 38 FFFFFF85 5B FFFFFF84 FFFFFF80 FFFFFF80 FFFFFFC2 00 17 04 09 3B
   FFFFFF85 5B FFFFFF84 FFFFFF80 FFFFFF80 FFFFFFC2 00 17 04 09 3E FFFFFF85 5B FFFFFF84 FFFFFF80 FFFFFF80
   FFFFFFC2 00 17 04 09 41 FFFFFF85 5B FFFFFF84 FFFFFF80 FFFFFF80 FFFFFFC2 00 17 04 09
   44 FFFFFF85 5B FFFFFF84 FFFFFF80 FFFFFF80 FFFFFFC2 00 17 04 09 47 FFFFFF85 5B FFFFFF84 FFFFFF80
   FFFFFF80 FFFFFFC2 00 17 04 09 4A FFFFFF85 5B FFFFFF84 FFFFFF80 FFFFFF80 FFFFFFC2 00 17 04
   09 4D FFFFFF85 5B FFFFFF84 FFFFFF80 FFFFFF80 FFFFFFC2 00 17 04 09 50 FFFFFF85 5B FFFFFF84
   FFFFFF80 FFFFFF80 FFFFFFC2 00 17 04 09 53 FFFFFF85 5B FFFFFF84 FFFFFF80 FFFFFF80 FFFFFFC2 00 17
   04 09 56 FFFFFF85 5B FFFFFF84 FFFFFF80 FFFFFF80 FFFFFFC2 00 17 04 09 59 FFFFFF85 5B
   FFFFFF84 FFFFFF80 FFFFFF80 FFFFFFC2 00 17 08 0C FFFFFF85 75 FFFFFF81 3B FFFFFF81 68 FFFFFF90 FFFFFF80
   FFFFFFC0 00 FFFFFF82 11 08 09 FFFFFF85 76 00 FFFFFF91 FFFFFF80 FFFFFF84 00 FFFFFF85 77 01
   0F 63 6F 70 79 24 64 65 66 61 75 6C 74 24 31 39
   15 2C FFFFFF85 78 FFFFFF85 79 FFFFFF85 7A FFFFFF85 7B FFFFFF85 7C FFFFFF85 7D FFFFFF85 7E
   FFFFFF85 7F FFFFFF86 00 FFFFFF86 01 FFFFFF86 02 FFFFFF86 03 FFFFFF86 04 FFFFFF86 05 FFFFFF86 06
   FFFFFF86 07 FFFFFF86 08 FFFFFF86 09 FFFFFF86 0A FFFFFF86 0B FFFFFF86 0C FFFFFF86 0D 2A 03
   51 FFFFFF82 1C 04 09 16 FFFFFF85 75 FFFFFF84 FFFFFF80 FFFFFF80 FFFFFFC2 00 17 04 09
   20 FFFFFF85 75 FFFFFF84 FFFFFF80 FFFFFF80 FFFFFFC2 00 17 04 09 23 FFFFFF85 75 FFFFFF84 FFFFFF80
   FFFFFF80 FFFFFFC2 00 17 04 09 26 FFFFFF85 75 FFFFFF84 FFFFFF80 FFFFFF80 FFFFFFC2 00 17 04
   09 29 FFFFFF85 75 FFFFFF84 FFFFFF80 FFFFFF80 FFFFFFC2 00 17 04 09 2C FFFFFF85 75 FFFFFF84
   FFFFFF80 FFFFFF80 FFFFFFC2 00 17 04 09 2F FFFFFF85 75 FFFFFF84 FFFFFF80 FFFFFF80 FFFFFFC2 00 17
   04 09 32 FFFFFF85 75 FFFFFF84 FFFFFF80 FFFFFF80 FFFFFFC2 00 17 04 09 35 FFFFFF85 75
   FFFFFF84 FFFFFF80 FFFFFF80 FFFFFFC2 00 17 04 09 38 FFFFFF85 75 FFFFFF84 FFFFFF80 FFFFFF80 FFFFFFC2 00
   17 04 09 3B FFFFFF85 75 FFFFFF84 FFFFFF80 FFFFFF80 FFFFFFC2 00 17 04 09 3E FFFFFF85
   75 FFFFFF84 FFFFFF80 FFFFFF80 FFFFFFC2 00 17 04 09 41 FFFFFF85 75 FFFFFF84 FFFFFF80 FFFFFF80 FFFFFFC2
   00 17 04 09 44 FFFFFF85 75 FFFFFF84 FFFFFF80 FFFFFF80 FFFFFFC2 00 17 04 09 47
   FFFFFF85 75 FFFFFF84 FFFFFF80 FFFFFF80 FFFFFFC2 00 17 04 09 4A FFFFFF85 75 FFFFFF84 FFFFFF80 FFFFFF80
   FFFFFFC2 00 17 04 09 4D FFFFFF85 75 FFFFFF84 FFFFFF80 FFFFFF80 FFFFFFC2 00 17 04 09
   50 FFFFFF85 75 FFFFFF84 FFFFFF80 FFFFFF80 FFFFFFC2 00 17 04 09 53 FFFFFF85 75 FFFFFF84 FFFFFF80
   FFFFFF80 FFFFFFC2 00 17 04 09 56 FFFFFF85 75 FFFFFF84 FFFFFF80 FFFFFF80 FFFFFFC2 00 17 04
   09 59 FFFFFF85 75 FFFFFF84 FFFFFF80 FFFFFF80 FFFFFFC2 00 17 08 0C FFFFFF86 0F FFFFFF81 40
   FFFFFF81 68 FFFFFF90 FFFFFF80 FFFFFFC0 00 FFFFFF82 13 08 09 FFFFFF86 10 00 FFFFFF91 FFFFFF80 FFFFFF84
   00 FFFFFF86 11 01 0F 63 6F 70 79 24 64 65 66 61 75 6C
   74 24 32 30 15 2C FFFFFF86 12 FFFFFF86 13 FFFFFF86 14 FFFFFF86 15 FFFFFF86 16
   FFFFFF86 17 FFFFFF86 18 FFFFFF86 19 FFFFFF86 1A FFFFFF86 1B FFFFFF86 1C FFFFFF86 1D FFFFFF86 1E
   FFFFFF86 1F FFFFFF86 20 FFFFFF86 21 FFFFFF86 22 FFFFFF86 23 FFFFFF86 24 FFFFFF86 25 FFFFFF86 26
   FFFFFF86 27 2A 03 54 FFFFFF82 1C 04 09 16 FFFFFF86 0F FFFFFF84 FFFFFF80 FFFFFF80 FFFFFFC2
   00 17 04 09 20 FFFFFF86 0F FFFFFF84 FFFFFF80 FFFFFF80 FFFFFFC2 00 17 04 09 23
   FFFFFF86 0F FFFFFF84 FFFFFF80 FFFFFF80 FFFFFFC2 00 17 04 09 26 FFFFFF86 0F FFFFFF84 FFFFFF80 FFFFFF80
   FFFFFFC2 00 17 04 09 29 FFFFFF86 0F FFFFFF84 FFFFFF80 FFFFFF80 FFFFFFC2 00 17 04 09
   2C FFFFFF86 0F FFFFFF84 FFFFFF80 FFFFFF80 FFFFFFC2 00 17 04 09 2F FFFFFF86 0F FFFFFF84 FFFFFF80
   FFFFFF80 FFFFFFC2 00 17 04 09 32 FFFFFF86 0F FFFFFF84 FFFFFF80 FFFFFF80 FFFFFFC2 00 17 04
   09 35 FFFFFF86 0F FFFFFF84 FFFFFF80 FFFFFF80 FFFFFFC2 00 17 04 09 38 FFFFFF86 0F FFFFFF84
   FFFFFF80 FFFFFF80 FFFFFFC2 00 17 04 09 3B FFFFFF86 0F FFFFFF84 FFFFFF80 FFFFFF80 FFFFFFC2 00 17
   04 09 3E FFFFFF86 0F FFFFFF84 FFFFFF80 FFFFFF80 FFFFFFC2 00 17 04 09 41 FFFFFF86 0F
   FFFFFF84 FFFFFF80 FFFFFF80 FFFFFFC2 00 17 04 09 44 FFFFFF86 0F FFFFFF84 FFFFFF80 FFFFFF80 FFFFFFC2 00
   17 04 09 47 FFFFFF86 0F FFFFFF84 FFFFFF80 FFFFFF80 FFFFFFC2 00 17 04 09 4A FFFFFF86
   0F FFFFFF84 FFFFFF80 FFFFFF80 FFFFFFC2 00 17 04 09 4D FFFFFF86 0F FFFFFF84 FFFFFF80 FFFFFF80 FFFFFFC2
   00 17 04 09 50 FFFFFF86 0F FFFFFF84 FFFFFF80 FFFFFF80 FFFFFFC2 00 17 04 09 53
   FFFFFF86 0F FFFFFF84 FFFFFF80 FFFFFF80 FFFFFFC2 00 17 04 09 56 FFFFFF86 0F FFFFFF84 FFFFFF80 FFFFFF80
   FFFFFFC2 00 17 04 09 59 FFFFFF86 0F FFFFFF84 FFFFFF80 FFFFFF80 FFFFFFC2 00 17 08 0C
   FFFFFF86 29 FFFFFF81 45 FFFFFF81 68 FFFFFF90 FFFFFF80 FFFFFFC0 00 FFFFFF82 15 08 09 FFFFFF86 2A
   00 FFFFFF91 FFFFFF80 FFFFFF84 00 FFFFFF86 2B 01 0F 63 6F 70 79 24 64 65
   66 61 75 6C 74 24 32 31 15 2C FFFFFF86 2C FFFFFF86 2D FFFFFF86 2E
   FFFFFF86 2F FFFFFF86 30 FFFFFF86 31 FFFFFF86 32 FFFFFF86 33 FFFFFF86 34 FFFFFF86 35 FFFFFF86 36
   FFFFFF86 37 FFFFFF86 38 FFFFFF86 39 FFFFFF86 3A FFFFFF86 3B FFFFFF86 3C FFFFFF86 3D FFFFFF86 3E
   FFFFFF86 3F FFFFFF86 40 FFFFFF86 41 2A 03 57 FFFFFF82 1C 04 09 16 FFFFFF86 29
   FFFFFF84 FFFFFF80 FFFFFF80 FFFFFFC2 00 17 04 09 20 FFFFFF86 29 FFFFFF84 FFFFFF80 FFFFFF80 FFFFFFC2 00
   17 04 09 23 FFFFFF86 29 FFFFFF84 FFFFFF80 FFFFFF80 FFFFFFC2 00 17 04 09 26 FFFFFF86
   29 FFFFFF84 FFFFFF80 FFFFFF80 FFFFFFC2 00 17 04 09 29 FFFFFF86 29 FFFFFF84 FFFFFF80 FFFFFF80 FFFFFFC2
   00 17 04 09 2C FFFFFF86 29 FFFFFF84 FFFFFF80 FFFFFF80 FFFFFFC2 00 17 04 09 2F
   FFFFFF86 29 FFFFFF84 FFFFFF80 FFFFFF80 FFFFFFC2 00 17 04 09 32 FFFFFF86 29 FFFFFF84 FFFFFF80 FFFFFF80
   FFFFFFC2 00 17 04 09 35 FFFFFF86 29 FFFFFF84 FFFFFF80 FFFFFF80 FFFFFFC2 00 17 04 09
   38 FFFFFF86 29 FFFFFF84 FFFFFF80 FFFFFF80 FFFFFFC2 00 17 04 09 3B FFFFFF86 29 FFFFFF84 FFFFFF80
   FFFFFF80 FFFFFFC2 00 17 04 09 3E FFFFFF86 29 FFFFFF84 FFFFFF80 FFFFFF80 FFFFFFC2 00 17 04
   09 41 FFFFFF86 29 FFFFFF84 FFFFFF80 FFFFFF80 FFFFFFC2 00 17 04 09 44 FFFFFF86 29 FFFFFF84
   FFFFFF80 FFFFFF80 FFFFFFC2 00 17 04 09 47 FFFFFF86 29 FFFFFF84 FFFFFF80 FFFFFF80 FFFFFFC2 00 17
   04 09 4A FFFFFF86 29 FFFFFF84 FFFFFF80 FFFFFF80 FFFFFFC2 00 17 04 09 4D FFFFFF86 29
   FFFFFF84 FFFFFF80 FFFFFF80 FFFFFFC2 00 17 04 09 50 FFFFFF86 29 FFFFFF84 FFFFFF80 FFFFFF80 FFFFFFC2 00
   17 04 09 53 FFFFFF86 29 FFFFFF84 FFFFFF80 FFFFFF80 FFFFFFC2 00 17 04 09 56 FFFFFF86
   29 FFFFFF84 FFFFFF80 FFFFFF80 FFFFFFC2 00 17 04 09 59 FFFFFF86 29 FFFFFF84 FFFFFF80 FFFFFF80 FFFFFFC2
   00 17 08 0A FFFFFF86 43 00 FFFFFF84 FFFFFF80 FFFFFF80 FFFFFF84 20 FFFFFF86 44 01 08
   68 61 73 68 43 6F 64 65 14 02 FFFFFF86 45 10 03 10 FFFFFF86
   46 09 03 FFFFFF86 47 02 02 03 49 6E 74 08 0A FFFFFF86 49 00
   FFFFFF84 FFFFFF80 FFFFFF80 FFFFFF84 20 FFFFFF86 4A 01 06 65 71 75 61 6C 73 14
   04 FFFFFF86 4B FFFFFF86 4E 10 03 10 FFFFFF86 4C 09 03 FFFFFF86 4D 02 02
   07 42 6F 6F 6C 65 61 6E 08 09 FFFFFF86 4F FFFFFF86 48 FFFFFF81 FFFFFF80
   FFFFFFC0 00 1B 01 03 78 24 31 08 0A FFFFFF86 51 00 FFFFFF84 FFFFFF80 FFFFFF80
   FFFFFF84 20 FFFFFF86 52 01 0D 70 72 6F 64 75 63 74 50 72 65
   66 69 78 15 02 FFFFFF81 65 08 0A FFFFFF86 54 00 FFFFFF84 FFFFFF80 FFFFFF80 FFFFFF84
   20 FFFFFF86 55 01 08 63 61 6E 45 71 75 61 6C 14 04 FFFFFF86
   4B FFFFFF86 56 08 09 FFFFFF86 4F FFFFFF86 53 FFFFFF81 FFFFFF80 FFFFFFC0 00 1B 28 03
   00 FFFFFF86 58 10 03 10 FFFFFF86 59 09 03 FFFFFF86 5A 02 02 0C 73
   65 72 69 61 6C 69 7A 61 62 6C 65 07 09 FFFFFF86 5C 02
   FFFFFF81 FFFFFF80 FFFFFF88 02 FFFFFF86 5D 01 07 54 75 70 6C 65 32 31 10
   03 10 FFFFFF86 5E 06 09 01 02 FFFFFF84 FFFFFF81 FFFFFF80 FFFFFF88 02 FFFFFF86 5F 13
   04 FFFFFF86 5E 07 5A 08 08 FFFFFF81 4A FFFFFF86 5E FFFFFF84 00 FFFFFF86 61 14
   02 FFFFFF86 5D 08 0A FFFFFF86 63 FFFFFF86 5E FFFFFF81 FFFFFF80 FFFFFF84 40 FFFFFF86 64 01
   05 61 70 70 6C 79 15 2C FFFFFF86 65 FFFFFF86 68 FFFFFF86 6A FFFFFF86 6C
   FFFFFF86 6E FFFFFF86 70 FFFFFF86 72 FFFFFF86 74 FFFFFF86 76 FFFFFF86 78 FFFFFF86 7A FFFFFF86 7C
   FFFFFF86 7E FFFFFF87 00 FFFFFF87 02 FFFFFF87 04 FFFFFF87 06 FFFFFF87 08 FFFFFF87 0A FFFFFF87 0C
   FFFFFF87 0E FFFFFF87 10 14 2C FFFFFF86 66 FFFFFF87 11 FFFFFF87 12 FFFFFF87 13 FFFFFF87 14
   FFFFFF87 15 FFFFFF87 16 FFFFFF87 17 FFFFFF87 18 FFFFFF87 19 FFFFFF87 1A FFFFFF87 1B FFFFFF87 1C
   FFFFFF87 1D FFFFFF87 1E FFFFFF87 1F FFFFFF87 20 FFFFFF87 21 FFFFFF87 22 FFFFFF87 23 FFFFFF87 24
   FFFFFF87 25 10 2C 10 00 FFFFFF86 67 FFFFFF86 69 FFFFFF86 6B FFFFFF86 6D FFFFFF86 6F
   FFFFFF86 71 FFFFFF86 73 FFFFFF86 75 FFFFFF86 77 FFFFFF86 79 FFFFFF86 7B FFFFFF86 7D FFFFFF86 7F
   FFFFFF87 01 FFFFFF87 03 FFFFFF87 05 FFFFFF87 07 FFFFFF87 09 FFFFFF87 0B FFFFFF87 0D FFFFFF87 0F
   10 03 14 FFFFFF86 68 04 09 16 FFFFFF86 62 FFFFFF84 FFFFFF80 FFFFFF80 FFFFFFC2 00 17
   10 03 14 FFFFFF86 6A 04 09 20 FFFFFF86 62 FFFFFF84 FFFFFF80 FFFFFF80 FFFFFFC2 00 17
   10 03 14 FFFFFF86 6C 04 09 23 FFFFFF86 62 FFFFFF84 FFFFFF80 FFFFFF80 FFFFFFC2 00 17
   10 03 14 FFFFFF86 6E 04 09 26 FFFFFF86 62 FFFFFF84 FFFFFF80 FFFFFF80 FFFFFFC2 00 17
   10 03 14 FFFFFF86 70 04 09 29 FFFFFF86 62 FFFFFF84 FFFFFF80 FFFFFF80 FFFFFFC2 00 17
   10 03 14 FFFFFF86 72 04 09 2C FFFFFF86 62 FFFFFF84 FFFFFF80 FFFFFF80 FFFFFFC2 00 17
   10 03 14 FFFFFF86 74 04 09 2F FFFFFF86 62 FFFFFF84 FFFFFF80 FFFFFF80 FFFFFFC2 00 17
   10 03 14 FFFFFF86 76 04 09 32 FFFFFF86 62 FFFFFF84 FFFFFF80 FFFFFF80 FFFFFFC2 00 17
   10 03 14 FFFFFF86 78 04 09 35 FFFFFF86 62 FFFFFF84 FFFFFF80 FFFFFF80 FFFFFFC2 00 17
   10 03 14 FFFFFF86 7A 04 09 38 FFFFFF86 62 FFFFFF84 FFFFFF80 FFFFFF80 FFFFFFC2 00 17
   10 03 14 FFFFFF86 7C 04 09 3B FFFFFF86 62 FFFFFF84 FFFFFF80 FFFFFF80 FFFFFFC2 00 17
   10 03 14 FFFFFF86 7E 04 09 3E FFFFFF86 62 FFFFFF84 FFFFFF80 FFFFFF80 FFFFFFC2 00 17
   10 03 14 FFFFFF87 00 04 09 41 FFFFFF86 62 FFFFFF84 FFFFFF80 FFFFFF80 FFFFFFC2 00 17
   10 03 14 FFFFFF87 02 04 09 44 FFFFFF86 62 FFFFFF84 FFFFFF80 FFFFFF80 FFFFFFC2 00 17
   10 03 14 FFFFFF87 04 04 09 47 FFFFFF86 62 FFFFFF84 FFFFFF80 FFFFFF80 FFFFFFC2 00 17
   10 03 14 FFFFFF87 06 04 09 4A FFFFFF86 62 FFFFFF84 FFFFFF80 FFFFFF80 FFFFFFC2 00 17
   10 03 14 FFFFFF87 08 04 09 4D FFFFFF86 62 FFFFFF84 FFFFFF80 FFFFFF80 FFFFFFC2 00 17
   10 03 14 FFFFFF87 0A 04 09 50 FFFFFF86 62 FFFFFF84 FFFFFF80 FFFFFF80 FFFFFFC2 00 17
   10 03 14 FFFFFF87 0C 04 09 53 FFFFFF86 62 FFFFFF84 FFFFFF80 FFFFFF80 FFFFFFC2 00 17
   10 03 14 FFFFFF87 0E 04 09 56 FFFFFF86 62 FFFFFF84 FFFFFF80 FFFFFF80 FFFFFFC2 00 17
   10 03 14 FFFFFF87 10 04 09 59 FFFFFF86 62 FFFFFF84 FFFFFF80 FFFFFF80 FFFFFFC2 00 17
   08 07 61 FFFFFF86 62 FFFFFFC0 00 FFFFFF86 67 08 07 66 FFFFFF86 62 FFFFFFC0 00
   FFFFFF86 69 08 07 6B FFFFFF86 62 FFFFFFC0 00 FFFFFF86 6B 08 07 70 FFFFFF86 62
   FFFFFFC0 00 FFFFFF86 6D 08 07 75 FFFFFF86 62 FFFFFFC0 00 FFFFFF86 6F 08 07 7A
   FFFFFF86 62 FFFFFFC0 00 FFFFFF86 71 08 07 7F FFFFFF86 62 FFFFFFC0 00 FFFFFF86 73 08
   08 FFFFFF81 04 FFFFFF86 62 FFFFFFC0 00 FFFFFF86 75 08 08 FFFFFF81 09 FFFFFF86 62 FFFFFFC0
   00 FFFFFF86 77 08 08 FFFFFF81 0E FFFFFF86 62 FFFFFFC0 00 FFFFFF86 79 08 08 FFFFFF81
   13 FFFFFF86 62 FFFFFFC0 00 FFFFFF86 7B 08 08 FFFFFF81 18 FFFFFF86 62 FFFFFFC0 00 FFFFFF86
   7D 08 08 FFFFFF81 1D FFFFFF86 62 FFFFFFC0 00 FFFFFF86 7F 08 08 FFFFFF81 22 FFFFFF86
   62 FFFFFFC0 00 FFFFFF87 01 08 08 FFFFFF81 27 FFFFFF86 62 FFFFFFC0 00 FFFFFF87 03 08
   08 FFFFFF81 2C FFFFFF86 62 FFFFFFC0 00 FFFFFF87 05 08 08 FFFFFF81 31 FFFFFF86 62 FFFFFFC0
   00 FFFFFF87 07 08 08 FFFFFF81 36 FFFFFF86 62 FFFFFFC0 00 FFFFFF87 09 08 08 FFFFFF81
   3B FFFFFF86 62 FFFFFFC0 00 FFFFFF87 0B 08 08 FFFFFF81 40 FFFFFF86 62 FFFFFFC0 00 FFFFFF87
   0D 08 08 FFFFFF81 45 FFFFFF86 62 FFFFFFC0 00 FFFFFF87 0F 08 0A FFFFFF87 27 FFFFFF86
   5E FFFFFF81 FFFFFF80 FFFFFF84 40 FFFFFF87 28 01 07 75 6E 61 70 70 6C 79
   15 2C FFFFFF87 29 FFFFFF87 2F FFFFFF87 31 FFFFFF87 33 FFFFFF87 35 FFFFFF87 37 FFFFFF87 39
   FFFFFF87 3B FFFFFF87 3D FFFFFF87 3F FFFFFF87 41 FFFFFF87 43 FFFFFF87 45 FFFFFF87 47 FFFFFF87 49
   FFFFFF87 4B FFFFFF87 4D FFFFFF87 4F FFFFFF87 51 FFFFFF87 53 FFFFFF87 55 FFFFFF87 57 14 04
   FFFFFF87 2A FFFFFF87 58 10 05 10 FFFFFF87 2B FFFFFF87 2D 09 03 FFFFFF87 2C 02
   02 04 53 6F 6D 65 10 2C 10 00 FFFFFF87 2E FFFFFF87 30 FFFFFF87 32
   FFFFFF87 34 FFFFFF87 36 FFFFFF87 38 FFFFFF87 3A FFFFFF87 3C FFFFFF87 3E FFFFFF87 40 FFFFFF87 42
   FFFFFF87 44 FFFFFF87 46 FFFFFF87 48 FFFFFF87 4A FFFFFF87 4C FFFFFF87 4E FFFFFF87 50 FFFFFF87 52
   FFFFFF87 54 FFFFFF87 56 10 03 14 FFFFFF87 2F 04 09 16 FFFFFF87 26 FFFFFF84 FFFFFF80
   FFFFFF80 FFFFFFC2 00 17 10 03 14 FFFFFF87 31 04 09 20 FFFFFF87 26 FFFFFF84 FFFFFF80
   FFFFFF80 FFFFFFC2 00 17 10 03 14 FFFFFF87 33 04 09 23 FFFFFF87 26 FFFFFF84 FFFFFF80
   FFFFFF80 FFFFFFC2 00 17 10 03 14 FFFFFF87 35 04 09 26 FFFFFF87 26 FFFFFF84 FFFFFF80
   FFFFFF80 FFFFFFC2 00 17 10 03 14 FFFFFF87 37 04 09 29 FFFFFF87 26 FFFFFF84 FFFFFF80
   FFFFFF80 FFFFFFC2 00 17 10 03 14 FFFFFF87 39 04 09 2C FFFFFF87 26 FFFFFF84 FFFFFF80
   FFFFFF80 FFFFFFC2 00 17 10 03 14 FFFFFF87 3B 04 09 2F FFFFFF87 26 FFFFFF84 FFFFFF80
   FFFFFF80 FFFFFFC2 00 17 10 03 14 FFFFFF87 3D 04 09 32 FFFFFF87 26 FFFFFF84 FFFFFF80
   FFFFFF80 FFFFFFC2 00 17 10 03 14 FFFFFF87 3F 04 09 35 FFFFFF87 26 FFFFFF84 FFFFFF80
   FFFFFF80 FFFFFFC2 00 17 10 03 14 FFFFFF87 41 04 09 38 FFFFFF87 26 FFFFFF84 FFFFFF80
   FFFFFF80 FFFFFFC2 00 17 10 03 14 FFFFFF87 43 04 09 3B FFFFFF87 26 FFFFFF84 FFFFFF80
   FFFFFF80 FFFFFFC2 00 17 10 03 14 FFFFFF87 45 04 09 3E FFFFFF87 26 FFFFFF84 FFFFFF80
   FFFFFF80 FFFFFFC2 00 17 10 03 14 FFFFFF87 47 04 09 41 FFFFFF87 26 FFFFFF84 FFFFFF80
   FFFFFF80 FFFFFFC2 00 17 10 03 14 FFFFFF87 49 04 09 44 FFFFFF87 26 FFFFFF84 FFFFFF80
   FFFFFF80 FFFFFFC2 00 17 10 03 14 FFFFFF87 4B 04 09 47 FFFFFF87 26 FFFFFF84 FFFFFF80
   FFFFFF80 FFFFFFC2 00 17 10 03 14 FFFFFF87 4D 04 09 4A FFFFFF87 26 FFFFFF84 FFFFFF80
   FFFFFF80 FFFFFFC2 00 17 10 03 14 FFFFFF87 4F 04 09 4D FFFFFF87 26 FFFFFF84 FFFFFF80
   FFFFFF80 FFFFFFC2 00 17 10 03 14 FFFFFF87 51 04 09 50 FFFFFF87 26 FFFFFF84 FFFFFF80
   FFFFFF80 FFFFFFC2 00 17 10 03 14 FFFFFF87 53 04 09 53 FFFFFF87 26 FFFFFF84 FFFFFF80
   FFFFFF80 FFFFFFC2 00 17 10 03 14 FFFFFF87 55 04 09 56 FFFFFF87 26 FFFFFF84 FFFFFF80
   FFFFFF80 FFFFFFC2 00 17 10 03 14 FFFFFF87 57 04 09 59 FFFFFF87 26 FFFFFF84 FFFFFF80
   FFFFFF80 FFFFFFC2 00 17 08 08 FFFFFF87 59 FFFFFF87 26 FFFFFFC0 00 FFFFFF87 2D 01 03
   78 24 30 
  minor version: 0
  major version: 49
  Constant pool:
Asciz	SourceFile;
Asciz	Tuple21.scala;
Asciz	_21;
Asciz	Ljava/lang/Object;;
Asciz	TT21;;
Asciz	Signature;
Asciz	_20;
Asciz	TT20;;
Asciz	_19;
Asciz	TT19;;
Asciz	_18;
Asciz	TT18;;
Asciz	_17;
Asciz	TT17;;
Asciz	_16;
Asciz	TT16;;
Asciz	_15;
Asciz	TT15;;
Asciz	_14;
Asciz	TT14;;
Asciz	_13;
Asciz	TT13;;
Asciz	_12;
Asciz	TT12;;
Asciz	_11;
Asciz	TT11;;
Asciz	_10;
Asciz	TT10;;
Asciz	_9;
Asciz	TT9;;
Asciz	_8;
Asciz	TT8;;
Asciz	_7;
Asciz	TT7;;
Asciz	_6;
Asciz	TT6;;
Asciz	_5;
Asciz	TT5;;
Asciz	_4;
Asciz	TT4;;
Asciz	_3;
Asciz	TT3;;
Asciz	_2;
Asciz	TT2;;
Asciz	_1;
Asciz	TT1;;
Asciz	<init>;
Asciz	(Ljava/lang/Object;Ljava/lang/Object;Ljava/lang/Object;Ljava/lang/Object;Ljava/lang/Object;Ljava/lang/Object;Ljava/lang/Object;Ljava/lang/Object;Ljava/lang/Object;Ljava/lang/Object;Ljava/lang/Object;Ljava/lang/Object;Ljava/lang/Object;Ljava/lang/Object;Ljava/lang/Object;Ljava/lang/Object;Ljava/lang/Object;Ljava/lang/Object;Ljava/lang/Object;Ljava/lang/Object;Ljava/lang/Object;)V;
Asciz	Code;
Asciz	LineNumberTable;
Asciz	scala/Tuple21;
class	scala/Tuple21
NameAndType	_1:Ljava/lang/Object;
Field	scala/Tuple21._1:Ljava/lang/Object;
NameAndType	_2:Ljava/lang/Object;
Field	scala/Tuple21._2:Ljava/lang/Object;
NameAndType	_3:Ljava/lang/Object;
Field	scala/Tuple21._3:Ljava/lang/Object;
NameAndType	_4:Ljava/lang/Object;
Field	scala/Tuple21._4:Ljava/lang/Object;
NameAndType	_5:Ljava/lang/Object;
Field	scala/Tuple21._5:Ljava/lang/Object;
NameAndType	_6:Ljava/lang/Object;
Field	scala/Tuple21._6:Ljava/lang/Object;
NameAndType	_7:Ljava/lang/Object;
Field	scala/Tuple21._7:Ljava/lang/Object;
NameAndType	_8:Ljava/lang/Object;
Field	scala/Tuple21._8:Ljava/lang/Object;
NameAndType	_9:Ljava/lang/Object;
Field	scala/Tuple21._9:Ljava/lang/Object;
NameAndType	_10:Ljava/lang/Object;
Field	scala/Tuple21._10:Ljava/lang/Object;
NameAndType	_11:Ljava/lang/Object;
Field	scala/Tuple21._11:Ljava/lang/Object;
NameAndType	_12:Ljava/lang/Object;
Field	scala/Tuple21._12:Ljava/lang/Object;
NameAndType	_13:Ljava/lang/Object;
Field	scala/Tuple21._13:Ljava/lang/Object;
NameAndType	_14:Ljava/lang/Object;
Field	scala/Tuple21._14:Ljava/lang/Object;
NameAndType	_15:Ljava/lang/Object;
Field	scala/Tuple21._15:Ljava/lang/Object;
NameAndType	_16:Ljava/lang/Object;
Field	scala/Tuple21._16:Ljava/lang/Object;
NameAndType	_17:Ljava/lang/Object;
Field	scala/Tuple21._17:Ljava/lang/Object;
NameAndType	_18:Ljava/lang/Object;
Field	scala/Tuple21._18:Ljava/lang/Object;
NameAndType	_19:Ljava/lang/Object;
Field	scala/Tuple21._19:Ljava/lang/Object;
NameAndType	_20:Ljava/lang/Object;
Field	scala/Tuple21._20:Ljava/lang/Object;
NameAndType	_21:Ljava/lang/Object;
Field	scala/Tuple21._21:Ljava/lang/Object;
Asciz	java/lang/Object;
class	java/lang/Object
Asciz	()V;
NameAndType	"<init>":()V
Method	java/lang/Object."<init>":()V
Asciz	scala/Product$class;
class	scala/Product$class
Asciz	$init$;
Asciz	(Lscala/Product;)V;
NameAndType	$init$:(Lscala/Product;)V
Method	scala/Product$class.$init$:(Lscala/Product;)V
Asciz	scala/Product21$class;
class	scala/Product21$class
Asciz	(Lscala/Product21;)V;
NameAndType	$init$:(Lscala/Product21;)V
Method	scala/Product21$class.$init$:(Lscala/Product21;)V
Asciz	this;
Asciz	Lscala/Tuple21;;
Asciz	LocalVariableTable;
Asciz	(TT1;TT2;TT3;TT4;TT5;TT6;TT7;TT8;TT9;TT10;TT11;TT12;TT13;TT14;TT15;TT16;TT17;TT18;TT19;TT20;TT21;)V;
Asciz	gd1$1;
Asciz	(Ljava/lang/Object;Ljava/lang/Object;Ljava/lang/Object;Ljava/lang/Object;Ljava/lang/Object;Ljava/lang/Object;Ljava/lang/Object;Ljava/lang/Object;Ljava/lang/Object;Ljava/lang/Object;Ljava/lang/Object;Ljava/lang/Object;Ljava/lang/Object;Ljava/lang/Object;Ljava/lang/Object;Ljava/lang/Object;Ljava/lang/Object;Ljava/lang/Object;Ljava/lang/Object;Ljava/lang/Object;Ljava/lang/Object;)Z;
Asciz	()Ljava/lang/Object;;
NameAndType	_1:()Ljava/lang/Object;
Method	scala/Tuple21._1:()Ljava/lang/Object;
Asciz	java/lang/Number;
class	java/lang/Number
Asciz	java/lang/Character;
class	java/lang/Character
Asciz	scala/runtime/BoxesRunTime;
class	scala/runtime/BoxesRunTime
Asciz	equals2;
Asciz	(Ljava/lang/Object;Ljava/lang/Object;)Z;
NameAndType	equals2:(Ljava/lang/Object;Ljava/lang/Object;)Z
Method	scala/runtime/BoxesRunTime.equals2:(Ljava/lang/Object;Ljava/lang/Object;)Z
Asciz	equals;
Asciz	(Ljava/lang/Object;)Z;
NameAndType	equals:(Ljava/lang/Object;)Z
Method	java/lang/Object.equals:(Ljava/lang/Object;)Z
NameAndType	_2:()Ljava/lang/Object;
Method	scala/Tuple21._2:()Ljava/lang/Object;
NameAndType	_3:()Ljava/lang/Object;
Method	scala/Tuple21._3:()Ljava/lang/Object;
NameAndType	_4:()Ljava/lang/Object;
Method	scala/Tuple21._4:()Ljava/lang/Object;
NameAndType	_5:()Ljava/lang/Object;
Method	scala/Tuple21._5:()Ljava/lang/Object;
NameAndType	_6:()Ljava/lang/Object;
Method	scala/Tuple21._6:()Ljava/lang/Object;
NameAndType	_7:()Ljava/lang/Object;
Method	scala/Tuple21._7:()Ljava/lang/Object;
NameAndType	_8:()Ljava/lang/Object;
Method	scala/Tuple21._8:()Ljava/lang/Object;
NameAndType	_9:()Ljava/lang/Object;
Method	scala/Tuple21._9:()Ljava/lang/Object;
NameAndType	_10:()Ljava/lang/Object;
Method	scala/Tuple21._10:()Ljava/lang/Object;
NameAndType	_11:()Ljava/lang/Object;
Method	scala/Tuple21._11:()Ljava/lang/Object;
NameAndType	_12:()Ljava/lang/Object;
Method	scala/Tuple21._12:()Ljava/lang/Object;
NameAndType	_13:()Ljava/lang/Object;
Method	scala/Tuple21._13:()Ljava/lang/Object;
NameAndType	_14:()Ljava/lang/Object;
Method	scala/Tuple21._14:()Ljava/lang/Object;
NameAndType	_15:()Ljava/lang/Object;
Method	scala/Tuple21._15:()Ljava/lang/Object;
Asciz	scala/runtime/ScalaRunTime$;
class	scala/runtime/ScalaRunTime$
Asciz	MODULE$;
Asciz	Lscala/runtime/ScalaRunTime$;;
NameAndType	MODULE$:Lscala/runtime/ScalaRunTime$;
Field	scala/runtime/ScalaRunTime$.MODULE$:Lscala/runtime/ScalaRunTime$;
NameAndType	_16:()Ljava/lang/Object;
Method	scala/Tuple21._16:()Ljava/lang/Object;
Asciz	inlinedEquals;
NameAndType	inlinedEquals:(Ljava/lang/Object;Ljava/lang/Object;)Z
Method	scala/runtime/ScalaRunTime$.inlinedEquals:(Ljava/lang/Object;Ljava/lang/Object;)Z
NameAndType	_17:()Ljava/lang/Object;
Method	scala/Tuple21._17:()Ljava/lang/Object;
NameAndType	_18:()Ljava/lang/Object;
Method	scala/Tuple21._18:()Ljava/lang/Object;
NameAndType	_19:()Ljava/lang/Object;
Method	scala/Tuple21._19:()Ljava/lang/Object;
NameAndType	_20:()Ljava/lang/Object;
Method	scala/Tuple21._20:()Ljava/lang/Object;
NameAndType	_21:()Ljava/lang/Object;
Method	scala/Tuple21._21:()Ljava/lang/Object;
Asciz	y0;
Asciz	y1;
Asciz	y2;
Asciz	y3;
Asciz	y4;
Asciz	y5;
Asciz	y6;
Asciz	y7;
Asciz	y8;
Asciz	y9;
Asciz	y10;
Asciz	y11;
Asciz	y12;
Asciz	y13;
Asciz	y14;
Asciz	canEqual;
Asciz	productPrefix;
Asciz	()Ljava/lang/String;;
Asciz	Tuple21;
String	Tuple21
NameAndType	gd1$1:(Ljava/lang/Object;Ljava/lang/Object;Ljava/lang/Object;Ljava/lang/Object;Ljava/lang/Object;Ljava/lang/Object;Ljava/lang/Object;Ljava/lang/Object;Ljava/lang/Object;Ljava/lang/Object;Ljava/lang/Object;Ljava/lang/Object;Ljava/lang/Object;Ljava/lang/Object;Ljava/lang/Object;Ljava/lang/Object;Ljava/lang/Object;Ljava/lang/Object;Ljava/lang/Object;Ljava/lang/Object;Ljava/lang/Object;)Z
Method	scala/Tuple21.gd1$1:(Ljava/lang/Object;Ljava/lang/Object;Ljava/lang/Object;Ljava/lang/Object;Ljava/lang/Object;Ljava/lang/Object;Ljava/lang/Object;Ljava/lang/Object;Ljava/lang/Object;Ljava/lang/Object;Ljava/lang/Object;Ljava/lang/Object;Ljava/lang/Object;Ljava/lang/Object;Ljava/lang/Object;Ljava/lang/Object;Ljava/lang/Object;Ljava/lang/Object;Ljava/lang/Object;Ljava/lang/Object;Ljava/lang/Object;)Z
Asciz	scala/Equals;
class	scala/Equals
NameAndType	canEqual:(Ljava/lang/Object;)Z
InterfaceMethod	scala/Equals.canEqual:(Ljava/lang/Object;)Z
Asciz	scala/MatchError;
class	scala/MatchError
Asciz	toString;
NameAndType	toString:()Ljava/lang/String;
Method	java/lang/Object.toString:()Ljava/lang/String;
Asciz	(Ljava/lang/String;)V;
NameAndType	"<init>":(Ljava/lang/String;)V
Method	scala/MatchError."<init>":(Ljava/lang/String;)V
Asciz	temp2;
Asciz	temp3;
Asciz	temp4;
Asciz	temp5;
Asciz	temp6;
Asciz	temp7;
Asciz	temp8;
Asciz	temp9;
Asciz	temp10;
Asciz	temp11;
Asciz	temp12;
Asciz	temp13;
Asciz	temp14;
Asciz	temp15;
Asciz	temp16;
Asciz	temp17;
Asciz	temp18;
Asciz	temp19;
Asciz	temp20;
Asciz	temp21;
Asciz	temp22;
Asciz	temp23;
Asciz	hashCode;
Asciz	()I;
Asciz	_hashCode;
Asciz	(Lscala/Product;)I;
NameAndType	_hashCode:(Lscala/Product;)I
Method	scala/runtime/ScalaRunTime$._hashCode:(Lscala/Product;)I
Asciz	copy;
Asciz	(Ljava/lang/Object;Ljava/lang/Object;Ljava/lang/Object;Ljava/lang/Object;Ljava/lang/Object;Ljava/lang/Object;Ljava/lang/Object;Ljava/lang/Object;Ljava/lang/Object;Ljava/lang/Object;Ljava/lang/Object;Ljava/lang/Object;Ljava/lang/Object;Ljava/lang/Object;Ljava/lang/Object;Ljava/lang/Object;Ljava/lang/Object;Ljava/lang/Object;Ljava/lang/Object;Ljava/lang/Object;Ljava/lang/Object;)Lscala/Tuple21;;
NameAndType	"<init>":(Ljava/lang/Object;Ljava/lang/Object;Ljava/lang/Object;Ljava/lang/Object;Ljava/lang/Object;Ljava/lang/Object;Ljava/lang/Object;Ljava/lang/Object;Ljava/lang/Object;Ljava/lang/Object;Ljava/lang/Object;Ljava/lang/Object;Ljava/lang/Object;Ljava/lang/Object;Ljava/lang/Object;Ljava/lang/Object;Ljava/lang/Object;Ljava/lang/Object;Ljava/lang/Object;Ljava/lang/Object;Ljava/lang/Object;)V
Method	scala/Tuple21."<init>":(Ljava/lang/Object;Ljava/lang/Object;Ljava/lang/Object;Ljava/lang/Object;Ljava/lang/Object;Ljava/lang/Object;Ljava/lang/Object;Ljava/lang/Object;Ljava/lang/Object;Ljava/lang/Object;Ljava/lang/Object;Ljava/lang/Object;Ljava/lang/Object;Ljava/lang/Object;Ljava/lang/Object;Ljava/lang/Object;Ljava/lang/Object;Ljava/lang/Object;Ljava/lang/Object;Ljava/lang/Object;Ljava/lang/Object;)V
Asciz	scala/collection/mutable/StringBuilder;
class	scala/collection/mutable/StringBuilder
Method	scala/collection/mutable/StringBuilder."<init>":()V
Asciz	(;
String	(
Asciz	append;
Asciz	(Ljava/lang/Object;)Lscala/collection/mutable/StringBuilder;;
NameAndType	append:(Ljava/lang/Object;)Lscala/collection/mutable/StringBuilder;
Method	scala/collection/mutable/StringBuilder.append:(Ljava/lang/Object;)Lscala/collection/mutable/StringBuilder;
Asciz	,;
String	,
Asciz	);
String	)
Method	scala/collection/mutable/StringBuilder.toString:()Ljava/lang/String;
Asciz	()TT21;;
Asciz	()TT20;;
Asciz	()TT19;;
Asciz	()TT18;;
Asciz	()TT17;;
Asciz	()TT16;;
Asciz	()TT15;;
Asciz	()TT14;;
Asciz	()TT13;;
Asciz	()TT12;;
Asciz	()TT11;;
Asciz	()TT10;;
Asciz	()TT9;;
Asciz	()TT8;;
Asciz	()TT7;;
Asciz	()TT6;;
Asciz	()TT5;;
Asciz	()TT4;;
Asciz	()TT3;;
Asciz	()TT2;;
Asciz	()TT1;;
Asciz	copy$default$1;
Asciz	copy$default$2;
Asciz	copy$default$3;
Asciz	copy$default$4;
Asciz	copy$default$5;
Asciz	copy$default$6;
Asciz	copy$default$7;
Asciz	copy$default$8;
Asciz	copy$default$9;
Asciz	copy$default$10;
Asciz	copy$default$11;
Asciz	copy$default$12;
Asciz	copy$default$13;
Asciz	copy$default$14;
Asciz	copy$default$15;
Asciz	copy$default$16;
Asciz	copy$default$17;
Asciz	copy$default$18;
Asciz	copy$default$19;
Asciz	copy$default$20;
Asciz	copy$default$21;
Asciz	productElements;
Asciz	()Lscala/collection/Iterator;;
Asciz	(Lscala/Product;)Lscala/collection/Iterator;;
NameAndType	productElements:(Lscala/Product;)Lscala/collection/Iterator;
Method	scala/Product$class.productElements:(Lscala/Product;)Lscala/collection/Iterator;
Asciz	Deprecated;
Asciz	productIterator;
NameAndType	productIterator:(Lscala/Product;)Lscala/collection/Iterator;
Method	scala/Product$class.productIterator:(Lscala/Product;)Lscala/collection/Iterator;
Asciz	productElement;
Asciz	(I)Ljava/lang/Object;;
Asciz	(Lscala/Product21;I)Ljava/lang/Object;;
NameAndType	productElement:(Lscala/Product21;I)Ljava/lang/Object;
Method	scala/Product21$class.productElement:(Lscala/Product21;I)Ljava/lang/Object;
Asciz	n;
Asciz	I;
Asciz	java/lang/IndexOutOfBoundsException;
class	java/lang/IndexOutOfBoundsException
Asciz	Exceptions;
Asciz	productArity;
Asciz	(Lscala/Product21;)I;
NameAndType	productArity:(Lscala/Product21;)I
Method	scala/Product21$class.productArity:(Lscala/Product21;)I
Asciz	<T1:Ljava/lang/Object;T2:Ljava/lang/Object;T3:Ljava/lang/Object;T4:Ljava/lang/Object;T5:Ljava/lang/Object;T6:Ljava/lang/Object;T7:Ljava/lang/Object;T8:Ljava/lang/Object;T9:Ljava/lang/Object;T10:Ljava/lang/Object;T11:Ljava/lang/Object;T12:Ljava/lang/Object;T13:Ljava/lang/Object;T14:Ljava/lang/Object;T15:Ljava/lang/Object;T16:Ljava/lang/Object;T17:Ljava/lang/Object;T18:Ljava/lang/Object;T19:Ljava/lang/Object;T20:Ljava/lang/Object;T21:Ljava/lang/Object;>Ljava/lang/Object;Lscala/Product21<TT1;TT2;TT3;TT4;TT5;TT6;TT7;TT8;TT9;TT10;TT11;TT12;TT13;TT14;TT15;TT16;TT17;TT18;TT19;TT20;TT21;>;Lscala/ScalaObject;Lscala/Product;;
Asciz	ScalaSig;
Asciz	scala/Product21;
class	scala/Product21
Asciz	scala/ScalaObject;
class	scala/ScalaObject
Asciz	scala/Product;
class	scala/Product
Asciz	java/io/Serializable;
class	java/io/Serializable

{
private final java.lang.Object _21;
  Signature: Ljava/lang/Object;
  Signature: length = 0x2
   00 05 

private final java.lang.Object _20;
  Signature: Ljava/lang/Object;
  Signature: length = 0x2
   00 08 

private final java.lang.Object _19;
  Signature: Ljava/lang/Object;
  Signature: length = 0x2
   00 0A 

private final java.lang.Object _18;
  Signature: Ljava/lang/Object;
  Signature: length = 0x2
   00 0C 

private final java.lang.Object _17;
  Signature: Ljava/lang/Object;
  Signature: length = 0x2
   00 0E 

private final java.lang.Object _16;
  Signature: Ljava/lang/Object;
  Signature: length = 0x2
   00 10 

private final java.lang.Object _15;
  Signature: Ljava/lang/Object;
  Signature: length = 0x2
   00 12 

private final java.lang.Object _14;
  Signature: Ljava/lang/Object;
  Signature: length = 0x2
   00 14 

private final java.lang.Object _13;
  Signature: Ljava/lang/Object;
  Signature: length = 0x2
   00 16 

private final java.lang.Object _12;
  Signature: Ljava/lang/Object;
  Signature: length = 0x2
   00 18 

private final java.lang.Object _11;
  Signature: Ljava/lang/Object;
  Signature: length = 0x2
   00 1A 

private final java.lang.Object _10;
  Signature: Ljava/lang/Object;
  Signature: length = 0x2
   00 1C 

private final java.lang.Object _9;
  Signature: Ljava/lang/Object;
  Signature: length = 0x2
   00 1E 

private final java.lang.Object _8;
  Signature: Ljava/lang/Object;
  Signature: length = 0x2
   00 20 

private final java.lang.Object _7;
  Signature: Ljava/lang/Object;
  Signature: length = 0x2
   00 22 

private final java.lang.Object _6;
  Signature: Ljava/lang/Object;
  Signature: length = 0x2
   00 24 

private final java.lang.Object _5;
  Signature: Ljava/lang/Object;
  Signature: length = 0x2
   00 26 

private final java.lang.Object _4;
  Signature: Ljava/lang/Object;
  Signature: length = 0x2
   00 28 

private final java.lang.Object _3;
  Signature: Ljava/lang/Object;
  Signature: length = 0x2
   00 2A 

private final java.lang.Object _2;
  Signature: Ljava/lang/Object;
  Signature: length = 0x2
   00 2C 

private final java.lang.Object _1;
  Signature: Ljava/lang/Object;
  Signature: length = 0x2
   00 2E 

public scala.Tuple21(java.lang.Object, java.lang.Object, java.lang.Object, java.lang.Object, java.lang.Object, java.lang.Object, java.lang.Object, java.lang.Object, java.lang.Object, java.lang.Object, java.lang.Object, java.lang.Object, java.lang.Object, java.lang.Object, java.lang.Object, java.lang.Object, java.lang.Object, java.lang.Object, java.lang.Object, java.lang.Object, java.lang.Object);
  Signature: (Ljava/lang/Object;Ljava/lang/Object;Ljava/lang/Object;Ljava/lang/Object;Ljava/lang/Object;Ljava/lang/Object;Ljava/lang/Object;Ljava/lang/Object;Ljava/lang/Object;Ljava/lang/Object;Ljava/lang/Object;Ljava/lang/Object;Ljava/lang/Object;Ljava/lang/Object;Ljava/lang/Object;Ljava/lang/Object;Ljava/lang/Object;Ljava/lang/Object;Ljava/lang/Object;Ljava/lang/Object;Ljava/lang/Object;)V
  Code:
   Stack=2, Locals=22, Args_size=22
	aload_0
	aload_1
	putfield	Field _1:Ljava/lang/Object;
	aload_0
	aload_2
	putfield	Field _2:Ljava/lang/Object;
	aload_0
	aload_3
	putfield	Field _3:Ljava/lang/Object;
	aload_0
	aload	4
	putfield	Field _4:Ljava/lang/Object;
	aload_0
	aload	5
	putfield	Field _5:Ljava/lang/Object;
	aload_0
	aload	6
	putfield	Field _6:Ljava/lang/Object;
	aload_0
	aload	7
	putfield	Field _7:Ljava/lang/Object;
	aload_0
	aload	8
	putfield	Field _8:Ljava/lang/Object;
	aload_0
	aload	9
	putfield	Field _9:Ljava/lang/Object;
	aload_0
	aload	10
	putfield	Field _10:Ljava/lang/Object;
	aload_0
	aload	11
	putfield	Field _11:Ljava/lang/Object;
	aload_0
	aload	12
	putfield	Field _12:Ljava/lang/Object;
	aload_0
	aload	13
	putfield	Field _13:Ljava/lang/Object;
	aload_0
	aload	14
	putfield	Field _14:Ljava/lang/Object;
	aload_0
	aload	15
	putfield	Field _15:Ljava/lang/Object;
	aload_0
	aload	16
	putfield	Field _16:Ljava/lang/Object;
	aload_0
	aload	17
	putfield	Field _17:Ljava/lang/Object;
	aload_0
	aload	18
	putfield	Field _18:Ljava/lang/Object;
	aload_0
	aload	19
	putfield	Field _19:Ljava/lang/Object;
	aload_0
	aload	20
	putfield	Field _20:Ljava/lang/Object;
	aload_0
	aload	21
	putfield	Field _21:Ljava/lang/Object;
	aload_0
	invokespecial	Method java/lang/Object."<init>":()V
	aload_0
	invokestatic	Method scala/Product$class.$init$:(Lscala/Product;)V
	aload_0
	invokestatic	Method scala/Product21$class.$init$:(Lscala/Product21;)V
	return
  Labels:
  LocalVariableTable: 
   Start  Length  Slot  Name   Signature
   0      136      0    this       Lscala/Tuple21;
   0      136      1    _1       Ljava/lang/Object;
   0      136      2    _2       Ljava/lang/Object;
   0      136      3    _3       Ljava/lang/Object;
   0      136      4    _4       Ljava/lang/Object;
   0      136      5    _5       Ljava/lang/Object;
   0      136      6    _6       Ljava/lang/Object;
   0      136      7    _7       Ljava/lang/Object;
   0      136      8    _8       Ljava/lang/Object;
   0      136      9    _9       Ljava/lang/Object;
   0      136      10    _10       Ljava/lang/Object;
   0      136      11    _11       Ljava/lang/Object;
   0      136      12    _12       Ljava/lang/Object;
   0      136      13    _13       Ljava/lang/Object;
   0      136      14    _14       Ljava/lang/Object;
   0      136      15    _15       Ljava/lang/Object;
   0      136      16    _16       Ljava/lang/Object;
   0      136      17    _17       Ljava/lang/Object;
   0      136      18    _18       Ljava/lang/Object;
   0      136      19    _19       Ljava/lang/Object;
   0      136      20    _20       Ljava/lang/Object;
   0      136      21    _21       Ljava/lang/Object;

  Signature: length = 0x2
   00 72 

private final boolean gd1$1(java.lang.Object, java.lang.Object, java.lang.Object, java.lang.Object, java.lang.Object, java.lang.Object, java.lang.Object, java.lang.Object, java.lang.Object, java.lang.Object, java.lang.Object, java.lang.Object, java.lang.Object, java.lang.Object, java.lang.Object, java.lang.Object, java.lang.Object, java.lang.Object, java.lang.Object, java.lang.Object, java.lang.Object);
  Signature: (Ljava/lang/Object;Ljava/lang/Object;Ljava/lang/Object;Ljava/lang/Object;Ljava/lang/Object;Ljava/lang/Object;Ljava/lang/Object;Ljava/lang/Object;Ljava/lang/Object;Ljava/lang/Object;Ljava/lang/Object;Ljava/lang/Object;Ljava/lang/Object;Ljava/lang/Object;Ljava/lang/Object;Ljava/lang/Object;Ljava/lang/Object;Ljava/lang/Object;Ljava/lang/Object;Ljava/lang/Object;Ljava/lang/Object;)Z
  Code:
   Stack=3, Locals=37, Args_size=22
	aload_0
	invokevirtual	Method _1:()Ljava/lang/Object;
	astore	22
	aload_1
	aload	22
	if_acmpne	l1 // aload_1
	iconst_1
	goto	l2 // ifeq
l1	aload_1
	ifnonnull	l3 // aload_1
	iconst_0
	goto	l2 // ifeq
l3	aload_1
	instanceof	class java/lang/Number
	ifne	l4 // aload_1
	aload_1
	instanceof	class java/lang/Character
	ifeq	l5 // aload_1
l4	aload_1
	aload	22
	invokestatic	Method scala/runtime/BoxesRunTime.equals2:(Ljava/lang/Object;Ljava/lang/Object;)Z
	goto	l2 // ifeq
l5	aload_1
	aload	22
	invokevirtual	Method java/lang/Object.equals:(Ljava/lang/Object;)Z
l2	ifeq	l6 // iconst_0
	aload_0
	invokevirtual	Method _2:()Ljava/lang/Object;
	astore	23
	aload_2
	aload	23
	if_acmpne	l7 // aload_2
	iconst_1
	goto	l8 // ifeq
l7	aload_2
	ifnonnull	l9 // aload_2
	iconst_0
	goto	l8 // ifeq
l9	aload_2
	instanceof	class java/lang/Number
	ifne	l10 // aload_2
	aload_2
	instanceof	class java/lang/Character
	ifeq	l11 // aload_2
l10	aload_2
	aload	23
	invokestatic	Method scala/runtime/BoxesRunTime.equals2:(Ljava/lang/Object;Ljava/lang/Object;)Z
	goto	l8 // ifeq
l11	aload_2
	aload	23
	invokevirtual	Method java/lang/Object.equals:(Ljava/lang/Object;)Z
l8	ifeq	l6 // iconst_0
	aload_0
	invokevirtual	Method _3:()Ljava/lang/Object;
	astore	24
	aload_3
	aload	24
	if_acmpne	l12 // aload_3
	iconst_1
	goto	l13 // ifeq
l12	aload_3
	ifnonnull	l14 // aload_3
	iconst_0
	goto	l13 // ifeq
l14	aload_3
	instanceof	class java/lang/Number
	ifne	l15 // aload_3
	aload_3
	instanceof	class java/lang/Character
	ifeq	l16 // aload_3
l15	aload_3
	aload	24
	invokestatic	Method scala/runtime/BoxesRunTime.equals2:(Ljava/lang/Object;Ljava/lang/Object;)Z
	goto	l13 // ifeq
l16	aload_3
	aload	24
	invokevirtual	Method java/lang/Object.equals:(Ljava/lang/Object;)Z
l13	ifeq	l6 // iconst_0
	aload_0
	invokevirtual	Method _4:()Ljava/lang/Object;
	astore	25
	aload	4
	aload	25
	if_acmpne	l17 // aload
	iconst_1
	goto	l18 // ifeq
l17	aload	4
	ifnonnull	l19 // aload
	iconst_0
	goto	l18 // ifeq
l19	aload	4
	instanceof	class java/lang/Number
	ifne	l20 // aload
	aload	4
	instanceof	class java/lang/Character
	ifeq	l21 // aload
l20	aload	4
	aload	25
	invokestatic	Method scala/runtime/BoxesRunTime.equals2:(Ljava/lang/Object;Ljava/lang/Object;)Z
	goto	l18 // ifeq
l21	aload	4
	aload	25
	invokevirtual	Method java/lang/Object.equals:(Ljava/lang/Object;)Z
l18	ifeq	l6 // iconst_0
	aload_0
	invokevirtual	Method _5:()Ljava/lang/Object;
	astore	26
	aload	5
	aload	26
	if_acmpne	l22 // aload
	iconst_1
	goto	l23 // ifeq
l22	aload	5
	ifnonnull	l24 // aload
	iconst_0
	goto	l23 // ifeq
l24	aload	5
	instanceof	class java/lang/Number
	ifne	l25 // aload
	aload	5
	instanceof	class java/lang/Character
	ifeq	l26 // aload
l25	aload	5
	aload	26
	invokestatic	Method scala/runtime/BoxesRunTime.equals2:(Ljava/lang/Object;Ljava/lang/Object;)Z
	goto	l23 // ifeq
l26	aload	5
	aload	26
	invokevirtual	Method java/lang/Object.equals:(Ljava/lang/Object;)Z
l23	ifeq	l6 // iconst_0
	aload_0
	invokevirtual	Method _6:()Ljava/lang/Object;
	astore	27
	aload	6
	aload	27
	if_acmpne	l27 // aload
	iconst_1
	goto	l28 // ifeq
l27	aload	6
	ifnonnull	l29 // aload
	iconst_0
	goto	l28 // ifeq
l29	aload	6
	instanceof	class java/lang/Number
	ifne	l30 // aload
	aload	6
	instanceof	class java/lang/Character
	ifeq	l31 // aload
l30	aload	6
	aload	27
	invokestatic	Method scala/runtime/BoxesRunTime.equals2:(Ljava/lang/Object;Ljava/lang/Object;)Z
	goto	l28 // ifeq
l31	aload	6
	aload	27
	invokevirtual	Method java/lang/Object.equals:(Ljava/lang/Object;)Z
l28	ifeq	l6 // iconst_0
	aload_0
	invokevirtual	Method _7:()Ljava/lang/Object;
	astore	28
	aload	7
	aload	28
	if_acmpne	l32 // aload
	iconst_1
	goto	l33 // ifeq
l32	aload	7
	ifnonnull	l34 // aload
	iconst_0
	goto	l33 // ifeq
l34	aload	7
	instanceof	class java/lang/Number
	ifne	l35 // aload
	aload	7
	instanceof	class java/lang/Character
	ifeq	l36 // aload
l35	aload	7
	aload	28
	invokestatic	Method scala/runtime/BoxesRunTime.equals2:(Ljava/lang/Object;Ljava/lang/Object;)Z
	goto	l33 // ifeq
l36	aload	7
	aload	28
	invokevirtual	Method java/lang/Object.equals:(Ljava/lang/Object;)Z
l33	ifeq	l6 // iconst_0
	aload_0
	invokevirtual	Method _8:()Ljava/lang/Object;
	astore	29
	aload	8
	aload	29
	if_acmpne	l37 // aload
	iconst_1
	goto	l38 // ifeq
l37	aload	8
	ifnonnull	l39 // aload
	iconst_0
	goto	l38 // ifeq
l39	aload	8
	instanceof	class java/lang/Number
	ifne	l40 // aload
	aload	8
	instanceof	class java/lang/Character
	ifeq	l41 // aload
l40	aload	8
	aload	29
	invokestatic	Method scala/runtime/BoxesRunTime.equals2:(Ljava/lang/Object;Ljava/lang/Object;)Z
	goto	l38 // ifeq
l41	aload	8
	aload	29
	invokevirtual	Method java/lang/Object.equals:(Ljava/lang/Object;)Z
l38	ifeq	l6 // iconst_0
	aload_0
	invokevirtual	Method _9:()Ljava/lang/Object;
	astore	30
	aload	9
	aload	30
	if_acmpne	l42 // aload
	iconst_1
	goto	l43 // ifeq
l42	aload	9
	ifnonnull	l44 // aload
	iconst_0
	goto	l43 // ifeq
l44	aload	9
	instanceof	class java/lang/Number
	ifne	l45 // aload
	aload	9
	instanceof	class java/lang/Character
	ifeq	l46 // aload
l45	aload	9
	aload	30
	invokestatic	Method scala/runtime/BoxesRunTime.equals2:(Ljava/lang/Object;Ljava/lang/Object;)Z
	goto	l43 // ifeq
l46	aload	9
	aload	30
	invokevirtual	Method java/lang/Object.equals:(Ljava/lang/Object;)Z
l43	ifeq	l6 // iconst_0
	aload_0
	invokevirtual	Method _10:()Ljava/lang/Object;
	astore	31
	aload	10
	aload	31
	if_acmpne	l47 // aload
	iconst_1
	goto	l48 // ifeq
l47	aload	10
	ifnonnull	l49 // aload
	iconst_0
	goto	l48 // ifeq
l49	aload	10
	instanceof	class java/lang/Number
	ifne	l50 // aload
	aload	10
	instanceof	class java/lang/Character
	ifeq	l51 // aload
l50	aload	10
	aload	31
	invokestatic	Method scala/runtime/BoxesRunTime.equals2:(Ljava/lang/Object;Ljava/lang/Object;)Z
	goto	l48 // ifeq
l51	aload	10
	aload	31
	invokevirtual	Method java/lang/Object.equals:(Ljava/lang/Object;)Z
l48	ifeq	l6 // iconst_0
	aload_0
	invokevirtual	Method _11:()Ljava/lang/Object;
	astore	32
	aload	11
	aload	32
	if_acmpne	l52 // aload
	iconst_1
	goto	l53 // ifeq
l52	aload	11
	ifnonnull	l54 // aload
	iconst_0
	goto	l53 // ifeq
l54	aload	11
	instanceof	class java/lang/Number
	ifne	l55 // aload
	aload	11
	instanceof	class java/lang/Character
	ifeq	l56 // aload
l55	aload	11
	aload	32
	invokestatic	Method scala/runtime/BoxesRunTime.equals2:(Ljava/lang/Object;Ljava/lang/Object;)Z
	goto	l53 // ifeq
l56	aload	11
	aload	32
	invokevirtual	Method java/lang/Object.equals:(Ljava/lang/Object;)Z
l53	ifeq	l6 // iconst_0
	aload_0
	invokevirtual	Method _12:()Ljava/lang/Object;
	astore	33
	aload	12
	aload	33
	if_acmpne	l57 // aload
	iconst_1
	goto	l58 // ifeq
l57	aload	12
	ifnonnull	l59 // aload
	iconst_0
	goto	l58 // ifeq
l59	aload	12
	instanceof	class java/lang/Number
	ifne	l60 // aload
	aload	12
	instanceof	class java/lang/Character
	ifeq	l61 // aload
l60	aload	12
	aload	33
	invokestatic	Method scala/runtime/BoxesRunTime.equals2:(Ljava/lang/Object;Ljava/lang/Object;)Z
	goto	l58 // ifeq
l61	aload	12
	aload	33
	invokevirtual	Method java/lang/Object.equals:(Ljava/lang/Object;)Z
l58	ifeq	l6 // iconst_0
	aload_0
	invokevirtual	Method _13:()Ljava/lang/Object;
	astore	34
	aload	13
	aload	34
	if_acmpne	l62 // aload
	iconst_1
	goto	l63 // ifeq
l62	aload	13
	ifnonnull	l64 // aload
	iconst_0
	goto	l63 // ifeq
l64	aload	13
	instanceof	class java/lang/Number
	ifne	l65 // aload
	aload	13
	instanceof	class java/lang/Character
	ifeq	l66 // aload
l65	aload	13
	aload	34
	invokestatic	Method scala/runtime/BoxesRunTime.equals2:(Ljava/lang/Object;Ljava/lang/Object;)Z
	goto	l63 // ifeq
l66	aload	13
	aload	34
	invokevirtual	Method java/lang/Object.equals:(Ljava/lang/Object;)Z
l63	ifeq	l6 // iconst_0
	aload_0
	invokevirtual	Method _14:()Ljava/lang/Object;
	astore	35
	aload	14
	aload	35
	if_acmpne	l67 // aload
	iconst_1
	goto	l68 // ifeq
l67	aload	14
	ifnonnull	l69 // aload
	iconst_0
	goto	l68 // ifeq
l69	aload	14
	instanceof	class java/lang/Number
	ifne	l70 // aload
	aload	14
	instanceof	class java/lang/Character
	ifeq	l71 // aload
l70	aload	14
	aload	35
	invokestatic	Method scala/runtime/BoxesRunTime.equals2:(Ljava/lang/Object;Ljava/lang/Object;)Z
	goto	l68 // ifeq
l71	aload	14
	aload	35
	invokevirtual	Method java/lang/Object.equals:(Ljava/lang/Object;)Z
l68	ifeq	l6 // iconst_0
	aload_0
	invokevirtual	Method _15:()Ljava/lang/Object;
	astore	36
	aload	15
	aload	36
	if_acmpne	l72 // aload
	iconst_1
	goto	l73 // ifeq
l72	aload	15
	ifnonnull	l74 // aload
	iconst_0
	goto	l73 // ifeq
l74	aload	15
	instanceof	class java/lang/Number
	ifne	l75 // aload
	aload	15
	instanceof	class java/lang/Character
	ifeq	l76 // aload
l75	aload	15
	aload	36
	invokestatic	Method scala/runtime/BoxesRunTime.equals2:(Ljava/lang/Object;Ljava/lang/Object;)Z
	goto	l73 // ifeq
l76	aload	15
	aload	36
	invokevirtual	Method java/lang/Object.equals:(Ljava/lang/Object;)Z
l73	ifeq	l6 // iconst_0
	getstatic	Field scala/runtime/ScalaRunTime$.MODULE$:Lscala/runtime/ScalaRunTime$;
	aload	16
	aload_0
	invokevirtual	Method _16:()Ljava/lang/Object;
	invokevirtual	Method scala/runtime/ScalaRunTime$.inlinedEquals:(Ljava/lang/Object;Ljava/lang/Object;)Z
	ifeq	l6 // iconst_0
	getstatic	Field scala/runtime/ScalaRunTime$.MODULE$:Lscala/runtime/ScalaRunTime$;
	aload	17
	aload_0
	invokevirtual	Method _17:()Ljava/lang/Object;
	invokevirtual	Method scala/runtime/ScalaRunTime$.inlinedEquals:(Ljava/lang/Object;Ljava/lang/Object;)Z
	ifeq	l6 // iconst_0
	getstatic	Field scala/runtime/ScalaRunTime$.MODULE$:Lscala/runtime/ScalaRunTime$;
	aload	18
	aload_0
	invokevirtual	Method _18:()Ljava/lang/Object;
	invokevirtual	Method scala/runtime/ScalaRunTime$.inlinedEquals:(Ljava/lang/Object;Ljava/lang/Object;)Z
	ifeq	l6 // iconst_0
	getstatic	Field scala/runtime/ScalaRunTime$.MODULE$:Lscala/runtime/ScalaRunTime$;
	aload	19
	aload_0
	invokevirtual	Method _19:()Ljava/lang/Object;
	invokevirtual	Method scala/runtime/ScalaRunTime$.inlinedEquals:(Ljava/lang/Object;Ljava/lang/Object;)Z
	ifeq	l6 // iconst_0
	getstatic	Field scala/runtime/ScalaRunTime$.MODULE$:Lscala/runtime/ScalaRunTime$;
	aload	20
	aload_0
	invokevirtual	Method _20:()Ljava/lang/Object;
	invokevirtual	Method scala/runtime/ScalaRunTime$.inlinedEquals:(Ljava/lang/Object;Ljava/lang/Object;)Z
	ifeq	l6 // iconst_0
	getstatic	Field scala/runtime/ScalaRunTime$.MODULE$:Lscala/runtime/ScalaRunTime$;
	aload	21
	aload_0
	invokevirtual	Method _21:()Ljava/lang/Object;
	invokevirtual	Method scala/runtime/ScalaRunTime$.inlinedEquals:(Ljava/lang/Object;Ljava/lang/Object;)Z
	ifeq	l6 // iconst_0
	iconst_1
	goto	l77 // ireturn
l6	iconst_0
l77	ireturn
  Labels:
   	l1 = 16 // aload_1
   	l3 = 24 // aload_1
   	l4 = 38 // aload_1
   	l5 = 47 // aload_1
   	l2 = 53 // ifeq
   	l7 = 72 // aload_2
   	l9 = 80 // aload_2
   	l10 = 94 // aload_2
   	l11 = 103 // aload_2
   	l8 = 109 // ifeq
   	l12 = 128 // aload_3
   	l14 = 136 // aload_3
   	l15 = 150 // aload_3
   	l16 = 159 // aload_3
   	l13 = 165 // ifeq
   	l17 = 185 // aload
   	l19 = 194 // aload
   	l20 = 210 // aload
   	l21 = 220 // aload
   	l18 = 227 // ifeq
   	l22 = 247 // aload
   	l24 = 256 // aload
   	l25 = 272 // aload
   	l26 = 282 // aload
   	l23 = 289 // ifeq
   	l27 = 309 // aload
   	l29 = 318 // aload
   	l30 = 334 // aload
   	l31 = 344 // aload
   	l28 = 351 // ifeq
   	l32 = 371 // aload
   	l34 = 380 // aload
   	l35 = 396 // aload
   	l36 = 406 // aload
   	l33 = 413 // ifeq
   	l37 = 433 // aload
   	l39 = 442 // aload
   	l40 = 458 // aload
   	l41 = 468 // aload
   	l38 = 475 // ifeq
   	l42 = 495 // aload
   	l44 = 504 // aload
   	l45 = 520 // aload
   	l46 = 530 // aload
   	l43 = 537 // ifeq
   	l47 = 557 // aload
   	l49 = 566 // aload
   	l50 = 582 // aload
   	l51 = 592 // aload
   	l48 = 599 // ifeq
   	l52 = 619 // aload
   	l54 = 628 // aload
   	l55 = 644 // aload
   	l56 = 654 // aload
   	l53 = 661 // ifeq
   	l57 = 681 // aload
   	l59 = 690 // aload
   	l60 = 706 // aload
   	l61 = 716 // aload
   	l58 = 723 // ifeq
   	l62 = 743 // aload
   	l64 = 752 // aload
   	l65 = 768 // aload
   	l66 = 778 // aload
   	l63 = 785 // ifeq
   	l67 = 805 // aload
   	l69 = 814 // aload
   	l70 = 830 // aload
   	l71 = 840 // aload
   	l68 = 847 // ifeq
   	l72 = 867 // aload
   	l74 = 876 // aload
   	l75 = 892 // aload
   	l76 = 902 // aload
   	l73 = 909 // ifeq
   	l6 = 1006 // iconst_0
   	l77 = 1007 // ireturn
  LocalVariableTable: 
   Start  Length  Slot  Name   Signature
   0      1008      0    this       Lscala/Tuple21;
   12      44      22    y0       Ljava/lang/Object;
   68      44      23    y1       Ljava/lang/Object;
   124      44      24    y2       Ljava/lang/Object;
   181      49      25    y3       Ljava/lang/Object;
   243      49      26    y4       Ljava/lang/Object;
   305      49      27    y5       Ljava/lang/Object;
   367      49      28    y6       Ljava/lang/Object;
   429      49      29    y7       Ljava/lang/Object;
   491      49      30    y8       Ljava/lang/Object;
   553      49      31    y9       Ljava/lang/Object;
   615      49      32    y10       Ljava/lang/Object;
   677      49      33    y11       Ljava/lang/Object;
   739      49      34    y12       Ljava/lang/Object;
   801      49      35    y13       Ljava/lang/Object;
   863      49      36    y14       Ljava/lang/Object;


public boolean canEqual(java.lang.Object);
  Signature: (Ljava/lang/Object;)Z
  Code:
   Stack=1, Locals=2, Args_size=2
	aload_1
	instanceof	class scala/Tuple21
	ireturn
  Labels:

public java.lang.String productPrefix();
  Signature: ()Ljava/lang/String;
  Code:
   Stack=1, Locals=1, Args_size=1
	ldc	String Tuple21
	areturn
  Labels:

public boolean equals(java.lang.Object);
  Signature: (Ljava/lang/Object;)Z
  Code:
   Stack=22, Locals=24, Args_size=2
	aload_0
	aload_1
	if_acmpeq	l1 // iconst_1
	aload_1
	instanceof	class scala/Tuple21
	ifeq	l2 // iconst_1
	aload_1
	checkcast	class scala/Tuple21
	astore_2
	aload_2
	invokevirtual	Method _1:()Ljava/lang/Object;
	astore_3
	aload_2
	invokevirtual	Method _2:()Ljava/lang/Object;
	astore	4
	aload_2
	invokevirtual	Method _3:()Ljava/lang/Object;
	astore	5
	aload_2
	invokevirtual	Method _4:()Ljava/lang/Object;
	astore	6
	aload_2
	invokevirtual	Method _5:()Ljava/lang/Object;
	astore	7
	aload_2
	invokevirtual	Method _6:()Ljava/lang/Object;
	astore	8
	aload_2
	invokevirtual	Method _7:()Ljava/lang/Object;
	astore	9
	aload_2
	invokevirtual	Method _8:()Ljava/lang/Object;
	astore	10
	aload_2
	invokevirtual	Method _9:()Ljava/lang/Object;
	astore	11
	aload_2
	invokevirtual	Method _10:()Ljava/lang/Object;
	astore	12
	aload_2
	invokevirtual	Method _11:()Ljava/lang/Object;
	astore	13
	aload_2
	invokevirtual	Method _12:()Ljava/lang/Object;
	astore	14
	aload_2
	invokevirtual	Method _13:()Ljava/lang/Object;
	astore	15
	aload_2
	invokevirtual	Method _14:()Ljava/lang/Object;
	astore	16
	aload_2
	invokevirtual	Method _15:()Ljava/lang/Object;
	astore	17
	aload_2
	invokevirtual	Method _16:()Ljava/lang/Object;
	astore	18
	aload_2
	invokevirtual	Method _17:()Ljava/lang/Object;
	astore	19
	aload_2
	invokevirtual	Method _18:()Ljava/lang/Object;
	astore	20
	aload_2
	invokevirtual	Method _19:()Ljava/lang/Object;
	astore	21
	aload_2
	invokevirtual	Method _20:()Ljava/lang/Object;
	astore	22
	aload_2
	invokevirtual	Method _21:()Ljava/lang/Object;
	astore	23
	aload_0
	aload_3
	aload	4
	aload	5
	aload	6
	aload	7
	aload	8
	aload	9
	aload	10
	aload	11
	aload	12
	aload	13
	aload	14
	aload	15
	aload	16
	aload	17
	aload	18
	aload	19
	aload	20
	aload	21
	aload	22
	aload	23
	invokespecial	Method gd1$1:(Ljava/lang/Object;Ljava/lang/Object;Ljava/lang/Object;Ljava/lang/Object;Ljava/lang/Object;Ljava/lang/Object;Ljava/lang/Object;Ljava/lang/Object;Ljava/lang/Object;Ljava/lang/Object;Ljava/lang/Object;Ljava/lang/Object;Ljava/lang/Object;Ljava/lang/Object;Ljava/lang/Object;Ljava/lang/Object;Ljava/lang/Object;Ljava/lang/Object;Ljava/lang/Object;Ljava/lang/Object;Ljava/lang/Object;)Z
	ifeq	l3 // iconst_1
	aload_1
	checkcast	class scala/Tuple21
	aload_0
	invokeinterface	InterfaceMethod scala/Equals.canEqual:(Ljava/lang/Object;)Z
	goto	l4 // ifeq
l3	iconst_1
	ifeq	l5 // new
	iconst_0
	goto	l4 // ifeq
l5	new	class scala/MatchError
	dup
	aload_1
	invokevirtual	Method java/lang/Object.toString:()Ljava/lang/String;
	invokespecial	Method scala/MatchError."<init>":(Ljava/lang/String;)V
	athrow
l2	iconst_1
	ifeq	l6 // new
	iconst_0
l4	ifeq	l7 // iconst_0
l1	iconst_1
	goto	l8 // ireturn
l7	iconst_0
l8	ireturn
l6	new	class scala/MatchError
	dup
	aload_1
	invokevirtual	Method java/lang/Object.toString:()Ljava/lang/String;
	invokespecial	Method scala/MatchError."<init>":(Ljava/lang/String;)V
	athrow
  Labels:
   	l3 = 203 // iconst_1
   	l5 = 211 // new
   	l2 = 223 // iconst_1
   	l4 = 228 // ifeq
   	l1 = 231 // iconst_1
   	l7 = 235 // iconst_0
   	l8 = 236 // ireturn
   	l6 = 237 // new
  LocalVariableTable: 
   Start  Length  Slot  Name   Signature
   0      249      0    this       Lscala/Tuple21;
   17      206      2    temp2       Lscala/Tuple21;
   22      201      3    temp3       Ljava/lang/Object;
   28      195      4    temp4       Ljava/lang/Object;
   34      189      5    temp5       Ljava/lang/Object;
   40      183      6    temp6       Ljava/lang/Object;
   46      177      7    temp7       Ljava/lang/Object;
   52      171      8    temp8       Ljava/lang/Object;
   58      165      9    temp9       Ljava/lang/Object;
   64      159      10    temp10       Ljava/lang/Object;
   70      153      11    temp11       Ljava/lang/Object;
   76      147      12    temp12       Ljava/lang/Object;
   82      141      13    temp13       Ljava/lang/Object;
   88      135      14    temp14       Ljava/lang/Object;
   94      129      15    temp15       Ljava/lang/Object;
   100      123      16    temp16       Ljava/lang/Object;
   106      117      17    temp17       Ljava/lang/Object;
   112      111      18    temp18       Ljava/lang/Object;
   118      105      19    temp19       Ljava/lang/Object;
   124      99      20    temp20       Ljava/lang/Object;
   130      93      21    temp21       Ljava/lang/Object;
   136      87      22    temp22       Ljava/lang/Object;
   142      81      23    temp23       Ljava/lang/Object;


public int hashCode();
  Signature: ()I
  Code:
   Stack=2, Locals=1, Args_size=1
	getstatic	Field scala/runtime/ScalaRunTime$.MODULE$:Lscala/runtime/ScalaRunTime$;
	aload_0
	invokevirtual	Method scala/runtime/ScalaRunTime$._hashCode:(Lscala/Product;)I
	ireturn
  Labels:

public scala.Tuple21 copy(java.lang.Object, java.lang.Object, java.lang.Object, java.lang.Object, java.lang.Object, java.lang.Object, java.lang.Object, java.lang.Object, java.lang.Object, java.lang.Object, java.lang.Object, java.lang.Object, java.lang.Object, java.lang.Object, java.lang.Object, java.lang.Object, java.lang.Object, java.lang.Object, java.lang.Object, java.lang.Object, java.lang.Object);
  Signature: (Ljava/lang/Object;Ljava/lang/Object;Ljava/lang/Object;Ljava/lang/Object;Ljava/lang/Object;Ljava/lang/Object;Ljava/lang/Object;Ljava/lang/Object;Ljava/lang/Object;Ljava/lang/Object;Ljava/lang/Object;Ljava/lang/Object;Ljava/lang/Object;Ljava/lang/Object;Ljava/lang/Object;Ljava/lang/Object;Ljava/lang/Object;Ljava/lang/Object;Ljava/lang/Object;Ljava/lang/Object;Ljava/lang/Object;)Lscala/Tuple21;
  Code:
   Stack=23, Locals=22, Args_size=22
	new	class scala/Tuple21
	dup
	aload_1
	aload_2
	aload_3
	aload	4
	aload	5
	aload	6
	aload	7
	aload	8
	aload	9
	aload	10
	aload	11
	aload	12
	aload	13
	aload	14
	aload	15
	aload	16
	aload	17
	aload	18
	aload	19
	aload	20
	aload	21
	invokespecial	Method "<init>":(Ljava/lang/Object;Ljava/lang/Object;Ljava/lang/Object;Ljava/lang/Object;Ljava/lang/Object;Ljava/lang/Object;Ljava/lang/Object;Ljava/lang/Object;Ljava/lang/Object;Ljava/lang/Object;Ljava/lang/Object;Ljava/lang/Object;Ljava/lang/Object;Ljava/lang/Object;Ljava/lang/Object;Ljava/lang/Object;Ljava/lang/Object;Ljava/lang/Object;Ljava/lang/Object;Ljava/lang/Object;Ljava/lang/Object;)V
	areturn
  Labels:
  LocalVariableTable: 
   Start  Length  Slot  Name   Signature
   0      47      0    this       Lscala/Tuple21;
   0      47      1    _1       Ljava/lang/Object;
   0      47      2    _2       Ljava/lang/Object;
   0      47      3    _3       Ljava/lang/Object;
   0      47      4    _4       Ljava/lang/Object;
   0      47      5    _5       Ljava/lang/Object;
   0      47      6    _6       Ljava/lang/Object;
   0      47      7    _7       Ljava/lang/Object;
   0      47      8    _8       Ljava/lang/Object;
   0      47      9    _9       Ljava/lang/Object;
   0      47      10    _10       Ljava/lang/Object;
   0      47      11    _11       Ljava/lang/Object;
   0      47      12    _12       Ljava/lang/Object;
   0      47      13    _13       Ljava/lang/Object;
   0      47      14    _14       Ljava/lang/Object;
   0      47      15    _15       Ljava/lang/Object;
   0      47      16    _16       Ljava/lang/Object;
   0      47      17    _17       Ljava/lang/Object;
   0      47      18    _18       Ljava/lang/Object;
   0      47      19    _19       Ljava/lang/Object;
   0      47      20    _20       Ljava/lang/Object;
   0      47      21    _21       Ljava/lang/Object;


public java.lang.String toString();
  Signature: ()Ljava/lang/String;
  Code:
   Stack=2, Locals=1, Args_size=1
	new	class scala/collection/mutable/StringBuilder
	dup
	invokespecial	Method scala/collection/mutable/StringBuilder."<init>":()V
	ldc	String (
	invokevirtual	Method scala/collection/mutable/StringBuilder.append:(Ljava/lang/Object;)Lscala/collection/mutable/StringBuilder;
	aload_0
	invokevirtual	Method _1:()Ljava/lang/Object;
	invokevirtual	Method scala/collection/mutable/StringBuilder.append:(Ljava/lang/Object;)Lscala/collection/mutable/StringBuilder;
	ldc_w	String ,
	invokevirtual	Method scala/collection/mutable/StringBuilder.append:(Ljava/lang/Object;)Lscala/collection/mutable/StringBuilder;
	aload_0
	invokevirtual	Method _2:()Ljava/lang/Object;
	invokevirtual	Method scala/collection/mutable/StringBuilder.append:(Ljava/lang/Object;)Lscala/collection/mutable/StringBuilder;
	ldc_w	String ,
	invokevirtual	Method scala/collection/mutable/StringBuilder.append:(Ljava/lang/Object;)Lscala/collection/mutable/StringBuilder;
	aload_0
	invokevirtual	Method _3:()Ljava/lang/Object;
	invokevirtual	Method scala/collection/mutable/StringBuilder.append:(Ljava/lang/Object;)Lscala/collection/mutable/StringBuilder;
	ldc_w	String ,
	invokevirtual	Method scala/collection/mutable/StringBuilder.append:(Ljava/lang/Object;)Lscala/collection/mutable/StringBuilder;
	aload_0
	invokevirtual	Method _4:()Ljava/lang/Object;
	invokevirtual	Method scala/collection/mutable/StringBuilder.append:(Ljava/lang/Object;)Lscala/collection/mutable/StringBuilder;
	ldc_w	String ,
	invokevirtual	Method scala/collection/mutable/StringBuilder.append:(Ljava/lang/Object;)Lscala/collection/mutable/StringBuilder;
	aload_0
	invokevirtual	Method _5:()Ljava/lang/Object;
	invokevirtual	Method scala/collection/mutable/StringBuilder.append:(Ljava/lang/Object;)Lscala/collection/mutable/StringBuilder;
	ldc_w	String ,
	invokevirtual	Method scala/collection/mutable/StringBuilder.append:(Ljava/lang/Object;)Lscala/collection/mutable/StringBuilder;
	aload_0
	invokevirtual	Method _6:()Ljava/lang/Object;
	invokevirtual	Method scala/collection/mutable/StringBuilder.append:(Ljava/lang/Object;)Lscala/collection/mutable/StringBuilder;
	ldc_w	String ,
	invokevirtual	Method scala/collection/mutable/StringBuilder.append:(Ljava/lang/Object;)Lscala/collection/mutable/StringBuilder;
	aload_0
	invokevirtual	Method _7:()Ljava/lang/Object;
	invokevirtual	Method scala/collection/mutable/StringBuilder.append:(Ljava/lang/Object;)Lscala/collection/mutable/StringBuilder;
	ldc_w	String ,
	invokevirtual	Method scala/collection/mutable/StringBuilder.append:(Ljava/lang/Object;)Lscala/collection/mutable/StringBuilder;
	aload_0
	invokevirtual	Method _8:()Ljava/lang/Object;
	invokevirtual	Method scala/collection/mutable/StringBuilder.append:(Ljava/lang/Object;)Lscala/collection/mutable/StringBuilder;
	ldc_w	String ,
	invokevirtual	Method scala/collection/mutable/StringBuilder.append:(Ljava/lang/Object;)Lscala/collection/mutable/StringBuilder;
	aload_0
	invokevirtual	Method _9:()Ljava/lang/Object;
	invokevirtual	Method scala/collection/mutable/StringBuilder.append:(Ljava/lang/Object;)Lscala/collection/mutable/StringBuilder;
	ldc_w	String ,
	invokevirtual	Method scala/collection/mutable/StringBuilder.append:(Ljava/lang/Object;)Lscala/collection/mutable/StringBuilder;
	aload_0
	invokevirtual	Method _10:()Ljava/lang/Object;
	invokevirtual	Method scala/collection/mutable/StringBuilder.append:(Ljava/lang/Object;)Lscala/collection/mutable/StringBuilder;
	ldc_w	String ,
	invokevirtual	Method scala/collection/mutable/StringBuilder.append:(Ljava/lang/Object;)Lscala/collection/mutable/StringBuilder;
	aload_0
	invokevirtual	Method _11:()Ljava/lang/Object;
	invokevirtual	Method scala/collection/mutable/StringBuilder.append:(Ljava/lang/Object;)Lscala/collection/mutable/StringBuilder;
	ldc_w	String ,
	invokevirtual	Method scala/collection/mutable/StringBuilder.append:(Ljava/lang/Object;)Lscala/collection/mutable/StringBuilder;
	aload_0
	invokevirtual	Method _12:()Ljava/lang/Object;
	invokevirtual	Method scala/collection/mutable/StringBuilder.append:(Ljava/lang/Object;)Lscala/collection/mutable/StringBuilder;
	ldc_w	String ,
	invokevirtual	Method scala/collection/mutable/StringBuilder.append:(Ljava/lang/Object;)Lscala/collection/mutable/StringBuilder;
	aload_0
	invokevirtual	Method _13:()Ljava/lang/Object;
	invokevirtual	Method scala/collection/mutable/StringBuilder.append:(Ljava/lang/Object;)Lscala/collection/mutable/StringBuilder;
	ldc_w	String ,
	invokevirtual	Method scala/collection/mutable/StringBuilder.append:(Ljava/lang/Object;)Lscala/collection/mutable/StringBuilder;
	aload_0
	invokevirtual	Method _14:()Ljava/lang/Object;
	invokevirtual	Method scala/collection/mutable/StringBuilder.append:(Ljava/lang/Object;)Lscala/collection/mutable/StringBuilder;
	ldc_w	String ,
	invokevirtual	Method scala/collection/mutable/StringBuilder.append:(Ljava/lang/Object;)Lscala/collection/mutable/StringBuilder;
	aload_0
	invokevirtual	Method _15:()Ljava/lang/Object;
	invokevirtual	Method scala/collection/mutable/StringBuilder.append:(Ljava/lang/Object;)Lscala/collection/mutable/StringBuilder;
	ldc_w	String ,
	invokevirtual	Method scala/collection/mutable/StringBuilder.append:(Ljava/lang/Object;)Lscala/collection/mutable/StringBuilder;
	aload_0
	invokevirtual	Method _16:()Ljava/lang/Object;
	invokevirtual	Method scala/collection/mutable/StringBuilder.append:(Ljava/lang/Object;)Lscala/collection/mutable/StringBuilder;
	ldc_w	String ,
	invokevirtual	Method scala/collection/mutable/StringBuilder.append:(Ljava/lang/Object;)Lscala/collection/mutable/StringBuilder;
	aload_0
	invokevirtual	Method _17:()Ljava/lang/Object;
	invokevirtual	Method scala/collection/mutable/StringBuilder.append:(Ljava/lang/Object;)Lscala/collection/mutable/StringBuilder;
	ldc_w	String ,
	invokevirtual	Method scala/collection/mutable/StringBuilder.append:(Ljava/lang/Object;)Lscala/collection/mutable/StringBuilder;
	aload_0
	invokevirtual	Method _18:()Ljava/lang/Object;
	invokevirtual	Method scala/collection/mutable/StringBuilder.append:(Ljava/lang/Object;)Lscala/collection/mutable/StringBuilder;
	ldc_w	String ,
	invokevirtual	Method scala/collection/mutable/StringBuilder.append:(Ljava/lang/Object;)Lscala/collection/mutable/StringBuilder;
	aload_0
	invokevirtual	Method _19:()Ljava/lang/Object;
	invokevirtual	Method scala/collection/mutable/StringBuilder.append:(Ljava/lang/Object;)Lscala/collection/mutable/StringBuilder;
	ldc_w	String ,
	invokevirtual	Method scala/collection/mutable/StringBuilder.append:(Ljava/lang/Object;)Lscala/collection/mutable/StringBuilder;
	aload_0
	invokevirtual	Method _20:()Ljava/lang/Object;
	invokevirtual	Method scala/collection/mutable/StringBuilder.append:(Ljava/lang/Object;)Lscala/collection/mutable/StringBuilder;
	ldc_w	String ,
	invokevirtual	Method scala/collection/mutable/StringBuilder.append:(Ljava/lang/Object;)Lscala/collection/mutable/StringBuilder;
	aload_0
	invokevirtual	Method _21:()Ljava/lang/Object;
	invokevirtual	Method scala/collection/mutable/StringBuilder.append:(Ljava/lang/Object;)Lscala/collection/mutable/StringBuilder;
	ldc_w	String )
	invokevirtual	Method scala/collection/mutable/StringBuilder.append:(Ljava/lang/Object;)Lscala/collection/mutable/StringBuilder;
	invokevirtual	Method scala/collection/mutable/StringBuilder.toString:()Ljava/lang/String;
	areturn
  Labels:

public java.lang.Object _21();
  Signature: ()Ljava/lang/Object;
  Code:
   Stack=1, Locals=1, Args_size=1
	aload_0
	getfield	Field _21:Ljava/lang/Object;
	areturn
  Labels:
  Signature: length = 0x2
   01 07 

public java.lang.Object _20();
  Signature: ()Ljava/lang/Object;
  Code:
   Stack=1, Locals=1, Args_size=1
	aload_0
	getfield	Field _20:Ljava/lang/Object;
	areturn
  Labels:
  Signature: length = 0x2
   01 08 

public java.lang.Object _19();
  Signature: ()Ljava/lang/Object;
  Code:
   Stack=1, Locals=1, Args_size=1
	aload_0
	getfield	Field _19:Ljava/lang/Object;
	areturn
  Labels:
  Signature: length = 0x2
   01 09 

public java.lang.Object _18();
  Signature: ()Ljava/lang/Object;
  Code:
   Stack=1, Locals=1, Args_size=1
	aload_0
	getfield	Field _18:Ljava/lang/Object;
	areturn
  Labels:
  Signature: length = 0x2
   01 0A 

public java.lang.Object _17();
  Signature: ()Ljava/lang/Object;
  Code:
   Stack=1, Locals=1, Args_size=1
	aload_0
	getfield	Field _17:Ljava/lang/Object;
	areturn
  Labels:
  Signature: length = 0x2
   01 0B 

public java.lang.Object _16();
  Signature: ()Ljava/lang/Object;
  Code:
   Stack=1, Locals=1, Args_size=1
	aload_0
	getfield	Field _16:Ljava/lang/Object;
	areturn
  Labels:
  Signature: length = 0x2
   01 0C 

public java.lang.Object _15();
  Signature: ()Ljava/lang/Object;
  Code:
   Stack=1, Locals=1, Args_size=1
	aload_0
	getfield	Field _15:Ljava/lang/Object;
	areturn
  Labels:
  Signature: length = 0x2
   01 0D 

public java.lang.Object _14();
  Signature: ()Ljava/lang/Object;
  Code:
   Stack=1, Locals=1, Args_size=1
	aload_0
	getfield	Field _14:Ljava/lang/Object;
	areturn
  Labels:
  Signature: length = 0x2
   01 0E 

public java.lang.Object _13();
  Signature: ()Ljava/lang/Object;
  Code:
   Stack=1, Locals=1, Args_size=1
	aload_0
	getfield	Field _13:Ljava/lang/Object;
	areturn
  Labels:
  Signature: length = 0x2
   01 0F 

public java.lang.Object _12();
  Signature: ()Ljava/lang/Object;
  Code:
   Stack=1, Locals=1, Args_size=1
	aload_0
	getfield	Field _12:Ljava/lang/Object;
	areturn
  Labels:
  Signature: length = 0x2
   01 10 

public java.lang.Object _11();
  Signature: ()Ljava/lang/Object;
  Code:
   Stack=1, Locals=1, Args_size=1
	aload_0
	getfield	Field _11:Ljava/lang/Object;
	areturn
  Labels:
  Signature: length = 0x2
   01 11 

public java.lang.Object _10();
  Signature: ()Ljava/lang/Object;
  Code:
   Stack=1, Locals=1, Args_size=1
	aload_0
	getfield	Field _10:Ljava/lang/Object;
	areturn
  Labels:
  Signature: length = 0x2
   01 12 

public java.lang.Object _9();
  Signature: ()Ljava/lang/Object;
  Code:
   Stack=1, Locals=1, Args_size=1
	aload_0
	getfield	Field _9:Ljava/lang/Object;
	areturn
  Labels:
  Signature: length = 0x2
   01 13 

public java.lang.Object _8();
  Signature: ()Ljava/lang/Object;
  Code:
   Stack=1, Locals=1, Args_size=1
	aload_0
	getfield	Field _8:Ljava/lang/Object;
	areturn
  Labels:
  Signature: length = 0x2
   01 14 

public java.lang.Object _7();
  Signature: ()Ljava/lang/Object;
  Code:
   Stack=1, Locals=1, Args_size=1
	aload_0
	getfield	Field _7:Ljava/lang/Object;
	areturn
  Labels:
  Signature: length = 0x2
   01 15 

public java.lang.Object _6();
  Signature: ()Ljava/lang/Object;
  Code:
   Stack=1, Locals=1, Args_size=1
	aload_0
	getfield	Field _6:Ljava/lang/Object;
	areturn
  Labels:
  Signature: length = 0x2
   01 16 

public java.lang.Object _5();
  Signature: ()Ljava/lang/Object;
  Code:
   Stack=1, Locals=1, Args_size=1
	aload_0
	getfield	Field _5:Ljava/lang/Object;
	areturn
  Labels:
  Signature: length = 0x2
   01 17 

public java.lang.Object _4();
  Signature: ()Ljava/lang/Object;
  Code:
   Stack=1, Locals=1, Args_size=1
	aload_0
	getfield	Field _4:Ljava/lang/Object;
	areturn
  Labels:
  Signature: length = 0x2
   01 18 

public java.lang.Object _3();
  Signature: ()Ljava/lang/Object;
  Code:
   Stack=1, Locals=1, Args_size=1
	aload_0
	getfield	Field _3:Ljava/lang/Object;
	areturn
  Labels:
  Signature: length = 0x2
   01 19 

public java.lang.Object _2();
  Signature: ()Ljava/lang/Object;
  Code:
   Stack=1, Locals=1, Args_size=1
	aload_0
	getfield	Field _2:Ljava/lang/Object;
	areturn
  Labels:
  Signature: length = 0x2
   01 1A 

public java.lang.Object _1();
  Signature: ()Ljava/lang/Object;
  Code:
   Stack=1, Locals=1, Args_size=1
	aload_0
	getfield	Field _1:Ljava/lang/Object;
	areturn
  Labels:
  Signature: length = 0x2
   01 1B 

public java.lang.Object copy$default$1();
  Signature: ()Ljava/lang/Object;
  Code:
   Stack=1, Locals=1, Args_size=1
	aload_0
	invokevirtual	Method _1:()Ljava/lang/Object;
	areturn
  Labels:

public java.lang.Object copy$default$2();
  Signature: ()Ljava/lang/Object;
  Code:
   Stack=1, Locals=1, Args_size=1
	aload_0
	invokevirtual	Method _2:()Ljava/lang/Object;
	areturn
  Labels:

public java.lang.Object copy$default$3();
  Signature: ()Ljava/lang/Object;
  Code:
   Stack=1, Locals=1, Args_size=1
	aload_0
	invokevirtual	Method _3:()Ljava/lang/Object;
	areturn
  Labels:

public java.lang.Object copy$default$4();
  Signature: ()Ljava/lang/Object;
  Code:
   Stack=1, Locals=1, Args_size=1
	aload_0
	invokevirtual	Method _4:()Ljava/lang/Object;
	areturn
  Labels:

public java.lang.Object copy$default$5();
  Signature: ()Ljava/lang/Object;
  Code:
   Stack=1, Locals=1, Args_size=1
	aload_0
	invokevirtual	Method _5:()Ljava/lang/Object;
	areturn
  Labels:

public java.lang.Object copy$default$6();
  Signature: ()Ljava/lang/Object;
  Code:
   Stack=1, Locals=1, Args_size=1
	aload_0
	invokevirtual	Method _6:()Ljava/lang/Object;
	areturn
  Labels:

public java.lang.Object copy$default$7();
  Signature: ()Ljava/lang/Object;
  Code:
   Stack=1, Locals=1, Args_size=1
	aload_0
	invokevirtual	Method _7:()Ljava/lang/Object;
	areturn
  Labels:

public java.lang.Object copy$default$8();
  Signature: ()Ljava/lang/Object;
  Code:
   Stack=1, Locals=1, Args_size=1
	aload_0
	invokevirtual	Method _8:()Ljava/lang/Object;
	areturn
  Labels:

public java.lang.Object copy$default$9();
  Signature: ()Ljava/lang/Object;
  Code:
   Stack=1, Locals=1, Args_size=1
	aload_0
	invokevirtual	Method _9:()Ljava/lang/Object;
	areturn
  Labels:

public java.lang.Object copy$default$10();
  Signature: ()Ljava/lang/Object;
  Code:
   Stack=1, Locals=1, Args_size=1
	aload_0
	invokevirtual	Method _10:()Ljava/lang/Object;
	areturn
  Labels:

public java.lang.Object copy$default$11();
  Signature: ()Ljava/lang/Object;
  Code:
   Stack=1, Locals=1, Args_size=1
	aload_0
	invokevirtual	Method _11:()Ljava/lang/Object;
	areturn
  Labels:

public java.lang.Object copy$default$12();
  Signature: ()Ljava/lang/Object;
  Code:
   Stack=1, Locals=1, Args_size=1
	aload_0
	invokevirtual	Method _12:()Ljava/lang/Object;
	areturn
  Labels:

public java.lang.Object copy$default$13();
  Signature: ()Ljava/lang/Object;
  Code:
   Stack=1, Locals=1, Args_size=1
	aload_0
	invokevirtual	Method _13:()Ljava/lang/Object;
	areturn
  Labels:

public java.lang.Object copy$default$14();
  Signature: ()Ljava/lang/Object;
  Code:
   Stack=1, Locals=1, Args_size=1
	aload_0
	invokevirtual	Method _14:()Ljava/lang/Object;
	areturn
  Labels:

public java.lang.Object copy$default$15();
  Signature: ()Ljava/lang/Object;
  Code:
   Stack=1, Locals=1, Args_size=1
	aload_0
	invokevirtual	Method _15:()Ljava/lang/Object;
	areturn
  Labels:

public java.lang.Object copy$default$16();
  Signature: ()Ljava/lang/Object;
  Code:
   Stack=1, Locals=1, Args_size=1
	aload_0
	invokevirtual	Method _16:()Ljava/lang/Object;
	areturn
  Labels:

public java.lang.Object copy$default$17();
  Signature: ()Ljava/lang/Object;
  Code:
   Stack=1, Locals=1, Args_size=1
	aload_0
	invokevirtual	Method _17:()Ljava/lang/Object;
	areturn
  Labels:

public java.lang.Object copy$default$18();
  Signature: ()Ljava/lang/Object;
  Code:
   Stack=1, Locals=1, Args_size=1
	aload_0
	invokevirtual	Method _18:()Ljava/lang/Object;
	areturn
  Labels:

public java.lang.Object copy$default$19();
  Signature: ()Ljava/lang/Object;
  Code:
   Stack=1, Locals=1, Args_size=1
	aload_0
	invokevirtual	Method _19:()Ljava/lang/Object;
	areturn
  Labels:

public java.lang.Object copy$default$20();
  Signature: ()Ljava/lang/Object;
  Code:
   Stack=1, Locals=1, Args_size=1
	aload_0
	invokevirtual	Method _20:()Ljava/lang/Object;
	areturn
  Labels:

public java.lang.Object copy$default$21();
  Signature: ()Ljava/lang/Object;
  Code:
   Stack=1, Locals=1, Args_size=1
	aload_0
	invokevirtual	Method _21:()Ljava/lang/Object;
	areturn
  Labels:

public scala.collection.Iterator productElements();
  Signature: ()Lscala/collection/Iterator;
  Code:
   Stack=1, Locals=1, Args_size=1
	aload_0
	invokestatic	Method scala/Product$class.productElements:(Lscala/Product;)Lscala/collection/Iterator;
	areturn
  Labels:
  Deprecated: true

public scala.collection.Iterator productIterator();
  Signature: ()Lscala/collection/Iterator;
  Code:
   Stack=1, Locals=1, Args_size=1
	aload_0
	invokestatic	Method scala/Product$class.productIterator:(Lscala/Product;)Lscala/collection/Iterator;
	areturn
  Labels:

public java.lang.Object productElement(int)   throws java.lang.IndexOutOfBoundsException;
  Signature: (I)Ljava/lang/Object;
  Code:
   Stack=2, Locals=2, Args_size=2
	aload_0
	iload_1
	invokestatic	Method scala/Product21$class.productElement:(Lscala/Product21;I)Ljava/lang/Object;
	areturn
  Labels:
  LocalVariableTable: 
   Start  Length  Slot  Name   Signature
   0      6      0    this       Lscala/Tuple21;
   0      6      1    n       I

  Exceptions: 
   throws java.lang.IndexOutOfBoundsException
public int productArity();
  Signature: ()I
  Code:
   Stack=1, Locals=1, Args_size=1
	aload_0
	invokestatic	Method scala/Product21$class.productArity:(Lscala/Product21;)I
	ireturn
  Labels:

}

