Compiled from "Tuple3.scala"
public final class scala.Tuple3$Zipped$$anonfun$forall$1 extends java.lang.Object implements scala.Function1,scala.ScalaObject,java.io.Serializable
  SourceFile: "Tuple3.scala"
  Scala: length = 0x
   
  InnerClass: 
   public Zipped=class scala/Tuple3$Zipped of class scala/Tuple3
   public final $anonfun$forall$1=class scala/Tuple3$Zipped$$anonfun$forall$1 of class scala/Tuple3$Zipped
  minor version: 0
  major version: 49
  Constant pool:
Asciz	SourceFile;
Asciz	Tuple3.scala;
Asciz	<clinit>;
Asciz	()V;
Asciz	Code;
Asciz	serialVersionUID;
Asciz	J;
Asciz	scala/Tuple3$Zipped$$anonfun$forall$1;
class	scala/Tuple3$Zipped$$anonfun$forall$1
NameAndType	serialVersionUID:J
Field	scala/Tuple3$Zipped$$anonfun$forall$1.serialVersionUID:J
Asciz	elems3$6;
Asciz	Lscala/collection/Iterator;;
Asciz	elems2$6;
Asciz	acc$2;
Asciz	Lscala/runtime/BooleanRef;;
Asciz	f$5;
Asciz	Lscala/Function3;;
Asciz	<init>;
Asciz	(Lscala/Tuple3$Zipped;Lscala/Function3;Lscala/runtime/BooleanRef;Lscala/collection/Iterator;Lscala/collection/Iterator;)V;
Asciz	LineNumberTable;
NameAndType	f$5:Lscala/Function3;
Field	scala/Tuple3$Zipped$$anonfun$forall$1.f$5:Lscala/Function3;
NameAndType	acc$2:Lscala/runtime/BooleanRef;
Field	scala/Tuple3$Zipped$$anonfun$forall$1.acc$2:Lscala/runtime/BooleanRef;
NameAndType	elems2$6:Lscala/collection/Iterator;
Field	scala/Tuple3$Zipped$$anonfun$forall$1.elems2$6:Lscala/collection/Iterator;
NameAndType	elems3$6:Lscala/collection/Iterator;
Field	scala/Tuple3$Zipped$$anonfun$forall$1.elems3$6:Lscala/collection/Iterator;
Asciz	java/lang/Object;
class	java/lang/Object
NameAndType	"<init>":()V
Method	java/lang/Object."<init>":()V
Asciz	scala/Function1$class;
class	scala/Function1$class
Asciz	$init$;
Asciz	(Lscala/Function1;)V;
NameAndType	$init$:(Lscala/Function1;)V
Method	scala/Function1$class.$init$:(Lscala/Function1;)V
Asciz	this;
Asciz	Lscala/Tuple3$Zipped$$anonfun$forall$1;;
Asciz	$outer;
Asciz	Lscala/Tuple3$Zipped;;
Asciz	LocalVariableTable;
Asciz	(Lscala/Tuple3<TT1;TT2;TT3;>.Zipped<TRepr1;TEl1;TRepr2;TEl2;TRepr3;TEl3;>;)V;
Asciz	Signature;
Asciz	apply;
Asciz	(Ljava/lang/Object;)Ljava/lang/Object;;
Asciz	(Ljava/lang/Object;)V;
NameAndType	apply:(Ljava/lang/Object;)V
Method	scala/Tuple3$Zipped$$anonfun$forall$1.apply:(Ljava/lang/Object;)V
Asciz	scala/runtime/BoxedUnit;
class	scala/runtime/BoxedUnit
Asciz	UNIT;
Asciz	Lscala/runtime/BoxedUnit;;
NameAndType	UNIT:Lscala/runtime/BoxedUnit;
Field	scala/runtime/BoxedUnit.UNIT:Lscala/runtime/BoxedUnit;
Asciz	v1;
Asciz	Ljava/lang/Object;;
Asciz	scala/runtime/BooleanRef;
class	scala/runtime/BooleanRef
Asciz	elem;
Asciz	Z;
NameAndType	elem:Z
Field	scala/runtime/BooleanRef.elem:Z
Asciz	scala/collection/Iterator;
class	scala/collection/Iterator
Asciz	hasNext;
Asciz	()Z;
NameAndType	hasNext:()Z
InterfaceMethod	scala/collection/Iterator.hasNext:()Z
Asciz	next;
Asciz	()Ljava/lang/Object;;
NameAndType	next:()Ljava/lang/Object;
InterfaceMethod	scala/collection/Iterator.next:()Ljava/lang/Object;
Asciz	scala/Function3;
class	scala/Function3
Asciz	(Ljava/lang/Object;Ljava/lang/Object;Ljava/lang/Object;)Ljava/lang/Object;;
NameAndType	apply:(Ljava/lang/Object;Ljava/lang/Object;Ljava/lang/Object;)Ljava/lang/Object;
InterfaceMethod	scala/Function3.apply:(Ljava/lang/Object;Ljava/lang/Object;Ljava/lang/Object;)Ljava/lang/Object;
Asciz	scala/runtime/BoxesRunTime;
class	scala/runtime/BoxesRunTime
Asciz	unboxToBoolean;
Asciz	(Ljava/lang/Object;)Z;
NameAndType	unboxToBoolean:(Ljava/lang/Object;)Z
Method	scala/runtime/BoxesRunTime.unboxToBoolean:(Ljava/lang/Object;)Z
Asciz	el1;
Asciz	(TEl1;)V;
Asciz	andThen;
Asciz	(Lscala/Function1;)Lscala/Function1;;
Asciz	(Lscala/Function1;Lscala/Function1;)Lscala/Function1;;
NameAndType	andThen:(Lscala/Function1;Lscala/Function1;)Lscala/Function1;
Method	scala/Function1$class.andThen:(Lscala/Function1;Lscala/Function1;)Lscala/Function1;
Asciz	g;
Asciz	Lscala/Function1;;
Asciz	compose;
NameAndType	compose:(Lscala/Function1;Lscala/Function1;)Lscala/Function1;
Method	scala/Function1$class.compose:(Lscala/Function1;Lscala/Function1;)Lscala/Function1;
Asciz	toString;
Asciz	()Ljava/lang/String;;
Asciz	(Lscala/Function1;)Ljava/lang/String;;
NameAndType	toString:(Lscala/Function1;)Ljava/lang/String;
Method	scala/Function1$class.toString:(Lscala/Function1;)Ljava/lang/String;
Asciz	Scala;
Asciz	InnerClasses;
Asciz	scala/Tuple3$Zipped;
class	scala/Tuple3$Zipped
Asciz	scala/Tuple3;
class	scala/Tuple3
Asciz	Zipped;
Asciz	$anonfun$forall$1;
Asciz	scala/Function1;
class	scala/Function1
Asciz	scala/ScalaObject;
class	scala/ScalaObject
Asciz	java/io/Serializable;
class	java/io/Serializable

{
public static final long serialVersionUID;
  Signature: J

private final scala.collection.Iterator elems3$6;
  Signature: Lscala/collection/Iterator;

private final scala.collection.Iterator elems2$6;
  Signature: Lscala/collection/Iterator;

private final scala.runtime.BooleanRef acc$2;
  Signature: Lscala/runtime/BooleanRef;

private final scala.Function3 f$5;
  Signature: Lscala/Function3;

public static {};
  Signature: ()V
  Code:
   Stack=2, Locals=0, Args_size=0
	lconst_0
	putstatic	Field serialVersionUID:J
	return
  Labels:

public scala.Tuple3$Zipped$$anonfun$forall$1(scala.Tuple3$Zipped, scala.Function3, scala.runtime.BooleanRef, scala.collection.Iterator, scala.collection.Iterator);
  Signature: (Lscala/Tuple3$Zipped;Lscala/Function3;Lscala/runtime/BooleanRef;Lscala/collection/Iterator;Lscala/collection/Iterator;)V
  Code:
   Stack=2, Locals=6, Args_size=6
	aload_0
	aload_2
	putfield	Field f$5:Lscala/Function3;
	aload_0
	aload_3
	putfield	Field acc$2:Lscala/runtime/BooleanRef;
	aload_0
	aload	4
	putfield	Field elems2$6:Lscala/collection/Iterator;
	aload_0
	aload	5
	putfield	Field elems3$6:Lscala/collection/Iterator;
	aload_0
	invokespecial	Method java/lang/Object."<init>":()V
	aload_0
	invokestatic	Method scala/Function1$class.$init$:(Lscala/Function1;)V
	return
  Labels:
  LocalVariableTable: 
   Start  Length  Slot  Name   Signature
   0      31      0    this       Lscala/Tuple3$Zipped$$anonfun$forall$1;
   0      31      1    $outer       Lscala/Tuple3$Zipped;

  Signature: length = 0x2
   00 2D 

public final java.lang.Object apply(java.lang.Object);
  Signature: (Ljava/lang/Object;)Ljava/lang/Object;
  Code:
   Stack=2, Locals=2, Args_size=2
	aload_0
	aload_1
	invokevirtual	Method apply:(Ljava/lang/Object;)V
	getstatic	Field scala/runtime/BoxedUnit.UNIT:Lscala/runtime/BoxedUnit;
	areturn
  Labels:
  LocalVariableTable: 
   Start  Length  Slot  Name   Signature
   0      9      0    this       Lscala/Tuple3$Zipped$$anonfun$forall$1;
   0      9      1    v1       Ljava/lang/Object;


public final void apply(java.lang.Object);
  Signature: (Ljava/lang/Object;)V
  Code:
   Stack=5, Locals=2, Args_size=2
	aload_0
	getfield	Field acc$2:Lscala/runtime/BooleanRef;
	getfield	Field scala/runtime/BooleanRef.elem:Z
	ifeq	l1 // return
	aload_0
	getfield	Field elems2$6:Lscala/collection/Iterator;
	invokeinterface	InterfaceMethod scala/collection/Iterator.hasNext:()Z
	ifeq	l1 // return
	aload_0
	getfield	Field elems3$6:Lscala/collection/Iterator;
	invokeinterface	InterfaceMethod scala/collection/Iterator.hasNext:()Z
	ifeq	l1 // return
	aload_0
	getfield	Field acc$2:Lscala/runtime/BooleanRef;
	aload_0
	getfield	Field f$5:Lscala/Function3;
	aload_1
	aload_0
	getfield	Field elems2$6:Lscala/collection/Iterator;
	invokeinterface	InterfaceMethod scala/collection/Iterator.next:()Ljava/lang/Object;
	aload_0
	getfield	Field elems3$6:Lscala/collection/Iterator;
	invokeinterface	InterfaceMethod scala/collection/Iterator.next:()Ljava/lang/Object;
	invokeinterface	InterfaceMethod scala/Function3.apply:(Ljava/lang/Object;Ljava/lang/Object;Ljava/lang/Object;)Ljava/lang/Object;
	invokestatic	Method scala/runtime/BoxesRunTime.unboxToBoolean:(Ljava/lang/Object;)Z
	putfield	Field scala/runtime/BooleanRef.elem:Z
l1	return
  Labels:
   	l1 = 72 // return
  LocalVariableTable: 
   Start  Length  Slot  Name   Signature
   0      73      0    this       Lscala/Tuple3$Zipped$$anonfun$forall$1;
   0      73      1    el1       Ljava/lang/Object;

  Signature: length = 0x2
   00 58 

public scala.Function1 andThen(scala.Function1);
  Signature: (Lscala/Function1;)Lscala/Function1;
  Code:
   Stack=2, Locals=2, Args_size=2
	aload_0
	aload_1
	invokestatic	Method scala/Function1$class.andThen:(Lscala/Function1;Lscala/Function1;)Lscala/Function1;
	areturn
  Labels:
  LocalVariableTable: 
   Start  Length  Slot  Name   Signature
   0      6      0    this       Lscala/Tuple3$Zipped$$anonfun$forall$1;
   0      6      1    g       Lscala/Function1;


public scala.Function1 compose(scala.Function1);
  Signature: (Lscala/Function1;)Lscala/Function1;
  Code:
   Stack=2, Locals=2, Args_size=2
	aload_0
	aload_1
	invokestatic	Method scala/Function1$class.compose:(Lscala/Function1;Lscala/Function1;)Lscala/Function1;
	areturn
  Labels:
  LocalVariableTable: 
   Start  Length  Slot  Name   Signature
   0      6      0    this       Lscala/Tuple3$Zipped$$anonfun$forall$1;
   0      6      1    g       Lscala/Function1;


public java.lang.String toString();
  Signature: ()Ljava/lang/String;
  Code:
   Stack=1, Locals=1, Args_size=1
	aload_0
	invokestatic	Method scala/Function1$class.toString:(Lscala/Function1;)Ljava/lang/String;
	areturn
  Labels:

}

