Compiled from "Tuple18.scala"
public final class scala.Tuple18$ extends java.lang.Object implements scala.ScalaObject
  SourceFile: "Tuple18.scala"
  Scala: length = 0x
   
  minor version: 0
  major version: 49
  Constant pool:
Asciz	SourceFile;
Asciz	Tuple18.scala;
Asciz	Scala;
Asciz	MODULE$;
Asciz	Lscala/Tuple18$;;
Asciz	<clinit>;
Asciz	()V;
Asciz	Code;
Asciz	scala/Tuple18$;
class	scala/Tuple18$
Asciz	<init>;
NameAndType	"<init>":()V
Method	scala/Tuple18$."<init>":()V
Asciz	unapply;
Asciz	(Lscala/Tuple18;)Lscala/Option;;
Asciz	LineNumberTable;
Asciz	java/lang/Object;
class	java/lang/Object
Asciz	equals;
Asciz	(Ljava/lang/Object;)Z;
NameAndType	equals:(Ljava/lang/Object;)Z
Method	java/lang/Object.equals:(Ljava/lang/Object;)Z
Asciz	scala/None$;
class	scala/None$
Asciz	Lscala/None$;;
NameAndType	MODULE$:Lscala/None$;
Field	scala/None$.MODULE$:Lscala/None$;
Asciz	scala/Some;
class	scala/Some
Asciz	scala/Tuple18;
class	scala/Tuple18
Asciz	_1;
Asciz	()Ljava/lang/Object;;
NameAndType	_1:()Ljava/lang/Object;
Method	scala/Tuple18._1:()Ljava/lang/Object;
Asciz	_2;
NameAndType	_2:()Ljava/lang/Object;
Method	scala/Tuple18._2:()Ljava/lang/Object;
Asciz	_3;
NameAndType	_3:()Ljava/lang/Object;
Method	scala/Tuple18._3:()Ljava/lang/Object;
Asciz	_4;
NameAndType	_4:()Ljava/lang/Object;
Method	scala/Tuple18._4:()Ljava/lang/Object;
Asciz	_5;
NameAndType	_5:()Ljava/lang/Object;
Method	scala/Tuple18._5:()Ljava/lang/Object;
Asciz	_6;
NameAndType	_6:()Ljava/lang/Object;
Method	scala/Tuple18._6:()Ljava/lang/Object;
Asciz	_7;
NameAndType	_7:()Ljava/lang/Object;
Method	scala/Tuple18._7:()Ljava/lang/Object;
Asciz	_8;
NameAndType	_8:()Ljava/lang/Object;
Method	scala/Tuple18._8:()Ljava/lang/Object;
Asciz	_9;
NameAndType	_9:()Ljava/lang/Object;
Method	scala/Tuple18._9:()Ljava/lang/Object;
Asciz	_10;
NameAndType	_10:()Ljava/lang/Object;
Method	scala/Tuple18._10:()Ljava/lang/Object;
Asciz	_11;
NameAndType	_11:()Ljava/lang/Object;
Method	scala/Tuple18._11:()Ljava/lang/Object;
Asciz	_12;
NameAndType	_12:()Ljava/lang/Object;
Method	scala/Tuple18._12:()Ljava/lang/Object;
Asciz	_13;
NameAndType	_13:()Ljava/lang/Object;
Method	scala/Tuple18._13:()Ljava/lang/Object;
Asciz	_14;
NameAndType	_14:()Ljava/lang/Object;
Method	scala/Tuple18._14:()Ljava/lang/Object;
Asciz	_15;
NameAndType	_15:()Ljava/lang/Object;
Method	scala/Tuple18._15:()Ljava/lang/Object;
Asciz	_16;
NameAndType	_16:()Ljava/lang/Object;
Method	scala/Tuple18._16:()Ljava/lang/Object;
Asciz	_17;
NameAndType	_17:()Ljava/lang/Object;
Method	scala/Tuple18._17:()Ljava/lang/Object;
Asciz	_18;
NameAndType	_18:()Ljava/lang/Object;
Method	scala/Tuple18._18:()Ljava/lang/Object;
Asciz	(Ljava/lang/Object;Ljava/lang/Object;Ljava/lang/Object;Ljava/lang/Object;Ljava/lang/Object;Ljava/lang/Object;Ljava/lang/Object;Ljava/lang/Object;Ljava/lang/Object;Ljava/lang/Object;Ljava/lang/Object;Ljava/lang/Object;Ljava/lang/Object;Ljava/lang/Object;Ljava/lang/Object;Ljava/lang/Object;Ljava/lang/Object;Ljava/lang/Object;)V;
NameAndType	"<init>":(Ljava/lang/Object;Ljava/lang/Object;Ljava/lang/Object;Ljava/lang/Object;Ljava/lang/Object;Ljava/lang/Object;Ljava/lang/Object;Ljava/lang/Object;Ljava/lang/Object;Ljava/lang/Object;Ljava/lang/Object;Ljava/lang/Object;Ljava/lang/Object;Ljava/lang/Object;Ljava/lang/Object;Ljava/lang/Object;Ljava/lang/Object;Ljava/lang/Object;)V
Method	scala/Tuple18."<init>":(Ljava/lang/Object;Ljava/lang/Object;Ljava/lang/Object;Ljava/lang/Object;Ljava/lang/Object;Ljava/lang/Object;Ljava/lang/Object;Ljava/lang/Object;Ljava/lang/Object;Ljava/lang/Object;Ljava/lang/Object;Ljava/lang/Object;Ljava/lang/Object;Ljava/lang/Object;Ljava/lang/Object;Ljava/lang/Object;Ljava/lang/Object;Ljava/lang/Object;)V
Asciz	(Ljava/lang/Object;)V;
NameAndType	"<init>":(Ljava/lang/Object;)V
Method	scala/Some."<init>":(Ljava/lang/Object;)V
Asciz	this;
Asciz	x$0;
Asciz	Lscala/Tuple18;;
Asciz	LocalVariableTable;
Asciz	apply;
Asciz	(Ljava/lang/Object;Ljava/lang/Object;Ljava/lang/Object;Ljava/lang/Object;Ljava/lang/Object;Ljava/lang/Object;Ljava/lang/Object;Ljava/lang/Object;Ljava/lang/Object;Ljava/lang/Object;Ljava/lang/Object;Ljava/lang/Object;Ljava/lang/Object;Ljava/lang/Object;Ljava/lang/Object;Ljava/lang/Object;Ljava/lang/Object;Ljava/lang/Object;)Lscala/Tuple18;;
Asciz	Ljava/lang/Object;;
Method	java/lang/Object."<init>":()V
NameAndType	MODULE$:Lscala/Tuple18$;
Field	scala/Tuple18$.MODULE$:Lscala/Tuple18$;
Asciz	scala/ScalaObject;
class	scala/ScalaObject

{
public static final scala.Tuple18$ MODULE$;
  Signature: Lscala/Tuple18$;

public static {};
  Signature: ()V
  Code:
   Stack=1, Locals=0, Args_size=0
	new	class scala/Tuple18$
	invokespecial	Method "<init>":()V
	return
  Labels:

public scala.Option unapply(scala.Tuple18);
  Signature: (Lscala/Tuple18;)Lscala/Option;
  Code:
   Stack=22, Locals=3, Args_size=2
	aload_1
	dup
	astore_2
	ifnull	l1 // getstatic
	aload_2
	aconst_null
	invokevirtual	Method java/lang/Object.equals:(Ljava/lang/Object;)Z
	ifeq	l2 // new
l1	getstatic	Field scala/None$.MODULE$:Lscala/None$;
	goto	l3 // areturn
l2	new	class scala/Some
	dup
	new	class scala/Tuple18
	dup
	aload_1
	invokevirtual	Method scala/Tuple18._1:()Ljava/lang/Object;
	aload_1
	invokevirtual	Method scala/Tuple18._2:()Ljava/lang/Object;
	aload_1
	invokevirtual	Method scala/Tuple18._3:()Ljava/lang/Object;
	aload_1
	invokevirtual	Method scala/Tuple18._4:()Ljava/lang/Object;
	aload_1
	invokevirtual	Method scala/Tuple18._5:()Ljava/lang/Object;
	aload_1
	invokevirtual	Method scala/Tuple18._6:()Ljava/lang/Object;
	aload_1
	invokevirtual	Method scala/Tuple18._7:()Ljava/lang/Object;
	aload_1
	invokevirtual	Method scala/Tuple18._8:()Ljava/lang/Object;
	aload_1
	invokevirtual	Method scala/Tuple18._9:()Ljava/lang/Object;
	aload_1
	invokevirtual	Method scala/Tuple18._10:()Ljava/lang/Object;
	aload_1
	invokevirtual	Method scala/Tuple18._11:()Ljava/lang/Object;
	aload_1
	invokevirtual	Method scala/Tuple18._12:()Ljava/lang/Object;
	aload_1
	invokevirtual	Method scala/Tuple18._13:()Ljava/lang/Object;
	aload_1
	invokevirtual	Method scala/Tuple18._14:()Ljava/lang/Object;
	aload_1
	invokevirtual	Method scala/Tuple18._15:()Ljava/lang/Object;
	aload_1
	invokevirtual	Method scala/Tuple18._16:()Ljava/lang/Object;
	aload_1
	invokevirtual	Method scala/Tuple18._17:()Ljava/lang/Object;
	aload_1
	invokevirtual	Method scala/Tuple18._18:()Ljava/lang/Object;
	invokespecial	Method scala/Tuple18."<init>":(Ljava/lang/Object;Ljava/lang/Object;Ljava/lang/Object;Ljava/lang/Object;Ljava/lang/Object;Ljava/lang/Object;Ljava/lang/Object;Ljava/lang/Object;Ljava/lang/Object;Ljava/lang/Object;Ljava/lang/Object;Ljava/lang/Object;Ljava/lang/Object;Ljava/lang/Object;Ljava/lang/Object;Ljava/lang/Object;Ljava/lang/Object;Ljava/lang/Object;)V
	invokespecial	Method scala/Some."<init>":(Ljava/lang/Object;)V
l3	areturn
  Labels:
   	l1 = 14 // getstatic
   	l2 = 20 // new
   	l3 = 106 // areturn
  LocalVariableTable: 
   Start  Length  Slot  Name   Signature
   0      107      0    this       Lscala/Tuple18$;
   0      107      1    x$0       Lscala/Tuple18;


public scala.Tuple18 apply(java.lang.Object, java.lang.Object, java.lang.Object, java.lang.Object, java.lang.Object, java.lang.Object, java.lang.Object, java.lang.Object, java.lang.Object, java.lang.Object, java.lang.Object, java.lang.Object, java.lang.Object, java.lang.Object, java.lang.Object, java.lang.Object, java.lang.Object, java.lang.Object);
  Signature: (Ljava/lang/Object;Ljava/lang/Object;Ljava/lang/Object;Ljava/lang/Object;Ljava/lang/Object;Ljava/lang/Object;Ljava/lang/Object;Ljava/lang/Object;Ljava/lang/Object;Ljava/lang/Object;Ljava/lang/Object;Ljava/lang/Object;Ljava/lang/Object;Ljava/lang/Object;Ljava/lang/Object;Ljava/lang/Object;Ljava/lang/Object;Ljava/lang/Object;)Lscala/Tuple18;
  Code:
   Stack=20, Locals=19, Args_size=19
	new	class scala/Tuple18
	dup
	aload_1
	aload_2
	aload_3
	aload	4
	aload	5
	aload	6
	aload	7
	aload	8
	aload	9
	aload	10
	aload	11
	aload	12
	aload	13
	aload	14
	aload	15
	aload	16
	aload	17
	aload	18
	invokespecial	Method scala/Tuple18."<init>":(Ljava/lang/Object;Ljava/lang/Object;Ljava/lang/Object;Ljava/lang/Object;Ljava/lang/Object;Ljava/lang/Object;Ljava/lang/Object;Ljava/lang/Object;Ljava/lang/Object;Ljava/lang/Object;Ljava/lang/Object;Ljava/lang/Object;Ljava/lang/Object;Ljava/lang/Object;Ljava/lang/Object;Ljava/lang/Object;Ljava/lang/Object;Ljava/lang/Object;)V
	areturn
  Labels:
  LocalVariableTable: 
   Start  Length  Slot  Name   Signature
   0      41      0    this       Lscala/Tuple18$;
   0      41      1    _1       Ljava/lang/Object;
   0      41      2    _2       Ljava/lang/Object;
   0      41      3    _3       Ljava/lang/Object;
   0      41      4    _4       Ljava/lang/Object;
   0      41      5    _5       Ljava/lang/Object;
   0      41      6    _6       Ljava/lang/Object;
   0      41      7    _7       Ljava/lang/Object;
   0      41      8    _8       Ljava/lang/Object;
   0      41      9    _9       Ljava/lang/Object;
   0      41      10    _10       Ljava/lang/Object;
   0      41      11    _11       Ljava/lang/Object;
   0      41      12    _12       Ljava/lang/Object;
   0      41      13    _13       Ljava/lang/Object;
   0      41      14    _14       Ljava/lang/Object;
   0      41      15    _15       Ljava/lang/Object;
   0      41      16    _16       Ljava/lang/Object;
   0      41      17    _17       Ljava/lang/Object;
   0      41      18    _18       Ljava/lang/Object;


private scala.Tuple18$();
  Signature: ()V
  Code:
   Stack=1, Locals=1, Args_size=1
	aload_0
	invokespecial	Method java/lang/Object."<init>":()V
	aload_0
	putstatic	Field MODULE$:Lscala/Tuple18$;
	return
  Labels:

}

