Compiled from "Tuple2.scala"
public class scala.Tuple2$mcDL$sp extends scala.Tuple2
  SourceFile: "Tuple2.scala"
  Scala: length = 0x
   
  Signature: length = 0x2
   00 FFFFFF81 
  InnerClass: 
   public Zipped=class scala/Tuple2$Zipped of class scala/Tuple2
   public final $anonfun$zip$mcDL$sp$1=class scala/Tuple2$mcDL$sp$$anonfun$zip$mcDL$sp$1 of class scala/Tuple2$mcDL$sp
  minor version: 0
  major version: 49
  Constant pool:
Asciz	SourceFile;
Asciz	Tuple2.scala;
Asciz	_1$mcD$sp;
Asciz	D;
Asciz	_2$mcL$sp;
Asciz	J;
Asciz	()D;
Asciz	Code;
Asciz	LineNumberTable;
Asciz	scala/Tuple2$mcDL$sp;
class	scala/Tuple2$mcDL$sp
NameAndType	_1$mcD$sp:D
Field	scala/Tuple2$mcDL$sp._1$mcD$sp:D
Asciz	_1;
NameAndType	_1$mcD$sp:()D
Method	scala/Tuple2$mcDL$sp._1$mcD$sp:()D
Asciz	()J;
NameAndType	_2$mcL$sp:J
Field	scala/Tuple2$mcDL$sp._2$mcL$sp:J
Asciz	_2;
NameAndType	_2$mcL$sp:()J
Method	scala/Tuple2$mcDL$sp._2$mcL$sp:()J
Asciz	swap;
Asciz	()Lscala/Tuple2;;
Asciz	swap$mcDL$sp;
NameAndType	swap$mcDL$sp:()Lscala/Tuple2;
Method	scala/Tuple2$mcDL$sp.swap$mcDL$sp:()Lscala/Tuple2;
Asciz	()Lscala/Tuple2<Ljava/lang/Long;Ljava/lang/Double;>;;
Asciz	Signature;
Asciz	scala/Tuple2$mcLD$sp;
class	scala/Tuple2$mcLD$sp
NameAndType	_2:()J
Method	scala/Tuple2$mcDL$sp._2:()J
NameAndType	_1:()D
Method	scala/Tuple2$mcDL$sp._1:()D
Asciz	<init>;
Asciz	(JD)V;
NameAndType	"<init>":(JD)V
Method	scala/Tuple2$mcLD$sp."<init>":(JD)V
Asciz	zip;
Asciz	(Lscala/Function1;Lscala/Function1;Lscala/collection/generic/CanBuildFrom;)Ljava/lang/Object;;
Asciz	zip$mcDL$sp;
NameAndType	zip$mcDL$sp:(Lscala/Function1;Lscala/Function1;Lscala/collection/generic/CanBuildFrom;)Ljava/lang/Object;
Method	scala/Tuple2$mcDL$sp.zip$mcDL$sp:(Lscala/Function1;Lscala/Function1;Lscala/collection/generic/CanBuildFrom;)Ljava/lang/Object;
Asciz	this;
Asciz	Lscala/Tuple2$mcDL$sp;;
Asciz	w1;
Asciz	Lscala/Function1;;
Asciz	w2;
Asciz	cbf1;
Asciz	Lscala/collection/generic/CanBuildFrom;;
Asciz	LocalVariableTable;
Asciz	<Repr1:Ljava/lang/Object;El1:Ljava/lang/Object;El2:Ljava/lang/Object;To:Ljava/lang/Object;>(Lscala/Function1<Ljava/lang/Double;Lscala/collection/TraversableLike<TEl1;TRepr1;>;>;Lscala/Function1<Ljava/lang/Long;Lscala/collection/Iterable<TEl2;>;>;Lscala/collection/generic/CanBuildFrom<TRepr1;Lscala/Tuple2<TEl1;TEl2;>;TTo;>;)TTo;;
Asciz	scala/runtime/BoxesRunTime;
class	scala/runtime/BoxesRunTime
Asciz	boxToDouble;
Asciz	(D)Ljava/lang/Double;;
NameAndType	boxToDouble:(D)Ljava/lang/Double;
Method	scala/runtime/BoxesRunTime.boxToDouble:(D)Ljava/lang/Double;
Asciz	scala/Function1;
class	scala/Function1
Asciz	apply;
Asciz	(Ljava/lang/Object;)Ljava/lang/Object;;
NameAndType	apply:(Ljava/lang/Object;)Ljava/lang/Object;
InterfaceMethod	scala/Function1.apply:(Ljava/lang/Object;)Ljava/lang/Object;
Asciz	scala/collection/TraversableLike;
class	scala/collection/TraversableLike
Asciz	boxToLong;
Asciz	(J)Ljava/lang/Long;;
NameAndType	boxToLong:(J)Ljava/lang/Long;
Method	scala/runtime/BoxesRunTime.boxToLong:(J)Ljava/lang/Long;
Asciz	scala/collection/Iterable;
class	scala/collection/Iterable
Asciz	repr;
Asciz	()Ljava/lang/Object;;
NameAndType	repr:()Ljava/lang/Object;
InterfaceMethod	scala/collection/TraversableLike.repr:()Ljava/lang/Object;
Asciz	scala/collection/generic/CanBuildFrom;
class	scala/collection/generic/CanBuildFrom
Asciz	(Ljava/lang/Object;)Lscala/collection/mutable/Builder;;
NameAndType	apply:(Ljava/lang/Object;)Lscala/collection/mutable/Builder;
InterfaceMethod	scala/collection/generic/CanBuildFrom.apply:(Ljava/lang/Object;)Lscala/collection/mutable/Builder;
Asciz	scala/collection/IterableLike;
class	scala/collection/IterableLike
Asciz	iterator;
Asciz	()Lscala/collection/Iterator;;
NameAndType	iterator:()Lscala/collection/Iterator;
InterfaceMethod	scala/collection/IterableLike.iterator:()Lscala/collection/Iterator;
Asciz	scala/Tuple2$mcDL$sp$$anonfun$zip$mcDL$sp$1;
class	scala/Tuple2$mcDL$sp$$anonfun$zip$mcDL$sp$1
Asciz	(Lscala/Tuple2$mcDL$sp;Lscala/collection/mutable/Builder;Lscala/collection/Iterator;)V;
NameAndType	"<init>":(Lscala/Tuple2$mcDL$sp;Lscala/collection/mutable/Builder;Lscala/collection/Iterator;)V
Method	scala/Tuple2$mcDL$sp$$anonfun$zip$mcDL$sp$1."<init>":(Lscala/Tuple2$mcDL$sp;Lscala/collection/mutable/Builder;Lscala/collection/Iterator;)V
Asciz	foreach;
Asciz	(Lscala/Function1;)V;
NameAndType	foreach:(Lscala/Function1;)V
InterfaceMethod	scala/collection/TraversableLike.foreach:(Lscala/Function1;)V
Asciz	scala/collection/mutable/Builder;
class	scala/collection/mutable/Builder
Asciz	result;
NameAndType	result:()Ljava/lang/Object;
InterfaceMethod	scala/collection/mutable/Builder.result:()Ljava/lang/Object;
Asciz	coll1;
Asciz	Lscala/collection/TraversableLike;;
Asciz	coll2;
Asciz	Lscala/collection/Iterable;;
Asciz	b1$10;
Asciz	Lscala/collection/mutable/Builder;;
Asciz	elems2$15;
Asciz	Lscala/collection/Iterator;;
Asciz	zipped;
Asciz	(Lscala/Function1;Lscala/Function1;)Lscala/Tuple2$Zipped;;
Asciz	zipped$mcDL$sp;
NameAndType	zipped$mcDL$sp:(Lscala/Function1;Lscala/Function1;)Lscala/Tuple2$Zipped;
Method	scala/Tuple2$mcDL$sp.zipped$mcDL$sp:(Lscala/Function1;Lscala/Function1;)Lscala/Tuple2$Zipped;
Asciz	<Repr1:Ljava/lang/Object;El1:Ljava/lang/Object;Repr2:Ljava/lang/Object;El2:Ljava/lang/Object;>(Lscala/Function1<Ljava/lang/Double;Lscala/collection/TraversableLike<TEl1;TRepr1;>;>;Lscala/Function1<Ljava/lang/Long;Lscala/collection/IterableLike<TEl2;TRepr2;>;>;)Lscala/Tuple2<Ljava/lang/Double;Ljava/lang/Long;>.Zipped<TRepr1;TEl1;TRepr2;TEl2;>;;
Asciz	scala/Tuple2$Zipped;
class	scala/Tuple2$Zipped
Asciz	(Lscala/Tuple2;Lscala/collection/TraversableLike;Lscala/collection/IterableLike;)V;
NameAndType	"<init>":(Lscala/Tuple2;Lscala/collection/TraversableLike;Lscala/collection/IterableLike;)V
Method	scala/Tuple2$Zipped."<init>":(Lscala/Tuple2;Lscala/collection/TraversableLike;Lscala/collection/IterableLike;)V
Asciz	(DJ)V;
Asciz	scala/Tuple2;
class	scala/Tuple2
Asciz	(Ljava/lang/Object;Ljava/lang/Object;)V;
NameAndType	"<init>":(Ljava/lang/Object;Ljava/lang/Object;)V
Method	scala/Tuple2."<init>":(Ljava/lang/Object;Ljava/lang/Object;)V
Asciz	Scala;
Asciz	Lscala/Tuple2<Ljava/lang/Double;Ljava/lang/Long;>;;
Asciz	InnerClasses;
Asciz	Zipped;
Asciz	$anonfun$zip$mcDL$sp$1;

{
public final double _1$mcD$sp;
  Signature: D

public final long _2$mcL$sp;
  Signature: J

public double _1$mcD$sp();
  Signature: ()D
  Code:
   Stack=2, Locals=1, Args_size=1
	aload_0
	getfield	Field _1$mcD$sp:D
	dreturn
  Labels:

public double _1();
  Signature: ()D
  Code:
   Stack=2, Locals=1, Args_size=1
	aload_0
	invokevirtual	Method _1$mcD$sp:()D
	dreturn
  Labels:

public long _2$mcL$sp();
  Signature: ()J
  Code:
   Stack=2, Locals=1, Args_size=1
	aload_0
	getfield	Field _2$mcL$sp:J
	lreturn
  Labels:

public long _2();
  Signature: ()J
  Code:
   Stack=2, Locals=1, Args_size=1
	aload_0
	invokevirtual	Method _2$mcL$sp:()J
	lreturn
  Labels:

public scala.Tuple2 swap();
  Signature: ()Lscala/Tuple2;
  Code:
   Stack=1, Locals=1, Args_size=1
	aload_0
	invokevirtual	Method swap$mcDL$sp:()Lscala/Tuple2;
	areturn
  Labels:
  Signature: length = 0x2
   00 1C 

public scala.Tuple2 swap$mcDL$sp();
  Signature: ()Lscala/Tuple2;
  Code:
   Stack=6, Locals=1, Args_size=1
	new	class scala/Tuple2$mcLD$sp
	dup
	aload_0
	invokevirtual	Method _2:()J
	aload_0
	invokevirtual	Method _1:()D
	invokespecial	Method scala/Tuple2$mcLD$sp."<init>":(JD)V
	areturn
  Labels:
  Signature: length = 0x2
   00 1C 

public java.lang.Object zip(scala.Function1, scala.Function1, scala.collection.generic.CanBuildFrom);
  Signature: (Lscala/Function1;Lscala/Function1;Lscala/collection/generic/CanBuildFrom;)Ljava/lang/Object;
  Code:
   Stack=4, Locals=4, Args_size=4
	aload_0
	aload_1
	aload_2
	aload_3
	invokevirtual	Method zip$mcDL$sp:(Lscala/Function1;Lscala/Function1;Lscala/collection/generic/CanBuildFrom;)Ljava/lang/Object;
	areturn
  Labels:
  LocalVariableTable: 
   Start  Length  Slot  Name   Signature
   0      8      0    this       Lscala/Tuple2$mcDL$sp;
   0      8      1    w1       Lscala/Function1;
   0      8      2    w2       Lscala/Function1;
   0      8      3    cbf1       Lscala/collection/generic/CanBuildFrom;

  Signature: length = 0x2
   00 35 

public java.lang.Object zip$mcDL$sp(scala.Function1, scala.Function1, scala.collection.generic.CanBuildFrom);
  Signature: (Lscala/Function1;Lscala/Function1;Lscala/collection/generic/CanBuildFrom;)Ljava/lang/Object;
  Code:
   Stack=6, Locals=12, Args_size=4
	aload_1
	aload_0
	invokevirtual	Method _1:()D
	dstore	5
	dload	5
	invokestatic	Method scala/runtime/BoxesRunTime.boxToDouble:(D)Ljava/lang/Double;
	invokeinterface	InterfaceMethod scala/Function1.apply:(Ljava/lang/Object;)Ljava/lang/Object;
	checkcast	class scala/collection/TraversableLike
	astore	4
	aload_2
	aload_0
	invokevirtual	Method _2:()J
	lstore	8
	lload	8
	invokestatic	Method scala/runtime/BoxesRunTime.boxToLong:(J)Ljava/lang/Long;
	invokeinterface	InterfaceMethod scala/Function1.apply:(Ljava/lang/Object;)Ljava/lang/Object;
	checkcast	class scala/collection/Iterable
	astore	7
	aload_3
	aload	4
	invokeinterface	InterfaceMethod scala/collection/TraversableLike.repr:()Ljava/lang/Object;
	invokeinterface	InterfaceMethod scala/collection/generic/CanBuildFrom.apply:(Ljava/lang/Object;)Lscala/collection/mutable/Builder;
	astore	10
	aload	7
	invokeinterface	InterfaceMethod scala/collection/IterableLike.iterator:()Lscala/collection/Iterator;
	astore	11
	aload	4
	new	class scala/Tuple2$mcDL$sp$$anonfun$zip$mcDL$sp$1
	dup
	aload_0
	aload	10
	aload	11
	invokespecial	Method scala/Tuple2$mcDL$sp$$anonfun$zip$mcDL$sp$1."<init>":(Lscala/Tuple2$mcDL$sp;Lscala/collection/mutable/Builder;Lscala/collection/Iterator;)V
	invokeinterface	InterfaceMethod scala/collection/TraversableLike.foreach:(Lscala/Function1;)V
	aload	10
	invokeinterface	InterfaceMethod scala/collection/mutable/Builder.result:()Ljava/lang/Object;
	areturn
  Labels:
  LocalVariableTable: 
   Start  Length  Slot  Name   Signature
   0      95      0    this       Lscala/Tuple2$mcDL$sp;
   0      95      1    w1       Lscala/Function1;
   0      95      2    w2       Lscala/Function1;
   0      95      3    cbf1       Lscala/collection/generic/CanBuildFrom;
   22      72      4    coll1       Lscala/collection/TraversableLike;
   44      50      7    coll2       Lscala/collection/Iterable;
   59      35      10    b1$10       Lscala/collection/mutable/Builder;
   68      26      11    elems2$15       Lscala/collection/Iterator;

  Signature: length = 0x2
   00 35 

public scala.Tuple2$Zipped zipped(scala.Function1, scala.Function1);
  Signature: (Lscala/Function1;Lscala/Function1;)Lscala/Tuple2$Zipped;
  Code:
   Stack=3, Locals=3, Args_size=3
	aload_0
	aload_1
	aload_2
	invokevirtual	Method zipped$mcDL$sp:(Lscala/Function1;Lscala/Function1;)Lscala/Tuple2$Zipped;
	areturn
  Labels:
  LocalVariableTable: 
   Start  Length  Slot  Name   Signature
   0      7      0    this       Lscala/Tuple2$mcDL$sp;
   0      7      1    w1       Lscala/Function1;
   0      7      2    w2       Lscala/Function1;

  Signature: length = 0x2
   00 74 

public scala.Tuple2$Zipped zipped$mcDL$sp(scala.Function1, scala.Function1);
  Signature: (Lscala/Function1;Lscala/Function1;)Lscala/Tuple2$Zipped;
  Code:
   Stack=7, Locals=7, Args_size=3
	new	class scala/Tuple2$Zipped
	dup
	aload_0
	aload_1
	aload_0
	invokevirtual	Method _1:()D
	dstore_3
	dload_3
	invokestatic	Method scala/runtime/BoxesRunTime.boxToDouble:(D)Ljava/lang/Double;
	invokeinterface	InterfaceMethod scala/Function1.apply:(Ljava/lang/Object;)Ljava/lang/Object;
	checkcast	class scala/collection/TraversableLike
	aload_2
	aload_0
	invokevirtual	Method _2:()J
	lstore	5
	lload	5
	invokestatic	Method scala/runtime/BoxesRunTime.boxToLong:(J)Ljava/lang/Long;
	invokeinterface	InterfaceMethod scala/Function1.apply:(Ljava/lang/Object;)Ljava/lang/Object;
	checkcast	class scala/collection/IterableLike
	invokespecial	Method scala/Tuple2$Zipped."<init>":(Lscala/Tuple2;Lscala/collection/TraversableLike;Lscala/collection/IterableLike;)V
	areturn
  Labels:
  LocalVariableTable: 
   Start  Length  Slot  Name   Signature
   0      47      0    this       Lscala/Tuple2$mcDL$sp;
   0      47      1    w1       Lscala/Function1;
   0      47      2    w2       Lscala/Function1;

  Signature: length = 0x2
   00 74 

public java.lang.Object _2();
  Signature: ()Ljava/lang/Object;
  Code:
   Stack=2, Locals=3, Args_size=1
	aload_0
	invokevirtual	Method _2:()J
	lstore_1
	lload_1
	invokestatic	Method scala/runtime/BoxesRunTime.boxToLong:(J)Ljava/lang/Long;
	areturn
  Labels:

public java.lang.Object _1();
  Signature: ()Ljava/lang/Object;
  Code:
   Stack=2, Locals=3, Args_size=1
	aload_0
	invokevirtual	Method _1:()D
	dstore_1
	dload_1
	invokestatic	Method scala/runtime/BoxesRunTime.boxToDouble:(D)Ljava/lang/Double;
	areturn
  Labels:

public scala.Tuple2$mcDL$sp(double, long);
  Signature: (DJ)V
  Code:
   Stack=4, Locals=5, Args_size=3
	aload_0
	dload_1
	putfield	Field _1$mcD$sp:D
	aload_0
	lload_3
	putfield	Field _2$mcL$sp:J
	aload_0
	dload_1
	invokestatic	Method scala/runtime/BoxesRunTime.boxToDouble:(D)Ljava/lang/Double;
	lload_3
	invokestatic	Method scala/runtime/BoxesRunTime.boxToLong:(J)Ljava/lang/Long;
	invokespecial	Method scala/Tuple2."<init>":(Ljava/lang/Object;Ljava/lang/Object;)V
	return
  Labels:
  LocalVariableTable: 
   Start  Length  Slot  Name   Signature
   0      23      0    this       Lscala/Tuple2$mcDL$sp;
   0      23      1    _1$mcD$sp       D
   0      23      3    _2$mcL$sp       J


}

