Compiled from "Tuple10.scala"
public class scala.Tuple10 extends java.lang.Object implements scala.Product10,scala.ScalaObject,scala.Product,java.io.Serializable
  SourceFile: "Tuple10.scala"
  ScalaSig: length = 0x3
   05 00 00 
  Signature: length = 0x2
   00 FFFFFFE1 
  RuntimeVisibleAnnotations: length = 0xB
   00 01 00 FFFFFFE2 00 01 00 FFFFFFE3 73 00 FFFFFFE4 
  minor version: 0
  major version: 49
  Constant pool:
Asciz	SourceFile;
Asciz	Tuple10.scala;
Asciz	_1;
Asciz	Ljava/lang/Object;;
Asciz	TT1;;
Asciz	Signature;
Asciz	_2;
Asciz	TT2;;
Asciz	_3;
Asciz	TT3;;
Asciz	_4;
Asciz	TT4;;
Asciz	_5;
Asciz	TT5;;
Asciz	_6;
Asciz	TT6;;
Asciz	_7;
Asciz	TT7;;
Asciz	_8;
Asciz	TT8;;
Asciz	_9;
Asciz	TT9;;
Asciz	_10;
Asciz	TT10;;
Asciz	productArity;
Asciz	()I;
Asciz	Code;
Asciz	LineNumberTable;
Asciz	scala/Product10$class;
class	scala/Product10$class
Asciz	(Lscala/Product10;)I;
NameAndType	productArity:(Lscala/Product10;)I
Method	scala/Product10$class.productArity:(Lscala/Product10;)I
Asciz	productElement;
Asciz	(I)Ljava/lang/Object;;
Asciz	(Lscala/Product10;I)Ljava/lang/Object;;
NameAndType	productElement:(Lscala/Product10;I)Ljava/lang/Object;
Method	scala/Product10$class.productElement:(Lscala/Product10;I)Ljava/lang/Object;
Asciz	this;
Asciz	Lscala/Tuple10;;
Asciz	n;
Asciz	I;
Asciz	LocalVariableTable;
Asciz	java/lang/IndexOutOfBoundsException;
class	java/lang/IndexOutOfBoundsException
Asciz	Exceptions;
Asciz	productElementName;
Asciz	(I)Ljava/lang/String;;
Asciz	scala/Product$class;
class	scala/Product$class
Asciz	(Lscala/Product;I)Ljava/lang/String;;
NameAndType	productElementName:(Lscala/Product;I)Ljava/lang/String;
Method	scala/Product$class.productElementName:(Lscala/Product;I)Ljava/lang/String;
Asciz	productIterator;
Asciz	()Lscala/collection/Iterator;;
Asciz	(Lscala/Product;)Lscala/collection/Iterator;;
NameAndType	productIterator:(Lscala/Product;)Lscala/collection/Iterator;
Method	scala/Product$class.productIterator:(Lscala/Product;)Lscala/collection/Iterator;
Asciz	productElements;
NameAndType	productElements:(Lscala/Product;)Lscala/collection/Iterator;
Method	scala/Product$class.productElements:(Lscala/Product;)Lscala/collection/Iterator;
Asciz	Deprecated;
Asciz	copy$default$10;
Asciz	()Ljava/lang/Object;;
Asciz	scala/Tuple10;
class	scala/Tuple10
NameAndType	_10:()Ljava/lang/Object;
Method	scala/Tuple10._10:()Ljava/lang/Object;
Asciz	copy$default$9;
NameAndType	_9:()Ljava/lang/Object;
Method	scala/Tuple10._9:()Ljava/lang/Object;
Asciz	copy$default$8;
NameAndType	_8:()Ljava/lang/Object;
Method	scala/Tuple10._8:()Ljava/lang/Object;
Asciz	copy$default$7;
NameAndType	_7:()Ljava/lang/Object;
Method	scala/Tuple10._7:()Ljava/lang/Object;
Asciz	copy$default$6;
NameAndType	_6:()Ljava/lang/Object;
Method	scala/Tuple10._6:()Ljava/lang/Object;
Asciz	copy$default$5;
NameAndType	_5:()Ljava/lang/Object;
Method	scala/Tuple10._5:()Ljava/lang/Object;
Asciz	copy$default$4;
NameAndType	_4:()Ljava/lang/Object;
Method	scala/Tuple10._4:()Ljava/lang/Object;
Asciz	copy$default$3;
NameAndType	_3:()Ljava/lang/Object;
Method	scala/Tuple10._3:()Ljava/lang/Object;
Asciz	copy$default$2;
NameAndType	_2:()Ljava/lang/Object;
Method	scala/Tuple10._2:()Ljava/lang/Object;
Asciz	copy$default$1;
NameAndType	_1:()Ljava/lang/Object;
Method	scala/Tuple10._1:()Ljava/lang/Object;
NameAndType	_1:Ljava/lang/Object;
Field	scala/Tuple10._1:Ljava/lang/Object;
Asciz	()TT1;;
NameAndType	_2:Ljava/lang/Object;
Field	scala/Tuple10._2:Ljava/lang/Object;
Asciz	()TT2;;
NameAndType	_3:Ljava/lang/Object;
Field	scala/Tuple10._3:Ljava/lang/Object;
Asciz	()TT3;;
NameAndType	_4:Ljava/lang/Object;
Field	scala/Tuple10._4:Ljava/lang/Object;
Asciz	()TT4;;
NameAndType	_5:Ljava/lang/Object;
Field	scala/Tuple10._5:Ljava/lang/Object;
Asciz	()TT5;;
NameAndType	_6:Ljava/lang/Object;
Field	scala/Tuple10._6:Ljava/lang/Object;
Asciz	()TT6;;
NameAndType	_7:Ljava/lang/Object;
Field	scala/Tuple10._7:Ljava/lang/Object;
Asciz	()TT7;;
NameAndType	_8:Ljava/lang/Object;
Field	scala/Tuple10._8:Ljava/lang/Object;
Asciz	()TT8;;
NameAndType	_9:Ljava/lang/Object;
Field	scala/Tuple10._9:Ljava/lang/Object;
Asciz	()TT9;;
NameAndType	_10:Ljava/lang/Object;
Field	scala/Tuple10._10:Ljava/lang/Object;
Asciz	()TT10;;
Asciz	toString;
Asciz	()Ljava/lang/String;;
Asciz	scala/collection/mutable/StringBuilder;
class	scala/collection/mutable/StringBuilder
Asciz	<init>;
Asciz	()V;
NameAndType	"<init>":()V
Method	scala/collection/mutable/StringBuilder."<init>":()V
Asciz	(;
String	(
Asciz	append;
Asciz	(Ljava/lang/Object;)Lscala/collection/mutable/StringBuilder;;
NameAndType	append:(Ljava/lang/Object;)Lscala/collection/mutable/StringBuilder;
Method	scala/collection/mutable/StringBuilder.append:(Ljava/lang/Object;)Lscala/collection/mutable/StringBuilder;
Asciz	,;
String	,
Asciz	);
String	)
NameAndType	toString:()Ljava/lang/String;
Method	scala/collection/mutable/StringBuilder.toString:()Ljava/lang/String;
Asciz	copy;
Asciz	(Ljava/lang/Object;Ljava/lang/Object;Ljava/lang/Object;Ljava/lang/Object;Ljava/lang/Object;Ljava/lang/Object;Ljava/lang/Object;Ljava/lang/Object;Ljava/lang/Object;Ljava/lang/Object;)Lscala/Tuple10;;
Asciz	(Ljava/lang/Object;Ljava/lang/Object;Ljava/lang/Object;Ljava/lang/Object;Ljava/lang/Object;Ljava/lang/Object;Ljava/lang/Object;Ljava/lang/Object;Ljava/lang/Object;Ljava/lang/Object;)V;
NameAndType	"<init>":(Ljava/lang/Object;Ljava/lang/Object;Ljava/lang/Object;Ljava/lang/Object;Ljava/lang/Object;Ljava/lang/Object;Ljava/lang/Object;Ljava/lang/Object;Ljava/lang/Object;Ljava/lang/Object;)V
Method	scala/Tuple10."<init>":(Ljava/lang/Object;Ljava/lang/Object;Ljava/lang/Object;Ljava/lang/Object;Ljava/lang/Object;Ljava/lang/Object;Ljava/lang/Object;Ljava/lang/Object;Ljava/lang/Object;Ljava/lang/Object;)V
Asciz	hashCode;
Asciz	scala/runtime/ScalaRunTime$;
class	scala/runtime/ScalaRunTime$
Asciz	MODULE$;
Asciz	Lscala/runtime/ScalaRunTime$;;
NameAndType	MODULE$:Lscala/runtime/ScalaRunTime$;
Field	scala/runtime/ScalaRunTime$.MODULE$:Lscala/runtime/ScalaRunTime$;
Asciz	_hashCode;
Asciz	(Lscala/Product;)I;
NameAndType	_hashCode:(Lscala/Product;)I
Method	scala/runtime/ScalaRunTime$._hashCode:(Lscala/Product;)I
Asciz	equals;
Asciz	(Ljava/lang/Object;)Z;
Asciz	gd1$1;
Asciz	(Ljava/lang/Object;Ljava/lang/Object;Ljava/lang/Object;Ljava/lang/Object;Ljava/lang/Object;Ljava/lang/Object;Ljava/lang/Object;Ljava/lang/Object;Ljava/lang/Object;Ljava/lang/Object;)Z;
NameAndType	gd1$1:(Ljava/lang/Object;Ljava/lang/Object;Ljava/lang/Object;Ljava/lang/Object;Ljava/lang/Object;Ljava/lang/Object;Ljava/lang/Object;Ljava/lang/Object;Ljava/lang/Object;Ljava/lang/Object;)Z
Method	scala/Tuple10.gd1$1:(Ljava/lang/Object;Ljava/lang/Object;Ljava/lang/Object;Ljava/lang/Object;Ljava/lang/Object;Ljava/lang/Object;Ljava/lang/Object;Ljava/lang/Object;Ljava/lang/Object;Ljava/lang/Object;)Z
Asciz	scala/Equals;
class	scala/Equals
Asciz	canEqual;
NameAndType	canEqual:(Ljava/lang/Object;)Z
InterfaceMethod	scala/Equals.canEqual:(Ljava/lang/Object;)Z
Asciz	temp2;
Asciz	temp3;
Asciz	temp4;
Asciz	temp5;
Asciz	temp6;
Asciz	temp7;
Asciz	temp8;
Asciz	temp9;
Asciz	temp10;
Asciz	temp11;
Asciz	temp12;
Asciz	productPrefix;
Asciz	Tuple10;
String	Tuple10
Asciz	java/lang/Number;
class	java/lang/Number
Asciz	scala/runtime/BoxesRunTime;
class	scala/runtime/BoxesRunTime
Asciz	equalsNumObject;
Asciz	(Ljava/lang/Number;Ljava/lang/Object;)Z;
NameAndType	equalsNumObject:(Ljava/lang/Number;Ljava/lang/Object;)Z
Method	scala/runtime/BoxesRunTime.equalsNumObject:(Ljava/lang/Number;Ljava/lang/Object;)Z
Asciz	java/lang/Character;
class	java/lang/Character
Asciz	equalsCharObject;
Asciz	(Ljava/lang/Character;Ljava/lang/Object;)Z;
NameAndType	equalsCharObject:(Ljava/lang/Character;Ljava/lang/Object;)Z
Method	scala/runtime/BoxesRunTime.equalsCharObject:(Ljava/lang/Character;Ljava/lang/Object;)Z
Asciz	java/lang/Object;
class	java/lang/Object
NameAndType	equals:(Ljava/lang/Object;)Z
Method	java/lang/Object.equals:(Ljava/lang/Object;)Z
Asciz	y0;
Asciz	y1;
Asciz	y2;
Asciz	y3;
Asciz	y4;
Asciz	y5;
Asciz	y6;
Asciz	y7;
Asciz	y8;
Asciz	y9;
Method	java/lang/Object."<init>":()V
Asciz	$init$;
Asciz	(Lscala/Product;)V;
NameAndType	$init$:(Lscala/Product;)V
Method	scala/Product$class.$init$:(Lscala/Product;)V
Asciz	(Lscala/Product10;)V;
NameAndType	$init$:(Lscala/Product10;)V
Method	scala/Product10$class.$init$:(Lscala/Product10;)V
Asciz	(TT1;TT2;TT3;TT4;TT5;TT6;TT7;TT8;TT9;TT10;)V;
Asciz	ScalaSig;
Asciz	<T1:Ljava/lang/Object;T2:Ljava/lang/Object;T3:Ljava/lang/Object;T4:Ljava/lang/Object;T5:Ljava/lang/Object;T6:Ljava/lang/Object;T7:Ljava/lang/Object;T8:Ljava/lang/Object;T9:Ljava/lang/Object;T10:Ljava/lang/Object;>Ljava/lang/Object;Lscala/Product10<TT1;TT2;TT3;TT4;TT5;TT6;TT7;TT8;TT9;TT10;>;Lscala/ScalaObject;Lscala/Product;;
Asciz	Lscala/reflect/ScalaSignature;;
Asciz	bytes;
Asciz	\rubBqV;qYGC8-7b)2BB EB3FL5oM)aB:yA\"D)!bCYtwMC\rQM^1\n9I!AB(cUG#MqJ+[Ad'D\t\"AAQe>$Wo;2aAA#\t!1\"A9\"A+2#\tA23%!D>$.8h!\tB$\tI\=QyB\t%)AQC#\t!\"A9\"A+4!\t!R'IQ1\t!FQAC\nqCUkAAc\tY!\t\"b/\tAK\t)9\"b\ra)^\"FIA!CC]!Q!DC\t%)AQKC8\t!A\"A9\"a+2aACOw\t1bU2bY|%M[3diB#P}\tq:pIVGA\tU\r\"B\ty'F!A!E!aA02A!AQ\tBKa)`eU\taI\tE\t!\ry&\t\t)!CqlMC!AQ\nB\tB%%A`gBb%\tU?R*\n\t%\t)AIq\tQ!Q3AU!aXBbIaJ?VC-+I.}3T#\tq!#Q\n)\n1a!!qA!f\nyAA08+iC1#B};d\tU\r\"e\ty(F1!1A!E!aA09A!ABK.`sU\t1l\tE\t!4\ry\t\t[)!C]q,\rYBIAN?FCs1/=S:LGOiV4x_={wrlhMqJ+[AdCAc1CFcaCKcCPcACUcqCZc!C_cQCdcCic1CncaC!\t%aQ|7:j]$\"!!!\t9!C\n%aa;sS:<\"CAIAAw]=-EqCA?\t#a\n,=1GAw!b#a>}IA\"\n9%!L5q\n\t!\t)\"!QEA[\t\t$!:AA#aY\tY\"A9cI%a\ra\t)}A!C\tQ1!\r!1\nM-A!AC]2FA\t%I1CqEW!LA\t)AQ\tyB0!\t!b/AA#a\rI\nY\"A9c8IQ'a\ra\t)mB!\tQ1%1I\t)CF\n1!I!*aQ\n-!aCAVA!\r!!\n\teY%AA%\"0A\tAA%1I\t\tCi\n16!IQ.a\n'!C+\nabY8qs\"WMZ1vYR$'X-QNA8c\n(!xe1PA?U\rL7B!!h5qC\n'Av]DWmY6fI*Q\rtgn;bi&|g.j}#!E;oG\",7m[3e-.8dKIa#!\ra\nAEC!AC]!bIA)\t)A\n\t\"A9B!CR\tQ1\t%aCqB0#\"\t!b/I!'!\ra\nkEC!AC]!OA)\t)A\t!%A\rAD2paf$C-4bk2$HEM9)!#5qRAI')*a&*a$!Y\ty\"A9B! \tQ1\t%qCqB'\"\t!b/I&a \ra\nY}D!AC]!bLA@\t)AI\ny\"A9B!C \tQ1\t%AqCqC\t\n\" q1m9zI,g-Y;miTCFAQG)+a**-QVAXc,!.+\nIB7#\t!b/I%a'\ra\nGmE!AC]!BJAN\t)A%\nY\n\"A9B!\tQ1\t%y1CqB37#\t!b/IQ'a'\ra\nqmE!AC]A\"!/#%\t!a/\r|/eKW;%iU1QXA`-!2H%1ZAg\tNK%3\"BFA\\t)A\n9\"A9B!C8\tQ1\t%1qCqB*o#\t!b/IA&a.\ra\n_]F!AC]!BMA\\t)AU\n9\"A9B!8\tQ1%\t)AI\n\t9.d_BLHZ3gCVdGJ-e1\Ao?\t/a9f^Av[T3aJA-\t%11CqB!'$\t!b/I1%a5\ra\nMMG!AC]!\"KAj\t)A1\n\"A9B!CT\tQ1\t%1CqB6'$\t!b/I(a5\ra\nc!CgabY8qs\"WMZ1vYR$c'v]`A~{yP!\t!qBU\rQ\n-=H!AC]!IAx\t)A\r\ny\"A9B!p\tQ1\t%IqCqB-_$\t!b/Iq&a<\ra\ne=H!AC]!\"NAx\t)Aa\ny\"A9\"BEIB9w]=%I4-7uI]*bC!\tU!qB\r7iBa\"\t\r\"Q[eC!\tQ1\t%#1CqB$!\t!b/IaEa\ra\nS\t-A!AC]!B\t)A=Y\"A9B!\tQ1\t%)$1CqB9!\t!b/!I!!1FG>\n3fM,H9+YiCa2\tM\"QBsYD!@\t#fZIaCa\n\ra\nA\tB!AC]!b\tB\t)A9\"A9B!C(\tQ1\t%a#qCqB0O!\t!b/I!Ga\n\ra\nk\tB!AC]!B\t)A\t\t!%A\tAD2paf$C-4bk2$H%OYE!P\tE#1B+/IFa^)1'!Y\"A9B!D\tQ1\t%#1\tCqB'\"\t!b/IFa\ra\nY\t\rC!AC]!bB\"\t)AI\"A9B!CD\tQ1\t%A$1\tCqCb\t\n\"dy1m9zI,g-Y;mi\n'f\t$B6[yG!t\tU$qB=U\r1\n-\t}C!AC]!\tB0\t)A\ry\"A9B!`\tQ1\t%I#qCqB-?\"\t!b/IqFa\ra\ne\t}C!AC]!\"B0\t)Aay\"A9BB?\t\" A.Y:i>$W\rBCa!\n\t%AAJ]RD!B!#\tI\tBF)/^1mgR!!QBJ!\r\"qR#!a\"p_2,M\n+9)!AAm\t12)I\nC#1TaJ|G-^2u!J,g-=BBP\t\"\"A1-8FcVG\n\r\"BK;\t1Q\r!q\t!\t%bBV\ta1/:jC2L'02mKI!q#!W)VH.Z1!\r\"1\n\t!!EkBAa-s!9!Oa-\teFCBY)iLa-%qXCBH._9Ma3P\nM'qBn?Oa:lR1\"1Bw_\tPa=v\n]( B~{y\t'Bg#)N!7^\n(QBu!\r!\"q\n-\tmF!AC]2Bf\t%#1CqE$b\tB^\t)AQB'w#\t!b/AACa6%Y\"A9c\IAFa/\ra\t)\t}G!C<\tQ1!\r!\"1\ne\tmF!AC]2Bt\t%)$1CqEW$B^\t)A\tY1F\"9QIa/A\t%b&<!Q\nmBi!&1a+Dq!B^IC_w\rA!8\t\rY1b\"9Na/A\tbB7<!,!AaB;oCBH._ba\r}11EBWyca\r8Q!1BB!21BB\riAB$n8-A1CB3ib!\t&\r%2QFBk2FB\n\t%12CqE/!IB\t)AQYB$!\t!b/AAca\t\"A9c$If!\ra\t)\rB!\tQ1!\r!21\n_\rA!AC]2FB\t%4CqEg!\"NB\t)AQ9B9!\t!b/!A11HBy!AyIA;
Asciz	RuntimeVisibleAnnotations;
Asciz	scala/Product10;
class	scala/Product10
Asciz	scala/ScalaObject;
class	scala/ScalaObject
Asciz	scala/Product;
class	scala/Product
Asciz	java/io/Serializable;
class	java/io/Serializable

{
private final java.lang.Object _1;
  Signature: Ljava/lang/Object;
  Signature: length = 0x2
   00 05 

private final java.lang.Object _2;
  Signature: Ljava/lang/Object;
  Signature: length = 0x2
   00 08 

private final java.lang.Object _3;
  Signature: Ljava/lang/Object;
  Signature: length = 0x2
   00 0A 

private final java.lang.Object _4;
  Signature: Ljava/lang/Object;
  Signature: length = 0x2
   00 0C 

private final java.lang.Object _5;
  Signature: Ljava/lang/Object;
  Signature: length = 0x2
   00 0E 

private final java.lang.Object _6;
  Signature: Ljava/lang/Object;
  Signature: length = 0x2
   00 10 

private final java.lang.Object _7;
  Signature: Ljava/lang/Object;
  Signature: length = 0x2
   00 12 

private final java.lang.Object _8;
  Signature: Ljava/lang/Object;
  Signature: length = 0x2
   00 14 

private final java.lang.Object _9;
  Signature: Ljava/lang/Object;
  Signature: length = 0x2
   00 16 

private final java.lang.Object _10;
  Signature: Ljava/lang/Object;
  Signature: length = 0x2
   00 18 

public int productArity();
  Signature: ()I
  Code:
   Stack=1, Locals=1, Args_size=1
	aload_0
	invokestatic	Method scala/Product10$class.productArity:(Lscala/Product10;)I
	ireturn
  Labels:

public java.lang.Object productElement(int)   throws java.lang.IndexOutOfBoundsException;
  Signature: (I)Ljava/lang/Object;
  Code:
   Stack=2, Locals=2, Args_size=2
	aload_0
	iload_1
	invokestatic	Method scala/Product10$class.productElement:(Lscala/Product10;I)Ljava/lang/Object;
	areturn
  Labels:
  LocalVariableTable: 
   Start  Length  Slot  Name   Signature
   0      6      0    this       Lscala/Tuple10;
   0      6      1    n       I

  Exceptions: 
   throws java.lang.IndexOutOfBoundsException
public java.lang.String productElementName(int);
  Signature: (I)Ljava/lang/String;
  Code:
   Stack=2, Locals=2, Args_size=2
	aload_0
	iload_1
	invokestatic	Method scala/Product$class.productElementName:(Lscala/Product;I)Ljava/lang/String;
	areturn
  Labels:
  LocalVariableTable: 
   Start  Length  Slot  Name   Signature
   0      6      0    this       Lscala/Tuple10;
   0      6      1    n       I


public scala.collection.Iterator productIterator();
  Signature: ()Lscala/collection/Iterator;
  Code:
   Stack=1, Locals=1, Args_size=1
	aload_0
	invokestatic	Method scala/Product$class.productIterator:(Lscala/Product;)Lscala/collection/Iterator;
	areturn
  Labels:

public scala.collection.Iterator productElements();
  Signature: ()Lscala/collection/Iterator;
  Code:
   Stack=1, Locals=1, Args_size=1
	aload_0
	invokestatic	Method scala/Product$class.productElements:(Lscala/Product;)Lscala/collection/Iterator;
	areturn
  Labels:
  Deprecated: true

public java.lang.Object copy$default$10();
  Signature: ()Ljava/lang/Object;
  Code:
   Stack=1, Locals=1, Args_size=1
	aload_0
	invokevirtual	Method _10:()Ljava/lang/Object;
	areturn
  Labels:

public java.lang.Object copy$default$9();
  Signature: ()Ljava/lang/Object;
  Code:
   Stack=1, Locals=1, Args_size=1
	aload_0
	invokevirtual	Method _9:()Ljava/lang/Object;
	areturn
  Labels:

public java.lang.Object copy$default$8();
  Signature: ()Ljava/lang/Object;
  Code:
   Stack=1, Locals=1, Args_size=1
	aload_0
	invokevirtual	Method _8:()Ljava/lang/Object;
	areturn
  Labels:

public java.lang.Object copy$default$7();
  Signature: ()Ljava/lang/Object;
  Code:
   Stack=1, Locals=1, Args_size=1
	aload_0
	invokevirtual	Method _7:()Ljava/lang/Object;
	areturn
  Labels:

public java.lang.Object copy$default$6();
  Signature: ()Ljava/lang/Object;
  Code:
   Stack=1, Locals=1, Args_size=1
	aload_0
	invokevirtual	Method _6:()Ljava/lang/Object;
	areturn
  Labels:

public java.lang.Object copy$default$5();
  Signature: ()Ljava/lang/Object;
  Code:
   Stack=1, Locals=1, Args_size=1
	aload_0
	invokevirtual	Method _5:()Ljava/lang/Object;
	areturn
  Labels:

public java.lang.Object copy$default$4();
  Signature: ()Ljava/lang/Object;
  Code:
   Stack=1, Locals=1, Args_size=1
	aload_0
	invokevirtual	Method _4:()Ljava/lang/Object;
	areturn
  Labels:

public java.lang.Object copy$default$3();
  Signature: ()Ljava/lang/Object;
  Code:
   Stack=1, Locals=1, Args_size=1
	aload_0
	invokevirtual	Method _3:()Ljava/lang/Object;
	areturn
  Labels:

public java.lang.Object copy$default$2();
  Signature: ()Ljava/lang/Object;
  Code:
   Stack=1, Locals=1, Args_size=1
	aload_0
	invokevirtual	Method _2:()Ljava/lang/Object;
	areturn
  Labels:

public java.lang.Object copy$default$1();
  Signature: ()Ljava/lang/Object;
  Code:
   Stack=1, Locals=1, Args_size=1
	aload_0
	invokevirtual	Method _1:()Ljava/lang/Object;
	areturn
  Labels:

public java.lang.Object _1();
  Signature: ()Ljava/lang/Object;
  Code:
   Stack=1, Locals=1, Args_size=1
	aload_0
	getfield	Field _1:Ljava/lang/Object;
	areturn
  Labels:
  Signature: length = 0x2
   00 62 

public java.lang.Object _2();
  Signature: ()Ljava/lang/Object;
  Code:
   Stack=1, Locals=1, Args_size=1
	aload_0
	getfield	Field _2:Ljava/lang/Object;
	areturn
  Labels:
  Signature: length = 0x2
   00 65 

public java.lang.Object _3();
  Signature: ()Ljava/lang/Object;
  Code:
   Stack=1, Locals=1, Args_size=1
	aload_0
	getfield	Field _3:Ljava/lang/Object;
	areturn
  Labels:
  Signature: length = 0x2
   00 68 

public java.lang.Object _4();
  Signature: ()Ljava/lang/Object;
  Code:
   Stack=1, Locals=1, Args_size=1
	aload_0
	getfield	Field _4:Ljava/lang/Object;
	areturn
  Labels:
  Signature: length = 0x2
   00 6B 

public java.lang.Object _5();
  Signature: ()Ljava/lang/Object;
  Code:
   Stack=1, Locals=1, Args_size=1
	aload_0
	getfield	Field _5:Ljava/lang/Object;
	areturn
  Labels:
  Signature: length = 0x2
   00 6E 

public java.lang.Object _6();
  Signature: ()Ljava/lang/Object;
  Code:
   Stack=1, Locals=1, Args_size=1
	aload_0
	getfield	Field _6:Ljava/lang/Object;
	areturn
  Labels:
  Signature: length = 0x2
   00 71 

public java.lang.Object _7();
  Signature: ()Ljava/lang/Object;
  Code:
   Stack=1, Locals=1, Args_size=1
	aload_0
	getfield	Field _7:Ljava/lang/Object;
	areturn
  Labels:
  Signature: length = 0x2
   00 74 

public java.lang.Object _8();
  Signature: ()Ljava/lang/Object;
  Code:
   Stack=1, Locals=1, Args_size=1
	aload_0
	getfield	Field _8:Ljava/lang/Object;
	areturn
  Labels:
  Signature: length = 0x2
   00 77 

public java.lang.Object _9();
  Signature: ()Ljava/lang/Object;
  Code:
   Stack=1, Locals=1, Args_size=1
	aload_0
	getfield	Field _9:Ljava/lang/Object;
	areturn
  Labels:
  Signature: length = 0x2
   00 7A 

public java.lang.Object _10();
  Signature: ()Ljava/lang/Object;
  Code:
   Stack=1, Locals=1, Args_size=1
	aload_0
	getfield	Field _10:Ljava/lang/Object;
	areturn
  Labels:
  Signature: length = 0x2
   00 7D 

public java.lang.String toString();
  Signature: ()Ljava/lang/String;
  Code:
   Stack=2, Locals=1, Args_size=1
	new	class scala/collection/mutable/StringBuilder
	dup
	invokespecial	Method scala/collection/mutable/StringBuilder."<init>":()V
	ldc	String (
	invokevirtual	Method scala/collection/mutable/StringBuilder.append:(Ljava/lang/Object;)Lscala/collection/mutable/StringBuilder;
	aload_0
	invokevirtual	Method _1:()Ljava/lang/Object;
	invokevirtual	Method scala/collection/mutable/StringBuilder.append:(Ljava/lang/Object;)Lscala/collection/mutable/StringBuilder;
	ldc	String ,
	invokevirtual	Method scala/collection/mutable/StringBuilder.append:(Ljava/lang/Object;)Lscala/collection/mutable/StringBuilder;
	aload_0
	invokevirtual	Method _2:()Ljava/lang/Object;
	invokevirtual	Method scala/collection/mutable/StringBuilder.append:(Ljava/lang/Object;)Lscala/collection/mutable/StringBuilder;
	ldc	String ,
	invokevirtual	Method scala/collection/mutable/StringBuilder.append:(Ljava/lang/Object;)Lscala/collection/mutable/StringBuilder;
	aload_0
	invokevirtual	Method _3:()Ljava/lang/Object;
	invokevirtual	Method scala/collection/mutable/StringBuilder.append:(Ljava/lang/Object;)Lscala/collection/mutable/StringBuilder;
	ldc	String ,
	invokevirtual	Method scala/collection/mutable/StringBuilder.append:(Ljava/lang/Object;)Lscala/collection/mutable/StringBuilder;
	aload_0
	invokevirtual	Method _4:()Ljava/lang/Object;
	invokevirtual	Method scala/collection/mutable/StringBuilder.append:(Ljava/lang/Object;)Lscala/collection/mutable/StringBuilder;
	ldc	String ,
	invokevirtual	Method scala/collection/mutable/StringBuilder.append:(Ljava/lang/Object;)Lscala/collection/mutable/StringBuilder;
	aload_0
	invokevirtual	Method _5:()Ljava/lang/Object;
	invokevirtual	Method scala/collection/mutable/StringBuilder.append:(Ljava/lang/Object;)Lscala/collection/mutable/StringBuilder;
	ldc	String ,
	invokevirtual	Method scala/collection/mutable/StringBuilder.append:(Ljava/lang/Object;)Lscala/collection/mutable/StringBuilder;
	aload_0
	invokevirtual	Method _6:()Ljava/lang/Object;
	invokevirtual	Method scala/collection/mutable/StringBuilder.append:(Ljava/lang/Object;)Lscala/collection/mutable/StringBuilder;
	ldc	String ,
	invokevirtual	Method scala/collection/mutable/StringBuilder.append:(Ljava/lang/Object;)Lscala/collection/mutable/StringBuilder;
	aload_0
	invokevirtual	Method _7:()Ljava/lang/Object;
	invokevirtual	Method scala/collection/mutable/StringBuilder.append:(Ljava/lang/Object;)Lscala/collection/mutable/StringBuilder;
	ldc	String ,
	invokevirtual	Method scala/collection/mutable/StringBuilder.append:(Ljava/lang/Object;)Lscala/collection/mutable/StringBuilder;
	aload_0
	invokevirtual	Method _8:()Ljava/lang/Object;
	invokevirtual	Method scala/collection/mutable/StringBuilder.append:(Ljava/lang/Object;)Lscala/collection/mutable/StringBuilder;
	ldc	String ,
	invokevirtual	Method scala/collection/mutable/StringBuilder.append:(Ljava/lang/Object;)Lscala/collection/mutable/StringBuilder;
	aload_0
	invokevirtual	Method _9:()Ljava/lang/Object;
	invokevirtual	Method scala/collection/mutable/StringBuilder.append:(Ljava/lang/Object;)Lscala/collection/mutable/StringBuilder;
	ldc	String ,
	invokevirtual	Method scala/collection/mutable/StringBuilder.append:(Ljava/lang/Object;)Lscala/collection/mutable/StringBuilder;
	aload_0
	invokevirtual	Method _10:()Ljava/lang/Object;
	invokevirtual	Method scala/collection/mutable/StringBuilder.append:(Ljava/lang/Object;)Lscala/collection/mutable/StringBuilder;
	ldc	String )
	invokevirtual	Method scala/collection/mutable/StringBuilder.append:(Ljava/lang/Object;)Lscala/collection/mutable/StringBuilder;
	invokevirtual	Method scala/collection/mutable/StringBuilder.toString:()Ljava/lang/String;
	areturn
  Labels:

public scala.Tuple10 copy(java.lang.Object, java.lang.Object, java.lang.Object, java.lang.Object, java.lang.Object, java.lang.Object, java.lang.Object, java.lang.Object, java.lang.Object, java.lang.Object);
  Signature: (Ljava/lang/Object;Ljava/lang/Object;Ljava/lang/Object;Ljava/lang/Object;Ljava/lang/Object;Ljava/lang/Object;Ljava/lang/Object;Ljava/lang/Object;Ljava/lang/Object;Ljava/lang/Object;)Lscala/Tuple10;
  Code:
   Stack=12, Locals=11, Args_size=11
	new	class scala/Tuple10
	dup
	aload_1
	aload_2
	aload_3
	aload	4
	aload	5
	aload	6
	aload	7
	aload	8
	aload	9
	aload	10
	invokespecial	Method "<init>":(Ljava/lang/Object;Ljava/lang/Object;Ljava/lang/Object;Ljava/lang/Object;Ljava/lang/Object;Ljava/lang/Object;Ljava/lang/Object;Ljava/lang/Object;Ljava/lang/Object;Ljava/lang/Object;)V
	areturn
  Labels:
  LocalVariableTable: 
   Start  Length  Slot  Name   Signature
   0      25      0    this       Lscala/Tuple10;
   0      25      1    _1       Ljava/lang/Object;
   0      25      2    _2       Ljava/lang/Object;
   0      25      3    _3       Ljava/lang/Object;
   0      25      4    _4       Ljava/lang/Object;
   0      25      5    _5       Ljava/lang/Object;
   0      25      6    _6       Ljava/lang/Object;
   0      25      7    _7       Ljava/lang/Object;
   0      25      8    _8       Ljava/lang/Object;
   0      25      9    _9       Ljava/lang/Object;
   0      25      10    _10       Ljava/lang/Object;


public int hashCode();
  Signature: ()I
  Code:
   Stack=2, Locals=1, Args_size=1
	getstatic	Field scala/runtime/ScalaRunTime$.MODULE$:Lscala/runtime/ScalaRunTime$;
	aload_0
	invokevirtual	Method scala/runtime/ScalaRunTime$._hashCode:(Lscala/Product;)I
	ireturn
  Labels:

public boolean equals(java.lang.Object);
  Signature: (Ljava/lang/Object;)Z
  Code:
   Stack=11, Locals=13, Args_size=2
	aload_0
	aload_1
	if_acmpeq	l1 // iconst_1
	aload_1
	instanceof	class scala/Tuple10
	ifeq	l2 // iconst_0
	aload_1
	checkcast	class scala/Tuple10
	astore_2
	aload_2
	invokevirtual	Method _1:()Ljava/lang/Object;
	astore_3
	aload_2
	invokevirtual	Method _2:()Ljava/lang/Object;
	astore	4
	aload_2
	invokevirtual	Method _3:()Ljava/lang/Object;
	astore	5
	aload_2
	invokevirtual	Method _4:()Ljava/lang/Object;
	astore	6
	aload_2
	invokevirtual	Method _5:()Ljava/lang/Object;
	astore	7
	aload_2
	invokevirtual	Method _6:()Ljava/lang/Object;
	astore	8
	aload_2
	invokevirtual	Method _7:()Ljava/lang/Object;
	astore	9
	aload_2
	invokevirtual	Method _8:()Ljava/lang/Object;
	astore	10
	aload_2
	invokevirtual	Method _9:()Ljava/lang/Object;
	astore	11
	aload_2
	invokevirtual	Method _10:()Ljava/lang/Object;
	astore	12
	aload_0
	aload_3
	aload	4
	aload	5
	aload	6
	aload	7
	aload	8
	aload	9
	aload	10
	aload	11
	aload	12
	invokespecial	Method gd1$1:(Ljava/lang/Object;Ljava/lang/Object;Ljava/lang/Object;Ljava/lang/Object;Ljava/lang/Object;Ljava/lang/Object;Ljava/lang/Object;Ljava/lang/Object;Ljava/lang/Object;Ljava/lang/Object;)Z
	ifeq	l3 // iconst_0
	aload_1
	checkcast	class scala/Tuple10
	aload_0
	invokeinterface	InterfaceMethod scala/Equals.canEqual:(Ljava/lang/Object;)Z
	goto	l4 // ifeq
l3	iconst_0
	goto	l4 // ifeq
l2	iconst_0
l4	ifeq	l5 // iconst_0
l1	iconst_1
	goto	l6 // ireturn
l5	iconst_0
l6	ireturn
  Labels:
   	l3 = 115 // iconst_0
   	l2 = 119 // iconst_0
   	l4 = 120 // ifeq
   	l1 = 123 // iconst_1
   	l5 = 127 // iconst_0
   	l6 = 128 // ireturn
  LocalVariableTable: 
   Start  Length  Slot  Name   Signature
   0      129      0    this       Lscala/Tuple10;
   17      102      2    temp2       Lscala/Tuple10;
   22      97      3    temp3       Ljava/lang/Object;
   28      91      4    temp4       Ljava/lang/Object;
   34      85      5    temp5       Ljava/lang/Object;
   40      79      6    temp6       Ljava/lang/Object;
   46      73      7    temp7       Ljava/lang/Object;
   52      67      8    temp8       Ljava/lang/Object;
   58      61      9    temp9       Ljava/lang/Object;
   64      55      10    temp10       Ljava/lang/Object;
   70      49      11    temp11       Ljava/lang/Object;
   76      43      12    temp12       Ljava/lang/Object;


public java.lang.String productPrefix();
  Signature: ()Ljava/lang/String;
  Code:
   Stack=1, Locals=1, Args_size=1
	ldc	String Tuple10
	areturn
  Labels:

public boolean canEqual(java.lang.Object);
  Signature: (Ljava/lang/Object;)Z
  Code:
   Stack=1, Locals=2, Args_size=2
	aload_1
	instanceof	class scala/Tuple10
	ireturn
  Labels:

private final boolean gd1$1(java.lang.Object, java.lang.Object, java.lang.Object, java.lang.Object, java.lang.Object, java.lang.Object, java.lang.Object, java.lang.Object, java.lang.Object, java.lang.Object);
  Signature: (Ljava/lang/Object;Ljava/lang/Object;Ljava/lang/Object;Ljava/lang/Object;Ljava/lang/Object;Ljava/lang/Object;Ljava/lang/Object;Ljava/lang/Object;Ljava/lang/Object;Ljava/lang/Object;)Z
  Code:
   Stack=2, Locals=21, Args_size=11
	aload_0
	invokevirtual	Method _1:()Ljava/lang/Object;
	astore	11
	aload_1
	aload	11
	if_acmpne	l1 // aload_1
	iconst_1
	goto	l2 // ifeq
l1	aload_1
	ifnonnull	l3 // aload_1
	iconst_0
	goto	l2 // ifeq
l3	aload_1
	instanceof	class java/lang/Number
	ifeq	l4 // aload_1
	aload_1
	checkcast	class java/lang/Number
	aload	11
	invokestatic	Method scala/runtime/BoxesRunTime.equalsNumObject:(Ljava/lang/Number;Ljava/lang/Object;)Z
	goto	l2 // ifeq
l4	aload_1
	instanceof	class java/lang/Character
	ifeq	l5 // aload_1
	aload_1
	checkcast	class java/lang/Character
	aload	11
	invokestatic	Method scala/runtime/BoxesRunTime.equalsCharObject:(Ljava/lang/Character;Ljava/lang/Object;)Z
	goto	l2 // ifeq
l5	aload_1
	aload	11
	invokevirtual	Method java/lang/Object.equals:(Ljava/lang/Object;)Z
l2	ifeq	l6 // iconst_0
	aload_0
	invokevirtual	Method _2:()Ljava/lang/Object;
	astore	12
	aload_2
	aload	12
	if_acmpne	l7 // aload_2
	iconst_1
	goto	l8 // ifeq
l7	aload_2
	ifnonnull	l9 // aload_2
	iconst_0
	goto	l8 // ifeq
l9	aload_2
	instanceof	class java/lang/Number
	ifeq	l10 // aload_2
	aload_2
	checkcast	class java/lang/Number
	aload	12
	invokestatic	Method scala/runtime/BoxesRunTime.equalsNumObject:(Ljava/lang/Number;Ljava/lang/Object;)Z
	goto	l8 // ifeq
l10	aload_2
	instanceof	class java/lang/Character
	ifeq	l11 // aload_2
	aload_2
	checkcast	class java/lang/Character
	aload	12
	invokestatic	Method scala/runtime/BoxesRunTime.equalsCharObject:(Ljava/lang/Character;Ljava/lang/Object;)Z
	goto	l8 // ifeq
l11	aload_2
	aload	12
	invokevirtual	Method java/lang/Object.equals:(Ljava/lang/Object;)Z
l8	ifeq	l6 // iconst_0
	aload_0
	invokevirtual	Method _3:()Ljava/lang/Object;
	astore	13
	aload_3
	aload	13
	if_acmpne	l12 // aload_3
	iconst_1
	goto	l13 // ifeq
l12	aload_3
	ifnonnull	l14 // aload_3
	iconst_0
	goto	l13 // ifeq
l14	aload_3
	instanceof	class java/lang/Number
	ifeq	l15 // aload_3
	aload_3
	checkcast	class java/lang/Number
	aload	13
	invokestatic	Method scala/runtime/BoxesRunTime.equalsNumObject:(Ljava/lang/Number;Ljava/lang/Object;)Z
	goto	l13 // ifeq
l15	aload_3
	instanceof	class java/lang/Character
	ifeq	l16 // aload_3
	aload_3
	checkcast	class java/lang/Character
	aload	13
	invokestatic	Method scala/runtime/BoxesRunTime.equalsCharObject:(Ljava/lang/Character;Ljava/lang/Object;)Z
	goto	l13 // ifeq
l16	aload_3
	aload	13
	invokevirtual	Method java/lang/Object.equals:(Ljava/lang/Object;)Z
l13	ifeq	l6 // iconst_0
	aload_0
	invokevirtual	Method _4:()Ljava/lang/Object;
	astore	14
	aload	4
	aload	14
	if_acmpne	l17 // aload
	iconst_1
	goto	l18 // ifeq
l17	aload	4
	ifnonnull	l19 // aload
	iconst_0
	goto	l18 // ifeq
l19	aload	4
	instanceof	class java/lang/Number
	ifeq	l20 // aload
	aload	4
	checkcast	class java/lang/Number
	aload	14
	invokestatic	Method scala/runtime/BoxesRunTime.equalsNumObject:(Ljava/lang/Number;Ljava/lang/Object;)Z
	goto	l18 // ifeq
l20	aload	4
	instanceof	class java/lang/Character
	ifeq	l21 // aload
	aload	4
	checkcast	class java/lang/Character
	aload	14
	invokestatic	Method scala/runtime/BoxesRunTime.equalsCharObject:(Ljava/lang/Character;Ljava/lang/Object;)Z
	goto	l18 // ifeq
l21	aload	4
	aload	14
	invokevirtual	Method java/lang/Object.equals:(Ljava/lang/Object;)Z
l18	ifeq	l6 // iconst_0
	aload_0
	invokevirtual	Method _5:()Ljava/lang/Object;
	astore	15
	aload	5
	aload	15
	if_acmpne	l22 // aload
	iconst_1
	goto	l23 // ifeq
l22	aload	5
	ifnonnull	l24 // aload
	iconst_0
	goto	l23 // ifeq
l24	aload	5
	instanceof	class java/lang/Number
	ifeq	l25 // aload
	aload	5
	checkcast	class java/lang/Number
	aload	15
	invokestatic	Method scala/runtime/BoxesRunTime.equalsNumObject:(Ljava/lang/Number;Ljava/lang/Object;)Z
	goto	l23 // ifeq
l25	aload	5
	instanceof	class java/lang/Character
	ifeq	l26 // aload
	aload	5
	checkcast	class java/lang/Character
	aload	15
	invokestatic	Method scala/runtime/BoxesRunTime.equalsCharObject:(Ljava/lang/Character;Ljava/lang/Object;)Z
	goto	l23 // ifeq
l26	aload	5
	aload	15
	invokevirtual	Method java/lang/Object.equals:(Ljava/lang/Object;)Z
l23	ifeq	l6 // iconst_0
	aload_0
	invokevirtual	Method _6:()Ljava/lang/Object;
	astore	16
	aload	6
	aload	16
	if_acmpne	l27 // aload
	iconst_1
	goto	l28 // ifeq
l27	aload	6
	ifnonnull	l29 // aload
	iconst_0
	goto	l28 // ifeq
l29	aload	6
	instanceof	class java/lang/Number
	ifeq	l30 // aload
	aload	6
	checkcast	class java/lang/Number
	aload	16
	invokestatic	Method scala/runtime/BoxesRunTime.equalsNumObject:(Ljava/lang/Number;Ljava/lang/Object;)Z
	goto	l28 // ifeq
l30	aload	6
	instanceof	class java/lang/Character
	ifeq	l31 // aload
	aload	6
	checkcast	class java/lang/Character
	aload	16
	invokestatic	Method scala/runtime/BoxesRunTime.equalsCharObject:(Ljava/lang/Character;Ljava/lang/Object;)Z
	goto	l28 // ifeq
l31	aload	6
	aload	16
	invokevirtual	Method java/lang/Object.equals:(Ljava/lang/Object;)Z
l28	ifeq	l6 // iconst_0
	aload_0
	invokevirtual	Method _7:()Ljava/lang/Object;
	astore	17
	aload	7
	aload	17
	if_acmpne	l32 // aload
	iconst_1
	goto	l33 // ifeq
l32	aload	7
	ifnonnull	l34 // aload
	iconst_0
	goto	l33 // ifeq
l34	aload	7
	instanceof	class java/lang/Number
	ifeq	l35 // aload
	aload	7
	checkcast	class java/lang/Number
	aload	17
	invokestatic	Method scala/runtime/BoxesRunTime.equalsNumObject:(Ljava/lang/Number;Ljava/lang/Object;)Z
	goto	l33 // ifeq
l35	aload	7
	instanceof	class java/lang/Character
	ifeq	l36 // aload
	aload	7
	checkcast	class java/lang/Character
	aload	17
	invokestatic	Method scala/runtime/BoxesRunTime.equalsCharObject:(Ljava/lang/Character;Ljava/lang/Object;)Z
	goto	l33 // ifeq
l36	aload	7
	aload	17
	invokevirtual	Method java/lang/Object.equals:(Ljava/lang/Object;)Z
l33	ifeq	l6 // iconst_0
	aload_0
	invokevirtual	Method _8:()Ljava/lang/Object;
	astore	18
	aload	8
	aload	18
	if_acmpne	l37 // aload
	iconst_1
	goto	l38 // ifeq
l37	aload	8
	ifnonnull	l39 // aload
	iconst_0
	goto	l38 // ifeq
l39	aload	8
	instanceof	class java/lang/Number
	ifeq	l40 // aload
	aload	8
	checkcast	class java/lang/Number
	aload	18
	invokestatic	Method scala/runtime/BoxesRunTime.equalsNumObject:(Ljava/lang/Number;Ljava/lang/Object;)Z
	goto	l38 // ifeq
l40	aload	8
	instanceof	class java/lang/Character
	ifeq	l41 // aload
	aload	8
	checkcast	class java/lang/Character
	aload	18
	invokestatic	Method scala/runtime/BoxesRunTime.equalsCharObject:(Ljava/lang/Character;Ljava/lang/Object;)Z
	goto	l38 // ifeq
l41	aload	8
	aload	18
	invokevirtual	Method java/lang/Object.equals:(Ljava/lang/Object;)Z
l38	ifeq	l6 // iconst_0
	aload_0
	invokevirtual	Method _9:()Ljava/lang/Object;
	astore	19
	aload	9
	aload	19
	if_acmpne	l42 // aload
	iconst_1
	goto	l43 // ifeq
l42	aload	9
	ifnonnull	l44 // aload
	iconst_0
	goto	l43 // ifeq
l44	aload	9
	instanceof	class java/lang/Number
	ifeq	l45 // aload
	aload	9
	checkcast	class java/lang/Number
	aload	19
	invokestatic	Method scala/runtime/BoxesRunTime.equalsNumObject:(Ljava/lang/Number;Ljava/lang/Object;)Z
	goto	l43 // ifeq
l45	aload	9
	instanceof	class java/lang/Character
	ifeq	l46 // aload
	aload	9
	checkcast	class java/lang/Character
	aload	19
	invokestatic	Method scala/runtime/BoxesRunTime.equalsCharObject:(Ljava/lang/Character;Ljava/lang/Object;)Z
	goto	l43 // ifeq
l46	aload	9
	aload	19
	invokevirtual	Method java/lang/Object.equals:(Ljava/lang/Object;)Z
l43	ifeq	l6 // iconst_0
	aload_0
	invokevirtual	Method _10:()Ljava/lang/Object;
	astore	20
	aload	10
	aload	20
	if_acmpne	l47 // aload
	iconst_1
	goto	l48 // ifeq
l47	aload	10
	ifnonnull	l49 // aload
	iconst_0
	goto	l48 // ifeq
l49	aload	10
	instanceof	class java/lang/Number
	ifeq	l50 // aload
	aload	10
	checkcast	class java/lang/Number
	aload	20
	invokestatic	Method scala/runtime/BoxesRunTime.equalsNumObject:(Ljava/lang/Number;Ljava/lang/Object;)Z
	goto	l48 // ifeq
l50	aload	10
	instanceof	class java/lang/Character
	ifeq	l51 // aload
	aload	10
	checkcast	class java/lang/Character
	aload	20
	invokestatic	Method scala/runtime/BoxesRunTime.equalsCharObject:(Ljava/lang/Character;Ljava/lang/Object;)Z
	goto	l48 // ifeq
l51	aload	10
	aload	20
	invokevirtual	Method java/lang/Object.equals:(Ljava/lang/Object;)Z
l48	ifeq	l6 // iconst_0
	iconst_1
	goto	l52 // ireturn
l6	iconst_0
l52	ireturn
  Labels:
   	l1 = 16 // aload_1
   	l3 = 24 // aload_1
   	l4 = 43 // aload_1
   	l5 = 62 // aload_1
   	l2 = 68 // ifeq
   	l7 = 87 // aload_2
   	l9 = 95 // aload_2
   	l10 = 114 // aload_2
   	l11 = 133 // aload_2
   	l8 = 139 // ifeq
   	l12 = 158 // aload_3
   	l14 = 166 // aload_3
   	l15 = 185 // aload_3
   	l16 = 204 // aload_3
   	l13 = 210 // ifeq
   	l17 = 230 // aload
   	l19 = 239 // aload
   	l20 = 260 // aload
   	l21 = 281 // aload
   	l18 = 288 // ifeq
   	l22 = 308 // aload
   	l24 = 317 // aload
   	l25 = 338 // aload
   	l26 = 359 // aload
   	l23 = 366 // ifeq
   	l27 = 386 // aload
   	l29 = 395 // aload
   	l30 = 416 // aload
   	l31 = 437 // aload
   	l28 = 444 // ifeq
   	l32 = 464 // aload
   	l34 = 473 // aload
   	l35 = 494 // aload
   	l36 = 515 // aload
   	l33 = 522 // ifeq
   	l37 = 542 // aload
   	l39 = 551 // aload
   	l40 = 572 // aload
   	l41 = 593 // aload
   	l38 = 600 // ifeq
   	l42 = 620 // aload
   	l44 = 629 // aload
   	l45 = 650 // aload
   	l46 = 671 // aload
   	l43 = 678 // ifeq
   	l47 = 698 // aload
   	l49 = 707 // aload
   	l50 = 728 // aload
   	l51 = 749 // aload
   	l48 = 756 // ifeq
   	l6 = 763 // iconst_0
   	l52 = 764 // ireturn
  LocalVariableTable: 
   Start  Length  Slot  Name   Signature
   0      765      0    this       Lscala/Tuple10;
   12      59      11    y0       Ljava/lang/Object;
   83      59      12    y1       Ljava/lang/Object;
   154      59      13    y2       Ljava/lang/Object;
   226      65      14    y3       Ljava/lang/Object;
   304      65      15    y4       Ljava/lang/Object;
   382      65      16    y5       Ljava/lang/Object;
   460      65      17    y6       Ljava/lang/Object;
   538      65      18    y7       Ljava/lang/Object;
   616      65      19    y8       Ljava/lang/Object;
   694      65      20    y9       Ljava/lang/Object;


public scala.Tuple10(java.lang.Object, java.lang.Object, java.lang.Object, java.lang.Object, java.lang.Object, java.lang.Object, java.lang.Object, java.lang.Object, java.lang.Object, java.lang.Object);
  Signature: (Ljava/lang/Object;Ljava/lang/Object;Ljava/lang/Object;Ljava/lang/Object;Ljava/lang/Object;Ljava/lang/Object;Ljava/lang/Object;Ljava/lang/Object;Ljava/lang/Object;Ljava/lang/Object;)V
  Code:
   Stack=2, Locals=11, Args_size=11
	aload_0
	aload_1
	putfield	Field _1:Ljava/lang/Object;
	aload_0
	aload_2
	putfield	Field _2:Ljava/lang/Object;
	aload_0
	aload_3
	putfield	Field _3:Ljava/lang/Object;
	aload_0
	aload	4
	putfield	Field _4:Ljava/lang/Object;
	aload_0
	aload	5
	putfield	Field _5:Ljava/lang/Object;
	aload_0
	aload	6
	putfield	Field _6:Ljava/lang/Object;
	aload_0
	aload	7
	putfield	Field _7:Ljava/lang/Object;
	aload_0
	aload	8
	putfield	Field _8:Ljava/lang/Object;
	aload_0
	aload	9
	putfield	Field _9:Ljava/lang/Object;
	aload_0
	aload	10
	putfield	Field _10:Ljava/lang/Object;
	aload_0
	invokespecial	Method java/lang/Object."<init>":()V
	aload_0
	invokestatic	Method scala/Product$class.$init$:(Lscala/Product;)V
	aload_0
	invokestatic	Method scala/Product10$class.$init$:(Lscala/Product10;)V
	return
  Labels:
  LocalVariableTable: 
   Start  Length  Slot  Name   Signature
   0      70      0    this       Lscala/Tuple10;
   0      70      1    _1       Ljava/lang/Object;
   0      70      2    _2       Ljava/lang/Object;
   0      70      3    _3       Ljava/lang/Object;
   0      70      4    _4       Ljava/lang/Object;
   0      70      5    _5       Ljava/lang/Object;
   0      70      6    _6       Ljava/lang/Object;
   0      70      7    _7       Ljava/lang/Object;
   0      70      8    _8       Ljava/lang/Object;
   0      70      9    _9       Ljava/lang/Object;
   0      70      10    _10       Ljava/lang/Object;

  Signature: length = 0x2
   00 FFFFFFDF 

}

