Compiled from "Tuple1.scala"
public class scala.Tuple1$mcL$sp extends scala.Tuple1 implements scala.Product1$mcL$sp
  SourceFile: "Tuple1.scala"
  Scala: length = 0x
   
  Signature: length = 0x2
   00 29 
  minor version: 0
  major version: 49
  Constant pool:
Asciz	SourceFile;
Asciz	Tuple1.scala;
Asciz	_1$mcL$sp;
Asciz	J;
Asciz	()J;
Asciz	Code;
Asciz	LineNumberTable;
Asciz	scala/Tuple1$mcL$sp;
class	scala/Tuple1$mcL$sp
NameAndType	_1$mcL$sp:J
Field	scala/Tuple1$mcL$sp._1$mcL$sp:J
Asciz	_1;
NameAndType	_1$mcL$sp:()J
Method	scala/Tuple1$mcL$sp._1$mcL$sp:()J
Asciz	()Ljava/lang/Object;;
NameAndType	_1:()J
Method	scala/Tuple1$mcL$sp._1:()J
Asciz	scala/runtime/BoxesRunTime;
class	scala/runtime/BoxesRunTime
Asciz	boxToLong;
Asciz	(J)Ljava/lang/Long;;
NameAndType	boxToLong:(J)Ljava/lang/Long;
Method	scala/runtime/BoxesRunTime.boxToLong:(J)Ljava/lang/Long;
Asciz	<init>;
Asciz	(J)V;
Asciz	scala/Tuple1;
class	scala/Tuple1
Asciz	(Ljava/lang/Object;)V;
NameAndType	"<init>":(Ljava/lang/Object;)V
Method	scala/Tuple1."<init>":(Ljava/lang/Object;)V
Asciz	scala/Product1$mcL$sp$class;
class	scala/Product1$mcL$sp$class
Asciz	$init$;
Asciz	(Lscala/Product1$mcL$sp;)V;
NameAndType	$init$:(Lscala/Product1$mcL$sp;)V
Method	scala/Product1$mcL$sp$class.$init$:(Lscala/Product1$mcL$sp;)V
Asciz	this;
Asciz	Lscala/Tuple1$mcL$sp;;
Asciz	LocalVariableTable;
Asciz	Scala;
Asciz	Lscala/Tuple1<Ljava/lang/Long;>;Lscala/Product1$mcL$sp;;
Asciz	Signature;
Asciz	scala/Product1$mcL$sp;
class	scala/Product1$mcL$sp

{
public final long _1$mcL$sp;
  Signature: J

public long _1$mcL$sp();
  Signature: ()J
  Code:
   Stack=2, Locals=1, Args_size=1
	aload_0
	getfield	Field _1$mcL$sp:J
	lreturn
  Labels:

public long _1();
  Signature: ()J
  Code:
   Stack=2, Locals=1, Args_size=1
	aload_0
	invokevirtual	Method _1$mcL$sp:()J
	lreturn
  Labels:

public java.lang.Object _1();
  Signature: ()Ljava/lang/Object;
  Code:
   Stack=2, Locals=3, Args_size=1
	aload_0
	invokevirtual	Method _1:()J
	lstore_1
	lload_1
	invokestatic	Method scala/runtime/BoxesRunTime.boxToLong:(J)Ljava/lang/Long;
	areturn
  Labels:

public scala.Tuple1$mcL$sp(long);
  Signature: (J)V
  Code:
   Stack=3, Locals=3, Args_size=2
	aload_0
	lload_1
	putfield	Field _1$mcL$sp:J
	aload_0
	lload_1
	invokestatic	Method scala/runtime/BoxesRunTime.boxToLong:(J)Ljava/lang/Long;
	invokespecial	Method scala/Tuple1."<init>":(Ljava/lang/Object;)V
	aload_0
	invokestatic	Method scala/Product1$mcL$sp$class.$init$:(Lscala/Product1$mcL$sp;)V
	return
  Labels:
  LocalVariableTable: 
   Start  Length  Slot  Name   Signature
   0      18      0    this       Lscala/Tuple1$mcL$sp;
   0      18      1    _1$mcL$sp       J


}

