Compiled from "Tuple2.scala"
public class scala.Tuple2$mcIL$sp extends scala.Tuple2
  SourceFile: "Tuple2.scala"
  Scala: length = 0x
   
  Signature: length = 0x2
   00 FFFFFF81 
  InnerClass: 
   public Zipped=class scala/Tuple2$Zipped of class scala/Tuple2
   public final $anonfun$zip$mcIL$sp$1=class scala/Tuple2$mcIL$sp$$anonfun$zip$mcIL$sp$1 of class scala/Tuple2$mcIL$sp
  minor version: 0
  major version: 49
  Constant pool:
Asciz	SourceFile;
Asciz	Tuple2.scala;
Asciz	_1$mcI$sp;
Asciz	I;
Asciz	_2$mcL$sp;
Asciz	J;
Asciz	()I;
Asciz	Code;
Asciz	LineNumberTable;
Asciz	scala/Tuple2$mcIL$sp;
class	scala/Tuple2$mcIL$sp
NameAndType	_1$mcI$sp:I
Field	scala/Tuple2$mcIL$sp._1$mcI$sp:I
Asciz	_1;
NameAndType	_1$mcI$sp:()I
Method	scala/Tuple2$mcIL$sp._1$mcI$sp:()I
Asciz	()J;
NameAndType	_2$mcL$sp:J
Field	scala/Tuple2$mcIL$sp._2$mcL$sp:J
Asciz	_2;
NameAndType	_2$mcL$sp:()J
Method	scala/Tuple2$mcIL$sp._2$mcL$sp:()J
Asciz	swap;
Asciz	()Lscala/Tuple2;;
Asciz	swap$mcIL$sp;
NameAndType	swap$mcIL$sp:()Lscala/Tuple2;
Method	scala/Tuple2$mcIL$sp.swap$mcIL$sp:()Lscala/Tuple2;
Asciz	()Lscala/Tuple2<Ljava/lang/Long;Ljava/lang/Integer;>;;
Asciz	Signature;
Asciz	scala/Tuple2$mcLI$sp;
class	scala/Tuple2$mcLI$sp
NameAndType	_2:()J
Method	scala/Tuple2$mcIL$sp._2:()J
NameAndType	_1:()I
Method	scala/Tuple2$mcIL$sp._1:()I
Asciz	<init>;
Asciz	(JI)V;
NameAndType	"<init>":(JI)V
Method	scala/Tuple2$mcLI$sp."<init>":(JI)V
Asciz	zip;
Asciz	(Lscala/Function1;Lscala/Function1;Lscala/collection/generic/CanBuildFrom;)Ljava/lang/Object;;
Asciz	zip$mcIL$sp;
NameAndType	zip$mcIL$sp:(Lscala/Function1;Lscala/Function1;Lscala/collection/generic/CanBuildFrom;)Ljava/lang/Object;
Method	scala/Tuple2$mcIL$sp.zip$mcIL$sp:(Lscala/Function1;Lscala/Function1;Lscala/collection/generic/CanBuildFrom;)Ljava/lang/Object;
Asciz	this;
Asciz	Lscala/Tuple2$mcIL$sp;;
Asciz	w1;
Asciz	Lscala/Function1;;
Asciz	w2;
Asciz	cbf1;
Asciz	Lscala/collection/generic/CanBuildFrom;;
Asciz	LocalVariableTable;
Asciz	<Repr1:Ljava/lang/Object;El1:Ljava/lang/Object;El2:Ljava/lang/Object;To:Ljava/lang/Object;>(Lscala/Function1<Ljava/lang/Integer;Lscala/collection/TraversableLike<TEl1;TRepr1;>;>;Lscala/Function1<Ljava/lang/Long;Lscala/collection/Iterable<TEl2;>;>;Lscala/collection/generic/CanBuildFrom<TRepr1;Lscala/Tuple2<TEl1;TEl2;>;TTo;>;)TTo;;
Asciz	scala/runtime/BoxesRunTime;
class	scala/runtime/BoxesRunTime
Asciz	boxToInteger;
Asciz	(I)Ljava/lang/Integer;;
NameAndType	boxToInteger:(I)Ljava/lang/Integer;
Method	scala/runtime/BoxesRunTime.boxToInteger:(I)Ljava/lang/Integer;
Asciz	scala/Function1;
class	scala/Function1
Asciz	apply;
Asciz	(Ljava/lang/Object;)Ljava/lang/Object;;
NameAndType	apply:(Ljava/lang/Object;)Ljava/lang/Object;
InterfaceMethod	scala/Function1.apply:(Ljava/lang/Object;)Ljava/lang/Object;
Asciz	scala/collection/TraversableLike;
class	scala/collection/TraversableLike
Asciz	boxToLong;
Asciz	(J)Ljava/lang/Long;;
NameAndType	boxToLong:(J)Ljava/lang/Long;
Method	scala/runtime/BoxesRunTime.boxToLong:(J)Ljava/lang/Long;
Asciz	scala/collection/Iterable;
class	scala/collection/Iterable
Asciz	repr;
Asciz	()Ljava/lang/Object;;
NameAndType	repr:()Ljava/lang/Object;
InterfaceMethod	scala/collection/TraversableLike.repr:()Ljava/lang/Object;
Asciz	scala/collection/generic/CanBuildFrom;
class	scala/collection/generic/CanBuildFrom
Asciz	(Ljava/lang/Object;)Lscala/collection/mutable/Builder;;
NameAndType	apply:(Ljava/lang/Object;)Lscala/collection/mutable/Builder;
InterfaceMethod	scala/collection/generic/CanBuildFrom.apply:(Ljava/lang/Object;)Lscala/collection/mutable/Builder;
Asciz	scala/collection/IterableLike;
class	scala/collection/IterableLike
Asciz	iterator;
Asciz	()Lscala/collection/Iterator;;
NameAndType	iterator:()Lscala/collection/Iterator;
InterfaceMethod	scala/collection/IterableLike.iterator:()Lscala/collection/Iterator;
Asciz	scala/Tuple2$mcIL$sp$$anonfun$zip$mcIL$sp$1;
class	scala/Tuple2$mcIL$sp$$anonfun$zip$mcIL$sp$1
Asciz	(Lscala/Tuple2$mcIL$sp;Lscala/collection/mutable/Builder;Lscala/collection/Iterator;)V;
NameAndType	"<init>":(Lscala/Tuple2$mcIL$sp;Lscala/collection/mutable/Builder;Lscala/collection/Iterator;)V
Method	scala/Tuple2$mcIL$sp$$anonfun$zip$mcIL$sp$1."<init>":(Lscala/Tuple2$mcIL$sp;Lscala/collection/mutable/Builder;Lscala/collection/Iterator;)V
Asciz	foreach;
Asciz	(Lscala/Function1;)V;
NameAndType	foreach:(Lscala/Function1;)V
InterfaceMethod	scala/collection/TraversableLike.foreach:(Lscala/Function1;)V
Asciz	scala/collection/mutable/Builder;
class	scala/collection/mutable/Builder
Asciz	result;
NameAndType	result:()Ljava/lang/Object;
InterfaceMethod	scala/collection/mutable/Builder.result:()Ljava/lang/Object;
Asciz	coll1;
Asciz	Lscala/collection/TraversableLike;;
Asciz	coll2;
Asciz	Lscala/collection/Iterable;;
Asciz	b1$4;
Asciz	Lscala/collection/mutable/Builder;;
Asciz	elems2$9;
Asciz	Lscala/collection/Iterator;;
Asciz	zipped;
Asciz	(Lscala/Function1;Lscala/Function1;)Lscala/Tuple2$Zipped;;
Asciz	zipped$mcIL$sp;
NameAndType	zipped$mcIL$sp:(Lscala/Function1;Lscala/Function1;)Lscala/Tuple2$Zipped;
Method	scala/Tuple2$mcIL$sp.zipped$mcIL$sp:(Lscala/Function1;Lscala/Function1;)Lscala/Tuple2$Zipped;
Asciz	<Repr1:Ljava/lang/Object;El1:Ljava/lang/Object;Repr2:Ljava/lang/Object;El2:Ljava/lang/Object;>(Lscala/Function1<Ljava/lang/Integer;Lscala/collection/TraversableLike<TEl1;TRepr1;>;>;Lscala/Function1<Ljava/lang/Long;Lscala/collection/IterableLike<TEl2;TRepr2;>;>;)Lscala/Tuple2<Ljava/lang/Integer;Ljava/lang/Long;>.Zipped<TRepr1;TEl1;TRepr2;TEl2;>;;
Asciz	scala/Tuple2$Zipped;
class	scala/Tuple2$Zipped
Asciz	(Lscala/Tuple2;Lscala/collection/TraversableLike;Lscala/collection/IterableLike;)V;
NameAndType	"<init>":(Lscala/Tuple2;Lscala/collection/TraversableLike;Lscala/collection/IterableLike;)V
Method	scala/Tuple2$Zipped."<init>":(Lscala/Tuple2;Lscala/collection/TraversableLike;Lscala/collection/IterableLike;)V
Asciz	(IJ)V;
Asciz	scala/Tuple2;
class	scala/Tuple2
Asciz	(Ljava/lang/Object;Ljava/lang/Object;)V;
NameAndType	"<init>":(Ljava/lang/Object;Ljava/lang/Object;)V
Method	scala/Tuple2."<init>":(Ljava/lang/Object;Ljava/lang/Object;)V
Asciz	Scala;
Asciz	Lscala/Tuple2<Ljava/lang/Integer;Ljava/lang/Long;>;;
Asciz	InnerClasses;
Asciz	Zipped;
Asciz	$anonfun$zip$mcIL$sp$1;

{
public final int _1$mcI$sp;
  Signature: I

public final long _2$mcL$sp;
  Signature: J

public int _1$mcI$sp();
  Signature: ()I
  Code:
   Stack=1, Locals=1, Args_size=1
	aload_0
	getfield	Field _1$mcI$sp:I
	ireturn
  Labels:

public int _1();
  Signature: ()I
  Code:
   Stack=1, Locals=1, Args_size=1
	aload_0
	invokevirtual	Method _1$mcI$sp:()I
	ireturn
  Labels:

public long _2$mcL$sp();
  Signature: ()J
  Code:
   Stack=2, Locals=1, Args_size=1
	aload_0
	getfield	Field _2$mcL$sp:J
	lreturn
  Labels:

public long _2();
  Signature: ()J
  Code:
   Stack=2, Locals=1, Args_size=1
	aload_0
	invokevirtual	Method _2$mcL$sp:()J
	lreturn
  Labels:

public scala.Tuple2 swap();
  Signature: ()Lscala/Tuple2;
  Code:
   Stack=1, Locals=1, Args_size=1
	aload_0
	invokevirtual	Method swap$mcIL$sp:()Lscala/Tuple2;
	areturn
  Labels:
  Signature: length = 0x2
   00 1C 

public scala.Tuple2 swap$mcIL$sp();
  Signature: ()Lscala/Tuple2;
  Code:
   Stack=5, Locals=1, Args_size=1
	new	class scala/Tuple2$mcLI$sp
	dup
	aload_0
	invokevirtual	Method _2:()J
	aload_0
	invokevirtual	Method _1:()I
	invokespecial	Method scala/Tuple2$mcLI$sp."<init>":(JI)V
	areturn
  Labels:
  Signature: length = 0x2
   00 1C 

public java.lang.Object zip(scala.Function1, scala.Function1, scala.collection.generic.CanBuildFrom);
  Signature: (Lscala/Function1;Lscala/Function1;Lscala/collection/generic/CanBuildFrom;)Ljava/lang/Object;
  Code:
   Stack=4, Locals=4, Args_size=4
	aload_0
	aload_1
	aload_2
	aload_3
	invokevirtual	Method zip$mcIL$sp:(Lscala/Function1;Lscala/Function1;Lscala/collection/generic/CanBuildFrom;)Ljava/lang/Object;
	areturn
  Labels:
  LocalVariableTable: 
   Start  Length  Slot  Name   Signature
   0      8      0    this       Lscala/Tuple2$mcIL$sp;
   0      8      1    w1       Lscala/Function1;
   0      8      2    w2       Lscala/Function1;
   0      8      3    cbf1       Lscala/collection/generic/CanBuildFrom;

  Signature: length = 0x2
   00 35 

public java.lang.Object zip$mcIL$sp(scala.Function1, scala.Function1, scala.collection.generic.CanBuildFrom);
  Signature: (Lscala/Function1;Lscala/Function1;Lscala/collection/generic/CanBuildFrom;)Ljava/lang/Object;
  Code:
   Stack=6, Locals=11, Args_size=4
	aload_1
	aload_0
	invokevirtual	Method _1:()I
	istore	5
	iload	5
	invokestatic	Method scala/runtime/BoxesRunTime.boxToInteger:(I)Ljava/lang/Integer;
	invokeinterface	InterfaceMethod scala/Function1.apply:(Ljava/lang/Object;)Ljava/lang/Object;
	checkcast	class scala/collection/TraversableLike
	astore	4
	aload_2
	aload_0
	invokevirtual	Method _2:()J
	lstore	7
	lload	7
	invokestatic	Method scala/runtime/BoxesRunTime.boxToLong:(J)Ljava/lang/Long;
	invokeinterface	InterfaceMethod scala/Function1.apply:(Ljava/lang/Object;)Ljava/lang/Object;
	checkcast	class scala/collection/Iterable
	astore	6
	aload_3
	aload	4
	invokeinterface	InterfaceMethod scala/collection/TraversableLike.repr:()Ljava/lang/Object;
	invokeinterface	InterfaceMethod scala/collection/generic/CanBuildFrom.apply:(Ljava/lang/Object;)Lscala/collection/mutable/Builder;
	astore	9
	aload	6
	invokeinterface	InterfaceMethod scala/collection/IterableLike.iterator:()Lscala/collection/Iterator;
	astore	10
	aload	4
	new	class scala/Tuple2$mcIL$sp$$anonfun$zip$mcIL$sp$1
	dup
	aload_0
	aload	9
	aload	10
	invokespecial	Method scala/Tuple2$mcIL$sp$$anonfun$zip$mcIL$sp$1."<init>":(Lscala/Tuple2$mcIL$sp;Lscala/collection/mutable/Builder;Lscala/collection/Iterator;)V
	invokeinterface	InterfaceMethod scala/collection/TraversableLike.foreach:(Lscala/Function1;)V
	aload	9
	invokeinterface	InterfaceMethod scala/collection/mutable/Builder.result:()Ljava/lang/Object;
	areturn
  Labels:
  LocalVariableTable: 
   Start  Length  Slot  Name   Signature
   0      95      0    this       Lscala/Tuple2$mcIL$sp;
   0      95      1    w1       Lscala/Function1;
   0      95      2    w2       Lscala/Function1;
   0      95      3    cbf1       Lscala/collection/generic/CanBuildFrom;
   22      72      4    coll1       Lscala/collection/TraversableLike;
   44      50      6    coll2       Lscala/collection/Iterable;
   59      35      9    b1$4       Lscala/collection/mutable/Builder;
   68      26      10    elems2$9       Lscala/collection/Iterator;

  Signature: length = 0x2
   00 35 

public scala.Tuple2$Zipped zipped(scala.Function1, scala.Function1);
  Signature: (Lscala/Function1;Lscala/Function1;)Lscala/Tuple2$Zipped;
  Code:
   Stack=3, Locals=3, Args_size=3
	aload_0
	aload_1
	aload_2
	invokevirtual	Method zipped$mcIL$sp:(Lscala/Function1;Lscala/Function1;)Lscala/Tuple2$Zipped;
	areturn
  Labels:
  LocalVariableTable: 
   Start  Length  Slot  Name   Signature
   0      7      0    this       Lscala/Tuple2$mcIL$sp;
   0      7      1    w1       Lscala/Function1;
   0      7      2    w2       Lscala/Function1;

  Signature: length = 0x2
   00 74 

public scala.Tuple2$Zipped zipped$mcIL$sp(scala.Function1, scala.Function1);
  Signature: (Lscala/Function1;Lscala/Function1;)Lscala/Tuple2$Zipped;
  Code:
   Stack=7, Locals=6, Args_size=3
	new	class scala/Tuple2$Zipped
	dup
	aload_0
	aload_1
	aload_0
	invokevirtual	Method _1:()I
	istore_3
	iload_3
	invokestatic	Method scala/runtime/BoxesRunTime.boxToInteger:(I)Ljava/lang/Integer;
	invokeinterface	InterfaceMethod scala/Function1.apply:(Ljava/lang/Object;)Ljava/lang/Object;
	checkcast	class scala/collection/TraversableLike
	aload_2
	aload_0
	invokevirtual	Method _2:()J
	lstore	4
	lload	4
	invokestatic	Method scala/runtime/BoxesRunTime.boxToLong:(J)Ljava/lang/Long;
	invokeinterface	InterfaceMethod scala/Function1.apply:(Ljava/lang/Object;)Ljava/lang/Object;
	checkcast	class scala/collection/IterableLike
	invokespecial	Method scala/Tuple2$Zipped."<init>":(Lscala/Tuple2;Lscala/collection/TraversableLike;Lscala/collection/IterableLike;)V
	areturn
  Labels:
  LocalVariableTable: 
   Start  Length  Slot  Name   Signature
   0      47      0    this       Lscala/Tuple2$mcIL$sp;
   0      47      1    w1       Lscala/Function1;
   0      47      2    w2       Lscala/Function1;

  Signature: length = 0x2
   00 74 

public java.lang.Object _2();
  Signature: ()Ljava/lang/Object;
  Code:
   Stack=2, Locals=3, Args_size=1
	aload_0
	invokevirtual	Method _2:()J
	lstore_1
	lload_1
	invokestatic	Method scala/runtime/BoxesRunTime.boxToLong:(J)Ljava/lang/Long;
	areturn
  Labels:

public java.lang.Object _1();
  Signature: ()Ljava/lang/Object;
  Code:
   Stack=1, Locals=2, Args_size=1
	aload_0
	invokevirtual	Method _1:()I
	istore_1
	iload_1
	invokestatic	Method scala/runtime/BoxesRunTime.boxToInteger:(I)Ljava/lang/Integer;
	areturn
  Labels:

public scala.Tuple2$mcIL$sp(int, long);
  Signature: (IJ)V
  Code:
   Stack=4, Locals=4, Args_size=3
	aload_0
	iload_1
	putfield	Field _1$mcI$sp:I
	aload_0
	lload_2
	putfield	Field _2$mcL$sp:J
	aload_0
	iload_1
	invokestatic	Method scala/runtime/BoxesRunTime.boxToInteger:(I)Ljava/lang/Integer;
	lload_2
	invokestatic	Method scala/runtime/BoxesRunTime.boxToLong:(J)Ljava/lang/Long;
	invokespecial	Method scala/Tuple2."<init>":(Ljava/lang/Object;Ljava/lang/Object;)V
	return
  Labels:
  LocalVariableTable: 
   Start  Length  Slot  Name   Signature
   0      23      0    this       Lscala/Tuple2$mcIL$sp;
   0      23      1    _1$mcI$sp       I
   0      23      2    _2$mcL$sp       J


}

