Compiled from "Unhashable.scala"
public abstract class scala.Unhashable$class extends java.lang.Object
  SourceFile: "Unhashable.scala"
  Scala: length = 0x
   
  minor version: 0
  major version: 49
  Constant pool:
const #1 = Asciz	SourceFile;
const #2 = Asciz	Unhashable.scala;
const #3 = Asciz	$init$;
const #4 = Asciz	(Lscala/Unhashable;)V;
const #5 = Asciz	Code;
const #6 = Asciz	LineNumberTable;
const #7 = Asciz	$this;
const #8 = Asciz	Lscala/Unhashable;;
const #9 = Asciz	LocalVariableTable;
const #10 = Asciz	identityHashCode;
const #11 = Asciz	(Lscala/Unhashable;)I;
const #12 = Asciz	scala/Unhashable;
const #13 = class	#12;	//  scala/Unhashable
const #14 = Asciz	scala$Unhashable$$super$hashCode;
const #15 = Asciz	()I;
const #16 = NameAndType	#14:#15;//  scala$Unhashable$$super$hashCode:()I
const #17 = InterfaceMethod	#13.#16;	//  scala/Unhashable.scala$Unhashable$$super$hashCode:()I
const #18 = Asciz	hashCode;
const #19 = Asciz	java/lang/UnsupportedOperationException;
const #20 = class	#19;	//  java/lang/UnsupportedOperationException
const #21 = Asciz	unsuitable as hash key;
const #22 = String	#21;	//  unsuitable as hash key
const #23 = Asciz	<init>;
const #24 = Asciz	(Ljava/lang/String;)V;
const #25 = NameAndType	#23:#24;//  "<init>":(Ljava/lang/String;)V
const #26 = Method	#20.#25;	//  java/lang/UnsupportedOperationException."<init>":(Ljava/lang/String;)V
const #27 = Asciz	Scala;
const #28 = Asciz	scala/Unhashable$class;
const #29 = class	#28;	//  scala/Unhashable$class
const #30 = Asciz	java/lang/Object;
const #31 = class	#30;	//  java/lang/Object

{
public static void $init$(scala.Unhashable);
  Code:
   Stack=0, Locals=1, Args_size=1
   0:	return
  LineNumberTable: 
   line 29: 0

  LocalVariableTable: 
   Start  Length  Slot  Name   Signature
   0      1      0    $this       Lscala/Unhashable;


public static int identityHashCode(scala.Unhashable);
  Code:
   Stack=1, Locals=1, Args_size=1
   0:	aload_0
   1:	invokeinterface	#17,  1; //InterfaceMethod scala/Unhashable.scala$Unhashable$$super$hashCode:()I
   6:	ireturn
  LineNumberTable: 
   line 42: 0

  LocalVariableTable: 
   Start  Length  Slot  Name   Signature
   0      7      0    $this       Lscala/Unhashable;


public static int hashCode(scala.Unhashable);
  Code:
   Stack=3, Locals=1, Args_size=1
   0:	new	#20; //class java/lang/UnsupportedOperationException
   3:	dup
   4:	ldc	#22; //String unsuitable as hash key
   6:	invokespecial	#26; //Method java/lang/UnsupportedOperationException."<init>":(Ljava/lang/String;)V
   9:	athrow
  LineNumberTable: 
   line 37: 0

  LocalVariableTable: 
   Start  Length  Slot  Name   Signature
   0      10      0    $this       Lscala/Unhashable;


}

