Compiled from "Symbol.scala"
public abstract class scala.UniquenessCache extends java.lang.Object implements scala.ScalaObject
  SourceFile: "Symbol.scala"
  Signature: length = 0x2
   00 FFFFFF81 
  ScalaSig: length = 0x302
   05 00 79 06 06 01 02 FFFFFF81 00 02 04 02 0F 55 6E 69
   71 75 65 6E 65 73 73 43 61 63 68 65 0A 01 03 01
   05 73 63 61 6C 61 15 03 05 19 23 13 03 00 06 0E
   10 02 07 0C 0D 01 08 0A 02 09 0A 01 04 6C 61 6E
   67 0A 01 0B 01 04 6A 61 76 61 09 02 0D 08 02 06
   4F 62 6A 65 63 74 10 02 0F 10 0D 01 02 09 02 11
   02 02 0B 53 63 61 6C 61 4F 62 6A 65 63 74 08 05
   13 00 FFFFFF84 00 15 01 06 3C 69 6E 69 74 3E 03 00 14
   01 16 10 04 0F 00 17 22 10 02 18 19 0C 00 04 08
   1A 00 FFFFFF84 FFFFFF80 FFFFFF80 FFFFFFC2 00 1B 02 01 4B 11 02 1C 1F 10
   02 0F 1D 09 02 1E 02 02 07 4E 6F 74 68 69 6E 67
   10 02 0F 20 09 02 21 02 02 03 41 6E 79 10 02 18
   23 04 08 24 00 FFFFFF84 FFFFFF80 FFFFFF80 FFFFFFC2 00 25 02 01 56 11 02
   26 1F 10 02 0F 27 09 02 28 02 02 04 4E 75 6C 6C
   08 07 2A 00 FFFFFFC2 FFFFFF80 FFFFFF84 04 2B 01 05 71 75 65 75 65
   15 01 2C 10 03 2D 30 22 0D 01 2E 0A 02 2F 08 01
   03 72 65 66 09 02 31 2E 02 0E 52 65 66 65 72 65
   6E 63 65 51 75 65 75 65 08 06 33 00 FFFFFFA0 FFFFFF80 04 2C
   01 06 71 75 65 75 65 20 08 07 35 00 FFFFFFC2 FFFFFF80 FFFFFF84 04
   36 01 03 72 77 6C 15 01 37 10 02 38 3F 0D 01 39
   0A 02 3A 3B 01 05 6C 6F 63 6B 73 0A 02 3C 3D 01
   0A 63 6F 6E 63 75 72 72 65 6E 74 0A 02 3E 0A 01
   04 75 74 69 6C 09 02 40 39 02 16 52 65 65 6E 74
   72 61 6E 74 52 65 61 64 57 72 69 74 65 4C 6F 63
   6B 08 06 42 00 FFFFFFA0 FFFFFF80 04 37 01 04 72 77 6C 20 08
   07 44 00 FFFFFFC2 FFFFFF80 FFFFFF84 04 45 01 05 72 6C 6F 63 6B 15
   01 46 10 02 47 4A 0D 01 48 0A 02 49 39 01 16 52
   65 65 6E 74 72 61 6E 74 52 65 61 64 57 72 69 74
   65 4C 6F 63 6B 09 02 4B 48 02 08 52 65 61 64 4C
   6F 63 6B 08 06 4D 00 FFFFFFA0 FFFFFF80 04 46 01 06 72 6C 6F
   63 6B 20 08 07 4F 00 FFFFFFC2 FFFFFF80 FFFFFF84 04 50 01 05 77 6C
   6F 63 6B 15 01 51 10 02 47 52 09 02 53 48 02 09
   57 72 69 74 65 4C 6F 63 6B 08 06 55 00 FFFFFFA0 FFFFFF80 04
   51 01 06 77 6C 6F 63 6B 20 08 07 57 00 FFFFFFC2 FFFFFF80 FFFFFF84
   04 58 01 03 6D 61 70 15 01 59 10 04 5A 5B 17 5D
   0D 01 3D 09 02 5C 3D 02 0B 57 65 61 6B 48 61 73
   68 4D 61 70 10 03 2D 5E 22 09 02 5F 2E 02 0D 57
   65 61 6B 52 65 66 65 72 65 6E 63 65 08 06 61 00
   FFFFFFA0 FFFFFF80 04 59 01 04 6D 61 70 20 08 05 63 00 FFFFFF86 08
   64 01 0C 76 61 6C 75 65 46 72 6F 6D 4B 65 79 14
   02 22 65 08 05 66 62 FFFFFFC0 00 17 01 01 6B 08 05 68
   00 FFFFFF86 08 69 01 0C 6B 65 79 46 72 6F 6D 56 61 6C
   75 65 14 02 6A 6D 10 03 0F 6B 17 09 02 6C 02 02
   06 4F 70 74 69 6F 6E 08 05 6E 67 FFFFFFC0 00 22 01 01
   76 08 05 70 00 FFFFFF84 00 71 01 05 61 70 70 6C 79 14
   02 22 72 08 05 73 6F FFFFFFC0 00 17 01 04 6E 61 6D 65
   08 05 75 00 FFFFFF84 00 76 01 07 75 6E 61 70 70 6C 79
   14 02 6A 77 08 05 78 74 FFFFFFC0 00 22 01 05 6F 74 68
   65 72 
  InnerClass: 
   public ReadLock=class java/util/concurrent/locks/ReentrantReadWriteLock$ReadLock of class java/util/concurrent/locks/ReentrantReadWriteLock
   public WriteLock=class java/util/concurrent/locks/ReentrantReadWriteLock$WriteLock of class java/util/concurrent/locks/ReentrantReadWriteLock
  minor version: 0
  major version: 49
  Constant pool:
Asciz	SourceFile;
Asciz	Symbol.scala;
Asciz	map;
Asciz	Ljava/util/WeakHashMap;;
Asciz	Ljava/util/WeakHashMap<TK;Ljava/lang/ref/WeakReference<TV;>;>;;
Asciz	Signature;
Asciz	wlock;
Asciz	Ljava/util/concurrent/locks/ReentrantReadWriteLock$WriteLock;;
Asciz	rlock;
Asciz	Ljava/util/concurrent/locks/ReentrantReadWriteLock$ReadLock;;
Asciz	rwl;
Asciz	Ljava/util/concurrent/locks/ReentrantReadWriteLock;;
Asciz	queue;
Asciz	Ljava/lang/ref/ReferenceQueue;;
Asciz	Ljava/lang/ref/ReferenceQueue<TV;>;;
Asciz	()Ljava/lang/ref/ReferenceQueue;;
Asciz	Code;
Asciz	LineNumberTable;
Asciz	scala/UniquenessCache;
class	scala/UniquenessCache
NameAndType	queue:Ljava/lang/ref/ReferenceQueue;
Field	scala/UniquenessCache.queue:Ljava/lang/ref/ReferenceQueue;
Asciz	()Ljava/lang/ref/ReferenceQueue<TV;>;;
Asciz	()Ljava/util/concurrent/locks/ReentrantReadWriteLock;;
NameAndType	rwl:Ljava/util/concurrent/locks/ReentrantReadWriteLock;
Field	scala/UniquenessCache.rwl:Ljava/util/concurrent/locks/ReentrantReadWriteLock;
Asciz	()Ljava/util/concurrent/locks/ReentrantReadWriteLock$ReadLock;;
NameAndType	rlock:Ljava/util/concurrent/locks/ReentrantReadWriteLock$ReadLock;
Field	scala/UniquenessCache.rlock:Ljava/util/concurrent/locks/ReentrantReadWriteLock$ReadLock;
Asciz	()Ljava/util/concurrent/locks/ReentrantReadWriteLock$WriteLock;;
NameAndType	wlock:Ljava/util/concurrent/locks/ReentrantReadWriteLock$WriteLock;
Field	scala/UniquenessCache.wlock:Ljava/util/concurrent/locks/ReentrantReadWriteLock$WriteLock;
Asciz	()Ljava/util/WeakHashMap;;
NameAndType	map:Ljava/util/WeakHashMap;
Field	scala/UniquenessCache.map:Ljava/util/WeakHashMap;
Asciz	()Ljava/util/WeakHashMap<TK;Ljava/lang/ref/WeakReference<TV;>;>;;
Asciz	valueFromKey;
Asciz	(Ljava/lang/Object;)Ljava/lang/Object;;
Asciz	(TK;)TV;;
Asciz	keyFromValue;
Asciz	(Ljava/lang/Object;)Lscala/Option;;
Asciz	(TV;)Lscala/Option<TK;>;;
Asciz	apply;
Asciz	cached$1;
NameAndType	cached$1:(Ljava/lang/Object;)Ljava/lang/Object;
Method	scala/UniquenessCache.cached$1:(Ljava/lang/Object;)Ljava/lang/Object;
Asciz	java/lang/Object;
class	java/lang/Object
Asciz	equals;
Asciz	(Ljava/lang/Object;)Z;
NameAndType	equals:(Ljava/lang/Object;)Z
Method	java/lang/Object.equals:(Ljava/lang/Object;)Z
Asciz	updateCache$1;
NameAndType	updateCache$1:(Ljava/lang/Object;)Ljava/lang/Object;
Method	scala/UniquenessCache.updateCache$1:(Ljava/lang/Object;)Ljava/lang/Object;
Asciz	this;
Asciz	Lscala/UniquenessCache;;
Asciz	name$1;
Asciz	Ljava/lang/Object;;
Asciz	res;
Asciz	LocalVariableTable;
Asciz	unapply;
NameAndType	keyFromValue:(Ljava/lang/Object;)Lscala/Option;
Method	scala/UniquenessCache.keyFromValue:(Ljava/lang/Object;)Lscala/Option;
Asciz	other;
NameAndType	rlock:()Ljava/util/concurrent/locks/ReentrantReadWriteLock$ReadLock;
Method	scala/UniquenessCache.rlock:()Ljava/util/concurrent/locks/ReentrantReadWriteLock$ReadLock;
Asciz	java/util/concurrent/locks/ReentrantReadWriteLock$ReadLock;
class	java/util/concurrent/locks/ReentrantReadWriteLock$ReadLock
Asciz	lock;
Asciz	()V;
NameAndType	lock:()V
Method	java/util/concurrent/locks/ReentrantReadWriteLock$ReadLock.lock:()V
NameAndType	map:()Ljava/util/WeakHashMap;
Method	scala/UniquenessCache.map:()Ljava/util/WeakHashMap;
Asciz	java/util/WeakHashMap;
class	java/util/WeakHashMap
Asciz	get;
NameAndType	get:(Ljava/lang/Object;)Ljava/lang/Object;
Method	java/util/WeakHashMap.get:(Ljava/lang/Object;)Ljava/lang/Object;
Asciz	java/lang/ref/WeakReference;
class	java/lang/ref/WeakReference
Asciz	()Ljava/lang/Object;;
NameAndType	get:()Ljava/lang/Object;
Method	java/lang/ref/WeakReference.get:()Ljava/lang/Object;
Asciz	unlock;
NameAndType	unlock:()V
Method	java/util/concurrent/locks/ReentrantReadWriteLock$ReadLock.unlock:()V
Asciz	exceptionResult1;
Asciz	reference;
Asciz	Ljava/lang/ref/WeakReference;;
NameAndType	wlock:()Ljava/util/concurrent/locks/ReentrantReadWriteLock$WriteLock;
Method	scala/UniquenessCache.wlock:()Ljava/util/concurrent/locks/ReentrantReadWriteLock$WriteLock;
Asciz	java/util/concurrent/locks/ReentrantReadWriteLock$WriteLock;
class	java/util/concurrent/locks/ReentrantReadWriteLock$WriteLock
Method	java/util/concurrent/locks/ReentrantReadWriteLock$WriteLock.lock:()V
NameAndType	valueFromKey:(Ljava/lang/Object;)Ljava/lang/Object;
Method	scala/UniquenessCache.valueFromKey:(Ljava/lang/Object;)Ljava/lang/Object;
NameAndType	queue:()Ljava/lang/ref/ReferenceQueue;
Method	scala/UniquenessCache.queue:()Ljava/lang/ref/ReferenceQueue;
Asciz	<init>;
Asciz	(Ljava/lang/Object;Ljava/lang/ref/ReferenceQueue;)V;
NameAndType	"<init>":(Ljava/lang/Object;Ljava/lang/ref/ReferenceQueue;)V
Method	java/lang/ref/WeakReference."<init>":(Ljava/lang/Object;Ljava/lang/ref/ReferenceQueue;)V
Asciz	put;
Asciz	(Ljava/lang/Object;Ljava/lang/Object;)Ljava/lang/Object;;
NameAndType	put:(Ljava/lang/Object;Ljava/lang/Object;)Ljava/lang/Object;
Method	java/util/WeakHashMap.put:(Ljava/lang/Object;Ljava/lang/Object;)Ljava/lang/Object;
Method	java/util/concurrent/locks/ReentrantReadWriteLock$WriteLock.unlock:()V
Asciz	exceptionResult2;
Asciz	sym;
NameAndType	"<init>":()V
Method	java/lang/Object."<init>":()V
Asciz	java/lang/ref/ReferenceQueue;
class	java/lang/ref/ReferenceQueue
Method	java/lang/ref/ReferenceQueue."<init>":()V
Asciz	java/util/concurrent/locks/ReentrantReadWriteLock;
class	java/util/concurrent/locks/ReentrantReadWriteLock
Method	java/util/concurrent/locks/ReentrantReadWriteLock."<init>":()V
NameAndType	rwl:()Ljava/util/concurrent/locks/ReentrantReadWriteLock;
Method	scala/UniquenessCache.rwl:()Ljava/util/concurrent/locks/ReentrantReadWriteLock;
Asciz	readLock;
NameAndType	readLock:()Ljava/util/concurrent/locks/ReentrantReadWriteLock$ReadLock;
Method	java/util/concurrent/locks/ReentrantReadWriteLock.readLock:()Ljava/util/concurrent/locks/ReentrantReadWriteLock$ReadLock;
Asciz	writeLock;
NameAndType	writeLock:()Ljava/util/concurrent/locks/ReentrantReadWriteLock$WriteLock;
Method	java/util/concurrent/locks/ReentrantReadWriteLock.writeLock:()Ljava/util/concurrent/locks/ReentrantReadWriteLock$WriteLock;
Method	java/util/WeakHashMap."<init>":()V
Asciz	<K:Ljava/lang/Object;V:Ljava/lang/Object;>Ljava/lang/Object;Lscala/ScalaObject;;
Asciz	ScalaSig;
Asciz	InnerClasses;
Asciz	ReadLock;
Asciz	WriteLock;
Asciz	scala/ScalaObject;
class	scala/ScalaObject

{
private final java.util.WeakHashMap map;
  Signature: Ljava/util/WeakHashMap;
  Signature: length = 0x2
   00 05 

private final java.util.concurrent.locks.ReentrantReadWriteLock$WriteLock wlock;
  Signature: Ljava/util/concurrent/locks/ReentrantReadWriteLock$WriteLock;

private final java.util.concurrent.locks.ReentrantReadWriteLock$ReadLock rlock;
  Signature: Ljava/util/concurrent/locks/ReentrantReadWriteLock$ReadLock;

private final java.util.concurrent.locks.ReentrantReadWriteLock rwl;
  Signature: Ljava/util/concurrent/locks/ReentrantReadWriteLock;

private final java.lang.ref.ReferenceQueue queue;
  Signature: Ljava/lang/ref/ReferenceQueue;
  Signature: length = 0x2
   00 0F 

private java.lang.ref.ReferenceQueue queue();
  Signature: ()Ljava/lang/ref/ReferenceQueue;
  Code:
   Stack=1, Locals=1, Args_size=1
	aload_0
	getfield	Field queue:Ljava/lang/ref/ReferenceQueue;
	areturn
  Labels:
  Signature: length = 0x2
   00 17 

private java.util.concurrent.locks.ReentrantReadWriteLock rwl();
  Signature: ()Ljava/util/concurrent/locks/ReentrantReadWriteLock;
  Code:
   Stack=1, Locals=1, Args_size=1
	aload_0
	getfield	Field rwl:Ljava/util/concurrent/locks/ReentrantReadWriteLock;
	areturn
  Labels:

private java.util.concurrent.locks.ReentrantReadWriteLock$ReadLock rlock();
  Signature: ()Ljava/util/concurrent/locks/ReentrantReadWriteLock$ReadLock;
  Code:
   Stack=1, Locals=1, Args_size=1
	aload_0
	getfield	Field rlock:Ljava/util/concurrent/locks/ReentrantReadWriteLock$ReadLock;
	areturn
  Labels:

private java.util.concurrent.locks.ReentrantReadWriteLock$WriteLock wlock();
  Signature: ()Ljava/util/concurrent/locks/ReentrantReadWriteLock$WriteLock;
  Code:
   Stack=1, Locals=1, Args_size=1
	aload_0
	getfield	Field wlock:Ljava/util/concurrent/locks/ReentrantReadWriteLock$WriteLock;
	areturn
  Labels:

private java.util.WeakHashMap map();
  Signature: ()Ljava/util/WeakHashMap;
  Code:
   Stack=1, Locals=1, Args_size=1
	aload_0
	getfield	Field map:Ljava/util/WeakHashMap;
	areturn
  Labels:
  Signature: length = 0x2
   00 24 

public abstract java.lang.Object valueFromKey(java.lang.Object);
  Signature: (Ljava/lang/Object;)Ljava/lang/Object;
  Signature: length = 0x2
   00 27 

public abstract scala.Option keyFromValue(java.lang.Object);
  Signature: (Ljava/lang/Object;)Lscala/Option;
  Signature: length = 0x2
   00 2A 

public java.lang.Object apply(java.lang.Object);
  Signature: (Ljava/lang/Object;)Ljava/lang/Object;
  Code:
   Stack=2, Locals=4, Args_size=2
	aload_0
	aload_1
	invokespecial	Method cached$1:(Ljava/lang/Object;)Ljava/lang/Object;
	astore_2
	aload_2
	dup
	astore_3
	ifnull	l1 // aload_0
	aload_3
	aconst_null
	invokevirtual	Method java/lang/Object.equals:(Ljava/lang/Object;)Z
	ifeq	l2 // aload_2
l1	aload_0
	aload_1
	invokespecial	Method updateCache$1:(Ljava/lang/Object;)Ljava/lang/Object;
	goto	l3 // areturn
l2	aload_2
l3	areturn
  Labels:
   	l1 = 20 // aload_0
   	l2 = 28 // aload_2
   	l3 = 29 // areturn
  LocalVariableTable: 
   Start  Length  Slot  Name   Signature
   0      30      0    this       Lscala/UniquenessCache;
   0      30      1    name$1       Ljava/lang/Object;
   6      24      2    res       Ljava/lang/Object;

  Signature: length = 0x2
   00 27 

public scala.Option unapply(java.lang.Object);
  Signature: (Ljava/lang/Object;)Lscala/Option;
  Code:
   Stack=2, Locals=2, Args_size=2
	aload_0
	aload_1
	invokevirtual	Method keyFromValue:(Ljava/lang/Object;)Lscala/Option;
	areturn
  Labels:
  LocalVariableTable: 
   Start  Length  Slot  Name   Signature
   0      6      0    this       Lscala/UniquenessCache;
   0      6      1    other       Ljava/lang/Object;

  Signature: length = 0x2
   00 2A 

private final java.lang.Object cached$1(java.lang.Object);
  Signature: (Ljava/lang/Object;)Ljava/lang/Object;
  Code:
   Stack=2, Locals=6, Args_size=2
	aload_0
	invokespecial	Method rlock:()Ljava/util/concurrent/locks/ReentrantReadWriteLock$ReadLock;
	invokevirtual	Method java/util/concurrent/locks/ReentrantReadWriteLock$ReadLock.lock:()V
	aconst_null
	astore_2
	aload_0
	invokespecial	Method map:()Ljava/util/WeakHashMap;
	aload_1
	invokevirtual	Method java/util/WeakHashMap.get:(Ljava/lang/Object;)Ljava/lang/Object;
	checkcast	class java/lang/ref/WeakReference
	astore	4
	aload	4
	dup
	astore	5
	ifnull	l1 // aconst_null
	aload	5
	aconst_null
	invokevirtual	Method java/lang/Object.equals:(Ljava/lang/Object;)Z
	ifeq	l2 // aload
l1	aconst_null
	pop
	aconst_null
	goto	l3 // astore_2
l2	aload	4
	invokevirtual	Method java/lang/ref/WeakReference.get:()Ljava/lang/Object;
l3	astore_2
	aload_0
	invokespecial	Method rlock:()Ljava/util/concurrent/locks/ReentrantReadWriteLock$ReadLock;
	invokevirtual	Method java/util/concurrent/locks/ReentrantReadWriteLock$ReadLock.unlock:()V
	aload_2
	areturn
	astore_3
	aload_0
	invokespecial	Method rlock:()Ljava/util/concurrent/locks/ReentrantReadWriteLock$ReadLock;
	invokevirtual	Method java/util/concurrent/locks/ReentrantReadWriteLock$ReadLock.unlock:()V
	aload_3
	athrow
  Labels:
   	l1 = 39 // aconst_null
   	l2 = 45 // aload
   	l3 = 50 // astore_2
  Exception table:
   from   to  target type
     9    51    60   any
  LocalVariableTable: 
   Start  Length  Slot  Name   Signature
   0      70      0    this       Lscala/UniquenessCache;
   9      50      2    exceptionResult1       Ljava/lang/Object;
   60      10      2    exceptionResult1       Ljava/lang/Object;
   22      29      4    reference       Ljava/lang/ref/WeakReference;


private final java.lang.Object updateCache$1(java.lang.Object);
  Signature: (Ljava/lang/Object;)Ljava/lang/Object;
  Code:
   Stack=6, Locals=7, Args_size=2
	aload_0
	invokespecial	Method wlock:()Ljava/util/concurrent/locks/ReentrantReadWriteLock$WriteLock;
	invokevirtual	Method java/util/concurrent/locks/ReentrantReadWriteLock$WriteLock.lock:()V
	aconst_null
	astore_2
	aload_0
	aload_1
	invokespecial	Method cached$1:(Ljava/lang/Object;)Ljava/lang/Object;
	astore	4
	aload	4
	dup
	astore	5
	ifnull	l1 // aload_0
	aload	5
	aconst_null
	invokevirtual	Method java/lang/Object.equals:(Ljava/lang/Object;)Z
	ifeq	l2 // aload
l1	aload_0
	aload_1
	invokevirtual	Method valueFromKey:(Ljava/lang/Object;)Ljava/lang/Object;
	astore	6
	aload_0
	invokespecial	Method map:()Ljava/util/WeakHashMap;
	aload_1
	new	class java/lang/ref/WeakReference
	dup
	aload	6
	aload_0
	invokespecial	Method queue:()Ljava/lang/ref/ReferenceQueue;
	invokespecial	Method java/lang/ref/WeakReference."<init>":(Ljava/lang/Object;Ljava/lang/ref/ReferenceQueue;)V
	invokevirtual	Method java/util/WeakHashMap.put:(Ljava/lang/Object;Ljava/lang/Object;)Ljava/lang/Object;
	pop
	aload	6
	goto	l3 // astore_2
l2	aload	4
l3	astore_2
	aload_0
	invokespecial	Method wlock:()Ljava/util/concurrent/locks/ReentrantReadWriteLock$WriteLock;
	invokevirtual	Method java/util/concurrent/locks/ReentrantReadWriteLock$WriteLock.unlock:()V
	aload_2
	areturn
	astore_3
	aload_0
	invokespecial	Method wlock:()Ljava/util/concurrent/locks/ReentrantReadWriteLock$WriteLock;
	invokevirtual	Method java/util/concurrent/locks/ReentrantReadWriteLock$WriteLock.unlock:()V
	aload_3
	athrow
  Labels:
   	l1 = 33 // aload_0
   	l2 = 67 // aload
   	l3 = 69 // astore_2
  Exception table:
   from   to  target type
     9    70    79   any
  LocalVariableTable: 
   Start  Length  Slot  Name   Signature
   0      89      0    this       Lscala/UniquenessCache;
   9      69      2    exceptionResult2       Ljava/lang/Object;
   79      10      2    exceptionResult2       Ljava/lang/Object;
   16      54      4    res       Ljava/lang/Object;
   40      24      6    sym       Ljava/lang/Object;


public scala.UniquenessCache();
  Signature: ()V
  Code:
   Stack=3, Locals=1, Args_size=1
	aload_0
	invokespecial	Method java/lang/Object."<init>":()V
	aload_0
	new	class java/lang/ref/ReferenceQueue
	dup
	invokespecial	Method java/lang/ref/ReferenceQueue."<init>":()V
	putfield	Field queue:Ljava/lang/ref/ReferenceQueue;
	aload_0
	new	class java/util/concurrent/locks/ReentrantReadWriteLock
	dup
	invokespecial	Method java/util/concurrent/locks/ReentrantReadWriteLock."<init>":()V
	putfield	Field rwl:Ljava/util/concurrent/locks/ReentrantReadWriteLock;
	aload_0
	aload_0
	invokespecial	Method rwl:()Ljava/util/concurrent/locks/ReentrantReadWriteLock;
	invokevirtual	Method java/util/concurrent/locks/ReentrantReadWriteLock.readLock:()Ljava/util/concurrent/locks/ReentrantReadWriteLock$ReadLock;
	putfield	Field rlock:Ljava/util/concurrent/locks/ReentrantReadWriteLock$ReadLock;
	aload_0
	aload_0
	invokespecial	Method rwl:()Ljava/util/concurrent/locks/ReentrantReadWriteLock;
	invokevirtual	Method java/util/concurrent/locks/ReentrantReadWriteLock.writeLock:()Ljava/util/concurrent/locks/ReentrantReadWriteLock$WriteLock;
	putfield	Field wlock:Ljava/util/concurrent/locks/ReentrantReadWriteLock$WriteLock;
	aload_0
	new	class java/util/WeakHashMap
	dup
	invokespecial	Method java/util/WeakHashMap."<init>":()V
	putfield	Field map:Ljava/util/WeakHashMap;
	return
  Labels:
  Signature: length = 0x2
   00 47 

}

