Compiled from "ByteCodecs.scala"
public final class scala.reflect.generic.ByteCodecs$ extends java.lang.Object implements scala.ScalaObject
  SourceFile: "ByteCodecs.scala"
  Scala: length = 0x
   
  InnerClass: 
   public abstract ByOne=class scala/collection/immutable/Range$ByOne of class scala/collection/immutable/Range
   public ofByte=class scala/collection/mutable/ArrayOps$ofByte of class scala/collection/mutable/ArrayOps
   public final $anonfun$main$1=class scala/reflect/generic/ByteCodecs$$anonfun$main$1 of class scala/reflect/generic/ByteCodecs
   public final $anonfun$test$1=class scala/reflect/generic/ByteCodecs$$anonfun$test$1 of class scala/reflect/generic/ByteCodecs
   public final $anonfun$testAll$1=class scala/reflect/generic/ByteCodecs$$anonfun$testAll$1 of class scala/reflect/generic/ByteCodecs
   public final $anonfun$test8to7$1=class scala/reflect/generic/ByteCodecs$$anonfun$test8to7$1 of class scala/reflect/generic/ByteCodecs
  minor version: 0
  major version: 49
  Constant pool:
Asciz	SourceFile;
Asciz	ByteCodecs.scala;
Asciz	Scala;
Asciz	MODULE$;
Asciz	Lscala/reflect/generic/ByteCodecs$;;
Asciz	<clinit>;
Asciz	()V;
Asciz	Code;
Asciz	scala/reflect/generic/ByteCodecs$;
class	scala/reflect/generic/ByteCodecs$
Asciz	<init>;
NameAndType	"<init>":()V
Method	scala/reflect/generic/ByteCodecs$."<init>":()V
Asciz	avoidZero;
Asciz	([B)[B;
Asciz	LineNumberTable;
int	127;
int	192;
int	128;
Asciz	this;
Asciz	src;
Asciz	[B;
Asciz	i;
Asciz	I;
Asciz	srclen;
Asciz	count;
Asciz	dst;
Asciz	j;
Asciz	in;
Asciz	B;
Asciz	LocalVariableTable;
Asciz	regenerateZero;
Asciz	([B)I;
int	255;
Asciz	encode8to7;
int	8;
int	6;
int	7;
Asciz	dstlen;
Asciz	out;
Asciz	decode7to8;
Asciz	([BII)V;
int	15;
int	31;
int	63;
Asciz	encode;
NameAndType	encode8to7:([B)[B
Method	scala/reflect/generic/ByteCodecs$.encode8to7:([B)[B
NameAndType	avoidZero:([B)[B
Method	scala/reflect/generic/ByteCodecs$.avoidZero:([B)[B
Asciz	xs;
Asciz	decode;
Asciz	([BI)V;
NameAndType	regenerateZero:([B)I
Method	scala/reflect/generic/ByteCodecs$.regenerateZero:([B)I
NameAndType	decode7to8:([BII)V
Method	scala/reflect/generic/ByteCodecs$.decode7to8:([BII)V
Asciz	len;
Asciz	test8to7;
Asciz	([B)V;
Asciz	scala/collection/mutable/ArrayOps$ofByte;
class	scala/collection/mutable/ArrayOps$ofByte
NameAndType	"<init>":([B)V
Method	scala/collection/mutable/ArrayOps$ofByte."<init>":([B)V
Asciz	scala/collection/IndexedSeqLike;
class	scala/collection/IndexedSeqLike
Asciz	take;
Asciz	(I)Ljava/lang/Object;;
NameAndType	take:(I)Ljava/lang/Object;
InterfaceMethod	scala/collection/IndexedSeqLike.take:(I)Ljava/lang/Object;
class	"[B"
Asciz	scala/collection/mutable/ArrayLike;
class	scala/collection/mutable/ArrayLike
Asciz	deep;
Asciz	()Lscala/collection/IndexedSeq;;
NameAndType	deep:()Lscala/collection/IndexedSeq;
InterfaceMethod	scala/collection/mutable/ArrayLike.deep:()Lscala/collection/IndexedSeq;
Asciz	java/lang/Object;
class	java/lang/Object
Asciz	equals;
Asciz	(Ljava/lang/Object;)Z;
NameAndType	equals:(Ljava/lang/Object;)Z
Method	java/lang/Object.equals:(Ljava/lang/Object;)Z
Asciz	java/lang/AssertionError;
class	java/lang/AssertionError
Asciz	scala/collection/mutable/StringBuilder;
class	scala/collection/mutable/StringBuilder
Method	scala/collection/mutable/StringBuilder."<init>":()V
Asciz	assertion failed: ;
String	assertion failed: 
Asciz	append;
Asciz	(Ljava/lang/Object;)Lscala/collection/mutable/StringBuilder;;
NameAndType	append:(Ljava/lang/Object;)Lscala/collection/mutable/StringBuilder;
Method	scala/collection/mutable/StringBuilder.append:(Ljava/lang/Object;)Lscala/collection/mutable/StringBuilder;
Asciz	test8to7(;
String	test8to7(
Asciz	scala/Predef$;
class	scala/Predef$
Asciz	Lscala/Predef$;;
NameAndType	MODULE$:Lscala/Predef$;
Field	scala/Predef$.MODULE$:Lscala/Predef$;
Asciz	byteArrayOps;
Asciz	([B)Lscala/collection/mutable/ArrayOps;;
NameAndType	byteArrayOps:([B)Lscala/collection/mutable/ArrayOps;
Method	scala/Predef$.byteArrayOps:([B)Lscala/collection/mutable/ArrayOps;
Asciz	) failed, result = ;
String	) failed, result = 
Asciz	toString;
Asciz	()Ljava/lang/String;;
NameAndType	toString:()Ljava/lang/String;
Method	scala/collection/mutable/StringBuilder.toString:()Ljava/lang/String;
Asciz	(Ljava/lang/Object;)V;
NameAndType	"<init>":(Ljava/lang/Object;)V
Method	java/lang/AssertionError."<init>":(Ljava/lang/Object;)V
Asciz	xs$1;
Asciz	assertion0;
Asciz	Z;
Asciz	ys$1;
Asciz	testAll;
Asciz	testAll(;
String	testAll(
Asciz	xs$2;
Asciz	len0;
Asciz	ys$2;
Asciz	test;
Asciz	(Lscala/collection/Seq;)V;
Asciz	scala/reflect/generic/ByteCodecs$$anonfun$test$1;
class	scala/reflect/generic/ByteCodecs$$anonfun$test$1
Method	scala/reflect/generic/ByteCodecs$$anonfun$test$1."<init>":()V
Asciz	scala/collection/IterableLike;
class	scala/collection/IterableLike
Asciz	foreach;
Asciz	(Lscala/Function1;)V;
NameAndType	foreach:(Lscala/Function1;)V
InterfaceMethod	scala/collection/IterableLike.foreach:(Lscala/Function1;)V
Asciz	inputs;
Asciz	Lscala/collection/Seq;;
Asciz	(Lscala/collection/Seq<[B>;)V;
Asciz	Signature;
Asciz	main;
Asciz	([Ljava/lang/String;)V;
Asciz	scala/Array$;
class	scala/Array$
Asciz	Lscala/Array$;;
NameAndType	MODULE$:Lscala/Array$;
Field	scala/Array$.MODULE$:Lscala/Array$;
Asciz	wrapByteArray;
Asciz	([B)Lscala/collection/mutable/WrappedArray;;
NameAndType	wrapByteArray:([B)Lscala/collection/mutable/WrappedArray;
Method	scala/Predef$.wrapByteArray:([B)Lscala/collection/mutable/WrappedArray;
Asciz	scala/reflect/Manifest$;
class	scala/reflect/Manifest$
Asciz	Lscala/reflect/Manifest$;;
NameAndType	MODULE$:Lscala/reflect/Manifest$;
Field	scala/reflect/Manifest$.MODULE$:Lscala/reflect/Manifest$;
Asciz	Byte;
Asciz	()Lscala/reflect/AnyValManifest;;
NameAndType	Byte:()Lscala/reflect/AnyValManifest;
Method	scala/reflect/Manifest$.Byte:()Lscala/reflect/AnyValManifest;
Asciz	apply;
Asciz	(Lscala/collection/Seq;Lscala/reflect/ClassManifest;)Ljava/lang/Object;;
NameAndType	apply:(Lscala/collection/Seq;Lscala/reflect/ClassManifest;)Ljava/lang/Object;
Method	scala/Array$.apply:(Lscala/collection/Seq;Lscala/reflect/ClassManifest;)Ljava/lang/Object;
int	10;
int	9;
Asciz	[Ljava/lang/Object;;
class	"[Ljava/lang/Object;"
Asciz	wrapRefArray;
Asciz	([Ljava/lang/Object;)Lscala/collection/mutable/WrappedArray;;
NameAndType	wrapRefArray:([Ljava/lang/Object;)Lscala/collection/mutable/WrappedArray;
Method	scala/Predef$.wrapRefArray:([Ljava/lang/Object;)Lscala/collection/mutable/WrappedArray;
NameAndType	test:(Lscala/collection/Seq;)V
Method	scala/reflect/generic/ByteCodecs$.test:(Lscala/collection/Seq;)V
Asciz	scala/util/Random;
class	scala/util/Random
Method	scala/util/Random."<init>":()V
Asciz	intWrapper;
Asciz	(I)Lscala/runtime/RichInt;;
NameAndType	intWrapper:(I)Lscala/runtime/RichInt;
Method	scala/Predef$.intWrapper:(I)Lscala/runtime/RichInt;
int	50000;
Asciz	scala/runtime/RichInt;
class	scala/runtime/RichInt
Asciz	until;
Asciz	(I)Lscala/collection/immutable/Range$ByOne;;
NameAndType	until:(I)Lscala/collection/immutable/Range$ByOne;
Method	scala/runtime/RichInt.until:(I)Lscala/collection/immutable/Range$ByOne;
Asciz	scala/reflect/generic/ByteCodecs$$anonfun$main$1;
class	scala/reflect/generic/ByteCodecs$$anonfun$main$1
Asciz	(Lscala/util/Random;)V;
NameAndType	"<init>":(Lscala/util/Random;)V
Method	scala/reflect/generic/ByteCodecs$$anonfun$main$1."<init>":(Lscala/util/Random;)V
Asciz	scala/collection/immutable/Range$ByOne;
class	scala/collection/immutable/Range$ByOne
InterfaceMethod	scala/collection/immutable/Range$ByOne.foreach:(Lscala/Function1;)V
Asciz	tested OK;
String	tested OK
Asciz	println;
NameAndType	println:(Ljava/lang/Object;)V
Method	scala/Predef$.println:(Ljava/lang/Object;)V
Asciz	args;
Asciz	[Ljava/lang/String;;
Asciz	rand$1;
Asciz	Lscala/util/Random;;
Method	java/lang/Object."<init>":()V
NameAndType	MODULE$:Lscala/reflect/generic/ByteCodecs$;
Field	scala/reflect/generic/ByteCodecs$.MODULE$:Lscala/reflect/generic/ByteCodecs$;
Asciz	InnerClasses;
Asciz	scala/collection/immutable/Range;
class	scala/collection/immutable/Range
Asciz	ByOne;
Asciz	scala/collection/mutable/ArrayOps;
class	scala/collection/mutable/ArrayOps
Asciz	ofByte;
Asciz	scala/reflect/generic/ByteCodecs;
class	scala/reflect/generic/ByteCodecs
Asciz	$anonfun$main$1;
Asciz	$anonfun$test$1;
Asciz	scala/reflect/generic/ByteCodecs$$anonfun$testAll$1;
class	scala/reflect/generic/ByteCodecs$$anonfun$testAll$1
Asciz	$anonfun$testAll$1;
Asciz	scala/reflect/generic/ByteCodecs$$anonfun$test8to7$1;
class	scala/reflect/generic/ByteCodecs$$anonfun$test8to7$1
Asciz	$anonfun$test8to7$1;
Asciz	scala/ScalaObject;
class	scala/ScalaObject

{
public static final scala.reflect.generic.ByteCodecs$ MODULE$;
  Signature: Lscala/reflect/generic/ByteCodecs$;

public static {};
  Signature: ()V
  Code:
   Stack=1, Locals=0, Args_size=0
	new	class scala/reflect/generic/ByteCodecs$
	invokespecial	Method "<init>":()V
	return
  Labels:

public byte[] avoidZero(byte[]);
  Signature: ([B)[B
  Code:
   Stack=4, Locals=8, Args_size=2
	iconst_0
	istore_2
	aload_1
	arraylength
	istore_3
	iconst_0
	istore	4
l3	iload_2
	iload_3
	if_icmpge	l1 // iload_3
	aload_1
	iload_2
	baload
	ldc	int 127
	if_icmpne	l2 // iload_2
	iload	4
	iconst_1
	iadd
	istore	4
l2	iload_2
	iconst_1
	iadd
	istore_2
	goto	l3 // iload_2
l1	iload_3
	iload	4
	iadd
	newarray byte
	astore	5
	iconst_0
	istore_2
	iconst_0
	istore	6
l7	iload_2
	iload_3
	if_icmpge	l4 // aload
	aload_1
	iload_2
	baload
	istore	7
	iload	7
	ldc	int 127
	if_icmpne	l5 // aload
	aload	5
	iload	6
	ldc	int 192
	i2b
	bastore
	aload	5
	iload	6
	iconst_1
	iadd
	ldc	int 128
	i2b
	bastore
	iload	6
	iconst_2
	iadd
	istore	6
	goto	l6 // iload_2
l5	aload	5
	iload	6
	iload	7
	iconst_1
	iadd
	i2b
	bastore
	iload	6
	iconst_1
	iadd
	istore	6
l6	iload_2
	iconst_1
	iadd
	istore_2
	goto	l7 // iload_2
l4	aload	5
	areturn
  Labels:
   	l3 = 8 // iload_2
   	l2 = 27 // iload_2
   	l1 = 34 // iload_3
   	l7 = 47 // iload_2
   	l5 = 91 // aload
   	l6 = 107 // iload_2
   	l4 = 114 // aload
  LocalVariableTable: 
   Start  Length  Slot  Name   Signature
   0      117      0    this       Lscala/reflect/generic/ByteCodecs$;
   0      117      1    src       [B
   2      114      2    i       I
   5      111      3    srclen       I
   8      108      4    count       I
   42      74      5    dst       [B
   47      69      6    j       I
   57      54      7    in       B


public int regenerateZero(byte[]);
  Signature: ([B)I
  Code:
   Stack=4, Locals=6, Args_size=2
	iconst_0
	istore_2
	aload_1
	arraylength
	istore_3
	iconst_0
	istore	4
l4	iload_2
	iload_3
	if_icmpge	l1 // iload
	aload_1
	iload_2
	baload
	ldc	int 255
	iand
	istore	5
	iload	5
	ldc	int 192
	if_icmpne	l2 // aload_1
	aload_1
	iload_2
	iconst_1
	iadd
	baload
	ldc	int 255
	iand
	ldc	int 128
	if_icmpne	l2 // aload_1
	aload_1
	iload	4
	bipush	127
	bastore
	iload_2
	iconst_2
	iadd
	istore_2
	goto	l3 // iload
l2	aload_1
	iload	4
	iload	5
	iconst_1
	isub
	i2b
	bastore
	iload_2
	iconst_1
	iadd
	istore_2
l3	iload	4
	iconst_1
	iadd
	istore	4
	goto	l4 // iload_2
l1	iload	4
	ireturn
  Labels:
   	l4 = 8 // iload_2
   	l2 = 54 // aload_1
   	l3 = 67 // iload
   	l1 = 76 // iload
  LocalVariableTable: 
   Start  Length  Slot  Name   Signature
   0      79      0    this       Lscala/reflect/generic/ByteCodecs$;
   0      79      1    src       [B
   2      76      2    i       I
   5      73      3    srclen       I
   8      70      4    j       I
   21      52      5    in       I


public byte[] encode8to7(byte[]);
  Signature: ([B)[B
  Code:
   Stack=5, Locals=11, Args_size=2
	aload_1
	arraylength
	istore_2
	iload_2
	ldc	int 8
	imul
	ldc	int 6
	iadd
	ldc	int 7
	idiv
	istore_3
	iload_3
	newarray byte
	astore	4
	iconst_0
	istore	5
	iconst_0
	istore	6
l2	iload	5
	ldc	int 6
	iadd
	iload_2
	if_icmpge	l1 // iload
	aload_1
	iload	5
	baload
	ldc	int 255
	iand
	istore	7
	aload	4
	iload	6
	iload	7
	ldc	int 127
	iand
	i2b
	bastore
	iload	7
	ldc	int 7
	iushr
	istore	8
	aload_1
	iload	5
	iconst_1
	iadd
	baload
	ldc	int 255
	iand
	istore	7
	aload	4
	iload	6
	iconst_1
	iadd
	iload	8
	iload	7
	iconst_1
	ishl
	ldc	int 127
	iand
	ior
	i2b
	bastore
	iload	7
	ldc	int 6
	iushr
	istore	8
	aload_1
	iload	5
	iconst_2
	iadd
	baload
	ldc	int 255
	iand
	istore	7
	aload	4
	iload	6
	iconst_2
	iadd
	iload	8
	iload	7
	iconst_2
	ishl
	ldc	int 127
	iand
	ior
	i2b
	bastore
	iload	7
	iconst_5
	iushr
	istore	8
	aload_1
	iload	5
	iconst_3
	iadd
	baload
	ldc	int 255
	iand
	istore	7
	aload	4
	iload	6
	iconst_3
	iadd
	iload	8
	iload	7
	iconst_3
	ishl
	ldc	int 127
	iand
	ior
	i2b
	bastore
	iload	7
	iconst_4
	iushr
	istore	8
	aload_1
	iload	5
	iconst_4
	iadd
	baload
	ldc	int 255
	iand
	istore	7
	aload	4
	iload	6
	iconst_4
	iadd
	iload	8
	iload	7
	iconst_4
	ishl
	ldc	int 127
	iand
	ior
	i2b
	bastore
	iload	7
	iconst_3
	iushr
	istore	8
	aload_1
	iload	5
	iconst_5
	iadd
	baload
	ldc	int 255
	iand
	istore	7
	aload	4
	iload	6
	iconst_5
	iadd
	iload	8
	iload	7
	iconst_5
	ishl
	ldc	int 127
	iand
	ior
	i2b
	bastore
	iload	7
	iconst_2
	iushr
	istore	8
	aload_1
	iload	5
	ldc	int 6
	iadd
	baload
	ldc	int 255
	iand
	istore	7
	aload	4
	iload	6
	ldc	int 6
	iadd
	iload	8
	iload	7
	ldc	int 6
	ishl
	ldc	int 127
	iand
	ior
	i2b
	bastore
	iload	7
	iconst_1
	iushr
	istore	8
	aload	4
	iload	6
	ldc	int 7
	iadd
	iload	8
	i2b
	bastore
	iload	5
	ldc	int 7
	iadd
	istore	5
	iload	6
	ldc	int 8
	iadd
	istore	6
	goto	l2 // iload
l1	iload	5
	iload_2
	if_icmpge	l3 // aload
	aload_1
	iload	5
	baload
	ldc	int 255
	iand
	istore	9
	aload	4
	iload	6
	iload	9
	ldc	int 127
	iand
	i2b
	bastore
	iload	6
	iconst_1
	iadd
	istore	6
	iload	9
	ldc	int 7
	iushr
	istore	10
	iload	5
	iconst_1
	iadd
	iload_2
	if_icmpge	l4 // iload
	aload_1
	iload	5
	iconst_1
	iadd
	baload
	ldc	int 255
	iand
	istore	9
	aload	4
	iload	6
	iload	10
	iload	9
	iconst_1
	ishl
	ldc	int 127
	iand
	ior
	i2b
	bastore
	iload	6
	iconst_1
	iadd
	istore	6
	iload	9
	ldc	int 6
	iushr
	istore	10
	iload	5
	iconst_2
	iadd
	iload_2
	if_icmpge	l4 // iload
	aload_1
	iload	5
	iconst_2
	iadd
	baload
	ldc	int 255
	iand
	istore	9
	aload	4
	iload	6
	iload	10
	iload	9
	iconst_2
	ishl
	ldc	int 127
	iand
	ior
	i2b
	bastore
	iload	6
	iconst_1
	iadd
	istore	6
	iload	9
	iconst_5
	iushr
	istore	10
	iload	5
	iconst_3
	iadd
	iload_2
	if_icmpge	l4 // iload
	aload_1
	iload	5
	iconst_3
	iadd
	baload
	ldc	int 255
	iand
	istore	9
	aload	4
	iload	6
	iload	10
	iload	9
	iconst_3
	ishl
	ldc	int 127
	iand
	ior
	i2b
	bastore
	iload	6
	iconst_1
	iadd
	istore	6
	iload	9
	iconst_4
	iushr
	istore	10
	iload	5
	iconst_4
	iadd
	iload_2
	if_icmpge	l4 // iload
	aload_1
	iload	5
	iconst_4
	iadd
	baload
	ldc	int 255
	iand
	istore	9
	aload	4
	iload	6
	iload	10
	iload	9
	iconst_4
	ishl
	ldc	int 127
	iand
	ior
	i2b
	bastore
	iload	6
	iconst_1
	iadd
	istore	6
	iload	9
	iconst_3
	iushr
	istore	10
	iload	5
	iconst_5
	iadd
	iload_2
	if_icmpge	l4 // iload
	aload_1
	iload	5
	iconst_5
	iadd
	baload
	ldc	int 255
	iand
	istore	9
	aload	4
	iload	6
	iload	10
	iload	9
	iconst_5
	ishl
	ldc	int 127
	iand
	ior
	i2b
	bastore
	iload	6
	iconst_1
	iadd
	istore	6
	iload	9
	iconst_2
	iushr
	istore	10
l4	iload	6
	iload_3
	if_icmpge	l3 // aload
	aload	4
	iload	6
	iload	10
	i2b
	bastore
l3	aload	4
	areturn
  Labels:
   	l2 = 25 // iload
   	l1 = 303 // iload
   	l4 = 578 // iload
   	l3 = 592 // aload
  LocalVariableTable: 
   Start  Length  Slot  Name   Signature
   0      595      0    this       Lscala/reflect/generic/ByteCodecs$;
   0      595      1    src       [B
   3      591      2    srclen       I
   14      580      3    dstlen       I
   19      575      4    dst       [B
   22      572      5    i       I
   25      569      6    j       I
   43      257      7    in       I
   61      239      8    out       I
   318      274      9    in       I
   342      250      10    out       I


public void decode7to8(byte[], int, int);
  Signature: ([BII)V
  Code:
   Stack=5, Locals=10, Args_size=4
	iconst_0
	istore	4
	iconst_0
	istore	5
l2	iload	4
	ldc	int 7
	iadd
	iload_2
	if_icmpge	l1 // iload
	aload_1
	iload	4
	baload
	istore	6
	aload_1
	iload	4
	iconst_1
	iadd
	baload
	istore	7
	aload_1
	iload	5
	iload	6
	iload	7
	iconst_1
	iand
	ldc	int 7
	ishl
	ior
	i2b
	bastore
	iload	7
	iconst_1
	iushr
	istore	6
	aload_1
	iload	4
	iconst_2
	iadd
	baload
	istore	7
	aload_1
	iload	5
	iconst_1
	iadd
	iload	6
	iload	7
	iconst_3
	iand
	ldc	int 6
	ishl
	ior
	i2b
	bastore
	iload	7
	iconst_2
	iushr
	istore	6
	aload_1
	iload	4
	iconst_3
	iadd
	baload
	istore	7
	aload_1
	iload	5
	iconst_2
	iadd
	iload	6
	iload	7
	ldc	int 7
	iand
	iconst_5
	ishl
	ior
	i2b
	bastore
	iload	7
	iconst_3
	iushr
	istore	6
	aload_1
	iload	4
	iconst_4
	iadd
	baload
	istore	7
	aload_1
	iload	5
	iconst_3
	iadd
	iload	6
	iload	7
	ldc	int 15
	iand
	iconst_4
	ishl
	ior
	i2b
	bastore
	iload	7
	iconst_4
	iushr
	istore	6
	aload_1
	iload	4
	iconst_5
	iadd
	baload
	istore	7
	aload_1
	iload	5
	iconst_4
	iadd
	iload	6
	iload	7
	ldc	int 31
	iand
	iconst_3
	ishl
	ior
	i2b
	bastore
	iload	7
	iconst_5
	iushr
	istore	6
	aload_1
	iload	4
	ldc	int 6
	iadd
	baload
	istore	7
	aload_1
	iload	5
	iconst_5
	iadd
	iload	6
	iload	7
	ldc	int 63
	iand
	iconst_2
	ishl
	ior
	i2b
	bastore
	iload	7
	ldc	int 6
	iushr
	istore	6
	aload_1
	iload	4
	ldc	int 7
	iadd
	baload
	istore	7
	aload_1
	iload	5
	ldc	int 6
	iadd
	iload	6
	iload	7
	iconst_1
	ishl
	ior
	i2b
	bastore
	iload	4
	ldc	int 8
	iadd
	istore	4
	iload	5
	ldc	int 7
	iadd
	istore	5
	goto	l2 // iload
l1	iload	4
	iload_2
	if_icmpge	l3 // return
	aload_1
	iload	4
	baload
	istore	8
	iload	4
	iconst_1
	iadd
	iload_2
	if_icmpge	l4 // iload
	aload_1
	iload	4
	iconst_1
	iadd
	baload
	istore	9
	aload_1
	iload	5
	iload	8
	iload	9
	iconst_1
	iand
	ldc	int 7
	ishl
	ior
	i2b
	bastore
	iload	5
	iconst_1
	iadd
	istore	5
	iload	9
	iconst_1
	iushr
	istore	8
	iload	4
	iconst_2
	iadd
	iload_2
	if_icmpge	l4 // iload
	aload_1
	iload	4
	iconst_2
	iadd
	baload
	istore	9
	aload_1
	iload	5
	iload	8
	iload	9
	iconst_3
	iand
	ldc	int 6
	ishl
	ior
	i2b
	bastore
	iload	5
	iconst_1
	iadd
	istore	5
	iload	9
	iconst_2
	iushr
	istore	8
	iload	4
	iconst_3
	iadd
	iload_2
	if_icmpge	l4 // iload
	aload_1
	iload	4
	iconst_3
	iadd
	baload
	istore	9
	aload_1
	iload	5
	iload	8
	iload	9
	ldc	int 7
	iand
	iconst_5
	ishl
	ior
	i2b
	bastore
	iload	5
	iconst_1
	iadd
	istore	5
	iload	9
	iconst_3
	iushr
	istore	8
	iload	4
	iconst_4
	iadd
	iload_2
	if_icmpge	l4 // iload
	aload_1
	iload	4
	iconst_4
	iadd
	baload
	istore	9
	aload_1
	iload	5
	iload	8
	iload	9
	ldc	int 15
	iand
	iconst_4
	ishl
	ior
	i2b
	bastore
	iload	5
	iconst_1
	iadd
	istore	5
	iload	9
	iconst_4
	iushr
	istore	8
	iload	4
	iconst_5
	iadd
	iload_2
	if_icmpge	l4 // iload
	aload_1
	iload	4
	iconst_5
	iadd
	baload
	istore	9
	aload_1
	iload	5
	iload	8
	iload	9
	ldc	int 31
	iand
	iconst_3
	ishl
	ior
	i2b
	bastore
	iload	5
	iconst_1
	iadd
	istore	5
	iload	9
	iconst_5
	iushr
	istore	8
	iload	4
	ldc	int 6
	iadd
	iload_2
	if_icmpge	l4 // iload
	aload_1
	iload	4
	ldc	int 6
	iadd
	baload
	istore	9
	aload_1
	iload	5
	iload	8
	iload	9
	ldc	int 63
	iand
	iconst_2
	ishl
	ior
	i2b
	bastore
	iload	5
	iconst_1
	iadd
	istore	5
	iload	9
	ldc	int 6
	iushr
	istore	8
l4	iload	5
	iload_3
	if_icmpge	l3 // return
	aload_1
	iload	5
	iload	8
	i2b
	bastore
l3	return
  Labels:
   	l2 = 6 // iload
   	l1 = 248 // iload
   	l4 = 521 // iload
   	l3 = 534 // return
  LocalVariableTable: 
   Start  Length  Slot  Name   Signature
   0      535      0    this       Lscala/reflect/generic/ByteCodecs$;
   0      535      1    src       [B
   0      535      2    srclen       I
   0      535      3    dstlen       I
   3      532      4    i       I
   6      529      5    j       I
   21      224      6    out       I
   29      216      7    in       B
   260      274      8    out       I
   276      245      9    in       B


public byte[] encode(byte[]);
  Signature: ([B)[B
  Code:
   Stack=3, Locals=2, Args_size=2
	aload_0
	aload_0
	aload_1
	invokevirtual	Method encode8to7:([B)[B
	invokevirtual	Method avoidZero:([B)[B
	areturn
  Labels:
  LocalVariableTable: 
   Start  Length  Slot  Name   Signature
   0      10      0    this       Lscala/reflect/generic/ByteCodecs$;
   0      10      1    xs       [B


public void decode(byte[], int);
  Signature: ([BI)V
  Code:
   Stack=4, Locals=4, Args_size=3
	aload_0
	aload_1
	invokevirtual	Method regenerateZero:([B)I
	istore_3
	aload_0
	aload_1
	iload_3
	iload_2
	invokevirtual	Method decode7to8:([BII)V
	return
  Labels:
  LocalVariableTable: 
   Start  Length  Slot  Name   Signature
   0      14      0    this       Lscala/reflect/generic/ByteCodecs$;
   0      14      1    xs       [B
   0      14      2    dstlen       I
   6      7      3    len       I


public void test8to7(byte[]);
  Signature: ([B)V
  Code:
   Stack=7, Locals=6, Args_size=2
	aload_0
	aload_1
	invokevirtual	Method encode8to7:([B)[B
	astore	5
	aload_0
	aload	5
	aload	5
	arraylength
	aload_1
	arraylength
	invokevirtual	Method decode7to8:([BII)V
	new	class scala/collection/mutable/ArrayOps$ofByte
	dup
	aload	5
	invokespecial	Method scala/collection/mutable/ArrayOps$ofByte."<init>":([B)V
	aload_1
	arraylength
	invokeinterface	InterfaceMethod scala/collection/IndexedSeqLike.take:(I)Ljava/lang/Object;
	checkcast	class "[B"
	astore_2
	new	class scala/collection/mutable/ArrayOps$ofByte
	dup
	aload_2
	invokespecial	Method scala/collection/mutable/ArrayOps$ofByte."<init>":([B)V
	invokeinterface	InterfaceMethod scala/collection/mutable/ArrayLike.deep:()Lscala/collection/IndexedSeq;
	new	class scala/collection/mutable/ArrayOps$ofByte
	dup
	aload_1
	invokespecial	Method scala/collection/mutable/ArrayOps$ofByte."<init>":([B)V
	invokeinterface	InterfaceMethod scala/collection/mutable/ArrayLike.deep:()Lscala/collection/IndexedSeq;
	astore_3
	dup
	ifnonnull	l1 // aload_3
	pop
	aload_3
	ifnull	l2 // iconst_1
	goto	l3 // iconst_0
l1	aload_3
	invokevirtual	Method java/lang/Object.equals:(Ljava/lang/Object;)Z
	ifeq	l3 // iconst_0
l2	iconst_1
	goto	l4 // istore
l3	iconst_0
l4	istore	4
	iload	4
	ifeq	l5 // new
	return
l5	new	class java/lang/AssertionError
	dup
	new	class scala/collection/mutable/StringBuilder
	dup
	invokespecial	Method scala/collection/mutable/StringBuilder."<init>":()V
	ldc	String assertion failed: 
	invokevirtual	Method scala/collection/mutable/StringBuilder.append:(Ljava/lang/Object;)Lscala/collection/mutable/StringBuilder;
	new	class scala/collection/mutable/StringBuilder
	dup
	invokespecial	Method scala/collection/mutable/StringBuilder."<init>":()V
	ldc	String test8to7(
	invokevirtual	Method scala/collection/mutable/StringBuilder.append:(Ljava/lang/Object;)Lscala/collection/mutable/StringBuilder;
	getstatic	Field scala/Predef$.MODULE$:Lscala/Predef$;
	aload_1
	invokevirtual	Method scala/Predef$.byteArrayOps:([B)Lscala/collection/mutable/ArrayOps;
	invokeinterface	InterfaceMethod scala/collection/mutable/ArrayLike.deep:()Lscala/collection/IndexedSeq;
	invokevirtual	Method scala/collection/mutable/StringBuilder.append:(Ljava/lang/Object;)Lscala/collection/mutable/StringBuilder;
	ldc	String ) failed, result = 
	invokevirtual	Method scala/collection/mutable/StringBuilder.append:(Ljava/lang/Object;)Lscala/collection/mutable/StringBuilder;
	getstatic	Field scala/Predef$.MODULE$:Lscala/Predef$;
	getstatic	Field scala/Predef$.MODULE$:Lscala/Predef$;
	aload	5
	invokevirtual	Method scala/Predef$.byteArrayOps:([B)Lscala/collection/mutable/ArrayOps;
	aload_1
	arraylength
	invokeinterface	InterfaceMethod scala/collection/IndexedSeqLike.take:(I)Ljava/lang/Object;
	checkcast	class "[B"
	invokevirtual	Method scala/Predef$.byteArrayOps:([B)Lscala/collection/mutable/ArrayOps;
	invokeinterface	InterfaceMethod scala/collection/mutable/ArrayLike.deep:()Lscala/collection/IndexedSeq;
	invokevirtual	Method scala/collection/mutable/StringBuilder.append:(Ljava/lang/Object;)Lscala/collection/mutable/StringBuilder;
	invokevirtual	Method scala/collection/mutable/StringBuilder.toString:()Ljava/lang/String;
	invokevirtual	Method scala/collection/mutable/StringBuilder.append:(Ljava/lang/Object;)Lscala/collection/mutable/StringBuilder;
	invokevirtual	Method scala/collection/mutable/StringBuilder.toString:()Ljava/lang/String;
	invokespecial	Method java/lang/AssertionError."<init>":(Ljava/lang/Object;)V
	athrow
  Labels:
   	l1 = 77 // aload_3
   	l2 = 84 // iconst_1
   	l3 = 88 // iconst_0
   	l4 = 89 // istore
   	l5 = 97 // new
  LocalVariableTable: 
   Start  Length  Slot  Name   Signature
   0      190      0    this       Lscala/reflect/generic/ByteCodecs$;
   0      190      1    xs$1       [B
   96      94      4    assertion0       Z
   7      89      5    ys$1       [B
   97      93      5    ys$1       [B


public void testAll(byte[]);
  Signature: ([B)V
  Code:
   Stack=7, Locals=8, Args_size=2
	aload_0
	aload_0
	aload_1
	invokevirtual	Method encode8to7:([B)[B
	invokevirtual	Method avoidZero:([B)[B
	astore	7
	aload_1
	arraylength
	istore_3
	aload_0
	aload	7
	invokevirtual	Method regenerateZero:([B)I
	istore_2
	aload_0
	aload	7
	iload_2
	iload_3
	invokevirtual	Method decode7to8:([BII)V
	new	class scala/collection/mutable/ArrayOps$ofByte
	dup
	aload	7
	invokespecial	Method scala/collection/mutable/ArrayOps$ofByte."<init>":([B)V
	aload_1
	arraylength
	invokeinterface	InterfaceMethod scala/collection/IndexedSeqLike.take:(I)Ljava/lang/Object;
	checkcast	class "[B"
	astore	4
	new	class scala/collection/mutable/ArrayOps$ofByte
	dup
	aload	4
	invokespecial	Method scala/collection/mutable/ArrayOps$ofByte."<init>":([B)V
	invokeinterface	InterfaceMethod scala/collection/mutable/ArrayLike.deep:()Lscala/collection/IndexedSeq;
	new	class scala/collection/mutable/ArrayOps$ofByte
	dup
	aload_1
	invokespecial	Method scala/collection/mutable/ArrayOps$ofByte."<init>":([B)V
	invokeinterface	InterfaceMethod scala/collection/mutable/ArrayLike.deep:()Lscala/collection/IndexedSeq;
	astore	5
	dup
	ifnonnull	l1 // aload
	pop
	aload	5
	ifnull	l2 // iconst_1
	goto	l3 // iconst_0
l1	aload	5
	invokevirtual	Method java/lang/Object.equals:(Ljava/lang/Object;)Z
	ifeq	l3 // iconst_0
l2	iconst_1
	goto	l4 // istore
l3	iconst_0
l4	istore	6
	iload	6
	ifeq	l5 // new
	return
l5	new	class java/lang/AssertionError
	dup
	new	class scala/collection/mutable/StringBuilder
	dup
	invokespecial	Method scala/collection/mutable/StringBuilder."<init>":()V
	ldc	String assertion failed: 
	invokevirtual	Method scala/collection/mutable/StringBuilder.append:(Ljava/lang/Object;)Lscala/collection/mutable/StringBuilder;
	new	class scala/collection/mutable/StringBuilder
	dup
	invokespecial	Method scala/collection/mutable/StringBuilder."<init>":()V
	ldc	String testAll(
	invokevirtual	Method scala/collection/mutable/StringBuilder.append:(Ljava/lang/Object;)Lscala/collection/mutable/StringBuilder;
	getstatic	Field scala/Predef$.MODULE$:Lscala/Predef$;
	aload_1
	invokevirtual	Method scala/Predef$.byteArrayOps:([B)Lscala/collection/mutable/ArrayOps;
	invokeinterface	InterfaceMethod scala/collection/mutable/ArrayLike.deep:()Lscala/collection/IndexedSeq;
	invokevirtual	Method scala/collection/mutable/StringBuilder.append:(Ljava/lang/Object;)Lscala/collection/mutable/StringBuilder;
	ldc	String ) failed, result = 
	invokevirtual	Method scala/collection/mutable/StringBuilder.append:(Ljava/lang/Object;)Lscala/collection/mutable/StringBuilder;
	getstatic	Field scala/Predef$.MODULE$:Lscala/Predef$;
	getstatic	Field scala/Predef$.MODULE$:Lscala/Predef$;
	aload	7
	invokevirtual	Method scala/Predef$.byteArrayOps:([B)Lscala/collection/mutable/ArrayOps;
	aload_1
	arraylength
	invokeinterface	InterfaceMethod scala/collection/IndexedSeqLike.take:(I)Ljava/lang/Object;
	checkcast	class "[B"
	invokevirtual	Method scala/Predef$.byteArrayOps:([B)Lscala/collection/mutable/ArrayOps;
	invokeinterface	InterfaceMethod scala/collection/mutable/ArrayLike.deep:()Lscala/collection/IndexedSeq;
	invokevirtual	Method scala/collection/mutable/StringBuilder.append:(Ljava/lang/Object;)Lscala/collection/mutable/StringBuilder;
	invokevirtual	Method scala/collection/mutable/StringBuilder.toString:()Ljava/lang/String;
	invokevirtual	Method scala/collection/mutable/StringBuilder.append:(Ljava/lang/Object;)Lscala/collection/mutable/StringBuilder;
	invokevirtual	Method scala/collection/mutable/StringBuilder.toString:()Ljava/lang/String;
	invokespecial	Method java/lang/AssertionError."<init>":(Ljava/lang/Object;)V
	athrow
  Labels:
   	l1 = 92 // aload
   	l2 = 100 // iconst_1
   	l3 = 104 // iconst_0
   	l4 = 105 // istore
   	l5 = 113 // new
  LocalVariableTable: 
   Start  Length  Slot  Name   Signature
   0      206      0    this       Lscala/reflect/generic/ByteCodecs$;
   0      206      1    xs$2       [B
   21      8      2    len0       I
   112      94      6    assertion0       Z
   11      101      7    ys$2       [B
   113      93      7    ys$2       [B


public void test(scala.collection.Seq);
  Signature: (Lscala/collection/Seq;)V
  Code:
   Stack=3, Locals=2, Args_size=2
	aload_1
	new	class scala/reflect/generic/ByteCodecs$$anonfun$test$1
	dup
	invokespecial	Method scala/reflect/generic/ByteCodecs$$anonfun$test$1."<init>":()V
	invokeinterface	InterfaceMethod scala/collection/IterableLike.foreach:(Lscala/Function1;)V
	return
  Labels:
  LocalVariableTable: 
   Start  Length  Slot  Name   Signature
   0      14      0    this       Lscala/reflect/generic/ByteCodecs$;
   0      14      1    inputs       Lscala/collection/Seq;

  Signature: length = 0x2
   00 FFFFFF8A 

public void main(java.lang.String[]);
  Signature: ([Ljava/lang/String;)V
  Code:
   Stack=11, Locals=3, Args_size=2
	aload_0
	getstatic	Field scala/Predef$.MODULE$:Lscala/Predef$;
	iconst_4
	anewarray	class "[B"
	dup
	iconst_0
	getstatic	Field scala/Array$.MODULE$:Lscala/Array$;
	getstatic	Field scala/Predef$.MODULE$:Lscala/Predef$;
	iconst_3
	newarray byte
	dup
	iconst_0
	bipush	1
	bastore
	dup
	iconst_1
	bipush	2
	bastore
	dup
	iconst_2
	bipush	3
	bastore
	invokevirtual	Method scala/Predef$.wrapByteArray:([B)Lscala/collection/mutable/WrappedArray;
	getstatic	Field scala/reflect/Manifest$.MODULE$:Lscala/reflect/Manifest$;
	invokevirtual	Method scala/reflect/Manifest$.Byte:()Lscala/reflect/AnyValManifest;
	invokevirtual	Method scala/Array$.apply:(Lscala/collection/Seq;Lscala/reflect/ClassManifest;)Ljava/lang/Object;
	checkcast	class "[B"
	aastore
	dup
	iconst_1
	getstatic	Field scala/Array$.MODULE$:Lscala/Array$;
	getstatic	Field scala/Predef$.MODULE$:Lscala/Predef$;
	ldc	int 7
	newarray byte
	dup
	iconst_0
	bipush	1
	bastore
	dup
	iconst_1
	bipush	2
	bastore
	dup
	iconst_2
	bipush	3
	bastore
	dup
	iconst_3
	bipush	4
	bastore
	dup
	iconst_4
	bipush	5
	bastore
	dup
	iconst_5
	bipush	6
	bastore
	dup
	ldc	int 6
	bipush	7
	bastore
	invokevirtual	Method scala/Predef$.wrapByteArray:([B)Lscala/collection/mutable/WrappedArray;
	getstatic	Field scala/reflect/Manifest$.MODULE$:Lscala/reflect/Manifest$;
	invokevirtual	Method scala/reflect/Manifest$.Byte:()Lscala/reflect/AnyValManifest;
	invokevirtual	Method scala/Array$.apply:(Lscala/collection/Seq;Lscala/reflect/ClassManifest;)Ljava/lang/Object;
	checkcast	class "[B"
	aastore
	dup
	iconst_2
	getstatic	Field scala/Array$.MODULE$:Lscala/Array$;
	getstatic	Field scala/Predef$.MODULE$:Lscala/Predef$;
	ldc	int 7
	newarray byte
	dup
	iconst_0
	bipush	1
	bastore
	dup
	iconst_1
	bipush	-2
	bastore
	dup
	iconst_2
	bipush	0
	bastore
	dup
	iconst_3
	bipush	-3
	bastore
	dup
	iconst_4
	bipush	-5
	bastore
	dup
	iconst_5
	bipush	-6
	bastore
	dup
	ldc	int 6
	bipush	-7
	bastore
	invokevirtual	Method scala/Predef$.wrapByteArray:([B)Lscala/collection/mutable/WrappedArray;
	getstatic	Field scala/reflect/Manifest$.MODULE$:Lscala/reflect/Manifest$;
	invokevirtual	Method scala/reflect/Manifest$.Byte:()Lscala/reflect/AnyValManifest;
	invokevirtual	Method scala/Array$.apply:(Lscala/collection/Seq;Lscala/reflect/ClassManifest;)Ljava/lang/Object;
	checkcast	class "[B"
	aastore
	dup
	iconst_3
	getstatic	Field scala/Array$.MODULE$:Lscala/Array$;
	getstatic	Field scala/Predef$.MODULE$:Lscala/Predef$;
	ldc	int 10
	newarray byte
	dup
	iconst_0
	bipush	1
	bastore
	dup
	iconst_1
	bipush	3
	bastore
	dup
	iconst_2
	bipush	-1
	bastore
	dup
	iconst_3
	bipush	-128
	bastore
	dup
	iconst_4
	bipush	0
	bastore
	dup
	iconst_5
	bipush	0
	bastore
	dup
	ldc	int 6
	bipush	-128
	bastore
	dup
	ldc	int 7
	bipush	1
	bastore
	dup
	ldc	int 8
	bipush	2
	bastore
	dup
	ldc	int 9
	bipush	3
	bastore
	invokevirtual	Method scala/Predef$.wrapByteArray:([B)Lscala/collection/mutable/WrappedArray;
	getstatic	Field scala/reflect/Manifest$.MODULE$:Lscala/reflect/Manifest$;
	invokevirtual	Method scala/reflect/Manifest$.Byte:()Lscala/reflect/AnyValManifest;
	invokevirtual	Method scala/Array$.apply:(Lscala/collection/Seq;Lscala/reflect/ClassManifest;)Ljava/lang/Object;
	checkcast	class "[B"
	aastore
	checkcast	class "[Ljava/lang/Object;"
	invokevirtual	Method scala/Predef$.wrapRefArray:([Ljava/lang/Object;)Lscala/collection/mutable/WrappedArray;
	invokevirtual	Method test:(Lscala/collection/Seq;)V
	new	class scala/util/Random
	dup
	invokespecial	Method scala/util/Random."<init>":()V
	astore_2
	getstatic	Field scala/Predef$.MODULE$:Lscala/Predef$;
	iconst_1
	invokevirtual	Method scala/Predef$.intWrapper:(I)Lscala/runtime/RichInt;
	ldc	int 50000
	invokevirtual	Method scala/runtime/RichInt.until:(I)Lscala/collection/immutable/Range$ByOne;
	new	class scala/reflect/generic/ByteCodecs$$anonfun$main$1
	dup
	aload_2
	invokespecial	Method scala/reflect/generic/ByteCodecs$$anonfun$main$1."<init>":(Lscala/util/Random;)V
	invokeinterface	InterfaceMethod scala/collection/immutable/Range$ByOne.foreach:(Lscala/Function1;)V
	getstatic	Field scala/Predef$.MODULE$:Lscala/Predef$;
	ldc	String tested OK
	invokevirtual	Method scala/Predef$.println:(Ljava/lang/Object;)V
	return
  Labels:
  LocalVariableTable: 
   Start  Length  Slot  Name   Signature
   0      311      0    this       Lscala/reflect/generic/ByteCodecs$;
   0      311      1    args       [Ljava/lang/String;
   277      33      2    rand$1       Lscala/util/Random;


private scala.reflect.generic.ByteCodecs$();
  Signature: ()V
  Code:
   Stack=1, Locals=1, Args_size=1
	aload_0
	invokespecial	Method java/lang/Object."<init>":()V
	aload_0
	putstatic	Field MODULE$:Lscala/reflect/generic/ByteCodecs$;
	return
  Labels:

}

