Compiled from "ByteCodecs.scala"
public final class scala.reflect.generic.ByteCodecs$$anonfun$main$1 extends scala.runtime.AbstractFunction1 implements java.io.Serializable
  SourceFile: "ByteCodecs.scala"
  Scala: length = 0x
   
  InnerClass: 
   public final $anonfun$test$1=class scala/reflect/generic/ByteCodecs$$anonfun$test$1 of class scala/reflect/generic/ByteCodecs
   public final $anonfun$main$1=class scala/reflect/generic/ByteCodecs$$anonfun$main$1 of class scala/reflect/generic/ByteCodecs
  minor version: 0
  major version: 49
  Constant pool:
Asciz	SourceFile;
Asciz	ByteCodecs.scala;
Asciz	<clinit>;
Asciz	()V;
Asciz	Code;
Asciz	serialVersionUID;
Asciz	J;
Asciz	scala/reflect/generic/ByteCodecs$$anonfun$main$1;
class	scala/reflect/generic/ByteCodecs$$anonfun$main$1
NameAndType	serialVersionUID:J
Field	scala/reflect/generic/ByteCodecs$$anonfun$main$1.serialVersionUID:J
Asciz	rand$1;
Asciz	Lscala/util/Random;;
Asciz	apply;
Asciz	(I)V;
Asciz	LineNumberTable;
int	100;
Asciz	scala/collection/mutable/StringBuilder;
class	scala/collection/mutable/StringBuilder
Asciz	<init>;
NameAndType	"<init>":()V
Method	scala/collection/mutable/StringBuilder."<init>":()V
Asciz	tested ;
String	tested 
Asciz	append;
Asciz	(Ljava/lang/Object;)Lscala/collection/mutable/StringBuilder;;
NameAndType	append:(Ljava/lang/Object;)Lscala/collection/mutable/StringBuilder;
Method	scala/collection/mutable/StringBuilder.append:(Ljava/lang/Object;)Lscala/collection/mutable/StringBuilder;
Asciz	scala/runtime/BoxesRunTime;
class	scala/runtime/BoxesRunTime
Asciz	boxToInteger;
Asciz	(I)Ljava/lang/Integer;;
NameAndType	boxToInteger:(I)Ljava/lang/Integer;
Method	scala/runtime/BoxesRunTime.boxToInteger:(I)Ljava/lang/Integer;
Asciz	toString;
Asciz	()Ljava/lang/String;;
NameAndType	toString:()Ljava/lang/String;
Method	scala/collection/mutable/StringBuilder.toString:()Ljava/lang/String;
Asciz	scala/Console$;
class	scala/Console$
Asciz	MODULE$;
Asciz	Lscala/Console$;;
NameAndType	MODULE$:Lscala/Console$;
Field	scala/Console$.MODULE$:Lscala/Console$;
Asciz	out;
Asciz	()Ljava/io/PrintStream;;
NameAndType	out:()Ljava/io/PrintStream;
Method	scala/Console$.out:()Ljava/io/PrintStream;
Asciz	java/io/PrintStream;
class	java/io/PrintStream
Asciz	println;
Asciz	(Ljava/lang/Object;)V;
NameAndType	println:(Ljava/lang/Object;)V
Method	java/io/PrintStream.println:(Ljava/lang/Object;)V
NameAndType	rand$1:Lscala/util/Random;
Field	scala/reflect/generic/ByteCodecs$$anonfun$main$1.rand$1:Lscala/util/Random;
Asciz	scala/util/Random;
class	scala/util/Random
Asciz	nextBytes;
Asciz	([B)V;
NameAndType	nextBytes:([B)V
Method	scala/util/Random.nextBytes:([B)V
Asciz	scala/Predef$;
class	scala/Predef$
Asciz	Lscala/Predef$;;
NameAndType	MODULE$:Lscala/Predef$;
Field	scala/Predef$.MODULE$:Lscala/Predef$;
Asciz	[B;
class	"[B"
Asciz	[Ljava/lang/Object;;
class	"[Ljava/lang/Object;"
Asciz	wrapRefArray;
Asciz	([Ljava/lang/Object;)Lscala/collection/mutable/WrappedArray;;
NameAndType	wrapRefArray:([Ljava/lang/Object;)Lscala/collection/mutable/WrappedArray;
Method	scala/Predef$.wrapRefArray:([Ljava/lang/Object;)Lscala/collection/mutable/WrappedArray;
Asciz	scala/reflect/generic/ByteCodecs$$anonfun$test$1;
class	scala/reflect/generic/ByteCodecs$$anonfun$test$1
Method	scala/reflect/generic/ByteCodecs$$anonfun$test$1."<init>":()V
Asciz	scala/collection/IterableLike;
class	scala/collection/IterableLike
Asciz	foreach;
Asciz	(Lscala/Function1;)V;
NameAndType	foreach:(Lscala/Function1;)V
InterfaceMethod	scala/collection/IterableLike.foreach:(Lscala/Function1;)V
Asciz	this;
Asciz	Lscala/reflect/generic/ByteCodecs$$anonfun$main$1;;
Asciz	i;
Asciz	I;
Asciz	xs;
Asciz	LocalVariableTable;
Asciz	(Ljava/lang/Object;)Ljava/lang/Object;;
Asciz	unboxToInt;
Asciz	(Ljava/lang/Object;)I;
NameAndType	unboxToInt:(Ljava/lang/Object;)I
Method	scala/runtime/BoxesRunTime.unboxToInt:(Ljava/lang/Object;)I
NameAndType	apply:(I)V
Method	scala/reflect/generic/ByteCodecs$$anonfun$main$1.apply:(I)V
Asciz	scala/runtime/BoxedUnit;
class	scala/runtime/BoxedUnit
Asciz	UNIT;
Asciz	Lscala/runtime/BoxedUnit;;
NameAndType	UNIT:Lscala/runtime/BoxedUnit;
Field	scala/runtime/BoxedUnit.UNIT:Lscala/runtime/BoxedUnit;
Asciz	v1;
Asciz	Ljava/lang/Object;;
Asciz	(Lscala/util/Random;)V;
Asciz	scala/runtime/AbstractFunction1;
class	scala/runtime/AbstractFunction1
Method	scala/runtime/AbstractFunction1."<init>":()V
Asciz	Scala;
Asciz	InnerClasses;
Asciz	scala/reflect/generic/ByteCodecs;
class	scala/reflect/generic/ByteCodecs
Asciz	$anonfun$test$1;
Asciz	$anonfun$main$1;
Asciz	java/io/Serializable;
class	java/io/Serializable

{
public static final long serialVersionUID;
  Signature: J

public final scala.util.Random rand$1;
  Signature: Lscala/util/Random;

public static {};
  Signature: ()V
  Code:
   Stack=2, Locals=0, Args_size=0
	lconst_0
	putstatic	Field serialVersionUID:J
	return
  Labels:

public final void apply(int);
  Signature: (I)V
  Code:
   Stack=5, Locals=6, Args_size=2
	iload_1
	ldc	int 100
	irem
	iconst_0
	if_icmpne	l1 // iload_1
	new	class scala/collection/mutable/StringBuilder
	dup
	invokespecial	Method scala/collection/mutable/StringBuilder."<init>":()V
	ldc	String tested 
	invokevirtual	Method scala/collection/mutable/StringBuilder.append:(Ljava/lang/Object;)Lscala/collection/mutable/StringBuilder;
	iload_1
	invokestatic	Method scala/runtime/BoxesRunTime.boxToInteger:(I)Ljava/lang/Integer;
	invokevirtual	Method scala/collection/mutable/StringBuilder.append:(Ljava/lang/Object;)Lscala/collection/mutable/StringBuilder;
	invokevirtual	Method scala/collection/mutable/StringBuilder.toString:()Ljava/lang/String;
	astore_3
	getstatic	Field scala/Console$.MODULE$:Lscala/Console$;
	astore_2
	aload_2
	invokevirtual	Method scala/Console$.out:()Ljava/io/PrintStream;
	aload_3
	invokevirtual	Method java/io/PrintStream.println:(Ljava/lang/Object;)V
l1	iload_1
	newarray byte
	astore	4
	aload_0
	getfield	Field rand$1:Lscala/util/Random;
	aload	4
	invokevirtual	Method scala/util/Random.nextBytes:([B)V
	getstatic	Field scala/Predef$.MODULE$:Lscala/Predef$;
	iconst_1
	anewarray	class "[B"
	dup
	iconst_0
	aload	4
	aastore
	checkcast	class "[Ljava/lang/Object;"
	invokevirtual	Method scala/Predef$.wrapRefArray:([Ljava/lang/Object;)Lscala/collection/mutable/WrappedArray;
	astore	5
	aload	5
	new	class scala/reflect/generic/ByteCodecs$$anonfun$test$1
	dup
	invokespecial	Method scala/reflect/generic/ByteCodecs$$anonfun$test$1."<init>":()V
	invokeinterface	InterfaceMethod scala/collection/IterableLike.foreach:(Lscala/Function1;)V
	return
  Labels:
   	l1 = 43 // iload_1
  LocalVariableTable: 
   Start  Length  Slot  Name   Signature
   0      92      0    this       Lscala/reflect/generic/ByteCodecs$$anonfun$main$1;
   0      92      1    i       I
   48      43      4    xs       [B


public final java.lang.Object apply(java.lang.Object);
  Signature: (Ljava/lang/Object;)Ljava/lang/Object;
  Code:
   Stack=2, Locals=2, Args_size=2
	aload_0
	aload_1
	invokestatic	Method scala/runtime/BoxesRunTime.unboxToInt:(Ljava/lang/Object;)I
	invokevirtual	Method apply:(I)V
	getstatic	Field scala/runtime/BoxedUnit.UNIT:Lscala/runtime/BoxedUnit;
	areturn
  Labels:
  LocalVariableTable: 
   Start  Length  Slot  Name   Signature
   0      12      0    this       Lscala/reflect/generic/ByteCodecs$$anonfun$main$1;
   0      12      1    v1       Ljava/lang/Object;


public scala.reflect.generic.ByteCodecs$$anonfun$main$1(scala.util.Random);
  Signature: (Lscala/util/Random;)V
  Code:
   Stack=2, Locals=2, Args_size=2
	aload_0
	aload_1
	putfield	Field rand$1:Lscala/util/Random;
	aload_0
	invokespecial	Method scala/runtime/AbstractFunction1."<init>":()V
	return
  Labels:

}

