Compiled from "ByteCodecs.scala"
public final class scala.reflect.generic.ByteCodecs extends java.lang.Object
  SourceFile: "ByteCodecs.scala"
  ScalaSig: length = 0x27A
   05 00 65 07 05 01 02 FFFFFF88 02 09 01 0A 42 79 74 65
   43 6F 64 65 63 73 0A 02 03 04 01 07 67 65 6E 65
   72 69 63 0A 02 05 06 01 07 72 65 66 6C 65 63 74
   0A 01 07 01 05 73 63 61 6C 61 03 00 10 02 0A 0B
   0D 01 02 06 08 0C 02 FFFFFF84 FFFFFF80 FFFFFF80 FFFFFF88 02 0D 02 0A 42
   79 74 65 43 6F 64 65 63 73 13 03 0B 0E 16 10 02
   0F 14 0D 01 10 0A 02 11 12 01 04 6C 61 6E 67 0A
   01 13 01 04 6A 61 76 61 09 02 15 10 02 06 4F 62
   6A 65 63 74 10 02 17 18 0D 01 06 09 02 19 06 02
   0B 53 63 61 6C 61 4F 62 6A 65 63 74 08 05 1B 0B
   FFFFFF84 00 1C 01 06 3C 69 6E 69 74 3E 14 01 09 08 05
   1E 0B FFFFFF84 00 1F 01 09 61 76 6F 69 64 5A 65 72 6F
   14 02 20 26 10 03 17 21 23 09 02 22 06 02 05 41
   72 72 61 79 10 02 17 24 09 02 25 06 02 04 42 79
   74 65 08 05 27 1D FFFFFFC0 00 20 01 03 73 72 63 08 05
   29 0B FFFFFF84 00 2A 01 0E 72 65 67 65 6E 65 72 61 74
   65 5A 65 72 6F 14 02 2B 2E 10 02 17 2C 09 02 2D
   06 02 03 49 6E 74 08 05 27 28 FFFFFFC0 00 20 08 05 30
   0B FFFFFF84 00 31 01 0A 65 6E 63 6F 64 65 38 74 6F 37
   14 02 20 32 08 05 27 2F FFFFFFC0 00 20 08 05 34 0B FFFFFF84
   00 35 01 0A 64 65 63 6F 64 65 37 74 6F 38 14 04
   36 39 3A 3C 10 02 17 37 09 02 38 06 02 04 55 6E
   69 74 08 05 27 33 FFFFFFC0 00 20 08 05 3B 33 FFFFFFC0 00 2B
   01 06 73 72 63 6C 65 6E 08 05 3D 33 FFFFFFC0 00 2B 01
   06 64 73 74 6C 65 6E 08 05 3F 0B FFFFFF84 00 40 01 06
   65 6E 63 6F 64 65 14 02 20 41 08 05 42 3E FFFFFFC0 00
   20 01 02 78 73 08 05 44 0B FFFFFF84 00 45 01 06 64 65
   63 6F 64 65 14 03 36 46 47 08 05 42 43 FFFFFFC0 00 20
   08 05 3D 43 FFFFFFC0 00 2B 08 05 49 0B FFFFFF84 00 4A 01 08
   74 65 73 74 38 74 6F 37 14 02 36 4B 08 05 42 48
   FFFFFFC0 00 20 08 05 4D 0B FFFFFF84 00 4E 01 07 74 65 73 74
   41 6C 6C 14 02 36 4F 08 05 42 4C FFFFFFC0 00 20 08 05
   51 0B FFFFFF84 00 52 01 04 74 65 73 74 14 02 36 53 08
   05 54 50 FFFFFFC0 00 55 01 06 69 6E 70 75 74 73 10 03
   17 56 20 09 02 57 06 02 0A 3C 72 65 70 65 61 74
   65 64 3E 08 05 59 0B FFFFFF84 00 5A 01 04 6D 61 69 6E
   14 02 36 5B 08 05 5C 58 FFFFFFC0 00 5D 01 04 61 72 67
   73 10 03 17 21 5E 10 02 5F 62 0E 02 17 60 09 02
   61 06 01 06 50 72 65 64 65 66 09 02 63 64 02 06
   53 74 72 69 6E 67 0A 02 61 06 
  InnerClass: 
   public final $anonfun$main$1=class scala/reflect/generic/ByteCodecs$$anonfun$main$1 of class scala/reflect/generic/ByteCodecs
   public final $anonfun$test$1=class scala/reflect/generic/ByteCodecs$$anonfun$test$1 of class scala/reflect/generic/ByteCodecs
   public final $anonfun$testAll$1=class scala/reflect/generic/ByteCodecs$$anonfun$testAll$1 of class scala/reflect/generic/ByteCodecs
   public final $anonfun$test8to7$1=class scala/reflect/generic/ByteCodecs$$anonfun$test8to7$1 of class scala/reflect/generic/ByteCodecs
  minor version: 0
  major version: 49
  Constant pool:
Asciz	SourceFile;
Asciz	ByteCodecs.scala;
Asciz	main;
Asciz	([Ljava/lang/String;)V;
Asciz	Code;
Asciz	scala/reflect/generic/ByteCodecs$;
class	scala/reflect/generic/ByteCodecs$
Asciz	MODULE$;
Asciz	Lscala/reflect/generic/ByteCodecs$;;
NameAndType	MODULE$:Lscala/reflect/generic/ByteCodecs$;
Field	scala/reflect/generic/ByteCodecs$.MODULE$:Lscala/reflect/generic/ByteCodecs$;
NameAndType	main:([Ljava/lang/String;)V
Method	scala/reflect/generic/ByteCodecs$.main:([Ljava/lang/String;)V
Asciz	test;
Asciz	(Lscala/collection/Seq;)V;
NameAndType	test:(Lscala/collection/Seq;)V
Method	scala/reflect/generic/ByteCodecs$.test:(Lscala/collection/Seq;)V
Asciz	(Lscala/collection/Seq<[B>;)V;
Asciz	Signature;
Asciz	testAll;
Asciz	([B)V;
NameAndType	testAll:([B)V
Method	scala/reflect/generic/ByteCodecs$.testAll:([B)V
Asciz	test8to7;
NameAndType	test8to7:([B)V
Method	scala/reflect/generic/ByteCodecs$.test8to7:([B)V
Asciz	decode;
Asciz	([BI)V;
NameAndType	decode:([BI)V
Method	scala/reflect/generic/ByteCodecs$.decode:([BI)V
Asciz	encode;
Asciz	([B)[B;
NameAndType	encode:([B)[B
Method	scala/reflect/generic/ByteCodecs$.encode:([B)[B
Asciz	decode7to8;
Asciz	([BII)V;
NameAndType	decode7to8:([BII)V
Method	scala/reflect/generic/ByteCodecs$.decode7to8:([BII)V
Asciz	encode8to7;
NameAndType	encode8to7:([B)[B
Method	scala/reflect/generic/ByteCodecs$.encode8to7:([B)[B
Asciz	regenerateZero;
Asciz	([B)I;
NameAndType	regenerateZero:([B)I
Method	scala/reflect/generic/ByteCodecs$.regenerateZero:([B)I
Asciz	avoidZero;
NameAndType	avoidZero:([B)[B
Method	scala/reflect/generic/ByteCodecs$.avoidZero:([B)[B
Asciz	ScalaSig;
Asciz	InnerClasses;
Asciz	scala/reflect/generic/ByteCodecs$$anonfun$main$1;
class	scala/reflect/generic/ByteCodecs$$anonfun$main$1
Asciz	scala/reflect/generic/ByteCodecs;
class	scala/reflect/generic/ByteCodecs
Asciz	$anonfun$main$1;
Asciz	scala/reflect/generic/ByteCodecs$$anonfun$test$1;
class	scala/reflect/generic/ByteCodecs$$anonfun$test$1
Asciz	$anonfun$test$1;
Asciz	scala/reflect/generic/ByteCodecs$$anonfun$testAll$1;
class	scala/reflect/generic/ByteCodecs$$anonfun$testAll$1
Asciz	$anonfun$testAll$1;
Asciz	scala/reflect/generic/ByteCodecs$$anonfun$test8to7$1;
class	scala/reflect/generic/ByteCodecs$$anonfun$test8to7$1
Asciz	$anonfun$test8to7$1;
Asciz	java/lang/Object;
class	java/lang/Object

{
public static final void main(java.lang.String[]);
  Signature: ([Ljava/lang/String;)V
  Code:
   Stack=2, Locals=1, Args_size=1
	getstatic	Field scala/reflect/generic/ByteCodecs$.MODULE$:Lscala/reflect/generic/ByteCodecs$;
	aload_0
	invokevirtual	Method scala/reflect/generic/ByteCodecs$.main:([Ljava/lang/String;)V
	return
  Labels:

public static final void test(scala.collection.Seq);
  Signature: (Lscala/collection/Seq;)V
  Code:
   Stack=2, Locals=1, Args_size=1
	getstatic	Field scala/reflect/generic/ByteCodecs$.MODULE$:Lscala/reflect/generic/ByteCodecs$;
	aload_0
	invokevirtual	Method scala/reflect/generic/ByteCodecs$.test:(Lscala/collection/Seq;)V
	return
  Labels:
  Signature: length = 0x2
   00 12 

public static final void testAll(byte[]);
  Signature: ([B)V
  Code:
   Stack=2, Locals=1, Args_size=1
	getstatic	Field scala/reflect/generic/ByteCodecs$.MODULE$:Lscala/reflect/generic/ByteCodecs$;
	aload_0
	invokevirtual	Method scala/reflect/generic/ByteCodecs$.testAll:([B)V
	return
  Labels:

public static final void test8to7(byte[]);
  Signature: ([B)V
  Code:
   Stack=2, Locals=1, Args_size=1
	getstatic	Field scala/reflect/generic/ByteCodecs$.MODULE$:Lscala/reflect/generic/ByteCodecs$;
	aload_0
	invokevirtual	Method scala/reflect/generic/ByteCodecs$.test8to7:([B)V
	return
  Labels:

public static final void decode(byte[], int);
  Signature: ([BI)V
  Code:
   Stack=3, Locals=2, Args_size=2
	getstatic	Field scala/reflect/generic/ByteCodecs$.MODULE$:Lscala/reflect/generic/ByteCodecs$;
	aload_0
	iload_1
	invokevirtual	Method scala/reflect/generic/ByteCodecs$.decode:([BI)V
	return
  Labels:

public static final byte[] encode(byte[]);
  Signature: ([B)[B
  Code:
   Stack=2, Locals=1, Args_size=1
	getstatic	Field scala/reflect/generic/ByteCodecs$.MODULE$:Lscala/reflect/generic/ByteCodecs$;
	aload_0
	invokevirtual	Method scala/reflect/generic/ByteCodecs$.encode:([B)[B
	areturn
  Labels:

public static final void decode7to8(byte[], int, int);
  Signature: ([BII)V
  Code:
   Stack=4, Locals=3, Args_size=3
	getstatic	Field scala/reflect/generic/ByteCodecs$.MODULE$:Lscala/reflect/generic/ByteCodecs$;
	aload_0
	iload_1
	iload_2
	invokevirtual	Method scala/reflect/generic/ByteCodecs$.decode7to8:([BII)V
	return
  Labels:

public static final byte[] encode8to7(byte[]);
  Signature: ([B)[B
  Code:
   Stack=2, Locals=1, Args_size=1
	getstatic	Field scala/reflect/generic/ByteCodecs$.MODULE$:Lscala/reflect/generic/ByteCodecs$;
	aload_0
	invokevirtual	Method scala/reflect/generic/ByteCodecs$.encode8to7:([B)[B
	areturn
  Labels:

public static final int regenerateZero(byte[]);
  Signature: ([B)I
  Code:
   Stack=2, Locals=1, Args_size=1
	getstatic	Field scala/reflect/generic/ByteCodecs$.MODULE$:Lscala/reflect/generic/ByteCodecs$;
	aload_0
	invokevirtual	Method scala/reflect/generic/ByteCodecs$.regenerateZero:([B)I
	ireturn
  Labels:

public static final byte[] avoidZero(byte[]);
  Signature: ([B)[B
  Code:
   Stack=2, Locals=1, Args_size=1
	getstatic	Field scala/reflect/generic/ByteCodecs$.MODULE$:Lscala/reflect/generic/ByteCodecs$;
	aload_0
	invokevirtual	Method scala/reflect/generic/ByteCodecs$.avoidZero:([B)[B
	areturn
  Labels:

}

