Compiled from "Constants.scala"
public class scala.reflect.generic.Constants$Constant extends java.lang.Object implements scala.ScalaObject,scala.Product,java.io.Serializable
  SourceFile: "Constants.scala"
  Scala: length = 0x
   
  InnerClass: 
   public abstract AbsType=class scala/reflect/generic/Types$AbsType of class scala/reflect/generic/Types
   public abstract AbsSymbol=class scala/reflect/generic/Symbols$AbsSymbol of class scala/reflect/generic/Symbols
   public Constant=class scala/reflect/generic/Constants$Constant of class scala/reflect/generic/Constants
   public abstract AbsDefinitions=class scala/reflect/generic/StandardDefinitions$AbsDefinitions of class scala/reflect/generic/StandardDefinitions
   public final $anonfun$escape$1$1=class scala/reflect/generic/Constants$Constant$$anonfun$escape$1$1 of class scala/reflect/generic/Constants$Constant
  minor version: 0
  major version: 49
  Constant pool:
Asciz	SourceFile;
Asciz	Constants.scala;
Asciz	$outer;
Asciz	Lscala/reflect/generic/Universe;;
Asciz	tag;
Asciz	I;
Asciz	value;
Asciz	Ljava/lang/Object;;
Asciz	productIterator;
Asciz	()Lscala/collection/Iterator;;
Asciz	Code;
Asciz	LineNumberTable;
Asciz	scala/Product$class;
class	scala/Product$class
Asciz	(Lscala/Product;)Lscala/collection/Iterator;;
NameAndType	productIterator:(Lscala/Product;)Lscala/collection/Iterator;
Method	scala/Product$class.productIterator:(Lscala/Product;)Lscala/collection/Iterator;
Asciz	productElements;
NameAndType	productElements:(Lscala/Product;)Lscala/collection/Iterator;
Method	scala/Product$class.productElements:(Lscala/Product;)Lscala/collection/Iterator;
Asciz	Deprecated;
Asciz	copy$default$1;
Asciz	()Ljava/lang/Object;;
Asciz	scala/reflect/generic/Constants$Constant;
class	scala/reflect/generic/Constants$Constant
NameAndType	value:()Ljava/lang/Object;
Method	scala/reflect/generic/Constants$Constant.value:()Ljava/lang/Object;
NameAndType	value:Ljava/lang/Object;
Field	scala/reflect/generic/Constants$Constant.value:Ljava/lang/Object;
Asciz	()I;
NameAndType	tag:I
Field	scala/reflect/generic/Constants$Constant.tag:I
Asciz	isNumeric;
Asciz	()Z;
NameAndType	tag:()I
Method	scala/reflect/generic/Constants$Constant.tag:()I
int	9;
Asciz	tpe;
Asciz	()Lscala/reflect/generic/Types$AbsType;;
Asciz	scala/MatchError;
class	scala/MatchError
Asciz	scala/runtime/BoxesRunTime;
class	scala/runtime/BoxesRunTime
Asciz	boxToInteger;
Asciz	(I)Ljava/lang/Integer;;
NameAndType	boxToInteger:(I)Ljava/lang/Integer;
Method	scala/runtime/BoxesRunTime.boxToInteger:(I)Ljava/lang/Integer;
Asciz	java/lang/Object;
class	java/lang/Object
Asciz	toString;
Asciz	()Ljava/lang/String;;
NameAndType	toString:()Ljava/lang/String;
Method	java/lang/Object.toString:()Ljava/lang/String;
Asciz	<init>;
Asciz	(Ljava/lang/String;)V;
NameAndType	"<init>":(Ljava/lang/String;)V
Method	scala/MatchError."<init>":(Ljava/lang/String;)V
Asciz	symbolValue;
Asciz	()Lscala/reflect/generic/Symbols$AbsSymbol;;
NameAndType	symbolValue:()Lscala/reflect/generic/Symbols$AbsSymbol;
Method	scala/reflect/generic/Constants$Constant.symbolValue:()Lscala/reflect/generic/Symbols$AbsSymbol;
Asciz	scala/reflect/generic/Symbols$AbsSymbol;
class	scala/reflect/generic/Symbols$AbsSymbol
Asciz	owner;
NameAndType	owner:()Lscala/reflect/generic/Symbols$AbsSymbol;
Method	scala/reflect/generic/Symbols$AbsSymbol.owner:()Lscala/reflect/generic/Symbols$AbsSymbol;
Asciz	linkedClassOfClass;
NameAndType	linkedClassOfClass:()Lscala/reflect/generic/Symbols$AbsSymbol;
Method	scala/reflect/generic/Symbols$AbsSymbol.linkedClassOfClass:()Lscala/reflect/generic/Symbols$AbsSymbol;
NameAndType	tpe:()Lscala/reflect/generic/Types$AbsType;
Method	scala/reflect/generic/Symbols$AbsSymbol.tpe:()Lscala/reflect/generic/Types$AbsType;
Asciz	scala$reflect$generic$Constants$Constant$$$outer;
Asciz	()Lscala/reflect/generic/Universe;;
NameAndType	scala$reflect$generic$Constants$Constant$$$outer:()Lscala/reflect/generic/Universe;
Method	scala/reflect/generic/Constants$Constant.scala$reflect$generic$Constants$Constant$$$outer:()Lscala/reflect/generic/Universe;
Asciz	scala/reflect/generic/StandardDefinitions;
class	scala/reflect/generic/StandardDefinitions
Asciz	definitions;
Asciz	()Lscala/reflect/generic/StandardDefinitions$AbsDefinitions;;
NameAndType	definitions:()Lscala/reflect/generic/StandardDefinitions$AbsDefinitions;
InterfaceMethod	scala/reflect/generic/StandardDefinitions.definitions:()Lscala/reflect/generic/StandardDefinitions$AbsDefinitions;
Asciz	scala/reflect/generic/Types$AbsType;
class	scala/reflect/generic/Types$AbsType
Asciz	scala/reflect/generic/StandardDefinitions$AbsDefinitions;
class	scala/reflect/generic/StandardDefinitions$AbsDefinitions
Asciz	ClassType;
Asciz	(Lscala/reflect/generic/Types$AbsType;)Lscala/reflect/generic/Types$AbsType;;
NameAndType	ClassType:(Lscala/reflect/generic/Types$AbsType;)Lscala/reflect/generic/Types$AbsType;
Method	scala/reflect/generic/StandardDefinitions$AbsDefinitions.ClassType:(Lscala/reflect/generic/Types$AbsType;)Lscala/reflect/generic/Types$AbsType;
Asciz	NullClass;
NameAndType	NullClass:()Lscala/reflect/generic/Symbols$AbsSymbol;
Method	scala/reflect/generic/StandardDefinitions$AbsDefinitions.NullClass:()Lscala/reflect/generic/Symbols$AbsSymbol;
Asciz	StringClass;
NameAndType	StringClass:()Lscala/reflect/generic/Symbols$AbsSymbol;
Method	scala/reflect/generic/StandardDefinitions$AbsDefinitions.StringClass:()Lscala/reflect/generic/Symbols$AbsSymbol;
Asciz	DoubleClass;
NameAndType	DoubleClass:()Lscala/reflect/generic/Symbols$AbsSymbol;
Method	scala/reflect/generic/StandardDefinitions$AbsDefinitions.DoubleClass:()Lscala/reflect/generic/Symbols$AbsSymbol;
Asciz	FloatClass;
NameAndType	FloatClass:()Lscala/reflect/generic/Symbols$AbsSymbol;
Method	scala/reflect/generic/StandardDefinitions$AbsDefinitions.FloatClass:()Lscala/reflect/generic/Symbols$AbsSymbol;
Asciz	LongClass;
NameAndType	LongClass:()Lscala/reflect/generic/Symbols$AbsSymbol;
Method	scala/reflect/generic/StandardDefinitions$AbsDefinitions.LongClass:()Lscala/reflect/generic/Symbols$AbsSymbol;
Asciz	IntClass;
NameAndType	IntClass:()Lscala/reflect/generic/Symbols$AbsSymbol;
Method	scala/reflect/generic/StandardDefinitions$AbsDefinitions.IntClass:()Lscala/reflect/generic/Symbols$AbsSymbol;
Asciz	CharClass;
NameAndType	CharClass:()Lscala/reflect/generic/Symbols$AbsSymbol;
Method	scala/reflect/generic/StandardDefinitions$AbsDefinitions.CharClass:()Lscala/reflect/generic/Symbols$AbsSymbol;
Asciz	ShortClass;
NameAndType	ShortClass:()Lscala/reflect/generic/Symbols$AbsSymbol;
Method	scala/reflect/generic/StandardDefinitions$AbsDefinitions.ShortClass:()Lscala/reflect/generic/Symbols$AbsSymbol;
Asciz	ByteClass;
NameAndType	ByteClass:()Lscala/reflect/generic/Symbols$AbsSymbol;
Method	scala/reflect/generic/StandardDefinitions$AbsDefinitions.ByteClass:()Lscala/reflect/generic/Symbols$AbsSymbol;
Asciz	BooleanClass;
NameAndType	BooleanClass:()Lscala/reflect/generic/Symbols$AbsSymbol;
Method	scala/reflect/generic/StandardDefinitions$AbsDefinitions.BooleanClass:()Lscala/reflect/generic/Symbols$AbsSymbol;
Asciz	UnitClass;
NameAndType	UnitClass:()Lscala/reflect/generic/Symbols$AbsSymbol;
Method	scala/reflect/generic/StandardDefinitions$AbsDefinitions.UnitClass:()Lscala/reflect/generic/Symbols$AbsSymbol;
Asciz	this;
Asciz	Lscala/reflect/generic/Constants$Constant;;
Asciz	temp1;
Asciz	LocalVariableTable;
Asciz	equals;
Asciz	(Ljava/lang/Object;)Z;
Asciz	java/lang/Number;
class	java/lang/Number
Asciz	java/lang/Character;
class	java/lang/Character
Asciz	equals2;
Asciz	(Ljava/lang/Object;Ljava/lang/Object;)Z;
NameAndType	equals2:(Ljava/lang/Object;Ljava/lang/Object;)Z
Method	scala/runtime/BoxesRunTime.equals2:(Ljava/lang/Object;Ljava/lang/Object;)Z
NameAndType	equals:(Ljava/lang/Object;)Z
Method	java/lang/Object.equals:(Ljava/lang/Object;)Z
Asciz	isNaN;
NameAndType	isNaN:()Z
Method	scala/reflect/generic/Constants$Constant.isNaN:()Z
Asciz	other;
Asciz	x0;
Asciz	y0;
Asciz	temp3;
Asciz	java/lang/Float;
class	java/lang/Float
Asciz	unboxToFloat;
Asciz	(Ljava/lang/Object;)F;
NameAndType	unboxToFloat:(Ljava/lang/Object;)F
Method	scala/runtime/BoxesRunTime.unboxToFloat:(Ljava/lang/Object;)F
Asciz	valueOf;
Asciz	(F)Ljava/lang/Float;;
NameAndType	valueOf:(F)Ljava/lang/Float;
Method	java/lang/Float.valueOf:(F)Ljava/lang/Float;
Method	java/lang/Float.isNaN:()Z
Asciz	java/lang/Double;
class	java/lang/Double
Asciz	unboxToDouble;
Asciz	(Ljava/lang/Object;)D;
NameAndType	unboxToDouble:(Ljava/lang/Object;)D
Method	scala/runtime/BoxesRunTime.unboxToDouble:(Ljava/lang/Object;)D
Asciz	(D)Ljava/lang/Double;;
NameAndType	valueOf:(D)Ljava/lang/Double;
Method	java/lang/Double.valueOf:(D)Ljava/lang/Double;
Method	java/lang/Double.isNaN:()Z
Asciz	temp6;
Asciz	F;
Asciz	temp5;
Asciz	temp7;
Asciz	D;
Asciz	booleanValue;
Asciz	unboxToBoolean;
NameAndType	unboxToBoolean:(Ljava/lang/Object;)Z
Method	scala/runtime/BoxesRunTime.unboxToBoolean:(Ljava/lang/Object;)Z
Asciz	java/lang/Error;
class	java/lang/Error
Asciz	scala/collection/mutable/StringBuilder;
class	scala/collection/mutable/StringBuilder
Asciz	()V;
NameAndType	"<init>":()V
Method	scala/collection/mutable/StringBuilder."<init>":()V
Asciz	value ;
String	value 
Asciz	append;
Asciz	(Ljava/lang/Object;)Lscala/collection/mutable/StringBuilder;;
NameAndType	append:(Ljava/lang/Object;)Lscala/collection/mutable/StringBuilder;
Method	scala/collection/mutable/StringBuilder.append:(Ljava/lang/Object;)Lscala/collection/mutable/StringBuilder;
Asciz	 is not a boolean;
String	 is not a boolean
Method	scala/collection/mutable/StringBuilder.toString:()Ljava/lang/String;
Method	java/lang/Error."<init>":(Ljava/lang/String;)V
Asciz	byteValue;
Asciz	()B;
Asciz	 is not a Byte;
String	 is not a Byte
Asciz	unboxToLong;
Asciz	(Ljava/lang/Object;)J;
NameAndType	unboxToLong:(Ljava/lang/Object;)J
Method	scala/runtime/BoxesRunTime.unboxToLong:(Ljava/lang/Object;)J
Asciz	unboxToInt;
Asciz	(Ljava/lang/Object;)I;
NameAndType	unboxToInt:(Ljava/lang/Object;)I
Method	scala/runtime/BoxesRunTime.unboxToInt:(Ljava/lang/Object;)I
Asciz	unboxToChar;
Asciz	(Ljava/lang/Object;)C;
NameAndType	unboxToChar:(Ljava/lang/Object;)C
Method	scala/runtime/BoxesRunTime.unboxToChar:(Ljava/lang/Object;)C
Asciz	unboxToShort;
Asciz	(Ljava/lang/Object;)S;
NameAndType	unboxToShort:(Ljava/lang/Object;)S
Method	scala/runtime/BoxesRunTime.unboxToShort:(Ljava/lang/Object;)S
Asciz	unboxToByte;
Asciz	(Ljava/lang/Object;)B;
NameAndType	unboxToByte:(Ljava/lang/Object;)B
Method	scala/runtime/BoxesRunTime.unboxToByte:(Ljava/lang/Object;)B
Asciz	temp8;
Asciz	shortValue;
Asciz	()S;
Asciz	 is not a Short;
String	 is not a Short
Asciz	temp9;
Asciz	charValue;
Asciz	()C;
Asciz	 is not a Char;
String	 is not a Char
Asciz	temp10;
Asciz	intValue;
Asciz	 is not an Int;
String	 is not an Int
Asciz	temp11;
Asciz	longValue;
Asciz	()J;
Asciz	 is not a Long;
String	 is not a Long
Asciz	temp12;
Asciz	floatValue;
Asciz	()F;
Asciz	 is not a Float;
String	 is not a Float
Asciz	temp13;
Asciz	doubleValue;
Asciz	()D;
Asciz	 is not a Double;
String	 is not a Double
Asciz	temp14;
Asciz	convertTo;
Asciz	(Lscala/reflect/generic/Types$AbsType;)Lscala/reflect/generic/Constants$Constant;;
Asciz	typeSymbol;
NameAndType	typeSymbol:()Lscala/reflect/generic/Symbols$AbsSymbol;
Method	scala/reflect/generic/Types$AbsType.typeSymbol:()Lscala/reflect/generic/Symbols$AbsSymbol;
Method	scala/reflect/generic/Constants$Constant.tpe:()Lscala/reflect/generic/Types$AbsType;
int	6;
int	-128;
NameAndType	intValue:()I
Method	scala/reflect/generic/Constants$Constant.intValue:()I
int	127;
NameAndType	byteValue:()B
Method	scala/reflect/generic/Constants$Constant.byteValue:()B
Asciz	boxToByte;
Asciz	(B)Ljava/lang/Byte;;
NameAndType	boxToByte:(B)Ljava/lang/Byte;
Method	scala/runtime/BoxesRunTime.boxToByte:(B)Ljava/lang/Byte;
Asciz	(Lscala/reflect/generic/Universe;Ljava/lang/Object;)V;
NameAndType	"<init>":(Lscala/reflect/generic/Universe;Ljava/lang/Object;)V
Method	scala/reflect/generic/Constants$Constant."<init>":(Lscala/reflect/generic/Universe;Ljava/lang/Object;)V
int	-32768;
int	32767;
NameAndType	shortValue:()S
Method	scala/reflect/generic/Constants$Constant.shortValue:()S
Asciz	boxToShort;
Asciz	(S)Ljava/lang/Short;;
NameAndType	boxToShort:(S)Ljava/lang/Short;
Method	scala/runtime/BoxesRunTime.boxToShort:(S)Ljava/lang/Short;
int	65635;
NameAndType	charValue:()C
Method	scala/reflect/generic/Constants$Constant.charValue:()C
Asciz	boxToCharacter;
Asciz	(C)Ljava/lang/Character;;
NameAndType	boxToCharacter:(C)Ljava/lang/Character;
Method	scala/runtime/BoxesRunTime.boxToCharacter:(C)Ljava/lang/Character;
int	7;
NameAndType	longValue:()J
Method	scala/reflect/generic/Constants$Constant.longValue:()J
Asciz	boxToLong;
Asciz	(J)Ljava/lang/Long;;
NameAndType	boxToLong:(J)Ljava/lang/Long;
Method	scala/runtime/BoxesRunTime.boxToLong:(J)Ljava/lang/Long;
int	8;
NameAndType	floatValue:()F
Method	scala/reflect/generic/Constants$Constant.floatValue:()F
Asciz	boxToFloat;
NameAndType	boxToFloat:(F)Ljava/lang/Float;
Method	scala/runtime/BoxesRunTime.boxToFloat:(F)Ljava/lang/Float;
NameAndType	doubleValue:()D
Method	scala/reflect/generic/Constants$Constant.doubleValue:()D
Asciz	boxToDouble;
NameAndType	boxToDouble:(D)Ljava/lang/Double;
Method	scala/runtime/BoxesRunTime.boxToDouble:(D)Ljava/lang/Double;
Asciz	pt;
Asciz	Lscala/reflect/generic/Types$AbsType;;
Asciz	target;
Asciz	Lscala/reflect/generic/Symbols$AbsSymbol;;
Asciz	stringValue;
Asciz	null;
String	null
int	12;
Asciz	typeValue;
NameAndType	typeValue:()Lscala/reflect/generic/Types$AbsType;
Method	scala/reflect/generic/Constants$Constant.typeValue:()Lscala/reflect/generic/Types$AbsType;
Asciz	signature;
Asciz	(Lscala/reflect/generic/Types$AbsType;)Ljava/lang/String;;
NameAndType	signature:(Lscala/reflect/generic/Types$AbsType;)Ljava/lang/String;
Method	scala/reflect/generic/StandardDefinitions$AbsDefinitions.signature:(Lscala/reflect/generic/Types$AbsType;)Ljava/lang/String;
Asciz	escapedStringValue;
Asciz	classOf[;
String	classOf[
Asciz	];
String	]
Asciz	\";
String	\"
NameAndType	stringValue:()Ljava/lang/String;
Method	scala/reflect/generic/Constants$Constant.stringValue:()Ljava/lang/String;
Asciz	escape$1;
Asciz	(Ljava/lang/String;)Ljava/lang/String;;
NameAndType	escape$1:(Ljava/lang/String;)Ljava/lang/String;
Method	scala/reflect/generic/Constants$Constant.escape$1:(Ljava/lang/String;)Ljava/lang/String;
Asciz	L;
String	L
Asciz	';
String	'
Asciz	temp15;
Asciz	hashCode;
NameAndType	hashCode:()I
Method	java/lang/Object.hashCode:()I
int	41;
int	17;
Asciz	copy;
Asciz	(Ljava/lang/Object;)Lscala/reflect/generic/Constants$Constant;;
Asciz	scala/runtime/ScalaRunTime$;
class	scala/runtime/ScalaRunTime$
Asciz	MODULE$;
Asciz	Lscala/runtime/ScalaRunTime$;;
NameAndType	MODULE$:Lscala/runtime/ScalaRunTime$;
Field	scala/runtime/ScalaRunTime$.MODULE$:Lscala/runtime/ScalaRunTime$;
Asciz	_toString;
Asciz	(Lscala/Product;)Ljava/lang/String;;
NameAndType	_toString:(Lscala/Product;)Ljava/lang/String;
Method	scala/runtime/ScalaRunTime$._toString:(Lscala/Product;)Ljava/lang/String;
Asciz	productPrefix;
Asciz	Constant;
String	Constant
Asciz	productArity;
Asciz	productElement;
Asciz	(I)Ljava/lang/Object;;
Asciz	java/lang/IndexOutOfBoundsException;
class	java/lang/IndexOutOfBoundsException
Method	java/lang/IndexOutOfBoundsException."<init>":(Ljava/lang/String;)V
Asciz	productElementName;
Asciz	(I)Ljava/lang/String;;
String	value
Asciz	canEqual;
NameAndType	$outer:Lscala/reflect/generic/Universe;
Field	scala/reflect/generic/Constants$Constant.$outer:Lscala/reflect/generic/Universe;
Method	scala/collection/mutable/StringBuilder."<init>":()V
Asciz	scala/Predef$;
class	scala/Predef$
Asciz	Lscala/Predef$;;
NameAndType	MODULE$:Lscala/Predef$;
Field	scala/Predef$.MODULE$:Lscala/Predef$;
Asciz	augmentString;
Asciz	(Ljava/lang/String;)Lscala/collection/immutable/StringOps;;
NameAndType	augmentString:(Ljava/lang/String;)Lscala/collection/immutable/StringOps;
Method	scala/Predef$.augmentString:(Ljava/lang/String;)Lscala/collection/immutable/StringOps;
Asciz	scala/collection/IndexedSeqLike;
class	scala/collection/IndexedSeqLike
Asciz	iterator;
NameAndType	iterator:()Lscala/collection/Iterator;
InterfaceMethod	scala/collection/IndexedSeqLike.iterator:()Lscala/collection/Iterator;
Asciz	scala/reflect/generic/Constants$Constant$$anonfun$escape$1$1;
class	scala/reflect/generic/Constants$Constant$$anonfun$escape$1$1
Asciz	(Lscala/reflect/generic/Constants$Constant;Lscala/collection/mutable/StringBuilder;)V;
NameAndType	"<init>":(Lscala/reflect/generic/Constants$Constant;Lscala/collection/mutable/StringBuilder;)V
Method	scala/reflect/generic/Constants$Constant$$anonfun$escape$1$1."<init>":(Lscala/reflect/generic/Constants$Constant;Lscala/collection/mutable/StringBuilder;)V
Asciz	scala/collection/Iterator;
class	scala/collection/Iterator
Asciz	foreach;
Asciz	(Lscala/Function1;)V;
NameAndType	foreach:(Lscala/Function1;)V
InterfaceMethod	scala/collection/Iterator.foreach:(Lscala/Function1;)V
Method	scala/collection/mutable/StringBuilder.toString:()Ljava/lang/String;
Asciz	text;
Asciz	Ljava/lang/String;;
Asciz	buf$1;
Asciz	Lscala/collection/mutable/StringBuilder;;
Asciz	java/lang/NullPointerException;
class	java/lang/NullPointerException
Method	java/lang/NullPointerException."<init>":()V
Method	java/lang/Object."<init>":()V
Asciz	$init$;
Asciz	(Lscala/Product;)V;
NameAndType	$init$:(Lscala/Product;)V
Method	scala/Product$class.$init$:(Lscala/Product;)V
Asciz	scala/runtime/BoxedUnit;
class	scala/runtime/BoxedUnit
Asciz	java/lang/Boolean;
class	java/lang/Boolean
Asciz	java/lang/Byte;
class	java/lang/Byte
Asciz	java/lang/Short;
class	java/lang/Short
Asciz	java/lang/Integer;
class	java/lang/Integer
Asciz	java/lang/Long;
class	java/lang/Long
Asciz	java/lang/String;
class	java/lang/String
int	10;
int	13;
int	11;
Asciz	bad constant value: ;
String	bad constant value: 
Asciz	Scala;
Asciz	InnerClasses;
Asciz	scala/reflect/generic/Types;
class	scala/reflect/generic/Types
Asciz	AbsType;
Asciz	scala/reflect/generic/Symbols;
class	scala/reflect/generic/Symbols
Asciz	AbsSymbol;
Asciz	scala/reflect/generic/Constants;
class	scala/reflect/generic/Constants
Asciz	AbsDefinitions;
Asciz	$anonfun$escape$1$1;
Asciz	scala/ScalaObject;
class	scala/ScalaObject
Asciz	scala/Product;
class	scala/Product
Asciz	java/io/Serializable;
class	java/io/Serializable

{
public final scala.reflect.generic.Universe $outer;
  Signature: Lscala/reflect/generic/Universe;

private final int tag;
  Signature: I

private final java.lang.Object value;
  Signature: Ljava/lang/Object;

public scala.collection.Iterator productIterator();
  Signature: ()Lscala/collection/Iterator;
  Code:
   Stack=1, Locals=1, Args_size=1
	aload_0
	invokestatic	Method scala/Product$class.productIterator:(Lscala/Product;)Lscala/collection/Iterator;
	areturn
  Labels:

public scala.collection.Iterator productElements();
  Signature: ()Lscala/collection/Iterator;
  Code:
   Stack=1, Locals=1, Args_size=1
	aload_0
	invokestatic	Method scala/Product$class.productElements:(Lscala/Product;)Lscala/collection/Iterator;
	areturn
  Labels:
  Deprecated: true

public java.lang.Object copy$default$1();
  Signature: ()Ljava/lang/Object;
  Code:
   Stack=1, Locals=1, Args_size=1
	aload_0
	invokevirtual	Method value:()Ljava/lang/Object;
	areturn
  Labels:

public java.lang.Object value();
  Signature: ()Ljava/lang/Object;
  Code:
   Stack=1, Locals=1, Args_size=1
	aload_0
	getfield	Field value:Ljava/lang/Object;
	areturn
  Labels:

public int tag();
  Signature: ()I
  Code:
   Stack=1, Locals=1, Args_size=1
	aload_0
	getfield	Field tag:I
	ireturn
  Labels:

public boolean isNumeric();
  Signature: ()Z
  Code:
   Stack=2, Locals=1, Args_size=1
	iconst_3
	aload_0
	invokevirtual	Method tag:()I
	if_icmpgt	l1 // iconst_0
	aload_0
	invokevirtual	Method tag:()I
	ldc	int 9
	if_icmpgt	l1 // iconst_0
	iconst_1
	goto	l2 // ireturn
l1	iconst_0
l2	ireturn
  Labels:
   	l1 = 21 // iconst_0
   	l2 = 22 // ireturn

public scala.reflect.generic.Types$AbsType tpe();
  Signature: ()Lscala/reflect/generic/Types$AbsType;
  Code:
   Stack=3, Locals=2, Args_size=1
	aload_0
	invokevirtual	Method tag:()I
	istore_1
	iload_1
	tableswitch{ //1 to 13
		1: 305;
		2: 287;
		3: 269;
		4: 251;
		5: 233;
		6: 215;
		7: 197;
		8: 179;
		9: 161;
		10: 143;
		11: 125;
		12: 103;
		13: 87;
		default: 72 }
	new	class scala/MatchError
	dup
	iload_1
	invokestatic	Method scala/runtime/BoxesRunTime.boxToInteger:(I)Ljava/lang/Integer;
	invokevirtual	Method java/lang/Object.toString:()Ljava/lang/String;
	invokespecial	Method scala/MatchError."<init>":(Ljava/lang/String;)V
	athrow
	aload_0
	invokevirtual	Method symbolValue:()Lscala/reflect/generic/Symbols$AbsSymbol;
	invokevirtual	Method scala/reflect/generic/Symbols$AbsSymbol.owner:()Lscala/reflect/generic/Symbols$AbsSymbol;
	invokevirtual	Method scala/reflect/generic/Symbols$AbsSymbol.linkedClassOfClass:()Lscala/reflect/generic/Symbols$AbsSymbol;
	invokevirtual	Method scala/reflect/generic/Symbols$AbsSymbol.tpe:()Lscala/reflect/generic/Types$AbsType;
	goto	l1 // areturn
	aload_0
	invokevirtual	Method scala$reflect$generic$Constants$Constant$$$outer:()Lscala/reflect/generic/Universe;
	invokeinterface	InterfaceMethod scala/reflect/generic/StandardDefinitions.definitions:()Lscala/reflect/generic/StandardDefinitions$AbsDefinitions;
	aload_0
	invokevirtual	Method value:()Ljava/lang/Object;
	checkcast	class scala/reflect/generic/Types$AbsType
	invokevirtual	Method scala/reflect/generic/StandardDefinitions$AbsDefinitions.ClassType:(Lscala/reflect/generic/Types$AbsType;)Lscala/reflect/generic/Types$AbsType;
	goto	l1 // areturn
	aload_0
	invokevirtual	Method scala$reflect$generic$Constants$Constant$$$outer:()Lscala/reflect/generic/Universe;
	invokeinterface	InterfaceMethod scala/reflect/generic/StandardDefinitions.definitions:()Lscala/reflect/generic/StandardDefinitions$AbsDefinitions;
	invokevirtual	Method scala/reflect/generic/StandardDefinitions$AbsDefinitions.NullClass:()Lscala/reflect/generic/Symbols$AbsSymbol;
	invokevirtual	Method scala/reflect/generic/Symbols$AbsSymbol.tpe:()Lscala/reflect/generic/Types$AbsType;
	goto	l1 // areturn
	aload_0
	invokevirtual	Method scala$reflect$generic$Constants$Constant$$$outer:()Lscala/reflect/generic/Universe;
	invokeinterface	InterfaceMethod scala/reflect/generic/StandardDefinitions.definitions:()Lscala/reflect/generic/StandardDefinitions$AbsDefinitions;
	invokevirtual	Method scala/reflect/generic/StandardDefinitions$AbsDefinitions.StringClass:()Lscala/reflect/generic/Symbols$AbsSymbol;
	invokevirtual	Method scala/reflect/generic/Symbols$AbsSymbol.tpe:()Lscala/reflect/generic/Types$AbsType;
	goto	l1 // areturn
	aload_0
	invokevirtual	Method scala$reflect$generic$Constants$Constant$$$outer:()Lscala/reflect/generic/Universe;
	invokeinterface	InterfaceMethod scala/reflect/generic/StandardDefinitions.definitions:()Lscala/reflect/generic/StandardDefinitions$AbsDefinitions;
	invokevirtual	Method scala/reflect/generic/StandardDefinitions$AbsDefinitions.DoubleClass:()Lscala/reflect/generic/Symbols$AbsSymbol;
	invokevirtual	Method scala/reflect/generic/Symbols$AbsSymbol.tpe:()Lscala/reflect/generic/Types$AbsType;
	goto	l1 // areturn
	aload_0
	invokevirtual	Method scala$reflect$generic$Constants$Constant$$$outer:()Lscala/reflect/generic/Universe;
	invokeinterface	InterfaceMethod scala/reflect/generic/StandardDefinitions.definitions:()Lscala/reflect/generic/StandardDefinitions$AbsDefinitions;
	invokevirtual	Method scala/reflect/generic/StandardDefinitions$AbsDefinitions.FloatClass:()Lscala/reflect/generic/Symbols$AbsSymbol;
	invokevirtual	Method scala/reflect/generic/Symbols$AbsSymbol.tpe:()Lscala/reflect/generic/Types$AbsType;
	goto	l1 // areturn
	aload_0
	invokevirtual	Method scala$reflect$generic$Constants$Constant$$$outer:()Lscala/reflect/generic/Universe;
	invokeinterface	InterfaceMethod scala/reflect/generic/StandardDefinitions.definitions:()Lscala/reflect/generic/StandardDefinitions$AbsDefinitions;
	invokevirtual	Method scala/reflect/generic/StandardDefinitions$AbsDefinitions.LongClass:()Lscala/reflect/generic/Symbols$AbsSymbol;
	invokevirtual	Method scala/reflect/generic/Symbols$AbsSymbol.tpe:()Lscala/reflect/generic/Types$AbsType;
	goto	l1 // areturn
	aload_0
	invokevirtual	Method scala$reflect$generic$Constants$Constant$$$outer:()Lscala/reflect/generic/Universe;
	invokeinterface	InterfaceMethod scala/reflect/generic/StandardDefinitions.definitions:()Lscala/reflect/generic/StandardDefinitions$AbsDefinitions;
	invokevirtual	Method scala/reflect/generic/StandardDefinitions$AbsDefinitions.IntClass:()Lscala/reflect/generic/Symbols$AbsSymbol;
	invokevirtual	Method scala/reflect/generic/Symbols$AbsSymbol.tpe:()Lscala/reflect/generic/Types$AbsType;
	goto	l1 // areturn
	aload_0
	invokevirtual	Method scala$reflect$generic$Constants$Constant$$$outer:()Lscala/reflect/generic/Universe;
	invokeinterface	InterfaceMethod scala/reflect/generic/StandardDefinitions.definitions:()Lscala/reflect/generic/StandardDefinitions$AbsDefinitions;
	invokevirtual	Method scala/reflect/generic/StandardDefinitions$AbsDefinitions.CharClass:()Lscala/reflect/generic/Symbols$AbsSymbol;
	invokevirtual	Method scala/reflect/generic/Symbols$AbsSymbol.tpe:()Lscala/reflect/generic/Types$AbsType;
	goto	l1 // areturn
	aload_0
	invokevirtual	Method scala$reflect$generic$Constants$Constant$$$outer:()Lscala/reflect/generic/Universe;
	invokeinterface	InterfaceMethod scala/reflect/generic/StandardDefinitions.definitions:()Lscala/reflect/generic/StandardDefinitions$AbsDefinitions;
	invokevirtual	Method scala/reflect/generic/StandardDefinitions$AbsDefinitions.ShortClass:()Lscala/reflect/generic/Symbols$AbsSymbol;
	invokevirtual	Method scala/reflect/generic/Symbols$AbsSymbol.tpe:()Lscala/reflect/generic/Types$AbsType;
	goto	l1 // areturn
	aload_0
	invokevirtual	Method scala$reflect$generic$Constants$Constant$$$outer:()Lscala/reflect/generic/Universe;
	invokeinterface	InterfaceMethod scala/reflect/generic/StandardDefinitions.definitions:()Lscala/reflect/generic/StandardDefinitions$AbsDefinitions;
	invokevirtual	Method scala/reflect/generic/StandardDefinitions$AbsDefinitions.ByteClass:()Lscala/reflect/generic/Symbols$AbsSymbol;
	invokevirtual	Method scala/reflect/generic/Symbols$AbsSymbol.tpe:()Lscala/reflect/generic/Types$AbsType;
	goto	l1 // areturn
	aload_0
	invokevirtual	Method scala$reflect$generic$Constants$Constant$$$outer:()Lscala/reflect/generic/Universe;
	invokeinterface	InterfaceMethod scala/reflect/generic/StandardDefinitions.definitions:()Lscala/reflect/generic/StandardDefinitions$AbsDefinitions;
	invokevirtual	Method scala/reflect/generic/StandardDefinitions$AbsDefinitions.BooleanClass:()Lscala/reflect/generic/Symbols$AbsSymbol;
	invokevirtual	Method scala/reflect/generic/Symbols$AbsSymbol.tpe:()Lscala/reflect/generic/Types$AbsType;
	goto	l1 // areturn
	aload_0
	invokevirtual	Method scala$reflect$generic$Constants$Constant$$$outer:()Lscala/reflect/generic/Universe;
	invokeinterface	InterfaceMethod scala/reflect/generic/StandardDefinitions.definitions:()Lscala/reflect/generic/StandardDefinitions$AbsDefinitions;
	invokevirtual	Method scala/reflect/generic/StandardDefinitions$AbsDefinitions.UnitClass:()Lscala/reflect/generic/Symbols$AbsSymbol;
	invokevirtual	Method scala/reflect/generic/Symbols$AbsSymbol.tpe:()Lscala/reflect/generic/Types$AbsType;
l1	areturn
  Labels:
   	l1 = 320 // areturn
  LocalVariableTable: 
   Start  Length  Slot  Name   Signature
   0      321      0    this       Lscala/reflect/generic/Constants$Constant;
   5      316      1    temp1       I


public boolean equals(java.lang.Object);
  Signature: (Ljava/lang/Object;)Z
  Code:
   Stack=2, Locals=5, Args_size=2
	aload_1
	instanceof	class scala/reflect/generic/Constants$Constant
	ifeq	l1 // iconst_0
	aload_1
	checkcast	class scala/reflect/generic/Constants$Constant
	invokevirtual	Method scala$reflect$generic$Constants$Constant$$$outer:()Lscala/reflect/generic/Universe;
	aload_0
	invokevirtual	Method scala$reflect$generic$Constants$Constant$$$outer:()Lscala/reflect/generic/Universe;
	if_acmpne	l1 // iconst_0
	aload_1
	checkcast	class scala/reflect/generic/Constants$Constant
	astore	4
	aload_0
	invokevirtual	Method tag:()I
	aload	4
	invokevirtual	Method tag:()I
	if_icmpne	l2 // iconst_0
	aload_0
	invokevirtual	Method value:()Ljava/lang/Object;
	aload	4
	invokevirtual	Method value:()Ljava/lang/Object;
	astore_3
	astore_2
	aload_2
	aload_3
	if_acmpne	l3 // aload_2
	iconst_1
	goto	l4 // ifne
l3	aload_2
	ifnonnull	l5 // aload_2
	iconst_0
	goto	l4 // ifne
l5	aload_2
	instanceof	class java/lang/Number
	ifne	l6 // aload_2
	aload_2
	instanceof	class java/lang/Character
	ifeq	l7 // aload_2
l6	aload_2
	aload_3
	invokestatic	Method scala/runtime/BoxesRunTime.equals2:(Ljava/lang/Object;Ljava/lang/Object;)Z
	goto	l4 // ifne
l7	aload_2
	aload_3
	invokevirtual	Method java/lang/Object.equals:(Ljava/lang/Object;)Z
l4	ifne	l8 // iconst_1
	aload_0
	invokevirtual	Method isNaN:()Z
	ifeq	l2 // iconst_0
	aload	4
	invokevirtual	Method isNaN:()Z
	ifeq	l2 // iconst_0
l8	iconst_1
	goto	l9 // ireturn
l2	iconst_0
	goto	l9 // ireturn
l1	iconst_0
l9	ireturn
  Labels:
   	l3 = 59 // aload_2
   	l5 = 67 // aload_2
   	l6 = 81 // aload_2
   	l7 = 89 // aload_2
   	l4 = 94 // ifne
   	l8 = 112 // iconst_1
   	l2 = 116 // iconst_0
   	l1 = 120 // iconst_0
   	l9 = 121 // ireturn
  LocalVariableTable: 
   Start  Length  Slot  Name   Signature
   0      122      0    this       Lscala/reflect/generic/Constants$Constant;
   0      122      1    other       Ljava/lang/Object;
   55      42      2    x0       Ljava/lang/Object;
   55      42      3    y0       Ljava/lang/Object;
   27      93      4    temp3       Lscala/reflect/generic/Constants$Constant;


public boolean isNaN();
  Signature: ()Z
  Code:
   Stack=2, Locals=5, Args_size=1
	aload_0
	invokevirtual	Method value:()Ljava/lang/Object;
	astore_2
	aload_2
	instanceof	class java/lang/Float
	ifeq	l1 // aload_2
	aload_2
	invokestatic	Method scala/runtime/BoxesRunTime.unboxToFloat:(Ljava/lang/Object;)F
	fstore_1
	fload_1
	invokestatic	Method java/lang/Float.valueOf:(F)Ljava/lang/Float;
	invokevirtual	Method java/lang/Float.isNaN:()Z
	goto	l2 // ireturn
l1	aload_2
	instanceof	class java/lang/Double
	ifeq	l3 // iconst_0
	aload_2
	invokestatic	Method scala/runtime/BoxesRunTime.unboxToDouble:(Ljava/lang/Object;)D
	dstore_3
	dload_3
	invokestatic	Method java/lang/Double.valueOf:(D)Ljava/lang/Double;
	invokevirtual	Method java/lang/Double.isNaN:()Z
	goto	l2 // ireturn
l3	iconst_0
l2	ireturn
  Labels:
   	l1 = 27 // aload_2
   	l3 = 49 // iconst_0
   	l2 = 50 // ireturn
  LocalVariableTable: 
   Start  Length  Slot  Name   Signature
   0      51      0    this       Lscala/reflect/generic/Constants$Constant;
   17      7      1    temp6       F
   5      46      2    temp5       Ljava/lang/Object;
   39      7      3    temp7       D


public boolean booleanValue();
  Signature: ()Z
  Code:
   Stack=4, Locals=1, Args_size=1
	aload_0
	invokevirtual	Method tag:()I
	iconst_2
	if_icmpne	l1 // new
	aload_0
	invokevirtual	Method value:()Ljava/lang/Object;
	invokestatic	Method scala/runtime/BoxesRunTime.unboxToBoolean:(Ljava/lang/Object;)Z
	ireturn
l1	new	class java/lang/Error
	dup
	new	class scala/collection/mutable/StringBuilder
	dup
	invokespecial	Method scala/collection/mutable/StringBuilder."<init>":()V
	ldc	String value 
	invokevirtual	Method scala/collection/mutable/StringBuilder.append:(Ljava/lang/Object;)Lscala/collection/mutable/StringBuilder;
	aload_0
	invokevirtual	Method value:()Ljava/lang/Object;
	invokevirtual	Method scala/collection/mutable/StringBuilder.append:(Ljava/lang/Object;)Lscala/collection/mutable/StringBuilder;
	ldc	String  is not a boolean
	invokevirtual	Method scala/collection/mutable/StringBuilder.append:(Ljava/lang/Object;)Lscala/collection/mutable/StringBuilder;
	invokevirtual	Method scala/collection/mutable/StringBuilder.toString:()Ljava/lang/String;
	invokespecial	Method java/lang/Error."<init>":(Ljava/lang/String;)V
	athrow
  Labels:
   	l1 = 16 // new

public byte byteValue();
  Signature: ()B
  Code:
   Stack=4, Locals=2, Args_size=1
	aload_0
	invokevirtual	Method tag:()I
	istore_1
	iload_1
	tableswitch{ //3 to 9
		3: 152;
		4: 141;
		5: 130;
		6: 119;
		7: 107;
		8: 95;
		9: 83;
		default: 48 }
	new	class java/lang/Error
	dup
	new	class scala/collection/mutable/StringBuilder
	dup
	invokespecial	Method scala/collection/mutable/StringBuilder."<init>":()V
	ldc	String value 
	invokevirtual	Method scala/collection/mutable/StringBuilder.append:(Ljava/lang/Object;)Lscala/collection/mutable/StringBuilder;
	aload_0
	invokevirtual	Method value:()Ljava/lang/Object;
	invokevirtual	Method scala/collection/mutable/StringBuilder.append:(Ljava/lang/Object;)Lscala/collection/mutable/StringBuilder;
	ldc	String  is not a Byte
	invokevirtual	Method scala/collection/mutable/StringBuilder.append:(Ljava/lang/Object;)Lscala/collection/mutable/StringBuilder;
	invokevirtual	Method scala/collection/mutable/StringBuilder.toString:()Ljava/lang/String;
	invokespecial	Method java/lang/Error."<init>":(Ljava/lang/String;)V
	athrow
	aload_0
	invokevirtual	Method value:()Ljava/lang/Object;
	invokestatic	Method scala/runtime/BoxesRunTime.unboxToDouble:(Ljava/lang/Object;)D
	d2i
	i2b
	goto	l1 // ireturn
	aload_0
	invokevirtual	Method value:()Ljava/lang/Object;
	invokestatic	Method scala/runtime/BoxesRunTime.unboxToFloat:(Ljava/lang/Object;)F
	f2i
	i2b
	goto	l1 // ireturn
	aload_0
	invokevirtual	Method value:()Ljava/lang/Object;
	invokestatic	Method scala/runtime/BoxesRunTime.unboxToLong:(Ljava/lang/Object;)J
	l2i
	i2b
	goto	l1 // ireturn
	aload_0
	invokevirtual	Method value:()Ljava/lang/Object;
	invokestatic	Method scala/runtime/BoxesRunTime.unboxToInt:(Ljava/lang/Object;)I
	i2b
	goto	l1 // ireturn
	aload_0
	invokevirtual	Method value:()Ljava/lang/Object;
	invokestatic	Method scala/runtime/BoxesRunTime.unboxToChar:(Ljava/lang/Object;)C
	i2b
	goto	l1 // ireturn
	aload_0
	invokevirtual	Method value:()Ljava/lang/Object;
	invokestatic	Method scala/runtime/BoxesRunTime.unboxToShort:(Ljava/lang/Object;)S
	i2b
	goto	l1 // ireturn
	aload_0
	invokevirtual	Method value:()Ljava/lang/Object;
	invokestatic	Method scala/runtime/BoxesRunTime.unboxToByte:(Ljava/lang/Object;)B
l1	ireturn
  Labels:
   	l1 = 159 // ireturn
  LocalVariableTable: 
   Start  Length  Slot  Name   Signature
   0      160      0    this       Lscala/reflect/generic/Constants$Constant;
   5      155      1    temp8       I


public short shortValue();
  Signature: ()S
  Code:
   Stack=4, Locals=2, Args_size=1
	aload_0
	invokevirtual	Method tag:()I
	istore_1
	iload_1
	tableswitch{ //3 to 9
		3: 151;
		4: 141;
		5: 130;
		6: 119;
		7: 107;
		8: 95;
		9: 83;
		default: 48 }
	new	class java/lang/Error
	dup
	new	class scala/collection/mutable/StringBuilder
	dup
	invokespecial	Method scala/collection/mutable/StringBuilder."<init>":()V
	ldc	String value 
	invokevirtual	Method scala/collection/mutable/StringBuilder.append:(Ljava/lang/Object;)Lscala/collection/mutable/StringBuilder;
	aload_0
	invokevirtual	Method value:()Ljava/lang/Object;
	invokevirtual	Method scala/collection/mutable/StringBuilder.append:(Ljava/lang/Object;)Lscala/collection/mutable/StringBuilder;
	ldc	String  is not a Short
	invokevirtual	Method scala/collection/mutable/StringBuilder.append:(Ljava/lang/Object;)Lscala/collection/mutable/StringBuilder;
	invokevirtual	Method scala/collection/mutable/StringBuilder.toString:()Ljava/lang/String;
	invokespecial	Method java/lang/Error."<init>":(Ljava/lang/String;)V
	athrow
	aload_0
	invokevirtual	Method value:()Ljava/lang/Object;
	invokestatic	Method scala/runtime/BoxesRunTime.unboxToDouble:(Ljava/lang/Object;)D
	d2i
	i2s
	goto	l1 // ireturn
	aload_0
	invokevirtual	Method value:()Ljava/lang/Object;
	invokestatic	Method scala/runtime/BoxesRunTime.unboxToFloat:(Ljava/lang/Object;)F
	f2i
	i2s
	goto	l1 // ireturn
	aload_0
	invokevirtual	Method value:()Ljava/lang/Object;
	invokestatic	Method scala/runtime/BoxesRunTime.unboxToLong:(Ljava/lang/Object;)J
	l2i
	i2s
	goto	l1 // ireturn
	aload_0
	invokevirtual	Method value:()Ljava/lang/Object;
	invokestatic	Method scala/runtime/BoxesRunTime.unboxToInt:(Ljava/lang/Object;)I
	i2s
	goto	l1 // ireturn
	aload_0
	invokevirtual	Method value:()Ljava/lang/Object;
	invokestatic	Method scala/runtime/BoxesRunTime.unboxToChar:(Ljava/lang/Object;)C
	i2s
	goto	l1 // ireturn
	aload_0
	invokevirtual	Method value:()Ljava/lang/Object;
	invokestatic	Method scala/runtime/BoxesRunTime.unboxToShort:(Ljava/lang/Object;)S
	goto	l1 // ireturn
	aload_0
	invokevirtual	Method value:()Ljava/lang/Object;
	invokestatic	Method scala/runtime/BoxesRunTime.unboxToByte:(Ljava/lang/Object;)B
l1	ireturn
  Labels:
   	l1 = 158 // ireturn
  LocalVariableTable: 
   Start  Length  Slot  Name   Signature
   0      159      0    this       Lscala/reflect/generic/Constants$Constant;
   5      154      1    temp9       I


public char charValue();
  Signature: ()C
  Code:
   Stack=4, Locals=2, Args_size=1
	aload_0
	invokevirtual	Method tag:()I
	istore_1
	iload_1
	tableswitch{ //3 to 9
		3: 151;
		4: 140;
		5: 130;
		6: 119;
		7: 107;
		8: 95;
		9: 83;
		default: 48 }
	new	class java/lang/Error
	dup
	new	class scala/collection/mutable/StringBuilder
	dup
	invokespecial	Method scala/collection/mutable/StringBuilder."<init>":()V
	ldc	String value 
	invokevirtual	Method scala/collection/mutable/StringBuilder.append:(Ljava/lang/Object;)Lscala/collection/mutable/StringBuilder;
	aload_0
	invokevirtual	Method value:()Ljava/lang/Object;
	invokevirtual	Method scala/collection/mutable/StringBuilder.append:(Ljava/lang/Object;)Lscala/collection/mutable/StringBuilder;
	ldc	String  is not a Char
	invokevirtual	Method scala/collection/mutable/StringBuilder.append:(Ljava/lang/Object;)Lscala/collection/mutable/StringBuilder;
	invokevirtual	Method scala/collection/mutable/StringBuilder.toString:()Ljava/lang/String;
	invokespecial	Method java/lang/Error."<init>":(Ljava/lang/String;)V
	athrow
	aload_0
	invokevirtual	Method value:()Ljava/lang/Object;
	invokestatic	Method scala/runtime/BoxesRunTime.unboxToDouble:(Ljava/lang/Object;)D
	d2i
	i2c
	goto	l1 // ireturn
	aload_0
	invokevirtual	Method value:()Ljava/lang/Object;
	invokestatic	Method scala/runtime/BoxesRunTime.unboxToFloat:(Ljava/lang/Object;)F
	f2i
	i2c
	goto	l1 // ireturn
	aload_0
	invokevirtual	Method value:()Ljava/lang/Object;
	invokestatic	Method scala/runtime/BoxesRunTime.unboxToLong:(Ljava/lang/Object;)J
	l2i
	i2c
	goto	l1 // ireturn
	aload_0
	invokevirtual	Method value:()Ljava/lang/Object;
	invokestatic	Method scala/runtime/BoxesRunTime.unboxToInt:(Ljava/lang/Object;)I
	i2c
	goto	l1 // ireturn
	aload_0
	invokevirtual	Method value:()Ljava/lang/Object;
	invokestatic	Method scala/runtime/BoxesRunTime.unboxToChar:(Ljava/lang/Object;)C
	goto	l1 // ireturn
	aload_0
	invokevirtual	Method value:()Ljava/lang/Object;
	invokestatic	Method scala/runtime/BoxesRunTime.unboxToShort:(Ljava/lang/Object;)S
	i2c
	goto	l1 // ireturn
	aload_0
	invokevirtual	Method value:()Ljava/lang/Object;
	invokestatic	Method scala/runtime/BoxesRunTime.unboxToByte:(Ljava/lang/Object;)B
	i2c
l1	ireturn
  Labels:
   	l1 = 159 // ireturn
  LocalVariableTable: 
   Start  Length  Slot  Name   Signature
   0      160      0    this       Lscala/reflect/generic/Constants$Constant;
   5      155      1    temp10       I


public int intValue();
  Signature: ()I
  Code:
   Stack=4, Locals=2, Args_size=1
	aload_0
	invokevirtual	Method tag:()I
	istore_1
	iload_1
	tableswitch{ //3 to 9
		3: 146;
		4: 136;
		5: 126;
		6: 116;
		7: 105;
		8: 94;
		9: 83;
		default: 48 }
	new	class java/lang/Error
	dup
	new	class scala/collection/mutable/StringBuilder
	dup
	invokespecial	Method scala/collection/mutable/StringBuilder."<init>":()V
	ldc	String value 
	invokevirtual	Method scala/collection/mutable/StringBuilder.append:(Ljava/lang/Object;)Lscala/collection/mutable/StringBuilder;
	aload_0
	invokevirtual	Method value:()Ljava/lang/Object;
	invokevirtual	Method scala/collection/mutable/StringBuilder.append:(Ljava/lang/Object;)Lscala/collection/mutable/StringBuilder;
	ldc	String  is not an Int
	invokevirtual	Method scala/collection/mutable/StringBuilder.append:(Ljava/lang/Object;)Lscala/collection/mutable/StringBuilder;
	invokevirtual	Method scala/collection/mutable/StringBuilder.toString:()Ljava/lang/String;
	invokespecial	Method java/lang/Error."<init>":(Ljava/lang/String;)V
	athrow
	aload_0
	invokevirtual	Method value:()Ljava/lang/Object;
	invokestatic	Method scala/runtime/BoxesRunTime.unboxToDouble:(Ljava/lang/Object;)D
	d2i
	goto	l1 // ireturn
	aload_0
	invokevirtual	Method value:()Ljava/lang/Object;
	invokestatic	Method scala/runtime/BoxesRunTime.unboxToFloat:(Ljava/lang/Object;)F
	f2i
	goto	l1 // ireturn
	aload_0
	invokevirtual	Method value:()Ljava/lang/Object;
	invokestatic	Method scala/runtime/BoxesRunTime.unboxToLong:(Ljava/lang/Object;)J
	l2i
	goto	l1 // ireturn
	aload_0
	invokevirtual	Method value:()Ljava/lang/Object;
	invokestatic	Method scala/runtime/BoxesRunTime.unboxToInt:(Ljava/lang/Object;)I
	goto	l1 // ireturn
	aload_0
	invokevirtual	Method value:()Ljava/lang/Object;
	invokestatic	Method scala/runtime/BoxesRunTime.unboxToChar:(Ljava/lang/Object;)C
	goto	l1 // ireturn
	aload_0
	invokevirtual	Method value:()Ljava/lang/Object;
	invokestatic	Method scala/runtime/BoxesRunTime.unboxToShort:(Ljava/lang/Object;)S
	goto	l1 // ireturn
	aload_0
	invokevirtual	Method value:()Ljava/lang/Object;
	invokestatic	Method scala/runtime/BoxesRunTime.unboxToByte:(Ljava/lang/Object;)B
l1	ireturn
  Labels:
   	l1 = 153 // ireturn
  LocalVariableTable: 
   Start  Length  Slot  Name   Signature
   0      154      0    this       Lscala/reflect/generic/Constants$Constant;
   5      149      1    temp11       I


public long longValue();
  Signature: ()J
  Code:
   Stack=4, Locals=2, Args_size=1
	aload_0
	invokevirtual	Method tag:()I
	istore_1
	iload_1
	tableswitch{ //3 to 9
		3: 148;
		4: 137;
		5: 126;
		6: 115;
		7: 105;
		8: 94;
		9: 83;
		default: 48 }
	new	class java/lang/Error
	dup
	new	class scala/collection/mutable/StringBuilder
	dup
	invokespecial	Method scala/collection/mutable/StringBuilder."<init>":()V
	ldc	String value 
	invokevirtual	Method scala/collection/mutable/StringBuilder.append:(Ljava/lang/Object;)Lscala/collection/mutable/StringBuilder;
	aload_0
	invokevirtual	Method value:()Ljava/lang/Object;
	invokevirtual	Method scala/collection/mutable/StringBuilder.append:(Ljava/lang/Object;)Lscala/collection/mutable/StringBuilder;
	ldc	String  is not a Long
	invokevirtual	Method scala/collection/mutable/StringBuilder.append:(Ljava/lang/Object;)Lscala/collection/mutable/StringBuilder;
	invokevirtual	Method scala/collection/mutable/StringBuilder.toString:()Ljava/lang/String;
	invokespecial	Method java/lang/Error."<init>":(Ljava/lang/String;)V
	athrow
	aload_0
	invokevirtual	Method value:()Ljava/lang/Object;
	invokestatic	Method scala/runtime/BoxesRunTime.unboxToDouble:(Ljava/lang/Object;)D
	d2l
	goto	l1 // lreturn
	aload_0
	invokevirtual	Method value:()Ljava/lang/Object;
	invokestatic	Method scala/runtime/BoxesRunTime.unboxToFloat:(Ljava/lang/Object;)F
	f2l
	goto	l1 // lreturn
	aload_0
	invokevirtual	Method value:()Ljava/lang/Object;
	invokestatic	Method scala/runtime/BoxesRunTime.unboxToLong:(Ljava/lang/Object;)J
	goto	l1 // lreturn
	aload_0
	invokevirtual	Method value:()Ljava/lang/Object;
	invokestatic	Method scala/runtime/BoxesRunTime.unboxToInt:(Ljava/lang/Object;)I
	i2l
	goto	l1 // lreturn
	aload_0
	invokevirtual	Method value:()Ljava/lang/Object;
	invokestatic	Method scala/runtime/BoxesRunTime.unboxToChar:(Ljava/lang/Object;)C
	i2l
	goto	l1 // lreturn
	aload_0
	invokevirtual	Method value:()Ljava/lang/Object;
	invokestatic	Method scala/runtime/BoxesRunTime.unboxToShort:(Ljava/lang/Object;)S
	i2l
	goto	l1 // lreturn
	aload_0
	invokevirtual	Method value:()Ljava/lang/Object;
	invokestatic	Method scala/runtime/BoxesRunTime.unboxToByte:(Ljava/lang/Object;)B
	i2l
l1	lreturn
  Labels:
   	l1 = 156 // lreturn
  LocalVariableTable: 
   Start  Length  Slot  Name   Signature
   0      157      0    this       Lscala/reflect/generic/Constants$Constant;
   5      152      1    temp12       I


public float floatValue();
  Signature: ()F
  Code:
   Stack=4, Locals=2, Args_size=1
	aload_0
	invokevirtual	Method tag:()I
	istore_1
	iload_1
	tableswitch{ //3 to 9
		3: 148;
		4: 137;
		5: 126;
		6: 115;
		7: 104;
		8: 94;
		9: 83;
		default: 48 }
	new	class java/lang/Error
	dup
	new	class scala/collection/mutable/StringBuilder
	dup
	invokespecial	Method scala/collection/mutable/StringBuilder."<init>":()V
	ldc	String value 
	invokevirtual	Method scala/collection/mutable/StringBuilder.append:(Ljava/lang/Object;)Lscala/collection/mutable/StringBuilder;
	aload_0
	invokevirtual	Method value:()Ljava/lang/Object;
	invokevirtual	Method scala/collection/mutable/StringBuilder.append:(Ljava/lang/Object;)Lscala/collection/mutable/StringBuilder;
	ldc	String  is not a Float
	invokevirtual	Method scala/collection/mutable/StringBuilder.append:(Ljava/lang/Object;)Lscala/collection/mutable/StringBuilder;
	invokevirtual	Method scala/collection/mutable/StringBuilder.toString:()Ljava/lang/String;
	invokespecial	Method java/lang/Error."<init>":(Ljava/lang/String;)V
	athrow
	aload_0
	invokevirtual	Method value:()Ljava/lang/Object;
	invokestatic	Method scala/runtime/BoxesRunTime.unboxToDouble:(Ljava/lang/Object;)D
	d2f
	goto	l1 // freturn
	aload_0
	invokevirtual	Method value:()Ljava/lang/Object;
	invokestatic	Method scala/runtime/BoxesRunTime.unboxToFloat:(Ljava/lang/Object;)F
	goto	l1 // freturn
	aload_0
	invokevirtual	Method value:()Ljava/lang/Object;
	invokestatic	Method scala/runtime/BoxesRunTime.unboxToLong:(Ljava/lang/Object;)J
	l2f
	goto	l1 // freturn
	aload_0
	invokevirtual	Method value:()Ljava/lang/Object;
	invokestatic	Method scala/runtime/BoxesRunTime.unboxToInt:(Ljava/lang/Object;)I
	i2f
	goto	l1 // freturn
	aload_0
	invokevirtual	Method value:()Ljava/lang/Object;
	invokestatic	Method scala/runtime/BoxesRunTime.unboxToChar:(Ljava/lang/Object;)C
	i2f
	goto	l1 // freturn
	aload_0
	invokevirtual	Method value:()Ljava/lang/Object;
	invokestatic	Method scala/runtime/BoxesRunTime.unboxToShort:(Ljava/lang/Object;)S
	i2f
	goto	l1 // freturn
	aload_0
	invokevirtual	Method value:()Ljava/lang/Object;
	invokestatic	Method scala/runtime/BoxesRunTime.unboxToByte:(Ljava/lang/Object;)B
	i2f
l1	freturn
  Labels:
   	l1 = 156 // freturn
  LocalVariableTable: 
   Start  Length  Slot  Name   Signature
   0      157      0    this       Lscala/reflect/generic/Constants$Constant;
   5      152      1    temp13       I


public double doubleValue();
  Signature: ()D
  Code:
   Stack=4, Locals=2, Args_size=1
	aload_0
	invokevirtual	Method tag:()I
	istore_1
	iload_1
	tableswitch{ //3 to 9
		3: 148;
		4: 137;
		5: 126;
		6: 115;
		7: 104;
		8: 93;
		9: 83;
		default: 48 }
	new	class java/lang/Error
	dup
	new	class scala/collection/mutable/StringBuilder
	dup
	invokespecial	Method scala/collection/mutable/StringBuilder."<init>":()V
	ldc	String value 
	invokevirtual	Method scala/collection/mutable/StringBuilder.append:(Ljava/lang/Object;)Lscala/collection/mutable/StringBuilder;
	aload_0
	invokevirtual	Method value:()Ljava/lang/Object;
	invokevirtual	Method scala/collection/mutable/StringBuilder.append:(Ljava/lang/Object;)Lscala/collection/mutable/StringBuilder;
	ldc	String  is not a Double
	invokevirtual	Method scala/collection/mutable/StringBuilder.append:(Ljava/lang/Object;)Lscala/collection/mutable/StringBuilder;
	invokevirtual	Method scala/collection/mutable/StringBuilder.toString:()Ljava/lang/String;
	invokespecial	Method java/lang/Error."<init>":(Ljava/lang/String;)V
	athrow
	aload_0
	invokevirtual	Method value:()Ljava/lang/Object;
	invokestatic	Method scala/runtime/BoxesRunTime.unboxToDouble:(Ljava/lang/Object;)D
	goto	l1 // dreturn
	aload_0
	invokevirtual	Method value:()Ljava/lang/Object;
	invokestatic	Method scala/runtime/BoxesRunTime.unboxToFloat:(Ljava/lang/Object;)F
	f2d
	goto	l1 // dreturn
	aload_0
	invokevirtual	Method value:()Ljava/lang/Object;
	invokestatic	Method scala/runtime/BoxesRunTime.unboxToLong:(Ljava/lang/Object;)J
	l2d
	goto	l1 // dreturn
	aload_0
	invokevirtual	Method value:()Ljava/lang/Object;
	invokestatic	Method scala/runtime/BoxesRunTime.unboxToInt:(Ljava/lang/Object;)I
	i2d
	goto	l1 // dreturn
	aload_0
	invokevirtual	Method value:()Ljava/lang/Object;
	invokestatic	Method scala/runtime/BoxesRunTime.unboxToChar:(Ljava/lang/Object;)C
	i2d
	goto	l1 // dreturn
	aload_0
	invokevirtual	Method value:()Ljava/lang/Object;
	invokestatic	Method scala/runtime/BoxesRunTime.unboxToShort:(Ljava/lang/Object;)S
	i2d
	goto	l1 // dreturn
	aload_0
	invokevirtual	Method value:()Ljava/lang/Object;
	invokestatic	Method scala/runtime/BoxesRunTime.unboxToByte:(Ljava/lang/Object;)B
	i2d
l1	dreturn
  Labels:
   	l1 = 156 // dreturn
  LocalVariableTable: 
   Start  Length  Slot  Name   Signature
   0      157      0    this       Lscala/reflect/generic/Constants$Constant;
   5      152      1    temp14       I


public scala.reflect.generic.Constants$Constant convertTo(scala.reflect.generic.Types$AbsType);
  Signature: (Lscala/reflect/generic/Types$AbsType;)Lscala/reflect/generic/Constants$Constant;
  Code:
   Stack=5, Locals=20, Args_size=2
	aload_1
	invokevirtual	Method scala/reflect/generic/Types$AbsType.typeSymbol:()Lscala/reflect/generic/Symbols$AbsSymbol;
	astore_2
	aload_2
	aload_0
	invokevirtual	Method tpe:()Lscala/reflect/generic/Types$AbsType;
	invokevirtual	Method scala/reflect/generic/Types$AbsType.typeSymbol:()Lscala/reflect/generic/Symbols$AbsSymbol;
	astore_3
	dup
	ifnonnull	l1 // aload_3
	pop
	aload_3
	ifnull	l2 // aload_0
	goto	l3 // aload_2
l1	aload_3
	invokevirtual	Method java/lang/Object.equals:(Ljava/lang/Object;)Z
	ifeq	l3 // aload_2
l2	aload_0
	goto	l4 // areturn
l3	aload_2
	aload_0
	invokevirtual	Method scala$reflect$generic$Constants$Constant$$$outer:()Lscala/reflect/generic/Universe;
	invokeinterface	InterfaceMethod scala/reflect/generic/StandardDefinitions.definitions:()Lscala/reflect/generic/StandardDefinitions$AbsDefinitions;
	invokevirtual	Method scala/reflect/generic/StandardDefinitions$AbsDefinitions.ByteClass:()Lscala/reflect/generic/Symbols$AbsSymbol;
	astore	4
	dup
	ifnonnull	l5 // aload
	pop
	aload	4
	ifnull	l6 // iconst_3
	goto	l7 // aload_2
l5	aload	4
	invokevirtual	Method java/lang/Object.equals:(Ljava/lang/Object;)Z
	ifeq	l7 // aload_2
l6	iconst_3
	aload_0
	invokevirtual	Method tag:()I
	if_icmpgt	l7 // aload_2
	aload_0
	invokevirtual	Method tag:()I
	ldc	int 6
	if_icmpgt	l7 // aload_2
	ldc	int -128
	aload_0
	invokevirtual	Method intValue:()I
	if_icmpgt	l7 // aload_2
	aload_0
	invokevirtual	Method intValue:()I
	ldc_w	int 127
	if_icmpgt	l7 // aload_2
	new	class scala/reflect/generic/Constants$Constant
	dup
	aload_0
	invokevirtual	Method scala$reflect$generic$Constants$Constant$$$outer:()Lscala/reflect/generic/Universe;
	aload_0
	invokevirtual	Method byteValue:()B
	istore	5
	iload	5
	invokestatic	Method scala/runtime/BoxesRunTime.boxToByte:(B)Ljava/lang/Byte;
	invokespecial	Method "<init>":(Lscala/reflect/generic/Universe;Ljava/lang/Object;)V
	goto	l4 // areturn
l7	aload_2
	aload_0
	invokevirtual	Method scala$reflect$generic$Constants$Constant$$$outer:()Lscala/reflect/generic/Universe;
	invokeinterface	InterfaceMethod scala/reflect/generic/StandardDefinitions.definitions:()Lscala/reflect/generic/StandardDefinitions$AbsDefinitions;
	invokevirtual	Method scala/reflect/generic/StandardDefinitions$AbsDefinitions.ShortClass:()Lscala/reflect/generic/Symbols$AbsSymbol;
	astore	6
	dup
	ifnonnull	l8 // aload
	pop
	aload	6
	ifnull	l9 // iconst_3
	goto	l10 // aload_2
l8	aload	6
	invokevirtual	Method java/lang/Object.equals:(Ljava/lang/Object;)Z
	ifeq	l10 // aload_2
l9	iconst_3
	aload_0
	invokevirtual	Method tag:()I
	if_icmpgt	l10 // aload_2
	aload_0
	invokevirtual	Method tag:()I
	ldc	int 6
	if_icmpgt	l10 // aload_2
	ldc_w	int -32768
	aload_0
	invokevirtual	Method intValue:()I
	if_icmpgt	l10 // aload_2
	aload_0
	invokevirtual	Method intValue:()I
	ldc_w	int 32767
	if_icmpgt	l10 // aload_2
	new	class scala/reflect/generic/Constants$Constant
	dup
	aload_0
	invokevirtual	Method scala$reflect$generic$Constants$Constant$$$outer:()Lscala/reflect/generic/Universe;
	aload_0
	invokevirtual	Method shortValue:()S
	istore	7
	iload	7
	invokestatic	Method scala/runtime/BoxesRunTime.boxToShort:(S)Ljava/lang/Short;
	invokespecial	Method "<init>":(Lscala/reflect/generic/Universe;Ljava/lang/Object;)V
	goto	l4 // areturn
l10	aload_2
	aload_0
	invokevirtual	Method scala$reflect$generic$Constants$Constant$$$outer:()Lscala/reflect/generic/Universe;
	invokeinterface	InterfaceMethod scala/reflect/generic/StandardDefinitions.definitions:()Lscala/reflect/generic/StandardDefinitions$AbsDefinitions;
	invokevirtual	Method scala/reflect/generic/StandardDefinitions$AbsDefinitions.CharClass:()Lscala/reflect/generic/Symbols$AbsSymbol;
	astore	8
	dup
	ifnonnull	l11 // aload
	pop
	aload	8
	ifnull	l12 // iconst_3
	goto	l13 // aload_2
l11	aload	8
	invokevirtual	Method java/lang/Object.equals:(Ljava/lang/Object;)Z
	ifeq	l13 // aload_2
l12	iconst_3
	aload_0
	invokevirtual	Method tag:()I
	if_icmpgt	l13 // aload_2
	aload_0
	invokevirtual	Method tag:()I
	ldc	int 6
	if_icmpgt	l13 // aload_2
	iconst_0
	aload_0
	invokevirtual	Method intValue:()I
	if_icmpgt	l13 // aload_2
	aload_0
	invokevirtual	Method intValue:()I
	ldc_w	int 65635
	if_icmpgt	l13 // aload_2
	new	class scala/reflect/generic/Constants$Constant
	dup
	aload_0
	invokevirtual	Method scala$reflect$generic$Constants$Constant$$$outer:()Lscala/reflect/generic/Universe;
	aload_0
	invokevirtual	Method charValue:()C
	istore	9
	iload	9
	invokestatic	Method scala/runtime/BoxesRunTime.boxToCharacter:(C)Ljava/lang/Character;
	invokespecial	Method "<init>":(Lscala/reflect/generic/Universe;Ljava/lang/Object;)V
	goto	l4 // areturn
l13	aload_2
	aload_0
	invokevirtual	Method scala$reflect$generic$Constants$Constant$$$outer:()Lscala/reflect/generic/Universe;
	invokeinterface	InterfaceMethod scala/reflect/generic/StandardDefinitions.definitions:()Lscala/reflect/generic/StandardDefinitions$AbsDefinitions;
	invokevirtual	Method scala/reflect/generic/StandardDefinitions$AbsDefinitions.IntClass:()Lscala/reflect/generic/Symbols$AbsSymbol;
	astore	10
	dup
	ifnonnull	l14 // aload
	pop
	aload	10
	ifnull	l15 // iconst_3
	goto	l16 // aload_2
l14	aload	10
	invokevirtual	Method java/lang/Object.equals:(Ljava/lang/Object;)Z
	ifeq	l16 // aload_2
l15	iconst_3
	aload_0
	invokevirtual	Method tag:()I
	if_icmpgt	l16 // aload_2
	aload_0
	invokevirtual	Method tag:()I
	ldc	int 6
	if_icmpgt	l16 // aload_2
	new	class scala/reflect/generic/Constants$Constant
	dup
	aload_0
	invokevirtual	Method scala$reflect$generic$Constants$Constant$$$outer:()Lscala/reflect/generic/Universe;
	aload_0
	invokevirtual	Method intValue:()I
	istore	11
	iload	11
	invokestatic	Method scala/runtime/BoxesRunTime.boxToInteger:(I)Ljava/lang/Integer;
	invokespecial	Method "<init>":(Lscala/reflect/generic/Universe;Ljava/lang/Object;)V
	goto	l4 // areturn
l16	aload_2
	aload_0
	invokevirtual	Method scala$reflect$generic$Constants$Constant$$$outer:()Lscala/reflect/generic/Universe;
	invokeinterface	InterfaceMethod scala/reflect/generic/StandardDefinitions.definitions:()Lscala/reflect/generic/StandardDefinitions$AbsDefinitions;
	invokevirtual	Method scala/reflect/generic/StandardDefinitions$AbsDefinitions.LongClass:()Lscala/reflect/generic/Symbols$AbsSymbol;
	astore	12
	dup
	ifnonnull	l17 // aload
	pop
	aload	12
	ifnull	l18 // iconst_3
	goto	l19 // aload_2
l17	aload	12
	invokevirtual	Method java/lang/Object.equals:(Ljava/lang/Object;)Z
	ifeq	l19 // aload_2
l18	iconst_3
	aload_0
	invokevirtual	Method tag:()I
	if_icmpgt	l19 // aload_2
	aload_0
	invokevirtual	Method tag:()I
	ldc_w	int 7
	if_icmpgt	l19 // aload_2
	new	class scala/reflect/generic/Constants$Constant
	dup
	aload_0
	invokevirtual	Method scala$reflect$generic$Constants$Constant$$$outer:()Lscala/reflect/generic/Universe;
	aload_0
	invokevirtual	Method longValue:()J
	lstore	13
	lload	13
	invokestatic	Method scala/runtime/BoxesRunTime.boxToLong:(J)Ljava/lang/Long;
	invokespecial	Method "<init>":(Lscala/reflect/generic/Universe;Ljava/lang/Object;)V
	goto	l4 // areturn
l19	aload_2
	aload_0
	invokevirtual	Method scala$reflect$generic$Constants$Constant$$$outer:()Lscala/reflect/generic/Universe;
	invokeinterface	InterfaceMethod scala/reflect/generic/StandardDefinitions.definitions:()Lscala/reflect/generic/StandardDefinitions$AbsDefinitions;
	invokevirtual	Method scala/reflect/generic/StandardDefinitions$AbsDefinitions.FloatClass:()Lscala/reflect/generic/Symbols$AbsSymbol;
	astore	15
	dup
	ifnonnull	l20 // aload
	pop
	aload	15
	ifnull	l21 // iconst_3
	goto	l22 // aload_2
l20	aload	15
	invokevirtual	Method java/lang/Object.equals:(Ljava/lang/Object;)Z
	ifeq	l22 // aload_2
l21	iconst_3
	aload_0
	invokevirtual	Method tag:()I
	if_icmpgt	l22 // aload_2
	aload_0
	invokevirtual	Method tag:()I
	ldc_w	int 8
	if_icmpgt	l22 // aload_2
	new	class scala/reflect/generic/Constants$Constant
	dup
	aload_0
	invokevirtual	Method scala$reflect$generic$Constants$Constant$$$outer:()Lscala/reflect/generic/Universe;
	aload_0
	invokevirtual	Method floatValue:()F
	fstore	16
	fload	16
	invokestatic	Method scala/runtime/BoxesRunTime.boxToFloat:(F)Ljava/lang/Float;
	invokespecial	Method "<init>":(Lscala/reflect/generic/Universe;Ljava/lang/Object;)V
	goto	l4 // areturn
l22	aload_2
	aload_0
	invokevirtual	Method scala$reflect$generic$Constants$Constant$$$outer:()Lscala/reflect/generic/Universe;
	invokeinterface	InterfaceMethod scala/reflect/generic/StandardDefinitions.definitions:()Lscala/reflect/generic/StandardDefinitions$AbsDefinitions;
	invokevirtual	Method scala/reflect/generic/StandardDefinitions$AbsDefinitions.DoubleClass:()Lscala/reflect/generic/Symbols$AbsSymbol;
	astore	17
	dup
	ifnonnull	l23 // aload
	pop
	aload	17
	ifnull	l24 // iconst_3
	goto	l25 // aconst_null
l23	aload	17
	invokevirtual	Method java/lang/Object.equals:(Ljava/lang/Object;)Z
	ifeq	l25 // aconst_null
l24	iconst_3
	aload_0
	invokevirtual	Method tag:()I
	if_icmpgt	l25 // aconst_null
	aload_0
	invokevirtual	Method tag:()I
	ldc	int 9
	if_icmpgt	l25 // aconst_null
	new	class scala/reflect/generic/Constants$Constant
	dup
	aload_0
	invokevirtual	Method scala$reflect$generic$Constants$Constant$$$outer:()Lscala/reflect/generic/Universe;
	aload_0
	invokevirtual	Method doubleValue:()D
	dstore	18
	dload	18
	invokestatic	Method scala/runtime/BoxesRunTime.boxToDouble:(D)Ljava/lang/Double;
	invokespecial	Method "<init>":(Lscala/reflect/generic/Universe;Ljava/lang/Object;)V
	goto	l4 // areturn
l25	aconst_null
l4	areturn
  Labels:
   	l1 = 26 // aload_3
   	l2 = 33 // aload_0
   	l3 = 37 // aload_2
   	l5 = 65 // aload
   	l6 = 73 // iconst_3
   	l7 = 134 // aload_2
   	l8 = 162 // aload
   	l9 = 170 // iconst_3
   	l10 = 232 // aload_2
   	l11 = 260 // aload
   	l12 = 268 // iconst_3
   	l13 = 328 // aload_2
   	l14 = 356 // aload
   	l15 = 364 // iconst_3
   	l16 = 406 // aload_2
   	l17 = 434 // aload
   	l18 = 442 // iconst_3
   	l19 = 485 // aload_2
   	l20 = 513 // aload
   	l21 = 521 // iconst_3
   	l22 = 564 // aload_2
   	l23 = 592 // aload
   	l24 = 600 // iconst_3
   	l25 = 642 // aconst_null
   	l4 = 643 // areturn
  LocalVariableTable: 
   Start  Length  Slot  Name   Signature
   0      644      0    this       Lscala/reflect/generic/Constants$Constant;
   0      644      1    pt       Lscala/reflect/generic/Types$AbsType;
   5      639      2    target       Lscala/reflect/generic/Symbols$AbsSymbol;


public java.lang.String stringValue();
  Signature: ()Ljava/lang/String;
  Code:
   Stack=2, Locals=2, Args_size=1
	aload_0
	invokevirtual	Method value:()Ljava/lang/Object;
	dup
	astore_1
	ifnull	l1 // ldc_w
	aload_1
	aconst_null
	invokevirtual	Method java/lang/Object.equals:(Ljava/lang/Object;)Z
	ifeq	l2 // aload_0
l1	ldc_w	String null
	goto	l3 // areturn
l2	aload_0
	invokevirtual	Method tag:()I
	ldc_w	int 12
	if_icmpne	l4 // aload_0
	aload_0
	invokevirtual	Method scala$reflect$generic$Constants$Constant$$$outer:()Lscala/reflect/generic/Universe;
	invokeinterface	InterfaceMethod scala/reflect/generic/StandardDefinitions.definitions:()Lscala/reflect/generic/StandardDefinitions$AbsDefinitions;
	aload_0
	invokevirtual	Method typeValue:()Lscala/reflect/generic/Types$AbsType;
	invokevirtual	Method scala/reflect/generic/StandardDefinitions$AbsDefinitions.signature:(Lscala/reflect/generic/Types$AbsType;)Ljava/lang/String;
	goto	l3 // areturn
l4	aload_0
	invokevirtual	Method value:()Ljava/lang/Object;
	invokevirtual	Method java/lang/Object.toString:()Ljava/lang/String;
l3	areturn
  Labels:
   	l1 = 17 // ldc_w
   	l2 = 23 // aload_0
   	l4 = 52 // aload_0
   	l3 = 59 // areturn

public java.lang.String escapedStringValue();
  Signature: ()Ljava/lang/String;
  Code:
   Stack=3, Locals=5, Args_size=1
	aload_0
	invokevirtual	Method tag:()I
	istore_1
	iload_1
	lookupswitch{ //5
		5: 186;
		7: 152;
		10: 116;
		11: 110;
		12: 66;
		default: 56 }
	aload_0
	invokevirtual	Method value:()Ljava/lang/Object;
	invokevirtual	Method java/lang/Object.toString:()Ljava/lang/String;
	goto	l1 // areturn
	new	class scala/collection/mutable/StringBuilder
	dup
	invokespecial	Method scala/collection/mutable/StringBuilder."<init>":()V
	ldc_w	String classOf[
	invokevirtual	Method scala/collection/mutable/StringBuilder.append:(Ljava/lang/Object;)Lscala/collection/mutable/StringBuilder;
	aload_0
	invokevirtual	Method scala$reflect$generic$Constants$Constant$$$outer:()Lscala/reflect/generic/Universe;
	invokeinterface	InterfaceMethod scala/reflect/generic/StandardDefinitions.definitions:()Lscala/reflect/generic/StandardDefinitions$AbsDefinitions;
	aload_0
	invokevirtual	Method typeValue:()Lscala/reflect/generic/Types$AbsType;
	invokevirtual	Method scala/reflect/generic/StandardDefinitions$AbsDefinitions.signature:(Lscala/reflect/generic/Types$AbsType;)Ljava/lang/String;
	invokevirtual	Method scala/collection/mutable/StringBuilder.append:(Ljava/lang/Object;)Lscala/collection/mutable/StringBuilder;
	ldc_w	String ]
	invokevirtual	Method scala/collection/mutable/StringBuilder.append:(Ljava/lang/Object;)Lscala/collection/mutable/StringBuilder;
	invokevirtual	Method scala/collection/mutable/StringBuilder.toString:()Ljava/lang/String;
	goto	l1 // areturn
	ldc_w	String null
	goto	l1 // areturn
	new	class scala/collection/mutable/StringBuilder
	dup
	invokespecial	Method scala/collection/mutable/StringBuilder."<init>":()V
	ldc_w	String \"
	invokevirtual	Method scala/collection/mutable/StringBuilder.append:(Ljava/lang/Object;)Lscala/collection/mutable/StringBuilder;
	aload_0
	aload_0
	invokevirtual	Method stringValue:()Ljava/lang/String;
	invokespecial	Method escape$1:(Ljava/lang/String;)Ljava/lang/String;
	invokevirtual	Method scala/collection/mutable/StringBuilder.append:(Ljava/lang/Object;)Lscala/collection/mutable/StringBuilder;
	ldc_w	String \"
	invokevirtual	Method scala/collection/mutable/StringBuilder.append:(Ljava/lang/Object;)Lscala/collection/mutable/StringBuilder;
	invokevirtual	Method scala/collection/mutable/StringBuilder.toString:()Ljava/lang/String;
	goto	l1 // areturn
	new	class scala/collection/mutable/StringBuilder
	dup
	invokespecial	Method scala/collection/mutable/StringBuilder."<init>":()V
	aload_0
	invokevirtual	Method longValue:()J
	lstore_3
	lload_3
	invokestatic	Method scala/runtime/BoxesRunTime.boxToLong:(J)Ljava/lang/Long;
	invokevirtual	Method java/lang/Object.toString:()Ljava/lang/String;
	invokevirtual	Method scala/collection/mutable/StringBuilder.append:(Ljava/lang/Object;)Lscala/collection/mutable/StringBuilder;
	ldc_w	String L
	invokevirtual	Method scala/collection/mutable/StringBuilder.append:(Ljava/lang/Object;)Lscala/collection/mutable/StringBuilder;
	invokevirtual	Method scala/collection/mutable/StringBuilder.toString:()Ljava/lang/String;
	goto	l1 // areturn
	aload_0
	new	class scala/collection/mutable/StringBuilder
	dup
	invokespecial	Method scala/collection/mutable/StringBuilder."<init>":()V
	ldc_w	String '
	invokevirtual	Method scala/collection/mutable/StringBuilder.append:(Ljava/lang/Object;)Lscala/collection/mutable/StringBuilder;
	aload_0
	invokevirtual	Method charValue:()C
	istore_2
	iload_2
	invokestatic	Method scala/runtime/BoxesRunTime.boxToCharacter:(C)Ljava/lang/Character;
	invokevirtual	Method scala/collection/mutable/StringBuilder.append:(Ljava/lang/Object;)Lscala/collection/mutable/StringBuilder;
	ldc_w	String '
	invokevirtual	Method scala/collection/mutable/StringBuilder.append:(Ljava/lang/Object;)Lscala/collection/mutable/StringBuilder;
	invokevirtual	Method scala/collection/mutable/StringBuilder.toString:()Ljava/lang/String;
	invokespecial	Method escape$1:(Ljava/lang/String;)Ljava/lang/String;
l1	areturn
  Labels:
   	l1 = 224 // areturn
  LocalVariableTable: 
   Start  Length  Slot  Name   Signature
   0      225      0    this       Lscala/reflect/generic/Constants$Constant;
   5      220      1    temp15       I


public scala.reflect.generic.Types$AbsType typeValue();
  Signature: ()Lscala/reflect/generic/Types$AbsType;
  Code:
   Stack=1, Locals=1, Args_size=1
	aload_0
	invokevirtual	Method value:()Ljava/lang/Object;
	checkcast	class scala/reflect/generic/Types$AbsType
	areturn
  Labels:

public scala.reflect.generic.Symbols$AbsSymbol symbolValue();
  Signature: ()Lscala/reflect/generic/Symbols$AbsSymbol;
  Code:
   Stack=1, Locals=1, Args_size=1
	aload_0
	invokevirtual	Method value:()Ljava/lang/Object;
	checkcast	class scala/reflect/generic/Symbols$AbsSymbol
	areturn
  Labels:

public int hashCode();
  Signature: ()I
  Code:
   Stack=2, Locals=2, Args_size=1
	aload_0
	invokevirtual	Method value:()Ljava/lang/Object;
	dup
	astore_1
	ifnull	l1 // iconst_0
	aload_1
	aconst_null
	invokevirtual	Method java/lang/Object.equals:(Ljava/lang/Object;)Z
	ifeq	l2 // aload_0
l1	iconst_0
	goto	l3 // ireturn
l2	aload_0
	invokevirtual	Method value:()Ljava/lang/Object;
	invokevirtual	Method java/lang/Object.hashCode:()I
	ldc_w	int 41
	imul
	ldc_w	int 17
	iadd
l3	ireturn
  Labels:
   	l1 = 17 // iconst_0
   	l2 = 21 // aload_0
   	l3 = 36 // ireturn

public scala.reflect.generic.Constants$Constant copy(java.lang.Object);
  Signature: (Ljava/lang/Object;)Lscala/reflect/generic/Constants$Constant;
  Code:
   Stack=4, Locals=2, Args_size=2
	new	class scala/reflect/generic/Constants$Constant
	dup
	aload_0
	invokevirtual	Method scala$reflect$generic$Constants$Constant$$$outer:()Lscala/reflect/generic/Universe;
	aload_1
	invokespecial	Method "<init>":(Lscala/reflect/generic/Universe;Ljava/lang/Object;)V
	areturn
  Labels:
  LocalVariableTable: 
   Start  Length  Slot  Name   Signature
   0      13      0    this       Lscala/reflect/generic/Constants$Constant;
   0      13      1    value       Ljava/lang/Object;


public java.lang.String toString();
  Signature: ()Ljava/lang/String;
  Code:
   Stack=2, Locals=1, Args_size=1
	getstatic	Field scala/runtime/ScalaRunTime$.MODULE$:Lscala/runtime/ScalaRunTime$;
	aload_0
	invokevirtual	Method scala/runtime/ScalaRunTime$._toString:(Lscala/Product;)Ljava/lang/String;
	areturn
  Labels:

public java.lang.String productPrefix();
  Signature: ()Ljava/lang/String;
  Code:
   Stack=1, Locals=1, Args_size=1
	ldc_w	String Constant
	areturn
  Labels:

public int productArity();
  Signature: ()I
  Code:
   Stack=1, Locals=1, Args_size=1
	iconst_1
	ireturn
  Labels:

public java.lang.Object productElement(int);
  Signature: (I)Ljava/lang/Object;
  Code:
   Stack=3, Locals=2, Args_size=2
	iload_1
	iconst_0
	if_icmpne	l1 // new
	aload_0
	invokevirtual	Method value:()Ljava/lang/Object;
	areturn
l1	new	class java/lang/IndexOutOfBoundsException
	dup
	iload_1
	invokestatic	Method scala/runtime/BoxesRunTime.boxToInteger:(I)Ljava/lang/Integer;
	invokevirtual	Method java/lang/Object.toString:()Ljava/lang/String;
	invokespecial	Method java/lang/IndexOutOfBoundsException."<init>":(Ljava/lang/String;)V
	athrow
  Labels:
   	l1 = 10 // new

public java.lang.String productElementName(int);
  Signature: (I)Ljava/lang/String;
  Code:
   Stack=3, Locals=2, Args_size=2
	iload_1
	iconst_0
	if_icmpne	l1 // new
	ldc_w	String value
	areturn
l1	new	class java/lang/IndexOutOfBoundsException
	dup
	iload_1
	invokestatic	Method scala/runtime/BoxesRunTime.boxToInteger:(I)Ljava/lang/Integer;
	invokevirtual	Method java/lang/Object.toString:()Ljava/lang/String;
	invokespecial	Method java/lang/IndexOutOfBoundsException."<init>":(Ljava/lang/String;)V
	athrow
  Labels:
   	l1 = 9 // new

public boolean canEqual(java.lang.Object);
  Signature: (Ljava/lang/Object;)Z
  Code:
   Stack=1, Locals=2, Args_size=2
	aload_1
	instanceof	class scala/reflect/generic/Constants$Constant
	ireturn
  Labels:

public scala.reflect.generic.Universe scala$reflect$generic$Constants$Constant$$$outer();
  Signature: ()Lscala/reflect/generic/Universe;
  Code:
   Stack=1, Locals=1, Args_size=1
	aload_0
	getfield	Field $outer:Lscala/reflect/generic/Universe;
	areturn
  Labels:

private final java.lang.String escape$1(java.lang.String);
  Signature: (Ljava/lang/String;)Ljava/lang/String;
  Code:
   Stack=5, Locals=3, Args_size=2
	new	class scala/collection/mutable/StringBuilder
	dup
	invokespecial	Method scala/collection/mutable/StringBuilder."<init>":()V
	astore_2
	getstatic	Field scala/Predef$.MODULE$:Lscala/Predef$;
	aload_1
	invokevirtual	Method scala/Predef$.augmentString:(Ljava/lang/String;)Lscala/collection/immutable/StringOps;
	invokeinterface	InterfaceMethod scala/collection/IndexedSeqLike.iterator:()Lscala/collection/Iterator;
	new	class scala/reflect/generic/Constants$Constant$$anonfun$escape$1$1
	dup
	aload_0
	aload_2
	invokespecial	Method scala/reflect/generic/Constants$Constant$$anonfun$escape$1$1."<init>":(Lscala/reflect/generic/Constants$Constant;Lscala/collection/mutable/StringBuilder;)V
	invokeinterface	InterfaceMethod scala/collection/Iterator.foreach:(Lscala/Function1;)V
	aload_2
	invokevirtual	Method scala/collection/mutable/StringBuilder.toString:()Ljava/lang/String;
	areturn
  Labels:
  LocalVariableTable: 
   Start  Length  Slot  Name   Signature
   0      39      0    this       Lscala/reflect/generic/Constants$Constant;
   0      39      1    text       Ljava/lang/String;
   8      30      2    buf$1       Lscala/collection/mutable/StringBuilder;


public scala.reflect.generic.Constants$Constant(scala.reflect.generic.Universe, java.lang.Object);
  Signature: (Lscala/reflect/generic/Universe;Ljava/lang/Object;)V
  Code:
   Stack=5, Locals=3, Args_size=3
	aload_0
	aload_2
	putfield	Field value:Ljava/lang/Object;
	aload_1
	ifnonnull	l1 // aload_0
	new	class java/lang/NullPointerException
	dup
	invokespecial	Method java/lang/NullPointerException."<init>":()V
	athrow
l1	aload_0
	aload_1
	putfield	Field $outer:Lscala/reflect/generic/Universe;
	aload_0
	invokespecial	Method java/lang/Object."<init>":()V
	aload_0
	invokestatic	Method scala/Product$class.$init$:(Lscala/Product;)V
	aload_0
	aload_2
	instanceof	class scala/runtime/BoxedUnit
	ifeq	l2 // aload_2
	iconst_1
	goto	l3 // putfield
l2	aload_2
	instanceof	class java/lang/Boolean
	ifeq	l4 // aload_2
	iconst_2
	goto	l3 // putfield
l4	aload_2
	instanceof	class java/lang/Byte
	ifeq	l5 // aload_2
	iconst_3
	goto	l3 // putfield
l5	aload_2
	instanceof	class java/lang/Short
	ifeq	l6 // aload_2
	iconst_4
	goto	l3 // putfield
l6	aload_2
	instanceof	class java/lang/Character
	ifeq	l7 // aload_2
	iconst_5
	goto	l3 // putfield
l7	aload_2
	instanceof	class java/lang/Integer
	ifeq	l8 // aload_2
	ldc	int 6
	goto	l3 // putfield
l8	aload_2
	instanceof	class java/lang/Long
	ifeq	l9 // aload_2
	ldc_w	int 7
	goto	l3 // putfield
l9	aload_2
	instanceof	class java/lang/Float
	ifeq	l10 // aload_2
	ldc_w	int 8
	goto	l3 // putfield
l10	aload_2
	instanceof	class java/lang/Double
	ifeq	l11 // aload_2
	ldc	int 9
	goto	l3 // putfield
l11	aload_2
	instanceof	class java/lang/String
	ifeq	l12 // aload_2
	ldc_w	int 10
	goto	l3 // putfield
l12	aload_2
	instanceof	class scala/reflect/generic/Types$AbsType
	ifeq	l13 // aload_2
	ldc_w	int 12
	goto	l3 // putfield
l13	aload_2
	instanceof	class scala/reflect/generic/Symbols$AbsSymbol
	ifeq	l14 // aload_2
	ldc_w	int 13
	goto	l3 // putfield
l14	aload_2
	dup
	pop
	ifnull	l15 // ldc_w
	aload_2
	aconst_null
	invokevirtual	Method java/lang/Object.equals:(Ljava/lang/Object;)Z
	ifeq	l16 // new
l15	ldc_w	int 11
l3	putfield	Field tag:I
	return
l16	new	class java/lang/Error
	dup
	new	class scala/collection/mutable/StringBuilder
	dup
	invokespecial	Method scala/collection/mutable/StringBuilder."<init>":()V
	ldc_w	String bad constant value: 
	invokevirtual	Method scala/collection/mutable/StringBuilder.append:(Ljava/lang/Object;)Lscala/collection/mutable/StringBuilder;
	aload_2
	invokevirtual	Method scala/collection/mutable/StringBuilder.append:(Ljava/lang/Object;)Lscala/collection/mutable/StringBuilder;
	invokevirtual	Method scala/collection/mutable/StringBuilder.toString:()Ljava/lang/String;
	invokespecial	Method java/lang/Error."<init>":(Ljava/lang/String;)V
	athrow
  Labels:
   	l1 = 17 // aload_0
   	l2 = 42 // aload_2
   	l4 = 53 // aload_2
   	l5 = 64 // aload_2
   	l6 = 75 // aload_2
   	l7 = 86 // aload_2
   	l8 = 98 // aload_2
   	l9 = 111 // aload_2
   	l10 = 124 // aload_2
   	l11 = 136 // aload_2
   	l12 = 149 // aload_2
   	l13 = 162 // aload_2
   	l14 = 175 // aload_2
   	l15 = 189 // ldc_w
   	l3 = 192 // putfield
   	l16 = 196 // new
  LocalVariableTable: 
   Start  Length  Slot  Name   Signature
   0      224      0    this       Lscala/reflect/generic/Constants$Constant;
   0      224      1    $outer       Lscala/reflect/generic/Universe;
   0      224      2    value       Ljava/lang/Object;


}

