Compiled from "Constants.scala"
public final class scala.reflect.generic.Constants$Constant$$anonfun$escape$1$1 extends scala.runtime.AbstractFunction1 implements java.io.Serializable
  SourceFile: "Constants.scala"
  Scala: length = 0x
   
  InnerClass: 
   public Constant=class scala/reflect/generic/Constants$Constant of class scala/reflect/generic/Constants
   public final $anonfun$escape$1$1=class scala/reflect/generic/Constants$Constant$$anonfun$escape$1$1 of class scala/reflect/generic/Constants$Constant
  minor version: 0
  major version: 49
  Constant pool:
Asciz	SourceFile;
Asciz	Constants.scala;
Asciz	<clinit>;
Asciz	()V;
Asciz	Code;
Asciz	serialVersionUID;
Asciz	J;
Asciz	scala/reflect/generic/Constants$Constant$$anonfun$escape$1$1;
class	scala/reflect/generic/Constants$Constant$$anonfun$escape$1$1
NameAndType	serialVersionUID:J
Field	scala/reflect/generic/Constants$Constant$$anonfun$escape$1$1.serialVersionUID:J
Asciz	buf$1;
Asciz	Lscala/collection/mutable/StringBuilder;;
Asciz	apply;
Asciz	(C)Lscala/collection/mutable/StringBuilder;;
Asciz	LineNumberTable;
Asciz	java/lang/Character;
class	java/lang/Character
Asciz	isISOControl;
Asciz	(C)Z;
NameAndType	isISOControl:(C)Z
Method	java/lang/Character.isISOControl:(C)Z
NameAndType	buf$1:Lscala/collection/mutable/StringBuilder;
Field	scala/reflect/generic/Constants$Constant$$anonfun$escape$1$1.buf$1:Lscala/collection/mutable/StringBuilder;
Asciz	scala/collection/mutable/StringBuilder;
class	scala/collection/mutable/StringBuilder
Asciz	<init>;
NameAndType	"<init>":()V
Method	scala/collection/mutable/StringBuilder."<init>":()V
Asciz	\0;
String	\0
Asciz	append;
Asciz	(Ljava/lang/Object;)Lscala/collection/mutable/StringBuilder;;
NameAndType	append:(Ljava/lang/Object;)Lscala/collection/mutable/StringBuilder;
Method	scala/collection/mutable/StringBuilder.append:(Ljava/lang/Object;)Lscala/collection/mutable/StringBuilder;
Asciz	java/lang/Integer;
class	java/lang/Integer
Asciz	toOctalString;
Asciz	(I)Ljava/lang/String;;
NameAndType	toOctalString:(I)Ljava/lang/String;
Method	java/lang/Integer.toOctalString:(I)Ljava/lang/String;
Asciz	toString;
Asciz	()Ljava/lang/String;;
NameAndType	toString:()Ljava/lang/String;
Method	scala/collection/mutable/StringBuilder.toString:()Ljava/lang/String;
Asciz	(Ljava/lang/String;)Lscala/collection/mutable/StringBuilder;;
NameAndType	append:(Ljava/lang/String;)Lscala/collection/mutable/StringBuilder;
Method	scala/collection/mutable/StringBuilder.append:(Ljava/lang/String;)Lscala/collection/mutable/StringBuilder;
NameAndType	append:(C)Lscala/collection/mutable/StringBuilder;
Method	scala/collection/mutable/StringBuilder.append:(C)Lscala/collection/mutable/StringBuilder;
Asciz	this;
Asciz	Lscala/reflect/generic/Constants$Constant$$anonfun$escape$1$1;;
Asciz	c;
Asciz	C;
Asciz	LocalVariableTable;
Asciz	(Ljava/lang/Object;)Ljava/lang/Object;;
Asciz	scala/runtime/BoxesRunTime;
class	scala/runtime/BoxesRunTime
Asciz	unboxToChar;
Asciz	(Ljava/lang/Object;)C;
NameAndType	unboxToChar:(Ljava/lang/Object;)C
Method	scala/runtime/BoxesRunTime.unboxToChar:(Ljava/lang/Object;)C
NameAndType	apply:(C)Lscala/collection/mutable/StringBuilder;
Method	scala/reflect/generic/Constants$Constant$$anonfun$escape$1$1.apply:(C)Lscala/collection/mutable/StringBuilder;
Asciz	v1;
Asciz	Ljava/lang/Object;;
Asciz	(Lscala/reflect/generic/Constants$Constant;Lscala/collection/mutable/StringBuilder;)V;
Asciz	scala/runtime/AbstractFunction1;
class	scala/runtime/AbstractFunction1
Method	scala/runtime/AbstractFunction1."<init>":()V
Asciz	$outer;
Asciz	Lscala/reflect/generic/Constants$Constant;;
Asciz	Scala;
Asciz	InnerClasses;
Asciz	scala/reflect/generic/Constants$Constant;
class	scala/reflect/generic/Constants$Constant
Asciz	scala/reflect/generic/Constants;
class	scala/reflect/generic/Constants
Asciz	Constant;
Asciz	$anonfun$escape$1$1;
Asciz	java/io/Serializable;
class	java/io/Serializable

{
public static final long serialVersionUID;
  Signature: J

public final scala.collection.mutable.StringBuilder buf$1;
  Signature: Lscala/collection/mutable/StringBuilder;

public static {};
  Signature: ()V
  Code:
   Stack=2, Locals=0, Args_size=0
	lconst_0
	putstatic	Field serialVersionUID:J
	return
  Labels:

public final scala.collection.mutable.StringBuilder apply(char);
  Signature: (C)Lscala/collection/mutable/StringBuilder;
  Code:
   Stack=3, Locals=2, Args_size=2
	iload_1
	invokestatic	Method java/lang/Character.isISOControl:(C)Z
	ifeq	l1 // aload_0
	aload_0
	getfield	Field buf$1:Lscala/collection/mutable/StringBuilder;
	new	class scala/collection/mutable/StringBuilder
	dup
	invokespecial	Method scala/collection/mutable/StringBuilder."<init>":()V
	ldc	String \0
	invokevirtual	Method scala/collection/mutable/StringBuilder.append:(Ljava/lang/Object;)Lscala/collection/mutable/StringBuilder;
	iload_1
	invokestatic	Method java/lang/Integer.toOctalString:(I)Ljava/lang/String;
	invokevirtual	Method scala/collection/mutable/StringBuilder.append:(Ljava/lang/Object;)Lscala/collection/mutable/StringBuilder;
	invokevirtual	Method scala/collection/mutable/StringBuilder.toString:()Ljava/lang/String;
	invokevirtual	Method scala/collection/mutable/StringBuilder.append:(Ljava/lang/String;)Lscala/collection/mutable/StringBuilder;
	goto	l2 // areturn
l1	aload_0
	getfield	Field buf$1:Lscala/collection/mutable/StringBuilder;
	iload_1
	invokevirtual	Method scala/collection/mutable/StringBuilder.append:(C)Lscala/collection/mutable/StringBuilder;
l2	areturn
  Labels:
   	l1 = 39 // aload_0
   	l2 = 47 // areturn
  LocalVariableTable: 
   Start  Length  Slot  Name   Signature
   0      48      0    this       Lscala/reflect/generic/Constants$Constant$$anonfun$escape$1$1;
   0      48      1    c       C


public final java.lang.Object apply(java.lang.Object);
  Signature: (Ljava/lang/Object;)Ljava/lang/Object;
  Code:
   Stack=2, Locals=2, Args_size=2
	aload_0
	aload_1
	invokestatic	Method scala/runtime/BoxesRunTime.unboxToChar:(Ljava/lang/Object;)C
	invokevirtual	Method apply:(C)Lscala/collection/mutable/StringBuilder;
	areturn
  Labels:
  LocalVariableTable: 
   Start  Length  Slot  Name   Signature
   0      9      0    this       Lscala/reflect/generic/Constants$Constant$$anonfun$escape$1$1;
   0      9      1    v1       Ljava/lang/Object;


public scala.reflect.generic.Constants$Constant$$anonfun$escape$1$1(scala.reflect.generic.Constants$Constant, scala.collection.mutable.StringBuilder);
  Signature: (Lscala/reflect/generic/Constants$Constant;Lscala/collection/mutable/StringBuilder;)V
  Code:
   Stack=2, Locals=3, Args_size=3
	aload_0
	aload_2
	putfield	Field buf$1:Lscala/collection/mutable/StringBuilder;
	aload_0
	invokespecial	Method scala/runtime/AbstractFunction1."<init>":()V
	return
  Labels:
  LocalVariableTable: 
   Start  Length  Slot  Name   Signature
   0      10      0    this       Lscala/reflect/generic/Constants$Constant$$anonfun$escape$1$1;
   0      10      1    $outer       Lscala/reflect/generic/Constants$Constant;


}

