Compiled from "Flags.scala"
public class scala.reflect.generic.Flags extends java.lang.Object implements scala.ScalaObject
  SourceFile: "Flags.scala"
  ScalaSig: length = 0xF09
   05 00 FFFFFF83 51 07 05 01 02 FFFFFF88 02 09 01 05 46 6C 61
   67 73 0A 02 03 04 01 07 67 65 6E 65 72 69 63 0A
   02 05 06 01 07 72 65 66 6C 65 63 74 0A 01 07 01
   05 73 63 61 6C 61 03 00 10 02 0A 0B 0D 01 02 06
   08 0C 02 FFFFFF84 FFFFFF80 FFFFFF80 FFFFFF88 02 0D 02 05 46 6C 61 67 73
   13 03 0B 0E 19 10 02 0A 0F 06 08 0C 02 FFFFFF84 FFFFFF80 FFFFFF80
   FFFFFF80 00 10 13 03 0F 11 19 10 02 12 17 0D 01 13 0A
   02 14 15 01 04 6C 61 6E 67 0A 01 16 01 04 6A 61
   76 61 09 02 18 13 02 06 4F 62 6A 65 63 74 10 02
   1A 1B 0D 01 06 09 02 1C 06 02 0B 53 63 61 6C 61
   4F 62 6A 65 63 74 08 05 1E 0F FFFFFF84 00 1F 01 06 3C
   69 6E 69 74 3E 14 01 0E 08 07 21 0F FFFFFFC2 FFFFFF80 FFFFFF84 02
   22 01 08 49 4D 50 4C 49 43 49 54 15 01 23 0F 01
   24 1D 02 02 00 08 06 26 0F FFFFFFA0 FFFFFF80 06 23 01 09 49
   4D 50 4C 49 43 49 54 20 08 07 28 0F FFFFFFC2 FFFFFF80 FFFFFF84 02
   29 01 05 46 49 4E 41 4C 15 01 2A 0F 01 2B 1D 01
   20 08 06 2D 0F FFFFFFA0 FFFFFF80 06 2A 01 06 46 49 4E 41 4C
   20 08 07 2F 0F FFFFFFC2 FFFFFF80 FFFFFF84 02 30 01 07 50 52 49 56
   41 54 45 15 01 31 0F 01 32 1D 01 04 08 06 34 0F
   FFFFFFA0 FFFFFF80 06 31 01 08 50 52 49 56 41 54 45 20 08 07
   36 0F FFFFFFC2 FFFFFF80 FFFFFF84 02 37 01 09 50 52 4F 54 45 43 54
   45 44 15 01 38 0F 01 39 1D 01 01 08 06 3B 0F FFFFFFA0
   FFFFFF80 06 38 01 0A 50 52 4F 54 45 43 54 45 44 20 08
   07 3D 0F FFFFFFC2 FFFFFF80 FFFFFF84 02 3E 01 06 53 45 41 4C 45 44
   15 01 3F 0F 01 40 1D 02 04 00 08 06 42 0F FFFFFFA0 FFFFFF80
   06 3F 01 07 53 45 41 4C 45 44 20 08 07 44 0F FFFFFFC2
   FFFFFF80 FFFFFF84 02 45 01 08 4F 56 45 52 52 49 44 45 15 01
   46 0F 01 47 1D 01 02 08 06 49 0F FFFFFFA0 FFFFFF80 06 46 01
   09 4F 56 45 52 52 49 44 45 20 08 07 4B 0F FFFFFFC2 FFFFFF80
   FFFFFF84 02 4C 01 04 43 41 53 45 15 01 4D 0F 01 4E 1D
   02 08 00 08 06 50 0F FFFFFFA0 FFFFFF80 06 4D 01 05 43 41 53
   45 20 08 07 52 0F FFFFFFC2 FFFFFF80 FFFFFF84 02 53 01 08 41 42 53
   54 52 41 43 54 15 01 54 0F 01 55 1D 01 08 08 06
   57 0F FFFFFFA0 FFFFFF80 06 54 01 09 41 42 53 54 52 41 43 54
   20 08 07 59 0F FFFFFFC2 FFFFFF80 FFFFFF84 02 5A 01 08 44 45 46 45
   52 52 45 44 15 01 5B 0F 01 5C 1D 01 10 08 06 5E
   0F FFFFFFA0 FFFFFF80 06 5B 01 09 44 45 46 45 52 52 45 44 20
   08 07 60 0F FFFFFFC2 FFFFFF80 FFFFFF84 02 61 01 06 4D 45 54 48 4F
   44 15 01 62 0F 01 63 1D 01 40 08 06 65 0F FFFFFFA0 FFFFFF80
   06 62 01 07 4D 45 54 48 4F 44 20 08 07 67 0F FFFFFFC2
   FFFFFF80 FFFFFF84 02 68 01 06 4D 4F 44 55 4C 45 15 01 69 0F
   01 6A 1D 02 01 00 08 06 6C 0F FFFFFFA0 FFFFFF80 06 69 01 07
   4D 4F 44 55 4C 45 20 08 07 6E 0F FFFFFFC2 FFFFFF80 FFFFFF84 02 6F
   01 09 49 4E 54 45 52 46 41 43 45 15 01 70 0F 01
   71 1D 02 00 FFFFFF80 08 06 73 0F FFFFFFA0 FFFFFF80 06 70 01 0A 49
   4E 54 45 52 46 41 43 45 20 08 07 75 0F FFFFFFC2 FFFFFF80 FFFFFF84
   02 76 01 07 4D 55 54 41 42 4C 45 15 01 77 0F 01
   78 1D 02 10 00 08 06 7A 0F FFFFFFA0 FFFFFF80 06 77 01 08 4D
   55 54 41 42 4C 45 20 08 07 7C 0F FFFFFFC2 FFFFFF80 FFFFFF84 02 7D
   01 05 50 41 52 41 4D 15 01 7E 0F 01 7F 1D 02 20
   00 08 07 FFFFFF81 01 0F FFFFFFA0 FFFFFF80 06 7E 01 06 50 41 52 41
   4D 20 08 09 FFFFFF81 03 0F FFFFFFC2 FFFFFF80 FFFFFF84 02 FFFFFF81 04 01 07 50
   41 43 4B 41 47 45 15 02 FFFFFF81 05 0F 02 FFFFFF81 06 1D 02
   40 00 08 08 FFFFFF81 08 0F FFFFFFA0 FFFFFF80 06 FFFFFF81 05 01 08 50 41
   43 4B 41 47 45 20 08 09 FFFFFF81 0A 0F FFFFFFC2 FFFFFF80 FFFFFF84 02 FFFFFF81
   0B 01 09 43 4F 56 41 52 49 41 4E 54 15 02 FFFFFF81 0C
   0F 02 FFFFFF81 0D 1D 03 01 00 00 08 08 FFFFFF81 0F 0F FFFFFFA0 FFFFFF80
   06 FFFFFF81 0C 01 0A 43 4F 56 41 52 49 41 4E 54 20 08
   09 FFFFFF81 11 0F FFFFFFC2 FFFFFF80 FFFFFF84 02 FFFFFF81 0B 01 08 43 41 50 54
   55 52 45 44 08 08 FFFFFF81 13 0F FFFFFFA0 FFFFFF80 06 FFFFFF81 0C 01 09
   43 41 50 54 55 52 45 44 20 08 09 FFFFFF81 15 0F FFFFFFC2 FFFFFF80
   FFFFFF84 02 FFFFFF81 0B 01 0B 42 59 4E 41 4D 45 50 41 52 41
   4D 08 08 FFFFFF81 17 0F FFFFFFA0 FFFFFF80 06 FFFFFF81 0C 01 0C 42 59 4E
   41 4D 45 50 41 52 41 4D 20 08 09 FFFFFF81 19 0F FFFFFFC2 FFFFFF80
   FFFFFF84 02 FFFFFF81 1A 01 0D 43 4F 4E 54 52 41 56 41 52 49
   41 4E 54 15 02 FFFFFF81 1B 0F 02 FFFFFF81 1C 1D 03 02 00 00
   08 08 FFFFFF81 1E 0F FFFFFFA0 FFFFFF80 06 FFFFFF81 1B 01 0E 43 4F 4E 54
   52 41 56 41 52 49 41 4E 54 20 08 09 FFFFFF81 20 0F FFFFFFC2
   FFFFFF80 FFFFFF84 02 FFFFFF81 1A 01 05 4C 41 42 45 4C 08 08 FFFFFF81 22
   0F FFFFFFA0 FFFFFF80 06 FFFFFF81 1B 01 06 4C 41 42 45 4C 20 08 09
   FFFFFF81 24 0F FFFFFFC2 FFFFFF80 FFFFFF84 02 FFFFFF81 1A 01 0D 49 4E 43 4F 4E
   53 54 52 55 43 54 4F 52 08 08 FFFFFF81 26 0F FFFFFFA0 FFFFFF80 06
   FFFFFF81 1B 01 0E 49 4E 43 4F 4E 53 54 52 55 43 54 4F
   52 20 08 09 FFFFFF81 28 0F FFFFFFC2 FFFFFF80 FFFFFF84 02 FFFFFF81 29 01 0B 41
   42 53 4F 56 45 52 52 49 44 45 15 02 FFFFFF81 2A 0F 02
   FFFFFF81 2B 1D 03 04 00 00 08 08 FFFFFF81 2D 0F FFFFFFA0 FFFFFF80 06 FFFFFF81
   2A 01 0C 41 42 53 4F 56 45 52 52 49 44 45 20 08
   09 FFFFFF81 2F 0F FFFFFFC2 FFFFFF80 FFFFFF84 02 FFFFFF81 30 01 05 4C 4F 43 41
   4C 15 02 FFFFFF81 31 0F 02 FFFFFF81 32 1D 03 08 00 00 08 08
   FFFFFF81 34 0F FFFFFFA0 FFFFFF80 06 FFFFFF81 31 01 06 4C 4F 43 41 4C 20
   08 09 FFFFFF81 36 0F FFFFFFC2 FFFFFF80 FFFFFF84 02 FFFFFF81 37 01 04 4A 41 56
   41 15 02 FFFFFF81 38 0F 02 FFFFFF81 39 1D 03 10 00 00 08 08
   FFFFFF81 3B 0F FFFFFFA0 FFFFFF80 06 FFFFFF81 38 01 05 4A 41 56 41 20 08
   09 FFFFFF81 3D 0F FFFFFFC2 FFFFFF80 FFFFFF84 02 FFFFFF81 3E 01 09 53 59 4E 54
   48 45 54 49 43 15 02 FFFFFF81 3F 0F 02 FFFFFF81 40 1D 03 20
   00 00 08 08 FFFFFF81 42 0F FFFFFFA0 FFFFFF80 06 FFFFFF81 3F 01 0A 53 59
   4E 54 48 45 54 49 43 20 08 09 FFFFFF81 44 0F FFFFFFC2 FFFFFF80 FFFFFF84
   02 FFFFFF81 45 01 06 53 54 41 42 4C 45 15 02 FFFFFF81 46 0F
   02 FFFFFF81 47 1D 03 40 00 00 08 08 FFFFFF81 49 0F FFFFFFA0 FFFFFF80 06
   FFFFFF81 46 01 07 53 54 41 42 4C 45 20 08 09 FFFFFF81 4B 0F
   FFFFFFC2 FFFFFF80 FFFFFF84 02 FFFFFF81 4C 01 06 53 54 41 54 49 43 15 02
   FFFFFF81 4D 0F 02 FFFFFF81 4E 1D 04 00 FFFFFF80 00 00 08 08 FFFFFF81 50
   0F FFFFFFA0 FFFFFF80 06 FFFFFF81 4D 01 07 53 54 41 54 49 43 20 08
   09 FFFFFF81 52 0F FFFFFFC2 FFFFFF80 FFFFFF84 02 FFFFFF81 53 01 0C 43 41 53 45
   41 43 43 45 53 53 4F 52 15 02 FFFFFF81 54 0F 02 FFFFFF81 55
   1D 04 01 00 00 00 08 08 FFFFFF81 57 0F FFFFFFA0 FFFFFF80 06 FFFFFF81 54
   01 0D 43 41 53 45 41 43 43 45 53 53 4F 52 20 08
   09 FFFFFF81 59 0F FFFFFFC2 FFFFFF80 FFFFFF84 02 FFFFFF81 5A 01 05 54 52 41 49
   54 15 02 FFFFFF81 5B 0F 02 FFFFFF81 5C 1D 04 02 00 00 00 08
   08 FFFFFF81 5E 0F FFFFFFA0 FFFFFF80 06 FFFFFF81 5B 01 06 54 52 41 49 54
   20 08 09 FFFFFF81 60 0F FFFFFFC2 FFFFFF80 FFFFFF84 02 FFFFFF81 5A 01 0C 44 45
   46 41 55 4C 54 50 41 52 41 4D 08 08 FFFFFF81 62 0F FFFFFFA0
   FFFFFF80 06 FFFFFF81 5B 01 0D 44 45 46 41 55 4C 54 50 41 52
   41 4D 20 08 09 FFFFFF81 64 0F FFFFFFC2 FFFFFF80 FFFFFF84 02 FFFFFF81 65 01 06
   42 52 49 44 47 45 15 02 FFFFFF81 66 0F 02 FFFFFF81 67 1D 04
   04 00 00 00 08 08 FFFFFF81 69 0F FFFFFFA0 FFFFFF80 06 FFFFFF81 66 01 07
   42 52 49 44 47 45 20 08 09 FFFFFF81 6B 0F FFFFFFC2 FFFFFF80 FFFFFF84 02
   FFFFFF81 6C 01 08 41 43 43 45 53 53 4F 52 15 02 FFFFFF81 6D
   0F 02 FFFFFF81 6E 1D 04 08 00 00 00 08 08 FFFFFF81 70 0F FFFFFFA0
   FFFFFF80 06 FFFFFF81 6D 01 09 41 43 43 45 53 53 4F 52 20 08
   09 FFFFFF81 72 0F FFFFFFC2 FFFFFF80 FFFFFF84 02 FFFFFF81 73 01 0D 53 55 50 45
   52 41 43 43 45 53 53 4F 52 15 02 FFFFFF81 74 0F 02 FFFFFF81
   75 1D 04 10 00 00 00 08 08 FFFFFF81 77 0F FFFFFFA0 FFFFFF80 06 FFFFFF81
   74 01 0E 53 55 50 45 52 41 43 43 45 53 53 4F 52
   20 08 09 FFFFFF81 79 0F FFFFFFC2 FFFFFF80 FFFFFF84 02 FFFFFF81 7A 01 0D 50 41
   52 41 4D 41 43 43 45 53 53 4F 52 15 02 FFFFFF81 7B 0F
   02 FFFFFF81 7C 1D 04 20 00 00 00 08 08 FFFFFF81 7E 0F FFFFFFA0 FFFFFF80
   06 FFFFFF81 7B 01 0E 50 41 52 41 4D 41 43 43 45 53 53
   4F 52 20 08 09 FFFFFF82 00 0F FFFFFFC2 FFFFFF80 FFFFFF84 02 FFFFFF82 01 01 09
   4D 4F 44 55 4C 45 56 41 52 15 02 FFFFFF82 02 0F 02 FFFFFF82
   03 1D 04 40 00 00 00 08 08 FFFFFF82 05 0F FFFFFFA0 FFFFFF80 06 FFFFFF82
   02 01 0A 4D 4F 44 55 4C 45 56 41 52 20 08 09 FFFFFF82
   07 0F FFFFFFC2 FFFFFF80 FFFFFF84 02 FFFFFF82 01 01 0D 53 59 4E 54 48 45
   54 49 43 4D 45 54 48 08 08 FFFFFF82 09 0F FFFFFFA0 FFFFFF80 06 FFFFFF82
   02 01 0E 53 59 4E 54 48 45 54 49 43 4D 45 54 48
   20 08 09 FFFFFF82 0B 0F FFFFFFC2 FFFFFF80 FFFFFF84 02 FFFFFF82 01 01 0B 4D 4F
   4E 4F 4D 4F 52 50 48 49 43 08 08 FFFFFF82 0D 0F FFFFFFA0 FFFFFF80
   06 FFFFFF82 02 01 0C 4D 4F 4E 4F 4D 4F 52 50 48 49 43
   20 08 09 FFFFFF82 0F 0F FFFFFFC2 FFFFFF80 FFFFFF84 02 FFFFFF82 10 01 04 4C 41
   5A 59 15 02 FFFFFF82 11 0F 02 FFFFFF82 12 1E 05 00 FFFFFF80 00 00
   00 08 08 FFFFFF82 14 0F FFFFFFA0 FFFFFF80 06 FFFFFF82 11 01 05 4C 41 5A
   59 20 08 09 FFFFFF82 16 0F FFFFFFC2 FFFFFF80 FFFFFF84 02 FFFFFF82 17 01 08 49
   53 5F 45 52 52 4F 52 15 02 FFFFFF82 18 0F 02 FFFFFF82 19 1E
   05 01 00 00 00 00 08 08 FFFFFF82 1B 0F FFFFFFA0 FFFFFF80 06 FFFFFF82 18
   01 09 49 53 5F 45 52 52 4F 52 20 08 09 FFFFFF82 1D 0F
   FFFFFFC2 FFFFFF80 FFFFFF84 02 FFFFFF82 1E 01 0A 4F 56 45 52 4C 4F 41 44
   45 44 15 02 FFFFFF82 1F 0F 02 FFFFFF82 20 1E 05 02 00 00 00
   00 08 08 FFFFFF82 22 0F FFFFFFA0 FFFFFF80 06 FFFFFF82 1F 01 0B 4F 56 45
   52 4C 4F 41 44 45 44 20 08 09 FFFFFF82 24 0F FFFFFFC2 FFFFFF80 FFFFFF84
   02 FFFFFF82 25 01 06 4C 49 46 54 45 44 15 02 FFFFFF82 26 0F
   02 FFFFFF82 27 1E 05 04 00 00 00 00 08 08 FFFFFF82 29 0F FFFFFFA0
   FFFFFF80 06 FFFFFF82 26 01 07 4C 49 46 54 45 44 20 08 09 FFFFFF82
   2B 0F FFFFFFC2 FFFFFF80 FFFFFF84 02 FFFFFF82 2C 01 07 4D 49 58 45 44 49
   4E 15 02 FFFFFF82 2D 0F 02 FFFFFF82 2E 1E 05 08 00 00 00 00
   08 08 FFFFFF82 30 0F FFFFFFA0 FFFFFF80 06 FFFFFF82 2D 01 08 4D 49 58 45
   44 49 4E 20 08 09 FFFFFF82 32 0F FFFFFFC2 FFFFFF80 FFFFFF84 02 FFFFFF82 2C 01
   0B 45 58 49 53 54 45 4E 54 49 41 4C 08 08 FFFFFF82 34
   0F FFFFFFA0 FFFFFF80 06 FFFFFF82 2D 01 0C 45 58 49 53 54 45 4E 54
   49 41 4C 20 08 09 FFFFFF82 36 0F FFFFFFC2 FFFFFF80 FFFFFF84 02 FFFFFF82 37 01
   0C 45 58 50 41 4E 44 45 44 4E 41 4D 45 15 02 FFFFFF82
   38 0F 02 FFFFFF82 39 1E 05 10 00 00 00 00 08 08 FFFFFF82 3B
   0F FFFFFFA0 FFFFFF80 06 FFFFFF82 38 01 0D 45 58 50 41 4E 44 45 44
   4E 41 4D 45 20 08 09 FFFFFF82 3D 0F FFFFFFC2 FFFFFF80 FFFFFF84 02 FFFFFF82 3E
   01 09 49 4D 50 4C 43 4C 41 53 53 15 02 FFFFFF82 3F 0F
   02 FFFFFF82 40 1E 05 20 00 00 00 00 08 08 FFFFFF82 42 0F FFFFFFA0
   FFFFFF80 06 FFFFFF82 3F 01 0A 49 4D 50 4C 43 4C 41 53 53 20
   08 09 FFFFFF82 44 0F FFFFFFC2 FFFFFF80 FFFFFF84 02 FFFFFF82 3E 01 08 50 52 45
   53 55 50 45 52 08 08 FFFFFF82 46 0F FFFFFFA0 FFFFFF80 06 FFFFFF82 3F 01
   09 50 52 45 53 55 50 45 52 20 08 09 FFFFFF82 48 0F FFFFFFC2
   FFFFFF80 FFFFFF84 02 FFFFFF82 49 01 0A 54 52 41 4E 53 5F 46 4C 41
   47 15 02 FFFFFF82 4A 0F 02 FFFFFF82 4B 1E 05 40 00 00 00 00
   08 08 FFFFFF82 4D 0F FFFFFFA0 FFFFFF80 06 FFFFFF82 4A 01 0B 54 52 41 4E
   53 5F 46 4C 41 47 20 08 09 FFFFFF82 4F 0F FFFFFFC2 FFFFFF80 FFFFFF84 02
   FFFFFF82 50 01 06 4C 4F 43 4B 45 44 15 02 FFFFFF82 51 0F 02
   FFFFFF82 52 1E 06 00 FFFFFF80 00 00 00 00 08 08 FFFFFF82 54 0F FFFFFFA0
   FFFFFF80 06 FFFFFF82 51 01 07 4C 4F 43 4B 45 44 20 08 09 FFFFFF82
   56 0F FFFFFFC2 FFFFFF80 FFFFFF84 02 FFFFFF82 57 01 0B 53 50 45 43 49 41
   4C 49 5A 45 44 15 02 FFFFFF82 58 0F 02 FFFFFF82 59 1E 06 01
   00 00 00 00 00 08 08 FFFFFF82 5B 0F FFFFFFA0 FFFFFF80 06 FFFFFF82 58 01
   0C 53 50 45 43 49 41 4C 49 5A 45 44 20 08 09 FFFFFF82
   5D 0F FFFFFFC2 FFFFFF80 FFFFFF84 02 FFFFFF82 5E 01 0B 44 45 46 41 55 4C
   54 49 4E 49 54 15 02 FFFFFF82 5F 0F 02 FFFFFF82 60 1E 06 02
   00 00 00 00 00 08 08 FFFFFF82 62 0F FFFFFFA0 FFFFFF80 06 FFFFFF82 5F 01
   0C 44 45 46 41 55 4C 54 49 4E 49 54 20 08 09 FFFFFF82
   64 0F FFFFFFC2 FFFFFF80 FFFFFF84 02 FFFFFF82 65 01 07 56 42 52 49 44 47
   45 15 02 FFFFFF82 66 0F 02 FFFFFF82 67 1E 06 04 00 00 00 00
   00 08 08 FFFFFF82 69 0F FFFFFFA0 FFFFFF80 06 FFFFFF82 66 01 08 56 42 52
   49 44 47 45 20 08 08 FFFFFF82 6B 0F FFFFFFC2 FFFFFF80 FFFFFF84 06 37 01
   0C 49 4D 50 4C 49 43 49 54 5F 50 4B 4C 08 07 FFFFFF82
   6D 0F FFFFFFA0 FFFFFF80 06 38 01 0D 49 4D 50 4C 49 43 49 54
   5F 50 4B 4C 20 08 08 FFFFFF82 6F 0F FFFFFFC2 FFFFFF80 FFFFFF84 06 45 01
   09 46 49 4E 41 4C 5F 50 4B 4C 08 07 FFFFFF82 71 0F FFFFFFA0
   FFFFFF80 06 46 01 0A 46 49 4E 41 4C 5F 50 4B 4C 20 08
   08 FFFFFF82 73 0F FFFFFFC2 FFFFFF80 FFFFFF84 06 30 01 0B 50 52 49 56 41
   54 45 5F 50 4B 4C 08 07 FFFFFF82 75 0F FFFFFFA0 FFFFFF80 06 31 01
   0C 50 52 49 56 41 54 45 5F 50 4B 4C 20 08 08 FFFFFF82
   77 0F FFFFFFC2 FFFFFF80 FFFFFF84 06 53 01 0D 50 52 4F 54 45 43 54
   45 44 5F 50 4B 4C 08 07 FFFFFF82 79 0F FFFFFFA0 FFFFFF80 06 54 01
   0E 50 52 4F 54 45 43 54 45 44 5F 50 4B 4C 20 08
   08 FFFFFF82 7B 0F FFFFFFC2 FFFFFF80 FFFFFF84 06 5A 01 0A 53 45 41 4C 45
   44 5F 50 4B 4C 08 07 FFFFFF82 7D 0F FFFFFFA0 FFFFFF80 06 5B 01 0B
   53 45 41 4C 45 44 5F 50 4B 4C 20 08 08 FFFFFF82 7F 0F
   FFFFFFC2 FFFFFF80 FFFFFF84 06 29 01 0C 4F 56 45 52 52 49 44 45 5F
   50 4B 4C 08 07 FFFFFF83 01 0F FFFFFFA0 FFFFFF80 06 2A 01 0D 4F 56
   45 52 52 49 44 45 5F 50 4B 4C 20 08 08 FFFFFF83 03 0F
   FFFFFFC2 FFFFFF80 FFFFFF84 06 61 01 08 43 41 53 45 5F 50 4B 4C 08
   07 FFFFFF83 05 0F FFFFFFA0 FFFFFF80 06 62 01 09 43 41 53 45 5F 50
   4B 4C 20 08 08 FFFFFF83 07 0F FFFFFFC2 FFFFFF80 FFFFFF84 06 6F 01 0C 41
   42 53 54 52 41 43 54 5F 50 4B 4C 08 07 FFFFFF83 09 0F
   FFFFFFA0 FFFFFF80 06 70 01 0D 41 42 53 54 52 41 43 54 5F 50
   4B 4C 20 08 08 FFFFFF83 0B 0F FFFFFFC2 FFFFFF80 FFFFFF84 06 68 01 0C 44
   45 46 45 52 52 45 44 5F 50 4B 4C 08 07 FFFFFF83 0D 0F
   FFFFFFA0 FFFFFF80 06 69 01 0D 44 45 46 45 52 52 45 44 5F 50
   4B 4C 20 08 08 FFFFFF83 0F 0F FFFFFFC2 FFFFFF80 FFFFFF84 06 22 01 0A 4D
   45 54 48 4F 44 5F 50 4B 4C 08 07 FFFFFF83 11 0F FFFFFFA0 FFFFFF80
   06 23 01 0B 4D 45 54 48 4F 44 5F 50 4B 4C 20 08
   08 FFFFFF83 13 0F FFFFFFC2 FFFFFF80 FFFFFF84 06 3E 01 0A 4D 4F 44 55 4C
   45 5F 50 4B 4C 08 07 FFFFFF83 15 0F FFFFFFA0 FFFFFF80 06 3F 01 0B
   4D 4F 44 55 4C 45 5F 50 4B 4C 20 08 08 FFFFFF83 17 0F
   FFFFFFC2 FFFFFF80 FFFFFF84 06 4C 01 0D 49 4E 54 45 52 46 41 43 45
   5F 50 4B 4C 08 07 FFFFFF83 19 0F FFFFFFA0 FFFFFF80 06 4D 01 0E 49
   4E 54 45 52 46 41 43 45 5F 50 4B 4C 20 08 09 FFFFFF83
   1B 0F FFFFFFC2 FFFFFF80 FFFFFF84 06 FFFFFF83 1C 01 08 50 4B 4C 5F 4D 41
   53 4B 15 02 FFFFFF83 1D 0F 02 FFFFFF83 1E 1D 02 0F FFFFFFFF 08 08
   FFFFFF83 20 0F FFFFFFA0 FFFFFF80 06 FFFFFF83 1D 01 09 50 4B 4C 5F 4D 41
   53 4B 20 08 09 FFFFFF83 22 0F FFFFFFC2 FFFFFF80 FFFFFF84 02 FFFFFF83 23 01 0C
   50 69 63 6B 6C 65 64 46 6C 61 67 73 15 02 FFFFFF83 24
   10 03 1A FFFFFF83 25 09 03 FFFFFF83 26 06 02 04 4C 6F 6E 67
   08 08 FFFFFF83 28 0F FFFFFFA0 FFFFFF80 06 FFFFFF83 24 01 0D 50 69 63 6B
   6C 65 64 46 6C 61 67 73 20 08 09 FFFFFF83 2A 0F FFFFFFC2 FFFFFF80
   FFFFFF84 04 FFFFFF83 2B 01 03 72 32 70 15 02 FFFFFF83 2C 10 05 1A
   FFFFFF83 2D FFFFFF83 2F 09 03 FFFFFF83 2E 06 02 05 41 72 72 61 79
   10 03 1A FFFFFF83 30 09 03 FFFFFF83 31 06 02 03 49 6E 74 08
   08 FFFFFF83 33 0F FFFFFFA0 FFFFFF80 04 FFFFFF83 2C 01 04 72 32 70 20 08
   09 FFFFFF83 35 0F FFFFFFC2 FFFFFF80 FFFFFF84 04 FFFFFF83 2B 01 03 70 32 72 08
   08 FFFFFF83 37 0F FFFFFFA0 FFFFFF80 04 FFFFFF83 2C 01 04 70 32 72 20 08
   07 FFFFFF83 39 0F FFFFFF84 00 FFFFFF83 3A 01 11 72 61 77 46 6C 61
   67 73 54 6F 50 69 63 6B 6C 65 64 14 04 FFFFFF83 24 FFFFFF83
   3B 08 08 FFFFFF83 3C FFFFFF83 38 FFFFFFC0 00 FFFFFF83 24 01 05 66 6C 61
   67 73 08 07 FFFFFF83 3E 0F FFFFFF84 00 FFFFFF83 3F 01 11 70 69 63
   6B 6C 65 64 54 6F 52 61 77 46 6C 61 67 73 14 04
   FFFFFF83 24 FFFFFF83 40 08 08 FFFFFF83 41 FFFFFF83 3D FFFFFFC0 00 FFFFFF83 24 01 06
   70 66 6C 61 67 73 08 09 FFFFFF83 43 0F FFFFFFC2 FFFFFF80 FFFFFF84 08 FFFFFF83
   44 01 10 70 69 63 6B 6C 65 64 4C 69 73 74 4F 72
   64 65 72 15 02 FFFFFF83 45 10 06 FFFFFF83 46 FFFFFF83 4B FFFFFF83 24 0D
   02 FFFFFF83 47 0A 04 FFFFFF83 48 FFFFFF83 49 01 09 69 6D 6D 75 74
   61 62 6C 65 0A 03 FFFFFF83 4A 06 01 0A 63 6F 6C 6C 65
   63 74 69 6F 6E 09 04 FFFFFF83 4C FFFFFF83 47 02 04 4C 69 73
   74 08 08 FFFFFF83 4E 0F FFFFFFA0 FFFFFF80 04 FFFFFF83 45 01 11 70 69 63
   6B 6C 65 64 4C 69 73 74 4F 72 64 65 72 20 08 06
   1E 0B FFFFFF84 00 FFFFFF83 50 14 01 09 
  minor version: 0
  major version: 49
  Constant pool:
Asciz	SourceFile;
Asciz	Flags.scala;
Asciz	pickledListOrder;
Asciz	Lscala/collection/immutable/List;;
Asciz	Lscala/collection/immutable/List<Ljava/lang/Long;>;;
Asciz	Signature;
Asciz	p2r;
Asciz	[I;
Asciz	r2p;
Asciz	PickledFlags;
Asciz	J;
Asciz	PKL_MASK;
Asciz	I;
Asciz	INTERFACE_PKL;
Asciz	MODULE_PKL;
Asciz	METHOD_PKL;
Asciz	DEFERRED_PKL;
Asciz	ABSTRACT_PKL;
Asciz	CASE_PKL;
Asciz	OVERRIDE_PKL;
Asciz	SEALED_PKL;
Asciz	PROTECTED_PKL;
Asciz	PRIVATE_PKL;
Asciz	FINAL_PKL;
Asciz	IMPLICIT_PKL;
Asciz	VBRIDGE;
Asciz	DEFAULTINIT;
Asciz	SPECIALIZED;
Asciz	LOCKED;
Asciz	TRANS_FLAG;
Asciz	PRESUPER;
Asciz	IMPLCLASS;
Asciz	EXPANDEDNAME;
Asciz	EXISTENTIAL;
Asciz	MIXEDIN;
Asciz	LIFTED;
Asciz	OVERLOADED;
Asciz	IS_ERROR;
Asciz	LAZY;
Asciz	MONOMORPHIC;
Asciz	SYNTHETICMETH;
Asciz	MODULEVAR;
Asciz	PARAMACCESSOR;
Asciz	SUPERACCESSOR;
Asciz	ACCESSOR;
Asciz	BRIDGE;
Asciz	DEFAULTPARAM;
Asciz	TRAIT;
Asciz	CASEACCESSOR;
Asciz	STATIC;
Asciz	STABLE;
Asciz	SYNTHETIC;
Asciz	JAVA;
Asciz	LOCAL;
Asciz	ABSOVERRIDE;
Asciz	INCONSTRUCTOR;
Asciz	LABEL;
Asciz	CONTRAVARIANT;
Asciz	BYNAMEPARAM;
Asciz	CAPTURED;
Asciz	COVARIANT;
Asciz	PACKAGE;
Asciz	PARAM;
Asciz	MUTABLE;
Asciz	INTERFACE;
Asciz	MODULE;
Asciz	METHOD;
Asciz	DEFERRED;
Asciz	ABSTRACT;
Asciz	CASE;
Asciz	OVERRIDE;
Asciz	SEALED;
Asciz	PROTECTED;
Asciz	PRIVATE;
Asciz	FINAL;
Asciz	IMPLICIT;
Asciz	()I;
Asciz	Code;
int	512;
Asciz	LineNumberTable;
int	32;
int	1024;
int	2048;
int	8;
int	16;
int	64;
int	256;
int	128;
int	4096;
int	8192;
int	16384;
int	65536;
int	131072;
int	262144;
int	524288;
int	1048576;
int	2097152;
int	4194304;
int	8388608;
int	16777216;
int	33554432;
int	67108864;
int	134217728;
int	268435456;
int	536870912;
int	1073741824;
Asciz	()J;
long	2147483648l;
long	4294967296l;
long	8589934592l;
long	17179869184l;
long	34359738368l;
long	68719476736l;
long	137438953472l;
long	274877906944l;
long	549755813888l;
long	1099511627776l;
long	2199023255552l;
long	4398046511104l;
int	4095;
Asciz	scala/reflect/generic/Flags;
class	scala/reflect/generic/Flags
NameAndType	PickledFlags:J
Field	scala/reflect/generic/Flags.PickledFlags:J
Asciz	()[I;
NameAndType	r2p:[I
Field	scala/reflect/generic/Flags.r2p:[I
NameAndType	p2r:[I
Field	scala/reflect/generic/Flags.p2r:[I
Asciz	rawFlagsToPickled;
Asciz	(J)J;
NameAndType	r2p:()[I
Method	scala/reflect/generic/Flags.r2p:()[I
Asciz	this;
Asciz	Lscala/reflect/generic/Flags;;
Asciz	flags;
Asciz	LocalVariableTable;
Asciz	pickledToRawFlags;
NameAndType	p2r:()[I
Method	scala/reflect/generic/Flags.p2r:()[I
Asciz	pflags;
Asciz	()Lscala/collection/immutable/List;;
NameAndType	pickledListOrder:Lscala/collection/immutable/List;
Field	scala/reflect/generic/Flags.pickledListOrder:Lscala/collection/immutable/List;
Asciz	()Lscala/collection/immutable/List<Ljava/lang/Long;>;;
Asciz	rawFlagsToPickledAux$1;
Asciz	(I)I;
Asciz	pickledToRawFlagsAux$1;
Asciz	findBit$1;
Asciz	(J)I;
int	62;
Asciz	java/lang/AssertionError;
class	java/lang/AssertionError
Asciz	<init>;
Asciz	()V;
NameAndType	"<init>":()V
Method	java/lang/AssertionError."<init>":()V
Asciz	m;
Asciz	mask;
Asciz	i;
Asciz	java/lang/Object;
class	java/lang/Object
Method	java/lang/Object."<init>":()V
long	4294967295l;
NameAndType	rawFlagsToPickledAux$1:(I)I
Method	scala/reflect/generic/Flags.rawFlagsToPickledAux$1:(I)I
NameAndType	pickledToRawFlagsAux$1:(I)I
Method	scala/reflect/generic/Flags.pickledToRawFlagsAux$1:(I)I
int	63;
NameAndType	findBit$1:(J)I
Method	scala/reflect/generic/Flags.findBit$1:(J)I
long	512l;
long	2l;
long	32l;
long	4l;
long	8l;
long	16l;
long	1024l;
long	64l;
long	2048l;
long	128l;
long	256l;
long	4096l;
Asciz	scala/Predef$;
class	scala/Predef$
Asciz	MODULE$;
Asciz	Lscala/Predef$;;
NameAndType	MODULE$:Lscala/Predef$;
Field	scala/Predef$.MODULE$:Lscala/Predef$;
Asciz	longArrayOps;
Asciz	([J)Lscala/collection/mutable/ArrayOps;;
NameAndType	longArrayOps:([J)Lscala/collection/mutable/ArrayOps;
Method	scala/Predef$.longArrayOps:([J)Lscala/collection/mutable/ArrayOps;
Asciz	scala/collection/TraversableLike;
class	scala/collection/TraversableLike
Asciz	toList;
NameAndType	toList:()Lscala/collection/immutable/List;
InterfaceMethod	scala/collection/TraversableLike.toList:()Lscala/collection/immutable/List;
Asciz	v;
Asciz	[J;
Asciz	ScalaSig;
Asciz	scala/ScalaObject;
class	scala/ScalaObject

{
private final scala.collection.immutable.List pickledListOrder;
  Signature: Lscala/collection/immutable/List;
  Signature: length = 0x2
   00 05 

private final int[] p2r;
  Signature: [I

private final int[] r2p;
  Signature: [I

private final long PickledFlags;
  Signature: J

private final int PKL_MASK;
  Signature: I

private final int INTERFACE_PKL;
  Signature: I

private final int MODULE_PKL;
  Signature: I

private final int METHOD_PKL;
  Signature: I

private final int DEFERRED_PKL;
  Signature: I

private final int ABSTRACT_PKL;
  Signature: I

private final int CASE_PKL;
  Signature: I

private final int OVERRIDE_PKL;
  Signature: I

private final int SEALED_PKL;
  Signature: I

private final int PROTECTED_PKL;
  Signature: I

private final int PRIVATE_PKL;
  Signature: I

private final int FINAL_PKL;
  Signature: I

private final int IMPLICIT_PKL;
  Signature: I

private final long VBRIDGE;
  Signature: J

private final long DEFAULTINIT;
  Signature: J

private final long SPECIALIZED;
  Signature: J

private final long LOCKED;
  Signature: J

private final long TRANS_FLAG;
  Signature: J

private final long PRESUPER;
  Signature: J

private final long IMPLCLASS;
  Signature: J

private final long EXPANDEDNAME;
  Signature: J

private final long EXISTENTIAL;
  Signature: J

private final long MIXEDIN;
  Signature: J

private final long LIFTED;
  Signature: J

private final long OVERLOADED;
  Signature: J

private final long IS_ERROR;
  Signature: J

private final long LAZY;
  Signature: J

private final int MONOMORPHIC;
  Signature: I

private final int SYNTHETICMETH;
  Signature: I

private final int MODULEVAR;
  Signature: I

private final int PARAMACCESSOR;
  Signature: I

private final int SUPERACCESSOR;
  Signature: I

private final int ACCESSOR;
  Signature: I

private final int BRIDGE;
  Signature: I

private final int DEFAULTPARAM;
  Signature: I

private final int TRAIT;
  Signature: I

private final int CASEACCESSOR;
  Signature: I

private final int STATIC;
  Signature: I

private final int STABLE;
  Signature: I

private final int SYNTHETIC;
  Signature: I

private final int JAVA;
  Signature: I

private final int LOCAL;
  Signature: I

private final int ABSOVERRIDE;
  Signature: I

private final int INCONSTRUCTOR;
  Signature: I

private final int LABEL;
  Signature: I

private final int CONTRAVARIANT;
  Signature: I

private final int BYNAMEPARAM;
  Signature: I

private final int CAPTURED;
  Signature: I

private final int COVARIANT;
  Signature: I

private final int PACKAGE;
  Signature: I

private final int PARAM;
  Signature: I

private final int MUTABLE;
  Signature: I

private final int INTERFACE;
  Signature: I

private final int MODULE;
  Signature: I

private final int METHOD;
  Signature: I

private final int DEFERRED;
  Signature: I

private final int ABSTRACT;
  Signature: I

private final int CASE;
  Signature: I

private final int OVERRIDE;
  Signature: I

private final int SEALED;
  Signature: I

private final int PROTECTED;
  Signature: I

private final int PRIVATE;
  Signature: I

private final int FINAL;
  Signature: I

private final int IMPLICIT;
  Signature: I

public final int IMPLICIT();
  Signature: ()I
  Code:
   Stack=1, Locals=1, Args_size=1
	ldc	int 512
	ireturn
  Labels:

public final int FINAL();
  Signature: ()I
  Code:
   Stack=1, Locals=1, Args_size=1
	ldc	int 32
	ireturn
  Labels:

public final int PRIVATE();
  Signature: ()I
  Code:
   Stack=1, Locals=1, Args_size=1
	iconst_4
	ireturn
  Labels:

public final int PROTECTED();
  Signature: ()I
  Code:
   Stack=1, Locals=1, Args_size=1
	iconst_1
	ireturn
  Labels:

public final int SEALED();
  Signature: ()I
  Code:
   Stack=1, Locals=1, Args_size=1
	ldc	int 1024
	ireturn
  Labels:

public final int OVERRIDE();
  Signature: ()I
  Code:
   Stack=1, Locals=1, Args_size=1
	iconst_2
	ireturn
  Labels:

public final int CASE();
  Signature: ()I
  Code:
   Stack=1, Locals=1, Args_size=1
	ldc	int 2048
	ireturn
  Labels:

public final int ABSTRACT();
  Signature: ()I
  Code:
   Stack=1, Locals=1, Args_size=1
	ldc	int 8
	ireturn
  Labels:

public final int DEFERRED();
  Signature: ()I
  Code:
   Stack=1, Locals=1, Args_size=1
	ldc	int 16
	ireturn
  Labels:

public final int METHOD();
  Signature: ()I
  Code:
   Stack=1, Locals=1, Args_size=1
	ldc	int 64
	ireturn
  Labels:

public final int MODULE();
  Signature: ()I
  Code:
   Stack=1, Locals=1, Args_size=1
	ldc	int 256
	ireturn
  Labels:

public final int INTERFACE();
  Signature: ()I
  Code:
   Stack=1, Locals=1, Args_size=1
	ldc	int 128
	ireturn
  Labels:

public final int MUTABLE();
  Signature: ()I
  Code:
   Stack=1, Locals=1, Args_size=1
	ldc	int 4096
	ireturn
  Labels:

public final int PARAM();
  Signature: ()I
  Code:
   Stack=1, Locals=1, Args_size=1
	ldc	int 8192
	ireturn
  Labels:

public final int PACKAGE();
  Signature: ()I
  Code:
   Stack=1, Locals=1, Args_size=1
	ldc	int 16384
	ireturn
  Labels:

public final int COVARIANT();
  Signature: ()I
  Code:
   Stack=1, Locals=1, Args_size=1
	ldc	int 65536
	ireturn
  Labels:

public final int CAPTURED();
  Signature: ()I
  Code:
   Stack=1, Locals=1, Args_size=1
	ldc	int 65536
	ireturn
  Labels:

public final int BYNAMEPARAM();
  Signature: ()I
  Code:
   Stack=1, Locals=1, Args_size=1
	ldc	int 65536
	ireturn
  Labels:

public final int CONTRAVARIANT();
  Signature: ()I
  Code:
   Stack=1, Locals=1, Args_size=1
	ldc	int 131072
	ireturn
  Labels:

public final int LABEL();
  Signature: ()I
  Code:
   Stack=1, Locals=1, Args_size=1
	ldc	int 131072
	ireturn
  Labels:

public final int INCONSTRUCTOR();
  Signature: ()I
  Code:
   Stack=1, Locals=1, Args_size=1
	ldc	int 131072
	ireturn
  Labels:

public final int ABSOVERRIDE();
  Signature: ()I
  Code:
   Stack=1, Locals=1, Args_size=1
	ldc	int 262144
	ireturn
  Labels:

public final int LOCAL();
  Signature: ()I
  Code:
   Stack=1, Locals=1, Args_size=1
	ldc	int 524288
	ireturn
  Labels:

public final int JAVA();
  Signature: ()I
  Code:
   Stack=1, Locals=1, Args_size=1
	ldc	int 1048576
	ireturn
  Labels:

public final int SYNTHETIC();
  Signature: ()I
  Code:
   Stack=1, Locals=1, Args_size=1
	ldc	int 2097152
	ireturn
  Labels:

public final int STABLE();
  Signature: ()I
  Code:
   Stack=1, Locals=1, Args_size=1
	ldc	int 4194304
	ireturn
  Labels:

public final int STATIC();
  Signature: ()I
  Code:
   Stack=1, Locals=1, Args_size=1
	ldc	int 8388608
	ireturn
  Labels:

public final int CASEACCESSOR();
  Signature: ()I
  Code:
   Stack=1, Locals=1, Args_size=1
	ldc	int 16777216
	ireturn
  Labels:

public final int TRAIT();
  Signature: ()I
  Code:
   Stack=1, Locals=1, Args_size=1
	ldc	int 33554432
	ireturn
  Labels:

public final int DEFAULTPARAM();
  Signature: ()I
  Code:
   Stack=1, Locals=1, Args_size=1
	ldc	int 33554432
	ireturn
  Labels:

public final int BRIDGE();
  Signature: ()I
  Code:
   Stack=1, Locals=1, Args_size=1
	ldc	int 67108864
	ireturn
  Labels:

public final int ACCESSOR();
  Signature: ()I
  Code:
   Stack=1, Locals=1, Args_size=1
	ldc	int 134217728
	ireturn
  Labels:

public final int SUPERACCESSOR();
  Signature: ()I
  Code:
   Stack=1, Locals=1, Args_size=1
	ldc	int 268435456
	ireturn
  Labels:

public final int PARAMACCESSOR();
  Signature: ()I
  Code:
   Stack=1, Locals=1, Args_size=1
	ldc	int 536870912
	ireturn
  Labels:

public final int MODULEVAR();
  Signature: ()I
  Code:
   Stack=1, Locals=1, Args_size=1
	ldc	int 1073741824
	ireturn
  Labels:

public final int SYNTHETICMETH();
  Signature: ()I
  Code:
   Stack=1, Locals=1, Args_size=1
	ldc	int 1073741824
	ireturn
  Labels:

public final int MONOMORPHIC();
  Signature: ()I
  Code:
   Stack=1, Locals=1, Args_size=1
	ldc	int 1073741824
	ireturn
  Labels:

public final long LAZY();
  Signature: ()J
  Code:
   Stack=2, Locals=1, Args_size=1
	ldc2_w	long 2147483648l
	lreturn
  Labels:

public final long IS_ERROR();
  Signature: ()J
  Code:
   Stack=2, Locals=1, Args_size=1
	ldc2_w	long 4294967296l
	lreturn
  Labels:

public final long OVERLOADED();
  Signature: ()J
  Code:
   Stack=2, Locals=1, Args_size=1
	ldc2_w	long 8589934592l
	lreturn
  Labels:

public final long LIFTED();
  Signature: ()J
  Code:
   Stack=2, Locals=1, Args_size=1
	ldc2_w	long 17179869184l
	lreturn
  Labels:

public final long MIXEDIN();
  Signature: ()J
  Code:
   Stack=2, Locals=1, Args_size=1
	ldc2_w	long 34359738368l
	lreturn
  Labels:

public final long EXISTENTIAL();
  Signature: ()J
  Code:
   Stack=2, Locals=1, Args_size=1
	ldc2_w	long 34359738368l
	lreturn
  Labels:

public final long EXPANDEDNAME();
  Signature: ()J
  Code:
   Stack=2, Locals=1, Args_size=1
	ldc2_w	long 68719476736l
	lreturn
  Labels:

public final long IMPLCLASS();
  Signature: ()J
  Code:
   Stack=2, Locals=1, Args_size=1
	ldc2_w	long 137438953472l
	lreturn
  Labels:

public final long PRESUPER();
  Signature: ()J
  Code:
   Stack=2, Locals=1, Args_size=1
	ldc2_w	long 137438953472l
	lreturn
  Labels:

public final long TRANS_FLAG();
  Signature: ()J
  Code:
   Stack=2, Locals=1, Args_size=1
	ldc2_w	long 274877906944l
	lreturn
  Labels:

public final long LOCKED();
  Signature: ()J
  Code:
   Stack=2, Locals=1, Args_size=1
	ldc2_w	long 549755813888l
	lreturn
  Labels:

public final long SPECIALIZED();
  Signature: ()J
  Code:
   Stack=2, Locals=1, Args_size=1
	ldc2_w	long 1099511627776l
	lreturn
  Labels:

public final long DEFAULTINIT();
  Signature: ()J
  Code:
   Stack=2, Locals=1, Args_size=1
	ldc2_w	long 2199023255552l
	lreturn
  Labels:

public final long VBRIDGE();
  Signature: ()J
  Code:
   Stack=2, Locals=1, Args_size=1
	ldc2_w	long 4398046511104l
	lreturn
  Labels:

private final int IMPLICIT_PKL();
  Signature: ()I
  Code:
   Stack=1, Locals=1, Args_size=1
	iconst_1
	ireturn
  Labels:

private final int FINAL_PKL();
  Signature: ()I
  Code:
   Stack=1, Locals=1, Args_size=1
	iconst_2
	ireturn
  Labels:

private final int PRIVATE_PKL();
  Signature: ()I
  Code:
   Stack=1, Locals=1, Args_size=1
	iconst_4
	ireturn
  Labels:

private final int PROTECTED_PKL();
  Signature: ()I
  Code:
   Stack=1, Locals=1, Args_size=1
	ldc	int 8
	ireturn
  Labels:

private final int SEALED_PKL();
  Signature: ()I
  Code:
   Stack=1, Locals=1, Args_size=1
	ldc	int 16
	ireturn
  Labels:

private final int OVERRIDE_PKL();
  Signature: ()I
  Code:
   Stack=1, Locals=1, Args_size=1
	ldc	int 32
	ireturn
  Labels:

private final int CASE_PKL();
  Signature: ()I
  Code:
   Stack=1, Locals=1, Args_size=1
	ldc	int 64
	ireturn
  Labels:

private final int ABSTRACT_PKL();
  Signature: ()I
  Code:
   Stack=1, Locals=1, Args_size=1
	ldc	int 128
	ireturn
  Labels:

private final int DEFERRED_PKL();
  Signature: ()I
  Code:
   Stack=1, Locals=1, Args_size=1
	ldc	int 256
	ireturn
  Labels:

private final int METHOD_PKL();
  Signature: ()I
  Code:
   Stack=1, Locals=1, Args_size=1
	ldc	int 512
	ireturn
  Labels:

private final int MODULE_PKL();
  Signature: ()I
  Code:
   Stack=1, Locals=1, Args_size=1
	ldc	int 1024
	ireturn
  Labels:

private final int INTERFACE_PKL();
  Signature: ()I
  Code:
   Stack=1, Locals=1, Args_size=1
	ldc	int 2048
	ireturn
  Labels:

private final int PKL_MASK();
  Signature: ()I
  Code:
   Stack=1, Locals=1, Args_size=1
	ldc	int 4095
	ireturn
  Labels:

public final long PickledFlags();
  Signature: ()J
  Code:
   Stack=2, Locals=1, Args_size=1
	aload_0
	getfield	Field PickledFlags:J
	lreturn
  Labels:

private int[] r2p();
  Signature: ()[I
  Code:
   Stack=1, Locals=1, Args_size=1
	aload_0
	getfield	Field r2p:[I
	areturn
  Labels:

private int[] p2r();
  Signature: ()[I
  Code:
   Stack=1, Locals=1, Args_size=1
	aload_0
	getfield	Field p2r:[I
	areturn
  Labels:

public long rawFlagsToPickled(long);
  Signature: (J)J
  Code:
   Stack=5, Locals=3, Args_size=2
	lload_1
	ldc	int 4095
	iconst_m1
	ixor
	i2l
	land
	aload_0
	invokespecial	Method r2p:()[I
	lload_1
	l2i
	ldc	int 4095
	iand
	iaload
	i2l
	lor
	lreturn
  Labels:
  LocalVariableTable: 
   Start  Length  Slot  Name   Signature
   0      20      0    this       Lscala/reflect/generic/Flags;
   0      20      1    flags       J


public long pickledToRawFlags(long);
  Signature: (J)J
  Code:
   Stack=5, Locals=3, Args_size=2
	lload_1
	ldc	int 4095
	iconst_m1
	ixor
	i2l
	land
	aload_0
	invokespecial	Method p2r:()[I
	lload_1
	l2i
	ldc	int 4095
	iand
	iaload
	i2l
	lor
	lreturn
  Labels:
  LocalVariableTable: 
   Start  Length  Slot  Name   Signature
   0      20      0    this       Lscala/reflect/generic/Flags;
   0      20      1    pflags       J


public scala.collection.immutable.List pickledListOrder();
  Signature: ()Lscala/collection/immutable/List;
  Code:
   Stack=1, Locals=1, Args_size=1
	aload_0
	getfield	Field pickledListOrder:Lscala/collection/immutable/List;
	areturn
  Labels:
  Signature: length = 0x2
   00 FFFFFF9D 

private final int rawFlagsToPickledAux$1(int);
  Signature: (I)I
  Code:
   Stack=2, Locals=3, Args_size=2
	iconst_0
	istore_2
	iload_1
	ldc	int 512
	iand
	iconst_0
	if_icmpeq	l1 // iload_1
	iload_2
	iconst_1
	ior
	istore_2
l1	iload_1
	ldc	int 32
	iand
	iconst_0
	if_icmpeq	l2 // iload_1
	iload_2
	iconst_2
	ior
	istore_2
l2	iload_1
	iconst_4
	iand
	iconst_0
	if_icmpeq	l3 // iload_1
	iload_2
	iconst_4
	ior
	istore_2
l3	iload_1
	iconst_1
	iand
	iconst_0
	if_icmpeq	l4 // iload_1
	iload_2
	ldc	int 8
	ior
	istore_2
l4	iload_1
	ldc	int 1024
	iand
	iconst_0
	if_icmpeq	l5 // iload_1
	iload_2
	ldc	int 16
	ior
	istore_2
l5	iload_1
	iconst_2
	iand
	iconst_0
	if_icmpeq	l6 // iload_1
	iload_2
	ldc	int 32
	ior
	istore_2
l6	iload_1
	ldc	int 2048
	iand
	iconst_0
	if_icmpeq	l7 // iload_1
	iload_2
	ldc	int 64
	ior
	istore_2
l7	iload_1
	ldc	int 8
	iand
	iconst_0
	if_icmpeq	l8 // iload_1
	iload_2
	ldc	int 128
	ior
	istore_2
l8	iload_1
	ldc	int 16
	iand
	iconst_0
	if_icmpeq	l9 // iload_1
	iload_2
	ldc	int 256
	ior
	istore_2
l9	iload_1
	ldc	int 64
	iand
	iconst_0
	if_icmpeq	l10 // iload_1
	iload_2
	ldc	int 512
	ior
	istore_2
l10	iload_1
	ldc	int 256
	iand
	iconst_0
	if_icmpeq	l11 // iload_1
	iload_2
	ldc	int 1024
	ior
	istore_2
l11	iload_1
	ldc	int 128
	iand
	iconst_0
	if_icmpeq	l12 // iload_2
	iload_2
	ldc	int 2048
	ior
	istore_2
l12	iload_2
	ireturn
  Labels:
   	l1 = 14 // iload_1
   	l2 = 26 // iload_1
   	l3 = 37 // iload_1
   	l4 = 49 // iload_1
   	l5 = 62 // iload_1
   	l6 = 74 // iload_1
   	l7 = 87 // iload_1
   	l8 = 100 // iload_1
   	l9 = 113 // iload_1
   	l10 = 126 // iload_1
   	l11 = 139 // iload_1
   	l12 = 152 // iload_2
  LocalVariableTable: 
   Start  Length  Slot  Name   Signature
   0      154      0    this       Lscala/reflect/generic/Flags;
   0      154      1    flags       I
   2      151      2    pflags       I


private final int pickledToRawFlagsAux$1(int);
  Signature: (I)I
  Code:
   Stack=2, Locals=3, Args_size=2
	iconst_0
	istore_2
	iload_1
	iconst_1
	iand
	iconst_0
	if_icmpeq	l1 // iload_1
	iload_2
	ldc	int 512
	ior
	istore_2
l1	iload_1
	iconst_2
	iand
	iconst_0
	if_icmpeq	l2 // iload_1
	iload_2
	ldc	int 32
	ior
	istore_2
l2	iload_1
	iconst_4
	iand
	iconst_0
	if_icmpeq	l3 // iload_1
	iload_2
	iconst_4
	ior
	istore_2
l3	iload_1
	ldc	int 8
	iand
	iconst_0
	if_icmpeq	l4 // iload_1
	iload_2
	iconst_1
	ior
	istore_2
l4	iload_1
	ldc	int 16
	iand
	iconst_0
	if_icmpeq	l5 // iload_1
	iload_2
	ldc	int 1024
	ior
	istore_2
l5	iload_1
	ldc	int 32
	iand
	iconst_0
	if_icmpeq	l6 // iload_1
	iload_2
	iconst_2
	ior
	istore_2
l6	iload_1
	ldc	int 64
	iand
	iconst_0
	if_icmpeq	l7 // iload_1
	iload_2
	ldc	int 2048
	ior
	istore_2
l7	iload_1
	ldc	int 128
	iand
	iconst_0
	if_icmpeq	l8 // iload_1
	iload_2
	ldc	int 8
	ior
	istore_2
l8	iload_1
	ldc	int 256
	iand
	iconst_0
	if_icmpeq	l9 // iload_1
	iload_2
	ldc	int 16
	ior
	istore_2
l9	iload_1
	ldc	int 512
	iand
	iconst_0
	if_icmpeq	l10 // iload_1
	iload_2
	ldc	int 64
	ior
	istore_2
l10	iload_1
	ldc	int 1024
	iand
	iconst_0
	if_icmpeq	l11 // iload_1
	iload_2
	ldc	int 256
	ior
	istore_2
l11	iload_1
	ldc	int 2048
	iand
	iconst_0
	if_icmpeq	l12 // iload_2
	iload_2
	ldc	int 128
	ior
	istore_2
l12	iload_2
	ireturn
  Labels:
   	l1 = 14 // iload_1
   	l2 = 26 // iload_1
   	l3 = 37 // iload_1
   	l4 = 49 // iload_1
   	l5 = 62 // iload_1
   	l6 = 74 // iload_1
   	l7 = 87 // iload_1
   	l8 = 100 // iload_1
   	l9 = 113 // iload_1
   	l10 = 126 // iload_1
   	l11 = 139 // iload_1
   	l12 = 152 // iload_2
  LocalVariableTable: 
   Start  Length  Slot  Name   Signature
   0      154      0    this       Lscala/reflect/generic/Flags;
   0      154      1    pflags       I
   2      151      2    flags       I


private final int findBit$1(long);
  Signature: (J)I
  Code:
   Stack=4, Locals=6, Args_size=2
	lload_1
	lstore_3
	iconst_0
	istore	5
l3	iload	5
	ldc	int 62
	if_icmpgt	l1 // new
	lload_3
	lconst_1
	land
	lconst_1
	lcmp
	ifne	l2 // lload_3
	iload	5
	ireturn
l2	lload_3
	iconst_1
	lshr
	lstore_3
	iload	5
	iconst_1
	iadd
	istore	5
	goto	l3 // iload
l1	new	class java/lang/AssertionError
	dup
	invokespecial	Method java/lang/AssertionError."<init>":()V
	athrow
  Labels:
   	l3 = 5 // iload
   	l2 = 23 // lload_3
   	l1 = 36 // new
  LocalVariableTable: 
   Start  Length  Slot  Name   Signature
   0      44      0    this       Lscala/reflect/generic/Flags;
   0      44      1    m       J
   2      42      3    mask       J
   5      39      5    i       I


public scala.reflect.generic.Flags();
  Signature: ()V
  Code:
   Stack=6, Locals=7, Args_size=1
	aload_0
	invokespecial	Method java/lang/Object."<init>":()V
	aload_0
	ldc2_w	long 4294967295l
	putfield	Field PickledFlags:J
	aload_0
	ldc	int 4096
	newarray int
	astore_1
	iconst_0
	istore_2
l2	iload_2
	ldc	int 4095
	if_icmpgt	l1 // aload_1
	aload_1
	iload_2
	aload_0
	iload_2
	invokespecial	Method rawFlagsToPickledAux$1:(I)I
	iastore
	iload_2
	iconst_1
	iadd
	istore_2
	goto	l2 // iload_2
l1	aload_1
	putfield	Field r2p:[I
	aload_0
	ldc	int 4096
	newarray int
	astore_3
	iconst_0
	istore	4
l4	iload	4
	ldc	int 4095
	if_icmpgt	l3 // aload_3
	aload_3
	iload	4
	aload_0
	iload	4
	invokespecial	Method pickledToRawFlagsAux$1:(I)I
	iastore
	iload	4
	iconst_1
	iadd
	istore	4
	goto	l4 // iload
l3	aload_3
	putfield	Field p2r:[I
	aload_0
	ldc	int 63
	newarray long
	astore	5
	aload	5
	aload_0
	lconst_1
	invokespecial	Method findBit$1:(J)I
	ldc2_w	long 512l
	lastore
	aload	5
	aload_0
	ldc2_w	long 2l
	invokespecial	Method findBit$1:(J)I
	ldc2_w	long 32l
	lastore
	aload	5
	aload_0
	ldc2_w	long 4l
	invokespecial	Method findBit$1:(J)I
	ldc2_w	long 4l
	lastore
	aload	5
	aload_0
	ldc2_w	long 8l
	invokespecial	Method findBit$1:(J)I
	lconst_1
	lastore
	aload	5
	aload_0
	ldc2_w	long 16l
	invokespecial	Method findBit$1:(J)I
	ldc2_w	long 1024l
	lastore
	aload	5
	aload_0
	ldc2_w	long 32l
	invokespecial	Method findBit$1:(J)I
	ldc2_w	long 2l
	lastore
	aload	5
	aload_0
	ldc2_w	long 64l
	invokespecial	Method findBit$1:(J)I
	ldc2_w	long 2048l
	lastore
	aload	5
	aload_0
	ldc2_w	long 128l
	invokespecial	Method findBit$1:(J)I
	ldc2_w	long 8l
	lastore
	aload	5
	aload_0
	ldc2_w	long 256l
	invokespecial	Method findBit$1:(J)I
	ldc2_w	long 16l
	lastore
	aload	5
	aload_0
	ldc2_w	long 512l
	invokespecial	Method findBit$1:(J)I
	ldc2_w	long 64l
	lastore
	aload	5
	aload_0
	ldc2_w	long 1024l
	invokespecial	Method findBit$1:(J)I
	ldc2_w	long 256l
	lastore
	aload	5
	aload_0
	ldc2_w	long 2048l
	invokespecial	Method findBit$1:(J)I
	ldc2_w	long 128l
	lastore
	aload_0
	ldc2_w	long 4096l
	invokespecial	Method findBit$1:(J)I
	istore	6
l6	iload	6
	ldc	int 62
	if_icmpgt	l5 // getstatic
	aload	5
	iload	6
	lconst_1
	iload	6
	lshl
	lastore
	iload	6
	iconst_1
	iadd
	istore	6
	goto	l6 // iload
l5	getstatic	Field scala/Predef$.MODULE$:Lscala/Predef$;
	aload	5
	invokevirtual	Method scala/Predef$.longArrayOps:([J)Lscala/collection/mutable/ArrayOps;
	invokeinterface	InterfaceMethod scala/collection/TraversableLike.toList:()Lscala/collection/immutable/List;
	putfield	Field pickledListOrder:Lscala/collection/immutable/List;
	return
  Labels:
   	l2 = 19 // iload_2
   	l1 = 40 // aload_1
   	l4 = 53 // iload
   	l3 = 79 // aload_3
   	l6 = 251 // iload
   	l5 = 276 // getstatic
  LocalVariableTable: 
   Start  Length  Slot  Name   Signature
   0      293      0    this       Lscala/reflect/generic/Flags;
   17      24      1    v       [I
   19      22      2    i       I
   50      30      3    v       [I
   53      27      4    i       I
   90      199      5    v       [J
   251      38      6    i       I


}

