Compiled from "PickleBuffer.scala"
public final class scala.reflect.generic.PickleBuffer$$anonfun$createIndex$1 extends scala.runtime.AbstractFunction1 implements java.io.Serializable
  SourceFile: "PickleBuffer.scala"
  Scala: length = 0x
   
  InnerClass: 
   public final $anonfun$createIndex$1=class scala/reflect/generic/PickleBuffer$$anonfun$createIndex$1 of class scala/reflect/generic/PickleBuffer
  minor version: 0
  major version: 49
  Constant pool:
Asciz	SourceFile;
Asciz	PickleBuffer.scala;
Asciz	<clinit>;
Asciz	()V;
Asciz	Code;
Asciz	serialVersionUID;
Asciz	J;
Asciz	scala/reflect/generic/PickleBuffer$$anonfun$createIndex$1;
class	scala/reflect/generic/PickleBuffer$$anonfun$createIndex$1
NameAndType	serialVersionUID:J
Field	scala/reflect/generic/PickleBuffer$$anonfun$createIndex$1.serialVersionUID:J
Asciz	index$1;
Asciz	[I;
Asciz	$outer;
Asciz	Lscala/reflect/generic/PickleBuffer;;
Asciz	apply;
Asciz	(I)V;
Asciz	LineNumberTable;
NameAndType	index$1:[I
Field	scala/reflect/generic/PickleBuffer$$anonfun$createIndex$1.index$1:[I
NameAndType	$outer:Lscala/reflect/generic/PickleBuffer;
Field	scala/reflect/generic/PickleBuffer$$anonfun$createIndex$1.$outer:Lscala/reflect/generic/PickleBuffer;
Asciz	scala/reflect/generic/PickleBuffer;
class	scala/reflect/generic/PickleBuffer
Asciz	readIndex;
Asciz	()I;
NameAndType	readIndex:()I
Method	scala/reflect/generic/PickleBuffer.readIndex:()I
Asciz	readByte;
NameAndType	readByte:()I
Method	scala/reflect/generic/PickleBuffer.readByte:()I
Asciz	readNat;
NameAndType	readNat:()I
Method	scala/reflect/generic/PickleBuffer.readNat:()I
Asciz	readIndex_$eq;
NameAndType	readIndex_$eq:(I)V
Method	scala/reflect/generic/PickleBuffer.readIndex_$eq:(I)V
Asciz	this;
Asciz	Lscala/reflect/generic/PickleBuffer$$anonfun$createIndex$1;;
Asciz	i;
Asciz	I;
Asciz	LocalVariableTable;
Asciz	(Ljava/lang/Object;)Ljava/lang/Object;;
Asciz	scala/runtime/BoxesRunTime;
class	scala/runtime/BoxesRunTime
Asciz	unboxToInt;
Asciz	(Ljava/lang/Object;)I;
NameAndType	unboxToInt:(Ljava/lang/Object;)I
Method	scala/runtime/BoxesRunTime.unboxToInt:(Ljava/lang/Object;)I
NameAndType	apply:(I)V
Method	scala/reflect/generic/PickleBuffer$$anonfun$createIndex$1.apply:(I)V
Asciz	scala/runtime/BoxedUnit;
class	scala/runtime/BoxedUnit
Asciz	UNIT;
Asciz	Lscala/runtime/BoxedUnit;;
NameAndType	UNIT:Lscala/runtime/BoxedUnit;
Field	scala/runtime/BoxedUnit.UNIT:Lscala/runtime/BoxedUnit;
Asciz	v1;
Asciz	Ljava/lang/Object;;
Asciz	<init>;
Asciz	(Lscala/reflect/generic/PickleBuffer;[I)V;
Asciz	java/lang/NullPointerException;
class	java/lang/NullPointerException
NameAndType	"<init>":()V
Method	java/lang/NullPointerException."<init>":()V
Asciz	scala/runtime/AbstractFunction1;
class	scala/runtime/AbstractFunction1
Method	scala/runtime/AbstractFunction1."<init>":()V
Asciz	Scala;
Asciz	InnerClasses;
Asciz	$anonfun$createIndex$1;
Asciz	java/io/Serializable;
class	java/io/Serializable

{
public static final long serialVersionUID;
  Signature: J

private final int[] index$1;
  Signature: [I

private final scala.reflect.generic.PickleBuffer $outer;
  Signature: Lscala/reflect/generic/PickleBuffer;

public static {};
  Signature: ()V
  Code:
   Stack=2, Locals=0, Args_size=0
	lconst_0
	putstatic	Field serialVersionUID:J
	return
  Labels:

public final void apply(int);
  Signature: (I)V
  Code:
   Stack=3, Locals=2, Args_size=2
	aload_0
	getfield	Field index$1:[I
	iload_1
	aload_0
	getfield	Field $outer:Lscala/reflect/generic/PickleBuffer;
	invokevirtual	Method scala/reflect/generic/PickleBuffer.readIndex:()I
	iastore
	aload_0
	getfield	Field $outer:Lscala/reflect/generic/PickleBuffer;
	invokevirtual	Method scala/reflect/generic/PickleBuffer.readByte:()I
	pop
	aload_0
	getfield	Field $outer:Lscala/reflect/generic/PickleBuffer;
	aload_0
	getfield	Field $outer:Lscala/reflect/generic/PickleBuffer;
	invokevirtual	Method scala/reflect/generic/PickleBuffer.readNat:()I
	aload_0
	getfield	Field $outer:Lscala/reflect/generic/PickleBuffer;
	invokevirtual	Method scala/reflect/generic/PickleBuffer.readIndex:()I
	iadd
	invokevirtual	Method scala/reflect/generic/PickleBuffer.readIndex_$eq:(I)V
	return
  Labels:
  LocalVariableTable: 
   Start  Length  Slot  Name   Signature
   0      44      0    this       Lscala/reflect/generic/PickleBuffer$$anonfun$createIndex$1;
   0      44      1    i       I


public final java.lang.Object apply(java.lang.Object);
  Signature: (Ljava/lang/Object;)Ljava/lang/Object;
  Code:
   Stack=2, Locals=2, Args_size=2
	aload_0
	aload_1
	invokestatic	Method scala/runtime/BoxesRunTime.unboxToInt:(Ljava/lang/Object;)I
	invokevirtual	Method apply:(I)V
	getstatic	Field scala/runtime/BoxedUnit.UNIT:Lscala/runtime/BoxedUnit;
	areturn
  Labels:
  LocalVariableTable: 
   Start  Length  Slot  Name   Signature
   0      12      0    this       Lscala/reflect/generic/PickleBuffer$$anonfun$createIndex$1;
   0      12      1    v1       Ljava/lang/Object;


public scala.reflect.generic.PickleBuffer$$anonfun$createIndex$1(scala.reflect.generic.PickleBuffer, int[]);
  Signature: (Lscala/reflect/generic/PickleBuffer;[I)V
  Code:
   Stack=2, Locals=3, Args_size=3
	aload_1
	ifnonnull	l1 // aload_0
	new	class java/lang/NullPointerException
	dup
	invokespecial	Method java/lang/NullPointerException."<init>":()V
	athrow
l1	aload_0
	aload_1
	putfield	Field $outer:Lscala/reflect/generic/PickleBuffer;
	aload_0
	aload_2
	putfield	Field index$1:[I
	aload_0
	invokespecial	Method scala/runtime/AbstractFunction1."<init>":()V
	return
  Labels:
   	l1 = 12 // aload_0
  LocalVariableTable: 
   Start  Length  Slot  Name   Signature
   0      27      0    this       Lscala/reflect/generic/PickleBuffer$$anonfun$createIndex$1;
   0      27      1    $outer       Lscala/reflect/generic/PickleBuffer;


}

