Compiled from "PickleBuffer.scala"
public class scala.reflect.generic.PickleBuffer extends java.lang.Object implements scala.ScalaObject
  SourceFile: "PickleBuffer.scala"
  ScalaSig: length = 0x3
   05 00 00 
  RuntimeVisibleAnnotations: length = 0xB
   00 01 00 FFFFFFDA 00 01 00 05 73 00 FFFFFFDB 
  InnerClass: 
   public abstract ByOne=class scala/collection/immutable/Range$ByOne of class scala/collection/immutable/Range
   public final $anonfun$createIndex$1=class scala/reflect/generic/PickleBuffer$$anonfun$createIndex$1 of class scala/reflect/generic/PickleBuffer
   public final $anonfun$toIndexedSeq$1=class scala/reflect/generic/PickleBuffer$$anonfun$toIndexedSeq$1 of class scala/reflect/generic/PickleBuffer
  minor version: 0
  major version: 49
  Constant pool:
Asciz	SourceFile;
Asciz	PickleBuffer.scala;
Asciz	scala$reflect$generic$PickleBuffer$$data;
Asciz	[B;
Asciz	bytes;
Asciz	readIndex;
Asciz	I;
Asciz	writeIndex;
Asciz	()[B;
Asciz	Code;
Asciz	LineNumberTable;
Asciz	scala/reflect/generic/PickleBuffer;
class	scala/reflect/generic/PickleBuffer
NameAndType	bytes:[B
Field	scala/reflect/generic/PickleBuffer.bytes:[B
Asciz	bytes_$eq;
Asciz	([B)V;
Asciz	()I;
NameAndType	readIndex:I
Field	scala/reflect/generic/PickleBuffer.readIndex:I
Asciz	readIndex_$eq;
Asciz	(I)V;
NameAndType	writeIndex:I
Field	scala/reflect/generic/PickleBuffer.writeIndex:I
Asciz	writeIndex_$eq;
Asciz	dble;
Asciz	()V;
NameAndType	bytes:()[B
Method	scala/reflect/generic/PickleBuffer.bytes:()[B
Asciz	scala/Array$;
class	scala/Array$
Asciz	MODULE$;
Asciz	Lscala/Array$;;
NameAndType	MODULE$:Lscala/Array$;
Field	scala/Array$.MODULE$:Lscala/Array$;
NameAndType	writeIndex:()I
Method	scala/reflect/generic/PickleBuffer.writeIndex:()I
Asciz	copy;
Asciz	(Ljava/lang/Object;ILjava/lang/Object;II)V;
NameAndType	copy:(Ljava/lang/Object;ILjava/lang/Object;II)V
Method	scala/Array$.copy:(Ljava/lang/Object;ILjava/lang/Object;II)V
NameAndType	bytes_$eq:([B)V
Method	scala/reflect/generic/PickleBuffer.bytes_$eq:([B)V
Asciz	this;
Asciz	Lscala/reflect/generic/PickleBuffer;;
Asciz	bytes1;
Asciz	LocalVariableTable;
Asciz	ensureCapacity;
NameAndType	dble:()V
Method	scala/reflect/generic/PickleBuffer.dble:()V
Asciz	capacity;
Asciz	writeByte;
NameAndType	writeIndex_$eq:(I)V
Method	scala/reflect/generic/PickleBuffer.writeIndex_$eq:(I)V
Asciz	b;
Asciz	writeNat;
long	4294967295l;
Asciz	writeLongNat;
Asciz	(J)V;
NameAndType	writeLongNat:(J)V
Method	scala/reflect/generic/PickleBuffer.writeLongNat:(J)V
Asciz	x;
int	7;
Asciz	writeNatPrefix$1;
NameAndType	writeNatPrefix$1:(J)V
Method	scala/reflect/generic/PickleBuffer.writeNatPrefix$1:(J)V
long	127l;
NameAndType	writeByte:(I)V
Method	scala/reflect/generic/PickleBuffer.writeByte:(I)V
Asciz	J;
Asciz	y;
Asciz	patchNat;
Asciz	(II)V;
int	127;
Asciz	patchNatPrefix$1;
NameAndType	patchNatPrefix$1:(II)V
Method	scala/reflect/generic/PickleBuffer.patchNatPrefix$1:(II)V
Asciz	pos$1;
Asciz	writeLong;
int	8;
long	255l;
NameAndType	writeLong:(J)V
Method	scala/reflect/generic/PickleBuffer.writeLong:(J)V
Asciz	z;
Asciz	peekByte;
NameAndType	readIndex:()I
Method	scala/reflect/generic/PickleBuffer.readIndex:()I
Asciz	readByte;
NameAndType	readIndex_$eq:(I)V
Method	scala/reflect/generic/PickleBuffer.readIndex_$eq:(I)V
Asciz	B;
Asciz	readNat;
Asciz	readLongNat;
Asciz	()J;
NameAndType	readLongNat:()J
Method	scala/reflect/generic/PickleBuffer.readLongNat:()J
NameAndType	readByte:()I
Method	scala/reflect/generic/PickleBuffer.readByte:()I
long	128l;
Asciz	readLong;
Asciz	(I)J;
int	255;
int	64;
Asciz	len;
Asciz	i;
Asciz	leading;
Asciz	toIndexedSeq;
Asciz	()Lscala/collection/IndexedSeq;;
NameAndType	readNat:()I
Method	scala/reflect/generic/PickleBuffer.readNat:()I
Asciz	scala/Tuple2;
class	scala/Tuple2
Asciz	scala/Predef$;
class	scala/Predef$
Asciz	Lscala/Predef$;;
NameAndType	MODULE$:Lscala/Predef$;
Field	scala/Predef$.MODULE$:Lscala/Predef$;
Asciz	[Ljava/lang/Object;;
class	"[Ljava/lang/Object;"
Asciz	refArrayOps;
Asciz	([Ljava/lang/Object;)Lscala/collection/mutable/ArrayOps;;
NameAndType	refArrayOps:([Ljava/lang/Object;)Lscala/collection/mutable/ArrayOps;
Method	scala/Predef$.refArrayOps:([Ljava/lang/Object;)Lscala/collection/mutable/ArrayOps;
Asciz	scala/collection/SeqLike;
class	scala/collection/SeqLike
Asciz	indices;
Asciz	()Lscala/collection/immutable/Range;;
NameAndType	indices:()Lscala/collection/immutable/Range;
InterfaceMethod	scala/collection/SeqLike.indices:()Lscala/collection/immutable/Range;
Asciz	scala/reflect/generic/PickleBuffer$$anonfun$toIndexedSeq$1;
class	scala/reflect/generic/PickleBuffer$$anonfun$toIndexedSeq$1
Asciz	<init>;
Asciz	(Lscala/reflect/generic/PickleBuffer;[Lscala/Tuple2;)V;
NameAndType	"<init>":(Lscala/reflect/generic/PickleBuffer;[Lscala/Tuple2;)V
Method	scala/reflect/generic/PickleBuffer$$anonfun$toIndexedSeq$1."<init>":(Lscala/reflect/generic/PickleBuffer;[Lscala/Tuple2;)V
Asciz	scala/collection/immutable/Range;
class	scala/collection/immutable/Range
Asciz	foreach$mVc$sp;
Asciz	(Lscala/Function1;)V;
NameAndType	foreach$mVc$sp:(Lscala/Function1;)V
Method	scala/collection/immutable/Range.foreach$mVc$sp:(Lscala/Function1;)V
Asciz	scala/collection/TraversableOnce;
class	scala/collection/TraversableOnce
Asciz	()Lscala/collection/mutable/IndexedSeq;;
NameAndType	toIndexedSeq:()Lscala/collection/mutable/IndexedSeq;
InterfaceMethod	scala/collection/TraversableOnce.toIndexedSeq:()Lscala/collection/mutable/IndexedSeq;
Asciz	saved;
Asciz	result$1;
Asciz	[Lscala/Tuple2;;
Asciz	()Lscala/collection/IndexedSeq<Lscala/Tuple2<Ljava/lang/Integer;[B>;>;;
Asciz	Signature;
Asciz	until;
Asciz	(ILscala/Function0;)Lscala/collection/immutable/List;;
Asciz	scala/collection/immutable/Nil$;
class	scala/collection/immutable/Nil$
Asciz	Lscala/collection/immutable/Nil$;;
NameAndType	MODULE$:Lscala/collection/immutable/Nil$;
Field	scala/collection/immutable/Nil$.MODULE$:Lscala/collection/immutable/Nil$;
Asciz	scala/Function0;
class	scala/Function0
Asciz	apply;
Asciz	()Ljava/lang/Object;;
NameAndType	apply:()Ljava/lang/Object;
InterfaceMethod	scala/Function0.apply:()Ljava/lang/Object;
NameAndType	until:(ILscala/Function0;)Lscala/collection/immutable/List;
Method	scala/reflect/generic/PickleBuffer.until:(ILscala/Function0;)Lscala/collection/immutable/List;
Asciz	scala/collection/immutable/List;
class	scala/collection/immutable/List
Asciz	$colon$colon;
Asciz	(Ljava/lang/Object;)Lscala/collection/immutable/List;;
NameAndType	$colon$colon:(Ljava/lang/Object;)Lscala/collection/immutable/List;
Method	scala/collection/immutable/List.$colon$colon:(Ljava/lang/Object;)Lscala/collection/immutable/List;
Asciz	end;
Asciz	op;
Asciz	Lscala/Function0;;
Asciz	<T:Ljava/lang/Object;>(ILscala/Function0<TT;>;)Lscala/collection/immutable/List<TT;>;;
Asciz	times;
NameAndType	times:(ILscala/Function0;)Lscala/collection/immutable/List;
Method	scala/reflect/generic/PickleBuffer.times:(ILscala/Function0;)Lscala/collection/immutable/List;
Asciz	n;
Asciz	createIndex;
Asciz	()[I;
Asciz	intWrapper;
Asciz	(I)Lscala/runtime/RichInt;;
NameAndType	intWrapper:(I)Lscala/runtime/RichInt;
Method	scala/Predef$.intWrapper:(I)Lscala/runtime/RichInt;
Asciz	scala/runtime/RichInt;
class	scala/runtime/RichInt
Asciz	(I)Lscala/collection/immutable/Range$ByOne;;
NameAndType	until:(I)Lscala/collection/immutable/Range$ByOne;
Method	scala/runtime/RichInt.until:(I)Lscala/collection/immutable/Range$ByOne;
Asciz	scala/reflect/generic/PickleBuffer$$anonfun$createIndex$1;
class	scala/reflect/generic/PickleBuffer$$anonfun$createIndex$1
Asciz	(Lscala/reflect/generic/PickleBuffer;[I)V;
NameAndType	"<init>":(Lscala/reflect/generic/PickleBuffer;[I)V
Method	scala/reflect/generic/PickleBuffer$$anonfun$createIndex$1."<init>":(Lscala/reflect/generic/PickleBuffer;[I)V
Asciz	scala/collection/immutable/Range$ByOne;
class	scala/collection/immutable/Range$ByOne
InterfaceMethod	scala/collection/immutable/Range$ByOne.foreach$mVc$sp:(Lscala/Function1;)V
Asciz	index$1;
Asciz	[I;
int	128;
Asciz	([BII)V;
NameAndType	scala$reflect$generic$PickleBuffer$$data:[B
Field	scala/reflect/generic/PickleBuffer.scala$reflect$generic$PickleBuffer$$data:[B
Asciz	java/lang/Object;
class	java/lang/Object
NameAndType	"<init>":()V
Method	java/lang/Object."<init>":()V
Asciz	data;
Asciz	from;
Asciz	to;
Asciz	ScalaSig;
Asciz	Lscala/reflect/ScalaSignature;;
Asciz	=dC\t\tAAK7m7fV4g-:\r!aB4f]n\tqA]3gYGOC8-7b2!\tY#D\r\tia\"mC:<'\"A\t)g/Y#1aa2kK$CA\n1BA-6-7b\nTWm;\t]!!Q\na\tAZ1uCB1#G\ni1!!B!seLCA\n\tibACsR,C\tx.\t'J!A\t%sG%\t\t!!\t!xC'q%=S:LGOQ)ZC*5\t!CKC KC%KC/IA\tLH/Z:aAq!\rA!'AcsR,7ofcR1G\t'QJ!!\tUsoA\n\t1\rAH%\rs\r\r\tLH/Z:!Y1Aq\nB]3bI&sG-=BqAAq(AsK$J3fq~#S-gCqaNCKIeG-8eKbb#%\tPoJLG/Z%oIDb$%\taRoJLG/Z%oIDxJ3r)\t\nC8\t\t\r))!-9(/;f:$W\r\t1AB'\tG.g!)q\nC!qQM\:ve\r]1dSRLHCARf\n1!!\r]1dSRL\"+\t)!C<sSR,');f)\tdCX'%AcI\"[!9(/;f$HCA\a1!A\"0\tyD<sSR,Gj8h$HCAaaV1b!\t\"-d\r\t!Aj8h)\"g!\r^2i$HcAhS\")aAo\:\tq#\t-A7]^3M_:<GCAna&1by\"q!X-Z6CsR,G#\tIA9I,\r\"ziDQAqA]3bI:GCwq/AsK$Gj8h$H#A1\teA>I,\r'p]$\"!Y>\tqD1,gCq0u_&sG-=fIN+/A11AA\n3qA!!9!qAA\t\tIAC!\ta:p_Rt\"A\nEa!AqC\mZ3\n\tUq:$W\r_3e'(bAA\t\rA)1#a!1%Q\rQ+\33\t\tCG\tQ!8uS2,B!!\n2Q1qEA\"b!a*5BA/AT5tiB!qFA!1\"a\r \tQ16\t\tA+8ucA\n:%19{G[5oOB1#a\ncAAB]fDq!! %Af]D\"! 1J_BRaEA'[I1!a%1UO\2uS>tCT!\t!!QLW.Z:\t]Q3\ny&a\r\rFA.!\ty#!MCQC\n\t1!qCA%#\r!!M\ti%a\t%\"lY1M]3biLeZ3y+\t\tiE3;
Asciz	RuntimeVisibleAnnotations;
Asciz	InnerClasses;
Asciz	ByOne;
Asciz	$anonfun$createIndex$1;
Asciz	$anonfun$toIndexedSeq$1;
Asciz	scala/ScalaObject;
class	scala/ScalaObject

{
public final byte[] scala$reflect$generic$PickleBuffer$$data;
  Signature: [B

private byte[] bytes;
  Signature: [B

private int readIndex;
  Signature: I

private int writeIndex;
  Signature: I

public byte[] bytes();
  Signature: ()[B
  Code:
   Stack=1, Locals=1, Args_size=1
	aload_0
	getfield	Field bytes:[B
	areturn
  Labels:

public void bytes_$eq(byte[]);
  Signature: ([B)V
  Code:
   Stack=2, Locals=2, Args_size=2
	aload_0
	aload_1
	putfield	Field bytes:[B
	return
  Labels:

public int readIndex();
  Signature: ()I
  Code:
   Stack=1, Locals=1, Args_size=1
	aload_0
	getfield	Field readIndex:I
	ireturn
  Labels:

public void readIndex_$eq(int);
  Signature: (I)V
  Code:
   Stack=2, Locals=2, Args_size=2
	aload_0
	iload_1
	putfield	Field readIndex:I
	return
  Labels:

public int writeIndex();
  Signature: ()I
  Code:
   Stack=1, Locals=1, Args_size=1
	aload_0
	getfield	Field writeIndex:I
	ireturn
  Labels:

public void writeIndex_$eq(int);
  Signature: (I)V
  Code:
   Stack=2, Locals=2, Args_size=2
	aload_0
	iload_1
	putfield	Field writeIndex:I
	return
  Labels:

private void dble();
  Signature: ()V
  Code:
   Stack=6, Locals=2, Args_size=1
	aload_0
	invokevirtual	Method bytes:()[B
	arraylength
	iconst_2
	imul
	newarray byte
	astore_1
	getstatic	Field scala/Array$.MODULE$:Lscala/Array$;
	aload_0
	invokevirtual	Method bytes:()[B
	iconst_0
	aload_1
	iconst_0
	aload_0
	invokevirtual	Method writeIndex:()I
	invokevirtual	Method scala/Array$.copy:(Ljava/lang/Object;ILjava/lang/Object;II)V
	aload_0
	aload_1
	invokevirtual	Method bytes_$eq:([B)V
	return
  Labels:
  LocalVariableTable: 
   Start  Length  Slot  Name   Signature
   0      33      0    this       Lscala/reflect/generic/PickleBuffer;
   10      22      1    bytes1       [B


public void ensureCapacity(int);
  Signature: (I)V
  Code:
   Stack=3, Locals=2, Args_size=2
l2	aload_0
	invokevirtual	Method bytes:()[B
	arraylength
	aload_0
	invokevirtual	Method writeIndex:()I
	iload_1
	iadd
	if_icmpge	l1 // return
	aload_0
	invokespecial	Method dble:()V
	goto	l2 // aload_0
l1	return
  Labels:
   	l2 = 0 // aload_0
   	l1 = 21 // return
  LocalVariableTable: 
   Start  Length  Slot  Name   Signature
   0      22      0    this       Lscala/reflect/generic/PickleBuffer;
   0      22      1    capacity       I


public void writeByte(int);
  Signature: (I)V
  Code:
   Stack=3, Locals=2, Args_size=2
	aload_0
	invokevirtual	Method writeIndex:()I
	aload_0
	invokevirtual	Method bytes:()[B
	arraylength
	if_icmpne	l1 // aload_0
	aload_0
	invokespecial	Method dble:()V
l1	aload_0
	invokevirtual	Method bytes:()[B
	aload_0
	invokevirtual	Method writeIndex:()I
	iload_1
	i2b
	bastore
	aload_0
	aload_0
	invokevirtual	Method writeIndex:()I
	iconst_1
	iadd
	invokevirtual	Method writeIndex_$eq:(I)V
	return
  Labels:
   	l1 = 16 // aload_0
  LocalVariableTable: 
   Start  Length  Slot  Name   Signature
   0      38      0    this       Lscala/reflect/generic/PickleBuffer;
   0      38      1    b       I


public void writeNat(int);
  Signature: (I)V
  Code:
   Stack=5, Locals=2, Args_size=2
	aload_0
	iload_1
	i2l
	ldc2_w	long 4294967295l
	land
	invokevirtual	Method writeLongNat:(J)V
	return
  Labels:
  LocalVariableTable: 
   Start  Length  Slot  Name   Signature
   0      11      0    this       Lscala/reflect/generic/PickleBuffer;
   0      11      1    x       I


public void writeLongNat(long);
  Signature: (J)V
  Code:
   Stack=5, Locals=5, Args_size=2
	lload_1
	ldc	int 7
	lushr
	lstore_3
	lload_3
	lconst_0
	lcmp
	ifeq	l1 // aload_0
	aload_0
	lload_3
	invokespecial	Method writeNatPrefix$1:(J)V
l1	aload_0
	lload_1
	ldc2_w	long 127l
	land
	l2i
	invokevirtual	Method writeByte:(I)V
	return
  Labels:
   	l1 = 16 // aload_0
  LocalVariableTable: 
   Start  Length  Slot  Name   Signature
   0      27      0    this       Lscala/reflect/generic/PickleBuffer;
   0      27      1    x       J
   5      21      3    y       J


public void patchNat(int, int);
  Signature: (II)V
  Code:
   Stack=4, Locals=4, Args_size=3
	aload_0
	invokevirtual	Method bytes:()[B
	iload_1
	iload_2
	ldc	int 127
	iand
	i2b
	bastore
	iload_2
	ldc	int 7
	iushr
	istore_3
	iload_3
	iconst_0
	if_icmpeq	l1 // return
	aload_0
	iload_3
	iload_1
	invokespecial	Method patchNatPrefix$1:(II)V
l1	return
  Labels:
   	l1 = 27 // return
  LocalVariableTable: 
   Start  Length  Slot  Name   Signature
   0      28      0    this       Lscala/reflect/generic/PickleBuffer;
   0      28      1    pos$1       I
   0      28      2    x       I
   16      12      3    y       I


public void writeLong(long);
  Signature: (J)V
  Code:
   Stack=5, Locals=7, Args_size=2
	lload_1
	ldc	int 8
	lshr
	lstore_3
	lload_1
	ldc2_w	long 255l
	land
	lstore	5
	lload_3
	lneg
	lload	5
	ldc	int 7
	lshr
	lcmp
	ifeq	l1 // aload_0
	aload_0
	lload_3
	invokevirtual	Method writeLong:(J)V
l1	aload_0
	lload	5
	l2i
	invokevirtual	Method writeByte:(I)V
	return
  Labels:
   	l1 = 28 // aload_0
  LocalVariableTable: 
   Start  Length  Slot  Name   Signature
   0      36      0    this       Lscala/reflect/generic/PickleBuffer;
   0      36      1    x       J
   5      30      3    y       J
   12      23      5    z       J


public int peekByte();
  Signature: ()I
  Code:
   Stack=2, Locals=1, Args_size=1
	aload_0
	invokevirtual	Method bytes:()[B
	aload_0
	invokevirtual	Method readIndex:()I
	baload
	ireturn
  Labels:

public int readByte();
  Signature: ()I
  Code:
   Stack=3, Locals=2, Args_size=1
	aload_0
	invokevirtual	Method bytes:()[B
	aload_0
	invokevirtual	Method readIndex:()I
	baload
	istore_1
	aload_0
	aload_0
	invokevirtual	Method readIndex:()I
	iconst_1
	iadd
	invokevirtual	Method readIndex_$eq:(I)V
	iload_1
	ireturn
  Labels:
  LocalVariableTable: 
   Start  Length  Slot  Name   Signature
   0      22      0    this       Lscala/reflect/generic/PickleBuffer;
   10      11      1    x       B


public int readNat();
  Signature: ()I
  Code:
   Stack=2, Locals=1, Args_size=1
	aload_0
	invokevirtual	Method readLongNat:()J
	l2i
	ireturn
  Labels:

public long readLongNat();
  Signature: ()J
  Code:
   Stack=6, Locals=5, Args_size=1
	lconst_0
	lstore_3
l1	aload_0
	invokevirtual	Method readByte:()I
	i2l
	lstore_1
	lload_3
	ldc	int 7
	lshl
	lload_1
	ldc2_w	long 127l
	land
	ladd
	lstore_3
	lload_1
	ldc2_w	long 128l
	land
	lconst_0
	lcmp
	ifne	l1 // aload_0
	lload_3
	lreturn
  Labels:
   	l1 = 2 // aload_0
  LocalVariableTable: 
   Start  Length  Slot  Name   Signature
   0      31      0    this       Lscala/reflect/generic/PickleBuffer;
   0      30      1    b       J
   2      28      3    x       J


public long readLong(int);
  Signature: (I)J
  Code:
   Stack=4, Locals=6, Args_size=2
	lconst_0
	lstore_2
	iconst_0
	istore	4
l2	iload	4
	iload_1
	if_icmpge	l1 // ldc
	lload_2
	ldc	int 8
	lshl
	aload_0
	invokevirtual	Method readByte:()I
	ldc	int 255
	iand
	i2l
	ladd
	lstore_2
	iload	4
	iconst_1
	iadd
	istore	4
	goto	l2 // iload
l1	ldc	int 64
	iload_1
	iconst_3
	ishl
	isub
	istore	5
	lload_2
	iload	5
	lshl
	iload	5
	lshr
	lreturn
  Labels:
   	l2 = 5 // iload
   	l1 = 34 // ldc
  LocalVariableTable: 
   Start  Length  Slot  Name   Signature
   0      50      0    this       Lscala/reflect/generic/PickleBuffer;
   0      50      1    len       I
   2      47      2    x       J
   5      44      4    i       I
   42      7      5    leading       I


public scala.collection.IndexedSeq toIndexedSeq();
  Signature: ()Lscala/collection/IndexedSeq;
  Code:
   Stack=5, Locals=3, Args_size=1
	aload_0
	invokevirtual	Method readIndex:()I
	istore_1
	aload_0
	iconst_0
	invokevirtual	Method readIndex_$eq:(I)V
	aload_0
	invokevirtual	Method readNat:()I
	pop
	aload_0
	invokevirtual	Method readNat:()I
	pop
	aload_0
	invokevirtual	Method readNat:()I
	anewarray	class scala/Tuple2
	astore_2
	getstatic	Field scala/Predef$.MODULE$:Lscala/Predef$;
	aload_2
	checkcast	class "[Ljava/lang/Object;"
	invokevirtual	Method scala/Predef$.refArrayOps:([Ljava/lang/Object;)Lscala/collection/mutable/ArrayOps;
	invokeinterface	InterfaceMethod scala/collection/SeqLike.indices:()Lscala/collection/immutable/Range;
	new	class scala/reflect/generic/PickleBuffer$$anonfun$toIndexedSeq$1
	dup
	aload_0
	aload_2
	invokespecial	Method scala/reflect/generic/PickleBuffer$$anonfun$toIndexedSeq$1."<init>":(Lscala/reflect/generic/PickleBuffer;[Lscala/Tuple2;)V
	invokevirtual	Method scala/collection/immutable/Range.foreach$mVc$sp:(Lscala/Function1;)V
	aload_0
	iload_1
	invokevirtual	Method readIndex_$eq:(I)V
	getstatic	Field scala/Predef$.MODULE$:Lscala/Predef$;
	aload_2
	checkcast	class "[Ljava/lang/Object;"
	invokevirtual	Method scala/Predef$.refArrayOps:([Ljava/lang/Object;)Lscala/collection/mutable/ArrayOps;
	invokeinterface	InterfaceMethod scala/collection/TraversableOnce.toIndexedSeq:()Lscala/collection/mutable/IndexedSeq;
	areturn
  Labels:
  LocalVariableTable: 
   Start  Length  Slot  Name   Signature
   0      76      0    this       Lscala/reflect/generic/PickleBuffer;
   5      70      1    saved       I
   28      47      2    result$1       [Lscala/Tuple2;

  Signature: length = 0x2
   00 FFFFFF9A 

public scala.collection.immutable.List until(int, scala.Function0);
  Signature: (ILscala/Function0;)Lscala/collection/immutable/List;
  Code:
   Stack=3, Locals=4, Args_size=3
	aload_0
	invokevirtual	Method readIndex:()I
	iload_1
	if_icmpne	l1 // aload_2
	getstatic	Field scala/collection/immutable/Nil$.MODULE$:Lscala/collection/immutable/Nil$;
	goto	l2 // areturn
l1	aload_2
	invokeinterface	InterfaceMethod scala/Function0.apply:()Ljava/lang/Object;
	astore_3
	aload_0
	iload_1
	aload_2
	invokevirtual	Method until:(ILscala/Function0;)Lscala/collection/immutable/List;
	aload_3
	invokevirtual	Method scala/collection/immutable/List.$colon$colon:(Ljava/lang/Object;)Lscala/collection/immutable/List;
l2	areturn
  Labels:
   	l1 = 14 // aload_2
   	l2 = 31 // areturn
  LocalVariableTable: 
   Start  Length  Slot  Name   Signature
   0      32      0    this       Lscala/reflect/generic/PickleBuffer;
   0      32      1    end       I
   0      32      2    op       Lscala/Function0;

  Signature: length = 0x2
   00 FFFFFFB4 

public scala.collection.immutable.List times(int, scala.Function0);
  Signature: (ILscala/Function0;)Lscala/collection/immutable/List;
  Code:
   Stack=3, Locals=4, Args_size=3
	iload_1
	iconst_0
	if_icmpne	l1 // aload_2
	getstatic	Field scala/collection/immutable/Nil$.MODULE$:Lscala/collection/immutable/Nil$;
	goto	l2 // areturn
l1	aload_2
	invokeinterface	InterfaceMethod scala/Function0.apply:()Ljava/lang/Object;
	astore_3
	aload_0
	iload_1
	iconst_1
	isub
	aload_2
	invokevirtual	Method times:(ILscala/Function0;)Lscala/collection/immutable/List;
	aload_3
	invokevirtual	Method scala/collection/immutable/List.$colon$colon:(Ljava/lang/Object;)Lscala/collection/immutable/List;
l2	areturn
  Labels:
   	l1 = 11 // aload_2
   	l2 = 30 // areturn
  LocalVariableTable: 
   Start  Length  Slot  Name   Signature
   0      31      0    this       Lscala/reflect/generic/PickleBuffer;
   0      31      1    n       I
   0      31      2    op       Lscala/Function0;

  Signature: length = 0x2
   00 FFFFFFB4 

public int[] createIndex();
  Signature: ()[I
  Code:
   Stack=5, Locals=2, Args_size=1
	aload_0
	invokevirtual	Method readNat:()I
	newarray int
	astore_1
	getstatic	Field scala/Predef$.MODULE$:Lscala/Predef$;
	iconst_0
	invokevirtual	Method scala/Predef$.intWrapper:(I)Lscala/runtime/RichInt;
	aload_1
	arraylength
	invokevirtual	Method scala/runtime/RichInt.until:(I)Lscala/collection/immutable/Range$ByOne;
	new	class scala/reflect/generic/PickleBuffer$$anonfun$createIndex$1
	dup
	aload_0
	aload_1
	invokespecial	Method scala/reflect/generic/PickleBuffer$$anonfun$createIndex$1."<init>":(Lscala/reflect/generic/PickleBuffer;[I)V
	invokeinterface	InterfaceMethod scala/collection/immutable/Range$ByOne.foreach$mVc$sp:(Lscala/Function1;)V
	aload_1
	areturn
  Labels:
  LocalVariableTable: 
   Start  Length  Slot  Name   Signature
   0      35      0    this       Lscala/reflect/generic/PickleBuffer;
   7      27      1    index$1       [I


private final void writeNatPrefix$1(long);
  Signature: (J)V
  Code:
   Stack=5, Locals=5, Args_size=2
	lload_1
	ldc	int 7
	lushr
	lstore_3
	lload_3
	lconst_0
	lcmp
	ifeq	l1 // aload_0
	aload_0
	lload_3
	invokespecial	Method writeNatPrefix$1:(J)V
l1	aload_0
	lload_1
	ldc2_w	long 127l
	land
	ldc2_w	long 128l
	lor
	l2i
	invokevirtual	Method writeByte:(I)V
	return
  Labels:
   	l1 = 16 // aload_0
  LocalVariableTable: 
   Start  Length  Slot  Name   Signature
   0      31      0    this       Lscala/reflect/generic/PickleBuffer;
   0      31      1    x       J
   5      25      3    y       J


private final void patchNatPrefix$1(int, int);
  Signature: (II)V
  Code:
   Stack=8, Locals=4, Args_size=3
l2	aload_0
	iconst_0
	invokevirtual	Method writeByte:(I)V
	getstatic	Field scala/Array$.MODULE$:Lscala/Array$;
	aload_0
	invokevirtual	Method bytes:()[B
	iload_2
	aload_0
	invokevirtual	Method bytes:()[B
	iload_2
	iconst_1
	iadd
	aload_0
	invokevirtual	Method writeIndex:()I
	iload_2
	iconst_1
	iadd
	isub
	invokevirtual	Method scala/Array$.copy:(Ljava/lang/Object;ILjava/lang/Object;II)V
	aload_0
	invokevirtual	Method bytes:()[B
	iload_2
	iload_1
	ldc	int 127
	iand
	ldc	int 128
	ior
	i2b
	bastore
	iload_1
	ldc	int 7
	iushr
	istore_3
	iload_3
	iconst_0
	if_icmpeq	l1 // return
	iload_3
	istore_1
	goto	l2 // aload_0
l1	return
  Labels:
   	l2 = 0 // aload_0
   	l1 = 60 // return
  LocalVariableTable: 
   Start  Length  Slot  Name   Signature
   0      61      0    this       Lscala/reflect/generic/PickleBuffer;
   0      61      1    x       I
   50      11      3    y       I


public scala.reflect.generic.PickleBuffer(byte[], int, int);
  Signature: ([BII)V
  Code:
   Stack=2, Locals=4, Args_size=4
	aload_0
	aload_1
	putfield	Field scala$reflect$generic$PickleBuffer$$data:[B
	aload_0
	invokespecial	Method java/lang/Object."<init>":()V
	aload_0
	aload_1
	putfield	Field bytes:[B
	aload_0
	iload_2
	putfield	Field readIndex:I
	aload_0
	iload_3
	putfield	Field writeIndex:I
	return
  Labels:
  LocalVariableTable: 
   Start  Length  Slot  Name   Signature
   0      25      0    this       Lscala/reflect/generic/PickleBuffer;
   0      25      1    data       [B
   0      25      2    from       I
   0      25      3    to       I


}

