Compiled from "PickleFormat.scala"
public final class scala.reflect.generic.PickleFormat extends java.lang.Object
  SourceFile: "PickleFormat.scala"
  ScalaSig: length = 0x13BE
   05 00 FFFFFF84 2F 07 05 01 02 FFFFFF88 02 09 01 0C 50 69 63
   6B 6C 65 46 6F 72 6D 61 74 0A 02 03 04 01 07 67
   65 6E 65 72 69 63 0A 02 05 06 01 07 72 65 66 6C
   65 63 74 0A 01 07 01 05 73 63 61 6C 61 03 00 10
   02 0A 0B 0D 01 02 06 08 0C 02 FFFFFF84 FFFFFF80 FFFFFF80 FFFFFF88 02 0D
   02 0C 50 69 63 6B 6C 65 46 6F 72 6D 61 74 13 03
   0B 0E 16 10 02 0F 14 0D 01 10 0A 02 11 12 01 04
   6C 61 6E 67 0A 01 13 01 04 6A 61 76 61 09 02 15
   10 02 06 4F 62 6A 65 63 74 10 02 17 18 0D 01 06
   09 02 19 06 02 0B 53 63 61 6C 61 4F 62 6A 65 63
   74 08 05 1B 0B FFFFFF84 00 1C 01 06 3C 69 6E 69 74 3E
   14 01 09 08 07 1E 0B FFFFFFC2 FFFFFF80 FFFFFF84 00 1F 01 0C 4D 61
   6A 6F 72 56 65 72 73 69 6F 6E 15 01 20 10 02 17
   21 09 02 22 06 02 03 49 6E 74 08 06 24 0B FFFFFFA0 FFFFFF80
   04 20 01 0D 4D 61 6A 6F 72 56 65 72 73 69 6F 6E
   20 08 07 26 0B FFFFFFC2 FFFFFF80 FFFFFF84 00 1F 01 0C 4D 69 6E 6F
   72 56 65 72 73 69 6F 6E 08 06 28 0B FFFFFFA0 FFFFFF80 04 20
   01 0D 4D 69 6E 6F 72 56 65 72 73 69 6F 6E 20 08
   07 2A 0B FFFFFFC2 FFFFFF80 FFFFFF84 02 2B 01 08 54 45 52 4D 6E 61
   6D 65 15 01 2C 0F 01 2D 1D 01 01 08 06 2F 0B FFFFFFA0
   FFFFFF80 06 2C 01 09 54 45 52 4D 6E 61 6D 65 20 08 07
   31 0B FFFFFFC2 FFFFFF80 FFFFFF84 02 32 01 08 54 59 50 45 6E 61 6D
   65 15 01 33 0F 01 34 1D 01 02 08 06 36 0B FFFFFFA0 FFFFFF80
   06 33 01 09 54 59 50 45 6E 61 6D 65 20 08 07 38
   0B FFFFFFC2 FFFFFF80 FFFFFF84 02 39 01 07 4E 4F 4E 45 73 79 6D 15
   01 3A 0F 01 3B 1D 01 03 08 06 3D 0B FFFFFFA0 FFFFFF80 06 3A
   01 08 4E 4F 4E 45 73 79 6D 20 08 07 3F 0B FFFFFFC2 FFFFFF80
   FFFFFF84 02 40 01 07 54 59 50 45 73 79 6D 15 01 41 0F
   01 42 1D 01 04 08 06 44 0B FFFFFFA0 FFFFFF80 06 41 01 08 54
   59 50 45 73 79 6D 20 08 07 46 0B FFFFFFC2 FFFFFF80 FFFFFF84 02 47
   01 08 41 4C 49 41 53 73 79 6D 15 01 48 0F 01 49
   1D 01 05 08 06 4B 0B FFFFFFA0 FFFFFF80 06 48 01 09 41 4C 49
   41 53 73 79 6D 20 08 07 4D 0B FFFFFFC2 FFFFFF80 FFFFFF84 02 4E 01
   08 43 4C 41 53 53 73 79 6D 15 01 4F 0F 01 50 1D
   01 06 08 06 52 0B FFFFFFA0 FFFFFF80 06 4F 01 09 43 4C 41 53
   53 73 79 6D 20 08 07 54 0B FFFFFFC2 FFFFFF80 FFFFFF84 02 55 01 09
   4D 4F 44 55 4C 45 73 79 6D 15 01 56 0F 01 57 1D
   01 07 08 06 59 0B FFFFFFA0 FFFFFF80 06 56 01 0A 4D 4F 44 55
   4C 45 73 79 6D 20 08 07 5B 0B FFFFFFC2 FFFFFF80 FFFFFF84 02 5C 01
   06 56 41 4C 73 79 6D 15 01 5D 0F 01 5E 1D 01 08
   08 06 60 0B FFFFFFA0 FFFFFF80 06 5D 01 07 56 41 4C 73 79 6D
   20 08 07 62 0B FFFFFFC2 FFFFFF80 FFFFFF84 02 63 01 06 45 58 54 72
   65 66 15 01 64 0F 01 65 1D 01 09 08 06 67 0B FFFFFFA0
   FFFFFF80 06 64 01 07 45 58 54 72 65 66 20 08 07 69 0B
   FFFFFFC2 FFFFFF80 FFFFFF84 02 6A 01 0E 45 58 54 4D 4F 44 43 4C 41
   53 53 72 65 66 15 01 6B 0F 01 6C 1D 01 0A 08 06
   6E 0B FFFFFFA0 FFFFFF80 06 6B 01 0F 45 58 54 4D 4F 44 43 4C
   41 53 53 72 65 66 20 08 07 70 0B FFFFFFC2 FFFFFF80 FFFFFF84 02 71
   01 05 4E 4F 74 70 65 15 01 72 0F 01 73 1D 01 0B
   08 06 75 0B FFFFFFA0 FFFFFF80 06 72 01 06 4E 4F 74 70 65 20
   08 07 77 0B FFFFFFC2 FFFFFF80 FFFFFF84 02 78 01 0B 4E 4F 50 52 45
   46 49 58 74 70 65 15 01 79 0F 01 7A 1D 01 0C 08
   06 7C 0B FFFFFFA0 FFFFFF80 06 79 01 0C 4E 4F 50 52 45 46 49
   58 74 70 65 20 08 07 7E 0B FFFFFFC2 FFFFFF80 FFFFFF84 02 7F 01 07
   54 48 49 53 74 70 65 15 02 FFFFFF81 00 0F 02 FFFFFF81 01 1D
   01 0D 08 08 FFFFFF81 03 0B FFFFFFA0 FFFFFF80 06 FFFFFF81 00 01 08 54 48
   49 53 74 70 65 20 08 09 FFFFFF81 05 0B FFFFFFC2 FFFFFF80 FFFFFF84 02 FFFFFF81
   06 01 09 53 49 4E 47 4C 45 74 70 65 15 02 FFFFFF81 07
   0F 02 FFFFFF81 08 1D 01 0E 08 08 FFFFFF81 0A 0B FFFFFFA0 FFFFFF80 06 FFFFFF81
   07 01 0A 53 49 4E 47 4C 45 74 70 65 20 08 09 FFFFFF81
   0C 0B FFFFFFC2 FFFFFF80 FFFFFF84 02 FFFFFF81 0D 01 0B 43 4F 4E 53 54 41
   4E 54 74 70 65 15 02 FFFFFF81 0E 0F 02 FFFFFF81 0F 1D 01 0F
   08 08 FFFFFF81 11 0B FFFFFFA0 FFFFFF80 06 FFFFFF81 0E 01 0C 43 4F 4E 53
   54 41 4E 54 74 70 65 20 08 09 FFFFFF81 13 0B FFFFFFC2 FFFFFF80 FFFFFF84
   02 FFFFFF81 14 01 0A 54 59 50 45 52 45 46 74 70 65 15
   02 FFFFFF81 15 0F 02 FFFFFF81 16 1D 01 10 08 08 FFFFFF81 18 0B FFFFFFA0
   FFFFFF80 06 FFFFFF81 15 01 0B 54 59 50 45 52 45 46 74 70 65
   20 08 09 FFFFFF81 1A 0B FFFFFFC2 FFFFFF80 FFFFFF84 02 FFFFFF81 1B 01 0D 54 59
   50 45 42 4F 55 4E 44 53 74 70 65 15 02 FFFFFF81 1C 0F
   02 FFFFFF81 1D 1D 01 11 08 08 FFFFFF81 1F 0B FFFFFFA0 FFFFFF80 06 FFFFFF81 1C
   01 0E 54 59 50 45 42 4F 55 4E 44 53 74 70 65 20
   08 09 FFFFFF81 21 0B FFFFFFC2 FFFFFF80 FFFFFF84 02 FFFFFF81 22 01 0A 52 45 46
   49 4E 45 44 74 70 65 15 02 FFFFFF81 23 0F 02 FFFFFF81 24 1D
   01 12 08 08 FFFFFF81 26 0B FFFFFFA0 FFFFFF80 06 FFFFFF81 23 01 0B 52 45
   46 49 4E 45 44 74 70 65 20 08 09 FFFFFF81 28 0B FFFFFFC2 FFFFFF80
   FFFFFF84 02 FFFFFF81 29 01 0C 43 4C 41 53 53 49 4E 46 4F 74
   70 65 15 02 FFFFFF81 2A 0F 02 FFFFFF81 2B 1D 01 13 08 08 FFFFFF81
   2D 0B FFFFFFA0 FFFFFF80 06 FFFFFF81 2A 01 0D 43 4C 41 53 53 49 4E
   46 4F 74 70 65 20 08 09 FFFFFF81 2F 0B FFFFFFC2 FFFFFF80 FFFFFF84 02 FFFFFF81
   30 01 09 4D 45 54 48 4F 44 74 70 65 15 02 FFFFFF81 31
   0F 02 FFFFFF81 32 1D 01 14 08 08 FFFFFF81 34 0B FFFFFFA0 FFFFFF80 06 FFFFFF81
   31 01 0A 4D 45 54 48 4F 44 74 70 65 20 08 09 FFFFFF81
   36 0B FFFFFFC2 FFFFFF80 FFFFFF84 02 FFFFFF81 37 01 07 50 4F 4C 59 74 70
   65 15 02 FFFFFF81 38 0F 02 FFFFFF81 39 1D 01 15 08 08 FFFFFF81 3B
   0B FFFFFFA0 FFFFFF80 06 FFFFFF81 38 01 08 50 4F 4C 59 74 70 65 20
   08 09 FFFFFF81 3D 0B FFFFFFC2 FFFFFF80 FFFFFF84 02 FFFFFF81 3E 01 11 49 4D 50
   4C 49 43 49 54 4D 45 54 48 4F 44 74 70 65 15 02
   FFFFFF81 3F 0F 02 FFFFFF81 40 1D 01 16 08 08 FFFFFF81 42 0B FFFFFFA0 FFFFFF80
   06 FFFFFF81 3F 01 12 49 4D 50 4C 49 43 49 54 4D 45 54
   48 4F 44 74 70 65 20 08 09 FFFFFF81 44 0B FFFFFFC2 FFFFFF80 FFFFFF84 02
   FFFFFF81 45 01 07 4C 49 54 45 52 41 4C 15 02 FFFFFF81 46 0F
   02 FFFFFF81 47 1D 01 17 08 08 FFFFFF81 49 0B FFFFFFA0 FFFFFF80 06 FFFFFF81 46
   01 08 4C 49 54 45 52 41 4C 20 08 09 FFFFFF81 4B 0B FFFFFFC2
   FFFFFF80 FFFFFF84 02 FFFFFF81 4C 01 0B 4C 49 54 45 52 41 4C 75 6E
   69 74 15 02 FFFFFF81 4D 0F 02 FFFFFF81 4E 1D 01 18 08 08 FFFFFF81
   50 0B FFFFFFA0 FFFFFF80 06 FFFFFF81 4D 01 0C 4C 49 54 45 52 41 4C
   75 6E 69 74 20 08 09 FFFFFF81 52 0B FFFFFFC2 FFFFFF80 FFFFFF84 02 FFFFFF81 53
   01 0E 4C 49 54 45 52 41 4C 62 6F 6F 6C 65 61 6E
   15 02 FFFFFF81 54 0F 02 FFFFFF81 55 1D 01 19 08 08 FFFFFF81 57 0B
   FFFFFFA0 FFFFFF80 06 FFFFFF81 54 01 0F 4C 49 54 45 52 41 4C 62 6F
   6F 6C 65 61 6E 20 08 09 FFFFFF81 59 0B FFFFFFC2 FFFFFF80 FFFFFF84 02 FFFFFF81
   5A 01 0B 4C 49 54 45 52 41 4C 62 79 74 65 15 02
   FFFFFF81 5B 0F 02 FFFFFF81 5C 1D 01 1A 08 08 FFFFFF81 5E 0B FFFFFFA0 FFFFFF80
   06 FFFFFF81 5B 01 0C 4C 49 54 45 52 41 4C 62 79 74 65
   20 08 09 FFFFFF81 60 0B FFFFFFC2 FFFFFF80 FFFFFF84 02 FFFFFF81 61 01 0C 4C 49
   54 45 52 41 4C 73 68 6F 72 74 15 02 FFFFFF81 62 0F 02
   FFFFFF81 63 1D 01 1B 08 08 FFFFFF81 65 0B FFFFFFA0 FFFFFF80 06 FFFFFF81 62 01
   0D 4C 49 54 45 52 41 4C 73 68 6F 72 74 20 08 09
   FFFFFF81 67 0B FFFFFFC2 FFFFFF80 FFFFFF84 02 FFFFFF81 68 01 0B 4C 49 54 45 52
   41 4C 63 68 61 72 15 02 FFFFFF81 69 0F 02 FFFFFF81 6A 1D 01
   1C 08 08 FFFFFF81 6C 0B FFFFFFA0 FFFFFF80 06 FFFFFF81 69 01 0C 4C 49 54
   45 52 41 4C 63 68 61 72 20 08 09 FFFFFF81 6E 0B FFFFFFC2 FFFFFF80
   FFFFFF84 02 FFFFFF81 6F 01 0A 4C 49 54 45 52 41 4C 69 6E 74
   15 02 FFFFFF81 70 0F 02 FFFFFF81 71 1D 01 1D 08 08 FFFFFF81 73 0B
   FFFFFFA0 FFFFFF80 06 FFFFFF81 70 01 0B 4C 49 54 45 52 41 4C 69 6E
   74 20 08 09 FFFFFF81 75 0B FFFFFFC2 FFFFFF80 FFFFFF84 02 FFFFFF81 76 01 0B 4C
   49 54 45 52 41 4C 6C 6F 6E 67 15 02 FFFFFF81 77 0F 02
   FFFFFF81 78 1D 01 1E 08 08 FFFFFF81 7A 0B FFFFFFA0 FFFFFF80 06 FFFFFF81 77 01
   0C 4C 49 54 45 52 41 4C 6C 6F 6E 67 20 08 09 FFFFFF81
   7C 0B FFFFFFC2 FFFFFF80 FFFFFF84 02 FFFFFF81 7D 01 0C 4C 49 54 45 52 41
   4C 66 6C 6F 61 74 15 02 FFFFFF81 7E 0F 02 FFFFFF81 7F 1D 01
   1F 08 08 FFFFFF82 01 0B FFFFFFA0 FFFFFF80 06 FFFFFF81 7E 01 0D 4C 49 54
   45 52 41 4C 66 6C 6F 61 74 20 08 09 FFFFFF82 03 0B FFFFFFC2
   FFFFFF80 FFFFFF84 02 FFFFFF82 04 01 0D 4C 49 54 45 52 41 4C 64 6F
   75 62 6C 65 15 02 FFFFFF82 05 0F 02 FFFFFF82 06 1D 01 20 08
   08 FFFFFF82 08 0B FFFFFFA0 FFFFFF80 06 FFFFFF82 05 01 0E 4C 49 54 45 52
   41 4C 64 6F 75 62 6C 65 20 08 09 FFFFFF82 0A 0B FFFFFFC2 FFFFFF80
   FFFFFF84 02 FFFFFF82 0B 01 0D 4C 49 54 45 52 41 4C 73 74 72
   69 6E 67 15 02 FFFFFF82 0C 0F 02 FFFFFF82 0D 1D 01 21 08 08
   FFFFFF82 0F 0B FFFFFFA0 FFFFFF80 06 FFFFFF82 0C 01 0E 4C 49 54 45 52 41
   4C 73 74 72 69 6E 67 20 08 09 FFFFFF82 11 0B FFFFFFC2 FFFFFF80 FFFFFF84
   02 FFFFFF82 12 01 0B 4C 49 54 45 52 41 4C 6E 75 6C 6C
   15 02 FFFFFF82 13 0F 02 FFFFFF82 14 1D 01 22 08 08 FFFFFF82 16 0B
   FFFFFFA0 FFFFFF80 06 FFFFFF82 13 01 0C 4C 49 54 45 52 41 4C 6E 75
   6C 6C 20 08 09 FFFFFF82 18 0B FFFFFFC2 FFFFFF80 FFFFFF84 02 FFFFFF82 19 01 0C
   4C 49 54 45 52 41 4C 63 6C 61 73 73 15 02 FFFFFF82 1A
   0F 02 FFFFFF82 1B 1D 01 23 08 08 FFFFFF82 1D 0B FFFFFFA0 FFFFFF80 06 FFFFFF82
   1A 01 0D 4C 49 54 45 52 41 4C 63 6C 61 73 73 20
   08 09 FFFFFF82 1F 0B FFFFFFC2 FFFFFF80 FFFFFF84 02 FFFFFF82 20 01 0B 4C 49 54
   45 52 41 4C 65 6E 75 6D 15 02 FFFFFF82 21 0F 02 FFFFFF82 22
   1D 01 24 08 08 FFFFFF82 24 0B FFFFFFA0 FFFFFF80 06 FFFFFF82 21 01 0C 4C
   49 54 45 52 41 4C 65 6E 75 6D 20 08 09 FFFFFF82 26 0B
   FFFFFFC2 FFFFFF80 FFFFFF84 02 FFFFFF82 27 01 08 53 59 4D 41 4E 4E 4F 54
   15 02 FFFFFF82 28 0F 02 FFFFFF82 29 1D 01 28 08 08 FFFFFF82 2B 0B
   FFFFFFA0 FFFFFF80 06 FFFFFF82 28 01 09 53 59 4D 41 4E 4E 4F 54 20
   08 09 FFFFFF82 2D 0B FFFFFFC2 FFFFFF80 FFFFFF84 02 FFFFFF82 2E 01 08 43 48 49
   4C 44 52 45 4E 15 02 FFFFFF82 2F 0F 02 FFFFFF82 30 1D 01 29
   08 08 FFFFFF82 32 0B FFFFFFA0 FFFFFF80 06 FFFFFF82 2F 01 09 43 48 49 4C
   44 52 45 4E 20 08 09 FFFFFF82 34 0B FFFFFFC2 FFFFFF80 FFFFFF84 02 FFFFFF82 35
   01 0C 41 4E 4E 4F 54 41 54 45 44 74 70 65 15 02
   FFFFFF82 36 0F 02 FFFFFF82 37 1D 01 2A 08 08 FFFFFF82 39 0B FFFFFFA0 FFFFFF80
   06 FFFFFF82 36 01 0D 41 4E 4E 4F 54 41 54 45 44 74 70
   65 20 08 09 FFFFFF82 3B 0B FFFFFFC2 FFFFFF80 FFFFFF84 02 FFFFFF82 3C 01 09 41
   4E 4E 4F 54 49 4E 46 4F 15 02 FFFFFF82 3D 0F 02 FFFFFF82 3E
   1D 01 2B 08 08 FFFFFF82 40 0B FFFFFFA0 FFFFFF80 06 FFFFFF82 3D 01 0A 41
   4E 4E 4F 54 49 4E 46 4F 20 08 09 FFFFFF82 42 0B FFFFFFC2 FFFFFF80
   FFFFFF84 02 FFFFFF82 43 01 0D 41 4E 4E 4F 54 41 52 47 41 52
   52 41 59 15 02 FFFFFF82 44 0F 02 FFFFFF82 45 1D 01 2C 08 08
   FFFFFF82 47 0B FFFFFFA0 FFFFFF80 06 FFFFFF82 44 01 0E 41 4E 4E 4F 54 41
   52 47 41 52 52 41 59 20 08 09 FFFFFF82 49 0B FFFFFFC2 FFFFFF80 FFFFFF84
   02 FFFFFF82 4A 01 08 53 55 50 45 52 74 70 65 15 02 FFFFFF82
   4B 0F 02 FFFFFF82 4C 1D 01 2E 08 08 FFFFFF82 4E 0B FFFFFFA0 FFFFFF80 06
   FFFFFF82 4B 01 09 53 55 50 45 52 74 70 65 20 08 09 FFFFFF82
   50 0B FFFFFFC2 FFFFFF80 FFFFFF84 02 FFFFFF82 51 01 10 44 45 42 52 55 49
   4A 4E 49 4E 44 45 58 74 70 65 15 02 FFFFFF82 52 0F 02
   FFFFFF82 53 1D 01 2F 08 08 FFFFFF82 55 0B FFFFFFA0 FFFFFF80 06 FFFFFF82 52 01
   11 44 45 42 52 55 49 4A 4E 49 4E 44 45 58 74 70
   65 20 08 09 FFFFFF82 57 0B FFFFFFC2 FFFFFF80 FFFFFF84 02 FFFFFF82 58 01 0E 45
   58 49 53 54 45 4E 54 49 41 4C 74 70 65 15 02 FFFFFF82
   59 0F 02 FFFFFF82 5A 1D 01 30 08 08 FFFFFF82 5C 0B FFFFFFA0 FFFFFF80 06
   FFFFFF82 59 01 0F 45 58 49 53 54 45 4E 54 49 41 4C 74
   70 65 20 08 09 FFFFFF82 5E 0B FFFFFFC2 FFFFFF80 FFFFFF84 02 FFFFFF82 5F 01 04
   54 52 45 45 15 02 FFFFFF82 60 0F 02 FFFFFF82 61 1D 01 31 08
   08 FFFFFF82 63 0B FFFFFFA0 FFFFFF80 06 FFFFFF82 60 01 05 54 52 45 45 20
   08 08 FFFFFF82 65 0B FFFFFFC2 FFFFFF80 FFFFFF84 02 2B 01 09 45 4D 50 54
   59 74 72 65 65 08 07 FFFFFF82 67 0B FFFFFFA0 FFFFFF80 06 2C 01 0A
   45 4D 50 54 59 74 72 65 65 20 08 08 FFFFFF82 69 0B FFFFFFC2
   FFFFFF80 FFFFFF84 02 32 01 0B 50 41 43 4B 41 47 45 74 72 65
   65 08 07 FFFFFF82 6B 0B FFFFFFA0 FFFFFF80 06 33 01 0C 50 41 43 4B
   41 47 45 74 72 65 65 20 08 08 FFFFFF82 6D 0B FFFFFFC2 FFFFFF80 FFFFFF84
   02 39 01 09 43 4C 41 53 53 74 72 65 65 08 07 FFFFFF82
   6F 0B FFFFFFA0 FFFFFF80 06 3A 01 0A 43 4C 41 53 53 74 72 65
   65 20 08 08 FFFFFF82 71 0B FFFFFFC2 FFFFFF80 FFFFFF84 02 40 01 0A 4D 4F
   44 55 4C 45 74 72 65 65 08 07 FFFFFF82 73 0B FFFFFFA0 FFFFFF80 06
   41 01 0B 4D 4F 44 55 4C 45 74 72 65 65 20 08 08
   FFFFFF82 75 0B FFFFFFC2 FFFFFF80 FFFFFF84 02 47 01 0A 56 41 4C 44 45 46
   74 72 65 65 08 07 FFFFFF82 77 0B FFFFFFA0 FFFFFF80 06 48 01 0B 56
   41 4C 44 45 46 74 72 65 65 20 08 08 FFFFFF82 79 0B FFFFFFC2
   FFFFFF80 FFFFFF84 02 4E 01 0A 44 45 46 44 45 46 74 72 65 65
   08 07 FFFFFF82 7B 0B FFFFFFA0 FFFFFF80 06 4F 01 0B 44 45 46 44 45
   46 74 72 65 65 20 08 08 FFFFFF82 7D 0B FFFFFFC2 FFFFFF80 FFFFFF84 02 55
   01 0B 54 59 50 45 44 45 46 74 72 65 65 08 07 FFFFFF82
   7F 0B FFFFFFA0 FFFFFF80 06 56 01 0C 54 59 50 45 44 45 46 74
   72 65 65 20 08 08 FFFFFF83 01 0B FFFFFFC2 FFFFFF80 FFFFFF84 02 5C 01 09
   4C 41 42 45 4C 74 72 65 65 08 07 FFFFFF83 03 0B FFFFFFA0 FFFFFF80
   06 5D 01 0A 4C 41 42 45 4C 74 72 65 65 20 08 08
   FFFFFF83 05 0B FFFFFFC2 FFFFFF80 FFFFFF84 02 63 01 0A 49 4D 50 4F 52 54
   74 72 65 65 08 07 FFFFFF83 07 0B FFFFFFA0 FFFFFF80 06 64 01 0B 49
   4D 50 4F 52 54 74 72 65 65 20 08 08 FFFFFF83 09 0B FFFFFFC2
   FFFFFF80 FFFFFF84 02 71 01 0A 44 4F 43 44 45 46 74 72 65 65
   08 07 FFFFFF83 0B 0B FFFFFFA0 FFFFFF80 06 72 01 0B 44 4F 43 44 45
   46 74 72 65 65 20 08 08 FFFFFF83 0D 0B FFFFFFC2 FFFFFF80 FFFFFF84 02 78
   01 0C 54 45 4D 50 4C 41 54 45 74 72 65 65 08 07
   FFFFFF83 0F 0B FFFFFFA0 FFFFFF80 06 79 01 0D 54 45 4D 50 4C 41 54
   45 74 72 65 65 20 08 08 FFFFFF83 11 0B FFFFFFC2 FFFFFF80 FFFFFF84 02 7F
   01 09 42 4C 4F 43 4B 74 72 65 65 08 08 FFFFFF83 13 0B
   FFFFFFA0 FFFFFF80 06 FFFFFF81 00 01 0A 42 4C 4F 43 4B 74 72 65 65
   20 08 09 FFFFFF83 15 0B FFFFFFC2 FFFFFF80 FFFFFF84 02 FFFFFF81 06 01 08 43 41
   53 45 74 72 65 65 08 08 FFFFFF83 17 0B FFFFFFA0 FFFFFF80 06 FFFFFF81 07
   01 09 43 41 53 45 74 72 65 65 20 08 09 FFFFFF83 19 0B
   FFFFFFC2 FFFFFF80 FFFFFF84 02 FFFFFF81 14 01 0F 41 4C 54 45 52 4E 41 54
   49 56 45 74 72 65 65 08 08 FFFFFF83 1B 0B FFFFFFA0 FFFFFF80 06 FFFFFF81
   15 01 10 41 4C 54 45 52 4E 41 54 49 56 45 74 72
   65 65 20 08 09 FFFFFF83 1D 0B FFFFFFC2 FFFFFF80 FFFFFF84 02 FFFFFF81 1B 01 08
   53 54 41 52 74 72 65 65 08 08 FFFFFF83 1F 0B FFFFFFA0 FFFFFF80 06
   FFFFFF81 1C 01 09 53 54 41 52 74 72 65 65 20 08 09 FFFFFF83
   21 0B FFFFFFC2 FFFFFF80 FFFFFF84 02 FFFFFF81 22 01 08 42 49 4E 44 74 72
   65 65 08 08 FFFFFF83 23 0B FFFFFFA0 FFFFFF80 06 FFFFFF81 23 01 09 42 49
   4E 44 74 72 65 65 20 08 09 FFFFFF83 25 0B FFFFFFC2 FFFFFF80 FFFFFF84 02
   FFFFFF81 29 01 0B 55 4E 41 50 50 4C 59 74 72 65 65 08
   08 FFFFFF83 27 0B FFFFFFA0 FFFFFF80 06 FFFFFF81 2A 01 0C 55 4E 41 50 50
   4C 59 74 72 65 65 20 08 09 FFFFFF83 29 0B FFFFFFC2 FFFFFF80 FFFFFF84 02
   FFFFFF81 30 01 0E 41 52 52 41 59 56 41 4C 55 45 74 72
   65 65 08 08 FFFFFF83 2B 0B FFFFFFA0 FFFFFF80 06 FFFFFF81 31 01 0F 41 52
   52 41 59 56 41 4C 55 45 74 72 65 65 20 08 09 FFFFFF83
   2D 0B FFFFFFC2 FFFFFF80 FFFFFF84 02 FFFFFF81 37 01 0C 46 55 4E 43 54 49
   4F 4E 74 72 65 65 08 08 FFFFFF83 2F 0B FFFFFFA0 FFFFFF80 06 FFFFFF81 38
   01 0D 46 55 4E 43 54 49 4F 4E 74 72 65 65 20 08
   09 FFFFFF83 31 0B FFFFFFC2 FFFFFF80 FFFFFF84 02 FFFFFF81 3E 01 0A 41 53 53 49
   47 4E 74 72 65 65 08 08 FFFFFF83 33 0B FFFFFFA0 FFFFFF80 06 FFFFFF81 3F
   01 0B 41 53 53 49 47 4E 74 72 65 65 20 08 09 FFFFFF83
   35 0B FFFFFFC2 FFFFFF80 FFFFFF84 02 FFFFFF81 45 01 06 49 46 74 72 65 65
   08 08 FFFFFF83 37 0B FFFFFFA0 FFFFFF80 06 FFFFFF81 46 01 07 49 46 74 72
   65 65 20 08 09 FFFFFF83 39 0B FFFFFFC2 FFFFFF80 FFFFFF84 02 FFFFFF81 4C 01 09
   4D 41 54 43 48 74 72 65 65 08 08 FFFFFF83 3B 0B FFFFFFA0 FFFFFF80
   06 FFFFFF81 4D 01 0A 4D 41 54 43 48 74 72 65 65 20 08
   09 FFFFFF83 3D 0B FFFFFFC2 FFFFFF80 FFFFFF84 02 FFFFFF81 53 01 0A 52 45 54 55
   52 4E 74 72 65 65 08 08 FFFFFF83 3F 0B FFFFFFA0 FFFFFF80 06 FFFFFF81 54
   01 0B 52 45 54 55 52 4E 74 72 65 65 20 08 09 FFFFFF83
   41 0B FFFFFFC2 FFFFFF80 FFFFFF84 02 FFFFFF81 5A 01 07 54 52 45 74 72 65
   65 08 08 FFFFFF83 43 0B FFFFFFA0 FFFFFF80 06 FFFFFF81 5B 01 08 54 52 45
   74 72 65 65 20 08 09 FFFFFF83 45 0B FFFFFFC2 FFFFFF80 FFFFFF84 02 FFFFFF81 61
   01 09 54 48 52 4F 57 74 72 65 65 08 08 FFFFFF83 47 0B
   FFFFFFA0 FFFFFF80 06 FFFFFF81 62 01 0A 54 48 52 4F 57 74 72 65 65
   20 08 09 FFFFFF83 49 0B FFFFFFC2 FFFFFF80 FFFFFF84 02 FFFFFF81 68 01 07 4E 45
   57 74 72 65 65 08 08 FFFFFF83 4B 0B FFFFFFA0 FFFFFF80 06 FFFFFF81 69 01
   08 4E 45 57 74 72 65 65 20 08 09 FFFFFF83 4D 0B FFFFFFC2 FFFFFF80
   FFFFFF84 02 FFFFFF81 6F 01 09 54 59 50 45 44 74 72 65 65 08
   08 FFFFFF83 4F 0B FFFFFFA0 FFFFFF80 06 FFFFFF81 70 01 0A 54 59 50 45 44
   74 72 65 65 20 08 09 FFFFFF83 51 0B FFFFFFC2 FFFFFF80 FFFFFF84 02 FFFFFF81 76
   01 0D 54 59 50 45 41 50 50 4C 59 74 72 65 65 08
   08 FFFFFF83 53 0B FFFFFFA0 FFFFFF80 06 FFFFFF81 77 01 0E 54 59 50 45 41
   50 50 4C 59 74 72 65 65 20 08 09 FFFFFF83 55 0B FFFFFFC2 FFFFFF80
   FFFFFF84 02 FFFFFF81 7D 01 09 41 50 50 4C 59 74 72 65 65 08
   08 FFFFFF83 57 0B FFFFFFA0 FFFFFF80 06 FFFFFF81 7E 01 0A 41 50 50 4C 59
   74 72 65 65 20 08 09 FFFFFF83 59 0B FFFFFFC2 FFFFFF80 FFFFFF84 02 FFFFFF82 04
   01 10 41 50 50 4C 59 44 59 4E 41 4D 49 43 74 72
   65 65 08 08 FFFFFF83 5B 0B FFFFFFA0 FFFFFF80 06 FFFFFF82 05 01 11 41 50
   50 4C 59 44 59 4E 41 4D 49 43 74 72 65 65 20 08
   09 FFFFFF83 5D 0B FFFFFFC2 FFFFFF80 FFFFFF84 02 FFFFFF82 0B 01 09 53 55 50 45
   52 74 72 65 65 08 08 FFFFFF83 5F 0B FFFFFFA0 FFFFFF80 06 FFFFFF82 0C 01
   0A 53 55 50 45 52 74 72 65 65 20 08 09 FFFFFF83 61 0B
   FFFFFFC2 FFFFFF80 FFFFFF84 02 FFFFFF82 12 01 08 54 48 49 53 74 72 65 65
   08 08 FFFFFF83 63 0B FFFFFFA0 FFFFFF80 06 FFFFFF82 13 01 09 54 48 49 53
   74 72 65 65 20 08 09 FFFFFF83 65 0B FFFFFFC2 FFFFFF80 FFFFFF84 02 FFFFFF82 19
   01 0A 53 45 4C 45 43 54 74 72 65 65 08 08 FFFFFF83 67
   0B FFFFFFA0 FFFFFF80 06 FFFFFF82 1A 01 0B 53 45 4C 45 43 54 74 72
   65 65 20 08 09 FFFFFF83 69 0B FFFFFFC2 FFFFFF80 FFFFFF84 02 FFFFFF82 20 01 09
   49 44 45 4E 54 74 72 65 65 08 08 FFFFFF83 6B 0B FFFFFFA0 FFFFFF80
   06 FFFFFF82 21 01 0A 49 44 45 4E 54 74 72 65 65 20 08
   09 FFFFFF83 6D 0B FFFFFFC2 FFFFFF80 FFFFFF84 02 FFFFFF83 6E 01 0B 4C 49 54 45
   52 41 4C 74 72 65 65 15 02 FFFFFF83 6F 0F 02 FFFFFF83 70 1D
   01 25 08 08 FFFFFF83 72 0B FFFFFFA0 FFFFFF80 06 FFFFFF83 6F 01 0C 4C 49
   54 45 52 41 4C 74 72 65 65 20 08 09 FFFFFF83 74 0B FFFFFFC2
   FFFFFF80 FFFFFF84 02 FFFFFF83 75 01 08 54 59 50 45 74 72 65 65 15
   02 FFFFFF83 76 0F 02 FFFFFF83 77 1D 01 26 08 08 FFFFFF83 79 0B FFFFFFA0
   FFFFFF80 06 FFFFFF83 76 01 09 54 59 50 45 74 72 65 65 20 08
   09 FFFFFF83 7B 0B FFFFFFC2 FFFFFF80 FFFFFF84 02 FFFFFF83 7C 01 0D 41 4E 4E 4F
   54 41 54 45 44 74 72 65 65 15 02 FFFFFF83 7D 0F 02 FFFFFF83
   7E 1D 01 27 08 08 FFFFFF84 00 0B FFFFFFA0 FFFFFF80 06 FFFFFF83 7D 01 0E
   41 4E 4E 4F 54 41 54 45 44 74 72 65 65 20 08 09
   FFFFFF84 02 0B FFFFFFC2 FFFFFF80 FFFFFF84 02 FFFFFF82 27 01 11 53 49 4E 47 4C
   45 54 4F 4E 54 59 50 45 74 72 65 65 08 08 FFFFFF84 04
   0B FFFFFFA0 FFFFFF80 06 FFFFFF82 28 01 12 53 49 4E 47 4C 45 54 4F
   4E 54 59 50 45 74 72 65 65 20 08 09 FFFFFF84 06 0B FFFFFFC2
   FFFFFF80 FFFFFF84 02 FFFFFF82 2E 01 12 53 45 4C 45 43 54 46 52 4F
   4D 54 59 50 45 74 72 65 65 08 08 FFFFFF84 08 0B FFFFFFA0 FFFFFF80
   06 FFFFFF82 2F 01 13 53 45 4C 45 43 54 46 52 4F 4D 54
   59 50 45 74 72 65 65 20 08 09 FFFFFF84 0A 0B FFFFFFC2 FFFFFF80 FFFFFF84
   02 FFFFFF82 35 01 10 43 4F 4D 50 4F 55 4E 44 54 59 50
   45 74 72 65 65 08 08 FFFFFF84 0C 0B FFFFFFA0 FFFFFF80 06 FFFFFF82 36 01
   11 43 4F 4D 50 4F 55 4E 44 54 59 50 45 74 72 65
   65 20 08 09 FFFFFF84 0E 0B FFFFFFC2 FFFFFF80 FFFFFF84 02 FFFFFF82 3C 01 0F 41
   50 50 4C 49 45 44 54 59 50 45 74 72 65 65 08 08
   FFFFFF84 10 0B FFFFFFA0 FFFFFF80 06 FFFFFF82 3D 01 10 41 50 50 4C 49 45
   44 54 59 50 45 74 72 65 65 20 08 09 FFFFFF84 12 0B FFFFFFC2
   FFFFFF80 FFFFFF84 02 FFFFFF82 43 01 0E 54 59 50 45 42 4F 55 4E 44
   53 74 72 65 65 08 08 FFFFFF84 14 0B FFFFFFA0 FFFFFF80 06 FFFFFF82 44 01
   0F 54 59 50 45 42 4F 55 4E 44 53 74 72 65 65 20
   08 09 FFFFFF84 16 0B FFFFFFC2 FFFFFF80 FFFFFF84 02 FFFFFF84 17 01 13 45 58 49
   53 54 45 4E 54 49 41 4C 54 59 50 45 74 72 65 65
   15 02 FFFFFF84 18 0F 02 FFFFFF84 19 1D 01 2D 08 08 FFFFFF84 1B 0B
   FFFFFFA0 FFFFFF80 06 FFFFFF84 18 01 14 45 58 49 53 54 45 4E 54 49
   41 4C 54 59 50 45 74 72 65 65 20 08 09 FFFFFF84 1D 0B
   FFFFFFC2 FFFFFF80 FFFFFF84 02 FFFFFF84 1E 01 09 4D 4F 44 49 46 49 45 52
   53 15 02 FFFFFF84 1F 0F 02 FFFFFF84 20 1D 01 32 08 08 FFFFFF84 22
   0B FFFFFFA0 FFFFFF80 06 FFFFFF84 1F 01 0A 4D 4F 44 49 46 49 45 52
   53 20 08 08 FFFFFF84 24 0B FFFFFFC2 FFFFFF80 FFFFFF84 02 39 01 0B 66 69
   72 73 74 53 79 6D 54 61 67 08 07 FFFFFF84 26 0B FFFFFFA0 FFFFFF80
   06 3A 01 0C 66 69 72 73 74 53 79 6D 54 61 67 20
   08 08 FFFFFF84 28 0B FFFFFFC2 FFFFFF80 FFFFFF84 02 5C 01 0A 6C 61 73 74
   53 79 6D 54 61 67 08 07 FFFFFF84 2A 0B FFFFFFA0 FFFFFF80 06 5D 01
   0B 6C 61 73 74 53 79 6D 54 61 67 20 08 08 FFFFFF84 2C
   0B FFFFFFC2 FFFFFF80 FFFFFF84 02 6A 01 0D 6C 61 73 74 45 78 74 53
   79 6D 54 61 67 08 07 FFFFFF84 2E 0B FFFFFFA0 FFFFFF80 06 6B 01 0E
   6C 61 73 74 45 78 74 53 79 6D 54 61 67 20 
  minor version: 0
  major version: 49
  Constant pool:
Asciz	SourceFile;
Asciz	PickleFormat.scala;
Asciz	lastExtSymTag;
Asciz	()I;
Asciz	Code;
Asciz	scala/reflect/generic/PickleFormat$;
class	scala/reflect/generic/PickleFormat$
Asciz	MODULE$;
Asciz	Lscala/reflect/generic/PickleFormat$;;
NameAndType	MODULE$:Lscala/reflect/generic/PickleFormat$;
Field	scala/reflect/generic/PickleFormat$.MODULE$:Lscala/reflect/generic/PickleFormat$;
NameAndType	lastExtSymTag:()I
Method	scala/reflect/generic/PickleFormat$.lastExtSymTag:()I
Asciz	lastSymTag;
NameAndType	lastSymTag:()I
Method	scala/reflect/generic/PickleFormat$.lastSymTag:()I
Asciz	firstSymTag;
NameAndType	firstSymTag:()I
Method	scala/reflect/generic/PickleFormat$.firstSymTag:()I
Asciz	MODIFIERS;
NameAndType	MODIFIERS:()I
Method	scala/reflect/generic/PickleFormat$.MODIFIERS:()I
Asciz	EXISTENTIALTYPEtree;
NameAndType	EXISTENTIALTYPEtree:()I
Method	scala/reflect/generic/PickleFormat$.EXISTENTIALTYPEtree:()I
Asciz	TYPEBOUNDStree;
NameAndType	TYPEBOUNDStree:()I
Method	scala/reflect/generic/PickleFormat$.TYPEBOUNDStree:()I
Asciz	APPLIEDTYPEtree;
NameAndType	APPLIEDTYPEtree:()I
Method	scala/reflect/generic/PickleFormat$.APPLIEDTYPEtree:()I
Asciz	COMPOUNDTYPEtree;
NameAndType	COMPOUNDTYPEtree:()I
Method	scala/reflect/generic/PickleFormat$.COMPOUNDTYPEtree:()I
Asciz	SELECTFROMTYPEtree;
NameAndType	SELECTFROMTYPEtree:()I
Method	scala/reflect/generic/PickleFormat$.SELECTFROMTYPEtree:()I
Asciz	SINGLETONTYPEtree;
NameAndType	SINGLETONTYPEtree:()I
Method	scala/reflect/generic/PickleFormat$.SINGLETONTYPEtree:()I
Asciz	ANNOTATEDtree;
NameAndType	ANNOTATEDtree:()I
Method	scala/reflect/generic/PickleFormat$.ANNOTATEDtree:()I
Asciz	TYPEtree;
NameAndType	TYPEtree:()I
Method	scala/reflect/generic/PickleFormat$.TYPEtree:()I
Asciz	LITERALtree;
NameAndType	LITERALtree:()I
Method	scala/reflect/generic/PickleFormat$.LITERALtree:()I
Asciz	IDENTtree;
NameAndType	IDENTtree:()I
Method	scala/reflect/generic/PickleFormat$.IDENTtree:()I
Asciz	SELECTtree;
NameAndType	SELECTtree:()I
Method	scala/reflect/generic/PickleFormat$.SELECTtree:()I
Asciz	THIStree;
NameAndType	THIStree:()I
Method	scala/reflect/generic/PickleFormat$.THIStree:()I
Asciz	SUPERtree;
NameAndType	SUPERtree:()I
Method	scala/reflect/generic/PickleFormat$.SUPERtree:()I
Asciz	APPLYDYNAMICtree;
NameAndType	APPLYDYNAMICtree:()I
Method	scala/reflect/generic/PickleFormat$.APPLYDYNAMICtree:()I
Asciz	APPLYtree;
NameAndType	APPLYtree:()I
Method	scala/reflect/generic/PickleFormat$.APPLYtree:()I
Asciz	TYPEAPPLYtree;
NameAndType	TYPEAPPLYtree:()I
Method	scala/reflect/generic/PickleFormat$.TYPEAPPLYtree:()I
Asciz	TYPEDtree;
NameAndType	TYPEDtree:()I
Method	scala/reflect/generic/PickleFormat$.TYPEDtree:()I
Asciz	NEWtree;
NameAndType	NEWtree:()I
Method	scala/reflect/generic/PickleFormat$.NEWtree:()I
Asciz	THROWtree;
NameAndType	THROWtree:()I
Method	scala/reflect/generic/PickleFormat$.THROWtree:()I
Asciz	TREtree;
NameAndType	TREtree:()I
Method	scala/reflect/generic/PickleFormat$.TREtree:()I
Asciz	RETURNtree;
NameAndType	RETURNtree:()I
Method	scala/reflect/generic/PickleFormat$.RETURNtree:()I
Asciz	MATCHtree;
NameAndType	MATCHtree:()I
Method	scala/reflect/generic/PickleFormat$.MATCHtree:()I
Asciz	IFtree;
NameAndType	IFtree:()I
Method	scala/reflect/generic/PickleFormat$.IFtree:()I
Asciz	ASSIGNtree;
NameAndType	ASSIGNtree:()I
Method	scala/reflect/generic/PickleFormat$.ASSIGNtree:()I
Asciz	FUNCTIONtree;
NameAndType	FUNCTIONtree:()I
Method	scala/reflect/generic/PickleFormat$.FUNCTIONtree:()I
Asciz	ARRAYVALUEtree;
NameAndType	ARRAYVALUEtree:()I
Method	scala/reflect/generic/PickleFormat$.ARRAYVALUEtree:()I
Asciz	UNAPPLYtree;
NameAndType	UNAPPLYtree:()I
Method	scala/reflect/generic/PickleFormat$.UNAPPLYtree:()I
Asciz	BINDtree;
NameAndType	BINDtree:()I
Method	scala/reflect/generic/PickleFormat$.BINDtree:()I
Asciz	STARtree;
NameAndType	STARtree:()I
Method	scala/reflect/generic/PickleFormat$.STARtree:()I
Asciz	ALTERNATIVEtree;
NameAndType	ALTERNATIVEtree:()I
Method	scala/reflect/generic/PickleFormat$.ALTERNATIVEtree:()I
Asciz	CASEtree;
NameAndType	CASEtree:()I
Method	scala/reflect/generic/PickleFormat$.CASEtree:()I
Asciz	BLOCKtree;
NameAndType	BLOCKtree:()I
Method	scala/reflect/generic/PickleFormat$.BLOCKtree:()I
Asciz	TEMPLATEtree;
NameAndType	TEMPLATEtree:()I
Method	scala/reflect/generic/PickleFormat$.TEMPLATEtree:()I
Asciz	DOCDEFtree;
NameAndType	DOCDEFtree:()I
Method	scala/reflect/generic/PickleFormat$.DOCDEFtree:()I
Asciz	IMPORTtree;
NameAndType	IMPORTtree:()I
Method	scala/reflect/generic/PickleFormat$.IMPORTtree:()I
Asciz	LABELtree;
NameAndType	LABELtree:()I
Method	scala/reflect/generic/PickleFormat$.LABELtree:()I
Asciz	TYPEDEFtree;
NameAndType	TYPEDEFtree:()I
Method	scala/reflect/generic/PickleFormat$.TYPEDEFtree:()I
Asciz	DEFDEFtree;
NameAndType	DEFDEFtree:()I
Method	scala/reflect/generic/PickleFormat$.DEFDEFtree:()I
Asciz	VALDEFtree;
NameAndType	VALDEFtree:()I
Method	scala/reflect/generic/PickleFormat$.VALDEFtree:()I
Asciz	MODULEtree;
NameAndType	MODULEtree:()I
Method	scala/reflect/generic/PickleFormat$.MODULEtree:()I
Asciz	CLASStree;
NameAndType	CLASStree:()I
Method	scala/reflect/generic/PickleFormat$.CLASStree:()I
Asciz	PACKAGEtree;
NameAndType	PACKAGEtree:()I
Method	scala/reflect/generic/PickleFormat$.PACKAGEtree:()I
Asciz	EMPTYtree;
NameAndType	EMPTYtree:()I
Method	scala/reflect/generic/PickleFormat$.EMPTYtree:()I
Asciz	TREE;
NameAndType	TREE:()I
Method	scala/reflect/generic/PickleFormat$.TREE:()I
Asciz	EXISTENTIALtpe;
NameAndType	EXISTENTIALtpe:()I
Method	scala/reflect/generic/PickleFormat$.EXISTENTIALtpe:()I
Asciz	DEBRUIJNINDEXtpe;
NameAndType	DEBRUIJNINDEXtpe:()I
Method	scala/reflect/generic/PickleFormat$.DEBRUIJNINDEXtpe:()I
Asciz	SUPERtpe;
NameAndType	SUPERtpe:()I
Method	scala/reflect/generic/PickleFormat$.SUPERtpe:()I
Asciz	ANNOTARGARRAY;
NameAndType	ANNOTARGARRAY:()I
Method	scala/reflect/generic/PickleFormat$.ANNOTARGARRAY:()I
Asciz	ANNOTINFO;
NameAndType	ANNOTINFO:()I
Method	scala/reflect/generic/PickleFormat$.ANNOTINFO:()I
Asciz	ANNOTATEDtpe;
NameAndType	ANNOTATEDtpe:()I
Method	scala/reflect/generic/PickleFormat$.ANNOTATEDtpe:()I
Asciz	CHILDREN;
NameAndType	CHILDREN:()I
Method	scala/reflect/generic/PickleFormat$.CHILDREN:()I
Asciz	SYMANNOT;
NameAndType	SYMANNOT:()I
Method	scala/reflect/generic/PickleFormat$.SYMANNOT:()I
Asciz	LITERALenum;
NameAndType	LITERALenum:()I
Method	scala/reflect/generic/PickleFormat$.LITERALenum:()I
Asciz	LITERALclass;
NameAndType	LITERALclass:()I
Method	scala/reflect/generic/PickleFormat$.LITERALclass:()I
Asciz	LITERALnull;
NameAndType	LITERALnull:()I
Method	scala/reflect/generic/PickleFormat$.LITERALnull:()I
Asciz	LITERALstring;
NameAndType	LITERALstring:()I
Method	scala/reflect/generic/PickleFormat$.LITERALstring:()I
Asciz	LITERALdouble;
NameAndType	LITERALdouble:()I
Method	scala/reflect/generic/PickleFormat$.LITERALdouble:()I
Asciz	LITERALfloat;
NameAndType	LITERALfloat:()I
Method	scala/reflect/generic/PickleFormat$.LITERALfloat:()I
Asciz	LITERALlong;
NameAndType	LITERALlong:()I
Method	scala/reflect/generic/PickleFormat$.LITERALlong:()I
Asciz	LITERALint;
NameAndType	LITERALint:()I
Method	scala/reflect/generic/PickleFormat$.LITERALint:()I
Asciz	LITERALchar;
NameAndType	LITERALchar:()I
Method	scala/reflect/generic/PickleFormat$.LITERALchar:()I
Asciz	LITERALshort;
NameAndType	LITERALshort:()I
Method	scala/reflect/generic/PickleFormat$.LITERALshort:()I
Asciz	LITERALbyte;
NameAndType	LITERALbyte:()I
Method	scala/reflect/generic/PickleFormat$.LITERALbyte:()I
Asciz	LITERALboolean;
NameAndType	LITERALboolean:()I
Method	scala/reflect/generic/PickleFormat$.LITERALboolean:()I
Asciz	LITERALunit;
NameAndType	LITERALunit:()I
Method	scala/reflect/generic/PickleFormat$.LITERALunit:()I
Asciz	LITERAL;
NameAndType	LITERAL:()I
Method	scala/reflect/generic/PickleFormat$.LITERAL:()I
Asciz	IMPLICITMETHODtpe;
NameAndType	IMPLICITMETHODtpe:()I
Method	scala/reflect/generic/PickleFormat$.IMPLICITMETHODtpe:()I
Asciz	POLYtpe;
NameAndType	POLYtpe:()I
Method	scala/reflect/generic/PickleFormat$.POLYtpe:()I
Asciz	METHODtpe;
NameAndType	METHODtpe:()I
Method	scala/reflect/generic/PickleFormat$.METHODtpe:()I
Asciz	CLASSINFOtpe;
NameAndType	CLASSINFOtpe:()I
Method	scala/reflect/generic/PickleFormat$.CLASSINFOtpe:()I
Asciz	REFINEDtpe;
NameAndType	REFINEDtpe:()I
Method	scala/reflect/generic/PickleFormat$.REFINEDtpe:()I
Asciz	TYPEBOUNDStpe;
NameAndType	TYPEBOUNDStpe:()I
Method	scala/reflect/generic/PickleFormat$.TYPEBOUNDStpe:()I
Asciz	TYPEREFtpe;
NameAndType	TYPEREFtpe:()I
Method	scala/reflect/generic/PickleFormat$.TYPEREFtpe:()I
Asciz	CONSTANTtpe;
NameAndType	CONSTANTtpe:()I
Method	scala/reflect/generic/PickleFormat$.CONSTANTtpe:()I
Asciz	SINGLEtpe;
NameAndType	SINGLEtpe:()I
Method	scala/reflect/generic/PickleFormat$.SINGLEtpe:()I
Asciz	THIStpe;
NameAndType	THIStpe:()I
Method	scala/reflect/generic/PickleFormat$.THIStpe:()I
Asciz	NOPREFIXtpe;
NameAndType	NOPREFIXtpe:()I
Method	scala/reflect/generic/PickleFormat$.NOPREFIXtpe:()I
Asciz	NOtpe;
NameAndType	NOtpe:()I
Method	scala/reflect/generic/PickleFormat$.NOtpe:()I
Asciz	EXTMODCLASSref;
NameAndType	EXTMODCLASSref:()I
Method	scala/reflect/generic/PickleFormat$.EXTMODCLASSref:()I
Asciz	EXTref;
NameAndType	EXTref:()I
Method	scala/reflect/generic/PickleFormat$.EXTref:()I
Asciz	VALsym;
NameAndType	VALsym:()I
Method	scala/reflect/generic/PickleFormat$.VALsym:()I
Asciz	MODULEsym;
NameAndType	MODULEsym:()I
Method	scala/reflect/generic/PickleFormat$.MODULEsym:()I
Asciz	CLASSsym;
NameAndType	CLASSsym:()I
Method	scala/reflect/generic/PickleFormat$.CLASSsym:()I
Asciz	ALIASsym;
NameAndType	ALIASsym:()I
Method	scala/reflect/generic/PickleFormat$.ALIASsym:()I
Asciz	TYPEsym;
NameAndType	TYPEsym:()I
Method	scala/reflect/generic/PickleFormat$.TYPEsym:()I
Asciz	NONEsym;
NameAndType	NONEsym:()I
Method	scala/reflect/generic/PickleFormat$.NONEsym:()I
Asciz	TYPEname;
NameAndType	TYPEname:()I
Method	scala/reflect/generic/PickleFormat$.TYPEname:()I
Asciz	TERMname;
NameAndType	TERMname:()I
Method	scala/reflect/generic/PickleFormat$.TERMname:()I
Asciz	MinorVersion;
NameAndType	MinorVersion:()I
Method	scala/reflect/generic/PickleFormat$.MinorVersion:()I
Asciz	MajorVersion;
NameAndType	MajorVersion:()I
Method	scala/reflect/generic/PickleFormat$.MajorVersion:()I
Asciz	ScalaSig;
Asciz	scala/reflect/generic/PickleFormat;
class	scala/reflect/generic/PickleFormat
Asciz	java/lang/Object;
class	java/lang/Object

{
public static final int lastExtSymTag();
  Signature: ()I
  Code:
   Stack=1, Locals=0, Args_size=0
	getstatic	Field scala/reflect/generic/PickleFormat$.MODULE$:Lscala/reflect/generic/PickleFormat$;
	invokevirtual	Method scala/reflect/generic/PickleFormat$.lastExtSymTag:()I
	ireturn
  Labels:

public static final int lastSymTag();
  Signature: ()I
  Code:
   Stack=1, Locals=0, Args_size=0
	getstatic	Field scala/reflect/generic/PickleFormat$.MODULE$:Lscala/reflect/generic/PickleFormat$;
	invokevirtual	Method scala/reflect/generic/PickleFormat$.lastSymTag:()I
	ireturn
  Labels:

public static final int firstSymTag();
  Signature: ()I
  Code:
   Stack=1, Locals=0, Args_size=0
	getstatic	Field scala/reflect/generic/PickleFormat$.MODULE$:Lscala/reflect/generic/PickleFormat$;
	invokevirtual	Method scala/reflect/generic/PickleFormat$.firstSymTag:()I
	ireturn
  Labels:

public static final int MODIFIERS();
  Signature: ()I
  Code:
   Stack=1, Locals=0, Args_size=0
	getstatic	Field scala/reflect/generic/PickleFormat$.MODULE$:Lscala/reflect/generic/PickleFormat$;
	invokevirtual	Method scala/reflect/generic/PickleFormat$.MODIFIERS:()I
	ireturn
  Labels:

public static final int EXISTENTIALTYPEtree();
  Signature: ()I
  Code:
   Stack=1, Locals=0, Args_size=0
	getstatic	Field scala/reflect/generic/PickleFormat$.MODULE$:Lscala/reflect/generic/PickleFormat$;
	invokevirtual	Method scala/reflect/generic/PickleFormat$.EXISTENTIALTYPEtree:()I
	ireturn
  Labels:

public static final int TYPEBOUNDStree();
  Signature: ()I
  Code:
   Stack=1, Locals=0, Args_size=0
	getstatic	Field scala/reflect/generic/PickleFormat$.MODULE$:Lscala/reflect/generic/PickleFormat$;
	invokevirtual	Method scala/reflect/generic/PickleFormat$.TYPEBOUNDStree:()I
	ireturn
  Labels:

public static final int APPLIEDTYPEtree();
  Signature: ()I
  Code:
   Stack=1, Locals=0, Args_size=0
	getstatic	Field scala/reflect/generic/PickleFormat$.MODULE$:Lscala/reflect/generic/PickleFormat$;
	invokevirtual	Method scala/reflect/generic/PickleFormat$.APPLIEDTYPEtree:()I
	ireturn
  Labels:

public static final int COMPOUNDTYPEtree();
  Signature: ()I
  Code:
   Stack=1, Locals=0, Args_size=0
	getstatic	Field scala/reflect/generic/PickleFormat$.MODULE$:Lscala/reflect/generic/PickleFormat$;
	invokevirtual	Method scala/reflect/generic/PickleFormat$.COMPOUNDTYPEtree:()I
	ireturn
  Labels:

public static final int SELECTFROMTYPEtree();
  Signature: ()I
  Code:
   Stack=1, Locals=0, Args_size=0
	getstatic	Field scala/reflect/generic/PickleFormat$.MODULE$:Lscala/reflect/generic/PickleFormat$;
	invokevirtual	Method scala/reflect/generic/PickleFormat$.SELECTFROMTYPEtree:()I
	ireturn
  Labels:

public static final int SINGLETONTYPEtree();
  Signature: ()I
  Code:
   Stack=1, Locals=0, Args_size=0
	getstatic	Field scala/reflect/generic/PickleFormat$.MODULE$:Lscala/reflect/generic/PickleFormat$;
	invokevirtual	Method scala/reflect/generic/PickleFormat$.SINGLETONTYPEtree:()I
	ireturn
  Labels:

public static final int ANNOTATEDtree();
  Signature: ()I
  Code:
   Stack=1, Locals=0, Args_size=0
	getstatic	Field scala/reflect/generic/PickleFormat$.MODULE$:Lscala/reflect/generic/PickleFormat$;
	invokevirtual	Method scala/reflect/generic/PickleFormat$.ANNOTATEDtree:()I
	ireturn
  Labels:

public static final int TYPEtree();
  Signature: ()I
  Code:
   Stack=1, Locals=0, Args_size=0
	getstatic	Field scala/reflect/generic/PickleFormat$.MODULE$:Lscala/reflect/generic/PickleFormat$;
	invokevirtual	Method scala/reflect/generic/PickleFormat$.TYPEtree:()I
	ireturn
  Labels:

public static final int LITERALtree();
  Signature: ()I
  Code:
   Stack=1, Locals=0, Args_size=0
	getstatic	Field scala/reflect/generic/PickleFormat$.MODULE$:Lscala/reflect/generic/PickleFormat$;
	invokevirtual	Method scala/reflect/generic/PickleFormat$.LITERALtree:()I
	ireturn
  Labels:

public static final int IDENTtree();
  Signature: ()I
  Code:
   Stack=1, Locals=0, Args_size=0
	getstatic	Field scala/reflect/generic/PickleFormat$.MODULE$:Lscala/reflect/generic/PickleFormat$;
	invokevirtual	Method scala/reflect/generic/PickleFormat$.IDENTtree:()I
	ireturn
  Labels:

public static final int SELECTtree();
  Signature: ()I
  Code:
   Stack=1, Locals=0, Args_size=0
	getstatic	Field scala/reflect/generic/PickleFormat$.MODULE$:Lscala/reflect/generic/PickleFormat$;
	invokevirtual	Method scala/reflect/generic/PickleFormat$.SELECTtree:()I
	ireturn
  Labels:

public static final int THIStree();
  Signature: ()I
  Code:
   Stack=1, Locals=0, Args_size=0
	getstatic	Field scala/reflect/generic/PickleFormat$.MODULE$:Lscala/reflect/generic/PickleFormat$;
	invokevirtual	Method scala/reflect/generic/PickleFormat$.THIStree:()I
	ireturn
  Labels:

public static final int SUPERtree();
  Signature: ()I
  Code:
   Stack=1, Locals=0, Args_size=0
	getstatic	Field scala/reflect/generic/PickleFormat$.MODULE$:Lscala/reflect/generic/PickleFormat$;
	invokevirtual	Method scala/reflect/generic/PickleFormat$.SUPERtree:()I
	ireturn
  Labels:

public static final int APPLYDYNAMICtree();
  Signature: ()I
  Code:
   Stack=1, Locals=0, Args_size=0
	getstatic	Field scala/reflect/generic/PickleFormat$.MODULE$:Lscala/reflect/generic/PickleFormat$;
	invokevirtual	Method scala/reflect/generic/PickleFormat$.APPLYDYNAMICtree:()I
	ireturn
  Labels:

public static final int APPLYtree();
  Signature: ()I
  Code:
   Stack=1, Locals=0, Args_size=0
	getstatic	Field scala/reflect/generic/PickleFormat$.MODULE$:Lscala/reflect/generic/PickleFormat$;
	invokevirtual	Method scala/reflect/generic/PickleFormat$.APPLYtree:()I
	ireturn
  Labels:

public static final int TYPEAPPLYtree();
  Signature: ()I
  Code:
   Stack=1, Locals=0, Args_size=0
	getstatic	Field scala/reflect/generic/PickleFormat$.MODULE$:Lscala/reflect/generic/PickleFormat$;
	invokevirtual	Method scala/reflect/generic/PickleFormat$.TYPEAPPLYtree:()I
	ireturn
  Labels:

public static final int TYPEDtree();
  Signature: ()I
  Code:
   Stack=1, Locals=0, Args_size=0
	getstatic	Field scala/reflect/generic/PickleFormat$.MODULE$:Lscala/reflect/generic/PickleFormat$;
	invokevirtual	Method scala/reflect/generic/PickleFormat$.TYPEDtree:()I
	ireturn
  Labels:

public static final int NEWtree();
  Signature: ()I
  Code:
   Stack=1, Locals=0, Args_size=0
	getstatic	Field scala/reflect/generic/PickleFormat$.MODULE$:Lscala/reflect/generic/PickleFormat$;
	invokevirtual	Method scala/reflect/generic/PickleFormat$.NEWtree:()I
	ireturn
  Labels:

public static final int THROWtree();
  Signature: ()I
  Code:
   Stack=1, Locals=0, Args_size=0
	getstatic	Field scala/reflect/generic/PickleFormat$.MODULE$:Lscala/reflect/generic/PickleFormat$;
	invokevirtual	Method scala/reflect/generic/PickleFormat$.THROWtree:()I
	ireturn
  Labels:

public static final int TREtree();
  Signature: ()I
  Code:
   Stack=1, Locals=0, Args_size=0
	getstatic	Field scala/reflect/generic/PickleFormat$.MODULE$:Lscala/reflect/generic/PickleFormat$;
	invokevirtual	Method scala/reflect/generic/PickleFormat$.TREtree:()I
	ireturn
  Labels:

public static final int RETURNtree();
  Signature: ()I
  Code:
   Stack=1, Locals=0, Args_size=0
	getstatic	Field scala/reflect/generic/PickleFormat$.MODULE$:Lscala/reflect/generic/PickleFormat$;
	invokevirtual	Method scala/reflect/generic/PickleFormat$.RETURNtree:()I
	ireturn
  Labels:

public static final int MATCHtree();
  Signature: ()I
  Code:
   Stack=1, Locals=0, Args_size=0
	getstatic	Field scala/reflect/generic/PickleFormat$.MODULE$:Lscala/reflect/generic/PickleFormat$;
	invokevirtual	Method scala/reflect/generic/PickleFormat$.MATCHtree:()I
	ireturn
  Labels:

public static final int IFtree();
  Signature: ()I
  Code:
   Stack=1, Locals=0, Args_size=0
	getstatic	Field scala/reflect/generic/PickleFormat$.MODULE$:Lscala/reflect/generic/PickleFormat$;
	invokevirtual	Method scala/reflect/generic/PickleFormat$.IFtree:()I
	ireturn
  Labels:

public static final int ASSIGNtree();
  Signature: ()I
  Code:
   Stack=1, Locals=0, Args_size=0
	getstatic	Field scala/reflect/generic/PickleFormat$.MODULE$:Lscala/reflect/generic/PickleFormat$;
	invokevirtual	Method scala/reflect/generic/PickleFormat$.ASSIGNtree:()I
	ireturn
  Labels:

public static final int FUNCTIONtree();
  Signature: ()I
  Code:
   Stack=1, Locals=0, Args_size=0
	getstatic	Field scala/reflect/generic/PickleFormat$.MODULE$:Lscala/reflect/generic/PickleFormat$;
	invokevirtual	Method scala/reflect/generic/PickleFormat$.FUNCTIONtree:()I
	ireturn
  Labels:

public static final int ARRAYVALUEtree();
  Signature: ()I
  Code:
   Stack=1, Locals=0, Args_size=0
	getstatic	Field scala/reflect/generic/PickleFormat$.MODULE$:Lscala/reflect/generic/PickleFormat$;
	invokevirtual	Method scala/reflect/generic/PickleFormat$.ARRAYVALUEtree:()I
	ireturn
  Labels:

public static final int UNAPPLYtree();
  Signature: ()I
  Code:
   Stack=1, Locals=0, Args_size=0
	getstatic	Field scala/reflect/generic/PickleFormat$.MODULE$:Lscala/reflect/generic/PickleFormat$;
	invokevirtual	Method scala/reflect/generic/PickleFormat$.UNAPPLYtree:()I
	ireturn
  Labels:

public static final int BINDtree();
  Signature: ()I
  Code:
   Stack=1, Locals=0, Args_size=0
	getstatic	Field scala/reflect/generic/PickleFormat$.MODULE$:Lscala/reflect/generic/PickleFormat$;
	invokevirtual	Method scala/reflect/generic/PickleFormat$.BINDtree:()I
	ireturn
  Labels:

public static final int STARtree();
  Signature: ()I
  Code:
   Stack=1, Locals=0, Args_size=0
	getstatic	Field scala/reflect/generic/PickleFormat$.MODULE$:Lscala/reflect/generic/PickleFormat$;
	invokevirtual	Method scala/reflect/generic/PickleFormat$.STARtree:()I
	ireturn
  Labels:

public static final int ALTERNATIVEtree();
  Signature: ()I
  Code:
   Stack=1, Locals=0, Args_size=0
	getstatic	Field scala/reflect/generic/PickleFormat$.MODULE$:Lscala/reflect/generic/PickleFormat$;
	invokevirtual	Method scala/reflect/generic/PickleFormat$.ALTERNATIVEtree:()I
	ireturn
  Labels:

public static final int CASEtree();
  Signature: ()I
  Code:
   Stack=1, Locals=0, Args_size=0
	getstatic	Field scala/reflect/generic/PickleFormat$.MODULE$:Lscala/reflect/generic/PickleFormat$;
	invokevirtual	Method scala/reflect/generic/PickleFormat$.CASEtree:()I
	ireturn
  Labels:

public static final int BLOCKtree();
  Signature: ()I
  Code:
   Stack=1, Locals=0, Args_size=0
	getstatic	Field scala/reflect/generic/PickleFormat$.MODULE$:Lscala/reflect/generic/PickleFormat$;
	invokevirtual	Method scala/reflect/generic/PickleFormat$.BLOCKtree:()I
	ireturn
  Labels:

public static final int TEMPLATEtree();
  Signature: ()I
  Code:
   Stack=1, Locals=0, Args_size=0
	getstatic	Field scala/reflect/generic/PickleFormat$.MODULE$:Lscala/reflect/generic/PickleFormat$;
	invokevirtual	Method scala/reflect/generic/PickleFormat$.TEMPLATEtree:()I
	ireturn
  Labels:

public static final int DOCDEFtree();
  Signature: ()I
  Code:
   Stack=1, Locals=0, Args_size=0
	getstatic	Field scala/reflect/generic/PickleFormat$.MODULE$:Lscala/reflect/generic/PickleFormat$;
	invokevirtual	Method scala/reflect/generic/PickleFormat$.DOCDEFtree:()I
	ireturn
  Labels:

public static final int IMPORTtree();
  Signature: ()I
  Code:
   Stack=1, Locals=0, Args_size=0
	getstatic	Field scala/reflect/generic/PickleFormat$.MODULE$:Lscala/reflect/generic/PickleFormat$;
	invokevirtual	Method scala/reflect/generic/PickleFormat$.IMPORTtree:()I
	ireturn
  Labels:

public static final int LABELtree();
  Signature: ()I
  Code:
   Stack=1, Locals=0, Args_size=0
	getstatic	Field scala/reflect/generic/PickleFormat$.MODULE$:Lscala/reflect/generic/PickleFormat$;
	invokevirtual	Method scala/reflect/generic/PickleFormat$.LABELtree:()I
	ireturn
  Labels:

public static final int TYPEDEFtree();
  Signature: ()I
  Code:
   Stack=1, Locals=0, Args_size=0
	getstatic	Field scala/reflect/generic/PickleFormat$.MODULE$:Lscala/reflect/generic/PickleFormat$;
	invokevirtual	Method scala/reflect/generic/PickleFormat$.TYPEDEFtree:()I
	ireturn
  Labels:

public static final int DEFDEFtree();
  Signature: ()I
  Code:
   Stack=1, Locals=0, Args_size=0
	getstatic	Field scala/reflect/generic/PickleFormat$.MODULE$:Lscala/reflect/generic/PickleFormat$;
	invokevirtual	Method scala/reflect/generic/PickleFormat$.DEFDEFtree:()I
	ireturn
  Labels:

public static final int VALDEFtree();
  Signature: ()I
  Code:
   Stack=1, Locals=0, Args_size=0
	getstatic	Field scala/reflect/generic/PickleFormat$.MODULE$:Lscala/reflect/generic/PickleFormat$;
	invokevirtual	Method scala/reflect/generic/PickleFormat$.VALDEFtree:()I
	ireturn
  Labels:

public static final int MODULEtree();
  Signature: ()I
  Code:
   Stack=1, Locals=0, Args_size=0
	getstatic	Field scala/reflect/generic/PickleFormat$.MODULE$:Lscala/reflect/generic/PickleFormat$;
	invokevirtual	Method scala/reflect/generic/PickleFormat$.MODULEtree:()I
	ireturn
  Labels:

public static final int CLASStree();
  Signature: ()I
  Code:
   Stack=1, Locals=0, Args_size=0
	getstatic	Field scala/reflect/generic/PickleFormat$.MODULE$:Lscala/reflect/generic/PickleFormat$;
	invokevirtual	Method scala/reflect/generic/PickleFormat$.CLASStree:()I
	ireturn
  Labels:

public static final int PACKAGEtree();
  Signature: ()I
  Code:
   Stack=1, Locals=0, Args_size=0
	getstatic	Field scala/reflect/generic/PickleFormat$.MODULE$:Lscala/reflect/generic/PickleFormat$;
	invokevirtual	Method scala/reflect/generic/PickleFormat$.PACKAGEtree:()I
	ireturn
  Labels:

public static final int EMPTYtree();
  Signature: ()I
  Code:
   Stack=1, Locals=0, Args_size=0
	getstatic	Field scala/reflect/generic/PickleFormat$.MODULE$:Lscala/reflect/generic/PickleFormat$;
	invokevirtual	Method scala/reflect/generic/PickleFormat$.EMPTYtree:()I
	ireturn
  Labels:

public static final int TREE();
  Signature: ()I
  Code:
   Stack=1, Locals=0, Args_size=0
	getstatic	Field scala/reflect/generic/PickleFormat$.MODULE$:Lscala/reflect/generic/PickleFormat$;
	invokevirtual	Method scala/reflect/generic/PickleFormat$.TREE:()I
	ireturn
  Labels:

public static final int EXISTENTIALtpe();
  Signature: ()I
  Code:
   Stack=1, Locals=0, Args_size=0
	getstatic	Field scala/reflect/generic/PickleFormat$.MODULE$:Lscala/reflect/generic/PickleFormat$;
	invokevirtual	Method scala/reflect/generic/PickleFormat$.EXISTENTIALtpe:()I
	ireturn
  Labels:

public static final int DEBRUIJNINDEXtpe();
  Signature: ()I
  Code:
   Stack=1, Locals=0, Args_size=0
	getstatic	Field scala/reflect/generic/PickleFormat$.MODULE$:Lscala/reflect/generic/PickleFormat$;
	invokevirtual	Method scala/reflect/generic/PickleFormat$.DEBRUIJNINDEXtpe:()I
	ireturn
  Labels:

public static final int SUPERtpe();
  Signature: ()I
  Code:
   Stack=1, Locals=0, Args_size=0
	getstatic	Field scala/reflect/generic/PickleFormat$.MODULE$:Lscala/reflect/generic/PickleFormat$;
	invokevirtual	Method scala/reflect/generic/PickleFormat$.SUPERtpe:()I
	ireturn
  Labels:

public static final int ANNOTARGARRAY();
  Signature: ()I
  Code:
   Stack=1, Locals=0, Args_size=0
	getstatic	Field scala/reflect/generic/PickleFormat$.MODULE$:Lscala/reflect/generic/PickleFormat$;
	invokevirtual	Method scala/reflect/generic/PickleFormat$.ANNOTARGARRAY:()I
	ireturn
  Labels:

public static final int ANNOTINFO();
  Signature: ()I
  Code:
   Stack=1, Locals=0, Args_size=0
	getstatic	Field scala/reflect/generic/PickleFormat$.MODULE$:Lscala/reflect/generic/PickleFormat$;
	invokevirtual	Method scala/reflect/generic/PickleFormat$.ANNOTINFO:()I
	ireturn
  Labels:

public static final int ANNOTATEDtpe();
  Signature: ()I
  Code:
   Stack=1, Locals=0, Args_size=0
	getstatic	Field scala/reflect/generic/PickleFormat$.MODULE$:Lscala/reflect/generic/PickleFormat$;
	invokevirtual	Method scala/reflect/generic/PickleFormat$.ANNOTATEDtpe:()I
	ireturn
  Labels:

public static final int CHILDREN();
  Signature: ()I
  Code:
   Stack=1, Locals=0, Args_size=0
	getstatic	Field scala/reflect/generic/PickleFormat$.MODULE$:Lscala/reflect/generic/PickleFormat$;
	invokevirtual	Method scala/reflect/generic/PickleFormat$.CHILDREN:()I
	ireturn
  Labels:

public static final int SYMANNOT();
  Signature: ()I
  Code:
   Stack=1, Locals=0, Args_size=0
	getstatic	Field scala/reflect/generic/PickleFormat$.MODULE$:Lscala/reflect/generic/PickleFormat$;
	invokevirtual	Method scala/reflect/generic/PickleFormat$.SYMANNOT:()I
	ireturn
  Labels:

public static final int LITERALenum();
  Signature: ()I
  Code:
   Stack=1, Locals=0, Args_size=0
	getstatic	Field scala/reflect/generic/PickleFormat$.MODULE$:Lscala/reflect/generic/PickleFormat$;
	invokevirtual	Method scala/reflect/generic/PickleFormat$.LITERALenum:()I
	ireturn
  Labels:

public static final int LITERALclass();
  Signature: ()I
  Code:
   Stack=1, Locals=0, Args_size=0
	getstatic	Field scala/reflect/generic/PickleFormat$.MODULE$:Lscala/reflect/generic/PickleFormat$;
	invokevirtual	Method scala/reflect/generic/PickleFormat$.LITERALclass:()I
	ireturn
  Labels:

public static final int LITERALnull();
  Signature: ()I
  Code:
   Stack=1, Locals=0, Args_size=0
	getstatic	Field scala/reflect/generic/PickleFormat$.MODULE$:Lscala/reflect/generic/PickleFormat$;
	invokevirtual	Method scala/reflect/generic/PickleFormat$.LITERALnull:()I
	ireturn
  Labels:

public static final int LITERALstring();
  Signature: ()I
  Code:
   Stack=1, Locals=0, Args_size=0
	getstatic	Field scala/reflect/generic/PickleFormat$.MODULE$:Lscala/reflect/generic/PickleFormat$;
	invokevirtual	Method scala/reflect/generic/PickleFormat$.LITERALstring:()I
	ireturn
  Labels:

public static final int LITERALdouble();
  Signature: ()I
  Code:
   Stack=1, Locals=0, Args_size=0
	getstatic	Field scala/reflect/generic/PickleFormat$.MODULE$:Lscala/reflect/generic/PickleFormat$;
	invokevirtual	Method scala/reflect/generic/PickleFormat$.LITERALdouble:()I
	ireturn
  Labels:

public static final int LITERALfloat();
  Signature: ()I
  Code:
   Stack=1, Locals=0, Args_size=0
	getstatic	Field scala/reflect/generic/PickleFormat$.MODULE$:Lscala/reflect/generic/PickleFormat$;
	invokevirtual	Method scala/reflect/generic/PickleFormat$.LITERALfloat:()I
	ireturn
  Labels:

public static final int LITERALlong();
  Signature: ()I
  Code:
   Stack=1, Locals=0, Args_size=0
	getstatic	Field scala/reflect/generic/PickleFormat$.MODULE$:Lscala/reflect/generic/PickleFormat$;
	invokevirtual	Method scala/reflect/generic/PickleFormat$.LITERALlong:()I
	ireturn
  Labels:

public static final int LITERALint();
  Signature: ()I
  Code:
   Stack=1, Locals=0, Args_size=0
	getstatic	Field scala/reflect/generic/PickleFormat$.MODULE$:Lscala/reflect/generic/PickleFormat$;
	invokevirtual	Method scala/reflect/generic/PickleFormat$.LITERALint:()I
	ireturn
  Labels:

public static final int LITERALchar();
  Signature: ()I
  Code:
   Stack=1, Locals=0, Args_size=0
	getstatic	Field scala/reflect/generic/PickleFormat$.MODULE$:Lscala/reflect/generic/PickleFormat$;
	invokevirtual	Method scala/reflect/generic/PickleFormat$.LITERALchar:()I
	ireturn
  Labels:

public static final int LITERALshort();
  Signature: ()I
  Code:
   Stack=1, Locals=0, Args_size=0
	getstatic	Field scala/reflect/generic/PickleFormat$.MODULE$:Lscala/reflect/generic/PickleFormat$;
	invokevirtual	Method scala/reflect/generic/PickleFormat$.LITERALshort:()I
	ireturn
  Labels:

public static final int LITERALbyte();
  Signature: ()I
  Code:
   Stack=1, Locals=0, Args_size=0
	getstatic	Field scala/reflect/generic/PickleFormat$.MODULE$:Lscala/reflect/generic/PickleFormat$;
	invokevirtual	Method scala/reflect/generic/PickleFormat$.LITERALbyte:()I
	ireturn
  Labels:

public static final int LITERALboolean();
  Signature: ()I
  Code:
   Stack=1, Locals=0, Args_size=0
	getstatic	Field scala/reflect/generic/PickleFormat$.MODULE$:Lscala/reflect/generic/PickleFormat$;
	invokevirtual	Method scala/reflect/generic/PickleFormat$.LITERALboolean:()I
	ireturn
  Labels:

public static final int LITERALunit();
  Signature: ()I
  Code:
   Stack=1, Locals=0, Args_size=0
	getstatic	Field scala/reflect/generic/PickleFormat$.MODULE$:Lscala/reflect/generic/PickleFormat$;
	invokevirtual	Method scala/reflect/generic/PickleFormat$.LITERALunit:()I
	ireturn
  Labels:

public static final int LITERAL();
  Signature: ()I
  Code:
   Stack=1, Locals=0, Args_size=0
	getstatic	Field scala/reflect/generic/PickleFormat$.MODULE$:Lscala/reflect/generic/PickleFormat$;
	invokevirtual	Method scala/reflect/generic/PickleFormat$.LITERAL:()I
	ireturn
  Labels:

public static final int IMPLICITMETHODtpe();
  Signature: ()I
  Code:
   Stack=1, Locals=0, Args_size=0
	getstatic	Field scala/reflect/generic/PickleFormat$.MODULE$:Lscala/reflect/generic/PickleFormat$;
	invokevirtual	Method scala/reflect/generic/PickleFormat$.IMPLICITMETHODtpe:()I
	ireturn
  Labels:

public static final int POLYtpe();
  Signature: ()I
  Code:
   Stack=1, Locals=0, Args_size=0
	getstatic	Field scala/reflect/generic/PickleFormat$.MODULE$:Lscala/reflect/generic/PickleFormat$;
	invokevirtual	Method scala/reflect/generic/PickleFormat$.POLYtpe:()I
	ireturn
  Labels:

public static final int METHODtpe();
  Signature: ()I
  Code:
   Stack=1, Locals=0, Args_size=0
	getstatic	Field scala/reflect/generic/PickleFormat$.MODULE$:Lscala/reflect/generic/PickleFormat$;
	invokevirtual	Method scala/reflect/generic/PickleFormat$.METHODtpe:()I
	ireturn
  Labels:

public static final int CLASSINFOtpe();
  Signature: ()I
  Code:
   Stack=1, Locals=0, Args_size=0
	getstatic	Field scala/reflect/generic/PickleFormat$.MODULE$:Lscala/reflect/generic/PickleFormat$;
	invokevirtual	Method scala/reflect/generic/PickleFormat$.CLASSINFOtpe:()I
	ireturn
  Labels:

public static final int REFINEDtpe();
  Signature: ()I
  Code:
   Stack=1, Locals=0, Args_size=0
	getstatic	Field scala/reflect/generic/PickleFormat$.MODULE$:Lscala/reflect/generic/PickleFormat$;
	invokevirtual	Method scala/reflect/generic/PickleFormat$.REFINEDtpe:()I
	ireturn
  Labels:

public static final int TYPEBOUNDStpe();
  Signature: ()I
  Code:
   Stack=1, Locals=0, Args_size=0
	getstatic	Field scala/reflect/generic/PickleFormat$.MODULE$:Lscala/reflect/generic/PickleFormat$;
	invokevirtual	Method scala/reflect/generic/PickleFormat$.TYPEBOUNDStpe:()I
	ireturn
  Labels:

public static final int TYPEREFtpe();
  Signature: ()I
  Code:
   Stack=1, Locals=0, Args_size=0
	getstatic	Field scala/reflect/generic/PickleFormat$.MODULE$:Lscala/reflect/generic/PickleFormat$;
	invokevirtual	Method scala/reflect/generic/PickleFormat$.TYPEREFtpe:()I
	ireturn
  Labels:

public static final int CONSTANTtpe();
  Signature: ()I
  Code:
   Stack=1, Locals=0, Args_size=0
	getstatic	Field scala/reflect/generic/PickleFormat$.MODULE$:Lscala/reflect/generic/PickleFormat$;
	invokevirtual	Method scala/reflect/generic/PickleFormat$.CONSTANTtpe:()I
	ireturn
  Labels:

public static final int SINGLEtpe();
  Signature: ()I
  Code:
   Stack=1, Locals=0, Args_size=0
	getstatic	Field scala/reflect/generic/PickleFormat$.MODULE$:Lscala/reflect/generic/PickleFormat$;
	invokevirtual	Method scala/reflect/generic/PickleFormat$.SINGLEtpe:()I
	ireturn
  Labels:

public static final int THIStpe();
  Signature: ()I
  Code:
   Stack=1, Locals=0, Args_size=0
	getstatic	Field scala/reflect/generic/PickleFormat$.MODULE$:Lscala/reflect/generic/PickleFormat$;
	invokevirtual	Method scala/reflect/generic/PickleFormat$.THIStpe:()I
	ireturn
  Labels:

public static final int NOPREFIXtpe();
  Signature: ()I
  Code:
   Stack=1, Locals=0, Args_size=0
	getstatic	Field scala/reflect/generic/PickleFormat$.MODULE$:Lscala/reflect/generic/PickleFormat$;
	invokevirtual	Method scala/reflect/generic/PickleFormat$.NOPREFIXtpe:()I
	ireturn
  Labels:

public static final int NOtpe();
  Signature: ()I
  Code:
   Stack=1, Locals=0, Args_size=0
	getstatic	Field scala/reflect/generic/PickleFormat$.MODULE$:Lscala/reflect/generic/PickleFormat$;
	invokevirtual	Method scala/reflect/generic/PickleFormat$.NOtpe:()I
	ireturn
  Labels:

public static final int EXTMODCLASSref();
  Signature: ()I
  Code:
   Stack=1, Locals=0, Args_size=0
	getstatic	Field scala/reflect/generic/PickleFormat$.MODULE$:Lscala/reflect/generic/PickleFormat$;
	invokevirtual	Method scala/reflect/generic/PickleFormat$.EXTMODCLASSref:()I
	ireturn
  Labels:

public static final int EXTref();
  Signature: ()I
  Code:
   Stack=1, Locals=0, Args_size=0
	getstatic	Field scala/reflect/generic/PickleFormat$.MODULE$:Lscala/reflect/generic/PickleFormat$;
	invokevirtual	Method scala/reflect/generic/PickleFormat$.EXTref:()I
	ireturn
  Labels:

public static final int VALsym();
  Signature: ()I
  Code:
   Stack=1, Locals=0, Args_size=0
	getstatic	Field scala/reflect/generic/PickleFormat$.MODULE$:Lscala/reflect/generic/PickleFormat$;
	invokevirtual	Method scala/reflect/generic/PickleFormat$.VALsym:()I
	ireturn
  Labels:

public static final int MODULEsym();
  Signature: ()I
  Code:
   Stack=1, Locals=0, Args_size=0
	getstatic	Field scala/reflect/generic/PickleFormat$.MODULE$:Lscala/reflect/generic/PickleFormat$;
	invokevirtual	Method scala/reflect/generic/PickleFormat$.MODULEsym:()I
	ireturn
  Labels:

public static final int CLASSsym();
  Signature: ()I
  Code:
   Stack=1, Locals=0, Args_size=0
	getstatic	Field scala/reflect/generic/PickleFormat$.MODULE$:Lscala/reflect/generic/PickleFormat$;
	invokevirtual	Method scala/reflect/generic/PickleFormat$.CLASSsym:()I
	ireturn
  Labels:

public static final int ALIASsym();
  Signature: ()I
  Code:
   Stack=1, Locals=0, Args_size=0
	getstatic	Field scala/reflect/generic/PickleFormat$.MODULE$:Lscala/reflect/generic/PickleFormat$;
	invokevirtual	Method scala/reflect/generic/PickleFormat$.ALIASsym:()I
	ireturn
  Labels:

public static final int TYPEsym();
  Signature: ()I
  Code:
   Stack=1, Locals=0, Args_size=0
	getstatic	Field scala/reflect/generic/PickleFormat$.MODULE$:Lscala/reflect/generic/PickleFormat$;
	invokevirtual	Method scala/reflect/generic/PickleFormat$.TYPEsym:()I
	ireturn
  Labels:

public static final int NONEsym();
  Signature: ()I
  Code:
   Stack=1, Locals=0, Args_size=0
	getstatic	Field scala/reflect/generic/PickleFormat$.MODULE$:Lscala/reflect/generic/PickleFormat$;
	invokevirtual	Method scala/reflect/generic/PickleFormat$.NONEsym:()I
	ireturn
  Labels:

public static final int TYPEname();
  Signature: ()I
  Code:
   Stack=1, Locals=0, Args_size=0
	getstatic	Field scala/reflect/generic/PickleFormat$.MODULE$:Lscala/reflect/generic/PickleFormat$;
	invokevirtual	Method scala/reflect/generic/PickleFormat$.TYPEname:()I
	ireturn
  Labels:

public static final int TERMname();
  Signature: ()I
  Code:
   Stack=1, Locals=0, Args_size=0
	getstatic	Field scala/reflect/generic/PickleFormat$.MODULE$:Lscala/reflect/generic/PickleFormat$;
	invokevirtual	Method scala/reflect/generic/PickleFormat$.TERMname:()I
	ireturn
  Labels:

public static final int MinorVersion();
  Signature: ()I
  Code:
   Stack=1, Locals=0, Args_size=0
	getstatic	Field scala/reflect/generic/PickleFormat$.MODULE$:Lscala/reflect/generic/PickleFormat$;
	invokevirtual	Method scala/reflect/generic/PickleFormat$.MinorVersion:()I
	ireturn
  Labels:

public static final int MajorVersion();
  Signature: ()I
  Code:
   Stack=1, Locals=0, Args_size=0
	getstatic	Field scala/reflect/generic/PickleFormat$.MODULE$:Lscala/reflect/generic/PickleFormat$;
	invokevirtual	Method scala/reflect/generic/PickleFormat$.MajorVersion:()I
	ireturn
  Labels:

}

