Compiled from "PickleBuffer.scala"
public final class scala.reflect.generic.PickleBuffer$$anonfun$toIndexedSeq$1 extends scala.runtime.AbstractFunction1 implements java.io.Serializable
  SourceFile: "PickleBuffer.scala"
  Scala: length = 0x
   
  InnerClass: 
   public final ArrowAssoc=class scala/Predef$ArrowAssoc of class scala/Predef
   public final $anonfun$toIndexedSeq$1=class scala/reflect/generic/PickleBuffer$$anonfun$toIndexedSeq$1 of class scala/reflect/generic/PickleBuffer
  minor version: 0
  major version: 49
  Constant pool:
Asciz	SourceFile;
Asciz	PickleBuffer.scala;
Asciz	<clinit>;
Asciz	()V;
Asciz	Code;
Asciz	serialVersionUID;
Asciz	J;
Asciz	scala/reflect/generic/PickleBuffer$$anonfun$toIndexedSeq$1;
class	scala/reflect/generic/PickleBuffer$$anonfun$toIndexedSeq$1
NameAndType	serialVersionUID:J
Field	scala/reflect/generic/PickleBuffer$$anonfun$toIndexedSeq$1.serialVersionUID:J
Asciz	result$1;
Asciz	[Lscala/Tuple2;;
Asciz	$outer;
Asciz	Lscala/reflect/generic/PickleBuffer;;
Asciz	apply;
Asciz	(I)V;
Asciz	LineNumberTable;
NameAndType	$outer:Lscala/reflect/generic/PickleBuffer;
Field	scala/reflect/generic/PickleBuffer$$anonfun$toIndexedSeq$1.$outer:Lscala/reflect/generic/PickleBuffer;
Asciz	scala/reflect/generic/PickleBuffer;
class	scala/reflect/generic/PickleBuffer
Asciz	readNat;
Asciz	()I;
NameAndType	readNat:()I
Method	scala/reflect/generic/PickleBuffer.readNat:()I
Asciz	scala/Predef$;
class	scala/Predef$
Asciz	MODULE$;
Asciz	Lscala/Predef$;;
NameAndType	MODULE$:Lscala/Predef$;
Field	scala/Predef$.MODULE$:Lscala/Predef$;
Asciz	scala$reflect$generic$PickleBuffer$$data;
Asciz	[B;
NameAndType	scala$reflect$generic$PickleBuffer$$data:[B
Field	scala/reflect/generic/PickleBuffer.scala$reflect$generic$PickleBuffer$$data:[B
Asciz	byteArrayOps;
Asciz	([B)Lscala/collection/mutable/ArrayOps;;
NameAndType	byteArrayOps:([B)Lscala/collection/mutable/ArrayOps;
Method	scala/Predef$.byteArrayOps:([B)Lscala/collection/mutable/ArrayOps;
Asciz	readIndex;
NameAndType	readIndex:()I
Method	scala/reflect/generic/PickleBuffer.readIndex:()I
Asciz	scala/collection/IndexedSeqLike;
class	scala/collection/IndexedSeqLike
Asciz	slice;
Asciz	(II)Ljava/lang/Object;;
NameAndType	slice:(II)Ljava/lang/Object;
InterfaceMethod	scala/collection/IndexedSeqLike.slice:(II)Ljava/lang/Object;
class	"[B"
Asciz	readIndex_$eq;
NameAndType	readIndex_$eq:(I)V
Method	scala/reflect/generic/PickleBuffer.readIndex_$eq:(I)V
NameAndType	result$1:[Lscala/Tuple2;
Field	scala/reflect/generic/PickleBuffer$$anonfun$toIndexedSeq$1.result$1:[Lscala/Tuple2;
Asciz	scala/runtime/BoxesRunTime;
class	scala/runtime/BoxesRunTime
Asciz	boxToInteger;
Asciz	(I)Ljava/lang/Integer;;
NameAndType	boxToInteger:(I)Ljava/lang/Integer;
Method	scala/runtime/BoxesRunTime.boxToInteger:(I)Ljava/lang/Integer;
Asciz	any2ArrowAssoc;
Asciz	(Ljava/lang/Object;)Lscala/Predef$ArrowAssoc;;
NameAndType	any2ArrowAssoc:(Ljava/lang/Object;)Lscala/Predef$ArrowAssoc;
Method	scala/Predef$.any2ArrowAssoc:(Ljava/lang/Object;)Lscala/Predef$ArrowAssoc;
Asciz	scala/Predef$ArrowAssoc;
class	scala/Predef$ArrowAssoc
Asciz	$minus$greater;
Asciz	(Ljava/lang/Object;)Lscala/Tuple2;;
NameAndType	$minus$greater:(Ljava/lang/Object;)Lscala/Tuple2;
Method	scala/Predef$ArrowAssoc.$minus$greater:(Ljava/lang/Object;)Lscala/Tuple2;
Asciz	this;
Asciz	Lscala/reflect/generic/PickleBuffer$$anonfun$toIndexedSeq$1;;
Asciz	index;
Asciz	I;
Asciz	tag;
Asciz	len;
Asciz	bytes;
Asciz	LocalVariableTable;
Asciz	(Ljava/lang/Object;)Ljava/lang/Object;;
Asciz	unboxToInt;
Asciz	(Ljava/lang/Object;)I;
NameAndType	unboxToInt:(Ljava/lang/Object;)I
Method	scala/runtime/BoxesRunTime.unboxToInt:(Ljava/lang/Object;)I
NameAndType	apply:(I)V
Method	scala/reflect/generic/PickleBuffer$$anonfun$toIndexedSeq$1.apply:(I)V
Asciz	scala/runtime/BoxedUnit;
class	scala/runtime/BoxedUnit
Asciz	UNIT;
Asciz	Lscala/runtime/BoxedUnit;;
NameAndType	UNIT:Lscala/runtime/BoxedUnit;
Field	scala/runtime/BoxedUnit.UNIT:Lscala/runtime/BoxedUnit;
Asciz	v1;
Asciz	Ljava/lang/Object;;
Asciz	<init>;
Asciz	(Lscala/reflect/generic/PickleBuffer;[Lscala/Tuple2;)V;
Asciz	java/lang/NullPointerException;
class	java/lang/NullPointerException
NameAndType	"<init>":()V
Method	java/lang/NullPointerException."<init>":()V
Asciz	scala/runtime/AbstractFunction1;
class	scala/runtime/AbstractFunction1
Method	scala/runtime/AbstractFunction1."<init>":()V
Asciz	Scala;
Asciz	InnerClasses;
Asciz	scala/Predef;
class	scala/Predef
Asciz	ArrowAssoc;
Asciz	$anonfun$toIndexedSeq$1;
Asciz	java/io/Serializable;
class	java/io/Serializable

{
public static final long serialVersionUID;
  Signature: J

private final scala.Tuple2[] result$1;
  Signature: [Lscala/Tuple2;

private final scala.reflect.generic.PickleBuffer $outer;
  Signature: Lscala/reflect/generic/PickleBuffer;

public static {};
  Signature: ()V
  Code:
   Stack=2, Locals=0, Args_size=0
	lconst_0
	putstatic	Field serialVersionUID:J
	return
  Labels:

public final void apply(int);
  Signature: (I)V
  Code:
   Stack=4, Locals=5, Args_size=2
	aload_0
	getfield	Field $outer:Lscala/reflect/generic/PickleBuffer;
	invokevirtual	Method scala/reflect/generic/PickleBuffer.readNat:()I
	istore_2
	aload_0
	getfield	Field $outer:Lscala/reflect/generic/PickleBuffer;
	invokevirtual	Method scala/reflect/generic/PickleBuffer.readNat:()I
	istore_3
	getstatic	Field scala/Predef$.MODULE$:Lscala/Predef$;
	aload_0
	getfield	Field $outer:Lscala/reflect/generic/PickleBuffer;
	getfield	Field scala/reflect/generic/PickleBuffer.scala$reflect$generic$PickleBuffer$$data:[B
	invokevirtual	Method scala/Predef$.byteArrayOps:([B)Lscala/collection/mutable/ArrayOps;
	aload_0
	getfield	Field $outer:Lscala/reflect/generic/PickleBuffer;
	invokevirtual	Method scala/reflect/generic/PickleBuffer.readIndex:()I
	iload_3
	aload_0
	getfield	Field $outer:Lscala/reflect/generic/PickleBuffer;
	invokevirtual	Method scala/reflect/generic/PickleBuffer.readIndex:()I
	iadd
	invokeinterface	InterfaceMethod scala/collection/IndexedSeqLike.slice:(II)Ljava/lang/Object;
	checkcast	class "[B"
	astore	4
	aload_0
	getfield	Field $outer:Lscala/reflect/generic/PickleBuffer;
	aload_0
	getfield	Field $outer:Lscala/reflect/generic/PickleBuffer;
	invokevirtual	Method scala/reflect/generic/PickleBuffer.readIndex:()I
	iload_3
	iadd
	invokevirtual	Method scala/reflect/generic/PickleBuffer.readIndex_$eq:(I)V
	aload_0
	getfield	Field result$1:[Lscala/Tuple2;
	iload_1
	getstatic	Field scala/Predef$.MODULE$:Lscala/Predef$;
	iload_2
	invokestatic	Method scala/runtime/BoxesRunTime.boxToInteger:(I)Ljava/lang/Integer;
	invokevirtual	Method scala/Predef$.any2ArrowAssoc:(Ljava/lang/Object;)Lscala/Predef$ArrowAssoc;
	aload	4
	invokevirtual	Method scala/Predef$ArrowAssoc.$minus$greater:(Ljava/lang/Object;)Lscala/Tuple2;
	aastore
	return
  Labels:
  LocalVariableTable: 
   Start  Length  Slot  Name   Signature
   0      93      0    this       Lscala/reflect/generic/PickleBuffer$$anonfun$toIndexedSeq$1;
   0      93      1    index       I
   8      84      2    tag       I
   16      76      3    len       I
   55      37      4    bytes       [B


public final java.lang.Object apply(java.lang.Object);
  Signature: (Ljava/lang/Object;)Ljava/lang/Object;
  Code:
   Stack=2, Locals=2, Args_size=2
	aload_0
	aload_1
	invokestatic	Method scala/runtime/BoxesRunTime.unboxToInt:(Ljava/lang/Object;)I
	invokevirtual	Method apply:(I)V
	getstatic	Field scala/runtime/BoxedUnit.UNIT:Lscala/runtime/BoxedUnit;
	areturn
  Labels:
  LocalVariableTable: 
   Start  Length  Slot  Name   Signature
   0      12      0    this       Lscala/reflect/generic/PickleBuffer$$anonfun$toIndexedSeq$1;
   0      12      1    v1       Ljava/lang/Object;


public scala.reflect.generic.PickleBuffer$$anonfun$toIndexedSeq$1(scala.reflect.generic.PickleBuffer, scala.Tuple2[]);
  Signature: (Lscala/reflect/generic/PickleBuffer;[Lscala/Tuple2;)V
  Code:
   Stack=2, Locals=3, Args_size=3
	aload_1
	ifnonnull	l1 // aload_0
	new	class java/lang/NullPointerException
	dup
	invokespecial	Method java/lang/NullPointerException."<init>":()V
	athrow
l1	aload_0
	aload_1
	putfield	Field $outer:Lscala/reflect/generic/PickleBuffer;
	aload_0
	aload_2
	putfield	Field result$1:[Lscala/Tuple2;
	aload_0
	invokespecial	Method scala/runtime/AbstractFunction1."<init>":()V
	return
  Labels:
   	l1 = 12 // aload_0
  LocalVariableTable: 
   Start  Length  Slot  Name   Signature
   0      27      0    this       Lscala/reflect/generic/PickleBuffer$$anonfun$toIndexedSeq$1;
   0      27      1    $outer       Lscala/reflect/generic/PickleBuffer;


}

