Compiled from "StdNames.scala"
public class scala.reflect.generic.StdNames$StandardNames extends java.lang.Object implements scala.ScalaObject
  SourceFile: "StdNames.scala"
  Scala: length = 0x
   
  InnerClass: 
   public abstract AbsSymbol=class scala/reflect/generic/Symbols$AbsSymbol of class scala/reflect/generic/Symbols
   public StandardNames=class scala/reflect/generic/StdNames$StandardNames of class scala/reflect/generic/StdNames
  minor version: 0
  major version: 49
  Constant pool:
Asciz	SourceFile;
Asciz	StdNames.scala;
Asciz	EXPAND_SEPARATOR_STRING;
Asciz	Ljava/lang/String;;
Asciz	LOCAL_SUFFIX_STRING;
Asciz	ANON_CLASS_NAME;
Asciz	Ljava/lang/Object;;
Asciz	ANON_FUN_NAME;
Asciz	EMPTY_PACKAGE_NAME;
Asciz	IMPORT;
Asciz	REFINE_CLASS_NAME;
Asciz	ROOT;
Asciz	ROOTPKG;
Asciz	EMPTY;
Asciz	$outer;
Asciz	Lscala/reflect/generic/Universe;;
Asciz	expandedName$default$3;
Asciz	()Ljava/lang/String;;
Asciz	Code;
Asciz	LineNumberTable;
Asciz	scala/reflect/generic/StdNames$StandardNames;
class	scala/reflect/generic/StdNames$StandardNames
NameAndType	EXPAND_SEPARATOR_STRING:()Ljava/lang/String;
Method	scala/reflect/generic/StdNames$StandardNames.EXPAND_SEPARATOR_STRING:()Ljava/lang/String;
NameAndType	EXPAND_SEPARATOR_STRING:Ljava/lang/String;
Field	scala/reflect/generic/StdNames$StandardNames.EXPAND_SEPARATOR_STRING:Ljava/lang/String;
NameAndType	LOCAL_SUFFIX_STRING:Ljava/lang/String;
Field	scala/reflect/generic/StdNames$StandardNames.LOCAL_SUFFIX_STRING:Ljava/lang/String;
Asciz	()Ljava/lang/Object;;
NameAndType	ANON_CLASS_NAME:Ljava/lang/Object;
Field	scala/reflect/generic/StdNames$StandardNames.ANON_CLASS_NAME:Ljava/lang/Object;
NameAndType	ANON_FUN_NAME:Ljava/lang/Object;
Field	scala/reflect/generic/StdNames$StandardNames.ANON_FUN_NAME:Ljava/lang/Object;
NameAndType	EMPTY_PACKAGE_NAME:Ljava/lang/Object;
Field	scala/reflect/generic/StdNames$StandardNames.EMPTY_PACKAGE_NAME:Ljava/lang/Object;
NameAndType	IMPORT:Ljava/lang/Object;
Field	scala/reflect/generic/StdNames$StandardNames.IMPORT:Ljava/lang/Object;
NameAndType	REFINE_CLASS_NAME:Ljava/lang/Object;
Field	scala/reflect/generic/StdNames$StandardNames.REFINE_CLASS_NAME:Ljava/lang/Object;
NameAndType	ROOT:Ljava/lang/Object;
Field	scala/reflect/generic/StdNames$StandardNames.ROOT:Ljava/lang/Object;
NameAndType	ROOTPKG:Ljava/lang/Object;
Field	scala/reflect/generic/StdNames$StandardNames.ROOTPKG:Ljava/lang/Object;
NameAndType	EMPTY:Ljava/lang/Object;
Field	scala/reflect/generic/StdNames$StandardNames.EMPTY:Ljava/lang/Object;
Asciz	expandedName;
Asciz	(Ljava/lang/Object;Lscala/reflect/generic/Symbols$AbsSymbol;Ljava/lang/String;)Ljava/lang/Object;;
Asciz	scala$reflect$generic$StdNames$StandardNames$$$outer;
Asciz	()Lscala/reflect/generic/Universe;;
NameAndType	scala$reflect$generic$StdNames$StandardNames$$$outer:()Lscala/reflect/generic/Universe;
Method	scala/reflect/generic/StdNames$StandardNames.scala$reflect$generic$StdNames$StandardNames$$$outer:()Lscala/reflect/generic/Universe;
Asciz	scala/collection/mutable/StringBuilder;
class	scala/collection/mutable/StringBuilder
Asciz	<init>;
Asciz	()V;
NameAndType	"<init>":()V
Method	scala/collection/mutable/StringBuilder."<init>":()V
int	36;
Asciz	scala/reflect/generic/Symbols$AbsSymbol;
class	scala/reflect/generic/Symbols$AbsSymbol
Asciz	fullName;
Asciz	(C)Ljava/lang/String;;
NameAndType	fullName:(C)Ljava/lang/String;
Method	scala/reflect/generic/Symbols$AbsSymbol.fullName:(C)Ljava/lang/String;
Asciz	append;
Asciz	(Ljava/lang/Object;)Lscala/collection/mutable/StringBuilder;;
NameAndType	append:(Ljava/lang/Object;)Lscala/collection/mutable/StringBuilder;
Method	scala/collection/mutable/StringBuilder.append:(Ljava/lang/Object;)Lscala/collection/mutable/StringBuilder;
Asciz	toString;
NameAndType	toString:()Ljava/lang/String;
Method	scala/collection/mutable/StringBuilder.toString:()Ljava/lang/String;
Asciz	scala/reflect/generic/Names;
class	scala/reflect/generic/Names
Asciz	newTermName;
Asciz	(Ljava/lang/String;)Ljava/lang/Object;;
NameAndType	newTermName:(Ljava/lang/String;)Ljava/lang/Object;
InterfaceMethod	scala/reflect/generic/Names.newTermName:(Ljava/lang/String;)Ljava/lang/Object;
Asciz	this;
Asciz	Lscala/reflect/generic/StdNames$StandardNames;;
Asciz	name;
Asciz	base;
Asciz	Lscala/reflect/generic/Symbols$AbsSymbol;;
Asciz	separator;
Asciz	LocalVariableTable;
NameAndType	$outer:Lscala/reflect/generic/Universe;
Field	scala/reflect/generic/StdNames$StandardNames.$outer:Lscala/reflect/generic/Universe;
Asciz	(Lscala/reflect/generic/Universe;)V;
Asciz	java/lang/NullPointerException;
class	java/lang/NullPointerException
Method	java/lang/NullPointerException."<init>":()V
Asciz	java/lang/Object;
class	java/lang/Object
Method	java/lang/Object."<init>":()V
Asciz	$$;
String	$$
Asciz	 ;
String	 
Asciz	$anon;
String	$anon
Asciz	$anonfun;
String	$anonfun
Asciz	<empty>;
String	<empty>
Asciz	<import>;
String	<import>
Asciz	<refinement>;
String	<refinement>
Asciz	<root>;
String	<root>
Asciz	_root_;
String	_root_
Asciz	;
String	
Asciz	Scala;
Asciz	InnerClasses;
Asciz	scala/reflect/generic/Symbols;
class	scala/reflect/generic/Symbols
Asciz	AbsSymbol;
Asciz	scala/reflect/generic/StdNames;
class	scala/reflect/generic/StdNames
Asciz	StandardNames;
Asciz	scala/ScalaObject;
class	scala/ScalaObject

{
private final java.lang.String EXPAND_SEPARATOR_STRING;
  Signature: Ljava/lang/String;

private final java.lang.String LOCAL_SUFFIX_STRING;
  Signature: Ljava/lang/String;

private final java.lang.Object ANON_CLASS_NAME;
  Signature: Ljava/lang/Object;

private final java.lang.Object ANON_FUN_NAME;
  Signature: Ljava/lang/Object;

private final java.lang.Object EMPTY_PACKAGE_NAME;
  Signature: Ljava/lang/Object;

private final java.lang.Object IMPORT;
  Signature: Ljava/lang/Object;

private final java.lang.Object REFINE_CLASS_NAME;
  Signature: Ljava/lang/Object;

private final java.lang.Object ROOT;
  Signature: Ljava/lang/Object;

private final java.lang.Object ROOTPKG;
  Signature: Ljava/lang/Object;

private final java.lang.Object EMPTY;
  Signature: Ljava/lang/Object;

public final scala.reflect.generic.Universe $outer;
  Signature: Lscala/reflect/generic/Universe;

public java.lang.String expandedName$default$3();
  Signature: ()Ljava/lang/String;
  Code:
   Stack=1, Locals=1, Args_size=1
	aload_0
	invokevirtual	Method EXPAND_SEPARATOR_STRING:()Ljava/lang/String;
	areturn
  Labels:

public java.lang.String EXPAND_SEPARATOR_STRING();
  Signature: ()Ljava/lang/String;
  Code:
   Stack=1, Locals=1, Args_size=1
	aload_0
	getfield	Field EXPAND_SEPARATOR_STRING:Ljava/lang/String;
	areturn
  Labels:

public java.lang.String LOCAL_SUFFIX_STRING();
  Signature: ()Ljava/lang/String;
  Code:
   Stack=1, Locals=1, Args_size=1
	aload_0
	getfield	Field LOCAL_SUFFIX_STRING:Ljava/lang/String;
	areturn
  Labels:

public java.lang.Object ANON_CLASS_NAME();
  Signature: ()Ljava/lang/Object;
  Code:
   Stack=1, Locals=1, Args_size=1
	aload_0
	getfield	Field ANON_CLASS_NAME:Ljava/lang/Object;
	areturn
  Labels:

public java.lang.Object ANON_FUN_NAME();
  Signature: ()Ljava/lang/Object;
  Code:
   Stack=1, Locals=1, Args_size=1
	aload_0
	getfield	Field ANON_FUN_NAME:Ljava/lang/Object;
	areturn
  Labels:

public java.lang.Object EMPTY_PACKAGE_NAME();
  Signature: ()Ljava/lang/Object;
  Code:
   Stack=1, Locals=1, Args_size=1
	aload_0
	getfield	Field EMPTY_PACKAGE_NAME:Ljava/lang/Object;
	areturn
  Labels:

public java.lang.Object IMPORT();
  Signature: ()Ljava/lang/Object;
  Code:
   Stack=1, Locals=1, Args_size=1
	aload_0
	getfield	Field IMPORT:Ljava/lang/Object;
	areturn
  Labels:

public java.lang.Object REFINE_CLASS_NAME();
  Signature: ()Ljava/lang/Object;
  Code:
   Stack=1, Locals=1, Args_size=1
	aload_0
	getfield	Field REFINE_CLASS_NAME:Ljava/lang/Object;
	areturn
  Labels:

public java.lang.Object ROOT();
  Signature: ()Ljava/lang/Object;
  Code:
   Stack=1, Locals=1, Args_size=1
	aload_0
	getfield	Field ROOT:Ljava/lang/Object;
	areturn
  Labels:

public java.lang.Object ROOTPKG();
  Signature: ()Ljava/lang/Object;
  Code:
   Stack=1, Locals=1, Args_size=1
	aload_0
	getfield	Field ROOTPKG:Ljava/lang/Object;
	areturn
  Labels:

public java.lang.Object EMPTY();
  Signature: ()Ljava/lang/Object;
  Code:
   Stack=1, Locals=1, Args_size=1
	aload_0
	getfield	Field EMPTY:Ljava/lang/Object;
	areturn
  Labels:

public java.lang.Object expandedName(java.lang.Object, scala.reflect.generic.Symbols$AbsSymbol, java.lang.String);
  Signature: (Ljava/lang/Object;Lscala/reflect/generic/Symbols$AbsSymbol;Ljava/lang/String;)Ljava/lang/Object;
  Code:
   Stack=4, Locals=4, Args_size=4
	aload_0
	invokevirtual	Method scala$reflect$generic$StdNames$StandardNames$$$outer:()Lscala/reflect/generic/Universe;
	new	class scala/collection/mutable/StringBuilder
	dup
	invokespecial	Method scala/collection/mutable/StringBuilder."<init>":()V
	aload_2
	ldc	int 36
	invokevirtual	Method scala/reflect/generic/Symbols$AbsSymbol.fullName:(C)Ljava/lang/String;
	invokevirtual	Method scala/collection/mutable/StringBuilder.append:(Ljava/lang/Object;)Lscala/collection/mutable/StringBuilder;
	aload_3
	invokevirtual	Method scala/collection/mutable/StringBuilder.append:(Ljava/lang/Object;)Lscala/collection/mutable/StringBuilder;
	aload_1
	invokevirtual	Method scala/collection/mutable/StringBuilder.append:(Ljava/lang/Object;)Lscala/collection/mutable/StringBuilder;
	invokevirtual	Method scala/collection/mutable/StringBuilder.toString:()Ljava/lang/String;
	invokeinterface	InterfaceMethod scala/reflect/generic/Names.newTermName:(Ljava/lang/String;)Ljava/lang/Object;
	areturn
  Labels:
  LocalVariableTable: 
   Start  Length  Slot  Name   Signature
   0      37      0    this       Lscala/reflect/generic/StdNames$StandardNames;
   0      37      1    name       Ljava/lang/Object;
   0      37      2    base       Lscala/reflect/generic/Symbols$AbsSymbol;
   0      37      3    separator       Ljava/lang/String;


public scala.reflect.generic.Universe scala$reflect$generic$StdNames$StandardNames$$$outer();
  Signature: ()Lscala/reflect/generic/Universe;
  Code:
   Stack=1, Locals=1, Args_size=1
	aload_0
	getfield	Field $outer:Lscala/reflect/generic/Universe;
	areturn
  Labels:

public scala.reflect.generic.StdNames$StandardNames(scala.reflect.generic.Universe);
  Signature: (Lscala/reflect/generic/Universe;)V
  Code:
   Stack=3, Locals=2, Args_size=2
	aload_1
	ifnonnull	l1 // aload_0
	new	class java/lang/NullPointerException
	dup
	invokespecial	Method java/lang/NullPointerException."<init>":()V
	athrow
l1	aload_0
	aload_1
	putfield	Field $outer:Lscala/reflect/generic/Universe;
	aload_0
	invokespecial	Method java/lang/Object."<init>":()V
	aload_0
	ldc	String $$
	putfield	Field EXPAND_SEPARATOR_STRING:Ljava/lang/String;
	aload_0
	ldc	String  
	putfield	Field LOCAL_SUFFIX_STRING:Ljava/lang/String;
	aload_0
	aload_1
	ldc	String $anon
	invokeinterface	InterfaceMethod scala/reflect/generic/Names.newTermName:(Ljava/lang/String;)Ljava/lang/Object;
	putfield	Field ANON_CLASS_NAME:Ljava/lang/Object;
	aload_0
	aload_1
	ldc	String $anonfun
	invokeinterface	InterfaceMethod scala/reflect/generic/Names.newTermName:(Ljava/lang/String;)Ljava/lang/Object;
	putfield	Field ANON_FUN_NAME:Ljava/lang/Object;
	aload_0
	aload_1
	ldc	String <empty>
	invokeinterface	InterfaceMethod scala/reflect/generic/Names.newTermName:(Ljava/lang/String;)Ljava/lang/Object;
	putfield	Field EMPTY_PACKAGE_NAME:Ljava/lang/Object;
	aload_0
	aload_1
	ldc	String <import>
	invokeinterface	InterfaceMethod scala/reflect/generic/Names.newTermName:(Ljava/lang/String;)Ljava/lang/Object;
	putfield	Field IMPORT:Ljava/lang/Object;
	aload_0
	aload_1
	ldc	String <refinement>
	invokeinterface	InterfaceMethod scala/reflect/generic/Names.newTermName:(Ljava/lang/String;)Ljava/lang/Object;
	putfield	Field REFINE_CLASS_NAME:Ljava/lang/Object;
	aload_0
	aload_1
	ldc	String <root>
	invokeinterface	InterfaceMethod scala/reflect/generic/Names.newTermName:(Ljava/lang/String;)Ljava/lang/Object;
	putfield	Field ROOT:Ljava/lang/Object;
	aload_0
	aload_1
	ldc	String _root_
	invokeinterface	InterfaceMethod scala/reflect/generic/Names.newTermName:(Ljava/lang/String;)Ljava/lang/Object;
	putfield	Field ROOTPKG:Ljava/lang/Object;
	aload_0
	aload_1
	ldc	String 
	invokeinterface	InterfaceMethod scala/reflect/generic/Names.newTermName:(Ljava/lang/String;)Ljava/lang/Object;
	putfield	Field EMPTY:Ljava/lang/Object;
	return
  Labels:
   	l1 = 12 // aload_0
  LocalVariableTable: 
   Start  Length  Slot  Name   Signature
   0      130      0    this       Lscala/reflect/generic/StdNames$StandardNames;
   0      130      1    $outer       Lscala/reflect/generic/Universe;


}

