Compiled from "Symbols.scala"
public abstract class scala.reflect.generic.Symbols$AbsSymbol extends java.lang.Object implements scala.ScalaObject
  SourceFile: "Symbols.scala"
  Scala: length = 0x
   
  InnerClass: 
   public abstract AbsType=class scala/reflect/generic/Types$AbsType of class scala/reflect/generic/Types
   public abstract AbsSymbol=class scala/reflect/generic/Symbols$AbsSymbol of class scala/reflect/generic/Symbols
   public StandardNames=class scala/reflect/generic/StdNames$StandardNames of class scala/reflect/generic/StdNames
   public abstract AbsDefinitions=class scala/reflect/generic/StandardDefinitions$AbsDefinitions of class scala/reflect/generic/StandardDefinitions
  minor version: 0
  major version: 49
  Constant pool:
Asciz	SourceFile;
Asciz	Symbols.scala;
Asciz	$outer;
Asciz	Lscala/reflect/generic/Universe;;
Asciz	newValue$default$2;
Asciz	()Ljava/lang/Object;;
Asciz	Code;
Asciz	LineNumberTable;
Asciz	scala/reflect/generic/Symbols$AbsSymbol;
class	scala/reflect/generic/Symbols$AbsSymbol
Asciz	scala$reflect$generic$Symbols$AbsSymbol$$$outer;
Asciz	()Lscala/reflect/generic/Universe;;
NameAndType	scala$reflect$generic$Symbols$AbsSymbol$$$outer:()Lscala/reflect/generic/Universe;
Method	scala/reflect/generic/Symbols$AbsSymbol.scala$reflect$generic$Symbols$AbsSymbol$$$outer:()Lscala/reflect/generic/Universe;
Asciz	scala/reflect/generic/Universe;
class	scala/reflect/generic/Universe
Asciz	NoPosition;
NameAndType	NoPosition:()Ljava/lang/Object;
Method	scala/reflect/generic/Universe.NoPosition:()Ljava/lang/Object;
Asciz	newModuleClass$default$2;
Asciz	newModule$default$3;
Asciz	newMethod$default$2;
Asciz	newClass$default$2;
Asciz	newAliasType$default$2;
Asciz	newAbstractType$default$2;
Asciz	owner;
Asciz	()Lscala/reflect/generic/Symbols$AbsSymbol;;
Asciz	flags;
Asciz	()J;
Asciz	name;
Asciz	encodedName;
Asciz	()Ljava/lang/String;;
Asciz	decodedName;
Asciz	scala/reflect/NameTransformer$;
class	scala/reflect/NameTransformer$
Asciz	MODULE$;
Asciz	Lscala/reflect/NameTransformer$;;
NameAndType	MODULE$:Lscala/reflect/NameTransformer$;
Field	scala/reflect/NameTransformer$.MODULE$:Lscala/reflect/NameTransformer$;
NameAndType	encodedName:()Ljava/lang/String;
Method	scala/reflect/generic/Symbols$AbsSymbol.encodedName:()Ljava/lang/String;
Asciz	decode;
Asciz	(Ljava/lang/String;)Ljava/lang/String;;
NameAndType	decode:(Ljava/lang/String;)Ljava/lang/String;
Method	scala/reflect/NameTransformer$.decode:(Ljava/lang/String;)Ljava/lang/String;
Asciz	stripLocalSuffix;
NameAndType	stripLocalSuffix:(Ljava/lang/String;)Ljava/lang/String;
Method	scala/reflect/generic/Symbols$AbsSymbol.stripLocalSuffix:(Ljava/lang/String;)Ljava/lang/String;
Asciz	fullName;
Asciz	(C)Ljava/lang/String;;
Asciz	isRoot;
Asciz	()Z;
NameAndType	isRoot:()Z
Method	scala/reflect/generic/Symbols$AbsSymbol.isRoot:()Z
Asciz	isRootPackage;
NameAndType	isRootPackage:()Z
Method	scala/reflect/generic/Symbols$AbsSymbol.isRootPackage:()Z
Asciz	scala/reflect/generic/Symbols;
class	scala/reflect/generic/Symbols
Asciz	NoSymbol;
NameAndType	NoSymbol:()Lscala/reflect/generic/Symbols$AbsSymbol;
InterfaceMethod	scala/reflect/generic/Symbols.NoSymbol:()Lscala/reflect/generic/Symbols$AbsSymbol;
Asciz	java/lang/Object;
class	java/lang/Object
Asciz	equals;
Asciz	(Ljava/lang/Object;)Z;
NameAndType	equals:(Ljava/lang/Object;)Z
Method	java/lang/Object.equals:(Ljava/lang/Object;)Z
Asciz	toString;
NameAndType	toString:()Ljava/lang/String;
Method	scala/reflect/generic/Symbols$AbsSymbol.toString:()Ljava/lang/String;
NameAndType	owner:()Lscala/reflect/generic/Symbols$AbsSymbol;
Method	scala/reflect/generic/Symbols$AbsSymbol.owner:()Lscala/reflect/generic/Symbols$AbsSymbol;
Asciz	isEffectiveRoot;
NameAndType	isEffectiveRoot:()Z
Method	scala/reflect/generic/Symbols$AbsSymbol.isEffectiveRoot:()Z
Asciz	scala/collection/mutable/StringBuilder;
class	scala/collection/mutable/StringBuilder
Asciz	<init>;
Asciz	()V;
NameAndType	"<init>":()V
Method	scala/collection/mutable/StringBuilder."<init>":()V
Asciz	enclClass;
NameAndType	enclClass:()Lscala/reflect/generic/Symbols$AbsSymbol;
Method	scala/reflect/generic/Symbols$AbsSymbol.enclClass:()Lscala/reflect/generic/Symbols$AbsSymbol;
NameAndType	fullName:(C)Ljava/lang/String;
Method	scala/reflect/generic/Symbols$AbsSymbol.fullName:(C)Ljava/lang/String;
Asciz	append;
Asciz	(Ljava/lang/Object;)Lscala/collection/mutable/StringBuilder;;
NameAndType	append:(Ljava/lang/Object;)Lscala/collection/mutable/StringBuilder;
Method	scala/collection/mutable/StringBuilder.append:(Ljava/lang/Object;)Lscala/collection/mutable/StringBuilder;
Asciz	scala/runtime/BoxesRunTime;
class	scala/runtime/BoxesRunTime
Asciz	boxToCharacter;
Asciz	(C)Ljava/lang/Character;;
NameAndType	boxToCharacter:(C)Ljava/lang/Character;
Method	scala/runtime/BoxesRunTime.boxToCharacter:(C)Ljava/lang/Character;
Method	scala/collection/mutable/StringBuilder.toString:()Ljava/lang/String;
Asciz	this;
Asciz	Lscala/reflect/generic/Symbols$AbsSymbol;;
Asciz	separator;
Asciz	C;
Asciz	LocalVariableTable;
Asciz	scala/Predef$;
class	scala/Predef$
Asciz	Lscala/Predef$;;
NameAndType	MODULE$:Lscala/Predef$;
Field	scala/Predef$.MODULE$:Lscala/Predef$;
Asciz	augmentString;
Asciz	(Ljava/lang/String;)Lscala/collection/immutable/StringOps;;
NameAndType	augmentString:(Ljava/lang/String;)Lscala/collection/immutable/StringOps;
Method	scala/Predef$.augmentString:(Ljava/lang/String;)Lscala/collection/immutable/StringOps;
Asciz	scala/reflect/generic/StdNames;
class	scala/reflect/generic/StdNames
Asciz	nme;
Asciz	()Lscala/reflect/generic/StdNames$StandardNames;;
NameAndType	nme:()Lscala/reflect/generic/StdNames$StandardNames;
InterfaceMethod	scala/reflect/generic/StdNames.nme:()Lscala/reflect/generic/StdNames$StandardNames;
Asciz	scala/reflect/generic/StdNames$StandardNames;
class	scala/reflect/generic/StdNames$StandardNames
Asciz	LOCAL_SUFFIX_STRING;
NameAndType	LOCAL_SUFFIX_STRING:()Ljava/lang/String;
Method	scala/reflect/generic/StdNames$StandardNames.LOCAL_SUFFIX_STRING:()Ljava/lang/String;
Asciz	scala/collection/immutable/StringLike;
class	scala/collection/immutable/StringLike
Asciz	stripSuffix;
NameAndType	stripSuffix:(Ljava/lang/String;)Ljava/lang/String;
InterfaceMethod	scala/collection/immutable/StringLike.stripSuffix:(Ljava/lang/String;)Ljava/lang/String;
Asciz	s;
Asciz	Ljava/lang/String;;
int	46;
Asciz	hasFlag;
Asciz	(J)Z;
NameAndType	flags:()J
Method	scala/reflect/generic/Symbols$AbsSymbol.flags:()J
Asciz	mask;
Asciz	J;
Asciz	hasAllFlags;
Asciz	privateWithin;
Asciz	rawInfo;
Asciz	()Lscala/reflect/generic/Types$AbsType;;
Asciz	tpe;
Asciz	info;
NameAndType	info:()Lscala/reflect/generic/Types$AbsType;
Method	scala/reflect/generic/Symbols$AbsSymbol.info:()Lscala/reflect/generic/Types$AbsType;
NameAndType	rawInfo:()Lscala/reflect/generic/Types$AbsType;
Method	scala/reflect/generic/Symbols$AbsSymbol.rawInfo:()Lscala/reflect/generic/Types$AbsType;
Asciz	scala/reflect/generic/Types$AbsType;
class	scala/reflect/generic/Types$AbsType
Asciz	complete;
Asciz	(Lscala/reflect/generic/Symbols$AbsSymbol;)V;
NameAndType	complete:(Lscala/reflect/generic/Symbols$AbsSymbol;)V
Method	scala/reflect/generic/Types$AbsType.complete:(Lscala/reflect/generic/Symbols$AbsSymbol;)V
Asciz	tp;
Asciz	Lscala/reflect/generic/Types$AbsType;;
Asciz	typeOfThis;
Asciz	owner_$eq;
Asciz	java/lang/UnsupportedOperationException;
class	java/lang/UnsupportedOperationException
Asciz	owner_= inapplicable for ;
String	owner_= inapplicable for 
Asciz	(Ljava/lang/String;)V;
NameAndType	"<init>":(Ljava/lang/String;)V
Method	java/lang/UnsupportedOperationException."<init>":(Ljava/lang/String;)V
Asciz	sym;
Asciz	flags_$eq;
Asciz	(J)V;
Asciz	flags_= inapplicable for ;
String	flags_= inapplicable for 
Asciz	info_$eq;
Asciz	(Lscala/reflect/generic/Types$AbsType;)V;
Asciz	info_= inapplicable for ;
String	info_= inapplicable for 
Asciz	typeOfThis_$eq;
Asciz	typeOfThis_= inapplicable for ;
String	typeOfThis_= inapplicable for 
Asciz	privateWithin_$eq;
Asciz	privateWithin_= inapplicable for ;
String	privateWithin_= inapplicable for 
Asciz	sourceModule_$eq;
Asciz	sourceModule_= inapplicable for ;
String	sourceModule_= inapplicable for 
Asciz	addChild;
Asciz	addChild inapplicable for ;
String	addChild inapplicable for 
Asciz	addAnnotation;
Asciz	(Ljava/lang/Object;)V;
Asciz	addAnnotation inapplicable for ;
String	addAnnotation inapplicable for 
Asciz	annot;
Asciz	Ljava/lang/Object;;
Asciz	linkedClassOfClass;
Asciz	sourceModule;
Asciz	moduleClass;
Asciz	isTerm;
Asciz	isType;
Asciz	isClass;
Asciz	isAliasType;
Asciz	isAbstractType;
Asciz	isSkolem;
Asciz	isTrait;
NameAndType	isClass:()Z
Method	scala/reflect/generic/Symbols$AbsSymbol.isClass:()Z
long	33554432l;
NameAndType	hasFlag:(J)Z
Method	scala/reflect/generic/Symbols$AbsSymbol.hasFlag:(J)Z
Asciz	hasDefault;
long	8192l;
Asciz	isAbstractClass;
long	8l;
Asciz	isAbstractOverride;
NameAndType	isTerm:()Z
Method	scala/reflect/generic/Symbols$AbsSymbol.isTerm:()Z
long	2l;
Asciz	isBridge;
long	67108864l;
Asciz	isCase;
long	2048l;
Asciz	isCaseAccessor;
long	16777216l;
Asciz	isContravariant;
NameAndType	isType:()Z
Method	scala/reflect/generic/Symbols$AbsSymbol.isType:()Z
long	131072l;
Asciz	isCovariant;
long	65536l;
Asciz	isDeferred;
long	16l;
Asciz	isEarlyInitialized;
long	137438953472l;
Asciz	isExistentiallyBound;
long	34359738368l;
Asciz	isFinal;
long	32l;
Asciz	isGetterOrSetter;
long	134217728l;
Asciz	isImplClass;
Asciz	isImplicit;
long	512l;
Asciz	isInterface;
long	128l;
Asciz	isJavaDefined;
long	1048576l;
Asciz	isLazy;
long	2147483648l;
Asciz	isMethod;
long	64l;
Asciz	isModule;
long	256l;
Asciz	isModuleClass;
Asciz	isMutable;
long	4096l;
Asciz	isOverloaded;
long	8589934592l;
Asciz	isOverride;
Asciz	isParamAccessor;
long	536870912l;
Asciz	isParameter;
Asciz	isRefinementClass;
NameAndType	name:()Ljava/lang/Object;
Method	scala/reflect/generic/Symbols$AbsSymbol.name:()Ljava/lang/Object;
Asciz	REFINE_CLASS_NAME;
NameAndType	REFINE_CLASS_NAME:()Ljava/lang/Object;
Method	scala/reflect/generic/StdNames$StandardNames.REFINE_CLASS_NAME:()Ljava/lang/Object;
Asciz	scala/reflect/generic/Names;
class	scala/reflect/generic/Names
Asciz	mkTypeName;
Asciz	(Ljava/lang/Object;)Ljava/lang/Object;;
NameAndType	mkTypeName:(Ljava/lang/Object;)Ljava/lang/Object;
InterfaceMethod	scala/reflect/generic/Names.mkTypeName:(Ljava/lang/Object;)Ljava/lang/Object;
Asciz	java/lang/Number;
class	java/lang/Number
Asciz	equalsNumObject;
Asciz	(Ljava/lang/Number;Ljava/lang/Object;)Z;
NameAndType	equalsNumObject:(Ljava/lang/Number;Ljava/lang/Object;)Z
Method	scala/runtime/BoxesRunTime.equalsNumObject:(Ljava/lang/Number;Ljava/lang/Object;)Z
Asciz	java/lang/Character;
class	java/lang/Character
Asciz	equalsCharObject;
Asciz	(Ljava/lang/Character;Ljava/lang/Object;)Z;
NameAndType	equalsCharObject:(Ljava/lang/Character;Ljava/lang/Object;)Z
Method	scala/runtime/BoxesRunTime.equalsCharObject:(Ljava/lang/Character;Ljava/lang/Object;)Z
Asciz	x0;
Asciz	y0;
Asciz	isSealed;
long	1024l;
Asciz	scala/reflect/generic/StandardDefinitions;
class	scala/reflect/generic/StandardDefinitions
Asciz	definitions;
Asciz	()Lscala/reflect/generic/StandardDefinitions$AbsDefinitions;;
NameAndType	definitions:()Lscala/reflect/generic/StandardDefinitions$AbsDefinitions;
InterfaceMethod	scala/reflect/generic/StandardDefinitions.definitions:()Lscala/reflect/generic/StandardDefinitions$AbsDefinitions;
Asciz	scala/reflect/generic/StandardDefinitions$AbsDefinitions;
class	scala/reflect/generic/StandardDefinitions$AbsDefinitions
Asciz	isValueClass;
Asciz	(Lscala/reflect/generic/Symbols$AbsSymbol;)Z;
NameAndType	isValueClass:(Lscala/reflect/generic/Symbols$AbsSymbol;)Z
Method	scala/reflect/generic/StandardDefinitions$AbsDefinitions.isValueClass:(Lscala/reflect/generic/Symbols$AbsSymbol;)Z
Asciz	isSourceMethod;
long	4194368l;
Asciz	isSuperAccessor;
long	268435456l;
Asciz	isSynthetic;
long	2097152l;
Asciz	isTypeParameter;
NameAndType	isSkolem:()Z
Method	scala/reflect/generic/Symbols$AbsSymbol.isSkolem:()Z
Asciz	isPrivate;
long	4l;
Asciz	isPrivateLocal;
long	524288l;
Asciz	isProtected;
Asciz	isProtectedLocal;
Asciz	isPublic;
long	5l;
NameAndType	privateWithin:()Lscala/reflect/generic/Symbols$AbsSymbol;
Method	scala/reflect/generic/Symbols$AbsSymbol.privateWithin:()Lscala/reflect/generic/Symbols$AbsSymbol;
Asciz	isEmptyPackage;
Asciz	isPackage;
NameAndType	isPackage:()Z
Method	scala/reflect/generic/Symbols$AbsSymbol.isPackage:()Z
Asciz	EMPTY_PACKAGE_NAME;
NameAndType	EMPTY_PACKAGE_NAME:()Ljava/lang/Object;
Method	scala/reflect/generic/StdNames$StandardNames.EMPTY_PACKAGE_NAME:()Ljava/lang/Object;
Asciz	isEmptyPackageClass;
Asciz	isPackageClass;
NameAndType	isPackageClass:()Z
Method	scala/reflect/generic/Symbols$AbsSymbol.isPackageClass:()Z
NameAndType	isModule:()Z
Method	scala/reflect/generic/Symbols$AbsSymbol.isModule:()Z
long	16384l;
NameAndType	isEmptyPackageClass:()Z
Method	scala/reflect/generic/Symbols$AbsSymbol.isEmptyPackageClass:()Z
Asciz	newAbstractType;
Asciz	(Ljava/lang/Object;Ljava/lang/Object;)Lscala/reflect/generic/Symbols$AbsSymbol;;
Asciz	newAliasType;
Asciz	newClass;
Asciz	newMethod;
Asciz	newModule;
Asciz	(Ljava/lang/Object;Lscala/reflect/generic/Symbols$AbsSymbol;Ljava/lang/Object;)Lscala/reflect/generic/Symbols$AbsSymbol;;
Asciz	newModuleClass;
Asciz	newValue;
Asciz	enclMethod;
NameAndType	isSourceMethod:()Z
Method	scala/reflect/generic/Symbols$AbsSymbol.isSourceMethod:()Z
NameAndType	enclMethod:()Lscala/reflect/generic/Symbols$AbsSymbol;
Method	scala/reflect/generic/Symbols$AbsSymbol.enclMethod:()Lscala/reflect/generic/Symbols$AbsSymbol;
NameAndType	$outer:Lscala/reflect/generic/Universe;
Field	scala/reflect/generic/Symbols$AbsSymbol.$outer:Lscala/reflect/generic/Universe;
Asciz	(Lscala/reflect/generic/Universe;)V;
Asciz	java/lang/NullPointerException;
class	java/lang/NullPointerException
Method	java/lang/NullPointerException."<init>":()V
Method	java/lang/Object."<init>":()V
Asciz	Scala;
Asciz	InnerClasses;
Asciz	scala/reflect/generic/Types;
class	scala/reflect/generic/Types
Asciz	AbsType;
Asciz	AbsSymbol;
Asciz	StandardNames;
Asciz	AbsDefinitions;
Asciz	scala/ScalaObject;
class	scala/ScalaObject

{
public final scala.reflect.generic.Universe $outer;
  Signature: Lscala/reflect/generic/Universe;

public java.lang.Object newValue$default$2();
  Signature: ()Ljava/lang/Object;
  Code:
   Stack=1, Locals=1, Args_size=1
	aload_0
	invokevirtual	Method scala$reflect$generic$Symbols$AbsSymbol$$$outer:()Lscala/reflect/generic/Universe;
	invokevirtual	Method scala/reflect/generic/Universe.NoPosition:()Ljava/lang/Object;
	areturn
  Labels:

public java.lang.Object newModuleClass$default$2();
  Signature: ()Ljava/lang/Object;
  Code:
   Stack=1, Locals=1, Args_size=1
	aload_0
	invokevirtual	Method scala$reflect$generic$Symbols$AbsSymbol$$$outer:()Lscala/reflect/generic/Universe;
	invokevirtual	Method scala/reflect/generic/Universe.NoPosition:()Ljava/lang/Object;
	areturn
  Labels:

public java.lang.Object newModule$default$3();
  Signature: ()Ljava/lang/Object;
  Code:
   Stack=1, Locals=1, Args_size=1
	aload_0
	invokevirtual	Method scala$reflect$generic$Symbols$AbsSymbol$$$outer:()Lscala/reflect/generic/Universe;
	invokevirtual	Method scala/reflect/generic/Universe.NoPosition:()Ljava/lang/Object;
	areturn
  Labels:

public java.lang.Object newMethod$default$2();
  Signature: ()Ljava/lang/Object;
  Code:
   Stack=1, Locals=1, Args_size=1
	aload_0
	invokevirtual	Method scala$reflect$generic$Symbols$AbsSymbol$$$outer:()Lscala/reflect/generic/Universe;
	invokevirtual	Method scala/reflect/generic/Universe.NoPosition:()Ljava/lang/Object;
	areturn
  Labels:

public java.lang.Object newClass$default$2();
  Signature: ()Ljava/lang/Object;
  Code:
   Stack=1, Locals=1, Args_size=1
	aload_0
	invokevirtual	Method scala$reflect$generic$Symbols$AbsSymbol$$$outer:()Lscala/reflect/generic/Universe;
	invokevirtual	Method scala/reflect/generic/Universe.NoPosition:()Ljava/lang/Object;
	areturn
  Labels:

public java.lang.Object newAliasType$default$2();
  Signature: ()Ljava/lang/Object;
  Code:
   Stack=1, Locals=1, Args_size=1
	aload_0
	invokevirtual	Method scala$reflect$generic$Symbols$AbsSymbol$$$outer:()Lscala/reflect/generic/Universe;
	invokevirtual	Method scala/reflect/generic/Universe.NoPosition:()Ljava/lang/Object;
	areturn
  Labels:

public java.lang.Object newAbstractType$default$2();
  Signature: ()Ljava/lang/Object;
  Code:
   Stack=1, Locals=1, Args_size=1
	aload_0
	invokevirtual	Method scala$reflect$generic$Symbols$AbsSymbol$$$outer:()Lscala/reflect/generic/Universe;
	invokevirtual	Method scala/reflect/generic/Universe.NoPosition:()Ljava/lang/Object;
	areturn
  Labels:

public abstract scala.reflect.generic.Symbols$AbsSymbol owner();
  Signature: ()Lscala/reflect/generic/Symbols$AbsSymbol;

public abstract long flags();
  Signature: ()J

public abstract java.lang.Object name();
  Signature: ()Ljava/lang/Object;

public abstract java.lang.String encodedName();
  Signature: ()Ljava/lang/String;

public java.lang.String decodedName();
  Signature: ()Ljava/lang/String;
  Code:
   Stack=3, Locals=1, Args_size=1
	aload_0
	getstatic	Field scala/reflect/NameTransformer$.MODULE$:Lscala/reflect/NameTransformer$;
	aload_0
	invokevirtual	Method encodedName:()Ljava/lang/String;
	invokevirtual	Method scala/reflect/NameTransformer$.decode:(Ljava/lang/String;)Ljava/lang/String;
	invokespecial	Method stripLocalSuffix:(Ljava/lang/String;)Ljava/lang/String;
	areturn
  Labels:

public final java.lang.String fullName(char);
  Signature: (C)Ljava/lang/String;
  Code:
   Stack=4, Locals=3, Args_size=2
	aload_0
	aload_0
	invokevirtual	Method isRoot:()Z
	ifne	l1 // aload_0
	aload_0
	invokevirtual	Method isRootPackage:()Z
	ifne	l1 // aload_0
	aload_0
	aload_0
	invokevirtual	Method scala$reflect$generic$Symbols$AbsSymbol$$$outer:()Lscala/reflect/generic/Universe;
	invokeinterface	InterfaceMethod scala/reflect/generic/Symbols.NoSymbol:()Lscala/reflect/generic/Symbols$AbsSymbol;
	astore_2
	dup
	ifnonnull	l2 // aload_2
	pop
	aload_2
	ifnull	l1 // aload_0
	goto	l3 // aload_0
l2	aload_2
	invokevirtual	Method java/lang/Object.equals:(Ljava/lang/Object;)Z
	ifeq	l3 // aload_0
l1	aload_0
	invokevirtual	Method toString:()Ljava/lang/String;
	goto	l4 // invokespecial
l3	aload_0
	invokevirtual	Method owner:()Lscala/reflect/generic/Symbols$AbsSymbol;
	invokevirtual	Method isEffectiveRoot:()Z
	ifeq	l5 // new
	aload_0
	invokevirtual	Method encodedName:()Ljava/lang/String;
	goto	l4 // invokespecial
l5	new	class scala/collection/mutable/StringBuilder
	dup
	invokespecial	Method scala/collection/mutable/StringBuilder."<init>":()V
	aload_0
	invokevirtual	Method owner:()Lscala/reflect/generic/Symbols$AbsSymbol;
	invokevirtual	Method enclClass:()Lscala/reflect/generic/Symbols$AbsSymbol;
	iload_1
	invokevirtual	Method fullName:(C)Ljava/lang/String;
	invokevirtual	Method scala/collection/mutable/StringBuilder.append:(Ljava/lang/Object;)Lscala/collection/mutable/StringBuilder;
	iload_1
	invokestatic	Method scala/runtime/BoxesRunTime.boxToCharacter:(C)Ljava/lang/Character;
	invokevirtual	Method scala/collection/mutable/StringBuilder.append:(Ljava/lang/Object;)Lscala/collection/mutable/StringBuilder;
	aload_0
	invokevirtual	Method encodedName:()Ljava/lang/String;
	invokevirtual	Method scala/collection/mutable/StringBuilder.append:(Ljava/lang/Object;)Lscala/collection/mutable/StringBuilder;
	invokevirtual	Method scala/collection/mutable/StringBuilder.toString:()Ljava/lang/String;
l4	invokespecial	Method stripLocalSuffix:(Ljava/lang/String;)Ljava/lang/String;
	areturn
  Labels:
   	l2 = 38 // aload_2
   	l1 = 45 // aload_0
   	l3 = 52 // aload_0
   	l5 = 69 // new
   	l4 = 107 // invokespecial
  LocalVariableTable: 
   Start  Length  Slot  Name   Signature
   0      111      0    this       Lscala/reflect/generic/Symbols$AbsSymbol;
   0      111      1    separator       C


private java.lang.String stripLocalSuffix(java.lang.String);
  Signature: (Ljava/lang/String;)Ljava/lang/String;
  Code:
   Stack=2, Locals=2, Args_size=2
	getstatic	Field scala/Predef$.MODULE$:Lscala/Predef$;
	aload_1
	invokevirtual	Method scala/Predef$.augmentString:(Ljava/lang/String;)Lscala/collection/immutable/StringOps;
	aload_0
	invokevirtual	Method scala$reflect$generic$Symbols$AbsSymbol$$$outer:()Lscala/reflect/generic/Universe;
	invokeinterface	InterfaceMethod scala/reflect/generic/StdNames.nme:()Lscala/reflect/generic/StdNames$StandardNames;
	invokevirtual	Method scala/reflect/generic/StdNames$StandardNames.LOCAL_SUFFIX_STRING:()Ljava/lang/String;
	invokeinterface	InterfaceMethod scala/collection/immutable/StringLike.stripSuffix:(Ljava/lang/String;)Ljava/lang/String;
	areturn
  Labels:
  LocalVariableTable: 
   Start  Length  Slot  Name   Signature
   0      25      0    this       Lscala/reflect/generic/Symbols$AbsSymbol;
   0      25      1    s       Ljava/lang/String;


public final java.lang.String fullName();
  Signature: ()Ljava/lang/String;
  Code:
   Stack=2, Locals=1, Args_size=1
	aload_0
	ldc	int 46
	invokevirtual	Method fullName:(C)Ljava/lang/String;
	areturn
  Labels:

public final boolean hasFlag(long);
  Signature: (J)Z
  Code:
   Stack=4, Locals=3, Args_size=2
	aload_0
	invokevirtual	Method flags:()J
	lload_1
	land
	lconst_0
	lcmp
	ifeq	l1 // iconst_0
	iconst_1
	goto	l2 // ireturn
l1	iconst_0
l2	ireturn
  Labels:
   	l1 = 15 // iconst_0
   	l2 = 16 // ireturn
  LocalVariableTable: 
   Start  Length  Slot  Name   Signature
   0      17      0    this       Lscala/reflect/generic/Symbols$AbsSymbol;
   0      17      1    mask       J


public final boolean hasAllFlags(long);
  Signature: (J)Z
  Code:
   Stack=4, Locals=3, Args_size=2
	aload_0
	invokevirtual	Method flags:()J
	lload_1
	land
	lload_1
	lcmp
	ifne	l1 // iconst_0
	iconst_1
	goto	l2 // ireturn
l1	iconst_0
l2	ireturn
  Labels:
   	l1 = 15 // iconst_0
   	l2 = 16 // ireturn
  LocalVariableTable: 
   Start  Length  Slot  Name   Signature
   0      17      0    this       Lscala/reflect/generic/Symbols$AbsSymbol;
   0      17      1    mask       J


public abstract scala.reflect.generic.Symbols$AbsSymbol privateWithin();
  Signature: ()Lscala/reflect/generic/Symbols$AbsSymbol;

public abstract scala.reflect.generic.Types$AbsType rawInfo();
  Signature: ()Lscala/reflect/generic/Types$AbsType;

public scala.reflect.generic.Types$AbsType tpe();
  Signature: ()Lscala/reflect/generic/Types$AbsType;
  Code:
   Stack=1, Locals=1, Args_size=1
	aload_0
	invokevirtual	Method info:()Lscala/reflect/generic/Types$AbsType;
	areturn
  Labels:

public scala.reflect.generic.Types$AbsType info();
  Signature: ()Lscala/reflect/generic/Types$AbsType;
  Code:
   Stack=2, Locals=2, Args_size=1
	aload_0
	invokevirtual	Method rawInfo:()Lscala/reflect/generic/Types$AbsType;
	astore_1
	aload_1
	aload_0
	invokevirtual	Method scala/reflect/generic/Types$AbsType.complete:(Lscala/reflect/generic/Symbols$AbsSymbol;)V
	aload_1
	areturn
  Labels:
  LocalVariableTable: 
   Start  Length  Slot  Name   Signature
   0      12      0    this       Lscala/reflect/generic/Symbols$AbsSymbol;
   5      6      1    tp       Lscala/reflect/generic/Types$AbsType;


public abstract scala.reflect.generic.Types$AbsType typeOfThis();
  Signature: ()Lscala/reflect/generic/Types$AbsType;

public void owner_$eq(scala.reflect.generic.Symbols$AbsSymbol);
  Signature: (Lscala/reflect/generic/Symbols$AbsSymbol;)V
  Code:
   Stack=4, Locals=2, Args_size=2
	new	class java/lang/UnsupportedOperationException
	dup
	new	class scala/collection/mutable/StringBuilder
	dup
	invokespecial	Method scala/collection/mutable/StringBuilder."<init>":()V
	ldc	String owner_= inapplicable for 
	invokevirtual	Method scala/collection/mutable/StringBuilder.append:(Ljava/lang/Object;)Lscala/collection/mutable/StringBuilder;
	aload_0
	invokevirtual	Method scala/collection/mutable/StringBuilder.append:(Ljava/lang/Object;)Lscala/collection/mutable/StringBuilder;
	invokevirtual	Method scala/collection/mutable/StringBuilder.toString:()Ljava/lang/String;
	invokespecial	Method java/lang/UnsupportedOperationException."<init>":(Ljava/lang/String;)V
	athrow
  Labels:
  LocalVariableTable: 
   Start  Length  Slot  Name   Signature
   0      27      0    this       Lscala/reflect/generic/Symbols$AbsSymbol;
   0      27      1    sym       Lscala/reflect/generic/Symbols$AbsSymbol;


public void flags_$eq(long);
  Signature: (J)V
  Code:
   Stack=4, Locals=3, Args_size=2
	new	class java/lang/UnsupportedOperationException
	dup
	new	class scala/collection/mutable/StringBuilder
	dup
	invokespecial	Method scala/collection/mutable/StringBuilder."<init>":()V
	ldc	String flags_= inapplicable for 
	invokevirtual	Method scala/collection/mutable/StringBuilder.append:(Ljava/lang/Object;)Lscala/collection/mutable/StringBuilder;
	aload_0
	invokevirtual	Method scala/collection/mutable/StringBuilder.append:(Ljava/lang/Object;)Lscala/collection/mutable/StringBuilder;
	invokevirtual	Method scala/collection/mutable/StringBuilder.toString:()Ljava/lang/String;
	invokespecial	Method java/lang/UnsupportedOperationException."<init>":(Ljava/lang/String;)V
	athrow
  Labels:
  LocalVariableTable: 
   Start  Length  Slot  Name   Signature
   0      27      0    this       Lscala/reflect/generic/Symbols$AbsSymbol;
   0      27      1    flags       J


public void info_$eq(scala.reflect.generic.Types$AbsType);
  Signature: (Lscala/reflect/generic/Types$AbsType;)V
  Code:
   Stack=4, Locals=2, Args_size=2
	new	class java/lang/UnsupportedOperationException
	dup
	new	class scala/collection/mutable/StringBuilder
	dup
	invokespecial	Method scala/collection/mutable/StringBuilder."<init>":()V
	ldc	String info_= inapplicable for 
	invokevirtual	Method scala/collection/mutable/StringBuilder.append:(Ljava/lang/Object;)Lscala/collection/mutable/StringBuilder;
	aload_0
	invokevirtual	Method scala/collection/mutable/StringBuilder.append:(Ljava/lang/Object;)Lscala/collection/mutable/StringBuilder;
	invokevirtual	Method scala/collection/mutable/StringBuilder.toString:()Ljava/lang/String;
	invokespecial	Method java/lang/UnsupportedOperationException."<init>":(Ljava/lang/String;)V
	athrow
  Labels:
  LocalVariableTable: 
   Start  Length  Slot  Name   Signature
   0      27      0    this       Lscala/reflect/generic/Symbols$AbsSymbol;
   0      27      1    tp       Lscala/reflect/generic/Types$AbsType;


public void typeOfThis_$eq(scala.reflect.generic.Types$AbsType);
  Signature: (Lscala/reflect/generic/Types$AbsType;)V
  Code:
   Stack=4, Locals=2, Args_size=2
	new	class java/lang/UnsupportedOperationException
	dup
	new	class scala/collection/mutable/StringBuilder
	dup
	invokespecial	Method scala/collection/mutable/StringBuilder."<init>":()V
	ldc	String typeOfThis_= inapplicable for 
	invokevirtual	Method scala/collection/mutable/StringBuilder.append:(Ljava/lang/Object;)Lscala/collection/mutable/StringBuilder;
	aload_0
	invokevirtual	Method scala/collection/mutable/StringBuilder.append:(Ljava/lang/Object;)Lscala/collection/mutable/StringBuilder;
	invokevirtual	Method scala/collection/mutable/StringBuilder.toString:()Ljava/lang/String;
	invokespecial	Method java/lang/UnsupportedOperationException."<init>":(Ljava/lang/String;)V
	athrow
  Labels:
  LocalVariableTable: 
   Start  Length  Slot  Name   Signature
   0      27      0    this       Lscala/reflect/generic/Symbols$AbsSymbol;
   0      27      1    tp       Lscala/reflect/generic/Types$AbsType;


public void privateWithin_$eq(scala.reflect.generic.Symbols$AbsSymbol);
  Signature: (Lscala/reflect/generic/Symbols$AbsSymbol;)V
  Code:
   Stack=4, Locals=2, Args_size=2
	new	class java/lang/UnsupportedOperationException
	dup
	new	class scala/collection/mutable/StringBuilder
	dup
	invokespecial	Method scala/collection/mutable/StringBuilder."<init>":()V
	ldc	String privateWithin_= inapplicable for 
	invokevirtual	Method scala/collection/mutable/StringBuilder.append:(Ljava/lang/Object;)Lscala/collection/mutable/StringBuilder;
	aload_0
	invokevirtual	Method scala/collection/mutable/StringBuilder.append:(Ljava/lang/Object;)Lscala/collection/mutable/StringBuilder;
	invokevirtual	Method scala/collection/mutable/StringBuilder.toString:()Ljava/lang/String;
	invokespecial	Method java/lang/UnsupportedOperationException."<init>":(Ljava/lang/String;)V
	athrow
  Labels:
  LocalVariableTable: 
   Start  Length  Slot  Name   Signature
   0      27      0    this       Lscala/reflect/generic/Symbols$AbsSymbol;
   0      27      1    sym       Lscala/reflect/generic/Symbols$AbsSymbol;


public void sourceModule_$eq(scala.reflect.generic.Symbols$AbsSymbol);
  Signature: (Lscala/reflect/generic/Symbols$AbsSymbol;)V
  Code:
   Stack=4, Locals=2, Args_size=2
	new	class java/lang/UnsupportedOperationException
	dup
	new	class scala/collection/mutable/StringBuilder
	dup
	invokespecial	Method scala/collection/mutable/StringBuilder."<init>":()V
	ldc	String sourceModule_= inapplicable for 
	invokevirtual	Method scala/collection/mutable/StringBuilder.append:(Ljava/lang/Object;)Lscala/collection/mutable/StringBuilder;
	aload_0
	invokevirtual	Method scala/collection/mutable/StringBuilder.append:(Ljava/lang/Object;)Lscala/collection/mutable/StringBuilder;
	invokevirtual	Method scala/collection/mutable/StringBuilder.toString:()Ljava/lang/String;
	invokespecial	Method java/lang/UnsupportedOperationException."<init>":(Ljava/lang/String;)V
	athrow
  Labels:
  LocalVariableTable: 
   Start  Length  Slot  Name   Signature
   0      27      0    this       Lscala/reflect/generic/Symbols$AbsSymbol;
   0      27      1    sym       Lscala/reflect/generic/Symbols$AbsSymbol;


public void addChild(scala.reflect.generic.Symbols$AbsSymbol);
  Signature: (Lscala/reflect/generic/Symbols$AbsSymbol;)V
  Code:
   Stack=4, Locals=2, Args_size=2
	new	class java/lang/UnsupportedOperationException
	dup
	new	class scala/collection/mutable/StringBuilder
	dup
	invokespecial	Method scala/collection/mutable/StringBuilder."<init>":()V
	ldc	String addChild inapplicable for 
	invokevirtual	Method scala/collection/mutable/StringBuilder.append:(Ljava/lang/Object;)Lscala/collection/mutable/StringBuilder;
	aload_0
	invokevirtual	Method scala/collection/mutable/StringBuilder.append:(Ljava/lang/Object;)Lscala/collection/mutable/StringBuilder;
	invokevirtual	Method scala/collection/mutable/StringBuilder.toString:()Ljava/lang/String;
	invokespecial	Method java/lang/UnsupportedOperationException."<init>":(Ljava/lang/String;)V
	athrow
  Labels:
  LocalVariableTable: 
   Start  Length  Slot  Name   Signature
   0      27      0    this       Lscala/reflect/generic/Symbols$AbsSymbol;
   0      27      1    sym       Lscala/reflect/generic/Symbols$AbsSymbol;


public void addAnnotation(java.lang.Object);
  Signature: (Ljava/lang/Object;)V
  Code:
   Stack=4, Locals=2, Args_size=2
	new	class java/lang/UnsupportedOperationException
	dup
	new	class scala/collection/mutable/StringBuilder
	dup
	invokespecial	Method scala/collection/mutable/StringBuilder."<init>":()V
	ldc	String addAnnotation inapplicable for 
	invokevirtual	Method scala/collection/mutable/StringBuilder.append:(Ljava/lang/Object;)Lscala/collection/mutable/StringBuilder;
	aload_0
	invokevirtual	Method scala/collection/mutable/StringBuilder.append:(Ljava/lang/Object;)Lscala/collection/mutable/StringBuilder;
	invokevirtual	Method scala/collection/mutable/StringBuilder.toString:()Ljava/lang/String;
	invokespecial	Method java/lang/UnsupportedOperationException."<init>":(Ljava/lang/String;)V
	athrow
  Labels:
  LocalVariableTable: 
   Start  Length  Slot  Name   Signature
   0      27      0    this       Lscala/reflect/generic/Symbols$AbsSymbol;
   0      27      1    annot       Ljava/lang/Object;


public abstract scala.reflect.generic.Symbols$AbsSymbol linkedClassOfClass();
  Signature: ()Lscala/reflect/generic/Symbols$AbsSymbol;

public scala.reflect.generic.Symbols$AbsSymbol sourceModule();
  Signature: ()Lscala/reflect/generic/Symbols$AbsSymbol;
  Code:
   Stack=1, Locals=1, Args_size=1
	aload_0
	invokevirtual	Method scala$reflect$generic$Symbols$AbsSymbol$$$outer:()Lscala/reflect/generic/Universe;
	invokeinterface	InterfaceMethod scala/reflect/generic/Symbols.NoSymbol:()Lscala/reflect/generic/Symbols$AbsSymbol;
	areturn
  Labels:

public abstract scala.reflect.generic.Symbols$AbsSymbol moduleClass();
  Signature: ()Lscala/reflect/generic/Symbols$AbsSymbol;

public boolean isTerm();
  Signature: ()Z
  Code:
   Stack=1, Locals=1, Args_size=1
	iconst_0
	ireturn
  Labels:

public boolean isType();
  Signature: ()Z
  Code:
   Stack=1, Locals=1, Args_size=1
	iconst_0
	ireturn
  Labels:

public boolean isClass();
  Signature: ()Z
  Code:
   Stack=1, Locals=1, Args_size=1
	iconst_0
	ireturn
  Labels:

public boolean isAliasType();
  Signature: ()Z
  Code:
   Stack=1, Locals=1, Args_size=1
	iconst_0
	ireturn
  Labels:

public boolean isAbstractType();
  Signature: ()Z
  Code:
   Stack=1, Locals=1, Args_size=1
	iconst_0
	ireturn
  Labels:

public boolean isSkolem();
  Signature: ()Z
  Code:
   Stack=1, Locals=1, Args_size=1
	iconst_0
	ireturn
  Labels:

public boolean isTrait();
  Signature: ()Z
  Code:
   Stack=3, Locals=1, Args_size=1
	aload_0
	invokevirtual	Method isClass:()Z
	ifeq	l1 // iconst_0
	aload_0
	ldc2_w	long 33554432l
	invokevirtual	Method hasFlag:(J)Z
	ifeq	l1 // iconst_0
	iconst_1
	goto	l2 // ireturn
l1	iconst_0
l2	ireturn
  Labels:
   	l1 = 21 // iconst_0
   	l2 = 22 // ireturn

public final boolean hasDefault();
  Signature: ()Z
  Code:
   Stack=3, Locals=1, Args_size=1
	aload_0
	ldc2_w	long 8192l
	invokevirtual	Method hasFlag:(J)Z
	ifeq	l1 // iconst_0
	aload_0
	ldc2_w	long 33554432l
	invokevirtual	Method hasFlag:(J)Z
	ifeq	l1 // iconst_0
	iconst_1
	goto	l2 // ireturn
l1	iconst_0
l2	ireturn
  Labels:
   	l1 = 24 // iconst_0
   	l2 = 25 // ireturn

public final boolean isAbstractClass();
  Signature: ()Z
  Code:
   Stack=3, Locals=1, Args_size=1
	aload_0
	invokevirtual	Method isClass:()Z
	ifeq	l1 // iconst_0
	aload_0
	ldc2_w	long 8l
	invokevirtual	Method hasFlag:(J)Z
	ifeq	l1 // iconst_0
	iconst_1
	goto	l2 // ireturn
l1	iconst_0
l2	ireturn
  Labels:
   	l1 = 21 // iconst_0
   	l2 = 22 // ireturn

public final boolean isAbstractOverride();
  Signature: ()Z
  Code:
   Stack=3, Locals=1, Args_size=1
	aload_0
	invokevirtual	Method isTerm:()Z
	ifeq	l1 // iconst_0
	aload_0
	ldc2_w	long 8l
	invokevirtual	Method hasFlag:(J)Z
	ifeq	l1 // iconst_0
	aload_0
	ldc2_w	long 2l
	invokevirtual	Method hasFlag:(J)Z
	ifeq	l1 // iconst_0
	iconst_1
	goto	l2 // ireturn
l1	iconst_0
l2	ireturn
  Labels:
   	l1 = 31 // iconst_0
   	l2 = 32 // ireturn

public final boolean isBridge();
  Signature: ()Z
  Code:
   Stack=3, Locals=1, Args_size=1
	aload_0
	ldc2_w	long 67108864l
	invokevirtual	Method hasFlag:(J)Z
	ireturn
  Labels:

public final boolean isCase();
  Signature: ()Z
  Code:
   Stack=3, Locals=1, Args_size=1
	aload_0
	ldc2_w	long 2048l
	invokevirtual	Method hasFlag:(J)Z
	ireturn
  Labels:

public final boolean isCaseAccessor();
  Signature: ()Z
  Code:
   Stack=3, Locals=1, Args_size=1
	aload_0
	ldc2_w	long 16777216l
	invokevirtual	Method hasFlag:(J)Z
	ireturn
  Labels:

public final boolean isContravariant();
  Signature: ()Z
  Code:
   Stack=3, Locals=1, Args_size=1
	aload_0
	invokevirtual	Method isType:()Z
	ifeq	l1 // iconst_0
	aload_0
	ldc2_w	long 131072l
	invokevirtual	Method hasFlag:(J)Z
	ifeq	l1 // iconst_0
	iconst_1
	goto	l2 // ireturn
l1	iconst_0
l2	ireturn
  Labels:
   	l1 = 21 // iconst_0
   	l2 = 22 // ireturn

public final boolean isCovariant();
  Signature: ()Z
  Code:
   Stack=3, Locals=1, Args_size=1
	aload_0
	invokevirtual	Method isType:()Z
	ifeq	l1 // iconst_0
	aload_0
	ldc2_w	long 65536l
	invokevirtual	Method hasFlag:(J)Z
	ifeq	l1 // iconst_0
	iconst_1
	goto	l2 // ireturn
l1	iconst_0
l2	ireturn
  Labels:
   	l1 = 21 // iconst_0
   	l2 = 22 // ireturn

public final boolean isDeferred();
  Signature: ()Z
  Code:
   Stack=3, Locals=1, Args_size=1
	aload_0
	ldc2_w	long 16l
	invokevirtual	Method hasFlag:(J)Z
	ifeq	l1 // iconst_0
	aload_0
	invokevirtual	Method isClass:()Z
	ifne	l1 // iconst_0
	iconst_1
	goto	l2 // ireturn
l1	iconst_0
l2	ireturn
  Labels:
   	l1 = 21 // iconst_0
   	l2 = 22 // ireturn

public final boolean isEarlyInitialized();
  Signature: ()Z
  Code:
   Stack=3, Locals=1, Args_size=1
	aload_0
	invokevirtual	Method isTerm:()Z
	ifeq	l1 // iconst_0
	aload_0
	ldc2_w	long 137438953472l
	invokevirtual	Method hasFlag:(J)Z
	ifeq	l1 // iconst_0
	iconst_1
	goto	l2 // ireturn
l1	iconst_0
l2	ireturn
  Labels:
   	l1 = 21 // iconst_0
   	l2 = 22 // ireturn

public final boolean isExistentiallyBound();
  Signature: ()Z
  Code:
   Stack=3, Locals=1, Args_size=1
	aload_0
	invokevirtual	Method isType:()Z
	ifeq	l1 // iconst_0
	aload_0
	ldc2_w	long 34359738368l
	invokevirtual	Method hasFlag:(J)Z
	ifeq	l1 // iconst_0
	iconst_1
	goto	l2 // ireturn
l1	iconst_0
l2	ireturn
  Labels:
   	l1 = 21 // iconst_0
   	l2 = 22 // ireturn

public final boolean isFinal();
  Signature: ()Z
  Code:
   Stack=3, Locals=1, Args_size=1
	aload_0
	ldc2_w	long 32l
	invokevirtual	Method hasFlag:(J)Z
	ireturn
  Labels:

public final boolean isGetterOrSetter();
  Signature: ()Z
  Code:
   Stack=3, Locals=1, Args_size=1
	aload_0
	ldc2_w	long 134217728l
	invokevirtual	Method hasFlag:(J)Z
	ireturn
  Labels:

public final boolean isImplClass();
  Signature: ()Z
  Code:
   Stack=3, Locals=1, Args_size=1
	aload_0
	invokevirtual	Method isClass:()Z
	ifeq	l1 // iconst_0
	aload_0
	ldc2_w	long 137438953472l
	invokevirtual	Method hasFlag:(J)Z
	ifeq	l1 // iconst_0
	iconst_1
	goto	l2 // ireturn
l1	iconst_0
l2	ireturn
  Labels:
   	l1 = 21 // iconst_0
   	l2 = 22 // ireturn

public final boolean isImplicit();
  Signature: ()Z
  Code:
   Stack=3, Locals=1, Args_size=1
	aload_0
	ldc2_w	long 512l
	invokevirtual	Method hasFlag:(J)Z
	ireturn
  Labels:

public final boolean isInterface();
  Signature: ()Z
  Code:
   Stack=3, Locals=1, Args_size=1
	aload_0
	ldc2_w	long 128l
	invokevirtual	Method hasFlag:(J)Z
	ireturn
  Labels:

public final boolean isJavaDefined();
  Signature: ()Z
  Code:
   Stack=3, Locals=1, Args_size=1
	aload_0
	ldc2_w	long 1048576l
	invokevirtual	Method hasFlag:(J)Z
	ireturn
  Labels:

public final boolean isLazy();
  Signature: ()Z
  Code:
   Stack=3, Locals=1, Args_size=1
	aload_0
	ldc2_w	long 2147483648l
	invokevirtual	Method hasFlag:(J)Z
	ireturn
  Labels:

public final boolean isMethod();
  Signature: ()Z
  Code:
   Stack=3, Locals=1, Args_size=1
	aload_0
	invokevirtual	Method isTerm:()Z
	ifeq	l1 // iconst_0
	aload_0
	ldc2_w	long 64l
	invokevirtual	Method hasFlag:(J)Z
	ifeq	l1 // iconst_0
	iconst_1
	goto	l2 // ireturn
l1	iconst_0
l2	ireturn
  Labels:
   	l1 = 21 // iconst_0
   	l2 = 22 // ireturn

public final boolean isModule();
  Signature: ()Z
  Code:
   Stack=3, Locals=1, Args_size=1
	aload_0
	invokevirtual	Method isTerm:()Z
	ifeq	l1 // iconst_0
	aload_0
	ldc2_w	long 256l
	invokevirtual	Method hasFlag:(J)Z
	ifeq	l1 // iconst_0
	iconst_1
	goto	l2 // ireturn
l1	iconst_0
l2	ireturn
  Labels:
   	l1 = 21 // iconst_0
   	l2 = 22 // ireturn

public final boolean isModuleClass();
  Signature: ()Z
  Code:
   Stack=3, Locals=1, Args_size=1
	aload_0
	invokevirtual	Method isClass:()Z
	ifeq	l1 // iconst_0
	aload_0
	ldc2_w	long 256l
	invokevirtual	Method hasFlag:(J)Z
	ifeq	l1 // iconst_0
	iconst_1
	goto	l2 // ireturn
l1	iconst_0
l2	ireturn
  Labels:
   	l1 = 21 // iconst_0
   	l2 = 22 // ireturn

public final boolean isMutable();
  Signature: ()Z
  Code:
   Stack=3, Locals=1, Args_size=1
	aload_0
	ldc2_w	long 4096l
	invokevirtual	Method hasFlag:(J)Z
	ireturn
  Labels:

public final boolean isOverloaded();
  Signature: ()Z
  Code:
   Stack=3, Locals=1, Args_size=1
	aload_0
	ldc2_w	long 8589934592l
	invokevirtual	Method hasFlag:(J)Z
	ireturn
  Labels:

public final boolean isOverride();
  Signature: ()Z
  Code:
   Stack=3, Locals=1, Args_size=1
	aload_0
	ldc2_w	long 2l
	invokevirtual	Method hasFlag:(J)Z
	ireturn
  Labels:

public final boolean isParamAccessor();
  Signature: ()Z
  Code:
   Stack=3, Locals=1, Args_size=1
	aload_0
	ldc2_w	long 536870912l
	invokevirtual	Method hasFlag:(J)Z
	ireturn
  Labels:

public final boolean isParameter();
  Signature: ()Z
  Code:
   Stack=3, Locals=1, Args_size=1
	aload_0
	ldc2_w	long 8192l
	invokevirtual	Method hasFlag:(J)Z
	ireturn
  Labels:

public final boolean isRefinementClass();
  Signature: ()Z
  Code:
   Stack=3, Locals=3, Args_size=1
	aload_0
	invokevirtual	Method isClass:()Z
	ifeq	l1 // iconst_0
	aload_0
	invokevirtual	Method name:()Ljava/lang/Object;
	aload_0
	invokevirtual	Method scala$reflect$generic$Symbols$AbsSymbol$$$outer:()Lscala/reflect/generic/Universe;
	aload_0
	invokevirtual	Method scala$reflect$generic$Symbols$AbsSymbol$$$outer:()Lscala/reflect/generic/Universe;
	invokeinterface	InterfaceMethod scala/reflect/generic/StdNames.nme:()Lscala/reflect/generic/StdNames$StandardNames;
	invokevirtual	Method scala/reflect/generic/StdNames$StandardNames.REFINE_CLASS_NAME:()Ljava/lang/Object;
	invokeinterface	InterfaceMethod scala/reflect/generic/Names.mkTypeName:(Ljava/lang/Object;)Ljava/lang/Object;
	astore_2
	astore_1
	aload_1
	aload_2
	if_acmpne	l2 // aload_1
	iconst_1
	goto	l3 // ifeq
l2	aload_1
	ifnonnull	l4 // aload_1
	iconst_0
	goto	l3 // ifeq
l4	aload_1
	instanceof	class java/lang/Number
	ifeq	l5 // aload_1
	aload_1
	checkcast	class java/lang/Number
	aload_2
	invokestatic	Method scala/runtime/BoxesRunTime.equalsNumObject:(Ljava/lang/Number;Ljava/lang/Object;)Z
	goto	l3 // ifeq
l5	aload_1
	instanceof	class java/lang/Character
	ifeq	l6 // aload_1
	aload_1
	checkcast	class java/lang/Character
	aload_2
	invokestatic	Method scala/runtime/BoxesRunTime.equalsCharObject:(Ljava/lang/Character;Ljava/lang/Object;)Z
	goto	l3 // ifeq
l6	aload_1
	aload_2
	invokevirtual	Method java/lang/Object.equals:(Ljava/lang/Object;)Z
l3	ifeq	l1 // iconst_0
	iconst_1
	goto	l7 // ireturn
l1	iconst_0
l7	ireturn
  Labels:
   	l2 = 43 // aload_1
   	l4 = 51 // aload_1
   	l5 = 69 // aload_1
   	l6 = 87 // aload_1
   	l3 = 92 // ifeq
   	l1 = 99 // iconst_0
   	l7 = 100 // ireturn
  LocalVariableTable: 
   Start  Length  Slot  Name   Signature
   0      101      0    this       Lscala/reflect/generic/Symbols$AbsSymbol;
   39      56      1    x0       Ljava/lang/Object;
   39      56      2    y0       Ljava/lang/Object;


public final boolean isSealed();
  Signature: ()Z
  Code:
   Stack=3, Locals=1, Args_size=1
	aload_0
	invokevirtual	Method isClass:()Z
	ifeq	l1 // iconst_0
	aload_0
	ldc2_w	long 1024l
	invokevirtual	Method hasFlag:(J)Z
	ifne	l2 // iconst_1
	aload_0
	invokevirtual	Method scala$reflect$generic$Symbols$AbsSymbol$$$outer:()Lscala/reflect/generic/Universe;
	invokeinterface	InterfaceMethod scala/reflect/generic/StandardDefinitions.definitions:()Lscala/reflect/generic/StandardDefinitions$AbsDefinitions;
	aload_0
	invokevirtual	Method scala/reflect/generic/StandardDefinitions$AbsDefinitions.isValueClass:(Lscala/reflect/generic/Symbols$AbsSymbol;)Z
	ifeq	l1 // iconst_0
l2	iconst_1
	goto	l3 // ireturn
l1	iconst_0
l3	ireturn
  Labels:
   	l2 = 33 // iconst_1
   	l1 = 37 // iconst_0
   	l3 = 38 // ireturn

public final boolean isSourceMethod();
  Signature: ()Z
  Code:
   Stack=4, Locals=1, Args_size=1
	aload_0
	invokevirtual	Method isTerm:()Z
	ifeq	l1 // iconst_0
	aload_0
	invokevirtual	Method flags:()J
	ldc2_w	long 4194368l
	land
	ldc2_w	long 64l
	lcmp
	ifne	l1 // iconst_0
	iconst_1
	goto	l2 // ireturn
l1	iconst_0
l2	ireturn
  Labels:
   	l1 = 26 // iconst_0
   	l2 = 27 // ireturn

public final boolean isSuperAccessor();
  Signature: ()Z
  Code:
   Stack=3, Locals=1, Args_size=1
	aload_0
	ldc2_w	long 268435456l
	invokevirtual	Method hasFlag:(J)Z
	ireturn
  Labels:

public final boolean isSynthetic();
  Signature: ()Z
  Code:
   Stack=3, Locals=1, Args_size=1
	aload_0
	ldc2_w	long 2097152l
	invokevirtual	Method hasFlag:(J)Z
	ireturn
  Labels:

public final boolean isTypeParameter();
  Signature: ()Z
  Code:
   Stack=3, Locals=1, Args_size=1
	aload_0
	invokevirtual	Method isType:()Z
	ifeq	l1 // iconst_0
	aload_0
	ldc2_w	long 8192l
	invokevirtual	Method hasFlag:(J)Z
	ifeq	l1 // iconst_0
	aload_0
	invokevirtual	Method isSkolem:()Z
	ifne	l1 // iconst_0
	iconst_1
	goto	l2 // ireturn
l1	iconst_0
l2	ireturn
  Labels:
   	l1 = 28 // iconst_0
   	l2 = 29 // ireturn

public final boolean isPrivate();
  Signature: ()Z
  Code:
   Stack=3, Locals=1, Args_size=1
	aload_0
	ldc2_w	long 4l
	invokevirtual	Method hasFlag:(J)Z
	ireturn
  Labels:

public final boolean isPrivateLocal();
  Signature: ()Z
  Code:
   Stack=3, Locals=1, Args_size=1
	aload_0
	ldc2_w	long 4l
	invokevirtual	Method hasFlag:(J)Z
	ifeq	l1 // iconst_0
	aload_0
	ldc2_w	long 524288l
	invokevirtual	Method hasFlag:(J)Z
	ifeq	l1 // iconst_0
	iconst_1
	goto	l2 // ireturn
l1	iconst_0
l2	ireturn
  Labels:
   	l1 = 24 // iconst_0
   	l2 = 25 // ireturn

public final boolean isProtected();
  Signature: ()Z
  Code:
   Stack=3, Locals=1, Args_size=1
	aload_0
	lconst_1
	invokevirtual	Method hasFlag:(J)Z
	ireturn
  Labels:

public final boolean isProtectedLocal();
  Signature: ()Z
  Code:
   Stack=3, Locals=1, Args_size=1
	aload_0
	lconst_1
	invokevirtual	Method hasFlag:(J)Z
	ifeq	l1 // iconst_0
	aload_0
	ldc2_w	long 524288l
	invokevirtual	Method hasFlag:(J)Z
	ifeq	l1 // iconst_0
	iconst_1
	goto	l2 // ireturn
l1	iconst_0
l2	ireturn
  Labels:
   	l1 = 22 // iconst_0
   	l2 = 23 // ireturn

public final boolean isPublic();
  Signature: ()Z
  Code:
   Stack=3, Locals=2, Args_size=1
	aload_0
	ldc2_w	long 5l
	invokevirtual	Method hasFlag:(J)Z
	ifne	l1 // iconst_0
	aload_0
	invokevirtual	Method privateWithin:()Lscala/reflect/generic/Symbols$AbsSymbol;
	aload_0
	invokevirtual	Method scala$reflect$generic$Symbols$AbsSymbol$$$outer:()Lscala/reflect/generic/Universe;
	invokeinterface	InterfaceMethod scala/reflect/generic/Symbols.NoSymbol:()Lscala/reflect/generic/Symbols$AbsSymbol;
	astore_1
	dup
	ifnonnull	l2 // aload_1
	pop
	aload_1
	ifnull	l3 // iconst_1
	goto	l1 // iconst_0
l2	aload_1
	invokevirtual	Method java/lang/Object.equals:(Ljava/lang/Object;)Z
	ifeq	l1 // iconst_0
l3	iconst_1
	goto	l4 // ireturn
l1	iconst_0
l4	ireturn
  Labels:
   	l2 = 36 // aload_1
   	l3 = 43 // iconst_1
   	l1 = 47 // iconst_0
   	l4 = 48 // ireturn

public final boolean isEmptyPackage();
  Signature: ()Z
  Code:
   Stack=2, Locals=3, Args_size=1
	aload_0
	invokevirtual	Method isPackage:()Z
	ifeq	l1 // iconst_0
	aload_0
	invokevirtual	Method name:()Ljava/lang/Object;
	aload_0
	invokevirtual	Method scala$reflect$generic$Symbols$AbsSymbol$$$outer:()Lscala/reflect/generic/Universe;
	invokeinterface	InterfaceMethod scala/reflect/generic/StdNames.nme:()Lscala/reflect/generic/StdNames$StandardNames;
	invokevirtual	Method scala/reflect/generic/StdNames$StandardNames.EMPTY_PACKAGE_NAME:()Ljava/lang/Object;
	astore_2
	astore_1
	aload_1
	aload_2
	if_acmpne	l2 // aload_1
	iconst_1
	goto	l3 // ifeq
l2	aload_1
	ifnonnull	l4 // aload_1
	iconst_0
	goto	l3 // ifeq
l4	aload_1
	instanceof	class java/lang/Number
	ifeq	l5 // aload_1
	aload_1
	checkcast	class java/lang/Number
	aload_2
	invokestatic	Method scala/runtime/BoxesRunTime.equalsNumObject:(Ljava/lang/Number;Ljava/lang/Object;)Z
	goto	l3 // ifeq
l5	aload_1
	instanceof	class java/lang/Character
	ifeq	l6 // aload_1
	aload_1
	checkcast	class java/lang/Character
	aload_2
	invokestatic	Method scala/runtime/BoxesRunTime.equalsCharObject:(Ljava/lang/Character;Ljava/lang/Object;)Z
	goto	l3 // ifeq
l6	aload_1
	aload_2
	invokevirtual	Method java/lang/Object.equals:(Ljava/lang/Object;)Z
l3	ifeq	l1 // iconst_0
	iconst_1
	goto	l7 // ireturn
l1	iconst_0
l7	ireturn
  Labels:
   	l2 = 34 // aload_1
   	l4 = 42 // aload_1
   	l5 = 60 // aload_1
   	l6 = 78 // aload_1
   	l3 = 83 // ifeq
   	l1 = 90 // iconst_0
   	l7 = 91 // ireturn
  LocalVariableTable: 
   Start  Length  Slot  Name   Signature
   0      92      0    this       Lscala/reflect/generic/Symbols$AbsSymbol;
   30      56      1    x0       Ljava/lang/Object;
   30      56      2    y0       Ljava/lang/Object;


public final boolean isEmptyPackageClass();
  Signature: ()Z
  Code:
   Stack=3, Locals=3, Args_size=1
	aload_0
	invokevirtual	Method isPackageClass:()Z
	ifeq	l1 // iconst_0
	aload_0
	invokevirtual	Method name:()Ljava/lang/Object;
	aload_0
	invokevirtual	Method scala$reflect$generic$Symbols$AbsSymbol$$$outer:()Lscala/reflect/generic/Universe;
	aload_0
	invokevirtual	Method scala$reflect$generic$Symbols$AbsSymbol$$$outer:()Lscala/reflect/generic/Universe;
	invokeinterface	InterfaceMethod scala/reflect/generic/StdNames.nme:()Lscala/reflect/generic/StdNames$StandardNames;
	invokevirtual	Method scala/reflect/generic/StdNames$StandardNames.EMPTY_PACKAGE_NAME:()Ljava/lang/Object;
	invokeinterface	InterfaceMethod scala/reflect/generic/Names.mkTypeName:(Ljava/lang/Object;)Ljava/lang/Object;
	astore_2
	astore_1
	aload_1
	aload_2
	if_acmpne	l2 // aload_1
	iconst_1
	goto	l3 // ifeq
l2	aload_1
	ifnonnull	l4 // aload_1
	iconst_0
	goto	l3 // ifeq
l4	aload_1
	instanceof	class java/lang/Number
	ifeq	l5 // aload_1
	aload_1
	checkcast	class java/lang/Number
	aload_2
	invokestatic	Method scala/runtime/BoxesRunTime.equalsNumObject:(Ljava/lang/Number;Ljava/lang/Object;)Z
	goto	l3 // ifeq
l5	aload_1
	instanceof	class java/lang/Character
	ifeq	l6 // aload_1
	aload_1
	checkcast	class java/lang/Character
	aload_2
	invokestatic	Method scala/runtime/BoxesRunTime.equalsCharObject:(Ljava/lang/Character;Ljava/lang/Object;)Z
	goto	l3 // ifeq
l6	aload_1
	aload_2
	invokevirtual	Method java/lang/Object.equals:(Ljava/lang/Object;)Z
l3	ifeq	l1 // iconst_0
	iconst_1
	goto	l7 // ireturn
l1	iconst_0
l7	ireturn
  Labels:
   	l2 = 43 // aload_1
   	l4 = 51 // aload_1
   	l5 = 69 // aload_1
   	l6 = 87 // aload_1
   	l3 = 92 // ifeq
   	l1 = 99 // iconst_0
   	l7 = 100 // ireturn
  LocalVariableTable: 
   Start  Length  Slot  Name   Signature
   0      101      0    this       Lscala/reflect/generic/Symbols$AbsSymbol;
   39      56      1    x0       Ljava/lang/Object;
   39      56      2    y0       Ljava/lang/Object;


public final boolean isPackage();
  Signature: ()Z
  Code:
   Stack=3, Locals=1, Args_size=1
	aload_0
	invokevirtual	Method isModule:()Z
	ifeq	l1 // iconst_0
	aload_0
	ldc2_w	long 16384l
	invokevirtual	Method hasFlag:(J)Z
	ifeq	l1 // iconst_0
	iconst_1
	goto	l2 // ireturn
l1	iconst_0
l2	ireturn
  Labels:
   	l1 = 21 // iconst_0
   	l2 = 22 // ireturn

public final boolean isPackageClass();
  Signature: ()Z
  Code:
   Stack=3, Locals=1, Args_size=1
	aload_0
	invokevirtual	Method isClass:()Z
	ifeq	l1 // iconst_0
	aload_0
	ldc2_w	long 16384l
	invokevirtual	Method hasFlag:(J)Z
	ifeq	l1 // iconst_0
	iconst_1
	goto	l2 // ireturn
l1	iconst_0
l2	ireturn
  Labels:
   	l1 = 21 // iconst_0
   	l2 = 22 // ireturn

public final boolean isRoot();
  Signature: ()Z
  Code:
   Stack=2, Locals=2, Args_size=1
	aload_0
	invokevirtual	Method isPackageClass:()Z
	ifeq	l1 // iconst_0
	aload_0
	invokevirtual	Method owner:()Lscala/reflect/generic/Symbols$AbsSymbol;
	aload_0
	invokevirtual	Method scala$reflect$generic$Symbols$AbsSymbol$$$outer:()Lscala/reflect/generic/Universe;
	invokeinterface	InterfaceMethod scala/reflect/generic/Symbols.NoSymbol:()Lscala/reflect/generic/Symbols$AbsSymbol;
	astore_1
	dup
	ifnonnull	l2 // aload_1
	pop
	aload_1
	ifnull	l3 // iconst_1
	goto	l1 // iconst_0
l2	aload_1
	invokevirtual	Method java/lang/Object.equals:(Ljava/lang/Object;)Z
	ifeq	l1 // iconst_0
l3	iconst_1
	goto	l4 // ireturn
l1	iconst_0
l4	ireturn
  Labels:
   	l2 = 33 // aload_1
   	l3 = 40 // iconst_1
   	l1 = 44 // iconst_0
   	l4 = 45 // ireturn

public final boolean isRootPackage();
  Signature: ()Z
  Code:
   Stack=2, Locals=2, Args_size=1
	aload_0
	invokevirtual	Method isPackage:()Z
	ifeq	l1 // iconst_0
	aload_0
	invokevirtual	Method owner:()Lscala/reflect/generic/Symbols$AbsSymbol;
	aload_0
	invokevirtual	Method scala$reflect$generic$Symbols$AbsSymbol$$$outer:()Lscala/reflect/generic/Universe;
	invokeinterface	InterfaceMethod scala/reflect/generic/Symbols.NoSymbol:()Lscala/reflect/generic/Symbols$AbsSymbol;
	astore_1
	dup
	ifnonnull	l2 // aload_1
	pop
	aload_1
	ifnull	l3 // iconst_1
	goto	l1 // iconst_0
l2	aload_1
	invokevirtual	Method java/lang/Object.equals:(Ljava/lang/Object;)Z
	ifeq	l1 // iconst_0
l3	iconst_1
	goto	l4 // ireturn
l1	iconst_0
l4	ireturn
  Labels:
   	l2 = 33 // aload_1
   	l3 = 40 // iconst_1
   	l1 = 44 // iconst_0
   	l4 = 45 // ireturn

public boolean isEffectiveRoot();
  Signature: ()Z
  Code:
   Stack=1, Locals=1, Args_size=1
	aload_0
	invokevirtual	Method isRoot:()Z
	ifne	l1 // iconst_1
	aload_0
	invokevirtual	Method isEmptyPackageClass:()Z
	ifeq	l2 // iconst_0
l1	iconst_1
	goto	l3 // ireturn
l2	iconst_0
l3	ireturn
  Labels:
   	l1 = 14 // iconst_1
   	l2 = 18 // iconst_0
   	l3 = 19 // ireturn

public abstract scala.reflect.generic.Symbols$AbsSymbol newAbstractType(java.lang.Object, java.lang.Object);
  Signature: (Ljava/lang/Object;Ljava/lang/Object;)Lscala/reflect/generic/Symbols$AbsSymbol;

public abstract scala.reflect.generic.Symbols$AbsSymbol newAliasType(java.lang.Object, java.lang.Object);
  Signature: (Ljava/lang/Object;Ljava/lang/Object;)Lscala/reflect/generic/Symbols$AbsSymbol;

public abstract scala.reflect.generic.Symbols$AbsSymbol newClass(java.lang.Object, java.lang.Object);
  Signature: (Ljava/lang/Object;Ljava/lang/Object;)Lscala/reflect/generic/Symbols$AbsSymbol;

public abstract scala.reflect.generic.Symbols$AbsSymbol newMethod(java.lang.Object, java.lang.Object);
  Signature: (Ljava/lang/Object;Ljava/lang/Object;)Lscala/reflect/generic/Symbols$AbsSymbol;

public abstract scala.reflect.generic.Symbols$AbsSymbol newModule(java.lang.Object, scala.reflect.generic.Symbols$AbsSymbol, java.lang.Object);
  Signature: (Ljava/lang/Object;Lscala/reflect/generic/Symbols$AbsSymbol;Ljava/lang/Object;)Lscala/reflect/generic/Symbols$AbsSymbol;

public abstract scala.reflect.generic.Symbols$AbsSymbol newModuleClass(java.lang.Object, java.lang.Object);
  Signature: (Ljava/lang/Object;Ljava/lang/Object;)Lscala/reflect/generic/Symbols$AbsSymbol;

public abstract scala.reflect.generic.Symbols$AbsSymbol newValue(java.lang.Object, java.lang.Object);
  Signature: (Ljava/lang/Object;Ljava/lang/Object;)Lscala/reflect/generic/Symbols$AbsSymbol;

public scala.reflect.generic.Symbols$AbsSymbol enclClass();
  Signature: ()Lscala/reflect/generic/Symbols$AbsSymbol;
  Code:
   Stack=1, Locals=1, Args_size=1
	aload_0
	invokevirtual	Method isClass:()Z
	ifeq	l1 // aload_0
	aload_0
	goto	l2 // areturn
l1	aload_0
	invokevirtual	Method owner:()Lscala/reflect/generic/Symbols$AbsSymbol;
	invokevirtual	Method enclClass:()Lscala/reflect/generic/Symbols$AbsSymbol;
l2	areturn
  Labels:
   	l1 = 11 // aload_0
   	l2 = 18 // areturn

public scala.reflect.generic.Symbols$AbsSymbol enclMethod();
  Signature: ()Lscala/reflect/generic/Symbols$AbsSymbol;
  Code:
   Stack=1, Locals=1, Args_size=1
	aload_0
	invokevirtual	Method isSourceMethod:()Z
	ifeq	l1 // aload_0
	aload_0
	goto	l2 // areturn
l1	aload_0
	invokevirtual	Method owner:()Lscala/reflect/generic/Symbols$AbsSymbol;
	invokevirtual	Method enclMethod:()Lscala/reflect/generic/Symbols$AbsSymbol;
l2	areturn
  Labels:
   	l1 = 11 // aload_0
   	l2 = 18 // areturn

public scala.reflect.generic.Universe scala$reflect$generic$Symbols$AbsSymbol$$$outer();
  Signature: ()Lscala/reflect/generic/Universe;
  Code:
   Stack=1, Locals=1, Args_size=1
	aload_0
	getfield	Field $outer:Lscala/reflect/generic/Universe;
	areturn
  Labels:

public scala.reflect.generic.Symbols$AbsSymbol(scala.reflect.generic.Universe);
  Signature: (Lscala/reflect/generic/Universe;)V
  Code:
   Stack=2, Locals=2, Args_size=2
	aload_1
	ifnonnull	l1 // aload_0
	new	class java/lang/NullPointerException
	dup
	invokespecial	Method java/lang/NullPointerException."<init>":()V
	athrow
l1	aload_0
	aload_1
	putfield	Field $outer:Lscala/reflect/generic/Universe;
	aload_0
	invokespecial	Method java/lang/Object."<init>":()V
	return
  Labels:
   	l1 = 12 // aload_0
  LocalVariableTable: 
   Start  Length  Slot  Name   Signature
   0      22      0    this       Lscala/reflect/generic/Symbols$AbsSymbol;
   0      22      1    $outer       Lscala/reflect/generic/Universe;


}

