Compiled from "Trees.scala"
public class scala.reflect.generic.Trees$Traverser extends java.lang.Object implements scala.ScalaObject
  SourceFile: "Trees.scala"
  Scala: length = 0x
   
  InnerClass: 
   public If=class scala/reflect/generic/Trees$If of class scala/reflect/generic/Trees
   public New=class scala/reflect/generic/Trees$New of class scala/reflect/generic/Trees
   public Try=class scala/reflect/generic/Trees$Try of class scala/reflect/generic/Trees
   public This=class scala/reflect/generic/Trees$This of class scala/reflect/generic/Trees
   public Bind=class scala/reflect/generic/Trees$Bind of class scala/reflect/generic/Trees
   public Star=class scala/reflect/generic/Trees$Star of class scala/reflect/generic/Trees
   public abstract Tree=class scala/reflect/generic/Trees$Tree of class scala/reflect/generic/Trees
   public Ident=class scala/reflect/generic/Trees$Ident of class scala/reflect/generic/Trees
   public Super=class scala/reflect/generic/Trees$Super of class scala/reflect/generic/Trees
   public Apply=class scala/reflect/generic/Trees$Apply of class scala/reflect/generic/Trees
   public Typed=class scala/reflect/generic/Trees$Typed of class scala/reflect/generic/Trees
   public Throw=class scala/reflect/generic/Trees$Throw of class scala/reflect/generic/Trees
   public Match=class scala/reflect/generic/Trees$Match of class scala/reflect/generic/Trees
   public Block=class scala/reflect/generic/Trees$Block of class scala/reflect/generic/Trees
   public Select=class scala/reflect/generic/Trees$Select of class scala/reflect/generic/Trees
   public Return=class scala/reflect/generic/Trees$Return of class scala/reflect/generic/Trees
   public Assign=class scala/reflect/generic/Trees$Assign of class scala/reflect/generic/Trees
   public Import=class scala/reflect/generic/Trees$Import of class scala/reflect/generic/Trees
   public DefDef=class scala/reflect/generic/Trees$DefDef of class scala/reflect/generic/Trees
   public ValDef=class scala/reflect/generic/Trees$ValDef of class scala/reflect/generic/Trees
   public Literal=class scala/reflect/generic/Trees$Literal of class scala/reflect/generic/Trees
   public UnApply=class scala/reflect/generic/Trees$UnApply of class scala/reflect/generic/Trees
   public CaseDef=class scala/reflect/generic/Trees$CaseDef of class scala/reflect/generic/Trees
   public TypeDef=class scala/reflect/generic/Trees$TypeDef of class scala/reflect/generic/Trees
   public abstract RefTree=class scala/reflect/generic/Trees$RefTree of class scala/reflect/generic/Trees
   public Function=class scala/reflect/generic/Trees$Function of class scala/reflect/generic/Trees
   public LabelDef=class scala/reflect/generic/Trees$LabelDef of class scala/reflect/generic/Trees
   public Template=class scala/reflect/generic/Trees$Template of class scala/reflect/generic/Trees
   public ClassDef=class scala/reflect/generic/Trees$ClassDef of class scala/reflect/generic/Trees
   public TypeApply=class scala/reflect/generic/Trees$TypeApply of class scala/reflect/generic/Trees
   public Annotated=class scala/reflect/generic/Trees$Annotated of class scala/reflect/generic/Trees
   public ModuleDef=class scala/reflect/generic/Trees$ModuleDef of class scala/reflect/generic/Trees
   public Modifiers=class scala/reflect/generic/Trees$Modifiers of class scala/reflect/generic/Trees
   public Traverser=class scala/reflect/generic/Trees$Traverser of class scala/reflect/generic/Trees
   public ArrayValue=class scala/reflect/generic/Trees$ArrayValue of class scala/reflect/generic/Trees
   public PackageDef=class scala/reflect/generic/Trees$PackageDef of class scala/reflect/generic/Trees
   public abstract AbsTypeTree=class scala/reflect/generic/Trees$AbsTypeTree of class scala/reflect/generic/Trees
   public Alternative=class scala/reflect/generic/Trees$Alternative of class scala/reflect/generic/Trees
   public abstract AbsSymbol=class scala/reflect/generic/Symbols$AbsSymbol of class scala/reflect/generic/Symbols
   public ApplyDynamic=class scala/reflect/generic/Trees$ApplyDynamic of class scala/reflect/generic/Trees
   public TypeBoundsTree=class scala/reflect/generic/Trees$TypeBoundsTree of class scala/reflect/generic/Trees
   public SelectFromArray=class scala/reflect/generic/Trees$SelectFromArray of class scala/reflect/generic/Trees
   public AppliedTypeTree=class scala/reflect/generic/Trees$AppliedTypeTree of class scala/reflect/generic/Trees
   public CompoundTypeTree=class scala/reflect/generic/Trees$CompoundTypeTree of class scala/reflect/generic/Trees
   public abstract TypeTreeExtractor=class scala/reflect/generic/Trees$TypeTreeExtractor of class scala/reflect/generic/Trees
   public SingletonTypeTree=class scala/reflect/generic/Trees$SingletonTypeTree of class scala/reflect/generic/Trees
   public SelectFromTypeTree=class scala/reflect/generic/Trees$SelectFromTypeTree of class scala/reflect/generic/Trees
   public ExistentialTypeTree=class scala/reflect/generic/Trees$ExistentialTypeTree of class scala/reflect/generic/Trees
   public abstract AbsDefinitions=class scala/reflect/generic/StandardDefinitions$AbsDefinitions of class scala/reflect/generic/StandardDefinitions
   public final $anonfun$traverse$7=class scala/reflect/generic/Trees$Traverser$$anonfun$traverse$7 of class scala/reflect/generic/Trees$Traverser
   public final $anonfun$traverse$6=class scala/reflect/generic/Trees$Traverser$$anonfun$traverse$6 of class scala/reflect/generic/Trees$Traverser
   public final $anonfun$traverse$5=class scala/reflect/generic/Trees$Traverser$$anonfun$traverse$5 of class scala/reflect/generic/Trees$Traverser
   public final $anonfun$traverse$4=class scala/reflect/generic/Trees$Traverser$$anonfun$traverse$4 of class scala/reflect/generic/Trees$Traverser
   public final $anonfun$traverse$3=class scala/reflect/generic/Trees$Traverser$$anonfun$traverse$3 of class scala/reflect/generic/Trees$Traverser
   public final $anonfun$traverse$2=class scala/reflect/generic/Trees$Traverser$$anonfun$traverse$2 of class scala/reflect/generic/Trees$Traverser
   public final $anonfun$traverse$1=class scala/reflect/generic/Trees$Traverser$$anonfun$traverse$1 of class scala/reflect/generic/Trees$Traverser
   public final $anonfun$traverseStats$1=class scala/reflect/generic/Trees$Traverser$$anonfun$traverseStats$1 of class scala/reflect/generic/Trees$Traverser
   public final $anonfun$traverseTrees$1=class scala/reflect/generic/Trees$Traverser$$anonfun$traverseTrees$1 of class scala/reflect/generic/Trees$Traverser
   public final $anonfun$traverseTreess$1=class scala/reflect/generic/Trees$Traverser$$anonfun$traverseTreess$1 of class scala/reflect/generic/Trees$Traverser
  minor version: 0
  major version: 49
  Constant pool:
Asciz	SourceFile;
Asciz	Trees.scala;
Asciz	$outer;
Asciz	Lscala/reflect/generic/Universe;;
Asciz	currentOwner;
Asciz	Lscala/reflect/generic/Symbols$AbsSymbol;;
Asciz	()Lscala/reflect/generic/Symbols$AbsSymbol;;
Asciz	Code;
Asciz	LineNumberTable;
Asciz	scala/reflect/generic/Trees$Traverser;
class	scala/reflect/generic/Trees$Traverser
NameAndType	currentOwner:Lscala/reflect/generic/Symbols$AbsSymbol;
Field	scala/reflect/generic/Trees$Traverser.currentOwner:Lscala/reflect/generic/Symbols$AbsSymbol;
Asciz	currentOwner_$eq;
Asciz	(Lscala/reflect/generic/Symbols$AbsSymbol;)V;
Asciz	traverse;
Asciz	(Lscala/reflect/generic/Trees$Tree;)V;
Asciz	scala$reflect$generic$Trees$Traverser$$$outer;
Asciz	()Lscala/reflect/generic/Universe;;
NameAndType	scala$reflect$generic$Trees$Traverser$$$outer:()Lscala/reflect/generic/Universe;
Method	scala/reflect/generic/Trees$Traverser.scala$reflect$generic$Trees$Traverser$$$outer:()Lscala/reflect/generic/Universe;
Asciz	scala/reflect/generic/Trees;
class	scala/reflect/generic/Trees
Asciz	EmptyTree;
Asciz	()Lscala/reflect/generic/Trees$EmptyTree$;;
NameAndType	EmptyTree:()Lscala/reflect/generic/Trees$EmptyTree$;
InterfaceMethod	scala/reflect/generic/Trees.EmptyTree:()Lscala/reflect/generic/Trees$EmptyTree$;
Asciz	java/lang/Object;
class	java/lang/Object
Asciz	equals;
Asciz	(Ljava/lang/Object;)Z;
NameAndType	equals:(Ljava/lang/Object;)Z
Method	java/lang/Object.equals:(Ljava/lang/Object;)Z
Asciz	scala/reflect/generic/Trees$PackageDef;
class	scala/reflect/generic/Trees$PackageDef
Asciz	pid;
Asciz	()Lscala/reflect/generic/Trees$RefTree;;
NameAndType	pid:()Lscala/reflect/generic/Trees$RefTree;
Method	scala/reflect/generic/Trees$PackageDef.pid:()Lscala/reflect/generic/Trees$RefTree;
Asciz	stats;
Asciz	()Lscala/collection/immutable/List;;
NameAndType	stats:()Lscala/collection/immutable/List;
Method	scala/reflect/generic/Trees$PackageDef.stats:()Lscala/collection/immutable/List;
Asciz	scala/reflect/generic/Trees$Tree;
class	scala/reflect/generic/Trees$Tree
NameAndType	traverse:(Lscala/reflect/generic/Trees$Tree;)V
Method	scala/reflect/generic/Trees$Traverser.traverse:(Lscala/reflect/generic/Trees$Tree;)V
Asciz	symbol;
NameAndType	symbol:()Lscala/reflect/generic/Symbols$AbsSymbol;
Method	scala/reflect/generic/Trees$Tree.symbol:()Lscala/reflect/generic/Symbols$AbsSymbol;
Asciz	scala/reflect/generic/Symbols$AbsSymbol;
class	scala/reflect/generic/Symbols$AbsSymbol
Asciz	moduleClass;
NameAndType	moduleClass:()Lscala/reflect/generic/Symbols$AbsSymbol;
Method	scala/reflect/generic/Symbols$AbsSymbol.moduleClass:()Lscala/reflect/generic/Symbols$AbsSymbol;
Asciz	scala/reflect/generic/Trees$Traverser$$anonfun$traverse$1;
class	scala/reflect/generic/Trees$Traverser$$anonfun$traverse$1
Asciz	<init>;
Asciz	(Lscala/reflect/generic/Trees$Traverser;Lscala/collection/immutable/List;)V;
NameAndType	"<init>":(Lscala/reflect/generic/Trees$Traverser;Lscala/collection/immutable/List;)V
Method	scala/reflect/generic/Trees$Traverser$$anonfun$traverse$1."<init>":(Lscala/reflect/generic/Trees$Traverser;Lscala/collection/immutable/List;)V
Asciz	atOwner;
Asciz	(Lscala/reflect/generic/Symbols$AbsSymbol;Lscala/Function0;)V;
NameAndType	atOwner:(Lscala/reflect/generic/Symbols$AbsSymbol;Lscala/Function0;)V
Method	scala/reflect/generic/Trees$Traverser.atOwner:(Lscala/reflect/generic/Symbols$AbsSymbol;Lscala/Function0;)V
Asciz	scala/reflect/generic/Trees$ClassDef;
class	scala/reflect/generic/Trees$ClassDef
Asciz	mods;
Asciz	()Lscala/reflect/generic/Trees$Modifiers;;
NameAndType	mods:()Lscala/reflect/generic/Trees$Modifiers;
Method	scala/reflect/generic/Trees$ClassDef.mods:()Lscala/reflect/generic/Trees$Modifiers;
Asciz	tparams;
NameAndType	tparams:()Lscala/collection/immutable/List;
Method	scala/reflect/generic/Trees$ClassDef.tparams:()Lscala/collection/immutable/List;
Asciz	impl;
Asciz	()Lscala/reflect/generic/Trees$Template;;
NameAndType	impl:()Lscala/reflect/generic/Trees$Template;
Method	scala/reflect/generic/Trees$ClassDef.impl:()Lscala/reflect/generic/Trees$Template;
Asciz	scala/reflect/generic/Trees$Traverser$$anonfun$traverse$2;
class	scala/reflect/generic/Trees$Traverser$$anonfun$traverse$2
Asciz	(Lscala/reflect/generic/Trees$Traverser;Lscala/reflect/generic/Trees$Modifiers;Lscala/collection/immutable/List;Lscala/reflect/generic/Trees$Template;)V;
NameAndType	"<init>":(Lscala/reflect/generic/Trees$Traverser;Lscala/reflect/generic/Trees$Modifiers;Lscala/collection/immutable/List;Lscala/reflect/generic/Trees$Template;)V
Method	scala/reflect/generic/Trees$Traverser$$anonfun$traverse$2."<init>":(Lscala/reflect/generic/Trees$Traverser;Lscala/reflect/generic/Trees$Modifiers;Lscala/collection/immutable/List;Lscala/reflect/generic/Trees$Template;)V
Asciz	scala/reflect/generic/Trees$ModuleDef;
class	scala/reflect/generic/Trees$ModuleDef
Method	scala/reflect/generic/Trees$ModuleDef.mods:()Lscala/reflect/generic/Trees$Modifiers;
Method	scala/reflect/generic/Trees$ModuleDef.impl:()Lscala/reflect/generic/Trees$Template;
Asciz	scala/reflect/generic/Trees$Traverser$$anonfun$traverse$3;
class	scala/reflect/generic/Trees$Traverser$$anonfun$traverse$3
Asciz	(Lscala/reflect/generic/Trees$Traverser;Lscala/reflect/generic/Trees$Modifiers;Lscala/reflect/generic/Trees$Template;)V;
NameAndType	"<init>":(Lscala/reflect/generic/Trees$Traverser;Lscala/reflect/generic/Trees$Modifiers;Lscala/reflect/generic/Trees$Template;)V
Method	scala/reflect/generic/Trees$Traverser$$anonfun$traverse$3."<init>":(Lscala/reflect/generic/Trees$Traverser;Lscala/reflect/generic/Trees$Modifiers;Lscala/reflect/generic/Trees$Template;)V
Asciz	scala/reflect/generic/Trees$ValDef;
class	scala/reflect/generic/Trees$ValDef
Method	scala/reflect/generic/Trees$ValDef.mods:()Lscala/reflect/generic/Trees$Modifiers;
Asciz	tpt;
Asciz	()Lscala/reflect/generic/Trees$Tree;;
NameAndType	tpt:()Lscala/reflect/generic/Trees$Tree;
Method	scala/reflect/generic/Trees$ValDef.tpt:()Lscala/reflect/generic/Trees$Tree;
Asciz	rhs;
NameAndType	rhs:()Lscala/reflect/generic/Trees$Tree;
Method	scala/reflect/generic/Trees$ValDef.rhs:()Lscala/reflect/generic/Trees$Tree;
Asciz	scala/reflect/generic/Trees$Traverser$$anonfun$traverse$4;
class	scala/reflect/generic/Trees$Traverser$$anonfun$traverse$4
Asciz	(Lscala/reflect/generic/Trees$Traverser;Lscala/reflect/generic/Trees$Modifiers;Lscala/reflect/generic/Trees$Tree;Lscala/reflect/generic/Trees$Tree;)V;
NameAndType	"<init>":(Lscala/reflect/generic/Trees$Traverser;Lscala/reflect/generic/Trees$Modifiers;Lscala/reflect/generic/Trees$Tree;Lscala/reflect/generic/Trees$Tree;)V
Method	scala/reflect/generic/Trees$Traverser$$anonfun$traverse$4."<init>":(Lscala/reflect/generic/Trees$Traverser;Lscala/reflect/generic/Trees$Modifiers;Lscala/reflect/generic/Trees$Tree;Lscala/reflect/generic/Trees$Tree;)V
Asciz	scala/reflect/generic/Trees$DefDef;
class	scala/reflect/generic/Trees$DefDef
Method	scala/reflect/generic/Trees$DefDef.mods:()Lscala/reflect/generic/Trees$Modifiers;
Method	scala/reflect/generic/Trees$DefDef.tparams:()Lscala/collection/immutable/List;
Asciz	vparamss;
NameAndType	vparamss:()Lscala/collection/immutable/List;
Method	scala/reflect/generic/Trees$DefDef.vparamss:()Lscala/collection/immutable/List;
Method	scala/reflect/generic/Trees$DefDef.tpt:()Lscala/reflect/generic/Trees$Tree;
Method	scala/reflect/generic/Trees$DefDef.rhs:()Lscala/reflect/generic/Trees$Tree;
Asciz	scala/reflect/generic/Trees$Traverser$$anonfun$traverse$5;
class	scala/reflect/generic/Trees$Traverser$$anonfun$traverse$5
Asciz	(Lscala/reflect/generic/Trees$Traverser;Lscala/reflect/generic/Trees$Modifiers;Lscala/collection/immutable/List;Lscala/collection/immutable/List;Lscala/reflect/generic/Trees$Tree;Lscala/reflect/generic/Trees$Tree;)V;
NameAndType	"<init>":(Lscala/reflect/generic/Trees$Traverser;Lscala/reflect/generic/Trees$Modifiers;Lscala/collection/immutable/List;Lscala/collection/immutable/List;Lscala/reflect/generic/Trees$Tree;Lscala/reflect/generic/Trees$Tree;)V
Method	scala/reflect/generic/Trees$Traverser$$anonfun$traverse$5."<init>":(Lscala/reflect/generic/Trees$Traverser;Lscala/reflect/generic/Trees$Modifiers;Lscala/collection/immutable/List;Lscala/collection/immutable/List;Lscala/reflect/generic/Trees$Tree;Lscala/reflect/generic/Trees$Tree;)V
Asciz	scala/reflect/generic/Trees$TypeDef;
class	scala/reflect/generic/Trees$TypeDef
Method	scala/reflect/generic/Trees$TypeDef.mods:()Lscala/reflect/generic/Trees$Modifiers;
Method	scala/reflect/generic/Trees$TypeDef.tparams:()Lscala/collection/immutable/List;
Method	scala/reflect/generic/Trees$TypeDef.rhs:()Lscala/reflect/generic/Trees$Tree;
Asciz	scala/reflect/generic/Trees$Traverser$$anonfun$traverse$6;
class	scala/reflect/generic/Trees$Traverser$$anonfun$traverse$6
Asciz	(Lscala/reflect/generic/Trees$Traverser;Lscala/reflect/generic/Trees$Modifiers;Lscala/collection/immutable/List;Lscala/reflect/generic/Trees$Tree;)V;
NameAndType	"<init>":(Lscala/reflect/generic/Trees$Traverser;Lscala/reflect/generic/Trees$Modifiers;Lscala/collection/immutable/List;Lscala/reflect/generic/Trees$Tree;)V
Method	scala/reflect/generic/Trees$Traverser$$anonfun$traverse$6."<init>":(Lscala/reflect/generic/Trees$Traverser;Lscala/reflect/generic/Trees$Modifiers;Lscala/collection/immutable/List;Lscala/reflect/generic/Trees$Tree;)V
Asciz	scala/reflect/generic/Trees$LabelDef;
class	scala/reflect/generic/Trees$LabelDef
Asciz	params;
NameAndType	params:()Lscala/collection/immutable/List;
Method	scala/reflect/generic/Trees$LabelDef.params:()Lscala/collection/immutable/List;
Method	scala/reflect/generic/Trees$LabelDef.rhs:()Lscala/reflect/generic/Trees$Tree;
Asciz	traverseTrees;
Asciz	(Lscala/collection/immutable/List;)V;
NameAndType	traverseTrees:(Lscala/collection/immutable/List;)V
Method	scala/reflect/generic/Trees$Traverser.traverseTrees:(Lscala/collection/immutable/List;)V
Asciz	scala/reflect/generic/Trees$Import;
class	scala/reflect/generic/Trees$Import
Asciz	expr;
NameAndType	expr:()Lscala/reflect/generic/Trees$Tree;
Method	scala/reflect/generic/Trees$Import.expr:()Lscala/reflect/generic/Trees$Tree;
Asciz	scala/reflect/generic/Trees$Annotated;
class	scala/reflect/generic/Trees$Annotated
Asciz	annot;
NameAndType	annot:()Lscala/reflect/generic/Trees$Tree;
Method	scala/reflect/generic/Trees$Annotated.annot:()Lscala/reflect/generic/Trees$Tree;
Asciz	arg;
NameAndType	arg:()Lscala/reflect/generic/Trees$Tree;
Method	scala/reflect/generic/Trees$Annotated.arg:()Lscala/reflect/generic/Trees$Tree;
Asciz	scala/reflect/generic/Trees$Template;
class	scala/reflect/generic/Trees$Template
Asciz	parents;
NameAndType	parents:()Lscala/collection/immutable/List;
Method	scala/reflect/generic/Trees$Template.parents:()Lscala/collection/immutable/List;
Asciz	self;
Asciz	()Lscala/reflect/generic/Trees$ValDef;;
NameAndType	self:()Lscala/reflect/generic/Trees$ValDef;
Method	scala/reflect/generic/Trees$Template.self:()Lscala/reflect/generic/Trees$ValDef;
Asciz	body;
NameAndType	body:()Lscala/collection/immutable/List;
Method	scala/reflect/generic/Trees$Template.body:()Lscala/collection/immutable/List;
Asciz	isEmpty;
Asciz	()Z;
NameAndType	isEmpty:()Z
Method	scala/reflect/generic/Trees$ValDef.isEmpty:()Z
Asciz	traverseStats;
Asciz	(Lscala/collection/immutable/List;Lscala/reflect/generic/Symbols$AbsSymbol;)V;
NameAndType	traverseStats:(Lscala/collection/immutable/List;Lscala/reflect/generic/Symbols$AbsSymbol;)V
Method	scala/reflect/generic/Trees$Traverser.traverseStats:(Lscala/collection/immutable/List;Lscala/reflect/generic/Symbols$AbsSymbol;)V
Asciz	scala/reflect/generic/Trees$Block;
class	scala/reflect/generic/Trees$Block
Method	scala/reflect/generic/Trees$Block.stats:()Lscala/collection/immutable/List;
Method	scala/reflect/generic/Trees$Block.expr:()Lscala/reflect/generic/Trees$Tree;
Asciz	scala/reflect/generic/Trees$CaseDef;
class	scala/reflect/generic/Trees$CaseDef
Asciz	pat;
NameAndType	pat:()Lscala/reflect/generic/Trees$Tree;
Method	scala/reflect/generic/Trees$CaseDef.pat:()Lscala/reflect/generic/Trees$Tree;
Asciz	guard;
NameAndType	guard:()Lscala/reflect/generic/Trees$Tree;
Method	scala/reflect/generic/Trees$CaseDef.guard:()Lscala/reflect/generic/Trees$Tree;
NameAndType	body:()Lscala/reflect/generic/Trees$Tree;
Method	scala/reflect/generic/Trees$CaseDef.body:()Lscala/reflect/generic/Trees$Tree;
Asciz	scala/reflect/generic/Trees$Alternative;
class	scala/reflect/generic/Trees$Alternative
Asciz	trees;
NameAndType	trees:()Lscala/collection/immutable/List;
Method	scala/reflect/generic/Trees$Alternative.trees:()Lscala/collection/immutable/List;
Asciz	scala/reflect/generic/Trees$Star;
class	scala/reflect/generic/Trees$Star
Asciz	elem;
NameAndType	elem:()Lscala/reflect/generic/Trees$Tree;
Method	scala/reflect/generic/Trees$Star.elem:()Lscala/reflect/generic/Trees$Tree;
Asciz	scala/reflect/generic/Trees$Bind;
class	scala/reflect/generic/Trees$Bind
Method	scala/reflect/generic/Trees$Bind.body:()Lscala/reflect/generic/Trees$Tree;
Asciz	scala/reflect/generic/Trees$UnApply;
class	scala/reflect/generic/Trees$UnApply
Asciz	fun;
NameAndType	fun:()Lscala/reflect/generic/Trees$Tree;
Method	scala/reflect/generic/Trees$UnApply.fun:()Lscala/reflect/generic/Trees$Tree;
Asciz	args;
NameAndType	args:()Lscala/collection/immutable/List;
Method	scala/reflect/generic/Trees$UnApply.args:()Lscala/collection/immutable/List;
Asciz	scala/reflect/generic/Trees$ArrayValue;
class	scala/reflect/generic/Trees$ArrayValue
Asciz	elemtpt;
NameAndType	elemtpt:()Lscala/reflect/generic/Trees$Tree;
Method	scala/reflect/generic/Trees$ArrayValue.elemtpt:()Lscala/reflect/generic/Trees$Tree;
Asciz	elems;
NameAndType	elems:()Lscala/collection/immutable/List;
Method	scala/reflect/generic/Trees$ArrayValue.elems:()Lscala/collection/immutable/List;
Asciz	scala/reflect/generic/Trees$Function;
class	scala/reflect/generic/Trees$Function
Asciz	vparams;
NameAndType	vparams:()Lscala/collection/immutable/List;
Method	scala/reflect/generic/Trees$Function.vparams:()Lscala/collection/immutable/List;
Method	scala/reflect/generic/Trees$Function.body:()Lscala/reflect/generic/Trees$Tree;
Asciz	scala/reflect/generic/Trees$Traverser$$anonfun$traverse$7;
class	scala/reflect/generic/Trees$Traverser$$anonfun$traverse$7
Asciz	(Lscala/reflect/generic/Trees$Traverser;Lscala/collection/immutable/List;Lscala/reflect/generic/Trees$Tree;)V;
NameAndType	"<init>":(Lscala/reflect/generic/Trees$Traverser;Lscala/collection/immutable/List;Lscala/reflect/generic/Trees$Tree;)V
Method	scala/reflect/generic/Trees$Traverser$$anonfun$traverse$7."<init>":(Lscala/reflect/generic/Trees$Traverser;Lscala/collection/immutable/List;Lscala/reflect/generic/Trees$Tree;)V
Asciz	scala/reflect/generic/Trees$Assign;
class	scala/reflect/generic/Trees$Assign
Asciz	lhs;
NameAndType	lhs:()Lscala/reflect/generic/Trees$Tree;
Method	scala/reflect/generic/Trees$Assign.lhs:()Lscala/reflect/generic/Trees$Tree;
Method	scala/reflect/generic/Trees$Assign.rhs:()Lscala/reflect/generic/Trees$Tree;
Asciz	scala/reflect/generic/Trees$If;
class	scala/reflect/generic/Trees$If
Asciz	cond;
NameAndType	cond:()Lscala/reflect/generic/Trees$Tree;
Method	scala/reflect/generic/Trees$If.cond:()Lscala/reflect/generic/Trees$Tree;
Asciz	thenp;
NameAndType	thenp:()Lscala/reflect/generic/Trees$Tree;
Method	scala/reflect/generic/Trees$If.thenp:()Lscala/reflect/generic/Trees$Tree;
Asciz	elsep;
NameAndType	elsep:()Lscala/reflect/generic/Trees$Tree;
Method	scala/reflect/generic/Trees$If.elsep:()Lscala/reflect/generic/Trees$Tree;
Asciz	scala/reflect/generic/Trees$Match;
class	scala/reflect/generic/Trees$Match
Asciz	selector;
NameAndType	selector:()Lscala/reflect/generic/Trees$Tree;
Method	scala/reflect/generic/Trees$Match.selector:()Lscala/reflect/generic/Trees$Tree;
Asciz	cases;
NameAndType	cases:()Lscala/collection/immutable/List;
Method	scala/reflect/generic/Trees$Match.cases:()Lscala/collection/immutable/List;
Asciz	scala/reflect/generic/Trees$Return;
class	scala/reflect/generic/Trees$Return
Method	scala/reflect/generic/Trees$Return.expr:()Lscala/reflect/generic/Trees$Tree;
Asciz	scala/reflect/generic/Trees$Try;
class	scala/reflect/generic/Trees$Try
Asciz	block;
NameAndType	block:()Lscala/reflect/generic/Trees$Tree;
Method	scala/reflect/generic/Trees$Try.block:()Lscala/reflect/generic/Trees$Tree;
Asciz	catches;
NameAndType	catches:()Lscala/collection/immutable/List;
Method	scala/reflect/generic/Trees$Try.catches:()Lscala/collection/immutable/List;
Asciz	finalizer;
NameAndType	finalizer:()Lscala/reflect/generic/Trees$Tree;
Method	scala/reflect/generic/Trees$Try.finalizer:()Lscala/reflect/generic/Trees$Tree;
Asciz	scala/reflect/generic/Trees$Throw;
class	scala/reflect/generic/Trees$Throw
Method	scala/reflect/generic/Trees$Throw.expr:()Lscala/reflect/generic/Trees$Tree;
Asciz	scala/reflect/generic/Trees$New;
class	scala/reflect/generic/Trees$New
Method	scala/reflect/generic/Trees$New.tpt:()Lscala/reflect/generic/Trees$Tree;
Asciz	scala/reflect/generic/Trees$Typed;
class	scala/reflect/generic/Trees$Typed
Method	scala/reflect/generic/Trees$Typed.expr:()Lscala/reflect/generic/Trees$Tree;
Method	scala/reflect/generic/Trees$Typed.tpt:()Lscala/reflect/generic/Trees$Tree;
Asciz	scala/reflect/generic/Trees$TypeApply;
class	scala/reflect/generic/Trees$TypeApply
Method	scala/reflect/generic/Trees$TypeApply.fun:()Lscala/reflect/generic/Trees$Tree;
Method	scala/reflect/generic/Trees$TypeApply.args:()Lscala/collection/immutable/List;
Asciz	scala/reflect/generic/Trees$Apply;
class	scala/reflect/generic/Trees$Apply
Method	scala/reflect/generic/Trees$Apply.fun:()Lscala/reflect/generic/Trees$Tree;
Method	scala/reflect/generic/Trees$Apply.args:()Lscala/collection/immutable/List;
Asciz	scala/reflect/generic/Trees$ApplyDynamic;
class	scala/reflect/generic/Trees$ApplyDynamic
Asciz	qual;
NameAndType	qual:()Lscala/reflect/generic/Trees$Tree;
Method	scala/reflect/generic/Trees$ApplyDynamic.qual:()Lscala/reflect/generic/Trees$Tree;
Method	scala/reflect/generic/Trees$ApplyDynamic.args:()Lscala/collection/immutable/List;
Asciz	scala/reflect/generic/Trees$Super;
class	scala/reflect/generic/Trees$Super
Asciz	scala/reflect/generic/Trees$This;
class	scala/reflect/generic/Trees$This
Asciz	scala/reflect/generic/Trees$Select;
class	scala/reflect/generic/Trees$Select
Asciz	qualifier;
NameAndType	qualifier:()Lscala/reflect/generic/Trees$Tree;
Method	scala/reflect/generic/Trees$Select.qualifier:()Lscala/reflect/generic/Trees$Tree;
Asciz	scala/reflect/generic/Trees$Ident;
class	scala/reflect/generic/Trees$Ident
Asciz	scala/reflect/generic/Trees$Literal;
class	scala/reflect/generic/Trees$Literal
Asciz	scala/reflect/generic/Trees$AbsTypeTree;
class	scala/reflect/generic/Trees$AbsTypeTree
Asciz	TypeTree;
Asciz	()Lscala/reflect/generic/Trees$TypeTreeExtractor;;
NameAndType	TypeTree:()Lscala/reflect/generic/Trees$TypeTreeExtractor;
InterfaceMethod	scala/reflect/generic/Trees.TypeTree:()Lscala/reflect/generic/Trees$TypeTreeExtractor;
Asciz	scala/reflect/generic/Trees$TypeTreeExtractor;
class	scala/reflect/generic/Trees$TypeTreeExtractor
Asciz	unapply;
Asciz	(Lscala/reflect/generic/Trees$AbsTypeTree;)Z;
NameAndType	unapply:(Lscala/reflect/generic/Trees$AbsTypeTree;)Z
Method	scala/reflect/generic/Trees$TypeTreeExtractor.unapply:(Lscala/reflect/generic/Trees$AbsTypeTree;)Z
Asciz	scala/MatchError;
class	scala/MatchError
Asciz	toString;
Asciz	()Ljava/lang/String;;
NameAndType	toString:()Ljava/lang/String;
Method	scala/reflect/generic/Trees$Tree.toString:()Ljava/lang/String;
Asciz	(Ljava/lang/String;)V;
NameAndType	"<init>":(Ljava/lang/String;)V
Method	scala/MatchError."<init>":(Ljava/lang/String;)V
Asciz	scala/reflect/generic/Trees$SingletonTypeTree;
class	scala/reflect/generic/Trees$SingletonTypeTree
Asciz	ref;
NameAndType	ref:()Lscala/reflect/generic/Trees$Tree;
Method	scala/reflect/generic/Trees$SingletonTypeTree.ref:()Lscala/reflect/generic/Trees$Tree;
Asciz	scala/reflect/generic/Trees$SelectFromTypeTree;
class	scala/reflect/generic/Trees$SelectFromTypeTree
Method	scala/reflect/generic/Trees$SelectFromTypeTree.qualifier:()Lscala/reflect/generic/Trees$Tree;
Asciz	scala/reflect/generic/Trees$CompoundTypeTree;
class	scala/reflect/generic/Trees$CompoundTypeTree
Asciz	templ;
NameAndType	templ:()Lscala/reflect/generic/Trees$Template;
Method	scala/reflect/generic/Trees$CompoundTypeTree.templ:()Lscala/reflect/generic/Trees$Template;
Asciz	scala/reflect/generic/Trees$AppliedTypeTree;
class	scala/reflect/generic/Trees$AppliedTypeTree
Method	scala/reflect/generic/Trees$AppliedTypeTree.tpt:()Lscala/reflect/generic/Trees$Tree;
Method	scala/reflect/generic/Trees$AppliedTypeTree.args:()Lscala/collection/immutable/List;
Asciz	scala/reflect/generic/Trees$TypeBoundsTree;
class	scala/reflect/generic/Trees$TypeBoundsTree
Asciz	lo;
NameAndType	lo:()Lscala/reflect/generic/Trees$Tree;
Method	scala/reflect/generic/Trees$TypeBoundsTree.lo:()Lscala/reflect/generic/Trees$Tree;
Asciz	hi;
NameAndType	hi:()Lscala/reflect/generic/Trees$Tree;
Method	scala/reflect/generic/Trees$TypeBoundsTree.hi:()Lscala/reflect/generic/Trees$Tree;
Asciz	scala/reflect/generic/Trees$ExistentialTypeTree;
class	scala/reflect/generic/Trees$ExistentialTypeTree
Method	scala/reflect/generic/Trees$ExistentialTypeTree.tpt:()Lscala/reflect/generic/Trees$Tree;
Asciz	whereClauses;
NameAndType	whereClauses:()Lscala/collection/immutable/List;
Method	scala/reflect/generic/Trees$ExistentialTypeTree.whereClauses:()Lscala/collection/immutable/List;
Asciz	scala/reflect/generic/Trees$SelectFromArray;
class	scala/reflect/generic/Trees$SelectFromArray
Method	scala/reflect/generic/Trees$SelectFromArray.qualifier:()Lscala/reflect/generic/Trees$Tree;
Asciz	this;
Asciz	Lscala/reflect/generic/Trees$Traverser;;
Asciz	tree;
Asciz	Lscala/reflect/generic/Trees$Tree;;
Asciz	temp85;
Asciz	Lscala/reflect/generic/Trees$PackageDef;;
Asciz	temp86;
Asciz	Lscala/reflect/generic/Trees$RefTree;;
Asciz	temp87;
Asciz	Lscala/collection/immutable/List;;
Asciz	temp88;
Asciz	Lscala/reflect/generic/Trees$ClassDef;;
Asciz	temp89;
Asciz	Lscala/reflect/generic/Trees$Modifiers;;
Asciz	temp91;
Asciz	temp92;
Asciz	Lscala/reflect/generic/Trees$Template;;
Asciz	temp93;
Asciz	Lscala/reflect/generic/Trees$ModuleDef;;
Asciz	temp94;
Asciz	temp96;
Asciz	temp97;
Asciz	Lscala/reflect/generic/Trees$ValDef;;
Asciz	temp98;
Asciz	temp100;
Asciz	temp101;
Asciz	temp102;
Asciz	Lscala/reflect/generic/Trees$DefDef;;
Asciz	temp103;
Asciz	temp105;
Asciz	temp106;
Asciz	temp107;
Asciz	temp108;
Asciz	temp109;
Asciz	Lscala/reflect/generic/Trees$TypeDef;;
Asciz	temp110;
Asciz	temp112;
Asciz	temp113;
Asciz	temp114;
Asciz	Lscala/reflect/generic/Trees$LabelDef;;
Asciz	temp116;
Asciz	temp117;
Asciz	temp118;
Asciz	Lscala/reflect/generic/Trees$Import;;
Asciz	temp119;
Asciz	temp121;
Asciz	Lscala/reflect/generic/Trees$Annotated;;
Asciz	temp122;
Asciz	temp123;
Asciz	temp124;
Asciz	temp125;
Asciz	temp126;
Asciz	temp127;
Asciz	temp128;
Asciz	Lscala/reflect/generic/Trees$Block;;
Asciz	temp129;
Asciz	temp130;
Asciz	temp131;
Asciz	Lscala/reflect/generic/Trees$CaseDef;;
Asciz	temp132;
Asciz	temp133;
Asciz	temp134;
Asciz	temp135;
Asciz	Lscala/reflect/generic/Trees$Alternative;;
Asciz	temp136;
Asciz	temp137;
Asciz	Lscala/reflect/generic/Trees$Star;;
Asciz	temp138;
Asciz	temp139;
Asciz	Lscala/reflect/generic/Trees$Bind;;
Asciz	temp141;
Asciz	temp142;
Asciz	Lscala/reflect/generic/Trees$UnApply;;
Asciz	temp143;
Asciz	temp144;
Asciz	temp145;
Asciz	Lscala/reflect/generic/Trees$ArrayValue;;
Asciz	temp146;
Asciz	temp147;
Asciz	temp148;
Asciz	Lscala/reflect/generic/Trees$Function;;
Asciz	temp149;
Asciz	temp150;
Asciz	temp151;
Asciz	Lscala/reflect/generic/Trees$Assign;;
Asciz	temp152;
Asciz	temp153;
Asciz	temp154;
Asciz	Lscala/reflect/generic/Trees$If;;
Asciz	temp155;
Asciz	temp156;
Asciz	temp157;
Asciz	temp158;
Asciz	Lscala/reflect/generic/Trees$Match;;
Asciz	temp159;
Asciz	temp160;
Asciz	temp161;
Asciz	Lscala/reflect/generic/Trees$Return;;
Asciz	temp162;
Asciz	temp163;
Asciz	Lscala/reflect/generic/Trees$Try;;
Asciz	temp164;
Asciz	temp165;
Asciz	temp166;
Asciz	temp167;
Asciz	Lscala/reflect/generic/Trees$Throw;;
Asciz	temp168;
Asciz	temp169;
Asciz	Lscala/reflect/generic/Trees$New;;
Asciz	temp170;
Asciz	temp171;
Asciz	Lscala/reflect/generic/Trees$Typed;;
Asciz	temp172;
Asciz	temp173;
Asciz	temp174;
Asciz	Lscala/reflect/generic/Trees$TypeApply;;
Asciz	temp175;
Asciz	temp176;
Asciz	temp177;
Asciz	Lscala/reflect/generic/Trees$Apply;;
Asciz	temp178;
Asciz	temp179;
Asciz	temp180;
Asciz	Lscala/reflect/generic/Trees$ApplyDynamic;;
Asciz	temp181;
Asciz	temp182;
Asciz	temp188;
Asciz	Lscala/reflect/generic/Trees$Select;;
Asciz	temp189;
Asciz	temp197;
Asciz	Lscala/reflect/generic/Trees$SingletonTypeTree;;
Asciz	temp198;
Asciz	temp199;
Asciz	Lscala/reflect/generic/Trees$SelectFromTypeTree;;
Asciz	temp200;
Asciz	temp202;
Asciz	Lscala/reflect/generic/Trees$CompoundTypeTree;;
Asciz	temp203;
Asciz	temp204;
Asciz	Lscala/reflect/generic/Trees$AppliedTypeTree;;
Asciz	temp205;
Asciz	temp206;
Asciz	temp207;
Asciz	Lscala/reflect/generic/Trees$TypeBoundsTree;;
Asciz	temp208;
Asciz	temp209;
Asciz	temp210;
Asciz	Lscala/reflect/generic/Trees$ExistentialTypeTree;;
Asciz	temp211;
Asciz	temp212;
Asciz	temp213;
Asciz	Lscala/reflect/generic/Trees$SelectFromArray;;
Asciz	temp214;
Asciz	LocalVariableTable;
Asciz	scala/reflect/generic/Trees$Traverser$$anonfun$traverseTrees$1;
class	scala/reflect/generic/Trees$Traverser$$anonfun$traverseTrees$1
Asciz	(Lscala/reflect/generic/Trees$Traverser;)V;
NameAndType	"<init>":(Lscala/reflect/generic/Trees$Traverser;)V
Method	scala/reflect/generic/Trees$Traverser$$anonfun$traverseTrees$1."<init>":(Lscala/reflect/generic/Trees$Traverser;)V
Asciz	scala/collection/LinearSeqLike;
class	scala/collection/LinearSeqLike
Asciz	foreach;
Asciz	(Lscala/Function1;)V;
NameAndType	foreach:(Lscala/Function1;)V
InterfaceMethod	scala/collection/LinearSeqLike.foreach:(Lscala/Function1;)V
Asciz	(Lscala/collection/immutable/List<Lscala/reflect/generic/Trees$Tree;>;)V;
Asciz	Signature;
Asciz	traverseTreess;
Asciz	scala/reflect/generic/Trees$Traverser$$anonfun$traverseTreess$1;
class	scala/reflect/generic/Trees$Traverser$$anonfun$traverseTreess$1
Method	scala/reflect/generic/Trees$Traverser$$anonfun$traverseTreess$1."<init>":(Lscala/reflect/generic/Trees$Traverser;)V
Asciz	treess;
Asciz	(Lscala/collection/immutable/List<Lscala/collection/immutable/List<Lscala/reflect/generic/Trees$Tree;>;>;)V;
Asciz	scala/reflect/generic/Trees$Traverser$$anonfun$traverseStats$1;
class	scala/reflect/generic/Trees$Traverser$$anonfun$traverseStats$1
Asciz	(Lscala/reflect/generic/Trees$Traverser;Lscala/reflect/generic/Symbols$AbsSymbol;)V;
NameAndType	"<init>":(Lscala/reflect/generic/Trees$Traverser;Lscala/reflect/generic/Symbols$AbsSymbol;)V
Method	scala/reflect/generic/Trees$Traverser$$anonfun$traverseStats$1."<init>":(Lscala/reflect/generic/Trees$Traverser;Lscala/reflect/generic/Symbols$AbsSymbol;)V
Asciz	exprOwner$1;
Asciz	(Lscala/collection/immutable/List<Lscala/reflect/generic/Trees$Tree;>;Lscala/reflect/generic/Symbols$AbsSymbol;)V;
NameAndType	currentOwner:()Lscala/reflect/generic/Symbols$AbsSymbol;
Method	scala/reflect/generic/Trees$Traverser.currentOwner:()Lscala/reflect/generic/Symbols$AbsSymbol;
NameAndType	currentOwner_$eq:(Lscala/reflect/generic/Symbols$AbsSymbol;)V
Method	scala/reflect/generic/Trees$Traverser.currentOwner_$eq:(Lscala/reflect/generic/Symbols$AbsSymbol;)V
Asciz	scala/Function0;
class	scala/Function0
Asciz	apply;
Asciz	()Ljava/lang/Object;;
NameAndType	apply:()Ljava/lang/Object;
InterfaceMethod	scala/Function0.apply:()Ljava/lang/Object;
Asciz	owner;
Asciz	Lscala/Function0;;
Asciz	prevOwner;
Asciz	(Lscala/reflect/generic/Symbols$AbsSymbol;Lscala/Function0<Ljava/lang/Object;>;)V;
NameAndType	$outer:Lscala/reflect/generic/Universe;
Field	scala/reflect/generic/Trees$Traverser.$outer:Lscala/reflect/generic/Universe;
Asciz	(Lscala/reflect/generic/Universe;)V;
Asciz	java/lang/NullPointerException;
class	java/lang/NullPointerException
Asciz	()V;
NameAndType	"<init>":()V
Method	java/lang/NullPointerException."<init>":()V
Method	java/lang/Object."<init>":()V
Asciz	scala/reflect/generic/StandardDefinitions;
class	scala/reflect/generic/StandardDefinitions
Asciz	definitions;
Asciz	()Lscala/reflect/generic/StandardDefinitions$AbsDefinitions;;
NameAndType	definitions:()Lscala/reflect/generic/StandardDefinitions$AbsDefinitions;
InterfaceMethod	scala/reflect/generic/StandardDefinitions.definitions:()Lscala/reflect/generic/StandardDefinitions$AbsDefinitions;
Asciz	scala/reflect/generic/StandardDefinitions$AbsDefinitions;
class	scala/reflect/generic/StandardDefinitions$AbsDefinitions
Asciz	RootClass;
NameAndType	RootClass:()Lscala/reflect/generic/Symbols$AbsSymbol;
Method	scala/reflect/generic/StandardDefinitions$AbsDefinitions.RootClass:()Lscala/reflect/generic/Symbols$AbsSymbol;
Asciz	Scala;
Asciz	InnerClasses;
Asciz	If;
Asciz	New;
Asciz	Try;
Asciz	This;
Asciz	Bind;
Asciz	Star;
Asciz	Tree;
Asciz	Ident;
Asciz	Super;
Asciz	Apply;
Asciz	Typed;
Asciz	Throw;
Asciz	Match;
Asciz	Block;
Asciz	Select;
Asciz	Return;
Asciz	Assign;
Asciz	Import;
Asciz	DefDef;
Asciz	ValDef;
Asciz	Literal;
Asciz	UnApply;
Asciz	CaseDef;
Asciz	TypeDef;
Asciz	scala/reflect/generic/Trees$RefTree;
class	scala/reflect/generic/Trees$RefTree
Asciz	RefTree;
Asciz	Function;
Asciz	LabelDef;
Asciz	Template;
Asciz	ClassDef;
Asciz	TypeApply;
Asciz	Annotated;
Asciz	ModuleDef;
Asciz	scala/reflect/generic/Trees$Modifiers;
class	scala/reflect/generic/Trees$Modifiers
Asciz	Modifiers;
Asciz	Traverser;
Asciz	ArrayValue;
Asciz	PackageDef;
Asciz	AbsTypeTree;
Asciz	Alternative;
Asciz	scala/reflect/generic/Symbols;
class	scala/reflect/generic/Symbols
Asciz	AbsSymbol;
Asciz	ApplyDynamic;
Asciz	TypeBoundsTree;
Asciz	SelectFromArray;
Asciz	AppliedTypeTree;
Asciz	CompoundTypeTree;
Asciz	TypeTreeExtractor;
Asciz	SingletonTypeTree;
Asciz	SelectFromTypeTree;
Asciz	ExistentialTypeTree;
Asciz	AbsDefinitions;
Asciz	$anonfun$traverse$7;
Asciz	$anonfun$traverse$6;
Asciz	$anonfun$traverse$5;
Asciz	$anonfun$traverse$4;
Asciz	$anonfun$traverse$3;
Asciz	$anonfun$traverse$2;
Asciz	$anonfun$traverse$1;
Asciz	$anonfun$traverseStats$1;
Asciz	$anonfun$traverseTrees$1;
Asciz	$anonfun$traverseTreess$1;
Asciz	scala/ScalaObject;
class	scala/ScalaObject

{
public final scala.reflect.generic.Universe $outer;
  Signature: Lscala/reflect/generic/Universe;

private scala.reflect.generic.Symbols$AbsSymbol currentOwner;
  Signature: Lscala/reflect/generic/Symbols$AbsSymbol;

public scala.reflect.generic.Symbols$AbsSymbol currentOwner();
  Signature: ()Lscala/reflect/generic/Symbols$AbsSymbol;
  Code:
   Stack=1, Locals=1, Args_size=1
	aload_0
	getfield	Field currentOwner:Lscala/reflect/generic/Symbols$AbsSymbol;
	areturn
  Labels:

public void currentOwner_$eq(scala.reflect.generic.Symbols$AbsSymbol);
  Signature: (Lscala/reflect/generic/Symbols$AbsSymbol;)V
  Code:
   Stack=2, Locals=2, Args_size=2
	aload_0
	aload_1
	putfield	Field currentOwner:Lscala/reflect/generic/Symbols$AbsSymbol;
	return
  Labels:

public void traverse(scala.reflect.generic.Trees$Tree);
  Signature: (Lscala/reflect/generic/Trees$Tree;)V
  Code:
   Stack=10, Locals=112, Args_size=2
	aload_1
	aload_0
	invokevirtual	Method scala$reflect$generic$Trees$Traverser$$$outer:()Lscala/reflect/generic/Universe;
	invokeinterface	InterfaceMethod scala/reflect/generic/Trees.EmptyTree:()Lscala/reflect/generic/Trees$EmptyTree$;
	astore_2
	dup
	ifnonnull	l1 // aload_2
	pop
	aload_2
	ifnull	l2 // return
	goto	l3 // aload_1
l1	aload_2
	invokevirtual	Method java/lang/Object.equals:(Ljava/lang/Object;)Z
	ifne	l2 // return
l3	aload_1
	instanceof	class scala/reflect/generic/Trees$PackageDef
	ifeq	l4 // aload_1
	aload_1
	checkcast	class scala/reflect/generic/Trees$PackageDef
	astore_3
	aload_3
	invokevirtual	Method scala/reflect/generic/Trees$PackageDef.pid:()Lscala/reflect/generic/Trees$RefTree;
	astore	4
	aload_3
	invokevirtual	Method scala/reflect/generic/Trees$PackageDef.stats:()Lscala/collection/immutable/List;
	astore	5
	aload_0
	aload	4
	checkcast	class scala/reflect/generic/Trees$Tree
	invokevirtual	Method traverse:(Lscala/reflect/generic/Trees$Tree;)V
	aload_0
	aload_1
	invokevirtual	Method scala/reflect/generic/Trees$Tree.symbol:()Lscala/reflect/generic/Symbols$AbsSymbol;
	invokevirtual	Method scala/reflect/generic/Symbols$AbsSymbol.moduleClass:()Lscala/reflect/generic/Symbols$AbsSymbol;
	new	class scala/reflect/generic/Trees$Traverser$$anonfun$traverse$1
	dup
	aload_0
	aload	5
	invokespecial	Method scala/reflect/generic/Trees$Traverser$$anonfun$traverse$1."<init>":(Lscala/reflect/generic/Trees$Traverser;Lscala/collection/immutable/List;)V
	invokevirtual	Method atOwner:(Lscala/reflect/generic/Symbols$AbsSymbol;Lscala/Function0;)V
	goto	l2 // return
l4	aload_1
	instanceof	class scala/reflect/generic/Trees$ClassDef
	ifeq	l5 // aload_1
	aload_1
	checkcast	class scala/reflect/generic/Trees$ClassDef
	astore	6
	aload	6
	invokevirtual	Method scala/reflect/generic/Trees$ClassDef.mods:()Lscala/reflect/generic/Trees$Modifiers;
	astore	7
	aload	6
	invokevirtual	Method scala/reflect/generic/Trees$ClassDef.tparams:()Lscala/collection/immutable/List;
	astore	8
	aload	6
	invokevirtual	Method scala/reflect/generic/Trees$ClassDef.impl:()Lscala/reflect/generic/Trees$Template;
	astore	9
	aload_0
	aload_1
	invokevirtual	Method scala/reflect/generic/Trees$Tree.symbol:()Lscala/reflect/generic/Symbols$AbsSymbol;
	new	class scala/reflect/generic/Trees$Traverser$$anonfun$traverse$2
	dup
	aload_0
	aload	7
	aload	8
	aload	9
	invokespecial	Method scala/reflect/generic/Trees$Traverser$$anonfun$traverse$2."<init>":(Lscala/reflect/generic/Trees$Traverser;Lscala/reflect/generic/Trees$Modifiers;Lscala/collection/immutable/List;Lscala/reflect/generic/Trees$Template;)V
	invokevirtual	Method atOwner:(Lscala/reflect/generic/Symbols$AbsSymbol;Lscala/Function0;)V
	goto	l2 // return
l5	aload_1
	instanceof	class scala/reflect/generic/Trees$ModuleDef
	ifeq	l6 // aload_1
	aload_1
	checkcast	class scala/reflect/generic/Trees$ModuleDef
	astore	10
	aload	10
	invokevirtual	Method scala/reflect/generic/Trees$ModuleDef.mods:()Lscala/reflect/generic/Trees$Modifiers;
	astore	11
	aload	10
	invokevirtual	Method scala/reflect/generic/Trees$ModuleDef.impl:()Lscala/reflect/generic/Trees$Template;
	astore	12
	aload_0
	aload_1
	invokevirtual	Method scala/reflect/generic/Trees$Tree.symbol:()Lscala/reflect/generic/Symbols$AbsSymbol;
	invokevirtual	Method scala/reflect/generic/Symbols$AbsSymbol.moduleClass:()Lscala/reflect/generic/Symbols$AbsSymbol;
	new	class scala/reflect/generic/Trees$Traverser$$anonfun$traverse$3
	dup
	aload_0
	aload	11
	aload	12
	invokespecial	Method scala/reflect/generic/Trees$Traverser$$anonfun$traverse$3."<init>":(Lscala/reflect/generic/Trees$Traverser;Lscala/reflect/generic/Trees$Modifiers;Lscala/reflect/generic/Trees$Template;)V
	invokevirtual	Method atOwner:(Lscala/reflect/generic/Symbols$AbsSymbol;Lscala/Function0;)V
	goto	l2 // return
l6	aload_1
	instanceof	class scala/reflect/generic/Trees$ValDef
	ifeq	l7 // aload_1
	aload_1
	checkcast	class scala/reflect/generic/Trees$ValDef
	astore	13
	aload	13
	invokevirtual	Method scala/reflect/generic/Trees$ValDef.mods:()Lscala/reflect/generic/Trees$Modifiers;
	astore	14
	aload	13
	invokevirtual	Method scala/reflect/generic/Trees$ValDef.tpt:()Lscala/reflect/generic/Trees$Tree;
	astore	15
	aload	13
	invokevirtual	Method scala/reflect/generic/Trees$ValDef.rhs:()Lscala/reflect/generic/Trees$Tree;
	astore	16
	aload_0
	aload_1
	invokevirtual	Method scala/reflect/generic/Trees$Tree.symbol:()Lscala/reflect/generic/Symbols$AbsSymbol;
	new	class scala/reflect/generic/Trees$Traverser$$anonfun$traverse$4
	dup
	aload_0
	aload	14
	aload	15
	aload	16
	invokespecial	Method scala/reflect/generic/Trees$Traverser$$anonfun$traverse$4."<init>":(Lscala/reflect/generic/Trees$Traverser;Lscala/reflect/generic/Trees$Modifiers;Lscala/reflect/generic/Trees$Tree;Lscala/reflect/generic/Trees$Tree;)V
	invokevirtual	Method atOwner:(Lscala/reflect/generic/Symbols$AbsSymbol;Lscala/Function0;)V
	goto	l2 // return
l7	aload_1
	instanceof	class scala/reflect/generic/Trees$DefDef
	ifeq	l8 // aload_1
	aload_1
	checkcast	class scala/reflect/generic/Trees$DefDef
	astore	17
	aload	17
	invokevirtual	Method scala/reflect/generic/Trees$DefDef.mods:()Lscala/reflect/generic/Trees$Modifiers;
	astore	18
	aload	17
	invokevirtual	Method scala/reflect/generic/Trees$DefDef.tparams:()Lscala/collection/immutable/List;
	astore	19
	aload	17
	invokevirtual	Method scala/reflect/generic/Trees$DefDef.vparamss:()Lscala/collection/immutable/List;
	astore	20
	aload	17
	invokevirtual	Method scala/reflect/generic/Trees$DefDef.tpt:()Lscala/reflect/generic/Trees$Tree;
	astore	21
	aload	17
	invokevirtual	Method scala/reflect/generic/Trees$DefDef.rhs:()Lscala/reflect/generic/Trees$Tree;
	astore	22
	aload_0
	aload_1
	invokevirtual	Method scala/reflect/generic/Trees$Tree.symbol:()Lscala/reflect/generic/Symbols$AbsSymbol;
	new	class scala/reflect/generic/Trees$Traverser$$anonfun$traverse$5
	dup
	aload_0
	aload	18
	aload	19
	aload	20
	aload	21
	aload	22
	invokespecial	Method scala/reflect/generic/Trees$Traverser$$anonfun$traverse$5."<init>":(Lscala/reflect/generic/Trees$Traverser;Lscala/reflect/generic/Trees$Modifiers;Lscala/collection/immutable/List;Lscala/collection/immutable/List;Lscala/reflect/generic/Trees$Tree;Lscala/reflect/generic/Trees$Tree;)V
	invokevirtual	Method atOwner:(Lscala/reflect/generic/Symbols$AbsSymbol;Lscala/Function0;)V
	goto	l2 // return
l8	aload_1
	instanceof	class scala/reflect/generic/Trees$TypeDef
	ifeq	l9 // aload_1
	aload_1
	checkcast	class scala/reflect/generic/Trees$TypeDef
	astore	23
	aload	23
	invokevirtual	Method scala/reflect/generic/Trees$TypeDef.mods:()Lscala/reflect/generic/Trees$Modifiers;
	astore	24
	aload	23
	invokevirtual	Method scala/reflect/generic/Trees$TypeDef.tparams:()Lscala/collection/immutable/List;
	astore	25
	aload	23
	invokevirtual	Method scala/reflect/generic/Trees$TypeDef.rhs:()Lscala/reflect/generic/Trees$Tree;
	astore	26
	aload_0
	aload_1
	invokevirtual	Method scala/reflect/generic/Trees$Tree.symbol:()Lscala/reflect/generic/Symbols$AbsSymbol;
	new	class scala/reflect/generic/Trees$Traverser$$anonfun$traverse$6
	dup
	aload_0
	aload	24
	aload	25
	aload	26
	invokespecial	Method scala/reflect/generic/Trees$Traverser$$anonfun$traverse$6."<init>":(Lscala/reflect/generic/Trees$Traverser;Lscala/reflect/generic/Trees$Modifiers;Lscala/collection/immutable/List;Lscala/reflect/generic/Trees$Tree;)V
	invokevirtual	Method atOwner:(Lscala/reflect/generic/Symbols$AbsSymbol;Lscala/Function0;)V
	goto	l2 // return
l9	aload_1
	instanceof	class scala/reflect/generic/Trees$LabelDef
	ifeq	l10 // aload_1
	aload_1
	checkcast	class scala/reflect/generic/Trees$LabelDef
	astore	27
	aload	27
	invokevirtual	Method scala/reflect/generic/Trees$LabelDef.params:()Lscala/collection/immutable/List;
	astore	28
	aload	27
	invokevirtual	Method scala/reflect/generic/Trees$LabelDef.rhs:()Lscala/reflect/generic/Trees$Tree;
	astore	29
	aload_0
	aload	28
	invokevirtual	Method traverseTrees:(Lscala/collection/immutable/List;)V
	aload_0
	aload	29
	invokevirtual	Method traverse:(Lscala/reflect/generic/Trees$Tree;)V
	goto	l2 // return
l10	aload_1
	instanceof	class scala/reflect/generic/Trees$Import
	ifeq	l11 // aload_1
	aload_1
	checkcast	class scala/reflect/generic/Trees$Import
	astore	30
	aload	30
	invokevirtual	Method scala/reflect/generic/Trees$Import.expr:()Lscala/reflect/generic/Trees$Tree;
	astore	31
	aload_0
	aload	31
	invokevirtual	Method traverse:(Lscala/reflect/generic/Trees$Tree;)V
	goto	l2 // return
l11	aload_1
	instanceof	class scala/reflect/generic/Trees$Annotated
	ifeq	l12 // aload_1
	aload_1
	checkcast	class scala/reflect/generic/Trees$Annotated
	astore	32
	aload	32
	invokevirtual	Method scala/reflect/generic/Trees$Annotated.annot:()Lscala/reflect/generic/Trees$Tree;
	astore	33
	aload	32
	invokevirtual	Method scala/reflect/generic/Trees$Annotated.arg:()Lscala/reflect/generic/Trees$Tree;
	astore	34
	aload_0
	aload	33
	invokevirtual	Method traverse:(Lscala/reflect/generic/Trees$Tree;)V
	aload_0
	aload	34
	invokevirtual	Method traverse:(Lscala/reflect/generic/Trees$Tree;)V
	goto	l2 // return
l12	aload_1
	instanceof	class scala/reflect/generic/Trees$Template
	ifeq	l13 // aload_1
	aload_1
	checkcast	class scala/reflect/generic/Trees$Template
	astore	35
	aload	35
	invokevirtual	Method scala/reflect/generic/Trees$Template.parents:()Lscala/collection/immutable/List;
	astore	36
	aload	35
	invokevirtual	Method scala/reflect/generic/Trees$Template.self:()Lscala/reflect/generic/Trees$ValDef;
	astore	37
	aload	35
	invokevirtual	Method scala/reflect/generic/Trees$Template.body:()Lscala/collection/immutable/List;
	astore	38
	aload_0
	aload	36
	invokevirtual	Method traverseTrees:(Lscala/collection/immutable/List;)V
	aload	37
	invokevirtual	Method scala/reflect/generic/Trees$ValDef.isEmpty:()Z
	ifne	l14 // aload_0
	aload_0
	aload	37
	invokevirtual	Method traverse:(Lscala/reflect/generic/Trees$Tree;)V
l14	aload_0
	aload	38
	aload_1
	invokevirtual	Method scala/reflect/generic/Trees$Tree.symbol:()Lscala/reflect/generic/Symbols$AbsSymbol;
	invokevirtual	Method traverseStats:(Lscala/collection/immutable/List;Lscala/reflect/generic/Symbols$AbsSymbol;)V
	goto	l2 // return
l13	aload_1
	instanceof	class scala/reflect/generic/Trees$Block
	ifeq	l15 // aload_1
	aload_1
	checkcast	class scala/reflect/generic/Trees$Block
	astore	39
	aload	39
	invokevirtual	Method scala/reflect/generic/Trees$Block.stats:()Lscala/collection/immutable/List;
	astore	40
	aload	39
	invokevirtual	Method scala/reflect/generic/Trees$Block.expr:()Lscala/reflect/generic/Trees$Tree;
	astore	41
	aload_0
	aload	40
	invokevirtual	Method traverseTrees:(Lscala/collection/immutable/List;)V
	aload_0
	aload	41
	invokevirtual	Method traverse:(Lscala/reflect/generic/Trees$Tree;)V
	goto	l2 // return
l15	aload_1
	instanceof	class scala/reflect/generic/Trees$CaseDef
	ifeq	l16 // aload_1
	aload_1
	checkcast	class scala/reflect/generic/Trees$CaseDef
	astore	42
	aload	42
	invokevirtual	Method scala/reflect/generic/Trees$CaseDef.pat:()Lscala/reflect/generic/Trees$Tree;
	astore	43
	aload	42
	invokevirtual	Method scala/reflect/generic/Trees$CaseDef.guard:()Lscala/reflect/generic/Trees$Tree;
	astore	44
	aload	42
	invokevirtual	Method scala/reflect/generic/Trees$CaseDef.body:()Lscala/reflect/generic/Trees$Tree;
	astore	45
	aload_0
	aload	43
	invokevirtual	Method traverse:(Lscala/reflect/generic/Trees$Tree;)V
	aload_0
	aload	44
	invokevirtual	Method traverse:(Lscala/reflect/generic/Trees$Tree;)V
	aload_0
	aload	45
	invokevirtual	Method traverse:(Lscala/reflect/generic/Trees$Tree;)V
	goto	l2 // return
l16	aload_1
	instanceof	class scala/reflect/generic/Trees$Alternative
	ifeq	l17 // aload_1
	aload_1
	checkcast	class scala/reflect/generic/Trees$Alternative
	astore	46
	aload	46
	invokevirtual	Method scala/reflect/generic/Trees$Alternative.trees:()Lscala/collection/immutable/List;
	astore	47
	aload_0
	aload	47
	invokevirtual	Method traverseTrees:(Lscala/collection/immutable/List;)V
	goto	l2 // return
l17	aload_1
	instanceof	class scala/reflect/generic/Trees$Star
	ifeq	l18 // aload_1
	aload_1
	checkcast	class scala/reflect/generic/Trees$Star
	astore	48
	aload	48
	invokevirtual	Method scala/reflect/generic/Trees$Star.elem:()Lscala/reflect/generic/Trees$Tree;
	astore	49
	aload_0
	aload	49
	invokevirtual	Method traverse:(Lscala/reflect/generic/Trees$Tree;)V
	goto	l2 // return
l18	aload_1
	instanceof	class scala/reflect/generic/Trees$Bind
	ifeq	l19 // aload_1
	aload_1
	checkcast	class scala/reflect/generic/Trees$Bind
	astore	50
	aload	50
	invokevirtual	Method scala/reflect/generic/Trees$Bind.body:()Lscala/reflect/generic/Trees$Tree;
	astore	51
	aload_0
	aload	51
	invokevirtual	Method traverse:(Lscala/reflect/generic/Trees$Tree;)V
	goto	l2 // return
l19	aload_1
	instanceof	class scala/reflect/generic/Trees$UnApply
	ifeq	l20 // aload_1
	aload_1
	checkcast	class scala/reflect/generic/Trees$UnApply
	astore	52
	aload	52
	invokevirtual	Method scala/reflect/generic/Trees$UnApply.fun:()Lscala/reflect/generic/Trees$Tree;
	astore	53
	aload	52
	invokevirtual	Method scala/reflect/generic/Trees$UnApply.args:()Lscala/collection/immutable/List;
	astore	54
	aload_0
	aload	53
	invokevirtual	Method traverse:(Lscala/reflect/generic/Trees$Tree;)V
	aload_0
	aload	54
	invokevirtual	Method traverseTrees:(Lscala/collection/immutable/List;)V
	goto	l2 // return
l20	aload_1
	instanceof	class scala/reflect/generic/Trees$ArrayValue
	ifeq	l21 // aload_1
	aload_1
	checkcast	class scala/reflect/generic/Trees$ArrayValue
	astore	55
	aload	55
	invokevirtual	Method scala/reflect/generic/Trees$ArrayValue.elemtpt:()Lscala/reflect/generic/Trees$Tree;
	astore	56
	aload	55
	invokevirtual	Method scala/reflect/generic/Trees$ArrayValue.elems:()Lscala/collection/immutable/List;
	astore	57
	aload_0
	aload	56
	invokevirtual	Method traverse:(Lscala/reflect/generic/Trees$Tree;)V
	aload_0
	aload	57
	invokevirtual	Method traverseTrees:(Lscala/collection/immutable/List;)V
	goto	l2 // return
l21	aload_1
	instanceof	class scala/reflect/generic/Trees$Function
	ifeq	l22 // aload_1
	aload_1
	checkcast	class scala/reflect/generic/Trees$Function
	astore	58
	aload	58
	invokevirtual	Method scala/reflect/generic/Trees$Function.vparams:()Lscala/collection/immutable/List;
	astore	59
	aload	58
	invokevirtual	Method scala/reflect/generic/Trees$Function.body:()Lscala/reflect/generic/Trees$Tree;
	astore	60
	aload_0
	aload_1
	invokevirtual	Method scala/reflect/generic/Trees$Tree.symbol:()Lscala/reflect/generic/Symbols$AbsSymbol;
	new	class scala/reflect/generic/Trees$Traverser$$anonfun$traverse$7
	dup
	aload_0
	aload	59
	aload	60
	invokespecial	Method scala/reflect/generic/Trees$Traverser$$anonfun$traverse$7."<init>":(Lscala/reflect/generic/Trees$Traverser;Lscala/collection/immutable/List;Lscala/reflect/generic/Trees$Tree;)V
	invokevirtual	Method atOwner:(Lscala/reflect/generic/Symbols$AbsSymbol;Lscala/Function0;)V
	goto	l2 // return
l22	aload_1
	instanceof	class scala/reflect/generic/Trees$Assign
	ifeq	l23 // aload_1
	aload_1
	checkcast	class scala/reflect/generic/Trees$Assign
	astore	61
	aload	61
	invokevirtual	Method scala/reflect/generic/Trees$Assign.lhs:()Lscala/reflect/generic/Trees$Tree;
	astore	62
	aload	61
	invokevirtual	Method scala/reflect/generic/Trees$Assign.rhs:()Lscala/reflect/generic/Trees$Tree;
	astore	63
	aload_0
	aload	62
	invokevirtual	Method traverse:(Lscala/reflect/generic/Trees$Tree;)V
	aload_0
	aload	63
	invokevirtual	Method traverse:(Lscala/reflect/generic/Trees$Tree;)V
	goto	l2 // return
l23	aload_1
	instanceof	class scala/reflect/generic/Trees$If
	ifeq	l24 // aload_1
	aload_1
	checkcast	class scala/reflect/generic/Trees$If
	astore	64
	aload	64
	invokevirtual	Method scala/reflect/generic/Trees$If.cond:()Lscala/reflect/generic/Trees$Tree;
	astore	65
	aload	64
	invokevirtual	Method scala/reflect/generic/Trees$If.thenp:()Lscala/reflect/generic/Trees$Tree;
	astore	66
	aload	64
	invokevirtual	Method scala/reflect/generic/Trees$If.elsep:()Lscala/reflect/generic/Trees$Tree;
	astore	67
	aload_0
	aload	65
	invokevirtual	Method traverse:(Lscala/reflect/generic/Trees$Tree;)V
	aload_0
	aload	66
	invokevirtual	Method traverse:(Lscala/reflect/generic/Trees$Tree;)V
	aload_0
	aload	67
	invokevirtual	Method traverse:(Lscala/reflect/generic/Trees$Tree;)V
	goto	l2 // return
l24	aload_1
	instanceof	class scala/reflect/generic/Trees$Match
	ifeq	l25 // aload_1
	aload_1
	checkcast	class scala/reflect/generic/Trees$Match
	astore	68
	aload	68
	invokevirtual	Method scala/reflect/generic/Trees$Match.selector:()Lscala/reflect/generic/Trees$Tree;
	astore	69
	aload	68
	invokevirtual	Method scala/reflect/generic/Trees$Match.cases:()Lscala/collection/immutable/List;
	astore	70
	aload_0
	aload	69
	invokevirtual	Method traverse:(Lscala/reflect/generic/Trees$Tree;)V
	aload_0
	aload	70
	invokevirtual	Method traverseTrees:(Lscala/collection/immutable/List;)V
	goto	l2 // return
l25	aload_1
	instanceof	class scala/reflect/generic/Trees$Return
	ifeq	l26 // aload_1
	aload_1
	checkcast	class scala/reflect/generic/Trees$Return
	astore	71
	aload	71
	invokevirtual	Method scala/reflect/generic/Trees$Return.expr:()Lscala/reflect/generic/Trees$Tree;
	astore	72
	aload_0
	aload	72
	invokevirtual	Method traverse:(Lscala/reflect/generic/Trees$Tree;)V
	goto	l2 // return
l26	aload_1
	instanceof	class scala/reflect/generic/Trees$Try
	ifeq	l27 // aload_1
	aload_1
	checkcast	class scala/reflect/generic/Trees$Try
	astore	73
	aload	73
	invokevirtual	Method scala/reflect/generic/Trees$Try.block:()Lscala/reflect/generic/Trees$Tree;
	astore	74
	aload	73
	invokevirtual	Method scala/reflect/generic/Trees$Try.catches:()Lscala/collection/immutable/List;
	astore	75
	aload	73
	invokevirtual	Method scala/reflect/generic/Trees$Try.finalizer:()Lscala/reflect/generic/Trees$Tree;
	astore	76
	aload_0
	aload	74
	invokevirtual	Method traverse:(Lscala/reflect/generic/Trees$Tree;)V
	aload_0
	aload	75
	invokevirtual	Method traverseTrees:(Lscala/collection/immutable/List;)V
	aload_0
	aload	76
	invokevirtual	Method traverse:(Lscala/reflect/generic/Trees$Tree;)V
	goto	l2 // return
l27	aload_1
	instanceof	class scala/reflect/generic/Trees$Throw
	ifeq	l28 // aload_1
	aload_1
	checkcast	class scala/reflect/generic/Trees$Throw
	astore	77
	aload	77
	invokevirtual	Method scala/reflect/generic/Trees$Throw.expr:()Lscala/reflect/generic/Trees$Tree;
	astore	78
	aload_0
	aload	78
	invokevirtual	Method traverse:(Lscala/reflect/generic/Trees$Tree;)V
	goto	l2 // return
l28	aload_1
	instanceof	class scala/reflect/generic/Trees$New
	ifeq	l29 // aload_1
	aload_1
	checkcast	class scala/reflect/generic/Trees$New
	astore	79
	aload	79
	invokevirtual	Method scala/reflect/generic/Trees$New.tpt:()Lscala/reflect/generic/Trees$Tree;
	astore	80
	aload_0
	aload	80
	invokevirtual	Method traverse:(Lscala/reflect/generic/Trees$Tree;)V
	goto	l2 // return
l29	aload_1
	instanceof	class scala/reflect/generic/Trees$Typed
	ifeq	l30 // aload_1
	aload_1
	checkcast	class scala/reflect/generic/Trees$Typed
	astore	81
	aload	81
	invokevirtual	Method scala/reflect/generic/Trees$Typed.expr:()Lscala/reflect/generic/Trees$Tree;
	astore	82
	aload	81
	invokevirtual	Method scala/reflect/generic/Trees$Typed.tpt:()Lscala/reflect/generic/Trees$Tree;
	astore	83
	aload_0
	aload	82
	invokevirtual	Method traverse:(Lscala/reflect/generic/Trees$Tree;)V
	aload_0
	aload	83
	invokevirtual	Method traverse:(Lscala/reflect/generic/Trees$Tree;)V
	goto	l2 // return
l30	aload_1
	instanceof	class scala/reflect/generic/Trees$TypeApply
	ifeq	l31 // aload_1
	aload_1
	checkcast	class scala/reflect/generic/Trees$TypeApply
	astore	84
	aload	84
	invokevirtual	Method scala/reflect/generic/Trees$TypeApply.fun:()Lscala/reflect/generic/Trees$Tree;
	astore	85
	aload	84
	invokevirtual	Method scala/reflect/generic/Trees$TypeApply.args:()Lscala/collection/immutable/List;
	astore	86
	aload_0
	aload	85
	invokevirtual	Method traverse:(Lscala/reflect/generic/Trees$Tree;)V
	aload_0
	aload	86
	invokevirtual	Method traverseTrees:(Lscala/collection/immutable/List;)V
	goto	l2 // return
l31	aload_1
	instanceof	class scala/reflect/generic/Trees$Apply
	ifeq	l32 // aload_1
	aload_1
	checkcast	class scala/reflect/generic/Trees$Apply
	astore	87
	aload	87
	invokevirtual	Method scala/reflect/generic/Trees$Apply.fun:()Lscala/reflect/generic/Trees$Tree;
	astore	88
	aload	87
	invokevirtual	Method scala/reflect/generic/Trees$Apply.args:()Lscala/collection/immutable/List;
	astore	89
	aload_0
	aload	88
	invokevirtual	Method traverse:(Lscala/reflect/generic/Trees$Tree;)V
	aload_0
	aload	89
	invokevirtual	Method traverseTrees:(Lscala/collection/immutable/List;)V
	goto	l2 // return
l32	aload_1
	instanceof	class scala/reflect/generic/Trees$ApplyDynamic
	ifeq	l33 // aload_1
	aload_1
	checkcast	class scala/reflect/generic/Trees$ApplyDynamic
	astore	90
	aload	90
	invokevirtual	Method scala/reflect/generic/Trees$ApplyDynamic.qual:()Lscala/reflect/generic/Trees$Tree;
	astore	91
	aload	90
	invokevirtual	Method scala/reflect/generic/Trees$ApplyDynamic.args:()Lscala/collection/immutable/List;
	astore	92
	aload_0
	aload	91
	invokevirtual	Method traverse:(Lscala/reflect/generic/Trees$Tree;)V
	aload_0
	aload	92
	invokevirtual	Method traverseTrees:(Lscala/collection/immutable/List;)V
	goto	l2 // return
l33	aload_1
	instanceof	class scala/reflect/generic/Trees$Super
	ifne	l2 // return
	aload_1
	instanceof	class scala/reflect/generic/Trees$This
	ifne	l2 // return
	aload_1
	instanceof	class scala/reflect/generic/Trees$Select
	ifeq	l34 // aload_1
	aload_1
	checkcast	class scala/reflect/generic/Trees$Select
	astore	93
	aload	93
	invokevirtual	Method scala/reflect/generic/Trees$Select.qualifier:()Lscala/reflect/generic/Trees$Tree;
	astore	94
	aload_0
	aload	94
	invokevirtual	Method traverse:(Lscala/reflect/generic/Trees$Tree;)V
	goto	l2 // return
l34	aload_1
	instanceof	class scala/reflect/generic/Trees$Ident
	ifne	l2 // return
	aload_1
	instanceof	class scala/reflect/generic/Trees$Literal
	ifne	l2 // return
	aload_1
	instanceof	class scala/reflect/generic/Trees$AbsTypeTree
	ifeq	l35 // aload_1
	aload_0
	invokevirtual	Method scala$reflect$generic$Trees$Traverser$$$outer:()Lscala/reflect/generic/Universe;
	invokeinterface	InterfaceMethod scala/reflect/generic/Trees.TypeTree:()Lscala/reflect/generic/Trees$TypeTreeExtractor;
	aload_1
	checkcast	class scala/reflect/generic/Trees$AbsTypeTree
	invokevirtual	Method scala/reflect/generic/Trees$TypeTreeExtractor.unapply:(Lscala/reflect/generic/Trees$AbsTypeTree;)Z
	ifne	l2 // return
	new	class scala/MatchError
	dup
	aload_1
	invokevirtual	Method scala/reflect/generic/Trees$Tree.toString:()Ljava/lang/String;
	invokespecial	Method scala/MatchError."<init>":(Ljava/lang/String;)V
	athrow
l35	aload_1
	instanceof	class scala/reflect/generic/Trees$SingletonTypeTree
	ifeq	l36 // aload_1
	aload_1
	checkcast	class scala/reflect/generic/Trees$SingletonTypeTree
	astore	95
	aload	95
	invokevirtual	Method scala/reflect/generic/Trees$SingletonTypeTree.ref:()Lscala/reflect/generic/Trees$Tree;
	astore	96
	aload_0
	aload	96
	invokevirtual	Method traverse:(Lscala/reflect/generic/Trees$Tree;)V
	goto	l2 // return
l36	aload_1
	instanceof	class scala/reflect/generic/Trees$SelectFromTypeTree
	ifeq	l37 // aload_1
	aload_1
	checkcast	class scala/reflect/generic/Trees$SelectFromTypeTree
	astore	97
	aload	97
	invokevirtual	Method scala/reflect/generic/Trees$SelectFromTypeTree.qualifier:()Lscala/reflect/generic/Trees$Tree;
	astore	98
	aload_0
	aload	98
	invokevirtual	Method traverse:(Lscala/reflect/generic/Trees$Tree;)V
	goto	l2 // return
l37	aload_1
	instanceof	class scala/reflect/generic/Trees$CompoundTypeTree
	ifeq	l38 // aload_1
	aload_1
	checkcast	class scala/reflect/generic/Trees$CompoundTypeTree
	astore	99
	aload	99
	invokevirtual	Method scala/reflect/generic/Trees$CompoundTypeTree.templ:()Lscala/reflect/generic/Trees$Template;
	astore	100
	aload_0
	aload	100
	invokevirtual	Method traverse:(Lscala/reflect/generic/Trees$Tree;)V
	goto	l2 // return
l38	aload_1
	instanceof	class scala/reflect/generic/Trees$AppliedTypeTree
	ifeq	l39 // aload_1
	aload_1
	checkcast	class scala/reflect/generic/Trees$AppliedTypeTree
	astore	101
	aload	101
	invokevirtual	Method scala/reflect/generic/Trees$AppliedTypeTree.tpt:()Lscala/reflect/generic/Trees$Tree;
	astore	102
	aload	101
	invokevirtual	Method scala/reflect/generic/Trees$AppliedTypeTree.args:()Lscala/collection/immutable/List;
	astore	103
	aload_0
	aload	102
	invokevirtual	Method traverse:(Lscala/reflect/generic/Trees$Tree;)V
	aload_0
	aload	103
	invokevirtual	Method traverseTrees:(Lscala/collection/immutable/List;)V
	goto	l2 // return
l39	aload_1
	instanceof	class scala/reflect/generic/Trees$TypeBoundsTree
	ifeq	l40 // aload_1
	aload_1
	checkcast	class scala/reflect/generic/Trees$TypeBoundsTree
	astore	104
	aload	104
	invokevirtual	Method scala/reflect/generic/Trees$TypeBoundsTree.lo:()Lscala/reflect/generic/Trees$Tree;
	astore	105
	aload	104
	invokevirtual	Method scala/reflect/generic/Trees$TypeBoundsTree.hi:()Lscala/reflect/generic/Trees$Tree;
	astore	106
	aload_0
	aload	105
	invokevirtual	Method traverse:(Lscala/reflect/generic/Trees$Tree;)V
	aload_0
	aload	106
	invokevirtual	Method traverse:(Lscala/reflect/generic/Trees$Tree;)V
	goto	l2 // return
l40	aload_1
	instanceof	class scala/reflect/generic/Trees$ExistentialTypeTree
	ifeq	l41 // aload_1
	aload_1
	checkcast	class scala/reflect/generic/Trees$ExistentialTypeTree
	astore	107
	aload	107
	invokevirtual	Method scala/reflect/generic/Trees$ExistentialTypeTree.tpt:()Lscala/reflect/generic/Trees$Tree;
	astore	108
	aload	107
	invokevirtual	Method scala/reflect/generic/Trees$ExistentialTypeTree.whereClauses:()Lscala/collection/immutable/List;
	astore	109
	aload_0
	aload	108
	invokevirtual	Method traverse:(Lscala/reflect/generic/Trees$Tree;)V
	aload_0
	aload	109
	invokevirtual	Method traverseTrees:(Lscala/collection/immutable/List;)V
	goto	l2 // return
l41	aload_1
	instanceof	class scala/reflect/generic/Trees$SelectFromArray
	ifeq	l42 // new
	aload_1
	checkcast	class scala/reflect/generic/Trees$SelectFromArray
	astore	110
	aload	110
	invokevirtual	Method scala/reflect/generic/Trees$SelectFromArray.qualifier:()Lscala/reflect/generic/Trees$Tree;
	astore	111
	aload_0
	aload	111
	invokevirtual	Method traverse:(Lscala/reflect/generic/Trees$Tree;)V
l2	return
l42	new	class scala/MatchError
	dup
	aload_1
	invokevirtual	Method scala/reflect/generic/Trees$Tree.toString:()Ljava/lang/String;
	invokespecial	Method scala/MatchError."<init>":(Ljava/lang/String;)V
	athrow
  Labels:
   	l1 = 23 // aload_2
   	l3 = 30 // aload_1
   	l4 = 87 // aload_1
   	l5 = 146 // aload_1
   	l6 = 199 // aload_1
   	l7 = 258 // aload_1
   	l8 = 335 // aload_1
   	l9 = 394 // aload_1
   	l10 = 436 // aload_1
   	l11 = 465 // aload_1
   	l12 = 507 // aload_1
   	l14 = 561 // aload_0
   	l13 = 574 // aload_1
   	l15 = 616 // aload_1
   	l16 = 671 // aload_1
   	l17 = 700 // aload_1
   	l18 = 729 // aload_1
   	l19 = 758 // aload_1
   	l20 = 800 // aload_1
   	l21 = 842 // aload_1
   	l22 = 892 // aload_1
   	l23 = 934 // aload_1
   	l24 = 989 // aload_1
   	l25 = 1031 // aload_1
   	l26 = 1060 // aload_1
   	l27 = 1115 // aload_1
   	l28 = 1144 // aload_1
   	l29 = 1173 // aload_1
   	l30 = 1215 // aload_1
   	l31 = 1257 // aload_1
   	l32 = 1299 // aload_1
   	l33 = 1341 // aload_1
   	l34 = 1384 // aload_1
   	l35 = 1436 // aload_1
   	l36 = 1465 // aload_1
   	l37 = 1494 // aload_1
   	l38 = 1523 // aload_1
   	l39 = 1565 // aload_1
   	l40 = 1607 // aload_1
   	l41 = 1649 // aload_1
   	l2 = 1675 // return
   	l42 = 1676 // new
  LocalVariableTable: 
   Start  Length  Slot  Name   Signature
   0      1688      0    this       Lscala/reflect/generic/Trees$Traverser;
   0      1688      1    tree       Lscala/reflect/generic/Trees$Tree;
   42      42      3    temp85       Lscala/reflect/generic/Trees$PackageDef;
   48      36      4    temp86       Lscala/reflect/generic/Trees$RefTree;
   54      30      5    temp87       Lscala/collection/immutable/List;
   100      43      6    temp88       Lscala/reflect/generic/Trees$ClassDef;
   107      36      7    temp89       Lscala/reflect/generic/Trees$Modifiers;
   114      29      8    temp91       Lscala/collection/immutable/List;
   121      22      9    temp92       Lscala/reflect/generic/Trees$Template;
   159      37      10    temp93       Lscala/reflect/generic/Trees$ModuleDef;
   166      30      11    temp94       Lscala/reflect/generic/Trees$Modifiers;
   173      23      12    temp96       Lscala/reflect/generic/Trees$Template;
   212      43      13    temp97       Lscala/reflect/generic/Trees$ValDef;
   219      36      14    temp98       Lscala/reflect/generic/Trees$Modifiers;
   226      29      15    temp100       Lscala/reflect/generic/Trees$Tree;
   233      22      16    temp101       Lscala/reflect/generic/Trees$Tree;
   271      61      17    temp102       Lscala/reflect/generic/Trees$DefDef;
   278      54      18    temp103       Lscala/reflect/generic/Trees$Modifiers;
   285      47      19    temp105       Lscala/collection/immutable/List;
   292      40      20    temp106       Lscala/collection/immutable/List;
   299      33      21    temp107       Lscala/reflect/generic/Trees$Tree;
   306      26      22    temp108       Lscala/reflect/generic/Trees$Tree;
   348      43      23    temp109       Lscala/reflect/generic/Trees$TypeDef;
   355      36      24    temp110       Lscala/reflect/generic/Trees$Modifiers;
   362      29      25    temp112       Lscala/collection/immutable/List;
   369      22      26    temp113       Lscala/reflect/generic/Trees$Tree;
   407      26      27    temp114       Lscala/reflect/generic/Trees$LabelDef;
   414      19      28    temp116       Lscala/collection/immutable/List;
   421      12      29    temp117       Lscala/reflect/generic/Trees$Tree;
   449      13      30    temp118       Lscala/reflect/generic/Trees$Import;
   456      6      31    temp119       Lscala/reflect/generic/Trees$Tree;
   478      26      32    temp121       Lscala/reflect/generic/Trees$Annotated;
   485      19      33    temp122       Lscala/reflect/generic/Trees$Tree;
   492      12      34    temp123       Lscala/reflect/generic/Trees$Tree;
   520      51      35    temp124       Lscala/reflect/generic/Trees$Template;
   527      44      36    temp125       Lscala/collection/immutable/List;
   534      37      37    temp126       Lscala/reflect/generic/Trees$ValDef;
   541      30      38    temp127       Lscala/collection/immutable/List;
   587      26      39    temp128       Lscala/reflect/generic/Trees$Block;
   594      19      40    temp129       Lscala/collection/immutable/List;
   601      12      41    temp130       Lscala/reflect/generic/Trees$Tree;
   629      39      42    temp131       Lscala/reflect/generic/Trees$CaseDef;
   636      32      43    temp132       Lscala/reflect/generic/Trees$Tree;
   643      25      44    temp133       Lscala/reflect/generic/Trees$Tree;
   650      18      45    temp134       Lscala/reflect/generic/Trees$Tree;
   684      13      46    temp135       Lscala/reflect/generic/Trees$Alternative;
   691      6      47    temp136       Lscala/collection/immutable/List;
   713      13      48    temp137       Lscala/reflect/generic/Trees$Star;
   720      6      49    temp138       Lscala/reflect/generic/Trees$Tree;
   742      13      50    temp139       Lscala/reflect/generic/Trees$Bind;
   749      6      51    temp141       Lscala/reflect/generic/Trees$Tree;
   771      26      52    temp142       Lscala/reflect/generic/Trees$UnApply;
   778      19      53    temp143       Lscala/reflect/generic/Trees$Tree;
   785      12      54    temp144       Lscala/collection/immutable/List;
   813      26      55    temp145       Lscala/reflect/generic/Trees$ArrayValue;
   820      19      56    temp146       Lscala/reflect/generic/Trees$Tree;
   827      12      57    temp147       Lscala/collection/immutable/List;
   855      34      58    temp148       Lscala/reflect/generic/Trees$Function;
   862      27      59    temp149       Lscala/collection/immutable/List;
   869      20      60    temp150       Lscala/reflect/generic/Trees$Tree;
   905      26      61    temp151       Lscala/reflect/generic/Trees$Assign;
   912      19      62    temp152       Lscala/reflect/generic/Trees$Tree;
   919      12      63    temp153       Lscala/reflect/generic/Trees$Tree;
   947      39      64    temp154       Lscala/reflect/generic/Trees$If;
   954      32      65    temp155       Lscala/reflect/generic/Trees$Tree;
   961      25      66    temp156       Lscala/reflect/generic/Trees$Tree;
   968      18      67    temp157       Lscala/reflect/generic/Trees$Tree;
   1002      26      68    temp158       Lscala/reflect/generic/Trees$Match;
   1009      19      69    temp159       Lscala/reflect/generic/Trees$Tree;
   1016      12      70    temp160       Lscala/collection/immutable/List;
   1044      13      71    temp161       Lscala/reflect/generic/Trees$Return;
   1051      6      72    temp162       Lscala/reflect/generic/Trees$Tree;
   1073      39      73    temp163       Lscala/reflect/generic/Trees$Try;
   1080      32      74    temp164       Lscala/reflect/generic/Trees$Tree;
   1087      25      75    temp165       Lscala/collection/immutable/List;
   1094      18      76    temp166       Lscala/reflect/generic/Trees$Tree;
   1128      13      77    temp167       Lscala/reflect/generic/Trees$Throw;
   1135      6      78    temp168       Lscala/reflect/generic/Trees$Tree;
   1157      13      79    temp169       Lscala/reflect/generic/Trees$New;
   1164      6      80    temp170       Lscala/reflect/generic/Trees$Tree;
   1186      26      81    temp171       Lscala/reflect/generic/Trees$Typed;
   1193      19      82    temp172       Lscala/reflect/generic/Trees$Tree;
   1200      12      83    temp173       Lscala/reflect/generic/Trees$Tree;
   1228      26      84    temp174       Lscala/reflect/generic/Trees$TypeApply;
   1235      19      85    temp175       Lscala/reflect/generic/Trees$Tree;
   1242      12      86    temp176       Lscala/collection/immutable/List;
   1270      26      87    temp177       Lscala/reflect/generic/Trees$Apply;
   1277      19      88    temp178       Lscala/reflect/generic/Trees$Tree;
   1284      12      89    temp179       Lscala/collection/immutable/List;
   1312      26      90    temp180       Lscala/reflect/generic/Trees$ApplyDynamic;
   1319      19      91    temp181       Lscala/reflect/generic/Trees$Tree;
   1326      12      92    temp182       Lscala/collection/immutable/List;
   1368      13      93    temp188       Lscala/reflect/generic/Trees$Select;
   1375      6      94    temp189       Lscala/reflect/generic/Trees$Tree;
   1449      13      95    temp197       Lscala/reflect/generic/Trees$SingletonTypeTree;
   1456      6      96    temp198       Lscala/reflect/generic/Trees$Tree;
   1478      13      97    temp199       Lscala/reflect/generic/Trees$SelectFromTypeTree;
   1485      6      98    temp200       Lscala/reflect/generic/Trees$Tree;
   1507      13      99    temp202       Lscala/reflect/generic/Trees$CompoundTypeTree;
   1514      6      100    temp203       Lscala/reflect/generic/Trees$Template;
   1536      26      101    temp204       Lscala/reflect/generic/Trees$AppliedTypeTree;
   1543      19      102    temp205       Lscala/reflect/generic/Trees$Tree;
   1550      12      103    temp206       Lscala/collection/immutable/List;
   1578      26      104    temp207       Lscala/reflect/generic/Trees$TypeBoundsTree;
   1585      19      105    temp208       Lscala/reflect/generic/Trees$Tree;
   1592      12      106    temp209       Lscala/reflect/generic/Trees$Tree;
   1620      26      107    temp210       Lscala/reflect/generic/Trees$ExistentialTypeTree;
   1627      19      108    temp211       Lscala/reflect/generic/Trees$Tree;
   1634      12      109    temp212       Lscala/collection/immutable/List;
   1662      13      110    temp213       Lscala/reflect/generic/Trees$SelectFromArray;
   1669      6      111    temp214       Lscala/reflect/generic/Trees$Tree;


public void traverseTrees(scala.collection.immutable.List);
  Signature: (Lscala/collection/immutable/List;)V
  Code:
   Stack=4, Locals=2, Args_size=2
	aload_1
	new	class scala/reflect/generic/Trees$Traverser$$anonfun$traverseTrees$1
	dup
	aload_0
	invokespecial	Method scala/reflect/generic/Trees$Traverser$$anonfun$traverseTrees$1."<init>":(Lscala/reflect/generic/Trees$Traverser;)V
	invokeinterface	InterfaceMethod scala/collection/LinearSeqLike.foreach:(Lscala/Function1;)V
	return
  Labels:
  LocalVariableTable: 
   Start  Length  Slot  Name   Signature
   0      15      0    this       Lscala/reflect/generic/Trees$Traverser;
   0      15      1    trees       Lscala/collection/immutable/List;

  Signature: length = 0x2
   02 0D 

public void traverseTreess(scala.collection.immutable.List);
  Signature: (Lscala/collection/immutable/List;)V
  Code:
   Stack=4, Locals=2, Args_size=2
	aload_1
	new	class scala/reflect/generic/Trees$Traverser$$anonfun$traverseTreess$1
	dup
	aload_0
	invokespecial	Method scala/reflect/generic/Trees$Traverser$$anonfun$traverseTreess$1."<init>":(Lscala/reflect/generic/Trees$Traverser;)V
	invokeinterface	InterfaceMethod scala/collection/LinearSeqLike.foreach:(Lscala/Function1;)V
	return
  Labels:
  LocalVariableTable: 
   Start  Length  Slot  Name   Signature
   0      15      0    this       Lscala/reflect/generic/Trees$Traverser;
   0      15      1    treess       Lscala/collection/immutable/List;

  Signature: length = 0x2
   02 14 

public void traverseStats(scala.collection.immutable.List, scala.reflect.generic.Symbols$AbsSymbol);
  Signature: (Lscala/collection/immutable/List;Lscala/reflect/generic/Symbols$AbsSymbol;)V
  Code:
   Stack=5, Locals=3, Args_size=3
	aload_1
	new	class scala/reflect/generic/Trees$Traverser$$anonfun$traverseStats$1
	dup
	aload_0
	aload_2
	invokespecial	Method scala/reflect/generic/Trees$Traverser$$anonfun$traverseStats$1."<init>":(Lscala/reflect/generic/Trees$Traverser;Lscala/reflect/generic/Symbols$AbsSymbol;)V
	invokeinterface	InterfaceMethod scala/collection/LinearSeqLike.foreach:(Lscala/Function1;)V
	return
  Labels:
  LocalVariableTable: 
   Start  Length  Slot  Name   Signature
   0      16      0    this       Lscala/reflect/generic/Trees$Traverser;
   0      16      1    stats       Lscala/collection/immutable/List;
   0      16      2    exprOwner$1       Lscala/reflect/generic/Symbols$AbsSymbol;

  Signature: length = 0x2
   02 1B 

public void atOwner(scala.reflect.generic.Symbols$AbsSymbol, scala.Function0);
  Signature: (Lscala/reflect/generic/Symbols$AbsSymbol;Lscala/Function0;)V
  Code:
   Stack=2, Locals=4, Args_size=3
	aload_0
	invokevirtual	Method currentOwner:()Lscala/reflect/generic/Symbols$AbsSymbol;
	astore_3
	aload_0
	aload_1
	invokevirtual	Method currentOwner_$eq:(Lscala/reflect/generic/Symbols$AbsSymbol;)V
	aload_2
	invokeinterface	InterfaceMethod scala/Function0.apply:()Ljava/lang/Object;
	pop
	aload_0
	aload_3
	invokevirtual	Method currentOwner_$eq:(Lscala/reflect/generic/Symbols$AbsSymbol;)V
	return
  Labels:
  LocalVariableTable: 
   Start  Length  Slot  Name   Signature
   0      23      0    this       Lscala/reflect/generic/Trees$Traverser;
   0      23      1    owner       Lscala/reflect/generic/Symbols$AbsSymbol;
   0      23      2    traverse       Lscala/Function0;
   5      17      3    prevOwner       Lscala/reflect/generic/Symbols$AbsSymbol;

  Signature: length = 0x2
   02 29 

public scala.reflect.generic.Universe scala$reflect$generic$Trees$Traverser$$$outer();
  Signature: ()Lscala/reflect/generic/Universe;
  Code:
   Stack=1, Locals=1, Args_size=1
	aload_0
	getfield	Field $outer:Lscala/reflect/generic/Universe;
	areturn
  Labels:

public scala.reflect.generic.Trees$Traverser(scala.reflect.generic.Universe);
  Signature: (Lscala/reflect/generic/Universe;)V
  Code:
   Stack=2, Locals=2, Args_size=2
	aload_1
	ifnonnull	l1 // aload_0
	new	class java/lang/NullPointerException
	dup
	invokespecial	Method java/lang/NullPointerException."<init>":()V
	athrow
l1	aload_0
	aload_1
	putfield	Field $outer:Lscala/reflect/generic/Universe;
	aload_0
	invokespecial	Method java/lang/Object."<init>":()V
	aload_0
	aload_1
	invokeinterface	InterfaceMethod scala/reflect/generic/StandardDefinitions.definitions:()Lscala/reflect/generic/StandardDefinitions$AbsDefinitions;
	invokevirtual	Method scala/reflect/generic/StandardDefinitions$AbsDefinitions.RootClass:()Lscala/reflect/generic/Symbols$AbsSymbol;
	putfield	Field currentOwner:Lscala/reflect/generic/Symbols$AbsSymbol;
	return
  Labels:
   	l1 = 12 // aload_0
  LocalVariableTable: 
   Start  Length  Slot  Name   Signature
   0      35      0    this       Lscala/reflect/generic/Trees$Traverser;
   0      35      1    $outer       Lscala/reflect/generic/Universe;


}

