Compiled from "Trees.scala"
public class scala.reflect.generic.Trees$Alternative extends scala.reflect.generic.Trees$Tree implements scala.reflect.generic.Trees$TermTree,scala.ScalaObject,scala.Product,java.io.Serializable
  SourceFile: "Trees.scala"
  Scala: length = 0x
   
  InnerClass: 
   public abstract Tree=class scala/reflect/generic/Trees$Tree of class scala/reflect/generic/Trees
   public abstract TermTree=class scala/reflect/generic/Trees$TermTree of class scala/reflect/generic/Trees
   public Alternative=class scala/reflect/generic/Trees$Alternative of class scala/reflect/generic/Trees
  minor version: 0
  major version: 49
  Constant pool:
Asciz	SourceFile;
Asciz	Trees.scala;
Asciz	trees;
Asciz	Lscala/collection/immutable/List;;
Asciz	Lscala/collection/immutable/List<Lscala/reflect/generic/Trees$Tree;>;;
Asciz	Signature;
Asciz	copy$default$1;
Asciz	()Lscala/collection/immutable/List;;
Asciz	Code;
Asciz	LineNumberTable;
Asciz	scala/reflect/generic/Trees$Alternative;
class	scala/reflect/generic/Trees$Alternative
NameAndType	trees:()Lscala/collection/immutable/List;
Method	scala/reflect/generic/Trees$Alternative.trees:()Lscala/collection/immutable/List;
NameAndType	trees:Lscala/collection/immutable/List;
Field	scala/reflect/generic/Trees$Alternative.trees:Lscala/collection/immutable/List;
Asciz	()Lscala/collection/immutable/List<Lscala/reflect/generic/Trees$Tree;>;;
Asciz	copy;
Asciz	(Lscala/collection/immutable/List;)Lscala/reflect/generic/Trees$Alternative;;
Asciz	scala$reflect$generic$Trees$Alternative$$$outer;
Asciz	()Lscala/reflect/generic/Universe;;
NameAndType	scala$reflect$generic$Trees$Alternative$$$outer:()Lscala/reflect/generic/Universe;
Method	scala/reflect/generic/Trees$Alternative.scala$reflect$generic$Trees$Alternative$$$outer:()Lscala/reflect/generic/Universe;
Asciz	<init>;
Asciz	(Lscala/reflect/generic/Universe;Lscala/collection/immutable/List;)V;
NameAndType	"<init>":(Lscala/reflect/generic/Universe;Lscala/collection/immutable/List;)V
Method	scala/reflect/generic/Trees$Alternative."<init>":(Lscala/reflect/generic/Universe;Lscala/collection/immutable/List;)V
Asciz	this;
Asciz	Lscala/reflect/generic/Trees$Alternative;;
Asciz	LocalVariableTable;
Asciz	productPrefix;
Asciz	()Ljava/lang/String;;
Asciz	Alternative;
String	Alternative
Asciz	productArity;
Asciz	()I;
Asciz	productElement;
Asciz	(I)Ljava/lang/Object;;
Asciz	java/lang/IndexOutOfBoundsException;
class	java/lang/IndexOutOfBoundsException
Asciz	scala/runtime/BoxesRunTime;
class	scala/runtime/BoxesRunTime
Asciz	boxToInteger;
Asciz	(I)Ljava/lang/Integer;;
NameAndType	boxToInteger:(I)Ljava/lang/Integer;
Method	scala/runtime/BoxesRunTime.boxToInteger:(I)Ljava/lang/Integer;
Asciz	java/lang/Object;
class	java/lang/Object
Asciz	toString;
NameAndType	toString:()Ljava/lang/String;
Method	java/lang/Object.toString:()Ljava/lang/String;
Asciz	(Ljava/lang/String;)V;
NameAndType	"<init>":(Ljava/lang/String;)V
Method	java/lang/IndexOutOfBoundsException."<init>":(Ljava/lang/String;)V
Asciz	canEqual;
Asciz	(Ljava/lang/Object;)Z;
Asciz	scala/reflect/generic/Trees$Tree;
class	scala/reflect/generic/Trees$Tree
Asciz	$outer;
Asciz	Lscala/reflect/generic/Universe;;
NameAndType	$outer:Lscala/reflect/generic/Universe;
Field	scala/reflect/generic/Trees$Tree.$outer:Lscala/reflect/generic/Universe;
Asciz	(Lscala/reflect/generic/Universe;)V;
NameAndType	"<init>":(Lscala/reflect/generic/Universe;)V
Method	scala/reflect/generic/Trees$Tree."<init>":(Lscala/reflect/generic/Universe;)V
Asciz	(Lscala/reflect/generic/Universe;Lscala/collection/immutable/List<Lscala/reflect/generic/Trees$Tree;>;)V;
Asciz	Scala;
Asciz	InnerClasses;
Asciz	scala/reflect/generic/Trees;
class	scala/reflect/generic/Trees
Asciz	Tree;
Asciz	scala/reflect/generic/Trees$TermTree;
class	scala/reflect/generic/Trees$TermTree
Asciz	TermTree;
Asciz	scala/ScalaObject;
class	scala/ScalaObject
Asciz	scala/Product;
class	scala/Product
Asciz	java/io/Serializable;
class	java/io/Serializable

{
private final scala.collection.immutable.List trees;
  Signature: Lscala/collection/immutable/List;
  Signature: length = 0x2
   00 05 

public scala.collection.immutable.List copy$default$1();
  Signature: ()Lscala/collection/immutable/List;
  Code:
   Stack=1, Locals=1, Args_size=1
	aload_0
	invokevirtual	Method trees:()Lscala/collection/immutable/List;
	areturn
  Labels:

public scala.collection.immutable.List trees();
  Signature: ()Lscala/collection/immutable/List;
  Code:
   Stack=1, Locals=1, Args_size=1
	aload_0
	getfield	Field trees:Lscala/collection/immutable/List;
	areturn
  Labels:
  Signature: length = 0x2
   00 11 

public scala.reflect.generic.Trees$Alternative copy(scala.collection.immutable.List);
  Signature: (Lscala/collection/immutable/List;)Lscala/reflect/generic/Trees$Alternative;
  Code:
   Stack=4, Locals=2, Args_size=2
	new	class scala/reflect/generic/Trees$Alternative
	dup
	aload_0
	invokevirtual	Method scala$reflect$generic$Trees$Alternative$$$outer:()Lscala/reflect/generic/Universe;
	aload_1
	invokespecial	Method "<init>":(Lscala/reflect/generic/Universe;Lscala/collection/immutable/List;)V
	areturn
  Labels:
  LocalVariableTable: 
   Start  Length  Slot  Name   Signature
   0      13      0    this       Lscala/reflect/generic/Trees$Alternative;
   0      13      1    trees       Lscala/collection/immutable/List;


public java.lang.String productPrefix();
  Signature: ()Ljava/lang/String;
  Code:
   Stack=1, Locals=1, Args_size=1
	ldc	String Alternative
	areturn
  Labels:

public int productArity();
  Signature: ()I
  Code:
   Stack=1, Locals=1, Args_size=1
	iconst_1
	ireturn
  Labels:

public java.lang.Object productElement(int);
  Signature: (I)Ljava/lang/Object;
  Code:
   Stack=3, Locals=2, Args_size=2
	iload_1
	iconst_0
	if_icmpne	l1 // new
	aload_0
	invokevirtual	Method trees:()Lscala/collection/immutable/List;
	areturn
l1	new	class java/lang/IndexOutOfBoundsException
	dup
	iload_1
	invokestatic	Method scala/runtime/BoxesRunTime.boxToInteger:(I)Ljava/lang/Integer;
	invokevirtual	Method java/lang/Object.toString:()Ljava/lang/String;
	invokespecial	Method java/lang/IndexOutOfBoundsException."<init>":(Ljava/lang/String;)V
	athrow
  Labels:
   	l1 = 10 // new

public boolean canEqual(java.lang.Object);
  Signature: (Ljava/lang/Object;)Z
  Code:
   Stack=1, Locals=2, Args_size=2
	aload_1
	instanceof	class scala/reflect/generic/Trees$Alternative
	ireturn
  Labels:

public scala.reflect.generic.Universe scala$reflect$generic$Trees$Alternative$$$outer();
  Signature: ()Lscala/reflect/generic/Universe;
  Code:
   Stack=1, Locals=1, Args_size=1
	aload_0
	getfield	Field scala/reflect/generic/Trees$Tree.$outer:Lscala/reflect/generic/Universe;
	areturn
  Labels:

public scala.reflect.generic.Trees$Alternative(scala.reflect.generic.Universe, scala.collection.immutable.List);
  Signature: (Lscala/reflect/generic/Universe;Lscala/collection/immutable/List;)V
  Code:
   Stack=2, Locals=3, Args_size=3
	aload_0
	aload_2
	putfield	Field trees:Lscala/collection/immutable/List;
	aload_0
	aload_1
	invokespecial	Method scala/reflect/generic/Trees$Tree."<init>":(Lscala/reflect/generic/Universe;)V
	return
  Labels:
  LocalVariableTable: 
   Start  Length  Slot  Name   Signature
   0      11      0    this       Lscala/reflect/generic/Trees$Alternative;
   0      11      1    $outer       Lscala/reflect/generic/Universe;
   0      11      2    trees       Lscala/collection/immutable/List;

  Signature: length = 0x2
   00 42 

}

