Compiled from "Trees.scala"
public final class scala.reflect.generic.Trees$Alternative$ extends java.lang.Object implements scala.Function1,scala.ScalaObject
  SourceFile: "Trees.scala"
  Scala: length = 0x
   
  InnerClass: 
   public Alternative=class scala/reflect/generic/Trees$Alternative of class scala/reflect/generic/Trees
  minor version: 0
  major version: 49
  Constant pool:
Asciz	SourceFile;
Asciz	Trees.scala;
Asciz	Scala;
Asciz	$outer;
Asciz	Lscala/reflect/generic/Universe;;
Asciz	toString;
Asciz	()Ljava/lang/String;;
Asciz	Code;
Asciz	LineNumberTable;
Asciz	scala/Function1$class;
class	scala/Function1$class
Asciz	(Lscala/Function1;)Ljava/lang/String;;
NameAndType	toString:(Lscala/Function1;)Ljava/lang/String;
Method	scala/Function1$class.toString:(Lscala/Function1;)Ljava/lang/String;
Asciz	compose;
Asciz	(Lscala/Function1;)Lscala/Function1;;
Asciz	(Lscala/Function1;Lscala/Function1;)Lscala/Function1;;
NameAndType	compose:(Lscala/Function1;Lscala/Function1;)Lscala/Function1;
Method	scala/Function1$class.compose:(Lscala/Function1;Lscala/Function1;)Lscala/Function1;
Asciz	this;
Asciz	Lscala/reflect/generic/Trees$Alternative$;;
Asciz	g;
Asciz	Lscala/Function1;;
Asciz	LocalVariableTable;
Asciz	andThen;
NameAndType	andThen:(Lscala/Function1;Lscala/Function1;)Lscala/Function1;
Method	scala/Function1$class.andThen:(Lscala/Function1;Lscala/Function1;)Lscala/Function1;
Asciz	unapply;
Asciz	(Lscala/reflect/generic/Trees$Alternative;)Lscala/Some;;
Asciz	scala/Some;
class	scala/Some
Asciz	scala/reflect/generic/Trees$Alternative;
class	scala/reflect/generic/Trees$Alternative
Asciz	trees;
Asciz	()Lscala/collection/immutable/List;;
NameAndType	trees:()Lscala/collection/immutable/List;
Method	scala/reflect/generic/Trees$Alternative.trees:()Lscala/collection/immutable/List;
Asciz	<init>;
Asciz	(Ljava/lang/Object;)V;
NameAndType	"<init>":(Ljava/lang/Object;)V
Method	scala/Some."<init>":(Ljava/lang/Object;)V
Asciz	x$0;
Asciz	Lscala/reflect/generic/Trees$Alternative;;
Asciz	apply;
Asciz	(Lscala/collection/immutable/List;)Lscala/reflect/generic/Trees$Alternative;;
Asciz	scala/reflect/generic/Trees$Alternative$;
class	scala/reflect/generic/Trees$Alternative$
NameAndType	$outer:Lscala/reflect/generic/Universe;
Field	scala/reflect/generic/Trees$Alternative$.$outer:Lscala/reflect/generic/Universe;
Asciz	(Lscala/reflect/generic/Universe;Lscala/collection/immutable/List;)V;
NameAndType	"<init>":(Lscala/reflect/generic/Universe;Lscala/collection/immutable/List;)V
Method	scala/reflect/generic/Trees$Alternative."<init>":(Lscala/reflect/generic/Universe;Lscala/collection/immutable/List;)V
Asciz	Lscala/collection/immutable/List;;
Asciz	(Ljava/lang/Object;)Ljava/lang/Object;;
Asciz	scala/collection/immutable/List;
class	scala/collection/immutable/List
NameAndType	apply:(Lscala/collection/immutable/List;)Lscala/reflect/generic/Trees$Alternative;
Method	scala/reflect/generic/Trees$Alternative$.apply:(Lscala/collection/immutable/List;)Lscala/reflect/generic/Trees$Alternative;
Asciz	v1;
Asciz	Ljava/lang/Object;;
Asciz	(Lscala/reflect/generic/Universe;)V;
Asciz	java/lang/NullPointerException;
class	java/lang/NullPointerException
Asciz	()V;
NameAndType	"<init>":()V
Method	java/lang/NullPointerException."<init>":()V
Asciz	java/lang/Object;
class	java/lang/Object
Method	java/lang/Object."<init>":()V
Asciz	$init$;
Asciz	(Lscala/Function1;)V;
NameAndType	$init$:(Lscala/Function1;)V
Method	scala/Function1$class.$init$:(Lscala/Function1;)V
Asciz	InnerClasses;
Asciz	scala/reflect/generic/Trees;
class	scala/reflect/generic/Trees
Asciz	Alternative;
Asciz	scala/Function1;
class	scala/Function1
Asciz	scala/ScalaObject;
class	scala/ScalaObject

{
public final scala.reflect.generic.Universe $outer;
  Signature: Lscala/reflect/generic/Universe;

public java.lang.String toString();
  Signature: ()Ljava/lang/String;
  Code:
   Stack=1, Locals=1, Args_size=1
	aload_0
	invokestatic	Method scala/Function1$class.toString:(Lscala/Function1;)Ljava/lang/String;
	areturn
  Labels:

public scala.Function1 compose(scala.Function1);
  Signature: (Lscala/Function1;)Lscala/Function1;
  Code:
   Stack=2, Locals=2, Args_size=2
	aload_0
	aload_1
	invokestatic	Method scala/Function1$class.compose:(Lscala/Function1;Lscala/Function1;)Lscala/Function1;
	areturn
  Labels:
  LocalVariableTable: 
   Start  Length  Slot  Name   Signature
   0      6      0    this       Lscala/reflect/generic/Trees$Alternative$;
   0      6      1    g       Lscala/Function1;


public scala.Function1 andThen(scala.Function1);
  Signature: (Lscala/Function1;)Lscala/Function1;
  Code:
   Stack=2, Locals=2, Args_size=2
	aload_0
	aload_1
	invokestatic	Method scala/Function1$class.andThen:(Lscala/Function1;Lscala/Function1;)Lscala/Function1;
	areturn
  Labels:
  LocalVariableTable: 
   Start  Length  Slot  Name   Signature
   0      6      0    this       Lscala/reflect/generic/Trees$Alternative$;
   0      6      1    g       Lscala/Function1;


public scala.Some unapply(scala.reflect.generic.Trees$Alternative);
  Signature: (Lscala/reflect/generic/Trees$Alternative;)Lscala/Some;
  Code:
   Stack=3, Locals=2, Args_size=2
	new	class scala/Some
	dup
	aload_1
	invokevirtual	Method scala/reflect/generic/Trees$Alternative.trees:()Lscala/collection/immutable/List;
	invokespecial	Method scala/Some."<init>":(Ljava/lang/Object;)V
	areturn
  Labels:
  LocalVariableTable: 
   Start  Length  Slot  Name   Signature
   0      12      0    this       Lscala/reflect/generic/Trees$Alternative$;
   0      12      1    x$0       Lscala/reflect/generic/Trees$Alternative;


public scala.reflect.generic.Trees$Alternative apply(scala.collection.immutable.List);
  Signature: (Lscala/collection/immutable/List;)Lscala/reflect/generic/Trees$Alternative;
  Code:
   Stack=4, Locals=3, Args_size=2
	aload_0
	getfield	Field $outer:Lscala/reflect/generic/Universe;
	astore_2
	new	class scala/reflect/generic/Trees$Alternative
	dup
	aload_0
	getfield	Field $outer:Lscala/reflect/generic/Universe;
	aload_1
	invokespecial	Method scala/reflect/generic/Trees$Alternative."<init>":(Lscala/reflect/generic/Universe;Lscala/collection/immutable/List;)V
	areturn
  Labels:
  LocalVariableTable: 
   Start  Length  Slot  Name   Signature
   0      18      0    this       Lscala/reflect/generic/Trees$Alternative$;
   5      13      1    trees       Lscala/collection/immutable/List;


public java.lang.Object apply(java.lang.Object);
  Signature: (Ljava/lang/Object;)Ljava/lang/Object;
  Code:
   Stack=2, Locals=3, Args_size=2
	aload_0
	getfield	Field $outer:Lscala/reflect/generic/Universe;
	astore_2
	aload_0
	aload_1
	checkcast	class scala/collection/immutable/List
	invokevirtual	Method apply:(Lscala/collection/immutable/List;)Lscala/reflect/generic/Trees$Alternative;
	areturn
  Labels:
  LocalVariableTable: 
   Start  Length  Slot  Name   Signature
   0      14      0    this       Lscala/reflect/generic/Trees$Alternative$;
   5      9      1    v1       Ljava/lang/Object;


public scala.reflect.generic.Trees$Alternative$(scala.reflect.generic.Universe);
  Signature: (Lscala/reflect/generic/Universe;)V
  Code:
   Stack=2, Locals=2, Args_size=2
	aload_1
	ifnonnull	l1 // aload_0
	new	class java/lang/NullPointerException
	dup
	invokespecial	Method java/lang/NullPointerException."<init>":()V
	athrow
l1	aload_0
	aload_1
	putfield	Field $outer:Lscala/reflect/generic/Universe;
	aload_0
	invokespecial	Method java/lang/Object."<init>":()V
	aload_0
	invokestatic	Method scala/Function1$class.$init$:(Lscala/Function1;)V
	return
  Labels:
   	l1 = 12 // aload_0
  LocalVariableTable: 
   Start  Length  Slot  Name   Signature
   0      26      0    this       Lscala/reflect/generic/Trees$Alternative$;
   0      26      1    $outer       Lscala/reflect/generic/Universe;


}

