Compiled from "Trees.scala"
public final class scala.reflect.generic.Trees$CompoundTypeTree$ extends java.lang.Object implements scala.Function1,scala.ScalaObject
  SourceFile: "Trees.scala"
  Scala: length = 0x
   
  InnerClass: 
   public Template=class scala/reflect/generic/Trees$Template of class scala/reflect/generic/Trees
   public CompoundTypeTree=class scala/reflect/generic/Trees$CompoundTypeTree of class scala/reflect/generic/Trees
  minor version: 0
  major version: 49
  Constant pool:
Asciz	SourceFile;
Asciz	Trees.scala;
Asciz	Scala;
Asciz	$outer;
Asciz	Lscala/reflect/generic/Universe;;
Asciz	toString;
Asciz	()Ljava/lang/String;;
Asciz	Code;
Asciz	LineNumberTable;
Asciz	scala/Function1$class;
class	scala/Function1$class
Asciz	(Lscala/Function1;)Ljava/lang/String;;
NameAndType	toString:(Lscala/Function1;)Ljava/lang/String;
Method	scala/Function1$class.toString:(Lscala/Function1;)Ljava/lang/String;
Asciz	compose;
Asciz	(Lscala/Function1;)Lscala/Function1;;
Asciz	(Lscala/Function1;Lscala/Function1;)Lscala/Function1;;
NameAndType	compose:(Lscala/Function1;Lscala/Function1;)Lscala/Function1;
Method	scala/Function1$class.compose:(Lscala/Function1;Lscala/Function1;)Lscala/Function1;
Asciz	this;
Asciz	Lscala/reflect/generic/Trees$CompoundTypeTree$;;
Asciz	g;
Asciz	Lscala/Function1;;
Asciz	LocalVariableTable;
Asciz	andThen;
NameAndType	andThen:(Lscala/Function1;Lscala/Function1;)Lscala/Function1;
Method	scala/Function1$class.andThen:(Lscala/Function1;Lscala/Function1;)Lscala/Function1;
Asciz	unapply;
Asciz	(Lscala/reflect/generic/Trees$CompoundTypeTree;)Lscala/Option;;
Asciz	java/lang/Object;
class	java/lang/Object
Asciz	equals;
Asciz	(Ljava/lang/Object;)Z;
NameAndType	equals:(Ljava/lang/Object;)Z
Method	java/lang/Object.equals:(Ljava/lang/Object;)Z
Asciz	scala/None$;
class	scala/None$
Asciz	MODULE$;
Asciz	Lscala/None$;;
NameAndType	MODULE$:Lscala/None$;
Field	scala/None$.MODULE$:Lscala/None$;
Asciz	scala/Some;
class	scala/Some
Asciz	scala/reflect/generic/Trees$CompoundTypeTree;
class	scala/reflect/generic/Trees$CompoundTypeTree
Asciz	templ;
Asciz	()Lscala/reflect/generic/Trees$Template;;
NameAndType	templ:()Lscala/reflect/generic/Trees$Template;
Method	scala/reflect/generic/Trees$CompoundTypeTree.templ:()Lscala/reflect/generic/Trees$Template;
Asciz	<init>;
Asciz	(Ljava/lang/Object;)V;
NameAndType	"<init>":(Ljava/lang/Object;)V
Method	scala/Some."<init>":(Ljava/lang/Object;)V
Asciz	x$0;
Asciz	Lscala/reflect/generic/Trees$CompoundTypeTree;;
Asciz	apply;
Asciz	(Lscala/reflect/generic/Trees$Template;)Lscala/reflect/generic/Trees$CompoundTypeTree;;
Asciz	scala/reflect/generic/Trees$CompoundTypeTree$;
class	scala/reflect/generic/Trees$CompoundTypeTree$
NameAndType	$outer:Lscala/reflect/generic/Universe;
Field	scala/reflect/generic/Trees$CompoundTypeTree$.$outer:Lscala/reflect/generic/Universe;
Asciz	(Lscala/reflect/generic/Universe;Lscala/reflect/generic/Trees$Template;)V;
NameAndType	"<init>":(Lscala/reflect/generic/Universe;Lscala/reflect/generic/Trees$Template;)V
Method	scala/reflect/generic/Trees$CompoundTypeTree."<init>":(Lscala/reflect/generic/Universe;Lscala/reflect/generic/Trees$Template;)V
Asciz	Lscala/reflect/generic/Trees$Template;;
Asciz	(Ljava/lang/Object;)Ljava/lang/Object;;
Asciz	scala/reflect/generic/Trees$Template;
class	scala/reflect/generic/Trees$Template
NameAndType	apply:(Lscala/reflect/generic/Trees$Template;)Lscala/reflect/generic/Trees$CompoundTypeTree;
Method	scala/reflect/generic/Trees$CompoundTypeTree$.apply:(Lscala/reflect/generic/Trees$Template;)Lscala/reflect/generic/Trees$CompoundTypeTree;
Asciz	v1;
Asciz	Ljava/lang/Object;;
Asciz	(Lscala/reflect/generic/Universe;)V;
Asciz	java/lang/NullPointerException;
class	java/lang/NullPointerException
Asciz	()V;
NameAndType	"<init>":()V
Method	java/lang/NullPointerException."<init>":()V
Method	java/lang/Object."<init>":()V
Asciz	$init$;
Asciz	(Lscala/Function1;)V;
NameAndType	$init$:(Lscala/Function1;)V
Method	scala/Function1$class.$init$:(Lscala/Function1;)V
Asciz	InnerClasses;
Asciz	scala/reflect/generic/Trees;
class	scala/reflect/generic/Trees
Asciz	Template;
Asciz	CompoundTypeTree;
Asciz	scala/Function1;
class	scala/Function1
Asciz	scala/ScalaObject;
class	scala/ScalaObject

{
public final scala.reflect.generic.Universe $outer;
  Signature: Lscala/reflect/generic/Universe;

public java.lang.String toString();
  Signature: ()Ljava/lang/String;
  Code:
   Stack=1, Locals=1, Args_size=1
	aload_0
	invokestatic	Method scala/Function1$class.toString:(Lscala/Function1;)Ljava/lang/String;
	areturn
  Labels:

public scala.Function1 compose(scala.Function1);
  Signature: (Lscala/Function1;)Lscala/Function1;
  Code:
   Stack=2, Locals=2, Args_size=2
	aload_0
	aload_1
	invokestatic	Method scala/Function1$class.compose:(Lscala/Function1;Lscala/Function1;)Lscala/Function1;
	areturn
  Labels:
  LocalVariableTable: 
   Start  Length  Slot  Name   Signature
   0      6      0    this       Lscala/reflect/generic/Trees$CompoundTypeTree$;
   0      6      1    g       Lscala/Function1;


public scala.Function1 andThen(scala.Function1);
  Signature: (Lscala/Function1;)Lscala/Function1;
  Code:
   Stack=2, Locals=2, Args_size=2
	aload_0
	aload_1
	invokestatic	Method scala/Function1$class.andThen:(Lscala/Function1;Lscala/Function1;)Lscala/Function1;
	areturn
  Labels:
  LocalVariableTable: 
   Start  Length  Slot  Name   Signature
   0      6      0    this       Lscala/reflect/generic/Trees$CompoundTypeTree$;
   0      6      1    g       Lscala/Function1;


public scala.Option unapply(scala.reflect.generic.Trees$CompoundTypeTree);
  Signature: (Lscala/reflect/generic/Trees$CompoundTypeTree;)Lscala/Option;
  Code:
   Stack=3, Locals=2, Args_size=2
	aload_1
	dup
	pop
	ifnull	l1 // getstatic
	aload_1
	aconst_null
	invokevirtual	Method java/lang/Object.equals:(Ljava/lang/Object;)Z
	ifeq	l2 // new
l1	getstatic	Field scala/None$.MODULE$:Lscala/None$;
	goto	l3 // areturn
l2	new	class scala/Some
	dup
	aload_1
	invokevirtual	Method scala/reflect/generic/Trees$CompoundTypeTree.templ:()Lscala/reflect/generic/Trees$Template;
	invokespecial	Method scala/Some."<init>":(Ljava/lang/Object;)V
l3	areturn
  Labels:
   	l1 = 14 // getstatic
   	l2 = 20 // new
   	l3 = 31 // areturn
  LocalVariableTable: 
   Start  Length  Slot  Name   Signature
   0      32      0    this       Lscala/reflect/generic/Trees$CompoundTypeTree$;
   0      32      1    x$0       Lscala/reflect/generic/Trees$CompoundTypeTree;


public scala.reflect.generic.Trees$CompoundTypeTree apply(scala.reflect.generic.Trees$Template);
  Signature: (Lscala/reflect/generic/Trees$Template;)Lscala/reflect/generic/Trees$CompoundTypeTree;
  Code:
   Stack=4, Locals=3, Args_size=2
	aload_0
	getfield	Field $outer:Lscala/reflect/generic/Universe;
	astore_2
	new	class scala/reflect/generic/Trees$CompoundTypeTree
	dup
	aload_0
	getfield	Field $outer:Lscala/reflect/generic/Universe;
	aload_1
	invokespecial	Method scala/reflect/generic/Trees$CompoundTypeTree."<init>":(Lscala/reflect/generic/Universe;Lscala/reflect/generic/Trees$Template;)V
	areturn
  Labels:
  LocalVariableTable: 
   Start  Length  Slot  Name   Signature
   0      18      0    this       Lscala/reflect/generic/Trees$CompoundTypeTree$;
   5      13      1    templ       Lscala/reflect/generic/Trees$Template;


public java.lang.Object apply(java.lang.Object);
  Signature: (Ljava/lang/Object;)Ljava/lang/Object;
  Code:
   Stack=2, Locals=3, Args_size=2
	aload_0
	getfield	Field $outer:Lscala/reflect/generic/Universe;
	astore_2
	aload_0
	aload_1
	checkcast	class scala/reflect/generic/Trees$Template
	invokevirtual	Method apply:(Lscala/reflect/generic/Trees$Template;)Lscala/reflect/generic/Trees$CompoundTypeTree;
	areturn
  Labels:
  LocalVariableTable: 
   Start  Length  Slot  Name   Signature
   0      14      0    this       Lscala/reflect/generic/Trees$CompoundTypeTree$;
   5      9      1    v1       Ljava/lang/Object;


public scala.reflect.generic.Trees$CompoundTypeTree$(scala.reflect.generic.Universe);
  Signature: (Lscala/reflect/generic/Universe;)V
  Code:
   Stack=2, Locals=2, Args_size=2
	aload_1
	ifnonnull	l1 // aload_0
	new	class java/lang/NullPointerException
	dup
	invokespecial	Method java/lang/NullPointerException."<init>":()V
	athrow
l1	aload_0
	aload_1
	putfield	Field $outer:Lscala/reflect/generic/Universe;
	aload_0
	invokespecial	Method java/lang/Object."<init>":()V
	aload_0
	invokestatic	Method scala/Function1$class.$init$:(Lscala/Function1;)V
	return
  Labels:
   	l1 = 12 // aload_0
  LocalVariableTable: 
   Start  Length  Slot  Name   Signature
   0      26      0    this       Lscala/reflect/generic/Trees$CompoundTypeTree$;
   0      26      1    $outer       Lscala/reflect/generic/Universe;


}

