Compiled from "Trees.scala"
public class scala.reflect.generic.Trees$ClassDef extends scala.reflect.generic.Trees$ImplDef implements scala.ScalaObject,scala.Product,java.io.Serializable
  SourceFile: "Trees.scala"
  Scala: length = 0x
   
  InnerClass: 
   public abstract Tree=class scala/reflect/generic/Trees$Tree of class scala/reflect/generic/Trees
   public abstract ImplDef=class scala/reflect/generic/Trees$ImplDef of class scala/reflect/generic/Trees
   public Template=class scala/reflect/generic/Trees$Template of class scala/reflect/generic/Trees
   public ClassDef=class scala/reflect/generic/Trees$ClassDef of class scala/reflect/generic/Trees
   public Modifiers=class scala/reflect/generic/Trees$Modifiers of class scala/reflect/generic/Trees
  minor version: 0
  major version: 49
  Constant pool:
Asciz	SourceFile;
Asciz	Trees.scala;
Asciz	mods;
Asciz	Lscala/reflect/generic/Trees$Modifiers;;
Asciz	name;
Asciz	Ljava/lang/Object;;
Asciz	tparams;
Asciz	Lscala/collection/immutable/List;;
Asciz	Lscala/collection/immutable/List<Lscala/reflect/generic/Trees$TypeDef;>;;
Asciz	Signature;
Asciz	impl;
Asciz	Lscala/reflect/generic/Trees$Template;;
Asciz	copy$default$4;
Asciz	()Lscala/reflect/generic/Trees$Template;;
Asciz	Code;
Asciz	LineNumberTable;
Asciz	scala/reflect/generic/Trees$ClassDef;
class	scala/reflect/generic/Trees$ClassDef
NameAndType	impl:()Lscala/reflect/generic/Trees$Template;
Method	scala/reflect/generic/Trees$ClassDef.impl:()Lscala/reflect/generic/Trees$Template;
Asciz	copy$default$3;
Asciz	()Lscala/collection/immutable/List;;
NameAndType	tparams:()Lscala/collection/immutable/List;
Method	scala/reflect/generic/Trees$ClassDef.tparams:()Lscala/collection/immutable/List;
Asciz	copy$default$2;
Asciz	()Ljava/lang/Object;;
NameAndType	name:()Ljava/lang/Object;
Method	scala/reflect/generic/Trees$ClassDef.name:()Ljava/lang/Object;
Asciz	copy$default$1;
Asciz	()Lscala/reflect/generic/Trees$Modifiers;;
NameAndType	mods:()Lscala/reflect/generic/Trees$Modifiers;
Method	scala/reflect/generic/Trees$ClassDef.mods:()Lscala/reflect/generic/Trees$Modifiers;
NameAndType	mods:Lscala/reflect/generic/Trees$Modifiers;
Field	scala/reflect/generic/Trees$ClassDef.mods:Lscala/reflect/generic/Trees$Modifiers;
NameAndType	name:Ljava/lang/Object;
Field	scala/reflect/generic/Trees$ClassDef.name:Ljava/lang/Object;
NameAndType	tparams:Lscala/collection/immutable/List;
Field	scala/reflect/generic/Trees$ClassDef.tparams:Lscala/collection/immutable/List;
Asciz	()Lscala/collection/immutable/List<Lscala/reflect/generic/Trees$TypeDef;>;;
NameAndType	impl:Lscala/reflect/generic/Trees$Template;
Field	scala/reflect/generic/Trees$ClassDef.impl:Lscala/reflect/generic/Trees$Template;
Asciz	copy;
Asciz	(Lscala/reflect/generic/Trees$Modifiers;Ljava/lang/Object;Lscala/collection/immutable/List;Lscala/reflect/generic/Trees$Template;)Lscala/reflect/generic/Trees$ClassDef;;
Asciz	scala$reflect$generic$Trees$ClassDef$$$outer;
Asciz	()Lscala/reflect/generic/Universe;;
NameAndType	scala$reflect$generic$Trees$ClassDef$$$outer:()Lscala/reflect/generic/Universe;
Method	scala/reflect/generic/Trees$ClassDef.scala$reflect$generic$Trees$ClassDef$$$outer:()Lscala/reflect/generic/Universe;
Asciz	<init>;
Asciz	(Lscala/reflect/generic/Universe;Lscala/reflect/generic/Trees$Modifiers;Ljava/lang/Object;Lscala/collection/immutable/List;Lscala/reflect/generic/Trees$Template;)V;
NameAndType	"<init>":(Lscala/reflect/generic/Universe;Lscala/reflect/generic/Trees$Modifiers;Ljava/lang/Object;Lscala/collection/immutable/List;Lscala/reflect/generic/Trees$Template;)V
Method	scala/reflect/generic/Trees$ClassDef."<init>":(Lscala/reflect/generic/Universe;Lscala/reflect/generic/Trees$Modifiers;Ljava/lang/Object;Lscala/collection/immutable/List;Lscala/reflect/generic/Trees$Template;)V
Asciz	this;
Asciz	Lscala/reflect/generic/Trees$ClassDef;;
Asciz	LocalVariableTable;
Asciz	productPrefix;
Asciz	()Ljava/lang/String;;
Asciz	ClassDef;
String	ClassDef
Asciz	productArity;
Asciz	()I;
Asciz	productElement;
Asciz	(I)Ljava/lang/Object;;
Asciz	java/lang/IndexOutOfBoundsException;
class	java/lang/IndexOutOfBoundsException
Asciz	scala/runtime/BoxesRunTime;
class	scala/runtime/BoxesRunTime
Asciz	boxToInteger;
Asciz	(I)Ljava/lang/Integer;;
NameAndType	boxToInteger:(I)Ljava/lang/Integer;
Method	scala/runtime/BoxesRunTime.boxToInteger:(I)Ljava/lang/Integer;
Asciz	java/lang/Object;
class	java/lang/Object
Asciz	toString;
NameAndType	toString:()Ljava/lang/String;
Method	java/lang/Object.toString:()Ljava/lang/String;
Asciz	(Ljava/lang/String;)V;
NameAndType	"<init>":(Ljava/lang/String;)V
Method	java/lang/IndexOutOfBoundsException."<init>":(Ljava/lang/String;)V
Asciz	canEqual;
Asciz	(Ljava/lang/Object;)Z;
Asciz	scala/reflect/generic/Trees$Tree;
class	scala/reflect/generic/Trees$Tree
Asciz	$outer;
Asciz	Lscala/reflect/generic/Universe;;
NameAndType	$outer:Lscala/reflect/generic/Universe;
Field	scala/reflect/generic/Trees$Tree.$outer:Lscala/reflect/generic/Universe;
Asciz	scala/reflect/generic/Trees$ImplDef;
class	scala/reflect/generic/Trees$ImplDef
Asciz	(Lscala/reflect/generic/Universe;)V;
NameAndType	"<init>":(Lscala/reflect/generic/Universe;)V
Method	scala/reflect/generic/Trees$ImplDef."<init>":(Lscala/reflect/generic/Universe;)V
Asciz	(Lscala/reflect/generic/Universe;Lscala/reflect/generic/Trees$Modifiers;Ljava/lang/Object;Lscala/collection/immutable/List<Lscala/reflect/generic/Trees$TypeDef;>;Lscala/reflect/generic/Trees$Template;)V;
Asciz	Scala;
Asciz	InnerClasses;
Asciz	scala/reflect/generic/Trees;
class	scala/reflect/generic/Trees
Asciz	Tree;
Asciz	ImplDef;
Asciz	scala/reflect/generic/Trees$Template;
class	scala/reflect/generic/Trees$Template
Asciz	Template;
Asciz	scala/reflect/generic/Trees$Modifiers;
class	scala/reflect/generic/Trees$Modifiers
Asciz	Modifiers;
Asciz	scala/ScalaObject;
class	scala/ScalaObject
Asciz	scala/Product;
class	scala/Product
Asciz	java/io/Serializable;
class	java/io/Serializable

{
private final scala.reflect.generic.Trees$Modifiers mods;
  Signature: Lscala/reflect/generic/Trees$Modifiers;

private final java.lang.Object name;
  Signature: Ljava/lang/Object;

private final scala.collection.immutable.List tparams;
  Signature: Lscala/collection/immutable/List;
  Signature: length = 0x2
   00 09 

private final scala.reflect.generic.Trees$Template impl;
  Signature: Lscala/reflect/generic/Trees$Template;

public scala.reflect.generic.Trees$Template copy$default$4();
  Signature: ()Lscala/reflect/generic/Trees$Template;
  Code:
   Stack=1, Locals=1, Args_size=1
	aload_0
	invokevirtual	Method impl:()Lscala/reflect/generic/Trees$Template;
	areturn
  Labels:

public scala.collection.immutable.List copy$default$3();
  Signature: ()Lscala/collection/immutable/List;
  Code:
   Stack=1, Locals=1, Args_size=1
	aload_0
	invokevirtual	Method tparams:()Lscala/collection/immutable/List;
	areturn
  Labels:

public java.lang.Object copy$default$2();
  Signature: ()Ljava/lang/Object;
  Code:
   Stack=1, Locals=1, Args_size=1
	aload_0
	invokevirtual	Method name:()Ljava/lang/Object;
	areturn
  Labels:

public scala.reflect.generic.Trees$Modifiers copy$default$1();
  Signature: ()Lscala/reflect/generic/Trees$Modifiers;
  Code:
   Stack=1, Locals=1, Args_size=1
	aload_0
	invokevirtual	Method mods:()Lscala/reflect/generic/Trees$Modifiers;
	areturn
  Labels:

public scala.reflect.generic.Trees$Modifiers mods();
  Signature: ()Lscala/reflect/generic/Trees$Modifiers;
  Code:
   Stack=1, Locals=1, Args_size=1
	aload_0
	getfield	Field mods:Lscala/reflect/generic/Trees$Modifiers;
	areturn
  Labels:

public java.lang.Object name();
  Signature: ()Ljava/lang/Object;
  Code:
   Stack=1, Locals=1, Args_size=1
	aload_0
	getfield	Field name:Ljava/lang/Object;
	areturn
  Labels:

public scala.collection.immutable.List tparams();
  Signature: ()Lscala/collection/immutable/List;
  Code:
   Stack=1, Locals=1, Args_size=1
	aload_0
	getfield	Field tparams:Lscala/collection/immutable/List;
	areturn
  Labels:
  Signature: length = 0x2
   00 27 

public scala.reflect.generic.Trees$Template impl();
  Signature: ()Lscala/reflect/generic/Trees$Template;
  Code:
   Stack=1, Locals=1, Args_size=1
	aload_0
	getfield	Field impl:Lscala/reflect/generic/Trees$Template;
	areturn
  Labels:

public scala.reflect.generic.Trees$ClassDef copy(scala.reflect.generic.Trees$Modifiers, java.lang.Object, scala.collection.immutable.List, scala.reflect.generic.Trees$Template);
  Signature: (Lscala/reflect/generic/Trees$Modifiers;Ljava/lang/Object;Lscala/collection/immutable/List;Lscala/reflect/generic/Trees$Template;)Lscala/reflect/generic/Trees$ClassDef;
  Code:
   Stack=7, Locals=5, Args_size=5
	new	class scala/reflect/generic/Trees$ClassDef
	dup
	aload_0
	invokevirtual	Method scala$reflect$generic$Trees$ClassDef$$$outer:()Lscala/reflect/generic/Universe;
	aload_1
	aload_2
	aload_3
	aload	4
	invokespecial	Method "<init>":(Lscala/reflect/generic/Universe;Lscala/reflect/generic/Trees$Modifiers;Ljava/lang/Object;Lscala/collection/immutable/List;Lscala/reflect/generic/Trees$Template;)V
	areturn
  Labels:
  LocalVariableTable: 
   Start  Length  Slot  Name   Signature
   0      17      0    this       Lscala/reflect/generic/Trees$ClassDef;
   0      17      1    mods       Lscala/reflect/generic/Trees$Modifiers;
   0      17      2    name       Ljava/lang/Object;
   0      17      3    tparams       Lscala/collection/immutable/List;
   0      17      4    impl       Lscala/reflect/generic/Trees$Template;


public java.lang.String productPrefix();
  Signature: ()Ljava/lang/String;
  Code:
   Stack=1, Locals=1, Args_size=1
	ldc	String ClassDef
	areturn
  Labels:

public int productArity();
  Signature: ()I
  Code:
   Stack=1, Locals=1, Args_size=1
	iconst_4
	ireturn
  Labels:

public java.lang.Object productElement(int);
  Signature: (I)Ljava/lang/Object;
  Code:
   Stack=3, Locals=2, Args_size=2
	iload_1
	tableswitch{ //0 to 3
		0: 68;
		1: 61;
		2: 54;
		3: 47;
		default: 32 }
	new	class java/lang/IndexOutOfBoundsException
	dup
	iload_1
	invokestatic	Method scala/runtime/BoxesRunTime.boxToInteger:(I)Ljava/lang/Integer;
	invokevirtual	Method java/lang/Object.toString:()Ljava/lang/String;
	invokespecial	Method java/lang/IndexOutOfBoundsException."<init>":(Ljava/lang/String;)V
	athrow
	aload_0
	invokevirtual	Method impl:()Lscala/reflect/generic/Trees$Template;
	goto	l1 // areturn
	aload_0
	invokevirtual	Method tparams:()Lscala/collection/immutable/List;
	goto	l1 // areturn
	aload_0
	invokevirtual	Method name:()Ljava/lang/Object;
	goto	l1 // areturn
	aload_0
	invokevirtual	Method mods:()Lscala/reflect/generic/Trees$Modifiers;
l1	areturn
  Labels:
   	l1 = 72 // areturn

public boolean canEqual(java.lang.Object);
  Signature: (Ljava/lang/Object;)Z
  Code:
   Stack=1, Locals=2, Args_size=2
	aload_1
	instanceof	class scala/reflect/generic/Trees$ClassDef
	ireturn
  Labels:

public scala.reflect.generic.Universe scala$reflect$generic$Trees$ClassDef$$$outer();
  Signature: ()Lscala/reflect/generic/Universe;
  Code:
   Stack=1, Locals=1, Args_size=1
	aload_0
	getfield	Field scala/reflect/generic/Trees$Tree.$outer:Lscala/reflect/generic/Universe;
	areturn
  Labels:

public scala.reflect.generic.Trees$ClassDef(scala.reflect.generic.Universe, scala.reflect.generic.Trees$Modifiers, java.lang.Object, scala.collection.immutable.List, scala.reflect.generic.Trees$Template);
  Signature: (Lscala/reflect/generic/Universe;Lscala/reflect/generic/Trees$Modifiers;Ljava/lang/Object;Lscala/collection/immutable/List;Lscala/reflect/generic/Trees$Template;)V
  Code:
   Stack=2, Locals=6, Args_size=6
	aload_0
	aload_2
	putfield	Field mods:Lscala/reflect/generic/Trees$Modifiers;
	aload_0
	aload_3
	putfield	Field name:Ljava/lang/Object;
	aload_0
	aload	4
	putfield	Field tparams:Lscala/collection/immutable/List;
	aload_0
	aload	5
	putfield	Field impl:Lscala/reflect/generic/Trees$Template;
	aload_0
	aload_1
	invokespecial	Method scala/reflect/generic/Trees$ImplDef."<init>":(Lscala/reflect/generic/Universe;)V
	return
  Labels:
  LocalVariableTable: 
   Start  Length  Slot  Name   Signature
   0      28      0    this       Lscala/reflect/generic/Trees$ClassDef;
   0      28      1    $outer       Lscala/reflect/generic/Universe;
   0      28      2    mods       Lscala/reflect/generic/Trees$Modifiers;
   0      28      3    name       Ljava/lang/Object;
   0      28      4    tparams       Lscala/collection/immutable/List;
   0      28      5    impl       Lscala/reflect/generic/Trees$Template;

  Signature: length = 0x2
   00 5C 

}

