Compiled from "Trees.scala"
public final class scala.reflect.generic.Trees$Traverser$$anonfun$traverse$5 extends scala.runtime.AbstractFunction0 implements java.io.Serializable
  SourceFile: "Trees.scala"
  Scala: length = 0x
   
  InnerClass: 
   public abstract Tree=class scala/reflect/generic/Trees$Tree of class scala/reflect/generic/Trees
   public Traverser=class scala/reflect/generic/Trees$Traverser of class scala/reflect/generic/Trees
   public Modifiers=class scala/reflect/generic/Trees$Modifiers of class scala/reflect/generic/Trees
   public final $anonfun$traverse$5=class scala/reflect/generic/Trees$Traverser$$anonfun$traverse$5 of class scala/reflect/generic/Trees$Traverser
  minor version: 0
  major version: 49
  Constant pool:
Asciz	SourceFile;
Asciz	Trees.scala;
Asciz	<clinit>;
Asciz	()V;
Asciz	Code;
Asciz	serialVersionUID;
Asciz	J;
Asciz	scala/reflect/generic/Trees$Traverser$$anonfun$traverse$5;
class	scala/reflect/generic/Trees$Traverser$$anonfun$traverse$5
NameAndType	serialVersionUID:J
Field	scala/reflect/generic/Trees$Traverser$$anonfun$traverse$5.serialVersionUID:J
Asciz	rhs$2;
Asciz	Lscala/reflect/generic/Trees$Tree;;
Asciz	tpt$2;
Asciz	vparamss$1;
Asciz	Lscala/collection/immutable/List;;
Asciz	tparams$2;
Asciz	mods$4;
Asciz	Lscala/reflect/generic/Trees$Modifiers;;
Asciz	$outer;
Asciz	Lscala/reflect/generic/Trees$Traverser;;
Asciz	apply;
Asciz	LineNumberTable;
NameAndType	$outer:Lscala/reflect/generic/Trees$Traverser;
Field	scala/reflect/generic/Trees$Traverser$$anonfun$traverse$5.$outer:Lscala/reflect/generic/Trees$Traverser;
NameAndType	mods$4:Lscala/reflect/generic/Trees$Modifiers;
Field	scala/reflect/generic/Trees$Traverser$$anonfun$traverse$5.mods$4:Lscala/reflect/generic/Trees$Modifiers;
Asciz	scala/reflect/generic/Trees$Modifiers;
class	scala/reflect/generic/Trees$Modifiers
Asciz	annotations;
Asciz	()Lscala/collection/immutable/List;;
NameAndType	annotations:()Lscala/collection/immutable/List;
Method	scala/reflect/generic/Trees$Modifiers.annotations:()Lscala/collection/immutable/List;
Asciz	scala/reflect/generic/Trees$Traverser;
class	scala/reflect/generic/Trees$Traverser
Asciz	traverseTrees;
Asciz	(Lscala/collection/immutable/List;)V;
NameAndType	traverseTrees:(Lscala/collection/immutable/List;)V
Method	scala/reflect/generic/Trees$Traverser.traverseTrees:(Lscala/collection/immutable/List;)V
NameAndType	tparams$2:Lscala/collection/immutable/List;
Field	scala/reflect/generic/Trees$Traverser$$anonfun$traverse$5.tparams$2:Lscala/collection/immutable/List;
NameAndType	vparamss$1:Lscala/collection/immutable/List;
Field	scala/reflect/generic/Trees$Traverser$$anonfun$traverse$5.vparamss$1:Lscala/collection/immutable/List;
Asciz	traverseTreess;
NameAndType	traverseTreess:(Lscala/collection/immutable/List;)V
Method	scala/reflect/generic/Trees$Traverser.traverseTreess:(Lscala/collection/immutable/List;)V
NameAndType	tpt$2:Lscala/reflect/generic/Trees$Tree;
Field	scala/reflect/generic/Trees$Traverser$$anonfun$traverse$5.tpt$2:Lscala/reflect/generic/Trees$Tree;
Asciz	traverse;
Asciz	(Lscala/reflect/generic/Trees$Tree;)V;
NameAndType	traverse:(Lscala/reflect/generic/Trees$Tree;)V
Method	scala/reflect/generic/Trees$Traverser.traverse:(Lscala/reflect/generic/Trees$Tree;)V
NameAndType	rhs$2:Lscala/reflect/generic/Trees$Tree;
Field	scala/reflect/generic/Trees$Traverser$$anonfun$traverse$5.rhs$2:Lscala/reflect/generic/Trees$Tree;
Asciz	()Ljava/lang/Object;;
NameAndType	apply:()V
Method	scala/reflect/generic/Trees$Traverser$$anonfun$traverse$5.apply:()V
Asciz	scala/runtime/BoxedUnit;
class	scala/runtime/BoxedUnit
Asciz	UNIT;
Asciz	Lscala/runtime/BoxedUnit;;
NameAndType	UNIT:Lscala/runtime/BoxedUnit;
Field	scala/runtime/BoxedUnit.UNIT:Lscala/runtime/BoxedUnit;
Asciz	<init>;
Asciz	(Lscala/reflect/generic/Trees$Traverser;Lscala/reflect/generic/Trees$Modifiers;Lscala/collection/immutable/List;Lscala/collection/immutable/List;Lscala/reflect/generic/Trees$Tree;Lscala/reflect/generic/Trees$Tree;)V;
Asciz	java/lang/NullPointerException;
class	java/lang/NullPointerException
NameAndType	"<init>":()V
Method	java/lang/NullPointerException."<init>":()V
Asciz	scala/runtime/AbstractFunction0;
class	scala/runtime/AbstractFunction0
Method	scala/runtime/AbstractFunction0."<init>":()V
Asciz	this;
Asciz	Lscala/reflect/generic/Trees$Traverser$$anonfun$traverse$5;;
Asciz	LocalVariableTable;
Asciz	Scala;
Asciz	InnerClasses;
Asciz	scala/reflect/generic/Trees$Tree;
class	scala/reflect/generic/Trees$Tree
Asciz	scala/reflect/generic/Trees;
class	scala/reflect/generic/Trees
Asciz	Tree;
Asciz	Traverser;
Asciz	Modifiers;
Asciz	$anonfun$traverse$5;
Asciz	java/io/Serializable;
class	java/io/Serializable

{
public static final long serialVersionUID;
  Signature: J

public final scala.reflect.generic.Trees$Tree rhs$2;
  Signature: Lscala/reflect/generic/Trees$Tree;

public final scala.reflect.generic.Trees$Tree tpt$2;
  Signature: Lscala/reflect/generic/Trees$Tree;

public final scala.collection.immutable.List vparamss$1;
  Signature: Lscala/collection/immutable/List;

public final scala.collection.immutable.List tparams$2;
  Signature: Lscala/collection/immutable/List;

public final scala.reflect.generic.Trees$Modifiers mods$4;
  Signature: Lscala/reflect/generic/Trees$Modifiers;

public final scala.reflect.generic.Trees$Traverser $outer;
  Signature: Lscala/reflect/generic/Trees$Traverser;

public static {};
  Signature: ()V
  Code:
   Stack=2, Locals=0, Args_size=0
	lconst_0
	putstatic	Field serialVersionUID:J
	return
  Labels:

public final void apply();
  Signature: ()V
  Code:
   Stack=2, Locals=1, Args_size=1
	aload_0
	getfield	Field $outer:Lscala/reflect/generic/Trees$Traverser;
	aload_0
	getfield	Field mods$4:Lscala/reflect/generic/Trees$Modifiers;
	invokevirtual	Method scala/reflect/generic/Trees$Modifiers.annotations:()Lscala/collection/immutable/List;
	invokevirtual	Method scala/reflect/generic/Trees$Traverser.traverseTrees:(Lscala/collection/immutable/List;)V
	aload_0
	getfield	Field $outer:Lscala/reflect/generic/Trees$Traverser;
	aload_0
	getfield	Field tparams$2:Lscala/collection/immutable/List;
	invokevirtual	Method scala/reflect/generic/Trees$Traverser.traverseTrees:(Lscala/collection/immutable/List;)V
	aload_0
	getfield	Field $outer:Lscala/reflect/generic/Trees$Traverser;
	aload_0
	getfield	Field vparamss$1:Lscala/collection/immutable/List;
	invokevirtual	Method scala/reflect/generic/Trees$Traverser.traverseTreess:(Lscala/collection/immutable/List;)V
	aload_0
	getfield	Field $outer:Lscala/reflect/generic/Trees$Traverser;
	aload_0
	getfield	Field tpt$2:Lscala/reflect/generic/Trees$Tree;
	invokevirtual	Method scala/reflect/generic/Trees$Traverser.traverse:(Lscala/reflect/generic/Trees$Tree;)V
	aload_0
	getfield	Field $outer:Lscala/reflect/generic/Trees$Traverser;
	aload_0
	getfield	Field rhs$2:Lscala/reflect/generic/Trees$Tree;
	invokevirtual	Method scala/reflect/generic/Trees$Traverser.traverse:(Lscala/reflect/generic/Trees$Tree;)V
	return
  Labels:

public final java.lang.Object apply();
  Signature: ()Ljava/lang/Object;
  Code:
   Stack=1, Locals=1, Args_size=1
	aload_0
	invokevirtual	Method apply:()V
	getstatic	Field scala/runtime/BoxedUnit.UNIT:Lscala/runtime/BoxedUnit;
	areturn
  Labels:

public scala.reflect.generic.Trees$Traverser$$anonfun$traverse$5(scala.reflect.generic.Trees$Traverser, scala.reflect.generic.Trees$Modifiers, scala.collection.immutable.List, scala.collection.immutable.List, scala.reflect.generic.Trees$Tree, scala.reflect.generic.Trees$Tree);
  Signature: (Lscala/reflect/generic/Trees$Traverser;Lscala/reflect/generic/Trees$Modifiers;Lscala/collection/immutable/List;Lscala/collection/immutable/List;Lscala/reflect/generic/Trees$Tree;Lscala/reflect/generic/Trees$Tree;)V
  Code:
   Stack=2, Locals=7, Args_size=7
	aload_1
	ifnonnull	l1 // aload_0
	new	class java/lang/NullPointerException
	dup
	invokespecial	Method java/lang/NullPointerException."<init>":()V
	athrow
l1	aload_0
	aload_1
	putfield	Field $outer:Lscala/reflect/generic/Trees$Traverser;
	aload_0
	aload_2
	putfield	Field mods$4:Lscala/reflect/generic/Trees$Modifiers;
	aload_0
	aload_3
	putfield	Field tparams$2:Lscala/collection/immutable/List;
	aload_0
	aload	4
	putfield	Field vparamss$1:Lscala/collection/immutable/List;
	aload_0
	aload	5
	putfield	Field tpt$2:Lscala/reflect/generic/Trees$Tree;
	aload_0
	aload	6
	putfield	Field rhs$2:Lscala/reflect/generic/Trees$Tree;
	aload_0
	invokespecial	Method scala/runtime/AbstractFunction0."<init>":()V
	return
  Labels:
   	l1 = 12 // aload_0
  LocalVariableTable: 
   Start  Length  Slot  Name   Signature
   0      50      0    this       Lscala/reflect/generic/Trees$Traverser$$anonfun$traverse$5;
   0      50      1    $outer       Lscala/reflect/generic/Trees$Traverser;


}

