Compiled from "Trees.scala"
public abstract class scala.reflect.generic.Trees$MemberDef extends scala.reflect.generic.Trees$DefTree implements scala.ScalaObject
  SourceFile: "Trees.scala"
  Scala: length = 0x
   
  InnerClass: 
   public abstract Tree=class scala/reflect/generic/Trees$Tree of class scala/reflect/generic/Trees
   public ValDef=class scala/reflect/generic/Trees$ValDef of class scala/reflect/generic/Trees
   public DefDef=class scala/reflect/generic/Trees$DefDef of class scala/reflect/generic/Trees
   public TypeDef=class scala/reflect/generic/Trees$TypeDef of class scala/reflect/generic/Trees
   public abstract DefTree=class scala/reflect/generic/Trees$DefTree of class scala/reflect/generic/Trees
   public ClassDef=class scala/reflect/generic/Trees$ClassDef of class scala/reflect/generic/Trees
   public ModuleDef=class scala/reflect/generic/Trees$ModuleDef of class scala/reflect/generic/Trees
   public Modifiers=class scala/reflect/generic/Trees$Modifiers of class scala/reflect/generic/Trees
   public abstract MemberDef=class scala/reflect/generic/Trees$MemberDef of class scala/reflect/generic/Trees
   public PackageDef=class scala/reflect/generic/Trees$PackageDef of class scala/reflect/generic/Trees
  minor version: 0
  major version: 49
  Constant pool:
Asciz	SourceFile;
Asciz	Trees.scala;
Asciz	mods;
Asciz	()Lscala/reflect/generic/Trees$Modifiers;;
Asciz	keyword;
Asciz	()Ljava/lang/String;;
Asciz	Code;
Asciz	LineNumberTable;
Asciz	scala/reflect/generic/Trees$TypeDef;
class	scala/reflect/generic/Trees$TypeDef
Asciz	type;
String	type
Asciz	scala/reflect/generic/Trees$ClassDef;
class	scala/reflect/generic/Trees$ClassDef
NameAndType	mods:()Lscala/reflect/generic/Trees$Modifiers;
Method	scala/reflect/generic/Trees$ClassDef.mods:()Lscala/reflect/generic/Trees$Modifiers;
Asciz	scala/reflect/generic/Trees$Modifiers;
class	scala/reflect/generic/Trees$Modifiers
Asciz	isTrait;
Asciz	()Z;
NameAndType	isTrait:()Z
Method	scala/reflect/generic/Trees$Modifiers.isTrait:()Z
Asciz	trait;
String	trait
Asciz	class;
String	class
Asciz	scala/reflect/generic/Trees$DefDef;
class	scala/reflect/generic/Trees$DefDef
Asciz	def;
String	def
Asciz	scala/reflect/generic/Trees$ModuleDef;
class	scala/reflect/generic/Trees$ModuleDef
Asciz	object;
String	object
Asciz	scala/reflect/generic/Trees$PackageDef;
class	scala/reflect/generic/Trees$PackageDef
Asciz	package;
String	package
Asciz	scala/reflect/generic/Trees$ValDef;
class	scala/reflect/generic/Trees$ValDef
Method	scala/reflect/generic/Trees$ValDef.mods:()Lscala/reflect/generic/Trees$Modifiers;
Asciz	isVariable;
NameAndType	isVariable:()Z
Method	scala/reflect/generic/Trees$Modifiers.isVariable:()Z
Asciz	var;
String	var
Asciz	val;
String	val
Asciz	;
String	
Asciz	this;
Asciz	Lscala/reflect/generic/Trees$MemberDef;;
Asciz	temp16;
Asciz	LocalVariableTable;
Asciz	hasFlag;
Asciz	(J)Z;
Asciz	scala/reflect/generic/Trees$MemberDef;
class	scala/reflect/generic/Trees$MemberDef
Method	scala/reflect/generic/Trees$MemberDef.mods:()Lscala/reflect/generic/Trees$Modifiers;
Asciz	flags;
Asciz	()J;
NameAndType	flags:()J
Method	scala/reflect/generic/Trees$Modifiers.flags:()J
Asciz	mask;
Asciz	J;
Asciz	scala$reflect$generic$Trees$MemberDef$$$outer;
Asciz	()Lscala/reflect/generic/Universe;;
Asciz	scala/reflect/generic/Trees$Tree;
class	scala/reflect/generic/Trees$Tree
Asciz	$outer;
Asciz	Lscala/reflect/generic/Universe;;
NameAndType	$outer:Lscala/reflect/generic/Universe;
Field	scala/reflect/generic/Trees$Tree.$outer:Lscala/reflect/generic/Universe;
Asciz	<init>;
Asciz	(Lscala/reflect/generic/Universe;)V;
Asciz	scala/reflect/generic/Trees$DefTree;
class	scala/reflect/generic/Trees$DefTree
NameAndType	"<init>":(Lscala/reflect/generic/Universe;)V
Method	scala/reflect/generic/Trees$DefTree."<init>":(Lscala/reflect/generic/Universe;)V
Asciz	Scala;
Asciz	InnerClasses;
Asciz	scala/reflect/generic/Trees;
class	scala/reflect/generic/Trees
Asciz	Tree;
Asciz	ValDef;
Asciz	DefDef;
Asciz	TypeDef;
Asciz	DefTree;
Asciz	ClassDef;
Asciz	ModuleDef;
Asciz	Modifiers;
Asciz	MemberDef;
Asciz	PackageDef;
Asciz	scala/ScalaObject;
class	scala/ScalaObject

{
public abstract scala.reflect.generic.Trees$Modifiers mods();
  Signature: ()Lscala/reflect/generic/Trees$Modifiers;

public java.lang.String keyword();
  Signature: ()Ljava/lang/String;
  Code:
   Stack=1, Locals=2, Args_size=1
	aload_0
	astore_1
	aload_1
	instanceof	class scala/reflect/generic/Trees$TypeDef
	ifeq	l1 // aload_1
	ldc	String type
	goto	l2 // areturn
l1	aload_1
	instanceof	class scala/reflect/generic/Trees$ClassDef
	ifeq	l3 // aload_1
	aload_1
	checkcast	class scala/reflect/generic/Trees$ClassDef
	invokevirtual	Method scala/reflect/generic/Trees$ClassDef.mods:()Lscala/reflect/generic/Trees$Modifiers;
	invokevirtual	Method scala/reflect/generic/Trees$Modifiers.isTrait:()Z
	ifeq	l4 // ldc
	ldc	String trait
	goto	l2 // areturn
l4	ldc	String class
	goto	l2 // areturn
l3	aload_1
	instanceof	class scala/reflect/generic/Trees$DefDef
	ifeq	l5 // aload_1
	ldc	String def
	goto	l2 // areturn
l5	aload_1
	instanceof	class scala/reflect/generic/Trees$ModuleDef
	ifeq	l6 // aload_1
	ldc	String object
	goto	l2 // areturn
l6	aload_1
	instanceof	class scala/reflect/generic/Trees$PackageDef
	ifeq	l7 // aload_1
	ldc	String package
	goto	l2 // areturn
l7	aload_1
	instanceof	class scala/reflect/generic/Trees$ValDef
	ifeq	l8 // ldc
	aload_1
	checkcast	class scala/reflect/generic/Trees$ValDef
	invokevirtual	Method scala/reflect/generic/Trees$ValDef.mods:()Lscala/reflect/generic/Trees$Modifiers;
	invokevirtual	Method scala/reflect/generic/Trees$Modifiers.isVariable:()Z
	ifeq	l9 // ldc
	ldc	String var
	goto	l2 // areturn
l9	ldc	String val
	goto	l2 // areturn
l8	ldc	String 
l2	areturn
  Labels:
   	l1 = 14 // aload_1
   	l4 = 39 // ldc
   	l3 = 44 // aload_1
   	l5 = 56 // aload_1
   	l6 = 68 // aload_1
   	l7 = 80 // aload_1
   	l9 = 105 // ldc
   	l8 = 110 // ldc
   	l2 = 112 // areturn
  LocalVariableTable: 
   Start  Length  Slot  Name   Signature
   0      113      0    this       Lscala/reflect/generic/Trees$MemberDef;
   2      111      1    temp16       Lscala/reflect/generic/Trees$MemberDef;


public final boolean hasFlag(long);
  Signature: (J)Z
  Code:
   Stack=4, Locals=3, Args_size=2
	aload_0
	invokevirtual	Method mods:()Lscala/reflect/generic/Trees$Modifiers;
	invokevirtual	Method scala/reflect/generic/Trees$Modifiers.flags:()J
	lload_1
	land
	lconst_0
	lcmp
	ifeq	l1 // iconst_0
	iconst_1
	goto	l2 // ireturn
l1	iconst_0
l2	ireturn
  Labels:
   	l1 = 18 // iconst_0
   	l2 = 19 // ireturn
  LocalVariableTable: 
   Start  Length  Slot  Name   Signature
   0      20      0    this       Lscala/reflect/generic/Trees$MemberDef;
   0      20      1    mask       J


public scala.reflect.generic.Universe scala$reflect$generic$Trees$MemberDef$$$outer();
  Signature: ()Lscala/reflect/generic/Universe;
  Code:
   Stack=1, Locals=1, Args_size=1
	aload_0
	getfield	Field scala/reflect/generic/Trees$Tree.$outer:Lscala/reflect/generic/Universe;
	areturn
  Labels:

public scala.reflect.generic.Trees$MemberDef(scala.reflect.generic.Universe);
  Signature: (Lscala/reflect/generic/Universe;)V
  Code:
   Stack=2, Locals=2, Args_size=2
	aload_0
	aload_1
	invokespecial	Method scala/reflect/generic/Trees$DefTree."<init>":(Lscala/reflect/generic/Universe;)V
	return
  Labels:
  LocalVariableTable: 
   Start  Length  Slot  Name   Signature
   0      6      0    this       Lscala/reflect/generic/Trees$MemberDef;
   0      6      1    $outer       Lscala/reflect/generic/Universe;


}

