Compiled from "Trees.scala"
public class scala.reflect.generic.Trees$CompoundTypeTree extends scala.reflect.generic.Trees$Tree implements scala.reflect.generic.Trees$TypTree,scala.ScalaObject,scala.Product,java.io.Serializable
  SourceFile: "Trees.scala"
  Scala: length = 0x
   
  InnerClass: 
   public abstract Tree=class scala/reflect/generic/Trees$Tree of class scala/reflect/generic/Trees
   public abstract TypTree=class scala/reflect/generic/Trees$TypTree of class scala/reflect/generic/Trees
   public Template=class scala/reflect/generic/Trees$Template of class scala/reflect/generic/Trees
   public CompoundTypeTree=class scala/reflect/generic/Trees$CompoundTypeTree of class scala/reflect/generic/Trees
  minor version: 0
  major version: 49
  Constant pool:
Asciz	SourceFile;
Asciz	Trees.scala;
Asciz	templ;
Asciz	Lscala/reflect/generic/Trees$Template;;
Asciz	copy$default$1;
Asciz	()Lscala/reflect/generic/Trees$Template;;
Asciz	Code;
Asciz	LineNumberTable;
Asciz	scala/reflect/generic/Trees$CompoundTypeTree;
class	scala/reflect/generic/Trees$CompoundTypeTree
NameAndType	templ:()Lscala/reflect/generic/Trees$Template;
Method	scala/reflect/generic/Trees$CompoundTypeTree.templ:()Lscala/reflect/generic/Trees$Template;
NameAndType	templ:Lscala/reflect/generic/Trees$Template;
Field	scala/reflect/generic/Trees$CompoundTypeTree.templ:Lscala/reflect/generic/Trees$Template;
Asciz	copy;
Asciz	(Lscala/reflect/generic/Trees$Template;)Lscala/reflect/generic/Trees$CompoundTypeTree;;
Asciz	scala$reflect$generic$Trees$CompoundTypeTree$$$outer;
Asciz	()Lscala/reflect/generic/Universe;;
NameAndType	scala$reflect$generic$Trees$CompoundTypeTree$$$outer:()Lscala/reflect/generic/Universe;
Method	scala/reflect/generic/Trees$CompoundTypeTree.scala$reflect$generic$Trees$CompoundTypeTree$$$outer:()Lscala/reflect/generic/Universe;
Asciz	<init>;
Asciz	(Lscala/reflect/generic/Universe;Lscala/reflect/generic/Trees$Template;)V;
NameAndType	"<init>":(Lscala/reflect/generic/Universe;Lscala/reflect/generic/Trees$Template;)V
Method	scala/reflect/generic/Trees$CompoundTypeTree."<init>":(Lscala/reflect/generic/Universe;Lscala/reflect/generic/Trees$Template;)V
Asciz	this;
Asciz	Lscala/reflect/generic/Trees$CompoundTypeTree;;
Asciz	LocalVariableTable;
Asciz	productPrefix;
Asciz	()Ljava/lang/String;;
Asciz	CompoundTypeTree;
String	CompoundTypeTree
Asciz	productArity;
Asciz	()I;
Asciz	productElement;
Asciz	(I)Ljava/lang/Object;;
Asciz	java/lang/IndexOutOfBoundsException;
class	java/lang/IndexOutOfBoundsException
Asciz	scala/runtime/BoxesRunTime;
class	scala/runtime/BoxesRunTime
Asciz	boxToInteger;
Asciz	(I)Ljava/lang/Integer;;
NameAndType	boxToInteger:(I)Ljava/lang/Integer;
Method	scala/runtime/BoxesRunTime.boxToInteger:(I)Ljava/lang/Integer;
Asciz	java/lang/Object;
class	java/lang/Object
Asciz	toString;
NameAndType	toString:()Ljava/lang/String;
Method	java/lang/Object.toString:()Ljava/lang/String;
Asciz	(Ljava/lang/String;)V;
NameAndType	"<init>":(Ljava/lang/String;)V
Method	java/lang/IndexOutOfBoundsException."<init>":(Ljava/lang/String;)V
Asciz	productElementName;
Asciz	(I)Ljava/lang/String;;
String	templ
Asciz	canEqual;
Asciz	(Ljava/lang/Object;)Z;
Asciz	scala/reflect/generic/Trees$Tree;
class	scala/reflect/generic/Trees$Tree
Asciz	$outer;
Asciz	Lscala/reflect/generic/Universe;;
NameAndType	$outer:Lscala/reflect/generic/Universe;
Field	scala/reflect/generic/Trees$Tree.$outer:Lscala/reflect/generic/Universe;
Asciz	(Lscala/reflect/generic/Universe;)V;
NameAndType	"<init>":(Lscala/reflect/generic/Universe;)V
Method	scala/reflect/generic/Trees$Tree."<init>":(Lscala/reflect/generic/Universe;)V
Asciz	Scala;
Asciz	InnerClasses;
Asciz	scala/reflect/generic/Trees;
class	scala/reflect/generic/Trees
Asciz	Tree;
Asciz	scala/reflect/generic/Trees$TypTree;
class	scala/reflect/generic/Trees$TypTree
Asciz	TypTree;
Asciz	scala/reflect/generic/Trees$Template;
class	scala/reflect/generic/Trees$Template
Asciz	Template;
Asciz	scala/ScalaObject;
class	scala/ScalaObject
Asciz	scala/Product;
class	scala/Product
Asciz	java/io/Serializable;
class	java/io/Serializable

{
private final scala.reflect.generic.Trees$Template templ;
  Signature: Lscala/reflect/generic/Trees$Template;

public scala.reflect.generic.Trees$Template copy$default$1();
  Signature: ()Lscala/reflect/generic/Trees$Template;
  Code:
   Stack=1, Locals=1, Args_size=1
	aload_0
	invokevirtual	Method templ:()Lscala/reflect/generic/Trees$Template;
	areturn
  Labels:

public scala.reflect.generic.Trees$Template templ();
  Signature: ()Lscala/reflect/generic/Trees$Template;
  Code:
   Stack=1, Locals=1, Args_size=1
	aload_0
	getfield	Field templ:Lscala/reflect/generic/Trees$Template;
	areturn
  Labels:

public scala.reflect.generic.Trees$CompoundTypeTree copy(scala.reflect.generic.Trees$Template);
  Signature: (Lscala/reflect/generic/Trees$Template;)Lscala/reflect/generic/Trees$CompoundTypeTree;
  Code:
   Stack=4, Locals=2, Args_size=2
	new	class scala/reflect/generic/Trees$CompoundTypeTree
	dup
	aload_0
	invokevirtual	Method scala$reflect$generic$Trees$CompoundTypeTree$$$outer:()Lscala/reflect/generic/Universe;
	aload_1
	invokespecial	Method "<init>":(Lscala/reflect/generic/Universe;Lscala/reflect/generic/Trees$Template;)V
	areturn
  Labels:
  LocalVariableTable: 
   Start  Length  Slot  Name   Signature
   0      13      0    this       Lscala/reflect/generic/Trees$CompoundTypeTree;
   0      13      1    templ       Lscala/reflect/generic/Trees$Template;


public java.lang.String productPrefix();
  Signature: ()Ljava/lang/String;
  Code:
   Stack=1, Locals=1, Args_size=1
	ldc	String CompoundTypeTree
	areturn
  Labels:

public int productArity();
  Signature: ()I
  Code:
   Stack=1, Locals=1, Args_size=1
	iconst_1
	ireturn
  Labels:

public java.lang.Object productElement(int);
  Signature: (I)Ljava/lang/Object;
  Code:
   Stack=3, Locals=2, Args_size=2
	iload_1
	iconst_0
	if_icmpne	l1 // new
	aload_0
	invokevirtual	Method templ:()Lscala/reflect/generic/Trees$Template;
	areturn
l1	new	class java/lang/IndexOutOfBoundsException
	dup
	iload_1
	invokestatic	Method scala/runtime/BoxesRunTime.boxToInteger:(I)Ljava/lang/Integer;
	invokevirtual	Method java/lang/Object.toString:()Ljava/lang/String;
	invokespecial	Method java/lang/IndexOutOfBoundsException."<init>":(Ljava/lang/String;)V
	athrow
  Labels:
   	l1 = 10 // new

public java.lang.String productElementName(int);
  Signature: (I)Ljava/lang/String;
  Code:
   Stack=3, Locals=2, Args_size=2
	iload_1
	iconst_0
	if_icmpne	l1 // new
	ldc	String templ
	areturn
l1	new	class java/lang/IndexOutOfBoundsException
	dup
	iload_1
	invokestatic	Method scala/runtime/BoxesRunTime.boxToInteger:(I)Ljava/lang/Integer;
	invokevirtual	Method java/lang/Object.toString:()Ljava/lang/String;
	invokespecial	Method java/lang/IndexOutOfBoundsException."<init>":(Ljava/lang/String;)V
	athrow
  Labels:
   	l1 = 8 // new

public boolean canEqual(java.lang.Object);
  Signature: (Ljava/lang/Object;)Z
  Code:
   Stack=1, Locals=2, Args_size=2
	aload_1
	instanceof	class scala/reflect/generic/Trees$CompoundTypeTree
	ireturn
  Labels:

public scala.reflect.generic.Universe scala$reflect$generic$Trees$CompoundTypeTree$$$outer();
  Signature: ()Lscala/reflect/generic/Universe;
  Code:
   Stack=1, Locals=1, Args_size=1
	aload_0
	getfield	Field scala/reflect/generic/Trees$Tree.$outer:Lscala/reflect/generic/Universe;
	areturn
  Labels:

public scala.reflect.generic.Trees$CompoundTypeTree(scala.reflect.generic.Universe, scala.reflect.generic.Trees$Template);
  Signature: (Lscala/reflect/generic/Universe;Lscala/reflect/generic/Trees$Template;)V
  Code:
   Stack=2, Locals=3, Args_size=3
	aload_0
	aload_2
	putfield	Field templ:Lscala/reflect/generic/Trees$Template;
	aload_0
	aload_1
	invokespecial	Method scala/reflect/generic/Trees$Tree."<init>":(Lscala/reflect/generic/Universe;)V
	return
  Labels:
  LocalVariableTable: 
   Start  Length  Slot  Name   Signature
   0      11      0    this       Lscala/reflect/generic/Trees$CompoundTypeTree;
   0      11      1    $outer       Lscala/reflect/generic/Universe;
   0      11      2    templ       Lscala/reflect/generic/Trees$Template;


}

