Compiled from "Trees.scala"
public final class scala.reflect.generic.Trees$SelectFromArray$ extends java.lang.Object implements scala.Function3,scala.ScalaObject
  SourceFile: "Trees.scala"
  Scala: length = 0x
   
  InnerClass: 
   public abstract Tree=class scala/reflect/generic/Trees$Tree of class scala/reflect/generic/Trees
   public abstract AbsType=class scala/reflect/generic/Types$AbsType of class scala/reflect/generic/Types
   public SelectFromArray=class scala/reflect/generic/Trees$SelectFromArray of class scala/reflect/generic/Trees
  minor version: 0
  major version: 49
  Constant pool:
Asciz	SourceFile;
Asciz	Trees.scala;
Asciz	Scala;
Asciz	$outer;
Asciz	Lscala/reflect/generic/Universe;;
Asciz	toString;
Asciz	()Ljava/lang/String;;
Asciz	Code;
Asciz	LineNumberTable;
Asciz	scala/Function3$class;
class	scala/Function3$class
Asciz	(Lscala/Function3;)Ljava/lang/String;;
NameAndType	toString:(Lscala/Function3;)Ljava/lang/String;
Method	scala/Function3$class.toString:(Lscala/Function3;)Ljava/lang/String;
Asciz	curried;
Asciz	()Lscala/Function1;;
Asciz	(Lscala/Function3;)Lscala/Function1;;
NameAndType	curried:(Lscala/Function3;)Lscala/Function1;
Method	scala/Function3$class.curried:(Lscala/Function3;)Lscala/Function1;
Asciz	curry;
NameAndType	curry:(Lscala/Function3;)Lscala/Function1;
Method	scala/Function3$class.curry:(Lscala/Function3;)Lscala/Function1;
Asciz	Deprecated;
Asciz	tupled;
NameAndType	tupled:(Lscala/Function3;)Lscala/Function1;
Method	scala/Function3$class.tupled:(Lscala/Function3;)Lscala/Function1;
Asciz	unapply;
Asciz	(Lscala/reflect/generic/Trees$SelectFromArray;)Lscala/Some;;
Asciz	scala/Some;
class	scala/Some
Asciz	scala/Tuple3;
class	scala/Tuple3
Asciz	scala/reflect/generic/Trees$SelectFromArray;
class	scala/reflect/generic/Trees$SelectFromArray
Asciz	qualifier;
Asciz	()Lscala/reflect/generic/Trees$Tree;;
NameAndType	qualifier:()Lscala/reflect/generic/Trees$Tree;
Method	scala/reflect/generic/Trees$SelectFromArray.qualifier:()Lscala/reflect/generic/Trees$Tree;
Asciz	name;
Asciz	()Ljava/lang/Object;;
NameAndType	name:()Ljava/lang/Object;
Method	scala/reflect/generic/Trees$SelectFromArray.name:()Ljava/lang/Object;
Asciz	erasure;
Asciz	()Lscala/reflect/generic/Types$AbsType;;
NameAndType	erasure:()Lscala/reflect/generic/Types$AbsType;
Method	scala/reflect/generic/Trees$SelectFromArray.erasure:()Lscala/reflect/generic/Types$AbsType;
Asciz	<init>;
Asciz	(Ljava/lang/Object;Ljava/lang/Object;Ljava/lang/Object;)V;
NameAndType	"<init>":(Ljava/lang/Object;Ljava/lang/Object;Ljava/lang/Object;)V
Method	scala/Tuple3."<init>":(Ljava/lang/Object;Ljava/lang/Object;Ljava/lang/Object;)V
Asciz	(Ljava/lang/Object;)V;
NameAndType	"<init>":(Ljava/lang/Object;)V
Method	scala/Some."<init>":(Ljava/lang/Object;)V
Asciz	this;
Asciz	Lscala/reflect/generic/Trees$SelectFromArray$;;
Asciz	x$0;
Asciz	Lscala/reflect/generic/Trees$SelectFromArray;;
Asciz	LocalVariableTable;
Asciz	apply;
Asciz	(Lscala/reflect/generic/Trees$Tree;Ljava/lang/Object;Lscala/reflect/generic/Types$AbsType;)Lscala/reflect/generic/Trees$SelectFromArray;;
Asciz	scala/reflect/generic/Trees$SelectFromArray$;
class	scala/reflect/generic/Trees$SelectFromArray$
NameAndType	$outer:Lscala/reflect/generic/Universe;
Field	scala/reflect/generic/Trees$SelectFromArray$.$outer:Lscala/reflect/generic/Universe;
Asciz	(Lscala/reflect/generic/Universe;Lscala/reflect/generic/Trees$Tree;Ljava/lang/Object;Lscala/reflect/generic/Types$AbsType;)V;
NameAndType	"<init>":(Lscala/reflect/generic/Universe;Lscala/reflect/generic/Trees$Tree;Ljava/lang/Object;Lscala/reflect/generic/Types$AbsType;)V
Method	scala/reflect/generic/Trees$SelectFromArray."<init>":(Lscala/reflect/generic/Universe;Lscala/reflect/generic/Trees$Tree;Ljava/lang/Object;Lscala/reflect/generic/Types$AbsType;)V
Asciz	Lscala/reflect/generic/Trees$Tree;;
Asciz	Ljava/lang/Object;;
Asciz	Lscala/reflect/generic/Types$AbsType;;
Asciz	(Ljava/lang/Object;Ljava/lang/Object;Ljava/lang/Object;)Ljava/lang/Object;;
Asciz	scala/reflect/generic/Trees$Tree;
class	scala/reflect/generic/Trees$Tree
Asciz	scala/reflect/generic/Types$AbsType;
class	scala/reflect/generic/Types$AbsType
NameAndType	apply:(Lscala/reflect/generic/Trees$Tree;Ljava/lang/Object;Lscala/reflect/generic/Types$AbsType;)Lscala/reflect/generic/Trees$SelectFromArray;
Method	scala/reflect/generic/Trees$SelectFromArray$.apply:(Lscala/reflect/generic/Trees$Tree;Ljava/lang/Object;Lscala/reflect/generic/Types$AbsType;)Lscala/reflect/generic/Trees$SelectFromArray;
Asciz	v1;
Asciz	v2;
Asciz	v3;
Asciz	(Lscala/reflect/generic/Universe;)V;
Asciz	java/lang/NullPointerException;
class	java/lang/NullPointerException
Asciz	()V;
NameAndType	"<init>":()V
Method	java/lang/NullPointerException."<init>":()V
Asciz	java/lang/Object;
class	java/lang/Object
Method	java/lang/Object."<init>":()V
Asciz	$init$;
Asciz	(Lscala/Function3;)V;
NameAndType	$init$:(Lscala/Function3;)V
Method	scala/Function3$class.$init$:(Lscala/Function3;)V
Asciz	InnerClasses;
Asciz	scala/reflect/generic/Trees;
class	scala/reflect/generic/Trees
Asciz	Tree;
Asciz	scala/reflect/generic/Types;
class	scala/reflect/generic/Types
Asciz	AbsType;
Asciz	SelectFromArray;
Asciz	scala/Function3;
class	scala/Function3
Asciz	scala/ScalaObject;
class	scala/ScalaObject

{
public final scala.reflect.generic.Universe $outer;
  Signature: Lscala/reflect/generic/Universe;

public java.lang.String toString();
  Signature: ()Ljava/lang/String;
  Code:
   Stack=1, Locals=1, Args_size=1
	aload_0
	invokestatic	Method scala/Function3$class.toString:(Lscala/Function3;)Ljava/lang/String;
	areturn
  Labels:

public scala.Function1 curried();
  Signature: ()Lscala/Function1;
  Code:
   Stack=1, Locals=1, Args_size=1
	aload_0
	invokestatic	Method scala/Function3$class.curried:(Lscala/Function3;)Lscala/Function1;
	areturn
  Labels:

public scala.Function1 curry();
  Signature: ()Lscala/Function1;
  Code:
   Stack=1, Locals=1, Args_size=1
	aload_0
	invokestatic	Method scala/Function3$class.curry:(Lscala/Function3;)Lscala/Function1;
	areturn
  Labels:
  Deprecated: true

public scala.Function1 tupled();
  Signature: ()Lscala/Function1;
  Code:
   Stack=1, Locals=1, Args_size=1
	aload_0
	invokestatic	Method scala/Function3$class.tupled:(Lscala/Function3;)Lscala/Function1;
	areturn
  Labels:

public scala.Some unapply(scala.reflect.generic.Trees$SelectFromArray);
  Signature: (Lscala/reflect/generic/Trees$SelectFromArray;)Lscala/Some;
  Code:
   Stack=7, Locals=2, Args_size=2
	new	class scala/Some
	dup
	new	class scala/Tuple3
	dup
	aload_1
	invokevirtual	Method scala/reflect/generic/Trees$SelectFromArray.qualifier:()Lscala/reflect/generic/Trees$Tree;
	aload_1
	invokevirtual	Method scala/reflect/generic/Trees$SelectFromArray.name:()Ljava/lang/Object;
	aload_1
	invokevirtual	Method scala/reflect/generic/Trees$SelectFromArray.erasure:()Lscala/reflect/generic/Types$AbsType;
	invokespecial	Method scala/Tuple3."<init>":(Ljava/lang/Object;Ljava/lang/Object;Ljava/lang/Object;)V
	invokespecial	Method scala/Some."<init>":(Ljava/lang/Object;)V
	areturn
  Labels:
  LocalVariableTable: 
   Start  Length  Slot  Name   Signature
   0      27      0    this       Lscala/reflect/generic/Trees$SelectFromArray$;
   0      27      1    x$0       Lscala/reflect/generic/Trees$SelectFromArray;


public scala.reflect.generic.Trees$SelectFromArray apply(scala.reflect.generic.Trees$Tree, java.lang.Object, scala.reflect.generic.Types$AbsType);
  Signature: (Lscala/reflect/generic/Trees$Tree;Ljava/lang/Object;Lscala/reflect/generic/Types$AbsType;)Lscala/reflect/generic/Trees$SelectFromArray;
  Code:
   Stack=6, Locals=5, Args_size=4
	aload_0
	getfield	Field $outer:Lscala/reflect/generic/Universe;
	astore	4
	new	class scala/reflect/generic/Trees$SelectFromArray
	dup
	aload_0
	getfield	Field $outer:Lscala/reflect/generic/Universe;
	aload_1
	aload_2
	aload_3
	invokespecial	Method scala/reflect/generic/Trees$SelectFromArray."<init>":(Lscala/reflect/generic/Universe;Lscala/reflect/generic/Trees$Tree;Ljava/lang/Object;Lscala/reflect/generic/Types$AbsType;)V
	areturn
  Labels:
  LocalVariableTable: 
   Start  Length  Slot  Name   Signature
   0      21      0    this       Lscala/reflect/generic/Trees$SelectFromArray$;
   6      15      1    qualifier       Lscala/reflect/generic/Trees$Tree;
   6      15      2    name       Ljava/lang/Object;
   6      15      3    erasure       Lscala/reflect/generic/Types$AbsType;


public java.lang.Object apply(java.lang.Object, java.lang.Object, java.lang.Object);
  Signature: (Ljava/lang/Object;Ljava/lang/Object;Ljava/lang/Object;)Ljava/lang/Object;
  Code:
   Stack=4, Locals=5, Args_size=4
	aload_0
	getfield	Field $outer:Lscala/reflect/generic/Universe;
	astore	4
	aload_0
	aload_1
	checkcast	class scala/reflect/generic/Trees$Tree
	aload_2
	aload_3
	checkcast	class scala/reflect/generic/Types$AbsType
	invokevirtual	Method apply:(Lscala/reflect/generic/Trees$Tree;Ljava/lang/Object;Lscala/reflect/generic/Types$AbsType;)Lscala/reflect/generic/Trees$SelectFromArray;
	areturn
  Labels:
  LocalVariableTable: 
   Start  Length  Slot  Name   Signature
   0      20      0    this       Lscala/reflect/generic/Trees$SelectFromArray$;
   6      14      1    v1       Ljava/lang/Object;
   6      14      2    v2       Ljava/lang/Object;
   6      14      3    v3       Ljava/lang/Object;


public scala.reflect.generic.Trees$SelectFromArray$(scala.reflect.generic.Universe);
  Signature: (Lscala/reflect/generic/Universe;)V
  Code:
   Stack=2, Locals=2, Args_size=2
	aload_1
	ifnonnull	l1 // aload_0
	new	class java/lang/NullPointerException
	dup
	invokespecial	Method java/lang/NullPointerException."<init>":()V
	athrow
l1	aload_0
	aload_1
	putfield	Field $outer:Lscala/reflect/generic/Universe;
	aload_0
	invokespecial	Method java/lang/Object."<init>":()V
	aload_0
	invokestatic	Method scala/Function3$class.$init$:(Lscala/Function3;)V
	return
  Labels:
   	l1 = 12 // aload_0
  LocalVariableTable: 
   Start  Length  Slot  Name   Signature
   0      26      0    this       Lscala/reflect/generic/Trees$SelectFromArray$;
   0      26      1    $outer       Lscala/reflect/generic/Universe;


}

