Compiled from "Trees.scala"
public class scala.reflect.generic.Trees$ImportSelector extends java.lang.Object implements scala.ScalaObject,scala.Product,java.io.Serializable
  SourceFile: "Trees.scala"
  Scala: length = 0x
   
  InnerClass: 
   public ImportSelector=class scala/reflect/generic/Trees$ImportSelector of class scala/reflect/generic/Trees
  minor version: 0
  major version: 49
  Constant pool:
Asciz	SourceFile;
Asciz	Trees.scala;
Asciz	$outer;
Asciz	Lscala/reflect/generic/Universe;;
Asciz	renamePos;
Asciz	I;
Asciz	rename;
Asciz	Ljava/lang/Object;;
Asciz	namePos;
Asciz	name;
Asciz	productIterator;
Asciz	()Lscala/collection/Iterator;;
Asciz	Code;
Asciz	LineNumberTable;
Asciz	scala/Product$class;
class	scala/Product$class
Asciz	(Lscala/Product;)Lscala/collection/Iterator;;
NameAndType	productIterator:(Lscala/Product;)Lscala/collection/Iterator;
Method	scala/Product$class.productIterator:(Lscala/Product;)Lscala/collection/Iterator;
Asciz	productElements;
NameAndType	productElements:(Lscala/Product;)Lscala/collection/Iterator;
Method	scala/Product$class.productElements:(Lscala/Product;)Lscala/collection/Iterator;
Asciz	Deprecated;
Asciz	copy$default$4;
Asciz	()I;
Asciz	scala/reflect/generic/Trees$ImportSelector;
class	scala/reflect/generic/Trees$ImportSelector
NameAndType	renamePos:()I
Method	scala/reflect/generic/Trees$ImportSelector.renamePos:()I
Asciz	copy$default$3;
Asciz	()Ljava/lang/Object;;
NameAndType	rename:()Ljava/lang/Object;
Method	scala/reflect/generic/Trees$ImportSelector.rename:()Ljava/lang/Object;
Asciz	copy$default$2;
NameAndType	namePos:()I
Method	scala/reflect/generic/Trees$ImportSelector.namePos:()I
Asciz	copy$default$1;
NameAndType	name:()Ljava/lang/Object;
Method	scala/reflect/generic/Trees$ImportSelector.name:()Ljava/lang/Object;
NameAndType	name:Ljava/lang/Object;
Field	scala/reflect/generic/Trees$ImportSelector.name:Ljava/lang/Object;
NameAndType	namePos:I
Field	scala/reflect/generic/Trees$ImportSelector.namePos:I
NameAndType	rename:Ljava/lang/Object;
Field	scala/reflect/generic/Trees$ImportSelector.rename:Ljava/lang/Object;
NameAndType	renamePos:I
Field	scala/reflect/generic/Trees$ImportSelector.renamePos:I
Asciz	copy;
Asciz	(Ljava/lang/Object;ILjava/lang/Object;I)Lscala/reflect/generic/Trees$ImportSelector;;
Asciz	scala$reflect$generic$Trees$ImportSelector$$$outer;
Asciz	()Lscala/reflect/generic/Universe;;
NameAndType	scala$reflect$generic$Trees$ImportSelector$$$outer:()Lscala/reflect/generic/Universe;
Method	scala/reflect/generic/Trees$ImportSelector.scala$reflect$generic$Trees$ImportSelector$$$outer:()Lscala/reflect/generic/Universe;
Asciz	<init>;
Asciz	(Lscala/reflect/generic/Universe;Ljava/lang/Object;ILjava/lang/Object;I)V;
NameAndType	"<init>":(Lscala/reflect/generic/Universe;Ljava/lang/Object;ILjava/lang/Object;I)V
Method	scala/reflect/generic/Trees$ImportSelector."<init>":(Lscala/reflect/generic/Universe;Ljava/lang/Object;ILjava/lang/Object;I)V
Asciz	this;
Asciz	Lscala/reflect/generic/Trees$ImportSelector;;
Asciz	LocalVariableTable;
Asciz	hashCode;
Asciz	scala/runtime/ScalaRunTime$;
class	scala/runtime/ScalaRunTime$
Asciz	MODULE$;
Asciz	Lscala/runtime/ScalaRunTime$;;
NameAndType	MODULE$:Lscala/runtime/ScalaRunTime$;
Field	scala/runtime/ScalaRunTime$.MODULE$:Lscala/runtime/ScalaRunTime$;
Asciz	_hashCode;
Asciz	(Lscala/Product;)I;
NameAndType	_hashCode:(Lscala/Product;)I
Method	scala/runtime/ScalaRunTime$._hashCode:(Lscala/Product;)I
Asciz	toString;
Asciz	()Ljava/lang/String;;
Asciz	_toString;
Asciz	(Lscala/Product;)Ljava/lang/String;;
NameAndType	_toString:(Lscala/Product;)Ljava/lang/String;
Method	scala/runtime/ScalaRunTime$._toString:(Lscala/Product;)Ljava/lang/String;
Asciz	equals;
Asciz	(Ljava/lang/Object;)Z;
Asciz	gd2$1;
Asciz	(Ljava/lang/Object;ILjava/lang/Object;I)Z;
NameAndType	gd2$1:(Ljava/lang/Object;ILjava/lang/Object;I)Z
Method	scala/reflect/generic/Trees$ImportSelector.gd2$1:(Ljava/lang/Object;ILjava/lang/Object;I)Z
Asciz	scala/Equals;
class	scala/Equals
Asciz	canEqual;
NameAndType	canEqual:(Ljava/lang/Object;)Z
InterfaceMethod	scala/Equals.canEqual:(Ljava/lang/Object;)Z
Asciz	temp52;
Asciz	temp53;
Asciz	temp54;
Asciz	temp55;
Asciz	temp56;
Asciz	productPrefix;
Asciz	ImportSelector;
String	ImportSelector
Asciz	productArity;
Asciz	productElement;
Asciz	(I)Ljava/lang/Object;;
Asciz	java/lang/IndexOutOfBoundsException;
class	java/lang/IndexOutOfBoundsException
Asciz	scala/runtime/BoxesRunTime;
class	scala/runtime/BoxesRunTime
Asciz	boxToInteger;
Asciz	(I)Ljava/lang/Integer;;
NameAndType	boxToInteger:(I)Ljava/lang/Integer;
Method	scala/runtime/BoxesRunTime.boxToInteger:(I)Ljava/lang/Integer;
Asciz	java/lang/Object;
class	java/lang/Object
NameAndType	toString:()Ljava/lang/String;
Method	java/lang/Object.toString:()Ljava/lang/String;
Asciz	(Ljava/lang/String;)V;
NameAndType	"<init>":(Ljava/lang/String;)V
Method	java/lang/IndexOutOfBoundsException."<init>":(Ljava/lang/String;)V
NameAndType	$outer:Lscala/reflect/generic/Universe;
Field	scala/reflect/generic/Trees$ImportSelector.$outer:Lscala/reflect/generic/Universe;
Asciz	java/lang/Number;
class	java/lang/Number
Asciz	java/lang/Character;
class	java/lang/Character
Asciz	equals2;
Asciz	(Ljava/lang/Object;Ljava/lang/Object;)Z;
NameAndType	equals2:(Ljava/lang/Object;Ljava/lang/Object;)Z
Method	scala/runtime/BoxesRunTime.equals2:(Ljava/lang/Object;Ljava/lang/Object;)Z
NameAndType	equals:(Ljava/lang/Object;)Z
Method	java/lang/Object.equals:(Ljava/lang/Object;)Z
Asciz	y0;
Asciz	y1;
Asciz	java/lang/NullPointerException;
class	java/lang/NullPointerException
Asciz	()V;
NameAndType	"<init>":()V
Method	java/lang/NullPointerException."<init>":()V
Method	java/lang/Object."<init>":()V
Asciz	$init$;
Asciz	(Lscala/Product;)V;
NameAndType	$init$:(Lscala/Product;)V
Method	scala/Product$class.$init$:(Lscala/Product;)V
Asciz	Scala;
Asciz	InnerClasses;
Asciz	scala/reflect/generic/Trees;
class	scala/reflect/generic/Trees
Asciz	scala/ScalaObject;
class	scala/ScalaObject
Asciz	scala/Product;
class	scala/Product
Asciz	java/io/Serializable;
class	java/io/Serializable

{
public final scala.reflect.generic.Universe $outer;
  Signature: Lscala/reflect/generic/Universe;

private final int renamePos;
  Signature: I

private final java.lang.Object rename;
  Signature: Ljava/lang/Object;

private final int namePos;
  Signature: I

private final java.lang.Object name;
  Signature: Ljava/lang/Object;

public scala.collection.Iterator productIterator();
  Signature: ()Lscala/collection/Iterator;
  Code:
   Stack=1, Locals=1, Args_size=1
	aload_0
	invokestatic	Method scala/Product$class.productIterator:(Lscala/Product;)Lscala/collection/Iterator;
	areturn
  Labels:

public scala.collection.Iterator productElements();
  Signature: ()Lscala/collection/Iterator;
  Code:
   Stack=1, Locals=1, Args_size=1
	aload_0
	invokestatic	Method scala/Product$class.productElements:(Lscala/Product;)Lscala/collection/Iterator;
	areturn
  Labels:
  Deprecated: true

public int copy$default$4();
  Signature: ()I
  Code:
   Stack=1, Locals=1, Args_size=1
	aload_0
	invokevirtual	Method renamePos:()I
	ireturn
  Labels:

public java.lang.Object copy$default$3();
  Signature: ()Ljava/lang/Object;
  Code:
   Stack=1, Locals=1, Args_size=1
	aload_0
	invokevirtual	Method rename:()Ljava/lang/Object;
	areturn
  Labels:

public int copy$default$2();
  Signature: ()I
  Code:
   Stack=1, Locals=1, Args_size=1
	aload_0
	invokevirtual	Method namePos:()I
	ireturn
  Labels:

public java.lang.Object copy$default$1();
  Signature: ()Ljava/lang/Object;
  Code:
   Stack=1, Locals=1, Args_size=1
	aload_0
	invokevirtual	Method name:()Ljava/lang/Object;
	areturn
  Labels:

public java.lang.Object name();
  Signature: ()Ljava/lang/Object;
  Code:
   Stack=1, Locals=1, Args_size=1
	aload_0
	getfield	Field name:Ljava/lang/Object;
	areturn
  Labels:

public int namePos();
  Signature: ()I
  Code:
   Stack=1, Locals=1, Args_size=1
	aload_0
	getfield	Field namePos:I
	ireturn
  Labels:

public java.lang.Object rename();
  Signature: ()Ljava/lang/Object;
  Code:
   Stack=1, Locals=1, Args_size=1
	aload_0
	getfield	Field rename:Ljava/lang/Object;
	areturn
  Labels:

public int renamePos();
  Signature: ()I
  Code:
   Stack=1, Locals=1, Args_size=1
	aload_0
	getfield	Field renamePos:I
	ireturn
  Labels:

public scala.reflect.generic.Trees$ImportSelector copy(java.lang.Object, int, java.lang.Object, int);
  Signature: (Ljava/lang/Object;ILjava/lang/Object;I)Lscala/reflect/generic/Trees$ImportSelector;
  Code:
   Stack=7, Locals=5, Args_size=5
	new	class scala/reflect/generic/Trees$ImportSelector
	dup
	aload_0
	invokevirtual	Method scala$reflect$generic$Trees$ImportSelector$$$outer:()Lscala/reflect/generic/Universe;
	aload_1
	iload_2
	aload_3
	iload	4
	invokespecial	Method "<init>":(Lscala/reflect/generic/Universe;Ljava/lang/Object;ILjava/lang/Object;I)V
	areturn
  Labels:
  LocalVariableTable: 
   Start  Length  Slot  Name   Signature
   0      17      0    this       Lscala/reflect/generic/Trees$ImportSelector;
   0      17      1    name       Ljava/lang/Object;
   0      17      2    namePos       I
   0      17      3    rename       Ljava/lang/Object;
   0      17      4    renamePos       I


public int hashCode();
  Signature: ()I
  Code:
   Stack=2, Locals=1, Args_size=1
	getstatic	Field scala/runtime/ScalaRunTime$.MODULE$:Lscala/runtime/ScalaRunTime$;
	aload_0
	invokevirtual	Method scala/runtime/ScalaRunTime$._hashCode:(Lscala/Product;)I
	ireturn
  Labels:

public java.lang.String toString();
  Signature: ()Ljava/lang/String;
  Code:
   Stack=2, Locals=1, Args_size=1
	getstatic	Field scala/runtime/ScalaRunTime$.MODULE$:Lscala/runtime/ScalaRunTime$;
	aload_0
	invokevirtual	Method scala/runtime/ScalaRunTime$._toString:(Lscala/Product;)Ljava/lang/String;
	areturn
  Labels:

public boolean equals(java.lang.Object);
  Signature: (Ljava/lang/Object;)Z
  Code:
   Stack=5, Locals=7, Args_size=2
	aload_0
	aload_1
	if_acmpeq	l1 // iconst_1
	aload_1
	instanceof	class scala/reflect/generic/Trees$ImportSelector
	ifeq	l2 // iconst_0
	aload_1
	checkcast	class scala/reflect/generic/Trees$ImportSelector
	invokevirtual	Method scala$reflect$generic$Trees$ImportSelector$$$outer:()Lscala/reflect/generic/Universe;
	aload_0
	invokevirtual	Method scala$reflect$generic$Trees$ImportSelector$$$outer:()Lscala/reflect/generic/Universe;
	if_acmpne	l2 // iconst_0
	aload_1
	checkcast	class scala/reflect/generic/Trees$ImportSelector
	astore_2
	aload_2
	invokevirtual	Method name:()Ljava/lang/Object;
	astore_3
	aload_2
	invokevirtual	Method namePos:()I
	istore	4
	aload_2
	invokevirtual	Method rename:()Ljava/lang/Object;
	astore	5
	aload_2
	invokevirtual	Method renamePos:()I
	istore	6
	aload_0
	aload_3
	iload	4
	aload	5
	iload	6
	invokespecial	Method gd2$1:(Ljava/lang/Object;ILjava/lang/Object;I)Z
	ifeq	l3 // iconst_0
	aload_1
	checkcast	class scala/reflect/generic/Trees$ImportSelector
	aload_0
	invokeinterface	InterfaceMethod scala/Equals.canEqual:(Ljava/lang/Object;)Z
	goto	l4 // ifeq
l3	iconst_0
	goto	l4 // ifeq
l2	iconst_0
l4	ifeq	l5 // iconst_0
l1	iconst_1
	goto	l6 // ireturn
l5	iconst_0
l6	ireturn
  Labels:
   	l3 = 81 // iconst_0
   	l2 = 85 // iconst_0
   	l4 = 86 // ifeq
   	l1 = 89 // iconst_1
   	l5 = 93 // iconst_0
   	l6 = 94 // ireturn
  LocalVariableTable: 
   Start  Length  Slot  Name   Signature
   0      95      0    this       Lscala/reflect/generic/Trees$ImportSelector;
   31      54      2    temp52       Lscala/reflect/generic/Trees$ImportSelector;
   36      49      3    temp53       Ljava/lang/Object;
   42      43      4    temp54       I
   48      37      5    temp55       Ljava/lang/Object;
   54      31      6    temp56       I


public java.lang.String productPrefix();
  Signature: ()Ljava/lang/String;
  Code:
   Stack=1, Locals=1, Args_size=1
	ldc	String ImportSelector
	areturn
  Labels:

public int productArity();
  Signature: ()I
  Code:
   Stack=1, Locals=1, Args_size=1
	iconst_4
	ireturn
  Labels:

public java.lang.Object productElement(int);
  Signature: (I)Ljava/lang/Object;
  Code:
   Stack=3, Locals=4, Args_size=2
	iload_1
	tableswitch{ //0 to 3
		0: 78;
		1: 66;
		2: 59;
		3: 47;
		default: 32 }
	new	class java/lang/IndexOutOfBoundsException
	dup
	iload_1
	invokestatic	Method scala/runtime/BoxesRunTime.boxToInteger:(I)Ljava/lang/Integer;
	invokevirtual	Method java/lang/Object.toString:()Ljava/lang/String;
	invokespecial	Method java/lang/IndexOutOfBoundsException."<init>":(Ljava/lang/String;)V
	athrow
	aload_0
	invokevirtual	Method renamePos:()I
	istore_2
	iload_2
	invokestatic	Method scala/runtime/BoxesRunTime.boxToInteger:(I)Ljava/lang/Integer;
	goto	l1 // areturn
	aload_0
	invokevirtual	Method rename:()Ljava/lang/Object;
	goto	l1 // areturn
	aload_0
	invokevirtual	Method namePos:()I
	istore_3
	iload_3
	invokestatic	Method scala/runtime/BoxesRunTime.boxToInteger:(I)Ljava/lang/Integer;
	goto	l1 // areturn
	aload_0
	invokevirtual	Method name:()Ljava/lang/Object;
l1	areturn
  Labels:
   	l1 = 82 // areturn

public boolean canEqual(java.lang.Object);
  Signature: (Ljava/lang/Object;)Z
  Code:
   Stack=1, Locals=2, Args_size=2
	aload_1
	instanceof	class scala/reflect/generic/Trees$ImportSelector
	ireturn
  Labels:

public scala.reflect.generic.Universe scala$reflect$generic$Trees$ImportSelector$$$outer();
  Signature: ()Lscala/reflect/generic/Universe;
  Code:
   Stack=1, Locals=1, Args_size=1
	aload_0
	getfield	Field $outer:Lscala/reflect/generic/Universe;
	areturn
  Labels:

private final boolean gd2$1(java.lang.Object, int, java.lang.Object, int);
  Signature: (Ljava/lang/Object;ILjava/lang/Object;I)Z
  Code:
   Stack=2, Locals=7, Args_size=5
	aload_0
	invokevirtual	Method name:()Ljava/lang/Object;
	astore	5
	aload_1
	aload	5
	if_acmpne	l1 // aload_1
	iconst_1
	goto	l2 // ifeq
l1	aload_1
	ifnonnull	l3 // aload_1
	iconst_0
	goto	l2 // ifeq
l3	aload_1
	instanceof	class java/lang/Number
	ifne	l4 // aload_1
	aload_1
	instanceof	class java/lang/Character
	ifeq	l5 // aload_1
l4	aload_1
	aload	5
	invokestatic	Method scala/runtime/BoxesRunTime.equals2:(Ljava/lang/Object;Ljava/lang/Object;)Z
	goto	l2 // ifeq
l5	aload_1
	aload	5
	invokevirtual	Method java/lang/Object.equals:(Ljava/lang/Object;)Z
l2	ifeq	l6 // iconst_0
	iload_2
	aload_0
	invokevirtual	Method namePos:()I
	if_icmpne	l6 // iconst_0
	aload_0
	invokevirtual	Method rename:()Ljava/lang/Object;
	astore	6
	aload_3
	aload	6
	if_acmpne	l7 // aload_3
	iconst_1
	goto	l8 // ifeq
l7	aload_3
	ifnonnull	l9 // aload_3
	iconst_0
	goto	l8 // ifeq
l9	aload_3
	instanceof	class java/lang/Number
	ifne	l10 // aload_3
	aload_3
	instanceof	class java/lang/Character
	ifeq	l11 // aload_3
l10	aload_3
	aload	6
	invokestatic	Method scala/runtime/BoxesRunTime.equals2:(Ljava/lang/Object;Ljava/lang/Object;)Z
	goto	l8 // ifeq
l11	aload_3
	aload	6
	invokevirtual	Method java/lang/Object.equals:(Ljava/lang/Object;)Z
l8	ifeq	l6 // iconst_0
	iload	4
	aload_0
	invokevirtual	Method renamePos:()I
	if_icmpne	l6 // iconst_0
	iconst_1
	goto	l12 // ireturn
l6	iconst_0
l12	ireturn
  Labels:
   	l1 = 16 // aload_1
   	l3 = 24 // aload_1
   	l4 = 38 // aload_1
   	l5 = 47 // aload_1
   	l2 = 53 // ifeq
   	l7 = 80 // aload_3
   	l9 = 88 // aload_3
   	l10 = 102 // aload_3
   	l11 = 111 // aload_3
   	l8 = 117 // ifeq
   	l6 = 133 // iconst_0
   	l12 = 134 // ireturn
  LocalVariableTable: 
   Start  Length  Slot  Name   Signature
   0      135      0    this       Lscala/reflect/generic/Trees$ImportSelector;
   12      44      5    y0       Ljava/lang/Object;
   76      44      6    y1       Ljava/lang/Object;


public scala.reflect.generic.Trees$ImportSelector(scala.reflect.generic.Universe, java.lang.Object, int, java.lang.Object, int);
  Signature: (Lscala/reflect/generic/Universe;Ljava/lang/Object;ILjava/lang/Object;I)V
  Code:
   Stack=2, Locals=6, Args_size=6
	aload_0
	aload_2
	putfield	Field name:Ljava/lang/Object;
	aload_0
	iload_3
	putfield	Field namePos:I
	aload_0
	aload	4
	putfield	Field rename:Ljava/lang/Object;
	aload_0
	iload	5
	putfield	Field renamePos:I
	aload_1
	ifnonnull	l1 // aload_0
	new	class java/lang/NullPointerException
	dup
	invokespecial	Method java/lang/NullPointerException."<init>":()V
	athrow
l1	aload_0
	aload_1
	putfield	Field $outer:Lscala/reflect/generic/Universe;
	aload_0
	invokespecial	Method java/lang/Object."<init>":()V
	aload_0
	invokestatic	Method scala/Product$class.$init$:(Lscala/Product;)V
	return
  Labels:
   	l1 = 34 // aload_0
  LocalVariableTable: 
   Start  Length  Slot  Name   Signature
   0      48      0    this       Lscala/reflect/generic/Trees$ImportSelector;
   0      48      1    $outer       Lscala/reflect/generic/Universe;
   0      48      2    name       Ljava/lang/Object;
   0      48      3    namePos       I
   0      48      4    rename       Ljava/lang/Object;
   0      48      5    renamePos       I


}

