Compiled from "Trees.scala"
public final class scala.reflect.generic.Trees$ClassDef$ extends scala.runtime.AbstractFunction4 implements scala.ScalaObject
  SourceFile: "Trees.scala"
  Scala: length = 0x
   
  InnerClass: 
   public Template=class scala/reflect/generic/Trees$Template of class scala/reflect/generic/Trees
   public ClassDef=class scala/reflect/generic/Trees$ClassDef of class scala/reflect/generic/Trees
   public Modifiers=class scala/reflect/generic/Trees$Modifiers of class scala/reflect/generic/Trees
  minor version: 0
  major version: 49
  Constant pool:
Asciz	SourceFile;
Asciz	Trees.scala;
Asciz	$outer;
Asciz	Lscala/reflect/generic/Universe;;
Asciz	unapply;
Asciz	(Lscala/reflect/generic/Trees$ClassDef;)Lscala/Option;;
Asciz	Code;
Asciz	LineNumberTable;
Asciz	scala/None$;
class	scala/None$
Asciz	MODULE$;
Asciz	Lscala/None$;;
NameAndType	MODULE$:Lscala/None$;
Field	scala/None$.MODULE$:Lscala/None$;
Asciz	scala/Some;
class	scala/Some
Asciz	scala/Tuple4;
class	scala/Tuple4
Asciz	scala/reflect/generic/Trees$ClassDef;
class	scala/reflect/generic/Trees$ClassDef
Asciz	mods;
Asciz	()Lscala/reflect/generic/Trees$Modifiers;;
NameAndType	mods:()Lscala/reflect/generic/Trees$Modifiers;
Method	scala/reflect/generic/Trees$ClassDef.mods:()Lscala/reflect/generic/Trees$Modifiers;
Asciz	name;
Asciz	()Ljava/lang/Object;;
NameAndType	name:()Ljava/lang/Object;
Method	scala/reflect/generic/Trees$ClassDef.name:()Ljava/lang/Object;
Asciz	tparams;
Asciz	()Lscala/collection/immutable/List;;
NameAndType	tparams:()Lscala/collection/immutable/List;
Method	scala/reflect/generic/Trees$ClassDef.tparams:()Lscala/collection/immutable/List;
Asciz	impl;
Asciz	()Lscala/reflect/generic/Trees$Template;;
NameAndType	impl:()Lscala/reflect/generic/Trees$Template;
Method	scala/reflect/generic/Trees$ClassDef.impl:()Lscala/reflect/generic/Trees$Template;
Asciz	<init>;
Asciz	(Ljava/lang/Object;Ljava/lang/Object;Ljava/lang/Object;Ljava/lang/Object;)V;
NameAndType	"<init>":(Ljava/lang/Object;Ljava/lang/Object;Ljava/lang/Object;Ljava/lang/Object;)V
Method	scala/Tuple4."<init>":(Ljava/lang/Object;Ljava/lang/Object;Ljava/lang/Object;Ljava/lang/Object;)V
Asciz	(Ljava/lang/Object;)V;
NameAndType	"<init>":(Ljava/lang/Object;)V
Method	scala/Some."<init>":(Ljava/lang/Object;)V
Asciz	this;
Asciz	Lscala/reflect/generic/Trees$ClassDef$;;
Asciz	x$0;
Asciz	Lscala/reflect/generic/Trees$ClassDef;;
Asciz	LocalVariableTable;
Asciz	apply;
Asciz	(Lscala/reflect/generic/Trees$Modifiers;Ljava/lang/Object;Lscala/collection/immutable/List;Lscala/reflect/generic/Trees$Template;)Lscala/reflect/generic/Trees$ClassDef;;
Asciz	scala/reflect/generic/Trees$ClassDef$;
class	scala/reflect/generic/Trees$ClassDef$
NameAndType	$outer:Lscala/reflect/generic/Universe;
Field	scala/reflect/generic/Trees$ClassDef$.$outer:Lscala/reflect/generic/Universe;
Asciz	(Lscala/reflect/generic/Universe;Lscala/reflect/generic/Trees$Modifiers;Ljava/lang/Object;Lscala/collection/immutable/List;Lscala/reflect/generic/Trees$Template;)V;
NameAndType	"<init>":(Lscala/reflect/generic/Universe;Lscala/reflect/generic/Trees$Modifiers;Ljava/lang/Object;Lscala/collection/immutable/List;Lscala/reflect/generic/Trees$Template;)V
Method	scala/reflect/generic/Trees$ClassDef."<init>":(Lscala/reflect/generic/Universe;Lscala/reflect/generic/Trees$Modifiers;Ljava/lang/Object;Lscala/collection/immutable/List;Lscala/reflect/generic/Trees$Template;)V
Asciz	Lscala/reflect/generic/Trees$Modifiers;;
Asciz	Ljava/lang/Object;;
Asciz	Lscala/collection/immutable/List;;
Asciz	Lscala/reflect/generic/Trees$Template;;
Asciz	(Ljava/lang/Object;Ljava/lang/Object;Ljava/lang/Object;Ljava/lang/Object;)Ljava/lang/Object;;
Asciz	scala/reflect/generic/Trees$Modifiers;
class	scala/reflect/generic/Trees$Modifiers
Asciz	scala/collection/immutable/List;
class	scala/collection/immutable/List
Asciz	scala/reflect/generic/Trees$Template;
class	scala/reflect/generic/Trees$Template
NameAndType	apply:(Lscala/reflect/generic/Trees$Modifiers;Ljava/lang/Object;Lscala/collection/immutable/List;Lscala/reflect/generic/Trees$Template;)Lscala/reflect/generic/Trees$ClassDef;
Method	scala/reflect/generic/Trees$ClassDef$.apply:(Lscala/reflect/generic/Trees$Modifiers;Ljava/lang/Object;Lscala/collection/immutable/List;Lscala/reflect/generic/Trees$Template;)Lscala/reflect/generic/Trees$ClassDef;
Asciz	v1;
Asciz	v2;
Asciz	v3;
Asciz	v4;
Asciz	(Lscala/reflect/generic/Universe;)V;
Asciz	java/lang/NullPointerException;
class	java/lang/NullPointerException
Asciz	()V;
NameAndType	"<init>":()V
Method	java/lang/NullPointerException."<init>":()V
Asciz	scala/runtime/AbstractFunction4;
class	scala/runtime/AbstractFunction4
Method	scala/runtime/AbstractFunction4."<init>":()V
Asciz	Scala;
Asciz	InnerClasses;
Asciz	scala/reflect/generic/Trees;
class	scala/reflect/generic/Trees
Asciz	Template;
Asciz	ClassDef;
Asciz	Modifiers;
Asciz	scala/ScalaObject;
class	scala/ScalaObject

{
public final scala.reflect.generic.Universe $outer;
  Signature: Lscala/reflect/generic/Universe;

public scala.Option unapply(scala.reflect.generic.Trees$ClassDef);
  Signature: (Lscala/reflect/generic/Trees$ClassDef;)Lscala/Option;
  Code:
   Stack=8, Locals=2, Args_size=2
	aload_1
	ifnonnull	l1 // new
	getstatic	Field scala/None$.MODULE$:Lscala/None$;
	goto	l2 // areturn
l1	new	class scala/Some
	dup
	new	class scala/Tuple4
	dup
	aload_1
	invokevirtual	Method scala/reflect/generic/Trees$ClassDef.mods:()Lscala/reflect/generic/Trees$Modifiers;
	aload_1
	invokevirtual	Method scala/reflect/generic/Trees$ClassDef.name:()Ljava/lang/Object;
	aload_1
	invokevirtual	Method scala/reflect/generic/Trees$ClassDef.tparams:()Lscala/collection/immutable/List;
	aload_1
	invokevirtual	Method scala/reflect/generic/Trees$ClassDef.impl:()Lscala/reflect/generic/Trees$Template;
	invokespecial	Method scala/Tuple4."<init>":(Ljava/lang/Object;Ljava/lang/Object;Ljava/lang/Object;Ljava/lang/Object;)V
	invokespecial	Method scala/Some."<init>":(Ljava/lang/Object;)V
l2	areturn
  Labels:
   	l1 = 10 // new
   	l2 = 40 // areturn
  LocalVariableTable: 
   Start  Length  Slot  Name   Signature
   0      41      0    this       Lscala/reflect/generic/Trees$ClassDef$;
   0      41      1    x$0       Lscala/reflect/generic/Trees$ClassDef;


public scala.reflect.generic.Trees$ClassDef apply(scala.reflect.generic.Trees$Modifiers, java.lang.Object, scala.collection.immutable.List, scala.reflect.generic.Trees$Template);
  Signature: (Lscala/reflect/generic/Trees$Modifiers;Ljava/lang/Object;Lscala/collection/immutable/List;Lscala/reflect/generic/Trees$Template;)Lscala/reflect/generic/Trees$ClassDef;
  Code:
   Stack=7, Locals=5, Args_size=5
	new	class scala/reflect/generic/Trees$ClassDef
	dup
	aload_0
	getfield	Field $outer:Lscala/reflect/generic/Universe;
	aload_1
	aload_2
	aload_3
	aload	4
	invokespecial	Method scala/reflect/generic/Trees$ClassDef."<init>":(Lscala/reflect/generic/Universe;Lscala/reflect/generic/Trees$Modifiers;Ljava/lang/Object;Lscala/collection/immutable/List;Lscala/reflect/generic/Trees$Template;)V
	areturn
  Labels:
  LocalVariableTable: 
   Start  Length  Slot  Name   Signature
   0      17      0    this       Lscala/reflect/generic/Trees$ClassDef$;
   0      17      1    mods       Lscala/reflect/generic/Trees$Modifiers;
   0      17      2    name       Ljava/lang/Object;
   0      17      3    tparams       Lscala/collection/immutable/List;
   0      17      4    impl       Lscala/reflect/generic/Trees$Template;


public java.lang.Object apply(java.lang.Object, java.lang.Object, java.lang.Object, java.lang.Object);
  Signature: (Ljava/lang/Object;Ljava/lang/Object;Ljava/lang/Object;Ljava/lang/Object;)Ljava/lang/Object;
  Code:
   Stack=5, Locals=5, Args_size=5
	aload_0
	aload_1
	checkcast	class scala/reflect/generic/Trees$Modifiers
	aload_2
	aload_3
	checkcast	class scala/collection/immutable/List
	aload	4
	checkcast	class scala/reflect/generic/Trees$Template
	invokevirtual	Method apply:(Lscala/reflect/generic/Trees$Modifiers;Ljava/lang/Object;Lscala/collection/immutable/List;Lscala/reflect/generic/Trees$Template;)Lscala/reflect/generic/Trees$ClassDef;
	areturn
  Labels:
  LocalVariableTable: 
   Start  Length  Slot  Name   Signature
   0      19      0    this       Lscala/reflect/generic/Trees$ClassDef$;
   0      19      1    v1       Ljava/lang/Object;
   0      19      2    v2       Ljava/lang/Object;
   0      19      3    v3       Ljava/lang/Object;
   0      19      4    v4       Ljava/lang/Object;


public scala.reflect.generic.Trees$ClassDef$(scala.reflect.generic.Universe);
  Signature: (Lscala/reflect/generic/Universe;)V
  Code:
   Stack=2, Locals=2, Args_size=2
	aload_1
	ifnonnull	l1 // aload_0
	new	class java/lang/NullPointerException
	dup
	invokespecial	Method java/lang/NullPointerException."<init>":()V
	athrow
l1	aload_0
	aload_1
	putfield	Field $outer:Lscala/reflect/generic/Universe;
	aload_0
	invokespecial	Method scala/runtime/AbstractFunction4."<init>":()V
	return
  Labels:
   	l1 = 12 // aload_0
  LocalVariableTable: 
   Start  Length  Slot  Name   Signature
   0      22      0    this       Lscala/reflect/generic/Trees$ClassDef$;
   0      22      1    $outer       Lscala/reflect/generic/Universe;


}

