Compiled from "Trees.scala"
public class scala.reflect.generic.Trees$PackageDef extends scala.reflect.generic.Trees$MemberDef implements scala.ScalaObject,scala.Product,java.io.Serializable
  SourceFile: "Trees.scala"
  Scala: length = 0x
   
  InnerClass: 
   public abstract Tree=class scala/reflect/generic/Trees$Tree of class scala/reflect/generic/Trees
   public abstract RefTree=class scala/reflect/generic/Trees$RefTree of class scala/reflect/generic/Trees
   public Modifiers=class scala/reflect/generic/Trees$Modifiers of class scala/reflect/generic/Trees
   public abstract MemberDef=class scala/reflect/generic/Trees$MemberDef of class scala/reflect/generic/Trees
   public PackageDef=class scala/reflect/generic/Trees$PackageDef of class scala/reflect/generic/Trees
  minor version: 0
  major version: 49
  Constant pool:
Asciz	SourceFile;
Asciz	Trees.scala;
Asciz	pid;
Asciz	Lscala/reflect/generic/Trees$RefTree;;
Asciz	stats;
Asciz	Lscala/collection/immutable/List;;
Asciz	Lscala/collection/immutable/List<Lscala/reflect/generic/Trees$Tree;>;;
Asciz	Signature;
Asciz	copy$default$2;
Asciz	()Lscala/collection/immutable/List;;
Asciz	Code;
Asciz	LineNumberTable;
Asciz	scala/reflect/generic/Trees$PackageDef;
class	scala/reflect/generic/Trees$PackageDef
NameAndType	stats:()Lscala/collection/immutable/List;
Method	scala/reflect/generic/Trees$PackageDef.stats:()Lscala/collection/immutable/List;
Asciz	copy$default$1;
Asciz	()Lscala/reflect/generic/Trees$RefTree;;
NameAndType	pid:()Lscala/reflect/generic/Trees$RefTree;
Method	scala/reflect/generic/Trees$PackageDef.pid:()Lscala/reflect/generic/Trees$RefTree;
NameAndType	pid:Lscala/reflect/generic/Trees$RefTree;
Field	scala/reflect/generic/Trees$PackageDef.pid:Lscala/reflect/generic/Trees$RefTree;
NameAndType	stats:Lscala/collection/immutable/List;
Field	scala/reflect/generic/Trees$PackageDef.stats:Lscala/collection/immutable/List;
Asciz	()Lscala/collection/immutable/List<Lscala/reflect/generic/Trees$Tree;>;;
Asciz	name;
Asciz	()Ljava/lang/Object;;
Asciz	scala/reflect/generic/Trees$RefTree;
class	scala/reflect/generic/Trees$RefTree
NameAndType	name:()Ljava/lang/Object;
InterfaceMethod	scala/reflect/generic/Trees$RefTree.name:()Ljava/lang/Object;
Asciz	mods;
Asciz	()Lscala/reflect/generic/Trees$Modifiers;;
Asciz	scala$reflect$generic$Trees$PackageDef$$$outer;
Asciz	()Lscala/reflect/generic/Universe;;
NameAndType	scala$reflect$generic$Trees$PackageDef$$$outer:()Lscala/reflect/generic/Universe;
Method	scala/reflect/generic/Trees$PackageDef.scala$reflect$generic$Trees$PackageDef$$$outer:()Lscala/reflect/generic/Universe;
Asciz	scala/reflect/generic/Trees;
class	scala/reflect/generic/Trees
Asciz	NoMods;
NameAndType	NoMods:()Lscala/reflect/generic/Trees$Modifiers;
InterfaceMethod	scala/reflect/generic/Trees.NoMods:()Lscala/reflect/generic/Trees$Modifiers;
Asciz	copy;
Asciz	(Lscala/reflect/generic/Trees$RefTree;Lscala/collection/immutable/List;)Lscala/reflect/generic/Trees$PackageDef;;
Asciz	<init>;
Asciz	(Lscala/reflect/generic/Universe;Lscala/reflect/generic/Trees$RefTree;Lscala/collection/immutable/List;)V;
NameAndType	"<init>":(Lscala/reflect/generic/Universe;Lscala/reflect/generic/Trees$RefTree;Lscala/collection/immutable/List;)V
Method	scala/reflect/generic/Trees$PackageDef."<init>":(Lscala/reflect/generic/Universe;Lscala/reflect/generic/Trees$RefTree;Lscala/collection/immutable/List;)V
Asciz	this;
Asciz	Lscala/reflect/generic/Trees$PackageDef;;
Asciz	LocalVariableTable;
Asciz	productPrefix;
Asciz	()Ljava/lang/String;;
Asciz	PackageDef;
String	PackageDef
Asciz	productArity;
Asciz	()I;
Asciz	productElement;
Asciz	(I)Ljava/lang/Object;;
Asciz	java/lang/IndexOutOfBoundsException;
class	java/lang/IndexOutOfBoundsException
Asciz	scala/runtime/BoxesRunTime;
class	scala/runtime/BoxesRunTime
Asciz	boxToInteger;
Asciz	(I)Ljava/lang/Integer;;
NameAndType	boxToInteger:(I)Ljava/lang/Integer;
Method	scala/runtime/BoxesRunTime.boxToInteger:(I)Ljava/lang/Integer;
Asciz	java/lang/Object;
class	java/lang/Object
Asciz	toString;
NameAndType	toString:()Ljava/lang/String;
Method	java/lang/Object.toString:()Ljava/lang/String;
Asciz	(Ljava/lang/String;)V;
NameAndType	"<init>":(Ljava/lang/String;)V
Method	java/lang/IndexOutOfBoundsException."<init>":(Ljava/lang/String;)V
Asciz	canEqual;
Asciz	(Ljava/lang/Object;)Z;
Asciz	scala/reflect/generic/Trees$Tree;
class	scala/reflect/generic/Trees$Tree
Asciz	$outer;
Asciz	Lscala/reflect/generic/Universe;;
NameAndType	$outer:Lscala/reflect/generic/Universe;
Field	scala/reflect/generic/Trees$Tree.$outer:Lscala/reflect/generic/Universe;
Asciz	scala/reflect/generic/Trees$MemberDef;
class	scala/reflect/generic/Trees$MemberDef
Asciz	(Lscala/reflect/generic/Universe;)V;
NameAndType	"<init>":(Lscala/reflect/generic/Universe;)V
Method	scala/reflect/generic/Trees$MemberDef."<init>":(Lscala/reflect/generic/Universe;)V
Asciz	(Lscala/reflect/generic/Universe;Lscala/reflect/generic/Trees$RefTree;Lscala/collection/immutable/List<Lscala/reflect/generic/Trees$Tree;>;)V;
Asciz	Scala;
Asciz	InnerClasses;
Asciz	Tree;
Asciz	RefTree;
Asciz	scala/reflect/generic/Trees$Modifiers;
class	scala/reflect/generic/Trees$Modifiers
Asciz	Modifiers;
Asciz	MemberDef;
Asciz	scala/ScalaObject;
class	scala/ScalaObject
Asciz	scala/Product;
class	scala/Product
Asciz	java/io/Serializable;
class	java/io/Serializable

{
private final scala.reflect.generic.Trees$RefTree pid;
  Signature: Lscala/reflect/generic/Trees$RefTree;

private final scala.collection.immutable.List stats;
  Signature: Lscala/collection/immutable/List;
  Signature: length = 0x2
   00 07 

public scala.collection.immutable.List copy$default$2();
  Signature: ()Lscala/collection/immutable/List;
  Code:
   Stack=1, Locals=1, Args_size=1
	aload_0
	invokevirtual	Method stats:()Lscala/collection/immutable/List;
	areturn
  Labels:

public scala.reflect.generic.Trees$RefTree copy$default$1();
  Signature: ()Lscala/reflect/generic/Trees$RefTree;
  Code:
   Stack=1, Locals=1, Args_size=1
	aload_0
	invokevirtual	Method pid:()Lscala/reflect/generic/Trees$RefTree;
	areturn
  Labels:

public scala.reflect.generic.Trees$RefTree pid();
  Signature: ()Lscala/reflect/generic/Trees$RefTree;
  Code:
   Stack=1, Locals=1, Args_size=1
	aload_0
	getfield	Field pid:Lscala/reflect/generic/Trees$RefTree;
	areturn
  Labels:

public scala.collection.immutable.List stats();
  Signature: ()Lscala/collection/immutable/List;
  Code:
   Stack=1, Locals=1, Args_size=1
	aload_0
	getfield	Field stats:Lscala/collection/immutable/List;
	areturn
  Labels:
  Signature: length = 0x2
   00 19 

public java.lang.Object name();
  Signature: ()Ljava/lang/Object;
  Code:
   Stack=1, Locals=1, Args_size=1
	aload_0
	invokevirtual	Method pid:()Lscala/reflect/generic/Trees$RefTree;
	invokeinterface	InterfaceMethod scala/reflect/generic/Trees$RefTree.name:()Ljava/lang/Object;
	areturn
  Labels:

public scala.reflect.generic.Trees$Modifiers mods();
  Signature: ()Lscala/reflect/generic/Trees$Modifiers;
  Code:
   Stack=1, Locals=1, Args_size=1
	aload_0
	invokevirtual	Method scala$reflect$generic$Trees$PackageDef$$$outer:()Lscala/reflect/generic/Universe;
	invokeinterface	InterfaceMethod scala/reflect/generic/Trees.NoMods:()Lscala/reflect/generic/Trees$Modifiers;
	areturn
  Labels:

public scala.reflect.generic.Trees$PackageDef copy(scala.reflect.generic.Trees$RefTree, scala.collection.immutable.List);
  Signature: (Lscala/reflect/generic/Trees$RefTree;Lscala/collection/immutable/List;)Lscala/reflect/generic/Trees$PackageDef;
  Code:
   Stack=5, Locals=3, Args_size=3
	new	class scala/reflect/generic/Trees$PackageDef
	dup
	aload_0
	invokevirtual	Method scala$reflect$generic$Trees$PackageDef$$$outer:()Lscala/reflect/generic/Universe;
	aload_1
	aload_2
	invokespecial	Method "<init>":(Lscala/reflect/generic/Universe;Lscala/reflect/generic/Trees$RefTree;Lscala/collection/immutable/List;)V
	areturn
  Labels:
  LocalVariableTable: 
   Start  Length  Slot  Name   Signature
   0      14      0    this       Lscala/reflect/generic/Trees$PackageDef;
   0      14      1    pid       Lscala/reflect/generic/Trees$RefTree;
   0      14      2    stats       Lscala/collection/immutable/List;


public java.lang.String productPrefix();
  Signature: ()Ljava/lang/String;
  Code:
   Stack=1, Locals=1, Args_size=1
	ldc	String PackageDef
	areturn
  Labels:

public int productArity();
  Signature: ()I
  Code:
   Stack=1, Locals=1, Args_size=1
	iconst_2
	ireturn
  Labels:

public java.lang.Object productElement(int);
  Signature: (I)Ljava/lang/Object;
  Code:
   Stack=3, Locals=2, Args_size=2
	iload_1
	tableswitch{ //0 to 1
		0: 46;
		1: 39;
		default: 24 }
	new	class java/lang/IndexOutOfBoundsException
	dup
	iload_1
	invokestatic	Method scala/runtime/BoxesRunTime.boxToInteger:(I)Ljava/lang/Integer;
	invokevirtual	Method java/lang/Object.toString:()Ljava/lang/String;
	invokespecial	Method java/lang/IndexOutOfBoundsException."<init>":(Ljava/lang/String;)V
	athrow
	aload_0
	invokevirtual	Method stats:()Lscala/collection/immutable/List;
	goto	l1 // areturn
	aload_0
	invokevirtual	Method pid:()Lscala/reflect/generic/Trees$RefTree;
l1	areturn
  Labels:
   	l1 = 50 // areturn

public boolean canEqual(java.lang.Object);
  Signature: (Ljava/lang/Object;)Z
  Code:
   Stack=1, Locals=2, Args_size=2
	aload_1
	instanceof	class scala/reflect/generic/Trees$PackageDef
	ireturn
  Labels:

public scala.reflect.generic.Universe scala$reflect$generic$Trees$PackageDef$$$outer();
  Signature: ()Lscala/reflect/generic/Universe;
  Code:
   Stack=1, Locals=1, Args_size=1
	aload_0
	getfield	Field scala/reflect/generic/Trees$Tree.$outer:Lscala/reflect/generic/Universe;
	areturn
  Labels:

public scala.reflect.generic.Trees$PackageDef(scala.reflect.generic.Universe, scala.reflect.generic.Trees$RefTree, scala.collection.immutable.List);
  Signature: (Lscala/reflect/generic/Universe;Lscala/reflect/generic/Trees$RefTree;Lscala/collection/immutable/List;)V
  Code:
   Stack=2, Locals=4, Args_size=4
	aload_0
	aload_2
	putfield	Field pid:Lscala/reflect/generic/Trees$RefTree;
	aload_0
	aload_3
	putfield	Field stats:Lscala/collection/immutable/List;
	aload_0
	aload_1
	invokespecial	Method scala/reflect/generic/Trees$MemberDef."<init>":(Lscala/reflect/generic/Universe;)V
	return
  Labels:
  LocalVariableTable: 
   Start  Length  Slot  Name   Signature
   0      16      0    this       Lscala/reflect/generic/Trees$PackageDef;
   0      16      1    $outer       Lscala/reflect/generic/Universe;
   0      16      2    pid       Lscala/reflect/generic/Trees$RefTree;
   0      16      3    stats       Lscala/collection/immutable/List;

  Signature: length = 0x2
   00 59 

}

