Compiled from "Trees.scala"
public class scala.reflect.generic.Trees$Template extends scala.reflect.generic.Trees$Tree implements scala.reflect.generic.Trees$SymTree,scala.ScalaObject,scala.Product,java.io.Serializable
  SourceFile: "Trees.scala"
  Scala: length = 0x
   
  InnerClass: 
   public abstract Tree=class scala/reflect/generic/Trees$Tree of class scala/reflect/generic/Trees
   public ValDef=class scala/reflect/generic/Trees$ValDef of class scala/reflect/generic/Trees
   public abstract SymTree=class scala/reflect/generic/Trees$SymTree of class scala/reflect/generic/Trees
   public Template=class scala/reflect/generic/Trees$Template of class scala/reflect/generic/Trees
   public abstract AbsSymbol=class scala/reflect/generic/Symbols$AbsSymbol of class scala/reflect/generic/Symbols
  minor version: 0
  major version: 49
  Constant pool:
Asciz	SourceFile;
Asciz	Trees.scala;
Asciz	parents;
Asciz	Lscala/collection/immutable/List;;
Asciz	Lscala/collection/immutable/List<Lscala/reflect/generic/Trees$Tree;>;;
Asciz	Signature;
Asciz	self;
Asciz	Lscala/reflect/generic/Trees$ValDef;;
Asciz	body;
Asciz	symbol;
Asciz	Lscala/reflect/generic/Symbols$AbsSymbol;;
Asciz	()Lscala/reflect/generic/Symbols$AbsSymbol;;
Asciz	Code;
Asciz	LineNumberTable;
Asciz	scala/reflect/generic/Trees$Template;
class	scala/reflect/generic/Trees$Template
NameAndType	symbol:Lscala/reflect/generic/Symbols$AbsSymbol;
Field	scala/reflect/generic/Trees$Template.symbol:Lscala/reflect/generic/Symbols$AbsSymbol;
Asciz	symbol_$eq;
Asciz	(Lscala/reflect/generic/Symbols$AbsSymbol;)V;
Asciz	hasSymbol;
Asciz	()Z;
Asciz	scala/reflect/generic/Trees$SymTree$class;
class	scala/reflect/generic/Trees$SymTree$class
Asciz	(Lscala/reflect/generic/Trees$SymTree;)Z;
NameAndType	hasSymbol:(Lscala/reflect/generic/Trees$SymTree;)Z
Method	scala/reflect/generic/Trees$SymTree$class.hasSymbol:(Lscala/reflect/generic/Trees$SymTree;)Z
Asciz	copy$default$3;
Asciz	()Lscala/collection/immutable/List;;
NameAndType	body:()Lscala/collection/immutable/List;
Method	scala/reflect/generic/Trees$Template.body:()Lscala/collection/immutable/List;
Asciz	copy$default$2;
Asciz	()Lscala/reflect/generic/Trees$ValDef;;
NameAndType	self:()Lscala/reflect/generic/Trees$ValDef;
Method	scala/reflect/generic/Trees$Template.self:()Lscala/reflect/generic/Trees$ValDef;
Asciz	copy$default$1;
NameAndType	parents:()Lscala/collection/immutable/List;
Method	scala/reflect/generic/Trees$Template.parents:()Lscala/collection/immutable/List;
NameAndType	parents:Lscala/collection/immutable/List;
Field	scala/reflect/generic/Trees$Template.parents:Lscala/collection/immutable/List;
Asciz	()Lscala/collection/immutable/List<Lscala/reflect/generic/Trees$Tree;>;;
NameAndType	self:Lscala/reflect/generic/Trees$ValDef;
Field	scala/reflect/generic/Trees$Template.self:Lscala/reflect/generic/Trees$ValDef;
NameAndType	body:Lscala/collection/immutable/List;
Field	scala/reflect/generic/Trees$Template.body:Lscala/collection/immutable/List;
Asciz	copy;
Asciz	(Lscala/collection/immutable/List;Lscala/reflect/generic/Trees$ValDef;Lscala/collection/immutable/List;)Lscala/reflect/generic/Trees$Template;;
Asciz	scala$reflect$generic$Trees$Template$$$outer;
Asciz	()Lscala/reflect/generic/Universe;;
NameAndType	scala$reflect$generic$Trees$Template$$$outer:()Lscala/reflect/generic/Universe;
Method	scala/reflect/generic/Trees$Template.scala$reflect$generic$Trees$Template$$$outer:()Lscala/reflect/generic/Universe;
Asciz	<init>;
Asciz	(Lscala/reflect/generic/Universe;Lscala/collection/immutable/List;Lscala/reflect/generic/Trees$ValDef;Lscala/collection/immutable/List;)V;
NameAndType	"<init>":(Lscala/reflect/generic/Universe;Lscala/collection/immutable/List;Lscala/reflect/generic/Trees$ValDef;Lscala/collection/immutable/List;)V
Method	scala/reflect/generic/Trees$Template."<init>":(Lscala/reflect/generic/Universe;Lscala/collection/immutable/List;Lscala/reflect/generic/Trees$ValDef;Lscala/collection/immutable/List;)V
Asciz	this;
Asciz	Lscala/reflect/generic/Trees$Template;;
Asciz	LocalVariableTable;
Asciz	productPrefix;
Asciz	()Ljava/lang/String;;
Asciz	Template;
String	Template
Asciz	productArity;
Asciz	()I;
Asciz	productElement;
Asciz	(I)Ljava/lang/Object;;
Asciz	java/lang/IndexOutOfBoundsException;
class	java/lang/IndexOutOfBoundsException
Asciz	scala/runtime/BoxesRunTime;
class	scala/runtime/BoxesRunTime
Asciz	boxToInteger;
Asciz	(I)Ljava/lang/Integer;;
NameAndType	boxToInteger:(I)Ljava/lang/Integer;
Method	scala/runtime/BoxesRunTime.boxToInteger:(I)Ljava/lang/Integer;
Asciz	java/lang/Object;
class	java/lang/Object
Asciz	toString;
NameAndType	toString:()Ljava/lang/String;
Method	java/lang/Object.toString:()Ljava/lang/String;
Asciz	(Ljava/lang/String;)V;
NameAndType	"<init>":(Ljava/lang/String;)V
Method	java/lang/IndexOutOfBoundsException."<init>":(Ljava/lang/String;)V
Asciz	canEqual;
Asciz	(Ljava/lang/Object;)Z;
Asciz	scala/reflect/generic/Trees$Tree;
class	scala/reflect/generic/Trees$Tree
Asciz	$outer;
Asciz	Lscala/reflect/generic/Universe;;
NameAndType	$outer:Lscala/reflect/generic/Universe;
Field	scala/reflect/generic/Trees$Tree.$outer:Lscala/reflect/generic/Universe;
Asciz	scala$reflect$generic$Trees$SymTree$$$outer;
Asciz	()Lscala/reflect/generic/Trees;;
Asciz	(Lscala/reflect/generic/Universe;)V;
NameAndType	"<init>":(Lscala/reflect/generic/Universe;)V
Method	scala/reflect/generic/Trees$Tree."<init>":(Lscala/reflect/generic/Universe;)V
Asciz	$init$;
Asciz	(Lscala/reflect/generic/Trees$SymTree;)V;
NameAndType	$init$:(Lscala/reflect/generic/Trees$SymTree;)V
Method	scala/reflect/generic/Trees$SymTree$class.$init$:(Lscala/reflect/generic/Trees$SymTree;)V
Asciz	(Lscala/reflect/generic/Universe;Lscala/collection/immutable/List<Lscala/reflect/generic/Trees$Tree;>;Lscala/reflect/generic/Trees$ValDef;Lscala/collection/immutable/List<Lscala/reflect/generic/Trees$Tree;>;)V;
Asciz	Scala;
Asciz	InnerClasses;
Asciz	scala/reflect/generic/Trees;
class	scala/reflect/generic/Trees
Asciz	Tree;
Asciz	scala/reflect/generic/Trees$ValDef;
class	scala/reflect/generic/Trees$ValDef
Asciz	ValDef;
Asciz	scala/reflect/generic/Trees$SymTree;
class	scala/reflect/generic/Trees$SymTree
Asciz	SymTree;
Asciz	scala/reflect/generic/Symbols$AbsSymbol;
class	scala/reflect/generic/Symbols$AbsSymbol
Asciz	scala/reflect/generic/Symbols;
class	scala/reflect/generic/Symbols
Asciz	AbsSymbol;
Asciz	scala/ScalaObject;
class	scala/ScalaObject
Asciz	scala/Product;
class	scala/Product
Asciz	java/io/Serializable;
class	java/io/Serializable

{
private final scala.collection.immutable.List parents;
  Signature: Lscala/collection/immutable/List;
  Signature: length = 0x2
   00 05 

private final scala.reflect.generic.Trees$ValDef self;
  Signature: Lscala/reflect/generic/Trees$ValDef;

private final scala.collection.immutable.List body;
  Signature: Lscala/collection/immutable/List;
  Signature: length = 0x2
   00 05 

private scala.reflect.generic.Symbols$AbsSymbol symbol;
  Signature: Lscala/reflect/generic/Symbols$AbsSymbol;

public scala.reflect.generic.Symbols$AbsSymbol symbol();
  Signature: ()Lscala/reflect/generic/Symbols$AbsSymbol;
  Code:
   Stack=1, Locals=1, Args_size=1
	aload_0
	getfield	Field symbol:Lscala/reflect/generic/Symbols$AbsSymbol;
	areturn
  Labels:

public void symbol_$eq(scala.reflect.generic.Symbols$AbsSymbol);
  Signature: (Lscala/reflect/generic/Symbols$AbsSymbol;)V
  Code:
   Stack=2, Locals=2, Args_size=2
	aload_0
	aload_1
	putfield	Field symbol:Lscala/reflect/generic/Symbols$AbsSymbol;
	return
  Labels:

public boolean hasSymbol();
  Signature: ()Z
  Code:
   Stack=1, Locals=1, Args_size=1
	aload_0
	invokestatic	Method scala/reflect/generic/Trees$SymTree$class.hasSymbol:(Lscala/reflect/generic/Trees$SymTree;)Z
	ireturn
  Labels:

public scala.collection.immutable.List copy$default$3();
  Signature: ()Lscala/collection/immutable/List;
  Code:
   Stack=1, Locals=1, Args_size=1
	aload_0
	invokevirtual	Method body:()Lscala/collection/immutable/List;
	areturn
  Labels:

public scala.reflect.generic.Trees$ValDef copy$default$2();
  Signature: ()Lscala/reflect/generic/Trees$ValDef;
  Code:
   Stack=1, Locals=1, Args_size=1
	aload_0
	invokevirtual	Method self:()Lscala/reflect/generic/Trees$ValDef;
	areturn
  Labels:

public scala.collection.immutable.List copy$default$1();
  Signature: ()Lscala/collection/immutable/List;
  Code:
   Stack=1, Locals=1, Args_size=1
	aload_0
	invokevirtual	Method parents:()Lscala/collection/immutable/List;
	areturn
  Labels:

public scala.collection.immutable.List parents();
  Signature: ()Lscala/collection/immutable/List;
  Code:
   Stack=1, Locals=1, Args_size=1
	aload_0
	getfield	Field parents:Lscala/collection/immutable/List;
	areturn
  Labels:
  Signature: length = 0x2
   00 29 

public scala.reflect.generic.Trees$ValDef self();
  Signature: ()Lscala/reflect/generic/Trees$ValDef;
  Code:
   Stack=1, Locals=1, Args_size=1
	aload_0
	getfield	Field self:Lscala/reflect/generic/Trees$ValDef;
	areturn
  Labels:

public scala.collection.immutable.List body();
  Signature: ()Lscala/collection/immutable/List;
  Code:
   Stack=1, Locals=1, Args_size=1
	aload_0
	getfield	Field body:Lscala/collection/immutable/List;
	areturn
  Labels:
  Signature: length = 0x2
   00 29 

public scala.reflect.generic.Trees$Template copy(scala.collection.immutable.List, scala.reflect.generic.Trees$ValDef, scala.collection.immutable.List);
  Signature: (Lscala/collection/immutable/List;Lscala/reflect/generic/Trees$ValDef;Lscala/collection/immutable/List;)Lscala/reflect/generic/Trees$Template;
  Code:
   Stack=6, Locals=4, Args_size=4
	new	class scala/reflect/generic/Trees$Template
	dup
	aload_0
	invokevirtual	Method scala$reflect$generic$Trees$Template$$$outer:()Lscala/reflect/generic/Universe;
	aload_1
	aload_2
	aload_3
	invokespecial	Method "<init>":(Lscala/reflect/generic/Universe;Lscala/collection/immutable/List;Lscala/reflect/generic/Trees$ValDef;Lscala/collection/immutable/List;)V
	areturn
  Labels:
  LocalVariableTable: 
   Start  Length  Slot  Name   Signature
   0      15      0    this       Lscala/reflect/generic/Trees$Template;
   0      15      1    parents       Lscala/collection/immutable/List;
   0      15      2    self       Lscala/reflect/generic/Trees$ValDef;
   0      15      3    body       Lscala/collection/immutable/List;


public java.lang.String productPrefix();
  Signature: ()Ljava/lang/String;
  Code:
   Stack=1, Locals=1, Args_size=1
	ldc	String Template
	areturn
  Labels:

public int productArity();
  Signature: ()I
  Code:
   Stack=1, Locals=1, Args_size=1
	iconst_3
	ireturn
  Labels:

public java.lang.Object productElement(int);
  Signature: (I)Ljava/lang/Object;
  Code:
   Stack=3, Locals=2, Args_size=2
	iload_1
	tableswitch{ //0 to 2
		0: 57;
		1: 50;
		2: 43;
		default: 28 }
	new	class java/lang/IndexOutOfBoundsException
	dup
	iload_1
	invokestatic	Method scala/runtime/BoxesRunTime.boxToInteger:(I)Ljava/lang/Integer;
	invokevirtual	Method java/lang/Object.toString:()Ljava/lang/String;
	invokespecial	Method java/lang/IndexOutOfBoundsException."<init>":(Ljava/lang/String;)V
	athrow
	aload_0
	invokevirtual	Method body:()Lscala/collection/immutable/List;
	goto	l1 // areturn
	aload_0
	invokevirtual	Method self:()Lscala/reflect/generic/Trees$ValDef;
	goto	l1 // areturn
	aload_0
	invokevirtual	Method parents:()Lscala/collection/immutable/List;
l1	areturn
  Labels:
   	l1 = 61 // areturn

public boolean canEqual(java.lang.Object);
  Signature: (Ljava/lang/Object;)Z
  Code:
   Stack=1, Locals=2, Args_size=2
	aload_1
	instanceof	class scala/reflect/generic/Trees$Template
	ireturn
  Labels:

public scala.reflect.generic.Universe scala$reflect$generic$Trees$Template$$$outer();
  Signature: ()Lscala/reflect/generic/Universe;
  Code:
   Stack=1, Locals=1, Args_size=1
	aload_0
	getfield	Field scala/reflect/generic/Trees$Tree.$outer:Lscala/reflect/generic/Universe;
	areturn
  Labels:

public scala.reflect.generic.Trees scala$reflect$generic$Trees$SymTree$$$outer();
  Signature: ()Lscala/reflect/generic/Trees;
  Code:
   Stack=1, Locals=1, Args_size=1
	aload_0
	invokevirtual	Method scala$reflect$generic$Trees$Template$$$outer:()Lscala/reflect/generic/Universe;
	areturn
  Labels:

public scala.reflect.generic.Trees$Template(scala.reflect.generic.Universe, scala.collection.immutable.List, scala.reflect.generic.Trees$ValDef, scala.collection.immutable.List);
  Signature: (Lscala/reflect/generic/Universe;Lscala/collection/immutable/List;Lscala/reflect/generic/Trees$ValDef;Lscala/collection/immutable/List;)V
  Code:
   Stack=2, Locals=5, Args_size=5
	aload_0
	aload_2
	putfield	Field parents:Lscala/collection/immutable/List;
	aload_0
	aload_3
	putfield	Field self:Lscala/reflect/generic/Trees$ValDef;
	aload_0
	aload	4
	putfield	Field body:Lscala/collection/immutable/List;
	aload_0
	aload_1
	invokespecial	Method scala/reflect/generic/Trees$Tree."<init>":(Lscala/reflect/generic/Universe;)V
	aload_0
	invokestatic	Method scala/reflect/generic/Trees$SymTree$class.$init$:(Lscala/reflect/generic/Trees$SymTree;)V
	return
  Labels:
  LocalVariableTable: 
   Start  Length  Slot  Name   Signature
   0      26      0    this       Lscala/reflect/generic/Trees$Template;
   0      26      1    $outer       Lscala/reflect/generic/Universe;
   0      26      2    parents       Lscala/collection/immutable/List;
   0      26      3    self       Lscala/reflect/generic/Trees$ValDef;
   0      26      4    body       Lscala/collection/immutable/List;

  Signature: length = 0x2
   00 64 

}

