Compiled from "Trees.scala"
public final class scala.reflect.generic.Trees$DefDef$ extends java.lang.Object implements scala.Function6,scala.ScalaObject
  SourceFile: "Trees.scala"
  Scala: length = 0x
   
  InnerClass: 
   public abstract Tree=class scala/reflect/generic/Trees$Tree of class scala/reflect/generic/Trees
   public DefDef=class scala/reflect/generic/Trees$DefDef of class scala/reflect/generic/Trees
   public Modifiers=class scala/reflect/generic/Trees$Modifiers of class scala/reflect/generic/Trees
  minor version: 0
  major version: 49
  Constant pool:
Asciz	SourceFile;
Asciz	Trees.scala;
Asciz	Scala;
Asciz	$outer;
Asciz	Lscala/reflect/generic/Universe;;
Asciz	toString;
Asciz	()Ljava/lang/String;;
Asciz	Code;
Asciz	LineNumberTable;
Asciz	scala/Function6$class;
class	scala/Function6$class
Asciz	(Lscala/Function6;)Ljava/lang/String;;
NameAndType	toString:(Lscala/Function6;)Ljava/lang/String;
Method	scala/Function6$class.toString:(Lscala/Function6;)Ljava/lang/String;
Asciz	curried;
Asciz	()Lscala/Function1;;
Asciz	(Lscala/Function6;)Lscala/Function1;;
NameAndType	curried:(Lscala/Function6;)Lscala/Function1;
Method	scala/Function6$class.curried:(Lscala/Function6;)Lscala/Function1;
Asciz	curry;
NameAndType	curry:(Lscala/Function6;)Lscala/Function1;
Method	scala/Function6$class.curry:(Lscala/Function6;)Lscala/Function1;
Asciz	Deprecated;
Asciz	tupled;
NameAndType	tupled:(Lscala/Function6;)Lscala/Function1;
Method	scala/Function6$class.tupled:(Lscala/Function6;)Lscala/Function1;
Asciz	unapply;
Asciz	(Lscala/reflect/generic/Trees$DefDef;)Lscala/Option;;
Asciz	java/lang/Object;
class	java/lang/Object
Asciz	equals;
Asciz	(Ljava/lang/Object;)Z;
NameAndType	equals:(Ljava/lang/Object;)Z
Method	java/lang/Object.equals:(Ljava/lang/Object;)Z
Asciz	scala/None$;
class	scala/None$
Asciz	MODULE$;
Asciz	Lscala/None$;;
NameAndType	MODULE$:Lscala/None$;
Field	scala/None$.MODULE$:Lscala/None$;
Asciz	scala/Some;
class	scala/Some
Asciz	scala/Tuple6;
class	scala/Tuple6
Asciz	scala/reflect/generic/Trees$DefDef;
class	scala/reflect/generic/Trees$DefDef
Asciz	mods;
Asciz	()Lscala/reflect/generic/Trees$Modifiers;;
NameAndType	mods:()Lscala/reflect/generic/Trees$Modifiers;
Method	scala/reflect/generic/Trees$DefDef.mods:()Lscala/reflect/generic/Trees$Modifiers;
Asciz	name;
Asciz	()Ljava/lang/Object;;
NameAndType	name:()Ljava/lang/Object;
Method	scala/reflect/generic/Trees$DefDef.name:()Ljava/lang/Object;
Asciz	tparams;
Asciz	()Lscala/collection/immutable/List;;
NameAndType	tparams:()Lscala/collection/immutable/List;
Method	scala/reflect/generic/Trees$DefDef.tparams:()Lscala/collection/immutable/List;
Asciz	vparamss;
NameAndType	vparamss:()Lscala/collection/immutable/List;
Method	scala/reflect/generic/Trees$DefDef.vparamss:()Lscala/collection/immutable/List;
Asciz	tpt;
Asciz	()Lscala/reflect/generic/Trees$Tree;;
NameAndType	tpt:()Lscala/reflect/generic/Trees$Tree;
Method	scala/reflect/generic/Trees$DefDef.tpt:()Lscala/reflect/generic/Trees$Tree;
Asciz	rhs;
NameAndType	rhs:()Lscala/reflect/generic/Trees$Tree;
Method	scala/reflect/generic/Trees$DefDef.rhs:()Lscala/reflect/generic/Trees$Tree;
Asciz	<init>;
Asciz	(Ljava/lang/Object;Ljava/lang/Object;Ljava/lang/Object;Ljava/lang/Object;Ljava/lang/Object;Ljava/lang/Object;)V;
NameAndType	"<init>":(Ljava/lang/Object;Ljava/lang/Object;Ljava/lang/Object;Ljava/lang/Object;Ljava/lang/Object;Ljava/lang/Object;)V
Method	scala/Tuple6."<init>":(Ljava/lang/Object;Ljava/lang/Object;Ljava/lang/Object;Ljava/lang/Object;Ljava/lang/Object;Ljava/lang/Object;)V
Asciz	(Ljava/lang/Object;)V;
NameAndType	"<init>":(Ljava/lang/Object;)V
Method	scala/Some."<init>":(Ljava/lang/Object;)V
Asciz	this;
Asciz	Lscala/reflect/generic/Trees$DefDef$;;
Asciz	x$0;
Asciz	Lscala/reflect/generic/Trees$DefDef;;
Asciz	LocalVariableTable;
Asciz	apply;
Asciz	(Lscala/reflect/generic/Trees$Modifiers;Ljava/lang/Object;Lscala/collection/immutable/List;Lscala/collection/immutable/List;Lscala/reflect/generic/Trees$Tree;Lscala/reflect/generic/Trees$Tree;)Lscala/reflect/generic/Trees$DefDef;;
Asciz	scala/reflect/generic/Trees$DefDef$;
class	scala/reflect/generic/Trees$DefDef$
NameAndType	$outer:Lscala/reflect/generic/Universe;
Field	scala/reflect/generic/Trees$DefDef$.$outer:Lscala/reflect/generic/Universe;
Asciz	(Lscala/reflect/generic/Universe;Lscala/reflect/generic/Trees$Modifiers;Ljava/lang/Object;Lscala/collection/immutable/List;Lscala/collection/immutable/List;Lscala/reflect/generic/Trees$Tree;Lscala/reflect/generic/Trees$Tree;)V;
NameAndType	"<init>":(Lscala/reflect/generic/Universe;Lscala/reflect/generic/Trees$Modifiers;Ljava/lang/Object;Lscala/collection/immutable/List;Lscala/collection/immutable/List;Lscala/reflect/generic/Trees$Tree;Lscala/reflect/generic/Trees$Tree;)V
Method	scala/reflect/generic/Trees$DefDef."<init>":(Lscala/reflect/generic/Universe;Lscala/reflect/generic/Trees$Modifiers;Ljava/lang/Object;Lscala/collection/immutable/List;Lscala/collection/immutable/List;Lscala/reflect/generic/Trees$Tree;Lscala/reflect/generic/Trees$Tree;)V
Asciz	Lscala/reflect/generic/Trees$Modifiers;;
Asciz	Ljava/lang/Object;;
Asciz	Lscala/collection/immutable/List;;
Asciz	Lscala/reflect/generic/Trees$Tree;;
Asciz	(Ljava/lang/Object;Ljava/lang/Object;Ljava/lang/Object;Ljava/lang/Object;Ljava/lang/Object;Ljava/lang/Object;)Ljava/lang/Object;;
Asciz	scala/reflect/generic/Trees$Modifiers;
class	scala/reflect/generic/Trees$Modifiers
Asciz	scala/collection/immutable/List;
class	scala/collection/immutable/List
Asciz	scala/reflect/generic/Trees$Tree;
class	scala/reflect/generic/Trees$Tree
NameAndType	apply:(Lscala/reflect/generic/Trees$Modifiers;Ljava/lang/Object;Lscala/collection/immutable/List;Lscala/collection/immutable/List;Lscala/reflect/generic/Trees$Tree;Lscala/reflect/generic/Trees$Tree;)Lscala/reflect/generic/Trees$DefDef;
Method	scala/reflect/generic/Trees$DefDef$.apply:(Lscala/reflect/generic/Trees$Modifiers;Ljava/lang/Object;Lscala/collection/immutable/List;Lscala/collection/immutable/List;Lscala/reflect/generic/Trees$Tree;Lscala/reflect/generic/Trees$Tree;)Lscala/reflect/generic/Trees$DefDef;
Asciz	v1;
Asciz	v2;
Asciz	v3;
Asciz	v4;
Asciz	v5;
Asciz	v6;
Asciz	(Lscala/reflect/generic/Universe;)V;
Asciz	java/lang/NullPointerException;
class	java/lang/NullPointerException
Asciz	()V;
NameAndType	"<init>":()V
Method	java/lang/NullPointerException."<init>":()V
Method	java/lang/Object."<init>":()V
Asciz	$init$;
Asciz	(Lscala/Function6;)V;
NameAndType	$init$:(Lscala/Function6;)V
Method	scala/Function6$class.$init$:(Lscala/Function6;)V
Asciz	InnerClasses;
Asciz	scala/reflect/generic/Trees;
class	scala/reflect/generic/Trees
Asciz	Tree;
Asciz	DefDef;
Asciz	Modifiers;
Asciz	scala/Function6;
class	scala/Function6
Asciz	scala/ScalaObject;
class	scala/ScalaObject

{
public final scala.reflect.generic.Universe $outer;
  Signature: Lscala/reflect/generic/Universe;

public java.lang.String toString();
  Signature: ()Ljava/lang/String;
  Code:
   Stack=1, Locals=1, Args_size=1
	aload_0
	invokestatic	Method scala/Function6$class.toString:(Lscala/Function6;)Ljava/lang/String;
	areturn
  Labels:

public scala.Function1 curried();
  Signature: ()Lscala/Function1;
  Code:
   Stack=1, Locals=1, Args_size=1
	aload_0
	invokestatic	Method scala/Function6$class.curried:(Lscala/Function6;)Lscala/Function1;
	areturn
  Labels:

public scala.Function1 curry();
  Signature: ()Lscala/Function1;
  Code:
   Stack=1, Locals=1, Args_size=1
	aload_0
	invokestatic	Method scala/Function6$class.curry:(Lscala/Function6;)Lscala/Function1;
	areturn
  Labels:
  Deprecated: true

public scala.Function1 tupled();
  Signature: ()Lscala/Function1;
  Code:
   Stack=1, Locals=1, Args_size=1
	aload_0
	invokestatic	Method scala/Function6$class.tupled:(Lscala/Function6;)Lscala/Function1;
	areturn
  Labels:

public scala.Option unapply(scala.reflect.generic.Trees$DefDef);
  Signature: (Lscala/reflect/generic/Trees$DefDef;)Lscala/Option;
  Code:
   Stack=10, Locals=2, Args_size=2
	aload_1
	dup
	pop
	ifnull	l1 // getstatic
	aload_1
	aconst_null
	invokevirtual	Method java/lang/Object.equals:(Ljava/lang/Object;)Z
	ifeq	l2 // new
l1	getstatic	Field scala/None$.MODULE$:Lscala/None$;
	goto	l3 // areturn
l2	new	class scala/Some
	dup
	new	class scala/Tuple6
	dup
	aload_1
	invokevirtual	Method scala/reflect/generic/Trees$DefDef.mods:()Lscala/reflect/generic/Trees$Modifiers;
	aload_1
	invokevirtual	Method scala/reflect/generic/Trees$DefDef.name:()Ljava/lang/Object;
	aload_1
	invokevirtual	Method scala/reflect/generic/Trees$DefDef.tparams:()Lscala/collection/immutable/List;
	aload_1
	invokevirtual	Method scala/reflect/generic/Trees$DefDef.vparamss:()Lscala/collection/immutable/List;
	aload_1
	invokevirtual	Method scala/reflect/generic/Trees$DefDef.tpt:()Lscala/reflect/generic/Trees$Tree;
	aload_1
	invokevirtual	Method scala/reflect/generic/Trees$DefDef.rhs:()Lscala/reflect/generic/Trees$Tree;
	invokespecial	Method scala/Tuple6."<init>":(Ljava/lang/Object;Ljava/lang/Object;Ljava/lang/Object;Ljava/lang/Object;Ljava/lang/Object;Ljava/lang/Object;)V
	invokespecial	Method scala/Some."<init>":(Ljava/lang/Object;)V
l3	areturn
  Labels:
   	l1 = 14 // getstatic
   	l2 = 20 // new
   	l3 = 58 // areturn
  LocalVariableTable: 
   Start  Length  Slot  Name   Signature
   0      59      0    this       Lscala/reflect/generic/Trees$DefDef$;
   0      59      1    x$0       Lscala/reflect/generic/Trees$DefDef;


public scala.reflect.generic.Trees$DefDef apply(scala.reflect.generic.Trees$Modifiers, java.lang.Object, scala.collection.immutable.List, scala.collection.immutable.List, scala.reflect.generic.Trees$Tree, scala.reflect.generic.Trees$Tree);
  Signature: (Lscala/reflect/generic/Trees$Modifiers;Ljava/lang/Object;Lscala/collection/immutable/List;Lscala/collection/immutable/List;Lscala/reflect/generic/Trees$Tree;Lscala/reflect/generic/Trees$Tree;)Lscala/reflect/generic/Trees$DefDef;
  Code:
   Stack=9, Locals=8, Args_size=7
	aload_0
	getfield	Field $outer:Lscala/reflect/generic/Universe;
	astore	7
	new	class scala/reflect/generic/Trees$DefDef
	dup
	aload_0
	getfield	Field $outer:Lscala/reflect/generic/Universe;
	aload_1
	aload_2
	aload_3
	aload	4
	aload	5
	aload	6
	invokespecial	Method scala/reflect/generic/Trees$DefDef."<init>":(Lscala/reflect/generic/Universe;Lscala/reflect/generic/Trees$Modifiers;Ljava/lang/Object;Lscala/collection/immutable/List;Lscala/collection/immutable/List;Lscala/reflect/generic/Trees$Tree;Lscala/reflect/generic/Trees$Tree;)V
	areturn
  Labels:
  LocalVariableTable: 
   Start  Length  Slot  Name   Signature
   0      27      0    this       Lscala/reflect/generic/Trees$DefDef$;
   6      21      1    mods       Lscala/reflect/generic/Trees$Modifiers;
   6      21      2    name       Ljava/lang/Object;
   6      21      3    tparams       Lscala/collection/immutable/List;
   6      21      4    vparamss       Lscala/collection/immutable/List;
   6      21      5    tpt       Lscala/reflect/generic/Trees$Tree;
   6      21      6    rhs       Lscala/reflect/generic/Trees$Tree;


public java.lang.Object apply(java.lang.Object, java.lang.Object, java.lang.Object, java.lang.Object, java.lang.Object, java.lang.Object);
  Signature: (Ljava/lang/Object;Ljava/lang/Object;Ljava/lang/Object;Ljava/lang/Object;Ljava/lang/Object;Ljava/lang/Object;)Ljava/lang/Object;
  Code:
   Stack=7, Locals=8, Args_size=7
	aload_0
	getfield	Field $outer:Lscala/reflect/generic/Universe;
	astore	7
	aload_0
	aload_1
	checkcast	class scala/reflect/generic/Trees$Modifiers
	aload_2
	aload_3
	checkcast	class scala/collection/immutable/List
	aload	4
	checkcast	class scala/collection/immutable/List
	aload	5
	checkcast	class scala/reflect/generic/Trees$Tree
	aload	6
	checkcast	class scala/reflect/generic/Trees$Tree
	invokevirtual	Method apply:(Lscala/reflect/generic/Trees$Modifiers;Ljava/lang/Object;Lscala/collection/immutable/List;Lscala/collection/immutable/List;Lscala/reflect/generic/Trees$Tree;Lscala/reflect/generic/Trees$Tree;)Lscala/reflect/generic/Trees$DefDef;
	areturn
  Labels:
  LocalVariableTable: 
   Start  Length  Slot  Name   Signature
   0      35      0    this       Lscala/reflect/generic/Trees$DefDef$;
   6      29      1    v1       Ljava/lang/Object;
   6      29      2    v2       Ljava/lang/Object;
   6      29      3    v3       Ljava/lang/Object;
   6      29      4    v4       Ljava/lang/Object;
   6      29      5    v5       Ljava/lang/Object;
   6      29      6    v6       Ljava/lang/Object;


public scala.reflect.generic.Trees$DefDef$(scala.reflect.generic.Universe);
  Signature: (Lscala/reflect/generic/Universe;)V
  Code:
   Stack=2, Locals=2, Args_size=2
	aload_1
	ifnonnull	l1 // aload_0
	new	class java/lang/NullPointerException
	dup
	invokespecial	Method java/lang/NullPointerException."<init>":()V
	athrow
l1	aload_0
	aload_1
	putfield	Field $outer:Lscala/reflect/generic/Universe;
	aload_0
	invokespecial	Method java/lang/Object."<init>":()V
	aload_0
	invokestatic	Method scala/Function6$class.$init$:(Lscala/Function6;)V
	return
  Labels:
   	l1 = 12 // aload_0
  LocalVariableTable: 
   Start  Length  Slot  Name   Signature
   0      26      0    this       Lscala/reflect/generic/Trees$DefDef$;
   0      26      1    $outer       Lscala/reflect/generic/Universe;


}

