Compiled from "Trees.scala"
public class scala.reflect.generic.Trees$SelectFromArray extends scala.reflect.generic.Trees$Tree implements scala.reflect.generic.Trees$TermTree,scala.reflect.generic.Trees$RefTree,scala.ScalaObject,scala.Product,java.io.Serializable
  SourceFile: "Trees.scala"
  Scala: length = 0x
   
  InnerClass: 
   public abstract Tree=class scala/reflect/generic/Trees$Tree of class scala/reflect/generic/Trees
   public abstract SymTree=class scala/reflect/generic/Trees$SymTree of class scala/reflect/generic/Trees
   public abstract AbsType=class scala/reflect/generic/Types$AbsType of class scala/reflect/generic/Types
   public abstract RefTree=class scala/reflect/generic/Trees$RefTree of class scala/reflect/generic/Trees
   public abstract TermTree=class scala/reflect/generic/Trees$TermTree of class scala/reflect/generic/Trees
   public abstract AbsSymbol=class scala/reflect/generic/Symbols$AbsSymbol of class scala/reflect/generic/Symbols
   public SelectFromArray=class scala/reflect/generic/Trees$SelectFromArray of class scala/reflect/generic/Trees
  minor version: 0
  major version: 49
  Constant pool:
Asciz	SourceFile;
Asciz	Trees.scala;
Asciz	symbol;
Asciz	Lscala/reflect/generic/Symbols$AbsSymbol;;
Asciz	erasure;
Asciz	Lscala/reflect/generic/Types$AbsType;;
Asciz	name;
Asciz	Ljava/lang/Object;;
Asciz	qualifier;
Asciz	Lscala/reflect/generic/Trees$Tree;;
Asciz	()Lscala/reflect/generic/Symbols$AbsSymbol;;
Asciz	Code;
Asciz	LineNumberTable;
Asciz	scala/reflect/generic/Trees$SelectFromArray;
class	scala/reflect/generic/Trees$SelectFromArray
NameAndType	symbol:Lscala/reflect/generic/Symbols$AbsSymbol;
Field	scala/reflect/generic/Trees$SelectFromArray.symbol:Lscala/reflect/generic/Symbols$AbsSymbol;
Asciz	symbol_$eq;
Asciz	(Lscala/reflect/generic/Symbols$AbsSymbol;)V;
Asciz	hasSymbol;
Asciz	()Z;
Asciz	scala/reflect/generic/Trees$SymTree$class;
class	scala/reflect/generic/Trees$SymTree$class
Asciz	(Lscala/reflect/generic/Trees$SymTree;)Z;
NameAndType	hasSymbol:(Lscala/reflect/generic/Trees$SymTree;)Z
Method	scala/reflect/generic/Trees$SymTree$class.hasSymbol:(Lscala/reflect/generic/Trees$SymTree;)Z
Asciz	copy$default$3;
Asciz	()Lscala/reflect/generic/Types$AbsType;;
NameAndType	erasure:()Lscala/reflect/generic/Types$AbsType;
Method	scala/reflect/generic/Trees$SelectFromArray.erasure:()Lscala/reflect/generic/Types$AbsType;
Asciz	copy$default$2;
Asciz	()Ljava/lang/Object;;
NameAndType	name:()Ljava/lang/Object;
Method	scala/reflect/generic/Trees$SelectFromArray.name:()Ljava/lang/Object;
Asciz	copy$default$1;
Asciz	()Lscala/reflect/generic/Trees$Tree;;
NameAndType	qualifier:()Lscala/reflect/generic/Trees$Tree;
Method	scala/reflect/generic/Trees$SelectFromArray.qualifier:()Lscala/reflect/generic/Trees$Tree;
NameAndType	qualifier:Lscala/reflect/generic/Trees$Tree;
Field	scala/reflect/generic/Trees$SelectFromArray.qualifier:Lscala/reflect/generic/Trees$Tree;
NameAndType	name:Ljava/lang/Object;
Field	scala/reflect/generic/Trees$SelectFromArray.name:Ljava/lang/Object;
NameAndType	erasure:Lscala/reflect/generic/Types$AbsType;
Field	scala/reflect/generic/Trees$SelectFromArray.erasure:Lscala/reflect/generic/Types$AbsType;
Asciz	copy;
Asciz	(Lscala/reflect/generic/Trees$Tree;Ljava/lang/Object;Lscala/reflect/generic/Types$AbsType;)Lscala/reflect/generic/Trees$SelectFromArray;;
Asciz	scala$reflect$generic$Trees$SelectFromArray$$$outer;
Asciz	()Lscala/reflect/generic/Universe;;
NameAndType	scala$reflect$generic$Trees$SelectFromArray$$$outer:()Lscala/reflect/generic/Universe;
Method	scala/reflect/generic/Trees$SelectFromArray.scala$reflect$generic$Trees$SelectFromArray$$$outer:()Lscala/reflect/generic/Universe;
Asciz	<init>;
Asciz	(Lscala/reflect/generic/Universe;Lscala/reflect/generic/Trees$Tree;Ljava/lang/Object;Lscala/reflect/generic/Types$AbsType;)V;
NameAndType	"<init>":(Lscala/reflect/generic/Universe;Lscala/reflect/generic/Trees$Tree;Ljava/lang/Object;Lscala/reflect/generic/Types$AbsType;)V
Method	scala/reflect/generic/Trees$SelectFromArray."<init>":(Lscala/reflect/generic/Universe;Lscala/reflect/generic/Trees$Tree;Ljava/lang/Object;Lscala/reflect/generic/Types$AbsType;)V
Asciz	this;
Asciz	Lscala/reflect/generic/Trees$SelectFromArray;;
Asciz	LocalVariableTable;
Asciz	productPrefix;
Asciz	()Ljava/lang/String;;
Asciz	SelectFromArray;
String	SelectFromArray
Asciz	productArity;
Asciz	()I;
Asciz	productElement;
Asciz	(I)Ljava/lang/Object;;
Asciz	java/lang/IndexOutOfBoundsException;
class	java/lang/IndexOutOfBoundsException
Asciz	scala/runtime/BoxesRunTime;
class	scala/runtime/BoxesRunTime
Asciz	boxToInteger;
Asciz	(I)Ljava/lang/Integer;;
NameAndType	boxToInteger:(I)Ljava/lang/Integer;
Method	scala/runtime/BoxesRunTime.boxToInteger:(I)Ljava/lang/Integer;
Asciz	java/lang/Object;
class	java/lang/Object
Asciz	toString;
NameAndType	toString:()Ljava/lang/String;
Method	java/lang/Object.toString:()Ljava/lang/String;
Asciz	(Ljava/lang/String;)V;
NameAndType	"<init>":(Ljava/lang/String;)V
Method	java/lang/IndexOutOfBoundsException."<init>":(Ljava/lang/String;)V
Asciz	temp267;
Asciz	I;
Asciz	productElementName;
Asciz	(I)Ljava/lang/String;;
String	erasure
String	name
String	qualifier
Asciz	temp268;
Asciz	canEqual;
Asciz	(Ljava/lang/Object;)Z;
Asciz	scala/reflect/generic/Trees$Tree;
class	scala/reflect/generic/Trees$Tree
Asciz	$outer;
Asciz	Lscala/reflect/generic/Universe;;
NameAndType	$outer:Lscala/reflect/generic/Universe;
Field	scala/reflect/generic/Trees$Tree.$outer:Lscala/reflect/generic/Universe;
Asciz	scala$reflect$generic$Trees$SymTree$$$outer;
Asciz	()Lscala/reflect/generic/Trees;;
Asciz	(Lscala/reflect/generic/Universe;)V;
NameAndType	"<init>":(Lscala/reflect/generic/Universe;)V
Method	scala/reflect/generic/Trees$Tree."<init>":(Lscala/reflect/generic/Universe;)V
Asciz	$init$;
Asciz	(Lscala/reflect/generic/Trees$SymTree;)V;
NameAndType	$init$:(Lscala/reflect/generic/Trees$SymTree;)V
Method	scala/reflect/generic/Trees$SymTree$class.$init$:(Lscala/reflect/generic/Trees$SymTree;)V
Asciz	Scala;
Asciz	InnerClasses;
Asciz	scala/reflect/generic/Trees;
class	scala/reflect/generic/Trees
Asciz	Tree;
Asciz	scala/reflect/generic/Trees$SymTree;
class	scala/reflect/generic/Trees$SymTree
Asciz	SymTree;
Asciz	scala/reflect/generic/Types$AbsType;
class	scala/reflect/generic/Types$AbsType
Asciz	scala/reflect/generic/Types;
class	scala/reflect/generic/Types
Asciz	AbsType;
Asciz	scala/reflect/generic/Trees$RefTree;
class	scala/reflect/generic/Trees$RefTree
Asciz	RefTree;
Asciz	scala/reflect/generic/Trees$TermTree;
class	scala/reflect/generic/Trees$TermTree
Asciz	TermTree;
Asciz	scala/reflect/generic/Symbols$AbsSymbol;
class	scala/reflect/generic/Symbols$AbsSymbol
Asciz	scala/reflect/generic/Symbols;
class	scala/reflect/generic/Symbols
Asciz	AbsSymbol;
Asciz	scala/ScalaObject;
class	scala/ScalaObject
Asciz	scala/Product;
class	scala/Product
Asciz	java/io/Serializable;
class	java/io/Serializable

{
private scala.reflect.generic.Symbols$AbsSymbol symbol;
  Signature: Lscala/reflect/generic/Symbols$AbsSymbol;

private final scala.reflect.generic.Types$AbsType erasure;
  Signature: Lscala/reflect/generic/Types$AbsType;

private final java.lang.Object name;
  Signature: Ljava/lang/Object;

private final scala.reflect.generic.Trees$Tree qualifier;
  Signature: Lscala/reflect/generic/Trees$Tree;

public scala.reflect.generic.Symbols$AbsSymbol symbol();
  Signature: ()Lscala/reflect/generic/Symbols$AbsSymbol;
  Code:
   Stack=1, Locals=1, Args_size=1
	aload_0
	getfield	Field symbol:Lscala/reflect/generic/Symbols$AbsSymbol;
	areturn
  Labels:

public void symbol_$eq(scala.reflect.generic.Symbols$AbsSymbol);
  Signature: (Lscala/reflect/generic/Symbols$AbsSymbol;)V
  Code:
   Stack=2, Locals=2, Args_size=2
	aload_0
	aload_1
	putfield	Field symbol:Lscala/reflect/generic/Symbols$AbsSymbol;
	return
  Labels:

public boolean hasSymbol();
  Signature: ()Z
  Code:
   Stack=1, Locals=1, Args_size=1
	aload_0
	invokestatic	Method scala/reflect/generic/Trees$SymTree$class.hasSymbol:(Lscala/reflect/generic/Trees$SymTree;)Z
	ireturn
  Labels:

public scala.reflect.generic.Types$AbsType copy$default$3();
  Signature: ()Lscala/reflect/generic/Types$AbsType;
  Code:
   Stack=1, Locals=1, Args_size=1
	aload_0
	invokevirtual	Method erasure:()Lscala/reflect/generic/Types$AbsType;
	areturn
  Labels:

public java.lang.Object copy$default$2();
  Signature: ()Ljava/lang/Object;
  Code:
   Stack=1, Locals=1, Args_size=1
	aload_0
	invokevirtual	Method name:()Ljava/lang/Object;
	areturn
  Labels:

public scala.reflect.generic.Trees$Tree copy$default$1();
  Signature: ()Lscala/reflect/generic/Trees$Tree;
  Code:
   Stack=1, Locals=1, Args_size=1
	aload_0
	invokevirtual	Method qualifier:()Lscala/reflect/generic/Trees$Tree;
	areturn
  Labels:

public scala.reflect.generic.Trees$Tree qualifier();
  Signature: ()Lscala/reflect/generic/Trees$Tree;
  Code:
   Stack=1, Locals=1, Args_size=1
	aload_0
	getfield	Field qualifier:Lscala/reflect/generic/Trees$Tree;
	areturn
  Labels:

public java.lang.Object name();
  Signature: ()Ljava/lang/Object;
  Code:
   Stack=1, Locals=1, Args_size=1
	aload_0
	getfield	Field name:Ljava/lang/Object;
	areturn
  Labels:

public scala.reflect.generic.Types$AbsType erasure();
  Signature: ()Lscala/reflect/generic/Types$AbsType;
  Code:
   Stack=1, Locals=1, Args_size=1
	aload_0
	getfield	Field erasure:Lscala/reflect/generic/Types$AbsType;
	areturn
  Labels:

public scala.reflect.generic.Trees$SelectFromArray copy(scala.reflect.generic.Trees$Tree, java.lang.Object, scala.reflect.generic.Types$AbsType);
  Signature: (Lscala/reflect/generic/Trees$Tree;Ljava/lang/Object;Lscala/reflect/generic/Types$AbsType;)Lscala/reflect/generic/Trees$SelectFromArray;
  Code:
   Stack=6, Locals=4, Args_size=4
	new	class scala/reflect/generic/Trees$SelectFromArray
	dup
	aload_0
	invokevirtual	Method scala$reflect$generic$Trees$SelectFromArray$$$outer:()Lscala/reflect/generic/Universe;
	aload_1
	aload_2
	aload_3
	invokespecial	Method "<init>":(Lscala/reflect/generic/Universe;Lscala/reflect/generic/Trees$Tree;Ljava/lang/Object;Lscala/reflect/generic/Types$AbsType;)V
	areturn
  Labels:
  LocalVariableTable: 
   Start  Length  Slot  Name   Signature
   0      15      0    this       Lscala/reflect/generic/Trees$SelectFromArray;
   0      15      1    qualifier       Lscala/reflect/generic/Trees$Tree;
   0      15      2    name       Ljava/lang/Object;
   0      15      3    erasure       Lscala/reflect/generic/Types$AbsType;


public java.lang.String productPrefix();
  Signature: ()Ljava/lang/String;
  Code:
   Stack=1, Locals=1, Args_size=1
	ldc	String SelectFromArray
	areturn
  Labels:

public int productArity();
  Signature: ()I
  Code:
   Stack=1, Locals=1, Args_size=1
	iconst_3
	ireturn
  Labels:

public java.lang.Object productElement(int);
  Signature: (I)Ljava/lang/Object;
  Code:
   Stack=3, Locals=3, Args_size=2
	iload_1
	istore_2
	iload_2
	tableswitch{ //0 to 2
		0: 57;
		1: 50;
		2: 43;
		default: 28 }
	new	class java/lang/IndexOutOfBoundsException
	dup
	iload_1
	invokestatic	Method scala/runtime/BoxesRunTime.boxToInteger:(I)Ljava/lang/Integer;
	invokevirtual	Method java/lang/Object.toString:()Ljava/lang/String;
	invokespecial	Method java/lang/IndexOutOfBoundsException."<init>":(Ljava/lang/String;)V
	athrow
	aload_0
	invokevirtual	Method erasure:()Lscala/reflect/generic/Types$AbsType;
	goto	l1 // areturn
	aload_0
	invokevirtual	Method name:()Ljava/lang/Object;
	goto	l1 // areturn
	aload_0
	invokevirtual	Method qualifier:()Lscala/reflect/generic/Trees$Tree;
l1	areturn
  Labels:
   	l1 = 61 // areturn
  LocalVariableTable: 
   Start  Length  Slot  Name   Signature
   0      62      0    this       Lscala/reflect/generic/Trees$SelectFromArray;
   2      60      2    temp267       I


public java.lang.String productElementName(int);
  Signature: (I)Ljava/lang/String;
  Code:
   Stack=3, Locals=3, Args_size=2
	iload_1
	istore_2
	iload_2
	tableswitch{ //0 to 2
		0: 53;
		1: 48;
		2: 43;
		default: 28 }
	new	class java/lang/IndexOutOfBoundsException
	dup
	iload_1
	invokestatic	Method scala/runtime/BoxesRunTime.boxToInteger:(I)Ljava/lang/Integer;
	invokevirtual	Method java/lang/Object.toString:()Ljava/lang/String;
	invokespecial	Method java/lang/IndexOutOfBoundsException."<init>":(Ljava/lang/String;)V
	athrow
	ldc	String erasure
	goto	l1 // areturn
	ldc	String name
	goto	l1 // areturn
	ldc	String qualifier
l1	areturn
  Labels:
   	l1 = 55 // areturn
  LocalVariableTable: 
   Start  Length  Slot  Name   Signature
   0      56      0    this       Lscala/reflect/generic/Trees$SelectFromArray;
   2      54      2    temp268       I


public boolean canEqual(java.lang.Object);
  Signature: (Ljava/lang/Object;)Z
  Code:
   Stack=1, Locals=2, Args_size=2
	aload_1
	instanceof	class scala/reflect/generic/Trees$SelectFromArray
	ireturn
  Labels:

public scala.reflect.generic.Universe scala$reflect$generic$Trees$SelectFromArray$$$outer();
  Signature: ()Lscala/reflect/generic/Universe;
  Code:
   Stack=1, Locals=1, Args_size=1
	aload_0
	getfield	Field scala/reflect/generic/Trees$Tree.$outer:Lscala/reflect/generic/Universe;
	areturn
  Labels:

public scala.reflect.generic.Trees scala$reflect$generic$Trees$SymTree$$$outer();
  Signature: ()Lscala/reflect/generic/Trees;
  Code:
   Stack=1, Locals=1, Args_size=1
	aload_0
	invokevirtual	Method scala$reflect$generic$Trees$SelectFromArray$$$outer:()Lscala/reflect/generic/Universe;
	areturn
  Labels:

public scala.reflect.generic.Trees$SelectFromArray(scala.reflect.generic.Universe, scala.reflect.generic.Trees$Tree, java.lang.Object, scala.reflect.generic.Types$AbsType);
  Signature: (Lscala/reflect/generic/Universe;Lscala/reflect/generic/Trees$Tree;Ljava/lang/Object;Lscala/reflect/generic/Types$AbsType;)V
  Code:
   Stack=2, Locals=5, Args_size=5
	aload_0
	aload_2
	putfield	Field qualifier:Lscala/reflect/generic/Trees$Tree;
	aload_0
	aload_3
	putfield	Field name:Ljava/lang/Object;
	aload_0
	aload	4
	putfield	Field erasure:Lscala/reflect/generic/Types$AbsType;
	aload_0
	aload_1
	invokespecial	Method scala/reflect/generic/Trees$Tree."<init>":(Lscala/reflect/generic/Universe;)V
	aload_0
	invokestatic	Method scala/reflect/generic/Trees$SymTree$class.$init$:(Lscala/reflect/generic/Trees$SymTree;)V
	return
  Labels:
  LocalVariableTable: 
   Start  Length  Slot  Name   Signature
   0      26      0    this       Lscala/reflect/generic/Trees$SelectFromArray;
   0      26      1    $outer       Lscala/reflect/generic/Universe;
   0      26      2    qualifier       Lscala/reflect/generic/Trees$Tree;
   0      26      3    name       Ljava/lang/Object;
   0      26      4    erasure       Lscala/reflect/generic/Types$AbsType;


}

