Compiled from "Trees.scala"
public final class scala.reflect.generic.Trees$Traverser$$anonfun$traverseTrees$1 extends scala.runtime.AbstractFunction1 implements java.io.Serializable
  SourceFile: "Trees.scala"
  Scala: length = 0x
   
  InnerClass: 
   public abstract Tree=class scala/reflect/generic/Trees$Tree of class scala/reflect/generic/Trees
   public Traverser=class scala/reflect/generic/Trees$Traverser of class scala/reflect/generic/Trees
   public final $anonfun$traverseTrees$1=class scala/reflect/generic/Trees$Traverser$$anonfun$traverseTrees$1 of class scala/reflect/generic/Trees$Traverser
  minor version: 0
  major version: 49
  Constant pool:
Asciz	SourceFile;
Asciz	Trees.scala;
Asciz	<clinit>;
Asciz	()V;
Asciz	Code;
Asciz	serialVersionUID;
Asciz	J;
Asciz	scala/reflect/generic/Trees$Traverser$$anonfun$traverseTrees$1;
class	scala/reflect/generic/Trees$Traverser$$anonfun$traverseTrees$1
NameAndType	serialVersionUID:J
Field	scala/reflect/generic/Trees$Traverser$$anonfun$traverseTrees$1.serialVersionUID:J
Asciz	$outer;
Asciz	Lscala/reflect/generic/Trees$Traverser;;
Asciz	apply;
Asciz	(Lscala/reflect/generic/Trees$Tree;)V;
Asciz	LineNumberTable;
NameAndType	$outer:Lscala/reflect/generic/Trees$Traverser;
Field	scala/reflect/generic/Trees$Traverser$$anonfun$traverseTrees$1.$outer:Lscala/reflect/generic/Trees$Traverser;
Asciz	scala/reflect/generic/Trees$Traverser;
class	scala/reflect/generic/Trees$Traverser
Asciz	traverse;
NameAndType	traverse:(Lscala/reflect/generic/Trees$Tree;)V
Method	scala/reflect/generic/Trees$Traverser.traverse:(Lscala/reflect/generic/Trees$Tree;)V
Asciz	(Ljava/lang/Object;)Ljava/lang/Object;;
Asciz	scala/reflect/generic/Trees$Tree;
class	scala/reflect/generic/Trees$Tree
NameAndType	apply:(Lscala/reflect/generic/Trees$Tree;)V
Method	scala/reflect/generic/Trees$Traverser$$anonfun$traverseTrees$1.apply:(Lscala/reflect/generic/Trees$Tree;)V
Asciz	scala/runtime/BoxedUnit;
class	scala/runtime/BoxedUnit
Asciz	UNIT;
Asciz	Lscala/runtime/BoxedUnit;;
NameAndType	UNIT:Lscala/runtime/BoxedUnit;
Field	scala/runtime/BoxedUnit.UNIT:Lscala/runtime/BoxedUnit;
Asciz	this;
Asciz	Lscala/reflect/generic/Trees$Traverser$$anonfun$traverseTrees$1;;
Asciz	v1;
Asciz	Ljava/lang/Object;;
Asciz	LocalVariableTable;
Asciz	<init>;
Asciz	(Lscala/reflect/generic/Trees$Traverser;)V;
Asciz	java/lang/NullPointerException;
class	java/lang/NullPointerException
NameAndType	"<init>":()V
Method	java/lang/NullPointerException."<init>":()V
Asciz	scala/runtime/AbstractFunction1;
class	scala/runtime/AbstractFunction1
Method	scala/runtime/AbstractFunction1."<init>":()V
Asciz	Scala;
Asciz	InnerClasses;
Asciz	scala/reflect/generic/Trees;
class	scala/reflect/generic/Trees
Asciz	Tree;
Asciz	Traverser;
Asciz	$anonfun$traverseTrees$1;
Asciz	java/io/Serializable;
class	java/io/Serializable

{
public static final long serialVersionUID;
  Signature: J

public final scala.reflect.generic.Trees$Traverser $outer;
  Signature: Lscala/reflect/generic/Trees$Traverser;

public static {};
  Signature: ()V
  Code:
   Stack=2, Locals=0, Args_size=0
	lconst_0
	putstatic	Field serialVersionUID:J
	return
  Labels:

public final void apply(scala.reflect.generic.Trees$Tree);
  Signature: (Lscala/reflect/generic/Trees$Tree;)V
  Code:
   Stack=2, Locals=2, Args_size=2
	aload_0
	getfield	Field $outer:Lscala/reflect/generic/Trees$Traverser;
	aload_1
	invokevirtual	Method scala/reflect/generic/Trees$Traverser.traverse:(Lscala/reflect/generic/Trees$Tree;)V
	return
  Labels:

public final java.lang.Object apply(java.lang.Object);
  Signature: (Ljava/lang/Object;)Ljava/lang/Object;
  Code:
   Stack=2, Locals=2, Args_size=2
	aload_0
	aload_1
	checkcast	class scala/reflect/generic/Trees$Tree
	invokevirtual	Method apply:(Lscala/reflect/generic/Trees$Tree;)V
	getstatic	Field scala/runtime/BoxedUnit.UNIT:Lscala/runtime/BoxedUnit;
	areturn
  Labels:
  LocalVariableTable: 
   Start  Length  Slot  Name   Signature
   0      12      0    this       Lscala/reflect/generic/Trees$Traverser$$anonfun$traverseTrees$1;
   0      12      1    v1       Ljava/lang/Object;


public scala.reflect.generic.Trees$Traverser$$anonfun$traverseTrees$1(scala.reflect.generic.Trees$Traverser);
  Signature: (Lscala/reflect/generic/Trees$Traverser;)V
  Code:
   Stack=2, Locals=2, Args_size=2
	aload_1
	ifnonnull	l1 // aload_0
	new	class java/lang/NullPointerException
	dup
	invokespecial	Method java/lang/NullPointerException."<init>":()V
	athrow
l1	aload_0
	aload_1
	putfield	Field $outer:Lscala/reflect/generic/Trees$Traverser;
	aload_0
	invokespecial	Method scala/runtime/AbstractFunction1."<init>":()V
	return
  Labels:
   	l1 = 12 // aload_0
  LocalVariableTable: 
   Start  Length  Slot  Name   Signature
   0      22      0    this       Lscala/reflect/generic/Trees$Traverser$$anonfun$traverseTrees$1;
   0      22      1    $outer       Lscala/reflect/generic/Trees$Traverser;


}

