Compiled from "Trees.scala"
public class scala.reflect.generic.Trees$Try extends scala.reflect.generic.Trees$Tree implements scala.reflect.generic.Trees$TermTree,scala.ScalaObject,scala.Product,java.io.Serializable
  SourceFile: "Trees.scala"
  Scala: length = 0x
   
  InnerClass: 
   public Try=class scala/reflect/generic/Trees$Try of class scala/reflect/generic/Trees
   public abstract Tree=class scala/reflect/generic/Trees$Tree of class scala/reflect/generic/Trees
   public abstract TermTree=class scala/reflect/generic/Trees$TermTree of class scala/reflect/generic/Trees
  minor version: 0
  major version: 49
  Constant pool:
Asciz	SourceFile;
Asciz	Trees.scala;
Asciz	finalizer;
Asciz	Lscala/reflect/generic/Trees$Tree;;
Asciz	catches;
Asciz	Lscala/collection/immutable/List;;
Asciz	Lscala/collection/immutable/List<Lscala/reflect/generic/Trees$CaseDef;>;;
Asciz	Signature;
Asciz	block;
Asciz	copy$default$3;
Asciz	()Lscala/reflect/generic/Trees$Tree;;
Asciz	Code;
Asciz	LineNumberTable;
Asciz	scala/reflect/generic/Trees$Try;
class	scala/reflect/generic/Trees$Try
NameAndType	finalizer:()Lscala/reflect/generic/Trees$Tree;
Method	scala/reflect/generic/Trees$Try.finalizer:()Lscala/reflect/generic/Trees$Tree;
Asciz	copy$default$2;
Asciz	()Lscala/collection/immutable/List;;
NameAndType	catches:()Lscala/collection/immutable/List;
Method	scala/reflect/generic/Trees$Try.catches:()Lscala/collection/immutable/List;
Asciz	copy$default$1;
NameAndType	block:()Lscala/reflect/generic/Trees$Tree;
Method	scala/reflect/generic/Trees$Try.block:()Lscala/reflect/generic/Trees$Tree;
NameAndType	block:Lscala/reflect/generic/Trees$Tree;
Field	scala/reflect/generic/Trees$Try.block:Lscala/reflect/generic/Trees$Tree;
NameAndType	catches:Lscala/collection/immutable/List;
Field	scala/reflect/generic/Trees$Try.catches:Lscala/collection/immutable/List;
Asciz	()Lscala/collection/immutable/List<Lscala/reflect/generic/Trees$CaseDef;>;;
NameAndType	finalizer:Lscala/reflect/generic/Trees$Tree;
Field	scala/reflect/generic/Trees$Try.finalizer:Lscala/reflect/generic/Trees$Tree;
Asciz	copy;
Asciz	(Lscala/reflect/generic/Trees$Tree;Lscala/collection/immutable/List;Lscala/reflect/generic/Trees$Tree;)Lscala/reflect/generic/Trees$Try;;
Asciz	scala$reflect$generic$Trees$Try$$$outer;
Asciz	()Lscala/reflect/generic/Universe;;
NameAndType	scala$reflect$generic$Trees$Try$$$outer:()Lscala/reflect/generic/Universe;
Method	scala/reflect/generic/Trees$Try.scala$reflect$generic$Trees$Try$$$outer:()Lscala/reflect/generic/Universe;
Asciz	<init>;
Asciz	(Lscala/reflect/generic/Universe;Lscala/reflect/generic/Trees$Tree;Lscala/collection/immutable/List;Lscala/reflect/generic/Trees$Tree;)V;
NameAndType	"<init>":(Lscala/reflect/generic/Universe;Lscala/reflect/generic/Trees$Tree;Lscala/collection/immutable/List;Lscala/reflect/generic/Trees$Tree;)V
Method	scala/reflect/generic/Trees$Try."<init>":(Lscala/reflect/generic/Universe;Lscala/reflect/generic/Trees$Tree;Lscala/collection/immutable/List;Lscala/reflect/generic/Trees$Tree;)V
Asciz	this;
Asciz	Lscala/reflect/generic/Trees$Try;;
Asciz	LocalVariableTable;
Asciz	productPrefix;
Asciz	()Ljava/lang/String;;
Asciz	Try;
String	Try
Asciz	productArity;
Asciz	()I;
Asciz	productElement;
Asciz	(I)Ljava/lang/Object;;
Asciz	java/lang/IndexOutOfBoundsException;
class	java/lang/IndexOutOfBoundsException
Asciz	scala/runtime/BoxesRunTime;
class	scala/runtime/BoxesRunTime
Asciz	boxToInteger;
Asciz	(I)Ljava/lang/Integer;;
NameAndType	boxToInteger:(I)Ljava/lang/Integer;
Method	scala/runtime/BoxesRunTime.boxToInteger:(I)Ljava/lang/Integer;
Asciz	java/lang/Object;
class	java/lang/Object
Asciz	toString;
NameAndType	toString:()Ljava/lang/String;
Method	java/lang/Object.toString:()Ljava/lang/String;
Asciz	(Ljava/lang/String;)V;
NameAndType	"<init>":(Ljava/lang/String;)V
Method	java/lang/IndexOutOfBoundsException."<init>":(Ljava/lang/String;)V
Asciz	productElementName;
Asciz	(I)Ljava/lang/String;;
String	finalizer
String	catches
String	block
Asciz	canEqual;
Asciz	(Ljava/lang/Object;)Z;
Asciz	scala/reflect/generic/Trees$Tree;
class	scala/reflect/generic/Trees$Tree
Asciz	$outer;
Asciz	Lscala/reflect/generic/Universe;;
NameAndType	$outer:Lscala/reflect/generic/Universe;
Field	scala/reflect/generic/Trees$Tree.$outer:Lscala/reflect/generic/Universe;
Asciz	(Lscala/reflect/generic/Universe;)V;
NameAndType	"<init>":(Lscala/reflect/generic/Universe;)V
Method	scala/reflect/generic/Trees$Tree."<init>":(Lscala/reflect/generic/Universe;)V
Asciz	(Lscala/reflect/generic/Universe;Lscala/reflect/generic/Trees$Tree;Lscala/collection/immutable/List<Lscala/reflect/generic/Trees$CaseDef;>;Lscala/reflect/generic/Trees$Tree;)V;
Asciz	Scala;
Asciz	InnerClasses;
Asciz	scala/reflect/generic/Trees;
class	scala/reflect/generic/Trees
Asciz	Tree;
Asciz	scala/reflect/generic/Trees$TermTree;
class	scala/reflect/generic/Trees$TermTree
Asciz	TermTree;
Asciz	scala/ScalaObject;
class	scala/ScalaObject
Asciz	scala/Product;
class	scala/Product
Asciz	java/io/Serializable;
class	java/io/Serializable

{
private final scala.reflect.generic.Trees$Tree finalizer;
  Signature: Lscala/reflect/generic/Trees$Tree;

private final scala.collection.immutable.List catches;
  Signature: Lscala/collection/immutable/List;
  Signature: length = 0x2
   00 07 

private final scala.reflect.generic.Trees$Tree block;
  Signature: Lscala/reflect/generic/Trees$Tree;

public scala.reflect.generic.Trees$Tree copy$default$3();
  Signature: ()Lscala/reflect/generic/Trees$Tree;
  Code:
   Stack=1, Locals=1, Args_size=1
	aload_0
	invokevirtual	Method finalizer:()Lscala/reflect/generic/Trees$Tree;
	areturn
  Labels:

public scala.collection.immutable.List copy$default$2();
  Signature: ()Lscala/collection/immutable/List;
  Code:
   Stack=1, Locals=1, Args_size=1
	aload_0
	invokevirtual	Method catches:()Lscala/collection/immutable/List;
	areturn
  Labels:

public scala.reflect.generic.Trees$Tree copy$default$1();
  Signature: ()Lscala/reflect/generic/Trees$Tree;
  Code:
   Stack=1, Locals=1, Args_size=1
	aload_0
	invokevirtual	Method block:()Lscala/reflect/generic/Trees$Tree;
	areturn
  Labels:

public scala.reflect.generic.Trees$Tree block();
  Signature: ()Lscala/reflect/generic/Trees$Tree;
  Code:
   Stack=1, Locals=1, Args_size=1
	aload_0
	getfield	Field block:Lscala/reflect/generic/Trees$Tree;
	areturn
  Labels:

public scala.collection.immutable.List catches();
  Signature: ()Lscala/collection/immutable/List;
  Code:
   Stack=1, Locals=1, Args_size=1
	aload_0
	getfield	Field catches:Lscala/collection/immutable/List;
	areturn
  Labels:
  Signature: length = 0x2
   00 1D 

public scala.reflect.generic.Trees$Tree finalizer();
  Signature: ()Lscala/reflect/generic/Trees$Tree;
  Code:
   Stack=1, Locals=1, Args_size=1
	aload_0
	getfield	Field finalizer:Lscala/reflect/generic/Trees$Tree;
	areturn
  Labels:

public scala.reflect.generic.Trees$Try copy(scala.reflect.generic.Trees$Tree, scala.collection.immutable.List, scala.reflect.generic.Trees$Tree);
  Signature: (Lscala/reflect/generic/Trees$Tree;Lscala/collection/immutable/List;Lscala/reflect/generic/Trees$Tree;)Lscala/reflect/generic/Trees$Try;
  Code:
   Stack=6, Locals=4, Args_size=4
	new	class scala/reflect/generic/Trees$Try
	dup
	aload_0
	invokevirtual	Method scala$reflect$generic$Trees$Try$$$outer:()Lscala/reflect/generic/Universe;
	aload_1
	aload_2
	aload_3
	invokespecial	Method "<init>":(Lscala/reflect/generic/Universe;Lscala/reflect/generic/Trees$Tree;Lscala/collection/immutable/List;Lscala/reflect/generic/Trees$Tree;)V
	areturn
  Labels:
  LocalVariableTable: 
   Start  Length  Slot  Name   Signature
   0      15      0    this       Lscala/reflect/generic/Trees$Try;
   0      15      1    block       Lscala/reflect/generic/Trees$Tree;
   0      15      2    catches       Lscala/collection/immutable/List;
   0      15      3    finalizer       Lscala/reflect/generic/Trees$Tree;


public java.lang.String productPrefix();
  Signature: ()Ljava/lang/String;
  Code:
   Stack=1, Locals=1, Args_size=1
	ldc	String Try
	areturn
  Labels:

public int productArity();
  Signature: ()I
  Code:
   Stack=1, Locals=1, Args_size=1
	iconst_3
	ireturn
  Labels:

public java.lang.Object productElement(int);
  Signature: (I)Ljava/lang/Object;
  Code:
   Stack=3, Locals=2, Args_size=2
	iload_1
	tableswitch{ //0 to 2
		0: 57;
		1: 50;
		2: 43;
		default: 28 }
	new	class java/lang/IndexOutOfBoundsException
	dup
	iload_1
	invokestatic	Method scala/runtime/BoxesRunTime.boxToInteger:(I)Ljava/lang/Integer;
	invokevirtual	Method java/lang/Object.toString:()Ljava/lang/String;
	invokespecial	Method java/lang/IndexOutOfBoundsException."<init>":(Ljava/lang/String;)V
	athrow
	aload_0
	invokevirtual	Method finalizer:()Lscala/reflect/generic/Trees$Tree;
	goto	l1 // areturn
	aload_0
	invokevirtual	Method catches:()Lscala/collection/immutable/List;
	goto	l1 // areturn
	aload_0
	invokevirtual	Method block:()Lscala/reflect/generic/Trees$Tree;
l1	areturn
  Labels:
   	l1 = 61 // areturn

public java.lang.String productElementName(int);
  Signature: (I)Ljava/lang/String;
  Code:
   Stack=3, Locals=2, Args_size=2
	iload_1
	tableswitch{ //0 to 2
		0: 53;
		1: 48;
		2: 43;
		default: 28 }
	new	class java/lang/IndexOutOfBoundsException
	dup
	iload_1
	invokestatic	Method scala/runtime/BoxesRunTime.boxToInteger:(I)Ljava/lang/Integer;
	invokevirtual	Method java/lang/Object.toString:()Ljava/lang/String;
	invokespecial	Method java/lang/IndexOutOfBoundsException."<init>":(Ljava/lang/String;)V
	athrow
	ldc	String finalizer
	goto	l1 // areturn
	ldc	String catches
	goto	l1 // areturn
	ldc	String block
l1	areturn
  Labels:
   	l1 = 55 // areturn

public boolean canEqual(java.lang.Object);
  Signature: (Ljava/lang/Object;)Z
  Code:
   Stack=1, Locals=2, Args_size=2
	aload_1
	instanceof	class scala/reflect/generic/Trees$Try
	ireturn
  Labels:

public scala.reflect.generic.Universe scala$reflect$generic$Trees$Try$$$outer();
  Signature: ()Lscala/reflect/generic/Universe;
  Code:
   Stack=1, Locals=1, Args_size=1
	aload_0
	getfield	Field scala/reflect/generic/Trees$Tree.$outer:Lscala/reflect/generic/Universe;
	areturn
  Labels:

public scala.reflect.generic.Trees$Try(scala.reflect.generic.Universe, scala.reflect.generic.Trees$Tree, scala.collection.immutable.List, scala.reflect.generic.Trees$Tree);
  Signature: (Lscala/reflect/generic/Universe;Lscala/reflect/generic/Trees$Tree;Lscala/collection/immutable/List;Lscala/reflect/generic/Trees$Tree;)V
  Code:
   Stack=2, Locals=5, Args_size=5
	aload_0
	aload_2
	putfield	Field block:Lscala/reflect/generic/Trees$Tree;
	aload_0
	aload_3
	putfield	Field catches:Lscala/collection/immutable/List;
	aload_0
	aload	4
	putfield	Field finalizer:Lscala/reflect/generic/Trees$Tree;
	aload_0
	aload_1
	invokespecial	Method scala/reflect/generic/Trees$Tree."<init>":(Lscala/reflect/generic/Universe;)V
	return
  Labels:
  LocalVariableTable: 
   Start  Length  Slot  Name   Signature
   0      22      0    this       Lscala/reflect/generic/Trees$Try;
   0      22      1    $outer       Lscala/reflect/generic/Universe;
   0      22      2    block       Lscala/reflect/generic/Trees$Tree;
   0      22      3    catches       Lscala/collection/immutable/List;
   0      22      4    finalizer       Lscala/reflect/generic/Trees$Tree;

  Signature: length = 0x2
   00 55 

}

