Compiled from "Trees.scala"
public abstract class scala.reflect.generic.Trees$class extends java.lang.Object
  SourceFile: "Trees.scala"
  Scala: length = 0x
   
  InnerClass: 
   public abstract Tree=class scala/reflect/generic/Trees$Tree of class scala/reflect/generic/Trees
   public EmptyMap=class scala/collection/immutable/Map$EmptyMap of class scala/collection/immutable/Map
   public Literal=class scala/reflect/generic/Trees$Literal of class scala/reflect/generic/Trees
   public Modifiers=class scala/reflect/generic/Trees$Modifiers of class scala/reflect/generic/Trees
   public Constant=class scala/reflect/generic/Constants$Constant of class scala/reflect/generic/Constants
   public StandardNames=class scala/reflect/generic/StdNames$StandardNames of class scala/reflect/generic/StdNames
  minor version: 0
  major version: 49
  Constant pool:
Asciz	SourceFile;
Asciz	Trees.scala;
Asciz	Modifiers;
Asciz	(Lscala/reflect/generic/Universe;JLjava/lang/Object;)Lscala/reflect/generic/Trees$Modifiers;;
Asciz	Code;
Asciz	scala/reflect/generic/Trees$Modifiers;
class	scala/reflect/generic/Trees$Modifiers
Asciz	LineNumberTable;
Asciz	scala/collection/immutable/Nil$;
class	scala/collection/immutable/Nil$
Asciz	MODULE$;
Asciz	Lscala/collection/immutable/Nil$;;
NameAndType	MODULE$:Lscala/collection/immutable/Nil$;
Field	scala/collection/immutable/Nil$.MODULE$:Lscala/collection/immutable/Nil$;
Asciz	scala/collection/immutable/Map$EmptyMap;
class	scala/collection/immutable/Map$EmptyMap
Asciz	<init>;
Asciz	()V;
NameAndType	"<init>":()V
Method	scala/collection/immutable/Map$EmptyMap."<init>":()V
Asciz	(Lscala/reflect/generic/Universe;JLjava/lang/Object;Lscala/collection/immutable/List;Lscala/collection/immutable/Map;)V;
NameAndType	"<init>":(Lscala/reflect/generic/Universe;JLjava/lang/Object;Lscala/collection/immutable/List;Lscala/collection/immutable/Map;)V
Method	scala/reflect/generic/Trees$Modifiers."<init>":(Lscala/reflect/generic/Universe;JLjava/lang/Object;Lscala/collection/immutable/List;Lscala/collection/immutable/Map;)V
Asciz	$this;
Asciz	Lscala/reflect/generic/Universe;;
Asciz	flags;
Asciz	J;
Asciz	privateWithin;
Asciz	Ljava/lang/Object;;
Asciz	LocalVariableTable;
Asciz	(Lscala/reflect/generic/Universe;J)Lscala/reflect/generic/Trees$Modifiers;;
Asciz	scala/reflect/generic/StdNames;
class	scala/reflect/generic/StdNames
Asciz	nme;
Asciz	()Lscala/reflect/generic/StdNames$StandardNames;;
NameAndType	nme:()Lscala/reflect/generic/StdNames$StandardNames;
InterfaceMethod	scala/reflect/generic/StdNames.nme:()Lscala/reflect/generic/StdNames$StandardNames;
Asciz	scala/reflect/generic/StdNames$StandardNames;
class	scala/reflect/generic/StdNames$StandardNames
Asciz	EMPTY;
Asciz	()Ljava/lang/Object;;
NameAndType	EMPTY:()Ljava/lang/Object;
Method	scala/reflect/generic/StdNames$StandardNames.EMPTY:()Ljava/lang/Object;
Asciz	scala/reflect/generic/Names;
class	scala/reflect/generic/Names
Asciz	mkTypeName;
Asciz	(Ljava/lang/Object;)Ljava/lang/Object;;
NameAndType	mkTypeName:(Ljava/lang/Object;)Ljava/lang/Object;
InterfaceMethod	scala/reflect/generic/Names.mkTypeName:(Ljava/lang/Object;)Ljava/lang/Object;
Asciz	scala/reflect/generic/Trees;
class	scala/reflect/generic/Trees
Asciz	(JLjava/lang/Object;)Lscala/reflect/generic/Trees$Modifiers;;
NameAndType	Modifiers:(JLjava/lang/Object;)Lscala/reflect/generic/Trees$Modifiers;
InterfaceMethod	scala/reflect/generic/Trees.Modifiers:(JLjava/lang/Object;)Lscala/reflect/generic/Trees$Modifiers;
Asciz	NoMods;
Asciz	(Lscala/reflect/generic/Universe;)Lscala/reflect/generic/Trees$Modifiers;;
Asciz	(J)Lscala/reflect/generic/Trees$Modifiers;;
NameAndType	Modifiers:(J)Lscala/reflect/generic/Trees$Modifiers;
InterfaceMethod	scala/reflect/generic/Trees.Modifiers:(J)Lscala/reflect/generic/Trees$Modifiers;
Asciz	duplicateTree;
Asciz	(Lscala/reflect/generic/Universe;Lscala/reflect/generic/Trees$Tree;)Lscala/reflect/generic/Trees$Tree;;
Asciz	tree;
Asciz	Lscala/reflect/generic/Trees$Tree;;
Asciz	Literal;
Asciz	(Lscala/reflect/generic/Universe;Ljava/lang/Object;)Lscala/reflect/generic/Trees$Literal;;
Asciz	scala/reflect/generic/Trees$Literal;
class	scala/reflect/generic/Trees$Literal
Asciz	scala/reflect/generic/Constants$Constant;
class	scala/reflect/generic/Constants$Constant
Asciz	(Lscala/reflect/generic/Universe;Ljava/lang/Object;)V;
NameAndType	"<init>":(Lscala/reflect/generic/Universe;Ljava/lang/Object;)V
Method	scala/reflect/generic/Constants$Constant."<init>":(Lscala/reflect/generic/Universe;Ljava/lang/Object;)V
Asciz	(Lscala/reflect/generic/Universe;Lscala/reflect/generic/Constants$Constant;)V;
NameAndType	"<init>":(Lscala/reflect/generic/Universe;Lscala/reflect/generic/Constants$Constant;)V
Method	scala/reflect/generic/Trees$Literal."<init>":(Lscala/reflect/generic/Universe;Lscala/reflect/generic/Constants$Constant;)V
Asciz	value;
Asciz	$init$;
Asciz	(Lscala/reflect/generic/Universe;)V;
Asciz	nodeCount_$eq;
Asciz	(I)V;
NameAndType	nodeCount_$eq:(I)V
InterfaceMethod	scala/reflect/generic/Trees.nodeCount_$eq:(I)V
Asciz	Scala;
Asciz	InnerClasses;
Asciz	scala/reflect/generic/Trees$Tree;
class	scala/reflect/generic/Trees$Tree
Asciz	Tree;
Asciz	scala/collection/immutable/Map;
class	scala/collection/immutable/Map
Asciz	EmptyMap;
Asciz	scala/reflect/generic/Constants;
class	scala/reflect/generic/Constants
Asciz	Constant;
Asciz	StandardNames;
Asciz	scala/reflect/generic/Trees$class;
class	scala/reflect/generic/Trees$class
Asciz	java/lang/Object;
class	java/lang/Object

{
public static scala.reflect.generic.Trees$Modifiers Modifiers(scala.reflect.generic.Universe, long, java.lang.Object);
  Signature: (Lscala/reflect/generic/Universe;JLjava/lang/Object;)Lscala/reflect/generic/Trees$Modifiers;
  Code:
   Stack=9, Locals=4, Args_size=3
	new	class scala/reflect/generic/Trees$Modifiers
	dup
	aload_0
	lload_1
	aload_3
	getstatic	Field scala/collection/immutable/Nil$.MODULE$:Lscala/collection/immutable/Nil$;
	new	class scala/collection/immutable/Map$EmptyMap
	dup
	invokespecial	Method scala/collection/immutable/Map$EmptyMap."<init>":()V
	invokespecial	Method scala/reflect/generic/Trees$Modifiers."<init>":(Lscala/reflect/generic/Universe;JLjava/lang/Object;Lscala/collection/immutable/List;Lscala/collection/immutable/Map;)V
	areturn
  Labels:
  LocalVariableTable: 
   Start  Length  Slot  Name   Signature
   0      21      0    $this       Lscala/reflect/generic/Universe;
   0      21      1    flags       J
   0      21      3    privateWithin       Ljava/lang/Object;


public static scala.reflect.generic.Trees$Modifiers Modifiers(scala.reflect.generic.Universe, long);
  Signature: (Lscala/reflect/generic/Universe;J)Lscala/reflect/generic/Trees$Modifiers;
  Code:
   Stack=5, Locals=3, Args_size=2
	aload_0
	lload_1
	aload_0
	aload_0
	invokeinterface	InterfaceMethod scala/reflect/generic/StdNames.nme:()Lscala/reflect/generic/StdNames$StandardNames;
	invokevirtual	Method scala/reflect/generic/StdNames$StandardNames.EMPTY:()Ljava/lang/Object;
	invokeinterface	InterfaceMethod scala/reflect/generic/Names.mkTypeName:(Ljava/lang/Object;)Ljava/lang/Object;
	invokeinterface	InterfaceMethod scala/reflect/generic/Trees.Modifiers:(JLjava/lang/Object;)Lscala/reflect/generic/Trees$Modifiers;
	areturn
  Labels:
  LocalVariableTable: 
   Start  Length  Slot  Name   Signature
   0      23      0    $this       Lscala/reflect/generic/Universe;
   0      23      1    flags       J


public static scala.reflect.generic.Trees$Modifiers NoMods(scala.reflect.generic.Universe);
  Signature: (Lscala/reflect/generic/Universe;)Lscala/reflect/generic/Trees$Modifiers;
  Code:
   Stack=3, Locals=1, Args_size=1
	aload_0
	lconst_0
	invokeinterface	InterfaceMethod scala/reflect/generic/Trees.Modifiers:(J)Lscala/reflect/generic/Trees$Modifiers;
	areturn
  Labels:
  LocalVariableTable: 
   Start  Length  Slot  Name   Signature
   0      8      0    $this       Lscala/reflect/generic/Universe;


public static scala.reflect.generic.Trees$Tree duplicateTree(scala.reflect.generic.Universe, scala.reflect.generic.Trees$Tree);
  Signature: (Lscala/reflect/generic/Universe;Lscala/reflect/generic/Trees$Tree;)Lscala/reflect/generic/Trees$Tree;
  Code:
   Stack=1, Locals=2, Args_size=2
	aload_1
	areturn
  Labels:
  LocalVariableTable: 
   Start  Length  Slot  Name   Signature
   0      2      0    $this       Lscala/reflect/generic/Universe;
   0      2      1    tree       Lscala/reflect/generic/Trees$Tree;


public static scala.reflect.generic.Trees$Literal Literal(scala.reflect.generic.Universe, java.lang.Object);
  Signature: (Lscala/reflect/generic/Universe;Ljava/lang/Object;)Lscala/reflect/generic/Trees$Literal;
  Code:
   Stack=7, Locals=2, Args_size=2
	new	class scala/reflect/generic/Trees$Literal
	dup
	aload_0
	new	class scala/reflect/generic/Constants$Constant
	dup
	aload_0
	aload_1
	invokespecial	Method scala/reflect/generic/Constants$Constant."<init>":(Lscala/reflect/generic/Universe;Ljava/lang/Object;)V
	invokespecial	Method scala/reflect/generic/Trees$Literal."<init>":(Lscala/reflect/generic/Universe;Lscala/reflect/generic/Constants$Constant;)V
	areturn
  Labels:
  LocalVariableTable: 
   Start  Length  Slot  Name   Signature
   0      18      0    $this       Lscala/reflect/generic/Universe;
   0      18      1    value       Ljava/lang/Object;


public static void $init$(scala.reflect.generic.Universe);
  Signature: (Lscala/reflect/generic/Universe;)V
  Code:
   Stack=2, Locals=1, Args_size=1
	aload_0
	iconst_0
	invokeinterface	InterfaceMethod scala/reflect/generic/Trees.nodeCount_$eq:(I)V
	return
  Labels:
  LocalVariableTable: 
   Start  Length  Slot  Name   Signature
   0      8      0    $this       Lscala/reflect/generic/Universe;


}

