Compiled from "Trees.scala"
public class scala.reflect.generic.Trees$Return extends scala.reflect.generic.Trees$Tree implements scala.reflect.generic.Trees$TermTree,scala.reflect.generic.Trees$SymTree,scala.ScalaObject,scala.Product,java.io.Serializable
  SourceFile: "Trees.scala"
  Scala: length = 0x
   
  InnerClass: 
   public abstract Tree=class scala/reflect/generic/Trees$Tree of class scala/reflect/generic/Trees
   public Return=class scala/reflect/generic/Trees$Return of class scala/reflect/generic/Trees
   public abstract SymTree=class scala/reflect/generic/Trees$SymTree of class scala/reflect/generic/Trees
   public abstract TermTree=class scala/reflect/generic/Trees$TermTree of class scala/reflect/generic/Trees
   public abstract AbsSymbol=class scala/reflect/generic/Symbols$AbsSymbol of class scala/reflect/generic/Symbols
  minor version: 0
  major version: 49
  Constant pool:
Asciz	SourceFile;
Asciz	Trees.scala;
Asciz	symbol;
Asciz	Lscala/reflect/generic/Symbols$AbsSymbol;;
Asciz	expr;
Asciz	Lscala/reflect/generic/Trees$Tree;;
Asciz	()Lscala/reflect/generic/Symbols$AbsSymbol;;
Asciz	Code;
Asciz	LineNumberTable;
Asciz	scala/reflect/generic/Trees$Return;
class	scala/reflect/generic/Trees$Return
NameAndType	symbol:Lscala/reflect/generic/Symbols$AbsSymbol;
Field	scala/reflect/generic/Trees$Return.symbol:Lscala/reflect/generic/Symbols$AbsSymbol;
Asciz	symbol_$eq;
Asciz	(Lscala/reflect/generic/Symbols$AbsSymbol;)V;
Asciz	hasSymbol;
Asciz	()Z;
Asciz	scala/reflect/generic/Trees$SymTree$class;
class	scala/reflect/generic/Trees$SymTree$class
Asciz	(Lscala/reflect/generic/Trees$SymTree;)Z;
NameAndType	hasSymbol:(Lscala/reflect/generic/Trees$SymTree;)Z
Method	scala/reflect/generic/Trees$SymTree$class.hasSymbol:(Lscala/reflect/generic/Trees$SymTree;)Z
Asciz	copy$default$1;
Asciz	()Lscala/reflect/generic/Trees$Tree;;
NameAndType	expr:()Lscala/reflect/generic/Trees$Tree;
Method	scala/reflect/generic/Trees$Return.expr:()Lscala/reflect/generic/Trees$Tree;
NameAndType	expr:Lscala/reflect/generic/Trees$Tree;
Field	scala/reflect/generic/Trees$Return.expr:Lscala/reflect/generic/Trees$Tree;
Asciz	copy;
Asciz	(Lscala/reflect/generic/Trees$Tree;)Lscala/reflect/generic/Trees$Return;;
Asciz	scala$reflect$generic$Trees$Return$$$outer;
Asciz	()Lscala/reflect/generic/Universe;;
NameAndType	scala$reflect$generic$Trees$Return$$$outer:()Lscala/reflect/generic/Universe;
Method	scala/reflect/generic/Trees$Return.scala$reflect$generic$Trees$Return$$$outer:()Lscala/reflect/generic/Universe;
Asciz	<init>;
Asciz	(Lscala/reflect/generic/Universe;Lscala/reflect/generic/Trees$Tree;)V;
NameAndType	"<init>":(Lscala/reflect/generic/Universe;Lscala/reflect/generic/Trees$Tree;)V
Method	scala/reflect/generic/Trees$Return."<init>":(Lscala/reflect/generic/Universe;Lscala/reflect/generic/Trees$Tree;)V
Asciz	this;
Asciz	Lscala/reflect/generic/Trees$Return;;
Asciz	LocalVariableTable;
Asciz	productPrefix;
Asciz	()Ljava/lang/String;;
Asciz	Return;
String	Return
Asciz	productArity;
Asciz	()I;
Asciz	productElement;
Asciz	(I)Ljava/lang/Object;;
Asciz	java/lang/IndexOutOfBoundsException;
class	java/lang/IndexOutOfBoundsException
Asciz	scala/runtime/BoxesRunTime;
class	scala/runtime/BoxesRunTime
Asciz	boxToInteger;
Asciz	(I)Ljava/lang/Integer;;
NameAndType	boxToInteger:(I)Ljava/lang/Integer;
Method	scala/runtime/BoxesRunTime.boxToInteger:(I)Ljava/lang/Integer;
Asciz	java/lang/Object;
class	java/lang/Object
Asciz	toString;
NameAndType	toString:()Ljava/lang/String;
Method	java/lang/Object.toString:()Ljava/lang/String;
Asciz	(Ljava/lang/String;)V;
NameAndType	"<init>":(Ljava/lang/String;)V
Method	java/lang/IndexOutOfBoundsException."<init>":(Ljava/lang/String;)V
Asciz	temp94;
Asciz	I;
Asciz	productElementName;
Asciz	(I)Ljava/lang/String;;
String	expr
Asciz	temp95;
Asciz	canEqual;
Asciz	(Ljava/lang/Object;)Z;
Asciz	scala/reflect/generic/Trees$Tree;
class	scala/reflect/generic/Trees$Tree
Asciz	$outer;
Asciz	Lscala/reflect/generic/Universe;;
NameAndType	$outer:Lscala/reflect/generic/Universe;
Field	scala/reflect/generic/Trees$Tree.$outer:Lscala/reflect/generic/Universe;
Asciz	scala$reflect$generic$Trees$SymTree$$$outer;
Asciz	()Lscala/reflect/generic/Trees;;
Asciz	(Lscala/reflect/generic/Universe;)V;
NameAndType	"<init>":(Lscala/reflect/generic/Universe;)V
Method	scala/reflect/generic/Trees$Tree."<init>":(Lscala/reflect/generic/Universe;)V
Asciz	$init$;
Asciz	(Lscala/reflect/generic/Trees$SymTree;)V;
NameAndType	$init$:(Lscala/reflect/generic/Trees$SymTree;)V
Method	scala/reflect/generic/Trees$SymTree$class.$init$:(Lscala/reflect/generic/Trees$SymTree;)V
Asciz	Scala;
Asciz	InnerClasses;
Asciz	scala/reflect/generic/Trees;
class	scala/reflect/generic/Trees
Asciz	Tree;
Asciz	scala/reflect/generic/Trees$SymTree;
class	scala/reflect/generic/Trees$SymTree
Asciz	SymTree;
Asciz	scala/reflect/generic/Trees$TermTree;
class	scala/reflect/generic/Trees$TermTree
Asciz	TermTree;
Asciz	scala/reflect/generic/Symbols$AbsSymbol;
class	scala/reflect/generic/Symbols$AbsSymbol
Asciz	scala/reflect/generic/Symbols;
class	scala/reflect/generic/Symbols
Asciz	AbsSymbol;
Asciz	scala/ScalaObject;
class	scala/ScalaObject
Asciz	scala/Product;
class	scala/Product
Asciz	java/io/Serializable;
class	java/io/Serializable

{
private scala.reflect.generic.Symbols$AbsSymbol symbol;
  Signature: Lscala/reflect/generic/Symbols$AbsSymbol;

private final scala.reflect.generic.Trees$Tree expr;
  Signature: Lscala/reflect/generic/Trees$Tree;

public scala.reflect.generic.Symbols$AbsSymbol symbol();
  Signature: ()Lscala/reflect/generic/Symbols$AbsSymbol;
  Code:
   Stack=1, Locals=1, Args_size=1
	aload_0
	getfield	Field symbol:Lscala/reflect/generic/Symbols$AbsSymbol;
	areturn
  Labels:

public void symbol_$eq(scala.reflect.generic.Symbols$AbsSymbol);
  Signature: (Lscala/reflect/generic/Symbols$AbsSymbol;)V
  Code:
   Stack=2, Locals=2, Args_size=2
	aload_0
	aload_1
	putfield	Field symbol:Lscala/reflect/generic/Symbols$AbsSymbol;
	return
  Labels:

public boolean hasSymbol();
  Signature: ()Z
  Code:
   Stack=1, Locals=1, Args_size=1
	aload_0
	invokestatic	Method scala/reflect/generic/Trees$SymTree$class.hasSymbol:(Lscala/reflect/generic/Trees$SymTree;)Z
	ireturn
  Labels:

public scala.reflect.generic.Trees$Tree copy$default$1();
  Signature: ()Lscala/reflect/generic/Trees$Tree;
  Code:
   Stack=1, Locals=1, Args_size=1
	aload_0
	invokevirtual	Method expr:()Lscala/reflect/generic/Trees$Tree;
	areturn
  Labels:

public scala.reflect.generic.Trees$Tree expr();
  Signature: ()Lscala/reflect/generic/Trees$Tree;
  Code:
   Stack=1, Locals=1, Args_size=1
	aload_0
	getfield	Field expr:Lscala/reflect/generic/Trees$Tree;
	areturn
  Labels:

public scala.reflect.generic.Trees$Return copy(scala.reflect.generic.Trees$Tree);
  Signature: (Lscala/reflect/generic/Trees$Tree;)Lscala/reflect/generic/Trees$Return;
  Code:
   Stack=4, Locals=2, Args_size=2
	new	class scala/reflect/generic/Trees$Return
	dup
	aload_0
	invokevirtual	Method scala$reflect$generic$Trees$Return$$$outer:()Lscala/reflect/generic/Universe;
	aload_1
	invokespecial	Method "<init>":(Lscala/reflect/generic/Universe;Lscala/reflect/generic/Trees$Tree;)V
	areturn
  Labels:
  LocalVariableTable: 
   Start  Length  Slot  Name   Signature
   0      13      0    this       Lscala/reflect/generic/Trees$Return;
   0      13      1    expr       Lscala/reflect/generic/Trees$Tree;


public java.lang.String productPrefix();
  Signature: ()Ljava/lang/String;
  Code:
   Stack=1, Locals=1, Args_size=1
	ldc	String Return
	areturn
  Labels:

public int productArity();
  Signature: ()I
  Code:
   Stack=1, Locals=1, Args_size=1
	iconst_1
	ireturn
  Labels:

public java.lang.Object productElement(int);
  Signature: (I)Ljava/lang/Object;
  Code:
   Stack=3, Locals=3, Args_size=2
	iload_1
	istore_2
	iload_2
	iconst_0
	if_icmpne	l1 // new
	aload_0
	invokevirtual	Method expr:()Lscala/reflect/generic/Trees$Tree;
	areturn
l1	new	class java/lang/IndexOutOfBoundsException
	dup
	iload_1
	invokestatic	Method scala/runtime/BoxesRunTime.boxToInteger:(I)Ljava/lang/Integer;
	invokevirtual	Method java/lang/Object.toString:()Ljava/lang/String;
	invokespecial	Method java/lang/IndexOutOfBoundsException."<init>":(Ljava/lang/String;)V
	athrow
  Labels:
   	l1 = 12 // new
  LocalVariableTable: 
   Start  Length  Slot  Name   Signature
   0      27      0    this       Lscala/reflect/generic/Trees$Return;
   2      25      2    temp94       I


public java.lang.String productElementName(int);
  Signature: (I)Ljava/lang/String;
  Code:
   Stack=3, Locals=3, Args_size=2
	iload_1
	istore_2
	iload_2
	iconst_0
	if_icmpne	l1 // new
	ldc	String expr
	areturn
l1	new	class java/lang/IndexOutOfBoundsException
	dup
	iload_1
	invokestatic	Method scala/runtime/BoxesRunTime.boxToInteger:(I)Ljava/lang/Integer;
	invokevirtual	Method java/lang/Object.toString:()Ljava/lang/String;
	invokespecial	Method java/lang/IndexOutOfBoundsException."<init>":(Ljava/lang/String;)V
	athrow
  Labels:
   	l1 = 10 // new
  LocalVariableTable: 
   Start  Length  Slot  Name   Signature
   0      25      0    this       Lscala/reflect/generic/Trees$Return;
   2      23      2    temp95       I


public boolean canEqual(java.lang.Object);
  Signature: (Ljava/lang/Object;)Z
  Code:
   Stack=1, Locals=2, Args_size=2
	aload_1
	instanceof	class scala/reflect/generic/Trees$Return
	ireturn
  Labels:

public scala.reflect.generic.Universe scala$reflect$generic$Trees$Return$$$outer();
  Signature: ()Lscala/reflect/generic/Universe;
  Code:
   Stack=1, Locals=1, Args_size=1
	aload_0
	getfield	Field scala/reflect/generic/Trees$Tree.$outer:Lscala/reflect/generic/Universe;
	areturn
  Labels:

public scala.reflect.generic.Trees scala$reflect$generic$Trees$SymTree$$$outer();
  Signature: ()Lscala/reflect/generic/Trees;
  Code:
   Stack=1, Locals=1, Args_size=1
	aload_0
	invokevirtual	Method scala$reflect$generic$Trees$Return$$$outer:()Lscala/reflect/generic/Universe;
	areturn
  Labels:

public scala.reflect.generic.Trees$Return(scala.reflect.generic.Universe, scala.reflect.generic.Trees$Tree);
  Signature: (Lscala/reflect/generic/Universe;Lscala/reflect/generic/Trees$Tree;)V
  Code:
   Stack=2, Locals=3, Args_size=3
	aload_0
	aload_2
	putfield	Field expr:Lscala/reflect/generic/Trees$Tree;
	aload_0
	aload_1
	invokespecial	Method scala/reflect/generic/Trees$Tree."<init>":(Lscala/reflect/generic/Universe;)V
	aload_0
	invokestatic	Method scala/reflect/generic/Trees$SymTree$class.$init$:(Lscala/reflect/generic/Trees$SymTree;)V
	return
  Labels:
  LocalVariableTable: 
   Start  Length  Slot  Name   Signature
   0      15      0    this       Lscala/reflect/generic/Trees$Return;
   0      15      1    $outer       Lscala/reflect/generic/Universe;
   0      15      2    expr       Lscala/reflect/generic/Trees$Tree;


}

