Compiled from "Trees.scala"
public final class scala.reflect.generic.Trees$Tree$$anonfun$subtrees$1$1 extends scala.runtime.AbstractFunction1 implements java.io.Serializable
  SourceFile: "Trees.scala"
  Scala: length = 0x
   
  InnerClass: 
   public abstract Tree=class scala/reflect/generic/Trees$Tree of class scala/reflect/generic/Trees
   public final $anonfun$subtrees$1$1=class scala/reflect/generic/Trees$Tree$$anonfun$subtrees$1$1 of class scala/reflect/generic/Trees$Tree
  minor version: 0
  major version: 49
  Constant pool:
Asciz	SourceFile;
Asciz	Trees.scala;
Asciz	<clinit>;
Asciz	()V;
Asciz	Code;
Asciz	serialVersionUID;
Asciz	J;
Asciz	scala/reflect/generic/Trees$Tree$$anonfun$subtrees$1$1;
class	scala/reflect/generic/Trees$Tree$$anonfun$subtrees$1$1
NameAndType	serialVersionUID:J
Field	scala/reflect/generic/Trees$Tree$$anonfun$subtrees$1$1.serialVersionUID:J
Asciz	$outer;
Asciz	Lscala/reflect/generic/Trees$Tree;;
Asciz	apply;
Asciz	(Ljava/lang/Object;)Lscala/collection/immutable/List;;
Asciz	LineNumberTable;
NameAndType	$outer:Lscala/reflect/generic/Trees$Tree;
Field	scala/reflect/generic/Trees$Tree$$anonfun$subtrees$1$1.$outer:Lscala/reflect/generic/Trees$Tree;
Asciz	scala/reflect/generic/Trees$Tree;
class	scala/reflect/generic/Trees$Tree
Asciz	subtrees$1;
NameAndType	subtrees$1:(Ljava/lang/Object;)Lscala/collection/immutable/List;
Method	scala/reflect/generic/Trees$Tree.subtrees$1:(Ljava/lang/Object;)Lscala/collection/immutable/List;
Asciz	(Ljava/lang/Object;)Lscala/collection/immutable/List<Lscala/reflect/generic/Trees$Tree;>;;
Asciz	Signature;
Asciz	(Ljava/lang/Object;)Ljava/lang/Object;;
NameAndType	apply:(Ljava/lang/Object;)Lscala/collection/immutable/List;
Method	scala/reflect/generic/Trees$Tree$$anonfun$subtrees$1$1.apply:(Ljava/lang/Object;)Lscala/collection/immutable/List;
Asciz	this;
Asciz	Lscala/reflect/generic/Trees$Tree$$anonfun$subtrees$1$1;;
Asciz	v1;
Asciz	Ljava/lang/Object;;
Asciz	LocalVariableTable;
Asciz	<init>;
Asciz	(Lscala/reflect/generic/Trees$Tree;)V;
Asciz	java/lang/NullPointerException;
class	java/lang/NullPointerException
NameAndType	"<init>":()V
Method	java/lang/NullPointerException."<init>":()V
Asciz	scala/runtime/AbstractFunction1;
class	scala/runtime/AbstractFunction1
Method	scala/runtime/AbstractFunction1."<init>":()V
Asciz	Scala;
Asciz	InnerClasses;
Asciz	scala/reflect/generic/Trees;
class	scala/reflect/generic/Trees
Asciz	Tree;
Asciz	$anonfun$subtrees$1$1;
Asciz	java/io/Serializable;
class	java/io/Serializable

{
public static final long serialVersionUID;
  Signature: J

private final scala.reflect.generic.Trees$Tree $outer;
  Signature: Lscala/reflect/generic/Trees$Tree;

public static {};
  Signature: ()V
  Code:
   Stack=2, Locals=0, Args_size=0
	lconst_0
	putstatic	Field serialVersionUID:J
	return
  Labels:

public final scala.collection.immutable.List apply(java.lang.Object);
  Signature: (Ljava/lang/Object;)Lscala/collection/immutable/List;
  Code:
   Stack=2, Locals=2, Args_size=2
	aload_0
	getfield	Field $outer:Lscala/reflect/generic/Trees$Tree;
	aload_1
	invokevirtual	Method scala/reflect/generic/Trees$Tree.subtrees$1:(Ljava/lang/Object;)Lscala/collection/immutable/List;
	areturn
  Labels:
  Signature: length = 0x2
   00 18 

public final java.lang.Object apply(java.lang.Object);
  Signature: (Ljava/lang/Object;)Ljava/lang/Object;
  Code:
   Stack=2, Locals=2, Args_size=2
	aload_0
	aload_1
	invokevirtual	Method apply:(Ljava/lang/Object;)Lscala/collection/immutable/List;
	areturn
  Labels:
  LocalVariableTable: 
   Start  Length  Slot  Name   Signature
   0      6      0    this       Lscala/reflect/generic/Trees$Tree$$anonfun$subtrees$1$1;
   0      6      1    v1       Ljava/lang/Object;


public scala.reflect.generic.Trees$Tree$$anonfun$subtrees$1$1(scala.reflect.generic.Trees$Tree);
  Signature: (Lscala/reflect/generic/Trees$Tree;)V
  Code:
   Stack=2, Locals=2, Args_size=2
	aload_1
	ifnonnull	l1 // aload_0
	new	class java/lang/NullPointerException
	dup
	invokespecial	Method java/lang/NullPointerException."<init>":()V
	athrow
l1	aload_0
	aload_1
	putfield	Field $outer:Lscala/reflect/generic/Trees$Tree;
	aload_0
	invokespecial	Method scala/runtime/AbstractFunction1."<init>":()V
	return
  Labels:
   	l1 = 12 // aload_0
  LocalVariableTable: 
   Start  Length  Slot  Name   Signature
   0      22      0    this       Lscala/reflect/generic/Trees$Tree$$anonfun$subtrees$1$1;
   0      22      1    $outer       Lscala/reflect/generic/Trees$Tree;


}

