Compiled from "Trees.scala"
public final class scala.reflect.generic.Trees$Literal$ extends java.lang.Object implements scala.Function1,scala.ScalaObject
  SourceFile: "Trees.scala"
  Scala: length = 0x
   
  InnerClass: 
   public Literal=class scala/reflect/generic/Trees$Literal of class scala/reflect/generic/Trees
   public Constant=class scala/reflect/generic/Constants$Constant of class scala/reflect/generic/Constants
  minor version: 0
  major version: 49
  Constant pool:
Asciz	SourceFile;
Asciz	Trees.scala;
Asciz	$outer;
Asciz	Lscala/reflect/generic/Universe;;
Asciz	toString;
Asciz	()Ljava/lang/String;;
Asciz	Code;
Asciz	LineNumberTable;
Asciz	scala/Function1$class;
class	scala/Function1$class
Asciz	(Lscala/Function1;)Ljava/lang/String;;
NameAndType	toString:(Lscala/Function1;)Ljava/lang/String;
Method	scala/Function1$class.toString:(Lscala/Function1;)Ljava/lang/String;
Asciz	compose;
Asciz	(Lscala/Function1;)Lscala/Function1;;
Asciz	(Lscala/Function1;Lscala/Function1;)Lscala/Function1;;
NameAndType	compose:(Lscala/Function1;Lscala/Function1;)Lscala/Function1;
Method	scala/Function1$class.compose:(Lscala/Function1;Lscala/Function1;)Lscala/Function1;
Asciz	this;
Asciz	Lscala/reflect/generic/Trees$Literal$;;
Asciz	g;
Asciz	Lscala/Function1;;
Asciz	LocalVariableTable;
Asciz	andThen;
NameAndType	andThen:(Lscala/Function1;Lscala/Function1;)Lscala/Function1;
Method	scala/Function1$class.andThen:(Lscala/Function1;Lscala/Function1;)Lscala/Function1;
Asciz	unapply;
Asciz	(Lscala/reflect/generic/Trees$Literal;)Lscala/Option;;
Asciz	scala/None$;
class	scala/None$
Asciz	MODULE$;
Asciz	Lscala/None$;;
NameAndType	MODULE$:Lscala/None$;
Field	scala/None$.MODULE$:Lscala/None$;
Asciz	scala/Some;
class	scala/Some
Asciz	scala/reflect/generic/Trees$Literal;
class	scala/reflect/generic/Trees$Literal
Asciz	value;
Asciz	()Lscala/reflect/generic/Constants$Constant;;
NameAndType	value:()Lscala/reflect/generic/Constants$Constant;
Method	scala/reflect/generic/Trees$Literal.value:()Lscala/reflect/generic/Constants$Constant;
Asciz	<init>;
Asciz	(Ljava/lang/Object;)V;
NameAndType	"<init>":(Ljava/lang/Object;)V
Method	scala/Some."<init>":(Ljava/lang/Object;)V
Asciz	x$0;
Asciz	Lscala/reflect/generic/Trees$Literal;;
Asciz	apply;
Asciz	(Lscala/reflect/generic/Constants$Constant;)Lscala/reflect/generic/Trees$Literal;;
Asciz	scala/reflect/generic/Trees$Literal$;
class	scala/reflect/generic/Trees$Literal$
NameAndType	$outer:Lscala/reflect/generic/Universe;
Field	scala/reflect/generic/Trees$Literal$.$outer:Lscala/reflect/generic/Universe;
Asciz	(Lscala/reflect/generic/Universe;Lscala/reflect/generic/Constants$Constant;)V;
NameAndType	"<init>":(Lscala/reflect/generic/Universe;Lscala/reflect/generic/Constants$Constant;)V
Method	scala/reflect/generic/Trees$Literal."<init>":(Lscala/reflect/generic/Universe;Lscala/reflect/generic/Constants$Constant;)V
Asciz	Lscala/reflect/generic/Constants$Constant;;
Asciz	(Ljava/lang/Object;)Ljava/lang/Object;;
Asciz	scala/reflect/generic/Constants$Constant;
class	scala/reflect/generic/Constants$Constant
NameAndType	apply:(Lscala/reflect/generic/Constants$Constant;)Lscala/reflect/generic/Trees$Literal;
Method	scala/reflect/generic/Trees$Literal$.apply:(Lscala/reflect/generic/Constants$Constant;)Lscala/reflect/generic/Trees$Literal;
Asciz	v1;
Asciz	Ljava/lang/Object;;
Asciz	(Lscala/reflect/generic/Universe;)V;
Asciz	java/lang/NullPointerException;
class	java/lang/NullPointerException
Asciz	()V;
NameAndType	"<init>":()V
Method	java/lang/NullPointerException."<init>":()V
Asciz	java/lang/Object;
class	java/lang/Object
Method	java/lang/Object."<init>":()V
Asciz	$init$;
Asciz	(Lscala/Function1;)V;
NameAndType	$init$:(Lscala/Function1;)V
Method	scala/Function1$class.$init$:(Lscala/Function1;)V
Asciz	Scala;
Asciz	InnerClasses;
Asciz	scala/reflect/generic/Trees;
class	scala/reflect/generic/Trees
Asciz	Literal;
Asciz	scala/reflect/generic/Constants;
class	scala/reflect/generic/Constants
Asciz	Constant;
Asciz	scala/Function1;
class	scala/Function1
Asciz	scala/ScalaObject;
class	scala/ScalaObject

{
public final scala.reflect.generic.Universe $outer;
  Signature: Lscala/reflect/generic/Universe;

public java.lang.String toString();
  Signature: ()Ljava/lang/String;
  Code:
   Stack=1, Locals=1, Args_size=1
	aload_0
	invokestatic	Method scala/Function1$class.toString:(Lscala/Function1;)Ljava/lang/String;
	areturn
  Labels:

public scala.Function1 compose(scala.Function1);
  Signature: (Lscala/Function1;)Lscala/Function1;
  Code:
   Stack=2, Locals=2, Args_size=2
	aload_0
	aload_1
	invokestatic	Method scala/Function1$class.compose:(Lscala/Function1;Lscala/Function1;)Lscala/Function1;
	areturn
  Labels:
  LocalVariableTable: 
   Start  Length  Slot  Name   Signature
   0      6      0    this       Lscala/reflect/generic/Trees$Literal$;
   0      6      1    g       Lscala/Function1;


public scala.Function1 andThen(scala.Function1);
  Signature: (Lscala/Function1;)Lscala/Function1;
  Code:
   Stack=2, Locals=2, Args_size=2
	aload_0
	aload_1
	invokestatic	Method scala/Function1$class.andThen:(Lscala/Function1;Lscala/Function1;)Lscala/Function1;
	areturn
  Labels:
  LocalVariableTable: 
   Start  Length  Slot  Name   Signature
   0      6      0    this       Lscala/reflect/generic/Trees$Literal$;
   0      6      1    g       Lscala/Function1;


public scala.Option unapply(scala.reflect.generic.Trees$Literal);
  Signature: (Lscala/reflect/generic/Trees$Literal;)Lscala/Option;
  Code:
   Stack=3, Locals=2, Args_size=2
	aload_1
	ifnonnull	l1 // new
	getstatic	Field scala/None$.MODULE$:Lscala/None$;
	goto	l2 // areturn
l1	new	class scala/Some
	dup
	aload_1
	invokevirtual	Method scala/reflect/generic/Trees$Literal.value:()Lscala/reflect/generic/Constants$Constant;
	invokespecial	Method scala/Some."<init>":(Ljava/lang/Object;)V
l2	areturn
  Labels:
   	l1 = 10 // new
   	l2 = 21 // areturn
  LocalVariableTable: 
   Start  Length  Slot  Name   Signature
   0      22      0    this       Lscala/reflect/generic/Trees$Literal$;
   0      22      1    x$0       Lscala/reflect/generic/Trees$Literal;


public scala.reflect.generic.Trees$Literal apply(scala.reflect.generic.Constants$Constant);
  Signature: (Lscala/reflect/generic/Constants$Constant;)Lscala/reflect/generic/Trees$Literal;
  Code:
   Stack=4, Locals=3, Args_size=2
	aload_0
	getfield	Field $outer:Lscala/reflect/generic/Universe;
	astore_2
	new	class scala/reflect/generic/Trees$Literal
	dup
	aload_0
	getfield	Field $outer:Lscala/reflect/generic/Universe;
	aload_1
	invokespecial	Method scala/reflect/generic/Trees$Literal."<init>":(Lscala/reflect/generic/Universe;Lscala/reflect/generic/Constants$Constant;)V
	areturn
  Labels:
  LocalVariableTable: 
   Start  Length  Slot  Name   Signature
   0      18      0    this       Lscala/reflect/generic/Trees$Literal$;
   5      13      1    value       Lscala/reflect/generic/Constants$Constant;


public java.lang.Object apply(java.lang.Object);
  Signature: (Ljava/lang/Object;)Ljava/lang/Object;
  Code:
   Stack=2, Locals=3, Args_size=2
	aload_0
	getfield	Field $outer:Lscala/reflect/generic/Universe;
	astore_2
	aload_0
	aload_1
	checkcast	class scala/reflect/generic/Constants$Constant
	invokevirtual	Method apply:(Lscala/reflect/generic/Constants$Constant;)Lscala/reflect/generic/Trees$Literal;
	areturn
  Labels:
  LocalVariableTable: 
   Start  Length  Slot  Name   Signature
   0      14      0    this       Lscala/reflect/generic/Trees$Literal$;
   5      9      1    v1       Ljava/lang/Object;


public scala.reflect.generic.Trees$Literal$(scala.reflect.generic.Universe);
  Signature: (Lscala/reflect/generic/Universe;)V
  Code:
   Stack=2, Locals=2, Args_size=2
	aload_1
	ifnonnull	l1 // aload_0
	new	class java/lang/NullPointerException
	dup
	invokespecial	Method java/lang/NullPointerException."<init>":()V
	athrow
l1	aload_0
	aload_1
	putfield	Field $outer:Lscala/reflect/generic/Universe;
	aload_0
	invokespecial	Method java/lang/Object."<init>":()V
	aload_0
	invokestatic	Method scala/Function1$class.$init$:(Lscala/Function1;)V
	return
  Labels:
   	l1 = 12 // aload_0
  LocalVariableTable: 
   Start  Length  Slot  Name   Signature
   0      26      0    this       Lscala/reflect/generic/Trees$Literal$;
   0      26      1    $outer       Lscala/reflect/generic/Universe;


}

