Compiled from "Trees.scala"
public class scala.reflect.generic.Trees$LabelDef extends scala.reflect.generic.Trees$DefTree implements scala.reflect.generic.Trees$TermTree,scala.ScalaObject,scala.Product,java.io.Serializable
  SourceFile: "Trees.scala"
  Scala: length = 0x
   
  InnerClass: 
   public abstract Tree=class scala/reflect/generic/Trees$Tree of class scala/reflect/generic/Trees
   public abstract DefTree=class scala/reflect/generic/Trees$DefTree of class scala/reflect/generic/Trees
   public abstract TermTree=class scala/reflect/generic/Trees$TermTree of class scala/reflect/generic/Trees
   public LabelDef=class scala/reflect/generic/Trees$LabelDef of class scala/reflect/generic/Trees
  minor version: 0
  major version: 49
  Constant pool:
Asciz	SourceFile;
Asciz	Trees.scala;
Asciz	rhs;
Asciz	Lscala/reflect/generic/Trees$Tree;;
Asciz	params;
Asciz	Lscala/collection/immutable/List;;
Asciz	Lscala/collection/immutable/List<Lscala/reflect/generic/Trees$Ident;>;;
Asciz	Signature;
Asciz	name;
Asciz	Ljava/lang/Object;;
Asciz	copy$default$3;
Asciz	()Lscala/reflect/generic/Trees$Tree;;
Asciz	Code;
Asciz	LineNumberTable;
Asciz	scala/reflect/generic/Trees$LabelDef;
class	scala/reflect/generic/Trees$LabelDef
NameAndType	rhs:()Lscala/reflect/generic/Trees$Tree;
Method	scala/reflect/generic/Trees$LabelDef.rhs:()Lscala/reflect/generic/Trees$Tree;
Asciz	copy$default$2;
Asciz	()Lscala/collection/immutable/List;;
NameAndType	params:()Lscala/collection/immutable/List;
Method	scala/reflect/generic/Trees$LabelDef.params:()Lscala/collection/immutable/List;
Asciz	copy$default$1;
Asciz	()Ljava/lang/Object;;
NameAndType	name:()Ljava/lang/Object;
Method	scala/reflect/generic/Trees$LabelDef.name:()Ljava/lang/Object;
NameAndType	name:Ljava/lang/Object;
Field	scala/reflect/generic/Trees$LabelDef.name:Ljava/lang/Object;
NameAndType	params:Lscala/collection/immutable/List;
Field	scala/reflect/generic/Trees$LabelDef.params:Lscala/collection/immutable/List;
Asciz	()Lscala/collection/immutable/List<Lscala/reflect/generic/Trees$Ident;>;;
NameAndType	rhs:Lscala/reflect/generic/Trees$Tree;
Field	scala/reflect/generic/Trees$LabelDef.rhs:Lscala/reflect/generic/Trees$Tree;
Asciz	copy;
Asciz	(Ljava/lang/Object;Lscala/collection/immutable/List;Lscala/reflect/generic/Trees$Tree;)Lscala/reflect/generic/Trees$LabelDef;;
Asciz	scala$reflect$generic$Trees$LabelDef$$$outer;
Asciz	()Lscala/reflect/generic/Universe;;
NameAndType	scala$reflect$generic$Trees$LabelDef$$$outer:()Lscala/reflect/generic/Universe;
Method	scala/reflect/generic/Trees$LabelDef.scala$reflect$generic$Trees$LabelDef$$$outer:()Lscala/reflect/generic/Universe;
Asciz	<init>;
Asciz	(Lscala/reflect/generic/Universe;Ljava/lang/Object;Lscala/collection/immutable/List;Lscala/reflect/generic/Trees$Tree;)V;
NameAndType	"<init>":(Lscala/reflect/generic/Universe;Ljava/lang/Object;Lscala/collection/immutable/List;Lscala/reflect/generic/Trees$Tree;)V
Method	scala/reflect/generic/Trees$LabelDef."<init>":(Lscala/reflect/generic/Universe;Ljava/lang/Object;Lscala/collection/immutable/List;Lscala/reflect/generic/Trees$Tree;)V
Asciz	this;
Asciz	Lscala/reflect/generic/Trees$LabelDef;;
Asciz	LocalVariableTable;
Asciz	productPrefix;
Asciz	()Ljava/lang/String;;
Asciz	LabelDef;
String	LabelDef
Asciz	productArity;
Asciz	()I;
Asciz	productElement;
Asciz	(I)Ljava/lang/Object;;
Asciz	java/lang/IndexOutOfBoundsException;
class	java/lang/IndexOutOfBoundsException
Asciz	scala/runtime/BoxesRunTime;
class	scala/runtime/BoxesRunTime
Asciz	boxToInteger;
Asciz	(I)Ljava/lang/Integer;;
NameAndType	boxToInteger:(I)Ljava/lang/Integer;
Method	scala/runtime/BoxesRunTime.boxToInteger:(I)Ljava/lang/Integer;
Asciz	java/lang/Object;
class	java/lang/Object
Asciz	toString;
NameAndType	toString:()Ljava/lang/String;
Method	java/lang/Object.toString:()Ljava/lang/String;
Asciz	(Ljava/lang/String;)V;
NameAndType	"<init>":(Ljava/lang/String;)V
Method	java/lang/IndexOutOfBoundsException."<init>":(Ljava/lang/String;)V
Asciz	canEqual;
Asciz	(Ljava/lang/Object;)Z;
Asciz	scala/reflect/generic/Trees$Tree;
class	scala/reflect/generic/Trees$Tree
Asciz	$outer;
Asciz	Lscala/reflect/generic/Universe;;
NameAndType	$outer:Lscala/reflect/generic/Universe;
Field	scala/reflect/generic/Trees$Tree.$outer:Lscala/reflect/generic/Universe;
Asciz	scala/reflect/generic/Trees$DefTree;
class	scala/reflect/generic/Trees$DefTree
Asciz	(Lscala/reflect/generic/Universe;)V;
NameAndType	"<init>":(Lscala/reflect/generic/Universe;)V
Method	scala/reflect/generic/Trees$DefTree."<init>":(Lscala/reflect/generic/Universe;)V
Asciz	(Lscala/reflect/generic/Universe;Ljava/lang/Object;Lscala/collection/immutable/List<Lscala/reflect/generic/Trees$Ident;>;Lscala/reflect/generic/Trees$Tree;)V;
Asciz	Scala;
Asciz	InnerClasses;
Asciz	scala/reflect/generic/Trees;
class	scala/reflect/generic/Trees
Asciz	Tree;
Asciz	DefTree;
Asciz	scala/reflect/generic/Trees$TermTree;
class	scala/reflect/generic/Trees$TermTree
Asciz	TermTree;
Asciz	scala/ScalaObject;
class	scala/ScalaObject
Asciz	scala/Product;
class	scala/Product
Asciz	java/io/Serializable;
class	java/io/Serializable

{
private final scala.reflect.generic.Trees$Tree rhs;
  Signature: Lscala/reflect/generic/Trees$Tree;

private final scala.collection.immutable.List params;
  Signature: Lscala/collection/immutable/List;
  Signature: length = 0x2
   00 07 

private final java.lang.Object name;
  Signature: Ljava/lang/Object;

public scala.reflect.generic.Trees$Tree copy$default$3();
  Signature: ()Lscala/reflect/generic/Trees$Tree;
  Code:
   Stack=1, Locals=1, Args_size=1
	aload_0
	invokevirtual	Method rhs:()Lscala/reflect/generic/Trees$Tree;
	areturn
  Labels:

public scala.collection.immutable.List copy$default$2();
  Signature: ()Lscala/collection/immutable/List;
  Code:
   Stack=1, Locals=1, Args_size=1
	aload_0
	invokevirtual	Method params:()Lscala/collection/immutable/List;
	areturn
  Labels:

public java.lang.Object copy$default$1();
  Signature: ()Ljava/lang/Object;
  Code:
   Stack=1, Locals=1, Args_size=1
	aload_0
	invokevirtual	Method name:()Ljava/lang/Object;
	areturn
  Labels:

public java.lang.Object name();
  Signature: ()Ljava/lang/Object;
  Code:
   Stack=1, Locals=1, Args_size=1
	aload_0
	getfield	Field name:Ljava/lang/Object;
	areturn
  Labels:

public scala.collection.immutable.List params();
  Signature: ()Lscala/collection/immutable/List;
  Code:
   Stack=1, Locals=1, Args_size=1
	aload_0
	getfield	Field params:Lscala/collection/immutable/List;
	areturn
  Labels:
  Signature: length = 0x2
   00 1F 

public scala.reflect.generic.Trees$Tree rhs();
  Signature: ()Lscala/reflect/generic/Trees$Tree;
  Code:
   Stack=1, Locals=1, Args_size=1
	aload_0
	getfield	Field rhs:Lscala/reflect/generic/Trees$Tree;
	areturn
  Labels:

public scala.reflect.generic.Trees$LabelDef copy(java.lang.Object, scala.collection.immutable.List, scala.reflect.generic.Trees$Tree);
  Signature: (Ljava/lang/Object;Lscala/collection/immutable/List;Lscala/reflect/generic/Trees$Tree;)Lscala/reflect/generic/Trees$LabelDef;
  Code:
   Stack=6, Locals=4, Args_size=4
	new	class scala/reflect/generic/Trees$LabelDef
	dup
	aload_0
	invokevirtual	Method scala$reflect$generic$Trees$LabelDef$$$outer:()Lscala/reflect/generic/Universe;
	aload_1
	aload_2
	aload_3
	invokespecial	Method "<init>":(Lscala/reflect/generic/Universe;Ljava/lang/Object;Lscala/collection/immutable/List;Lscala/reflect/generic/Trees$Tree;)V
	areturn
  Labels:
  LocalVariableTable: 
   Start  Length  Slot  Name   Signature
   0      15      0    this       Lscala/reflect/generic/Trees$LabelDef;
   0      15      1    name       Ljava/lang/Object;
   0      15      2    params       Lscala/collection/immutable/List;
   0      15      3    rhs       Lscala/reflect/generic/Trees$Tree;


public java.lang.String productPrefix();
  Signature: ()Ljava/lang/String;
  Code:
   Stack=1, Locals=1, Args_size=1
	ldc	String LabelDef
	areturn
  Labels:

public int productArity();
  Signature: ()I
  Code:
   Stack=1, Locals=1, Args_size=1
	iconst_3
	ireturn
  Labels:

public java.lang.Object productElement(int);
  Signature: (I)Ljava/lang/Object;
  Code:
   Stack=3, Locals=2, Args_size=2
	iload_1
	tableswitch{ //0 to 2
		0: 57;
		1: 50;
		2: 43;
		default: 28 }
	new	class java/lang/IndexOutOfBoundsException
	dup
	iload_1
	invokestatic	Method scala/runtime/BoxesRunTime.boxToInteger:(I)Ljava/lang/Integer;
	invokevirtual	Method java/lang/Object.toString:()Ljava/lang/String;
	invokespecial	Method java/lang/IndexOutOfBoundsException."<init>":(Ljava/lang/String;)V
	athrow
	aload_0
	invokevirtual	Method rhs:()Lscala/reflect/generic/Trees$Tree;
	goto	l1 // areturn
	aload_0
	invokevirtual	Method params:()Lscala/collection/immutable/List;
	goto	l1 // areturn
	aload_0
	invokevirtual	Method name:()Ljava/lang/Object;
l1	areturn
  Labels:
   	l1 = 61 // areturn

public boolean canEqual(java.lang.Object);
  Signature: (Ljava/lang/Object;)Z
  Code:
   Stack=1, Locals=2, Args_size=2
	aload_1
	instanceof	class scala/reflect/generic/Trees$LabelDef
	ireturn
  Labels:

public scala.reflect.generic.Universe scala$reflect$generic$Trees$LabelDef$$$outer();
  Signature: ()Lscala/reflect/generic/Universe;
  Code:
   Stack=1, Locals=1, Args_size=1
	aload_0
	getfield	Field scala/reflect/generic/Trees$Tree.$outer:Lscala/reflect/generic/Universe;
	areturn
  Labels:

public scala.reflect.generic.Trees$LabelDef(scala.reflect.generic.Universe, java.lang.Object, scala.collection.immutable.List, scala.reflect.generic.Trees$Tree);
  Signature: (Lscala/reflect/generic/Universe;Ljava/lang/Object;Lscala/collection/immutable/List;Lscala/reflect/generic/Trees$Tree;)V
  Code:
   Stack=2, Locals=5, Args_size=5
	aload_0
	aload_2
	putfield	Field name:Ljava/lang/Object;
	aload_0
	aload_3
	putfield	Field params:Lscala/collection/immutable/List;
	aload_0
	aload	4
	putfield	Field rhs:Lscala/reflect/generic/Trees$Tree;
	aload_0
	aload_1
	invokespecial	Method scala/reflect/generic/Trees$DefTree."<init>":(Lscala/reflect/generic/Universe;)V
	return
  Labels:
  LocalVariableTable: 
   Start  Length  Slot  Name   Signature
   0      22      0    this       Lscala/reflect/generic/Trees$LabelDef;
   0      22      1    $outer       Lscala/reflect/generic/Universe;
   0      22      2    name       Ljava/lang/Object;
   0      22      3    params       Lscala/collection/immutable/List;
   0      22      4    rhs       Lscala/reflect/generic/Trees$Tree;

  Signature: length = 0x2
   00 54 

}

