Compiled from "Types.scala"
public abstract class scala.reflect.generic.Types$AbsType extends java.lang.Object implements scala.ScalaObject
  SourceFile: "Types.scala"
  Scala: length = 0x
   
  InnerClass: 
   public abstract AbsType=class scala/reflect/generic/Types$AbsType of class scala/reflect/generic/Types
   public abstract AbsSymbol=class scala/reflect/generic/Symbols$AbsSymbol of class scala/reflect/generic/Symbols
  minor version: 0
  major version: 49
  Constant pool:
Asciz	SourceFile;
Asciz	Types.scala;
Asciz	$outer;
Asciz	Lscala/reflect/generic/Universe;;
Asciz	typeSymbol;
Asciz	()Lscala/reflect/generic/Symbols$AbsSymbol;;
Asciz	decl;
Asciz	(Ljava/lang/Object;)Lscala/reflect/generic/Symbols$AbsSymbol;;
Asciz	isComplete;
Asciz	()Z;
Asciz	Code;
Asciz	LineNumberTable;
Asciz	complete;
Asciz	(Lscala/reflect/generic/Symbols$AbsSymbol;)V;
Asciz	this;
Asciz	Lscala/reflect/generic/Types$AbsType;;
Asciz	sym;
Asciz	Lscala/reflect/generic/Symbols$AbsSymbol;;
Asciz	LocalVariableTable;
Asciz	toString;
Asciz	()Ljava/lang/String;;
Asciz	scala/reflect/generic/Types$AbsType;
class	scala/reflect/generic/Types$AbsType
Asciz	scala$reflect$generic$Types$AbsType$$$outer;
Asciz	()Lscala/reflect/generic/Universe;;
NameAndType	scala$reflect$generic$Types$AbsType$$$outer:()Lscala/reflect/generic/Universe;
Method	scala/reflect/generic/Types$AbsType.scala$reflect$generic$Types$AbsType$$$outer:()Lscala/reflect/generic/Universe;
Asciz	scala/reflect/generic/Types;
class	scala/reflect/generic/Types
Asciz	scala$reflect$generic$Types$$tostringRecursions;
Asciz	()I;
NameAndType	scala$reflect$generic$Types$$tostringRecursions:()I
InterfaceMethod	scala/reflect/generic/Types.scala$reflect$generic$Types$$tostringRecursions:()I
int	50;
Asciz	...;
String	...
Asciz	scala$reflect$generic$Types$$tostringRecursions_$eq;
Asciz	(I)V;
NameAndType	scala$reflect$generic$Types$$tostringRecursions_$eq:(I)V
InterfaceMethod	scala/reflect/generic/Types.scala$reflect$generic$Types$$tostringRecursions_$eq:(I)V
Asciz	safeToString;
NameAndType	safeToString:()Ljava/lang/String;
Method	scala/reflect/generic/Types$AbsType.safeToString:()Ljava/lang/String;
Asciz	exceptionResult1;
Asciz	Ljava/lang/String;;
Asciz	java/lang/Object;
class	java/lang/Object
NameAndType	toString:()Ljava/lang/String;
Method	java/lang/Object.toString:()Ljava/lang/String;
NameAndType	$outer:Lscala/reflect/generic/Universe;
Field	scala/reflect/generic/Types$AbsType.$outer:Lscala/reflect/generic/Universe;
Asciz	<init>;
Asciz	(Lscala/reflect/generic/Universe;)V;
Asciz	java/lang/NullPointerException;
class	java/lang/NullPointerException
Asciz	()V;
NameAndType	"<init>":()V
Method	java/lang/NullPointerException."<init>":()V
Method	java/lang/Object."<init>":()V
Asciz	Scala;
Asciz	InnerClasses;
Asciz	AbsType;
Asciz	scala/reflect/generic/Symbols$AbsSymbol;
class	scala/reflect/generic/Symbols$AbsSymbol
Asciz	scala/reflect/generic/Symbols;
class	scala/reflect/generic/Symbols
Asciz	AbsSymbol;
Asciz	scala/ScalaObject;
class	scala/ScalaObject

{
public final scala.reflect.generic.Universe $outer;
  Signature: Lscala/reflect/generic/Universe;

public abstract scala.reflect.generic.Symbols$AbsSymbol typeSymbol();
  Signature: ()Lscala/reflect/generic/Symbols$AbsSymbol;

public abstract scala.reflect.generic.Symbols$AbsSymbol decl(java.lang.Object);
  Signature: (Ljava/lang/Object;)Lscala/reflect/generic/Symbols$AbsSymbol;

public boolean isComplete();
  Signature: ()Z
  Code:
   Stack=1, Locals=1, Args_size=1
	iconst_1
	ireturn
  Labels:

public void complete(scala.reflect.generic.Symbols$AbsSymbol);
  Signature: (Lscala/reflect/generic/Symbols$AbsSymbol;)V
  Code:
   Stack=0, Locals=2, Args_size=2
	return
  Labels:
  LocalVariableTable: 
   Start  Length  Slot  Name   Signature
   0      1      0    this       Lscala/reflect/generic/Types$AbsType;
   0      1      1    sym       Lscala/reflect/generic/Symbols$AbsSymbol;


public java.lang.String toString();
  Signature: ()Ljava/lang/String;
  Code:
   Stack=3, Locals=3, Args_size=1
	aload_0
	invokevirtual	Method scala$reflect$generic$Types$AbsType$$$outer:()Lscala/reflect/generic/Universe;
	invokeinterface	InterfaceMethod scala/reflect/generic/Types.scala$reflect$generic$Types$$tostringRecursions:()I
	ldc	int 50
	if_icmplt	l1 // aload_0
	ldc	String ...
	goto	l2 // areturn
l1	aload_0
	invokevirtual	Method scala$reflect$generic$Types$AbsType$$$outer:()Lscala/reflect/generic/Universe;
	aload_0
	invokevirtual	Method scala$reflect$generic$Types$AbsType$$$outer:()Lscala/reflect/generic/Universe;
	invokeinterface	InterfaceMethod scala/reflect/generic/Types.scala$reflect$generic$Types$$tostringRecursions:()I
	iconst_1
	iadd
	invokeinterface	InterfaceMethod scala/reflect/generic/Types.scala$reflect$generic$Types$$tostringRecursions_$eq:(I)V
	aload_0
	invokevirtual	Method safeToString:()Ljava/lang/String;
	astore_1
	aload_0
	invokevirtual	Method scala$reflect$generic$Types$AbsType$$$outer:()Lscala/reflect/generic/Universe;
	aload_0
	invokevirtual	Method scala$reflect$generic$Types$AbsType$$$outer:()Lscala/reflect/generic/Universe;
	invokeinterface	InterfaceMethod scala/reflect/generic/Types.scala$reflect$generic$Types$$tostringRecursions:()I
	iconst_1
	isub
	invokeinterface	InterfaceMethod scala/reflect/generic/Types.scala$reflect$generic$Types$$tostringRecursions_$eq:(I)V
	aload_1
l2	areturn
	astore_2
	aload_0
	invokevirtual	Method scala$reflect$generic$Types$AbsType$$$outer:()Lscala/reflect/generic/Universe;
	aload_0
	invokevirtual	Method scala$reflect$generic$Types$AbsType$$$outer:()Lscala/reflect/generic/Universe;
	invokeinterface	InterfaceMethod scala/reflect/generic/Types.scala$reflect$generic$Types$$tostringRecursions:()I
	iconst_1
	isub
	invokeinterface	InterfaceMethod scala/reflect/generic/Types.scala$reflect$generic$Types$$tostringRecursions_$eq:(I)V
	aload_2
	athrow
  Labels:
   	l1 = 19 // aload_0
   	l2 = 65 // areturn
  Exception table:
   from   to  target type
    19    44    66   any
  LocalVariableTable: 
   Start  Length  Slot  Name   Signature
   0      89      0    this       Lscala/reflect/generic/Types$AbsType;
   19      46      1    exceptionResult1       Ljava/lang/String;
   66      23      1    exceptionResult1       Ljava/lang/String;


public java.lang.String safeToString();
  Signature: ()Ljava/lang/String;
  Code:
   Stack=1, Locals=1, Args_size=1
	aload_0
	invokespecial	Method java/lang/Object.toString:()Ljava/lang/String;
	areturn
  Labels:

public scala.reflect.generic.Universe scala$reflect$generic$Types$AbsType$$$outer();
  Signature: ()Lscala/reflect/generic/Universe;
  Code:
   Stack=1, Locals=1, Args_size=1
	aload_0
	getfield	Field $outer:Lscala/reflect/generic/Universe;
	areturn
  Labels:

public scala.reflect.generic.Types$AbsType(scala.reflect.generic.Universe);
  Signature: (Lscala/reflect/generic/Universe;)V
  Code:
   Stack=2, Locals=2, Args_size=2
	aload_1
	ifnonnull	l1 // aload_0
	new	class java/lang/NullPointerException
	dup
	invokespecial	Method java/lang/NullPointerException."<init>":()V
	athrow
l1	aload_0
	aload_1
	putfield	Field $outer:Lscala/reflect/generic/Universe;
	aload_0
	invokespecial	Method java/lang/Object."<init>":()V
	return
  Labels:
   	l1 = 12 // aload_0
  LocalVariableTable: 
   Start  Length  Slot  Name   Signature
   0      22      0    this       Lscala/reflect/generic/Types$AbsType;
   0      22      1    $outer       Lscala/reflect/generic/Universe;


}

