Compiled from "UnPickler.scala"
public abstract class scala.reflect.generic.UnPickler$Scan extends scala.reflect.generic.PickleBuffer implements scala.ScalaObject
  SourceFile: "UnPickler.scala"
  Scala: length = 0x
   
  InnerClass: 
   public If=class scala/reflect/generic/Trees$If of class scala/reflect/generic/Trees
   public Try=class scala/reflect/generic/Trees$Try of class scala/reflect/generic/Trees
   public New=class scala/reflect/generic/Trees$New of class scala/reflect/generic/Trees
   public Star=class scala/reflect/generic/Trees$Star of class scala/reflect/generic/Trees
   public Bind=class scala/reflect/generic/Trees$Bind of class scala/reflect/generic/Trees
   public This=class scala/reflect/generic/Trees$This of class scala/reflect/generic/Trees
   public abstract Tree=class scala/reflect/generic/Trees$Tree of class scala/reflect/generic/Trees
   public Block=class scala/reflect/generic/Trees$Block of class scala/reflect/generic/Trees
   public Match=class scala/reflect/generic/Trees$Match of class scala/reflect/generic/Trees
   public Throw=class scala/reflect/generic/Trees$Throw of class scala/reflect/generic/Trees
   public Typed=class scala/reflect/generic/Trees$Typed of class scala/reflect/generic/Trees
   public Apply=class scala/reflect/generic/Trees$Apply of class scala/reflect/generic/Trees
   public Super=class scala/reflect/generic/Trees$Super of class scala/reflect/generic/Trees
   public Ident=class scala/reflect/generic/Trees$Ident of class scala/reflect/generic/Trees
   public abstract ByOne=class scala/collection/immutable/Range$ByOne of class scala/collection/immutable/Range
   public DefDef=class scala/reflect/generic/Trees$DefDef of class scala/reflect/generic/Trees
   public Import=class scala/reflect/generic/Trees$Import of class scala/reflect/generic/Trees
   public Assign=class scala/reflect/generic/Trees$Assign of class scala/reflect/generic/Trees
   public Return=class scala/reflect/generic/Trees$Return of class scala/reflect/generic/Trees
   public Select=class scala/reflect/generic/Trees$Select of class scala/reflect/generic/Trees
   public ValDef=class scala/reflect/generic/Trees$ValDef of class scala/reflect/generic/Trees
   public TypeDef=class scala/reflect/generic/Trees$TypeDef of class scala/reflect/generic/Trees
   public CaseDef=class scala/reflect/generic/Trees$CaseDef of class scala/reflect/generic/Trees
   public UnApply=class scala/reflect/generic/Trees$UnApply of class scala/reflect/generic/Trees
   public abstract RefTree=class scala/reflect/generic/Trees$RefTree of class scala/reflect/generic/Trees
   public Literal=class scala/reflect/generic/Trees$Literal of class scala/reflect/generic/Trees
   public abstract AbsType=class scala/reflect/generic/Types$AbsType of class scala/reflect/generic/Types
   public ClassDef=class scala/reflect/generic/Trees$ClassDef of class scala/reflect/generic/Trees
   public LabelDef=class scala/reflect/generic/Trees$LabelDef of class scala/reflect/generic/Trees
   public Function=class scala/reflect/generic/Trees$Function of class scala/reflect/generic/Trees
   public Template=class scala/reflect/generic/Trees$Template of class scala/reflect/generic/Trees
   public abstract Scan=class scala/reflect/generic/UnPickler$Scan of class scala/reflect/generic/UnPickler
   public ModuleDef=class scala/reflect/generic/Trees$ModuleDef of class scala/reflect/generic/Trees
   public Modifiers=class scala/reflect/generic/Trees$Modifiers of class scala/reflect/generic/Trees
   public TypeApply=class scala/reflect/generic/Trees$TypeApply of class scala/reflect/generic/Trees
   public Annotated=class scala/reflect/generic/Trees$Annotated of class scala/reflect/generic/Trees
   public abstract AbsScope=class scala/reflect/generic/Scopes$AbsScope of class scala/reflect/generic/Scopes
   public PackageDef=class scala/reflect/generic/Trees$PackageDef of class scala/reflect/generic/Trees
   public ArrayValue=class scala/reflect/generic/Trees$ArrayValue of class scala/reflect/generic/Trees
   public Alternative=class scala/reflect/generic/Trees$Alternative of class scala/reflect/generic/Trees
   public abstract AbsTypeTree=class scala/reflect/generic/Trees$AbsTypeTree of class scala/reflect/generic/Trees
   public abstract AbsSymbol=class scala/reflect/generic/Symbols$AbsSymbol of class scala/reflect/generic/Symbols
   public ApplyDynamic=class scala/reflect/generic/Trees$ApplyDynamic of class scala/reflect/generic/Trees
   public Constant=class scala/reflect/generic/Constants$Constant of class scala/reflect/generic/Constants
   public TypeBoundsTree=class scala/reflect/generic/Trees$TypeBoundsTree of class scala/reflect/generic/Trees
   public AppliedTypeTree=class scala/reflect/generic/Trees$AppliedTypeTree of class scala/reflect/generic/Trees
   public CompoundTypeTree=class scala/reflect/generic/Trees$CompoundTypeTree of class scala/reflect/generic/Trees
   public abstract TypeRefExtractor=class scala/reflect/generic/Types$TypeRefExtractor of class scala/reflect/generic/Types
   public StandardNames=class scala/reflect/generic/StdNames$StandardNames of class scala/reflect/generic/StdNames
   public abstract TypeTreeExtractor=class scala/reflect/generic/Trees$TypeTreeExtractor of class scala/reflect/generic/Trees
   public SingletonTypeTree=class scala/reflect/generic/Trees$SingletonTypeTree of class scala/reflect/generic/Trees
   public abstract ThisTypeExtractor=class scala/reflect/generic/Types$ThisTypeExtractor of class scala/reflect/generic/Types
   public abstract PolyTypeExtractor=class scala/reflect/generic/Types$PolyTypeExtractor of class scala/reflect/generic/Types
   public SelectFromTypeTree=class scala/reflect/generic/Trees$SelectFromTypeTree of class scala/reflect/generic/Trees
   public abstract SuperTypeExtractor=class scala/reflect/generic/Types$SuperTypeExtractor of class scala/reflect/generic/Types
   public ExistentialTypeTree=class scala/reflect/generic/Trees$ExistentialTypeTree of class scala/reflect/generic/Trees
   public final $anonfun$9=class scala/reflect/generic/UnPickler$Scan$$anonfun$9 of class scala/reflect/generic/UnPickler$Scan
   public abstract SingleTypeExtractor=class scala/reflect/generic/Types$SingleTypeExtractor of class scala/reflect/generic/Types
   public final $anonfun$3=class scala/reflect/generic/UnPickler$Scan$$anonfun$3 of class scala/reflect/generic/UnPickler$Scan
   public abstract TypeBoundsExtractor=class scala/reflect/generic/Types$TypeBoundsExtractor of class scala/reflect/generic/Types
   public abstract MethodTypeExtractor=class scala/reflect/generic/Types$MethodTypeExtractor of class scala/reflect/generic/Types
   public final $anonfun$4=class scala/reflect/generic/UnPickler$Scan$$anonfun$4 of class scala/reflect/generic/UnPickler$Scan
   public final $anonfun$5=class scala/reflect/generic/UnPickler$Scan$$anonfun$5 of class scala/reflect/generic/UnPickler$Scan
   public final $anonfun$8=class scala/reflect/generic/UnPickler$Scan$$anonfun$8 of class scala/reflect/generic/UnPickler$Scan
   public final $anonfun$7=class scala/reflect/generic/UnPickler$Scan$$anonfun$7 of class scala/reflect/generic/UnPickler$Scan
   public final $anonfun$6=class scala/reflect/generic/UnPickler$Scan$$anonfun$6 of class scala/reflect/generic/UnPickler$Scan
   public final $anonfun$2=class scala/reflect/generic/UnPickler$Scan$$anonfun$2 of class scala/reflect/generic/UnPickler$Scan
   public final $anonfun$1=class scala/reflect/generic/UnPickler$Scan$$anonfun$1 of class scala/reflect/generic/UnPickler$Scan
   public final $anonfun$11=class scala/reflect/generic/UnPickler$Scan$$anonfun$11 of class scala/reflect/generic/UnPickler$Scan
   public final $anonfun$12=class scala/reflect/generic/UnPickler$Scan$$anonfun$12 of class scala/reflect/generic/UnPickler$Scan
   public final $anonfun$14=class scala/reflect/generic/UnPickler$Scan$$anonfun$14 of class scala/reflect/generic/UnPickler$Scan
   public final $anonfun$13=class scala/reflect/generic/UnPickler$Scan$$anonfun$13 of class scala/reflect/generic/UnPickler$Scan
   public final $anonfun$15=class scala/reflect/generic/UnPickler$Scan$$anonfun$15 of class scala/reflect/generic/UnPickler$Scan
   public final $anonfun$16=class scala/reflect/generic/UnPickler$Scan$$anonfun$16 of class scala/reflect/generic/UnPickler$Scan
   public final $anonfun$17=class scala/reflect/generic/UnPickler$Scan$$anonfun$17 of class scala/reflect/generic/UnPickler$Scan
   public final $anonfun$19=class scala/reflect/generic/UnPickler$Scan$$anonfun$19 of class scala/reflect/generic/UnPickler$Scan
   public final $anonfun$18=class scala/reflect/generic/UnPickler$Scan$$anonfun$18 of class scala/reflect/generic/UnPickler$Scan
   public final $anonfun$20=class scala/reflect/generic/UnPickler$Scan$$anonfun$20 of class scala/reflect/generic/UnPickler$Scan
   public final $anonfun$21=class scala/reflect/generic/UnPickler$Scan$$anonfun$21 of class scala/reflect/generic/UnPickler$Scan
   public final $anonfun$22=class scala/reflect/generic/UnPickler$Scan$$anonfun$22 of class scala/reflect/generic/UnPickler$Scan
   public final $anonfun$23=class scala/reflect/generic/UnPickler$Scan$$anonfun$23 of class scala/reflect/generic/UnPickler$Scan
   public final $anonfun$24=class scala/reflect/generic/UnPickler$Scan$$anonfun$24 of class scala/reflect/generic/UnPickler$Scan
   public final $anonfun$25=class scala/reflect/generic/UnPickler$Scan$$anonfun$25 of class scala/reflect/generic/UnPickler$Scan
   public final $anonfun$26=class scala/reflect/generic/UnPickler$Scan$$anonfun$26 of class scala/reflect/generic/UnPickler$Scan
   public final $anonfun$27=class scala/reflect/generic/UnPickler$Scan$$anonfun$27 of class scala/reflect/generic/UnPickler$Scan
   public final $anonfun$29=class scala/reflect/generic/UnPickler$Scan$$anonfun$29 of class scala/reflect/generic/UnPickler$Scan
   public final $anonfun$28=class scala/reflect/generic/UnPickler$Scan$$anonfun$28 of class scala/reflect/generic/UnPickler$Scan
   public final $anonfun$30=class scala/reflect/generic/UnPickler$Scan$$anonfun$30 of class scala/reflect/generic/UnPickler$Scan
   public final $anonfun$31=class scala/reflect/generic/UnPickler$Scan$$anonfun$31 of class scala/reflect/generic/UnPickler$Scan
   public final $anonfun$32=class scala/reflect/generic/UnPickler$Scan$$anonfun$32 of class scala/reflect/generic/UnPickler$Scan
   public final $anonfun$10=class scala/reflect/generic/UnPickler$Scan$$anonfun$10 of class scala/reflect/generic/UnPickler$Scan
   public abstract RefinedTypeExtractor=class scala/reflect/generic/Types$RefinedTypeExtractor of class scala/reflect/generic/Types
   public abstract ConstantTypeExtractor=class scala/reflect/generic/Types$ConstantTypeExtractor of class scala/reflect/generic/Types
   public abstract ClassInfoTypeExtractor=class scala/reflect/generic/Types$ClassInfoTypeExtractor of class scala/reflect/generic/Types
   public abstract AnnotatedTypeExtractor=class scala/reflect/generic/Types$AnnotatedTypeExtractor of class scala/reflect/generic/Types
   public final $anonfun$at$1=class scala/reflect/generic/UnPickler$Scan$$anonfun$at$1 of class scala/reflect/generic/UnPickler$Scan
   public final $anonfun$run$1=class scala/reflect/generic/UnPickler$Scan$$anonfun$run$1 of class scala/reflect/generic/UnPickler$Scan
   public abstract ExistentialTypeExtractor=class scala/reflect/generic/Types$ExistentialTypeExtractor of class scala/reflect/generic/Types
   public final $anonfun$readType$1=class scala/reflect/generic/UnPickler$Scan$$anonfun$readType$1 of class scala/reflect/generic/UnPickler$Scan
   public final $anonfun$readType$2=class scala/reflect/generic/UnPickler$Scan$$anonfun$readType$2 of class scala/reflect/generic/UnPickler$Scan
   public final $anonfun$readType$3=class scala/reflect/generic/UnPickler$Scan$$anonfun$readType$3 of class scala/reflect/generic/UnPickler$Scan
   public abstract AbsDefinitions=class scala/reflect/generic/StandardDefinitions$AbsDefinitions of class scala/reflect/generic/StandardDefinitions
   public final $anonfun$readSymbol$3=class scala/reflect/generic/UnPickler$Scan$$anonfun$readSymbol$3 of class scala/reflect/generic/UnPickler$Scan
   public final $anonfun$readSymbol$2=class scala/reflect/generic/UnPickler$Scan$$anonfun$readSymbol$2 of class scala/reflect/generic/UnPickler$Scan
   public final $anonfun$readSymbol$1=class scala/reflect/generic/UnPickler$Scan$$anonfun$readSymbol$1 of class scala/reflect/generic/UnPickler$Scan
   public final $anonfun$readTreeRef$1=class scala/reflect/generic/UnPickler$Scan$$anonfun$readTreeRef$1 of class scala/reflect/generic/UnPickler$Scan
   public final $anonfun$readTypeRef$1=class scala/reflect/generic/UnPickler$Scan$$anonfun$readTypeRef$1 of class scala/reflect/generic/UnPickler$Scan
   public final $anonfun$readNameRef$1=class scala/reflect/generic/UnPickler$Scan$$anonfun$readNameRef$1 of class scala/reflect/generic/UnPickler$Scan
   public final $anonfun$readAnnotArg$1=class scala/reflect/generic/UnPickler$Scan$$anonfun$readAnnotArg$1 of class scala/reflect/generic/UnPickler$Scan
   public final $anonfun$readSymbolRef$1=class scala/reflect/generic/UnPickler$Scan$$anonfun$readSymbolRef$1 of class scala/reflect/generic/UnPickler$Scan
   public abstract AnnotationInfoExtractor=class scala/reflect/generic/AnnotationInfos$AnnotationInfoExtractor of class scala/reflect/generic/AnnotationInfos
   public abstract NestedAnnotArgExtractor=class scala/reflect/generic/AnnotationInfos$NestedAnnotArgExtractor of class scala/reflect/generic/AnnotationInfos
   public abstract LiteralAnnotArgExtractor=class scala/reflect/generic/AnnotationInfos$LiteralAnnotArgExtractor of class scala/reflect/generic/AnnotationInfos
   public final $anonfun$readConstantRef$1=class scala/reflect/generic/UnPickler$Scan$$anonfun$readConstantRef$1 of class scala/reflect/generic/UnPickler$Scan
   public final $anonfun$readModifiersRef$1=class scala/reflect/generic/UnPickler$Scan$$anonfun$readModifiersRef$1 of class scala/reflect/generic/UnPickler$Scan
   public final $anonfun$readAnnotationRef$1=class scala/reflect/generic/UnPickler$Scan$$anonfun$readAnnotationRef$1 of class scala/reflect/generic/UnPickler$Scan
   public final $anonfun$readClassfileAnnotArg$3=class scala/reflect/generic/UnPickler$Scan$$anonfun$readClassfileAnnotArg$3 of class scala/reflect/generic/UnPickler$Scan
   public final $anonfun$readClassfileAnnotArg$2=class scala/reflect/generic/UnPickler$Scan$$anonfun$readClassfileAnnotArg$2 of class scala/reflect/generic/UnPickler$Scan
   public final $anonfun$readClassfileAnnotArg$1=class scala/reflect/generic/UnPickler$Scan$$anonfun$readClassfileAnnotArg$1 of class scala/reflect/generic/UnPickler$Scan
  minor version: 0
  major version: 49
  Constant pool:
Asciz	SourceFile;
Asciz	UnPickler.scala;
Asciz	$outer;
Asciz	Lscala/reflect/generic/UnPickler;;
Asciz	symScopes;
Asciz	Lscala/collection/mutable/HashMap;;
Asciz	Lscala/collection/mutable/HashMap<Lscala/reflect/generic/Symbols$AbsSymbol;Lscala/reflect/generic/Scopes$AbsScope;>;;
Asciz	Signature;
Asciz	scala$reflect$generic$UnPickler$Scan$$entries;
Asciz	[Ljava/lang/Object;;
Asciz	index;
Asciz	[I;
Asciz	filename;
Asciz	Ljava/lang/String;;
Asciz	moduleRoot;
Asciz	Lscala/reflect/generic/Symbols$AbsSymbol;;
Asciz	classRoot;
Asciz	bytes;
Asciz	[B;
Asciz	debug;
Asciz	()Z;
Asciz	Code;
Asciz	LineNumberTable;
Asciz	()[I;
Asciz	scala/reflect/generic/UnPickler$Scan;
class	scala/reflect/generic/UnPickler$Scan
NameAndType	index:[I
Field	scala/reflect/generic/UnPickler$Scan.index:[I
Asciz	()[Ljava/lang/Object;;
NameAndType	scala$reflect$generic$UnPickler$Scan$$entries:[Ljava/lang/Object;
Field	scala/reflect/generic/UnPickler$Scan.scala$reflect$generic$UnPickler$Scan$$entries:[Ljava/lang/Object;
Asciz	()Lscala/collection/mutable/HashMap;;
NameAndType	symScopes:Lscala/collection/mutable/HashMap;
Field	scala/reflect/generic/UnPickler$Scan.symScopes:Lscala/collection/mutable/HashMap;
Asciz	()Lscala/collection/mutable/HashMap<Lscala/reflect/generic/Symbols$AbsSymbol;Lscala/reflect/generic/Scopes$AbsScope;>;;
Asciz	run;
Asciz	()V;
Asciz	scala/Predef$;
class	scala/Predef$
Asciz	MODULE$;
Asciz	Lscala/Predef$;;
NameAndType	MODULE$:Lscala/Predef$;
Field	scala/Predef$.MODULE$:Lscala/Predef$;
Asciz	intWrapper;
Asciz	(I)Lscala/runtime/RichInt;;
NameAndType	intWrapper:(I)Lscala/runtime/RichInt;
Method	scala/Predef$.intWrapper:(I)Lscala/runtime/RichInt;
NameAndType	index:()[I
Method	scala/reflect/generic/UnPickler$Scan.index:()[I
Asciz	scala/runtime/RichInt;
class	scala/runtime/RichInt
Asciz	until;
Asciz	(I)Lscala/collection/immutable/Range$ByOne;;
NameAndType	until:(I)Lscala/collection/immutable/Range$ByOne;
Method	scala/runtime/RichInt.until:(I)Lscala/collection/immutable/Range$ByOne;
Asciz	scala/reflect/generic/UnPickler$Scan$$anonfun$run$1;
class	scala/reflect/generic/UnPickler$Scan$$anonfun$run$1
Asciz	<init>;
Asciz	(Lscala/reflect/generic/UnPickler$Scan;)V;
NameAndType	"<init>":(Lscala/reflect/generic/UnPickler$Scan;)V
Method	scala/reflect/generic/UnPickler$Scan$$anonfun$run$1."<init>":(Lscala/reflect/generic/UnPickler$Scan;)V
Asciz	scala/collection/immutable/Range$ByOne;
class	scala/collection/immutable/Range$ByOne
Asciz	foreach;
Asciz	(Lscala/Function1;)V;
NameAndType	foreach:(Lscala/Function1;)V
InterfaceMethod	scala/collection/immutable/Range$ByOne.foreach:(Lscala/Function1;)V
Asciz	checkVersion;
Asciz	readNat;
Asciz	()I;
NameAndType	readNat:()I
Method	scala/reflect/generic/UnPickler$Scan.readNat:()I
Asciz	scala/reflect/generic/PickleFormat$;
class	scala/reflect/generic/PickleFormat$
Asciz	Lscala/reflect/generic/PickleFormat$;;
NameAndType	MODULE$:Lscala/reflect/generic/PickleFormat$;
Field	scala/reflect/generic/PickleFormat$.MODULE$:Lscala/reflect/generic/PickleFormat$;
Asciz	MajorVersion;
NameAndType	MajorVersion:()I
Method	scala/reflect/generic/PickleFormat$.MajorVersion:()I
Asciz	MinorVersion;
NameAndType	MinorVersion:()I
Method	scala/reflect/generic/PickleFormat$.MinorVersion:()I
Asciz	java/io/IOException;
class	java/io/IOException
Asciz	scala/collection/mutable/StringBuilder;
class	scala/collection/mutable/StringBuilder
NameAndType	"<init>":()V
Method	scala/collection/mutable/StringBuilder."<init>":()V
Asciz	Scala signature ;
String	Scala signature 
Asciz	append;
Asciz	(Ljava/lang/Object;)Lscala/collection/mutable/StringBuilder;;
NameAndType	append:(Ljava/lang/Object;)Lscala/collection/mutable/StringBuilder;
Method	scala/collection/mutable/StringBuilder.append:(Ljava/lang/Object;)Lscala/collection/mutable/StringBuilder;
NameAndType	classRoot:Lscala/reflect/generic/Symbols$AbsSymbol;
Field	scala/reflect/generic/UnPickler$Scan.classRoot:Lscala/reflect/generic/Symbols$AbsSymbol;
Asciz	scala/reflect/generic/Symbols$AbsSymbol;
class	scala/reflect/generic/Symbols$AbsSymbol
Asciz	decodedName;
Asciz	()Ljava/lang/String;;
NameAndType	decodedName:()Ljava/lang/String;
Method	scala/reflect/generic/Symbols$AbsSymbol.decodedName:()Ljava/lang/String;
Asciz	 has wrong version\n expected: ;
String	 has wrong version\n expected: 
Asciz	scala/runtime/BoxesRunTime;
class	scala/runtime/BoxesRunTime
Asciz	boxToInteger;
Asciz	(I)Ljava/lang/Integer;;
NameAndType	boxToInteger:(I)Ljava/lang/Integer;
Method	scala/runtime/BoxesRunTime.boxToInteger:(I)Ljava/lang/Integer;
Asciz	.;
String	.
Asciz	\n found: ;
String	\n found: 
Asciz	 in ;
String	 in 
NameAndType	filename:Ljava/lang/String;
Field	scala/reflect/generic/UnPickler$Scan.filename:Ljava/lang/String;
Asciz	toString;
NameAndType	toString:()Ljava/lang/String;
Method	scala/collection/mutable/StringBuilder.toString:()Ljava/lang/String;
Asciz	(Ljava/lang/String;)V;
NameAndType	"<init>":(Ljava/lang/String;)V
Method	java/io/IOException."<init>":(Ljava/lang/String;)V
Asciz	this;
Asciz	Lscala/reflect/generic/UnPickler$Scan;;
Asciz	major;
Asciz	I;
Asciz	minor;
Asciz	LocalVariableTable;
Asciz	symScope;
Asciz	(Lscala/reflect/generic/Symbols$AbsSymbol;)Lscala/reflect/generic/Scopes$AbsScope;;
NameAndType	symScopes:()Lscala/collection/mutable/HashMap;
Method	scala/reflect/generic/UnPickler$Scan.symScopes:()Lscala/collection/mutable/HashMap;
Asciz	scala/collection/mutable/HashMap;
class	scala/collection/mutable/HashMap
Asciz	get;
Asciz	(Ljava/lang/Object;)Lscala/Option;;
NameAndType	get:(Ljava/lang/Object;)Lscala/Option;
Method	scala/collection/mutable/HashMap.get:(Ljava/lang/Object;)Lscala/Option;
Asciz	scala/None$;
class	scala/None$
Asciz	Lscala/None$;;
NameAndType	MODULE$:Lscala/None$;
Field	scala/None$.MODULE$:Lscala/None$;
Asciz	java/lang/Object;
class	java/lang/Object
Asciz	equals;
Asciz	(Ljava/lang/Object;)Z;
NameAndType	equals:(Ljava/lang/Object;)Z
Method	java/lang/Object.equals:(Ljava/lang/Object;)Z
Asciz	scala$reflect$generic$UnPickler$Scan$$$outer;
Asciz	()Lscala/reflect/generic/UnPickler;;
NameAndType	scala$reflect$generic$UnPickler$Scan$$$outer:()Lscala/reflect/generic/UnPickler;
Method	scala/reflect/generic/UnPickler$Scan.scala$reflect$generic$UnPickler$Scan$$$outer:()Lscala/reflect/generic/UnPickler;
Asciz	scala/reflect/generic/UnPickler;
class	scala/reflect/generic/UnPickler
Asciz	global;
Asciz	()Lscala/reflect/generic/Universe;;
NameAndType	global:()Lscala/reflect/generic/Universe;
Method	scala/reflect/generic/UnPickler.global:()Lscala/reflect/generic/Universe;
Asciz	scala/reflect/generic/Scopes;
class	scala/reflect/generic/Scopes
Asciz	newScope;
Asciz	()Lscala/reflect/generic/Scopes$AbsScope;;
NameAndType	newScope:()Lscala/reflect/generic/Scopes$AbsScope;
InterfaceMethod	scala/reflect/generic/Scopes.newScope:()Lscala/reflect/generic/Scopes$AbsScope;
Asciz	update;
Asciz	(Ljava/lang/Object;Ljava/lang/Object;)V;
NameAndType	update:(Ljava/lang/Object;Ljava/lang/Object;)V
Method	scala/collection/mutable/HashMap.update:(Ljava/lang/Object;Ljava/lang/Object;)V
Asciz	scala/Some;
class	scala/Some
Asciz	x;
Asciz	()Ljava/lang/Object;;
NameAndType	x:()Ljava/lang/Object;
Method	scala/Some.x:()Ljava/lang/Object;
Asciz	scala/reflect/generic/Scopes$AbsScope;
class	scala/reflect/generic/Scopes$AbsScope
Asciz	scala/MatchError;
class	scala/MatchError
Asciz	(Ljava/lang/Object;)V;
NameAndType	"<init>":(Ljava/lang/Object;)V
Method	scala/MatchError."<init>":(Ljava/lang/Object;)V
Asciz	sym;
Asciz	temp1;
Asciz	Lscala/Option;;
Asciz	s;
Asciz	Lscala/reflect/generic/Scopes$AbsScope;;
Asciz	isSymbolEntry;
Asciz	(I)Z;
NameAndType	bytes:[B
Field	scala/reflect/generic/UnPickler$Scan.bytes:[B
int	8;
int	6;
Asciz	isRefinementSymbolEntry;
NameAndType	isRefinementSymbolEntry:(I)Z
Method	scala/reflect/generic/UnPickler$Scan.isRefinementSymbolEntry:(I)Z
Asciz	i;
Asciz	tag;
Asciz	isSymbolRef;
int	10;
Asciz	B;
Asciz	isNameEntry;
Asciz	isSymbolAnnotationEntry;
int	40;
Asciz	isChildrenEntry;
int	41;
Asciz	readIndex;
NameAndType	readIndex:()I
Method	scala/reflect/generic/UnPickler$Scan.readIndex:()I
Asciz	readIndex_$eq;
Asciz	(I)V;
NameAndType	readIndex_$eq:(I)V
Method	scala/reflect/generic/UnPickler$Scan.readIndex_$eq:(I)V
Asciz	readByte;
NameAndType	readByte:()I
Method	scala/reflect/generic/UnPickler$Scan.readByte:()I
Asciz	assert;
Asciz	(Z)V;
NameAndType	assert:(Z)V
Method	scala/Predef$.assert:(Z)V
Asciz	readNameRef;
NameAndType	readNameRef:()Ljava/lang/Object;
Method	scala/reflect/generic/UnPickler$Scan.readNameRef:()Ljava/lang/Object;
Asciz	scala/reflect/generic/StdNames;
class	scala/reflect/generic/StdNames
Asciz	nme;
Asciz	()Lscala/reflect/generic/StdNames$StandardNames;;
NameAndType	nme:()Lscala/reflect/generic/StdNames$StandardNames;
InterfaceMethod	scala/reflect/generic/StdNames.nme:()Lscala/reflect/generic/StdNames$StandardNames;
Asciz	scala/reflect/generic/StdNames$StandardNames;
class	scala/reflect/generic/StdNames$StandardNames
Asciz	REFINE_CLASS_NAME;
NameAndType	REFINE_CLASS_NAME:()Ljava/lang/Object;
Method	scala/reflect/generic/StdNames$StandardNames.REFINE_CLASS_NAME:()Ljava/lang/Object;
Asciz	scala/reflect/generic/Names;
class	scala/reflect/generic/Names
Asciz	mkTypeName;
Asciz	(Ljava/lang/Object;)Ljava/lang/Object;;
NameAndType	mkTypeName:(Ljava/lang/Object;)Ljava/lang/Object;
InterfaceMethod	scala/reflect/generic/Names.mkTypeName:(Ljava/lang/Object;)Ljava/lang/Object;
Asciz	(Ljava/lang/Object;Ljava/lang/Object;)Z;
NameAndType	equals:(Ljava/lang/Object;Ljava/lang/Object;)Z
Method	scala/runtime/BoxesRunTime.equals:(Ljava/lang/Object;Ljava/lang/Object;)Z
Asciz	savedIndex;
Asciz	result;
Asciz	Z;
Asciz	at;
Asciz	(ILscala/Function0;)Ljava/lang/Object;;
NameAndType	scala$reflect$generic$UnPickler$Scan$$entries:()[Ljava/lang/Object;
Method	scala/reflect/generic/UnPickler$Scan.scala$reflect$generic$UnPickler$Scan$$entries:()[Ljava/lang/Object;
Asciz	scala/Function0;
class	scala/Function0
Asciz	apply;
NameAndType	apply:()Ljava/lang/Object;
InterfaceMethod	scala/Function0.apply:()Ljava/lang/Object;
Asciz	scala/reflect/generic/UnPickler$Scan$$anonfun$at$1;
class	scala/reflect/generic/UnPickler$Scan$$anonfun$at$1
Asciz	(Lscala/reflect/generic/UnPickler$Scan;I)V;
NameAndType	"<init>":(Lscala/reflect/generic/UnPickler$Scan;I)V
Method	scala/reflect/generic/UnPickler$Scan$$anonfun$at$1."<init>":(Lscala/reflect/generic/UnPickler$Scan;I)V
Asciz	(ZLscala/Function0;)V;
NameAndType	assert:(ZLscala/Function0;)V
Method	scala/Predef$.assert:(ZLscala/Function0;)V
Asciz	i$1;
Asciz	op;
Asciz	Lscala/Function0;;
Asciz	r;
Asciz	Ljava/lang/Object;;
Asciz	<T:Ljava/lang/Object;>(ILscala/Function0<TT;>;)TT;;
Asciz	readName;
Asciz	bad name tag: ;
String	bad name tag: 
Asciz	errorBadSignature;
Asciz	(Ljava/lang/String;)Lscala/runtime/Nothing$;;
NameAndType	errorBadSignature:(Ljava/lang/String;)Lscala/runtime/Nothing$;
Method	scala/reflect/generic/UnPickler$Scan.errorBadSignature:(Ljava/lang/String;)Lscala/runtime/Nothing$;
Asciz	newTypeName;
Asciz	([BII)Ljava/lang/Object;;
NameAndType	newTypeName:([BII)Ljava/lang/Object;
InterfaceMethod	scala/reflect/generic/Names.newTypeName:([BII)Ljava/lang/Object;
Asciz	newTermName;
NameAndType	newTermName:([BII)Ljava/lang/Object;
InterfaceMethod	scala/reflect/generic/Names.newTermName:([BII)Ljava/lang/Object;
Asciz	len;
Asciz	temp5;
Asciz	readSymbol;
Asciz	()Lscala/reflect/generic/Symbols$AbsSymbol;;
Asciz	scala/runtime/ObjectRef;
class	scala/runtime/ObjectRef
Asciz	scala/reflect/generic/Symbols;
class	scala/reflect/generic/Symbols
Asciz	NoSymbol;
NameAndType	NoSymbol:()Lscala/reflect/generic/Symbols$AbsSymbol;
InterfaceMethod	scala/reflect/generic/Symbols.NoSymbol:()Lscala/reflect/generic/Symbols$AbsSymbol;
Method	scala/runtime/ObjectRef."<init>":(Ljava/lang/Object;)V
NameAndType	isSymbolRef:(I)Z
Method	scala/reflect/generic/UnPickler$Scan.isSymbolRef:(I)Z
Asciz	scala/reflect/generic/UnPickler$Scan$$anonfun$readSymbol$1;
class	scala/reflect/generic/UnPickler$Scan$$anonfun$readSymbol$1
Method	scala/reflect/generic/UnPickler$Scan$$anonfun$readSymbol$1."<init>":(Lscala/reflect/generic/UnPickler$Scan;)V
NameAndType	at:(ILscala/Function0;)Ljava/lang/Object;
Method	scala/reflect/generic/UnPickler$Scan.at:(ILscala/Function0;)Ljava/lang/Object;
Asciz	scala/reflect/generic/UnPickler$Scan$$anonfun$1;
class	scala/reflect/generic/UnPickler$Scan$$anonfun$1
Method	scala/reflect/generic/UnPickler$Scan$$anonfun$1."<init>":(Lscala/reflect/generic/UnPickler$Scan;)V
Asciz	readSymbolRef;
NameAndType	readSymbolRef:()Lscala/reflect/generic/Symbols$AbsSymbol;
Method	scala/reflect/generic/UnPickler$Scan.readSymbolRef:()Lscala/reflect/generic/Symbols$AbsSymbol;
Asciz	scala/reflect/generic/Flags$;
class	scala/reflect/generic/Flags$
Asciz	Lscala/reflect/generic/Flags$;;
NameAndType	MODULE$:Lscala/reflect/generic/Flags$;
Field	scala/reflect/generic/Flags$.MODULE$:Lscala/reflect/generic/Flags$;
Asciz	readLongNat;
Asciz	()J;
NameAndType	readLongNat:()J
Method	scala/reflect/generic/UnPickler$Scan.readLongNat:()J
Asciz	pickledToRawFlags;
Asciz	(J)J;
NameAndType	pickledToRawFlags:(J)J
Method	scala/reflect/generic/Flags$.pickledToRawFlags:(J)J
Asciz	scala/reflect/generic/UnPickler$Scan$$anonfun$readSymbol$2;
class	scala/reflect/generic/UnPickler$Scan$$anonfun$readSymbol$2
Method	scala/reflect/generic/UnPickler$Scan$$anonfun$readSymbol$2."<init>":(Lscala/reflect/generic/UnPickler$Scan;)V
Asciz	noSuchSymbolTag;
Asciz	(IILjava/lang/Object;Lscala/reflect/generic/Symbols$AbsSymbol;)Lscala/runtime/Nothing$;;
NameAndType	noSuchSymbolTag:(IILjava/lang/Object;Lscala/reflect/generic/Symbols$AbsSymbol;)Lscala/runtime/Nothing$;
Method	scala/reflect/generic/UnPickler$Scan.noSuchSymbolTag:(IILjava/lang/Object;Lscala/reflect/generic/Symbols$AbsSymbol;)Lscala/runtime/Nothing$;
NameAndType	moduleRoot:Lscala/reflect/generic/Symbols$AbsSymbol;
Field	scala/reflect/generic/UnPickler$Scan.moduleRoot:Lscala/reflect/generic/Symbols$AbsSymbol;
Asciz	name;
NameAndType	name:()Ljava/lang/Object;
Method	scala/reflect/generic/Symbols$AbsSymbol.name:()Ljava/lang/Object;
Asciz	owner;
NameAndType	owner:()Lscala/reflect/generic/Symbols$AbsSymbol;
Method	scala/reflect/generic/Symbols$AbsSymbol.owner:()Lscala/reflect/generic/Symbols$AbsSymbol;
long	64l;
Asciz	newMethod$default$2;
NameAndType	newMethod$default$2:()Ljava/lang/Object;
Method	scala/reflect/generic/Symbols$AbsSymbol.newMethod$default$2:()Ljava/lang/Object;
Asciz	newMethod;
Asciz	(Ljava/lang/Object;Ljava/lang/Object;)Lscala/reflect/generic/Symbols$AbsSymbol;;
NameAndType	newMethod:(Ljava/lang/Object;Ljava/lang/Object;)Lscala/reflect/generic/Symbols$AbsSymbol;
Method	scala/reflect/generic/Symbols$AbsSymbol.newMethod:(Ljava/lang/Object;Ljava/lang/Object;)Lscala/reflect/generic/Symbols$AbsSymbol;
Asciz	newValue$default$2;
NameAndType	newValue$default$2:()Ljava/lang/Object;
Method	scala/reflect/generic/Symbols$AbsSymbol.newValue$default$2:()Ljava/lang/Object;
Asciz	newValue;
NameAndType	newValue:(Ljava/lang/Object;Ljava/lang/Object;)Lscala/reflect/generic/Symbols$AbsSymbol;
Method	scala/reflect/generic/Symbols$AbsSymbol.newValue:(Ljava/lang/Object;Ljava/lang/Object;)Lscala/reflect/generic/Symbols$AbsSymbol;
Asciz	elem;
NameAndType	elem:Ljava/lang/Object;
Field	scala/runtime/ObjectRef.elem:Ljava/lang/Object;
Asciz	scala/reflect/generic/UnPickler$Scan$$anonfun$2;
class	scala/reflect/generic/UnPickler$Scan$$anonfun$2
Method	scala/reflect/generic/UnPickler$Scan$$anonfun$2."<init>":(Lscala/reflect/generic/UnPickler$Scan;)V
Asciz	scala/reflect/generic/Types$AbsType;
class	scala/reflect/generic/Types$AbsType
Asciz	typeSymbol;
NameAndType	typeSymbol:()Lscala/reflect/generic/Symbols$AbsSymbol;
Method	scala/reflect/generic/Types$AbsType.typeSymbol:()Lscala/reflect/generic/Symbols$AbsSymbol;
Asciz	newModule$default$3;
NameAndType	newModule$default$3:()Ljava/lang/Object;
Method	scala/reflect/generic/Symbols$AbsSymbol.newModule$default$3:()Ljava/lang/Object;
Asciz	newModule;
Asciz	(Ljava/lang/Object;Lscala/reflect/generic/Symbols$AbsSymbol;Ljava/lang/Object;)Lscala/reflect/generic/Symbols$AbsSymbol;;
NameAndType	newModule:(Ljava/lang/Object;Lscala/reflect/generic/Symbols$AbsSymbol;Ljava/lang/Object;)Lscala/reflect/generic/Symbols$AbsSymbol;
Method	scala/reflect/generic/Symbols$AbsSymbol.newModule:(Ljava/lang/Object;Lscala/reflect/generic/Symbols$AbsSymbol;Ljava/lang/Object;)Lscala/reflect/generic/Symbols$AbsSymbol;
Asciz	sourceModule_$eq;
Asciz	(Lscala/reflect/generic/Symbols$AbsSymbol;)V;
NameAndType	sourceModule_$eq:(Lscala/reflect/generic/Symbols$AbsSymbol;)V
Method	scala/reflect/generic/Symbols$AbsSymbol.sourceModule_$eq:(Lscala/reflect/generic/Symbols$AbsSymbol;)V
long	256l;
Asciz	moduleClass;
NameAndType	moduleClass:()Lscala/reflect/generic/Symbols$AbsSymbol;
Method	scala/reflect/generic/Symbols$AbsSymbol.moduleClass:()Lscala/reflect/generic/Symbols$AbsSymbol;
Asciz	newModuleClass$default$2;
NameAndType	newModuleClass$default$2:()Ljava/lang/Object;
Method	scala/reflect/generic/Symbols$AbsSymbol.newModuleClass$default$2:()Ljava/lang/Object;
Asciz	newModuleClass;
NameAndType	newModuleClass:(Ljava/lang/Object;Ljava/lang/Object;)Lscala/reflect/generic/Symbols$AbsSymbol;
Method	scala/reflect/generic/Symbols$AbsSymbol.newModuleClass:(Ljava/lang/Object;Ljava/lang/Object;)Lscala/reflect/generic/Symbols$AbsSymbol;
Asciz	newClass$default$2;
NameAndType	newClass$default$2:()Ljava/lang/Object;
Method	scala/reflect/generic/Symbols$AbsSymbol.newClass$default$2:()Ljava/lang/Object;
Asciz	newClass;
NameAndType	newClass:(Ljava/lang/Object;Ljava/lang/Object;)Lscala/reflect/generic/Symbols$AbsSymbol;
Method	scala/reflect/generic/Symbols$AbsSymbol.newClass:(Ljava/lang/Object;Ljava/lang/Object;)Lscala/reflect/generic/Symbols$AbsSymbol;
Asciz	newLazyTypeRef;
Asciz	(I)Lscala/reflect/generic/Types$AbsType;;
NameAndType	newLazyTypeRef:(I)Lscala/reflect/generic/Types$AbsType;
Method	scala/reflect/generic/UnPickler$Scan.newLazyTypeRef:(I)Lscala/reflect/generic/Types$AbsType;
Asciz	typeOfThis_$eq;
Asciz	(Lscala/reflect/generic/Types$AbsType;)V;
NameAndType	typeOfThis_$eq:(Lscala/reflect/generic/Types$AbsType;)V
Method	scala/reflect/generic/Symbols$AbsSymbol.typeOfThis_$eq:(Lscala/reflect/generic/Types$AbsType;)V
Asciz	newAliasType$default$2;
NameAndType	newAliasType$default$2:()Ljava/lang/Object;
Method	scala/reflect/generic/Symbols$AbsSymbol.newAliasType$default$2:()Ljava/lang/Object;
Asciz	newAliasType;
NameAndType	newAliasType:(Ljava/lang/Object;Ljava/lang/Object;)Lscala/reflect/generic/Symbols$AbsSymbol;
Method	scala/reflect/generic/Symbols$AbsSymbol.newAliasType:(Ljava/lang/Object;Ljava/lang/Object;)Lscala/reflect/generic/Symbols$AbsSymbol;
Asciz	newAbstractType$default$2;
NameAndType	newAbstractType$default$2:()Ljava/lang/Object;
Method	scala/reflect/generic/Symbols$AbsSymbol.newAbstractType$default$2:()Ljava/lang/Object;
Asciz	newAbstractType;
NameAndType	newAbstractType:(Ljava/lang/Object;Ljava/lang/Object;)Lscala/reflect/generic/Symbols$AbsSymbol;
Method	scala/reflect/generic/Symbols$AbsSymbol.newAbstractType:(Ljava/lang/Object;Ljava/lang/Object;)Lscala/reflect/generic/Symbols$AbsSymbol;
Asciz	PickledFlags;
NameAndType	PickledFlags:()J
Method	scala/reflect/generic/Flags$.PickledFlags:()J
Asciz	flags_$eq;
Asciz	(J)V;
NameAndType	flags_$eq:(J)V
Method	scala/reflect/generic/Symbols$AbsSymbol.flags_$eq:(J)V
Asciz	privateWithin_$eq;
NameAndType	privateWithin_$eq:(Lscala/reflect/generic/Symbols$AbsSymbol;)V
Method	scala/reflect/generic/Symbols$AbsSymbol.privateWithin_$eq:(Lscala/reflect/generic/Symbols$AbsSymbol;)V
long	805306368l;
Asciz	hasFlag;
Asciz	(J)Z;
NameAndType	hasFlag:(J)Z
Method	scala/reflect/generic/Symbols$AbsSymbol.hasFlag:(J)Z
Asciz	scala/reflect/generic/UnPickler$Scan$$anonfun$readSymbol$3;
class	scala/reflect/generic/UnPickler$Scan$$anonfun$readSymbol$3
Asciz	(Lscala/reflect/generic/UnPickler$Scan;Lscala/runtime/ObjectRef;)V;
NameAndType	"<init>":(Lscala/reflect/generic/UnPickler$Scan;Lscala/runtime/ObjectRef;)V
Method	scala/reflect/generic/UnPickler$Scan$$anonfun$readSymbol$3."<init>":(Lscala/reflect/generic/UnPickler$Scan;Lscala/runtime/ObjectRef;)V
long	268435456l;
Asciz	newLazyTypeRefAndAlias;
Asciz	(II)Lscala/reflect/generic/Types$AbsType;;
NameAndType	newLazyTypeRefAndAlias:(II)Lscala/reflect/generic/Types$AbsType;
Method	scala/reflect/generic/UnPickler$Scan.newLazyTypeRefAndAlias:(II)Lscala/reflect/generic/Types$AbsType;
Asciz	info_$eq;
NameAndType	info_$eq:(Lscala/reflect/generic/Types$AbsType;)V
Method	scala/reflect/generic/Symbols$AbsSymbol.info_$eq:(Lscala/reflect/generic/Types$AbsType;)V
Asciz	isClass;
NameAndType	isClass:()Z
Method	scala/reflect/generic/Symbols$AbsSymbol.isClass:()Z
Asciz	isModuleClass;
NameAndType	isModuleClass:()Z
Method	scala/reflect/generic/Symbols$AbsSymbol.isModuleClass:()Z
Asciz	isRefinementClass;
NameAndType	isRefinementClass:()Z
Method	scala/reflect/generic/Symbols$AbsSymbol.isRefinementClass:()Z
Asciz	isTypeParameter;
NameAndType	isTypeParameter:()Z
Method	scala/reflect/generic/Symbols$AbsSymbol.isTypeParameter:()Z
Asciz	isExistentiallyBound;
NameAndType	isExistentiallyBound:()Z
Method	scala/reflect/generic/Symbols$AbsSymbol.isExistentiallyBound:()Z
NameAndType	symScope:(Lscala/reflect/generic/Symbols$AbsSymbol;)Lscala/reflect/generic/Scopes$AbsScope;
Method	scala/reflect/generic/UnPickler$Scan.symScope:(Lscala/reflect/generic/Symbols$AbsSymbol;)Lscala/reflect/generic/Scopes$AbsScope;
Asciz	enter;
Asciz	(Lscala/reflect/generic/Symbols$AbsSymbol;)Lscala/reflect/generic/Symbols$AbsSymbol;;
NameAndType	enter:(Lscala/reflect/generic/Symbols$AbsSymbol;)Lscala/reflect/generic/Symbols$AbsSymbol;
Method	scala/reflect/generic/Scopes$AbsScope.enter:(Lscala/reflect/generic/Symbols$AbsSymbol;)Lscala/reflect/generic/Symbols$AbsSymbol;
Asciz	scala/runtime/BoxedUnit;
class	scala/runtime/BoxedUnit
Asciz	UNIT;
Asciz	Lscala/runtime/BoxedUnit;;
NameAndType	UNIT:Lscala/runtime/BoxedUnit;
Field	scala/runtime/BoxedUnit.UNIT:Lscala/runtime/BoxedUnit;
Asciz	scala/reflect/generic/StandardDefinitions;
class	scala/reflect/generic/StandardDefinitions
Asciz	definitions;
Asciz	()Lscala/reflect/generic/StandardDefinitions$AbsDefinitions;;
NameAndType	definitions:()Lscala/reflect/generic/StandardDefinitions$AbsDefinitions;
InterfaceMethod	scala/reflect/generic/StandardDefinitions.definitions:()Lscala/reflect/generic/StandardDefinitions$AbsDefinitions;
Asciz	scala/reflect/generic/StandardDefinitions$AbsDefinitions;
class	scala/reflect/generic/StandardDefinitions$AbsDefinitions
Asciz	RootClass;
NameAndType	RootClass:()Lscala/reflect/generic/Symbols$AbsSymbol;
Method	scala/reflect/generic/StandardDefinitions$AbsDefinitions.RootClass:()Lscala/reflect/generic/Symbols$AbsSymbol;
Asciz	fromName$1;
Asciz	(Ljava/lang/Object;ILscala/reflect/generic/Symbols$AbsSymbol;)Lscala/reflect/generic/Symbols$AbsSymbol;;
NameAndType	fromName$1:(Ljava/lang/Object;ILscala/reflect/generic/Symbols$AbsSymbol;)Lscala/reflect/generic/Symbols$AbsSymbol;
Method	scala/reflect/generic/UnPickler$Scan.fromName$1:(Ljava/lang/Object;ILscala/reflect/generic/Symbols$AbsSymbol;)Lscala/reflect/generic/Symbols$AbsSymbol;
Asciz	expandedName$default$3;
NameAndType	expandedName$default$3:()Ljava/lang/String;
Method	scala/reflect/generic/StdNames$StandardNames.expandedName$default$3:()Ljava/lang/String;
Asciz	expandedName;
Asciz	(Ljava/lang/Object;Lscala/reflect/generic/Symbols$AbsSymbol;Ljava/lang/String;)Ljava/lang/Object;;
NameAndType	expandedName:(Ljava/lang/Object;Lscala/reflect/generic/Symbols$AbsSymbol;Ljava/lang/String;)Ljava/lang/Object;
Method	scala/reflect/generic/StdNames$StandardNames.expandedName:(Ljava/lang/Object;Lscala/reflect/generic/Symbols$AbsSymbol;Ljava/lang/String;)Ljava/lang/Object;
Asciz	isOverloaded;
NameAndType	isOverloaded:()Z
Method	scala/reflect/generic/Symbols$AbsSymbol.isOverloaded:()Z
Asciz	errorMissingRequirement;
Asciz	(Ljava/lang/Object;Lscala/reflect/generic/Symbols$AbsSymbol;)Lscala/runtime/Nothing$;;
NameAndType	errorMissingRequirement:(Ljava/lang/Object;Lscala/reflect/generic/Symbols$AbsSymbol;)Lscala/runtime/Nothing$;
Method	scala/reflect/generic/UnPickler$Scan.errorMissingRequirement:(Ljava/lang/Object;Lscala/reflect/generic/Symbols$AbsSymbol;)Lscala/runtime/Nothing$;
Asciz	tag$1;
Asciz	end;
Asciz	sym$1;
Asciz	Lscala/runtime/ObjectRef;;
Asciz	temp7;
Asciz	owner$1;
Asciz	defaultGetter;
Asciz	nameref;
Asciz	flags;
Asciz	J;
Asciz	privateWithin;
Asciz	inforef;
Asciz	temp6;
Asciz	clazz;
Asciz	m;
Asciz	bad symbol tag: ;
String	bad symbol tag: 
Asciz	readType;
Asciz	()Lscala/reflect/generic/Types$AbsType;;
Asciz	noSuchTypeTag;
NameAndType	noSuchTypeTag:(II)Lscala/reflect/generic/Types$AbsType;
Method	scala/reflect/generic/UnPickler$Scan.noSuchTypeTag:(II)Lscala/reflect/generic/Types$AbsType;
Asciz	readTypeRef;
NameAndType	readTypeRef:()Lscala/reflect/generic/Types$AbsType;
Method	scala/reflect/generic/UnPickler$Scan.readTypeRef:()Lscala/reflect/generic/Types$AbsType;
Asciz	scala/reflect/generic/Types;
class	scala/reflect/generic/Types
Asciz	ExistentialType;
Asciz	()Lscala/reflect/generic/Types$ExistentialTypeExtractor;;
NameAndType	ExistentialType:()Lscala/reflect/generic/Types$ExistentialTypeExtractor;
InterfaceMethod	scala/reflect/generic/Types.ExistentialType:()Lscala/reflect/generic/Types$ExistentialTypeExtractor;
Asciz	scala/reflect/generic/UnPickler$Scan$$anonfun$readType$3;
class	scala/reflect/generic/UnPickler$Scan$$anonfun$readType$3
Method	scala/reflect/generic/UnPickler$Scan$$anonfun$readType$3."<init>":(Lscala/reflect/generic/UnPickler$Scan;)V
Asciz	(ILscala/Function0;)Lscala/collection/immutable/List;;
NameAndType	until:(ILscala/Function0;)Lscala/collection/immutable/List;
Method	scala/reflect/generic/UnPickler$Scan.until:(ILscala/Function0;)Lscala/collection/immutable/List;
Asciz	scala/reflect/generic/Types$ExistentialTypeExtractor;
class	scala/reflect/generic/Types$ExistentialTypeExtractor
Asciz	(Lscala/collection/immutable/List;Lscala/reflect/generic/Types$AbsType;)Lscala/reflect/generic/Types$AbsType;;
NameAndType	apply:(Lscala/collection/immutable/List;Lscala/reflect/generic/Types$AbsType;)Lscala/reflect/generic/Types$AbsType;
Method	scala/reflect/generic/Types$ExistentialTypeExtractor.apply:(Lscala/collection/immutable/List;Lscala/reflect/generic/Types$AbsType;)Lscala/reflect/generic/Types$AbsType;
Asciz	SuperType;
Asciz	()Lscala/reflect/generic/Types$SuperTypeExtractor;;
NameAndType	SuperType:()Lscala/reflect/generic/Types$SuperTypeExtractor;
InterfaceMethod	scala/reflect/generic/Types.SuperType:()Lscala/reflect/generic/Types$SuperTypeExtractor;
Asciz	scala/reflect/generic/Types$SuperTypeExtractor;
class	scala/reflect/generic/Types$SuperTypeExtractor
Asciz	(Lscala/reflect/generic/Types$AbsType;Lscala/reflect/generic/Types$AbsType;)Lscala/reflect/generic/Types$AbsType;;
NameAndType	apply:(Lscala/reflect/generic/Types$AbsType;Lscala/reflect/generic/Types$AbsType;)Lscala/reflect/generic/Types$AbsType;
Method	scala/reflect/generic/Types$SuperTypeExtractor.apply:(Lscala/reflect/generic/Types$AbsType;Lscala/reflect/generic/Types$AbsType;)Lscala/reflect/generic/Types$AbsType;
Asciz	scala/reflect/generic/UnPickler$Scan$$anonfun$6;
class	scala/reflect/generic/UnPickler$Scan$$anonfun$6
Method	scala/reflect/generic/UnPickler$Scan$$anonfun$6."<init>":(Lscala/reflect/generic/UnPickler$Scan;)V
Asciz	scala/reflect/generic/UnPickler$Scan$$anonfun$7;
class	scala/reflect/generic/UnPickler$Scan$$anonfun$7
Method	scala/reflect/generic/UnPickler$Scan$$anonfun$7."<init>":(Lscala/reflect/generic/UnPickler$Scan;)V
Asciz	scala/reflect/generic/UnPickler$Scan$$anonfun$8;
class	scala/reflect/generic/UnPickler$Scan$$anonfun$8
Method	scala/reflect/generic/UnPickler$Scan$$anonfun$8."<init>":(Lscala/reflect/generic/UnPickler$Scan;)V
Asciz	AnnotatedType;
Asciz	()Lscala/reflect/generic/Types$AnnotatedTypeExtractor;;
NameAndType	AnnotatedType:()Lscala/reflect/generic/Types$AnnotatedTypeExtractor;
InterfaceMethod	scala/reflect/generic/Types.AnnotatedType:()Lscala/reflect/generic/Types$AnnotatedTypeExtractor;
Asciz	scala/reflect/generic/Types$AnnotatedTypeExtractor;
class	scala/reflect/generic/Types$AnnotatedTypeExtractor
Asciz	(Lscala/collection/immutable/List;Lscala/reflect/generic/Types$AbsType;Lscala/reflect/generic/Symbols$AbsSymbol;)Lscala/reflect/generic/Types$AbsType;;
NameAndType	apply:(Lscala/collection/immutable/List;Lscala/reflect/generic/Types$AbsType;Lscala/reflect/generic/Symbols$AbsSymbol;)Lscala/reflect/generic/Types$AbsType;
Method	scala/reflect/generic/Types$AnnotatedTypeExtractor.apply:(Lscala/collection/immutable/List;Lscala/reflect/generic/Types$AbsType;Lscala/reflect/generic/Symbols$AbsSymbol;)Lscala/reflect/generic/Types$AbsType;
Asciz	scala/reflect/generic/UnPickler$Scan$$anonfun$5;
class	scala/reflect/generic/UnPickler$Scan$$anonfun$5
Method	scala/reflect/generic/UnPickler$Scan$$anonfun$5."<init>":(Lscala/reflect/generic/UnPickler$Scan;)V
Asciz	PolyType;
Asciz	()Lscala/reflect/generic/Types$PolyTypeExtractor;;
NameAndType	PolyType:()Lscala/reflect/generic/Types$PolyTypeExtractor;
InterfaceMethod	scala/reflect/generic/Types.PolyType:()Lscala/reflect/generic/Types$PolyTypeExtractor;
Asciz	scala/reflect/generic/Types$PolyTypeExtractor;
class	scala/reflect/generic/Types$PolyTypeExtractor
Method	scala/reflect/generic/Types$PolyTypeExtractor.apply:(Lscala/collection/immutable/List;Lscala/reflect/generic/Types$AbsType;)Lscala/reflect/generic/Types$AbsType;
Asciz	scala/reflect/generic/UnPickler$Scan$$anonfun$4;
class	scala/reflect/generic/UnPickler$Scan$$anonfun$4
Method	scala/reflect/generic/UnPickler$Scan$$anonfun$4."<init>":(Lscala/reflect/generic/UnPickler$Scan;)V
Asciz	scala/collection/SeqLike;
class	scala/collection/SeqLike
Asciz	contains;
NameAndType	contains:(Ljava/lang/Object;)Z
InterfaceMethod	scala/collection/SeqLike.contains:(Ljava/lang/Object;)Z
Asciz	NoType;
NameAndType	NoType:()Lscala/reflect/generic/Types$AbsType;
InterfaceMethod	scala/reflect/generic/Types.NoType:()Lscala/reflect/generic/Types$AbsType;
Asciz	MethodType;
Asciz	()Lscala/reflect/generic/Types$MethodTypeExtractor;;
NameAndType	MethodType:()Lscala/reflect/generic/Types$MethodTypeExtractor;
InterfaceMethod	scala/reflect/generic/Types.MethodType:()Lscala/reflect/generic/Types$MethodTypeExtractor;
Asciz	scala/reflect/generic/Types$MethodTypeExtractor;
class	scala/reflect/generic/Types$MethodTypeExtractor
Method	scala/reflect/generic/Types$MethodTypeExtractor.apply:(Lscala/collection/immutable/List;Lscala/reflect/generic/Types$AbsType;)Lscala/reflect/generic/Types$AbsType;
Asciz	ClassInfoType;
Asciz	()Lscala/reflect/generic/Types$ClassInfoTypeExtractor;;
NameAndType	ClassInfoType:()Lscala/reflect/generic/Types$ClassInfoTypeExtractor;
InterfaceMethod	scala/reflect/generic/Types.ClassInfoType:()Lscala/reflect/generic/Types$ClassInfoTypeExtractor;
Asciz	scala/reflect/generic/UnPickler$Scan$$anonfun$readType$2;
class	scala/reflect/generic/UnPickler$Scan$$anonfun$readType$2
Method	scala/reflect/generic/UnPickler$Scan$$anonfun$readType$2."<init>":(Lscala/reflect/generic/UnPickler$Scan;)V
Asciz	scala/reflect/generic/Types$ClassInfoTypeExtractor;
class	scala/reflect/generic/Types$ClassInfoTypeExtractor
Asciz	(Lscala/collection/immutable/List;Lscala/reflect/generic/Scopes$AbsScope;Lscala/reflect/generic/Symbols$AbsSymbol;)Lscala/reflect/generic/Types$AbsType;;
NameAndType	apply:(Lscala/collection/immutable/List;Lscala/reflect/generic/Scopes$AbsScope;Lscala/reflect/generic/Symbols$AbsSymbol;)Lscala/reflect/generic/Types$AbsType;
Method	scala/reflect/generic/Types$ClassInfoTypeExtractor.apply:(Lscala/collection/immutable/List;Lscala/reflect/generic/Scopes$AbsScope;Lscala/reflect/generic/Symbols$AbsSymbol;)Lscala/reflect/generic/Types$AbsType;
Asciz	RefinedType;
Asciz	()Lscala/reflect/generic/Types$RefinedTypeExtractor;;
NameAndType	RefinedType:()Lscala/reflect/generic/Types$RefinedTypeExtractor;
InterfaceMethod	scala/reflect/generic/Types.RefinedType:()Lscala/reflect/generic/Types$RefinedTypeExtractor;
Asciz	scala/reflect/generic/UnPickler$Scan$$anonfun$readType$1;
class	scala/reflect/generic/UnPickler$Scan$$anonfun$readType$1
Method	scala/reflect/generic/UnPickler$Scan$$anonfun$readType$1."<init>":(Lscala/reflect/generic/UnPickler$Scan;)V
Asciz	scala/reflect/generic/Types$RefinedTypeExtractor;
class	scala/reflect/generic/Types$RefinedTypeExtractor
Method	scala/reflect/generic/Types$RefinedTypeExtractor.apply:(Lscala/collection/immutable/List;Lscala/reflect/generic/Scopes$AbsScope;Lscala/reflect/generic/Symbols$AbsSymbol;)Lscala/reflect/generic/Types$AbsType;
Asciz	TypeBounds;
Asciz	()Lscala/reflect/generic/Types$TypeBoundsExtractor;;
NameAndType	TypeBounds:()Lscala/reflect/generic/Types$TypeBoundsExtractor;
InterfaceMethod	scala/reflect/generic/Types.TypeBounds:()Lscala/reflect/generic/Types$TypeBoundsExtractor;
Asciz	scala/reflect/generic/Types$TypeBoundsExtractor;
class	scala/reflect/generic/Types$TypeBoundsExtractor
Method	scala/reflect/generic/Types$TypeBoundsExtractor.apply:(Lscala/reflect/generic/Types$AbsType;Lscala/reflect/generic/Types$AbsType;)Lscala/reflect/generic/Types$AbsType;
Asciz	scala/reflect/generic/UnPickler$Scan$$anonfun$3;
class	scala/reflect/generic/UnPickler$Scan$$anonfun$3
Method	scala/reflect/generic/UnPickler$Scan$$anonfun$3."<init>":(Lscala/reflect/generic/UnPickler$Scan;)V
Asciz	TypeRef;
Asciz	()Lscala/reflect/generic/Types$TypeRefExtractor;;
NameAndType	TypeRef:()Lscala/reflect/generic/Types$TypeRefExtractor;
InterfaceMethod	scala/reflect/generic/Types.TypeRef:()Lscala/reflect/generic/Types$TypeRefExtractor;
Asciz	scala/reflect/generic/Types$TypeRefExtractor;
class	scala/reflect/generic/Types$TypeRefExtractor
Asciz	(Lscala/reflect/generic/Types$AbsType;Lscala/reflect/generic/Symbols$AbsSymbol;Lscala/collection/immutable/List;)Lscala/reflect/generic/Types$AbsType;;
NameAndType	apply:(Lscala/reflect/generic/Types$AbsType;Lscala/reflect/generic/Symbols$AbsSymbol;Lscala/collection/immutable/List;)Lscala/reflect/generic/Types$AbsType;
Method	scala/reflect/generic/Types$TypeRefExtractor.apply:(Lscala/reflect/generic/Types$AbsType;Lscala/reflect/generic/Symbols$AbsSymbol;Lscala/collection/immutable/List;)Lscala/reflect/generic/Types$AbsType;
Asciz	ConstantType;
Asciz	()Lscala/reflect/generic/Types$ConstantTypeExtractor;;
NameAndType	ConstantType:()Lscala/reflect/generic/Types$ConstantTypeExtractor;
InterfaceMethod	scala/reflect/generic/Types.ConstantType:()Lscala/reflect/generic/Types$ConstantTypeExtractor;
Asciz	readConstantRef;
Asciz	()Lscala/reflect/generic/Constants$Constant;;
NameAndType	readConstantRef:()Lscala/reflect/generic/Constants$Constant;
Method	scala/reflect/generic/UnPickler$Scan.readConstantRef:()Lscala/reflect/generic/Constants$Constant;
Asciz	scala/reflect/generic/Types$ConstantTypeExtractor;
class	scala/reflect/generic/Types$ConstantTypeExtractor
Asciz	(Lscala/reflect/generic/Constants$Constant;)Lscala/reflect/generic/Types$AbsType;;
NameAndType	apply:(Lscala/reflect/generic/Constants$Constant;)Lscala/reflect/generic/Types$AbsType;
Method	scala/reflect/generic/Types$ConstantTypeExtractor.apply:(Lscala/reflect/generic/Constants$Constant;)Lscala/reflect/generic/Types$AbsType;
Asciz	SingleType;
Asciz	()Lscala/reflect/generic/Types$SingleTypeExtractor;;
NameAndType	SingleType:()Lscala/reflect/generic/Types$SingleTypeExtractor;
InterfaceMethod	scala/reflect/generic/Types.SingleType:()Lscala/reflect/generic/Types$SingleTypeExtractor;
Asciz	scala/reflect/generic/Types$SingleTypeExtractor;
class	scala/reflect/generic/Types$SingleTypeExtractor
Asciz	(Lscala/reflect/generic/Types$AbsType;Lscala/reflect/generic/Symbols$AbsSymbol;)Lscala/reflect/generic/Types$AbsType;;
NameAndType	apply:(Lscala/reflect/generic/Types$AbsType;Lscala/reflect/generic/Symbols$AbsSymbol;)Lscala/reflect/generic/Types$AbsType;
Method	scala/reflect/generic/Types$SingleTypeExtractor.apply:(Lscala/reflect/generic/Types$AbsType;Lscala/reflect/generic/Symbols$AbsSymbol;)Lscala/reflect/generic/Types$AbsType;
Asciz	ThisType;
Asciz	()Lscala/reflect/generic/Types$ThisTypeExtractor;;
NameAndType	ThisType:()Lscala/reflect/generic/Types$ThisTypeExtractor;
InterfaceMethod	scala/reflect/generic/Types.ThisType:()Lscala/reflect/generic/Types$ThisTypeExtractor;
Asciz	scala/reflect/generic/Types$ThisTypeExtractor;
class	scala/reflect/generic/Types$ThisTypeExtractor
Asciz	(Lscala/reflect/generic/Symbols$AbsSymbol;)Lscala/reflect/generic/Types$AbsType;;
NameAndType	apply:(Lscala/reflect/generic/Symbols$AbsSymbol;)Lscala/reflect/generic/Types$AbsType;
Method	scala/reflect/generic/Types$ThisTypeExtractor.apply:(Lscala/reflect/generic/Symbols$AbsSymbol;)Lscala/reflect/generic/Types$AbsType;
Asciz	NoPrefix;
NameAndType	NoPrefix:()Lscala/reflect/generic/Types$AbsType;
InterfaceMethod	scala/reflect/generic/Types.NoPrefix:()Lscala/reflect/generic/Types$AbsType;
Asciz	temp8;
Asciz	pre;
Asciz	Lscala/reflect/generic/Types$AbsType;;
Asciz	args;
Asciz	Lscala/collection/immutable/List;;
Asciz	restpe;
Asciz	params;
Asciz	typeParams;
Asciz	typeRef;
Asciz	selfsym;
Asciz	tp;
Asciz	annots;
Asciz	thistpe;
Asciz	supertpe;
Asciz	bad type tag: ;
String	bad type tag: 
Asciz	readConstant;
Asciz	noSuchConstantTag;
Asciz	(II)Lscala/reflect/generic/Constants$Constant;;
NameAndType	noSuchConstantTag:(II)Lscala/reflect/generic/Constants$Constant;
Method	scala/reflect/generic/UnPickler$Scan.noSuchConstantTag:(II)Lscala/reflect/generic/Constants$Constant;
Asciz	scala/reflect/generic/Constants$Constant;
class	scala/reflect/generic/Constants$Constant
Asciz	(Lscala/reflect/generic/Universe;Ljava/lang/Object;)V;
NameAndType	"<init>":(Lscala/reflect/generic/Universe;Ljava/lang/Object;)V
Method	scala/reflect/generic/Constants$Constant."<init>":(Lscala/reflect/generic/Universe;Ljava/lang/Object;)V
Method	java/lang/Object.toString:()Ljava/lang/String;
Asciz	readLong;
Asciz	(I)J;
NameAndType	readLong:(I)J
Method	scala/reflect/generic/UnPickler$Scan.readLong:(I)J
Asciz	java/lang/Double;
class	java/lang/Double
Asciz	longBitsToDouble;
Asciz	(J)D;
NameAndType	longBitsToDouble:(J)D
Method	java/lang/Double.longBitsToDouble:(J)D
Asciz	boxToDouble;
Asciz	(D)Ljava/lang/Double;;
NameAndType	boxToDouble:(D)Ljava/lang/Double;
Method	scala/runtime/BoxesRunTime.boxToDouble:(D)Ljava/lang/Double;
Asciz	java/lang/Float;
class	java/lang/Float
Asciz	intBitsToFloat;
Asciz	(I)F;
NameAndType	intBitsToFloat:(I)F
Method	java/lang/Float.intBitsToFloat:(I)F
Asciz	boxToFloat;
Asciz	(F)Ljava/lang/Float;;
NameAndType	boxToFloat:(F)Ljava/lang/Float;
Method	scala/runtime/BoxesRunTime.boxToFloat:(F)Ljava/lang/Float;
Asciz	boxToLong;
Asciz	(J)Ljava/lang/Long;;
NameAndType	boxToLong:(J)Ljava/lang/Long;
Method	scala/runtime/BoxesRunTime.boxToLong:(J)Ljava/lang/Long;
Asciz	boxToCharacter;
Asciz	(C)Ljava/lang/Character;;
NameAndType	boxToCharacter:(C)Ljava/lang/Character;
Method	scala/runtime/BoxesRunTime.boxToCharacter:(C)Ljava/lang/Character;
Asciz	boxToShort;
Asciz	(S)Ljava/lang/Short;;
NameAndType	boxToShort:(S)Ljava/lang/Short;
Method	scala/runtime/BoxesRunTime.boxToShort:(S)Ljava/lang/Short;
Asciz	boxToByte;
Asciz	(B)Ljava/lang/Byte;;
NameAndType	boxToByte:(B)Ljava/lang/Byte;
Method	scala/runtime/BoxesRunTime.boxToByte:(B)Ljava/lang/Byte;
Asciz	boxToBoolean;
Asciz	(Z)Ljava/lang/Boolean;;
NameAndType	boxToBoolean:(Z)Ljava/lang/Boolean;
Method	scala/runtime/BoxesRunTime.boxToBoolean:(Z)Ljava/lang/Boolean;
Asciz	temp9;
Asciz	bad constant tag: ;
String	bad constant tag: 
Asciz	readChildren;
Asciz	addChild;
NameAndType	addChild:(Lscala/reflect/generic/Symbols$AbsSymbol;)V
Method	scala/reflect/generic/Symbols$AbsSymbol.addChild:(Lscala/reflect/generic/Symbols$AbsSymbol;)V
Asciz	target;
Asciz	readAnnotArg;
Asciz	(I)Lscala/reflect/generic/Trees$Tree;;
int	49;
Asciz	scala/reflect/generic/UnPickler$Scan$$anonfun$readAnnotArg$1;
class	scala/reflect/generic/UnPickler$Scan$$anonfun$readAnnotArg$1
Method	scala/reflect/generic/UnPickler$Scan$$anonfun$readAnnotArg$1."<init>":(Lscala/reflect/generic/UnPickler$Scan;)V
Asciz	scala/reflect/generic/Trees$Tree;
class	scala/reflect/generic/Trees$Tree
Asciz	scala/reflect/generic/UnPickler$Scan$$anonfun$9;
class	scala/reflect/generic/UnPickler$Scan$$anonfun$9
Method	scala/reflect/generic/UnPickler$Scan$$anonfun$9."<init>":(Lscala/reflect/generic/UnPickler$Scan;)V
Asciz	scala/reflect/generic/Trees$Literal;
class	scala/reflect/generic/Trees$Literal
Asciz	(Lscala/reflect/generic/Universe;Lscala/reflect/generic/Constants$Constant;)V;
NameAndType	"<init>":(Lscala/reflect/generic/Universe;Lscala/reflect/generic/Constants$Constant;)V
Method	scala/reflect/generic/Trees$Literal."<init>":(Lscala/reflect/generic/Universe;Lscala/reflect/generic/Constants$Constant;)V
Asciz	tpe;
NameAndType	tpe:()Lscala/reflect/generic/Types$AbsType;
Method	scala/reflect/generic/Constants$Constant.tpe:()Lscala/reflect/generic/Types$AbsType;
Asciz	setType;
Asciz	(Lscala/reflect/generic/Types$AbsType;)Lscala/reflect/generic/Trees$Tree;;
NameAndType	setType:(Lscala/reflect/generic/Types$AbsType;)Lscala/reflect/generic/Trees$Tree;
Method	scala/reflect/generic/Trees$Literal.setType:(Lscala/reflect/generic/Types$AbsType;)Lscala/reflect/generic/Trees$Tree;
Asciz	const;
Asciz	Lscala/reflect/generic/Constants$Constant;;
Asciz	readClassfileAnnotArg;
Asciz	(I)Ljava/lang/Object;;
int	43;
Asciz	scala/reflect/generic/AnnotationInfos;
class	scala/reflect/generic/AnnotationInfos
Asciz	NestedAnnotArg;
Asciz	()Lscala/reflect/generic/AnnotationInfos$NestedAnnotArgExtractor;;
NameAndType	NestedAnnotArg:()Lscala/reflect/generic/AnnotationInfos$NestedAnnotArgExtractor;
InterfaceMethod	scala/reflect/generic/AnnotationInfos.NestedAnnotArg:()Lscala/reflect/generic/AnnotationInfos$NestedAnnotArgExtractor;
Asciz	scala/reflect/generic/UnPickler$Scan$$anonfun$readClassfileAnnotArg$1;
class	scala/reflect/generic/UnPickler$Scan$$anonfun$readClassfileAnnotArg$1
Method	scala/reflect/generic/UnPickler$Scan$$anonfun$readClassfileAnnotArg$1."<init>":(Lscala/reflect/generic/UnPickler$Scan;)V
Asciz	scala/reflect/generic/AnnotationInfos$NestedAnnotArgExtractor;
class	scala/reflect/generic/AnnotationInfos$NestedAnnotArgExtractor
NameAndType	apply:(Ljava/lang/Object;)Ljava/lang/Object;
Method	scala/reflect/generic/AnnotationInfos$NestedAnnotArgExtractor.apply:(Ljava/lang/Object;)Ljava/lang/Object;
int	44;
Asciz	scala/reflect/generic/UnPickler$Scan$$anonfun$readClassfileAnnotArg$2;
class	scala/reflect/generic/UnPickler$Scan$$anonfun$readClassfileAnnotArg$2
Method	scala/reflect/generic/UnPickler$Scan$$anonfun$readClassfileAnnotArg$2."<init>":(Lscala/reflect/generic/UnPickler$Scan;)V
Asciz	LiteralAnnotArg;
Asciz	()Lscala/reflect/generic/AnnotationInfos$LiteralAnnotArgExtractor;;
NameAndType	LiteralAnnotArg:()Lscala/reflect/generic/AnnotationInfos$LiteralAnnotArgExtractor;
InterfaceMethod	scala/reflect/generic/AnnotationInfos.LiteralAnnotArg:()Lscala/reflect/generic/AnnotationInfos$LiteralAnnotArgExtractor;
Asciz	scala/reflect/generic/UnPickler$Scan$$anonfun$readClassfileAnnotArg$3;
class	scala/reflect/generic/UnPickler$Scan$$anonfun$readClassfileAnnotArg$3
Method	scala/reflect/generic/UnPickler$Scan$$anonfun$readClassfileAnnotArg$3."<init>":(Lscala/reflect/generic/UnPickler$Scan;)V
Asciz	scala/reflect/generic/AnnotationInfos$LiteralAnnotArgExtractor;
class	scala/reflect/generic/AnnotationInfos$LiteralAnnotArgExtractor
Asciz	(Lscala/reflect/generic/Constants$Constant;)Ljava/lang/Object;;
NameAndType	apply:(Lscala/reflect/generic/Constants$Constant;)Ljava/lang/Object;
Method	scala/reflect/generic/AnnotationInfos$LiteralAnnotArgExtractor.apply:(Lscala/reflect/generic/Constants$Constant;)Ljava/lang/Object;
Asciz	temp10;
Asciz	readAnnotationInfo;
Asciz	scala/collection/mutable/ListBuffer;
class	scala/collection/mutable/ListBuffer
Method	scala/collection/mutable/ListBuffer."<init>":()V
NameAndType	isNameEntry:(I)Z
Method	scala/reflect/generic/UnPickler$Scan.isNameEntry:(I)Z
Asciz	scala/reflect/generic/UnPickler$Scan$$anonfun$10;
class	scala/reflect/generic/UnPickler$Scan$$anonfun$10
Method	scala/reflect/generic/UnPickler$Scan$$anonfun$10."<init>":(Lscala/reflect/generic/UnPickler$Scan;)V
NameAndType	readClassfileAnnotArg:(I)Ljava/lang/Object;
Method	scala/reflect/generic/UnPickler$Scan.readClassfileAnnotArg:(I)Ljava/lang/Object;
Asciz	scala/Tuple2;
class	scala/Tuple2
NameAndType	"<init>":(Ljava/lang/Object;Ljava/lang/Object;)V
Method	scala/Tuple2."<init>":(Ljava/lang/Object;Ljava/lang/Object;)V
Asciz	$plus$eq;
Asciz	(Ljava/lang/Object;)Lscala/collection/mutable/ListBuffer;;
NameAndType	$plus$eq:(Ljava/lang/Object;)Lscala/collection/mutable/ListBuffer;
Method	scala/collection/mutable/ListBuffer.$plus$eq:(Ljava/lang/Object;)Lscala/collection/mutable/ListBuffer;
NameAndType	readAnnotArg:(I)Lscala/reflect/generic/Trees$Tree;
Method	scala/reflect/generic/UnPickler$Scan.readAnnotArg:(I)Lscala/reflect/generic/Trees$Tree;
Asciz	AnnotationInfo;
Asciz	()Lscala/reflect/generic/AnnotationInfos$AnnotationInfoExtractor;;
NameAndType	AnnotationInfo:()Lscala/reflect/generic/AnnotationInfos$AnnotationInfoExtractor;
InterfaceMethod	scala/reflect/generic/AnnotationInfos.AnnotationInfo:()Lscala/reflect/generic/AnnotationInfos$AnnotationInfoExtractor;
Asciz	toList;
Asciz	()Lscala/collection/immutable/List;;
NameAndType	toList:()Lscala/collection/immutable/List;
Method	scala/collection/mutable/ListBuffer.toList:()Lscala/collection/immutable/List;
Asciz	scala/reflect/generic/AnnotationInfos$AnnotationInfoExtractor;
class	scala/reflect/generic/AnnotationInfos$AnnotationInfoExtractor
Asciz	(Lscala/reflect/generic/Types$AbsType;Lscala/collection/immutable/List;Lscala/collection/immutable/List;)Ljava/lang/Object;;
NameAndType	apply:(Lscala/reflect/generic/Types$AbsType;Lscala/collection/immutable/List;Lscala/collection/immutable/List;)Ljava/lang/Object;
Method	scala/reflect/generic/AnnotationInfos$AnnotationInfoExtractor.apply:(Lscala/reflect/generic/Types$AbsType;Lscala/collection/immutable/List;Lscala/collection/immutable/List;)Ljava/lang/Object;
Asciz	atp;
Asciz	Lscala/collection/mutable/ListBuffer;;
Asciz	assocs;
Asciz	argref;
Asciz	arg;
Asciz	readSymbolAnnotation;
Asciz	symbol annotation expected (;
String	symbol annotation expected (
Asciz	);
String	)
NameAndType	readAnnotationInfo:(I)Ljava/lang/Object;
Method	scala/reflect/generic/UnPickler$Scan.readAnnotationInfo:(I)Ljava/lang/Object;
Asciz	addAnnotation;
NameAndType	addAnnotation:(Ljava/lang/Object;)V
Method	scala/reflect/generic/Symbols$AbsSymbol.addAnnotation:(Ljava/lang/Object;)V
Asciz	readAnnotation;
Asciz	annotation expected (;
String	annotation expected (
Asciz	readTree;
Asciz	()Lscala/reflect/generic/Trees$Tree;;
Asciz	tree expected (;
String	tree expected (
Asciz	noSuchTreeTag;
Asciz	(II)Lscala/runtime/Nothing$;;
NameAndType	noSuchTreeTag:(II)Lscala/runtime/Nothing$;
Method	scala/reflect/generic/UnPickler$Scan.noSuchTreeTag:(II)Lscala/runtime/Nothing$;
Asciz	readTreeRef;
NameAndType	readTreeRef:()Lscala/reflect/generic/Trees$Tree;
Method	scala/reflect/generic/UnPickler$Scan.readTreeRef:()Lscala/reflect/generic/Trees$Tree;
Asciz	scala/reflect/generic/UnPickler$Scan$$anonfun$32;
class	scala/reflect/generic/UnPickler$Scan$$anonfun$32
Method	scala/reflect/generic/UnPickler$Scan$$anonfun$32."<init>":(Lscala/reflect/generic/UnPickler$Scan;)V
Asciz	scala/reflect/generic/Trees$ExistentialTypeTree;
class	scala/reflect/generic/Trees$ExistentialTypeTree
Asciz	(Lscala/reflect/generic/Universe;Lscala/reflect/generic/Trees$Tree;Lscala/collection/immutable/List;)V;
NameAndType	"<init>":(Lscala/reflect/generic/Universe;Lscala/reflect/generic/Trees$Tree;Lscala/collection/immutable/List;)V
Method	scala/reflect/generic/Trees$ExistentialTypeTree."<init>":(Lscala/reflect/generic/Universe;Lscala/reflect/generic/Trees$Tree;Lscala/collection/immutable/List;)V
Asciz	scala/reflect/generic/Trees$TypeBoundsTree;
class	scala/reflect/generic/Trees$TypeBoundsTree
Asciz	(Lscala/reflect/generic/Universe;Lscala/reflect/generic/Trees$Tree;Lscala/reflect/generic/Trees$Tree;)V;
NameAndType	"<init>":(Lscala/reflect/generic/Universe;Lscala/reflect/generic/Trees$Tree;Lscala/reflect/generic/Trees$Tree;)V
Method	scala/reflect/generic/Trees$TypeBoundsTree."<init>":(Lscala/reflect/generic/Universe;Lscala/reflect/generic/Trees$Tree;Lscala/reflect/generic/Trees$Tree;)V
Asciz	scala/reflect/generic/UnPickler$Scan$$anonfun$31;
class	scala/reflect/generic/UnPickler$Scan$$anonfun$31
Method	scala/reflect/generic/UnPickler$Scan$$anonfun$31."<init>":(Lscala/reflect/generic/UnPickler$Scan;)V
Asciz	scala/reflect/generic/Trees$AppliedTypeTree;
class	scala/reflect/generic/Trees$AppliedTypeTree
Method	scala/reflect/generic/Trees$AppliedTypeTree."<init>":(Lscala/reflect/generic/Universe;Lscala/reflect/generic/Trees$Tree;Lscala/collection/immutable/List;)V
Asciz	scala/reflect/generic/Trees$CompoundTypeTree;
class	scala/reflect/generic/Trees$CompoundTypeTree
Asciz	readTemplateRef;
Asciz	()Lscala/reflect/generic/Trees$Template;;
NameAndType	readTemplateRef:()Lscala/reflect/generic/Trees$Template;
Method	scala/reflect/generic/UnPickler$Scan.readTemplateRef:()Lscala/reflect/generic/Trees$Template;
Asciz	(Lscala/reflect/generic/Universe;Lscala/reflect/generic/Trees$Template;)V;
NameAndType	"<init>":(Lscala/reflect/generic/Universe;Lscala/reflect/generic/Trees$Template;)V
Method	scala/reflect/generic/Trees$CompoundTypeTree."<init>":(Lscala/reflect/generic/Universe;Lscala/reflect/generic/Trees$Template;)V
Asciz	scala/reflect/generic/Trees$SelectFromTypeTree;
class	scala/reflect/generic/Trees$SelectFromTypeTree
Asciz	(Lscala/reflect/generic/Universe;Lscala/reflect/generic/Trees$Tree;Ljava/lang/Object;)V;
NameAndType	"<init>":(Lscala/reflect/generic/Universe;Lscala/reflect/generic/Trees$Tree;Ljava/lang/Object;)V
Method	scala/reflect/generic/Trees$SelectFromTypeTree."<init>":(Lscala/reflect/generic/Universe;Lscala/reflect/generic/Trees$Tree;Ljava/lang/Object;)V
Asciz	scala/reflect/generic/Trees$SingletonTypeTree;
class	scala/reflect/generic/Trees$SingletonTypeTree
Asciz	(Lscala/reflect/generic/Universe;Lscala/reflect/generic/Trees$Tree;)V;
NameAndType	"<init>":(Lscala/reflect/generic/Universe;Lscala/reflect/generic/Trees$Tree;)V
Method	scala/reflect/generic/Trees$SingletonTypeTree."<init>":(Lscala/reflect/generic/Universe;Lscala/reflect/generic/Trees$Tree;)V
Asciz	scala/reflect/generic/Trees$Annotated;
class	scala/reflect/generic/Trees$Annotated
Method	scala/reflect/generic/Trees$Annotated."<init>":(Lscala/reflect/generic/Universe;Lscala/reflect/generic/Trees$Tree;Lscala/reflect/generic/Trees$Tree;)V
Asciz	scala/reflect/generic/Trees;
class	scala/reflect/generic/Trees
Asciz	TypeTree;
Asciz	()Lscala/reflect/generic/Trees$TypeTreeExtractor;;
NameAndType	TypeTree:()Lscala/reflect/generic/Trees$TypeTreeExtractor;
InterfaceMethod	scala/reflect/generic/Trees.TypeTree:()Lscala/reflect/generic/Trees$TypeTreeExtractor;
Asciz	scala/reflect/generic/Trees$TypeTreeExtractor;
class	scala/reflect/generic/Trees$TypeTreeExtractor
Asciz	()Lscala/reflect/generic/Trees$AbsTypeTree;;
NameAndType	apply:()Lscala/reflect/generic/Trees$AbsTypeTree;
Method	scala/reflect/generic/Trees$TypeTreeExtractor.apply:()Lscala/reflect/generic/Trees$AbsTypeTree;
Asciz	setSymName$1;
Asciz	(Lscala/runtime/ObjectRef;Lscala/runtime/ObjectRef;)V;
NameAndType	setSymName$1:(Lscala/runtime/ObjectRef;Lscala/runtime/ObjectRef;)V
Method	scala/reflect/generic/UnPickler$Scan.setSymName$1:(Lscala/runtime/ObjectRef;Lscala/runtime/ObjectRef;)V
Asciz	scala/reflect/generic/Trees$Ident;
class	scala/reflect/generic/Trees$Ident
Method	scala/reflect/generic/Trees$Ident."<init>":(Lscala/reflect/generic/Universe;Ljava/lang/Object;)V
Asciz	setSym$1;
Asciz	(Lscala/runtime/ObjectRef;)V;
NameAndType	setSym$1:(Lscala/runtime/ObjectRef;)V
Method	scala/reflect/generic/UnPickler$Scan.setSym$1:(Lscala/runtime/ObjectRef;)V
Asciz	scala/reflect/generic/Trees$Select;
class	scala/reflect/generic/Trees$Select
Method	scala/reflect/generic/Trees$Select."<init>":(Lscala/reflect/generic/Universe;Lscala/reflect/generic/Trees$Tree;Ljava/lang/Object;)V
Asciz	scala/reflect/generic/Trees$This;
class	scala/reflect/generic/Trees$This
Method	scala/reflect/generic/Trees$This."<init>":(Lscala/reflect/generic/Universe;Ljava/lang/Object;)V
Asciz	scala/reflect/generic/Trees$Super;
class	scala/reflect/generic/Trees$Super
Asciz	(Lscala/reflect/generic/Universe;Ljava/lang/Object;Ljava/lang/Object;)V;
NameAndType	"<init>":(Lscala/reflect/generic/Universe;Ljava/lang/Object;Ljava/lang/Object;)V
Method	scala/reflect/generic/Trees$Super."<init>":(Lscala/reflect/generic/Universe;Ljava/lang/Object;Ljava/lang/Object;)V
Asciz	scala/reflect/generic/UnPickler$Scan$$anonfun$30;
class	scala/reflect/generic/UnPickler$Scan$$anonfun$30
Method	scala/reflect/generic/UnPickler$Scan$$anonfun$30."<init>":(Lscala/reflect/generic/UnPickler$Scan;)V
Asciz	scala/reflect/generic/Trees$ApplyDynamic;
class	scala/reflect/generic/Trees$ApplyDynamic
Method	scala/reflect/generic/Trees$ApplyDynamic."<init>":(Lscala/reflect/generic/Universe;Lscala/reflect/generic/Trees$Tree;Lscala/collection/immutable/List;)V
Asciz	scala/reflect/generic/UnPickler$Scan$$anonfun$28;
class	scala/reflect/generic/UnPickler$Scan$$anonfun$28
Method	scala/reflect/generic/UnPickler$Scan$$anonfun$28."<init>":(Lscala/reflect/generic/UnPickler$Scan;)V
Asciz	symbol;
NameAndType	symbol:()Lscala/reflect/generic/Symbols$AbsSymbol;
Method	scala/reflect/generic/Trees$Tree.symbol:()Lscala/reflect/generic/Symbols$AbsSymbol;
Asciz	info;
NameAndType	info:()Lscala/reflect/generic/Types$AbsType;
Method	scala/reflect/generic/Symbols$AbsSymbol.info:()Lscala/reflect/generic/Types$AbsType;
Method	scala/reflect/generic/Trees$Tree.setType:(Lscala/reflect/generic/Types$AbsType;)Lscala/reflect/generic/Trees$Tree;
Asciz	scala/reflect/generic/UnPickler$Scan$$anonfun$29;
class	scala/reflect/generic/UnPickler$Scan$$anonfun$29
Method	scala/reflect/generic/UnPickler$Scan$$anonfun$29."<init>":(Lscala/reflect/generic/UnPickler$Scan;)V
Asciz	scala/collection/immutable/List$;
class	scala/collection/immutable/List$
Asciz	Lscala/collection/immutable/List$;;
NameAndType	MODULE$:Lscala/collection/immutable/List$;
Field	scala/collection/immutable/List$.MODULE$:Lscala/collection/immutable/List$;
Asciz	canBuildFrom;
Asciz	()Lscala/collection/generic/CanBuildFrom;;
NameAndType	canBuildFrom:()Lscala/collection/generic/CanBuildFrom;
Method	scala/collection/immutable/List$.canBuildFrom:()Lscala/collection/generic/CanBuildFrom;
Asciz	scala/collection/TraversableLike;
class	scala/collection/TraversableLike
Asciz	map;
Asciz	(Lscala/Function1;Lscala/collection/generic/CanBuildFrom;)Ljava/lang/Object;;
NameAndType	map:(Lscala/Function1;Lscala/collection/generic/CanBuildFrom;)Ljava/lang/Object;
InterfaceMethod	scala/collection/TraversableLike.map:(Lscala/Function1;Lscala/collection/generic/CanBuildFrom;)Ljava/lang/Object;
Asciz	scala/collection/immutable/List;
class	scala/collection/immutable/List
Asciz	inferMethodAlternative;
Asciz	(Lscala/reflect/generic/Trees$Tree;Lscala/collection/immutable/List;Lscala/reflect/generic/Types$AbsType;)V;
NameAndType	inferMethodAlternative:(Lscala/reflect/generic/Trees$Tree;Lscala/collection/immutable/List;Lscala/reflect/generic/Types$AbsType;)V
Method	scala/reflect/generic/UnPickler$Scan.inferMethodAlternative:(Lscala/reflect/generic/Trees$Tree;Lscala/collection/immutable/List;Lscala/reflect/generic/Types$AbsType;)V
Asciz	scala/reflect/generic/Trees$Apply;
class	scala/reflect/generic/Trees$Apply
Method	scala/reflect/generic/Trees$Apply."<init>":(Lscala/reflect/generic/Universe;Lscala/reflect/generic/Trees$Tree;Lscala/collection/immutable/List;)V
Asciz	scala/reflect/generic/UnPickler$Scan$$anonfun$27;
class	scala/reflect/generic/UnPickler$Scan$$anonfun$27
Method	scala/reflect/generic/UnPickler$Scan$$anonfun$27."<init>":(Lscala/reflect/generic/UnPickler$Scan;)V
Asciz	scala/reflect/generic/Trees$TypeApply;
class	scala/reflect/generic/Trees$TypeApply
Method	scala/reflect/generic/Trees$TypeApply."<init>":(Lscala/reflect/generic/Universe;Lscala/reflect/generic/Trees$Tree;Lscala/collection/immutable/List;)V
Asciz	scala/reflect/generic/Trees$Typed;
class	scala/reflect/generic/Trees$Typed
Method	scala/reflect/generic/Trees$Typed."<init>":(Lscala/reflect/generic/Universe;Lscala/reflect/generic/Trees$Tree;Lscala/reflect/generic/Trees$Tree;)V
Asciz	scala/reflect/generic/Trees$New;
class	scala/reflect/generic/Trees$New
Method	scala/reflect/generic/Trees$New."<init>":(Lscala/reflect/generic/Universe;Lscala/reflect/generic/Trees$Tree;)V
Asciz	scala/reflect/generic/Trees$Throw;
class	scala/reflect/generic/Trees$Throw
Method	scala/reflect/generic/Trees$Throw."<init>":(Lscala/reflect/generic/Universe;Lscala/reflect/generic/Trees$Tree;)V
Asciz	scala/reflect/generic/UnPickler$Scan$$anonfun$26;
class	scala/reflect/generic/UnPickler$Scan$$anonfun$26
Method	scala/reflect/generic/UnPickler$Scan$$anonfun$26."<init>":(Lscala/reflect/generic/UnPickler$Scan;)V
Asciz	scala/reflect/generic/Trees$Try;
class	scala/reflect/generic/Trees$Try
Asciz	(Lscala/reflect/generic/Universe;Lscala/reflect/generic/Trees$Tree;Lscala/collection/immutable/List;Lscala/reflect/generic/Trees$Tree;)V;
NameAndType	"<init>":(Lscala/reflect/generic/Universe;Lscala/reflect/generic/Trees$Tree;Lscala/collection/immutable/List;Lscala/reflect/generic/Trees$Tree;)V
Method	scala/reflect/generic/Trees$Try."<init>":(Lscala/reflect/generic/Universe;Lscala/reflect/generic/Trees$Tree;Lscala/collection/immutable/List;Lscala/reflect/generic/Trees$Tree;)V
Asciz	scala/reflect/generic/Trees$Return;
class	scala/reflect/generic/Trees$Return
Method	scala/reflect/generic/Trees$Return."<init>":(Lscala/reflect/generic/Universe;Lscala/reflect/generic/Trees$Tree;)V
Asciz	scala/reflect/generic/UnPickler$Scan$$anonfun$25;
class	scala/reflect/generic/UnPickler$Scan$$anonfun$25
Method	scala/reflect/generic/UnPickler$Scan$$anonfun$25."<init>":(Lscala/reflect/generic/UnPickler$Scan;)V
Asciz	scala/reflect/generic/Trees$Match;
class	scala/reflect/generic/Trees$Match
Method	scala/reflect/generic/Trees$Match."<init>":(Lscala/reflect/generic/Universe;Lscala/reflect/generic/Trees$Tree;Lscala/collection/immutable/List;)V
Asciz	scala/reflect/generic/Trees$If;
class	scala/reflect/generic/Trees$If
Asciz	(Lscala/reflect/generic/Universe;Lscala/reflect/generic/Trees$Tree;Lscala/reflect/generic/Trees$Tree;Lscala/reflect/generic/Trees$Tree;)V;
NameAndType	"<init>":(Lscala/reflect/generic/Universe;Lscala/reflect/generic/Trees$Tree;Lscala/reflect/generic/Trees$Tree;Lscala/reflect/generic/Trees$Tree;)V
Method	scala/reflect/generic/Trees$If."<init>":(Lscala/reflect/generic/Universe;Lscala/reflect/generic/Trees$Tree;Lscala/reflect/generic/Trees$Tree;Lscala/reflect/generic/Trees$Tree;)V
Asciz	scala/reflect/generic/Trees$Assign;
class	scala/reflect/generic/Trees$Assign
Method	scala/reflect/generic/Trees$Assign."<init>":(Lscala/reflect/generic/Universe;Lscala/reflect/generic/Trees$Tree;Lscala/reflect/generic/Trees$Tree;)V
Asciz	scala/reflect/generic/UnPickler$Scan$$anonfun$24;
class	scala/reflect/generic/UnPickler$Scan$$anonfun$24
Method	scala/reflect/generic/UnPickler$Scan$$anonfun$24."<init>":(Lscala/reflect/generic/UnPickler$Scan;)V
Asciz	scala/reflect/generic/Trees$Function;
class	scala/reflect/generic/Trees$Function
Asciz	(Lscala/reflect/generic/Universe;Lscala/collection/immutable/List;Lscala/reflect/generic/Trees$Tree;)V;
NameAndType	"<init>":(Lscala/reflect/generic/Universe;Lscala/collection/immutable/List;Lscala/reflect/generic/Trees$Tree;)V
Method	scala/reflect/generic/Trees$Function."<init>":(Lscala/reflect/generic/Universe;Lscala/collection/immutable/List;Lscala/reflect/generic/Trees$Tree;)V
Asciz	scala/reflect/generic/UnPickler$Scan$$anonfun$23;
class	scala/reflect/generic/UnPickler$Scan$$anonfun$23
Method	scala/reflect/generic/UnPickler$Scan$$anonfun$23."<init>":(Lscala/reflect/generic/UnPickler$Scan;)V
Asciz	scala/reflect/generic/Trees$ArrayValue;
class	scala/reflect/generic/Trees$ArrayValue
Method	scala/reflect/generic/Trees$ArrayValue."<init>":(Lscala/reflect/generic/Universe;Lscala/reflect/generic/Trees$Tree;Lscala/collection/immutable/List;)V
Asciz	scala/reflect/generic/UnPickler$Scan$$anonfun$22;
class	scala/reflect/generic/UnPickler$Scan$$anonfun$22
Method	scala/reflect/generic/UnPickler$Scan$$anonfun$22."<init>":(Lscala/reflect/generic/UnPickler$Scan;)V
Asciz	scala/reflect/generic/Trees$UnApply;
class	scala/reflect/generic/Trees$UnApply
Method	scala/reflect/generic/Trees$UnApply."<init>":(Lscala/reflect/generic/Universe;Lscala/reflect/generic/Trees$Tree;Lscala/collection/immutable/List;)V
Asciz	scala/reflect/generic/Trees$Bind;
class	scala/reflect/generic/Trees$Bind
Asciz	(Lscala/reflect/generic/Universe;Ljava/lang/Object;Lscala/reflect/generic/Trees$Tree;)V;
NameAndType	"<init>":(Lscala/reflect/generic/Universe;Ljava/lang/Object;Lscala/reflect/generic/Trees$Tree;)V
Method	scala/reflect/generic/Trees$Bind."<init>":(Lscala/reflect/generic/Universe;Ljava/lang/Object;Lscala/reflect/generic/Trees$Tree;)V
Asciz	scala/reflect/generic/Trees$Star;
class	scala/reflect/generic/Trees$Star
Method	scala/reflect/generic/Trees$Star."<init>":(Lscala/reflect/generic/Universe;Lscala/reflect/generic/Trees$Tree;)V
Asciz	scala/reflect/generic/Trees$Alternative;
class	scala/reflect/generic/Trees$Alternative
Asciz	scala/reflect/generic/UnPickler$Scan$$anonfun$21;
class	scala/reflect/generic/UnPickler$Scan$$anonfun$21
Method	scala/reflect/generic/UnPickler$Scan$$anonfun$21."<init>":(Lscala/reflect/generic/UnPickler$Scan;)V
Asciz	(Lscala/reflect/generic/Universe;Lscala/collection/immutable/List;)V;
NameAndType	"<init>":(Lscala/reflect/generic/Universe;Lscala/collection/immutable/List;)V
Method	scala/reflect/generic/Trees$Alternative."<init>":(Lscala/reflect/generic/Universe;Lscala/collection/immutable/List;)V
Asciz	scala/reflect/generic/Trees$CaseDef;
class	scala/reflect/generic/Trees$CaseDef
Method	scala/reflect/generic/Trees$CaseDef."<init>":(Lscala/reflect/generic/Universe;Lscala/reflect/generic/Trees$Tree;Lscala/reflect/generic/Trees$Tree;Lscala/reflect/generic/Trees$Tree;)V
Asciz	scala/reflect/generic/UnPickler$Scan$$anonfun$20;
class	scala/reflect/generic/UnPickler$Scan$$anonfun$20
Method	scala/reflect/generic/UnPickler$Scan$$anonfun$20."<init>":(Lscala/reflect/generic/UnPickler$Scan;)V
Asciz	scala/reflect/generic/Trees$Block;
class	scala/reflect/generic/Trees$Block
Method	scala/reflect/generic/Trees$Block."<init>":(Lscala/reflect/generic/Universe;Lscala/collection/immutable/List;Lscala/reflect/generic/Trees$Tree;)V
Asciz	scala/reflect/generic/UnPickler$Scan$$anonfun$18;
class	scala/reflect/generic/UnPickler$Scan$$anonfun$18
Method	scala/reflect/generic/UnPickler$Scan$$anonfun$18."<init>":(Lscala/reflect/generic/UnPickler$Scan;)V
Asciz	times;
NameAndType	times:(ILscala/Function0;)Lscala/collection/immutable/List;
Method	scala/reflect/generic/UnPickler$Scan.times:(ILscala/Function0;)Lscala/collection/immutable/List;
Asciz	readValDefRef;
Asciz	()Lscala/reflect/generic/Trees$ValDef;;
NameAndType	readValDefRef:()Lscala/reflect/generic/Trees$ValDef;
Method	scala/reflect/generic/UnPickler$Scan.readValDefRef:()Lscala/reflect/generic/Trees$ValDef;
Asciz	scala/reflect/generic/UnPickler$Scan$$anonfun$19;
class	scala/reflect/generic/UnPickler$Scan$$anonfun$19
Method	scala/reflect/generic/UnPickler$Scan$$anonfun$19."<init>":(Lscala/reflect/generic/UnPickler$Scan;)V
Asciz	scala/reflect/generic/Trees$Template;
class	scala/reflect/generic/Trees$Template
Asciz	(Lscala/reflect/generic/Universe;Lscala/collection/immutable/List;Lscala/reflect/generic/Trees$ValDef;Lscala/collection/immutable/List;)V;
NameAndType	"<init>":(Lscala/reflect/generic/Universe;Lscala/collection/immutable/List;Lscala/reflect/generic/Trees$ValDef;Lscala/collection/immutable/List;)V
Method	scala/reflect/generic/Trees$Template."<init>":(Lscala/reflect/generic/Universe;Lscala/collection/immutable/List;Lscala/reflect/generic/Trees$ValDef;Lscala/collection/immutable/List;)V
Asciz	scala/reflect/generic/UnPickler$Scan$$anonfun$17;
class	scala/reflect/generic/UnPickler$Scan$$anonfun$17
Method	scala/reflect/generic/UnPickler$Scan$$anonfun$17."<init>":(Lscala/reflect/generic/UnPickler$Scan;)V
Asciz	scala/reflect/generic/Trees$Import;
class	scala/reflect/generic/Trees$Import
Method	scala/reflect/generic/Trees$Import."<init>":(Lscala/reflect/generic/Universe;Lscala/reflect/generic/Trees$Tree;Lscala/collection/immutable/List;)V
Asciz	scala/reflect/generic/UnPickler$Scan$$anonfun$16;
class	scala/reflect/generic/UnPickler$Scan$$anonfun$16
Method	scala/reflect/generic/UnPickler$Scan$$anonfun$16."<init>":(Lscala/reflect/generic/UnPickler$Scan;)V
Asciz	scala/reflect/generic/Trees$LabelDef;
class	scala/reflect/generic/Trees$LabelDef
Asciz	(Lscala/reflect/generic/Universe;Ljava/lang/Object;Lscala/collection/immutable/List;Lscala/reflect/generic/Trees$Tree;)V;
NameAndType	"<init>":(Lscala/reflect/generic/Universe;Ljava/lang/Object;Lscala/collection/immutable/List;Lscala/reflect/generic/Trees$Tree;)V
Method	scala/reflect/generic/Trees$LabelDef."<init>":(Lscala/reflect/generic/Universe;Ljava/lang/Object;Lscala/collection/immutable/List;Lscala/reflect/generic/Trees$Tree;)V
Asciz	setSymModsName$1;
Asciz	(Lscala/runtime/ObjectRef;Lscala/runtime/ObjectRef;Lscala/runtime/ObjectRef;)V;
NameAndType	setSymModsName$1:(Lscala/runtime/ObjectRef;Lscala/runtime/ObjectRef;Lscala/runtime/ObjectRef;)V
Method	scala/reflect/generic/UnPickler$Scan.setSymModsName$1:(Lscala/runtime/ObjectRef;Lscala/runtime/ObjectRef;Lscala/runtime/ObjectRef;)V
Asciz	scala/reflect/generic/UnPickler$Scan$$anonfun$15;
class	scala/reflect/generic/UnPickler$Scan$$anonfun$15
Method	scala/reflect/generic/UnPickler$Scan$$anonfun$15."<init>":(Lscala/reflect/generic/UnPickler$Scan;)V
Asciz	scala/reflect/generic/Trees$TypeDef;
class	scala/reflect/generic/Trees$TypeDef
Asciz	scala/reflect/generic/Trees$Modifiers;
class	scala/reflect/generic/Trees$Modifiers
Asciz	(Lscala/reflect/generic/Universe;Lscala/reflect/generic/Trees$Modifiers;Ljava/lang/Object;Lscala/collection/immutable/List;Lscala/reflect/generic/Trees$Tree;)V;
NameAndType	"<init>":(Lscala/reflect/generic/Universe;Lscala/reflect/generic/Trees$Modifiers;Ljava/lang/Object;Lscala/collection/immutable/List;Lscala/reflect/generic/Trees$Tree;)V
Method	scala/reflect/generic/Trees$TypeDef."<init>":(Lscala/reflect/generic/Universe;Lscala/reflect/generic/Trees$Modifiers;Ljava/lang/Object;Lscala/collection/immutable/List;Lscala/reflect/generic/Trees$Tree;)V
Asciz	scala/reflect/generic/UnPickler$Scan$$anonfun$13;
class	scala/reflect/generic/UnPickler$Scan$$anonfun$13
Method	scala/reflect/generic/UnPickler$Scan$$anonfun$13."<init>":(Lscala/reflect/generic/UnPickler$Scan;)V
Asciz	scala/reflect/generic/UnPickler$Scan$$anonfun$14;
class	scala/reflect/generic/UnPickler$Scan$$anonfun$14
Method	scala/reflect/generic/UnPickler$Scan$$anonfun$14."<init>":(Lscala/reflect/generic/UnPickler$Scan;)V
Asciz	scala/reflect/generic/Trees$DefDef;
class	scala/reflect/generic/Trees$DefDef
Asciz	(Lscala/reflect/generic/Universe;Lscala/reflect/generic/Trees$Modifiers;Ljava/lang/Object;Lscala/collection/immutable/List;Lscala/collection/immutable/List;Lscala/reflect/generic/Trees$Tree;Lscala/reflect/generic/Trees$Tree;)V;
NameAndType	"<init>":(Lscala/reflect/generic/Universe;Lscala/reflect/generic/Trees$Modifiers;Ljava/lang/Object;Lscala/collection/immutable/List;Lscala/collection/immutable/List;Lscala/reflect/generic/Trees$Tree;Lscala/reflect/generic/Trees$Tree;)V
Method	scala/reflect/generic/Trees$DefDef."<init>":(Lscala/reflect/generic/Universe;Lscala/reflect/generic/Trees$Modifiers;Ljava/lang/Object;Lscala/collection/immutable/List;Lscala/collection/immutable/List;Lscala/reflect/generic/Trees$Tree;Lscala/reflect/generic/Trees$Tree;)V
Asciz	scala/reflect/generic/Trees$ValDef;
class	scala/reflect/generic/Trees$ValDef
Asciz	(Lscala/reflect/generic/Universe;Lscala/reflect/generic/Trees$Modifiers;Ljava/lang/Object;Lscala/reflect/generic/Trees$Tree;Lscala/reflect/generic/Trees$Tree;)V;
NameAndType	"<init>":(Lscala/reflect/generic/Universe;Lscala/reflect/generic/Trees$Modifiers;Ljava/lang/Object;Lscala/reflect/generic/Trees$Tree;Lscala/reflect/generic/Trees$Tree;)V
Method	scala/reflect/generic/Trees$ValDef."<init>":(Lscala/reflect/generic/Universe;Lscala/reflect/generic/Trees$Modifiers;Ljava/lang/Object;Lscala/reflect/generic/Trees$Tree;Lscala/reflect/generic/Trees$Tree;)V
Asciz	scala/reflect/generic/Trees$ModuleDef;
class	scala/reflect/generic/Trees$ModuleDef
Asciz	(Lscala/reflect/generic/Universe;Lscala/reflect/generic/Trees$Modifiers;Ljava/lang/Object;Lscala/reflect/generic/Trees$Template;)V;
NameAndType	"<init>":(Lscala/reflect/generic/Universe;Lscala/reflect/generic/Trees$Modifiers;Ljava/lang/Object;Lscala/reflect/generic/Trees$Template;)V
Method	scala/reflect/generic/Trees$ModuleDef."<init>":(Lscala/reflect/generic/Universe;Lscala/reflect/generic/Trees$Modifiers;Ljava/lang/Object;Lscala/reflect/generic/Trees$Template;)V
Asciz	scala/reflect/generic/UnPickler$Scan$$anonfun$12;
class	scala/reflect/generic/UnPickler$Scan$$anonfun$12
Method	scala/reflect/generic/UnPickler$Scan$$anonfun$12."<init>":(Lscala/reflect/generic/UnPickler$Scan;)V
Asciz	scala/reflect/generic/Trees$ClassDef;
class	scala/reflect/generic/Trees$ClassDef
Asciz	(Lscala/reflect/generic/Universe;Lscala/reflect/generic/Trees$Modifiers;Ljava/lang/Object;Lscala/collection/immutable/List;Lscala/reflect/generic/Trees$Template;)V;
NameAndType	"<init>":(Lscala/reflect/generic/Universe;Lscala/reflect/generic/Trees$Modifiers;Ljava/lang/Object;Lscala/collection/immutable/List;Lscala/reflect/generic/Trees$Template;)V
Method	scala/reflect/generic/Trees$ClassDef."<init>":(Lscala/reflect/generic/Universe;Lscala/reflect/generic/Trees$Modifiers;Ljava/lang/Object;Lscala/collection/immutable/List;Lscala/reflect/generic/Trees$Template;)V
Asciz	scala/reflect/generic/Trees$RefTree;
class	scala/reflect/generic/Trees$RefTree
Asciz	scala/reflect/generic/UnPickler$Scan$$anonfun$11;
class	scala/reflect/generic/UnPickler$Scan$$anonfun$11
Method	scala/reflect/generic/UnPickler$Scan$$anonfun$11."<init>":(Lscala/reflect/generic/UnPickler$Scan;)V
Asciz	scala/reflect/generic/Trees$PackageDef;
class	scala/reflect/generic/Trees$PackageDef
Asciz	(Lscala/reflect/generic/Universe;Lscala/reflect/generic/Trees$RefTree;Lscala/collection/immutable/List;)V;
NameAndType	"<init>":(Lscala/reflect/generic/Universe;Lscala/reflect/generic/Trees$RefTree;Lscala/collection/immutable/List;)V
Method	scala/reflect/generic/Trees$PackageDef."<init>":(Lscala/reflect/generic/Universe;Lscala/reflect/generic/Trees$RefTree;Lscala/collection/immutable/List;)V
Asciz	EmptyTree;
Asciz	()Lscala/reflect/generic/Trees$EmptyTree$;;
NameAndType	EmptyTree:()Lscala/reflect/generic/Trees$EmptyTree$;
InterfaceMethod	scala/reflect/generic/Trees.EmptyTree:()Lscala/reflect/generic/Trees$EmptyTree$;
Asciz	setSymbol;
Asciz	(Lscala/reflect/generic/Symbols$AbsSymbol;)Lscala/reflect/generic/Trees$Tree;;
NameAndType	setSymbol:(Lscala/reflect/generic/Symbols$AbsSymbol;)Lscala/reflect/generic/Trees$Tree;
Method	scala/reflect/generic/Trees$Tree.setSymbol:(Lscala/reflect/generic/Symbols$AbsSymbol;)Lscala/reflect/generic/Trees$Tree;
Asciz	outerTag;
Asciz	symbol$1;
Asciz	mods$1;
Asciz	name$1;
Asciz	t;
Asciz	Lscala/reflect/generic/Trees$Tree;;
Asciz	temp11;
Asciz	pid;
Asciz	Lscala/reflect/generic/Trees$RefTree;;
Asciz	stats;
Asciz	impl;
Asciz	Lscala/reflect/generic/Trees$Template;;
Asciz	tparams;
Asciz	tpt;
Asciz	rhs;
Asciz	vparamss;
Asciz	expr;
Asciz	selectors;
Asciz	parents;
Asciz	self;
Asciz	Lscala/reflect/generic/Trees$ValDef;;
Asciz	body;
Asciz	pat;
Asciz	guard;
Asciz	fun;
Asciz	elemtpt;
Asciz	trees;
Asciz	vparams;
Asciz	lhs;
Asciz	cond;
Asciz	thenp;
Asciz	elsep;
Asciz	selector;
Asciz	cases;
Asciz	block;
Asciz	finalizer;
Asciz	catches;
Asciz	qual;
Asciz	mix;
Asciz	qualifier;
Asciz	annot;
Asciz	lo;
Asciz	hi;
Asciz	whereClauses;
Asciz	unknown tree type (;
String	unknown tree type (
Asciz	readModifiers;
Asciz	()Lscala/reflect/generic/Trees$Modifiers;;
int	50;
Asciz	expected a modifiers tag (;
String	expected a modifiers tag (
int	32;
Asciz	scala/collection/immutable/Nil$;
class	scala/collection/immutable/Nil$
Asciz	Lscala/collection/immutable/Nil$;;
NameAndType	MODULE$:Lscala/collection/immutable/Nil$;
Field	scala/collection/immutable/Nil$.MODULE$:Lscala/collection/immutable/Nil$;
Asciz	Map;
Asciz	()Lscala/collection/immutable/Map$;;
NameAndType	Map:()Lscala/collection/immutable/Map$;
Method	scala/Predef$.Map:()Lscala/collection/immutable/Map$;
Asciz	scala/collection/immutable/Map$;
class	scala/collection/immutable/Map$
Asciz	empty;
Asciz	()Lscala/collection/immutable/Map;;
NameAndType	empty:()Lscala/collection/immutable/Map;
Method	scala/collection/immutable/Map$.empty:()Lscala/collection/immutable/Map;
Asciz	(Lscala/reflect/generic/Universe;JLjava/lang/Object;Lscala/collection/immutable/List;Lscala/collection/immutable/Map;)V;
NameAndType	"<init>":(Lscala/reflect/generic/Universe;JLjava/lang/Object;Lscala/collection/immutable/List;Lscala/collection/immutable/Map;)V
Method	scala/reflect/generic/Trees$Modifiers."<init>":(Lscala/reflect/generic/Universe;JLjava/lang/Object;Lscala/collection/immutable/List;Lscala/collection/immutable/Map;)V
Asciz	pflagsHi;
Asciz	pflagsLo;
Asciz	pflags;
Asciz	scala/reflect/generic/UnPickler$Scan$$anonfun$readNameRef$1;
class	scala/reflect/generic/UnPickler$Scan$$anonfun$readNameRef$1
Method	scala/reflect/generic/UnPickler$Scan$$anonfun$readNameRef$1."<init>":(Lscala/reflect/generic/UnPickler$Scan;)V
Asciz	scala/reflect/generic/UnPickler$Scan$$anonfun$readSymbolRef$1;
class	scala/reflect/generic/UnPickler$Scan$$anonfun$readSymbolRef$1
Method	scala/reflect/generic/UnPickler$Scan$$anonfun$readSymbolRef$1."<init>":(Lscala/reflect/generic/UnPickler$Scan;)V
Asciz	scala/reflect/generic/UnPickler$Scan$$anonfun$readTypeRef$1;
class	scala/reflect/generic/UnPickler$Scan$$anonfun$readTypeRef$1
Method	scala/reflect/generic/UnPickler$Scan$$anonfun$readTypeRef$1."<init>":(Lscala/reflect/generic/UnPickler$Scan;)V
Asciz	scala/reflect/generic/UnPickler$Scan$$anonfun$readConstantRef$1;
class	scala/reflect/generic/UnPickler$Scan$$anonfun$readConstantRef$1
Method	scala/reflect/generic/UnPickler$Scan$$anonfun$readConstantRef$1."<init>":(Lscala/reflect/generic/UnPickler$Scan;)V
Asciz	readAnnotationRef;
Asciz	scala/reflect/generic/UnPickler$Scan$$anonfun$readAnnotationRef$1;
class	scala/reflect/generic/UnPickler$Scan$$anonfun$readAnnotationRef$1
Method	scala/reflect/generic/UnPickler$Scan$$anonfun$readAnnotationRef$1."<init>":(Lscala/reflect/generic/UnPickler$Scan;)V
Asciz	readModifiersRef;
Asciz	scala/reflect/generic/UnPickler$Scan$$anonfun$readModifiersRef$1;
class	scala/reflect/generic/UnPickler$Scan$$anonfun$readModifiersRef$1
Method	scala/reflect/generic/UnPickler$Scan$$anonfun$readModifiersRef$1."<init>":(Lscala/reflect/generic/UnPickler$Scan;)V
Asciz	scala/reflect/generic/UnPickler$Scan$$anonfun$readTreeRef$1;
class	scala/reflect/generic/UnPickler$Scan$$anonfun$readTreeRef$1
Method	scala/reflect/generic/UnPickler$Scan$$anonfun$readTreeRef$1."<init>":(Lscala/reflect/generic/UnPickler$Scan;)V
Asciz	expected a template (;
String	expected a template (
Asciz	temp12;
Asciz	readCaseDefRef;
Asciz	()Lscala/reflect/generic/Trees$CaseDef;;
Asciz	expected a case def (;
String	expected a case def (
Asciz	temp17;
Asciz	expected a ValDef (;
String	expected a ValDef (
Asciz	temp22;
Asciz	readIdentRef;
Asciz	()Lscala/reflect/generic/Trees$Ident;;
Asciz	expected an Ident (;
String	expected an Ident (
Asciz	temp28;
Asciz	readTypeDefRef;
Asciz	()Lscala/reflect/generic/Trees$TypeDef;;
Asciz	expected an TypeDef (;
String	expected an TypeDef (
Asciz	temp31;
Asciz	java/lang/RuntimeException;
class	java/lang/RuntimeException
Asciz	malformed Scala signature of ;
String	malformed Scala signature of 
Asciz	 at ;
String	 at 
Asciz	; ;
String	; 
Method	java/lang/RuntimeException."<init>":(Ljava/lang/String;)V
Asciz	msg;
NameAndType	debug:()Z
Method	scala/reflect/generic/UnPickler$Scan.debug:()Z
Asciz	class file needed by ;
String	class file needed by 
Asciz	 is missing.\n;
String	 is missing.\n
Asciz	reference ;
String	reference 
Asciz	scala/reflect/NameTransformer$;
class	scala/reflect/NameTransformer$
Asciz	Lscala/reflect/NameTransformer$;;
NameAndType	MODULE$:Lscala/reflect/NameTransformer$;
Field	scala/reflect/NameTransformer$.MODULE$:Lscala/reflect/NameTransformer$;
Asciz	decode;
Asciz	(Ljava/lang/String;)Ljava/lang/String;;
NameAndType	decode:(Ljava/lang/String;)Ljava/lang/String;
Method	scala/reflect/NameTransformer$.decode:(Ljava/lang/String;)Ljava/lang/String;
Asciz	 of ;
String	 of 
Method	scala/reflect/generic/Symbols$AbsSymbol.tpe:()Lscala/reflect/generic/Types$AbsType;
Asciz	 refers to nonexisting symbol.;
String	 refers to nonexisting symbol.
NameAndType	errorMissingRequirement:(Ljava/lang/String;)Lscala/runtime/Nothing$;
Method	scala/reflect/generic/UnPickler$Scan.errorMissingRequirement:(Ljava/lang/String;)Lscala/runtime/Nothing$;
Asciz	(Lscala/reflect/generic/Trees$Tree;Lscala/collection/immutable/List<Lscala/reflect/generic/Types$AbsType;>;Lscala/reflect/generic/Types$AbsType;)V;
NameAndType	$outer:Lscala/reflect/generic/UnPickler;
Field	scala/reflect/generic/UnPickler$Scan.$outer:Lscala/reflect/generic/UnPickler;
Asciz	mkTermName;
NameAndType	mkTermName:(Ljava/lang/Object;)Ljava/lang/Object;
InterfaceMethod	scala/reflect/generic/Names.mkTermName:(Ljava/lang/Object;)Ljava/lang/Object;
Asciz	ROOT;
NameAndType	ROOT:()Ljava/lang/Object;
Method	scala/reflect/generic/StdNames$StandardNames.ROOT:()Ljava/lang/Object;
Asciz	ROOTPKG;
NameAndType	ROOTPKG:()Ljava/lang/Object;
Method	scala/reflect/generic/StdNames$StandardNames.ROOTPKG:()Ljava/lang/Object;
Asciz	RootPackage;
NameAndType	RootPackage:()Lscala/reflect/generic/Symbols$AbsSymbol;
Method	scala/reflect/generic/StandardDefinitions$AbsDefinitions.RootPackage:()Lscala/reflect/generic/Symbols$AbsSymbol;
int	9;
Asciz	decl;
Asciz	(Ljava/lang/Object;)Lscala/reflect/generic/Symbols$AbsSymbol;;
NameAndType	decl:(Ljava/lang/Object;)Lscala/reflect/generic/Symbols$AbsSymbol;
Method	scala/reflect/generic/Types$AbsType.decl:(Ljava/lang/Object;)Lscala/reflect/generic/Symbols$AbsSymbol;
NameAndType	readModifiersRef:()Lscala/reflect/generic/Trees$Modifiers;
Method	scala/reflect/generic/UnPickler$Scan.readModifiersRef:()Lscala/reflect/generic/Trees$Modifiers;
Asciz	(Lscala/reflect/generic/UnPickler;[BILscala/reflect/generic/Symbols$AbsSymbol;Lscala/reflect/generic/Symbols$AbsSymbol;Ljava/lang/String;)V;
Asciz	java/lang/NullPointerException;
class	java/lang/NullPointerException
Method	java/lang/NullPointerException."<init>":()V
Asciz	scala/reflect/generic/PickleBuffer;
class	scala/reflect/generic/PickleBuffer
Asciz	([BII)V;
NameAndType	"<init>":([BII)V
Method	scala/reflect/generic/PickleBuffer."<init>":([BII)V
NameAndType	checkVersion:()V
Method	scala/reflect/generic/UnPickler$Scan.checkVersion:()V
Asciz	createIndex;
NameAndType	createIndex:()[I
Method	scala/reflect/generic/UnPickler$Scan.createIndex:()[I
Method	scala/collection/mutable/HashMap."<init>":()V
Asciz	offset;
Asciz	Scala;
Asciz	InnerClasses;
Asciz	If;
Asciz	Try;
Asciz	New;
Asciz	Star;
Asciz	Bind;
Asciz	This;
Asciz	Tree;
Asciz	Block;
Asciz	Match;
Asciz	Throw;
Asciz	Typed;
Asciz	Apply;
Asciz	Super;
Asciz	Ident;
Asciz	scala/collection/immutable/Range;
class	scala/collection/immutable/Range
Asciz	ByOne;
Asciz	DefDef;
Asciz	Import;
Asciz	Assign;
Asciz	Return;
Asciz	Select;
Asciz	ValDef;
Asciz	TypeDef;
Asciz	CaseDef;
Asciz	UnApply;
Asciz	RefTree;
Asciz	Literal;
Asciz	AbsType;
Asciz	ClassDef;
Asciz	LabelDef;
Asciz	Function;
Asciz	Template;
Asciz	Scan;
Asciz	ModuleDef;
Asciz	Modifiers;
Asciz	TypeApply;
Asciz	Annotated;
Asciz	AbsScope;
Asciz	PackageDef;
Asciz	ArrayValue;
Asciz	Alternative;
Asciz	scala/reflect/generic/Trees$AbsTypeTree;
class	scala/reflect/generic/Trees$AbsTypeTree
Asciz	AbsTypeTree;
Asciz	AbsSymbol;
Asciz	ApplyDynamic;
Asciz	scala/reflect/generic/Constants;
class	scala/reflect/generic/Constants
Asciz	Constant;
Asciz	TypeBoundsTree;
Asciz	AppliedTypeTree;
Asciz	CompoundTypeTree;
Asciz	TypeRefExtractor;
Asciz	StandardNames;
Asciz	TypeTreeExtractor;
Asciz	SingletonTypeTree;
Asciz	ThisTypeExtractor;
Asciz	PolyTypeExtractor;
Asciz	SelectFromTypeTree;
Asciz	SuperTypeExtractor;
Asciz	ExistentialTypeTree;
Asciz	$anonfun$9;
Asciz	SingleTypeExtractor;
Asciz	$anonfun$3;
Asciz	TypeBoundsExtractor;
Asciz	MethodTypeExtractor;
Asciz	$anonfun$4;
Asciz	$anonfun$5;
Asciz	$anonfun$8;
Asciz	$anonfun$7;
Asciz	$anonfun$6;
Asciz	$anonfun$2;
Asciz	$anonfun$1;
Asciz	$anonfun$11;
Asciz	$anonfun$12;
Asciz	$anonfun$14;
Asciz	$anonfun$13;
Asciz	$anonfun$15;
Asciz	$anonfun$16;
Asciz	$anonfun$17;
Asciz	$anonfun$19;
Asciz	$anonfun$18;
Asciz	$anonfun$20;
Asciz	$anonfun$21;
Asciz	$anonfun$22;
Asciz	$anonfun$23;
Asciz	$anonfun$24;
Asciz	$anonfun$25;
Asciz	$anonfun$26;
Asciz	$anonfun$27;
Asciz	$anonfun$29;
Asciz	$anonfun$28;
Asciz	$anonfun$30;
Asciz	$anonfun$31;
Asciz	$anonfun$32;
Asciz	$anonfun$10;
Asciz	RefinedTypeExtractor;
Asciz	ConstantTypeExtractor;
Asciz	ClassInfoTypeExtractor;
Asciz	AnnotatedTypeExtractor;
Asciz	$anonfun$at$1;
Asciz	$anonfun$run$1;
Asciz	ExistentialTypeExtractor;
Asciz	$anonfun$readType$1;
Asciz	$anonfun$readType$2;
Asciz	$anonfun$readType$3;
Asciz	AbsDefinitions;
Asciz	$anonfun$readSymbol$3;
Asciz	$anonfun$readSymbol$2;
Asciz	$anonfun$readSymbol$1;
Asciz	$anonfun$readTreeRef$1;
Asciz	$anonfun$readTypeRef$1;
Asciz	$anonfun$readNameRef$1;
Asciz	$anonfun$readAnnotArg$1;
Asciz	$anonfun$readSymbolRef$1;
Asciz	AnnotationInfoExtractor;
Asciz	NestedAnnotArgExtractor;
Asciz	LiteralAnnotArgExtractor;
Asciz	$anonfun$readConstantRef$1;
Asciz	$anonfun$readModifiersRef$1;
Asciz	$anonfun$readAnnotationRef$1;
Asciz	$anonfun$readClassfileAnnotArg$3;
Asciz	$anonfun$readClassfileAnnotArg$2;
Asciz	$anonfun$readClassfileAnnotArg$1;
Asciz	scala/ScalaObject;
class	scala/ScalaObject

{
public final scala.reflect.generic.UnPickler $outer;
  Signature: Lscala/reflect/generic/UnPickler;

private final scala.collection.mutable.HashMap symScopes;
  Signature: Lscala/collection/mutable/HashMap;
  Signature: length = 0x2
   00 07 

private final java.lang.Object[] scala$reflect$generic$UnPickler$Scan$$entries;
  Signature: [Ljava/lang/Object;

private final int[] index;
  Signature: [I

private final java.lang.String filename;
  Signature: Ljava/lang/String;

private final scala.reflect.generic.Symbols$AbsSymbol moduleRoot;
  Signature: Lscala/reflect/generic/Symbols$AbsSymbol;

private final scala.reflect.generic.Symbols$AbsSymbol classRoot;
  Signature: Lscala/reflect/generic/Symbols$AbsSymbol;

private final byte[] bytes;
  Signature: [B

public boolean debug();
  Signature: ()Z
  Code:
   Stack=1, Locals=1, Args_size=1
	iconst_0
	ireturn
  Labels:

private int[] index();
  Signature: ()[I
  Code:
   Stack=1, Locals=1, Args_size=1
	aload_0
	getfield	Field index:[I
	areturn
  Labels:

public final java.lang.Object[] scala$reflect$generic$UnPickler$Scan$$entries();
  Signature: ()[Ljava/lang/Object;
  Code:
   Stack=1, Locals=1, Args_size=1
	aload_0
	getfield	Field scala$reflect$generic$UnPickler$Scan$$entries:[Ljava/lang/Object;
	areturn
  Labels:

private scala.collection.mutable.HashMap symScopes();
  Signature: ()Lscala/collection/mutable/HashMap;
  Code:
   Stack=1, Locals=1, Args_size=1
	aload_0
	getfield	Field symScopes:Lscala/collection/mutable/HashMap;
	areturn
  Labels:
  Signature: length = 0x2
   00 23 

public void run();
  Signature: ()V
  Code:
   Stack=4, Locals=1, Args_size=1
	getstatic	Field scala/Predef$.MODULE$:Lscala/Predef$;
	iconst_0
	invokevirtual	Method scala/Predef$.intWrapper:(I)Lscala/runtime/RichInt;
	aload_0
	invokespecial	Method index:()[I
	arraylength
	invokevirtual	Method scala/runtime/RichInt.until:(I)Lscala/collection/immutable/Range$ByOne;
	new	class scala/reflect/generic/UnPickler$Scan$$anonfun$run$1
	dup
	aload_0
	invokespecial	Method scala/reflect/generic/UnPickler$Scan$$anonfun$run$1."<init>":(Lscala/reflect/generic/UnPickler$Scan;)V
	invokeinterface	InterfaceMethod scala/collection/immutable/Range$ByOne.foreach:(Lscala/Function1;)V
	return
  Labels:

private void checkVersion();
  Signature: ()V
  Code:
   Stack=4, Locals=3, Args_size=1
	aload_0
	invokevirtual	Method readNat:()I
	istore_1
	aload_0
	invokevirtual	Method readNat:()I
	istore_2
	iload_1
	getstatic	Field scala/reflect/generic/PickleFormat$.MODULE$:Lscala/reflect/generic/PickleFormat$;
	invokevirtual	Method scala/reflect/generic/PickleFormat$.MajorVersion:()I
	if_icmpne	l1 // new
	iload_2
	getstatic	Field scala/reflect/generic/PickleFormat$.MODULE$:Lscala/reflect/generic/PickleFormat$;
	invokevirtual	Method scala/reflect/generic/PickleFormat$.MinorVersion:()I
	if_icmple	l2 // return
l1	new	class java/io/IOException
	dup
	new	class scala/collection/mutable/StringBuilder
	dup
	invokespecial	Method scala/collection/mutable/StringBuilder."<init>":()V
	ldc	String Scala signature 
	invokevirtual	Method scala/collection/mutable/StringBuilder.append:(Ljava/lang/Object;)Lscala/collection/mutable/StringBuilder;
	aload_0
	getfield	Field classRoot:Lscala/reflect/generic/Symbols$AbsSymbol;
	invokevirtual	Method scala/reflect/generic/Symbols$AbsSymbol.decodedName:()Ljava/lang/String;
	invokevirtual	Method scala/collection/mutable/StringBuilder.append:(Ljava/lang/Object;)Lscala/collection/mutable/StringBuilder;
	ldc	String  has wrong version\n expected: 
	invokevirtual	Method scala/collection/mutable/StringBuilder.append:(Ljava/lang/Object;)Lscala/collection/mutable/StringBuilder;
	getstatic	Field scala/reflect/generic/PickleFormat$.MODULE$:Lscala/reflect/generic/PickleFormat$;
	invokevirtual	Method scala/reflect/generic/PickleFormat$.MajorVersion:()I
	invokestatic	Method scala/runtime/BoxesRunTime.boxToInteger:(I)Ljava/lang/Integer;
	invokevirtual	Method scala/collection/mutable/StringBuilder.append:(Ljava/lang/Object;)Lscala/collection/mutable/StringBuilder;
	ldc	String .
	invokevirtual	Method scala/collection/mutable/StringBuilder.append:(Ljava/lang/Object;)Lscala/collection/mutable/StringBuilder;
	getstatic	Field scala/reflect/generic/PickleFormat$.MODULE$:Lscala/reflect/generic/PickleFormat$;
	invokevirtual	Method scala/reflect/generic/PickleFormat$.MinorVersion:()I
	invokestatic	Method scala/runtime/BoxesRunTime.boxToInteger:(I)Ljava/lang/Integer;
	invokevirtual	Method scala/collection/mutable/StringBuilder.append:(Ljava/lang/Object;)Lscala/collection/mutable/StringBuilder;
	ldc	String \n found: 
	invokevirtual	Method scala/collection/mutable/StringBuilder.append:(Ljava/lang/Object;)Lscala/collection/mutable/StringBuilder;
	iload_1
	invokestatic	Method scala/runtime/BoxesRunTime.boxToInteger:(I)Ljava/lang/Integer;
	invokevirtual	Method scala/collection/mutable/StringBuilder.append:(Ljava/lang/Object;)Lscala/collection/mutable/StringBuilder;
	ldc	String .
	invokevirtual	Method scala/collection/mutable/StringBuilder.append:(Ljava/lang/Object;)Lscala/collection/mutable/StringBuilder;
	iload_2
	invokestatic	Method scala/runtime/BoxesRunTime.boxToInteger:(I)Ljava/lang/Integer;
	invokevirtual	Method scala/collection/mutable/StringBuilder.append:(Ljava/lang/Object;)Lscala/collection/mutable/StringBuilder;
	ldc	String  in 
	invokevirtual	Method scala/collection/mutable/StringBuilder.append:(Ljava/lang/Object;)Lscala/collection/mutable/StringBuilder;
	aload_0
	getfield	Field filename:Ljava/lang/String;
	invokevirtual	Method scala/collection/mutable/StringBuilder.append:(Ljava/lang/Object;)Lscala/collection/mutable/StringBuilder;
	invokevirtual	Method scala/collection/mutable/StringBuilder.toString:()Ljava/lang/String;
	invokespecial	Method java/io/IOException."<init>":(Ljava/lang/String;)V
	athrow
l2	return
  Labels:
   	l1 = 30 // new
   	l2 = 133 // return
  LocalVariableTable: 
   Start  Length  Slot  Name   Signature
   0      134      0    this       Lscala/reflect/generic/UnPickler$Scan;
   5      129      1    major       I
   10      124      2    minor       I


public scala.reflect.generic.Scopes$AbsScope symScope(scala.reflect.generic.Symbols$AbsSymbol);
  Signature: (Lscala/reflect/generic/Symbols$AbsSymbol;)Lscala/reflect/generic/Scopes$AbsScope;
  Code:
   Stack=3, Locals=5, Args_size=2
	aload_0
	invokespecial	Method symScopes:()Lscala/collection/mutable/HashMap;
	aload_1
	invokevirtual	Method scala/collection/mutable/HashMap.get:(Ljava/lang/Object;)Lscala/Option;
	astore_2
	getstatic	Field scala/None$.MODULE$:Lscala/None$;
	aload_2
	astore_3
	dup
	ifnonnull	l1 // aload_3
	pop
	aload_3
	ifnull	l2 // aload_0
	goto	l3 // aload_2
l1	aload_3
	invokevirtual	Method java/lang/Object.equals:(Ljava/lang/Object;)Z
	ifeq	l3 // aload_2
l2	aload_0
	invokevirtual	Method scala$reflect$generic$UnPickler$Scan$$$outer:()Lscala/reflect/generic/UnPickler;
	invokevirtual	Method scala/reflect/generic/UnPickler.global:()Lscala/reflect/generic/Universe;
	invokeinterface	InterfaceMethod scala/reflect/generic/Scopes.newScope:()Lscala/reflect/generic/Scopes$AbsScope;
	astore	4
	aload_0
	invokespecial	Method symScopes:()Lscala/collection/mutable/HashMap;
	aload_1
	aload	4
	invokevirtual	Method scala/collection/mutable/HashMap.update:(Ljava/lang/Object;Ljava/lang/Object;)V
	aload	4
	goto	l4 // areturn
l3	aload_2
	instanceof	class scala/Some
	ifeq	l5 // new
	aload_2
	checkcast	class scala/Some
	invokevirtual	Method scala/Some.x:()Ljava/lang/Object;
	checkcast	class scala/reflect/generic/Scopes$AbsScope
l4	areturn
l5	new	class scala/MatchError
	dup
	aload_2
	invokespecial	Method scala/MatchError."<init>":(Ljava/lang/Object;)V
	athrow
  Labels:
   	l1 = 26 // aload_3
   	l2 = 33 // aload_0
   	l3 = 62 // aload_2
   	l4 = 79 // areturn
   	l5 = 80 // new
  LocalVariableTable: 
   Start  Length  Slot  Name   Signature
   0      89      0    this       Lscala/reflect/generic/UnPickler$Scan;
   0      89      1    sym       Lscala/reflect/generic/Symbols$AbsSymbol;
   9      80      2    temp1       Lscala/Option;
   47      12      4    s       Lscala/reflect/generic/Scopes$AbsScope;


public boolean isSymbolEntry(int);
  Signature: (I)Z
  Code:
   Stack=3, Locals=3, Args_size=2
	aload_0
	getfield	Field bytes:[B
	aload_0
	invokespecial	Method index:()[I
	iload_1
	iaload
	baload
	istore_2
	iconst_3
	iload_2
	if_icmpgt	l1 // iconst_0
	iload_2
	ldc	int 8
	if_icmpgt	l1 // iconst_0
	iload_2
	ldc	int 6
	if_icmpne	l2 // iconst_1
	aload_0
	iload_1
	invokevirtual	Method isRefinementSymbolEntry:(I)Z
	ifne	l1 // iconst_0
l2	iconst_1
	goto	l3 // ireturn
l1	iconst_0
l3	ireturn
  Labels:
   	l2 = 37 // iconst_1
   	l1 = 41 // iconst_0
   	l3 = 42 // ireturn
  LocalVariableTable: 
   Start  Length  Slot  Name   Signature
   0      43      0    this       Lscala/reflect/generic/UnPickler$Scan;
   0      43      1    i       I
   12      31      2    tag       I


public boolean isSymbolRef(int);
  Signature: (I)Z
  Code:
   Stack=3, Locals=3, Args_size=2
	aload_0
	getfield	Field bytes:[B
	aload_0
	invokespecial	Method index:()[I
	iload_1
	iaload
	baload
	istore_2
	iconst_3
	iload_2
	if_icmpgt	l1 // iconst_0
	iload_2
	ldc	int 10
	if_icmpgt	l1 // iconst_0
	iconst_1
	goto	l2 // ireturn
l1	iconst_0
l2	ireturn
  Labels:
   	l1 = 27 // iconst_0
   	l2 = 28 // ireturn
  LocalVariableTable: 
   Start  Length  Slot  Name   Signature
   0      29      0    this       Lscala/reflect/generic/UnPickler$Scan;
   0      29      1    i       I
   12      17      2    tag       B


public boolean isNameEntry(int);
  Signature: (I)Z
  Code:
   Stack=3, Locals=3, Args_size=2
	aload_0
	getfield	Field bytes:[B
	aload_0
	invokespecial	Method index:()[I
	iload_1
	iaload
	baload
	istore_2
	iload_2
	iconst_1
	if_icmpeq	l1 // iconst_1
	iload_2
	iconst_2
	if_icmpne	l2 // iconst_0
l1	iconst_1
	goto	l3 // ireturn
l2	iconst_0
l3	ireturn
  Labels:
   	l1 = 22 // iconst_1
   	l2 = 26 // iconst_0
   	l3 = 27 // ireturn
  LocalVariableTable: 
   Start  Length  Slot  Name   Signature
   0      28      0    this       Lscala/reflect/generic/UnPickler$Scan;
   0      28      1    i       I
   12      16      2    tag       I


public boolean isSymbolAnnotationEntry(int);
  Signature: (I)Z
  Code:
   Stack=3, Locals=3, Args_size=2
	aload_0
	getfield	Field bytes:[B
	aload_0
	invokespecial	Method index:()[I
	iload_1
	iaload
	baload
	istore_2
	iload_2
	ldc	int 40
	if_icmpne	l1 // iconst_0
	iconst_1
	goto	l2 // ireturn
l1	iconst_0
l2	ireturn
  Labels:
   	l1 = 22 // iconst_0
   	l2 = 23 // ireturn
  LocalVariableTable: 
   Start  Length  Slot  Name   Signature
   0      24      0    this       Lscala/reflect/generic/UnPickler$Scan;
   0      24      1    i       I
   12      12      2    tag       I


public boolean isChildrenEntry(int);
  Signature: (I)Z
  Code:
   Stack=3, Locals=3, Args_size=2
	aload_0
	getfield	Field bytes:[B
	aload_0
	invokespecial	Method index:()[I
	iload_1
	iaload
	baload
	istore_2
	iload_2
	ldc	int 41
	if_icmpne	l1 // iconst_0
	iconst_1
	goto	l2 // ireturn
l1	iconst_0
l2	ireturn
  Labels:
   	l1 = 22 // iconst_0
   	l2 = 23 // ireturn
  LocalVariableTable: 
   Start  Length  Slot  Name   Signature
   0      24      0    this       Lscala/reflect/generic/UnPickler$Scan;
   0      24      1    i       I
   12      12      2    tag       I


public boolean isRefinementSymbolEntry(int);
  Signature: (I)Z
  Code:
   Stack=3, Locals=5, Args_size=2
	aload_0
	invokevirtual	Method readIndex:()I
	istore_2
	aload_0
	aload_0
	invokespecial	Method index:()[I
	iload_1
	iaload
	invokevirtual	Method readIndex_$eq:(I)V
	aload_0
	invokevirtual	Method readByte:()I
	istore_3
	getstatic	Field scala/Predef$.MODULE$:Lscala/Predef$;
	iload_3
	ldc	int 6
	if_icmpne	l1 // iconst_0
	iconst_1
	goto	l2 // invokevirtual
l1	iconst_0
l2	invokevirtual	Method scala/Predef$.assert:(Z)V
	aload_0
	invokevirtual	Method readNat:()I
	pop
	aload_0
	invokevirtual	Method readNameRef:()Ljava/lang/Object;
	aload_0
	invokevirtual	Method scala$reflect$generic$UnPickler$Scan$$$outer:()Lscala/reflect/generic/UnPickler;
	invokevirtual	Method scala/reflect/generic/UnPickler.global:()Lscala/reflect/generic/Universe;
	aload_0
	invokevirtual	Method scala$reflect$generic$UnPickler$Scan$$$outer:()Lscala/reflect/generic/UnPickler;
	invokevirtual	Method scala/reflect/generic/UnPickler.global:()Lscala/reflect/generic/Universe;
	invokeinterface	InterfaceMethod scala/reflect/generic/StdNames.nme:()Lscala/reflect/generic/StdNames$StandardNames;
	invokevirtual	Method scala/reflect/generic/StdNames$StandardNames.REFINE_CLASS_NAME:()Ljava/lang/Object;
	invokeinterface	InterfaceMethod scala/reflect/generic/Names.mkTypeName:(Ljava/lang/Object;)Ljava/lang/Object;
	invokestatic	Method scala/runtime/BoxesRunTime.equals:(Ljava/lang/Object;Ljava/lang/Object;)Z
	ifeq	l3 // iconst_0
	iconst_1
	goto	l4 // istore
l3	iconst_0
l4	istore	4
	aload_0
	iload_2
	invokevirtual	Method readIndex_$eq:(I)V
	iload	4
	ireturn
  Labels:
   	l1 = 33 // iconst_0
   	l2 = 34 // invokevirtual
   	l3 = 83 // iconst_0
   	l4 = 84 // istore
  LocalVariableTable: 
   Start  Length  Slot  Name   Signature
   0      94      0    this       Lscala/reflect/generic/UnPickler$Scan;
   0      94      1    i       I
   5      88      2    savedIndex       I
   20      73      3    tag       I
   86      7      4    result       Z


public java.lang.Object at(int, scala.Function0);
  Signature: (ILscala/Function0;)Ljava/lang/Object;
  Code:
   Stack=6, Locals=5, Args_size=3
	aload_0
	invokevirtual	Method scala$reflect$generic$UnPickler$Scan$$entries:()[Ljava/lang/Object;
	iload_1
	aaload
	astore_3
	aload_3
	ifnonnull	l1 // aload_3
	aload_0
	invokevirtual	Method readIndex:()I
	istore	4
	aload_0
	aload_0
	invokespecial	Method index:()[I
	iload_1
	iaload
	invokevirtual	Method readIndex_$eq:(I)V
	aload_2
	invokeinterface	InterfaceMethod scala/Function0.apply:()Ljava/lang/Object;
	astore_3
	getstatic	Field scala/Predef$.MODULE$:Lscala/Predef$;
	aload_0
	invokevirtual	Method scala$reflect$generic$UnPickler$Scan$$entries:()[Ljava/lang/Object;
	iload_1
	aaload
	ifnonnull	l2 // iconst_0
	iconst_1
	goto	l3 // new
l2	iconst_0
l3	new	class scala/reflect/generic/UnPickler$Scan$$anonfun$at$1
	dup
	aload_0
	iload_1
	invokespecial	Method scala/reflect/generic/UnPickler$Scan$$anonfun$at$1."<init>":(Lscala/reflect/generic/UnPickler$Scan;I)V
	invokevirtual	Method scala/Predef$.assert:(ZLscala/Function0;)V
	aload_0
	invokevirtual	Method scala$reflect$generic$UnPickler$Scan$$entries:()[Ljava/lang/Object;
	iload_1
	aload_3
	aastore
	aload_0
	iload	4
	invokevirtual	Method readIndex_$eq:(I)V
l1	aload_3
	areturn
  Labels:
   	l2 = 50 // iconst_0
   	l3 = 51 // new
   	l1 = 76 // aload_3
  LocalVariableTable: 
   Start  Length  Slot  Name   Signature
   0      78      0    this       Lscala/reflect/generic/UnPickler$Scan;
   0      78      1    i$1       I
   0      78      2    op       Lscala/Function0;
   7      70      3    r       Ljava/lang/Object;
   17      59      4    savedIndex       I

  Signature: length = 0x2
   01 10 

public java.lang.Object readName();
  Signature: ()Ljava/lang/Object;
  Code:
   Stack=4, Locals=4, Args_size=1
	aload_0
	invokevirtual	Method readByte:()I
	istore_1
	aload_0
	invokevirtual	Method readNat:()I
	istore_2
	iload_1
	istore_3
	iload_3
	tableswitch{ //1 to 2
		1: 88;
		2: 64;
		default: 36 }
	aload_0
	new	class scala/collection/mutable/StringBuilder
	dup
	invokespecial	Method scala/collection/mutable/StringBuilder."<init>":()V
	ldc_w	String bad name tag: 
	invokevirtual	Method scala/collection/mutable/StringBuilder.append:(Ljava/lang/Object;)Lscala/collection/mutable/StringBuilder;
	iload_1
	invokestatic	Method scala/runtime/BoxesRunTime.boxToInteger:(I)Ljava/lang/Integer;
	invokevirtual	Method scala/collection/mutable/StringBuilder.append:(Ljava/lang/Object;)Lscala/collection/mutable/StringBuilder;
	invokevirtual	Method scala/collection/mutable/StringBuilder.toString:()Ljava/lang/String;
	invokevirtual	Method errorBadSignature:(Ljava/lang/String;)Lscala/runtime/Nothing$;
	athrow
	aload_0
	invokevirtual	Method scala$reflect$generic$UnPickler$Scan$$$outer:()Lscala/reflect/generic/UnPickler;
	invokevirtual	Method scala/reflect/generic/UnPickler.global:()Lscala/reflect/generic/Universe;
	aload_0
	getfield	Field bytes:[B
	aload_0
	invokevirtual	Method readIndex:()I
	iload_2
	invokeinterface	InterfaceMethod scala/reflect/generic/Names.newTypeName:([BII)Ljava/lang/Object;
	goto	l1 // areturn
	aload_0
	invokevirtual	Method scala$reflect$generic$UnPickler$Scan$$$outer:()Lscala/reflect/generic/UnPickler;
	invokevirtual	Method scala/reflect/generic/UnPickler.global:()Lscala/reflect/generic/Universe;
	aload_0
	getfield	Field bytes:[B
	aload_0
	invokevirtual	Method readIndex:()I
	iload_2
	invokeinterface	InterfaceMethod scala/reflect/generic/Names.newTermName:([BII)Ljava/lang/Object;
l1	areturn
  Labels:
   	l1 = 109 // areturn
  LocalVariableTable: 
   Start  Length  Slot  Name   Signature
   0      110      0    this       Lscala/reflect/generic/UnPickler$Scan;
   5      105      1    tag       I
   10      100      2    len       I
   12      98      3    temp5       I


public scala.reflect.generic.Symbols$AbsSymbol readSymbol();
  Signature: ()Lscala/reflect/generic/Symbols$AbsSymbol;
  Code:
   Stack=6, Locals=25, Args_size=1
	aload_0
	invokevirtual	Method readByte:()I
	istore_1
	aload_0
	invokevirtual	Method readNat:()I
	aload_0
	invokevirtual	Method readIndex:()I
	iadd
	istore_2
	new	class scala/runtime/ObjectRef
	dup
	aload_0
	invokevirtual	Method scala$reflect$generic$UnPickler$Scan$$$outer:()Lscala/reflect/generic/UnPickler;
	invokevirtual	Method scala/reflect/generic/UnPickler.global:()Lscala/reflect/generic/Universe;
	invokeinterface	InterfaceMethod scala/reflect/generic/Symbols.NoSymbol:()Lscala/reflect/generic/Symbols$AbsSymbol;
	invokespecial	Method scala/runtime/ObjectRef."<init>":(Ljava/lang/Object;)V
	astore_3
	iload_1
	istore	4
	iload	4
	lookupswitch{ //3
		3: 1189;
		9: 986;
		10: 986;
		default: 76 }
	aload_0
	invokevirtual	Method scala$reflect$generic$UnPickler$Scan$$$outer:()Lscala/reflect/generic/UnPickler;
	invokevirtual	Method scala/reflect/generic/UnPickler.global:()Lscala/reflect/generic/Universe;
	invokeinterface	InterfaceMethod scala/reflect/generic/Symbols.NoSymbol:()Lscala/reflect/generic/Symbols$AbsSymbol;
	astore	9
	aload_0
	invokevirtual	Method readNat:()I
	istore	10
	iload_1
	ldc	int 8
	if_icmpne	l1 // aload_0
	aload_0
	iload	10
	invokevirtual	Method isSymbolRef:(I)Z
	ifeq	l1 // aload_0
	aload_0
	iload	10
	new	class scala/reflect/generic/UnPickler$Scan$$anonfun$readSymbol$1
	dup
	aload_0
	invokespecial	Method scala/reflect/generic/UnPickler$Scan$$anonfun$readSymbol$1."<init>":(Lscala/reflect/generic/UnPickler$Scan;)V
	invokevirtual	Method at:(ILscala/Function0;)Ljava/lang/Object;
	checkcast	class scala/reflect/generic/Symbols$AbsSymbol
	astore	9
	aload_0
	invokevirtual	Method readNat:()I
	istore	10
l1	aload_0
	iload	10
	new	class scala/reflect/generic/UnPickler$Scan$$anonfun$1
	dup
	aload_0
	invokespecial	Method scala/reflect/generic/UnPickler$Scan$$anonfun$1."<init>":(Lscala/reflect/generic/UnPickler$Scan;)V
	invokevirtual	Method at:(ILscala/Function0;)Ljava/lang/Object;
	astore	11
	aload_0
	invokevirtual	Method readSymbolRef:()Lscala/reflect/generic/Symbols$AbsSymbol;
	astore	12
	getstatic	Field scala/reflect/generic/Flags$.MODULE$:Lscala/reflect/generic/Flags$;
	aload_0
	invokevirtual	Method readLongNat:()J
	invokevirtual	Method scala/reflect/generic/Flags$.pickledToRawFlags:(J)J
	lstore	13
	aload_0
	invokevirtual	Method scala$reflect$generic$UnPickler$Scan$$$outer:()Lscala/reflect/generic/UnPickler;
	invokevirtual	Method scala/reflect/generic/UnPickler.global:()Lscala/reflect/generic/Universe;
	invokeinterface	InterfaceMethod scala/reflect/generic/Symbols.NoSymbol:()Lscala/reflect/generic/Symbols$AbsSymbol;
	astore	15
	aload_0
	invokevirtual	Method readNat:()I
	istore	16
	aload_0
	iload	16
	invokevirtual	Method isSymbolRef:(I)Z
	ifeq	l2 // iload_1
	aload_0
	iload	16
	new	class scala/reflect/generic/UnPickler$Scan$$anonfun$readSymbol$2
	dup
	aload_0
	invokespecial	Method scala/reflect/generic/UnPickler$Scan$$anonfun$readSymbol$2."<init>":(Lscala/reflect/generic/UnPickler$Scan;)V
	invokevirtual	Method at:(ILscala/Function0;)Ljava/lang/Object;
	checkcast	class scala/reflect/generic/Symbols$AbsSymbol
	astore	15
	aload_0
	invokevirtual	Method readNat:()I
	istore	16
l2	iload_1
	istore	17
	iload	17
	tableswitch{ //4 to 8
		4: 662;
		5: 643;
		6: 497;
		7: 389;
		8: 275;
		default: 264 }
	aload_0
	iload_1
	iload_2
	aload	11
	aload	12
	invokevirtual	Method noSuchSymbolTag:(IILjava/lang/Object;Lscala/reflect/generic/Symbols$AbsSymbol;)Lscala/runtime/Nothing$;
	athrow
	aload_3
	aload	11
	aload_0
	getfield	Field moduleRoot:Lscala/reflect/generic/Symbols$AbsSymbol;
	invokevirtual	Method scala/reflect/generic/Symbols$AbsSymbol.name:()Ljava/lang/Object;
	invokestatic	Method scala/runtime/BoxesRunTime.equals:(Ljava/lang/Object;Ljava/lang/Object;)Z
	ifeq	l3 // lload
	aload	12
	aload_0
	getfield	Field moduleRoot:Lscala/reflect/generic/Symbols$AbsSymbol;
	invokevirtual	Method scala/reflect/generic/Symbols$AbsSymbol.owner:()Lscala/reflect/generic/Symbols$AbsSymbol;
	astore	22
	dup
	ifnonnull	l4 // aload
	pop
	aload	22
	ifnull	l5 // getstatic
	goto	l3 // lload
l4	aload	22
	invokevirtual	Method java/lang/Object.equals:(Ljava/lang/Object;)Z
	ifeq	l3 // lload
l5	getstatic	Field scala/Predef$.MODULE$:Lscala/Predef$;
	iconst_0
	invokevirtual	Method scala/Predef$.assert:(Z)V
	aload_0
	invokevirtual	Method scala$reflect$generic$UnPickler$Scan$$$outer:()Lscala/reflect/generic/UnPickler;
	invokevirtual	Method scala/reflect/generic/UnPickler.global:()Lscala/reflect/generic/Universe;
	invokeinterface	InterfaceMethod scala/reflect/generic/Symbols.NoSymbol:()Lscala/reflect/generic/Symbols$AbsSymbol;
	goto	l6 // putfield
l3	lload	13
	ldc2_w	long 64l
	land
	lconst_0
	lcmp
	ifeq	l7 // aload
	aload	12
	aload	11
	aload	12
	invokevirtual	Method scala/reflect/generic/Symbols$AbsSymbol.newMethod$default$2:()Ljava/lang/Object;
	invokevirtual	Method scala/reflect/generic/Symbols$AbsSymbol.newMethod:(Ljava/lang/Object;Ljava/lang/Object;)Lscala/reflect/generic/Symbols$AbsSymbol;
	goto	l6 // putfield
l7	aload	12
	aload	11
	aload	12
	invokevirtual	Method scala/reflect/generic/Symbols$AbsSymbol.newValue$default$2:()Ljava/lang/Object;
	invokevirtual	Method scala/reflect/generic/Symbols$AbsSymbol.newValue:(Ljava/lang/Object;Ljava/lang/Object;)Lscala/reflect/generic/Symbols$AbsSymbol;
l6	putfield	Field scala/runtime/ObjectRef.elem:Ljava/lang/Object;
	goto	l8 // aload_3
	aload_0
	iload	16
	new	class scala/reflect/generic/UnPickler$Scan$$anonfun$2
	dup
	aload_0
	invokespecial	Method scala/reflect/generic/UnPickler$Scan$$anonfun$2."<init>":(Lscala/reflect/generic/UnPickler$Scan;)V
	invokevirtual	Method at:(ILscala/Function0;)Ljava/lang/Object;
	checkcast	class scala/reflect/generic/Types$AbsType
	invokevirtual	Method scala/reflect/generic/Types$AbsType.typeSymbol:()Lscala/reflect/generic/Symbols$AbsSymbol;
	astore	19
	aload_3
	aload	11
	aload_0
	getfield	Field moduleRoot:Lscala/reflect/generic/Symbols$AbsSymbol;
	invokevirtual	Method scala/reflect/generic/Symbols$AbsSymbol.name:()Ljava/lang/Object;
	invokestatic	Method scala/runtime/BoxesRunTime.equals:(Ljava/lang/Object;Ljava/lang/Object;)Z
	ifeq	l9 // aload
	aload	12
	aload_0
	getfield	Field moduleRoot:Lscala/reflect/generic/Symbols$AbsSymbol;
	invokevirtual	Method scala/reflect/generic/Symbols$AbsSymbol.owner:()Lscala/reflect/generic/Symbols$AbsSymbol;
	astore	20
	dup
	ifnonnull	l10 // aload
	pop
	aload	20
	ifnull	l11 // aload_0
	goto	l9 // aload
l10	aload	20
	invokevirtual	Method java/lang/Object.equals:(Ljava/lang/Object;)Z
	ifeq	l9 // aload
l11	aload_0
	getfield	Field moduleRoot:Lscala/reflect/generic/Symbols$AbsSymbol;
	goto	l12 // putfield
l9	aload	12
	aload	11
	aload	19
	aload	12
	invokevirtual	Method scala/reflect/generic/Symbols$AbsSymbol.newModule$default$3:()Ljava/lang/Object;
	invokevirtual	Method scala/reflect/generic/Symbols$AbsSymbol.newModule:(Ljava/lang/Object;Lscala/reflect/generic/Symbols$AbsSymbol;Ljava/lang/Object;)Lscala/reflect/generic/Symbols$AbsSymbol;
	astore	21
	aload	19
	aload	21
	invokevirtual	Method scala/reflect/generic/Symbols$AbsSymbol.sourceModule_$eq:(Lscala/reflect/generic/Symbols$AbsSymbol;)V
	aload	21
l12	putfield	Field scala/runtime/ObjectRef.elem:Ljava/lang/Object;
	goto	l8 // aload_3
	aload_3
	aload	11
	aload_0
	getfield	Field classRoot:Lscala/reflect/generic/Symbols$AbsSymbol;
	invokevirtual	Method scala/reflect/generic/Symbols$AbsSymbol.name:()Ljava/lang/Object;
	invokestatic	Method scala/runtime/BoxesRunTime.equals:(Ljava/lang/Object;Ljava/lang/Object;)Z
	ifeq	l13 // lload
	aload	12
	aload_0
	getfield	Field classRoot:Lscala/reflect/generic/Symbols$AbsSymbol;
	invokevirtual	Method scala/reflect/generic/Symbols$AbsSymbol.owner:()Lscala/reflect/generic/Symbols$AbsSymbol;
	astore	18
	dup
	ifnonnull	l14 // aload
	pop
	aload	18
	ifnull	l15 // lload
	goto	l13 // lload
l14	aload	18
	invokevirtual	Method java/lang/Object.equals:(Ljava/lang/Object;)Z
	ifeq	l13 // lload
l15	lload	13
	ldc2_w	long 256l
	land
	lconst_0
	lcmp
	ifeq	l16 // aload_0
	aload_0
	getfield	Field moduleRoot:Lscala/reflect/generic/Symbols$AbsSymbol;
	invokevirtual	Method scala/reflect/generic/Symbols$AbsSymbol.moduleClass:()Lscala/reflect/generic/Symbols$AbsSymbol;
	goto	l17 // putfield
l16	aload_0
	getfield	Field classRoot:Lscala/reflect/generic/Symbols$AbsSymbol;
	goto	l17 // putfield
l13	lload	13
	ldc2_w	long 256l
	land
	lconst_0
	lcmp
	ifeq	l18 // aload
	aload	12
	aload	11
	aload	12
	invokevirtual	Method scala/reflect/generic/Symbols$AbsSymbol.newModuleClass$default$2:()Ljava/lang/Object;
	invokevirtual	Method scala/reflect/generic/Symbols$AbsSymbol.newModuleClass:(Ljava/lang/Object;Ljava/lang/Object;)Lscala/reflect/generic/Symbols$AbsSymbol;
	goto	l17 // putfield
l18	aload	12
	aload	11
	aload	12
	invokevirtual	Method scala/reflect/generic/Symbols$AbsSymbol.newClass$default$2:()Ljava/lang/Object;
	invokevirtual	Method scala/reflect/generic/Symbols$AbsSymbol.newClass:(Ljava/lang/Object;Ljava/lang/Object;)Lscala/reflect/generic/Symbols$AbsSymbol;
l17	putfield	Field scala/runtime/ObjectRef.elem:Ljava/lang/Object;
	aload_0
	invokevirtual	Method readIndex:()I
	iload_2
	if_icmpeq	l8 // aload_3
	aload_3
	getfield	Field scala/runtime/ObjectRef.elem:Ljava/lang/Object;
	checkcast	class scala/reflect/generic/Symbols$AbsSymbol
	aload_0
	aload_0
	invokevirtual	Method readNat:()I
	invokevirtual	Method newLazyTypeRef:(I)Lscala/reflect/generic/Types$AbsType;
	invokevirtual	Method scala/reflect/generic/Symbols$AbsSymbol.typeOfThis_$eq:(Lscala/reflect/generic/Types$AbsType;)V
	goto	l8 // aload_3
	aload_3
	aload	12
	aload	11
	aload	12
	invokevirtual	Method scala/reflect/generic/Symbols$AbsSymbol.newAliasType$default$2:()Ljava/lang/Object;
	invokevirtual	Method scala/reflect/generic/Symbols$AbsSymbol.newAliasType:(Ljava/lang/Object;Ljava/lang/Object;)Lscala/reflect/generic/Symbols$AbsSymbol;
	putfield	Field scala/runtime/ObjectRef.elem:Ljava/lang/Object;
	goto	l8 // aload_3
	aload_3
	aload	12
	aload	11
	aload	12
	invokevirtual	Method scala/reflect/generic/Symbols$AbsSymbol.newAbstractType$default$2:()Ljava/lang/Object;
	invokevirtual	Method scala/reflect/generic/Symbols$AbsSymbol.newAbstractType:(Ljava/lang/Object;Ljava/lang/Object;)Lscala/reflect/generic/Symbols$AbsSymbol;
	putfield	Field scala/runtime/ObjectRef.elem:Ljava/lang/Object;
l8	aload_3
	getfield	Field scala/runtime/ObjectRef.elem:Ljava/lang/Object;
	checkcast	class scala/reflect/generic/Symbols$AbsSymbol
	lload	13
	getstatic	Field scala/reflect/generic/Flags$.MODULE$:Lscala/reflect/generic/Flags$;
	invokevirtual	Method scala/reflect/generic/Flags$.PickledFlags:()J
	land
	invokevirtual	Method scala/reflect/generic/Symbols$AbsSymbol.flags_$eq:(J)V
	aload_3
	getfield	Field scala/runtime/ObjectRef.elem:Ljava/lang/Object;
	checkcast	class scala/reflect/generic/Symbols$AbsSymbol
	aload	15
	invokevirtual	Method scala/reflect/generic/Symbols$AbsSymbol.privateWithin_$eq:(Lscala/reflect/generic/Symbols$AbsSymbol;)V
	aload_0
	invokevirtual	Method readIndex:()I
	iload_2
	if_icmpeq	l19 // aload_3
	getstatic	Field scala/Predef$.MODULE$:Lscala/Predef$;
	aload_3
	getfield	Field scala/runtime/ObjectRef.elem:Ljava/lang/Object;
	checkcast	class scala/reflect/generic/Symbols$AbsSymbol
	ldc2_w	long 805306368l
	invokevirtual	Method scala/reflect/generic/Symbols$AbsSymbol.hasFlag:(J)Z
	new	class scala/reflect/generic/UnPickler$Scan$$anonfun$readSymbol$3
	dup
	aload_0
	aload_3
	invokespecial	Method scala/reflect/generic/UnPickler$Scan$$anonfun$readSymbol$3."<init>":(Lscala/reflect/generic/UnPickler$Scan;Lscala/runtime/ObjectRef;)V
	invokevirtual	Method scala/Predef$.assert:(ZLscala/Function0;)V
l19	aload_3
	getfield	Field scala/runtime/ObjectRef.elem:Ljava/lang/Object;
	checkcast	class scala/reflect/generic/Symbols$AbsSymbol
	ldc2_w	long 268435456l
	invokevirtual	Method scala/reflect/generic/Symbols$AbsSymbol.hasFlag:(J)Z
	ifeq	l20 // aload_3
	getstatic	Field scala/Predef$.MODULE$:Lscala/Predef$;
	aload_0
	invokevirtual	Method readIndex:()I
	iload_2
	if_icmpeq	l21 // iconst_0
	iconst_1
	goto	l22 // invokevirtual
l21	iconst_0
l22	invokevirtual	Method scala/Predef$.assert:(Z)V
l20	aload_3
	getfield	Field scala/runtime/ObjectRef.elem:Ljava/lang/Object;
	checkcast	class scala/reflect/generic/Symbols$AbsSymbol
	aload_0
	invokevirtual	Method readIndex:()I
	iload_2
	if_icmpeq	l23 // aload_0
	aload_0
	iload	16
	aload_0
	invokevirtual	Method readNat:()I
	invokevirtual	Method newLazyTypeRefAndAlias:(II)Lscala/reflect/generic/Types$AbsType;
	goto	l24 // invokevirtual
l23	aload_0
	iload	16
	invokevirtual	Method newLazyTypeRef:(I)Lscala/reflect/generic/Types$AbsType;
l24	invokevirtual	Method scala/reflect/generic/Symbols$AbsSymbol.info_$eq:(Lscala/reflect/generic/Types$AbsType;)V
	aload_3
	getfield	Field scala/runtime/ObjectRef.elem:Ljava/lang/Object;
	checkcast	class scala/reflect/generic/Symbols$AbsSymbol
	invokevirtual	Method scala/reflect/generic/Symbols$AbsSymbol.owner:()Lscala/reflect/generic/Symbols$AbsSymbol;
	invokevirtual	Method scala/reflect/generic/Symbols$AbsSymbol.isClass:()Z
	ifeq	l25 // getstatic
	aload_3
	getfield	Field scala/runtime/ObjectRef.elem:Ljava/lang/Object;
	checkcast	class scala/reflect/generic/Symbols$AbsSymbol
	aload_0
	getfield	Field classRoot:Lscala/reflect/generic/Symbols$AbsSymbol;
	astore	23
	dup
	ifnonnull	l26 // aload
	pop
	aload	23
	ifnull	l25 // getstatic
	goto	l27 // aload_3
l26	aload	23
	invokevirtual	Method java/lang/Object.equals:(Ljava/lang/Object;)Z
	ifne	l25 // getstatic
l27	aload_3
	getfield	Field scala/runtime/ObjectRef.elem:Ljava/lang/Object;
	checkcast	class scala/reflect/generic/Symbols$AbsSymbol
	aload_0
	getfield	Field moduleRoot:Lscala/reflect/generic/Symbols$AbsSymbol;
	astore	24
	dup
	ifnonnull	l28 // aload
	pop
	aload	24
	ifnull	l25 // getstatic
	goto	l29 // aload_3
l28	aload	24
	invokevirtual	Method java/lang/Object.equals:(Ljava/lang/Object;)Z
	ifne	l25 // getstatic
l29	aload_3
	getfield	Field scala/runtime/ObjectRef.elem:Ljava/lang/Object;
	checkcast	class scala/reflect/generic/Symbols$AbsSymbol
	invokevirtual	Method scala/reflect/generic/Symbols$AbsSymbol.isModuleClass:()Z
	ifne	l25 // getstatic
	aload_3
	getfield	Field scala/runtime/ObjectRef.elem:Ljava/lang/Object;
	checkcast	class scala/reflect/generic/Symbols$AbsSymbol
	invokevirtual	Method scala/reflect/generic/Symbols$AbsSymbol.isRefinementClass:()Z
	ifne	l25 // getstatic
	aload_3
	getfield	Field scala/runtime/ObjectRef.elem:Ljava/lang/Object;
	checkcast	class scala/reflect/generic/Symbols$AbsSymbol
	invokevirtual	Method scala/reflect/generic/Symbols$AbsSymbol.isTypeParameter:()Z
	ifne	l25 // getstatic
	aload_3
	getfield	Field scala/runtime/ObjectRef.elem:Ljava/lang/Object;
	checkcast	class scala/reflect/generic/Symbols$AbsSymbol
	invokevirtual	Method scala/reflect/generic/Symbols$AbsSymbol.isExistentiallyBound:()Z
	ifne	l25 // getstatic
	aload_0
	aload_3
	getfield	Field scala/runtime/ObjectRef.elem:Ljava/lang/Object;
	checkcast	class scala/reflect/generic/Symbols$AbsSymbol
	invokevirtual	Method scala/reflect/generic/Symbols$AbsSymbol.owner:()Lscala/reflect/generic/Symbols$AbsSymbol;
	invokevirtual	Method symScope:(Lscala/reflect/generic/Symbols$AbsSymbol;)Lscala/reflect/generic/Scopes$AbsScope;
	aload_3
	getfield	Field scala/runtime/ObjectRef.elem:Ljava/lang/Object;
	checkcast	class scala/reflect/generic/Symbols$AbsSymbol
	invokevirtual	Method scala/reflect/generic/Scopes$AbsScope.enter:(Lscala/reflect/generic/Symbols$AbsSymbol;)Lscala/reflect/generic/Symbols$AbsSymbol;
	goto	l30 // pop
l25	getstatic	Field scala/runtime/BoxedUnit.UNIT:Lscala/runtime/BoxedUnit;
	goto	l30 // pop
	aload_0
	invokevirtual	Method readNameRef:()Ljava/lang/Object;
	astore	5
	aload_0
	invokevirtual	Method readIndex:()I
	iload_2
	if_icmpne	l31 // aload_0
	aload_0
	invokevirtual	Method scala$reflect$generic$UnPickler$Scan$$$outer:()Lscala/reflect/generic/UnPickler;
	invokevirtual	Method scala/reflect/generic/UnPickler.global:()Lscala/reflect/generic/Universe;
	invokeinterface	InterfaceMethod scala/reflect/generic/StandardDefinitions.definitions:()Lscala/reflect/generic/StandardDefinitions$AbsDefinitions;
	invokevirtual	Method scala/reflect/generic/StandardDefinitions$AbsDefinitions.RootClass:()Lscala/reflect/generic/Symbols$AbsSymbol;
	goto	l32 // astore
l31	aload_0
	invokevirtual	Method readSymbolRef:()Lscala/reflect/generic/Symbols$AbsSymbol;
l32	astore	6
	aload_3
	aload_0
	aload	5
	iload_1
	aload	6
	invokespecial	Method fromName$1:(Ljava/lang/Object;ILscala/reflect/generic/Symbols$AbsSymbol;)Lscala/reflect/generic/Symbols$AbsSymbol;
	putfield	Field scala/runtime/ObjectRef.elem:Ljava/lang/Object;
	aload_3
	getfield	Field scala/runtime/ObjectRef.elem:Ljava/lang/Object;
	checkcast	class scala/reflect/generic/Symbols$AbsSymbol
	aload_0
	invokevirtual	Method scala$reflect$generic$UnPickler$Scan$$$outer:()Lscala/reflect/generic/UnPickler;
	invokevirtual	Method scala/reflect/generic/UnPickler.global:()Lscala/reflect/generic/Universe;
	invokeinterface	InterfaceMethod scala/reflect/generic/Symbols.NoSymbol:()Lscala/reflect/generic/Symbols$AbsSymbol;
	astore	7
	dup
	ifnonnull	l33 // aload
	pop
	aload	7
	ifnull	l34 // aload_3
	goto	l35 // aload_3
l33	aload	7
	invokevirtual	Method java/lang/Object.equals:(Ljava/lang/Object;)Z
	ifeq	l35 // aload_3
l34	aload_3
	aload_0
	aload_0
	invokevirtual	Method scala$reflect$generic$UnPickler$Scan$$$outer:()Lscala/reflect/generic/UnPickler;
	invokevirtual	Method scala/reflect/generic/UnPickler.global:()Lscala/reflect/generic/Universe;
	invokeinterface	InterfaceMethod scala/reflect/generic/StdNames.nme:()Lscala/reflect/generic/StdNames$StandardNames;
	aload	5
	aload	6
	aload_0
	invokevirtual	Method scala$reflect$generic$UnPickler$Scan$$$outer:()Lscala/reflect/generic/UnPickler;
	invokevirtual	Method scala/reflect/generic/UnPickler.global:()Lscala/reflect/generic/Universe;
	invokeinterface	InterfaceMethod scala/reflect/generic/StdNames.nme:()Lscala/reflect/generic/StdNames$StandardNames;
	invokevirtual	Method scala/reflect/generic/StdNames$StandardNames.expandedName$default$3:()Ljava/lang/String;
	invokevirtual	Method scala/reflect/generic/StdNames$StandardNames.expandedName:(Ljava/lang/Object;Lscala/reflect/generic/Symbols$AbsSymbol;Ljava/lang/String;)Ljava/lang/Object;
	iload_1
	aload	6
	invokespecial	Method fromName$1:(Ljava/lang/Object;ILscala/reflect/generic/Symbols$AbsSymbol;)Lscala/reflect/generic/Symbols$AbsSymbol;
	putfield	Field scala/runtime/ObjectRef.elem:Ljava/lang/Object;
l35	aload_3
	getfield	Field scala/runtime/ObjectRef.elem:Ljava/lang/Object;
	checkcast	class scala/reflect/generic/Symbols$AbsSymbol
	aload_0
	invokevirtual	Method scala$reflect$generic$UnPickler$Scan$$$outer:()Lscala/reflect/generic/UnPickler;
	invokevirtual	Method scala/reflect/generic/UnPickler.global:()Lscala/reflect/generic/Universe;
	invokeinterface	InterfaceMethod scala/reflect/generic/Symbols.NoSymbol:()Lscala/reflect/generic/Symbols$AbsSymbol;
	astore	8
	dup
	ifnonnull	l36 // aload
	pop
	aload	8
	ifnull	l37 // aload
	goto	l38 // getstatic
l36	aload	8
	invokevirtual	Method java/lang/Object.equals:(Ljava/lang/Object;)Z
	ifeq	l38 // getstatic
l37	aload	6
	invokevirtual	Method scala/reflect/generic/Symbols$AbsSymbol.isOverloaded:()Z
	ifne	l38 // getstatic
	aload_0
	aload	5
	aload	6
	invokevirtual	Method errorMissingRequirement:(Ljava/lang/Object;Lscala/reflect/generic/Symbols$AbsSymbol;)Lscala/runtime/Nothing$;
	athrow
l38	getstatic	Field scala/runtime/BoxedUnit.UNIT:Lscala/runtime/BoxedUnit;
	goto	l30 // pop
	aload_3
	aload_0
	invokevirtual	Method scala$reflect$generic$UnPickler$Scan$$$outer:()Lscala/reflect/generic/UnPickler;
	invokevirtual	Method scala/reflect/generic/UnPickler.global:()Lscala/reflect/generic/Universe;
	invokeinterface	InterfaceMethod scala/reflect/generic/Symbols.NoSymbol:()Lscala/reflect/generic/Symbols$AbsSymbol;
	putfield	Field scala/runtime/ObjectRef.elem:Ljava/lang/Object;
	getstatic	Field scala/runtime/BoxedUnit.UNIT:Lscala/runtime/BoxedUnit;
l30	pop
	aload_3
	getfield	Field scala/runtime/ObjectRef.elem:Ljava/lang/Object;
	checkcast	class scala/reflect/generic/Symbols$AbsSymbol
	areturn
  Labels:
   	l1 = 136 // aload_0
   	l2 = 224 // iload_1
   	l4 = 315 // aload
   	l5 = 323 // getstatic
   	l3 = 345 // lload
   	l7 = 371 // aload
   	l6 = 383 // putfield
   	l10 = 451 // aload
   	l11 = 459 // aload_0
   	l9 = 466 // aload
   	l12 = 491 // putfield
   	l14 = 537 // aload
   	l15 = 545 // lload
   	l16 = 566 // aload_0
   	l13 = 573 // lload
   	l18 = 599 // aload
   	l17 = 611 // putfield
   	l8 = 678 // aload_3
   	l19 = 745 // aload_3
   	l21 = 776 // iconst_0
   	l22 = 777 // invokevirtual
   	l20 = 780 // aload_3
   	l23 = 808 // aload_0
   	l24 = 814 // invokevirtual
   	l26 = 859 // aload
   	l27 = 867 // aload_3
   	l28 = 893 // aload
   	l29 = 901 // aload_3
   	l25 = 980 // getstatic
   	l31 = 1018 // aload_0
   	l32 = 1022 // astore
   	l33 = 1071 // aload
   	l34 = 1079 // aload_3
   	l35 = 1124 // aload_3
   	l36 = 1158 // aload
   	l37 = 1166 // aload
   	l38 = 1183 // getstatic
   	l30 = 1208 // pop
  LocalVariableTable: 
   Start  Length  Slot  Name   Signature
   0      1217      0    this       Lscala/reflect/generic/UnPickler$Scan;
   5      1211      1    tag$1       I
   15      1201      2    end       I
   35      1181      3    sym$1       Lscala/runtime/ObjectRef;
   38      1171      4    temp7       I
   992      197      5    name       Ljava/lang/Object;
   1024      165      6    owner$1       Lscala/reflect/generic/Symbols$AbsSymbol;
   90      896      9    defaultGetter       Lscala/reflect/generic/Symbols$AbsSymbol;
   96      890      10    nameref       I
   152      834      11    name       Ljava/lang/Object;
   158      828      12    owner       Lscala/reflect/generic/Symbols$AbsSymbol;
   170      816      13    flags       J
   184      802      15    privateWithin       Lscala/reflect/generic/Symbols$AbsSymbol;
   190      796      16    inforef       I
   227      490      17    temp6       I
   411      83      19    clazz       Lscala/reflect/generic/Symbols$AbsSymbol;
   482      9      21    m       Lscala/reflect/generic/Symbols$AbsSymbol;


public scala.runtime.Nothing$ noSuchSymbolTag(int, int, java.lang.Object, scala.reflect.generic.Symbols$AbsSymbol);
  Signature: (IILjava/lang/Object;Lscala/reflect/generic/Symbols$AbsSymbol;)Lscala/runtime/Nothing$;
  Code:
   Stack=3, Locals=5, Args_size=5
	aload_0
	new	class scala/collection/mutable/StringBuilder
	dup
	invokespecial	Method scala/collection/mutable/StringBuilder."<init>":()V
	ldc_w	String bad symbol tag: 
	invokevirtual	Method scala/collection/mutable/StringBuilder.append:(Ljava/lang/Object;)Lscala/collection/mutable/StringBuilder;
	iload_1
	invokestatic	Method scala/runtime/BoxesRunTime.boxToInteger:(I)Ljava/lang/Integer;
	invokevirtual	Method scala/collection/mutable/StringBuilder.append:(Ljava/lang/Object;)Lscala/collection/mutable/StringBuilder;
	invokevirtual	Method scala/collection/mutable/StringBuilder.toString:()Ljava/lang/String;
	invokevirtual	Method errorBadSignature:(Ljava/lang/String;)Lscala/runtime/Nothing$;
	areturn
  Labels:
  LocalVariableTable: 
   Start  Length  Slot  Name   Signature
   0      28      0    this       Lscala/reflect/generic/UnPickler$Scan;
   0      28      1    tag       I
   0      28      2    end       I
   0      28      3    name       Ljava/lang/Object;
   0      28      4    owner       Lscala/reflect/generic/Symbols$AbsSymbol;


public scala.reflect.generic.Types$AbsType readType();
  Signature: ()Lscala/reflect/generic/Types$AbsType;
  Code:
   Stack=6, Locals=23, Args_size=1
	aload_0
	invokevirtual	Method readByte:()I
	istore_1
	aload_0
	invokevirtual	Method readNat:()I
	aload_0
	invokevirtual	Method readIndex:()I
	iadd
	istore_2
	iload_1
	istore_3
	iload_3
	lookupswitch{ //15
		11: 801;
		12: 786;
		13: 764;
		14: 738;
		15: 716;
		16: 665;
		17: 639;
		18: 594;
		19: 549;
		20: 432;
		21: 389;
		22: 432;
		42: 230;
		46: 196;
		48: 157;
		default: 148 }
	aload_0
	iload_1
	iload_2
	invokevirtual	Method noSuchTypeTag:(II)Lscala/reflect/generic/Types$AbsType;
	goto	l1 // areturn
	aload_0
	invokevirtual	Method readTypeRef:()Lscala/reflect/generic/Types$AbsType;
	astore	22
	aload_0
	invokevirtual	Method scala$reflect$generic$UnPickler$Scan$$$outer:()Lscala/reflect/generic/UnPickler;
	invokevirtual	Method scala/reflect/generic/UnPickler.global:()Lscala/reflect/generic/Universe;
	invokeinterface	InterfaceMethod scala/reflect/generic/Types.ExistentialType:()Lscala/reflect/generic/Types$ExistentialTypeExtractor;
	aload_0
	iload_2
	new	class scala/reflect/generic/UnPickler$Scan$$anonfun$readType$3
	dup
	aload_0
	invokespecial	Method scala/reflect/generic/UnPickler$Scan$$anonfun$readType$3."<init>":(Lscala/reflect/generic/UnPickler$Scan;)V
	invokevirtual	Method until:(ILscala/Function0;)Lscala/collection/immutable/List;
	aload	22
	invokevirtual	Method scala/reflect/generic/Types$ExistentialTypeExtractor.apply:(Lscala/collection/immutable/List;Lscala/reflect/generic/Types$AbsType;)Lscala/reflect/generic/Types$AbsType;
	goto	l1 // areturn
	aload_0
	invokevirtual	Method readTypeRef:()Lscala/reflect/generic/Types$AbsType;
	astore	20
	aload_0
	invokevirtual	Method readTypeRef:()Lscala/reflect/generic/Types$AbsType;
	astore	21
	aload_0
	invokevirtual	Method scala$reflect$generic$UnPickler$Scan$$$outer:()Lscala/reflect/generic/UnPickler;
	invokevirtual	Method scala/reflect/generic/UnPickler.global:()Lscala/reflect/generic/Universe;
	invokeinterface	InterfaceMethod scala/reflect/generic/Types.SuperType:()Lscala/reflect/generic/Types$SuperTypeExtractor;
	aload	20
	aload	21
	invokevirtual	Method scala/reflect/generic/Types$SuperTypeExtractor.apply:(Lscala/reflect/generic/Types$AbsType;Lscala/reflect/generic/Types$AbsType;)Lscala/reflect/generic/Types$AbsType;
	goto	l1 // areturn
	aload_0
	invokevirtual	Method readNat:()I
	istore	14
	aload_0
	iload	14
	invokevirtual	Method isSymbolRef:(I)Z
	ifeq	l2 // aload_0
	aload_0
	iload	14
	new	class scala/reflect/generic/UnPickler$Scan$$anonfun$6
	dup
	aload_0
	invokespecial	Method scala/reflect/generic/UnPickler$Scan$$anonfun$6."<init>":(Lscala/reflect/generic/UnPickler$Scan;)V
	invokevirtual	Method at:(ILscala/Function0;)Ljava/lang/Object;
	checkcast	class scala/reflect/generic/Symbols$AbsSymbol
	astore	16
	aload_0
	invokevirtual	Method readNat:()I
	istore	14
	aload	16
	goto	l3 // astore
l2	aload_0
	invokevirtual	Method scala$reflect$generic$UnPickler$Scan$$$outer:()Lscala/reflect/generic/UnPickler;
	invokevirtual	Method scala/reflect/generic/UnPickler.global:()Lscala/reflect/generic/Universe;
	invokeinterface	InterfaceMethod scala/reflect/generic/Symbols.NoSymbol:()Lscala/reflect/generic/Symbols$AbsSymbol;
l3	astore	15
	aload_0
	iload	14
	new	class scala/reflect/generic/UnPickler$Scan$$anonfun$7
	dup
	aload_0
	invokespecial	Method scala/reflect/generic/UnPickler$Scan$$anonfun$7."<init>":(Lscala/reflect/generic/UnPickler$Scan;)V
	invokevirtual	Method at:(ILscala/Function0;)Ljava/lang/Object;
	checkcast	class scala/reflect/generic/Types$AbsType
	astore	17
	aload_0
	iload_2
	new	class scala/reflect/generic/UnPickler$Scan$$anonfun$8
	dup
	aload_0
	invokespecial	Method scala/reflect/generic/UnPickler$Scan$$anonfun$8."<init>":(Lscala/reflect/generic/UnPickler$Scan;)V
	invokevirtual	Method until:(ILscala/Function0;)Lscala/collection/immutable/List;
	astore	18
	aload	15
	aload_0
	invokevirtual	Method scala$reflect$generic$UnPickler$Scan$$$outer:()Lscala/reflect/generic/UnPickler;
	invokevirtual	Method scala/reflect/generic/UnPickler.global:()Lscala/reflect/generic/Universe;
	invokeinterface	InterfaceMethod scala/reflect/generic/Symbols.NoSymbol:()Lscala/reflect/generic/Symbols$AbsSymbol;
	astore	19
	dup
	ifnonnull	l4 // aload
	pop
	aload	19
	ifnull	l5 // aload_0
	goto	l6 // aload
l4	aload	19
	invokevirtual	Method java/lang/Object.equals:(Ljava/lang/Object;)Z
	ifeq	l6 // aload
l5	aload_0
	invokevirtual	Method scala$reflect$generic$UnPickler$Scan$$$outer:()Lscala/reflect/generic/UnPickler;
	invokevirtual	Method scala/reflect/generic/UnPickler.global:()Lscala/reflect/generic/Universe;
	invokeinterface	InterfaceMethod scala/reflect/generic/Types.AnnotatedType:()Lscala/reflect/generic/Types$AnnotatedTypeExtractor;
	aload	18
	aload	17
	aload	15
	invokevirtual	Method scala/reflect/generic/Types$AnnotatedTypeExtractor.apply:(Lscala/collection/immutable/List;Lscala/reflect/generic/Types$AbsType;Lscala/reflect/generic/Symbols$AbsSymbol;)Lscala/reflect/generic/Types$AbsType;
	goto	l1 // areturn
l6	aload	17
	goto	l1 // areturn
	aload_0
	invokevirtual	Method readTypeRef:()Lscala/reflect/generic/Types$AbsType;
	astore	12
	aload_0
	iload_2
	new	class scala/reflect/generic/UnPickler$Scan$$anonfun$5
	dup
	aload_0
	invokespecial	Method scala/reflect/generic/UnPickler$Scan$$anonfun$5."<init>":(Lscala/reflect/generic/UnPickler$Scan;)V
	invokevirtual	Method until:(ILscala/Function0;)Lscala/collection/immutable/List;
	astore	13
	aload_0
	invokevirtual	Method scala$reflect$generic$UnPickler$Scan$$$outer:()Lscala/reflect/generic/UnPickler;
	invokevirtual	Method scala/reflect/generic/UnPickler.global:()Lscala/reflect/generic/Universe;
	invokeinterface	InterfaceMethod scala/reflect/generic/Types.PolyType:()Lscala/reflect/generic/Types$PolyTypeExtractor;
	aload	13
	aload	12
	invokevirtual	Method scala/reflect/generic/Types$PolyTypeExtractor.apply:(Lscala/collection/immutable/List;Lscala/reflect/generic/Types$AbsType;)Lscala/reflect/generic/Types$AbsType;
	goto	l1 // areturn
	aload_0
	invokevirtual	Method readTypeRef:()Lscala/reflect/generic/Types$AbsType;
	astore	9
	aload_0
	iload_2
	new	class scala/reflect/generic/UnPickler$Scan$$anonfun$4
	dup
	aload_0
	invokespecial	Method scala/reflect/generic/UnPickler$Scan$$anonfun$4."<init>":(Lscala/reflect/generic/UnPickler$Scan;)V
	invokevirtual	Method until:(ILscala/Function0;)Lscala/collection/immutable/List;
	astore	10
	aload	10
	aload_0
	invokevirtual	Method scala$reflect$generic$UnPickler$Scan$$$outer:()Lscala/reflect/generic/UnPickler;
	invokevirtual	Method scala/reflect/generic/UnPickler.global:()Lscala/reflect/generic/Universe;
	invokeinterface	InterfaceMethod scala/reflect/generic/Symbols.NoSymbol:()Lscala/reflect/generic/Symbols$AbsSymbol;
	invokeinterface	InterfaceMethod scala/collection/SeqLike.contains:(Ljava/lang/Object;)Z
	ifne	l7 // aload_0
	aload	9
	aload_0
	invokevirtual	Method scala$reflect$generic$UnPickler$Scan$$$outer:()Lscala/reflect/generic/UnPickler;
	invokevirtual	Method scala/reflect/generic/UnPickler.global:()Lscala/reflect/generic/Universe;
	invokeinterface	InterfaceMethod scala/reflect/generic/Types.NoType:()Lscala/reflect/generic/Types$AbsType;
	astore	11
	dup
	ifnonnull	l8 // aload
	pop
	aload	11
	ifnull	l7 // aload_0
	goto	l9 // aload_0
l8	aload	11
	invokevirtual	Method java/lang/Object.equals:(Ljava/lang/Object;)Z
	ifeq	l9 // aload_0
l7	aload_0
	invokevirtual	Method scala$reflect$generic$UnPickler$Scan$$$outer:()Lscala/reflect/generic/UnPickler;
	invokevirtual	Method scala/reflect/generic/UnPickler.global:()Lscala/reflect/generic/Universe;
	invokeinterface	InterfaceMethod scala/reflect/generic/Types.NoType:()Lscala/reflect/generic/Types$AbsType;
	goto	l1 // areturn
l9	aload_0
	invokevirtual	Method scala$reflect$generic$UnPickler$Scan$$$outer:()Lscala/reflect/generic/UnPickler;
	invokevirtual	Method scala/reflect/generic/UnPickler.global:()Lscala/reflect/generic/Universe;
	invokeinterface	InterfaceMethod scala/reflect/generic/Types.MethodType:()Lscala/reflect/generic/Types$MethodTypeExtractor;
	aload	10
	aload	9
	invokevirtual	Method scala/reflect/generic/Types$MethodTypeExtractor.apply:(Lscala/collection/immutable/List;Lscala/reflect/generic/Types$AbsType;)Lscala/reflect/generic/Types$AbsType;
	goto	l1 // areturn
	aload_0
	invokevirtual	Method readSymbolRef:()Lscala/reflect/generic/Symbols$AbsSymbol;
	astore	8
	aload_0
	invokevirtual	Method scala$reflect$generic$UnPickler$Scan$$$outer:()Lscala/reflect/generic/UnPickler;
	invokevirtual	Method scala/reflect/generic/UnPickler.global:()Lscala/reflect/generic/Universe;
	invokeinterface	InterfaceMethod scala/reflect/generic/Types.ClassInfoType:()Lscala/reflect/generic/Types$ClassInfoTypeExtractor;
	aload_0
	iload_2
	new	class scala/reflect/generic/UnPickler$Scan$$anonfun$readType$2
	dup
	aload_0
	invokespecial	Method scala/reflect/generic/UnPickler$Scan$$anonfun$readType$2."<init>":(Lscala/reflect/generic/UnPickler$Scan;)V
	invokevirtual	Method until:(ILscala/Function0;)Lscala/collection/immutable/List;
	aload_0
	aload	8
	invokevirtual	Method symScope:(Lscala/reflect/generic/Symbols$AbsSymbol;)Lscala/reflect/generic/Scopes$AbsScope;
	aload	8
	invokevirtual	Method scala/reflect/generic/Types$ClassInfoTypeExtractor.apply:(Lscala/collection/immutable/List;Lscala/reflect/generic/Scopes$AbsScope;Lscala/reflect/generic/Symbols$AbsSymbol;)Lscala/reflect/generic/Types$AbsType;
	goto	l1 // areturn
	aload_0
	invokevirtual	Method readSymbolRef:()Lscala/reflect/generic/Symbols$AbsSymbol;
	astore	7
	aload_0
	invokevirtual	Method scala$reflect$generic$UnPickler$Scan$$$outer:()Lscala/reflect/generic/UnPickler;
	invokevirtual	Method scala/reflect/generic/UnPickler.global:()Lscala/reflect/generic/Universe;
	invokeinterface	InterfaceMethod scala/reflect/generic/Types.RefinedType:()Lscala/reflect/generic/Types$RefinedTypeExtractor;
	aload_0
	iload_2
	new	class scala/reflect/generic/UnPickler$Scan$$anonfun$readType$1
	dup
	aload_0
	invokespecial	Method scala/reflect/generic/UnPickler$Scan$$anonfun$readType$1."<init>":(Lscala/reflect/generic/UnPickler$Scan;)V
	invokevirtual	Method until:(ILscala/Function0;)Lscala/collection/immutable/List;
	aload_0
	aload	7
	invokevirtual	Method symScope:(Lscala/reflect/generic/Symbols$AbsSymbol;)Lscala/reflect/generic/Scopes$AbsScope;
	aload	7
	invokevirtual	Method scala/reflect/generic/Types$RefinedTypeExtractor.apply:(Lscala/collection/immutable/List;Lscala/reflect/generic/Scopes$AbsScope;Lscala/reflect/generic/Symbols$AbsSymbol;)Lscala/reflect/generic/Types$AbsType;
	goto	l1 // areturn
	aload_0
	invokevirtual	Method scala$reflect$generic$UnPickler$Scan$$$outer:()Lscala/reflect/generic/UnPickler;
	invokevirtual	Method scala/reflect/generic/UnPickler.global:()Lscala/reflect/generic/Universe;
	invokeinterface	InterfaceMethod scala/reflect/generic/Types.TypeBounds:()Lscala/reflect/generic/Types$TypeBoundsExtractor;
	aload_0
	invokevirtual	Method readTypeRef:()Lscala/reflect/generic/Types$AbsType;
	aload_0
	invokevirtual	Method readTypeRef:()Lscala/reflect/generic/Types$AbsType;
	invokevirtual	Method scala/reflect/generic/Types$TypeBoundsExtractor.apply:(Lscala/reflect/generic/Types$AbsType;Lscala/reflect/generic/Types$AbsType;)Lscala/reflect/generic/Types$AbsType;
	goto	l1 // areturn
	aload_0
	invokevirtual	Method readTypeRef:()Lscala/reflect/generic/Types$AbsType;
	astore	4
	aload_0
	invokevirtual	Method readSymbolRef:()Lscala/reflect/generic/Symbols$AbsSymbol;
	astore	5
	aload_0
	iload_2
	new	class scala/reflect/generic/UnPickler$Scan$$anonfun$3
	dup
	aload_0
	invokespecial	Method scala/reflect/generic/UnPickler$Scan$$anonfun$3."<init>":(Lscala/reflect/generic/UnPickler$Scan;)V
	invokevirtual	Method until:(ILscala/Function0;)Lscala/collection/immutable/List;
	astore	6
	aload_0
	invokevirtual	Method scala$reflect$generic$UnPickler$Scan$$$outer:()Lscala/reflect/generic/UnPickler;
	invokevirtual	Method scala/reflect/generic/UnPickler.global:()Lscala/reflect/generic/Universe;
	invokeinterface	InterfaceMethod scala/reflect/generic/Types.TypeRef:()Lscala/reflect/generic/Types$TypeRefExtractor;
	aload	4
	aload	5
	aload	6
	invokevirtual	Method scala/reflect/generic/Types$TypeRefExtractor.apply:(Lscala/reflect/generic/Types$AbsType;Lscala/reflect/generic/Symbols$AbsSymbol;Lscala/collection/immutable/List;)Lscala/reflect/generic/Types$AbsType;
	goto	l1 // areturn
	aload_0
	invokevirtual	Method scala$reflect$generic$UnPickler$Scan$$$outer:()Lscala/reflect/generic/UnPickler;
	invokevirtual	Method scala/reflect/generic/UnPickler.global:()Lscala/reflect/generic/Universe;
	invokeinterface	InterfaceMethod scala/reflect/generic/Types.ConstantType:()Lscala/reflect/generic/Types$ConstantTypeExtractor;
	aload_0
	invokevirtual	Method readConstantRef:()Lscala/reflect/generic/Constants$Constant;
	invokevirtual	Method scala/reflect/generic/Types$ConstantTypeExtractor.apply:(Lscala/reflect/generic/Constants$Constant;)Lscala/reflect/generic/Types$AbsType;
	goto	l1 // areturn
	aload_0
	invokevirtual	Method scala$reflect$generic$UnPickler$Scan$$$outer:()Lscala/reflect/generic/UnPickler;
	invokevirtual	Method scala/reflect/generic/UnPickler.global:()Lscala/reflect/generic/Universe;
	invokeinterface	InterfaceMethod scala/reflect/generic/Types.SingleType:()Lscala/reflect/generic/Types$SingleTypeExtractor;
	aload_0
	invokevirtual	Method readTypeRef:()Lscala/reflect/generic/Types$AbsType;
	aload_0
	invokevirtual	Method readSymbolRef:()Lscala/reflect/generic/Symbols$AbsSymbol;
	invokevirtual	Method scala/reflect/generic/Types$SingleTypeExtractor.apply:(Lscala/reflect/generic/Types$AbsType;Lscala/reflect/generic/Symbols$AbsSymbol;)Lscala/reflect/generic/Types$AbsType;
	goto	l1 // areturn
	aload_0
	invokevirtual	Method scala$reflect$generic$UnPickler$Scan$$$outer:()Lscala/reflect/generic/UnPickler;
	invokevirtual	Method scala/reflect/generic/UnPickler.global:()Lscala/reflect/generic/Universe;
	invokeinterface	InterfaceMethod scala/reflect/generic/Types.ThisType:()Lscala/reflect/generic/Types$ThisTypeExtractor;
	aload_0
	invokevirtual	Method readSymbolRef:()Lscala/reflect/generic/Symbols$AbsSymbol;
	invokevirtual	Method scala/reflect/generic/Types$ThisTypeExtractor.apply:(Lscala/reflect/generic/Symbols$AbsSymbol;)Lscala/reflect/generic/Types$AbsType;
	goto	l1 // areturn
	aload_0
	invokevirtual	Method scala$reflect$generic$UnPickler$Scan$$$outer:()Lscala/reflect/generic/UnPickler;
	invokevirtual	Method scala/reflect/generic/UnPickler.global:()Lscala/reflect/generic/Universe;
	invokeinterface	InterfaceMethod scala/reflect/generic/Types.NoPrefix:()Lscala/reflect/generic/Types$AbsType;
	goto	l1 // areturn
	aload_0
	invokevirtual	Method scala$reflect$generic$UnPickler$Scan$$$outer:()Lscala/reflect/generic/UnPickler;
	invokevirtual	Method scala/reflect/generic/UnPickler.global:()Lscala/reflect/generic/Universe;
	invokeinterface	InterfaceMethod scala/reflect/generic/Types.NoType:()Lscala/reflect/generic/Types$AbsType;
l1	areturn
  Labels:
   	l2 = 275 // aload_0
   	l3 = 287 // astore
   	l4 = 352 // aload
   	l5 = 360 // aload_0
   	l6 = 384 // aload
   	l8 = 504 // aload
   	l7 = 512 // aload_0
   	l9 = 527 // aload_0
   	l1 = 813 // areturn
  LocalVariableTable: 
   Start  Length  Slot  Name   Signature
   0      814      0    this       Lscala/reflect/generic/UnPickler$Scan;
   5      809      1    tag       I
   15      799      2    end       I
   17      797      3    temp8       I
   671      42      4    pre       Lscala/reflect/generic/Types$AbsType;
   677      36      5    sym       Lscala/reflect/generic/Symbols$AbsSymbol;
   692      21      6    args       Lscala/collection/immutable/List;
   600      36      7    clazz       Lscala/reflect/generic/Symbols$AbsSymbol;
   555      36      8    clazz       Lscala/reflect/generic/Symbols$AbsSymbol;
   438      111      9    restpe       Lscala/reflect/generic/Types$AbsType;
   453      96      10    params       Lscala/collection/immutable/List;
   395      34      12    restpe       Lscala/reflect/generic/Types$AbsType;
   410      19      13    typeParams       Lscala/collection/immutable/List;
   236      153      14    typeRef       I
   289      100      15    selfsym       Lscala/reflect/generic/Symbols$AbsSymbol;
   264      8      16    s       Lscala/reflect/generic/Symbols$AbsSymbol;
   308      81      17    tp       Lscala/reflect/generic/Types$AbsType;
   323      66      18    annots       Lscala/collection/immutable/List;
   202      25      20    thistpe       Lscala/reflect/generic/Types$AbsType;
   208      19      21    supertpe       Lscala/reflect/generic/Types$AbsType;
   163      30      22    restpe       Lscala/reflect/generic/Types$AbsType;


public scala.reflect.generic.Types$AbsType noSuchTypeTag(int, int);
  Signature: (II)Lscala/reflect/generic/Types$AbsType;
  Code:
   Stack=3, Locals=3, Args_size=3
	aload_0
	new	class scala/collection/mutable/StringBuilder
	dup
	invokespecial	Method scala/collection/mutable/StringBuilder."<init>":()V
	ldc_w	String bad type tag: 
	invokevirtual	Method scala/collection/mutable/StringBuilder.append:(Ljava/lang/Object;)Lscala/collection/mutable/StringBuilder;
	iload_1
	invokestatic	Method scala/runtime/BoxesRunTime.boxToInteger:(I)Ljava/lang/Integer;
	invokevirtual	Method scala/collection/mutable/StringBuilder.append:(Ljava/lang/Object;)Lscala/collection/mutable/StringBuilder;
	invokevirtual	Method scala/collection/mutable/StringBuilder.toString:()Ljava/lang/String;
	invokevirtual	Method errorBadSignature:(Ljava/lang/String;)Lscala/runtime/Nothing$;
	athrow
  Labels:
  LocalVariableTable: 
   Start  Length  Slot  Name   Signature
   0      28      0    this       Lscala/reflect/generic/UnPickler$Scan;
   0      28      1    tag       I
   0      28      2    end       I


public scala.reflect.generic.Constants$Constant readConstant();
  Signature: ()Lscala/reflect/generic/Constants$Constant;
  Code:
   Stack=7, Locals=4, Args_size=1
	aload_0
	invokevirtual	Method readByte:()I
	istore_1
	aload_0
	invokevirtual	Method readNat:()I
	istore_2
	iload_1
	istore_3
	iload_3
	tableswitch{ //24 to 36
		24: 399;
		25: 364;
		26: 337;
		27: 310;
		28: 283;
		29: 257;
		30: 232;
		31: 203;
		32: 175;
		33: 151;
		34: 131;
		35: 110;
		36: 89;
		default: 80 }
	aload_0
	iload_1
	iload_2
	invokevirtual	Method noSuchConstantTag:(II)Lscala/reflect/generic/Constants$Constant;
	goto	l1 // areturn
	new	class scala/reflect/generic/Constants$Constant
	dup
	aload_0
	invokevirtual	Method scala$reflect$generic$UnPickler$Scan$$$outer:()Lscala/reflect/generic/UnPickler;
	invokevirtual	Method scala/reflect/generic/UnPickler.global:()Lscala/reflect/generic/Universe;
	aload_0
	invokevirtual	Method readSymbolRef:()Lscala/reflect/generic/Symbols$AbsSymbol;
	invokespecial	Method scala/reflect/generic/Constants$Constant."<init>":(Lscala/reflect/generic/Universe;Ljava/lang/Object;)V
	goto	l1 // areturn
	new	class scala/reflect/generic/Constants$Constant
	dup
	aload_0
	invokevirtual	Method scala$reflect$generic$UnPickler$Scan$$$outer:()Lscala/reflect/generic/UnPickler;
	invokevirtual	Method scala/reflect/generic/UnPickler.global:()Lscala/reflect/generic/Universe;
	aload_0
	invokevirtual	Method readTypeRef:()Lscala/reflect/generic/Types$AbsType;
	invokespecial	Method scala/reflect/generic/Constants$Constant."<init>":(Lscala/reflect/generic/Universe;Ljava/lang/Object;)V
	goto	l1 // areturn
	new	class scala/reflect/generic/Constants$Constant
	dup
	aload_0
	invokevirtual	Method scala$reflect$generic$UnPickler$Scan$$$outer:()Lscala/reflect/generic/UnPickler;
	invokevirtual	Method scala/reflect/generic/UnPickler.global:()Lscala/reflect/generic/Universe;
	aconst_null
	pop
	aconst_null
	invokespecial	Method scala/reflect/generic/Constants$Constant."<init>":(Lscala/reflect/generic/Universe;Ljava/lang/Object;)V
	goto	l1 // areturn
	new	class scala/reflect/generic/Constants$Constant
	dup
	aload_0
	invokevirtual	Method scala$reflect$generic$UnPickler$Scan$$$outer:()Lscala/reflect/generic/UnPickler;
	invokevirtual	Method scala/reflect/generic/UnPickler.global:()Lscala/reflect/generic/Universe;
	aload_0
	invokevirtual	Method readNameRef:()Ljava/lang/Object;
	invokevirtual	Method java/lang/Object.toString:()Ljava/lang/String;
	invokespecial	Method scala/reflect/generic/Constants$Constant."<init>":(Lscala/reflect/generic/Universe;Ljava/lang/Object;)V
	goto	l1 // areturn
	new	class scala/reflect/generic/Constants$Constant
	dup
	aload_0
	invokevirtual	Method scala$reflect$generic$UnPickler$Scan$$$outer:()Lscala/reflect/generic/UnPickler;
	invokevirtual	Method scala/reflect/generic/UnPickler.global:()Lscala/reflect/generic/Universe;
	aload_0
	iload_2
	invokevirtual	Method readLong:(I)J
	invokestatic	Method java/lang/Double.longBitsToDouble:(J)D
	invokestatic	Method scala/runtime/BoxesRunTime.boxToDouble:(D)Ljava/lang/Double;
	invokespecial	Method scala/reflect/generic/Constants$Constant."<init>":(Lscala/reflect/generic/Universe;Ljava/lang/Object;)V
	goto	l1 // areturn
	new	class scala/reflect/generic/Constants$Constant
	dup
	aload_0
	invokevirtual	Method scala$reflect$generic$UnPickler$Scan$$$outer:()Lscala/reflect/generic/UnPickler;
	invokevirtual	Method scala/reflect/generic/UnPickler.global:()Lscala/reflect/generic/Universe;
	aload_0
	iload_2
	invokevirtual	Method readLong:(I)J
	l2i
	invokestatic	Method java/lang/Float.intBitsToFloat:(I)F
	invokestatic	Method scala/runtime/BoxesRunTime.boxToFloat:(F)Ljava/lang/Float;
	invokespecial	Method scala/reflect/generic/Constants$Constant."<init>":(Lscala/reflect/generic/Universe;Ljava/lang/Object;)V
	goto	l1 // areturn
	new	class scala/reflect/generic/Constants$Constant
	dup
	aload_0
	invokevirtual	Method scala$reflect$generic$UnPickler$Scan$$$outer:()Lscala/reflect/generic/UnPickler;
	invokevirtual	Method scala/reflect/generic/UnPickler.global:()Lscala/reflect/generic/Universe;
	aload_0
	iload_2
	invokevirtual	Method readLong:(I)J
	invokestatic	Method scala/runtime/BoxesRunTime.boxToLong:(J)Ljava/lang/Long;
	invokespecial	Method scala/reflect/generic/Constants$Constant."<init>":(Lscala/reflect/generic/Universe;Ljava/lang/Object;)V
	goto	l1 // areturn
	new	class scala/reflect/generic/Constants$Constant
	dup
	aload_0
	invokevirtual	Method scala$reflect$generic$UnPickler$Scan$$$outer:()Lscala/reflect/generic/UnPickler;
	invokevirtual	Method scala/reflect/generic/UnPickler.global:()Lscala/reflect/generic/Universe;
	aload_0
	iload_2
	invokevirtual	Method readLong:(I)J
	l2i
	invokestatic	Method scala/runtime/BoxesRunTime.boxToInteger:(I)Ljava/lang/Integer;
	invokespecial	Method scala/reflect/generic/Constants$Constant."<init>":(Lscala/reflect/generic/Universe;Ljava/lang/Object;)V
	goto	l1 // areturn
	new	class scala/reflect/generic/Constants$Constant
	dup
	aload_0
	invokevirtual	Method scala$reflect$generic$UnPickler$Scan$$$outer:()Lscala/reflect/generic/UnPickler;
	invokevirtual	Method scala/reflect/generic/UnPickler.global:()Lscala/reflect/generic/Universe;
	aload_0
	iload_2
	invokevirtual	Method readLong:(I)J
	l2i
	i2c
	invokestatic	Method scala/runtime/BoxesRunTime.boxToCharacter:(C)Ljava/lang/Character;
	invokespecial	Method scala/reflect/generic/Constants$Constant."<init>":(Lscala/reflect/generic/Universe;Ljava/lang/Object;)V
	goto	l1 // areturn
	new	class scala/reflect/generic/Constants$Constant
	dup
	aload_0
	invokevirtual	Method scala$reflect$generic$UnPickler$Scan$$$outer:()Lscala/reflect/generic/UnPickler;
	invokevirtual	Method scala/reflect/generic/UnPickler.global:()Lscala/reflect/generic/Universe;
	aload_0
	iload_2
	invokevirtual	Method readLong:(I)J
	l2i
	i2s
	invokestatic	Method scala/runtime/BoxesRunTime.boxToShort:(S)Ljava/lang/Short;
	invokespecial	Method scala/reflect/generic/Constants$Constant."<init>":(Lscala/reflect/generic/Universe;Ljava/lang/Object;)V
	goto	l1 // areturn
	new	class scala/reflect/generic/Constants$Constant
	dup
	aload_0
	invokevirtual	Method scala$reflect$generic$UnPickler$Scan$$$outer:()Lscala/reflect/generic/UnPickler;
	invokevirtual	Method scala/reflect/generic/UnPickler.global:()Lscala/reflect/generic/Universe;
	aload_0
	iload_2
	invokevirtual	Method readLong:(I)J
	l2i
	i2b
	invokestatic	Method scala/runtime/BoxesRunTime.boxToByte:(B)Ljava/lang/Byte;
	invokespecial	Method scala/reflect/generic/Constants$Constant."<init>":(Lscala/reflect/generic/Universe;Ljava/lang/Object;)V
	goto	l1 // areturn
	new	class scala/reflect/generic/Constants$Constant
	dup
	aload_0
	invokevirtual	Method scala$reflect$generic$UnPickler$Scan$$$outer:()Lscala/reflect/generic/UnPickler;
	invokevirtual	Method scala/reflect/generic/UnPickler.global:()Lscala/reflect/generic/Universe;
	aload_0
	iload_2
	invokevirtual	Method readLong:(I)J
	lconst_0
	lcmp
	ifeq	l2 // iconst_0
	iconst_1
	goto	l3 // invokestatic
l2	iconst_0
l3	invokestatic	Method scala/runtime/BoxesRunTime.boxToBoolean:(Z)Ljava/lang/Boolean;
	invokespecial	Method scala/reflect/generic/Constants$Constant."<init>":(Lscala/reflect/generic/Universe;Ljava/lang/Object;)V
	goto	l1 // areturn
	new	class scala/reflect/generic/Constants$Constant
	dup
	aload_0
	invokevirtual	Method scala$reflect$generic$UnPickler$Scan$$$outer:()Lscala/reflect/generic/UnPickler;
	invokevirtual	Method scala/reflect/generic/UnPickler.global:()Lscala/reflect/generic/Universe;
	getstatic	Field scala/runtime/BoxedUnit.UNIT:Lscala/runtime/BoxedUnit;
	invokespecial	Method scala/reflect/generic/Constants$Constant."<init>":(Lscala/reflect/generic/Universe;Ljava/lang/Object;)V
l1	areturn
  Labels:
   	l2 = 389 // iconst_0
   	l3 = 390 // invokestatic
   	l1 = 416 // areturn
  LocalVariableTable: 
   Start  Length  Slot  Name   Signature
   0      417      0    this       Lscala/reflect/generic/UnPickler$Scan;
   5      412      1    tag       I
   10      407      2    len       I
   12      405      3    temp9       I


public scala.reflect.generic.Constants$Constant noSuchConstantTag(int, int);
  Signature: (II)Lscala/reflect/generic/Constants$Constant;
  Code:
   Stack=3, Locals=3, Args_size=3
	aload_0
	new	class scala/collection/mutable/StringBuilder
	dup
	invokespecial	Method scala/collection/mutable/StringBuilder."<init>":()V
	ldc_w	String bad constant tag: 
	invokevirtual	Method scala/collection/mutable/StringBuilder.append:(Ljava/lang/Object;)Lscala/collection/mutable/StringBuilder;
	iload_1
	invokestatic	Method scala/runtime/BoxesRunTime.boxToInteger:(I)Ljava/lang/Integer;
	invokevirtual	Method scala/collection/mutable/StringBuilder.append:(Ljava/lang/Object;)Lscala/collection/mutable/StringBuilder;
	invokevirtual	Method scala/collection/mutable/StringBuilder.toString:()Ljava/lang/String;
	invokevirtual	Method errorBadSignature:(Ljava/lang/String;)Lscala/runtime/Nothing$;
	athrow
  Labels:
  LocalVariableTable: 
   Start  Length  Slot  Name   Signature
   0      28      0    this       Lscala/reflect/generic/UnPickler$Scan;
   0      28      1    tag       I
   0      28      2    len       I


public void readChildren();
  Signature: ()V
  Code:
   Stack=3, Locals=4, Args_size=1
	aload_0
	invokevirtual	Method readByte:()I
	istore_1
	getstatic	Field scala/Predef$.MODULE$:Lscala/Predef$;
	iload_1
	ldc	int 41
	if_icmpne	l1 // iconst_0
	iconst_1
	goto	l2 // invokevirtual
l1	iconst_0
l2	invokevirtual	Method scala/Predef$.assert:(Z)V
	aload_0
	invokevirtual	Method readNat:()I
	aload_0
	invokevirtual	Method readIndex:()I
	iadd
	istore_2
	aload_0
	invokevirtual	Method readSymbolRef:()Lscala/reflect/generic/Symbols$AbsSymbol;
	astore_3
l4	aload_0
	invokevirtual	Method readIndex:()I
	iload_2
	if_icmpeq	l3 // return
	aload_3
	aload_0
	invokevirtual	Method readSymbolRef:()Lscala/reflect/generic/Symbols$AbsSymbol;
	invokevirtual	Method scala/reflect/generic/Symbols$AbsSymbol.addChild:(Lscala/reflect/generic/Symbols$AbsSymbol;)V
	goto	l4 // aload_0
l3	return
  Labels:
   	l1 = 18 // iconst_0
   	l2 = 19 // invokevirtual
   	l4 = 37 // aload_0
   	l3 = 56 // return
  LocalVariableTable: 
   Start  Length  Slot  Name   Signature
   0      57      0    this       Lscala/reflect/generic/UnPickler$Scan;
   5      52      1    tag       I
   32      25      2    end       I
   37      20      3    target       Lscala/reflect/generic/Symbols$AbsSymbol;


public scala.reflect.generic.Trees$Tree readAnnotArg(int);
  Signature: (I)Lscala/reflect/generic/Trees$Tree;
  Code:
   Stack=5, Locals=3, Args_size=2
	aload_0
	getfield	Field bytes:[B
	aload_0
	invokespecial	Method index:()[I
	iload_1
	iaload
	baload
	ldc_w	int 49
	if_icmpne	l1 // aload_0
	aload_0
	iload_1
	new	class scala/reflect/generic/UnPickler$Scan$$anonfun$readAnnotArg$1
	dup
	aload_0
	invokespecial	Method scala/reflect/generic/UnPickler$Scan$$anonfun$readAnnotArg$1."<init>":(Lscala/reflect/generic/UnPickler$Scan;)V
	invokevirtual	Method at:(ILscala/Function0;)Ljava/lang/Object;
	checkcast	class scala/reflect/generic/Trees$Tree
	goto	l2 // areturn
l1	aload_0
	iload_1
	new	class scala/reflect/generic/UnPickler$Scan$$anonfun$9
	dup
	aload_0
	invokespecial	Method scala/reflect/generic/UnPickler$Scan$$anonfun$9."<init>":(Lscala/reflect/generic/UnPickler$Scan;)V
	invokevirtual	Method at:(ILscala/Function0;)Ljava/lang/Object;
	checkcast	class scala/reflect/generic/Constants$Constant
	astore_2
	new	class scala/reflect/generic/Trees$Literal
	dup
	aload_0
	invokevirtual	Method scala$reflect$generic$UnPickler$Scan$$$outer:()Lscala/reflect/generic/UnPickler;
	invokevirtual	Method scala/reflect/generic/UnPickler.global:()Lscala/reflect/generic/Universe;
	aload_2
	invokespecial	Method scala/reflect/generic/Trees$Literal."<init>":(Lscala/reflect/generic/Universe;Lscala/reflect/generic/Constants$Constant;)V
	aload_2
	invokevirtual	Method scala/reflect/generic/Constants$Constant.tpe:()Lscala/reflect/generic/Types$AbsType;
	invokevirtual	Method scala/reflect/generic/Trees$Literal.setType:(Lscala/reflect/generic/Types$AbsType;)Lscala/reflect/generic/Trees$Tree;
l2	areturn
  Labels:
   	l1 = 36 // aload_0
   	l2 = 75 // areturn
  LocalVariableTable: 
   Start  Length  Slot  Name   Signature
   0      76      0    this       Lscala/reflect/generic/UnPickler$Scan;
   0      76      1    i       I
   53      22      2    const       Lscala/reflect/generic/Constants$Constant;


public java.lang.Object readClassfileAnnotArg(int);
  Signature: (I)Ljava/lang/Object;
  Code:
   Stack=6, Locals=3, Args_size=2
	aload_0
	getfield	Field bytes:[B
	aload_0
	invokespecial	Method index:()[I
	iload_1
	iaload
	baload
	istore_2
	iload_2
	ldc_w	int 43
	if_icmpne	l1 // iload_2
	aload_0
	invokevirtual	Method scala$reflect$generic$UnPickler$Scan$$$outer:()Lscala/reflect/generic/UnPickler;
	invokevirtual	Method scala/reflect/generic/UnPickler.global:()Lscala/reflect/generic/Universe;
	invokeinterface	InterfaceMethod scala/reflect/generic/AnnotationInfos.NestedAnnotArg:()Lscala/reflect/generic/AnnotationInfos$NestedAnnotArgExtractor;
	aload_0
	iload_1
	new	class scala/reflect/generic/UnPickler$Scan$$anonfun$readClassfileAnnotArg$1
	dup
	aload_0
	invokespecial	Method scala/reflect/generic/UnPickler$Scan$$anonfun$readClassfileAnnotArg$1."<init>":(Lscala/reflect/generic/UnPickler$Scan;)V
	invokevirtual	Method at:(ILscala/Function0;)Ljava/lang/Object;
	invokevirtual	Method scala/reflect/generic/AnnotationInfos$NestedAnnotArgExtractor.apply:(Ljava/lang/Object;)Ljava/lang/Object;
	goto	l2 // areturn
l1	iload_2
	ldc_w	int 44
	if_icmpne	l3 // aload_0
	aload_0
	iload_1
	new	class scala/reflect/generic/UnPickler$Scan$$anonfun$readClassfileAnnotArg$2
	dup
	aload_0
	invokespecial	Method scala/reflect/generic/UnPickler$Scan$$anonfun$readClassfileAnnotArg$2."<init>":(Lscala/reflect/generic/UnPickler$Scan;)V
	invokevirtual	Method at:(ILscala/Function0;)Ljava/lang/Object;
	goto	l2 // areturn
l3	aload_0
	invokevirtual	Method scala$reflect$generic$UnPickler$Scan$$$outer:()Lscala/reflect/generic/UnPickler;
	invokevirtual	Method scala/reflect/generic/UnPickler.global:()Lscala/reflect/generic/Universe;
	invokeinterface	InterfaceMethod scala/reflect/generic/AnnotationInfos.LiteralAnnotArg:()Lscala/reflect/generic/AnnotationInfos$LiteralAnnotArgExtractor;
	aload_0
	iload_1
	new	class scala/reflect/generic/UnPickler$Scan$$anonfun$readClassfileAnnotArg$3
	dup
	aload_0
	invokespecial	Method scala/reflect/generic/UnPickler$Scan$$anonfun$readClassfileAnnotArg$3."<init>":(Lscala/reflect/generic/UnPickler$Scan;)V
	invokevirtual	Method at:(ILscala/Function0;)Ljava/lang/Object;
	checkcast	class scala/reflect/generic/Constants$Constant
	invokevirtual	Method scala/reflect/generic/AnnotationInfos$LiteralAnnotArgExtractor.apply:(Lscala/reflect/generic/Constants$Constant;)Ljava/lang/Object;
l2	areturn
  Labels:
   	l1 = 50 // iload_2
   	l3 = 73 // aload_0
   	l2 = 104 // areturn
  LocalVariableTable: 
   Start  Length  Slot  Name   Signature
   0      105      0    this       Lscala/reflect/generic/UnPickler$Scan;
   0      105      1    i       I
   12      93      2    temp10       B


public java.lang.Object readAnnotationInfo(int);
  Signature: (I)Ljava/lang/Object;
  Code:
   Stack=5, Locals=8, Args_size=2
	aload_0
	invokevirtual	Method readTypeRef:()Lscala/reflect/generic/Types$AbsType;
	astore_2
	new	class scala/collection/mutable/ListBuffer
	dup
	invokespecial	Method scala/collection/mutable/ListBuffer."<init>":()V
	astore_3
	new	class scala/collection/mutable/ListBuffer
	dup
	invokespecial	Method scala/collection/mutable/ListBuffer."<init>":()V
	astore	4
l4	aload_0
	invokevirtual	Method readIndex:()I
	iload_1
	if_icmpeq	l1 // aload_0
	aload_0
	invokevirtual	Method readNat:()I
	istore	5
	aload_0
	iload	5
	invokevirtual	Method isNameEntry:(I)Z
	ifeq	l2 // aload_3
	aload_0
	iload	5
	new	class scala/reflect/generic/UnPickler$Scan$$anonfun$10
	dup
	aload_0
	invokespecial	Method scala/reflect/generic/UnPickler$Scan$$anonfun$10."<init>":(Lscala/reflect/generic/UnPickler$Scan;)V
	invokevirtual	Method at:(ILscala/Function0;)Ljava/lang/Object;
	astore	6
	aload_0
	aload_0
	invokevirtual	Method readNat:()I
	invokevirtual	Method readClassfileAnnotArg:(I)Ljava/lang/Object;
	astore	7
	aload	4
	new	class scala/Tuple2
	dup
	aload	6
	aload	7
	invokespecial	Method scala/Tuple2."<init>":(Ljava/lang/Object;Ljava/lang/Object;)V
	invokevirtual	Method scala/collection/mutable/ListBuffer.$plus$eq:(Ljava/lang/Object;)Lscala/collection/mutable/ListBuffer;
	goto	l3 // pop
l2	aload_3
	aload_0
	iload	5
	invokevirtual	Method readAnnotArg:(I)Lscala/reflect/generic/Trees$Tree;
	invokevirtual	Method scala/collection/mutable/ListBuffer.$plus$eq:(Ljava/lang/Object;)Lscala/collection/mutable/ListBuffer;
l3	pop
	goto	l4 // aload_0
l1	aload_0
	invokevirtual	Method scala$reflect$generic$UnPickler$Scan$$$outer:()Lscala/reflect/generic/UnPickler;
	invokevirtual	Method scala/reflect/generic/UnPickler.global:()Lscala/reflect/generic/Universe;
	invokeinterface	InterfaceMethod scala/reflect/generic/AnnotationInfos.AnnotationInfo:()Lscala/reflect/generic/AnnotationInfos$AnnotationInfoExtractor;
	aload_2
	aload_3
	invokevirtual	Method scala/collection/mutable/ListBuffer.toList:()Lscala/collection/immutable/List;
	aload	4
	invokevirtual	Method scala/collection/mutable/ListBuffer.toList:()Lscala/collection/immutable/List;
	invokevirtual	Method scala/reflect/generic/AnnotationInfos$AnnotationInfoExtractor.apply:(Lscala/reflect/generic/Types$AbsType;Lscala/collection/immutable/List;Lscala/collection/immutable/List;)Ljava/lang/Object;
	areturn
  Labels:
   	l4 = 22 // aload_0
   	l2 = 90 // aload_3
   	l3 = 100 // pop
   	l1 = 104 // aload_0
  LocalVariableTable: 
   Start  Length  Slot  Name   Signature
   0      130      0    this       Lscala/reflect/generic/UnPickler$Scan;
   0      130      1    end       I
   5      124      2    atp       Lscala/reflect/generic/Types$AbsType;
   13      116      3    args       Lscala/collection/mutable/ListBuffer;
   22      107      4    assocs       Lscala/collection/mutable/ListBuffer;
   36      65      5    argref       I
   61      26      6    name       Ljava/lang/Object;
   71      16      7    arg       Ljava/lang/Object;


public void readSymbolAnnotation();
  Signature: ()V
  Code:
   Stack=3, Locals=4, Args_size=1
	aload_0
	invokevirtual	Method readByte:()I
	istore_1
	iload_1
	ldc	int 40
	if_icmpeq	l1 // aload_0
	aload_0
	new	class scala/collection/mutable/StringBuilder
	dup
	invokespecial	Method scala/collection/mutable/StringBuilder."<init>":()V
	ldc_w	String symbol annotation expected (
	invokevirtual	Method scala/collection/mutable/StringBuilder.append:(Ljava/lang/Object;)Lscala/collection/mutable/StringBuilder;
	iload_1
	invokestatic	Method scala/runtime/BoxesRunTime.boxToInteger:(I)Ljava/lang/Integer;
	invokevirtual	Method scala/collection/mutable/StringBuilder.append:(Ljava/lang/Object;)Lscala/collection/mutable/StringBuilder;
	ldc_w	String )
	invokevirtual	Method scala/collection/mutable/StringBuilder.append:(Ljava/lang/Object;)Lscala/collection/mutable/StringBuilder;
	invokevirtual	Method scala/collection/mutable/StringBuilder.toString:()Ljava/lang/String;
	invokevirtual	Method errorBadSignature:(Ljava/lang/String;)Lscala/runtime/Nothing$;
	athrow
l1	aload_0
	invokevirtual	Method readNat:()I
	aload_0
	invokevirtual	Method readIndex:()I
	iadd
	istore_2
	aload_0
	invokevirtual	Method readSymbolRef:()Lscala/reflect/generic/Symbols$AbsSymbol;
	astore_3
	aload_3
	aload_0
	iload_2
	invokevirtual	Method readAnnotationInfo:(I)Ljava/lang/Object;
	invokevirtual	Method scala/reflect/generic/Symbols$AbsSymbol.addAnnotation:(Ljava/lang/Object;)V
	return
  Labels:
   	l1 = 45 // aload_0
  LocalVariableTable: 
   Start  Length  Slot  Name   Signature
   0      70      0    this       Lscala/reflect/generic/UnPickler$Scan;
   5      64      1    tag       I
   55      14      2    end       I
   60      9      3    target       Lscala/reflect/generic/Symbols$AbsSymbol;


public java.lang.Object readAnnotation();
  Signature: ()Ljava/lang/Object;
  Code:
   Stack=3, Locals=3, Args_size=1
	aload_0
	invokevirtual	Method readByte:()I
	istore_1
	iload_1
	ldc_w	int 43
	if_icmpeq	l1 // aload_0
	aload_0
	new	class scala/collection/mutable/StringBuilder
	dup
	invokespecial	Method scala/collection/mutable/StringBuilder."<init>":()V
	ldc_w	String annotation expected (
	invokevirtual	Method scala/collection/mutable/StringBuilder.append:(Ljava/lang/Object;)Lscala/collection/mutable/StringBuilder;
	iload_1
	invokestatic	Method scala/runtime/BoxesRunTime.boxToInteger:(I)Ljava/lang/Integer;
	invokevirtual	Method scala/collection/mutable/StringBuilder.append:(Ljava/lang/Object;)Lscala/collection/mutable/StringBuilder;
	ldc_w	String )
	invokevirtual	Method scala/collection/mutable/StringBuilder.append:(Ljava/lang/Object;)Lscala/collection/mutable/StringBuilder;
	invokevirtual	Method scala/collection/mutable/StringBuilder.toString:()Ljava/lang/String;
	invokevirtual	Method errorBadSignature:(Ljava/lang/String;)Lscala/runtime/Nothing$;
	athrow
l1	aload_0
	invokevirtual	Method readNat:()I
	aload_0
	invokevirtual	Method readIndex:()I
	iadd
	istore_2
	aload_0
	iload_2
	invokevirtual	Method readAnnotationInfo:(I)Ljava/lang/Object;
	areturn
  Labels:
   	l1 = 46 // aload_0
  LocalVariableTable: 
   Start  Length  Slot  Name   Signature
   0      62      0    this       Lscala/reflect/generic/UnPickler$Scan;
   5      56      1    tag       I
   56      5      2    end       I


public scala.reflect.generic.Trees$Tree readTree();
  Signature: ()Lscala/reflect/generic/Trees$Tree;
  Code:
   Stack=9, Locals=73, Args_size=1
	aload_0
	invokevirtual	Method readByte:()I
	istore_1
	iload_1
	ldc_w	int 49
	if_icmpeq	l1 // aload_0
	aload_0
	new	class scala/collection/mutable/StringBuilder
	dup
	invokespecial	Method scala/collection/mutable/StringBuilder."<init>":()V
	ldc_w	String tree expected (
	invokevirtual	Method scala/collection/mutable/StringBuilder.append:(Ljava/lang/Object;)Lscala/collection/mutable/StringBuilder;
	iload_1
	invokestatic	Method scala/runtime/BoxesRunTime.boxToInteger:(I)Ljava/lang/Integer;
	invokevirtual	Method scala/collection/mutable/StringBuilder.append:(Ljava/lang/Object;)Lscala/collection/mutable/StringBuilder;
	ldc_w	String )
	invokevirtual	Method scala/collection/mutable/StringBuilder.append:(Ljava/lang/Object;)Lscala/collection/mutable/StringBuilder;
	invokevirtual	Method scala/collection/mutable/StringBuilder.toString:()Ljava/lang/String;
	invokevirtual	Method errorBadSignature:(Ljava/lang/String;)Lscala/runtime/Nothing$;
	athrow
l1	aload_0
	invokevirtual	Method readNat:()I
	aload_0
	invokevirtual	Method readIndex:()I
	iadd
	istore_2
	aload_0
	invokevirtual	Method readByte:()I
	istore_3
	iload_3
	iconst_1
	if_icmpne	l2 // aload_0
	aload_0
	invokevirtual	Method scala$reflect$generic$UnPickler$Scan$$$outer:()Lscala/reflect/generic/UnPickler;
	invokevirtual	Method scala/reflect/generic/UnPickler.global:()Lscala/reflect/generic/Universe;
	invokeinterface	InterfaceMethod scala/reflect/generic/Types.NoType:()Lscala/reflect/generic/Types$AbsType;
	goto	l3 // astore
l2	aload_0
	invokevirtual	Method readTypeRef:()Lscala/reflect/generic/Types$AbsType;
l3	astore	4
	new	class scala/runtime/ObjectRef
	dup
	aconst_null
	pop
	aconst_null
	invokespecial	Method scala/runtime/ObjectRef."<init>":(Ljava/lang/Object;)V
	astore	5
	new	class scala/runtime/ObjectRef
	dup
	aconst_null
	pop
	aconst_null
	invokespecial	Method scala/runtime/ObjectRef."<init>":(Ljava/lang/Object;)V
	astore	6
	new	class scala/runtime/ObjectRef
	dup
	aconst_null
	pop
	aconst_null
	invokespecial	Method scala/runtime/ObjectRef."<init>":(Ljava/lang/Object;)V
	astore	7
	iload_3
	istore	9
	iload	9
	tableswitch{ //1 to 45
		1: 2035;
		2: 1984;
		3: 1919;
		4: 1875;
		5: 1819;
		6: 1723;
		7: 1658;
		8: 1603;
		9: 1555;
		10: 324;
		11: 324;
		12: 1487;
		13: 1445;
		14: 1404;
		15: 324;
		16: 1374;
		17: 1353;
		18: 1319;
		19: 1277;
		20: 1235;
		21: 1187;
		22: 1154;
		23: 1113;
		24: 1071;
		25: 1044;
		26: 994;
		27: 973;
		28: 952;
		29: 919;
		30: 877;
		31: 778;
		32: 730;
		33: 691;
		34: 664;
		35: 625;
		36: 595;
		37: 574;
		38: 556;
		39: 523;
		40: 502;
		41: 469;
		42: 448;
		43: 406;
		44: 373;
		45: 331;
		default: 324 }
	aload_0
	iload_3
	iload_2
	invokevirtual	Method noSuchTreeTag:(II)Lscala/runtime/Nothing$;
	athrow
	aload_0
	invokevirtual	Method readTreeRef:()Lscala/reflect/generic/Trees$Tree;
	astore	70
	aload_0
	iload_2
	new	class scala/reflect/generic/UnPickler$Scan$$anonfun$32
	dup
	aload_0
	invokespecial	Method scala/reflect/generic/UnPickler$Scan$$anonfun$32."<init>":(Lscala/reflect/generic/UnPickler$Scan;)V
	invokevirtual	Method until:(ILscala/Function0;)Lscala/collection/immutable/List;
	astore	71
	new	class scala/reflect/generic/Trees$ExistentialTypeTree
	dup
	aload_0
	invokevirtual	Method scala$reflect$generic$UnPickler$Scan$$$outer:()Lscala/reflect/generic/UnPickler;
	invokevirtual	Method scala/reflect/generic/UnPickler.global:()Lscala/reflect/generic/Universe;
	aload	70
	aload	71
	invokespecial	Method scala/reflect/generic/Trees$ExistentialTypeTree."<init>":(Lscala/reflect/generic/Universe;Lscala/reflect/generic/Trees$Tree;Lscala/collection/immutable/List;)V
	goto	l4 // astore
	aload_0
	invokevirtual	Method readTreeRef:()Lscala/reflect/generic/Trees$Tree;
	astore	68
	aload_0
	invokevirtual	Method readTreeRef:()Lscala/reflect/generic/Trees$Tree;
	astore	69
	new	class scala/reflect/generic/Trees$TypeBoundsTree
	dup
	aload_0
	invokevirtual	Method scala$reflect$generic$UnPickler$Scan$$$outer:()Lscala/reflect/generic/UnPickler;
	invokevirtual	Method scala/reflect/generic/UnPickler.global:()Lscala/reflect/generic/Universe;
	aload	68
	aload	69
	invokespecial	Method scala/reflect/generic/Trees$TypeBoundsTree."<init>":(Lscala/reflect/generic/Universe;Lscala/reflect/generic/Trees$Tree;Lscala/reflect/generic/Trees$Tree;)V
	goto	l4 // astore
	aload_0
	invokevirtual	Method readTreeRef:()Lscala/reflect/generic/Trees$Tree;
	astore	66
	aload_0
	iload_2
	new	class scala/reflect/generic/UnPickler$Scan$$anonfun$31
	dup
	aload_0
	invokespecial	Method scala/reflect/generic/UnPickler$Scan$$anonfun$31."<init>":(Lscala/reflect/generic/UnPickler$Scan;)V
	invokevirtual	Method until:(ILscala/Function0;)Lscala/collection/immutable/List;
	astore	67
	new	class scala/reflect/generic/Trees$AppliedTypeTree
	dup
	aload_0
	invokevirtual	Method scala$reflect$generic$UnPickler$Scan$$$outer:()Lscala/reflect/generic/UnPickler;
	invokevirtual	Method scala/reflect/generic/UnPickler.global:()Lscala/reflect/generic/Universe;
	aload	66
	aload	67
	invokespecial	Method scala/reflect/generic/Trees$AppliedTypeTree."<init>":(Lscala/reflect/generic/Universe;Lscala/reflect/generic/Trees$Tree;Lscala/collection/immutable/List;)V
	goto	l4 // astore
	new	class scala/reflect/generic/Trees$CompoundTypeTree
	dup
	aload_0
	invokevirtual	Method scala$reflect$generic$UnPickler$Scan$$$outer:()Lscala/reflect/generic/UnPickler;
	invokevirtual	Method scala/reflect/generic/UnPickler.global:()Lscala/reflect/generic/Universe;
	aload_0
	invokevirtual	Method readTemplateRef:()Lscala/reflect/generic/Trees$Template;
	invokespecial	Method scala/reflect/generic/Trees$CompoundTypeTree."<init>":(Lscala/reflect/generic/Universe;Lscala/reflect/generic/Trees$Template;)V
	goto	l4 // astore
	aload_0
	invokevirtual	Method readTreeRef:()Lscala/reflect/generic/Trees$Tree;
	astore	64
	aload_0
	invokevirtual	Method readNameRef:()Ljava/lang/Object;
	astore	65
	new	class scala/reflect/generic/Trees$SelectFromTypeTree
	dup
	aload_0
	invokevirtual	Method scala$reflect$generic$UnPickler$Scan$$$outer:()Lscala/reflect/generic/UnPickler;
	invokevirtual	Method scala/reflect/generic/UnPickler.global:()Lscala/reflect/generic/Universe;
	aload	64
	aload	65
	invokespecial	Method scala/reflect/generic/Trees$SelectFromTypeTree."<init>":(Lscala/reflect/generic/Universe;Lscala/reflect/generic/Trees$Tree;Ljava/lang/Object;)V
	goto	l4 // astore
	new	class scala/reflect/generic/Trees$SingletonTypeTree
	dup
	aload_0
	invokevirtual	Method scala$reflect$generic$UnPickler$Scan$$$outer:()Lscala/reflect/generic/UnPickler;
	invokevirtual	Method scala/reflect/generic/UnPickler.global:()Lscala/reflect/generic/Universe;
	aload_0
	invokevirtual	Method readTreeRef:()Lscala/reflect/generic/Trees$Tree;
	invokespecial	Method scala/reflect/generic/Trees$SingletonTypeTree."<init>":(Lscala/reflect/generic/Universe;Lscala/reflect/generic/Trees$Tree;)V
	goto	l4 // astore
	aload_0
	invokevirtual	Method readTreeRef:()Lscala/reflect/generic/Trees$Tree;
	astore	62
	aload_0
	invokevirtual	Method readTreeRef:()Lscala/reflect/generic/Trees$Tree;
	astore	63
	new	class scala/reflect/generic/Trees$Annotated
	dup
	aload_0
	invokevirtual	Method scala$reflect$generic$UnPickler$Scan$$$outer:()Lscala/reflect/generic/UnPickler;
	invokevirtual	Method scala/reflect/generic/UnPickler.global:()Lscala/reflect/generic/Universe;
	aload	62
	aload	63
	invokespecial	Method scala/reflect/generic/Trees$Annotated."<init>":(Lscala/reflect/generic/Universe;Lscala/reflect/generic/Trees$Tree;Lscala/reflect/generic/Trees$Tree;)V
	goto	l4 // astore
	aload_0
	invokevirtual	Method scala$reflect$generic$UnPickler$Scan$$$outer:()Lscala/reflect/generic/UnPickler;
	invokevirtual	Method scala/reflect/generic/UnPickler.global:()Lscala/reflect/generic/Universe;
	invokeinterface	InterfaceMethod scala/reflect/generic/Trees.TypeTree:()Lscala/reflect/generic/Trees$TypeTreeExtractor;
	invokevirtual	Method scala/reflect/generic/Trees$TypeTreeExtractor.apply:()Lscala/reflect/generic/Trees$AbsTypeTree;
	goto	l4 // astore
	new	class scala/reflect/generic/Trees$Literal
	dup
	aload_0
	invokevirtual	Method scala$reflect$generic$UnPickler$Scan$$$outer:()Lscala/reflect/generic/UnPickler;
	invokevirtual	Method scala/reflect/generic/UnPickler.global:()Lscala/reflect/generic/Universe;
	aload_0
	invokevirtual	Method readConstantRef:()Lscala/reflect/generic/Constants$Constant;
	invokespecial	Method scala/reflect/generic/Trees$Literal."<init>":(Lscala/reflect/generic/Universe;Lscala/reflect/generic/Constants$Constant;)V
	goto	l4 // astore
	aload_0
	aload	5
	aload	7
	invokespecial	Method setSymName$1:(Lscala/runtime/ObjectRef;Lscala/runtime/ObjectRef;)V
	new	class scala/reflect/generic/Trees$Ident
	dup
	aload_0
	invokevirtual	Method scala$reflect$generic$UnPickler$Scan$$$outer:()Lscala/reflect/generic/UnPickler;
	invokevirtual	Method scala/reflect/generic/UnPickler.global:()Lscala/reflect/generic/Universe;
	aload	7
	getfield	Field scala/runtime/ObjectRef.elem:Ljava/lang/Object;
	invokespecial	Method scala/reflect/generic/Trees$Ident."<init>":(Lscala/reflect/generic/Universe;Ljava/lang/Object;)V
	goto	l4 // astore
	aload_0
	aload	5
	invokespecial	Method setSym$1:(Lscala/runtime/ObjectRef;)V
	aload_0
	invokevirtual	Method readTreeRef:()Lscala/reflect/generic/Trees$Tree;
	astore	60
	aload_0
	invokevirtual	Method readNameRef:()Ljava/lang/Object;
	astore	61
	new	class scala/reflect/generic/Trees$Select
	dup
	aload_0
	invokevirtual	Method scala$reflect$generic$UnPickler$Scan$$$outer:()Lscala/reflect/generic/UnPickler;
	invokevirtual	Method scala/reflect/generic/UnPickler.global:()Lscala/reflect/generic/Universe;
	aload	60
	aload	61
	invokespecial	Method scala/reflect/generic/Trees$Select."<init>":(Lscala/reflect/generic/Universe;Lscala/reflect/generic/Trees$Tree;Ljava/lang/Object;)V
	goto	l4 // astore
	aload_0
	aload	5
	invokespecial	Method setSym$1:(Lscala/runtime/ObjectRef;)V
	new	class scala/reflect/generic/Trees$This
	dup
	aload_0
	invokevirtual	Method scala$reflect$generic$UnPickler$Scan$$$outer:()Lscala/reflect/generic/UnPickler;
	invokevirtual	Method scala/reflect/generic/UnPickler.global:()Lscala/reflect/generic/Universe;
	aload_0
	invokevirtual	Method readNameRef:()Ljava/lang/Object;
	invokespecial	Method scala/reflect/generic/Trees$This."<init>":(Lscala/reflect/generic/Universe;Ljava/lang/Object;)V
	goto	l4 // astore
	aload_0
	aload	5
	invokespecial	Method setSym$1:(Lscala/runtime/ObjectRef;)V
	aload_0
	invokevirtual	Method readNameRef:()Ljava/lang/Object;
	astore	58
	aload_0
	invokevirtual	Method readNameRef:()Ljava/lang/Object;
	astore	59
	new	class scala/reflect/generic/Trees$Super
	dup
	aload_0
	invokevirtual	Method scala$reflect$generic$UnPickler$Scan$$$outer:()Lscala/reflect/generic/UnPickler;
	invokevirtual	Method scala/reflect/generic/UnPickler.global:()Lscala/reflect/generic/Universe;
	aload	58
	aload	59
	invokespecial	Method scala/reflect/generic/Trees$Super."<init>":(Lscala/reflect/generic/Universe;Ljava/lang/Object;Ljava/lang/Object;)V
	goto	l4 // astore
	aload_0
	aload	5
	invokespecial	Method setSym$1:(Lscala/runtime/ObjectRef;)V
	aload_0
	invokevirtual	Method readTreeRef:()Lscala/reflect/generic/Trees$Tree;
	astore	56
	aload_0
	iload_2
	new	class scala/reflect/generic/UnPickler$Scan$$anonfun$30
	dup
	aload_0
	invokespecial	Method scala/reflect/generic/UnPickler$Scan$$anonfun$30."<init>":(Lscala/reflect/generic/UnPickler$Scan;)V
	invokevirtual	Method until:(ILscala/Function0;)Lscala/collection/immutable/List;
	astore	57
	new	class scala/reflect/generic/Trees$ApplyDynamic
	dup
	aload_0
	invokevirtual	Method scala$reflect$generic$UnPickler$Scan$$$outer:()Lscala/reflect/generic/UnPickler;
	invokevirtual	Method scala/reflect/generic/UnPickler.global:()Lscala/reflect/generic/Universe;
	aload	56
	aload	57
	invokespecial	Method scala/reflect/generic/Trees$ApplyDynamic."<init>":(Lscala/reflect/generic/Universe;Lscala/reflect/generic/Trees$Tree;Lscala/collection/immutable/List;)V
	goto	l4 // astore
	aload_0
	invokevirtual	Method readTreeRef:()Lscala/reflect/generic/Trees$Tree;
	astore	54
	aload_0
	iload_2
	new	class scala/reflect/generic/UnPickler$Scan$$anonfun$28
	dup
	aload_0
	invokespecial	Method scala/reflect/generic/UnPickler$Scan$$anonfun$28."<init>":(Lscala/reflect/generic/UnPickler$Scan;)V
	invokevirtual	Method until:(ILscala/Function0;)Lscala/collection/immutable/List;
	astore	55
	aload	54
	invokevirtual	Method scala/reflect/generic/Trees$Tree.symbol:()Lscala/reflect/generic/Symbols$AbsSymbol;
	invokevirtual	Method scala/reflect/generic/Symbols$AbsSymbol.isOverloaded:()Z
	ifeq	l5 // new
	aload	54
	aload	54
	invokevirtual	Method scala/reflect/generic/Trees$Tree.symbol:()Lscala/reflect/generic/Symbols$AbsSymbol;
	invokevirtual	Method scala/reflect/generic/Symbols$AbsSymbol.info:()Lscala/reflect/generic/Types$AbsType;
	invokevirtual	Method scala/reflect/generic/Trees$Tree.setType:(Lscala/reflect/generic/Types$AbsType;)Lscala/reflect/generic/Trees$Tree;
	pop
	aload_0
	aload	54
	aload	55
	new	class scala/reflect/generic/UnPickler$Scan$$anonfun$29
	dup
	aload_0
	invokespecial	Method scala/reflect/generic/UnPickler$Scan$$anonfun$29."<init>":(Lscala/reflect/generic/UnPickler$Scan;)V
	getstatic	Field scala/collection/immutable/List$.MODULE$:Lscala/collection/immutable/List$;
	invokevirtual	Method scala/collection/immutable/List$.canBuildFrom:()Lscala/collection/generic/CanBuildFrom;
	invokeinterface	InterfaceMethod scala/collection/TraversableLike.map:(Lscala/Function1;Lscala/collection/generic/CanBuildFrom;)Ljava/lang/Object;
	checkcast	class scala/collection/immutable/List
	aload	4
	invokevirtual	Method inferMethodAlternative:(Lscala/reflect/generic/Trees$Tree;Lscala/collection/immutable/List;Lscala/reflect/generic/Types$AbsType;)V
l5	new	class scala/reflect/generic/Trees$Apply
	dup
	aload_0
	invokevirtual	Method scala$reflect$generic$UnPickler$Scan$$$outer:()Lscala/reflect/generic/UnPickler;
	invokevirtual	Method scala/reflect/generic/UnPickler.global:()Lscala/reflect/generic/Universe;
	aload	54
	aload	55
	invokespecial	Method scala/reflect/generic/Trees$Apply."<init>":(Lscala/reflect/generic/Universe;Lscala/reflect/generic/Trees$Tree;Lscala/collection/immutable/List;)V
	goto	l4 // astore
	aload_0
	invokevirtual	Method readTreeRef:()Lscala/reflect/generic/Trees$Tree;
	astore	52
	aload_0
	iload_2
	new	class scala/reflect/generic/UnPickler$Scan$$anonfun$27
	dup
	aload_0
	invokespecial	Method scala/reflect/generic/UnPickler$Scan$$anonfun$27."<init>":(Lscala/reflect/generic/UnPickler$Scan;)V
	invokevirtual	Method until:(ILscala/Function0;)Lscala/collection/immutable/List;
	astore	53
	new	class scala/reflect/generic/Trees$TypeApply
	dup
	aload_0
	invokevirtual	Method scala$reflect$generic$UnPickler$Scan$$$outer:()Lscala/reflect/generic/UnPickler;
	invokevirtual	Method scala/reflect/generic/UnPickler.global:()Lscala/reflect/generic/Universe;
	aload	52
	aload	53
	invokespecial	Method scala/reflect/generic/Trees$TypeApply."<init>":(Lscala/reflect/generic/Universe;Lscala/reflect/generic/Trees$Tree;Lscala/collection/immutable/List;)V
	goto	l4 // astore
	aload_0
	invokevirtual	Method readTreeRef:()Lscala/reflect/generic/Trees$Tree;
	astore	50
	aload_0
	invokevirtual	Method readTreeRef:()Lscala/reflect/generic/Trees$Tree;
	astore	51
	new	class scala/reflect/generic/Trees$Typed
	dup
	aload_0
	invokevirtual	Method scala$reflect$generic$UnPickler$Scan$$$outer:()Lscala/reflect/generic/UnPickler;
	invokevirtual	Method scala/reflect/generic/UnPickler.global:()Lscala/reflect/generic/Universe;
	aload	50
	aload	51
	invokespecial	Method scala/reflect/generic/Trees$Typed."<init>":(Lscala/reflect/generic/Universe;Lscala/reflect/generic/Trees$Tree;Lscala/reflect/generic/Trees$Tree;)V
	goto	l4 // astore
	new	class scala/reflect/generic/Trees$New
	dup
	aload_0
	invokevirtual	Method scala$reflect$generic$UnPickler$Scan$$$outer:()Lscala/reflect/generic/UnPickler;
	invokevirtual	Method scala/reflect/generic/UnPickler.global:()Lscala/reflect/generic/Universe;
	aload_0
	invokevirtual	Method readTreeRef:()Lscala/reflect/generic/Trees$Tree;
	invokespecial	Method scala/reflect/generic/Trees$New."<init>":(Lscala/reflect/generic/Universe;Lscala/reflect/generic/Trees$Tree;)V
	goto	l4 // astore
	new	class scala/reflect/generic/Trees$Throw
	dup
	aload_0
	invokevirtual	Method scala$reflect$generic$UnPickler$Scan$$$outer:()Lscala/reflect/generic/UnPickler;
	invokevirtual	Method scala/reflect/generic/UnPickler.global:()Lscala/reflect/generic/Universe;
	aload_0
	invokevirtual	Method readTreeRef:()Lscala/reflect/generic/Trees$Tree;
	invokespecial	Method scala/reflect/generic/Trees$Throw."<init>":(Lscala/reflect/generic/Universe;Lscala/reflect/generic/Trees$Tree;)V
	goto	l4 // astore
	aload_0
	invokevirtual	Method readTreeRef:()Lscala/reflect/generic/Trees$Tree;
	astore	47
	aload_0
	invokevirtual	Method readTreeRef:()Lscala/reflect/generic/Trees$Tree;
	astore	48
	aload_0
	iload_2
	new	class scala/reflect/generic/UnPickler$Scan$$anonfun$26
	dup
	aload_0
	invokespecial	Method scala/reflect/generic/UnPickler$Scan$$anonfun$26."<init>":(Lscala/reflect/generic/UnPickler$Scan;)V
	invokevirtual	Method until:(ILscala/Function0;)Lscala/collection/immutable/List;
	astore	49
	new	class scala/reflect/generic/Trees$Try
	dup
	aload_0
	invokevirtual	Method scala$reflect$generic$UnPickler$Scan$$$outer:()Lscala/reflect/generic/UnPickler;
	invokevirtual	Method scala/reflect/generic/UnPickler.global:()Lscala/reflect/generic/Universe;
	aload	47
	aload	49
	aload	48
	invokespecial	Method scala/reflect/generic/Trees$Try."<init>":(Lscala/reflect/generic/Universe;Lscala/reflect/generic/Trees$Tree;Lscala/collection/immutable/List;Lscala/reflect/generic/Trees$Tree;)V
	goto	l4 // astore
	aload_0
	aload	5
	invokespecial	Method setSym$1:(Lscala/runtime/ObjectRef;)V
	new	class scala/reflect/generic/Trees$Return
	dup
	aload_0
	invokevirtual	Method scala$reflect$generic$UnPickler$Scan$$$outer:()Lscala/reflect/generic/UnPickler;
	invokevirtual	Method scala/reflect/generic/UnPickler.global:()Lscala/reflect/generic/Universe;
	aload_0
	invokevirtual	Method readTreeRef:()Lscala/reflect/generic/Trees$Tree;
	invokespecial	Method scala/reflect/generic/Trees$Return."<init>":(Lscala/reflect/generic/Universe;Lscala/reflect/generic/Trees$Tree;)V
	goto	l4 // astore
	aload_0
	invokevirtual	Method readTreeRef:()Lscala/reflect/generic/Trees$Tree;
	astore	45
	aload_0
	iload_2
	new	class scala/reflect/generic/UnPickler$Scan$$anonfun$25
	dup
	aload_0
	invokespecial	Method scala/reflect/generic/UnPickler$Scan$$anonfun$25."<init>":(Lscala/reflect/generic/UnPickler$Scan;)V
	invokevirtual	Method until:(ILscala/Function0;)Lscala/collection/immutable/List;
	astore	46
	new	class scala/reflect/generic/Trees$Match
	dup
	aload_0
	invokevirtual	Method scala$reflect$generic$UnPickler$Scan$$$outer:()Lscala/reflect/generic/UnPickler;
	invokevirtual	Method scala/reflect/generic/UnPickler.global:()Lscala/reflect/generic/Universe;
	aload	45
	aload	46
	invokespecial	Method scala/reflect/generic/Trees$Match."<init>":(Lscala/reflect/generic/Universe;Lscala/reflect/generic/Trees$Tree;Lscala/collection/immutable/List;)V
	goto	l4 // astore
	aload_0
	invokevirtual	Method readTreeRef:()Lscala/reflect/generic/Trees$Tree;
	astore	42
	aload_0
	invokevirtual	Method readTreeRef:()Lscala/reflect/generic/Trees$Tree;
	astore	43
	aload_0
	invokevirtual	Method readTreeRef:()Lscala/reflect/generic/Trees$Tree;
	astore	44
	new	class scala/reflect/generic/Trees$If
	dup
	aload_0
	invokevirtual	Method scala$reflect$generic$UnPickler$Scan$$$outer:()Lscala/reflect/generic/UnPickler;
	invokevirtual	Method scala/reflect/generic/UnPickler.global:()Lscala/reflect/generic/Universe;
	aload	42
	aload	43
	aload	44
	invokespecial	Method scala/reflect/generic/Trees$If."<init>":(Lscala/reflect/generic/Universe;Lscala/reflect/generic/Trees$Tree;Lscala/reflect/generic/Trees$Tree;Lscala/reflect/generic/Trees$Tree;)V
	goto	l4 // astore
	aload_0
	invokevirtual	Method readTreeRef:()Lscala/reflect/generic/Trees$Tree;
	astore	40
	aload_0
	invokevirtual	Method readTreeRef:()Lscala/reflect/generic/Trees$Tree;
	astore	41
	new	class scala/reflect/generic/Trees$Assign
	dup
	aload_0
	invokevirtual	Method scala$reflect$generic$UnPickler$Scan$$$outer:()Lscala/reflect/generic/UnPickler;
	invokevirtual	Method scala/reflect/generic/UnPickler.global:()Lscala/reflect/generic/Universe;
	aload	40
	aload	41
	invokespecial	Method scala/reflect/generic/Trees$Assign."<init>":(Lscala/reflect/generic/Universe;Lscala/reflect/generic/Trees$Tree;Lscala/reflect/generic/Trees$Tree;)V
	goto	l4 // astore
	aload_0
	aload	5
	invokespecial	Method setSym$1:(Lscala/runtime/ObjectRef;)V
	aload_0
	invokevirtual	Method readTreeRef:()Lscala/reflect/generic/Trees$Tree;
	astore	38
	aload_0
	iload_2
	new	class scala/reflect/generic/UnPickler$Scan$$anonfun$24
	dup
	aload_0
	invokespecial	Method scala/reflect/generic/UnPickler$Scan$$anonfun$24."<init>":(Lscala/reflect/generic/UnPickler$Scan;)V
	invokevirtual	Method until:(ILscala/Function0;)Lscala/collection/immutable/List;
	astore	39
	new	class scala/reflect/generic/Trees$Function
	dup
	aload_0
	invokevirtual	Method scala$reflect$generic$UnPickler$Scan$$$outer:()Lscala/reflect/generic/UnPickler;
	invokevirtual	Method scala/reflect/generic/UnPickler.global:()Lscala/reflect/generic/Universe;
	aload	39
	aload	38
	invokespecial	Method scala/reflect/generic/Trees$Function."<init>":(Lscala/reflect/generic/Universe;Lscala/collection/immutable/List;Lscala/reflect/generic/Trees$Tree;)V
	goto	l4 // astore
	aload_0
	invokevirtual	Method readTreeRef:()Lscala/reflect/generic/Trees$Tree;
	astore	36
	aload_0
	iload_2
	new	class scala/reflect/generic/UnPickler$Scan$$anonfun$23
	dup
	aload_0
	invokespecial	Method scala/reflect/generic/UnPickler$Scan$$anonfun$23."<init>":(Lscala/reflect/generic/UnPickler$Scan;)V
	invokevirtual	Method until:(ILscala/Function0;)Lscala/collection/immutable/List;
	astore	37
	new	class scala/reflect/generic/Trees$ArrayValue
	dup
	aload_0
	invokevirtual	Method scala$reflect$generic$UnPickler$Scan$$$outer:()Lscala/reflect/generic/UnPickler;
	invokevirtual	Method scala/reflect/generic/UnPickler.global:()Lscala/reflect/generic/Universe;
	aload	36
	aload	37
	invokespecial	Method scala/reflect/generic/Trees$ArrayValue."<init>":(Lscala/reflect/generic/Universe;Lscala/reflect/generic/Trees$Tree;Lscala/collection/immutable/List;)V
	goto	l4 // astore
	aload_0
	invokevirtual	Method readTreeRef:()Lscala/reflect/generic/Trees$Tree;
	astore	34
	aload_0
	iload_2
	new	class scala/reflect/generic/UnPickler$Scan$$anonfun$22
	dup
	aload_0
	invokespecial	Method scala/reflect/generic/UnPickler$Scan$$anonfun$22."<init>":(Lscala/reflect/generic/UnPickler$Scan;)V
	invokevirtual	Method until:(ILscala/Function0;)Lscala/collection/immutable/List;
	astore	35
	new	class scala/reflect/generic/Trees$UnApply
	dup
	aload_0
	invokevirtual	Method scala$reflect$generic$UnPickler$Scan$$$outer:()Lscala/reflect/generic/UnPickler;
	invokevirtual	Method scala/reflect/generic/UnPickler.global:()Lscala/reflect/generic/Universe;
	aload	34
	aload	35
	invokespecial	Method scala/reflect/generic/Trees$UnApply."<init>":(Lscala/reflect/generic/Universe;Lscala/reflect/generic/Trees$Tree;Lscala/collection/immutable/List;)V
	goto	l4 // astore
	aload_0
	aload	5
	aload	7
	invokespecial	Method setSymName$1:(Lscala/runtime/ObjectRef;Lscala/runtime/ObjectRef;)V
	new	class scala/reflect/generic/Trees$Bind
	dup
	aload_0
	invokevirtual	Method scala$reflect$generic$UnPickler$Scan$$$outer:()Lscala/reflect/generic/UnPickler;
	invokevirtual	Method scala/reflect/generic/UnPickler.global:()Lscala/reflect/generic/Universe;
	aload	7
	getfield	Field scala/runtime/ObjectRef.elem:Ljava/lang/Object;
	aload_0
	invokevirtual	Method readTreeRef:()Lscala/reflect/generic/Trees$Tree;
	invokespecial	Method scala/reflect/generic/Trees$Bind."<init>":(Lscala/reflect/generic/Universe;Ljava/lang/Object;Lscala/reflect/generic/Trees$Tree;)V
	goto	l4 // astore
	new	class scala/reflect/generic/Trees$Star
	dup
	aload_0
	invokevirtual	Method scala$reflect$generic$UnPickler$Scan$$$outer:()Lscala/reflect/generic/UnPickler;
	invokevirtual	Method scala/reflect/generic/UnPickler.global:()Lscala/reflect/generic/Universe;
	aload_0
	invokevirtual	Method readTreeRef:()Lscala/reflect/generic/Trees$Tree;
	invokespecial	Method scala/reflect/generic/Trees$Star."<init>":(Lscala/reflect/generic/Universe;Lscala/reflect/generic/Trees$Tree;)V
	goto	l4 // astore
	new	class scala/reflect/generic/Trees$Alternative
	dup
	aload_0
	invokevirtual	Method scala$reflect$generic$UnPickler$Scan$$$outer:()Lscala/reflect/generic/UnPickler;
	invokevirtual	Method scala/reflect/generic/UnPickler.global:()Lscala/reflect/generic/Universe;
	aload_0
	iload_2
	new	class scala/reflect/generic/UnPickler$Scan$$anonfun$21
	dup
	aload_0
	invokespecial	Method scala/reflect/generic/UnPickler$Scan$$anonfun$21."<init>":(Lscala/reflect/generic/UnPickler$Scan;)V
	invokevirtual	Method until:(ILscala/Function0;)Lscala/collection/immutable/List;
	invokespecial	Method scala/reflect/generic/Trees$Alternative."<init>":(Lscala/reflect/generic/Universe;Lscala/collection/immutable/List;)V
	goto	l4 // astore
	aload_0
	invokevirtual	Method readTreeRef:()Lscala/reflect/generic/Trees$Tree;
	astore	31
	aload_0
	invokevirtual	Method readTreeRef:()Lscala/reflect/generic/Trees$Tree;
	astore	32
	aload_0
	invokevirtual	Method readTreeRef:()Lscala/reflect/generic/Trees$Tree;
	astore	33
	new	class scala/reflect/generic/Trees$CaseDef
	dup
	aload_0
	invokevirtual	Method scala$reflect$generic$UnPickler$Scan$$$outer:()Lscala/reflect/generic/UnPickler;
	invokevirtual	Method scala/reflect/generic/UnPickler.global:()Lscala/reflect/generic/Universe;
	aload	31
	aload	32
	aload	33
	invokespecial	Method scala/reflect/generic/Trees$CaseDef."<init>":(Lscala/reflect/generic/Universe;Lscala/reflect/generic/Trees$Tree;Lscala/reflect/generic/Trees$Tree;Lscala/reflect/generic/Trees$Tree;)V
	goto	l4 // astore
	aload_0
	invokevirtual	Method readTreeRef:()Lscala/reflect/generic/Trees$Tree;
	astore	29
	aload_0
	iload_2
	new	class scala/reflect/generic/UnPickler$Scan$$anonfun$20
	dup
	aload_0
	invokespecial	Method scala/reflect/generic/UnPickler$Scan$$anonfun$20."<init>":(Lscala/reflect/generic/UnPickler$Scan;)V
	invokevirtual	Method until:(ILscala/Function0;)Lscala/collection/immutable/List;
	astore	30
	new	class scala/reflect/generic/Trees$Block
	dup
	aload_0
	invokevirtual	Method scala$reflect$generic$UnPickler$Scan$$$outer:()Lscala/reflect/generic/UnPickler;
	invokevirtual	Method scala/reflect/generic/UnPickler.global:()Lscala/reflect/generic/Universe;
	aload	30
	aload	29
	invokespecial	Method scala/reflect/generic/Trees$Block."<init>":(Lscala/reflect/generic/Universe;Lscala/collection/immutable/List;Lscala/reflect/generic/Trees$Tree;)V
	goto	l4 // astore
	aload_0
	aload	5
	invokespecial	Method setSym$1:(Lscala/runtime/ObjectRef;)V
	aload_0
	aload_0
	invokevirtual	Method readNat:()I
	new	class scala/reflect/generic/UnPickler$Scan$$anonfun$18
	dup
	aload_0
	invokespecial	Method scala/reflect/generic/UnPickler$Scan$$anonfun$18."<init>":(Lscala/reflect/generic/UnPickler$Scan;)V
	invokevirtual	Method times:(ILscala/Function0;)Lscala/collection/immutable/List;
	astore	26
	aload_0
	invokevirtual	Method readValDefRef:()Lscala/reflect/generic/Trees$ValDef;
	astore	27
	aload_0
	iload_2
	new	class scala/reflect/generic/UnPickler$Scan$$anonfun$19
	dup
	aload_0
	invokespecial	Method scala/reflect/generic/UnPickler$Scan$$anonfun$19."<init>":(Lscala/reflect/generic/UnPickler$Scan;)V
	invokevirtual	Method until:(ILscala/Function0;)Lscala/collection/immutable/List;
	astore	28
	new	class scala/reflect/generic/Trees$Template
	dup
	aload_0
	invokevirtual	Method scala$reflect$generic$UnPickler$Scan$$$outer:()Lscala/reflect/generic/UnPickler;
	invokevirtual	Method scala/reflect/generic/UnPickler.global:()Lscala/reflect/generic/Universe;
	aload	26
	aload	27
	aload	28
	invokespecial	Method scala/reflect/generic/Trees$Template."<init>":(Lscala/reflect/generic/Universe;Lscala/collection/immutable/List;Lscala/reflect/generic/Trees$ValDef;Lscala/collection/immutable/List;)V
	goto	l4 // astore
	aload_0
	aload	5
	invokespecial	Method setSym$1:(Lscala/runtime/ObjectRef;)V
	aload_0
	invokevirtual	Method readTreeRef:()Lscala/reflect/generic/Trees$Tree;
	astore	24
	aload_0
	iload_2
	new	class scala/reflect/generic/UnPickler$Scan$$anonfun$17
	dup
	aload_0
	invokespecial	Method scala/reflect/generic/UnPickler$Scan$$anonfun$17."<init>":(Lscala/reflect/generic/UnPickler$Scan;)V
	invokevirtual	Method until:(ILscala/Function0;)Lscala/collection/immutable/List;
	astore	25
	new	class scala/reflect/generic/Trees$Import
	dup
	aload_0
	invokevirtual	Method scala$reflect$generic$UnPickler$Scan$$$outer:()Lscala/reflect/generic/UnPickler;
	invokevirtual	Method scala/reflect/generic/UnPickler.global:()Lscala/reflect/generic/Universe;
	aload	24
	aload	25
	invokespecial	Method scala/reflect/generic/Trees$Import."<init>":(Lscala/reflect/generic/Universe;Lscala/reflect/generic/Trees$Tree;Lscala/collection/immutable/List;)V
	goto	l4 // astore
	aload_0
	aload	5
	aload	7
	invokespecial	Method setSymName$1:(Lscala/runtime/ObjectRef;Lscala/runtime/ObjectRef;)V
	aload_0
	invokevirtual	Method readTreeRef:()Lscala/reflect/generic/Trees$Tree;
	astore	22
	aload_0
	iload_2
	new	class scala/reflect/generic/UnPickler$Scan$$anonfun$16
	dup
	aload_0
	invokespecial	Method scala/reflect/generic/UnPickler$Scan$$anonfun$16."<init>":(Lscala/reflect/generic/UnPickler$Scan;)V
	invokevirtual	Method until:(ILscala/Function0;)Lscala/collection/immutable/List;
	astore	23
	new	class scala/reflect/generic/Trees$LabelDef
	dup
	aload_0
	invokevirtual	Method scala$reflect$generic$UnPickler$Scan$$$outer:()Lscala/reflect/generic/UnPickler;
	invokevirtual	Method scala/reflect/generic/UnPickler.global:()Lscala/reflect/generic/Universe;
	aload	7
	getfield	Field scala/runtime/ObjectRef.elem:Ljava/lang/Object;
	aload	23
	aload	22
	invokespecial	Method scala/reflect/generic/Trees$LabelDef."<init>":(Lscala/reflect/generic/Universe;Ljava/lang/Object;Lscala/collection/immutable/List;Lscala/reflect/generic/Trees$Tree;)V
	goto	l4 // astore
	aload_0
	aload	5
	aload	6
	aload	7
	invokespecial	Method setSymModsName$1:(Lscala/runtime/ObjectRef;Lscala/runtime/ObjectRef;Lscala/runtime/ObjectRef;)V
	aload_0
	invokevirtual	Method readTreeRef:()Lscala/reflect/generic/Trees$Tree;
	astore	20
	aload_0
	iload_2
	new	class scala/reflect/generic/UnPickler$Scan$$anonfun$15
	dup
	aload_0
	invokespecial	Method scala/reflect/generic/UnPickler$Scan$$anonfun$15."<init>":(Lscala/reflect/generic/UnPickler$Scan;)V
	invokevirtual	Method until:(ILscala/Function0;)Lscala/collection/immutable/List;
	astore	21
	new	class scala/reflect/generic/Trees$TypeDef
	dup
	aload_0
	invokevirtual	Method scala$reflect$generic$UnPickler$Scan$$$outer:()Lscala/reflect/generic/UnPickler;
	invokevirtual	Method scala/reflect/generic/UnPickler.global:()Lscala/reflect/generic/Universe;
	aload	6
	getfield	Field scala/runtime/ObjectRef.elem:Ljava/lang/Object;
	checkcast	class scala/reflect/generic/Trees$Modifiers
	aload	7
	getfield	Field scala/runtime/ObjectRef.elem:Ljava/lang/Object;
	aload	21
	aload	20
	invokespecial	Method scala/reflect/generic/Trees$TypeDef."<init>":(Lscala/reflect/generic/Universe;Lscala/reflect/generic/Trees$Modifiers;Ljava/lang/Object;Lscala/collection/immutable/List;Lscala/reflect/generic/Trees$Tree;)V
	goto	l4 // astore
	aload_0
	aload	5
	aload	6
	aload	7
	invokespecial	Method setSymModsName$1:(Lscala/runtime/ObjectRef;Lscala/runtime/ObjectRef;Lscala/runtime/ObjectRef;)V
	aload_0
	aload_0
	invokevirtual	Method readNat:()I
	new	class scala/reflect/generic/UnPickler$Scan$$anonfun$13
	dup
	aload_0
	invokespecial	Method scala/reflect/generic/UnPickler$Scan$$anonfun$13."<init>":(Lscala/reflect/generic/UnPickler$Scan;)V
	invokevirtual	Method times:(ILscala/Function0;)Lscala/collection/immutable/List;
	astore	16
	aload_0
	aload_0
	invokevirtual	Method readNat:()I
	new	class scala/reflect/generic/UnPickler$Scan$$anonfun$14
	dup
	aload_0
	invokespecial	Method scala/reflect/generic/UnPickler$Scan$$anonfun$14."<init>":(Lscala/reflect/generic/UnPickler$Scan;)V
	invokevirtual	Method times:(ILscala/Function0;)Lscala/collection/immutable/List;
	astore	17
	aload_0
	invokevirtual	Method readTreeRef:()Lscala/reflect/generic/Trees$Tree;
	astore	18
	aload_0
	invokevirtual	Method readTreeRef:()Lscala/reflect/generic/Trees$Tree;
	astore	19
	new	class scala/reflect/generic/Trees$DefDef
	dup
	aload_0
	invokevirtual	Method scala$reflect$generic$UnPickler$Scan$$$outer:()Lscala/reflect/generic/UnPickler;
	invokevirtual	Method scala/reflect/generic/UnPickler.global:()Lscala/reflect/generic/Universe;
	aload	6
	getfield	Field scala/runtime/ObjectRef.elem:Ljava/lang/Object;
	checkcast	class scala/reflect/generic/Trees$Modifiers
	aload	7
	getfield	Field scala/runtime/ObjectRef.elem:Ljava/lang/Object;
	aload	16
	aload	17
	aload	18
	aload	19
	invokespecial	Method scala/reflect/generic/Trees$DefDef."<init>":(Lscala/reflect/generic/Universe;Lscala/reflect/generic/Trees$Modifiers;Ljava/lang/Object;Lscala/collection/immutable/List;Lscala/collection/immutable/List;Lscala/reflect/generic/Trees$Tree;Lscala/reflect/generic/Trees$Tree;)V
	goto	l4 // astore
	aload_0
	aload	5
	aload	6
	aload	7
	invokespecial	Method setSymModsName$1:(Lscala/runtime/ObjectRef;Lscala/runtime/ObjectRef;Lscala/runtime/ObjectRef;)V
	aload_0
	invokevirtual	Method readTreeRef:()Lscala/reflect/generic/Trees$Tree;
	astore	14
	aload_0
	invokevirtual	Method readTreeRef:()Lscala/reflect/generic/Trees$Tree;
	astore	15
	new	class scala/reflect/generic/Trees$ValDef
	dup
	aload_0
	invokevirtual	Method scala$reflect$generic$UnPickler$Scan$$$outer:()Lscala/reflect/generic/UnPickler;
	invokevirtual	Method scala/reflect/generic/UnPickler.global:()Lscala/reflect/generic/Universe;
	aload	6
	getfield	Field scala/runtime/ObjectRef.elem:Ljava/lang/Object;
	checkcast	class scala/reflect/generic/Trees$Modifiers
	aload	7
	getfield	Field scala/runtime/ObjectRef.elem:Ljava/lang/Object;
	aload	14
	aload	15
	invokespecial	Method scala/reflect/generic/Trees$ValDef."<init>":(Lscala/reflect/generic/Universe;Lscala/reflect/generic/Trees$Modifiers;Ljava/lang/Object;Lscala/reflect/generic/Trees$Tree;Lscala/reflect/generic/Trees$Tree;)V
	goto	l4 // astore
	aload_0
	aload	5
	aload	6
	aload	7
	invokespecial	Method setSymModsName$1:(Lscala/runtime/ObjectRef;Lscala/runtime/ObjectRef;Lscala/runtime/ObjectRef;)V
	new	class scala/reflect/generic/Trees$ModuleDef
	dup
	aload_0
	invokevirtual	Method scala$reflect$generic$UnPickler$Scan$$$outer:()Lscala/reflect/generic/UnPickler;
	invokevirtual	Method scala/reflect/generic/UnPickler.global:()Lscala/reflect/generic/Universe;
	aload	6
	getfield	Field scala/runtime/ObjectRef.elem:Ljava/lang/Object;
	checkcast	class scala/reflect/generic/Trees$Modifiers
	aload	7
	getfield	Field scala/runtime/ObjectRef.elem:Ljava/lang/Object;
	aload_0
	invokevirtual	Method readTemplateRef:()Lscala/reflect/generic/Trees$Template;
	invokespecial	Method scala/reflect/generic/Trees$ModuleDef."<init>":(Lscala/reflect/generic/Universe;Lscala/reflect/generic/Trees$Modifiers;Ljava/lang/Object;Lscala/reflect/generic/Trees$Template;)V
	goto	l4 // astore
	aload_0
	aload	5
	aload	6
	aload	7
	invokespecial	Method setSymModsName$1:(Lscala/runtime/ObjectRef;Lscala/runtime/ObjectRef;Lscala/runtime/ObjectRef;)V
	aload_0
	invokevirtual	Method readTemplateRef:()Lscala/reflect/generic/Trees$Template;
	astore	12
	aload_0
	iload_2
	new	class scala/reflect/generic/UnPickler$Scan$$anonfun$12
	dup
	aload_0
	invokespecial	Method scala/reflect/generic/UnPickler$Scan$$anonfun$12."<init>":(Lscala/reflect/generic/UnPickler$Scan;)V
	invokevirtual	Method until:(ILscala/Function0;)Lscala/collection/immutable/List;
	astore	13
	new	class scala/reflect/generic/Trees$ClassDef
	dup
	aload_0
	invokevirtual	Method scala$reflect$generic$UnPickler$Scan$$$outer:()Lscala/reflect/generic/UnPickler;
	invokevirtual	Method scala/reflect/generic/UnPickler.global:()Lscala/reflect/generic/Universe;
	aload	6
	getfield	Field scala/runtime/ObjectRef.elem:Ljava/lang/Object;
	checkcast	class scala/reflect/generic/Trees$Modifiers
	aload	7
	getfield	Field scala/runtime/ObjectRef.elem:Ljava/lang/Object;
	aload	13
	aload	12
	invokespecial	Method scala/reflect/generic/Trees$ClassDef."<init>":(Lscala/reflect/generic/Universe;Lscala/reflect/generic/Trees$Modifiers;Ljava/lang/Object;Lscala/collection/immutable/List;Lscala/reflect/generic/Trees$Template;)V
	goto	l4 // astore
	aload_0
	aload	5
	invokespecial	Method setSym$1:(Lscala/runtime/ObjectRef;)V
	aload_0
	invokevirtual	Method readTreeRef:()Lscala/reflect/generic/Trees$Tree;
	checkcast	class scala/reflect/generic/Trees$RefTree
	astore	10
	aload_0
	iload_2
	new	class scala/reflect/generic/UnPickler$Scan$$anonfun$11
	dup
	aload_0
	invokespecial	Method scala/reflect/generic/UnPickler$Scan$$anonfun$11."<init>":(Lscala/reflect/generic/UnPickler$Scan;)V
	invokevirtual	Method until:(ILscala/Function0;)Lscala/collection/immutable/List;
	astore	11
	new	class scala/reflect/generic/Trees$PackageDef
	dup
	aload_0
	invokevirtual	Method scala$reflect$generic$UnPickler$Scan$$$outer:()Lscala/reflect/generic/UnPickler;
	invokevirtual	Method scala/reflect/generic/UnPickler.global:()Lscala/reflect/generic/Universe;
	aload	10
	aload	11
	invokespecial	Method scala/reflect/generic/Trees$PackageDef."<init>":(Lscala/reflect/generic/Universe;Lscala/reflect/generic/Trees$RefTree;Lscala/collection/immutable/List;)V
	goto	l4 // astore
	aload_0
	invokevirtual	Method scala$reflect$generic$UnPickler$Scan$$$outer:()Lscala/reflect/generic/UnPickler;
	invokevirtual	Method scala/reflect/generic/UnPickler.global:()Lscala/reflect/generic/Universe;
	invokeinterface	InterfaceMethod scala/reflect/generic/Trees.EmptyTree:()Lscala/reflect/generic/Trees$EmptyTree$;
l4	astore	8
	aload	5
	getfield	Field scala/runtime/ObjectRef.elem:Ljava/lang/Object;
	checkcast	class scala/reflect/generic/Symbols$AbsSymbol
	dup
	astore	72
	ifnull	l6 // aload
	aload	72
	aconst_null
	invokevirtual	Method java/lang/Object.equals:(Ljava/lang/Object;)Z
	ifeq	l7 // aload
l6	aload	8
	aload	4
	invokevirtual	Method scala/reflect/generic/Trees$Tree.setType:(Lscala/reflect/generic/Types$AbsType;)Lscala/reflect/generic/Trees$Tree;
	goto	l8 // areturn
l7	aload	8
	aload	5
	getfield	Field scala/runtime/ObjectRef.elem:Ljava/lang/Object;
	checkcast	class scala/reflect/generic/Symbols$AbsSymbol
	invokevirtual	Method scala/reflect/generic/Trees$Tree.setSymbol:(Lscala/reflect/generic/Symbols$AbsSymbol;)Lscala/reflect/generic/Trees$Tree;
	aload	4
	invokevirtual	Method scala/reflect/generic/Trees$Tree.setType:(Lscala/reflect/generic/Types$AbsType;)Lscala/reflect/generic/Trees$Tree;
l8	areturn
  Labels:
   	l1 = 46 // aload_0
   	l2 = 81 // aload_0
   	l3 = 85 // astore
   	l5 = 856 // new
   	l4 = 2047 // astore
   	l6 = 2072 // aload
   	l7 = 2082 // aload
   	l8 = 2100 // areturn
  LocalVariableTable: 
   Start  Length  Slot  Name   Signature
   0      2101      0    this       Lscala/reflect/generic/UnPickler$Scan;
   5      2096      1    outerTag       I
   56      2045      2    end       I
   61      2040      3    tag       I
   87      2014      4    tpe       Lscala/reflect/generic/Types$AbsType;
   99      2002      5    symbol$1       Lscala/runtime/ObjectRef;
   111      1990      6    mods$1       Lscala/runtime/ObjectRef;
   123      1978      7    name$1       Lscala/runtime/ObjectRef;
   2049      52      8    t       Lscala/reflect/generic/Trees$Tree;
   126      1937      9    temp11       I
   1999      33      10    pid       Lscala/reflect/generic/Trees$RefTree;
   2014      18      11    stats       Lscala/collection/immutable/List;
   1935      46      12    impl       Lscala/reflect/generic/Trees$Template;
   1950      31      13    tparams       Lscala/collection/immutable/List;
   1835      37      14    tpt       Lscala/reflect/generic/Trees$Tree;
   1841      31      15    rhs       Lscala/reflect/generic/Trees$Tree;
   1751      65      16    tparams       Lscala/collection/immutable/List;
   1769      47      17    vparamss       Lscala/collection/immutable/List;
   1775      41      18    tpt       Lscala/reflect/generic/Trees$Tree;
   1781      35      19    rhs       Lscala/reflect/generic/Trees$Tree;
   1674      46      20    rhs       Lscala/reflect/generic/Trees$Tree;
   1689      31      21    tparams       Lscala/collection/immutable/List;
   1617      38      22    rhs       Lscala/reflect/generic/Trees$Tree;
   1632      23      23    params       Lscala/collection/immutable/List;
   1567      33      24    expr       Lscala/reflect/generic/Trees$Tree;
   1582      18      25    selectors       Lscala/collection/immutable/List;
   1511      41      26    parents       Lscala/collection/immutable/List;
   1517      35      27    self       Lscala/reflect/generic/Trees$ValDef;
   1532      20      28    body       Lscala/collection/immutable/List;
   1451      33      29    expr       Lscala/reflect/generic/Trees$Tree;
   1466      18      30    stats       Lscala/collection/immutable/List;
   1410      32      31    pat       Lscala/reflect/generic/Trees$Tree;
   1416      26      32    guard       Lscala/reflect/generic/Trees$Tree;
   1422      20      33    body       Lscala/reflect/generic/Trees$Tree;
   1283      33      34    fun       Lscala/reflect/generic/Trees$Tree;
   1298      18      35    args       Lscala/collection/immutable/List;
   1241      33      36    elemtpt       Lscala/reflect/generic/Trees$Tree;
   1256      18      37    trees       Lscala/collection/immutable/List;
   1199      33      38    body       Lscala/reflect/generic/Trees$Tree;
   1214      18      39    vparams       Lscala/collection/immutable/List;
   1160      24      40    lhs       Lscala/reflect/generic/Trees$Tree;
   1166      18      41    rhs       Lscala/reflect/generic/Trees$Tree;
   1119      32      42    cond       Lscala/reflect/generic/Trees$Tree;
   1125      26      43    thenp       Lscala/reflect/generic/Trees$Tree;
   1131      20      44    elsep       Lscala/reflect/generic/Trees$Tree;
   1077      33      45    selector       Lscala/reflect/generic/Trees$Tree;
   1092      18      46    cases       Lscala/collection/immutable/List;
   1000      41      47    block       Lscala/reflect/generic/Trees$Tree;
   1006      35      48    finalizer       Lscala/reflect/generic/Trees$Tree;
   1021      20      49    catches       Lscala/collection/immutable/List;
   925      24      50    expr       Lscala/reflect/generic/Trees$Tree;
   931      18      51    tpt       Lscala/reflect/generic/Trees$Tree;
   883      33      52    fun       Lscala/reflect/generic/Trees$Tree;
   898      18      53    args       Lscala/collection/immutable/List;
   784      90      54    fun       Lscala/reflect/generic/Trees$Tree;
   799      75      55    args       Lscala/collection/immutable/List;
   742      33      56    qual       Lscala/reflect/generic/Trees$Tree;
   757      18      57    args       Lscala/collection/immutable/List;
   703      24      58    qual       Ljava/lang/Object;
   709      18      59    mix       Ljava/lang/Object;
   637      24      60    qualifier       Lscala/reflect/generic/Trees$Tree;
   643      18      61    selector       Ljava/lang/Object;
   529      24      62    annot       Lscala/reflect/generic/Trees$Tree;
   535      18      63    arg       Lscala/reflect/generic/Trees$Tree;
   475      24      64    qualifier       Lscala/reflect/generic/Trees$Tree;
   481      18      65    selector       Ljava/lang/Object;
   412      33      66    tpt       Lscala/reflect/generic/Trees$Tree;
   427      18      67    args       Lscala/collection/immutable/List;
   379      24      68    lo       Lscala/reflect/generic/Trees$Tree;
   385      18      69    hi       Lscala/reflect/generic/Trees$Tree;
   337      33      70    tpt       Lscala/reflect/generic/Trees$Tree;
   352      18      71    whereClauses       Lscala/collection/immutable/List;


public scala.runtime.Nothing$ noSuchTreeTag(int, int);
  Signature: (II)Lscala/runtime/Nothing$;
  Code:
   Stack=3, Locals=3, Args_size=3
	aload_0
	new	class scala/collection/mutable/StringBuilder
	dup
	invokespecial	Method scala/collection/mutable/StringBuilder."<init>":()V
	ldc_w	String unknown tree type (
	invokevirtual	Method scala/collection/mutable/StringBuilder.append:(Ljava/lang/Object;)Lscala/collection/mutable/StringBuilder;
	iload_1
	invokestatic	Method scala/runtime/BoxesRunTime.boxToInteger:(I)Ljava/lang/Integer;
	invokevirtual	Method scala/collection/mutable/StringBuilder.append:(Ljava/lang/Object;)Lscala/collection/mutable/StringBuilder;
	ldc_w	String )
	invokevirtual	Method scala/collection/mutable/StringBuilder.append:(Ljava/lang/Object;)Lscala/collection/mutable/StringBuilder;
	invokevirtual	Method scala/collection/mutable/StringBuilder.toString:()Ljava/lang/String;
	invokevirtual	Method errorBadSignature:(Ljava/lang/String;)Lscala/runtime/Nothing$;
	areturn
  Labels:
  LocalVariableTable: 
   Start  Length  Slot  Name   Signature
   0      34      0    this       Lscala/reflect/generic/UnPickler$Scan;
   0      34      1    tag       I
   0      34      2    end       I


public scala.reflect.generic.Trees$Modifiers readModifiers();
  Signature: ()Lscala/reflect/generic/Trees$Modifiers;
  Code:
   Stack=8, Locals=10, Args_size=1
	aload_0
	invokevirtual	Method readNat:()I
	istore_1
	iload_1
	ldc_w	int 50
	if_icmpeq	l1 // aload_0
	aload_0
	new	class scala/collection/mutable/StringBuilder
	dup
	invokespecial	Method scala/collection/mutable/StringBuilder."<init>":()V
	ldc_w	String expected a modifiers tag (
	invokevirtual	Method scala/collection/mutable/StringBuilder.append:(Ljava/lang/Object;)Lscala/collection/mutable/StringBuilder;
	iload_1
	invokestatic	Method scala/runtime/BoxesRunTime.boxToInteger:(I)Ljava/lang/Integer;
	invokevirtual	Method scala/collection/mutable/StringBuilder.append:(Ljava/lang/Object;)Lscala/collection/mutable/StringBuilder;
	ldc_w	String )
	invokevirtual	Method scala/collection/mutable/StringBuilder.append:(Ljava/lang/Object;)Lscala/collection/mutable/StringBuilder;
	invokevirtual	Method scala/collection/mutable/StringBuilder.toString:()Ljava/lang/String;
	invokevirtual	Method errorBadSignature:(Ljava/lang/String;)Lscala/runtime/Nothing$;
	athrow
l1	aload_0
	invokevirtual	Method readNat:()I
	aload_0
	invokevirtual	Method readIndex:()I
	iadd
	istore_2
	aload_0
	invokevirtual	Method readNat:()I
	istore_3
	aload_0
	invokevirtual	Method readNat:()I
	istore	4
	iload_3
	i2l
	ldc_w	int 32
	lshl
	iload	4
	i2l
	ladd
	lstore	5
	getstatic	Field scala/reflect/generic/Flags$.MODULE$:Lscala/reflect/generic/Flags$;
	lload	5
	invokevirtual	Method scala/reflect/generic/Flags$.pickledToRawFlags:(J)J
	lstore	7
	aload_0
	invokevirtual	Method readNameRef:()Ljava/lang/Object;
	astore	9
	new	class scala/reflect/generic/Trees$Modifiers
	dup
	aload_0
	invokevirtual	Method scala$reflect$generic$UnPickler$Scan$$$outer:()Lscala/reflect/generic/UnPickler;
	invokevirtual	Method scala/reflect/generic/UnPickler.global:()Lscala/reflect/generic/Universe;
	lload	7
	aload	9
	getstatic	Field scala/collection/immutable/Nil$.MODULE$:Lscala/collection/immutable/Nil$;
	getstatic	Field scala/Predef$.MODULE$:Lscala/Predef$;
	invokevirtual	Method scala/Predef$.Map:()Lscala/collection/immutable/Map$;
	invokevirtual	Method scala/collection/immutable/Map$.empty:()Lscala/collection/immutable/Map;
	invokespecial	Method scala/reflect/generic/Trees$Modifiers."<init>":(Lscala/reflect/generic/Universe;JLjava/lang/Object;Lscala/collection/immutable/List;Lscala/collection/immutable/Map;)V
	areturn
  Labels:
   	l1 = 46 // aload_0
  LocalVariableTable: 
   Start  Length  Slot  Name   Signature
   0      126      0    this       Lscala/reflect/generic/UnPickler$Scan;
   5      120      1    tag       I
   56      69      2    end       I
   61      64      3    pflagsHi       I
   67      58      4    pflagsLo       I
   79      46      5    pflags       J
   89      36      7    flags       J
   95      30      9    privateWithin       Ljava/lang/Object;


public java.lang.Object readNameRef();
  Signature: ()Ljava/lang/Object;
  Code:
   Stack=5, Locals=1, Args_size=1
	aload_0
	aload_0
	invokevirtual	Method readNat:()I
	new	class scala/reflect/generic/UnPickler$Scan$$anonfun$readNameRef$1
	dup
	aload_0
	invokespecial	Method scala/reflect/generic/UnPickler$Scan$$anonfun$readNameRef$1."<init>":(Lscala/reflect/generic/UnPickler$Scan;)V
	invokevirtual	Method at:(ILscala/Function0;)Ljava/lang/Object;
	areturn
  Labels:

public scala.reflect.generic.Symbols$AbsSymbol readSymbolRef();
  Signature: ()Lscala/reflect/generic/Symbols$AbsSymbol;
  Code:
   Stack=5, Locals=1, Args_size=1
	aload_0
	aload_0
	invokevirtual	Method readNat:()I
	new	class scala/reflect/generic/UnPickler$Scan$$anonfun$readSymbolRef$1
	dup
	aload_0
	invokespecial	Method scala/reflect/generic/UnPickler$Scan$$anonfun$readSymbolRef$1."<init>":(Lscala/reflect/generic/UnPickler$Scan;)V
	invokevirtual	Method at:(ILscala/Function0;)Ljava/lang/Object;
	checkcast	class scala/reflect/generic/Symbols$AbsSymbol
	areturn
  Labels:

public scala.reflect.generic.Types$AbsType readTypeRef();
  Signature: ()Lscala/reflect/generic/Types$AbsType;
  Code:
   Stack=5, Locals=1, Args_size=1
	aload_0
	aload_0
	invokevirtual	Method readNat:()I
	new	class scala/reflect/generic/UnPickler$Scan$$anonfun$readTypeRef$1
	dup
	aload_0
	invokespecial	Method scala/reflect/generic/UnPickler$Scan$$anonfun$readTypeRef$1."<init>":(Lscala/reflect/generic/UnPickler$Scan;)V
	invokevirtual	Method at:(ILscala/Function0;)Ljava/lang/Object;
	checkcast	class scala/reflect/generic/Types$AbsType
	areturn
  Labels:

public scala.reflect.generic.Constants$Constant readConstantRef();
  Signature: ()Lscala/reflect/generic/Constants$Constant;
  Code:
   Stack=5, Locals=1, Args_size=1
	aload_0
	aload_0
	invokevirtual	Method readNat:()I
	new	class scala/reflect/generic/UnPickler$Scan$$anonfun$readConstantRef$1
	dup
	aload_0
	invokespecial	Method scala/reflect/generic/UnPickler$Scan$$anonfun$readConstantRef$1."<init>":(Lscala/reflect/generic/UnPickler$Scan;)V
	invokevirtual	Method at:(ILscala/Function0;)Ljava/lang/Object;
	checkcast	class scala/reflect/generic/Constants$Constant
	areturn
  Labels:

public java.lang.Object readAnnotationRef();
  Signature: ()Ljava/lang/Object;
  Code:
   Stack=5, Locals=1, Args_size=1
	aload_0
	aload_0
	invokevirtual	Method readNat:()I
	new	class scala/reflect/generic/UnPickler$Scan$$anonfun$readAnnotationRef$1
	dup
	aload_0
	invokespecial	Method scala/reflect/generic/UnPickler$Scan$$anonfun$readAnnotationRef$1."<init>":(Lscala/reflect/generic/UnPickler$Scan;)V
	invokevirtual	Method at:(ILscala/Function0;)Ljava/lang/Object;
	areturn
  Labels:

public scala.reflect.generic.Trees$Modifiers readModifiersRef();
  Signature: ()Lscala/reflect/generic/Trees$Modifiers;
  Code:
   Stack=5, Locals=1, Args_size=1
	aload_0
	aload_0
	invokevirtual	Method readNat:()I
	new	class scala/reflect/generic/UnPickler$Scan$$anonfun$readModifiersRef$1
	dup
	aload_0
	invokespecial	Method scala/reflect/generic/UnPickler$Scan$$anonfun$readModifiersRef$1."<init>":(Lscala/reflect/generic/UnPickler$Scan;)V
	invokevirtual	Method at:(ILscala/Function0;)Ljava/lang/Object;
	checkcast	class scala/reflect/generic/Trees$Modifiers
	areturn
  Labels:

public scala.reflect.generic.Trees$Tree readTreeRef();
  Signature: ()Lscala/reflect/generic/Trees$Tree;
  Code:
   Stack=5, Locals=1, Args_size=1
	aload_0
	aload_0
	invokevirtual	Method readNat:()I
	new	class scala/reflect/generic/UnPickler$Scan$$anonfun$readTreeRef$1
	dup
	aload_0
	invokespecial	Method scala/reflect/generic/UnPickler$Scan$$anonfun$readTreeRef$1."<init>":(Lscala/reflect/generic/UnPickler$Scan;)V
	invokevirtual	Method at:(ILscala/Function0;)Ljava/lang/Object;
	checkcast	class scala/reflect/generic/Trees$Tree
	areturn
  Labels:

public scala.reflect.generic.Trees$Template readTemplateRef();
  Signature: ()Lscala/reflect/generic/Trees$Template;
  Code:
   Stack=3, Locals=2, Args_size=1
	aload_0
	invokevirtual	Method readTreeRef:()Lscala/reflect/generic/Trees$Tree;
	astore_1
	aload_1
	instanceof	class scala/reflect/generic/Trees$Template
	ifeq	l1 // aload_0
	aload_1
	checkcast	class scala/reflect/generic/Trees$Template
	areturn
l1	aload_0
	new	class scala/collection/mutable/StringBuilder
	dup
	invokespecial	Method scala/collection/mutable/StringBuilder."<init>":()V
	ldc_w	String expected a template (
	invokevirtual	Method scala/collection/mutable/StringBuilder.append:(Ljava/lang/Object;)Lscala/collection/mutable/StringBuilder;
	aload_1
	invokevirtual	Method scala/collection/mutable/StringBuilder.append:(Ljava/lang/Object;)Lscala/collection/mutable/StringBuilder;
	ldc_w	String )
	invokevirtual	Method scala/collection/mutable/StringBuilder.append:(Ljava/lang/Object;)Lscala/collection/mutable/StringBuilder;
	invokevirtual	Method scala/collection/mutable/StringBuilder.toString:()Ljava/lang/String;
	invokevirtual	Method errorBadSignature:(Ljava/lang/String;)Lscala/runtime/Nothing$;
	athrow
  Labels:
   	l1 = 17 // aload_0
  LocalVariableTable: 
   Start  Length  Slot  Name   Signature
   0      48      0    this       Lscala/reflect/generic/UnPickler$Scan;
   5      43      1    temp12       Lscala/reflect/generic/Trees$Tree;


public scala.reflect.generic.Trees$CaseDef readCaseDefRef();
  Signature: ()Lscala/reflect/generic/Trees$CaseDef;
  Code:
   Stack=3, Locals=2, Args_size=1
	aload_0
	invokevirtual	Method readTreeRef:()Lscala/reflect/generic/Trees$Tree;
	astore_1
	aload_1
	instanceof	class scala/reflect/generic/Trees$CaseDef
	ifeq	l1 // aload_0
	aload_1
	checkcast	class scala/reflect/generic/Trees$CaseDef
	areturn
l1	aload_0
	new	class scala/collection/mutable/StringBuilder
	dup
	invokespecial	Method scala/collection/mutable/StringBuilder."<init>":()V
	ldc_w	String expected a case def (
	invokevirtual	Method scala/collection/mutable/StringBuilder.append:(Ljava/lang/Object;)Lscala/collection/mutable/StringBuilder;
	aload_1
	invokevirtual	Method scala/collection/mutable/StringBuilder.append:(Ljava/lang/Object;)Lscala/collection/mutable/StringBuilder;
	ldc_w	String )
	invokevirtual	Method scala/collection/mutable/StringBuilder.append:(Ljava/lang/Object;)Lscala/collection/mutable/StringBuilder;
	invokevirtual	Method scala/collection/mutable/StringBuilder.toString:()Ljava/lang/String;
	invokevirtual	Method errorBadSignature:(Ljava/lang/String;)Lscala/runtime/Nothing$;
	athrow
  Labels:
   	l1 = 17 // aload_0
  LocalVariableTable: 
   Start  Length  Slot  Name   Signature
   0      48      0    this       Lscala/reflect/generic/UnPickler$Scan;
   5      43      1    temp17       Lscala/reflect/generic/Trees$Tree;


public scala.reflect.generic.Trees$ValDef readValDefRef();
  Signature: ()Lscala/reflect/generic/Trees$ValDef;
  Code:
   Stack=3, Locals=2, Args_size=1
	aload_0
	invokevirtual	Method readTreeRef:()Lscala/reflect/generic/Trees$Tree;
	astore_1
	aload_1
	instanceof	class scala/reflect/generic/Trees$ValDef
	ifeq	l1 // aload_0
	aload_1
	checkcast	class scala/reflect/generic/Trees$ValDef
	areturn
l1	aload_0
	new	class scala/collection/mutable/StringBuilder
	dup
	invokespecial	Method scala/collection/mutable/StringBuilder."<init>":()V
	ldc_w	String expected a ValDef (
	invokevirtual	Method scala/collection/mutable/StringBuilder.append:(Ljava/lang/Object;)Lscala/collection/mutable/StringBuilder;
	aload_1
	invokevirtual	Method scala/collection/mutable/StringBuilder.append:(Ljava/lang/Object;)Lscala/collection/mutable/StringBuilder;
	ldc_w	String )
	invokevirtual	Method scala/collection/mutable/StringBuilder.append:(Ljava/lang/Object;)Lscala/collection/mutable/StringBuilder;
	invokevirtual	Method scala/collection/mutable/StringBuilder.toString:()Ljava/lang/String;
	invokevirtual	Method errorBadSignature:(Ljava/lang/String;)Lscala/runtime/Nothing$;
	athrow
  Labels:
   	l1 = 17 // aload_0
  LocalVariableTable: 
   Start  Length  Slot  Name   Signature
   0      48      0    this       Lscala/reflect/generic/UnPickler$Scan;
   5      43      1    temp22       Lscala/reflect/generic/Trees$Tree;


public scala.reflect.generic.Trees$Ident readIdentRef();
  Signature: ()Lscala/reflect/generic/Trees$Ident;
  Code:
   Stack=3, Locals=2, Args_size=1
	aload_0
	invokevirtual	Method readTreeRef:()Lscala/reflect/generic/Trees$Tree;
	astore_1
	aload_1
	instanceof	class scala/reflect/generic/Trees$Ident
	ifeq	l1 // aload_0
	aload_1
	checkcast	class scala/reflect/generic/Trees$Ident
	areturn
l1	aload_0
	new	class scala/collection/mutable/StringBuilder
	dup
	invokespecial	Method scala/collection/mutable/StringBuilder."<init>":()V
	ldc_w	String expected an Ident (
	invokevirtual	Method scala/collection/mutable/StringBuilder.append:(Ljava/lang/Object;)Lscala/collection/mutable/StringBuilder;
	aload_1
	invokevirtual	Method scala/collection/mutable/StringBuilder.append:(Ljava/lang/Object;)Lscala/collection/mutable/StringBuilder;
	ldc_w	String )
	invokevirtual	Method scala/collection/mutable/StringBuilder.append:(Ljava/lang/Object;)Lscala/collection/mutable/StringBuilder;
	invokevirtual	Method scala/collection/mutable/StringBuilder.toString:()Ljava/lang/String;
	invokevirtual	Method errorBadSignature:(Ljava/lang/String;)Lscala/runtime/Nothing$;
	athrow
  Labels:
   	l1 = 17 // aload_0
  LocalVariableTable: 
   Start  Length  Slot  Name   Signature
   0      48      0    this       Lscala/reflect/generic/UnPickler$Scan;
   5      43      1    temp28       Lscala/reflect/generic/Trees$Tree;


public scala.reflect.generic.Trees$TypeDef readTypeDefRef();
  Signature: ()Lscala/reflect/generic/Trees$TypeDef;
  Code:
   Stack=3, Locals=2, Args_size=1
	aload_0
	invokevirtual	Method readTreeRef:()Lscala/reflect/generic/Trees$Tree;
	astore_1
	aload_1
	instanceof	class scala/reflect/generic/Trees$TypeDef
	ifeq	l1 // aload_0
	aload_1
	checkcast	class scala/reflect/generic/Trees$TypeDef
	areturn
l1	aload_0
	new	class scala/collection/mutable/StringBuilder
	dup
	invokespecial	Method scala/collection/mutable/StringBuilder."<init>":()V
	ldc_w	String expected an TypeDef (
	invokevirtual	Method scala/collection/mutable/StringBuilder.append:(Ljava/lang/Object;)Lscala/collection/mutable/StringBuilder;
	aload_1
	invokevirtual	Method scala/collection/mutable/StringBuilder.append:(Ljava/lang/Object;)Lscala/collection/mutable/StringBuilder;
	ldc_w	String )
	invokevirtual	Method scala/collection/mutable/StringBuilder.append:(Ljava/lang/Object;)Lscala/collection/mutable/StringBuilder;
	invokevirtual	Method scala/collection/mutable/StringBuilder.toString:()Ljava/lang/String;
	invokevirtual	Method errorBadSignature:(Ljava/lang/String;)Lscala/runtime/Nothing$;
	athrow
  Labels:
   	l1 = 17 // aload_0
  LocalVariableTable: 
   Start  Length  Slot  Name   Signature
   0      48      0    this       Lscala/reflect/generic/UnPickler$Scan;
   5      43      1    temp31       Lscala/reflect/generic/Trees$Tree;


public scala.runtime.Nothing$ errorBadSignature(java.lang.String);
  Signature: (Ljava/lang/String;)Lscala/runtime/Nothing$;
  Code:
   Stack=4, Locals=2, Args_size=2
	new	class java/lang/RuntimeException
	dup
	new	class scala/collection/mutable/StringBuilder
	dup
	invokespecial	Method scala/collection/mutable/StringBuilder."<init>":()V
	ldc_w	String malformed Scala signature of 
	invokevirtual	Method scala/collection/mutable/StringBuilder.append:(Ljava/lang/Object;)Lscala/collection/mutable/StringBuilder;
	aload_0
	getfield	Field classRoot:Lscala/reflect/generic/Symbols$AbsSymbol;
	invokevirtual	Method scala/reflect/generic/Symbols$AbsSymbol.name:()Ljava/lang/Object;
	invokevirtual	Method scala/collection/mutable/StringBuilder.append:(Ljava/lang/Object;)Lscala/collection/mutable/StringBuilder;
	ldc_w	String  at 
	invokevirtual	Method scala/collection/mutable/StringBuilder.append:(Ljava/lang/Object;)Lscala/collection/mutable/StringBuilder;
	aload_0
	invokevirtual	Method readIndex:()I
	invokestatic	Method scala/runtime/BoxesRunTime.boxToInteger:(I)Ljava/lang/Integer;
	invokevirtual	Method scala/collection/mutable/StringBuilder.append:(Ljava/lang/Object;)Lscala/collection/mutable/StringBuilder;
	ldc_w	String ; 
	invokevirtual	Method scala/collection/mutable/StringBuilder.append:(Ljava/lang/Object;)Lscala/collection/mutable/StringBuilder;
	aload_1
	invokevirtual	Method scala/collection/mutable/StringBuilder.append:(Ljava/lang/Object;)Lscala/collection/mutable/StringBuilder;
	invokevirtual	Method scala/collection/mutable/StringBuilder.toString:()Ljava/lang/String;
	invokespecial	Method java/lang/RuntimeException."<init>":(Ljava/lang/String;)V
	athrow
  Labels:
  LocalVariableTable: 
   Start  Length  Slot  Name   Signature
   0      60      0    this       Lscala/reflect/generic/UnPickler$Scan;
   0      60      1    msg       Ljava/lang/String;


public scala.runtime.Nothing$ errorMissingRequirement(java.lang.String);
  Signature: (Ljava/lang/String;)Lscala/runtime/Nothing$;
  Code:
   Stack=4, Locals=2, Args_size=2
	aload_0
	invokevirtual	Method debug:()Z
	ifeq	l1 // new
	aload_0
	aload_1
	invokevirtual	Method errorBadSignature:(Ljava/lang/String;)Lscala/runtime/Nothing$;
	areturn
l1	new	class java/io/IOException
	dup
	new	class scala/collection/mutable/StringBuilder
	dup
	invokespecial	Method scala/collection/mutable/StringBuilder."<init>":()V
	ldc_w	String class file needed by 
	invokevirtual	Method scala/collection/mutable/StringBuilder.append:(Ljava/lang/Object;)Lscala/collection/mutable/StringBuilder;
	aload_0
	getfield	Field classRoot:Lscala/reflect/generic/Symbols$AbsSymbol;
	invokevirtual	Method scala/reflect/generic/Symbols$AbsSymbol.name:()Ljava/lang/Object;
	invokevirtual	Method scala/collection/mutable/StringBuilder.append:(Ljava/lang/Object;)Lscala/collection/mutable/StringBuilder;
	ldc_w	String  is missing.\n
	invokevirtual	Method scala/collection/mutable/StringBuilder.append:(Ljava/lang/Object;)Lscala/collection/mutable/StringBuilder;
	aload_1
	invokevirtual	Method scala/collection/mutable/StringBuilder.append:(Ljava/lang/Object;)Lscala/collection/mutable/StringBuilder;
	invokevirtual	Method scala/collection/mutable/StringBuilder.toString:()Ljava/lang/String;
	invokespecial	Method java/io/IOException."<init>":(Ljava/lang/String;)V
	athrow
  Labels:
   	l1 = 13 // new
  LocalVariableTable: 
   Start  Length  Slot  Name   Signature
   0      57      0    this       Lscala/reflect/generic/UnPickler$Scan;
   0      57      1    msg       Ljava/lang/String;


public scala.runtime.Nothing$ errorMissingRequirement(java.lang.Object, scala.reflect.generic.Symbols$AbsSymbol);
  Signature: (Ljava/lang/Object;Lscala/reflect/generic/Symbols$AbsSymbol;)Lscala/runtime/Nothing$;
  Code:
   Stack=4, Locals=3, Args_size=3
	aload_0
	new	class scala/collection/mutable/StringBuilder
	dup
	invokespecial	Method scala/collection/mutable/StringBuilder."<init>":()V
	ldc_w	String reference 
	invokevirtual	Method scala/collection/mutable/StringBuilder.append:(Ljava/lang/Object;)Lscala/collection/mutable/StringBuilder;
	getstatic	Field scala/reflect/NameTransformer$.MODULE$:Lscala/reflect/NameTransformer$;
	aload_1
	invokevirtual	Method java/lang/Object.toString:()Ljava/lang/String;
	invokevirtual	Method scala/reflect/NameTransformer$.decode:(Ljava/lang/String;)Ljava/lang/String;
	invokevirtual	Method scala/collection/mutable/StringBuilder.append:(Ljava/lang/Object;)Lscala/collection/mutable/StringBuilder;
	ldc_w	String  of 
	invokevirtual	Method scala/collection/mutable/StringBuilder.append:(Ljava/lang/Object;)Lscala/collection/mutable/StringBuilder;
	aload_2
	invokevirtual	Method scala/reflect/generic/Symbols$AbsSymbol.tpe:()Lscala/reflect/generic/Types$AbsType;
	invokevirtual	Method scala/collection/mutable/StringBuilder.append:(Ljava/lang/Object;)Lscala/collection/mutable/StringBuilder;
	ldc_w	String  refers to nonexisting symbol.
	invokevirtual	Method scala/collection/mutable/StringBuilder.append:(Ljava/lang/Object;)Lscala/collection/mutable/StringBuilder;
	invokevirtual	Method scala/collection/mutable/StringBuilder.toString:()Ljava/lang/String;
	invokevirtual	Method errorMissingRequirement:(Ljava/lang/String;)Lscala/runtime/Nothing$;
	areturn
  Labels:
  LocalVariableTable: 
   Start  Length  Slot  Name   Signature
   0      53      0    this       Lscala/reflect/generic/UnPickler$Scan;
   0      53      1    name       Ljava/lang/Object;
   0      53      2    owner       Lscala/reflect/generic/Symbols$AbsSymbol;


public abstract void inferMethodAlternative(scala.reflect.generic.Trees$Tree, scala.collection.immutable.List, scala.reflect.generic.Types$AbsType);
  Signature: (Lscala/reflect/generic/Trees$Tree;Lscala/collection/immutable/List;Lscala/reflect/generic/Types$AbsType;)V
  Signature: length = 0x2
   05 26 

public abstract scala.reflect.generic.Types$AbsType newLazyTypeRef(int);
  Signature: (I)Lscala/reflect/generic/Types$AbsType;

public abstract scala.reflect.generic.Types$AbsType newLazyTypeRefAndAlias(int, int);
  Signature: (II)Lscala/reflect/generic/Types$AbsType;

public scala.reflect.generic.UnPickler scala$reflect$generic$UnPickler$Scan$$$outer();
  Signature: ()Lscala/reflect/generic/UnPickler;
  Code:
   Stack=1, Locals=1, Args_size=1
	aload_0
	getfield	Field $outer:Lscala/reflect/generic/UnPickler;
	areturn
  Labels:

private final scala.reflect.generic.Symbols$AbsSymbol fromName$1(java.lang.Object, int, scala.reflect.generic.Symbols$AbsSymbol);
  Signature: (Ljava/lang/Object;ILscala/reflect/generic/Symbols$AbsSymbol;)Lscala/reflect/generic/Symbols$AbsSymbol;
  Code:
   Stack=2, Locals=4, Args_size=4
	aload_0
	invokevirtual	Method scala$reflect$generic$UnPickler$Scan$$$outer:()Lscala/reflect/generic/UnPickler;
	invokevirtual	Method scala/reflect/generic/UnPickler.global:()Lscala/reflect/generic/Universe;
	aload_1
	invokeinterface	InterfaceMethod scala/reflect/generic/Names.mkTermName:(Ljava/lang/Object;)Ljava/lang/Object;
	aload_0
	invokevirtual	Method scala$reflect$generic$UnPickler$Scan$$$outer:()Lscala/reflect/generic/UnPickler;
	invokevirtual	Method scala/reflect/generic/UnPickler.global:()Lscala/reflect/generic/Universe;
	invokeinterface	InterfaceMethod scala/reflect/generic/StdNames.nme:()Lscala/reflect/generic/StdNames$StandardNames;
	invokevirtual	Method scala/reflect/generic/StdNames$StandardNames.ROOT:()Ljava/lang/Object;
	invokestatic	Method scala/runtime/BoxesRunTime.equals:(Ljava/lang/Object;Ljava/lang/Object;)Z
	ifeq	l1 // aload_1
	aload_0
	invokevirtual	Method scala$reflect$generic$UnPickler$Scan$$$outer:()Lscala/reflect/generic/UnPickler;
	invokevirtual	Method scala/reflect/generic/UnPickler.global:()Lscala/reflect/generic/Universe;
	invokeinterface	InterfaceMethod scala/reflect/generic/StandardDefinitions.definitions:()Lscala/reflect/generic/StandardDefinitions$AbsDefinitions;
	invokevirtual	Method scala/reflect/generic/StandardDefinitions$AbsDefinitions.RootClass:()Lscala/reflect/generic/Symbols$AbsSymbol;
	goto	l2 // areturn
l1	aload_1
	aload_0
	invokevirtual	Method scala$reflect$generic$UnPickler$Scan$$$outer:()Lscala/reflect/generic/UnPickler;
	invokevirtual	Method scala/reflect/generic/UnPickler.global:()Lscala/reflect/generic/Universe;
	invokeinterface	InterfaceMethod scala/reflect/generic/StdNames.nme:()Lscala/reflect/generic/StdNames$StandardNames;
	invokevirtual	Method scala/reflect/generic/StdNames$StandardNames.ROOTPKG:()Ljava/lang/Object;
	invokestatic	Method scala/runtime/BoxesRunTime.equals:(Ljava/lang/Object;Ljava/lang/Object;)Z
	ifeq	l3 // iload_2
	aload_0
	invokevirtual	Method scala$reflect$generic$UnPickler$Scan$$$outer:()Lscala/reflect/generic/UnPickler;
	invokevirtual	Method scala/reflect/generic/UnPickler.global:()Lscala/reflect/generic/Universe;
	invokeinterface	InterfaceMethod scala/reflect/generic/StandardDefinitions.definitions:()Lscala/reflect/generic/StandardDefinitions$AbsDefinitions;
	invokevirtual	Method scala/reflect/generic/StandardDefinitions$AbsDefinitions.RootPackage:()Lscala/reflect/generic/Symbols$AbsSymbol;
	goto	l2 // areturn
l3	iload_2
	ldc_w	int 9
	if_icmpne	l4 // aload_3
	aload_3
	invokevirtual	Method scala/reflect/generic/Symbols$AbsSymbol.info:()Lscala/reflect/generic/Types$AbsType;
	aload_1
	invokevirtual	Method scala/reflect/generic/Types$AbsType.decl:(Ljava/lang/Object;)Lscala/reflect/generic/Symbols$AbsSymbol;
	goto	l2 // areturn
l4	aload_3
	invokevirtual	Method scala/reflect/generic/Symbols$AbsSymbol.info:()Lscala/reflect/generic/Types$AbsType;
	aload_1
	invokevirtual	Method scala/reflect/generic/Types$AbsType.decl:(Ljava/lang/Object;)Lscala/reflect/generic/Symbols$AbsSymbol;
	invokevirtual	Method scala/reflect/generic/Symbols$AbsSymbol.moduleClass:()Lscala/reflect/generic/Symbols$AbsSymbol;
l2	areturn
  Labels:
   	l1 = 52 // aload_1
   	l3 = 92 // iload_2
   	l4 = 110 // aload_3
   	l2 = 121 // areturn
  LocalVariableTable: 
   Start  Length  Slot  Name   Signature
   0      122      0    this       Lscala/reflect/generic/UnPickler$Scan;
   0      122      1    name       Ljava/lang/Object;


private final void setSymModsName$1(scala.runtime.ObjectRef, scala.runtime.ObjectRef, scala.runtime.ObjectRef);
  Signature: (Lscala/runtime/ObjectRef;Lscala/runtime/ObjectRef;Lscala/runtime/ObjectRef;)V
  Code:
   Stack=2, Locals=4, Args_size=4
	aload_1
	aload_0
	invokevirtual	Method readSymbolRef:()Lscala/reflect/generic/Symbols$AbsSymbol;
	putfield	Field scala/runtime/ObjectRef.elem:Ljava/lang/Object;
	aload_2
	aload_0
	invokevirtual	Method readModifiersRef:()Lscala/reflect/generic/Trees$Modifiers;
	putfield	Field scala/runtime/ObjectRef.elem:Ljava/lang/Object;
	aload_3
	aload_0
	invokevirtual	Method readNameRef:()Ljava/lang/Object;
	putfield	Field scala/runtime/ObjectRef.elem:Ljava/lang/Object;
	return
  Labels:

private final void setSymName$1(scala.runtime.ObjectRef, scala.runtime.ObjectRef);
  Signature: (Lscala/runtime/ObjectRef;Lscala/runtime/ObjectRef;)V
  Code:
   Stack=2, Locals=3, Args_size=3
	aload_1
	aload_0
	invokevirtual	Method readSymbolRef:()Lscala/reflect/generic/Symbols$AbsSymbol;
	putfield	Field scala/runtime/ObjectRef.elem:Ljava/lang/Object;
	aload_2
	aload_0
	invokevirtual	Method readNameRef:()Ljava/lang/Object;
	putfield	Field scala/runtime/ObjectRef.elem:Ljava/lang/Object;
	return
  Labels:

private final void setSym$1(scala.runtime.ObjectRef);
  Signature: (Lscala/runtime/ObjectRef;)V
  Code:
   Stack=2, Locals=2, Args_size=2
	aload_1
	aload_0
	invokevirtual	Method readSymbolRef:()Lscala/reflect/generic/Symbols$AbsSymbol;
	putfield	Field scala/runtime/ObjectRef.elem:Ljava/lang/Object;
	return
  Labels:

public scala.reflect.generic.UnPickler$Scan(scala.reflect.generic.UnPickler, byte[], int, scala.reflect.generic.Symbols$AbsSymbol, scala.reflect.generic.Symbols$AbsSymbol, java.lang.String);
  Signature: (Lscala/reflect/generic/UnPickler;[BILscala/reflect/generic/Symbols$AbsSymbol;Lscala/reflect/generic/Symbols$AbsSymbol;Ljava/lang/String;)V
  Code:
   Stack=4, Locals=7, Args_size=7
	aload_0
	aload_2
	putfield	Field bytes:[B
	aload_0
	aload	4
	putfield	Field classRoot:Lscala/reflect/generic/Symbols$AbsSymbol;
	aload_0
	aload	5
	putfield	Field moduleRoot:Lscala/reflect/generic/Symbols$AbsSymbol;
	aload_0
	aload	6
	putfield	Field filename:Ljava/lang/String;
	aload_1
	ifnonnull	l1 // aload_0
	new	class java/lang/NullPointerException
	dup
	invokespecial	Method java/lang/NullPointerException."<init>":()V
	athrow
l1	aload_0
	aload_1
	putfield	Field $outer:Lscala/reflect/generic/UnPickler;
	aload_0
	aload_2
	iload_3
	iconst_m1
	invokespecial	Method scala/reflect/generic/PickleBuffer."<init>":([BII)V
	aload_0
	invokespecial	Method checkVersion:()V
	aload_0
	aload_0
	invokevirtual	Method createIndex:()[I
	putfield	Field index:[I
	aload_0
	aload_0
	invokespecial	Method index:()[I
	arraylength
	anewarray	class java/lang/Object
	putfield	Field scala$reflect$generic$UnPickler$Scan$$entries:[Ljava/lang/Object;
	aload_0
	new	class scala/collection/mutable/HashMap
	dup
	invokespecial	Method scala/collection/mutable/HashMap."<init>":()V
	putfield	Field symScopes:Lscala/collection/mutable/HashMap;
	return
  Labels:
   	l1 = 35 // aload_0
  LocalVariableTable: 
   Start  Length  Slot  Name   Signature
   0      83      0    this       Lscala/reflect/generic/UnPickler$Scan;
   0      83      1    $outer       Lscala/reflect/generic/UnPickler;
   0      83      2    bytes       [B
   0      83      3    offset       I
   0      83      4    classRoot       Lscala/reflect/generic/Symbols$AbsSymbol;
   0      83      5    moduleRoot       Lscala/reflect/generic/Symbols$AbsSymbol;
   0      83      6    filename       Ljava/lang/String;


}

