Compiled from "UnPickler.scala"
public final class scala.reflect.generic.UnPickler$Scan$$anonfun$17 extends scala.runtime.AbstractFunction0 implements java.io.Serializable
  SourceFile: "UnPickler.scala"
  Scala: length = 0x
   
  InnerClass: 
   public abstract Scan=class scala/reflect/generic/UnPickler$Scan of class scala/reflect/generic/UnPickler
   public ImportSelector=class scala/reflect/generic/Trees$ImportSelector of class scala/reflect/generic/Trees
   public final $anonfun$17=class scala/reflect/generic/UnPickler$Scan$$anonfun$17 of class scala/reflect/generic/UnPickler$Scan
  minor version: 0
  major version: 49
  Constant pool:
Asciz	SourceFile;
Asciz	UnPickler.scala;
Asciz	<clinit>;
Asciz	()V;
Asciz	Code;
Asciz	serialVersionUID;
Asciz	J;
Asciz	scala/reflect/generic/UnPickler$Scan$$anonfun$17;
class	scala/reflect/generic/UnPickler$Scan$$anonfun$17
NameAndType	serialVersionUID:J
Field	scala/reflect/generic/UnPickler$Scan$$anonfun$17.serialVersionUID:J
Asciz	$outer;
Asciz	Lscala/reflect/generic/UnPickler$Scan;;
Asciz	apply;
Asciz	()Lscala/reflect/generic/Trees$ImportSelector;;
Asciz	LineNumberTable;
NameAndType	$outer:Lscala/reflect/generic/UnPickler$Scan;
Field	scala/reflect/generic/UnPickler$Scan$$anonfun$17.$outer:Lscala/reflect/generic/UnPickler$Scan;
Asciz	scala/reflect/generic/UnPickler$Scan;
class	scala/reflect/generic/UnPickler$Scan
Asciz	readNameRef;
Asciz	()Ljava/lang/Object;;
NameAndType	readNameRef:()Ljava/lang/Object;
Method	scala/reflect/generic/UnPickler$Scan.readNameRef:()Ljava/lang/Object;
Asciz	scala/reflect/generic/Trees$ImportSelector;
class	scala/reflect/generic/Trees$ImportSelector
Asciz	scala$reflect$generic$UnPickler$Scan$$$outer;
Asciz	()Lscala/reflect/generic/UnPickler;;
NameAndType	scala$reflect$generic$UnPickler$Scan$$$outer:()Lscala/reflect/generic/UnPickler;
Method	scala/reflect/generic/UnPickler$Scan.scala$reflect$generic$UnPickler$Scan$$$outer:()Lscala/reflect/generic/UnPickler;
Asciz	scala/reflect/generic/UnPickler;
class	scala/reflect/generic/UnPickler
Asciz	global;
Asciz	()Lscala/reflect/generic/Universe;;
NameAndType	global:()Lscala/reflect/generic/Universe;
Method	scala/reflect/generic/UnPickler.global:()Lscala/reflect/generic/Universe;
Asciz	<init>;
Asciz	(Lscala/reflect/generic/Universe;Ljava/lang/Object;ILjava/lang/Object;I)V;
NameAndType	"<init>":(Lscala/reflect/generic/Universe;Ljava/lang/Object;ILjava/lang/Object;I)V
Method	scala/reflect/generic/Trees$ImportSelector."<init>":(Lscala/reflect/generic/Universe;Ljava/lang/Object;ILjava/lang/Object;I)V
Asciz	this;
Asciz	Lscala/reflect/generic/UnPickler$Scan$$anonfun$17;;
Asciz	from;
Asciz	Ljava/lang/Object;;
Asciz	to;
Asciz	LocalVariableTable;
NameAndType	apply:()Lscala/reflect/generic/Trees$ImportSelector;
Method	scala/reflect/generic/UnPickler$Scan$$anonfun$17.apply:()Lscala/reflect/generic/Trees$ImportSelector;
Asciz	(Lscala/reflect/generic/UnPickler$Scan;)V;
Asciz	java/lang/NullPointerException;
class	java/lang/NullPointerException
NameAndType	"<init>":()V
Method	java/lang/NullPointerException."<init>":()V
Asciz	scala/runtime/AbstractFunction0;
class	scala/runtime/AbstractFunction0
Method	scala/runtime/AbstractFunction0."<init>":()V
Asciz	Scala;
Asciz	InnerClasses;
Asciz	Scan;
Asciz	scala/reflect/generic/Trees;
class	scala/reflect/generic/Trees
Asciz	ImportSelector;
Asciz	$anonfun$17;
Asciz	java/io/Serializable;
class	java/io/Serializable

{
public static final long serialVersionUID;
  Signature: J

public final scala.reflect.generic.UnPickler$Scan $outer;
  Signature: Lscala/reflect/generic/UnPickler$Scan;

public static {};
  Signature: ()V
  Code:
   Stack=2, Locals=0, Args_size=0
	lconst_0
	putstatic	Field serialVersionUID:J
	return
  Labels:

public final scala.reflect.generic.Trees$ImportSelector apply();
  Signature: ()Lscala/reflect/generic/Trees$ImportSelector;
  Code:
   Stack=7, Locals=3, Args_size=1
	aload_0
	getfield	Field $outer:Lscala/reflect/generic/UnPickler$Scan;
	invokevirtual	Method scala/reflect/generic/UnPickler$Scan.readNameRef:()Ljava/lang/Object;
	astore_1
	aload_0
	getfield	Field $outer:Lscala/reflect/generic/UnPickler$Scan;
	invokevirtual	Method scala/reflect/generic/UnPickler$Scan.readNameRef:()Ljava/lang/Object;
	astore_2
	new	class scala/reflect/generic/Trees$ImportSelector
	dup
	aload_0
	getfield	Field $outer:Lscala/reflect/generic/UnPickler$Scan;
	invokevirtual	Method scala/reflect/generic/UnPickler$Scan.scala$reflect$generic$UnPickler$Scan$$$outer:()Lscala/reflect/generic/UnPickler;
	invokevirtual	Method scala/reflect/generic/UnPickler.global:()Lscala/reflect/generic/Universe;
	aload_1
	iconst_m1
	aload_2
	iconst_m1
	invokespecial	Method scala/reflect/generic/Trees$ImportSelector."<init>":(Lscala/reflect/generic/Universe;Ljava/lang/Object;ILjava/lang/Object;I)V
	areturn
  Labels:
  LocalVariableTable: 
   Start  Length  Slot  Name   Signature
   0      38      0    this       Lscala/reflect/generic/UnPickler$Scan$$anonfun$17;
   8      29      1    from       Ljava/lang/Object;
   16      21      2    to       Ljava/lang/Object;


public final java.lang.Object apply();
  Signature: ()Ljava/lang/Object;
  Code:
   Stack=1, Locals=1, Args_size=1
	aload_0
	invokevirtual	Method apply:()Lscala/reflect/generic/Trees$ImportSelector;
	areturn
  Labels:

public scala.reflect.generic.UnPickler$Scan$$anonfun$17(scala.reflect.generic.UnPickler$Scan);
  Signature: (Lscala/reflect/generic/UnPickler$Scan;)V
  Code:
   Stack=2, Locals=2, Args_size=2
	aload_1
	ifnonnull	l1 // aload_0
	new	class java/lang/NullPointerException
	dup
	invokespecial	Method java/lang/NullPointerException."<init>":()V
	athrow
l1	aload_0
	aload_1
	putfield	Field $outer:Lscala/reflect/generic/UnPickler$Scan;
	aload_0
	invokespecial	Method scala/runtime/AbstractFunction0."<init>":()V
	return
  Labels:
   	l1 = 12 // aload_0
  LocalVariableTable: 
   Start  Length  Slot  Name   Signature
   0      22      0    this       Lscala/reflect/generic/UnPickler$Scan$$anonfun$17;
   0      22      1    $outer       Lscala/reflect/generic/UnPickler$Scan;


}

