Compiled from "UnPickler.scala"
public final class scala.reflect.generic.UnPickler$Scan$$anonfun$readClassfileAnnotArg$2$$anonfun$apply$4 extends scala.runtime.AbstractFunction0 implements java.io.Serializable
  SourceFile: "UnPickler.scala"
  Scala: length = 0x
   
  InnerClass: 
   public abstract Scan=class scala/reflect/generic/UnPickler$Scan of class scala/reflect/generic/UnPickler
   public final $anonfun$readClassfileAnnotArg$2=class scala/reflect/generic/UnPickler$Scan$$anonfun$readClassfileAnnotArg$2 of class scala/reflect/generic/UnPickler$Scan
   public final $anonfun$apply$4=class scala/reflect/generic/UnPickler$Scan$$anonfun$readClassfileAnnotArg$2$$anonfun$apply$4 of class scala/reflect/generic/UnPickler$Scan$$anonfun$readClassfileAnnotArg$2
  minor version: 0
  major version: 49
  Constant pool:
Asciz	SourceFile;
Asciz	UnPickler.scala;
Asciz	<clinit>;
Asciz	()V;
Asciz	Code;
Asciz	serialVersionUID;
Asciz	J;
Asciz	scala/reflect/generic/UnPickler$Scan$$anonfun$readClassfileAnnotArg$2$$anonfun$apply$4;
class	scala/reflect/generic/UnPickler$Scan$$anonfun$readClassfileAnnotArg$2$$anonfun$apply$4
NameAndType	serialVersionUID:J
Field	scala/reflect/generic/UnPickler$Scan$$anonfun$readClassfileAnnotArg$2$$anonfun$apply$4.serialVersionUID:J
Asciz	$outer;
Asciz	Lscala/reflect/generic/UnPickler$Scan$$anonfun$readClassfileAnnotArg$2;;
Asciz	apply;
Asciz	()Ljava/lang/Object;;
Asciz	LineNumberTable;
NameAndType	$outer:Lscala/reflect/generic/UnPickler$Scan$$anonfun$readClassfileAnnotArg$2;
Field	scala/reflect/generic/UnPickler$Scan$$anonfun$readClassfileAnnotArg$2$$anonfun$apply$4.$outer:Lscala/reflect/generic/UnPickler$Scan$$anonfun$readClassfileAnnotArg$2;
Asciz	scala/reflect/generic/UnPickler$Scan$$anonfun$readClassfileAnnotArg$2;
class	scala/reflect/generic/UnPickler$Scan$$anonfun$readClassfileAnnotArg$2
Asciz	scala$reflect$generic$UnPickler$Scan$$anonfun$$$outer;
Asciz	()Lscala/reflect/generic/UnPickler$Scan;;
NameAndType	scala$reflect$generic$UnPickler$Scan$$anonfun$$$outer:()Lscala/reflect/generic/UnPickler$Scan;
Method	scala/reflect/generic/UnPickler$Scan$$anonfun$readClassfileAnnotArg$2.scala$reflect$generic$UnPickler$Scan$$anonfun$$$outer:()Lscala/reflect/generic/UnPickler$Scan;
Asciz	scala/reflect/generic/UnPickler$Scan;
class	scala/reflect/generic/UnPickler$Scan
Asciz	readNat;
Asciz	()I;
NameAndType	readNat:()I
Method	scala/reflect/generic/UnPickler$Scan.readNat:()I
Asciz	readClassfileAnnotArg;
Asciz	(I)Ljava/lang/Object;;
NameAndType	readClassfileAnnotArg:(I)Ljava/lang/Object;
Method	scala/reflect/generic/UnPickler$Scan.readClassfileAnnotArg:(I)Ljava/lang/Object;
Asciz	<init>;
Asciz	(Lscala/reflect/generic/UnPickler$Scan$$anonfun$readClassfileAnnotArg$2;)V;
Asciz	java/lang/NullPointerException;
class	java/lang/NullPointerException
NameAndType	"<init>":()V
Method	java/lang/NullPointerException."<init>":()V
Asciz	scala/runtime/AbstractFunction0;
class	scala/runtime/AbstractFunction0
Method	scala/runtime/AbstractFunction0."<init>":()V
Asciz	this;
Asciz	Lscala/reflect/generic/UnPickler$Scan$$anonfun$readClassfileAnnotArg$2$$anonfun$apply$4;;
Asciz	LocalVariableTable;
Asciz	Scala;
Asciz	InnerClasses;
Asciz	scala/reflect/generic/UnPickler;
class	scala/reflect/generic/UnPickler
Asciz	Scan;
Asciz	$anonfun$readClassfileAnnotArg$2;
Asciz	$anonfun$apply$4;
Asciz	java/io/Serializable;
class	java/io/Serializable

{
public static final long serialVersionUID;
  Signature: J

private final scala.reflect.generic.UnPickler$Scan$$anonfun$readClassfileAnnotArg$2 $outer;
  Signature: Lscala/reflect/generic/UnPickler$Scan$$anonfun$readClassfileAnnotArg$2;

public static {};
  Signature: ()V
  Code:
   Stack=2, Locals=0, Args_size=0
	lconst_0
	putstatic	Field serialVersionUID:J
	return
  Labels:

public final java.lang.Object apply();
  Signature: ()Ljava/lang/Object;
  Code:
   Stack=2, Locals=1, Args_size=1
	aload_0
	getfield	Field $outer:Lscala/reflect/generic/UnPickler$Scan$$anonfun$readClassfileAnnotArg$2;
	invokevirtual	Method scala/reflect/generic/UnPickler$Scan$$anonfun$readClassfileAnnotArg$2.scala$reflect$generic$UnPickler$Scan$$anonfun$$$outer:()Lscala/reflect/generic/UnPickler$Scan;
	aload_0
	getfield	Field $outer:Lscala/reflect/generic/UnPickler$Scan$$anonfun$readClassfileAnnotArg$2;
	invokevirtual	Method scala/reflect/generic/UnPickler$Scan$$anonfun$readClassfileAnnotArg$2.scala$reflect$generic$UnPickler$Scan$$anonfun$$$outer:()Lscala/reflect/generic/UnPickler$Scan;
	invokevirtual	Method scala/reflect/generic/UnPickler$Scan.readNat:()I
	invokevirtual	Method scala/reflect/generic/UnPickler$Scan.readClassfileAnnotArg:(I)Ljava/lang/Object;
	areturn
  Labels:

public scala.reflect.generic.UnPickler$Scan$$anonfun$readClassfileAnnotArg$2$$anonfun$apply$4(scala.reflect.generic.UnPickler$Scan$$anonfun$readClassfileAnnotArg$2);
  Signature: (Lscala/reflect/generic/UnPickler$Scan$$anonfun$readClassfileAnnotArg$2;)V
  Code:
   Stack=2, Locals=2, Args_size=2
	aload_1
	ifnonnull	l1 // aload_0
	new	class java/lang/NullPointerException
	dup
	invokespecial	Method java/lang/NullPointerException."<init>":()V
	athrow
l1	aload_0
	aload_1
	putfield	Field $outer:Lscala/reflect/generic/UnPickler$Scan$$anonfun$readClassfileAnnotArg$2;
	aload_0
	invokespecial	Method scala/runtime/AbstractFunction0."<init>":()V
	return
  Labels:
   	l1 = 12 // aload_0
  LocalVariableTable: 
   Start  Length  Slot  Name   Signature
   0      22      0    this       Lscala/reflect/generic/UnPickler$Scan$$anonfun$readClassfileAnnotArg$2$$anonfun$apply$4;
   0      22      1    $outer       Lscala/reflect/generic/UnPickler$Scan$$anonfun$readClassfileAnnotArg$2;


}

