Compiled from "UnPickler.scala"
public final class scala.reflect.generic.UnPickler$Scan$$anonfun$14 extends scala.runtime.AbstractFunction0 implements java.io.Serializable
  SourceFile: "UnPickler.scala"
  Scala: length = 0x
   
  InnerClass: 
   public abstract Scan=class scala/reflect/generic/UnPickler$Scan of class scala/reflect/generic/UnPickler
   public final $anonfun$14=class scala/reflect/generic/UnPickler$Scan$$anonfun$14 of class scala/reflect/generic/UnPickler$Scan
   public final $anonfun$apply$5=class scala/reflect/generic/UnPickler$Scan$$anonfun$14$$anonfun$apply$5 of class scala/reflect/generic/UnPickler$Scan$$anonfun$14
  minor version: 0
  major version: 49
  Constant pool:
Asciz	SourceFile;
Asciz	UnPickler.scala;
Asciz	<clinit>;
Asciz	()V;
Asciz	Code;
Asciz	serialVersionUID;
Asciz	J;
Asciz	scala/reflect/generic/UnPickler$Scan$$anonfun$14;
class	scala/reflect/generic/UnPickler$Scan$$anonfun$14
NameAndType	serialVersionUID:J
Field	scala/reflect/generic/UnPickler$Scan$$anonfun$14.serialVersionUID:J
Asciz	$outer;
Asciz	Lscala/reflect/generic/UnPickler$Scan;;
Asciz	apply;
Asciz	()Lscala/collection/immutable/List;;
Asciz	LineNumberTable;
NameAndType	$outer:Lscala/reflect/generic/UnPickler$Scan;
Field	scala/reflect/generic/UnPickler$Scan$$anonfun$14.$outer:Lscala/reflect/generic/UnPickler$Scan;
Asciz	scala/reflect/generic/UnPickler$Scan;
class	scala/reflect/generic/UnPickler$Scan
Asciz	readNat;
Asciz	()I;
NameAndType	readNat:()I
Method	scala/reflect/generic/UnPickler$Scan.readNat:()I
Asciz	scala/reflect/generic/UnPickler$Scan$$anonfun$14$$anonfun$apply$5;
class	scala/reflect/generic/UnPickler$Scan$$anonfun$14$$anonfun$apply$5
Asciz	<init>;
Asciz	(Lscala/reflect/generic/UnPickler$Scan$$anonfun$14;)V;
NameAndType	"<init>":(Lscala/reflect/generic/UnPickler$Scan$$anonfun$14;)V
Method	scala/reflect/generic/UnPickler$Scan$$anonfun$14$$anonfun$apply$5."<init>":(Lscala/reflect/generic/UnPickler$Scan$$anonfun$14;)V
Asciz	times;
Asciz	(ILscala/Function0;)Lscala/collection/immutable/List;;
NameAndType	times:(ILscala/Function0;)Lscala/collection/immutable/List;
Method	scala/reflect/generic/UnPickler$Scan.times:(ILscala/Function0;)Lscala/collection/immutable/List;
Asciz	()Lscala/collection/immutable/List<Lscala/reflect/generic/Trees$ValDef;>;;
Asciz	Signature;
Asciz	scala$reflect$generic$UnPickler$Scan$$anonfun$$$outer;
Asciz	()Lscala/reflect/generic/UnPickler$Scan;;
Asciz	()Ljava/lang/Object;;
NameAndType	apply:()Lscala/collection/immutable/List;
Method	scala/reflect/generic/UnPickler$Scan$$anonfun$14.apply:()Lscala/collection/immutable/List;
Asciz	(Lscala/reflect/generic/UnPickler$Scan;)V;
Asciz	java/lang/NullPointerException;
class	java/lang/NullPointerException
NameAndType	"<init>":()V
Method	java/lang/NullPointerException."<init>":()V
Asciz	scala/runtime/AbstractFunction0;
class	scala/runtime/AbstractFunction0
Method	scala/runtime/AbstractFunction0."<init>":()V
Asciz	this;
Asciz	Lscala/reflect/generic/UnPickler$Scan$$anonfun$14;;
Asciz	LocalVariableTable;
Asciz	Scala;
Asciz	InnerClasses;
Asciz	scala/reflect/generic/UnPickler;
class	scala/reflect/generic/UnPickler
Asciz	Scan;
Asciz	$anonfun$14;
Asciz	$anonfun$apply$5;
Asciz	java/io/Serializable;
class	java/io/Serializable

{
public static final long serialVersionUID;
  Signature: J

private final scala.reflect.generic.UnPickler$Scan $outer;
  Signature: Lscala/reflect/generic/UnPickler$Scan;

public static {};
  Signature: ()V
  Code:
   Stack=2, Locals=0, Args_size=0
	lconst_0
	putstatic	Field serialVersionUID:J
	return
  Labels:

public final scala.collection.immutable.List apply();
  Signature: ()Lscala/collection/immutable/List;
  Code:
   Stack=5, Locals=1, Args_size=1
	aload_0
	getfield	Field $outer:Lscala/reflect/generic/UnPickler$Scan;
	aload_0
	getfield	Field $outer:Lscala/reflect/generic/UnPickler$Scan;
	invokevirtual	Method scala/reflect/generic/UnPickler$Scan.readNat:()I
	new	class scala/reflect/generic/UnPickler$Scan$$anonfun$14$$anonfun$apply$5
	dup
	aload_0
	invokespecial	Method scala/reflect/generic/UnPickler$Scan$$anonfun$14$$anonfun$apply$5."<init>":(Lscala/reflect/generic/UnPickler$Scan$$anonfun$14;)V
	invokevirtual	Method scala/reflect/generic/UnPickler$Scan.times:(ILscala/Function0;)Lscala/collection/immutable/List;
	areturn
  Labels:
  Signature: length = 0x2
   00 23 

public scala.reflect.generic.UnPickler$Scan scala$reflect$generic$UnPickler$Scan$$anonfun$$$outer();
  Signature: ()Lscala/reflect/generic/UnPickler$Scan;
  Code:
   Stack=1, Locals=1, Args_size=1
	aload_0
	getfield	Field $outer:Lscala/reflect/generic/UnPickler$Scan;
	areturn
  Labels:

public final java.lang.Object apply();
  Signature: ()Ljava/lang/Object;
  Code:
   Stack=1, Locals=1, Args_size=1
	aload_0
	invokevirtual	Method apply:()Lscala/collection/immutable/List;
	areturn
  Labels:

public scala.reflect.generic.UnPickler$Scan$$anonfun$14(scala.reflect.generic.UnPickler$Scan);
  Signature: (Lscala/reflect/generic/UnPickler$Scan;)V
  Code:
   Stack=2, Locals=2, Args_size=2
	aload_1
	ifnonnull	l1 // aload_0
	new	class java/lang/NullPointerException
	dup
	invokespecial	Method java/lang/NullPointerException."<init>":()V
	athrow
l1	aload_0
	aload_1
	putfield	Field $outer:Lscala/reflect/generic/UnPickler$Scan;
	aload_0
	invokespecial	Method scala/runtime/AbstractFunction0."<init>":()V
	return
  Labels:
   	l1 = 12 // aload_0
  LocalVariableTable: 
   Start  Length  Slot  Name   Signature
   0      22      0    this       Lscala/reflect/generic/UnPickler$Scan$$anonfun$14;
   0      22      1    $outer       Lscala/reflect/generic/UnPickler$Scan;


}

