Compiled from "UnPickler.scala"
public final class scala.reflect.generic.UnPickler$Scan$$anonfun$readClassfileAnnotArg$2 extends scala.runtime.AbstractFunction0 implements java.io.Serializable
  SourceFile: "UnPickler.scala"
  Scala: length = 0x
   
  InnerClass: 
   public abstract Scan=class scala/reflect/generic/UnPickler$Scan of class scala/reflect/generic/UnPickler
   public abstract ArrayAnnotArgExtractor=class scala/reflect/generic/AnnotationInfos$ArrayAnnotArgExtractor of class scala/reflect/generic/AnnotationInfos
   public final $anonfun$readClassfileAnnotArg$2=class scala/reflect/generic/UnPickler$Scan$$anonfun$readClassfileAnnotArg$2 of class scala/reflect/generic/UnPickler$Scan
   public final $anonfun$apply$4=class scala/reflect/generic/UnPickler$Scan$$anonfun$readClassfileAnnotArg$2$$anonfun$apply$4 of class scala/reflect/generic/UnPickler$Scan$$anonfun$readClassfileAnnotArg$2
  minor version: 0
  major version: 49
  Constant pool:
Asciz	SourceFile;
Asciz	UnPickler.scala;
Asciz	<clinit>;
Asciz	()V;
Asciz	Code;
Asciz	serialVersionUID;
Asciz	J;
Asciz	scala/reflect/generic/UnPickler$Scan$$anonfun$readClassfileAnnotArg$2;
class	scala/reflect/generic/UnPickler$Scan$$anonfun$readClassfileAnnotArg$2
NameAndType	serialVersionUID:J
Field	scala/reflect/generic/UnPickler$Scan$$anonfun$readClassfileAnnotArg$2.serialVersionUID:J
Asciz	$outer;
Asciz	Lscala/reflect/generic/UnPickler$Scan;;
Asciz	apply;
Asciz	()Ljava/lang/Object;;
Asciz	LineNumberTable;
NameAndType	$outer:Lscala/reflect/generic/UnPickler$Scan;
Field	scala/reflect/generic/UnPickler$Scan$$anonfun$readClassfileAnnotArg$2.$outer:Lscala/reflect/generic/UnPickler$Scan;
Asciz	scala/reflect/generic/UnPickler$Scan;
class	scala/reflect/generic/UnPickler$Scan
Asciz	readByte;
Asciz	()I;
NameAndType	readByte:()I
Method	scala/reflect/generic/UnPickler$Scan.readByte:()I
Asciz	readNat;
NameAndType	readNat:()I
Method	scala/reflect/generic/UnPickler$Scan.readNat:()I
Asciz	readIndex;
NameAndType	readIndex:()I
Method	scala/reflect/generic/UnPickler$Scan.readIndex:()I
Asciz	scala$reflect$generic$UnPickler$Scan$$$outer;
Asciz	()Lscala/reflect/generic/UnPickler;;
NameAndType	scala$reflect$generic$UnPickler$Scan$$$outer:()Lscala/reflect/generic/UnPickler;
Method	scala/reflect/generic/UnPickler$Scan.scala$reflect$generic$UnPickler$Scan$$$outer:()Lscala/reflect/generic/UnPickler;
Asciz	scala/reflect/generic/UnPickler;
class	scala/reflect/generic/UnPickler
Asciz	global;
Asciz	()Lscala/reflect/generic/Universe;;
NameAndType	global:()Lscala/reflect/generic/Universe;
Method	scala/reflect/generic/UnPickler.global:()Lscala/reflect/generic/Universe;
Asciz	scala/reflect/generic/AnnotationInfos;
class	scala/reflect/generic/AnnotationInfos
Asciz	ArrayAnnotArg;
Asciz	()Lscala/reflect/generic/AnnotationInfos$ArrayAnnotArgExtractor;;
NameAndType	ArrayAnnotArg:()Lscala/reflect/generic/AnnotationInfos$ArrayAnnotArgExtractor;
InterfaceMethod	scala/reflect/generic/AnnotationInfos.ArrayAnnotArg:()Lscala/reflect/generic/AnnotationInfos$ArrayAnnotArgExtractor;
Asciz	scala/reflect/generic/UnPickler$Scan$$anonfun$readClassfileAnnotArg$2$$anonfun$apply$4;
class	scala/reflect/generic/UnPickler$Scan$$anonfun$readClassfileAnnotArg$2$$anonfun$apply$4
Asciz	<init>;
Asciz	(Lscala/reflect/generic/UnPickler$Scan$$anonfun$readClassfileAnnotArg$2;)V;
NameAndType	"<init>":(Lscala/reflect/generic/UnPickler$Scan$$anonfun$readClassfileAnnotArg$2;)V
Method	scala/reflect/generic/UnPickler$Scan$$anonfun$readClassfileAnnotArg$2$$anonfun$apply$4."<init>":(Lscala/reflect/generic/UnPickler$Scan$$anonfun$readClassfileAnnotArg$2;)V
Asciz	until;
Asciz	(ILscala/Function0;)Lscala/collection/immutable/List;;
NameAndType	until:(ILscala/Function0;)Lscala/collection/immutable/List;
Method	scala/reflect/generic/UnPickler$Scan.until:(ILscala/Function0;)Lscala/collection/immutable/List;
Asciz	classfileAnnotArgManifest;
Asciz	()Lscala/reflect/ClassManifest;;
NameAndType	classfileAnnotArgManifest:()Lscala/reflect/ClassManifest;
InterfaceMethod	scala/reflect/generic/AnnotationInfos.classfileAnnotArgManifest:()Lscala/reflect/ClassManifest;
Asciz	scala/collection/TraversableLike;
class	scala/collection/TraversableLike
Asciz	toArray;
Asciz	(Lscala/reflect/ClassManifest;)Ljava/lang/Object;;
NameAndType	toArray:(Lscala/reflect/ClassManifest;)Ljava/lang/Object;
InterfaceMethod	scala/collection/TraversableLike.toArray:(Lscala/reflect/ClassManifest;)Ljava/lang/Object;
Asciz	[Ljava/lang/Object;;
class	"[Ljava/lang/Object;"
Asciz	scala/reflect/generic/AnnotationInfos$ArrayAnnotArgExtractor;
class	scala/reflect/generic/AnnotationInfos$ArrayAnnotArgExtractor
Asciz	([Ljava/lang/Object;)Ljava/lang/Object;;
NameAndType	apply:([Ljava/lang/Object;)Ljava/lang/Object;
Method	scala/reflect/generic/AnnotationInfos$ArrayAnnotArgExtractor.apply:([Ljava/lang/Object;)Ljava/lang/Object;
Asciz	this;
Asciz	Lscala/reflect/generic/UnPickler$Scan$$anonfun$readClassfileAnnotArg$2;;
Asciz	end;
Asciz	I;
Asciz	LocalVariableTable;
Asciz	scala$reflect$generic$UnPickler$Scan$$anonfun$$$outer;
Asciz	()Lscala/reflect/generic/UnPickler$Scan;;
Asciz	(Lscala/reflect/generic/UnPickler$Scan;)V;
Asciz	java/lang/NullPointerException;
class	java/lang/NullPointerException
NameAndType	"<init>":()V
Method	java/lang/NullPointerException."<init>":()V
Asciz	scala/runtime/AbstractFunction0;
class	scala/runtime/AbstractFunction0
Method	scala/runtime/AbstractFunction0."<init>":()V
Asciz	Scala;
Asciz	InnerClasses;
Asciz	Scan;
Asciz	ArrayAnnotArgExtractor;
Asciz	$anonfun$readClassfileAnnotArg$2;
Asciz	$anonfun$apply$4;
Asciz	java/io/Serializable;
class	java/io/Serializable

{
public static final long serialVersionUID;
  Signature: J

private final scala.reflect.generic.UnPickler$Scan $outer;
  Signature: Lscala/reflect/generic/UnPickler$Scan;

public static {};
  Signature: ()V
  Code:
   Stack=2, Locals=0, Args_size=0
	lconst_0
	putstatic	Field serialVersionUID:J
	return
  Labels:

public final java.lang.Object apply();
  Signature: ()Ljava/lang/Object;
  Code:
   Stack=6, Locals=2, Args_size=1
	aload_0
	getfield	Field $outer:Lscala/reflect/generic/UnPickler$Scan;
	invokevirtual	Method scala/reflect/generic/UnPickler$Scan.readByte:()I
	pop
	aload_0
	getfield	Field $outer:Lscala/reflect/generic/UnPickler$Scan;
	invokevirtual	Method scala/reflect/generic/UnPickler$Scan.readNat:()I
	aload_0
	getfield	Field $outer:Lscala/reflect/generic/UnPickler$Scan;
	invokevirtual	Method scala/reflect/generic/UnPickler$Scan.readIndex:()I
	iadd
	istore_1
	aload_0
	getfield	Field $outer:Lscala/reflect/generic/UnPickler$Scan;
	invokevirtual	Method scala/reflect/generic/UnPickler$Scan.scala$reflect$generic$UnPickler$Scan$$$outer:()Lscala/reflect/generic/UnPickler;
	invokevirtual	Method scala/reflect/generic/UnPickler.global:()Lscala/reflect/generic/Universe;
	invokeinterface	InterfaceMethod scala/reflect/generic/AnnotationInfos.ArrayAnnotArg:()Lscala/reflect/generic/AnnotationInfos$ArrayAnnotArgExtractor;
	aload_0
	getfield	Field $outer:Lscala/reflect/generic/UnPickler$Scan;
	iload_1
	new	class scala/reflect/generic/UnPickler$Scan$$anonfun$readClassfileAnnotArg$2$$anonfun$apply$4
	dup
	aload_0
	invokespecial	Method scala/reflect/generic/UnPickler$Scan$$anonfun$readClassfileAnnotArg$2$$anonfun$apply$4."<init>":(Lscala/reflect/generic/UnPickler$Scan$$anonfun$readClassfileAnnotArg$2;)V
	invokevirtual	Method scala/reflect/generic/UnPickler$Scan.until:(ILscala/Function0;)Lscala/collection/immutable/List;
	aload_0
	getfield	Field $outer:Lscala/reflect/generic/UnPickler$Scan;
	invokevirtual	Method scala/reflect/generic/UnPickler$Scan.scala$reflect$generic$UnPickler$Scan$$$outer:()Lscala/reflect/generic/UnPickler;
	invokevirtual	Method scala/reflect/generic/UnPickler.global:()Lscala/reflect/generic/Universe;
	invokeinterface	InterfaceMethod scala/reflect/generic/AnnotationInfos.classfileAnnotArgManifest:()Lscala/reflect/ClassManifest;
	invokeinterface	InterfaceMethod scala/collection/TraversableLike.toArray:(Lscala/reflect/ClassManifest;)Ljava/lang/Object;
	checkcast	class "[Ljava/lang/Object;"
	invokevirtual	Method scala/reflect/generic/AnnotationInfos$ArrayAnnotArgExtractor.apply:([Ljava/lang/Object;)Ljava/lang/Object;
	areturn
  Labels:
  LocalVariableTable: 
   Start  Length  Slot  Name   Signature
   0      82      0    this       Lscala/reflect/generic/UnPickler$Scan$$anonfun$readClassfileAnnotArg$2;
   24      57      1    end       I


public scala.reflect.generic.UnPickler$Scan scala$reflect$generic$UnPickler$Scan$$anonfun$$$outer();
  Signature: ()Lscala/reflect/generic/UnPickler$Scan;
  Code:
   Stack=1, Locals=1, Args_size=1
	aload_0
	getfield	Field $outer:Lscala/reflect/generic/UnPickler$Scan;
	areturn
  Labels:

public scala.reflect.generic.UnPickler$Scan$$anonfun$readClassfileAnnotArg$2(scala.reflect.generic.UnPickler$Scan);
  Signature: (Lscala/reflect/generic/UnPickler$Scan;)V
  Code:
   Stack=2, Locals=2, Args_size=2
	aload_1
	ifnonnull	l1 // aload_0
	new	class java/lang/NullPointerException
	dup
	invokespecial	Method java/lang/NullPointerException."<init>":()V
	athrow
l1	aload_0
	aload_1
	putfield	Field $outer:Lscala/reflect/generic/UnPickler$Scan;
	aload_0
	invokespecial	Method scala/runtime/AbstractFunction0."<init>":()V
	return
  Labels:
   	l1 = 12 // aload_0
  LocalVariableTable: 
   Start  Length  Slot  Name   Signature
   0      22      0    this       Lscala/reflect/generic/UnPickler$Scan$$anonfun$readClassfileAnnotArg$2;
   0      22      1    $outer       Lscala/reflect/generic/UnPickler$Scan;


}

