Compiled from "Addable.scala"
public abstract class scala.collection.generic.Addable$class extends java.lang.Object
  SourceFile: "Addable.scala"
  Scala: length = 0x
   
  InnerClass: 
   public final $anonfun$$plus$plus$1=class scala/collection/generic/Addable$$anonfun$$plus$plus$1 of class scala/collection/generic/Addable
   public final $anonfun$$plus$plus$2=class scala/collection/generic/Addable$$anonfun$$plus$plus$2 of class scala/collection/generic/Addable
  minor version: 0
  major version: 49
  Constant pool:
Asciz	SourceFile;
Asciz	Addable.scala;
Asciz	$init$;
Asciz	(Lscala/collection/generic/Addable;)V;
Asciz	Code;
Asciz	LineNumberTable;
Asciz	$this;
Asciz	Lscala/collection/generic/Addable;;
Asciz	LocalVariableTable;
Asciz	$plus$plus;
Asciz	(Lscala/collection/generic/Addable;Lscala/collection/Iterator;)Lscala/collection/generic/Addable;;
Asciz	scala/collection/generic/Addable;
class	scala/collection/generic/Addable
Asciz	repr;
Asciz	()Lscala/collection/generic/Addable;;
NameAndType	repr:()Lscala/collection/generic/Addable;
InterfaceMethod	scala/collection/generic/Addable.repr:()Lscala/collection/generic/Addable;
Asciz	scala/collection/generic/Addable$$anonfun$$plus$plus$2;
class	scala/collection/generic/Addable$$anonfun$$plus$plus$2
Asciz	<init>;
NameAndType	"<init>":(Lscala/collection/generic/Addable;)V
Method	scala/collection/generic/Addable$$anonfun$$plus$plus$2."<init>":(Lscala/collection/generic/Addable;)V
Asciz	scala/collection/Iterator;
class	scala/collection/Iterator
Asciz	$div$colon;
Asciz	(Ljava/lang/Object;Lscala/Function2;)Ljava/lang/Object;;
NameAndType	$div$colon:(Ljava/lang/Object;Lscala/Function2;)Ljava/lang/Object;
InterfaceMethod	scala/collection/Iterator.$div$colon:(Ljava/lang/Object;Lscala/Function2;)Ljava/lang/Object;
Asciz	iter;
Asciz	Lscala/collection/Iterator;;
Asciz	(Lscala/collection/generic/Addable;Lscala/collection/Traversable;)Lscala/collection/generic/Addable;;
Asciz	scala/collection/generic/Addable$$anonfun$$plus$plus$1;
class	scala/collection/generic/Addable$$anonfun$$plus$plus$1
Method	scala/collection/generic/Addable$$anonfun$$plus$plus$1."<init>":(Lscala/collection/generic/Addable;)V
Asciz	scala/collection/TraversableLike;
class	scala/collection/TraversableLike
InterfaceMethod	scala/collection/TraversableLike.$div$colon:(Ljava/lang/Object;Lscala/Function2;)Ljava/lang/Object;
Asciz	elems;
Asciz	Lscala/collection/Traversable;;
Asciz	$plus;
Asciz	(Lscala/collection/generic/Addable;Ljava/lang/Object;Ljava/lang/Object;Lscala/collection/Seq;)Lscala/collection/generic/Addable;;
Asciz	(Ljava/lang/Object;)Lscala/collection/generic/Addable;;
NameAndType	$plus:(Ljava/lang/Object;)Lscala/collection/generic/Addable;
InterfaceMethod	scala/collection/generic/Addable.$plus:(Ljava/lang/Object;)Lscala/collection/generic/Addable;
Asciz	(Lscala/collection/Traversable;)Lscala/collection/generic/Addable;;
NameAndType	$plus$plus:(Lscala/collection/Traversable;)Lscala/collection/generic/Addable;
InterfaceMethod	scala/collection/generic/Addable.$plus$plus:(Lscala/collection/Traversable;)Lscala/collection/generic/Addable;
Asciz	elem1;
Asciz	Ljava/lang/Object;;
Asciz	elem2;
Asciz	Lscala/collection/Seq;;
Asciz	Scala;
Asciz	InnerClasses;
Asciz	$anonfun$$plus$plus$1;
Asciz	$anonfun$$plus$plus$2;
Asciz	scala/collection/generic/Addable$class;
class	scala/collection/generic/Addable$class
Asciz	java/lang/Object;
class	java/lang/Object

{
public static void $init$(scala.collection.generic.Addable);
  Signature: (Lscala/collection/generic/Addable;)V
  Code:
   Stack=0, Locals=1, Args_size=1
	return
  Labels:
  LocalVariableTable: 
   Start  Length  Slot  Name   Signature
   0      1      0    $this       Lscala/collection/generic/Addable;


public static scala.collection.generic.Addable $plus$plus(scala.collection.generic.Addable, scala.collection.Iterator);
  Signature: (Lscala/collection/generic/Addable;Lscala/collection/Iterator;)Lscala/collection/generic/Addable;
  Code:
   Stack=5, Locals=3, Args_size=2
	aload_0
	invokeinterface	InterfaceMethod scala/collection/generic/Addable.repr:()Lscala/collection/generic/Addable;
	astore_2
	aload_1
	aload_2
	new	class scala/collection/generic/Addable$$anonfun$$plus$plus$2
	dup
	aload_0
	invokespecial	Method scala/collection/generic/Addable$$anonfun$$plus$plus$2."<init>":(Lscala/collection/generic/Addable;)V
	invokeinterface	InterfaceMethod scala/collection/Iterator.$div$colon:(Ljava/lang/Object;Lscala/Function2;)Ljava/lang/Object;
	checkcast	class scala/collection/generic/Addable
	areturn
  Labels:
  LocalVariableTable: 
   Start  Length  Slot  Name   Signature
   0      26      0    $this       Lscala/collection/generic/Addable;
   0      26      1    iter       Lscala/collection/Iterator;


public static scala.collection.generic.Addable $plus$plus(scala.collection.generic.Addable, scala.collection.Traversable);
  Signature: (Lscala/collection/generic/Addable;Lscala/collection/Traversable;)Lscala/collection/generic/Addable;
  Code:
   Stack=5, Locals=3, Args_size=2
	aload_0
	invokeinterface	InterfaceMethod scala/collection/generic/Addable.repr:()Lscala/collection/generic/Addable;
	astore_2
	aload_1
	aload_2
	new	class scala/collection/generic/Addable$$anonfun$$plus$plus$1
	dup
	aload_0
	invokespecial	Method scala/collection/generic/Addable$$anonfun$$plus$plus$1."<init>":(Lscala/collection/generic/Addable;)V
	invokeinterface	InterfaceMethod scala/collection/TraversableLike.$div$colon:(Ljava/lang/Object;Lscala/Function2;)Ljava/lang/Object;
	checkcast	class scala/collection/generic/Addable
	areturn
  Labels:
  LocalVariableTable: 
   Start  Length  Slot  Name   Signature
   0      26      0    $this       Lscala/collection/generic/Addable;
   0      26      1    elems       Lscala/collection/Traversable;


public static scala.collection.generic.Addable $plus(scala.collection.generic.Addable, java.lang.Object, java.lang.Object, scala.collection.Seq);
  Signature: (Lscala/collection/generic/Addable;Ljava/lang/Object;Ljava/lang/Object;Lscala/collection/Seq;)Lscala/collection/generic/Addable;
  Code:
   Stack=2, Locals=4, Args_size=4
	aload_0
	aload_1
	invokeinterface	InterfaceMethod scala/collection/generic/Addable.$plus:(Ljava/lang/Object;)Lscala/collection/generic/Addable;
	aload_2
	invokeinterface	InterfaceMethod scala/collection/generic/Addable.$plus:(Ljava/lang/Object;)Lscala/collection/generic/Addable;
	aload_3
	invokeinterface	InterfaceMethod scala/collection/generic/Addable.$plus$plus:(Lscala/collection/Traversable;)Lscala/collection/generic/Addable;
	areturn
  Labels:
  LocalVariableTable: 
   Start  Length  Slot  Name   Signature
   0      20      0    $this       Lscala/collection/generic/Addable;
   0      20      1    elem1       Ljava/lang/Object;
   0      20      2    elem2       Ljava/lang/Object;
   0      20      3    elems       Lscala/collection/Seq;


}

