Compiled from "BitSetFactory.scala"
public final class scala.collection.generic.BitSetFactory$$anon$1 extends java.lang.Object implements scala.collection.generic.BuilderFactory
  SourceFile: "BitSetFactory.scala"
  Signature: length = 0x2
   00 2B 
  Scala: length = 0x
   
  InnerClass: 
   public final #46= #15 of #36; //$anon$1=class scala/collection/generic/BitSetFactory$$anon$1 of class scala/collection/generic/BitSetFactory
  minor version: 0
  major version: 49
  Constant pool:
const #1 = Asciz	SourceFile;
const #2 = Asciz	BitSetFactory.scala;
const #3 = Asciz	$outer;
const #4 = Asciz	Lscala/collection/generic/BitSetFactory;;
const #5 = Asciz	<init>;
const #6 = Asciz	(Lscala/collection/generic/BitSetFactory;)V;
const #7 = Asciz	Code;
const #8 = Asciz	LineNumberTable;
const #9 = Asciz	java/lang/NullPointerException;
const #10 = class	#9;	//  java/lang/NullPointerException
const #11 = Asciz	()V;
const #12 = NameAndType	#5:#11;//  "<init>":()V
const #13 = Method	#10.#12;	//  java/lang/NullPointerException."<init>":()V
const #14 = Asciz	scala/collection/generic/BitSetFactory$$anon$1;
const #15 = class	#14;	//  scala/collection/generic/BitSetFactory$$anon$1
const #16 = NameAndType	#3:#4;//  $outer:Lscala/collection/generic/BitSetFactory;
const #17 = Field	#15.#16;	//  scala/collection/generic/BitSetFactory$$anon$1.$outer:Lscala/collection/generic/BitSetFactory;
const #18 = Asciz	java/lang/Object;
const #19 = class	#18;	//  java/lang/Object
const #20 = Method	#19.#12;	//  java/lang/Object."<init>":()V
const #21 = Asciz	this;
const #22 = Asciz	Lscala/collection/generic/BitSetFactory$$anon$1;;
const #23 = Asciz	LocalVariableTable;
const #24 = Asciz	(Lscala/collection/generic/BitSetFactory<TColl;>;)V;
const #25 = Asciz	Signature;
const #26 = Asciz	apply;
const #27 = Asciz	(Ljava/lang/Object;)Lscala/collection/generic/Builder;;
const #28 = Asciz	scala/collection/BitSet;
const #29 = class	#28;	//  scala/collection/BitSet
const #30 = Asciz	(Lscala/collection/BitSet;)Lscala/collection/generic/Builder;;
const #31 = NameAndType	#26:#30;//  apply:(Lscala/collection/BitSet;)Lscala/collection/generic/Builder;
const #32 = Method	#15.#31;	//  scala/collection/generic/BitSetFactory$$anon$1.apply:(Lscala/collection/BitSet;)Lscala/collection/generic/Builder;
const #33 = Asciz	from;
const #34 = Asciz	Ljava/lang/Object;;
const #35 = Asciz	scala/collection/generic/BitSetFactory;
const #36 = class	#35;	//  scala/collection/generic/BitSetFactory
const #37 = Asciz	newBuilder;
const #38 = Asciz	()Lscala/collection/generic/Builder;;
const #39 = NameAndType	#37:#38;//  newBuilder:()Lscala/collection/generic/Builder;
const #40 = InterfaceMethod	#36.#39;	//  scala/collection/generic/BitSetFactory.newBuilder:()Lscala/collection/generic/Builder;
const #41 = Asciz	Lscala/collection/BitSet;;
const #42 = Asciz	(TColl;)Lscala/collection/generic/Builder<Ljava/lang/Integer;TColl;>;;
const #43 = Asciz	Ljava/lang/Object;Lscala/collection/generic/BuilderFactory<Ljava/lang/Integer;TColl;TColl;>;;
const #44 = Asciz	Scala;
const #45 = Asciz	InnerClasses;
const #46 = Asciz	$anon$1;
const #47 = Asciz	scala/collection/generic/BuilderFactory;
const #48 = class	#47;	//  scala/collection/generic/BuilderFactory

{
public scala.collection.generic.BitSetFactory$$anon$1(scala.collection.generic.BitSetFactory);
  Code:
   Stack=2, Locals=2, Args_size=2
   0:	aload_1
   1:	ifnonnull	12
   4:	new	#10; //class java/lang/NullPointerException
   7:	dup
   8:	invokespecial	#13; //Method java/lang/NullPointerException."<init>":()V
   11:	athrow
   12:	aload_0
   13:	aload_1
   14:	putfield	#17; //Field $outer:Lscala/collection/generic/BitSetFactory;
   17:	aload_0
   18:	invokespecial	#20; //Method java/lang/Object."<init>":()V
   21:	return
  LineNumberTable: 
   line 16: 0

  LocalVariableTable: 
   Start  Length  Slot  Name   Signature
   0      22      0    this       Lscala/collection/generic/BitSetFactory$$anon$1;
   0      22      1    $outer       Lscala/collection/generic/BitSetFactory;

  Signature: length = 0x2
   00 18 

public scala.collection.generic.Builder apply(java.lang.Object);
  Code:
   Stack=2, Locals=2, Args_size=2
   0:	aload_0
   1:	aload_1
   2:	checkcast	#29; //class scala/collection/BitSet
   5:	invokevirtual	#32; //Method apply:(Lscala/collection/BitSet;)Lscala/collection/generic/Builder;
   8:	areturn
  LineNumberTable: 
   line 16: 0

  LocalVariableTable: 
   Start  Length  Slot  Name   Signature
   0      9      0    this       Lscala/collection/generic/BitSetFactory$$anon$1;
   0      9      1    from       Ljava/lang/Object;


public scala.collection.generic.Builder apply(scala.collection.BitSet);
  Code:
   Stack=1, Locals=2, Args_size=2
   0:	aload_0
   1:	getfield	#17; //Field $outer:Lscala/collection/generic/BitSetFactory;
   4:	invokeinterface	#40,  1; //InterfaceMethod scala/collection/generic/BitSetFactory.newBuilder:()Lscala/collection/generic/Builder;
   9:	areturn
  LineNumberTable: 
   line 17: 0

  LocalVariableTable: 
   Start  Length  Slot  Name   Signature
   0      10      0    this       Lscala/collection/generic/BitSetFactory$$anon$1;
   0      10      1    from       Lscala/collection/BitSet;

  Signature: length = 0x2
   00 2A 

}

