Compiled from "BitSetFactory.scala"
public abstract class scala.collection.generic.BitSetFactory$class extends java.lang.Object
  SourceFile: "BitSetFactory.scala"
  Scala: length = 0x
   
  InnerClass: 
   public final $anon$1=class scala/collection/generic/BitSetFactory$$anon$1 of class scala/collection/generic/BitSetFactory
   public final $anonfun$apply$1=class scala/collection/generic/BitSetFactory$$anonfun$apply$1 of class scala/collection/generic/BitSetFactory
  minor version: 0
  major version: 49
  Constant pool:
Asciz	SourceFile;
Asciz	BitSetFactory.scala;
Asciz	$init$;
Asciz	(Lscala/collection/generic/BitSetFactory;)V;
Asciz	Code;
Asciz	LineNumberTable;
Asciz	$this;
Asciz	Lscala/collection/generic/BitSetFactory;;
Asciz	LocalVariableTable;
Asciz	bitsetCanBuildFrom;
Asciz	(Lscala/collection/generic/BitSetFactory;)Ljava/lang/Object;;
Asciz	scala/collection/generic/BitSetFactory$$anon$1;
class	scala/collection/generic/BitSetFactory$$anon$1
Asciz	<init>;
NameAndType	"<init>":(Lscala/collection/generic/BitSetFactory;)V
Method	scala/collection/generic/BitSetFactory$$anon$1."<init>":(Lscala/collection/generic/BitSetFactory;)V
Asciz	apply;
Asciz	(Lscala/collection/generic/BitSetFactory;Lscala/collection/Seq;)Lscala/collection/BitSet;;
Asciz	scala/collection/generic/BitSetFactory;
class	scala/collection/generic/BitSetFactory
Asciz	empty;
Asciz	()Lscala/collection/BitSet;;
NameAndType	empty:()Lscala/collection/BitSet;
InterfaceMethod	scala/collection/generic/BitSetFactory.empty:()Lscala/collection/BitSet;
Asciz	scala/collection/generic/BitSetFactory$$anonfun$apply$1;
class	scala/collection/generic/BitSetFactory$$anonfun$apply$1
Method	scala/collection/generic/BitSetFactory$$anonfun$apply$1."<init>":(Lscala/collection/generic/BitSetFactory;)V
Asciz	scala/collection/TraversableLike;
class	scala/collection/TraversableLike
Asciz	$div$colon;
Asciz	(Ljava/lang/Object;Lscala/Function2;)Ljava/lang/Object;;
NameAndType	$div$colon:(Ljava/lang/Object;Lscala/Function2;)Ljava/lang/Object;
InterfaceMethod	scala/collection/TraversableLike.$div$colon:(Ljava/lang/Object;Lscala/Function2;)Ljava/lang/Object;
Asciz	scala/collection/BitSet;
class	scala/collection/BitSet
Asciz	elems;
Asciz	Lscala/collection/Seq;;
Asciz	newBuilder;
Asciz	(Lscala/collection/generic/BitSetFactory;)Lscala/collection/mutable/Builder;;
Asciz	scala/collection/mutable/AddingBuilder;
class	scala/collection/mutable/AddingBuilder
Asciz	(Lscala/collection/generic/Addable;)V;
NameAndType	"<init>":(Lscala/collection/generic/Addable;)V
Method	scala/collection/mutable/AddingBuilder."<init>":(Lscala/collection/generic/Addable;)V
Asciz	Scala;
Asciz	InnerClasses;
Asciz	$anon$1;
Asciz	$anonfun$apply$1;
Asciz	scala/collection/generic/BitSetFactory$class;
class	scala/collection/generic/BitSetFactory$class
Asciz	java/lang/Object;
class	java/lang/Object

{
public static void $init$(scala.collection.generic.BitSetFactory);
  Signature: (Lscala/collection/generic/BitSetFactory;)V
  Code:
   Stack=0, Locals=1, Args_size=1
	return
  Labels:
  LocalVariableTable: 
   Start  Length  Slot  Name   Signature
   0      1      0    $this       Lscala/collection/generic/BitSetFactory;


public static java.lang.Object bitsetCanBuildFrom(scala.collection.generic.BitSetFactory);
  Signature: (Lscala/collection/generic/BitSetFactory;)Ljava/lang/Object;
  Code:
   Stack=3, Locals=1, Args_size=1
	new	class scala/collection/generic/BitSetFactory$$anon$1
	dup
	aload_0
	invokespecial	Method scala/collection/generic/BitSetFactory$$anon$1."<init>":(Lscala/collection/generic/BitSetFactory;)V
	areturn
  Labels:
  LocalVariableTable: 
   Start  Length  Slot  Name   Signature
   0      9      0    $this       Lscala/collection/generic/BitSetFactory;


public static scala.collection.BitSet apply(scala.collection.generic.BitSetFactory, scala.collection.Seq);
  Signature: (Lscala/collection/generic/BitSetFactory;Lscala/collection/Seq;)Lscala/collection/BitSet;
  Code:
   Stack=5, Locals=3, Args_size=2
	aload_0
	invokeinterface	InterfaceMethod scala/collection/generic/BitSetFactory.empty:()Lscala/collection/BitSet;
	astore_2
	aload_1
	aload_2
	new	class scala/collection/generic/BitSetFactory$$anonfun$apply$1
	dup
	aload_0
	invokespecial	Method scala/collection/generic/BitSetFactory$$anonfun$apply$1."<init>":(Lscala/collection/generic/BitSetFactory;)V
	invokeinterface	InterfaceMethod scala/collection/TraversableLike.$div$colon:(Ljava/lang/Object;Lscala/Function2;)Ljava/lang/Object;
	checkcast	class scala/collection/BitSet
	areturn
  Labels:
  LocalVariableTable: 
   Start  Length  Slot  Name   Signature
   0      26      0    $this       Lscala/collection/generic/BitSetFactory;
   0      26      1    elems       Lscala/collection/Seq;


public static scala.collection.mutable.Builder newBuilder(scala.collection.generic.BitSetFactory);
  Signature: (Lscala/collection/generic/BitSetFactory;)Lscala/collection/mutable/Builder;
  Code:
   Stack=3, Locals=1, Args_size=1
	new	class scala/collection/mutable/AddingBuilder
	dup
	aload_0
	invokeinterface	InterfaceMethod scala/collection/generic/BitSetFactory.empty:()Lscala/collection/BitSet;
	invokespecial	Method scala/collection/mutable/AddingBuilder."<init>":(Lscala/collection/generic/Addable;)V
	areturn
  Labels:
  LocalVariableTable: 
   Start  Length  Slot  Name   Signature
   0      14      0    $this       Lscala/collection/generic/BitSetFactory;


}

