Compiled from "BitSetTemplate.scala"
public abstract class scala.collection.generic.BitSetTemplate$class extends java.lang.Object
  SourceFile: "BitSetTemplate.scala"
  Scala: length = 0x
   
  InnerClass: 
   public final #164= #151 of #37; //$anon$1=class scala/collection/generic/BitSetTemplate$$anon$1 of class scala/collection/generic/BitSetTemplate
   public final #165= #108 of #37; //$anonfun$$up$1=class scala/collection/generic/BitSetTemplate$$anonfun$$up$1 of class scala/collection/generic/BitSetTemplate
   public final #166= #131 of #37; //$anonfun$$amp$1=class scala/collection/generic/BitSetTemplate$$anonfun$$amp$1 of class scala/collection/generic/BitSetTemplate
   public final #167= #137 of #37; //$anonfun$$bar$1=class scala/collection/generic/BitSetTemplate$$anonfun$$bar$1 of class scala/collection/generic/BitSetTemplate
   public final #168= #78 of #37; //$anonfun$subSet$1=class scala/collection/generic/BitSetTemplate$$anonfun$subSet$1 of class scala/collection/generic/BitSetTemplate
   public final #169= #143 of #37; //$anonfun$foreach$1=class scala/collection/generic/BitSetTemplate$$anonfun$foreach$1 of class scala/collection/generic/BitSetTemplate
   public final #170= #57 of #37; //$anonfun$addString$1=class scala/collection/generic/BitSetTemplate$$anonfun$addString$1 of class scala/collection/generic/BitSetTemplate
   public final #171= #122 of #37; //$anonfun$$amp$tilde$1=class scala/collection/generic/BitSetTemplate$$anonfun$$amp$tilde$1 of class scala/collection/generic/BitSetTemplate
  minor version: 0
  major version: 49
  Constant pool:
const #1 = Asciz	SourceFile;
const #2 = Asciz	BitSetTemplate.scala;
const #3 = Asciz	$init$;
const #4 = Asciz	(Lscala/collection/generic/BitSetTemplate;)V;
const #5 = Asciz	Code;
const #6 = Asciz	LineNumberTable;
const #7 = Asciz	$this;
const #8 = Asciz	Lscala/collection/generic/BitSetTemplate;;
const #9 = Asciz	LocalVariableTable;
const #10 = Asciz	addString;
const #11 = Asciz	(Lscala/collection/generic/BitSetTemplate;Lscala/collection/mutable/StringBuilder;Ljava/lang/String;Ljava/lang/String;Ljava/lang/String;)Lscala/collection/mutable/StringBuilder;;
const #12 = Asciz	scala/collection/mutable/StringBuilder;
const #13 = class	#12;	//  scala/collection/mutable/StringBuilder
const #14 = Asciz	append;
const #15 = Asciz	(Ljava/lang/String;)Lscala/collection/mutable/StringBuilder;;
const #16 = NameAndType	#14:#15;//  append:(Ljava/lang/String;)Lscala/collection/mutable/StringBuilder;
const #17 = Method	#13.#16;	//  scala/collection/mutable/StringBuilder.append:(Ljava/lang/String;)Lscala/collection/mutable/StringBuilder;
const #18 = Asciz	scala/runtime/ObjectRef;
const #19 = class	#18;	//  scala/runtime/ObjectRef
const #20 = Asciz	;
const #21 = String	#20;	//  
const #22 = Asciz	<init>;
const #23 = Asciz	(Ljava/lang/Object;)V;
const #24 = NameAndType	#22:#23;//  "<init>":(Ljava/lang/Object;)V
const #25 = Method	#19.#24;	//  scala/runtime/ObjectRef."<init>":(Ljava/lang/Object;)V
const #26 = Asciz	scala/Predef$;
const #27 = class	#26;	//  scala/Predef$
const #28 = Asciz	MODULE$;
const #29 = Asciz	Lscala/Predef$;;
const #30 = NameAndType	#28:#29;//  MODULE$:Lscala/Predef$;
const #31 = Field	#27.#30;	//  scala/Predef$.MODULE$:Lscala/Predef$;
const #32 = Asciz	intWrapper;
const #33 = Asciz	(I)Lscala/runtime/RichInt;;
const #34 = NameAndType	#32:#33;//  intWrapper:(I)Lscala/runtime/RichInt;
const #35 = Method	#27.#34;	//  scala/Predef$.intWrapper:(I)Lscala/runtime/RichInt;
const #36 = Asciz	scala/collection/generic/BitSetTemplate;
const #37 = class	#36;	//  scala/collection/generic/BitSetTemplate
const #38 = Asciz	nwords;
const #39 = Asciz	()I;
const #40 = NameAndType	#38:#39;//  nwords:()I
const #41 = InterfaceMethod	#37.#40;	//  scala/collection/generic/BitSetTemplate.nwords:()I
const #42 = Asciz	scala/collection/generic/BitSetTemplate$;
const #43 = class	#42;	//  scala/collection/generic/BitSetTemplate$
const #44 = Asciz	Lscala/collection/generic/BitSetTemplate$;;
const #45 = NameAndType	#28:#44;//  MODULE$:Lscala/collection/generic/BitSetTemplate$;
const #46 = Field	#43.#45;	//  scala/collection/generic/BitSetTemplate$.MODULE$:Lscala/collection/generic/BitSetTemplate$;
const #47 = Asciz	scala$collection$generic$BitSetTemplate$$WordLength;
const #48 = NameAndType	#47:#39;//  scala$collection$generic$BitSetTemplate$$WordLength:()I
const #49 = Method	#43.#48;	//  scala/collection/generic/BitSetTemplate$.scala$collection$generic$BitSetTemplate$$WordLength:()I
const #50 = Asciz	scala/runtime/RichInt;
const #51 = class	#50;	//  scala/runtime/RichInt
const #52 = Asciz	until;
const #53 = Asciz	(I)Lscala/Range;;
const #54 = NameAndType	#52:#53;//  until:(I)Lscala/Range;
const #55 = Method	#51.#54;	//  scala/runtime/RichInt.until:(I)Lscala/Range;
const #56 = Asciz	scala/collection/generic/BitSetTemplate$$anonfun$addString$1;
const #57 = class	#56;	//  scala/collection/generic/BitSetTemplate$$anonfun$addString$1
const #58 = Asciz	(Lscala/collection/generic/BitSetTemplate;Lscala/collection/mutable/StringBuilder;Ljava/lang/String;Lscala/runtime/ObjectRef;)V;
const #59 = NameAndType	#22:#58;//  "<init>":(Lscala/collection/generic/BitSetTemplate;Lscala/collection/mutable/StringBuilder;Ljava/lang/String;Lscala/runtime/ObjectRef;)V
const #60 = Method	#57.#59;	//  scala/collection/generic/BitSetTemplate$$anonfun$addString$1."<init>":(Lscala/collection/generic/BitSetTemplate;Lscala/collection/mutable/StringBuilder;Ljava/lang/String;Lscala/runtime/ObjectRef;)V
const #61 = Asciz	scala/Range;
const #62 = class	#61;	//  scala/Range
const #63 = Asciz	foreach;
const #64 = Asciz	(Lscala/Function1;)V;
const #65 = NameAndType	#63:#64;//  foreach:(Lscala/Function1;)V
const #66 = Method	#62.#65;	//  scala/Range.foreach:(Lscala/Function1;)V
const #67 = Asciz	sb$1;
const #68 = Asciz	Lscala/collection/mutable/StringBuilder;;
const #69 = Asciz	start;
const #70 = Asciz	Ljava/lang/String;;
const #71 = Asciz	sep$1;
const #72 = Asciz	end;
const #73 = Asciz	pre$1;
const #74 = Asciz	Lscala/runtime/ObjectRef;;
const #75 = Asciz	subSet;
const #76 = Asciz	(Lscala/collection/generic/BitSetTemplate;Lscala/collection/BitSet;)Z;
const #77 = Asciz	scala/collection/generic/BitSetTemplate$$anonfun$subSet$1;
const #78 = class	#77;	//  scala/collection/generic/BitSetTemplate$$anonfun$subSet$1
const #79 = Asciz	(Lscala/collection/generic/BitSetTemplate;Lscala/collection/BitSet;)V;
const #80 = NameAndType	#22:#79;//  "<init>":(Lscala/collection/generic/BitSetTemplate;Lscala/collection/BitSet;)V
const #81 = Method	#78.#80;	//  scala/collection/generic/BitSetTemplate$$anonfun$subSet$1."<init>":(Lscala/collection/generic/BitSetTemplate;Lscala/collection/BitSet;)V
const #82 = Asciz	scala/collection/generic/VectorTemplate;
const #83 = class	#82;	//  scala/collection/generic/VectorTemplate
const #84 = Asciz	forall;
const #85 = Asciz	(Lscala/Function1;)Z;
const #86 = NameAndType	#84:#85;//  forall:(Lscala/Function1;)Z
const #87 = InterfaceMethod	#83.#86;	//  scala/collection/generic/VectorTemplate.forall:(Lscala/Function1;)Z
const #88 = Asciz	other$5;
const #89 = Asciz	Lscala/collection/BitSet;;
const #90 = Asciz	contains;
const #91 = Asciz	(Lscala/collection/generic/BitSetTemplate;I)Z;
const #92 = Asciz	LogWL;
const #93 = NameAndType	#92:#39;//  LogWL:()I
const #94 = Method	#43.#93;	//  scala/collection/generic/BitSetTemplate$.LogWL:()I
const #95 = Asciz	word;
const #96 = Asciz	(I)J;
const #97 = NameAndType	#95:#96;//  word:(I)J
const #98 = InterfaceMethod	#37.#97;	//  scala/collection/generic/BitSetTemplate.word:(I)J
const #99 = Asciz	elem;
const #100 = Asciz	I;
const #101 = Asciz	$up;
const #102 = Asciz	(Lscala/collection/generic/BitSetTemplate;Lscala/collection/BitSet;)Lscala/collection/generic/BitSetTemplate;;
const #103 = Asciz	max;
const #104 = Asciz	(I)I;
const #105 = NameAndType	#103:#104;//  max:(I)I
const #106 = Method	#51.#105;	//  scala/runtime/RichInt.max:(I)I
const #107 = Asciz	scala/collection/generic/BitSetTemplate$$anonfun$$up$1;
const #108 = class	#107;	//  scala/collection/generic/BitSetTemplate$$anonfun$$up$1
const #109 = Asciz	(Lscala/collection/generic/BitSetTemplate;Lscala/collection/BitSet;[J)V;
const #110 = NameAndType	#22:#109;//  "<init>":(Lscala/collection/generic/BitSetTemplate;Lscala/collection/BitSet;[J)V
const #111 = Method	#108.#110;	//  scala/collection/generic/BitSetTemplate$$anonfun$$up$1."<init>":(Lscala/collection/generic/BitSetTemplate;Lscala/collection/BitSet;[J)V
const #112 = Asciz	fromArray;
const #113 = Asciz	([J)Lscala/collection/generic/BitSetTemplate;;
const #114 = NameAndType	#112:#113;//  fromArray:([J)Lscala/collection/generic/BitSetTemplate;
const #115 = InterfaceMethod	#37.#114;	//  scala/collection/generic/BitSetTemplate.fromArray:([J)Lscala/collection/generic/BitSetTemplate;
const #116 = Asciz	other$4;
const #117 = Asciz	len;
const #118 = Asciz	words$4;
const #119 = Asciz	[J;
const #120 = Asciz	$amp$tilde;
const #121 = Asciz	scala/collection/generic/BitSetTemplate$$anonfun$$amp$tilde$1;
const #122 = class	#121;	//  scala/collection/generic/BitSetTemplate$$anonfun$$amp$tilde$1
const #123 = Method	#122.#110;	//  scala/collection/generic/BitSetTemplate$$anonfun$$amp$tilde$1."<init>":(Lscala/collection/generic/BitSetTemplate;Lscala/collection/BitSet;[J)V
const #124 = Asciz	other$3;
const #125 = Asciz	words$3;
const #126 = Asciz	$amp;
const #127 = Asciz	min;
const #128 = NameAndType	#127:#104;//  min:(I)I
const #129 = Method	#51.#128;	//  scala/runtime/RichInt.min:(I)I
const #130 = Asciz	scala/collection/generic/BitSetTemplate$$anonfun$$amp$1;
const #131 = class	#130;	//  scala/collection/generic/BitSetTemplate$$anonfun$$amp$1
const #132 = Method	#131.#110;	//  scala/collection/generic/BitSetTemplate$$anonfun$$amp$1."<init>":(Lscala/collection/generic/BitSetTemplate;Lscala/collection/BitSet;[J)V
const #133 = Asciz	other$2;
const #134 = Asciz	words$2;
const #135 = Asciz	$bar;
const #136 = Asciz	scala/collection/generic/BitSetTemplate$$anonfun$$bar$1;
const #137 = class	#136;	//  scala/collection/generic/BitSetTemplate$$anonfun$$bar$1
const #138 = Method	#137.#110;	//  scala/collection/generic/BitSetTemplate$$anonfun$$bar$1."<init>":(Lscala/collection/generic/BitSetTemplate;Lscala/collection/BitSet;[J)V
const #139 = Asciz	other$1;
const #140 = Asciz	words$1;
const #141 = Asciz	(Lscala/collection/generic/BitSetTemplate;Lscala/Function1;)V;
const #142 = Asciz	scala/collection/generic/BitSetTemplate$$anonfun$foreach$1;
const #143 = class	#142;	//  scala/collection/generic/BitSetTemplate$$anonfun$foreach$1
const #144 = NameAndType	#22:#141;//  "<init>":(Lscala/collection/generic/BitSetTemplate;Lscala/Function1;)V
const #145 = Method	#143.#144;	//  scala/collection/generic/BitSetTemplate$$anonfun$foreach$1."<init>":(Lscala/collection/generic/BitSetTemplate;Lscala/Function1;)V
const #146 = Asciz	f$1;
const #147 = Asciz	Lscala/Function1;;
const #148 = Asciz	iterator;
const #149 = Asciz	(Lscala/collection/generic/BitSetTemplate;)Ljava/lang/Object;;
const #150 = Asciz	scala/collection/generic/BitSetTemplate$$anon$1;
const #151 = class	#150;	//  scala/collection/generic/BitSetTemplate$$anon$1
const #152 = NameAndType	#22:#4;//  "<init>":(Lscala/collection/generic/BitSetTemplate;)V
const #153 = Method	#151.#152;	//  scala/collection/generic/BitSetTemplate$$anon$1."<init>":(Lscala/collection/generic/BitSetTemplate;)V
const #154 = Asciz	size;
const #155 = Asciz	(Lscala/collection/generic/BitSetTemplate;)I;
const #156 = Asciz	scala$collection$generic$BitSetTemplate$$popCount;
const #157 = Asciz	(J)I;
const #158 = NameAndType	#156:#157;//  scala$collection$generic$BitSetTemplate$$popCount:(J)I
const #159 = Method	#43.#158;	//  scala/collection/generic/BitSetTemplate$.scala$collection$generic$BitSetTemplate$$popCount:(J)I
const #160 = Asciz	s;
const #161 = Asciz	i;
const #162 = Asciz	Scala;
const #163 = Asciz	InnerClasses;
const #164 = Asciz	$anon$1;
const #165 = Asciz	$anonfun$$up$1;
const #166 = Asciz	$anonfun$$amp$1;
const #167 = Asciz	$anonfun$$bar$1;
const #168 = Asciz	$anonfun$subSet$1;
const #169 = Asciz	$anonfun$foreach$1;
const #170 = Asciz	$anonfun$addString$1;
const #171 = Asciz	$anonfun$$amp$tilde$1;
const #172 = Asciz	scala/collection/generic/BitSetTemplate$class;
const #173 = class	#172;	//  scala/collection/generic/BitSetTemplate$class
const #174 = Asciz	java/lang/Object;
const #175 = class	#174;	//  java/lang/Object

{
public static void $init$(scala.collection.generic.BitSetTemplate);
  Code:
   Stack=0, Locals=1, Args_size=1
   0:	return
  LineNumberTable: 
   line 20: 0

  LocalVariableTable: 
   Start  Length  Slot  Name   Signature
   0      1      0    $this       Lscala/collection/generic/BitSetTemplate;


public static scala.collection.mutable.StringBuilder addString(scala.collection.generic.BitSetTemplate, scala.collection.mutable.StringBuilder, java.lang.String, java.lang.String, java.lang.String);
  Code:
   Stack=7, Locals=6, Args_size=5
   0:	aload_1
   1:	aload_2
   2:	invokevirtual	#17; //Method scala/collection/mutable/StringBuilder.append:(Ljava/lang/String;)Lscala/collection/mutable/StringBuilder;
   5:	pop
   6:	new	#19; //class scala/runtime/ObjectRef
   9:	dup
   10:	ldc	#21; //String 
   12:	invokespecial	#25; //Method scala/runtime/ObjectRef."<init>":(Ljava/lang/Object;)V
   15:	astore	5
   17:	getstatic	#31; //Field scala/Predef$.MODULE$:Lscala/Predef$;
   20:	iconst_0
   21:	invokevirtual	#35; //Method scala/Predef$.intWrapper:(I)Lscala/runtime/RichInt;
   24:	aload_0
   25:	invokeinterface	#41,  1; //InterfaceMethod scala/collection/generic/BitSetTemplate.nwords:()I
   30:	getstatic	#46; //Field scala/collection/generic/BitSetTemplate$.MODULE$:Lscala/collection/generic/BitSetTemplate$;
   33:	invokevirtual	#49; //Method scala/collection/generic/BitSetTemplate$.scala$collection$generic$BitSetTemplate$$WordLength:()I
   36:	imul
   37:	invokevirtual	#55; //Method scala/runtime/RichInt.until:(I)Lscala/Range;
   40:	new	#57; //class scala/collection/generic/BitSetTemplate$$anonfun$addString$1
   43:	dup
   44:	aload_0
   45:	aload_1
   46:	aload_3
   47:	aload	5
   49:	invokespecial	#60; //Method scala/collection/generic/BitSetTemplate$$anonfun$addString$1."<init>":(Lscala/collection/generic/BitSetTemplate;Lscala/collection/mutable/StringBuilder;Ljava/lang/String;Lscala/runtime/ObjectRef;)V
   52:	invokevirtual	#66; //Method scala/Range.foreach:(Lscala/Function1;)V
   55:	aload_1
   56:	aload	4
   58:	invokevirtual	#17; //Method scala/collection/mutable/StringBuilder.append:(Ljava/lang/String;)Lscala/collection/mutable/StringBuilder;
   61:	areturn
  LineNumberTable: 
   line 122: 0
   line 123: 6
   line 124: 17
   line 129: 55

  LocalVariableTable: 
   Start  Length  Slot  Name   Signature
   0      62      0    $this       Lscala/collection/generic/BitSetTemplate;
   0      62      1    sb$1       Lscala/collection/mutable/StringBuilder;
   0      62      2    start       Ljava/lang/String;
   0      62      3    sep$1       Ljava/lang/String;
   0      62      4    end       Ljava/lang/String;
   17      44      5    pre$1       Lscala/runtime/ObjectRef;


public static boolean subSet(scala.collection.generic.BitSetTemplate, scala.collection.BitSet);
  Code:
   Stack=5, Locals=2, Args_size=2
   0:	getstatic	#31; //Field scala/Predef$.MODULE$:Lscala/Predef$;
   3:	iconst_0
   4:	invokevirtual	#35; //Method scala/Predef$.intWrapper:(I)Lscala/runtime/RichInt;
   7:	aload_0
   8:	invokeinterface	#41,  1; //InterfaceMethod scala/collection/generic/BitSetTemplate.nwords:()I
   13:	invokevirtual	#55; //Method scala/runtime/RichInt.until:(I)Lscala/Range;
   16:	new	#78; //class scala/collection/generic/BitSetTemplate$$anonfun$subSet$1
   19:	dup
   20:	aload_0
   21:	aload_1
   22:	invokespecial	#81; //Method scala/collection/generic/BitSetTemplate$$anonfun$subSet$1."<init>":(Lscala/collection/generic/BitSetTemplate;Lscala/collection/BitSet;)V
   25:	invokeinterface	#87,  2; //InterfaceMethod scala/collection/generic/VectorTemplate.forall:(Lscala/Function1;)Z
   30:	ireturn
  LineNumberTable: 
   line 117: 0

  LocalVariableTable: 
   Start  Length  Slot  Name   Signature
   0      31      0    $this       Lscala/collection/generic/BitSetTemplate;
   0      31      1    other$5       Lscala/collection/BitSet;


public static boolean contains(scala.collection.generic.BitSetTemplate, int);
  Code:
   Stack=5, Locals=2, Args_size=2
   0:	iconst_0
   1:	iload_1
   2:	if_icmpgt	32
   5:	aload_0
   6:	iload_1
   7:	getstatic	#46; //Field scala/collection/generic/BitSetTemplate$.MODULE$:Lscala/collection/generic/BitSetTemplate$;
   10:	invokevirtual	#94; //Method scala/collection/generic/BitSetTemplate$.LogWL:()I
   13:	ishr
   14:	invokeinterface	#98,  2; //InterfaceMethod scala/collection/generic/BitSetTemplate.word:(I)J
   19:	lconst_1
   20:	iload_1
   21:	lshl
   22:	land
   23:	lconst_0
   24:	lcmp
   25:	ifeq	32
   28:	iconst_1
   29:	goto	33
   32:	iconst_0
   33:	ireturn
  LineNumberTable: 
   line 112: 0

  LocalVariableTable: 
   Start  Length  Slot  Name   Signature
   0      34      0    $this       Lscala/collection/generic/BitSetTemplate;
   0      34      1    elem       I


public static scala.collection.generic.BitSetTemplate $up(scala.collection.generic.BitSetTemplate, scala.collection.BitSet);
  Code:
   Stack=6, Locals=4, Args_size=2
   0:	getstatic	#31; //Field scala/Predef$.MODULE$:Lscala/Predef$;
   3:	aload_0
   4:	invokeinterface	#41,  1; //InterfaceMethod scala/collection/generic/BitSetTemplate.nwords:()I
   9:	invokevirtual	#35; //Method scala/Predef$.intWrapper:(I)Lscala/runtime/RichInt;
   12:	aload_1
   13:	invokeinterface	#41,  1; //InterfaceMethod scala/collection/generic/BitSetTemplate.nwords:()I
   18:	invokevirtual	#106; //Method scala/runtime/RichInt.max:(I)I
   21:	istore_2
   22:	iload_2
   23:	newarray long
   25:	astore_3
   26:	getstatic	#31; //Field scala/Predef$.MODULE$:Lscala/Predef$;
   29:	iconst_0
   30:	invokevirtual	#35; //Method scala/Predef$.intWrapper:(I)Lscala/runtime/RichInt;
   33:	iload_2
   34:	invokevirtual	#55; //Method scala/runtime/RichInt.until:(I)Lscala/Range;
   37:	new	#108; //class scala/collection/generic/BitSetTemplate$$anonfun$$up$1
   40:	dup
   41:	aload_0
   42:	aload_1
   43:	aload_3
   44:	invokespecial	#111; //Method scala/collection/generic/BitSetTemplate$$anonfun$$up$1."<init>":(Lscala/collection/generic/BitSetTemplate;Lscala/collection/BitSet;[J)V
   47:	invokevirtual	#66; //Method scala/Range.foreach:(Lscala/Function1;)V
   50:	aload_0
   51:	aload_3
   52:	invokeinterface	#115,  2; //InterfaceMethod scala/collection/generic/BitSetTemplate.fromArray:([J)Lscala/collection/generic/BitSetTemplate;
   57:	areturn
  LineNumberTable: 
   line 102: 0
   line 103: 22
   line 104: 26
   line 106: 50

  LocalVariableTable: 
   Start  Length  Slot  Name   Signature
   0      58      0    $this       Lscala/collection/generic/BitSetTemplate;
   0      58      1    other$4       Lscala/collection/BitSet;
   22      35      2    len       I
   26      31      3    words$4       [J


public static scala.collection.generic.BitSetTemplate $amp$tilde(scala.collection.generic.BitSetTemplate, scala.collection.BitSet);
  Code:
   Stack=6, Locals=4, Args_size=2
   0:	aload_0
   1:	invokeinterface	#41,  1; //InterfaceMethod scala/collection/generic/BitSetTemplate.nwords:()I
   6:	istore_2
   7:	iload_2
   8:	newarray long
   10:	astore_3
   11:	getstatic	#31; //Field scala/Predef$.MODULE$:Lscala/Predef$;
   14:	iconst_0
   15:	invokevirtual	#35; //Method scala/Predef$.intWrapper:(I)Lscala/runtime/RichInt;
   18:	iload_2
   19:	invokevirtual	#55; //Method scala/runtime/RichInt.until:(I)Lscala/Range;
   22:	new	#122; //class scala/collection/generic/BitSetTemplate$$anonfun$$amp$tilde$1
   25:	dup
   26:	aload_0
   27:	aload_1
   28:	aload_3
   29:	invokespecial	#123; //Method scala/collection/generic/BitSetTemplate$$anonfun$$amp$tilde$1."<init>":(Lscala/collection/generic/BitSetTemplate;Lscala/collection/BitSet;[J)V
   32:	invokevirtual	#66; //Method scala/Range.foreach:(Lscala/Function1;)V
   35:	aload_0
   36:	aload_3
   37:	invokeinterface	#115,  2; //InterfaceMethod scala/collection/generic/BitSetTemplate.fromArray:([J)Lscala/collection/generic/BitSetTemplate;
   42:	areturn
  LineNumberTable: 
   line 92: 0
   line 93: 7
   line 94: 11
   line 96: 35

  LocalVariableTable: 
   Start  Length  Slot  Name   Signature
   0      43      0    $this       Lscala/collection/generic/BitSetTemplate;
   0      43      1    other$3       Lscala/collection/BitSet;
   7      35      2    len       I
   11      31      3    words$3       [J


public static scala.collection.generic.BitSetTemplate $amp(scala.collection.generic.BitSetTemplate, scala.collection.BitSet);
  Code:
   Stack=6, Locals=4, Args_size=2
   0:	getstatic	#31; //Field scala/Predef$.MODULE$:Lscala/Predef$;
   3:	aload_0
   4:	invokeinterface	#41,  1; //InterfaceMethod scala/collection/generic/BitSetTemplate.nwords:()I
   9:	invokevirtual	#35; //Method scala/Predef$.intWrapper:(I)Lscala/runtime/RichInt;
   12:	aload_1
   13:	invokeinterface	#41,  1; //InterfaceMethod scala/collection/generic/BitSetTemplate.nwords:()I
   18:	invokevirtual	#129; //Method scala/runtime/RichInt.min:(I)I
   21:	istore_2
   22:	iload_2
   23:	newarray long
   25:	astore_3
   26:	getstatic	#31; //Field scala/Predef$.MODULE$:Lscala/Predef$;
   29:	iconst_0
   30:	invokevirtual	#35; //Method scala/Predef$.intWrapper:(I)Lscala/runtime/RichInt;
   33:	iload_2
   34:	invokevirtual	#55; //Method scala/runtime/RichInt.until:(I)Lscala/Range;
   37:	new	#131; //class scala/collection/generic/BitSetTemplate$$anonfun$$amp$1
   40:	dup
   41:	aload_0
   42:	aload_1
   43:	aload_3
   44:	invokespecial	#132; //Method scala/collection/generic/BitSetTemplate$$anonfun$$amp$1."<init>":(Lscala/collection/generic/BitSetTemplate;Lscala/collection/BitSet;[J)V
   47:	invokevirtual	#66; //Method scala/Range.foreach:(Lscala/Function1;)V
   50:	aload_0
   51:	aload_3
   52:	invokeinterface	#115,  2; //InterfaceMethod scala/collection/generic/BitSetTemplate.fromArray:([J)Lscala/collection/generic/BitSetTemplate;
   57:	areturn
  LineNumberTable: 
   line 82: 0
   line 83: 22
   line 84: 26
   line 86: 50

  LocalVariableTable: 
   Start  Length  Slot  Name   Signature
   0      58      0    $this       Lscala/collection/generic/BitSetTemplate;
   0      58      1    other$2       Lscala/collection/BitSet;
   22      35      2    len       I
   26      31      3    words$2       [J


public static scala.collection.generic.BitSetTemplate $bar(scala.collection.generic.BitSetTemplate, scala.collection.BitSet);
  Code:
   Stack=6, Locals=4, Args_size=2
   0:	getstatic	#31; //Field scala/Predef$.MODULE$:Lscala/Predef$;
   3:	aload_0
   4:	invokeinterface	#41,  1; //InterfaceMethod scala/collection/generic/BitSetTemplate.nwords:()I
   9:	invokevirtual	#35; //Method scala/Predef$.intWrapper:(I)Lscala/runtime/RichInt;
   12:	aload_1
   13:	invokeinterface	#41,  1; //InterfaceMethod scala/collection/generic/BitSetTemplate.nwords:()I
   18:	invokevirtual	#106; //Method scala/runtime/RichInt.max:(I)I
   21:	istore_2
   22:	iload_2
   23:	newarray long
   25:	astore_3
   26:	getstatic	#31; //Field scala/Predef$.MODULE$:Lscala/Predef$;
   29:	iconst_0
   30:	invokevirtual	#35; //Method scala/Predef$.intWrapper:(I)Lscala/runtime/RichInt;
   33:	iload_2
   34:	invokevirtual	#55; //Method scala/runtime/RichInt.until:(I)Lscala/Range;
   37:	new	#137; //class scala/collection/generic/BitSetTemplate$$anonfun$$bar$1
   40:	dup
   41:	aload_0
   42:	aload_1
   43:	aload_3
   44:	invokespecial	#138; //Method scala/collection/generic/BitSetTemplate$$anonfun$$bar$1."<init>":(Lscala/collection/generic/BitSetTemplate;Lscala/collection/BitSet;[J)V
   47:	invokevirtual	#66; //Method scala/Range.foreach:(Lscala/Function1;)V
   50:	aload_0
   51:	aload_3
   52:	invokeinterface	#115,  2; //InterfaceMethod scala/collection/generic/BitSetTemplate.fromArray:([J)Lscala/collection/generic/BitSetTemplate;
   57:	areturn
  LineNumberTable: 
   line 72: 0
   line 73: 22
   line 74: 26
   line 76: 50

  LocalVariableTable: 
   Start  Length  Slot  Name   Signature
   0      58      0    $this       Lscala/collection/generic/BitSetTemplate;
   0      58      1    other$1       Lscala/collection/BitSet;
   22      35      2    len       I
   26      31      3    words$1       [J


public static void foreach(scala.collection.generic.BitSetTemplate, scala.Function1);
  Code:
   Stack=5, Locals=2, Args_size=2
   0:	getstatic	#31; //Field scala/Predef$.MODULE$:Lscala/Predef$;
   3:	iconst_0
   4:	invokevirtual	#35; //Method scala/Predef$.intWrapper:(I)Lscala/runtime/RichInt;
   7:	aload_0
   8:	invokeinterface	#41,  1; //InterfaceMethod scala/collection/generic/BitSetTemplate.nwords:()I
   13:	invokevirtual	#55; //Method scala/runtime/RichInt.until:(I)Lscala/Range;
   16:	new	#143; //class scala/collection/generic/BitSetTemplate$$anonfun$foreach$1
   19:	dup
   20:	aload_0
   21:	aload_1
   22:	invokespecial	#145; //Method scala/collection/generic/BitSetTemplate$$anonfun$foreach$1."<init>":(Lscala/collection/generic/BitSetTemplate;Lscala/Function1;)V
   25:	invokevirtual	#66; //Method scala/Range.foreach:(Lscala/Function1;)V
   28:	return
  LineNumberTable: 
   line 61: 0

  LocalVariableTable: 
   Start  Length  Slot  Name   Signature
   0      29      0    $this       Lscala/collection/generic/BitSetTemplate;
   0      29      1    f$1       Lscala/Function1;


public static java.lang.Object iterator(scala.collection.generic.BitSetTemplate);
  Code:
   Stack=3, Locals=1, Args_size=1
   0:	new	#151; //class scala/collection/generic/BitSetTemplate$$anon$1
   3:	dup
   4:	aload_0
   5:	invokespecial	#153; //Method scala/collection/generic/BitSetTemplate$$anon$1."<init>":(Lscala/collection/generic/BitSetTemplate;)V
   8:	areturn
  LineNumberTable: 
   line 48: 0

  LocalVariableTable: 
   Start  Length  Slot  Name   Signature
   0      9      0    $this       Lscala/collection/generic/BitSetTemplate;


public static int size(scala.collection.generic.BitSetTemplate);
  Code:
   Stack=4, Locals=3, Args_size=1
   0:	iconst_0
   1:	istore_1
   2:	aload_0
   3:	invokeinterface	#41,  1; //InterfaceMethod scala/collection/generic/BitSetTemplate.nwords:()I
   8:	istore_2
   9:	iload_2
   10:	iconst_0
   11:	if_icmple	37
   14:	iload_2
   15:	iconst_1
   16:	isub
   17:	istore_2
   18:	iload_1
   19:	getstatic	#46; //Field scala/collection/generic/BitSetTemplate$.MODULE$:Lscala/collection/generic/BitSetTemplate$;
   22:	aload_0
   23:	iload_2
   24:	invokeinterface	#98,  2; //InterfaceMethod scala/collection/generic/BitSetTemplate.word:(I)J
   29:	invokevirtual	#159; //Method scala/collection/generic/BitSetTemplate$.scala$collection$generic$BitSetTemplate$$popCount:(J)I
   32:	iadd
   33:	istore_1
   34:	goto	9
   37:	iload_1
   38:	ireturn
  LineNumberTable: 
   line 39: 0
   line 40: 2
   line 41: 9
   line 42: 14
   line 43: 18
   line 41: 34
   line 45: 37

  LocalVariableTable: 
   Start  Length  Slot  Name   Signature
   0      39      0    $this       Lscala/collection/generic/BitSetTemplate;
   2      36      1    s       I
   9      29      2    i       I


}

