Compiled from "BufferTemplate.scala"
public abstract class scala.collection.generic.BufferTemplate$class extends java.lang.Object
  SourceFile: "BufferTemplate.scala"
  Scala: length = 0x
   
  InnerClass: 
   public final #313= #303 of #30; //$anonfun$remove$1=class scala/collection/generic/BufferTemplate$$anonfun$remove$1 of class scala/collection/generic/BufferTemplate
   public final #314= #213 of #30; //$anonfun$$less$less$1=class scala/collection/generic/BufferTemplate$$anonfun$$less$less$1 of class scala/collection/generic/BufferTemplate
   public final #315= #62 of #30; //$anonfun$$plus$plus$2=class scala/collection/generic/BufferTemplate$$anonfun$$plus$plus$2 of class scala/collection/generic/BufferTemplate
   public final #316= #65 of #30; //$anonfun$$plus$plus$1=class scala/collection/generic/BufferTemplate$$anonfun$$plus$plus$1 of class scala/collection/generic/BufferTemplate
   public final #317= #13 of #30; //$anonfun$$minus$minus$2=class scala/collection/generic/BufferTemplate$$anonfun$$minus$minus$2 of class scala/collection/generic/BufferTemplate
   public final #318= #35 of #30; //$anonfun$$minus$minus$1=class scala/collection/generic/BufferTemplate$$anonfun$$minus$minus$1 of class scala/collection/generic/BufferTemplate
   public final #319= #283 of #30; //$anonfun$$plus$plus$colon$1=class scala/collection/generic/BufferTemplate$$anonfun$$plus$plus$colon$1 of class scala/collection/generic/BufferTemplate
   public final #320= #280 of #30; //$anonfun$$plus$plus$colon$2=class scala/collection/generic/BufferTemplate$$anonfun$$plus$plus$colon$2 of class scala/collection/generic/BufferTemplate
  minor version: 0
  major version: 49
  Constant pool:
const #1 = Asciz	SourceFile;
const #2 = Asciz	BufferTemplate.scala;
const #3 = Asciz	$init$;
const #4 = Asciz	(Lscala/collection/generic/BufferTemplate;)V;
const #5 = Asciz	Code;
const #6 = Asciz	LineNumberTable;
const #7 = Asciz	$this;
const #8 = Asciz	Lscala/collection/generic/BufferTemplate;;
const #9 = Asciz	LocalVariableTable;
const #10 = Asciz	$minus$minus;
const #11 = Asciz	(Lscala/collection/generic/BufferTemplate;Lscala/collection/Iterator;)Lscala/collection/generic/BufferTemplate;;
const #12 = Asciz	scala/collection/generic/BufferTemplate$$anonfun$$minus$minus$2;
const #13 = class	#12;	//  scala/collection/generic/BufferTemplate$$anonfun$$minus$minus$2
const #14 = Asciz	<init>;
const #15 = NameAndType	#14:#4;//  "<init>":(Lscala/collection/generic/BufferTemplate;)V
const #16 = Method	#13.#15;	//  scala/collection/generic/BufferTemplate$$anonfun$$minus$minus$2."<init>":(Lscala/collection/generic/BufferTemplate;)V
const #17 = Asciz	scala/collection/Iterator;
const #18 = class	#17;	//  scala/collection/Iterator
const #19 = Asciz	foreach;
const #20 = Asciz	(Lscala/Function1;)V;
const #21 = NameAndType	#19:#20;//  foreach:(Lscala/Function1;)V
const #22 = InterfaceMethod	#18.#21;	//  scala/collection/Iterator.foreach:(Lscala/Function1;)V
const #23 = Asciz	scala/collection/generic/TraversableTemplate;
const #24 = class	#23;	//  scala/collection/generic/TraversableTemplate
const #25 = Asciz	thisCollection;
const #26 = Asciz	()Lscala/collection/generic/TraversableTemplate;;
const #27 = NameAndType	#25:#26;//  thisCollection:()Lscala/collection/generic/TraversableTemplate;
const #28 = InterfaceMethod	#24.#27;	//  scala/collection/generic/TraversableTemplate.thisCollection:()Lscala/collection/generic/TraversableTemplate;
const #29 = Asciz	scala/collection/generic/BufferTemplate;
const #30 = class	#29;	//  scala/collection/generic/BufferTemplate
const #31 = Asciz	iter;
const #32 = Asciz	Lscala/collection/Iterator;;
const #33 = Asciz	(Lscala/collection/generic/BufferTemplate;Lscala/collection/Traversable;)Lscala/collection/generic/BufferTemplate;;
const #34 = Asciz	scala/collection/generic/BufferTemplate$$anonfun$$minus$minus$1;
const #35 = class	#34;	//  scala/collection/generic/BufferTemplate$$anonfun$$minus$minus$1
const #36 = Method	#35.#15;	//  scala/collection/generic/BufferTemplate$$anonfun$$minus$minus$1."<init>":(Lscala/collection/generic/BufferTemplate;)V
const #37 = Asciz	scala/collection/generic/TraversableClass;
const #38 = class	#37;	//  scala/collection/generic/TraversableClass
const #39 = InterfaceMethod	#38.#21;	//  scala/collection/generic/TraversableClass.foreach:(Lscala/Function1;)V
const #40 = Asciz	Lscala/collection/Traversable;;
const #41 = Asciz	$minus;
const #42 = Asciz	(Lscala/collection/generic/BufferTemplate;Ljava/lang/Object;Ljava/lang/Object;Lscala/collection/Sequence;)Lscala/collection/generic/BufferTemplate;;
const #43 = Asciz	$minus$eq;
const #44 = Asciz	(Ljava/lang/Object;)Lscala/collection/generic/BufferTemplate;;
const #45 = NameAndType	#43:#44;//  $minus$eq:(Ljava/lang/Object;)Lscala/collection/generic/BufferTemplate;
const #46 = InterfaceMethod	#30.#45;	//  scala/collection/generic/BufferTemplate.$minus$eq:(Ljava/lang/Object;)Lscala/collection/generic/BufferTemplate;
const #47 = Asciz	scala/collection/generic/Shrinkable;
const #48 = class	#47;	//  scala/collection/generic/Shrinkable
const #49 = Asciz	$minus$minus$eq;
const #50 = Asciz	(Lscala/collection/Traversable;)Lscala/collection/generic/Shrinkable;;
const #51 = NameAndType	#49:#50;//  $minus$minus$eq:(Lscala/collection/Traversable;)Lscala/collection/generic/Shrinkable;
const #52 = InterfaceMethod	#48.#51;	//  scala/collection/generic/Shrinkable.$minus$minus$eq:(Lscala/collection/Traversable;)Lscala/collection/generic/Shrinkable;
const #53 = Asciz	elem1;
const #54 = Asciz	Ljava/lang/Object;;
const #55 = Asciz	elem2;
const #56 = Asciz	elems;
const #57 = Asciz	Lscala/collection/Sequence;;
const #58 = Asciz	(Lscala/collection/generic/BufferTemplate;Ljava/lang/Object;)Lscala/collection/generic/BufferTemplate;;
const #59 = Asciz	elem;
const #60 = Asciz	$plus$plus;
const #61 = Asciz	scala/collection/generic/BufferTemplate$$anonfun$$plus$plus$2;
const #62 = class	#61;	//  scala/collection/generic/BufferTemplate$$anonfun$$plus$plus$2
const #63 = Method	#62.#15;	//  scala/collection/generic/BufferTemplate$$anonfun$$plus$plus$2."<init>":(Lscala/collection/generic/BufferTemplate;)V
const #64 = Asciz	scala/collection/generic/BufferTemplate$$anonfun$$plus$plus$1;
const #65 = class	#64;	//  scala/collection/generic/BufferTemplate$$anonfun$$plus$plus$1
const #66 = Method	#65.#15;	//  scala/collection/generic/BufferTemplate$$anonfun$$plus$plus$1."<init>":(Lscala/collection/generic/BufferTemplate;)V
const #67 = Asciz	$plus;
const #68 = Asciz	$plus$eq;
const #69 = NameAndType	#68:#44;//  $plus$eq:(Ljava/lang/Object;)Lscala/collection/generic/BufferTemplate;
const #70 = InterfaceMethod	#30.#69;	//  scala/collection/generic/BufferTemplate.$plus$eq:(Ljava/lang/Object;)Lscala/collection/generic/BufferTemplate;
const #71 = Asciz	scala/collection/generic/Growable;
const #72 = class	#71;	//  scala/collection/generic/Growable
const #73 = Asciz	$plus$plus$eq;
const #74 = Asciz	(Lscala/collection/Traversable;)Lscala/collection/generic/Growable;;
const #75 = NameAndType	#73:#74;//  $plus$plus$eq:(Lscala/collection/Traversable;)Lscala/collection/generic/Growable;
const #76 = InterfaceMethod	#72.#75;	//  scala/collection/generic/Growable.$plus$plus$eq:(Lscala/collection/Traversable;)Lscala/collection/generic/Growable;
const #77 = Asciz	(Lscala/collection/generic/BufferTemplate;Lscala/runtime/BoxedArray;II)V;
const #78 = Asciz	scala/runtime/BoxedArray;
const #79 = class	#78;	//  scala/runtime/BoxedArray
const #80 = Asciz	apply;
const #81 = Asciz	(I)Ljava/lang/Object;;
const #82 = NameAndType	#80:#81;//  apply:(I)Ljava/lang/Object;
const #83 = Method	#79.#82;	//  scala/runtime/BoxedArray.apply:(I)Ljava/lang/Object;
const #84 = Asciz	src;
const #85 = Asciz	Lscala/runtime/BoxedArray;;
const #86 = Asciz	start;
const #87 = Asciz	I;
const #88 = Asciz	len;
const #89 = Asciz	i;
const #90 = Asciz	end;
const #91 = Asciz	stringPrefix;
const #92 = Asciz	(Lscala/collection/generic/BufferTemplate;)Ljava/lang/String;;
const #93 = Asciz	Buffer;
const #94 = String	#93;	//  Buffer
const #95 = Asciz	$less$less;
const #96 = Asciz	(Lscala/collection/generic/BufferTemplate;Lscala/collection/script/Message;)V;
const #97 = Asciz	scala/collection/script/Include;
const #98 = class	#97;	//  scala/collection/script/Include
const #99 = Asciz	location;
const #100 = Asciz	()Lscala/collection/script/Location;;
const #101 = NameAndType	#99:#100;//  location:()Lscala/collection/script/Location;
const #102 = Method	#98.#101;	//  scala/collection/script/Include.location:()Lscala/collection/script/Location;
const #103 = Asciz	()Ljava/lang/Object;;
const #104 = NameAndType	#59:#103;//  elem:()Ljava/lang/Object;
const #105 = Method	#98.#104;	//  scala/collection/script/Include.elem:()Ljava/lang/Object;
const #106 = Asciz	scala/collection/script/Start$;
const #107 = class	#106;	//  scala/collection/script/Start$
const #108 = Asciz	MODULE$;
const #109 = Asciz	Lscala/collection/script/Start$;;
const #110 = NameAndType	#108:#109;//  MODULE$:Lscala/collection/script/Start$;
const #111 = Field	#107.#110;	//  scala/collection/script/Start$.MODULE$:Lscala/collection/script/Start$;
const #112 = Asciz	java/lang/Object;
const #113 = class	#112;	//  java/lang/Object
const #114 = Asciz	equals;
const #115 = Asciz	(Ljava/lang/Object;)Z;
const #116 = NameAndType	#114:#115;//  equals:(Ljava/lang/Object;)Z
const #117 = Method	#113.#116;	//  java/lang/Object.equals:(Ljava/lang/Object;)Z
const #118 = Asciz	scala/runtime/ScalaRunTime$;
const #119 = class	#118;	//  scala/runtime/ScalaRunTime$
const #120 = Asciz	Lscala/runtime/ScalaRunTime$;;
const #121 = NameAndType	#108:#120;//  MODULE$:Lscala/runtime/ScalaRunTime$;
const #122 = Field	#119.#121;	//  scala/runtime/ScalaRunTime$.MODULE$:Lscala/runtime/ScalaRunTime$;
const #123 = Asciz	boxArray;
const #124 = Asciz	(Ljava/lang/Object;)Lscala/runtime/BoxedArray;;
const #125 = NameAndType	#123:#124;//  boxArray:(Ljava/lang/Object;)Lscala/runtime/BoxedArray;
const #126 = Method	#119.#125;	//  scala/runtime/ScalaRunTime$.boxArray:(Ljava/lang/Object;)Lscala/runtime/BoxedArray;
const #127 = Asciz	prepend;
const #128 = Asciz	(Lscala/collection/Sequence;)V;
const #129 = NameAndType	#127:#128;//  prepend:(Lscala/collection/Sequence;)V
const #130 = InterfaceMethod	#30.#129;	//  scala/collection/generic/BufferTemplate.prepend:(Lscala/collection/Sequence;)V
const #131 = Asciz	scala/collection/script/End$;
const #132 = class	#131;	//  scala/collection/script/End$
const #133 = Asciz	Lscala/collection/script/End$;;
const #134 = NameAndType	#108:#133;//  MODULE$:Lscala/collection/script/End$;
const #135 = Field	#132.#134;	//  scala/collection/script/End$.MODULE$:Lscala/collection/script/End$;
const #136 = Asciz	append;
const #137 = NameAndType	#136:#128;//  append:(Lscala/collection/Sequence;)V
const #138 = InterfaceMethod	#30.#137;	//  scala/collection/generic/BufferTemplate.append:(Lscala/collection/Sequence;)V
const #139 = Asciz	scala/collection/script/Index;
const #140 = class	#139;	//  scala/collection/script/Index
const #141 = Asciz	n;
const #142 = Asciz	()I;
const #143 = NameAndType	#141:#142;//  n:()I
const #144 = Method	#140.#143;	//  scala/collection/script/Index.n:()I
const #145 = Asciz	insert;
const #146 = Asciz	(ILscala/collection/Sequence;)V;
const #147 = NameAndType	#145:#146;//  insert:(ILscala/collection/Sequence;)V
const #148 = InterfaceMethod	#30.#147;	//  scala/collection/generic/BufferTemplate.insert:(ILscala/collection/Sequence;)V
const #149 = Asciz	scala/collection/script/NoLo$;
const #150 = class	#149;	//  scala/collection/script/NoLo$
const #151 = Asciz	Lscala/collection/script/NoLo$;;
const #152 = NameAndType	#108:#151;//  MODULE$:Lscala/collection/script/NoLo$;
const #153 = Field	#150.#152;	//  scala/collection/script/NoLo$.MODULE$:Lscala/collection/script/NoLo$;
const #154 = Asciz	java/lang/UnsupportedOperationException;
const #155 = class	#154;	//  java/lang/UnsupportedOperationException
const #156 = Asciz	scala/collection/mutable/StringBuilder;
const #157 = class	#156;	//  scala/collection/mutable/StringBuilder
const #158 = Asciz	()V;
const #159 = NameAndType	#14:#158;//  "<init>":()V
const #160 = Method	#157.#159;	//  scala/collection/mutable/StringBuilder."<init>":()V
const #161 = Asciz	message ;
const #162 = String	#161;	//  message 
const #163 = Asciz	(Ljava/lang/Object;)Lscala/collection/mutable/StringBuilder;;
const #164 = NameAndType	#136:#163;//  append:(Ljava/lang/Object;)Lscala/collection/mutable/StringBuilder;
const #165 = Method	#157.#164;	//  scala/collection/mutable/StringBuilder.append:(Ljava/lang/Object;)Lscala/collection/mutable/StringBuilder;
const #166 = Asciz	 not understood;
const #167 = String	#166;	//   not understood
const #168 = Asciz	toString;
const #169 = Asciz	()Ljava/lang/String;;
const #170 = NameAndType	#168:#169;//  toString:()Ljava/lang/String;
const #171 = Method	#157.#170;	//  scala/collection/mutable/StringBuilder.toString:()Ljava/lang/String;
const #172 = Asciz	(Ljava/lang/String;)V;
const #173 = NameAndType	#14:#172;//  "<init>":(Ljava/lang/String;)V
const #174 = Method	#155.#173;	//  java/lang/UnsupportedOperationException."<init>":(Ljava/lang/String;)V
const #175 = Asciz	scala/collection/script/Update;
const #176 = class	#175;	//  scala/collection/script/Update
const #177 = Method	#176.#101;	//  scala/collection/script/Update.location:()Lscala/collection/script/Location;
const #178 = Method	#176.#104;	//  scala/collection/script/Update.elem:()Ljava/lang/Object;
const #179 = Asciz	update;
const #180 = Asciz	(ILjava/lang/Object;)V;
const #181 = NameAndType	#179:#180;//  update:(ILjava/lang/Object;)V
const #182 = InterfaceMethod	#30.#181;	//  scala/collection/generic/BufferTemplate.update:(ILjava/lang/Object;)V
const #183 = Asciz	length;
const #184 = NameAndType	#183:#142;//  length:()I
const #185 = InterfaceMethod	#30.#184;	//  scala/collection/generic/BufferTemplate.length:()I
const #186 = Asciz	scala/collection/script/Remove;
const #187 = class	#186;	//  scala/collection/script/Remove
const #188 = Method	#187.#101;	//  scala/collection/script/Remove.location:()Lscala/collection/script/Location;
const #189 = Method	#187.#104;	//  scala/collection/script/Remove.elem:()Ljava/lang/Object;
const #190 = InterfaceMethod	#30.#82;	//  scala/collection/generic/BufferTemplate.apply:(I)Ljava/lang/Object;
const #191 = Asciz	scala/runtime/BoxesRunTime;
const #192 = class	#191;	//  scala/runtime/BoxesRunTime
const #193 = Asciz	(Ljava/lang/Object;Ljava/lang/Object;)Z;
const #194 = NameAndType	#114:#193;//  equals:(Ljava/lang/Object;Ljava/lang/Object;)Z
const #195 = Method	#192.#194;	//  scala/runtime/BoxesRunTime.equals:(Ljava/lang/Object;Ljava/lang/Object;)Z
const #196 = Asciz	remove;
const #197 = NameAndType	#196:#81;//  remove:(I)Ljava/lang/Object;
const #198 = InterfaceMethod	#30.#197;	//  scala/collection/generic/BufferTemplate.remove:(I)Ljava/lang/Object;
const #199 = Asciz	scala/collection/script/Reset;
const #200 = class	#199;	//  scala/collection/script/Reset
const #201 = Asciz	clear;
const #202 = NameAndType	#201:#158;//  clear:()V
const #203 = InterfaceMethod	#30.#202;	//  scala/collection/generic/BufferTemplate.clear:()V
const #204 = Asciz	scala/collection/script/Script;
const #205 = class	#204;	//  scala/collection/script/Script
const #206 = Asciz	scala/collection/generic/VectorTemplate;
const #207 = class	#206;	//  scala/collection/generic/VectorTemplate
const #208 = Asciz	iterator;
const #209 = Asciz	()Lscala/collection/Iterator;;
const #210 = NameAndType	#208:#209;//  iterator:()Lscala/collection/Iterator;
const #211 = InterfaceMethod	#207.#210;	//  scala/collection/generic/VectorTemplate.iterator:()Lscala/collection/Iterator;
const #212 = Asciz	scala/collection/generic/BufferTemplate$$anonfun$$less$less$1;
const #213 = class	#212;	//  scala/collection/generic/BufferTemplate$$anonfun$$less$less$1
const #214 = Method	#213.#15;	//  scala/collection/generic/BufferTemplate$$anonfun$$less$less$1."<init>":(Lscala/collection/generic/BufferTemplate;)V
const #215 = Asciz	cmd;
const #216 = Asciz	Lscala/collection/script/Message;;
const #217 = Asciz	temp1;
const #218 = Asciz	temp2;
const #219 = Asciz	Lscala/collection/script/Include;;
const #220 = Asciz	temp3;
const #221 = Asciz	Lscala/collection/script/Location;;
const #222 = Asciz	temp4;
const #223 = Asciz	temp7;
const #224 = Asciz	Lscala/collection/script/Index;;
const #225 = Asciz	temp8;
const #226 = Asciz	x;
const #227 = Asciz	temp10;
const #228 = Asciz	Lscala/collection/script/Update;;
const #229 = Asciz	temp11;
const #230 = Asciz	temp12;
const #231 = Asciz	temp15;
const #232 = Asciz	temp16;
const #233 = Asciz	temp17;
const #234 = Asciz	Lscala/collection/script/Remove;;
const #235 = Asciz	temp18;
const #236 = Asciz	temp19;
const #237 = Asciz	temp22;
const #238 = Asciz	temp23;
const #239 = Asciz	temp26;
const #240 = Asciz	Lscala/collection/script/Script;;
const #241 = Asciz	trimEnd;
const #242 = Asciz	(Lscala/collection/generic/BufferTemplate;I)V;
const #243 = Asciz	scala/Predef$;
const #244 = class	#243;	//  scala/Predef$
const #245 = Asciz	Lscala/Predef$;;
const #246 = NameAndType	#108:#245;//  MODULE$:Lscala/Predef$;
const #247 = Field	#244.#246;	//  scala/Predef$.MODULE$:Lscala/Predef$;
const #248 = Asciz	intWrapper;
const #249 = Asciz	(I)Lscala/runtime/RichInt;;
const #250 = NameAndType	#248:#249;//  intWrapper:(I)Lscala/runtime/RichInt;
const #251 = Method	#244.#250;	//  scala/Predef$.intWrapper:(I)Lscala/runtime/RichInt;
const #252 = Asciz	scala/runtime/RichInt;
const #253 = class	#252;	//  scala/runtime/RichInt
const #254 = Asciz	max;
const #255 = Asciz	(I)I;
const #256 = NameAndType	#254:#255;//  max:(I)I
const #257 = Method	#253.#256;	//  scala/runtime/RichInt.max:(I)I
const #258 = Asciz	(II)V;
const #259 = NameAndType	#196:#258;//  remove:(II)V
const #260 = InterfaceMethod	#30.#259;	//  scala/collection/generic/BufferTemplate.remove:(II)V
const #261 = Asciz	trimStart;
const #262 = Asciz	(Lscala/collection/generic/BufferTemplate;ILscala/collection/Sequence;)V;
const #263 = Asciz	insertAll;
const #264 = Asciz	(ILscala/collection/Traversable;)V;
const #265 = NameAndType	#263:#264;//  insertAll:(ILscala/collection/Traversable;)V
const #266 = InterfaceMethod	#30.#265;	//  scala/collection/generic/BufferTemplate.insertAll:(ILscala/collection/Traversable;)V
const #267 = Asciz	prependAll;
const #268 = Asciz	(Lscala/collection/generic/BufferTemplate;Lscala/collection/Iterator;)V;
const #269 = Asciz	$plus$plus$colon;
const #270 = Asciz	(Lscala/collection/Iterator;)Lscala/collection/generic/BufferTemplate;;
const #271 = NameAndType	#269:#270;//  $plus$plus$colon:(Lscala/collection/Iterator;)Lscala/collection/generic/BufferTemplate;
const #272 = InterfaceMethod	#30.#271;	//  scala/collection/generic/BufferTemplate.$plus$plus$colon:(Lscala/collection/Iterator;)Lscala/collection/generic/BufferTemplate;
const #273 = Asciz	(Lscala/collection/generic/BufferTemplate;Lscala/collection/Traversable;)V;
const #274 = Asciz	(Lscala/collection/Traversable;)Lscala/collection/generic/BufferTemplate;;
const #275 = NameAndType	#269:#274;//  $plus$plus$colon:(Lscala/collection/Traversable;)Lscala/collection/generic/BufferTemplate;
const #276 = InterfaceMethod	#30.#275;	//  scala/collection/generic/BufferTemplate.$plus$plus$colon:(Lscala/collection/Traversable;)Lscala/collection/generic/BufferTemplate;
const #277 = Asciz	(Lscala/collection/generic/BufferTemplate;Lscala/collection/Sequence;)V;
const #278 = Asciz	appendAll;
const #279 = Asciz	scala/collection/generic/BufferTemplate$$anonfun$$plus$plus$colon$2;
const #280 = class	#279;	//  scala/collection/generic/BufferTemplate$$anonfun$$plus$plus$colon$2
const #281 = Method	#280.#15;	//  scala/collection/generic/BufferTemplate$$anonfun$$plus$plus$colon$2."<init>":(Lscala/collection/generic/BufferTemplate;)V
const #282 = Asciz	scala/collection/generic/BufferTemplate$$anonfun$$plus$plus$colon$1;
const #283 = class	#282;	//  scala/collection/generic/BufferTemplate$$anonfun$$plus$plus$colon$1
const #284 = Method	#283.#15;	//  scala/collection/generic/BufferTemplate$$anonfun$$plus$plus$colon$1."<init>":(Lscala/collection/generic/BufferTemplate;)V
const #285 = Asciz	scala/collection/generic/SequenceTemplate;
const #286 = class	#285;	//  scala/collection/generic/SequenceTemplate
const #287 = Asciz	indexOf;
const #288 = Asciz	(Ljava/lang/Object;)I;
const #289 = NameAndType	#287:#288;//  indexOf:(Ljava/lang/Object;)I
const #290 = InterfaceMethod	#286.#289;	//  scala/collection/generic/SequenceTemplate.indexOf:(Ljava/lang/Object;)I
const #291 = Asciz	scala/runtime/BoxedUnit;
const #292 = class	#291;	//  scala/runtime/BoxedUnit
const #293 = Asciz	UNIT;
const #294 = Asciz	Lscala/runtime/BoxedUnit;;
const #295 = NameAndType	#293:#294;//  UNIT:Lscala/runtime/BoxedUnit;
const #296 = Field	#292.#295;	//  scala/runtime/BoxedUnit.UNIT:Lscala/runtime/BoxedUnit;
const #297 = Asciz	(Lscala/collection/generic/BufferTemplate;II)V;
const #298 = Asciz	until;
const #299 = Asciz	(I)Lscala/Range;;
const #300 = NameAndType	#298:#299;//  until:(I)Lscala/Range;
const #301 = Method	#253.#300;	//  scala/runtime/RichInt.until:(I)Lscala/Range;
const #302 = Asciz	scala/collection/generic/BufferTemplate$$anonfun$remove$1;
const #303 = class	#302;	//  scala/collection/generic/BufferTemplate$$anonfun$remove$1
const #304 = NameAndType	#14:#242;//  "<init>":(Lscala/collection/generic/BufferTemplate;I)V
const #305 = Method	#303.#304;	//  scala/collection/generic/BufferTemplate$$anonfun$remove$1."<init>":(Lscala/collection/generic/BufferTemplate;I)V
const #306 = Asciz	scala/Range;
const #307 = class	#306;	//  scala/Range
const #308 = Method	#307.#21;	//  scala/Range.foreach:(Lscala/Function1;)V
const #309 = Asciz	n$1;
const #310 = Asciz	count;
const #311 = Asciz	Scala;
const #312 = Asciz	InnerClasses;
const #313 = Asciz	$anonfun$remove$1;
const #314 = Asciz	$anonfun$$less$less$1;
const #315 = Asciz	$anonfun$$plus$plus$2;
const #316 = Asciz	$anonfun$$plus$plus$1;
const #317 = Asciz	$anonfun$$minus$minus$2;
const #318 = Asciz	$anonfun$$minus$minus$1;
const #319 = Asciz	$anonfun$$plus$plus$colon$1;
const #320 = Asciz	$anonfun$$plus$plus$colon$2;
const #321 = Asciz	scala/collection/generic/BufferTemplate$class;
const #322 = class	#321;	//  scala/collection/generic/BufferTemplate$class

{
public static void $init$(scala.collection.generic.BufferTemplate);
  Code:
   Stack=0, Locals=1, Args_size=1
   0:	return
  LineNumberTable: 
   line 29: 0

  LocalVariableTable: 
   Start  Length  Slot  Name   Signature
   0      1      0    $this       Lscala/collection/generic/BufferTemplate;


public static scala.collection.generic.BufferTemplate $minus$minus(scala.collection.generic.BufferTemplate, scala.collection.Iterator);
  Code:
   Stack=4, Locals=2, Args_size=2
   0:	aload_1
   1:	new	#13; //class scala/collection/generic/BufferTemplate$$anonfun$$minus$minus$2
   4:	dup
   5:	aload_0
   6:	invokespecial	#16; //Method scala/collection/generic/BufferTemplate$$anonfun$$minus$minus$2."<init>":(Lscala/collection/generic/BufferTemplate;)V
   9:	invokeinterface	#22,  2; //InterfaceMethod scala/collection/Iterator.foreach:(Lscala/Function1;)V
   14:	aload_0
   15:	invokeinterface	#28,  1; //InterfaceMethod scala/collection/generic/TraversableTemplate.thisCollection:()Lscala/collection/generic/TraversableTemplate;
   20:	checkcast	#30; //class scala/collection/generic/BufferTemplate
   23:	areturn
  LineNumberTable: 
   line 327: 0
   line 328: 14

  LocalVariableTable: 
   Start  Length  Slot  Name   Signature
   0      24      0    $this       Lscala/collection/generic/BufferTemplate;
   0      24      1    iter       Lscala/collection/Iterator;


public static scala.collection.generic.BufferTemplate $minus$minus(scala.collection.generic.BufferTemplate, scala.collection.Traversable);
  Code:
   Stack=4, Locals=2, Args_size=2
   0:	aload_1
   1:	new	#35; //class scala/collection/generic/BufferTemplate$$anonfun$$minus$minus$1
   4:	dup
   5:	aload_0
   6:	invokespecial	#36; //Method scala/collection/generic/BufferTemplate$$anonfun$$minus$minus$1."<init>":(Lscala/collection/generic/BufferTemplate;)V
   9:	invokeinterface	#39,  2; //InterfaceMethod scala/collection/generic/TraversableClass.foreach:(Lscala/Function1;)V
   14:	aload_0
   15:	invokeinterface	#28,  1; //InterfaceMethod scala/collection/generic/TraversableTemplate.thisCollection:()Lscala/collection/generic/TraversableTemplate;
   20:	checkcast	#30; //class scala/collection/generic/BufferTemplate
   23:	areturn
  LineNumberTable: 
   line 315: 0
   line 316: 14

  LocalVariableTable: 
   Start  Length  Slot  Name   Signature
   0      24      0    $this       Lscala/collection/generic/BufferTemplate;
   0      24      1    iter       Lscala/collection/Traversable;


public static scala.collection.generic.BufferTemplate $minus(scala.collection.generic.BufferTemplate, java.lang.Object, java.lang.Object, scala.collection.Sequence);
  Code:
   Stack=2, Locals=4, Args_size=4
   0:	aload_0
   1:	aload_1
   2:	invokeinterface	#46,  2; //InterfaceMethod scala/collection/generic/BufferTemplate.$minus$eq:(Ljava/lang/Object;)Lscala/collection/generic/BufferTemplate;
   7:	aload_2
   8:	invokeinterface	#46,  2; //InterfaceMethod scala/collection/generic/BufferTemplate.$minus$eq:(Ljava/lang/Object;)Lscala/collection/generic/BufferTemplate;
   13:	aload_3
   14:	invokeinterface	#52,  2; //InterfaceMethod scala/collection/generic/Shrinkable.$minus$minus$eq:(Lscala/collection/Traversable;)Lscala/collection/generic/Shrinkable;
   19:	pop
   20:	aload_0
   21:	invokeinterface	#28,  1; //InterfaceMethod scala/collection/generic/TraversableTemplate.thisCollection:()Lscala/collection/generic/TraversableTemplate;
   26:	checkcast	#30; //class scala/collection/generic/BufferTemplate
   29:	areturn
  LineNumberTable: 
   line 303: 0
   line 304: 20

  LocalVariableTable: 
   Start  Length  Slot  Name   Signature
   0      30      0    $this       Lscala/collection/generic/BufferTemplate;
   0      30      1    elem1       Ljava/lang/Object;
   0      30      2    elem2       Ljava/lang/Object;
   0      30      3    elems       Lscala/collection/Sequence;


public static scala.collection.generic.BufferTemplate $minus(scala.collection.generic.BufferTemplate, java.lang.Object);
  Code:
   Stack=2, Locals=2, Args_size=2
   0:	aload_0
   1:	aload_1
   2:	invokeinterface	#46,  2; //InterfaceMethod scala/collection/generic/BufferTemplate.$minus$eq:(Ljava/lang/Object;)Lscala/collection/generic/BufferTemplate;
   7:	pop
   8:	aload_0
   9:	invokeinterface	#28,  1; //InterfaceMethod scala/collection/generic/TraversableTemplate.thisCollection:()Lscala/collection/generic/TraversableTemplate;
   14:	checkcast	#30; //class scala/collection/generic/BufferTemplate
   17:	areturn
  LineNumberTable: 
   line 291: 0

  LocalVariableTable: 
   Start  Length  Slot  Name   Signature
   0      18      0    $this       Lscala/collection/generic/BufferTemplate;
   0      18      1    elem       Ljava/lang/Object;


public static scala.collection.generic.BufferTemplate $plus$plus(scala.collection.generic.BufferTemplate, scala.collection.Iterator);
  Code:
   Stack=4, Locals=2, Args_size=2
   0:	aload_1
   1:	new	#62; //class scala/collection/generic/BufferTemplate$$anonfun$$plus$plus$2
   4:	dup
   5:	aload_0
   6:	invokespecial	#63; //Method scala/collection/generic/BufferTemplate$$anonfun$$plus$plus$2."<init>":(Lscala/collection/generic/BufferTemplate;)V
   9:	invokeinterface	#22,  2; //InterfaceMethod scala/collection/Iterator.foreach:(Lscala/Function1;)V
   14:	aload_0
   15:	invokeinterface	#28,  1; //InterfaceMethod scala/collection/generic/TraversableTemplate.thisCollection:()Lscala/collection/generic/TraversableTemplate;
   20:	checkcast	#30; //class scala/collection/generic/BufferTemplate
   23:	areturn
  LineNumberTable: 
   line 280: 0
   line 281: 14

  LocalVariableTable: 
   Start  Length  Slot  Name   Signature
   0      24      0    $this       Lscala/collection/generic/BufferTemplate;
   0      24      1    iter       Lscala/collection/Iterator;


public static scala.collection.generic.BufferTemplate $plus$plus(scala.collection.generic.BufferTemplate, scala.collection.Traversable);
  Code:
   Stack=4, Locals=2, Args_size=2
   0:	aload_1
   1:	new	#65; //class scala/collection/generic/BufferTemplate$$anonfun$$plus$plus$1
   4:	dup
   5:	aload_0
   6:	invokespecial	#66; //Method scala/collection/generic/BufferTemplate$$anonfun$$plus$plus$1."<init>":(Lscala/collection/generic/BufferTemplate;)V
   9:	invokeinterface	#39,  2; //InterfaceMethod scala/collection/generic/TraversableClass.foreach:(Lscala/Function1;)V
   14:	aload_0
   15:	invokeinterface	#28,  1; //InterfaceMethod scala/collection/generic/TraversableTemplate.thisCollection:()Lscala/collection/generic/TraversableTemplate;
   20:	checkcast	#30; //class scala/collection/generic/BufferTemplate
   23:	areturn
  LineNumberTable: 
   line 268: 0
   line 269: 14

  LocalVariableTable: 
   Start  Length  Slot  Name   Signature
   0      24      0    $this       Lscala/collection/generic/BufferTemplate;
   0      24      1    iter       Lscala/collection/Traversable;


public static scala.collection.generic.BufferTemplate $plus(scala.collection.generic.BufferTemplate, java.lang.Object, java.lang.Object, scala.collection.Sequence);
  Code:
   Stack=2, Locals=4, Args_size=4
   0:	aload_0
   1:	aload_1
   2:	invokeinterface	#70,  2; //InterfaceMethod scala/collection/generic/BufferTemplate.$plus$eq:(Ljava/lang/Object;)Lscala/collection/generic/BufferTemplate;
   7:	aload_2
   8:	invokeinterface	#70,  2; //InterfaceMethod scala/collection/generic/BufferTemplate.$plus$eq:(Ljava/lang/Object;)Lscala/collection/generic/BufferTemplate;
   13:	aload_3
   14:	invokeinterface	#76,  2; //InterfaceMethod scala/collection/generic/Growable.$plus$plus$eq:(Lscala/collection/Traversable;)Lscala/collection/generic/Growable;
   19:	pop
   20:	aload_0
   21:	invokeinterface	#28,  1; //InterfaceMethod scala/collection/generic/TraversableTemplate.thisCollection:()Lscala/collection/generic/TraversableTemplate;
   26:	checkcast	#30; //class scala/collection/generic/BufferTemplate
   29:	areturn
  LineNumberTable: 
   line 256: 0
   line 257: 20

  LocalVariableTable: 
   Start  Length  Slot  Name   Signature
   0      30      0    $this       Lscala/collection/generic/BufferTemplate;
   0      30      1    elem1       Ljava/lang/Object;
   0      30      2    elem2       Ljava/lang/Object;
   0      30      3    elems       Lscala/collection/Sequence;


public static scala.collection.generic.BufferTemplate $plus(scala.collection.generic.BufferTemplate, java.lang.Object);
  Code:
   Stack=2, Locals=2, Args_size=2
   0:	aload_0
   1:	aload_1
   2:	invokeinterface	#70,  2; //InterfaceMethod scala/collection/generic/BufferTemplate.$plus$eq:(Ljava/lang/Object;)Lscala/collection/generic/BufferTemplate;
   7:	pop
   8:	aload_0
   9:	invokeinterface	#28,  1; //InterfaceMethod scala/collection/generic/TraversableTemplate.thisCollection:()Lscala/collection/generic/TraversableTemplate;
   14:	checkcast	#30; //class scala/collection/generic/BufferTemplate
   17:	areturn
  LineNumberTable: 
   line 244: 0

  LocalVariableTable: 
   Start  Length  Slot  Name   Signature
   0      18      0    $this       Lscala/collection/generic/BufferTemplate;
   0      18      1    elem       Ljava/lang/Object;


public static void $plus$plus$eq(scala.collection.generic.BufferTemplate, scala.runtime.BoxedArray, int, int);
  Code:
   Stack=3, Locals=6, Args_size=4
   0:	iload_2
   1:	istore	4
   3:	iload	4
   5:	iload_3
   6:	iadd
   7:	istore	5
   9:	iload	4
   11:	iload	5
   13:	if_icmpge	38
   16:	aload_0
   17:	aload_1
   18:	iload	4
   20:	invokevirtual	#83; //Method scala/runtime/BoxedArray.apply:(I)Ljava/lang/Object;
   23:	invokeinterface	#70,  2; //InterfaceMethod scala/collection/generic/BufferTemplate.$plus$eq:(Ljava/lang/Object;)Lscala/collection/generic/BufferTemplate;
   28:	pop
   29:	iload	4
   31:	iconst_1
   32:	iadd
   33:	istore	4
   35:	goto	9
   38:	return
  LineNumberTable: 
   line 229: 0
   line 230: 3
   line 231: 9
   line 232: 16
   line 233: 29
   line 231: 35
   line 228: 38

  LocalVariableTable: 
   Start  Length  Slot  Name   Signature
   0      39      0    $this       Lscala/collection/generic/BufferTemplate;
   0      39      1    src       Lscala/runtime/BoxedArray;
   0      39      2    start       I
   0      39      3    len       I
   3      36      4    i       I
   9      30      5    end       I


public static java.lang.String stringPrefix(scala.collection.generic.BufferTemplate);
  Code:
   Stack=1, Locals=1, Args_size=1
   0:	ldc	#94; //String Buffer
   2:	areturn
  LineNumberTable: 
   line 219: 0

  LocalVariableTable: 
   Start  Length  Slot  Name   Signature
   0      3      0    $this       Lscala/collection/generic/BufferTemplate;


public static void $less$less(scala.collection.generic.BufferTemplate, scala.collection.script.Message);
  Code:
   Stack=7, Locals=31, Args_size=2
   0:	aload_1
   1:	astore_2
   2:	aload_2
   3:	instanceof	#98; //class scala/collection/script/Include
   6:	ifeq	278
   9:	aload_2
   10:	checkcast	#98; //class scala/collection/script/Include
   13:	astore_3
   14:	aload_3
   15:	invokevirtual	#102; //Method scala/collection/script/Include.location:()Lscala/collection/script/Location;
   18:	astore	4
   20:	aload_3
   21:	invokevirtual	#105; //Method scala/collection/script/Include.elem:()Ljava/lang/Object;
   24:	astore	5
   26:	getstatic	#111; //Field scala/collection/script/Start$.MODULE$:Lscala/collection/script/Start$;
   29:	aload	4
   31:	astore	6
   33:	dup
   34:	ifnonnull	46
   37:	pop
   38:	aload	6
   40:	ifnull	54
   43:	goto	86
   46:	aload	6
   48:	invokevirtual	#117; //Method java/lang/Object.equals:(Ljava/lang/Object;)Z
   51:	ifeq	86
   54:	aload	4
   56:	instanceof	#107; //class scala/collection/script/Start$
   59:	ifeq	86
   62:	aload_0
   63:	getstatic	#122; //Field scala/runtime/ScalaRunTime$.MODULE$:Lscala/runtime/ScalaRunTime$;
   66:	iconst_1
   67:	anewarray	#113; //class java/lang/Object
   70:	dup
   71:	iconst_0
   72:	aload	5
   74:	aastore
   75:	invokevirtual	#126; //Method scala/runtime/ScalaRunTime$.boxArray:(Ljava/lang/Object;)Lscala/runtime/BoxedArray;
   78:	invokeinterface	#130,  2; //InterfaceMethod scala/collection/generic/BufferTemplate.prepend:(Lscala/collection/Sequence;)V
   83:	goto	831
   86:	getstatic	#135; //Field scala/collection/script/End$.MODULE$:Lscala/collection/script/End$;
   89:	aload	4
   91:	astore	7
   93:	dup
   94:	ifnonnull	106
   97:	pop
   98:	aload	7
   100:	ifnull	114
   103:	goto	146
   106:	aload	7
   108:	invokevirtual	#117; //Method java/lang/Object.equals:(Ljava/lang/Object;)Z
   111:	ifeq	146
   114:	aload	4
   116:	instanceof	#132; //class scala/collection/script/End$
   119:	ifeq	146
   122:	aload_0
   123:	getstatic	#122; //Field scala/runtime/ScalaRunTime$.MODULE$:Lscala/runtime/ScalaRunTime$;
   126:	iconst_1
   127:	anewarray	#113; //class java/lang/Object
   130:	dup
   131:	iconst_0
   132:	aload	5
   134:	aastore
   135:	invokevirtual	#126; //Method scala/runtime/ScalaRunTime$.boxArray:(Ljava/lang/Object;)Lscala/runtime/BoxedArray;
   138:	invokeinterface	#138,  2; //InterfaceMethod scala/collection/generic/BufferTemplate.append:(Lscala/collection/Sequence;)V
   143:	goto	831
   146:	aload	4
   148:	instanceof	#140; //class scala/collection/script/Index
   151:	ifeq	198
   154:	aload	4
   156:	checkcast	#140; //class scala/collection/script/Index
   159:	astore	8
   161:	aload	8
   163:	invokevirtual	#144; //Method scala/collection/script/Index.n:()I
   166:	istore	9
   168:	aload	5
   170:	astore	10
   172:	aload_0
   173:	iload	9
   175:	getstatic	#122; //Field scala/runtime/ScalaRunTime$.MODULE$:Lscala/runtime/ScalaRunTime$;
   178:	iconst_1
   179:	anewarray	#113; //class java/lang/Object
   182:	dup
   183:	iconst_0
   184:	aload	10
   186:	aastore
   187:	invokevirtual	#126; //Method scala/runtime/ScalaRunTime$.boxArray:(Ljava/lang/Object;)Lscala/runtime/BoxedArray;
   190:	invokeinterface	#148,  3; //InterfaceMethod scala/collection/generic/BufferTemplate.insert:(ILscala/collection/Sequence;)V
   195:	goto	831
   198:	getstatic	#153; //Field scala/collection/script/NoLo$.MODULE$:Lscala/collection/script/NoLo$;
   201:	aload	4
   203:	astore	11
   205:	dup
   206:	ifnonnull	218
   209:	pop
   210:	aload	11
   212:	ifnull	226
   215:	goto	246
   218:	aload	11
   220:	invokevirtual	#117; //Method java/lang/Object.equals:(Ljava/lang/Object;)Z
   223:	ifeq	246
   226:	aload	4
   228:	instanceof	#150; //class scala/collection/script/NoLo$
   231:	ifeq	246
   234:	aload_0
   235:	aload	5
   237:	invokeinterface	#70,  2; //InterfaceMethod scala/collection/generic/BufferTemplate.$plus$eq:(Ljava/lang/Object;)Lscala/collection/generic/BufferTemplate;
   242:	pop
   243:	goto	831
   246:	new	#155; //class java/lang/UnsupportedOperationException
   249:	dup
   250:	new	#157; //class scala/collection/mutable/StringBuilder
   253:	dup
   254:	invokespecial	#160; //Method scala/collection/mutable/StringBuilder."<init>":()V
   257:	ldc	#162; //String message 
   259:	invokevirtual	#165; //Method scala/collection/mutable/StringBuilder.append:(Ljava/lang/Object;)Lscala/collection/mutable/StringBuilder;
   262:	aload_1
   263:	invokevirtual	#165; //Method scala/collection/mutable/StringBuilder.append:(Ljava/lang/Object;)Lscala/collection/mutable/StringBuilder;
   266:	ldc	#167; //String  not understood
   268:	invokevirtual	#165; //Method scala/collection/mutable/StringBuilder.append:(Ljava/lang/Object;)Lscala/collection/mutable/StringBuilder;
   271:	invokevirtual	#171; //Method scala/collection/mutable/StringBuilder.toString:()Ljava/lang/String;
   274:	invokespecial	#174; //Method java/lang/UnsupportedOperationException."<init>":(Ljava/lang/String;)V
   277:	athrow
   278:	aload_2
   279:	instanceof	#176; //class scala/collection/script/Update
   282:	ifeq	479
   285:	aload_2
   286:	checkcast	#176; //class scala/collection/script/Update
   289:	astore	12
   291:	aload	12
   293:	invokevirtual	#177; //Method scala/collection/script/Update.location:()Lscala/collection/script/Location;
   296:	astore	13
   298:	aload	12
   300:	invokevirtual	#178; //Method scala/collection/script/Update.elem:()Ljava/lang/Object;
   303:	astore	14
   305:	getstatic	#111; //Field scala/collection/script/Start$.MODULE$:Lscala/collection/script/Start$;
   308:	aload	13
   310:	astore	15
   312:	dup
   313:	ifnonnull	325
   316:	pop
   317:	aload	15
   319:	ifnull	333
   322:	goto	353
   325:	aload	15
   327:	invokevirtual	#117; //Method java/lang/Object.equals:(Ljava/lang/Object;)Z
   330:	ifeq	353
   333:	aload	13
   335:	instanceof	#107; //class scala/collection/script/Start$
   338:	ifeq	353
   341:	aload_0
   342:	iconst_0
   343:	aload	14
   345:	invokeinterface	#182,  3; //InterfaceMethod scala/collection/generic/BufferTemplate.update:(ILjava/lang/Object;)V
   350:	goto	831
   353:	getstatic	#135; //Field scala/collection/script/End$.MODULE$:Lscala/collection/script/End$;
   356:	aload	13
   358:	astore	16
   360:	dup
   361:	ifnonnull	373
   364:	pop
   365:	aload	16
   367:	ifnull	381
   370:	goto	408
   373:	aload	16
   375:	invokevirtual	#117; //Method java/lang/Object.equals:(Ljava/lang/Object;)Z
   378:	ifeq	408
   381:	aload	13
   383:	instanceof	#132; //class scala/collection/script/End$
   386:	ifeq	408
   389:	aload_0
   390:	aload_0
   391:	invokeinterface	#185,  1; //InterfaceMethod scala/collection/generic/BufferTemplate.length:()I
   396:	iconst_1
   397:	isub
   398:	aload	14
   400:	invokeinterface	#182,  3; //InterfaceMethod scala/collection/generic/BufferTemplate.update:(ILjava/lang/Object;)V
   405:	goto	831
   408:	aload	13
   410:	instanceof	#140; //class scala/collection/script/Index
   413:	ifeq	447
   416:	aload	13
   418:	checkcast	#140; //class scala/collection/script/Index
   421:	astore	17
   423:	aload	17
   425:	invokevirtual	#144; //Method scala/collection/script/Index.n:()I
   428:	istore	18
   430:	aload	14
   432:	astore	19
   434:	aload_0
   435:	iload	18
   437:	aload	19
   439:	invokeinterface	#182,  3; //InterfaceMethod scala/collection/generic/BufferTemplate.update:(ILjava/lang/Object;)V
   444:	goto	831
   447:	new	#155; //class java/lang/UnsupportedOperationException
   450:	dup
   451:	new	#157; //class scala/collection/mutable/StringBuilder
   454:	dup
   455:	invokespecial	#160; //Method scala/collection/mutable/StringBuilder."<init>":()V
   458:	ldc	#162; //String message 
   460:	invokevirtual	#165; //Method scala/collection/mutable/StringBuilder.append:(Ljava/lang/Object;)Lscala/collection/mutable/StringBuilder;
   463:	aload_1
   464:	invokevirtual	#165; //Method scala/collection/mutable/StringBuilder.append:(Ljava/lang/Object;)Lscala/collection/mutable/StringBuilder;
   467:	ldc	#167; //String  not understood
   469:	invokevirtual	#165; //Method scala/collection/mutable/StringBuilder.append:(Ljava/lang/Object;)Lscala/collection/mutable/StringBuilder;
   472:	invokevirtual	#171; //Method scala/collection/mutable/StringBuilder.toString:()Ljava/lang/String;
   475:	invokespecial	#174; //Method java/lang/UnsupportedOperationException."<init>":(Ljava/lang/String;)V
   478:	athrow
   479:	aload_2
   480:	instanceof	#187; //class scala/collection/script/Remove
   483:	ifeq	782
   486:	aload_2
   487:	checkcast	#187; //class scala/collection/script/Remove
   490:	astore	20
   492:	aload	20
   494:	invokevirtual	#188; //Method scala/collection/script/Remove.location:()Lscala/collection/script/Location;
   497:	astore	21
   499:	aload	20
   501:	invokevirtual	#189; //Method scala/collection/script/Remove.elem:()Ljava/lang/Object;
   504:	astore	22
   506:	getstatic	#111; //Field scala/collection/script/Start$.MODULE$:Lscala/collection/script/Start$;
   509:	aload	21
   511:	astore	23
   513:	dup
   514:	ifnonnull	526
   517:	pop
   518:	aload	23
   520:	ifnull	534
   523:	goto	568
   526:	aload	23
   528:	invokevirtual	#117; //Method java/lang/Object.equals:(Ljava/lang/Object;)Z
   531:	ifeq	568
   534:	aload	21
   536:	instanceof	#107; //class scala/collection/script/Start$
   539:	ifeq	568
   542:	aload_0
   543:	iconst_0
   544:	invokeinterface	#190,  2; //InterfaceMethod scala/collection/generic/BufferTemplate.apply:(I)Ljava/lang/Object;
   549:	aload	22
   551:	invokestatic	#195; //Method scala/runtime/BoxesRunTime.equals:(Ljava/lang/Object;Ljava/lang/Object;)Z
   554:	ifeq	831
   557:	aload_0
   558:	iconst_0
   559:	invokeinterface	#198,  2; //InterfaceMethod scala/collection/generic/BufferTemplate.remove:(I)Ljava/lang/Object;
   564:	pop
   565:	goto	831
   568:	getstatic	#135; //Field scala/collection/script/End$.MODULE$:Lscala/collection/script/End$;
   571:	aload	21
   573:	astore	24
   575:	dup
   576:	ifnonnull	588
   579:	pop
   580:	aload	24
   582:	ifnull	596
   585:	goto	644
   588:	aload	24
   590:	invokevirtual	#117; //Method java/lang/Object.equals:(Ljava/lang/Object;)Z
   593:	ifeq	644
   596:	aload	21
   598:	instanceof	#132; //class scala/collection/script/End$
   601:	ifeq	644
   604:	aload_0
   605:	aload_0
   606:	invokeinterface	#185,  1; //InterfaceMethod scala/collection/generic/BufferTemplate.length:()I
   611:	iconst_1
   612:	isub
   613:	invokeinterface	#190,  2; //InterfaceMethod scala/collection/generic/BufferTemplate.apply:(I)Ljava/lang/Object;
   618:	aload	22
   620:	invokestatic	#195; //Method scala/runtime/BoxesRunTime.equals:(Ljava/lang/Object;Ljava/lang/Object;)Z
   623:	ifeq	831
   626:	aload_0
   627:	aload_0
   628:	invokeinterface	#185,  1; //InterfaceMethod scala/collection/generic/BufferTemplate.length:()I
   633:	iconst_1
   634:	isub
   635:	invokeinterface	#198,  2; //InterfaceMethod scala/collection/generic/BufferTemplate.remove:(I)Ljava/lang/Object;
   640:	pop
   641:	goto	831
   644:	aload	21
   646:	instanceof	#140; //class scala/collection/script/Index
   649:	ifeq	702
   652:	aload	21
   654:	checkcast	#140; //class scala/collection/script/Index
   657:	astore	25
   659:	aload	25
   661:	invokevirtual	#144; //Method scala/collection/script/Index.n:()I
   664:	istore	26
   666:	aload	22
   668:	astore	27
   670:	iload	26
   672:	istore	28
   674:	aload_0
   675:	iload	28
   677:	invokeinterface	#190,  2; //InterfaceMethod scala/collection/generic/BufferTemplate.apply:(I)Ljava/lang/Object;
   682:	aload	27
   684:	invokestatic	#195; //Method scala/runtime/BoxesRunTime.equals:(Ljava/lang/Object;Ljava/lang/Object;)Z
   687:	ifeq	831
   690:	aload_0
   691:	iload	28
   693:	invokeinterface	#198,  2; //InterfaceMethod scala/collection/generic/BufferTemplate.remove:(I)Ljava/lang/Object;
   698:	pop
   699:	goto	831
   702:	getstatic	#153; //Field scala/collection/script/NoLo$.MODULE$:Lscala/collection/script/NoLo$;
   705:	aload	21
   707:	astore	29
   709:	dup
   710:	ifnonnull	722
   713:	pop
   714:	aload	29
   716:	ifnull	730
   719:	goto	750
   722:	aload	29
   724:	invokevirtual	#117; //Method java/lang/Object.equals:(Ljava/lang/Object;)Z
   727:	ifeq	750
   730:	aload	21
   732:	instanceof	#150; //class scala/collection/script/NoLo$
   735:	ifeq	750
   738:	aload_0
   739:	aload	22
   741:	invokeinterface	#46,  2; //InterfaceMethod scala/collection/generic/BufferTemplate.$minus$eq:(Ljava/lang/Object;)Lscala/collection/generic/BufferTemplate;
   746:	pop
   747:	goto	831
   750:	new	#155; //class java/lang/UnsupportedOperationException
   753:	dup
   754:	new	#157; //class scala/collection/mutable/StringBuilder
   757:	dup
   758:	invokespecial	#160; //Method scala/collection/mutable/StringBuilder."<init>":()V
   761:	ldc	#162; //String message 
   763:	invokevirtual	#165; //Method scala/collection/mutable/StringBuilder.append:(Ljava/lang/Object;)Lscala/collection/mutable/StringBuilder;
   766:	aload_1
   767:	invokevirtual	#165; //Method scala/collection/mutable/StringBuilder.append:(Ljava/lang/Object;)Lscala/collection/mutable/StringBuilder;
   770:	ldc	#167; //String  not understood
   772:	invokevirtual	#165; //Method scala/collection/mutable/StringBuilder.append:(Ljava/lang/Object;)Lscala/collection/mutable/StringBuilder;
   775:	invokevirtual	#171; //Method scala/collection/mutable/StringBuilder.toString:()Ljava/lang/String;
   778:	invokespecial	#174; //Method java/lang/UnsupportedOperationException."<init>":(Ljava/lang/String;)V
   781:	athrow
   782:	aload_2
   783:	instanceof	#200; //class scala/collection/script/Reset
   786:	ifeq	798
   789:	aload_0
   790:	invokeinterface	#203,  1; //InterfaceMethod scala/collection/generic/BufferTemplate.clear:()V
   795:	goto	831
   798:	aload_2
   799:	instanceof	#205; //class scala/collection/script/Script
   802:	ifeq	832
   805:	aload_2
   806:	checkcast	#205; //class scala/collection/script/Script
   809:	astore	30
   811:	aload	30
   813:	invokeinterface	#211,  1; //InterfaceMethod scala/collection/generic/VectorTemplate.iterator:()Lscala/collection/Iterator;
   818:	new	#213; //class scala/collection/generic/BufferTemplate$$anonfun$$less$less$1
   821:	dup
   822:	aload_0
   823:	invokespecial	#214; //Method scala/collection/generic/BufferTemplate$$anonfun$$less$less$1."<init>":(Lscala/collection/generic/BufferTemplate;)V
   826:	invokeinterface	#22,  2; //InterfaceMethod scala/collection/Iterator.foreach:(Lscala/Function1;)V
   831:	return
   832:	new	#155; //class java/lang/UnsupportedOperationException
   835:	dup
   836:	new	#157; //class scala/collection/mutable/StringBuilder
   839:	dup
   840:	invokespecial	#160; //Method scala/collection/mutable/StringBuilder."<init>":()V
   843:	ldc	#162; //String message 
   845:	invokevirtual	#165; //Method scala/collection/mutable/StringBuilder.append:(Ljava/lang/Object;)Lscala/collection/mutable/StringBuilder;
   848:	aload_1
   849:	invokevirtual	#165; //Method scala/collection/mutable/StringBuilder.append:(Ljava/lang/Object;)Lscala/collection/mutable/StringBuilder;
   852:	ldc	#167; //String  not understood
   854:	invokevirtual	#165; //Method scala/collection/mutable/StringBuilder.append:(Ljava/lang/Object;)Lscala/collection/mutable/StringBuilder;
   857:	invokevirtual	#171; //Method scala/collection/mutable/StringBuilder.toString:()Ljava/lang/String;
   860:	invokespecial	#174; //Method java/lang/UnsupportedOperationException."<init>":(Ljava/lang/String;)V
   863:	athrow
  LineNumberTable: 
   line 197: 0
   line 198: 62
   line 197: 86
   line 199: 122
   line 197: 146
   line 200: 168
   line 197: 198
   line 201: 234
   line 214: 246
   line 197: 278
   line 203: 341
   line 197: 353
   line 204: 389
   line 197: 408
   line 205: 430
   line 214: 447
   line 197: 479
   line 207: 542
   line 197: 568
   line 208: 604
   line 197: 644
   line 209: 666
   line 197: 702
   line 210: 738
   line 214: 750
   line 197: 782
   line 212: 789
   line 197: 798
   line 213: 811
   line 197: 831
   line 214: 832

  LocalVariableTable: 
   Start  Length  Slot  Name   Signature
   0      864      0    $this       Lscala/collection/generic/BufferTemplate;
   0      864      1    cmd       Lscala/collection/script/Message;
   2      862      2    temp1       Lscala/collection/script/Message;
   14      264      3    temp2       Lscala/collection/script/Include;
   20      258      4    temp3       Lscala/collection/script/Location;
   26      252      5    temp4       Ljava/lang/Object;
   161      34      8    temp7       Lscala/collection/script/Index;
   168      27      9    temp8       I
   172      23      10    x       Ljava/lang/Object;
   291      188      12    temp10       Lscala/collection/script/Update;
   298      181      13    temp11       Lscala/collection/script/Location;
   305      174      14    temp12       Ljava/lang/Object;
   423      21      17    temp15       Lscala/collection/script/Index;
   430      14      18    temp16       I
   434      10      19    x       Ljava/lang/Object;
   492      290      20    temp17       Lscala/collection/script/Remove;
   499      283      21    temp18       Lscala/collection/script/Location;
   506      276      22    temp19       Ljava/lang/Object;
   659      43      25    temp22       Lscala/collection/script/Index;
   666      36      26    temp23       I
   670      32      27    x       Ljava/lang/Object;
   674      28      28    n       I
   811      20      30    temp26       Lscala/collection/script/Script;


public static void trimEnd(scala.collection.generic.BufferTemplate, int);
  Code:
   Stack=4, Locals=2, Args_size=2
   0:	aload_0
   1:	getstatic	#247; //Field scala/Predef$.MODULE$:Lscala/Predef$;
   4:	aload_0
   5:	invokeinterface	#185,  1; //InterfaceMethod scala/collection/generic/BufferTemplate.length:()I
   10:	iload_1
   11:	isub
   12:	invokevirtual	#251; //Method scala/Predef$.intWrapper:(I)Lscala/runtime/RichInt;
   15:	iconst_0
   16:	invokevirtual	#257; //Method scala/runtime/RichInt.max:(I)I
   19:	iload_1
   20:	invokeinterface	#260,  3; //InterfaceMethod scala/collection/generic/BufferTemplate.remove:(II)V
   25:	return
  LineNumberTable: 
   line 191: 0

  LocalVariableTable: 
   Start  Length  Slot  Name   Signature
   0      26      0    $this       Lscala/collection/generic/BufferTemplate;
   0      26      1    n       I


public static void trimStart(scala.collection.generic.BufferTemplate, int);
  Code:
   Stack=3, Locals=2, Args_size=2
   0:	aload_0
   1:	iconst_0
   2:	iload_1
   3:	invokeinterface	#260,  3; //InterfaceMethod scala/collection/generic/BufferTemplate.remove:(II)V
   8:	return
  LineNumberTable: 
   line 184: 0

  LocalVariableTable: 
   Start  Length  Slot  Name   Signature
   0      9      0    $this       Lscala/collection/generic/BufferTemplate;
   0      9      1    n       I


public static void insert(scala.collection.generic.BufferTemplate, int, scala.collection.Sequence);
  Code:
   Stack=3, Locals=3, Args_size=3
   0:	aload_0
   1:	iload_1
   2:	aload_2
   3:	invokeinterface	#266,  3; //InterfaceMethod scala/collection/generic/BufferTemplate.insertAll:(ILscala/collection/Traversable;)V
   8:	return
  LineNumberTable: 
   line 177: 0

  LocalVariableTable: 
   Start  Length  Slot  Name   Signature
   0      9      0    $this       Lscala/collection/generic/BufferTemplate;
   0      9      1    n       I
   0      9      2    elems       Lscala/collection/Sequence;


public static void prependAll(scala.collection.generic.BufferTemplate, scala.collection.Iterator);
  Code:
   Stack=2, Locals=3, Args_size=2
   0:	aload_1
   1:	astore_2
   2:	aload_0
   3:	aload_2
   4:	invokeinterface	#272,  2; //InterfaceMethod scala/collection/generic/BufferTemplate.$plus$plus$colon:(Lscala/collection/Iterator;)Lscala/collection/generic/BufferTemplate;
   9:	pop
   10:	return
  LineNumberTable: 
   line 168: 0

  LocalVariableTable: 
   Start  Length  Slot  Name   Signature
   0      11      0    $this       Lscala/collection/generic/BufferTemplate;
   0      11      1    iter       Lscala/collection/Iterator;


public static void prependAll(scala.collection.generic.BufferTemplate, scala.collection.Traversable);
  Code:
   Stack=2, Locals=3, Args_size=2
   0:	aload_1
   1:	astore_2
   2:	aload_0
   3:	aload_2
   4:	invokeinterface	#276,  2; //InterfaceMethod scala/collection/generic/BufferTemplate.$plus$plus$colon:(Lscala/collection/Traversable;)Lscala/collection/generic/BufferTemplate;
   9:	pop
   10:	return
  LineNumberTable: 
   line 160: 0

  LocalVariableTable: 
   Start  Length  Slot  Name   Signature
   0      11      0    $this       Lscala/collection/generic/BufferTemplate;
   0      11      1    iter       Lscala/collection/Traversable;


public static void prepend(scala.collection.generic.BufferTemplate, scala.collection.Sequence);
  Code:
   Stack=2, Locals=3, Args_size=2
   0:	aload_1
   1:	astore_2
   2:	aload_0
   3:	aload_2
   4:	invokeinterface	#276,  2; //InterfaceMethod scala/collection/generic/BufferTemplate.$plus$plus$colon:(Lscala/collection/Traversable;)Lscala/collection/generic/BufferTemplate;
   9:	pop
   10:	return
  LineNumberTable: 
   line 152: 0

  LocalVariableTable: 
   Start  Length  Slot  Name   Signature
   0      11      0    $this       Lscala/collection/generic/BufferTemplate;
   0      11      1    elems       Lscala/collection/Sequence;


public static void appendAll(scala.collection.generic.BufferTemplate, scala.collection.Traversable);
  Code:
   Stack=2, Locals=2, Args_size=2
   0:	aload_0
   1:	aload_1
   2:	invokeinterface	#76,  2; //InterfaceMethod scala/collection/generic/Growable.$plus$plus$eq:(Lscala/collection/Traversable;)Lscala/collection/generic/Growable;
   7:	pop
   8:	return
  LineNumberTable: 
   line 146: 0

  LocalVariableTable: 
   Start  Length  Slot  Name   Signature
   0      9      0    $this       Lscala/collection/generic/BufferTemplate;
   0      9      1    iter       Lscala/collection/Traversable;


public static void append(scala.collection.generic.BufferTemplate, scala.collection.Sequence);
  Code:
   Stack=2, Locals=2, Args_size=2
   0:	aload_0
   1:	aload_1
   2:	invokeinterface	#76,  2; //InterfaceMethod scala/collection/generic/Growable.$plus$plus$eq:(Lscala/collection/Traversable;)Lscala/collection/generic/Growable;
   7:	pop
   8:	return
  LineNumberTable: 
   line 139: 0

  LocalVariableTable: 
   Start  Length  Slot  Name   Signature
   0      9      0    $this       Lscala/collection/generic/BufferTemplate;
   0      9      1    elems       Lscala/collection/Sequence;


public static scala.collection.generic.BufferTemplate $plus$plus$colon(scala.collection.generic.BufferTemplate, scala.collection.Iterator);
  Code:
   Stack=4, Locals=2, Args_size=2
   0:	aload_1
   1:	new	#280; //class scala/collection/generic/BufferTemplate$$anonfun$$plus$plus$colon$2
   4:	dup
   5:	aload_0
   6:	invokespecial	#281; //Method scala/collection/generic/BufferTemplate$$anonfun$$plus$plus$colon$2."<init>":(Lscala/collection/generic/BufferTemplate;)V
   9:	invokeinterface	#22,  2; //InterfaceMethod scala/collection/Iterator.foreach:(Lscala/Function1;)V
   14:	aload_0
   15:	invokeinterface	#28,  1; //InterfaceMethod scala/collection/generic/TraversableTemplate.thisCollection:()Lscala/collection/generic/TraversableTemplate;
   20:	checkcast	#30; //class scala/collection/generic/BufferTemplate
   23:	areturn
  LineNumberTable: 
   line 133: 0

  LocalVariableTable: 
   Start  Length  Slot  Name   Signature
   0      24      0    $this       Lscala/collection/generic/BufferTemplate;
   0      24      1    iter       Lscala/collection/Iterator;


public static scala.collection.generic.BufferTemplate $plus$plus$colon(scala.collection.generic.BufferTemplate, scala.collection.Traversable);
  Code:
   Stack=4, Locals=2, Args_size=2
   0:	aload_1
   1:	new	#283; //class scala/collection/generic/BufferTemplate$$anonfun$$plus$plus$colon$1
   4:	dup
   5:	aload_0
   6:	invokespecial	#284; //Method scala/collection/generic/BufferTemplate$$anonfun$$plus$plus$colon$1."<init>":(Lscala/collection/generic/BufferTemplate;)V
   9:	invokeinterface	#39,  2; //InterfaceMethod scala/collection/generic/TraversableClass.foreach:(Lscala/Function1;)V
   14:	aload_0
   15:	invokeinterface	#28,  1; //InterfaceMethod scala/collection/generic/TraversableTemplate.thisCollection:()Lscala/collection/generic/TraversableTemplate;
   20:	checkcast	#30; //class scala/collection/generic/BufferTemplate
   23:	areturn
  LineNumberTable: 
   line 125: 0

  LocalVariableTable: 
   Start  Length  Slot  Name   Signature
   0      24      0    $this       Lscala/collection/generic/BufferTemplate;
   0      24      1    iter       Lscala/collection/Traversable;


public static scala.collection.generic.BufferTemplate $minus$eq(scala.collection.generic.BufferTemplate, java.lang.Object);
  Code:
   Stack=2, Locals=3, Args_size=2
   0:	aload_0
   1:	aload_1
   2:	invokeinterface	#290,  2; //InterfaceMethod scala/collection/generic/SequenceTemplate.indexOf:(Ljava/lang/Object;)I
   7:	istore_2
   8:	iload_2
   9:	iconst_m1
   10:	if_icmpeq	23
   13:	aload_0
   14:	iload_2
   15:	invokeinterface	#198,  2; //InterfaceMethod scala/collection/generic/BufferTemplate.remove:(I)Ljava/lang/Object;
   20:	goto	26
   23:	getstatic	#296; //Field scala/runtime/BoxedUnit.UNIT:Lscala/runtime/BoxedUnit;
   26:	pop
   27:	aload_0
   28:	areturn
  LineNumberTable: 
   line 114: 0
   line 115: 8
   line 116: 27

  LocalVariableTable: 
   Start  Length  Slot  Name   Signature
   0      29      0    $this       Lscala/collection/generic/BufferTemplate;
   0      29      1    x       Ljava/lang/Object;
   8      20      2    i       I


public static void remove(scala.collection.generic.BufferTemplate, int, int);
  Code:
   Stack=5, Locals=3, Args_size=3
   0:	getstatic	#247; //Field scala/Predef$.MODULE$:Lscala/Predef$;
   3:	iconst_0
   4:	invokevirtual	#251; //Method scala/Predef$.intWrapper:(I)Lscala/runtime/RichInt;
   7:	iload_2
   8:	invokevirtual	#301; //Method scala/runtime/RichInt.until:(I)Lscala/Range;
   11:	new	#303; //class scala/collection/generic/BufferTemplate$$anonfun$remove$1
   14:	dup
   15:	aload_0
   16:	iload_1
   17:	invokespecial	#305; //Method scala/collection/generic/BufferTemplate$$anonfun$remove$1."<init>":(Lscala/collection/generic/BufferTemplate;I)V
   20:	invokevirtual	#308; //Method scala/Range.foreach:(Lscala/Function1;)V
   23:	return
  LineNumberTable: 
   line 105: 0

  LocalVariableTable: 
   Start  Length  Slot  Name   Signature
   0      24      0    $this       Lscala/collection/generic/BufferTemplate;
   0      24      1    n$1       I
   0      24      2    count       I


}

