Compiled from "Builder.scala"
public abstract class scala.collection.generic.Builder$class extends java.lang.Object
  SourceFile: "Builder.scala"
  Scala: length = 0x
   
  InnerClass: 
   public final #28= #13 of #27; //$anon$1=class scala/collection/generic/Builder$$anon$1 of class scala/collection/generic/Builder
  minor version: 0
  major version: 49
  Constant pool:
const #1 = Asciz	SourceFile;
const #2 = Asciz	Builder.scala;
const #3 = Asciz	$init$;
const #4 = Asciz	(Lscala/collection/generic/Builder;)V;
const #5 = Asciz	Code;
const #6 = Asciz	LineNumberTable;
const #7 = Asciz	$this;
const #8 = Asciz	Lscala/collection/generic/Builder;;
const #9 = Asciz	LocalVariableTable;
const #10 = Asciz	mapResult;
const #11 = Asciz	(Lscala/collection/generic/Builder;Lscala/Function1;)Lscala/collection/generic/Builder;;
const #12 = Asciz	scala/collection/generic/Builder$$anon$1;
const #13 = class	#12;	//  scala/collection/generic/Builder$$anon$1
const #14 = Asciz	<init>;
const #15 = Asciz	(Lscala/collection/generic/Builder;Lscala/Function1;)V;
const #16 = NameAndType	#14:#15;//  "<init>":(Lscala/collection/generic/Builder;Lscala/Function1;)V
const #17 = Method	#13.#16;	//  scala/collection/generic/Builder$$anon$1."<init>":(Lscala/collection/generic/Builder;Lscala/Function1;)V
const #18 = Asciz	f$1;
const #19 = Asciz	Lscala/Function1;;
const #20 = Asciz	sizeHint;
const #21 = Asciz	(Lscala/collection/generic/Builder;I)V;
const #22 = Asciz	size;
const #23 = Asciz	I;
const #24 = Asciz	Scala;
const #25 = Asciz	InnerClasses;
const #26 = Asciz	scala/collection/generic/Builder;
const #27 = class	#26;	//  scala/collection/generic/Builder
const #28 = Asciz	$anon$1;
const #29 = Asciz	scala/collection/generic/Builder$class;
const #30 = class	#29;	//  scala/collection/generic/Builder$class
const #31 = Asciz	java/lang/Object;
const #32 = class	#31;	//  java/lang/Object

{
public static void $init$(scala.collection.generic.Builder);
  Code:
   Stack=0, Locals=1, Args_size=1
   0:	return
  LineNumberTable: 
   line 19: 0

  LocalVariableTable: 
   Start  Length  Slot  Name   Signature
   0      1      0    $this       Lscala/collection/generic/Builder;


public static scala.collection.generic.Builder mapResult(scala.collection.generic.Builder, scala.Function1);
  Code:
   Stack=4, Locals=2, Args_size=2
   0:	new	#13; //class scala/collection/generic/Builder$$anon$1
   3:	dup
   4:	aload_0
   5:	aload_1
   6:	invokespecial	#17; //Method scala/collection/generic/Builder$$anon$1."<init>":(Lscala/collection/generic/Builder;Lscala/Function1;)V
   9:	areturn
  LineNumberTable: 
   line 45: 0

  LocalVariableTable: 
   Start  Length  Slot  Name   Signature
   0      10      0    $this       Lscala/collection/generic/Builder;
   0      10      1    f$1       Lscala/Function1;


public static void sizeHint(scala.collection.generic.Builder, int);
  Code:
   Stack=0, Locals=2, Args_size=2
   0:	return
  LineNumberTable: 
   line 38: 0

  LocalVariableTable: 
   Start  Length  Slot  Name   Signature
   0      1      0    $this       Lscala/collection/generic/Builder;
   0      1      1    size       I


}

