Compiled from "Builder.scala"
public final class scala.collection.generic.Builder$$anon$1 extends java.lang.Object implements scala.collection.generic.Builder,scala.Proxy
  SourceFile: "Builder.scala"
  Signature: length = 0x2
   00 FFFFFF87 
  Scala: length = 0x
   
  InnerClass: 
   public final #138= #14 of #71; //$anon$1=class scala/collection/generic/Builder$$anon$1 of class scala/collection/generic/Builder
  minor version: 0
  major version: 49
  Constant pool:
const #1 = Asciz	SourceFile;
const #2 = Asciz	Builder.scala;
const #3 = Asciz	f$1;
const #4 = Asciz	Lscala/Function1;;
const #5 = Asciz	self;
const #6 = Asciz	Lscala/collection/generic/Builder;;
const #7 = Asciz	Lscala/collection/generic/Builder<TElem;TTo;>;;
const #8 = Asciz	Signature;
const #9 = Asciz	<init>;
const #10 = Asciz	(Lscala/collection/generic/Builder;Lscala/Function1;)V;
const #11 = Asciz	Code;
const #12 = Asciz	LineNumberTable;
const #13 = Asciz	scala/collection/generic/Builder$$anon$1;
const #14 = class	#13;	//  scala/collection/generic/Builder$$anon$1
const #15 = NameAndType	#3:#4;//  f$1:Lscala/Function1;
const #16 = Field	#14.#15;	//  scala/collection/generic/Builder$$anon$1.f$1:Lscala/Function1;
const #17 = Asciz	java/lang/Object;
const #18 = class	#17;	//  java/lang/Object
const #19 = Asciz	()V;
const #20 = NameAndType	#9:#19;//  "<init>":()V
const #21 = Method	#18.#20;	//  java/lang/Object."<init>":()V
const #22 = Asciz	scala/collection/generic/Growable$class;
const #23 = class	#22;	//  scala/collection/generic/Growable$class
const #24 = Asciz	$init$;
const #25 = Asciz	(Lscala/collection/generic/Growable;)V;
const #26 = NameAndType	#24:#25;//  $init$:(Lscala/collection/generic/Growable;)V
const #27 = Method	#23.#26;	//  scala/collection/generic/Growable$class.$init$:(Lscala/collection/generic/Growable;)V
const #28 = Asciz	scala/collection/generic/Builder$class;
const #29 = class	#28;	//  scala/collection/generic/Builder$class
const #30 = Asciz	(Lscala/collection/generic/Builder;)V;
const #31 = NameAndType	#24:#30;//  $init$:(Lscala/collection/generic/Builder;)V
const #32 = Method	#29.#31;	//  scala/collection/generic/Builder$class.$init$:(Lscala/collection/generic/Builder;)V
const #33 = Asciz	scala/Proxy$class;
const #34 = class	#33;	//  scala/Proxy$class
const #35 = Asciz	(Lscala/Proxy;)V;
const #36 = NameAndType	#24:#35;//  $init$:(Lscala/Proxy;)V
const #37 = Method	#34.#36;	//  scala/Proxy$class.$init$:(Lscala/Proxy;)V
const #38 = NameAndType	#5:#6;//  self:Lscala/collection/generic/Builder;
const #39 = Field	#14.#38;	//  scala/collection/generic/Builder$$anon$1.self:Lscala/collection/generic/Builder;
const #40 = Asciz	this;
const #41 = Asciz	Lscala/collection/generic/Builder$$anon$1;;
const #42 = Asciz	$outer;
const #43 = Asciz	LocalVariableTable;
const #44 = Asciz	(Lscala/collection/generic/Builder<TElem;TTo;>;)V;
const #45 = Asciz	()Ljava/lang/Object;;
const #46 = Asciz	()Lscala/collection/generic/Builder;;
const #47 = NameAndType	#5:#46;//  self:()Lscala/collection/generic/Builder;
const #48 = Method	#14.#47;	//  scala/collection/generic/Builder$$anon$1.self:()Lscala/collection/generic/Builder;
const #49 = Asciz	$plus$eq;
const #50 = Asciz	(Ljava/lang/Object;)Lscala/collection/generic/Builder;;
const #51 = Asciz	(Ljava/lang/Object;)Lscala/collection/generic/Builder$$anon$1;;
const #52 = NameAndType	#49:#51;//  $plus$eq:(Ljava/lang/Object;)Lscala/collection/generic/Builder$$anon$1;
const #53 = Method	#14.#52;	//  scala/collection/generic/Builder$$anon$1.$plus$eq:(Ljava/lang/Object;)Lscala/collection/generic/Builder$$anon$1;
const #54 = Asciz	elem;
const #55 = Asciz	Ljava/lang/Object;;
const #56 = Asciz	(Ljava/lang/Object;)Lscala/collection/generic/Growable;;
const #57 = Asciz	$plus$plus$eq;
const #58 = Asciz	(Lscala/collection/Iterator;)Lscala/collection/generic/Growable;;
const #59 = Asciz	(Lscala/collection/Iterator;)Lscala/collection/generic/Builder$$anon$1;;
const #60 = NameAndType	#57:#59;//  $plus$plus$eq:(Lscala/collection/Iterator;)Lscala/collection/generic/Builder$$anon$1;
const #61 = Method	#14.#60;	//  scala/collection/generic/Builder$$anon$1.$plus$plus$eq:(Lscala/collection/Iterator;)Lscala/collection/generic/Builder$$anon$1;
const #62 = Asciz	iter;
const #63 = Asciz	Lscala/collection/Iterator;;
const #64 = Asciz	(Lscala/collection/Traversable;)Lscala/collection/generic/Growable;;
const #65 = Asciz	(Lscala/collection/Traversable;)Lscala/collection/generic/Builder$$anon$1;;
const #66 = NameAndType	#57:#65;//  $plus$plus$eq:(Lscala/collection/Traversable;)Lscala/collection/generic/Builder$$anon$1;
const #67 = Method	#14.#66;	//  scala/collection/generic/Builder$$anon$1.$plus$plus$eq:(Lscala/collection/Traversable;)Lscala/collection/generic/Builder$$anon$1;
const #68 = Asciz	Lscala/collection/Traversable;;
const #69 = Asciz	result;
const #70 = Asciz	scala/collection/generic/Builder;
const #71 = class	#70;	//  scala/collection/generic/Builder
const #72 = NameAndType	#69:#45;//  result:()Ljava/lang/Object;
const #73 = InterfaceMethod	#71.#72;	//  scala/collection/generic/Builder.result:()Ljava/lang/Object;
const #74 = Asciz	scala/Function1;
const #75 = class	#74;	//  scala/Function1
const #76 = Asciz	apply;
const #77 = Asciz	(Ljava/lang/Object;)Ljava/lang/Object;;
const #78 = NameAndType	#76:#77;//  apply:(Ljava/lang/Object;)Ljava/lang/Object;
const #79 = InterfaceMethod	#75.#78;	//  scala/Function1.apply:(Ljava/lang/Object;)Ljava/lang/Object;
const #80 = Asciz	()TNewTo;;
const #81 = Asciz	scala/collection/generic/Growable;
const #82 = class	#81;	//  scala/collection/generic/Growable
const #83 = NameAndType	#57:#64;//  $plus$plus$eq:(Lscala/collection/Traversable;)Lscala/collection/generic/Growable;
const #84 = InterfaceMethod	#82.#83;	//  scala/collection/generic/Growable.$plus$plus$eq:(Lscala/collection/Traversable;)Lscala/collection/generic/Growable;
const #85 = Asciz	xs;
const #86 = Asciz	(Lscala/collection/Traversable<TElem;>;)Lscala/collection/generic/Builder<TElem;TTo;>.$anon$1;;
const #87 = NameAndType	#57:#58;//  $plus$plus$eq:(Lscala/collection/Iterator;)Lscala/collection/generic/Growable;
const #88 = InterfaceMethod	#82.#87;	//  scala/collection/generic/Growable.$plus$plus$eq:(Lscala/collection/Iterator;)Lscala/collection/generic/Growable;
const #89 = Asciz	(Lscala/collection/Iterator<TElem;>;)Lscala/collection/generic/Builder<TElem;TTo;>.$anon$1;;
const #90 = Asciz	clear;
const #91 = NameAndType	#90:#19;//  clear:()V
const #92 = InterfaceMethod	#71.#91;	//  scala/collection/generic/Builder.clear:()V
const #93 = NameAndType	#49:#50;//  $plus$eq:(Ljava/lang/Object;)Lscala/collection/generic/Builder;
const #94 = InterfaceMethod	#71.#93;	//  scala/collection/generic/Builder.$plus$eq:(Ljava/lang/Object;)Lscala/collection/generic/Builder;
const #95 = Asciz	x;
const #96 = Asciz	(TElem;)Lscala/collection/generic/Builder<TElem;TTo;>.$anon$1;;
const #97 = Asciz	()Lscala/collection/generic/Builder<TElem;TTo;>;;
const #98 = Asciz	(Ljava/lang/Object;Ljava/lang/Object;Lscala/collection/Sequence;)Lscala/collection/generic/Growable;;
const #99 = Asciz	(Lscala/collection/generic/Growable;Ljava/lang/Object;Ljava/lang/Object;Lscala/collection/Sequence;)Lscala/collection/generic/Growable;;
const #100 = NameAndType	#49:#99;//  $plus$eq:(Lscala/collection/generic/Growable;Ljava/lang/Object;Ljava/lang/Object;Lscala/collection/Sequence;)Lscala/collection/generic/Growable;
const #101 = Method	#23.#100;	//  scala/collection/generic/Growable$class.$plus$eq:(Lscala/collection/generic/Growable;Ljava/lang/Object;Ljava/lang/Object;Lscala/collection/Sequence;)Lscala/collection/generic/Growable;
const #102 = Asciz	elem1;
const #103 = Asciz	elem2;
const #104 = Asciz	elems;
const #105 = Asciz	Lscala/collection/Sequence;;
const #106 = Asciz	mapResult;
const #107 = Asciz	(Lscala/Function1;)Lscala/collection/generic/Builder;;
const #108 = Asciz	(Lscala/collection/generic/Builder;Lscala/Function1;)Lscala/collection/generic/Builder;;
const #109 = NameAndType	#106:#108;//  mapResult:(Lscala/collection/generic/Builder;Lscala/Function1;)Lscala/collection/generic/Builder;
const #110 = Method	#29.#109;	//  scala/collection/generic/Builder$class.mapResult:(Lscala/collection/generic/Builder;Lscala/Function1;)Lscala/collection/generic/Builder;
const #111 = Asciz	f;
const #112 = Asciz	sizeHint;
const #113 = Asciz	(I)V;
const #114 = Asciz	(Lscala/collection/generic/Builder;I)V;
const #115 = NameAndType	#112:#114;//  sizeHint:(Lscala/collection/generic/Builder;I)V
const #116 = Method	#29.#115;	//  scala/collection/generic/Builder$class.sizeHint:(Lscala/collection/generic/Builder;I)V
const #117 = Asciz	size;
const #118 = Asciz	I;
const #119 = Asciz	toString;
const #120 = Asciz	()Ljava/lang/String;;
const #121 = Asciz	(Lscala/Proxy;)Ljava/lang/String;;
const #122 = NameAndType	#119:#121;//  toString:(Lscala/Proxy;)Ljava/lang/String;
const #123 = Method	#34.#122;	//  scala/Proxy$class.toString:(Lscala/Proxy;)Ljava/lang/String;
const #124 = Asciz	equals;
const #125 = Asciz	(Ljava/lang/Object;)Z;
const #126 = Asciz	(Lscala/Proxy;Ljava/lang/Object;)Z;
const #127 = NameAndType	#124:#126;//  equals:(Lscala/Proxy;Ljava/lang/Object;)Z
const #128 = Method	#34.#127;	//  scala/Proxy$class.equals:(Lscala/Proxy;Ljava/lang/Object;)Z
const #129 = Asciz	that;
const #130 = Asciz	hashCode;
const #131 = Asciz	()I;
const #132 = Asciz	(Lscala/Proxy;)I;
const #133 = NameAndType	#130:#132;//  hashCode:(Lscala/Proxy;)I
const #134 = Method	#34.#133;	//  scala/Proxy$class.hashCode:(Lscala/Proxy;)I
const #135 = Asciz	Ljava/lang/Object;Lscala/collection/generic/Builder<TElem;TNewTo;>;Lscala/Proxy;;
const #136 = Asciz	Scala;
const #137 = Asciz	InnerClasses;
const #138 = Asciz	$anon$1;
const #139 = Asciz	scala/Proxy;
const #140 = class	#139;	//  scala/Proxy

{
public scala.collection.generic.Builder$$anon$1(scala.collection.generic.Builder, scala.Function1);
  Code:
   Stack=2, Locals=3, Args_size=3
   0:	aload_0
   1:	aload_2
   2:	putfield	#16; //Field f$1:Lscala/Function1;
   5:	aload_0
   6:	invokespecial	#21; //Method java/lang/Object."<init>":()V
   9:	aload_0
   10:	invokestatic	#27; //Method scala/collection/generic/Growable$class.$init$:(Lscala/collection/generic/Growable;)V
   13:	aload_0
   14:	invokestatic	#32; //Method scala/collection/generic/Builder$class.$init$:(Lscala/collection/generic/Builder;)V
   17:	aload_0
   18:	invokestatic	#37; //Method scala/Proxy$class.$init$:(Lscala/Proxy;)V
   21:	aload_0
   22:	aload_1
   23:	putfield	#39; //Field self:Lscala/collection/generic/Builder;
   26:	return
  LineNumberTable: 
   line 45: 0
   line 46: 21

  LocalVariableTable: 
   Start  Length  Slot  Name   Signature
   0      27      0    this       Lscala/collection/generic/Builder$$anon$1;
   0      27      1    $outer       Lscala/collection/generic/Builder;

  Signature: length = 0x2
   00 2C 

public java.lang.Object self();
  Code:
   Stack=1, Locals=1, Args_size=1
   0:	aload_0
   1:	invokevirtual	#48; //Method self:()Lscala/collection/generic/Builder;
   4:	areturn
  LineNumberTable: 
   line 45: 0


public scala.collection.generic.Builder $plus$eq(java.lang.Object);
  Code:
   Stack=2, Locals=2, Args_size=2
   0:	aload_0
   1:	aload_1
   2:	invokevirtual	#53; //Method $plus$eq:(Ljava/lang/Object;)Lscala/collection/generic/Builder$$anon$1;
   5:	areturn
  LineNumberTable: 
   line 45: 0

  LocalVariableTable: 
   Start  Length  Slot  Name   Signature
   0      6      0    this       Lscala/collection/generic/Builder$$anon$1;
   0      6      1    elem       Ljava/lang/Object;


public scala.collection.generic.Growable $plus$eq(java.lang.Object);
  Code:
   Stack=2, Locals=2, Args_size=2
   0:	aload_0
   1:	aload_1
   2:	invokevirtual	#53; //Method $plus$eq:(Ljava/lang/Object;)Lscala/collection/generic/Builder$$anon$1;
   5:	areturn
  LineNumberTable: 
   line 45: 0

  LocalVariableTable: 
   Start  Length  Slot  Name   Signature
   0      6      0    this       Lscala/collection/generic/Builder$$anon$1;
   0      6      1    elem       Ljava/lang/Object;


public scala.collection.generic.Growable $plus$plus$eq(scala.collection.Iterator);
  Code:
   Stack=2, Locals=2, Args_size=2
   0:	aload_0
   1:	aload_1
   2:	invokevirtual	#61; //Method $plus$plus$eq:(Lscala/collection/Iterator;)Lscala/collection/generic/Builder$$anon$1;
   5:	areturn
  LineNumberTable: 
   line 45: 0

  LocalVariableTable: 
   Start  Length  Slot  Name   Signature
   0      6      0    this       Lscala/collection/generic/Builder$$anon$1;
   0      6      1    iter       Lscala/collection/Iterator;


public scala.collection.generic.Growable $plus$plus$eq(scala.collection.Traversable);
  Code:
   Stack=2, Locals=2, Args_size=2
   0:	aload_0
   1:	aload_1
   2:	invokevirtual	#67; //Method $plus$plus$eq:(Lscala/collection/Traversable;)Lscala/collection/generic/Builder$$anon$1;
   5:	areturn
  LineNumberTable: 
   line 45: 0

  LocalVariableTable: 
   Start  Length  Slot  Name   Signature
   0      6      0    this       Lscala/collection/generic/Builder$$anon$1;
   0      6      1    iter       Lscala/collection/Traversable;


public java.lang.Object result();
  Code:
   Stack=2, Locals=1, Args_size=1
   0:	aload_0
   1:	getfield	#16; //Field f$1:Lscala/Function1;
   4:	aload_0
   5:	invokevirtual	#48; //Method self:()Lscala/collection/generic/Builder;
   8:	invokeinterface	#73,  1; //InterfaceMethod scala/collection/generic/Builder.result:()Ljava/lang/Object;
   13:	invokeinterface	#79,  2; //InterfaceMethod scala/Function1.apply:(Ljava/lang/Object;)Ljava/lang/Object;
   18:	areturn
  LineNumberTable: 
   line 51: 0

  Signature: length = 0x2
   00 50 

public scala.collection.generic.Builder$$anon$1 $plus$plus$eq(scala.collection.Traversable);
  Code:
   Stack=2, Locals=2, Args_size=2
   0:	aload_0
   1:	invokevirtual	#48; //Method self:()Lscala/collection/generic/Builder;
   4:	aload_1
   5:	invokeinterface	#84,  2; //InterfaceMethod scala/collection/generic/Growable.$plus$plus$eq:(Lscala/collection/Traversable;)Lscala/collection/generic/Growable;
   10:	pop
   11:	aload_0
   12:	areturn
  LineNumberTable: 
   line 50: 0

  LocalVariableTable: 
   Start  Length  Slot  Name   Signature
   0      13      0    this       Lscala/collection/generic/Builder$$anon$1;
   0      13      1    xs       Lscala/collection/Traversable;

  Signature: length = 0x2
   00 56 

public scala.collection.generic.Builder$$anon$1 $plus$plus$eq(scala.collection.Iterator);
  Code:
   Stack=2, Locals=2, Args_size=2
   0:	aload_0
   1:	invokevirtual	#48; //Method self:()Lscala/collection/generic/Builder;
   4:	aload_1
   5:	invokeinterface	#88,  2; //InterfaceMethod scala/collection/generic/Growable.$plus$plus$eq:(Lscala/collection/Iterator;)Lscala/collection/generic/Growable;
   10:	pop
   11:	aload_0
   12:	areturn
  LineNumberTable: 
   line 49: 0

  LocalVariableTable: 
   Start  Length  Slot  Name   Signature
   0      13      0    this       Lscala/collection/generic/Builder$$anon$1;
   0      13      1    xs       Lscala/collection/Iterator;

  Signature: length = 0x2
   00 59 

public void clear();
  Code:
   Stack=1, Locals=1, Args_size=1
   0:	aload_0
   1:	invokevirtual	#48; //Method self:()Lscala/collection/generic/Builder;
   4:	invokeinterface	#92,  1; //InterfaceMethod scala/collection/generic/Builder.clear:()V
   9:	return
  LineNumberTable: 
   line 48: 0


public scala.collection.generic.Builder$$anon$1 $plus$eq(java.lang.Object);
  Code:
   Stack=2, Locals=2, Args_size=2
   0:	aload_0
   1:	invokevirtual	#48; //Method self:()Lscala/collection/generic/Builder;
   4:	aload_1
   5:	invokeinterface	#94,  2; //InterfaceMethod scala/collection/generic/Builder.$plus$eq:(Ljava/lang/Object;)Lscala/collection/generic/Builder;
   10:	pop
   11:	aload_0
   12:	areturn
  LineNumberTable: 
   line 47: 0

  LocalVariableTable: 
   Start  Length  Slot  Name   Signature
   0      13      0    this       Lscala/collection/generic/Builder$$anon$1;
   0      13      1    x       Ljava/lang/Object;

  Signature: length = 0x2
   00 60 

public scala.collection.generic.Builder self();
  Code:
   Stack=1, Locals=1, Args_size=1
   0:	aload_0
   1:	getfield	#39; //Field self:Lscala/collection/generic/Builder;
   4:	areturn
  LineNumberTable: 
   line 46: 0

  Signature: length = 0x2
   00 61 

public scala.collection.generic.Growable $plus$eq(java.lang.Object, java.lang.Object, scala.collection.Sequence);
  Code:
   Stack=4, Locals=4, Args_size=4
   0:	aload_0
   1:	aload_1
   2:	aload_2
   3:	aload_3
   4:	invokestatic	#101; //Method scala/collection/generic/Growable$class.$plus$eq:(Lscala/collection/generic/Growable;Ljava/lang/Object;Ljava/lang/Object;Lscala/collection/Sequence;)Lscala/collection/generic/Growable;
   7:	areturn
  LineNumberTable: 
   line 45: 0

  LocalVariableTable: 
   Start  Length  Slot  Name   Signature
   0      8      0    this       Lscala/collection/generic/Builder$$anon$1;
   0      8      1    elem1       Ljava/lang/Object;
   0      8      2    elem2       Ljava/lang/Object;
   0      8      3    elems       Lscala/collection/Sequence;


public scala.collection.generic.Builder mapResult(scala.Function1);
  Code:
   Stack=2, Locals=2, Args_size=2
   0:	aload_0
   1:	aload_1
   2:	invokestatic	#110; //Method scala/collection/generic/Builder$class.mapResult:(Lscala/collection/generic/Builder;Lscala/Function1;)Lscala/collection/generic/Builder;
   5:	areturn
  LineNumberTable: 
   line 45: 0

  LocalVariableTable: 
   Start  Length  Slot  Name   Signature
   0      6      0    this       Lscala/collection/generic/Builder$$anon$1;
   0      6      1    f       Lscala/Function1;


public void sizeHint(int);
  Code:
   Stack=2, Locals=2, Args_size=2
   0:	aload_0
   1:	iload_1
   2:	invokestatic	#116; //Method scala/collection/generic/Builder$class.sizeHint:(Lscala/collection/generic/Builder;I)V
   5:	return
  LineNumberTable: 
   line 45: 0

  LocalVariableTable: 
   Start  Length  Slot  Name   Signature
   0      6      0    this       Lscala/collection/generic/Builder$$anon$1;
   0      6      1    size       I


public java.lang.String toString();
  Code:
   Stack=1, Locals=1, Args_size=1
   0:	aload_0
   1:	invokestatic	#123; //Method scala/Proxy$class.toString:(Lscala/Proxy;)Ljava/lang/String;
   4:	areturn
  LineNumberTable: 
   line 45: 0


public boolean equals(java.lang.Object);
  Code:
   Stack=2, Locals=2, Args_size=2
   0:	aload_0
   1:	aload_1
   2:	invokestatic	#128; //Method scala/Proxy$class.equals:(Lscala/Proxy;Ljava/lang/Object;)Z
   5:	ireturn
  LineNumberTable: 
   line 45: 0

  LocalVariableTable: 
   Start  Length  Slot  Name   Signature
   0      6      0    this       Lscala/collection/generic/Builder$$anon$1;
   0      6      1    that       Ljava/lang/Object;


public int hashCode();
  Code:
   Stack=1, Locals=1, Args_size=1
   0:	aload_0
   1:	invokestatic	#134; //Method scala/Proxy$class.hashCode:(Lscala/Proxy;)I
   4:	ireturn
  LineNumberTable: 
   line 45: 0


}

