Compiled from "Companion.scala"
public abstract class scala.collection.generic.Companion extends java.lang.Object implements scala.ScalaObject
  SourceFile: "Companion.scala"
  Signature: length = 0x2
   00 38 
  ScalaSig: length = 0x1E1
   05 00 53 06 05 01 02 FFFFFF81 00 09 02 09 43 6F 6D 70
   61 6E 69 6F 6E 0A 02 03 04 01 07 67 65 6E 65 72
   69 63 0A 02 05 06 01 0A 63 6F 6C 6C 65 63 74 69
   6F 6E 0A 01 07 01 05 73 63 61 6C 61 03 00 15 02
   0A 1E 13 03 00 0B 13 10 02 0C 11 0D 01 0D 0A 02
   0E 0F 01 04 6C 61 6E 67 0A 01 10 01 04 6A 61 76
   61 09 02 12 0D 02 06 4F 62 6A 65 63 74 10 02 14
   15 0D 01 06 09 02 16 06 02 0B 53 63 61 6C 61 4F
   62 6A 65 63 74 08 05 18 00 FFFFFF84 00 19 01 06 3C 69
   6E 69 74 3E 14 01 1A 10 03 1B 00 1C 0D 01 02 10
   02 1D 1E 0C 00 04 06 1F 00 FFFFFF84 FFFFFFC2 00 20 02 02 43
   43 15 02 21 2A 11 02 22 25 10 02 14 23 09 02 24
   06 02 07 4E 6F 74 68 69 6E 67 10 03 26 27 29 0D
   01 04 09 02 28 04 02 0B 54 72 61 76 65 72 73 61
   62 6C 65 10 02 1D 2A 04 08 2B 1E FFFFFF84 FFFFFF80 FFFFFF80 FFFFFFC2 00
   2C 02 01 58 11 02 22 2D 10 02 14 2E 09 02 2F 06
   02 03 41 6E 79 05 08 31 00 FFFFFF84 FFFFFF80 FFFFFF80 FFFFFF80 00 32 02
   04 43 6F 6C 6C 30 02 33 35 10 03 1D 1E 34 10 02
   1D 35 04 08 36 00 FFFFFF84 FFFFFF80 FFFFFF80 FFFFFF82 00 2C 02 03 5F 24
   31 08 05 38 00 FFFFFF86 00 39 01 0A 6E 65 77 42 75 69
   6C 64 65 72 15 02 3A 3E 10 04 1B 3B 3D 40 09 02
   3C 02 02 07 42 75 69 6C 64 65 72 10 02 1D 3E 04
   08 3F 37 FFFFFF84 FFFFFF80 FFFFFF80 FFFFFFC2 00 2C 02 01 41 10 03 1D 1E
   3D 08 05 42 00 FFFFFF84 00 43 01 05 65 6D 70 74 79 15
   02 44 46 10 03 1D 1E 45 10 02 1D 46 04 08 3F 41
   FFFFFF84 FFFFFF80 FFFFFF80 FFFFFFC2 00 2C 08 05 48 00 FFFFFF84 00 49 01 05 61
   70 70 6C 79 15 02 4A 4D 14 02 4B 4E 10 03 1D 1E
   4C 10 02 1D 4D 04 08 3F 47 FFFFFF84 FFFFFF80 FFFFFF80 FFFFFFC2 00 2C 08
   05 4F 47 FFFFFFC0 00 50 01 04 61 72 67 73 10 03 14 51
   4C 09 02 52 06 02 0A 3C 72 65 70 65 61 74 65 64
   3E 
  minor version: 0
  major version: 49
  Constant pool:
const #1 = Asciz	SourceFile;
const #2 = Asciz	Companion.scala;
const #3 = Asciz	<init>;
const #4 = Asciz	()V;
const #5 = Asciz	Code;
const #6 = Asciz	LineNumberTable;
const #7 = Asciz	java/lang/Object;
const #8 = class	#7;	//  java/lang/Object
const #9 = NameAndType	#3:#4;//  "<init>":()V
const #10 = Method	#8.#9;	//  java/lang/Object."<init>":()V
const #11 = Asciz	Signature;
const #12 = Asciz	apply;
const #13 = Asciz	(Lscala/collection/Sequence;)Lscala/collection/Traversable;;
const #14 = Asciz	scala/collection/generic/Companion;
const #15 = class	#14;	//  scala/collection/generic/Companion
const #16 = Asciz	newBuilder;
const #17 = Asciz	()Lscala/collection/generic/Builder;;
const #18 = NameAndType	#16:#17;//  newBuilder:()Lscala/collection/generic/Builder;
const #19 = Method	#15.#18;	//  scala/collection/generic/Companion.newBuilder:()Lscala/collection/generic/Builder;
const #20 = Asciz	scala/collection/generic/Growable;
const #21 = class	#20;	//  scala/collection/generic/Growable
const #22 = Asciz	$plus$plus$eq;
const #23 = Asciz	(Lscala/collection/Traversable;)Lscala/collection/generic/Growable;;
const #24 = NameAndType	#22:#23;//  $plus$plus$eq:(Lscala/collection/Traversable;)Lscala/collection/generic/Growable;
const #25 = InterfaceMethod	#21.#24;	//  scala/collection/generic/Growable.$plus$plus$eq:(Lscala/collection/Traversable;)Lscala/collection/generic/Growable;
const #26 = Asciz	scala/collection/generic/Builder;
const #27 = class	#26;	//  scala/collection/generic/Builder
const #28 = Asciz	result;
const #29 = Asciz	()Ljava/lang/Object;;
const #30 = NameAndType	#28:#29;//  result:()Ljava/lang/Object;
const #31 = InterfaceMethod	#27.#30;	//  scala/collection/generic/Builder.result:()Ljava/lang/Object;
const #32 = Asciz	scala/collection/Traversable;
const #33 = class	#32;	//  scala/collection/Traversable
const #34 = Asciz	scala/runtime/ScalaRunTime$;
const #35 = class	#34;	//  scala/runtime/ScalaRunTime$
const #36 = Asciz	MODULE$;
const #37 = Asciz	Lscala/runtime/ScalaRunTime$;;
const #38 = NameAndType	#36:#37;//  MODULE$:Lscala/runtime/ScalaRunTime$;
const #39 = Field	#35.#38;	//  scala/runtime/ScalaRunTime$.MODULE$:Lscala/runtime/ScalaRunTime$;
const #40 = Asciz	boxArray;
const #41 = Asciz	(Ljava/lang/Object;)Lscala/runtime/BoxedArray;;
const #42 = NameAndType	#40:#41;//  boxArray:(Ljava/lang/Object;)Lscala/runtime/BoxedArray;
const #43 = Method	#35.#42;	//  scala/runtime/ScalaRunTime$.boxArray:(Ljava/lang/Object;)Lscala/runtime/BoxedArray;
const #44 = Asciz	this;
const #45 = Asciz	Lscala/collection/generic/Companion;;
const #46 = Asciz	args;
const #47 = Asciz	Lscala/collection/Sequence;;
const #48 = Asciz	b;
const #49 = Asciz	Lscala/collection/generic/Builder;;
const #50 = Asciz	LocalVariableTable;
const #51 = Asciz	<A:Ljava/lang/Object;>(Lscala/collection/Sequence<TA;>;)TCC;;
const #52 = Asciz	empty;
const #53 = Asciz	()Lscala/collection/Traversable;;
const #54 = Asciz	<A:Ljava/lang/Object;>()TCC;;
const #55 = Asciz	<A:Ljava/lang/Object;>()Lscala/collection/generic/Builder<TA;TCC;>;;
const #56 = Asciz	<CC::Lscala/collection/Traversable<Ljava/lang/Object;>;>Ljava/lang/Object;Lscala/ScalaObject;;
const #57 = Asciz	ScalaSig;
const #58 = Asciz	scala/ScalaObject;
const #59 = class	#58;	//  scala/ScalaObject

{
public scala.collection.generic.Companion();
  Code:
   Stack=1, Locals=1, Args_size=1
   0:	aload_0
   1:	invokespecial	#10; //Method java/lang/Object."<init>":()V
   4:	return
  LineNumberTable: 
   line 17: 0

  Signature: length = 0x2
   00 04 

public scala.collection.Traversable apply(scala.collection.Sequence);
  Code:
   Stack=2, Locals=4, Args_size=2
   0:	aload_0
   1:	invokevirtual	#19; //Method newBuilder:()Lscala/collection/generic/Builder;
   4:	astore_2
   5:	aload_2
   6:	aload_1
   7:	invokeinterface	#25,  2; //InterfaceMethod scala/collection/generic/Growable.$plus$plus$eq:(Lscala/collection/Traversable;)Lscala/collection/generic/Growable;
   12:	pop
   13:	aload_2
   14:	invokeinterface	#31,  1; //InterfaceMethod scala/collection/generic/Builder.result:()Ljava/lang/Object;
   19:	astore_3
   20:	aload_3
   21:	instanceof	#33; //class scala/collection/Traversable
   24:	ifeq	31
   27:	aload_3
   28:	goto	38
   31:	getstatic	#39; //Field scala/runtime/ScalaRunTime$.MODULE$:Lscala/runtime/ScalaRunTime$;
   34:	aload_3
   35:	invokevirtual	#43; //Method scala/runtime/ScalaRunTime$.boxArray:(Ljava/lang/Object;)Lscala/runtime/BoxedArray;
   38:	checkcast	#33; //class scala/collection/Traversable
   41:	areturn
  LineNumberTable: 
   line 27: 0
   line 28: 5
   line 29: 13

  LocalVariableTable: 
   Start  Length  Slot  Name   Signature
   0      42      0    this       Lscala/collection/generic/Companion;
   0      42      1    args       Lscala/collection/Sequence;
   5      36      2    b       Lscala/collection/generic/Builder;

  Signature: length = 0x2
   00 33 

public scala.collection.Traversable empty();
  Code:
   Stack=2, Locals=2, Args_size=1
   0:	aload_0
   1:	invokevirtual	#19; //Method newBuilder:()Lscala/collection/generic/Builder;
   4:	invokeinterface	#31,  1; //InterfaceMethod scala/collection/generic/Builder.result:()Ljava/lang/Object;
   9:	astore_1
   10:	aload_1
   11:	instanceof	#33; //class scala/collection/Traversable
   14:	ifeq	21
   17:	aload_1
   18:	goto	28
   21:	getstatic	#39; //Field scala/runtime/ScalaRunTime$.MODULE$:Lscala/runtime/ScalaRunTime$;
   24:	aload_1
   25:	invokevirtual	#43; //Method scala/runtime/ScalaRunTime$.boxArray:(Ljava/lang/Object;)Lscala/runtime/BoxedArray;
   28:	checkcast	#33; //class scala/collection/Traversable
   31:	areturn
  LineNumberTable: 
   line 23: 0

  Signature: length = 0x2
   00 36 

public abstract scala.collection.generic.Builder newBuilder();
  Signature: length = 0x2
   00 37 

}

