Compiled from "DoubleLinkedListTemplate.scala"
public abstract class scala.collection.generic.DoubleLinkedListTemplate$class extends java.lang.Object
  SourceFile: "DoubleLinkedListTemplate.scala"
  Scala: length = 0x
   
  minor version: 0
  major version: 49
  Constant pool:
const #1 = Asciz	SourceFile;
const #2 = Asciz	DoubleLinkedListTemplate.scala;
const #3 = Asciz	$init$;
const #4 = Asciz	(Lscala/collection/generic/DoubleLinkedListTemplate;)V;
const #5 = Asciz	Code;
const #6 = Asciz	LineNumberTable;
const #7 = Asciz	$this;
const #8 = Asciz	Lscala/collection/generic/DoubleLinkedListTemplate;;
const #9 = Asciz	LocalVariableTable;
const #10 = Asciz	remove;
const #11 = Asciz	scala/collection/generic/LinkedListTemplate;
const #12 = class	#11;	//  scala/collection/generic/LinkedListTemplate
const #13 = Asciz	next;
const #14 = Asciz	()Lscala/collection/Sequence;;
const #15 = NameAndType	#13:#14;//  next:()Lscala/collection/Sequence;
const #16 = InterfaceMethod	#12.#15;	//  scala/collection/generic/LinkedListTemplate.next:()Lscala/collection/Sequence;
const #17 = Asciz	scala/collection/generic/DoubleLinkedListTemplate;
const #18 = class	#17;	//  scala/collection/generic/DoubleLinkedListTemplate
const #19 = Asciz	prev;
const #20 = Asciz	()Lscala/collection/LinearSequence;;
const #21 = NameAndType	#19:#20;//  prev:()Lscala/collection/LinearSequence;
const #22 = InterfaceMethod	#18.#21;	//  scala/collection/generic/DoubleLinkedListTemplate.prev:()Lscala/collection/LinearSequence;
const #23 = Asciz	prev_$eq;
const #24 = Asciz	(Lscala/collection/LinearSequence;)V;
const #25 = NameAndType	#23:#24;//  prev_$eq:(Lscala/collection/LinearSequence;)V
const #26 = InterfaceMethod	#18.#25;	//  scala/collection/generic/DoubleLinkedListTemplate.prev_$eq:(Lscala/collection/LinearSequence;)V
const #27 = Asciz	next_$eq;
const #28 = Asciz	(Lscala/collection/Sequence;)V;
const #29 = NameAndType	#27:#28;//  next_$eq:(Lscala/collection/Sequence;)V
const #30 = InterfaceMethod	#12.#29;	//  scala/collection/generic/LinkedListTemplate.next_$eq:(Lscala/collection/Sequence;)V
const #31 = Asciz	insert;
const #32 = Asciz	(Lscala/collection/generic/DoubleLinkedListTemplate;Lscala/collection/LinearSequence;)V;
const #33 = Asciz	scala/collection/LinearSequence;
const #34 = class	#33;	//  scala/collection/LinearSequence
const #35 = Asciz	append;
const #36 = NameAndType	#35:#24;//  append:(Lscala/collection/LinearSequence;)V
const #37 = InterfaceMethod	#18.#36;	//  scala/collection/generic/DoubleLinkedListTemplate.append:(Lscala/collection/LinearSequence;)V
const #38 = Asciz	scala/collection/generic/TraversableTemplate;
const #39 = class	#38;	//  scala/collection/generic/TraversableTemplate
const #40 = Asciz	thisCollection;
const #41 = Asciz	()Lscala/collection/generic/TraversableTemplate;;
const #42 = NameAndType	#40:#41;//  thisCollection:()Lscala/collection/generic/TraversableTemplate;
const #43 = InterfaceMethod	#39.#42;	//  scala/collection/generic/TraversableTemplate.thisCollection:()Lscala/collection/generic/TraversableTemplate;
const #44 = Asciz	that;
const #45 = Asciz	Lscala/collection/LinearSequence;;
const #46 = Asciz	Scala;
const #47 = Asciz	scala/collection/generic/DoubleLinkedListTemplate$class;
const #48 = class	#47;	//  scala/collection/generic/DoubleLinkedListTemplate$class
const #49 = Asciz	java/lang/Object;
const #50 = class	#49;	//  java/lang/Object

{
public static void $init$(scala.collection.generic.DoubleLinkedListTemplate);
  Code:
   Stack=0, Locals=1, Args_size=1
   0:	return
  LineNumberTable: 
   line 23: 0

  LocalVariableTable: 
   Start  Length  Slot  Name   Signature
   0      1      0    $this       Lscala/collection/generic/DoubleLinkedListTemplate;


public static void remove(scala.collection.generic.DoubleLinkedListTemplate);
  Code:
   Stack=2, Locals=1, Args_size=1
   0:	aload_0
   1:	invokeinterface	#16,  1; //InterfaceMethod scala/collection/generic/LinkedListTemplate.next:()Lscala/collection/Sequence;
   6:	ifnull	29
   9:	aload_0
   10:	invokeinterface	#16,  1; //InterfaceMethod scala/collection/generic/LinkedListTemplate.next:()Lscala/collection/Sequence;
   15:	checkcast	#18; //class scala/collection/generic/DoubleLinkedListTemplate
   18:	aload_0
   19:	invokeinterface	#22,  1; //InterfaceMethod scala/collection/generic/DoubleLinkedListTemplate.prev:()Lscala/collection/LinearSequence;
   24:	invokeinterface	#26,  2; //InterfaceMethod scala/collection/generic/DoubleLinkedListTemplate.prev_$eq:(Lscala/collection/LinearSequence;)V
   29:	aload_0
   30:	invokeinterface	#22,  1; //InterfaceMethod scala/collection/generic/DoubleLinkedListTemplate.prev:()Lscala/collection/LinearSequence;
   35:	ifnull	58
   38:	aload_0
   39:	invokeinterface	#22,  1; //InterfaceMethod scala/collection/generic/DoubleLinkedListTemplate.prev:()Lscala/collection/LinearSequence;
   44:	checkcast	#12; //class scala/collection/generic/LinkedListTemplate
   47:	aload_0
   48:	invokeinterface	#16,  1; //InterfaceMethod scala/collection/generic/LinkedListTemplate.next:()Lscala/collection/Sequence;
   53:	invokeinterface	#30,  2; //InterfaceMethod scala/collection/generic/LinkedListTemplate.next_$eq:(Lscala/collection/Sequence;)V
   58:	aload_0
   59:	aconst_null
   60:	pop
   61:	aconst_null
   62:	invokeinterface	#26,  2; //InterfaceMethod scala/collection/generic/DoubleLinkedListTemplate.prev_$eq:(Lscala/collection/LinearSequence;)V
   67:	aload_0
   68:	aconst_null
   69:	pop
   70:	aconst_null
   71:	invokeinterface	#30,  2; //InterfaceMethod scala/collection/generic/LinkedListTemplate.next_$eq:(Lscala/collection/Sequence;)V
   76:	return
  LineNumberTable: 
   line 41: 0
   line 42: 9
   line 43: 29
   line 44: 38
   line 45: 58
   line 46: 67

  LocalVariableTable: 
   Start  Length  Slot  Name   Signature
   0      77      0    $this       Lscala/collection/generic/DoubleLinkedListTemplate;


public static void insert(scala.collection.generic.DoubleLinkedListTemplate, scala.collection.LinearSequence);
  Code:
   Stack=2, Locals=2, Args_size=2
   0:	aload_1
   1:	ifnull	47
   4:	aload_1
   5:	checkcast	#18; //class scala/collection/generic/DoubleLinkedListTemplate
   8:	aload_0
   9:	invokeinterface	#16,  1; //InterfaceMethod scala/collection/generic/LinkedListTemplate.next:()Lscala/collection/Sequence;
   14:	checkcast	#34; //class scala/collection/LinearSequence
   17:	invokeinterface	#37,  2; //InterfaceMethod scala/collection/generic/DoubleLinkedListTemplate.append:(Lscala/collection/LinearSequence;)V
   22:	aload_0
   23:	aload_1
   24:	invokeinterface	#30,  2; //InterfaceMethod scala/collection/generic/LinkedListTemplate.next_$eq:(Lscala/collection/Sequence;)V
   29:	aload_1
   30:	checkcast	#18; //class scala/collection/generic/DoubleLinkedListTemplate
   33:	aload_0
   34:	invokeinterface	#43,  1; //InterfaceMethod scala/collection/generic/TraversableTemplate.thisCollection:()Lscala/collection/generic/TraversableTemplate;
   39:	checkcast	#34; //class scala/collection/LinearSequence
   42:	invokeinterface	#26,  2; //InterfaceMethod scala/collection/generic/DoubleLinkedListTemplate.prev_$eq:(Lscala/collection/LinearSequence;)V
   47:	return
  LineNumberTable: 
   line 34: 0
   line 35: 4
   line 36: 22
   line 37: 29
   line 34: 47

  LocalVariableTable: 
   Start  Length  Slot  Name   Signature
   0      48      0    $this       Lscala/collection/generic/DoubleLinkedListTemplate;
   0      48      1    that       Lscala/collection/LinearSequence;


public static void append(scala.collection.generic.DoubleLinkedListTemplate, scala.collection.LinearSequence);
  Code:
   Stack=2, Locals=2, Args_size=2
   0:	aload_0
   1:	invokeinterface	#16,  1; //InterfaceMethod scala/collection/generic/LinkedListTemplate.next:()Lscala/collection/Sequence;
   6:	ifnonnull	41
   9:	aload_0
   10:	aload_1
   11:	invokeinterface	#30,  2; //InterfaceMethod scala/collection/generic/LinkedListTemplate.next_$eq:(Lscala/collection/Sequence;)V
   16:	aload_1
   17:	ifnull	56
   20:	aload_1
   21:	checkcast	#18; //class scala/collection/generic/DoubleLinkedListTemplate
   24:	aload_0
   25:	invokeinterface	#43,  1; //InterfaceMethod scala/collection/generic/TraversableTemplate.thisCollection:()Lscala/collection/generic/TraversableTemplate;
   30:	checkcast	#34; //class scala/collection/LinearSequence
   33:	invokeinterface	#26,  2; //InterfaceMethod scala/collection/generic/DoubleLinkedListTemplate.prev_$eq:(Lscala/collection/LinearSequence;)V
   38:	goto	56
   41:	aload_0
   42:	invokeinterface	#16,  1; //InterfaceMethod scala/collection/generic/LinkedListTemplate.next:()Lscala/collection/Sequence;
   47:	checkcast	#18; //class scala/collection/generic/DoubleLinkedListTemplate
   50:	aload_1
   51:	invokeinterface	#37,  2; //InterfaceMethod scala/collection/generic/DoubleLinkedListTemplate.append:(Lscala/collection/LinearSequence;)V
   56:	return
  LineNumberTable: 
   line 28: 0
   line 29: 9
   line 30: 16
   line 32: 41
   line 28: 56

  LocalVariableTable: 
   Start  Length  Slot  Name   Signature
   0      57      0    $this       Lscala/collection/generic/DoubleLinkedListTemplate;
   0      57      1    that       Lscala/collection/LinearSequence;


}

