Compiled from "GenericTraversableTemplate.scala"
public abstract class scala.collection.generic.GenericTraversableTemplate$class extends java.lang.Object
  SourceFile: "GenericTraversableTemplate.scala"
  Scala: length = 0x
   
  InnerClass: 
   public final #118= #27 of #13; //$anonfun$1=class scala/collection/generic/GenericTraversableTemplate$$anonfun$1 of class scala/collection/generic/GenericTraversableTemplate
   public final #119= #94 of #13; //$anonfun$unzip$1=class scala/collection/generic/GenericTraversableTemplate$$anonfun$unzip$1 of class scala/collection/generic/GenericTraversableTemplate
   public final #120= #85 of #13; //$anonfun$flatten$1=class scala/collection/generic/GenericTraversableTemplate$$anonfun$flatten$1 of class scala/collection/generic/GenericTraversableTemplate
   public final #121= #63 of #13; //$anonfun$transpose$2=class scala/collection/generic/GenericTraversableTemplate$$anonfun$transpose$2 of class scala/collection/generic/GenericTraversableTemplate
   public final #122= #50 of #13; //$anonfun$transpose$1=class scala/collection/generic/GenericTraversableTemplate$$anonfun$transpose$1 of class scala/collection/generic/GenericTraversableTemplate
  minor version: 0
  major version: 49
  Constant pool:
const #1 = Asciz	SourceFile;
const #2 = Asciz	GenericTraversableTemplate.scala;
const #3 = Asciz	$init$;
const #4 = Asciz	(Lscala/collection/generic/GenericTraversableTemplate;)V;
const #5 = Asciz	Code;
const #6 = Asciz	LineNumberTable;
const #7 = Asciz	$this;
const #8 = Asciz	Lscala/collection/generic/GenericTraversableTemplate;;
const #9 = Asciz	LocalVariableTable;
const #10 = Asciz	transpose;
const #11 = Asciz	(Lscala/collection/generic/GenericTraversableTemplate;Lscala/Function1;)Lscala/collection/Traversable;;
const #12 = Asciz	scala/collection/generic/GenericTraversableTemplate;
const #13 = class	#12;	//  scala/collection/generic/GenericTraversableTemplate
const #14 = Asciz	head;
const #15 = Asciz	()Ljava/lang/Object;;
const #16 = NameAndType	#14:#15;//  head:()Ljava/lang/Object;
const #17 = InterfaceMethod	#13.#16;	//  scala/collection/generic/GenericTraversableTemplate.head:()Ljava/lang/Object;
const #18 = Asciz	scala/Function1;
const #19 = class	#18;	//  scala/Function1
const #20 = Asciz	apply;
const #21 = Asciz	(Ljava/lang/Object;)Ljava/lang/Object;;
const #22 = NameAndType	#20:#21;//  apply:(Ljava/lang/Object;)Ljava/lang/Object;
const #23 = InterfaceMethod	#19.#22;	//  scala/Function1.apply:(Ljava/lang/Object;)Ljava/lang/Object;
const #24 = Asciz	scala/collection/TraversableLike;
const #25 = class	#24;	//  scala/collection/TraversableLike
const #26 = Asciz	scala/collection/generic/GenericTraversableTemplate$$anonfun$1;
const #27 = class	#26;	//  scala/collection/generic/GenericTraversableTemplate$$anonfun$1
const #28 = Asciz	<init>;
const #29 = NameAndType	#28:#4;//  "<init>":(Lscala/collection/generic/GenericTraversableTemplate;)V
const #30 = Method	#27.#29;	//  scala/collection/generic/GenericTraversableTemplate$$anonfun$1."<init>":(Lscala/collection/generic/GenericTraversableTemplate;)V
const #31 = Asciz	scala/collection/Traversable$;
const #32 = class	#31;	//  scala/collection/Traversable$
const #33 = Asciz	MODULE$;
const #34 = Asciz	Lscala/collection/Traversable$;;
const #35 = NameAndType	#33:#34;//  MODULE$:Lscala/collection/Traversable$;
const #36 = Field	#32.#35;	//  scala/collection/Traversable$.MODULE$:Lscala/collection/Traversable$;
const #37 = Asciz	canBuildFrom;
const #38 = Asciz	()Lscala/collection/generic/CanBuildFrom;;
const #39 = NameAndType	#37:#38;//  canBuildFrom:()Lscala/collection/generic/CanBuildFrom;
const #40 = Method	#32.#39;	//  scala/collection/Traversable$.canBuildFrom:()Lscala/collection/generic/CanBuildFrom;
const #41 = Asciz	map;
const #42 = Asciz	(Lscala/Function1;Lscala/collection/generic/CanBuildFrom;)Ljava/lang/Object;;
const #43 = NameAndType	#41:#42;//  map:(Lscala/Function1;Lscala/collection/generic/CanBuildFrom;)Ljava/lang/Object;
const #44 = InterfaceMethod	#25.#43;	//  scala/collection/TraversableLike.map:(Lscala/Function1;Lscala/collection/generic/CanBuildFrom;)Ljava/lang/Object;
const #45 = Asciz	toIndexedSeq;
const #46 = Asciz	()Lscala/collection/mutable/IndexedSeq;;
const #47 = NameAndType	#45:#46;//  toIndexedSeq:()Lscala/collection/mutable/IndexedSeq;
const #48 = InterfaceMethod	#25.#47;	//  scala/collection/TraversableLike.toIndexedSeq:()Lscala/collection/mutable/IndexedSeq;
const #49 = Asciz	scala/collection/generic/GenericTraversableTemplate$$anonfun$transpose$1;
const #50 = class	#49;	//  scala/collection/generic/GenericTraversableTemplate$$anonfun$transpose$1
const #51 = Asciz	(Lscala/collection/generic/GenericTraversableTemplate;Lscala/Function1;Lscala/collection/IndexedSeq;)V;
const #52 = NameAndType	#28:#51;//  "<init>":(Lscala/collection/generic/GenericTraversableTemplate;Lscala/Function1;Lscala/collection/IndexedSeq;)V
const #53 = Method	#50.#52;	//  scala/collection/generic/GenericTraversableTemplate$$anonfun$transpose$1."<init>":(Lscala/collection/generic/GenericTraversableTemplate;Lscala/Function1;Lscala/collection/IndexedSeq;)V
const #54 = Asciz	foreach;
const #55 = Asciz	(Lscala/Function1;)V;
const #56 = NameAndType	#54:#55;//  foreach:(Lscala/Function1;)V
const #57 = InterfaceMethod	#13.#56;	//  scala/collection/generic/GenericTraversableTemplate.foreach:(Lscala/Function1;)V
const #58 = Asciz	genericBuilder;
const #59 = Asciz	()Lscala/collection/mutable/Builder;;
const #60 = NameAndType	#58:#59;//  genericBuilder:()Lscala/collection/mutable/Builder;
const #61 = InterfaceMethod	#13.#60;	//  scala/collection/generic/GenericTraversableTemplate.genericBuilder:()Lscala/collection/mutable/Builder;
const #62 = Asciz	scala/collection/generic/GenericTraversableTemplate$$anonfun$transpose$2;
const #63 = class	#62;	//  scala/collection/generic/GenericTraversableTemplate$$anonfun$transpose$2
const #64 = Asciz	(Lscala/collection/generic/GenericTraversableTemplate;Lscala/collection/mutable/Builder;)V;
const #65 = NameAndType	#28:#64;//  "<init>":(Lscala/collection/generic/GenericTraversableTemplate;Lscala/collection/mutable/Builder;)V
const #66 = Method	#63.#65;	//  scala/collection/generic/GenericTraversableTemplate$$anonfun$transpose$2."<init>":(Lscala/collection/generic/GenericTraversableTemplate;Lscala/collection/mutable/Builder;)V
const #67 = Asciz	scala/collection/IndexedSeqLike;
const #68 = class	#67;	//  scala/collection/IndexedSeqLike
const #69 = InterfaceMethod	#68.#56;	//  scala/collection/IndexedSeqLike.foreach:(Lscala/Function1;)V
const #70 = Asciz	scala/collection/mutable/Builder;
const #71 = class	#70;	//  scala/collection/mutable/Builder
const #72 = Asciz	result;
const #73 = NameAndType	#72:#15;//  result:()Ljava/lang/Object;
const #74 = InterfaceMethod	#71.#73;	//  scala/collection/mutable/Builder.result:()Ljava/lang/Object;
const #75 = Asciz	scala/collection/Traversable;
const #76 = class	#75;	//  scala/collection/Traversable
const #77 = Asciz	asTraversable$2;
const #78 = Asciz	Lscala/Function1;;
const #79 = Asciz	bs$1;
const #80 = Asciz	Lscala/collection/IndexedSeq;;
const #81 = Asciz	bb$1;
const #82 = Asciz	Lscala/collection/mutable/Builder;;
const #83 = Asciz	flatten;
const #84 = Asciz	scala/collection/generic/GenericTraversableTemplate$$anonfun$flatten$1;
const #85 = class	#84;	//  scala/collection/generic/GenericTraversableTemplate$$anonfun$flatten$1
const #86 = Asciz	(Lscala/collection/generic/GenericTraversableTemplate;Lscala/Function1;Lscala/collection/mutable/Builder;)V;
const #87 = NameAndType	#28:#86;//  "<init>":(Lscala/collection/generic/GenericTraversableTemplate;Lscala/Function1;Lscala/collection/mutable/Builder;)V
const #88 = Method	#85.#87;	//  scala/collection/generic/GenericTraversableTemplate$$anonfun$flatten$1."<init>":(Lscala/collection/generic/GenericTraversableTemplate;Lscala/Function1;Lscala/collection/mutable/Builder;)V
const #89 = Asciz	asTraversable$1;
const #90 = Asciz	b$1;
const #91 = Asciz	unzip;
const #92 = Asciz	(Lscala/collection/generic/GenericTraversableTemplate;Lscala/Function1;)Lscala/Tuple2;;
const #93 = Asciz	scala/collection/generic/GenericTraversableTemplate$$anonfun$unzip$1;
const #94 = class	#93;	//  scala/collection/generic/GenericTraversableTemplate$$anonfun$unzip$1
const #95 = Asciz	(Lscala/collection/generic/GenericTraversableTemplate;Lscala/Function1;Lscala/collection/mutable/Builder;Lscala/collection/mutable/Builder;)V;
const #96 = NameAndType	#28:#95;//  "<init>":(Lscala/collection/generic/GenericTraversableTemplate;Lscala/Function1;Lscala/collection/mutable/Builder;Lscala/collection/mutable/Builder;)V
const #97 = Method	#94.#96;	//  scala/collection/generic/GenericTraversableTemplate$$anonfun$unzip$1."<init>":(Lscala/collection/generic/GenericTraversableTemplate;Lscala/Function1;Lscala/collection/mutable/Builder;Lscala/collection/mutable/Builder;)V
const #98 = Asciz	scala/Tuple2;
const #99 = class	#98;	//  scala/Tuple2
const #100 = Asciz	(Ljava/lang/Object;Ljava/lang/Object;)V;
const #101 = NameAndType	#28:#100;//  "<init>":(Ljava/lang/Object;Ljava/lang/Object;)V
const #102 = Method	#99.#101;	//  scala/Tuple2."<init>":(Ljava/lang/Object;Ljava/lang/Object;)V
const #103 = Asciz	asPair$1;
const #104 = Asciz	b1$1;
const #105 = Asciz	b2$1;
const #106 = Asciz	(Lscala/collection/generic/GenericTraversableTemplate;)Lscala/collection/mutable/Builder;;
const #107 = Asciz	companion;
const #108 = Asciz	()Lscala/collection/generic/GenericCompanion;;
const #109 = NameAndType	#107:#108;//  companion:()Lscala/collection/generic/GenericCompanion;
const #110 = InterfaceMethod	#13.#109;	//  scala/collection/generic/GenericTraversableTemplate.companion:()Lscala/collection/generic/GenericCompanion;
const #111 = Asciz	scala/collection/generic/GenericCompanion;
const #112 = class	#111;	//  scala/collection/generic/GenericCompanion
const #113 = Asciz	newBuilder;
const #114 = NameAndType	#113:#59;//  newBuilder:()Lscala/collection/mutable/Builder;
const #115 = Method	#112.#114;	//  scala/collection/generic/GenericCompanion.newBuilder:()Lscala/collection/mutable/Builder;
const #116 = Asciz	Scala;
const #117 = Asciz	InnerClasses;
const #118 = Asciz	$anonfun$1;
const #119 = Asciz	$anonfun$unzip$1;
const #120 = Asciz	$anonfun$flatten$1;
const #121 = Asciz	$anonfun$transpose$2;
const #122 = Asciz	$anonfun$transpose$1;
const #123 = Asciz	scala/collection/generic/GenericTraversableTemplate$class;
const #124 = class	#123;	//  scala/collection/generic/GenericTraversableTemplate$class
const #125 = Asciz	java/lang/Object;
const #126 = class	#125;	//  java/lang/Object

{
public static void $init$(scala.collection.generic.GenericTraversableTemplate);
  Code:
   Stack=0, Locals=1, Args_size=1
   0:	return
  LineNumberTable: 
   line 27: 0

  LocalVariableTable: 
   Start  Length  Slot  Name   Signature
   0      1      0    $this       Lscala/collection/generic/GenericTraversableTemplate;


public static scala.collection.Traversable transpose(scala.collection.generic.GenericTraversableTemplate, scala.Function1);
  Code:
   Stack=6, Locals=4, Args_size=2
   0:	aload_1
   1:	aload_0
   2:	invokeinterface	#17,  1; //InterfaceMethod scala/collection/generic/GenericTraversableTemplate.head:()Ljava/lang/Object;
   7:	invokeinterface	#23,  2; //InterfaceMethod scala/Function1.apply:(Ljava/lang/Object;)Ljava/lang/Object;
   12:	checkcast	#25; //class scala/collection/TraversableLike
   15:	new	#27; //class scala/collection/generic/GenericTraversableTemplate$$anonfun$1
   18:	dup
   19:	aload_0
   20:	invokespecial	#30; //Method scala/collection/generic/GenericTraversableTemplate$$anonfun$1."<init>":(Lscala/collection/generic/GenericTraversableTemplate;)V
   23:	getstatic	#36; //Field scala/collection/Traversable$.MODULE$:Lscala/collection/Traversable$;
   26:	invokevirtual	#40; //Method scala/collection/Traversable$.canBuildFrom:()Lscala/collection/generic/CanBuildFrom;
   29:	invokeinterface	#44,  3; //InterfaceMethod scala/collection/TraversableLike.map:(Lscala/Function1;Lscala/collection/generic/CanBuildFrom;)Ljava/lang/Object;
   34:	checkcast	#25; //class scala/collection/TraversableLike
   37:	invokeinterface	#48,  1; //InterfaceMethod scala/collection/TraversableLike.toIndexedSeq:()Lscala/collection/mutable/IndexedSeq;
   42:	astore_2
   43:	aload_0
   44:	new	#50; //class scala/collection/generic/GenericTraversableTemplate$$anonfun$transpose$1
   47:	dup
   48:	aload_0
   49:	aload_1
   50:	aload_2
   51:	invokespecial	#53; //Method scala/collection/generic/GenericTraversableTemplate$$anonfun$transpose$1."<init>":(Lscala/collection/generic/GenericTraversableTemplate;Lscala/Function1;Lscala/collection/IndexedSeq;)V
   54:	invokeinterface	#57,  2; //InterfaceMethod scala/collection/generic/GenericTraversableTemplate.foreach:(Lscala/Function1;)V
   59:	aload_0
   60:	invokeinterface	#61,  1; //InterfaceMethod scala/collection/generic/GenericTraversableTemplate.genericBuilder:()Lscala/collection/mutable/Builder;
   65:	astore_3
   66:	aload_2
   67:	new	#63; //class scala/collection/generic/GenericTraversableTemplate$$anonfun$transpose$2
   70:	dup
   71:	aload_0
   72:	aload_3
   73:	invokespecial	#66; //Method scala/collection/generic/GenericTraversableTemplate$$anonfun$transpose$2."<init>":(Lscala/collection/generic/GenericTraversableTemplate;Lscala/collection/mutable/Builder;)V
   76:	invokeinterface	#69,  2; //InterfaceMethod scala/collection/IndexedSeqLike.foreach:(Lscala/Function1;)V
   81:	aload_3
   82:	invokeinterface	#74,  1; //InterfaceMethod scala/collection/mutable/Builder.result:()Ljava/lang/Object;
   87:	checkcast	#76; //class scala/collection/Traversable
   90:	areturn
  LineNumberTable: 
   line 110: 0
   line 111: 43
   line 118: 59
   line 119: 66
   line 120: 81

  LocalVariableTable: 
   Start  Length  Slot  Name   Signature
   0      91      0    $this       Lscala/collection/generic/GenericTraversableTemplate;
   0      91      1    asTraversable$2       Lscala/Function1;
   43      47      2    bs$1       Lscala/collection/IndexedSeq;
   66      24      3    bb$1       Lscala/collection/mutable/Builder;


public static scala.collection.Traversable flatten(scala.collection.generic.GenericTraversableTemplate, scala.Function1);
  Code:
   Stack=6, Locals=3, Args_size=2
   0:	aload_0
   1:	invokeinterface	#61,  1; //InterfaceMethod scala/collection/generic/GenericTraversableTemplate.genericBuilder:()Lscala/collection/mutable/Builder;
   6:	astore_2
   7:	aload_0
   8:	new	#85; //class scala/collection/generic/GenericTraversableTemplate$$anonfun$flatten$1
   11:	dup
   12:	aload_0
   13:	aload_1
   14:	aload_2
   15:	invokespecial	#88; //Method scala/collection/generic/GenericTraversableTemplate$$anonfun$flatten$1."<init>":(Lscala/collection/generic/GenericTraversableTemplate;Lscala/Function1;Lscala/collection/mutable/Builder;)V
   18:	invokeinterface	#57,  2; //InterfaceMethod scala/collection/generic/GenericTraversableTemplate.foreach:(Lscala/Function1;)V
   23:	aload_2
   24:	invokeinterface	#74,  1; //InterfaceMethod scala/collection/mutable/Builder.result:()Ljava/lang/Object;
   29:	checkcast	#76; //class scala/collection/Traversable
   32:	areturn
  LineNumberTable: 
   line 96: 0
   line 97: 7
   line 99: 23

  LocalVariableTable: 
   Start  Length  Slot  Name   Signature
   0      33      0    $this       Lscala/collection/generic/GenericTraversableTemplate;
   0      33      1    asTraversable$1       Lscala/Function1;
   7      25      2    b$1       Lscala/collection/mutable/Builder;


public static scala.Tuple2 unzip(scala.collection.generic.GenericTraversableTemplate, scala.Function1);
  Code:
   Stack=7, Locals=4, Args_size=2
   0:	aload_0
   1:	invokeinterface	#61,  1; //InterfaceMethod scala/collection/generic/GenericTraversableTemplate.genericBuilder:()Lscala/collection/mutable/Builder;
   6:	astore_2
   7:	aload_0
   8:	invokeinterface	#61,  1; //InterfaceMethod scala/collection/generic/GenericTraversableTemplate.genericBuilder:()Lscala/collection/mutable/Builder;
   13:	astore_3
   14:	aload_0
   15:	new	#94; //class scala/collection/generic/GenericTraversableTemplate$$anonfun$unzip$1
   18:	dup
   19:	aload_0
   20:	aload_1
   21:	aload_2
   22:	aload_3
   23:	invokespecial	#97; //Method scala/collection/generic/GenericTraversableTemplate$$anonfun$unzip$1."<init>":(Lscala/collection/generic/GenericTraversableTemplate;Lscala/Function1;Lscala/collection/mutable/Builder;Lscala/collection/mutable/Builder;)V
   26:	invokeinterface	#57,  2; //InterfaceMethod scala/collection/generic/GenericTraversableTemplate.foreach:(Lscala/Function1;)V
   31:	new	#99; //class scala/Tuple2
   34:	dup
   35:	aload_2
   36:	invokeinterface	#74,  1; //InterfaceMethod scala/collection/mutable/Builder.result:()Ljava/lang/Object;
   41:	aload_3
   42:	invokeinterface	#74,  1; //InterfaceMethod scala/collection/mutable/Builder.result:()Ljava/lang/Object;
   47:	invokespecial	#102; //Method scala/Tuple2."<init>":(Ljava/lang/Object;Ljava/lang/Object;)V
   50:	areturn
  LineNumberTable: 
   line 77: 0
   line 78: 7
   line 79: 14
   line 84: 31

  LocalVariableTable: 
   Start  Length  Slot  Name   Signature
   0      51      0    $this       Lscala/collection/generic/GenericTraversableTemplate;
   0      51      1    asPair$1       Lscala/Function1;
   7      43      2    b1$1       Lscala/collection/mutable/Builder;
   14      36      3    b2$1       Lscala/collection/mutable/Builder;


public static scala.collection.mutable.Builder genericBuilder(scala.collection.generic.GenericTraversableTemplate);
  Code:
   Stack=1, Locals=1, Args_size=1
   0:	aload_0
   1:	invokeinterface	#110,  1; //InterfaceMethod scala/collection/generic/GenericTraversableTemplate.companion:()Lscala/collection/generic/GenericCompanion;
   6:	invokevirtual	#115; //Method scala/collection/generic/GenericCompanion.newBuilder:()Lscala/collection/mutable/Builder;
   9:	areturn
  LineNumberTable: 
   line 65: 0

  LocalVariableTable: 
   Start  Length  Slot  Name   Signature
   0      10      0    $this       Lscala/collection/generic/GenericTraversableTemplate;


public static scala.collection.mutable.Builder newBuilder(scala.collection.generic.GenericTraversableTemplate);
  Code:
   Stack=1, Locals=1, Args_size=1
   0:	aload_0
   1:	invokeinterface	#110,  1; //InterfaceMethod scala/collection/generic/GenericTraversableTemplate.companion:()Lscala/collection/generic/GenericCompanion;
   6:	invokevirtual	#115; //Method scala/collection/generic/GenericCompanion.newBuilder:()Lscala/collection/mutable/Builder;
   9:	areturn
  LineNumberTable: 
   line 60: 0

  LocalVariableTable: 
   Start  Length  Slot  Name   Signature
   0      10      0    $this       Lscala/collection/generic/GenericTraversableTemplate;


}

