Compiled from "GenericSetTemplate.scala"
public abstract class scala.collection.generic.GenericSetTemplate$class extends java.lang.Object
  SourceFile: "GenericSetTemplate.scala"
  Scala: length = 0x
   
  minor version: 0
  major version: 49
  Constant pool:
const #1 = Asciz	SourceFile;
const #2 = Asciz	GenericSetTemplate.scala;
const #3 = Asciz	$init$;
const #4 = Asciz	(Lscala/collection/generic/GenericSetTemplate;)V;
const #5 = Asciz	Code;
const #6 = Asciz	LineNumberTable;
const #7 = Asciz	$this;
const #8 = Asciz	Lscala/collection/generic/GenericSetTemplate;;
const #9 = Asciz	LocalVariableTable;
const #10 = Asciz	empty;
const #11 = Asciz	(Lscala/collection/generic/GenericSetTemplate;)Lscala/collection/Set;;
const #12 = Asciz	scala/collection/generic/GenericTraversableTemplate;
const #13 = class	#12;	//  scala/collection/generic/GenericTraversableTemplate
const #14 = Asciz	companion;
const #15 = Asciz	()Lscala/collection/generic/GenericCompanion;;
const #16 = NameAndType	#14:#15;//  companion:()Lscala/collection/generic/GenericCompanion;
const #17 = InterfaceMethod	#13.#16;	//  scala/collection/generic/GenericTraversableTemplate.companion:()Lscala/collection/generic/GenericCompanion;
const #18 = Asciz	scala/collection/generic/GenericCompanion;
const #19 = class	#18;	//  scala/collection/generic/GenericCompanion
const #20 = Asciz	()Lscala/collection/Traversable;;
const #21 = NameAndType	#10:#20;//  empty:()Lscala/collection/Traversable;
const #22 = Method	#19.#21;	//  scala/collection/generic/GenericCompanion.empty:()Lscala/collection/Traversable;
const #23 = Asciz	scala/collection/Set;
const #24 = class	#23;	//  scala/collection/Set
const #25 = Asciz	Scala;
const #26 = Asciz	scala/collection/generic/GenericSetTemplate$class;
const #27 = class	#26;	//  scala/collection/generic/GenericSetTemplate$class
const #28 = Asciz	java/lang/Object;
const #29 = class	#28;	//  java/lang/Object

{
public static void $init$(scala.collection.generic.GenericSetTemplate);
  Code:
   Stack=0, Locals=1, Args_size=1
   0:	return
  LineNumberTable: 
   line 18: 0

  LocalVariableTable: 
   Start  Length  Slot  Name   Signature
   0      1      0    $this       Lscala/collection/generic/GenericSetTemplate;


public static scala.collection.Set empty(scala.collection.generic.GenericSetTemplate);
  Code:
   Stack=1, Locals=1, Args_size=1
   0:	aload_0
   1:	invokeinterface	#17,  1; //InterfaceMethod scala/collection/generic/GenericTraversableTemplate.companion:()Lscala/collection/generic/GenericCompanion;
   6:	invokevirtual	#22; //Method scala/collection/generic/GenericCompanion.empty:()Lscala/collection/Traversable;
   9:	checkcast	#24; //class scala/collection/Set
   12:	areturn
  LineNumberTable: 
   line 19: 0

  LocalVariableTable: 
   Start  Length  Slot  Name   Signature
   0      13      0    $this       Lscala/collection/generic/GenericSetTemplate;


}

