Compiled from "GenericTraversableTemplate.scala"
public final class scala.collection.generic.GenericTraversableTemplate$$anonfun$1 extends java.lang.Object implements scala.Function1,scala.ScalaObject,java.io.Serializable
  SourceFile: "GenericTraversableTemplate.scala"
  Scala: length = 0x
   
  InnerClass: 
   public final $anonfun$1=class scala/collection/generic/GenericTraversableTemplate$$anonfun$1 of class scala/collection/generic/GenericTraversableTemplate
  minor version: 0
  major version: 49
  Constant pool:
Asciz	SourceFile;
Asciz	GenericTraversableTemplate.scala;
Asciz	<clinit>;
Asciz	()V;
Asciz	Code;
Asciz	serialVersionUID;
Asciz	J;
Asciz	scala/collection/generic/GenericTraversableTemplate$$anonfun$1;
class	scala/collection/generic/GenericTraversableTemplate$$anonfun$1
NameAndType	serialVersionUID:J
Field	scala/collection/generic/GenericTraversableTemplate$$anonfun$1.serialVersionUID:J
Asciz	$outer;
Asciz	Lscala/collection/generic/GenericTraversableTemplate;;
Asciz	<init>;
Asciz	(Lscala/collection/generic/GenericTraversableTemplate;)V;
Asciz	LineNumberTable;
Asciz	java/lang/NullPointerException;
class	java/lang/NullPointerException
NameAndType	"<init>":()V
Method	java/lang/NullPointerException."<init>":()V
NameAndType	$outer:Lscala/collection/generic/GenericTraversableTemplate;
Field	scala/collection/generic/GenericTraversableTemplate$$anonfun$1.$outer:Lscala/collection/generic/GenericTraversableTemplate;
Asciz	java/lang/Object;
class	java/lang/Object
Method	java/lang/Object."<init>":()V
Asciz	scala/Function1$class;
class	scala/Function1$class
Asciz	$init$;
Asciz	(Lscala/Function1;)V;
NameAndType	$init$:(Lscala/Function1;)V
Method	scala/Function1$class.$init$:(Lscala/Function1;)V
Asciz	this;
Asciz	Lscala/collection/generic/GenericTraversableTemplate$$anonfun$1;;
Asciz	LocalVariableTable;
Asciz	(Lscala/collection/generic/GenericTraversableTemplate<TA;TCC;>;)V;
Asciz	Signature;
Asciz	apply;
Asciz	(Ljava/lang/Object;)Ljava/lang/Object;;
Asciz	(Ljava/lang/Object;)Lscala/collection/mutable/Builder;;
NameAndType	apply:(Ljava/lang/Object;)Lscala/collection/mutable/Builder;
Method	scala/collection/generic/GenericTraversableTemplate$$anonfun$1.apply:(Ljava/lang/Object;)Lscala/collection/mutable/Builder;
Asciz	v1;
Asciz	Ljava/lang/Object;;
Asciz	scala/collection/generic/GenericTraversableTemplate;
class	scala/collection/generic/GenericTraversableTemplate
Asciz	genericBuilder;
Asciz	()Lscala/collection/mutable/Builder;;
NameAndType	genericBuilder:()Lscala/collection/mutable/Builder;
InterfaceMethod	scala/collection/generic/GenericTraversableTemplate.genericBuilder:()Lscala/collection/mutable/Builder;
Asciz	x$2;
Asciz	(TB;)Lscala/collection/mutable/Builder<TB;TCC;>;;
Asciz	andThen;
Asciz	(Lscala/Function1;)Lscala/Function1;;
Asciz	(Lscala/Function1;Lscala/Function1;)Lscala/Function1;;
NameAndType	andThen:(Lscala/Function1;Lscala/Function1;)Lscala/Function1;
Method	scala/Function1$class.andThen:(Lscala/Function1;Lscala/Function1;)Lscala/Function1;
Asciz	g;
Asciz	Lscala/Function1;;
Asciz	compose;
NameAndType	compose:(Lscala/Function1;Lscala/Function1;)Lscala/Function1;
Method	scala/Function1$class.compose:(Lscala/Function1;Lscala/Function1;)Lscala/Function1;
Asciz	toString;
Asciz	()Ljava/lang/String;;
Asciz	(Lscala/Function1;)Ljava/lang/String;;
NameAndType	toString:(Lscala/Function1;)Ljava/lang/String;
Method	scala/Function1$class.toString:(Lscala/Function1;)Ljava/lang/String;
Asciz	Scala;
Asciz	InnerClasses;
Asciz	$anonfun$1;
Asciz	scala/Function1;
class	scala/Function1
Asciz	scala/ScalaObject;
class	scala/ScalaObject
Asciz	java/io/Serializable;
class	java/io/Serializable

{
public static final long serialVersionUID;
  Signature: J

private final scala.collection.generic.GenericTraversableTemplate $outer;
  Signature: Lscala/collection/generic/GenericTraversableTemplate;

public static {};
  Signature: ()V
  Code:
   Stack=2, Locals=0, Args_size=0
	lconst_0
	putstatic	Field serialVersionUID:J
	return
  Labels:

public scala.collection.generic.GenericTraversableTemplate$$anonfun$1(scala.collection.generic.GenericTraversableTemplate);
  Signature: (Lscala/collection/generic/GenericTraversableTemplate;)V
  Code:
   Stack=2, Locals=2, Args_size=2
	aload_1
	ifnonnull	l1 // aload_0
	new	class java/lang/NullPointerException
	dup
	invokespecial	Method java/lang/NullPointerException."<init>":()V
	athrow
l1	aload_0
	aload_1
	putfield	Field $outer:Lscala/collection/generic/GenericTraversableTemplate;
	aload_0
	invokespecial	Method java/lang/Object."<init>":()V
	aload_0
	invokestatic	Method scala/Function1$class.$init$:(Lscala/Function1;)V
	return
  Labels:
   	l1 = 12 // aload_0
  LocalVariableTable: 
   Start  Length  Slot  Name   Signature
   0      26      0    this       Lscala/collection/generic/GenericTraversableTemplate$$anonfun$1;
   0      26      1    $outer       Lscala/collection/generic/GenericTraversableTemplate;

  Signature: length = 0x2
   00 23 

public final java.lang.Object apply(java.lang.Object);
  Signature: (Ljava/lang/Object;)Ljava/lang/Object;
  Code:
   Stack=2, Locals=3, Args_size=2
	aload_0
	getfield	Field $outer:Lscala/collection/generic/GenericTraversableTemplate;
	astore_2
	aload_0
	aload_1
	invokevirtual	Method apply:(Ljava/lang/Object;)Lscala/collection/mutable/Builder;
	areturn
  Labels:
  LocalVariableTable: 
   Start  Length  Slot  Name   Signature
   0      11      0    this       Lscala/collection/generic/GenericTraversableTemplate$$anonfun$1;
   5      6      1    v1       Ljava/lang/Object;


public final scala.collection.mutable.Builder apply(java.lang.Object);
  Signature: (Ljava/lang/Object;)Lscala/collection/mutable/Builder;
  Code:
   Stack=1, Locals=3, Args_size=2
	aload_0
	getfield	Field $outer:Lscala/collection/generic/GenericTraversableTemplate;
	astore_2
	aload_0
	getfield	Field $outer:Lscala/collection/generic/GenericTraversableTemplate;
	invokeinterface	InterfaceMethod scala/collection/generic/GenericTraversableTemplate.genericBuilder:()Lscala/collection/mutable/Builder;
	areturn
  Labels:
  LocalVariableTable: 
   Start  Length  Slot  Name   Signature
   0      15      0    this       Lscala/collection/generic/GenericTraversableTemplate$$anonfun$1;
   5      10      1    x$2       Ljava/lang/Object;

  Signature: length = 0x2
   00 33 

public scala.Function1 andThen(scala.Function1);
  Signature: (Lscala/Function1;)Lscala/Function1;
  Code:
   Stack=2, Locals=2, Args_size=2
	aload_0
	aload_1
	invokestatic	Method scala/Function1$class.andThen:(Lscala/Function1;Lscala/Function1;)Lscala/Function1;
	areturn
  Labels:
  LocalVariableTable: 
   Start  Length  Slot  Name   Signature
   0      6      0    this       Lscala/collection/generic/GenericTraversableTemplate$$anonfun$1;
   0      6      1    g       Lscala/Function1;


public scala.Function1 compose(scala.Function1);
  Signature: (Lscala/Function1;)Lscala/Function1;
  Code:
   Stack=2, Locals=2, Args_size=2
	aload_0
	aload_1
	invokestatic	Method scala/Function1$class.compose:(Lscala/Function1;Lscala/Function1;)Lscala/Function1;
	areturn
  Labels:
  LocalVariableTable: 
   Start  Length  Slot  Name   Signature
   0      6      0    this       Lscala/collection/generic/GenericTraversableTemplate$$anonfun$1;
   0      6      1    g       Lscala/Function1;


public java.lang.String toString();
  Signature: ()Ljava/lang/String;
  Code:
   Stack=1, Locals=1, Args_size=1
	aload_0
	invokestatic	Method scala/Function1$class.toString:(Lscala/Function1;)Ljava/lang/String;
	areturn
  Labels:

}

