Compiled from "ImmutableMapTemplate.scala"
public abstract class scala.collection.generic.ImmutableMapTemplate$class extends java.lang.Object
  SourceFile: "ImmutableMapTemplate.scala"
  Scala: length = 0x
   
  InnerClass: 
   public final #121= #36 of #13; //$anonfun$filterNot$1=class scala/collection/generic/ImmutableMapTemplate$$anonfun$filterNot$1 of class scala/collection/generic/ImmutableMapTemplate
   public final #122= #62 of #13; //$anonfun$transform$1=class scala/collection/generic/ImmutableMapTemplate$$anonfun$transform$1 of class scala/collection/generic/ImmutableMapTemplate
   public final #123= #83 of #13; //$anonfun$$plus$plus$2=class scala/collection/generic/ImmutableMapTemplate$$anonfun$$plus$plus$2 of class scala/collection/generic/ImmutableMapTemplate
   public final #124= #96 of #13; //$anonfun$$plus$plus$1=class scala/collection/generic/ImmutableMapTemplate$$anonfun$$plus$plus$1 of class scala/collection/generic/ImmutableMapTemplate
  minor version: 0
  major version: 49
  Constant pool:
const #1 = Asciz	SourceFile;
const #2 = Asciz	ImmutableMapTemplate.scala;
const #3 = Asciz	$init$;
const #4 = Asciz	(Lscala/collection/generic/ImmutableMapTemplate;)V;
const #5 = Asciz	Code;
const #6 = Asciz	LineNumberTable;
const #7 = Asciz	$this;
const #8 = Asciz	Lscala/collection/generic/ImmutableMapTemplate;;
const #9 = Asciz	LocalVariableTable;
const #10 = Asciz	update;
const #11 = Asciz	(Lscala/collection/generic/ImmutableMapTemplate;Ljava/lang/Object;Ljava/lang/Object;)Lscala/collection/immutable/Map;;
const #12 = Asciz	scala/collection/generic/ImmutableMapTemplate;
const #13 = class	#12;	//  scala/collection/generic/ImmutableMapTemplate
const #14 = Asciz	updated;
const #15 = Asciz	(Ljava/lang/Object;Ljava/lang/Object;)Lscala/collection/immutable/Map;;
const #16 = NameAndType	#14:#15;//  updated:(Ljava/lang/Object;Ljava/lang/Object;)Lscala/collection/immutable/Map;
const #17 = InterfaceMethod	#13.#16;	//  scala/collection/generic/ImmutableMapTemplate.updated:(Ljava/lang/Object;Ljava/lang/Object;)Lscala/collection/immutable/Map;
const #18 = Asciz	key;
const #19 = Asciz	Ljava/lang/Object;;
const #20 = Asciz	value;
const #21 = Asciz	filterNot;
const #22 = Asciz	(Lscala/collection/generic/ImmutableMapTemplate;Lscala/Function1;)Lscala/collection/generic/ImmutableMapTemplate;;
const #23 = Asciz	scala/runtime/ObjectRef;
const #24 = class	#23;	//  scala/runtime/ObjectRef
const #25 = Asciz	scala/collection/generic/TraversableTemplate;
const #26 = class	#25;	//  scala/collection/generic/TraversableTemplate
const #27 = Asciz	thisCollection;
const #28 = Asciz	()Lscala/collection/generic/TraversableTemplate;;
const #29 = NameAndType	#27:#28;//  thisCollection:()Lscala/collection/generic/TraversableTemplate;
const #30 = InterfaceMethod	#26.#29;	//  scala/collection/generic/TraversableTemplate.thisCollection:()Lscala/collection/generic/TraversableTemplate;
const #31 = Asciz	<init>;
const #32 = Asciz	(Ljava/lang/Object;)V;
const #33 = NameAndType	#31:#32;//  "<init>":(Ljava/lang/Object;)V
const #34 = Method	#24.#33;	//  scala/runtime/ObjectRef."<init>":(Ljava/lang/Object;)V
const #35 = Asciz	scala/collection/generic/ImmutableMapTemplate$$anonfun$filterNot$1;
const #36 = class	#35;	//  scala/collection/generic/ImmutableMapTemplate$$anonfun$filterNot$1
const #37 = Asciz	(Lscala/collection/generic/ImmutableMapTemplate;Lscala/Function1;Lscala/runtime/ObjectRef;)V;
const #38 = NameAndType	#31:#37;//  "<init>":(Lscala/collection/generic/ImmutableMapTemplate;Lscala/Function1;Lscala/runtime/ObjectRef;)V
const #39 = Method	#36.#38;	//  scala/collection/generic/ImmutableMapTemplate$$anonfun$filterNot$1."<init>":(Lscala/collection/generic/ImmutableMapTemplate;Lscala/Function1;Lscala/runtime/ObjectRef;)V
const #40 = Asciz	scala/collection/generic/IterableTemplate;
const #41 = class	#40;	//  scala/collection/generic/IterableTemplate
const #42 = Asciz	foreach;
const #43 = Asciz	(Lscala/Function1;)V;
const #44 = NameAndType	#42:#43;//  foreach:(Lscala/Function1;)V
const #45 = InterfaceMethod	#41.#44;	//  scala/collection/generic/IterableTemplate.foreach:(Lscala/Function1;)V
const #46 = Asciz	elem;
const #47 = NameAndType	#46:#19;//  elem:Ljava/lang/Object;
const #48 = Field	#24.#47;	//  scala/runtime/ObjectRef.elem:Ljava/lang/Object;
const #49 = Asciz	p$1;
const #50 = Asciz	Lscala/Function1;;
const #51 = Asciz	res$1;
const #52 = Asciz	Lscala/runtime/ObjectRef;;
const #53 = Asciz	transform;
const #54 = Asciz	(Lscala/collection/generic/ImmutableMapTemplate;Lscala/Function2;Lscala/collection/generic/BuilderFactory;)Ljava/lang/Object;;
const #55 = Asciz	scala/collection/generic/BuilderFactory;
const #56 = class	#55;	//  scala/collection/generic/BuilderFactory
const #57 = Asciz	apply;
const #58 = Asciz	(Ljava/lang/Object;)Lscala/collection/generic/Builder;;
const #59 = NameAndType	#57:#58;//  apply:(Ljava/lang/Object;)Lscala/collection/generic/Builder;
const #60 = InterfaceMethod	#56.#59;	//  scala/collection/generic/BuilderFactory.apply:(Ljava/lang/Object;)Lscala/collection/generic/Builder;
const #61 = Asciz	scala/collection/generic/ImmutableMapTemplate$$anonfun$transform$1;
const #62 = class	#61;	//  scala/collection/generic/ImmutableMapTemplate$$anonfun$transform$1
const #63 = Asciz	(Lscala/collection/generic/ImmutableMapTemplate;Lscala/Function2;Lscala/collection/generic/Builder;)V;
const #64 = NameAndType	#31:#63;//  "<init>":(Lscala/collection/generic/ImmutableMapTemplate;Lscala/Function2;Lscala/collection/generic/Builder;)V
const #65 = Method	#62.#64;	//  scala/collection/generic/ImmutableMapTemplate$$anonfun$transform$1."<init>":(Lscala/collection/generic/ImmutableMapTemplate;Lscala/Function2;Lscala/collection/generic/Builder;)V
const #66 = Asciz	scala/collection/generic/Builder;
const #67 = class	#66;	//  scala/collection/generic/Builder
const #68 = Asciz	result;
const #69 = Asciz	()Ljava/lang/Object;;
const #70 = NameAndType	#68:#69;//  result:()Ljava/lang/Object;
const #71 = InterfaceMethod	#67.#70;	//  scala/collection/generic/Builder.result:()Ljava/lang/Object;
const #72 = Asciz	f$1;
const #73 = Asciz	Lscala/Function2;;
const #74 = Asciz	bf;
const #75 = Asciz	Lscala/collection/generic/BuilderFactory;;
const #76 = Asciz	b$1;
const #77 = Asciz	Lscala/collection/generic/Builder;;
const #78 = Asciz	$plus$plus;
const #79 = Asciz	(Lscala/collection/generic/ImmutableMapTemplate;Lscala/collection/Iterator;)Lscala/collection/immutable/Map;;
const #80 = Asciz	scala/collection/immutable/Map;
const #81 = class	#80;	//  scala/collection/immutable/Map
const #82 = Asciz	scala/collection/generic/ImmutableMapTemplate$$anonfun$$plus$plus$2;
const #83 = class	#82;	//  scala/collection/generic/ImmutableMapTemplate$$anonfun$$plus$plus$2
const #84 = NameAndType	#31:#4;//  "<init>":(Lscala/collection/generic/ImmutableMapTemplate;)V
const #85 = Method	#83.#84;	//  scala/collection/generic/ImmutableMapTemplate$$anonfun$$plus$plus$2."<init>":(Lscala/collection/generic/ImmutableMapTemplate;)V
const #86 = Asciz	scala/collection/Iterator;
const #87 = class	#86;	//  scala/collection/Iterator
const #88 = Asciz	$div$colon;
const #89 = Asciz	(Ljava/lang/Object;Lscala/Function2;)Ljava/lang/Object;;
const #90 = NameAndType	#88:#89;//  $div$colon:(Ljava/lang/Object;Lscala/Function2;)Ljava/lang/Object;
const #91 = InterfaceMethod	#87.#90;	//  scala/collection/Iterator.$div$colon:(Ljava/lang/Object;Lscala/Function2;)Ljava/lang/Object;
const #92 = Asciz	iter;
const #93 = Asciz	Lscala/collection/Iterator;;
const #94 = Asciz	(Lscala/collection/generic/ImmutableMapTemplate;Lscala/collection/Traversable;)Lscala/collection/immutable/Map;;
const #95 = Asciz	scala/collection/generic/ImmutableMapTemplate$$anonfun$$plus$plus$1;
const #96 = class	#95;	//  scala/collection/generic/ImmutableMapTemplate$$anonfun$$plus$plus$1
const #97 = Method	#96.#84;	//  scala/collection/generic/ImmutableMapTemplate$$anonfun$$plus$plus$1."<init>":(Lscala/collection/generic/ImmutableMapTemplate;)V
const #98 = InterfaceMethod	#26.#90;	//  scala/collection/generic/TraversableTemplate.$div$colon:(Ljava/lang/Object;Lscala/Function2;)Ljava/lang/Object;
const #99 = Asciz	elems;
const #100 = Asciz	Lscala/collection/Traversable;;
const #101 = Asciz	$plus;
const #102 = Asciz	(Lscala/collection/generic/ImmutableMapTemplate;Lscala/Tuple2;Lscala/Tuple2;Lscala/collection/Sequence;)Lscala/collection/immutable/Map;;
const #103 = Asciz	(Lscala/Tuple2;)Lscala/collection/immutable/Map;;
const #104 = NameAndType	#101:#103;//  $plus:(Lscala/Tuple2;)Lscala/collection/immutable/Map;
const #105 = InterfaceMethod	#13.#104;	//  scala/collection/generic/ImmutableMapTemplate.$plus:(Lscala/Tuple2;)Lscala/collection/immutable/Map;
const #106 = InterfaceMethod	#81.#104;	//  scala/collection/immutable/Map.$plus:(Lscala/Tuple2;)Lscala/collection/immutable/Map;
const #107 = Asciz	(Lscala/collection/Traversable;)Lscala/collection/immutable/Map;;
const #108 = NameAndType	#78:#107;//  $plus$plus:(Lscala/collection/Traversable;)Lscala/collection/immutable/Map;
const #109 = InterfaceMethod	#13.#108;	//  scala/collection/generic/ImmutableMapTemplate.$plus$plus:(Lscala/collection/Traversable;)Lscala/collection/immutable/Map;
const #110 = Asciz	elem1;
const #111 = Asciz	Lscala/Tuple2;;
const #112 = Asciz	elem2;
const #113 = Asciz	Lscala/collection/Sequence;;
const #114 = Asciz	scala/Tuple2;
const #115 = class	#114;	//  scala/Tuple2
const #116 = Asciz	(Ljava/lang/Object;Ljava/lang/Object;)V;
const #117 = NameAndType	#31:#116;//  "<init>":(Ljava/lang/Object;Ljava/lang/Object;)V
const #118 = Method	#115.#117;	//  scala/Tuple2."<init>":(Ljava/lang/Object;Ljava/lang/Object;)V
const #119 = Asciz	Scala;
const #120 = Asciz	InnerClasses;
const #121 = Asciz	$anonfun$filterNot$1;
const #122 = Asciz	$anonfun$transform$1;
const #123 = Asciz	$anonfun$$plus$plus$2;
const #124 = Asciz	$anonfun$$plus$plus$1;
const #125 = Asciz	scala/collection/generic/ImmutableMapTemplate$class;
const #126 = class	#125;	//  scala/collection/generic/ImmutableMapTemplate$class
const #127 = Asciz	java/lang/Object;
const #128 = class	#127;	//  java/lang/Object

{
public static void $init$(scala.collection.generic.ImmutableMapTemplate);
  Code:
   Stack=0, Locals=1, Args_size=1
   0:	return
  LineNumberTable: 
   line 42: 0

  LocalVariableTable: 
   Start  Length  Slot  Name   Signature
   0      1      0    $this       Lscala/collection/generic/ImmutableMapTemplate;


public static scala.collection.immutable.Map update(scala.collection.generic.ImmutableMapTemplate, java.lang.Object, java.lang.Object);
  Code:
   Stack=3, Locals=3, Args_size=3
   0:	aload_0
   1:	aload_1
   2:	aload_2
   3:	invokeinterface	#17,  3; //InterfaceMethod scala/collection/generic/ImmutableMapTemplate.updated:(Ljava/lang/Object;Ljava/lang/Object;)Lscala/collection/immutable/Map;
   8:	areturn
  LineNumberTable: 
   line 114: 0

  LocalVariableTable: 
   Start  Length  Slot  Name   Signature
   0      9      0    $this       Lscala/collection/generic/ImmutableMapTemplate;
   0      9      1    key       Ljava/lang/Object;
   0      9      2    value       Ljava/lang/Object;


public static scala.collection.generic.ImmutableMapTemplate filterNot(scala.collection.generic.ImmutableMapTemplate, scala.Function1);
  Code:
   Stack=6, Locals=3, Args_size=2
   0:	new	#24; //class scala/runtime/ObjectRef
   3:	dup
   4:	aload_0
   5:	invokeinterface	#30,  1; //InterfaceMethod scala/collection/generic/TraversableTemplate.thisCollection:()Lscala/collection/generic/TraversableTemplate;
   10:	checkcast	#13; //class scala/collection/generic/ImmutableMapTemplate
   13:	invokespecial	#34; //Method scala/runtime/ObjectRef."<init>":(Ljava/lang/Object;)V
   16:	astore_2
   17:	aload_0
   18:	new	#36; //class scala/collection/generic/ImmutableMapTemplate$$anonfun$filterNot$1
   21:	dup
   22:	aload_0
   23:	aload_1
   24:	aload_2
   25:	invokespecial	#39; //Method scala/collection/generic/ImmutableMapTemplate$$anonfun$filterNot$1."<init>":(Lscala/collection/generic/ImmutableMapTemplate;Lscala/Function1;Lscala/runtime/ObjectRef;)V
   28:	invokeinterface	#45,  2; //InterfaceMethod scala/collection/generic/IterableTemplate.foreach:(Lscala/Function1;)V
   33:	aload_2
   34:	getfield	#48; //Field scala/runtime/ObjectRef.elem:Ljava/lang/Object;
   37:	checkcast	#13; //class scala/collection/generic/ImmutableMapTemplate
   40:	areturn
  LineNumberTable: 
   line 107: 0
   line 108: 17
   line 110: 33

  LocalVariableTable: 
   Start  Length  Slot  Name   Signature
   0      41      0    $this       Lscala/collection/generic/ImmutableMapTemplate;
   0      41      1    p$1       Lscala/Function1;
   17      23      2    res$1       Lscala/runtime/ObjectRef;


public static java.lang.Object transform(scala.collection.generic.ImmutableMapTemplate, scala.Function2, scala.collection.generic.BuilderFactory);
  Code:
   Stack=6, Locals=4, Args_size=3
   0:	aload_2
   1:	aload_0
   2:	invokeinterface	#30,  1; //InterfaceMethod scala/collection/generic/TraversableTemplate.thisCollection:()Lscala/collection/generic/TraversableTemplate;
   7:	invokeinterface	#60,  2; //InterfaceMethod scala/collection/generic/BuilderFactory.apply:(Ljava/lang/Object;)Lscala/collection/generic/Builder;
   12:	astore_3
   13:	aload_0
   14:	new	#62; //class scala/collection/generic/ImmutableMapTemplate$$anonfun$transform$1
   17:	dup
   18:	aload_0
   19:	aload_1
   20:	aload_3
   21:	invokespecial	#65; //Method scala/collection/generic/ImmutableMapTemplate$$anonfun$transform$1."<init>":(Lscala/collection/generic/ImmutableMapTemplate;Lscala/Function2;Lscala/collection/generic/Builder;)V
   24:	invokeinterface	#45,  2; //InterfaceMethod scala/collection/generic/IterableTemplate.foreach:(Lscala/Function1;)V
   29:	aload_3
   30:	invokeinterface	#71,  1; //InterfaceMethod scala/collection/generic/Builder.result:()Ljava/lang/Object;
   35:	areturn
  LineNumberTable: 
   line 91: 0
   line 92: 13
   line 93: 29

  LocalVariableTable: 
   Start  Length  Slot  Name   Signature
   0      36      0    $this       Lscala/collection/generic/ImmutableMapTemplate;
   0      36      1    f$1       Lscala/Function2;
   0      36      2    bf       Lscala/collection/generic/BuilderFactory;
   13      22      3    b$1       Lscala/collection/generic/Builder;


public static scala.collection.immutable.Map $plus$plus(scala.collection.generic.ImmutableMapTemplate, scala.collection.Iterator);
  Code:
   Stack=5, Locals=3, Args_size=2
   0:	aload_0
   1:	invokeinterface	#30,  1; //InterfaceMethod scala/collection/generic/TraversableTemplate.thisCollection:()Lscala/collection/generic/TraversableTemplate;
   6:	checkcast	#81; //class scala/collection/immutable/Map
   9:	astore_2
   10:	aload_1
   11:	aload_2
   12:	new	#83; //class scala/collection/generic/ImmutableMapTemplate$$anonfun$$plus$plus$2
   15:	dup
   16:	aload_0
   17:	invokespecial	#85; //Method scala/collection/generic/ImmutableMapTemplate$$anonfun$$plus$plus$2."<init>":(Lscala/collection/generic/ImmutableMapTemplate;)V
   20:	invokeinterface	#91,  3; //InterfaceMethod scala/collection/Iterator.$div$colon:(Ljava/lang/Object;Lscala/Function2;)Ljava/lang/Object;
   25:	checkcast	#81; //class scala/collection/immutable/Map
   28:	areturn
  LineNumberTable: 
   line 82: 0

  LocalVariableTable: 
   Start  Length  Slot  Name   Signature
   0      29      0    $this       Lscala/collection/generic/ImmutableMapTemplate;
   0      29      1    iter       Lscala/collection/Iterator;


public static scala.collection.immutable.Map $plus$plus(scala.collection.generic.ImmutableMapTemplate, scala.collection.Traversable);
  Code:
   Stack=5, Locals=3, Args_size=2
   0:	aload_0
   1:	invokeinterface	#30,  1; //InterfaceMethod scala/collection/generic/TraversableTemplate.thisCollection:()Lscala/collection/generic/TraversableTemplate;
   6:	checkcast	#81; //class scala/collection/immutable/Map
   9:	astore_2
   10:	aload_1
   11:	aload_2
   12:	new	#96; //class scala/collection/generic/ImmutableMapTemplate$$anonfun$$plus$plus$1
   15:	dup
   16:	aload_0
   17:	invokespecial	#97; //Method scala/collection/generic/ImmutableMapTemplate$$anonfun$$plus$plus$1."<init>":(Lscala/collection/generic/ImmutableMapTemplate;)V
   20:	invokeinterface	#98,  3; //InterfaceMethod scala/collection/generic/TraversableTemplate.$div$colon:(Ljava/lang/Object;Lscala/Function2;)Ljava/lang/Object;
   25:	checkcast	#81; //class scala/collection/immutable/Map
   28:	areturn
  LineNumberTable: 
   line 74: 0

  LocalVariableTable: 
   Start  Length  Slot  Name   Signature
   0      29      0    $this       Lscala/collection/generic/ImmutableMapTemplate;
   0      29      1    elems       Lscala/collection/Traversable;


public static scala.collection.immutable.Map $plus(scala.collection.generic.ImmutableMapTemplate, scala.Tuple2, scala.Tuple2, scala.collection.Sequence);
  Code:
   Stack=2, Locals=4, Args_size=4
   0:	aload_0
   1:	aload_1
   2:	invokeinterface	#105,  2; //InterfaceMethod scala/collection/generic/ImmutableMapTemplate.$plus:(Lscala/Tuple2;)Lscala/collection/immutable/Map;
   7:	aload_2
   8:	invokeinterface	#106,  2; //InterfaceMethod scala/collection/immutable/Map.$plus:(Lscala/Tuple2;)Lscala/collection/immutable/Map;
   13:	aload_3
   14:	invokeinterface	#109,  2; //InterfaceMethod scala/collection/generic/ImmutableMapTemplate.$plus$plus:(Lscala/collection/Traversable;)Lscala/collection/immutable/Map;
   19:	areturn
  LineNumberTable: 
   line 66: 0

  LocalVariableTable: 
   Start  Length  Slot  Name   Signature
   0      20      0    $this       Lscala/collection/generic/ImmutableMapTemplate;
   0      20      1    elem1       Lscala/Tuple2;
   0      20      2    elem2       Lscala/Tuple2;
   0      20      3    elems       Lscala/collection/Sequence;


public static scala.collection.immutable.Map updated(scala.collection.generic.ImmutableMapTemplate, java.lang.Object, java.lang.Object);
  Code:
   Stack=5, Locals=3, Args_size=3
   0:	aload_0
   1:	new	#115; //class scala/Tuple2
   4:	dup
   5:	aload_1
   6:	aload_2
   7:	invokespecial	#118; //Method scala/Tuple2."<init>":(Ljava/lang/Object;Ljava/lang/Object;)V
   10:	invokeinterface	#105,  2; //InterfaceMethod scala/collection/generic/ImmutableMapTemplate.$plus:(Lscala/Tuple2;)Lscala/collection/immutable/Map;
   15:	areturn
  LineNumberTable: 
   line 50: 0

  LocalVariableTable: 
   Start  Length  Slot  Name   Signature
   0      16      0    $this       Lscala/collection/generic/ImmutableMapTemplate;
   0      16      1    key       Ljava/lang/Object;
   0      16      2    value       Ljava/lang/Object;


}

