Compiled from "ImmutableSortedMapFactory.scala"
public abstract class scala.collection.generic.ImmutableSortedMapFactory extends scala.collection.generic.SortedMapFactory implements scala.ScalaObject
  SourceFile: "ImmutableSortedMapFactory.scala"
  Signature: length = 0x2
   00 1F 
  ScalaSig: length = 0x1EC
   05 00 4B 06 05 01 02 FFFFFF81 00 09 02 19 49 6D 6D 75
   74 61 62 6C 65 53 6F 72 74 65 64 4D 61 70 46 61
   63 74 6F 72 79 0A 02 03 04 01 07 67 65 6E 65 72
   69 63 0A 02 05 06 01 0A 63 6F 6C 6C 65 63 74 69
   6F 6E 0A 01 07 01 05 73 63 61 6C 61 03 00 15 02
   0A 11 13 03 00 0B 30 10 03 0C 0D 0F 0D 01 02 09
   02 0E 02 02 10 53 6F 72 74 65 64 4D 61 70 46 61
   63 74 6F 72 79 10 02 10 11 0C 00 04 05 12 00 FFFFFFC2
   00 13 02 02 43 43 15 03 14 23 2A 11 02 15 19 10
   02 16 17 0D 01 06 09 02 18 06 02 07 4E 6F 74 68
   69 6E 67 12 03 1A 1C 2C 06 08 1B 02 FFFFFF84 FFFFFF80 FFFFFF80 FFFFFF80
   00 19 02 0C 3C 72 65 66 69 6E 65 6D 65 6E 74 3E
   10 04 1D 20 22 29 0D 01 1E 0A 02 1F 04 01 09 69
   6D 6D 75 74 61 62 6C 65 09 02 21 1E 02 09 53 6F
   72 74 65 64 4D 61 70 10 02 10 23 04 08 24 11 FFFFFF84
   FFFFFF80 FFFFFF80 FFFFFFC2 00 25 02 01 41 11 02 15 26 10 02 16 27
   09 02 28 06 02 03 41 6E 79 10 02 10 2A 04 08 2B
   11 FFFFFF84 FFFFFF80 FFFFFF80 FFFFFFC2 00 25 02 01 42 10 05 0C 2D 22 29
   2F 09 02 2E 02 02 11 53 6F 72 74 65 64 4D 61 70
   54 65 6D 70 6C 61 74 65 10 04 10 11 22 29 10 02
   16 31 09 02 32 06 02 0B 53 63 61 6C 61 4F 62 6A
   65 63 74 08 05 34 00 FFFFFF84 00 35 01 06 3C 69 6E 69
   74 3E 14 01 36 10 03 0C 00 0F 08 05 38 00 FFFFFF84 00
   39 01 0A 6E 65 77 42 75 69 6C 64 65 72 15 03 3A
   42 44 16 02 3B 46 10 04 0C 3C 3E 45 09 02 3D 02
   02 07 42 75 69 6C 64 65 72 10 04 16 3F 41 43 09
   02 40 06 02 06 54 75 70 6C 65 32 10 02 10 42 04
   08 24 37 FFFFFF84 FFFFFF80 FFFFFF80 FFFFFFC2 00 25 10 02 10 44 04 08 2B
   37 FFFFFF84 FFFFFF80 FFFFFF80 FFFFFFC2 00 25 10 04 10 11 41 43 08 05 47
   37 FFFFFFC0 01 48 01 03 6F 72 64 10 03 16 49 41 09 02
   4A 06 02 08 4F 72 64 65 72 69 6E 67 
  minor version: 0
  major version: 49
  Constant pool:
const #1 = Asciz	SourceFile;
const #2 = Asciz	ImmutableSortedMapFactory.scala;
const #3 = Asciz	<init>;
const #4 = Asciz	()V;
const #5 = Asciz	Code;
const #6 = Asciz	LineNumberTable;
const #7 = Asciz	scala/collection/generic/SortedMapFactory;
const #8 = class	#7;	//  scala/collection/generic/SortedMapFactory
const #9 = NameAndType	#3:#4;//  "<init>":()V
const #10 = Method	#8.#9;	//  scala/collection/generic/SortedMapFactory."<init>":()V
const #11 = Asciz	Signature;
const #12 = Asciz	newBuilder;
const #13 = Asciz	(Lscala/Ordering;)Lscala/collection/generic/Builder;;
const #14 = Asciz	scala/collection/generic/MapBuilder;
const #15 = class	#14;	//  scala/collection/generic/MapBuilder
const #16 = Asciz	scala/collection/generic/ImmutableSortedMapFactory;
const #17 = class	#16;	//  scala/collection/generic/ImmutableSortedMapFactory
const #18 = Asciz	empty;
const #19 = Asciz	(Lscala/Ordering;)Lscala/collection/SortedMap;;
const #20 = NameAndType	#18:#19;//  empty:(Lscala/Ordering;)Lscala/collection/SortedMap;
const #21 = Method	#17.#20;	//  scala/collection/generic/ImmutableSortedMapFactory.empty:(Lscala/Ordering;)Lscala/collection/SortedMap;
const #22 = Asciz	(Lscala/collection/Map;)V;
const #23 = NameAndType	#3:#22;//  "<init>":(Lscala/collection/Map;)V
const #24 = Method	#15.#23;	//  scala/collection/generic/MapBuilder."<init>":(Lscala/collection/Map;)V
const #25 = Asciz	this;
const #26 = Asciz	Lscala/collection/generic/ImmutableSortedMapFactory;;
const #27 = Asciz	ord;
const #28 = Asciz	Lscala/Ordering;;
const #29 = Asciz	LocalVariableTable;
const #30 = Asciz	<A:Ljava/lang/Object;B:Ljava/lang/Object;>(Lscala/Ordering<TA;>;)Lscala/collection/generic/Builder<Lscala/Tuple2<TA;TB;>;TCC;>;;
const #31 = Asciz	<CC:Lscala/collection/immutable/SortedMap<Ljava/lang/Object;Ljava/lang/Object;>;>Lscala/collection/generic/SortedMapFactory<TCC;>;Lscala/ScalaObject;;
const #32 = Asciz	ScalaSig;
const #33 = Asciz	scala/ScalaObject;
const #34 = class	#33;	//  scala/ScalaObject

{
public scala.collection.generic.ImmutableSortedMapFactory();
  Code:
   Stack=1, Locals=1, Args_size=1
   0:	aload_0
   1:	invokespecial	#10; //Method scala/collection/generic/SortedMapFactory."<init>":()V
   4:	return
  LineNumberTable: 
   line 18: 0

  Signature: length = 0x2
   00 04 

public scala.collection.generic.Builder newBuilder(scala.Ordering);
  Code:
   Stack=4, Locals=2, Args_size=2
   0:	new	#15; //class scala/collection/generic/MapBuilder
   3:	dup
   4:	aload_0
   5:	aload_1
   6:	invokevirtual	#21; //Method empty:(Lscala/Ordering;)Lscala/collection/SortedMap;
   9:	invokespecial	#24; //Method scala/collection/generic/MapBuilder."<init>":(Lscala/collection/Map;)V
   12:	areturn
  LineNumberTable: 
   line 21: 0

  LocalVariableTable: 
   Start  Length  Slot  Name   Signature
   0      13      0    this       Lscala/collection/generic/ImmutableSortedMapFactory;
   0      13      1    ord       Lscala/Ordering;

  Signature: length = 0x2
   00 1E 

}

