Compiled from "IterableProxyTemplate.scala"
public abstract class scala.collection.generic.IterableProxyTemplate$class extends java.lang.Object
  SourceFile: "IterableProxyTemplate.scala"
  Scala: length = 0x
   
  minor version: 0
  major version: 49
  Constant pool:
const #1 = Asciz	SourceFile;
const #2 = Asciz	IterableProxyTemplate.scala;
const #3 = Asciz	$init$;
const #4 = Asciz	(Lscala/collection/generic/IterableProxyTemplate;)V;
const #5 = Asciz	Code;
const #6 = Asciz	LineNumberTable;
const #7 = Asciz	$this;
const #8 = Asciz	Lscala/collection/generic/IterableProxyTemplate;;
const #9 = Asciz	LocalVariableTable;
const #10 = Asciz	view;
const #11 = Asciz	(Lscala/collection/generic/IterableProxyTemplate;II)Lscala/collection/generic/IterableView;;
const #12 = Asciz	scala/collection/generic/TraversableProxyTemplate;
const #13 = class	#12;	//  scala/collection/generic/TraversableProxyTemplate
const #14 = Asciz	self;
const #15 = Asciz	()Lscala/collection/generic/TraversableTemplate;;
const #16 = NameAndType	#14:#15;//  self:()Lscala/collection/generic/TraversableTemplate;
const #17 = InterfaceMethod	#13.#16;	//  scala/collection/generic/TraversableProxyTemplate.self:()Lscala/collection/generic/TraversableTemplate;
const #18 = Asciz	scala/collection/generic/IterableTemplate;
const #19 = class	#18;	//  scala/collection/generic/IterableTemplate
const #20 = Asciz	(II)Lscala/collection/generic/IterableView;;
const #21 = NameAndType	#10:#20;//  view:(II)Lscala/collection/generic/IterableView;
const #22 = InterfaceMethod	#19.#21;	//  scala/collection/generic/IterableTemplate.view:(II)Lscala/collection/generic/IterableView;
const #23 = Asciz	from;
const #24 = Asciz	I;
const #25 = Asciz	until;
const #26 = Asciz	(Lscala/collection/generic/IterableProxyTemplate;)Ljava/lang/Object;;
const #27 = Asciz	()Ljava/lang/Object;;
const #28 = NameAndType	#10:#27;//  view:()Ljava/lang/Object;
const #29 = InterfaceMethod	#19.#28;	//  scala/collection/generic/IterableTemplate.view:()Ljava/lang/Object;
const #30 = Asciz	toStream;
const #31 = Asciz	(Lscala/collection/generic/IterableProxyTemplate;)Lscala/collection/immutable/Stream;;
const #32 = Asciz	()Lscala/collection/immutable/Stream;;
const #33 = NameAndType	#30:#32;//  toStream:()Lscala/collection/immutable/Stream;
const #34 = InterfaceMethod	#19.#33;	//  scala/collection/generic/IterableTemplate.toStream:()Lscala/collection/immutable/Stream;
const #35 = Asciz	sameElements;
const #36 = Asciz	(Lscala/collection/generic/IterableProxyTemplate;Lscala/collection/Iterable;)Z;
const #37 = Asciz	(Lscala/collection/Iterable;)Z;
const #38 = NameAndType	#35:#37;//  sameElements:(Lscala/collection/Iterable;)Z
const #39 = InterfaceMethod	#19.#38;	//  scala/collection/generic/IterableTemplate.sameElements:(Lscala/collection/Iterable;)Z
const #40 = Asciz	that;
const #41 = Asciz	Lscala/collection/Iterable;;
const #42 = Asciz	dropRight;
const #43 = Asciz	(Lscala/collection/generic/IterableProxyTemplate;I)Lscala/collection/generic/IterableTemplate;;
const #44 = Asciz	(I)Lscala/collection/generic/IterableTemplate;;
const #45 = NameAndType	#42:#44;//  dropRight:(I)Lscala/collection/generic/IterableTemplate;
const #46 = InterfaceMethod	#19.#45;	//  scala/collection/generic/IterableTemplate.dropRight:(I)Lscala/collection/generic/IterableTemplate;
const #47 = Asciz	n;
const #48 = Asciz	takeRight;
const #49 = NameAndType	#48:#44;//  takeRight:(I)Lscala/collection/generic/IterableTemplate;
const #50 = InterfaceMethod	#19.#49;	//  scala/collection/generic/IterableTemplate.takeRight:(I)Lscala/collection/generic/IterableTemplate;
const #51 = Asciz	head;
const #52 = NameAndType	#51:#27;//  head:()Ljava/lang/Object;
const #53 = InterfaceMethod	#19.#52;	//  scala/collection/generic/IterableTemplate.head:()Ljava/lang/Object;
const #54 = Asciz	toIterable;
const #55 = Asciz	(Lscala/collection/generic/IterableProxyTemplate;)Lscala/collection/Iterable;;
const #56 = Asciz	()Lscala/collection/Iterable;;
const #57 = NameAndType	#54:#56;//  toIterable:()Lscala/collection/Iterable;
const #58 = InterfaceMethod	#19.#57;	//  scala/collection/generic/IterableTemplate.toIterable:()Lscala/collection/Iterable;
const #59 = Asciz	reduceRight;
const #60 = Asciz	(Lscala/collection/generic/IterableProxyTemplate;Lscala/Function2;)Ljava/lang/Object;;
const #61 = Asciz	(Lscala/Function2;)Ljava/lang/Object;;
const #62 = NameAndType	#59:#61;//  reduceRight:(Lscala/Function2;)Ljava/lang/Object;
const #63 = InterfaceMethod	#19.#62;	//  scala/collection/generic/IterableTemplate.reduceRight:(Lscala/Function2;)Ljava/lang/Object;
const #64 = Asciz	op;
const #65 = Asciz	Lscala/Function2;;
const #66 = Asciz	foldRight;
const #67 = Asciz	(Lscala/collection/generic/IterableProxyTemplate;Ljava/lang/Object;Lscala/Function2;)Ljava/lang/Object;;
const #68 = Asciz	(Ljava/lang/Object;Lscala/Function2;)Ljava/lang/Object;;
const #69 = NameAndType	#66:#68;//  foldRight:(Ljava/lang/Object;Lscala/Function2;)Ljava/lang/Object;
const #70 = InterfaceMethod	#19.#69;	//  scala/collection/generic/IterableTemplate.foldRight:(Ljava/lang/Object;Lscala/Function2;)Ljava/lang/Object;
const #71 = Asciz	z;
const #72 = Asciz	Ljava/lang/Object;;
const #73 = Asciz	isEmpty;
const #74 = Asciz	(Lscala/collection/generic/IterableProxyTemplate;)Z;
const #75 = Asciz	()Z;
const #76 = NameAndType	#73:#75;//  isEmpty:()Z
const #77 = InterfaceMethod	#19.#76;	//  scala/collection/generic/IterableTemplate.isEmpty:()Z
const #78 = Asciz	foreach;
const #79 = Asciz	(Lscala/collection/generic/IterableProxyTemplate;Lscala/Function1;)V;
const #80 = Asciz	(Lscala/Function1;)V;
const #81 = NameAndType	#78:#80;//  foreach:(Lscala/Function1;)V
const #82 = InterfaceMethod	#19.#81;	//  scala/collection/generic/IterableTemplate.foreach:(Lscala/Function1;)V
const #83 = Asciz	f;
const #84 = Asciz	Lscala/Function1;;
const #85 = Asciz	iterator;
const #86 = Asciz	(Lscala/collection/generic/IterableProxyTemplate;)Lscala/collection/Iterator;;
const #87 = Asciz	()Lscala/collection/Iterator;;
const #88 = NameAndType	#85:#87;//  iterator:()Lscala/collection/Iterator;
const #89 = InterfaceMethod	#19.#88;	//  scala/collection/generic/IterableTemplate.iterator:()Lscala/collection/Iterator;
const #90 = Asciz	Scala;
const #91 = Asciz	scala/collection/generic/IterableProxyTemplate$class;
const #92 = class	#91;	//  scala/collection/generic/IterableProxyTemplate$class
const #93 = Asciz	java/lang/Object;
const #94 = class	#93;	//  java/lang/Object

{
public static void $init$(scala.collection.generic.IterableProxyTemplate);
  Code:
   Stack=0, Locals=1, Args_size=1
   0:	return
  LineNumberTable: 
   line 27: 0

  LocalVariableTable: 
   Start  Length  Slot  Name   Signature
   0      1      0    $this       Lscala/collection/generic/IterableProxyTemplate;


public static scala.collection.generic.IterableView view(scala.collection.generic.IterableProxyTemplate, int, int);
  Code:
   Stack=3, Locals=3, Args_size=3
   0:	aload_0
   1:	invokeinterface	#17,  1; //InterfaceMethod scala/collection/generic/TraversableProxyTemplate.self:()Lscala/collection/generic/TraversableTemplate;
   6:	checkcast	#19; //class scala/collection/generic/IterableTemplate
   9:	iload_1
   10:	iload_2
   11:	invokeinterface	#22,  3; //InterfaceMethod scala/collection/generic/IterableTemplate.view:(II)Lscala/collection/generic/IterableView;
   16:	areturn
  LineNumberTable: 
   line 42: 0

  LocalVariableTable: 
   Start  Length  Slot  Name   Signature
   0      17      0    $this       Lscala/collection/generic/IterableProxyTemplate;
   0      17      1    from       I
   0      17      2    until       I


public static java.lang.Object view(scala.collection.generic.IterableProxyTemplate);
  Code:
   Stack=1, Locals=1, Args_size=1
   0:	aload_0
   1:	invokeinterface	#17,  1; //InterfaceMethod scala/collection/generic/TraversableProxyTemplate.self:()Lscala/collection/generic/TraversableTemplate;
   6:	checkcast	#19; //class scala/collection/generic/IterableTemplate
   9:	invokeinterface	#29,  1; //InterfaceMethod scala/collection/generic/IterableTemplate.view:()Ljava/lang/Object;
   14:	areturn
  LineNumberTable: 
   line 41: 0

  LocalVariableTable: 
   Start  Length  Slot  Name   Signature
   0      15      0    $this       Lscala/collection/generic/IterableProxyTemplate;


public static scala.collection.immutable.Stream toStream(scala.collection.generic.IterableProxyTemplate);
  Code:
   Stack=1, Locals=1, Args_size=1
   0:	aload_0
   1:	invokeinterface	#17,  1; //InterfaceMethod scala/collection/generic/TraversableProxyTemplate.self:()Lscala/collection/generic/TraversableTemplate;
   6:	checkcast	#19; //class scala/collection/generic/IterableTemplate
   9:	invokeinterface	#34,  1; //InterfaceMethod scala/collection/generic/IterableTemplate.toStream:()Lscala/collection/immutable/Stream;
   14:	areturn
  LineNumberTable: 
   line 40: 0

  LocalVariableTable: 
   Start  Length  Slot  Name   Signature
   0      15      0    $this       Lscala/collection/generic/IterableProxyTemplate;


public static boolean sameElements(scala.collection.generic.IterableProxyTemplate, scala.collection.Iterable);
  Code:
   Stack=2, Locals=2, Args_size=2
   0:	aload_0
   1:	invokeinterface	#17,  1; //InterfaceMethod scala/collection/generic/TraversableProxyTemplate.self:()Lscala/collection/generic/TraversableTemplate;
   6:	checkcast	#19; //class scala/collection/generic/IterableTemplate
   9:	aload_1
   10:	invokeinterface	#39,  2; //InterfaceMethod scala/collection/generic/IterableTemplate.sameElements:(Lscala/collection/Iterable;)Z
   15:	ireturn
  LineNumberTable: 
   line 39: 0

  LocalVariableTable: 
   Start  Length  Slot  Name   Signature
   0      16      0    $this       Lscala/collection/generic/IterableProxyTemplate;
   0      16      1    that       Lscala/collection/Iterable;


public static scala.collection.generic.IterableTemplate dropRight(scala.collection.generic.IterableProxyTemplate, int);
  Code:
   Stack=2, Locals=2, Args_size=2
   0:	aload_0
   1:	invokeinterface	#17,  1; //InterfaceMethod scala/collection/generic/TraversableProxyTemplate.self:()Lscala/collection/generic/TraversableTemplate;
   6:	checkcast	#19; //class scala/collection/generic/IterableTemplate
   9:	iload_1
   10:	invokeinterface	#46,  2; //InterfaceMethod scala/collection/generic/IterableTemplate.dropRight:(I)Lscala/collection/generic/IterableTemplate;
   15:	areturn
  LineNumberTable: 
   line 38: 0

  LocalVariableTable: 
   Start  Length  Slot  Name   Signature
   0      16      0    $this       Lscala/collection/generic/IterableProxyTemplate;
   0      16      1    n       I


public static scala.collection.generic.IterableTemplate takeRight(scala.collection.generic.IterableProxyTemplate, int);
  Code:
   Stack=2, Locals=2, Args_size=2
   0:	aload_0
   1:	invokeinterface	#17,  1; //InterfaceMethod scala/collection/generic/TraversableProxyTemplate.self:()Lscala/collection/generic/TraversableTemplate;
   6:	checkcast	#19; //class scala/collection/generic/IterableTemplate
   9:	iload_1
   10:	invokeinterface	#50,  2; //InterfaceMethod scala/collection/generic/IterableTemplate.takeRight:(I)Lscala/collection/generic/IterableTemplate;
   15:	areturn
  LineNumberTable: 
   line 37: 0

  LocalVariableTable: 
   Start  Length  Slot  Name   Signature
   0      16      0    $this       Lscala/collection/generic/IterableProxyTemplate;
   0      16      1    n       I


public static java.lang.Object head(scala.collection.generic.IterableProxyTemplate);
  Code:
   Stack=1, Locals=1, Args_size=1
   0:	aload_0
   1:	invokeinterface	#17,  1; //InterfaceMethod scala/collection/generic/TraversableProxyTemplate.self:()Lscala/collection/generic/TraversableTemplate;
   6:	checkcast	#19; //class scala/collection/generic/IterableTemplate
   9:	invokeinterface	#53,  1; //InterfaceMethod scala/collection/generic/IterableTemplate.head:()Ljava/lang/Object;
   14:	areturn
  LineNumberTable: 
   line 36: 0

  LocalVariableTable: 
   Start  Length  Slot  Name   Signature
   0      15      0    $this       Lscala/collection/generic/IterableProxyTemplate;


public static scala.collection.Iterable toIterable(scala.collection.generic.IterableProxyTemplate);
  Code:
   Stack=1, Locals=1, Args_size=1
   0:	aload_0
   1:	invokeinterface	#17,  1; //InterfaceMethod scala/collection/generic/TraversableProxyTemplate.self:()Lscala/collection/generic/TraversableTemplate;
   6:	checkcast	#19; //class scala/collection/generic/IterableTemplate
   9:	invokeinterface	#58,  1; //InterfaceMethod scala/collection/generic/IterableTemplate.toIterable:()Lscala/collection/Iterable;
   14:	areturn
  LineNumberTable: 
   line 35: 0

  LocalVariableTable: 
   Start  Length  Slot  Name   Signature
   0      15      0    $this       Lscala/collection/generic/IterableProxyTemplate;


public static java.lang.Object reduceRight(scala.collection.generic.IterableProxyTemplate, scala.Function2);
  Code:
   Stack=2, Locals=2, Args_size=2
   0:	aload_0
   1:	invokeinterface	#17,  1; //InterfaceMethod scala/collection/generic/TraversableProxyTemplate.self:()Lscala/collection/generic/TraversableTemplate;
   6:	checkcast	#19; //class scala/collection/generic/IterableTemplate
   9:	aload_1
   10:	invokeinterface	#63,  2; //InterfaceMethod scala/collection/generic/IterableTemplate.reduceRight:(Lscala/Function2;)Ljava/lang/Object;
   15:	areturn
  LineNumberTable: 
   line 34: 0

  LocalVariableTable: 
   Start  Length  Slot  Name   Signature
   0      16      0    $this       Lscala/collection/generic/IterableProxyTemplate;
   0      16      1    op       Lscala/Function2;


public static java.lang.Object foldRight(scala.collection.generic.IterableProxyTemplate, java.lang.Object, scala.Function2);
  Code:
   Stack=3, Locals=3, Args_size=3
   0:	aload_0
   1:	invokeinterface	#17,  1; //InterfaceMethod scala/collection/generic/TraversableProxyTemplate.self:()Lscala/collection/generic/TraversableTemplate;
   6:	checkcast	#19; //class scala/collection/generic/IterableTemplate
   9:	aload_1
   10:	aload_2
   11:	invokeinterface	#70,  3; //InterfaceMethod scala/collection/generic/IterableTemplate.foldRight:(Ljava/lang/Object;Lscala/Function2;)Ljava/lang/Object;
   16:	areturn
  LineNumberTable: 
   line 33: 0

  LocalVariableTable: 
   Start  Length  Slot  Name   Signature
   0      17      0    $this       Lscala/collection/generic/IterableProxyTemplate;
   0      17      1    z       Ljava/lang/Object;
   0      17      2    op       Lscala/Function2;


public static boolean isEmpty(scala.collection.generic.IterableProxyTemplate);
  Code:
   Stack=1, Locals=1, Args_size=1
   0:	aload_0
   1:	invokeinterface	#17,  1; //InterfaceMethod scala/collection/generic/TraversableProxyTemplate.self:()Lscala/collection/generic/TraversableTemplate;
   6:	checkcast	#19; //class scala/collection/generic/IterableTemplate
   9:	invokeinterface	#77,  1; //InterfaceMethod scala/collection/generic/IterableTemplate.isEmpty:()Z
   14:	ireturn
  LineNumberTable: 
   line 32: 0

  LocalVariableTable: 
   Start  Length  Slot  Name   Signature
   0      15      0    $this       Lscala/collection/generic/IterableProxyTemplate;


public static void foreach(scala.collection.generic.IterableProxyTemplate, scala.Function1);
  Code:
   Stack=2, Locals=2, Args_size=2
   0:	aload_0
   1:	invokeinterface	#17,  1; //InterfaceMethod scala/collection/generic/TraversableProxyTemplate.self:()Lscala/collection/generic/TraversableTemplate;
   6:	checkcast	#19; //class scala/collection/generic/IterableTemplate
   9:	aload_1
   10:	invokeinterface	#82,  2; //InterfaceMethod scala/collection/generic/IterableTemplate.foreach:(Lscala/Function1;)V
   15:	return
  LineNumberTable: 
   line 31: 0

  LocalVariableTable: 
   Start  Length  Slot  Name   Signature
   0      16      0    $this       Lscala/collection/generic/IterableProxyTemplate;
   0      16      1    f       Lscala/Function1;


public static scala.collection.Iterator iterator(scala.collection.generic.IterableProxyTemplate);
  Code:
   Stack=1, Locals=1, Args_size=1
   0:	aload_0
   1:	invokeinterface	#17,  1; //InterfaceMethod scala/collection/generic/TraversableProxyTemplate.self:()Lscala/collection/generic/TraversableTemplate;
   6:	checkcast	#19; //class scala/collection/generic/IterableTemplate
   9:	invokeinterface	#89,  1; //InterfaceMethod scala/collection/generic/IterableTemplate.iterator:()Lscala/collection/Iterator;
   14:	areturn
  LineNumberTable: 
   line 30: 0

  LocalVariableTable: 
   Start  Length  Slot  Name   Signature
   0      15      0    $this       Lscala/collection/generic/IterableProxyTemplate;


}

