Compiled from "IterableTemplate.scala"
public abstract class scala.collection.generic.IterableTemplate$class extends java.lang.Object
  SourceFile: "IterableTemplate.scala"
  Scala: length = 0x
   
  InnerClass: 
   public final #185= #49 of #13; //$anon$1=class scala/collection/generic/IterableTemplate$$anon$1 of class scala/collection/generic/IterableTemplate
   public final #186= #101 of #13; //$anonfun$dropRight$1=class scala/collection/generic/IterableTemplate$$anonfun$dropRight$1 of class scala/collection/generic/IterableTemplate
   public final #187= #134 of #13; //$anonfun$takeRight$1=class scala/collection/generic/IterableTemplate$$anonfun$takeRight$1 of class scala/collection/generic/IterableTemplate
  minor version: 0
  major version: 49
  Constant pool:
const #1 = Asciz	SourceFile;
const #2 = Asciz	IterableTemplate.scala;
const #3 = Asciz	$init$;
const #4 = Asciz	(Lscala/collection/generic/IterableTemplate;)V;
const #5 = Asciz	Code;
const #6 = Asciz	LineNumberTable;
const #7 = Asciz	$this;
const #8 = Asciz	Lscala/collection/generic/IterableTemplate;;
const #9 = Asciz	LocalVariableTable;
const #10 = Asciz	projection;
const #11 = Asciz	(Lscala/collection/generic/IterableTemplate;)Ljava/lang/Object;;
const #12 = Asciz	scala/collection/generic/IterableTemplate;
const #13 = class	#12;	//  scala/collection/generic/IterableTemplate
const #14 = Asciz	view;
const #15 = Asciz	()Ljava/lang/Object;;
const #16 = NameAndType	#14:#15;//  view:()Ljava/lang/Object;
const #17 = InterfaceMethod	#13.#16;	//  scala/collection/generic/IterableTemplate.view:()Ljava/lang/Object;
const #18 = Asciz	toSeq;
const #19 = Asciz	(Lscala/collection/generic/IterableTemplate;)Lscala/collection/Sequence;;
const #20 = Asciz	scala/collection/generic/TraversableTemplate;
const #21 = class	#20;	//  scala/collection/generic/TraversableTemplate
const #22 = Asciz	toSequence;
const #23 = Asciz	()Lscala/collection/Sequence;;
const #24 = NameAndType	#22:#23;//  toSequence:()Lscala/collection/Sequence;
const #25 = InterfaceMethod	#21.#24;	//  scala/collection/generic/TraversableTemplate.toSequence:()Lscala/collection/Sequence;
const #26 = Asciz	firstOption;
const #27 = Asciz	(Lscala/collection/generic/IterableTemplate;)Lscala/Option;;
const #28 = Asciz	headOption;
const #29 = Asciz	()Lscala/Option;;
const #30 = NameAndType	#28:#29;//  headOption:()Lscala/Option;
const #31 = InterfaceMethod	#21.#30;	//  scala/collection/generic/TraversableTemplate.headOption:()Lscala/Option;
const #32 = Asciz	first;
const #33 = Asciz	head;
const #34 = NameAndType	#33:#15;//  head:()Ljava/lang/Object;
const #35 = InterfaceMethod	#13.#34;	//  scala/collection/generic/IterableTemplate.head:()Ljava/lang/Object;
const #36 = Asciz	(Lscala/collection/generic/IterableTemplate;II)Lscala/collection/generic/IterableView;;
const #37 = Asciz	scala/collection/generic/TraversableViewTemplate;
const #38 = class	#37;	//  scala/collection/generic/TraversableViewTemplate
const #39 = Asciz	slice;
const #40 = Asciz	(II)Lscala/collection/generic/TraversableView;;
const #41 = NameAndType	#39:#40;//  slice:(II)Lscala/collection/generic/TraversableView;
const #42 = InterfaceMethod	#38.#41;	//  scala/collection/generic/TraversableViewTemplate.slice:(II)Lscala/collection/generic/TraversableView;
const #43 = Asciz	scala/collection/generic/IterableView;
const #44 = class	#43;	//  scala/collection/generic/IterableView
const #45 = Asciz	from;
const #46 = Asciz	I;
const #47 = Asciz	until;
const #48 = Asciz	scala/collection/generic/IterableTemplate$$anon$1;
const #49 = class	#48;	//  scala/collection/generic/IterableTemplate$$anon$1
const #50 = Asciz	<init>;
const #51 = NameAndType	#50:#4;//  "<init>":(Lscala/collection/generic/IterableTemplate;)V
const #52 = Method	#49.#51;	//  scala/collection/generic/IterableTemplate$$anon$1."<init>":(Lscala/collection/generic/IterableTemplate;)V
const #53 = Asciz	toStream;
const #54 = Asciz	(Lscala/collection/generic/IterableTemplate;)Lscala/collection/immutable/Stream;;
const #55 = Asciz	iterator;
const #56 = Asciz	()Lscala/collection/Iterator;;
const #57 = NameAndType	#55:#56;//  iterator:()Lscala/collection/Iterator;
const #58 = InterfaceMethod	#13.#57;	//  scala/collection/generic/IterableTemplate.iterator:()Lscala/collection/Iterator;
const #59 = Asciz	scala/collection/Iterator;
const #60 = class	#59;	//  scala/collection/Iterator
const #61 = Asciz	()Lscala/collection/immutable/Stream;;
const #62 = NameAndType	#53:#61;//  toStream:()Lscala/collection/immutable/Stream;
const #63 = InterfaceMethod	#60.#62;	//  scala/collection/Iterator.toStream:()Lscala/collection/immutable/Stream;
const #64 = Asciz	sameElements;
const #65 = Asciz	(Lscala/collection/generic/IterableTemplate;Lscala/collection/Iterable;)Z;
const #66 = Asciz	hasNext;
const #67 = Asciz	()Z;
const #68 = NameAndType	#66:#67;//  hasNext:()Z
const #69 = InterfaceMethod	#60.#68;	//  scala/collection/Iterator.hasNext:()Z
const #70 = Asciz	next;
const #71 = NameAndType	#70:#15;//  next:()Ljava/lang/Object;
const #72 = InterfaceMethod	#60.#71;	//  scala/collection/Iterator.next:()Ljava/lang/Object;
const #73 = Asciz	scala/runtime/BoxesRunTime;
const #74 = class	#73;	//  scala/runtime/BoxesRunTime
const #75 = Asciz	equals;
const #76 = Asciz	(Ljava/lang/Object;Ljava/lang/Object;)Z;
const #77 = NameAndType	#75:#76;//  equals:(Ljava/lang/Object;Ljava/lang/Object;)Z
const #78 = Method	#74.#77;	//  scala/runtime/BoxesRunTime.equals:(Ljava/lang/Object;Ljava/lang/Object;)Z
const #79 = Asciz	that;
const #80 = Asciz	Lscala/collection/Iterable;;
const #81 = Asciz	these;
const #82 = Asciz	Lscala/collection/Iterator;;
const #83 = Asciz	those;
const #84 = Asciz	dropRight;
const #85 = Asciz	(Lscala/collection/generic/IterableTemplate;I)Lscala/collection/generic/IterableTemplate;;
const #86 = Asciz	newBuilder;
const #87 = Asciz	()Lscala/collection/generic/Builder;;
const #88 = NameAndType	#86:#87;//  newBuilder:()Lscala/collection/generic/Builder;
const #89 = InterfaceMethod	#21.#88;	//  scala/collection/generic/TraversableTemplate.newBuilder:()Lscala/collection/generic/Builder;
const #90 = Asciz	drop;
const #91 = Asciz	(I)Lscala/collection/Iterator;;
const #92 = NameAndType	#90:#91;//  drop:(I)Lscala/collection/Iterator;
const #93 = InterfaceMethod	#60.#92;	//  scala/collection/Iterator.drop:(I)Lscala/collection/Iterator;
const #94 = Asciz	scala/util/control/Breaks$;
const #95 = class	#94;	//  scala/util/control/Breaks$
const #96 = Asciz	MODULE$;
const #97 = Asciz	Lscala/util/control/Breaks$;;
const #98 = NameAndType	#96:#97;//  MODULE$:Lscala/util/control/Breaks$;
const #99 = Field	#95.#98;	//  scala/util/control/Breaks$.MODULE$:Lscala/util/control/Breaks$;
const #100 = Asciz	scala/collection/generic/IterableTemplate$$anonfun$dropRight$1;
const #101 = class	#100;	//  scala/collection/generic/IterableTemplate$$anonfun$dropRight$1
const #102 = Asciz	(Lscala/collection/generic/IterableTemplate;Lscala/collection/generic/Builder;Lscala/collection/Iterator;)V;
const #103 = NameAndType	#50:#102;//  "<init>":(Lscala/collection/generic/IterableTemplate;Lscala/collection/generic/Builder;Lscala/collection/Iterator;)V
const #104 = Method	#101.#103;	//  scala/collection/generic/IterableTemplate$$anonfun$dropRight$1."<init>":(Lscala/collection/generic/IterableTemplate;Lscala/collection/generic/Builder;Lscala/collection/Iterator;)V
const #105 = Asciz	breakable;
const #106 = Asciz	(Lscala/Function0;)V;
const #107 = NameAndType	#105:#106;//  breakable:(Lscala/Function0;)V
const #108 = Method	#95.#107;	//  scala/util/control/Breaks$.breakable:(Lscala/Function0;)V
const #109 = Asciz	scala/collection/generic/Builder;
const #110 = class	#109;	//  scala/collection/generic/Builder
const #111 = Asciz	result;
const #112 = NameAndType	#111:#15;//  result:()Ljava/lang/Object;
const #113 = InterfaceMethod	#110.#112;	//  scala/collection/generic/Builder.result:()Ljava/lang/Object;
const #114 = Asciz	scala/runtime/ScalaRunTime$;
const #115 = class	#114;	//  scala/runtime/ScalaRunTime$
const #116 = Asciz	Lscala/runtime/ScalaRunTime$;;
const #117 = NameAndType	#96:#116;//  MODULE$:Lscala/runtime/ScalaRunTime$;
const #118 = Field	#115.#117;	//  scala/runtime/ScalaRunTime$.MODULE$:Lscala/runtime/ScalaRunTime$;
const #119 = Asciz	boxArray;
const #120 = Asciz	(Ljava/lang/Object;)Lscala/runtime/BoxedArray;;
const #121 = NameAndType	#119:#120;//  boxArray:(Ljava/lang/Object;)Lscala/runtime/BoxedArray;
const #122 = Method	#115.#121;	//  scala/runtime/ScalaRunTime$.boxArray:(Ljava/lang/Object;)Lscala/runtime/BoxedArray;
const #123 = Asciz	n;
const #124 = Asciz	b$2;
const #125 = Asciz	Lscala/collection/generic/Builder;;
const #126 = Asciz	lead$2;
const #127 = Asciz	takeRight;
const #128 = Asciz	scala/runtime/BooleanRef;
const #129 = class	#128;	//  scala/runtime/BooleanRef
const #130 = Asciz	(Z)V;
const #131 = NameAndType	#50:#130;//  "<init>":(Z)V
const #132 = Method	#129.#131;	//  scala/runtime/BooleanRef."<init>":(Z)V
const #133 = Asciz	scala/collection/generic/IterableTemplate$$anonfun$takeRight$1;
const #134 = class	#133;	//  scala/collection/generic/IterableTemplate$$anonfun$takeRight$1
const #135 = Asciz	(Lscala/collection/generic/IterableTemplate;Lscala/collection/generic/Builder;Lscala/collection/Iterator;Lscala/runtime/BooleanRef;)V;
const #136 = NameAndType	#50:#135;//  "<init>":(Lscala/collection/generic/IterableTemplate;Lscala/collection/generic/Builder;Lscala/collection/Iterator;Lscala/runtime/BooleanRef;)V
const #137 = Method	#134.#136;	//  scala/collection/generic/IterableTemplate$$anonfun$takeRight$1."<init>":(Lscala/collection/generic/IterableTemplate;Lscala/collection/generic/Builder;Lscala/collection/Iterator;Lscala/runtime/BooleanRef;)V
const #138 = Asciz	foreach;
const #139 = Asciz	(Lscala/Function1;)V;
const #140 = NameAndType	#138:#139;//  foreach:(Lscala/Function1;)V
const #141 = InterfaceMethod	#13.#140;	//  scala/collection/generic/IterableTemplate.foreach:(Lscala/Function1;)V
const #142 = Asciz	b$1;
const #143 = Asciz	lead$1;
const #144 = Asciz	go$1;
const #145 = Asciz	Lscala/runtime/BooleanRef;;
const #146 = Asciz	isEmpty;
const #147 = NameAndType	#146:#67;//  isEmpty:()Z
const #148 = InterfaceMethod	#13.#147;	//  scala/collection/generic/IterableTemplate.isEmpty:()Z
const #149 = Asciz	java/util/NoSuchElementException;
const #150 = class	#149;	//  java/util/NoSuchElementException
const #151 = Asciz	()V;
const #152 = NameAndType	#50:#151;//  "<init>":()V
const #153 = Method	#150.#152;	//  java/util/NoSuchElementException."<init>":()V
const #154 = Asciz	toIterable;
const #155 = Asciz	(Lscala/collection/generic/IterableTemplate;)Lscala/collection/Iterable;;
const #156 = Asciz	thisCollection;
const #157 = Asciz	()Lscala/collection/generic/TraversableTemplate;;
const #158 = NameAndType	#156:#157;//  thisCollection:()Lscala/collection/generic/TraversableTemplate;
const #159 = InterfaceMethod	#21.#158;	//  scala/collection/generic/TraversableTemplate.thisCollection:()Lscala/collection/generic/TraversableTemplate;
const #160 = Asciz	scala/collection/Iterable;
const #161 = class	#160;	//  scala/collection/Iterable
const #162 = Asciz	reduceRight;
const #163 = Asciz	(Lscala/collection/generic/IterableTemplate;Lscala/Function2;)Ljava/lang/Object;;
const #164 = Asciz	(Lscala/Function2;)Ljava/lang/Object;;
const #165 = NameAndType	#162:#164;//  reduceRight:(Lscala/Function2;)Ljava/lang/Object;
const #166 = InterfaceMethod	#60.#165;	//  scala/collection/Iterator.reduceRight:(Lscala/Function2;)Ljava/lang/Object;
const #167 = Asciz	op;
const #168 = Asciz	Lscala/Function2;;
const #169 = Asciz	foldRight;
const #170 = Asciz	(Lscala/collection/generic/IterableTemplate;Ljava/lang/Object;Lscala/Function2;)Ljava/lang/Object;;
const #171 = Asciz	(Ljava/lang/Object;Lscala/Function2;)Ljava/lang/Object;;
const #172 = NameAndType	#169:#171;//  foldRight:(Ljava/lang/Object;Lscala/Function2;)Ljava/lang/Object;
const #173 = InterfaceMethod	#60.#172;	//  scala/collection/Iterator.foldRight:(Ljava/lang/Object;Lscala/Function2;)Ljava/lang/Object;
const #174 = Asciz	z;
const #175 = Asciz	Ljava/lang/Object;;
const #176 = Asciz	(Lscala/collection/generic/IterableTemplate;)Z;
const #177 = Asciz	(Lscala/collection/generic/IterableTemplate;Lscala/Function1;)V;
const #178 = InterfaceMethod	#60.#140;	//  scala/collection/Iterator.foreach:(Lscala/Function1;)V
const #179 = Asciz	f;
const #180 = Asciz	Lscala/Function1;;
const #181 = Asciz	elements;
const #182 = Asciz	(Lscala/collection/generic/IterableTemplate;)Lscala/collection/Iterator;;
const #183 = Asciz	Scala;
const #184 = Asciz	InnerClasses;
const #185 = Asciz	$anon$1;
const #186 = Asciz	$anonfun$dropRight$1;
const #187 = Asciz	$anonfun$takeRight$1;
const #188 = Asciz	scala/collection/generic/IterableTemplate$class;
const #189 = class	#188;	//  scala/collection/generic/IterableTemplate$class
const #190 = Asciz	java/lang/Object;
const #191 = class	#190;	//  java/lang/Object

{
public static void $init$(scala.collection.generic.IterableTemplate);
  Code:
   Stack=0, Locals=1, Args_size=1
   0:	return
  LineNumberTable: 
   line 43: 0

  LocalVariableTable: 
   Start  Length  Slot  Name   Signature
   0      1      0    $this       Lscala/collection/generic/IterableTemplate;


public static java.lang.Object projection(scala.collection.generic.IterableTemplate);
  Code:
   Stack=1, Locals=1, Args_size=1
   0:	aload_0
   1:	invokeinterface	#17,  1; //InterfaceMethod scala/collection/generic/IterableTemplate.view:()Ljava/lang/Object;
   6:	areturn
  LineNumberTable: 
   line 203: 0

  LocalVariableTable: 
   Start  Length  Slot  Name   Signature
   0      7      0    $this       Lscala/collection/generic/IterableTemplate;


public static scala.collection.Sequence toSeq(scala.collection.generic.IterableTemplate);
  Code:
   Stack=1, Locals=1, Args_size=1
   0:	aload_0
   1:	invokeinterface	#25,  1; //InterfaceMethod scala/collection/generic/TraversableTemplate.toSequence:()Lscala/collection/Sequence;
   6:	areturn
  LineNumberTable: 
   line 196: 0

  LocalVariableTable: 
   Start  Length  Slot  Name   Signature
   0      7      0    $this       Lscala/collection/generic/IterableTemplate;


public static scala.Option firstOption(scala.collection.generic.IterableTemplate);
  Code:
   Stack=1, Locals=1, Args_size=1
   0:	aload_0
   1:	invokeinterface	#31,  1; //InterfaceMethod scala/collection/generic/TraversableTemplate.headOption:()Lscala/Option;
   6:	areturn
  LineNumberTable: 
   line 194: 0

  LocalVariableTable: 
   Start  Length  Slot  Name   Signature
   0      7      0    $this       Lscala/collection/generic/IterableTemplate;


public static java.lang.Object first(scala.collection.generic.IterableTemplate);
  Code:
   Stack=1, Locals=1, Args_size=1
   0:	aload_0
   1:	invokeinterface	#35,  1; //InterfaceMethod scala/collection/generic/IterableTemplate.head:()Ljava/lang/Object;
   6:	areturn
  LineNumberTable: 
   line 191: 0

  LocalVariableTable: 
   Start  Length  Slot  Name   Signature
   0      7      0    $this       Lscala/collection/generic/IterableTemplate;


public static scala.collection.generic.IterableView view(scala.collection.generic.IterableTemplate, int, int);
  Code:
   Stack=3, Locals=3, Args_size=3
   0:	aload_0
   1:	invokeinterface	#17,  1; //InterfaceMethod scala/collection/generic/IterableTemplate.view:()Ljava/lang/Object;
   6:	checkcast	#38; //class scala/collection/generic/TraversableViewTemplate
   9:	iload_1
   10:	iload_2
   11:	invokeinterface	#42,  3; //InterfaceMethod scala/collection/generic/TraversableViewTemplate.slice:(II)Lscala/collection/generic/TraversableView;
   16:	checkcast	#44; //class scala/collection/generic/IterableView
   19:	areturn
  LineNumberTable: 
   line 189: 0

  LocalVariableTable: 
   Start  Length  Slot  Name   Signature
   0      20      0    $this       Lscala/collection/generic/IterableTemplate;
   0      20      1    from       I
   0      20      2    until       I


public static java.lang.Object view(scala.collection.generic.IterableTemplate);
  Code:
   Stack=3, Locals=1, Args_size=1
   0:	new	#49; //class scala/collection/generic/IterableTemplate$$anon$1
   3:	dup
   4:	aload_0
   5:	invokespecial	#52; //Method scala/collection/generic/IterableTemplate$$anon$1."<init>":(Lscala/collection/generic/IterableTemplate;)V
   8:	areturn
  LineNumberTable: 
   line 173: 0

  LocalVariableTable: 
   Start  Length  Slot  Name   Signature
   0      9      0    $this       Lscala/collection/generic/IterableTemplate;


public static scala.collection.immutable.Stream toStream(scala.collection.generic.IterableTemplate);
  Code:
   Stack=1, Locals=1, Args_size=1
   0:	aload_0
   1:	invokeinterface	#58,  1; //InterfaceMethod scala/collection/generic/IterableTemplate.iterator:()Lscala/collection/Iterator;
   6:	invokeinterface	#63,  1; //InterfaceMethod scala/collection/Iterator.toStream:()Lscala/collection/immutable/Stream;
   11:	areturn
  LineNumberTable: 
   line 169: 0

  LocalVariableTable: 
   Start  Length  Slot  Name   Signature
   0      12      0    $this       Lscala/collection/generic/IterableTemplate;


public static boolean sameElements(scala.collection.generic.IterableTemplate, scala.collection.Iterable);
  Code:
   Stack=2, Locals=4, Args_size=2
   0:	aload_0
   1:	invokeinterface	#58,  1; //InterfaceMethod scala/collection/generic/IterableTemplate.iterator:()Lscala/collection/Iterator;
   6:	astore_2
   7:	aload_1
   8:	invokeinterface	#58,  1; //InterfaceMethod scala/collection/generic/IterableTemplate.iterator:()Lscala/collection/Iterator;
   13:	astore_3
   14:	aload_2
   15:	invokeinterface	#69,  1; //InterfaceMethod scala/collection/Iterator.hasNext:()Z
   20:	ifeq	52
   23:	aload_3
   24:	invokeinterface	#69,  1; //InterfaceMethod scala/collection/Iterator.hasNext:()Z
   29:	ifeq	52
   32:	aload_2
   33:	invokeinterface	#72,  1; //InterfaceMethod scala/collection/Iterator.next:()Ljava/lang/Object;
   38:	aload_3
   39:	invokeinterface	#72,  1; //InterfaceMethod scala/collection/Iterator.next:()Ljava/lang/Object;
   44:	invokestatic	#78; //Method scala/runtime/BoxesRunTime.equals:(Ljava/lang/Object;Ljava/lang/Object;)Z
   47:	ifne	14
   50:	iconst_0
   51:	ireturn
   52:	aload_2
   53:	invokeinterface	#69,  1; //InterfaceMethod scala/collection/Iterator.hasNext:()Z
   58:	ifne	70
   61:	aload_3
   62:	invokeinterface	#69,  1; //InterfaceMethod scala/collection/Iterator.hasNext:()Z
   67:	ifeq	74
   70:	iconst_0
   71:	goto	75
   74:	iconst_1
   75:	ireturn
  LineNumberTable: 
   line 158: 0
   line 159: 7
   line 160: 14
   line 161: 32
   line 162: 50
   line 164: 52
   line 157: 75

  LocalVariableTable: 
   Start  Length  Slot  Name   Signature
   0      76      0    $this       Lscala/collection/generic/IterableTemplate;
   0      76      1    that       Lscala/collection/Iterable;
   7      69      2    these       Lscala/collection/Iterator;
   14      62      3    those       Lscala/collection/Iterator;


public static scala.collection.generic.IterableTemplate dropRight(scala.collection.generic.IterableTemplate, int);
  Code:
   Stack=6, Locals=5, Args_size=2
   0:	aload_0
   1:	invokeinterface	#89,  1; //InterfaceMethod scala/collection/generic/TraversableTemplate.newBuilder:()Lscala/collection/generic/Builder;
   6:	astore_2
   7:	aload_0
   8:	invokeinterface	#58,  1; //InterfaceMethod scala/collection/generic/IterableTemplate.iterator:()Lscala/collection/Iterator;
   13:	iload_1
   14:	invokeinterface	#93,  2; //InterfaceMethod scala/collection/Iterator.drop:(I)Lscala/collection/Iterator;
   19:	astore_3
   20:	getstatic	#99; //Field scala/util/control/Breaks$.MODULE$:Lscala/util/control/Breaks$;
   23:	new	#101; //class scala/collection/generic/IterableTemplate$$anonfun$dropRight$1
   26:	dup
   27:	aload_0
   28:	aload_2
   29:	aload_3
   30:	invokespecial	#104; //Method scala/collection/generic/IterableTemplate$$anonfun$dropRight$1."<init>":(Lscala/collection/generic/IterableTemplate;Lscala/collection/generic/Builder;Lscala/collection/Iterator;)V
   33:	invokevirtual	#108; //Method scala/util/control/Breaks$.breakable:(Lscala/Function0;)V
   36:	aload_2
   37:	invokeinterface	#113,  1; //InterfaceMethod scala/collection/generic/Builder.result:()Ljava/lang/Object;
   42:	astore	4
   44:	aload	4
   46:	instanceof	#13; //class scala/collection/generic/IterableTemplate
   49:	ifeq	57
   52:	aload	4
   54:	goto	65
   57:	getstatic	#118; //Field scala/runtime/ScalaRunTime$.MODULE$:Lscala/runtime/ScalaRunTime$;
   60:	aload	4
   62:	invokevirtual	#122; //Method scala/runtime/ScalaRunTime$.boxArray:(Ljava/lang/Object;)Lscala/runtime/BoxedArray;
   65:	checkcast	#13; //class scala/collection/generic/IterableTemplate
   68:	areturn
  LineNumberTable: 
   line 138: 0
   line 139: 7
   line 140: 20
   line 141: 23
   line 140: 33
   line 147: 36

  LocalVariableTable: 
   Start  Length  Slot  Name   Signature
   0      69      0    $this       Lscala/collection/generic/IterableTemplate;
   0      69      1    n       I
   7      61      2    b$2       Lscala/collection/generic/Builder;
   20      48      3    lead$2       Lscala/collection/Iterator;


public static scala.collection.generic.IterableTemplate takeRight(scala.collection.generic.IterableTemplate, int);
  Code:
   Stack=7, Locals=6, Args_size=2
   0:	aload_0
   1:	invokeinterface	#89,  1; //InterfaceMethod scala/collection/generic/TraversableTemplate.newBuilder:()Lscala/collection/generic/Builder;
   6:	astore_2
   7:	aload_0
   8:	invokeinterface	#58,  1; //InterfaceMethod scala/collection/generic/IterableTemplate.iterator:()Lscala/collection/Iterator;
   13:	iload_1
   14:	invokeinterface	#93,  2; //InterfaceMethod scala/collection/Iterator.drop:(I)Lscala/collection/Iterator;
   19:	astore_3
   20:	new	#129; //class scala/runtime/BooleanRef
   23:	dup
   24:	iconst_0
   25:	invokespecial	#132; //Method scala/runtime/BooleanRef."<init>":(Z)V
   28:	astore	4
   30:	aload_0
   31:	new	#134; //class scala/collection/generic/IterableTemplate$$anonfun$takeRight$1
   34:	dup
   35:	aload_0
   36:	aload_2
   37:	aload_3
   38:	aload	4
   40:	invokespecial	#137; //Method scala/collection/generic/IterableTemplate$$anonfun$takeRight$1."<init>":(Lscala/collection/generic/IterableTemplate;Lscala/collection/generic/Builder;Lscala/collection/Iterator;Lscala/runtime/BooleanRef;)V
   43:	invokeinterface	#141,  2; //InterfaceMethod scala/collection/generic/IterableTemplate.foreach:(Lscala/Function1;)V
   48:	aload_2
   49:	invokeinterface	#113,  1; //InterfaceMethod scala/collection/generic/Builder.result:()Ljava/lang/Object;
   54:	astore	5
   56:	aload	5
   58:	instanceof	#13; //class scala/collection/generic/IterableTemplate
   61:	ifeq	69
   64:	aload	5
   66:	goto	77
   69:	getstatic	#118; //Field scala/runtime/ScalaRunTime$.MODULE$:Lscala/runtime/ScalaRunTime$;
   72:	aload	5
   74:	invokevirtual	#122; //Method scala/runtime/ScalaRunTime$.boxArray:(Ljava/lang/Object;)Lscala/runtime/BoxedArray;
   77:	checkcast	#13; //class scala/collection/generic/IterableTemplate
   80:	areturn
  LineNumberTable: 
   line 121: 0
   line 122: 7
   line 123: 20
   line 124: 30
   line 129: 48

  LocalVariableTable: 
   Start  Length  Slot  Name   Signature
   0      81      0    $this       Lscala/collection/generic/IterableTemplate;
   0      81      1    n       I
   7      73      2    b$1       Lscala/collection/generic/Builder;
   20      60      3    lead$1       Lscala/collection/Iterator;
   30      50      4    go$1       Lscala/runtime/BooleanRef;


public static java.lang.Object head(scala.collection.generic.IterableTemplate);
  Code:
   Stack=2, Locals=1, Args_size=1
   0:	aload_0
   1:	invokeinterface	#148,  1; //InterfaceMethod scala/collection/generic/IterableTemplate.isEmpty:()Z
   6:	ifeq	17
   9:	new	#150; //class java/util/NoSuchElementException
   12:	dup
   13:	invokespecial	#153; //Method java/util/NoSuchElementException."<init>":()V
   16:	athrow
   17:	aload_0
   18:	invokeinterface	#58,  1; //InterfaceMethod scala/collection/generic/IterableTemplate.iterator:()Lscala/collection/Iterator;
   23:	invokeinterface	#72,  1; //InterfaceMethod scala/collection/Iterator.next:()Ljava/lang/Object;
   28:	areturn
  LineNumberTable: 
   line 110: 0
   line 111: 9
   line 113: 17
   line 110: 28

  LocalVariableTable: 
   Start  Length  Slot  Name   Signature
   0      29      0    $this       Lscala/collection/generic/IterableTemplate;


public static scala.collection.Iterable toIterable(scala.collection.generic.IterableTemplate);
  Code:
   Stack=1, Locals=1, Args_size=1
   0:	aload_0
   1:	invokeinterface	#159,  1; //InterfaceMethod scala/collection/generic/TraversableTemplate.thisCollection:()Lscala/collection/generic/TraversableTemplate;
   6:	checkcast	#161; //class scala/collection/Iterable
   9:	areturn
  LineNumberTable: 
   line 102: 0

  LocalVariableTable: 
   Start  Length  Slot  Name   Signature
   0      10      0    $this       Lscala/collection/generic/IterableTemplate;


public static java.lang.Object reduceRight(scala.collection.generic.IterableTemplate, scala.Function2);
  Code:
   Stack=2, Locals=2, Args_size=2
   0:	aload_0
   1:	invokeinterface	#58,  1; //InterfaceMethod scala/collection/generic/IterableTemplate.iterator:()Lscala/collection/Iterator;
   6:	aload_1
   7:	invokeinterface	#166,  2; //InterfaceMethod scala/collection/Iterator.reduceRight:(Lscala/Function2;)Ljava/lang/Object;
   12:	areturn
  LineNumberTable: 
   line 99: 0

  LocalVariableTable: 
   Start  Length  Slot  Name   Signature
   0      13      0    $this       Lscala/collection/generic/IterableTemplate;
   0      13      1    op       Lscala/Function2;


public static java.lang.Object foldRight(scala.collection.generic.IterableTemplate, java.lang.Object, scala.Function2);
  Code:
   Stack=3, Locals=3, Args_size=3
   0:	aload_0
   1:	invokeinterface	#58,  1; //InterfaceMethod scala/collection/generic/IterableTemplate.iterator:()Lscala/collection/Iterator;
   6:	aload_1
   7:	aload_2
   8:	invokeinterface	#173,  3; //InterfaceMethod scala/collection/Iterator.foldRight:(Ljava/lang/Object;Lscala/Function2;)Ljava/lang/Object;
   13:	areturn
  LineNumberTable: 
   line 83: 0

  LocalVariableTable: 
   Start  Length  Slot  Name   Signature
   0      14      0    $this       Lscala/collection/generic/IterableTemplate;
   0      14      1    z       Ljava/lang/Object;
   0      14      2    op       Lscala/Function2;


public static boolean isEmpty(scala.collection.generic.IterableTemplate);
  Code:
   Stack=1, Locals=1, Args_size=1
   0:	aload_0
   1:	invokeinterface	#58,  1; //InterfaceMethod scala/collection/generic/IterableTemplate.iterator:()Lscala/collection/Iterator;
   6:	invokeinterface	#69,  1; //InterfaceMethod scala/collection/Iterator.hasNext:()Z
   11:	ifeq	18
   14:	iconst_0
   15:	goto	19
   18:	iconst_1
   19:	ireturn
  LineNumberTable: 
   line 70: 0

  LocalVariableTable: 
   Start  Length  Slot  Name   Signature
   0      20      0    $this       Lscala/collection/generic/IterableTemplate;


public static void foreach(scala.collection.generic.IterableTemplate, scala.Function1);
  Code:
   Stack=2, Locals=2, Args_size=2
   0:	aload_0
   1:	invokeinterface	#58,  1; //InterfaceMethod scala/collection/generic/IterableTemplate.iterator:()Lscala/collection/Iterator;
   6:	aload_1
   7:	invokeinterface	#178,  2; //InterfaceMethod scala/collection/Iterator.foreach:(Lscala/Function1;)V
   12:	return
  LineNumberTable: 
   line 66: 0

  LocalVariableTable: 
   Start  Length  Slot  Name   Signature
   0      13      0    $this       Lscala/collection/generic/IterableTemplate;
   0      13      1    f       Lscala/Function1;


public static scala.collection.Iterator elements(scala.collection.generic.IterableTemplate);
  Code:
   Stack=1, Locals=1, Args_size=1
   0:	aload_0
   1:	invokeinterface	#58,  1; //InterfaceMethod scala/collection/generic/IterableTemplate.iterator:()Lscala/collection/Iterator;
   6:	areturn
  LineNumberTable: 
   line 53: 0

  LocalVariableTable: 
   Start  Length  Slot  Name   Signature
   0      7      0    $this       Lscala/collection/generic/IterableTemplate;


}

