Compiled from "IterableViewTemplate.scala"
public abstract class scala.collection.generic.IterableViewTemplate$Mapped$class extends java.lang.Object
  SourceFile: "IterableViewTemplate.scala"
  Scala: length = 0x
   
  InnerClass: 
   public abstract #39= #13 of #38; //Mapped=class scala/collection/generic/IterableViewTemplate$Mapped of class scala/collection/generic/IterableViewTemplate
   public abstract #39= #24 of #41; //Mapped=class scala/collection/generic/TraversableViewTemplate$Mapped of class scala/collection/generic/TraversableViewTemplate
  minor version: 0
  major version: 49
  Constant pool:
const #1 = Asciz	SourceFile;
const #2 = Asciz	IterableViewTemplate.scala;
const #3 = Asciz	$init$;
const #4 = Asciz	(Lscala/collection/generic/IterableViewTemplate$Mapped;)V;
const #5 = Asciz	Code;
const #6 = Asciz	LineNumberTable;
const #7 = Asciz	$this;
const #8 = Asciz	Lscala/collection/generic/IterableViewTemplate$Mapped;;
const #9 = Asciz	LocalVariableTable;
const #10 = Asciz	iterator;
const #11 = Asciz	(Lscala/collection/generic/IterableViewTemplate$Mapped;)Lscala/collection/Iterator;;
const #12 = Asciz	scala/collection/generic/IterableViewTemplate$Mapped;
const #13 = class	#12;	//  scala/collection/generic/IterableViewTemplate$Mapped
const #14 = Asciz	scala$collection$generic$IterableViewTemplate$Mapped$$$outer;
const #15 = Asciz	()Lscala/collection/generic/IterableViewTemplate;;
const #16 = NameAndType	#14:#15;//  scala$collection$generic$IterableViewTemplate$Mapped$$$outer:()Lscala/collection/generic/IterableViewTemplate;
const #17 = InterfaceMethod	#13.#16;	//  scala/collection/generic/IterableViewTemplate$Mapped.scala$collection$generic$IterableViewTemplate$Mapped$$$outer:()Lscala/collection/generic/IterableViewTemplate;
const #18 = Asciz	scala/collection/generic/IterableTemplate;
const #19 = class	#18;	//  scala/collection/generic/IterableTemplate
const #20 = Asciz	()Lscala/collection/Iterator;;
const #21 = NameAndType	#10:#20;//  iterator:()Lscala/collection/Iterator;
const #22 = InterfaceMethod	#19.#21;	//  scala/collection/generic/IterableTemplate.iterator:()Lscala/collection/Iterator;
const #23 = Asciz	scala/collection/generic/TraversableViewTemplate$Mapped;
const #24 = class	#23;	//  scala/collection/generic/TraversableViewTemplate$Mapped
const #25 = Asciz	mapping;
const #26 = Asciz	()Lscala/Function1;;
const #27 = NameAndType	#25:#26;//  mapping:()Lscala/Function1;
const #28 = InterfaceMethod	#24.#27;	//  scala/collection/generic/TraversableViewTemplate$Mapped.mapping:()Lscala/Function1;
const #29 = Asciz	scala/collection/Iterator;
const #30 = class	#29;	//  scala/collection/Iterator
const #31 = Asciz	map;
const #32 = Asciz	(Lscala/Function1;)Lscala/collection/Iterator;;
const #33 = NameAndType	#31:#32;//  map:(Lscala/Function1;)Lscala/collection/Iterator;
const #34 = InterfaceMethod	#30.#33;	//  scala/collection/Iterator.map:(Lscala/Function1;)Lscala/collection/Iterator;
const #35 = Asciz	Scala;
const #36 = Asciz	InnerClasses;
const #37 = Asciz	scala/collection/generic/IterableViewTemplate;
const #38 = class	#37;	//  scala/collection/generic/IterableViewTemplate
const #39 = Asciz	Mapped;
const #40 = Asciz	scala/collection/generic/TraversableViewTemplate;
const #41 = class	#40;	//  scala/collection/generic/TraversableViewTemplate
const #42 = Asciz	scala/collection/generic/IterableViewTemplate$Mapped$class;
const #43 = class	#42;	//  scala/collection/generic/IterableViewTemplate$Mapped$class
const #44 = Asciz	java/lang/Object;
const #45 = class	#44;	//  java/lang/Object

{
public static void $init$(scala.collection.generic.IterableViewTemplate$Mapped);
  Code:
   Stack=0, Locals=1, Args_size=1
   0:	return
  LineNumberTable: 
   line 34: 0

  LocalVariableTable: 
   Start  Length  Slot  Name   Signature
   0      1      0    $this       Lscala/collection/generic/IterableViewTemplate$Mapped;


public static scala.collection.Iterator iterator(scala.collection.generic.IterableViewTemplate$Mapped);
  Code:
   Stack=2, Locals=1, Args_size=1
   0:	aload_0
   1:	invokeinterface	#17,  1; //InterfaceMethod scala/collection/generic/IterableViewTemplate$Mapped.scala$collection$generic$IterableViewTemplate$Mapped$$$outer:()Lscala/collection/generic/IterableViewTemplate;
   6:	invokeinterface	#22,  1; //InterfaceMethod scala/collection/generic/IterableTemplate.iterator:()Lscala/collection/Iterator;
   11:	aload_0
   12:	invokeinterface	#28,  1; //InterfaceMethod scala/collection/generic/TraversableViewTemplate$Mapped.mapping:()Lscala/Function1;
   17:	invokeinterface	#34,  2; //InterfaceMethod scala/collection/Iterator.map:(Lscala/Function1;)Lscala/collection/Iterator;
   22:	areturn
  LineNumberTable: 
   line 35: 0

  LocalVariableTable: 
   Start  Length  Slot  Name   Signature
   0      23      0    $this       Lscala/collection/generic/IterableViewTemplate$Mapped;


}

