Compiled from "IterableViewTemplate.scala"
public abstract class scala.collection.generic.IterableViewTemplate$FlatMapped$class extends java.lang.Object
  SourceFile: "IterableViewTemplate.scala"
  Scala: length = 0x
   
  InnerClass: 
   public abstract #38= #13 of #37; //FlatMapped=class scala/collection/generic/IterableViewTemplate$FlatMapped of class scala/collection/generic/IterableViewTemplate
   public final #39= #24 of #13; //$anonfun$iterator$1=class scala/collection/generic/IterableViewTemplate$FlatMapped$$anonfun$iterator$1 of class scala/collection/generic/IterableViewTemplate$FlatMapped
  minor version: 0
  major version: 49
  Constant pool:
const #1 = Asciz	SourceFile;
const #2 = Asciz	IterableViewTemplate.scala;
const #3 = Asciz	$init$;
const #4 = Asciz	(Lscala/collection/generic/IterableViewTemplate$FlatMapped;)V;
const #5 = Asciz	Code;
const #6 = Asciz	LineNumberTable;
const #7 = Asciz	$this;
const #8 = Asciz	Lscala/collection/generic/IterableViewTemplate$FlatMapped;;
const #9 = Asciz	LocalVariableTable;
const #10 = Asciz	iterator;
const #11 = Asciz	(Lscala/collection/generic/IterableViewTemplate$FlatMapped;)Lscala/collection/Iterator;;
const #12 = Asciz	scala/collection/generic/IterableViewTemplate$FlatMapped;
const #13 = class	#12;	//  scala/collection/generic/IterableViewTemplate$FlatMapped
const #14 = Asciz	scala$collection$generic$IterableViewTemplate$FlatMapped$$$outer;
const #15 = Asciz	()Lscala/collection/generic/IterableViewTemplate;;
const #16 = NameAndType	#14:#15;//  scala$collection$generic$IterableViewTemplate$FlatMapped$$$outer:()Lscala/collection/generic/IterableViewTemplate;
const #17 = InterfaceMethod	#13.#16;	//  scala/collection/generic/IterableViewTemplate$FlatMapped.scala$collection$generic$IterableViewTemplate$FlatMapped$$$outer:()Lscala/collection/generic/IterableViewTemplate;
const #18 = Asciz	scala/collection/generic/IterableTemplate;
const #19 = class	#18;	//  scala/collection/generic/IterableTemplate
const #20 = Asciz	()Lscala/collection/Iterator;;
const #21 = NameAndType	#10:#20;//  iterator:()Lscala/collection/Iterator;
const #22 = InterfaceMethod	#19.#21;	//  scala/collection/generic/IterableTemplate.iterator:()Lscala/collection/Iterator;
const #23 = Asciz	scala/collection/generic/IterableViewTemplate$FlatMapped$$anonfun$iterator$1;
const #24 = class	#23;	//  scala/collection/generic/IterableViewTemplate$FlatMapped$$anonfun$iterator$1
const #25 = Asciz	<init>;
const #26 = NameAndType	#25:#4;//  "<init>":(Lscala/collection/generic/IterableViewTemplate$FlatMapped;)V
const #27 = Method	#24.#26;	//  scala/collection/generic/IterableViewTemplate$FlatMapped$$anonfun$iterator$1."<init>":(Lscala/collection/generic/IterableViewTemplate$FlatMapped;)V
const #28 = Asciz	scala/collection/Iterator;
const #29 = class	#28;	//  scala/collection/Iterator
const #30 = Asciz	flatMap;
const #31 = Asciz	(Lscala/Function1;)Lscala/collection/Iterator;;
const #32 = NameAndType	#30:#31;//  flatMap:(Lscala/Function1;)Lscala/collection/Iterator;
const #33 = InterfaceMethod	#29.#32;	//  scala/collection/Iterator.flatMap:(Lscala/Function1;)Lscala/collection/Iterator;
const #34 = Asciz	Scala;
const #35 = Asciz	InnerClasses;
const #36 = Asciz	scala/collection/generic/IterableViewTemplate;
const #37 = class	#36;	//  scala/collection/generic/IterableViewTemplate
const #38 = Asciz	FlatMapped;
const #39 = Asciz	$anonfun$iterator$1;
const #40 = Asciz	scala/collection/generic/IterableViewTemplate$FlatMapped$class;
const #41 = class	#40;	//  scala/collection/generic/IterableViewTemplate$FlatMapped$class
const #42 = Asciz	java/lang/Object;
const #43 = class	#42;	//  java/lang/Object

{
public static void $init$(scala.collection.generic.IterableViewTemplate$FlatMapped);
  Code:
   Stack=0, Locals=1, Args_size=1
   0:	return
  LineNumberTable: 
   line 38: 0

  LocalVariableTable: 
   Start  Length  Slot  Name   Signature
   0      1      0    $this       Lscala/collection/generic/IterableViewTemplate$FlatMapped;


public static scala.collection.Iterator iterator(scala.collection.generic.IterableViewTemplate$FlatMapped);
  Code:
   Stack=4, Locals=1, Args_size=1
   0:	aload_0
   1:	invokeinterface	#17,  1; //InterfaceMethod scala/collection/generic/IterableViewTemplate$FlatMapped.scala$collection$generic$IterableViewTemplate$FlatMapped$$$outer:()Lscala/collection/generic/IterableViewTemplate;
   6:	invokeinterface	#22,  1; //InterfaceMethod scala/collection/generic/IterableTemplate.iterator:()Lscala/collection/Iterator;
   11:	new	#24; //class scala/collection/generic/IterableViewTemplate$FlatMapped$$anonfun$iterator$1
   14:	dup
   15:	aload_0
   16:	invokespecial	#27; //Method scala/collection/generic/IterableViewTemplate$FlatMapped$$anonfun$iterator$1."<init>":(Lscala/collection/generic/IterableViewTemplate$FlatMapped;)V
   19:	invokeinterface	#33,  2; //InterfaceMethod scala/collection/Iterator.flatMap:(Lscala/Function1;)Lscala/collection/Iterator;
   24:	areturn
  LineNumberTable: 
   line 39: 0

  LocalVariableTable: 
   Start  Length  Slot  Name   Signature
   0      25      0    $this       Lscala/collection/generic/IterableViewTemplate$FlatMapped;


}

