Compiled from "IterableViewTemplate.scala"
public final class scala.collection.generic.IterableViewTemplate$Appended$$anonfun$iterator$2 extends java.lang.Object implements scala.Function0,scala.ScalaObject,java.io.Serializable
  SourceFile: "IterableViewTemplate.scala"
  Scala: length = 0x
   
  InnerClass: 
   public abstract #66= #63 of #65; //Appended=class scala/collection/generic/IterableViewTemplate$Appended of class scala/collection/generic/IterableViewTemplate
   public abstract #66= #38 of #68; //Appended=class scala/collection/generic/TraversableViewTemplate$Appended of class scala/collection/generic/TraversableViewTemplate
   public final #69= #15 of #63; //$anonfun$iterator$2=class scala/collection/generic/IterableViewTemplate$Appended$$anonfun$iterator$2 of class scala/collection/generic/IterableViewTemplate$Appended
  minor version: 0
  major version: 49
  Constant pool:
const #1 = Asciz	SourceFile;
const #2 = Asciz	IterableViewTemplate.scala;
const #3 = Asciz	$outer;
const #4 = Asciz	Lscala/collection/generic/IterableViewTemplate$Appended;;
const #5 = Asciz	<init>;
const #6 = Asciz	(Lscala/collection/generic/IterableViewTemplate$Appended;)V;
const #7 = Asciz	Code;
const #8 = Asciz	LineNumberTable;
const #9 = Asciz	java/lang/NullPointerException;
const #10 = class	#9;	//  java/lang/NullPointerException
const #11 = Asciz	()V;
const #12 = NameAndType	#5:#11;//  "<init>":()V
const #13 = Method	#10.#12;	//  java/lang/NullPointerException."<init>":()V
const #14 = Asciz	scala/collection/generic/IterableViewTemplate$Appended$$anonfun$iterator$2;
const #15 = class	#14;	//  scala/collection/generic/IterableViewTemplate$Appended$$anonfun$iterator$2
const #16 = NameAndType	#3:#4;//  $outer:Lscala/collection/generic/IterableViewTemplate$Appended;
const #17 = Field	#15.#16;	//  scala/collection/generic/IterableViewTemplate$Appended$$anonfun$iterator$2.$outer:Lscala/collection/generic/IterableViewTemplate$Appended;
const #18 = Asciz	java/lang/Object;
const #19 = class	#18;	//  java/lang/Object
const #20 = Method	#19.#12;	//  java/lang/Object."<init>":()V
const #21 = Asciz	scala/Function0$class;
const #22 = class	#21;	//  scala/Function0$class
const #23 = Asciz	$init$;
const #24 = Asciz	(Lscala/Function0;)V;
const #25 = NameAndType	#23:#24;//  $init$:(Lscala/Function0;)V
const #26 = Method	#22.#25;	//  scala/Function0$class.$init$:(Lscala/Function0;)V
const #27 = Asciz	this;
const #28 = Asciz	Lscala/collection/generic/IterableViewTemplate$Appended$$anonfun$iterator$2;;
const #29 = Asciz	LocalVariableTable;
const #30 = Asciz	(Lscala/collection/generic/IterableViewTemplate<TA;TColl;TThis;>.Appended<TB;>;)V;
const #31 = Asciz	Signature;
const #32 = Asciz	apply;
const #33 = Asciz	()Ljava/lang/Object;;
const #34 = Asciz	()Lscala/collection/Iterator;;
const #35 = NameAndType	#32:#34;//  apply:()Lscala/collection/Iterator;
const #36 = Method	#15.#35;	//  scala/collection/generic/IterableViewTemplate$Appended$$anonfun$iterator$2.apply:()Lscala/collection/Iterator;
const #37 = Asciz	scala/collection/generic/TraversableViewTemplate$Appended;
const #38 = class	#37;	//  scala/collection/generic/TraversableViewTemplate$Appended
const #39 = Asciz	rest;
const #40 = Asciz	()Lscala/collection/Traversable;;
const #41 = NameAndType	#39:#40;//  rest:()Lscala/collection/Traversable;
const #42 = InterfaceMethod	#38.#41;	//  scala/collection/generic/TraversableViewTemplate$Appended.rest:()Lscala/collection/Traversable;
const #43 = Asciz	scala/collection/generic/TraversableTemplate;
const #44 = class	#43;	//  scala/collection/generic/TraversableTemplate
const #45 = Asciz	toIterable;
const #46 = Asciz	()Lscala/collection/Iterable;;
const #47 = NameAndType	#45:#46;//  toIterable:()Lscala/collection/Iterable;
const #48 = InterfaceMethod	#44.#47;	//  scala/collection/generic/TraversableTemplate.toIterable:()Lscala/collection/Iterable;
const #49 = Asciz	scala/collection/generic/IterableTemplate;
const #50 = class	#49;	//  scala/collection/generic/IterableTemplate
const #51 = Asciz	iterator;
const #52 = NameAndType	#51:#34;//  iterator:()Lscala/collection/Iterator;
const #53 = InterfaceMethod	#50.#52;	//  scala/collection/generic/IterableTemplate.iterator:()Lscala/collection/Iterator;
const #54 = Asciz	()Lscala/collection/Iterator<TB;>;;
const #55 = Asciz	toString;
const #56 = Asciz	()Ljava/lang/String;;
const #57 = Asciz	(Lscala/Function0;)Ljava/lang/String;;
const #58 = NameAndType	#55:#57;//  toString:(Lscala/Function0;)Ljava/lang/String;
const #59 = Method	#22.#58;	//  scala/Function0$class.toString:(Lscala/Function0;)Ljava/lang/String;
const #60 = Asciz	Scala;
const #61 = Asciz	InnerClasses;
const #62 = Asciz	scala/collection/generic/IterableViewTemplate$Appended;
const #63 = class	#62;	//  scala/collection/generic/IterableViewTemplate$Appended
const #64 = Asciz	scala/collection/generic/IterableViewTemplate;
const #65 = class	#64;	//  scala/collection/generic/IterableViewTemplate
const #66 = Asciz	Appended;
const #67 = Asciz	scala/collection/generic/TraversableViewTemplate;
const #68 = class	#67;	//  scala/collection/generic/TraversableViewTemplate
const #69 = Asciz	$anonfun$iterator$2;
const #70 = Asciz	scala/Function0;
const #71 = class	#70;	//  scala/Function0
const #72 = Asciz	scala/ScalaObject;
const #73 = class	#72;	//  scala/ScalaObject
const #74 = Asciz	java/io/Serializable;
const #75 = class	#74;	//  java/io/Serializable

{
public scala.collection.generic.IterableViewTemplate$Appended$$anonfun$iterator$2(scala.collection.generic.IterableViewTemplate$Appended);
  Code:
   Stack=2, Locals=2, Args_size=2
   0:	aload_1
   1:	ifnonnull	12
   4:	new	#10; //class java/lang/NullPointerException
   7:	dup
   8:	invokespecial	#13; //Method java/lang/NullPointerException."<init>":()V
   11:	athrow
   12:	aload_0
   13:	aload_1
   14:	putfield	#17; //Field $outer:Lscala/collection/generic/IterableViewTemplate$Appended;
   17:	aload_0
   18:	invokespecial	#20; //Method java/lang/Object."<init>":()V
   21:	aload_0
   22:	invokestatic	#26; //Method scala/Function0$class.$init$:(Lscala/Function0;)V
   25:	return
  LineNumberTable: 
   line 43: 0

  LocalVariableTable: 
   Start  Length  Slot  Name   Signature
   0      26      0    this       Lscala/collection/generic/IterableViewTemplate$Appended$$anonfun$iterator$2;
   0      26      1    $outer       Lscala/collection/generic/IterableViewTemplate$Appended;

  Signature: length = 0x2
   00 1E 

public final java.lang.Object apply();
  Code:
   Stack=1, Locals=2, Args_size=1
   0:	aload_0
   1:	getfield	#17; //Field $outer:Lscala/collection/generic/IterableViewTemplate$Appended;
   4:	astore_1
   5:	aload_0
   6:	invokevirtual	#36; //Method apply:()Lscala/collection/Iterator;
   9:	areturn
  LineNumberTable: 
   line 43: 0

  LocalVariableTable: 
   Start  Length  Slot  Name   Signature
   0      10      0    this       Lscala/collection/generic/IterableViewTemplate$Appended$$anonfun$iterator$2;


public final scala.collection.Iterator apply();
  Code:
   Stack=1, Locals=2, Args_size=1
   0:	aload_0
   1:	getfield	#17; //Field $outer:Lscala/collection/generic/IterableViewTemplate$Appended;
   4:	astore_1
   5:	aload_0
   6:	getfield	#17; //Field $outer:Lscala/collection/generic/IterableViewTemplate$Appended;
   9:	invokeinterface	#42,  1; //InterfaceMethod scala/collection/generic/TraversableViewTemplate$Appended.rest:()Lscala/collection/Traversable;
   14:	invokeinterface	#48,  1; //InterfaceMethod scala/collection/generic/TraversableTemplate.toIterable:()Lscala/collection/Iterable;
   19:	invokeinterface	#53,  1; //InterfaceMethod scala/collection/generic/IterableTemplate.iterator:()Lscala/collection/Iterator;
   24:	areturn
  LineNumberTable: 
   line 43: 0

  LocalVariableTable: 
   Start  Length  Slot  Name   Signature
   0      25      0    this       Lscala/collection/generic/IterableViewTemplate$Appended$$anonfun$iterator$2;

  Signature: length = 0x2
   00 36 

public java.lang.String toString();
  Code:
   Stack=1, Locals=1, Args_size=1
   0:	aload_0
   1:	invokestatic	#59; //Method scala/Function0$class.toString:(Lscala/Function0;)Ljava/lang/String;
   4:	areturn
  LineNumberTable: 
   line 43: 0


}

