Compiled from "LazyBuilder.scala"
public abstract class scala.collection.generic.LazyBuilder extends java.lang.Object implements scala.collection.generic.Builder,scala.ScalaObject
  SourceFile: "LazyBuilder.scala"
  Signature: length = 0x2
   00 7C 
  ScalaSig: length = 0x225
   05 00 5B 06 05 01 02 FFFFFF81 00 09 02 0B 4C 61 7A 79
   42 75 69 6C 64 65 72 0A 02 03 04 01 07 67 65 6E
   65 72 69 63 0A 02 05 06 01 0A 63 6F 6C 6C 65 63
   74 69 6F 6E 0A 01 07 01 05 73 63 61 6C 61 03 00
   15 03 0A 19 24 13 04 00 0B 13 26 10 02 0C 11 0D
   01 0D 0A 02 0E 0F 01 04 6C 61 6E 67 0A 01 10 01
   04 6A 61 76 61 09 02 12 0D 02 06 4F 62 6A 65 63
   74 10 04 14 15 17 23 0D 01 02 09 02 16 02 02 07
   42 75 69 6C 64 65 72 10 02 18 19 0C 00 04 08 1A
   00 FFFFFF84 FFFFFF80 FFFFFF80 FFFFFFC2 00 1B 02 04 45 6C 65 6D 11 02 1C
   20 10 02 1D 1E 0D 01 06 09 02 1F 06 02 07 4E 6F
   74 68 69 6E 67 10 02 1D 21 09 02 22 06 02 03 41
   6E 79 10 02 18 24 04 08 25 00 FFFFFF84 FFFFFF80 FFFFFF84 FFFFFFC2 00 1B
   02 02 54 6F 10 02 1D 27 09 02 28 06 02 0B 53 63
   61 6C 61 4F 62 6A 65 63 74 08 05 2A 00 FFFFFF84 00 2B
   01 06 3C 69 6E 69 74 3E 14 01 2C 10 04 14 00 17
   23 08 07 2E 00 FFFFFFC0 FFFFFF80 FFFFFF84 08 2F 01 05 70 61 72 74
   73 15 01 30 10 03 31 34 36 0D 01 32 0A 02 33 04
   01 07 6D 75 74 61 62 6C 65 09 02 35 32 02 0A 4C
   69 73 74 42 75 66 66 65 72 10 03 37 38 17 0D 01
   04 09 02 39 04 02 0B 54 72 61 76 65 72 73 61 62
   6C 65 08 07 3B 00 FFFFFFC0 FFFFFF80 FFFFFF84 08 3C 01 09 70 61 72
   74 73 5F 24 65 71 14 02 3D 40 10 02 1D 3E 09 02
   3F 06 02 04 55 6E 69 74 08 07 41 3A FFFFFF81 FFFFFF80 FFFFFFC0 00
   30 01 03 78 24 31 08 06 43 00 FFFFFFA0 FFFFFFA0 04 30 01 06
   70 61 72 74 73 20 08 05 45 00 FFFFFF84 00 46 01 08 24
   70 6C 75 73 24 65 71 14 02 47 48 0D 01 00 08 05
   49 44 FFFFFFC0 00 17 01 01 78 08 05 4B 00 FFFFFF84 20 4C 01
   0D 24 70 6C 75 73 24 70 6C 75 73 24 65 71 14 02
   47 4D 08 05 4E 4A FFFFFFC0 00 4F 01 02 78 73 10 03 37
   50 17 09 02 51 04 02 08 49 74 65 72 61 74 6F 72
   08 05 4B 00 FFFFFF84 20 53 14 02 47 54 08 05 4E 52 FFFFFFC0
   00 36 08 05 56 00 FFFFFF86 00 57 01 06 72 65 73 75 6C
   74 14 01 23 08 05 59 00 FFFFFF84 00 5A 01 05 63 6C 65
   61 72 14 01 3D 
  minor version: 0
  major version: 49
  Constant pool:
const #1 = Asciz	SourceFile;
const #2 = Asciz	LazyBuilder.scala;
const #3 = Asciz	parts;
const #4 = Asciz	Lscala/collection/mutable/ListBuffer;;
const #5 = Asciz	Lscala/collection/mutable/ListBuffer<Lscala/collection/Traversable<TElem;>;>;;
const #6 = Asciz	Signature;
const #7 = Asciz	<init>;
const #8 = Asciz	()V;
const #9 = Asciz	Code;
const #10 = Asciz	LineNumberTable;
const #11 = Asciz	java/lang/Object;
const #12 = class	#11;	//  java/lang/Object
const #13 = NameAndType	#7:#8;//  "<init>":()V
const #14 = Method	#12.#13;	//  java/lang/Object."<init>":()V
const #15 = Asciz	scala/collection/generic/Growable$class;
const #16 = class	#15;	//  scala/collection/generic/Growable$class
const #17 = Asciz	$init$;
const #18 = Asciz	(Lscala/collection/generic/Growable;)V;
const #19 = NameAndType	#17:#18;//  $init$:(Lscala/collection/generic/Growable;)V
const #20 = Method	#16.#19;	//  scala/collection/generic/Growable$class.$init$:(Lscala/collection/generic/Growable;)V
const #21 = Asciz	scala/collection/generic/Builder$class;
const #22 = class	#21;	//  scala/collection/generic/Builder$class
const #23 = Asciz	(Lscala/collection/generic/Builder;)V;
const #24 = NameAndType	#17:#23;//  $init$:(Lscala/collection/generic/Builder;)V
const #25 = Method	#22.#24;	//  scala/collection/generic/Builder$class.$init$:(Lscala/collection/generic/Builder;)V
const #26 = Asciz	scala/collection/mutable/ListBuffer;
const #27 = class	#26;	//  scala/collection/mutable/ListBuffer
const #28 = Method	#27.#13;	//  scala/collection/mutable/ListBuffer."<init>":()V
const #29 = Asciz	scala/collection/generic/LazyBuilder;
const #30 = class	#29;	//  scala/collection/generic/LazyBuilder
const #31 = NameAndType	#3:#4;//  parts:Lscala/collection/mutable/ListBuffer;
const #32 = Field	#30.#31;	//  scala/collection/generic/LazyBuilder.parts:Lscala/collection/mutable/ListBuffer;
const #33 = Asciz	$plus$eq;
const #34 = Asciz	(Ljava/lang/Object;)Lscala/collection/generic/Builder;;
const #35 = Asciz	(Ljava/lang/Object;)Lscala/collection/generic/LazyBuilder;;
const #36 = NameAndType	#33:#35;//  $plus$eq:(Ljava/lang/Object;)Lscala/collection/generic/LazyBuilder;
const #37 = Method	#30.#36;	//  scala/collection/generic/LazyBuilder.$plus$eq:(Ljava/lang/Object;)Lscala/collection/generic/LazyBuilder;
const #38 = Asciz	this;
const #39 = Asciz	Lscala/collection/generic/LazyBuilder;;
const #40 = Asciz	elem;
const #41 = Asciz	Ljava/lang/Object;;
const #42 = Asciz	LocalVariableTable;
const #43 = Asciz	(Ljava/lang/Object;)Lscala/collection/generic/Growable;;
const #44 = Asciz	$plus$plus$eq;
const #45 = Asciz	(Lscala/collection/Iterator;)Lscala/collection/generic/Growable;;
const #46 = Asciz	(Lscala/collection/Iterator;)Lscala/collection/generic/LazyBuilder;;
const #47 = NameAndType	#44:#46;//  $plus$plus$eq:(Lscala/collection/Iterator;)Lscala/collection/generic/LazyBuilder;
const #48 = Method	#30.#47;	//  scala/collection/generic/LazyBuilder.$plus$plus$eq:(Lscala/collection/Iterator;)Lscala/collection/generic/LazyBuilder;
const #49 = Asciz	iter;
const #50 = Asciz	Lscala/collection/Iterator;;
const #51 = Asciz	(Lscala/collection/Traversable;)Lscala/collection/generic/Growable;;
const #52 = Asciz	(Lscala/collection/Traversable;)Lscala/collection/generic/LazyBuilder;;
const #53 = NameAndType	#44:#52;//  $plus$plus$eq:(Lscala/collection/Traversable;)Lscala/collection/generic/LazyBuilder;
const #54 = Method	#30.#53;	//  scala/collection/generic/LazyBuilder.$plus$plus$eq:(Lscala/collection/Traversable;)Lscala/collection/generic/LazyBuilder;
const #55 = Asciz	Lscala/collection/Traversable;;
const #56 = Asciz	clear;
const #57 = Asciz	()Lscala/collection/mutable/ListBuffer;;
const #58 = NameAndType	#3:#57;//  parts:()Lscala/collection/mutable/ListBuffer;
const #59 = Method	#30.#58;	//  scala/collection/generic/LazyBuilder.parts:()Lscala/collection/mutable/ListBuffer;
const #60 = NameAndType	#56:#8;//  clear:()V
const #61 = Method	#27.#60;	//  scala/collection/mutable/ListBuffer.clear:()V
const #62 = Asciz	result;
const #63 = Asciz	()Ljava/lang/Object;;
const #64 = Asciz	()TTo;;
const #65 = Asciz	(Ljava/lang/Object;)Lscala/collection/mutable/ListBuffer;;
const #66 = NameAndType	#33:#65;//  $plus$eq:(Ljava/lang/Object;)Lscala/collection/mutable/ListBuffer;
const #67 = Method	#27.#66;	//  scala/collection/mutable/ListBuffer.$plus$eq:(Ljava/lang/Object;)Lscala/collection/mutable/ListBuffer;
const #68 = Asciz	xs;
const #69 = Asciz	(Lscala/collection/Traversable<TElem;>;)Lscala/collection/generic/LazyBuilder<TElem;TTo;>;;
const #70 = Asciz	scala/collection/Iterator;
const #71 = class	#70;	//  scala/collection/Iterator
const #72 = Asciz	toStream;
const #73 = Asciz	()Lscala/collection/immutable/Stream;;
const #74 = NameAndType	#72:#73;//  toStream:()Lscala/collection/immutable/Stream;
const #75 = InterfaceMethod	#71.#74;	//  scala/collection/Iterator.toStream:()Lscala/collection/immutable/Stream;
const #76 = Asciz	(Lscala/collection/Iterator<TElem;>;)Lscala/collection/generic/LazyBuilder<TElem;TTo;>;;
const #77 = Asciz	scala/collection/immutable/List$;
const #78 = class	#77;	//  scala/collection/immutable/List$
const #79 = Asciz	MODULE$;
const #80 = Asciz	Lscala/collection/immutable/List$;;
const #81 = NameAndType	#79:#80;//  MODULE$:Lscala/collection/immutable/List$;
const #82 = Field	#78.#81;	//  scala/collection/immutable/List$.MODULE$:Lscala/collection/immutable/List$;
const #83 = Asciz	scala/runtime/ScalaRunTime$;
const #84 = class	#83;	//  scala/runtime/ScalaRunTime$
const #85 = Asciz	Lscala/runtime/ScalaRunTime$;;
const #86 = NameAndType	#79:#85;//  MODULE$:Lscala/runtime/ScalaRunTime$;
const #87 = Field	#84.#86;	//  scala/runtime/ScalaRunTime$.MODULE$:Lscala/runtime/ScalaRunTime$;
const #88 = Asciz	boxArray;
const #89 = Asciz	(Ljava/lang/Object;)Lscala/runtime/BoxedArray;;
const #90 = NameAndType	#88:#89;//  boxArray:(Ljava/lang/Object;)Lscala/runtime/BoxedArray;
const #91 = Method	#84.#90;	//  scala/runtime/ScalaRunTime$.boxArray:(Ljava/lang/Object;)Lscala/runtime/BoxedArray;
const #92 = Asciz	apply;
const #93 = Asciz	(Lscala/collection/Sequence;)Lscala/collection/immutable/List;;
const #94 = NameAndType	#92:#93;//  apply:(Lscala/collection/Sequence;)Lscala/collection/immutable/List;
const #95 = Method	#78.#94;	//  scala/collection/immutable/List$.apply:(Lscala/collection/Sequence;)Lscala/collection/immutable/List;
const #96 = Asciz	x;
const #97 = Asciz	(TElem;)Lscala/collection/generic/LazyBuilder<TElem;TTo;>;;
const #98 = Asciz	parts_$eq;
const #99 = Asciz	(Lscala/collection/mutable/ListBuffer;)V;
const #100 = Asciz	(Lscala/collection/mutable/ListBuffer<Lscala/collection/Traversable<TElem;>;>;)V;
const #101 = Asciz	()Lscala/collection/mutable/ListBuffer<Lscala/collection/Traversable<TElem;>;>;;
const #102 = Asciz	(Ljava/lang/Object;Ljava/lang/Object;Lscala/collection/Sequence;)Lscala/collection/generic/Growable;;
const #103 = Asciz	(Lscala/collection/generic/Growable;Ljava/lang/Object;Ljava/lang/Object;Lscala/collection/Sequence;)Lscala/collection/generic/Growable;;
const #104 = NameAndType	#33:#103;//  $plus$eq:(Lscala/collection/generic/Growable;Ljava/lang/Object;Ljava/lang/Object;Lscala/collection/Sequence;)Lscala/collection/generic/Growable;
const #105 = Method	#16.#104;	//  scala/collection/generic/Growable$class.$plus$eq:(Lscala/collection/generic/Growable;Ljava/lang/Object;Ljava/lang/Object;Lscala/collection/Sequence;)Lscala/collection/generic/Growable;
const #106 = Asciz	elem1;
const #107 = Asciz	elem2;
const #108 = Asciz	elems;
const #109 = Asciz	Lscala/collection/Sequence;;
const #110 = Asciz	mapResult;
const #111 = Asciz	(Lscala/Function1;)Lscala/collection/generic/Builder;;
const #112 = Asciz	(Lscala/collection/generic/Builder;Lscala/Function1;)Lscala/collection/generic/Builder;;
const #113 = NameAndType	#110:#112;//  mapResult:(Lscala/collection/generic/Builder;Lscala/Function1;)Lscala/collection/generic/Builder;
const #114 = Method	#22.#113;	//  scala/collection/generic/Builder$class.mapResult:(Lscala/collection/generic/Builder;Lscala/Function1;)Lscala/collection/generic/Builder;
const #115 = Asciz	f;
const #116 = Asciz	Lscala/Function1;;
const #117 = Asciz	sizeHint;
const #118 = Asciz	(I)V;
const #119 = Asciz	(Lscala/collection/generic/Builder;I)V;
const #120 = NameAndType	#117:#119;//  sizeHint:(Lscala/collection/generic/Builder;I)V
const #121 = Method	#22.#120;	//  scala/collection/generic/Builder$class.sizeHint:(Lscala/collection/generic/Builder;I)V
const #122 = Asciz	size;
const #123 = Asciz	I;
const #124 = Asciz	<Elem:Ljava/lang/Object;To:Ljava/lang/Object;>Ljava/lang/Object;Lscala/collection/generic/Builder<TElem;TTo;>;Lscala/ScalaObject;;
const #125 = Asciz	ScalaSig;
const #126 = Asciz	scala/collection/generic/Builder;
const #127 = class	#126;	//  scala/collection/generic/Builder
const #128 = Asciz	scala/ScalaObject;
const #129 = class	#128;	//  scala/ScalaObject

{
public scala.collection.generic.LazyBuilder();
  Code:
   Stack=3, Locals=1, Args_size=1
   0:	aload_0
   1:	invokespecial	#14; //Method java/lang/Object."<init>":()V
   4:	aload_0
   5:	invokestatic	#20; //Method scala/collection/generic/Growable$class.$init$:(Lscala/collection/generic/Growable;)V
   8:	aload_0
   9:	invokestatic	#25; //Method scala/collection/generic/Builder$class.$init$:(Lscala/collection/generic/Builder;)V
   12:	aload_0
   13:	new	#27; //class scala/collection/mutable/ListBuffer
   16:	dup
   17:	invokespecial	#28; //Method scala/collection/mutable/ListBuffer."<init>":()V
   20:	putfield	#32; //Field parts:Lscala/collection/mutable/ListBuffer;
   23:	return
  LineNumberTable: 
   line 20: 0
   line 22: 12

  Signature: length = 0x2
   00 08 

public scala.collection.generic.Builder $plus$eq(java.lang.Object);
  Code:
   Stack=2, Locals=2, Args_size=2
   0:	aload_0
   1:	aload_1
   2:	invokevirtual	#37; //Method $plus$eq:(Ljava/lang/Object;)Lscala/collection/generic/LazyBuilder;
   5:	areturn
  LineNumberTable: 
   line 20: 0

  LocalVariableTable: 
   Start  Length  Slot  Name   Signature
   0      6      0    this       Lscala/collection/generic/LazyBuilder;
   0      6      1    elem       Ljava/lang/Object;


public scala.collection.generic.Growable $plus$eq(java.lang.Object);
  Code:
   Stack=2, Locals=2, Args_size=2
   0:	aload_0
   1:	aload_1
   2:	invokevirtual	#37; //Method $plus$eq:(Ljava/lang/Object;)Lscala/collection/generic/LazyBuilder;
   5:	areturn
  LineNumberTable: 
   line 20: 0

  LocalVariableTable: 
   Start  Length  Slot  Name   Signature
   0      6      0    this       Lscala/collection/generic/LazyBuilder;
   0      6      1    elem       Ljava/lang/Object;


public scala.collection.generic.Growable $plus$plus$eq(scala.collection.Iterator);
  Code:
   Stack=2, Locals=2, Args_size=2
   0:	aload_0
   1:	aload_1
   2:	invokevirtual	#48; //Method $plus$plus$eq:(Lscala/collection/Iterator;)Lscala/collection/generic/LazyBuilder;
   5:	areturn
  LineNumberTable: 
   line 20: 0

  LocalVariableTable: 
   Start  Length  Slot  Name   Signature
   0      6      0    this       Lscala/collection/generic/LazyBuilder;
   0      6      1    iter       Lscala/collection/Iterator;


public scala.collection.generic.Growable $plus$plus$eq(scala.collection.Traversable);
  Code:
   Stack=2, Locals=2, Args_size=2
   0:	aload_0
   1:	aload_1
   2:	invokevirtual	#54; //Method $plus$plus$eq:(Lscala/collection/Traversable;)Lscala/collection/generic/LazyBuilder;
   5:	areturn
  LineNumberTable: 
   line 20: 0

  LocalVariableTable: 
   Start  Length  Slot  Name   Signature
   0      6      0    this       Lscala/collection/generic/LazyBuilder;
   0      6      1    iter       Lscala/collection/Traversable;


public void clear();
  Code:
   Stack=1, Locals=1, Args_size=1
   0:	aload_0
   1:	invokevirtual	#59; //Method parts:()Lscala/collection/mutable/ListBuffer;
   4:	invokevirtual	#61; //Method scala/collection/mutable/ListBuffer.clear:()V
   7:	return
  LineNumberTable: 
   line 27: 0


public abstract java.lang.Object result();
  Signature: length = 0x2
   00 40 

public scala.collection.generic.LazyBuilder $plus$plus$eq(scala.collection.Traversable);
  Code:
   Stack=2, Locals=2, Args_size=2
   0:	aload_0
   1:	invokevirtual	#59; //Method parts:()Lscala/collection/mutable/ListBuffer;
   4:	aload_1
   5:	invokevirtual	#67; //Method scala/collection/mutable/ListBuffer.$plus$eq:(Ljava/lang/Object;)Lscala/collection/mutable/ListBuffer;
   8:	pop
   9:	aload_0
   10:	areturn
  LineNumberTable: 
   line 25: 0

  LocalVariableTable: 
   Start  Length  Slot  Name   Signature
   0      11      0    this       Lscala/collection/generic/LazyBuilder;
   0      11      1    xs       Lscala/collection/Traversable;

  Signature: length = 0x2
   00 45 

public scala.collection.generic.LazyBuilder $plus$plus$eq(scala.collection.Iterator);
  Code:
   Stack=2, Locals=2, Args_size=2
   0:	aload_0
   1:	invokevirtual	#59; //Method parts:()Lscala/collection/mutable/ListBuffer;
   4:	aload_1
   5:	invokeinterface	#75,  1; //InterfaceMethod scala/collection/Iterator.toStream:()Lscala/collection/immutable/Stream;
   10:	invokevirtual	#67; //Method scala/collection/mutable/ListBuffer.$plus$eq:(Ljava/lang/Object;)Lscala/collection/mutable/ListBuffer;
   13:	pop
   14:	aload_0
   15:	areturn
  LineNumberTable: 
   line 24: 0

  LocalVariableTable: 
   Start  Length  Slot  Name   Signature
   0      16      0    this       Lscala/collection/generic/LazyBuilder;
   0      16      1    xs       Lscala/collection/Iterator;

  Signature: length = 0x2
   00 4C 

public scala.collection.generic.LazyBuilder $plus$eq(java.lang.Object);
  Code:
   Stack=7, Locals=2, Args_size=2
   0:	aload_0
   1:	invokevirtual	#59; //Method parts:()Lscala/collection/mutable/ListBuffer;
   4:	getstatic	#82; //Field scala/collection/immutable/List$.MODULE$:Lscala/collection/immutable/List$;
   7:	getstatic	#87; //Field scala/runtime/ScalaRunTime$.MODULE$:Lscala/runtime/ScalaRunTime$;
   10:	iconst_1
   11:	anewarray	#12; //class java/lang/Object
   14:	dup
   15:	iconst_0
   16:	aload_1
   17:	aastore
   18:	invokevirtual	#91; //Method scala/runtime/ScalaRunTime$.boxArray:(Ljava/lang/Object;)Lscala/runtime/BoxedArray;
   21:	invokevirtual	#95; //Method scala/collection/immutable/List$.apply:(Lscala/collection/Sequence;)Lscala/collection/immutable/List;
   24:	invokevirtual	#67; //Method scala/collection/mutable/ListBuffer.$plus$eq:(Ljava/lang/Object;)Lscala/collection/mutable/ListBuffer;
   27:	pop
   28:	aload_0
   29:	areturn
  LineNumberTable: 
   line 23: 0

  LocalVariableTable: 
   Start  Length  Slot  Name   Signature
   0      30      0    this       Lscala/collection/generic/LazyBuilder;
   0      30      1    x       Ljava/lang/Object;

  Signature: length = 0x2
   00 61 

public void parts_$eq(scala.collection.mutable.ListBuffer);
  Code:
   Stack=2, Locals=2, Args_size=2
   0:	aload_0
   1:	aload_1
   2:	putfield	#32; //Field parts:Lscala/collection/mutable/ListBuffer;
   5:	return
  LineNumberTable: 
   line 22: 0

  Signature: length = 0x2
   00 64 

public scala.collection.mutable.ListBuffer parts();
  Code:
   Stack=1, Locals=1, Args_size=1
   0:	aload_0
   1:	getfield	#32; //Field parts:Lscala/collection/mutable/ListBuffer;
   4:	areturn
  LineNumberTable: 
   line 22: 0

  Signature: length = 0x2
   00 65 

public scala.collection.generic.Growable $plus$eq(java.lang.Object, java.lang.Object, scala.collection.Sequence);
  Code:
   Stack=4, Locals=4, Args_size=4
   0:	aload_0
   1:	aload_1
   2:	aload_2
   3:	aload_3
   4:	invokestatic	#105; //Method scala/collection/generic/Growable$class.$plus$eq:(Lscala/collection/generic/Growable;Ljava/lang/Object;Ljava/lang/Object;Lscala/collection/Sequence;)Lscala/collection/generic/Growable;
   7:	areturn
  LineNumberTable: 
   line 20: 0

  LocalVariableTable: 
   Start  Length  Slot  Name   Signature
   0      8      0    this       Lscala/collection/generic/LazyBuilder;
   0      8      1    elem1       Ljava/lang/Object;
   0      8      2    elem2       Ljava/lang/Object;
   0      8      3    elems       Lscala/collection/Sequence;


public scala.collection.generic.Builder mapResult(scala.Function1);
  Code:
   Stack=2, Locals=2, Args_size=2
   0:	aload_0
   1:	aload_1
   2:	invokestatic	#114; //Method scala/collection/generic/Builder$class.mapResult:(Lscala/collection/generic/Builder;Lscala/Function1;)Lscala/collection/generic/Builder;
   5:	areturn
  LineNumberTable: 
   line 20: 0

  LocalVariableTable: 
   Start  Length  Slot  Name   Signature
   0      6      0    this       Lscala/collection/generic/LazyBuilder;
   0      6      1    f       Lscala/Function1;


public void sizeHint(int);
  Code:
   Stack=2, Locals=2, Args_size=2
   0:	aload_0
   1:	iload_1
   2:	invokestatic	#121; //Method scala/collection/generic/Builder$class.sizeHint:(Lscala/collection/generic/Builder;I)V
   5:	return
  LineNumberTable: 
   line 20: 0

  LocalVariableTable: 
   Start  Length  Slot  Name   Signature
   0      6      0    this       Lscala/collection/generic/LazyBuilder;
   0      6      1    size       I


}

