Compiled from "LinearSequenceTemplate.scala"
public abstract class scala.collection.generic.LinearSequenceTemplate$class extends java.lang.Object
  SourceFile: "LinearSequenceTemplate.scala"
  Scala: length = 0x
   
  InnerClass: 
   public final #200= #192 of #15; //$anon$1=class scala/collection/generic/LinearSequenceTemplate$$anon$1 of class scala/collection/generic/LinearSequenceTemplate
  minor version: 0
  major version: 49
  Constant pool:
const #1 = Asciz	SourceFile;
const #2 = Asciz	LinearSequenceTemplate.scala;
const #3 = Asciz	$init$;
const #4 = Asciz	(Lscala/collection/generic/LinearSequenceTemplate;)V;
const #5 = Asciz	Code;
const #6 = Asciz	LineNumberTable;
const #7 = Asciz	$this;
const #8 = Asciz	Lscala/collection/generic/LinearSequenceTemplate;;
const #9 = Asciz	LocalVariableTable;
const #10 = Asciz	equals;
const #11 = Asciz	(Lscala/collection/generic/LinearSequenceTemplate;Ljava/lang/Object;)Z;
const #12 = Asciz	scala/collection/LinearSequence;
const #13 = class	#12;	//  scala/collection/LinearSequence
const #14 = Asciz	scala/collection/generic/LinearSequenceTemplate;
const #15 = class	#14;	//  scala/collection/generic/LinearSequenceTemplate
const #16 = Asciz	sameElements;
const #17 = Asciz	(Lscala/collection/Iterable;)Z;
const #18 = NameAndType	#16:#17;//  sameElements:(Lscala/collection/Iterable;)Z
const #19 = InterfaceMethod	#15.#18;	//  scala/collection/generic/LinearSequenceTemplate.sameElements:(Lscala/collection/Iterable;)Z
const #20 = Asciz	scala$collection$generic$LinearSequenceTemplate$$super$equals;
const #21 = Asciz	(Ljava/lang/Object;)Z;
const #22 = NameAndType	#20:#21;//  scala$collection$generic$LinearSequenceTemplate$$super$equals:(Ljava/lang/Object;)Z
const #23 = InterfaceMethod	#15.#22;	//  scala/collection/generic/LinearSequenceTemplate.scala$collection$generic$LinearSequenceTemplate$$super$equals:(Ljava/lang/Object;)Z
const #24 = Asciz	that;
const #25 = Asciz	Ljava/lang/Object;;
const #26 = Asciz	temp3;
const #27 = Asciz	temp4;
const #28 = Asciz	Lscala/collection/LinearSequence;;
const #29 = Asciz	lastIndexWhere;
const #30 = Asciz	(Lscala/collection/generic/LinearSequenceTemplate;Lscala/Function1;I)I;
const #31 = Asciz	scala/collection/generic/IterableTemplate;
const #32 = class	#31;	//  scala/collection/generic/IterableTemplate
const #33 = Asciz	isEmpty;
const #34 = Asciz	()Z;
const #35 = NameAndType	#33:#34;//  isEmpty:()Z
const #36 = InterfaceMethod	#32.#35;	//  scala/collection/generic/IterableTemplate.isEmpty:()Z
const #37 = Asciz	head;
const #38 = Asciz	()Ljava/lang/Object;;
const #39 = NameAndType	#37:#38;//  head:()Ljava/lang/Object;
const #40 = InterfaceMethod	#32.#39;	//  scala/collection/generic/IterableTemplate.head:()Ljava/lang/Object;
const #41 = Asciz	scala/Function1;
const #42 = class	#41;	//  scala/Function1
const #43 = Asciz	apply;
const #44 = Asciz	(Ljava/lang/Object;)Ljava/lang/Object;;
const #45 = NameAndType	#43:#44;//  apply:(Ljava/lang/Object;)Ljava/lang/Object;
const #46 = InterfaceMethod	#42.#45;	//  scala/Function1.apply:(Ljava/lang/Object;)Ljava/lang/Object;
const #47 = Asciz	scala/runtime/BoxesRunTime;
const #48 = class	#47;	//  scala/runtime/BoxesRunTime
const #49 = Asciz	unboxToBoolean;
const #50 = NameAndType	#49:#21;//  unboxToBoolean:(Ljava/lang/Object;)Z
const #51 = Method	#48.#50;	//  scala/runtime/BoxesRunTime.unboxToBoolean:(Ljava/lang/Object;)Z
const #52 = Asciz	scala/collection/generic/TraversableTemplate;
const #53 = class	#52;	//  scala/collection/generic/TraversableTemplate
const #54 = Asciz	tail;
const #55 = Asciz	()Lscala/collection/generic/TraversableTemplate;;
const #56 = NameAndType	#54:#55;//  tail:()Lscala/collection/generic/TraversableTemplate;
const #57 = InterfaceMethod	#53.#56;	//  scala/collection/generic/TraversableTemplate.tail:()Lscala/collection/generic/TraversableTemplate;
const #58 = Asciz	p;
const #59 = Asciz	Lscala/Function1;;
const #60 = Asciz	end;
const #61 = Asciz	I;
const #62 = Asciz	i;
const #63 = Asciz	these;
const #64 = Asciz	last;
const #65 = Asciz	indexWhere;
const #66 = Asciz	drop;
const #67 = Asciz	(I)Lscala/collection/generic/LinearSequenceTemplate;;
const #68 = NameAndType	#66:#67;//  drop:(I)Lscala/collection/generic/LinearSequenceTemplate;
const #69 = InterfaceMethod	#15.#68;	//  scala/collection/generic/LinearSequenceTemplate.drop:(I)Lscala/collection/generic/LinearSequenceTemplate;
const #70 = Asciz	from;
const #71 = Asciz	segmentLength;
const #72 = Asciz	isDefinedAt;
const #73 = Asciz	(Lscala/collection/generic/LinearSequenceTemplate;I)Z;
const #74 = Asciz	lengthCompare;
const #75 = Asciz	(I)I;
const #76 = NameAndType	#74:#75;//  lengthCompare:(I)I
const #77 = InterfaceMethod	#15.#76;	//  scala/collection/generic/LinearSequenceTemplate.lengthCompare:(I)I
const #78 = Asciz	x;
const #79 = Asciz	(Lscala/collection/generic/LinearSequenceTemplate;I)I;
const #80 = Asciz	len;
const #81 = Asciz	(Lscala/collection/generic/LinearSequenceTemplate;Lscala/collection/Iterable;)Z;
const #82 = Asciz	java/lang/Object;
const #83 = class	#82;	//  java/lang/Object
const #84 = NameAndType	#10:#21;//  equals:(Ljava/lang/Object;)Z
const #85 = Method	#83.#84;	//  java/lang/Object.equals:(Ljava/lang/Object;)Z
const #86 = Asciz	(Ljava/lang/Object;Ljava/lang/Object;)Z;
const #87 = NameAndType	#10:#86;//  equals:(Ljava/lang/Object;Ljava/lang/Object;)Z
const #88 = Method	#48.#87;	//  scala/runtime/BoxesRunTime.equals:(Ljava/lang/Object;Ljava/lang/Object;)Z
const #89 = Asciz	scala$collection$generic$LinearSequenceTemplate$$super$sameElements;
const #90 = NameAndType	#89:#17;//  scala$collection$generic$LinearSequenceTemplate$$super$sameElements:(Lscala/collection/Iterable;)Z
const #91 = InterfaceMethod	#15.#90;	//  scala/collection/generic/LinearSequenceTemplate.scala$collection$generic$LinearSequenceTemplate$$super$sameElements:(Lscala/collection/Iterable;)Z
const #92 = Asciz	Lscala/collection/Iterable;;
const #93 = Asciz	temp1;
const #94 = Asciz	temp2;
const #95 = Asciz	that1;
const #96 = Asciz	those;
const #97 = Asciz	span;
const #98 = Asciz	(Lscala/collection/generic/LinearSequenceTemplate;Lscala/Function1;)Lscala/Tuple2;;
const #99 = Asciz	thisCollection;
const #100 = NameAndType	#99:#55;//  thisCollection:()Lscala/collection/generic/TraversableTemplate;
const #101 = InterfaceMethod	#53.#100;	//  scala/collection/generic/TraversableTemplate.thisCollection:()Lscala/collection/generic/TraversableTemplate;
const #102 = Asciz	newBuilder;
const #103 = Asciz	()Lscala/collection/generic/Builder;;
const #104 = NameAndType	#102:#103;//  newBuilder:()Lscala/collection/generic/Builder;
const #105 = InterfaceMethod	#53.#104;	//  scala/collection/generic/TraversableTemplate.newBuilder:()Lscala/collection/generic/Builder;
const #106 = Asciz	scala/collection/generic/Builder;
const #107 = class	#106;	//  scala/collection/generic/Builder
const #108 = Asciz	$plus$eq;
const #109 = Asciz	(Ljava/lang/Object;)Lscala/collection/generic/Builder;;
const #110 = NameAndType	#108:#109;//  $plus$eq:(Ljava/lang/Object;)Lscala/collection/generic/Builder;
const #111 = InterfaceMethod	#107.#110;	//  scala/collection/generic/Builder.$plus$eq:(Ljava/lang/Object;)Lscala/collection/generic/Builder;
const #112 = Asciz	scala/Tuple2;
const #113 = class	#112;	//  scala/Tuple2
const #114 = Asciz	result;
const #115 = NameAndType	#114:#38;//  result:()Ljava/lang/Object;
const #116 = InterfaceMethod	#107.#115;	//  scala/collection/generic/Builder.result:()Ljava/lang/Object;
const #117 = Asciz	<init>;
const #118 = Asciz	(Ljava/lang/Object;Ljava/lang/Object;)V;
const #119 = NameAndType	#117:#118;//  "<init>":(Ljava/lang/Object;Ljava/lang/Object;)V
const #120 = Method	#113.#119;	//  scala/Tuple2."<init>":(Ljava/lang/Object;Ljava/lang/Object;)V
const #121 = Asciz	b;
const #122 = Asciz	Lscala/collection/generic/Builder;;
const #123 = Asciz	dropRight;
const #124 = Asciz	(Lscala/collection/generic/LinearSequenceTemplate;I)Lscala/collection/generic/LinearSequenceTemplate;;
const #125 = Asciz	n;
const #126 = Asciz	lead;
const #127 = Asciz	count;
const #128 = Asciz	take;
const #129 = Asciz	(Lscala/collection/generic/LinearSequenceTemplate;)Ljava/lang/Object;;
const #130 = Asciz	java/util/NoSuchElementException;
const #131 = class	#130;	//  java/util/NoSuchElementException
const #132 = Asciz	()V;
const #133 = NameAndType	#117:#132;//  "<init>":()V
const #134 = Method	#131.#133;	//  java/util/NoSuchElementException."<init>":()V
const #135 = Asciz	nx;
const #136 = Asciz	reduceRight;
const #137 = Asciz	(Lscala/collection/generic/LinearSequenceTemplate;Lscala/Function2;)Ljava/lang/Object;;
const #138 = Asciz	java/lang/UnsupportedOperationException;
const #139 = class	#138;	//  java/lang/UnsupportedOperationException
const #140 = Asciz	Nil.reduceRight;
const #141 = String	#140;	//  Nil.reduceRight
const #142 = Asciz	(Ljava/lang/String;)V;
const #143 = NameAndType	#117:#142;//  "<init>":(Ljava/lang/String;)V
const #144 = Method	#139.#143;	//  java/lang/UnsupportedOperationException."<init>":(Ljava/lang/String;)V
const #145 = Asciz	(Lscala/Function2;)Ljava/lang/Object;;
const #146 = NameAndType	#136:#145;//  reduceRight:(Lscala/Function2;)Ljava/lang/Object;
const #147 = InterfaceMethod	#15.#146;	//  scala/collection/generic/LinearSequenceTemplate.reduceRight:(Lscala/Function2;)Ljava/lang/Object;
const #148 = Asciz	scala/Function2;
const #149 = class	#148;	//  scala/Function2
const #150 = Asciz	(Ljava/lang/Object;Ljava/lang/Object;)Ljava/lang/Object;;
const #151 = NameAndType	#43:#150;//  apply:(Ljava/lang/Object;Ljava/lang/Object;)Ljava/lang/Object;
const #152 = InterfaceMethod	#149.#151;	//  scala/Function2.apply:(Ljava/lang/Object;Ljava/lang/Object;)Ljava/lang/Object;
const #153 = Asciz	op;
const #154 = Asciz	Lscala/Function2;;
const #155 = Asciz	reduceLeft;
const #156 = Asciz	empty.reduceLeft;
const #157 = String	#156;	//  empty.reduceLeft
const #158 = Asciz	foldLeft;
const #159 = Asciz	(Ljava/lang/Object;Lscala/Function2;)Ljava/lang/Object;;
const #160 = NameAndType	#158:#159;//  foldLeft:(Ljava/lang/Object;Lscala/Function2;)Ljava/lang/Object;
const #161 = InterfaceMethod	#15.#160;	//  scala/collection/generic/LinearSequenceTemplate.foldLeft:(Ljava/lang/Object;Lscala/Function2;)Ljava/lang/Object;
const #162 = Asciz	f;
const #163 = Asciz	foldRight;
const #164 = Asciz	(Lscala/collection/generic/LinearSequenceTemplate;Ljava/lang/Object;Lscala/Function2;)Ljava/lang/Object;;
const #165 = NameAndType	#163:#159;//  foldRight:(Ljava/lang/Object;Lscala/Function2;)Ljava/lang/Object;
const #166 = InterfaceMethod	#15.#165;	//  scala/collection/generic/LinearSequenceTemplate.foldRight:(Ljava/lang/Object;Lscala/Function2;)Ljava/lang/Object;
const #167 = Asciz	z;
const #168 = Asciz	acc;
const #169 = Asciz	find;
const #170 = Asciz	(Lscala/collection/generic/LinearSequenceTemplate;Lscala/Function1;)Lscala/Option;;
const #171 = Asciz	scala/None$;
const #172 = class	#171;	//  scala/None$
const #173 = Asciz	MODULE$;
const #174 = Asciz	Lscala/None$;;
const #175 = NameAndType	#173:#174;//  MODULE$:Lscala/None$;
const #176 = Field	#172.#175;	//  scala/None$.MODULE$:Lscala/None$;
const #177 = Asciz	scala/Some;
const #178 = class	#177;	//  scala/Some
const #179 = Asciz	(Ljava/lang/Object;)V;
const #180 = NameAndType	#117:#179;//  "<init>":(Ljava/lang/Object;)V
const #181 = Method	#178.#180;	//  scala/Some."<init>":(Ljava/lang/Object;)V
const #182 = Asciz	(Lscala/collection/generic/LinearSequenceTemplate;Lscala/Function1;)I;
const #183 = Asciz	cnt;
const #184 = Asciz	exists;
const #185 = Asciz	(Lscala/collection/generic/LinearSequenceTemplate;Lscala/Function1;)Z;
const #186 = Asciz	forall;
const #187 = Asciz	foreach;
const #188 = Asciz	(Lscala/collection/generic/LinearSequenceTemplate;Lscala/Function1;)V;
const #189 = Asciz	iterator;
const #190 = Asciz	(Lscala/collection/generic/LinearSequenceTemplate;)Lscala/collection/Iterator;;
const #191 = Asciz	scala/collection/generic/LinearSequenceTemplate$$anon$1;
const #192 = class	#191;	//  scala/collection/generic/LinearSequenceTemplate$$anon$1
const #193 = NameAndType	#117:#4;//  "<init>":(Lscala/collection/generic/LinearSequenceTemplate;)V
const #194 = Method	#192.#193;	//  scala/collection/generic/LinearSequenceTemplate$$anon$1."<init>":(Lscala/collection/generic/LinearSequenceTemplate;)V
const #195 = Asciz	(Lscala/collection/generic/LinearSequenceTemplate;I)Ljava/lang/Object;;
const #196 = Asciz	length;
const #197 = Asciz	(Lscala/collection/generic/LinearSequenceTemplate;)I;
const #198 = Asciz	Scala;
const #199 = Asciz	InnerClasses;
const #200 = Asciz	$anon$1;
const #201 = Asciz	scala/collection/generic/LinearSequenceTemplate$class;
const #202 = class	#201;	//  scala/collection/generic/LinearSequenceTemplate$class

{
public static void $init$(scala.collection.generic.LinearSequenceTemplate);
  Code:
   Stack=0, Locals=1, Args_size=1
   0:	return
  LineNumberTable: 
   line 30: 0

  LocalVariableTable: 
   Start  Length  Slot  Name   Signature
   0      1      0    $this       Lscala/collection/generic/LinearSequenceTemplate;


public static boolean equals(scala.collection.generic.LinearSequenceTemplate, java.lang.Object);
  Code:
   Stack=2, Locals=4, Args_size=2
   0:	aload_1
   1:	astore_2
   2:	aload_2
   3:	instanceof	#13; //class scala/collection/LinearSequence
   6:	ifeq	24
   9:	aload_2
   10:	checkcast	#13; //class scala/collection/LinearSequence
   13:	astore_3
   14:	aload_0
   15:	aload_3
   16:	invokeinterface	#19,  2; //InterfaceMethod scala/collection/generic/LinearSequenceTemplate.sameElements:(Lscala/collection/Iterable;)Z
   21:	goto	31
   24:	aload_0
   25:	aload_1
   26:	invokeinterface	#23,  2; //InterfaceMethod scala/collection/generic/LinearSequenceTemplate.scala$collection$generic$LinearSequenceTemplate$$super$equals:(Ljava/lang/Object;)Z
   31:	ireturn
  LineNumberTable: 
   line 369: 0
   line 370: 14
   line 371: 24
   line 369: 31

  LocalVariableTable: 
   Start  Length  Slot  Name   Signature
   0      32      0    $this       Lscala/collection/generic/LinearSequenceTemplate;
   0      32      1    that       Ljava/lang/Object;
   2      30      2    temp3       Ljava/lang/Object;
   14      7      3    temp4       Lscala/collection/LinearSequence;


public static int lastIndexWhere(scala.collection.generic.LinearSequenceTemplate, scala.Function1, int);
  Code:
   Stack=2, Locals=6, Args_size=3
   0:	iconst_0
   1:	istore_3
   2:	aload_0
   3:	astore	4
   5:	iconst_m1
   6:	istore	5
   8:	aload	4
   10:	invokeinterface	#36,  1; //InterfaceMethod scala/collection/generic/IterableTemplate.isEmpty:()Z
   15:	ifne	64
   18:	iload_3
   19:	iload_2
   20:	if_icmpgt	64
   23:	aload_1
   24:	aload	4
   26:	invokeinterface	#40,  1; //InterfaceMethod scala/collection/generic/IterableTemplate.head:()Ljava/lang/Object;
   31:	invokeinterface	#46,  2; //InterfaceMethod scala/Function1.apply:(Ljava/lang/Object;)Ljava/lang/Object;
   36:	invokestatic	#51; //Method scala/runtime/BoxesRunTime.unboxToBoolean:(Ljava/lang/Object;)Z
   39:	ifeq	45
   42:	iload_3
   43:	istore	5
   45:	aload	4
   47:	invokeinterface	#57,  1; //InterfaceMethod scala/collection/generic/TraversableTemplate.tail:()Lscala/collection/generic/TraversableTemplate;
   52:	checkcast	#15; //class scala/collection/generic/LinearSequenceTemplate
   55:	astore	4
   57:	iload_3
   58:	iconst_1
   59:	iadd
   60:	istore_3
   61:	goto	8
   64:	iload	5
   66:	ireturn
  LineNumberTable: 
   line 358: 0
   line 359: 2
   line 360: 5
   line 361: 8
   line 362: 23
   line 363: 45
   line 364: 57
   line 361: 61
   line 366: 64

  LocalVariableTable: 
   Start  Length  Slot  Name   Signature
   0      67      0    $this       Lscala/collection/generic/LinearSequenceTemplate;
   0      67      1    p       Lscala/Function1;
   0      67      2    end       I
   2      64      3    i       I
   5      61      4    these       Lscala/collection/generic/LinearSequenceTemplate;
   8      58      5    last       I


public static int indexWhere(scala.collection.generic.LinearSequenceTemplate, scala.Function1, int);
  Code:
   Stack=2, Locals=5, Args_size=3
   0:	iload_2
   1:	istore_3
   2:	aload_0
   3:	iload_2
   4:	invokeinterface	#69,  2; //InterfaceMethod scala/collection/generic/LinearSequenceTemplate.drop:(I)Lscala/collection/generic/LinearSequenceTemplate;
   9:	astore	4
   11:	aload	4
   13:	invokeinterface	#36,  1; //InterfaceMethod scala/collection/generic/IterableTemplate.isEmpty:()Z
   18:	ifne	40
   21:	aload_1
   22:	aload	4
   24:	invokeinterface	#40,  1; //InterfaceMethod scala/collection/generic/IterableTemplate.head:()Ljava/lang/Object;
   29:	invokeinterface	#46,  2; //InterfaceMethod scala/Function1.apply:(Ljava/lang/Object;)Ljava/lang/Object;
   34:	invokestatic	#51; //Method scala/runtime/BoxesRunTime.unboxToBoolean:(Ljava/lang/Object;)Z
   37:	ifeq	56
   40:	aload	4
   42:	invokeinterface	#36,  1; //InterfaceMethod scala/collection/generic/IterableTemplate.isEmpty:()Z
   47:	ifeq	54
   50:	iconst_m1
   51:	goto	55
   54:	iload_3
   55:	ireturn
   56:	iload_3
   57:	iconst_1
   58:	iadd
   59:	istore_3
   60:	aload	4
   62:	invokeinterface	#57,  1; //InterfaceMethod scala/collection/generic/TraversableTemplate.tail:()Lscala/collection/generic/TraversableTemplate;
   67:	checkcast	#15; //class scala/collection/generic/LinearSequenceTemplate
   70:	astore	4
   72:	goto	11
  LineNumberTable: 
   line 342: 0
   line 343: 2
   line 344: 11
   line 348: 40
   line 341: 55
   line 345: 56
   line 346: 60
   line 344: 72

  LocalVariableTable: 
   Start  Length  Slot  Name   Signature
   0      75      0    $this       Lscala/collection/generic/LinearSequenceTemplate;
   0      75      1    p       Lscala/Function1;
   0      75      2    from       I
   2      73      3    i       I
   11      64      4    these       Lscala/collection/generic/LinearSequenceTemplate;


public static int segmentLength(scala.collection.generic.LinearSequenceTemplate, scala.Function1, int);
  Code:
   Stack=2, Locals=5, Args_size=3
   0:	iconst_0
   1:	istore_3
   2:	aload_0
   3:	iload_2
   4:	invokeinterface	#69,  2; //InterfaceMethod scala/collection/generic/LinearSequenceTemplate.drop:(I)Lscala/collection/generic/LinearSequenceTemplate;
   9:	astore	4
   11:	aload	4
   13:	invokeinterface	#36,  1; //InterfaceMethod scala/collection/generic/IterableTemplate.isEmpty:()Z
   18:	ifne	59
   21:	aload_1
   22:	aload	4
   24:	invokeinterface	#40,  1; //InterfaceMethod scala/collection/generic/IterableTemplate.head:()Ljava/lang/Object;
   29:	invokeinterface	#46,  2; //InterfaceMethod scala/Function1.apply:(Ljava/lang/Object;)Ljava/lang/Object;
   34:	invokestatic	#51; //Method scala/runtime/BoxesRunTime.unboxToBoolean:(Ljava/lang/Object;)Z
   37:	ifeq	59
   40:	iload_3
   41:	iconst_1
   42:	iadd
   43:	istore_3
   44:	aload	4
   46:	invokeinterface	#57,  1; //InterfaceMethod scala/collection/generic/TraversableTemplate.tail:()Lscala/collection/generic/TraversableTemplate;
   51:	checkcast	#15; //class scala/collection/generic/LinearSequenceTemplate
   54:	astore	4
   56:	goto	11
   59:	iload_3
   60:	ireturn
  LineNumberTable: 
   line 325: 0
   line 326: 2
   line 327: 11
   line 328: 40
   line 329: 44
   line 327: 56
   line 331: 59

  LocalVariableTable: 
   Start  Length  Slot  Name   Signature
   0      61      0    $this       Lscala/collection/generic/LinearSequenceTemplate;
   0      61      1    p       Lscala/Function1;
   0      61      2    from       I
   2      58      3    i       I
   11      49      4    these       Lscala/collection/generic/LinearSequenceTemplate;


public static boolean isDefinedAt(scala.collection.generic.LinearSequenceTemplate, int);
  Code:
   Stack=2, Locals=2, Args_size=2
   0:	iload_1
   1:	iconst_0
   2:	if_icmplt	20
   5:	aload_0
   6:	iload_1
   7:	invokeinterface	#77,  2; //InterfaceMethod scala/collection/generic/LinearSequenceTemplate.lengthCompare:(I)I
   12:	iconst_0
   13:	if_icmple	20
   16:	iconst_1
   17:	goto	21
   20:	iconst_0
   21:	ireturn
  LineNumberTable: 
   line 316: 0

  LocalVariableTable: 
   Start  Length  Slot  Name   Signature
   0      22      0    $this       Lscala/collection/generic/LinearSequenceTemplate;
   0      22      1    x       I


public static int lengthCompare(scala.collection.generic.LinearSequenceTemplate, int);
  Code:
   Stack=2, Locals=4, Args_size=2
   0:	iconst_0
   1:	istore_2
   2:	aload_0
   3:	astore_3
   4:	aload_3
   5:	invokeinterface	#36,  1; //InterfaceMethod scala/collection/generic/IterableTemplate.isEmpty:()Z
   10:	ifne	35
   13:	iload_2
   14:	iload_1
   15:	if_icmpgt	35
   18:	iload_2
   19:	iconst_1
   20:	iadd
   21:	istore_2
   22:	aload_3
   23:	invokeinterface	#57,  1; //InterfaceMethod scala/collection/generic/TraversableTemplate.tail:()Lscala/collection/generic/TraversableTemplate;
   28:	checkcast	#15; //class scala/collection/generic/LinearSequenceTemplate
   31:	astore_3
   32:	goto	4
   35:	iload_2
   36:	iload_1
   37:	isub
   38:	ireturn
  LineNumberTable: 
   line 305: 0
   line 306: 2
   line 307: 4
   line 308: 18
   line 309: 22
   line 307: 32
   line 311: 35

  LocalVariableTable: 
   Start  Length  Slot  Name   Signature
   0      39      0    $this       Lscala/collection/generic/LinearSequenceTemplate;
   0      39      1    len       I
   2      36      2    i       I
   4      34      3    these       Lscala/collection/generic/LinearSequenceTemplate;


public static boolean sameElements(scala.collection.generic.LinearSequenceTemplate, scala.collection.Iterable);
  Code:
   Stack=2, Locals=12, Args_size=2
   0:	aload_1
   1:	astore_2
   2:	aload_2
   3:	instanceof	#13; //class scala/collection/LinearSequence
   6:	ifeq	216
   9:	aload_2
   10:	checkcast	#13; //class scala/collection/LinearSequence
   13:	astore_3
   14:	aload_3
   15:	astore	4
   17:	aload_0
   18:	astore	5
   20:	aload	4
   22:	astore	6
   24:	aload	5
   26:	dup
   27:	astore	7
   29:	ifnull	125
   32:	aload	7
   34:	aconst_null
   35:	invokevirtual	#85; //Method java/lang/Object.equals:(Ljava/lang/Object;)Z
   38:	ifne	125
   41:	aload	6
   43:	dup
   44:	astore	8
   46:	ifnull	125
   49:	aload	8
   51:	aconst_null
   52:	invokevirtual	#85; //Method java/lang/Object.equals:(Ljava/lang/Object;)Z
   55:	ifne	125
   58:	aload	5
   60:	invokeinterface	#36,  1; //InterfaceMethod scala/collection/generic/IterableTemplate.isEmpty:()Z
   65:	ifne	125
   68:	aload	6
   70:	invokeinterface	#36,  1; //InterfaceMethod scala/collection/generic/IterableTemplate.isEmpty:()Z
   75:	ifne	125
   78:	aload	5
   80:	invokeinterface	#40,  1; //InterfaceMethod scala/collection/generic/IterableTemplate.head:()Ljava/lang/Object;
   85:	aload	6
   87:	invokeinterface	#40,  1; //InterfaceMethod scala/collection/generic/IterableTemplate.head:()Ljava/lang/Object;
   92:	invokestatic	#88; //Method scala/runtime/BoxesRunTime.equals:(Ljava/lang/Object;Ljava/lang/Object;)Z
   95:	ifeq	125
   98:	aload	5
   100:	invokeinterface	#57,  1; //InterfaceMethod scala/collection/generic/TraversableTemplate.tail:()Lscala/collection/generic/TraversableTemplate;
   105:	checkcast	#15; //class scala/collection/generic/LinearSequenceTemplate
   108:	astore	5
   110:	aload	6
   112:	invokeinterface	#57,  1; //InterfaceMethod scala/collection/generic/TraversableTemplate.tail:()Lscala/collection/generic/TraversableTemplate;
   117:	checkcast	#13; //class scala/collection/LinearSequence
   120:	astore	6
   122:	goto	24
   125:	aload	5
   127:	dup
   128:	astore	9
   130:	ifnull	142
   133:	aload	9
   135:	aconst_null
   136:	invokevirtual	#85; //Method java/lang/Object.equals:(Ljava/lang/Object;)Z
   139:	ifeq	167
   142:	aload	6
   144:	dup
   145:	astore	10
   147:	ifnull	159
   150:	aload	10
   152:	aconst_null
   153:	invokevirtual	#85; //Method java/lang/Object.equals:(Ljava/lang/Object;)Z
   156:	ifeq	163
   159:	iconst_1
   160:	goto	223
   163:	iconst_0
   164:	goto	223
   167:	aload	6
   169:	dup
   170:	astore	11
   172:	ifnull	184
   175:	aload	11
   177:	aconst_null
   178:	invokevirtual	#85; //Method java/lang/Object.equals:(Ljava/lang/Object;)Z
   181:	ifeq	188
   184:	iconst_0
   185:	goto	223
   188:	aload	5
   190:	invokeinterface	#36,  1; //InterfaceMethod scala/collection/generic/IterableTemplate.isEmpty:()Z
   195:	ifeq	212
   198:	aload	6
   200:	invokeinterface	#36,  1; //InterfaceMethod scala/collection/generic/IterableTemplate.isEmpty:()Z
   205:	ifeq	212
   208:	iconst_1
   209:	goto	223
   212:	iconst_0
   213:	goto	223
   216:	aload_0
   217:	aload_1
   218:	invokeinterface	#91,  2; //InterfaceMethod scala/collection/generic/LinearSequenceTemplate.scala$collection$generic$LinearSequenceTemplate$$super$sameElements:(Lscala/collection/Iterable;)Z
   223:	ireturn
  LineNumberTable: 
   line 279: 0
   line 280: 14
   line 281: 17
   line 282: 20
   line 283: 24
   line 284: 98
   line 285: 110
   line 283: 122
   line 287: 125
   line 288: 142
   line 289: 167
   line 290: 184
   line 292: 188
   line 293: 216
   line 279: 223

  LocalVariableTable: 
   Start  Length  Slot  Name   Signature
   0      224      0    $this       Lscala/collection/generic/LinearSequenceTemplate;
   0      224      1    that       Lscala/collection/Iterable;
   2      222      2    temp1       Lscala/collection/Iterable;
   14      202      3    temp2       Lscala/collection/LinearSequence;
   17      199      4    that1       Lscala/collection/LinearSequence;
   20      196      5    these       Lscala/collection/generic/LinearSequenceTemplate;
   24      192      6    those       Lscala/collection/LinearSequence;


public static scala.Tuple2 span(scala.collection.generic.LinearSequenceTemplate, scala.Function1);
  Code:
   Stack=4, Locals=4, Args_size=2
   0:	aload_0
   1:	invokeinterface	#101,  1; //InterfaceMethod scala/collection/generic/TraversableTemplate.thisCollection:()Lscala/collection/generic/TraversableTemplate;
   6:	checkcast	#15; //class scala/collection/generic/LinearSequenceTemplate
   9:	astore_2
   10:	aload_0
   11:	invokeinterface	#105,  1; //InterfaceMethod scala/collection/generic/TraversableTemplate.newBuilder:()Lscala/collection/generic/Builder;
   16:	astore_3
   17:	aload_2
   18:	invokeinterface	#36,  1; //InterfaceMethod scala/collection/generic/IterableTemplate.isEmpty:()Z
   23:	ifne	70
   26:	aload_1
   27:	aload_2
   28:	invokeinterface	#40,  1; //InterfaceMethod scala/collection/generic/IterableTemplate.head:()Ljava/lang/Object;
   33:	invokeinterface	#46,  2; //InterfaceMethod scala/Function1.apply:(Ljava/lang/Object;)Ljava/lang/Object;
   38:	invokestatic	#51; //Method scala/runtime/BoxesRunTime.unboxToBoolean:(Ljava/lang/Object;)Z
   41:	ifeq	70
   44:	aload_3
   45:	aload_2
   46:	invokeinterface	#40,  1; //InterfaceMethod scala/collection/generic/IterableTemplate.head:()Ljava/lang/Object;
   51:	invokeinterface	#111,  2; //InterfaceMethod scala/collection/generic/Builder.$plus$eq:(Ljava/lang/Object;)Lscala/collection/generic/Builder;
   56:	pop
   57:	aload_2
   58:	invokeinterface	#57,  1; //InterfaceMethod scala/collection/generic/TraversableTemplate.tail:()Lscala/collection/generic/TraversableTemplate;
   63:	checkcast	#15; //class scala/collection/generic/LinearSequenceTemplate
   66:	astore_2
   67:	goto	17
   70:	new	#113; //class scala/Tuple2
   73:	dup
   74:	aload_3
   75:	invokeinterface	#116,  1; //InterfaceMethod scala/collection/generic/Builder.result:()Ljava/lang/Object;
   80:	aload_2
   81:	invokespecial	#120; //Method scala/Tuple2."<init>":(Ljava/lang/Object;Ljava/lang/Object;)V
   84:	areturn
  LineNumberTable: 
   line 265: 0
   line 266: 10
   line 267: 17
   line 268: 44
   line 269: 57
   line 267: 67
   line 271: 70

  LocalVariableTable: 
   Start  Length  Slot  Name   Signature
   0      85      0    $this       Lscala/collection/generic/LinearSequenceTemplate;
   0      85      1    p       Lscala/Function1;
   10      74      2    these       Lscala/collection/generic/LinearSequenceTemplate;
   17      67      3    b       Lscala/collection/generic/Builder;


public static scala.collection.generic.LinearSequenceTemplate dropRight(scala.collection.generic.LinearSequenceTemplate, int);
  Code:
   Stack=2, Locals=5, Args_size=2
   0:	aload_0
   1:	invokeinterface	#105,  1; //InterfaceMethod scala/collection/generic/TraversableTemplate.newBuilder:()Lscala/collection/generic/Builder;
   6:	astore_2
   7:	aload_0
   8:	astore_3
   9:	aload_0
   10:	iload_1
   11:	invokeinterface	#69,  2; //InterfaceMethod scala/collection/generic/LinearSequenceTemplate.drop:(I)Lscala/collection/generic/LinearSequenceTemplate;
   16:	astore	4
   18:	aload	4
   20:	invokeinterface	#36,  1; //InterfaceMethod scala/collection/generic/IterableTemplate.isEmpty:()Z
   25:	ifeq	38
   28:	aload_2
   29:	invokeinterface	#116,  1; //InterfaceMethod scala/collection/generic/Builder.result:()Ljava/lang/Object;
   34:	checkcast	#15; //class scala/collection/generic/LinearSequenceTemplate
   37:	areturn
   38:	aload_2
   39:	aload_3
   40:	invokeinterface	#40,  1; //InterfaceMethod scala/collection/generic/IterableTemplate.head:()Ljava/lang/Object;
   45:	invokeinterface	#111,  2; //InterfaceMethod scala/collection/generic/Builder.$plus$eq:(Ljava/lang/Object;)Lscala/collection/generic/Builder;
   50:	pop
   51:	aload_3
   52:	invokeinterface	#57,  1; //InterfaceMethod scala/collection/generic/TraversableTemplate.tail:()Lscala/collection/generic/TraversableTemplate;
   57:	checkcast	#15; //class scala/collection/generic/LinearSequenceTemplate
   60:	astore_3
   61:	aload	4
   63:	invokeinterface	#57,  1; //InterfaceMethod scala/collection/generic/TraversableTemplate.tail:()Lscala/collection/generic/TraversableTemplate;
   68:	checkcast	#15; //class scala/collection/generic/LinearSequenceTemplate
   71:	astore	4
   73:	goto	18
  LineNumberTable: 
   line 248: 0
   line 249: 7
   line 250: 9
   line 251: 18
   line 256: 28
   line 252: 38
   line 253: 51
   line 254: 61
   line 251: 73

  LocalVariableTable: 
   Start  Length  Slot  Name   Signature
   0      76      0    $this       Lscala/collection/generic/LinearSequenceTemplate;
   0      76      1    n       I
   7      30      2    b       Lscala/collection/generic/Builder;
   38      38      2    b       Lscala/collection/generic/Builder;
   9      28      3    these       Lscala/collection/generic/LinearSequenceTemplate;
   38      38      3    these       Lscala/collection/generic/LinearSequenceTemplate;
   18      19      4    lead       Lscala/collection/generic/LinearSequenceTemplate;
   38      38      4    lead       Lscala/collection/generic/LinearSequenceTemplate;


public static scala.collection.generic.LinearSequenceTemplate drop(scala.collection.generic.LinearSequenceTemplate, int);
  Code:
   Stack=2, Locals=4, Args_size=2
   0:	aload_0
   1:	invokeinterface	#101,  1; //InterfaceMethod scala/collection/generic/TraversableTemplate.thisCollection:()Lscala/collection/generic/TraversableTemplate;
   6:	checkcast	#15; //class scala/collection/generic/LinearSequenceTemplate
   9:	astore_2
   10:	iload_1
   11:	istore_3
   12:	aload_2
   13:	invokeinterface	#36,  1; //InterfaceMethod scala/collection/generic/IterableTemplate.isEmpty:()Z
   18:	ifne	43
   21:	iload_3
   22:	iconst_0
   23:	if_icmple	43
   26:	aload_2
   27:	invokeinterface	#57,  1; //InterfaceMethod scala/collection/generic/TraversableTemplate.tail:()Lscala/collection/generic/TraversableTemplate;
   32:	checkcast	#15; //class scala/collection/generic/LinearSequenceTemplate
   35:	astore_2
   36:	iload_3
   37:	iconst_1
   38:	isub
   39:	istore_3
   40:	goto	12
   43:	aload_2
   44:	areturn
  LineNumberTable: 
   line 235: 0
   line 236: 10
   line 237: 12
   line 238: 26
   line 239: 36
   line 237: 40
   line 241: 43

  LocalVariableTable: 
   Start  Length  Slot  Name   Signature
   0      45      0    $this       Lscala/collection/generic/LinearSequenceTemplate;
   0      45      1    n       I
   10      34      2    these       Lscala/collection/generic/LinearSequenceTemplate;
   12      32      3    count       I


public static scala.collection.generic.LinearSequenceTemplate take(scala.collection.generic.LinearSequenceTemplate, int);
  Code:
   Stack=2, Locals=5, Args_size=2
   0:	aload_0
   1:	invokeinterface	#105,  1; //InterfaceMethod scala/collection/generic/TraversableTemplate.newBuilder:()Lscala/collection/generic/Builder;
   6:	astore_2
   7:	iconst_0
   8:	istore_3
   9:	aload_0
   10:	astore	4
   12:	aload	4
   14:	invokeinterface	#36,  1; //InterfaceMethod scala/collection/generic/IterableTemplate.isEmpty:()Z
   19:	ifne	60
   22:	iload_3
   23:	iload_1
   24:	if_icmpge	60
   27:	iload_3
   28:	iconst_1
   29:	iadd
   30:	istore_3
   31:	aload_2
   32:	aload	4
   34:	invokeinterface	#40,  1; //InterfaceMethod scala/collection/generic/IterableTemplate.head:()Ljava/lang/Object;
   39:	invokeinterface	#111,  2; //InterfaceMethod scala/collection/generic/Builder.$plus$eq:(Ljava/lang/Object;)Lscala/collection/generic/Builder;
   44:	pop
   45:	aload	4
   47:	invokeinterface	#57,  1; //InterfaceMethod scala/collection/generic/TraversableTemplate.tail:()Lscala/collection/generic/TraversableTemplate;
   52:	checkcast	#15; //class scala/collection/generic/LinearSequenceTemplate
   55:	astore	4
   57:	goto	12
   60:	aload_2
   61:	invokeinterface	#116,  1; //InterfaceMethod scala/collection/generic/Builder.result:()Ljava/lang/Object;
   66:	checkcast	#15; //class scala/collection/generic/LinearSequenceTemplate
   69:	areturn
  LineNumberTable: 
   line 223: 0
   line 224: 7
   line 225: 9
   line 226: 12
   line 227: 27
   line 228: 31
   line 229: 45
   line 226: 57
   line 231: 60

  LocalVariableTable: 
   Start  Length  Slot  Name   Signature
   0      70      0    $this       Lscala/collection/generic/LinearSequenceTemplate;
   0      70      1    n       I
   7      62      2    b       Lscala/collection/generic/Builder;
   9      60      3    i       I
   12      57      4    these       Lscala/collection/generic/LinearSequenceTemplate;


public static java.lang.Object last(scala.collection.generic.LinearSequenceTemplate);
  Code:
   Stack=2, Locals=3, Args_size=1
   0:	aload_0
   1:	invokeinterface	#36,  1; //InterfaceMethod scala/collection/generic/IterableTemplate.isEmpty:()Z
   6:	ifeq	17
   9:	new	#131; //class java/util/NoSuchElementException
   12:	dup
   13:	invokespecial	#134; //Method java/util/NoSuchElementException."<init>":()V
   16:	athrow
   17:	aload_0
   18:	astore_1
   19:	aload_1
   20:	invokeinterface	#57,  1; //InterfaceMethod scala/collection/generic/TraversableTemplate.tail:()Lscala/collection/generic/TraversableTemplate;
   25:	checkcast	#15; //class scala/collection/generic/LinearSequenceTemplate
   28:	astore_2
   29:	aload_2
   30:	invokeinterface	#36,  1; //InterfaceMethod scala/collection/generic/IterableTemplate.isEmpty:()Z
   35:	ifeq	45
   38:	aload_1
   39:	invokeinterface	#40,  1; //InterfaceMethod scala/collection/generic/IterableTemplate.head:()Ljava/lang/Object;
   44:	areturn
   45:	aload_2
   46:	astore_1
   47:	aload_2
   48:	invokeinterface	#57,  1; //InterfaceMethod scala/collection/generic/TraversableTemplate.tail:()Lscala/collection/generic/TraversableTemplate;
   53:	checkcast	#15; //class scala/collection/generic/LinearSequenceTemplate
   56:	astore_2
   57:	goto	29
  LineNumberTable: 
   line 212: 0
   line 213: 17
   line 214: 19
   line 215: 29
   line 219: 38
   line 216: 45
   line 217: 47
   line 215: 57

  LocalVariableTable: 
   Start  Length  Slot  Name   Signature
   0      60      0    $this       Lscala/collection/generic/LinearSequenceTemplate;
   19      25      1    these       Lscala/collection/generic/LinearSequenceTemplate;
   45      15      1    these       Lscala/collection/generic/LinearSequenceTemplate;
   29      15      2    nx       Lscala/collection/generic/LinearSequenceTemplate;
   45      15      2    nx       Lscala/collection/generic/LinearSequenceTemplate;


public static java.lang.Object reduceRight(scala.collection.generic.LinearSequenceTemplate, scala.Function2);
  Code:
   Stack=4, Locals=2, Args_size=2
   0:	aload_0
   1:	invokeinterface	#36,  1; //InterfaceMethod scala/collection/generic/IterableTemplate.isEmpty:()Z
   6:	ifeq	19
   9:	new	#139; //class java/lang/UnsupportedOperationException
   12:	dup
   13:	ldc	#141; //String Nil.reduceRight
   15:	invokespecial	#144; //Method java/lang/UnsupportedOperationException."<init>":(Ljava/lang/String;)V
   18:	athrow
   19:	aload_0
   20:	invokeinterface	#57,  1; //InterfaceMethod scala/collection/generic/TraversableTemplate.tail:()Lscala/collection/generic/TraversableTemplate;
   25:	checkcast	#32; //class scala/collection/generic/IterableTemplate
   28:	invokeinterface	#36,  1; //InterfaceMethod scala/collection/generic/IterableTemplate.isEmpty:()Z
   33:	ifeq	45
   36:	aload_0
   37:	invokeinterface	#40,  1; //InterfaceMethod scala/collection/generic/IterableTemplate.head:()Ljava/lang/Object;
   42:	goto	72
   45:	aload_1
   46:	aload_0
   47:	invokeinterface	#40,  1; //InterfaceMethod scala/collection/generic/IterableTemplate.head:()Ljava/lang/Object;
   52:	aload_0
   53:	invokeinterface	#57,  1; //InterfaceMethod scala/collection/generic/TraversableTemplate.tail:()Lscala/collection/generic/TraversableTemplate;
   58:	checkcast	#15; //class scala/collection/generic/LinearSequenceTemplate
   61:	aload_1
   62:	invokeinterface	#147,  2; //InterfaceMethod scala/collection/generic/LinearSequenceTemplate.reduceRight:(Lscala/Function2;)Ljava/lang/Object;
   67:	invokeinterface	#152,  3; //InterfaceMethod scala/Function2.apply:(Ljava/lang/Object;Ljava/lang/Object;)Ljava/lang/Object;
   72:	areturn
  LineNumberTable: 
   line 203: 0
   line 204: 19
   line 205: 45
   line 203: 72

  LocalVariableTable: 
   Start  Length  Slot  Name   Signature
   0      73      0    $this       Lscala/collection/generic/LinearSequenceTemplate;
   0      73      1    op       Lscala/Function2;


public static java.lang.Object reduceLeft(scala.collection.generic.LinearSequenceTemplate, scala.Function2);
  Code:
   Stack=3, Locals=2, Args_size=2
   0:	aload_0
   1:	invokeinterface	#36,  1; //InterfaceMethod scala/collection/generic/IterableTemplate.isEmpty:()Z
   6:	ifeq	19
   9:	new	#139; //class java/lang/UnsupportedOperationException
   12:	dup
   13:	ldc	#157; //String empty.reduceLeft
   15:	invokespecial	#144; //Method java/lang/UnsupportedOperationException."<init>":(Ljava/lang/String;)V
   18:	athrow
   19:	aload_0
   20:	invokeinterface	#57,  1; //InterfaceMethod scala/collection/generic/TraversableTemplate.tail:()Lscala/collection/generic/TraversableTemplate;
   25:	checkcast	#15; //class scala/collection/generic/LinearSequenceTemplate
   28:	aload_0
   29:	invokeinterface	#40,  1; //InterfaceMethod scala/collection/generic/IterableTemplate.head:()Ljava/lang/Object;
   34:	aload_1
   35:	invokeinterface	#161,  3; //InterfaceMethod scala/collection/generic/LinearSequenceTemplate.foldLeft:(Ljava/lang/Object;Lscala/Function2;)Ljava/lang/Object;
   40:	areturn
  LineNumberTable: 
   line 188: 0
   line 189: 19
   line 188: 40

  LocalVariableTable: 
   Start  Length  Slot  Name   Signature
   0      41      0    $this       Lscala/collection/generic/LinearSequenceTemplate;
   0      41      1    f       Lscala/Function2;


public static java.lang.Object foldRight(scala.collection.generic.LinearSequenceTemplate, java.lang.Object, scala.Function2);
  Code:
   Stack=5, Locals=3, Args_size=3
   0:	aload_0
   1:	invokeinterface	#36,  1; //InterfaceMethod scala/collection/generic/IterableTemplate.isEmpty:()Z
   6:	ifeq	13
   9:	aload_1
   10:	goto	41
   13:	aload_2
   14:	aload_0
   15:	invokeinterface	#40,  1; //InterfaceMethod scala/collection/generic/IterableTemplate.head:()Ljava/lang/Object;
   20:	aload_0
   21:	invokeinterface	#57,  1; //InterfaceMethod scala/collection/generic/TraversableTemplate.tail:()Lscala/collection/generic/TraversableTemplate;
   26:	checkcast	#15; //class scala/collection/generic/LinearSequenceTemplate
   29:	aload_1
   30:	aload_2
   31:	invokeinterface	#166,  3; //InterfaceMethod scala/collection/generic/LinearSequenceTemplate.foldRight:(Ljava/lang/Object;Lscala/Function2;)Ljava/lang/Object;
   36:	invokeinterface	#152,  3; //InterfaceMethod scala/Function2.apply:(Ljava/lang/Object;Ljava/lang/Object;)Ljava/lang/Object;
   41:	areturn
  LineNumberTable: 
   line 176: 0
   line 177: 13
   line 176: 41

  LocalVariableTable: 
   Start  Length  Slot  Name   Signature
   0      42      0    $this       Lscala/collection/generic/LinearSequenceTemplate;
   0      42      1    z       Ljava/lang/Object;
   0      42      2    f       Lscala/Function2;


public static java.lang.Object foldLeft(scala.collection.generic.LinearSequenceTemplate, java.lang.Object, scala.Function2);
  Code:
   Stack=3, Locals=5, Args_size=3
   0:	aload_1
   1:	astore_3
   2:	aload_0
   3:	astore	4
   5:	aload	4
   7:	invokeinterface	#36,  1; //InterfaceMethod scala/collection/generic/IterableTemplate.isEmpty:()Z
   12:	ifeq	17
   15:	aload_3
   16:	areturn
   17:	aload_2
   18:	aload_3
   19:	aload	4
   21:	invokeinterface	#40,  1; //InterfaceMethod scala/collection/generic/IterableTemplate.head:()Ljava/lang/Object;
   26:	invokeinterface	#152,  3; //InterfaceMethod scala/Function2.apply:(Ljava/lang/Object;Ljava/lang/Object;)Ljava/lang/Object;
   31:	astore_3
   32:	aload	4
   34:	invokeinterface	#57,  1; //InterfaceMethod scala/collection/generic/TraversableTemplate.tail:()Lscala/collection/generic/TraversableTemplate;
   39:	checkcast	#15; //class scala/collection/generic/LinearSequenceTemplate
   42:	astore	4
   44:	goto	5
  LineNumberTable: 
   line 159: 0
   line 160: 2
   line 161: 5
   line 165: 15
   line 162: 17
   line 163: 32
   line 161: 44

  LocalVariableTable: 
   Start  Length  Slot  Name   Signature
   0      47      0    $this       Lscala/collection/generic/LinearSequenceTemplate;
   0      47      1    z       Ljava/lang/Object;
   0      47      2    f       Lscala/Function2;
   2      14      3    acc       Ljava/lang/Object;
   17      30      3    acc       Ljava/lang/Object;
   5      11      4    these       Lscala/collection/generic/LinearSequenceTemplate;
   17      30      4    these       Lscala/collection/generic/LinearSequenceTemplate;


public static scala.Option find(scala.collection.generic.LinearSequenceTemplate, scala.Function1);
  Code:
   Stack=3, Locals=3, Args_size=2
   0:	aload_0
   1:	astore_2
   2:	aload_2
   3:	invokeinterface	#36,  1; //InterfaceMethod scala/collection/generic/IterableTemplate.isEmpty:()Z
   8:	ifeq	15
   11:	getstatic	#176; //Field scala/None$.MODULE$:Lscala/None$;
   14:	areturn
   15:	aload_1
   16:	aload_2
   17:	invokeinterface	#40,  1; //InterfaceMethod scala/collection/generic/IterableTemplate.head:()Ljava/lang/Object;
   22:	invokeinterface	#46,  2; //InterfaceMethod scala/Function1.apply:(Ljava/lang/Object;)Ljava/lang/Object;
   27:	invokestatic	#51; //Method scala/runtime/BoxesRunTime.unboxToBoolean:(Ljava/lang/Object;)Z
   30:	ifeq	47
   33:	new	#178; //class scala/Some
   36:	dup
   37:	aload_2
   38:	invokeinterface	#40,  1; //InterfaceMethod scala/collection/generic/IterableTemplate.head:()Ljava/lang/Object;
   43:	invokespecial	#181; //Method scala/Some."<init>":(Ljava/lang/Object;)V
   46:	areturn
   47:	aload_2
   48:	invokeinterface	#57,  1; //InterfaceMethod scala/collection/generic/TraversableTemplate.tail:()Lscala/collection/generic/TraversableTemplate;
   53:	checkcast	#15; //class scala/collection/generic/LinearSequenceTemplate
   56:	astore_2
   57:	goto	2
  LineNumberTable: 
   line 142: 0
   line 143: 2
   line 147: 11
   line 144: 15
   line 145: 47
   line 143: 57

  LocalVariableTable: 
   Start  Length  Slot  Name   Signature
   0      60      0    $this       Lscala/collection/generic/LinearSequenceTemplate;
   0      60      1    p       Lscala/Function1;
   2      12      2    these       Lscala/collection/generic/LinearSequenceTemplate;
   15      45      2    these       Lscala/collection/generic/LinearSequenceTemplate;


public static int count(scala.collection.generic.LinearSequenceTemplate, scala.Function1);
  Code:
   Stack=2, Locals=4, Args_size=2
   0:	aload_0
   1:	astore_2
   2:	iconst_0
   3:	istore_3
   4:	aload_2
   5:	invokeinterface	#36,  1; //InterfaceMethod scala/collection/generic/IterableTemplate.isEmpty:()Z
   10:	ifeq	15
   13:	iload_3
   14:	ireturn
   15:	aload_1
   16:	aload_2
   17:	invokeinterface	#40,  1; //InterfaceMethod scala/collection/generic/IterableTemplate.head:()Ljava/lang/Object;
   22:	invokeinterface	#46,  2; //InterfaceMethod scala/Function1.apply:(Ljava/lang/Object;)Ljava/lang/Object;
   27:	invokestatic	#51; //Method scala/runtime/BoxesRunTime.unboxToBoolean:(Ljava/lang/Object;)Z
   30:	ifeq	37
   33:	iload_3
   34:	iconst_1
   35:	iadd
   36:	istore_3
   37:	aload_2
   38:	invokeinterface	#57,  1; //InterfaceMethod scala/collection/generic/TraversableTemplate.tail:()Lscala/collection/generic/TraversableTemplate;
   43:	checkcast	#15; //class scala/collection/generic/LinearSequenceTemplate
   46:	astore_2
   47:	goto	4
  LineNumberTable: 
   line 125: 0
   line 126: 2
   line 127: 4
   line 131: 13
   line 128: 15
   line 129: 37
   line 127: 47

  LocalVariableTable: 
   Start  Length  Slot  Name   Signature
   0      50      0    $this       Lscala/collection/generic/LinearSequenceTemplate;
   0      50      1    p       Lscala/Function1;
   2      12      2    these       Lscala/collection/generic/LinearSequenceTemplate;
   15      35      2    these       Lscala/collection/generic/LinearSequenceTemplate;
   4      10      3    cnt       I
   15      35      3    cnt       I


public static boolean exists(scala.collection.generic.LinearSequenceTemplate, scala.Function1);
  Code:
   Stack=2, Locals=3, Args_size=2
   0:	aload_0
   1:	astore_2
   2:	aload_2
   3:	invokeinterface	#36,  1; //InterfaceMethod scala/collection/generic/IterableTemplate.isEmpty:()Z
   8:	ifeq	13
   11:	iconst_0
   12:	ireturn
   13:	aload_1
   14:	aload_2
   15:	invokeinterface	#40,  1; //InterfaceMethod scala/collection/generic/IterableTemplate.head:()Ljava/lang/Object;
   20:	invokeinterface	#46,  2; //InterfaceMethod scala/Function1.apply:(Ljava/lang/Object;)Ljava/lang/Object;
   25:	invokestatic	#51; //Method scala/runtime/BoxesRunTime.unboxToBoolean:(Ljava/lang/Object;)Z
   28:	ifeq	33
   31:	iconst_1
   32:	ireturn
   33:	aload_2
   34:	invokeinterface	#57,  1; //InterfaceMethod scala/collection/generic/TraversableTemplate.tail:()Lscala/collection/generic/TraversableTemplate;
   39:	checkcast	#15; //class scala/collection/generic/LinearSequenceTemplate
   42:	astore_2
   43:	goto	2
  LineNumberTable: 
   line 111: 0
   line 112: 2
   line 116: 11
   line 113: 13
   line 114: 33
   line 112: 43

  LocalVariableTable: 
   Start  Length  Slot  Name   Signature
   0      46      0    $this       Lscala/collection/generic/LinearSequenceTemplate;
   0      46      1    p       Lscala/Function1;
   2      10      2    these       Lscala/collection/generic/LinearSequenceTemplate;
   13      33      2    these       Lscala/collection/generic/LinearSequenceTemplate;


public static boolean forall(scala.collection.generic.LinearSequenceTemplate, scala.Function1);
  Code:
   Stack=2, Locals=3, Args_size=2
   0:	aload_0
   1:	astore_2
   2:	aload_2
   3:	invokeinterface	#36,  1; //InterfaceMethod scala/collection/generic/IterableTemplate.isEmpty:()Z
   8:	ifeq	13
   11:	iconst_1
   12:	ireturn
   13:	aload_1
   14:	aload_2
   15:	invokeinterface	#40,  1; //InterfaceMethod scala/collection/generic/IterableTemplate.head:()Ljava/lang/Object;
   20:	invokeinterface	#46,  2; //InterfaceMethod scala/Function1.apply:(Ljava/lang/Object;)Ljava/lang/Object;
   25:	invokestatic	#51; //Method scala/runtime/BoxesRunTime.unboxToBoolean:(Ljava/lang/Object;)Z
   28:	ifeq	44
   31:	aload_2
   32:	invokeinterface	#57,  1; //InterfaceMethod scala/collection/generic/TraversableTemplate.tail:()Lscala/collection/generic/TraversableTemplate;
   37:	checkcast	#15; //class scala/collection/generic/LinearSequenceTemplate
   40:	astore_2
   41:	goto	2
   44:	iconst_0
   45:	ireturn
  LineNumberTable: 
   line 95: 0
   line 96: 2
   line 100: 11
   line 97: 13
   line 98: 31
   line 96: 41
   line 97: 44

  LocalVariableTable: 
   Start  Length  Slot  Name   Signature
   0      46      0    $this       Lscala/collection/generic/LinearSequenceTemplate;
   0      46      1    p       Lscala/Function1;
   2      10      2    these       Lscala/collection/generic/LinearSequenceTemplate;
   13      33      2    these       Lscala/collection/generic/LinearSequenceTemplate;


public static void foreach(scala.collection.generic.LinearSequenceTemplate, scala.Function1);
  Code:
   Stack=2, Locals=3, Args_size=2
   0:	aload_0
   1:	astore_2
   2:	aload_2
   3:	invokeinterface	#36,  1; //InterfaceMethod scala/collection/generic/IterableTemplate.isEmpty:()Z
   8:	ifeq	12
   11:	return
   12:	aload_1
   13:	aload_2
   14:	invokeinterface	#40,  1; //InterfaceMethod scala/collection/generic/IterableTemplate.head:()Ljava/lang/Object;
   19:	invokeinterface	#46,  2; //InterfaceMethod scala/Function1.apply:(Ljava/lang/Object;)Ljava/lang/Object;
   24:	pop
   25:	aload_2
   26:	invokeinterface	#57,  1; //InterfaceMethod scala/collection/generic/TraversableTemplate.tail:()Lscala/collection/generic/TraversableTemplate;
   31:	checkcast	#15; //class scala/collection/generic/LinearSequenceTemplate
   34:	astore_2
   35:	goto	2
  LineNumberTable: 
   line 80: 0
   line 81: 2
   line 79: 11
   line 82: 12
   line 83: 25
   line 81: 35

  LocalVariableTable: 
   Start  Length  Slot  Name   Signature
   0      38      0    $this       Lscala/collection/generic/LinearSequenceTemplate;
   0      38      1    f       Lscala/Function1;
   2      36      2    these       Lscala/collection/generic/LinearSequenceTemplate;


public static scala.collection.Iterator iterator(scala.collection.generic.LinearSequenceTemplate);
  Code:
   Stack=3, Locals=1, Args_size=1
   0:	new	#192; //class scala/collection/generic/LinearSequenceTemplate$$anon$1
   3:	dup
   4:	aload_0
   5:	invokespecial	#194; //Method scala/collection/generic/LinearSequenceTemplate$$anon$1."<init>":(Lscala/collection/generic/LinearSequenceTemplate;)V
   8:	areturn
  LineNumberTable: 
   line 64: 0

  LocalVariableTable: 
   Start  Length  Slot  Name   Signature
   0      9      0    $this       Lscala/collection/generic/LinearSequenceTemplate;


public static java.lang.Object apply(scala.collection.generic.LinearSequenceTemplate, int);
  Code:
   Stack=2, Locals=2, Args_size=2
   0:	aload_0
   1:	iload_1
   2:	invokeinterface	#69,  2; //InterfaceMethod scala/collection/generic/LinearSequenceTemplate.drop:(I)Lscala/collection/generic/LinearSequenceTemplate;
   7:	invokeinterface	#40,  1; //InterfaceMethod scala/collection/generic/IterableTemplate.head:()Ljava/lang/Object;
   12:	areturn
  LineNumberTable: 
   line 60: 0

  LocalVariableTable: 
   Start  Length  Slot  Name   Signature
   0      13      0    $this       Lscala/collection/generic/LinearSequenceTemplate;
   0      13      1    n       I


public static int length(scala.collection.generic.LinearSequenceTemplate);
  Code:
   Stack=2, Locals=3, Args_size=1
   0:	aload_0
   1:	astore_1
   2:	iconst_0
   3:	istore_2
   4:	aload_1
   5:	invokeinterface	#36,  1; //InterfaceMethod scala/collection/generic/IterableTemplate.isEmpty:()Z
   10:	ifeq	15
   13:	iload_2
   14:	ireturn
   15:	iload_2
   16:	iconst_1
   17:	iadd
   18:	istore_2
   19:	aload_1
   20:	invokeinterface	#57,  1; //InterfaceMethod scala/collection/generic/TraversableTemplate.tail:()Lscala/collection/generic/TraversableTemplate;
   25:	checkcast	#15; //class scala/collection/generic/LinearSequenceTemplate
   28:	astore_1
   29:	goto	4
  LineNumberTable: 
   line 44: 0
   line 45: 2
   line 46: 4
   line 50: 13
   line 47: 15
   line 48: 19
   line 46: 29

  LocalVariableTable: 
   Start  Length  Slot  Name   Signature
   0      32      0    $this       Lscala/collection/generic/LinearSequenceTemplate;
   2      12      1    these       Lscala/collection/generic/LinearSequenceTemplate;
   15      17      1    these       Lscala/collection/generic/LinearSequenceTemplate;
   4      10      2    len       I
   15      17      2    len       I


}

