Compiled from "LinkedListTemplate.scala"
public abstract class scala.collection.generic.LinkedListTemplate$class extends java.lang.Object
  SourceFile: "LinkedListTemplate.scala"
  Scala: length = 0x
   
  InnerClass: 
   public final #117= #34 of #13; //$anon$1=class scala/collection/generic/LinkedListTemplate$$anon$1 of class scala/collection/generic/LinkedListTemplate
  minor version: 0
  major version: 49
  Constant pool:
const #1 = Asciz	SourceFile;
const #2 = Asciz	LinkedListTemplate.scala;
const #3 = Asciz	$init$;
const #4 = Asciz	(Lscala/collection/generic/LinkedListTemplate;)V;
const #5 = Asciz	Code;
const #6 = Asciz	LineNumberTable;
const #7 = Asciz	$this;
const #8 = Asciz	Lscala/collection/generic/LinkedListTemplate;;
const #9 = Asciz	LocalVariableTable;
const #10 = Asciz	foreach;
const #11 = Asciz	(Lscala/collection/generic/LinkedListTemplate;Lscala/Function1;)V;
const #12 = Asciz	scala/collection/generic/LinkedListTemplate;
const #13 = class	#12;	//  scala/collection/generic/LinkedListTemplate
const #14 = Asciz	elem;
const #15 = Asciz	()Ljava/lang/Object;;
const #16 = NameAndType	#14:#15;//  elem:()Ljava/lang/Object;
const #17 = InterfaceMethod	#13.#16;	//  scala/collection/generic/LinkedListTemplate.elem:()Ljava/lang/Object;
const #18 = Asciz	scala/Function1;
const #19 = class	#18;	//  scala/Function1
const #20 = Asciz	apply;
const #21 = Asciz	(Ljava/lang/Object;)Ljava/lang/Object;;
const #22 = NameAndType	#20:#21;//  apply:(Ljava/lang/Object;)Ljava/lang/Object;
const #23 = InterfaceMethod	#19.#22;	//  scala/Function1.apply:(Ljava/lang/Object;)Ljava/lang/Object;
const #24 = Asciz	next;
const #25 = Asciz	()Lscala/collection/Sequence;;
const #26 = NameAndType	#24:#25;//  next:()Lscala/collection/Sequence;
const #27 = InterfaceMethod	#13.#26;	//  scala/collection/generic/LinkedListTemplate.next:()Lscala/collection/Sequence;
const #28 = Asciz	f;
const #29 = Asciz	Lscala/Function1;;
const #30 = Asciz	these;
const #31 = Asciz	iterator;
const #32 = Asciz	(Lscala/collection/generic/LinkedListTemplate;)Lscala/collection/Iterator;;
const #33 = Asciz	scala/collection/generic/LinkedListTemplate$$anon$1;
const #34 = class	#33;	//  scala/collection/generic/LinkedListTemplate$$anon$1
const #35 = Asciz	<init>;
const #36 = NameAndType	#35:#4;//  "<init>":(Lscala/collection/generic/LinkedListTemplate;)V
const #37 = Method	#34.#36;	//  scala/collection/generic/LinkedListTemplate$$anon$1."<init>":(Lscala/collection/generic/LinkedListTemplate;)V
const #38 = Asciz	get;
const #39 = Asciz	(Lscala/collection/generic/LinkedListTemplate;I)Lscala/Option;;
const #40 = Asciz	drop;
const #41 = Asciz	(I)Lscala/collection/Sequence;;
const #42 = NameAndType	#40:#41;//  drop:(I)Lscala/collection/Sequence;
const #43 = InterfaceMethod	#13.#42;	//  scala/collection/generic/LinkedListTemplate.drop:(I)Lscala/collection/Sequence;
const #44 = Asciz	scala/Some;
const #45 = class	#44;	//  scala/Some
const #46 = Asciz	(Ljava/lang/Object;)V;
const #47 = NameAndType	#35:#46;//  "<init>":(Ljava/lang/Object;)V
const #48 = Method	#45.#47;	//  scala/Some."<init>":(Ljava/lang/Object;)V
const #49 = Asciz	scala/None$;
const #50 = class	#49;	//  scala/None$
const #51 = Asciz	MODULE$;
const #52 = Asciz	Lscala/None$;;
const #53 = NameAndType	#51:#52;//  MODULE$:Lscala/None$;
const #54 = Field	#50.#53;	//  scala/None$.MODULE$:Lscala/None$;
const #55 = Asciz	n;
const #56 = Asciz	I;
const #57 = Asciz	loc;
const #58 = Asciz	Lscala/collection/Sequence;;
const #59 = Asciz	update;
const #60 = Asciz	(Lscala/collection/generic/LinkedListTemplate;ILjava/lang/Object;)V;
const #61 = Asciz	elem_$eq;
const #62 = NameAndType	#61:#46;//  elem_$eq:(Ljava/lang/Object;)V
const #63 = InterfaceMethod	#13.#62;	//  scala/collection/generic/LinkedListTemplate.elem_$eq:(Ljava/lang/Object;)V
const #64 = Asciz	java/lang/IndexOutOfBoundsException;
const #65 = class	#64;	//  java/lang/IndexOutOfBoundsException
const #66 = Asciz	scala/runtime/BoxesRunTime;
const #67 = class	#66;	//  scala/runtime/BoxesRunTime
const #68 = Asciz	boxToInteger;
const #69 = Asciz	(I)Ljava/lang/Integer;;
const #70 = NameAndType	#68:#69;//  boxToInteger:(I)Ljava/lang/Integer;
const #71 = Method	#67.#70;	//  scala/runtime/BoxesRunTime.boxToInteger:(I)Ljava/lang/Integer;
const #72 = Asciz	java/lang/Object;
const #73 = class	#72;	//  java/lang/Object
const #74 = Asciz	toString;
const #75 = Asciz	()Ljava/lang/String;;
const #76 = NameAndType	#74:#75;//  toString:()Ljava/lang/String;
const #77 = Method	#73.#76;	//  java/lang/Object.toString:()Ljava/lang/String;
const #78 = Asciz	(Ljava/lang/String;)V;
const #79 = NameAndType	#35:#78;//  "<init>":(Ljava/lang/String;)V
const #80 = Method	#65.#79;	//  java/lang/IndexOutOfBoundsException."<init>":(Ljava/lang/String;)V
const #81 = Asciz	x;
const #82 = Asciz	Ljava/lang/Object;;
const #83 = Asciz	(Lscala/collection/generic/LinkedListTemplate;I)Ljava/lang/Object;;
const #84 = Asciz	(Lscala/collection/generic/LinkedListTemplate;I)Lscala/collection/Sequence;;
const #85 = Asciz	scala/collection/generic/TraversableTemplate;
const #86 = class	#85;	//  scala/collection/generic/TraversableTemplate
const #87 = Asciz	thisCollection;
const #88 = Asciz	()Lscala/collection/generic/TraversableTemplate;;
const #89 = NameAndType	#87:#88;//  thisCollection:()Lscala/collection/generic/TraversableTemplate;
const #90 = InterfaceMethod	#86.#89;	//  scala/collection/generic/TraversableTemplate.thisCollection:()Lscala/collection/generic/TraversableTemplate;
const #91 = Asciz	scala/collection/Sequence;
const #92 = class	#91;	//  scala/collection/Sequence
const #93 = Asciz	i;
const #94 = Asciz	insert;
const #95 = Asciz	(Lscala/collection/generic/LinkedListTemplate;Lscala/collection/Sequence;)V;
const #96 = Asciz	append;
const #97 = Asciz	(Lscala/collection/Sequence;)V;
const #98 = NameAndType	#96:#97;//  append:(Lscala/collection/Sequence;)V
const #99 = InterfaceMethod	#13.#98;	//  scala/collection/generic/LinkedListTemplate.append:(Lscala/collection/Sequence;)V
const #100 = Asciz	next_$eq;
const #101 = NameAndType	#100:#97;//  next_$eq:(Lscala/collection/Sequence;)V
const #102 = InterfaceMethod	#13.#101;	//  scala/collection/generic/LinkedListTemplate.next_$eq:(Lscala/collection/Sequence;)V
const #103 = Asciz	that;
const #104 = Asciz	tail;
const #105 = Asciz	(Lscala/collection/generic/LinkedListTemplate;)Lscala/collection/Sequence;;
const #106 = Asciz	head;
const #107 = Asciz	(Lscala/collection/generic/LinkedListTemplate;)Ljava/lang/Object;;
const #108 = Asciz	length;
const #109 = Asciz	(Lscala/collection/generic/LinkedListTemplate;)I;
const #110 = Asciz	()I;
const #111 = NameAndType	#108:#110;//  length:()I
const #112 = InterfaceMethod	#13.#111;	//  scala/collection/generic/LinkedListTemplate.length:()I
const #113 = Asciz	isEmpty;
const #114 = Asciz	(Lscala/collection/generic/LinkedListTemplate;)Z;
const #115 = Asciz	Scala;
const #116 = Asciz	InnerClasses;
const #117 = Asciz	$anon$1;
const #118 = Asciz	scala/collection/generic/LinkedListTemplate$class;
const #119 = class	#118;	//  scala/collection/generic/LinkedListTemplate$class

{
public static void $init$(scala.collection.generic.LinkedListTemplate);
  Code:
   Stack=0, Locals=1, Args_size=1
   0:	return
  LineNumberTable: 
   line 24: 0

  LocalVariableTable: 
   Start  Length  Slot  Name   Signature
   0      1      0    $this       Lscala/collection/generic/LinkedListTemplate;


public static void foreach(scala.collection.generic.LinkedListTemplate, scala.Function1);
  Code:
   Stack=2, Locals=3, Args_size=2
   0:	aload_0
   1:	astore_2
   2:	aload_2
   3:	ifnull	32
   6:	aload_1
   7:	aload_2
   8:	invokeinterface	#17,  1; //InterfaceMethod scala/collection/generic/LinkedListTemplate.elem:()Ljava/lang/Object;
   13:	invokeinterface	#23,  2; //InterfaceMethod scala/Function1.apply:(Ljava/lang/Object;)Ljava/lang/Object;
   18:	pop
   19:	aload_2
   20:	invokeinterface	#27,  1; //InterfaceMethod scala/collection/generic/LinkedListTemplate.next:()Lscala/collection/Sequence;
   25:	checkcast	#13; //class scala/collection/generic/LinkedListTemplate
   28:	astore_2
   29:	goto	2
   32:	return
  LineNumberTable: 
   line 84: 0
   line 85: 2
   line 86: 6
   line 87: 19
   line 85: 29
   line 83: 32

  LocalVariableTable: 
   Start  Length  Slot  Name   Signature
   0      33      0    $this       Lscala/collection/generic/LinkedListTemplate;
   0      33      1    f       Lscala/Function1;
   2      31      2    these       Lscala/collection/generic/LinkedListTemplate;


public static scala.collection.Iterator iterator(scala.collection.generic.LinkedListTemplate);
  Code:
   Stack=3, Locals=1, Args_size=1
   0:	new	#34; //class scala/collection/generic/LinkedListTemplate$$anon$1
   3:	dup
   4:	aload_0
   5:	invokespecial	#37; //Method scala/collection/generic/LinkedListTemplate$$anon$1."<init>":(Lscala/collection/generic/LinkedListTemplate;)V
   8:	areturn
  LineNumberTable: 
   line 73: 0

  LocalVariableTable: 
   Start  Length  Slot  Name   Signature
   0      9      0    $this       Lscala/collection/generic/LinkedListTemplate;


public static scala.Option get(scala.collection.generic.LinkedListTemplate, int);
  Code:
   Stack=3, Locals=3, Args_size=2
   0:	aload_0
   1:	iload_1
   2:	invokeinterface	#43,  2; //InterfaceMethod scala/collection/generic/LinkedListTemplate.drop:(I)Lscala/collection/Sequence;
   7:	astore_2
   8:	aload_2
   9:	ifnull	31
   12:	new	#45; //class scala/Some
   15:	dup
   16:	aload_2
   17:	checkcast	#13; //class scala/collection/generic/LinkedListTemplate
   20:	invokeinterface	#17,  1; //InterfaceMethod scala/collection/generic/LinkedListTemplate.elem:()Ljava/lang/Object;
   25:	invokespecial	#48; //Method scala/Some."<init>":(Ljava/lang/Object;)V
   28:	goto	34
   31:	getstatic	#54; //Field scala/None$.MODULE$:Lscala/None$;
   34:	areturn
  LineNumberTable: 
   line 68: 0
   line 69: 8
   line 70: 31
   line 67: 34

  LocalVariableTable: 
   Start  Length  Slot  Name   Signature
   0      35      0    $this       Lscala/collection/generic/LinkedListTemplate;
   0      35      1    n       I
   8      27      2    loc       Lscala/collection/Sequence;


public static void update(scala.collection.generic.LinkedListTemplate, int, java.lang.Object);
  Code:
   Stack=3, Locals=4, Args_size=3
   0:	aload_0
   1:	iload_1
   2:	invokeinterface	#43,  2; //InterfaceMethod scala/collection/generic/LinkedListTemplate.drop:(I)Lscala/collection/Sequence;
   7:	astore_3
   8:	aload_3
   9:	ifnull	23
   12:	aload_3
   13:	checkcast	#13; //class scala/collection/generic/LinkedListTemplate
   16:	aload_2
   17:	invokeinterface	#63,  2; //InterfaceMethod scala/collection/generic/LinkedListTemplate.elem_$eq:(Ljava/lang/Object;)V
   22:	return
   23:	new	#65; //class java/lang/IndexOutOfBoundsException
   26:	dup
   27:	iload_1
   28:	invokestatic	#71; //Method scala/runtime/BoxesRunTime.boxToInteger:(I)Ljava/lang/Integer;
   31:	invokevirtual	#77; //Method java/lang/Object.toString:()Ljava/lang/String;
   34:	invokespecial	#80; //Method java/lang/IndexOutOfBoundsException."<init>":(Ljava/lang/String;)V
   37:	athrow
  LineNumberTable: 
   line 62: 0
   line 63: 8
   line 61: 22
   line 64: 23

  LocalVariableTable: 
   Start  Length  Slot  Name   Signature
   0      38      0    $this       Lscala/collection/generic/LinkedListTemplate;
   0      38      1    n       I
   0      38      2    x       Ljava/lang/Object;
   8      30      3    loc       Lscala/collection/Sequence;


public static java.lang.Object apply(scala.collection.generic.LinkedListTemplate, int);
  Code:
   Stack=3, Locals=3, Args_size=2
   0:	aload_0
   1:	iload_1
   2:	invokeinterface	#43,  2; //InterfaceMethod scala/collection/generic/LinkedListTemplate.drop:(I)Lscala/collection/Sequence;
   7:	astore_2
   8:	aload_2
   9:	ifnull	22
   12:	aload_2
   13:	checkcast	#13; //class scala/collection/generic/LinkedListTemplate
   16:	invokeinterface	#17,  1; //InterfaceMethod scala/collection/generic/LinkedListTemplate.elem:()Ljava/lang/Object;
   21:	areturn
   22:	new	#65; //class java/lang/IndexOutOfBoundsException
   25:	dup
   26:	iload_1
   27:	invokestatic	#71; //Method scala/runtime/BoxesRunTime.boxToInteger:(I)Ljava/lang/Integer;
   30:	invokevirtual	#77; //Method java/lang/Object.toString:()Ljava/lang/String;
   33:	invokespecial	#80; //Method java/lang/IndexOutOfBoundsException."<init>":(Ljava/lang/String;)V
   36:	athrow
  LineNumberTable: 
   line 56: 0
   line 57: 8
   line 55: 21
   line 58: 22

  LocalVariableTable: 
   Start  Length  Slot  Name   Signature
   0      37      0    $this       Lscala/collection/generic/LinkedListTemplate;
   0      37      1    n       I
   8      29      2    loc       Lscala/collection/Sequence;


public static scala.collection.Sequence drop(scala.collection.generic.LinkedListTemplate, int);
  Code:
   Stack=2, Locals=4, Args_size=2
   0:	iconst_0
   1:	istore_2
   2:	aload_0
   3:	invokeinterface	#90,  1; //InterfaceMethod scala/collection/generic/TraversableTemplate.thisCollection:()Lscala/collection/generic/TraversableTemplate;
   8:	checkcast	#92; //class scala/collection/Sequence
   11:	astore_3
   12:	iload_2
   13:	iload_1
   14:	if_icmpge	38
   17:	aload_3
   18:	ifnull	38
   21:	aload_3
   22:	checkcast	#13; //class scala/collection/generic/LinkedListTemplate
   25:	invokeinterface	#27,  1; //InterfaceMethod scala/collection/generic/LinkedListTemplate.next:()Lscala/collection/Sequence;
   30:	astore_3
   31:	iload_2
   32:	iconst_1
   33:	iadd
   34:	istore_2
   35:	goto	12
   38:	aload_3
   39:	areturn
  LineNumberTable: 
   line 46: 0
   line 47: 2
   line 48: 12
   line 49: 21
   line 50: 31
   line 48: 35
   line 52: 38

  LocalVariableTable: 
   Start  Length  Slot  Name   Signature
   0      40      0    $this       Lscala/collection/generic/LinkedListTemplate;
   0      40      1    n       I
   2      37      2    i       I
   12      27      3    these       Lscala/collection/Sequence;


public static void insert(scala.collection.generic.LinkedListTemplate, scala.collection.Sequence);
  Code:
   Stack=2, Locals=2, Args_size=2
   0:	aload_1
   1:	ifnull	26
   4:	aload_1
   5:	checkcast	#13; //class scala/collection/generic/LinkedListTemplate
   8:	aload_0
   9:	invokeinterface	#27,  1; //InterfaceMethod scala/collection/generic/LinkedListTemplate.next:()Lscala/collection/Sequence;
   14:	invokeinterface	#99,  2; //InterfaceMethod scala/collection/generic/LinkedListTemplate.append:(Lscala/collection/Sequence;)V
   19:	aload_0
   20:	aload_1
   21:	invokeinterface	#102,  2; //InterfaceMethod scala/collection/generic/LinkedListTemplate.next_$eq:(Lscala/collection/Sequence;)V
   26:	return
  LineNumberTable: 
   line 40: 0
   line 41: 4
   line 42: 19
   line 40: 26

  LocalVariableTable: 
   Start  Length  Slot  Name   Signature
   0      27      0    $this       Lscala/collection/generic/LinkedListTemplate;
   0      27      1    that       Lscala/collection/Sequence;


public static void append(scala.collection.generic.LinkedListTemplate, scala.collection.Sequence);
  Code:
   Stack=2, Locals=2, Args_size=2
   0:	aload_0
   1:	invokeinterface	#27,  1; //InterfaceMethod scala/collection/generic/LinkedListTemplate.next:()Lscala/collection/Sequence;
   6:	ifnonnull	19
   9:	aload_0
   10:	aload_1
   11:	invokeinterface	#102,  2; //InterfaceMethod scala/collection/generic/LinkedListTemplate.next_$eq:(Lscala/collection/Sequence;)V
   16:	goto	34
   19:	aload_0
   20:	invokeinterface	#27,  1; //InterfaceMethod scala/collection/generic/LinkedListTemplate.next:()Lscala/collection/Sequence;
   25:	checkcast	#13; //class scala/collection/generic/LinkedListTemplate
   28:	aload_1
   29:	invokeinterface	#99,  2; //InterfaceMethod scala/collection/generic/LinkedListTemplate.append:(Lscala/collection/Sequence;)V
   34:	return
  LineNumberTable: 
   line 38: 0

  LocalVariableTable: 
   Start  Length  Slot  Name   Signature
   0      35      0    $this       Lscala/collection/generic/LinkedListTemplate;
   0      35      1    that       Lscala/collection/Sequence;


public static scala.collection.Sequence tail(scala.collection.generic.LinkedListTemplate);
  Code:
   Stack=1, Locals=1, Args_size=1
   0:	aload_0
   1:	invokeinterface	#27,  1; //InterfaceMethod scala/collection/generic/LinkedListTemplate.next:()Lscala/collection/Sequence;
   6:	areturn
  LineNumberTable: 
   line 35: 0

  LocalVariableTable: 
   Start  Length  Slot  Name   Signature
   0      7      0    $this       Lscala/collection/generic/LinkedListTemplate;


public static java.lang.Object head(scala.collection.generic.LinkedListTemplate);
  Code:
   Stack=1, Locals=1, Args_size=1
   0:	aload_0
   1:	invokeinterface	#17,  1; //InterfaceMethod scala/collection/generic/LinkedListTemplate.elem:()Ljava/lang/Object;
   6:	areturn
  LineNumberTable: 
   line 33: 0

  LocalVariableTable: 
   Start  Length  Slot  Name   Signature
   0      7      0    $this       Lscala/collection/generic/LinkedListTemplate;


public static int length(scala.collection.generic.LinkedListTemplate);
  Code:
   Stack=2, Locals=1, Args_size=1
   0:	iconst_1
   1:	aload_0
   2:	invokeinterface	#27,  1; //InterfaceMethod scala/collection/generic/LinkedListTemplate.next:()Lscala/collection/Sequence;
   7:	ifnonnull	14
   10:	iconst_0
   11:	goto	28
   14:	aload_0
   15:	invokeinterface	#27,  1; //InterfaceMethod scala/collection/generic/LinkedListTemplate.next:()Lscala/collection/Sequence;
   20:	checkcast	#13; //class scala/collection/generic/LinkedListTemplate
   23:	invokeinterface	#112,  1; //InterfaceMethod scala/collection/generic/LinkedListTemplate.length:()I
   28:	iadd
   29:	ireturn
  LineNumberTable: 
   line 31: 0

  LocalVariableTable: 
   Start  Length  Slot  Name   Signature
   0      30      0    $this       Lscala/collection/generic/LinkedListTemplate;


public static boolean isEmpty(scala.collection.generic.LinkedListTemplate);
  Code:
   Stack=1, Locals=1, Args_size=1
   0:	iconst_0
   1:	ireturn
  LineNumberTable: 
   line 29: 0

  LocalVariableTable: 
   Start  Length  Slot  Name   Signature
   0      2      0    $this       Lscala/collection/generic/LinkedListTemplate;


}

