Compiled from "MapFactory.scala"
public abstract class scala.collection.generic.MapFactory extends java.lang.Object implements scala.ScalaObject
  SourceFile: "MapFactory.scala"
  ScalaSig: length = 0x3
   05 00 00 
  Signature: length = 0x2
   00 34 
  RuntimeVisibleAnnotations: length = 0xB
   00 01 00 35 00 01 00 36 73 00 37 
  InnerClass: 
   public MapCanBuildFrom=class scala/collection/generic/MapFactory$MapCanBuildFrom of class scala/collection/generic/MapFactory
  minor version: 0
  major version: 49
  Constant pool:
Asciz	SourceFile;
Asciz	MapFactory.scala;
Asciz	empty;
Asciz	()Lscala/collection/Map;;
Asciz	<A:Ljava/lang/Object;B:Ljava/lang/Object;>()TCC;;
Asciz	Signature;
Asciz	apply;
Asciz	(Lscala/collection/Seq;)Lscala/collection/Map;;
Asciz	Code;
Asciz	LineNumberTable;
Asciz	scala/collection/generic/MapFactory;
class	scala/collection/generic/MapFactory
Asciz	newBuilder;
Asciz	()Lscala/collection/mutable/Builder;;
NameAndType	newBuilder:()Lscala/collection/mutable/Builder;
Method	scala/collection/generic/MapFactory.newBuilder:()Lscala/collection/mutable/Builder;
Asciz	scala/collection/generic/Growable;
class	scala/collection/generic/Growable
Asciz	$plus$plus$eq;
Asciz	(Lscala/collection/TraversableOnce;)Lscala/collection/generic/Growable;;
NameAndType	$plus$plus$eq:(Lscala/collection/TraversableOnce;)Lscala/collection/generic/Growable;
InterfaceMethod	scala/collection/generic/Growable.$plus$plus$eq:(Lscala/collection/TraversableOnce;)Lscala/collection/generic/Growable;
Asciz	scala/collection/mutable/Builder;
class	scala/collection/mutable/Builder
Asciz	result;
Asciz	()Ljava/lang/Object;;
NameAndType	result:()Ljava/lang/Object;
InterfaceMethod	scala/collection/mutable/Builder.result:()Ljava/lang/Object;
Asciz	scala/collection/Map;
class	scala/collection/Map
Asciz	this;
Asciz	Lscala/collection/generic/MapFactory;;
Asciz	elems;
Asciz	Lscala/collection/Seq;;
Asciz	LocalVariableTable;
Asciz	<A:Ljava/lang/Object;B:Ljava/lang/Object;>(Lscala/collection/Seq<Lscala/Tuple2<TA;TB;>;>;)TCC;;
Asciz	scala/collection/mutable/MapBuilder;
class	scala/collection/mutable/MapBuilder
NameAndType	empty:()Lscala/collection/Map;
Method	scala/collection/generic/MapFactory.empty:()Lscala/collection/Map;
Asciz	<init>;
Asciz	(Lscala/collection/Map;)V;
NameAndType	"<init>":(Lscala/collection/Map;)V
Method	scala/collection/mutable/MapBuilder."<init>":(Lscala/collection/Map;)V
Asciz	<A:Ljava/lang/Object;B:Ljava/lang/Object;>()Lscala/collection/mutable/Builder<Lscala/Tuple2<TA;TB;>;TCC;>;;
Asciz	()V;
Asciz	java/lang/Object;
class	java/lang/Object
NameAndType	"<init>":()V
Method	java/lang/Object."<init>":()V
Asciz	ScalaSig;
Asciz	<CC:Lscala/collection/Map<Ljava/lang/Object;Ljava/lang/Object;>;>Ljava/lang/Object;Lscala/ScalaObject;;
Asciz	Lscala/reflect/ScalaSignature;;
Asciz	bytes;
Asciz	-a!BI!AC'ba7\r^8ss*1BOtWM]5d\t)a!d_2dWm;j_:TaBgG.Y+\tQadEM\"D\t5Q!AD\t1gn!!!.<b\tRBPE*,7\r\t)UiAB-1bU2bY|%M[3di\")C31A(8jiz\"A\t7aR\"uqB?\r\t+2!I5#\tSG%AE>$.8h%\r1F\tO!\t!AK\taAH]3gS:,W.8u}A!F4!BA\ri\r\t;5\"B\raF!\r\t)EJ!A\rsiAQGCqFAC!IsL:\tADAANCBdn[3\tuqBfM\tw!\t!Ay\t!1i7ma\ritH\t;yq\tAICqFA`IE\"!\"\rSD!A=1a3)A\"G)W;z+\r9j\t;yA%\nAaCqAQCqCNa*AbaBd0FP%R#\"U+\tuqk\t;I#B'\ra\t;Q#\"'\ra-2\raVK2,Wn\t)aSBA-)a$/9fCR,GM\t)m6+]\r\t1A+9mKJBQA}!B\3xVLGZ3s+\rN\tC47.Dc\tG!AnkR'\r\3\n'a\"vS2$WM\t)m;QAa&CqUAQ'Cq=LgB79q\"T1qt')^5mIx.\_^L87aNRaG9tkjL!A\rgNQ;jY4%o\7QTT\"\tQYf\t;]$B7\ra\t;e$\"7\ra\t;y1CYAF~!!HN=\t5cGA@\t1\tC,(y\ra]MJ|WNY;
Asciz	RuntimeVisibleAnnotations;
Asciz	InnerClasses;
Asciz	scala/collection/generic/MapFactory$MapCanBuildFrom;
class	scala/collection/generic/MapFactory$MapCanBuildFrom
Asciz	MapCanBuildFrom;
Asciz	scala/ScalaObject;
class	scala/ScalaObject

{
public abstract scala.collection.Map empty();
  Signature: ()Lscala/collection/Map;
  Signature: length = 0x2
   00 05 

public scala.collection.Map apply(scala.collection.Seq);
  Signature: (Lscala/collection/Seq;)Lscala/collection/Map;
  Code:
   Stack=2, Locals=2, Args_size=2
	aload_0
	invokevirtual	Method newBuilder:()Lscala/collection/mutable/Builder;
	aload_1
	invokeinterface	InterfaceMethod scala/collection/generic/Growable.$plus$plus$eq:(Lscala/collection/TraversableOnce;)Lscala/collection/generic/Growable;
	checkcast	class scala/collection/mutable/Builder
	invokeinterface	InterfaceMethod scala/collection/mutable/Builder.result:()Ljava/lang/Object;
	checkcast	class scala/collection/Map
	areturn
  Labels:
  LocalVariableTable: 
   Start  Length  Slot  Name   Signature
   0      22      0    this       Lscala/collection/generic/MapFactory;
   0      22      1    elems       Lscala/collection/Seq;

  Signature: length = 0x2
   00 24 

public scala.collection.mutable.Builder newBuilder();
  Signature: ()Lscala/collection/mutable/Builder;
  Code:
   Stack=3, Locals=1, Args_size=1
	new	class scala/collection/mutable/MapBuilder
	dup
	aload_0
	invokevirtual	Method empty:()Lscala/collection/Map;
	invokespecial	Method scala/collection/mutable/MapBuilder."<init>":(Lscala/collection/Map;)V
	areturn
  Labels:
  Signature: length = 0x2
   00 2D 

public scala.collection.generic.MapFactory();
  Signature: ()V
  Code:
   Stack=1, Locals=1, Args_size=1
	aload_0
	invokespecial	Method java/lang/Object."<init>":()V
	return
  Labels:
  Signature: length = 0x2
   00 2E 

}

