Compiled from "MapFactory.scala"
public abstract class scala.collection.generic.MapFactory extends java.lang.Object implements scala.ScalaObject
  SourceFile: "MapFactory.scala"
  Signature: length = 0x2
   00 2C 
  ScalaSig: length = 0x31F
   05 00 FFFFFF81 00 06 05 01 02 FFFFFF81 00 09 02 0A 4D 61 70
   46 61 63 74 6F 72 79 0A 02 03 04 01 07 67 65 6E
   65 72 69 63 0A 02 05 06 01 0A 63 6F 6C 6C 65 63
   74 69 6F 6E 0A 01 07 01 05 73 63 61 6C 61 03 00
   15 02 0A 1E 13 03 00 0B 13 10 02 0C 11 0D 01 0D
   0A 02 0E 0F 01 04 6C 61 6E 67 0A 01 10 01 04 6A
   61 76 61 09 02 12 0D 02 06 4F 62 6A 65 63 74 10
   02 14 15 0D 01 06 09 02 16 06 02 0B 53 63 61 6C
   61 4F 62 6A 65 63 74 08 05 18 00 FFFFFF84 00 19 01 06
   3C 69 6E 69 74 3E 14 01 1A 10 03 1B 00 1C 0D 01
   02 10 02 1D 1E 0C 00 04 05 1F 00 FFFFFFC2 00 20 02 02
   43 43 15 03 21 2D 34 11 02 22 25 10 02 14 23 09
   02 24 06 02 07 4E 6F 74 68 69 6E 67 12 03 26 28
   36 06 08 27 02 FFFFFF84 FFFFFF80 FFFFFF80 FFFFFF80 00 25 02 0C 3C 72 65
   66 69 6E 65 6D 65 6E 74 3E 10 04 29 2A 2C 33 0D
   01 04 09 02 2B 04 02 03 4D 61 70 10 02 1D 2D 04
   08 2E 1E FFFFFF84 FFFFFF80 FFFFFF80 FFFFFFC2 00 2F 02 01 41 11 02 22 30
   10 02 14 31 09 02 32 06 02 03 41 6E 79 10 02 1D
   34 04 08 35 1E FFFFFF84 FFFFFF80 FFFFFF80 FFFFFFC2 00 2F 02 01 42 10 05
   1B 37 2C 33 39 09 02 38 02 02 0B 4D 61 70 54 65
   6D 70 6C 61 74 65 10 04 1D 1E 2C 33 05 08 3B 00
   FFFFFF84 FFFFFF80 FFFFFF80 FFFFFF80 00 3C 02 04 43 6F 6C 6C 30 03 3D 3F
   42 10 04 1D 1E 3E 41 10 02 1D 3F 04 08 40 00 FFFFFF84
   FFFFFF80 FFFFFF80 FFFFFF82 00 2F 02 03 5F 24 31 10 02 1D 42 04 08
   43 00 FFFFFF84 FFFFFF80 FFFFFF80 FFFFFF82 00 2F 02 03 5F 24 32 08 05 45
   00 FFFFFF86 00 46 01 0A 6E 65 77 42 75 69 6C 64 65 72
   15 03 47 4E 50 10 04 1B 48 4A 51 09 02 49 02 02
   07 42 75 69 6C 64 65 72 10 04 14 4B 4D 4F 09 02
   4C 06 02 06 54 75 70 6C 65 32 10 02 1D 4E 04 08
   2E 44 FFFFFF84 FFFFFF80 FFFFFF80 FFFFFFC2 00 2F 10 02 1D 50 04 08 35 44
   FFFFFF84 FFFFFF80 FFFFFF80 FFFFFFC2 00 2F 10 04 1D 1E 4D 4F 08 05 53 00
   FFFFFF86 00 54 01 05 65 6D 70 74 79 15 03 55 57 59 10
   04 1D 1E 56 58 10 02 1D 57 04 08 2E 52 FFFFFF84 FFFFFF80 FFFFFF80
   FFFFFFC2 00 2F 10 02 1D 59 04 08 35 52 FFFFFF84 FFFFFF80 FFFFFF80 FFFFFFC2 00
   2F 08 05 5B 00 FFFFFF84 00 5C 01 05 61 70 70 6C 79 15
   03 5D 60 62 14 02 5E 63 10 04 1D 1E 5F 61 10 02
   1D 60 04 08 2E 5A FFFFFF84 FFFFFF80 FFFFFF80 FFFFFFC2 00 2F 10 02 1D 62
   04 08 35 5A FFFFFF84 FFFFFF80 FFFFFF80 FFFFFFC2 00 2F 08 05 64 5A FFFFFFC0 00
   65 01 05 65 6C 65 6D 73 10 03 14 66 68 09 02 67
   06 02 0A 3C 72 65 70 65 61 74 65 64 3E 10 04 14
   4B 5F 61 06 04 6A 00 00 6B 02 11 4D 61 70 42 75
   69 6C 64 65 72 46 61 63 74 6F 72 79 15 03 6C 72
   74 13 04 69 0B 6D 13 10 05 1B 6E 70 75 76 09 02
   6F 02 02 0E 42 75 69 6C 64 65 72 46 61 63 74 6F
   72 79 10 04 14 4B 71 73 10 02 1D 72 04 08 2E 69
   FFFFFF84 FFFFFF80 FFFFFF80 FFFFFFC2 00 2F 10 02 1D 74 04 08 35 69 FFFFFF84 FFFFFF80
   FFFFFF80 FFFFFFC2 00 2F 10 04 1D 1E 71 73 10 02 77 3A 0D 01
   00 08 05 18 69 FFFFFF84 00 79 14 01 7A 10 04 77 69 71
   73 08 05 5B 69 FFFFFF84 00 7C 14 02 7D 7E 10 04 1B 48
   70 75 08 05 7F 7B FFFFFFC0 00 76 01 04 66 72 6F 6D 
  InnerClass: 
   public #49= #48 of #15; //MapBuilderFactory=class scala/collection/generic/MapFactory$MapBuilderFactory of class scala/collection/generic/MapFactory
  minor version: 0
  major version: 49
  Constant pool:
const #1 = Asciz	SourceFile;
const #2 = Asciz	MapFactory.scala;
const #3 = Asciz	<init>;
const #4 = Asciz	()V;
const #5 = Asciz	Code;
const #6 = Asciz	LineNumberTable;
const #7 = Asciz	java/lang/Object;
const #8 = class	#7;	//  java/lang/Object
const #9 = NameAndType	#3:#4;//  "<init>":()V
const #10 = Method	#8.#9;	//  java/lang/Object."<init>":()V
const #11 = Asciz	Signature;
const #12 = Asciz	apply;
const #13 = Asciz	(Lscala/collection/Sequence;)Lscala/collection/Map;;
const #14 = Asciz	scala/collection/generic/MapFactory;
const #15 = class	#14;	//  scala/collection/generic/MapFactory
const #16 = Asciz	newBuilder;
const #17 = Asciz	()Lscala/collection/generic/Builder;;
const #18 = NameAndType	#16:#17;//  newBuilder:()Lscala/collection/generic/Builder;
const #19 = Method	#15.#18;	//  scala/collection/generic/MapFactory.newBuilder:()Lscala/collection/generic/Builder;
const #20 = Asciz	scala/collection/generic/Growable;
const #21 = class	#20;	//  scala/collection/generic/Growable
const #22 = Asciz	$plus$plus$eq;
const #23 = Asciz	(Lscala/collection/Traversable;)Lscala/collection/generic/Growable;;
const #24 = NameAndType	#22:#23;//  $plus$plus$eq:(Lscala/collection/Traversable;)Lscala/collection/generic/Growable;
const #25 = InterfaceMethod	#21.#24;	//  scala/collection/generic/Growable.$plus$plus$eq:(Lscala/collection/Traversable;)Lscala/collection/generic/Growable;
const #26 = Asciz	scala/collection/generic/Builder;
const #27 = class	#26;	//  scala/collection/generic/Builder
const #28 = Asciz	result;
const #29 = Asciz	()Ljava/lang/Object;;
const #30 = NameAndType	#28:#29;//  result:()Ljava/lang/Object;
const #31 = InterfaceMethod	#27.#30;	//  scala/collection/generic/Builder.result:()Ljava/lang/Object;
const #32 = Asciz	scala/collection/Map;
const #33 = class	#32;	//  scala/collection/Map
const #34 = Asciz	this;
const #35 = Asciz	Lscala/collection/generic/MapFactory;;
const #36 = Asciz	elems;
const #37 = Asciz	Lscala/collection/Sequence;;
const #38 = Asciz	LocalVariableTable;
const #39 = Asciz	<A:Ljava/lang/Object;B:Ljava/lang/Object;>(Lscala/collection/Sequence<Lscala/Tuple2<TA;TB;>;>;)TCC;;
const #40 = Asciz	empty;
const #41 = Asciz	()Lscala/collection/Map;;
const #42 = Asciz	<A:Ljava/lang/Object;B:Ljava/lang/Object;>()TCC;;
const #43 = Asciz	<A:Ljava/lang/Object;B:Ljava/lang/Object;>()Lscala/collection/generic/Builder<Lscala/Tuple2<TA;TB;>;TCC;>;;
const #44 = Asciz	<CC:Lscala/collection/Map<Ljava/lang/Object;Ljava/lang/Object;>;>Ljava/lang/Object;Lscala/ScalaObject;;
const #45 = Asciz	ScalaSig;
const #46 = Asciz	InnerClasses;
const #47 = Asciz	scala/collection/generic/MapFactory$MapBuilderFactory;
const #48 = class	#47;	//  scala/collection/generic/MapFactory$MapBuilderFactory
const #49 = Asciz	MapBuilderFactory;
const #50 = Asciz	scala/ScalaObject;
const #51 = class	#50;	//  scala/ScalaObject

{
public scala.collection.generic.MapFactory();
  Code:
   Stack=1, Locals=1, Args_size=1
   0:	aload_0
   1:	invokespecial	#10; //Method java/lang/Object."<init>":()V
   4:	return
  LineNumberTable: 
   line 18: 0

  Signature: length = 0x2
   00 04 

public scala.collection.Map apply(scala.collection.Sequence);
  Code:
   Stack=2, Locals=2, Args_size=2
   0:	aload_0
   1:	invokevirtual	#19; //Method newBuilder:()Lscala/collection/generic/Builder;
   4:	aload_1
   5:	invokeinterface	#25,  2; //InterfaceMethod scala/collection/generic/Growable.$plus$plus$eq:(Lscala/collection/Traversable;)Lscala/collection/generic/Growable;
   10:	checkcast	#27; //class scala/collection/generic/Builder
   13:	invokeinterface	#31,  1; //InterfaceMethod scala/collection/generic/Builder.result:()Ljava/lang/Object;
   18:	checkcast	#33; //class scala/collection/Map
   21:	areturn
  LineNumberTable: 
   line 26: 0

  LocalVariableTable: 
   Start  Length  Slot  Name   Signature
   0      22      0    this       Lscala/collection/generic/MapFactory;
   0      22      1    elems       Lscala/collection/Sequence;

  Signature: length = 0x2
   00 27 

public abstract scala.collection.Map empty();
  Signature: length = 0x2
   00 2A 

public abstract scala.collection.generic.Builder newBuilder();
  Signature: length = 0x2
   00 2B 

}

