Compiled from "MapFactory.scala"
public class scala.collection.generic.MapFactory$MapCanBuildFrom extends java.lang.Object implements scala.collection.generic.CanBuildFrom,scala.ScalaObject
  SourceFile: "MapFactory.scala"
  Signature: length = 0x2
   00 30 
  Scala: length = 0x
   
  InnerClass: 
   public MapCanBuildFrom=class scala/collection/generic/MapFactory$MapCanBuildFrom of class scala/collection/generic/MapFactory
  minor version: 0
  major version: 49
  Constant pool:
Asciz	SourceFile;
Asciz	MapFactory.scala;
Asciz	$outer;
Asciz	Lscala/collection/generic/MapFactory;;
Asciz	<init>;
Asciz	(Lscala/collection/generic/MapFactory;)V;
Asciz	Code;
Asciz	LineNumberTable;
Asciz	java/lang/NullPointerException;
class	java/lang/NullPointerException
Asciz	()V;
NameAndType	"<init>":()V
Method	java/lang/NullPointerException."<init>":()V
Asciz	scala/collection/generic/MapFactory$MapCanBuildFrom;
class	scala/collection/generic/MapFactory$MapCanBuildFrom
NameAndType	$outer:Lscala/collection/generic/MapFactory;
Field	scala/collection/generic/MapFactory$MapCanBuildFrom.$outer:Lscala/collection/generic/MapFactory;
Asciz	java/lang/Object;
class	java/lang/Object
Method	java/lang/Object."<init>":()V
Asciz	this;
Asciz	Lscala/collection/generic/MapFactory$MapCanBuildFrom;;
Asciz	LocalVariableTable;
Asciz	(Lscala/collection/generic/MapFactory<TCC;>;)V;
Asciz	Signature;
Asciz	apply;
Asciz	(Ljava/lang/Object;)Lscala/collection/mutable/Builder;;
Asciz	scala/collection/Map;
class	scala/collection/Map
Asciz	(Lscala/collection/Map;)Lscala/collection/mutable/Builder;;
NameAndType	apply:(Lscala/collection/Map;)Lscala/collection/mutable/Builder;
Method	scala/collection/generic/MapFactory$MapCanBuildFrom.apply:(Lscala/collection/Map;)Lscala/collection/mutable/Builder;
Asciz	from;
Asciz	Ljava/lang/Object;;
Asciz	scala$collection$generic$MapFactory$MapCanBuildFrom$$$outer;
Asciz	()Lscala/collection/generic/MapFactory;;
Asciz	()Lscala/collection/mutable/Builder;;
NameAndType	scala$collection$generic$MapFactory$MapCanBuildFrom$$$outer:()Lscala/collection/generic/MapFactory;
Method	scala/collection/generic/MapFactory$MapCanBuildFrom.scala$collection$generic$MapFactory$MapCanBuildFrom$$$outer:()Lscala/collection/generic/MapFactory;
Asciz	scala/collection/generic/MapFactory;
class	scala/collection/generic/MapFactory
Asciz	newBuilder;
NameAndType	newBuilder:()Lscala/collection/mutable/Builder;
Method	scala/collection/generic/MapFactory.newBuilder:()Lscala/collection/mutable/Builder;
Asciz	()Lscala/collection/mutable/Builder<Lscala/Tuple2<TA;TB;>;TCC;>;;
Asciz	Lscala/collection/Map;;
Asciz	(TCC;)Lscala/collection/mutable/Builder<Lscala/Tuple2<TA;TB;>;TCC;>;;
Asciz	<A:Ljava/lang/Object;B:Ljava/lang/Object;>Ljava/lang/Object;Lscala/collection/generic/CanBuildFrom<TCC;Lscala/Tuple2<TA;TB;>;TCC;>;Lscala/ScalaObject;;
Asciz	Scala;
Asciz	InnerClasses;
Asciz	MapCanBuildFrom;
Asciz	scala/collection/generic/CanBuildFrom;
class	scala/collection/generic/CanBuildFrom
Asciz	scala/ScalaObject;
class	scala/ScalaObject

{
public final scala.collection.generic.MapFactory $outer;
  Signature: Lscala/collection/generic/MapFactory;

public scala.collection.generic.MapFactory$MapCanBuildFrom(scala.collection.generic.MapFactory);
  Signature: (Lscala/collection/generic/MapFactory;)V
  Code:
   Stack=2, Locals=2, Args_size=2
	aload_1
	ifnonnull	l1 // aload_0
	new	class java/lang/NullPointerException
	dup
	invokespecial	Method java/lang/NullPointerException."<init>":()V
	athrow
l1	aload_0
	aload_1
	putfield	Field $outer:Lscala/collection/generic/MapFactory;
	aload_0
	invokespecial	Method java/lang/Object."<init>":()V
	return
  Labels:
   	l1 = 12 // aload_0
  LocalVariableTable: 
   Start  Length  Slot  Name   Signature
   0      22      0    this       Lscala/collection/generic/MapFactory$MapCanBuildFrom;
   0      22      1    $outer       Lscala/collection/generic/MapFactory;

  Signature: length = 0x2
   00 18 

public scala.collection.mutable.Builder apply(java.lang.Object);
  Signature: (Ljava/lang/Object;)Lscala/collection/mutable/Builder;
  Code:
   Stack=2, Locals=2, Args_size=2
	aload_0
	aload_1
	checkcast	class scala/collection/Map
	invokevirtual	Method apply:(Lscala/collection/Map;)Lscala/collection/mutable/Builder;
	areturn
  Labels:
  LocalVariableTable: 
   Start  Length  Slot  Name   Signature
   0      9      0    this       Lscala/collection/generic/MapFactory$MapCanBuildFrom;
   0      9      1    from       Ljava/lang/Object;


public scala.collection.generic.MapFactory scala$collection$generic$MapFactory$MapCanBuildFrom$$$outer();
  Signature: ()Lscala/collection/generic/MapFactory;
  Code:
   Stack=1, Locals=1, Args_size=1
	aload_0
	getfield	Field $outer:Lscala/collection/generic/MapFactory;
	areturn
  Labels:

public scala.collection.mutable.Builder apply();
  Signature: ()Lscala/collection/mutable/Builder;
  Code:
   Stack=1, Locals=1, Args_size=1
	aload_0
	invokevirtual	Method scala$collection$generic$MapFactory$MapCanBuildFrom$$$outer:()Lscala/collection/generic/MapFactory;
	invokevirtual	Method scala/collection/generic/MapFactory.newBuilder:()Lscala/collection/mutable/Builder;
	areturn
  Labels:
  Signature: length = 0x2
   00 2D 

public scala.collection.mutable.Builder apply(scala.collection.Map);
  Signature: (Lscala/collection/Map;)Lscala/collection/mutable/Builder;
  Code:
   Stack=1, Locals=2, Args_size=2
	aload_0
	invokevirtual	Method scala$collection$generic$MapFactory$MapCanBuildFrom$$$outer:()Lscala/collection/generic/MapFactory;
	invokevirtual	Method scala/collection/generic/MapFactory.newBuilder:()Lscala/collection/mutable/Builder;
	areturn
  Labels:
  LocalVariableTable: 
   Start  Length  Slot  Name   Signature
   0      8      0    this       Lscala/collection/generic/MapFactory$MapCanBuildFrom;
   0      8      1    from       Lscala/collection/Map;

  Signature: length = 0x2
   00 2F 

}

