Compiled from "MapProxyTemplate.scala"
public abstract class scala.collection.generic.MapProxyTemplate$class extends java.lang.Object
  SourceFile: "MapProxyTemplate.scala"
  Scala: length = 0x
   
  minor version: 0
  major version: 49
  Constant pool:
const #1 = Asciz	SourceFile;
const #2 = Asciz	MapProxyTemplate.scala;
const #3 = Asciz	$init$;
const #4 = Asciz	(Lscala/collection/generic/MapProxyTemplate;)V;
const #5 = Asciz	Code;
const #6 = Asciz	LineNumberTable;
const #7 = Asciz	$this;
const #8 = Asciz	Lscala/collection/generic/MapProxyTemplate;;
const #9 = Asciz	LocalVariableTable;
const #10 = Asciz	addString;
const #11 = Asciz	(Lscala/collection/generic/MapProxyTemplate;Lscala/collection/mutable/StringBuilder;Ljava/lang/String;Ljava/lang/String;Ljava/lang/String;)Lscala/collection/mutable/StringBuilder;;
const #12 = Asciz	scala/collection/generic/TraversableProxyTemplate;
const #13 = class	#12;	//  scala/collection/generic/TraversableProxyTemplate
const #14 = Asciz	self;
const #15 = Asciz	()Lscala/collection/generic/TraversableTemplate;;
const #16 = NameAndType	#14:#15;//  self:()Lscala/collection/generic/TraversableTemplate;
const #17 = InterfaceMethod	#13.#16;	//  scala/collection/generic/TraversableProxyTemplate.self:()Lscala/collection/generic/TraversableTemplate;
const #18 = Asciz	scala/collection/generic/MapTemplate;
const #19 = class	#18;	//  scala/collection/generic/MapTemplate
const #20 = Asciz	(Lscala/collection/mutable/StringBuilder;Ljava/lang/String;Ljava/lang/String;Ljava/lang/String;)Lscala/collection/mutable/StringBuilder;;
const #21 = NameAndType	#10:#20;//  addString:(Lscala/collection/mutable/StringBuilder;Ljava/lang/String;Ljava/lang/String;Ljava/lang/String;)Lscala/collection/mutable/StringBuilder;
const #22 = InterfaceMethod	#19.#21;	//  scala/collection/generic/MapTemplate.addString:(Lscala/collection/mutable/StringBuilder;Ljava/lang/String;Ljava/lang/String;Ljava/lang/String;)Lscala/collection/mutable/StringBuilder;
const #23 = Asciz	b;
const #24 = Asciz	Lscala/collection/mutable/StringBuilder;;
const #25 = Asciz	start;
const #26 = Asciz	Ljava/lang/String;;
const #27 = Asciz	sep;
const #28 = Asciz	end;
const #29 = Asciz	mapValues;
const #30 = Asciz	(Lscala/collection/generic/MapProxyTemplate;Lscala/Function1;)Ljava/lang/Object;;
const #31 = Asciz	(Lscala/Function1;)Ljava/lang/Object;;
const #32 = NameAndType	#29:#31;//  mapValues:(Lscala/Function1;)Ljava/lang/Object;
const #33 = InterfaceMethod	#19.#32;	//  scala/collection/generic/MapTemplate.mapValues:(Lscala/Function1;)Ljava/lang/Object;
const #34 = Asciz	f;
const #35 = Asciz	Lscala/Function1;;
const #36 = Asciz	filterKeys;
const #37 = NameAndType	#36:#31;//  filterKeys:(Lscala/Function1;)Ljava/lang/Object;
const #38 = InterfaceMethod	#19.#37;	//  scala/collection/generic/MapTemplate.filterKeys:(Lscala/Function1;)Ljava/lang/Object;
const #39 = Asciz	p;
const #40 = Asciz	default;
const #41 = Asciz	(Lscala/collection/generic/MapProxyTemplate;Ljava/lang/Object;)Ljava/lang/Object;;
const #42 = Asciz	(Ljava/lang/Object;)Ljava/lang/Object;;
const #43 = NameAndType	#40:#42;//  default:(Ljava/lang/Object;)Ljava/lang/Object;
const #44 = InterfaceMethod	#19.#43;	//  scala/collection/generic/MapTemplate.default:(Ljava/lang/Object;)Ljava/lang/Object;
const #45 = Asciz	key;
const #46 = Asciz	Ljava/lang/Object;;
const #47 = Asciz	values;
const #48 = Asciz	(Lscala/collection/generic/MapProxyTemplate;)Lscala/collection/Iterator;;
const #49 = Asciz	()Lscala/collection/Iterator;;
const #50 = NameAndType	#47:#49;//  values:()Lscala/collection/Iterator;
const #51 = InterfaceMethod	#19.#50;	//  scala/collection/generic/MapTemplate.values:()Lscala/collection/Iterator;
const #52 = Asciz	valuesIterator;
const #53 = NameAndType	#52:#49;//  valuesIterator:()Lscala/collection/Iterator;
const #54 = InterfaceMethod	#19.#53;	//  scala/collection/generic/MapTemplate.valuesIterator:()Lscala/collection/Iterator;
const #55 = Asciz	valueIterable;
const #56 = Asciz	(Lscala/collection/generic/MapProxyTemplate;)Lscala/collection/Iterable;;
const #57 = Asciz	()Lscala/collection/Iterable;;
const #58 = NameAndType	#55:#57;//  valueIterable:()Lscala/collection/Iterable;
const #59 = InterfaceMethod	#19.#58;	//  scala/collection/generic/MapTemplate.valueIterable:()Lscala/collection/Iterable;
const #60 = Asciz	keys;
const #61 = NameAndType	#60:#49;//  keys:()Lscala/collection/Iterator;
const #62 = InterfaceMethod	#19.#61;	//  scala/collection/generic/MapTemplate.keys:()Lscala/collection/Iterator;
const #63 = Asciz	keysIterator;
const #64 = NameAndType	#63:#49;//  keysIterator:()Lscala/collection/Iterator;
const #65 = InterfaceMethod	#19.#64;	//  scala/collection/generic/MapTemplate.keysIterator:()Lscala/collection/Iterator;
const #66 = Asciz	keySet;
const #67 = Asciz	(Lscala/collection/generic/MapProxyTemplate;)Lscala/collection/Set;;
const #68 = Asciz	()Lscala/collection/Set;;
const #69 = NameAndType	#66:#68;//  keySet:()Lscala/collection/Set;
const #70 = InterfaceMethod	#19.#69;	//  scala/collection/generic/MapTemplate.keySet:()Lscala/collection/Set;
const #71 = Asciz	isDefinedAt;
const #72 = Asciz	(Lscala/collection/generic/MapProxyTemplate;Ljava/lang/Object;)Z;
const #73 = Asciz	(Ljava/lang/Object;)Z;
const #74 = NameAndType	#71:#73;//  isDefinedAt:(Ljava/lang/Object;)Z
const #75 = InterfaceMethod	#19.#74;	//  scala/collection/generic/MapTemplate.isDefinedAt:(Ljava/lang/Object;)Z
const #76 = Asciz	contains;
const #77 = NameAndType	#76:#73;//  contains:(Ljava/lang/Object;)Z
const #78 = InterfaceMethod	#19.#77;	//  scala/collection/generic/MapTemplate.contains:(Ljava/lang/Object;)Z
const #79 = Asciz	apply;
const #80 = NameAndType	#79:#42;//  apply:(Ljava/lang/Object;)Ljava/lang/Object;
const #81 = InterfaceMethod	#19.#80;	//  scala/collection/generic/MapTemplate.apply:(Ljava/lang/Object;)Ljava/lang/Object;
const #82 = Asciz	getOrElse;
const #83 = Asciz	(Lscala/collection/generic/MapProxyTemplate;Ljava/lang/Object;Lscala/Function0;)Ljava/lang/Object;;
const #84 = Asciz	(Ljava/lang/Object;Lscala/Function0;)Ljava/lang/Object;;
const #85 = NameAndType	#82:#84;//  getOrElse:(Ljava/lang/Object;Lscala/Function0;)Ljava/lang/Object;
const #86 = InterfaceMethod	#19.#85;	//  scala/collection/generic/MapTemplate.getOrElse:(Ljava/lang/Object;Lscala/Function0;)Ljava/lang/Object;
const #87 = Asciz	Lscala/Function0;;
const #88 = Asciz	isEmpty;
const #89 = Asciz	(Lscala/collection/generic/MapProxyTemplate;)Z;
const #90 = Asciz	()Z;
const #91 = NameAndType	#88:#90;//  isEmpty:()Z
const #92 = InterfaceMethod	#19.#91;	//  scala/collection/generic/MapTemplate.isEmpty:()Z
const #93 = Asciz	iterator;
const #94 = NameAndType	#93:#49;//  iterator:()Lscala/collection/Iterator;
const #95 = InterfaceMethod	#19.#94;	//  scala/collection/generic/MapTemplate.iterator:()Lscala/collection/Iterator;
const #96 = Asciz	get;
const #97 = Asciz	(Lscala/collection/generic/MapProxyTemplate;Ljava/lang/Object;)Lscala/Option;;
const #98 = Asciz	(Ljava/lang/Object;)Lscala/Option;;
const #99 = NameAndType	#96:#98;//  get:(Ljava/lang/Object;)Lscala/Option;
const #100 = InterfaceMethod	#19.#99;	//  scala/collection/generic/MapTemplate.get:(Ljava/lang/Object;)Lscala/Option;
const #101 = Asciz	Scala;
const #102 = Asciz	scala/collection/generic/MapProxyTemplate$class;
const #103 = class	#102;	//  scala/collection/generic/MapProxyTemplate$class
const #104 = Asciz	java/lang/Object;
const #105 = class	#104;	//  java/lang/Object

{
public static void $init$(scala.collection.generic.MapProxyTemplate);
  Code:
   Stack=0, Locals=1, Args_size=1
   0:	return
  LineNumberTable: 
   line 21: 0

  LocalVariableTable: 
   Start  Length  Slot  Name   Signature
   0      1      0    $this       Lscala/collection/generic/MapProxyTemplate;


public static scala.collection.mutable.StringBuilder addString(scala.collection.generic.MapProxyTemplate, scala.collection.mutable.StringBuilder, java.lang.String, java.lang.String, java.lang.String);
  Code:
   Stack=5, Locals=5, Args_size=5
   0:	aload_0
   1:	invokeinterface	#17,  1; //InterfaceMethod scala/collection/generic/TraversableProxyTemplate.self:()Lscala/collection/generic/TraversableTemplate;
   6:	checkcast	#19; //class scala/collection/generic/MapTemplate
   9:	aload_1
   10:	aload_2
   11:	aload_3
   12:	aload	4
   14:	invokeinterface	#22,  5; //InterfaceMethod scala/collection/generic/MapTemplate.addString:(Lscala/collection/mutable/StringBuilder;Ljava/lang/String;Ljava/lang/String;Ljava/lang/String;)Lscala/collection/mutable/StringBuilder;
   19:	areturn
  LineNumberTable: 
   line 51: 0

  LocalVariableTable: 
   Start  Length  Slot  Name   Signature
   0      20      0    $this       Lscala/collection/generic/MapProxyTemplate;
   0      20      1    b       Lscala/collection/mutable/StringBuilder;
   0      20      2    start       Ljava/lang/String;
   0      20      3    sep       Ljava/lang/String;
   0      20      4    end       Ljava/lang/String;


public static java.lang.Object mapValues(scala.collection.generic.MapProxyTemplate, scala.Function1);
  Code:
   Stack=2, Locals=2, Args_size=2
   0:	aload_0
   1:	invokeinterface	#17,  1; //InterfaceMethod scala/collection/generic/TraversableProxyTemplate.self:()Lscala/collection/generic/TraversableTemplate;
   6:	checkcast	#19; //class scala/collection/generic/MapTemplate
   9:	aload_1
   10:	invokeinterface	#33,  2; //InterfaceMethod scala/collection/generic/MapTemplate.mapValues:(Lscala/Function1;)Ljava/lang/Object;
   15:	areturn
  LineNumberTable: 
   line 43: 0

  LocalVariableTable: 
   Start  Length  Slot  Name   Signature
   0      16      0    $this       Lscala/collection/generic/MapProxyTemplate;
   0      16      1    f       Lscala/Function1;


public static java.lang.Object filterKeys(scala.collection.generic.MapProxyTemplate, scala.Function1);
  Code:
   Stack=2, Locals=2, Args_size=2
   0:	aload_0
   1:	invokeinterface	#17,  1; //InterfaceMethod scala/collection/generic/TraversableProxyTemplate.self:()Lscala/collection/generic/TraversableTemplate;
   6:	checkcast	#19; //class scala/collection/generic/MapTemplate
   9:	aload_1
   10:	invokeinterface	#38,  2; //InterfaceMethod scala/collection/generic/MapTemplate.filterKeys:(Lscala/Function1;)Ljava/lang/Object;
   15:	areturn
  LineNumberTable: 
   line 42: 0

  LocalVariableTable: 
   Start  Length  Slot  Name   Signature
   0      16      0    $this       Lscala/collection/generic/MapProxyTemplate;
   0      16      1    p       Lscala/Function1;


public static java.lang.Object default(scala.collection.generic.MapProxyTemplate, java.lang.Object);
  Code:
   Stack=2, Locals=2, Args_size=2
   0:	aload_0
   1:	invokeinterface	#17,  1; //InterfaceMethod scala/collection/generic/TraversableProxyTemplate.self:()Lscala/collection/generic/TraversableTemplate;
   6:	checkcast	#19; //class scala/collection/generic/MapTemplate
   9:	aload_1
   10:	invokeinterface	#44,  2; //InterfaceMethod scala/collection/generic/MapTemplate.default:(Ljava/lang/Object;)Ljava/lang/Object;
   15:	areturn
  LineNumberTable: 
   line 41: 0

  LocalVariableTable: 
   Start  Length  Slot  Name   Signature
   0      16      0    $this       Lscala/collection/generic/MapProxyTemplate;
   0      16      1    key       Ljava/lang/Object;


public static scala.collection.Iterator values(scala.collection.generic.MapProxyTemplate);
  Code:
   Stack=1, Locals=1, Args_size=1
   0:	aload_0
   1:	invokeinterface	#17,  1; //InterfaceMethod scala/collection/generic/TraversableProxyTemplate.self:()Lscala/collection/generic/TraversableTemplate;
   6:	checkcast	#19; //class scala/collection/generic/MapTemplate
   9:	invokeinterface	#51,  1; //InterfaceMethod scala/collection/generic/MapTemplate.values:()Lscala/collection/Iterator;
   14:	areturn
  LineNumberTable: 
   line 40: 0

  LocalVariableTable: 
   Start  Length  Slot  Name   Signature
   0      15      0    $this       Lscala/collection/generic/MapProxyTemplate;


public static scala.collection.Iterator valuesIterator(scala.collection.generic.MapProxyTemplate);
  Code:
   Stack=1, Locals=1, Args_size=1
   0:	aload_0
   1:	invokeinterface	#17,  1; //InterfaceMethod scala/collection/generic/TraversableProxyTemplate.self:()Lscala/collection/generic/TraversableTemplate;
   6:	checkcast	#19; //class scala/collection/generic/MapTemplate
   9:	invokeinterface	#54,  1; //InterfaceMethod scala/collection/generic/MapTemplate.valuesIterator:()Lscala/collection/Iterator;
   14:	areturn
  LineNumberTable: 
   line 39: 0

  LocalVariableTable: 
   Start  Length  Slot  Name   Signature
   0      15      0    $this       Lscala/collection/generic/MapProxyTemplate;


public static scala.collection.Iterable valueIterable(scala.collection.generic.MapProxyTemplate);
  Code:
   Stack=1, Locals=1, Args_size=1
   0:	aload_0
   1:	invokeinterface	#17,  1; //InterfaceMethod scala/collection/generic/TraversableProxyTemplate.self:()Lscala/collection/generic/TraversableTemplate;
   6:	checkcast	#19; //class scala/collection/generic/MapTemplate
   9:	invokeinterface	#59,  1; //InterfaceMethod scala/collection/generic/MapTemplate.valueIterable:()Lscala/collection/Iterable;
   14:	areturn
  LineNumberTable: 
   line 38: 0

  LocalVariableTable: 
   Start  Length  Slot  Name   Signature
   0      15      0    $this       Lscala/collection/generic/MapProxyTemplate;


public static scala.collection.Iterator keys(scala.collection.generic.MapProxyTemplate);
  Code:
   Stack=1, Locals=1, Args_size=1
   0:	aload_0
   1:	invokeinterface	#17,  1; //InterfaceMethod scala/collection/generic/TraversableProxyTemplate.self:()Lscala/collection/generic/TraversableTemplate;
   6:	checkcast	#19; //class scala/collection/generic/MapTemplate
   9:	invokeinterface	#62,  1; //InterfaceMethod scala/collection/generic/MapTemplate.keys:()Lscala/collection/Iterator;
   14:	areturn
  LineNumberTable: 
   line 37: 0

  LocalVariableTable: 
   Start  Length  Slot  Name   Signature
   0      15      0    $this       Lscala/collection/generic/MapProxyTemplate;


public static scala.collection.Iterator keysIterator(scala.collection.generic.MapProxyTemplate);
  Code:
   Stack=1, Locals=1, Args_size=1
   0:	aload_0
   1:	invokeinterface	#17,  1; //InterfaceMethod scala/collection/generic/TraversableProxyTemplate.self:()Lscala/collection/generic/TraversableTemplate;
   6:	checkcast	#19; //class scala/collection/generic/MapTemplate
   9:	invokeinterface	#65,  1; //InterfaceMethod scala/collection/generic/MapTemplate.keysIterator:()Lscala/collection/Iterator;
   14:	areturn
  LineNumberTable: 
   line 36: 0

  LocalVariableTable: 
   Start  Length  Slot  Name   Signature
   0      15      0    $this       Lscala/collection/generic/MapProxyTemplate;


public static scala.collection.Set keySet(scala.collection.generic.MapProxyTemplate);
  Code:
   Stack=1, Locals=1, Args_size=1
   0:	aload_0
   1:	invokeinterface	#17,  1; //InterfaceMethod scala/collection/generic/TraversableProxyTemplate.self:()Lscala/collection/generic/TraversableTemplate;
   6:	checkcast	#19; //class scala/collection/generic/MapTemplate
   9:	invokeinterface	#70,  1; //InterfaceMethod scala/collection/generic/MapTemplate.keySet:()Lscala/collection/Set;
   14:	areturn
  LineNumberTable: 
   line 35: 0

  LocalVariableTable: 
   Start  Length  Slot  Name   Signature
   0      15      0    $this       Lscala/collection/generic/MapProxyTemplate;


public static boolean isDefinedAt(scala.collection.generic.MapProxyTemplate, java.lang.Object);
  Code:
   Stack=2, Locals=2, Args_size=2
   0:	aload_0
   1:	invokeinterface	#17,  1; //InterfaceMethod scala/collection/generic/TraversableProxyTemplate.self:()Lscala/collection/generic/TraversableTemplate;
   6:	checkcast	#19; //class scala/collection/generic/MapTemplate
   9:	aload_1
   10:	invokeinterface	#75,  2; //InterfaceMethod scala/collection/generic/MapTemplate.isDefinedAt:(Ljava/lang/Object;)Z
   15:	ireturn
  LineNumberTable: 
   line 34: 0

  LocalVariableTable: 
   Start  Length  Slot  Name   Signature
   0      16      0    $this       Lscala/collection/generic/MapProxyTemplate;
   0      16      1    key       Ljava/lang/Object;


public static boolean contains(scala.collection.generic.MapProxyTemplate, java.lang.Object);
  Code:
   Stack=2, Locals=2, Args_size=2
   0:	aload_0
   1:	invokeinterface	#17,  1; //InterfaceMethod scala/collection/generic/TraversableProxyTemplate.self:()Lscala/collection/generic/TraversableTemplate;
   6:	checkcast	#19; //class scala/collection/generic/MapTemplate
   9:	aload_1
   10:	invokeinterface	#78,  2; //InterfaceMethod scala/collection/generic/MapTemplate.contains:(Ljava/lang/Object;)Z
   15:	ireturn
  LineNumberTable: 
   line 33: 0

  LocalVariableTable: 
   Start  Length  Slot  Name   Signature
   0      16      0    $this       Lscala/collection/generic/MapProxyTemplate;
   0      16      1    key       Ljava/lang/Object;


public static java.lang.Object apply(scala.collection.generic.MapProxyTemplate, java.lang.Object);
  Code:
   Stack=2, Locals=2, Args_size=2
   0:	aload_0
   1:	invokeinterface	#17,  1; //InterfaceMethod scala/collection/generic/TraversableProxyTemplate.self:()Lscala/collection/generic/TraversableTemplate;
   6:	checkcast	#19; //class scala/collection/generic/MapTemplate
   9:	aload_1
   10:	invokeinterface	#81,  2; //InterfaceMethod scala/collection/generic/MapTemplate.apply:(Ljava/lang/Object;)Ljava/lang/Object;
   15:	areturn
  LineNumberTable: 
   line 32: 0

  LocalVariableTable: 
   Start  Length  Slot  Name   Signature
   0      16      0    $this       Lscala/collection/generic/MapProxyTemplate;
   0      16      1    key       Ljava/lang/Object;


public static java.lang.Object getOrElse(scala.collection.generic.MapProxyTemplate, java.lang.Object, scala.Function0);
  Code:
   Stack=3, Locals=3, Args_size=3
   0:	aload_0
   1:	invokeinterface	#17,  1; //InterfaceMethod scala/collection/generic/TraversableProxyTemplate.self:()Lscala/collection/generic/TraversableTemplate;
   6:	checkcast	#19; //class scala/collection/generic/MapTemplate
   9:	aload_1
   10:	aload_2
   11:	invokeinterface	#86,  3; //InterfaceMethod scala/collection/generic/MapTemplate.getOrElse:(Ljava/lang/Object;Lscala/Function0;)Ljava/lang/Object;
   16:	areturn
  LineNumberTable: 
   line 31: 0

  LocalVariableTable: 
   Start  Length  Slot  Name   Signature
   0      17      0    $this       Lscala/collection/generic/MapProxyTemplate;
   0      17      1    key       Ljava/lang/Object;
   0      17      2    default       Lscala/Function0;


public static boolean isEmpty(scala.collection.generic.MapProxyTemplate);
  Code:
   Stack=1, Locals=1, Args_size=1
   0:	aload_0
   1:	invokeinterface	#17,  1; //InterfaceMethod scala/collection/generic/TraversableProxyTemplate.self:()Lscala/collection/generic/TraversableTemplate;
   6:	checkcast	#19; //class scala/collection/generic/MapTemplate
   9:	invokeinterface	#92,  1; //InterfaceMethod scala/collection/generic/MapTemplate.isEmpty:()Z
   14:	ireturn
  LineNumberTable: 
   line 30: 0

  LocalVariableTable: 
   Start  Length  Slot  Name   Signature
   0      15      0    $this       Lscala/collection/generic/MapProxyTemplate;


public static scala.collection.Iterator iterator(scala.collection.generic.MapProxyTemplate);
  Code:
   Stack=1, Locals=1, Args_size=1
   0:	aload_0
   1:	invokeinterface	#17,  1; //InterfaceMethod scala/collection/generic/TraversableProxyTemplate.self:()Lscala/collection/generic/TraversableTemplate;
   6:	checkcast	#19; //class scala/collection/generic/MapTemplate
   9:	invokeinterface	#95,  1; //InterfaceMethod scala/collection/generic/MapTemplate.iterator:()Lscala/collection/Iterator;
   14:	areturn
  LineNumberTable: 
   line 29: 0

  LocalVariableTable: 
   Start  Length  Slot  Name   Signature
   0      15      0    $this       Lscala/collection/generic/MapProxyTemplate;


public static scala.Option get(scala.collection.generic.MapProxyTemplate, java.lang.Object);
  Code:
   Stack=2, Locals=2, Args_size=2
   0:	aload_0
   1:	invokeinterface	#17,  1; //InterfaceMethod scala/collection/generic/TraversableProxyTemplate.self:()Lscala/collection/generic/TraversableTemplate;
   6:	checkcast	#19; //class scala/collection/generic/MapTemplate
   9:	aload_1
   10:	invokeinterface	#100,  2; //InterfaceMethod scala/collection/generic/MapTemplate.get:(Ljava/lang/Object;)Lscala/Option;
   15:	areturn
  LineNumberTable: 
   line 28: 0

  LocalVariableTable: 
   Start  Length  Slot  Name   Signature
   0      16      0    $this       Lscala/collection/generic/MapProxyTemplate;
   0      16      1    key       Ljava/lang/Object;


}

