Compiled from "MapTemplate.scala"
public abstract class scala.collection.generic.MapTemplate$class extends java.lang.Object
  SourceFile: "MapTemplate.scala"
  Scala: length = 0x
   
  InnerClass: 
   public final #251= #166 of #53; //$anon$4=class scala/collection/generic/MapTemplate$$anon$4 of class scala/collection/generic/MapTemplate
   public final #252= #129 of #53; //$anon$2=class scala/collection/generic/MapTemplate$$anon$2 of class scala/collection/generic/MapTemplate
   public final #253= #178 of #53; //$anon$3=class scala/collection/generic/MapTemplate$$anon$3 of class scala/collection/generic/MapTemplate
   public final #254= #136 of #53; //$anon$1=class scala/collection/generic/MapTemplate$$anon$1 of class scala/collection/generic/MapTemplate
   public #255= #183 of #53; //DefaultKeySet=class scala/collection/generic/MapTemplate$DefaultKeySet of class scala/collection/generic/MapTemplate
   public final #256= #31 of #53; //$anonfun$equals$1=class scala/collection/generic/MapTemplate$$anonfun$equals$1 of class scala/collection/generic/MapTemplate
   public final #257= #59 of #53; //$anonfun$addString$1=class scala/collection/generic/MapTemplate$$anonfun$addString$1 of class scala/collection/generic/MapTemplate
   public final #258= #84 of #53; //$anonfun$$plus$plus$2=class scala/collection/generic/MapTemplate$$anonfun$$plus$plus$2 of class scala/collection/generic/MapTemplate
   public final #259= #94 of #53; //$anonfun$$plus$plus$1=class scala/collection/generic/MapTemplate$$anonfun$$plus$plus$1 of class scala/collection/generic/MapTemplate
   public #260= #171 of #53; //DefaultValuesIterable=class scala/collection/generic/MapTemplate$DefaultValuesIterable of class scala/collection/generic/MapTemplate
  minor version: 0
  major version: 49
  Constant pool:
const #1 = Asciz	SourceFile;
const #2 = Asciz	MapTemplate.scala;
const #3 = Asciz	$init$;
const #4 = Asciz	(Lscala/collection/generic/MapTemplate;)V;
const #5 = Asciz	Code;
const #6 = Asciz	LineNumberTable;
const #7 = Asciz	$this;
const #8 = Asciz	Lscala/collection/generic/MapTemplate;;
const #9 = Asciz	LocalVariableTable;
const #10 = Asciz	toString;
const #11 = Asciz	(Lscala/collection/generic/MapTemplate;)Ljava/lang/String;;
const #12 = Asciz	scala/collection/generic/TraversableTemplate$class;
const #13 = class	#12;	//  scala/collection/generic/TraversableTemplate$class
const #14 = Asciz	(Lscala/collection/generic/TraversableTemplate;)Ljava/lang/String;;
const #15 = NameAndType	#10:#14;//  toString:(Lscala/collection/generic/TraversableTemplate;)Ljava/lang/String;
const #16 = Method	#13.#15;	//  scala/collection/generic/TraversableTemplate$class.toString:(Lscala/collection/generic/TraversableTemplate;)Ljava/lang/String;
const #17 = Asciz	stringPrefix;
const #18 = Asciz	Map;
const #19 = String	#18;	//  Map
const #20 = Asciz	equals;
const #21 = Asciz	(Lscala/collection/generic/MapTemplate;Ljava/lang/Object;)Z;
const #22 = Asciz	scala/collection/Map;
const #23 = class	#22;	//  scala/collection/Map
const #24 = Asciz	scala/collection/generic/TraversableTemplate;
const #25 = class	#24;	//  scala/collection/generic/TraversableTemplate
const #26 = Asciz	size;
const #27 = Asciz	()I;
const #28 = NameAndType	#26:#27;//  size:()I
const #29 = InterfaceMethod	#25.#28;	//  scala/collection/generic/TraversableTemplate.size:()I
const #30 = Asciz	scala/collection/generic/MapTemplate$$anonfun$equals$1;
const #31 = class	#30;	//  scala/collection/generic/MapTemplate$$anonfun$equals$1
const #32 = Asciz	<init>;
const #33 = Asciz	(Lscala/collection/generic/MapTemplate;Lscala/collection/Map;)V;
const #34 = NameAndType	#32:#33;//  "<init>":(Lscala/collection/generic/MapTemplate;Lscala/collection/Map;)V
const #35 = Method	#31.#34;	//  scala/collection/generic/MapTemplate$$anonfun$equals$1."<init>":(Lscala/collection/generic/MapTemplate;Lscala/collection/Map;)V
const #36 = Asciz	forall;
const #37 = Asciz	(Lscala/Function1;)Z;
const #38 = NameAndType	#36:#37;//  forall:(Lscala/Function1;)Z
const #39 = InterfaceMethod	#25.#38;	//  scala/collection/generic/TraversableTemplate.forall:(Lscala/Function1;)Z
const #40 = Asciz	java/lang/ClassCastException;
const #41 = class	#40;	//  java/lang/ClassCastException
const #42 = Asciz	that;
const #43 = Asciz	Ljava/lang/Object;;
const #44 = Asciz	temp35;
const #45 = Asciz	temp36;
const #46 = Asciz	Lscala/collection/Map;;
const #47 = Asciz	other$1;
const #48 = Asciz	exceptionResult1;
const #49 = Asciz	Z;
const #50 = Asciz	addString;
const #51 = Asciz	(Lscala/collection/generic/MapTemplate;Lscala/collection/mutable/StringBuilder;Ljava/lang/String;Ljava/lang/String;Ljava/lang/String;)Lscala/collection/mutable/StringBuilder;;
const #52 = Asciz	scala/collection/generic/MapTemplate;
const #53 = class	#52;	//  scala/collection/generic/MapTemplate
const #54 = Asciz	iterator;
const #55 = Asciz	()Lscala/collection/Iterator;;
const #56 = NameAndType	#54:#55;//  iterator:()Lscala/collection/Iterator;
const #57 = InterfaceMethod	#53.#56;	//  scala/collection/generic/MapTemplate.iterator:()Lscala/collection/Iterator;
const #58 = Asciz	scala/collection/generic/MapTemplate$$anonfun$addString$1;
const #59 = class	#58;	//  scala/collection/generic/MapTemplate$$anonfun$addString$1
const #60 = NameAndType	#32:#4;//  "<init>":(Lscala/collection/generic/MapTemplate;)V
const #61 = Method	#59.#60;	//  scala/collection/generic/MapTemplate$$anonfun$addString$1."<init>":(Lscala/collection/generic/MapTemplate;)V
const #62 = Asciz	scala/collection/Iterator;
const #63 = class	#62;	//  scala/collection/Iterator
const #64 = Asciz	map;
const #65 = Asciz	(Lscala/Function1;)Lscala/collection/Iterator;;
const #66 = NameAndType	#64:#65;//  map:(Lscala/Function1;)Lscala/collection/Iterator;
const #67 = InterfaceMethod	#63.#66;	//  scala/collection/Iterator.map:(Lscala/Function1;)Lscala/collection/Iterator;
const #68 = Asciz	(Lscala/collection/mutable/StringBuilder;Ljava/lang/String;Ljava/lang/String;Ljava/lang/String;)Lscala/collection/mutable/StringBuilder;;
const #69 = NameAndType	#50:#68;//  addString:(Lscala/collection/mutable/StringBuilder;Ljava/lang/String;Ljava/lang/String;Ljava/lang/String;)Lscala/collection/mutable/StringBuilder;
const #70 = InterfaceMethod	#63.#69;	//  scala/collection/Iterator.addString:(Lscala/collection/mutable/StringBuilder;Ljava/lang/String;Ljava/lang/String;Ljava/lang/String;)Lscala/collection/mutable/StringBuilder;
const #71 = Asciz	b;
const #72 = Asciz	Lscala/collection/mutable/StringBuilder;;
const #73 = Asciz	start;
const #74 = Asciz	Ljava/lang/String;;
const #75 = Asciz	sep;
const #76 = Asciz	end;
const #77 = Asciz	$plus$plus;
const #78 = Asciz	(Lscala/collection/generic/MapTemplate;Lscala/collection/Iterator;)Lscala/collection/Map;;
const #79 = Asciz	thisCollection;
const #80 = Asciz	()Lscala/collection/generic/TraversableTemplate;;
const #81 = NameAndType	#79:#80;//  thisCollection:()Lscala/collection/generic/TraversableTemplate;
const #82 = InterfaceMethod	#25.#81;	//  scala/collection/generic/TraversableTemplate.thisCollection:()Lscala/collection/generic/TraversableTemplate;
const #83 = Asciz	scala/collection/generic/MapTemplate$$anonfun$$plus$plus$2;
const #84 = class	#83;	//  scala/collection/generic/MapTemplate$$anonfun$$plus$plus$2
const #85 = Method	#84.#60;	//  scala/collection/generic/MapTemplate$$anonfun$$plus$plus$2."<init>":(Lscala/collection/generic/MapTemplate;)V
const #86 = Asciz	$div$colon;
const #87 = Asciz	(Ljava/lang/Object;Lscala/Function2;)Ljava/lang/Object;;
const #88 = NameAndType	#86:#87;//  $div$colon:(Ljava/lang/Object;Lscala/Function2;)Ljava/lang/Object;
const #89 = InterfaceMethod	#63.#88;	//  scala/collection/Iterator.$div$colon:(Ljava/lang/Object;Lscala/Function2;)Ljava/lang/Object;
const #90 = Asciz	iter;
const #91 = Asciz	Lscala/collection/Iterator;;
const #92 = Asciz	(Lscala/collection/generic/MapTemplate;Lscala/collection/Traversable;)Lscala/collection/Map;;
const #93 = Asciz	scala/collection/generic/MapTemplate$$anonfun$$plus$plus$1;
const #94 = class	#93;	//  scala/collection/generic/MapTemplate$$anonfun$$plus$plus$1
const #95 = Method	#94.#60;	//  scala/collection/generic/MapTemplate$$anonfun$$plus$plus$1."<init>":(Lscala/collection/generic/MapTemplate;)V
const #96 = InterfaceMethod	#25.#88;	//  scala/collection/generic/TraversableTemplate.$div$colon:(Ljava/lang/Object;Lscala/Function2;)Ljava/lang/Object;
const #97 = Asciz	elems;
const #98 = Asciz	Lscala/collection/Traversable;;
const #99 = Asciz	$plus;
const #100 = Asciz	(Lscala/collection/generic/MapTemplate;Lscala/Tuple2;Lscala/Tuple2;Lscala/collection/Sequence;)Lscala/collection/Map;;
const #101 = Asciz	(Lscala/Tuple2;)Lscala/collection/Map;;
const #102 = NameAndType	#99:#101;//  $plus:(Lscala/Tuple2;)Lscala/collection/Map;
const #103 = InterfaceMethod	#53.#102;	//  scala/collection/generic/MapTemplate.$plus:(Lscala/Tuple2;)Lscala/collection/Map;
const #104 = Asciz	(Lscala/collection/Traversable;)Lscala/collection/Map;;
const #105 = NameAndType	#77:#104;//  $plus$plus:(Lscala/collection/Traversable;)Lscala/collection/Map;
const #106 = InterfaceMethod	#53.#105;	//  scala/collection/generic/MapTemplate.$plus$plus:(Lscala/collection/Traversable;)Lscala/collection/Map;
const #107 = Asciz	elem1;
const #108 = Asciz	Lscala/Tuple2;;
const #109 = Asciz	elem2;
const #110 = Asciz	Lscala/collection/Sequence;;
const #111 = Asciz	updated;
const #112 = Asciz	(Lscala/collection/generic/MapTemplate;Ljava/lang/Object;Ljava/lang/Object;)Lscala/collection/Map;;
const #113 = Asciz	scala/Tuple2;
const #114 = class	#113;	//  scala/Tuple2
const #115 = Asciz	(Ljava/lang/Object;Ljava/lang/Object;)V;
const #116 = NameAndType	#32:#115;//  "<init>":(Ljava/lang/Object;Ljava/lang/Object;)V
const #117 = Method	#114.#116;	//  scala/Tuple2."<init>":(Ljava/lang/Object;Ljava/lang/Object;)V
const #118 = Asciz	key;
const #119 = Asciz	value;
const #120 = Asciz	mapElements;
const #121 = Asciz	(Lscala/collection/generic/MapTemplate;Lscala/Function1;)Ljava/lang/Object;;
const #122 = Asciz	mapValues;
const #123 = Asciz	(Lscala/Function1;)Ljava/lang/Object;;
const #124 = NameAndType	#122:#123;//  mapValues:(Lscala/Function1;)Ljava/lang/Object;
const #125 = InterfaceMethod	#53.#124;	//  scala/collection/generic/MapTemplate.mapValues:(Lscala/Function1;)Ljava/lang/Object;
const #126 = Asciz	f;
const #127 = Asciz	Lscala/Function1;;
const #128 = Asciz	scala/collection/generic/MapTemplate$$anon$2;
const #129 = class	#128;	//  scala/collection/generic/MapTemplate$$anon$2
const #130 = Asciz	(Lscala/collection/generic/MapTemplate;Lscala/Function1;)V;
const #131 = NameAndType	#32:#130;//  "<init>":(Lscala/collection/generic/MapTemplate;Lscala/Function1;)V
const #132 = Method	#129.#131;	//  scala/collection/generic/MapTemplate$$anon$2."<init>":(Lscala/collection/generic/MapTemplate;Lscala/Function1;)V
const #133 = Asciz	f$4;
const #134 = Asciz	filterKeys;
const #135 = Asciz	scala/collection/generic/MapTemplate$$anon$1;
const #136 = class	#135;	//  scala/collection/generic/MapTemplate$$anon$1
const #137 = Method	#136.#131;	//  scala/collection/generic/MapTemplate$$anon$1."<init>":(Lscala/collection/generic/MapTemplate;Lscala/Function1;)V
const #138 = Asciz	p$1;
const #139 = Asciz	default;
const #140 = Asciz	(Lscala/collection/generic/MapTemplate;Ljava/lang/Object;)Ljava/lang/Object;;
const #141 = Asciz	java/util/NoSuchElementException;
const #142 = class	#141;	//  java/util/NoSuchElementException
const #143 = Asciz	scala/collection/mutable/StringBuilder;
const #144 = class	#143;	//  scala/collection/mutable/StringBuilder
const #145 = Asciz	()V;
const #146 = NameAndType	#32:#145;//  "<init>":()V
const #147 = Method	#144.#146;	//  scala/collection/mutable/StringBuilder."<init>":()V
const #148 = Asciz	key not found: ;
const #149 = String	#148;	//  key not found: 
const #150 = Asciz	append;
const #151 = Asciz	(Ljava/lang/Object;)Lscala/collection/mutable/StringBuilder;;
const #152 = NameAndType	#150:#151;//  append:(Ljava/lang/Object;)Lscala/collection/mutable/StringBuilder;
const #153 = Method	#144.#152;	//  scala/collection/mutable/StringBuilder.append:(Ljava/lang/Object;)Lscala/collection/mutable/StringBuilder;
const #154 = Asciz	()Ljava/lang/String;;
const #155 = NameAndType	#10:#154;//  toString:()Ljava/lang/String;
const #156 = Method	#144.#155;	//  scala/collection/mutable/StringBuilder.toString:()Ljava/lang/String;
const #157 = Asciz	(Ljava/lang/String;)V;
const #158 = NameAndType	#32:#157;//  "<init>":(Ljava/lang/String;)V
const #159 = Method	#142.#158;	//  java/util/NoSuchElementException."<init>":(Ljava/lang/String;)V
const #160 = Asciz	values;
const #161 = Asciz	(Lscala/collection/generic/MapTemplate;)Lscala/collection/Iterator;;
const #162 = Asciz	valuesIterator;
const #163 = NameAndType	#162:#55;//  valuesIterator:()Lscala/collection/Iterator;
const #164 = InterfaceMethod	#53.#163;	//  scala/collection/generic/MapTemplate.valuesIterator:()Lscala/collection/Iterator;
const #165 = Asciz	scala/collection/generic/MapTemplate$$anon$4;
const #166 = class	#165;	//  scala/collection/generic/MapTemplate$$anon$4
const #167 = Method	#166.#60;	//  scala/collection/generic/MapTemplate$$anon$4."<init>":(Lscala/collection/generic/MapTemplate;)V
const #168 = Asciz	valueIterable;
const #169 = Asciz	(Lscala/collection/generic/MapTemplate;)Lscala/collection/Iterable;;
const #170 = Asciz	scala/collection/generic/MapTemplate$DefaultValuesIterable;
const #171 = class	#170;	//  scala/collection/generic/MapTemplate$DefaultValuesIterable
const #172 = Method	#171.#60;	//  scala/collection/generic/MapTemplate$DefaultValuesIterable."<init>":(Lscala/collection/generic/MapTemplate;)V
const #173 = Asciz	keys;
const #174 = Asciz	keysIterator;
const #175 = NameAndType	#174:#55;//  keysIterator:()Lscala/collection/Iterator;
const #176 = InterfaceMethod	#53.#175;	//  scala/collection/generic/MapTemplate.keysIterator:()Lscala/collection/Iterator;
const #177 = Asciz	scala/collection/generic/MapTemplate$$anon$3;
const #178 = class	#177;	//  scala/collection/generic/MapTemplate$$anon$3
const #179 = Method	#178.#60;	//  scala/collection/generic/MapTemplate$$anon$3."<init>":(Lscala/collection/generic/MapTemplate;)V
const #180 = Asciz	keySet;
const #181 = Asciz	(Lscala/collection/generic/MapTemplate;)Lscala/collection/Set;;
const #182 = Asciz	scala/collection/generic/MapTemplate$DefaultKeySet;
const #183 = class	#182;	//  scala/collection/generic/MapTemplate$DefaultKeySet
const #184 = Method	#183.#60;	//  scala/collection/generic/MapTemplate$DefaultKeySet."<init>":(Lscala/collection/generic/MapTemplate;)V
const #185 = Asciz	isDefinedAt;
const #186 = Asciz	contains;
const #187 = Asciz	(Ljava/lang/Object;)Z;
const #188 = NameAndType	#186:#187;//  contains:(Ljava/lang/Object;)Z
const #189 = InterfaceMethod	#53.#188;	//  scala/collection/generic/MapTemplate.contains:(Ljava/lang/Object;)Z
const #190 = Asciz	get;
const #191 = Asciz	(Ljava/lang/Object;)Lscala/Option;;
const #192 = NameAndType	#190:#191;//  get:(Ljava/lang/Object;)Lscala/Option;
const #193 = InterfaceMethod	#53.#192;	//  scala/collection/generic/MapTemplate.get:(Ljava/lang/Object;)Lscala/Option;
const #194 = Asciz	scala/None$;
const #195 = class	#194;	//  scala/None$
const #196 = Asciz	MODULE$;
const #197 = Asciz	Lscala/None$;;
const #198 = NameAndType	#196:#197;//  MODULE$:Lscala/None$;
const #199 = Field	#195.#198;	//  scala/None$.MODULE$:Lscala/None$;
const #200 = Asciz	java/lang/Object;
const #201 = class	#200;	//  java/lang/Object
const #202 = NameAndType	#20:#187;//  equals:(Ljava/lang/Object;)Z
const #203 = Method	#201.#202;	//  java/lang/Object.equals:(Ljava/lang/Object;)Z
const #204 = Asciz	scala/Some;
const #205 = class	#204;	//  scala/Some
const #206 = Asciz	scala/MatchError;
const #207 = class	#206;	//  scala/MatchError
const #208 = Asciz	scala/Option;
const #209 = class	#208;	//  scala/Option
const #210 = Method	#209.#155;	//  scala/Option.toString:()Ljava/lang/String;
const #211 = Method	#207.#158;	//  scala/MatchError."<init>":(Ljava/lang/String;)V
const #212 = Asciz	temp9;
const #213 = Asciz	Lscala/Option;;
const #214 = Asciz	apply;
const #215 = Asciz	(Ljava/lang/Object;)Ljava/lang/Object;;
const #216 = NameAndType	#139:#215;//  default:(Ljava/lang/Object;)Ljava/lang/Object;
const #217 = InterfaceMethod	#53.#216;	//  scala/collection/generic/MapTemplate.default:(Ljava/lang/Object;)Ljava/lang/Object;
const #218 = Asciz	x;
const #219 = Asciz	()Ljava/lang/Object;;
const #220 = NameAndType	#218:#219;//  x:()Ljava/lang/Object;
const #221 = Method	#205.#220;	//  scala/Some.x:()Ljava/lang/Object;
const #222 = Asciz	temp5;
const #223 = Asciz	temp7;
const #224 = Asciz	Lscala/Some;;
const #225 = Asciz	temp8;
const #226 = Asciz	getOrElse;
const #227 = Asciz	(Lscala/collection/generic/MapTemplate;Ljava/lang/Object;Lscala/Function0;)Ljava/lang/Object;;
const #228 = Asciz	scala/Function0;
const #229 = class	#228;	//  scala/Function0
const #230 = NameAndType	#214:#219;//  apply:()Ljava/lang/Object;
const #231 = InterfaceMethod	#229.#230;	//  scala/Function0.apply:()Ljava/lang/Object;
const #232 = Asciz	Lscala/Function0;;
const #233 = Asciz	temp1;
const #234 = Asciz	temp2;
const #235 = Asciz	temp3;
const #236 = Asciz	isEmpty;
const #237 = Asciz	(Lscala/collection/generic/MapTemplate;)Z;
const #238 = Asciz	newBuilder;
const #239 = Asciz	(Lscala/collection/generic/MapTemplate;)Lscala/collection/generic/Builder;;
const #240 = Asciz	scala/collection/generic/MapBuilder;
const #241 = class	#240;	//  scala/collection/generic/MapBuilder
const #242 = Asciz	empty;
const #243 = Asciz	()Lscala/collection/generic/MapTemplate;;
const #244 = NameAndType	#242:#243;//  empty:()Lscala/collection/generic/MapTemplate;
const #245 = InterfaceMethod	#53.#244;	//  scala/collection/generic/MapTemplate.empty:()Lscala/collection/generic/MapTemplate;
const #246 = Asciz	(Lscala/collection/Map;)V;
const #247 = NameAndType	#32:#246;//  "<init>":(Lscala/collection/Map;)V
const #248 = Method	#241.#247;	//  scala/collection/generic/MapBuilder."<init>":(Lscala/collection/Map;)V
const #249 = Asciz	Scala;
const #250 = Asciz	InnerClasses;
const #251 = Asciz	$anon$4;
const #252 = Asciz	$anon$2;
const #253 = Asciz	$anon$3;
const #254 = Asciz	$anon$1;
const #255 = Asciz	DefaultKeySet;
const #256 = Asciz	$anonfun$equals$1;
const #257 = Asciz	$anonfun$addString$1;
const #258 = Asciz	$anonfun$$plus$plus$2;
const #259 = Asciz	$anonfun$$plus$plus$1;
const #260 = Asciz	DefaultValuesIterable;
const #261 = Asciz	scala/collection/generic/MapTemplate$class;
const #262 = class	#261;	//  scala/collection/generic/MapTemplate$class

{
public static void $init$(scala.collection.generic.MapTemplate);
  Code:
   Stack=0, Locals=1, Args_size=1
   0:	return
  LineNumberTable: 
   line 42: 0

  LocalVariableTable: 
   Start  Length  Slot  Name   Signature
   0      1      0    $this       Lscala/collection/generic/MapTemplate;


public static java.lang.String toString(scala.collection.generic.MapTemplate);
  Code:
   Stack=1, Locals=1, Args_size=1
   0:	aload_0
   1:	invokestatic	#16; //Method scala/collection/generic/TraversableTemplate$class.toString:(Lscala/collection/generic/TraversableTemplate;)Ljava/lang/String;
   4:	areturn
  LineNumberTable: 
   line 288: 0

  LocalVariableTable: 
   Start  Length  Slot  Name   Signature
   0      5      0    $this       Lscala/collection/generic/MapTemplate;


public static java.lang.String stringPrefix(scala.collection.generic.MapTemplate);
  Code:
   Stack=1, Locals=1, Args_size=1
   0:	ldc	#19; //String Map
   2:	areturn
  LineNumberTable: 
   line 284: 0

  LocalVariableTable: 
   Start  Length  Slot  Name   Signature
   0      3      0    $this       Lscala/collection/generic/MapTemplate;


public static boolean equals(scala.collection.generic.MapTemplate, java.lang.Object);
  Code:
   Stack=5, Locals=7, Args_size=2
   0:	aload_1
   1:	astore_2
   2:	aload_2
   3:	instanceof	#23; //class scala/collection/Map
   6:	ifeq	61
   9:	aload_2
   10:	checkcast	#23; //class scala/collection/Map
   13:	astore_3
   14:	aload_3
   15:	astore	4
   17:	aload_0
   18:	invokeinterface	#29,  1; //InterfaceMethod scala/collection/generic/TraversableTemplate.size:()I
   23:	aload	4
   25:	invokeinterface	#29,  1; //InterfaceMethod scala/collection/generic/TraversableTemplate.size:()I
   30:	if_icmpne	57
   33:	iconst_0
   34:	istore	5
   36:	aload_0
   37:	new	#31; //class scala/collection/generic/MapTemplate$$anonfun$equals$1
   40:	dup
   41:	aload_0
   42:	aload	4
   44:	invokespecial	#35; //Method scala/collection/generic/MapTemplate$$anonfun$equals$1."<init>":(Lscala/collection/generic/MapTemplate;Lscala/collection/Map;)V
   47:	invokeinterface	#39,  2; //InterfaceMethod scala/collection/generic/TraversableTemplate.forall:(Lscala/Function1;)Z
   52:	istore	5
   54:	goto	70
   57:	iconst_0
   58:	goto	72
   61:	iconst_0
   62:	goto	72
   65:	astore	6
   67:	iconst_0
   68:	istore	5
   70:	iload	5
   72:	ireturn
  Exception table:
   from   to  target type
    36    57    65   Class java/lang/ClassCastException

  LineNumberTable: 
   line 265: 0
   line 266: 14
   line 267: 17
   line 269: 33
   line 268: 34
   line 269: 36
   line 278: 57
   line 279: 61
   line 276: 65
   line 265: 70

  LocalVariableTable: 
   Start  Length  Slot  Name   Signature
   0      73      0    $this       Lscala/collection/generic/MapTemplate;
   0      73      1    that       Ljava/lang/Object;
   2      71      2    temp35       Ljava/lang/Object;
   14      47      3    temp36       Lscala/collection/Map;
   65      7      3    temp36       Lscala/collection/Map;
   17      44      4    other$1       Lscala/collection/Map;
   65      7      4    other$1       Lscala/collection/Map;
   36      21      5    exceptionResult1       Z
   65      7      5    exceptionResult1       Z


public static scala.collection.mutable.StringBuilder addString(scala.collection.generic.MapTemplate, scala.collection.mutable.StringBuilder, java.lang.String, java.lang.String, java.lang.String);
  Code:
   Stack=5, Locals=5, Args_size=5
   0:	aload_0
   1:	invokeinterface	#57,  1; //InterfaceMethod scala/collection/generic/MapTemplate.iterator:()Lscala/collection/Iterator;
   6:	new	#59; //class scala/collection/generic/MapTemplate$$anonfun$addString$1
   9:	dup
   10:	aload_0
   11:	invokespecial	#61; //Method scala/collection/generic/MapTemplate$$anonfun$addString$1."<init>":(Lscala/collection/generic/MapTemplate;)V
   14:	invokeinterface	#67,  2; //InterfaceMethod scala/collection/Iterator.map:(Lscala/Function1;)Lscala/collection/Iterator;
   19:	aload_1
   20:	aload_2
   21:	aload_3
   22:	aload	4
   24:	invokeinterface	#70,  5; //InterfaceMethod scala/collection/Iterator.addString:(Lscala/collection/mutable/StringBuilder;Ljava/lang/String;Ljava/lang/String;Ljava/lang/String;)Lscala/collection/mutable/StringBuilder;
   29:	areturn
  LineNumberTable: 
   line 255: 0

  LocalVariableTable: 
   Start  Length  Slot  Name   Signature
   0      30      0    $this       Lscala/collection/generic/MapTemplate;
   0      30      1    b       Lscala/collection/mutable/StringBuilder;
   0      30      2    start       Ljava/lang/String;
   0      30      3    sep       Ljava/lang/String;
   0      30      4    end       Ljava/lang/String;


public static scala.collection.Map $plus$plus(scala.collection.generic.MapTemplate, scala.collection.Iterator);
  Code:
   Stack=5, Locals=3, Args_size=2
   0:	aload_0
   1:	invokeinterface	#82,  1; //InterfaceMethod scala/collection/generic/TraversableTemplate.thisCollection:()Lscala/collection/generic/TraversableTemplate;
   6:	checkcast	#23; //class scala/collection/Map
   9:	astore_2
   10:	aload_1
   11:	aload_2
   12:	new	#84; //class scala/collection/generic/MapTemplate$$anonfun$$plus$plus$2
   15:	dup
   16:	aload_0
   17:	invokespecial	#85; //Method scala/collection/generic/MapTemplate$$anonfun$$plus$plus$2."<init>":(Lscala/collection/generic/MapTemplate;)V
   20:	invokeinterface	#89,  3; //InterfaceMethod scala/collection/Iterator.$div$colon:(Ljava/lang/Object;Lscala/Function2;)Ljava/lang/Object;
   25:	checkcast	#23; //class scala/collection/Map
   28:	areturn
  LineNumberTable: 
   line 248: 0

  LocalVariableTable: 
   Start  Length  Slot  Name   Signature
   0      29      0    $this       Lscala/collection/generic/MapTemplate;
   0      29      1    iter       Lscala/collection/Iterator;


public static scala.collection.Map $plus$plus(scala.collection.generic.MapTemplate, scala.collection.Traversable);
  Code:
   Stack=5, Locals=3, Args_size=2
   0:	aload_0
   1:	invokeinterface	#82,  1; //InterfaceMethod scala/collection/generic/TraversableTemplate.thisCollection:()Lscala/collection/generic/TraversableTemplate;
   6:	checkcast	#23; //class scala/collection/Map
   9:	astore_2
   10:	aload_1
   11:	aload_2
   12:	new	#94; //class scala/collection/generic/MapTemplate$$anonfun$$plus$plus$1
   15:	dup
   16:	aload_0
   17:	invokespecial	#95; //Method scala/collection/generic/MapTemplate$$anonfun$$plus$plus$1."<init>":(Lscala/collection/generic/MapTemplate;)V
   20:	invokeinterface	#96,  3; //InterfaceMethod scala/collection/generic/TraversableTemplate.$div$colon:(Ljava/lang/Object;Lscala/Function2;)Ljava/lang/Object;
   25:	checkcast	#23; //class scala/collection/Map
   28:	areturn
  LineNumberTable: 
   line 240: 0

  LocalVariableTable: 
   Start  Length  Slot  Name   Signature
   0      29      0    $this       Lscala/collection/generic/MapTemplate;
   0      29      1    elems       Lscala/collection/Traversable;


public static scala.collection.Map $plus(scala.collection.generic.MapTemplate, scala.Tuple2, scala.Tuple2, scala.collection.Sequence);
  Code:
   Stack=2, Locals=4, Args_size=4
   0:	aload_0
   1:	aload_1
   2:	invokeinterface	#103,  2; //InterfaceMethod scala/collection/generic/MapTemplate.$plus:(Lscala/Tuple2;)Lscala/collection/Map;
   7:	aload_2
   8:	invokeinterface	#103,  2; //InterfaceMethod scala/collection/generic/MapTemplate.$plus:(Lscala/Tuple2;)Lscala/collection/Map;
   13:	aload_3
   14:	invokeinterface	#106,  2; //InterfaceMethod scala/collection/generic/MapTemplate.$plus$plus:(Lscala/collection/Traversable;)Lscala/collection/Map;
   19:	areturn
  LineNumberTable: 
   line 232: 0

  LocalVariableTable: 
   Start  Length  Slot  Name   Signature
   0      20      0    $this       Lscala/collection/generic/MapTemplate;
   0      20      1    elem1       Lscala/Tuple2;
   0      20      2    elem2       Lscala/Tuple2;
   0      20      3    elems       Lscala/collection/Sequence;


public static scala.collection.Map updated(scala.collection.generic.MapTemplate, java.lang.Object, java.lang.Object);
  Code:
   Stack=5, Locals=3, Args_size=3
   0:	aload_0
   1:	new	#114; //class scala/Tuple2
   4:	dup
   5:	aload_1
   6:	aload_2
   7:	invokespecial	#117; //Method scala/Tuple2."<init>":(Ljava/lang/Object;Ljava/lang/Object;)V
   10:	invokeinterface	#103,  2; //InterfaceMethod scala/collection/generic/MapTemplate.$plus:(Lscala/Tuple2;)Lscala/collection/Map;
   15:	areturn
  LineNumberTable: 
   line 222: 0

  LocalVariableTable: 
   Start  Length  Slot  Name   Signature
   0      16      0    $this       Lscala/collection/generic/MapTemplate;
   0      16      1    key       Ljava/lang/Object;
   0      16      2    value       Ljava/lang/Object;


public static java.lang.Object mapElements(scala.collection.generic.MapTemplate, scala.Function1);
  Code:
   Stack=2, Locals=2, Args_size=2
   0:	aload_0
   1:	aload_1
   2:	invokeinterface	#125,  2; //InterfaceMethod scala/collection/generic/MapTemplate.mapValues:(Lscala/Function1;)Ljava/lang/Object;
   7:	areturn
  LineNumberTable: 
   line 211: 0

  LocalVariableTable: 
   Start  Length  Slot  Name   Signature
   0      8      0    $this       Lscala/collection/generic/MapTemplate;
   0      8      1    f       Lscala/Function1;


public static java.lang.Object mapValues(scala.collection.generic.MapTemplate, scala.Function1);
  Code:
   Stack=4, Locals=2, Args_size=2
   0:	new	#129; //class scala/collection/generic/MapTemplate$$anon$2
   3:	dup
   4:	aload_0
   5:	aload_1
   6:	invokespecial	#132; //Method scala/collection/generic/MapTemplate$$anon$2."<init>":(Lscala/collection/generic/MapTemplate;Lscala/Function1;)V
   9:	areturn
  LineNumberTable: 
   line 203: 0

  LocalVariableTable: 
   Start  Length  Slot  Name   Signature
   0      10      0    $this       Lscala/collection/generic/MapTemplate;
   0      10      1    f$4       Lscala/Function1;


public static java.lang.Object filterKeys(scala.collection.generic.MapTemplate, scala.Function1);
  Code:
   Stack=4, Locals=2, Args_size=2
   0:	new	#136; //class scala/collection/generic/MapTemplate$$anon$1
   3:	dup
   4:	aload_0
   5:	aload_1
   6:	invokespecial	#137; //Method scala/collection/generic/MapTemplate$$anon$1."<init>":(Lscala/collection/generic/MapTemplate;Lscala/Function1;)V
   9:	areturn
  LineNumberTable: 
   line 193: 0

  LocalVariableTable: 
   Start  Length  Slot  Name   Signature
   0      10      0    $this       Lscala/collection/generic/MapTemplate;
   0      10      1    p$1       Lscala/Function1;


public static java.lang.Object default(scala.collection.generic.MapTemplate, java.lang.Object);
  Code:
   Stack=4, Locals=2, Args_size=2
   0:	new	#142; //class java/util/NoSuchElementException
   3:	dup
   4:	new	#144; //class scala/collection/mutable/StringBuilder
   7:	dup
   8:	invokespecial	#147; //Method scala/collection/mutable/StringBuilder."<init>":()V
   11:	ldc	#149; //String key not found: 
   13:	invokevirtual	#153; //Method scala/collection/mutable/StringBuilder.append:(Ljava/lang/Object;)Lscala/collection/mutable/StringBuilder;
   16:	aload_1
   17:	invokevirtual	#153; //Method scala/collection/mutable/StringBuilder.append:(Ljava/lang/Object;)Lscala/collection/mutable/StringBuilder;
   20:	invokevirtual	#156; //Method scala/collection/mutable/StringBuilder.toString:()Ljava/lang/String;
   23:	invokespecial	#159; //Method java/util/NoSuchElementException."<init>":(Ljava/lang/String;)V
   26:	athrow
  LineNumberTable: 
   line 188: 0

  LocalVariableTable: 
   Start  Length  Slot  Name   Signature
   0      27      0    $this       Lscala/collection/generic/MapTemplate;
   0      27      1    key       Ljava/lang/Object;


public static scala.collection.Iterator values(scala.collection.generic.MapTemplate);
  Code:
   Stack=1, Locals=1, Args_size=1
   0:	aload_0
   1:	invokeinterface	#164,  1; //InterfaceMethod scala/collection/generic/MapTemplate.valuesIterator:()Lscala/collection/Iterator;
   6:	areturn
  LineNumberTable: 
   line 178: 0

  LocalVariableTable: 
   Start  Length  Slot  Name   Signature
   0      7      0    $this       Lscala/collection/generic/MapTemplate;


public static scala.collection.Iterator valuesIterator(scala.collection.generic.MapTemplate);
  Code:
   Stack=3, Locals=1, Args_size=1
   0:	new	#166; //class scala/collection/generic/MapTemplate$$anon$4
   3:	dup
   4:	aload_0
   5:	invokespecial	#167; //Method scala/collection/generic/MapTemplate$$anon$4."<init>":(Lscala/collection/generic/MapTemplate;)V
   8:	areturn
  LineNumberTable: 
   line 167: 0

  LocalVariableTable: 
   Start  Length  Slot  Name   Signature
   0      9      0    $this       Lscala/collection/generic/MapTemplate;


public static scala.collection.Iterable valueIterable(scala.collection.generic.MapTemplate);
  Code:
   Stack=3, Locals=1, Args_size=1
   0:	new	#171; //class scala/collection/generic/MapTemplate$DefaultValuesIterable
   3:	dup
   4:	aload_0
   5:	invokespecial	#172; //Method scala/collection/generic/MapTemplate$DefaultValuesIterable."<init>":(Lscala/collection/generic/MapTemplate;)V
   8:	areturn
  LineNumberTable: 
   line 155: 0

  LocalVariableTable: 
   Start  Length  Slot  Name   Signature
   0      9      0    $this       Lscala/collection/generic/MapTemplate;


public static scala.collection.Iterator keys(scala.collection.generic.MapTemplate);
  Code:
   Stack=1, Locals=1, Args_size=1
   0:	aload_0
   1:	invokeinterface	#176,  1; //InterfaceMethod scala/collection/generic/MapTemplate.keysIterator:()Lscala/collection/Iterator;
   6:	areturn
  LineNumberTable: 
   line 151: 0

  LocalVariableTable: 
   Start  Length  Slot  Name   Signature
   0      7      0    $this       Lscala/collection/generic/MapTemplate;


public static scala.collection.Iterator keysIterator(scala.collection.generic.MapTemplate);
  Code:
   Stack=3, Locals=1, Args_size=1
   0:	new	#178; //class scala/collection/generic/MapTemplate$$anon$3
   3:	dup
   4:	aload_0
   5:	invokespecial	#179; //Method scala/collection/generic/MapTemplate$$anon$3."<init>":(Lscala/collection/generic/MapTemplate;)V
   8:	areturn
  LineNumberTable: 
   line 140: 0

  LocalVariableTable: 
   Start  Length  Slot  Name   Signature
   0      9      0    $this       Lscala/collection/generic/MapTemplate;


public static scala.collection.Set keySet(scala.collection.generic.MapTemplate);
  Code:
   Stack=3, Locals=1, Args_size=1
   0:	new	#183; //class scala/collection/generic/MapTemplate$DefaultKeySet
   3:	dup
   4:	aload_0
   5:	invokespecial	#184; //Method scala/collection/generic/MapTemplate$DefaultKeySet."<init>":(Lscala/collection/generic/MapTemplate;)V
   8:	areturn
  LineNumberTable: 
   line 125: 0

  LocalVariableTable: 
   Start  Length  Slot  Name   Signature
   0      9      0    $this       Lscala/collection/generic/MapTemplate;


public static boolean isDefinedAt(scala.collection.generic.MapTemplate, java.lang.Object);
  Code:
   Stack=2, Locals=2, Args_size=2
   0:	aload_0
   1:	aload_1
   2:	invokeinterface	#189,  2; //InterfaceMethod scala/collection/generic/MapTemplate.contains:(Ljava/lang/Object;)Z
   7:	ireturn
  LineNumberTable: 
   line 122: 0

  LocalVariableTable: 
   Start  Length  Slot  Name   Signature
   0      8      0    $this       Lscala/collection/generic/MapTemplate;
   0      8      1    key       Ljava/lang/Object;


public static boolean contains(scala.collection.generic.MapTemplate, java.lang.Object);
  Code:
   Stack=3, Locals=4, Args_size=2
   0:	aload_0
   1:	aload_1
   2:	invokeinterface	#193,  2; //InterfaceMethod scala/collection/generic/MapTemplate.get:(Ljava/lang/Object;)Lscala/Option;
   7:	astore_2
   8:	getstatic	#199; //Field scala/None$.MODULE$:Lscala/None$;
   11:	aload_2
   12:	astore_3
   13:	dup
   14:	ifnonnull	25
   17:	pop
   18:	aload_3
   19:	ifnull	32
   22:	goto	43
   25:	aload_3
   26:	invokevirtual	#203; //Method java/lang/Object.equals:(Ljava/lang/Object;)Z
   29:	ifeq	43
   32:	aload_2
   33:	instanceof	#195; //class scala/None$
   36:	ifeq	43
   39:	iconst_0
   40:	goto	51
   43:	aload_2
   44:	instanceof	#205; //class scala/Some
   47:	ifeq	52
   50:	iconst_1
   51:	ireturn
   52:	new	#207; //class scala/MatchError
   55:	dup
   56:	aload_2
   57:	invokevirtual	#210; //Method scala/Option.toString:()Ljava/lang/String;
   60:	invokespecial	#211; //Method scala/MatchError."<init>":(Ljava/lang/String;)V
   63:	athrow
  LineNumberTable: 
   line 112: 0
   line 113: 39
   line 112: 43
   line 114: 50
   line 112: 51

  LocalVariableTable: 
   Start  Length  Slot  Name   Signature
   0      64      0    $this       Lscala/collection/generic/MapTemplate;
   0      64      1    key       Ljava/lang/Object;
   8      56      2    temp9       Lscala/Option;


public static java.lang.Object apply(scala.collection.generic.MapTemplate, java.lang.Object);
  Code:
   Stack=3, Locals=6, Args_size=2
   0:	aload_0
   1:	aload_1
   2:	invokeinterface	#193,  2; //InterfaceMethod scala/collection/generic/MapTemplate.get:(Ljava/lang/Object;)Lscala/Option;
   7:	astore_2
   8:	getstatic	#199; //Field scala/None$.MODULE$:Lscala/None$;
   11:	aload_2
   12:	astore_3
   13:	dup
   14:	ifnonnull	25
   17:	pop
   18:	aload_3
   19:	ifnull	32
   22:	goto	49
   25:	aload_3
   26:	invokevirtual	#203; //Method java/lang/Object.equals:(Ljava/lang/Object;)Z
   29:	ifeq	49
   32:	aload_2
   33:	instanceof	#195; //class scala/None$
   36:	ifeq	49
   39:	aload_0
   40:	aload_1
   41:	invokeinterface	#217,  2; //InterfaceMethod scala/collection/generic/MapTemplate.default:(Ljava/lang/Object;)Ljava/lang/Object;
   46:	goto	71
   49:	aload_2
   50:	instanceof	#205; //class scala/Some
   53:	ifeq	72
   56:	aload_2
   57:	checkcast	#205; //class scala/Some
   60:	astore	4
   62:	aload	4
   64:	invokevirtual	#221; //Method scala/Some.x:()Ljava/lang/Object;
   67:	astore	5
   69:	aload	5
   71:	areturn
   72:	new	#207; //class scala/MatchError
   75:	dup
   76:	aload_2
   77:	invokevirtual	#210; //Method scala/Option.toString:()Ljava/lang/String;
   80:	invokespecial	#211; //Method scala/MatchError."<init>":(Ljava/lang/String;)V
   83:	athrow
  LineNumberTable: 
   line 102: 0
   line 103: 39
   line 102: 49
   line 104: 69
   line 102: 71

  LocalVariableTable: 
   Start  Length  Slot  Name   Signature
   0      84      0    $this       Lscala/collection/generic/MapTemplate;
   0      84      1    key       Ljava/lang/Object;
   8      76      2    temp5       Lscala/Option;
   62      9      4    temp7       Lscala/Some;
   69      2      5    temp8       Ljava/lang/Object;


public static java.lang.Object getOrElse(scala.collection.generic.MapTemplate, java.lang.Object, scala.Function0);
  Code:
   Stack=3, Locals=7, Args_size=3
   0:	aload_0
   1:	aload_1
   2:	invokeinterface	#193,  2; //InterfaceMethod scala/collection/generic/MapTemplate.get:(Ljava/lang/Object;)Lscala/Option;
   7:	astore_3
   8:	aload_3
   9:	instanceof	#205; //class scala/Some
   12:	ifeq	33
   15:	aload_3
   16:	checkcast	#205; //class scala/Some
   19:	astore	4
   21:	aload	4
   23:	invokevirtual	#221; //Method scala/Some.x:()Ljava/lang/Object;
   26:	astore	5
   28:	aload	5
   30:	goto	73
   33:	getstatic	#199; //Field scala/None$.MODULE$:Lscala/None$;
   36:	aload_3
   37:	astore	6
   39:	dup
   40:	ifnonnull	52
   43:	pop
   44:	aload	6
   46:	ifnull	60
   49:	goto	74
   52:	aload	6
   54:	invokevirtual	#203; //Method java/lang/Object.equals:(Ljava/lang/Object;)Z
   57:	ifeq	74
   60:	aload_3
   61:	instanceof	#195; //class scala/None$
   64:	ifeq	74
   67:	aload_2
   68:	invokeinterface	#231,  1; //InterfaceMethod scala/Function0.apply:()Ljava/lang/Object;
   73:	areturn
   74:	new	#207; //class scala/MatchError
   77:	dup
   78:	aload_3
   79:	invokevirtual	#210; //Method scala/Option.toString:()Ljava/lang/String;
   82:	invokespecial	#211; //Method scala/MatchError."<init>":(Ljava/lang/String;)V
   85:	athrow
  LineNumberTable: 
   line 90: 0
   line 91: 28
   line 90: 33
   line 92: 67
   line 90: 73

  LocalVariableTable: 
   Start  Length  Slot  Name   Signature
   0      86      0    $this       Lscala/collection/generic/MapTemplate;
   0      86      1    key       Ljava/lang/Object;
   0      86      2    default       Lscala/Function0;
   8      78      3    temp1       Lscala/Option;
   21      9      4    temp2       Lscala/Some;
   28      2      5    temp3       Ljava/lang/Object;


public static boolean isEmpty(scala.collection.generic.MapTemplate);
  Code:
   Stack=2, Locals=1, Args_size=1
   0:	aload_0
   1:	invokeinterface	#29,  1; //InterfaceMethod scala/collection/generic/TraversableTemplate.size:()I
   6:	iconst_0
   7:	if_icmpne	14
   10:	iconst_1
   11:	goto	15
   14:	iconst_0
   15:	ireturn
  LineNumberTable: 
   line 82: 0

  LocalVariableTable: 
   Start  Length  Slot  Name   Signature
   0      16      0    $this       Lscala/collection/generic/MapTemplate;


public static scala.collection.generic.Builder newBuilder(scala.collection.generic.MapTemplate);
  Code:
   Stack=3, Locals=1, Args_size=1
   0:	new	#241; //class scala/collection/generic/MapBuilder
   3:	dup
   4:	aload_0
   5:	invokeinterface	#245,  1; //InterfaceMethod scala/collection/generic/MapTemplate.empty:()Lscala/collection/generic/MapTemplate;
   10:	checkcast	#23; //class scala/collection/Map
   13:	invokespecial	#248; //Method scala/collection/generic/MapBuilder."<init>":(Lscala/collection/Map;)V
   16:	areturn
  LineNumberTable: 
   line 53: 0

  LocalVariableTable: 
   Start  Length  Slot  Name   Signature
   0      17      0    $this       Lscala/collection/generic/MapTemplate;


}

