Compiled from "MapTemplate.scala"
public class scala.collection.generic.MapTemplate$DefaultKeySet extends java.lang.Object implements scala.collection.Set,scala.ScalaObject
  SourceFile: "MapTemplate.scala"
  Signature: length = 0x2
   02 5E 
  Scala: length = 0x
   
  InnerClass: 
   public #609= #15 of #188; //DefaultKeySet=class scala/collection/generic/MapTemplate$DefaultKeySet of class scala/collection/generic/MapTemplate
   public final #610= #143 of #15; //$anonfun$foreach$1=class scala/collection/generic/MapTemplate$DefaultKeySet$$anonfun$foreach$1 of class scala/collection/generic/MapTemplate$DefaultKeySet
   public final #611= #192 of #15; //$anonfun$iterator$1=class scala/collection/generic/MapTemplate$DefaultKeySet$$anonfun$iterator$1 of class scala/collection/generic/MapTemplate$DefaultKeySet
  minor version: 0
  major version: 49
  Constant pool:
const #1 = Asciz	SourceFile;
const #2 = Asciz	MapTemplate.scala;
const #3 = Asciz	$outer;
const #4 = Asciz	Lscala/collection/generic/MapTemplate;;
const #5 = Asciz	<init>;
const #6 = Asciz	(Lscala/collection/generic/MapTemplate;)V;
const #7 = Asciz	Code;
const #8 = Asciz	LineNumberTable;
const #9 = Asciz	java/lang/NullPointerException;
const #10 = class	#9;	//  java/lang/NullPointerException
const #11 = Asciz	()V;
const #12 = NameAndType	#5:#11;//  "<init>":()V
const #13 = Method	#10.#12;	//  java/lang/NullPointerException."<init>":()V
const #14 = Asciz	scala/collection/generic/MapTemplate$DefaultKeySet;
const #15 = class	#14;	//  scala/collection/generic/MapTemplate$DefaultKeySet
const #16 = NameAndType	#3:#4;//  $outer:Lscala/collection/generic/MapTemplate;
const #17 = Field	#15.#16;	//  scala/collection/generic/MapTemplate$DefaultKeySet.$outer:Lscala/collection/generic/MapTemplate;
const #18 = Asciz	java/lang/Object;
const #19 = class	#18;	//  java/lang/Object
const #20 = Method	#19.#12;	//  java/lang/Object."<init>":()V
const #21 = Asciz	scala/Function1$class;
const #22 = class	#21;	//  scala/Function1$class
const #23 = Asciz	$init$;
const #24 = Asciz	(Lscala/Function1;)V;
const #25 = NameAndType	#23:#24;//  $init$:(Lscala/Function1;)V
const #26 = Method	#22.#25;	//  scala/Function1$class.$init$:(Lscala/Function1;)V
const #27 = Asciz	scala/collection/generic/TraversableTemplate$class;
const #28 = class	#27;	//  scala/collection/generic/TraversableTemplate$class
const #29 = Asciz	(Lscala/collection/generic/TraversableTemplate;)V;
const #30 = NameAndType	#23:#29;//  $init$:(Lscala/collection/generic/TraversableTemplate;)V
const #31 = Method	#28.#30;	//  scala/collection/generic/TraversableTemplate$class.$init$:(Lscala/collection/generic/TraversableTemplate;)V
const #32 = Asciz	scala/collection/generic/TraversableClass$class;
const #33 = class	#32;	//  scala/collection/generic/TraversableClass$class
const #34 = Asciz	(Lscala/collection/generic/TraversableClass;)V;
const #35 = NameAndType	#23:#34;//  $init$:(Lscala/collection/generic/TraversableClass;)V
const #36 = Method	#33.#35;	//  scala/collection/generic/TraversableClass$class.$init$:(Lscala/collection/generic/TraversableClass;)V
const #37 = Asciz	scala/collection/Traversable$class;
const #38 = class	#37;	//  scala/collection/Traversable$class
const #39 = Asciz	(Lscala/collection/Traversable;)V;
const #40 = NameAndType	#23:#39;//  $init$:(Lscala/collection/Traversable;)V
const #41 = Method	#38.#40;	//  scala/collection/Traversable$class.$init$:(Lscala/collection/Traversable;)V
const #42 = Asciz	scala/collection/generic/IterableTemplate$class;
const #43 = class	#42;	//  scala/collection/generic/IterableTemplate$class
const #44 = Asciz	(Lscala/collection/generic/IterableTemplate;)V;
const #45 = NameAndType	#23:#44;//  $init$:(Lscala/collection/generic/IterableTemplate;)V
const #46 = Method	#43.#45;	//  scala/collection/generic/IterableTemplate$class.$init$:(Lscala/collection/generic/IterableTemplate;)V
const #47 = Asciz	scala/collection/Iterable$class;
const #48 = class	#47;	//  scala/collection/Iterable$class
const #49 = Asciz	(Lscala/collection/Iterable;)V;
const #50 = NameAndType	#23:#49;//  $init$:(Lscala/collection/Iterable;)V
const #51 = Method	#48.#50;	//  scala/collection/Iterable$class.$init$:(Lscala/collection/Iterable;)V
const #52 = Asciz	scala/collection/generic/SetClass$class;
const #53 = class	#52;	//  scala/collection/generic/SetClass$class
const #54 = Asciz	(Lscala/collection/generic/SetClass;)V;
const #55 = NameAndType	#23:#54;//  $init$:(Lscala/collection/generic/SetClass;)V
const #56 = Method	#53.#55;	//  scala/collection/generic/SetClass$class.$init$:(Lscala/collection/generic/SetClass;)V
const #57 = Asciz	scala/collection/generic/Addable$class;
const #58 = class	#57;	//  scala/collection/generic/Addable$class
const #59 = Asciz	(Lscala/collection/generic/Addable;)V;
const #60 = NameAndType	#23:#59;//  $init$:(Lscala/collection/generic/Addable;)V
const #61 = Method	#58.#60;	//  scala/collection/generic/Addable$class.$init$:(Lscala/collection/generic/Addable;)V
const #62 = Asciz	scala/collection/generic/Subtractable$class;
const #63 = class	#62;	//  scala/collection/generic/Subtractable$class
const #64 = Asciz	(Lscala/collection/generic/Subtractable;)V;
const #65 = NameAndType	#23:#64;//  $init$:(Lscala/collection/generic/Subtractable;)V
const #66 = Method	#63.#65;	//  scala/collection/generic/Subtractable$class.$init$:(Lscala/collection/generic/Subtractable;)V
const #67 = Asciz	scala/collection/generic/SetTemplate$class;
const #68 = class	#67;	//  scala/collection/generic/SetTemplate$class
const #69 = Asciz	(Lscala/collection/generic/SetTemplate;)V;
const #70 = NameAndType	#23:#69;//  $init$:(Lscala/collection/generic/SetTemplate;)V
const #71 = Method	#68.#70;	//  scala/collection/generic/SetTemplate$class.$init$:(Lscala/collection/generic/SetTemplate;)V
const #72 = Asciz	scala/collection/Set$class;
const #73 = class	#72;	//  scala/collection/Set$class
const #74 = Asciz	(Lscala/collection/Set;)V;
const #75 = NameAndType	#23:#74;//  $init$:(Lscala/collection/Set;)V
const #76 = Method	#73.#75;	//  scala/collection/Set$class.$init$:(Lscala/collection/Set;)V
const #77 = Asciz	this;
const #78 = Asciz	Lscala/collection/generic/MapTemplate$DefaultKeySet;;
const #79 = Asciz	LocalVariableTable;
const #80 = Asciz	(Lscala/collection/generic/MapTemplate<TA;TB;TThis;>;)V;
const #81 = Asciz	Signature;
const #82 = Asciz	$plus;
const #83 = Asciz	(Ljava/lang/Object;)Lscala/collection/generic/SetTemplate;;
const #84 = Asciz	(Ljava/lang/Object;)Lscala/collection/Set;;
const #85 = NameAndType	#82:#84;//  $plus:(Ljava/lang/Object;)Lscala/collection/Set;
const #86 = Method	#15.#85;	//  scala/collection/generic/MapTemplate$DefaultKeySet.$plus:(Ljava/lang/Object;)Lscala/collection/Set;
const #87 = Asciz	elem;
const #88 = Asciz	Ljava/lang/Object;;
const #89 = Asciz	(Ljava/lang/Object;)Lscala/collection/generic/Addable;;
const #90 = Asciz	$minus;
const #91 = NameAndType	#90:#84;//  $minus:(Ljava/lang/Object;)Lscala/collection/Set;
const #92 = Method	#15.#91;	//  scala/collection/generic/MapTemplate$DefaultKeySet.$minus:(Ljava/lang/Object;)Lscala/collection/Set;
const #93 = Asciz	(Ljava/lang/Object;)Lscala/collection/generic/Subtractable;;
const #94 = Asciz	apply;
const #95 = Asciz	(Ljava/lang/Object;)Ljava/lang/Object;;
const #96 = Asciz	scala/collection/generic/SetTemplate;
const #97 = class	#96;	//  scala/collection/generic/SetTemplate
const #98 = Asciz	(Ljava/lang/Object;)Z;
const #99 = NameAndType	#94:#98;//  apply:(Ljava/lang/Object;)Z
const #100 = InterfaceMethod	#97.#99;	//  scala/collection/generic/SetTemplate.apply:(Ljava/lang/Object;)Z
const #101 = Asciz	scala/runtime/BoxesRunTime;
const #102 = class	#101;	//  scala/runtime/BoxesRunTime
const #103 = Asciz	boxToBoolean;
const #104 = Asciz	(Z)Ljava/lang/Boolean;;
const #105 = NameAndType	#103:#104;//  boxToBoolean:(Z)Ljava/lang/Boolean;
const #106 = Method	#102.#105;	//  scala/runtime/BoxesRunTime.boxToBoolean:(Z)Ljava/lang/Boolean;
const #107 = Asciz	v1;
const #108 = Asciz	empty;
const #109 = Asciz	()Lscala/collection/generic/SetTemplate;;
const #110 = Asciz	scala/collection/generic/SetClass;
const #111 = class	#110;	//  scala/collection/generic/SetClass
const #112 = Asciz	()Lscala/collection/Set;;
const #113 = NameAndType	#108:#112;//  empty:()Lscala/collection/Set;
const #114 = InterfaceMethod	#111.#113;	//  scala/collection/generic/SetClass.empty:()Lscala/collection/Set;
const #115 = Asciz	view;
const #116 = Asciz	(II)Lscala/collection/generic/TraversableView;;
const #117 = Asciz	scala/collection/generic/IterableTemplate;
const #118 = class	#117;	//  scala/collection/generic/IterableTemplate
const #119 = Asciz	(II)Lscala/collection/generic/IterableView;;
const #120 = NameAndType	#115:#119;//  view:(II)Lscala/collection/generic/IterableView;
const #121 = InterfaceMethod	#118.#120;	//  scala/collection/generic/IterableTemplate.view:(II)Lscala/collection/generic/IterableView;
const #122 = Asciz	from;
const #123 = Asciz	I;
const #124 = Asciz	until;
const #125 = Asciz	thisCollection;
const #126 = Asciz	()Lscala/collection/generic/Subtractable;;
const #127 = Asciz	scala/collection/generic/TraversableTemplate;
const #128 = class	#127;	//  scala/collection/generic/TraversableTemplate
const #129 = Asciz	()Lscala/collection/generic/TraversableTemplate;;
const #130 = NameAndType	#125:#129;//  thisCollection:()Lscala/collection/generic/TraversableTemplate;
const #131 = InterfaceMethod	#128.#130;	//  scala/collection/generic/TraversableTemplate.thisCollection:()Lscala/collection/generic/TraversableTemplate;
const #132 = Asciz	scala/collection/generic/Subtractable;
const #133 = class	#132;	//  scala/collection/generic/Subtractable
const #134 = Asciz	()Lscala/collection/generic/Addable;;
const #135 = Asciz	scala/collection/generic/Addable;
const #136 = class	#135;	//  scala/collection/generic/Addable
const #137 = Asciz	scala$collection$generic$MapTemplate$DefaultKeySet$$$outer;
const #138 = Asciz	()Lscala/collection/generic/MapTemplate;;
const #139 = Asciz	foreach;
const #140 = NameAndType	#137:#138;//  scala$collection$generic$MapTemplate$DefaultKeySet$$$outer:()Lscala/collection/generic/MapTemplate;
const #141 = Method	#15.#140;	//  scala/collection/generic/MapTemplate$DefaultKeySet.scala$collection$generic$MapTemplate$DefaultKeySet$$$outer:()Lscala/collection/generic/MapTemplate;
const #142 = Asciz	scala/collection/generic/MapTemplate$DefaultKeySet$$anonfun$foreach$1;
const #143 = class	#142;	//  scala/collection/generic/MapTemplate$DefaultKeySet$$anonfun$foreach$1
const #144 = Asciz	(Lscala/collection/generic/MapTemplate$DefaultKeySet;Lscala/Function1;)V;
const #145 = NameAndType	#5:#144;//  "<init>":(Lscala/collection/generic/MapTemplate$DefaultKeySet;Lscala/Function1;)V
const #146 = Method	#143.#145;	//  scala/collection/generic/MapTemplate$DefaultKeySet$$anonfun$foreach$1."<init>":(Lscala/collection/generic/MapTemplate$DefaultKeySet;Lscala/Function1;)V
const #147 = NameAndType	#139:#24;//  foreach:(Lscala/Function1;)V
const #148 = InterfaceMethod	#118.#147;	//  scala/collection/generic/IterableTemplate.foreach:(Lscala/Function1;)V
const #149 = Asciz	f$1;
const #150 = Asciz	Lscala/Function1;;
const #151 = Asciz	<C:Ljava/lang/Object;>(Lscala/Function1<TA;TC;>;)V;
const #152 = Asciz	size;
const #153 = Asciz	()I;
const #154 = NameAndType	#152:#153;//  size:()I
const #155 = InterfaceMethod	#128.#154;	//  scala/collection/generic/TraversableTemplate.size:()I
const #156 = Asciz	scala/collection/Set$;
const #157 = class	#156;	//  scala/collection/Set$
const #158 = Asciz	MODULE$;
const #159 = Asciz	Lscala/collection/Set$;;
const #160 = NameAndType	#158:#159;//  MODULE$:Lscala/collection/Set$;
const #161 = Field	#157.#160;	//  scala/collection/Set$.MODULE$:Lscala/collection/Set$;
const #162 = Asciz	scala/runtime/ScalaRunTime$;
const #163 = class	#162;	//  scala/runtime/ScalaRunTime$
const #164 = Asciz	Lscala/runtime/ScalaRunTime$;;
const #165 = NameAndType	#158:#164;//  MODULE$:Lscala/runtime/ScalaRunTime$;
const #166 = Field	#163.#165;	//  scala/runtime/ScalaRunTime$.MODULE$:Lscala/runtime/ScalaRunTime$;
const #167 = Asciz	boxArray;
const #168 = Asciz	(Ljava/lang/Object;)Lscala/runtime/BoxedArray;;
const #169 = NameAndType	#167:#168;//  boxArray:(Ljava/lang/Object;)Lscala/runtime/BoxedArray;
const #170 = Method	#163.#169;	//  scala/runtime/ScalaRunTime$.boxArray:(Ljava/lang/Object;)Lscala/runtime/BoxedArray;
const #171 = Asciz	(Lscala/collection/Sequence;)Lscala/collection/Traversable;;
const #172 = NameAndType	#94:#171;//  apply:(Lscala/collection/Sequence;)Lscala/collection/Traversable;
const #173 = Method	#157.#172;	//  scala/collection/Set$.apply:(Lscala/collection/Sequence;)Lscala/collection/Traversable;
const #174 = Asciz	$plus$plus;
const #175 = Asciz	(Lscala/collection/Traversable;)Lscala/collection/generic/Addable;;
const #176 = NameAndType	#174:#175;//  $plus$plus:(Lscala/collection/Traversable;)Lscala/collection/generic/Addable;
const #177 = InterfaceMethod	#136.#176;	//  scala/collection/generic/Addable.$plus$plus:(Lscala/collection/Traversable;)Lscala/collection/generic/Addable;
const #178 = NameAndType	#90:#83;//  $minus:(Ljava/lang/Object;)Lscala/collection/generic/SetTemplate;
const #179 = InterfaceMethod	#97.#178;	//  scala/collection/generic/SetTemplate.$minus:(Ljava/lang/Object;)Lscala/collection/generic/SetTemplate;
const #180 = Asciz	scala/collection/Set;
const #181 = class	#180;	//  scala/collection/Set
const #182 = Asciz	(TA;)Lscala/collection/Set<TA;>;;
const #183 = NameAndType	#82:#83;//  $plus:(Ljava/lang/Object;)Lscala/collection/generic/SetTemplate;
const #184 = InterfaceMethod	#97.#183;	//  scala/collection/generic/SetTemplate.$plus:(Ljava/lang/Object;)Lscala/collection/generic/SetTemplate;
const #185 = Asciz	iterator;
const #186 = Asciz	()Lscala/collection/Iterator;;
const #187 = Asciz	scala/collection/generic/MapTemplate;
const #188 = class	#187;	//  scala/collection/generic/MapTemplate
const #189 = NameAndType	#185:#186;//  iterator:()Lscala/collection/Iterator;
const #190 = InterfaceMethod	#188.#189;	//  scala/collection/generic/MapTemplate.iterator:()Lscala/collection/Iterator;
const #191 = Asciz	scala/collection/generic/MapTemplate$DefaultKeySet$$anonfun$iterator$1;
const #192 = class	#191;	//  scala/collection/generic/MapTemplate$DefaultKeySet$$anonfun$iterator$1
const #193 = Asciz	(Lscala/collection/generic/MapTemplate$DefaultKeySet;)V;
const #194 = NameAndType	#5:#193;//  "<init>":(Lscala/collection/generic/MapTemplate$DefaultKeySet;)V
const #195 = Method	#192.#194;	//  scala/collection/generic/MapTemplate$DefaultKeySet$$anonfun$iterator$1."<init>":(Lscala/collection/generic/MapTemplate$DefaultKeySet;)V
const #196 = Asciz	scala/collection/Iterator;
const #197 = class	#196;	//  scala/collection/Iterator
const #198 = Asciz	map;
const #199 = Asciz	(Lscala/Function1;)Lscala/collection/Iterator;;
const #200 = NameAndType	#198:#199;//  map:(Lscala/Function1;)Lscala/collection/Iterator;
const #201 = InterfaceMethod	#197.#200;	//  scala/collection/Iterator.map:(Lscala/Function1;)Lscala/collection/Iterator;
const #202 = Asciz	()Lscala/collection/Iterator<TA;>;;
const #203 = Asciz	contains;
const #204 = NameAndType	#203:#98;//  contains:(Ljava/lang/Object;)Z
const #205 = InterfaceMethod	#188.#204;	//  scala/collection/generic/MapTemplate.contains:(Ljava/lang/Object;)Z
const #206 = Asciz	key;
const #207 = Asciz	(TA;)Z;
const #208 = Asciz	andThen;
const #209 = Asciz	(Lscala/Function1;)Lscala/Function1;;
const #210 = Asciz	(Lscala/Function1;Lscala/Function1;)Lscala/Function1;;
const #211 = NameAndType	#208:#210;//  andThen:(Lscala/Function1;Lscala/Function1;)Lscala/Function1;
const #212 = Method	#22.#211;	//  scala/Function1$class.andThen:(Lscala/Function1;Lscala/Function1;)Lscala/Function1;
const #213 = Asciz	g;
const #214 = Asciz	compose;
const #215 = NameAndType	#214:#210;//  compose:(Lscala/Function1;Lscala/Function1;)Lscala/Function1;
const #216 = Method	#22.#215;	//  scala/Function1$class.compose:(Lscala/Function1;Lscala/Function1;)Lscala/Function1;
const #217 = Asciz	addString;
const #218 = Asciz	(Lscala/collection/mutable/StringBuilder;)Lscala/collection/mutable/StringBuilder;;
const #219 = Asciz	(Lscala/collection/generic/TraversableTemplate;Lscala/collection/mutable/StringBuilder;)Lscala/collection/mutable/StringBuilder;;
const #220 = NameAndType	#217:#219;//  addString:(Lscala/collection/generic/TraversableTemplate;Lscala/collection/mutable/StringBuilder;)Lscala/collection/mutable/StringBuilder;
const #221 = Method	#28.#220;	//  scala/collection/generic/TraversableTemplate$class.addString:(Lscala/collection/generic/TraversableTemplate;Lscala/collection/mutable/StringBuilder;)Lscala/collection/mutable/StringBuilder;
const #222 = Asciz	b;
const #223 = Asciz	Lscala/collection/mutable/StringBuilder;;
const #224 = Asciz	(Lscala/collection/mutable/StringBuilder;Ljava/lang/String;)Lscala/collection/mutable/StringBuilder;;
const #225 = Asciz	(Lscala/collection/generic/TraversableTemplate;Lscala/collection/mutable/StringBuilder;Ljava/lang/String;)Lscala/collection/mutable/StringBuilder;;
const #226 = NameAndType	#217:#225;//  addString:(Lscala/collection/generic/TraversableTemplate;Lscala/collection/mutable/StringBuilder;Ljava/lang/String;)Lscala/collection/mutable/StringBuilder;
const #227 = Method	#28.#226;	//  scala/collection/generic/TraversableTemplate$class.addString:(Lscala/collection/generic/TraversableTemplate;Lscala/collection/mutable/StringBuilder;Ljava/lang/String;)Lscala/collection/mutable/StringBuilder;
const #228 = Asciz	sep;
const #229 = Asciz	Ljava/lang/String;;
const #230 = Asciz	(Lscala/collection/mutable/StringBuilder;Ljava/lang/String;Ljava/lang/String;Ljava/lang/String;)Lscala/collection/mutable/StringBuilder;;
const #231 = Asciz	(Lscala/collection/generic/TraversableTemplate;Lscala/collection/mutable/StringBuilder;Ljava/lang/String;Ljava/lang/String;Ljava/lang/String;)Lscala/collection/mutable/StringBuilder;;
const #232 = NameAndType	#217:#231;//  addString:(Lscala/collection/generic/TraversableTemplate;Lscala/collection/mutable/StringBuilder;Ljava/lang/String;Ljava/lang/String;Ljava/lang/String;)Lscala/collection/mutable/StringBuilder;
const #233 = Method	#28.#232;	//  scala/collection/generic/TraversableTemplate$class.addString:(Lscala/collection/generic/TraversableTemplate;Lscala/collection/mutable/StringBuilder;Ljava/lang/String;Ljava/lang/String;Ljava/lang/String;)Lscala/collection/mutable/StringBuilder;
const #234 = Asciz	start;
const #235 = Asciz	end;
const #236 = Asciz	mkString;
const #237 = Asciz	()Ljava/lang/String;;
const #238 = Asciz	(Lscala/collection/generic/TraversableTemplate;)Ljava/lang/String;;
const #239 = NameAndType	#236:#238;//  mkString:(Lscala/collection/generic/TraversableTemplate;)Ljava/lang/String;
const #240 = Method	#28.#239;	//  scala/collection/generic/TraversableTemplate$class.mkString:(Lscala/collection/generic/TraversableTemplate;)Ljava/lang/String;
const #241 = Asciz	(Ljava/lang/String;)Ljava/lang/String;;
const #242 = Asciz	(Lscala/collection/generic/TraversableTemplate;Ljava/lang/String;)Ljava/lang/String;;
const #243 = NameAndType	#236:#242;//  mkString:(Lscala/collection/generic/TraversableTemplate;Ljava/lang/String;)Ljava/lang/String;
const #244 = Method	#28.#243;	//  scala/collection/generic/TraversableTemplate$class.mkString:(Lscala/collection/generic/TraversableTemplate;Ljava/lang/String;)Ljava/lang/String;
const #245 = Asciz	(Ljava/lang/String;Ljava/lang/String;Ljava/lang/String;)Ljava/lang/String;;
const #246 = Asciz	(Lscala/collection/generic/TraversableTemplate;Ljava/lang/String;Ljava/lang/String;Ljava/lang/String;)Ljava/lang/String;;
const #247 = NameAndType	#236:#246;//  mkString:(Lscala/collection/generic/TraversableTemplate;Ljava/lang/String;Ljava/lang/String;Ljava/lang/String;)Ljava/lang/String;
const #248 = Method	#28.#247;	//  scala/collection/generic/TraversableTemplate$class.mkString:(Lscala/collection/generic/TraversableTemplate;Ljava/lang/String;Ljava/lang/String;Ljava/lang/String;)Ljava/lang/String;
const #249 = Asciz	toSet;
const #250 = Asciz	()Lscala/collection/immutable/Set;;
const #251 = Asciz	(Lscala/collection/generic/TraversableTemplate;)Lscala/collection/immutable/Set;;
const #252 = NameAndType	#249:#251;//  toSet:(Lscala/collection/generic/TraversableTemplate;)Lscala/collection/immutable/Set;
const #253 = Method	#28.#252;	//  scala/collection/generic/TraversableTemplate$class.toSet:(Lscala/collection/generic/TraversableTemplate;)Lscala/collection/immutable/Set;
const #254 = Asciz	toSequence;
const #255 = Asciz	()Lscala/collection/Sequence;;
const #256 = Asciz	(Lscala/collection/generic/TraversableTemplate;)Lscala/collection/Sequence;;
const #257 = NameAndType	#254:#256;//  toSequence:(Lscala/collection/generic/TraversableTemplate;)Lscala/collection/Sequence;
const #258 = Method	#28.#257;	//  scala/collection/generic/TraversableTemplate$class.toSequence:(Lscala/collection/generic/TraversableTemplate;)Lscala/collection/Sequence;
const #259 = Asciz	toList;
const #260 = Asciz	()Lscala/collection/immutable/List;;
const #261 = Asciz	(Lscala/collection/generic/TraversableTemplate;)Lscala/collection/immutable/List;;
const #262 = NameAndType	#259:#261;//  toList:(Lscala/collection/generic/TraversableTemplate;)Lscala/collection/immutable/List;
const #263 = Method	#28.#262;	//  scala/collection/generic/TraversableTemplate$class.toList:(Lscala/collection/generic/TraversableTemplate;)Lscala/collection/immutable/List;
const #264 = Asciz	toArray;
const #265 = Asciz	()Lscala/runtime/BoxedArray;;
const #266 = Asciz	(Lscala/collection/generic/TraversableTemplate;)Lscala/runtime/BoxedArray;;
const #267 = NameAndType	#264:#266;//  toArray:(Lscala/collection/generic/TraversableTemplate;)Lscala/runtime/BoxedArray;
const #268 = Method	#28.#267;	//  scala/collection/generic/TraversableTemplate$class.toArray:(Lscala/collection/generic/TraversableTemplate;)Lscala/runtime/BoxedArray;
const #269 = Asciz	copyToArray;
const #270 = Asciz	(Lscala/runtime/BoxedArray;I)V;
const #271 = Asciz	(Lscala/collection/generic/TraversableTemplate;Lscala/runtime/BoxedArray;I)V;
const #272 = NameAndType	#269:#271;//  copyToArray:(Lscala/collection/generic/TraversableTemplate;Lscala/runtime/BoxedArray;I)V
const #273 = Method	#28.#272;	//  scala/collection/generic/TraversableTemplate$class.copyToArray:(Lscala/collection/generic/TraversableTemplate;Lscala/runtime/BoxedArray;I)V
const #274 = Asciz	xs;
const #275 = Asciz	Lscala/runtime/BoxedArray;;
const #276 = Asciz	(Lscala/runtime/BoxedArray;II)V;
const #277 = Asciz	(Lscala/collection/generic/TraversableTemplate;Lscala/runtime/BoxedArray;II)V;
const #278 = NameAndType	#269:#277;//  copyToArray:(Lscala/collection/generic/TraversableTemplate;Lscala/runtime/BoxedArray;II)V
const #279 = Method	#28.#278;	//  scala/collection/generic/TraversableTemplate$class.copyToArray:(Lscala/collection/generic/TraversableTemplate;Lscala/runtime/BoxedArray;II)V
const #280 = Asciz	len;
const #281 = Asciz	copyToBuffer;
const #282 = Asciz	(Lscala/collection/mutable/Buffer;)V;
const #283 = Asciz	(Lscala/collection/generic/TraversableTemplate;Lscala/collection/mutable/Buffer;)V;
const #284 = NameAndType	#281:#283;//  copyToBuffer:(Lscala/collection/generic/TraversableTemplate;Lscala/collection/mutable/Buffer;)V
const #285 = Method	#28.#284;	//  scala/collection/generic/TraversableTemplate$class.copyToBuffer:(Lscala/collection/generic/TraversableTemplate;Lscala/collection/mutable/Buffer;)V
const #286 = Asciz	dest;
const #287 = Asciz	Lscala/collection/mutable/Buffer;;
const #288 = Asciz	splitAt;
const #289 = Asciz	(I)Lscala/Tuple2;;
const #290 = Asciz	(Lscala/collection/generic/TraversableTemplate;I)Lscala/Tuple2;;
const #291 = NameAndType	#288:#290;//  splitAt:(Lscala/collection/generic/TraversableTemplate;I)Lscala/Tuple2;
const #292 = Method	#28.#291;	//  scala/collection/generic/TraversableTemplate$class.splitAt:(Lscala/collection/generic/TraversableTemplate;I)Lscala/Tuple2;
const #293 = Asciz	n;
const #294 = Asciz	span;
const #295 = Asciz	(Lscala/Function1;)Lscala/Tuple2;;
const #296 = Asciz	(Lscala/collection/generic/TraversableTemplate;Lscala/Function1;)Lscala/Tuple2;;
const #297 = NameAndType	#294:#296;//  span:(Lscala/collection/generic/TraversableTemplate;Lscala/Function1;)Lscala/Tuple2;
const #298 = Method	#28.#297;	//  scala/collection/generic/TraversableTemplate$class.span:(Lscala/collection/generic/TraversableTemplate;Lscala/Function1;)Lscala/Tuple2;
const #299 = Asciz	p;
const #300 = Asciz	dropWhile;
const #301 = Asciz	(Lscala/Function1;)Lscala/collection/generic/TraversableTemplate;;
const #302 = Asciz	(Lscala/collection/generic/TraversableTemplate;Lscala/Function1;)Lscala/collection/generic/TraversableTemplate;;
const #303 = NameAndType	#300:#302;//  dropWhile:(Lscala/collection/generic/TraversableTemplate;Lscala/Function1;)Lscala/collection/generic/TraversableTemplate;
const #304 = Method	#28.#303;	//  scala/collection/generic/TraversableTemplate$class.dropWhile:(Lscala/collection/generic/TraversableTemplate;Lscala/Function1;)Lscala/collection/generic/TraversableTemplate;
const #305 = Asciz	takeWhile;
const #306 = NameAndType	#305:#302;//  takeWhile:(Lscala/collection/generic/TraversableTemplate;Lscala/Function1;)Lscala/collection/generic/TraversableTemplate;
const #307 = Method	#28.#306;	//  scala/collection/generic/TraversableTemplate$class.takeWhile:(Lscala/collection/generic/TraversableTemplate;Lscala/Function1;)Lscala/collection/generic/TraversableTemplate;
const #308 = Asciz	slice;
const #309 = Asciz	(II)Lscala/collection/generic/TraversableTemplate;;
const #310 = Asciz	(Lscala/collection/generic/TraversableTemplate;II)Lscala/collection/generic/TraversableTemplate;;
const #311 = NameAndType	#308:#310;//  slice:(Lscala/collection/generic/TraversableTemplate;II)Lscala/collection/generic/TraversableTemplate;
const #312 = Method	#28.#311;	//  scala/collection/generic/TraversableTemplate$class.slice:(Lscala/collection/generic/TraversableTemplate;II)Lscala/collection/generic/TraversableTemplate;
const #313 = Asciz	drop;
const #314 = Asciz	(I)Lscala/collection/generic/TraversableTemplate;;
const #315 = Asciz	(Lscala/collection/generic/TraversableTemplate;I)Lscala/collection/generic/TraversableTemplate;;
const #316 = NameAndType	#313:#315;//  drop:(Lscala/collection/generic/TraversableTemplate;I)Lscala/collection/generic/TraversableTemplate;
const #317 = Method	#28.#316;	//  scala/collection/generic/TraversableTemplate$class.drop:(Lscala/collection/generic/TraversableTemplate;I)Lscala/collection/generic/TraversableTemplate;
const #318 = Asciz	take;
const #319 = NameAndType	#318:#315;//  take:(Lscala/collection/generic/TraversableTemplate;I)Lscala/collection/generic/TraversableTemplate;
const #320 = Method	#28.#319;	//  scala/collection/generic/TraversableTemplate$class.take:(Lscala/collection/generic/TraversableTemplate;I)Lscala/collection/generic/TraversableTemplate;
const #321 = Asciz	init;
const #322 = Asciz	(Lscala/collection/generic/TraversableTemplate;)Lscala/collection/generic/TraversableTemplate;;
const #323 = NameAndType	#321:#322;//  init:(Lscala/collection/generic/TraversableTemplate;)Lscala/collection/generic/TraversableTemplate;
const #324 = Method	#28.#323;	//  scala/collection/generic/TraversableTemplate$class.init:(Lscala/collection/generic/TraversableTemplate;)Lscala/collection/generic/TraversableTemplate;
const #325 = Asciz	lastOption;
const #326 = Asciz	()Lscala/Option;;
const #327 = Asciz	(Lscala/collection/generic/TraversableTemplate;)Lscala/Option;;
const #328 = NameAndType	#325:#327;//  lastOption:(Lscala/collection/generic/TraversableTemplate;)Lscala/Option;
const #329 = Method	#28.#328;	//  scala/collection/generic/TraversableTemplate$class.lastOption:(Lscala/collection/generic/TraversableTemplate;)Lscala/Option;
const #330 = Asciz	last;
const #331 = Asciz	()Ljava/lang/Object;;
const #332 = Asciz	(Lscala/collection/generic/TraversableTemplate;)Ljava/lang/Object;;
const #333 = NameAndType	#330:#332;//  last:(Lscala/collection/generic/TraversableTemplate;)Ljava/lang/Object;
const #334 = Method	#28.#333;	//  scala/collection/generic/TraversableTemplate$class.last:(Lscala/collection/generic/TraversableTemplate;)Ljava/lang/Object;
const #335 = Asciz	tail;
const #336 = NameAndType	#335:#322;//  tail:(Lscala/collection/generic/TraversableTemplate;)Lscala/collection/generic/TraversableTemplate;
const #337 = Method	#28.#336;	//  scala/collection/generic/TraversableTemplate$class.tail:(Lscala/collection/generic/TraversableTemplate;)Lscala/collection/generic/TraversableTemplate;
const #338 = Asciz	headOption;
const #339 = NameAndType	#338:#327;//  headOption:(Lscala/collection/generic/TraversableTemplate;)Lscala/Option;
const #340 = Method	#28.#339;	//  scala/collection/generic/TraversableTemplate$class.headOption:(Lscala/collection/generic/TraversableTemplate;)Lscala/Option;
const #341 = Asciz	reduceRightOption;
const #342 = Asciz	(Lscala/Function2;)Lscala/Option;;
const #343 = Asciz	(Lscala/collection/generic/TraversableTemplate;Lscala/Function2;)Lscala/Option;;
const #344 = NameAndType	#341:#343;//  reduceRightOption:(Lscala/collection/generic/TraversableTemplate;Lscala/Function2;)Lscala/Option;
const #345 = Method	#28.#344;	//  scala/collection/generic/TraversableTemplate$class.reduceRightOption:(Lscala/collection/generic/TraversableTemplate;Lscala/Function2;)Lscala/Option;
const #346 = Asciz	op;
const #347 = Asciz	Lscala/Function2;;
const #348 = Asciz	reduceLeftOption;
const #349 = NameAndType	#348:#343;//  reduceLeftOption:(Lscala/collection/generic/TraversableTemplate;Lscala/Function2;)Lscala/Option;
const #350 = Method	#28.#349;	//  scala/collection/generic/TraversableTemplate$class.reduceLeftOption:(Lscala/collection/generic/TraversableTemplate;Lscala/Function2;)Lscala/Option;
const #351 = Asciz	reduceLeft;
const #352 = Asciz	(Lscala/Function2;)Ljava/lang/Object;;
const #353 = Asciz	(Lscala/collection/generic/TraversableTemplate;Lscala/Function2;)Ljava/lang/Object;;
const #354 = NameAndType	#351:#353;//  reduceLeft:(Lscala/collection/generic/TraversableTemplate;Lscala/Function2;)Ljava/lang/Object;
const #355 = Method	#28.#354;	//  scala/collection/generic/TraversableTemplate$class.reduceLeft:(Lscala/collection/generic/TraversableTemplate;Lscala/Function2;)Ljava/lang/Object;
const #356 = Asciz	$colon$bslash;
const #357 = Asciz	(Ljava/lang/Object;Lscala/Function2;)Ljava/lang/Object;;
const #358 = Asciz	(Lscala/collection/generic/TraversableTemplate;Ljava/lang/Object;Lscala/Function2;)Ljava/lang/Object;;
const #359 = NameAndType	#356:#358;//  $colon$bslash:(Lscala/collection/generic/TraversableTemplate;Ljava/lang/Object;Lscala/Function2;)Ljava/lang/Object;
const #360 = Method	#28.#359;	//  scala/collection/generic/TraversableTemplate$class.$colon$bslash:(Lscala/collection/generic/TraversableTemplate;Ljava/lang/Object;Lscala/Function2;)Ljava/lang/Object;
const #361 = Asciz	z;
const #362 = Asciz	$div$colon;
const #363 = NameAndType	#362:#358;//  $div$colon:(Lscala/collection/generic/TraversableTemplate;Ljava/lang/Object;Lscala/Function2;)Ljava/lang/Object;
const #364 = Method	#28.#363;	//  scala/collection/generic/TraversableTemplate$class.$div$colon:(Lscala/collection/generic/TraversableTemplate;Ljava/lang/Object;Lscala/Function2;)Ljava/lang/Object;
const #365 = Asciz	foldLeft;
const #366 = NameAndType	#365:#358;//  foldLeft:(Lscala/collection/generic/TraversableTemplate;Ljava/lang/Object;Lscala/Function2;)Ljava/lang/Object;
const #367 = Method	#28.#366;	//  scala/collection/generic/TraversableTemplate$class.foldLeft:(Lscala/collection/generic/TraversableTemplate;Ljava/lang/Object;Lscala/Function2;)Ljava/lang/Object;
const #368 = Asciz	find;
const #369 = Asciz	(Lscala/Function1;)Lscala/Option;;
const #370 = Asciz	(Lscala/collection/generic/TraversableTemplate;Lscala/Function1;)Lscala/Option;;
const #371 = NameAndType	#368:#370;//  find:(Lscala/collection/generic/TraversableTemplate;Lscala/Function1;)Lscala/Option;
const #372 = Method	#28.#371;	//  scala/collection/generic/TraversableTemplate$class.find:(Lscala/collection/generic/TraversableTemplate;Lscala/Function1;)Lscala/Option;
const #373 = Asciz	count;
const #374 = Asciz	(Lscala/Function1;)I;
const #375 = Asciz	(Lscala/collection/generic/TraversableTemplate;Lscala/Function1;)I;
const #376 = NameAndType	#373:#375;//  count:(Lscala/collection/generic/TraversableTemplate;Lscala/Function1;)I
const #377 = Method	#28.#376;	//  scala/collection/generic/TraversableTemplate$class.count:(Lscala/collection/generic/TraversableTemplate;Lscala/Function1;)I
const #378 = Asciz	exists;
const #379 = Asciz	(Lscala/Function1;)Z;
const #380 = Asciz	(Lscala/collection/generic/TraversableTemplate;Lscala/Function1;)Z;
const #381 = NameAndType	#378:#380;//  exists:(Lscala/collection/generic/TraversableTemplate;Lscala/Function1;)Z
const #382 = Method	#28.#381;	//  scala/collection/generic/TraversableTemplate$class.exists:(Lscala/collection/generic/TraversableTemplate;Lscala/Function1;)Z
const #383 = Asciz	forall;
const #384 = NameAndType	#383:#380;//  forall:(Lscala/collection/generic/TraversableTemplate;Lscala/Function1;)Z
const #385 = Method	#28.#384;	//  scala/collection/generic/TraversableTemplate$class.forall:(Lscala/collection/generic/TraversableTemplate;Lscala/Function1;)Z
const #386 = Asciz	groupBy;
const #387 = Asciz	(Lscala/Function1;)Lscala/collection/Map;;
const #388 = Asciz	(Lscala/collection/generic/TraversableTemplate;Lscala/Function1;)Lscala/collection/Map;;
const #389 = NameAndType	#386:#388;//  groupBy:(Lscala/collection/generic/TraversableTemplate;Lscala/Function1;)Lscala/collection/Map;
const #390 = Method	#28.#389;	//  scala/collection/generic/TraversableTemplate$class.groupBy:(Lscala/collection/generic/TraversableTemplate;Lscala/Function1;)Lscala/collection/Map;
const #391 = Asciz	f;
const #392 = Asciz	partition;
const #393 = NameAndType	#392:#296;//  partition:(Lscala/collection/generic/TraversableTemplate;Lscala/Function1;)Lscala/Tuple2;
const #394 = Method	#28.#393;	//  scala/collection/generic/TraversableTemplate$class.partition:(Lscala/collection/generic/TraversableTemplate;Lscala/Function1;)Lscala/Tuple2;
const #395 = Asciz	remove;
const #396 = NameAndType	#395:#302;//  remove:(Lscala/collection/generic/TraversableTemplate;Lscala/Function1;)Lscala/collection/generic/TraversableTemplate;
const #397 = Method	#28.#396;	//  scala/collection/generic/TraversableTemplate$class.remove:(Lscala/collection/generic/TraversableTemplate;Lscala/Function1;)Lscala/collection/generic/TraversableTemplate;
const #398 = Asciz	filterNot;
const #399 = NameAndType	#398:#302;//  filterNot:(Lscala/collection/generic/TraversableTemplate;Lscala/Function1;)Lscala/collection/generic/TraversableTemplate;
const #400 = Method	#28.#399;	//  scala/collection/generic/TraversableTemplate$class.filterNot:(Lscala/collection/generic/TraversableTemplate;Lscala/Function1;)Lscala/collection/generic/TraversableTemplate;
const #401 = Asciz	filterMap;
const #402 = Asciz	(Lscala/PartialFunction;Lscala/collection/generic/BuilderFactory;)Ljava/lang/Object;;
const #403 = Asciz	(Lscala/collection/generic/TraversableTemplate;Lscala/PartialFunction;Lscala/collection/generic/BuilderFactory;)Ljava/lang/Object;;
const #404 = NameAndType	#401:#403;//  filterMap:(Lscala/collection/generic/TraversableTemplate;Lscala/PartialFunction;Lscala/collection/generic/BuilderFactory;)Ljava/lang/Object;
const #405 = Method	#28.#404;	//  scala/collection/generic/TraversableTemplate$class.filterMap:(Lscala/collection/generic/TraversableTemplate;Lscala/PartialFunction;Lscala/collection/generic/BuilderFactory;)Ljava/lang/Object;
const #406 = Asciz	pf;
const #407 = Asciz	Lscala/PartialFunction;;
const #408 = Asciz	bf;
const #409 = Asciz	Lscala/collection/generic/BuilderFactory;;
const #410 = Asciz	filter;
const #411 = NameAndType	#410:#302;//  filter:(Lscala/collection/generic/TraversableTemplate;Lscala/Function1;)Lscala/collection/generic/TraversableTemplate;
const #412 = Method	#28.#411;	//  scala/collection/generic/TraversableTemplate$class.filter:(Lscala/collection/generic/TraversableTemplate;Lscala/Function1;)Lscala/collection/generic/TraversableTemplate;
const #413 = Asciz	flatMap;
const #414 = Asciz	(Lscala/Function1;Lscala/collection/generic/BuilderFactory;)Ljava/lang/Object;;
const #415 = Asciz	(Lscala/collection/generic/TraversableTemplate;Lscala/Function1;Lscala/collection/generic/BuilderFactory;)Ljava/lang/Object;;
const #416 = NameAndType	#413:#415;//  flatMap:(Lscala/collection/generic/TraversableTemplate;Lscala/Function1;Lscala/collection/generic/BuilderFactory;)Ljava/lang/Object;
const #417 = Method	#28.#416;	//  scala/collection/generic/TraversableTemplate$class.flatMap:(Lscala/collection/generic/TraversableTemplate;Lscala/Function1;Lscala/collection/generic/BuilderFactory;)Ljava/lang/Object;
const #418 = NameAndType	#198:#415;//  map:(Lscala/collection/generic/TraversableTemplate;Lscala/Function1;Lscala/collection/generic/BuilderFactory;)Ljava/lang/Object;
const #419 = Method	#28.#418;	//  scala/collection/generic/TraversableTemplate$class.map:(Lscala/collection/generic/TraversableTemplate;Lscala/Function1;Lscala/collection/generic/BuilderFactory;)Ljava/lang/Object;
const #420 = Asciz	(Lscala/collection/Iterator;Lscala/collection/generic/BuilderFactory;)Ljava/lang/Object;;
const #421 = Asciz	(Lscala/collection/generic/TraversableTemplate;Lscala/collection/Iterator;Lscala/collection/generic/BuilderFactory;)Ljava/lang/Object;;
const #422 = NameAndType	#174:#421;//  $plus$plus:(Lscala/collection/generic/TraversableTemplate;Lscala/collection/Iterator;Lscala/collection/generic/BuilderFactory;)Ljava/lang/Object;
const #423 = Method	#28.#422;	//  scala/collection/generic/TraversableTemplate$class.$plus$plus:(Lscala/collection/generic/TraversableTemplate;Lscala/collection/Iterator;Lscala/collection/generic/BuilderFactory;)Ljava/lang/Object;
const #424 = Asciz	that;
const #425 = Asciz	Lscala/collection/Iterator;;
const #426 = Asciz	(Lscala/collection/Traversable;Lscala/collection/generic/BuilderFactory;)Ljava/lang/Object;;
const #427 = Asciz	(Lscala/collection/generic/TraversableTemplate;Lscala/collection/Traversable;Lscala/collection/generic/BuilderFactory;)Ljava/lang/Object;;
const #428 = NameAndType	#174:#427;//  $plus$plus:(Lscala/collection/generic/TraversableTemplate;Lscala/collection/Traversable;Lscala/collection/generic/BuilderFactory;)Ljava/lang/Object;
const #429 = Method	#28.#428;	//  scala/collection/generic/TraversableTemplate$class.$plus$plus:(Lscala/collection/generic/TraversableTemplate;Lscala/collection/Traversable;Lscala/collection/generic/BuilderFactory;)Ljava/lang/Object;
const #430 = Asciz	Lscala/collection/Traversable;;
const #431 = Asciz	hasDefiniteSize;
const #432 = Asciz	()Z;
const #433 = Asciz	(Lscala/collection/generic/TraversableTemplate;)Z;
const #434 = NameAndType	#431:#433;//  hasDefiniteSize:(Lscala/collection/generic/TraversableTemplate;)Z
const #435 = Method	#28.#434;	//  scala/collection/generic/TraversableTemplate$class.hasDefiniteSize:(Lscala/collection/generic/TraversableTemplate;)Z
const #436 = Asciz	nonEmpty;
const #437 = NameAndType	#436:#433;//  nonEmpty:(Lscala/collection/generic/TraversableTemplate;)Z
const #438 = Method	#28.#437;	//  scala/collection/generic/TraversableTemplate$class.nonEmpty:(Lscala/collection/generic/TraversableTemplate;)Z
const #439 = NameAndType	#125:#322;//  thisCollection:(Lscala/collection/generic/TraversableTemplate;)Lscala/collection/generic/TraversableTemplate;
const #440 = Method	#28.#439;	//  scala/collection/generic/TraversableTemplate$class.thisCollection:(Lscala/collection/generic/TraversableTemplate;)Lscala/collection/generic/TraversableTemplate;
const #441 = Asciz	transpose;
const #442 = Asciz	(Lscala/Function1;)Lscala/collection/Traversable;;
const #443 = Asciz	(Lscala/collection/generic/TraversableClass;Lscala/Function1;)Lscala/collection/Traversable;;
const #444 = NameAndType	#441:#443;//  transpose:(Lscala/collection/generic/TraversableClass;Lscala/Function1;)Lscala/collection/Traversable;
const #445 = Method	#33.#444;	//  scala/collection/generic/TraversableClass$class.transpose:(Lscala/collection/generic/TraversableClass;Lscala/Function1;)Lscala/collection/Traversable;
const #446 = Asciz	toTraversable;
const #447 = Asciz	flatten;
const #448 = NameAndType	#447:#443;//  flatten:(Lscala/collection/generic/TraversableClass;Lscala/Function1;)Lscala/collection/Traversable;
const #449 = Method	#33.#448;	//  scala/collection/generic/TraversableClass$class.flatten:(Lscala/collection/generic/TraversableClass;Lscala/Function1;)Lscala/collection/Traversable;
const #450 = Asciz	unzip;
const #451 = Asciz	(Lscala/collection/generic/TraversableClass;Lscala/Function1;)Lscala/Tuple2;;
const #452 = NameAndType	#450:#451;//  unzip:(Lscala/collection/generic/TraversableClass;Lscala/Function1;)Lscala/Tuple2;
const #453 = Method	#33.#452;	//  scala/collection/generic/TraversableClass$class.unzip:(Lscala/collection/generic/TraversableClass;Lscala/Function1;)Lscala/Tuple2;
const #454 = Asciz	toPair;
const #455 = Asciz	genericBuilder;
const #456 = Asciz	()Lscala/collection/generic/Builder;;
const #457 = Asciz	(Lscala/collection/generic/TraversableClass;)Lscala/collection/generic/Builder;;
const #458 = NameAndType	#455:#457;//  genericBuilder:(Lscala/collection/generic/TraversableClass;)Lscala/collection/generic/Builder;
const #459 = Method	#33.#458;	//  scala/collection/generic/TraversableClass$class.genericBuilder:(Lscala/collection/generic/TraversableClass;)Lscala/collection/generic/Builder;
const #460 = Asciz	projection;
const #461 = Asciz	(Lscala/collection/generic/IterableTemplate;)Ljava/lang/Object;;
const #462 = NameAndType	#460:#461;//  projection:(Lscala/collection/generic/IterableTemplate;)Ljava/lang/Object;
const #463 = Method	#43.#462;	//  scala/collection/generic/IterableTemplate$class.projection:(Lscala/collection/generic/IterableTemplate;)Ljava/lang/Object;
const #464 = Asciz	toSeq;
const #465 = Asciz	(Lscala/collection/generic/IterableTemplate;)Lscala/collection/Sequence;;
const #466 = NameAndType	#464:#465;//  toSeq:(Lscala/collection/generic/IterableTemplate;)Lscala/collection/Sequence;
const #467 = Method	#43.#466;	//  scala/collection/generic/IterableTemplate$class.toSeq:(Lscala/collection/generic/IterableTemplate;)Lscala/collection/Sequence;
const #468 = Asciz	firstOption;
const #469 = Asciz	(Lscala/collection/generic/IterableTemplate;)Lscala/Option;;
const #470 = NameAndType	#468:#469;//  firstOption:(Lscala/collection/generic/IterableTemplate;)Lscala/Option;
const #471 = Method	#43.#470;	//  scala/collection/generic/IterableTemplate$class.firstOption:(Lscala/collection/generic/IterableTemplate;)Lscala/Option;
const #472 = Asciz	first;
const #473 = NameAndType	#472:#461;//  first:(Lscala/collection/generic/IterableTemplate;)Ljava/lang/Object;
const #474 = Method	#43.#473;	//  scala/collection/generic/IterableTemplate$class.first:(Lscala/collection/generic/IterableTemplate;)Ljava/lang/Object;
const #475 = Asciz	(Lscala/collection/generic/IterableTemplate;II)Lscala/collection/generic/IterableView;;
const #476 = NameAndType	#115:#475;//  view:(Lscala/collection/generic/IterableTemplate;II)Lscala/collection/generic/IterableView;
const #477 = Method	#43.#476;	//  scala/collection/generic/IterableTemplate$class.view:(Lscala/collection/generic/IterableTemplate;II)Lscala/collection/generic/IterableView;
const #478 = NameAndType	#115:#461;//  view:(Lscala/collection/generic/IterableTemplate;)Ljava/lang/Object;
const #479 = Method	#43.#478;	//  scala/collection/generic/IterableTemplate$class.view:(Lscala/collection/generic/IterableTemplate;)Ljava/lang/Object;
const #480 = Asciz	toStream;
const #481 = Asciz	()Lscala/collection/immutable/Stream;;
const #482 = Asciz	(Lscala/collection/generic/IterableTemplate;)Lscala/collection/immutable/Stream;;
const #483 = NameAndType	#480:#482;//  toStream:(Lscala/collection/generic/IterableTemplate;)Lscala/collection/immutable/Stream;
const #484 = Method	#43.#483;	//  scala/collection/generic/IterableTemplate$class.toStream:(Lscala/collection/generic/IterableTemplate;)Lscala/collection/immutable/Stream;
const #485 = Asciz	sameElements;
const #486 = Asciz	(Lscala/collection/Iterable;)Z;
const #487 = Asciz	(Lscala/collection/generic/IterableTemplate;Lscala/collection/Iterable;)Z;
const #488 = NameAndType	#485:#487;//  sameElements:(Lscala/collection/generic/IterableTemplate;Lscala/collection/Iterable;)Z
const #489 = Method	#43.#488;	//  scala/collection/generic/IterableTemplate$class.sameElements:(Lscala/collection/generic/IterableTemplate;Lscala/collection/Iterable;)Z
const #490 = Asciz	Lscala/collection/Iterable;;
const #491 = Asciz	dropRight;
const #492 = Asciz	(I)Lscala/collection/generic/IterableTemplate;;
const #493 = Asciz	(Lscala/collection/generic/IterableTemplate;I)Lscala/collection/generic/IterableTemplate;;
const #494 = NameAndType	#491:#493;//  dropRight:(Lscala/collection/generic/IterableTemplate;I)Lscala/collection/generic/IterableTemplate;
const #495 = Method	#43.#494;	//  scala/collection/generic/IterableTemplate$class.dropRight:(Lscala/collection/generic/IterableTemplate;I)Lscala/collection/generic/IterableTemplate;
const #496 = Asciz	takeRight;
const #497 = NameAndType	#496:#493;//  takeRight:(Lscala/collection/generic/IterableTemplate;I)Lscala/collection/generic/IterableTemplate;
const #498 = Method	#43.#497;	//  scala/collection/generic/IterableTemplate$class.takeRight:(Lscala/collection/generic/IterableTemplate;I)Lscala/collection/generic/IterableTemplate;
const #499 = Asciz	head;
const #500 = NameAndType	#499:#461;//  head:(Lscala/collection/generic/IterableTemplate;)Ljava/lang/Object;
const #501 = Method	#43.#500;	//  scala/collection/generic/IterableTemplate$class.head:(Lscala/collection/generic/IterableTemplate;)Ljava/lang/Object;
const #502 = Asciz	toIterable;
const #503 = Asciz	()Lscala/collection/Iterable;;
const #504 = Asciz	(Lscala/collection/generic/IterableTemplate;)Lscala/collection/Iterable;;
const #505 = NameAndType	#502:#504;//  toIterable:(Lscala/collection/generic/IterableTemplate;)Lscala/collection/Iterable;
const #506 = Method	#43.#505;	//  scala/collection/generic/IterableTemplate$class.toIterable:(Lscala/collection/generic/IterableTemplate;)Lscala/collection/Iterable;
const #507 = Asciz	reduceRight;
const #508 = Asciz	(Lscala/collection/generic/IterableTemplate;Lscala/Function2;)Ljava/lang/Object;;
const #509 = NameAndType	#507:#508;//  reduceRight:(Lscala/collection/generic/IterableTemplate;Lscala/Function2;)Ljava/lang/Object;
const #510 = Method	#43.#509;	//  scala/collection/generic/IterableTemplate$class.reduceRight:(Lscala/collection/generic/IterableTemplate;Lscala/Function2;)Ljava/lang/Object;
const #511 = Asciz	foldRight;
const #512 = Asciz	(Lscala/collection/generic/IterableTemplate;Ljava/lang/Object;Lscala/Function2;)Ljava/lang/Object;;
const #513 = NameAndType	#511:#512;//  foldRight:(Lscala/collection/generic/IterableTemplate;Ljava/lang/Object;Lscala/Function2;)Ljava/lang/Object;
const #514 = Method	#43.#513;	//  scala/collection/generic/IterableTemplate$class.foldRight:(Lscala/collection/generic/IterableTemplate;Ljava/lang/Object;Lscala/Function2;)Ljava/lang/Object;
const #515 = Asciz	elements;
const #516 = Asciz	(Lscala/collection/generic/IterableTemplate;)Lscala/collection/Iterator;;
const #517 = NameAndType	#515:#516;//  elements:(Lscala/collection/generic/IterableTemplate;)Lscala/collection/Iterator;
const #518 = Method	#43.#517;	//  scala/collection/generic/IterableTemplate$class.elements:(Lscala/collection/generic/IterableTemplate;)Lscala/collection/Iterator;
const #519 = Asciz	(Lscala/collection/generic/SetClass;)Lscala/collection/Set;;
const #520 = NameAndType	#108:#519;//  empty:(Lscala/collection/generic/SetClass;)Lscala/collection/Set;
const #521 = Method	#53.#520;	//  scala/collection/generic/SetClass$class.empty:(Lscala/collection/generic/SetClass;)Lscala/collection/Set;
const #522 = Asciz	(Lscala/collection/Iterator;)Lscala/collection/generic/Addable;;
const #523 = Asciz	(Lscala/collection/generic/Addable;Lscala/collection/Iterator;)Lscala/collection/generic/Addable;;
const #524 = NameAndType	#174:#523;//  $plus$plus:(Lscala/collection/generic/Addable;Lscala/collection/Iterator;)Lscala/collection/generic/Addable;
const #525 = Method	#58.#524;	//  scala/collection/generic/Addable$class.$plus$plus:(Lscala/collection/generic/Addable;Lscala/collection/Iterator;)Lscala/collection/generic/Addable;
const #526 = Asciz	iter;
const #527 = Asciz	(Lscala/collection/generic/Addable;Lscala/collection/Traversable;)Lscala/collection/generic/Addable;;
const #528 = NameAndType	#174:#527;//  $plus$plus:(Lscala/collection/generic/Addable;Lscala/collection/Traversable;)Lscala/collection/generic/Addable;
const #529 = Method	#58.#528;	//  scala/collection/generic/Addable$class.$plus$plus:(Lscala/collection/generic/Addable;Lscala/collection/Traversable;)Lscala/collection/generic/Addable;
const #530 = Asciz	elems;
const #531 = Asciz	(Ljava/lang/Object;Ljava/lang/Object;Lscala/collection/Sequence;)Lscala/collection/generic/Addable;;
const #532 = Asciz	(Lscala/collection/generic/Addable;Ljava/lang/Object;Ljava/lang/Object;Lscala/collection/Sequence;)Lscala/collection/generic/Addable;;
const #533 = NameAndType	#82:#532;//  $plus:(Lscala/collection/generic/Addable;Ljava/lang/Object;Ljava/lang/Object;Lscala/collection/Sequence;)Lscala/collection/generic/Addable;
const #534 = Method	#58.#533;	//  scala/collection/generic/Addable$class.$plus:(Lscala/collection/generic/Addable;Ljava/lang/Object;Ljava/lang/Object;Lscala/collection/Sequence;)Lscala/collection/generic/Addable;
const #535 = Asciz	elem1;
const #536 = Asciz	elem2;
const #537 = Asciz	Lscala/collection/Sequence;;
const #538 = Asciz	$minus$minus;
const #539 = Asciz	(Lscala/collection/Iterator;)Lscala/collection/generic/Subtractable;;
const #540 = Asciz	(Lscala/collection/generic/Subtractable;Lscala/collection/Iterator;)Lscala/collection/generic/Subtractable;;
const #541 = NameAndType	#538:#540;//  $minus$minus:(Lscala/collection/generic/Subtractable;Lscala/collection/Iterator;)Lscala/collection/generic/Subtractable;
const #542 = Method	#63.#541;	//  scala/collection/generic/Subtractable$class.$minus$minus:(Lscala/collection/generic/Subtractable;Lscala/collection/Iterator;)Lscala/collection/generic/Subtractable;
const #543 = Asciz	(Lscala/collection/Traversable;)Lscala/collection/generic/Subtractable;;
const #544 = Asciz	(Lscala/collection/generic/Subtractable;Lscala/collection/Traversable;)Lscala/collection/generic/Subtractable;;
const #545 = NameAndType	#538:#544;//  $minus$minus:(Lscala/collection/generic/Subtractable;Lscala/collection/Traversable;)Lscala/collection/generic/Subtractable;
const #546 = Method	#63.#545;	//  scala/collection/generic/Subtractable$class.$minus$minus:(Lscala/collection/generic/Subtractable;Lscala/collection/Traversable;)Lscala/collection/generic/Subtractable;
const #547 = Asciz	(Ljava/lang/Object;Ljava/lang/Object;Lscala/collection/Sequence;)Lscala/collection/generic/Subtractable;;
const #548 = Asciz	(Lscala/collection/generic/Subtractable;Ljava/lang/Object;Ljava/lang/Object;Lscala/collection/Sequence;)Lscala/collection/generic/Subtractable;;
const #549 = NameAndType	#90:#548;//  $minus:(Lscala/collection/generic/Subtractable;Ljava/lang/Object;Ljava/lang/Object;Lscala/collection/Sequence;)Lscala/collection/generic/Subtractable;
const #550 = Method	#63.#549;	//  scala/collection/generic/Subtractable$class.$minus:(Lscala/collection/generic/Subtractable;Ljava/lang/Object;Ljava/lang/Object;Lscala/collection/Sequence;)Lscala/collection/generic/Subtractable;
const #551 = Asciz	toString;
const #552 = Asciz	(Lscala/collection/generic/SetTemplate;)Ljava/lang/String;;
const #553 = NameAndType	#551:#552;//  toString:(Lscala/collection/generic/SetTemplate;)Ljava/lang/String;
const #554 = Method	#68.#553;	//  scala/collection/generic/SetTemplate$class.toString:(Lscala/collection/generic/SetTemplate;)Ljava/lang/String;
const #555 = Asciz	stringPrefix;
const #556 = NameAndType	#555:#552;//  stringPrefix:(Lscala/collection/generic/SetTemplate;)Ljava/lang/String;
const #557 = Method	#68.#556;	//  scala/collection/generic/SetTemplate$class.stringPrefix:(Lscala/collection/generic/SetTemplate;)Ljava/lang/String;
const #558 = Asciz	equals;
const #559 = Asciz	(Lscala/collection/generic/SetTemplate;Ljava/lang/Object;)Z;
const #560 = NameAndType	#558:#559;//  equals:(Lscala/collection/generic/SetTemplate;Ljava/lang/Object;)Z
const #561 = Method	#68.#560;	//  scala/collection/generic/SetTemplate$class.equals:(Lscala/collection/generic/SetTemplate;Ljava/lang/Object;)Z
const #562 = Asciz	subsetOf;
const #563 = Asciz	(Lscala/collection/Set;)Z;
const #564 = Asciz	(Lscala/collection/generic/SetTemplate;Lscala/collection/Set;)Z;
const #565 = NameAndType	#562:#564;//  subsetOf:(Lscala/collection/generic/SetTemplate;Lscala/collection/Set;)Z
const #566 = Method	#68.#565;	//  scala/collection/generic/SetTemplate$class.subsetOf:(Lscala/collection/generic/SetTemplate;Lscala/collection/Set;)Z
const #567 = Asciz	Lscala/collection/Set;;
const #568 = Asciz	$amp$tilde;
const #569 = Asciz	(Lscala/collection/Set;)Lscala/collection/generic/SetTemplate;;
const #570 = Asciz	(Lscala/collection/generic/SetTemplate;Lscala/collection/Set;)Lscala/collection/generic/SetTemplate;;
const #571 = NameAndType	#568:#570;//  $amp$tilde:(Lscala/collection/generic/SetTemplate;Lscala/collection/Set;)Lscala/collection/generic/SetTemplate;
const #572 = Method	#68.#571;	//  scala/collection/generic/SetTemplate$class.$amp$tilde:(Lscala/collection/generic/SetTemplate;Lscala/collection/Set;)Lscala/collection/generic/SetTemplate;
const #573 = Asciz	diff;
const #574 = NameAndType	#573:#570;//  diff:(Lscala/collection/generic/SetTemplate;Lscala/collection/Set;)Lscala/collection/generic/SetTemplate;
const #575 = Method	#68.#574;	//  scala/collection/generic/SetTemplate$class.diff:(Lscala/collection/generic/SetTemplate;Lscala/collection/Set;)Lscala/collection/generic/SetTemplate;
const #576 = Asciz	$bar;
const #577 = NameAndType	#576:#570;//  $bar:(Lscala/collection/generic/SetTemplate;Lscala/collection/Set;)Lscala/collection/generic/SetTemplate;
const #578 = Method	#68.#577;	//  scala/collection/generic/SetTemplate$class.$bar:(Lscala/collection/generic/SetTemplate;Lscala/collection/Set;)Lscala/collection/generic/SetTemplate;
const #579 = Asciz	union;
const #580 = NameAndType	#579:#570;//  union:(Lscala/collection/generic/SetTemplate;Lscala/collection/Set;)Lscala/collection/generic/SetTemplate;
const #581 = Method	#68.#580;	//  scala/collection/generic/SetTemplate$class.union:(Lscala/collection/generic/SetTemplate;Lscala/collection/Set;)Lscala/collection/generic/SetTemplate;
const #582 = Asciz	$times$times;
const #583 = NameAndType	#582:#570;//  $times$times:(Lscala/collection/generic/SetTemplate;Lscala/collection/Set;)Lscala/collection/generic/SetTemplate;
const #584 = Method	#68.#583;	//  scala/collection/generic/SetTemplate$class.$times$times:(Lscala/collection/generic/SetTemplate;Lscala/collection/Set;)Lscala/collection/generic/SetTemplate;
const #585 = Asciz	$amp;
const #586 = NameAndType	#585:#570;//  $amp:(Lscala/collection/generic/SetTemplate;Lscala/collection/Set;)Lscala/collection/generic/SetTemplate;
const #587 = Method	#68.#586;	//  scala/collection/generic/SetTemplate$class.$amp:(Lscala/collection/generic/SetTemplate;Lscala/collection/Set;)Lscala/collection/generic/SetTemplate;
const #588 = Asciz	intersect;
const #589 = NameAndType	#588:#570;//  intersect:(Lscala/collection/generic/SetTemplate;Lscala/collection/Set;)Lscala/collection/generic/SetTemplate;
const #590 = Method	#68.#589;	//  scala/collection/generic/SetTemplate$class.intersect:(Lscala/collection/generic/SetTemplate;Lscala/collection/Set;)Lscala/collection/generic/SetTemplate;
const #591 = NameAndType	#94:#559;//  apply:(Lscala/collection/generic/SetTemplate;Ljava/lang/Object;)Z
const #592 = Method	#68.#591;	//  scala/collection/generic/SetTemplate$class.apply:(Lscala/collection/generic/SetTemplate;Ljava/lang/Object;)Z
const #593 = Asciz	isEmpty;
const #594 = Asciz	(Lscala/collection/generic/SetTemplate;)Z;
const #595 = NameAndType	#593:#594;//  isEmpty:(Lscala/collection/generic/SetTemplate;)Z
const #596 = Method	#68.#595;	//  scala/collection/generic/SetTemplate$class.isEmpty:(Lscala/collection/generic/SetTemplate;)Z
const #597 = Asciz	newBuilder;
const #598 = Asciz	(Lscala/collection/generic/SetTemplate;)Lscala/collection/generic/Builder;;
const #599 = NameAndType	#597:#598;//  newBuilder:(Lscala/collection/generic/SetTemplate;)Lscala/collection/generic/Builder;
const #600 = Method	#68.#599;	//  scala/collection/generic/SetTemplate$class.newBuilder:(Lscala/collection/generic/SetTemplate;)Lscala/collection/generic/Builder;
const #601 = Asciz	companion;
const #602 = Asciz	()Lscala/collection/generic/Companion;;
const #603 = Asciz	(Lscala/collection/Set;)Lscala/collection/generic/Companion;;
const #604 = NameAndType	#601:#603;//  companion:(Lscala/collection/Set;)Lscala/collection/generic/Companion;
const #605 = Method	#73.#604;	//  scala/collection/Set$class.companion:(Lscala/collection/Set;)Lscala/collection/generic/Companion;
const #606 = Asciz	Ljava/lang/Object;Lscala/collection/Set<TA;>;Lscala/ScalaObject;;
const #607 = Asciz	Scala;
const #608 = Asciz	InnerClasses;
const #609 = Asciz	DefaultKeySet;
const #610 = Asciz	$anonfun$foreach$1;
const #611 = Asciz	$anonfun$iterator$1;
const #612 = Asciz	scala/ScalaObject;
const #613 = class	#612;	//  scala/ScalaObject

{
public final scala.collection.generic.MapTemplate $outer;

public scala.collection.generic.MapTemplate$DefaultKeySet(scala.collection.generic.MapTemplate);
  Code:
   Stack=2, Locals=2, Args_size=2
   0:	aload_1
   1:	ifnonnull	12
   4:	new	#10; //class java/lang/NullPointerException
   7:	dup
   8:	invokespecial	#13; //Method java/lang/NullPointerException."<init>":()V
   11:	athrow
   12:	aload_0
   13:	aload_1
   14:	putfield	#17; //Field $outer:Lscala/collection/generic/MapTemplate;
   17:	aload_0
   18:	invokespecial	#20; //Method java/lang/Object."<init>":()V
   21:	aload_0
   22:	invokestatic	#26; //Method scala/Function1$class.$init$:(Lscala/Function1;)V
   25:	aload_0
   26:	invokestatic	#31; //Method scala/collection/generic/TraversableTemplate$class.$init$:(Lscala/collection/generic/TraversableTemplate;)V
   29:	aload_0
   30:	invokestatic	#36; //Method scala/collection/generic/TraversableClass$class.$init$:(Lscala/collection/generic/TraversableClass;)V
   33:	aload_0
   34:	invokestatic	#41; //Method scala/collection/Traversable$class.$init$:(Lscala/collection/Traversable;)V
   37:	aload_0
   38:	invokestatic	#46; //Method scala/collection/generic/IterableTemplate$class.$init$:(Lscala/collection/generic/IterableTemplate;)V
   41:	aload_0
   42:	invokestatic	#51; //Method scala/collection/Iterable$class.$init$:(Lscala/collection/Iterable;)V
   45:	aload_0
   46:	invokestatic	#56; //Method scala/collection/generic/SetClass$class.$init$:(Lscala/collection/generic/SetClass;)V
   49:	aload_0
   50:	invokestatic	#61; //Method scala/collection/generic/Addable$class.$init$:(Lscala/collection/generic/Addable;)V
   53:	aload_0
   54:	invokestatic	#66; //Method scala/collection/generic/Subtractable$class.$init$:(Lscala/collection/generic/Subtractable;)V
   57:	aload_0
   58:	invokestatic	#71; //Method scala/collection/generic/SetTemplate$class.$init$:(Lscala/collection/generic/SetTemplate;)V
   61:	aload_0
   62:	invokestatic	#76; //Method scala/collection/Set$class.$init$:(Lscala/collection/Set;)V
   65:	return
  LineNumberTable: 
   line 127: 0

  LocalVariableTable: 
   Start  Length  Slot  Name   Signature
   0      66      0    this       Lscala/collection/generic/MapTemplate$DefaultKeySet;
   0      66      1    $outer       Lscala/collection/generic/MapTemplate;

  Signature: length = 0x2
   00 50 

public scala.collection.generic.SetTemplate $plus(java.lang.Object);
  Code:
   Stack=2, Locals=2, Args_size=2
   0:	aload_0
   1:	aload_1
   2:	invokevirtual	#86; //Method $plus:(Ljava/lang/Object;)Lscala/collection/Set;
   5:	areturn
  LineNumberTable: 
   line 127: 0

  LocalVariableTable: 
   Start  Length  Slot  Name   Signature
   0      6      0    this       Lscala/collection/generic/MapTemplate$DefaultKeySet;
   0      6      1    elem       Ljava/lang/Object;


public scala.collection.generic.Addable $plus(java.lang.Object);
  Code:
   Stack=2, Locals=2, Args_size=2
   0:	aload_0
   1:	aload_1
   2:	invokevirtual	#86; //Method $plus:(Ljava/lang/Object;)Lscala/collection/Set;
   5:	areturn
  LineNumberTable: 
   line 127: 0

  LocalVariableTable: 
   Start  Length  Slot  Name   Signature
   0      6      0    this       Lscala/collection/generic/MapTemplate$DefaultKeySet;
   0      6      1    elem       Ljava/lang/Object;


public scala.collection.generic.SetTemplate $minus(java.lang.Object);
  Code:
   Stack=2, Locals=2, Args_size=2
   0:	aload_0
   1:	aload_1
   2:	invokevirtual	#92; //Method $minus:(Ljava/lang/Object;)Lscala/collection/Set;
   5:	areturn
  LineNumberTable: 
   line 127: 0

  LocalVariableTable: 
   Start  Length  Slot  Name   Signature
   0      6      0    this       Lscala/collection/generic/MapTemplate$DefaultKeySet;
   0      6      1    elem       Ljava/lang/Object;


public scala.collection.generic.Subtractable $minus(java.lang.Object);
  Code:
   Stack=2, Locals=2, Args_size=2
   0:	aload_0
   1:	aload_1
   2:	invokevirtual	#92; //Method $minus:(Ljava/lang/Object;)Lscala/collection/Set;
   5:	areturn
  LineNumberTable: 
   line 127: 0

  LocalVariableTable: 
   Start  Length  Slot  Name   Signature
   0      6      0    this       Lscala/collection/generic/MapTemplate$DefaultKeySet;
   0      6      1    elem       Ljava/lang/Object;


public java.lang.Object apply(java.lang.Object);
  Code:
   Stack=2, Locals=2, Args_size=2
   0:	aload_0
   1:	aload_1
   2:	invokeinterface	#100,  2; //InterfaceMethod scala/collection/generic/SetTemplate.apply:(Ljava/lang/Object;)Z
   7:	invokestatic	#106; //Method scala/runtime/BoxesRunTime.boxToBoolean:(Z)Ljava/lang/Boolean;
   10:	areturn
  LineNumberTable: 
   line 127: 0

  LocalVariableTable: 
   Start  Length  Slot  Name   Signature
   0      11      0    this       Lscala/collection/generic/MapTemplate$DefaultKeySet;
   0      11      1    v1       Ljava/lang/Object;


public scala.collection.generic.SetTemplate empty();
  Code:
   Stack=1, Locals=1, Args_size=1
   0:	aload_0
   1:	invokeinterface	#114,  1; //InterfaceMethod scala/collection/generic/SetClass.empty:()Lscala/collection/Set;
   6:	areturn
  LineNumberTable: 
   line 127: 0


public scala.collection.generic.TraversableView view(int, int);
  Code:
   Stack=3, Locals=3, Args_size=3
   0:	aload_0
   1:	iload_1
   2:	iload_2
   3:	invokeinterface	#121,  3; //InterfaceMethod scala/collection/generic/IterableTemplate.view:(II)Lscala/collection/generic/IterableView;
   8:	areturn
  LineNumberTable: 
   line 127: 0

  LocalVariableTable: 
   Start  Length  Slot  Name   Signature
   0      9      0    this       Lscala/collection/generic/MapTemplate$DefaultKeySet;
   0      9      1    from       I
   0      9      2    until       I


public scala.collection.generic.Subtractable thisCollection();
  Code:
   Stack=1, Locals=1, Args_size=1
   0:	aload_0
   1:	invokeinterface	#131,  1; //InterfaceMethod scala/collection/generic/TraversableTemplate.thisCollection:()Lscala/collection/generic/TraversableTemplate;
   6:	checkcast	#133; //class scala/collection/generic/Subtractable
   9:	areturn
  LineNumberTable: 
   line 127: 0


public scala.collection.generic.Addable thisCollection();
  Code:
   Stack=1, Locals=1, Args_size=1
   0:	aload_0
   1:	invokeinterface	#131,  1; //InterfaceMethod scala/collection/generic/TraversableTemplate.thisCollection:()Lscala/collection/generic/TraversableTemplate;
   6:	checkcast	#136; //class scala/collection/generic/Addable
   9:	areturn
  LineNumberTable: 
   line 127: 0


public scala.collection.generic.MapTemplate scala$collection$generic$MapTemplate$DefaultKeySet$$$outer();
  Code:
   Stack=1, Locals=1, Args_size=1
   0:	aload_0
   1:	getfield	#17; //Field $outer:Lscala/collection/generic/MapTemplate;
   4:	areturn
  LineNumberTable: 
   line 127: 0


public void foreach(scala.Function1);
  Code:
   Stack=5, Locals=2, Args_size=2
   0:	aload_0
   1:	invokevirtual	#141; //Method scala$collection$generic$MapTemplate$DefaultKeySet$$$outer:()Lscala/collection/generic/MapTemplate;
   4:	new	#143; //class scala/collection/generic/MapTemplate$DefaultKeySet$$anonfun$foreach$1
   7:	dup
   8:	aload_0
   9:	aload_1
   10:	invokespecial	#146; //Method scala/collection/generic/MapTemplate$DefaultKeySet$$anonfun$foreach$1."<init>":(Lscala/collection/generic/MapTemplate$DefaultKeySet;Lscala/Function1;)V
   13:	invokeinterface	#148,  2; //InterfaceMethod scala/collection/generic/IterableTemplate.foreach:(Lscala/Function1;)V
   18:	return
  LineNumberTable: 
   line 133: 0

  LocalVariableTable: 
   Start  Length  Slot  Name   Signature
   0      19      0    this       Lscala/collection/generic/MapTemplate$DefaultKeySet;
   0      19      1    f$1       Lscala/Function1;

  Signature: length = 0x2
   00 FFFFFF97 

public int size();
  Code:
   Stack=1, Locals=1, Args_size=1
   0:	aload_0
   1:	invokevirtual	#141; //Method scala$collection$generic$MapTemplate$DefaultKeySet$$$outer:()Lscala/collection/generic/MapTemplate;
   4:	invokeinterface	#155,  1; //InterfaceMethod scala/collection/generic/TraversableTemplate.size:()I
   9:	ireturn
  LineNumberTable: 
   line 132: 0


public scala.collection.Set $minus(java.lang.Object);
  Code:
   Stack=3, Locals=2, Args_size=2
   0:	getstatic	#161; //Field scala/collection/Set$.MODULE$:Lscala/collection/Set$;
   3:	getstatic	#166; //Field scala/runtime/ScalaRunTime$.MODULE$:Lscala/runtime/ScalaRunTime$;
   6:	iconst_0
   7:	anewarray	#19; //class java/lang/Object
   10:	invokevirtual	#170; //Method scala/runtime/ScalaRunTime$.boxArray:(Ljava/lang/Object;)Lscala/runtime/BoxedArray;
   13:	invokevirtual	#173; //Method scala/collection/Set$.apply:(Lscala/collection/Sequence;)Lscala/collection/Traversable;
   16:	checkcast	#136; //class scala/collection/generic/Addable
   19:	aload_0
   20:	invokeinterface	#177,  2; //InterfaceMethod scala/collection/generic/Addable.$plus$plus:(Lscala/collection/Traversable;)Lscala/collection/generic/Addable;
   25:	checkcast	#97; //class scala/collection/generic/SetTemplate
   28:	aload_1
   29:	invokeinterface	#179,  2; //InterfaceMethod scala/collection/generic/SetTemplate.$minus:(Ljava/lang/Object;)Lscala/collection/generic/SetTemplate;
   34:	checkcast	#181; //class scala/collection/Set
   37:	areturn
  LineNumberTable: 
   line 131: 0

  LocalVariableTable: 
   Start  Length  Slot  Name   Signature
   0      38      0    this       Lscala/collection/generic/MapTemplate$DefaultKeySet;
   0      38      1    elem       Ljava/lang/Object;

  Signature: length = 0x2
   00 FFFFFFB6 

public scala.collection.Set $plus(java.lang.Object);
  Code:
   Stack=3, Locals=2, Args_size=2
   0:	getstatic	#161; //Field scala/collection/Set$.MODULE$:Lscala/collection/Set$;
   3:	getstatic	#166; //Field scala/runtime/ScalaRunTime$.MODULE$:Lscala/runtime/ScalaRunTime$;
   6:	iconst_0
   7:	anewarray	#19; //class java/lang/Object
   10:	invokevirtual	#170; //Method scala/runtime/ScalaRunTime$.boxArray:(Ljava/lang/Object;)Lscala/runtime/BoxedArray;
   13:	invokevirtual	#173; //Method scala/collection/Set$.apply:(Lscala/collection/Sequence;)Lscala/collection/Traversable;
   16:	checkcast	#136; //class scala/collection/generic/Addable
   19:	aload_0
   20:	invokeinterface	#177,  2; //InterfaceMethod scala/collection/generic/Addable.$plus$plus:(Lscala/collection/Traversable;)Lscala/collection/generic/Addable;
   25:	checkcast	#97; //class scala/collection/generic/SetTemplate
   28:	aload_1
   29:	invokeinterface	#184,  2; //InterfaceMethod scala/collection/generic/SetTemplate.$plus:(Ljava/lang/Object;)Lscala/collection/generic/SetTemplate;
   34:	checkcast	#181; //class scala/collection/Set
   37:	areturn
  LineNumberTable: 
   line 130: 0

  LocalVariableTable: 
   Start  Length  Slot  Name   Signature
   0      38      0    this       Lscala/collection/generic/MapTemplate$DefaultKeySet;
   0      38      1    elem       Ljava/lang/Object;

  Signature: length = 0x2
   00 FFFFFFB6 

public scala.collection.Iterator iterator();
  Code:
   Stack=4, Locals=1, Args_size=1
   0:	aload_0
   1:	invokevirtual	#141; //Method scala$collection$generic$MapTemplate$DefaultKeySet$$$outer:()Lscala/collection/generic/MapTemplate;
   4:	invokeinterface	#190,  1; //InterfaceMethod scala/collection/generic/MapTemplate.iterator:()Lscala/collection/Iterator;
   9:	new	#192; //class scala/collection/generic/MapTemplate$DefaultKeySet$$anonfun$iterator$1
   12:	dup
   13:	aload_0
   14:	invokespecial	#195; //Method scala/collection/generic/MapTemplate$DefaultKeySet$$anonfun$iterator$1."<init>":(Lscala/collection/generic/MapTemplate$DefaultKeySet;)V
   17:	invokeinterface	#201,  2; //InterfaceMethod scala/collection/Iterator.map:(Lscala/Function1;)Lscala/collection/Iterator;
   22:	areturn
  LineNumberTable: 
   line 129: 0

  Signature: length = 0x2
   00 FFFFFFCA 

public boolean contains(java.lang.Object);
  Code:
   Stack=2, Locals=2, Args_size=2
   0:	aload_0
   1:	invokevirtual	#141; //Method scala$collection$generic$MapTemplate$DefaultKeySet$$$outer:()Lscala/collection/generic/MapTemplate;
   4:	aload_1
   5:	invokeinterface	#205,  2; //InterfaceMethod scala/collection/generic/MapTemplate.contains:(Ljava/lang/Object;)Z
   10:	ireturn
  LineNumberTable: 
   line 128: 0

  LocalVariableTable: 
   Start  Length  Slot  Name   Signature
   0      11      0    this       Lscala/collection/generic/MapTemplate$DefaultKeySet;
   0      11      1    key       Ljava/lang/Object;

  Signature: length = 0x2
   00 FFFFFFCF 

public scala.Function1 andThen(scala.Function1);
  Code:
   Stack=2, Locals=2, Args_size=2
   0:	aload_0
   1:	aload_1
   2:	invokestatic	#212; //Method scala/Function1$class.andThen:(Lscala/Function1;Lscala/Function1;)Lscala/Function1;
   5:	areturn
  LineNumberTable: 
   line 127: 0

  LocalVariableTable: 
   Start  Length  Slot  Name   Signature
   0      6      0    this       Lscala/collection/generic/MapTemplate$DefaultKeySet;
   0      6      1    g       Lscala/Function1;


public scala.Function1 compose(scala.Function1);
  Code:
   Stack=2, Locals=2, Args_size=2
   0:	aload_0
   1:	aload_1
   2:	invokestatic	#216; //Method scala/Function1$class.compose:(Lscala/Function1;Lscala/Function1;)Lscala/Function1;
   5:	areturn
  LineNumberTable: 
   line 127: 0

  LocalVariableTable: 
   Start  Length  Slot  Name   Signature
   0      6      0    this       Lscala/collection/generic/MapTemplate$DefaultKeySet;
   0      6      1    g       Lscala/Function1;


public scala.collection.mutable.StringBuilder addString(scala.collection.mutable.StringBuilder);
  Code:
   Stack=2, Locals=2, Args_size=2
   0:	aload_0
   1:	aload_1
   2:	invokestatic	#221; //Method scala/collection/generic/TraversableTemplate$class.addString:(Lscala/collection/generic/TraversableTemplate;Lscala/collection/mutable/StringBuilder;)Lscala/collection/mutable/StringBuilder;
   5:	areturn
  LineNumberTable: 
   line 127: 0

  LocalVariableTable: 
   Start  Length  Slot  Name   Signature
   0      6      0    this       Lscala/collection/generic/MapTemplate$DefaultKeySet;
   0      6      1    b       Lscala/collection/mutable/StringBuilder;


public scala.collection.mutable.StringBuilder addString(scala.collection.mutable.StringBuilder, java.lang.String);
  Code:
   Stack=3, Locals=3, Args_size=3
   0:	aload_0
   1:	aload_1
   2:	aload_2
   3:	invokestatic	#227; //Method scala/collection/generic/TraversableTemplate$class.addString:(Lscala/collection/generic/TraversableTemplate;Lscala/collection/mutable/StringBuilder;Ljava/lang/String;)Lscala/collection/mutable/StringBuilder;
   6:	areturn
  LineNumberTable: 
   line 127: 0

  LocalVariableTable: 
   Start  Length  Slot  Name   Signature
   0      7      0    this       Lscala/collection/generic/MapTemplate$DefaultKeySet;
   0      7      1    b       Lscala/collection/mutable/StringBuilder;
   0      7      2    sep       Ljava/lang/String;


public scala.collection.mutable.StringBuilder addString(scala.collection.mutable.StringBuilder, java.lang.String, java.lang.String, java.lang.String);
  Code:
   Stack=5, Locals=5, Args_size=5
   0:	aload_0
   1:	aload_1
   2:	aload_2
   3:	aload_3
   4:	aload	4
   6:	invokestatic	#233; //Method scala/collection/generic/TraversableTemplate$class.addString:(Lscala/collection/generic/TraversableTemplate;Lscala/collection/mutable/StringBuilder;Ljava/lang/String;Ljava/lang/String;Ljava/lang/String;)Lscala/collection/mutable/StringBuilder;
   9:	areturn
  LineNumberTable: 
   line 127: 0

  LocalVariableTable: 
   Start  Length  Slot  Name   Signature
   0      10      0    this       Lscala/collection/generic/MapTemplate$DefaultKeySet;
   0      10      1    b       Lscala/collection/mutable/StringBuilder;
   0      10      2    start       Ljava/lang/String;
   0      10      3    sep       Ljava/lang/String;
   0      10      4    end       Ljava/lang/String;


public java.lang.String mkString();
  Code:
   Stack=1, Locals=1, Args_size=1
   0:	aload_0
   1:	invokestatic	#240; //Method scala/collection/generic/TraversableTemplate$class.mkString:(Lscala/collection/generic/TraversableTemplate;)Ljava/lang/String;
   4:	areturn
  LineNumberTable: 
   line 127: 0


public java.lang.String mkString(java.lang.String);
  Code:
   Stack=2, Locals=2, Args_size=2
   0:	aload_0
   1:	aload_1
   2:	invokestatic	#244; //Method scala/collection/generic/TraversableTemplate$class.mkString:(Lscala/collection/generic/TraversableTemplate;Ljava/lang/String;)Ljava/lang/String;
   5:	areturn
  LineNumberTable: 
   line 127: 0

  LocalVariableTable: 
   Start  Length  Slot  Name   Signature
   0      6      0    this       Lscala/collection/generic/MapTemplate$DefaultKeySet;
   0      6      1    sep       Ljava/lang/String;


public java.lang.String mkString(java.lang.String, java.lang.String, java.lang.String);
  Code:
   Stack=4, Locals=4, Args_size=4
   0:	aload_0
   1:	aload_1
   2:	aload_2
   3:	aload_3
   4:	invokestatic	#248; //Method scala/collection/generic/TraversableTemplate$class.mkString:(Lscala/collection/generic/TraversableTemplate;Ljava/lang/String;Ljava/lang/String;Ljava/lang/String;)Ljava/lang/String;
   7:	areturn
  LineNumberTable: 
   line 127: 0

  LocalVariableTable: 
   Start  Length  Slot  Name   Signature
   0      8      0    this       Lscala/collection/generic/MapTemplate$DefaultKeySet;
   0      8      1    start       Ljava/lang/String;
   0      8      2    sep       Ljava/lang/String;
   0      8      3    end       Ljava/lang/String;


public scala.collection.immutable.Set toSet();
  Code:
   Stack=1, Locals=1, Args_size=1
   0:	aload_0
   1:	invokestatic	#253; //Method scala/collection/generic/TraversableTemplate$class.toSet:(Lscala/collection/generic/TraversableTemplate;)Lscala/collection/immutable/Set;
   4:	areturn
  LineNumberTable: 
   line 127: 0


public scala.collection.Sequence toSequence();
  Code:
   Stack=1, Locals=1, Args_size=1
   0:	aload_0
   1:	invokestatic	#258; //Method scala/collection/generic/TraversableTemplate$class.toSequence:(Lscala/collection/generic/TraversableTemplate;)Lscala/collection/Sequence;
   4:	areturn
  LineNumberTable: 
   line 127: 0


public scala.collection.immutable.List toList();
  Code:
   Stack=1, Locals=1, Args_size=1
   0:	aload_0
   1:	invokestatic	#263; //Method scala/collection/generic/TraversableTemplate$class.toList:(Lscala/collection/generic/TraversableTemplate;)Lscala/collection/immutable/List;
   4:	areturn
  LineNumberTable: 
   line 127: 0


public scala.runtime.BoxedArray toArray();
  Code:
   Stack=1, Locals=1, Args_size=1
   0:	aload_0
   1:	invokestatic	#268; //Method scala/collection/generic/TraversableTemplate$class.toArray:(Lscala/collection/generic/TraversableTemplate;)Lscala/runtime/BoxedArray;
   4:	areturn
  LineNumberTable: 
   line 127: 0


public void copyToArray(scala.runtime.BoxedArray, int);
  Code:
   Stack=3, Locals=3, Args_size=3
   0:	aload_0
   1:	aload_1
   2:	iload_2
   3:	invokestatic	#273; //Method scala/collection/generic/TraversableTemplate$class.copyToArray:(Lscala/collection/generic/TraversableTemplate;Lscala/runtime/BoxedArray;I)V
   6:	return
  LineNumberTable: 
   line 127: 0

  LocalVariableTable: 
   Start  Length  Slot  Name   Signature
   0      7      0    this       Lscala/collection/generic/MapTemplate$DefaultKeySet;
   0      7      1    xs       Lscala/runtime/BoxedArray;
   0      7      2    start       I


public void copyToArray(scala.runtime.BoxedArray, int, int);
  Code:
   Stack=4, Locals=4, Args_size=4
   0:	aload_0
   1:	aload_1
   2:	iload_2
   3:	iload_3
   4:	invokestatic	#279; //Method scala/collection/generic/TraversableTemplate$class.copyToArray:(Lscala/collection/generic/TraversableTemplate;Lscala/runtime/BoxedArray;II)V
   7:	return
  LineNumberTable: 
   line 127: 0

  LocalVariableTable: 
   Start  Length  Slot  Name   Signature
   0      8      0    this       Lscala/collection/generic/MapTemplate$DefaultKeySet;
   0      8      1    xs       Lscala/runtime/BoxedArray;
   0      8      2    start       I
   0      8      3    len       I


public void copyToBuffer(scala.collection.mutable.Buffer);
  Code:
   Stack=2, Locals=2, Args_size=2
   0:	aload_0
   1:	aload_1
   2:	invokestatic	#285; //Method scala/collection/generic/TraversableTemplate$class.copyToBuffer:(Lscala/collection/generic/TraversableTemplate;Lscala/collection/mutable/Buffer;)V
   5:	return
  LineNumberTable: 
   line 127: 0

  LocalVariableTable: 
   Start  Length  Slot  Name   Signature
   0      6      0    this       Lscala/collection/generic/MapTemplate$DefaultKeySet;
   0      6      1    dest       Lscala/collection/mutable/Buffer;


public scala.Tuple2 splitAt(int);
  Code:
   Stack=2, Locals=2, Args_size=2
   0:	aload_0
   1:	iload_1
   2:	invokestatic	#292; //Method scala/collection/generic/TraversableTemplate$class.splitAt:(Lscala/collection/generic/TraversableTemplate;I)Lscala/Tuple2;
   5:	areturn
  LineNumberTable: 
   line 127: 0

  LocalVariableTable: 
   Start  Length  Slot  Name   Signature
   0      6      0    this       Lscala/collection/generic/MapTemplate$DefaultKeySet;
   0      6      1    n       I


public scala.Tuple2 span(scala.Function1);
  Code:
   Stack=2, Locals=2, Args_size=2
   0:	aload_0
   1:	aload_1
   2:	invokestatic	#298; //Method scala/collection/generic/TraversableTemplate$class.span:(Lscala/collection/generic/TraversableTemplate;Lscala/Function1;)Lscala/Tuple2;
   5:	areturn
  LineNumberTable: 
   line 127: 0

  LocalVariableTable: 
   Start  Length  Slot  Name   Signature
   0      6      0    this       Lscala/collection/generic/MapTemplate$DefaultKeySet;
   0      6      1    p       Lscala/Function1;


public scala.collection.generic.TraversableTemplate dropWhile(scala.Function1);
  Code:
   Stack=2, Locals=2, Args_size=2
   0:	aload_0
   1:	aload_1
   2:	invokestatic	#304; //Method scala/collection/generic/TraversableTemplate$class.dropWhile:(Lscala/collection/generic/TraversableTemplate;Lscala/Function1;)Lscala/collection/generic/TraversableTemplate;
   5:	areturn
  LineNumberTable: 
   line 127: 0

  LocalVariableTable: 
   Start  Length  Slot  Name   Signature
   0      6      0    this       Lscala/collection/generic/MapTemplate$DefaultKeySet;
   0      6      1    p       Lscala/Function1;


public scala.collection.generic.TraversableTemplate takeWhile(scala.Function1);
  Code:
   Stack=2, Locals=2, Args_size=2
   0:	aload_0
   1:	aload_1
   2:	invokestatic	#307; //Method scala/collection/generic/TraversableTemplate$class.takeWhile:(Lscala/collection/generic/TraversableTemplate;Lscala/Function1;)Lscala/collection/generic/TraversableTemplate;
   5:	areturn
  LineNumberTable: 
   line 127: 0

  LocalVariableTable: 
   Start  Length  Slot  Name   Signature
   0      6      0    this       Lscala/collection/generic/MapTemplate$DefaultKeySet;
   0      6      1    p       Lscala/Function1;


public scala.collection.generic.TraversableTemplate slice(int, int);
  Code:
   Stack=3, Locals=3, Args_size=3
   0:	aload_0
   1:	iload_1
   2:	iload_2
   3:	invokestatic	#312; //Method scala/collection/generic/TraversableTemplate$class.slice:(Lscala/collection/generic/TraversableTemplate;II)Lscala/collection/generic/TraversableTemplate;
   6:	areturn
  LineNumberTable: 
   line 127: 0

  LocalVariableTable: 
   Start  Length  Slot  Name   Signature
   0      7      0    this       Lscala/collection/generic/MapTemplate$DefaultKeySet;
   0      7      1    from       I
   0      7      2    until       I


public scala.collection.generic.TraversableTemplate drop(int);
  Code:
   Stack=2, Locals=2, Args_size=2
   0:	aload_0
   1:	iload_1
   2:	invokestatic	#317; //Method scala/collection/generic/TraversableTemplate$class.drop:(Lscala/collection/generic/TraversableTemplate;I)Lscala/collection/generic/TraversableTemplate;
   5:	areturn
  LineNumberTable: 
   line 127: 0

  LocalVariableTable: 
   Start  Length  Slot  Name   Signature
   0      6      0    this       Lscala/collection/generic/MapTemplate$DefaultKeySet;
   0      6      1    n       I


public scala.collection.generic.TraversableTemplate take(int);
  Code:
   Stack=2, Locals=2, Args_size=2
   0:	aload_0
   1:	iload_1
   2:	invokestatic	#320; //Method scala/collection/generic/TraversableTemplate$class.take:(Lscala/collection/generic/TraversableTemplate;I)Lscala/collection/generic/TraversableTemplate;
   5:	areturn
  LineNumberTable: 
   line 127: 0

  LocalVariableTable: 
   Start  Length  Slot  Name   Signature
   0      6      0    this       Lscala/collection/generic/MapTemplate$DefaultKeySet;
   0      6      1    n       I


public scala.collection.generic.TraversableTemplate init();
  Code:
   Stack=1, Locals=1, Args_size=1
   0:	aload_0
   1:	invokestatic	#324; //Method scala/collection/generic/TraversableTemplate$class.init:(Lscala/collection/generic/TraversableTemplate;)Lscala/collection/generic/TraversableTemplate;
   4:	areturn
  LineNumberTable: 
   line 127: 0


public scala.Option lastOption();
  Code:
   Stack=1, Locals=1, Args_size=1
   0:	aload_0
   1:	invokestatic	#329; //Method scala/collection/generic/TraversableTemplate$class.lastOption:(Lscala/collection/generic/TraversableTemplate;)Lscala/Option;
   4:	areturn
  LineNumberTable: 
   line 127: 0


public java.lang.Object last();
  Code:
   Stack=1, Locals=1, Args_size=1
   0:	aload_0
   1:	invokestatic	#334; //Method scala/collection/generic/TraversableTemplate$class.last:(Lscala/collection/generic/TraversableTemplate;)Ljava/lang/Object;
   4:	areturn
  LineNumberTable: 
   line 127: 0


public scala.collection.generic.TraversableTemplate tail();
  Code:
   Stack=1, Locals=1, Args_size=1
   0:	aload_0
   1:	invokestatic	#337; //Method scala/collection/generic/TraversableTemplate$class.tail:(Lscala/collection/generic/TraversableTemplate;)Lscala/collection/generic/TraversableTemplate;
   4:	areturn
  LineNumberTable: 
   line 127: 0


public scala.Option headOption();
  Code:
   Stack=1, Locals=1, Args_size=1
   0:	aload_0
   1:	invokestatic	#340; //Method scala/collection/generic/TraversableTemplate$class.headOption:(Lscala/collection/generic/TraversableTemplate;)Lscala/Option;
   4:	areturn
  LineNumberTable: 
   line 127: 0


public scala.Option reduceRightOption(scala.Function2);
  Code:
   Stack=2, Locals=2, Args_size=2
   0:	aload_0
   1:	aload_1
   2:	invokestatic	#345; //Method scala/collection/generic/TraversableTemplate$class.reduceRightOption:(Lscala/collection/generic/TraversableTemplate;Lscala/Function2;)Lscala/Option;
   5:	areturn
  LineNumberTable: 
   line 127: 0

  LocalVariableTable: 
   Start  Length  Slot  Name   Signature
   0      6      0    this       Lscala/collection/generic/MapTemplate$DefaultKeySet;
   0      6      1    op       Lscala/Function2;


public scala.Option reduceLeftOption(scala.Function2);
  Code:
   Stack=2, Locals=2, Args_size=2
   0:	aload_0
   1:	aload_1
   2:	invokestatic	#350; //Method scala/collection/generic/TraversableTemplate$class.reduceLeftOption:(Lscala/collection/generic/TraversableTemplate;Lscala/Function2;)Lscala/Option;
   5:	areturn
  LineNumberTable: 
   line 127: 0

  LocalVariableTable: 
   Start  Length  Slot  Name   Signature
   0      6      0    this       Lscala/collection/generic/MapTemplate$DefaultKeySet;
   0      6      1    op       Lscala/Function2;


public java.lang.Object reduceLeft(scala.Function2);
  Code:
   Stack=2, Locals=2, Args_size=2
   0:	aload_0
   1:	aload_1
   2:	invokestatic	#355; //Method scala/collection/generic/TraversableTemplate$class.reduceLeft:(Lscala/collection/generic/TraversableTemplate;Lscala/Function2;)Ljava/lang/Object;
   5:	areturn
  LineNumberTable: 
   line 127: 0

  LocalVariableTable: 
   Start  Length  Slot  Name   Signature
   0      6      0    this       Lscala/collection/generic/MapTemplate$DefaultKeySet;
   0      6      1    op       Lscala/Function2;


public java.lang.Object $colon$bslash(java.lang.Object, scala.Function2);
  Code:
   Stack=3, Locals=3, Args_size=3
   0:	aload_0
   1:	aload_1
   2:	aload_2
   3:	invokestatic	#360; //Method scala/collection/generic/TraversableTemplate$class.$colon$bslash:(Lscala/collection/generic/TraversableTemplate;Ljava/lang/Object;Lscala/Function2;)Ljava/lang/Object;
   6:	areturn
  LineNumberTable: 
   line 127: 0

  LocalVariableTable: 
   Start  Length  Slot  Name   Signature
   0      7      0    this       Lscala/collection/generic/MapTemplate$DefaultKeySet;
   0      7      1    z       Ljava/lang/Object;
   0      7      2    op       Lscala/Function2;


public java.lang.Object $div$colon(java.lang.Object, scala.Function2);
  Code:
   Stack=3, Locals=3, Args_size=3
   0:	aload_0
   1:	aload_1
   2:	aload_2
   3:	invokestatic	#364; //Method scala/collection/generic/TraversableTemplate$class.$div$colon:(Lscala/collection/generic/TraversableTemplate;Ljava/lang/Object;Lscala/Function2;)Ljava/lang/Object;
   6:	areturn
  LineNumberTable: 
   line 127: 0

  LocalVariableTable: 
   Start  Length  Slot  Name   Signature
   0      7      0    this       Lscala/collection/generic/MapTemplate$DefaultKeySet;
   0      7      1    z       Ljava/lang/Object;
   0      7      2    op       Lscala/Function2;


public java.lang.Object foldLeft(java.lang.Object, scala.Function2);
  Code:
   Stack=3, Locals=3, Args_size=3
   0:	aload_0
   1:	aload_1
   2:	aload_2
   3:	invokestatic	#367; //Method scala/collection/generic/TraversableTemplate$class.foldLeft:(Lscala/collection/generic/TraversableTemplate;Ljava/lang/Object;Lscala/Function2;)Ljava/lang/Object;
   6:	areturn
  LineNumberTable: 
   line 127: 0

  LocalVariableTable: 
   Start  Length  Slot  Name   Signature
   0      7      0    this       Lscala/collection/generic/MapTemplate$DefaultKeySet;
   0      7      1    z       Ljava/lang/Object;
   0      7      2    op       Lscala/Function2;


public scala.Option find(scala.Function1);
  Code:
   Stack=2, Locals=2, Args_size=2
   0:	aload_0
   1:	aload_1
   2:	invokestatic	#372; //Method scala/collection/generic/TraversableTemplate$class.find:(Lscala/collection/generic/TraversableTemplate;Lscala/Function1;)Lscala/Option;
   5:	areturn
  LineNumberTable: 
   line 127: 0

  LocalVariableTable: 
   Start  Length  Slot  Name   Signature
   0      6      0    this       Lscala/collection/generic/MapTemplate$DefaultKeySet;
   0      6      1    p       Lscala/Function1;


public int count(scala.Function1);
  Code:
   Stack=2, Locals=2, Args_size=2
   0:	aload_0
   1:	aload_1
   2:	invokestatic	#377; //Method scala/collection/generic/TraversableTemplate$class.count:(Lscala/collection/generic/TraversableTemplate;Lscala/Function1;)I
   5:	ireturn
  LineNumberTable: 
   line 127: 0

  LocalVariableTable: 
   Start  Length  Slot  Name   Signature
   0      6      0    this       Lscala/collection/generic/MapTemplate$DefaultKeySet;
   0      6      1    p       Lscala/Function1;


public boolean exists(scala.Function1);
  Code:
   Stack=2, Locals=2, Args_size=2
   0:	aload_0
   1:	aload_1
   2:	invokestatic	#382; //Method scala/collection/generic/TraversableTemplate$class.exists:(Lscala/collection/generic/TraversableTemplate;Lscala/Function1;)Z
   5:	ireturn
  LineNumberTable: 
   line 127: 0

  LocalVariableTable: 
   Start  Length  Slot  Name   Signature
   0      6      0    this       Lscala/collection/generic/MapTemplate$DefaultKeySet;
   0      6      1    p       Lscala/Function1;


public boolean forall(scala.Function1);
  Code:
   Stack=2, Locals=2, Args_size=2
   0:	aload_0
   1:	aload_1
   2:	invokestatic	#385; //Method scala/collection/generic/TraversableTemplate$class.forall:(Lscala/collection/generic/TraversableTemplate;Lscala/Function1;)Z
   5:	ireturn
  LineNumberTable: 
   line 127: 0

  LocalVariableTable: 
   Start  Length  Slot  Name   Signature
   0      6      0    this       Lscala/collection/generic/MapTemplate$DefaultKeySet;
   0      6      1    p       Lscala/Function1;


public scala.collection.Map groupBy(scala.Function1);
  Code:
   Stack=2, Locals=2, Args_size=2
   0:	aload_0
   1:	aload_1
   2:	invokestatic	#390; //Method scala/collection/generic/TraversableTemplate$class.groupBy:(Lscala/collection/generic/TraversableTemplate;Lscala/Function1;)Lscala/collection/Map;
   5:	areturn
  LineNumberTable: 
   line 127: 0

  LocalVariableTable: 
   Start  Length  Slot  Name   Signature
   0      6      0    this       Lscala/collection/generic/MapTemplate$DefaultKeySet;
   0      6      1    f       Lscala/Function1;


public scala.Tuple2 partition(scala.Function1);
  Code:
   Stack=2, Locals=2, Args_size=2
   0:	aload_0
   1:	aload_1
   2:	invokestatic	#394; //Method scala/collection/generic/TraversableTemplate$class.partition:(Lscala/collection/generic/TraversableTemplate;Lscala/Function1;)Lscala/Tuple2;
   5:	areturn
  LineNumberTable: 
   line 127: 0

  LocalVariableTable: 
   Start  Length  Slot  Name   Signature
   0      6      0    this       Lscala/collection/generic/MapTemplate$DefaultKeySet;
   0      6      1    p       Lscala/Function1;


public scala.collection.generic.TraversableTemplate remove(scala.Function1);
  Code:
   Stack=2, Locals=2, Args_size=2
   0:	aload_0
   1:	aload_1
   2:	invokestatic	#397; //Method scala/collection/generic/TraversableTemplate$class.remove:(Lscala/collection/generic/TraversableTemplate;Lscala/Function1;)Lscala/collection/generic/TraversableTemplate;
   5:	areturn
  LineNumberTable: 
   line 127: 0

  LocalVariableTable: 
   Start  Length  Slot  Name   Signature
   0      6      0    this       Lscala/collection/generic/MapTemplate$DefaultKeySet;
   0      6      1    p       Lscala/Function1;


public scala.collection.generic.TraversableTemplate filterNot(scala.Function1);
  Code:
   Stack=2, Locals=2, Args_size=2
   0:	aload_0
   1:	aload_1
   2:	invokestatic	#400; //Method scala/collection/generic/TraversableTemplate$class.filterNot:(Lscala/collection/generic/TraversableTemplate;Lscala/Function1;)Lscala/collection/generic/TraversableTemplate;
   5:	areturn
  LineNumberTable: 
   line 127: 0

  LocalVariableTable: 
   Start  Length  Slot  Name   Signature
   0      6      0    this       Lscala/collection/generic/MapTemplate$DefaultKeySet;
   0      6      1    p       Lscala/Function1;


public java.lang.Object filterMap(scala.PartialFunction, scala.collection.generic.BuilderFactory);
  Code:
   Stack=3, Locals=3, Args_size=3
   0:	aload_0
   1:	aload_1
   2:	aload_2
   3:	invokestatic	#405; //Method scala/collection/generic/TraversableTemplate$class.filterMap:(Lscala/collection/generic/TraversableTemplate;Lscala/PartialFunction;Lscala/collection/generic/BuilderFactory;)Ljava/lang/Object;
   6:	areturn
  LineNumberTable: 
   line 127: 0

  LocalVariableTable: 
   Start  Length  Slot  Name   Signature
   0      7      0    this       Lscala/collection/generic/MapTemplate$DefaultKeySet;
   0      7      1    pf       Lscala/PartialFunction;
   0      7      2    bf       Lscala/collection/generic/BuilderFactory;


public scala.collection.generic.TraversableTemplate filter(scala.Function1);
  Code:
   Stack=2, Locals=2, Args_size=2
   0:	aload_0
   1:	aload_1
   2:	invokestatic	#412; //Method scala/collection/generic/TraversableTemplate$class.filter:(Lscala/collection/generic/TraversableTemplate;Lscala/Function1;)Lscala/collection/generic/TraversableTemplate;
   5:	areturn
  LineNumberTable: 
   line 127: 0

  LocalVariableTable: 
   Start  Length  Slot  Name   Signature
   0      6      0    this       Lscala/collection/generic/MapTemplate$DefaultKeySet;
   0      6      1    p       Lscala/Function1;


public java.lang.Object flatMap(scala.Function1, scala.collection.generic.BuilderFactory);
  Code:
   Stack=3, Locals=3, Args_size=3
   0:	aload_0
   1:	aload_1
   2:	aload_2
   3:	invokestatic	#417; //Method scala/collection/generic/TraversableTemplate$class.flatMap:(Lscala/collection/generic/TraversableTemplate;Lscala/Function1;Lscala/collection/generic/BuilderFactory;)Ljava/lang/Object;
   6:	areturn
  LineNumberTable: 
   line 127: 0

  LocalVariableTable: 
   Start  Length  Slot  Name   Signature
   0      7      0    this       Lscala/collection/generic/MapTemplate$DefaultKeySet;
   0      7      1    f       Lscala/Function1;
   0      7      2    bf       Lscala/collection/generic/BuilderFactory;


public java.lang.Object map(scala.Function1, scala.collection.generic.BuilderFactory);
  Code:
   Stack=3, Locals=3, Args_size=3
   0:	aload_0
   1:	aload_1
   2:	aload_2
   3:	invokestatic	#419; //Method scala/collection/generic/TraversableTemplate$class.map:(Lscala/collection/generic/TraversableTemplate;Lscala/Function1;Lscala/collection/generic/BuilderFactory;)Ljava/lang/Object;
   6:	areturn
  LineNumberTable: 
   line 127: 0

  LocalVariableTable: 
   Start  Length  Slot  Name   Signature
   0      7      0    this       Lscala/collection/generic/MapTemplate$DefaultKeySet;
   0      7      1    f       Lscala/Function1;
   0      7      2    bf       Lscala/collection/generic/BuilderFactory;


public java.lang.Object $plus$plus(scala.collection.Iterator, scala.collection.generic.BuilderFactory);
  Code:
   Stack=3, Locals=3, Args_size=3
   0:	aload_0
   1:	aload_1
   2:	aload_2
   3:	invokestatic	#423; //Method scala/collection/generic/TraversableTemplate$class.$plus$plus:(Lscala/collection/generic/TraversableTemplate;Lscala/collection/Iterator;Lscala/collection/generic/BuilderFactory;)Ljava/lang/Object;
   6:	areturn
  LineNumberTable: 
   line 127: 0

  LocalVariableTable: 
   Start  Length  Slot  Name   Signature
   0      7      0    this       Lscala/collection/generic/MapTemplate$DefaultKeySet;
   0      7      1    that       Lscala/collection/Iterator;
   0      7      2    bf       Lscala/collection/generic/BuilderFactory;


public java.lang.Object $plus$plus(scala.collection.Traversable, scala.collection.generic.BuilderFactory);
  Code:
   Stack=3, Locals=3, Args_size=3
   0:	aload_0
   1:	aload_1
   2:	aload_2
   3:	invokestatic	#429; //Method scala/collection/generic/TraversableTemplate$class.$plus$plus:(Lscala/collection/generic/TraversableTemplate;Lscala/collection/Traversable;Lscala/collection/generic/BuilderFactory;)Ljava/lang/Object;
   6:	areturn
  LineNumberTable: 
   line 127: 0

  LocalVariableTable: 
   Start  Length  Slot  Name   Signature
   0      7      0    this       Lscala/collection/generic/MapTemplate$DefaultKeySet;
   0      7      1    that       Lscala/collection/Traversable;
   0      7      2    bf       Lscala/collection/generic/BuilderFactory;


public boolean hasDefiniteSize();
  Code:
   Stack=1, Locals=1, Args_size=1
   0:	aload_0
   1:	invokestatic	#435; //Method scala/collection/generic/TraversableTemplate$class.hasDefiniteSize:(Lscala/collection/generic/TraversableTemplate;)Z
   4:	ireturn
  LineNumberTable: 
   line 127: 0


public boolean nonEmpty();
  Code:
   Stack=1, Locals=1, Args_size=1
   0:	aload_0
   1:	invokestatic	#438; //Method scala/collection/generic/TraversableTemplate$class.nonEmpty:(Lscala/collection/generic/TraversableTemplate;)Z
   4:	ireturn
  LineNumberTable: 
   line 127: 0


public scala.collection.generic.TraversableTemplate thisCollection();
  Code:
   Stack=1, Locals=1, Args_size=1
   0:	aload_0
   1:	invokestatic	#440; //Method scala/collection/generic/TraversableTemplate$class.thisCollection:(Lscala/collection/generic/TraversableTemplate;)Lscala/collection/generic/TraversableTemplate;
   4:	areturn
  LineNumberTable: 
   line 127: 0


public scala.collection.Traversable transpose(scala.Function1);
  Code:
   Stack=2, Locals=2, Args_size=2
   0:	aload_0
   1:	aload_1
   2:	invokestatic	#445; //Method scala/collection/generic/TraversableClass$class.transpose:(Lscala/collection/generic/TraversableClass;Lscala/Function1;)Lscala/collection/Traversable;
   5:	areturn
  LineNumberTable: 
   line 127: 0

  LocalVariableTable: 
   Start  Length  Slot  Name   Signature
   0      6      0    this       Lscala/collection/generic/MapTemplate$DefaultKeySet;
   0      6      1    toTraversable       Lscala/Function1;


public scala.collection.Traversable flatten(scala.Function1);
  Code:
   Stack=2, Locals=2, Args_size=2
   0:	aload_0
   1:	aload_1
   2:	invokestatic	#449; //Method scala/collection/generic/TraversableClass$class.flatten:(Lscala/collection/generic/TraversableClass;Lscala/Function1;)Lscala/collection/Traversable;
   5:	areturn
  LineNumberTable: 
   line 127: 0

  LocalVariableTable: 
   Start  Length  Slot  Name   Signature
   0      6      0    this       Lscala/collection/generic/MapTemplate$DefaultKeySet;
   0      6      1    toTraversable       Lscala/Function1;


public scala.Tuple2 unzip(scala.Function1);
  Code:
   Stack=2, Locals=2, Args_size=2
   0:	aload_0
   1:	aload_1
   2:	invokestatic	#453; //Method scala/collection/generic/TraversableClass$class.unzip:(Lscala/collection/generic/TraversableClass;Lscala/Function1;)Lscala/Tuple2;
   5:	areturn
  LineNumberTable: 
   line 127: 0

  LocalVariableTable: 
   Start  Length  Slot  Name   Signature
   0      6      0    this       Lscala/collection/generic/MapTemplate$DefaultKeySet;
   0      6      1    toPair       Lscala/Function1;


public scala.collection.generic.Builder genericBuilder();
  Code:
   Stack=1, Locals=1, Args_size=1
   0:	aload_0
   1:	invokestatic	#459; //Method scala/collection/generic/TraversableClass$class.genericBuilder:(Lscala/collection/generic/TraversableClass;)Lscala/collection/generic/Builder;
   4:	areturn
  LineNumberTable: 
   line 127: 0


public java.lang.Object projection();
  Code:
   Stack=1, Locals=1, Args_size=1
   0:	aload_0
   1:	invokestatic	#463; //Method scala/collection/generic/IterableTemplate$class.projection:(Lscala/collection/generic/IterableTemplate;)Ljava/lang/Object;
   4:	areturn
  LineNumberTable: 
   line 127: 0


public scala.collection.Sequence toSeq();
  Code:
   Stack=1, Locals=1, Args_size=1
   0:	aload_0
   1:	invokestatic	#467; //Method scala/collection/generic/IterableTemplate$class.toSeq:(Lscala/collection/generic/IterableTemplate;)Lscala/collection/Sequence;
   4:	areturn
  LineNumberTable: 
   line 127: 0


public scala.Option firstOption();
  Code:
   Stack=1, Locals=1, Args_size=1
   0:	aload_0
   1:	invokestatic	#471; //Method scala/collection/generic/IterableTemplate$class.firstOption:(Lscala/collection/generic/IterableTemplate;)Lscala/Option;
   4:	areturn
  LineNumberTable: 
   line 127: 0


public java.lang.Object first();
  Code:
   Stack=1, Locals=1, Args_size=1
   0:	aload_0
   1:	invokestatic	#474; //Method scala/collection/generic/IterableTemplate$class.first:(Lscala/collection/generic/IterableTemplate;)Ljava/lang/Object;
   4:	areturn
  LineNumberTable: 
   line 127: 0


public scala.collection.generic.IterableView view(int, int);
  Code:
   Stack=3, Locals=3, Args_size=3
   0:	aload_0
   1:	iload_1
   2:	iload_2
   3:	invokestatic	#477; //Method scala/collection/generic/IterableTemplate$class.view:(Lscala/collection/generic/IterableTemplate;II)Lscala/collection/generic/IterableView;
   6:	areturn
  LineNumberTable: 
   line 127: 0

  LocalVariableTable: 
   Start  Length  Slot  Name   Signature
   0      7      0    this       Lscala/collection/generic/MapTemplate$DefaultKeySet;
   0      7      1    from       I
   0      7      2    until       I


public java.lang.Object view();
  Code:
   Stack=1, Locals=1, Args_size=1
   0:	aload_0
   1:	invokestatic	#479; //Method scala/collection/generic/IterableTemplate$class.view:(Lscala/collection/generic/IterableTemplate;)Ljava/lang/Object;
   4:	areturn
  LineNumberTable: 
   line 127: 0


public scala.collection.immutable.Stream toStream();
  Code:
   Stack=1, Locals=1, Args_size=1
   0:	aload_0
   1:	invokestatic	#484; //Method scala/collection/generic/IterableTemplate$class.toStream:(Lscala/collection/generic/IterableTemplate;)Lscala/collection/immutable/Stream;
   4:	areturn
  LineNumberTable: 
   line 127: 0


public boolean sameElements(scala.collection.Iterable);
  Code:
   Stack=2, Locals=2, Args_size=2
   0:	aload_0
   1:	aload_1
   2:	invokestatic	#489; //Method scala/collection/generic/IterableTemplate$class.sameElements:(Lscala/collection/generic/IterableTemplate;Lscala/collection/Iterable;)Z
   5:	ireturn
  LineNumberTable: 
   line 127: 0

  LocalVariableTable: 
   Start  Length  Slot  Name   Signature
   0      6      0    this       Lscala/collection/generic/MapTemplate$DefaultKeySet;
   0      6      1    that       Lscala/collection/Iterable;


public scala.collection.generic.IterableTemplate dropRight(int);
  Code:
   Stack=2, Locals=2, Args_size=2
   0:	aload_0
   1:	iload_1
   2:	invokestatic	#495; //Method scala/collection/generic/IterableTemplate$class.dropRight:(Lscala/collection/generic/IterableTemplate;I)Lscala/collection/generic/IterableTemplate;
   5:	areturn
  LineNumberTable: 
   line 127: 0

  LocalVariableTable: 
   Start  Length  Slot  Name   Signature
   0      6      0    this       Lscala/collection/generic/MapTemplate$DefaultKeySet;
   0      6      1    n       I


public scala.collection.generic.IterableTemplate takeRight(int);
  Code:
   Stack=2, Locals=2, Args_size=2
   0:	aload_0
   1:	iload_1
   2:	invokestatic	#498; //Method scala/collection/generic/IterableTemplate$class.takeRight:(Lscala/collection/generic/IterableTemplate;I)Lscala/collection/generic/IterableTemplate;
   5:	areturn
  LineNumberTable: 
   line 127: 0

  LocalVariableTable: 
   Start  Length  Slot  Name   Signature
   0      6      0    this       Lscala/collection/generic/MapTemplate$DefaultKeySet;
   0      6      1    n       I


public java.lang.Object head();
  Code:
   Stack=1, Locals=1, Args_size=1
   0:	aload_0
   1:	invokestatic	#501; //Method scala/collection/generic/IterableTemplate$class.head:(Lscala/collection/generic/IterableTemplate;)Ljava/lang/Object;
   4:	areturn
  LineNumberTable: 
   line 127: 0


public scala.collection.Iterable toIterable();
  Code:
   Stack=1, Locals=1, Args_size=1
   0:	aload_0
   1:	invokestatic	#506; //Method scala/collection/generic/IterableTemplate$class.toIterable:(Lscala/collection/generic/IterableTemplate;)Lscala/collection/Iterable;
   4:	areturn
  LineNumberTable: 
   line 127: 0


public java.lang.Object reduceRight(scala.Function2);
  Code:
   Stack=2, Locals=2, Args_size=2
   0:	aload_0
   1:	aload_1
   2:	invokestatic	#510; //Method scala/collection/generic/IterableTemplate$class.reduceRight:(Lscala/collection/generic/IterableTemplate;Lscala/Function2;)Ljava/lang/Object;
   5:	areturn
  LineNumberTable: 
   line 127: 0

  LocalVariableTable: 
   Start  Length  Slot  Name   Signature
   0      6      0    this       Lscala/collection/generic/MapTemplate$DefaultKeySet;
   0      6      1    op       Lscala/Function2;


public java.lang.Object foldRight(java.lang.Object, scala.Function2);
  Code:
   Stack=3, Locals=3, Args_size=3
   0:	aload_0
   1:	aload_1
   2:	aload_2
   3:	invokestatic	#514; //Method scala/collection/generic/IterableTemplate$class.foldRight:(Lscala/collection/generic/IterableTemplate;Ljava/lang/Object;Lscala/Function2;)Ljava/lang/Object;
   6:	areturn
  LineNumberTable: 
   line 127: 0

  LocalVariableTable: 
   Start  Length  Slot  Name   Signature
   0      7      0    this       Lscala/collection/generic/MapTemplate$DefaultKeySet;
   0      7      1    z       Ljava/lang/Object;
   0      7      2    op       Lscala/Function2;


public scala.collection.Iterator elements();
  Code:
   Stack=1, Locals=1, Args_size=1
   0:	aload_0
   1:	invokestatic	#518; //Method scala/collection/generic/IterableTemplate$class.elements:(Lscala/collection/generic/IterableTemplate;)Lscala/collection/Iterator;
   4:	areturn
  LineNumberTable: 
   line 127: 0


public scala.collection.Set empty();
  Code:
   Stack=1, Locals=1, Args_size=1
   0:	aload_0
   1:	invokestatic	#521; //Method scala/collection/generic/SetClass$class.empty:(Lscala/collection/generic/SetClass;)Lscala/collection/Set;
   4:	areturn
  LineNumberTable: 
   line 127: 0


public scala.collection.generic.Addable $plus$plus(scala.collection.Iterator);
  Code:
   Stack=2, Locals=2, Args_size=2
   0:	aload_0
   1:	aload_1
   2:	invokestatic	#525; //Method scala/collection/generic/Addable$class.$plus$plus:(Lscala/collection/generic/Addable;Lscala/collection/Iterator;)Lscala/collection/generic/Addable;
   5:	areturn
  LineNumberTable: 
   line 127: 0

  LocalVariableTable: 
   Start  Length  Slot  Name   Signature
   0      6      0    this       Lscala/collection/generic/MapTemplate$DefaultKeySet;
   0      6      1    iter       Lscala/collection/Iterator;


public scala.collection.generic.Addable $plus$plus(scala.collection.Traversable);
  Code:
   Stack=2, Locals=2, Args_size=2
   0:	aload_0
   1:	aload_1
   2:	invokestatic	#529; //Method scala/collection/generic/Addable$class.$plus$plus:(Lscala/collection/generic/Addable;Lscala/collection/Traversable;)Lscala/collection/generic/Addable;
   5:	areturn
  LineNumberTable: 
   line 127: 0

  LocalVariableTable: 
   Start  Length  Slot  Name   Signature
   0      6      0    this       Lscala/collection/generic/MapTemplate$DefaultKeySet;
   0      6      1    elems       Lscala/collection/Traversable;


public scala.collection.generic.Addable $plus(java.lang.Object, java.lang.Object, scala.collection.Sequence);
  Code:
   Stack=4, Locals=4, Args_size=4
   0:	aload_0
   1:	aload_1
   2:	aload_2
   3:	aload_3
   4:	invokestatic	#534; //Method scala/collection/generic/Addable$class.$plus:(Lscala/collection/generic/Addable;Ljava/lang/Object;Ljava/lang/Object;Lscala/collection/Sequence;)Lscala/collection/generic/Addable;
   7:	areturn
  LineNumberTable: 
   line 127: 0

  LocalVariableTable: 
   Start  Length  Slot  Name   Signature
   0      8      0    this       Lscala/collection/generic/MapTemplate$DefaultKeySet;
   0      8      1    elem1       Ljava/lang/Object;
   0      8      2    elem2       Ljava/lang/Object;
   0      8      3    elems       Lscala/collection/Sequence;


public scala.collection.generic.Subtractable $minus$minus(scala.collection.Iterator);
  Code:
   Stack=2, Locals=2, Args_size=2
   0:	aload_0
   1:	aload_1
   2:	invokestatic	#542; //Method scala/collection/generic/Subtractable$class.$minus$minus:(Lscala/collection/generic/Subtractable;Lscala/collection/Iterator;)Lscala/collection/generic/Subtractable;
   5:	areturn
  LineNumberTable: 
   line 127: 0

  LocalVariableTable: 
   Start  Length  Slot  Name   Signature
   0      6      0    this       Lscala/collection/generic/MapTemplate$DefaultKeySet;
   0      6      1    iter       Lscala/collection/Iterator;


public scala.collection.generic.Subtractable $minus$minus(scala.collection.Traversable);
  Code:
   Stack=2, Locals=2, Args_size=2
   0:	aload_0
   1:	aload_1
   2:	invokestatic	#546; //Method scala/collection/generic/Subtractable$class.$minus$minus:(Lscala/collection/generic/Subtractable;Lscala/collection/Traversable;)Lscala/collection/generic/Subtractable;
   5:	areturn
  LineNumberTable: 
   line 127: 0

  LocalVariableTable: 
   Start  Length  Slot  Name   Signature
   0      6      0    this       Lscala/collection/generic/MapTemplate$DefaultKeySet;
   0      6      1    elems       Lscala/collection/Traversable;


public scala.collection.generic.Subtractable $minus(java.lang.Object, java.lang.Object, scala.collection.Sequence);
  Code:
   Stack=4, Locals=4, Args_size=4
   0:	aload_0
   1:	aload_1
   2:	aload_2
   3:	aload_3
   4:	invokestatic	#550; //Method scala/collection/generic/Subtractable$class.$minus:(Lscala/collection/generic/Subtractable;Ljava/lang/Object;Ljava/lang/Object;Lscala/collection/Sequence;)Lscala/collection/generic/Subtractable;
   7:	areturn
  LineNumberTable: 
   line 127: 0

  LocalVariableTable: 
   Start  Length  Slot  Name   Signature
   0      8      0    this       Lscala/collection/generic/MapTemplate$DefaultKeySet;
   0      8      1    elem1       Ljava/lang/Object;
   0      8      2    elem2       Ljava/lang/Object;
   0      8      3    elems       Lscala/collection/Sequence;


public java.lang.String toString();
  Code:
   Stack=1, Locals=1, Args_size=1
   0:	aload_0
   1:	invokestatic	#554; //Method scala/collection/generic/SetTemplate$class.toString:(Lscala/collection/generic/SetTemplate;)Ljava/lang/String;
   4:	areturn
  LineNumberTable: 
   line 127: 0


public java.lang.String stringPrefix();
  Code:
   Stack=1, Locals=1, Args_size=1
   0:	aload_0
   1:	invokestatic	#557; //Method scala/collection/generic/SetTemplate$class.stringPrefix:(Lscala/collection/generic/SetTemplate;)Ljava/lang/String;
   4:	areturn
  LineNumberTable: 
   line 127: 0


public boolean equals(java.lang.Object);
  Code:
   Stack=2, Locals=2, Args_size=2
   0:	aload_0
   1:	aload_1
   2:	invokestatic	#561; //Method scala/collection/generic/SetTemplate$class.equals:(Lscala/collection/generic/SetTemplate;Ljava/lang/Object;)Z
   5:	ireturn
  LineNumberTable: 
   line 127: 0

  LocalVariableTable: 
   Start  Length  Slot  Name   Signature
   0      6      0    this       Lscala/collection/generic/MapTemplate$DefaultKeySet;
   0      6      1    that       Ljava/lang/Object;


public boolean subsetOf(scala.collection.Set);
  Code:
   Stack=2, Locals=2, Args_size=2
   0:	aload_0
   1:	aload_1
   2:	invokestatic	#566; //Method scala/collection/generic/SetTemplate$class.subsetOf:(Lscala/collection/generic/SetTemplate;Lscala/collection/Set;)Z
   5:	ireturn
  LineNumberTable: 
   line 127: 0

  LocalVariableTable: 
   Start  Length  Slot  Name   Signature
   0      6      0    this       Lscala/collection/generic/MapTemplate$DefaultKeySet;
   0      6      1    that       Lscala/collection/Set;


public scala.collection.generic.SetTemplate $amp$tilde(scala.collection.Set);
  Code:
   Stack=2, Locals=2, Args_size=2
   0:	aload_0
   1:	aload_1
   2:	invokestatic	#572; //Method scala/collection/generic/SetTemplate$class.$amp$tilde:(Lscala/collection/generic/SetTemplate;Lscala/collection/Set;)Lscala/collection/generic/SetTemplate;
   5:	areturn
  LineNumberTable: 
   line 127: 0

  LocalVariableTable: 
   Start  Length  Slot  Name   Signature
   0      6      0    this       Lscala/collection/generic/MapTemplate$DefaultKeySet;
   0      6      1    that       Lscala/collection/Set;


public scala.collection.generic.SetTemplate diff(scala.collection.Set);
  Code:
   Stack=2, Locals=2, Args_size=2
   0:	aload_0
   1:	aload_1
   2:	invokestatic	#575; //Method scala/collection/generic/SetTemplate$class.diff:(Lscala/collection/generic/SetTemplate;Lscala/collection/Set;)Lscala/collection/generic/SetTemplate;
   5:	areturn
  LineNumberTable: 
   line 127: 0

  LocalVariableTable: 
   Start  Length  Slot  Name   Signature
   0      6      0    this       Lscala/collection/generic/MapTemplate$DefaultKeySet;
   0      6      1    that       Lscala/collection/Set;


public scala.collection.generic.SetTemplate $bar(scala.collection.Set);
  Code:
   Stack=2, Locals=2, Args_size=2
   0:	aload_0
   1:	aload_1
   2:	invokestatic	#578; //Method scala/collection/generic/SetTemplate$class.$bar:(Lscala/collection/generic/SetTemplate;Lscala/collection/Set;)Lscala/collection/generic/SetTemplate;
   5:	areturn
  LineNumberTable: 
   line 127: 0

  LocalVariableTable: 
   Start  Length  Slot  Name   Signature
   0      6      0    this       Lscala/collection/generic/MapTemplate$DefaultKeySet;
   0      6      1    that       Lscala/collection/Set;


public scala.collection.generic.SetTemplate union(scala.collection.Set);
  Code:
   Stack=2, Locals=2, Args_size=2
   0:	aload_0
   1:	aload_1
   2:	invokestatic	#581; //Method scala/collection/generic/SetTemplate$class.union:(Lscala/collection/generic/SetTemplate;Lscala/collection/Set;)Lscala/collection/generic/SetTemplate;
   5:	areturn
  LineNumberTable: 
   line 127: 0

  LocalVariableTable: 
   Start  Length  Slot  Name   Signature
   0      6      0    this       Lscala/collection/generic/MapTemplate$DefaultKeySet;
   0      6      1    that       Lscala/collection/Set;


public scala.collection.generic.SetTemplate $times$times(scala.collection.Set);
  Code:
   Stack=2, Locals=2, Args_size=2
   0:	aload_0
   1:	aload_1
   2:	invokestatic	#584; //Method scala/collection/generic/SetTemplate$class.$times$times:(Lscala/collection/generic/SetTemplate;Lscala/collection/Set;)Lscala/collection/generic/SetTemplate;
   5:	areturn
  LineNumberTable: 
   line 127: 0

  LocalVariableTable: 
   Start  Length  Slot  Name   Signature
   0      6      0    this       Lscala/collection/generic/MapTemplate$DefaultKeySet;
   0      6      1    that       Lscala/collection/Set;


public scala.collection.generic.SetTemplate $amp(scala.collection.Set);
  Code:
   Stack=2, Locals=2, Args_size=2
   0:	aload_0
   1:	aload_1
   2:	invokestatic	#587; //Method scala/collection/generic/SetTemplate$class.$amp:(Lscala/collection/generic/SetTemplate;Lscala/collection/Set;)Lscala/collection/generic/SetTemplate;
   5:	areturn
  LineNumberTable: 
   line 127: 0

  LocalVariableTable: 
   Start  Length  Slot  Name   Signature
   0      6      0    this       Lscala/collection/generic/MapTemplate$DefaultKeySet;
   0      6      1    that       Lscala/collection/Set;


public scala.collection.generic.SetTemplate intersect(scala.collection.Set);
  Code:
   Stack=2, Locals=2, Args_size=2
   0:	aload_0
   1:	aload_1
   2:	invokestatic	#590; //Method scala/collection/generic/SetTemplate$class.intersect:(Lscala/collection/generic/SetTemplate;Lscala/collection/Set;)Lscala/collection/generic/SetTemplate;
   5:	areturn
  LineNumberTable: 
   line 127: 0

  LocalVariableTable: 
   Start  Length  Slot  Name   Signature
   0      6      0    this       Lscala/collection/generic/MapTemplate$DefaultKeySet;
   0      6      1    that       Lscala/collection/Set;


public boolean apply(java.lang.Object);
  Code:
   Stack=2, Locals=2, Args_size=2
   0:	aload_0
   1:	aload_1
   2:	invokestatic	#592; //Method scala/collection/generic/SetTemplate$class.apply:(Lscala/collection/generic/SetTemplate;Ljava/lang/Object;)Z
   5:	ireturn
  LineNumberTable: 
   line 127: 0

  LocalVariableTable: 
   Start  Length  Slot  Name   Signature
   0      6      0    this       Lscala/collection/generic/MapTemplate$DefaultKeySet;
   0      6      1    elem       Ljava/lang/Object;


public boolean isEmpty();
  Code:
   Stack=1, Locals=1, Args_size=1
   0:	aload_0
   1:	invokestatic	#596; //Method scala/collection/generic/SetTemplate$class.isEmpty:(Lscala/collection/generic/SetTemplate;)Z
   4:	ireturn
  LineNumberTable: 
   line 127: 0


public scala.collection.generic.Builder newBuilder();
  Code:
   Stack=1, Locals=1, Args_size=1
   0:	aload_0
   1:	invokestatic	#600; //Method scala/collection/generic/SetTemplate$class.newBuilder:(Lscala/collection/generic/SetTemplate;)Lscala/collection/generic/Builder;
   4:	areturn
  LineNumberTable: 
   line 127: 0


public scala.collection.generic.Companion companion();
  Code:
   Stack=1, Locals=1, Args_size=1
   0:	aload_0
   1:	invokestatic	#605; //Method scala/collection/Set$class.companion:(Lscala/collection/Set;)Lscala/collection/generic/Companion;
   4:	areturn
  LineNumberTable: 
   line 127: 0


}

