Compiled from "MutableVectorTemplate.scala"
public abstract class scala.collection.generic.MutableVectorTemplate$class extends java.lang.Object
  SourceFile: "MutableVectorTemplate.scala"
  Scala: length = 0x
   
  InnerClass: 
   public final #36= #30 of #13; //$anon$1=class scala/collection/generic/MutableVectorTemplate$$anon$1 of class scala/collection/generic/MutableVectorTemplate
  minor version: 0
  major version: 49
  Constant pool:
const #1 = Asciz	SourceFile;
const #2 = Asciz	MutableVectorTemplate.scala;
const #3 = Asciz	$init$;
const #4 = Asciz	(Lscala/collection/generic/MutableVectorTemplate;)V;
const #5 = Asciz	Code;
const #6 = Asciz	LineNumberTable;
const #7 = Asciz	$this;
const #8 = Asciz	Lscala/collection/generic/MutableVectorTemplate;;
const #9 = Asciz	LocalVariableTable;
const #10 = Asciz	view;
const #11 = Asciz	(Lscala/collection/generic/MutableVectorTemplate;II)Lscala/collection/generic/MutableVectorView;;
const #12 = Asciz	scala/collection/generic/MutableVectorTemplate;
const #13 = class	#12;	//  scala/collection/generic/MutableVectorTemplate
const #14 = Asciz	()Ljava/lang/Object;;
const #15 = NameAndType	#10:#14;//  view:()Ljava/lang/Object;
const #16 = InterfaceMethod	#13.#15;	//  scala/collection/generic/MutableVectorTemplate.view:()Ljava/lang/Object;
const #17 = Asciz	scala/collection/generic/TraversableViewTemplate;
const #18 = class	#17;	//  scala/collection/generic/TraversableViewTemplate
const #19 = Asciz	slice;
const #20 = Asciz	(II)Lscala/collection/generic/TraversableView;;
const #21 = NameAndType	#19:#20;//  slice:(II)Lscala/collection/generic/TraversableView;
const #22 = InterfaceMethod	#18.#21;	//  scala/collection/generic/TraversableViewTemplate.slice:(II)Lscala/collection/generic/TraversableView;
const #23 = Asciz	scala/collection/generic/MutableVectorView;
const #24 = class	#23;	//  scala/collection/generic/MutableVectorView
const #25 = Asciz	from;
const #26 = Asciz	I;
const #27 = Asciz	until;
const #28 = Asciz	(Lscala/collection/generic/MutableVectorTemplate;)Ljava/lang/Object;;
const #29 = Asciz	scala/collection/generic/MutableVectorTemplate$$anon$1;
const #30 = class	#29;	//  scala/collection/generic/MutableVectorTemplate$$anon$1
const #31 = Asciz	<init>;
const #32 = NameAndType	#31:#4;//  "<init>":(Lscala/collection/generic/MutableVectorTemplate;)V
const #33 = Method	#30.#32;	//  scala/collection/generic/MutableVectorTemplate$$anon$1."<init>":(Lscala/collection/generic/MutableVectorTemplate;)V
const #34 = Asciz	Scala;
const #35 = Asciz	InnerClasses;
const #36 = Asciz	$anon$1;
const #37 = Asciz	scala/collection/generic/MutableVectorTemplate$class;
const #38 = class	#37;	//  scala/collection/generic/MutableVectorTemplate$class
const #39 = Asciz	java/lang/Object;
const #40 = class	#39;	//  java/lang/Object

{
public static void $init$(scala.collection.generic.MutableVectorTemplate);
  Code:
   Stack=0, Locals=1, Args_size=1
   0:	return
  LineNumberTable: 
   line 18: 0

  LocalVariableTable: 
   Start  Length  Slot  Name   Signature
   0      1      0    $this       Lscala/collection/generic/MutableVectorTemplate;


public static scala.collection.generic.MutableVectorView view(scala.collection.generic.MutableVectorTemplate, int, int);
  Code:
   Stack=3, Locals=3, Args_size=3
   0:	aload_0
   1:	invokeinterface	#16,  1; //InterfaceMethod scala/collection/generic/MutableVectorTemplate.view:()Ljava/lang/Object;
   6:	checkcast	#18; //class scala/collection/generic/TraversableViewTemplate
   9:	iload_1
   10:	iload_2
   11:	invokeinterface	#22,  3; //InterfaceMethod scala/collection/generic/TraversableViewTemplate.slice:(II)Lscala/collection/generic/TraversableView;
   16:	checkcast	#24; //class scala/collection/generic/MutableVectorView
   19:	areturn
  LineNumberTable: 
   line 42: 0

  LocalVariableTable: 
   Start  Length  Slot  Name   Signature
   0      20      0    $this       Lscala/collection/generic/MutableVectorTemplate;
   0      20      1    from       I
   0      20      2    until       I


public static java.lang.Object view(scala.collection.generic.MutableVectorTemplate);
  Code:
   Stack=3, Locals=1, Args_size=1
   0:	new	#30; //class scala/collection/generic/MutableVectorTemplate$$anon$1
   3:	dup
   4:	aload_0
   5:	invokespecial	#33; //Method scala/collection/generic/MutableVectorTemplate$$anon$1."<init>":(Lscala/collection/generic/MutableVectorTemplate;)V
   8:	areturn
  LineNumberTable: 
   line 24: 0

  LocalVariableTable: 
   Start  Length  Slot  Name   Signature
   0      9      0    $this       Lscala/collection/generic/MutableVectorTemplate;


}

