Compiled from "MutableVectorView.scala"
public final class scala.collection.generic.MutableVectorView$$anon$1 extends java.lang.Object implements scala.collection.generic.BuilderFactory
  SourceFile: "MutableVectorView.scala"
  Signature: length = 0x2
   00 1F 
  Scala: length = 0x
   
  InnerClass: 
   public final #36= #16 of #35; //$anon$1=class scala/collection/generic/MutableVectorView$$anon$1 of class scala/collection/generic/MutableVectorView
   public #37= #26 of #14; //NoBuilder=class scala/collection/generic/TraversableView$NoBuilder of class scala/collection/generic/TraversableView
  minor version: 0
  major version: 49
  Constant pool:
const #1 = Asciz	SourceFile;
const #2 = Asciz	MutableVectorView.scala;
const #3 = Asciz	<init>;
const #4 = Asciz	()V;
const #5 = Asciz	Code;
const #6 = Asciz	LineNumberTable;
const #7 = Asciz	java/lang/Object;
const #8 = class	#7;	//  java/lang/Object
const #9 = NameAndType	#3:#4;//  "<init>":()V
const #10 = Method	#8.#9;	//  java/lang/Object."<init>":()V
const #11 = Asciz	apply;
const #12 = Asciz	(Ljava/lang/Object;)Lscala/collection/generic/Builder;;
const #13 = Asciz	scala/collection/generic/TraversableView;
const #14 = class	#13;	//  scala/collection/generic/TraversableView
const #15 = Asciz	scala/collection/generic/MutableVectorView$$anon$1;
const #16 = class	#15;	//  scala/collection/generic/MutableVectorView$$anon$1
const #17 = Asciz	(Lscala/collection/generic/TraversableView;)Lscala/collection/generic/TraversableView$NoBuilder;;
const #18 = NameAndType	#11:#17;//  apply:(Lscala/collection/generic/TraversableView;)Lscala/collection/generic/TraversableView$NoBuilder;
const #19 = Method	#16.#18;	//  scala/collection/generic/MutableVectorView$$anon$1.apply:(Lscala/collection/generic/TraversableView;)Lscala/collection/generic/TraversableView$NoBuilder;
const #20 = Asciz	this;
const #21 = Asciz	Lscala/collection/generic/MutableVectorView$$anon$1;;
const #22 = Asciz	from;
const #23 = Asciz	Ljava/lang/Object;;
const #24 = Asciz	LocalVariableTable;
const #25 = Asciz	scala/collection/generic/TraversableView$NoBuilder;
const #26 = class	#25;	//  scala/collection/generic/TraversableView$NoBuilder
const #27 = Method	#26.#9;	//  scala/collection/generic/TraversableView$NoBuilder."<init>":()V
const #28 = Asciz	Lscala/collection/generic/TraversableView;;
const #29 = Asciz	(Lscala/collection/generic/TraversableView<**>;)Lscala/collection/generic/TraversableView$NoBuilder<TA;>;;
const #30 = Asciz	Signature;
const #31 = Asciz	Ljava/lang/Object;Lscala/collection/generic/BuilderFactory<TA;Lscala/collection/generic/MutableVectorView<TA;Lscala/collection/mutable/Vector<*>;>;Lscala/collection/generic/TraversableView<**>;>;;
const #32 = Asciz	Scala;
const #33 = Asciz	InnerClasses;
const #34 = Asciz	scala/collection/generic/MutableVectorView;
const #35 = class	#34;	//  scala/collection/generic/MutableVectorView
const #36 = Asciz	$anon$1;
const #37 = Asciz	NoBuilder;
const #38 = Asciz	scala/collection/generic/BuilderFactory;
const #39 = class	#38;	//  scala/collection/generic/BuilderFactory

{
public scala.collection.generic.MutableVectorView$$anon$1();
  Code:
   Stack=1, Locals=1, Args_size=1
   0:	aload_0
   1:	invokespecial	#10; //Method java/lang/Object."<init>":()V
   4:	return
  LineNumberTable: 
   line 26: 0


public scala.collection.generic.Builder apply(java.lang.Object);
  Code:
   Stack=2, Locals=2, Args_size=2
   0:	aload_0
   1:	aload_1
   2:	checkcast	#14; //class scala/collection/generic/TraversableView
   5:	invokevirtual	#19; //Method apply:(Lscala/collection/generic/TraversableView;)Lscala/collection/generic/TraversableView$NoBuilder;
   8:	areturn
  LineNumberTable: 
   line 26: 0

  LocalVariableTable: 
   Start  Length  Slot  Name   Signature
   0      9      0    this       Lscala/collection/generic/MutableVectorView$$anon$1;
   0      9      1    from       Ljava/lang/Object;


public scala.collection.generic.TraversableView$NoBuilder apply(scala.collection.generic.TraversableView);
  Code:
   Stack=2, Locals=2, Args_size=2
   0:	new	#26; //class scala/collection/generic/TraversableView$NoBuilder
   3:	dup
   4:	invokespecial	#27; //Method scala/collection/generic/TraversableView$NoBuilder."<init>":()V
   7:	areturn
  LineNumberTable: 
   line 26: 0

  LocalVariableTable: 
   Start  Length  Slot  Name   Signature
   0      8      0    this       Lscala/collection/generic/MutableVectorView$$anon$1;
   0      8      1    from       Lscala/collection/generic/TraversableView;

  Signature: length = 0x2
   00 1D 

}

