Compiled from "MutableVectorViewTemplate.scala"
public abstract class scala.collection.generic.MutableVectorViewTemplate$class extends java.lang.Object
  SourceFile: "MutableVectorViewTemplate.scala"
  Scala: length = 0x
   
  InnerClass: 
   public final #50= #20 of #49; //$anon$4=class scala/collection/generic/MutableVectorViewTemplate$$anon$4 of class scala/collection/generic/MutableVectorViewTemplate
   public final #51= #34 of #49; //$anon$2=class scala/collection/generic/MutableVectorViewTemplate$$anon$2 of class scala/collection/generic/MutableVectorViewTemplate
   public final #52= #28 of #49; //$anon$3=class scala/collection/generic/MutableVectorViewTemplate$$anon$3 of class scala/collection/generic/MutableVectorViewTemplate
   public final #53= #13 of #49; //$anon$5=class scala/collection/generic/MutableVectorViewTemplate$$anon$5 of class scala/collection/generic/MutableVectorViewTemplate
   public final #54= #43 of #49; //$anon$1=class scala/collection/generic/MutableVectorViewTemplate$$anon$1 of class scala/collection/generic/MutableVectorViewTemplate
   public abstract #57= #56 of #49; //Transformed=class scala/collection/generic/MutableVectorViewTemplate$Transformed of class scala/collection/generic/MutableVectorViewTemplate
  minor version: 0
  major version: 49
  Constant pool:
const #1 = Asciz	SourceFile;
const #2 = Asciz	MutableVectorViewTemplate.scala;
const #3 = Asciz	$init$;
const #4 = Asciz	(Lscala/collection/generic/MutableVectorViewTemplate;)V;
const #5 = Asciz	Code;
const #6 = Asciz	LineNumberTable;
const #7 = Asciz	$this;
const #8 = Asciz	Lscala/collection/generic/MutableVectorViewTemplate;;
const #9 = Asciz	LocalVariableTable;
const #10 = Asciz	newReversed;
const #11 = Asciz	(Lscala/collection/generic/MutableVectorViewTemplate;)Lscala/collection/generic/MutableVectorViewTemplate$Transformed;;
const #12 = Asciz	scala/collection/generic/MutableVectorViewTemplate$$anon$5;
const #13 = class	#12;	//  scala/collection/generic/MutableVectorViewTemplate$$anon$5
const #14 = Asciz	<init>;
const #15 = NameAndType	#14:#4;//  "<init>":(Lscala/collection/generic/MutableVectorViewTemplate;)V
const #16 = Method	#13.#15;	//  scala/collection/generic/MutableVectorViewTemplate$$anon$5."<init>":(Lscala/collection/generic/MutableVectorViewTemplate;)V
const #17 = Asciz	newTakenWhile;
const #18 = Asciz	(Lscala/collection/generic/MutableVectorViewTemplate;Lscala/Function1;)Lscala/collection/generic/MutableVectorViewTemplate$Transformed;;
const #19 = Asciz	scala/collection/generic/MutableVectorViewTemplate$$anon$4;
const #20 = class	#19;	//  scala/collection/generic/MutableVectorViewTemplate$$anon$4
const #21 = Asciz	(Lscala/collection/generic/MutableVectorViewTemplate;Lscala/Function1;)V;
const #22 = NameAndType	#14:#21;//  "<init>":(Lscala/collection/generic/MutableVectorViewTemplate;Lscala/Function1;)V
const #23 = Method	#20.#22;	//  scala/collection/generic/MutableVectorViewTemplate$$anon$4."<init>":(Lscala/collection/generic/MutableVectorViewTemplate;Lscala/Function1;)V
const #24 = Asciz	p$3;
const #25 = Asciz	Lscala/Function1;;
const #26 = Asciz	newDroppedWhile;
const #27 = Asciz	scala/collection/generic/MutableVectorViewTemplate$$anon$3;
const #28 = class	#27;	//  scala/collection/generic/MutableVectorViewTemplate$$anon$3
const #29 = Method	#28.#22;	//  scala/collection/generic/MutableVectorViewTemplate$$anon$3."<init>":(Lscala/collection/generic/MutableVectorViewTemplate;Lscala/Function1;)V
const #30 = Asciz	p$2;
const #31 = Asciz	newSliced;
const #32 = Asciz	(Lscala/collection/generic/MutableVectorViewTemplate;II)Lscala/collection/generic/MutableVectorViewTemplate$Transformed;;
const #33 = Asciz	scala/collection/generic/MutableVectorViewTemplate$$anon$2;
const #34 = class	#33;	//  scala/collection/generic/MutableVectorViewTemplate$$anon$2
const #35 = Asciz	(Lscala/collection/generic/MutableVectorViewTemplate;II)V;
const #36 = NameAndType	#14:#35;//  "<init>":(Lscala/collection/generic/MutableVectorViewTemplate;II)V
const #37 = Method	#34.#36;	//  scala/collection/generic/MutableVectorViewTemplate$$anon$2."<init>":(Lscala/collection/generic/MutableVectorViewTemplate;II)V
const #38 = Asciz	_from$1;
const #39 = Asciz	I;
const #40 = Asciz	_until$1;
const #41 = Asciz	newFiltered;
const #42 = Asciz	scala/collection/generic/MutableVectorViewTemplate$$anon$1;
const #43 = class	#42;	//  scala/collection/generic/MutableVectorViewTemplate$$anon$1
const #44 = Method	#43.#22;	//  scala/collection/generic/MutableVectorViewTemplate$$anon$1."<init>":(Lscala/collection/generic/MutableVectorViewTemplate;Lscala/Function1;)V
const #45 = Asciz	p$1;
const #46 = Asciz	Scala;
const #47 = Asciz	InnerClasses;
const #48 = Asciz	scala/collection/generic/MutableVectorViewTemplate;
const #49 = class	#48;	//  scala/collection/generic/MutableVectorViewTemplate
const #50 = Asciz	$anon$4;
const #51 = Asciz	$anon$2;
const #52 = Asciz	$anon$3;
const #53 = Asciz	$anon$5;
const #54 = Asciz	$anon$1;
const #55 = Asciz	scala/collection/generic/MutableVectorViewTemplate$Transformed;
const #56 = class	#55;	//  scala/collection/generic/MutableVectorViewTemplate$Transformed
const #57 = Asciz	Transformed;
const #58 = Asciz	scala/collection/generic/MutableVectorViewTemplate$class;
const #59 = class	#58;	//  scala/collection/generic/MutableVectorViewTemplate$class
const #60 = Asciz	java/lang/Object;
const #61 = class	#60;	//  java/lang/Object

{
public static void $init$(scala.collection.generic.MutableVectorViewTemplate);
  Code:
   Stack=0, Locals=1, Args_size=1
   0:	return
  LineNumberTable: 
   line 25: 0

  LocalVariableTable: 
   Start  Length  Slot  Name   Signature
   0      1      0    $this       Lscala/collection/generic/MutableVectorViewTemplate;


public static scala.collection.generic.MutableVectorViewTemplate$Transformed newReversed(scala.collection.generic.MutableVectorViewTemplate);
  Code:
   Stack=3, Locals=1, Args_size=1
   0:	new	#13; //class scala/collection/generic/MutableVectorViewTemplate$$anon$5
   3:	dup
   4:	aload_0
   5:	invokespecial	#16; //Method scala/collection/generic/MutableVectorViewTemplate$$anon$5."<init>":(Lscala/collection/generic/MutableVectorViewTemplate;)V
   8:	areturn
  LineNumberTable: 
   line 65: 0

  LocalVariableTable: 
   Start  Length  Slot  Name   Signature
   0      9      0    $this       Lscala/collection/generic/MutableVectorViewTemplate;


public static scala.collection.generic.MutableVectorViewTemplate$Transformed newTakenWhile(scala.collection.generic.MutableVectorViewTemplate, scala.Function1);
  Code:
   Stack=4, Locals=2, Args_size=2
   0:	new	#20; //class scala/collection/generic/MutableVectorViewTemplate$$anon$4
   3:	dup
   4:	aload_0
   5:	aload_1
   6:	invokespecial	#23; //Method scala/collection/generic/MutableVectorViewTemplate$$anon$4."<init>":(Lscala/collection/generic/MutableVectorViewTemplate;Lscala/Function1;)V
   9:	areturn
  LineNumberTable: 
   line 64: 0

  LocalVariableTable: 
   Start  Length  Slot  Name   Signature
   0      10      0    $this       Lscala/collection/generic/MutableVectorViewTemplate;
   0      10      1    p$3       Lscala/Function1;


public static scala.collection.generic.MutableVectorViewTemplate$Transformed newDroppedWhile(scala.collection.generic.MutableVectorViewTemplate, scala.Function1);
  Code:
   Stack=4, Locals=2, Args_size=2
   0:	new	#28; //class scala/collection/generic/MutableVectorViewTemplate$$anon$3
   3:	dup
   4:	aload_0
   5:	aload_1
   6:	invokespecial	#29; //Method scala/collection/generic/MutableVectorViewTemplate$$anon$3."<init>":(Lscala/collection/generic/MutableVectorViewTemplate;Lscala/Function1;)V
   9:	areturn
  LineNumberTable: 
   line 63: 0

  LocalVariableTable: 
   Start  Length  Slot  Name   Signature
   0      10      0    $this       Lscala/collection/generic/MutableVectorViewTemplate;
   0      10      1    p$2       Lscala/Function1;


public static scala.collection.generic.MutableVectorViewTemplate$Transformed newSliced(scala.collection.generic.MutableVectorViewTemplate, int, int);
  Code:
   Stack=5, Locals=3, Args_size=3
   0:	new	#34; //class scala/collection/generic/MutableVectorViewTemplate$$anon$2
   3:	dup
   4:	aload_0
   5:	iload_1
   6:	iload_2
   7:	invokespecial	#37; //Method scala/collection/generic/MutableVectorViewTemplate$$anon$2."<init>":(Lscala/collection/generic/MutableVectorViewTemplate;II)V
   10:	areturn
  LineNumberTable: 
   line 62: 0

  LocalVariableTable: 
   Start  Length  Slot  Name   Signature
   0      11      0    $this       Lscala/collection/generic/MutableVectorViewTemplate;
   0      11      1    _from$1       I
   0      11      2    _until$1       I


public static scala.collection.generic.MutableVectorViewTemplate$Transformed newFiltered(scala.collection.generic.MutableVectorViewTemplate, scala.Function1);
  Code:
   Stack=4, Locals=2, Args_size=2
   0:	new	#43; //class scala/collection/generic/MutableVectorViewTemplate$$anon$1
   3:	dup
   4:	aload_0
   5:	aload_1
   6:	invokespecial	#44; //Method scala/collection/generic/MutableVectorViewTemplate$$anon$1."<init>":(Lscala/collection/generic/MutableVectorViewTemplate;Lscala/Function1;)V
   9:	areturn
  LineNumberTable: 
   line 61: 0

  LocalVariableTable: 
   Start  Length  Slot  Name   Signature
   0      10      0    $this       Lscala/collection/generic/MutableVectorViewTemplate;
   0      10      1    p$1       Lscala/Function1;


}

