Compiled from "MutableVectorViewTemplate.scala"
public abstract class scala.collection.generic.MutableVectorViewTemplate$Filtered$class extends java.lang.Object
  SourceFile: "MutableVectorViewTemplate.scala"
  Scala: length = 0x
   
  InnerClass: 
   public abstract #37= #19 of #36; //Filtered=class scala/collection/generic/SequenceViewTemplate$Filtered of class scala/collection/generic/SequenceViewTemplate
   public abstract #37= #13 of #39; //Filtered=class scala/collection/generic/MutableVectorViewTemplate$Filtered of class scala/collection/generic/MutableVectorViewTemplate
  minor version: 0
  major version: 49
  Constant pool:
const #1 = Asciz	SourceFile;
const #2 = Asciz	MutableVectorViewTemplate.scala;
const #3 = Asciz	$init$;
const #4 = Asciz	(Lscala/collection/generic/MutableVectorViewTemplate$Filtered;)V;
const #5 = Asciz	Code;
const #6 = Asciz	LineNumberTable;
const #7 = Asciz	$this;
const #8 = Asciz	Lscala/collection/generic/MutableVectorViewTemplate$Filtered;;
const #9 = Asciz	LocalVariableTable;
const #10 = Asciz	update;
const #11 = Asciz	(Lscala/collection/generic/MutableVectorViewTemplate$Filtered;ILjava/lang/Object;)V;
const #12 = Asciz	scala/collection/generic/MutableVectorViewTemplate$Filtered;
const #13 = class	#12;	//  scala/collection/generic/MutableVectorViewTemplate$Filtered
const #14 = Asciz	scala$collection$generic$MutableVectorViewTemplate$Filtered$$$outer;
const #15 = Asciz	()Lscala/collection/generic/MutableVectorViewTemplate;;
const #16 = NameAndType	#14:#15;//  scala$collection$generic$MutableVectorViewTemplate$Filtered$$$outer:()Lscala/collection/generic/MutableVectorViewTemplate;
const #17 = InterfaceMethod	#13.#16;	//  scala/collection/generic/MutableVectorViewTemplate$Filtered.scala$collection$generic$MutableVectorViewTemplate$Filtered$$$outer:()Lscala/collection/generic/MutableVectorViewTemplate;
const #18 = Asciz	scala/collection/generic/SequenceViewTemplate$Filtered;
const #19 = class	#18;	//  scala/collection/generic/SequenceViewTemplate$Filtered
const #20 = Asciz	index;
const #21 = Asciz	()[I;
const #22 = NameAndType	#20:#21;//  index:()[I
const #23 = InterfaceMethod	#19.#22;	//  scala/collection/generic/SequenceViewTemplate$Filtered.index:()[I
const #24 = Asciz	scala/collection/generic/MutableVectorTemplate;
const #25 = class	#24;	//  scala/collection/generic/MutableVectorTemplate
const #26 = Asciz	(ILjava/lang/Object;)V;
const #27 = NameAndType	#10:#26;//  update:(ILjava/lang/Object;)V
const #28 = InterfaceMethod	#25.#27;	//  scala/collection/generic/MutableVectorTemplate.update:(ILjava/lang/Object;)V
const #29 = Asciz	idx;
const #30 = Asciz	I;
const #31 = Asciz	elem;
const #32 = Asciz	Ljava/lang/Object;;
const #33 = Asciz	Scala;
const #34 = Asciz	InnerClasses;
const #35 = Asciz	scala/collection/generic/SequenceViewTemplate;
const #36 = class	#35;	//  scala/collection/generic/SequenceViewTemplate
const #37 = Asciz	Filtered;
const #38 = Asciz	scala/collection/generic/MutableVectorViewTemplate;
const #39 = class	#38;	//  scala/collection/generic/MutableVectorViewTemplate
const #40 = Asciz	scala/collection/generic/MutableVectorViewTemplate$Filtered$class;
const #41 = class	#40;	//  scala/collection/generic/MutableVectorViewTemplate$Filtered$class
const #42 = Asciz	java/lang/Object;
const #43 = class	#42;	//  java/lang/Object

{
public static void $init$(scala.collection.generic.MutableVectorViewTemplate$Filtered);
  Code:
   Stack=0, Locals=1, Args_size=1
   0:	return
  LineNumberTable: 
   line 38: 0

  LocalVariableTable: 
   Start  Length  Slot  Name   Signature
   0      1      0    $this       Lscala/collection/generic/MutableVectorViewTemplate$Filtered;


public static void update(scala.collection.generic.MutableVectorViewTemplate$Filtered, int, java.lang.Object);
  Code:
   Stack=3, Locals=3, Args_size=3
   0:	aload_0
   1:	invokeinterface	#17,  1; //InterfaceMethod scala/collection/generic/MutableVectorViewTemplate$Filtered.scala$collection$generic$MutableVectorViewTemplate$Filtered$$$outer:()Lscala/collection/generic/MutableVectorViewTemplate;
   6:	aload_0
   7:	invokeinterface	#23,  1; //InterfaceMethod scala/collection/generic/SequenceViewTemplate$Filtered.index:()[I
   12:	iload_1
   13:	iaload
   14:	aload_2
   15:	invokeinterface	#28,  3; //InterfaceMethod scala/collection/generic/MutableVectorTemplate.update:(ILjava/lang/Object;)V
   20:	return
  LineNumberTable: 
   line 39: 0

  LocalVariableTable: 
   Start  Length  Slot  Name   Signature
   0      21      0    $this       Lscala/collection/generic/MutableVectorViewTemplate$Filtered;
   0      21      1    idx       I
   0      21      2    elem       Ljava/lang/Object;


}

