Compiled from "MutableMapTemplate.scala"
public abstract class scala.collection.generic.MutableMapTemplate$class extends java.lang.Object
  SourceFile: "MutableMapTemplate.scala"
  Scala: length = 0x
   
  InnerClass: 
   public final #209= #151 of #30; //$anonfun$clear$1=class scala/collection/generic/MutableMapTemplate$$anonfun$clear$1 of class scala/collection/generic/MutableMapTemplate
   public final #210= #78 of #30; //$anonfun$retain$1=class scala/collection/generic/MutableMapTemplate$$anonfun$retain$1 of class scala/collection/generic/MutableMapTemplate
   public final #211= #93 of #30; //$anonfun$transform$1=class scala/collection/generic/MutableMapTemplate$$anonfun$transform$1 of class scala/collection/generic/MutableMapTemplate
   public final #212= #162 of #30; //$anonfun$$plus$plus$2=class scala/collection/generic/MutableMapTemplate$$anonfun$$plus$plus$2 of class scala/collection/generic/MutableMapTemplate
   public final #213= #165 of #30; //$anonfun$$plus$plus$1=class scala/collection/generic/MutableMapTemplate$$anonfun$$plus$plus$1 of class scala/collection/generic/MutableMapTemplate
   public final #214= #35 of #30; //$anonfun$$minus$minus$1=class scala/collection/generic/MutableMapTemplate$$anonfun$$minus$minus$1 of class scala/collection/generic/MutableMapTemplate
   public final #215= #13 of #30; //$anonfun$$minus$minus$2=class scala/collection/generic/MutableMapTemplate$$anonfun$$minus$minus$2 of class scala/collection/generic/MutableMapTemplate
  minor version: 0
  major version: 49
  Constant pool:
const #1 = Asciz	SourceFile;
const #2 = Asciz	MutableMapTemplate.scala;
const #3 = Asciz	$init$;
const #4 = Asciz	(Lscala/collection/generic/MutableMapTemplate;)V;
const #5 = Asciz	Code;
const #6 = Asciz	LineNumberTable;
const #7 = Asciz	$this;
const #8 = Asciz	Lscala/collection/generic/MutableMapTemplate;;
const #9 = Asciz	LocalVariableTable;
const #10 = Asciz	$minus$minus;
const #11 = Asciz	(Lscala/collection/generic/MutableMapTemplate;Lscala/collection/Iterator;)Lscala/collection/generic/MutableMapTemplate;;
const #12 = Asciz	scala/collection/generic/MutableMapTemplate$$anonfun$$minus$minus$2;
const #13 = class	#12;	//  scala/collection/generic/MutableMapTemplate$$anonfun$$minus$minus$2
const #14 = Asciz	<init>;
const #15 = NameAndType	#14:#4;//  "<init>":(Lscala/collection/generic/MutableMapTemplate;)V
const #16 = Method	#13.#15;	//  scala/collection/generic/MutableMapTemplate$$anonfun$$minus$minus$2."<init>":(Lscala/collection/generic/MutableMapTemplate;)V
const #17 = Asciz	scala/collection/Iterator;
const #18 = class	#17;	//  scala/collection/Iterator
const #19 = Asciz	foreach;
const #20 = Asciz	(Lscala/Function1;)V;
const #21 = NameAndType	#19:#20;//  foreach:(Lscala/Function1;)V
const #22 = InterfaceMethod	#18.#21;	//  scala/collection/Iterator.foreach:(Lscala/Function1;)V
const #23 = Asciz	scala/collection/generic/TraversableTemplate;
const #24 = class	#23;	//  scala/collection/generic/TraversableTemplate
const #25 = Asciz	thisCollection;
const #26 = Asciz	()Lscala/collection/generic/TraversableTemplate;;
const #27 = NameAndType	#25:#26;//  thisCollection:()Lscala/collection/generic/TraversableTemplate;
const #28 = InterfaceMethod	#24.#27;	//  scala/collection/generic/TraversableTemplate.thisCollection:()Lscala/collection/generic/TraversableTemplate;
const #29 = Asciz	scala/collection/generic/MutableMapTemplate;
const #30 = class	#29;	//  scala/collection/generic/MutableMapTemplate
const #31 = Asciz	iter;
const #32 = Asciz	Lscala/collection/Iterator;;
const #33 = Asciz	(Lscala/collection/generic/MutableMapTemplate;Lscala/collection/Traversable;)Lscala/collection/generic/MutableMapTemplate;;
const #34 = Asciz	scala/collection/generic/MutableMapTemplate$$anonfun$$minus$minus$1;
const #35 = class	#34;	//  scala/collection/generic/MutableMapTemplate$$anonfun$$minus$minus$1
const #36 = Method	#35.#15;	//  scala/collection/generic/MutableMapTemplate$$anonfun$$minus$minus$1."<init>":(Lscala/collection/generic/MutableMapTemplate;)V
const #37 = Asciz	scala/collection/generic/TraversableClass;
const #38 = class	#37;	//  scala/collection/generic/TraversableClass
const #39 = InterfaceMethod	#38.#21;	//  scala/collection/generic/TraversableClass.foreach:(Lscala/Function1;)V
const #40 = Asciz	Lscala/collection/Traversable;;
const #41 = Asciz	$minus;
const #42 = Asciz	(Lscala/collection/generic/MutableMapTemplate;Ljava/lang/Object;Ljava/lang/Object;Lscala/collection/Sequence;)Lscala/collection/generic/MutableMapTemplate;;
const #43 = Asciz	$minus$eq;
const #44 = Asciz	(Ljava/lang/Object;)Lscala/collection/generic/MutableMapTemplate;;
const #45 = NameAndType	#43:#44;//  $minus$eq:(Ljava/lang/Object;)Lscala/collection/generic/MutableMapTemplate;
const #46 = InterfaceMethod	#30.#45;	//  scala/collection/generic/MutableMapTemplate.$minus$eq:(Ljava/lang/Object;)Lscala/collection/generic/MutableMapTemplate;
const #47 = Asciz	scala/collection/generic/Shrinkable;
const #48 = class	#47;	//  scala/collection/generic/Shrinkable
const #49 = Asciz	$minus$minus$eq;
const #50 = Asciz	(Lscala/collection/Traversable;)Lscala/collection/generic/Shrinkable;;
const #51 = NameAndType	#49:#50;//  $minus$minus$eq:(Lscala/collection/Traversable;)Lscala/collection/generic/Shrinkable;
const #52 = InterfaceMethod	#48.#51;	//  scala/collection/generic/Shrinkable.$minus$minus$eq:(Lscala/collection/Traversable;)Lscala/collection/generic/Shrinkable;
const #53 = Asciz	elem1;
const #54 = Asciz	Ljava/lang/Object;;
const #55 = Asciz	elem2;
const #56 = Asciz	elems;
const #57 = Asciz	Lscala/collection/Sequence;;
const #58 = Asciz	result;
const #59 = Asciz	(Lscala/collection/generic/MutableMapTemplate;)Lscala/collection/generic/MutableMapTemplate;;
const #60 = Asciz	clone;
const #61 = Asciz	scala/collection/generic/MapTemplate;
const #62 = class	#61;	//  scala/collection/generic/MapTemplate
const #63 = Asciz	empty;
const #64 = Asciz	()Lscala/collection/generic/MapTemplate;;
const #65 = NameAndType	#63:#64;//  empty:()Lscala/collection/generic/MapTemplate;
const #66 = InterfaceMethod	#62.#65;	//  scala/collection/generic/MapTemplate.empty:()Lscala/collection/generic/MapTemplate;
const #67 = Asciz	scala/collection/generic/Growable;
const #68 = class	#67;	//  scala/collection/generic/Growable
const #69 = Asciz	scala/collection/Traversable;
const #70 = class	#69;	//  scala/collection/Traversable
const #71 = Asciz	$plus$plus$eq;
const #72 = Asciz	(Lscala/collection/Traversable;)Lscala/collection/generic/Growable;;
const #73 = NameAndType	#71:#72;//  $plus$plus$eq:(Lscala/collection/Traversable;)Lscala/collection/generic/Growable;
const #74 = InterfaceMethod	#68.#73;	//  scala/collection/generic/Growable.$plus$plus$eq:(Lscala/collection/Traversable;)Lscala/collection/generic/Growable;
const #75 = Asciz	retain;
const #76 = Asciz	(Lscala/collection/generic/MutableMapTemplate;Lscala/Function2;)Lscala/collection/generic/MutableMapTemplate;;
const #77 = Asciz	scala/collection/generic/MutableMapTemplate$$anonfun$retain$1;
const #78 = class	#77;	//  scala/collection/generic/MutableMapTemplate$$anonfun$retain$1
const #79 = Asciz	(Lscala/collection/generic/MutableMapTemplate;Lscala/Function2;)V;
const #80 = NameAndType	#14:#79;//  "<init>":(Lscala/collection/generic/MutableMapTemplate;Lscala/Function2;)V
const #81 = Method	#78.#80;	//  scala/collection/generic/MutableMapTemplate$$anonfun$retain$1."<init>":(Lscala/collection/generic/MutableMapTemplate;Lscala/Function2;)V
const #82 = Asciz	scala/collection/generic/IterableTemplate;
const #83 = class	#82;	//  scala/collection/generic/IterableTemplate
const #84 = InterfaceMethod	#83.#21;	//  scala/collection/generic/IterableTemplate.foreach:(Lscala/Function1;)V
const #85 = Asciz	p$1;
const #86 = Asciz	Lscala/Function2;;
const #87 = Asciz	transform;
const #88 = Asciz	iterator;
const #89 = Asciz	()Lscala/collection/Iterator;;
const #90 = NameAndType	#88:#89;//  iterator:()Lscala/collection/Iterator;
const #91 = InterfaceMethod	#62.#90;	//  scala/collection/generic/MapTemplate.iterator:()Lscala/collection/Iterator;
const #92 = Asciz	scala/collection/generic/MutableMapTemplate$$anonfun$transform$1;
const #93 = class	#92;	//  scala/collection/generic/MutableMapTemplate$$anonfun$transform$1
const #94 = Method	#93.#80;	//  scala/collection/generic/MutableMapTemplate$$anonfun$transform$1."<init>":(Lscala/collection/generic/MutableMapTemplate;Lscala/Function2;)V
const #95 = Asciz	f$1;
const #96 = Asciz	getOrElseUpdate;
const #97 = Asciz	(Lscala/collection/generic/MutableMapTemplate;Ljava/lang/Object;Lscala/Function0;)Ljava/lang/Object;;
const #98 = Asciz	get;
const #99 = Asciz	(Ljava/lang/Object;)Lscala/Option;;
const #100 = NameAndType	#98:#99;//  get:(Ljava/lang/Object;)Lscala/Option;
const #101 = InterfaceMethod	#62.#100;	//  scala/collection/generic/MapTemplate.get:(Ljava/lang/Object;)Lscala/Option;
const #102 = Asciz	scala/Some;
const #103 = class	#102;	//  scala/Some
const #104 = Asciz	x;
const #105 = Asciz	()Ljava/lang/Object;;
const #106 = NameAndType	#104:#105;//  x:()Ljava/lang/Object;
const #107 = Method	#103.#106;	//  scala/Some.x:()Ljava/lang/Object;
const #108 = Asciz	scala/None$;
const #109 = class	#108;	//  scala/None$
const #110 = Asciz	MODULE$;
const #111 = Asciz	Lscala/None$;;
const #112 = NameAndType	#110:#111;//  MODULE$:Lscala/None$;
const #113 = Field	#109.#112;	//  scala/None$.MODULE$:Lscala/None$;
const #114 = Asciz	java/lang/Object;
const #115 = class	#114;	//  java/lang/Object
const #116 = Asciz	equals;
const #117 = Asciz	(Ljava/lang/Object;)Z;
const #118 = NameAndType	#116:#117;//  equals:(Ljava/lang/Object;)Z
const #119 = Method	#115.#118;	//  java/lang/Object.equals:(Ljava/lang/Object;)Z
const #120 = Asciz	scala/Function0;
const #121 = class	#120;	//  scala/Function0
const #122 = Asciz	apply;
const #123 = NameAndType	#122:#105;//  apply:()Ljava/lang/Object;
const #124 = InterfaceMethod	#121.#123;	//  scala/Function0.apply:()Ljava/lang/Object;
const #125 = Asciz	update;
const #126 = Asciz	(Ljava/lang/Object;Ljava/lang/Object;)V;
const #127 = NameAndType	#125:#126;//  update:(Ljava/lang/Object;Ljava/lang/Object;)V
const #128 = InterfaceMethod	#30.#127;	//  scala/collection/generic/MutableMapTemplate.update:(Ljava/lang/Object;Ljava/lang/Object;)V
const #129 = Asciz	scala/MatchError;
const #130 = class	#129;	//  scala/MatchError
const #131 = Asciz	scala/Option;
const #132 = class	#131;	//  scala/Option
const #133 = Asciz	toString;
const #134 = Asciz	()Ljava/lang/String;;
const #135 = NameAndType	#133:#134;//  toString:()Ljava/lang/String;
const #136 = Method	#132.#135;	//  scala/Option.toString:()Ljava/lang/String;
const #137 = Asciz	(Ljava/lang/String;)V;
const #138 = NameAndType	#14:#137;//  "<init>":(Ljava/lang/String;)V
const #139 = Method	#130.#138;	//  scala/MatchError."<init>":(Ljava/lang/String;)V
const #140 = Asciz	key;
const #141 = Asciz	default;
const #142 = Asciz	Lscala/Function0;;
const #143 = Asciz	temp8;
const #144 = Asciz	Lscala/Option;;
const #145 = Asciz	temp9;
const #146 = Asciz	Lscala/Some;;
const #147 = Asciz	temp10;
const #148 = Asciz	d;
const #149 = Asciz	clear;
const #150 = Asciz	scala/collection/generic/MutableMapTemplate$$anonfun$clear$1;
const #151 = class	#150;	//  scala/collection/generic/MutableMapTemplate$$anonfun$clear$1
const #152 = Method	#151.#15;	//  scala/collection/generic/MutableMapTemplate$$anonfun$clear$1."<init>":(Lscala/collection/generic/MutableMapTemplate;)V
const #153 = Asciz	removeKey;
const #154 = Asciz	(Lscala/collection/generic/MutableMapTemplate;Ljava/lang/Object;)Lscala/Option;;
const #155 = Asciz	remove;
const #156 = NameAndType	#155:#99;//  remove:(Ljava/lang/Object;)Lscala/Option;
const #157 = InterfaceMethod	#30.#156;	//  scala/collection/generic/MutableMapTemplate.remove:(Ljava/lang/Object;)Lscala/Option;
const #158 = Asciz	(Lscala/collection/generic/MutableMapTemplate;Ljava/lang/Object;)Lscala/collection/generic/MutableMapTemplate;;
const #159 = Asciz	r;
const #160 = Asciz	$plus$plus;
const #161 = Asciz	scala/collection/generic/MutableMapTemplate$$anonfun$$plus$plus$2;
const #162 = class	#161;	//  scala/collection/generic/MutableMapTemplate$$anonfun$$plus$plus$2
const #163 = Method	#162.#15;	//  scala/collection/generic/MutableMapTemplate$$anonfun$$plus$plus$2."<init>":(Lscala/collection/generic/MutableMapTemplate;)V
const #164 = Asciz	scala/collection/generic/MutableMapTemplate$$anonfun$$plus$plus$1;
const #165 = class	#164;	//  scala/collection/generic/MutableMapTemplate$$anonfun$$plus$plus$1
const #166 = Method	#165.#15;	//  scala/collection/generic/MutableMapTemplate$$anonfun$$plus$plus$1."<init>":(Lscala/collection/generic/MutableMapTemplate;)V
const #167 = Asciz	$plus;
const #168 = Asciz	(Lscala/collection/generic/MutableMapTemplate;Lscala/Tuple2;Lscala/Tuple2;Lscala/collection/Sequence;)Lscala/collection/generic/MutableMapTemplate;;
const #169 = Asciz	$plus$eq;
const #170 = Asciz	(Lscala/Tuple2;)Lscala/collection/generic/MutableMapTemplate;;
const #171 = NameAndType	#169:#170;//  $plus$eq:(Lscala/Tuple2;)Lscala/collection/generic/MutableMapTemplate;
const #172 = InterfaceMethod	#30.#171;	//  scala/collection/generic/MutableMapTemplate.$plus$eq:(Lscala/Tuple2;)Lscala/collection/generic/MutableMapTemplate;
const #173 = Asciz	Lscala/Tuple2;;
const #174 = Asciz	(Lscala/collection/generic/MutableMapTemplate;Lscala/Tuple2;)Lscala/collection/generic/MutableMapTemplate;;
const #175 = Asciz	scala/Tuple2;
const #176 = class	#175;	//  scala/Tuple2
const #177 = Asciz	_1;
const #178 = NameAndType	#177:#105;//  _1:()Ljava/lang/Object;
const #179 = Method	#176.#178;	//  scala/Tuple2._1:()Ljava/lang/Object;
const #180 = Asciz	_2;
const #181 = NameAndType	#180:#105;//  _2:()Ljava/lang/Object;
const #182 = Method	#176.#181;	//  scala/Tuple2._2:()Ljava/lang/Object;
const #183 = Asciz	kv;
const #184 = Asciz	cached;
const #185 = Asciz	op;
const #186 = Asciz	temp1;
const #187 = Asciz	temp2;
const #188 = Asciz	temp3;
const #189 = Asciz	v;
const #190 = Asciz	updated;
const #191 = Asciz	(Lscala/collection/generic/MutableMapTemplate;Ljava/lang/Object;Ljava/lang/Object;)Lscala/collection/mutable/Map;;
const #192 = NameAndType	#14:#126;//  "<init>":(Ljava/lang/Object;Ljava/lang/Object;)V
const #193 = Method	#176.#192;	//  scala/Tuple2."<init>":(Ljava/lang/Object;Ljava/lang/Object;)V
const #194 = Asciz	scala/collection/generic/MutableMapTemplateBase;
const #195 = class	#194;	//  scala/collection/generic/MutableMapTemplateBase
const #196 = Asciz	(Lscala/Tuple2;)Lscala/collection/mutable/Map;;
const #197 = NameAndType	#167:#196;//  $plus:(Lscala/Tuple2;)Lscala/collection/mutable/Map;
const #198 = InterfaceMethod	#195.#197;	//  scala/collection/generic/MutableMapTemplateBase.$plus:(Lscala/Tuple2;)Lscala/collection/mutable/Map;
const #199 = Asciz	value;
const #200 = Asciz	(Lscala/collection/generic/MutableMapTemplate;Ljava/lang/Object;Ljava/lang/Object;)V;
const #201 = Asciz	put;
const #202 = Asciz	(Lscala/collection/generic/MutableMapTemplate;Ljava/lang/Object;Ljava/lang/Object;)Lscala/Option;;
const #203 = Asciz	newBuilder;
const #204 = Asciz	(Lscala/collection/generic/MutableMapTemplate;)Lscala/collection/generic/Builder;;
const #205 = Asciz	scala/collection/generic/Builder;
const #206 = class	#205;	//  scala/collection/generic/Builder
const #207 = Asciz	Scala;
const #208 = Asciz	InnerClasses;
const #209 = Asciz	$anonfun$clear$1;
const #210 = Asciz	$anonfun$retain$1;
const #211 = Asciz	$anonfun$transform$1;
const #212 = Asciz	$anonfun$$plus$plus$2;
const #213 = Asciz	$anonfun$$plus$plus$1;
const #214 = Asciz	$anonfun$$minus$minus$1;
const #215 = Asciz	$anonfun$$minus$minus$2;
const #216 = Asciz	scala/collection/generic/MutableMapTemplate$class;
const #217 = class	#216;	//  scala/collection/generic/MutableMapTemplate$class

{
public static void $init$(scala.collection.generic.MutableMapTemplate);
  Code:
   Stack=0, Locals=1, Args_size=1
   0:	return
  LineNumberTable: 
   line 44: 0

  LocalVariableTable: 
   Start  Length  Slot  Name   Signature
   0      1      0    $this       Lscala/collection/generic/MutableMapTemplate;


public static scala.collection.generic.MutableMapTemplate $minus$minus(scala.collection.generic.MutableMapTemplate, scala.collection.Iterator);
  Code:
   Stack=4, Locals=2, Args_size=2
   0:	aload_1
   1:	new	#13; //class scala/collection/generic/MutableMapTemplate$$anonfun$$minus$minus$2
   4:	dup
   5:	aload_0
   6:	invokespecial	#16; //Method scala/collection/generic/MutableMapTemplate$$anonfun$$minus$minus$2."<init>":(Lscala/collection/generic/MutableMapTemplate;)V
   9:	invokeinterface	#22,  2; //InterfaceMethod scala/collection/Iterator.foreach:(Lscala/Function1;)V
   14:	aload_0
   15:	invokeinterface	#28,  1; //InterfaceMethod scala/collection/generic/TraversableTemplate.thisCollection:()Lscala/collection/generic/TraversableTemplate;
   20:	checkcast	#30; //class scala/collection/generic/MutableMapTemplate
   23:	areturn
  LineNumberTable: 
   line 264: 0
   line 265: 14

  LocalVariableTable: 
   Start  Length  Slot  Name   Signature
   0      24      0    $this       Lscala/collection/generic/MutableMapTemplate;
   0      24      1    iter       Lscala/collection/Iterator;


public static scala.collection.generic.MutableMapTemplate $minus$minus(scala.collection.generic.MutableMapTemplate, scala.collection.Traversable);
  Code:
   Stack=4, Locals=2, Args_size=2
   0:	aload_1
   1:	new	#35; //class scala/collection/generic/MutableMapTemplate$$anonfun$$minus$minus$1
   4:	dup
   5:	aload_0
   6:	invokespecial	#36; //Method scala/collection/generic/MutableMapTemplate$$anonfun$$minus$minus$1."<init>":(Lscala/collection/generic/MutableMapTemplate;)V
   9:	invokeinterface	#39,  2; //InterfaceMethod scala/collection/generic/TraversableClass.foreach:(Lscala/Function1;)V
   14:	aload_0
   15:	invokeinterface	#28,  1; //InterfaceMethod scala/collection/generic/TraversableTemplate.thisCollection:()Lscala/collection/generic/TraversableTemplate;
   20:	checkcast	#30; //class scala/collection/generic/MutableMapTemplate
   23:	areturn
  LineNumberTable: 
   line 251: 0
   line 252: 14

  LocalVariableTable: 
   Start  Length  Slot  Name   Signature
   0      24      0    $this       Lscala/collection/generic/MutableMapTemplate;
   0      24      1    iter       Lscala/collection/Traversable;


public static scala.collection.generic.MutableMapTemplate $minus(scala.collection.generic.MutableMapTemplate, java.lang.Object, java.lang.Object, scala.collection.Sequence);
  Code:
   Stack=2, Locals=4, Args_size=4
   0:	aload_0
   1:	aload_1
   2:	invokeinterface	#46,  2; //InterfaceMethod scala/collection/generic/MutableMapTemplate.$minus$eq:(Ljava/lang/Object;)Lscala/collection/generic/MutableMapTemplate;
   7:	aload_2
   8:	invokeinterface	#46,  2; //InterfaceMethod scala/collection/generic/MutableMapTemplate.$minus$eq:(Ljava/lang/Object;)Lscala/collection/generic/MutableMapTemplate;
   13:	aload_3
   14:	invokeinterface	#52,  2; //InterfaceMethod scala/collection/generic/Shrinkable.$minus$minus$eq:(Lscala/collection/Traversable;)Lscala/collection/generic/Shrinkable;
   19:	pop
   20:	aload_0
   21:	invokeinterface	#28,  1; //InterfaceMethod scala/collection/generic/TraversableTemplate.thisCollection:()Lscala/collection/generic/TraversableTemplate;
   26:	checkcast	#30; //class scala/collection/generic/MutableMapTemplate
   29:	areturn
  LineNumberTable: 
   line 239: 0
   line 240: 20

  LocalVariableTable: 
   Start  Length  Slot  Name   Signature
   0      30      0    $this       Lscala/collection/generic/MutableMapTemplate;
   0      30      1    elem1       Ljava/lang/Object;
   0      30      2    elem2       Ljava/lang/Object;
   0      30      3    elems       Lscala/collection/Sequence;


public static scala.collection.generic.MutableMapTemplate result(scala.collection.generic.MutableMapTemplate);
  Code:
   Stack=1, Locals=1, Args_size=1
   0:	aload_0
   1:	invokeinterface	#28,  1; //InterfaceMethod scala/collection/generic/TraversableTemplate.thisCollection:()Lscala/collection/generic/TraversableTemplate;
   6:	checkcast	#30; //class scala/collection/generic/MutableMapTemplate
   9:	areturn
  LineNumberTable: 
   line 227: 0

  LocalVariableTable: 
   Start  Length  Slot  Name   Signature
   0      10      0    $this       Lscala/collection/generic/MutableMapTemplate;


public static scala.collection.generic.MutableMapTemplate clone(scala.collection.generic.MutableMapTemplate);
  Code:
   Stack=2, Locals=1, Args_size=1
   0:	aload_0
   1:	invokeinterface	#66,  1; //InterfaceMethod scala/collection/generic/MapTemplate.empty:()Lscala/collection/generic/MapTemplate;
   6:	checkcast	#68; //class scala/collection/generic/Growable
   9:	aload_0
   10:	invokeinterface	#28,  1; //InterfaceMethod scala/collection/generic/TraversableTemplate.thisCollection:()Lscala/collection/generic/TraversableTemplate;
   15:	checkcast	#70; //class scala/collection/Traversable
   18:	invokeinterface	#74,  2; //InterfaceMethod scala/collection/generic/Growable.$plus$plus$eq:(Lscala/collection/Traversable;)Lscala/collection/generic/Growable;
   23:	checkcast	#30; //class scala/collection/generic/MutableMapTemplate
   26:	areturn
  LineNumberTable: 
   line 224: 0

  LocalVariableTable: 
   Start  Length  Slot  Name   Signature
   0      27      0    $this       Lscala/collection/generic/MutableMapTemplate;


public static scala.collection.generic.MutableMapTemplate retain(scala.collection.generic.MutableMapTemplate, scala.Function2);
  Code:
   Stack=5, Locals=2, Args_size=2
   0:	aload_0
   1:	new	#78; //class scala/collection/generic/MutableMapTemplate$$anonfun$retain$1
   4:	dup
   5:	aload_0
   6:	aload_1
   7:	invokespecial	#81; //Method scala/collection/generic/MutableMapTemplate$$anonfun$retain$1."<init>":(Lscala/collection/generic/MutableMapTemplate;Lscala/Function2;)V
   10:	invokeinterface	#84,  2; //InterfaceMethod scala/collection/generic/IterableTemplate.foreach:(Lscala/Function1;)V
   15:	aload_0
   16:	areturn
  LineNumberTable: 
   line 219: 0
   line 220: 15

  LocalVariableTable: 
   Start  Length  Slot  Name   Signature
   0      17      0    $this       Lscala/collection/generic/MutableMapTemplate;
   0      17      1    p$1       Lscala/Function2;


public static scala.collection.generic.MutableMapTemplate transform(scala.collection.generic.MutableMapTemplate, scala.Function2);
  Code:
   Stack=5, Locals=2, Args_size=2
   0:	aload_0
   1:	invokeinterface	#91,  1; //InterfaceMethod scala/collection/generic/MapTemplate.iterator:()Lscala/collection/Iterator;
   6:	new	#93; //class scala/collection/generic/MutableMapTemplate$$anonfun$transform$1
   9:	dup
   10:	aload_0
   11:	aload_1
   12:	invokespecial	#94; //Method scala/collection/generic/MutableMapTemplate$$anonfun$transform$1."<init>":(Lscala/collection/generic/MutableMapTemplate;Lscala/Function2;)V
   15:	invokeinterface	#22,  2; //InterfaceMethod scala/collection/Iterator.foreach:(Lscala/Function1;)V
   20:	aload_0
   21:	areturn
  LineNumberTable: 
   line 206: 0
   line 209: 20

  LocalVariableTable: 
   Start  Length  Slot  Name   Signature
   0      22      0    $this       Lscala/collection/generic/MutableMapTemplate;
   0      22      1    f$1       Lscala/Function2;


public static java.lang.Object getOrElseUpdate(scala.collection.generic.MutableMapTemplate, java.lang.Object, scala.Function0);
  Code:
   Stack=3, Locals=8, Args_size=3
   0:	aload_0
   1:	aload_1
   2:	invokeinterface	#101,  2; //InterfaceMethod scala/collection/generic/MapTemplate.get:(Ljava/lang/Object;)Lscala/Option;
   7:	astore_3
   8:	aload_3
   9:	instanceof	#103; //class scala/Some
   12:	ifeq	33
   15:	aload_3
   16:	checkcast	#103; //class scala/Some
   19:	astore	4
   21:	aload	4
   23:	invokevirtual	#107; //Method scala/Some.x:()Ljava/lang/Object;
   26:	astore	5
   28:	aload	5
   30:	goto	86
   33:	getstatic	#113; //Field scala/None$.MODULE$:Lscala/None$;
   36:	aload_3
   37:	astore	6
   39:	dup
   40:	ifnonnull	52
   43:	pop
   44:	aload	6
   46:	ifnull	60
   49:	goto	87
   52:	aload	6
   54:	invokevirtual	#119; //Method java/lang/Object.equals:(Ljava/lang/Object;)Z
   57:	ifeq	87
   60:	aload_3
   61:	instanceof	#109; //class scala/None$
   64:	ifeq	87
   67:	aload_2
   68:	invokeinterface	#124,  1; //InterfaceMethod scala/Function0.apply:()Ljava/lang/Object;
   73:	astore	7
   75:	aload_0
   76:	aload_1
   77:	aload	7
   79:	invokeinterface	#128,  3; //InterfaceMethod scala/collection/generic/MutableMapTemplate.update:(Ljava/lang/Object;Ljava/lang/Object;)V
   84:	aload	7
   86:	areturn
   87:	new	#130; //class scala/MatchError
   90:	dup
   91:	aload_3
   92:	invokevirtual	#136; //Method scala/Option.toString:()Ljava/lang/String;
   95:	invokespecial	#139; //Method scala/MatchError."<init>":(Ljava/lang/String;)V
   98:	athrow
  LineNumberTable: 
   line 195: 0
   line 196: 28
   line 195: 33
   line 197: 67
   line 195: 86

  LocalVariableTable: 
   Start  Length  Slot  Name   Signature
   0      99      0    $this       Lscala/collection/generic/MutableMapTemplate;
   0      99      1    key       Ljava/lang/Object;
   0      99      2    default       Lscala/Function0;
   8      91      3    temp8       Lscala/Option;
   21      9      4    temp9       Lscala/Some;
   28      2      5    temp10       Ljava/lang/Object;
   75      11      7    d       Ljava/lang/Object;


public static void clear(scala.collection.generic.MutableMapTemplate);
  Code:
   Stack=4, Locals=1, Args_size=1
   0:	aload_0
   1:	invokeinterface	#91,  1; //InterfaceMethod scala/collection/generic/MapTemplate.iterator:()Lscala/collection/Iterator;
   6:	new	#151; //class scala/collection/generic/MutableMapTemplate$$anonfun$clear$1
   9:	dup
   10:	aload_0
   11:	invokespecial	#152; //Method scala/collection/generic/MutableMapTemplate$$anonfun$clear$1."<init>":(Lscala/collection/generic/MutableMapTemplate;)V
   14:	invokeinterface	#22,  2; //InterfaceMethod scala/collection/Iterator.foreach:(Lscala/Function1;)V
   19:	return
  LineNumberTable: 
   line 188: 0

  LocalVariableTable: 
   Start  Length  Slot  Name   Signature
   0      20      0    $this       Lscala/collection/generic/MutableMapTemplate;


public static scala.Option removeKey(scala.collection.generic.MutableMapTemplate, java.lang.Object);
  Code:
   Stack=2, Locals=2, Args_size=2
   0:	aload_0
   1:	aload_1
   2:	invokeinterface	#157,  2; //InterfaceMethod scala/collection/generic/MutableMapTemplate.remove:(Ljava/lang/Object;)Lscala/Option;
   7:	areturn
  LineNumberTable: 
   line 182: 0

  LocalVariableTable: 
   Start  Length  Slot  Name   Signature
   0      8      0    $this       Lscala/collection/generic/MutableMapTemplate;
   0      8      1    key       Ljava/lang/Object;


public static scala.collection.generic.MutableMapTemplate $minus(scala.collection.generic.MutableMapTemplate, java.lang.Object);
  Code:
   Stack=2, Locals=2, Args_size=2
   0:	aload_0
   1:	aload_1
   2:	invokeinterface	#46,  2; //InterfaceMethod scala/collection/generic/MutableMapTemplate.$minus$eq:(Ljava/lang/Object;)Lscala/collection/generic/MutableMapTemplate;
   7:	pop
   8:	aload_0
   9:	invokeinterface	#28,  1; //InterfaceMethod scala/collection/generic/TraversableTemplate.thisCollection:()Lscala/collection/generic/TraversableTemplate;
   14:	checkcast	#30; //class scala/collection/generic/MutableMapTemplate
   17:	areturn
  LineNumberTable: 
   line 176: 0

  LocalVariableTable: 
   Start  Length  Slot  Name   Signature
   0      18      0    $this       Lscala/collection/generic/MutableMapTemplate;
   0      18      1    key       Ljava/lang/Object;


public static scala.Option remove(scala.collection.generic.MutableMapTemplate, java.lang.Object);
  Code:
   Stack=2, Locals=3, Args_size=2
   0:	aload_0
   1:	aload_1
   2:	invokeinterface	#101,  2; //InterfaceMethod scala/collection/generic/MapTemplate.get:(Ljava/lang/Object;)Lscala/Option;
   7:	astore_2
   8:	aload_0
   9:	aload_1
   10:	invokeinterface	#46,  2; //InterfaceMethod scala/collection/generic/MutableMapTemplate.$minus$eq:(Ljava/lang/Object;)Lscala/collection/generic/MutableMapTemplate;
   15:	pop
   16:	aload_2
   17:	areturn
  LineNumberTable: 
   line 159: 0
   line 160: 8
   line 161: 16

  LocalVariableTable: 
   Start  Length  Slot  Name   Signature
   0      18      0    $this       Lscala/collection/generic/MutableMapTemplate;
   0      18      1    key       Ljava/lang/Object;
   8      9      2    r       Lscala/Option;


public static scala.collection.generic.MutableMapTemplate $plus$plus(scala.collection.generic.MutableMapTemplate, scala.collection.Iterator);
  Code:
   Stack=4, Locals=2, Args_size=2
   0:	aload_1
   1:	new	#162; //class scala/collection/generic/MutableMapTemplate$$anonfun$$plus$plus$2
   4:	dup
   5:	aload_0
   6:	invokespecial	#163; //Method scala/collection/generic/MutableMapTemplate$$anonfun$$plus$plus$2."<init>":(Lscala/collection/generic/MutableMapTemplate;)V
   9:	invokeinterface	#22,  2; //InterfaceMethod scala/collection/Iterator.foreach:(Lscala/Function1;)V
   14:	aload_0
   15:	areturn
  LineNumberTable: 
   line 152: 0

  LocalVariableTable: 
   Start  Length  Slot  Name   Signature
   0      16      0    $this       Lscala/collection/generic/MutableMapTemplate;
   0      16      1    iter       Lscala/collection/Iterator;


public static scala.collection.generic.MutableMapTemplate $plus$plus(scala.collection.generic.MutableMapTemplate, scala.collection.Traversable);
  Code:
   Stack=4, Locals=2, Args_size=2
   0:	aload_1
   1:	new	#165; //class scala/collection/generic/MutableMapTemplate$$anonfun$$plus$plus$1
   4:	dup
   5:	aload_0
   6:	invokespecial	#166; //Method scala/collection/generic/MutableMapTemplate$$anonfun$$plus$plus$1."<init>":(Lscala/collection/generic/MutableMapTemplate;)V
   9:	invokeinterface	#39,  2; //InterfaceMethod scala/collection/generic/TraversableClass.foreach:(Lscala/Function1;)V
   14:	aload_0
   15:	areturn
  LineNumberTable: 
   line 141: 0

  LocalVariableTable: 
   Start  Length  Slot  Name   Signature
   0      16      0    $this       Lscala/collection/generic/MutableMapTemplate;
   0      16      1    iter       Lscala/collection/Traversable;


public static scala.collection.generic.MutableMapTemplate $plus(scala.collection.generic.MutableMapTemplate, scala.Tuple2, scala.Tuple2, scala.collection.Sequence);
  Code:
   Stack=2, Locals=4, Args_size=4
   0:	aload_0
   1:	aload_1
   2:	invokeinterface	#172,  2; //InterfaceMethod scala/collection/generic/MutableMapTemplate.$plus$eq:(Lscala/Tuple2;)Lscala/collection/generic/MutableMapTemplate;
   7:	aload_2
   8:	invokeinterface	#172,  2; //InterfaceMethod scala/collection/generic/MutableMapTemplate.$plus$eq:(Lscala/Tuple2;)Lscala/collection/generic/MutableMapTemplate;
   13:	aload_3
   14:	invokeinterface	#74,  2; //InterfaceMethod scala/collection/generic/Growable.$plus$plus$eq:(Lscala/collection/Traversable;)Lscala/collection/generic/Growable;
   19:	checkcast	#30; //class scala/collection/generic/MutableMapTemplate
   22:	areturn
  LineNumberTable: 
   line 129: 0

  LocalVariableTable: 
   Start  Length  Slot  Name   Signature
   0      23      0    $this       Lscala/collection/generic/MutableMapTemplate;
   0      23      1    elem1       Lscala/Tuple2;
   0      23      2    elem2       Lscala/Tuple2;
   0      23      3    elems       Lscala/collection/Sequence;


public static scala.collection.generic.MutableMapTemplate $plus(scala.collection.generic.MutableMapTemplate, scala.Tuple2);
  Code:
   Stack=3, Locals=2, Args_size=2
   0:	aload_0
   1:	aload_1
   2:	invokevirtual	#179; //Method scala/Tuple2._1:()Ljava/lang/Object;
   5:	aload_1
   6:	invokevirtual	#182; //Method scala/Tuple2._2:()Ljava/lang/Object;
   9:	invokeinterface	#128,  3; //InterfaceMethod scala/collection/generic/MutableMapTemplate.update:(Ljava/lang/Object;Ljava/lang/Object;)V
   14:	aload_0
   15:	areturn
  LineNumberTable: 
   line 116: 0

  LocalVariableTable: 
   Start  Length  Slot  Name   Signature
   0      16      0    $this       Lscala/collection/generic/MutableMapTemplate;
   0      16      1    kv       Lscala/Tuple2;


public static java.lang.Object cached(scala.collection.generic.MutableMapTemplate, java.lang.Object, scala.Function0);
  Code:
   Stack=3, Locals=8, Args_size=3
   0:	aload_0
   1:	aload_1
   2:	invokeinterface	#101,  2; //InterfaceMethod scala/collection/generic/MapTemplate.get:(Ljava/lang/Object;)Lscala/Option;
   7:	astore_3
   8:	aload_3
   9:	instanceof	#103; //class scala/Some
   12:	ifeq	33
   15:	aload_3
   16:	checkcast	#103; //class scala/Some
   19:	astore	4
   21:	aload	4
   23:	invokevirtual	#107; //Method scala/Some.x:()Ljava/lang/Object;
   26:	astore	5
   28:	aload	5
   30:	goto	86
   33:	getstatic	#113; //Field scala/None$.MODULE$:Lscala/None$;
   36:	aload_3
   37:	astore	6
   39:	dup
   40:	ifnonnull	52
   43:	pop
   44:	aload	6
   46:	ifnull	60
   49:	goto	87
   52:	aload	6
   54:	invokevirtual	#119; //Method java/lang/Object.equals:(Ljava/lang/Object;)Z
   57:	ifeq	87
   60:	aload_3
   61:	instanceof	#109; //class scala/None$
   64:	ifeq	87
   67:	aload_2
   68:	invokeinterface	#124,  1; //InterfaceMethod scala/Function0.apply:()Ljava/lang/Object;
   73:	astore	7
   75:	aload_0
   76:	aload_1
   77:	aload	7
   79:	invokeinterface	#128,  3; //InterfaceMethod scala/collection/generic/MutableMapTemplate.update:(Ljava/lang/Object;Ljava/lang/Object;)V
   84:	aload	7
   86:	areturn
   87:	new	#130; //class scala/MatchError
   90:	dup
   91:	aload_3
   92:	invokevirtual	#136; //Method scala/Option.toString:()Ljava/lang/String;
   95:	invokespecial	#139; //Method scala/MatchError."<init>":(Ljava/lang/String;)V
   98:	athrow
  LineNumberTable: 
   line 104: 0
   line 105: 28
   line 104: 33
   line 106: 67
   line 104: 86

  LocalVariableTable: 
   Start  Length  Slot  Name   Signature
   0      99      0    $this       Lscala/collection/generic/MutableMapTemplate;
   0      99      1    key       Ljava/lang/Object;
   0      99      2    op       Lscala/Function0;
   8      91      3    temp1       Lscala/Option;
   21      9      4    temp2       Lscala/Some;
   28      2      5    temp3       Ljava/lang/Object;
   75      11      7    v       Ljava/lang/Object;


public static scala.collection.mutable.Map updated(scala.collection.generic.MutableMapTemplate, java.lang.Object, java.lang.Object);
  Code:
   Stack=5, Locals=3, Args_size=3
   0:	aload_0
   1:	new	#176; //class scala/Tuple2
   4:	dup
   5:	aload_1
   6:	aload_2
   7:	invokespecial	#193; //Method scala/Tuple2."<init>":(Ljava/lang/Object;Ljava/lang/Object;)V
   10:	invokeinterface	#198,  2; //InterfaceMethod scala/collection/generic/MutableMapTemplateBase.$plus:(Lscala/Tuple2;)Lscala/collection/mutable/Map;
   15:	areturn
  LineNumberTable: 
   line 98: 0

  LocalVariableTable: 
   Start  Length  Slot  Name   Signature
   0      16      0    $this       Lscala/collection/generic/MutableMapTemplate;
   0      16      1    key       Ljava/lang/Object;
   0      16      2    value       Ljava/lang/Object;


public static void update(scala.collection.generic.MutableMapTemplate, java.lang.Object, java.lang.Object);
  Code:
   Stack=5, Locals=3, Args_size=3
   0:	aload_0
   1:	new	#176; //class scala/Tuple2
   4:	dup
   5:	aload_1
   6:	aload_2
   7:	invokespecial	#193; //Method scala/Tuple2."<init>":(Ljava/lang/Object;Ljava/lang/Object;)V
   10:	invokeinterface	#172,  2; //InterfaceMethod scala/collection/generic/MutableMapTemplate.$plus$eq:(Lscala/Tuple2;)Lscala/collection/generic/MutableMapTemplate;
   15:	pop
   16:	return
  LineNumberTable: 
   line 83: 0

  LocalVariableTable: 
   Start  Length  Slot  Name   Signature
   0      17      0    $this       Lscala/collection/generic/MutableMapTemplate;
   0      17      1    key       Ljava/lang/Object;
   0      17      2    value       Ljava/lang/Object;


public static scala.Option put(scala.collection.generic.MutableMapTemplate, java.lang.Object, java.lang.Object);
  Code:
   Stack=3, Locals=4, Args_size=3
   0:	aload_0
   1:	aload_1
   2:	invokeinterface	#101,  2; //InterfaceMethod scala/collection/generic/MapTemplate.get:(Ljava/lang/Object;)Lscala/Option;
   7:	astore_3
   8:	aload_0
   9:	aload_1
   10:	aload_2
   11:	invokeinterface	#128,  3; //InterfaceMethod scala/collection/generic/MutableMapTemplate.update:(Ljava/lang/Object;Ljava/lang/Object;)V
   16:	aload_3
   17:	areturn
  LineNumberTable: 
   line 69: 0
   line 70: 8
   line 71: 16

  LocalVariableTable: 
   Start  Length  Slot  Name   Signature
   0      18      0    $this       Lscala/collection/generic/MutableMapTemplate;
   0      18      1    key       Ljava/lang/Object;
   0      18      2    value       Ljava/lang/Object;
   8      9      3    r       Lscala/Option;


public static scala.collection.generic.Builder newBuilder(scala.collection.generic.MutableMapTemplate);
  Code:
   Stack=1, Locals=1, Args_size=1
   0:	aload_0
   1:	invokeinterface	#66,  1; //InterfaceMethod scala/collection/generic/MapTemplate.empty:()Lscala/collection/generic/MapTemplate;
   6:	checkcast	#206; //class scala/collection/generic/Builder
   9:	areturn
  LineNumberTable: 
   line 59: 0

  LocalVariableTable: 
   Start  Length  Slot  Name   Signature
   0      10      0    $this       Lscala/collection/generic/MutableMapTemplate;


}

