Compiled from "MutableVectorViewTemplate.scala"
public abstract class scala.collection.generic.MutableVectorViewTemplate$Sliced$class extends java.lang.Object
  SourceFile: "MutableVectorViewTemplate.scala"
  Scala: length = 0x
   
  InnerClass: 
   public abstract #58= #13 of #57; //Sliced=class scala/collection/generic/TraversableViewTemplate$Sliced of class scala/collection/generic/TraversableViewTemplate
   public abstract #58= #22 of #60; //Sliced=class scala/collection/generic/MutableVectorViewTemplate$Sliced of class scala/collection/generic/MutableVectorViewTemplate
  minor version: 0
  major version: 49
  Constant pool:
const #1 = Asciz	SourceFile;
const #2 = Asciz	MutableVectorViewTemplate.scala;
const #3 = Asciz	$init$;
const #4 = Asciz	(Lscala/collection/generic/MutableVectorViewTemplate$Sliced;)V;
const #5 = Asciz	Code;
const #6 = Asciz	LineNumberTable;
const #7 = Asciz	$this;
const #8 = Asciz	Lscala/collection/generic/MutableVectorViewTemplate$Sliced;;
const #9 = Asciz	LocalVariableTable;
const #10 = Asciz	update;
const #11 = Asciz	(Lscala/collection/generic/MutableVectorViewTemplate$Sliced;ILjava/lang/Object;)V;
const #12 = Asciz	scala/collection/generic/TraversableViewTemplate$Sliced;
const #13 = class	#12;	//  scala/collection/generic/TraversableViewTemplate$Sliced
const #14 = Asciz	from;
const #15 = Asciz	()I;
const #16 = NameAndType	#14:#15;//  from:()I
const #17 = InterfaceMethod	#13.#16;	//  scala/collection/generic/TraversableViewTemplate$Sliced.from:()I
const #18 = Asciz	until;
const #19 = NameAndType	#18:#15;//  until:()I
const #20 = InterfaceMethod	#13.#19;	//  scala/collection/generic/TraversableViewTemplate$Sliced.until:()I
const #21 = Asciz	scala/collection/generic/MutableVectorViewTemplate$Sliced;
const #22 = class	#21;	//  scala/collection/generic/MutableVectorViewTemplate$Sliced
const #23 = Asciz	scala$collection$generic$MutableVectorViewTemplate$Sliced$$$outer;
const #24 = Asciz	()Lscala/collection/generic/MutableVectorViewTemplate;;
const #25 = NameAndType	#23:#24;//  scala$collection$generic$MutableVectorViewTemplate$Sliced$$$outer:()Lscala/collection/generic/MutableVectorViewTemplate;
const #26 = InterfaceMethod	#22.#25;	//  scala/collection/generic/MutableVectorViewTemplate$Sliced.scala$collection$generic$MutableVectorViewTemplate$Sliced$$$outer:()Lscala/collection/generic/MutableVectorViewTemplate;
const #27 = Asciz	scala/collection/generic/MutableVectorTemplate;
const #28 = class	#27;	//  scala/collection/generic/MutableVectorTemplate
const #29 = Asciz	(ILjava/lang/Object;)V;
const #30 = NameAndType	#10:#29;//  update:(ILjava/lang/Object;)V
const #31 = InterfaceMethod	#28.#30;	//  scala/collection/generic/MutableVectorTemplate.update:(ILjava/lang/Object;)V
const #32 = Asciz	java/lang/IndexOutOfBoundsException;
const #33 = class	#32;	//  java/lang/IndexOutOfBoundsException
const #34 = Asciz	scala/runtime/BoxesRunTime;
const #35 = class	#34;	//  scala/runtime/BoxesRunTime
const #36 = Asciz	boxToInteger;
const #37 = Asciz	(I)Ljava/lang/Integer;;
const #38 = NameAndType	#36:#37;//  boxToInteger:(I)Ljava/lang/Integer;
const #39 = Method	#35.#38;	//  scala/runtime/BoxesRunTime.boxToInteger:(I)Ljava/lang/Integer;
const #40 = Asciz	java/lang/Object;
const #41 = class	#40;	//  java/lang/Object
const #42 = Asciz	toString;
const #43 = Asciz	()Ljava/lang/String;;
const #44 = NameAndType	#42:#43;//  toString:()Ljava/lang/String;
const #45 = Method	#41.#44;	//  java/lang/Object.toString:()Ljava/lang/String;
const #46 = Asciz	<init>;
const #47 = Asciz	(Ljava/lang/String;)V;
const #48 = NameAndType	#46:#47;//  "<init>":(Ljava/lang/String;)V
const #49 = Method	#33.#48;	//  java/lang/IndexOutOfBoundsException."<init>":(Ljava/lang/String;)V
const #50 = Asciz	idx;
const #51 = Asciz	I;
const #52 = Asciz	elem;
const #53 = Asciz	Ljava/lang/Object;;
const #54 = Asciz	Scala;
const #55 = Asciz	InnerClasses;
const #56 = Asciz	scala/collection/generic/TraversableViewTemplate;
const #57 = class	#56;	//  scala/collection/generic/TraversableViewTemplate
const #58 = Asciz	Sliced;
const #59 = Asciz	scala/collection/generic/MutableVectorViewTemplate;
const #60 = class	#59;	//  scala/collection/generic/MutableVectorViewTemplate
const #61 = Asciz	scala/collection/generic/MutableVectorViewTemplate$Sliced$class;
const #62 = class	#61;	//  scala/collection/generic/MutableVectorViewTemplate$Sliced$class

{
public static void $init$(scala.collection.generic.MutableVectorViewTemplate$Sliced);
  Code:
   Stack=0, Locals=1, Args_size=1
   0:	return
  LineNumberTable: 
   line 32: 0

  LocalVariableTable: 
   Start  Length  Slot  Name   Signature
   0      1      0    $this       Lscala/collection/generic/MutableVectorViewTemplate$Sliced;


public static void update(scala.collection.generic.MutableVectorViewTemplate$Sliced, int, java.lang.Object);
  Code:
   Stack=3, Locals=3, Args_size=3
   0:	iload_1
   1:	aload_0
   2:	invokeinterface	#17,  1; //InterfaceMethod scala/collection/generic/TraversableViewTemplate$Sliced.from:()I
   7:	iadd
   8:	aload_0
   9:	invokeinterface	#20,  1; //InterfaceMethod scala/collection/generic/TraversableViewTemplate$Sliced.until:()I
   14:	if_icmpge	38
   17:	aload_0
   18:	invokeinterface	#26,  1; //InterfaceMethod scala/collection/generic/MutableVectorViewTemplate$Sliced.scala$collection$generic$MutableVectorViewTemplate$Sliced$$$outer:()Lscala/collection/generic/MutableVectorViewTemplate;
   23:	iload_1
   24:	aload_0
   25:	invokeinterface	#17,  1; //InterfaceMethod scala/collection/generic/TraversableViewTemplate$Sliced.from:()I
   30:	iadd
   31:	aload_2
   32:	invokeinterface	#31,  3; //InterfaceMethod scala/collection/generic/MutableVectorTemplate.update:(ILjava/lang/Object;)V
   37:	return
   38:	new	#33; //class java/lang/IndexOutOfBoundsException
   41:	dup
   42:	iload_1
   43:	invokestatic	#39; //Method scala/runtime/BoxesRunTime.boxToInteger:(I)Ljava/lang/Integer;
   46:	invokevirtual	#45; //Method java/lang/Object.toString:()Ljava/lang/String;
   49:	invokespecial	#49; //Method java/lang/IndexOutOfBoundsException."<init>":(Ljava/lang/String;)V
   52:	athrow
  LineNumberTable: 
   line 34: 0
   line 35: 38

  LocalVariableTable: 
   Start  Length  Slot  Name   Signature
   0      53      0    $this       Lscala/collection/generic/MutableVectorViewTemplate$Sliced;
   0      53      1    idx       I
   0      53      2    elem       Ljava/lang/Object;


}

