Compiled from "MutableSetTemplate.scala"
public abstract class scala.collection.generic.MutableSetTemplate$class extends java.lang.Object
  SourceFile: "MutableSetTemplate.scala"
  Scala: length = 0x
   
  InnerClass: 
   public final #189= #151 of #19; //$anonfun$clear$1=class scala/collection/generic/MutableSetTemplate$$anonfun$clear$1 of class scala/collection/generic/MutableSetTemplate
   public final #190= #163 of #19; //$anonfun$retain$1=class scala/collection/generic/MutableSetTemplate$$anonfun$retain$1 of class scala/collection/generic/MutableSetTemplate
   public final #191= #124 of #19; //$anonfun$$plus$plus$2=class scala/collection/generic/MutableSetTemplate$$anonfun$$plus$plus$2 of class scala/collection/generic/MutableSetTemplate
   public final #192= #45 of #19; //$anonfun$$less$less$1=class scala/collection/generic/MutableSetTemplate$$anonfun$$less$less$1 of class scala/collection/generic/MutableSetTemplate
   public final #193= #127 of #19; //$anonfun$$plus$plus$1=class scala/collection/generic/MutableSetTemplate$$anonfun$$plus$plus$1 of class scala/collection/generic/MutableSetTemplate
   public final #194= #91 of #19; //$anonfun$$minus$minus$2=class scala/collection/generic/MutableSetTemplate$$anonfun$$minus$minus$2 of class scala/collection/generic/MutableSetTemplate
   public final #195= #103 of #19; //$anonfun$$minus$minus$1=class scala/collection/generic/MutableSetTemplate$$anonfun$$minus$minus$1 of class scala/collection/generic/MutableSetTemplate
  minor version: 0
  major version: 49
  Constant pool:
const #1 = Asciz	SourceFile;
const #2 = Asciz	MutableSetTemplate.scala;
const #3 = Asciz	$init$;
const #4 = Asciz	(Lscala/collection/generic/MutableSetTemplate;)V;
const #5 = Asciz	Code;
const #6 = Asciz	LineNumberTable;
const #7 = Asciz	$this;
const #8 = Asciz	Lscala/collection/generic/MutableSetTemplate;;
const #9 = Asciz	LocalVariableTable;
const #10 = Asciz	$less$less;
const #11 = Asciz	(Lscala/collection/generic/MutableSetTemplate;Lscala/collection/script/Message;)V;
const #12 = Asciz	scala/collection/script/Include;
const #13 = class	#12;	//  scala/collection/script/Include
const #14 = Asciz	elem;
const #15 = Asciz	()Ljava/lang/Object;;
const #16 = NameAndType	#14:#15;//  elem:()Ljava/lang/Object;
const #17 = Method	#13.#16;	//  scala/collection/script/Include.elem:()Ljava/lang/Object;
const #18 = Asciz	scala/collection/generic/MutableSetTemplate;
const #19 = class	#18;	//  scala/collection/generic/MutableSetTemplate
const #20 = Asciz	$plus$eq;
const #21 = Asciz	(Ljava/lang/Object;)Lscala/collection/generic/MutableSetTemplate;;
const #22 = NameAndType	#20:#21;//  $plus$eq:(Ljava/lang/Object;)Lscala/collection/generic/MutableSetTemplate;
const #23 = InterfaceMethod	#19.#22;	//  scala/collection/generic/MutableSetTemplate.$plus$eq:(Ljava/lang/Object;)Lscala/collection/generic/MutableSetTemplate;
const #24 = Asciz	scala/collection/script/Remove;
const #25 = class	#24;	//  scala/collection/script/Remove
const #26 = Method	#25.#16;	//  scala/collection/script/Remove.elem:()Ljava/lang/Object;
const #27 = Asciz	$minus$eq;
const #28 = NameAndType	#27:#21;//  $minus$eq:(Ljava/lang/Object;)Lscala/collection/generic/MutableSetTemplate;
const #29 = InterfaceMethod	#19.#28;	//  scala/collection/generic/MutableSetTemplate.$minus$eq:(Ljava/lang/Object;)Lscala/collection/generic/MutableSetTemplate;
const #30 = Asciz	scala/collection/script/Reset;
const #31 = class	#30;	//  scala/collection/script/Reset
const #32 = Asciz	clear;
const #33 = Asciz	()V;
const #34 = NameAndType	#32:#33;//  clear:()V
const #35 = InterfaceMethod	#19.#34;	//  scala/collection/generic/MutableSetTemplate.clear:()V
const #36 = Asciz	scala/collection/script/Script;
const #37 = class	#36;	//  scala/collection/script/Script
const #38 = Asciz	scala/collection/generic/VectorTemplate;
const #39 = class	#38;	//  scala/collection/generic/VectorTemplate
const #40 = Asciz	iterator;
const #41 = Asciz	()Lscala/collection/Iterator;;
const #42 = NameAndType	#40:#41;//  iterator:()Lscala/collection/Iterator;
const #43 = InterfaceMethod	#39.#42;	//  scala/collection/generic/VectorTemplate.iterator:()Lscala/collection/Iterator;
const #44 = Asciz	scala/collection/generic/MutableSetTemplate$$anonfun$$less$less$1;
const #45 = class	#44;	//  scala/collection/generic/MutableSetTemplate$$anonfun$$less$less$1
const #46 = Asciz	<init>;
const #47 = NameAndType	#46:#4;//  "<init>":(Lscala/collection/generic/MutableSetTemplate;)V
const #48 = Method	#45.#47;	//  scala/collection/generic/MutableSetTemplate$$anonfun$$less$less$1."<init>":(Lscala/collection/generic/MutableSetTemplate;)V
const #49 = Asciz	scala/collection/Iterator;
const #50 = class	#49;	//  scala/collection/Iterator
const #51 = Asciz	foreach;
const #52 = Asciz	(Lscala/Function1;)V;
const #53 = NameAndType	#51:#52;//  foreach:(Lscala/Function1;)V
const #54 = InterfaceMethod	#50.#53;	//  scala/collection/Iterator.foreach:(Lscala/Function1;)V
const #55 = Asciz	java/lang/UnsupportedOperationException;
const #56 = class	#55;	//  java/lang/UnsupportedOperationException
const #57 = Asciz	scala/collection/mutable/StringBuilder;
const #58 = class	#57;	//  scala/collection/mutable/StringBuilder
const #59 = NameAndType	#46:#33;//  "<init>":()V
const #60 = Method	#58.#59;	//  scala/collection/mutable/StringBuilder."<init>":()V
const #61 = Asciz	message ;
const #62 = String	#61;	//  message 
const #63 = Asciz	append;
const #64 = Asciz	(Ljava/lang/Object;)Lscala/collection/mutable/StringBuilder;;
const #65 = NameAndType	#63:#64;//  append:(Ljava/lang/Object;)Lscala/collection/mutable/StringBuilder;
const #66 = Method	#58.#65;	//  scala/collection/mutable/StringBuilder.append:(Ljava/lang/Object;)Lscala/collection/mutable/StringBuilder;
const #67 = Asciz	 not understood;
const #68 = String	#67;	//   not understood
const #69 = Asciz	toString;
const #70 = Asciz	()Ljava/lang/String;;
const #71 = NameAndType	#69:#70;//  toString:()Ljava/lang/String;
const #72 = Method	#58.#71;	//  scala/collection/mutable/StringBuilder.toString:()Ljava/lang/String;
const #73 = Asciz	(Ljava/lang/String;)V;
const #74 = NameAndType	#46:#73;//  "<init>":(Ljava/lang/String;)V
const #75 = Method	#56.#74;	//  java/lang/UnsupportedOperationException."<init>":(Ljava/lang/String;)V
const #76 = Asciz	cmd;
const #77 = Asciz	Lscala/collection/script/Message;;
const #78 = Asciz	temp1;
const #79 = Asciz	temp2;
const #80 = Asciz	Lscala/collection/script/Include;;
const #81 = Asciz	temp4;
const #82 = Asciz	Ljava/lang/Object;;
const #83 = Asciz	temp5;
const #84 = Asciz	Lscala/collection/script/Remove;;
const #85 = Asciz	temp7;
const #86 = Asciz	temp9;
const #87 = Asciz	Lscala/collection/script/Script;;
const #88 = Asciz	$minus$minus;
const #89 = Asciz	(Lscala/collection/generic/MutableSetTemplate;Lscala/collection/Iterator;)Lscala/collection/generic/MutableSetTemplate;;
const #90 = Asciz	scala/collection/generic/MutableSetTemplate$$anonfun$$minus$minus$2;
const #91 = class	#90;	//  scala/collection/generic/MutableSetTemplate$$anonfun$$minus$minus$2
const #92 = Method	#91.#47;	//  scala/collection/generic/MutableSetTemplate$$anonfun$$minus$minus$2."<init>":(Lscala/collection/generic/MutableSetTemplate;)V
const #93 = Asciz	scala/collection/generic/TraversableTemplate;
const #94 = class	#93;	//  scala/collection/generic/TraversableTemplate
const #95 = Asciz	thisCollection;
const #96 = Asciz	()Lscala/collection/generic/TraversableTemplate;;
const #97 = NameAndType	#95:#96;//  thisCollection:()Lscala/collection/generic/TraversableTemplate;
const #98 = InterfaceMethod	#94.#97;	//  scala/collection/generic/TraversableTemplate.thisCollection:()Lscala/collection/generic/TraversableTemplate;
const #99 = Asciz	iter;
const #100 = Asciz	Lscala/collection/Iterator;;
const #101 = Asciz	(Lscala/collection/generic/MutableSetTemplate;Lscala/collection/Traversable;)Lscala/collection/generic/MutableSetTemplate;;
const #102 = Asciz	scala/collection/generic/MutableSetTemplate$$anonfun$$minus$minus$1;
const #103 = class	#102;	//  scala/collection/generic/MutableSetTemplate$$anonfun$$minus$minus$1
const #104 = Method	#103.#47;	//  scala/collection/generic/MutableSetTemplate$$anonfun$$minus$minus$1."<init>":(Lscala/collection/generic/MutableSetTemplate;)V
const #105 = Asciz	scala/collection/generic/TraversableClass;
const #106 = class	#105;	//  scala/collection/generic/TraversableClass
const #107 = InterfaceMethod	#106.#53;	//  scala/collection/generic/TraversableClass.foreach:(Lscala/Function1;)V
const #108 = Asciz	Lscala/collection/Traversable;;
const #109 = Asciz	$minus;
const #110 = Asciz	(Lscala/collection/generic/MutableSetTemplate;Ljava/lang/Object;Ljava/lang/Object;Lscala/collection/Sequence;)Lscala/collection/generic/MutableSetTemplate;;
const #111 = Asciz	scala/collection/generic/Shrinkable;
const #112 = class	#111;	//  scala/collection/generic/Shrinkable
const #113 = Asciz	$minus$minus$eq;
const #114 = Asciz	(Lscala/collection/Traversable;)Lscala/collection/generic/Shrinkable;;
const #115 = NameAndType	#113:#114;//  $minus$minus$eq:(Lscala/collection/Traversable;)Lscala/collection/generic/Shrinkable;
const #116 = InterfaceMethod	#112.#115;	//  scala/collection/generic/Shrinkable.$minus$minus$eq:(Lscala/collection/Traversable;)Lscala/collection/generic/Shrinkable;
const #117 = Asciz	elem1;
const #118 = Asciz	elem2;
const #119 = Asciz	elems;
const #120 = Asciz	Lscala/collection/Sequence;;
const #121 = Asciz	(Lscala/collection/generic/MutableSetTemplate;Ljava/lang/Object;)Lscala/collection/generic/MutableSetTemplate;;
const #122 = Asciz	$plus$plus;
const #123 = Asciz	scala/collection/generic/MutableSetTemplate$$anonfun$$plus$plus$2;
const #124 = class	#123;	//  scala/collection/generic/MutableSetTemplate$$anonfun$$plus$plus$2
const #125 = Method	#124.#47;	//  scala/collection/generic/MutableSetTemplate$$anonfun$$plus$plus$2."<init>":(Lscala/collection/generic/MutableSetTemplate;)V
const #126 = Asciz	scala/collection/generic/MutableSetTemplate$$anonfun$$plus$plus$1;
const #127 = class	#126;	//  scala/collection/generic/MutableSetTemplate$$anonfun$$plus$plus$1
const #128 = Method	#127.#47;	//  scala/collection/generic/MutableSetTemplate$$anonfun$$plus$plus$1."<init>":(Lscala/collection/generic/MutableSetTemplate;)V
const #129 = Asciz	$plus;
const #130 = Asciz	scala/collection/generic/Growable;
const #131 = class	#130;	//  scala/collection/generic/Growable
const #132 = Asciz	$plus$plus$eq;
const #133 = Asciz	(Lscala/collection/Traversable;)Lscala/collection/generic/Growable;;
const #134 = NameAndType	#132:#133;//  $plus$plus$eq:(Lscala/collection/Traversable;)Lscala/collection/generic/Growable;
const #135 = InterfaceMethod	#131.#134;	//  scala/collection/generic/Growable.$plus$plus$eq:(Lscala/collection/Traversable;)Lscala/collection/generic/Growable;
const #136 = Asciz	result;
const #137 = Asciz	(Lscala/collection/generic/MutableSetTemplate;)Lscala/collection/generic/MutableSetTemplate;;
const #138 = Asciz	clone;
const #139 = Asciz	(Lscala/collection/generic/MutableSetTemplate;)Lscala/collection/mutable/Set;;
const #140 = Asciz	scala/collection/generic/SetTemplate;
const #141 = class	#140;	//  scala/collection/generic/SetTemplate
const #142 = Asciz	empty;
const #143 = Asciz	()Lscala/collection/generic/SetTemplate;;
const #144 = NameAndType	#142:#143;//  empty:()Lscala/collection/generic/SetTemplate;
const #145 = InterfaceMethod	#141.#144;	//  scala/collection/generic/SetTemplate.empty:()Lscala/collection/generic/SetTemplate;
const #146 = Asciz	scala/collection/Traversable;
const #147 = class	#146;	//  scala/collection/Traversable
const #148 = Asciz	scala/collection/mutable/Set;
const #149 = class	#148;	//  scala/collection/mutable/Set
const #150 = Asciz	scala/collection/generic/MutableSetTemplate$$anonfun$clear$1;
const #151 = class	#150;	//  scala/collection/generic/MutableSetTemplate$$anonfun$clear$1
const #152 = Method	#151.#47;	//  scala/collection/generic/MutableSetTemplate$$anonfun$clear$1."<init>":(Lscala/collection/generic/MutableSetTemplate;)V
const #153 = Asciz	scala/collection/generic/IterableTemplate;
const #154 = class	#153;	//  scala/collection/generic/IterableTemplate
const #155 = InterfaceMethod	#154.#53;	//  scala/collection/generic/IterableTemplate.foreach:(Lscala/Function1;)V
const #156 = Asciz	retain;
const #157 = Asciz	(Lscala/collection/generic/MutableSetTemplate;Lscala/Function1;)V;
const #158 = Asciz	toList;
const #159 = Asciz	()Lscala/collection/immutable/List;;
const #160 = NameAndType	#158:#159;//  toList:()Lscala/collection/immutable/List;
const #161 = InterfaceMethod	#94.#160;	//  scala/collection/generic/TraversableTemplate.toList:()Lscala/collection/immutable/List;
const #162 = Asciz	scala/collection/generic/MutableSetTemplate$$anonfun$retain$1;
const #163 = class	#162;	//  scala/collection/generic/MutableSetTemplate$$anonfun$retain$1
const #164 = NameAndType	#46:#157;//  "<init>":(Lscala/collection/generic/MutableSetTemplate;Lscala/Function1;)V
const #165 = Method	#163.#164;	//  scala/collection/generic/MutableSetTemplate$$anonfun$retain$1."<init>":(Lscala/collection/generic/MutableSetTemplate;Lscala/Function1;)V
const #166 = Asciz	scala/collection/generic/LinearSequenceTemplate;
const #167 = class	#166;	//  scala/collection/generic/LinearSequenceTemplate
const #168 = InterfaceMethod	#167.#53;	//  scala/collection/generic/LinearSequenceTemplate.foreach:(Lscala/Function1;)V
const #169 = Asciz	p$1;
const #170 = Asciz	Lscala/Function1;;
const #171 = Asciz	update;
const #172 = Asciz	(Lscala/collection/generic/MutableSetTemplate;Ljava/lang/Object;Z)V;
const #173 = Asciz	included;
const #174 = Asciz	Z;
const #175 = Asciz	remove;
const #176 = Asciz	(Lscala/collection/generic/MutableSetTemplate;Ljava/lang/Object;)Z;
const #177 = Asciz	contains;
const #178 = Asciz	(Ljava/lang/Object;)Z;
const #179 = NameAndType	#177:#178;//  contains:(Ljava/lang/Object;)Z
const #180 = InterfaceMethod	#141.#179;	//  scala/collection/generic/SetTemplate.contains:(Ljava/lang/Object;)Z
const #181 = Asciz	r;
const #182 = Asciz	add;
const #183 = Asciz	newBuilder;
const #184 = Asciz	(Lscala/collection/generic/MutableSetTemplate;)Lscala/collection/generic/Builder;;
const #185 = Asciz	scala/collection/generic/Builder;
const #186 = class	#185;	//  scala/collection/generic/Builder
const #187 = Asciz	Scala;
const #188 = Asciz	InnerClasses;
const #189 = Asciz	$anonfun$clear$1;
const #190 = Asciz	$anonfun$retain$1;
const #191 = Asciz	$anonfun$$plus$plus$2;
const #192 = Asciz	$anonfun$$less$less$1;
const #193 = Asciz	$anonfun$$plus$plus$1;
const #194 = Asciz	$anonfun$$minus$minus$2;
const #195 = Asciz	$anonfun$$minus$minus$1;
const #196 = Asciz	scala/collection/generic/MutableSetTemplate$class;
const #197 = class	#196;	//  scala/collection/generic/MutableSetTemplate$class
const #198 = Asciz	java/lang/Object;
const #199 = class	#198;	//  java/lang/Object

{
public static void $init$(scala.collection.generic.MutableSetTemplate);
  Code:
   Stack=0, Locals=1, Args_size=1
   0:	return
  LineNumberTable: 
   line 39: 0

  LocalVariableTable: 
   Start  Length  Slot  Name   Signature
   0      1      0    $this       Lscala/collection/generic/MutableSetTemplate;


public static void $less$less(scala.collection.generic.MutableSetTemplate, scala.collection.script.Message);
  Code:
   Stack=4, Locals=8, Args_size=2
   0:	aload_1
   1:	astore_2
   2:	aload_2
   3:	instanceof	#13; //class scala/collection/script/Include
   6:	ifeq	32
   9:	aload_2
   10:	checkcast	#13; //class scala/collection/script/Include
   13:	astore_3
   14:	aload_3
   15:	invokevirtual	#17; //Method scala/collection/script/Include.elem:()Ljava/lang/Object;
   18:	astore	4
   20:	aload_0
   21:	aload	4
   23:	invokeinterface	#23,  2; //InterfaceMethod scala/collection/generic/MutableSetTemplate.$plus$eq:(Ljava/lang/Object;)Lscala/collection/generic/MutableSetTemplate;
   28:	pop
   29:	goto	113
   32:	aload_2
   33:	instanceof	#25; //class scala/collection/script/Remove
   36:	ifeq	64
   39:	aload_2
   40:	checkcast	#25; //class scala/collection/script/Remove
   43:	astore	5
   45:	aload	5
   47:	invokevirtual	#26; //Method scala/collection/script/Remove.elem:()Ljava/lang/Object;
   50:	astore	6
   52:	aload_0
   53:	aload	6
   55:	invokeinterface	#29,  2; //InterfaceMethod scala/collection/generic/MutableSetTemplate.$minus$eq:(Ljava/lang/Object;)Lscala/collection/generic/MutableSetTemplate;
   60:	pop
   61:	goto	113
   64:	aload_2
   65:	instanceof	#31; //class scala/collection/script/Reset
   68:	ifeq	80
   71:	aload_0
   72:	invokeinterface	#35,  1; //InterfaceMethod scala/collection/generic/MutableSetTemplate.clear:()V
   77:	goto	113
   80:	aload_2
   81:	instanceof	#37; //class scala/collection/script/Script
   84:	ifeq	114
   87:	aload_2
   88:	checkcast	#37; //class scala/collection/script/Script
   91:	astore	7
   93:	aload	7
   95:	invokeinterface	#43,  1; //InterfaceMethod scala/collection/generic/VectorTemplate.iterator:()Lscala/collection/Iterator;
   100:	new	#45; //class scala/collection/generic/MutableSetTemplate$$anonfun$$less$less$1
   103:	dup
   104:	aload_0
   105:	invokespecial	#48; //Method scala/collection/generic/MutableSetTemplate$$anonfun$$less$less$1."<init>":(Lscala/collection/generic/MutableSetTemplate;)V
   108:	invokeinterface	#54,  2; //InterfaceMethod scala/collection/Iterator.foreach:(Lscala/Function1;)V
   113:	return
   114:	new	#56; //class java/lang/UnsupportedOperationException
   117:	dup
   118:	new	#58; //class scala/collection/mutable/StringBuilder
   121:	dup
   122:	invokespecial	#60; //Method scala/collection/mutable/StringBuilder."<init>":()V
   125:	ldc	#62; //String message 
   127:	invokevirtual	#66; //Method scala/collection/mutable/StringBuilder.append:(Ljava/lang/Object;)Lscala/collection/mutable/StringBuilder;
   130:	aload_1
   131:	invokevirtual	#66; //Method scala/collection/mutable/StringBuilder.append:(Ljava/lang/Object;)Lscala/collection/mutable/StringBuilder;
   134:	ldc	#68; //String  not understood
   136:	invokevirtual	#66; //Method scala/collection/mutable/StringBuilder.append:(Ljava/lang/Object;)Lscala/collection/mutable/StringBuilder;
   139:	invokevirtual	#72; //Method scala/collection/mutable/StringBuilder.toString:()Ljava/lang/String;
   142:	invokespecial	#75; //Method java/lang/UnsupportedOperationException."<init>":(Ljava/lang/String;)V
   145:	athrow
  LineNumberTable: 
   line 211: 0
   line 212: 20
   line 211: 32
   line 213: 52
   line 211: 64
   line 214: 71
   line 211: 80
   line 215: 93
   line 211: 113
   line 216: 114

  LocalVariableTable: 
   Start  Length  Slot  Name   Signature
   0      146      0    $this       Lscala/collection/generic/MutableSetTemplate;
   0      146      1    cmd       Lscala/collection/script/Message;
   2      144      2    temp1       Lscala/collection/script/Message;
   14      15      3    temp2       Lscala/collection/script/Include;
   20      9      4    temp4       Ljava/lang/Object;
   45      16      5    temp5       Lscala/collection/script/Remove;
   52      9      6    temp7       Ljava/lang/Object;
   93      20      7    temp9       Lscala/collection/script/Script;


public static scala.collection.generic.MutableSetTemplate $minus$minus(scala.collection.generic.MutableSetTemplate, scala.collection.Iterator);
  Code:
   Stack=4, Locals=2, Args_size=2
   0:	aload_1
   1:	new	#91; //class scala/collection/generic/MutableSetTemplate$$anonfun$$minus$minus$2
   4:	dup
   5:	aload_0
   6:	invokespecial	#92; //Method scala/collection/generic/MutableSetTemplate$$anonfun$$minus$minus$2."<init>":(Lscala/collection/generic/MutableSetTemplate;)V
   9:	invokeinterface	#54,  2; //InterfaceMethod scala/collection/Iterator.foreach:(Lscala/Function1;)V
   14:	aload_0
   15:	invokeinterface	#98,  1; //InterfaceMethod scala/collection/generic/TraversableTemplate.thisCollection:()Lscala/collection/generic/TraversableTemplate;
   20:	checkcast	#19; //class scala/collection/generic/MutableSetTemplate
   23:	areturn
  LineNumberTable: 
   line 201: 0
   line 202: 14

  LocalVariableTable: 
   Start  Length  Slot  Name   Signature
   0      24      0    $this       Lscala/collection/generic/MutableSetTemplate;
   0      24      1    iter       Lscala/collection/Iterator;


public static scala.collection.generic.MutableSetTemplate $minus$minus(scala.collection.generic.MutableSetTemplate, scala.collection.Traversable);
  Code:
   Stack=4, Locals=2, Args_size=2
   0:	aload_1
   1:	new	#103; //class scala/collection/generic/MutableSetTemplate$$anonfun$$minus$minus$1
   4:	dup
   5:	aload_0
   6:	invokespecial	#104; //Method scala/collection/generic/MutableSetTemplate$$anonfun$$minus$minus$1."<init>":(Lscala/collection/generic/MutableSetTemplate;)V
   9:	invokeinterface	#107,  2; //InterfaceMethod scala/collection/generic/TraversableClass.foreach:(Lscala/Function1;)V
   14:	aload_0
   15:	invokeinterface	#98,  1; //InterfaceMethod scala/collection/generic/TraversableTemplate.thisCollection:()Lscala/collection/generic/TraversableTemplate;
   20:	checkcast	#19; //class scala/collection/generic/MutableSetTemplate
   23:	areturn
  LineNumberTable: 
   line 189: 0
   line 190: 14

  LocalVariableTable: 
   Start  Length  Slot  Name   Signature
   0      24      0    $this       Lscala/collection/generic/MutableSetTemplate;
   0      24      1    iter       Lscala/collection/Traversable;


public static scala.collection.generic.MutableSetTemplate $minus(scala.collection.generic.MutableSetTemplate, java.lang.Object, java.lang.Object, scala.collection.Sequence);
  Code:
   Stack=2, Locals=4, Args_size=4
   0:	aload_0
   1:	aload_1
   2:	invokeinterface	#29,  2; //InterfaceMethod scala/collection/generic/MutableSetTemplate.$minus$eq:(Ljava/lang/Object;)Lscala/collection/generic/MutableSetTemplate;
   7:	aload_2
   8:	invokeinterface	#29,  2; //InterfaceMethod scala/collection/generic/MutableSetTemplate.$minus$eq:(Ljava/lang/Object;)Lscala/collection/generic/MutableSetTemplate;
   13:	aload_3
   14:	invokeinterface	#116,  2; //InterfaceMethod scala/collection/generic/Shrinkable.$minus$minus$eq:(Lscala/collection/Traversable;)Lscala/collection/generic/Shrinkable;
   19:	pop
   20:	aload_0
   21:	invokeinterface	#98,  1; //InterfaceMethod scala/collection/generic/TraversableTemplate.thisCollection:()Lscala/collection/generic/TraversableTemplate;
   26:	checkcast	#19; //class scala/collection/generic/MutableSetTemplate
   29:	areturn
  LineNumberTable: 
   line 177: 0
   line 178: 20

  LocalVariableTable: 
   Start  Length  Slot  Name   Signature
   0      30      0    $this       Lscala/collection/generic/MutableSetTemplate;
   0      30      1    elem1       Ljava/lang/Object;
   0      30      2    elem2       Ljava/lang/Object;
   0      30      3    elems       Lscala/collection/Sequence;


public static scala.collection.generic.MutableSetTemplate $minus(scala.collection.generic.MutableSetTemplate, java.lang.Object);
  Code:
   Stack=2, Locals=2, Args_size=2
   0:	aload_0
   1:	aload_1
   2:	invokeinterface	#29,  2; //InterfaceMethod scala/collection/generic/MutableSetTemplate.$minus$eq:(Ljava/lang/Object;)Lscala/collection/generic/MutableSetTemplate;
   7:	pop
   8:	aload_0
   9:	invokeinterface	#98,  1; //InterfaceMethod scala/collection/generic/TraversableTemplate.thisCollection:()Lscala/collection/generic/TraversableTemplate;
   14:	checkcast	#19; //class scala/collection/generic/MutableSetTemplate
   17:	areturn
  LineNumberTable: 
   line 165: 0

  LocalVariableTable: 
   Start  Length  Slot  Name   Signature
   0      18      0    $this       Lscala/collection/generic/MutableSetTemplate;
   0      18      1    elem       Ljava/lang/Object;


public static scala.collection.generic.MutableSetTemplate $plus$plus(scala.collection.generic.MutableSetTemplate, scala.collection.Iterator);
  Code:
   Stack=4, Locals=2, Args_size=2
   0:	aload_1
   1:	new	#124; //class scala/collection/generic/MutableSetTemplate$$anonfun$$plus$plus$2
   4:	dup
   5:	aload_0
   6:	invokespecial	#125; //Method scala/collection/generic/MutableSetTemplate$$anonfun$$plus$plus$2."<init>":(Lscala/collection/generic/MutableSetTemplate;)V
   9:	invokeinterface	#54,  2; //InterfaceMethod scala/collection/Iterator.foreach:(Lscala/Function1;)V
   14:	aload_0
   15:	invokeinterface	#98,  1; //InterfaceMethod scala/collection/generic/TraversableTemplate.thisCollection:()Lscala/collection/generic/TraversableTemplate;
   20:	checkcast	#19; //class scala/collection/generic/MutableSetTemplate
   23:	areturn
  LineNumberTable: 
   line 154: 0
   line 155: 14

  LocalVariableTable: 
   Start  Length  Slot  Name   Signature
   0      24      0    $this       Lscala/collection/generic/MutableSetTemplate;
   0      24      1    iter       Lscala/collection/Iterator;


public static scala.collection.generic.MutableSetTemplate $plus$plus(scala.collection.generic.MutableSetTemplate, scala.collection.Traversable);
  Code:
   Stack=4, Locals=2, Args_size=2
   0:	aload_1
   1:	new	#127; //class scala/collection/generic/MutableSetTemplate$$anonfun$$plus$plus$1
   4:	dup
   5:	aload_0
   6:	invokespecial	#128; //Method scala/collection/generic/MutableSetTemplate$$anonfun$$plus$plus$1."<init>":(Lscala/collection/generic/MutableSetTemplate;)V
   9:	invokeinterface	#107,  2; //InterfaceMethod scala/collection/generic/TraversableClass.foreach:(Lscala/Function1;)V
   14:	aload_0
   15:	invokeinterface	#98,  1; //InterfaceMethod scala/collection/generic/TraversableTemplate.thisCollection:()Lscala/collection/generic/TraversableTemplate;
   20:	checkcast	#19; //class scala/collection/generic/MutableSetTemplate
   23:	areturn
  LineNumberTable: 
   line 141: 0
   line 142: 14

  LocalVariableTable: 
   Start  Length  Slot  Name   Signature
   0      24      0    $this       Lscala/collection/generic/MutableSetTemplate;
   0      24      1    iter       Lscala/collection/Traversable;


public static scala.collection.generic.MutableSetTemplate $plus(scala.collection.generic.MutableSetTemplate, java.lang.Object, java.lang.Object, scala.collection.Sequence);
  Code:
   Stack=2, Locals=4, Args_size=4
   0:	aload_0
   1:	aload_1
   2:	invokeinterface	#23,  2; //InterfaceMethod scala/collection/generic/MutableSetTemplate.$plus$eq:(Ljava/lang/Object;)Lscala/collection/generic/MutableSetTemplate;
   7:	aload_2
   8:	invokeinterface	#23,  2; //InterfaceMethod scala/collection/generic/MutableSetTemplate.$plus$eq:(Ljava/lang/Object;)Lscala/collection/generic/MutableSetTemplate;
   13:	aload_3
   14:	invokeinterface	#135,  2; //InterfaceMethod scala/collection/generic/Growable.$plus$plus$eq:(Lscala/collection/Traversable;)Lscala/collection/generic/Growable;
   19:	pop
   20:	aload_0
   21:	invokeinterface	#98,  1; //InterfaceMethod scala/collection/generic/TraversableTemplate.thisCollection:()Lscala/collection/generic/TraversableTemplate;
   26:	checkcast	#19; //class scala/collection/generic/MutableSetTemplate
   29:	areturn
  LineNumberTable: 
   line 129: 0
   line 130: 20

  LocalVariableTable: 
   Start  Length  Slot  Name   Signature
   0      30      0    $this       Lscala/collection/generic/MutableSetTemplate;
   0      30      1    elem1       Ljava/lang/Object;
   0      30      2    elem2       Ljava/lang/Object;
   0      30      3    elems       Lscala/collection/Sequence;


public static scala.collection.generic.MutableSetTemplate $plus(scala.collection.generic.MutableSetTemplate, java.lang.Object);
  Code:
   Stack=2, Locals=2, Args_size=2
   0:	aload_0
   1:	aload_1
   2:	invokeinterface	#23,  2; //InterfaceMethod scala/collection/generic/MutableSetTemplate.$plus$eq:(Ljava/lang/Object;)Lscala/collection/generic/MutableSetTemplate;
   7:	pop
   8:	aload_0
   9:	invokeinterface	#98,  1; //InterfaceMethod scala/collection/generic/TraversableTemplate.thisCollection:()Lscala/collection/generic/TraversableTemplate;
   14:	checkcast	#19; //class scala/collection/generic/MutableSetTemplate
   17:	areturn
  LineNumberTable: 
   line 117: 0

  LocalVariableTable: 
   Start  Length  Slot  Name   Signature
   0      18      0    $this       Lscala/collection/generic/MutableSetTemplate;
   0      18      1    elem       Ljava/lang/Object;


public static scala.collection.generic.MutableSetTemplate result(scala.collection.generic.MutableSetTemplate);
  Code:
   Stack=1, Locals=1, Args_size=1
   0:	aload_0
   1:	invokeinterface	#98,  1; //InterfaceMethod scala/collection/generic/TraversableTemplate.thisCollection:()Lscala/collection/generic/TraversableTemplate;
   6:	checkcast	#19; //class scala/collection/generic/MutableSetTemplate
   9:	areturn
  LineNumberTable: 
   line 108: 0

  LocalVariableTable: 
   Start  Length  Slot  Name   Signature
   0      10      0    $this       Lscala/collection/generic/MutableSetTemplate;


public static scala.collection.mutable.Set clone(scala.collection.generic.MutableSetTemplate);
  Code:
   Stack=2, Locals=1, Args_size=1
   0:	aload_0
   1:	invokeinterface	#145,  1; //InterfaceMethod scala/collection/generic/SetTemplate.empty:()Lscala/collection/generic/SetTemplate;
   6:	checkcast	#131; //class scala/collection/generic/Growable
   9:	aload_0
   10:	invokeinterface	#98,  1; //InterfaceMethod scala/collection/generic/TraversableTemplate.thisCollection:()Lscala/collection/generic/TraversableTemplate;
   15:	checkcast	#147; //class scala/collection/Traversable
   18:	invokeinterface	#135,  2; //InterfaceMethod scala/collection/generic/Growable.$plus$plus$eq:(Lscala/collection/Traversable;)Lscala/collection/generic/Growable;
   23:	checkcast	#149; //class scala/collection/mutable/Set
   26:	areturn
  LineNumberTable: 
   line 106: 0

  LocalVariableTable: 
   Start  Length  Slot  Name   Signature
   0      27      0    $this       Lscala/collection/generic/MutableSetTemplate;


public static void clear(scala.collection.generic.MutableSetTemplate);
  Code:
   Stack=4, Locals=1, Args_size=1
   0:	aload_0
   1:	new	#151; //class scala/collection/generic/MutableSetTemplate$$anonfun$clear$1
   4:	dup
   5:	aload_0
   6:	invokespecial	#152; //Method scala/collection/generic/MutableSetTemplate$$anonfun$clear$1."<init>":(Lscala/collection/generic/MutableSetTemplate;)V
   9:	invokeinterface	#155,  2; //InterfaceMethod scala/collection/generic/IterableTemplate.foreach:(Lscala/Function1;)V
   14:	return
  LineNumberTable: 
   line 104: 0

  LocalVariableTable: 
   Start  Length  Slot  Name   Signature
   0      15      0    $this       Lscala/collection/generic/MutableSetTemplate;


public static void retain(scala.collection.generic.MutableSetTemplate, scala.Function1);
  Code:
   Stack=5, Locals=2, Args_size=2
   0:	aload_0
   1:	invokeinterface	#161,  1; //InterfaceMethod scala/collection/generic/TraversableTemplate.toList:()Lscala/collection/immutable/List;
   6:	new	#163; //class scala/collection/generic/MutableSetTemplate$$anonfun$retain$1
   9:	dup
   10:	aload_0
   11:	aload_1
   12:	invokespecial	#165; //Method scala/collection/generic/MutableSetTemplate$$anonfun$retain$1."<init>":(Lscala/collection/generic/MutableSetTemplate;Lscala/Function1;)V
   15:	invokeinterface	#168,  2; //InterfaceMethod scala/collection/generic/LinearSequenceTemplate.foreach:(Lscala/Function1;)V
   20:	return
  LineNumberTable: 
   line 99: 0

  LocalVariableTable: 
   Start  Length  Slot  Name   Signature
   0      21      0    $this       Lscala/collection/generic/MutableSetTemplate;
   0      21      1    p$1       Lscala/Function1;


public static void update(scala.collection.generic.MutableSetTemplate, java.lang.Object, boolean);
  Code:
   Stack=2, Locals=3, Args_size=3
   0:	iload_2
   1:	ifeq	15
   4:	aload_0
   5:	aload_1
   6:	invokeinterface	#23,  2; //InterfaceMethod scala/collection/generic/MutableSetTemplate.$plus$eq:(Ljava/lang/Object;)Lscala/collection/generic/MutableSetTemplate;
   11:	pop
   12:	goto	23
   15:	aload_0
   16:	aload_1
   17:	invokeinterface	#29,  2; //InterfaceMethod scala/collection/generic/MutableSetTemplate.$minus$eq:(Ljava/lang/Object;)Lscala/collection/generic/MutableSetTemplate;
   22:	pop
   23:	return
  LineNumberTable: 
   line 82: 0

  LocalVariableTable: 
   Start  Length  Slot  Name   Signature
   0      24      0    $this       Lscala/collection/generic/MutableSetTemplate;
   0      24      1    elem       Ljava/lang/Object;
   0      24      2    included       Z


public static boolean remove(scala.collection.generic.MutableSetTemplate, java.lang.Object);
  Code:
   Stack=2, Locals=3, Args_size=2
   0:	aload_0
   1:	aload_1
   2:	invokeinterface	#180,  2; //InterfaceMethod scala/collection/generic/SetTemplate.contains:(Ljava/lang/Object;)Z
   7:	istore_2
   8:	aload_0
   9:	aload_1
   10:	invokeinterface	#29,  2; //InterfaceMethod scala/collection/generic/MutableSetTemplate.$minus$eq:(Ljava/lang/Object;)Lscala/collection/generic/MutableSetTemplate;
   15:	pop
   16:	iload_2
   17:	ireturn
  LineNumberTable: 
   line 70: 0
   line 71: 8
   line 72: 16

  LocalVariableTable: 
   Start  Length  Slot  Name   Signature
   0      18      0    $this       Lscala/collection/generic/MutableSetTemplate;
   0      18      1    elem       Ljava/lang/Object;
   8      9      2    r       Z


public static boolean add(scala.collection.generic.MutableSetTemplate, java.lang.Object);
  Code:
   Stack=2, Locals=3, Args_size=2
   0:	aload_0
   1:	aload_1
   2:	invokeinterface	#180,  2; //InterfaceMethod scala/collection/generic/SetTemplate.contains:(Ljava/lang/Object;)Z
   7:	istore_2
   8:	aload_0
   9:	aload_1
   10:	invokeinterface	#23,  2; //InterfaceMethod scala/collection/generic/MutableSetTemplate.$plus$eq:(Ljava/lang/Object;)Lscala/collection/generic/MutableSetTemplate;
   15:	pop
   16:	iload_2
   17:	ireturn
  LineNumberTable: 
   line 59: 0
   line 60: 8
   line 61: 16

  LocalVariableTable: 
   Start  Length  Slot  Name   Signature
   0      18      0    $this       Lscala/collection/generic/MutableSetTemplate;
   0      18      1    elem       Ljava/lang/Object;
   8      9      2    r       Z


public static scala.collection.generic.Builder newBuilder(scala.collection.generic.MutableSetTemplate);
  Code:
   Stack=1, Locals=1, Args_size=1
   0:	aload_0
   1:	invokeinterface	#145,  1; //InterfaceMethod scala/collection/generic/SetTemplate.empty:()Lscala/collection/generic/SetTemplate;
   6:	checkcast	#186; //class scala/collection/generic/Builder
   9:	areturn
  LineNumberTable: 
   line 51: 0

  LocalVariableTable: 
   Start  Length  Slot  Name   Signature
   0      10      0    $this       Lscala/collection/generic/MutableSetTemplate;


}

