Compiled from "package.scala"
public final class scala.collection.generic.package$ extends java.lang.Object implements scala.ScalaObject
  SourceFile: "package.scala"
  Scala: length = 0x
   
  minor version: 0
  major version: 49
  Constant pool:
const #1 = Asciz	SourceFile;
const #2 = Asciz	package.scala;
const #3 = Asciz	Scala;
const #4 = Asciz	MODULE$;
const #5 = Asciz	Lscala/collection/generic/package$;;
const #6 = Asciz	<clinit>;
const #7 = Asciz	()V;
const #8 = Asciz	Code;
const #9 = Asciz	scala/collection/generic/package$;
const #10 = class	#9;	//  scala/collection/generic/package$
const #11 = Asciz	<init>;
const #12 = NameAndType	#11:#7;//  "<init>":()V
const #13 = Method	#10.#12;	//  scala/collection/generic/package$."<init>":()V
const #14 = Asciz	LineNumberTable;
const #15 = Asciz	java/lang/Object;
const #16 = class	#15;	//  java/lang/Object
const #17 = Method	#16.#12;	//  java/lang/Object."<init>":()V
const #18 = NameAndType	#4:#5;//  MODULE$:Lscala/collection/generic/package$;
const #19 = Field	#10.#18;	//  scala/collection/generic/package$.MODULE$:Lscala/collection/generic/package$;
const #20 = Asciz	scala/ScalaObject;
const #21 = class	#20;	//  scala/ScalaObject

{
public static final scala.collection.generic.package$ MODULE$;

public static {};
  Code:
   Stack=1, Locals=0, Args_size=0
   0:	new	#10; //class scala/collection/generic/package$
   3:	invokespecial	#13; //Method "<init>":()V
   6:	return

}

