Compiled from "SequenceViewTemplate.scala"
public abstract class scala.collection.generic.SequenceViewTemplate$DroppedWhile$class extends java.lang.Object
  SourceFile: "SequenceViewTemplate.scala"
  Scala: length = 0x
   
  InnerClass: 
   public abstract #65= #13 of #64; //DroppedWhile=class scala/collection/generic/SequenceViewTemplate$DroppedWhile of class scala/collection/generic/SequenceViewTemplate
   public abstract #65= #52 of #67; //DroppedWhile=class scala/collection/generic/TraversableViewTemplate$DroppedWhile of class scala/collection/generic/TraversableViewTemplate
  minor version: 0
  major version: 49
  Constant pool:
const #1 = Asciz	SourceFile;
const #2 = Asciz	SequenceViewTemplate.scala;
const #3 = Asciz	$init$;
const #4 = Asciz	(Lscala/collection/generic/SequenceViewTemplate$DroppedWhile;)V;
const #5 = Asciz	Code;
const #6 = Asciz	LineNumberTable;
const #7 = Asciz	$this;
const #8 = Asciz	Lscala/collection/generic/SequenceViewTemplate$DroppedWhile;;
const #9 = Asciz	LocalVariableTable;
const #10 = Asciz	apply;
const #11 = Asciz	(Lscala/collection/generic/SequenceViewTemplate$DroppedWhile;I)Ljava/lang/Object;;
const #12 = Asciz	scala/collection/generic/SequenceViewTemplate$DroppedWhile;
const #13 = class	#12;	//  scala/collection/generic/SequenceViewTemplate$DroppedWhile
const #14 = Asciz	scala$collection$generic$SequenceViewTemplate$DroppedWhile$$$outer;
const #15 = Asciz	()Lscala/collection/generic/SequenceViewTemplate;;
const #16 = NameAndType	#14:#15;//  scala$collection$generic$SequenceViewTemplate$DroppedWhile$$$outer:()Lscala/collection/generic/SequenceViewTemplate;
const #17 = InterfaceMethod	#13.#16;	//  scala/collection/generic/SequenceViewTemplate$DroppedWhile.scala$collection$generic$SequenceViewTemplate$DroppedWhile$$$outer:()Lscala/collection/generic/SequenceViewTemplate;
const #18 = Asciz	start;
const #19 = Asciz	()I;
const #20 = NameAndType	#18:#19;//  start:()I
const #21 = InterfaceMethod	#13.#20;	//  scala/collection/generic/SequenceViewTemplate$DroppedWhile.start:()I
const #22 = Asciz	scala/collection/generic/SequenceTemplate;
const #23 = class	#22;	//  scala/collection/generic/SequenceTemplate
const #24 = Asciz	(I)Ljava/lang/Object;;
const #25 = NameAndType	#10:#24;//  apply:(I)Ljava/lang/Object;
const #26 = InterfaceMethod	#23.#25;	//  scala/collection/generic/SequenceTemplate.apply:(I)Ljava/lang/Object;
const #27 = Asciz	java/lang/IndexOutOfBoundsException;
const #28 = class	#27;	//  java/lang/IndexOutOfBoundsException
const #29 = Asciz	scala/runtime/BoxesRunTime;
const #30 = class	#29;	//  scala/runtime/BoxesRunTime
const #31 = Asciz	boxToInteger;
const #32 = Asciz	(I)Ljava/lang/Integer;;
const #33 = NameAndType	#31:#32;//  boxToInteger:(I)Ljava/lang/Integer;
const #34 = Method	#30.#33;	//  scala/runtime/BoxesRunTime.boxToInteger:(I)Ljava/lang/Integer;
const #35 = Asciz	java/lang/Object;
const #36 = class	#35;	//  java/lang/Object
const #37 = Asciz	toString;
const #38 = Asciz	()Ljava/lang/String;;
const #39 = NameAndType	#37:#38;//  toString:()Ljava/lang/String;
const #40 = Method	#36.#39;	//  java/lang/Object.toString:()Ljava/lang/String;
const #41 = Asciz	<init>;
const #42 = Asciz	(Ljava/lang/String;)V;
const #43 = NameAndType	#41:#42;//  "<init>":(Ljava/lang/String;)V
const #44 = Method	#28.#43;	//  java/lang/IndexOutOfBoundsException."<init>":(Ljava/lang/String;)V
const #45 = Asciz	idx;
const #46 = Asciz	I;
const #47 = Asciz	length;
const #48 = Asciz	(Lscala/collection/generic/SequenceViewTemplate$DroppedWhile;)I;
const #49 = NameAndType	#47:#19;//  length:()I
const #50 = InterfaceMethod	#23.#49;	//  scala/collection/generic/SequenceTemplate.length:()I
const #51 = Asciz	scala/collection/generic/TraversableViewTemplate$DroppedWhile;
const #52 = class	#51;	//  scala/collection/generic/TraversableViewTemplate$DroppedWhile
const #53 = Asciz	pred;
const #54 = Asciz	()Lscala/Function1;;
const #55 = NameAndType	#53:#54;//  pred:()Lscala/Function1;
const #56 = InterfaceMethod	#52.#55;	//  scala/collection/generic/TraversableViewTemplate$DroppedWhile.pred:()Lscala/Function1;
const #57 = Asciz	prefixLength;
const #58 = Asciz	(Lscala/Function1;)I;
const #59 = NameAndType	#57:#58;//  prefixLength:(Lscala/Function1;)I
const #60 = InterfaceMethod	#23.#59;	//  scala/collection/generic/SequenceTemplate.prefixLength:(Lscala/Function1;)I
const #61 = Asciz	Scala;
const #62 = Asciz	InnerClasses;
const #63 = Asciz	scala/collection/generic/SequenceViewTemplate;
const #64 = class	#63;	//  scala/collection/generic/SequenceViewTemplate
const #65 = Asciz	DroppedWhile;
const #66 = Asciz	scala/collection/generic/TraversableViewTemplate;
const #67 = class	#66;	//  scala/collection/generic/TraversableViewTemplate
const #68 = Asciz	scala/collection/generic/SequenceViewTemplate$DroppedWhile$class;
const #69 = class	#68;	//  scala/collection/generic/SequenceViewTemplate$DroppedWhile$class

{
public static void $init$(scala.collection.generic.SequenceViewTemplate$DroppedWhile);
  Code:
   Stack=0, Locals=1, Args_size=1
   0:	return
  LineNumberTable: 
   line 97: 0

  LocalVariableTable: 
   Start  Length  Slot  Name   Signature
   0      1      0    $this       Lscala/collection/generic/SequenceViewTemplate$DroppedWhile;


public static java.lang.Object apply(scala.collection.generic.SequenceViewTemplate$DroppedWhile, int);
  Code:
   Stack=3, Locals=2, Args_size=2
   0:	iload_1
   1:	iconst_0
   2:	if_icmplt	25
   5:	aload_0
   6:	invokeinterface	#17,  1; //InterfaceMethod scala/collection/generic/SequenceViewTemplate$DroppedWhile.scala$collection$generic$SequenceViewTemplate$DroppedWhile$$$outer:()Lscala/collection/generic/SequenceViewTemplate;
   11:	iload_1
   12:	aload_0
   13:	invokeinterface	#21,  1; //InterfaceMethod scala/collection/generic/SequenceViewTemplate$DroppedWhile.start:()I
   18:	iadd
   19:	invokeinterface	#26,  2; //InterfaceMethod scala/collection/generic/SequenceTemplate.apply:(I)Ljava/lang/Object;
   24:	areturn
   25:	new	#28; //class java/lang/IndexOutOfBoundsException
   28:	dup
   29:	iload_1
   30:	invokestatic	#34; //Method scala/runtime/BoxesRunTime.boxToInteger:(I)Ljava/lang/Integer;
   33:	invokevirtual	#40; //Method java/lang/Object.toString:()Ljava/lang/String;
   36:	invokespecial	#44; //Method java/lang/IndexOutOfBoundsException."<init>":(Ljava/lang/String;)V
   39:	athrow
  LineNumberTable: 
   line 101: 0
   line 102: 25

  LocalVariableTable: 
   Start  Length  Slot  Name   Signature
   0      40      0    $this       Lscala/collection/generic/SequenceViewTemplate$DroppedWhile;
   0      40      1    idx       I


public static int length(scala.collection.generic.SequenceViewTemplate$DroppedWhile);
  Code:
   Stack=2, Locals=1, Args_size=1
   0:	aload_0
   1:	invokeinterface	#17,  1; //InterfaceMethod scala/collection/generic/SequenceViewTemplate$DroppedWhile.scala$collection$generic$SequenceViewTemplate$DroppedWhile$$$outer:()Lscala/collection/generic/SequenceViewTemplate;
   6:	invokeinterface	#50,  1; //InterfaceMethod scala/collection/generic/SequenceTemplate.length:()I
   11:	aload_0
   12:	invokeinterface	#21,  1; //InterfaceMethod scala/collection/generic/SequenceViewTemplate$DroppedWhile.start:()I
   17:	isub
   18:	ireturn
  LineNumberTable: 
   line 99: 0

  LocalVariableTable: 
   Start  Length  Slot  Name   Signature
   0      19      0    $this       Lscala/collection/generic/SequenceViewTemplate$DroppedWhile;


public static int start(scala.collection.generic.SequenceViewTemplate$DroppedWhile);
  Code:
   Stack=2, Locals=1, Args_size=1
   0:	aload_0
   1:	invokeinterface	#17,  1; //InterfaceMethod scala/collection/generic/SequenceViewTemplate$DroppedWhile.scala$collection$generic$SequenceViewTemplate$DroppedWhile$$$outer:()Lscala/collection/generic/SequenceViewTemplate;
   6:	aload_0
   7:	invokeinterface	#56,  1; //InterfaceMethod scala/collection/generic/TraversableViewTemplate$DroppedWhile.pred:()Lscala/Function1;
   12:	invokeinterface	#60,  2; //InterfaceMethod scala/collection/generic/SequenceTemplate.prefixLength:(Lscala/Function1;)I
   17:	ireturn
  LineNumberTable: 
   line 98: 0

  LocalVariableTable: 
   Start  Length  Slot  Name   Signature
   0      18      0    $this       Lscala/collection/generic/SequenceViewTemplate$DroppedWhile;


}

