Compiled from "SequenceForwarder.scala"
public abstract class scala.collection.generic.SequenceForwarder$class extends java.lang.Object
  SourceFile: "SequenceForwarder.scala"
  Scala: length = 0x
   
  minor version: 0
  major version: 49
  Constant pool:
const #1 = Asciz	SourceFile;
const #2 = Asciz	SequenceForwarder.scala;
const #3 = Asciz	$init$;
const #4 = Asciz	(Lscala/collection/generic/SequenceForwarder;)V;
const #5 = Asciz	Code;
const #6 = Asciz	LineNumberTable;
const #7 = Asciz	$this;
const #8 = Asciz	Lscala/collection/generic/SequenceForwarder;;
const #9 = Asciz	LocalVariableTable;
const #10 = Asciz	indices;
const #11 = Asciz	(Lscala/collection/generic/SequenceForwarder;)Lscala/Range;;
const #12 = Asciz	scala/collection/generic/SequenceForwarder;
const #13 = class	#12;	//  scala/collection/generic/SequenceForwarder
const #14 = Asciz	underlying;
const #15 = Asciz	()Lscala/collection/Sequence;;
const #16 = NameAndType	#14:#15;//  underlying:()Lscala/collection/Sequence;
const #17 = InterfaceMethod	#13.#16;	//  scala/collection/generic/SequenceForwarder.underlying:()Lscala/collection/Sequence;
const #18 = Asciz	scala/collection/generic/SequenceTemplate;
const #19 = class	#18;	//  scala/collection/generic/SequenceTemplate
const #20 = Asciz	()Lscala/Range;;
const #21 = NameAndType	#10:#20;//  indices:()Lscala/Range;
const #22 = InterfaceMethod	#19.#21;	//  scala/collection/generic/SequenceTemplate.indices:()Lscala/Range;
const #23 = Asciz	contains;
const #24 = Asciz	(Lscala/collection/generic/SequenceForwarder;Ljava/lang/Object;)Z;
const #25 = Asciz	(Ljava/lang/Object;)Z;
const #26 = NameAndType	#23:#25;//  contains:(Ljava/lang/Object;)Z
const #27 = InterfaceMethod	#19.#26;	//  scala/collection/generic/SequenceTemplate.contains:(Ljava/lang/Object;)Z
const #28 = Asciz	elem;
const #29 = Asciz	Ljava/lang/Object;;
const #30 = Asciz	indexOfSeq;
const #31 = Asciz	(Lscala/collection/generic/SequenceForwarder;Lscala/collection/Sequence;)I;
const #32 = Asciz	(Lscala/collection/Sequence;)I;
const #33 = NameAndType	#30:#32;//  indexOfSeq:(Lscala/collection/Sequence;)I
const #34 = InterfaceMethod	#19.#33;	//  scala/collection/generic/SequenceTemplate.indexOfSeq:(Lscala/collection/Sequence;)I
const #35 = Asciz	that;
const #36 = Asciz	Lscala/collection/Sequence;;
const #37 = Asciz	endsWith;
const #38 = Asciz	(Lscala/collection/generic/SequenceForwarder;Lscala/collection/Sequence;)Z;
const #39 = Asciz	(Lscala/collection/Sequence;)Z;
const #40 = NameAndType	#37:#39;//  endsWith:(Lscala/collection/Sequence;)Z
const #41 = InterfaceMethod	#19.#40;	//  scala/collection/generic/SequenceTemplate.endsWith:(Lscala/collection/Sequence;)Z
const #42 = Asciz	startsWith;
const #43 = Asciz	(Lscala/collection/generic/SequenceForwarder;Lscala/collection/Sequence;I)Z;
const #44 = Asciz	(Lscala/collection/Sequence;I)Z;
const #45 = NameAndType	#42:#44;//  startsWith:(Lscala/collection/Sequence;I)Z
const #46 = InterfaceMethod	#19.#45;	//  scala/collection/generic/SequenceTemplate.startsWith:(Lscala/collection/Sequence;I)Z
const #47 = Asciz	offset;
const #48 = Asciz	I;
const #49 = Asciz	reverseIterator;
const #50 = Asciz	(Lscala/collection/generic/SequenceForwarder;)Lscala/collection/Iterator;;
const #51 = Asciz	()Lscala/collection/Iterator;;
const #52 = NameAndType	#49:#51;//  reverseIterator:()Lscala/collection/Iterator;
const #53 = InterfaceMethod	#19.#52;	//  scala/collection/generic/SequenceTemplate.reverseIterator:()Lscala/collection/Iterator;
const #54 = Asciz	indexOf;
const #55 = Asciz	(Lscala/collection/generic/SequenceForwarder;Ljava/lang/Object;I)I;
const #56 = Asciz	(Ljava/lang/Object;I)I;
const #57 = NameAndType	#54:#56;//  indexOf:(Ljava/lang/Object;I)I
const #58 = InterfaceMethod	#19.#57;	//  scala/collection/generic/SequenceTemplate.indexOf:(Ljava/lang/Object;I)I
const #59 = Asciz	from;
const #60 = Asciz	indexWhere;
const #61 = Asciz	(Lscala/collection/generic/SequenceForwarder;Lscala/Function1;I)I;
const #62 = Asciz	(Lscala/Function1;I)I;
const #63 = NameAndType	#60:#62;//  indexWhere:(Lscala/Function1;I)I
const #64 = InterfaceMethod	#19.#63;	//  scala/collection/generic/SequenceTemplate.indexWhere:(Lscala/Function1;I)I
const #65 = Asciz	p;
const #66 = Asciz	Lscala/Function1;;
const #67 = Asciz	prefixLength;
const #68 = Asciz	(Lscala/collection/generic/SequenceForwarder;Lscala/Function1;)I;
const #69 = Asciz	(Lscala/Function1;)I;
const #70 = NameAndType	#67:#69;//  prefixLength:(Lscala/Function1;)I
const #71 = InterfaceMethod	#19.#70;	//  scala/collection/generic/SequenceTemplate.prefixLength:(Lscala/Function1;)I
const #72 = Asciz	segmentLength;
const #73 = NameAndType	#72:#62;//  segmentLength:(Lscala/Function1;I)I
const #74 = InterfaceMethod	#19.#73;	//  scala/collection/generic/SequenceTemplate.segmentLength:(Lscala/Function1;I)I
const #75 = Asciz	lengthCompare;
const #76 = Asciz	(Lscala/collection/generic/SequenceForwarder;I)I;
const #77 = Asciz	(I)I;
const #78 = NameAndType	#75:#77;//  lengthCompare:(I)I
const #79 = InterfaceMethod	#19.#78;	//  scala/collection/generic/SequenceTemplate.lengthCompare:(I)I
const #80 = Asciz	l;
const #81 = Asciz	length;
const #82 = Asciz	(Lscala/collection/generic/SequenceForwarder;)I;
const #83 = Asciz	()I;
const #84 = NameAndType	#81:#83;//  length:()I
const #85 = InterfaceMethod	#19.#84;	//  scala/collection/generic/SequenceTemplate.length:()I
const #86 = Asciz	isDefinedAt;
const #87 = Asciz	(Lscala/collection/generic/SequenceForwarder;I)Z;
const #88 = Asciz	(I)Z;
const #89 = NameAndType	#86:#88;//  isDefinedAt:(I)Z
const #90 = InterfaceMethod	#19.#89;	//  scala/collection/generic/SequenceTemplate.isDefinedAt:(I)Z
const #91 = Asciz	x;
const #92 = Asciz	apply;
const #93 = Asciz	(Lscala/collection/generic/SequenceForwarder;I)Ljava/lang/Object;;
const #94 = Asciz	(I)Ljava/lang/Object;;
const #95 = NameAndType	#92:#94;//  apply:(I)Ljava/lang/Object;
const #96 = InterfaceMethod	#19.#95;	//  scala/collection/generic/SequenceTemplate.apply:(I)Ljava/lang/Object;
const #97 = Asciz	i;
const #98 = Asciz	Scala;
const #99 = Asciz	scala/collection/generic/SequenceForwarder$class;
const #100 = class	#99;	//  scala/collection/generic/SequenceForwarder$class
const #101 = Asciz	java/lang/Object;
const #102 = class	#101;	//  java/lang/Object

{
public static void $init$(scala.collection.generic.SequenceForwarder);
  Code:
   Stack=0, Locals=1, Args_size=1
   0:	return
  LineNumberTable: 
   line 27: 0

  LocalVariableTable: 
   Start  Length  Slot  Name   Signature
   0      1      0    $this       Lscala/collection/generic/SequenceForwarder;


public static scala.Range indices(scala.collection.generic.SequenceForwarder);
  Code:
   Stack=1, Locals=1, Args_size=1
   0:	aload_0
   1:	invokeinterface	#17,  1; //InterfaceMethod scala/collection/generic/SequenceForwarder.underlying:()Lscala/collection/Sequence;
   6:	invokeinterface	#22,  1; //InterfaceMethod scala/collection/generic/SequenceTemplate.indices:()Lscala/Range;
   11:	areturn
  LineNumberTable: 
   line 50: 0

  LocalVariableTable: 
   Start  Length  Slot  Name   Signature
   0      12      0    $this       Lscala/collection/generic/SequenceForwarder;


public static boolean contains(scala.collection.generic.SequenceForwarder, java.lang.Object);
  Code:
   Stack=2, Locals=2, Args_size=2
   0:	aload_0
   1:	invokeinterface	#17,  1; //InterfaceMethod scala/collection/generic/SequenceForwarder.underlying:()Lscala/collection/Sequence;
   6:	aload_1
   7:	invokeinterface	#27,  2; //InterfaceMethod scala/collection/generic/SequenceTemplate.contains:(Ljava/lang/Object;)Z
   12:	ireturn
  LineNumberTable: 
   line 49: 0

  LocalVariableTable: 
   Start  Length  Slot  Name   Signature
   0      13      0    $this       Lscala/collection/generic/SequenceForwarder;
   0      13      1    elem       Ljava/lang/Object;


public static int indexOfSeq(scala.collection.generic.SequenceForwarder, scala.collection.Sequence);
  Code:
   Stack=2, Locals=2, Args_size=2
   0:	aload_0
   1:	invokeinterface	#17,  1; //InterfaceMethod scala/collection/generic/SequenceForwarder.underlying:()Lscala/collection/Sequence;
   6:	aload_1
   7:	invokeinterface	#34,  2; //InterfaceMethod scala/collection/generic/SequenceTemplate.indexOfSeq:(Lscala/collection/Sequence;)I
   12:	ireturn
  LineNumberTable: 
   line 48: 0

  LocalVariableTable: 
   Start  Length  Slot  Name   Signature
   0      13      0    $this       Lscala/collection/generic/SequenceForwarder;
   0      13      1    that       Lscala/collection/Sequence;


public static boolean endsWith(scala.collection.generic.SequenceForwarder, scala.collection.Sequence);
  Code:
   Stack=2, Locals=2, Args_size=2
   0:	aload_0
   1:	invokeinterface	#17,  1; //InterfaceMethod scala/collection/generic/SequenceForwarder.underlying:()Lscala/collection/Sequence;
   6:	aload_1
   7:	invokeinterface	#41,  2; //InterfaceMethod scala/collection/generic/SequenceTemplate.endsWith:(Lscala/collection/Sequence;)Z
   12:	ireturn
  LineNumberTable: 
   line 47: 0

  LocalVariableTable: 
   Start  Length  Slot  Name   Signature
   0      13      0    $this       Lscala/collection/generic/SequenceForwarder;
   0      13      1    that       Lscala/collection/Sequence;


public static boolean startsWith(scala.collection.generic.SequenceForwarder, scala.collection.Sequence, int);
  Code:
   Stack=3, Locals=3, Args_size=3
   0:	aload_0
   1:	invokeinterface	#17,  1; //InterfaceMethod scala/collection/generic/SequenceForwarder.underlying:()Lscala/collection/Sequence;
   6:	aload_1
   7:	iload_2
   8:	invokeinterface	#46,  3; //InterfaceMethod scala/collection/generic/SequenceTemplate.startsWith:(Lscala/collection/Sequence;I)Z
   13:	ireturn
  LineNumberTable: 
   line 46: 0

  LocalVariableTable: 
   Start  Length  Slot  Name   Signature
   0      14      0    $this       Lscala/collection/generic/SequenceForwarder;
   0      14      1    that       Lscala/collection/Sequence;
   0      14      2    offset       I


public static scala.collection.Iterator reverseIterator(scala.collection.generic.SequenceForwarder);
  Code:
   Stack=1, Locals=1, Args_size=1
   0:	aload_0
   1:	invokeinterface	#17,  1; //InterfaceMethod scala/collection/generic/SequenceForwarder.underlying:()Lscala/collection/Sequence;
   6:	invokeinterface	#53,  1; //InterfaceMethod scala/collection/generic/SequenceTemplate.reverseIterator:()Lscala/collection/Iterator;
   11:	areturn
  LineNumberTable: 
   line 45: 0

  LocalVariableTable: 
   Start  Length  Slot  Name   Signature
   0      12      0    $this       Lscala/collection/generic/SequenceForwarder;


public static int indexOf(scala.collection.generic.SequenceForwarder, java.lang.Object, int);
  Code:
   Stack=3, Locals=3, Args_size=3
   0:	aload_0
   1:	invokeinterface	#17,  1; //InterfaceMethod scala/collection/generic/SequenceForwarder.underlying:()Lscala/collection/Sequence;
   6:	aload_1
   7:	iload_2
   8:	invokeinterface	#58,  3; //InterfaceMethod scala/collection/generic/SequenceTemplate.indexOf:(Ljava/lang/Object;I)I
   13:	ireturn
  LineNumberTable: 
   line 44: 0

  LocalVariableTable: 
   Start  Length  Slot  Name   Signature
   0      14      0    $this       Lscala/collection/generic/SequenceForwarder;
   0      14      1    elem       Ljava/lang/Object;
   0      14      2    from       I


public static int indexWhere(scala.collection.generic.SequenceForwarder, scala.Function1, int);
  Code:
   Stack=3, Locals=3, Args_size=3
   0:	aload_0
   1:	invokeinterface	#17,  1; //InterfaceMethod scala/collection/generic/SequenceForwarder.underlying:()Lscala/collection/Sequence;
   6:	aload_1
   7:	iload_2
   8:	invokeinterface	#64,  3; //InterfaceMethod scala/collection/generic/SequenceTemplate.indexWhere:(Lscala/Function1;I)I
   13:	ireturn
  LineNumberTable: 
   line 43: 0

  LocalVariableTable: 
   Start  Length  Slot  Name   Signature
   0      14      0    $this       Lscala/collection/generic/SequenceForwarder;
   0      14      1    p       Lscala/Function1;
   0      14      2    from       I


public static int prefixLength(scala.collection.generic.SequenceForwarder, scala.Function1);
  Code:
   Stack=2, Locals=2, Args_size=2
   0:	aload_0
   1:	invokeinterface	#17,  1; //InterfaceMethod scala/collection/generic/SequenceForwarder.underlying:()Lscala/collection/Sequence;
   6:	aload_1
   7:	invokeinterface	#71,  2; //InterfaceMethod scala/collection/generic/SequenceTemplate.prefixLength:(Lscala/Function1;)I
   12:	ireturn
  LineNumberTable: 
   line 42: 0

  LocalVariableTable: 
   Start  Length  Slot  Name   Signature
   0      13      0    $this       Lscala/collection/generic/SequenceForwarder;
   0      13      1    p       Lscala/Function1;


public static int segmentLength(scala.collection.generic.SequenceForwarder, scala.Function1, int);
  Code:
   Stack=3, Locals=3, Args_size=3
   0:	aload_0
   1:	invokeinterface	#17,  1; //InterfaceMethod scala/collection/generic/SequenceForwarder.underlying:()Lscala/collection/Sequence;
   6:	aload_1
   7:	iload_2
   8:	invokeinterface	#74,  3; //InterfaceMethod scala/collection/generic/SequenceTemplate.segmentLength:(Lscala/Function1;I)I
   13:	ireturn
  LineNumberTable: 
   line 41: 0

  LocalVariableTable: 
   Start  Length  Slot  Name   Signature
   0      14      0    $this       Lscala/collection/generic/SequenceForwarder;
   0      14      1    p       Lscala/Function1;
   0      14      2    from       I


public static int lengthCompare(scala.collection.generic.SequenceForwarder, int);
  Code:
   Stack=2, Locals=2, Args_size=2
   0:	aload_0
   1:	invokeinterface	#17,  1; //InterfaceMethod scala/collection/generic/SequenceForwarder.underlying:()Lscala/collection/Sequence;
   6:	iload_1
   7:	invokeinterface	#79,  2; //InterfaceMethod scala/collection/generic/SequenceTemplate.lengthCompare:(I)I
   12:	ireturn
  LineNumberTable: 
   line 40: 0

  LocalVariableTable: 
   Start  Length  Slot  Name   Signature
   0      13      0    $this       Lscala/collection/generic/SequenceForwarder;
   0      13      1    l       I


public static int length(scala.collection.generic.SequenceForwarder);
  Code:
   Stack=1, Locals=1, Args_size=1
   0:	aload_0
   1:	invokeinterface	#17,  1; //InterfaceMethod scala/collection/generic/SequenceForwarder.underlying:()Lscala/collection/Sequence;
   6:	invokeinterface	#85,  1; //InterfaceMethod scala/collection/generic/SequenceTemplate.length:()I
   11:	ireturn
  LineNumberTable: 
   line 39: 0

  LocalVariableTable: 
   Start  Length  Slot  Name   Signature
   0      12      0    $this       Lscala/collection/generic/SequenceForwarder;


public static boolean isDefinedAt(scala.collection.generic.SequenceForwarder, int);
  Code:
   Stack=2, Locals=2, Args_size=2
   0:	aload_0
   1:	invokeinterface	#17,  1; //InterfaceMethod scala/collection/generic/SequenceForwarder.underlying:()Lscala/collection/Sequence;
   6:	iload_1
   7:	invokeinterface	#90,  2; //InterfaceMethod scala/collection/generic/SequenceTemplate.isDefinedAt:(I)Z
   12:	ireturn
  LineNumberTable: 
   line 34: 0

  LocalVariableTable: 
   Start  Length  Slot  Name   Signature
   0      13      0    $this       Lscala/collection/generic/SequenceForwarder;
   0      13      1    x       I


public static java.lang.Object apply(scala.collection.generic.SequenceForwarder, int);
  Code:
   Stack=2, Locals=2, Args_size=2
   0:	aload_0
   1:	invokeinterface	#17,  1; //InterfaceMethod scala/collection/generic/SequenceForwarder.underlying:()Lscala/collection/Sequence;
   6:	iload_1
   7:	invokeinterface	#96,  2; //InterfaceMethod scala/collection/generic/SequenceTemplate.apply:(I)Ljava/lang/Object;
   12:	areturn
  LineNumberTable: 
   line 33: 0

  LocalVariableTable: 
   Start  Length  Slot  Name   Signature
   0      13      0    $this       Lscala/collection/generic/SequenceForwarder;
   0      13      1    i       I


}

