Compiled from "SequenceViewTemplate.scala"
public abstract class scala.collection.generic.SequenceViewTemplate$Reversed$class extends java.lang.Object
  SourceFile: "SequenceViewTemplate.scala"
  Scala: length = 0x
   
  InnerClass: 
   public abstract #62= #19 of #61; //Reversed=class scala/collection/generic/SequenceViewTemplate$Reversed of class scala/collection/generic/SequenceViewTemplate
  minor version: 0
  major version: 49
  Constant pool:
const #1 = Asciz	SourceFile;
const #2 = Asciz	SequenceViewTemplate.scala;
const #3 = Asciz	$init$;
const #4 = Asciz	(Lscala/collection/generic/SequenceViewTemplate$Reversed;)V;
const #5 = Asciz	Code;
const #6 = Asciz	LineNumberTable;
const #7 = Asciz	$this;
const #8 = Asciz	Lscala/collection/generic/SequenceViewTemplate$Reversed;;
const #9 = Asciz	LocalVariableTable;
const #10 = Asciz	stringPrefix;
const #11 = Asciz	(Lscala/collection/generic/SequenceViewTemplate$Reversed;)Ljava/lang/String;;
const #12 = Asciz	scala/collection/mutable/StringBuilder;
const #13 = class	#12;	//  scala/collection/mutable/StringBuilder
const #14 = Asciz	<init>;
const #15 = Asciz	()V;
const #16 = NameAndType	#14:#15;//  "<init>":()V
const #17 = Method	#13.#16;	//  scala/collection/mutable/StringBuilder."<init>":()V
const #18 = Asciz	scala/collection/generic/SequenceViewTemplate$Reversed;
const #19 = class	#18;	//  scala/collection/generic/SequenceViewTemplate$Reversed
const #20 = Asciz	scala$collection$generic$SequenceViewTemplate$Reversed$$super$stringPrefix;
const #21 = Asciz	()Ljava/lang/String;;
const #22 = NameAndType	#20:#21;//  scala$collection$generic$SequenceViewTemplate$Reversed$$super$stringPrefix:()Ljava/lang/String;
const #23 = InterfaceMethod	#19.#22;	//  scala/collection/generic/SequenceViewTemplate$Reversed.scala$collection$generic$SequenceViewTemplate$Reversed$$super$stringPrefix:()Ljava/lang/String;
const #24 = Asciz	append;
const #25 = Asciz	(Ljava/lang/Object;)Lscala/collection/mutable/StringBuilder;;
const #26 = NameAndType	#24:#25;//  append:(Ljava/lang/Object;)Lscala/collection/mutable/StringBuilder;
const #27 = Method	#13.#26;	//  scala/collection/mutable/StringBuilder.append:(Ljava/lang/Object;)Lscala/collection/mutable/StringBuilder;
const #28 = Asciz	R;
const #29 = String	#28;	//  R
const #30 = Asciz	toString;
const #31 = NameAndType	#30:#21;//  toString:()Ljava/lang/String;
const #32 = Method	#13.#31;	//  scala/collection/mutable/StringBuilder.toString:()Ljava/lang/String;
const #33 = Asciz	apply;
const #34 = Asciz	(Lscala/collection/generic/SequenceViewTemplate$Reversed;I)Ljava/lang/Object;;
const #35 = Asciz	scala$collection$generic$SequenceViewTemplate$Reversed$$$outer;
const #36 = Asciz	()Lscala/collection/generic/SequenceViewTemplate;;
const #37 = NameAndType	#35:#36;//  scala$collection$generic$SequenceViewTemplate$Reversed$$$outer:()Lscala/collection/generic/SequenceViewTemplate;
const #38 = InterfaceMethod	#19.#37;	//  scala/collection/generic/SequenceViewTemplate$Reversed.scala$collection$generic$SequenceViewTemplate$Reversed$$$outer:()Lscala/collection/generic/SequenceViewTemplate;
const #39 = Asciz	length;
const #40 = Asciz	()I;
const #41 = NameAndType	#39:#40;//  length:()I
const #42 = InterfaceMethod	#19.#41;	//  scala/collection/generic/SequenceViewTemplate$Reversed.length:()I
const #43 = Asciz	scala/collection/generic/SequenceTemplate;
const #44 = class	#43;	//  scala/collection/generic/SequenceTemplate
const #45 = Asciz	(I)Ljava/lang/Object;;
const #46 = NameAndType	#33:#45;//  apply:(I)Ljava/lang/Object;
const #47 = InterfaceMethod	#44.#46;	//  scala/collection/generic/SequenceTemplate.apply:(I)Ljava/lang/Object;
const #48 = Asciz	idx;
const #49 = Asciz	I;
const #50 = Asciz	(Lscala/collection/generic/SequenceViewTemplate$Reversed;)I;
const #51 = InterfaceMethod	#44.#41;	//  scala/collection/generic/SequenceTemplate.length:()I
const #52 = Asciz	iterator;
const #53 = Asciz	(Lscala/collection/generic/SequenceViewTemplate$Reversed;)Lscala/collection/Iterator;;
const #54 = Asciz	reverseIterator;
const #55 = Asciz	()Lscala/collection/Iterator;;
const #56 = NameAndType	#54:#55;//  reverseIterator:()Lscala/collection/Iterator;
const #57 = InterfaceMethod	#44.#56;	//  scala/collection/generic/SequenceTemplate.reverseIterator:()Lscala/collection/Iterator;
const #58 = Asciz	Scala;
const #59 = Asciz	InnerClasses;
const #60 = Asciz	scala/collection/generic/SequenceViewTemplate;
const #61 = class	#60;	//  scala/collection/generic/SequenceViewTemplate
const #62 = Asciz	Reversed;
const #63 = Asciz	scala/collection/generic/SequenceViewTemplate$Reversed$class;
const #64 = class	#63;	//  scala/collection/generic/SequenceViewTemplate$Reversed$class
const #65 = Asciz	java/lang/Object;
const #66 = class	#65;	//  java/lang/Object

{
public static void $init$(scala.collection.generic.SequenceViewTemplate$Reversed);
  Code:
   Stack=0, Locals=1, Args_size=1
   0:	return
  LineNumberTable: 
   line 105: 0

  LocalVariableTable: 
   Start  Length  Slot  Name   Signature
   0      1      0    $this       Lscala/collection/generic/SequenceViewTemplate$Reversed;


public static java.lang.String stringPrefix(scala.collection.generic.SequenceViewTemplate$Reversed);
  Code:
   Stack=2, Locals=1, Args_size=1
   0:	new	#13; //class scala/collection/mutable/StringBuilder
   3:	dup
   4:	invokespecial	#17; //Method scala/collection/mutable/StringBuilder."<init>":()V
   7:	aload_0
   8:	invokeinterface	#23,  1; //InterfaceMethod scala/collection/generic/SequenceViewTemplate$Reversed.scala$collection$generic$SequenceViewTemplate$Reversed$$super$stringPrefix:()Ljava/lang/String;
   13:	invokevirtual	#27; //Method scala/collection/mutable/StringBuilder.append:(Ljava/lang/Object;)Lscala/collection/mutable/StringBuilder;
   16:	ldc	#29; //String R
   18:	invokevirtual	#27; //Method scala/collection/mutable/StringBuilder.append:(Ljava/lang/Object;)Lscala/collection/mutable/StringBuilder;
   21:	invokevirtual	#32; //Method scala/collection/mutable/StringBuilder.toString:()Ljava/lang/String;
   24:	areturn
  LineNumberTable: 
   line 109: 0

  LocalVariableTable: 
   Start  Length  Slot  Name   Signature
   0      25      0    $this       Lscala/collection/generic/SequenceViewTemplate$Reversed;


public static java.lang.Object apply(scala.collection.generic.SequenceViewTemplate$Reversed, int);
  Code:
   Stack=3, Locals=2, Args_size=2
   0:	aload_0
   1:	invokeinterface	#38,  1; //InterfaceMethod scala/collection/generic/SequenceViewTemplate$Reversed.scala$collection$generic$SequenceViewTemplate$Reversed$$$outer:()Lscala/collection/generic/SequenceViewTemplate;
   6:	aload_0
   7:	invokeinterface	#42,  1; //InterfaceMethod scala/collection/generic/SequenceViewTemplate$Reversed.length:()I
   12:	iconst_1
   13:	isub
   14:	iload_1
   15:	isub
   16:	invokeinterface	#47,  2; //InterfaceMethod scala/collection/generic/SequenceTemplate.apply:(I)Ljava/lang/Object;
   21:	areturn
  LineNumberTable: 
   line 108: 0

  LocalVariableTable: 
   Start  Length  Slot  Name   Signature
   0      22      0    $this       Lscala/collection/generic/SequenceViewTemplate$Reversed;
   0      22      1    idx       I


public static int length(scala.collection.generic.SequenceViewTemplate$Reversed);
  Code:
   Stack=1, Locals=1, Args_size=1
   0:	aload_0
   1:	invokeinterface	#38,  1; //InterfaceMethod scala/collection/generic/SequenceViewTemplate$Reversed.scala$collection$generic$SequenceViewTemplate$Reversed$$$outer:()Lscala/collection/generic/SequenceViewTemplate;
   6:	invokeinterface	#51,  1; //InterfaceMethod scala/collection/generic/SequenceTemplate.length:()I
   11:	ireturn
  LineNumberTable: 
   line 107: 0

  LocalVariableTable: 
   Start  Length  Slot  Name   Signature
   0      12      0    $this       Lscala/collection/generic/SequenceViewTemplate$Reversed;


public static scala.collection.Iterator iterator(scala.collection.generic.SequenceViewTemplate$Reversed);
  Code:
   Stack=1, Locals=1, Args_size=1
   0:	aload_0
   1:	invokeinterface	#38,  1; //InterfaceMethod scala/collection/generic/SequenceViewTemplate$Reversed.scala$collection$generic$SequenceViewTemplate$Reversed$$$outer:()Lscala/collection/generic/SequenceViewTemplate;
   6:	invokeinterface	#57,  1; //InterfaceMethod scala/collection/generic/SequenceTemplate.reverseIterator:()Lscala/collection/Iterator;
   11:	areturn
  LineNumberTable: 
   line 106: 0

  LocalVariableTable: 
   Start  Length  Slot  Name   Signature
   0      12      0    $this       Lscala/collection/generic/SequenceViewTemplate$Reversed;


}

