Compiled from "SequenceProxyTemplate.scala"
public abstract class scala.collection.generic.SequenceProxyTemplate$class extends java.lang.Object
  SourceFile: "SequenceProxyTemplate.scala"
  Scala: length = 0x
   
  InnerClass: 
   public final #218= #141 of #130; //$anonfun$lastIndexOf$1=class scala/collection/generic/SequenceProxyTemplate$$anonfun$lastIndexOf$1 of class scala/collection/generic/SequenceProxyTemplate
  minor version: 0
  major version: 49
  Constant pool:
const #1 = Asciz	SourceFile;
const #2 = Asciz	SequenceProxyTemplate.scala;
const #3 = Asciz	$init$;
const #4 = Asciz	(Lscala/collection/generic/SequenceProxyTemplate;)V;
const #5 = Asciz	Code;
const #6 = Asciz	LineNumberTable;
const #7 = Asciz	$this;
const #8 = Asciz	Lscala/collection/generic/SequenceProxyTemplate;;
const #9 = Asciz	LocalVariableTable;
const #10 = Asciz	containsSlice;
const #11 = Asciz	(Lscala/collection/generic/SequenceProxyTemplate;Lscala/collection/Sequence;)Z;
const #12 = Asciz	scala/collection/generic/TraversableProxyTemplate;
const #13 = class	#12;	//  scala/collection/generic/TraversableProxyTemplate
const #14 = Asciz	self;
const #15 = Asciz	()Lscala/collection/generic/TraversableTemplate;;
const #16 = NameAndType	#14:#15;//  self:()Lscala/collection/generic/TraversableTemplate;
const #17 = InterfaceMethod	#13.#16;	//  scala/collection/generic/TraversableProxyTemplate.self:()Lscala/collection/generic/TraversableTemplate;
const #18 = Asciz	scala/collection/generic/SequenceTemplate;
const #19 = class	#18;	//  scala/collection/generic/SequenceTemplate
const #20 = Asciz	(Lscala/collection/Sequence;)Z;
const #21 = NameAndType	#10:#20;//  containsSlice:(Lscala/collection/Sequence;)Z
const #22 = InterfaceMethod	#19.#21;	//  scala/collection/generic/SequenceTemplate.containsSlice:(Lscala/collection/Sequence;)Z
const #23 = Asciz	that;
const #24 = Asciz	Lscala/collection/Sequence;;
const #25 = Asciz	equalsWith;
const #26 = Asciz	(Lscala/collection/generic/SequenceProxyTemplate;Lscala/collection/Sequence;Lscala/Function2;)Z;
const #27 = Asciz	(Lscala/collection/Sequence;Lscala/Function2;)Z;
const #28 = NameAndType	#25:#27;//  equalsWith:(Lscala/collection/Sequence;Lscala/Function2;)Z
const #29 = InterfaceMethod	#19.#28;	//  scala/collection/generic/SequenceTemplate.equalsWith:(Lscala/collection/Sequence;Lscala/Function2;)Z
const #30 = Asciz	f;
const #31 = Asciz	Lscala/Function2;;
const #32 = Asciz	slice;
const #33 = Asciz	(Lscala/collection/generic/SequenceProxyTemplate;I)Lscala/collection/Sequence;;
const #34 = Asciz	(I)Lscala/collection/Sequence;;
const #35 = NameAndType	#32:#34;//  slice:(I)Lscala/collection/Sequence;
const #36 = InterfaceMethod	#19.#35;	//  scala/collection/generic/SequenceTemplate.slice:(I)Lscala/collection/Sequence;
const #37 = Asciz	from;
const #38 = Asciz	I;
const #39 = Asciz	findLastIndexOf;
const #40 = Asciz	(Lscala/collection/generic/SequenceProxyTemplate;Lscala/Function1;)I;
const #41 = Asciz	(Lscala/Function1;)I;
const #42 = NameAndType	#39:#41;//  findLastIndexOf:(Lscala/Function1;)I
const #43 = InterfaceMethod	#19.#42;	//  scala/collection/generic/SequenceTemplate.findLastIndexOf:(Lscala/Function1;)I
const #44 = Asciz	p;
const #45 = Asciz	Lscala/Function1;;
const #46 = Asciz	view;
const #47 = Asciz	(Lscala/collection/generic/SequenceProxyTemplate;II)Lscala/collection/generic/SequenceView;;
const #48 = Asciz	(II)Lscala/collection/generic/SequenceView;;
const #49 = NameAndType	#46:#48;//  view:(II)Lscala/collection/generic/SequenceView;
const #50 = InterfaceMethod	#19.#49;	//  scala/collection/generic/SequenceTemplate.view:(II)Lscala/collection/generic/SequenceView;
const #51 = Asciz	until;
const #52 = Asciz	(Lscala/collection/generic/SequenceProxyTemplate;)Ljava/lang/Object;;
const #53 = Asciz	()Ljava/lang/Object;;
const #54 = NameAndType	#46:#53;//  view:()Ljava/lang/Object;
const #55 = InterfaceMethod	#19.#54;	//  scala/collection/generic/SequenceTemplate.view:()Ljava/lang/Object;
const #56 = Asciz	indices;
const #57 = Asciz	(Lscala/collection/generic/SequenceProxyTemplate;)Lscala/Range;;
const #58 = Asciz	()Lscala/Range;;
const #59 = NameAndType	#56:#58;//  indices:()Lscala/Range;
const #60 = InterfaceMethod	#19.#59;	//  scala/collection/generic/SequenceTemplate.indices:()Lscala/Range;
const #61 = Asciz	padTo;
const #62 = Asciz	(Lscala/collection/generic/SequenceProxyTemplate;ILjava/lang/Object;Lscala/collection/generic/BuilderFactory;)Ljava/lang/Object;;
const #63 = Asciz	(ILjava/lang/Object;Lscala/collection/generic/BuilderFactory;)Ljava/lang/Object;;
const #64 = NameAndType	#61:#63;//  padTo:(ILjava/lang/Object;Lscala/collection/generic/BuilderFactory;)Ljava/lang/Object;
const #65 = InterfaceMethod	#19.#64;	//  scala/collection/generic/SequenceTemplate.padTo:(ILjava/lang/Object;Lscala/collection/generic/BuilderFactory;)Ljava/lang/Object;
const #66 = Asciz	len;
const #67 = Asciz	elem;
const #68 = Asciz	Ljava/lang/Object;;
const #69 = Asciz	bf;
const #70 = Asciz	Lscala/collection/generic/BuilderFactory;;
const #71 = Asciz	patch;
const #72 = Asciz	(Lscala/collection/generic/SequenceProxyTemplate;ILscala/collection/Sequence;ILscala/collection/generic/BuilderFactory;)Ljava/lang/Object;;
const #73 = Asciz	(ILscala/collection/Sequence;ILscala/collection/generic/BuilderFactory;)Ljava/lang/Object;;
const #74 = NameAndType	#71:#73;//  patch:(ILscala/collection/Sequence;ILscala/collection/generic/BuilderFactory;)Ljava/lang/Object;
const #75 = InterfaceMethod	#19.#74;	//  scala/collection/generic/SequenceTemplate.patch:(ILscala/collection/Sequence;ILscala/collection/generic/BuilderFactory;)Ljava/lang/Object;
const #76 = Asciz	replaced;
const #77 = Asciz	removeDuplicates;
const #78 = Asciz	(Lscala/collection/generic/SequenceProxyTemplate;)Lscala/collection/generic/SequenceTemplate;;
const #79 = Asciz	()Lscala/collection/generic/IterableTemplate;;
const #80 = NameAndType	#77:#79;//  removeDuplicates:()Lscala/collection/generic/IterableTemplate;
const #81 = InterfaceMethod	#19.#80;	//  scala/collection/generic/SequenceTemplate.removeDuplicates:()Lscala/collection/generic/IterableTemplate;
const #82 = Asciz	intersect;
const #83 = Asciz	(Lscala/collection/generic/SequenceProxyTemplate;Lscala/collection/Sequence;)Lscala/collection/generic/SequenceTemplate;;
const #84 = Asciz	(Lscala/collection/Sequence;)Lscala/collection/generic/IterableTemplate;;
const #85 = NameAndType	#82:#84;//  intersect:(Lscala/collection/Sequence;)Lscala/collection/generic/IterableTemplate;
const #86 = InterfaceMethod	#19.#85;	//  scala/collection/generic/SequenceTemplate.intersect:(Lscala/collection/Sequence;)Lscala/collection/generic/IterableTemplate;
const #87 = Asciz	diff;
const #88 = NameAndType	#87:#84;//  diff:(Lscala/collection/Sequence;)Lscala/collection/generic/IterableTemplate;
const #89 = InterfaceMethod	#19.#88;	//  scala/collection/generic/SequenceTemplate.diff:(Lscala/collection/Sequence;)Lscala/collection/generic/IterableTemplate;
const #90 = Asciz	union;
const #91 = Asciz	(Lscala/collection/generic/SequenceProxyTemplate;Lscala/collection/Sequence;Lscala/collection/generic/BuilderFactory;)Ljava/lang/Object;;
const #92 = Asciz	(Lscala/collection/Sequence;Lscala/collection/generic/BuilderFactory;)Ljava/lang/Object;;
const #93 = NameAndType	#90:#92;//  union:(Lscala/collection/Sequence;Lscala/collection/generic/BuilderFactory;)Ljava/lang/Object;
const #94 = InterfaceMethod	#19.#93;	//  scala/collection/generic/SequenceTemplate.union:(Lscala/collection/Sequence;Lscala/collection/generic/BuilderFactory;)Ljava/lang/Object;
const #95 = Asciz	contains;
const #96 = Asciz	(Lscala/collection/generic/SequenceProxyTemplate;Ljava/lang/Object;)Z;
const #97 = Asciz	(Ljava/lang/Object;)Z;
const #98 = NameAndType	#95:#97;//  contains:(Ljava/lang/Object;)Z
const #99 = InterfaceMethod	#19.#98;	//  scala/collection/generic/SequenceTemplate.contains:(Ljava/lang/Object;)Z
const #100 = Asciz	indexOfSeq;
const #101 = Asciz	(Lscala/collection/generic/SequenceProxyTemplate;Lscala/collection/Sequence;)I;
const #102 = Asciz	(Lscala/collection/Sequence;)I;
const #103 = NameAndType	#100:#102;//  indexOfSeq:(Lscala/collection/Sequence;)I
const #104 = InterfaceMethod	#19.#103;	//  scala/collection/generic/SequenceTemplate.indexOfSeq:(Lscala/collection/Sequence;)I
const #105 = Asciz	endsWith;
const #106 = NameAndType	#105:#20;//  endsWith:(Lscala/collection/Sequence;)Z
const #107 = InterfaceMethod	#19.#106;	//  scala/collection/generic/SequenceTemplate.endsWith:(Lscala/collection/Sequence;)Z
const #108 = Asciz	startsWith;
const #109 = NameAndType	#108:#20;//  startsWith:(Lscala/collection/Sequence;)Z
const #110 = InterfaceMethod	#19.#109;	//  scala/collection/generic/SequenceTemplate.startsWith:(Lscala/collection/Sequence;)Z
const #111 = Asciz	(Lscala/collection/generic/SequenceProxyTemplate;Lscala/collection/Sequence;I)Z;
const #112 = Asciz	(Lscala/collection/Sequence;I)Z;
const #113 = NameAndType	#108:#112;//  startsWith:(Lscala/collection/Sequence;I)Z
const #114 = InterfaceMethod	#19.#113;	//  scala/collection/generic/SequenceTemplate.startsWith:(Lscala/collection/Sequence;I)Z
const #115 = Asciz	offset;
const #116 = Asciz	reverseIterator;
const #117 = Asciz	(Lscala/collection/generic/SequenceProxyTemplate;)Lscala/collection/Iterator;;
const #118 = Asciz	()Lscala/collection/Iterator;;
const #119 = NameAndType	#116:#118;//  reverseIterator:()Lscala/collection/Iterator;
const #120 = InterfaceMethod	#19.#119;	//  scala/collection/generic/SequenceTemplate.reverseIterator:()Lscala/collection/Iterator;
const #121 = Asciz	reverse;
const #122 = NameAndType	#121:#79;//  reverse:()Lscala/collection/generic/IterableTemplate;
const #123 = InterfaceMethod	#19.#122;	//  scala/collection/generic/SequenceTemplate.reverse:()Lscala/collection/generic/IterableTemplate;
const #124 = Asciz	lastIndexWhere;
const #125 = Asciz	(Lscala/collection/generic/SequenceProxyTemplate;Lscala/Function1;I)I;
const #126 = NameAndType	#124:#41;//  lastIndexWhere:(Lscala/Function1;)I
const #127 = InterfaceMethod	#19.#126;	//  scala/collection/generic/SequenceTemplate.lastIndexWhere:(Lscala/Function1;)I
const #128 = Asciz	end;
const #129 = Asciz	scala/collection/generic/SequenceProxyTemplate;
const #130 = class	#129;	//  scala/collection/generic/SequenceProxyTemplate
const #131 = Asciz	length;
const #132 = Asciz	()I;
const #133 = NameAndType	#131:#132;//  length:()I
const #134 = InterfaceMethod	#130.#133;	//  scala/collection/generic/SequenceProxyTemplate.length:()I
const #135 = Asciz	(Lscala/Function1;I)I;
const #136 = NameAndType	#124:#135;//  lastIndexWhere:(Lscala/Function1;I)I
const #137 = InterfaceMethod	#19.#136;	//  scala/collection/generic/SequenceTemplate.lastIndexWhere:(Lscala/Function1;I)I
const #138 = Asciz	lastIndexOf;
const #139 = Asciz	(Lscala/collection/generic/SequenceProxyTemplate;Ljava/lang/Object;I)I;
const #140 = Asciz	scala/collection/generic/SequenceProxyTemplate$$anonfun$lastIndexOf$1;
const #141 = class	#140;	//  scala/collection/generic/SequenceProxyTemplate$$anonfun$lastIndexOf$1
const #142 = Asciz	<init>;
const #143 = Asciz	(Lscala/collection/generic/SequenceProxyTemplate;Ljava/lang/Object;)V;
const #144 = NameAndType	#142:#143;//  "<init>":(Lscala/collection/generic/SequenceProxyTemplate;Ljava/lang/Object;)V
const #145 = Method	#141.#144;	//  scala/collection/generic/SequenceProxyTemplate$$anonfun$lastIndexOf$1."<init>":(Lscala/collection/generic/SequenceProxyTemplate;Ljava/lang/Object;)V
const #146 = Asciz	elem$1;
const #147 = Asciz	(Lscala/collection/generic/SequenceProxyTemplate;Ljava/lang/Object;)I;
const #148 = Asciz	(Ljava/lang/Object;)I;
const #149 = NameAndType	#138:#148;//  lastIndexOf:(Ljava/lang/Object;)I
const #150 = InterfaceMethod	#19.#149;	//  scala/collection/generic/SequenceTemplate.lastIndexOf:(Ljava/lang/Object;)I
const #151 = Asciz	indexOf;
const #152 = Asciz	(Ljava/lang/Object;I)I;
const #153 = NameAndType	#151:#152;//  indexOf:(Ljava/lang/Object;I)I
const #154 = InterfaceMethod	#19.#153;	//  scala/collection/generic/SequenceTemplate.indexOf:(Ljava/lang/Object;I)I
const #155 = NameAndType	#151:#148;//  indexOf:(Ljava/lang/Object;)I
const #156 = InterfaceMethod	#19.#155;	//  scala/collection/generic/SequenceTemplate.indexOf:(Ljava/lang/Object;)I
const #157 = Asciz	findIndexOf;
const #158 = NameAndType	#157:#41;//  findIndexOf:(Lscala/Function1;)I
const #159 = InterfaceMethod	#19.#158;	//  scala/collection/generic/SequenceTemplate.findIndexOf:(Lscala/Function1;)I
const #160 = Asciz	indexWhere;
const #161 = NameAndType	#160:#135;//  indexWhere:(Lscala/Function1;I)I
const #162 = InterfaceMethod	#19.#161;	//  scala/collection/generic/SequenceTemplate.indexWhere:(Lscala/Function1;I)I
const #163 = NameAndType	#160:#41;//  indexWhere:(Lscala/Function1;)I
const #164 = InterfaceMethod	#19.#163;	//  scala/collection/generic/SequenceTemplate.indexWhere:(Lscala/Function1;)I
const #165 = Asciz	prefixLength;
const #166 = NameAndType	#165:#41;//  prefixLength:(Lscala/Function1;)I
const #167 = InterfaceMethod	#19.#166;	//  scala/collection/generic/SequenceTemplate.prefixLength:(Lscala/Function1;)I
const #168 = Asciz	segmentLength;
const #169 = NameAndType	#168:#135;//  segmentLength:(Lscala/Function1;I)I
const #170 = InterfaceMethod	#19.#169;	//  scala/collection/generic/SequenceTemplate.segmentLength:(Lscala/Function1;I)I
const #171 = Asciz	zipWithIndex;
const #172 = Asciz	(Lscala/collection/generic/SequenceProxyTemplate;Lscala/collection/generic/BuilderFactory;)Ljava/lang/Object;;
const #173 = Asciz	(Lscala/collection/generic/BuilderFactory;)Ljava/lang/Object;;
const #174 = NameAndType	#171:#173;//  zipWithIndex:(Lscala/collection/generic/BuilderFactory;)Ljava/lang/Object;
const #175 = InterfaceMethod	#19.#174;	//  scala/collection/generic/SequenceTemplate.zipWithIndex:(Lscala/collection/generic/BuilderFactory;)Ljava/lang/Object;
const #176 = Asciz	zipAll;
const #177 = Asciz	(Lscala/collection/generic/SequenceProxyTemplate;Lscala/collection/Sequence;Ljava/lang/Object;Ljava/lang/Object;Lscala/collection/generic/BuilderFactory;)Ljava/lang/Object;;
const #178 = Asciz	(Lscala/collection/Sequence;Ljava/lang/Object;Ljava/lang/Object;Lscala/collection/generic/BuilderFactory;)Ljava/lang/Object;;
const #179 = NameAndType	#176:#178;//  zipAll:(Lscala/collection/Sequence;Ljava/lang/Object;Ljava/lang/Object;Lscala/collection/generic/BuilderFactory;)Ljava/lang/Object;
const #180 = InterfaceMethod	#19.#179;	//  scala/collection/generic/SequenceTemplate.zipAll:(Lscala/collection/Sequence;Ljava/lang/Object;Ljava/lang/Object;Lscala/collection/generic/BuilderFactory;)Ljava/lang/Object;
const #181 = Asciz	thisElem;
const #182 = Asciz	thatElem;
const #183 = Asciz	zip;
const #184 = NameAndType	#183:#92;//  zip:(Lscala/collection/Sequence;Lscala/collection/generic/BuilderFactory;)Ljava/lang/Object;
const #185 = InterfaceMethod	#19.#184;	//  scala/collection/generic/SequenceTemplate.zip:(Lscala/collection/Sequence;Lscala/collection/generic/BuilderFactory;)Ljava/lang/Object;
const #186 = Asciz	isDefinedAt;
const #187 = Asciz	(Lscala/collection/generic/SequenceProxyTemplate;I)Z;
const #188 = Asciz	(I)Z;
const #189 = NameAndType	#186:#188;//  isDefinedAt:(I)Z
const #190 = InterfaceMethod	#19.#189;	//  scala/collection/generic/SequenceTemplate.isDefinedAt:(I)Z
const #191 = Asciz	x;
const #192 = Asciz	size;
const #193 = Asciz	(Lscala/collection/generic/SequenceProxyTemplate;)I;
const #194 = NameAndType	#192:#132;//  size:()I
const #195 = InterfaceMethod	#19.#194;	//  scala/collection/generic/SequenceTemplate.size:()I
const #196 = Asciz	lengthCompare;
const #197 = Asciz	(Lscala/collection/generic/SequenceProxyTemplate;I)I;
const #198 = Asciz	(I)I;
const #199 = NameAndType	#196:#198;//  lengthCompare:(I)I
const #200 = InterfaceMethod	#19.#199;	//  scala/collection/generic/SequenceTemplate.lengthCompare:(I)I
const #201 = Asciz	apply;
const #202 = Asciz	(Lscala/collection/generic/SequenceProxyTemplate;I)Ljava/lang/Object;;
const #203 = Asciz	scala/Function1;
const #204 = class	#203;	//  scala/Function1
const #205 = Asciz	scala/runtime/BoxesRunTime;
const #206 = class	#205;	//  scala/runtime/BoxesRunTime
const #207 = Asciz	boxToInteger;
const #208 = Asciz	(I)Ljava/lang/Integer;;
const #209 = NameAndType	#207:#208;//  boxToInteger:(I)Ljava/lang/Integer;
const #210 = Method	#206.#209;	//  scala/runtime/BoxesRunTime.boxToInteger:(I)Ljava/lang/Integer;
const #211 = Asciz	(Ljava/lang/Object;)Ljava/lang/Object;;
const #212 = NameAndType	#201:#211;//  apply:(Ljava/lang/Object;)Ljava/lang/Object;
const #213 = InterfaceMethod	#204.#212;	//  scala/Function1.apply:(Ljava/lang/Object;)Ljava/lang/Object;
const #214 = Asciz	idx;
const #215 = InterfaceMethod	#19.#133;	//  scala/collection/generic/SequenceTemplate.length:()I
const #216 = Asciz	Scala;
const #217 = Asciz	InnerClasses;
const #218 = Asciz	$anonfun$lastIndexOf$1;
const #219 = Asciz	scala/collection/generic/SequenceProxyTemplate$class;
const #220 = class	#219;	//  scala/collection/generic/SequenceProxyTemplate$class
const #221 = Asciz	java/lang/Object;
const #222 = class	#221;	//  java/lang/Object

{
public static void $init$(scala.collection.generic.SequenceProxyTemplate);
  Code:
   Stack=0, Locals=1, Args_size=1
   0:	return
  LineNumberTable: 
   line 26: 0

  LocalVariableTable: 
   Start  Length  Slot  Name   Signature
   0      1      0    $this       Lscala/collection/generic/SequenceProxyTemplate;


public static boolean containsSlice(scala.collection.generic.SequenceProxyTemplate, scala.collection.Sequence);
  Code:
   Stack=2, Locals=2, Args_size=2
   0:	aload_0
   1:	invokeinterface	#17,  1; //InterfaceMethod scala/collection/generic/TraversableProxyTemplate.self:()Lscala/collection/generic/TraversableTemplate;
   6:	checkcast	#19; //class scala/collection/generic/SequenceTemplate
   9:	aload_1
   10:	invokeinterface	#22,  2; //InterfaceMethod scala/collection/generic/SequenceTemplate.containsSlice:(Lscala/collection/Sequence;)Z
   15:	ireturn
  LineNumberTable: 
   line 65: 0

  LocalVariableTable: 
   Start  Length  Slot  Name   Signature
   0      16      0    $this       Lscala/collection/generic/SequenceProxyTemplate;
   0      16      1    that       Lscala/collection/Sequence;


public static boolean equalsWith(scala.collection.generic.SequenceProxyTemplate, scala.collection.Sequence, scala.Function2);
  Code:
   Stack=3, Locals=3, Args_size=3
   0:	aload_0
   1:	invokeinterface	#17,  1; //InterfaceMethod scala/collection/generic/TraversableProxyTemplate.self:()Lscala/collection/generic/TraversableTemplate;
   6:	checkcast	#19; //class scala/collection/generic/SequenceTemplate
   9:	aload_1
   10:	aload_2
   11:	invokeinterface	#29,  3; //InterfaceMethod scala/collection/generic/SequenceTemplate.equalsWith:(Lscala/collection/Sequence;Lscala/Function2;)Z
   16:	ireturn
  LineNumberTable: 
   line 64: 0

  LocalVariableTable: 
   Start  Length  Slot  Name   Signature
   0      17      0    $this       Lscala/collection/generic/SequenceProxyTemplate;
   0      17      1    that       Lscala/collection/Sequence;
   0      17      2    f       Lscala/Function2;


public static scala.collection.Sequence slice(scala.collection.generic.SequenceProxyTemplate, int);
  Code:
   Stack=2, Locals=2, Args_size=2
   0:	aload_0
   1:	invokeinterface	#17,  1; //InterfaceMethod scala/collection/generic/TraversableProxyTemplate.self:()Lscala/collection/generic/TraversableTemplate;
   6:	checkcast	#19; //class scala/collection/generic/SequenceTemplate
   9:	iload_1
   10:	invokeinterface	#36,  2; //InterfaceMethod scala/collection/generic/SequenceTemplate.slice:(I)Lscala/collection/Sequence;
   15:	areturn
  LineNumberTable: 
   line 63: 0

  LocalVariableTable: 
   Start  Length  Slot  Name   Signature
   0      16      0    $this       Lscala/collection/generic/SequenceProxyTemplate;
   0      16      1    from       I


public static int findLastIndexOf(scala.collection.generic.SequenceProxyTemplate, scala.Function1);
  Code:
   Stack=2, Locals=2, Args_size=2
   0:	aload_0
   1:	invokeinterface	#17,  1; //InterfaceMethod scala/collection/generic/TraversableProxyTemplate.self:()Lscala/collection/generic/TraversableTemplate;
   6:	checkcast	#19; //class scala/collection/generic/SequenceTemplate
   9:	aload_1
   10:	invokeinterface	#43,  2; //InterfaceMethod scala/collection/generic/SequenceTemplate.findLastIndexOf:(Lscala/Function1;)I
   15:	ireturn
  LineNumberTable: 
   line 62: 0

  LocalVariableTable: 
   Start  Length  Slot  Name   Signature
   0      16      0    $this       Lscala/collection/generic/SequenceProxyTemplate;
   0      16      1    p       Lscala/Function1;


public static scala.collection.generic.SequenceView view(scala.collection.generic.SequenceProxyTemplate, int, int);
  Code:
   Stack=3, Locals=3, Args_size=3
   0:	aload_0
   1:	invokeinterface	#17,  1; //InterfaceMethod scala/collection/generic/TraversableProxyTemplate.self:()Lscala/collection/generic/TraversableTemplate;
   6:	checkcast	#19; //class scala/collection/generic/SequenceTemplate
   9:	iload_1
   10:	iload_2
   11:	invokeinterface	#50,  3; //InterfaceMethod scala/collection/generic/SequenceTemplate.view:(II)Lscala/collection/generic/SequenceView;
   16:	areturn
  LineNumberTable: 
   line 61: 0

  LocalVariableTable: 
   Start  Length  Slot  Name   Signature
   0      17      0    $this       Lscala/collection/generic/SequenceProxyTemplate;
   0      17      1    from       I
   0      17      2    until       I


public static java.lang.Object view(scala.collection.generic.SequenceProxyTemplate);
  Code:
   Stack=1, Locals=1, Args_size=1
   0:	aload_0
   1:	invokeinterface	#17,  1; //InterfaceMethod scala/collection/generic/TraversableProxyTemplate.self:()Lscala/collection/generic/TraversableTemplate;
   6:	checkcast	#19; //class scala/collection/generic/SequenceTemplate
   9:	invokeinterface	#55,  1; //InterfaceMethod scala/collection/generic/SequenceTemplate.view:()Ljava/lang/Object;
   14:	areturn
  LineNumberTable: 
   line 60: 0

  LocalVariableTable: 
   Start  Length  Slot  Name   Signature
   0      15      0    $this       Lscala/collection/generic/SequenceProxyTemplate;


public static scala.Range indices(scala.collection.generic.SequenceProxyTemplate);
  Code:
   Stack=1, Locals=1, Args_size=1
   0:	aload_0
   1:	invokeinterface	#17,  1; //InterfaceMethod scala/collection/generic/TraversableProxyTemplate.self:()Lscala/collection/generic/TraversableTemplate;
   6:	checkcast	#19; //class scala/collection/generic/SequenceTemplate
   9:	invokeinterface	#60,  1; //InterfaceMethod scala/collection/generic/SequenceTemplate.indices:()Lscala/Range;
   14:	areturn
  LineNumberTable: 
   line 59: 0

  LocalVariableTable: 
   Start  Length  Slot  Name   Signature
   0      15      0    $this       Lscala/collection/generic/SequenceProxyTemplate;


public static java.lang.Object padTo(scala.collection.generic.SequenceProxyTemplate, int, java.lang.Object, scala.collection.generic.BuilderFactory);
  Code:
   Stack=4, Locals=4, Args_size=4
   0:	aload_0
   1:	invokeinterface	#17,  1; //InterfaceMethod scala/collection/generic/TraversableProxyTemplate.self:()Lscala/collection/generic/TraversableTemplate;
   6:	checkcast	#19; //class scala/collection/generic/SequenceTemplate
   9:	iload_1
   10:	aload_2
   11:	aload_3
   12:	invokeinterface	#65,  4; //InterfaceMethod scala/collection/generic/SequenceTemplate.padTo:(ILjava/lang/Object;Lscala/collection/generic/BuilderFactory;)Ljava/lang/Object;
   17:	areturn
  LineNumberTable: 
   line 58: 0

  LocalVariableTable: 
   Start  Length  Slot  Name   Signature
   0      18      0    $this       Lscala/collection/generic/SequenceProxyTemplate;
   0      18      1    len       I
   0      18      2    elem       Ljava/lang/Object;
   0      18      3    bf       Lscala/collection/generic/BuilderFactory;


public static java.lang.Object patch(scala.collection.generic.SequenceProxyTemplate, int, scala.collection.Sequence, int, scala.collection.generic.BuilderFactory);
  Code:
   Stack=5, Locals=5, Args_size=5
   0:	aload_0
   1:	invokeinterface	#17,  1; //InterfaceMethod scala/collection/generic/TraversableProxyTemplate.self:()Lscala/collection/generic/TraversableTemplate;
   6:	checkcast	#19; //class scala/collection/generic/SequenceTemplate
   9:	iload_1
   10:	aload_2
   11:	iload_3
   12:	aload	4
   14:	invokeinterface	#75,  5; //InterfaceMethod scala/collection/generic/SequenceTemplate.patch:(ILscala/collection/Sequence;ILscala/collection/generic/BuilderFactory;)Ljava/lang/Object;
   19:	areturn
  LineNumberTable: 
   line 57: 0

  LocalVariableTable: 
   Start  Length  Slot  Name   Signature
   0      20      0    $this       Lscala/collection/generic/SequenceProxyTemplate;
   0      20      1    from       I
   0      20      2    patch       Lscala/collection/Sequence;
   0      20      3    replaced       I
   0      20      4    bf       Lscala/collection/generic/BuilderFactory;


public static scala.collection.generic.SequenceTemplate removeDuplicates(scala.collection.generic.SequenceProxyTemplate);
  Code:
   Stack=1, Locals=1, Args_size=1
   0:	aload_0
   1:	invokeinterface	#17,  1; //InterfaceMethod scala/collection/generic/TraversableProxyTemplate.self:()Lscala/collection/generic/TraversableTemplate;
   6:	checkcast	#19; //class scala/collection/generic/SequenceTemplate
   9:	invokeinterface	#81,  1; //InterfaceMethod scala/collection/generic/SequenceTemplate.removeDuplicates:()Lscala/collection/generic/IterableTemplate;
   14:	checkcast	#19; //class scala/collection/generic/SequenceTemplate
   17:	areturn
  LineNumberTable: 
   line 56: 0

  LocalVariableTable: 
   Start  Length  Slot  Name   Signature
   0      18      0    $this       Lscala/collection/generic/SequenceProxyTemplate;


public static scala.collection.generic.SequenceTemplate intersect(scala.collection.generic.SequenceProxyTemplate, scala.collection.Sequence);
  Code:
   Stack=2, Locals=2, Args_size=2
   0:	aload_0
   1:	invokeinterface	#17,  1; //InterfaceMethod scala/collection/generic/TraversableProxyTemplate.self:()Lscala/collection/generic/TraversableTemplate;
   6:	checkcast	#19; //class scala/collection/generic/SequenceTemplate
   9:	aload_1
   10:	invokeinterface	#86,  2; //InterfaceMethod scala/collection/generic/SequenceTemplate.intersect:(Lscala/collection/Sequence;)Lscala/collection/generic/IterableTemplate;
   15:	checkcast	#19; //class scala/collection/generic/SequenceTemplate
   18:	areturn
  LineNumberTable: 
   line 55: 0

  LocalVariableTable: 
   Start  Length  Slot  Name   Signature
   0      19      0    $this       Lscala/collection/generic/SequenceProxyTemplate;
   0      19      1    that       Lscala/collection/Sequence;


public static scala.collection.generic.SequenceTemplate diff(scala.collection.generic.SequenceProxyTemplate, scala.collection.Sequence);
  Code:
   Stack=2, Locals=2, Args_size=2
   0:	aload_0
   1:	invokeinterface	#17,  1; //InterfaceMethod scala/collection/generic/TraversableProxyTemplate.self:()Lscala/collection/generic/TraversableTemplate;
   6:	checkcast	#19; //class scala/collection/generic/SequenceTemplate
   9:	aload_1
   10:	invokeinterface	#89,  2; //InterfaceMethod scala/collection/generic/SequenceTemplate.diff:(Lscala/collection/Sequence;)Lscala/collection/generic/IterableTemplate;
   15:	checkcast	#19; //class scala/collection/generic/SequenceTemplate
   18:	areturn
  LineNumberTable: 
   line 54: 0

  LocalVariableTable: 
   Start  Length  Slot  Name   Signature
   0      19      0    $this       Lscala/collection/generic/SequenceProxyTemplate;
   0      19      1    that       Lscala/collection/Sequence;


public static java.lang.Object union(scala.collection.generic.SequenceProxyTemplate, scala.collection.Sequence, scala.collection.generic.BuilderFactory);
  Code:
   Stack=3, Locals=3, Args_size=3
   0:	aload_0
   1:	invokeinterface	#17,  1; //InterfaceMethod scala/collection/generic/TraversableProxyTemplate.self:()Lscala/collection/generic/TraversableTemplate;
   6:	checkcast	#19; //class scala/collection/generic/SequenceTemplate
   9:	aload_1
   10:	aload_2
   11:	invokeinterface	#94,  3; //InterfaceMethod scala/collection/generic/SequenceTemplate.union:(Lscala/collection/Sequence;Lscala/collection/generic/BuilderFactory;)Ljava/lang/Object;
   16:	areturn
  LineNumberTable: 
   line 53: 0

  LocalVariableTable: 
   Start  Length  Slot  Name   Signature
   0      17      0    $this       Lscala/collection/generic/SequenceProxyTemplate;
   0      17      1    that       Lscala/collection/Sequence;
   0      17      2    bf       Lscala/collection/generic/BuilderFactory;


public static boolean contains(scala.collection.generic.SequenceProxyTemplate, java.lang.Object);
  Code:
   Stack=2, Locals=2, Args_size=2
   0:	aload_0
   1:	invokeinterface	#17,  1; //InterfaceMethod scala/collection/generic/TraversableProxyTemplate.self:()Lscala/collection/generic/TraversableTemplate;
   6:	checkcast	#19; //class scala/collection/generic/SequenceTemplate
   9:	aload_1
   10:	invokeinterface	#99,  2; //InterfaceMethod scala/collection/generic/SequenceTemplate.contains:(Ljava/lang/Object;)Z
   15:	ireturn
  LineNumberTable: 
   line 52: 0

  LocalVariableTable: 
   Start  Length  Slot  Name   Signature
   0      16      0    $this       Lscala/collection/generic/SequenceProxyTemplate;
   0      16      1    elem       Ljava/lang/Object;


public static int indexOfSeq(scala.collection.generic.SequenceProxyTemplate, scala.collection.Sequence);
  Code:
   Stack=2, Locals=2, Args_size=2
   0:	aload_0
   1:	invokeinterface	#17,  1; //InterfaceMethod scala/collection/generic/TraversableProxyTemplate.self:()Lscala/collection/generic/TraversableTemplate;
   6:	checkcast	#19; //class scala/collection/generic/SequenceTemplate
   9:	aload_1
   10:	invokeinterface	#104,  2; //InterfaceMethod scala/collection/generic/SequenceTemplate.indexOfSeq:(Lscala/collection/Sequence;)I
   15:	ireturn
  LineNumberTable: 
   line 51: 0

  LocalVariableTable: 
   Start  Length  Slot  Name   Signature
   0      16      0    $this       Lscala/collection/generic/SequenceProxyTemplate;
   0      16      1    that       Lscala/collection/Sequence;


public static boolean endsWith(scala.collection.generic.SequenceProxyTemplate, scala.collection.Sequence);
  Code:
   Stack=2, Locals=2, Args_size=2
   0:	aload_0
   1:	invokeinterface	#17,  1; //InterfaceMethod scala/collection/generic/TraversableProxyTemplate.self:()Lscala/collection/generic/TraversableTemplate;
   6:	checkcast	#19; //class scala/collection/generic/SequenceTemplate
   9:	aload_1
   10:	invokeinterface	#107,  2; //InterfaceMethod scala/collection/generic/SequenceTemplate.endsWith:(Lscala/collection/Sequence;)Z
   15:	ireturn
  LineNumberTable: 
   line 50: 0

  LocalVariableTable: 
   Start  Length  Slot  Name   Signature
   0      16      0    $this       Lscala/collection/generic/SequenceProxyTemplate;
   0      16      1    that       Lscala/collection/Sequence;


public static boolean startsWith(scala.collection.generic.SequenceProxyTemplate, scala.collection.Sequence);
  Code:
   Stack=2, Locals=2, Args_size=2
   0:	aload_0
   1:	invokeinterface	#17,  1; //InterfaceMethod scala/collection/generic/TraversableProxyTemplate.self:()Lscala/collection/generic/TraversableTemplate;
   6:	checkcast	#19; //class scala/collection/generic/SequenceTemplate
   9:	aload_1
   10:	invokeinterface	#110,  2; //InterfaceMethod scala/collection/generic/SequenceTemplate.startsWith:(Lscala/collection/Sequence;)Z
   15:	ireturn
  LineNumberTable: 
   line 49: 0

  LocalVariableTable: 
   Start  Length  Slot  Name   Signature
   0      16      0    $this       Lscala/collection/generic/SequenceProxyTemplate;
   0      16      1    that       Lscala/collection/Sequence;


public static boolean startsWith(scala.collection.generic.SequenceProxyTemplate, scala.collection.Sequence, int);
  Code:
   Stack=3, Locals=3, Args_size=3
   0:	aload_0
   1:	invokeinterface	#17,  1; //InterfaceMethod scala/collection/generic/TraversableProxyTemplate.self:()Lscala/collection/generic/TraversableTemplate;
   6:	checkcast	#19; //class scala/collection/generic/SequenceTemplate
   9:	aload_1
   10:	iload_2
   11:	invokeinterface	#114,  3; //InterfaceMethod scala/collection/generic/SequenceTemplate.startsWith:(Lscala/collection/Sequence;I)Z
   16:	ireturn
  LineNumberTable: 
   line 48: 0

  LocalVariableTable: 
   Start  Length  Slot  Name   Signature
   0      17      0    $this       Lscala/collection/generic/SequenceProxyTemplate;
   0      17      1    that       Lscala/collection/Sequence;
   0      17      2    offset       I


public static scala.collection.Iterator reverseIterator(scala.collection.generic.SequenceProxyTemplate);
  Code:
   Stack=1, Locals=1, Args_size=1
   0:	aload_0
   1:	invokeinterface	#17,  1; //InterfaceMethod scala/collection/generic/TraversableProxyTemplate.self:()Lscala/collection/generic/TraversableTemplate;
   6:	checkcast	#19; //class scala/collection/generic/SequenceTemplate
   9:	invokeinterface	#120,  1; //InterfaceMethod scala/collection/generic/SequenceTemplate.reverseIterator:()Lscala/collection/Iterator;
   14:	areturn
  LineNumberTable: 
   line 47: 0

  LocalVariableTable: 
   Start  Length  Slot  Name   Signature
   0      15      0    $this       Lscala/collection/generic/SequenceProxyTemplate;


public static scala.collection.generic.SequenceTemplate reverse(scala.collection.generic.SequenceProxyTemplate);
  Code:
   Stack=1, Locals=1, Args_size=1
   0:	aload_0
   1:	invokeinterface	#17,  1; //InterfaceMethod scala/collection/generic/TraversableProxyTemplate.self:()Lscala/collection/generic/TraversableTemplate;
   6:	checkcast	#19; //class scala/collection/generic/SequenceTemplate
   9:	invokeinterface	#123,  1; //InterfaceMethod scala/collection/generic/SequenceTemplate.reverse:()Lscala/collection/generic/IterableTemplate;
   14:	checkcast	#19; //class scala/collection/generic/SequenceTemplate
   17:	areturn
  LineNumberTable: 
   line 46: 0

  LocalVariableTable: 
   Start  Length  Slot  Name   Signature
   0      18      0    $this       Lscala/collection/generic/SequenceProxyTemplate;


public static int lastIndexWhere(scala.collection.generic.SequenceProxyTemplate, scala.Function1, int);
  Code:
   Stack=2, Locals=3, Args_size=3
   0:	aload_0
   1:	invokeinterface	#17,  1; //InterfaceMethod scala/collection/generic/TraversableProxyTemplate.self:()Lscala/collection/generic/TraversableTemplate;
   6:	checkcast	#19; //class scala/collection/generic/SequenceTemplate
   9:	aload_1
   10:	invokeinterface	#127,  2; //InterfaceMethod scala/collection/generic/SequenceTemplate.lastIndexWhere:(Lscala/Function1;)I
   15:	ireturn
  LineNumberTable: 
   line 45: 0

  LocalVariableTable: 
   Start  Length  Slot  Name   Signature
   0      16      0    $this       Lscala/collection/generic/SequenceProxyTemplate;
   0      16      1    p       Lscala/Function1;
   0      16      2    end       I


public static int lastIndexWhere(scala.collection.generic.SequenceProxyTemplate, scala.Function1);
  Code:
   Stack=4, Locals=2, Args_size=2
   0:	aload_0
   1:	invokeinterface	#17,  1; //InterfaceMethod scala/collection/generic/TraversableProxyTemplate.self:()Lscala/collection/generic/TraversableTemplate;
   6:	checkcast	#19; //class scala/collection/generic/SequenceTemplate
   9:	aload_1
   10:	aload_0
   11:	invokeinterface	#134,  1; //InterfaceMethod scala/collection/generic/SequenceProxyTemplate.length:()I
   16:	iconst_1
   17:	isub
   18:	invokeinterface	#137,  3; //InterfaceMethod scala/collection/generic/SequenceTemplate.lastIndexWhere:(Lscala/Function1;I)I
   23:	ireturn
  LineNumberTable: 
   line 44: 0

  LocalVariableTable: 
   Start  Length  Slot  Name   Signature
   0      24      0    $this       Lscala/collection/generic/SequenceProxyTemplate;
   0      24      1    p       Lscala/Function1;


public static int lastIndexOf(scala.collection.generic.SequenceProxyTemplate, java.lang.Object, int);
  Code:
   Stack=5, Locals=3, Args_size=3
   0:	aload_0
   1:	invokeinterface	#17,  1; //InterfaceMethod scala/collection/generic/TraversableProxyTemplate.self:()Lscala/collection/generic/TraversableTemplate;
   6:	checkcast	#19; //class scala/collection/generic/SequenceTemplate
   9:	new	#141; //class scala/collection/generic/SequenceProxyTemplate$$anonfun$lastIndexOf$1
   12:	dup
   13:	aload_0
   14:	aload_1
   15:	invokespecial	#145; //Method scala/collection/generic/SequenceProxyTemplate$$anonfun$lastIndexOf$1."<init>":(Lscala/collection/generic/SequenceProxyTemplate;Ljava/lang/Object;)V
   18:	iload_2
   19:	invokeinterface	#137,  3; //InterfaceMethod scala/collection/generic/SequenceTemplate.lastIndexWhere:(Lscala/Function1;I)I
   24:	ireturn
  LineNumberTable: 
   line 43: 0

  LocalVariableTable: 
   Start  Length  Slot  Name   Signature
   0      25      0    $this       Lscala/collection/generic/SequenceProxyTemplate;
   0      25      1    elem$1       Ljava/lang/Object;
   0      25      2    end       I


public static int lastIndexOf(scala.collection.generic.SequenceProxyTemplate, java.lang.Object);
  Code:
   Stack=2, Locals=2, Args_size=2
   0:	aload_0
   1:	invokeinterface	#17,  1; //InterfaceMethod scala/collection/generic/TraversableProxyTemplate.self:()Lscala/collection/generic/TraversableTemplate;
   6:	checkcast	#19; //class scala/collection/generic/SequenceTemplate
   9:	aload_1
   10:	invokeinterface	#150,  2; //InterfaceMethod scala/collection/generic/SequenceTemplate.lastIndexOf:(Ljava/lang/Object;)I
   15:	ireturn
  LineNumberTable: 
   line 42: 0

  LocalVariableTable: 
   Start  Length  Slot  Name   Signature
   0      16      0    $this       Lscala/collection/generic/SequenceProxyTemplate;
   0      16      1    elem       Ljava/lang/Object;


public static int indexOf(scala.collection.generic.SequenceProxyTemplate, java.lang.Object, int);
  Code:
   Stack=3, Locals=3, Args_size=3
   0:	aload_0
   1:	invokeinterface	#17,  1; //InterfaceMethod scala/collection/generic/TraversableProxyTemplate.self:()Lscala/collection/generic/TraversableTemplate;
   6:	checkcast	#19; //class scala/collection/generic/SequenceTemplate
   9:	aload_1
   10:	iload_2
   11:	invokeinterface	#154,  3; //InterfaceMethod scala/collection/generic/SequenceTemplate.indexOf:(Ljava/lang/Object;I)I
   16:	ireturn
  LineNumberTable: 
   line 41: 0

  LocalVariableTable: 
   Start  Length  Slot  Name   Signature
   0      17      0    $this       Lscala/collection/generic/SequenceProxyTemplate;
   0      17      1    elem       Ljava/lang/Object;
   0      17      2    from       I


public static int indexOf(scala.collection.generic.SequenceProxyTemplate, java.lang.Object);
  Code:
   Stack=2, Locals=2, Args_size=2
   0:	aload_0
   1:	invokeinterface	#17,  1; //InterfaceMethod scala/collection/generic/TraversableProxyTemplate.self:()Lscala/collection/generic/TraversableTemplate;
   6:	checkcast	#19; //class scala/collection/generic/SequenceTemplate
   9:	aload_1
   10:	invokeinterface	#156,  2; //InterfaceMethod scala/collection/generic/SequenceTemplate.indexOf:(Ljava/lang/Object;)I
   15:	ireturn
  LineNumberTable: 
   line 40: 0

  LocalVariableTable: 
   Start  Length  Slot  Name   Signature
   0      16      0    $this       Lscala/collection/generic/SequenceProxyTemplate;
   0      16      1    elem       Ljava/lang/Object;


public static int findIndexOf(scala.collection.generic.SequenceProxyTemplate, scala.Function1);
  Code:
   Stack=2, Locals=2, Args_size=2
   0:	aload_0
   1:	invokeinterface	#17,  1; //InterfaceMethod scala/collection/generic/TraversableProxyTemplate.self:()Lscala/collection/generic/TraversableTemplate;
   6:	checkcast	#19; //class scala/collection/generic/SequenceTemplate
   9:	aload_1
   10:	invokeinterface	#159,  2; //InterfaceMethod scala/collection/generic/SequenceTemplate.findIndexOf:(Lscala/Function1;)I
   15:	ireturn
  LineNumberTable: 
   line 39: 0

  LocalVariableTable: 
   Start  Length  Slot  Name   Signature
   0      16      0    $this       Lscala/collection/generic/SequenceProxyTemplate;
   0      16      1    p       Lscala/Function1;


public static int indexWhere(scala.collection.generic.SequenceProxyTemplate, scala.Function1, int);
  Code:
   Stack=3, Locals=3, Args_size=3
   0:	aload_0
   1:	invokeinterface	#17,  1; //InterfaceMethod scala/collection/generic/TraversableProxyTemplate.self:()Lscala/collection/generic/TraversableTemplate;
   6:	checkcast	#19; //class scala/collection/generic/SequenceTemplate
   9:	aload_1
   10:	iload_2
   11:	invokeinterface	#162,  3; //InterfaceMethod scala/collection/generic/SequenceTemplate.indexWhere:(Lscala/Function1;I)I
   16:	ireturn
  LineNumberTable: 
   line 38: 0

  LocalVariableTable: 
   Start  Length  Slot  Name   Signature
   0      17      0    $this       Lscala/collection/generic/SequenceProxyTemplate;
   0      17      1    p       Lscala/Function1;
   0      17      2    from       I


public static int indexWhere(scala.collection.generic.SequenceProxyTemplate, scala.Function1);
  Code:
   Stack=2, Locals=2, Args_size=2
   0:	aload_0
   1:	invokeinterface	#17,  1; //InterfaceMethod scala/collection/generic/TraversableProxyTemplate.self:()Lscala/collection/generic/TraversableTemplate;
   6:	checkcast	#19; //class scala/collection/generic/SequenceTemplate
   9:	aload_1
   10:	invokeinterface	#164,  2; //InterfaceMethod scala/collection/generic/SequenceTemplate.indexWhere:(Lscala/Function1;)I
   15:	ireturn
  LineNumberTable: 
   line 37: 0

  LocalVariableTable: 
   Start  Length  Slot  Name   Signature
   0      16      0    $this       Lscala/collection/generic/SequenceProxyTemplate;
   0      16      1    p       Lscala/Function1;


public static int prefixLength(scala.collection.generic.SequenceProxyTemplate, scala.Function1);
  Code:
   Stack=2, Locals=2, Args_size=2
   0:	aload_0
   1:	invokeinterface	#17,  1; //InterfaceMethod scala/collection/generic/TraversableProxyTemplate.self:()Lscala/collection/generic/TraversableTemplate;
   6:	checkcast	#19; //class scala/collection/generic/SequenceTemplate
   9:	aload_1
   10:	invokeinterface	#167,  2; //InterfaceMethod scala/collection/generic/SequenceTemplate.prefixLength:(Lscala/Function1;)I
   15:	ireturn
  LineNumberTable: 
   line 36: 0

  LocalVariableTable: 
   Start  Length  Slot  Name   Signature
   0      16      0    $this       Lscala/collection/generic/SequenceProxyTemplate;
   0      16      1    p       Lscala/Function1;


public static int segmentLength(scala.collection.generic.SequenceProxyTemplate, scala.Function1, int);
  Code:
   Stack=3, Locals=3, Args_size=3
   0:	aload_0
   1:	invokeinterface	#17,  1; //InterfaceMethod scala/collection/generic/TraversableProxyTemplate.self:()Lscala/collection/generic/TraversableTemplate;
   6:	checkcast	#19; //class scala/collection/generic/SequenceTemplate
   9:	aload_1
   10:	iload_2
   11:	invokeinterface	#170,  3; //InterfaceMethod scala/collection/generic/SequenceTemplate.segmentLength:(Lscala/Function1;I)I
   16:	ireturn
  LineNumberTable: 
   line 35: 0

  LocalVariableTable: 
   Start  Length  Slot  Name   Signature
   0      17      0    $this       Lscala/collection/generic/SequenceProxyTemplate;
   0      17      1    p       Lscala/Function1;
   0      17      2    from       I


public static java.lang.Object zipWithIndex(scala.collection.generic.SequenceProxyTemplate, scala.collection.generic.BuilderFactory);
  Code:
   Stack=2, Locals=2, Args_size=2
   0:	aload_0
   1:	invokeinterface	#17,  1; //InterfaceMethod scala/collection/generic/TraversableProxyTemplate.self:()Lscala/collection/generic/TraversableTemplate;
   6:	checkcast	#19; //class scala/collection/generic/SequenceTemplate
   9:	aload_1
   10:	invokeinterface	#175,  2; //InterfaceMethod scala/collection/generic/SequenceTemplate.zipWithIndex:(Lscala/collection/generic/BuilderFactory;)Ljava/lang/Object;
   15:	areturn
  LineNumberTable: 
   line 34: 0

  LocalVariableTable: 
   Start  Length  Slot  Name   Signature
   0      16      0    $this       Lscala/collection/generic/SequenceProxyTemplate;
   0      16      1    bf       Lscala/collection/generic/BuilderFactory;


public static java.lang.Object zipAll(scala.collection.generic.SequenceProxyTemplate, scala.collection.Sequence, java.lang.Object, java.lang.Object, scala.collection.generic.BuilderFactory);
  Code:
   Stack=5, Locals=5, Args_size=5
   0:	aload_0
   1:	invokeinterface	#17,  1; //InterfaceMethod scala/collection/generic/TraversableProxyTemplate.self:()Lscala/collection/generic/TraversableTemplate;
   6:	checkcast	#19; //class scala/collection/generic/SequenceTemplate
   9:	aload_1
   10:	aload_2
   11:	aload_3
   12:	aload	4
   14:	invokeinterface	#180,  5; //InterfaceMethod scala/collection/generic/SequenceTemplate.zipAll:(Lscala/collection/Sequence;Ljava/lang/Object;Ljava/lang/Object;Lscala/collection/generic/BuilderFactory;)Ljava/lang/Object;
   19:	areturn
  LineNumberTable: 
   line 33: 0

  LocalVariableTable: 
   Start  Length  Slot  Name   Signature
   0      20      0    $this       Lscala/collection/generic/SequenceProxyTemplate;
   0      20      1    that       Lscala/collection/Sequence;
   0      20      2    thisElem       Ljava/lang/Object;
   0      20      3    thatElem       Ljava/lang/Object;
   0      20      4    bf       Lscala/collection/generic/BuilderFactory;


public static java.lang.Object zip(scala.collection.generic.SequenceProxyTemplate, scala.collection.Sequence, scala.collection.generic.BuilderFactory);
  Code:
   Stack=3, Locals=3, Args_size=3
   0:	aload_0
   1:	invokeinterface	#17,  1; //InterfaceMethod scala/collection/generic/TraversableProxyTemplate.self:()Lscala/collection/generic/TraversableTemplate;
   6:	checkcast	#19; //class scala/collection/generic/SequenceTemplate
   9:	aload_1
   10:	aload_2
   11:	invokeinterface	#185,  3; //InterfaceMethod scala/collection/generic/SequenceTemplate.zip:(Lscala/collection/Sequence;Lscala/collection/generic/BuilderFactory;)Ljava/lang/Object;
   16:	areturn
  LineNumberTable: 
   line 32: 0

  LocalVariableTable: 
   Start  Length  Slot  Name   Signature
   0      17      0    $this       Lscala/collection/generic/SequenceProxyTemplate;
   0      17      1    that       Lscala/collection/Sequence;
   0      17      2    bf       Lscala/collection/generic/BuilderFactory;


public static boolean isDefinedAt(scala.collection.generic.SequenceProxyTemplate, int);
  Code:
   Stack=2, Locals=2, Args_size=2
   0:	aload_0
   1:	invokeinterface	#17,  1; //InterfaceMethod scala/collection/generic/TraversableProxyTemplate.self:()Lscala/collection/generic/TraversableTemplate;
   6:	checkcast	#19; //class scala/collection/generic/SequenceTemplate
   9:	iload_1
   10:	invokeinterface	#190,  2; //InterfaceMethod scala/collection/generic/SequenceTemplate.isDefinedAt:(I)Z
   15:	ireturn
  LineNumberTable: 
   line 31: 0

  LocalVariableTable: 
   Start  Length  Slot  Name   Signature
   0      16      0    $this       Lscala/collection/generic/SequenceProxyTemplate;
   0      16      1    x       I


public static int size(scala.collection.generic.SequenceProxyTemplate);
  Code:
   Stack=1, Locals=1, Args_size=1
   0:	aload_0
   1:	invokeinterface	#17,  1; //InterfaceMethod scala/collection/generic/TraversableProxyTemplate.self:()Lscala/collection/generic/TraversableTemplate;
   6:	checkcast	#19; //class scala/collection/generic/SequenceTemplate
   9:	invokeinterface	#195,  1; //InterfaceMethod scala/collection/generic/SequenceTemplate.size:()I
   14:	ireturn
  LineNumberTable: 
   line 30: 0

  LocalVariableTable: 
   Start  Length  Slot  Name   Signature
   0      15      0    $this       Lscala/collection/generic/SequenceProxyTemplate;


public static int lengthCompare(scala.collection.generic.SequenceProxyTemplate, int);
  Code:
   Stack=2, Locals=2, Args_size=2
   0:	aload_0
   1:	invokeinterface	#17,  1; //InterfaceMethod scala/collection/generic/TraversableProxyTemplate.self:()Lscala/collection/generic/TraversableTemplate;
   6:	checkcast	#19; //class scala/collection/generic/SequenceTemplate
   9:	iload_1
   10:	invokeinterface	#200,  2; //InterfaceMethod scala/collection/generic/SequenceTemplate.lengthCompare:(I)I
   15:	ireturn
  LineNumberTable: 
   line 29: 0

  LocalVariableTable: 
   Start  Length  Slot  Name   Signature
   0      16      0    $this       Lscala/collection/generic/SequenceProxyTemplate;
   0      16      1    len       I


public static java.lang.Object apply(scala.collection.generic.SequenceProxyTemplate, int);
  Code:
   Stack=2, Locals=2, Args_size=2
   0:	aload_0
   1:	invokeinterface	#17,  1; //InterfaceMethod scala/collection/generic/TraversableProxyTemplate.self:()Lscala/collection/generic/TraversableTemplate;
   6:	checkcast	#204; //class scala/Function1
   9:	iload_1
   10:	invokestatic	#210; //Method scala/runtime/BoxesRunTime.boxToInteger:(I)Ljava/lang/Integer;
   13:	invokeinterface	#213,  2; //InterfaceMethod scala/Function1.apply:(Ljava/lang/Object;)Ljava/lang/Object;
   18:	areturn
  LineNumberTable: 
   line 28: 0

  LocalVariableTable: 
   Start  Length  Slot  Name   Signature
   0      19      0    $this       Lscala/collection/generic/SequenceProxyTemplate;
   0      19      1    idx       I


public static int length(scala.collection.generic.SequenceProxyTemplate);
  Code:
   Stack=1, Locals=1, Args_size=1
   0:	aload_0
   1:	invokeinterface	#17,  1; //InterfaceMethod scala/collection/generic/TraversableProxyTemplate.self:()Lscala/collection/generic/TraversableTemplate;
   6:	checkcast	#19; //class scala/collection/generic/SequenceTemplate
   9:	invokeinterface	#215,  1; //InterfaceMethod scala/collection/generic/SequenceTemplate.length:()I
   14:	ireturn
  LineNumberTable: 
   line 27: 0

  LocalVariableTable: 
   Start  Length  Slot  Name   Signature
   0      15      0    $this       Lscala/collection/generic/SequenceProxyTemplate;


}

