Compiled from "SequenceViewTemplate.scala"
public abstract class scala.collection.generic.SequenceViewTemplate$FlatMapped$class extends java.lang.Object
  SourceFile: "SequenceViewTemplate.scala"
  Scala: length = 0x
   
  InnerClass: 
   public abstract #104= #13 of #103; //FlatMapped=class scala/collection/generic/SequenceViewTemplate$FlatMapped of class scala/collection/generic/SequenceViewTemplate
   public abstract #104= #29 of #106; //FlatMapped=class scala/collection/generic/TraversableViewTemplate$FlatMapped of class scala/collection/generic/TraversableViewTemplate
   public final #107= #87 of #13; //$anonfun$index$1=class scala/collection/generic/SequenceViewTemplate$FlatMapped$$anonfun$index$1 of class scala/collection/generic/SequenceViewTemplate$FlatMapped
  minor version: 0
  major version: 49
  Constant pool:
const #1 = Asciz	SourceFile;
const #2 = Asciz	SequenceViewTemplate.scala;
const #3 = Asciz	$init$;
const #4 = Asciz	(Lscala/collection/generic/SequenceViewTemplate$FlatMapped;)V;
const #5 = Asciz	Code;
const #6 = Asciz	LineNumberTable;
const #7 = Asciz	$this;
const #8 = Asciz	Lscala/collection/generic/SequenceViewTemplate$FlatMapped;;
const #9 = Asciz	LocalVariableTable;
const #10 = Asciz	apply;
const #11 = Asciz	(Lscala/collection/generic/SequenceViewTemplate$FlatMapped;I)Ljava/lang/Object;;
const #12 = Asciz	scala/collection/generic/SequenceViewTemplate$FlatMapped;
const #13 = class	#12;	//  scala/collection/generic/SequenceViewTemplate$FlatMapped
const #14 = Asciz	scala$collection$generic$SequenceViewTemplate$FlatMapped$$$outer;
const #15 = Asciz	()Lscala/collection/generic/SequenceViewTemplate;;
const #16 = NameAndType	#14:#15;//  scala$collection$generic$SequenceViewTemplate$FlatMapped$$$outer:()Lscala/collection/generic/SequenceViewTemplate;
const #17 = InterfaceMethod	#13.#16;	//  scala/collection/generic/SequenceViewTemplate$FlatMapped.scala$collection$generic$SequenceViewTemplate$FlatMapped$$$outer:()Lscala/collection/generic/SequenceViewTemplate;
const #18 = Asciz	scala/collection/generic/SequenceTemplate;
const #19 = class	#18;	//  scala/collection/generic/SequenceTemplate
const #20 = Asciz	length;
const #21 = Asciz	()I;
const #22 = NameAndType	#20:#21;//  length:()I
const #23 = InterfaceMethod	#19.#22;	//  scala/collection/generic/SequenceTemplate.length:()I
const #24 = Asciz	findRow;
const #25 = Asciz	(III)I;
const #26 = NameAndType	#24:#25;//  findRow:(III)I
const #27 = InterfaceMethod	#13.#26;	//  scala/collection/generic/SequenceViewTemplate$FlatMapped.findRow:(III)I
const #28 = Asciz	scala/collection/generic/TraversableViewTemplate$FlatMapped;
const #29 = class	#28;	//  scala/collection/generic/TraversableViewTemplate$FlatMapped
const #30 = Asciz	mapping;
const #31 = Asciz	()Lscala/Function1;;
const #32 = NameAndType	#30:#31;//  mapping:()Lscala/Function1;
const #33 = InterfaceMethod	#29.#32;	//  scala/collection/generic/TraversableViewTemplate$FlatMapped.mapping:()Lscala/Function1;
const #34 = Asciz	(I)Ljava/lang/Object;;
const #35 = NameAndType	#10:#34;//  apply:(I)Ljava/lang/Object;
const #36 = InterfaceMethod	#19.#35;	//  scala/collection/generic/SequenceTemplate.apply:(I)Ljava/lang/Object;
const #37 = Asciz	scala/Function1;
const #38 = class	#37;	//  scala/Function1
const #39 = Asciz	(Ljava/lang/Object;)Ljava/lang/Object;;
const #40 = NameAndType	#10:#39;//  apply:(Ljava/lang/Object;)Ljava/lang/Object;
const #41 = InterfaceMethod	#38.#40;	//  scala/Function1.apply:(Ljava/lang/Object;)Ljava/lang/Object;
const #42 = Asciz	scala/collection/generic/TraversableTemplate;
const #43 = class	#42;	//  scala/collection/generic/TraversableTemplate
const #44 = Asciz	scala/runtime/ScalaRunTime$;
const #45 = class	#44;	//  scala/runtime/ScalaRunTime$
const #46 = Asciz	MODULE$;
const #47 = Asciz	Lscala/runtime/ScalaRunTime$;;
const #48 = NameAndType	#46:#47;//  MODULE$:Lscala/runtime/ScalaRunTime$;
const #49 = Field	#45.#48;	//  scala/runtime/ScalaRunTime$.MODULE$:Lscala/runtime/ScalaRunTime$;
const #50 = Asciz	boxArray;
const #51 = Asciz	(Ljava/lang/Object;)Lscala/runtime/BoxedArray;;
const #52 = NameAndType	#50:#51;//  boxArray:(Ljava/lang/Object;)Lscala/runtime/BoxedArray;
const #53 = Method	#45.#52;	//  scala/runtime/ScalaRunTime$.boxArray:(Ljava/lang/Object;)Lscala/runtime/BoxedArray;
const #54 = Asciz	toSequence;
const #55 = Asciz	()Lscala/collection/Sequence;;
const #56 = NameAndType	#54:#55;//  toSequence:()Lscala/collection/Sequence;
const #57 = InterfaceMethod	#43.#56;	//  scala/collection/generic/TraversableTemplate.toSequence:()Lscala/collection/Sequence;
const #58 = Asciz	index;
const #59 = Asciz	()[I;
const #60 = NameAndType	#58:#59;//  index:()[I
const #61 = InterfaceMethod	#13.#60;	//  scala/collection/generic/SequenceViewTemplate$FlatMapped.index:()[I
const #62 = Asciz	idx;
const #63 = Asciz	I;
const #64 = Asciz	row;
const #65 = Asciz	(Lscala/collection/generic/SequenceViewTemplate$FlatMapped;)I;
const #66 = Asciz	(Lscala/collection/generic/SequenceViewTemplate$FlatMapped;III)I;
const #67 = Asciz	lo;
const #68 = Asciz	hi;
const #69 = Asciz	mid;
const #70 = Asciz	(Lscala/collection/generic/SequenceViewTemplate$FlatMapped;)[I;
const #71 = Asciz	scala/Predef$;
const #72 = class	#71;	//  scala/Predef$
const #73 = Asciz	Lscala/Predef$;;
const #74 = NameAndType	#46:#73;//  MODULE$:Lscala/Predef$;
const #75 = Field	#72.#74;	//  scala/Predef$.MODULE$:Lscala/Predef$;
const #76 = Asciz	intWrapper;
const #77 = Asciz	(I)Lscala/runtime/RichInt;;
const #78 = NameAndType	#76:#77;//  intWrapper:(I)Lscala/runtime/RichInt;
const #79 = Method	#72.#78;	//  scala/Predef$.intWrapper:(I)Lscala/runtime/RichInt;
const #80 = Asciz	scala/runtime/RichInt;
const #81 = class	#80;	//  scala/runtime/RichInt
const #82 = Asciz	until;
const #83 = Asciz	(I)Lscala/Range;;
const #84 = NameAndType	#82:#83;//  until:(I)Lscala/Range;
const #85 = Method	#81.#84;	//  scala/runtime/RichInt.until:(I)Lscala/Range;
const #86 = Asciz	scala/collection/generic/SequenceViewTemplate$FlatMapped$$anonfun$index$1;
const #87 = class	#86;	//  scala/collection/generic/SequenceViewTemplate$FlatMapped$$anonfun$index$1
const #88 = Asciz	<init>;
const #89 = Asciz	(Lscala/collection/generic/SequenceViewTemplate$FlatMapped;[I)V;
const #90 = NameAndType	#88:#89;//  "<init>":(Lscala/collection/generic/SequenceViewTemplate$FlatMapped;[I)V
const #91 = Method	#87.#90;	//  scala/collection/generic/SequenceViewTemplate$FlatMapped$$anonfun$index$1."<init>":(Lscala/collection/generic/SequenceViewTemplate$FlatMapped;[I)V
const #92 = Asciz	scala/Range;
const #93 = class	#92;	//  scala/Range
const #94 = Asciz	foreach;
const #95 = Asciz	(Lscala/Function1;)V;
const #96 = NameAndType	#94:#95;//  foreach:(Lscala/Function1;)V
const #97 = Method	#93.#96;	//  scala/Range.foreach:(Lscala/Function1;)V
const #98 = Asciz	index$1;
const #99 = Asciz	[I;
const #100 = Asciz	Scala;
const #101 = Asciz	InnerClasses;
const #102 = Asciz	scala/collection/generic/SequenceViewTemplate;
const #103 = class	#102;	//  scala/collection/generic/SequenceViewTemplate
const #104 = Asciz	FlatMapped;
const #105 = Asciz	scala/collection/generic/TraversableViewTemplate;
const #106 = class	#105;	//  scala/collection/generic/TraversableViewTemplate
const #107 = Asciz	$anonfun$index$1;
const #108 = Asciz	scala/collection/generic/SequenceViewTemplate$FlatMapped$class;
const #109 = class	#108;	//  scala/collection/generic/SequenceViewTemplate$FlatMapped$class
const #110 = Asciz	java/lang/Object;
const #111 = class	#110;	//  java/lang/Object

{
public static void $init$(scala.collection.generic.SequenceViewTemplate$FlatMapped);
  Code:
   Stack=0, Locals=1, Args_size=1
   0:	return
  LineNumberTable: 
   line 46: 0

  LocalVariableTable: 
   Start  Length  Slot  Name   Signature
   0      1      0    $this       Lscala/collection/generic/SequenceViewTemplate$FlatMapped;


public static java.lang.Object apply(scala.collection.generic.SequenceViewTemplate$FlatMapped, int);
  Code:
   Stack=5, Locals=4, Args_size=2
   0:	aload_0
   1:	iload_1
   2:	iconst_0
   3:	aload_0
   4:	invokeinterface	#17,  1; //InterfaceMethod scala/collection/generic/SequenceViewTemplate$FlatMapped.scala$collection$generic$SequenceViewTemplate$FlatMapped$$$outer:()Lscala/collection/generic/SequenceViewTemplate;
   9:	invokeinterface	#23,  1; //InterfaceMethod scala/collection/generic/SequenceTemplate.length:()I
   14:	iconst_1
   15:	isub
   16:	invokeinterface	#27,  4; //InterfaceMethod scala/collection/generic/SequenceViewTemplate$FlatMapped.findRow:(III)I
   21:	istore_2
   22:	aload_0
   23:	invokeinterface	#33,  1; //InterfaceMethod scala/collection/generic/TraversableViewTemplate$FlatMapped.mapping:()Lscala/Function1;
   28:	aload_0
   29:	invokeinterface	#17,  1; //InterfaceMethod scala/collection/generic/SequenceViewTemplate$FlatMapped.scala$collection$generic$SequenceViewTemplate$FlatMapped$$$outer:()Lscala/collection/generic/SequenceViewTemplate;
   34:	iload_2
   35:	invokeinterface	#36,  2; //InterfaceMethod scala/collection/generic/SequenceTemplate.apply:(I)Ljava/lang/Object;
   40:	invokeinterface	#41,  2; //InterfaceMethod scala/Function1.apply:(Ljava/lang/Object;)Ljava/lang/Object;
   45:	astore_3
   46:	aload_3
   47:	instanceof	#43; //class scala/collection/generic/TraversableTemplate
   50:	ifeq	57
   53:	aload_3
   54:	goto	64
   57:	getstatic	#49; //Field scala/runtime/ScalaRunTime$.MODULE$:Lscala/runtime/ScalaRunTime$;
   60:	aload_3
   61:	invokevirtual	#53; //Method scala/runtime/ScalaRunTime$.boxArray:(Ljava/lang/Object;)Lscala/runtime/BoxedArray;
   64:	checkcast	#43; //class scala/collection/generic/TraversableTemplate
   67:	invokeinterface	#57,  1; //InterfaceMethod scala/collection/generic/TraversableTemplate.toSequence:()Lscala/collection/Sequence;
   72:	iload_1
   73:	aload_0
   74:	invokeinterface	#61,  1; //InterfaceMethod scala/collection/generic/SequenceViewTemplate$FlatMapped.index:()[I
   79:	iload_2
   80:	iaload
   81:	isub
   82:	invokeinterface	#36,  2; //InterfaceMethod scala/collection/generic/SequenceTemplate.apply:(I)Ljava/lang/Object;
   87:	areturn
  LineNumberTable: 
   line 62: 0
   line 63: 22

  LocalVariableTable: 
   Start  Length  Slot  Name   Signature
   0      88      0    $this       Lscala/collection/generic/SequenceViewTemplate$FlatMapped;
   0      88      1    idx       I
   22      65      2    row       I


public static int length(scala.collection.generic.SequenceViewTemplate$FlatMapped);
  Code:
   Stack=2, Locals=1, Args_size=1
   0:	aload_0
   1:	invokeinterface	#61,  1; //InterfaceMethod scala/collection/generic/SequenceViewTemplate$FlatMapped.index:()[I
   6:	aload_0
   7:	invokeinterface	#17,  1; //InterfaceMethod scala/collection/generic/SequenceViewTemplate$FlatMapped.scala$collection$generic$SequenceViewTemplate$FlatMapped$$$outer:()Lscala/collection/generic/SequenceViewTemplate;
   12:	invokeinterface	#23,  1; //InterfaceMethod scala/collection/generic/SequenceTemplate.length:()I
   17:	iaload
   18:	ireturn
  LineNumberTable: 
   line 60: 0

  LocalVariableTable: 
   Start  Length  Slot  Name   Signature
   0      19      0    $this       Lscala/collection/generic/SequenceViewTemplate$FlatMapped;


public static int findRow(scala.collection.generic.SequenceViewTemplate$FlatMapped, int, int, int);
  Code:
   Stack=5, Locals=5, Args_size=4
   0:	iload_2
   1:	iload_3
   2:	iadd
   3:	iconst_2
   4:	idiv
   5:	istore	4
   7:	iload_1
   8:	aload_0
   9:	invokeinterface	#61,  1; //InterfaceMethod scala/collection/generic/SequenceViewTemplate$FlatMapped.index:()[I
   14:	iload	4
   16:	iaload
   17:	if_icmpge	35
   20:	aload_0
   21:	iload_1
   22:	iload_2
   23:	iload	4
   25:	iconst_1
   26:	isub
   27:	invokeinterface	#27,  4; //InterfaceMethod scala/collection/generic/SequenceViewTemplate$FlatMapped.findRow:(III)I
   32:	goto	67
   35:	iload_1
   36:	aload_0
   37:	invokeinterface	#61,  1; //InterfaceMethod scala/collection/generic/SequenceViewTemplate$FlatMapped.index:()[I
   42:	iload	4
   44:	iconst_1
   45:	iadd
   46:	iaload
   47:	if_icmplt	65
   50:	aload_0
   51:	iload_1
   52:	iload	4
   54:	iconst_1
   55:	iadd
   56:	iload_3
   57:	invokeinterface	#27,  4; //InterfaceMethod scala/collection/generic/SequenceViewTemplate$FlatMapped.findRow:(III)I
   62:	goto	67
   65:	iload	4
   67:	ireturn
  LineNumberTable: 
   line 55: 0
   line 56: 7
   line 57: 35
   line 58: 65
   line 54: 67

  LocalVariableTable: 
   Start  Length  Slot  Name   Signature
   0      68      0    $this       Lscala/collection/generic/SequenceViewTemplate$FlatMapped;
   0      68      1    idx       I
   0      68      2    lo       I
   0      68      3    hi       I
   7      61      4    mid       I


public static int[] index(scala.collection.generic.SequenceViewTemplate$FlatMapped);
  Code:
   Stack=5, Locals=2, Args_size=1
   0:	aload_0
   1:	invokeinterface	#17,  1; //InterfaceMethod scala/collection/generic/SequenceViewTemplate$FlatMapped.scala$collection$generic$SequenceViewTemplate$FlatMapped$$$outer:()Lscala/collection/generic/SequenceViewTemplate;
   6:	invokeinterface	#23,  1; //InterfaceMethod scala/collection/generic/SequenceTemplate.length:()I
   11:	iconst_1
   12:	iadd
   13:	newarray int
   15:	astore_1
   16:	aload_1
   17:	iconst_0
   18:	iconst_0
   19:	iastore
   20:	getstatic	#75; //Field scala/Predef$.MODULE$:Lscala/Predef$;
   23:	iconst_0
   24:	invokevirtual	#79; //Method scala/Predef$.intWrapper:(I)Lscala/runtime/RichInt;
   27:	aload_0
   28:	invokeinterface	#17,  1; //InterfaceMethod scala/collection/generic/SequenceViewTemplate$FlatMapped.scala$collection$generic$SequenceViewTemplate$FlatMapped$$$outer:()Lscala/collection/generic/SequenceViewTemplate;
   33:	invokeinterface	#23,  1; //InterfaceMethod scala/collection/generic/SequenceTemplate.length:()I
   38:	invokevirtual	#85; //Method scala/runtime/RichInt.until:(I)Lscala/Range;
   41:	new	#87; //class scala/collection/generic/SequenceViewTemplate$FlatMapped$$anonfun$index$1
   44:	dup
   45:	aload_0
   46:	aload_1
   47:	invokespecial	#91; //Method scala/collection/generic/SequenceViewTemplate$FlatMapped$$anonfun$index$1."<init>":(Lscala/collection/generic/SequenceViewTemplate$FlatMapped;[I)V
   50:	invokevirtual	#97; //Method scala/Range.foreach:(Lscala/Function1;)V
   53:	aload_1
   54:	areturn
  LineNumberTable: 
   line 48: 0
   line 49: 16
   line 50: 20
   line 52: 53

  LocalVariableTable: 
   Start  Length  Slot  Name   Signature
   0      55      0    $this       Lscala/collection/generic/SequenceViewTemplate$FlatMapped;
   16      38      1    index$1       [I


}

