Compiled from "SequenceTemplate.scala"
public final class scala.collection.generic.SequenceTemplate$$anonfun$segmentLength$1$$anonfun$apply$2 extends java.lang.Object implements scala.Function1,scala.ScalaObject,java.io.Serializable
  SourceFile: "SequenceTemplate.scala"
  Scala: length = 0x
   
  InnerClass: 
   public final #112= #46 of #111; //$anonfun$segmentLength$1=class scala/collection/generic/SequenceTemplate$$anonfun$segmentLength$1 of class scala/collection/generic/SequenceTemplate
   public final #113= #15 of #46; //$anonfun$apply$2=class scala/collection/generic/SequenceTemplate$$anonfun$segmentLength$1$$anonfun$apply$2 of class scala/collection/generic/SequenceTemplate$$anonfun$segmentLength$1
  minor version: 0
  major version: 49
  Constant pool:
const #1 = Asciz	SourceFile;
const #2 = Asciz	SequenceTemplate.scala;
const #3 = Asciz	$outer;
const #4 = Asciz	Lscala/collection/generic/SequenceTemplate$$anonfun$segmentLength$1;;
const #5 = Asciz	<init>;
const #6 = Asciz	(Lscala/collection/generic/SequenceTemplate$$anonfun$segmentLength$1;)V;
const #7 = Asciz	Code;
const #8 = Asciz	LineNumberTable;
const #9 = Asciz	java/lang/NullPointerException;
const #10 = class	#9;	//  java/lang/NullPointerException
const #11 = Asciz	()V;
const #12 = NameAndType	#5:#11;//  "<init>":()V
const #13 = Method	#10.#12;	//  java/lang/NullPointerException."<init>":()V
const #14 = Asciz	scala/collection/generic/SequenceTemplate$$anonfun$segmentLength$1$$anonfun$apply$2;
const #15 = class	#14;	//  scala/collection/generic/SequenceTemplate$$anonfun$segmentLength$1$$anonfun$apply$2
const #16 = NameAndType	#3:#4;//  $outer:Lscala/collection/generic/SequenceTemplate$$anonfun$segmentLength$1;
const #17 = Field	#15.#16;	//  scala/collection/generic/SequenceTemplate$$anonfun$segmentLength$1$$anonfun$apply$2.$outer:Lscala/collection/generic/SequenceTemplate$$anonfun$segmentLength$1;
const #18 = Asciz	java/lang/Object;
const #19 = class	#18;	//  java/lang/Object
const #20 = Method	#19.#12;	//  java/lang/Object."<init>":()V
const #21 = Asciz	scala/Function1$class;
const #22 = class	#21;	//  scala/Function1$class
const #23 = Asciz	$init$;
const #24 = Asciz	(Lscala/Function1;)V;
const #25 = NameAndType	#23:#24;//  $init$:(Lscala/Function1;)V
const #26 = Method	#22.#25;	//  scala/Function1$class.$init$:(Lscala/Function1;)V
const #27 = Asciz	this;
const #28 = Asciz	Lscala/collection/generic/SequenceTemplate$$anonfun$segmentLength$1$$anonfun$apply$2;;
const #29 = Asciz	LocalVariableTable;
const #30 = Asciz	(Lscala/collection/generic/SequenceTemplate<TA;TThis;>.$anonfun$segmentLength$1;)V;
const #31 = Asciz	Signature;
const #32 = Asciz	apply;
const #33 = Asciz	(Ljava/lang/Object;)Ljava/lang/Object;;
const #34 = Asciz	(Ljava/lang/Object;)V;
const #35 = NameAndType	#32:#34;//  apply:(Ljava/lang/Object;)V
const #36 = Method	#15.#35;	//  scala/collection/generic/SequenceTemplate$$anonfun$segmentLength$1$$anonfun$apply$2.apply:(Ljava/lang/Object;)V
const #37 = Asciz	scala/runtime/BoxedUnit;
const #38 = class	#37;	//  scala/runtime/BoxedUnit
const #39 = Asciz	UNIT;
const #40 = Asciz	Lscala/runtime/BoxedUnit;;
const #41 = NameAndType	#39:#40;//  UNIT:Lscala/runtime/BoxedUnit;
const #42 = Field	#38.#41;	//  scala/runtime/BoxedUnit.UNIT:Lscala/runtime/BoxedUnit;
const #43 = Asciz	v1;
const #44 = Asciz	Ljava/lang/Object;;
const #45 = Asciz	scala/collection/generic/SequenceTemplate$$anonfun$segmentLength$1;
const #46 = class	#45;	//  scala/collection/generic/SequenceTemplate$$anonfun$segmentLength$1
const #47 = Asciz	i$3;
const #48 = Asciz	Lscala/runtime/IntRef;;
const #49 = NameAndType	#47:#48;//  i$3:Lscala/runtime/IntRef;
const #50 = Field	#46.#49;	//  scala/collection/generic/SequenceTemplate$$anonfun$segmentLength$1.i$3:Lscala/runtime/IntRef;
const #51 = Asciz	scala/runtime/IntRef;
const #52 = class	#51;	//  scala/runtime/IntRef
const #53 = Asciz	elem;
const #54 = Asciz	I;
const #55 = NameAndType	#53:#54;//  elem:I
const #56 = Field	#52.#55;	//  scala/runtime/IntRef.elem:I
const #57 = Asciz	from$1;
const #58 = NameAndType	#57:#54;//  from$1:I
const #59 = Field	#46.#58;	//  scala/collection/generic/SequenceTemplate$$anonfun$segmentLength$1.from$1:I
const #60 = Asciz	p$1;
const #61 = Asciz	Lscala/Function1;;
const #62 = NameAndType	#60:#61;//  p$1:Lscala/Function1;
const #63 = Field	#46.#62;	//  scala/collection/generic/SequenceTemplate$$anonfun$segmentLength$1.p$1:Lscala/Function1;
const #64 = Asciz	scala/Function1;
const #65 = class	#64;	//  scala/Function1
const #66 = NameAndType	#32:#33;//  apply:(Ljava/lang/Object;)Ljava/lang/Object;
const #67 = InterfaceMethod	#65.#66;	//  scala/Function1.apply:(Ljava/lang/Object;)Ljava/lang/Object;
const #68 = Asciz	scala/runtime/BoxesRunTime;
const #69 = class	#68;	//  scala/runtime/BoxesRunTime
const #70 = Asciz	unboxToBoolean;
const #71 = Asciz	(Ljava/lang/Object;)Z;
const #72 = NameAndType	#70:#71;//  unboxToBoolean:(Ljava/lang/Object;)Z
const #73 = Method	#69.#72;	//  scala/runtime/BoxesRunTime.unboxToBoolean:(Ljava/lang/Object;)Z
const #74 = Asciz	result$1;
const #75 = NameAndType	#74:#48;//  result$1:Lscala/runtime/IntRef;
const #76 = Field	#46.#75;	//  scala/collection/generic/SequenceTemplate$$anonfun$segmentLength$1.result$1:Lscala/runtime/IntRef;
const #77 = Asciz	scala/collection/Traversable$;
const #78 = class	#77;	//  scala/collection/Traversable$
const #79 = Asciz	MODULE$;
const #80 = Asciz	Lscala/collection/Traversable$;;
const #81 = NameAndType	#79:#80;//  MODULE$:Lscala/collection/Traversable$;
const #82 = Field	#78.#81;	//  scala/collection/Traversable$.MODULE$:Lscala/collection/Traversable$;
const #83 = Asciz	breaks;
const #84 = Asciz	()Lscala/util/control/Breaks;;
const #85 = NameAndType	#83:#84;//  breaks:()Lscala/util/control/Breaks;
const #86 = Method	#78.#85;	//  scala/collection/Traversable$.breaks:()Lscala/util/control/Breaks;
const #87 = Asciz	scala/util/control/Breaks;
const #88 = class	#87;	//  scala/util/control/Breaks
const #89 = Asciz	break;
const #90 = NameAndType	#89:#11;//  break:()V
const #91 = Method	#88.#90;	//  scala/util/control/Breaks.break:()V
const #92 = Asciz	x;
const #93 = Asciz	(TA;)V;
const #94 = Asciz	andThen;
const #95 = Asciz	(Lscala/Function1;)Lscala/Function1;;
const #96 = Asciz	(Lscala/Function1;Lscala/Function1;)Lscala/Function1;;
const #97 = NameAndType	#94:#96;//  andThen:(Lscala/Function1;Lscala/Function1;)Lscala/Function1;
const #98 = Method	#22.#97;	//  scala/Function1$class.andThen:(Lscala/Function1;Lscala/Function1;)Lscala/Function1;
const #99 = Asciz	g;
const #100 = Asciz	compose;
const #101 = NameAndType	#100:#96;//  compose:(Lscala/Function1;Lscala/Function1;)Lscala/Function1;
const #102 = Method	#22.#101;	//  scala/Function1$class.compose:(Lscala/Function1;Lscala/Function1;)Lscala/Function1;
const #103 = Asciz	toString;
const #104 = Asciz	()Ljava/lang/String;;
const #105 = Asciz	(Lscala/Function1;)Ljava/lang/String;;
const #106 = NameAndType	#103:#105;//  toString:(Lscala/Function1;)Ljava/lang/String;
const #107 = Method	#22.#106;	//  scala/Function1$class.toString:(Lscala/Function1;)Ljava/lang/String;
const #108 = Asciz	Scala;
const #109 = Asciz	InnerClasses;
const #110 = Asciz	scala/collection/generic/SequenceTemplate;
const #111 = class	#110;	//  scala/collection/generic/SequenceTemplate
const #112 = Asciz	$anonfun$segmentLength$1;
const #113 = Asciz	$anonfun$apply$2;
const #114 = Asciz	scala/ScalaObject;
const #115 = class	#114;	//  scala/ScalaObject
const #116 = Asciz	java/io/Serializable;
const #117 = class	#116;	//  java/io/Serializable

{
public scala.collection.generic.SequenceTemplate$$anonfun$segmentLength$1$$anonfun$apply$2(scala.collection.generic.SequenceTemplate$$anonfun$segmentLength$1);
  Code:
   Stack=2, Locals=2, Args_size=2
   0:	aload_1
   1:	ifnonnull	12
   4:	new	#10; //class java/lang/NullPointerException
   7:	dup
   8:	invokespecial	#13; //Method java/lang/NullPointerException."<init>":()V
   11:	athrow
   12:	aload_0
   13:	aload_1
   14:	putfield	#17; //Field $outer:Lscala/collection/generic/SequenceTemplate$$anonfun$segmentLength$1;
   17:	aload_0
   18:	invokespecial	#20; //Method java/lang/Object."<init>":()V
   21:	aload_0
   22:	invokestatic	#26; //Method scala/Function1$class.$init$:(Lscala/Function1;)V
   25:	return
  LineNumberTable: 
   line 143: 0

  LocalVariableTable: 
   Start  Length  Slot  Name   Signature
   0      26      0    this       Lscala/collection/generic/SequenceTemplate$$anonfun$segmentLength$1$$anonfun$apply$2;
   0      26      1    $outer       Lscala/collection/generic/SequenceTemplate$$anonfun$segmentLength$1;

  Signature: length = 0x2
   00 1E 

public final java.lang.Object apply(java.lang.Object);
  Code:
   Stack=2, Locals=3, Args_size=2
   0:	aload_0
   1:	getfield	#17; //Field $outer:Lscala/collection/generic/SequenceTemplate$$anonfun$segmentLength$1;
   4:	astore_2
   5:	aload_0
   6:	aload_1
   7:	invokevirtual	#36; //Method apply:(Ljava/lang/Object;)V
   10:	getstatic	#42; //Field scala/runtime/BoxedUnit.UNIT:Lscala/runtime/BoxedUnit;
   13:	areturn
  LineNumberTable: 
   line 143: 0

  LocalVariableTable: 
   Start  Length  Slot  Name   Signature
   0      14      0    this       Lscala/collection/generic/SequenceTemplate$$anonfun$segmentLength$1$$anonfun$apply$2;
   5      9      1    v1       Ljava/lang/Object;


public final void apply(java.lang.Object);
  Code:
   Stack=3, Locals=3, Args_size=2
   0:	aload_0
   1:	getfield	#17; //Field $outer:Lscala/collection/generic/SequenceTemplate$$anonfun$segmentLength$1;
   4:	astore_2
   5:	aload_0
   6:	getfield	#17; //Field $outer:Lscala/collection/generic/SequenceTemplate$$anonfun$segmentLength$1;
   9:	getfield	#50; //Field scala/collection/generic/SequenceTemplate$$anonfun$segmentLength$1.i$3:Lscala/runtime/IntRef;
   12:	getfield	#56; //Field scala/runtime/IntRef.elem:I
   15:	aload_0
   16:	getfield	#17; //Field $outer:Lscala/collection/generic/SequenceTemplate$$anonfun$segmentLength$1;
   19:	getfield	#59; //Field scala/collection/generic/SequenceTemplate$$anonfun$segmentLength$1.from$1:I
   22:	if_icmplt	84
   25:	aload_0
   26:	getfield	#17; //Field $outer:Lscala/collection/generic/SequenceTemplate$$anonfun$segmentLength$1;
   29:	getfield	#63; //Field scala/collection/generic/SequenceTemplate$$anonfun$segmentLength$1.p$1:Lscala/Function1;
   32:	aload_1
   33:	invokeinterface	#67,  2; //InterfaceMethod scala/Function1.apply:(Ljava/lang/Object;)Ljava/lang/Object;
   38:	invokestatic	#73; //Method scala/runtime/BoxesRunTime.unboxToBoolean:(Ljava/lang/Object;)Z
   41:	ifne	84
   44:	aload_0
   45:	getfield	#17; //Field $outer:Lscala/collection/generic/SequenceTemplate$$anonfun$segmentLength$1;
   48:	getfield	#76; //Field scala/collection/generic/SequenceTemplate$$anonfun$segmentLength$1.result$1:Lscala/runtime/IntRef;
   51:	aload_0
   52:	getfield	#17; //Field $outer:Lscala/collection/generic/SequenceTemplate$$anonfun$segmentLength$1;
   55:	getfield	#50; //Field scala/collection/generic/SequenceTemplate$$anonfun$segmentLength$1.i$3:Lscala/runtime/IntRef;
   58:	getfield	#56; //Field scala/runtime/IntRef.elem:I
   61:	aload_0
   62:	getfield	#17; //Field $outer:Lscala/collection/generic/SequenceTemplate$$anonfun$segmentLength$1;
   65:	getfield	#59; //Field scala/collection/generic/SequenceTemplate$$anonfun$segmentLength$1.from$1:I
   68:	isub
   69:	putfield	#56; //Field scala/runtime/IntRef.elem:I
   72:	getstatic	#82; //Field scala/collection/Traversable$.MODULE$:Lscala/collection/Traversable$;
   75:	invokevirtual	#86; //Method scala/collection/Traversable$.breaks:()Lscala/util/control/Breaks;
   78:	invokevirtual	#91; //Method scala/util/control/Breaks.break:()V
   81:	goto	106
   84:	aload_0
   85:	getfield	#17; //Field $outer:Lscala/collection/generic/SequenceTemplate$$anonfun$segmentLength$1;
   88:	getfield	#50; //Field scala/collection/generic/SequenceTemplate$$anonfun$segmentLength$1.i$3:Lscala/runtime/IntRef;
   91:	aload_0
   92:	getfield	#17; //Field $outer:Lscala/collection/generic/SequenceTemplate$$anonfun$segmentLength$1;
   95:	getfield	#50; //Field scala/collection/generic/SequenceTemplate$$anonfun$segmentLength$1.i$3:Lscala/runtime/IntRef;
   98:	getfield	#56; //Field scala/runtime/IntRef.elem:I
   101:	iconst_1
   102:	iadd
   103:	putfield	#56; //Field scala/runtime/IntRef.elem:I
   106:	return
  LineNumberTable: 
   line 144: 0
   line 145: 84
   line 144: 106

  LocalVariableTable: 
   Start  Length  Slot  Name   Signature
   0      107      0    this       Lscala/collection/generic/SequenceTemplate$$anonfun$segmentLength$1$$anonfun$apply$2;
   5      102      1    x       Ljava/lang/Object;

  Signature: length = 0x2
   00 5D 

public scala.Function1 andThen(scala.Function1);
  Code:
   Stack=2, Locals=2, Args_size=2
   0:	aload_0
   1:	aload_1
   2:	invokestatic	#98; //Method scala/Function1$class.andThen:(Lscala/Function1;Lscala/Function1;)Lscala/Function1;
   5:	areturn
  LineNumberTable: 
   line 143: 0

  LocalVariableTable: 
   Start  Length  Slot  Name   Signature
   0      6      0    this       Lscala/collection/generic/SequenceTemplate$$anonfun$segmentLength$1$$anonfun$apply$2;
   0      6      1    g       Lscala/Function1;


public scala.Function1 compose(scala.Function1);
  Code:
   Stack=2, Locals=2, Args_size=2
   0:	aload_0
   1:	aload_1
   2:	invokestatic	#102; //Method scala/Function1$class.compose:(Lscala/Function1;Lscala/Function1;)Lscala/Function1;
   5:	areturn
  LineNumberTable: 
   line 143: 0

  LocalVariableTable: 
   Start  Length  Slot  Name   Signature
   0      6      0    this       Lscala/collection/generic/SequenceTemplate$$anonfun$segmentLength$1$$anonfun$apply$2;
   0      6      1    g       Lscala/Function1;


public java.lang.String toString();
  Code:
   Stack=1, Locals=1, Args_size=1
   0:	aload_0
   1:	invokestatic	#107; //Method scala/Function1$class.toString:(Lscala/Function1;)Ljava/lang/String;
   4:	areturn
  LineNumberTable: 
   line 143: 0


}

