Compiled from "SequenceViewTemplate.scala"
public abstract class scala.collection.generic.SequenceViewTemplate$TakenWhile$class extends java.lang.Object
  SourceFile: "SequenceViewTemplate.scala"
  Scala: length = 0x
   
  InnerClass: 
   public abstract #63= #13 of #62; //TakenWhile=class scala/collection/generic/SequenceViewTemplate$TakenWhile of class scala/collection/generic/SequenceViewTemplate
   public abstract #63= #50 of #65; //TakenWhile=class scala/collection/generic/TraversableViewTemplate$TakenWhile of class scala/collection/generic/TraversableViewTemplate
  minor version: 0
  major version: 49
  Constant pool:
const #1 = Asciz	SourceFile;
const #2 = Asciz	SequenceViewTemplate.scala;
const #3 = Asciz	$init$;
const #4 = Asciz	(Lscala/collection/generic/SequenceViewTemplate$TakenWhile;)V;
const #5 = Asciz	Code;
const #6 = Asciz	LineNumberTable;
const #7 = Asciz	$this;
const #8 = Asciz	Lscala/collection/generic/SequenceViewTemplate$TakenWhile;;
const #9 = Asciz	LocalVariableTable;
const #10 = Asciz	apply;
const #11 = Asciz	(Lscala/collection/generic/SequenceViewTemplate$TakenWhile;I)Ljava/lang/Object;;
const #12 = Asciz	scala/collection/generic/SequenceViewTemplate$TakenWhile;
const #13 = class	#12;	//  scala/collection/generic/SequenceViewTemplate$TakenWhile
const #14 = Asciz	len;
const #15 = Asciz	()I;
const #16 = NameAndType	#14:#15;//  len:()I
const #17 = InterfaceMethod	#13.#16;	//  scala/collection/generic/SequenceViewTemplate$TakenWhile.len:()I
const #18 = Asciz	scala$collection$generic$SequenceViewTemplate$TakenWhile$$$outer;
const #19 = Asciz	()Lscala/collection/generic/SequenceViewTemplate;;
const #20 = NameAndType	#18:#19;//  scala$collection$generic$SequenceViewTemplate$TakenWhile$$$outer:()Lscala/collection/generic/SequenceViewTemplate;
const #21 = InterfaceMethod	#13.#20;	//  scala/collection/generic/SequenceViewTemplate$TakenWhile.scala$collection$generic$SequenceViewTemplate$TakenWhile$$$outer:()Lscala/collection/generic/SequenceViewTemplate;
const #22 = Asciz	scala/collection/generic/SequenceTemplate;
const #23 = class	#22;	//  scala/collection/generic/SequenceTemplate
const #24 = Asciz	(I)Ljava/lang/Object;;
const #25 = NameAndType	#10:#24;//  apply:(I)Ljava/lang/Object;
const #26 = InterfaceMethod	#23.#25;	//  scala/collection/generic/SequenceTemplate.apply:(I)Ljava/lang/Object;
const #27 = Asciz	java/lang/IndexOutOfBoundsException;
const #28 = class	#27;	//  java/lang/IndexOutOfBoundsException
const #29 = Asciz	scala/runtime/BoxesRunTime;
const #30 = class	#29;	//  scala/runtime/BoxesRunTime
const #31 = Asciz	boxToInteger;
const #32 = Asciz	(I)Ljava/lang/Integer;;
const #33 = NameAndType	#31:#32;//  boxToInteger:(I)Ljava/lang/Integer;
const #34 = Method	#30.#33;	//  scala/runtime/BoxesRunTime.boxToInteger:(I)Ljava/lang/Integer;
const #35 = Asciz	java/lang/Object;
const #36 = class	#35;	//  java/lang/Object
const #37 = Asciz	toString;
const #38 = Asciz	()Ljava/lang/String;;
const #39 = NameAndType	#37:#38;//  toString:()Ljava/lang/String;
const #40 = Method	#36.#39;	//  java/lang/Object.toString:()Ljava/lang/String;
const #41 = Asciz	<init>;
const #42 = Asciz	(Ljava/lang/String;)V;
const #43 = NameAndType	#41:#42;//  "<init>":(Ljava/lang/String;)V
const #44 = Method	#28.#43;	//  java/lang/IndexOutOfBoundsException."<init>":(Ljava/lang/String;)V
const #45 = Asciz	idx;
const #46 = Asciz	I;
const #47 = Asciz	length;
const #48 = Asciz	(Lscala/collection/generic/SequenceViewTemplate$TakenWhile;)I;
const #49 = Asciz	scala/collection/generic/TraversableViewTemplate$TakenWhile;
const #50 = class	#49;	//  scala/collection/generic/TraversableViewTemplate$TakenWhile
const #51 = Asciz	pred;
const #52 = Asciz	()Lscala/Function1;;
const #53 = NameAndType	#51:#52;//  pred:()Lscala/Function1;
const #54 = InterfaceMethod	#50.#53;	//  scala/collection/generic/TraversableViewTemplate$TakenWhile.pred:()Lscala/Function1;
const #55 = Asciz	prefixLength;
const #56 = Asciz	(Lscala/Function1;)I;
const #57 = NameAndType	#55:#56;//  prefixLength:(Lscala/Function1;)I
const #58 = InterfaceMethod	#23.#57;	//  scala/collection/generic/SequenceTemplate.prefixLength:(Lscala/Function1;)I
const #59 = Asciz	Scala;
const #60 = Asciz	InnerClasses;
const #61 = Asciz	scala/collection/generic/SequenceViewTemplate;
const #62 = class	#61;	//  scala/collection/generic/SequenceViewTemplate
const #63 = Asciz	TakenWhile;
const #64 = Asciz	scala/collection/generic/TraversableViewTemplate;
const #65 = class	#64;	//  scala/collection/generic/TraversableViewTemplate
const #66 = Asciz	scala/collection/generic/SequenceViewTemplate$TakenWhile$class;
const #67 = class	#66;	//  scala/collection/generic/SequenceViewTemplate$TakenWhile$class

{
public static void $init$(scala.collection.generic.SequenceViewTemplate$TakenWhile);
  Code:
   Stack=0, Locals=1, Args_size=1
   0:	return
  LineNumberTable: 
   line 89: 0

  LocalVariableTable: 
   Start  Length  Slot  Name   Signature
   0      1      0    $this       Lscala/collection/generic/SequenceViewTemplate$TakenWhile;


public static java.lang.Object apply(scala.collection.generic.SequenceViewTemplate$TakenWhile, int);
  Code:
   Stack=3, Locals=2, Args_size=2
   0:	iload_1
   1:	aload_0
   2:	invokeinterface	#17,  1; //InterfaceMethod scala/collection/generic/SequenceViewTemplate$TakenWhile.len:()I
   7:	if_icmpge	23
   10:	aload_0
   11:	invokeinterface	#21,  1; //InterfaceMethod scala/collection/generic/SequenceViewTemplate$TakenWhile.scala$collection$generic$SequenceViewTemplate$TakenWhile$$$outer:()Lscala/collection/generic/SequenceViewTemplate;
   16:	iload_1
   17:	invokeinterface	#26,  2; //InterfaceMethod scala/collection/generic/SequenceTemplate.apply:(I)Ljava/lang/Object;
   22:	areturn
   23:	new	#28; //class java/lang/IndexOutOfBoundsException
   26:	dup
   27:	iload_1
   28:	invokestatic	#34; //Method scala/runtime/BoxesRunTime.boxToInteger:(I)Ljava/lang/Integer;
   31:	invokevirtual	#40; //Method java/lang/Object.toString:()Ljava/lang/String;
   34:	invokespecial	#44; //Method java/lang/IndexOutOfBoundsException."<init>":(Ljava/lang/String;)V
   37:	athrow
  LineNumberTable: 
   line 93: 0
   line 94: 23

  LocalVariableTable: 
   Start  Length  Slot  Name   Signature
   0      38      0    $this       Lscala/collection/generic/SequenceViewTemplate$TakenWhile;
   0      38      1    idx       I


public static int length(scala.collection.generic.SequenceViewTemplate$TakenWhile);
  Code:
   Stack=1, Locals=1, Args_size=1
   0:	aload_0
   1:	invokeinterface	#17,  1; //InterfaceMethod scala/collection/generic/SequenceViewTemplate$TakenWhile.len:()I
   6:	ireturn
  LineNumberTable: 
   line 91: 0

  LocalVariableTable: 
   Start  Length  Slot  Name   Signature
   0      7      0    $this       Lscala/collection/generic/SequenceViewTemplate$TakenWhile;


public static int len(scala.collection.generic.SequenceViewTemplate$TakenWhile);
  Code:
   Stack=2, Locals=1, Args_size=1
   0:	aload_0
   1:	invokeinterface	#21,  1; //InterfaceMethod scala/collection/generic/SequenceViewTemplate$TakenWhile.scala$collection$generic$SequenceViewTemplate$TakenWhile$$$outer:()Lscala/collection/generic/SequenceViewTemplate;
   6:	aload_0
   7:	invokeinterface	#54,  1; //InterfaceMethod scala/collection/generic/TraversableViewTemplate$TakenWhile.pred:()Lscala/Function1;
   12:	invokeinterface	#58,  2; //InterfaceMethod scala/collection/generic/SequenceTemplate.prefixLength:(Lscala/Function1;)I
   17:	ireturn
  LineNumberTable: 
   line 90: 0

  LocalVariableTable: 
   Start  Length  Slot  Name   Signature
   0      18      0    $this       Lscala/collection/generic/SequenceViewTemplate$TakenWhile;


}

