Compiled from "SequenceViewTemplate.scala"
public final class scala.collection.generic.SequenceViewTemplate$FlatMapped$$anonfun$index$1 extends java.lang.Object implements scala.Function1,scala.ScalaObject,java.io.Serializable
  SourceFile: "SequenceViewTemplate.scala"
  Scala: length = 0x
   
  InnerClass: 
   public abstract #113= #62 of #112; //FlatMapped=class scala/collection/generic/SequenceViewTemplate$FlatMapped of class scala/collection/generic/SequenceViewTemplate
   public abstract #113= #56 of #115; //FlatMapped=class scala/collection/generic/TraversableViewTemplate$FlatMapped of class scala/collection/generic/TraversableViewTemplate
   public final #116= #17 of #62; //$anonfun$index$1=class scala/collection/generic/SequenceViewTemplate$FlatMapped$$anonfun$index$1 of class scala/collection/generic/SequenceViewTemplate$FlatMapped
  minor version: 0
  major version: 49
  Constant pool:
const #1 = Asciz	SourceFile;
const #2 = Asciz	SequenceViewTemplate.scala;
const #3 = Asciz	index$1;
const #4 = Asciz	[I;
const #5 = Asciz	$outer;
const #6 = Asciz	Lscala/collection/generic/SequenceViewTemplate$FlatMapped;;
const #7 = Asciz	<init>;
const #8 = Asciz	(Lscala/collection/generic/SequenceViewTemplate$FlatMapped;[I)V;
const #9 = Asciz	Code;
const #10 = Asciz	LineNumberTable;
const #11 = Asciz	java/lang/NullPointerException;
const #12 = class	#11;	//  java/lang/NullPointerException
const #13 = Asciz	()V;
const #14 = NameAndType	#7:#13;//  "<init>":()V
const #15 = Method	#12.#14;	//  java/lang/NullPointerException."<init>":()V
const #16 = Asciz	scala/collection/generic/SequenceViewTemplate$FlatMapped$$anonfun$index$1;
const #17 = class	#16;	//  scala/collection/generic/SequenceViewTemplate$FlatMapped$$anonfun$index$1
const #18 = NameAndType	#5:#6;//  $outer:Lscala/collection/generic/SequenceViewTemplate$FlatMapped;
const #19 = Field	#17.#18;	//  scala/collection/generic/SequenceViewTemplate$FlatMapped$$anonfun$index$1.$outer:Lscala/collection/generic/SequenceViewTemplate$FlatMapped;
const #20 = NameAndType	#3:#4;//  index$1:[I
const #21 = Field	#17.#20;	//  scala/collection/generic/SequenceViewTemplate$FlatMapped$$anonfun$index$1.index$1:[I
const #22 = Asciz	java/lang/Object;
const #23 = class	#22;	//  java/lang/Object
const #24 = Method	#23.#14;	//  java/lang/Object."<init>":()V
const #25 = Asciz	scala/Function1$class;
const #26 = class	#25;	//  scala/Function1$class
const #27 = Asciz	$init$;
const #28 = Asciz	(Lscala/Function1;)V;
const #29 = NameAndType	#27:#28;//  $init$:(Lscala/Function1;)V
const #30 = Method	#26.#29;	//  scala/Function1$class.$init$:(Lscala/Function1;)V
const #31 = Asciz	this;
const #32 = Asciz	Lscala/collection/generic/SequenceViewTemplate$FlatMapped$$anonfun$index$1;;
const #33 = Asciz	LocalVariableTable;
const #34 = Asciz	(Lscala/collection/generic/SequenceViewTemplate<TA;TColl;TThis;>.FlatMapped<TB;>;)V;
const #35 = Asciz	Signature;
const #36 = Asciz	apply;
const #37 = Asciz	(Ljava/lang/Object;)Ljava/lang/Object;;
const #38 = Asciz	scala/runtime/BoxesRunTime;
const #39 = class	#38;	//  scala/runtime/BoxesRunTime
const #40 = Asciz	unboxToInt;
const #41 = Asciz	(Ljava/lang/Object;)I;
const #42 = NameAndType	#40:#41;//  unboxToInt:(Ljava/lang/Object;)I
const #43 = Method	#39.#42;	//  scala/runtime/BoxesRunTime.unboxToInt:(Ljava/lang/Object;)I
const #44 = Asciz	(I)V;
const #45 = NameAndType	#36:#44;//  apply:(I)V
const #46 = Method	#17.#45;	//  scala/collection/generic/SequenceViewTemplate$FlatMapped$$anonfun$index$1.apply:(I)V
const #47 = Asciz	scala/runtime/BoxedUnit;
const #48 = class	#47;	//  scala/runtime/BoxedUnit
const #49 = Asciz	UNIT;
const #50 = Asciz	Lscala/runtime/BoxedUnit;;
const #51 = NameAndType	#49:#50;//  UNIT:Lscala/runtime/BoxedUnit;
const #52 = Field	#48.#51;	//  scala/runtime/BoxedUnit.UNIT:Lscala/runtime/BoxedUnit;
const #53 = Asciz	v1;
const #54 = Asciz	Ljava/lang/Object;;
const #55 = Asciz	scala/collection/generic/TraversableViewTemplate$FlatMapped;
const #56 = class	#55;	//  scala/collection/generic/TraversableViewTemplate$FlatMapped
const #57 = Asciz	mapping;
const #58 = Asciz	()Lscala/Function1;;
const #59 = NameAndType	#57:#58;//  mapping:()Lscala/Function1;
const #60 = InterfaceMethod	#56.#59;	//  scala/collection/generic/TraversableViewTemplate$FlatMapped.mapping:()Lscala/Function1;
const #61 = Asciz	scala/collection/generic/SequenceViewTemplate$FlatMapped;
const #62 = class	#61;	//  scala/collection/generic/SequenceViewTemplate$FlatMapped
const #63 = Asciz	scala$collection$generic$SequenceViewTemplate$FlatMapped$$$outer;
const #64 = Asciz	()Lscala/collection/generic/SequenceViewTemplate;;
const #65 = NameAndType	#63:#64;//  scala$collection$generic$SequenceViewTemplate$FlatMapped$$$outer:()Lscala/collection/generic/SequenceViewTemplate;
const #66 = InterfaceMethod	#62.#65;	//  scala/collection/generic/SequenceViewTemplate$FlatMapped.scala$collection$generic$SequenceViewTemplate$FlatMapped$$$outer:()Lscala/collection/generic/SequenceViewTemplate;
const #67 = Asciz	scala/collection/generic/SequenceTemplate;
const #68 = class	#67;	//  scala/collection/generic/SequenceTemplate
const #69 = Asciz	(I)Ljava/lang/Object;;
const #70 = NameAndType	#36:#69;//  apply:(I)Ljava/lang/Object;
const #71 = InterfaceMethod	#68.#70;	//  scala/collection/generic/SequenceTemplate.apply:(I)Ljava/lang/Object;
const #72 = Asciz	scala/Function1;
const #73 = class	#72;	//  scala/Function1
const #74 = NameAndType	#36:#37;//  apply:(Ljava/lang/Object;)Ljava/lang/Object;
const #75 = InterfaceMethod	#73.#74;	//  scala/Function1.apply:(Ljava/lang/Object;)Ljava/lang/Object;
const #76 = Asciz	scala/collection/generic/TraversableTemplate;
const #77 = class	#76;	//  scala/collection/generic/TraversableTemplate
const #78 = Asciz	scala/runtime/ScalaRunTime$;
const #79 = class	#78;	//  scala/runtime/ScalaRunTime$
const #80 = Asciz	MODULE$;
const #81 = Asciz	Lscala/runtime/ScalaRunTime$;;
const #82 = NameAndType	#80:#81;//  MODULE$:Lscala/runtime/ScalaRunTime$;
const #83 = Field	#79.#82;	//  scala/runtime/ScalaRunTime$.MODULE$:Lscala/runtime/ScalaRunTime$;
const #84 = Asciz	boxArray;
const #85 = Asciz	(Ljava/lang/Object;)Lscala/runtime/BoxedArray;;
const #86 = NameAndType	#84:#85;//  boxArray:(Ljava/lang/Object;)Lscala/runtime/BoxedArray;
const #87 = Method	#79.#86;	//  scala/runtime/ScalaRunTime$.boxArray:(Ljava/lang/Object;)Lscala/runtime/BoxedArray;
const #88 = Asciz	size;
const #89 = Asciz	()I;
const #90 = NameAndType	#88:#89;//  size:()I
const #91 = InterfaceMethod	#77.#90;	//  scala/collection/generic/TraversableTemplate.size:()I
const #92 = Asciz	i;
const #93 = Asciz	I;
const #94 = Asciz	andThen;
const #95 = Asciz	(Lscala/Function1;)Lscala/Function1;;
const #96 = Asciz	(Lscala/Function1;Lscala/Function1;)Lscala/Function1;;
const #97 = NameAndType	#94:#96;//  andThen:(Lscala/Function1;Lscala/Function1;)Lscala/Function1;
const #98 = Method	#26.#97;	//  scala/Function1$class.andThen:(Lscala/Function1;Lscala/Function1;)Lscala/Function1;
const #99 = Asciz	g;
const #100 = Asciz	Lscala/Function1;;
const #101 = Asciz	compose;
const #102 = NameAndType	#101:#96;//  compose:(Lscala/Function1;Lscala/Function1;)Lscala/Function1;
const #103 = Method	#26.#102;	//  scala/Function1$class.compose:(Lscala/Function1;Lscala/Function1;)Lscala/Function1;
const #104 = Asciz	toString;
const #105 = Asciz	()Ljava/lang/String;;
const #106 = Asciz	(Lscala/Function1;)Ljava/lang/String;;
const #107 = NameAndType	#104:#106;//  toString:(Lscala/Function1;)Ljava/lang/String;
const #108 = Method	#26.#107;	//  scala/Function1$class.toString:(Lscala/Function1;)Ljava/lang/String;
const #109 = Asciz	Scala;
const #110 = Asciz	InnerClasses;
const #111 = Asciz	scala/collection/generic/SequenceViewTemplate;
const #112 = class	#111;	//  scala/collection/generic/SequenceViewTemplate
const #113 = Asciz	FlatMapped;
const #114 = Asciz	scala/collection/generic/TraversableViewTemplate;
const #115 = class	#114;	//  scala/collection/generic/TraversableViewTemplate
const #116 = Asciz	$anonfun$index$1;
const #117 = Asciz	scala/ScalaObject;
const #118 = class	#117;	//  scala/ScalaObject
const #119 = Asciz	java/io/Serializable;
const #120 = class	#119;	//  java/io/Serializable

{
public scala.collection.generic.SequenceViewTemplate$FlatMapped$$anonfun$index$1(scala.collection.generic.SequenceViewTemplate$FlatMapped, int[]);
  Code:
   Stack=2, Locals=3, Args_size=3
   0:	aload_1
   1:	ifnonnull	12
   4:	new	#12; //class java/lang/NullPointerException
   7:	dup
   8:	invokespecial	#15; //Method java/lang/NullPointerException."<init>":()V
   11:	athrow
   12:	aload_0
   13:	aload_1
   14:	putfield	#19; //Field $outer:Lscala/collection/generic/SequenceViewTemplate$FlatMapped;
   17:	aload_0
   18:	aload_2
   19:	putfield	#21; //Field index$1:[I
   22:	aload_0
   23:	invokespecial	#24; //Method java/lang/Object."<init>":()V
   26:	aload_0
   27:	invokestatic	#30; //Method scala/Function1$class.$init$:(Lscala/Function1;)V
   30:	return
  LineNumberTable: 
   line 50: 0

  LocalVariableTable: 
   Start  Length  Slot  Name   Signature
   0      31      0    this       Lscala/collection/generic/SequenceViewTemplate$FlatMapped$$anonfun$index$1;
   0      31      1    $outer       Lscala/collection/generic/SequenceViewTemplate$FlatMapped;

  Signature: length = 0x2
   00 22 

public final java.lang.Object apply(java.lang.Object);
  Code:
   Stack=2, Locals=3, Args_size=2
   0:	aload_0
   1:	getfield	#19; //Field $outer:Lscala/collection/generic/SequenceViewTemplate$FlatMapped;
   4:	astore_2
   5:	aload_0
   6:	aload_1
   7:	invokestatic	#43; //Method scala/runtime/BoxesRunTime.unboxToInt:(Ljava/lang/Object;)I
   10:	invokevirtual	#46; //Method apply:(I)V
   13:	getstatic	#52; //Field scala/runtime/BoxedUnit.UNIT:Lscala/runtime/BoxedUnit;
   16:	areturn
  LineNumberTable: 
   line 50: 0

  LocalVariableTable: 
   Start  Length  Slot  Name   Signature
   0      17      0    this       Lscala/collection/generic/SequenceViewTemplate$FlatMapped$$anonfun$index$1;
   5      12      1    v1       Ljava/lang/Object;


public final void apply(int);
  Code:
   Stack=6, Locals=4, Args_size=2
   0:	aload_0
   1:	getfield	#19; //Field $outer:Lscala/collection/generic/SequenceViewTemplate$FlatMapped;
   4:	astore_3
   5:	aload_0
   6:	getfield	#21; //Field index$1:[I
   9:	iload_1
   10:	iconst_1
   11:	iadd
   12:	aload_0
   13:	getfield	#21; //Field index$1:[I
   16:	iload_1
   17:	iaload
   18:	aload_0
   19:	getfield	#19; //Field $outer:Lscala/collection/generic/SequenceViewTemplate$FlatMapped;
   22:	invokeinterface	#60,  1; //InterfaceMethod scala/collection/generic/TraversableViewTemplate$FlatMapped.mapping:()Lscala/Function1;
   27:	aload_0
   28:	getfield	#19; //Field $outer:Lscala/collection/generic/SequenceViewTemplate$FlatMapped;
   31:	invokeinterface	#66,  1; //InterfaceMethod scala/collection/generic/SequenceViewTemplate$FlatMapped.scala$collection$generic$SequenceViewTemplate$FlatMapped$$$outer:()Lscala/collection/generic/SequenceViewTemplate;
   36:	iload_1
   37:	invokeinterface	#71,  2; //InterfaceMethod scala/collection/generic/SequenceTemplate.apply:(I)Ljava/lang/Object;
   42:	invokeinterface	#75,  2; //InterfaceMethod scala/Function1.apply:(Ljava/lang/Object;)Ljava/lang/Object;
   47:	astore_2
   48:	aload_2
   49:	instanceof	#77; //class scala/collection/generic/TraversableTemplate
   52:	ifeq	59
   55:	aload_2
   56:	goto	66
   59:	getstatic	#83; //Field scala/runtime/ScalaRunTime$.MODULE$:Lscala/runtime/ScalaRunTime$;
   62:	aload_2
   63:	invokevirtual	#87; //Method scala/runtime/ScalaRunTime$.boxArray:(Ljava/lang/Object;)Lscala/runtime/BoxedArray;
   66:	checkcast	#77; //class scala/collection/generic/TraversableTemplate
   69:	invokeinterface	#91,  1; //InterfaceMethod scala/collection/generic/TraversableTemplate.size:()I
   74:	iadd
   75:	iastore
   76:	return
  LineNumberTable: 
   line 51: 0

  LocalVariableTable: 
   Start  Length  Slot  Name   Signature
   0      77      0    this       Lscala/collection/generic/SequenceViewTemplate$FlatMapped$$anonfun$index$1;
   5      72      1    i       I


public scala.Function1 andThen(scala.Function1);
  Code:
   Stack=2, Locals=2, Args_size=2
   0:	aload_0
   1:	aload_1
   2:	invokestatic	#98; //Method scala/Function1$class.andThen:(Lscala/Function1;Lscala/Function1;)Lscala/Function1;
   5:	areturn
  LineNumberTable: 
   line 50: 0

  LocalVariableTable: 
   Start  Length  Slot  Name   Signature
   0      6      0    this       Lscala/collection/generic/SequenceViewTemplate$FlatMapped$$anonfun$index$1;
   0      6      1    g       Lscala/Function1;


public scala.Function1 compose(scala.Function1);
  Code:
   Stack=2, Locals=2, Args_size=2
   0:	aload_0
   1:	aload_1
   2:	invokestatic	#103; //Method scala/Function1$class.compose:(Lscala/Function1;Lscala/Function1;)Lscala/Function1;
   5:	areturn
  LineNumberTable: 
   line 50: 0

  LocalVariableTable: 
   Start  Length  Slot  Name   Signature
   0      6      0    this       Lscala/collection/generic/SequenceViewTemplate$FlatMapped$$anonfun$index$1;
   0      6      1    g       Lscala/Function1;


public java.lang.String toString();
  Code:
   Stack=1, Locals=1, Args_size=1
   0:	aload_0
   1:	invokestatic	#108; //Method scala/Function1$class.toString:(Lscala/Function1;)Ljava/lang/String;
   4:	areturn
  LineNumberTable: 
   line 50: 0


}

