Compiled from "SequenceViewTemplate.scala"
public final class scala.collection.generic.SequenceViewTemplate$Filtered$$anonfun$index$2 extends java.lang.Object implements scala.Function1,scala.ScalaObject,java.io.Serializable
  SourceFile: "SequenceViewTemplate.scala"
  Scala: length = 0x
   
  InnerClass: 
   public abstract #110= #66 of #109; //Filtered=class scala/collection/generic/SequenceViewTemplate$Filtered of class scala/collection/generic/SequenceViewTemplate
   public abstract #110= #60 of #112; //Filtered=class scala/collection/generic/TraversableViewTemplate$Filtered of class scala/collection/generic/TraversableViewTemplate
   public final #113= #19 of #66; //$anonfun$index$2=class scala/collection/generic/SequenceViewTemplate$Filtered$$anonfun$index$2 of class scala/collection/generic/SequenceViewTemplate$Filtered
  minor version: 0
  major version: 49
  Constant pool:
const #1 = Asciz	SourceFile;
const #2 = Asciz	SequenceViewTemplate.scala;
const #3 = Asciz	arr$1;
const #4 = Asciz	[I;
const #5 = Asciz	len$1;
const #6 = Asciz	Lscala/runtime/IntRef;;
const #7 = Asciz	$outer;
const #8 = Asciz	Lscala/collection/generic/SequenceViewTemplate$Filtered;;
const #9 = Asciz	<init>;
const #10 = Asciz	(Lscala/collection/generic/SequenceViewTemplate$Filtered;Lscala/runtime/IntRef;[I)V;
const #11 = Asciz	Code;
const #12 = Asciz	LineNumberTable;
const #13 = Asciz	java/lang/NullPointerException;
const #14 = class	#13;	//  java/lang/NullPointerException
const #15 = Asciz	()V;
const #16 = NameAndType	#9:#15;//  "<init>":()V
const #17 = Method	#14.#16;	//  java/lang/NullPointerException."<init>":()V
const #18 = Asciz	scala/collection/generic/SequenceViewTemplate$Filtered$$anonfun$index$2;
const #19 = class	#18;	//  scala/collection/generic/SequenceViewTemplate$Filtered$$anonfun$index$2
const #20 = NameAndType	#7:#8;//  $outer:Lscala/collection/generic/SequenceViewTemplate$Filtered;
const #21 = Field	#19.#20;	//  scala/collection/generic/SequenceViewTemplate$Filtered$$anonfun$index$2.$outer:Lscala/collection/generic/SequenceViewTemplate$Filtered;
const #22 = NameAndType	#5:#6;//  len$1:Lscala/runtime/IntRef;
const #23 = Field	#19.#22;	//  scala/collection/generic/SequenceViewTemplate$Filtered$$anonfun$index$2.len$1:Lscala/runtime/IntRef;
const #24 = NameAndType	#3:#4;//  arr$1:[I
const #25 = Field	#19.#24;	//  scala/collection/generic/SequenceViewTemplate$Filtered$$anonfun$index$2.arr$1:[I
const #26 = Asciz	java/lang/Object;
const #27 = class	#26;	//  java/lang/Object
const #28 = Method	#27.#16;	//  java/lang/Object."<init>":()V
const #29 = Asciz	scala/Function1$class;
const #30 = class	#29;	//  scala/Function1$class
const #31 = Asciz	$init$;
const #32 = Asciz	(Lscala/Function1;)V;
const #33 = NameAndType	#31:#32;//  $init$:(Lscala/Function1;)V
const #34 = Method	#30.#33;	//  scala/Function1$class.$init$:(Lscala/Function1;)V
const #35 = Asciz	this;
const #36 = Asciz	Lscala/collection/generic/SequenceViewTemplate$Filtered$$anonfun$index$2;;
const #37 = Asciz	LocalVariableTable;
const #38 = Asciz	(Lscala/collection/generic/SequenceViewTemplate<TA;TColl;TThis;>.Filtered;)V;
const #39 = Asciz	Signature;
const #40 = Asciz	apply;
const #41 = Asciz	(Ljava/lang/Object;)Ljava/lang/Object;;
const #42 = Asciz	scala/runtime/BoxesRunTime;
const #43 = class	#42;	//  scala/runtime/BoxesRunTime
const #44 = Asciz	unboxToInt;
const #45 = Asciz	(Ljava/lang/Object;)I;
const #46 = NameAndType	#44:#45;//  unboxToInt:(Ljava/lang/Object;)I
const #47 = Method	#43.#46;	//  scala/runtime/BoxesRunTime.unboxToInt:(Ljava/lang/Object;)I
const #48 = Asciz	(I)V;
const #49 = NameAndType	#40:#48;//  apply:(I)V
const #50 = Method	#19.#49;	//  scala/collection/generic/SequenceViewTemplate$Filtered$$anonfun$index$2.apply:(I)V
const #51 = Asciz	scala/runtime/BoxedUnit;
const #52 = class	#51;	//  scala/runtime/BoxedUnit
const #53 = Asciz	UNIT;
const #54 = Asciz	Lscala/runtime/BoxedUnit;;
const #55 = NameAndType	#53:#54;//  UNIT:Lscala/runtime/BoxedUnit;
const #56 = Field	#52.#55;	//  scala/runtime/BoxedUnit.UNIT:Lscala/runtime/BoxedUnit;
const #57 = Asciz	v1;
const #58 = Asciz	Ljava/lang/Object;;
const #59 = Asciz	scala/collection/generic/TraversableViewTemplate$Filtered;
const #60 = class	#59;	//  scala/collection/generic/TraversableViewTemplate$Filtered
const #61 = Asciz	pred;
const #62 = Asciz	()Lscala/Function1;;
const #63 = NameAndType	#61:#62;//  pred:()Lscala/Function1;
const #64 = InterfaceMethod	#60.#63;	//  scala/collection/generic/TraversableViewTemplate$Filtered.pred:()Lscala/Function1;
const #65 = Asciz	scala/collection/generic/SequenceViewTemplate$Filtered;
const #66 = class	#65;	//  scala/collection/generic/SequenceViewTemplate$Filtered
const #67 = Asciz	scala$collection$generic$SequenceViewTemplate$Filtered$$$outer;
const #68 = Asciz	()Lscala/collection/generic/SequenceViewTemplate;;
const #69 = NameAndType	#67:#68;//  scala$collection$generic$SequenceViewTemplate$Filtered$$$outer:()Lscala/collection/generic/SequenceViewTemplate;
const #70 = InterfaceMethod	#66.#69;	//  scala/collection/generic/SequenceViewTemplate$Filtered.scala$collection$generic$SequenceViewTemplate$Filtered$$$outer:()Lscala/collection/generic/SequenceViewTemplate;
const #71 = Asciz	scala/collection/generic/SequenceTemplate;
const #72 = class	#71;	//  scala/collection/generic/SequenceTemplate
const #73 = Asciz	(I)Ljava/lang/Object;;
const #74 = NameAndType	#40:#73;//  apply:(I)Ljava/lang/Object;
const #75 = InterfaceMethod	#72.#74;	//  scala/collection/generic/SequenceTemplate.apply:(I)Ljava/lang/Object;
const #76 = Asciz	scala/Function1;
const #77 = class	#76;	//  scala/Function1
const #78 = NameAndType	#40:#41;//  apply:(Ljava/lang/Object;)Ljava/lang/Object;
const #79 = InterfaceMethod	#77.#78;	//  scala/Function1.apply:(Ljava/lang/Object;)Ljava/lang/Object;
const #80 = Asciz	unboxToBoolean;
const #81 = Asciz	(Ljava/lang/Object;)Z;
const #82 = NameAndType	#80:#81;//  unboxToBoolean:(Ljava/lang/Object;)Z
const #83 = Method	#43.#82;	//  scala/runtime/BoxesRunTime.unboxToBoolean:(Ljava/lang/Object;)Z
const #84 = Asciz	scala/runtime/IntRef;
const #85 = class	#84;	//  scala/runtime/IntRef
const #86 = Asciz	elem;
const #87 = Asciz	I;
const #88 = NameAndType	#86:#87;//  elem:I
const #89 = Field	#85.#88;	//  scala/runtime/IntRef.elem:I
const #90 = Asciz	i;
const #91 = Asciz	andThen;
const #92 = Asciz	(Lscala/Function1;)Lscala/Function1;;
const #93 = Asciz	(Lscala/Function1;Lscala/Function1;)Lscala/Function1;;
const #94 = NameAndType	#91:#93;//  andThen:(Lscala/Function1;Lscala/Function1;)Lscala/Function1;
const #95 = Method	#30.#94;	//  scala/Function1$class.andThen:(Lscala/Function1;Lscala/Function1;)Lscala/Function1;
const #96 = Asciz	g;
const #97 = Asciz	Lscala/Function1;;
const #98 = Asciz	compose;
const #99 = NameAndType	#98:#93;//  compose:(Lscala/Function1;Lscala/Function1;)Lscala/Function1;
const #100 = Method	#30.#99;	//  scala/Function1$class.compose:(Lscala/Function1;Lscala/Function1;)Lscala/Function1;
const #101 = Asciz	toString;
const #102 = Asciz	()Ljava/lang/String;;
const #103 = Asciz	(Lscala/Function1;)Ljava/lang/String;;
const #104 = NameAndType	#101:#103;//  toString:(Lscala/Function1;)Ljava/lang/String;
const #105 = Method	#30.#104;	//  scala/Function1$class.toString:(Lscala/Function1;)Ljava/lang/String;
const #106 = Asciz	Scala;
const #107 = Asciz	InnerClasses;
const #108 = Asciz	scala/collection/generic/SequenceViewTemplate;
const #109 = class	#108;	//  scala/collection/generic/SequenceViewTemplate
const #110 = Asciz	Filtered;
const #111 = Asciz	scala/collection/generic/TraversableViewTemplate;
const #112 = class	#111;	//  scala/collection/generic/TraversableViewTemplate
const #113 = Asciz	$anonfun$index$2;
const #114 = Asciz	scala/ScalaObject;
const #115 = class	#114;	//  scala/ScalaObject
const #116 = Asciz	java/io/Serializable;
const #117 = class	#116;	//  java/io/Serializable

{
public scala.collection.generic.SequenceViewTemplate$Filtered$$anonfun$index$2(scala.collection.generic.SequenceViewTemplate$Filtered, scala.runtime.IntRef, int[]);
  Code:
   Stack=2, Locals=4, Args_size=4
   0:	aload_1
   1:	ifnonnull	12
   4:	new	#14; //class java/lang/NullPointerException
   7:	dup
   8:	invokespecial	#17; //Method java/lang/NullPointerException."<init>":()V
   11:	athrow
   12:	aload_0
   13:	aload_1
   14:	putfield	#21; //Field $outer:Lscala/collection/generic/SequenceViewTemplate$Filtered;
   17:	aload_0
   18:	aload_2
   19:	putfield	#23; //Field len$1:Lscala/runtime/IntRef;
   22:	aload_0
   23:	aload_3
   24:	putfield	#25; //Field arr$1:[I
   27:	aload_0
   28:	invokespecial	#28; //Method java/lang/Object."<init>":()V
   31:	aload_0
   32:	invokestatic	#34; //Method scala/Function1$class.$init$:(Lscala/Function1;)V
   35:	return
  LineNumberTable: 
   line 78: 0

  LocalVariableTable: 
   Start  Length  Slot  Name   Signature
   0      36      0    this       Lscala/collection/generic/SequenceViewTemplate$Filtered$$anonfun$index$2;
   0      36      1    $outer       Lscala/collection/generic/SequenceViewTemplate$Filtered;

  Signature: length = 0x2
   00 26 

public final java.lang.Object apply(java.lang.Object);
  Code:
   Stack=2, Locals=3, Args_size=2
   0:	aload_0
   1:	getfield	#21; //Field $outer:Lscala/collection/generic/SequenceViewTemplate$Filtered;
   4:	astore_2
   5:	aload_0
   6:	aload_1
   7:	invokestatic	#47; //Method scala/runtime/BoxesRunTime.unboxToInt:(Ljava/lang/Object;)I
   10:	invokevirtual	#50; //Method apply:(I)V
   13:	getstatic	#56; //Field scala/runtime/BoxedUnit.UNIT:Lscala/runtime/BoxedUnit;
   16:	areturn
  LineNumberTable: 
   line 78: 0

  LocalVariableTable: 
   Start  Length  Slot  Name   Signature
   0      17      0    this       Lscala/collection/generic/SequenceViewTemplate$Filtered$$anonfun$index$2;
   5      12      1    v1       Ljava/lang/Object;


public final void apply(int);
  Code:
   Stack=3, Locals=3, Args_size=2
   0:	aload_0
   1:	getfield	#21; //Field $outer:Lscala/collection/generic/SequenceViewTemplate$Filtered;
   4:	astore_2
   5:	aload_0
   6:	getfield	#21; //Field $outer:Lscala/collection/generic/SequenceViewTemplate$Filtered;
   9:	invokeinterface	#64,  1; //InterfaceMethod scala/collection/generic/TraversableViewTemplate$Filtered.pred:()Lscala/Function1;
   14:	aload_0
   15:	getfield	#21; //Field $outer:Lscala/collection/generic/SequenceViewTemplate$Filtered;
   18:	invokeinterface	#70,  1; //InterfaceMethod scala/collection/generic/SequenceViewTemplate$Filtered.scala$collection$generic$SequenceViewTemplate$Filtered$$$outer:()Lscala/collection/generic/SequenceViewTemplate;
   23:	iload_1
   24:	invokeinterface	#75,  2; //InterfaceMethod scala/collection/generic/SequenceTemplate.apply:(I)Ljava/lang/Object;
   29:	invokeinterface	#79,  2; //InterfaceMethod scala/Function1.apply:(Ljava/lang/Object;)Ljava/lang/Object;
   34:	invokestatic	#83; //Method scala/runtime/BoxesRunTime.unboxToBoolean:(Ljava/lang/Object;)Z
   37:	ifeq	69
   40:	aload_0
   41:	getfield	#25; //Field arr$1:[I
   44:	aload_0
   45:	getfield	#23; //Field len$1:Lscala/runtime/IntRef;
   48:	getfield	#89; //Field scala/runtime/IntRef.elem:I
   51:	iload_1
   52:	iastore
   53:	aload_0
   54:	getfield	#23; //Field len$1:Lscala/runtime/IntRef;
   57:	aload_0
   58:	getfield	#23; //Field len$1:Lscala/runtime/IntRef;
   61:	getfield	#89; //Field scala/runtime/IntRef.elem:I
   64:	iconst_1
   65:	iadd
   66:	putfield	#89; //Field scala/runtime/IntRef.elem:I
   69:	return
  LineNumberTable: 
   line 79: 0
   line 80: 40
   line 81: 53
   line 79: 69

  LocalVariableTable: 
   Start  Length  Slot  Name   Signature
   0      70      0    this       Lscala/collection/generic/SequenceViewTemplate$Filtered$$anonfun$index$2;
   5      65      1    i       I


public scala.Function1 andThen(scala.Function1);
  Code:
   Stack=2, Locals=2, Args_size=2
   0:	aload_0
   1:	aload_1
   2:	invokestatic	#95; //Method scala/Function1$class.andThen:(Lscala/Function1;Lscala/Function1;)Lscala/Function1;
   5:	areturn
  LineNumberTable: 
   line 78: 0

  LocalVariableTable: 
   Start  Length  Slot  Name   Signature
   0      6      0    this       Lscala/collection/generic/SequenceViewTemplate$Filtered$$anonfun$index$2;
   0      6      1    g       Lscala/Function1;


public scala.Function1 compose(scala.Function1);
  Code:
   Stack=2, Locals=2, Args_size=2
   0:	aload_0
   1:	aload_1
   2:	invokestatic	#100; //Method scala/Function1$class.compose:(Lscala/Function1;Lscala/Function1;)Lscala/Function1;
   5:	areturn
  LineNumberTable: 
   line 78: 0

  LocalVariableTable: 
   Start  Length  Slot  Name   Signature
   0      6      0    this       Lscala/collection/generic/SequenceViewTemplate$Filtered$$anonfun$index$2;
   0      6      1    g       Lscala/Function1;


public java.lang.String toString();
  Code:
   Stack=1, Locals=1, Args_size=1
   0:	aload_0
   1:	invokestatic	#105; //Method scala/Function1$class.toString:(Lscala/Function1;)Ljava/lang/String;
   4:	areturn
  LineNumberTable: 
   line 78: 0


}

