Compiled from "SequenceViewTemplate.scala"
public abstract class scala.collection.generic.SequenceViewTemplate$class extends java.lang.Object
  SourceFile: "SequenceViewTemplate.scala"
  Scala: length = 0x
   
  InnerClass: 
   public final #175= #123 of #29; //$anon$8=class scala/collection/generic/SequenceViewTemplate$$anon$8 of class scala/collection/generic/SequenceViewTemplate
   public final #176= #151 of #29; //$anon$4=class scala/collection/generic/SequenceViewTemplate$$anon$4 of class scala/collection/generic/SequenceViewTemplate
   public final #177= #137 of #29; //$anon$6=class scala/collection/generic/SequenceViewTemplate$$anon$6 of class scala/collection/generic/SequenceViewTemplate
   public final #178= #161 of #29; //$anon$2=class scala/collection/generic/SequenceViewTemplate$$anon$2 of class scala/collection/generic/SequenceViewTemplate
   public final #179= #129 of #29; //$anon$7=class scala/collection/generic/SequenceViewTemplate$$anon$7 of class scala/collection/generic/SequenceViewTemplate
   public final #180= #156 of #29; //$anon$3=class scala/collection/generic/SequenceViewTemplate$$anon$3 of class scala/collection/generic/SequenceViewTemplate
   public final #181= #143 of #29; //$anon$5=class scala/collection/generic/SequenceViewTemplate$$anon$5 of class scala/collection/generic/SequenceViewTemplate
   public final #182= #114 of #29; //$anon$9=class scala/collection/generic/SequenceViewTemplate$$anon$9 of class scala/collection/generic/SequenceViewTemplate
   public final #183= #167 of #29; //$anon$1=class scala/collection/generic/SequenceViewTemplate$$anon$1 of class scala/collection/generic/SequenceViewTemplate
   public final #184= #107 of #29; //$anon$10=class scala/collection/generic/SequenceViewTemplate$$anon$10 of class scala/collection/generic/SequenceViewTemplate
   public abstract #187= #186 of #29; //Transformed=class scala/collection/generic/SequenceViewTemplate$Transformed of class scala/collection/generic/SequenceViewTemplate
   public final #188= #76 of #29; //$anonfun$padTo$1=class scala/collection/generic/SequenceViewTemplate$$anonfun$padTo$1 of class scala/collection/generic/SequenceViewTemplate
  minor version: 0
  major version: 49
  Constant pool:
const #1 = Asciz	SourceFile;
const #2 = Asciz	SequenceViewTemplate.scala;
const #3 = Asciz	$init$;
const #4 = Asciz	(Lscala/collection/generic/SequenceViewTemplate;)V;
const #5 = Asciz	Code;
const #6 = Asciz	LineNumberTable;
const #7 = Asciz	$this;
const #8 = Asciz	Lscala/collection/generic/SequenceViewTemplate;;
const #9 = Asciz	LocalVariableTable;
const #10 = Asciz	zipAll;
const #11 = Asciz	(Lscala/collection/generic/SequenceViewTemplate;Lscala/collection/Sequence;Ljava/lang/Object;Ljava/lang/Object;Lscala/collection/generic/BuilderFactory;)Ljava/lang/Object;;
const #12 = Asciz	scala/collection/generic/SequenceTemplate;
const #13 = class	#12;	//  scala/collection/generic/SequenceTemplate
const #14 = Asciz	length;
const #15 = Asciz	()I;
const #16 = NameAndType	#14:#15;//  length:()I
const #17 = InterfaceMethod	#13.#16;	//  scala/collection/generic/SequenceTemplate.length:()I
const #18 = Asciz	scala/collection/generic/SequenceView$;
const #19 = class	#18;	//  scala/collection/generic/SequenceView$
const #20 = Asciz	MODULE$;
const #21 = Asciz	Lscala/collection/generic/SequenceView$;;
const #22 = NameAndType	#20:#21;//  MODULE$:Lscala/collection/generic/SequenceView$;
const #23 = Field	#19.#22;	//  scala/collection/generic/SequenceView$.MODULE$:Lscala/collection/generic/SequenceView$;
const #24 = Asciz	builderFactory;
const #25 = Asciz	()Lscala/collection/generic/BuilderFactory;;
const #26 = NameAndType	#24:#25;//  builderFactory:()Lscala/collection/generic/BuilderFactory;
const #27 = Method	#19.#26;	//  scala/collection/generic/SequenceView$.builderFactory:()Lscala/collection/generic/BuilderFactory;
const #28 = Asciz	scala/collection/generic/SequenceViewTemplate;
const #29 = class	#28;	//  scala/collection/generic/SequenceViewTemplate
const #30 = Asciz	padTo;
const #31 = Asciz	(ILjava/lang/Object;Lscala/collection/generic/BuilderFactory;)Ljava/lang/Object;;
const #32 = NameAndType	#30:#31;//  padTo:(ILjava/lang/Object;Lscala/collection/generic/BuilderFactory;)Ljava/lang/Object;
const #33 = InterfaceMethod	#29.#32;	//  scala/collection/generic/SequenceViewTemplate.padTo:(ILjava/lang/Object;Lscala/collection/generic/BuilderFactory;)Ljava/lang/Object;
const #34 = Asciz	scala/collection/Sequence$;
const #35 = class	#34;	//  scala/collection/Sequence$
const #36 = Asciz	Lscala/collection/Sequence$;;
const #37 = NameAndType	#20:#36;//  MODULE$:Lscala/collection/Sequence$;
const #38 = Field	#35.#37;	//  scala/collection/Sequence$.MODULE$:Lscala/collection/Sequence$;
const #39 = Method	#35.#26;	//  scala/collection/Sequence$.builderFactory:()Lscala/collection/generic/BuilderFactory;
const #40 = InterfaceMethod	#13.#32;	//  scala/collection/generic/SequenceTemplate.padTo:(ILjava/lang/Object;Lscala/collection/generic/BuilderFactory;)Ljava/lang/Object;
const #41 = Asciz	scala/collection/Sequence;
const #42 = class	#41;	//  scala/collection/Sequence
const #43 = Asciz	scala/runtime/ScalaRunTime$;
const #44 = class	#43;	//  scala/runtime/ScalaRunTime$
const #45 = Asciz	Lscala/runtime/ScalaRunTime$;;
const #46 = NameAndType	#20:#45;//  MODULE$:Lscala/runtime/ScalaRunTime$;
const #47 = Field	#44.#46;	//  scala/runtime/ScalaRunTime$.MODULE$:Lscala/runtime/ScalaRunTime$;
const #48 = Asciz	boxArray;
const #49 = Asciz	(Ljava/lang/Object;)Lscala/runtime/BoxedArray;;
const #50 = NameAndType	#48:#49;//  boxArray:(Ljava/lang/Object;)Lscala/runtime/BoxedArray;
const #51 = Method	#44.#50;	//  scala/runtime/ScalaRunTime$.boxArray:(Ljava/lang/Object;)Lscala/runtime/BoxedArray;
const #52 = Asciz	zip;
const #53 = Asciz	(Lscala/collection/Sequence;Lscala/collection/generic/BuilderFactory;)Ljava/lang/Object;;
const #54 = NameAndType	#52:#53;//  zip:(Lscala/collection/Sequence;Lscala/collection/generic/BuilderFactory;)Ljava/lang/Object;
const #55 = InterfaceMethod	#29.#54;	//  scala/collection/generic/SequenceViewTemplate.zip:(Lscala/collection/Sequence;Lscala/collection/generic/BuilderFactory;)Ljava/lang/Object;
const #56 = Asciz	that;
const #57 = Asciz	Lscala/collection/Sequence;;
const #58 = Asciz	thisElem;
const #59 = Asciz	Ljava/lang/Object;;
const #60 = Asciz	thatElem;
const #61 = Asciz	bf;
const #62 = Asciz	Lscala/collection/generic/BuilderFactory;;
const #63 = Asciz	zipWithIndex;
const #64 = Asciz	(Lscala/collection/generic/SequenceViewTemplate;Lscala/collection/generic/BuilderFactory;)Ljava/lang/Object;;
const #65 = Asciz	range;
const #66 = Asciz	(II)Lscala/collection/Traversable;;
const #67 = NameAndType	#65:#66;//  range:(II)Lscala/collection/Traversable;
const #68 = Method	#35.#67;	//  scala/collection/Sequence$.range:(II)Lscala/collection/Traversable;
const #69 = Asciz	(Lscala/collection/generic/SequenceViewTemplate;Lscala/collection/Sequence;Lscala/collection/generic/BuilderFactory;)Ljava/lang/Object;;
const #70 = Asciz	newZipped;
const #71 = Asciz	(Lscala/collection/Sequence;)Lscala/collection/generic/SequenceViewTemplate$Transformed;;
const #72 = NameAndType	#70:#71;//  newZipped:(Lscala/collection/Sequence;)Lscala/collection/generic/SequenceViewTemplate$Transformed;
const #73 = InterfaceMethod	#29.#72;	//  scala/collection/generic/SequenceViewTemplate.newZipped:(Lscala/collection/Sequence;)Lscala/collection/generic/SequenceViewTemplate$Transformed;
const #74 = Asciz	(Lscala/collection/generic/SequenceViewTemplate;ILjava/lang/Object;Lscala/collection/generic/BuilderFactory;)Ljava/lang/Object;;
const #75 = Asciz	scala/collection/generic/SequenceViewTemplate$$anonfun$padTo$1;
const #76 = class	#75;	//  scala/collection/generic/SequenceViewTemplate$$anonfun$padTo$1
const #77 = Asciz	<init>;
const #78 = Asciz	(Lscala/collection/generic/SequenceViewTemplate;Ljava/lang/Object;)V;
const #79 = NameAndType	#77:#78;//  "<init>":(Lscala/collection/generic/SequenceViewTemplate;Ljava/lang/Object;)V
const #80 = Method	#76.#79;	//  scala/collection/generic/SequenceViewTemplate$$anonfun$padTo$1."<init>":(Lscala/collection/generic/SequenceViewTemplate;Ljava/lang/Object;)V
const #81 = Asciz	fill;
const #82 = Asciz	(ILscala/Function0;)Lscala/collection/Traversable;;
const #83 = NameAndType	#81:#82;//  fill:(ILscala/Function0;)Lscala/collection/Traversable;
const #84 = Method	#35.#83;	//  scala/collection/Sequence$.fill:(ILscala/Function0;)Lscala/collection/Traversable;
const #85 = Asciz	patch;
const #86 = Asciz	(ILscala/collection/Sequence;ILscala/collection/generic/BuilderFactory;)Ljava/lang/Object;;
const #87 = NameAndType	#85:#86;//  patch:(ILscala/collection/Sequence;ILscala/collection/generic/BuilderFactory;)Ljava/lang/Object;
const #88 = InterfaceMethod	#29.#87;	//  scala/collection/generic/SequenceViewTemplate.patch:(ILscala/collection/Sequence;ILscala/collection/generic/BuilderFactory;)Ljava/lang/Object;
const #89 = Asciz	len;
const #90 = Asciz	I;
const #91 = Asciz	elem$1;
const #92 = Asciz	(Lscala/collection/generic/SequenceViewTemplate;ILscala/collection/Sequence;ILscala/collection/generic/BuilderFactory;)Ljava/lang/Object;;
const #93 = Asciz	newPatched;
const #94 = Asciz	(ILscala/collection/Sequence;I)Lscala/collection/generic/SequenceViewTemplate$Transformed;;
const #95 = NameAndType	#93:#94;//  newPatched:(ILscala/collection/Sequence;I)Lscala/collection/generic/SequenceViewTemplate$Transformed;
const #96 = InterfaceMethod	#29.#95;	//  scala/collection/generic/SequenceViewTemplate.newPatched:(ILscala/collection/Sequence;I)Lscala/collection/generic/SequenceViewTemplate$Transformed;
const #97 = Asciz	from;
const #98 = Asciz	replaced;
const #99 = Asciz	reverse;
const #100 = Asciz	(Lscala/collection/generic/SequenceViewTemplate;)Lscala/collection/generic/SequenceView;;
const #101 = Asciz	newReversed;
const #102 = Asciz	()Lscala/collection/generic/SequenceViewTemplate$Transformed;;
const #103 = NameAndType	#101:#102;//  newReversed:()Lscala/collection/generic/SequenceViewTemplate$Transformed;
const #104 = InterfaceMethod	#29.#103;	//  scala/collection/generic/SequenceViewTemplate.newReversed:()Lscala/collection/generic/SequenceViewTemplate$Transformed;
const #105 = Asciz	(Lscala/collection/generic/SequenceViewTemplate;Lscala/collection/Sequence;)Lscala/collection/generic/SequenceViewTemplate$Transformed;;
const #106 = Asciz	scala/collection/generic/SequenceViewTemplate$$anon$10;
const #107 = class	#106;	//  scala/collection/generic/SequenceViewTemplate$$anon$10
const #108 = Asciz	(Lscala/collection/generic/SequenceViewTemplate;Lscala/collection/Sequence;)V;
const #109 = NameAndType	#77:#108;//  "<init>":(Lscala/collection/generic/SequenceViewTemplate;Lscala/collection/Sequence;)V
const #110 = Method	#107.#109;	//  scala/collection/generic/SequenceViewTemplate$$anon$10."<init>":(Lscala/collection/generic/SequenceViewTemplate;Lscala/collection/Sequence;)V
const #111 = Asciz	that$2;
const #112 = Asciz	(Lscala/collection/generic/SequenceViewTemplate;ILscala/collection/Sequence;I)Lscala/collection/generic/SequenceViewTemplate$Transformed;;
const #113 = Asciz	scala/collection/generic/SequenceViewTemplate$$anon$9;
const #114 = class	#113;	//  scala/collection/generic/SequenceViewTemplate$$anon$9
const #115 = Asciz	(Lscala/collection/generic/SequenceViewTemplate;ILscala/collection/Sequence;I)V;
const #116 = NameAndType	#77:#115;//  "<init>":(Lscala/collection/generic/SequenceViewTemplate;ILscala/collection/Sequence;I)V
const #117 = Method	#114.#116;	//  scala/collection/generic/SequenceViewTemplate$$anon$9."<init>":(Lscala/collection/generic/SequenceViewTemplate;ILscala/collection/Sequence;I)V
const #118 = Asciz	_from$2;
const #119 = Asciz	_patch$1;
const #120 = Asciz	_replaced$1;
const #121 = Asciz	(Lscala/collection/generic/SequenceViewTemplate;)Lscala/collection/generic/SequenceViewTemplate$Transformed;;
const #122 = Asciz	scala/collection/generic/SequenceViewTemplate$$anon$8;
const #123 = class	#122;	//  scala/collection/generic/SequenceViewTemplate$$anon$8
const #124 = NameAndType	#77:#4;//  "<init>":(Lscala/collection/generic/SequenceViewTemplate;)V
const #125 = Method	#123.#124;	//  scala/collection/generic/SequenceViewTemplate$$anon$8."<init>":(Lscala/collection/generic/SequenceViewTemplate;)V
const #126 = Asciz	newTakenWhile;
const #127 = Asciz	(Lscala/collection/generic/SequenceViewTemplate;Lscala/Function1;)Lscala/collection/generic/SequenceViewTemplate$Transformed;;
const #128 = Asciz	scala/collection/generic/SequenceViewTemplate$$anon$7;
const #129 = class	#128;	//  scala/collection/generic/SequenceViewTemplate$$anon$7
const #130 = Asciz	(Lscala/collection/generic/SequenceViewTemplate;Lscala/Function1;)V;
const #131 = NameAndType	#77:#130;//  "<init>":(Lscala/collection/generic/SequenceViewTemplate;Lscala/Function1;)V
const #132 = Method	#129.#131;	//  scala/collection/generic/SequenceViewTemplate$$anon$7."<init>":(Lscala/collection/generic/SequenceViewTemplate;Lscala/Function1;)V
const #133 = Asciz	p$3;
const #134 = Asciz	Lscala/Function1;;
const #135 = Asciz	newDroppedWhile;
const #136 = Asciz	scala/collection/generic/SequenceViewTemplate$$anon$6;
const #137 = class	#136;	//  scala/collection/generic/SequenceViewTemplate$$anon$6
const #138 = Method	#137.#131;	//  scala/collection/generic/SequenceViewTemplate$$anon$6."<init>":(Lscala/collection/generic/SequenceViewTemplate;Lscala/Function1;)V
const #139 = Asciz	p$2;
const #140 = Asciz	newSliced;
const #141 = Asciz	(Lscala/collection/generic/SequenceViewTemplate;II)Lscala/collection/generic/SequenceViewTemplate$Transformed;;
const #142 = Asciz	scala/collection/generic/SequenceViewTemplate$$anon$5;
const #143 = class	#142;	//  scala/collection/generic/SequenceViewTemplate$$anon$5
const #144 = Asciz	(Lscala/collection/generic/SequenceViewTemplate;II)V;
const #145 = NameAndType	#77:#144;//  "<init>":(Lscala/collection/generic/SequenceViewTemplate;II)V
const #146 = Method	#143.#145;	//  scala/collection/generic/SequenceViewTemplate$$anon$5."<init>":(Lscala/collection/generic/SequenceViewTemplate;II)V
const #147 = Asciz	_from$1;
const #148 = Asciz	_until$1;
const #149 = Asciz	newFiltered;
const #150 = Asciz	scala/collection/generic/SequenceViewTemplate$$anon$4;
const #151 = class	#150;	//  scala/collection/generic/SequenceViewTemplate$$anon$4
const #152 = Method	#151.#131;	//  scala/collection/generic/SequenceViewTemplate$$anon$4."<init>":(Lscala/collection/generic/SequenceViewTemplate;Lscala/Function1;)V
const #153 = Asciz	p$1;
const #154 = Asciz	newFlatMapped;
const #155 = Asciz	scala/collection/generic/SequenceViewTemplate$$anon$3;
const #156 = class	#155;	//  scala/collection/generic/SequenceViewTemplate$$anon$3
const #157 = Method	#156.#131;	//  scala/collection/generic/SequenceViewTemplate$$anon$3."<init>":(Lscala/collection/generic/SequenceViewTemplate;Lscala/Function1;)V
const #158 = Asciz	f$2;
const #159 = Asciz	newMapped;
const #160 = Asciz	scala/collection/generic/SequenceViewTemplate$$anon$2;
const #161 = class	#160;	//  scala/collection/generic/SequenceViewTemplate$$anon$2
const #162 = Method	#161.#131;	//  scala/collection/generic/SequenceViewTemplate$$anon$2."<init>":(Lscala/collection/generic/SequenceViewTemplate;Lscala/Function1;)V
const #163 = Asciz	f$1;
const #164 = Asciz	newAppended;
const #165 = Asciz	(Lscala/collection/generic/SequenceViewTemplate;Lscala/collection/Traversable;)Lscala/collection/generic/SequenceViewTemplate$Transformed;;
const #166 = Asciz	scala/collection/generic/SequenceViewTemplate$$anon$1;
const #167 = class	#166;	//  scala/collection/generic/SequenceViewTemplate$$anon$1
const #168 = Asciz	(Lscala/collection/generic/SequenceViewTemplate;Lscala/collection/Traversable;)V;
const #169 = NameAndType	#77:#168;//  "<init>":(Lscala/collection/generic/SequenceViewTemplate;Lscala/collection/Traversable;)V
const #170 = Method	#167.#169;	//  scala/collection/generic/SequenceViewTemplate$$anon$1."<init>":(Lscala/collection/generic/SequenceViewTemplate;Lscala/collection/Traversable;)V
const #171 = Asciz	that$1;
const #172 = Asciz	Lscala/collection/Traversable;;
const #173 = Asciz	Scala;
const #174 = Asciz	InnerClasses;
const #175 = Asciz	$anon$8;
const #176 = Asciz	$anon$4;
const #177 = Asciz	$anon$6;
const #178 = Asciz	$anon$2;
const #179 = Asciz	$anon$7;
const #180 = Asciz	$anon$3;
const #181 = Asciz	$anon$5;
const #182 = Asciz	$anon$9;
const #183 = Asciz	$anon$1;
const #184 = Asciz	$anon$10;
const #185 = Asciz	scala/collection/generic/SequenceViewTemplate$Transformed;
const #186 = class	#185;	//  scala/collection/generic/SequenceViewTemplate$Transformed
const #187 = Asciz	Transformed;
const #188 = Asciz	$anonfun$padTo$1;
const #189 = Asciz	scala/collection/generic/SequenceViewTemplate$class;
const #190 = class	#189;	//  scala/collection/generic/SequenceViewTemplate$class
const #191 = Asciz	java/lang/Object;
const #192 = class	#191;	//  java/lang/Object

{
public static void $init$(scala.collection.generic.SequenceViewTemplate);
  Code:
   Stack=0, Locals=1, Args_size=1
   0:	return
  LineNumberTable: 
   line 26: 0

  LocalVariableTable: 
   Start  Length  Slot  Name   Signature
   0      1      0    $this       Lscala/collection/generic/SequenceViewTemplate;


public static java.lang.Object zipAll(scala.collection.generic.SequenceViewTemplate, scala.collection.Sequence, java.lang.Object, java.lang.Object, scala.collection.generic.BuilderFactory);
  Code:
   Stack=5, Locals=6, Args_size=5
   0:	aload_0
   1:	aload_1
   2:	invokeinterface	#17,  1; //InterfaceMethod scala/collection/generic/SequenceTemplate.length:()I
   7:	aload_2
   8:	getstatic	#23; //Field scala/collection/generic/SequenceView$.MODULE$:Lscala/collection/generic/SequenceView$;
   11:	invokevirtual	#27; //Method scala/collection/generic/SequenceView$.builderFactory:()Lscala/collection/generic/BuilderFactory;
   14:	invokeinterface	#33,  4; //InterfaceMethod scala/collection/generic/SequenceViewTemplate.padTo:(ILjava/lang/Object;Lscala/collection/generic/BuilderFactory;)Ljava/lang/Object;
   19:	checkcast	#29; //class scala/collection/generic/SequenceViewTemplate
   22:	aload_1
   23:	aload_0
   24:	invokeinterface	#17,  1; //InterfaceMethod scala/collection/generic/SequenceTemplate.length:()I
   29:	aload_3
   30:	getstatic	#38; //Field scala/collection/Sequence$.MODULE$:Lscala/collection/Sequence$;
   33:	invokevirtual	#39; //Method scala/collection/Sequence$.builderFactory:()Lscala/collection/generic/BuilderFactory;
   36:	invokeinterface	#40,  4; //InterfaceMethod scala/collection/generic/SequenceTemplate.padTo:(ILjava/lang/Object;Lscala/collection/generic/BuilderFactory;)Ljava/lang/Object;
   41:	astore	5
   43:	aload	5
   45:	instanceof	#42; //class scala/collection/Sequence
   48:	ifeq	56
   51:	aload	5
   53:	goto	64
   56:	getstatic	#47; //Field scala/runtime/ScalaRunTime$.MODULE$:Lscala/runtime/ScalaRunTime$;
   59:	aload	5
   61:	invokevirtual	#51; //Method scala/runtime/ScalaRunTime$.boxArray:(Ljava/lang/Object;)Lscala/runtime/BoxedArray;
   64:	checkcast	#42; //class scala/collection/Sequence
   67:	aload	4
   69:	invokeinterface	#55,  3; //InterfaceMethod scala/collection/generic/SequenceViewTemplate.zip:(Lscala/collection/Sequence;Lscala/collection/generic/BuilderFactory;)Ljava/lang/Object;
   74:	areturn
  LineNumberTable: 
   line 175: 0

  LocalVariableTable: 
   Start  Length  Slot  Name   Signature
   0      75      0    $this       Lscala/collection/generic/SequenceViewTemplate;
   0      75      1    that       Lscala/collection/Sequence;
   0      75      2    thisElem       Ljava/lang/Object;
   0      75      3    thatElem       Ljava/lang/Object;
   0      75      4    bf       Lscala/collection/generic/BuilderFactory;


public static java.lang.Object zipWithIndex(scala.collection.generic.SequenceViewTemplate, scala.collection.generic.BuilderFactory);
  Code:
   Stack=4, Locals=2, Args_size=2
   0:	aload_0
   1:	getstatic	#38; //Field scala/collection/Sequence$.MODULE$:Lscala/collection/Sequence$;
   4:	iconst_0
   5:	aload_0
   6:	invokeinterface	#17,  1; //InterfaceMethod scala/collection/generic/SequenceTemplate.length:()I
   11:	invokevirtual	#68; //Method scala/collection/Sequence$.range:(II)Lscala/collection/Traversable;
   14:	checkcast	#42; //class scala/collection/Sequence
   17:	aload_1
   18:	invokeinterface	#55,  3; //InterfaceMethod scala/collection/generic/SequenceViewTemplate.zip:(Lscala/collection/Sequence;Lscala/collection/generic/BuilderFactory;)Ljava/lang/Object;
   23:	areturn
  LineNumberTable: 
   line 172: 0

  LocalVariableTable: 
   Start  Length  Slot  Name   Signature
   0      24      0    $this       Lscala/collection/generic/SequenceViewTemplate;
   0      24      1    bf       Lscala/collection/generic/BuilderFactory;


public static java.lang.Object zip(scala.collection.generic.SequenceViewTemplate, scala.collection.Sequence, scala.collection.generic.BuilderFactory);
  Code:
   Stack=2, Locals=3, Args_size=3
   0:	aload_0
   1:	aload_1
   2:	invokeinterface	#73,  2; //InterfaceMethod scala/collection/generic/SequenceViewTemplate.newZipped:(Lscala/collection/Sequence;)Lscala/collection/generic/SequenceViewTemplate$Transformed;
   7:	areturn
  LineNumberTable: 
   line 165: 0

  LocalVariableTable: 
   Start  Length  Slot  Name   Signature
   0      8      0    $this       Lscala/collection/generic/SequenceViewTemplate;
   0      8      1    that       Lscala/collection/Sequence;
   0      8      2    bf       Lscala/collection/generic/BuilderFactory;


public static java.lang.Object padTo(scala.collection.generic.SequenceViewTemplate, int, java.lang.Object, scala.collection.generic.BuilderFactory);
  Code:
   Stack=8, Locals=4, Args_size=4
   0:	aload_0
   1:	aload_0
   2:	invokeinterface	#17,  1; //InterfaceMethod scala/collection/generic/SequenceTemplate.length:()I
   7:	getstatic	#38; //Field scala/collection/Sequence$.MODULE$:Lscala/collection/Sequence$;
   10:	iload_1
   11:	aload_0
   12:	invokeinterface	#17,  1; //InterfaceMethod scala/collection/generic/SequenceTemplate.length:()I
   17:	isub
   18:	new	#76; //class scala/collection/generic/SequenceViewTemplate$$anonfun$padTo$1
   21:	dup
   22:	aload_0
   23:	aload_2
   24:	invokespecial	#80; //Method scala/collection/generic/SequenceViewTemplate$$anonfun$padTo$1."<init>":(Lscala/collection/generic/SequenceViewTemplate;Ljava/lang/Object;)V
   27:	invokevirtual	#84; //Method scala/collection/Sequence$.fill:(ILscala/Function0;)Lscala/collection/Traversable;
   30:	checkcast	#42; //class scala/collection/Sequence
   33:	iconst_0
   34:	aload_3
   35:	invokeinterface	#88,  5; //InterfaceMethod scala/collection/generic/SequenceViewTemplate.patch:(ILscala/collection/Sequence;ILscala/collection/generic/BuilderFactory;)Ljava/lang/Object;
   40:	areturn
  LineNumberTable: 
   line 162: 0

  LocalVariableTable: 
   Start  Length  Slot  Name   Signature
   0      41      0    $this       Lscala/collection/generic/SequenceViewTemplate;
   0      41      1    len       I
   0      41      2    elem$1       Ljava/lang/Object;
   0      41      3    bf       Lscala/collection/generic/BuilderFactory;


public static java.lang.Object patch(scala.collection.generic.SequenceViewTemplate, int, scala.collection.Sequence, int, scala.collection.generic.BuilderFactory);
  Code:
   Stack=4, Locals=5, Args_size=5
   0:	aload_0
   1:	iload_1
   2:	aload_2
   3:	iload_3
   4:	invokeinterface	#96,  4; //InterfaceMethod scala/collection/generic/SequenceViewTemplate.newPatched:(ILscala/collection/Sequence;I)Lscala/collection/generic/SequenceViewTemplate$Transformed;
   9:	areturn
  LineNumberTable: 
   line 155: 0

  LocalVariableTable: 
   Start  Length  Slot  Name   Signature
   0      10      0    $this       Lscala/collection/generic/SequenceViewTemplate;
   0      10      1    from       I
   0      10      2    patch       Lscala/collection/Sequence;
   0      10      3    replaced       I
   0      10      4    bf       Lscala/collection/generic/BuilderFactory;


public static scala.collection.generic.SequenceView reverse(scala.collection.generic.SequenceViewTemplate);
  Code:
   Stack=1, Locals=1, Args_size=1
   0:	aload_0
   1:	invokeinterface	#104,  1; //InterfaceMethod scala/collection/generic/SequenceViewTemplate.newReversed:()Lscala/collection/generic/SequenceViewTemplate$Transformed;
   6:	areturn
  LineNumberTable: 
   line 152: 0

  LocalVariableTable: 
   Start  Length  Slot  Name   Signature
   0      7      0    $this       Lscala/collection/generic/SequenceViewTemplate;


public static scala.collection.generic.SequenceViewTemplate$Transformed newZipped(scala.collection.generic.SequenceViewTemplate, scala.collection.Sequence);
  Code:
   Stack=4, Locals=2, Args_size=2
   0:	new	#107; //class scala/collection/generic/SequenceViewTemplate$$anon$10
   3:	dup
   4:	aload_0
   5:	aload_1
   6:	invokespecial	#110; //Method scala/collection/generic/SequenceViewTemplate$$anon$10."<init>":(Lscala/collection/generic/SequenceViewTemplate;Lscala/collection/Sequence;)V
   9:	areturn
  LineNumberTable: 
   line 148: 0

  LocalVariableTable: 
   Start  Length  Slot  Name   Signature
   0      10      0    $this       Lscala/collection/generic/SequenceViewTemplate;
   0      10      1    that$2       Lscala/collection/Sequence;


public static scala.collection.generic.SequenceViewTemplate$Transformed newPatched(scala.collection.generic.SequenceViewTemplate, int, scala.collection.Sequence, int);
  Code:
   Stack=6, Locals=4, Args_size=4
   0:	new	#114; //class scala/collection/generic/SequenceViewTemplate$$anon$9
   3:	dup
   4:	aload_0
   5:	iload_1
   6:	aload_2
   7:	iload_3
   8:	invokespecial	#117; //Method scala/collection/generic/SequenceViewTemplate$$anon$9."<init>":(Lscala/collection/generic/SequenceViewTemplate;ILscala/collection/Sequence;I)V
   11:	areturn
  LineNumberTable: 
   line 145: 0

  LocalVariableTable: 
   Start  Length  Slot  Name   Signature
   0      12      0    $this       Lscala/collection/generic/SequenceViewTemplate;
   0      12      1    _from$2       I
   0      12      2    _patch$1       Lscala/collection/Sequence;
   0      12      3    _replaced$1       I


public static scala.collection.generic.SequenceViewTemplate$Transformed newReversed(scala.collection.generic.SequenceViewTemplate);
  Code:
   Stack=3, Locals=1, Args_size=1
   0:	new	#123; //class scala/collection/generic/SequenceViewTemplate$$anon$8
   3:	dup
   4:	aload_0
   5:	invokespecial	#125; //Method scala/collection/generic/SequenceViewTemplate$$anon$8."<init>":(Lscala/collection/generic/SequenceViewTemplate;)V
   8:	areturn
  LineNumberTable: 
   line 144: 0

  LocalVariableTable: 
   Start  Length  Slot  Name   Signature
   0      9      0    $this       Lscala/collection/generic/SequenceViewTemplate;


public static scala.collection.generic.SequenceViewTemplate$Transformed newTakenWhile(scala.collection.generic.SequenceViewTemplate, scala.Function1);
  Code:
   Stack=4, Locals=2, Args_size=2
   0:	new	#129; //class scala/collection/generic/SequenceViewTemplate$$anon$7
   3:	dup
   4:	aload_0
   5:	aload_1
   6:	invokespecial	#132; //Method scala/collection/generic/SequenceViewTemplate$$anon$7."<init>":(Lscala/collection/generic/SequenceViewTemplate;Lscala/Function1;)V
   9:	areturn
  LineNumberTable: 
   line 143: 0

  LocalVariableTable: 
   Start  Length  Slot  Name   Signature
   0      10      0    $this       Lscala/collection/generic/SequenceViewTemplate;
   0      10      1    p$3       Lscala/Function1;


public static scala.collection.generic.SequenceViewTemplate$Transformed newDroppedWhile(scala.collection.generic.SequenceViewTemplate, scala.Function1);
  Code:
   Stack=4, Locals=2, Args_size=2
   0:	new	#137; //class scala/collection/generic/SequenceViewTemplate$$anon$6
   3:	dup
   4:	aload_0
   5:	aload_1
   6:	invokespecial	#138; //Method scala/collection/generic/SequenceViewTemplate$$anon$6."<init>":(Lscala/collection/generic/SequenceViewTemplate;Lscala/Function1;)V
   9:	areturn
  LineNumberTable: 
   line 142: 0

  LocalVariableTable: 
   Start  Length  Slot  Name   Signature
   0      10      0    $this       Lscala/collection/generic/SequenceViewTemplate;
   0      10      1    p$2       Lscala/Function1;


public static scala.collection.generic.SequenceViewTemplate$Transformed newSliced(scala.collection.generic.SequenceViewTemplate, int, int);
  Code:
   Stack=5, Locals=3, Args_size=3
   0:	new	#143; //class scala/collection/generic/SequenceViewTemplate$$anon$5
   3:	dup
   4:	aload_0
   5:	iload_1
   6:	iload_2
   7:	invokespecial	#146; //Method scala/collection/generic/SequenceViewTemplate$$anon$5."<init>":(Lscala/collection/generic/SequenceViewTemplate;II)V
   10:	areturn
  LineNumberTable: 
   line 141: 0

  LocalVariableTable: 
   Start  Length  Slot  Name   Signature
   0      11      0    $this       Lscala/collection/generic/SequenceViewTemplate;
   0      11      1    _from$1       I
   0      11      2    _until$1       I


public static scala.collection.generic.SequenceViewTemplate$Transformed newFiltered(scala.collection.generic.SequenceViewTemplate, scala.Function1);
  Code:
   Stack=4, Locals=2, Args_size=2
   0:	new	#151; //class scala/collection/generic/SequenceViewTemplate$$anon$4
   3:	dup
   4:	aload_0
   5:	aload_1
   6:	invokespecial	#152; //Method scala/collection/generic/SequenceViewTemplate$$anon$4."<init>":(Lscala/collection/generic/SequenceViewTemplate;Lscala/Function1;)V
   9:	areturn
  LineNumberTable: 
   line 140: 0

  LocalVariableTable: 
   Start  Length  Slot  Name   Signature
   0      10      0    $this       Lscala/collection/generic/SequenceViewTemplate;
   0      10      1    p$1       Lscala/Function1;


public static scala.collection.generic.SequenceViewTemplate$Transformed newFlatMapped(scala.collection.generic.SequenceViewTemplate, scala.Function1);
  Code:
   Stack=4, Locals=2, Args_size=2
   0:	new	#156; //class scala/collection/generic/SequenceViewTemplate$$anon$3
   3:	dup
   4:	aload_0
   5:	aload_1
   6:	invokespecial	#157; //Method scala/collection/generic/SequenceViewTemplate$$anon$3."<init>":(Lscala/collection/generic/SequenceViewTemplate;Lscala/Function1;)V
   9:	areturn
  LineNumberTable: 
   line 139: 0

  LocalVariableTable: 
   Start  Length  Slot  Name   Signature
   0      10      0    $this       Lscala/collection/generic/SequenceViewTemplate;
   0      10      1    f$2       Lscala/Function1;


public static scala.collection.generic.SequenceViewTemplate$Transformed newMapped(scala.collection.generic.SequenceViewTemplate, scala.Function1);
  Code:
   Stack=4, Locals=2, Args_size=2
   0:	new	#161; //class scala/collection/generic/SequenceViewTemplate$$anon$2
   3:	dup
   4:	aload_0
   5:	aload_1
   6:	invokespecial	#162; //Method scala/collection/generic/SequenceViewTemplate$$anon$2."<init>":(Lscala/collection/generic/SequenceViewTemplate;Lscala/Function1;)V
   9:	areturn
  LineNumberTable: 
   line 138: 0

  LocalVariableTable: 
   Start  Length  Slot  Name   Signature
   0      10      0    $this       Lscala/collection/generic/SequenceViewTemplate;
   0      10      1    f$1       Lscala/Function1;


public static scala.collection.generic.SequenceViewTemplate$Transformed newAppended(scala.collection.generic.SequenceViewTemplate, scala.collection.Traversable);
  Code:
   Stack=4, Locals=2, Args_size=2
   0:	new	#167; //class scala/collection/generic/SequenceViewTemplate$$anon$1
   3:	dup
   4:	aload_0
   5:	aload_1
   6:	invokespecial	#170; //Method scala/collection/generic/SequenceViewTemplate$$anon$1."<init>":(Lscala/collection/generic/SequenceViewTemplate;Lscala/collection/Traversable;)V
   9:	areturn
  LineNumberTable: 
   line 137: 0

  LocalVariableTable: 
   Start  Length  Slot  Name   Signature
   0      10      0    $this       Lscala/collection/generic/SequenceViewTemplate;
   0      10      1    that$1       Lscala/collection/Traversable;


}

