Compiled from "SequenceTemplate.scala"
public final class scala.collection.generic.SequenceTemplate$$anonfun$intersect$1 extends java.lang.Object implements scala.Function1,scala.ScalaObject,java.io.Serializable
  SourceFile: "SequenceTemplate.scala"
  Scala: length = 0x
   
  InnerClass: 
   public final #95= #12 of #94; //$anonfun$intersect$1=class scala/collection/generic/SequenceTemplate$$anonfun$intersect$1 of class scala/collection/generic/SequenceTemplate
  minor version: 0
  major version: 49
  Constant pool:
const #1 = Asciz	SourceFile;
const #2 = Asciz	SequenceTemplate.scala;
const #3 = Asciz	b$4;
const #4 = Asciz	Lscala/collection/generic/Builder;;
const #5 = Asciz	occ$2;
const #6 = Asciz	Lscala/collection/mutable/Map;;
const #7 = Asciz	<init>;
const #8 = Asciz	(Lscala/collection/generic/SequenceTemplate;Lscala/collection/mutable/Map;Lscala/collection/generic/Builder;)V;
const #9 = Asciz	Code;
const #10 = Asciz	LineNumberTable;
const #11 = Asciz	scala/collection/generic/SequenceTemplate$$anonfun$intersect$1;
const #12 = class	#11;	//  scala/collection/generic/SequenceTemplate$$anonfun$intersect$1
const #13 = NameAndType	#5:#6;//  occ$2:Lscala/collection/mutable/Map;
const #14 = Field	#12.#13;	//  scala/collection/generic/SequenceTemplate$$anonfun$intersect$1.occ$2:Lscala/collection/mutable/Map;
const #15 = NameAndType	#3:#4;//  b$4:Lscala/collection/generic/Builder;
const #16 = Field	#12.#15;	//  scala/collection/generic/SequenceTemplate$$anonfun$intersect$1.b$4:Lscala/collection/generic/Builder;
const #17 = Asciz	java/lang/Object;
const #18 = class	#17;	//  java/lang/Object
const #19 = Asciz	()V;
const #20 = NameAndType	#7:#19;//  "<init>":()V
const #21 = Method	#18.#20;	//  java/lang/Object."<init>":()V
const #22 = Asciz	scala/Function1$class;
const #23 = class	#22;	//  scala/Function1$class
const #24 = Asciz	$init$;
const #25 = Asciz	(Lscala/Function1;)V;
const #26 = NameAndType	#24:#25;//  $init$:(Lscala/Function1;)V
const #27 = Method	#23.#26;	//  scala/Function1$class.$init$:(Lscala/Function1;)V
const #28 = Asciz	this;
const #29 = Asciz	Lscala/collection/generic/SequenceTemplate$$anonfun$intersect$1;;
const #30 = Asciz	$outer;
const #31 = Asciz	Lscala/collection/generic/SequenceTemplate;;
const #32 = Asciz	LocalVariableTable;
const #33 = Asciz	(Lscala/collection/generic/SequenceTemplate<TA;TThis;>;)V;
const #34 = Asciz	Signature;
const #35 = Asciz	apply;
const #36 = Asciz	(Ljava/lang/Object;)Ljava/lang/Object;;
const #37 = Asciz	(Ljava/lang/Object;)V;
const #38 = NameAndType	#35:#37;//  apply:(Ljava/lang/Object;)V
const #39 = Method	#12.#38;	//  scala/collection/generic/SequenceTemplate$$anonfun$intersect$1.apply:(Ljava/lang/Object;)V
const #40 = Asciz	scala/runtime/BoxedUnit;
const #41 = class	#40;	//  scala/runtime/BoxedUnit
const #42 = Asciz	UNIT;
const #43 = Asciz	Lscala/runtime/BoxedUnit;;
const #44 = NameAndType	#42:#43;//  UNIT:Lscala/runtime/BoxedUnit;
const #45 = Field	#41.#44;	//  scala/runtime/BoxedUnit.UNIT:Lscala/runtime/BoxedUnit;
const #46 = Asciz	v1;
const #47 = Asciz	Ljava/lang/Object;;
const #48 = Asciz	scala/collection/generic/MapTemplate;
const #49 = class	#48;	//  scala/collection/generic/MapTemplate
const #50 = NameAndType	#35:#36;//  apply:(Ljava/lang/Object;)Ljava/lang/Object;
const #51 = InterfaceMethod	#49.#50;	//  scala/collection/generic/MapTemplate.apply:(Ljava/lang/Object;)Ljava/lang/Object;
const #52 = Asciz	scala/runtime/BoxesRunTime;
const #53 = class	#52;	//  scala/runtime/BoxesRunTime
const #54 = Asciz	unboxToInt;
const #55 = Asciz	(Ljava/lang/Object;)I;
const #56 = NameAndType	#54:#55;//  unboxToInt:(Ljava/lang/Object;)I
const #57 = Method	#53.#56;	//  scala/runtime/BoxesRunTime.unboxToInt:(Ljava/lang/Object;)I
const #58 = Asciz	scala/collection/generic/Builder;
const #59 = class	#58;	//  scala/collection/generic/Builder
const #60 = Asciz	$plus$eq;
const #61 = Asciz	(Ljava/lang/Object;)Lscala/collection/generic/Builder;;
const #62 = NameAndType	#60:#61;//  $plus$eq:(Ljava/lang/Object;)Lscala/collection/generic/Builder;
const #63 = InterfaceMethod	#59.#62;	//  scala/collection/generic/Builder.$plus$eq:(Ljava/lang/Object;)Lscala/collection/generic/Builder;
const #64 = Asciz	boxToInteger;
const #65 = Asciz	(I)Ljava/lang/Integer;;
const #66 = NameAndType	#64:#65;//  boxToInteger:(I)Ljava/lang/Integer;
const #67 = Method	#53.#66;	//  scala/runtime/BoxesRunTime.boxToInteger:(I)Ljava/lang/Integer;
const #68 = Asciz	scala/collection/generic/MutableMapTemplate;
const #69 = class	#68;	//  scala/collection/generic/MutableMapTemplate
const #70 = Asciz	update;
const #71 = Asciz	(Ljava/lang/Object;Ljava/lang/Object;)V;
const #72 = NameAndType	#70:#71;//  update:(Ljava/lang/Object;Ljava/lang/Object;)V
const #73 = InterfaceMethod	#69.#72;	//  scala/collection/generic/MutableMapTemplate.update:(Ljava/lang/Object;Ljava/lang/Object;)V
const #74 = Asciz	x;
const #75 = Asciz	(TA;)V;
const #76 = Asciz	andThen;
const #77 = Asciz	(Lscala/Function1;)Lscala/Function1;;
const #78 = Asciz	(Lscala/Function1;Lscala/Function1;)Lscala/Function1;;
const #79 = NameAndType	#76:#78;//  andThen:(Lscala/Function1;Lscala/Function1;)Lscala/Function1;
const #80 = Method	#23.#79;	//  scala/Function1$class.andThen:(Lscala/Function1;Lscala/Function1;)Lscala/Function1;
const #81 = Asciz	g;
const #82 = Asciz	Lscala/Function1;;
const #83 = Asciz	compose;
const #84 = NameAndType	#83:#78;//  compose:(Lscala/Function1;Lscala/Function1;)Lscala/Function1;
const #85 = Method	#23.#84;	//  scala/Function1$class.compose:(Lscala/Function1;Lscala/Function1;)Lscala/Function1;
const #86 = Asciz	toString;
const #87 = Asciz	()Ljava/lang/String;;
const #88 = Asciz	(Lscala/Function1;)Ljava/lang/String;;
const #89 = NameAndType	#86:#88;//  toString:(Lscala/Function1;)Ljava/lang/String;
const #90 = Method	#23.#89;	//  scala/Function1$class.toString:(Lscala/Function1;)Ljava/lang/String;
const #91 = Asciz	Scala;
const #92 = Asciz	InnerClasses;
const #93 = Asciz	scala/collection/generic/SequenceTemplate;
const #94 = class	#93;	//  scala/collection/generic/SequenceTemplate
const #95 = Asciz	$anonfun$intersect$1;
const #96 = Asciz	scala/Function1;
const #97 = class	#96;	//  scala/Function1
const #98 = Asciz	scala/ScalaObject;
const #99 = class	#98;	//  scala/ScalaObject
const #100 = Asciz	java/io/Serializable;
const #101 = class	#100;	//  java/io/Serializable

{
public scala.collection.generic.SequenceTemplate$$anonfun$intersect$1(scala.collection.generic.SequenceTemplate, scala.collection.mutable.Map, scala.collection.generic.Builder);
  Code:
   Stack=2, Locals=4, Args_size=4
   0:	aload_0
   1:	aload_2
   2:	putfield	#14; //Field occ$2:Lscala/collection/mutable/Map;
   5:	aload_0
   6:	aload_3
   7:	putfield	#16; //Field b$4:Lscala/collection/generic/Builder;
   10:	aload_0
   11:	invokespecial	#21; //Method java/lang/Object."<init>":()V
   14:	aload_0
   15:	invokestatic	#27; //Method scala/Function1$class.$init$:(Lscala/Function1;)V
   18:	return
  LineNumberTable: 
   line 423: 0

  LocalVariableTable: 
   Start  Length  Slot  Name   Signature
   0      19      0    this       Lscala/collection/generic/SequenceTemplate$$anonfun$intersect$1;
   0      19      1    $outer       Lscala/collection/generic/SequenceTemplate;

  Signature: length = 0x2
   00 21 

public final java.lang.Object apply(java.lang.Object);
  Code:
   Stack=2, Locals=2, Args_size=2
   0:	aload_0
   1:	aload_1
   2:	invokevirtual	#39; //Method apply:(Ljava/lang/Object;)V
   5:	getstatic	#45; //Field scala/runtime/BoxedUnit.UNIT:Lscala/runtime/BoxedUnit;
   8:	areturn
  LineNumberTable: 
   line 423: 0

  LocalVariableTable: 
   Start  Length  Slot  Name   Signature
   0      9      0    this       Lscala/collection/generic/SequenceTemplate$$anonfun$intersect$1;
   0      9      1    v1       Ljava/lang/Object;


public final void apply(java.lang.Object);
  Code:
   Stack=4, Locals=2, Args_size=2
   0:	aload_0
   1:	getfield	#14; //Field occ$2:Lscala/collection/mutable/Map;
   4:	aload_1
   5:	invokeinterface	#51,  2; //InterfaceMethod scala/collection/generic/MapTemplate.apply:(Ljava/lang/Object;)Ljava/lang/Object;
   10:	invokestatic	#57; //Method scala/runtime/BoxesRunTime.unboxToInt:(Ljava/lang/Object;)I
   13:	iconst_0
   14:	if_icmple	56
   17:	aload_0
   18:	getfield	#16; //Field b$4:Lscala/collection/generic/Builder;
   21:	aload_1
   22:	invokeinterface	#63,  2; //InterfaceMethod scala/collection/generic/Builder.$plus$eq:(Ljava/lang/Object;)Lscala/collection/generic/Builder;
   27:	pop
   28:	aload_0
   29:	getfield	#14; //Field occ$2:Lscala/collection/mutable/Map;
   32:	aload_1
   33:	aload_0
   34:	getfield	#14; //Field occ$2:Lscala/collection/mutable/Map;
   37:	aload_1
   38:	invokeinterface	#51,  2; //InterfaceMethod scala/collection/generic/MapTemplate.apply:(Ljava/lang/Object;)Ljava/lang/Object;
   43:	invokestatic	#57; //Method scala/runtime/BoxesRunTime.unboxToInt:(Ljava/lang/Object;)I
   46:	iconst_1
   47:	isub
   48:	invokestatic	#67; //Method scala/runtime/BoxesRunTime.boxToInteger:(I)Ljava/lang/Integer;
   51:	invokeinterface	#73,  3; //InterfaceMethod scala/collection/generic/MutableMapTemplate.update:(Ljava/lang/Object;Ljava/lang/Object;)V
   56:	return
  LineNumberTable: 
   line 424: 0
   line 425: 17
   line 426: 28
   line 424: 56

  LocalVariableTable: 
   Start  Length  Slot  Name   Signature
   0      57      0    this       Lscala/collection/generic/SequenceTemplate$$anonfun$intersect$1;
   0      57      1    x       Ljava/lang/Object;

  Signature: length = 0x2
   00 4B 

public scala.Function1 andThen(scala.Function1);
  Code:
   Stack=2, Locals=2, Args_size=2
   0:	aload_0
   1:	aload_1
   2:	invokestatic	#80; //Method scala/Function1$class.andThen:(Lscala/Function1;Lscala/Function1;)Lscala/Function1;
   5:	areturn
  LineNumberTable: 
   line 423: 0

  LocalVariableTable: 
   Start  Length  Slot  Name   Signature
   0      6      0    this       Lscala/collection/generic/SequenceTemplate$$anonfun$intersect$1;
   0      6      1    g       Lscala/Function1;


public scala.Function1 compose(scala.Function1);
  Code:
   Stack=2, Locals=2, Args_size=2
   0:	aload_0
   1:	aload_1
   2:	invokestatic	#85; //Method scala/Function1$class.compose:(Lscala/Function1;Lscala/Function1;)Lscala/Function1;
   5:	areturn
  LineNumberTable: 
   line 423: 0

  LocalVariableTable: 
   Start  Length  Slot  Name   Signature
   0      6      0    this       Lscala/collection/generic/SequenceTemplate$$anonfun$intersect$1;
   0      6      1    g       Lscala/Function1;


public java.lang.String toString();
  Code:
   Stack=1, Locals=1, Args_size=1
   0:	aload_0
   1:	invokestatic	#90; //Method scala/Function1$class.toString:(Lscala/Function1;)Ljava/lang/String;
   4:	areturn
  LineNumberTable: 
   line 423: 0


}

