Compiled from "SequenceFactory.scala"
public abstract class scala.collection.generic.SequenceFactory extends scala.collection.generic.TraversableFactory implements scala.ScalaObject
  SourceFile: "SequenceFactory.scala"
  Signature: length = 0x2
   00 19 
  ScalaSig: length = 0x181
   05 00 3E 06 05 01 02 FFFFFF81 00 09 02 0F 53 65 71 75
   65 6E 63 65 46 61 63 74 6F 72 79 0A 02 03 04 01
   07 67 65 6E 65 72 69 63 0A 02 05 06 01 0A 63 6F
   6C 6C 65 63 74 69 6F 6E 0A 01 07 01 05 73 63 61
   6C 61 03 00 15 02 0A 11 13 03 00 0B 2A 10 03 0C
   0D 0F 0D 01 02 09 02 0E 02 02 12 54 72 61 76 65
   72 73 61 62 6C 65 46 61 63 74 6F 72 79 10 02 10
   11 0C 00 04 05 12 00 FFFFFFC2 00 13 02 02 43 43 15 02
   14 21 11 02 15 19 10 02 16 17 0D 01 06 09 02 18
   06 02 07 4E 6F 74 68 69 6E 67 12 03 1A 1C 27 06
   08 1B 02 FFFFFF84 FFFFFF80 FFFFFF80 FFFFFF80 00 19 02 0C 3C 72 65 66 69
   6E 65 6D 65 6E 74 3E 10 03 1D 1E 20 0D 01 04 09
   02 1F 04 02 08 53 65 71 75 65 6E 63 65 10 02 10
   21 04 08 22 11 FFFFFF84 FFFFFF80 FFFFFF80 FFFFFFC2 00 23 02 01 58 11 02
   15 24 10 02 16 25 09 02 26 06 02 03 41 6E 79 10
   04 0C 28 20 0F 09 02 29 02 02 10 54 72 61 76 65
   72 73 61 62 6C 65 43 6C 61 73 73 10 02 16 2B 09
   02 2C 06 02 0B 53 63 61 6C 61 4F 62 6A 65 63 74
   08 05 2E 00 FFFFFF84 00 2F 01 06 3C 69 6E 69 74 3E 14
   01 30 10 03 0C 00 0F 08 05 32 00 FFFFFF84 00 33 01 0A
   75 6E 61 70 70 6C 79 53 65 71 15 02 34 3A 14 02
   35 3C 10 03 16 36 38 09 02 37 06 02 04 53 6F 6D
   65 10 03 10 11 39 10 02 10 3A 04 08 3B 31 FFFFFF84 FFFFFF80
   FFFFFF80 FFFFFFC2 00 23 02 01 41 08 05 3D 31 FFFFFFC0 00 38 01 01
   78 
  minor version: 0
  major version: 49
  Constant pool:
const #1 = Asciz	SourceFile;
const #2 = Asciz	SequenceFactory.scala;
const #3 = Asciz	<init>;
const #4 = Asciz	()V;
const #5 = Asciz	Code;
const #6 = Asciz	LineNumberTable;
const #7 = Asciz	scala/collection/generic/TraversableFactory;
const #8 = class	#7;	//  scala/collection/generic/TraversableFactory
const #9 = NameAndType	#3:#4;//  "<init>":()V
const #10 = Method	#8.#9;	//  scala/collection/generic/TraversableFactory."<init>":()V
const #11 = Asciz	Signature;
const #12 = Asciz	unapplySeq;
const #13 = Asciz	(Lscala/collection/Sequence;)Lscala/Some;;
const #14 = Asciz	scala/Some;
const #15 = class	#14;	//  scala/Some
const #16 = Asciz	(Ljava/lang/Object;)V;
const #17 = NameAndType	#3:#16;//  "<init>":(Ljava/lang/Object;)V
const #18 = Method	#15.#17;	//  scala/Some."<init>":(Ljava/lang/Object;)V
const #19 = Asciz	this;
const #20 = Asciz	Lscala/collection/generic/SequenceFactory;;
const #21 = Asciz	x;
const #22 = Asciz	Lscala/collection/Sequence;;
const #23 = Asciz	LocalVariableTable;
const #24 = Asciz	<A:Ljava/lang/Object;>(TCC;)Lscala/Some<TCC;>;;
const #25 = Asciz	<CC:Lscala/collection/Sequence<Ljava/lang/Object;>;>Lscala/collection/generic/TraversableFactory<TCC;>;Lscala/ScalaObject;;
const #26 = Asciz	ScalaSig;
const #27 = Asciz	scala/collection/generic/SequenceFactory;
const #28 = class	#27;	//  scala/collection/generic/SequenceFactory
const #29 = Asciz	scala/ScalaObject;
const #30 = class	#29;	//  scala/ScalaObject

{
public scala.collection.generic.SequenceFactory();
  Code:
   Stack=1, Locals=1, Args_size=1
   0:	aload_0
   1:	invokespecial	#10; //Method scala/collection/generic/TraversableFactory."<init>":()V
   4:	return
  LineNumberTable: 
   line 18: 0

  Signature: length = 0x2
   00 04 

public scala.Some unapplySeq(scala.collection.Sequence);
  Code:
   Stack=3, Locals=2, Args_size=2
   0:	new	#15; //class scala/Some
   3:	dup
   4:	aload_1
   5:	invokespecial	#18; //Method scala/Some."<init>":(Ljava/lang/Object;)V
   8:	areturn
  LineNumberTable: 
   line 25: 0

  LocalVariableTable: 
   Start  Length  Slot  Name   Signature
   0      9      0    this       Lscala/collection/generic/SequenceFactory;
   0      9      1    x       Lscala/collection/Sequence;

  Signature: length = 0x2
   00 18 

}

