Compiled from "SequenceViewTemplate.scala"
public abstract class scala.collection.generic.SequenceViewTemplate$Filtered$class extends java.lang.Object
  SourceFile: "SequenceViewTemplate.scala"
  Scala: length = 0x
   
  InnerClass: 
   public abstract #107= #13 of #106; //Filtered=class scala/collection/generic/SequenceViewTemplate$Filtered of class scala/collection/generic/SequenceViewTemplate
   public final #108= #58 of #13; //$anonfun$index$2=class scala/collection/generic/SequenceViewTemplate$Filtered$$anonfun$index$2 of class scala/collection/generic/SequenceViewTemplate$Filtered
  minor version: 0
  major version: 49
  Constant pool:
const #1 = Asciz	SourceFile;
const #2 = Asciz	SequenceViewTemplate.scala;
const #3 = Asciz	$init$;
const #4 = Asciz	(Lscala/collection/generic/SequenceViewTemplate$Filtered;)V;
const #5 = Asciz	Code;
const #6 = Asciz	LineNumberTable;
const #7 = Asciz	$this;
const #8 = Asciz	Lscala/collection/generic/SequenceViewTemplate$Filtered;;
const #9 = Asciz	LocalVariableTable;
const #10 = Asciz	apply;
const #11 = Asciz	(Lscala/collection/generic/SequenceViewTemplate$Filtered;I)Ljava/lang/Object;;
const #12 = Asciz	scala/collection/generic/SequenceViewTemplate$Filtered;
const #13 = class	#12;	//  scala/collection/generic/SequenceViewTemplate$Filtered
const #14 = Asciz	scala$collection$generic$SequenceViewTemplate$Filtered$$$outer;
const #15 = Asciz	()Lscala/collection/generic/SequenceViewTemplate;;
const #16 = NameAndType	#14:#15;//  scala$collection$generic$SequenceViewTemplate$Filtered$$$outer:()Lscala/collection/generic/SequenceViewTemplate;
const #17 = InterfaceMethod	#13.#16;	//  scala/collection/generic/SequenceViewTemplate$Filtered.scala$collection$generic$SequenceViewTemplate$Filtered$$$outer:()Lscala/collection/generic/SequenceViewTemplate;
const #18 = Asciz	index;
const #19 = Asciz	()[I;
const #20 = NameAndType	#18:#19;//  index:()[I
const #21 = InterfaceMethod	#13.#20;	//  scala/collection/generic/SequenceViewTemplate$Filtered.index:()[I
const #22 = Asciz	scala/collection/generic/SequenceTemplate;
const #23 = class	#22;	//  scala/collection/generic/SequenceTemplate
const #24 = Asciz	(I)Ljava/lang/Object;;
const #25 = NameAndType	#10:#24;//  apply:(I)Ljava/lang/Object;
const #26 = InterfaceMethod	#23.#25;	//  scala/collection/generic/SequenceTemplate.apply:(I)Ljava/lang/Object;
const #27 = Asciz	idx;
const #28 = Asciz	I;
const #29 = Asciz	length;
const #30 = Asciz	(Lscala/collection/generic/SequenceViewTemplate$Filtered;)I;
const #31 = Asciz	(Lscala/collection/generic/SequenceViewTemplate$Filtered;)[I;
const #32 = Asciz	scala/runtime/IntRef;
const #33 = class	#32;	//  scala/runtime/IntRef
const #34 = Asciz	<init>;
const #35 = Asciz	(I)V;
const #36 = NameAndType	#34:#35;//  "<init>":(I)V
const #37 = Method	#33.#36;	//  scala/runtime/IntRef."<init>":(I)V
const #38 = Asciz	()I;
const #39 = NameAndType	#29:#38;//  length:()I
const #40 = InterfaceMethod	#23.#39;	//  scala/collection/generic/SequenceTemplate.length:()I
const #41 = Asciz	scala/Predef$;
const #42 = class	#41;	//  scala/Predef$
const #43 = Asciz	MODULE$;
const #44 = Asciz	Lscala/Predef$;;
const #45 = NameAndType	#43:#44;//  MODULE$:Lscala/Predef$;
const #46 = Field	#42.#45;	//  scala/Predef$.MODULE$:Lscala/Predef$;
const #47 = Asciz	intWrapper;
const #48 = Asciz	(I)Lscala/runtime/RichInt;;
const #49 = NameAndType	#47:#48;//  intWrapper:(I)Lscala/runtime/RichInt;
const #50 = Method	#42.#49;	//  scala/Predef$.intWrapper:(I)Lscala/runtime/RichInt;
const #51 = Asciz	scala/runtime/RichInt;
const #52 = class	#51;	//  scala/runtime/RichInt
const #53 = Asciz	until;
const #54 = Asciz	(I)Lscala/Range;;
const #55 = NameAndType	#53:#54;//  until:(I)Lscala/Range;
const #56 = Method	#52.#55;	//  scala/runtime/RichInt.until:(I)Lscala/Range;
const #57 = Asciz	scala/collection/generic/SequenceViewTemplate$Filtered$$anonfun$index$2;
const #58 = class	#57;	//  scala/collection/generic/SequenceViewTemplate$Filtered$$anonfun$index$2
const #59 = Asciz	(Lscala/collection/generic/SequenceViewTemplate$Filtered;Lscala/runtime/IntRef;[I)V;
const #60 = NameAndType	#34:#59;//  "<init>":(Lscala/collection/generic/SequenceViewTemplate$Filtered;Lscala/runtime/IntRef;[I)V
const #61 = Method	#58.#60;	//  scala/collection/generic/SequenceViewTemplate$Filtered$$anonfun$index$2."<init>":(Lscala/collection/generic/SequenceViewTemplate$Filtered;Lscala/runtime/IntRef;[I)V
const #62 = Asciz	scala/Range;
const #63 = class	#62;	//  scala/Range
const #64 = Asciz	foreach;
const #65 = Asciz	(Lscala/Function1;)V;
const #66 = NameAndType	#64:#65;//  foreach:(Lscala/Function1;)V
const #67 = Method	#63.#66;	//  scala/Range.foreach:(Lscala/Function1;)V
const #68 = Asciz	scala/runtime/ScalaRunTime$;
const #69 = class	#68;	//  scala/runtime/ScalaRunTime$
const #70 = Asciz	Lscala/runtime/ScalaRunTime$;;
const #71 = NameAndType	#43:#70;//  MODULE$:Lscala/runtime/ScalaRunTime$;
const #72 = Field	#69.#71;	//  scala/runtime/ScalaRunTime$.MODULE$:Lscala/runtime/ScalaRunTime$;
const #73 = Asciz	boxArray;
const #74 = Asciz	(Ljava/lang/Object;)Lscala/runtime/BoxedArray;;
const #75 = NameAndType	#73:#74;//  boxArray:(Ljava/lang/Object;)Lscala/runtime/BoxedArray;
const #76 = Method	#69.#75;	//  scala/runtime/ScalaRunTime$.boxArray:(Ljava/lang/Object;)Lscala/runtime/BoxedArray;
const #77 = Asciz	elem;
const #78 = NameAndType	#77:#28;//  elem:I
const #79 = Field	#33.#78;	//  scala/runtime/IntRef.elem:I
const #80 = Asciz	scala/collection/generic/VectorTemplate;
const #81 = class	#80;	//  scala/collection/generic/VectorTemplate
const #82 = Asciz	take;
const #83 = Asciz	(I)Lscala/collection/generic/VectorTemplate;;
const #84 = NameAndType	#82:#83;//  take:(I)Lscala/collection/generic/VectorTemplate;
const #85 = InterfaceMethod	#81.#84;	//  scala/collection/generic/VectorTemplate.take:(I)Lscala/collection/generic/VectorTemplate;
const #86 = Asciz	scala/runtime/BoxedArray;
const #87 = class	#86;	//  scala/runtime/BoxedArray
const #88 = Asciz	java/lang/Integer;
const #89 = class	#88;	//  java/lang/Integer
const #90 = Asciz	TYPE;
const #91 = Asciz	Ljava/lang/Class;;
const #92 = NameAndType	#90:#91;//  TYPE:Ljava/lang/Class;
const #93 = Field	#89.#92;	//  java/lang/Integer.TYPE:Ljava/lang/Class;
const #94 = Asciz	arrayValue;
const #95 = Asciz	(Lscala/runtime/BoxedArray;Ljava/lang/Class;)Ljava/lang/Object;;
const #96 = NameAndType	#94:#95;//  arrayValue:(Lscala/runtime/BoxedArray;Ljava/lang/Class;)Ljava/lang/Object;
const #97 = Method	#69.#96;	//  scala/runtime/ScalaRunTime$.arrayValue:(Lscala/runtime/BoxedArray;Ljava/lang/Class;)Ljava/lang/Object;
const #98 = Asciz	[I;
const #99 = class	#98;	//  "[I"
const #100 = Asciz	len$1;
const #101 = Asciz	Lscala/runtime/IntRef;;
const #102 = Asciz	arr$1;
const #103 = Asciz	Scala;
const #104 = Asciz	InnerClasses;
const #105 = Asciz	scala/collection/generic/SequenceViewTemplate;
const #106 = class	#105;	//  scala/collection/generic/SequenceViewTemplate
const #107 = Asciz	Filtered;
const #108 = Asciz	$anonfun$index$2;
const #109 = Asciz	scala/collection/generic/SequenceViewTemplate$Filtered$class;
const #110 = class	#109;	//  scala/collection/generic/SequenceViewTemplate$Filtered$class
const #111 = Asciz	java/lang/Object;
const #112 = class	#111;	//  java/lang/Object

{
public static void $init$(scala.collection.generic.SequenceViewTemplate$Filtered);
  Code:
   Stack=0, Locals=1, Args_size=1
   0:	return
  LineNumberTable: 
   line 74: 0

  LocalVariableTable: 
   Start  Length  Slot  Name   Signature
   0      1      0    $this       Lscala/collection/generic/SequenceViewTemplate$Filtered;


public static java.lang.Object apply(scala.collection.generic.SequenceViewTemplate$Filtered, int);
  Code:
   Stack=3, Locals=2, Args_size=2
   0:	aload_0
   1:	invokeinterface	#17,  1; //InterfaceMethod scala/collection/generic/SequenceViewTemplate$Filtered.scala$collection$generic$SequenceViewTemplate$Filtered$$$outer:()Lscala/collection/generic/SequenceViewTemplate;
   6:	aload_0
   7:	invokeinterface	#21,  1; //InterfaceMethod scala/collection/generic/SequenceViewTemplate$Filtered.index:()[I
   12:	iload_1
   13:	iaload
   14:	invokeinterface	#26,  2; //InterfaceMethod scala/collection/generic/SequenceTemplate.apply:(I)Ljava/lang/Object;
   19:	areturn
  LineNumberTable: 
   line 86: 0

  LocalVariableTable: 
   Start  Length  Slot  Name   Signature
   0      20      0    $this       Lscala/collection/generic/SequenceViewTemplate$Filtered;
   0      20      1    idx       I


public static int length(scala.collection.generic.SequenceViewTemplate$Filtered);
  Code:
   Stack=1, Locals=1, Args_size=1
   0:	aload_0
   1:	invokeinterface	#21,  1; //InterfaceMethod scala/collection/generic/SequenceViewTemplate$Filtered.index:()[I
   6:	arraylength
   7:	ireturn
  LineNumberTable: 
   line 85: 0

  LocalVariableTable: 
   Start  Length  Slot  Name   Signature
   0      8      0    $this       Lscala/collection/generic/SequenceViewTemplate$Filtered;


public static int[] index(scala.collection.generic.SequenceViewTemplate$Filtered);
  Code:
   Stack=6, Locals=4, Args_size=1
   0:	new	#33; //class scala/runtime/IntRef
   3:	dup
   4:	iconst_0
   5:	invokespecial	#37; //Method scala/runtime/IntRef."<init>":(I)V
   8:	astore_1
   9:	aload_0
   10:	invokeinterface	#17,  1; //InterfaceMethod scala/collection/generic/SequenceViewTemplate$Filtered.scala$collection$generic$SequenceViewTemplate$Filtered$$$outer:()Lscala/collection/generic/SequenceViewTemplate;
   15:	invokeinterface	#40,  1; //InterfaceMethod scala/collection/generic/SequenceTemplate.length:()I
   20:	newarray int
   22:	astore_2
   23:	getstatic	#46; //Field scala/Predef$.MODULE$:Lscala/Predef$;
   26:	iconst_0
   27:	invokevirtual	#50; //Method scala/Predef$.intWrapper:(I)Lscala/runtime/RichInt;
   30:	aload_0
   31:	invokeinterface	#17,  1; //InterfaceMethod scala/collection/generic/SequenceViewTemplate$Filtered.scala$collection$generic$SequenceViewTemplate$Filtered$$$outer:()Lscala/collection/generic/SequenceViewTemplate;
   36:	invokeinterface	#40,  1; //InterfaceMethod scala/collection/generic/SequenceTemplate.length:()I
   41:	invokevirtual	#56; //Method scala/runtime/RichInt.until:(I)Lscala/Range;
   44:	new	#58; //class scala/collection/generic/SequenceViewTemplate$Filtered$$anonfun$index$2
   47:	dup
   48:	aload_0
   49:	aload_1
   50:	aload_2
   51:	invokespecial	#61; //Method scala/collection/generic/SequenceViewTemplate$Filtered$$anonfun$index$2."<init>":(Lscala/collection/generic/SequenceViewTemplate$Filtered;Lscala/runtime/IntRef;[I)V
   54:	invokevirtual	#67; //Method scala/Range.foreach:(Lscala/Function1;)V
   57:	getstatic	#72; //Field scala/runtime/ScalaRunTime$.MODULE$:Lscala/runtime/ScalaRunTime$;
   60:	getstatic	#72; //Field scala/runtime/ScalaRunTime$.MODULE$:Lscala/runtime/ScalaRunTime$;
   63:	aload_2
   64:	invokevirtual	#76; //Method scala/runtime/ScalaRunTime$.boxArray:(Ljava/lang/Object;)Lscala/runtime/BoxedArray;
   67:	aload_1
   68:	getfield	#79; //Field scala/runtime/IntRef.elem:I
   71:	invokeinterface	#85,  2; //InterfaceMethod scala/collection/generic/VectorTemplate.take:(I)Lscala/collection/generic/VectorTemplate;
   76:	checkcast	#87; //class scala/runtime/BoxedArray
   79:	getstatic	#93; //Field java/lang/Integer.TYPE:Ljava/lang/Class;
   82:	invokevirtual	#97; //Method scala/runtime/ScalaRunTime$.arrayValue:(Lscala/runtime/BoxedArray;Ljava/lang/Class;)Ljava/lang/Object;
   85:	astore_3
   86:	aload_3
   87:	instanceof	#87; //class scala/runtime/BoxedArray
   90:	ifeq	109
   93:	getstatic	#72; //Field scala/runtime/ScalaRunTime$.MODULE$:Lscala/runtime/ScalaRunTime$;
   96:	aload_3
   97:	checkcast	#87; //class scala/runtime/BoxedArray
   100:	getstatic	#93; //Field java/lang/Integer.TYPE:Ljava/lang/Class;
   103:	invokevirtual	#97; //Method scala/runtime/ScalaRunTime$.arrayValue:(Lscala/runtime/BoxedArray;Ljava/lang/Class;)Ljava/lang/Object;
   106:	goto	110
   109:	aload_3
   110:	checkcast	#99; //class "[I"
   113:	areturn
  LineNumberTable: 
   line 76: 0
   line 77: 9
   line 78: 23
   line 83: 57

  LocalVariableTable: 
   Start  Length  Slot  Name   Signature
   0      114      0    $this       Lscala/collection/generic/SequenceViewTemplate$Filtered;
   9      104      1    len$1       Lscala/runtime/IntRef;
   23      90      2    arr$1       [I


}

