Compiled from "SequenceTemplate.scala"
public abstract class scala.collection.generic.SequenceTemplate$class extends java.lang.Object
  SourceFile: "SequenceTemplate.scala"
  Scala: length = 0x
   
  InnerClass: 
   public final #561= #355 of #21; //$anon$1=class scala/collection/generic/SequenceTemplate$$anon$1 of class scala/collection/generic/SequenceTemplate
   public final #562= #352 of #21; //$anon$2=class scala/collection/generic/SequenceTemplate$$anon$2 of class scala/collection/generic/SequenceTemplate
   public final #563= #233 of #21; //$anon$3=class scala/collection/generic/SequenceTemplate$$anon$3 of class scala/collection/generic/SequenceTemplate
   public final #564= #378 of #21; //$anonfun$diff$1=class scala/collection/generic/SequenceTemplate$$anonfun$diff$1 of class scala/collection/generic/SequenceTemplate
   public final #565= #451 of #21; //$anonfun$reverse$2=class scala/collection/generic/SequenceTemplate$$anonfun$reverse$2 of class scala/collection/generic/SequenceTemplate
   public final #566= #483 of #21; //$anonfun$indexOf$1=class scala/collection/generic/SequenceTemplate$$anonfun$indexOf$1 of class scala/collection/generic/SequenceTemplate
   public final #567= #442 of #21; //$anonfun$reverse$1=class scala/collection/generic/SequenceTemplate$$anonfun$reverse$1 of class scala/collection/generic/SequenceTemplate
   public final #568= #390 of #21; //$anonfun$contains$1=class scala/collection/generic/SequenceTemplate$$anonfun$contains$1 of class scala/collection/generic/SequenceTemplate
   public final #569= #371 of #21; //$anonfun$intersect$1=class scala/collection/generic/SequenceTemplate$$anonfun$intersect$1 of class scala/collection/generic/SequenceTemplate
   public final #570= #358 of #21; //$anonfun$occCounts$1=class scala/collection/generic/SequenceTemplate$$anonfun$occCounts$1 of class scala/collection/generic/SequenceTemplate
   public final #571= #505 of #21; //$anonfun$indexWhere$1=class scala/collection/generic/SequenceTemplate$$anonfun$indexWhere$1 of class scala/collection/generic/SequenceTemplate
   public final #572= #479 of #21; //$anonfun$lastIndexOf$1=class scala/collection/generic/SequenceTemplate$$anonfun$lastIndexOf$1 of class scala/collection/generic/SequenceTemplate
   public final #573= #474 of #21; //$anonfun$lastIndexOf$2=class scala/collection/generic/SequenceTemplate$$anonfun$lastIndexOf$2 of class scala/collection/generic/SequenceTemplate
   public final #574= #533 of #21; //$anonfun$zipWithIndex$1=class scala/collection/generic/SequenceTemplate$$anonfun$zipWithIndex$1 of class scala/collection/generic/SequenceTemplate
   public final #575= #524 of #21; //$anonfun$segmentLength$1=class scala/collection/generic/SequenceTemplate$$anonfun$segmentLength$1 of class scala/collection/generic/SequenceTemplate
   public final #576= #553 of #21; //$anonfun$lengthCompare$1=class scala/collection/generic/SequenceTemplate$$anonfun$lengthCompare$1 of class scala/collection/generic/SequenceTemplate
   public final #577= #333 of #21; //$anonfun$removeDuplicates$1=class scala/collection/generic/SequenceTemplate$$anonfun$removeDuplicates$1 of class scala/collection/generic/SequenceTemplate
  minor version: 0
  major version: 49
  Constant pool:
const #1 = Asciz	SourceFile;
const #2 = Asciz	SequenceTemplate.scala;
const #3 = Asciz	$init$;
const #4 = Asciz	(Lscala/collection/generic/SequenceTemplate;)V;
const #5 = Asciz	Code;
const #6 = Asciz	LineNumberTable;
const #7 = Asciz	$this;
const #8 = Asciz	Lscala/collection/generic/SequenceTemplate;;
const #9 = Asciz	LocalVariableTable;
const #10 = Asciz	mi$1;
const #11 = Asciz	(Lscala/collection/generic/SequenceTemplate;Lscala/runtime/IntRef;Lscala/runtime/IntRef;)I;
const #12 = Asciz	scala/runtime/IntRef;
const #13 = class	#12;	//  scala/runtime/IntRef
const #14 = Asciz	elem;
const #15 = Asciz	I;
const #16 = NameAndType	#14:#15;//  elem:I
const #17 = Field	#13.#16;	//  scala/runtime/IntRef.elem:I
const #18 = Asciz	projection;
const #19 = Asciz	(Lscala/collection/generic/SequenceTemplate;)Ljava/lang/Object;;
const #20 = Asciz	scala/collection/generic/SequenceTemplate;
const #21 = class	#20;	//  scala/collection/generic/SequenceTemplate
const #22 = Asciz	view;
const #23 = Asciz	()Ljava/lang/Object;;
const #24 = NameAndType	#22:#23;//  view:()Ljava/lang/Object;
const #25 = InterfaceMethod	#21.#24;	//  scala/collection/generic/SequenceTemplate.view:()Ljava/lang/Object;
const #26 = Asciz	containsSlice;
const #27 = Asciz	(Lscala/collection/generic/SequenceTemplate;Lscala/collection/Sequence;)Z;
const #28 = Asciz	indexOfSeq;
const #29 = Asciz	(Lscala/collection/Sequence;)I;
const #30 = NameAndType	#28:#29;//  indexOfSeq:(Lscala/collection/Sequence;)I
const #31 = InterfaceMethod	#21.#30;	//  scala/collection/generic/SequenceTemplate.indexOfSeq:(Lscala/collection/Sequence;)I
const #32 = Asciz	that;
const #33 = Asciz	Lscala/collection/Sequence;;
const #34 = Asciz	equalsWith;
const #35 = Asciz	(Lscala/collection/generic/SequenceTemplate;Lscala/collection/Sequence;Lscala/Function2;)Z;
const #36 = Asciz	scala/collection/generic/IterableTemplate;
const #37 = class	#36;	//  scala/collection/generic/IterableTemplate
const #38 = Asciz	iterator;
const #39 = Asciz	()Lscala/collection/Iterator;;
const #40 = NameAndType	#38:#39;//  iterator:()Lscala/collection/Iterator;
const #41 = InterfaceMethod	#37.#40;	//  scala/collection/generic/IterableTemplate.iterator:()Lscala/collection/Iterator;
const #42 = Asciz	scala/collection/Iterator;
const #43 = class	#42;	//  scala/collection/Iterator
const #44 = Asciz	hasNext;
const #45 = Asciz	()Z;
const #46 = NameAndType	#44:#45;//  hasNext:()Z
const #47 = InterfaceMethod	#43.#46;	//  scala/collection/Iterator.hasNext:()Z
const #48 = Asciz	next;
const #49 = NameAndType	#48:#23;//  next:()Ljava/lang/Object;
const #50 = InterfaceMethod	#43.#49;	//  scala/collection/Iterator.next:()Ljava/lang/Object;
const #51 = Asciz	scala/Function2;
const #52 = class	#51;	//  scala/Function2
const #53 = Asciz	apply;
const #54 = Asciz	(Ljava/lang/Object;Ljava/lang/Object;)Ljava/lang/Object;;
const #55 = NameAndType	#53:#54;//  apply:(Ljava/lang/Object;Ljava/lang/Object;)Ljava/lang/Object;
const #56 = InterfaceMethod	#52.#55;	//  scala/Function2.apply:(Ljava/lang/Object;Ljava/lang/Object;)Ljava/lang/Object;
const #57 = Asciz	scala/runtime/BoxesRunTime;
const #58 = class	#57;	//  scala/runtime/BoxesRunTime
const #59 = Asciz	unboxToBoolean;
const #60 = Asciz	(Ljava/lang/Object;)Z;
const #61 = NameAndType	#59:#60;//  unboxToBoolean:(Ljava/lang/Object;)Z
const #62 = Method	#58.#61;	//  scala/runtime/BoxesRunTime.unboxToBoolean:(Ljava/lang/Object;)Z
const #63 = Asciz	f;
const #64 = Asciz	Lscala/Function2;;
const #65 = Asciz	i;
const #66 = Asciz	Lscala/collection/Iterator;;
const #67 = Asciz	j;
const #68 = Asciz	slice;
const #69 = Asciz	(Lscala/collection/generic/SequenceTemplate;I)Lscala/collection/Sequence;;
const #70 = Asciz	length;
const #71 = Asciz	()I;
const #72 = NameAndType	#70:#71;//  length:()I
const #73 = InterfaceMethod	#21.#72;	//  scala/collection/generic/SequenceTemplate.length:()I
const #74 = Asciz	scala/collection/generic/TraversableTemplate;
const #75 = class	#74;	//  scala/collection/generic/TraversableTemplate
const #76 = Asciz	(II)Lscala/collection/generic/TraversableTemplate;;
const #77 = NameAndType	#68:#76;//  slice:(II)Lscala/collection/generic/TraversableTemplate;
const #78 = InterfaceMethod	#75.#77;	//  scala/collection/generic/TraversableTemplate.slice:(II)Lscala/collection/generic/TraversableTemplate;
const #79 = Asciz	scala/collection/Sequence;
const #80 = class	#79;	//  scala/collection/Sequence
const #81 = Asciz	from;
const #82 = Asciz	findLastIndexOf;
const #83 = Asciz	(Lscala/collection/generic/SequenceTemplate;Lscala/Function1;)I;
const #84 = Asciz	lastIndexWhere;
const #85 = Asciz	(Lscala/Function1;)I;
const #86 = NameAndType	#84:#85;//  lastIndexWhere:(Lscala/Function1;)I
const #87 = InterfaceMethod	#21.#86;	//  scala/collection/generic/SequenceTemplate.lastIndexWhere:(Lscala/Function1;)I
const #88 = Asciz	p;
const #89 = Asciz	Lscala/Function1;;
const #90 = Asciz	toString;
const #91 = Asciz	(Lscala/collection/generic/SequenceTemplate;)Ljava/lang/String;;
const #92 = Asciz	scala/collection/generic/TraversableTemplate$class;
const #93 = class	#92;	//  scala/collection/generic/TraversableTemplate$class
const #94 = Asciz	(Lscala/collection/generic/TraversableTemplate;)Ljava/lang/String;;
const #95 = NameAndType	#90:#94;//  toString:(Lscala/collection/generic/TraversableTemplate;)Ljava/lang/String;
const #96 = Method	#93.#95;	//  scala/collection/generic/TraversableTemplate$class.toString:(Lscala/collection/generic/TraversableTemplate;)Ljava/lang/String;
const #97 = Asciz	equals;
const #98 = Asciz	(Lscala/collection/generic/SequenceTemplate;Ljava/lang/Object;)Z;
const #99 = Asciz	scala/runtime/ScalaRunTime$;
const #100 = class	#99;	//  scala/runtime/ScalaRunTime$
const #101 = Asciz	MODULE$;
const #102 = Asciz	Lscala/runtime/ScalaRunTime$;;
const #103 = NameAndType	#101:#102;//  MODULE$:Lscala/runtime/ScalaRunTime$;
const #104 = Field	#100.#103;	//  scala/runtime/ScalaRunTime$.MODULE$:Lscala/runtime/ScalaRunTime$;
const #105 = Asciz	isArray;
const #106 = NameAndType	#105:#60;//  isArray:(Ljava/lang/Object;)Z
const #107 = Method	#100.#106;	//  scala/runtime/ScalaRunTime$.isArray:(Ljava/lang/Object;)Z
const #108 = Asciz	boxArray;
const #109 = Asciz	(Ljava/lang/Object;)Lscala/runtime/BoxedArray;;
const #110 = NameAndType	#108:#109;//  boxArray:(Ljava/lang/Object;)Lscala/runtime/BoxedArray;
const #111 = Method	#100.#110;	//  scala/runtime/ScalaRunTime$.boxArray:(Ljava/lang/Object;)Lscala/runtime/BoxedArray;
const #112 = Asciz	sameElements;
const #113 = Asciz	(Lscala/collection/Iterable;)Z;
const #114 = NameAndType	#112:#113;//  sameElements:(Lscala/collection/Iterable;)Z
const #115 = InterfaceMethod	#37.#114;	//  scala/collection/generic/IterableTemplate.sameElements:(Lscala/collection/Iterable;)Z
const #116 = Asciz	Ljava/lang/Object;;
const #117 = Asciz	temp13;
const #118 = Asciz	temp14;
const #119 = Asciz	lastIndexOf_KMP;
const #120 = Asciz	(Lscala/collection/generic/SequenceTemplate;Lscala/collection/Sequence;IILscala/collection/Sequence;III)I;
const #121 = Asciz	take;
const #122 = Asciz	(I)Lscala/collection/generic/TraversableTemplate;;
const #123 = NameAndType	#121:#122;//  take:(I)Lscala/collection/generic/TraversableTemplate;
const #124 = InterfaceMethod	#75.#123;	//  scala/collection/generic/TraversableTemplate.take:(I)Lscala/collection/generic/TraversableTemplate;
const #125 = Asciz	reverse;
const #126 = Asciz	()Lscala/collection/generic/IterableTemplate;;
const #127 = NameAndType	#125:#126;//  reverse:()Lscala/collection/generic/IterableTemplate;
const #128 = InterfaceMethod	#21.#127;	//  scala/collection/generic/SequenceTemplate.reverse:()Lscala/collection/generic/IterableTemplate;
const #129 = Asciz	scala/collection/generic/SequenceTemplate$class;
const #130 = class	#129;	//  scala/collection/generic/SequenceTemplate$class
const #131 = Asciz	KMP;
const #132 = Asciz	(Lscala/collection/generic/SequenceTemplate;Lscala/collection/Sequence;Lscala/collection/Sequence;)Lscala/Option;;
const #133 = NameAndType	#131:#132;//  KMP:(Lscala/collection/generic/SequenceTemplate;Lscala/collection/Sequence;Lscala/collection/Sequence;)Lscala/Option;
const #134 = Method	#130.#133;	//  scala/collection/generic/SequenceTemplate$class.KMP:(Lscala/collection/generic/SequenceTemplate;Lscala/collection/Sequence;Lscala/collection/Sequence;)Lscala/Option;
const #135 = Asciz	scala/None$;
const #136 = class	#135;	//  scala/None$
const #137 = Asciz	Lscala/None$;;
const #138 = NameAndType	#101:#137;//  MODULE$:Lscala/None$;
const #139 = Field	#136.#138;	//  scala/None$.MODULE$:Lscala/None$;
const #140 = Asciz	java/lang/Object;
const #141 = class	#140;	//  java/lang/Object
const #142 = NameAndType	#97:#60;//  equals:(Ljava/lang/Object;)Z
const #143 = Method	#141.#142;	//  java/lang/Object.equals:(Ljava/lang/Object;)Z
const #144 = Asciz	scala/Some;
const #145 = class	#144;	//  scala/Some
const #146 = Asciz	x;
const #147 = NameAndType	#146:#23;//  x:()Ljava/lang/Object;
const #148 = Method	#145.#147;	//  scala/Some.x:()Ljava/lang/Object;
const #149 = Asciz	unboxToInt;
const #150 = Asciz	(Ljava/lang/Object;)I;
const #151 = NameAndType	#149:#150;//  unboxToInt:(Ljava/lang/Object;)I
const #152 = Method	#58.#151;	//  scala/runtime/BoxesRunTime.unboxToInt:(Ljava/lang/Object;)I
const #153 = Asciz	scala/MatchError;
const #154 = class	#153;	//  scala/MatchError
const #155 = Asciz	scala/Option;
const #156 = class	#155;	//  scala/Option
const #157 = Asciz	()Ljava/lang/String;;
const #158 = NameAndType	#90:#157;//  toString:()Ljava/lang/String;
const #159 = Method	#156.#158;	//  scala/Option.toString:()Ljava/lang/String;
const #160 = Asciz	<init>;
const #161 = Asciz	(Ljava/lang/String;)V;
const #162 = NameAndType	#160:#161;//  "<init>":(Ljava/lang/String;)V
const #163 = Method	#154.#162;	//  scala/MatchError."<init>":(Ljava/lang/String;)V
const #164 = Asciz	source;
const #165 = Asciz	sourceOffset;
const #166 = Asciz	sourceCount;
const #167 = Asciz	target;
const #168 = Asciz	targetOffset;
const #169 = Asciz	targetCount;
const #170 = Asciz	fromIndex;
const #171 = Asciz	src;
const #172 = Asciz	tgt;
const #173 = Asciz	temp9;
const #174 = Asciz	Lscala/Option;;
const #175 = Asciz	temp11;
const #176 = Asciz	Lscala/Some;;
const #177 = Asciz	temp12;
const #178 = Asciz	<B:Ljava/lang/Object;>(Lscala/collection/Sequence<TB;>;IILscala/collection/Sequence<TB;>;III)I;
const #179 = Asciz	Signature;
const #180 = Asciz	indexOf_KMP;
const #181 = Asciz	drop;
const #182 = NameAndType	#181:#122;//  drop:(I)Lscala/collection/generic/TraversableTemplate;
const #183 = InterfaceMethod	#75.#182;	//  scala/collection/generic/TraversableTemplate.drop:(I)Lscala/collection/generic/TraversableTemplate;
const #184 = Asciz	temp5;
const #185 = Asciz	temp7;
const #186 = Asciz	temp8;
const #187 = Asciz	isEmpty;
const #188 = NameAndType	#187:#45;//  isEmpty:()Z
const #189 = InterfaceMethod	#37.#188;	//  scala/collection/generic/IterableTemplate.isEmpty:()Z
const #190 = Asciz	boxToInteger;
const #191 = Asciz	(I)Ljava/lang/Integer;;
const #192 = NameAndType	#190:#191;//  boxToInteger:(I)Ljava/lang/Integer;
const #193 = Method	#58.#192;	//  scala/runtime/BoxesRunTime.boxToInteger:(I)Ljava/lang/Integer;
const #194 = Asciz	(Ljava/lang/Object;)V;
const #195 = NameAndType	#160:#194;//  "<init>":(Ljava/lang/Object;)V
const #196 = Method	#145.#195;	//  scala/Some."<init>":(Ljava/lang/Object;)V
const #197 = Asciz	(I)Ljava/lang/Object;;
const #198 = NameAndType	#53:#197;//  apply:(I)Ljava/lang/Object;
const #199 = InterfaceMethod	#21.#198;	//  scala/collection/generic/SequenceTemplate.apply:(I)Ljava/lang/Object;
const #200 = Asciz	indexOf;
const #201 = NameAndType	#200:#150;//  indexOf:(Ljava/lang/Object;)I
const #202 = InterfaceMethod	#21.#201;	//  scala/collection/generic/SequenceTemplate.indexOf:(Ljava/lang/Object;)I
const #203 = Asciz	(Ljava/lang/Object;Ljava/lang/Object;)Z;
const #204 = NameAndType	#97:#203;//  equals:(Ljava/lang/Object;Ljava/lang/Object;)Z
const #205 = Method	#58.#204;	//  scala/runtime/BoxesRunTime.equals:(Ljava/lang/Object;Ljava/lang/Object;)Z
const #206 = Asciz	(I)V;
const #207 = NameAndType	#160:#206;//  "<init>":(I)V
const #208 = Method	#13.#207;	//  scala/runtime/IntRef."<init>":(I)V
const #209 = NameAndType	#10:#11;//  mi$1:(Lscala/collection/generic/SequenceTemplate;Lscala/runtime/IntRef;Lscala/runtime/IntRef;)I
const #210 = Method	#130.#209;	//  scala/collection/generic/SequenceTemplate$class.mi$1:(Lscala/collection/generic/SequenceTemplate;Lscala/runtime/IntRef;Lscala/runtime/IntRef;)I
const #211 = Asciz	S;
const #212 = Asciz	W;
const #213 = Asciz	temp4;
const #214 = Asciz	T;
const #215 = Asciz	[I;
const #216 = Asciz	arr;
const #217 = Asciz	pos;
const #218 = Asciz	cnd;
const #219 = Asciz	m$1;
const #220 = Asciz	Lscala/runtime/IntRef;;
const #221 = Asciz	i$5;
const #222 = Asciz	<B:Ljava/lang/Object;>(Lscala/collection/Sequence<TB;>;Lscala/collection/Sequence<TB;>;)Lscala/Option<Ljava/lang/Integer;>;;
const #223 = Asciz	(Lscala/collection/generic/SequenceTemplate;II)Lscala/collection/generic/SequenceView;;
const #224 = Asciz	scala/collection/generic/TraversableViewTemplate;
const #225 = class	#224;	//  scala/collection/generic/TraversableViewTemplate
const #226 = Asciz	(II)Lscala/collection/generic/TraversableView;;
const #227 = NameAndType	#68:#226;//  slice:(II)Lscala/collection/generic/TraversableView;
const #228 = InterfaceMethod	#225.#227;	//  scala/collection/generic/TraversableViewTemplate.slice:(II)Lscala/collection/generic/TraversableView;
const #229 = Asciz	scala/collection/generic/SequenceView;
const #230 = class	#229;	//  scala/collection/generic/SequenceView
const #231 = Asciz	until;
const #232 = Asciz	scala/collection/generic/SequenceTemplate$$anon$3;
const #233 = class	#232;	//  scala/collection/generic/SequenceTemplate$$anon$3
const #234 = NameAndType	#160:#4;//  "<init>":(Lscala/collection/generic/SequenceTemplate;)V
const #235 = Method	#233.#234;	//  scala/collection/generic/SequenceTemplate$$anon$3."<init>":(Lscala/collection/generic/SequenceTemplate;)V
const #236 = Asciz	indices;
const #237 = Asciz	(Lscala/collection/generic/SequenceTemplate;)Lscala/Range;;
const #238 = Asciz	scala/Predef$;
const #239 = class	#238;	//  scala/Predef$
const #240 = Asciz	Lscala/Predef$;;
const #241 = NameAndType	#101:#240;//  MODULE$:Lscala/Predef$;
const #242 = Field	#239.#241;	//  scala/Predef$.MODULE$:Lscala/Predef$;
const #243 = Asciz	intWrapper;
const #244 = Asciz	(I)Lscala/runtime/RichInt;;
const #245 = NameAndType	#243:#244;//  intWrapper:(I)Lscala/runtime/RichInt;
const #246 = Method	#239.#245;	//  scala/Predef$.intWrapper:(I)Lscala/runtime/RichInt;
const #247 = Asciz	scala/runtime/RichInt;
const #248 = class	#247;	//  scala/runtime/RichInt
const #249 = Asciz	(I)Lscala/Range;;
const #250 = NameAndType	#231:#249;//  until:(I)Lscala/Range;
const #251 = Method	#248.#250;	//  scala/runtime/RichInt.until:(I)Lscala/Range;
const #252 = Asciz	toSequence;
const #253 = Asciz	(Lscala/collection/generic/SequenceTemplate;)Lscala/collection/Sequence;;
const #254 = Asciz	thisCollection;
const #255 = Asciz	()Lscala/collection/generic/TraversableTemplate;;
const #256 = NameAndType	#254:#255;//  thisCollection:()Lscala/collection/generic/TraversableTemplate;
const #257 = InterfaceMethod	#75.#256;	//  scala/collection/generic/TraversableTemplate.thisCollection:()Lscala/collection/generic/TraversableTemplate;
const #258 = Asciz	padTo;
const #259 = Asciz	(Lscala/collection/generic/SequenceTemplate;ILjava/lang/Object;Lscala/collection/generic/BuilderFactory;)Ljava/lang/Object;;
const #260 = Asciz	scala/collection/generic/BuilderFactory;
const #261 = class	#260;	//  scala/collection/generic/BuilderFactory
const #262 = Asciz	(Ljava/lang/Object;)Lscala/collection/generic/Builder;;
const #263 = NameAndType	#53:#262;//  apply:(Ljava/lang/Object;)Lscala/collection/generic/Builder;
const #264 = InterfaceMethod	#261.#263;	//  scala/collection/generic/BuilderFactory.apply:(Ljava/lang/Object;)Lscala/collection/generic/Builder;
const #265 = Asciz	scala/collection/Traversable;
const #266 = class	#265;	//  scala/collection/Traversable
const #267 = Asciz	scala/collection/generic/Growable;
const #268 = class	#267;	//  scala/collection/generic/Growable
const #269 = Asciz	$plus$plus$eq;
const #270 = Asciz	(Lscala/collection/Traversable;)Lscala/collection/generic/Growable;;
const #271 = NameAndType	#269:#270;//  $plus$plus$eq:(Lscala/collection/Traversable;)Lscala/collection/generic/Growable;
const #272 = InterfaceMethod	#268.#271;	//  scala/collection/generic/Growable.$plus$plus$eq:(Lscala/collection/Traversable;)Lscala/collection/generic/Growable;
const #273 = Asciz	scala/collection/generic/Builder;
const #274 = class	#273;	//  scala/collection/generic/Builder
const #275 = Asciz	$plus$eq;
const #276 = NameAndType	#275:#262;//  $plus$eq:(Ljava/lang/Object;)Lscala/collection/generic/Builder;
const #277 = InterfaceMethod	#274.#276;	//  scala/collection/generic/Builder.$plus$eq:(Ljava/lang/Object;)Lscala/collection/generic/Builder;
const #278 = Asciz	result;
const #279 = NameAndType	#278:#23;//  result:()Ljava/lang/Object;
const #280 = InterfaceMethod	#274.#279;	//  scala/collection/generic/Builder.result:()Ljava/lang/Object;
const #281 = Asciz	len;
const #282 = Asciz	bf;
const #283 = Asciz	Lscala/collection/generic/BuilderFactory;;
const #284 = Asciz	b;
const #285 = Asciz	Lscala/collection/generic/Builder;;
const #286 = Asciz	diff;
const #287 = Asciz	patch;
const #288 = Asciz	(Lscala/collection/generic/SequenceTemplate;ILscala/collection/Sequence;ILscala/collection/generic/BuilderFactory;)Ljava/lang/Object;;
const #289 = Asciz	splitAt;
const #290 = Asciz	(I)Lscala/Tuple2;;
const #291 = NameAndType	#289:#290;//  splitAt:(I)Lscala/Tuple2;
const #292 = InterfaceMethod	#75.#291;	//  scala/collection/generic/TraversableTemplate.splitAt:(I)Lscala/Tuple2;
const #293 = Asciz	scala/Tuple2;
const #294 = class	#293;	//  scala/Tuple2
const #295 = Asciz	_1;
const #296 = NameAndType	#295:#23;//  _1:()Ljava/lang/Object;
const #297 = Method	#294.#296;	//  scala/Tuple2._1:()Ljava/lang/Object;
const #298 = Asciz	_2;
const #299 = NameAndType	#298:#23;//  _2:()Ljava/lang/Object;
const #300 = Method	#294.#299;	//  scala/Tuple2._2:()Ljava/lang/Object;
const #301 = Asciz	(Ljava/lang/Object;Ljava/lang/Object;)V;
const #302 = NameAndType	#160:#301;//  "<init>":(Ljava/lang/Object;Ljava/lang/Object;)V
const #303 = Method	#294.#302;	//  scala/Tuple2."<init>":(Ljava/lang/Object;Ljava/lang/Object;)V
const #304 = Method	#294.#158;	//  scala/Tuple2.toString:()Ljava/lang/String;
const #305 = Asciz	replaced;
const #306 = Asciz	temp1;
const #307 = Asciz	Lscala/Tuple2;;
const #308 = Asciz	temp2;
const #309 = Asciz	Lscala/collection/generic/IterableTemplate;;
const #310 = Asciz	temp3;
const #311 = Asciz	rest;
const #312 = Asciz	prefix;
const #313 = Asciz	removeDuplicates;
const #314 = Asciz	(Lscala/collection/generic/SequenceTemplate;)Lscala/collection/generic/IterableTemplate;;
const #315 = Asciz	newBuilder;
const #316 = Asciz	()Lscala/collection/generic/Builder;;
const #317 = NameAndType	#315:#316;//  newBuilder:()Lscala/collection/generic/Builder;
const #318 = InterfaceMethod	#75.#317;	//  scala/collection/generic/TraversableTemplate.newBuilder:()Lscala/collection/generic/Builder;
const #319 = Asciz	scala/runtime/ObjectRef;
const #320 = class	#319;	//  scala/runtime/ObjectRef
const #321 = Asciz	scala/collection/Set$;
const #322 = class	#321;	//  scala/collection/Set$
const #323 = Asciz	Lscala/collection/Set$;;
const #324 = NameAndType	#101:#323;//  MODULE$:Lscala/collection/Set$;
const #325 = Field	#322.#324;	//  scala/collection/Set$.MODULE$:Lscala/collection/Set$;
const #326 = Asciz	(Lscala/collection/Sequence;)Lscala/collection/Traversable;;
const #327 = NameAndType	#53:#326;//  apply:(Lscala/collection/Sequence;)Lscala/collection/Traversable;
const #328 = Method	#322.#327;	//  scala/collection/Set$.apply:(Lscala/collection/Sequence;)Lscala/collection/Traversable;
const #329 = Asciz	scala/collection/Set;
const #330 = class	#329;	//  scala/collection/Set
const #331 = Method	#320.#195;	//  scala/runtime/ObjectRef."<init>":(Ljava/lang/Object;)V
const #332 = Asciz	scala/collection/generic/SequenceTemplate$$anonfun$removeDuplicates$1;
const #333 = class	#332;	//  scala/collection/generic/SequenceTemplate$$anonfun$removeDuplicates$1
const #334 = Asciz	(Lscala/collection/generic/SequenceTemplate;Lscala/collection/generic/Builder;Lscala/runtime/ObjectRef;)V;
const #335 = NameAndType	#160:#334;//  "<init>":(Lscala/collection/generic/SequenceTemplate;Lscala/collection/generic/Builder;Lscala/runtime/ObjectRef;)V
const #336 = Method	#333.#335;	//  scala/collection/generic/SequenceTemplate$$anonfun$removeDuplicates$1."<init>":(Lscala/collection/generic/SequenceTemplate;Lscala/collection/generic/Builder;Lscala/runtime/ObjectRef;)V
const #337 = Asciz	foreach;
const #338 = Asciz	(Lscala/Function1;)V;
const #339 = NameAndType	#337:#338;//  foreach:(Lscala/Function1;)V
const #340 = InterfaceMethod	#37.#339;	//  scala/collection/generic/IterableTemplate.foreach:(Lscala/Function1;)V
const #341 = Asciz	b$5;
const #342 = Asciz	seen$1;
const #343 = Asciz	Lscala/runtime/ObjectRef;;
const #344 = Asciz	occCounts;
const #345 = Asciz	(Lscala/collection/generic/SequenceTemplate;Lscala/collection/Sequence;)Lscala/collection/mutable/Map;;
const #346 = Asciz	head;
const #347 = NameAndType	#346:#23;//  head:()Ljava/lang/Object;
const #348 = InterfaceMethod	#37.#347;	//  scala/collection/generic/IterableTemplate.head:()Ljava/lang/Object;
const #349 = Asciz	scala/Unhashable;
const #350 = class	#349;	//  scala/Unhashable
const #351 = Asciz	scala/collection/generic/SequenceTemplate$$anon$2;
const #352 = class	#351;	//  scala/collection/generic/SequenceTemplate$$anon$2
const #353 = Method	#352.#234;	//  scala/collection/generic/SequenceTemplate$$anon$2."<init>":(Lscala/collection/generic/SequenceTemplate;)V
const #354 = Asciz	scala/collection/generic/SequenceTemplate$$anon$1;
const #355 = class	#354;	//  scala/collection/generic/SequenceTemplate$$anon$1
const #356 = Method	#355.#234;	//  scala/collection/generic/SequenceTemplate$$anon$1."<init>":(Lscala/collection/generic/SequenceTemplate;)V
const #357 = Asciz	scala/collection/generic/SequenceTemplate$$anonfun$occCounts$1;
const #358 = class	#357;	//  scala/collection/generic/SequenceTemplate$$anonfun$occCounts$1
const #359 = Asciz	(Lscala/collection/generic/SequenceTemplate;Lscala/collection/mutable/Map;)V;
const #360 = NameAndType	#160:#359;//  "<init>":(Lscala/collection/generic/SequenceTemplate;Lscala/collection/mutable/Map;)V
const #361 = Method	#358.#360;	//  scala/collection/generic/SequenceTemplate$$anonfun$occCounts$1."<init>":(Lscala/collection/generic/SequenceTemplate;Lscala/collection/mutable/Map;)V
const #362 = Asciz	seq;
const #363 = Asciz	occ$3;
const #364 = Asciz	Lscala/collection/mutable/Map;;
const #365 = Asciz	<B:Ljava/lang/Object;>(Lscala/collection/Sequence<TB;>;)Lscala/collection/mutable/Map<TB;Ljava/lang/Integer;>;;
const #366 = Asciz	intersect;
const #367 = Asciz	(Lscala/collection/generic/SequenceTemplate;Lscala/collection/Sequence;)Lscala/collection/generic/IterableTemplate;;
const #368 = NameAndType	#344:#345;//  occCounts:(Lscala/collection/generic/SequenceTemplate;Lscala/collection/Sequence;)Lscala/collection/mutable/Map;
const #369 = Method	#130.#368;	//  scala/collection/generic/SequenceTemplate$class.occCounts:(Lscala/collection/generic/SequenceTemplate;Lscala/collection/Sequence;)Lscala/collection/mutable/Map;
const #370 = Asciz	scala/collection/generic/SequenceTemplate$$anonfun$intersect$1;
const #371 = class	#370;	//  scala/collection/generic/SequenceTemplate$$anonfun$intersect$1
const #372 = Asciz	(Lscala/collection/generic/SequenceTemplate;Lscala/collection/mutable/Map;Lscala/collection/generic/Builder;)V;
const #373 = NameAndType	#160:#372;//  "<init>":(Lscala/collection/generic/SequenceTemplate;Lscala/collection/mutable/Map;Lscala/collection/generic/Builder;)V
const #374 = Method	#371.#373;	//  scala/collection/generic/SequenceTemplate$$anonfun$intersect$1."<init>":(Lscala/collection/generic/SequenceTemplate;Lscala/collection/mutable/Map;Lscala/collection/generic/Builder;)V
const #375 = Asciz	occ$2;
const #376 = Asciz	b$4;
const #377 = Asciz	scala/collection/generic/SequenceTemplate$$anonfun$diff$1;
const #378 = class	#377;	//  scala/collection/generic/SequenceTemplate$$anonfun$diff$1
const #379 = Method	#378.#373;	//  scala/collection/generic/SequenceTemplate$$anonfun$diff$1."<init>":(Lscala/collection/generic/SequenceTemplate;Lscala/collection/mutable/Map;Lscala/collection/generic/Builder;)V
const #380 = Asciz	occ$1;
const #381 = Asciz	b$3;
const #382 = Asciz	union;
const #383 = Asciz	(Lscala/collection/generic/SequenceTemplate;Lscala/collection/Sequence;Lscala/collection/generic/BuilderFactory;)Ljava/lang/Object;;
const #384 = Asciz	$plus$plus;
const #385 = Asciz	(Lscala/collection/Traversable;Lscala/collection/generic/BuilderFactory;)Ljava/lang/Object;;
const #386 = NameAndType	#384:#385;//  $plus$plus:(Lscala/collection/Traversable;Lscala/collection/generic/BuilderFactory;)Ljava/lang/Object;
const #387 = InterfaceMethod	#75.#386;	//  scala/collection/generic/TraversableTemplate.$plus$plus:(Lscala/collection/Traversable;Lscala/collection/generic/BuilderFactory;)Ljava/lang/Object;
const #388 = Asciz	contains;
const #389 = Asciz	scala/collection/generic/SequenceTemplate$$anonfun$contains$1;
const #390 = class	#389;	//  scala/collection/generic/SequenceTemplate$$anonfun$contains$1
const #391 = Asciz	(Lscala/collection/generic/SequenceTemplate;Ljava/lang/Object;)V;
const #392 = NameAndType	#160:#391;//  "<init>":(Lscala/collection/generic/SequenceTemplate;Ljava/lang/Object;)V
const #393 = Method	#390.#392;	//  scala/collection/generic/SequenceTemplate$$anonfun$contains$1."<init>":(Lscala/collection/generic/SequenceTemplate;Ljava/lang/Object;)V
const #394 = Asciz	exists;
const #395 = Asciz	(Lscala/Function1;)Z;
const #396 = NameAndType	#394:#395;//  exists:(Lscala/Function1;)Z
const #397 = InterfaceMethod	#75.#396;	//  scala/collection/generic/TraversableTemplate.exists:(Lscala/Function1;)Z
const #398 = Asciz	elem$1;
const #399 = Asciz	lastIndexOfSeq;
const #400 = Asciz	(Lscala/collection/generic/SequenceTemplate;Lscala/collection/Sequence;I)I;
const #401 = NameAndType	#119:#120;//  lastIndexOf_KMP:(Lscala/collection/generic/SequenceTemplate;Lscala/collection/Sequence;IILscala/collection/Sequence;III)I
const #402 = Method	#130.#401;	//  scala/collection/generic/SequenceTemplate$class.lastIndexOf_KMP:(Lscala/collection/generic/SequenceTemplate;Lscala/collection/Sequence;IILscala/collection/Sequence;III)I
const #403 = Asciz	(Lscala/collection/generic/SequenceTemplate;Lscala/collection/Sequence;)I;
const #404 = Asciz	(Lscala/collection/Sequence;I)I;
const #405 = NameAndType	#399:#404;//  lastIndexOfSeq:(Lscala/collection/Sequence;I)I
const #406 = InterfaceMethod	#21.#405;	//  scala/collection/generic/SequenceTemplate.lastIndexOfSeq:(Lscala/collection/Sequence;I)I
const #407 = Asciz	hasDefiniteSize;
const #408 = NameAndType	#407:#45;//  hasDefiniteSize:()Z
const #409 = InterfaceMethod	#75.#408;	//  scala/collection/generic/TraversableTemplate.hasDefiniteSize:()Z
const #410 = NameAndType	#180:#120;//  indexOf_KMP:(Lscala/collection/generic/SequenceTemplate;Lscala/collection/Sequence;IILscala/collection/Sequence;III)I
const #411 = Method	#130.#410;	//  scala/collection/generic/SequenceTemplate$class.indexOf_KMP:(Lscala/collection/generic/SequenceTemplate;Lscala/collection/Sequence;IILscala/collection/Sequence;III)I
const #412 = Asciz	startsWith;
const #413 = Asciz	(Lscala/collection/Sequence;)Z;
const #414 = NameAndType	#412:#413;//  startsWith:(Lscala/collection/Sequence;)Z
const #415 = InterfaceMethod	#21.#414;	//  scala/collection/generic/SequenceTemplate.startsWith:(Lscala/collection/Sequence;)Z
const #416 = Asciz	tail;
const #417 = NameAndType	#416:#255;//  tail:()Lscala/collection/generic/TraversableTemplate;
const #418 = InterfaceMethod	#75.#417;	//  scala/collection/generic/TraversableTemplate.tail:()Lscala/collection/generic/TraversableTemplate;
const #419 = Asciz	s;
const #420 = NameAndType	#28:#404;//  indexOfSeq:(Lscala/collection/Sequence;I)I
const #421 = InterfaceMethod	#21.#420;	//  scala/collection/generic/SequenceTemplate.indexOfSeq:(Lscala/collection/Sequence;I)I
const #422 = Asciz	endsWith;
const #423 = Asciz	(I)Lscala/collection/Iterator;;
const #424 = NameAndType	#181:#423;//  drop:(I)Lscala/collection/Iterator;
const #425 = InterfaceMethod	#43.#424;	//  scala/collection/Iterator.drop:(I)Lscala/collection/Iterator;
const #426 = Asciz	(Lscala/collection/Sequence;I)Z;
const #427 = NameAndType	#412:#426;//  startsWith:(Lscala/collection/Sequence;I)Z
const #428 = InterfaceMethod	#21.#427;	//  scala/collection/generic/SequenceTemplate.startsWith:(Lscala/collection/Sequence;I)Z
const #429 = Asciz	(Lscala/collection/generic/SequenceTemplate;Lscala/collection/Sequence;I)Z;
const #430 = Asciz	offset;
const #431 = Asciz	reversedElements;
const #432 = Asciz	(Lscala/collection/generic/SequenceTemplate;)Lscala/collection/Iterator;;
const #433 = Asciz	reverseIterator;
const #434 = NameAndType	#433:#39;//  reverseIterator:()Lscala/collection/Iterator;
const #435 = InterfaceMethod	#21.#434;	//  scala/collection/generic/SequenceTemplate.reverseIterator:()Lscala/collection/Iterator;
const #436 = Asciz	scala/collection/immutable/Nil$;
const #437 = class	#436;	//  scala/collection/immutable/Nil$
const #438 = Asciz	Lscala/collection/immutable/Nil$;;
const #439 = NameAndType	#101:#438;//  MODULE$:Lscala/collection/immutable/Nil$;
const #440 = Field	#437.#439;	//  scala/collection/immutable/Nil$.MODULE$:Lscala/collection/immutable/Nil$;
const #441 = Asciz	scala/collection/generic/SequenceTemplate$$anonfun$reverse$1;
const #442 = class	#441;	//  scala/collection/generic/SequenceTemplate$$anonfun$reverse$1
const #443 = Asciz	(Lscala/collection/generic/SequenceTemplate;Lscala/runtime/ObjectRef;)V;
const #444 = NameAndType	#160:#443;//  "<init>":(Lscala/collection/generic/SequenceTemplate;Lscala/runtime/ObjectRef;)V
const #445 = Method	#442.#444;	//  scala/collection/generic/SequenceTemplate$$anonfun$reverse$1."<init>":(Lscala/collection/generic/SequenceTemplate;Lscala/runtime/ObjectRef;)V
const #446 = NameAndType	#14:#116;//  elem:Ljava/lang/Object;
const #447 = Field	#320.#446;	//  scala/runtime/ObjectRef.elem:Ljava/lang/Object;
const #448 = Asciz	scala/collection/immutable/List;
const #449 = class	#448;	//  scala/collection/immutable/List
const #450 = Asciz	scala/collection/generic/SequenceTemplate$$anonfun$reverse$2;
const #451 = class	#450;	//  scala/collection/generic/SequenceTemplate$$anonfun$reverse$2
const #452 = Asciz	(Lscala/collection/generic/SequenceTemplate;Lscala/collection/generic/Builder;)V;
const #453 = NameAndType	#160:#452;//  "<init>":(Lscala/collection/generic/SequenceTemplate;Lscala/collection/generic/Builder;)V
const #454 = Method	#451.#453;	//  scala/collection/generic/SequenceTemplate$$anonfun$reverse$2."<init>":(Lscala/collection/generic/SequenceTemplate;Lscala/collection/generic/Builder;)V
const #455 = Asciz	scala/collection/generic/LinearSequenceTemplate;
const #456 = class	#455;	//  scala/collection/generic/LinearSequenceTemplate
const #457 = InterfaceMethod	#456.#339;	//  scala/collection/generic/LinearSequenceTemplate.foreach:(Lscala/Function1;)V
const #458 = Asciz	xs$1;
const #459 = Asciz	b$2;
const #460 = Asciz	(Lscala/collection/generic/SequenceTemplate;Lscala/Function1;I)I;
const #461 = Asciz	scala/Function1;
const #462 = class	#461;	//  scala/Function1
const #463 = Asciz	(Ljava/lang/Object;)Ljava/lang/Object;;
const #464 = NameAndType	#53:#463;//  apply:(Ljava/lang/Object;)Ljava/lang/Object;
const #465 = InterfaceMethod	#462.#464;	//  scala/Function1.apply:(Ljava/lang/Object;)Ljava/lang/Object;
const #466 = Asciz	end;
const #467 = Asciz	it;
const #468 = Asciz	(Lscala/Function1;I)I;
const #469 = NameAndType	#84:#468;//  lastIndexWhere:(Lscala/Function1;I)I
const #470 = InterfaceMethod	#21.#469;	//  scala/collection/generic/SequenceTemplate.lastIndexWhere:(Lscala/Function1;I)I
const #471 = Asciz	lastIndexOf;
const #472 = Asciz	(Lscala/collection/generic/SequenceTemplate;Ljava/lang/Object;I)I;
const #473 = Asciz	scala/collection/generic/SequenceTemplate$$anonfun$lastIndexOf$2;
const #474 = class	#473;	//  scala/collection/generic/SequenceTemplate$$anonfun$lastIndexOf$2
const #475 = Method	#474.#392;	//  scala/collection/generic/SequenceTemplate$$anonfun$lastIndexOf$2."<init>":(Lscala/collection/generic/SequenceTemplate;Ljava/lang/Object;)V
const #476 = Asciz	elem$3;
const #477 = Asciz	(Lscala/collection/generic/SequenceTemplate;Ljava/lang/Object;)I;
const #478 = Asciz	scala/collection/generic/SequenceTemplate$$anonfun$lastIndexOf$1;
const #479 = class	#478;	//  scala/collection/generic/SequenceTemplate$$anonfun$lastIndexOf$1
const #480 = Method	#479.#392;	//  scala/collection/generic/SequenceTemplate$$anonfun$lastIndexOf$1."<init>":(Lscala/collection/generic/SequenceTemplate;Ljava/lang/Object;)V
const #481 = Asciz	elem$4;
const #482 = Asciz	scala/collection/generic/SequenceTemplate$$anonfun$indexOf$1;
const #483 = class	#482;	//  scala/collection/generic/SequenceTemplate$$anonfun$indexOf$1
const #484 = Method	#483.#392;	//  scala/collection/generic/SequenceTemplate$$anonfun$indexOf$1."<init>":(Lscala/collection/generic/SequenceTemplate;Ljava/lang/Object;)V
const #485 = Asciz	indexWhere;
const #486 = NameAndType	#485:#468;//  indexWhere:(Lscala/Function1;I)I
const #487 = InterfaceMethod	#21.#486;	//  scala/collection/generic/SequenceTemplate.indexWhere:(Lscala/Function1;I)I
const #488 = Asciz	elem$2;
const #489 = Asciz	(Ljava/lang/Object;I)I;
const #490 = NameAndType	#200:#489;//  indexOf:(Ljava/lang/Object;I)I
const #491 = InterfaceMethod	#21.#490;	//  scala/collection/generic/SequenceTemplate.indexOf:(Ljava/lang/Object;I)I
const #492 = Asciz	findIndexOf;
const #493 = NameAndType	#485:#85;//  indexWhere:(Lscala/Function1;)I
const #494 = InterfaceMethod	#21.#493;	//  scala/collection/generic/SequenceTemplate.indexWhere:(Lscala/Function1;)I
const #495 = Asciz	scala/collection/Traversable$;
const #496 = class	#495;	//  scala/collection/Traversable$
const #497 = Asciz	Lscala/collection/Traversable$;;
const #498 = NameAndType	#101:#497;//  MODULE$:Lscala/collection/Traversable$;
const #499 = Field	#496.#498;	//  scala/collection/Traversable$.MODULE$:Lscala/collection/Traversable$;
const #500 = Asciz	breaks;
const #501 = Asciz	()Lscala/util/control/Breaks;;
const #502 = NameAndType	#500:#501;//  breaks:()Lscala/util/control/Breaks;
const #503 = Method	#496.#502;	//  scala/collection/Traversable$.breaks:()Lscala/util/control/Breaks;
const #504 = Asciz	scala/collection/generic/SequenceTemplate$$anonfun$indexWhere$1;
const #505 = class	#504;	//  scala/collection/generic/SequenceTemplate$$anonfun$indexWhere$1
const #506 = Asciz	(Lscala/collection/generic/SequenceTemplate;Lscala/Function1;ILscala/runtime/IntRef;Lscala/runtime/IntRef;)V;
const #507 = NameAndType	#160:#506;//  "<init>":(Lscala/collection/generic/SequenceTemplate;Lscala/Function1;ILscala/runtime/IntRef;Lscala/runtime/IntRef;)V
const #508 = Method	#505.#507;	//  scala/collection/generic/SequenceTemplate$$anonfun$indexWhere$1."<init>":(Lscala/collection/generic/SequenceTemplate;Lscala/Function1;ILscala/runtime/IntRef;Lscala/runtime/IntRef;)V
const #509 = Asciz	scala/util/control/Breaks;
const #510 = class	#509;	//  scala/util/control/Breaks
const #511 = Asciz	breakable;
const #512 = Asciz	(Lscala/Function0;)V;
const #513 = NameAndType	#511:#512;//  breakable:(Lscala/Function0;)V
const #514 = Method	#510.#513;	//  scala/util/control/Breaks.breakable:(Lscala/Function0;)V
const #515 = Asciz	p$2;
const #516 = Asciz	from$2;
const #517 = Asciz	result$2;
const #518 = Asciz	i$4;
const #519 = Asciz	prefixLength;
const #520 = Asciz	segmentLength;
const #521 = NameAndType	#520:#468;//  segmentLength:(Lscala/Function1;I)I
const #522 = InterfaceMethod	#21.#521;	//  scala/collection/generic/SequenceTemplate.segmentLength:(Lscala/Function1;I)I
const #523 = Asciz	scala/collection/generic/SequenceTemplate$$anonfun$segmentLength$1;
const #524 = class	#523;	//  scala/collection/generic/SequenceTemplate$$anonfun$segmentLength$1
const #525 = Method	#524.#507;	//  scala/collection/generic/SequenceTemplate$$anonfun$segmentLength$1."<init>":(Lscala/collection/generic/SequenceTemplate;Lscala/Function1;ILscala/runtime/IntRef;Lscala/runtime/IntRef;)V
const #526 = Asciz	p$1;
const #527 = Asciz	from$1;
const #528 = Asciz	result$1;
const #529 = Asciz	i$3;
const #530 = Asciz	zipWithIndex;
const #531 = Asciz	(Lscala/collection/generic/SequenceTemplate;Lscala/collection/generic/BuilderFactory;)Ljava/lang/Object;;
const #532 = Asciz	scala/collection/generic/SequenceTemplate$$anonfun$zipWithIndex$1;
const #533 = class	#532;	//  scala/collection/generic/SequenceTemplate$$anonfun$zipWithIndex$1
const #534 = Asciz	(Lscala/collection/generic/SequenceTemplate;Lscala/collection/generic/Builder;Lscala/runtime/IntRef;)V;
const #535 = NameAndType	#160:#534;//  "<init>":(Lscala/collection/generic/SequenceTemplate;Lscala/collection/generic/Builder;Lscala/runtime/IntRef;)V
const #536 = Method	#533.#535;	//  scala/collection/generic/SequenceTemplate$$anonfun$zipWithIndex$1."<init>":(Lscala/collection/generic/SequenceTemplate;Lscala/collection/generic/Builder;Lscala/runtime/IntRef;)V
const #537 = Asciz	b$1;
const #538 = Asciz	i$2;
const #539 = Asciz	zipAll;
const #540 = Asciz	(Lscala/collection/generic/SequenceTemplate;Lscala/collection/Sequence;Ljava/lang/Object;Ljava/lang/Object;Lscala/collection/generic/BuilderFactory;)Ljava/lang/Object;;
const #541 = Asciz	thisElem;
const #542 = Asciz	thatElem;
const #543 = Asciz	these;
const #544 = Asciz	those;
const #545 = Asciz	zip;
const #546 = Asciz	isDefinedAt;
const #547 = Asciz	(Lscala/collection/generic/SequenceTemplate;I)Z;
const #548 = Asciz	size;
const #549 = Asciz	(Lscala/collection/generic/SequenceTemplate;)I;
const #550 = Asciz	lengthCompare;
const #551 = Asciz	(Lscala/collection/generic/SequenceTemplate;I)I;
const #552 = Asciz	scala/collection/generic/SequenceTemplate$$anonfun$lengthCompare$1;
const #553 = class	#552;	//  scala/collection/generic/SequenceTemplate$$anonfun$lengthCompare$1
const #554 = Asciz	(Lscala/collection/generic/SequenceTemplate;ILscala/runtime/IntRef;)V;
const #555 = NameAndType	#160:#554;//  "<init>":(Lscala/collection/generic/SequenceTemplate;ILscala/runtime/IntRef;)V
const #556 = Method	#553.#555;	//  scala/collection/generic/SequenceTemplate$$anonfun$lengthCompare$1."<init>":(Lscala/collection/generic/SequenceTemplate;ILscala/runtime/IntRef;)V
const #557 = Asciz	len$1;
const #558 = Asciz	i$1;
const #559 = Asciz	Scala;
const #560 = Asciz	InnerClasses;
const #561 = Asciz	$anon$1;
const #562 = Asciz	$anon$2;
const #563 = Asciz	$anon$3;
const #564 = Asciz	$anonfun$diff$1;
const #565 = Asciz	$anonfun$reverse$2;
const #566 = Asciz	$anonfun$indexOf$1;
const #567 = Asciz	$anonfun$reverse$1;
const #568 = Asciz	$anonfun$contains$1;
const #569 = Asciz	$anonfun$intersect$1;
const #570 = Asciz	$anonfun$occCounts$1;
const #571 = Asciz	$anonfun$indexWhere$1;
const #572 = Asciz	$anonfun$lastIndexOf$1;
const #573 = Asciz	$anonfun$lastIndexOf$2;
const #574 = Asciz	$anonfun$zipWithIndex$1;
const #575 = Asciz	$anonfun$segmentLength$1;
const #576 = Asciz	$anonfun$lengthCompare$1;
const #577 = Asciz	$anonfun$removeDuplicates$1;

{
public static void $init$(scala.collection.generic.SequenceTemplate);
  Code:
   Stack=0, Locals=1, Args_size=1
   0:	return
  LineNumberTable: 
   line 32: 0

  LocalVariableTable: 
   Start  Length  Slot  Name   Signature
   0      1      0    $this       Lscala/collection/generic/SequenceTemplate;


public static java.lang.Object projection(scala.collection.generic.SequenceTemplate);
  Code:
   Stack=1, Locals=1, Args_size=1
   0:	aload_0
   1:	invokeinterface	#25,  1; //InterfaceMethod scala/collection/generic/SequenceTemplate.view:()Ljava/lang/Object;
   6:	areturn
  LineNumberTable: 
   line 615: 0

  LocalVariableTable: 
   Start  Length  Slot  Name   Signature
   0      7      0    $this       Lscala/collection/generic/SequenceTemplate;


public static boolean containsSlice(scala.collection.generic.SequenceTemplate, scala.collection.Sequence);
  Code:
   Stack=2, Locals=2, Args_size=2
   0:	aload_0
   1:	aload_1
   2:	invokeinterface	#31,  2; //InterfaceMethod scala/collection/generic/SequenceTemplate.indexOfSeq:(Lscala/collection/Sequence;)I
   7:	iconst_m1
   8:	if_icmpeq	15
   11:	iconst_1
   12:	goto	16
   15:	iconst_0
   16:	ireturn
  LineNumberTable: 
   line 607: 0

  LocalVariableTable: 
   Start  Length  Slot  Name   Signature
   0      17      0    $this       Lscala/collection/generic/SequenceTemplate;
   0      17      1    that       Lscala/collection/Sequence;


public static boolean equalsWith(scala.collection.generic.SequenceTemplate, scala.collection.Sequence, scala.Function2);
  Code:
   Stack=3, Locals=5, Args_size=3
   0:	aload_0
   1:	invokeinterface	#41,  1; //InterfaceMethod scala/collection/generic/IterableTemplate.iterator:()Lscala/collection/Iterator;
   6:	astore_3
   7:	aload_1
   8:	invokeinterface	#41,  1; //InterfaceMethod scala/collection/generic/IterableTemplate.iterator:()Lscala/collection/Iterator;
   13:	astore	4
   15:	aload_3
   16:	invokeinterface	#47,  1; //InterfaceMethod scala/collection/Iterator.hasNext:()Z
   21:	ifeq	61
   24:	aload	4
   26:	invokeinterface	#47,  1; //InterfaceMethod scala/collection/Iterator.hasNext:()Z
   31:	ifeq	61
   34:	aload_2
   35:	aload_3
   36:	invokeinterface	#50,  1; //InterfaceMethod scala/collection/Iterator.next:()Ljava/lang/Object;
   41:	aload	4
   43:	invokeinterface	#50,  1; //InterfaceMethod scala/collection/Iterator.next:()Ljava/lang/Object;
   48:	invokeinterface	#56,  3; //InterfaceMethod scala/Function2.apply:(Ljava/lang/Object;Ljava/lang/Object;)Ljava/lang/Object;
   53:	invokestatic	#62; //Method scala/runtime/BoxesRunTime.unboxToBoolean:(Ljava/lang/Object;)Z
   56:	ifne	15
   59:	iconst_0
   60:	ireturn
   61:	aload_3
   62:	invokeinterface	#47,  1; //InterfaceMethod scala/collection/Iterator.hasNext:()Z
   67:	ifne	80
   70:	aload	4
   72:	invokeinterface	#47,  1; //InterfaceMethod scala/collection/Iterator.hasNext:()Z
   77:	ifeq	84
   80:	iconst_0
   81:	goto	85
   84:	iconst_1
   85:	ireturn
  LineNumberTable: 
   line 596: 0
   line 597: 7
   line 598: 15
   line 599: 34
   line 600: 59
   line 602: 61
   line 595: 85

  LocalVariableTable: 
   Start  Length  Slot  Name   Signature
   0      86      0    $this       Lscala/collection/generic/SequenceTemplate;
   0      86      1    that       Lscala/collection/Sequence;
   0      86      2    f       Lscala/Function2;
   7      79      3    i       Lscala/collection/Iterator;
   15      71      4    j       Lscala/collection/Iterator;


public static scala.collection.Sequence slice(scala.collection.generic.SequenceTemplate, int);
  Code:
   Stack=3, Locals=2, Args_size=2
   0:	aload_0
   1:	iload_1
   2:	aload_0
   3:	invokeinterface	#73,  1; //InterfaceMethod scala/collection/generic/SequenceTemplate.length:()I
   8:	invokeinterface	#78,  3; //InterfaceMethod scala/collection/generic/TraversableTemplate.slice:(II)Lscala/collection/generic/TraversableTemplate;
   13:	checkcast	#80; //class scala/collection/Sequence
   16:	areturn
  LineNumberTable: 
   line 592: 0

  LocalVariableTable: 
   Start  Length  Slot  Name   Signature
   0      17      0    $this       Lscala/collection/generic/SequenceTemplate;
   0      17      1    from       I


public static int findLastIndexOf(scala.collection.generic.SequenceTemplate, scala.Function1);
  Code:
   Stack=2, Locals=2, Args_size=2
   0:	aload_0
   1:	aload_1
   2:	invokeinterface	#87,  2; //InterfaceMethod scala/collection/generic/SequenceTemplate.lastIndexWhere:(Lscala/Function1;)I
   7:	ireturn
  LineNumberTable: 
   line 583: 0

  LocalVariableTable: 
   Start  Length  Slot  Name   Signature
   0      8      0    $this       Lscala/collection/generic/SequenceTemplate;
   0      8      1    p       Lscala/Function1;


public static java.lang.String toString(scala.collection.generic.SequenceTemplate);
  Code:
   Stack=1, Locals=1, Args_size=1
   0:	aload_0
   1:	invokestatic	#96; //Method scala/collection/generic/TraversableTemplate$class.toString:(Lscala/collection/generic/TraversableTemplate;)Ljava/lang/String;
   4:	areturn
  LineNumberTable: 
   line 579: 0

  LocalVariableTable: 
   Start  Length  Slot  Name   Signature
   0      5      0    $this       Lscala/collection/generic/SequenceTemplate;


public static boolean equals(scala.collection.generic.SequenceTemplate, java.lang.Object);
  Code:
   Stack=2, Locals=6, Args_size=2
   0:	aload_1
   1:	astore_2
   2:	aload_2
   3:	astore_3
   4:	aload_3
   5:	instanceof	#80; //class scala/collection/Sequence
   8:	ifne	21
   11:	getstatic	#104; //Field scala/runtime/ScalaRunTime$.MODULE$:Lscala/runtime/ScalaRunTime$;
   14:	aload_3
   15:	invokevirtual	#107; //Method scala/runtime/ScalaRunTime$.isArray:(Ljava/lang/Object;)Z
   18:	ifeq	25
   21:	iconst_1
   22:	goto	26
   25:	iconst_0
   26:	ifeq	69
   29:	aload_2
   30:	astore	5
   32:	aload	5
   34:	instanceof	#80; //class scala/collection/Sequence
   37:	ifeq	45
   40:	aload	5
   42:	goto	53
   45:	getstatic	#104; //Field scala/runtime/ScalaRunTime$.MODULE$:Lscala/runtime/ScalaRunTime$;
   48:	aload	5
   50:	invokevirtual	#111; //Method scala/runtime/ScalaRunTime$.boxArray:(Ljava/lang/Object;)Lscala/runtime/BoxedArray;
   53:	checkcast	#80; //class scala/collection/Sequence
   56:	astore	4
   58:	aload_0
   59:	aload	4
   61:	invokeinterface	#115,  2; //InterfaceMethod scala/collection/generic/IterableTemplate.sameElements:(Lscala/collection/Iterable;)Z
   66:	goto	70
   69:	iconst_0
   70:	ireturn
  LineNumberTable: 
   line 572: 0
   line 574: 53
   line 572: 56
   line 573: 58
   line 574: 69
   line 572: 70

  LocalVariableTable: 
   Start  Length  Slot  Name   Signature
   0      71      0    $this       Lscala/collection/generic/SequenceTemplate;
   0      71      1    that       Ljava/lang/Object;
   2      69      2    temp13       Ljava/lang/Object;
   58      8      4    temp14       Lscala/collection/Sequence;


public static scala.collection.generic.SequenceView view(scala.collection.generic.SequenceTemplate, int, int);
  Code:
   Stack=3, Locals=3, Args_size=3
   0:	aload_0
   1:	invokeinterface	#25,  1; //InterfaceMethod scala/collection/generic/SequenceTemplate.view:()Ljava/lang/Object;
   6:	checkcast	#225; //class scala/collection/generic/TraversableViewTemplate
   9:	iload_1
   10:	iload_2
   11:	invokeinterface	#228,  3; //InterfaceMethod scala/collection/generic/TraversableViewTemplate.slice:(II)Lscala/collection/generic/TraversableView;
   16:	checkcast	#230; //class scala/collection/generic/SequenceView
   19:	areturn
  LineNumberTable: 
   line 499: 0

  LocalVariableTable: 
   Start  Length  Slot  Name   Signature
   0      20      0    $this       Lscala/collection/generic/SequenceTemplate;
   0      20      1    from       I
   0      20      2    until       I


public static java.lang.Object view(scala.collection.generic.SequenceTemplate);
  Code:
   Stack=3, Locals=1, Args_size=1
   0:	new	#233; //class scala/collection/generic/SequenceTemplate$$anon$3
   3:	dup
   4:	aload_0
   5:	invokespecial	#235; //Method scala/collection/generic/SequenceTemplate$$anon$3."<init>":(Lscala/collection/generic/SequenceTemplate;)V
   8:	areturn
  LineNumberTable: 
   line 492: 0

  LocalVariableTable: 
   Start  Length  Slot  Name   Signature
   0      9      0    $this       Lscala/collection/generic/SequenceTemplate;


public static scala.Range indices(scala.collection.generic.SequenceTemplate);
  Code:
   Stack=2, Locals=1, Args_size=1
   0:	getstatic	#242; //Field scala/Predef$.MODULE$:Lscala/Predef$;
   3:	iconst_0
   4:	invokevirtual	#246; //Method scala/Predef$.intWrapper:(I)Lscala/runtime/RichInt;
   7:	aload_0
   8:	invokeinterface	#73,  1; //InterfaceMethod scala/collection/generic/SequenceTemplate.length:()I
   13:	invokevirtual	#251; //Method scala/runtime/RichInt.until:(I)Lscala/Range;
   16:	areturn
  LineNumberTable: 
   line 490: 0

  LocalVariableTable: 
   Start  Length  Slot  Name   Signature
   0      17      0    $this       Lscala/collection/generic/SequenceTemplate;


public static scala.collection.Sequence toSequence(scala.collection.generic.SequenceTemplate);
  Code:
   Stack=1, Locals=1, Args_size=1
   0:	aload_0
   1:	invokeinterface	#257,  1; //InterfaceMethod scala/collection/generic/TraversableTemplate.thisCollection:()Lscala/collection/generic/TraversableTemplate;
   6:	checkcast	#80; //class scala/collection/Sequence
   9:	areturn
  LineNumberTable: 
   line 488: 0

  LocalVariableTable: 
   Start  Length  Slot  Name   Signature
   0      10      0    $this       Lscala/collection/generic/SequenceTemplate;


public static java.lang.Object padTo(scala.collection.generic.SequenceTemplate, int, java.lang.Object, scala.collection.generic.BuilderFactory);
  Code:
   Stack=2, Locals=6, Args_size=4
   0:	aload_3
   1:	aload_0
   2:	invokeinterface	#257,  1; //InterfaceMethod scala/collection/generic/TraversableTemplate.thisCollection:()Lscala/collection/generic/TraversableTemplate;
   7:	invokeinterface	#264,  2; //InterfaceMethod scala/collection/generic/BuilderFactory.apply:(Ljava/lang/Object;)Lscala/collection/generic/Builder;
   12:	astore	4
   14:	iload_1
   15:	aload_0
   16:	invokeinterface	#73,  1; //InterfaceMethod scala/collection/generic/SequenceTemplate.length:()I
   21:	isub
   22:	istore	5
   24:	aload	4
   26:	aload_0
   27:	invokeinterface	#257,  1; //InterfaceMethod scala/collection/generic/TraversableTemplate.thisCollection:()Lscala/collection/generic/TraversableTemplate;
   32:	checkcast	#266; //class scala/collection/Traversable
   35:	invokeinterface	#272,  2; //InterfaceMethod scala/collection/generic/Growable.$plus$plus$eq:(Lscala/collection/Traversable;)Lscala/collection/generic/Growable;
   40:	pop
   41:	iload	5
   43:	iconst_0
   44:	if_icmple	65
   47:	aload	4
   49:	aload_2
   50:	invokeinterface	#277,  2; //InterfaceMethod scala/collection/generic/Builder.$plus$eq:(Ljava/lang/Object;)Lscala/collection/generic/Builder;
   55:	pop
   56:	iload	5
   58:	iconst_1
   59:	isub
   60:	istore	5
   62:	goto	41
   65:	aload	4
   67:	invokeinterface	#280,  1; //InterfaceMethod scala/collection/generic/Builder.result:()Ljava/lang/Object;
   72:	areturn
  LineNumberTable: 
   line 473: 0
   line 474: 14
   line 475: 24
   line 476: 41
   line 477: 47
   line 478: 56
   line 476: 62
   line 480: 65

  LocalVariableTable: 
   Start  Length  Slot  Name   Signature
   0      73      0    $this       Lscala/collection/generic/SequenceTemplate;
   0      73      1    len       I
   0      73      2    elem       Ljava/lang/Object;
   0      73      3    bf       Lscala/collection/generic/BuilderFactory;
   14      58      4    b       Lscala/collection/generic/Builder;
   24      48      5    diff       I


public static java.lang.Object patch(scala.collection.generic.SequenceTemplate, int, scala.collection.Sequence, int, scala.collection.generic.BuilderFactory);
  Code:
   Stack=4, Locals=15, Args_size=5
   0:	aload	4
   2:	aload_0
   3:	invokeinterface	#257,  1; //InterfaceMethod scala/collection/generic/TraversableTemplate.thisCollection:()Lscala/collection/generic/TraversableTemplate;
   8:	invokeinterface	#264,  2; //InterfaceMethod scala/collection/generic/BuilderFactory.apply:(Ljava/lang/Object;)Lscala/collection/generic/Builder;
   13:	astore	5
   15:	aload_0
   16:	iload_1
   17:	invokeinterface	#292,  2; //InterfaceMethod scala/collection/generic/TraversableTemplate.splitAt:(I)Lscala/Tuple2;
   22:	astore	7
   24:	aload	7
   26:	ifnull	231
   29:	aload	7
   31:	invokevirtual	#297; //Method scala/Tuple2._1:()Ljava/lang/Object;
   34:	astore	9
   36:	aload	9
   38:	instanceof	#37; //class scala/collection/generic/IterableTemplate
   41:	ifeq	49
   44:	aload	9
   46:	goto	57
   49:	getstatic	#104; //Field scala/runtime/ScalaRunTime$.MODULE$:Lscala/runtime/ScalaRunTime$;
   52:	aload	9
   54:	invokevirtual	#111; //Method scala/runtime/ScalaRunTime$.boxArray:(Ljava/lang/Object;)Lscala/runtime/BoxedArray;
   57:	checkcast	#37; //class scala/collection/generic/IterableTemplate
   60:	astore	8
   62:	aload	7
   64:	invokevirtual	#300; //Method scala/Tuple2._2:()Ljava/lang/Object;
   67:	astore	11
   69:	aload	11
   71:	instanceof	#37; //class scala/collection/generic/IterableTemplate
   74:	ifeq	82
   77:	aload	11
   79:	goto	90
   82:	getstatic	#104; //Field scala/runtime/ScalaRunTime$.MODULE$:Lscala/runtime/ScalaRunTime$;
   85:	aload	11
   87:	invokevirtual	#111; //Method scala/runtime/ScalaRunTime$.boxArray:(Ljava/lang/Object;)Lscala/runtime/BoxedArray;
   90:	checkcast	#37; //class scala/collection/generic/IterableTemplate
   93:	astore	10
   95:	aload	10
   97:	astore	12
   99:	new	#294; //class scala/Tuple2
   102:	dup
   103:	aload	8
   105:	aload	12
   107:	invokespecial	#303; //Method scala/Tuple2."<init>":(Ljava/lang/Object;Ljava/lang/Object;)V
   110:	astore	6
   112:	aload	6
   114:	invokevirtual	#297; //Method scala/Tuple2._1:()Ljava/lang/Object;
   117:	instanceof	#37; //class scala/collection/generic/IterableTemplate
   120:	ifeq	131
   123:	aload	6
   125:	invokevirtual	#297; //Method scala/Tuple2._1:()Ljava/lang/Object;
   128:	goto	142
   131:	getstatic	#104; //Field scala/runtime/ScalaRunTime$.MODULE$:Lscala/runtime/ScalaRunTime$;
   134:	aload	6
   136:	invokevirtual	#297; //Method scala/Tuple2._1:()Ljava/lang/Object;
   139:	invokevirtual	#111; //Method scala/runtime/ScalaRunTime$.boxArray:(Ljava/lang/Object;)Lscala/runtime/BoxedArray;
   142:	checkcast	#37; //class scala/collection/generic/IterableTemplate
   145:	astore	13
   147:	aload	6
   149:	invokevirtual	#300; //Method scala/Tuple2._2:()Ljava/lang/Object;
   152:	instanceof	#37; //class scala/collection/generic/IterableTemplate
   155:	ifeq	166
   158:	aload	6
   160:	invokevirtual	#300; //Method scala/Tuple2._2:()Ljava/lang/Object;
   163:	goto	177
   166:	getstatic	#104; //Field scala/runtime/ScalaRunTime$.MODULE$:Lscala/runtime/ScalaRunTime$;
   169:	aload	6
   171:	invokevirtual	#300; //Method scala/Tuple2._2:()Ljava/lang/Object;
   174:	invokevirtual	#111; //Method scala/runtime/ScalaRunTime$.boxArray:(Ljava/lang/Object;)Lscala/runtime/BoxedArray;
   177:	checkcast	#37; //class scala/collection/generic/IterableTemplate
   180:	astore	14
   182:	aload	5
   184:	aload	13
   186:	checkcast	#266; //class scala/collection/Traversable
   189:	invokeinterface	#272,  2; //InterfaceMethod scala/collection/generic/Growable.$plus$plus$eq:(Lscala/collection/Traversable;)Lscala/collection/generic/Growable;
   194:	pop
   195:	aload	5
   197:	aload_2
   198:	invokeinterface	#272,  2; //InterfaceMethod scala/collection/generic/Growable.$plus$plus$eq:(Lscala/collection/Traversable;)Lscala/collection/generic/Growable;
   203:	pop
   204:	aload	5
   206:	aload	14
   208:	iload_3
   209:	invokeinterface	#183,  2; //InterfaceMethod scala/collection/generic/TraversableTemplate.drop:(I)Lscala/collection/generic/TraversableTemplate;
   214:	checkcast	#266; //class scala/collection/Traversable
   217:	invokeinterface	#272,  2; //InterfaceMethod scala/collection/generic/Growable.$plus$plus$eq:(Lscala/collection/Traversable;)Lscala/collection/generic/Growable;
   222:	pop
   223:	aload	5
   225:	invokeinterface	#280,  1; //InterfaceMethod scala/collection/generic/Builder.result:()Ljava/lang/Object;
   230:	areturn
   231:	new	#154; //class scala/MatchError
   234:	dup
   235:	aload	7
   237:	invokevirtual	#304; //Method scala/Tuple2.toString:()Ljava/lang/String;
   240:	invokespecial	#163; //Method scala/MatchError."<init>":(Ljava/lang/String;)V
   243:	athrow
  LineNumberTable: 
   line 461: 0
   line 462: 15
   line 463: 182
   line 464: 195
   line 465: 204
   line 466: 223
   line 462: 231

  LocalVariableTable: 
   Start  Length  Slot  Name   Signature
   0      244      0    $this       Lscala/collection/generic/SequenceTemplate;
   0      244      1    from       I
   0      244      2    patch       Lscala/collection/Sequence;
   0      244      3    replaced       I
   0      244      4    bf       Lscala/collection/generic/BuilderFactory;
   15      215      5    b       Lscala/collection/generic/Builder;
   231      13      5    b       Lscala/collection/generic/Builder;
   24      99      7    temp1       Lscala/Tuple2;
   231      13      7    temp1       Lscala/Tuple2;
   62      48      8    temp2       Lscala/collection/generic/IterableTemplate;
   95      15      10    temp3       Lscala/collection/generic/IterableTemplate;
   99      11      12    rest       Lscala/collection/generic/IterableTemplate;
   147      83      13    prefix       Lscala/collection/generic/IterableTemplate;
   182      48      14    rest       Lscala/collection/generic/IterableTemplate;


public static scala.collection.generic.IterableTemplate removeDuplicates(scala.collection.generic.SequenceTemplate);
  Code:
   Stack=6, Locals=4, Args_size=1
   0:	aload_0
   1:	invokeinterface	#318,  1; //InterfaceMethod scala/collection/generic/TraversableTemplate.newBuilder:()Lscala/collection/generic/Builder;
   6:	astore_1
   7:	new	#320; //class scala/runtime/ObjectRef
   10:	dup
   11:	getstatic	#325; //Field scala/collection/Set$.MODULE$:Lscala/collection/Set$;
   14:	getstatic	#104; //Field scala/runtime/ScalaRunTime$.MODULE$:Lscala/runtime/ScalaRunTime$;
   17:	iconst_0
   18:	anewarray	#141; //class java/lang/Object
   21:	invokevirtual	#111; //Method scala/runtime/ScalaRunTime$.boxArray:(Ljava/lang/Object;)Lscala/runtime/BoxedArray;
   24:	invokevirtual	#328; //Method scala/collection/Set$.apply:(Lscala/collection/Sequence;)Lscala/collection/Traversable;
   27:	checkcast	#330; //class scala/collection/Set
   30:	invokespecial	#331; //Method scala/runtime/ObjectRef."<init>":(Ljava/lang/Object;)V
   33:	astore_2
   34:	aload_0
   35:	new	#333; //class scala/collection/generic/SequenceTemplate$$anonfun$removeDuplicates$1
   38:	dup
   39:	aload_0
   40:	aload_1
   41:	aload_2
   42:	invokespecial	#336; //Method scala/collection/generic/SequenceTemplate$$anonfun$removeDuplicates$1."<init>":(Lscala/collection/generic/SequenceTemplate;Lscala/collection/generic/Builder;Lscala/runtime/ObjectRef;)V
   45:	invokeinterface	#340,  2; //InterfaceMethod scala/collection/generic/IterableTemplate.foreach:(Lscala/Function1;)V
   50:	aload_1
   51:	invokeinterface	#280,  1; //InterfaceMethod scala/collection/generic/Builder.result:()Ljava/lang/Object;
   56:	astore_3
   57:	aload_3
   58:	instanceof	#37; //class scala/collection/generic/IterableTemplate
   61:	ifeq	68
   64:	aload_3
   65:	goto	75
   68:	getstatic	#104; //Field scala/runtime/ScalaRunTime$.MODULE$:Lscala/runtime/ScalaRunTime$;
   71:	aload_3
   72:	invokevirtual	#111; //Method scala/runtime/ScalaRunTime$.boxArray:(Ljava/lang/Object;)Lscala/runtime/BoxedArray;
   75:	checkcast	#37; //class scala/collection/generic/IterableTemplate
   78:	areturn
  LineNumberTable: 
   line 445: 0
   line 446: 7
   line 447: 34
   line 453: 50

  LocalVariableTable: 
   Start  Length  Slot  Name   Signature
   0      79      0    $this       Lscala/collection/generic/SequenceTemplate;
   7      71      1    b$5       Lscala/collection/generic/Builder;
   34      44      2    seen$1       Lscala/runtime/ObjectRef;


public static scala.collection.generic.IterableTemplate intersect(scala.collection.generic.SequenceTemplate, scala.collection.Sequence);
  Code:
   Stack=6, Locals=5, Args_size=2
   0:	aload_0
   1:	aload_1
   2:	invokestatic	#369; //Method occCounts:(Lscala/collection/generic/SequenceTemplate;Lscala/collection/Sequence;)Lscala/collection/mutable/Map;
   5:	astore_2
   6:	aload_0
   7:	invokeinterface	#318,  1; //InterfaceMethod scala/collection/generic/TraversableTemplate.newBuilder:()Lscala/collection/generic/Builder;
   12:	astore_3
   13:	aload_0
   14:	new	#371; //class scala/collection/generic/SequenceTemplate$$anonfun$intersect$1
   17:	dup
   18:	aload_0
   19:	aload_2
   20:	aload_3
   21:	invokespecial	#374; //Method scala/collection/generic/SequenceTemplate$$anonfun$intersect$1."<init>":(Lscala/collection/generic/SequenceTemplate;Lscala/collection/mutable/Map;Lscala/collection/generic/Builder;)V
   24:	invokeinterface	#340,  2; //InterfaceMethod scala/collection/generic/IterableTemplate.foreach:(Lscala/Function1;)V
   29:	aload_3
   30:	invokeinterface	#280,  1; //InterfaceMethod scala/collection/generic/Builder.result:()Ljava/lang/Object;
   35:	astore	4
   37:	aload	4
   39:	instanceof	#37; //class scala/collection/generic/IterableTemplate
   42:	ifeq	50
   45:	aload	4
   47:	goto	58
   50:	getstatic	#104; //Field scala/runtime/ScalaRunTime$.MODULE$:Lscala/runtime/ScalaRunTime$;
   53:	aload	4
   55:	invokevirtual	#111; //Method scala/runtime/ScalaRunTime$.boxArray:(Ljava/lang/Object;)Lscala/runtime/BoxedArray;
   58:	checkcast	#37; //class scala/collection/generic/IterableTemplate
   61:	areturn
  LineNumberTable: 
   line 421: 0
   line 422: 6
   line 423: 13
   line 428: 29

  LocalVariableTable: 
   Start  Length  Slot  Name   Signature
   0      62      0    $this       Lscala/collection/generic/SequenceTemplate;
   0      62      1    that       Lscala/collection/Sequence;
   6      55      2    occ$2       Lscala/collection/mutable/Map;
   13      48      3    b$4       Lscala/collection/generic/Builder;


public static scala.collection.generic.IterableTemplate diff(scala.collection.generic.SequenceTemplate, scala.collection.Sequence);
  Code:
   Stack=6, Locals=5, Args_size=2
   0:	aload_0
   1:	aload_1
   2:	invokestatic	#369; //Method occCounts:(Lscala/collection/generic/SequenceTemplate;Lscala/collection/Sequence;)Lscala/collection/mutable/Map;
   5:	astore_2
   6:	aload_0
   7:	invokeinterface	#318,  1; //InterfaceMethod scala/collection/generic/TraversableTemplate.newBuilder:()Lscala/collection/generic/Builder;
   12:	astore_3
   13:	aload_0
   14:	new	#378; //class scala/collection/generic/SequenceTemplate$$anonfun$diff$1
   17:	dup
   18:	aload_0
   19:	aload_2
   20:	aload_3
   21:	invokespecial	#379; //Method scala/collection/generic/SequenceTemplate$$anonfun$diff$1."<init>":(Lscala/collection/generic/SequenceTemplate;Lscala/collection/mutable/Map;Lscala/collection/generic/Builder;)V
   24:	invokeinterface	#340,  2; //InterfaceMethod scala/collection/generic/IterableTemplate.foreach:(Lscala/Function1;)V
   29:	aload_3
   30:	invokeinterface	#280,  1; //InterfaceMethod scala/collection/generic/Builder.result:()Ljava/lang/Object;
   35:	astore	4
   37:	aload	4
   39:	instanceof	#37; //class scala/collection/generic/IterableTemplate
   42:	ifeq	50
   45:	aload	4
   47:	goto	58
   50:	getstatic	#104; //Field scala/runtime/ScalaRunTime$.MODULE$:Lscala/runtime/ScalaRunTime$;
   53:	aload	4
   55:	invokevirtual	#111; //Method scala/runtime/ScalaRunTime$.boxArray:(Ljava/lang/Object;)Lscala/runtime/BoxedArray;
   58:	checkcast	#37; //class scala/collection/generic/IterableTemplate
   61:	areturn
  LineNumberTable: 
   line 395: 0
   line 396: 6
   line 397: 13
   line 400: 29

  LocalVariableTable: 
   Start  Length  Slot  Name   Signature
   0      62      0    $this       Lscala/collection/generic/SequenceTemplate;
   0      62      1    that       Lscala/collection/Sequence;
   6      55      2    occ$1       Lscala/collection/mutable/Map;
   13      48      3    b$3       Lscala/collection/generic/Builder;


public static java.lang.Object union(scala.collection.generic.SequenceTemplate, scala.collection.Sequence, scala.collection.generic.BuilderFactory);
  Code:
   Stack=3, Locals=3, Args_size=3
   0:	aload_0
   1:	invokeinterface	#257,  1; //InterfaceMethod scala/collection/generic/TraversableTemplate.thisCollection:()Lscala/collection/generic/TraversableTemplate;
   6:	aload_1
   7:	aload_2
   8:	invokeinterface	#387,  3; //InterfaceMethod scala/collection/generic/TraversableTemplate.$plus$plus:(Lscala/collection/Traversable;Lscala/collection/generic/BuilderFactory;)Ljava/lang/Object;
   13:	areturn
  LineNumberTable: 
   line 373: 0

  LocalVariableTable: 
   Start  Length  Slot  Name   Signature
   0      14      0    $this       Lscala/collection/generic/SequenceTemplate;
   0      14      1    that       Lscala/collection/Sequence;
   0      14      2    bf       Lscala/collection/generic/BuilderFactory;


public static boolean contains(scala.collection.generic.SequenceTemplate, java.lang.Object);
  Code:
   Stack=5, Locals=2, Args_size=2
   0:	aload_0
   1:	new	#390; //class scala/collection/generic/SequenceTemplate$$anonfun$contains$1
   4:	dup
   5:	aload_0
   6:	aload_1
   7:	invokespecial	#393; //Method scala/collection/generic/SequenceTemplate$$anonfun$contains$1."<init>":(Lscala/collection/generic/SequenceTemplate;Ljava/lang/Object;)V
   10:	invokeinterface	#397,  2; //InterfaceMethod scala/collection/generic/TraversableTemplate.exists:(Lscala/Function1;)Z
   15:	ireturn
  LineNumberTable: 
   line 356: 0

  LocalVariableTable: 
   Start  Length  Slot  Name   Signature
   0      16      0    $this       Lscala/collection/generic/SequenceTemplate;
   0      16      1    elem$1       Ljava/lang/Object;


public static int lastIndexOfSeq(scala.collection.generic.SequenceTemplate, scala.collection.Sequence, int);
  Code:
   Stack=8, Locals=3, Args_size=3
   0:	aload_0
   1:	aload_0
   2:	invokeinterface	#257,  1; //InterfaceMethod scala/collection/generic/TraversableTemplate.thisCollection:()Lscala/collection/generic/TraversableTemplate;
   7:	checkcast	#80; //class scala/collection/Sequence
   10:	iconst_0
   11:	aload_0
   12:	invokeinterface	#73,  1; //InterfaceMethod scala/collection/generic/SequenceTemplate.length:()I
   17:	aload_1
   18:	iconst_0
   19:	aload_1
   20:	invokeinterface	#73,  1; //InterfaceMethod scala/collection/generic/SequenceTemplate.length:()I
   25:	iload_2
   26:	invokestatic	#402; //Method lastIndexOf_KMP:(Lscala/collection/generic/SequenceTemplate;Lscala/collection/Sequence;IILscala/collection/Sequence;III)I
   29:	ireturn
  LineNumberTable: 
   line 347: 0

  LocalVariableTable: 
   Start  Length  Slot  Name   Signature
   0      30      0    $this       Lscala/collection/generic/SequenceTemplate;
   0      30      1    that       Lscala/collection/Sequence;
   0      30      2    fromIndex       I


public static int lastIndexOfSeq(scala.collection.generic.SequenceTemplate, scala.collection.Sequence);
  Code:
   Stack=3, Locals=2, Args_size=2
   0:	aload_0
   1:	aload_1
   2:	aload_1
   3:	invokeinterface	#73,  1; //InterfaceMethod scala/collection/generic/SequenceTemplate.length:()I
   8:	invokeinterface	#406,  3; //InterfaceMethod scala/collection/generic/SequenceTemplate.lastIndexOfSeq:(Lscala/collection/Sequence;I)I
   13:	ireturn
  LineNumberTable: 
   line 342: 0

  LocalVariableTable: 
   Start  Length  Slot  Name   Signature
   0      14      0    $this       Lscala/collection/generic/SequenceTemplate;
   0      14      1    that       Lscala/collection/Sequence;


public static int indexOfSeq(scala.collection.generic.SequenceTemplate, scala.collection.Sequence, int);
  Code:
   Stack=8, Locals=5, Args_size=3
   0:	aload_0
   1:	invokeinterface	#257,  1; //InterfaceMethod scala/collection/generic/TraversableTemplate.thisCollection:()Lscala/collection/generic/TraversableTemplate;
   6:	invokeinterface	#409,  1; //InterfaceMethod scala/collection/generic/TraversableTemplate.hasDefiniteSize:()Z
   11:	ifeq	55
   14:	aload_1
   15:	invokeinterface	#409,  1; //InterfaceMethod scala/collection/generic/TraversableTemplate.hasDefiniteSize:()Z
   20:	ifeq	55
   23:	aload_0
   24:	aload_0
   25:	invokeinterface	#257,  1; //InterfaceMethod scala/collection/generic/TraversableTemplate.thisCollection:()Lscala/collection/generic/TraversableTemplate;
   30:	checkcast	#80; //class scala/collection/Sequence
   33:	iconst_0
   34:	aload_0
   35:	invokeinterface	#73,  1; //InterfaceMethod scala/collection/generic/SequenceTemplate.length:()I
   40:	aload_1
   41:	iconst_0
   42:	aload_1
   43:	invokeinterface	#73,  1; //InterfaceMethod scala/collection/generic/SequenceTemplate.length:()I
   48:	iload_2
   49:	invokestatic	#411; //Method indexOf_KMP:(Lscala/collection/generic/SequenceTemplate;Lscala/collection/Sequence;IILscala/collection/Sequence;III)I
   52:	goto	85
   55:	iload_2
   56:	istore_3
   57:	aload_0
   58:	invokeinterface	#257,  1; //InterfaceMethod scala/collection/generic/TraversableTemplate.thisCollection:()Lscala/collection/generic/TraversableTemplate;
   63:	iload_3
   64:	invokeinterface	#183,  2; //InterfaceMethod scala/collection/generic/TraversableTemplate.drop:(I)Lscala/collection/generic/TraversableTemplate;
   69:	checkcast	#80; //class scala/collection/Sequence
   72:	astore	4
   74:	aload	4
   76:	invokeinterface	#189,  1; //InterfaceMethod scala/collection/generic/IterableTemplate.isEmpty:()Z
   81:	ifeq	86
   84:	iconst_m1
   85:	ireturn
   86:	aload	4
   88:	aload_1
   89:	invokeinterface	#415,  2; //InterfaceMethod scala/collection/generic/SequenceTemplate.startsWith:(Lscala/collection/Sequence;)Z
   94:	ifeq	99
   97:	iload_3
   98:	ireturn
   99:	iload_3
   100:	iconst_1
   101:	iadd
   102:	istore_3
   103:	aload	4
   105:	invokeinterface	#418,  1; //InterfaceMethod scala/collection/generic/TraversableTemplate.tail:()Lscala/collection/generic/TraversableTemplate;
   110:	checkcast	#80; //class scala/collection/Sequence
   113:	astore	4
   115:	goto	74
  LineNumberTable: 
   line 323: 0
   line 324: 23
   line 326: 55
   line 327: 57
   line 328: 74
   line 335: 84
   line 323: 85
   line 329: 86
   line 330: 97
   line 332: 99
   line 333: 103
   line 328: 115

  LocalVariableTable: 
   Start  Length  Slot  Name   Signature
   0      118      0    $this       Lscala/collection/generic/SequenceTemplate;
   0      118      1    that       Lscala/collection/Sequence;
   0      118      2    fromIndex       I
   57      28      3    i       I
   86      32      3    i       I
   74      11      4    s       Lscala/collection/Sequence;
   86      32      4    s       Lscala/collection/Sequence;


public static int indexOfSeq(scala.collection.generic.SequenceTemplate, scala.collection.Sequence);
  Code:
   Stack=3, Locals=2, Args_size=2
   0:	aload_0
   1:	aload_1
   2:	iconst_0
   3:	invokeinterface	#421,  3; //InterfaceMethod scala/collection/generic/SequenceTemplate.indexOfSeq:(Lscala/collection/Sequence;I)I
   8:	ireturn
  LineNumberTable: 
   line 320: 0

  LocalVariableTable: 
   Start  Length  Slot  Name   Signature
   0      9      0    $this       Lscala/collection/generic/SequenceTemplate;
   0      9      1    that       Lscala/collection/Sequence;


public static boolean endsWith(scala.collection.generic.SequenceTemplate, scala.collection.Sequence);
  Code:
   Stack=3, Locals=4, Args_size=2
   0:	aload_0
   1:	invokeinterface	#41,  1; //InterfaceMethod scala/collection/generic/IterableTemplate.iterator:()Lscala/collection/Iterator;
   6:	aload_0
   7:	invokeinterface	#73,  1; //InterfaceMethod scala/collection/generic/SequenceTemplate.length:()I
   12:	aload_1
   13:	invokeinterface	#73,  1; //InterfaceMethod scala/collection/generic/SequenceTemplate.length:()I
   18:	isub
   19:	invokeinterface	#425,  2; //InterfaceMethod scala/collection/Iterator.drop:(I)Lscala/collection/Iterator;
   24:	astore_2
   25:	aload_1
   26:	invokeinterface	#41,  1; //InterfaceMethod scala/collection/generic/IterableTemplate.iterator:()Lscala/collection/Iterator;
   31:	astore_3
   32:	aload_2
   33:	invokeinterface	#47,  1; //InterfaceMethod scala/collection/Iterator.hasNext:()Z
   38:	ifeq	70
   41:	aload_3
   42:	invokeinterface	#47,  1; //InterfaceMethod scala/collection/Iterator.hasNext:()Z
   47:	ifeq	70
   50:	aload_2
   51:	invokeinterface	#50,  1; //InterfaceMethod scala/collection/Iterator.next:()Ljava/lang/Object;
   56:	aload_3
   57:	invokeinterface	#50,  1; //InterfaceMethod scala/collection/Iterator.next:()Ljava/lang/Object;
   62:	invokestatic	#205; //Method scala/runtime/BoxesRunTime.equals:(Ljava/lang/Object;Ljava/lang/Object;)Z
   65:	ifne	32
   68:	iconst_0
   69:	ireturn
   70:	aload_3
   71:	invokeinterface	#47,  1; //InterfaceMethod scala/collection/Iterator.hasNext:()Z
   76:	ifeq	83
   79:	iconst_0
   80:	goto	84
   83:	iconst_1
   84:	ireturn
  LineNumberTable: 
   line 308: 0
   line 309: 25
   line 310: 32
   line 311: 50
   line 312: 68
   line 314: 70
   line 307: 84

  LocalVariableTable: 
   Start  Length  Slot  Name   Signature
   0      85      0    $this       Lscala/collection/generic/SequenceTemplate;
   0      85      1    that       Lscala/collection/Sequence;
   25      60      2    i       Lscala/collection/Iterator;
   32      53      3    j       Lscala/collection/Iterator;


public static boolean startsWith(scala.collection.generic.SequenceTemplate, scala.collection.Sequence);
  Code:
   Stack=3, Locals=2, Args_size=2
   0:	aload_0
   1:	aload_1
   2:	iconst_0
   3:	invokeinterface	#428,  3; //InterfaceMethod scala/collection/generic/SequenceTemplate.startsWith:(Lscala/collection/Sequence;I)Z
   8:	ireturn
  LineNumberTable: 
   line 302: 0

  LocalVariableTable: 
   Start  Length  Slot  Name   Signature
   0      9      0    $this       Lscala/collection/generic/SequenceTemplate;
   0      9      1    that       Lscala/collection/Sequence;


public static boolean startsWith(scala.collection.generic.SequenceTemplate, scala.collection.Sequence, int);
  Code:
   Stack=2, Locals=5, Args_size=3
   0:	aload_0
   1:	invokeinterface	#41,  1; //InterfaceMethod scala/collection/generic/IterableTemplate.iterator:()Lscala/collection/Iterator;
   6:	iload_2
   7:	invokeinterface	#425,  2; //InterfaceMethod scala/collection/Iterator.drop:(I)Lscala/collection/Iterator;
   12:	astore_3
   13:	aload_1
   14:	invokeinterface	#41,  1; //InterfaceMethod scala/collection/generic/IterableTemplate.iterator:()Lscala/collection/Iterator;
   19:	astore	4
   21:	aload	4
   23:	invokeinterface	#47,  1; //InterfaceMethod scala/collection/Iterator.hasNext:()Z
   28:	ifeq	61
   31:	aload_3
   32:	invokeinterface	#47,  1; //InterfaceMethod scala/collection/Iterator.hasNext:()Z
   37:	ifeq	61
   40:	aload_3
   41:	invokeinterface	#50,  1; //InterfaceMethod scala/collection/Iterator.next:()Ljava/lang/Object;
   46:	aload	4
   48:	invokeinterface	#50,  1; //InterfaceMethod scala/collection/Iterator.next:()Ljava/lang/Object;
   53:	invokestatic	#205; //Method scala/runtime/BoxesRunTime.equals:(Ljava/lang/Object;Ljava/lang/Object;)Z
   56:	ifne	21
   59:	iconst_0
   60:	ireturn
   61:	aload	4
   63:	invokeinterface	#47,  1; //InterfaceMethod scala/collection/Iterator.hasNext:()Z
   68:	ifeq	75
   71:	iconst_0
   72:	goto	76
   75:	iconst_1
   76:	ireturn
  LineNumberTable: 
   line 287: 0
   line 288: 13
   line 289: 21
   line 290: 40
   line 291: 59
   line 293: 61
   line 286: 76

  LocalVariableTable: 
   Start  Length  Slot  Name   Signature
   0      77      0    $this       Lscala/collection/generic/SequenceTemplate;
   0      77      1    that       Lscala/collection/Sequence;
   0      77      2    offset       I
   13      64      3    i       Lscala/collection/Iterator;
   21      56      4    j       Lscala/collection/Iterator;


public static scala.collection.Iterator reversedElements(scala.collection.generic.SequenceTemplate);
  Code:
   Stack=1, Locals=1, Args_size=1
   0:	aload_0
   1:	invokeinterface	#435,  1; //InterfaceMethod scala/collection/generic/SequenceTemplate.reverseIterator:()Lscala/collection/Iterator;
   6:	areturn
  LineNumberTable: 
   line 271: 0

  LocalVariableTable: 
   Start  Length  Slot  Name   Signature
   0      7      0    $this       Lscala/collection/generic/SequenceTemplate;


public static scala.collection.Iterator reverseIterator(scala.collection.generic.SequenceTemplate);
  Code:
   Stack=1, Locals=1, Args_size=1
   0:	aload_0
   1:	invokeinterface	#128,  1; //InterfaceMethod scala/collection/generic/SequenceTemplate.reverse:()Lscala/collection/generic/IterableTemplate;
   6:	invokeinterface	#41,  1; //InterfaceMethod scala/collection/generic/IterableTemplate.iterator:()Lscala/collection/Iterator;
   11:	areturn
  LineNumberTable: 
   line 268: 0

  LocalVariableTable: 
   Start  Length  Slot  Name   Signature
   0      12      0    $this       Lscala/collection/generic/SequenceTemplate;


public static scala.collection.generic.IterableTemplate reverse(scala.collection.generic.SequenceTemplate);
  Code:
   Stack=5, Locals=4, Args_size=1
   0:	new	#320; //class scala/runtime/ObjectRef
   3:	dup
   4:	getstatic	#440; //Field scala/collection/immutable/Nil$.MODULE$:Lscala/collection/immutable/Nil$;
   7:	invokespecial	#331; //Method scala/runtime/ObjectRef."<init>":(Ljava/lang/Object;)V
   10:	astore_1
   11:	aload_0
   12:	new	#442; //class scala/collection/generic/SequenceTemplate$$anonfun$reverse$1
   15:	dup
   16:	aload_0
   17:	aload_1
   18:	invokespecial	#445; //Method scala/collection/generic/SequenceTemplate$$anonfun$reverse$1."<init>":(Lscala/collection/generic/SequenceTemplate;Lscala/runtime/ObjectRef;)V
   21:	invokeinterface	#340,  2; //InterfaceMethod scala/collection/generic/IterableTemplate.foreach:(Lscala/Function1;)V
   26:	aload_0
   27:	invokeinterface	#318,  1; //InterfaceMethod scala/collection/generic/TraversableTemplate.newBuilder:()Lscala/collection/generic/Builder;
   32:	astore_2
   33:	aload_1
   34:	getfield	#447; //Field scala/runtime/ObjectRef.elem:Ljava/lang/Object;
   37:	checkcast	#449; //class scala/collection/immutable/List
   40:	new	#451; //class scala/collection/generic/SequenceTemplate$$anonfun$reverse$2
   43:	dup
   44:	aload_0
   45:	aload_2
   46:	invokespecial	#454; //Method scala/collection/generic/SequenceTemplate$$anonfun$reverse$2."<init>":(Lscala/collection/generic/SequenceTemplate;Lscala/collection/generic/Builder;)V
   49:	invokeinterface	#457,  2; //InterfaceMethod scala/collection/generic/LinearSequenceTemplate.foreach:(Lscala/Function1;)V
   54:	aload_2
   55:	invokeinterface	#280,  1; //InterfaceMethod scala/collection/generic/Builder.result:()Ljava/lang/Object;
   60:	astore_3
   61:	aload_3
   62:	instanceof	#37; //class scala/collection/generic/IterableTemplate
   65:	ifeq	72
   68:	aload_3
   69:	goto	79
   72:	getstatic	#104; //Field scala/runtime/ScalaRunTime$.MODULE$:Lscala/runtime/ScalaRunTime$;
   75:	aload_3
   76:	invokevirtual	#111; //Method scala/runtime/ScalaRunTime$.boxArray:(Ljava/lang/Object;)Lscala/runtime/BoxedArray;
   79:	checkcast	#37; //class scala/collection/generic/IterableTemplate
   82:	areturn
  LineNumberTable: 
   line 257: 0
   line 258: 11
   line 260: 26
   line 261: 33
   line 263: 54

  LocalVariableTable: 
   Start  Length  Slot  Name   Signature
   0      83      0    $this       Lscala/collection/generic/SequenceTemplate;
   11      71      1    xs$1       Lscala/runtime/ObjectRef;
   33      49      2    b$2       Lscala/collection/generic/Builder;


public static int lastIndexWhere(scala.collection.generic.SequenceTemplate, scala.Function1, int);
  Code:
   Stack=2, Locals=6, Args_size=3
   0:	aload_0
   1:	invokeinterface	#73,  1; //InterfaceMethod scala/collection/generic/SequenceTemplate.length:()I
   6:	iconst_1
   7:	isub
   8:	istore_3
   9:	aload_0
   10:	invokeinterface	#435,  1; //InterfaceMethod scala/collection/generic/SequenceTemplate.reverseIterator:()Lscala/collection/Iterator;
   15:	astore	4
   17:	aload	4
   19:	invokeinterface	#47,  1; //InterfaceMethod scala/collection/Iterator.hasNext:()Z
   24:	ifeq	70
   27:	aload	4
   29:	invokeinterface	#50,  1; //InterfaceMethod scala/collection/Iterator.next:()Ljava/lang/Object;
   34:	astore	5
   36:	iload_3
   37:	iload_2
   38:	if_icmpgt	59
   41:	aload_1
   42:	aload	5
   44:	invokeinterface	#465,  2; //InterfaceMethod scala/Function1.apply:(Ljava/lang/Object;)Ljava/lang/Object;
   49:	invokestatic	#62; //Method scala/runtime/BoxesRunTime.unboxToBoolean:(Ljava/lang/Object;)Z
   52:	ifeq	59
   55:	iconst_0
   56:	goto	60
   59:	iconst_1
   60:	ifeq	70
   63:	iload_3
   64:	iconst_1
   65:	isub
   66:	istore_3
   67:	goto	17
   70:	iload_3
   71:	ireturn
  LineNumberTable: 
   line 243: 0
   line 244: 9
   line 245: 17
   line 246: 70

  LocalVariableTable: 
   Start  Length  Slot  Name   Signature
   0      72      0    $this       Lscala/collection/generic/SequenceTemplate;
   0      72      1    p       Lscala/Function1;
   0      72      2    end       I
   9      62      3    i       I
   17      54      4    it       Lscala/collection/Iterator;
   36      27      5    elem       Ljava/lang/Object;


public static int lastIndexWhere(scala.collection.generic.SequenceTemplate, scala.Function1);
  Code:
   Stack=4, Locals=2, Args_size=2
   0:	aload_0
   1:	aload_1
   2:	aload_0
   3:	invokeinterface	#73,  1; //InterfaceMethod scala/collection/generic/SequenceTemplate.length:()I
   8:	iconst_1
   9:	isub
   10:	invokeinterface	#470,  3; //InterfaceMethod scala/collection/generic/SequenceTemplate.lastIndexWhere:(Lscala/Function1;I)I
   15:	ireturn
  LineNumberTable: 
   line 234: 0

  LocalVariableTable: 
   Start  Length  Slot  Name   Signature
   0      16      0    $this       Lscala/collection/generic/SequenceTemplate;
   0      16      1    p       Lscala/Function1;


public static int lastIndexOf(scala.collection.generic.SequenceTemplate, java.lang.Object, int);
  Code:
   Stack=5, Locals=3, Args_size=3
   0:	aload_0
   1:	new	#474; //class scala/collection/generic/SequenceTemplate$$anonfun$lastIndexOf$2
   4:	dup
   5:	aload_0
   6:	aload_1
   7:	invokespecial	#475; //Method scala/collection/generic/SequenceTemplate$$anonfun$lastIndexOf$2."<init>":(Lscala/collection/generic/SequenceTemplate;Ljava/lang/Object;)V
   10:	iload_2
   11:	invokeinterface	#470,  3; //InterfaceMethod scala/collection/generic/SequenceTemplate.lastIndexWhere:(Lscala/Function1;I)I
   16:	ireturn
  LineNumberTable: 
   line 226: 0

  LocalVariableTable: 
   Start  Length  Slot  Name   Signature
   0      17      0    $this       Lscala/collection/generic/SequenceTemplate;
   0      17      1    elem$3       Ljava/lang/Object;
   0      17      2    end       I


public static int lastIndexOf(scala.collection.generic.SequenceTemplate, java.lang.Object);
  Code:
   Stack=5, Locals=2, Args_size=2
   0:	aload_0
   1:	new	#479; //class scala/collection/generic/SequenceTemplate$$anonfun$lastIndexOf$1
   4:	dup
   5:	aload_0
   6:	aload_1
   7:	invokespecial	#480; //Method scala/collection/generic/SequenceTemplate$$anonfun$lastIndexOf$1."<init>":(Lscala/collection/generic/SequenceTemplate;Ljava/lang/Object;)V
   10:	invokeinterface	#87,  2; //InterfaceMethod scala/collection/generic/SequenceTemplate.lastIndexWhere:(Lscala/Function1;)I
   15:	ireturn
  LineNumberTable: 
   line 216: 0

  LocalVariableTable: 
   Start  Length  Slot  Name   Signature
   0      16      0    $this       Lscala/collection/generic/SequenceTemplate;
   0      16      1    elem$4       Ljava/lang/Object;


public static int indexOf(scala.collection.generic.SequenceTemplate, java.lang.Object, int);
  Code:
   Stack=5, Locals=3, Args_size=3
   0:	aload_0
   1:	new	#483; //class scala/collection/generic/SequenceTemplate$$anonfun$indexOf$1
   4:	dup
   5:	aload_0
   6:	aload_1
   7:	invokespecial	#484; //Method scala/collection/generic/SequenceTemplate$$anonfun$indexOf$1."<init>":(Lscala/collection/generic/SequenceTemplate;Ljava/lang/Object;)V
   10:	iload_2
   11:	invokeinterface	#487,  3; //InterfaceMethod scala/collection/generic/SequenceTemplate.indexWhere:(Lscala/Function1;I)I
   16:	ireturn
  LineNumberTable: 
   line 206: 0

  LocalVariableTable: 
   Start  Length  Slot  Name   Signature
   0      17      0    $this       Lscala/collection/generic/SequenceTemplate;
   0      17      1    elem$2       Ljava/lang/Object;
   0      17      2    from       I


public static int indexOf(scala.collection.generic.SequenceTemplate, java.lang.Object);
  Code:
   Stack=3, Locals=2, Args_size=2
   0:	aload_0
   1:	aload_1
   2:	iconst_0
   3:	invokeinterface	#491,  3; //InterfaceMethod scala/collection/generic/SequenceTemplate.indexOf:(Ljava/lang/Object;I)I
   8:	ireturn
  LineNumberTable: 
   line 197: 0

  LocalVariableTable: 
   Start  Length  Slot  Name   Signature
   0      9      0    $this       Lscala/collection/generic/SequenceTemplate;
   0      9      1    elem       Ljava/lang/Object;


public static int findIndexOf(scala.collection.generic.SequenceTemplate, scala.Function1);
  Code:
   Stack=2, Locals=2, Args_size=2
   0:	aload_0
   1:	aload_1
   2:	invokeinterface	#494,  2; //InterfaceMethod scala/collection/generic/SequenceTemplate.indexWhere:(Lscala/Function1;)I
   7:	ireturn
  LineNumberTable: 
   line 186: 0

  LocalVariableTable: 
   Start  Length  Slot  Name   Signature
   0      8      0    $this       Lscala/collection/generic/SequenceTemplate;
   0      8      1    p       Lscala/Function1;


public static int indexWhere(scala.collection.generic.SequenceTemplate, scala.Function1, int);
  Code:
   Stack=8, Locals=5, Args_size=3
   0:	new	#13; //class scala/runtime/IntRef
   3:	dup
   4:	iconst_m1
   5:	invokespecial	#208; //Method scala/runtime/IntRef."<init>":(I)V
   8:	astore_3
   9:	new	#13; //class scala/runtime/IntRef
   12:	dup
   13:	iload_2
   14:	invokespecial	#208; //Method scala/runtime/IntRef."<init>":(I)V
   17:	astore	4
   19:	getstatic	#499; //Field scala/collection/Traversable$.MODULE$:Lscala/collection/Traversable$;
   22:	invokevirtual	#503; //Method scala/collection/Traversable$.breaks:()Lscala/util/control/Breaks;
   25:	new	#505; //class scala/collection/generic/SequenceTemplate$$anonfun$indexWhere$1
   28:	dup
   29:	aload_0
   30:	aload_1
   31:	iload_2
   32:	aload_3
   33:	aload	4
   35:	invokespecial	#508; //Method scala/collection/generic/SequenceTemplate$$anonfun$indexWhere$1."<init>":(Lscala/collection/generic/SequenceTemplate;Lscala/Function1;ILscala/runtime/IntRef;Lscala/runtime/IntRef;)V
   38:	invokevirtual	#514; //Method scala/util/control/Breaks.breakable:(Lscala/Function0;)V
   41:	aload_3
   42:	getfield	#17; //Field scala/runtime/IntRef.elem:I
   45:	ireturn
  LineNumberTable: 
   line 173: 0
   line 174: 9
   line 175: 19
   line 176: 25
   line 175: 38
   line 181: 41

  LocalVariableTable: 
   Start  Length  Slot  Name   Signature
   0      46      0    $this       Lscala/collection/generic/SequenceTemplate;
   0      46      1    p$2       Lscala/Function1;
   0      46      2    from$2       I
   9      36      3    result$2       Lscala/runtime/IntRef;
   19      26      4    i$4       Lscala/runtime/IntRef;


public static int indexWhere(scala.collection.generic.SequenceTemplate, scala.Function1);
  Code:
   Stack=3, Locals=2, Args_size=2
   0:	aload_0
   1:	aload_1
   2:	iconst_0
   3:	invokeinterface	#487,  3; //InterfaceMethod scala/collection/generic/SequenceTemplate.indexWhere:(Lscala/Function1;I)I
   8:	ireturn
  LineNumberTable: 
   line 163: 0

  LocalVariableTable: 
   Start  Length  Slot  Name   Signature
   0      9      0    $this       Lscala/collection/generic/SequenceTemplate;
   0      9      1    p       Lscala/Function1;


public static int prefixLength(scala.collection.generic.SequenceTemplate, scala.Function1);
  Code:
   Stack=3, Locals=2, Args_size=2
   0:	aload_0
   1:	aload_1
   2:	iconst_0
   3:	invokeinterface	#522,  3; //InterfaceMethod scala/collection/generic/SequenceTemplate.segmentLength:(Lscala/Function1;I)I
   8:	ireturn
  LineNumberTable: 
   line 156: 0

  LocalVariableTable: 
   Start  Length  Slot  Name   Signature
   0      9      0    $this       Lscala/collection/generic/SequenceTemplate;
   0      9      1    p       Lscala/Function1;


public static int segmentLength(scala.collection.generic.SequenceTemplate, scala.Function1, int);
  Code:
   Stack=8, Locals=5, Args_size=3
   0:	new	#13; //class scala/runtime/IntRef
   3:	dup
   4:	iconst_0
   5:	invokespecial	#208; //Method scala/runtime/IntRef."<init>":(I)V
   8:	astore_3
   9:	new	#13; //class scala/runtime/IntRef
   12:	dup
   13:	iconst_0
   14:	invokespecial	#208; //Method scala/runtime/IntRef."<init>":(I)V
   17:	astore	4
   19:	getstatic	#499; //Field scala/collection/Traversable$.MODULE$:Lscala/collection/Traversable$;
   22:	invokevirtual	#503; //Method scala/collection/Traversable$.breaks:()Lscala/util/control/Breaks;
   25:	new	#524; //class scala/collection/generic/SequenceTemplate$$anonfun$segmentLength$1
   28:	dup
   29:	aload_0
   30:	aload_1
   31:	iload_2
   32:	aload_3
   33:	aload	4
   35:	invokespecial	#525; //Method scala/collection/generic/SequenceTemplate$$anonfun$segmentLength$1."<init>":(Lscala/collection/generic/SequenceTemplate;Lscala/Function1;ILscala/runtime/IntRef;Lscala/runtime/IntRef;)V
   38:	invokevirtual	#514; //Method scala/util/control/Breaks.breakable:(Lscala/Function0;)V
   41:	aload_3
   42:	getfield	#17; //Field scala/runtime/IntRef.elem:I
   45:	ireturn
  LineNumberTable: 
   line 140: 0
   line 141: 9
   line 142: 19
   line 143: 25
   line 142: 38
   line 148: 41

  LocalVariableTable: 
   Start  Length  Slot  Name   Signature
   0      46      0    $this       Lscala/collection/generic/SequenceTemplate;
   0      46      1    p$1       Lscala/Function1;
   0      46      2    from$1       I
   9      36      3    result$1       Lscala/runtime/IntRef;
   19      26      4    i$3       Lscala/runtime/IntRef;


public static java.lang.Object zipWithIndex(scala.collection.generic.SequenceTemplate, scala.collection.generic.BuilderFactory);
  Code:
   Stack=6, Locals=4, Args_size=2
   0:	aload_1
   1:	aload_0
   2:	invokeinterface	#257,  1; //InterfaceMethod scala/collection/generic/TraversableTemplate.thisCollection:()Lscala/collection/generic/TraversableTemplate;
   7:	invokeinterface	#264,  2; //InterfaceMethod scala/collection/generic/BuilderFactory.apply:(Ljava/lang/Object;)Lscala/collection/generic/Builder;
   12:	astore_2
   13:	new	#13; //class scala/runtime/IntRef
   16:	dup
   17:	iconst_0
   18:	invokespecial	#208; //Method scala/runtime/IntRef."<init>":(I)V
   21:	astore_3
   22:	aload_0
   23:	new	#533; //class scala/collection/generic/SequenceTemplate$$anonfun$zipWithIndex$1
   26:	dup
   27:	aload_0
   28:	aload_2
   29:	aload_3
   30:	invokespecial	#536; //Method scala/collection/generic/SequenceTemplate$$anonfun$zipWithIndex$1."<init>":(Lscala/collection/generic/SequenceTemplate;Lscala/collection/generic/Builder;Lscala/runtime/IntRef;)V
   33:	invokeinterface	#340,  2; //InterfaceMethod scala/collection/generic/IterableTemplate.foreach:(Lscala/Function1;)V
   38:	aload_2
   39:	invokeinterface	#280,  1; //InterfaceMethod scala/collection/generic/Builder.result:()Ljava/lang/Object;
   44:	areturn
  LineNumberTable: 
   line 124: 0
   line 125: 13
   line 126: 22
   line 130: 38

  LocalVariableTable: 
   Start  Length  Slot  Name   Signature
   0      45      0    $this       Lscala/collection/generic/SequenceTemplate;
   0      45      1    bf       Lscala/collection/generic/BuilderFactory;
   13      31      2    b$1       Lscala/collection/generic/Builder;
   22      22      3    i$2       Lscala/runtime/IntRef;


public static java.lang.Object zipAll(scala.collection.generic.SequenceTemplate, scala.collection.Sequence, java.lang.Object, java.lang.Object, scala.collection.generic.BuilderFactory);
  Code:
   Stack=5, Locals=8, Args_size=5
   0:	aload	4
   2:	aload_0
   3:	invokeinterface	#257,  1; //InterfaceMethod scala/collection/generic/TraversableTemplate.thisCollection:()Lscala/collection/generic/TraversableTemplate;
   8:	invokeinterface	#264,  2; //InterfaceMethod scala/collection/generic/BuilderFactory.apply:(Ljava/lang/Object;)Lscala/collection/generic/Builder;
   13:	astore	5
   15:	aload_0
   16:	invokeinterface	#41,  1; //InterfaceMethod scala/collection/generic/IterableTemplate.iterator:()Lscala/collection/Iterator;
   21:	astore	6
   23:	aload_1
   24:	invokeinterface	#41,  1; //InterfaceMethod scala/collection/generic/IterableTemplate.iterator:()Lscala/collection/Iterator;
   29:	astore	7
   31:	aload	6
   33:	invokeinterface	#47,  1; //InterfaceMethod scala/collection/Iterator.hasNext:()Z
   38:	ifeq	83
   41:	aload	7
   43:	invokeinterface	#47,  1; //InterfaceMethod scala/collection/Iterator.hasNext:()Z
   48:	ifeq	83
   51:	aload	5
   53:	new	#294; //class scala/Tuple2
   56:	dup
   57:	aload	6
   59:	invokeinterface	#50,  1; //InterfaceMethod scala/collection/Iterator.next:()Ljava/lang/Object;
   64:	aload	7
   66:	invokeinterface	#50,  1; //InterfaceMethod scala/collection/Iterator.next:()Ljava/lang/Object;
   71:	invokespecial	#303; //Method scala/Tuple2."<init>":(Ljava/lang/Object;Ljava/lang/Object;)V
   74:	invokeinterface	#277,  2; //InterfaceMethod scala/collection/generic/Builder.$plus$eq:(Ljava/lang/Object;)Lscala/collection/generic/Builder;
   79:	pop
   80:	goto	31
   83:	aload	6
   85:	invokeinterface	#47,  1; //InterfaceMethod scala/collection/Iterator.hasNext:()Z
   90:	ifeq	119
   93:	aload	5
   95:	new	#294; //class scala/Tuple2
   98:	dup
   99:	aload	6
   101:	invokeinterface	#50,  1; //InterfaceMethod scala/collection/Iterator.next:()Ljava/lang/Object;
   106:	aload_3
   107:	invokespecial	#303; //Method scala/Tuple2."<init>":(Ljava/lang/Object;Ljava/lang/Object;)V
   110:	invokeinterface	#277,  2; //InterfaceMethod scala/collection/generic/Builder.$plus$eq:(Ljava/lang/Object;)Lscala/collection/generic/Builder;
   115:	pop
   116:	goto	83
   119:	aload	7
   121:	invokeinterface	#47,  1; //InterfaceMethod scala/collection/Iterator.hasNext:()Z
   126:	ifeq	155
   129:	aload	5
   131:	new	#294; //class scala/Tuple2
   134:	dup
   135:	aload_2
   136:	aload	7
   138:	invokeinterface	#50,  1; //InterfaceMethod scala/collection/Iterator.next:()Ljava/lang/Object;
   143:	invokespecial	#303; //Method scala/Tuple2."<init>":(Ljava/lang/Object;Ljava/lang/Object;)V
   146:	invokeinterface	#277,  2; //InterfaceMethod scala/collection/generic/Builder.$plus$eq:(Ljava/lang/Object;)Lscala/collection/generic/Builder;
   151:	pop
   152:	goto	119
   155:	aload	5
   157:	invokeinterface	#280,  1; //InterfaceMethod scala/collection/generic/Builder.result:()Ljava/lang/Object;
   162:	areturn
  LineNumberTable: 
   line 109: 0
   line 110: 15
   line 111: 23
   line 112: 31
   line 113: 51
   line 114: 83
   line 115: 93
   line 116: 119
   line 117: 129
   line 118: 155

  LocalVariableTable: 
   Start  Length  Slot  Name   Signature
   0      163      0    $this       Lscala/collection/generic/SequenceTemplate;
   0      163      1    that       Lscala/collection/Sequence;
   0      163      2    thisElem       Ljava/lang/Object;
   0      163      3    thatElem       Ljava/lang/Object;
   0      163      4    bf       Lscala/collection/generic/BuilderFactory;
   15      147      5    b       Lscala/collection/generic/Builder;
   23      139      6    these       Lscala/collection/Iterator;
   31      131      7    those       Lscala/collection/Iterator;


public static java.lang.Object zip(scala.collection.generic.SequenceTemplate, scala.collection.Sequence, scala.collection.generic.BuilderFactory);
  Code:
   Stack=5, Locals=6, Args_size=3
   0:	aload_2
   1:	aload_0
   2:	invokeinterface	#257,  1; //InterfaceMethod scala/collection/generic/TraversableTemplate.thisCollection:()Lscala/collection/generic/TraversableTemplate;
   7:	invokeinterface	#264,  2; //InterfaceMethod scala/collection/generic/BuilderFactory.apply:(Ljava/lang/Object;)Lscala/collection/generic/Builder;
   12:	astore_3
   13:	aload_0
   14:	invokeinterface	#41,  1; //InterfaceMethod scala/collection/generic/IterableTemplate.iterator:()Lscala/collection/Iterator;
   19:	astore	4
   21:	aload_1
   22:	invokeinterface	#41,  1; //InterfaceMethod scala/collection/generic/IterableTemplate.iterator:()Lscala/collection/Iterator;
   27:	astore	5
   29:	aload	4
   31:	invokeinterface	#47,  1; //InterfaceMethod scala/collection/Iterator.hasNext:()Z
   36:	ifeq	80
   39:	aload	5
   41:	invokeinterface	#47,  1; //InterfaceMethod scala/collection/Iterator.hasNext:()Z
   46:	ifeq	80
   49:	aload_3
   50:	new	#294; //class scala/Tuple2
   53:	dup
   54:	aload	4
   56:	invokeinterface	#50,  1; //InterfaceMethod scala/collection/Iterator.next:()Ljava/lang/Object;
   61:	aload	5
   63:	invokeinterface	#50,  1; //InterfaceMethod scala/collection/Iterator.next:()Ljava/lang/Object;
   68:	invokespecial	#303; //Method scala/Tuple2."<init>":(Ljava/lang/Object;Ljava/lang/Object;)V
   71:	invokeinterface	#277,  2; //InterfaceMethod scala/collection/generic/Builder.$plus$eq:(Ljava/lang/Object;)Lscala/collection/generic/Builder;
   76:	pop
   77:	goto	29
   80:	aload_3
   81:	invokeinterface	#280,  1; //InterfaceMethod scala/collection/generic/Builder.result:()Ljava/lang/Object;
   86:	areturn
  LineNumberTable: 
   line 80: 0
   line 81: 13
   line 82: 21
   line 83: 29
   line 84: 49
   line 85: 80

  LocalVariableTable: 
   Start  Length  Slot  Name   Signature
   0      87      0    $this       Lscala/collection/generic/SequenceTemplate;
   0      87      1    that       Lscala/collection/Sequence;
   0      87      2    bf       Lscala/collection/generic/BuilderFactory;
   13      73      3    b       Lscala/collection/generic/Builder;
   21      65      4    these       Lscala/collection/Iterator;
   29      57      5    those       Lscala/collection/Iterator;


public static boolean isDefinedAt(scala.collection.generic.SequenceTemplate, int);
  Code:
   Stack=2, Locals=2, Args_size=2
   0:	iload_1
   1:	iconst_0
   2:	if_icmplt	19
   5:	iload_1
   6:	aload_0
   7:	invokeinterface	#73,  1; //InterfaceMethod scala/collection/generic/SequenceTemplate.length:()I
   12:	if_icmpge	19
   15:	iconst_1
   16:	goto	20
   19:	iconst_0
   20:	ireturn
  LineNumberTable: 
   line 72: 0

  LocalVariableTable: 
   Start  Length  Slot  Name   Signature
   0      21      0    $this       Lscala/collection/generic/SequenceTemplate;
   0      21      1    x       I


public static int size(scala.collection.generic.SequenceTemplate);
  Code:
   Stack=1, Locals=1, Args_size=1
   0:	aload_0
   1:	invokeinterface	#73,  1; //InterfaceMethod scala/collection/generic/SequenceTemplate.length:()I
   6:	ireturn
  LineNumberTable: 
   line 68: 0

  LocalVariableTable: 
   Start  Length  Slot  Name   Signature
   0      7      0    $this       Lscala/collection/generic/SequenceTemplate;


public static int lengthCompare(scala.collection.generic.SequenceTemplate, int);
  Code:
   Stack=6, Locals=3, Args_size=2
   0:	new	#13; //class scala/runtime/IntRef
   3:	dup
   4:	iconst_0
   5:	invokespecial	#208; //Method scala/runtime/IntRef."<init>":(I)V
   8:	astore_2
   9:	getstatic	#499; //Field scala/collection/Traversable$.MODULE$:Lscala/collection/Traversable$;
   12:	invokevirtual	#503; //Method scala/collection/Traversable$.breaks:()Lscala/util/control/Breaks;
   15:	new	#553; //class scala/collection/generic/SequenceTemplate$$anonfun$lengthCompare$1
   18:	dup
   19:	aload_0
   20:	iload_1
   21:	aload_2
   22:	invokespecial	#556; //Method scala/collection/generic/SequenceTemplate$$anonfun$lengthCompare$1."<init>":(Lscala/collection/generic/SequenceTemplate;ILscala/runtime/IntRef;)V
   25:	invokevirtual	#514; //Method scala/util/control/Breaks.breakable:(Lscala/Function0;)V
   28:	aload_2
   29:	getfield	#17; //Field scala/runtime/IntRef.elem:I
   32:	iload_1
   33:	isub
   34:	ireturn
  LineNumberTable: 
   line 57: 0
   line 58: 9
   line 59: 15
   line 58: 25
   line 64: 28

  LocalVariableTable: 
   Start  Length  Slot  Name   Signature
   0      35      0    $this       Lscala/collection/generic/SequenceTemplate;
   0      35      1    len$1       I
   9      25      2    i$1       Lscala/runtime/IntRef;


}

