Compiled from "SequenceTemplate.scala"
public final class scala.collection.generic.SequenceTemplate$$anon$2 extends scala.collection.mutable.ListMap
  SourceFile: "SequenceTemplate.scala"
  Signature: length = 0x2
   00 23 
  Scala: length = 0x
   
  InnerClass: 
   public final #40= #20 of #39; //$anon$2=class scala/collection/generic/SequenceTemplate$$anon$2 of class scala/collection/generic/SequenceTemplate
  minor version: 0
  major version: 49
  Constant pool:
const #1 = Asciz	SourceFile;
const #2 = Asciz	SequenceTemplate.scala;
const #3 = Asciz	<init>;
const #4 = Asciz	(Lscala/collection/generic/SequenceTemplate;)V;
const #5 = Asciz	Code;
const #6 = Asciz	LineNumberTable;
const #7 = Asciz	scala/collection/mutable/ListMap;
const #8 = class	#7;	//  scala/collection/mutable/ListMap
const #9 = Asciz	()V;
const #10 = NameAndType	#3:#9;//  "<init>":()V
const #11 = Method	#8.#10;	//  scala/collection/mutable/ListMap."<init>":()V
const #12 = Asciz	this;
const #13 = Asciz	Lscala/collection/generic/SequenceTemplate$$anon$2;;
const #14 = Asciz	$outer;
const #15 = Asciz	Lscala/collection/generic/SequenceTemplate;;
const #16 = Asciz	LocalVariableTable;
const #17 = Asciz	default;
const #18 = Asciz	(Ljava/lang/Object;)Ljava/lang/Object;;
const #19 = Asciz	scala/collection/generic/SequenceTemplate$$anon$2;
const #20 = class	#19;	//  scala/collection/generic/SequenceTemplate$$anon$2
const #21 = Asciz	(Ljava/lang/Object;)I;
const #22 = NameAndType	#17:#21;//  default:(Ljava/lang/Object;)I
const #23 = Method	#20.#22;	//  scala/collection/generic/SequenceTemplate$$anon$2.default:(Ljava/lang/Object;)I
const #24 = Asciz	scala/runtime/BoxesRunTime;
const #25 = class	#24;	//  scala/runtime/BoxesRunTime
const #26 = Asciz	boxToInteger;
const #27 = Asciz	(I)Ljava/lang/Integer;;
const #28 = NameAndType	#26:#27;//  boxToInteger:(I)Ljava/lang/Integer;
const #29 = Method	#25.#28;	//  scala/runtime/BoxesRunTime.boxToInteger:(I)Ljava/lang/Integer;
const #30 = Asciz	key;
const #31 = Asciz	Ljava/lang/Object;;
const #32 = Asciz	k;
const #33 = Asciz	(TB;)I;
const #34 = Asciz	Signature;
const #35 = Asciz	Lscala/collection/mutable/ListMap<TB;Ljava/lang/Integer;>;;
const #36 = Asciz	Scala;
const #37 = Asciz	InnerClasses;
const #38 = Asciz	scala/collection/generic/SequenceTemplate;
const #39 = class	#38;	//  scala/collection/generic/SequenceTemplate
const #40 = Asciz	$anon$2;

{
public scala.collection.generic.SequenceTemplate$$anon$2(scala.collection.generic.SequenceTemplate);
  Code:
   Stack=1, Locals=2, Args_size=2
   0:	aload_0
   1:	invokespecial	#11; //Method scala/collection/mutable/ListMap."<init>":()V
   4:	return
  LineNumberTable: 
   line 434: 0

  LocalVariableTable: 
   Start  Length  Slot  Name   Signature
   0      5      0    this       Lscala/collection/generic/SequenceTemplate$$anon$2;
   0      5      1    $outer       Lscala/collection/generic/SequenceTemplate;


public java.lang.Object default(java.lang.Object);
  Code:
   Stack=2, Locals=2, Args_size=2
   0:	aload_0
   1:	aload_1
   2:	invokevirtual	#23; //Method default:(Ljava/lang/Object;)I
   5:	invokestatic	#29; //Method scala/runtime/BoxesRunTime.boxToInteger:(I)Ljava/lang/Integer;
   8:	areturn
  LineNumberTable: 
   line 434: 0

  LocalVariableTable: 
   Start  Length  Slot  Name   Signature
   0      9      0    this       Lscala/collection/generic/SequenceTemplate$$anon$2;
   0      9      1    key       Ljava/lang/Object;


public int default(java.lang.Object);
  Code:
   Stack=1, Locals=2, Args_size=2
   0:	iconst_0
   1:	ireturn
  LineNumberTable: 
   line 434: 0

  LocalVariableTable: 
   Start  Length  Slot  Name   Signature
   0      2      0    this       Lscala/collection/generic/SequenceTemplate$$anon$2;
   0      2      1    k       Ljava/lang/Object;

  Signature: length = 0x2
   00 21 

}

