Compiled from "SequenceViewTemplate.scala"
public abstract class scala.collection.generic.SequenceViewTemplate$Patched$class extends java.lang.Object
  SourceFile: "SequenceViewTemplate.scala"
  Scala: length = 0x
   
  InnerClass: 
   public abstract #80= #19 of #79; //Patched=class scala/collection/generic/SequenceViewTemplate$Patched of class scala/collection/generic/SequenceViewTemplate
  minor version: 0
  major version: 49
  Constant pool:
const #1 = Asciz	SourceFile;
const #2 = Asciz	SequenceViewTemplate.scala;
const #3 = Asciz	$init$;
const #4 = Asciz	(Lscala/collection/generic/SequenceViewTemplate$Patched;)V;
const #5 = Asciz	Code;
const #6 = Asciz	LineNumberTable;
const #7 = Asciz	$this;
const #8 = Asciz	Lscala/collection/generic/SequenceViewTemplate$Patched;;
const #9 = Asciz	LocalVariableTable;
const #10 = Asciz	stringPrefix;
const #11 = Asciz	(Lscala/collection/generic/SequenceViewTemplate$Patched;)Ljava/lang/String;;
const #12 = Asciz	scala/collection/mutable/StringBuilder;
const #13 = class	#12;	//  scala/collection/mutable/StringBuilder
const #14 = Asciz	<init>;
const #15 = Asciz	()V;
const #16 = NameAndType	#14:#15;//  "<init>":()V
const #17 = Method	#13.#16;	//  scala/collection/mutable/StringBuilder."<init>":()V
const #18 = Asciz	scala/collection/generic/SequenceViewTemplate$Patched;
const #19 = class	#18;	//  scala/collection/generic/SequenceViewTemplate$Patched
const #20 = Asciz	scala$collection$generic$SequenceViewTemplate$Patched$$super$stringPrefix;
const #21 = Asciz	()Ljava/lang/String;;
const #22 = NameAndType	#20:#21;//  scala$collection$generic$SequenceViewTemplate$Patched$$super$stringPrefix:()Ljava/lang/String;
const #23 = InterfaceMethod	#19.#22;	//  scala/collection/generic/SequenceViewTemplate$Patched.scala$collection$generic$SequenceViewTemplate$Patched$$super$stringPrefix:()Ljava/lang/String;
const #24 = Asciz	append;
const #25 = Asciz	(Ljava/lang/Object;)Lscala/collection/mutable/StringBuilder;;
const #26 = NameAndType	#24:#25;//  append:(Ljava/lang/Object;)Lscala/collection/mutable/StringBuilder;
const #27 = Method	#13.#26;	//  scala/collection/mutable/StringBuilder.append:(Ljava/lang/Object;)Lscala/collection/mutable/StringBuilder;
const #28 = Asciz	P;
const #29 = String	#28;	//  P
const #30 = Asciz	toString;
const #31 = NameAndType	#30:#21;//  toString:()Ljava/lang/String;
const #32 = Method	#13.#31;	//  scala/collection/mutable/StringBuilder.toString:()Ljava/lang/String;
const #33 = Asciz	apply;
const #34 = Asciz	(Lscala/collection/generic/SequenceViewTemplate$Patched;I)Ljava/lang/Object;;
const #35 = Asciz	from;
const #36 = Asciz	()I;
const #37 = NameAndType	#35:#36;//  from:()I
const #38 = InterfaceMethod	#19.#37;	//  scala/collection/generic/SequenceViewTemplate$Patched.from:()I
const #39 = Asciz	scala$collection$generic$SequenceViewTemplate$Patched$$$outer;
const #40 = Asciz	()Lscala/collection/generic/SequenceViewTemplate;;
const #41 = NameAndType	#39:#40;//  scala$collection$generic$SequenceViewTemplate$Patched$$$outer:()Lscala/collection/generic/SequenceViewTemplate;
const #42 = InterfaceMethod	#19.#41;	//  scala/collection/generic/SequenceViewTemplate$Patched.scala$collection$generic$SequenceViewTemplate$Patched$$$outer:()Lscala/collection/generic/SequenceViewTemplate;
const #43 = Asciz	scala/collection/generic/SequenceTemplate;
const #44 = class	#43;	//  scala/collection/generic/SequenceTemplate
const #45 = Asciz	(I)Ljava/lang/Object;;
const #46 = NameAndType	#33:#45;//  apply:(I)Ljava/lang/Object;
const #47 = InterfaceMethod	#44.#46;	//  scala/collection/generic/SequenceTemplate.apply:(I)Ljava/lang/Object;
const #48 = Asciz	scala$collection$generic$SequenceViewTemplate$Patched$$plen;
const #49 = NameAndType	#48:#36;//  scala$collection$generic$SequenceViewTemplate$Patched$$plen:()I
const #50 = InterfaceMethod	#19.#49;	//  scala/collection/generic/SequenceViewTemplate$Patched.scala$collection$generic$SequenceViewTemplate$Patched$$plen:()I
const #51 = Asciz	patch;
const #52 = Asciz	()Lscala/collection/Sequence;;
const #53 = NameAndType	#51:#52;//  patch:()Lscala/collection/Sequence;
const #54 = InterfaceMethod	#19.#53;	//  scala/collection/generic/SequenceViewTemplate$Patched.patch:()Lscala/collection/Sequence;
const #55 = Asciz	replaced;
const #56 = NameAndType	#55:#36;//  replaced:()I
const #57 = InterfaceMethod	#19.#56;	//  scala/collection/generic/SequenceViewTemplate$Patched.replaced:()I
const #58 = Asciz	idx;
const #59 = Asciz	I;
const #60 = Asciz	length;
const #61 = Asciz	(Lscala/collection/generic/SequenceViewTemplate$Patched;)I;
const #62 = NameAndType	#60:#36;//  length:()I
const #63 = InterfaceMethod	#44.#62;	//  scala/collection/generic/SequenceTemplate.length:()I
const #64 = Asciz	iterator;
const #65 = Asciz	(Lscala/collection/generic/SequenceViewTemplate$Patched;)Lscala/collection/Iterator;;
const #66 = Asciz	scala/collection/generic/IterableTemplate;
const #67 = class	#66;	//  scala/collection/generic/IterableTemplate
const #68 = Asciz	()Lscala/collection/Iterator;;
const #69 = NameAndType	#64:#68;//  iterator:()Lscala/collection/Iterator;
const #70 = InterfaceMethod	#67.#69;	//  scala/collection/generic/IterableTemplate.iterator:()Lscala/collection/Iterator;
const #71 = Asciz	scala/collection/Iterator;
const #72 = class	#71;	//  scala/collection/Iterator
const #73 = Asciz	(ILscala/collection/Iterator;I)Ljava/lang/Object;;
const #74 = NameAndType	#51:#73;//  patch:(ILscala/collection/Iterator;I)Ljava/lang/Object;
const #75 = InterfaceMethod	#72.#74;	//  scala/collection/Iterator.patch:(ILscala/collection/Iterator;I)Ljava/lang/Object;
const #76 = Asciz	Scala;
const #77 = Asciz	InnerClasses;
const #78 = Asciz	scala/collection/generic/SequenceViewTemplate;
const #79 = class	#78;	//  scala/collection/generic/SequenceViewTemplate
const #80 = Asciz	Patched;
const #81 = Asciz	scala/collection/generic/SequenceViewTemplate$Patched$class;
const #82 = class	#81;	//  scala/collection/generic/SequenceViewTemplate$Patched$class
const #83 = Asciz	java/lang/Object;
const #84 = class	#83;	//  java/lang/Object

{
public static void $init$(scala.collection.generic.SequenceViewTemplate$Patched);
  Code:
   Stack=0, Locals=1, Args_size=1
   0:	return
  LineNumberTable: 
   line 112: 0

  LocalVariableTable: 
   Start  Length  Slot  Name   Signature
   0      1      0    $this       Lscala/collection/generic/SequenceViewTemplate$Patched;


public static java.lang.String stringPrefix(scala.collection.generic.SequenceViewTemplate$Patched);
  Code:
   Stack=2, Locals=1, Args_size=1
   0:	new	#13; //class scala/collection/mutable/StringBuilder
   3:	dup
   4:	invokespecial	#17; //Method scala/collection/mutable/StringBuilder."<init>":()V
   7:	aload_0
   8:	invokeinterface	#23,  1; //InterfaceMethod scala/collection/generic/SequenceViewTemplate$Patched.scala$collection$generic$SequenceViewTemplate$Patched$$super$stringPrefix:()Ljava/lang/String;
   13:	invokevirtual	#27; //Method scala/collection/mutable/StringBuilder.append:(Ljava/lang/Object;)Lscala/collection/mutable/StringBuilder;
   16:	ldc	#29; //String P
   18:	invokevirtual	#27; //Method scala/collection/mutable/StringBuilder.append:(Ljava/lang/Object;)Lscala/collection/mutable/StringBuilder;
   21:	invokevirtual	#32; //Method scala/collection/mutable/StringBuilder.toString:()Ljava/lang/String;
   24:	areturn
  LineNumberTable: 
   line 123: 0

  LocalVariableTable: 
   Start  Length  Slot  Name   Signature
   0      25      0    $this       Lscala/collection/generic/SequenceViewTemplate$Patched;


public static java.lang.Object apply(scala.collection.generic.SequenceViewTemplate$Patched, int);
  Code:
   Stack=3, Locals=2, Args_size=2
   0:	iload_1
   1:	aload_0
   2:	invokeinterface	#38,  1; //InterfaceMethod scala/collection/generic/SequenceViewTemplate$Patched.from:()I
   7:	if_icmpge	25
   10:	aload_0
   11:	invokeinterface	#42,  1; //InterfaceMethod scala/collection/generic/SequenceViewTemplate$Patched.scala$collection$generic$SequenceViewTemplate$Patched$$$outer:()Lscala/collection/generic/SequenceViewTemplate;
   16:	iload_1
   17:	invokeinterface	#47,  2; //InterfaceMethod scala/collection/generic/SequenceTemplate.apply:(I)Ljava/lang/Object;
   22:	goto	90
   25:	iload_1
   26:	aload_0
   27:	invokeinterface	#38,  1; //InterfaceMethod scala/collection/generic/SequenceViewTemplate$Patched.from:()I
   32:	aload_0
   33:	invokeinterface	#50,  1; //InterfaceMethod scala/collection/generic/SequenceViewTemplate$Patched.scala$collection$generic$SequenceViewTemplate$Patched$$plen:()I
   38:	iadd
   39:	if_icmpge	64
   42:	aload_0
   43:	invokeinterface	#54,  1; //InterfaceMethod scala/collection/generic/SequenceViewTemplate$Patched.patch:()Lscala/collection/Sequence;
   48:	iload_1
   49:	aload_0
   50:	invokeinterface	#38,  1; //InterfaceMethod scala/collection/generic/SequenceViewTemplate$Patched.from:()I
   55:	isub
   56:	invokeinterface	#47,  2; //InterfaceMethod scala/collection/generic/SequenceTemplate.apply:(I)Ljava/lang/Object;
   61:	goto	90
   64:	aload_0
   65:	invokeinterface	#42,  1; //InterfaceMethod scala/collection/generic/SequenceViewTemplate$Patched.scala$collection$generic$SequenceViewTemplate$Patched$$$outer:()Lscala/collection/generic/SequenceViewTemplate;
   70:	iload_1
   71:	aload_0
   72:	invokeinterface	#50,  1; //InterfaceMethod scala/collection/generic/SequenceViewTemplate$Patched.scala$collection$generic$SequenceViewTemplate$Patched$$plen:()I
   77:	isub
   78:	aload_0
   79:	invokeinterface	#57,  1; //InterfaceMethod scala/collection/generic/SequenceViewTemplate$Patched.replaced:()I
   84:	iadd
   85:	invokeinterface	#47,  2; //InterfaceMethod scala/collection/generic/SequenceTemplate.apply:(I)Ljava/lang/Object;
   90:	areturn
  LineNumberTable: 
   line 120: 0
   line 121: 25
   line 122: 64
   line 120: 90

  LocalVariableTable: 
   Start  Length  Slot  Name   Signature
   0      91      0    $this       Lscala/collection/generic/SequenceViewTemplate$Patched;
   0      91      1    idx       I


public static int length(scala.collection.generic.SequenceViewTemplate$Patched);
  Code:
   Stack=2, Locals=1, Args_size=1
   0:	aload_0
   1:	invokeinterface	#42,  1; //InterfaceMethod scala/collection/generic/SequenceViewTemplate$Patched.scala$collection$generic$SequenceViewTemplate$Patched$$$outer:()Lscala/collection/generic/SequenceViewTemplate;
   6:	invokeinterface	#63,  1; //InterfaceMethod scala/collection/generic/SequenceTemplate.length:()I
   11:	aload_0
   12:	invokeinterface	#50,  1; //InterfaceMethod scala/collection/generic/SequenceViewTemplate$Patched.scala$collection$generic$SequenceViewTemplate$Patched$$plen:()I
   17:	iadd
   18:	aload_0
   19:	invokeinterface	#57,  1; //InterfaceMethod scala/collection/generic/SequenceViewTemplate$Patched.replaced:()I
   24:	isub
   25:	ireturn
  LineNumberTable: 
   line 118: 0

  LocalVariableTable: 
   Start  Length  Slot  Name   Signature
   0      26      0    $this       Lscala/collection/generic/SequenceViewTemplate$Patched;


public static scala.collection.Iterator iterator(scala.collection.generic.SequenceViewTemplate$Patched);
  Code:
   Stack=4, Locals=1, Args_size=1
   0:	aload_0
   1:	invokeinterface	#42,  1; //InterfaceMethod scala/collection/generic/SequenceViewTemplate$Patched.scala$collection$generic$SequenceViewTemplate$Patched$$$outer:()Lscala/collection/generic/SequenceViewTemplate;
   6:	invokeinterface	#70,  1; //InterfaceMethod scala/collection/generic/IterableTemplate.iterator:()Lscala/collection/Iterator;
   11:	aload_0
   12:	invokeinterface	#38,  1; //InterfaceMethod scala/collection/generic/SequenceViewTemplate$Patched.from:()I
   17:	aload_0
   18:	invokeinterface	#54,  1; //InterfaceMethod scala/collection/generic/SequenceViewTemplate$Patched.patch:()Lscala/collection/Sequence;
   23:	invokeinterface	#70,  1; //InterfaceMethod scala/collection/generic/IterableTemplate.iterator:()Lscala/collection/Iterator;
   28:	aload_0
   29:	invokeinterface	#57,  1; //InterfaceMethod scala/collection/generic/SequenceViewTemplate$Patched.replaced:()I
   34:	invokeinterface	#75,  4; //InterfaceMethod scala/collection/Iterator.patch:(ILscala/collection/Iterator;I)Ljava/lang/Object;
   39:	checkcast	#72; //class scala/collection/Iterator
   42:	areturn
  LineNumberTable: 
   line 117: 0

  LocalVariableTable: 
   Start  Length  Slot  Name   Signature
   0      43      0    $this       Lscala/collection/generic/SequenceViewTemplate$Patched;


public static final int scala$collection$generic$SequenceViewTemplate$Patched$$plen(scala.collection.generic.SequenceViewTemplate$Patched);
  Code:
   Stack=1, Locals=1, Args_size=1
   0:	aload_0
   1:	invokeinterface	#54,  1; //InterfaceMethod scala/collection/generic/SequenceViewTemplate$Patched.patch:()Lscala/collection/Sequence;
   6:	invokeinterface	#63,  1; //InterfaceMethod scala/collection/generic/SequenceTemplate.length:()I
   11:	ireturn
  LineNumberTable: 
   line 116: 0

  LocalVariableTable: 
   Start  Length  Slot  Name   Signature
   0      12      0    $this       Lscala/collection/generic/SequenceViewTemplate$Patched;


}

