Compiled from "SequenceViewTemplate.scala"
public abstract class scala.collection.generic.SequenceViewTemplate$Mapped$class extends java.lang.Object
  SourceFile: "SequenceViewTemplate.scala"
  Scala: length = 0x
   
  InnerClass: 
   public abstract #45= #19 of #44; //Mapped=class scala/collection/generic/SequenceViewTemplate$Mapped of class scala/collection/generic/SequenceViewTemplate
   public abstract #45= #13 of #47; //Mapped=class scala/collection/generic/TraversableViewTemplate$Mapped of class scala/collection/generic/TraversableViewTemplate
  minor version: 0
  major version: 49
  Constant pool:
const #1 = Asciz	SourceFile;
const #2 = Asciz	SequenceViewTemplate.scala;
const #3 = Asciz	$init$;
const #4 = Asciz	(Lscala/collection/generic/SequenceViewTemplate$Mapped;)V;
const #5 = Asciz	Code;
const #6 = Asciz	LineNumberTable;
const #7 = Asciz	$this;
const #8 = Asciz	Lscala/collection/generic/SequenceViewTemplate$Mapped;;
const #9 = Asciz	LocalVariableTable;
const #10 = Asciz	apply;
const #11 = Asciz	(Lscala/collection/generic/SequenceViewTemplate$Mapped;I)Ljava/lang/Object;;
const #12 = Asciz	scala/collection/generic/TraversableViewTemplate$Mapped;
const #13 = class	#12;	//  scala/collection/generic/TraversableViewTemplate$Mapped
const #14 = Asciz	mapping;
const #15 = Asciz	()Lscala/Function1;;
const #16 = NameAndType	#14:#15;//  mapping:()Lscala/Function1;
const #17 = InterfaceMethod	#13.#16;	//  scala/collection/generic/TraversableViewTemplate$Mapped.mapping:()Lscala/Function1;
const #18 = Asciz	scala/collection/generic/SequenceViewTemplate$Mapped;
const #19 = class	#18;	//  scala/collection/generic/SequenceViewTemplate$Mapped
const #20 = Asciz	scala$collection$generic$SequenceViewTemplate$Mapped$$$outer;
const #21 = Asciz	()Lscala/collection/generic/SequenceViewTemplate;;
const #22 = NameAndType	#20:#21;//  scala$collection$generic$SequenceViewTemplate$Mapped$$$outer:()Lscala/collection/generic/SequenceViewTemplate;
const #23 = InterfaceMethod	#19.#22;	//  scala/collection/generic/SequenceViewTemplate$Mapped.scala$collection$generic$SequenceViewTemplate$Mapped$$$outer:()Lscala/collection/generic/SequenceViewTemplate;
const #24 = Asciz	scala/collection/generic/SequenceTemplate;
const #25 = class	#24;	//  scala/collection/generic/SequenceTemplate
const #26 = Asciz	(I)Ljava/lang/Object;;
const #27 = NameAndType	#10:#26;//  apply:(I)Ljava/lang/Object;
const #28 = InterfaceMethod	#25.#27;	//  scala/collection/generic/SequenceTemplate.apply:(I)Ljava/lang/Object;
const #29 = Asciz	scala/Function1;
const #30 = class	#29;	//  scala/Function1
const #31 = Asciz	(Ljava/lang/Object;)Ljava/lang/Object;;
const #32 = NameAndType	#10:#31;//  apply:(Ljava/lang/Object;)Ljava/lang/Object;
const #33 = InterfaceMethod	#30.#32;	//  scala/Function1.apply:(Ljava/lang/Object;)Ljava/lang/Object;
const #34 = Asciz	idx;
const #35 = Asciz	I;
const #36 = Asciz	length;
const #37 = Asciz	(Lscala/collection/generic/SequenceViewTemplate$Mapped;)I;
const #38 = Asciz	()I;
const #39 = NameAndType	#36:#38;//  length:()I
const #40 = InterfaceMethod	#25.#39;	//  scala/collection/generic/SequenceTemplate.length:()I
const #41 = Asciz	Scala;
const #42 = Asciz	InnerClasses;
const #43 = Asciz	scala/collection/generic/SequenceViewTemplate;
const #44 = class	#43;	//  scala/collection/generic/SequenceViewTemplate
const #45 = Asciz	Mapped;
const #46 = Asciz	scala/collection/generic/TraversableViewTemplate;
const #47 = class	#46;	//  scala/collection/generic/TraversableViewTemplate
const #48 = Asciz	scala/collection/generic/SequenceViewTemplate$Mapped$class;
const #49 = class	#48;	//  scala/collection/generic/SequenceViewTemplate$Mapped$class
const #50 = Asciz	java/lang/Object;
const #51 = class	#50;	//  java/lang/Object

{
public static void $init$(scala.collection.generic.SequenceViewTemplate$Mapped);
  Code:
   Stack=0, Locals=1, Args_size=1
   0:	return
  LineNumberTable: 
   line 41: 0

  LocalVariableTable: 
   Start  Length  Slot  Name   Signature
   0      1      0    $this       Lscala/collection/generic/SequenceViewTemplate$Mapped;


public static java.lang.Object apply(scala.collection.generic.SequenceViewTemplate$Mapped, int);
  Code:
   Stack=3, Locals=2, Args_size=2
   0:	aload_0
   1:	invokeinterface	#17,  1; //InterfaceMethod scala/collection/generic/TraversableViewTemplate$Mapped.mapping:()Lscala/Function1;
   6:	aload_0
   7:	invokeinterface	#23,  1; //InterfaceMethod scala/collection/generic/SequenceViewTemplate$Mapped.scala$collection$generic$SequenceViewTemplate$Mapped$$$outer:()Lscala/collection/generic/SequenceViewTemplate;
   12:	iload_1
   13:	invokeinterface	#28,  2; //InterfaceMethod scala/collection/generic/SequenceTemplate.apply:(I)Ljava/lang/Object;
   18:	invokeinterface	#33,  2; //InterfaceMethod scala/Function1.apply:(Ljava/lang/Object;)Ljava/lang/Object;
   23:	areturn
  LineNumberTable: 
   line 43: 0

  LocalVariableTable: 
   Start  Length  Slot  Name   Signature
   0      24      0    $this       Lscala/collection/generic/SequenceViewTemplate$Mapped;
   0      24      1    idx       I


public static int length(scala.collection.generic.SequenceViewTemplate$Mapped);
  Code:
   Stack=1, Locals=1, Args_size=1
   0:	aload_0
   1:	invokeinterface	#23,  1; //InterfaceMethod scala/collection/generic/SequenceViewTemplate$Mapped.scala$collection$generic$SequenceViewTemplate$Mapped$$$outer:()Lscala/collection/generic/SequenceViewTemplate;
   6:	invokeinterface	#40,  1; //InterfaceMethod scala/collection/generic/SequenceTemplate.length:()I
   11:	ireturn
  LineNumberTable: 
   line 42: 0

  LocalVariableTable: 
   Start  Length  Slot  Name   Signature
   0      12      0    $this       Lscala/collection/generic/SequenceViewTemplate$Mapped;


}

