Compiled from "SetFactory.scala"
public final class scala.collection.generic.SetFactory$$anon$1 extends java.lang.Object implements scala.collection.generic.CanBuildFrom
  SourceFile: "SetFactory.scala"
  Signature: length = 0x2
   00 2C 
  Scala: length = 0x
   
  InnerClass: 
   public final $anon$1=class scala/collection/generic/SetFactory$$anon$1 of class scala/collection/generic/SetFactory
  minor version: 0
  major version: 49
  Constant pool:
Asciz	SourceFile;
Asciz	SetFactory.scala;
Asciz	$outer;
Asciz	Lscala/collection/generic/SetFactory;;
Asciz	<init>;
Asciz	(Lscala/collection/generic/SetFactory;)V;
Asciz	Code;
Asciz	LineNumberTable;
Asciz	java/lang/NullPointerException;
class	java/lang/NullPointerException
Asciz	()V;
NameAndType	"<init>":()V
Method	java/lang/NullPointerException."<init>":()V
Asciz	scala/collection/generic/SetFactory$$anon$1;
class	scala/collection/generic/SetFactory$$anon$1
NameAndType	$outer:Lscala/collection/generic/SetFactory;
Field	scala/collection/generic/SetFactory$$anon$1.$outer:Lscala/collection/generic/SetFactory;
Asciz	java/lang/Object;
class	java/lang/Object
Method	java/lang/Object."<init>":()V
Asciz	this;
Asciz	Lscala/collection/generic/SetFactory$$anon$1;;
Asciz	LocalVariableTable;
Asciz	(Lscala/collection/generic/SetFactory<TCC;>;)V;
Asciz	Signature;
Asciz	apply;
Asciz	(Ljava/lang/Object;)Lscala/collection/mutable/Builder;;
Asciz	scala/collection/Set;
class	scala/collection/Set
Asciz	(Lscala/collection/Set;)Lscala/collection/mutable/Builder;;
NameAndType	apply:(Lscala/collection/Set;)Lscala/collection/mutable/Builder;
Method	scala/collection/generic/SetFactory$$anon$1.apply:(Lscala/collection/Set;)Lscala/collection/mutable/Builder;
Asciz	from;
Asciz	Ljava/lang/Object;;
Asciz	()Lscala/collection/mutable/Builder;;
Asciz	scala/collection/generic/SetFactory;
class	scala/collection/generic/SetFactory
Asciz	newBuilder;
NameAndType	newBuilder:()Lscala/collection/mutable/Builder;
Method	scala/collection/generic/SetFactory.newBuilder:()Lscala/collection/mutable/Builder;
Asciz	()Lscala/collection/mutable/Builder<TA;TCC;>;;
Asciz	Lscala/collection/Set;;
Asciz	(TCC;)Lscala/collection/mutable/Builder<TA;TCC;>;;
Asciz	Ljava/lang/Object;Lscala/collection/generic/CanBuildFrom<TCC;TA;TCC;>;;
Asciz	Scala;
Asciz	InnerClasses;
Asciz	$anon$1;
Asciz	scala/collection/generic/CanBuildFrom;
class	scala/collection/generic/CanBuildFrom

{
public final scala.collection.generic.SetFactory $outer;
  Signature: Lscala/collection/generic/SetFactory;

public scala.collection.generic.SetFactory$$anon$1(scala.collection.generic.SetFactory);
  Signature: (Lscala/collection/generic/SetFactory;)V
  Code:
   Stack=2, Locals=2, Args_size=2
	aload_1
	ifnonnull	l1 // aload_0
	new	class java/lang/NullPointerException
	dup
	invokespecial	Method java/lang/NullPointerException."<init>":()V
	athrow
l1	aload_0
	aload_1
	putfield	Field $outer:Lscala/collection/generic/SetFactory;
	aload_0
	invokespecial	Method java/lang/Object."<init>":()V
	return
  Labels:
   	l1 = 12 // aload_0
  LocalVariableTable: 
   Start  Length  Slot  Name   Signature
   0      22      0    this       Lscala/collection/generic/SetFactory$$anon$1;
   0      22      1    $outer       Lscala/collection/generic/SetFactory;

  Signature: length = 0x2
   00 18 

public scala.collection.mutable.Builder apply(java.lang.Object);
  Signature: (Ljava/lang/Object;)Lscala/collection/mutable/Builder;
  Code:
   Stack=2, Locals=2, Args_size=2
	aload_0
	aload_1
	checkcast	class scala/collection/Set
	invokevirtual	Method apply:(Lscala/collection/Set;)Lscala/collection/mutable/Builder;
	areturn
  Labels:
  LocalVariableTable: 
   Start  Length  Slot  Name   Signature
   0      9      0    this       Lscala/collection/generic/SetFactory$$anon$1;
   0      9      1    from       Ljava/lang/Object;


public scala.collection.mutable.Builder apply();
  Signature: ()Lscala/collection/mutable/Builder;
  Code:
   Stack=1, Locals=1, Args_size=1
	aload_0
	getfield	Field $outer:Lscala/collection/generic/SetFactory;
	invokevirtual	Method scala/collection/generic/SetFactory.newBuilder:()Lscala/collection/mutable/Builder;
	areturn
  Labels:
  Signature: length = 0x2
   00 29 

public scala.collection.mutable.Builder apply(scala.collection.Set);
  Signature: (Lscala/collection/Set;)Lscala/collection/mutable/Builder;
  Code:
   Stack=1, Locals=2, Args_size=2
	aload_0
	getfield	Field $outer:Lscala/collection/generic/SetFactory;
	invokevirtual	Method scala/collection/generic/SetFactory.newBuilder:()Lscala/collection/mutable/Builder;
	areturn
  Labels:
  LocalVariableTable: 
   Start  Length  Slot  Name   Signature
   0      8      0    this       Lscala/collection/generic/SetFactory$$anon$1;
   0      8      1    from       Lscala/collection/Set;

  Signature: length = 0x2
   00 2B 

}

