Compiled from "SetFactory.scala"
public abstract class scala.collection.generic.SetFactory extends scala.collection.generic.GenericCompanion implements scala.ScalaObject
  SourceFile: "SetFactory.scala"
  Signature: length = 0x2
   00 24 
  ScalaSig: length = 0x299
   05 00 6E 06 05 01 02 FFFFFF81 00 09 02 0A 53 65 74 46
   61 63 74 6F 72 79 0A 02 03 04 01 07 67 65 6E 65
   72 69 63 0A 02 05 06 01 0A 63 6F 6C 6C 65 63 74
   69 6F 6E 0A 01 07 01 05 73 63 61 6C 61 03 00 15
   02 0A 11 13 03 00 0B 2B 10 03 0C 0D 0F 0D 01 02
   09 02 0E 02 02 10 47 65 6E 65 72 69 63 43 6F 6D
   70 61 6E 69 6F 6E 10 02 10 11 0C 00 04 05 12 00
   FFFFFFC2 00 13 02 02 43 43 15 02 14 21 11 02 15 19 10
   02 16 17 0D 01 06 09 02 18 06 02 07 4E 6F 74 68
   69 6E 67 12 03 1A 1C 27 06 08 1B 00 FFFFFF84 FFFFFF80 FFFFFF80 FFFFFF80
   00 19 02 0C 3C 72 65 66 69 6E 65 6D 65 6E 74 3E
   10 03 1D 1E 20 0D 01 04 09 02 1F 04 02 03 53 65
   74 10 02 10 21 04 08 22 11 FFFFFF84 FFFFFF80 FFFFFF80 FFFFFFC2 00 23 02
   01 58 11 02 15 24 10 02 16 25 09 02 26 06 02 03
   41 6E 79 10 04 1D 28 20 2A 09 02 29 04 02 07 53
   65 74 4C 69 6B 65 10 03 10 11 20 10 02 16 2C 09
   02 2D 06 02 0B 53 63 61 6C 61 4F 62 6A 65 63 74
   08 05 2F 00 FFFFFF84 00 30 01 06 3C 69 6E 69 74 3E 14
   01 31 10 03 0C 00 0F 08 05 33 00 FFFFFF84 00 34 01 0A
   6E 65 77 42 75 69 6C 64 65 72 15 02 35 3C 10 04
   36 39 3B 3E 0D 01 37 0A 02 38 04 01 07 6D 75 74
   61 62 6C 65 09 02 3A 37 02 07 42 75 69 6C 64 65
   72 10 02 10 3C 04 08 3D 32 FFFFFF84 FFFFFF80 FFFFFF80 FFFFFFC2 00 23 02
   01 41 10 03 10 11 3B 08 05 40 00 FFFFFF84 00 41 01 0F
   73 65 74 43 61 6E 42 75 69 6C 64 46 72 6F 6D 15
   02 42 6C 12 03 43 44 4C 06 08 1B 3F FFFFFF84 FFFFFF80 FFFFFF80 FFFFFF80
   00 42 10 02 45 4A 0D 01 46 0A 02 47 48 01 04 6C
   61 6E 67 0A 01 49 01 04 6A 61 76 61 09 02 4B 46
   02 06 4F 62 6A 65 63 74 10 05 0C 4D 4F 6B 6D 09
   02 4E 02 02 0C 43 61 6E 42 75 69 6C 64 46 72 6F
   6D 30 02 50 52 10 03 10 11 51 10 02 10 52 04 08
   53 54 FFFFFF84 FFFFFF80 FFFFFF80 FFFFFF82 00 23 02 03 5F 24 31 06 08 55
   3F FFFFFF84 FFFFFF80 FFFFFF80 FFFFFF80 02 56 02 05 24 61 6E 6F 6E 13 03
   54 44 57 10 05 0C 4D 4F 58 5A 10 02 10 59 04 08
   3D 3F FFFFFF84 FFFFFF80 FFFFFF80 FFFFFFC2 00 23 10 03 10 11 58 08 05 2F
   54 FFFFFF84 00 5C 14 01 5D 10 02 10 54 08 05 5F 54 FFFFFF84
   00 60 01 05 61 70 70 6C 79 14 02 61 62 10 04 36
   39 58 5A 08 05 63 5E FFFFFFC0 00 64 01 04 66 72 6F 6D
   30 02 65 67 10 03 10 11 66 10 02 10 67 04 08 68
   5E FFFFFF84 FFFFFF80 FFFFFF80 FFFFFF82 00 23 02 03 5F 24 32 08 05 5F 54
   FFFFFF84 00 6A 14 01 61 10 02 10 6C 04 08 3D 3F FFFFFF84 FFFFFF80
   FFFFFF80 FFFFFFC2 00 23 10 03 10 11 6B 
  InnerClass: 
   public final #39= #15 of #25; //$anon$1=class scala/collection/generic/SetFactory$$anon$1 of class scala/collection/generic/SetFactory
  minor version: 0
  major version: 49
  Constant pool:
const #1 = Asciz	SourceFile;
const #2 = Asciz	SetFactory.scala;
const #3 = Asciz	<init>;
const #4 = Asciz	()V;
const #5 = Asciz	Code;
const #6 = Asciz	LineNumberTable;
const #7 = Asciz	scala/collection/generic/GenericCompanion;
const #8 = class	#7;	//  scala/collection/generic/GenericCompanion
const #9 = NameAndType	#3:#4;//  "<init>":()V
const #10 = Method	#8.#9;	//  scala/collection/generic/GenericCompanion."<init>":()V
const #11 = Asciz	Signature;
const #12 = Asciz	setCanBuildFrom;
const #13 = Asciz	()Ljava/lang/Object;;
const #14 = Asciz	scala/collection/generic/SetFactory$$anon$1;
const #15 = class	#14;	//  scala/collection/generic/SetFactory$$anon$1
const #16 = Asciz	(Lscala/collection/generic/SetFactory;)V;
const #17 = NameAndType	#3:#16;//  "<init>":(Lscala/collection/generic/SetFactory;)V
const #18 = Method	#15.#17;	//  scala/collection/generic/SetFactory$$anon$1."<init>":(Lscala/collection/generic/SetFactory;)V
const #19 = Asciz	<A:Ljava/lang/Object;>()Ljava/lang/Object;;
const #20 = Asciz	newBuilder;
const #21 = Asciz	()Lscala/collection/mutable/Builder;;
const #22 = Asciz	scala/collection/mutable/AddingBuilder;
const #23 = class	#22;	//  scala/collection/mutable/AddingBuilder
const #24 = Asciz	scala/collection/generic/SetFactory;
const #25 = class	#24;	//  scala/collection/generic/SetFactory
const #26 = Asciz	empty;
const #27 = Asciz	()Lscala/collection/Traversable;;
const #28 = NameAndType	#26:#27;//  empty:()Lscala/collection/Traversable;
const #29 = Method	#25.#28;	//  scala/collection/generic/SetFactory.empty:()Lscala/collection/Traversable;
const #30 = Asciz	scala/collection/generic/Addable;
const #31 = class	#30;	//  scala/collection/generic/Addable
const #32 = Asciz	(Lscala/collection/generic/Addable;)V;
const #33 = NameAndType	#3:#32;//  "<init>":(Lscala/collection/generic/Addable;)V
const #34 = Method	#23.#33;	//  scala/collection/mutable/AddingBuilder."<init>":(Lscala/collection/generic/Addable;)V
const #35 = Asciz	<A:Ljava/lang/Object;>()Lscala/collection/mutable/Builder<TA;TCC;>;;
const #36 = Asciz	<CC:Lscala/collection/Set<Ljava/lang/Object;>;>Lscala/collection/generic/GenericCompanion<TCC;>;Lscala/ScalaObject;;
const #37 = Asciz	ScalaSig;
const #38 = Asciz	InnerClasses;
const #39 = Asciz	$anon$1;
const #40 = Asciz	scala/ScalaObject;
const #41 = class	#40;	//  scala/ScalaObject

{
public scala.collection.generic.SetFactory();
  Code:
   Stack=1, Locals=1, Args_size=1
   0:	aload_0
   1:	invokespecial	#10; //Method scala/collection/generic/GenericCompanion."<init>":()V
   4:	return
  LineNumberTable: 
   line 23: 0

  Signature: length = 0x2
   00 04 

public java.lang.Object setCanBuildFrom();
  Code:
   Stack=3, Locals=1, Args_size=1
   0:	new	#15; //class scala/collection/generic/SetFactory$$anon$1
   3:	dup
   4:	aload_0
   5:	invokespecial	#18; //Method scala/collection/generic/SetFactory$$anon$1."<init>":(Lscala/collection/generic/SetFactory;)V
   8:	areturn
  LineNumberTable: 
   line 27: 0

  Signature: length = 0x2
   00 13 

public scala.collection.mutable.Builder newBuilder();
  Code:
   Stack=3, Locals=1, Args_size=1
   0:	new	#23; //class scala/collection/mutable/AddingBuilder
   3:	dup
   4:	aload_0
   5:	invokevirtual	#29; //Method empty:()Lscala/collection/Traversable;
   8:	checkcast	#31; //class scala/collection/generic/Addable
   11:	invokespecial	#34; //Method scala/collection/mutable/AddingBuilder."<init>":(Lscala/collection/generic/Addable;)V
   14:	areturn
  LineNumberTable: 
   line 25: 0

  Signature: length = 0x2
   00 23 

}

