Compiled from "SetFactory.scala"
public final class scala.collection.generic.SetFactory$$anon$1 extends java.lang.Object implements scala.collection.generic.CanBuildFrom
  SourceFile: "SetFactory.scala"
  Signature: length = 0x2
   00 2C 
  Scala: length = 0x
   
  InnerClass: 
   public final #47= #15 of #37; //$anon$1=class scala/collection/generic/SetFactory$$anon$1 of class scala/collection/generic/SetFactory
  minor version: 0
  major version: 49
  Constant pool:
const #1 = Asciz	SourceFile;
const #2 = Asciz	SetFactory.scala;
const #3 = Asciz	$outer;
const #4 = Asciz	Lscala/collection/generic/SetFactory;;
const #5 = Asciz	<init>;
const #6 = Asciz	(Lscala/collection/generic/SetFactory;)V;
const #7 = Asciz	Code;
const #8 = Asciz	LineNumberTable;
const #9 = Asciz	java/lang/NullPointerException;
const #10 = class	#9;	//  java/lang/NullPointerException
const #11 = Asciz	()V;
const #12 = NameAndType	#5:#11;//  "<init>":()V
const #13 = Method	#10.#12;	//  java/lang/NullPointerException."<init>":()V
const #14 = Asciz	scala/collection/generic/SetFactory$$anon$1;
const #15 = class	#14;	//  scala/collection/generic/SetFactory$$anon$1
const #16 = NameAndType	#3:#4;//  $outer:Lscala/collection/generic/SetFactory;
const #17 = Field	#15.#16;	//  scala/collection/generic/SetFactory$$anon$1.$outer:Lscala/collection/generic/SetFactory;
const #18 = Asciz	java/lang/Object;
const #19 = class	#18;	//  java/lang/Object
const #20 = Method	#19.#12;	//  java/lang/Object."<init>":()V
const #21 = Asciz	this;
const #22 = Asciz	Lscala/collection/generic/SetFactory$$anon$1;;
const #23 = Asciz	LocalVariableTable;
const #24 = Asciz	(Lscala/collection/generic/SetFactory<TCC;>;)V;
const #25 = Asciz	Signature;
const #26 = Asciz	apply;
const #27 = Asciz	(Ljava/lang/Object;)Lscala/collection/mutable/Builder;;
const #28 = Asciz	scala/collection/Set;
const #29 = class	#28;	//  scala/collection/Set
const #30 = Asciz	(Lscala/collection/Set;)Lscala/collection/mutable/Builder;;
const #31 = NameAndType	#26:#30;//  apply:(Lscala/collection/Set;)Lscala/collection/mutable/Builder;
const #32 = Method	#15.#31;	//  scala/collection/generic/SetFactory$$anon$1.apply:(Lscala/collection/Set;)Lscala/collection/mutable/Builder;
const #33 = Asciz	from;
const #34 = Asciz	Ljava/lang/Object;;
const #35 = Asciz	()Lscala/collection/mutable/Builder;;
const #36 = Asciz	scala/collection/generic/SetFactory;
const #37 = class	#36;	//  scala/collection/generic/SetFactory
const #38 = Asciz	newBuilder;
const #39 = NameAndType	#38:#35;//  newBuilder:()Lscala/collection/mutable/Builder;
const #40 = Method	#37.#39;	//  scala/collection/generic/SetFactory.newBuilder:()Lscala/collection/mutable/Builder;
const #41 = Asciz	()Lscala/collection/mutable/Builder<TA;TCC;>;;
const #42 = Asciz	Lscala/collection/Set;;
const #43 = Asciz	(TCC;)Lscala/collection/mutable/Builder<TA;TCC;>;;
const #44 = Asciz	Ljava/lang/Object;Lscala/collection/generic/CanBuildFrom<TCC;TA;TCC;>;;
const #45 = Asciz	Scala;
const #46 = Asciz	InnerClasses;
const #47 = Asciz	$anon$1;
const #48 = Asciz	scala/collection/generic/CanBuildFrom;
const #49 = class	#48;	//  scala/collection/generic/CanBuildFrom

{
public scala.collection.generic.SetFactory$$anon$1(scala.collection.generic.SetFactory);
  Code:
   Stack=2, Locals=2, Args_size=2
   0:	aload_1
   1:	ifnonnull	12
   4:	new	#10; //class java/lang/NullPointerException
   7:	dup
   8:	invokespecial	#13; //Method java/lang/NullPointerException."<init>":()V
   11:	athrow
   12:	aload_0
   13:	aload_1
   14:	putfield	#17; //Field $outer:Lscala/collection/generic/SetFactory;
   17:	aload_0
   18:	invokespecial	#20; //Method java/lang/Object."<init>":()V
   21:	return
  LineNumberTable: 
   line 27: 0

  LocalVariableTable: 
   Start  Length  Slot  Name   Signature
   0      22      0    this       Lscala/collection/generic/SetFactory$$anon$1;
   0      22      1    $outer       Lscala/collection/generic/SetFactory;

  Signature: length = 0x2
   00 18 

public scala.collection.mutable.Builder apply(java.lang.Object);
  Code:
   Stack=2, Locals=2, Args_size=2
   0:	aload_0
   1:	aload_1
   2:	checkcast	#29; //class scala/collection/Set
   5:	invokevirtual	#32; //Method apply:(Lscala/collection/Set;)Lscala/collection/mutable/Builder;
   8:	areturn
  LineNumberTable: 
   line 27: 0

  LocalVariableTable: 
   Start  Length  Slot  Name   Signature
   0      9      0    this       Lscala/collection/generic/SetFactory$$anon$1;
   0      9      1    from       Ljava/lang/Object;


public scala.collection.mutable.Builder apply();
  Code:
   Stack=1, Locals=1, Args_size=1
   0:	aload_0
   1:	getfield	#17; //Field $outer:Lscala/collection/generic/SetFactory;
   4:	invokevirtual	#40; //Method scala/collection/generic/SetFactory.newBuilder:()Lscala/collection/mutable/Builder;
   7:	areturn
  LineNumberTable: 
   line 29: 0

  Signature: length = 0x2
   00 29 

public scala.collection.mutable.Builder apply(scala.collection.Set);
  Code:
   Stack=1, Locals=2, Args_size=2
   0:	aload_0
   1:	getfield	#17; //Field $outer:Lscala/collection/generic/SetFactory;
   4:	invokevirtual	#40; //Method scala/collection/generic/SetFactory.newBuilder:()Lscala/collection/mutable/Builder;
   7:	areturn
  LineNumberTable: 
   line 28: 0

  LocalVariableTable: 
   Start  Length  Slot  Name   Signature
   0      8      0    this       Lscala/collection/generic/SetFactory$$anon$1;
   0      8      1    from       Lscala/collection/Set;

  Signature: length = 0x2
   00 2B 

}

