Compiled from "SetProxyTemplate.scala"
public abstract class scala.collection.generic.SetProxyTemplate$class extends java.lang.Object
  SourceFile: "SetProxyTemplate.scala"
  Scala: length = 0x
   
  minor version: 0
  major version: 49
  Constant pool:
const #1 = Asciz	SourceFile;
const #2 = Asciz	SetProxyTemplate.scala;
const #3 = Asciz	$init$;
const #4 = Asciz	(Lscala/collection/generic/SetProxyTemplate;)V;
const #5 = Asciz	Code;
const #6 = Asciz	LineNumberTable;
const #7 = Asciz	$this;
const #8 = Asciz	Lscala/collection/generic/SetProxyTemplate;;
const #9 = Asciz	LocalVariableTable;
const #10 = Asciz	subsetOf;
const #11 = Asciz	(Lscala/collection/generic/SetProxyTemplate;Lscala/collection/Set;)Z;
const #12 = Asciz	scala/collection/generic/TraversableProxyTemplate;
const #13 = class	#12;	//  scala/collection/generic/TraversableProxyTemplate
const #14 = Asciz	self;
const #15 = Asciz	()Lscala/collection/generic/TraversableTemplate;;
const #16 = NameAndType	#14:#15;//  self:()Lscala/collection/generic/TraversableTemplate;
const #17 = InterfaceMethod	#13.#16;	//  scala/collection/generic/TraversableProxyTemplate.self:()Lscala/collection/generic/TraversableTemplate;
const #18 = Asciz	scala/collection/generic/SetTemplate;
const #19 = class	#18;	//  scala/collection/generic/SetTemplate
const #20 = Asciz	(Lscala/collection/Set;)Z;
const #21 = NameAndType	#10:#20;//  subsetOf:(Lscala/collection/Set;)Z
const #22 = InterfaceMethod	#19.#21;	//  scala/collection/generic/SetTemplate.subsetOf:(Lscala/collection/Set;)Z
const #23 = Asciz	that;
const #24 = Asciz	Lscala/collection/Set;;
const #25 = Asciz	$amp$tilde;
const #26 = Asciz	(Lscala/collection/generic/SetProxyTemplate;Lscala/collection/Set;)Lscala/collection/generic/SetTemplate;;
const #27 = Asciz	(Lscala/collection/Set;)Lscala/collection/generic/SetTemplate;;
const #28 = NameAndType	#25:#27;//  $amp$tilde:(Lscala/collection/Set;)Lscala/collection/generic/SetTemplate;
const #29 = InterfaceMethod	#19.#28;	//  scala/collection/generic/SetTemplate.$amp$tilde:(Lscala/collection/Set;)Lscala/collection/generic/SetTemplate;
const #30 = Asciz	diff;
const #31 = NameAndType	#30:#27;//  diff:(Lscala/collection/Set;)Lscala/collection/generic/SetTemplate;
const #32 = InterfaceMethod	#19.#31;	//  scala/collection/generic/SetTemplate.diff:(Lscala/collection/Set;)Lscala/collection/generic/SetTemplate;
const #33 = Asciz	$bar;
const #34 = NameAndType	#33:#27;//  $bar:(Lscala/collection/Set;)Lscala/collection/generic/SetTemplate;
const #35 = InterfaceMethod	#19.#34;	//  scala/collection/generic/SetTemplate.$bar:(Lscala/collection/Set;)Lscala/collection/generic/SetTemplate;
const #36 = Asciz	union;
const #37 = NameAndType	#36:#27;//  union:(Lscala/collection/Set;)Lscala/collection/generic/SetTemplate;
const #38 = InterfaceMethod	#19.#37;	//  scala/collection/generic/SetTemplate.union:(Lscala/collection/Set;)Lscala/collection/generic/SetTemplate;
const #39 = Asciz	$amp;
const #40 = NameAndType	#39:#27;//  $amp:(Lscala/collection/Set;)Lscala/collection/generic/SetTemplate;
const #41 = InterfaceMethod	#19.#40;	//  scala/collection/generic/SetTemplate.$amp:(Lscala/collection/Set;)Lscala/collection/generic/SetTemplate;
const #42 = Asciz	intersect;
const #43 = NameAndType	#42:#27;//  intersect:(Lscala/collection/Set;)Lscala/collection/generic/SetTemplate;
const #44 = InterfaceMethod	#19.#43;	//  scala/collection/generic/SetTemplate.intersect:(Lscala/collection/Set;)Lscala/collection/generic/SetTemplate;
const #45 = Asciz	apply;
const #46 = Asciz	(Lscala/collection/generic/SetProxyTemplate;Ljava/lang/Object;)Z;
const #47 = Asciz	(Ljava/lang/Object;)Z;
const #48 = NameAndType	#45:#47;//  apply:(Ljava/lang/Object;)Z
const #49 = InterfaceMethod	#19.#48;	//  scala/collection/generic/SetTemplate.apply:(Ljava/lang/Object;)Z
const #50 = Asciz	elem;
const #51 = Asciz	Ljava/lang/Object;;
const #52 = Asciz	isEmpty;
const #53 = Asciz	(Lscala/collection/generic/SetProxyTemplate;)Z;
const #54 = Asciz	()Z;
const #55 = NameAndType	#52:#54;//  isEmpty:()Z
const #56 = InterfaceMethod	#19.#55;	//  scala/collection/generic/SetTemplate.isEmpty:()Z
const #57 = Asciz	contains;
const #58 = NameAndType	#57:#47;//  contains:(Ljava/lang/Object;)Z
const #59 = InterfaceMethod	#19.#58;	//  scala/collection/generic/SetTemplate.contains:(Ljava/lang/Object;)Z
const #60 = Asciz	Scala;
const #61 = Asciz	scala/collection/generic/SetProxyTemplate$class;
const #62 = class	#61;	//  scala/collection/generic/SetProxyTemplate$class
const #63 = Asciz	java/lang/Object;
const #64 = class	#63;	//  java/lang/Object

{
public static void $init$(scala.collection.generic.SetProxyTemplate);
  Code:
   Stack=0, Locals=1, Args_size=1
   0:	return
  LineNumberTable: 
   line 21: 0

  LocalVariableTable: 
   Start  Length  Slot  Name   Signature
   0      1      0    $this       Lscala/collection/generic/SetProxyTemplate;


public static boolean subsetOf(scala.collection.generic.SetProxyTemplate, scala.collection.Set);
  Code:
   Stack=2, Locals=2, Args_size=2
   0:	aload_0
   1:	invokeinterface	#17,  1; //InterfaceMethod scala/collection/generic/TraversableProxyTemplate.self:()Lscala/collection/generic/TraversableTemplate;
   6:	checkcast	#19; //class scala/collection/generic/SetTemplate
   9:	aload_1
   10:	invokeinterface	#22,  2; //InterfaceMethod scala/collection/generic/SetTemplate.subsetOf:(Lscala/collection/Set;)Z
   15:	ireturn
  LineNumberTable: 
   line 35: 0

  LocalVariableTable: 
   Start  Length  Slot  Name   Signature
   0      16      0    $this       Lscala/collection/generic/SetProxyTemplate;
   0      16      1    that       Lscala/collection/Set;


public static scala.collection.generic.SetTemplate $amp$tilde(scala.collection.generic.SetProxyTemplate, scala.collection.Set);
  Code:
   Stack=2, Locals=2, Args_size=2
   0:	aload_0
   1:	invokeinterface	#17,  1; //InterfaceMethod scala/collection/generic/TraversableProxyTemplate.self:()Lscala/collection/generic/TraversableTemplate;
   6:	checkcast	#19; //class scala/collection/generic/SetTemplate
   9:	aload_1
   10:	invokeinterface	#29,  2; //InterfaceMethod scala/collection/generic/SetTemplate.$amp$tilde:(Lscala/collection/Set;)Lscala/collection/generic/SetTemplate;
   15:	areturn
  LineNumberTable: 
   line 34: 0

  LocalVariableTable: 
   Start  Length  Slot  Name   Signature
   0      16      0    $this       Lscala/collection/generic/SetProxyTemplate;
   0      16      1    that       Lscala/collection/Set;


public static scala.collection.generic.SetTemplate diff(scala.collection.generic.SetProxyTemplate, scala.collection.Set);
  Code:
   Stack=2, Locals=2, Args_size=2
   0:	aload_0
   1:	invokeinterface	#17,  1; //InterfaceMethod scala/collection/generic/TraversableProxyTemplate.self:()Lscala/collection/generic/TraversableTemplate;
   6:	checkcast	#19; //class scala/collection/generic/SetTemplate
   9:	aload_1
   10:	invokeinterface	#32,  2; //InterfaceMethod scala/collection/generic/SetTemplate.diff:(Lscala/collection/Set;)Lscala/collection/generic/SetTemplate;
   15:	areturn
  LineNumberTable: 
   line 33: 0

  LocalVariableTable: 
   Start  Length  Slot  Name   Signature
   0      16      0    $this       Lscala/collection/generic/SetProxyTemplate;
   0      16      1    that       Lscala/collection/Set;


public static scala.collection.generic.SetTemplate $bar(scala.collection.generic.SetProxyTemplate, scala.collection.Set);
  Code:
   Stack=2, Locals=2, Args_size=2
   0:	aload_0
   1:	invokeinterface	#17,  1; //InterfaceMethod scala/collection/generic/TraversableProxyTemplate.self:()Lscala/collection/generic/TraversableTemplate;
   6:	checkcast	#19; //class scala/collection/generic/SetTemplate
   9:	aload_1
   10:	invokeinterface	#35,  2; //InterfaceMethod scala/collection/generic/SetTemplate.$bar:(Lscala/collection/Set;)Lscala/collection/generic/SetTemplate;
   15:	areturn
  LineNumberTable: 
   line 32: 0

  LocalVariableTable: 
   Start  Length  Slot  Name   Signature
   0      16      0    $this       Lscala/collection/generic/SetProxyTemplate;
   0      16      1    that       Lscala/collection/Set;


public static scala.collection.generic.SetTemplate union(scala.collection.generic.SetProxyTemplate, scala.collection.Set);
  Code:
   Stack=2, Locals=2, Args_size=2
   0:	aload_0
   1:	invokeinterface	#17,  1; //InterfaceMethod scala/collection/generic/TraversableProxyTemplate.self:()Lscala/collection/generic/TraversableTemplate;
   6:	checkcast	#19; //class scala/collection/generic/SetTemplate
   9:	aload_1
   10:	invokeinterface	#38,  2; //InterfaceMethod scala/collection/generic/SetTemplate.union:(Lscala/collection/Set;)Lscala/collection/generic/SetTemplate;
   15:	areturn
  LineNumberTable: 
   line 31: 0

  LocalVariableTable: 
   Start  Length  Slot  Name   Signature
   0      16      0    $this       Lscala/collection/generic/SetProxyTemplate;
   0      16      1    that       Lscala/collection/Set;


public static scala.collection.generic.SetTemplate $amp(scala.collection.generic.SetProxyTemplate, scala.collection.Set);
  Code:
   Stack=2, Locals=2, Args_size=2
   0:	aload_0
   1:	invokeinterface	#17,  1; //InterfaceMethod scala/collection/generic/TraversableProxyTemplate.self:()Lscala/collection/generic/TraversableTemplate;
   6:	checkcast	#19; //class scala/collection/generic/SetTemplate
   9:	aload_1
   10:	invokeinterface	#41,  2; //InterfaceMethod scala/collection/generic/SetTemplate.$amp:(Lscala/collection/Set;)Lscala/collection/generic/SetTemplate;
   15:	areturn
  LineNumberTable: 
   line 30: 0

  LocalVariableTable: 
   Start  Length  Slot  Name   Signature
   0      16      0    $this       Lscala/collection/generic/SetProxyTemplate;
   0      16      1    that       Lscala/collection/Set;


public static scala.collection.generic.SetTemplate intersect(scala.collection.generic.SetProxyTemplate, scala.collection.Set);
  Code:
   Stack=2, Locals=2, Args_size=2
   0:	aload_0
   1:	invokeinterface	#17,  1; //InterfaceMethod scala/collection/generic/TraversableProxyTemplate.self:()Lscala/collection/generic/TraversableTemplate;
   6:	checkcast	#19; //class scala/collection/generic/SetTemplate
   9:	aload_1
   10:	invokeinterface	#44,  2; //InterfaceMethod scala/collection/generic/SetTemplate.intersect:(Lscala/collection/Set;)Lscala/collection/generic/SetTemplate;
   15:	areturn
  LineNumberTable: 
   line 29: 0

  LocalVariableTable: 
   Start  Length  Slot  Name   Signature
   0      16      0    $this       Lscala/collection/generic/SetProxyTemplate;
   0      16      1    that       Lscala/collection/Set;


public static boolean apply(scala.collection.generic.SetProxyTemplate, java.lang.Object);
  Code:
   Stack=2, Locals=2, Args_size=2
   0:	aload_0
   1:	invokeinterface	#17,  1; //InterfaceMethod scala/collection/generic/TraversableProxyTemplate.self:()Lscala/collection/generic/TraversableTemplate;
   6:	checkcast	#19; //class scala/collection/generic/SetTemplate
   9:	aload_1
   10:	invokeinterface	#49,  2; //InterfaceMethod scala/collection/generic/SetTemplate.apply:(Ljava/lang/Object;)Z
   15:	ireturn
  LineNumberTable: 
   line 28: 0

  LocalVariableTable: 
   Start  Length  Slot  Name   Signature
   0      16      0    $this       Lscala/collection/generic/SetProxyTemplate;
   0      16      1    elem       Ljava/lang/Object;


public static boolean isEmpty(scala.collection.generic.SetProxyTemplate);
  Code:
   Stack=1, Locals=1, Args_size=1
   0:	aload_0
   1:	invokeinterface	#17,  1; //InterfaceMethod scala/collection/generic/TraversableProxyTemplate.self:()Lscala/collection/generic/TraversableTemplate;
   6:	checkcast	#19; //class scala/collection/generic/SetTemplate
   9:	invokeinterface	#56,  1; //InterfaceMethod scala/collection/generic/SetTemplate.isEmpty:()Z
   14:	ireturn
  LineNumberTable: 
   line 27: 0

  LocalVariableTable: 
   Start  Length  Slot  Name   Signature
   0      15      0    $this       Lscala/collection/generic/SetProxyTemplate;


public static boolean contains(scala.collection.generic.SetProxyTemplate, java.lang.Object);
  Code:
   Stack=2, Locals=2, Args_size=2
   0:	aload_0
   1:	invokeinterface	#17,  1; //InterfaceMethod scala/collection/generic/TraversableProxyTemplate.self:()Lscala/collection/generic/TraversableTemplate;
   6:	checkcast	#19; //class scala/collection/generic/SetTemplate
   9:	aload_1
   10:	invokeinterface	#59,  2; //InterfaceMethod scala/collection/generic/SetTemplate.contains:(Ljava/lang/Object;)Z
   15:	ireturn
  LineNumberTable: 
   line 26: 0

  LocalVariableTable: 
   Start  Length  Slot  Name   Signature
   0      16      0    $this       Lscala/collection/generic/SetProxyTemplate;
   0      16      1    elem       Ljava/lang/Object;


}

