Compiled from "SetTemplate.scala"
public abstract class scala.collection.generic.SetTemplate$class extends java.lang.Object
  SourceFile: "SetTemplate.scala"
  Scala: length = 0x
   
  InnerClass: 
   public final #114= #48 of #31; //$anonfun$subsetOf$1=class scala/collection/generic/SetTemplate$$anonfun$subsetOf$1 of class scala/collection/generic/SetTemplate
   public final #115= #86 of #31; //$anonfun$intersect$1=class scala/collection/generic/SetTemplate$$anonfun$intersect$1 of class scala/collection/generic/SetTemplate
  minor version: 0
  major version: 49
  Constant pool:
const #1 = Asciz	SourceFile;
const #2 = Asciz	SetTemplate.scala;
const #3 = Asciz	$init$;
const #4 = Asciz	(Lscala/collection/generic/SetTemplate;)V;
const #5 = Asciz	Code;
const #6 = Asciz	LineNumberTable;
const #7 = Asciz	$this;
const #8 = Asciz	Lscala/collection/generic/SetTemplate;;
const #9 = Asciz	LocalVariableTable;
const #10 = Asciz	toString;
const #11 = Asciz	(Lscala/collection/generic/SetTemplate;)Ljava/lang/String;;
const #12 = Asciz	scala/collection/generic/TraversableTemplate$class;
const #13 = class	#12;	//  scala/collection/generic/TraversableTemplate$class
const #14 = Asciz	(Lscala/collection/generic/TraversableTemplate;)Ljava/lang/String;;
const #15 = NameAndType	#10:#14;//  toString:(Lscala/collection/generic/TraversableTemplate;)Ljava/lang/String;
const #16 = Method	#13.#15;	//  scala/collection/generic/TraversableTemplate$class.toString:(Lscala/collection/generic/TraversableTemplate;)Ljava/lang/String;
const #17 = Asciz	stringPrefix;
const #18 = Asciz	Set;
const #19 = String	#18;	//  Set
const #20 = Asciz	equals;
const #21 = Asciz	(Lscala/collection/generic/SetTemplate;Ljava/lang/Object;)Z;
const #22 = Asciz	scala/collection/Set;
const #23 = class	#22;	//  scala/collection/Set
const #24 = Asciz	scala/collection/generic/TraversableTemplate;
const #25 = class	#24;	//  scala/collection/generic/TraversableTemplate
const #26 = Asciz	size;
const #27 = Asciz	()I;
const #28 = NameAndType	#26:#27;//  size:()I
const #29 = InterfaceMethod	#25.#28;	//  scala/collection/generic/TraversableTemplate.size:()I
const #30 = Asciz	scala/collection/generic/SetTemplate;
const #31 = class	#30;	//  scala/collection/generic/SetTemplate
const #32 = Asciz	subsetOf;
const #33 = Asciz	(Lscala/collection/Set;)Z;
const #34 = NameAndType	#32:#33;//  subsetOf:(Lscala/collection/Set;)Z
const #35 = InterfaceMethod	#31.#34;	//  scala/collection/generic/SetTemplate.subsetOf:(Lscala/collection/Set;)Z
const #36 = Asciz	java/lang/ClassCastException;
const #37 = class	#36;	//  java/lang/ClassCastException
const #38 = Asciz	that;
const #39 = Asciz	Ljava/lang/Object;;
const #40 = Asciz	temp1;
const #41 = Asciz	temp2;
const #42 = Asciz	Lscala/collection/Set;;
const #43 = Asciz	other;
const #44 = Asciz	exceptionResult1;
const #45 = Asciz	Z;
const #46 = Asciz	(Lscala/collection/generic/SetTemplate;Lscala/collection/Set;)Z;
const #47 = Asciz	scala/collection/generic/SetTemplate$$anonfun$subsetOf$1;
const #48 = class	#47;	//  scala/collection/generic/SetTemplate$$anonfun$subsetOf$1
const #49 = Asciz	<init>;
const #50 = Asciz	(Lscala/collection/generic/SetTemplate;Lscala/collection/Set;)V;
const #51 = NameAndType	#49:#50;//  "<init>":(Lscala/collection/generic/SetTemplate;Lscala/collection/Set;)V
const #52 = Method	#48.#51;	//  scala/collection/generic/SetTemplate$$anonfun$subsetOf$1."<init>":(Lscala/collection/generic/SetTemplate;Lscala/collection/Set;)V
const #53 = Asciz	forall;
const #54 = Asciz	(Lscala/Function1;)Z;
const #55 = NameAndType	#53:#54;//  forall:(Lscala/Function1;)Z
const #56 = InterfaceMethod	#25.#55;	//  scala/collection/generic/TraversableTemplate.forall:(Lscala/Function1;)Z
const #57 = Asciz	that$2;
const #58 = Asciz	$amp$tilde;
const #59 = Asciz	(Lscala/collection/generic/SetTemplate;Lscala/collection/Set;)Lscala/collection/generic/SetTemplate;;
const #60 = Asciz	diff;
const #61 = Asciz	(Lscala/collection/Set;)Lscala/collection/generic/SetTemplate;;
const #62 = NameAndType	#60:#61;//  diff:(Lscala/collection/Set;)Lscala/collection/generic/SetTemplate;
const #63 = InterfaceMethod	#31.#62;	//  scala/collection/generic/SetTemplate.diff:(Lscala/collection/Set;)Lscala/collection/generic/SetTemplate;
const #64 = Asciz	scala/collection/generic/Subtractable;
const #65 = class	#64;	//  scala/collection/generic/Subtractable
const #66 = Asciz	$minus$minus;
const #67 = Asciz	(Lscala/collection/Traversable;)Lscala/collection/generic/Subtractable;;
const #68 = NameAndType	#66:#67;//  $minus$minus:(Lscala/collection/Traversable;)Lscala/collection/generic/Subtractable;
const #69 = InterfaceMethod	#65.#68;	//  scala/collection/generic/Subtractable.$minus$minus:(Lscala/collection/Traversable;)Lscala/collection/generic/Subtractable;
const #70 = Asciz	$bar;
const #71 = Asciz	union;
const #72 = NameAndType	#71:#61;//  union:(Lscala/collection/Set;)Lscala/collection/generic/SetTemplate;
const #73 = InterfaceMethod	#31.#72;	//  scala/collection/generic/SetTemplate.union:(Lscala/collection/Set;)Lscala/collection/generic/SetTemplate;
const #74 = Asciz	scala/collection/generic/Addable;
const #75 = class	#74;	//  scala/collection/generic/Addable
const #76 = Asciz	$plus$plus;
const #77 = Asciz	(Lscala/collection/Traversable;)Lscala/collection/generic/Addable;;
const #78 = NameAndType	#76:#77;//  $plus$plus:(Lscala/collection/Traversable;)Lscala/collection/generic/Addable;
const #79 = InterfaceMethod	#75.#78;	//  scala/collection/generic/Addable.$plus$plus:(Lscala/collection/Traversable;)Lscala/collection/generic/Addable;
const #80 = Asciz	$times$times;
const #81 = Asciz	intersect;
const #82 = NameAndType	#81:#61;//  intersect:(Lscala/collection/Set;)Lscala/collection/generic/SetTemplate;
const #83 = InterfaceMethod	#31.#82;	//  scala/collection/generic/SetTemplate.intersect:(Lscala/collection/Set;)Lscala/collection/generic/SetTemplate;
const #84 = Asciz	$amp;
const #85 = Asciz	scala/collection/generic/SetTemplate$$anonfun$intersect$1;
const #86 = class	#85;	//  scala/collection/generic/SetTemplate$$anonfun$intersect$1
const #87 = Method	#86.#51;	//  scala/collection/generic/SetTemplate$$anonfun$intersect$1."<init>":(Lscala/collection/generic/SetTemplate;Lscala/collection/Set;)V
const #88 = Asciz	filter;
const #89 = Asciz	(Lscala/Function1;)Lscala/collection/generic/TraversableTemplate;;
const #90 = NameAndType	#88:#89;//  filter:(Lscala/Function1;)Lscala/collection/generic/TraversableTemplate;
const #91 = InterfaceMethod	#25.#90;	//  scala/collection/generic/TraversableTemplate.filter:(Lscala/Function1;)Lscala/collection/generic/TraversableTemplate;
const #92 = Asciz	that$1;
const #93 = Asciz	apply;
const #94 = Asciz	contains;
const #95 = Asciz	(Ljava/lang/Object;)Z;
const #96 = NameAndType	#94:#95;//  contains:(Ljava/lang/Object;)Z
const #97 = InterfaceMethod	#31.#96;	//  scala/collection/generic/SetTemplate.contains:(Ljava/lang/Object;)Z
const #98 = Asciz	elem;
const #99 = Asciz	isEmpty;
const #100 = Asciz	(Lscala/collection/generic/SetTemplate;)Z;
const #101 = Asciz	newBuilder;
const #102 = Asciz	(Lscala/collection/generic/SetTemplate;)Lscala/collection/generic/Builder;;
const #103 = Asciz	scala/collection/generic/AddingBuilder;
const #104 = class	#103;	//  scala/collection/generic/AddingBuilder
const #105 = Asciz	empty;
const #106 = Asciz	()Lscala/collection/generic/SetTemplate;;
const #107 = NameAndType	#105:#106;//  empty:()Lscala/collection/generic/SetTemplate;
const #108 = InterfaceMethod	#31.#107;	//  scala/collection/generic/SetTemplate.empty:()Lscala/collection/generic/SetTemplate;
const #109 = Asciz	(Lscala/collection/generic/Addable;)V;
const #110 = NameAndType	#49:#109;//  "<init>":(Lscala/collection/generic/Addable;)V
const #111 = Method	#104.#110;	//  scala/collection/generic/AddingBuilder."<init>":(Lscala/collection/generic/Addable;)V
const #112 = Asciz	Scala;
const #113 = Asciz	InnerClasses;
const #114 = Asciz	$anonfun$subsetOf$1;
const #115 = Asciz	$anonfun$intersect$1;
const #116 = Asciz	scala/collection/generic/SetTemplate$class;
const #117 = class	#116;	//  scala/collection/generic/SetTemplate$class
const #118 = Asciz	java/lang/Object;
const #119 = class	#118;	//  java/lang/Object

{
public static void $init$(scala.collection.generic.SetTemplate);
  Code:
   Stack=0, Locals=1, Args_size=1
   0:	return
  LineNumberTable: 
   line 39: 0

  LocalVariableTable: 
   Start  Length  Slot  Name   Signature
   0      1      0    $this       Lscala/collection/generic/SetTemplate;


public static java.lang.String toString(scala.collection.generic.SetTemplate);
  Code:
   Stack=1, Locals=1, Args_size=1
   0:	aload_0
   1:	invokestatic	#16; //Method scala/collection/generic/TraversableTemplate$class.toString:(Lscala/collection/generic/TraversableTemplate;)Ljava/lang/String;
   4:	areturn
  LineNumberTable: 
   line 184: 0

  LocalVariableTable: 
   Start  Length  Slot  Name   Signature
   0      5      0    $this       Lscala/collection/generic/SetTemplate;


public static java.lang.String stringPrefix(scala.collection.generic.SetTemplate);
  Code:
   Stack=1, Locals=1, Args_size=1
   0:	ldc	#19; //String Set
   2:	areturn
  LineNumberTable: 
   line 180: 0

  LocalVariableTable: 
   Start  Length  Slot  Name   Signature
   0      3      0    $this       Lscala/collection/generic/SetTemplate;


public static boolean equals(scala.collection.generic.SetTemplate, java.lang.Object);
  Code:
   Stack=2, Locals=7, Args_size=2
   0:	aload_1
   1:	astore_2
   2:	aload_2
   3:	instanceof	#23; //class scala/collection/Set
   6:	ifeq	53
   9:	aload_2
   10:	checkcast	#23; //class scala/collection/Set
   13:	astore_3
   14:	aload_3
   15:	astore	4
   17:	aload_0
   18:	invokeinterface	#29,  1; //InterfaceMethod scala/collection/generic/TraversableTemplate.size:()I
   23:	aload	4
   25:	invokeinterface	#29,  1; //InterfaceMethod scala/collection/generic/TraversableTemplate.size:()I
   30:	if_icmpne	49
   33:	iconst_0
   34:	istore	5
   36:	aload_0
   37:	aload	4
   39:	invokeinterface	#35,  2; //InterfaceMethod scala/collection/generic/SetTemplate.subsetOf:(Lscala/collection/Set;)Z
   44:	istore	5
   46:	goto	62
   49:	iconst_0
   50:	goto	64
   53:	iconst_0
   54:	goto	64
   57:	astore	6
   59:	iconst_0
   60:	istore	5
   62:	iload	5
   64:	ireturn
  Exception table:
   from   to  target type
    36    49    57   Class java/lang/ClassCastException

  LineNumberTable: 
   line 165: 0
   line 166: 14
   line 167: 17
   line 169: 33
   line 168: 34
   line 169: 36
   line 173: 49
   line 175: 53
   line 171: 57
   line 165: 62

  LocalVariableTable: 
   Start  Length  Slot  Name   Signature
   0      65      0    $this       Lscala/collection/generic/SetTemplate;
   0      65      1    that       Ljava/lang/Object;
   2      63      2    temp1       Ljava/lang/Object;
   14      39      3    temp2       Lscala/collection/Set;
   57      7      3    temp2       Lscala/collection/Set;
   17      36      4    other       Lscala/collection/Set;
   57      7      4    other       Lscala/collection/Set;
   36      13      5    exceptionResult1       Z
   57      7      5    exceptionResult1       Z


public static boolean subsetOf(scala.collection.generic.SetTemplate, scala.collection.Set);
  Code:
   Stack=5, Locals=2, Args_size=2
   0:	aload_0
   1:	new	#48; //class scala/collection/generic/SetTemplate$$anonfun$subsetOf$1
   4:	dup
   5:	aload_0
   6:	aload_1
   7:	invokespecial	#52; //Method scala/collection/generic/SetTemplate$$anonfun$subsetOf$1."<init>":(Lscala/collection/generic/SetTemplate;Lscala/collection/Set;)V
   10:	invokeinterface	#56,  2; //InterfaceMethod scala/collection/generic/TraversableTemplate.forall:(Lscala/Function1;)Z
   15:	ireturn
  LineNumberTable: 
   line 154: 0

  LocalVariableTable: 
   Start  Length  Slot  Name   Signature
   0      16      0    $this       Lscala/collection/generic/SetTemplate;
   0      16      1    that$2       Lscala/collection/Set;


public static scala.collection.generic.SetTemplate $amp$tilde(scala.collection.generic.SetTemplate, scala.collection.Set);
  Code:
   Stack=2, Locals=2, Args_size=2
   0:	aload_0
   1:	aload_1
   2:	invokeinterface	#63,  2; //InterfaceMethod scala/collection/generic/SetTemplate.diff:(Lscala/collection/Set;)Lscala/collection/generic/SetTemplate;
   7:	areturn
  LineNumberTable: 
   line 145: 0

  LocalVariableTable: 
   Start  Length  Slot  Name   Signature
   0      8      0    $this       Lscala/collection/generic/SetTemplate;
   0      8      1    that       Lscala/collection/Set;


public static scala.collection.generic.SetTemplate diff(scala.collection.generic.SetTemplate, scala.collection.Set);
  Code:
   Stack=2, Locals=2, Args_size=2
   0:	aload_0
   1:	aload_1
   2:	invokeinterface	#69,  2; //InterfaceMethod scala/collection/generic/Subtractable.$minus$minus:(Lscala/collection/Traversable;)Lscala/collection/generic/Subtractable;
   7:	checkcast	#31; //class scala/collection/generic/SetTemplate
   10:	areturn
  LineNumberTable: 
   line 136: 0

  LocalVariableTable: 
   Start  Length  Slot  Name   Signature
   0      11      0    $this       Lscala/collection/generic/SetTemplate;
   0      11      1    that       Lscala/collection/Set;


public static scala.collection.generic.SetTemplate $bar(scala.collection.generic.SetTemplate, scala.collection.Set);
  Code:
   Stack=2, Locals=2, Args_size=2
   0:	aload_0
   1:	aload_1
   2:	invokeinterface	#73,  2; //InterfaceMethod scala/collection/generic/SetTemplate.union:(Lscala/collection/Set;)Lscala/collection/generic/SetTemplate;
   7:	areturn
  LineNumberTable: 
   line 128: 0

  LocalVariableTable: 
   Start  Length  Slot  Name   Signature
   0      8      0    $this       Lscala/collection/generic/SetTemplate;
   0      8      1    that       Lscala/collection/Set;


public static scala.collection.generic.SetTemplate union(scala.collection.generic.SetTemplate, scala.collection.Set);
  Code:
   Stack=2, Locals=2, Args_size=2
   0:	aload_0
   1:	aload_1
   2:	invokeinterface	#79,  2; //InterfaceMethod scala/collection/generic/Addable.$plus$plus:(Lscala/collection/Traversable;)Lscala/collection/generic/Addable;
   7:	checkcast	#31; //class scala/collection/generic/SetTemplate
   10:	areturn
  LineNumberTable: 
   line 119: 0

  LocalVariableTable: 
   Start  Length  Slot  Name   Signature
   0      11      0    $this       Lscala/collection/generic/SetTemplate;
   0      11      1    that       Lscala/collection/Set;


public static scala.collection.generic.SetTemplate $times$times(scala.collection.generic.SetTemplate, scala.collection.Set);
  Code:
   Stack=2, Locals=2, Args_size=2
   0:	aload_0
   1:	aload_1
   2:	invokeinterface	#83,  2; //InterfaceMethod scala/collection/generic/SetTemplate.intersect:(Lscala/collection/Set;)Lscala/collection/generic/SetTemplate;
   7:	areturn
  LineNumberTable: 
   line 111: 0

  LocalVariableTable: 
   Start  Length  Slot  Name   Signature
   0      8      0    $this       Lscala/collection/generic/SetTemplate;
   0      8      1    that       Lscala/collection/Set;


public static scala.collection.generic.SetTemplate $amp(scala.collection.generic.SetTemplate, scala.collection.Set);
  Code:
   Stack=2, Locals=2, Args_size=2
   0:	aload_0
   1:	aload_1
   2:	invokeinterface	#83,  2; //InterfaceMethod scala/collection/generic/SetTemplate.intersect:(Lscala/collection/Set;)Lscala/collection/generic/SetTemplate;
   7:	areturn
  LineNumberTable: 
   line 103: 0

  LocalVariableTable: 
   Start  Length  Slot  Name   Signature
   0      8      0    $this       Lscala/collection/generic/SetTemplate;
   0      8      1    that       Lscala/collection/Set;


public static scala.collection.generic.SetTemplate intersect(scala.collection.generic.SetTemplate, scala.collection.Set);
  Code:
   Stack=5, Locals=2, Args_size=2
   0:	aload_0
   1:	new	#86; //class scala/collection/generic/SetTemplate$$anonfun$intersect$1
   4:	dup
   5:	aload_0
   6:	aload_1
   7:	invokespecial	#87; //Method scala/collection/generic/SetTemplate$$anonfun$intersect$1."<init>":(Lscala/collection/generic/SetTemplate;Lscala/collection/Set;)V
   10:	invokeinterface	#91,  2; //InterfaceMethod scala/collection/generic/TraversableTemplate.filter:(Lscala/Function1;)Lscala/collection/generic/TraversableTemplate;
   15:	checkcast	#31; //class scala/collection/generic/SetTemplate
   18:	areturn
  LineNumberTable: 
   line 95: 0

  LocalVariableTable: 
   Start  Length  Slot  Name   Signature
   0      19      0    $this       Lscala/collection/generic/SetTemplate;
   0      19      1    that$1       Lscala/collection/Set;


public static boolean apply(scala.collection.generic.SetTemplate, java.lang.Object);
  Code:
   Stack=2, Locals=2, Args_size=2
   0:	aload_0
   1:	aload_1
   2:	invokeinterface	#97,  2; //InterfaceMethod scala/collection/generic/SetTemplate.contains:(Ljava/lang/Object;)Z
   7:	ireturn
  LineNumberTable: 
   line 88: 0

  LocalVariableTable: 
   Start  Length  Slot  Name   Signature
   0      8      0    $this       Lscala/collection/generic/SetTemplate;
   0      8      1    elem       Ljava/lang/Object;


public static boolean isEmpty(scala.collection.generic.SetTemplate);
  Code:
   Stack=2, Locals=1, Args_size=1
   0:	aload_0
   1:	invokeinterface	#29,  1; //InterfaceMethod scala/collection/generic/TraversableTemplate.size:()I
   6:	iconst_0
   7:	if_icmpne	14
   10:	iconst_1
   11:	goto	15
   14:	iconst_0
   15:	ireturn
  LineNumberTable: 
   line 78: 0

  LocalVariableTable: 
   Start  Length  Slot  Name   Signature
   0      16      0    $this       Lscala/collection/generic/SetTemplate;


public static scala.collection.generic.Builder newBuilder(scala.collection.generic.SetTemplate);
  Code:
   Stack=3, Locals=1, Args_size=1
   0:	new	#104; //class scala/collection/generic/AddingBuilder
   3:	dup
   4:	aload_0
   5:	invokeinterface	#108,  1; //InterfaceMethod scala/collection/generic/SetTemplate.empty:()Lscala/collection/generic/SetTemplate;
   10:	invokespecial	#111; //Method scala/collection/generic/AddingBuilder."<init>":(Lscala/collection/generic/Addable;)V
   13:	areturn
  LineNumberTable: 
   line 50: 0

  LocalVariableTable: 
   Start  Length  Slot  Name   Signature
   0      14      0    $this       Lscala/collection/generic/SetTemplate;


}

