Compiled from "SortedSetTemplate.scala"
public abstract class scala.collection.generic.SortedSetTemplate$class extends java.lang.Object
  SourceFile: "SortedSetTemplate.scala"
  Scala: length = 0x
   
  minor version: 0
  major version: 49
  Constant pool:
const #1 = Asciz	SourceFile;
const #2 = Asciz	SortedSetTemplate.scala;
const #3 = Asciz	$init$;
const #4 = Asciz	(Lscala/collection/generic/SortedSetTemplate;)V;
const #5 = Asciz	Code;
const #6 = Asciz	LineNumberTable;
const #7 = Asciz	$this;
const #8 = Asciz	Lscala/collection/generic/SortedSetTemplate;;
const #9 = Asciz	LocalVariableTable;
const #10 = Asciz	gd1$1;
const #11 = Asciz	(Lscala/collection/generic/SortedSetTemplate;Lscala/collection/SortedSet;)Z;
const #12 = Asciz	scala/collection/generic/Sorted;
const #13 = class	#12;	//  scala/collection/generic/Sorted
const #14 = Asciz	ordering;
const #15 = Asciz	()Lscala/Ordering;;
const #16 = NameAndType	#14:#15;//  ordering:()Lscala/Ordering;
const #17 = InterfaceMethod	#13.#16;	//  scala/collection/generic/Sorted.ordering:()Lscala/Ordering;
const #18 = Asciz	java/lang/Object;
const #19 = class	#18;	//  java/lang/Object
const #20 = Asciz	equals;
const #21 = Asciz	(Ljava/lang/Object;)Z;
const #22 = NameAndType	#20:#21;//  equals:(Ljava/lang/Object;)Z
const #23 = Method	#19.#22;	//  java/lang/Object.equals:(Ljava/lang/Object;)Z
const #24 = Asciz	subsetOf;
const #25 = Asciz	(Lscala/collection/generic/SortedSetTemplate;Lscala/collection/Set;)Z;
const #26 = Asciz	scala/collection/SortedSet;
const #27 = class	#26;	//  scala/collection/SortedSet
const #28 = Asciz	scala/collection/generic/SortedSetTemplate$class;
const #29 = class	#28;	//  scala/collection/generic/SortedSetTemplate$class
const #30 = NameAndType	#10:#11;//  gd1$1:(Lscala/collection/generic/SortedSetTemplate;Lscala/collection/SortedSet;)Z
const #31 = Method	#29.#30;	//  scala/collection/generic/SortedSetTemplate$class.gd1$1:(Lscala/collection/generic/SortedSetTemplate;Lscala/collection/SortedSet;)Z
const #32 = Asciz	scala/collection/generic/IterableTemplate;
const #33 = class	#32;	//  scala/collection/generic/IterableTemplate
const #34 = Asciz	iterator;
const #35 = Asciz	()Lscala/collection/Iterator;;
const #36 = NameAndType	#34:#35;//  iterator:()Lscala/collection/Iterator;
const #37 = InterfaceMethod	#33.#36;	//  scala/collection/generic/IterableTemplate.iterator:()Lscala/collection/Iterator;
const #38 = Asciz	hasAll;
const #39 = Asciz	(Lscala/collection/Iterator;)Z;
const #40 = NameAndType	#38:#39;//  hasAll:(Lscala/collection/Iterator;)Z
const #41 = InterfaceMethod	#13.#40;	//  scala/collection/generic/Sorted.hasAll:(Lscala/collection/Iterator;)Z
const #42 = Asciz	scala/collection/generic/SortedSetTemplate;
const #43 = class	#42;	//  scala/collection/generic/SortedSetTemplate
const #44 = Asciz	scala$collection$generic$SortedSetTemplate$$super$subsetOf;
const #45 = Asciz	(Lscala/collection/Set;)Z;
const #46 = NameAndType	#44:#45;//  scala$collection$generic$SortedSetTemplate$$super$subsetOf:(Lscala/collection/Set;)Z
const #47 = InterfaceMethod	#43.#46;	//  scala/collection/generic/SortedSetTemplate.scala$collection$generic$SortedSetTemplate$$super$subsetOf:(Lscala/collection/Set;)Z
const #48 = Asciz	that;
const #49 = Asciz	Lscala/collection/Set;;
const #50 = Asciz	temp1;
const #51 = Asciz	temp2;
const #52 = Asciz	Lscala/collection/SortedSet;;
const #53 = Asciz	range;
const #54 = Asciz	(Lscala/collection/generic/SortedSetTemplate;Ljava/lang/Object;Ljava/lang/Object;)Lscala/collection/SortedSet;;
const #55 = Asciz	scala/Some;
const #56 = class	#55;	//  scala/Some
const #57 = Asciz	<init>;
const #58 = Asciz	(Ljava/lang/Object;)V;
const #59 = NameAndType	#57:#58;//  "<init>":(Ljava/lang/Object;)V
const #60 = Method	#56.#59;	//  scala/Some."<init>":(Ljava/lang/Object;)V
const #61 = Asciz	rangeImpl;
const #62 = Asciz	(Lscala/Option;Lscala/Option;)Lscala/collection/SortedSet;;
const #63 = NameAndType	#61:#62;//  rangeImpl:(Lscala/Option;Lscala/Option;)Lscala/collection/SortedSet;
const #64 = InterfaceMethod	#43.#63;	//  scala/collection/generic/SortedSetTemplate.rangeImpl:(Lscala/Option;Lscala/Option;)Lscala/collection/SortedSet;
const #65 = Asciz	from;
const #66 = Asciz	Ljava/lang/Object;;
const #67 = Asciz	until;
const #68 = Asciz	(Lscala/collection/generic/SortedSetTemplate;Ljava/lang/Object;)Lscala/collection/SortedSet;;
const #69 = Asciz	scala/None$;
const #70 = class	#69;	//  scala/None$
const #71 = Asciz	MODULE$;
const #72 = Asciz	Lscala/None$;;
const #73 = NameAndType	#71:#72;//  MODULE$:Lscala/None$;
const #74 = Field	#70.#73;	//  scala/None$.MODULE$:Lscala/None$;
const #75 = Asciz	lastKey;
const #76 = Asciz	(Lscala/collection/generic/SortedSetTemplate;)Ljava/lang/Object;;
const #77 = Asciz	scala/collection/generic/TraversableTemplate;
const #78 = class	#77;	//  scala/collection/generic/TraversableTemplate
const #79 = Asciz	last;
const #80 = Asciz	()Ljava/lang/Object;;
const #81 = NameAndType	#79:#80;//  last:()Ljava/lang/Object;
const #82 = InterfaceMethod	#78.#81;	//  scala/collection/generic/TraversableTemplate.last:()Ljava/lang/Object;
const #83 = Asciz	firstKey;
const #84 = Asciz	head;
const #85 = NameAndType	#84:#80;//  head:()Ljava/lang/Object;
const #86 = InterfaceMethod	#33.#85;	//  scala/collection/generic/IterableTemplate.head:()Ljava/lang/Object;
const #87 = Asciz	keySet;
const #88 = Asciz	(Lscala/collection/generic/SortedSetTemplate;)Lscala/collection/SortedSet;;
const #89 = Asciz	thisCollection;
const #90 = Asciz	()Lscala/collection/generic/TraversableTemplate;;
const #91 = NameAndType	#89:#90;//  thisCollection:()Lscala/collection/generic/TraversableTemplate;
const #92 = InterfaceMethod	#78.#91;	//  scala/collection/generic/TraversableTemplate.thisCollection:()Lscala/collection/generic/TraversableTemplate;
const #93 = Asciz	Scala;

{
public static void $init$(scala.collection.generic.SortedSetTemplate);
  Code:
   Stack=0, Locals=1, Args_size=1
   0:	return
  LineNumberTable: 
   line 21: 0

  LocalVariableTable: 
   Start  Length  Slot  Name   Signature
   0      1      0    $this       Lscala/collection/generic/SortedSetTemplate;


public static boolean subsetOf(scala.collection.generic.SortedSetTemplate, scala.collection.Set);
  Code:
   Stack=2, Locals=6, Args_size=2
   0:	aload_1
   1:	astore_2
   2:	aload_2
   3:	instanceof	#27; //class scala/collection/SortedSet
   6:	ifeq	47
   9:	aload_2
   10:	checkcast	#27; //class scala/collection/SortedSet
   13:	astore_3
   14:	aload_3
   15:	astore	4
   17:	aload_0
   18:	aload	4
   20:	invokestatic	#31; //Method gd1$1:(Lscala/collection/generic/SortedSetTemplate;Lscala/collection/SortedSet;)Z
   23:	ifeq	41
   26:	aload_3
   27:	aload_0
   28:	invokeinterface	#37,  1; //InterfaceMethod scala/collection/generic/IterableTemplate.iterator:()Lscala/collection/Iterator;
   33:	invokeinterface	#41,  2; //InterfaceMethod scala/collection/generic/Sorted.hasAll:(Lscala/collection/Iterator;)Z
   38:	goto	58
   41:	aload_3
   42:	astore	5
   44:	goto	50
   47:	aload_2
   48:	astore	5
   50:	aload_0
   51:	aload	5
   53:	invokeinterface	#47,  2; //InterfaceMethod scala/collection/generic/SortedSetTemplate.scala$collection$generic$SortedSetTemplate$$super$subsetOf:(Lscala/collection/Set;)Z
   58:	ireturn
  LineNumberTable: 
   line 35: 0
   line 39: 14
   line 35: 17
   line 39: 26
   line 40: 41
   line 35: 47
   line 40: 50
   line 35: 58

  LocalVariableTable: 
   Start  Length  Slot  Name   Signature
   0      59      0    $this       Lscala/collection/generic/SortedSetTemplate;
   0      59      1    that       Lscala/collection/Set;
   2      57      2    temp1       Lscala/collection/Set;
   14      33      3    temp2       Lscala/collection/SortedSet;
   50      8      3    temp2       Lscala/collection/SortedSet;
   17      30      4    that       Lscala/collection/SortedSet;
   50      8      4    that       Lscala/collection/SortedSet;
   44      3      5    that       Lscala/collection/Set;
   50      8      5    that       Lscala/collection/Set;


public static scala.collection.SortedSet range(scala.collection.generic.SortedSetTemplate, java.lang.Object, java.lang.Object);
  Code:
   Stack=5, Locals=3, Args_size=3
   0:	aload_0
   1:	new	#56; //class scala/Some
   4:	dup
   5:	aload_1
   6:	invokespecial	#60; //Method scala/Some."<init>":(Ljava/lang/Object;)V
   9:	new	#56; //class scala/Some
   12:	dup
   13:	aload_2
   14:	invokespecial	#60; //Method scala/Some."<init>":(Ljava/lang/Object;)V
   17:	invokeinterface	#64,  3; //InterfaceMethod scala/collection/generic/SortedSetTemplate.rangeImpl:(Lscala/Option;Lscala/Option;)Lscala/collection/SortedSet;
   22:	areturn
  LineNumberTable: 
   line 33: 0

  LocalVariableTable: 
   Start  Length  Slot  Name   Signature
   0      23      0    $this       Lscala/collection/generic/SortedSetTemplate;
   0      23      1    from       Ljava/lang/Object;
   0      23      2    until       Ljava/lang/Object;


public static scala.collection.SortedSet until(scala.collection.generic.SortedSetTemplate, java.lang.Object);
  Code:
   Stack=5, Locals=2, Args_size=2
   0:	aload_0
   1:	getstatic	#74; //Field scala/None$.MODULE$:Lscala/None$;
   4:	new	#56; //class scala/Some
   7:	dup
   8:	aload_1
   9:	invokespecial	#60; //Method scala/Some."<init>":(Ljava/lang/Object;)V
   12:	invokeinterface	#64,  3; //InterfaceMethod scala/collection/generic/SortedSetTemplate.rangeImpl:(Lscala/Option;Lscala/Option;)Lscala/collection/SortedSet;
   17:	areturn
  LineNumberTable: 
   line 32: 0

  LocalVariableTable: 
   Start  Length  Slot  Name   Signature
   0      18      0    $this       Lscala/collection/generic/SortedSetTemplate;
   0      18      1    until       Ljava/lang/Object;


public static scala.collection.SortedSet from(scala.collection.generic.SortedSetTemplate, java.lang.Object);
  Code:
   Stack=4, Locals=2, Args_size=2
   0:	aload_0
   1:	new	#56; //class scala/Some
   4:	dup
   5:	aload_1
   6:	invokespecial	#60; //Method scala/Some."<init>":(Ljava/lang/Object;)V
   9:	getstatic	#74; //Field scala/None$.MODULE$:Lscala/None$;
   12:	invokeinterface	#64,  3; //InterfaceMethod scala/collection/generic/SortedSetTemplate.rangeImpl:(Lscala/Option;Lscala/Option;)Lscala/collection/SortedSet;
   17:	areturn
  LineNumberTable: 
   line 31: 0

  LocalVariableTable: 
   Start  Length  Slot  Name   Signature
   0      18      0    $this       Lscala/collection/generic/SortedSetTemplate;
   0      18      1    from       Ljava/lang/Object;


public static java.lang.Object lastKey(scala.collection.generic.SortedSetTemplate);
  Code:
   Stack=1, Locals=1, Args_size=1
   0:	aload_0
   1:	invokeinterface	#82,  1; //InterfaceMethod scala/collection/generic/TraversableTemplate.last:()Ljava/lang/Object;
   6:	areturn
  LineNumberTable: 
   line 27: 0

  LocalVariableTable: 
   Start  Length  Slot  Name   Signature
   0      7      0    $this       Lscala/collection/generic/SortedSetTemplate;


public static java.lang.Object firstKey(scala.collection.generic.SortedSetTemplate);
  Code:
   Stack=1, Locals=1, Args_size=1
   0:	aload_0
   1:	invokeinterface	#86,  1; //InterfaceMethod scala/collection/generic/IterableTemplate.head:()Ljava/lang/Object;
   6:	areturn
  LineNumberTable: 
   line 26: 0

  LocalVariableTable: 
   Start  Length  Slot  Name   Signature
   0      7      0    $this       Lscala/collection/generic/SortedSetTemplate;


public static scala.collection.SortedSet keySet(scala.collection.generic.SortedSetTemplate);
  Code:
   Stack=1, Locals=1, Args_size=1
   0:	aload_0
   1:	invokeinterface	#92,  1; //InterfaceMethod scala/collection/generic/TraversableTemplate.thisCollection:()Lscala/collection/generic/TraversableTemplate;
   6:	checkcast	#27; //class scala/collection/SortedSet
   9:	areturn
  LineNumberTable: 
   line 24: 0

  LocalVariableTable: 
   Start  Length  Slot  Name   Signature
   0      10      0    $this       Lscala/collection/generic/SortedSetTemplate;


}

