Compiled from "SortedSetFactory.scala"
public abstract class scala.collection.generic.SortedSetFactory extends java.lang.Object implements scala.ScalaObject
  SourceFile: "SortedSetFactory.scala"
  Signature: length = 0x2
   00 3D 
  ScalaSig: length = 0x3A9
   05 00 FFFFFF81 15 06 05 01 02 FFFFFF81 00 09 02 10 53 6F 72
   74 65 64 53 65 74 46 61 63 74 6F 72 79 0A 02 03
   04 01 07 67 65 6E 65 72 69 63 0A 02 05 06 01 0A
   63 6F 6C 6C 65 63 74 69 6F 6E 0A 01 07 01 05 73
   63 61 6C 61 03 00 15 02 0A 1E 13 03 00 0B 13 10
   02 0C 11 0D 01 0D 0A 02 0E 0F 01 04 6C 61 6E 67
   0A 01 10 01 04 6A 61 76 61 09 02 12 0D 02 06 4F
   62 6A 65 63 74 10 02 14 15 0D 01 06 09 02 16 06
   02 0B 53 63 61 6C 61 4F 62 6A 65 63 74 08 05 18
   00 FFFFFF84 00 19 01 06 3C 69 6E 69 74 3E 14 01 1A 10
   03 1B 00 1C 0D 01 02 10 02 1D 1E 0C 00 04 05 1F
   00 FFFFFFC2 00 20 02 02 43 43 15 02 21 2D 11 02 22 25
   10 02 14 23 09 02 24 06 02 07 4E 6F 74 68 69 6E
   67 12 03 26 28 33 06 08 27 00 FFFFFF84 FFFFFF80 FFFFFF80 FFFFFF80 00 25
   02 0C 3C 72 65 66 69 6E 65 6D 65 6E 74 3E 10 03
   29 2A 2C 0D 01 04 09 02 2B 04 02 09 53 6F 72 74
   65 64 53 65 74 10 02 1D 2D 04 08 2E 1E FFFFFF84 FFFFFF80 FFFFFF80
   FFFFFFC2 00 2F 02 01 41 11 02 22 30 10 02 14 31 09 02
   32 06 02 03 41 6E 79 10 04 29 34 2C 36 09 02 35
   04 02 0D 53 6F 72 74 65 64 53 65 74 4C 69 6B 65
   10 03 1D 1E 2C 05 08 38 00 FFFFFF84 FFFFFF80 FFFFFF80 FFFFFF80 00 39 02
   04 43 6F 6C 6C 30 02 3A 3C 10 03 1D 1E 3B 10 02
   1D 3C 04 08 3D 37 FFFFFF84 FFFFFF80 FFFFFF80 FFFFFF82 00 2F 02 03 5F 24
   31 08 05 3F 00 FFFFFF86 00 40 01 05 65 6D 70 74 79 15
   02 41 44 16 02 42 45 10 03 1D 1E 43 10 02 1D 44
   04 08 2E 3E FFFFFF84 FFFFFF80 FFFFFF80 FFFFFFC2 00 2F 08 05 46 3E FFFFFFC0 01
   47 01 03 6F 72 64 10 03 48 50 43 0E 02 49 4E 0E
   02 4A 4D 0D 01 4B 0A 02 4C 08 01 06 3C 72 6F 6F
   74 3E 09 01 07 09 02 4F 06 01 07 70 61 63 6B 61
   67 65 09 02 51 52 02 08 4F 72 64 65 72 69 6E 67
   0A 02 4F 06 08 05 54 00 FFFFFF84 00 55 01 05 61 70 70
   6C 79 15 02 56 5A 14 02 57 5D 16 02 58 5B 10 03
   1D 1E 59 10 02 1D 5A 04 08 2E 53 FFFFFF84 FFFFFF80 FFFFFF80 FFFFFFC2 00
   2F 08 05 46 53 FFFFFFC0 01 5C 10 03 48 50 59 08 05 5E
   53 FFFFFFC0 00 5F 01 05 65 6C 65 6D 73 10 03 14 60 59
   09 02 61 06 02 0A 3C 72 65 70 65 61 74 65 64 3E
   08 05 63 00 FFFFFF84 00 64 01 0A 6E 65 77 42 75 69 6C
   64 65 72 15 02 65 6D 16 02 66 6F 10 04 67 6A 6C
   6E 0D 01 68 0A 02 69 04 01 07 6D 75 74 61 62 6C
   65 09 02 6B 68 02 07 42 75 69 6C 64 65 72 10 02
   1D 6D 04 08 2E 62 FFFFFF84 FFFFFF80 FFFFFF80 FFFFFFC2 00 2F 10 03 1D 1E
   6C 08 05 46 62 FFFFFFC0 01 70 10 03 48 50 6C 08 05 72
   00 FFFFFF84 01 73 01 0F 6E 65 77 43 61 6E 42 75 69 6C
   64 46 72 6F 6D 15 02 74 7B 16 02 75 7D 10 05 1B
   76 78 7A 7C 09 02 77 02 02 0C 43 61 6E 42 75 69
   6C 64 46 72 6F 6D 10 02 79 37 0D 01 00 10 02 1D
   7B 04 08 2E 71 FFFFFF84 FFFFFF80 FFFFFF80 FFFFFFC2 00 2F 10 03 1D 1E 7A
   08 05 46 71 FFFFFFC0 01 7E 10 03 48 50 7A 06 06 FFFFFF81 00
   00 00 FFFFFF81 01 02 15 53 6F 72 74 65 64 53 65 74 43
   61 6E 42 75 69 6C 64 46 72 6F 6D 15 04 FFFFFF81 02 FFFFFF81
   05 13 05 7F 0B FFFFFF81 03 13 10 07 1B 76 78 FFFFFF81 04 FFFFFF81
   06 10 03 1D FFFFFF81 05 04 08 2E 7F FFFFFF84 FFFFFF80 FFFFFF80 FFFFFFC2 00 2F
   10 04 1D 1E FFFFFF81 04 08 09 46 7F FFFFFF82 FFFFFF80 FFFFFFA0 FFFFFF80 05 FFFFFF81
   08 10 04 48 50 FFFFFF81 04 08 06 18 7F FFFFFF84 00 FFFFFF81 0A 14
   02 FFFFFF81 0B 16 04 FFFFFF81 0C FFFFFF81 0D 10 04 79 7F FFFFFF81 04 08
   07 46 FFFFFF81 09 FFFFFFC0 01 FFFFFF81 08 08 06 54 7F FFFFFF84 00 FFFFFF81 0F
   14 04 FFFFFF81 10 FFFFFF81 11 10 06 67 6A FFFFFF81 04 FFFFFF81 06 08 07
   FFFFFF81 12 FFFFFF81 0E FFFFFFC0 00 78 01 04 66 72 6F 6D 08 06 54
   7F FFFFFF84 00 FFFFFF81 14 14 02 FFFFFF81 10 
  InnerClass: 
   public #64= #15 of #30; //SortedSetCanBuildFrom=class scala/collection/generic/SortedSetFactory$SortedSetCanBuildFrom of class scala/collection/generic/SortedSetFactory
  minor version: 0
  major version: 49
  Constant pool:
const #1 = Asciz	SourceFile;
const #2 = Asciz	SortedSetFactory.scala;
const #3 = Asciz	<init>;
const #4 = Asciz	()V;
const #5 = Asciz	Code;
const #6 = Asciz	LineNumberTable;
const #7 = Asciz	java/lang/Object;
const #8 = class	#7;	//  java/lang/Object
const #9 = NameAndType	#3:#4;//  "<init>":()V
const #10 = Method	#8.#9;	//  java/lang/Object."<init>":()V
const #11 = Asciz	Signature;
const #12 = Asciz	newCanBuildFrom;
const #13 = Asciz	(Lscala/math/Ordering;)Lscala/collection/generic/CanBuildFrom;;
const #14 = Asciz	scala/collection/generic/SortedSetFactory$SortedSetCanBuildFrom;
const #15 = class	#14;	//  scala/collection/generic/SortedSetFactory$SortedSetCanBuildFrom
const #16 = Asciz	(Lscala/collection/generic/SortedSetFactory;Lscala/math/Ordering;)V;
const #17 = NameAndType	#3:#16;//  "<init>":(Lscala/collection/generic/SortedSetFactory;Lscala/math/Ordering;)V
const #18 = Method	#15.#17;	//  scala/collection/generic/SortedSetFactory$SortedSetCanBuildFrom."<init>":(Lscala/collection/generic/SortedSetFactory;Lscala/math/Ordering;)V
const #19 = Asciz	this;
const #20 = Asciz	Lscala/collection/generic/SortedSetFactory;;
const #21 = Asciz	ord;
const #22 = Asciz	Lscala/math/Ordering;;
const #23 = Asciz	LocalVariableTable;
const #24 = Asciz	<A:Ljava/lang/Object;>(Lscala/math/Ordering<TA;>;)Lscala/collection/generic/CanBuildFrom<TCC;TA;TCC;>;;
const #25 = Asciz	newBuilder;
const #26 = Asciz	(Lscala/math/Ordering;)Lscala/collection/mutable/Builder;;
const #27 = Asciz	scala/collection/mutable/SetBuilder;
const #28 = class	#27;	//  scala/collection/mutable/SetBuilder
const #29 = Asciz	scala/collection/generic/SortedSetFactory;
const #30 = class	#29;	//  scala/collection/generic/SortedSetFactory
const #31 = Asciz	empty;
const #32 = Asciz	(Lscala/math/Ordering;)Lscala/collection/SortedSet;;
const #33 = NameAndType	#31:#32;//  empty:(Lscala/math/Ordering;)Lscala/collection/SortedSet;
const #34 = Method	#30.#33;	//  scala/collection/generic/SortedSetFactory.empty:(Lscala/math/Ordering;)Lscala/collection/SortedSet;
const #35 = Asciz	(Lscala/collection/generic/Addable;)V;
const #36 = NameAndType	#3:#35;//  "<init>":(Lscala/collection/generic/Addable;)V
const #37 = Method	#28.#36;	//  scala/collection/mutable/SetBuilder."<init>":(Lscala/collection/generic/Addable;)V
const #38 = Asciz	<A:Ljava/lang/Object;>(Lscala/math/Ordering<TA;>;)Lscala/collection/mutable/Builder<TA;TCC;>;;
const #39 = Asciz	apply;
const #40 = Asciz	(Lscala/collection/Seq;Lscala/math/Ordering;)Lscala/collection/SortedSet;;
const #41 = NameAndType	#25:#26;//  newBuilder:(Lscala/math/Ordering;)Lscala/collection/mutable/Builder;
const #42 = Method	#30.#41;	//  scala/collection/generic/SortedSetFactory.newBuilder:(Lscala/math/Ordering;)Lscala/collection/mutable/Builder;
const #43 = Asciz	scala/collection/generic/Growable;
const #44 = class	#43;	//  scala/collection/generic/Growable
const #45 = Asciz	$plus$plus$eq;
const #46 = Asciz	(Lscala/collection/Traversable;)Lscala/collection/generic/Growable;;
const #47 = NameAndType	#45:#46;//  $plus$plus$eq:(Lscala/collection/Traversable;)Lscala/collection/generic/Growable;
const #48 = InterfaceMethod	#44.#47;	//  scala/collection/generic/Growable.$plus$plus$eq:(Lscala/collection/Traversable;)Lscala/collection/generic/Growable;
const #49 = Asciz	scala/collection/mutable/Builder;
const #50 = class	#49;	//  scala/collection/mutable/Builder
const #51 = Asciz	result;
const #52 = Asciz	()Ljava/lang/Object;;
const #53 = NameAndType	#51:#52;//  result:()Ljava/lang/Object;
const #54 = InterfaceMethod	#50.#53;	//  scala/collection/mutable/Builder.result:()Ljava/lang/Object;
const #55 = Asciz	scala/collection/SortedSet;
const #56 = class	#55;	//  scala/collection/SortedSet
const #57 = Asciz	elems;
const #58 = Asciz	Lscala/collection/Seq;;
const #59 = Asciz	<A:Ljava/lang/Object;>(Lscala/collection/Seq<TA;>;Lscala/math/Ordering<TA;>;)TCC;;
const #60 = Asciz	<A:Ljava/lang/Object;>(Lscala/math/Ordering<TA;>;)TCC;;
const #61 = Asciz	<CC:Lscala/collection/SortedSet<Ljava/lang/Object;>;>Ljava/lang/Object;Lscala/ScalaObject;;
const #62 = Asciz	ScalaSig;
const #63 = Asciz	InnerClasses;
const #64 = Asciz	SortedSetCanBuildFrom;
const #65 = Asciz	scala/ScalaObject;
const #66 = class	#65;	//  scala/ScalaObject

{
public scala.collection.generic.SortedSetFactory();
  Code:
   Stack=1, Locals=1, Args_size=1
   0:	aload_0
   1:	invokespecial	#10; //Method java/lang/Object."<init>":()V
   4:	return
  LineNumberTable: 
   line 21: 0

  Signature: length = 0x2
   00 04 

public scala.collection.generic.CanBuildFrom newCanBuildFrom(scala.math.Ordering);
  Code:
   Stack=4, Locals=2, Args_size=2
   0:	new	#15; //class scala/collection/generic/SortedSetFactory$SortedSetCanBuildFrom
   3:	dup
   4:	aload_0
   5:	aload_1
   6:	invokespecial	#18; //Method scala/collection/generic/SortedSetFactory$SortedSetCanBuildFrom."<init>":(Lscala/collection/generic/SortedSetFactory;Lscala/math/Ordering;)V
   9:	areturn
  LineNumberTable: 
   line 30: 0

  LocalVariableTable: 
   Start  Length  Slot  Name   Signature
   0      10      0    this       Lscala/collection/generic/SortedSetFactory;
   0      10      1    ord       Lscala/math/Ordering;

  Signature: length = 0x2
   00 18 

public scala.collection.mutable.Builder newBuilder(scala.math.Ordering);
  Code:
   Stack=4, Locals=2, Args_size=2
   0:	new	#28; //class scala/collection/mutable/SetBuilder
   3:	dup
   4:	aload_0
   5:	aload_1
   6:	invokevirtual	#34; //Method empty:(Lscala/math/Ordering;)Lscala/collection/SortedSet;
   9:	invokespecial	#37; //Method scala/collection/mutable/SetBuilder."<init>":(Lscala/collection/generic/Addable;)V
   12:	areturn
  LineNumberTable: 
   line 28: 0

  LocalVariableTable: 
   Start  Length  Slot  Name   Signature
   0      13      0    this       Lscala/collection/generic/SortedSetFactory;
   0      13      1    ord       Lscala/math/Ordering;

  Signature: length = 0x2
   00 26 

public scala.collection.SortedSet apply(scala.collection.Seq, scala.math.Ordering);
  Code:
   Stack=2, Locals=3, Args_size=3
   0:	aload_0
   1:	aload_2
   2:	invokevirtual	#42; //Method newBuilder:(Lscala/math/Ordering;)Lscala/collection/mutable/Builder;
   5:	aload_1
   6:	invokeinterface	#48,  2; //InterfaceMethod scala/collection/generic/Growable.$plus$plus$eq:(Lscala/collection/Traversable;)Lscala/collection/generic/Growable;
   11:	checkcast	#50; //class scala/collection/mutable/Builder
   14:	invokeinterface	#54,  1; //InterfaceMethod scala/collection/mutable/Builder.result:()Ljava/lang/Object;
   19:	checkcast	#56; //class scala/collection/SortedSet
   22:	areturn
  LineNumberTable: 
   line 26: 0

  LocalVariableTable: 
   Start  Length  Slot  Name   Signature
   0      23      0    this       Lscala/collection/generic/SortedSetFactory;
   0      23      1    elems       Lscala/collection/Seq;
   0      23      2    ord       Lscala/math/Ordering;

  Signature: length = 0x2
   00 3B 

public abstract scala.collection.SortedSet empty(scala.math.Ordering);
  Signature: length = 0x2
   00 3C 

}

