Compiled from "SortedSetFactory.scala"
public class scala.collection.generic.SortedSetFactory$SortedSetCanBuildFrom extends java.lang.Object implements scala.collection.generic.CanBuildFrom,scala.ScalaObject
  SourceFile: "SortedSetFactory.scala"
  Signature: length = 0x2
   00 36 
  Scala: length = 0x
   
  InnerClass: 
   public #57= #14 of #46; //SortedSetCanBuildFrom=class scala/collection/generic/SortedSetFactory$SortedSetCanBuildFrom of class scala/collection/generic/SortedSetFactory
  minor version: 0
  major version: 49
  Constant pool:
const #1 = Asciz	SourceFile;
const #2 = Asciz	SortedSetFactory.scala;
const #3 = Asciz	$outer;
const #4 = Asciz	Lscala/collection/generic/SortedSetFactory;;
const #5 = Asciz	ord;
const #6 = Asciz	Lscala/math/Ordering;;
const #7 = Asciz	Lscala/math/Ordering<TA;>;;
const #8 = Asciz	Signature;
const #9 = Asciz	<init>;
const #10 = Asciz	(Lscala/collection/generic/SortedSetFactory;Lscala/math/Ordering;)V;
const #11 = Asciz	Code;
const #12 = Asciz	LineNumberTable;
const #13 = Asciz	scala/collection/generic/SortedSetFactory$SortedSetCanBuildFrom;
const #14 = class	#13;	//  scala/collection/generic/SortedSetFactory$SortedSetCanBuildFrom
const #15 = NameAndType	#5:#6;//  ord:Lscala/math/Ordering;
const #16 = Field	#14.#15;	//  scala/collection/generic/SortedSetFactory$SortedSetCanBuildFrom.ord:Lscala/math/Ordering;
const #17 = Asciz	java/lang/NullPointerException;
const #18 = class	#17;	//  java/lang/NullPointerException
const #19 = Asciz	()V;
const #20 = NameAndType	#9:#19;//  "<init>":()V
const #21 = Method	#18.#20;	//  java/lang/NullPointerException."<init>":()V
const #22 = NameAndType	#3:#4;//  $outer:Lscala/collection/generic/SortedSetFactory;
const #23 = Field	#14.#22;	//  scala/collection/generic/SortedSetFactory$SortedSetCanBuildFrom.$outer:Lscala/collection/generic/SortedSetFactory;
const #24 = Asciz	java/lang/Object;
const #25 = class	#24;	//  java/lang/Object
const #26 = Method	#25.#20;	//  java/lang/Object."<init>":()V
const #27 = Asciz	this;
const #28 = Asciz	Lscala/collection/generic/SortedSetFactory$SortedSetCanBuildFrom;;
const #29 = Asciz	LocalVariableTable;
const #30 = Asciz	(Lscala/collection/generic/SortedSetFactory<TCC;>;Lscala/math/Ordering<TA;>;)V;
const #31 = Asciz	apply;
const #32 = Asciz	(Ljava/lang/Object;)Lscala/collection/mutable/Builder;;
const #33 = Asciz	scala/collection/SortedSet;
const #34 = class	#33;	//  scala/collection/SortedSet
const #35 = Asciz	(Lscala/collection/SortedSet;)Lscala/collection/mutable/Builder;;
const #36 = NameAndType	#31:#35;//  apply:(Lscala/collection/SortedSet;)Lscala/collection/mutable/Builder;
const #37 = Method	#14.#36;	//  scala/collection/generic/SortedSetFactory$SortedSetCanBuildFrom.apply:(Lscala/collection/SortedSet;)Lscala/collection/mutable/Builder;
const #38 = Asciz	from;
const #39 = Asciz	Ljava/lang/Object;;
const #40 = Asciz	scala$collection$generic$SortedSetFactory$SortedSetCanBuildFrom$$$outer;
const #41 = Asciz	()Lscala/collection/generic/SortedSetFactory;;
const #42 = Asciz	()Lscala/collection/mutable/Builder;;
const #43 = NameAndType	#40:#41;//  scala$collection$generic$SortedSetFactory$SortedSetCanBuildFrom$$$outer:()Lscala/collection/generic/SortedSetFactory;
const #44 = Method	#14.#43;	//  scala/collection/generic/SortedSetFactory$SortedSetCanBuildFrom.scala$collection$generic$SortedSetFactory$SortedSetCanBuildFrom$$$outer:()Lscala/collection/generic/SortedSetFactory;
const #45 = Asciz	scala/collection/generic/SortedSetFactory;
const #46 = class	#45;	//  scala/collection/generic/SortedSetFactory
const #47 = Asciz	newBuilder;
const #48 = Asciz	(Lscala/math/Ordering;)Lscala/collection/mutable/Builder;;
const #49 = NameAndType	#47:#48;//  newBuilder:(Lscala/math/Ordering;)Lscala/collection/mutable/Builder;
const #50 = Method	#46.#49;	//  scala/collection/generic/SortedSetFactory.newBuilder:(Lscala/math/Ordering;)Lscala/collection/mutable/Builder;
const #51 = Asciz	()Lscala/collection/mutable/Builder<TA;TCC;>;;
const #52 = Asciz	Lscala/collection/SortedSet;;
const #53 = Asciz	(TCC;)Lscala/collection/mutable/Builder<TA;TCC;>;;
const #54 = Asciz	<A:Ljava/lang/Object;>Ljava/lang/Object;Lscala/collection/generic/CanBuildFrom<TCC;TA;TCC;>;Lscala/ScalaObject;;
const #55 = Asciz	Scala;
const #56 = Asciz	InnerClasses;
const #57 = Asciz	SortedSetCanBuildFrom;
const #58 = Asciz	scala/collection/generic/CanBuildFrom;
const #59 = class	#58;	//  scala/collection/generic/CanBuildFrom
const #60 = Asciz	scala/ScalaObject;
const #61 = class	#60;	//  scala/ScalaObject

{
public final scala.collection.generic.SortedSetFactory $outer;

public scala.collection.generic.SortedSetFactory$SortedSetCanBuildFrom(scala.collection.generic.SortedSetFactory, scala.math.Ordering);
  Code:
   Stack=2, Locals=3, Args_size=3
   0:	aload_0
   1:	aload_2
   2:	putfield	#16; //Field ord:Lscala/math/Ordering;
   5:	aload_1
   6:	ifnonnull	17
   9:	new	#18; //class java/lang/NullPointerException
   12:	dup
   13:	invokespecial	#21; //Method java/lang/NullPointerException."<init>":()V
   16:	athrow
   17:	aload_0
   18:	aload_1
   19:	putfield	#23; //Field $outer:Lscala/collection/generic/SortedSetFactory;
   22:	aload_0
   23:	invokespecial	#26; //Method java/lang/Object."<init>":()V
   26:	return
  LineNumberTable: 
   line 32: 0

  LocalVariableTable: 
   Start  Length  Slot  Name   Signature
   0      27      0    this       Lscala/collection/generic/SortedSetFactory$SortedSetCanBuildFrom;
   0      27      1    $outer       Lscala/collection/generic/SortedSetFactory;
   0      27      2    ord       Lscala/math/Ordering;

  Signature: length = 0x2
   00 1E 

public scala.collection.mutable.Builder apply(java.lang.Object);
  Code:
   Stack=2, Locals=2, Args_size=2
   0:	aload_0
   1:	aload_1
   2:	checkcast	#34; //class scala/collection/SortedSet
   5:	invokevirtual	#37; //Method apply:(Lscala/collection/SortedSet;)Lscala/collection/mutable/Builder;
   8:	areturn
  LineNumberTable: 
   line 32: 0

  LocalVariableTable: 
   Start  Length  Slot  Name   Signature
   0      9      0    this       Lscala/collection/generic/SortedSetFactory$SortedSetCanBuildFrom;
   0      9      1    from       Ljava/lang/Object;


public scala.collection.generic.SortedSetFactory scala$collection$generic$SortedSetFactory$SortedSetCanBuildFrom$$$outer();
  Code:
   Stack=1, Locals=1, Args_size=1
   0:	aload_0
   1:	getfield	#23; //Field $outer:Lscala/collection/generic/SortedSetFactory;
   4:	areturn
  LineNumberTable: 
   line 32: 0


public scala.collection.mutable.Builder apply();
  Code:
   Stack=2, Locals=1, Args_size=1
   0:	aload_0
   1:	invokevirtual	#44; //Method scala$collection$generic$SortedSetFactory$SortedSetCanBuildFrom$$$outer:()Lscala/collection/generic/SortedSetFactory;
   4:	aload_0
   5:	getfield	#16; //Field ord:Lscala/math/Ordering;
   8:	invokevirtual	#50; //Method scala/collection/generic/SortedSetFactory.newBuilder:(Lscala/math/Ordering;)Lscala/collection/mutable/Builder;
   11:	areturn
  LineNumberTable: 
   line 34: 0

  Signature: length = 0x2
   00 33 

public scala.collection.mutable.Builder apply(scala.collection.SortedSet);
  Code:
   Stack=2, Locals=2, Args_size=2
   0:	aload_0
   1:	invokevirtual	#44; //Method scala$collection$generic$SortedSetFactory$SortedSetCanBuildFrom$$$outer:()Lscala/collection/generic/SortedSetFactory;
   4:	aload_0
   5:	getfield	#16; //Field ord:Lscala/math/Ordering;
   8:	invokevirtual	#50; //Method scala/collection/generic/SortedSetFactory.newBuilder:(Lscala/math/Ordering;)Lscala/collection/mutable/Builder;
   11:	areturn
  LineNumberTable: 
   line 33: 0

  LocalVariableTable: 
   Start  Length  Slot  Name   Signature
   0      12      0    this       Lscala/collection/generic/SortedSetFactory$SortedSetCanBuildFrom;
   0      12      1    from       Lscala/collection/SortedSet;

  Signature: length = 0x2
   00 35 

}

