Compiled from "SortedMapTemplate.scala"
public abstract class scala.collection.generic.SortedMapTemplate$class extends java.lang.Object
  SourceFile: "SortedMapTemplate.scala"
  Scala: length = 0x
   
  InnerClass: 
   public final #79= #24 of #15; //$anonfun$$plus$1=class scala/collection/generic/SortedMapTemplate$$anonfun$$plus$1 of class scala/collection/generic/SortedMapTemplate
   public #80= #59 of #15; //DefaultKeySortedSet=class scala/collection/generic/SortedMapTemplate$DefaultKeySortedSet of class scala/collection/generic/SortedMapTemplate
  minor version: 0
  major version: 49
  Constant pool:
const #1 = Asciz	SourceFile;
const #2 = Asciz	SortedMapTemplate.scala;
const #3 = Asciz	$init$;
const #4 = Asciz	(Lscala/collection/generic/SortedMapTemplate;)V;
const #5 = Asciz	Code;
const #6 = Asciz	LineNumberTable;
const #7 = Asciz	$this;
const #8 = Asciz	Lscala/collection/generic/SortedMapTemplate;;
const #9 = Asciz	LocalVariableTable;
const #10 = Asciz	$plus;
const #11 = Asciz	(Lscala/collection/generic/SortedMapTemplate;Lscala/Tuple2;Lscala/Tuple2;Lscala/collection/Sequence;)Lscala/collection/SortedMap;;
const #12 = Asciz	scala/runtime/ObjectRef;
const #13 = class	#12;	//  scala/runtime/ObjectRef
const #14 = Asciz	scala/collection/generic/SortedMapTemplate;
const #15 = class	#14;	//  scala/collection/generic/SortedMapTemplate
const #16 = Asciz	(Lscala/Tuple2;)Lscala/collection/SortedMap;;
const #17 = NameAndType	#10:#16;//  $plus:(Lscala/Tuple2;)Lscala/collection/SortedMap;
const #18 = InterfaceMethod	#15.#17;	//  scala/collection/generic/SortedMapTemplate.$plus:(Lscala/Tuple2;)Lscala/collection/SortedMap;
const #19 = Asciz	<init>;
const #20 = Asciz	(Ljava/lang/Object;)V;
const #21 = NameAndType	#19:#20;//  "<init>":(Ljava/lang/Object;)V
const #22 = Method	#13.#21;	//  scala/runtime/ObjectRef."<init>":(Ljava/lang/Object;)V
const #23 = Asciz	scala/collection/generic/SortedMapTemplate$$anonfun$$plus$1;
const #24 = class	#23;	//  scala/collection/generic/SortedMapTemplate$$anonfun$$plus$1
const #25 = Asciz	(Lscala/collection/generic/SortedMapTemplate;Lscala/runtime/ObjectRef;)V;
const #26 = NameAndType	#19:#25;//  "<init>":(Lscala/collection/generic/SortedMapTemplate;Lscala/runtime/ObjectRef;)V
const #27 = Method	#24.#26;	//  scala/collection/generic/SortedMapTemplate$$anonfun$$plus$1."<init>":(Lscala/collection/generic/SortedMapTemplate;Lscala/runtime/ObjectRef;)V
const #28 = Asciz	scala/collection/generic/IterableTemplate;
const #29 = class	#28;	//  scala/collection/generic/IterableTemplate
const #30 = Asciz	foreach;
const #31 = Asciz	(Lscala/Function1;)V;
const #32 = NameAndType	#30:#31;//  foreach:(Lscala/Function1;)V
const #33 = InterfaceMethod	#29.#32;	//  scala/collection/generic/IterableTemplate.foreach:(Lscala/Function1;)V
const #34 = Asciz	elem;
const #35 = Asciz	Ljava/lang/Object;;
const #36 = NameAndType	#34:#35;//  elem:Ljava/lang/Object;
const #37 = Field	#13.#36;	//  scala/runtime/ObjectRef.elem:Ljava/lang/Object;
const #38 = Asciz	scala/collection/SortedMap;
const #39 = class	#38;	//  scala/collection/SortedMap
const #40 = Asciz	elem1;
const #41 = Asciz	Lscala/Tuple2;;
const #42 = Asciz	elem2;
const #43 = Asciz	elems;
const #44 = Asciz	Lscala/collection/Sequence;;
const #45 = Asciz	m$1;
const #46 = Asciz	Lscala/runtime/ObjectRef;;
const #47 = Asciz	updated;
const #48 = Asciz	(Lscala/collection/generic/SortedMapTemplate;Ljava/lang/Object;Ljava/lang/Object;)Lscala/collection/SortedMap;;
const #49 = Asciz	scala/Tuple2;
const #50 = class	#49;	//  scala/Tuple2
const #51 = Asciz	(Ljava/lang/Object;Ljava/lang/Object;)V;
const #52 = NameAndType	#19:#51;//  "<init>":(Ljava/lang/Object;Ljava/lang/Object;)V
const #53 = Method	#50.#52;	//  scala/Tuple2."<init>":(Ljava/lang/Object;Ljava/lang/Object;)V
const #54 = Asciz	key;
const #55 = Asciz	value;
const #56 = Asciz	keySet;
const #57 = Asciz	(Lscala/collection/generic/SortedMapTemplate;)Lscala/collection/SortedSet;;
const #58 = Asciz	scala/collection/generic/SortedMapTemplate$DefaultKeySortedSet;
const #59 = class	#58;	//  scala/collection/generic/SortedMapTemplate$DefaultKeySortedSet
const #60 = NameAndType	#19:#4;//  "<init>":(Lscala/collection/generic/SortedMapTemplate;)V
const #61 = Method	#59.#60;	//  scala/collection/generic/SortedMapTemplate$DefaultKeySortedSet."<init>":(Lscala/collection/generic/SortedMapTemplate;)V
const #62 = Asciz	lastKey;
const #63 = Asciz	(Lscala/collection/generic/SortedMapTemplate;)Ljava/lang/Object;;
const #64 = Asciz	scala/collection/generic/TraversableTemplate;
const #65 = class	#64;	//  scala/collection/generic/TraversableTemplate
const #66 = Asciz	last;
const #67 = Asciz	()Ljava/lang/Object;;
const #68 = NameAndType	#66:#67;//  last:()Ljava/lang/Object;
const #69 = InterfaceMethod	#65.#68;	//  scala/collection/generic/TraversableTemplate.last:()Ljava/lang/Object;
const #70 = Asciz	_1;
const #71 = NameAndType	#70:#67;//  _1:()Ljava/lang/Object;
const #72 = Method	#50.#71;	//  scala/Tuple2._1:()Ljava/lang/Object;
const #73 = Asciz	firstKey;
const #74 = Asciz	head;
const #75 = NameAndType	#74:#67;//  head:()Ljava/lang/Object;
const #76 = InterfaceMethod	#29.#75;	//  scala/collection/generic/IterableTemplate.head:()Ljava/lang/Object;
const #77 = Asciz	Scala;
const #78 = Asciz	InnerClasses;
const #79 = Asciz	$anonfun$$plus$1;
const #80 = Asciz	DefaultKeySortedSet;
const #81 = Asciz	scala/collection/generic/SortedMapTemplate$class;
const #82 = class	#81;	//  scala/collection/generic/SortedMapTemplate$class
const #83 = Asciz	java/lang/Object;
const #84 = class	#83;	//  java/lang/Object

{
public static void $init$(scala.collection.generic.SortedMapTemplate);
  Code:
   Stack=0, Locals=1, Args_size=1
   0:	return
  LineNumberTable: 
   line 23: 0

  LocalVariableTable: 
   Start  Length  Slot  Name   Signature
   0      1      0    $this       Lscala/collection/generic/SortedMapTemplate;


public static scala.collection.SortedMap $plus(scala.collection.generic.SortedMapTemplate, scala.Tuple2, scala.Tuple2, scala.collection.Sequence);
  Code:
   Stack=5, Locals=5, Args_size=4
   0:	new	#13; //class scala/runtime/ObjectRef
   3:	dup
   4:	aload_0
   5:	aload_1
   6:	invokeinterface	#18,  2; //InterfaceMethod scala/collection/generic/SortedMapTemplate.$plus:(Lscala/Tuple2;)Lscala/collection/SortedMap;
   11:	aload_2
   12:	invokeinterface	#18,  2; //InterfaceMethod scala/collection/generic/SortedMapTemplate.$plus:(Lscala/Tuple2;)Lscala/collection/SortedMap;
   17:	invokespecial	#22; //Method scala/runtime/ObjectRef."<init>":(Ljava/lang/Object;)V
   20:	astore	4
   22:	aload_3
   23:	new	#24; //class scala/collection/generic/SortedMapTemplate$$anonfun$$plus$1
   26:	dup
   27:	aload_0
   28:	aload	4
   30:	invokespecial	#27; //Method scala/collection/generic/SortedMapTemplate$$anonfun$$plus$1."<init>":(Lscala/collection/generic/SortedMapTemplate;Lscala/runtime/ObjectRef;)V
   33:	invokeinterface	#33,  2; //InterfaceMethod scala/collection/generic/IterableTemplate.foreach:(Lscala/Function1;)V
   38:	aload	4
   40:	getfield	#37; //Field scala/runtime/ObjectRef.elem:Ljava/lang/Object;
   43:	checkcast	#39; //class scala/collection/SortedMap
   46:	areturn
  LineNumberTable: 
   line 72: 0
   line 73: 22
   line 74: 38

  LocalVariableTable: 
   Start  Length  Slot  Name   Signature
   0      47      0    $this       Lscala/collection/generic/SortedMapTemplate;
   0      47      1    elem1       Lscala/Tuple2;
   0      47      2    elem2       Lscala/Tuple2;
   0      47      3    elems       Lscala/collection/Sequence;
   22      24      4    m$1       Lscala/runtime/ObjectRef;


public static scala.collection.SortedMap updated(scala.collection.generic.SortedMapTemplate, java.lang.Object, java.lang.Object);
  Code:
   Stack=5, Locals=3, Args_size=3
   0:	aload_0
   1:	new	#50; //class scala/Tuple2
   4:	dup
   5:	aload_1
   6:	aload_2
   7:	invokespecial	#53; //Method scala/Tuple2."<init>":(Ljava/lang/Object;Ljava/lang/Object;)V
   10:	invokeinterface	#18,  2; //InterfaceMethod scala/collection/generic/SortedMapTemplate.$plus:(Lscala/Tuple2;)Lscala/collection/SortedMap;
   15:	areturn
  LineNumberTable: 
   line 53: 0

  LocalVariableTable: 
   Start  Length  Slot  Name   Signature
   0      16      0    $this       Lscala/collection/generic/SortedMapTemplate;
   0      16      1    key       Ljava/lang/Object;
   0      16      2    value       Ljava/lang/Object;


public static scala.collection.SortedSet keySet(scala.collection.generic.SortedMapTemplate);
  Code:
   Stack=3, Locals=1, Args_size=1
   0:	new	#59; //class scala/collection/generic/SortedMapTemplate$DefaultKeySortedSet
   3:	dup
   4:	aload_0
   5:	invokespecial	#61; //Method scala/collection/generic/SortedMapTemplate$DefaultKeySortedSet."<init>":(Lscala/collection/generic/SortedMapTemplate;)V
   8:	areturn
  LineNumberTable: 
   line 34: 0

  LocalVariableTable: 
   Start  Length  Slot  Name   Signature
   0      9      0    $this       Lscala/collection/generic/SortedMapTemplate;


public static java.lang.Object lastKey(scala.collection.generic.SortedMapTemplate);
  Code:
   Stack=1, Locals=1, Args_size=1
   0:	aload_0
   1:	invokeinterface	#69,  1; //InterfaceMethod scala/collection/generic/TraversableTemplate.last:()Ljava/lang/Object;
   6:	checkcast	#50; //class scala/Tuple2
   9:	invokevirtual	#72; //Method scala/Tuple2._1:()Ljava/lang/Object;
   12:	areturn
  LineNumberTable: 
   line 27: 0

  LocalVariableTable: 
   Start  Length  Slot  Name   Signature
   0      13      0    $this       Lscala/collection/generic/SortedMapTemplate;


public static java.lang.Object firstKey(scala.collection.generic.SortedMapTemplate);
  Code:
   Stack=1, Locals=1, Args_size=1
   0:	aload_0
   1:	invokeinterface	#76,  1; //InterfaceMethod scala/collection/generic/IterableTemplate.head:()Ljava/lang/Object;
   6:	checkcast	#50; //class scala/Tuple2
   9:	invokevirtual	#72; //Method scala/Tuple2._1:()Ljava/lang/Object;
   12:	areturn
  LineNumberTable: 
   line 26: 0

  LocalVariableTable: 
   Start  Length  Slot  Name   Signature
   0      13      0    $this       Lscala/collection/generic/SortedMapTemplate;


}

