Compiled from "SortedMapFactory.scala"
public class scala.collection.generic.SortedMapFactory$SortedMapBuilderFactory extends java.lang.Object implements scala.collection.generic.BuilderFactory,scala.ScalaObject
  SourceFile: "SortedMapFactory.scala"
  Signature: length = 0x2
   00 34 
  Scala: length = 0x
   
  InnerClass: 
   public #55= #14 of #45; //SortedMapBuilderFactory=class scala/collection/generic/SortedMapFactory$SortedMapBuilderFactory of class scala/collection/generic/SortedMapFactory
  minor version: 0
  major version: 49
  Constant pool:
const #1 = Asciz	SourceFile;
const #2 = Asciz	SortedMapFactory.scala;
const #3 = Asciz	$outer;
const #4 = Asciz	Lscala/collection/generic/SortedMapFactory;;
const #5 = Asciz	ord;
const #6 = Asciz	Lscala/Ordering;;
const #7 = Asciz	Lscala/Ordering<TA;>;;
const #8 = Asciz	Signature;
const #9 = Asciz	<init>;
const #10 = Asciz	(Lscala/collection/generic/SortedMapFactory;Lscala/Ordering;)V;
const #11 = Asciz	Code;
const #12 = Asciz	LineNumberTable;
const #13 = Asciz	scala/collection/generic/SortedMapFactory$SortedMapBuilderFactory;
const #14 = class	#13;	//  scala/collection/generic/SortedMapFactory$SortedMapBuilderFactory
const #15 = NameAndType	#5:#6;//  ord:Lscala/Ordering;
const #16 = Field	#14.#15;	//  scala/collection/generic/SortedMapFactory$SortedMapBuilderFactory.ord:Lscala/Ordering;
const #17 = Asciz	java/lang/NullPointerException;
const #18 = class	#17;	//  java/lang/NullPointerException
const #19 = Asciz	()V;
const #20 = NameAndType	#9:#19;//  "<init>":()V
const #21 = Method	#18.#20;	//  java/lang/NullPointerException."<init>":()V
const #22 = NameAndType	#3:#4;//  $outer:Lscala/collection/generic/SortedMapFactory;
const #23 = Field	#14.#22;	//  scala/collection/generic/SortedMapFactory$SortedMapBuilderFactory.$outer:Lscala/collection/generic/SortedMapFactory;
const #24 = Asciz	java/lang/Object;
const #25 = class	#24;	//  java/lang/Object
const #26 = Method	#25.#20;	//  java/lang/Object."<init>":()V
const #27 = Asciz	this;
const #28 = Asciz	Lscala/collection/generic/SortedMapFactory$SortedMapBuilderFactory;;
const #29 = Asciz	LocalVariableTable;
const #30 = Asciz	(Lscala/collection/generic/SortedMapFactory<TCC;>;Lscala/Ordering<TA;>;)V;
const #31 = Asciz	apply;
const #32 = Asciz	(Ljava/lang/Object;)Lscala/collection/generic/Builder;;
const #33 = Asciz	scala/collection/SortedMap;
const #34 = class	#33;	//  scala/collection/SortedMap
const #35 = Asciz	(Lscala/collection/SortedMap;)Lscala/collection/generic/Builder;;
const #36 = NameAndType	#31:#35;//  apply:(Lscala/collection/SortedMap;)Lscala/collection/generic/Builder;
const #37 = Method	#14.#36;	//  scala/collection/generic/SortedMapFactory$SortedMapBuilderFactory.apply:(Lscala/collection/SortedMap;)Lscala/collection/generic/Builder;
const #38 = Asciz	from;
const #39 = Asciz	Ljava/lang/Object;;
const #40 = Asciz	scala$collection$generic$SortedMapFactory$SortedMapBuilderFactory$$$outer;
const #41 = Asciz	()Lscala/collection/generic/SortedMapFactory;;
const #42 = NameAndType	#40:#41;//  scala$collection$generic$SortedMapFactory$SortedMapBuilderFactory$$$outer:()Lscala/collection/generic/SortedMapFactory;
const #43 = Method	#14.#42;	//  scala/collection/generic/SortedMapFactory$SortedMapBuilderFactory.scala$collection$generic$SortedMapFactory$SortedMapBuilderFactory$$$outer:()Lscala/collection/generic/SortedMapFactory;
const #44 = Asciz	scala/collection/generic/SortedMapFactory;
const #45 = class	#44;	//  scala/collection/generic/SortedMapFactory
const #46 = Asciz	newBuilder;
const #47 = Asciz	(Lscala/Ordering;)Lscala/collection/generic/Builder;;
const #48 = NameAndType	#46:#47;//  newBuilder:(Lscala/Ordering;)Lscala/collection/generic/Builder;
const #49 = Method	#45.#48;	//  scala/collection/generic/SortedMapFactory.newBuilder:(Lscala/Ordering;)Lscala/collection/generic/Builder;
const #50 = Asciz	Lscala/collection/SortedMap;;
const #51 = Asciz	(TCC;)Lscala/collection/generic/Builder<Lscala/Tuple2<TA;TB;>;TCC;>;;
const #52 = Asciz	<A:Ljava/lang/Object;B:Ljava/lang/Object;>Ljava/lang/Object;Lscala/collection/generic/BuilderFactory<Lscala/Tuple2<TA;TB;>;TCC;TCC;>;Lscala/ScalaObject;;
const #53 = Asciz	Scala;
const #54 = Asciz	InnerClasses;
const #55 = Asciz	SortedMapBuilderFactory;
const #56 = Asciz	scala/collection/generic/BuilderFactory;
const #57 = class	#56;	//  scala/collection/generic/BuilderFactory
const #58 = Asciz	scala/ScalaObject;
const #59 = class	#58;	//  scala/ScalaObject

{
public final scala.collection.generic.SortedMapFactory $outer;

public scala.collection.generic.SortedMapFactory$SortedMapBuilderFactory(scala.collection.generic.SortedMapFactory, scala.Ordering);
  Code:
   Stack=2, Locals=3, Args_size=3
   0:	aload_0
   1:	aload_2
   2:	putfield	#16; //Field ord:Lscala/Ordering;
   5:	aload_1
   6:	ifnonnull	17
   9:	new	#18; //class java/lang/NullPointerException
   12:	dup
   13:	invokespecial	#21; //Method java/lang/NullPointerException."<init>":()V
   16:	athrow
   17:	aload_0
   18:	aload_1
   19:	putfield	#23; //Field $outer:Lscala/collection/generic/SortedMapFactory;
   22:	aload_0
   23:	invokespecial	#26; //Method java/lang/Object."<init>":()V
   26:	return
  LineNumberTable: 
   line 27: 0

  LocalVariableTable: 
   Start  Length  Slot  Name   Signature
   0      27      0    this       Lscala/collection/generic/SortedMapFactory$SortedMapBuilderFactory;
   0      27      1    $outer       Lscala/collection/generic/SortedMapFactory;
   0      27      2    ord       Lscala/Ordering;

  Signature: length = 0x2
   00 1E 

public scala.collection.generic.Builder apply(java.lang.Object);
  Code:
   Stack=2, Locals=2, Args_size=2
   0:	aload_0
   1:	aload_1
   2:	checkcast	#34; //class scala/collection/SortedMap
   5:	invokevirtual	#37; //Method apply:(Lscala/collection/SortedMap;)Lscala/collection/generic/Builder;
   8:	areturn
  LineNumberTable: 
   line 27: 0

  LocalVariableTable: 
   Start  Length  Slot  Name   Signature
   0      9      0    this       Lscala/collection/generic/SortedMapFactory$SortedMapBuilderFactory;
   0      9      1    from       Ljava/lang/Object;


public scala.collection.generic.SortedMapFactory scala$collection$generic$SortedMapFactory$SortedMapBuilderFactory$$$outer();
  Code:
   Stack=1, Locals=1, Args_size=1
   0:	aload_0
   1:	getfield	#23; //Field $outer:Lscala/collection/generic/SortedMapFactory;
   4:	areturn
  LineNumberTable: 
   line 27: 0


public scala.collection.generic.Builder apply(scala.collection.SortedMap);
  Code:
   Stack=2, Locals=2, Args_size=2
   0:	aload_0
   1:	invokevirtual	#43; //Method scala$collection$generic$SortedMapFactory$SortedMapBuilderFactory$$$outer:()Lscala/collection/generic/SortedMapFactory;
   4:	aload_0
   5:	getfield	#16; //Field ord:Lscala/Ordering;
   8:	invokevirtual	#49; //Method scala/collection/generic/SortedMapFactory.newBuilder:(Lscala/Ordering;)Lscala/collection/generic/Builder;
   11:	areturn
  LineNumberTable: 
   line 28: 0

  LocalVariableTable: 
   Start  Length  Slot  Name   Signature
   0      12      0    this       Lscala/collection/generic/SortedMapFactory$SortedMapBuilderFactory;
   0      12      1    from       Lscala/collection/SortedMap;

  Signature: length = 0x2
   00 33 

}

