Compiled from "SortedMapFactory.scala"
public abstract class scala.collection.generic.SortedMapFactory extends java.lang.Object implements scala.ScalaObject
  SourceFile: "SortedMapFactory.scala"
  Signature: length = 0x2
   00 35 
  ScalaSig: length = 0x401
   05 00 FFFFFF81 1E 06 05 01 02 FFFFFF81 00 09 02 10 53 6F 72
   74 65 64 4D 61 70 46 61 63 74 6F 72 79 0A 02 03
   04 01 07 67 65 6E 65 72 69 63 0A 02 05 06 01 0A
   63 6F 6C 6C 65 63 74 69 6F 6E 0A 01 07 01 05 73
   63 61 6C 61 03 00 15 02 0A 1E 13 03 00 0B 13 10
   02 0C 11 0D 01 0D 0A 02 0E 0F 01 04 6C 61 6E 67
   0A 01 10 01 04 6A 61 76 61 09 02 12 0D 02 06 4F
   62 6A 65 63 74 10 02 14 15 0D 01 06 09 02 16 06
   02 0B 53 63 61 6C 61 4F 62 6A 65 63 74 08 05 18
   00 FFFFFF84 00 19 01 06 3C 69 6E 69 74 3E 14 01 1A 10
   03 1B 00 1C 0D 01 02 10 02 1D 1E 0C 00 04 05 1F
   00 FFFFFFC2 00 20 02 02 43 43 15 03 21 2D 34 11 02 22
   25 10 02 14 23 09 02 24 06 02 07 4E 6F 74 68 69
   6E 67 12 03 26 28 36 06 08 27 00 FFFFFF84 FFFFFF80 FFFFFF80 FFFFFF80 00
   25 02 0C 3C 72 65 66 69 6E 65 6D 65 6E 74 3E 10
   04 29 2A 2C 33 0D 01 04 09 02 2B 04 02 09 53 6F
   72 74 65 64 4D 61 70 10 02 1D 2D 04 08 2E 1E FFFFFF84
   FFFFFF80 FFFFFF80 FFFFFFC2 00 2F 02 01 41 11 02 22 30 10 02 14 31
   09 02 32 06 02 03 41 6E 79 10 02 1D 34 04 08 35
   1E FFFFFF84 FFFFFF80 FFFFFF80 FFFFFFC2 00 2F 02 01 42 10 05 29 37 2C 33
   39 09 02 38 04 02 0D 53 6F 72 74 65 64 4D 61 70
   4C 69 6B 65 10 04 1D 1E 2C 33 05 08 3B 00 FFFFFF84 FFFFFF80
   FFFFFF80 FFFFFF80 00 3C 02 04 43 6F 6C 6C 30 03 3D 3F 42 10
   04 1D 1E 3E 41 10 02 1D 3F 04 08 40 3A FFFFFF84 FFFFFF80 FFFFFF80
   FFFFFF82 00 2F 02 03 5F 24 31 10 02 1D 42 04 08 43 3A
   FFFFFF84 FFFFFF80 FFFFFF80 FFFFFF82 00 2F 02 03 5F 24 32 08 05 45 00 FFFFFF86
   00 46 01 05 65 6D 70 74 79 15 03 47 4A 4C 16 02
   48 4D 10 04 1D 1E 49 4B 10 02 1D 4A 04 08 2E 44
   FFFFFF84 FFFFFF80 FFFFFF80 FFFFFFC2 00 2F 10 02 1D 4C 04 08 35 44 FFFFFF84 FFFFFF80
   FFFFFF80 FFFFFFC2 00 2F 08 05 4E 44 FFFFFFC0 01 4F 01 03 6F 72 64
   10 03 50 58 49 0E 02 51 56 0E 02 52 55 0D 01 53
   0A 02 54 08 01 06 3C 72 6F 6F 74 3E 09 01 07 09
   02 57 06 01 07 70 61 63 6B 61 67 65 09 02 59 5A
   02 08 4F 72 64 65 72 69 6E 67 0A 02 57 06 08 05
   5C 00 FFFFFF84 00 5D 01 05 61 70 70 6C 79 15 03 5E 62
   64 14 02 5F 67 16 02 60 65 10 04 1D 1E 61 63 10
   02 1D 62 04 08 2E 5B FFFFFF84 FFFFFF80 FFFFFF80 FFFFFFC2 00 2F 10 02 1D
   64 04 08 35 5B FFFFFF84 FFFFFF80 FFFFFF80 FFFFFFC2 00 2F 08 05 4E 5B FFFFFFC0
   01 66 10 03 50 58 61 08 05 68 5B FFFFFFC0 00 69 01 05
   65 6C 65 6D 73 10 03 14 6A 6C 09 02 6B 06 02 0A
   3C 72 65 70 65 61 74 65 64 3E 10 04 14 6D 61 63
   09 02 6E 06 02 06 54 75 70 6C 65 32 08 05 70 00
   FFFFFF84 00 71 01 0A 6E 65 77 42 75 69 6C 64 65 72 15
   03 72 7B 7D 16 02 73 7F 10 04 74 77 79 7E 0D 01
   75 0A 02 76 04 01 07 6D 75 74 61 62 6C 65 09 02
   78 75 02 07 42 75 69 6C 64 65 72 10 04 14 6D 7A
   7C 10 02 1D 7B 04 08 2E 6F FFFFFF84 FFFFFF80 FFFFFF80 FFFFFFC2 00 2F 10
   02 1D 7D 04 08 35 6F FFFFFF84 FFFFFF80 FFFFFF80 FFFFFFC2 00 2F 10 04 1D
   1E 7A 7C 08 06 4E 6F FFFFFFC0 01 FFFFFF81 00 10 03 50 58 7A
   06 06 FFFFFF81 02 00 00 FFFFFF81 03 02 15 53 6F 72 74 65 64
   4D 61 70 43 61 6E 42 75 69 6C 64 46 72 6F 6D 15
   06 FFFFFF81 04 FFFFFF81 0C FFFFFF81 0E 13 06 FFFFFF81 01 0B FFFFFF81 05 13 10
   09 1B FFFFFF81 06 FFFFFF81 08 FFFFFF81 0A FFFFFF81 0F 09 03 FFFFFF81 07 02 02
   0C 43 61 6E 42 75 69 6C 64 46 72 6F 6D 10 03 FFFFFF81
   09 3A 0D 01 00 10 06 14 6D FFFFFF81 0B FFFFFF81 0D 10 03 1D
   FFFFFF81 0C 04 09 2E FFFFFF81 01 FFFFFF84 FFFFFF80 FFFFFF80 FFFFFFC2 00 2F 10 03 1D
   FFFFFF81 0E 04 09 35 FFFFFF81 01 FFFFFF84 FFFFFF80 FFFFFF80 FFFFFFC2 00 2F 10 06 1D
   1E FFFFFF81 0B FFFFFF81 0D 08 0A 4E FFFFFF81 01 FFFFFF82 FFFFFF80 FFFFFFA0 FFFFFF80 05 FFFFFF81
   11 10 04 50 58 FFFFFF81 0B 08 07 18 FFFFFF81 01 FFFFFF84 00 FFFFFF81 13
   14 02 FFFFFF81 14 16 04 FFFFFF81 15 FFFFFF81 16 10 08 FFFFFF81 09 FFFFFF81 01
   FFFFFF81 0B FFFFFF81 0D 08 07 4E FFFFFF81 12 FFFFFFC0 01 FFFFFF81 11 08 07 5C
   FFFFFF81 01 FFFFFF84 00 FFFFFF81 18 14 04 FFFFFF81 19 FFFFFF81 1A 10 06 74 77
   FFFFFF81 0A FFFFFF81 0F 08 08 FFFFFF81 1B FFFFFF81 17 FFFFFFC0 00 FFFFFF81 08 01 04
   66 72 6F 6D 08 07 5C FFFFFF81 01 FFFFFF84 00 FFFFFF81 1D 14 02 FFFFFF81
   19 
  InnerClass: 
   public #58= #57 of #17; //SortedMapCanBuildFrom=class scala/collection/generic/SortedMapFactory$SortedMapCanBuildFrom of class scala/collection/generic/SortedMapFactory
  minor version: 0
  major version: 49
  Constant pool:
const #1 = Asciz	SourceFile;
const #2 = Asciz	SortedMapFactory.scala;
const #3 = Asciz	<init>;
const #4 = Asciz	()V;
const #5 = Asciz	Code;
const #6 = Asciz	LineNumberTable;
const #7 = Asciz	java/lang/Object;
const #8 = class	#7;	//  java/lang/Object
const #9 = NameAndType	#3:#4;//  "<init>":()V
const #10 = Method	#8.#9;	//  java/lang/Object."<init>":()V
const #11 = Asciz	Signature;
const #12 = Asciz	newBuilder;
const #13 = Asciz	(Lscala/math/Ordering;)Lscala/collection/mutable/Builder;;
const #14 = Asciz	scala/collection/mutable/MapBuilder;
const #15 = class	#14;	//  scala/collection/mutable/MapBuilder
const #16 = Asciz	scala/collection/generic/SortedMapFactory;
const #17 = class	#16;	//  scala/collection/generic/SortedMapFactory
const #18 = Asciz	empty;
const #19 = Asciz	(Lscala/math/Ordering;)Lscala/collection/SortedMap;;
const #20 = NameAndType	#18:#19;//  empty:(Lscala/math/Ordering;)Lscala/collection/SortedMap;
const #21 = Method	#17.#20;	//  scala/collection/generic/SortedMapFactory.empty:(Lscala/math/Ordering;)Lscala/collection/SortedMap;
const #22 = Asciz	(Lscala/collection/Map;)V;
const #23 = NameAndType	#3:#22;//  "<init>":(Lscala/collection/Map;)V
const #24 = Method	#15.#23;	//  scala/collection/mutable/MapBuilder."<init>":(Lscala/collection/Map;)V
const #25 = Asciz	this;
const #26 = Asciz	Lscala/collection/generic/SortedMapFactory;;
const #27 = Asciz	ord;
const #28 = Asciz	Lscala/math/Ordering;;
const #29 = Asciz	LocalVariableTable;
const #30 = Asciz	<A:Ljava/lang/Object;B:Ljava/lang/Object;>(Lscala/math/Ordering<TA;>;)Lscala/collection/mutable/Builder<Lscala/Tuple2<TA;TB;>;TCC;>;;
const #31 = Asciz	apply;
const #32 = Asciz	(Lscala/collection/Seq;Lscala/math/Ordering;)Lscala/collection/SortedMap;;
const #33 = NameAndType	#12:#13;//  newBuilder:(Lscala/math/Ordering;)Lscala/collection/mutable/Builder;
const #34 = Method	#17.#33;	//  scala/collection/generic/SortedMapFactory.newBuilder:(Lscala/math/Ordering;)Lscala/collection/mutable/Builder;
const #35 = Asciz	scala/collection/generic/Growable;
const #36 = class	#35;	//  scala/collection/generic/Growable
const #37 = Asciz	$plus$plus$eq;
const #38 = Asciz	(Lscala/collection/Traversable;)Lscala/collection/generic/Growable;;
const #39 = NameAndType	#37:#38;//  $plus$plus$eq:(Lscala/collection/Traversable;)Lscala/collection/generic/Growable;
const #40 = InterfaceMethod	#36.#39;	//  scala/collection/generic/Growable.$plus$plus$eq:(Lscala/collection/Traversable;)Lscala/collection/generic/Growable;
const #41 = Asciz	scala/collection/mutable/Builder;
const #42 = class	#41;	//  scala/collection/mutable/Builder
const #43 = Asciz	result;
const #44 = Asciz	()Ljava/lang/Object;;
const #45 = NameAndType	#43:#44;//  result:()Ljava/lang/Object;
const #46 = InterfaceMethod	#42.#45;	//  scala/collection/mutable/Builder.result:()Ljava/lang/Object;
const #47 = Asciz	scala/collection/SortedMap;
const #48 = class	#47;	//  scala/collection/SortedMap
const #49 = Asciz	elems;
const #50 = Asciz	Lscala/collection/Seq;;
const #51 = Asciz	<A:Ljava/lang/Object;B:Ljava/lang/Object;>(Lscala/collection/Seq<Lscala/Tuple2<TA;TB;>;>;Lscala/math/Ordering<TA;>;)TCC;;
const #52 = Asciz	<A:Ljava/lang/Object;B:Ljava/lang/Object;>(Lscala/math/Ordering<TA;>;)TCC;;
const #53 = Asciz	<CC:Lscala/collection/SortedMap<Ljava/lang/Object;Ljava/lang/Object;>;>Ljava/lang/Object;Lscala/ScalaObject;;
const #54 = Asciz	ScalaSig;
const #55 = Asciz	InnerClasses;
const #56 = Asciz	scala/collection/generic/SortedMapFactory$SortedMapCanBuildFrom;
const #57 = class	#56;	//  scala/collection/generic/SortedMapFactory$SortedMapCanBuildFrom
const #58 = Asciz	SortedMapCanBuildFrom;
const #59 = Asciz	scala/ScalaObject;
const #60 = class	#59;	//  scala/ScalaObject

{
public scala.collection.generic.SortedMapFactory();
  Code:
   Stack=1, Locals=1, Args_size=1
   0:	aload_0
   1:	invokespecial	#10; //Method java/lang/Object."<init>":()V
   4:	return
  LineNumberTable: 
   line 21: 0

  Signature: length = 0x2
   00 04 

public scala.collection.mutable.Builder newBuilder(scala.math.Ordering);
  Code:
   Stack=4, Locals=2, Args_size=2
   0:	new	#15; //class scala/collection/mutable/MapBuilder
   3:	dup
   4:	aload_0
   5:	aload_1
   6:	invokevirtual	#21; //Method empty:(Lscala/math/Ordering;)Lscala/collection/SortedMap;
   9:	invokespecial	#24; //Method scala/collection/mutable/MapBuilder."<init>":(Lscala/collection/Map;)V
   12:	areturn
  LineNumberTable: 
   line 30: 0

  LocalVariableTable: 
   Start  Length  Slot  Name   Signature
   0      13      0    this       Lscala/collection/generic/SortedMapFactory;
   0      13      1    ord       Lscala/math/Ordering;

  Signature: length = 0x2
   00 1E 

public scala.collection.SortedMap apply(scala.collection.Seq, scala.math.Ordering);
  Code:
   Stack=2, Locals=3, Args_size=3
   0:	aload_0
   1:	aload_2
   2:	invokevirtual	#34; //Method newBuilder:(Lscala/math/Ordering;)Lscala/collection/mutable/Builder;
   5:	aload_1
   6:	invokeinterface	#40,  2; //InterfaceMethod scala/collection/generic/Growable.$plus$plus$eq:(Lscala/collection/Traversable;)Lscala/collection/generic/Growable;
   11:	checkcast	#42; //class scala/collection/mutable/Builder
   14:	invokeinterface	#46,  1; //InterfaceMethod scala/collection/mutable/Builder.result:()Ljava/lang/Object;
   19:	checkcast	#48; //class scala/collection/SortedMap
   22:	areturn
  LineNumberTable: 
   line 27: 0

  LocalVariableTable: 
   Start  Length  Slot  Name   Signature
   0      23      0    this       Lscala/collection/generic/SortedMapFactory;
   0      23      1    elems       Lscala/collection/Seq;
   0      23      2    ord       Lscala/math/Ordering;

  Signature: length = 0x2
   00 33 

public abstract scala.collection.SortedMap empty(scala.math.Ordering);
  Signature: length = 0x2
   00 34 

}

