Compiled from "SortedMapTemplate.scala"
public class scala.collection.generic.SortedMapTemplate$DefaultKeySortedSet extends scala.collection.generic.MapTemplate$DefaultKeySet implements scala.collection.SortedSet,scala.ScalaObject
  SourceFile: "SortedMapTemplate.scala"
  Signature: length = 0x2
   00 FFFFFFCC 
  Scala: length = 0x
   
  InnerClass: 
   public #209= #19 of #208; //DefaultKeySet=class scala/collection/generic/MapTemplate$DefaultKeySet of class scala/collection/generic/MapTemplate
   public #210= #15 of #127; //DefaultKeySortedSet=class scala/collection/generic/SortedMapTemplate$DefaultKeySortedSet of class scala/collection/generic/SortedMapTemplate
  minor version: 0
  major version: 49
  Constant pool:
const #1 = Asciz	SourceFile;
const #2 = Asciz	SortedMapTemplate.scala;
const #3 = Asciz	$outer;
const #4 = Asciz	Lscala/collection/generic/SortedMapTemplate;;
const #5 = Asciz	<init>;
const #6 = Asciz	(Lscala/collection/generic/SortedMapTemplate;)V;
const #7 = Asciz	Code;
const #8 = Asciz	LineNumberTable;
const #9 = Asciz	java/lang/NullPointerException;
const #10 = class	#9;	//  java/lang/NullPointerException
const #11 = Asciz	()V;
const #12 = NameAndType	#5:#11;//  "<init>":()V
const #13 = Method	#10.#12;	//  java/lang/NullPointerException."<init>":()V
const #14 = Asciz	scala/collection/generic/SortedMapTemplate$DefaultKeySortedSet;
const #15 = class	#14;	//  scala/collection/generic/SortedMapTemplate$DefaultKeySortedSet
const #16 = NameAndType	#3:#4;//  $outer:Lscala/collection/generic/SortedMapTemplate;
const #17 = Field	#15.#16;	//  scala/collection/generic/SortedMapTemplate$DefaultKeySortedSet.$outer:Lscala/collection/generic/SortedMapTemplate;
const #18 = Asciz	scala/collection/generic/MapTemplate$DefaultKeySet;
const #19 = class	#18;	//  scala/collection/generic/MapTemplate$DefaultKeySet
const #20 = Asciz	(Lscala/collection/generic/MapTemplate;)V;
const #21 = NameAndType	#5:#20;//  "<init>":(Lscala/collection/generic/MapTemplate;)V
const #22 = Method	#19.#21;	//  scala/collection/generic/MapTemplate$DefaultKeySet."<init>":(Lscala/collection/generic/MapTemplate;)V
const #23 = Asciz	scala/collection/generic/Sorted$class;
const #24 = class	#23;	//  scala/collection/generic/Sorted$class
const #25 = Asciz	$init$;
const #26 = Asciz	(Lscala/collection/generic/Sorted;)V;
const #27 = NameAndType	#25:#26;//  $init$:(Lscala/collection/generic/Sorted;)V
const #28 = Method	#24.#27;	//  scala/collection/generic/Sorted$class.$init$:(Lscala/collection/generic/Sorted;)V
const #29 = Asciz	scala/collection/generic/SortedSetTemplate$class;
const #30 = class	#29;	//  scala/collection/generic/SortedSetTemplate$class
const #31 = Asciz	(Lscala/collection/generic/SortedSetTemplate;)V;
const #32 = NameAndType	#25:#31;//  $init$:(Lscala/collection/generic/SortedSetTemplate;)V
const #33 = Method	#30.#32;	//  scala/collection/generic/SortedSetTemplate$class.$init$:(Lscala/collection/generic/SortedSetTemplate;)V
const #34 = Asciz	scala/collection/SortedSet$class;
const #35 = class	#34;	//  scala/collection/SortedSet$class
const #36 = Asciz	(Lscala/collection/SortedSet;)V;
const #37 = NameAndType	#25:#36;//  $init$:(Lscala/collection/SortedSet;)V
const #38 = Method	#35.#37;	//  scala/collection/SortedSet$class.$init$:(Lscala/collection/SortedSet;)V
const #39 = Asciz	this;
const #40 = Asciz	Lscala/collection/generic/SortedMapTemplate$DefaultKeySortedSet;;
const #41 = Asciz	LocalVariableTable;
const #42 = Asciz	(Lscala/collection/generic/SortedMapTemplate<TA;TB;TThis;>;)V;
const #43 = Asciz	Signature;
const #44 = Asciz	$plus;
const #45 = Asciz	(Ljava/lang/Object;)Lscala/collection/Set;;
const #46 = Asciz	(Ljava/lang/Object;)Lscala/collection/SortedSet;;
const #47 = NameAndType	#44:#46;//  $plus:(Ljava/lang/Object;)Lscala/collection/SortedSet;
const #48 = Method	#15.#47;	//  scala/collection/generic/SortedMapTemplate$DefaultKeySortedSet.$plus:(Ljava/lang/Object;)Lscala/collection/SortedSet;
const #49 = Asciz	elem;
const #50 = Asciz	Ljava/lang/Object;;
const #51 = Asciz	(Ljava/lang/Object;)Lscala/collection/generic/SetTemplate;;
const #52 = Asciz	(Ljava/lang/Object;)Lscala/collection/generic/Addable;;
const #53 = Asciz	$minus;
const #54 = NameAndType	#53:#46;//  $minus:(Ljava/lang/Object;)Lscala/collection/SortedSet;
const #55 = Method	#15.#54;	//  scala/collection/generic/SortedMapTemplate$DefaultKeySortedSet.$minus:(Ljava/lang/Object;)Lscala/collection/SortedSet;
const #56 = Asciz	(Ljava/lang/Object;)Lscala/collection/generic/Subtractable;;
const #57 = Asciz	rangeImpl;
const #58 = Asciz	(Lscala/Option;Lscala/Option;)Lscala/collection/generic/Sorted;;
const #59 = Asciz	(Lscala/Option;Lscala/Option;)Lscala/collection/SortedSet;;
const #60 = NameAndType	#57:#59;//  rangeImpl:(Lscala/Option;Lscala/Option;)Lscala/collection/SortedSet;
const #61 = Method	#15.#60;	//  scala/collection/generic/SortedMapTemplate$DefaultKeySortedSet.rangeImpl:(Lscala/Option;Lscala/Option;)Lscala/collection/SortedSet;
const #62 = Asciz	from;
const #63 = Asciz	Lscala/Option;;
const #64 = Asciz	until;
const #65 = Asciz	empty;
const #66 = Asciz	()Lscala/collection/Set;;
const #67 = Asciz	scala/collection/SortedSet;
const #68 = class	#67;	//  scala/collection/SortedSet
const #69 = Asciz	()Lscala/collection/SortedSet;;
const #70 = NameAndType	#65:#69;//  empty:()Lscala/collection/SortedSet;
const #71 = InterfaceMethod	#68.#70;	//  scala/collection/SortedSet.empty:()Lscala/collection/SortedSet;
const #72 = Asciz	()Lscala/collection/generic/SetTemplate;;
const #73 = Asciz	(Ljava/lang/Object;)Lscala/collection/generic/Sorted;;
const #74 = Asciz	scala/collection/generic/SortedSetTemplate;
const #75 = class	#74;	//  scala/collection/generic/SortedSetTemplate
const #76 = NameAndType	#62:#46;//  from:(Ljava/lang/Object;)Lscala/collection/SortedSet;
const #77 = InterfaceMethod	#75.#76;	//  scala/collection/generic/SortedSetTemplate.from:(Ljava/lang/Object;)Lscala/collection/SortedSet;
const #78 = NameAndType	#64:#46;//  until:(Ljava/lang/Object;)Lscala/collection/SortedSet;
const #79 = InterfaceMethod	#75.#78;	//  scala/collection/generic/SortedSetTemplate.until:(Ljava/lang/Object;)Lscala/collection/SortedSet;
const #80 = Asciz	range;
const #81 = Asciz	(Ljava/lang/Object;Ljava/lang/Object;)Lscala/collection/generic/Sorted;;
const #82 = Asciz	(Ljava/lang/Object;Ljava/lang/Object;)Lscala/collection/SortedSet;;
const #83 = NameAndType	#80:#82;//  range:(Ljava/lang/Object;Ljava/lang/Object;)Lscala/collection/SortedSet;
const #84 = InterfaceMethod	#75.#83;	//  scala/collection/generic/SortedSetTemplate.range:(Ljava/lang/Object;Ljava/lang/Object;)Lscala/collection/SortedSet;
const #85 = Asciz	apply;
const #86 = Asciz	(Ljava/lang/Object;)Ljava/lang/Object;;
const #87 = Asciz	scala/collection/generic/SetTemplate;
const #88 = class	#87;	//  scala/collection/generic/SetTemplate
const #89 = Asciz	(Ljava/lang/Object;)Z;
const #90 = NameAndType	#85:#89;//  apply:(Ljava/lang/Object;)Z
const #91 = InterfaceMethod	#88.#90;	//  scala/collection/generic/SetTemplate.apply:(Ljava/lang/Object;)Z
const #92 = Asciz	scala/runtime/BoxesRunTime;
const #93 = class	#92;	//  scala/runtime/BoxesRunTime
const #94 = Asciz	boxToBoolean;
const #95 = Asciz	(Z)Ljava/lang/Boolean;;
const #96 = NameAndType	#94:#95;//  boxToBoolean:(Z)Ljava/lang/Boolean;
const #97 = Method	#93.#96;	//  scala/runtime/BoxesRunTime.boxToBoolean:(Z)Ljava/lang/Boolean;
const #98 = Asciz	v1;
const #99 = Asciz	view;
const #100 = Asciz	(II)Lscala/collection/generic/TraversableView;;
const #101 = Asciz	scala/collection/generic/IterableTemplate;
const #102 = class	#101;	//  scala/collection/generic/IterableTemplate
const #103 = Asciz	(II)Lscala/collection/generic/IterableView;;
const #104 = NameAndType	#99:#103;//  view:(II)Lscala/collection/generic/IterableView;
const #105 = InterfaceMethod	#102.#104;	//  scala/collection/generic/IterableTemplate.view:(II)Lscala/collection/generic/IterableView;
const #106 = Asciz	I;
const #107 = Asciz	thisCollection;
const #108 = Asciz	()Lscala/collection/generic/Sorted;;
const #109 = Asciz	scala/collection/generic/TraversableTemplate;
const #110 = class	#109;	//  scala/collection/generic/TraversableTemplate
const #111 = Asciz	()Lscala/collection/generic/TraversableTemplate;;
const #112 = NameAndType	#107:#111;//  thisCollection:()Lscala/collection/generic/TraversableTemplate;
const #113 = InterfaceMethod	#110.#112;	//  scala/collection/generic/TraversableTemplate.thisCollection:()Lscala/collection/generic/TraversableTemplate;
const #114 = Asciz	scala/collection/generic/Sorted;
const #115 = class	#114;	//  scala/collection/generic/Sorted
const #116 = Asciz	()Lscala/collection/generic/Subtractable;;
const #117 = Asciz	scala/collection/generic/Subtractable;
const #118 = class	#117;	//  scala/collection/generic/Subtractable
const #119 = Asciz	()Lscala/collection/generic/Addable;;
const #120 = Asciz	scala/collection/generic/Addable;
const #121 = class	#120;	//  scala/collection/generic/Addable
const #122 = Asciz	scala$collection$generic$SortedMapTemplate$DefaultKeySortedSet$$$outer;
const #123 = Asciz	()Lscala/collection/generic/SortedMapTemplate;;
const #124 = NameAndType	#122:#123;//  scala$collection$generic$SortedMapTemplate$DefaultKeySortedSet$$$outer:()Lscala/collection/generic/SortedMapTemplate;
const #125 = Method	#15.#124;	//  scala/collection/generic/SortedMapTemplate$DefaultKeySortedSet.scala$collection$generic$SortedMapTemplate$DefaultKeySortedSet$$$outer:()Lscala/collection/generic/SortedMapTemplate;
const #126 = Asciz	scala/collection/generic/SortedMapTemplate;
const #127 = class	#126;	//  scala/collection/generic/SortedMapTemplate
const #128 = Asciz	(Lscala/Option;Lscala/Option;)Lscala/collection/generic/SortedMapTemplate;;
const #129 = NameAndType	#57:#128;//  rangeImpl:(Lscala/Option;Lscala/Option;)Lscala/collection/generic/SortedMapTemplate;
const #130 = InterfaceMethod	#127.#129;	//  scala/collection/generic/SortedMapTemplate.rangeImpl:(Lscala/Option;Lscala/Option;)Lscala/collection/generic/SortedMapTemplate;
const #131 = NameAndType	#5:#6;//  "<init>":(Lscala/collection/generic/SortedMapTemplate;)V
const #132 = Method	#15.#131;	//  scala/collection/generic/SortedMapTemplate$DefaultKeySortedSet."<init>":(Lscala/collection/generic/SortedMapTemplate;)V
const #133 = Asciz	map;
const #134 = Asciz	(Lscala/Option<TA;>;Lscala/Option<TA;>;)Lscala/collection/SortedSet<TA;>;;
const #135 = Asciz	java/lang/UnsupportedOperationException;
const #136 = class	#135;	//  java/lang/UnsupportedOperationException
const #137 = Asciz	keySet.-;
const #138 = String	#137;	//  keySet.-
const #139 = Asciz	(Ljava/lang/String;)V;
const #140 = NameAndType	#5:#139;//  "<init>":(Ljava/lang/String;)V
const #141 = Method	#136.#140;	//  java/lang/UnsupportedOperationException."<init>":(Ljava/lang/String;)V
const #142 = Asciz	(TA;)Lscala/collection/SortedSet<TA;>;;
const #143 = Asciz	keySet.+;
const #144 = String	#143;	//  keySet.+
const #145 = Asciz	ordering;
const #146 = Asciz	()Lscala/Ordering;;
const #147 = NameAndType	#145:#146;//  ordering:()Lscala/Ordering;
const #148 = InterfaceMethod	#127.#147;	//  scala/collection/generic/SortedMapTemplate.ordering:()Lscala/Ordering;
const #149 = Asciz	()Lscala/Ordering<TA;>;;
const #150 = Asciz	hasAll;
const #151 = Asciz	(Lscala/collection/Iterator;)Z;
const #152 = Asciz	(Lscala/collection/generic/Sorted;Lscala/collection/Iterator;)Z;
const #153 = NameAndType	#150:#152;//  hasAll:(Lscala/collection/generic/Sorted;Lscala/collection/Iterator;)Z
const #154 = Method	#24.#153;	//  scala/collection/generic/Sorted$class.hasAll:(Lscala/collection/generic/Sorted;Lscala/collection/Iterator;)Z
const #155 = Asciz	j;
const #156 = Asciz	Lscala/collection/Iterator;;
const #157 = Asciz	to;
const #158 = Asciz	(Lscala/collection/generic/Sorted;Ljava/lang/Object;)Lscala/collection/generic/Sorted;;
const #159 = NameAndType	#157:#158;//  to:(Lscala/collection/generic/Sorted;Ljava/lang/Object;)Lscala/collection/generic/Sorted;
const #160 = Method	#24.#159;	//  scala/collection/generic/Sorted$class.to:(Lscala/collection/generic/Sorted;Ljava/lang/Object;)Lscala/collection/generic/Sorted;
const #161 = Asciz	compare;
const #162 = Asciz	(Ljava/lang/Object;Ljava/lang/Object;)I;
const #163 = Asciz	(Lscala/collection/generic/Sorted;Ljava/lang/Object;Ljava/lang/Object;)I;
const #164 = NameAndType	#161:#163;//  compare:(Lscala/collection/generic/Sorted;Ljava/lang/Object;Ljava/lang/Object;)I
const #165 = Method	#24.#164;	//  scala/collection/generic/Sorted$class.compare:(Lscala/collection/generic/Sorted;Ljava/lang/Object;Ljava/lang/Object;)I
const #166 = Asciz	k0;
const #167 = Asciz	k1;
const #168 = Asciz	subsetOf;
const #169 = Asciz	(Lscala/collection/Set;)Z;
const #170 = Asciz	(Lscala/collection/generic/SortedSetTemplate;Lscala/collection/Set;)Z;
const #171 = NameAndType	#168:#170;//  subsetOf:(Lscala/collection/generic/SortedSetTemplate;Lscala/collection/Set;)Z
const #172 = Method	#30.#171;	//  scala/collection/generic/SortedSetTemplate$class.subsetOf:(Lscala/collection/generic/SortedSetTemplate;Lscala/collection/Set;)Z
const #173 = Asciz	that;
const #174 = Asciz	Lscala/collection/Set;;
const #175 = Asciz	(Lscala/collection/generic/SortedSetTemplate;Ljava/lang/Object;Ljava/lang/Object;)Lscala/collection/SortedSet;;
const #176 = NameAndType	#80:#175;//  range:(Lscala/collection/generic/SortedSetTemplate;Ljava/lang/Object;Ljava/lang/Object;)Lscala/collection/SortedSet;
const #177 = Method	#30.#176;	//  scala/collection/generic/SortedSetTemplate$class.range:(Lscala/collection/generic/SortedSetTemplate;Ljava/lang/Object;Ljava/lang/Object;)Lscala/collection/SortedSet;
const #178 = Asciz	(Lscala/collection/generic/SortedSetTemplate;Ljava/lang/Object;)Lscala/collection/SortedSet;;
const #179 = NameAndType	#64:#178;//  until:(Lscala/collection/generic/SortedSetTemplate;Ljava/lang/Object;)Lscala/collection/SortedSet;
const #180 = Method	#30.#179;	//  scala/collection/generic/SortedSetTemplate$class.until:(Lscala/collection/generic/SortedSetTemplate;Ljava/lang/Object;)Lscala/collection/SortedSet;
const #181 = NameAndType	#62:#178;//  from:(Lscala/collection/generic/SortedSetTemplate;Ljava/lang/Object;)Lscala/collection/SortedSet;
const #182 = Method	#30.#181;	//  scala/collection/generic/SortedSetTemplate$class.from:(Lscala/collection/generic/SortedSetTemplate;Ljava/lang/Object;)Lscala/collection/SortedSet;
const #183 = Asciz	lastKey;
const #184 = Asciz	()Ljava/lang/Object;;
const #185 = Asciz	(Lscala/collection/generic/SortedSetTemplate;)Ljava/lang/Object;;
const #186 = NameAndType	#183:#185;//  lastKey:(Lscala/collection/generic/SortedSetTemplate;)Ljava/lang/Object;
const #187 = Method	#30.#186;	//  scala/collection/generic/SortedSetTemplate$class.lastKey:(Lscala/collection/generic/SortedSetTemplate;)Ljava/lang/Object;
const #188 = Asciz	firstKey;
const #189 = NameAndType	#188:#185;//  firstKey:(Lscala/collection/generic/SortedSetTemplate;)Ljava/lang/Object;
const #190 = Method	#30.#189;	//  scala/collection/generic/SortedSetTemplate$class.firstKey:(Lscala/collection/generic/SortedSetTemplate;)Ljava/lang/Object;
const #191 = Asciz	keySet;
const #192 = Asciz	(Lscala/collection/generic/SortedSetTemplate;)Lscala/collection/SortedSet;;
const #193 = NameAndType	#191:#192;//  keySet:(Lscala/collection/generic/SortedSetTemplate;)Lscala/collection/SortedSet;
const #194 = Method	#30.#193;	//  scala/collection/generic/SortedSetTemplate$class.keySet:(Lscala/collection/generic/SortedSetTemplate;)Lscala/collection/SortedSet;
const #195 = Asciz	scala$collection$generic$SortedSetTemplate$$super$subsetOf;
const #196 = Asciz	scala/collection/generic/SetTemplate$class;
const #197 = class	#196;	//  scala/collection/generic/SetTemplate$class
const #198 = Asciz	(Lscala/collection/generic/SetTemplate;Lscala/collection/Set;)Z;
const #199 = NameAndType	#168:#198;//  subsetOf:(Lscala/collection/generic/SetTemplate;Lscala/collection/Set;)Z
const #200 = Method	#197.#199;	//  scala/collection/generic/SetTemplate$class.subsetOf:(Lscala/collection/generic/SetTemplate;Lscala/collection/Set;)Z
const #201 = Asciz	(Lscala/collection/SortedSet;)Lscala/collection/SortedSet;;
const #202 = NameAndType	#65:#201;//  empty:(Lscala/collection/SortedSet;)Lscala/collection/SortedSet;
const #203 = Method	#35.#202;	//  scala/collection/SortedSet$class.empty:(Lscala/collection/SortedSet;)Lscala/collection/SortedSet;
const #204 = Asciz	Lscala/collection/generic/SortedMapTemplate<TA;TB;TThis;>.DefaultKeySet;Lscala/collection/SortedSet<TA;>;Lscala/ScalaObject;;
const #205 = Asciz	Scala;
const #206 = Asciz	InnerClasses;
const #207 = Asciz	scala/collection/generic/MapTemplate;
const #208 = class	#207;	//  scala/collection/generic/MapTemplate
const #209 = Asciz	DefaultKeySet;
const #210 = Asciz	DefaultKeySortedSet;
const #211 = Asciz	scala/ScalaObject;
const #212 = class	#211;	//  scala/ScalaObject

{
public final scala.collection.generic.SortedMapTemplate $outer;

public scala.collection.generic.SortedMapTemplate$DefaultKeySortedSet(scala.collection.generic.SortedMapTemplate);
  Code:
   Stack=2, Locals=2, Args_size=2
   0:	aload_1
   1:	ifnonnull	12
   4:	new	#10; //class java/lang/NullPointerException
   7:	dup
   8:	invokespecial	#13; //Method java/lang/NullPointerException."<init>":()V
   11:	athrow
   12:	aload_0
   13:	aload_1
   14:	putfield	#17; //Field $outer:Lscala/collection/generic/SortedMapTemplate;
   17:	aload_0
   18:	aload_1
   19:	invokespecial	#22; //Method scala/collection/generic/MapTemplate$DefaultKeySet."<init>":(Lscala/collection/generic/MapTemplate;)V
   22:	aload_0
   23:	invokestatic	#28; //Method scala/collection/generic/Sorted$class.$init$:(Lscala/collection/generic/Sorted;)V
   26:	aload_0
   27:	invokestatic	#33; //Method scala/collection/generic/SortedSetTemplate$class.$init$:(Lscala/collection/generic/SortedSetTemplate;)V
   30:	aload_0
   31:	invokestatic	#38; //Method scala/collection/SortedSet$class.$init$:(Lscala/collection/SortedSet;)V
   34:	return
  LineNumberTable: 
   line 36: 0

  LocalVariableTable: 
   Start  Length  Slot  Name   Signature
   0      35      0    this       Lscala/collection/generic/SortedMapTemplate$DefaultKeySortedSet;
   0      35      1    $outer       Lscala/collection/generic/SortedMapTemplate;

  Signature: length = 0x2
   00 2A 

public scala.collection.Set $plus(java.lang.Object);
  Code:
   Stack=2, Locals=2, Args_size=2
   0:	aload_0
   1:	aload_1
   2:	invokevirtual	#48; //Method $plus:(Ljava/lang/Object;)Lscala/collection/SortedSet;
   5:	areturn
  LineNumberTable: 
   line 36: 0

  LocalVariableTable: 
   Start  Length  Slot  Name   Signature
   0      6      0    this       Lscala/collection/generic/SortedMapTemplate$DefaultKeySortedSet;
   0      6      1    elem       Ljava/lang/Object;


public scala.collection.generic.SetTemplate $plus(java.lang.Object);
  Code:
   Stack=2, Locals=2, Args_size=2
   0:	aload_0
   1:	aload_1
   2:	invokevirtual	#48; //Method $plus:(Ljava/lang/Object;)Lscala/collection/SortedSet;
   5:	areturn
  LineNumberTable: 
   line 36: 0

  LocalVariableTable: 
   Start  Length  Slot  Name   Signature
   0      6      0    this       Lscala/collection/generic/SortedMapTemplate$DefaultKeySortedSet;
   0      6      1    elem       Ljava/lang/Object;


public scala.collection.generic.Addable $plus(java.lang.Object);
  Code:
   Stack=2, Locals=2, Args_size=2
   0:	aload_0
   1:	aload_1
   2:	invokevirtual	#48; //Method $plus:(Ljava/lang/Object;)Lscala/collection/SortedSet;
   5:	areturn
  LineNumberTable: 
   line 36: 0

  LocalVariableTable: 
   Start  Length  Slot  Name   Signature
   0      6      0    this       Lscala/collection/generic/SortedMapTemplate$DefaultKeySortedSet;
   0      6      1    elem       Ljava/lang/Object;


public scala.collection.Set $minus(java.lang.Object);
  Code:
   Stack=2, Locals=2, Args_size=2
   0:	aload_0
   1:	aload_1
   2:	invokevirtual	#55; //Method $minus:(Ljava/lang/Object;)Lscala/collection/SortedSet;
   5:	areturn
  LineNumberTable: 
   line 36: 0

  LocalVariableTable: 
   Start  Length  Slot  Name   Signature
   0      6      0    this       Lscala/collection/generic/SortedMapTemplate$DefaultKeySortedSet;
   0      6      1    elem       Ljava/lang/Object;


public scala.collection.generic.SetTemplate $minus(java.lang.Object);
  Code:
   Stack=2, Locals=2, Args_size=2
   0:	aload_0
   1:	aload_1
   2:	invokevirtual	#55; //Method $minus:(Ljava/lang/Object;)Lscala/collection/SortedSet;
   5:	areturn
  LineNumberTable: 
   line 36: 0

  LocalVariableTable: 
   Start  Length  Slot  Name   Signature
   0      6      0    this       Lscala/collection/generic/SortedMapTemplate$DefaultKeySortedSet;
   0      6      1    elem       Ljava/lang/Object;


public scala.collection.generic.Subtractable $minus(java.lang.Object);
  Code:
   Stack=2, Locals=2, Args_size=2
   0:	aload_0
   1:	aload_1
   2:	invokevirtual	#55; //Method $minus:(Ljava/lang/Object;)Lscala/collection/SortedSet;
   5:	areturn
  LineNumberTable: 
   line 36: 0

  LocalVariableTable: 
   Start  Length  Slot  Name   Signature
   0      6      0    this       Lscala/collection/generic/SortedMapTemplate$DefaultKeySortedSet;
   0      6      1    elem       Ljava/lang/Object;


public scala.collection.generic.Sorted rangeImpl(scala.Option, scala.Option);
  Code:
   Stack=3, Locals=3, Args_size=3
   0:	aload_0
   1:	aload_1
   2:	aload_2
   3:	invokevirtual	#61; //Method rangeImpl:(Lscala/Option;Lscala/Option;)Lscala/collection/SortedSet;
   6:	areturn
  LineNumberTable: 
   line 36: 0

  LocalVariableTable: 
   Start  Length  Slot  Name   Signature
   0      7      0    this       Lscala/collection/generic/SortedMapTemplate$DefaultKeySortedSet;
   0      7      1    from       Lscala/Option;
   0      7      2    until       Lscala/Option;


public scala.collection.Set empty();
  Code:
   Stack=1, Locals=1, Args_size=1
   0:	aload_0
   1:	invokeinterface	#71,  1; //InterfaceMethod scala/collection/SortedSet.empty:()Lscala/collection/SortedSet;
   6:	areturn
  LineNumberTable: 
   line 36: 0


public scala.collection.generic.SetTemplate empty();
  Code:
   Stack=1, Locals=1, Args_size=1
   0:	aload_0
   1:	invokeinterface	#71,  1; //InterfaceMethod scala/collection/SortedSet.empty:()Lscala/collection/SortedSet;
   6:	areturn
  LineNumberTable: 
   line 36: 0


public scala.collection.generic.Sorted from(java.lang.Object);
  Code:
   Stack=2, Locals=2, Args_size=2
   0:	aload_0
   1:	aload_1
   2:	invokeinterface	#77,  2; //InterfaceMethod scala/collection/generic/SortedSetTemplate.from:(Ljava/lang/Object;)Lscala/collection/SortedSet;
   7:	areturn
  LineNumberTable: 
   line 36: 0

  LocalVariableTable: 
   Start  Length  Slot  Name   Signature
   0      8      0    this       Lscala/collection/generic/SortedMapTemplate$DefaultKeySortedSet;
   0      8      1    from       Ljava/lang/Object;


public scala.collection.generic.Sorted until(java.lang.Object);
  Code:
   Stack=2, Locals=2, Args_size=2
   0:	aload_0
   1:	aload_1
   2:	invokeinterface	#79,  2; //InterfaceMethod scala/collection/generic/SortedSetTemplate.until:(Ljava/lang/Object;)Lscala/collection/SortedSet;
   7:	areturn
  LineNumberTable: 
   line 36: 0

  LocalVariableTable: 
   Start  Length  Slot  Name   Signature
   0      8      0    this       Lscala/collection/generic/SortedMapTemplate$DefaultKeySortedSet;
   0      8      1    until       Ljava/lang/Object;


public scala.collection.generic.Sorted range(java.lang.Object, java.lang.Object);
  Code:
   Stack=3, Locals=3, Args_size=3
   0:	aload_0
   1:	aload_1
   2:	aload_2
   3:	invokeinterface	#84,  3; //InterfaceMethod scala/collection/generic/SortedSetTemplate.range:(Ljava/lang/Object;Ljava/lang/Object;)Lscala/collection/SortedSet;
   8:	areturn
  LineNumberTable: 
   line 36: 0

  LocalVariableTable: 
   Start  Length  Slot  Name   Signature
   0      9      0    this       Lscala/collection/generic/SortedMapTemplate$DefaultKeySortedSet;
   0      9      1    from       Ljava/lang/Object;
   0      9      2    until       Ljava/lang/Object;


public java.lang.Object apply(java.lang.Object);
  Code:
   Stack=2, Locals=2, Args_size=2
   0:	aload_0
   1:	aload_1
   2:	invokeinterface	#91,  2; //InterfaceMethod scala/collection/generic/SetTemplate.apply:(Ljava/lang/Object;)Z
   7:	invokestatic	#97; //Method scala/runtime/BoxesRunTime.boxToBoolean:(Z)Ljava/lang/Boolean;
   10:	areturn
  LineNumberTable: 
   line 36: 0

  LocalVariableTable: 
   Start  Length  Slot  Name   Signature
   0      11      0    this       Lscala/collection/generic/SortedMapTemplate$DefaultKeySortedSet;
   0      11      1    v1       Ljava/lang/Object;


public scala.collection.generic.TraversableView view(int, int);
  Code:
   Stack=3, Locals=3, Args_size=3
   0:	aload_0
   1:	iload_1
   2:	iload_2
   3:	invokeinterface	#105,  3; //InterfaceMethod scala/collection/generic/IterableTemplate.view:(II)Lscala/collection/generic/IterableView;
   8:	areturn
  LineNumberTable: 
   line 36: 0

  LocalVariableTable: 
   Start  Length  Slot  Name   Signature
   0      9      0    this       Lscala/collection/generic/SortedMapTemplate$DefaultKeySortedSet;
   0      9      1    from       I
   0      9      2    until       I


public scala.collection.generic.Sorted thisCollection();
  Code:
   Stack=1, Locals=1, Args_size=1
   0:	aload_0
   1:	invokeinterface	#113,  1; //InterfaceMethod scala/collection/generic/TraversableTemplate.thisCollection:()Lscala/collection/generic/TraversableTemplate;
   6:	checkcast	#115; //class scala/collection/generic/Sorted
   9:	areturn
  LineNumberTable: 
   line 36: 0


public scala.collection.generic.Subtractable thisCollection();
  Code:
   Stack=1, Locals=1, Args_size=1
   0:	aload_0
   1:	invokeinterface	#113,  1; //InterfaceMethod scala/collection/generic/TraversableTemplate.thisCollection:()Lscala/collection/generic/TraversableTemplate;
   6:	checkcast	#118; //class scala/collection/generic/Subtractable
   9:	areturn
  LineNumberTable: 
   line 36: 0


public scala.collection.generic.Addable thisCollection();
  Code:
   Stack=1, Locals=1, Args_size=1
   0:	aload_0
   1:	invokeinterface	#113,  1; //InterfaceMethod scala/collection/generic/TraversableTemplate.thisCollection:()Lscala/collection/generic/TraversableTemplate;
   6:	checkcast	#121; //class scala/collection/generic/Addable
   9:	areturn
  LineNumberTable: 
   line 36: 0


public scala.collection.generic.SortedMapTemplate scala$collection$generic$SortedMapTemplate$DefaultKeySortedSet$$$outer();
  Code:
   Stack=1, Locals=1, Args_size=1
   0:	aload_0
   1:	getfield	#17; //Field $outer:Lscala/collection/generic/SortedMapTemplate;
   4:	areturn
  LineNumberTable: 
   line 36: 0


public scala.collection.SortedSet rangeImpl(scala.Option, scala.Option);
  Code:
   Stack=3, Locals=4, Args_size=3
   0:	aload_0
   1:	invokevirtual	#125; //Method scala$collection$generic$SortedMapTemplate$DefaultKeySortedSet$$$outer:()Lscala/collection/generic/SortedMapTemplate;
   4:	aload_1
   5:	aload_2
   6:	invokeinterface	#130,  3; //InterfaceMethod scala/collection/generic/SortedMapTemplate.rangeImpl:(Lscala/Option;Lscala/Option;)Lscala/collection/generic/SortedMapTemplate;
   11:	astore_3
   12:	new	#15; //class scala/collection/generic/SortedMapTemplate$DefaultKeySortedSet
   15:	dup
   16:	aload_3
   17:	invokespecial	#132; //Method "<init>":(Lscala/collection/generic/SortedMapTemplate;)V
   20:	areturn
  LineNumberTable: 
   line 43: 0
   line 44: 12

  LocalVariableTable: 
   Start  Length  Slot  Name   Signature
   0      21      0    this       Lscala/collection/generic/SortedMapTemplate$DefaultKeySortedSet;
   0      21      1    from       Lscala/Option;
   0      21      2    until       Lscala/Option;
   12      8      3    map       Lscala/collection/generic/SortedMapTemplate;

  Signature: length = 0x2
   00 FFFFFF86 

public scala.collection.SortedSet $minus(java.lang.Object);
  Code:
   Stack=3, Locals=2, Args_size=2
   0:	new	#136; //class java/lang/UnsupportedOperationException
   3:	dup
   4:	ldc	#138; //String keySet.-
   6:	invokespecial	#141; //Method java/lang/UnsupportedOperationException."<init>":(Ljava/lang/String;)V
   9:	athrow
  LineNumberTable: 
   line 41: 0

  LocalVariableTable: 
   Start  Length  Slot  Name   Signature
   0      10      0    this       Lscala/collection/generic/SortedMapTemplate$DefaultKeySortedSet;
   0      10      1    elem       Ljava/lang/Object;

  Signature: length = 0x2
   00 FFFFFF8E 

public scala.collection.SortedSet $plus(java.lang.Object);
  Code:
   Stack=3, Locals=2, Args_size=2
   0:	new	#136; //class java/lang/UnsupportedOperationException
   3:	dup
   4:	ldc	#144; //String keySet.+
   6:	invokespecial	#141; //Method java/lang/UnsupportedOperationException."<init>":(Ljava/lang/String;)V
   9:	athrow
  LineNumberTable: 
   line 40: 0

  LocalVariableTable: 
   Start  Length  Slot  Name   Signature
   0      10      0    this       Lscala/collection/generic/SortedMapTemplate$DefaultKeySortedSet;
   0      10      1    elem       Ljava/lang/Object;

  Signature: length = 0x2
   00 FFFFFF8E 

public scala.Ordering ordering();
  Code:
   Stack=1, Locals=1, Args_size=1
   0:	aload_0
   1:	invokevirtual	#125; //Method scala$collection$generic$SortedMapTemplate$DefaultKeySortedSet$$$outer:()Lscala/collection/generic/SortedMapTemplate;
   4:	invokeinterface	#148,  1; //InterfaceMethod scala/collection/generic/SortedMapTemplate.ordering:()Lscala/Ordering;
   9:	areturn
  LineNumberTable: 
   line 37: 0

  Signature: length = 0x2
   00 FFFFFF95 

public boolean hasAll(scala.collection.Iterator);
  Code:
   Stack=2, Locals=2, Args_size=2
   0:	aload_0
   1:	aload_1
   2:	invokestatic	#154; //Method scala/collection/generic/Sorted$class.hasAll:(Lscala/collection/generic/Sorted;Lscala/collection/Iterator;)Z
   5:	ireturn
  LineNumberTable: 
   line 36: 0

  LocalVariableTable: 
   Start  Length  Slot  Name   Signature
   0      6      0    this       Lscala/collection/generic/SortedMapTemplate$DefaultKeySortedSet;
   0      6      1    j       Lscala/collection/Iterator;


public scala.collection.generic.Sorted to(java.lang.Object);
  Code:
   Stack=2, Locals=2, Args_size=2
   0:	aload_0
   1:	aload_1
   2:	invokestatic	#160; //Method scala/collection/generic/Sorted$class.to:(Lscala/collection/generic/Sorted;Ljava/lang/Object;)Lscala/collection/generic/Sorted;
   5:	areturn
  LineNumberTable: 
   line 36: 0

  LocalVariableTable: 
   Start  Length  Slot  Name   Signature
   0      6      0    this       Lscala/collection/generic/SortedMapTemplate$DefaultKeySortedSet;
   0      6      1    to       Ljava/lang/Object;


public int compare(java.lang.Object, java.lang.Object);
  Code:
   Stack=3, Locals=3, Args_size=3
   0:	aload_0
   1:	aload_1
   2:	aload_2
   3:	invokestatic	#165; //Method scala/collection/generic/Sorted$class.compare:(Lscala/collection/generic/Sorted;Ljava/lang/Object;Ljava/lang/Object;)I
   6:	ireturn
  LineNumberTable: 
   line 36: 0

  LocalVariableTable: 
   Start  Length  Slot  Name   Signature
   0      7      0    this       Lscala/collection/generic/SortedMapTemplate$DefaultKeySortedSet;
   0      7      1    k0       Ljava/lang/Object;
   0      7      2    k1       Ljava/lang/Object;


public boolean subsetOf(scala.collection.Set);
  Code:
   Stack=2, Locals=2, Args_size=2
   0:	aload_0
   1:	aload_1
   2:	invokestatic	#172; //Method scala/collection/generic/SortedSetTemplate$class.subsetOf:(Lscala/collection/generic/SortedSetTemplate;Lscala/collection/Set;)Z
   5:	ireturn
  LineNumberTable: 
   line 36: 0

  LocalVariableTable: 
   Start  Length  Slot  Name   Signature
   0      6      0    this       Lscala/collection/generic/SortedMapTemplate$DefaultKeySortedSet;
   0      6      1    that       Lscala/collection/Set;


public scala.collection.SortedSet range(java.lang.Object, java.lang.Object);
  Code:
   Stack=3, Locals=3, Args_size=3
   0:	aload_0
   1:	aload_1
   2:	aload_2
   3:	invokestatic	#177; //Method scala/collection/generic/SortedSetTemplate$class.range:(Lscala/collection/generic/SortedSetTemplate;Ljava/lang/Object;Ljava/lang/Object;)Lscala/collection/SortedSet;
   6:	areturn
  LineNumberTable: 
   line 36: 0

  LocalVariableTable: 
   Start  Length  Slot  Name   Signature
   0      7      0    this       Lscala/collection/generic/SortedMapTemplate$DefaultKeySortedSet;
   0      7      1    from       Ljava/lang/Object;
   0      7      2    until       Ljava/lang/Object;


public scala.collection.SortedSet until(java.lang.Object);
  Code:
   Stack=2, Locals=2, Args_size=2
   0:	aload_0
   1:	aload_1
   2:	invokestatic	#180; //Method scala/collection/generic/SortedSetTemplate$class.until:(Lscala/collection/generic/SortedSetTemplate;Ljava/lang/Object;)Lscala/collection/SortedSet;
   5:	areturn
  LineNumberTable: 
   line 36: 0

  LocalVariableTable: 
   Start  Length  Slot  Name   Signature
   0      6      0    this       Lscala/collection/generic/SortedMapTemplate$DefaultKeySortedSet;
   0      6      1    until       Ljava/lang/Object;


public scala.collection.SortedSet from(java.lang.Object);
  Code:
   Stack=2, Locals=2, Args_size=2
   0:	aload_0
   1:	aload_1
   2:	invokestatic	#182; //Method scala/collection/generic/SortedSetTemplate$class.from:(Lscala/collection/generic/SortedSetTemplate;Ljava/lang/Object;)Lscala/collection/SortedSet;
   5:	areturn
  LineNumberTable: 
   line 36: 0

  LocalVariableTable: 
   Start  Length  Slot  Name   Signature
   0      6      0    this       Lscala/collection/generic/SortedMapTemplate$DefaultKeySortedSet;
   0      6      1    from       Ljava/lang/Object;


public java.lang.Object lastKey();
  Code:
   Stack=1, Locals=1, Args_size=1
   0:	aload_0
   1:	invokestatic	#187; //Method scala/collection/generic/SortedSetTemplate$class.lastKey:(Lscala/collection/generic/SortedSetTemplate;)Ljava/lang/Object;
   4:	areturn
  LineNumberTable: 
   line 36: 0


public java.lang.Object firstKey();
  Code:
   Stack=1, Locals=1, Args_size=1
   0:	aload_0
   1:	invokestatic	#190; //Method scala/collection/generic/SortedSetTemplate$class.firstKey:(Lscala/collection/generic/SortedSetTemplate;)Ljava/lang/Object;
   4:	areturn
  LineNumberTable: 
   line 36: 0


public scala.collection.SortedSet keySet();
  Code:
   Stack=1, Locals=1, Args_size=1
   0:	aload_0
   1:	invokestatic	#194; //Method scala/collection/generic/SortedSetTemplate$class.keySet:(Lscala/collection/generic/SortedSetTemplate;)Lscala/collection/SortedSet;
   4:	areturn
  LineNumberTable: 
   line 36: 0


public final boolean scala$collection$generic$SortedSetTemplate$$super$subsetOf(scala.collection.Set);
  Code:
   Stack=2, Locals=2, Args_size=2
   0:	aload_0
   1:	aload_1
   2:	invokestatic	#200; //Method scala/collection/generic/SetTemplate$class.subsetOf:(Lscala/collection/generic/SetTemplate;Lscala/collection/Set;)Z
   5:	ireturn
  LineNumberTable: 
   line 36: 0

  LocalVariableTable: 
   Start  Length  Slot  Name   Signature
   0      6      0    this       Lscala/collection/generic/SortedMapTemplate$DefaultKeySortedSet;
   0      6      1    that       Lscala/collection/Set;


public scala.collection.SortedSet empty();
  Code:
   Stack=1, Locals=1, Args_size=1
   0:	aload_0
   1:	invokestatic	#203; //Method scala/collection/SortedSet$class.empty:(Lscala/collection/SortedSet;)Lscala/collection/SortedSet;
   4:	areturn
  LineNumberTable: 
   line 36: 0


}

