Compiled from "Sorted.scala"
public abstract class scala.collection.generic.Sorted$class extends java.lang.Object
  SourceFile: "Sorted.scala"
  Scala: length = 0x
   
  minor version: 0
  major version: 49
  Constant pool:
const #1 = Asciz	SourceFile;
const #2 = Asciz	Sorted.scala;
const #3 = Asciz	$init$;
const #4 = Asciz	(Lscala/collection/generic/Sorted;)V;
const #5 = Asciz	Code;
const #6 = Asciz	LineNumberTable;
const #7 = Asciz	$this;
const #8 = Asciz	Lscala/collection/generic/Sorted;;
const #9 = Asciz	LocalVariableTable;
const #10 = Asciz	hasAll;
const #11 = Asciz	(Lscala/collection/generic/Sorted;Lscala/collection/Iterator;)Z;
const #12 = Asciz	scala/collection/generic/Sorted;
const #13 = class	#12;	//  scala/collection/generic/Sorted
const #14 = Asciz	keySet;
const #15 = Asciz	()Lscala/collection/SortedSet;;
const #16 = NameAndType	#14:#15;//  keySet:()Lscala/collection/SortedSet;
const #17 = InterfaceMethod	#13.#16;	//  scala/collection/generic/Sorted.keySet:()Lscala/collection/SortedSet;
const #18 = Asciz	scala/collection/IterableLike;
const #19 = class	#18;	//  scala/collection/IterableLike
const #20 = Asciz	iterator;
const #21 = Asciz	()Lscala/collection/Iterator;;
const #22 = NameAndType	#20:#21;//  iterator:()Lscala/collection/Iterator;
const #23 = InterfaceMethod	#19.#22;	//  scala/collection/IterableLike.iterator:()Lscala/collection/Iterator;
const #24 = Asciz	scala/collection/Iterator;
const #25 = class	#24;	//  scala/collection/Iterator
const #26 = Asciz	hasNext;
const #27 = Asciz	()Z;
const #28 = NameAndType	#26:#27;//  hasNext:()Z
const #29 = InterfaceMethod	#25.#28;	//  scala/collection/Iterator.hasNext:()Z
const #30 = Asciz	next;
const #31 = Asciz	()Ljava/lang/Object;;
const #32 = NameAndType	#30:#31;//  next:()Ljava/lang/Object;
const #33 = InterfaceMethod	#25.#32;	//  scala/collection/Iterator.next:()Ljava/lang/Object;
const #34 = Asciz	compare;
const #35 = Asciz	(Ljava/lang/Object;Ljava/lang/Object;)I;
const #36 = NameAndType	#34:#35;//  compare:(Ljava/lang/Object;Ljava/lang/Object;)I
const #37 = InterfaceMethod	#13.#36;	//  scala/collection/generic/Sorted.compare:(Ljava/lang/Object;Ljava/lang/Object;)I
const #38 = Asciz	j;
const #39 = Asciz	Lscala/collection/Iterator;;
const #40 = Asciz	i;
const #41 = Asciz	in;
const #42 = Asciz	Ljava/lang/Object;;
const #43 = Asciz	jn;
const #44 = Asciz	n;
const #45 = Asciz	I;
const #46 = Asciz	to;
const #47 = Asciz	(Lscala/collection/generic/Sorted;Ljava/lang/Object;)Lscala/collection/generic/Sorted;;
const #48 = Asciz	scala/collection/SortedSetLike;
const #49 = class	#48;	//  scala/collection/SortedSetLike
const #50 = Asciz	from;
const #51 = Asciz	(Ljava/lang/Object;)Lscala/collection/SortedSet;;
const #52 = NameAndType	#50:#51;//  from:(Ljava/lang/Object;)Lscala/collection/SortedSet;
const #53 = InterfaceMethod	#49.#52;	//  scala/collection/SortedSetLike.from:(Ljava/lang/Object;)Lscala/collection/SortedSet;
const #54 = Asciz	java/lang/Number;
const #55 = class	#54;	//  java/lang/Number
const #56 = Asciz	java/lang/Character;
const #57 = class	#56;	//  java/lang/Character
const #58 = Asciz	scala/runtime/BoxesRunTime;
const #59 = class	#58;	//  scala/runtime/BoxesRunTime
const #60 = Asciz	equals2;
const #61 = Asciz	(Ljava/lang/Object;Ljava/lang/Object;)Z;
const #62 = NameAndType	#60:#61;//  equals2:(Ljava/lang/Object;Ljava/lang/Object;)Z
const #63 = Method	#59.#62;	//  scala/runtime/BoxesRunTime.equals2:(Ljava/lang/Object;Ljava/lang/Object;)Z
const #64 = Asciz	java/lang/Object;
const #65 = class	#64;	//  java/lang/Object
const #66 = Asciz	equals;
const #67 = Asciz	(Ljava/lang/Object;)Z;
const #68 = NameAndType	#66:#67;//  equals:(Ljava/lang/Object;)Z
const #69 = Method	#65.#68;	//  java/lang/Object.equals:(Ljava/lang/Object;)Z
const #70 = Asciz	until;
const #71 = Asciz	(Ljava/lang/Object;)Lscala/collection/generic/Sorted;;
const #72 = NameAndType	#70:#71;//  until:(Ljava/lang/Object;)Lscala/collection/generic/Sorted;
const #73 = InterfaceMethod	#13.#72;	//  scala/collection/generic/Sorted.until:(Ljava/lang/Object;)Lscala/collection/generic/Sorted;
const #74 = Asciz	repr;
const #75 = Asciz	()Lscala/collection/generic/Sorted;;
const #76 = NameAndType	#74:#75;//  repr:()Lscala/collection/generic/Sorted;
const #77 = InterfaceMethod	#13.#76;	//  scala/collection/generic/Sorted.repr:()Lscala/collection/generic/Sorted;
const #78 = Asciz	range;
const #79 = Asciz	(Lscala/collection/generic/Sorted;Ljava/lang/Object;Ljava/lang/Object;)Lscala/collection/generic/Sorted;;
const #80 = Asciz	scala/Some;
const #81 = class	#80;	//  scala/Some
const #82 = Asciz	<init>;
const #83 = Asciz	(Ljava/lang/Object;)V;
const #84 = NameAndType	#82:#83;//  "<init>":(Ljava/lang/Object;)V
const #85 = Method	#81.#84;	//  scala/Some."<init>":(Ljava/lang/Object;)V
const #86 = Asciz	rangeImpl;
const #87 = Asciz	(Lscala/Option;Lscala/Option;)Lscala/collection/generic/Sorted;;
const #88 = NameAndType	#86:#87;//  rangeImpl:(Lscala/Option;Lscala/Option;)Lscala/collection/generic/Sorted;
const #89 = InterfaceMethod	#13.#88;	//  scala/collection/generic/Sorted.rangeImpl:(Lscala/Option;Lscala/Option;)Lscala/collection/generic/Sorted;
const #90 = Asciz	scala/None$;
const #91 = class	#90;	//  scala/None$
const #92 = Asciz	MODULE$;
const #93 = Asciz	Lscala/None$;;
const #94 = NameAndType	#92:#93;//  MODULE$:Lscala/None$;
const #95 = Field	#91.#94;	//  scala/None$.MODULE$:Lscala/None$;
const #96 = Asciz	(Lscala/collection/generic/Sorted;Ljava/lang/Object;Ljava/lang/Object;)I;
const #97 = Asciz	ordering;
const #98 = Asciz	()Lscala/math/Ordering;;
const #99 = NameAndType	#97:#98;//  ordering:()Lscala/math/Ordering;
const #100 = InterfaceMethod	#13.#99;	//  scala/collection/generic/Sorted.ordering:()Lscala/math/Ordering;
const #101 = Asciz	scala/math/Ordering;
const #102 = class	#101;	//  scala/math/Ordering
const #103 = InterfaceMethod	#102.#36;	//  scala/math/Ordering.compare:(Ljava/lang/Object;Ljava/lang/Object;)I
const #104 = Asciz	k0;
const #105 = Asciz	k1;
const #106 = Asciz	Scala;
const #107 = Asciz	scala/collection/generic/Sorted$class;
const #108 = class	#107;	//  scala/collection/generic/Sorted$class

{
public static void $init$(scala.collection.generic.Sorted);
  Code:
   Stack=0, Locals=1, Args_size=1
   0:	return
  LineNumberTable: 
   line 19: 0

  LocalVariableTable: 
   Start  Length  Slot  Name   Signature
   0      1      0    $this       Lscala/collection/generic/Sorted;


public static boolean hasAll(scala.collection.generic.Sorted, scala.collection.Iterator);
  Code:
   Stack=3, Locals=6, Args_size=2
   0:	aload_0
   1:	invokeinterface	#17,  1; //InterfaceMethod scala/collection/generic/Sorted.keySet:()Lscala/collection/SortedSet;
   6:	invokeinterface	#23,  1; //InterfaceMethod scala/collection/IterableLike.iterator:()Lscala/collection/Iterator;
   11:	astore_2
   12:	aload_2
   13:	invokeinterface	#29,  1; //InterfaceMethod scala/collection/Iterator.hasNext:()Z
   18:	ifeq	101
   21:	aload_2
   22:	invokeinterface	#33,  1; //InterfaceMethod scala/collection/Iterator.next:()Ljava/lang/Object;
   27:	astore_3
   28:	aload_1
   29:	invokeinterface	#29,  1; //InterfaceMethod scala/collection/Iterator.hasNext:()Z
   34:	ifeq	99
   37:	aload_1
   38:	invokeinterface	#33,  1; //InterfaceMethod scala/collection/Iterator.next:()Ljava/lang/Object;
   43:	astore	4
   45:	aload_0
   46:	aload	4
   48:	aload_3
   49:	invokeinterface	#37,  3; //InterfaceMethod scala/collection/generic/Sorted.compare:(Ljava/lang/Object;Ljava/lang/Object;)I
   54:	istore	5
   56:	iload	5
   58:	iconst_0
   59:	if_icmpne	66
   62:	iconst_0
   63:	goto	84
   66:	iload	5
   68:	iconst_0
   69:	if_icmpge	74
   72:	iconst_0
   73:	ireturn
   74:	aload_2
   75:	invokeinterface	#29,  1; //InterfaceMethod scala/collection/Iterator.hasNext:()Z
   80:	ifeq	97
   83:	iconst_1
   84:	ifeq	28
   87:	aload_2
   88:	invokeinterface	#33,  1; //InterfaceMethod scala/collection/Iterator.next:()Ljava/lang/Object;
   93:	astore_3
   94:	goto	45
   97:	iconst_0
   98:	ireturn
   99:	iconst_1
   100:	ireturn
   101:	aload_1
   102:	invokeinterface	#29,  1; //InterfaceMethod scala/collection/Iterator.hasNext:()Z
   107:	ifeq	114
   110:	iconst_0
   111:	goto	115
   114:	iconst_1
   115:	ireturn
  LineNumberTable: 
   line 87: 0
   line 88: 12
   line 89: 21
   line 90: 28
   line 91: 37
   line 93: 45
   line 94: 56
   line 95: 66
   line 96: 74
   line 97: 83
   line 92: 84
   line 98: 87
   line 96: 97
   line 100: 99
   line 88: 101

  LocalVariableTable: 
   Start  Length  Slot  Name   Signature
   0      116      0    $this       Lscala/collection/generic/Sorted;
   0      116      1    j       Lscala/collection/Iterator;
   12      88      2    i       Lscala/collection/Iterator;
   101      15      2    i       Lscala/collection/Iterator;
   28      72      3    in       Ljava/lang/Object;
   45      54      4    jn       Ljava/lang/Object;
   56      31      5    n       I
   97      2      5    n       I


public static scala.collection.generic.Sorted to(scala.collection.generic.Sorted, java.lang.Object);
  Code:
   Stack=2, Locals=4, Args_size=2
   0:	aload_0
   1:	invokeinterface	#17,  1; //InterfaceMethod scala/collection/generic/Sorted.keySet:()Lscala/collection/SortedSet;
   6:	aload_1
   7:	invokeinterface	#53,  2; //InterfaceMethod scala/collection/SortedSetLike.from:(Ljava/lang/Object;)Lscala/collection/SortedSet;
   12:	invokeinterface	#23,  1; //InterfaceMethod scala/collection/IterableLike.iterator:()Lscala/collection/Iterator;
   17:	astore_2
   18:	aload_2
   19:	invokeinterface	#29,  1; //InterfaceMethod scala/collection/Iterator.hasNext:()Z
   24:	ifeq	118
   27:	aload_2
   28:	invokeinterface	#33,  1; //InterfaceMethod scala/collection/Iterator.next:()Ljava/lang/Object;
   33:	astore_3
   34:	aload_3
   35:	aload_1
   36:	if_acmpne	43
   39:	iconst_1
   40:	goto	78
   43:	aload_3
   44:	ifnonnull	51
   47:	iconst_0
   48:	goto	78
   51:	aload_3
   52:	instanceof	#55; //class java/lang/Number
   55:	ifne	65
   58:	aload_3
   59:	instanceof	#57; //class java/lang/Character
   62:	ifeq	73
   65:	aload_3
   66:	aload_1
   67:	invokestatic	#63; //Method scala/runtime/BoxesRunTime.equals2:(Ljava/lang/Object;Ljava/lang/Object;)Z
   70:	goto	78
   73:	aload_3
   74:	aload_1
   75:	invokevirtual	#69; //Method java/lang/Object.equals:(Ljava/lang/Object;)Z
   78:	ifeq	110
   81:	aload_2
   82:	invokeinterface	#29,  1; //InterfaceMethod scala/collection/Iterator.hasNext:()Z
   87:	ifeq	103
   90:	aload_0
   91:	aload_2
   92:	invokeinterface	#33,  1; //InterfaceMethod scala/collection/Iterator.next:()Ljava/lang/Object;
   97:	invokeinterface	#73,  2; //InterfaceMethod scala/collection/generic/Sorted.until:(Ljava/lang/Object;)Lscala/collection/generic/Sorted;
   102:	areturn
   103:	aload_0
   104:	invokeinterface	#77,  1; //InterfaceMethod scala/collection/generic/Sorted.repr:()Lscala/collection/generic/Sorted;
   109:	areturn
   110:	aload_0
   111:	aload_3
   112:	invokeinterface	#73,  2; //InterfaceMethod scala/collection/generic/Sorted.until:(Ljava/lang/Object;)Lscala/collection/generic/Sorted;
   117:	areturn
   118:	aload_0
   119:	invokeinterface	#77,  1; //InterfaceMethod scala/collection/generic/Sorted.repr:()Lscala/collection/generic/Sorted;
   124:	areturn
  LineNumberTable: 
   line 77: 0
   line 78: 18
   line 79: 27
   line 80: 34
   line 81: 81
   line 82: 90
   line 81: 103
   line 83: 110
   line 78: 118

  LocalVariableTable: 
   Start  Length  Slot  Name   Signature
   0      125      0    $this       Lscala/collection/generic/Sorted;
   0      125      1    to       Ljava/lang/Object;
   18      107      2    i       Lscala/collection/Iterator;
   34      84      3    next       Ljava/lang/Object;


public static scala.collection.generic.Sorted range(scala.collection.generic.Sorted, java.lang.Object, java.lang.Object);
  Code:
   Stack=5, Locals=3, Args_size=3
   0:	aload_0
   1:	new	#81; //class scala/Some
   4:	dup
   5:	aload_1
   6:	invokespecial	#85; //Method scala/Some."<init>":(Ljava/lang/Object;)V
   9:	new	#81; //class scala/Some
   12:	dup
   13:	aload_2
   14:	invokespecial	#85; //Method scala/Some."<init>":(Ljava/lang/Object;)V
   17:	invokeinterface	#89,  3; //InterfaceMethod scala/collection/generic/Sorted.rangeImpl:(Lscala/Option;Lscala/Option;)Lscala/collection/generic/Sorted;
   22:	areturn
  LineNumberTable: 
   line 69: 0

  LocalVariableTable: 
   Start  Length  Slot  Name   Signature
   0      23      0    $this       Lscala/collection/generic/Sorted;
   0      23      1    from       Ljava/lang/Object;
   0      23      2    until       Ljava/lang/Object;


public static scala.collection.generic.Sorted until(scala.collection.generic.Sorted, java.lang.Object);
  Code:
   Stack=5, Locals=2, Args_size=2
   0:	aload_0
   1:	getstatic	#95; //Field scala/None$.MODULE$:Lscala/None$;
   4:	new	#81; //class scala/Some
   7:	dup
   8:	aload_1
   9:	invokespecial	#85; //Method scala/Some."<init>":(Ljava/lang/Object;)V
   12:	invokeinterface	#89,  3; //InterfaceMethod scala/collection/generic/Sorted.rangeImpl:(Lscala/Option;Lscala/Option;)Lscala/collection/generic/Sorted;
   17:	areturn
  LineNumberTable: 
   line 60: 0

  LocalVariableTable: 
   Start  Length  Slot  Name   Signature
   0      18      0    $this       Lscala/collection/generic/Sorted;
   0      18      1    until       Ljava/lang/Object;


public static scala.collection.generic.Sorted from(scala.collection.generic.Sorted, java.lang.Object);
  Code:
   Stack=4, Locals=2, Args_size=2
   0:	aload_0
   1:	new	#81; //class scala/Some
   4:	dup
   5:	aload_1
   6:	invokespecial	#85; //Method scala/Some."<init>":(Ljava/lang/Object;)V
   9:	getstatic	#95; //Field scala/None$.MODULE$:Lscala/None$;
   12:	invokeinterface	#89,  3; //InterfaceMethod scala/collection/generic/Sorted.rangeImpl:(Lscala/Option;Lscala/Option;)Lscala/collection/generic/Sorted;
   17:	areturn
  LineNumberTable: 
   line 54: 0

  LocalVariableTable: 
   Start  Length  Slot  Name   Signature
   0      18      0    $this       Lscala/collection/generic/Sorted;
   0      18      1    from       Ljava/lang/Object;


public static int compare(scala.collection.generic.Sorted, java.lang.Object, java.lang.Object);
  Code:
   Stack=3, Locals=3, Args_size=3
   0:	aload_0
   1:	invokeinterface	#100,  1; //InterfaceMethod scala/collection/generic/Sorted.ordering:()Lscala/math/Ordering;
   6:	aload_1
   7:	aload_2
   8:	invokeinterface	#103,  3; //InterfaceMethod scala/math/Ordering.compare:(Ljava/lang/Object;Ljava/lang/Object;)I
   13:	ireturn
  LineNumberTable: 
   line 36: 0

  LocalVariableTable: 
   Start  Length  Slot  Name   Signature
   0      14      0    $this       Lscala/collection/generic/Sorted;
   0      14      1    k0       Ljava/lang/Object;
   0      14      2    k1       Ljava/lang/Object;


}

