Compiled from "Subtractable.scala"
public abstract class scala.collection.generic.Subtractable$class extends java.lang.Object
  SourceFile: "Subtractable.scala"
  Scala: length = 0x
   
  InnerClass: 
   public final #54= #19 of #13; //$anonfun$$minus$minus$2=class scala/collection/generic/Subtractable$$anonfun$$minus$minus$2 of class scala/collection/generic/Subtractable
   public final #55= #33 of #13; //$anonfun$$minus$minus$1=class scala/collection/generic/Subtractable$$anonfun$$minus$minus$1 of class scala/collection/generic/Subtractable
  minor version: 0
  major version: 49
  Constant pool:
const #1 = Asciz	SourceFile;
const #2 = Asciz	Subtractable.scala;
const #3 = Asciz	$init$;
const #4 = Asciz	(Lscala/collection/generic/Subtractable;)V;
const #5 = Asciz	Code;
const #6 = Asciz	LineNumberTable;
const #7 = Asciz	$this;
const #8 = Asciz	Lscala/collection/generic/Subtractable;;
const #9 = Asciz	LocalVariableTable;
const #10 = Asciz	$minus$minus;
const #11 = Asciz	(Lscala/collection/generic/Subtractable;Lscala/collection/Iterator;)Lscala/collection/generic/Subtractable;;
const #12 = Asciz	scala/collection/generic/Subtractable;
const #13 = class	#12;	//  scala/collection/generic/Subtractable
const #14 = Asciz	thisCollection;
const #15 = Asciz	()Lscala/collection/generic/Subtractable;;
const #16 = NameAndType	#14:#15;//  thisCollection:()Lscala/collection/generic/Subtractable;
const #17 = InterfaceMethod	#13.#16;	//  scala/collection/generic/Subtractable.thisCollection:()Lscala/collection/generic/Subtractable;
const #18 = Asciz	scala/collection/generic/Subtractable$$anonfun$$minus$minus$2;
const #19 = class	#18;	//  scala/collection/generic/Subtractable$$anonfun$$minus$minus$2
const #20 = Asciz	<init>;
const #21 = NameAndType	#20:#4;//  "<init>":(Lscala/collection/generic/Subtractable;)V
const #22 = Method	#19.#21;	//  scala/collection/generic/Subtractable$$anonfun$$minus$minus$2."<init>":(Lscala/collection/generic/Subtractable;)V
const #23 = Asciz	scala/collection/Iterator;
const #24 = class	#23;	//  scala/collection/Iterator
const #25 = Asciz	$div$colon;
const #26 = Asciz	(Ljava/lang/Object;Lscala/Function2;)Ljava/lang/Object;;
const #27 = NameAndType	#25:#26;//  $div$colon:(Ljava/lang/Object;Lscala/Function2;)Ljava/lang/Object;
const #28 = InterfaceMethod	#24.#27;	//  scala/collection/Iterator.$div$colon:(Ljava/lang/Object;Lscala/Function2;)Ljava/lang/Object;
const #29 = Asciz	iter;
const #30 = Asciz	Lscala/collection/Iterator;;
const #31 = Asciz	(Lscala/collection/generic/Subtractable;Lscala/collection/Traversable;)Lscala/collection/generic/Subtractable;;
const #32 = Asciz	scala/collection/generic/Subtractable$$anonfun$$minus$minus$1;
const #33 = class	#32;	//  scala/collection/generic/Subtractable$$anonfun$$minus$minus$1
const #34 = Method	#33.#21;	//  scala/collection/generic/Subtractable$$anonfun$$minus$minus$1."<init>":(Lscala/collection/generic/Subtractable;)V
const #35 = Asciz	scala/collection/generic/TraversableTemplate;
const #36 = class	#35;	//  scala/collection/generic/TraversableTemplate
const #37 = InterfaceMethod	#36.#27;	//  scala/collection/generic/TraversableTemplate.$div$colon:(Ljava/lang/Object;Lscala/Function2;)Ljava/lang/Object;
const #38 = Asciz	elems;
const #39 = Asciz	Lscala/collection/Traversable;;
const #40 = Asciz	$minus;
const #41 = Asciz	(Lscala/collection/generic/Subtractable;Ljava/lang/Object;Ljava/lang/Object;Lscala/collection/Sequence;)Lscala/collection/generic/Subtractable;;
const #42 = Asciz	(Ljava/lang/Object;)Lscala/collection/generic/Subtractable;;
const #43 = NameAndType	#40:#42;//  $minus:(Ljava/lang/Object;)Lscala/collection/generic/Subtractable;
const #44 = InterfaceMethod	#13.#43;	//  scala/collection/generic/Subtractable.$minus:(Ljava/lang/Object;)Lscala/collection/generic/Subtractable;
const #45 = Asciz	(Lscala/collection/Traversable;)Lscala/collection/generic/Subtractable;;
const #46 = NameAndType	#10:#45;//  $minus$minus:(Lscala/collection/Traversable;)Lscala/collection/generic/Subtractable;
const #47 = InterfaceMethod	#13.#46;	//  scala/collection/generic/Subtractable.$minus$minus:(Lscala/collection/Traversable;)Lscala/collection/generic/Subtractable;
const #48 = Asciz	elem1;
const #49 = Asciz	Ljava/lang/Object;;
const #50 = Asciz	elem2;
const #51 = Asciz	Lscala/collection/Sequence;;
const #52 = Asciz	Scala;
const #53 = Asciz	InnerClasses;
const #54 = Asciz	$anonfun$$minus$minus$2;
const #55 = Asciz	$anonfun$$minus$minus$1;
const #56 = Asciz	scala/collection/generic/Subtractable$class;
const #57 = class	#56;	//  scala/collection/generic/Subtractable$class
const #58 = Asciz	java/lang/Object;
const #59 = class	#58;	//  java/lang/Object

{
public static void $init$(scala.collection.generic.Subtractable);
  Code:
   Stack=0, Locals=1, Args_size=1
   0:	return
  LineNumberTable: 
   line 20: 0

  LocalVariableTable: 
   Start  Length  Slot  Name   Signature
   0      1      0    $this       Lscala/collection/generic/Subtractable;


public static scala.collection.generic.Subtractable $minus$minus(scala.collection.generic.Subtractable, scala.collection.Iterator);
  Code:
   Stack=5, Locals=3, Args_size=2
   0:	aload_0
   1:	invokeinterface	#17,  1; //InterfaceMethod scala/collection/generic/Subtractable.thisCollection:()Lscala/collection/generic/Subtractable;
   6:	astore_2
   7:	aload_1
   8:	aload_2
   9:	new	#19; //class scala/collection/generic/Subtractable$$anonfun$$minus$minus$2
   12:	dup
   13:	aload_0
   14:	invokespecial	#22; //Method scala/collection/generic/Subtractable$$anonfun$$minus$minus$2."<init>":(Lscala/collection/generic/Subtractable;)V
   17:	invokeinterface	#28,  3; //InterfaceMethod scala/collection/Iterator.$div$colon:(Ljava/lang/Object;Lscala/Function2;)Ljava/lang/Object;
   22:	checkcast	#13; //class scala/collection/generic/Subtractable
   25:	areturn
  LineNumberTable: 
   line 54: 0

  LocalVariableTable: 
   Start  Length  Slot  Name   Signature
   0      26      0    $this       Lscala/collection/generic/Subtractable;
   0      26      1    iter       Lscala/collection/Iterator;


public static scala.collection.generic.Subtractable $minus$minus(scala.collection.generic.Subtractable, scala.collection.Traversable);
  Code:
   Stack=5, Locals=3, Args_size=2
   0:	aload_0
   1:	invokeinterface	#17,  1; //InterfaceMethod scala/collection/generic/Subtractable.thisCollection:()Lscala/collection/generic/Subtractable;
   6:	astore_2
   7:	aload_1
   8:	aload_2
   9:	new	#33; //class scala/collection/generic/Subtractable$$anonfun$$minus$minus$1
   12:	dup
   13:	aload_0
   14:	invokespecial	#34; //Method scala/collection/generic/Subtractable$$anonfun$$minus$minus$1."<init>":(Lscala/collection/generic/Subtractable;)V
   17:	invokeinterface	#37,  3; //InterfaceMethod scala/collection/generic/TraversableTemplate.$div$colon:(Ljava/lang/Object;Lscala/Function2;)Ljava/lang/Object;
   22:	checkcast	#13; //class scala/collection/generic/Subtractable
   25:	areturn
  LineNumberTable: 
   line 46: 0

  LocalVariableTable: 
   Start  Length  Slot  Name   Signature
   0      26      0    $this       Lscala/collection/generic/Subtractable;
   0      26      1    elems       Lscala/collection/Traversable;


public static scala.collection.generic.Subtractable $minus(scala.collection.generic.Subtractable, java.lang.Object, java.lang.Object, scala.collection.Sequence);
  Code:
   Stack=2, Locals=4, Args_size=4
   0:	aload_0
   1:	aload_1
   2:	invokeinterface	#44,  2; //InterfaceMethod scala/collection/generic/Subtractable.$minus:(Ljava/lang/Object;)Lscala/collection/generic/Subtractable;
   7:	aload_2
   8:	invokeinterface	#44,  2; //InterfaceMethod scala/collection/generic/Subtractable.$minus:(Ljava/lang/Object;)Lscala/collection/generic/Subtractable;
   13:	aload_3
   14:	invokeinterface	#47,  2; //InterfaceMethod scala/collection/generic/Subtractable.$minus$minus:(Lscala/collection/Traversable;)Lscala/collection/generic/Subtractable;
   19:	areturn
  LineNumberTable: 
   line 39: 0

  LocalVariableTable: 
   Start  Length  Slot  Name   Signature
   0      20      0    $this       Lscala/collection/generic/Subtractable;
   0      20      1    elem1       Ljava/lang/Object;
   0      20      2    elem2       Ljava/lang/Object;
   0      20      3    elems       Lscala/collection/Sequence;


}

