Compiled from "TraversableFactory.scala"
public final class scala.collection.generic.TraversableFactory$$anonfun$concat$1 extends java.lang.Object implements scala.Function1,scala.ScalaObject,java.io.Serializable
  SourceFile: "TraversableFactory.scala"
  Scala: length = 0x
   
  InnerClass: 
   public final $anonfun$concat$1=class scala/collection/generic/TraversableFactory$$anonfun$concat$1 of class scala/collection/generic/TraversableFactory
  minor version: 0
  major version: 49
  Constant pool:
Asciz	SourceFile;
Asciz	TraversableFactory.scala;
Asciz	<clinit>;
Asciz	()V;
Asciz	Code;
Asciz	serialVersionUID;
Asciz	J;
Asciz	scala/collection/generic/TraversableFactory$$anonfun$concat$1;
class	scala/collection/generic/TraversableFactory$$anonfun$concat$1
NameAndType	serialVersionUID:J
Field	scala/collection/generic/TraversableFactory$$anonfun$concat$1.serialVersionUID:J
Asciz	b$1;
Asciz	Lscala/collection/mutable/Builder;;
Asciz	<init>;
Asciz	(Lscala/collection/generic/TraversableFactory;Lscala/collection/mutable/Builder;)V;
Asciz	LineNumberTable;
NameAndType	b$1:Lscala/collection/mutable/Builder;
Field	scala/collection/generic/TraversableFactory$$anonfun$concat$1.b$1:Lscala/collection/mutable/Builder;
Asciz	java/lang/Object;
class	java/lang/Object
NameAndType	"<init>":()V
Method	java/lang/Object."<init>":()V
Asciz	scala/Function1$class;
class	scala/Function1$class
Asciz	$init$;
Asciz	(Lscala/Function1;)V;
NameAndType	$init$:(Lscala/Function1;)V
Method	scala/Function1$class.$init$:(Lscala/Function1;)V
Asciz	this;
Asciz	Lscala/collection/generic/TraversableFactory$$anonfun$concat$1;;
Asciz	$outer;
Asciz	Lscala/collection/generic/TraversableFactory;;
Asciz	LocalVariableTable;
Asciz	(Lscala/collection/generic/TraversableFactory<TCC;>;)V;
Asciz	Signature;
Asciz	apply;
Asciz	(Ljava/lang/Object;)Ljava/lang/Object;;
Asciz	scala/collection/Traversable;
class	scala/collection/Traversable
Asciz	(Lscala/collection/Traversable;)Lscala/collection/mutable/Builder;;
NameAndType	apply:(Lscala/collection/Traversable;)Lscala/collection/mutable/Builder;
Method	scala/collection/generic/TraversableFactory$$anonfun$concat$1.apply:(Lscala/collection/Traversable;)Lscala/collection/mutable/Builder;
Asciz	v1;
Asciz	Ljava/lang/Object;;
Asciz	scala/collection/generic/Growable;
class	scala/collection/generic/Growable
Asciz	$plus$plus$eq;
Asciz	(Lscala/collection/Traversable;)Lscala/collection/generic/Growable;;
NameAndType	$plus$plus$eq:(Lscala/collection/Traversable;)Lscala/collection/generic/Growable;
InterfaceMethod	scala/collection/generic/Growable.$plus$plus$eq:(Lscala/collection/Traversable;)Lscala/collection/generic/Growable;
Asciz	scala/collection/mutable/Builder;
class	scala/collection/mutable/Builder
Asciz	xs;
Asciz	Lscala/collection/Traversable;;
Asciz	(Lscala/collection/Traversable<TA;>;)Lscala/collection/mutable/Builder<TA;TCC;>;;
Asciz	andThen;
Asciz	(Lscala/Function1;)Lscala/Function1;;
Asciz	(Lscala/Function1;Lscala/Function1;)Lscala/Function1;;
NameAndType	andThen:(Lscala/Function1;Lscala/Function1;)Lscala/Function1;
Method	scala/Function1$class.andThen:(Lscala/Function1;Lscala/Function1;)Lscala/Function1;
Asciz	g;
Asciz	Lscala/Function1;;
Asciz	compose;
NameAndType	compose:(Lscala/Function1;Lscala/Function1;)Lscala/Function1;
Method	scala/Function1$class.compose:(Lscala/Function1;Lscala/Function1;)Lscala/Function1;
Asciz	toString;
Asciz	()Ljava/lang/String;;
Asciz	(Lscala/Function1;)Ljava/lang/String;;
NameAndType	toString:(Lscala/Function1;)Ljava/lang/String;
Method	scala/Function1$class.toString:(Lscala/Function1;)Ljava/lang/String;
Asciz	Scala;
Asciz	InnerClasses;
Asciz	scala/collection/generic/TraversableFactory;
class	scala/collection/generic/TraversableFactory
Asciz	$anonfun$concat$1;
Asciz	scala/Function1;
class	scala/Function1
Asciz	scala/ScalaObject;
class	scala/ScalaObject
Asciz	java/io/Serializable;
class	java/io/Serializable

{
public static final long serialVersionUID;
  Signature: J

private final scala.collection.mutable.Builder b$1;
  Signature: Lscala/collection/mutable/Builder;

public static {};
  Signature: ()V
  Code:
   Stack=2, Locals=0, Args_size=0
	lconst_0
	putstatic	Field serialVersionUID:J
	return
  Labels:

public scala.collection.generic.TraversableFactory$$anonfun$concat$1(scala.collection.generic.TraversableFactory, scala.collection.mutable.Builder);
  Signature: (Lscala/collection/generic/TraversableFactory;Lscala/collection/mutable/Builder;)V
  Code:
   Stack=2, Locals=3, Args_size=3
	aload_0
	aload_2
	putfield	Field b$1:Lscala/collection/mutable/Builder;
	aload_0
	invokespecial	Method java/lang/Object."<init>":()V
	aload_0
	invokestatic	Method scala/Function1$class.$init$:(Lscala/Function1;)V
	return
  Labels:
  LocalVariableTable: 
   Start  Length  Slot  Name   Signature
   0      14      0    this       Lscala/collection/generic/TraversableFactory$$anonfun$concat$1;
   0      14      1    $outer       Lscala/collection/generic/TraversableFactory;

  Signature: length = 0x2
   00 22 

public final java.lang.Object apply(java.lang.Object);
  Signature: (Ljava/lang/Object;)Ljava/lang/Object;
  Code:
   Stack=2, Locals=2, Args_size=2
	aload_0
	aload_1
	checkcast	class scala/collection/Traversable
	invokevirtual	Method apply:(Lscala/collection/Traversable;)Lscala/collection/mutable/Builder;
	areturn
  Labels:
  LocalVariableTable: 
   Start  Length  Slot  Name   Signature
   0      9      0    this       Lscala/collection/generic/TraversableFactory$$anonfun$concat$1;
   0      9      1    v1       Ljava/lang/Object;


public final scala.collection.mutable.Builder apply(scala.collection.Traversable);
  Signature: (Lscala/collection/Traversable;)Lscala/collection/mutable/Builder;
  Code:
   Stack=2, Locals=2, Args_size=2
	aload_0
	getfield	Field b$1:Lscala/collection/mutable/Builder;
	aload_1
	invokeinterface	InterfaceMethod scala/collection/generic/Growable.$plus$plus$eq:(Lscala/collection/Traversable;)Lscala/collection/generic/Growable;
	checkcast	class scala/collection/mutable/Builder
	areturn
  Labels:
  LocalVariableTable: 
   Start  Length  Slot  Name   Signature
   0      14      0    this       Lscala/collection/generic/TraversableFactory$$anonfun$concat$1;
   0      14      1    xs       Lscala/collection/Traversable;

  Signature: length = 0x2
   00 37 

public scala.Function1 andThen(scala.Function1);
  Signature: (Lscala/Function1;)Lscala/Function1;
  Code:
   Stack=2, Locals=2, Args_size=2
	aload_0
	aload_1
	invokestatic	Method scala/Function1$class.andThen:(Lscala/Function1;Lscala/Function1;)Lscala/Function1;
	areturn
  Labels:
  LocalVariableTable: 
   Start  Length  Slot  Name   Signature
   0      6      0    this       Lscala/collection/generic/TraversableFactory$$anonfun$concat$1;
   0      6      1    g       Lscala/Function1;


public scala.Function1 compose(scala.Function1);
  Signature: (Lscala/Function1;)Lscala/Function1;
  Code:
   Stack=2, Locals=2, Args_size=2
	aload_0
	aload_1
	invokestatic	Method scala/Function1$class.compose:(Lscala/Function1;Lscala/Function1;)Lscala/Function1;
	areturn
  Labels:
  LocalVariableTable: 
   Start  Length  Slot  Name   Signature
   0      6      0    this       Lscala/collection/generic/TraversableFactory$$anonfun$concat$1;
   0      6      1    g       Lscala/Function1;


public java.lang.String toString();
  Signature: ()Ljava/lang/String;
  Code:
   Stack=1, Locals=1, Args_size=1
	aload_0
	invokestatic	Method scala/Function1$class.toString:(Lscala/Function1;)Ljava/lang/String;
	areturn
  Labels:

}

