Compiled from "TraversableFactory.scala"
public final class scala.collection.generic.TraversableFactory$$anonfun$tabulate$4$$anonfun$apply$4 extends java.lang.Object implements scala.Function4,scala.ScalaObject,java.io.Serializable
  SourceFile: "TraversableFactory.scala"
  Scala: length = 0x
   
  InnerClass: 
   public final $anonfun$tabulate$4=class scala/collection/generic/TraversableFactory$$anonfun$tabulate$4 of class scala/collection/generic/TraversableFactory
   public final $anonfun$apply$4=class scala/collection/generic/TraversableFactory$$anonfun$tabulate$4$$anonfun$apply$4 of class scala/collection/generic/TraversableFactory$$anonfun$tabulate$4
  minor version: 0
  major version: 49
  Constant pool:
Asciz	SourceFile;
Asciz	TraversableFactory.scala;
Asciz	<clinit>;
Asciz	()V;
Asciz	Code;
Asciz	serialVersionUID;
Asciz	J;
Asciz	scala/collection/generic/TraversableFactory$$anonfun$tabulate$4$$anonfun$apply$4;
class	scala/collection/generic/TraversableFactory$$anonfun$tabulate$4$$anonfun$apply$4
NameAndType	serialVersionUID:J
Field	scala/collection/generic/TraversableFactory$$anonfun$tabulate$4$$anonfun$apply$4.serialVersionUID:J
Asciz	i1$4;
Asciz	I;
Asciz	$outer;
Asciz	Lscala/collection/generic/TraversableFactory$$anonfun$tabulate$4;;
Asciz	<init>;
Asciz	(Lscala/collection/generic/TraversableFactory$$anonfun$tabulate$4;I)V;
Asciz	LineNumberTable;
Asciz	java/lang/NullPointerException;
class	java/lang/NullPointerException
NameAndType	"<init>":()V
Method	java/lang/NullPointerException."<init>":()V
NameAndType	$outer:Lscala/collection/generic/TraversableFactory$$anonfun$tabulate$4;
Field	scala/collection/generic/TraversableFactory$$anonfun$tabulate$4$$anonfun$apply$4.$outer:Lscala/collection/generic/TraversableFactory$$anonfun$tabulate$4;
NameAndType	i1$4:I
Field	scala/collection/generic/TraversableFactory$$anonfun$tabulate$4$$anonfun$apply$4.i1$4:I
Asciz	java/lang/Object;
class	java/lang/Object
Method	java/lang/Object."<init>":()V
Asciz	scala/Function4$class;
class	scala/Function4$class
Asciz	$init$;
Asciz	(Lscala/Function4;)V;
NameAndType	$init$:(Lscala/Function4;)V
Method	scala/Function4$class.$init$:(Lscala/Function4;)V
Asciz	this;
Asciz	Lscala/collection/generic/TraversableFactory$$anonfun$tabulate$4$$anonfun$apply$4;;
Asciz	LocalVariableTable;
Asciz	(Lscala/collection/generic/TraversableFactory<TCC;>.$anonfun$tabulate$4;)V;
Asciz	Signature;
Asciz	apply;
Asciz	(Ljava/lang/Object;Ljava/lang/Object;Ljava/lang/Object;Ljava/lang/Object;)Ljava/lang/Object;;
Asciz	scala/runtime/BoxesRunTime;
class	scala/runtime/BoxesRunTime
Asciz	unboxToInt;
Asciz	(Ljava/lang/Object;)I;
NameAndType	unboxToInt:(Ljava/lang/Object;)I
Method	scala/runtime/BoxesRunTime.unboxToInt:(Ljava/lang/Object;)I
Asciz	(IIII)Ljava/lang/Object;;
NameAndType	apply:(IIII)Ljava/lang/Object;
Method	scala/collection/generic/TraversableFactory$$anonfun$tabulate$4$$anonfun$apply$4.apply:(IIII)Ljava/lang/Object;
Asciz	v1;
Asciz	Ljava/lang/Object;;
Asciz	v2;
Asciz	v3;
Asciz	v4;
Asciz	scala/collection/generic/TraversableFactory$$anonfun$tabulate$4;
class	scala/collection/generic/TraversableFactory$$anonfun$tabulate$4
Asciz	f$1;
Asciz	Lscala/Function5;;
NameAndType	f$1:Lscala/Function5;
Field	scala/collection/generic/TraversableFactory$$anonfun$tabulate$4.f$1:Lscala/Function5;
Asciz	boxToInteger;
Asciz	(I)Ljava/lang/Integer;;
NameAndType	boxToInteger:(I)Ljava/lang/Integer;
Method	scala/runtime/BoxesRunTime.boxToInteger:(I)Ljava/lang/Integer;
Asciz	scala/Function5;
class	scala/Function5
Asciz	(Ljava/lang/Object;Ljava/lang/Object;Ljava/lang/Object;Ljava/lang/Object;Ljava/lang/Object;)Ljava/lang/Object;;
NameAndType	apply:(Ljava/lang/Object;Ljava/lang/Object;Ljava/lang/Object;Ljava/lang/Object;Ljava/lang/Object;)Ljava/lang/Object;
InterfaceMethod	scala/Function5.apply:(Ljava/lang/Object;Ljava/lang/Object;Ljava/lang/Object;Ljava/lang/Object;Ljava/lang/Object;)Ljava/lang/Object;
Asciz	(IIII)TA;;
Asciz	curry;
Asciz	()Lscala/Function1;;
Asciz	(Lscala/Function4;)Lscala/Function1;;
NameAndType	curry:(Lscala/Function4;)Lscala/Function1;
Method	scala/Function4$class.curry:(Lscala/Function4;)Lscala/Function1;
Asciz	toString;
Asciz	()Ljava/lang/String;;
Asciz	(Lscala/Function4;)Ljava/lang/String;;
NameAndType	toString:(Lscala/Function4;)Ljava/lang/String;
Method	scala/Function4$class.toString:(Lscala/Function4;)Ljava/lang/String;
Asciz	Scala;
Asciz	InnerClasses;
Asciz	scala/collection/generic/TraversableFactory;
class	scala/collection/generic/TraversableFactory
Asciz	$anonfun$tabulate$4;
Asciz	$anonfun$apply$4;
Asciz	scala/Function4;
class	scala/Function4
Asciz	scala/ScalaObject;
class	scala/ScalaObject
Asciz	java/io/Serializable;
class	java/io/Serializable

{
public static final long serialVersionUID;
  Signature: J

private final int i1$4;
  Signature: I

private final scala.collection.generic.TraversableFactory$$anonfun$tabulate$4 $outer;
  Signature: Lscala/collection/generic/TraversableFactory$$anonfun$tabulate$4;

public static {};
  Signature: ()V
  Code:
   Stack=2, Locals=0, Args_size=0
	lconst_0
	putstatic	Field serialVersionUID:J
	return
  Labels:

public scala.collection.generic.TraversableFactory$$anonfun$tabulate$4$$anonfun$apply$4(scala.collection.generic.TraversableFactory$$anonfun$tabulate$4, int);
  Signature: (Lscala/collection/generic/TraversableFactory$$anonfun$tabulate$4;I)V
  Code:
   Stack=2, Locals=3, Args_size=3
	aload_1
	ifnonnull	l1 // aload_0
	new	class java/lang/NullPointerException
	dup
	invokespecial	Method java/lang/NullPointerException."<init>":()V
	athrow
l1	aload_0
	aload_1
	putfield	Field $outer:Lscala/collection/generic/TraversableFactory$$anonfun$tabulate$4;
	aload_0
	iload_2
	putfield	Field i1$4:I
	aload_0
	invokespecial	Method java/lang/Object."<init>":()V
	aload_0
	invokestatic	Method scala/Function4$class.$init$:(Lscala/Function4;)V
	return
  Labels:
   	l1 = 12 // aload_0
  LocalVariableTable: 
   Start  Length  Slot  Name   Signature
   0      31      0    this       Lscala/collection/generic/TraversableFactory$$anonfun$tabulate$4$$anonfun$apply$4;
   0      31      1    $outer       Lscala/collection/generic/TraversableFactory$$anonfun$tabulate$4;

  Signature: length = 0x2
   00 27 

public final java.lang.Object apply(java.lang.Object, java.lang.Object, java.lang.Object, java.lang.Object);
  Signature: (Ljava/lang/Object;Ljava/lang/Object;Ljava/lang/Object;Ljava/lang/Object;)Ljava/lang/Object;
  Code:
   Stack=5, Locals=6, Args_size=5
	aload_0
	getfield	Field $outer:Lscala/collection/generic/TraversableFactory$$anonfun$tabulate$4;
	astore	5
	aload_0
	aload_1
	invokestatic	Method scala/runtime/BoxesRunTime.unboxToInt:(Ljava/lang/Object;)I
	aload_2
	invokestatic	Method scala/runtime/BoxesRunTime.unboxToInt:(Ljava/lang/Object;)I
	aload_3
	invokestatic	Method scala/runtime/BoxesRunTime.unboxToInt:(Ljava/lang/Object;)I
	aload	4
	invokestatic	Method scala/runtime/BoxesRunTime.unboxToInt:(Ljava/lang/Object;)I
	invokevirtual	Method apply:(IIII)Ljava/lang/Object;
	areturn
  Labels:
  LocalVariableTable: 
   Start  Length  Slot  Name   Signature
   0      28      0    this       Lscala/collection/generic/TraversableFactory$$anonfun$tabulate$4$$anonfun$apply$4;
   6      22      1    v1       Ljava/lang/Object;
   6      22      2    v2       Ljava/lang/Object;
   6      22      3    v3       Ljava/lang/Object;
   6      22      4    v4       Ljava/lang/Object;


public final java.lang.Object apply(int, int, int, int);
  Signature: (IIII)Ljava/lang/Object;
  Code:
   Stack=6, Locals=7, Args_size=5
	aload_0
	getfield	Field $outer:Lscala/collection/generic/TraversableFactory$$anonfun$tabulate$4;
	astore	6
	aload_0
	getfield	Field $outer:Lscala/collection/generic/TraversableFactory$$anonfun$tabulate$4;
	getfield	Field scala/collection/generic/TraversableFactory$$anonfun$tabulate$4.f$1:Lscala/Function5;
	aload_0
	getfield	Field i1$4:I
	istore	5
	iload	5
	invokestatic	Method scala/runtime/BoxesRunTime.boxToInteger:(I)Ljava/lang/Integer;
	iload_1
	invokestatic	Method scala/runtime/BoxesRunTime.boxToInteger:(I)Ljava/lang/Integer;
	iload_2
	invokestatic	Method scala/runtime/BoxesRunTime.boxToInteger:(I)Ljava/lang/Integer;
	iload_3
	invokestatic	Method scala/runtime/BoxesRunTime.boxToInteger:(I)Ljava/lang/Integer;
	iload	4
	invokestatic	Method scala/runtime/BoxesRunTime.boxToInteger:(I)Ljava/lang/Integer;
	invokeinterface	InterfaceMethod scala/Function5.apply:(Ljava/lang/Object;Ljava/lang/Object;Ljava/lang/Object;Ljava/lang/Object;Ljava/lang/Object;)Ljava/lang/Object;
	areturn
  Labels:
  LocalVariableTable: 
   Start  Length  Slot  Name   Signature
   0      47      0    this       Lscala/collection/generic/TraversableFactory$$anonfun$tabulate$4$$anonfun$apply$4;

  Signature: length = 0x2
   00 48 

public scala.Function1 curry();
  Signature: ()Lscala/Function1;
  Code:
   Stack=1, Locals=1, Args_size=1
	aload_0
	invokestatic	Method scala/Function4$class.curry:(Lscala/Function4;)Lscala/Function1;
	areturn
  Labels:

public java.lang.String toString();
  Signature: ()Ljava/lang/String;
  Code:
   Stack=1, Locals=1, Args_size=1
	aload_0
	invokestatic	Method scala/Function4$class.toString:(Lscala/Function4;)Ljava/lang/String;
	areturn
  Labels:

}

