Compiled from "TraversableFactory.scala"
public abstract class scala.collection.generic.TraversableFactory extends scala.collection.generic.GenericCompanion implements scala.ScalaObject
  SourceFile: "TraversableFactory.scala"
  Signature: length = 0x2
   00 FFFFFFC3 
  ScalaSig: length = 0x839
   05 00 FFFFFF82 2A 06 05 01 02 FFFFFF81 00 09 02 12 54 72 61
   76 65 72 73 61 62 6C 65 46 61 63 74 6F 72 79 0A
   02 03 04 01 07 67 65 6E 65 72 69 63 0A 02 05 06
   01 0A 63 6F 6C 6C 65 63 74 69 6F 6E 0A 01 07 01
   05 73 63 61 6C 61 03 00 15 02 0A 11 13 03 00 0B
   2A 10 03 0C 0D 0F 0D 01 02 09 02 0E 02 02 10 47
   65 6E 65 72 69 63 43 6F 6D 70 61 6E 69 6F 6E 10
   02 10 11 0C 00 04 05 12 00 FFFFFFC2 00 13 02 02 43 43
   15 02 14 21 11 02 15 19 10 02 16 17 0D 01 06 09
   02 18 06 02 07 4E 6F 74 68 69 6E 67 12 03 1A 1C
   27 06 08 1B 00 FFFFFF84 FFFFFF80 FFFFFF80 FFFFFF80 00 19 02 0C 3C 72 65
   66 69 6E 65 6D 65 6E 74 3E 10 03 1D 1E 20 0D 01
   04 09 02 1F 04 02 0B 54 72 61 76 65 72 73 61 62
   6C 65 10 02 10 21 04 08 22 11 FFFFFF84 FFFFFF80 FFFFFF80 FFFFFFC2 00 23
   02 01 58 11 02 15 24 10 02 16 25 09 02 26 06 02
   03 41 6E 79 10 04 0C 28 20 0F 09 02 29 02 02 1A
   47 65 6E 65 72 69 63 54 72 61 76 65 72 73 61 62
   6C 65 54 65 6D 70 6C 61 74 65 10 02 16 2B 09 02
   2C 06 02 0B 53 63 61 6C 61 4F 62 6A 65 63 74 08
   05 2E 00 FFFFFF84 00 2F 01 06 3C 69 6E 69 74 3E 14 01
   30 10 03 0C 00 0F 06 04 32 00 00 33 02 13 47 65
   6E 65 72 69 63 43 61 6E 42 75 69 6C 64 46 72 6F
   6D 15 02 34 46 13 04 31 35 3D 2A 10 02 36 3B 0D
   01 37 0A 02 38 39 01 04 6C 61 6E 67 0A 01 3A 01
   04 6A 61 76 61 09 02 3C 37 02 06 4F 62 6A 65 63
   74 10 05 0C 3E 40 45 48 09 02 3F 02 02 0C 43 61
   6E 42 75 69 6C 64 46 72 6F 6D 30 02 41 43 10 03
   10 11 42 10 02 10 43 04 08 44 31 FFFFFF84 FFFFFF80 FFFFFF80 FFFFFF82 00
   23 02 03 5F 24 31 10 02 10 46 04 08 47 31 FFFFFF84 FFFFFF80
   FFFFFF80 FFFFFFC2 00 23 02 01 41 10 03 10 11 45 08 05 2E 31
   FFFFFF84 00 4A 14 01 4B 10 03 4C 31 45 0D 01 00 08 05
   4E 31 FFFFFF84 00 4F 01 05 61 70 70 6C 79 14 02 50 56
   10 04 51 54 45 48 0D 01 52 0A 02 53 04 01 07 6D
   75 74 61 62 6C 65 09 02 55 52 02 07 42 75 69 6C
   64 65 72 08 05 57 4D FFFFFFC0 00 58 01 04 66 72 6F 6D
   10 02 4C 59 09 02 5A 0D 02 04 43 6F 6C 6C 08 05
   4E 31 FFFFFF84 00 5C 14 01 50 08 05 5E 00 FFFFFF84 00 5F 01
   06 63 6F 6E 63 61 74 15 02 60 63 14 02 61 64 10
   03 10 11 62 10 02 10 63 04 08 47 5D FFFFFF84 FFFFFF80 FFFFFF80 FFFFFFC2
   00 23 08 05 65 5D FFFFFFC0 00 66 01 03 78 73 73 10 03
   16 67 69 09 02 68 06 02 0A 3C 72 65 70 65 61 74
   65 64 3E 10 03 1D 1E 62 08 05 6B 00 FFFFFF84 00 6C 01
   04 66 69 6C 6C 15 02 6D 71 14 02 6E 77 14 02 6F
   72 10 03 10 11 70 10 02 10 71 04 08 47 6A FFFFFF84 FFFFFF80
   FFFFFF80 FFFFFFC2 00 23 08 06 73 6A FFFFFF84 FFFFFFC0 00 74 01 04 65 6C
   65 6D 10 03 16 75 70 09 02 76 06 02 08 3C 62 79
   6E 61 6D 65 3E 08 05 78 6A FFFFFFC0 00 79 01 01 6E 10
   02 16 7A 09 02 7B 06 02 03 49 6E 74 08 05 6B 00
   FFFFFF84 00 7D 15 03 7E FFFFFF81 03 14 05 7F FFFFFF81 06 FFFFFF81 08 14
   04 FFFFFF81 00 FFFFFF81 04 10 04 10 11 FFFFFF81 01 10 04 10 11 FFFFFF81
   02 10 03 10 FFFFFF81 03 04 08 47 7C FFFFFF84 FFFFFF80 FFFFFF80 FFFFFFC2 00 23
   08 07 73 7C FFFFFF84 FFFFFFC0 00 FFFFFF81 05 10 04 16 75 FFFFFF81 02 08
   06 FFFFFF81 07 7C FFFFFFC0 00 79 01 02 6E 31 08 06 FFFFFF81 09 7C
   FFFFFFC0 00 79 01 02 6E 32 08 06 6B 00 FFFFFF84 00 FFFFFF81 0B 15
   04 FFFFFF81 0C FFFFFF81 12 14 08 FFFFFF81 0D FFFFFF81 15 FFFFFF81 16 FFFFFF81 17 14
   04 FFFFFF81 0E FFFFFF81 13 10 04 10 11 FFFFFF81 0F 10 04 10 11 FFFFFF81
   10 10 04 10 11 FFFFFF81 11 10 03 10 FFFFFF81 12 04 09 47 FFFFFF81
   0A FFFFFF84 FFFFFF80 FFFFFF80 FFFFFFC2 00 23 08 08 73 FFFFFF81 0A FFFFFF84 FFFFFFC0 00 FFFFFF81
   14 10 04 16 75 FFFFFF81 11 08 07 FFFFFF81 07 FFFFFF81 0A FFFFFFC0 00 79
   08 07 FFFFFF81 09 FFFFFF81 0A FFFFFFC0 00 79 08 07 FFFFFF81 18 FFFFFF81 0A FFFFFFC0
   00 79 01 02 6E 33 08 06 6B 00 FFFFFF84 00 FFFFFF81 1A 15 04
   FFFFFF81 1B FFFFFF81 22 14 0A FFFFFF81 1C FFFFFF81 25 FFFFFF81 26 FFFFFF81 27 FFFFFF81 28
   14 04 FFFFFF81 1D FFFFFF81 23 10 04 10 11 FFFFFF81 1E 10 04 10 11
   FFFFFF81 1F 10 04 10 11 FFFFFF81 20 10 04 10 11 FFFFFF81 21 10 03
   10 FFFFFF81 22 04 09 47 FFFFFF81 19 FFFFFF84 FFFFFF80 FFFFFF80 FFFFFFC2 00 23 08 08
   73 FFFFFF81 19 FFFFFF84 FFFFFFC0 00 FFFFFF81 24 10 04 16 75 FFFFFF81 21 08 07
   FFFFFF81 07 FFFFFF81 19 FFFFFFC0 00 79 08 07 FFFFFF81 09 FFFFFF81 19 FFFFFFC0 00 79
   08 07 FFFFFF81 18 FFFFFF81 19 FFFFFFC0 00 79 08 07 FFFFFF81 29 FFFFFF81 19 FFFFFFC0
   00 79 01 02 6E 34 08 06 6B 00 FFFFFF84 00 FFFFFF81 2B 15 04
   FFFFFF81 2C FFFFFF81 34 14 0C FFFFFF81 2D FFFFFF81 37 FFFFFF81 38 FFFFFF81 39 FFFFFF81 3A
   FFFFFF81 3B 14 04 FFFFFF81 2E FFFFFF81 35 10 04 10 11 FFFFFF81 2F 10 04
   10 11 FFFFFF81 30 10 04 10 11 FFFFFF81 31 10 04 10 11 FFFFFF81 32
   10 04 10 11 FFFFFF81 33 10 03 10 FFFFFF81 34 04 09 47 FFFFFF81 2A
   FFFFFF84 FFFFFF80 FFFFFF80 FFFFFFC2 00 23 08 08 73 FFFFFF81 2A FFFFFF84 FFFFFFC0 00 FFFFFF81 36
   10 04 16 75 FFFFFF81 33 08 07 FFFFFF81 07 FFFFFF81 2A FFFFFFC0 00 79 08
   07 FFFFFF81 09 FFFFFF81 2A FFFFFFC0 00 79 08 07 FFFFFF81 18 FFFFFF81 2A FFFFFFC0 00
   79 08 07 FFFFFF81 29 FFFFFF81 2A FFFFFFC0 00 79 08 07 FFFFFF81 3C FFFFFF81 2A
   FFFFFFC0 00 79 01 02 6E 35 08 07 FFFFFF81 3E 00 FFFFFF84 00 FFFFFF81 3F
   01 08 74 61 62 75 6C 61 74 65 15 04 FFFFFF81 40 FFFFFF81 44
   14 04 FFFFFF81 41 FFFFFF81 4A 14 04 FFFFFF81 42 FFFFFF81 45 10 04 10 11
   FFFFFF81 43 10 03 10 FFFFFF81 44 04 09 47 FFFFFF81 3D FFFFFF84 FFFFFF80 FFFFFF80 FFFFFFC2
   00 23 08 08 FFFFFF81 46 FFFFFF81 3D FFFFFFC0 00 FFFFFF81 47 01 01 66 10
   06 16 FFFFFF81 48 79 FFFFFF81 43 09 03 FFFFFF81 49 06 02 09 46 75
   6E 63 74 69 6F 6E 31 08 06 78 FFFFFF81 3D FFFFFFC0 00 79 08
   07 FFFFFF81 3E 00 FFFFFF84 00 FFFFFF81 4C 15 04 FFFFFF81 4D FFFFFF81 52 14 06
   FFFFFF81 4E FFFFFF81 57 FFFFFF81 58 14 04 FFFFFF81 4F FFFFFF81 53 10 04 10 11
   FFFFFF81 50 10 04 10 11 FFFFFF81 51 10 03 10 FFFFFF81 52 04 09 47
   FFFFFF81 4B FFFFFF84 FFFFFF80 FFFFFF80 FFFFFFC2 00 23 08 08 FFFFFF81 46 FFFFFF81 4B FFFFFFC0 00
   FFFFFF81 54 10 07 16 FFFFFF81 55 79 79 FFFFFF81 51 09 03 FFFFFF81 56 06
   02 09 46 75 6E 63 74 69 6F 6E 32 08 07 FFFFFF81 07 FFFFFF81
   4B FFFFFFC0 00 79 08 07 FFFFFF81 09 FFFFFF81 4B FFFFFFC0 00 79 08 07 FFFFFF81
   3E 00 FFFFFF84 00 FFFFFF81 5A 15 04 FFFFFF81 5B FFFFFF81 61 14 08 FFFFFF81 5C
   FFFFFF81 66 FFFFFF81 67 FFFFFF81 68 14 04 FFFFFF81 5D FFFFFF81 62 10 04 10 11
   FFFFFF81 5E 10 04 10 11 FFFFFF81 5F 10 04 10 11 FFFFFF81 60 10 03
   10 FFFFFF81 61 04 09 47 FFFFFF81 59 FFFFFF84 FFFFFF80 FFFFFF80 FFFFFFC2 00 23 08 08
   FFFFFF81 46 FFFFFF81 59 FFFFFFC0 00 FFFFFF81 63 10 08 16 FFFFFF81 64 79 79 79
   FFFFFF81 60 09 03 FFFFFF81 65 06 02 09 46 75 6E 63 74 69 6F
   6E 33 08 07 FFFFFF81 07 FFFFFF81 59 FFFFFFC0 00 79 08 07 FFFFFF81 09 FFFFFF81
   59 FFFFFFC0 00 79 08 07 FFFFFF81 18 FFFFFF81 59 FFFFFFC0 00 79 08 07 FFFFFF81
   3E 00 FFFFFF84 00 FFFFFF81 6A 15 04 FFFFFF81 6B FFFFFF81 72 14 0A FFFFFF81 6C
   FFFFFF81 77 FFFFFF81 78 FFFFFF81 79 FFFFFF81 7A 14 04 FFFFFF81 6D FFFFFF81 73 10 04
   10 11 FFFFFF81 6E 10 04 10 11 FFFFFF81 6F 10 04 10 11 FFFFFF81 70
   10 04 10 11 FFFFFF81 71 10 03 10 FFFFFF81 72 04 09 47 FFFFFF81 69
   FFFFFF84 FFFFFF80 FFFFFF80 FFFFFFC2 00 23 08 08 FFFFFF81 46 FFFFFF81 69 FFFFFFC0 00 FFFFFF81 74
   10 09 16 FFFFFF81 75 79 79 79 79 FFFFFF81 71 09 03 FFFFFF81 76 06
   02 09 46 75 6E 63 74 69 6F 6E 34 08 07 FFFFFF81 07 FFFFFF81
   69 FFFFFFC0 00 79 08 07 FFFFFF81 09 FFFFFF81 69 FFFFFFC0 00 79 08 07 FFFFFF81
   18 FFFFFF81 69 FFFFFFC0 00 79 08 07 FFFFFF81 29 FFFFFF81 69 FFFFFFC0 00 79 08
   07 FFFFFF81 3E 00 FFFFFF84 00 FFFFFF81 7C 15 04 FFFFFF81 7D FFFFFF82 05 14 0C
   FFFFFF81 7E FFFFFF82 0A FFFFFF82 0B FFFFFF82 0C FFFFFF82 0D FFFFFF82 0E 14 04 FFFFFF81 7F
   FFFFFF82 06 10 04 10 11 FFFFFF82 00 10 04 10 11 FFFFFF82 01 10 04
   10 11 FFFFFF82 02 10 04 10 11 FFFFFF82 03 10 04 10 11 FFFFFF82 04
   10 03 10 FFFFFF82 05 04 09 47 FFFFFF81 7B FFFFFF84 FFFFFF80 FFFFFF80 FFFFFFC2 00 23
   08 08 FFFFFF81 46 FFFFFF81 7B FFFFFFC0 00 FFFFFF82 07 10 0A 16 FFFFFF82 08 79
   79 79 79 79 FFFFFF82 04 09 03 FFFFFF82 09 06 02 09 46 75 6E
   63 74 69 6F 6E 35 08 07 FFFFFF81 07 FFFFFF81 7B FFFFFFC0 00 79 08
   07 FFFFFF81 09 FFFFFF81 7B FFFFFFC0 00 79 08 07 FFFFFF81 18 FFFFFF81 7B FFFFFFC0 00
   79 08 07 FFFFFF81 29 FFFFFF81 7B FFFFFFC0 00 79 08 07 FFFFFF81 3C FFFFFF81 7B
   FFFFFFC0 00 79 08 07 FFFFFF82 10 00 FFFFFF84 00 FFFFFF82 11 01 05 72 61
   6E 67 65 14 06 FFFFFF82 12 FFFFFF82 13 FFFFFF82 15 10 03 10 11 79
   08 07 FFFFFF82 14 FFFFFF82 0F FFFFFFC0 00 79 01 05 73 74 61 72 74
   08 07 FFFFFF82 16 FFFFFF82 0F FFFFFFC0 00 79 01 03 65 6E 64 08 07
   FFFFFF82 10 00 FFFFFF84 00 FFFFFF82 18 14 08 FFFFFF82 12 FFFFFF82 19 FFFFFF82 1A FFFFFF82
   1B 08 07 FFFFFF82 14 FFFFFF82 17 FFFFFFC0 00 79 08 07 FFFFFF82 16 FFFFFF82 17
   FFFFFFC0 00 79 08 07 FFFFFF82 1C FFFFFF82 17 FFFFFFC0 00 79 01 04 73 74
   65 70 08 07 FFFFFF82 1E 00 FFFFFF84 00 FFFFFF82 1F 01 07 69 74 65
   72 61 74 65 15 04 FFFFFF82 20 FFFFFF82 24 14 06 FFFFFF82 21 FFFFFF82 27
   FFFFFF82 28 14 04 FFFFFF82 22 FFFFFF82 25 10 04 10 11 FFFFFF82 23 10 03
   10 FFFFFF82 24 04 09 47 FFFFFF82 1D FFFFFF84 FFFFFF80 FFFFFF80 FFFFFFC2 00 23 08 08
   FFFFFF81 46 FFFFFF82 1D FFFFFFC0 00 FFFFFF82 26 10 07 16 FFFFFF81 48 FFFFFF82 23 FFFFFF82
   23 08 08 FFFFFF82 14 FFFFFF82 1D FFFFFFC0 00 FFFFFF82 23 08 07 FFFFFF82 29 FFFFFF82
   1D FFFFFFC0 00 79 01 03 6C 65 6E 
  InnerClass: 
   public final $anonfun$fill$4=class scala/collection/generic/TraversableFactory$$anonfun$fill$4 of class scala/collection/generic/TraversableFactory
   public final $anonfun$fill$3=class scala/collection/generic/TraversableFactory$$anonfun$fill$3 of class scala/collection/generic/TraversableFactory
   public final $anonfun$fill$2=class scala/collection/generic/TraversableFactory$$anonfun$fill$2 of class scala/collection/generic/TraversableFactory
   public final $anonfun$fill$1=class scala/collection/generic/TraversableFactory$$anonfun$fill$1 of class scala/collection/generic/TraversableFactory
   public final $anonfun$concat$1=class scala/collection/generic/TraversableFactory$$anonfun$concat$1 of class scala/collection/generic/TraversableFactory
   public GenericCanBuildFrom=class scala/collection/generic/TraversableFactory$GenericCanBuildFrom of class scala/collection/generic/TraversableFactory
   public final $anonfun$tabulate$4=class scala/collection/generic/TraversableFactory$$anonfun$tabulate$4 of class scala/collection/generic/TraversableFactory
   public final $anonfun$tabulate$3=class scala/collection/generic/TraversableFactory$$anonfun$tabulate$3 of class scala/collection/generic/TraversableFactory
   public final $anonfun$tabulate$2=class scala/collection/generic/TraversableFactory$$anonfun$tabulate$2 of class scala/collection/generic/TraversableFactory
   public final $anonfun$tabulate$1=class scala/collection/generic/TraversableFactory$$anonfun$tabulate$1 of class scala/collection/generic/TraversableFactory
  minor version: 0
  major version: 49
  Constant pool:
Asciz	SourceFile;
Asciz	TraversableFactory.scala;
Asciz	concat;
Asciz	(Lscala/collection/Seq;)Lscala/collection/Traversable;;
Asciz	Code;
Asciz	LineNumberTable;
Asciz	scala/collection/generic/TraversableFactory;
class	scala/collection/generic/TraversableFactory
Asciz	newBuilder;
Asciz	()Lscala/collection/mutable/Builder;;
NameAndType	newBuilder:()Lscala/collection/mutable/Builder;
Method	scala/collection/generic/TraversableFactory.newBuilder:()Lscala/collection/mutable/Builder;
Asciz	scala/collection/generic/TraversableFactory$$anonfun$concat$1;
class	scala/collection/generic/TraversableFactory$$anonfun$concat$1
Asciz	<init>;
Asciz	(Lscala/collection/generic/TraversableFactory;Lscala/collection/mutable/Builder;)V;
NameAndType	"<init>":(Lscala/collection/generic/TraversableFactory;Lscala/collection/mutable/Builder;)V
Method	scala/collection/generic/TraversableFactory$$anonfun$concat$1."<init>":(Lscala/collection/generic/TraversableFactory;Lscala/collection/mutable/Builder;)V
Asciz	scala/collection/IterableLike;
class	scala/collection/IterableLike
Asciz	foreach;
Asciz	(Lscala/Function1;)V;
NameAndType	foreach:(Lscala/Function1;)V
InterfaceMethod	scala/collection/IterableLike.foreach:(Lscala/Function1;)V
Asciz	scala/collection/mutable/Builder;
class	scala/collection/mutable/Builder
Asciz	result;
Asciz	()Ljava/lang/Object;;
NameAndType	result:()Ljava/lang/Object;
InterfaceMethod	scala/collection/mutable/Builder.result:()Ljava/lang/Object;
Asciz	scala/collection/Traversable;
class	scala/collection/Traversable
Asciz	this;
Asciz	Lscala/collection/generic/TraversableFactory;;
Asciz	xss;
Asciz	Lscala/collection/Seq;;
Asciz	b$1;
Asciz	Lscala/collection/mutable/Builder;;
Asciz	LocalVariableTable;
Asciz	<A:Ljava/lang/Object;>(Lscala/collection/Seq<Lscala/collection/Traversable<TA;>;>;)TCC;;
Asciz	Signature;
Asciz	fill;
Asciz	(ILscala/Function0;)Lscala/collection/Traversable;;
Asciz	scala/Function0;
class	scala/Function0
Asciz	apply;
NameAndType	apply:()Ljava/lang/Object;
InterfaceMethod	scala/Function0.apply:()Ljava/lang/Object;
Asciz	$plus$eq;
Asciz	(Ljava/lang/Object;)Lscala/collection/mutable/Builder;;
NameAndType	$plus$eq:(Ljava/lang/Object;)Lscala/collection/mutable/Builder;
InterfaceMethod	scala/collection/mutable/Builder.$plus$eq:(Ljava/lang/Object;)Lscala/collection/mutable/Builder;
Asciz	n;
Asciz	I;
Asciz	elem;
Asciz	Lscala/Function0;;
Asciz	b;
Asciz	i;
Asciz	<A:Ljava/lang/Object;>(ILscala/Function0<TA;>;)TCC;;
Asciz	(IILscala/Function0;)Lscala/collection/Traversable;;
Asciz	scala/collection/generic/TraversableFactory$$anonfun$fill$1;
class	scala/collection/generic/TraversableFactory$$anonfun$fill$1
Asciz	(Lscala/collection/generic/TraversableFactory;ILscala/Function0;)V;
NameAndType	"<init>":(Lscala/collection/generic/TraversableFactory;ILscala/Function0;)V
Method	scala/collection/generic/TraversableFactory$$anonfun$fill$1."<init>":(Lscala/collection/generic/TraversableFactory;ILscala/Function0;)V
Asciz	tabulate;
Asciz	(ILscala/Function1;)Lscala/collection/Traversable;;
NameAndType	tabulate:(ILscala/Function1;)Lscala/collection/Traversable;
Method	scala/collection/generic/TraversableFactory.tabulate:(ILscala/Function1;)Lscala/collection/Traversable;
Asciz	n1;
Asciz	n2$4;
Asciz	elem$4;
Asciz	<A:Ljava/lang/Object;>(IILscala/Function0<TA;>;)TCC;;
Asciz	(IIILscala/Function0;)Lscala/collection/Traversable;;
Asciz	scala/collection/generic/TraversableFactory$$anonfun$fill$2;
class	scala/collection/generic/TraversableFactory$$anonfun$fill$2
Asciz	(Lscala/collection/generic/TraversableFactory;IILscala/Function0;)V;
NameAndType	"<init>":(Lscala/collection/generic/TraversableFactory;IILscala/Function0;)V
Method	scala/collection/generic/TraversableFactory$$anonfun$fill$2."<init>":(Lscala/collection/generic/TraversableFactory;IILscala/Function0;)V
Asciz	n2$3;
Asciz	n3$3;
Asciz	elem$3;
Asciz	<A:Ljava/lang/Object;>(IIILscala/Function0<TA;>;)TCC;;
Asciz	(IIIILscala/Function0;)Lscala/collection/Traversable;;
Asciz	scala/collection/generic/TraversableFactory$$anonfun$fill$3;
class	scala/collection/generic/TraversableFactory$$anonfun$fill$3
Asciz	(Lscala/collection/generic/TraversableFactory;IIILscala/Function0;)V;
NameAndType	"<init>":(Lscala/collection/generic/TraversableFactory;IIILscala/Function0;)V
Method	scala/collection/generic/TraversableFactory$$anonfun$fill$3."<init>":(Lscala/collection/generic/TraversableFactory;IIILscala/Function0;)V
Asciz	n2$2;
Asciz	n3$2;
Asciz	n4$2;
Asciz	elem$2;
Asciz	<A:Ljava/lang/Object;>(IIIILscala/Function0<TA;>;)TCC;;
Asciz	(IIIIILscala/Function0;)Lscala/collection/Traversable;;
Asciz	scala/collection/generic/TraversableFactory$$anonfun$fill$4;
class	scala/collection/generic/TraversableFactory$$anonfun$fill$4
Asciz	(Lscala/collection/generic/TraversableFactory;IIIILscala/Function0;)V;
NameAndType	"<init>":(Lscala/collection/generic/TraversableFactory;IIIILscala/Function0;)V
Method	scala/collection/generic/TraversableFactory$$anonfun$fill$4."<init>":(Lscala/collection/generic/TraversableFactory;IIIILscala/Function0;)V
Asciz	n2$1;
Asciz	n3$1;
Asciz	n4$1;
Asciz	n5$1;
Asciz	elem$1;
Asciz	<A:Ljava/lang/Object;>(IIIIILscala/Function0<TA;>;)TCC;;
Asciz	scala/runtime/BoxesRunTime;
class	scala/runtime/BoxesRunTime
Asciz	boxToInteger;
Asciz	(I)Ljava/lang/Integer;;
NameAndType	boxToInteger:(I)Ljava/lang/Integer;
Method	scala/runtime/BoxesRunTime.boxToInteger:(I)Ljava/lang/Integer;
Asciz	scala/Function1;
class	scala/Function1
Asciz	(Ljava/lang/Object;)Ljava/lang/Object;;
NameAndType	apply:(Ljava/lang/Object;)Ljava/lang/Object;
InterfaceMethod	scala/Function1.apply:(Ljava/lang/Object;)Ljava/lang/Object;
Asciz	f;
Asciz	Lscala/Function1;;
Asciz	<A:Ljava/lang/Object;>(ILscala/Function1<Ljava/lang/Integer;TA;>;)TCC;;
Asciz	(IILscala/Function2;)Lscala/collection/Traversable;;
Asciz	scala/collection/generic/TraversableFactory$$anonfun$tabulate$1;
class	scala/collection/generic/TraversableFactory$$anonfun$tabulate$1
Asciz	(Lscala/collection/generic/TraversableFactory;ILscala/Function2;)V;
NameAndType	"<init>":(Lscala/collection/generic/TraversableFactory;ILscala/Function2;)V
Method	scala/collection/generic/TraversableFactory$$anonfun$tabulate$1."<init>":(Lscala/collection/generic/TraversableFactory;ILscala/Function2;)V
Asciz	n2$8;
Asciz	f$4;
Asciz	Lscala/Function2;;
Asciz	<A:Ljava/lang/Object;>(IILscala/Function2<Ljava/lang/Integer;Ljava/lang/Integer;TA;>;)TCC;;
Asciz	(IIILscala/Function3;)Lscala/collection/Traversable;;
Asciz	scala/collection/generic/TraversableFactory$$anonfun$tabulate$2;
class	scala/collection/generic/TraversableFactory$$anonfun$tabulate$2
Asciz	(Lscala/collection/generic/TraversableFactory;IILscala/Function3;)V;
NameAndType	"<init>":(Lscala/collection/generic/TraversableFactory;IILscala/Function3;)V
Method	scala/collection/generic/TraversableFactory$$anonfun$tabulate$2."<init>":(Lscala/collection/generic/TraversableFactory;IILscala/Function3;)V
Asciz	n2$7;
Asciz	n3$6;
Asciz	f$3;
Asciz	Lscala/Function3;;
Asciz	<A:Ljava/lang/Object;>(IIILscala/Function3<Ljava/lang/Integer;Ljava/lang/Integer;Ljava/lang/Integer;TA;>;)TCC;;
Asciz	(IIIILscala/Function4;)Lscala/collection/Traversable;;
Asciz	scala/collection/generic/TraversableFactory$$anonfun$tabulate$3;
class	scala/collection/generic/TraversableFactory$$anonfun$tabulate$3
Asciz	(Lscala/collection/generic/TraversableFactory;IIILscala/Function4;)V;
NameAndType	"<init>":(Lscala/collection/generic/TraversableFactory;IIILscala/Function4;)V
Method	scala/collection/generic/TraversableFactory$$anonfun$tabulate$3."<init>":(Lscala/collection/generic/TraversableFactory;IIILscala/Function4;)V
Asciz	n2$6;
Asciz	n3$5;
Asciz	n4$4;
Asciz	f$2;
Asciz	Lscala/Function4;;
Asciz	<A:Ljava/lang/Object;>(IIIILscala/Function4<Ljava/lang/Integer;Ljava/lang/Integer;Ljava/lang/Integer;Ljava/lang/Integer;TA;>;)TCC;;
Asciz	(IIIIILscala/Function5;)Lscala/collection/Traversable;;
Asciz	scala/collection/generic/TraversableFactory$$anonfun$tabulate$4;
class	scala/collection/generic/TraversableFactory$$anonfun$tabulate$4
Asciz	(Lscala/collection/generic/TraversableFactory;IIIILscala/Function5;)V;
NameAndType	"<init>":(Lscala/collection/generic/TraversableFactory;IIIILscala/Function5;)V
Method	scala/collection/generic/TraversableFactory$$anonfun$tabulate$4."<init>":(Lscala/collection/generic/TraversableFactory;IIIILscala/Function5;)V
Asciz	n2$5;
Asciz	n3$4;
Asciz	n4$3;
Asciz	n5$2;
Asciz	f$1;
Asciz	Lscala/Function5;;
Asciz	<A:Ljava/lang/Object;>(IIIIILscala/Function5<Ljava/lang/Integer;Ljava/lang/Integer;Ljava/lang/Integer;Ljava/lang/Integer;Ljava/lang/Integer;TA;>;)TCC;;
Asciz	range;
Asciz	(II)Lscala/collection/Traversable;;
Asciz	(III)Lscala/collection/Traversable;;
NameAndType	range:(III)Lscala/collection/Traversable;
Method	scala/collection/generic/TraversableFactory.range:(III)Lscala/collection/Traversable;
Asciz	start;
Asciz	end;
Asciz	(II)TCC;;
Asciz	java/lang/IllegalArgumentException;
class	java/lang/IllegalArgumentException
Asciz	zero step;
String	zero step
Asciz	(Ljava/lang/String;)V;
NameAndType	"<init>":(Ljava/lang/String;)V
Method	java/lang/IllegalArgumentException."<init>":(Ljava/lang/String;)V
Asciz	step;
Asciz	(III)TCC;;
Asciz	iterate;
Asciz	(Ljava/lang/Object;ILscala/Function1;)Lscala/collection/Traversable;;
Asciz	Ljava/lang/Object;;
Asciz	len;
Asciz	acc;
Asciz	<A:Ljava/lang/Object;>(TA;ILscala/Function1<TA;TA;>;)TCC;;
Asciz	()V;
Asciz	scala/collection/generic/GenericCompanion;
class	scala/collection/generic/GenericCompanion
NameAndType	"<init>":()V
Method	scala/collection/generic/GenericCompanion."<init>":()V
Asciz	<CC:Lscala/collection/Traversable<Ljava/lang/Object;>;>Lscala/collection/generic/GenericCompanion<TCC;>;Lscala/ScalaObject;;
Asciz	ScalaSig;
Asciz	InnerClasses;
Asciz	$anonfun$fill$4;
Asciz	$anonfun$fill$3;
Asciz	$anonfun$fill$2;
Asciz	$anonfun$fill$1;
Asciz	$anonfun$concat$1;
Asciz	scala/collection/generic/TraversableFactory$GenericCanBuildFrom;
class	scala/collection/generic/TraversableFactory$GenericCanBuildFrom
Asciz	GenericCanBuildFrom;
Asciz	$anonfun$tabulate$4;
Asciz	$anonfun$tabulate$3;
Asciz	$anonfun$tabulate$2;
Asciz	$anonfun$tabulate$1;
Asciz	scala/ScalaObject;
class	scala/ScalaObject

{
public scala.collection.Traversable concat(scala.collection.Seq);
  Signature: (Lscala/collection/Seq;)Lscala/collection/Traversable;
  Code:
   Stack=5, Locals=3, Args_size=2
	aload_0
	invokevirtual	Method newBuilder:()Lscala/collection/mutable/Builder;
	astore_2
	aload_1
	new	class scala/collection/generic/TraversableFactory$$anonfun$concat$1
	dup
	aload_0
	aload_2
	invokespecial	Method scala/collection/generic/TraversableFactory$$anonfun$concat$1."<init>":(Lscala/collection/generic/TraversableFactory;Lscala/collection/mutable/Builder;)V
	invokeinterface	InterfaceMethod scala/collection/IterableLike.foreach:(Lscala/Function1;)V
	aload_2
	invokeinterface	InterfaceMethod scala/collection/mutable/Builder.result:()Ljava/lang/Object;
	checkcast	class scala/collection/Traversable
	areturn
  Labels:
  LocalVariableTable: 
   Start  Length  Slot  Name   Signature
   0      30      0    this       Lscala/collection/generic/TraversableFactory;
   0      30      1    xss       Lscala/collection/Seq;
   5      24      2    b$1       Lscala/collection/mutable/Builder;

  Signature: length = 0x2
   00 28 

public scala.collection.Traversable fill(int, scala.Function0);
  Signature: (ILscala/Function0;)Lscala/collection/Traversable;
  Code:
   Stack=2, Locals=5, Args_size=3
	aload_0
	invokevirtual	Method newBuilder:()Lscala/collection/mutable/Builder;
	astore_3
	iconst_0
	istore	4
l2	iload	4
	iload_1
	if_icmpge	l1 // aload_3
	aload_3
	aload_2
	invokeinterface	InterfaceMethod scala/Function0.apply:()Ljava/lang/Object;
	invokeinterface	InterfaceMethod scala/collection/mutable/Builder.$plus$eq:(Ljava/lang/Object;)Lscala/collection/mutable/Builder;
	pop
	iload	4
	iconst_1
	iadd
	istore	4
	goto	l2 // iload
l1	aload_3
	invokeinterface	InterfaceMethod scala/collection/mutable/Builder.result:()Ljava/lang/Object;
	checkcast	class scala/collection/Traversable
	areturn
  Labels:
   	l2 = 8 // iload
   	l1 = 36 // aload_3
  LocalVariableTable: 
   Start  Length  Slot  Name   Signature
   0      46      0    this       Lscala/collection/generic/TraversableFactory;
   0      46      1    n       I
   0      46      2    elem       Lscala/Function0;
   5      40      3    b       Lscala/collection/mutable/Builder;
   8      37      4    i       I

  Signature: length = 0x2
   00 3B 

public scala.collection.Traversable fill(int, int, scala.Function0);
  Signature: (IILscala/Function0;)Lscala/collection/Traversable;
  Code:
   Stack=7, Locals=4, Args_size=4
	aload_0
	iload_1
	new	class scala/collection/generic/TraversableFactory$$anonfun$fill$1
	dup
	aload_0
	iload_2
	aload_3
	invokespecial	Method scala/collection/generic/TraversableFactory$$anonfun$fill$1."<init>":(Lscala/collection/generic/TraversableFactory;ILscala/Function0;)V
	invokevirtual	Method tabulate:(ILscala/Function1;)Lscala/collection/Traversable;
	areturn
  Labels:
  LocalVariableTable: 
   Start  Length  Slot  Name   Signature
   0      16      0    this       Lscala/collection/generic/TraversableFactory;
   0      16      1    n1       I
   0      16      2    n2$4       I
   0      16      3    elem$4       Lscala/Function0;

  Signature: length = 0x2
   00 49 

public scala.collection.Traversable fill(int, int, int, scala.Function0);
  Signature: (IIILscala/Function0;)Lscala/collection/Traversable;
  Code:
   Stack=8, Locals=5, Args_size=5
	aload_0
	iload_1
	new	class scala/collection/generic/TraversableFactory$$anonfun$fill$2
	dup
	aload_0
	iload_2
	iload_3
	aload	4
	invokespecial	Method scala/collection/generic/TraversableFactory$$anonfun$fill$2."<init>":(Lscala/collection/generic/TraversableFactory;IILscala/Function0;)V
	invokevirtual	Method tabulate:(ILscala/Function1;)Lscala/collection/Traversable;
	areturn
  Labels:
  LocalVariableTable: 
   Start  Length  Slot  Name   Signature
   0      18      0    this       Lscala/collection/generic/TraversableFactory;
   0      18      1    n1       I
   0      18      2    n2$3       I
   0      18      3    n3$3       I
   0      18      4    elem$3       Lscala/Function0;

  Signature: length = 0x2
   00 53 

public scala.collection.Traversable fill(int, int, int, int, scala.Function0);
  Signature: (IIIILscala/Function0;)Lscala/collection/Traversable;
  Code:
   Stack=9, Locals=6, Args_size=6
	aload_0
	iload_1
	new	class scala/collection/generic/TraversableFactory$$anonfun$fill$3
	dup
	aload_0
	iload_2
	iload_3
	iload	4
	aload	5
	invokespecial	Method scala/collection/generic/TraversableFactory$$anonfun$fill$3."<init>":(Lscala/collection/generic/TraversableFactory;IIILscala/Function0;)V
	invokevirtual	Method tabulate:(ILscala/Function1;)Lscala/collection/Traversable;
	areturn
  Labels:
  LocalVariableTable: 
   Start  Length  Slot  Name   Signature
   0      20      0    this       Lscala/collection/generic/TraversableFactory;
   0      20      1    n1       I
   0      20      2    n2$2       I
   0      20      3    n3$2       I
   0      20      4    n4$2       I
   0      20      5    elem$2       Lscala/Function0;

  Signature: length = 0x2
   00 5E 

public scala.collection.Traversable fill(int, int, int, int, int, scala.Function0);
  Signature: (IIIIILscala/Function0;)Lscala/collection/Traversable;
  Code:
   Stack=10, Locals=7, Args_size=7
	aload_0
	iload_1
	new	class scala/collection/generic/TraversableFactory$$anonfun$fill$4
	dup
	aload_0
	iload_2
	iload_3
	iload	4
	iload	5
	aload	6
	invokespecial	Method scala/collection/generic/TraversableFactory$$anonfun$fill$4."<init>":(Lscala/collection/generic/TraversableFactory;IIIILscala/Function0;)V
	invokevirtual	Method tabulate:(ILscala/Function1;)Lscala/collection/Traversable;
	areturn
  Labels:
  LocalVariableTable: 
   Start  Length  Slot  Name   Signature
   0      22      0    this       Lscala/collection/generic/TraversableFactory;
   0      22      1    n1       I
   0      22      2    n2$1       I
   0      22      3    n3$1       I
   0      22      4    n4$1       I
   0      22      5    n5$1       I
   0      22      6    elem$1       Lscala/Function0;

  Signature: length = 0x2
   00 6A 

public scala.collection.Traversable tabulate(int, scala.Function1);
  Signature: (ILscala/Function1;)Lscala/collection/Traversable;
  Code:
   Stack=3, Locals=5, Args_size=3
	aload_0
	invokevirtual	Method newBuilder:()Lscala/collection/mutable/Builder;
	astore	4
	iconst_0
	istore_3
l2	iload_3
	iload_1
	if_icmpge	l1 // aload
	aload	4
	aload_2
	iload_3
	invokestatic	Method scala/runtime/BoxesRunTime.boxToInteger:(I)Ljava/lang/Integer;
	invokeinterface	InterfaceMethod scala/Function1.apply:(Ljava/lang/Object;)Ljava/lang/Object;
	invokeinterface	InterfaceMethod scala/collection/mutable/Builder.$plus$eq:(Ljava/lang/Object;)Lscala/collection/mutable/Builder;
	pop
	iload_3
	iconst_1
	iadd
	istore_3
	goto	l2 // iload_3
l1	aload	4
	invokeinterface	InterfaceMethod scala/collection/mutable/Builder.result:()Ljava/lang/Object;
	checkcast	class scala/collection/Traversable
	areturn
  Labels:
   	l2 = 8 // iload_3
   	l1 = 38 // aload
  LocalVariableTable: 
   Start  Length  Slot  Name   Signature
   0      49      0    this       Lscala/collection/generic/TraversableFactory;
   0      49      1    n       I
   0      49      2    f       Lscala/Function1;
   8      40      3    i       I
   6      42      4    b       Lscala/collection/mutable/Builder;

  Signature: length = 0x2
   00 78 

public scala.collection.Traversable tabulate(int, int, scala.Function2);
  Signature: (IILscala/Function2;)Lscala/collection/Traversable;
  Code:
   Stack=7, Locals=4, Args_size=4
	aload_0
	iload_1
	new	class scala/collection/generic/TraversableFactory$$anonfun$tabulate$1
	dup
	aload_0
	iload_2
	aload_3
	invokespecial	Method scala/collection/generic/TraversableFactory$$anonfun$tabulate$1."<init>":(Lscala/collection/generic/TraversableFactory;ILscala/Function2;)V
	invokevirtual	Method tabulate:(ILscala/Function1;)Lscala/collection/Traversable;
	areturn
  Labels:
  LocalVariableTable: 
   Start  Length  Slot  Name   Signature
   0      16      0    this       Lscala/collection/generic/TraversableFactory;
   0      16      1    n1       I
   0      16      2    n2$8       I
   0      16      3    f$4       Lscala/Function2;

  Signature: length = 0x2
   00 FFFFFF82 

public scala.collection.Traversable tabulate(int, int, int, scala.Function3);
  Signature: (IIILscala/Function3;)Lscala/collection/Traversable;
  Code:
   Stack=8, Locals=5, Args_size=5
	aload_0
	iload_1
	new	class scala/collection/generic/TraversableFactory$$anonfun$tabulate$2
	dup
	aload_0
	iload_2
	iload_3
	aload	4
	invokespecial	Method scala/collection/generic/TraversableFactory$$anonfun$tabulate$2."<init>":(Lscala/collection/generic/TraversableFactory;IILscala/Function3;)V
	invokevirtual	Method tabulate:(ILscala/Function1;)Lscala/collection/Traversable;
	areturn
  Labels:
  LocalVariableTable: 
   Start  Length  Slot  Name   Signature
   0      18      0    this       Lscala/collection/generic/TraversableFactory;
   0      18      1    n1       I
   0      18      2    n2$7       I
   0      18      3    n3$6       I
   0      18      4    f$3       Lscala/Function3;

  Signature: length = 0x2
   00 FFFFFF8D 

public scala.collection.Traversable tabulate(int, int, int, int, scala.Function4);
  Signature: (IIIILscala/Function4;)Lscala/collection/Traversable;
  Code:
   Stack=9, Locals=6, Args_size=6
	aload_0
	iload_1
	new	class scala/collection/generic/TraversableFactory$$anonfun$tabulate$3
	dup
	aload_0
	iload_2
	iload_3
	iload	4
	aload	5
	invokespecial	Method scala/collection/generic/TraversableFactory$$anonfun$tabulate$3."<init>":(Lscala/collection/generic/TraversableFactory;IIILscala/Function4;)V
	invokevirtual	Method tabulate:(ILscala/Function1;)Lscala/collection/Traversable;
	areturn
  Labels:
  LocalVariableTable: 
   Start  Length  Slot  Name   Signature
   0      20      0    this       Lscala/collection/generic/TraversableFactory;
   0      20      1    n1       I
   0      20      2    n2$6       I
   0      20      3    n3$5       I
   0      20      4    n4$4       I
   0      20      5    f$2       Lscala/Function4;

  Signature: length = 0x2
   00 FFFFFF99 

public scala.collection.Traversable tabulate(int, int, int, int, int, scala.Function5);
  Signature: (IIIIILscala/Function5;)Lscala/collection/Traversable;
  Code:
   Stack=10, Locals=7, Args_size=7
	aload_0
	iload_1
	new	class scala/collection/generic/TraversableFactory$$anonfun$tabulate$4
	dup
	aload_0
	iload_2
	iload_3
	iload	4
	iload	5
	aload	6
	invokespecial	Method scala/collection/generic/TraversableFactory$$anonfun$tabulate$4."<init>":(Lscala/collection/generic/TraversableFactory;IIIILscala/Function5;)V
	invokevirtual	Method tabulate:(ILscala/Function1;)Lscala/collection/Traversable;
	areturn
  Labels:
  LocalVariableTable: 
   Start  Length  Slot  Name   Signature
   0      22      0    this       Lscala/collection/generic/TraversableFactory;
   0      22      1    n1       I
   0      22      2    n2$5       I
   0      22      3    n3$4       I
   0      22      4    n4$3       I
   0      22      5    n5$2       I
   0      22      6    f$1       Lscala/Function5;

  Signature: length = 0x2
   00 FFFFFFA6 

public scala.collection.Traversable range(int, int);
  Signature: (II)Lscala/collection/Traversable;
  Code:
   Stack=4, Locals=3, Args_size=3
	aload_0
	iload_1
	iload_2
	iconst_1
	invokevirtual	Method range:(III)Lscala/collection/Traversable;
	areturn
  Labels:
  LocalVariableTable: 
   Start  Length  Slot  Name   Signature
   0      8      0    this       Lscala/collection/generic/TraversableFactory;
   0      8      1    start       I
   0      8      2    end       I

  Signature: length = 0x2
   00 FFFFFFAE 

public scala.collection.Traversable range(int, int, int);
  Signature: (III)Lscala/collection/Traversable;
  Code:
   Stack=3, Locals=6, Args_size=4
	iload_3
	iconst_0
	if_icmpne	l1 // aload_0
	new	class java/lang/IllegalArgumentException
	dup
	ldc	String zero step
	invokespecial	Method java/lang/IllegalArgumentException."<init>":(Ljava/lang/String;)V
	athrow
l1	aload_0
	invokevirtual	Method newBuilder:()Lscala/collection/mutable/Builder;
	astore	5
	iload_1
	istore	4
l7	iload_3
	iconst_0
	if_icmpge	l2 // iload
	iload_2
	iload	4
	if_icmpge	l3 // iconst_0
	iconst_1
	goto	l4 // ifeq
l3	iconst_0
	goto	l4 // ifeq
l2	iload	4
	iload_2
	if_icmpge	l5 // iconst_0
	iconst_1
	goto	l4 // ifeq
l5	iconst_0
l4	ifeq	l6 // aload
	aload	5
	iload	4
	invokestatic	Method scala/runtime/BoxesRunTime.boxToInteger:(I)Ljava/lang/Integer;
	invokeinterface	InterfaceMethod scala/collection/mutable/Builder.$plus$eq:(Ljava/lang/Object;)Lscala/collection/mutable/Builder;
	pop
	iload	4
	iload_3
	iadd
	istore	4
	goto	l7 // iload_3
l6	aload	5
	invokeinterface	InterfaceMethod scala/collection/mutable/Builder.result:()Ljava/lang/Object;
	checkcast	class scala/collection/Traversable
	areturn
  Labels:
   	l1 = 15 // aload_0
   	l7 = 24 // iload_3
   	l3 = 39 // iconst_0
   	l2 = 43 // iload
   	l5 = 53 // iconst_0
   	l4 = 54 // ifeq
   	l6 = 79 // aload
  LocalVariableTable: 
   Start  Length  Slot  Name   Signature
   0      90      0    this       Lscala/collection/generic/TraversableFactory;
   0      90      1    start       I
   0      90      2    end       I
   0      90      3    step       I
   24      65      4    i       I
   21      68      5    b       Lscala/collection/mutable/Builder;

  Signature: length = 0x2
   00 FFFFFFB7 

public scala.collection.Traversable iterate(java.lang.Object, int, scala.Function1);
  Signature: (Ljava/lang/Object;ILscala/Function1;)Lscala/collection/Traversable;
  Code:
   Stack=2, Locals=7, Args_size=4
	aload_0
	invokevirtual	Method newBuilder:()Lscala/collection/mutable/Builder;
	astore	4
	aload_1
	astore	5
	iconst_0
	istore	6
l2	iload	6
	iload_2
	if_icmpge	l1 // aload
	aload	4
	aload	5
	invokeinterface	InterfaceMethod scala/collection/mutable/Builder.$plus$eq:(Ljava/lang/Object;)Lscala/collection/mutable/Builder;
	pop
	aload_3
	aload	5
	invokeinterface	InterfaceMethod scala/Function1.apply:(Ljava/lang/Object;)Ljava/lang/Object;
	astore	5
	iload	6
	iconst_1
	iadd
	istore	6
	goto	l2 // iload
l1	aload	4
	invokeinterface	InterfaceMethod scala/collection/mutable/Builder.result:()Ljava/lang/Object;
	checkcast	class scala/collection/Traversable
	areturn
  Labels:
   	l2 = 12 // iload
   	l1 = 47 // aload
  LocalVariableTable: 
   Start  Length  Slot  Name   Signature
   0      58      0    this       Lscala/collection/generic/TraversableFactory;
   0      58      1    start       Ljava/lang/Object;
   0      58      2    len       I
   0      58      3    f       Lscala/Function1;
   6      51      4    b       Lscala/collection/mutable/Builder;
   9      48      5    acc       Ljava/lang/Object;
   12      45      6    i       I

  Signature: length = 0x2
   00 FFFFFFBD 

public scala.collection.generic.TraversableFactory();
  Signature: ()V
  Code:
   Stack=1, Locals=1, Args_size=1
	aload_0
	invokespecial	Method scala/collection/generic/GenericCompanion."<init>":()V
	return
  Labels:
  Signature: length = 0x2
   00 FFFFFFBE 

}

