Compiled from "TraversableFactory.scala"
public class scala.collection.generic.TraversableFactory$GenericCanBuildFrom extends java.lang.Object implements scala.collection.generic.CanBuildFrom,scala.ScalaObject
  SourceFile: "TraversableFactory.scala"
  Signature: length = 0x2
   00 35 
  Scala: length = 0x
   
  InnerClass: 
   public GenericCanBuildFrom=class scala/collection/generic/TraversableFactory$GenericCanBuildFrom of class scala/collection/generic/TraversableFactory
  minor version: 0
  major version: 49
  Constant pool:
Asciz	SourceFile;
Asciz	TraversableFactory.scala;
Asciz	$outer;
Asciz	Lscala/collection/generic/TraversableFactory;;
Asciz	<init>;
Asciz	(Lscala/collection/generic/TraversableFactory;)V;
Asciz	Code;
Asciz	LineNumberTable;
Asciz	java/lang/NullPointerException;
class	java/lang/NullPointerException
Asciz	()V;
NameAndType	"<init>":()V
Method	java/lang/NullPointerException."<init>":()V
Asciz	scala/collection/generic/TraversableFactory$GenericCanBuildFrom;
class	scala/collection/generic/TraversableFactory$GenericCanBuildFrom
NameAndType	$outer:Lscala/collection/generic/TraversableFactory;
Field	scala/collection/generic/TraversableFactory$GenericCanBuildFrom.$outer:Lscala/collection/generic/TraversableFactory;
Asciz	java/lang/Object;
class	java/lang/Object
Method	java/lang/Object."<init>":()V
Asciz	this;
Asciz	Lscala/collection/generic/TraversableFactory$GenericCanBuildFrom;;
Asciz	LocalVariableTable;
Asciz	(Lscala/collection/generic/TraversableFactory<TCC;>;)V;
Asciz	Signature;
Asciz	apply;
Asciz	(Ljava/lang/Object;)Lscala/collection/mutable/Builder;;
Asciz	scala/collection/Traversable;
class	scala/collection/Traversable
Asciz	(Lscala/collection/Traversable;)Lscala/collection/mutable/Builder;;
NameAndType	apply:(Lscala/collection/Traversable;)Lscala/collection/mutable/Builder;
Method	scala/collection/generic/TraversableFactory$GenericCanBuildFrom.apply:(Lscala/collection/Traversable;)Lscala/collection/mutable/Builder;
Asciz	from;
Asciz	Ljava/lang/Object;;
Asciz	scala$collection$generic$TraversableFactory$GenericCanBuildFrom$$$outer;
Asciz	()Lscala/collection/generic/TraversableFactory;;
Asciz	()Lscala/collection/mutable/Builder;;
NameAndType	scala$collection$generic$TraversableFactory$GenericCanBuildFrom$$$outer:()Lscala/collection/generic/TraversableFactory;
Method	scala/collection/generic/TraversableFactory$GenericCanBuildFrom.scala$collection$generic$TraversableFactory$GenericCanBuildFrom$$$outer:()Lscala/collection/generic/TraversableFactory;
Asciz	scala/collection/generic/TraversableFactory;
class	scala/collection/generic/TraversableFactory
Asciz	newBuilder;
NameAndType	newBuilder:()Lscala/collection/mutable/Builder;
Method	scala/collection/generic/TraversableFactory.newBuilder:()Lscala/collection/mutable/Builder;
Asciz	()Lscala/collection/mutable/Builder<TA;TCC;>;;
Asciz	scala/collection/generic/GenericTraversableTemplate;
class	scala/collection/generic/GenericTraversableTemplate
Asciz	genericBuilder;
NameAndType	genericBuilder:()Lscala/collection/mutable/Builder;
InterfaceMethod	scala/collection/generic/GenericTraversableTemplate.genericBuilder:()Lscala/collection/mutable/Builder;
Asciz	Lscala/collection/Traversable;;
Asciz	(TCC;)Lscala/collection/mutable/Builder<TA;TCC;>;;
Asciz	<A:Ljava/lang/Object;>Ljava/lang/Object;Lscala/collection/generic/CanBuildFrom<TCC;TA;TCC;>;Lscala/ScalaObject;;
Asciz	Scala;
Asciz	InnerClasses;
Asciz	GenericCanBuildFrom;
Asciz	scala/collection/generic/CanBuildFrom;
class	scala/collection/generic/CanBuildFrom
Asciz	scala/ScalaObject;
class	scala/ScalaObject

{
public final scala.collection.generic.TraversableFactory $outer;
  Signature: Lscala/collection/generic/TraversableFactory;

public scala.collection.generic.TraversableFactory$GenericCanBuildFrom(scala.collection.generic.TraversableFactory);
  Signature: (Lscala/collection/generic/TraversableFactory;)V
  Code:
   Stack=2, Locals=2, Args_size=2
	aload_1
	ifnonnull	l1 // aload_0
	new	class java/lang/NullPointerException
	dup
	invokespecial	Method java/lang/NullPointerException."<init>":()V
	athrow
l1	aload_0
	aload_1
	putfield	Field $outer:Lscala/collection/generic/TraversableFactory;
	aload_0
	invokespecial	Method java/lang/Object."<init>":()V
	return
  Labels:
   	l1 = 12 // aload_0
  LocalVariableTable: 
   Start  Length  Slot  Name   Signature
   0      22      0    this       Lscala/collection/generic/TraversableFactory$GenericCanBuildFrom;
   0      22      1    $outer       Lscala/collection/generic/TraversableFactory;

  Signature: length = 0x2
   00 18 

public scala.collection.mutable.Builder apply(java.lang.Object);
  Signature: (Ljava/lang/Object;)Lscala/collection/mutable/Builder;
  Code:
   Stack=2, Locals=2, Args_size=2
	aload_0
	aload_1
	checkcast	class scala/collection/Traversable
	invokevirtual	Method apply:(Lscala/collection/Traversable;)Lscala/collection/mutable/Builder;
	areturn
  Labels:
  LocalVariableTable: 
   Start  Length  Slot  Name   Signature
   0      9      0    this       Lscala/collection/generic/TraversableFactory$GenericCanBuildFrom;
   0      9      1    from       Ljava/lang/Object;


public scala.collection.generic.TraversableFactory scala$collection$generic$TraversableFactory$GenericCanBuildFrom$$$outer();
  Signature: ()Lscala/collection/generic/TraversableFactory;
  Code:
   Stack=1, Locals=1, Args_size=1
	aload_0
	getfield	Field $outer:Lscala/collection/generic/TraversableFactory;
	areturn
  Labels:

public scala.collection.mutable.Builder apply();
  Signature: ()Lscala/collection/mutable/Builder;
  Code:
   Stack=1, Locals=1, Args_size=1
	aload_0
	invokevirtual	Method scala$collection$generic$TraversableFactory$GenericCanBuildFrom$$$outer:()Lscala/collection/generic/TraversableFactory;
	invokevirtual	Method scala/collection/generic/TraversableFactory.newBuilder:()Lscala/collection/mutable/Builder;
	areturn
  Labels:
  Signature: length = 0x2
   00 2D 

public scala.collection.mutable.Builder apply(scala.collection.Traversable);
  Signature: (Lscala/collection/Traversable;)Lscala/collection/mutable/Builder;
  Code:
   Stack=1, Locals=2, Args_size=2
	aload_1
	invokeinterface	InterfaceMethod scala/collection/generic/GenericTraversableTemplate.genericBuilder:()Lscala/collection/mutable/Builder;
	areturn
  Labels:
  LocalVariableTable: 
   Start  Length  Slot  Name   Signature
   0      7      0    this       Lscala/collection/generic/TraversableFactory$GenericCanBuildFrom;
   0      7      1    from       Lscala/collection/Traversable;

  Signature: length = 0x2
   00 34 

}

