Compiled from "TraversableFactory.scala"
public final class scala.collection.generic.TraversableFactory$$anonfun$tabulate$4 extends java.lang.Object implements scala.Function1,scala.ScalaObject,java.io.Serializable
  SourceFile: "TraversableFactory.scala"
  Scala: length = 0x
   
  InnerClass: 
   public final $anonfun$tabulate$4=class scala/collection/generic/TraversableFactory$$anonfun$tabulate$4 of class scala/collection/generic/TraversableFactory
   public final $anonfun$apply$4=class scala/collection/generic/TraversableFactory$$anonfun$tabulate$4$$anonfun$apply$4 of class scala/collection/generic/TraversableFactory$$anonfun$tabulate$4
  minor version: 0
  major version: 49
  Constant pool:
Asciz	SourceFile;
Asciz	TraversableFactory.scala;
Asciz	<clinit>;
Asciz	()V;
Asciz	Code;
Asciz	serialVersionUID;
Asciz	J;
Asciz	scala/collection/generic/TraversableFactory$$anonfun$tabulate$4;
class	scala/collection/generic/TraversableFactory$$anonfun$tabulate$4
NameAndType	serialVersionUID:J
Field	scala/collection/generic/TraversableFactory$$anonfun$tabulate$4.serialVersionUID:J
Asciz	f$1;
Asciz	Lscala/Function5;;
Asciz	n5$2;
Asciz	I;
Asciz	n4$3;
Asciz	n3$4;
Asciz	n2$5;
Asciz	$outer;
Asciz	Lscala/collection/generic/TraversableFactory;;
Asciz	<init>;
Asciz	(Lscala/collection/generic/TraversableFactory;IIIILscala/Function5;)V;
Asciz	LineNumberTable;
Asciz	java/lang/NullPointerException;
class	java/lang/NullPointerException
NameAndType	"<init>":()V
Method	java/lang/NullPointerException."<init>":()V
NameAndType	$outer:Lscala/collection/generic/TraversableFactory;
Field	scala/collection/generic/TraversableFactory$$anonfun$tabulate$4.$outer:Lscala/collection/generic/TraversableFactory;
NameAndType	n2$5:I
Field	scala/collection/generic/TraversableFactory$$anonfun$tabulate$4.n2$5:I
NameAndType	n3$4:I
Field	scala/collection/generic/TraversableFactory$$anonfun$tabulate$4.n3$4:I
NameAndType	n4$3:I
Field	scala/collection/generic/TraversableFactory$$anonfun$tabulate$4.n4$3:I
NameAndType	n5$2:I
Field	scala/collection/generic/TraversableFactory$$anonfun$tabulate$4.n5$2:I
NameAndType	f$1:Lscala/Function5;
Field	scala/collection/generic/TraversableFactory$$anonfun$tabulate$4.f$1:Lscala/Function5;
Asciz	java/lang/Object;
class	java/lang/Object
Method	java/lang/Object."<init>":()V
Asciz	scala/Function1$class;
class	scala/Function1$class
Asciz	$init$;
Asciz	(Lscala/Function1;)V;
NameAndType	$init$:(Lscala/Function1;)V
Method	scala/Function1$class.$init$:(Lscala/Function1;)V
Asciz	this;
Asciz	Lscala/collection/generic/TraversableFactory$$anonfun$tabulate$4;;
Asciz	LocalVariableTable;
Asciz	(Lscala/collection/generic/TraversableFactory<TCC;>;)V;
Asciz	Signature;
Asciz	apply;
Asciz	(Ljava/lang/Object;)Ljava/lang/Object;;
Asciz	scala/runtime/BoxesRunTime;
class	scala/runtime/BoxesRunTime
Asciz	unboxToInt;
Asciz	(Ljava/lang/Object;)I;
NameAndType	unboxToInt:(Ljava/lang/Object;)I
Method	scala/runtime/BoxesRunTime.unboxToInt:(Ljava/lang/Object;)I
Asciz	(I)Lscala/collection/Traversable;;
NameAndType	apply:(I)Lscala/collection/Traversable;
Method	scala/collection/generic/TraversableFactory$$anonfun$tabulate$4.apply:(I)Lscala/collection/Traversable;
Asciz	v1;
Asciz	Ljava/lang/Object;;
Asciz	scala/collection/generic/TraversableFactory$$anonfun$tabulate$4$$anonfun$apply$4;
class	scala/collection/generic/TraversableFactory$$anonfun$tabulate$4$$anonfun$apply$4
Asciz	(Lscala/collection/generic/TraversableFactory$$anonfun$tabulate$4;I)V;
NameAndType	"<init>":(Lscala/collection/generic/TraversableFactory$$anonfun$tabulate$4;I)V
Method	scala/collection/generic/TraversableFactory$$anonfun$tabulate$4$$anonfun$apply$4."<init>":(Lscala/collection/generic/TraversableFactory$$anonfun$tabulate$4;I)V
Asciz	scala/collection/generic/TraversableFactory;
class	scala/collection/generic/TraversableFactory
Asciz	tabulate;
Asciz	(IIIILscala/Function4;)Lscala/collection/Traversable;;
NameAndType	tabulate:(IIIILscala/Function4;)Lscala/collection/Traversable;
Method	scala/collection/generic/TraversableFactory.tabulate:(IIIILscala/Function4;)Lscala/collection/Traversable;
Asciz	i1$4;
Asciz	(I)TCC;;
Asciz	andThen;
Asciz	(Lscala/Function1;)Lscala/Function1;;
Asciz	(Lscala/Function1;Lscala/Function1;)Lscala/Function1;;
NameAndType	andThen:(Lscala/Function1;Lscala/Function1;)Lscala/Function1;
Method	scala/Function1$class.andThen:(Lscala/Function1;Lscala/Function1;)Lscala/Function1;
Asciz	g;
Asciz	Lscala/Function1;;
Asciz	compose;
NameAndType	compose:(Lscala/Function1;Lscala/Function1;)Lscala/Function1;
Method	scala/Function1$class.compose:(Lscala/Function1;Lscala/Function1;)Lscala/Function1;
Asciz	toString;
Asciz	()Ljava/lang/String;;
Asciz	(Lscala/Function1;)Ljava/lang/String;;
NameAndType	toString:(Lscala/Function1;)Ljava/lang/String;
Method	scala/Function1$class.toString:(Lscala/Function1;)Ljava/lang/String;
Asciz	Scala;
Asciz	InnerClasses;
Asciz	$anonfun$tabulate$4;
Asciz	$anonfun$apply$4;
Asciz	scala/Function1;
class	scala/Function1
Asciz	scala/ScalaObject;
class	scala/ScalaObject
Asciz	java/io/Serializable;
class	java/io/Serializable

{
public static final long serialVersionUID;
  Signature: J

public final scala.Function5 f$1;
  Signature: Lscala/Function5;

private final int n5$2;
  Signature: I

private final int n4$3;
  Signature: I

private final int n3$4;
  Signature: I

private final int n2$5;
  Signature: I

private final scala.collection.generic.TraversableFactory $outer;
  Signature: Lscala/collection/generic/TraversableFactory;

public static {};
  Signature: ()V
  Code:
   Stack=2, Locals=0, Args_size=0
	lconst_0
	putstatic	Field serialVersionUID:J
	return
  Labels:

public scala.collection.generic.TraversableFactory$$anonfun$tabulate$4(scala.collection.generic.TraversableFactory, int, int, int, int, scala.Function5);
  Signature: (Lscala/collection/generic/TraversableFactory;IIIILscala/Function5;)V
  Code:
   Stack=2, Locals=7, Args_size=7
	aload_1
	ifnonnull	l1 // aload_0
	new	class java/lang/NullPointerException
	dup
	invokespecial	Method java/lang/NullPointerException."<init>":()V
	athrow
l1	aload_0
	aload_1
	putfield	Field $outer:Lscala/collection/generic/TraversableFactory;
	aload_0
	iload_2
	putfield	Field n2$5:I
	aload_0
	iload_3
	putfield	Field n3$4:I
	aload_0
	iload	4
	putfield	Field n4$3:I
	aload_0
	iload	5
	putfield	Field n5$2:I
	aload_0
	aload	6
	putfield	Field f$1:Lscala/Function5;
	aload_0
	invokespecial	Method java/lang/Object."<init>":()V
	aload_0
	invokestatic	Method scala/Function1$class.$init$:(Lscala/Function1;)V
	return
  Labels:
   	l1 = 12 // aload_0
  LocalVariableTable: 
   Start  Length  Slot  Name   Signature
   0      54      0    this       Lscala/collection/generic/TraversableFactory$$anonfun$tabulate$4;
   0      54      1    $outer       Lscala/collection/generic/TraversableFactory;

  Signature: length = 0x2
   00 34 

public final java.lang.Object apply(java.lang.Object);
  Signature: (Ljava/lang/Object;)Ljava/lang/Object;
  Code:
   Stack=2, Locals=3, Args_size=2
	aload_0
	getfield	Field $outer:Lscala/collection/generic/TraversableFactory;
	astore_2
	aload_0
	aload_1
	invokestatic	Method scala/runtime/BoxesRunTime.unboxToInt:(Ljava/lang/Object;)I
	invokevirtual	Method apply:(I)Lscala/collection/Traversable;
	areturn
  Labels:
  LocalVariableTable: 
   Start  Length  Slot  Name   Signature
   0      14      0    this       Lscala/collection/generic/TraversableFactory$$anonfun$tabulate$4;
   5      9      1    v1       Ljava/lang/Object;


public final scala.collection.Traversable apply(int);
  Signature: (I)Lscala/collection/Traversable;
  Code:
   Stack=9, Locals=3, Args_size=2
	aload_0
	getfield	Field $outer:Lscala/collection/generic/TraversableFactory;
	astore_2
	aload_0
	getfield	Field $outer:Lscala/collection/generic/TraversableFactory;
	aload_0
	getfield	Field n2$5:I
	aload_0
	getfield	Field n3$4:I
	aload_0
	getfield	Field n4$3:I
	aload_0
	getfield	Field n5$2:I
	new	class scala/collection/generic/TraversableFactory$$anonfun$tabulate$4$$anonfun$apply$4
	dup
	aload_0
	iload_1
	invokespecial	Method scala/collection/generic/TraversableFactory$$anonfun$tabulate$4$$anonfun$apply$4."<init>":(Lscala/collection/generic/TraversableFactory$$anonfun$tabulate$4;I)V
	invokevirtual	Method scala/collection/generic/TraversableFactory.tabulate:(IIIILscala/Function4;)Lscala/collection/Traversable;
	areturn
  Labels:
  LocalVariableTable: 
   Start  Length  Slot  Name   Signature
   0      38      0    this       Lscala/collection/generic/TraversableFactory$$anonfun$tabulate$4;
   5      33      1    i1$4       I

  Signature: length = 0x2
   00 4F 

public scala.Function1 andThen(scala.Function1);
  Signature: (Lscala/Function1;)Lscala/Function1;
  Code:
   Stack=2, Locals=2, Args_size=2
	aload_0
	aload_1
	invokestatic	Method scala/Function1$class.andThen:(Lscala/Function1;Lscala/Function1;)Lscala/Function1;
	areturn
  Labels:
  LocalVariableTable: 
   Start  Length  Slot  Name   Signature
   0      6      0    this       Lscala/collection/generic/TraversableFactory$$anonfun$tabulate$4;
   0      6      1    g       Lscala/Function1;


public scala.Function1 compose(scala.Function1);
  Signature: (Lscala/Function1;)Lscala/Function1;
  Code:
   Stack=2, Locals=2, Args_size=2
	aload_0
	aload_1
	invokestatic	Method scala/Function1$class.compose:(Lscala/Function1;Lscala/Function1;)Lscala/Function1;
	areturn
  Labels:
  LocalVariableTable: 
   Start  Length  Slot  Name   Signature
   0      6      0    this       Lscala/collection/generic/TraversableFactory$$anonfun$tabulate$4;
   0      6      1    g       Lscala/Function1;


public java.lang.String toString();
  Signature: ()Ljava/lang/String;
  Code:
   Stack=1, Locals=1, Args_size=1
	aload_0
	invokestatic	Method scala/Function1$class.toString:(Lscala/Function1;)Ljava/lang/String;
	areturn
  Labels:

}

