Compiled from "TraversableProxyTemplate.scala"
public abstract class scala.collection.generic.TraversableProxyTemplate$class extends java.lang.Object
  SourceFile: "TraversableProxyTemplate.scala"
  Scala: length = 0x
   
  minor version: 0
  major version: 49
  Constant pool:
const #1 = Asciz	SourceFile;
const #2 = Asciz	TraversableProxyTemplate.scala;
const #3 = Asciz	$init$;
const #4 = Asciz	(Lscala/collection/generic/TraversableProxyTemplate;)V;
const #5 = Asciz	Code;
const #6 = Asciz	LineNumberTable;
const #7 = Asciz	$this;
const #8 = Asciz	Lscala/collection/generic/TraversableProxyTemplate;;
const #9 = Asciz	LocalVariableTable;
const #10 = Asciz	view;
const #11 = Asciz	(Lscala/collection/generic/TraversableProxyTemplate;II)Lscala/collection/generic/TraversableView;;
const #12 = Asciz	scala/collection/generic/TraversableProxyTemplate;
const #13 = class	#12;	//  scala/collection/generic/TraversableProxyTemplate
const #14 = Asciz	self;
const #15 = Asciz	()Lscala/collection/generic/TraversableTemplate;;
const #16 = NameAndType	#14:#15;//  self:()Lscala/collection/generic/TraversableTemplate;
const #17 = InterfaceMethod	#13.#16;	//  scala/collection/generic/TraversableProxyTemplate.self:()Lscala/collection/generic/TraversableTemplate;
const #18 = Asciz	scala/collection/generic/TraversableTemplate;
const #19 = class	#18;	//  scala/collection/generic/TraversableTemplate
const #20 = Asciz	(II)Lscala/collection/generic/TraversableView;;
const #21 = NameAndType	#10:#20;//  view:(II)Lscala/collection/generic/TraversableView;
const #22 = InterfaceMethod	#19.#21;	//  scala/collection/generic/TraversableTemplate.view:(II)Lscala/collection/generic/TraversableView;
const #23 = Asciz	from;
const #24 = Asciz	I;
const #25 = Asciz	until;
const #26 = Asciz	(Lscala/collection/generic/TraversableProxyTemplate;)Ljava/lang/Object;;
const #27 = Asciz	()Ljava/lang/Object;;
const #28 = NameAndType	#10:#27;//  view:()Ljava/lang/Object;
const #29 = InterfaceMethod	#19.#28;	//  scala/collection/generic/TraversableTemplate.view:()Ljava/lang/Object;
const #30 = Asciz	stringPrefix;
const #31 = Asciz	(Lscala/collection/generic/TraversableProxyTemplate;)Ljava/lang/String;;
const #32 = Asciz	()Ljava/lang/String;;
const #33 = NameAndType	#30:#32;//  stringPrefix:()Ljava/lang/String;
const #34 = InterfaceMethod	#19.#33;	//  scala/collection/generic/TraversableTemplate.stringPrefix:()Ljava/lang/String;
const #35 = Asciz	addString;
const #36 = Asciz	(Lscala/collection/generic/TraversableProxyTemplate;Lscala/collection/mutable/StringBuilder;)Lscala/collection/mutable/StringBuilder;;
const #37 = Asciz	(Lscala/collection/mutable/StringBuilder;)Lscala/collection/mutable/StringBuilder;;
const #38 = NameAndType	#35:#37;//  addString:(Lscala/collection/mutable/StringBuilder;)Lscala/collection/mutable/StringBuilder;
const #39 = InterfaceMethod	#19.#38;	//  scala/collection/generic/TraversableTemplate.addString:(Lscala/collection/mutable/StringBuilder;)Lscala/collection/mutable/StringBuilder;
const #40 = Asciz	b;
const #41 = Asciz	Lscala/collection/mutable/StringBuilder;;
const #42 = Asciz	(Lscala/collection/generic/TraversableProxyTemplate;Lscala/collection/mutable/StringBuilder;Ljava/lang/String;)Lscala/collection/mutable/StringBuilder;;
const #43 = Asciz	(Lscala/collection/mutable/StringBuilder;Ljava/lang/String;)Lscala/collection/mutable/StringBuilder;;
const #44 = NameAndType	#35:#43;//  addString:(Lscala/collection/mutable/StringBuilder;Ljava/lang/String;)Lscala/collection/mutable/StringBuilder;
const #45 = InterfaceMethod	#19.#44;	//  scala/collection/generic/TraversableTemplate.addString:(Lscala/collection/mutable/StringBuilder;Ljava/lang/String;)Lscala/collection/mutable/StringBuilder;
const #46 = Asciz	sep;
const #47 = Asciz	Ljava/lang/String;;
const #48 = Asciz	(Lscala/collection/generic/TraversableProxyTemplate;Lscala/collection/mutable/StringBuilder;Ljava/lang/String;Ljava/lang/String;Ljava/lang/String;)Lscala/collection/mutable/StringBuilder;;
const #49 = Asciz	(Lscala/collection/mutable/StringBuilder;Ljava/lang/String;Ljava/lang/String;Ljava/lang/String;)Lscala/collection/mutable/StringBuilder;;
const #50 = NameAndType	#35:#49;//  addString:(Lscala/collection/mutable/StringBuilder;Ljava/lang/String;Ljava/lang/String;Ljava/lang/String;)Lscala/collection/mutable/StringBuilder;
const #51 = InterfaceMethod	#19.#50;	//  scala/collection/generic/TraversableTemplate.addString:(Lscala/collection/mutable/StringBuilder;Ljava/lang/String;Ljava/lang/String;Ljava/lang/String;)Lscala/collection/mutable/StringBuilder;
const #52 = Asciz	start;
const #53 = Asciz	end;
const #54 = Asciz	mkString;
const #55 = NameAndType	#54:#32;//  mkString:()Ljava/lang/String;
const #56 = InterfaceMethod	#19.#55;	//  scala/collection/generic/TraversableTemplate.mkString:()Ljava/lang/String;
const #57 = Asciz	(Lscala/collection/generic/TraversableProxyTemplate;Ljava/lang/String;)Ljava/lang/String;;
const #58 = Asciz	(Ljava/lang/String;)Ljava/lang/String;;
const #59 = NameAndType	#54:#58;//  mkString:(Ljava/lang/String;)Ljava/lang/String;
const #60 = InterfaceMethod	#19.#59;	//  scala/collection/generic/TraversableTemplate.mkString:(Ljava/lang/String;)Ljava/lang/String;
const #61 = Asciz	(Lscala/collection/generic/TraversableProxyTemplate;Ljava/lang/String;Ljava/lang/String;Ljava/lang/String;)Ljava/lang/String;;
const #62 = Asciz	(Ljava/lang/String;Ljava/lang/String;Ljava/lang/String;)Ljava/lang/String;;
const #63 = NameAndType	#54:#62;//  mkString:(Ljava/lang/String;Ljava/lang/String;Ljava/lang/String;)Ljava/lang/String;
const #64 = InterfaceMethod	#19.#63;	//  scala/collection/generic/TraversableTemplate.mkString:(Ljava/lang/String;Ljava/lang/String;Ljava/lang/String;)Ljava/lang/String;
const #65 = Asciz	toSet;
const #66 = Asciz	(Lscala/collection/generic/TraversableProxyTemplate;)Lscala/collection/immutable/Set;;
const #67 = Asciz	()Lscala/collection/immutable/Set;;
const #68 = NameAndType	#65:#67;//  toSet:()Lscala/collection/immutable/Set;
const #69 = InterfaceMethod	#19.#68;	//  scala/collection/generic/TraversableTemplate.toSet:()Lscala/collection/immutable/Set;
const #70 = Asciz	toStream;
const #71 = Asciz	(Lscala/collection/generic/TraversableProxyTemplate;)Lscala/collection/immutable/Stream;;
const #72 = Asciz	()Lscala/collection/immutable/Stream;;
const #73 = NameAndType	#70:#72;//  toStream:()Lscala/collection/immutable/Stream;
const #74 = InterfaceMethod	#19.#73;	//  scala/collection/generic/TraversableTemplate.toStream:()Lscala/collection/immutable/Stream;
const #75 = Asciz	toSequence;
const #76 = Asciz	(Lscala/collection/generic/TraversableProxyTemplate;)Lscala/collection/Sequence;;
const #77 = Asciz	()Lscala/collection/Sequence;;
const #78 = NameAndType	#75:#77;//  toSequence:()Lscala/collection/Sequence;
const #79 = InterfaceMethod	#19.#78;	//  scala/collection/generic/TraversableTemplate.toSequence:()Lscala/collection/Sequence;
const #80 = Asciz	toIterable;
const #81 = Asciz	(Lscala/collection/generic/TraversableProxyTemplate;)Lscala/collection/Iterable;;
const #82 = Asciz	()Lscala/collection/Iterable;;
const #83 = NameAndType	#80:#82;//  toIterable:()Lscala/collection/Iterable;
const #84 = InterfaceMethod	#19.#83;	//  scala/collection/generic/TraversableTemplate.toIterable:()Lscala/collection/Iterable;
const #85 = Asciz	toList;
const #86 = Asciz	(Lscala/collection/generic/TraversableProxyTemplate;)Lscala/collection/immutable/List;;
const #87 = Asciz	()Lscala/collection/immutable/List;;
const #88 = NameAndType	#85:#87;//  toList:()Lscala/collection/immutable/List;
const #89 = InterfaceMethod	#19.#88;	//  scala/collection/generic/TraversableTemplate.toList:()Lscala/collection/immutable/List;
const #90 = Asciz	toArray;
const #91 = Asciz	(Lscala/collection/generic/TraversableProxyTemplate;)Lscala/runtime/BoxedArray;;
const #92 = Asciz	()Lscala/runtime/BoxedArray;;
const #93 = NameAndType	#90:#92;//  toArray:()Lscala/runtime/BoxedArray;
const #94 = InterfaceMethod	#19.#93;	//  scala/collection/generic/TraversableTemplate.toArray:()Lscala/runtime/BoxedArray;
const #95 = Asciz	copyToArray;
const #96 = Asciz	(Lscala/collection/generic/TraversableProxyTemplate;Lscala/runtime/BoxedArray;I)V;
const #97 = Asciz	(Lscala/runtime/BoxedArray;I)V;
const #98 = NameAndType	#95:#97;//  copyToArray:(Lscala/runtime/BoxedArray;I)V
const #99 = InterfaceMethod	#19.#98;	//  scala/collection/generic/TraversableTemplate.copyToArray:(Lscala/runtime/BoxedArray;I)V
const #100 = Asciz	xs;
const #101 = Asciz	Lscala/runtime/BoxedArray;;
const #102 = Asciz	(Lscala/collection/generic/TraversableProxyTemplate;Lscala/runtime/BoxedArray;II)V;
const #103 = Asciz	(Lscala/runtime/BoxedArray;II)V;
const #104 = NameAndType	#95:#103;//  copyToArray:(Lscala/runtime/BoxedArray;II)V
const #105 = InterfaceMethod	#19.#104;	//  scala/collection/generic/TraversableTemplate.copyToArray:(Lscala/runtime/BoxedArray;II)V
const #106 = Asciz	len;
const #107 = Asciz	copyToBuffer;
const #108 = Asciz	(Lscala/collection/generic/TraversableProxyTemplate;Lscala/collection/mutable/Buffer;)V;
const #109 = Asciz	(Lscala/collection/mutable/Buffer;)V;
const #110 = NameAndType	#107:#109;//  copyToBuffer:(Lscala/collection/mutable/Buffer;)V
const #111 = InterfaceMethod	#19.#110;	//  scala/collection/generic/TraversableTemplate.copyToBuffer:(Lscala/collection/mutable/Buffer;)V
const #112 = Asciz	dest;
const #113 = Asciz	Lscala/collection/mutable/Buffer;;
const #114 = Asciz	splitAt;
const #115 = Asciz	(Lscala/collection/generic/TraversableProxyTemplate;I)Lscala/Tuple2;;
const #116 = Asciz	(I)Lscala/Tuple2;;
const #117 = NameAndType	#114:#116;//  splitAt:(I)Lscala/Tuple2;
const #118 = InterfaceMethod	#19.#117;	//  scala/collection/generic/TraversableTemplate.splitAt:(I)Lscala/Tuple2;
const #119 = Asciz	n;
const #120 = Asciz	span;
const #121 = Asciz	(Lscala/collection/generic/TraversableProxyTemplate;Lscala/Function1;)Lscala/Tuple2;;
const #122 = Asciz	(Lscala/Function1;)Lscala/Tuple2;;
const #123 = NameAndType	#120:#122;//  span:(Lscala/Function1;)Lscala/Tuple2;
const #124 = InterfaceMethod	#19.#123;	//  scala/collection/generic/TraversableTemplate.span:(Lscala/Function1;)Lscala/Tuple2;
const #125 = Asciz	p;
const #126 = Asciz	Lscala/Function1;;
const #127 = Asciz	dropWhile;
const #128 = Asciz	(Lscala/collection/generic/TraversableProxyTemplate;Lscala/Function1;)Lscala/collection/generic/TraversableTemplate;;
const #129 = Asciz	(Lscala/Function1;)Lscala/collection/generic/TraversableTemplate;;
const #130 = NameAndType	#127:#129;//  dropWhile:(Lscala/Function1;)Lscala/collection/generic/TraversableTemplate;
const #131 = InterfaceMethod	#19.#130;	//  scala/collection/generic/TraversableTemplate.dropWhile:(Lscala/Function1;)Lscala/collection/generic/TraversableTemplate;
const #132 = Asciz	takeWhile;
const #133 = NameAndType	#132:#129;//  takeWhile:(Lscala/Function1;)Lscala/collection/generic/TraversableTemplate;
const #134 = InterfaceMethod	#19.#133;	//  scala/collection/generic/TraversableTemplate.takeWhile:(Lscala/Function1;)Lscala/collection/generic/TraversableTemplate;
const #135 = Asciz	slice;
const #136 = Asciz	(Lscala/collection/generic/TraversableProxyTemplate;II)Lscala/collection/generic/TraversableTemplate;;
const #137 = Asciz	(II)Lscala/collection/generic/TraversableTemplate;;
const #138 = NameAndType	#135:#137;//  slice:(II)Lscala/collection/generic/TraversableTemplate;
const #139 = InterfaceMethod	#19.#138;	//  scala/collection/generic/TraversableTemplate.slice:(II)Lscala/collection/generic/TraversableTemplate;
const #140 = Asciz	drop;
const #141 = Asciz	(Lscala/collection/generic/TraversableProxyTemplate;I)Lscala/collection/generic/TraversableTemplate;;
const #142 = Asciz	(I)Lscala/collection/generic/TraversableTemplate;;
const #143 = NameAndType	#140:#142;//  drop:(I)Lscala/collection/generic/TraversableTemplate;
const #144 = InterfaceMethod	#19.#143;	//  scala/collection/generic/TraversableTemplate.drop:(I)Lscala/collection/generic/TraversableTemplate;
const #145 = Asciz	take;
const #146 = NameAndType	#145:#142;//  take:(I)Lscala/collection/generic/TraversableTemplate;
const #147 = InterfaceMethod	#19.#146;	//  scala/collection/generic/TraversableTemplate.take:(I)Lscala/collection/generic/TraversableTemplate;
const #148 = Asciz	init;
const #149 = Asciz	(Lscala/collection/generic/TraversableProxyTemplate;)Lscala/collection/generic/TraversableTemplate;;
const #150 = NameAndType	#148:#15;//  init:()Lscala/collection/generic/TraversableTemplate;
const #151 = InterfaceMethod	#19.#150;	//  scala/collection/generic/TraversableTemplate.init:()Lscala/collection/generic/TraversableTemplate;
const #152 = Asciz	lastOption;
const #153 = Asciz	(Lscala/collection/generic/TraversableProxyTemplate;)Lscala/Option;;
const #154 = Asciz	()Lscala/Option;;
const #155 = NameAndType	#152:#154;//  lastOption:()Lscala/Option;
const #156 = InterfaceMethod	#19.#155;	//  scala/collection/generic/TraversableTemplate.lastOption:()Lscala/Option;
const #157 = Asciz	last;
const #158 = NameAndType	#157:#27;//  last:()Ljava/lang/Object;
const #159 = InterfaceMethod	#19.#158;	//  scala/collection/generic/TraversableTemplate.last:()Ljava/lang/Object;
const #160 = Asciz	tail;
const #161 = NameAndType	#160:#15;//  tail:()Lscala/collection/generic/TraversableTemplate;
const #162 = InterfaceMethod	#19.#161;	//  scala/collection/generic/TraversableTemplate.tail:()Lscala/collection/generic/TraversableTemplate;
const #163 = Asciz	headOption;
const #164 = NameAndType	#163:#154;//  headOption:()Lscala/Option;
const #165 = InterfaceMethod	#19.#164;	//  scala/collection/generic/TraversableTemplate.headOption:()Lscala/Option;
const #166 = Asciz	head;
const #167 = NameAndType	#166:#27;//  head:()Ljava/lang/Object;
const #168 = InterfaceMethod	#19.#167;	//  scala/collection/generic/TraversableTemplate.head:()Ljava/lang/Object;
const #169 = Asciz	reduceRightOption;
const #170 = Asciz	(Lscala/collection/generic/TraversableProxyTemplate;Lscala/Function2;)Lscala/Option;;
const #171 = Asciz	(Lscala/Function2;)Lscala/Option;;
const #172 = NameAndType	#169:#171;//  reduceRightOption:(Lscala/Function2;)Lscala/Option;
const #173 = InterfaceMethod	#19.#172;	//  scala/collection/generic/TraversableTemplate.reduceRightOption:(Lscala/Function2;)Lscala/Option;
const #174 = Asciz	op;
const #175 = Asciz	Lscala/Function2;;
const #176 = Asciz	reduceRight;
const #177 = Asciz	(Lscala/collection/generic/TraversableProxyTemplate;Lscala/Function2;)Ljava/lang/Object;;
const #178 = Asciz	(Lscala/Function2;)Ljava/lang/Object;;
const #179 = NameAndType	#176:#178;//  reduceRight:(Lscala/Function2;)Ljava/lang/Object;
const #180 = InterfaceMethod	#19.#179;	//  scala/collection/generic/TraversableTemplate.reduceRight:(Lscala/Function2;)Ljava/lang/Object;
const #181 = Asciz	reduceLeftOption;
const #182 = NameAndType	#181:#171;//  reduceLeftOption:(Lscala/Function2;)Lscala/Option;
const #183 = InterfaceMethod	#19.#182;	//  scala/collection/generic/TraversableTemplate.reduceLeftOption:(Lscala/Function2;)Lscala/Option;
const #184 = Asciz	reduceLeft;
const #185 = NameAndType	#184:#178;//  reduceLeft:(Lscala/Function2;)Ljava/lang/Object;
const #186 = InterfaceMethod	#19.#185;	//  scala/collection/generic/TraversableTemplate.reduceLeft:(Lscala/Function2;)Ljava/lang/Object;
const #187 = Asciz	$colon$bslash;
const #188 = Asciz	(Lscala/collection/generic/TraversableProxyTemplate;Ljava/lang/Object;Lscala/Function2;)Ljava/lang/Object;;
const #189 = Asciz	(Ljava/lang/Object;Lscala/Function2;)Ljava/lang/Object;;
const #190 = NameAndType	#187:#189;//  $colon$bslash:(Ljava/lang/Object;Lscala/Function2;)Ljava/lang/Object;
const #191 = InterfaceMethod	#19.#190;	//  scala/collection/generic/TraversableTemplate.$colon$bslash:(Ljava/lang/Object;Lscala/Function2;)Ljava/lang/Object;
const #192 = Asciz	z;
const #193 = Asciz	Ljava/lang/Object;;
const #194 = Asciz	foldRight;
const #195 = NameAndType	#194:#189;//  foldRight:(Ljava/lang/Object;Lscala/Function2;)Ljava/lang/Object;
const #196 = InterfaceMethod	#19.#195;	//  scala/collection/generic/TraversableTemplate.foldRight:(Ljava/lang/Object;Lscala/Function2;)Ljava/lang/Object;
const #197 = Asciz	$div$colon;
const #198 = NameAndType	#197:#189;//  $div$colon:(Ljava/lang/Object;Lscala/Function2;)Ljava/lang/Object;
const #199 = InterfaceMethod	#19.#198;	//  scala/collection/generic/TraversableTemplate.$div$colon:(Ljava/lang/Object;Lscala/Function2;)Ljava/lang/Object;
const #200 = Asciz	foldLeft;
const #201 = NameAndType	#200:#189;//  foldLeft:(Ljava/lang/Object;Lscala/Function2;)Ljava/lang/Object;
const #202 = InterfaceMethod	#19.#201;	//  scala/collection/generic/TraversableTemplate.foldLeft:(Ljava/lang/Object;Lscala/Function2;)Ljava/lang/Object;
const #203 = Asciz	find;
const #204 = Asciz	(Lscala/collection/generic/TraversableProxyTemplate;Lscala/Function1;)Lscala/Option;;
const #205 = Asciz	(Lscala/Function1;)Lscala/Option;;
const #206 = NameAndType	#203:#205;//  find:(Lscala/Function1;)Lscala/Option;
const #207 = InterfaceMethod	#19.#206;	//  scala/collection/generic/TraversableTemplate.find:(Lscala/Function1;)Lscala/Option;
const #208 = Asciz	count;
const #209 = Asciz	(Lscala/collection/generic/TraversableProxyTemplate;Lscala/Function1;)I;
const #210 = Asciz	(Lscala/Function1;)I;
const #211 = NameAndType	#208:#210;//  count:(Lscala/Function1;)I
const #212 = InterfaceMethod	#19.#211;	//  scala/collection/generic/TraversableTemplate.count:(Lscala/Function1;)I
const #213 = Asciz	exists;
const #214 = Asciz	(Lscala/collection/generic/TraversableProxyTemplate;Lscala/Function1;)Z;
const #215 = Asciz	(Lscala/Function1;)Z;
const #216 = NameAndType	#213:#215;//  exists:(Lscala/Function1;)Z
const #217 = InterfaceMethod	#19.#216;	//  scala/collection/generic/TraversableTemplate.exists:(Lscala/Function1;)Z
const #218 = Asciz	forall;
const #219 = NameAndType	#218:#215;//  forall:(Lscala/Function1;)Z
const #220 = InterfaceMethod	#19.#219;	//  scala/collection/generic/TraversableTemplate.forall:(Lscala/Function1;)Z
const #221 = Asciz	groupBy;
const #222 = Asciz	(Lscala/collection/generic/TraversableProxyTemplate;Lscala/Function1;)Lscala/collection/Map;;
const #223 = Asciz	(Lscala/Function1;)Lscala/collection/Map;;
const #224 = NameAndType	#221:#223;//  groupBy:(Lscala/Function1;)Lscala/collection/Map;
const #225 = InterfaceMethod	#19.#224;	//  scala/collection/generic/TraversableTemplate.groupBy:(Lscala/Function1;)Lscala/collection/Map;
const #226 = Asciz	f;
const #227 = Asciz	partition;
const #228 = NameAndType	#227:#122;//  partition:(Lscala/Function1;)Lscala/Tuple2;
const #229 = InterfaceMethod	#19.#228;	//  scala/collection/generic/TraversableTemplate.partition:(Lscala/Function1;)Lscala/Tuple2;
const #230 = Asciz	remove;
const #231 = NameAndType	#230:#129;//  remove:(Lscala/Function1;)Lscala/collection/generic/TraversableTemplate;
const #232 = InterfaceMethod	#19.#231;	//  scala/collection/generic/TraversableTemplate.remove:(Lscala/Function1;)Lscala/collection/generic/TraversableTemplate;
const #233 = Asciz	filterNot;
const #234 = NameAndType	#233:#129;//  filterNot:(Lscala/Function1;)Lscala/collection/generic/TraversableTemplate;
const #235 = InterfaceMethod	#19.#234;	//  scala/collection/generic/TraversableTemplate.filterNot:(Lscala/Function1;)Lscala/collection/generic/TraversableTemplate;
const #236 = Asciz	filter;
const #237 = NameAndType	#236:#129;//  filter:(Lscala/Function1;)Lscala/collection/generic/TraversableTemplate;
const #238 = InterfaceMethod	#19.#237;	//  scala/collection/generic/TraversableTemplate.filter:(Lscala/Function1;)Lscala/collection/generic/TraversableTemplate;
const #239 = Asciz	flatMap;
const #240 = Asciz	(Lscala/collection/generic/TraversableProxyTemplate;Lscala/Function1;Lscala/collection/generic/BuilderFactory;)Ljava/lang/Object;;
const #241 = Asciz	(Lscala/Function1;Lscala/collection/generic/BuilderFactory;)Ljava/lang/Object;;
const #242 = NameAndType	#239:#241;//  flatMap:(Lscala/Function1;Lscala/collection/generic/BuilderFactory;)Ljava/lang/Object;
const #243 = InterfaceMethod	#19.#242;	//  scala/collection/generic/TraversableTemplate.flatMap:(Lscala/Function1;Lscala/collection/generic/BuilderFactory;)Ljava/lang/Object;
const #244 = Asciz	bf;
const #245 = Asciz	Lscala/collection/generic/BuilderFactory;;
const #246 = Asciz	map;
const #247 = NameAndType	#246:#241;//  map:(Lscala/Function1;Lscala/collection/generic/BuilderFactory;)Ljava/lang/Object;
const #248 = InterfaceMethod	#19.#247;	//  scala/collection/generic/TraversableTemplate.map:(Lscala/Function1;Lscala/collection/generic/BuilderFactory;)Ljava/lang/Object;
const #249 = Asciz	$plus$plus;
const #250 = Asciz	(Lscala/collection/generic/TraversableProxyTemplate;Lscala/collection/Iterator;Lscala/collection/generic/BuilderFactory;)Ljava/lang/Object;;
const #251 = Asciz	(Lscala/collection/Iterator;Lscala/collection/generic/BuilderFactory;)Ljava/lang/Object;;
const #252 = NameAndType	#249:#251;//  $plus$plus:(Lscala/collection/Iterator;Lscala/collection/generic/BuilderFactory;)Ljava/lang/Object;
const #253 = InterfaceMethod	#19.#252;	//  scala/collection/generic/TraversableTemplate.$plus$plus:(Lscala/collection/Iterator;Lscala/collection/generic/BuilderFactory;)Ljava/lang/Object;
const #254 = Asciz	that;
const #255 = Asciz	Lscala/collection/Iterator;;
const #256 = Asciz	(Lscala/collection/generic/TraversableProxyTemplate;Lscala/collection/Traversable;Lscala/collection/generic/BuilderFactory;)Ljava/lang/Object;;
const #257 = Asciz	(Lscala/collection/Traversable;Lscala/collection/generic/BuilderFactory;)Ljava/lang/Object;;
const #258 = NameAndType	#249:#257;//  $plus$plus:(Lscala/collection/Traversable;Lscala/collection/generic/BuilderFactory;)Ljava/lang/Object;
const #259 = InterfaceMethod	#19.#258;	//  scala/collection/generic/TraversableTemplate.$plus$plus:(Lscala/collection/Traversable;Lscala/collection/generic/BuilderFactory;)Ljava/lang/Object;
const #260 = Asciz	Lscala/collection/Traversable;;
const #261 = Asciz	hasDefiniteSize;
const #262 = Asciz	(Lscala/collection/generic/TraversableProxyTemplate;)Z;
const #263 = Asciz	()Z;
const #264 = NameAndType	#261:#263;//  hasDefiniteSize:()Z
const #265 = InterfaceMethod	#19.#264;	//  scala/collection/generic/TraversableTemplate.hasDefiniteSize:()Z
const #266 = Asciz	size;
const #267 = Asciz	(Lscala/collection/generic/TraversableProxyTemplate;)I;
const #268 = Asciz	()I;
const #269 = NameAndType	#266:#268;//  size:()I
const #270 = InterfaceMethod	#19.#269;	//  scala/collection/generic/TraversableTemplate.size:()I
const #271 = Asciz	nonEmpty;
const #272 = NameAndType	#271:#263;//  nonEmpty:()Z
const #273 = InterfaceMethod	#19.#272;	//  scala/collection/generic/TraversableTemplate.nonEmpty:()Z
const #274 = Asciz	isEmpty;
const #275 = NameAndType	#274:#263;//  isEmpty:()Z
const #276 = InterfaceMethod	#19.#275;	//  scala/collection/generic/TraversableTemplate.isEmpty:()Z
const #277 = Asciz	foreach;
const #278 = Asciz	(Lscala/collection/generic/TraversableProxyTemplate;Lscala/Function1;)V;
const #279 = Asciz	scala/collection/generic/TraversableClass;
const #280 = class	#279;	//  scala/collection/generic/TraversableClass
const #281 = Asciz	(Lscala/Function1;)V;
const #282 = NameAndType	#277:#281;//  foreach:(Lscala/Function1;)V
const #283 = InterfaceMethod	#280.#282;	//  scala/collection/generic/TraversableClass.foreach:(Lscala/Function1;)V
const #284 = Asciz	Scala;
const #285 = Asciz	scala/collection/generic/TraversableProxyTemplate$class;
const #286 = class	#285;	//  scala/collection/generic/TraversableProxyTemplate$class
const #287 = Asciz	java/lang/Object;
const #288 = class	#287;	//  java/lang/Object

{
public static void $init$(scala.collection.generic.TraversableProxyTemplate);
  Code:
   Stack=0, Locals=1, Args_size=1
   0:	return
  LineNumberTable: 
   line 26: 0

  LocalVariableTable: 
   Start  Length  Slot  Name   Signature
   0      1      0    $this       Lscala/collection/generic/TraversableProxyTemplate;


public static scala.collection.generic.TraversableView view(scala.collection.generic.TraversableProxyTemplate, int, int);
  Code:
   Stack=3, Locals=3, Args_size=3
   0:	aload_0
   1:	invokeinterface	#17,  1; //InterfaceMethod scala/collection/generic/TraversableProxyTemplate.self:()Lscala/collection/generic/TraversableTemplate;
   6:	iload_1
   7:	iload_2
   8:	invokeinterface	#22,  3; //InterfaceMethod scala/collection/generic/TraversableTemplate.view:(II)Lscala/collection/generic/TraversableView;
   13:	areturn
  LineNumberTable: 
   line 86: 0

  LocalVariableTable: 
   Start  Length  Slot  Name   Signature
   0      14      0    $this       Lscala/collection/generic/TraversableProxyTemplate;
   0      14      1    from       I
   0      14      2    until       I


public static java.lang.Object view(scala.collection.generic.TraversableProxyTemplate);
  Code:
   Stack=1, Locals=1, Args_size=1
   0:	aload_0
   1:	invokeinterface	#17,  1; //InterfaceMethod scala/collection/generic/TraversableProxyTemplate.self:()Lscala/collection/generic/TraversableTemplate;
   6:	invokeinterface	#29,  1; //InterfaceMethod scala/collection/generic/TraversableTemplate.view:()Ljava/lang/Object;
   11:	areturn
  LineNumberTable: 
   line 85: 0

  LocalVariableTable: 
   Start  Length  Slot  Name   Signature
   0      12      0    $this       Lscala/collection/generic/TraversableProxyTemplate;


public static java.lang.String stringPrefix(scala.collection.generic.TraversableProxyTemplate);
  Code:
   Stack=1, Locals=1, Args_size=1
   0:	aload_0
   1:	invokeinterface	#17,  1; //InterfaceMethod scala/collection/generic/TraversableProxyTemplate.self:()Lscala/collection/generic/TraversableTemplate;
   6:	invokeinterface	#34,  1; //InterfaceMethod scala/collection/generic/TraversableTemplate.stringPrefix:()Ljava/lang/String;
   11:	areturn
  LineNumberTable: 
   line 84: 0

  LocalVariableTable: 
   Start  Length  Slot  Name   Signature
   0      12      0    $this       Lscala/collection/generic/TraversableProxyTemplate;


public static scala.collection.mutable.StringBuilder addString(scala.collection.generic.TraversableProxyTemplate, scala.collection.mutable.StringBuilder);
  Code:
   Stack=2, Locals=2, Args_size=2
   0:	aload_0
   1:	invokeinterface	#17,  1; //InterfaceMethod scala/collection/generic/TraversableProxyTemplate.self:()Lscala/collection/generic/TraversableTemplate;
   6:	aload_1
   7:	invokeinterface	#39,  2; //InterfaceMethod scala/collection/generic/TraversableTemplate.addString:(Lscala/collection/mutable/StringBuilder;)Lscala/collection/mutable/StringBuilder;
   12:	areturn
  LineNumberTable: 
   line 83: 0

  LocalVariableTable: 
   Start  Length  Slot  Name   Signature
   0      13      0    $this       Lscala/collection/generic/TraversableProxyTemplate;
   0      13      1    b       Lscala/collection/mutable/StringBuilder;


public static scala.collection.mutable.StringBuilder addString(scala.collection.generic.TraversableProxyTemplate, scala.collection.mutable.StringBuilder, java.lang.String);
  Code:
   Stack=3, Locals=3, Args_size=3
   0:	aload_0
   1:	invokeinterface	#17,  1; //InterfaceMethod scala/collection/generic/TraversableProxyTemplate.self:()Lscala/collection/generic/TraversableTemplate;
   6:	aload_1
   7:	aload_2
   8:	invokeinterface	#45,  3; //InterfaceMethod scala/collection/generic/TraversableTemplate.addString:(Lscala/collection/mutable/StringBuilder;Ljava/lang/String;)Lscala/collection/mutable/StringBuilder;
   13:	areturn
  LineNumberTable: 
   line 82: 0

  LocalVariableTable: 
   Start  Length  Slot  Name   Signature
   0      14      0    $this       Lscala/collection/generic/TraversableProxyTemplate;
   0      14      1    b       Lscala/collection/mutable/StringBuilder;
   0      14      2    sep       Ljava/lang/String;


public static scala.collection.mutable.StringBuilder addString(scala.collection.generic.TraversableProxyTemplate, scala.collection.mutable.StringBuilder, java.lang.String, java.lang.String, java.lang.String);
  Code:
   Stack=5, Locals=5, Args_size=5
   0:	aload_0
   1:	invokeinterface	#17,  1; //InterfaceMethod scala/collection/generic/TraversableProxyTemplate.self:()Lscala/collection/generic/TraversableTemplate;
   6:	aload_1
   7:	aload_2
   8:	aload_3
   9:	aload	4
   11:	invokeinterface	#51,  5; //InterfaceMethod scala/collection/generic/TraversableTemplate.addString:(Lscala/collection/mutable/StringBuilder;Ljava/lang/String;Ljava/lang/String;Ljava/lang/String;)Lscala/collection/mutable/StringBuilder;
   16:	areturn
  LineNumberTable: 
   line 81: 0

  LocalVariableTable: 
   Start  Length  Slot  Name   Signature
   0      17      0    $this       Lscala/collection/generic/TraversableProxyTemplate;
   0      17      1    b       Lscala/collection/mutable/StringBuilder;
   0      17      2    start       Ljava/lang/String;
   0      17      3    sep       Ljava/lang/String;
   0      17      4    end       Ljava/lang/String;


public static java.lang.String mkString(scala.collection.generic.TraversableProxyTemplate);
  Code:
   Stack=1, Locals=1, Args_size=1
   0:	aload_0
   1:	invokeinterface	#17,  1; //InterfaceMethod scala/collection/generic/TraversableProxyTemplate.self:()Lscala/collection/generic/TraversableTemplate;
   6:	invokeinterface	#56,  1; //InterfaceMethod scala/collection/generic/TraversableTemplate.mkString:()Ljava/lang/String;
   11:	areturn
  LineNumberTable: 
   line 80: 0

  LocalVariableTable: 
   Start  Length  Slot  Name   Signature
   0      12      0    $this       Lscala/collection/generic/TraversableProxyTemplate;


public static java.lang.String mkString(scala.collection.generic.TraversableProxyTemplate, java.lang.String);
  Code:
   Stack=2, Locals=2, Args_size=2
   0:	aload_0
   1:	invokeinterface	#17,  1; //InterfaceMethod scala/collection/generic/TraversableProxyTemplate.self:()Lscala/collection/generic/TraversableTemplate;
   6:	aload_1
   7:	invokeinterface	#60,  2; //InterfaceMethod scala/collection/generic/TraversableTemplate.mkString:(Ljava/lang/String;)Ljava/lang/String;
   12:	areturn
  LineNumberTable: 
   line 79: 0

  LocalVariableTable: 
   Start  Length  Slot  Name   Signature
   0      13      0    $this       Lscala/collection/generic/TraversableProxyTemplate;
   0      13      1    sep       Ljava/lang/String;


public static java.lang.String mkString(scala.collection.generic.TraversableProxyTemplate, java.lang.String, java.lang.String, java.lang.String);
  Code:
   Stack=4, Locals=4, Args_size=4
   0:	aload_0
   1:	invokeinterface	#17,  1; //InterfaceMethod scala/collection/generic/TraversableProxyTemplate.self:()Lscala/collection/generic/TraversableTemplate;
   6:	aload_1
   7:	aload_2
   8:	aload_3
   9:	invokeinterface	#64,  4; //InterfaceMethod scala/collection/generic/TraversableTemplate.mkString:(Ljava/lang/String;Ljava/lang/String;Ljava/lang/String;)Ljava/lang/String;
   14:	areturn
  LineNumberTable: 
   line 78: 0

  LocalVariableTable: 
   Start  Length  Slot  Name   Signature
   0      15      0    $this       Lscala/collection/generic/TraversableProxyTemplate;
   0      15      1    start       Ljava/lang/String;
   0      15      2    sep       Ljava/lang/String;
   0      15      3    end       Ljava/lang/String;


public static scala.collection.immutable.Set toSet(scala.collection.generic.TraversableProxyTemplate);
  Code:
   Stack=1, Locals=1, Args_size=1
   0:	aload_0
   1:	invokeinterface	#17,  1; //InterfaceMethod scala/collection/generic/TraversableProxyTemplate.self:()Lscala/collection/generic/TraversableTemplate;
   6:	invokeinterface	#69,  1; //InterfaceMethod scala/collection/generic/TraversableTemplate.toSet:()Lscala/collection/immutable/Set;
   11:	areturn
  LineNumberTable: 
   line 76: 0

  LocalVariableTable: 
   Start  Length  Slot  Name   Signature
   0      12      0    $this       Lscala/collection/generic/TraversableProxyTemplate;


public static scala.collection.immutable.Stream toStream(scala.collection.generic.TraversableProxyTemplate);
  Code:
   Stack=1, Locals=1, Args_size=1
   0:	aload_0
   1:	invokeinterface	#17,  1; //InterfaceMethod scala/collection/generic/TraversableProxyTemplate.self:()Lscala/collection/generic/TraversableTemplate;
   6:	invokeinterface	#74,  1; //InterfaceMethod scala/collection/generic/TraversableTemplate.toStream:()Lscala/collection/immutable/Stream;
   11:	areturn
  LineNumberTable: 
   line 75: 0

  LocalVariableTable: 
   Start  Length  Slot  Name   Signature
   0      12      0    $this       Lscala/collection/generic/TraversableProxyTemplate;


public static scala.collection.Sequence toSequence(scala.collection.generic.TraversableProxyTemplate);
  Code:
   Stack=1, Locals=1, Args_size=1
   0:	aload_0
   1:	invokeinterface	#17,  1; //InterfaceMethod scala/collection/generic/TraversableProxyTemplate.self:()Lscala/collection/generic/TraversableTemplate;
   6:	invokeinterface	#79,  1; //InterfaceMethod scala/collection/generic/TraversableTemplate.toSequence:()Lscala/collection/Sequence;
   11:	areturn
  LineNumberTable: 
   line 74: 0

  LocalVariableTable: 
   Start  Length  Slot  Name   Signature
   0      12      0    $this       Lscala/collection/generic/TraversableProxyTemplate;


public static scala.collection.Iterable toIterable(scala.collection.generic.TraversableProxyTemplate);
  Code:
   Stack=1, Locals=1, Args_size=1
   0:	aload_0
   1:	invokeinterface	#17,  1; //InterfaceMethod scala/collection/generic/TraversableProxyTemplate.self:()Lscala/collection/generic/TraversableTemplate;
   6:	invokeinterface	#84,  1; //InterfaceMethod scala/collection/generic/TraversableTemplate.toIterable:()Lscala/collection/Iterable;
   11:	areturn
  LineNumberTable: 
   line 73: 0

  LocalVariableTable: 
   Start  Length  Slot  Name   Signature
   0      12      0    $this       Lscala/collection/generic/TraversableProxyTemplate;


public static scala.collection.immutable.List toList(scala.collection.generic.TraversableProxyTemplate);
  Code:
   Stack=1, Locals=1, Args_size=1
   0:	aload_0
   1:	invokeinterface	#17,  1; //InterfaceMethod scala/collection/generic/TraversableProxyTemplate.self:()Lscala/collection/generic/TraversableTemplate;
   6:	invokeinterface	#89,  1; //InterfaceMethod scala/collection/generic/TraversableTemplate.toList:()Lscala/collection/immutable/List;
   11:	areturn
  LineNumberTable: 
   line 72: 0

  LocalVariableTable: 
   Start  Length  Slot  Name   Signature
   0      12      0    $this       Lscala/collection/generic/TraversableProxyTemplate;


public static scala.runtime.BoxedArray toArray(scala.collection.generic.TraversableProxyTemplate);
  Code:
   Stack=1, Locals=1, Args_size=1
   0:	aload_0
   1:	invokeinterface	#17,  1; //InterfaceMethod scala/collection/generic/TraversableProxyTemplate.self:()Lscala/collection/generic/TraversableTemplate;
   6:	invokeinterface	#94,  1; //InterfaceMethod scala/collection/generic/TraversableTemplate.toArray:()Lscala/runtime/BoxedArray;
   11:	areturn
  LineNumberTable: 
   line 71: 0

  LocalVariableTable: 
   Start  Length  Slot  Name   Signature
   0      12      0    $this       Lscala/collection/generic/TraversableProxyTemplate;


public static void copyToArray(scala.collection.generic.TraversableProxyTemplate, scala.runtime.BoxedArray, int);
  Code:
   Stack=3, Locals=3, Args_size=3
   0:	aload_0
   1:	invokeinterface	#17,  1; //InterfaceMethod scala/collection/generic/TraversableProxyTemplate.self:()Lscala/collection/generic/TraversableTemplate;
   6:	aload_1
   7:	iload_2
   8:	invokeinterface	#99,  3; //InterfaceMethod scala/collection/generic/TraversableTemplate.copyToArray:(Lscala/runtime/BoxedArray;I)V
   13:	return
  LineNumberTable: 
   line 70: 0

  LocalVariableTable: 
   Start  Length  Slot  Name   Signature
   0      14      0    $this       Lscala/collection/generic/TraversableProxyTemplate;
   0      14      1    xs       Lscala/runtime/BoxedArray;
   0      14      2    start       I


public static void copyToArray(scala.collection.generic.TraversableProxyTemplate, scala.runtime.BoxedArray, int, int);
  Code:
   Stack=4, Locals=4, Args_size=4
   0:	aload_0
   1:	invokeinterface	#17,  1; //InterfaceMethod scala/collection/generic/TraversableProxyTemplate.self:()Lscala/collection/generic/TraversableTemplate;
   6:	aload_1
   7:	iload_2
   8:	iload_3
   9:	invokeinterface	#105,  4; //InterfaceMethod scala/collection/generic/TraversableTemplate.copyToArray:(Lscala/runtime/BoxedArray;II)V
   14:	return
  LineNumberTable: 
   line 69: 0

  LocalVariableTable: 
   Start  Length  Slot  Name   Signature
   0      15      0    $this       Lscala/collection/generic/TraversableProxyTemplate;
   0      15      1    xs       Lscala/runtime/BoxedArray;
   0      15      2    start       I
   0      15      3    len       I


public static void copyToBuffer(scala.collection.generic.TraversableProxyTemplate, scala.collection.mutable.Buffer);
  Code:
   Stack=2, Locals=2, Args_size=2
   0:	aload_0
   1:	invokeinterface	#17,  1; //InterfaceMethod scala/collection/generic/TraversableProxyTemplate.self:()Lscala/collection/generic/TraversableTemplate;
   6:	aload_1
   7:	invokeinterface	#111,  2; //InterfaceMethod scala/collection/generic/TraversableTemplate.copyToBuffer:(Lscala/collection/mutable/Buffer;)V
   12:	return
  LineNumberTable: 
   line 68: 0

  LocalVariableTable: 
   Start  Length  Slot  Name   Signature
   0      13      0    $this       Lscala/collection/generic/TraversableProxyTemplate;
   0      13      1    dest       Lscala/collection/mutable/Buffer;


public static scala.Tuple2 splitAt(scala.collection.generic.TraversableProxyTemplate, int);
  Code:
   Stack=2, Locals=2, Args_size=2
   0:	aload_0
   1:	invokeinterface	#17,  1; //InterfaceMethod scala/collection/generic/TraversableProxyTemplate.self:()Lscala/collection/generic/TraversableTemplate;
   6:	iload_1
   7:	invokeinterface	#118,  2; //InterfaceMethod scala/collection/generic/TraversableTemplate.splitAt:(I)Lscala/Tuple2;
   12:	areturn
  LineNumberTable: 
   line 67: 0

  LocalVariableTable: 
   Start  Length  Slot  Name   Signature
   0      13      0    $this       Lscala/collection/generic/TraversableProxyTemplate;
   0      13      1    n       I


public static scala.Tuple2 span(scala.collection.generic.TraversableProxyTemplate, scala.Function1);
  Code:
   Stack=2, Locals=2, Args_size=2
   0:	aload_0
   1:	invokeinterface	#17,  1; //InterfaceMethod scala/collection/generic/TraversableProxyTemplate.self:()Lscala/collection/generic/TraversableTemplate;
   6:	aload_1
   7:	invokeinterface	#124,  2; //InterfaceMethod scala/collection/generic/TraversableTemplate.span:(Lscala/Function1;)Lscala/Tuple2;
   12:	areturn
  LineNumberTable: 
   line 66: 0

  LocalVariableTable: 
   Start  Length  Slot  Name   Signature
   0      13      0    $this       Lscala/collection/generic/TraversableProxyTemplate;
   0      13      1    p       Lscala/Function1;


public static scala.collection.generic.TraversableTemplate dropWhile(scala.collection.generic.TraversableProxyTemplate, scala.Function1);
  Code:
   Stack=2, Locals=2, Args_size=2
   0:	aload_0
   1:	invokeinterface	#17,  1; //InterfaceMethod scala/collection/generic/TraversableProxyTemplate.self:()Lscala/collection/generic/TraversableTemplate;
   6:	aload_1
   7:	invokeinterface	#131,  2; //InterfaceMethod scala/collection/generic/TraversableTemplate.dropWhile:(Lscala/Function1;)Lscala/collection/generic/TraversableTemplate;
   12:	areturn
  LineNumberTable: 
   line 65: 0

  LocalVariableTable: 
   Start  Length  Slot  Name   Signature
   0      13      0    $this       Lscala/collection/generic/TraversableProxyTemplate;
   0      13      1    p       Lscala/Function1;


public static scala.collection.generic.TraversableTemplate takeWhile(scala.collection.generic.TraversableProxyTemplate, scala.Function1);
  Code:
   Stack=2, Locals=2, Args_size=2
   0:	aload_0
   1:	invokeinterface	#17,  1; //InterfaceMethod scala/collection/generic/TraversableProxyTemplate.self:()Lscala/collection/generic/TraversableTemplate;
   6:	aload_1
   7:	invokeinterface	#134,  2; //InterfaceMethod scala/collection/generic/TraversableTemplate.takeWhile:(Lscala/Function1;)Lscala/collection/generic/TraversableTemplate;
   12:	areturn
  LineNumberTable: 
   line 64: 0

  LocalVariableTable: 
   Start  Length  Slot  Name   Signature
   0      13      0    $this       Lscala/collection/generic/TraversableProxyTemplate;
   0      13      1    p       Lscala/Function1;


public static scala.collection.generic.TraversableTemplate slice(scala.collection.generic.TraversableProxyTemplate, int, int);
  Code:
   Stack=3, Locals=3, Args_size=3
   0:	aload_0
   1:	invokeinterface	#17,  1; //InterfaceMethod scala/collection/generic/TraversableProxyTemplate.self:()Lscala/collection/generic/TraversableTemplate;
   6:	iload_1
   7:	iload_2
   8:	invokeinterface	#139,  3; //InterfaceMethod scala/collection/generic/TraversableTemplate.slice:(II)Lscala/collection/generic/TraversableTemplate;
   13:	areturn
  LineNumberTable: 
   line 63: 0

  LocalVariableTable: 
   Start  Length  Slot  Name   Signature
   0      14      0    $this       Lscala/collection/generic/TraversableProxyTemplate;
   0      14      1    from       I
   0      14      2    until       I


public static scala.collection.generic.TraversableTemplate drop(scala.collection.generic.TraversableProxyTemplate, int);
  Code:
   Stack=2, Locals=2, Args_size=2
   0:	aload_0
   1:	invokeinterface	#17,  1; //InterfaceMethod scala/collection/generic/TraversableProxyTemplate.self:()Lscala/collection/generic/TraversableTemplate;
   6:	iload_1
   7:	invokeinterface	#144,  2; //InterfaceMethod scala/collection/generic/TraversableTemplate.drop:(I)Lscala/collection/generic/TraversableTemplate;
   12:	areturn
  LineNumberTable: 
   line 62: 0

  LocalVariableTable: 
   Start  Length  Slot  Name   Signature
   0      13      0    $this       Lscala/collection/generic/TraversableProxyTemplate;
   0      13      1    n       I


public static scala.collection.generic.TraversableTemplate take(scala.collection.generic.TraversableProxyTemplate, int);
  Code:
   Stack=2, Locals=2, Args_size=2
   0:	aload_0
   1:	invokeinterface	#17,  1; //InterfaceMethod scala/collection/generic/TraversableProxyTemplate.self:()Lscala/collection/generic/TraversableTemplate;
   6:	iload_1
   7:	invokeinterface	#147,  2; //InterfaceMethod scala/collection/generic/TraversableTemplate.take:(I)Lscala/collection/generic/TraversableTemplate;
   12:	areturn
  LineNumberTable: 
   line 61: 0

  LocalVariableTable: 
   Start  Length  Slot  Name   Signature
   0      13      0    $this       Lscala/collection/generic/TraversableProxyTemplate;
   0      13      1    n       I


public static scala.collection.generic.TraversableTemplate init(scala.collection.generic.TraversableProxyTemplate);
  Code:
   Stack=1, Locals=1, Args_size=1
   0:	aload_0
   1:	invokeinterface	#17,  1; //InterfaceMethod scala/collection/generic/TraversableProxyTemplate.self:()Lscala/collection/generic/TraversableTemplate;
   6:	invokeinterface	#151,  1; //InterfaceMethod scala/collection/generic/TraversableTemplate.init:()Lscala/collection/generic/TraversableTemplate;
   11:	areturn
  LineNumberTable: 
   line 60: 0

  LocalVariableTable: 
   Start  Length  Slot  Name   Signature
   0      12      0    $this       Lscala/collection/generic/TraversableProxyTemplate;


public static scala.Option lastOption(scala.collection.generic.TraversableProxyTemplate);
  Code:
   Stack=1, Locals=1, Args_size=1
   0:	aload_0
   1:	invokeinterface	#17,  1; //InterfaceMethod scala/collection/generic/TraversableProxyTemplate.self:()Lscala/collection/generic/TraversableTemplate;
   6:	invokeinterface	#156,  1; //InterfaceMethod scala/collection/generic/TraversableTemplate.lastOption:()Lscala/Option;
   11:	areturn
  LineNumberTable: 
   line 59: 0

  LocalVariableTable: 
   Start  Length  Slot  Name   Signature
   0      12      0    $this       Lscala/collection/generic/TraversableProxyTemplate;


public static java.lang.Object last(scala.collection.generic.TraversableProxyTemplate);
  Code:
   Stack=1, Locals=1, Args_size=1
   0:	aload_0
   1:	invokeinterface	#17,  1; //InterfaceMethod scala/collection/generic/TraversableProxyTemplate.self:()Lscala/collection/generic/TraversableTemplate;
   6:	invokeinterface	#159,  1; //InterfaceMethod scala/collection/generic/TraversableTemplate.last:()Ljava/lang/Object;
   11:	areturn
  LineNumberTable: 
   line 58: 0

  LocalVariableTable: 
   Start  Length  Slot  Name   Signature
   0      12      0    $this       Lscala/collection/generic/TraversableProxyTemplate;


public static scala.collection.generic.TraversableTemplate tail(scala.collection.generic.TraversableProxyTemplate);
  Code:
   Stack=1, Locals=1, Args_size=1
   0:	aload_0
   1:	invokeinterface	#17,  1; //InterfaceMethod scala/collection/generic/TraversableProxyTemplate.self:()Lscala/collection/generic/TraversableTemplate;
   6:	invokeinterface	#162,  1; //InterfaceMethod scala/collection/generic/TraversableTemplate.tail:()Lscala/collection/generic/TraversableTemplate;
   11:	areturn
  LineNumberTable: 
   line 57: 0

  LocalVariableTable: 
   Start  Length  Slot  Name   Signature
   0      12      0    $this       Lscala/collection/generic/TraversableProxyTemplate;


public static scala.Option headOption(scala.collection.generic.TraversableProxyTemplate);
  Code:
   Stack=1, Locals=1, Args_size=1
   0:	aload_0
   1:	invokeinterface	#17,  1; //InterfaceMethod scala/collection/generic/TraversableProxyTemplate.self:()Lscala/collection/generic/TraversableTemplate;
   6:	invokeinterface	#165,  1; //InterfaceMethod scala/collection/generic/TraversableTemplate.headOption:()Lscala/Option;
   11:	areturn
  LineNumberTable: 
   line 56: 0

  LocalVariableTable: 
   Start  Length  Slot  Name   Signature
   0      12      0    $this       Lscala/collection/generic/TraversableProxyTemplate;


public static java.lang.Object head(scala.collection.generic.TraversableProxyTemplate);
  Code:
   Stack=1, Locals=1, Args_size=1
   0:	aload_0
   1:	invokeinterface	#17,  1; //InterfaceMethod scala/collection/generic/TraversableProxyTemplate.self:()Lscala/collection/generic/TraversableTemplate;
   6:	invokeinterface	#168,  1; //InterfaceMethod scala/collection/generic/TraversableTemplate.head:()Ljava/lang/Object;
   11:	areturn
  LineNumberTable: 
   line 55: 0

  LocalVariableTable: 
   Start  Length  Slot  Name   Signature
   0      12      0    $this       Lscala/collection/generic/TraversableProxyTemplate;


public static scala.Option reduceRightOption(scala.collection.generic.TraversableProxyTemplate, scala.Function2);
  Code:
   Stack=2, Locals=2, Args_size=2
   0:	aload_0
   1:	invokeinterface	#17,  1; //InterfaceMethod scala/collection/generic/TraversableProxyTemplate.self:()Lscala/collection/generic/TraversableTemplate;
   6:	aload_1
   7:	invokeinterface	#173,  2; //InterfaceMethod scala/collection/generic/TraversableTemplate.reduceRightOption:(Lscala/Function2;)Lscala/Option;
   12:	areturn
  LineNumberTable: 
   line 54: 0

  LocalVariableTable: 
   Start  Length  Slot  Name   Signature
   0      13      0    $this       Lscala/collection/generic/TraversableProxyTemplate;
   0      13      1    op       Lscala/Function2;


public static java.lang.Object reduceRight(scala.collection.generic.TraversableProxyTemplate, scala.Function2);
  Code:
   Stack=2, Locals=2, Args_size=2
   0:	aload_0
   1:	invokeinterface	#17,  1; //InterfaceMethod scala/collection/generic/TraversableProxyTemplate.self:()Lscala/collection/generic/TraversableTemplate;
   6:	aload_1
   7:	invokeinterface	#180,  2; //InterfaceMethod scala/collection/generic/TraversableTemplate.reduceRight:(Lscala/Function2;)Ljava/lang/Object;
   12:	areturn
  LineNumberTable: 
   line 53: 0

  LocalVariableTable: 
   Start  Length  Slot  Name   Signature
   0      13      0    $this       Lscala/collection/generic/TraversableProxyTemplate;
   0      13      1    op       Lscala/Function2;


public static scala.Option reduceLeftOption(scala.collection.generic.TraversableProxyTemplate, scala.Function2);
  Code:
   Stack=2, Locals=2, Args_size=2
   0:	aload_0
   1:	invokeinterface	#17,  1; //InterfaceMethod scala/collection/generic/TraversableProxyTemplate.self:()Lscala/collection/generic/TraversableTemplate;
   6:	aload_1
   7:	invokeinterface	#183,  2; //InterfaceMethod scala/collection/generic/TraversableTemplate.reduceLeftOption:(Lscala/Function2;)Lscala/Option;
   12:	areturn
  LineNumberTable: 
   line 52: 0

  LocalVariableTable: 
   Start  Length  Slot  Name   Signature
   0      13      0    $this       Lscala/collection/generic/TraversableProxyTemplate;
   0      13      1    op       Lscala/Function2;


public static java.lang.Object reduceLeft(scala.collection.generic.TraversableProxyTemplate, scala.Function2);
  Code:
   Stack=2, Locals=2, Args_size=2
   0:	aload_0
   1:	invokeinterface	#17,  1; //InterfaceMethod scala/collection/generic/TraversableProxyTemplate.self:()Lscala/collection/generic/TraversableTemplate;
   6:	aload_1
   7:	invokeinterface	#186,  2; //InterfaceMethod scala/collection/generic/TraversableTemplate.reduceLeft:(Lscala/Function2;)Ljava/lang/Object;
   12:	areturn
  LineNumberTable: 
   line 51: 0

  LocalVariableTable: 
   Start  Length  Slot  Name   Signature
   0      13      0    $this       Lscala/collection/generic/TraversableProxyTemplate;
   0      13      1    op       Lscala/Function2;


public static java.lang.Object $colon$bslash(scala.collection.generic.TraversableProxyTemplate, java.lang.Object, scala.Function2);
  Code:
   Stack=3, Locals=3, Args_size=3
   0:	aload_0
   1:	invokeinterface	#17,  1; //InterfaceMethod scala/collection/generic/TraversableProxyTemplate.self:()Lscala/collection/generic/TraversableTemplate;
   6:	aload_1
   7:	aload_2
   8:	invokeinterface	#191,  3; //InterfaceMethod scala/collection/generic/TraversableTemplate.$colon$bslash:(Ljava/lang/Object;Lscala/Function2;)Ljava/lang/Object;
   13:	areturn
  LineNumberTable: 
   line 50: 0

  LocalVariableTable: 
   Start  Length  Slot  Name   Signature
   0      14      0    $this       Lscala/collection/generic/TraversableProxyTemplate;
   0      14      1    z       Ljava/lang/Object;
   0      14      2    op       Lscala/Function2;


public static java.lang.Object foldRight(scala.collection.generic.TraversableProxyTemplate, java.lang.Object, scala.Function2);
  Code:
   Stack=3, Locals=3, Args_size=3
   0:	aload_0
   1:	invokeinterface	#17,  1; //InterfaceMethod scala/collection/generic/TraversableProxyTemplate.self:()Lscala/collection/generic/TraversableTemplate;
   6:	aload_1
   7:	aload_2
   8:	invokeinterface	#196,  3; //InterfaceMethod scala/collection/generic/TraversableTemplate.foldRight:(Ljava/lang/Object;Lscala/Function2;)Ljava/lang/Object;
   13:	areturn
  LineNumberTable: 
   line 49: 0

  LocalVariableTable: 
   Start  Length  Slot  Name   Signature
   0      14      0    $this       Lscala/collection/generic/TraversableProxyTemplate;
   0      14      1    z       Ljava/lang/Object;
   0      14      2    op       Lscala/Function2;


public static java.lang.Object $div$colon(scala.collection.generic.TraversableProxyTemplate, java.lang.Object, scala.Function2);
  Code:
   Stack=3, Locals=3, Args_size=3
   0:	aload_0
   1:	invokeinterface	#17,  1; //InterfaceMethod scala/collection/generic/TraversableProxyTemplate.self:()Lscala/collection/generic/TraversableTemplate;
   6:	aload_1
   7:	aload_2
   8:	invokeinterface	#199,  3; //InterfaceMethod scala/collection/generic/TraversableTemplate.$div$colon:(Ljava/lang/Object;Lscala/Function2;)Ljava/lang/Object;
   13:	areturn
  LineNumberTable: 
   line 48: 0

  LocalVariableTable: 
   Start  Length  Slot  Name   Signature
   0      14      0    $this       Lscala/collection/generic/TraversableProxyTemplate;
   0      14      1    z       Ljava/lang/Object;
   0      14      2    op       Lscala/Function2;


public static java.lang.Object foldLeft(scala.collection.generic.TraversableProxyTemplate, java.lang.Object, scala.Function2);
  Code:
   Stack=3, Locals=3, Args_size=3
   0:	aload_0
   1:	invokeinterface	#17,  1; //InterfaceMethod scala/collection/generic/TraversableProxyTemplate.self:()Lscala/collection/generic/TraversableTemplate;
   6:	aload_1
   7:	aload_2
   8:	invokeinterface	#202,  3; //InterfaceMethod scala/collection/generic/TraversableTemplate.foldLeft:(Ljava/lang/Object;Lscala/Function2;)Ljava/lang/Object;
   13:	areturn
  LineNumberTable: 
   line 47: 0

  LocalVariableTable: 
   Start  Length  Slot  Name   Signature
   0      14      0    $this       Lscala/collection/generic/TraversableProxyTemplate;
   0      14      1    z       Ljava/lang/Object;
   0      14      2    op       Lscala/Function2;


public static scala.Option find(scala.collection.generic.TraversableProxyTemplate, scala.Function1);
  Code:
   Stack=2, Locals=2, Args_size=2
   0:	aload_0
   1:	invokeinterface	#17,  1; //InterfaceMethod scala/collection/generic/TraversableProxyTemplate.self:()Lscala/collection/generic/TraversableTemplate;
   6:	aload_1
   7:	invokeinterface	#207,  2; //InterfaceMethod scala/collection/generic/TraversableTemplate.find:(Lscala/Function1;)Lscala/Option;
   12:	areturn
  LineNumberTable: 
   line 46: 0

  LocalVariableTable: 
   Start  Length  Slot  Name   Signature
   0      13      0    $this       Lscala/collection/generic/TraversableProxyTemplate;
   0      13      1    p       Lscala/Function1;


public static int count(scala.collection.generic.TraversableProxyTemplate, scala.Function1);
  Code:
   Stack=2, Locals=2, Args_size=2
   0:	aload_0
   1:	invokeinterface	#17,  1; //InterfaceMethod scala/collection/generic/TraversableProxyTemplate.self:()Lscala/collection/generic/TraversableTemplate;
   6:	aload_1
   7:	invokeinterface	#212,  2; //InterfaceMethod scala/collection/generic/TraversableTemplate.count:(Lscala/Function1;)I
   12:	ireturn
  LineNumberTable: 
   line 45: 0

  LocalVariableTable: 
   Start  Length  Slot  Name   Signature
   0      13      0    $this       Lscala/collection/generic/TraversableProxyTemplate;
   0      13      1    p       Lscala/Function1;


public static boolean exists(scala.collection.generic.TraversableProxyTemplate, scala.Function1);
  Code:
   Stack=2, Locals=2, Args_size=2
   0:	aload_0
   1:	invokeinterface	#17,  1; //InterfaceMethod scala/collection/generic/TraversableProxyTemplate.self:()Lscala/collection/generic/TraversableTemplate;
   6:	aload_1
   7:	invokeinterface	#217,  2; //InterfaceMethod scala/collection/generic/TraversableTemplate.exists:(Lscala/Function1;)Z
   12:	ireturn
  LineNumberTable: 
   line 44: 0

  LocalVariableTable: 
   Start  Length  Slot  Name   Signature
   0      13      0    $this       Lscala/collection/generic/TraversableProxyTemplate;
   0      13      1    p       Lscala/Function1;


public static boolean forall(scala.collection.generic.TraversableProxyTemplate, scala.Function1);
  Code:
   Stack=2, Locals=2, Args_size=2
   0:	aload_0
   1:	invokeinterface	#17,  1; //InterfaceMethod scala/collection/generic/TraversableProxyTemplate.self:()Lscala/collection/generic/TraversableTemplate;
   6:	aload_1
   7:	invokeinterface	#220,  2; //InterfaceMethod scala/collection/generic/TraversableTemplate.forall:(Lscala/Function1;)Z
   12:	ireturn
  LineNumberTable: 
   line 43: 0

  LocalVariableTable: 
   Start  Length  Slot  Name   Signature
   0      13      0    $this       Lscala/collection/generic/TraversableProxyTemplate;
   0      13      1    p       Lscala/Function1;


public static scala.collection.Map groupBy(scala.collection.generic.TraversableProxyTemplate, scala.Function1);
  Code:
   Stack=2, Locals=2, Args_size=2
   0:	aload_0
   1:	invokeinterface	#17,  1; //InterfaceMethod scala/collection/generic/TraversableProxyTemplate.self:()Lscala/collection/generic/TraversableTemplate;
   6:	aload_1
   7:	invokeinterface	#225,  2; //InterfaceMethod scala/collection/generic/TraversableTemplate.groupBy:(Lscala/Function1;)Lscala/collection/Map;
   12:	areturn
  LineNumberTable: 
   line 42: 0

  LocalVariableTable: 
   Start  Length  Slot  Name   Signature
   0      13      0    $this       Lscala/collection/generic/TraversableProxyTemplate;
   0      13      1    f       Lscala/Function1;


public static scala.Tuple2 partition(scala.collection.generic.TraversableProxyTemplate, scala.Function1);
  Code:
   Stack=2, Locals=2, Args_size=2
   0:	aload_0
   1:	invokeinterface	#17,  1; //InterfaceMethod scala/collection/generic/TraversableProxyTemplate.self:()Lscala/collection/generic/TraversableTemplate;
   6:	aload_1
   7:	invokeinterface	#229,  2; //InterfaceMethod scala/collection/generic/TraversableTemplate.partition:(Lscala/Function1;)Lscala/Tuple2;
   12:	areturn
  LineNumberTable: 
   line 41: 0

  LocalVariableTable: 
   Start  Length  Slot  Name   Signature
   0      13      0    $this       Lscala/collection/generic/TraversableProxyTemplate;
   0      13      1    p       Lscala/Function1;


public static scala.collection.generic.TraversableTemplate remove(scala.collection.generic.TraversableProxyTemplate, scala.Function1);
  Code:
   Stack=2, Locals=2, Args_size=2
   0:	aload_0
   1:	invokeinterface	#17,  1; //InterfaceMethod scala/collection/generic/TraversableProxyTemplate.self:()Lscala/collection/generic/TraversableTemplate;
   6:	aload_1
   7:	invokeinterface	#232,  2; //InterfaceMethod scala/collection/generic/TraversableTemplate.remove:(Lscala/Function1;)Lscala/collection/generic/TraversableTemplate;
   12:	areturn
  LineNumberTable: 
   line 40: 0

  LocalVariableTable: 
   Start  Length  Slot  Name   Signature
   0      13      0    $this       Lscala/collection/generic/TraversableProxyTemplate;
   0      13      1    p       Lscala/Function1;


public static scala.collection.generic.TraversableTemplate filterNot(scala.collection.generic.TraversableProxyTemplate, scala.Function1);
  Code:
   Stack=2, Locals=2, Args_size=2
   0:	aload_0
   1:	invokeinterface	#17,  1; //InterfaceMethod scala/collection/generic/TraversableProxyTemplate.self:()Lscala/collection/generic/TraversableTemplate;
   6:	aload_1
   7:	invokeinterface	#235,  2; //InterfaceMethod scala/collection/generic/TraversableTemplate.filterNot:(Lscala/Function1;)Lscala/collection/generic/TraversableTemplate;
   12:	areturn
  LineNumberTable: 
   line 39: 0

  LocalVariableTable: 
   Start  Length  Slot  Name   Signature
   0      13      0    $this       Lscala/collection/generic/TraversableProxyTemplate;
   0      13      1    p       Lscala/Function1;


public static scala.collection.generic.TraversableTemplate filter(scala.collection.generic.TraversableProxyTemplate, scala.Function1);
  Code:
   Stack=2, Locals=2, Args_size=2
   0:	aload_0
   1:	invokeinterface	#17,  1; //InterfaceMethod scala/collection/generic/TraversableProxyTemplate.self:()Lscala/collection/generic/TraversableTemplate;
   6:	aload_1
   7:	invokeinterface	#238,  2; //InterfaceMethod scala/collection/generic/TraversableTemplate.filter:(Lscala/Function1;)Lscala/collection/generic/TraversableTemplate;
   12:	areturn
  LineNumberTable: 
   line 38: 0

  LocalVariableTable: 
   Start  Length  Slot  Name   Signature
   0      13      0    $this       Lscala/collection/generic/TraversableProxyTemplate;
   0      13      1    p       Lscala/Function1;


public static java.lang.Object flatMap(scala.collection.generic.TraversableProxyTemplate, scala.Function1, scala.collection.generic.BuilderFactory);
  Code:
   Stack=3, Locals=3, Args_size=3
   0:	aload_0
   1:	invokeinterface	#17,  1; //InterfaceMethod scala/collection/generic/TraversableProxyTemplate.self:()Lscala/collection/generic/TraversableTemplate;
   6:	aload_1
   7:	aload_2
   8:	invokeinterface	#243,  3; //InterfaceMethod scala/collection/generic/TraversableTemplate.flatMap:(Lscala/Function1;Lscala/collection/generic/BuilderFactory;)Ljava/lang/Object;
   13:	areturn
  LineNumberTable: 
   line 37: 0

  LocalVariableTable: 
   Start  Length  Slot  Name   Signature
   0      14      0    $this       Lscala/collection/generic/TraversableProxyTemplate;
   0      14      1    f       Lscala/Function1;
   0      14      2    bf       Lscala/collection/generic/BuilderFactory;


public static java.lang.Object map(scala.collection.generic.TraversableProxyTemplate, scala.Function1, scala.collection.generic.BuilderFactory);
  Code:
   Stack=3, Locals=3, Args_size=3
   0:	aload_0
   1:	invokeinterface	#17,  1; //InterfaceMethod scala/collection/generic/TraversableProxyTemplate.self:()Lscala/collection/generic/TraversableTemplate;
   6:	aload_1
   7:	aload_2
   8:	invokeinterface	#248,  3; //InterfaceMethod scala/collection/generic/TraversableTemplate.map:(Lscala/Function1;Lscala/collection/generic/BuilderFactory;)Ljava/lang/Object;
   13:	areturn
  LineNumberTable: 
   line 36: 0

  LocalVariableTable: 
   Start  Length  Slot  Name   Signature
   0      14      0    $this       Lscala/collection/generic/TraversableProxyTemplate;
   0      14      1    f       Lscala/Function1;
   0      14      2    bf       Lscala/collection/generic/BuilderFactory;


public static java.lang.Object $plus$plus(scala.collection.generic.TraversableProxyTemplate, scala.collection.Iterator, scala.collection.generic.BuilderFactory);
  Code:
   Stack=3, Locals=3, Args_size=3
   0:	aload_0
   1:	invokeinterface	#17,  1; //InterfaceMethod scala/collection/generic/TraversableProxyTemplate.self:()Lscala/collection/generic/TraversableTemplate;
   6:	aload_1
   7:	aload_2
   8:	invokeinterface	#253,  3; //InterfaceMethod scala/collection/generic/TraversableTemplate.$plus$plus:(Lscala/collection/Iterator;Lscala/collection/generic/BuilderFactory;)Ljava/lang/Object;
   13:	areturn
  LineNumberTable: 
   line 35: 0

  LocalVariableTable: 
   Start  Length  Slot  Name   Signature
   0      14      0    $this       Lscala/collection/generic/TraversableProxyTemplate;
   0      14      1    that       Lscala/collection/Iterator;
   0      14      2    bf       Lscala/collection/generic/BuilderFactory;


public static java.lang.Object $plus$plus(scala.collection.generic.TraversableProxyTemplate, scala.collection.Traversable, scala.collection.generic.BuilderFactory);
  Code:
   Stack=3, Locals=3, Args_size=3
   0:	aload_0
   1:	invokeinterface	#17,  1; //InterfaceMethod scala/collection/generic/TraversableProxyTemplate.self:()Lscala/collection/generic/TraversableTemplate;
   6:	aload_1
   7:	aload_2
   8:	invokeinterface	#259,  3; //InterfaceMethod scala/collection/generic/TraversableTemplate.$plus$plus:(Lscala/collection/Traversable;Lscala/collection/generic/BuilderFactory;)Ljava/lang/Object;
   13:	areturn
  LineNumberTable: 
   line 34: 0

  LocalVariableTable: 
   Start  Length  Slot  Name   Signature
   0      14      0    $this       Lscala/collection/generic/TraversableProxyTemplate;
   0      14      1    that       Lscala/collection/Traversable;
   0      14      2    bf       Lscala/collection/generic/BuilderFactory;


public static boolean hasDefiniteSize(scala.collection.generic.TraversableProxyTemplate);
  Code:
   Stack=1, Locals=1, Args_size=1
   0:	aload_0
   1:	invokeinterface	#17,  1; //InterfaceMethod scala/collection/generic/TraversableProxyTemplate.self:()Lscala/collection/generic/TraversableTemplate;
   6:	invokeinterface	#265,  1; //InterfaceMethod scala/collection/generic/TraversableTemplate.hasDefiniteSize:()Z
   11:	ireturn
  LineNumberTable: 
   line 33: 0

  LocalVariableTable: 
   Start  Length  Slot  Name   Signature
   0      12      0    $this       Lscala/collection/generic/TraversableProxyTemplate;


public static int size(scala.collection.generic.TraversableProxyTemplate);
  Code:
   Stack=1, Locals=1, Args_size=1
   0:	aload_0
   1:	invokeinterface	#17,  1; //InterfaceMethod scala/collection/generic/TraversableProxyTemplate.self:()Lscala/collection/generic/TraversableTemplate;
   6:	invokeinterface	#270,  1; //InterfaceMethod scala/collection/generic/TraversableTemplate.size:()I
   11:	ireturn
  LineNumberTable: 
   line 32: 0

  LocalVariableTable: 
   Start  Length  Slot  Name   Signature
   0      12      0    $this       Lscala/collection/generic/TraversableProxyTemplate;


public static boolean nonEmpty(scala.collection.generic.TraversableProxyTemplate);
  Code:
   Stack=1, Locals=1, Args_size=1
   0:	aload_0
   1:	invokeinterface	#17,  1; //InterfaceMethod scala/collection/generic/TraversableProxyTemplate.self:()Lscala/collection/generic/TraversableTemplate;
   6:	invokeinterface	#273,  1; //InterfaceMethod scala/collection/generic/TraversableTemplate.nonEmpty:()Z
   11:	ireturn
  LineNumberTable: 
   line 31: 0

  LocalVariableTable: 
   Start  Length  Slot  Name   Signature
   0      12      0    $this       Lscala/collection/generic/TraversableProxyTemplate;


public static boolean isEmpty(scala.collection.generic.TraversableProxyTemplate);
  Code:
   Stack=1, Locals=1, Args_size=1
   0:	aload_0
   1:	invokeinterface	#17,  1; //InterfaceMethod scala/collection/generic/TraversableProxyTemplate.self:()Lscala/collection/generic/TraversableTemplate;
   6:	invokeinterface	#276,  1; //InterfaceMethod scala/collection/generic/TraversableTemplate.isEmpty:()Z
   11:	ireturn
  LineNumberTable: 
   line 30: 0

  LocalVariableTable: 
   Start  Length  Slot  Name   Signature
   0      12      0    $this       Lscala/collection/generic/TraversableProxyTemplate;


public static void foreach(scala.collection.generic.TraversableProxyTemplate, scala.Function1);
  Code:
   Stack=2, Locals=2, Args_size=2
   0:	aload_0
   1:	invokeinterface	#17,  1; //InterfaceMethod scala/collection/generic/TraversableProxyTemplate.self:()Lscala/collection/generic/TraversableTemplate;
   6:	checkcast	#280; //class scala/collection/generic/TraversableClass
   9:	aload_1
   10:	invokeinterface	#283,  2; //InterfaceMethod scala/collection/generic/TraversableClass.foreach:(Lscala/Function1;)V
   15:	return
  LineNumberTable: 
   line 29: 0

  LocalVariableTable: 
   Start  Length  Slot  Name   Signature
   0      16      0    $this       Lscala/collection/generic/TraversableProxyTemplate;
   0      16      1    f       Lscala/Function1;


}

