Compiled from "TraversableClass.scala"
public abstract class scala.collection.generic.TraversableClass$class extends java.lang.Object
  SourceFile: "TraversableClass.scala"
  Scala: length = 0x
   
  InnerClass: 
   public final #134= #37 of #19; //$anonfun$1=class scala/collection/generic/TraversableClass$$anonfun$1 of class scala/collection/generic/TraversableClass
   public final #135= #110 of #19; //$anonfun$unzip$1=class scala/collection/generic/TraversableClass$$anonfun$unzip$1 of class scala/collection/generic/TraversableClass
   public final #136= #101 of #19; //$anonfun$flatten$1=class scala/collection/generic/TraversableClass$$anonfun$flatten$1 of class scala/collection/generic/TraversableClass
   public final #137= #69 of #19; //$anonfun$transpose$1=class scala/collection/generic/TraversableClass$$anonfun$transpose$1 of class scala/collection/generic/TraversableClass
   public final #138= #82 of #19; //$anonfun$transpose$2=class scala/collection/generic/TraversableClass$$anonfun$transpose$2 of class scala/collection/generic/TraversableClass
  minor version: 0
  major version: 49
  Constant pool:
const #1 = Asciz	SourceFile;
const #2 = Asciz	TraversableClass.scala;
const #3 = Asciz	$init$;
const #4 = Asciz	(Lscala/collection/generic/TraversableClass;)V;
const #5 = Asciz	Code;
const #6 = Asciz	LineNumberTable;
const #7 = Asciz	$this;
const #8 = Asciz	Lscala/collection/generic/TraversableClass;;
const #9 = Asciz	LocalVariableTable;
const #10 = Asciz	transpose;
const #11 = Asciz	(Lscala/collection/generic/TraversableClass;Lscala/Function1;)Lscala/collection/Traversable;;
const #12 = Asciz	scala/runtime/ScalaRunTime$;
const #13 = class	#12;	//  scala/runtime/ScalaRunTime$
const #14 = Asciz	MODULE$;
const #15 = Asciz	Lscala/runtime/ScalaRunTime$;;
const #16 = NameAndType	#14:#15;//  MODULE$:Lscala/runtime/ScalaRunTime$;
const #17 = Field	#13.#16;	//  scala/runtime/ScalaRunTime$.MODULE$:Lscala/runtime/ScalaRunTime$;
const #18 = Asciz	scala/collection/generic/TraversableClass;
const #19 = class	#18;	//  scala/collection/generic/TraversableClass
const #20 = Asciz	head;
const #21 = Asciz	()Ljava/lang/Object;;
const #22 = NameAndType	#20:#21;//  head:()Ljava/lang/Object;
const #23 = InterfaceMethod	#19.#22;	//  scala/collection/generic/TraversableClass.head:()Ljava/lang/Object;
const #24 = Asciz	scala/Function1;
const #25 = class	#24;	//  scala/Function1
const #26 = Asciz	apply;
const #27 = Asciz	(Ljava/lang/Object;)Ljava/lang/Object;;
const #28 = NameAndType	#26:#27;//  apply:(Ljava/lang/Object;)Ljava/lang/Object;
const #29 = InterfaceMethod	#25.#28;	//  scala/Function1.apply:(Ljava/lang/Object;)Ljava/lang/Object;
const #30 = Asciz	scala/collection/generic/TraversableTemplate;
const #31 = class	#30;	//  scala/collection/generic/TraversableTemplate
const #32 = Asciz	boxArray;
const #33 = Asciz	(Ljava/lang/Object;)Lscala/runtime/BoxedArray;;
const #34 = NameAndType	#32:#33;//  boxArray:(Ljava/lang/Object;)Lscala/runtime/BoxedArray;
const #35 = Method	#13.#34;	//  scala/runtime/ScalaRunTime$.boxArray:(Ljava/lang/Object;)Lscala/runtime/BoxedArray;
const #36 = Asciz	scala/collection/generic/TraversableClass$$anonfun$1;
const #37 = class	#36;	//  scala/collection/generic/TraversableClass$$anonfun$1
const #38 = Asciz	<init>;
const #39 = NameAndType	#38:#4;//  "<init>":(Lscala/collection/generic/TraversableClass;)V
const #40 = Method	#37.#39;	//  scala/collection/generic/TraversableClass$$anonfun$1."<init>":(Lscala/collection/generic/TraversableClass;)V
const #41 = Asciz	scala/collection/Traversable$;
const #42 = class	#41;	//  scala/collection/Traversable$
const #43 = Asciz	Lscala/collection/Traversable$;;
const #44 = NameAndType	#14:#43;//  MODULE$:Lscala/collection/Traversable$;
const #45 = Field	#42.#44;	//  scala/collection/Traversable$.MODULE$:Lscala/collection/Traversable$;
const #46 = Asciz	builderFactory;
const #47 = Asciz	()Lscala/collection/generic/BuilderFactory;;
const #48 = NameAndType	#46:#47;//  builderFactory:()Lscala/collection/generic/BuilderFactory;
const #49 = Method	#42.#48;	//  scala/collection/Traversable$.builderFactory:()Lscala/collection/generic/BuilderFactory;
const #50 = Asciz	map;
const #51 = Asciz	(Lscala/Function1;Lscala/collection/generic/BuilderFactory;)Ljava/lang/Object;;
const #52 = NameAndType	#50:#51;//  map:(Lscala/Function1;Lscala/collection/generic/BuilderFactory;)Ljava/lang/Object;
const #53 = InterfaceMethod	#31.#52;	//  scala/collection/generic/TraversableTemplate.map:(Lscala/Function1;Lscala/collection/generic/BuilderFactory;)Ljava/lang/Object;
const #54 = Asciz	toArray;
const #55 = Asciz	()Lscala/runtime/BoxedArray;;
const #56 = NameAndType	#54:#55;//  toArray:()Lscala/runtime/BoxedArray;
const #57 = InterfaceMethod	#31.#56;	//  scala/collection/generic/TraversableTemplate.toArray:()Lscala/runtime/BoxedArray;
const #58 = Asciz	scala/collection/generic/Builder;
const #59 = class	#58;	//  scala/collection/generic/Builder
const #60 = Asciz	arrayValue;
const #61 = Asciz	(Lscala/runtime/BoxedArray;Ljava/lang/Class;)Ljava/lang/Object;;
const #62 = NameAndType	#60:#61;//  arrayValue:(Lscala/runtime/BoxedArray;Ljava/lang/Class;)Ljava/lang/Object;
const #63 = Method	#13.#62;	//  scala/runtime/ScalaRunTime$.arrayValue:(Lscala/runtime/BoxedArray;Ljava/lang/Class;)Ljava/lang/Object;
const #64 = Asciz	scala/runtime/BoxedArray;
const #65 = class	#64;	//  scala/runtime/BoxedArray
const #66 = Asciz	[Lscala/collection/generic/Builder;;
const #67 = class	#66;	//  "[Lscala/collection/generic/Builder;"
const #68 = Asciz	scala/collection/generic/TraversableClass$$anonfun$transpose$1;
const #69 = class	#68;	//  scala/collection/generic/TraversableClass$$anonfun$transpose$1
const #70 = Asciz	(Lscala/collection/generic/TraversableClass;Lscala/Function1;[Lscala/collection/generic/Builder;)V;
const #71 = NameAndType	#38:#70;//  "<init>":(Lscala/collection/generic/TraversableClass;Lscala/Function1;[Lscala/collection/generic/Builder;)V
const #72 = Method	#69.#71;	//  scala/collection/generic/TraversableClass$$anonfun$transpose$1."<init>":(Lscala/collection/generic/TraversableClass;Lscala/Function1;[Lscala/collection/generic/Builder;)V
const #73 = Asciz	foreach;
const #74 = Asciz	(Lscala/Function1;)V;
const #75 = NameAndType	#73:#74;//  foreach:(Lscala/Function1;)V
const #76 = InterfaceMethod	#19.#75;	//  scala/collection/generic/TraversableClass.foreach:(Lscala/Function1;)V
const #77 = Asciz	genericBuilder;
const #78 = Asciz	()Lscala/collection/generic/Builder;;
const #79 = NameAndType	#77:#78;//  genericBuilder:()Lscala/collection/generic/Builder;
const #80 = InterfaceMethod	#19.#79;	//  scala/collection/generic/TraversableClass.genericBuilder:()Lscala/collection/generic/Builder;
const #81 = Asciz	scala/collection/generic/TraversableClass$$anonfun$transpose$2;
const #82 = class	#81;	//  scala/collection/generic/TraversableClass$$anonfun$transpose$2
const #83 = Asciz	(Lscala/collection/generic/TraversableClass;Lscala/collection/generic/Builder;)V;
const #84 = NameAndType	#38:#83;//  "<init>":(Lscala/collection/generic/TraversableClass;Lscala/collection/generic/Builder;)V
const #85 = Method	#82.#84;	//  scala/collection/generic/TraversableClass$$anonfun$transpose$2."<init>":(Lscala/collection/generic/TraversableClass;Lscala/collection/generic/Builder;)V
const #86 = Asciz	scala/collection/generic/VectorTemplate;
const #87 = class	#86;	//  scala/collection/generic/VectorTemplate
const #88 = InterfaceMethod	#87.#75;	//  scala/collection/generic/VectorTemplate.foreach:(Lscala/Function1;)V
const #89 = Asciz	result;
const #90 = NameAndType	#89:#21;//  result:()Ljava/lang/Object;
const #91 = InterfaceMethod	#59.#90;	//  scala/collection/generic/Builder.result:()Ljava/lang/Object;
const #92 = Asciz	scala/collection/Traversable;
const #93 = class	#92;	//  scala/collection/Traversable
const #94 = Asciz	toTraversable$2;
const #95 = Asciz	Lscala/Function1;;
const #96 = Asciz	bs$1;
const #97 = Asciz	bb$1;
const #98 = Asciz	Lscala/collection/generic/Builder;;
const #99 = Asciz	flatten;
const #100 = Asciz	scala/collection/generic/TraversableClass$$anonfun$flatten$1;
const #101 = class	#100;	//  scala/collection/generic/TraversableClass$$anonfun$flatten$1
const #102 = Asciz	(Lscala/collection/generic/TraversableClass;Lscala/Function1;Lscala/collection/generic/Builder;)V;
const #103 = NameAndType	#38:#102;//  "<init>":(Lscala/collection/generic/TraversableClass;Lscala/Function1;Lscala/collection/generic/Builder;)V
const #104 = Method	#101.#103;	//  scala/collection/generic/TraversableClass$$anonfun$flatten$1."<init>":(Lscala/collection/generic/TraversableClass;Lscala/Function1;Lscala/collection/generic/Builder;)V
const #105 = Asciz	toTraversable$1;
const #106 = Asciz	b$1;
const #107 = Asciz	unzip;
const #108 = Asciz	(Lscala/collection/generic/TraversableClass;Lscala/Function1;)Lscala/Tuple2;;
const #109 = Asciz	scala/collection/generic/TraversableClass$$anonfun$unzip$1;
const #110 = class	#109;	//  scala/collection/generic/TraversableClass$$anonfun$unzip$1
const #111 = Asciz	(Lscala/collection/generic/TraversableClass;Lscala/Function1;Lscala/collection/generic/Builder;Lscala/collection/generic/Builder;)V;
const #112 = NameAndType	#38:#111;//  "<init>":(Lscala/collection/generic/TraversableClass;Lscala/Function1;Lscala/collection/generic/Builder;Lscala/collection/generic/Builder;)V
const #113 = Method	#110.#112;	//  scala/collection/generic/TraversableClass$$anonfun$unzip$1."<init>":(Lscala/collection/generic/TraversableClass;Lscala/Function1;Lscala/collection/generic/Builder;Lscala/collection/generic/Builder;)V
const #114 = Asciz	scala/Tuple2;
const #115 = class	#114;	//  scala/Tuple2
const #116 = Asciz	(Ljava/lang/Object;Ljava/lang/Object;)V;
const #117 = NameAndType	#38:#116;//  "<init>":(Ljava/lang/Object;Ljava/lang/Object;)V
const #118 = Method	#115.#117;	//  scala/Tuple2."<init>":(Ljava/lang/Object;Ljava/lang/Object;)V
const #119 = Asciz	toPair$1;
const #120 = Asciz	b1$1;
const #121 = Asciz	b2$1;
const #122 = Asciz	(Lscala/collection/generic/TraversableClass;)Lscala/collection/generic/Builder;;
const #123 = Asciz	companion;
const #124 = Asciz	()Lscala/collection/generic/Companion;;
const #125 = NameAndType	#123:#124;//  companion:()Lscala/collection/generic/Companion;
const #126 = InterfaceMethod	#19.#125;	//  scala/collection/generic/TraversableClass.companion:()Lscala/collection/generic/Companion;
const #127 = Asciz	scala/collection/generic/Companion;
const #128 = class	#127;	//  scala/collection/generic/Companion
const #129 = Asciz	newBuilder;
const #130 = NameAndType	#129:#78;//  newBuilder:()Lscala/collection/generic/Builder;
const #131 = Method	#128.#130;	//  scala/collection/generic/Companion.newBuilder:()Lscala/collection/generic/Builder;
const #132 = Asciz	Scala;
const #133 = Asciz	InnerClasses;
const #134 = Asciz	$anonfun$1;
const #135 = Asciz	$anonfun$unzip$1;
const #136 = Asciz	$anonfun$flatten$1;
const #137 = Asciz	$anonfun$transpose$1;
const #138 = Asciz	$anonfun$transpose$2;
const #139 = Asciz	scala/collection/generic/TraversableClass$class;
const #140 = class	#139;	//  scala/collection/generic/TraversableClass$class
const #141 = Asciz	java/lang/Object;
const #142 = class	#141;	//  java/lang/Object

{
public static void $init$(scala.collection.generic.TraversableClass);
  Code:
   Stack=0, Locals=1, Args_size=1
   0:	return
  LineNumberTable: 
   line 17: 0

  LocalVariableTable: 
   Start  Length  Slot  Name   Signature
   0      1      0    $this       Lscala/collection/generic/TraversableClass;


public static scala.collection.Traversable transpose(scala.collection.generic.TraversableClass, scala.Function1);
  Code:
   Stack=6, Locals=8, Args_size=2
   0:	getstatic	#17; //Field scala/runtime/ScalaRunTime$.MODULE$:Lscala/runtime/ScalaRunTime$;
   3:	aload_1
   4:	aload_0
   5:	invokeinterface	#23,  1; //InterfaceMethod scala/collection/generic/TraversableClass.head:()Ljava/lang/Object;
   10:	invokeinterface	#29,  2; //InterfaceMethod scala/Function1.apply:(Ljava/lang/Object;)Ljava/lang/Object;
   15:	astore	5
   17:	aload	5
   19:	instanceof	#31; //class scala/collection/generic/TraversableTemplate
   22:	ifeq	30
   25:	aload	5
   27:	goto	38
   30:	getstatic	#17; //Field scala/runtime/ScalaRunTime$.MODULE$:Lscala/runtime/ScalaRunTime$;
   33:	aload	5
   35:	invokevirtual	#35; //Method scala/runtime/ScalaRunTime$.boxArray:(Ljava/lang/Object;)Lscala/runtime/BoxedArray;
   38:	checkcast	#31; //class scala/collection/generic/TraversableTemplate
   41:	new	#37; //class scala/collection/generic/TraversableClass$$anonfun$1
   44:	dup
   45:	aload_0
   46:	invokespecial	#40; //Method scala/collection/generic/TraversableClass$$anonfun$1."<init>":(Lscala/collection/generic/TraversableClass;)V
   49:	getstatic	#45; //Field scala/collection/Traversable$.MODULE$:Lscala/collection/Traversable$;
   52:	invokevirtual	#49; //Method scala/collection/Traversable$.builderFactory:()Lscala/collection/generic/BuilderFactory;
   55:	invokeinterface	#53,  3; //InterfaceMethod scala/collection/generic/TraversableTemplate.map:(Lscala/Function1;Lscala/collection/generic/BuilderFactory;)Ljava/lang/Object;
   60:	astore	4
   62:	aload	4
   64:	instanceof	#31; //class scala/collection/generic/TraversableTemplate
   67:	ifeq	75
   70:	aload	4
   72:	goto	83
   75:	getstatic	#17; //Field scala/runtime/ScalaRunTime$.MODULE$:Lscala/runtime/ScalaRunTime$;
   78:	aload	4
   80:	invokevirtual	#35; //Method scala/runtime/ScalaRunTime$.boxArray:(Ljava/lang/Object;)Lscala/runtime/BoxedArray;
   83:	checkcast	#31; //class scala/collection/generic/TraversableTemplate
   86:	invokeinterface	#57,  1; //InterfaceMethod scala/collection/generic/TraversableTemplate.toArray:()Lscala/runtime/BoxedArray;
   91:	ldc	#59; //class scala/collection/generic/Builder
   93:	invokevirtual	#63; //Method scala/runtime/ScalaRunTime$.arrayValue:(Lscala/runtime/BoxedArray;Ljava/lang/Class;)Ljava/lang/Object;
   96:	astore_3
   97:	aload_3
   98:	instanceof	#65; //class scala/runtime/BoxedArray
   101:	ifeq	119
   104:	getstatic	#17; //Field scala/runtime/ScalaRunTime$.MODULE$:Lscala/runtime/ScalaRunTime$;
   107:	aload_3
   108:	checkcast	#65; //class scala/runtime/BoxedArray
   111:	ldc	#59; //class scala/collection/generic/Builder
   113:	invokevirtual	#63; //Method scala/runtime/ScalaRunTime$.arrayValue:(Lscala/runtime/BoxedArray;Ljava/lang/Class;)Ljava/lang/Object;
   116:	goto	120
   119:	aload_3
   120:	checkcast	#67; //class "[Lscala/collection/generic/Builder;"
   123:	astore_2
   124:	aload_0
   125:	new	#69; //class scala/collection/generic/TraversableClass$$anonfun$transpose$1
   128:	dup
   129:	aload_0
   130:	aload_1
   131:	aload_2
   132:	invokespecial	#72; //Method scala/collection/generic/TraversableClass$$anonfun$transpose$1."<init>":(Lscala/collection/generic/TraversableClass;Lscala/Function1;[Lscala/collection/generic/Builder;)V
   135:	invokeinterface	#76,  2; //InterfaceMethod scala/collection/generic/TraversableClass.foreach:(Lscala/Function1;)V
   140:	aload_0
   141:	invokeinterface	#80,  1; //InterfaceMethod scala/collection/generic/TraversableClass.genericBuilder:()Lscala/collection/generic/Builder;
   146:	astore	6
   148:	getstatic	#17; //Field scala/runtime/ScalaRunTime$.MODULE$:Lscala/runtime/ScalaRunTime$;
   151:	aload_2
   152:	invokevirtual	#35; //Method scala/runtime/ScalaRunTime$.boxArray:(Ljava/lang/Object;)Lscala/runtime/BoxedArray;
   155:	new	#82; //class scala/collection/generic/TraversableClass$$anonfun$transpose$2
   158:	dup
   159:	aload_0
   160:	aload	6
   162:	invokespecial	#85; //Method scala/collection/generic/TraversableClass$$anonfun$transpose$2."<init>":(Lscala/collection/generic/TraversableClass;Lscala/collection/generic/Builder;)V
   165:	invokeinterface	#88,  2; //InterfaceMethod scala/collection/generic/VectorTemplate.foreach:(Lscala/Function1;)V
   170:	aload	6
   172:	invokeinterface	#91,  1; //InterfaceMethod scala/collection/generic/Builder.result:()Ljava/lang/Object;
   177:	astore	7
   179:	aload	7
   181:	instanceof	#93; //class scala/collection/Traversable
   184:	ifeq	192
   187:	aload	7
   189:	goto	200
   192:	getstatic	#17; //Field scala/runtime/ScalaRunTime$.MODULE$:Lscala/runtime/ScalaRunTime$;
   195:	aload	7
   197:	invokevirtual	#35; //Method scala/runtime/ScalaRunTime$.boxArray:(Ljava/lang/Object;)Lscala/runtime/BoxedArray;
   200:	checkcast	#93; //class scala/collection/Traversable
   203:	areturn
  LineNumberTable: 
   line 51: 0
   line 61: 120
   line 51: 123
   line 52: 124
   line 59: 140
   line 60: 148
   line 61: 170

  LocalVariableTable: 
   Start  Length  Slot  Name   Signature
   0      204      0    $this       Lscala/collection/generic/TraversableClass;
   0      204      1    toTraversable$2       Lscala/Function1;
   124      79      2    bs$1       [Lscala/collection/generic/Builder;
   148      55      6    bb$1       Lscala/collection/generic/Builder;


public static scala.collection.Traversable flatten(scala.collection.generic.TraversableClass, scala.Function1);
  Code:
   Stack=6, Locals=4, Args_size=2
   0:	aload_0
   1:	invokeinterface	#80,  1; //InterfaceMethod scala/collection/generic/TraversableClass.genericBuilder:()Lscala/collection/generic/Builder;
   6:	astore_2
   7:	aload_0
   8:	new	#101; //class scala/collection/generic/TraversableClass$$anonfun$flatten$1
   11:	dup
   12:	aload_0
   13:	aload_1
   14:	aload_2
   15:	invokespecial	#104; //Method scala/collection/generic/TraversableClass$$anonfun$flatten$1."<init>":(Lscala/collection/generic/TraversableClass;Lscala/Function1;Lscala/collection/generic/Builder;)V
   18:	invokeinterface	#76,  2; //InterfaceMethod scala/collection/generic/TraversableClass.foreach:(Lscala/Function1;)V
   23:	aload_2
   24:	invokeinterface	#91,  1; //InterfaceMethod scala/collection/generic/Builder.result:()Ljava/lang/Object;
   29:	astore_3
   30:	aload_3
   31:	instanceof	#93; //class scala/collection/Traversable
   34:	ifeq	41
   37:	aload_3
   38:	goto	48
   41:	getstatic	#17; //Field scala/runtime/ScalaRunTime$.MODULE$:Lscala/runtime/ScalaRunTime$;
   44:	aload_3
   45:	invokevirtual	#35; //Method scala/runtime/ScalaRunTime$.boxArray:(Ljava/lang/Object;)Lscala/runtime/BoxedArray;
   48:	checkcast	#93; //class scala/collection/Traversable
   51:	areturn
  LineNumberTable: 
   line 44: 0
   line 45: 7
   line 47: 23

  LocalVariableTable: 
   Start  Length  Slot  Name   Signature
   0      52      0    $this       Lscala/collection/generic/TraversableClass;
   0      52      1    toTraversable$1       Lscala/Function1;
   7      44      2    b$1       Lscala/collection/generic/Builder;


public static scala.Tuple2 unzip(scala.collection.generic.TraversableClass, scala.Function1);
  Code:
   Stack=7, Locals=4, Args_size=2
   0:	aload_0
   1:	invokeinterface	#80,  1; //InterfaceMethod scala/collection/generic/TraversableClass.genericBuilder:()Lscala/collection/generic/Builder;
   6:	astore_2
   7:	aload_0
   8:	invokeinterface	#80,  1; //InterfaceMethod scala/collection/generic/TraversableClass.genericBuilder:()Lscala/collection/generic/Builder;
   13:	astore_3
   14:	aload_0
   15:	new	#110; //class scala/collection/generic/TraversableClass$$anonfun$unzip$1
   18:	dup
   19:	aload_0
   20:	aload_1
   21:	aload_2
   22:	aload_3
   23:	invokespecial	#113; //Method scala/collection/generic/TraversableClass$$anonfun$unzip$1."<init>":(Lscala/collection/generic/TraversableClass;Lscala/Function1;Lscala/collection/generic/Builder;Lscala/collection/generic/Builder;)V
   26:	invokeinterface	#76,  2; //InterfaceMethod scala/collection/generic/TraversableClass.foreach:(Lscala/Function1;)V
   31:	new	#115; //class scala/Tuple2
   34:	dup
   35:	aload_2
   36:	invokeinterface	#91,  1; //InterfaceMethod scala/collection/generic/Builder.result:()Ljava/lang/Object;
   41:	aload_3
   42:	invokeinterface	#91,  1; //InterfaceMethod scala/collection/generic/Builder.result:()Ljava/lang/Object;
   47:	invokespecial	#118; //Method scala/Tuple2."<init>":(Ljava/lang/Object;Ljava/lang/Object;)V
   50:	areturn
  LineNumberTable: 
   line 33: 0
   line 34: 7
   line 35: 14
   line 40: 31

  LocalVariableTable: 
   Start  Length  Slot  Name   Signature
   0      51      0    $this       Lscala/collection/generic/TraversableClass;
   0      51      1    toPair$1       Lscala/Function1;
   7      43      2    b1$1       Lscala/collection/generic/Builder;
   14      36      3    b2$1       Lscala/collection/generic/Builder;


public static scala.collection.generic.Builder genericBuilder(scala.collection.generic.TraversableClass);
  Code:
   Stack=1, Locals=1, Args_size=1
   0:	aload_0
   1:	invokeinterface	#126,  1; //InterfaceMethod scala/collection/generic/TraversableClass.companion:()Lscala/collection/generic/Companion;
   6:	invokevirtual	#131; //Method scala/collection/generic/Companion.newBuilder:()Lscala/collection/generic/Builder;
   9:	areturn
  LineNumberTable: 
   line 30: 0

  LocalVariableTable: 
   Start  Length  Slot  Name   Signature
   0      10      0    $this       Lscala/collection/generic/TraversableClass;


public static scala.collection.generic.Builder newBuilder(scala.collection.generic.TraversableClass);
  Code:
   Stack=1, Locals=1, Args_size=1
   0:	aload_0
   1:	invokeinterface	#126,  1; //InterfaceMethod scala/collection/generic/TraversableClass.companion:()Lscala/collection/generic/Companion;
   6:	invokevirtual	#131; //Method scala/collection/generic/Companion.newBuilder:()Lscala/collection/generic/Builder;
   9:	areturn
  LineNumberTable: 
   line 27: 0

  LocalVariableTable: 
   Start  Length  Slot  Name   Signature
   0      10      0    $this       Lscala/collection/generic/TraversableClass;


}

