Compiled from "TraversableFactory.scala"
public final class scala.collection.generic.TraversableFactory$$anonfun$tabulate$3$$anonfun$apply$3 extends scala.runtime.AbstractFunction3 implements java.io.Serializable
  SourceFile: "TraversableFactory.scala"
  Scala: length = 0x
   
  InnerClass: 
   public final $anonfun$tabulate$3=class scala/collection/generic/TraversableFactory$$anonfun$tabulate$3 of class scala/collection/generic/TraversableFactory
   public final $anonfun$apply$3=class scala/collection/generic/TraversableFactory$$anonfun$tabulate$3$$anonfun$apply$3 of class scala/collection/generic/TraversableFactory$$anonfun$tabulate$3
  minor version: 0
  major version: 49
  Constant pool:
Asciz	SourceFile;
Asciz	TraversableFactory.scala;
Asciz	<clinit>;
Asciz	()V;
Asciz	Code;
Asciz	serialVersionUID;
Asciz	J;
Asciz	scala/collection/generic/TraversableFactory$$anonfun$tabulate$3$$anonfun$apply$3;
class	scala/collection/generic/TraversableFactory$$anonfun$tabulate$3$$anonfun$apply$3
NameAndType	serialVersionUID:J
Field	scala/collection/generic/TraversableFactory$$anonfun$tabulate$3$$anonfun$apply$3.serialVersionUID:J
Asciz	i1$3;
Asciz	I;
Asciz	$outer;
Asciz	Lscala/collection/generic/TraversableFactory$$anonfun$tabulate$3;;
Asciz	<init>;
Asciz	(Lscala/collection/generic/TraversableFactory$$anonfun$tabulate$3;I)V;
Asciz	LineNumberTable;
Asciz	java/lang/NullPointerException;
class	java/lang/NullPointerException
NameAndType	"<init>":()V
Method	java/lang/NullPointerException."<init>":()V
NameAndType	$outer:Lscala/collection/generic/TraversableFactory$$anonfun$tabulate$3;
Field	scala/collection/generic/TraversableFactory$$anonfun$tabulate$3$$anonfun$apply$3.$outer:Lscala/collection/generic/TraversableFactory$$anonfun$tabulate$3;
NameAndType	i1$3:I
Field	scala/collection/generic/TraversableFactory$$anonfun$tabulate$3$$anonfun$apply$3.i1$3:I
Asciz	scala/runtime/AbstractFunction3;
class	scala/runtime/AbstractFunction3
Method	scala/runtime/AbstractFunction3."<init>":()V
Asciz	this;
Asciz	Lscala/collection/generic/TraversableFactory$$anonfun$tabulate$3$$anonfun$apply$3;;
Asciz	LocalVariableTable;
Asciz	(Lscala/collection/generic/TraversableFactory<TCC;>.$anonfun$tabulate$3;)V;
Asciz	Signature;
Asciz	apply;
Asciz	(Ljava/lang/Object;Ljava/lang/Object;Ljava/lang/Object;)Ljava/lang/Object;;
Asciz	scala/runtime/BoxesRunTime;
class	scala/runtime/BoxesRunTime
Asciz	unboxToInt;
Asciz	(Ljava/lang/Object;)I;
NameAndType	unboxToInt:(Ljava/lang/Object;)I
Method	scala/runtime/BoxesRunTime.unboxToInt:(Ljava/lang/Object;)I
Asciz	(III)Ljava/lang/Object;;
NameAndType	apply:(III)Ljava/lang/Object;
Method	scala/collection/generic/TraversableFactory$$anonfun$tabulate$3$$anonfun$apply$3.apply:(III)Ljava/lang/Object;
Asciz	v1;
Asciz	Ljava/lang/Object;;
Asciz	v2;
Asciz	v3;
Asciz	scala/collection/generic/TraversableFactory$$anonfun$tabulate$3;
class	scala/collection/generic/TraversableFactory$$anonfun$tabulate$3
Asciz	f$2;
Asciz	Lscala/Function4;;
NameAndType	f$2:Lscala/Function4;
Field	scala/collection/generic/TraversableFactory$$anonfun$tabulate$3.f$2:Lscala/Function4;
Asciz	boxToInteger;
Asciz	(I)Ljava/lang/Integer;;
NameAndType	boxToInteger:(I)Ljava/lang/Integer;
Method	scala/runtime/BoxesRunTime.boxToInteger:(I)Ljava/lang/Integer;
Asciz	scala/Function4;
class	scala/Function4
Asciz	(Ljava/lang/Object;Ljava/lang/Object;Ljava/lang/Object;Ljava/lang/Object;)Ljava/lang/Object;;
NameAndType	apply:(Ljava/lang/Object;Ljava/lang/Object;Ljava/lang/Object;Ljava/lang/Object;)Ljava/lang/Object;
InterfaceMethod	scala/Function4.apply:(Ljava/lang/Object;Ljava/lang/Object;Ljava/lang/Object;Ljava/lang/Object;)Ljava/lang/Object;
Asciz	(III)TA;;
Asciz	Scala;
Asciz	InnerClasses;
Asciz	scala/collection/generic/TraversableFactory;
class	scala/collection/generic/TraversableFactory
Asciz	$anonfun$tabulate$3;
Asciz	$anonfun$apply$3;
Asciz	java/io/Serializable;
class	java/io/Serializable

{
public static final long serialVersionUID;
  Signature: J

public final int i1$3;
  Signature: I

public final scala.collection.generic.TraversableFactory$$anonfun$tabulate$3 $outer;
  Signature: Lscala/collection/generic/TraversableFactory$$anonfun$tabulate$3;

public static {};
  Signature: ()V
  Code:
   Stack=2, Locals=0, Args_size=0
	lconst_0
	putstatic	Field serialVersionUID:J
	return
  Labels:

public scala.collection.generic.TraversableFactory$$anonfun$tabulate$3$$anonfun$apply$3(scala.collection.generic.TraversableFactory$$anonfun$tabulate$3, int);
  Signature: (Lscala/collection/generic/TraversableFactory$$anonfun$tabulate$3;I)V
  Code:
   Stack=2, Locals=3, Args_size=3
	aload_1
	ifnonnull	l1 // aload_0
	new	class java/lang/NullPointerException
	dup
	invokespecial	Method java/lang/NullPointerException."<init>":()V
	athrow
l1	aload_0
	aload_1
	putfield	Field $outer:Lscala/collection/generic/TraversableFactory$$anonfun$tabulate$3;
	aload_0
	iload_2
	putfield	Field i1$3:I
	aload_0
	invokespecial	Method scala/runtime/AbstractFunction3."<init>":()V
	return
  Labels:
   	l1 = 12 // aload_0
  LocalVariableTable: 
   Start  Length  Slot  Name   Signature
   0      27      0    this       Lscala/collection/generic/TraversableFactory$$anonfun$tabulate$3$$anonfun$apply$3;
   0      27      1    $outer       Lscala/collection/generic/TraversableFactory$$anonfun$tabulate$3;

  Signature: length = 0x2
   00 21 

public final java.lang.Object apply(java.lang.Object, java.lang.Object, java.lang.Object);
  Signature: (Ljava/lang/Object;Ljava/lang/Object;Ljava/lang/Object;)Ljava/lang/Object;
  Code:
   Stack=4, Locals=4, Args_size=4
	aload_0
	aload_1
	invokestatic	Method scala/runtime/BoxesRunTime.unboxToInt:(Ljava/lang/Object;)I
	aload_2
	invokestatic	Method scala/runtime/BoxesRunTime.unboxToInt:(Ljava/lang/Object;)I
	aload_3
	invokestatic	Method scala/runtime/BoxesRunTime.unboxToInt:(Ljava/lang/Object;)I
	invokevirtual	Method apply:(III)Ljava/lang/Object;
	areturn
  Labels:
  LocalVariableTable: 
   Start  Length  Slot  Name   Signature
   0      17      0    this       Lscala/collection/generic/TraversableFactory$$anonfun$tabulate$3$$anonfun$apply$3;
   0      17      1    v1       Ljava/lang/Object;
   0      17      2    v2       Ljava/lang/Object;
   0      17      3    v3       Ljava/lang/Object;


public final java.lang.Object apply(int, int, int);
  Signature: (III)Ljava/lang/Object;
  Code:
   Stack=5, Locals=5, Args_size=4
	aload_0
	getfield	Field $outer:Lscala/collection/generic/TraversableFactory$$anonfun$tabulate$3;
	getfield	Field scala/collection/generic/TraversableFactory$$anonfun$tabulate$3.f$2:Lscala/Function4;
	aload_0
	getfield	Field i1$3:I
	istore	4
	iload	4
	invokestatic	Method scala/runtime/BoxesRunTime.boxToInteger:(I)Ljava/lang/Integer;
	iload_1
	invokestatic	Method scala/runtime/BoxesRunTime.boxToInteger:(I)Ljava/lang/Integer;
	iload_2
	invokestatic	Method scala/runtime/BoxesRunTime.boxToInteger:(I)Ljava/lang/Integer;
	iload_3
	invokestatic	Method scala/runtime/BoxesRunTime.boxToInteger:(I)Ljava/lang/Integer;
	invokeinterface	InterfaceMethod scala/Function4.apply:(Ljava/lang/Object;Ljava/lang/Object;Ljava/lang/Object;Ljava/lang/Object;)Ljava/lang/Object;
	areturn
  Labels:
  Signature: length = 0x2
   00 41 

}

