Compiled from "TraversableViewTemplate.scala"
public abstract class scala.collection.generic.TraversableViewTemplate$Appended$class extends java.lang.Object
  SourceFile: "TraversableViewTemplate.scala"
  Scala: length = 0x
   
  InnerClass: 
   public abstract #62= #19 of #61; //Appended=class scala/collection/generic/TraversableViewTemplate$Appended of class scala/collection/generic/TraversableViewTemplate
   public final #63= #41 of #19; //$anonfun$foreach$4=class scala/collection/generic/TraversableViewTemplate$Appended$$anonfun$foreach$4 of class scala/collection/generic/TraversableViewTemplate$Appended
   public final #64= #54 of #19; //$anonfun$foreach$5=class scala/collection/generic/TraversableViewTemplate$Appended$$anonfun$foreach$5 of class scala/collection/generic/TraversableViewTemplate$Appended
  minor version: 0
  major version: 49
  Constant pool:
const #1 = Asciz	SourceFile;
const #2 = Asciz	TraversableViewTemplate.scala;
const #3 = Asciz	$init$;
const #4 = Asciz	(Lscala/collection/generic/TraversableViewTemplate$Appended;)V;
const #5 = Asciz	Code;
const #6 = Asciz	LineNumberTable;
const #7 = Asciz	$this;
const #8 = Asciz	Lscala/collection/generic/TraversableViewTemplate$Appended;;
const #9 = Asciz	LocalVariableTable;
const #10 = Asciz	stringPrefix;
const #11 = Asciz	(Lscala/collection/generic/TraversableViewTemplate$Appended;)Ljava/lang/String;;
const #12 = Asciz	scala/collection/mutable/StringBuilder;
const #13 = class	#12;	//  scala/collection/mutable/StringBuilder
const #14 = Asciz	<init>;
const #15 = Asciz	()V;
const #16 = NameAndType	#14:#15;//  "<init>":()V
const #17 = Method	#13.#16;	//  scala/collection/mutable/StringBuilder."<init>":()V
const #18 = Asciz	scala/collection/generic/TraversableViewTemplate$Appended;
const #19 = class	#18;	//  scala/collection/generic/TraversableViewTemplate$Appended
const #20 = Asciz	scala$collection$generic$TraversableViewTemplate$Appended$$$outer;
const #21 = Asciz	()Lscala/collection/generic/TraversableViewTemplate;;
const #22 = NameAndType	#20:#21;//  scala$collection$generic$TraversableViewTemplate$Appended$$$outer:()Lscala/collection/generic/TraversableViewTemplate;
const #23 = InterfaceMethod	#19.#22;	//  scala/collection/generic/TraversableViewTemplate$Appended.scala$collection$generic$TraversableViewTemplate$Appended$$$outer:()Lscala/collection/generic/TraversableViewTemplate;
const #24 = Asciz	scala/collection/generic/TraversableTemplate;
const #25 = class	#24;	//  scala/collection/generic/TraversableTemplate
const #26 = Asciz	()Ljava/lang/String;;
const #27 = NameAndType	#10:#26;//  stringPrefix:()Ljava/lang/String;
const #28 = InterfaceMethod	#25.#27;	//  scala/collection/generic/TraversableTemplate.stringPrefix:()Ljava/lang/String;
const #29 = Asciz	append;
const #30 = Asciz	(Ljava/lang/Object;)Lscala/collection/mutable/StringBuilder;;
const #31 = NameAndType	#29:#30;//  append:(Ljava/lang/Object;)Lscala/collection/mutable/StringBuilder;
const #32 = Method	#13.#31;	//  scala/collection/mutable/StringBuilder.append:(Ljava/lang/Object;)Lscala/collection/mutable/StringBuilder;
const #33 = Asciz	A;
const #34 = String	#33;	//  A
const #35 = Asciz	toString;
const #36 = NameAndType	#35:#26;//  toString:()Ljava/lang/String;
const #37 = Method	#13.#36;	//  scala/collection/mutable/StringBuilder.toString:()Ljava/lang/String;
const #38 = Asciz	foreach;
const #39 = Asciz	(Lscala/collection/generic/TraversableViewTemplate$Appended;Lscala/Function1;)V;
const #40 = Asciz	scala/collection/generic/TraversableViewTemplate$Appended$$anonfun$foreach$4;
const #41 = class	#40;	//  scala/collection/generic/TraversableViewTemplate$Appended$$anonfun$foreach$4
const #42 = NameAndType	#14:#39;//  "<init>":(Lscala/collection/generic/TraversableViewTemplate$Appended;Lscala/Function1;)V
const #43 = Method	#41.#42;	//  scala/collection/generic/TraversableViewTemplate$Appended$$anonfun$foreach$4."<init>":(Lscala/collection/generic/TraversableViewTemplate$Appended;Lscala/Function1;)V
const #44 = Asciz	scala/collection/generic/TraversableClass;
const #45 = class	#44;	//  scala/collection/generic/TraversableClass
const #46 = Asciz	(Lscala/Function1;)V;
const #47 = NameAndType	#38:#46;//  foreach:(Lscala/Function1;)V
const #48 = InterfaceMethod	#45.#47;	//  scala/collection/generic/TraversableClass.foreach:(Lscala/Function1;)V
const #49 = Asciz	rest;
const #50 = Asciz	()Lscala/collection/Traversable;;
const #51 = NameAndType	#49:#50;//  rest:()Lscala/collection/Traversable;
const #52 = InterfaceMethod	#19.#51;	//  scala/collection/generic/TraversableViewTemplate$Appended.rest:()Lscala/collection/Traversable;
const #53 = Asciz	scala/collection/generic/TraversableViewTemplate$Appended$$anonfun$foreach$5;
const #54 = class	#53;	//  scala/collection/generic/TraversableViewTemplate$Appended$$anonfun$foreach$5
const #55 = Method	#54.#42;	//  scala/collection/generic/TraversableViewTemplate$Appended$$anonfun$foreach$5."<init>":(Lscala/collection/generic/TraversableViewTemplate$Appended;Lscala/Function1;)V
const #56 = Asciz	f$6;
const #57 = Asciz	Lscala/Function1;;
const #58 = Asciz	Scala;
const #59 = Asciz	InnerClasses;
const #60 = Asciz	scala/collection/generic/TraversableViewTemplate;
const #61 = class	#60;	//  scala/collection/generic/TraversableViewTemplate
const #62 = Asciz	Appended;
const #63 = Asciz	$anonfun$foreach$4;
const #64 = Asciz	$anonfun$foreach$5;
const #65 = Asciz	scala/collection/generic/TraversableViewTemplate$Appended$class;
const #66 = class	#65;	//  scala/collection/generic/TraversableViewTemplate$Appended$class
const #67 = Asciz	java/lang/Object;
const #68 = class	#67;	//  java/lang/Object

{
public static void $init$(scala.collection.generic.TraversableViewTemplate$Appended);
  Code:
   Stack=0, Locals=1, Args_size=1
   0:	return
  LineNumberTable: 
   line 93: 0

  LocalVariableTable: 
   Start  Length  Slot  Name   Signature
   0      1      0    $this       Lscala/collection/generic/TraversableViewTemplate$Appended;


public static java.lang.String stringPrefix(scala.collection.generic.TraversableViewTemplate$Appended);
  Code:
   Stack=2, Locals=1, Args_size=1
   0:	new	#13; //class scala/collection/mutable/StringBuilder
   3:	dup
   4:	invokespecial	#17; //Method scala/collection/mutable/StringBuilder."<init>":()V
   7:	aload_0
   8:	invokeinterface	#23,  1; //InterfaceMethod scala/collection/generic/TraversableViewTemplate$Appended.scala$collection$generic$TraversableViewTemplate$Appended$$$outer:()Lscala/collection/generic/TraversableViewTemplate;
   13:	invokeinterface	#28,  1; //InterfaceMethod scala/collection/generic/TraversableTemplate.stringPrefix:()Ljava/lang/String;
   18:	invokevirtual	#32; //Method scala/collection/mutable/StringBuilder.append:(Ljava/lang/Object;)Lscala/collection/mutable/StringBuilder;
   21:	ldc	#34; //String A
   23:	invokevirtual	#32; //Method scala/collection/mutable/StringBuilder.append:(Ljava/lang/Object;)Lscala/collection/mutable/StringBuilder;
   26:	invokevirtual	#37; //Method scala/collection/mutable/StringBuilder.toString:()Ljava/lang/String;
   29:	areturn
  LineNumberTable: 
   line 99: 0

  LocalVariableTable: 
   Start  Length  Slot  Name   Signature
   0      30      0    $this       Lscala/collection/generic/TraversableViewTemplate$Appended;


public static void foreach(scala.collection.generic.TraversableViewTemplate$Appended, scala.Function1);
  Code:
   Stack=5, Locals=2, Args_size=2
   0:	aload_0
   1:	invokeinterface	#23,  1; //InterfaceMethod scala/collection/generic/TraversableViewTemplate$Appended.scala$collection$generic$TraversableViewTemplate$Appended$$$outer:()Lscala/collection/generic/TraversableViewTemplate;
   6:	new	#41; //class scala/collection/generic/TraversableViewTemplate$Appended$$anonfun$foreach$4
   9:	dup
   10:	aload_0
   11:	aload_1
   12:	invokespecial	#43; //Method scala/collection/generic/TraversableViewTemplate$Appended$$anonfun$foreach$4."<init>":(Lscala/collection/generic/TraversableViewTemplate$Appended;Lscala/Function1;)V
   15:	invokeinterface	#48,  2; //InterfaceMethod scala/collection/generic/TraversableClass.foreach:(Lscala/Function1;)V
   20:	aload_0
   21:	invokeinterface	#52,  1; //InterfaceMethod scala/collection/generic/TraversableViewTemplate$Appended.rest:()Lscala/collection/Traversable;
   26:	new	#54; //class scala/collection/generic/TraversableViewTemplate$Appended$$anonfun$foreach$5
   29:	dup
   30:	aload_0
   31:	aload_1
   32:	invokespecial	#55; //Method scala/collection/generic/TraversableViewTemplate$Appended$$anonfun$foreach$5."<init>":(Lscala/collection/generic/TraversableViewTemplate$Appended;Lscala/Function1;)V
   35:	invokeinterface	#48,  2; //InterfaceMethod scala/collection/generic/TraversableClass.foreach:(Lscala/Function1;)V
   40:	return
  LineNumberTable: 
   line 96: 0
   line 97: 20

  LocalVariableTable: 
   Start  Length  Slot  Name   Signature
   0      41      0    $this       Lscala/collection/generic/TraversableViewTemplate$Appended;
   0      41      1    f$6       Lscala/Function1;


}

