Compiled from "TraversableFactory.scala"
public abstract class scala.collection.generic.TraversableFactory extends scala.collection.generic.Companion implements scala.ScalaObject
  SourceFile: "TraversableFactory.scala"
  Signature: length = 0x2
   00 FFFFFFCD 
  ScalaSig: length = 0x81C
   05 00 FFFFFF82 27 06 05 01 02 FFFFFF81 00 09 02 12 54 72 61
   76 65 72 73 61 62 6C 65 46 61 63 74 6F 72 79 0A
   02 03 04 01 07 67 65 6E 65 72 69 63 0A 02 05 06
   01 0A 63 6F 6C 6C 65 63 74 69 6F 6E 0A 01 07 01
   05 73 63 61 6C 61 03 00 15 02 0A 11 13 03 00 0B
   2A 10 03 0C 0D 0F 0D 01 02 09 02 0E 02 02 09 43
   6F 6D 70 61 6E 69 6F 6E 10 02 10 11 0C 00 04 05
   12 00 FFFFFFC2 00 13 02 02 43 43 15 02 14 21 11 02 15
   19 10 02 16 17 0D 01 06 09 02 18 06 02 07 4E 6F
   74 68 69 6E 67 12 03 1A 1C 27 06 08 1B 02 FFFFFF84 FFFFFF80
   FFFFFF80 FFFFFF80 00 19 02 0C 3C 72 65 66 69 6E 65 6D 65 6E
   74 3E 10 03 1D 1E 20 0D 01 04 09 02 1F 04 02 0B
   54 72 61 76 65 72 73 61 62 6C 65 10 02 10 21 04
   08 22 11 FFFFFF84 FFFFFF80 FFFFFF80 FFFFFFC2 00 23 02 01 58 11 02 15 24
   10 02 16 25 09 02 26 06 02 03 41 6E 79 10 04 0C
   28 20 0F 09 02 29 02 02 10 54 72 61 76 65 72 73
   61 62 6C 65 43 6C 61 73 73 10 02 16 2B 09 02 2C
   06 02 0B 53 63 61 6C 61 4F 62 6A 65 63 74 08 05
   2E 00 FFFFFF84 00 2F 01 06 3C 69 6E 69 74 3E 14 01 30
   10 03 0C 00 0F 06 04 32 00 00 33 02 15 56 69 72
   74 75 61 6C 42 75 69 6C 64 65 72 46 61 63 74 6F
   72 79 15 02 34 41 13 04 31 35 3D 2A 10 02 36 3B
   0D 01 37 0A 02 38 39 01 04 6C 61 6E 67 0A 01 3A
   01 04 6A 61 76 61 09 02 3C 37 02 06 4F 62 6A 65
   63 74 10 05 0C 3E 40 43 44 09 02 3F 02 02 0E 42
   75 69 6C 64 65 72 46 61 63 74 6F 72 79 10 02 10
   41 04 08 42 31 FFFFFF84 FFFFFF80 FFFFFF80 FFFFFFC2 00 23 02 01 41 10 03
   10 11 40 30 02 45 47 10 03 10 11 46 10 02 10 47
   04 08 48 00 FFFFFF84 FFFFFF80 FFFFFF80 FFFFFF82 00 23 02 03 5F 24 31 08
   05 2E 31 FFFFFF84 00 4A 14 01 4B 10 03 4C 31 40 0D 01
   00 08 05 4E 31 FFFFFF84 00 4F 01 05 61 70 70 6C 79 14
   02 50 53 10 04 0C 51 40 43 09 02 52 02 02 07 42
   75 69 6C 64 65 72 08 05 54 4D FFFFFFC0 00 55 01 04 66
   72 6F 6D 10 02 4C 56 09 02 57 0D 02 04 43 6F 6C
   6C 08 05 59 00 FFFFFF84 00 5A 01 06 63 6F 6E 63 61 74
   15 02 5B 5E 14 02 5C 5F 10 03 10 11 5D 10 02 10
   5E 04 08 42 58 FFFFFF84 FFFFFF80 FFFFFF80 FFFFFFC2 00 23 08 05 60 58 FFFFFFC0
   00 61 01 03 78 73 73 10 03 16 62 64 09 02 63 06
   02 0A 3C 72 65 70 65 61 74 65 64 3E 10 03 1D 1E
   5D 08 05 66 00 FFFFFF84 00 67 01 04 66 69 6C 6C 15 02
   68 6C 14 02 69 72 14 02 6A 6D 10 03 10 11 6B 10
   02 10 6C 04 08 42 65 FFFFFF84 FFFFFF80 FFFFFF80 FFFFFFC2 00 23 08 06 6E
   65 FFFFFF84 FFFFFFC0 00 6F 01 04 65 6C 65 6D 10 03 16 70 6B
   09 02 71 06 02 08 3C 62 79 6E 61 6D 65 3E 08 05
   73 65 FFFFFFC0 00 74 01 01 6E 10 02 16 75 09 02 76 06
   02 03 49 6E 74 08 05 66 00 FFFFFF84 00 78 15 02 79 7E
   14 05 7A FFFFFF81 01 FFFFFF81 03 14 02 7B 7F 10 03 10 11 7C
   10 03 10 11 7D 10 02 10 7E 04 08 42 77 FFFFFF84 FFFFFF80 FFFFFF80
   FFFFFFC2 00 23 08 07 6E 77 FFFFFF84 FFFFFFC0 00 FFFFFF81 00 10 03 16 70
   7D 08 06 FFFFFF81 02 77 FFFFFFC0 00 74 01 02 6E 31 08 06 FFFFFF81
   04 77 FFFFFFC0 00 74 01 02 6E 32 08 06 66 00 FFFFFF84 00 FFFFFF81
   06 15 04 FFFFFF81 07 FFFFFF81 0D 14 08 FFFFFF81 08 FFFFFF81 10 FFFFFF81 11 FFFFFF81
   12 14 04 FFFFFF81 09 FFFFFF81 0E 10 04 10 11 FFFFFF81 0A 10 04 10
   11 FFFFFF81 0B 10 04 10 11 FFFFFF81 0C 10 03 10 FFFFFF81 0D 04 09
   42 FFFFFF81 05 FFFFFF84 FFFFFF80 FFFFFF80 FFFFFFC2 00 23 08 08 6E FFFFFF81 05 FFFFFF84 FFFFFFC0
   00 FFFFFF81 0F 10 04 16 70 FFFFFF81 0C 08 07 FFFFFF81 02 FFFFFF81 05 FFFFFFC0
   00 74 08 07 FFFFFF81 04 FFFFFF81 05 FFFFFFC0 00 74 08 07 FFFFFF81 13 FFFFFF81
   05 FFFFFFC0 00 74 01 02 6E 33 08 06 66 00 FFFFFF84 00 FFFFFF81 15
   15 04 FFFFFF81 16 FFFFFF81 1D 14 0A FFFFFF81 17 FFFFFF81 20 FFFFFF81 21 FFFFFF81 22
   FFFFFF81 23 14 04 FFFFFF81 18 FFFFFF81 1E 10 04 10 11 FFFFFF81 19 10 04
   10 11 FFFFFF81 1A 10 04 10 11 FFFFFF81 1B 10 04 10 11 FFFFFF81 1C
   10 03 10 FFFFFF81 1D 04 09 42 FFFFFF81 14 FFFFFF84 FFFFFF80 FFFFFF80 FFFFFFC2 00 23
   08 08 6E FFFFFF81 14 FFFFFF84 FFFFFFC0 00 FFFFFF81 1F 10 04 16 70 FFFFFF81 1C
   08 07 FFFFFF81 02 FFFFFF81 14 FFFFFFC0 00 74 08 07 FFFFFF81 04 FFFFFF81 14 FFFFFFC0
   00 74 08 07 FFFFFF81 13 FFFFFF81 14 FFFFFFC0 00 74 08 07 FFFFFF81 24 FFFFFF81
   14 FFFFFFC0 00 74 01 02 6E 34 08 06 66 00 FFFFFF84 00 FFFFFF81 26
   15 04 FFFFFF81 27 FFFFFF81 2F 14 0C FFFFFF81 28 FFFFFF81 32 FFFFFF81 33 FFFFFF81 34
   FFFFFF81 35 FFFFFF81 36 14 04 FFFFFF81 29 FFFFFF81 30 10 04 10 11 FFFFFF81 2A
   10 04 10 11 FFFFFF81 2B 10 04 10 11 FFFFFF81 2C 10 04 10 11
   FFFFFF81 2D 10 04 10 11 FFFFFF81 2E 10 03 10 FFFFFF81 2F 04 09 42
   FFFFFF81 25 FFFFFF84 FFFFFF80 FFFFFF80 FFFFFFC2 00 23 08 08 6E FFFFFF81 25 FFFFFF84 FFFFFFC0 00
   FFFFFF81 31 10 04 16 70 FFFFFF81 2E 08 07 FFFFFF81 02 FFFFFF81 25 FFFFFFC0 00
   74 08 07 FFFFFF81 04 FFFFFF81 25 FFFFFFC0 00 74 08 07 FFFFFF81 13 FFFFFF81 25
   FFFFFFC0 00 74 08 07 FFFFFF81 24 FFFFFF81 25 FFFFFFC0 00 74 08 07 FFFFFF81 37
   FFFFFF81 25 FFFFFFC0 00 74 01 02 6E 35 08 07 FFFFFF81 39 00 FFFFFF84 00
   FFFFFF81 3A 01 08 74 61 62 75 6C 61 74 65 15 04 FFFFFF81 3B
   FFFFFF81 3F 14 04 FFFFFF81 3C FFFFFF81 45 14 04 FFFFFF81 3D FFFFFF81 40 10 04
   10 11 FFFFFF81 3E 10 03 10 FFFFFF81 3F 04 09 42 FFFFFF81 38 FFFFFF84 FFFFFF80
   FFFFFF80 FFFFFFC2 00 23 08 08 FFFFFF81 41 FFFFFF81 38 FFFFFFC0 00 FFFFFF81 42 01 01
   66 10 06 16 FFFFFF81 43 74 FFFFFF81 3E 09 03 FFFFFF81 44 06 02 09
   46 75 6E 63 74 69 6F 6E 31 08 06 73 FFFFFF81 38 FFFFFFC0 00
   74 08 07 FFFFFF81 39 00 FFFFFF84 00 FFFFFF81 47 15 04 FFFFFF81 48 FFFFFF81 4D
   14 06 FFFFFF81 49 FFFFFF81 52 FFFFFF81 53 14 04 FFFFFF81 4A FFFFFF81 4E 10 04
   10 11 FFFFFF81 4B 10 04 10 11 FFFFFF81 4C 10 03 10 FFFFFF81 4D 04
   09 42 FFFFFF81 46 FFFFFF84 FFFFFF80 FFFFFF80 FFFFFFC2 00 23 08 08 FFFFFF81 41 FFFFFF81 46
   FFFFFFC0 00 FFFFFF81 4F 10 07 16 FFFFFF81 50 74 74 FFFFFF81 4C 09 03 FFFFFF81
   51 06 02 09 46 75 6E 63 74 69 6F 6E 32 08 07 FFFFFF81
   02 FFFFFF81 46 FFFFFFC0 00 74 08 07 FFFFFF81 04 FFFFFF81 46 FFFFFFC0 00 74 08
   07 FFFFFF81 39 00 FFFFFF84 00 FFFFFF81 55 15 04 FFFFFF81 56 FFFFFF81 5C 14 08
   FFFFFF81 57 FFFFFF81 61 FFFFFF81 62 FFFFFF81 63 14 04 FFFFFF81 58 FFFFFF81 5D 10 04
   10 11 FFFFFF81 59 10 04 10 11 FFFFFF81 5A 10 04 10 11 FFFFFF81 5B
   10 03 10 FFFFFF81 5C 04 09 42 FFFFFF81 54 FFFFFF84 FFFFFF80 FFFFFF80 FFFFFFC2 00 23
   08 08 FFFFFF81 41 FFFFFF81 54 FFFFFFC0 00 FFFFFF81 5E 10 08 16 FFFFFF81 5F 74
   74 74 FFFFFF81 5B 09 03 FFFFFF81 60 06 02 09 46 75 6E 63 74
   69 6F 6E 33 08 07 FFFFFF81 02 FFFFFF81 54 FFFFFFC0 00 74 08 07 FFFFFF81
   04 FFFFFF81 54 FFFFFFC0 00 74 08 07 FFFFFF81 13 FFFFFF81 54 FFFFFFC0 00 74 08
   07 FFFFFF81 39 00 FFFFFF84 00 FFFFFF81 65 15 04 FFFFFF81 66 FFFFFF81 6D 14 0A
   FFFFFF81 67 FFFFFF81 72 FFFFFF81 73 FFFFFF81 74 FFFFFF81 75 14 04 FFFFFF81 68 FFFFFF81 6E
   10 04 10 11 FFFFFF81 69 10 04 10 11 FFFFFF81 6A 10 04 10 11
   FFFFFF81 6B 10 04 10 11 FFFFFF81 6C 10 03 10 FFFFFF81 6D 04 09 42
   FFFFFF81 64 FFFFFF84 FFFFFF80 FFFFFF80 FFFFFFC2 00 23 08 08 FFFFFF81 41 FFFFFF81 64 FFFFFFC0 00
   FFFFFF81 6F 10 09 16 FFFFFF81 70 74 74 74 74 FFFFFF81 6C 09 03 FFFFFF81
   71 06 02 09 46 75 6E 63 74 69 6F 6E 34 08 07 FFFFFF81
   02 FFFFFF81 64 FFFFFFC0 00 74 08 07 FFFFFF81 04 FFFFFF81 64 FFFFFFC0 00 74 08
   07 FFFFFF81 13 FFFFFF81 64 FFFFFFC0 00 74 08 07 FFFFFF81 24 FFFFFF81 64 FFFFFFC0 00
   74 08 07 FFFFFF81 39 00 FFFFFF84 00 FFFFFF81 77 15 04 FFFFFF81 78 FFFFFF82 00
   14 0C FFFFFF81 79 FFFFFF82 05 FFFFFF82 06 FFFFFF82 07 FFFFFF82 08 FFFFFF82 09 14 04
   FFFFFF81 7A FFFFFF82 01 10 04 10 11 FFFFFF81 7B 10 04 10 11 FFFFFF81 7C
   10 04 10 11 FFFFFF81 7D 10 04 10 11 FFFFFF81 7E 10 04 10 11
   FFFFFF81 7F 10 03 10 FFFFFF82 00 04 09 42 FFFFFF81 76 FFFFFF84 FFFFFF80 FFFFFF80 FFFFFFC2
   00 23 08 08 FFFFFF81 41 FFFFFF81 76 FFFFFFC0 00 FFFFFF82 02 10 0A 16 FFFFFF82
   03 74 74 74 74 74 FFFFFF81 7F 09 03 FFFFFF82 04 06 02 09 46
   75 6E 63 74 69 6F 6E 35 08 07 FFFFFF81 02 FFFFFF81 76 FFFFFFC0 00
   74 08 07 FFFFFF81 04 FFFFFF81 76 FFFFFFC0 00 74 08 07 FFFFFF81 13 FFFFFF81 76
   FFFFFFC0 00 74 08 07 FFFFFF81 24 FFFFFF81 76 FFFFFFC0 00 74 08 07 FFFFFF81 37
   FFFFFF81 76 FFFFFFC0 00 74 08 07 FFFFFF82 0B 00 FFFFFF84 00 FFFFFF82 0C 01 05
   72 61 6E 67 65 15 04 FFFFFF82 0D FFFFFF82 13 14 06 FFFFFF82 0E FFFFFF82
   0F FFFFFF82 11 10 03 10 11 74 08 07 FFFFFF82 10 FFFFFF82 0A FFFFFFC0 00
   74 01 05 73 74 61 72 74 08 07 FFFFFF82 12 FFFFFF82 0A FFFFFFC0 00
   74 01 03 65 6E 64 04 09 42 FFFFFF82 0A FFFFFF84 FFFFFF80 FFFFFF80 FFFFFFC2 00
   23 08 07 FFFFFF82 0B 00 FFFFFF84 00 FFFFFF82 15 14 08 FFFFFF82 0E FFFFFF82 16
   FFFFFF82 17 FFFFFF82 18 08 07 FFFFFF82 10 FFFFFF82 14 FFFFFFC0 00 74 08 07 FFFFFF82
   12 FFFFFF82 14 FFFFFFC0 00 74 08 07 FFFFFF82 19 FFFFFF82 14 FFFFFFC0 00 74 01
   04 73 74 65 70 08 07 FFFFFF82 1B 00 FFFFFF84 00 FFFFFF82 1C 01 07
   69 74 65 72 61 74 65 15 04 FFFFFF82 1D FFFFFF82 21 14 06 FFFFFF82
   1E FFFFFF82 24 FFFFFF82 25 14 04 FFFFFF82 1F FFFFFF82 22 10 04 10 11 FFFFFF82
   20 10 03 10 FFFFFF82 21 04 09 42 FFFFFF82 1A FFFFFF84 FFFFFF80 FFFFFF80 FFFFFFC2 00
   23 08 08 FFFFFF81 41 FFFFFF82 1A FFFFFFC0 00 FFFFFF82 23 10 07 16 FFFFFF81 43
   FFFFFF82 20 FFFFFF82 20 08 08 FFFFFF82 10 FFFFFF82 1A FFFFFFC0 00 FFFFFF82 20 08 07
   FFFFFF82 26 FFFFFF82 1A FFFFFFC0 00 74 01 03 6C 65 6E 
  InnerClass: 
   public final #208= #164 of #15; //$anonfun$fill$2=class scala/collection/generic/TraversableFactory$$anonfun$fill$2 of class scala/collection/generic/TraversableFactory
   public final #209= #140 of #15; //$anonfun$fill$4=class scala/collection/generic/TraversableFactory$$anonfun$fill$4 of class scala/collection/generic/TraversableFactory
   public final #210= #174 of #15; //$anonfun$fill$1=class scala/collection/generic/TraversableFactory$$anonfun$fill$1 of class scala/collection/generic/TraversableFactory
   public final #211= #153 of #15; //$anonfun$fill$3=class scala/collection/generic/TraversableFactory$$anonfun$fill$3 of class scala/collection/generic/TraversableFactory
   public final #212= #191 of #15; //$anonfun$concat$1=class scala/collection/generic/TraversableFactory$$anonfun$concat$1 of class scala/collection/generic/TraversableFactory
   public final #213= #116 of #15; //$anonfun$tabulate$2=class scala/collection/generic/TraversableFactory$$anonfun$tabulate$2 of class scala/collection/generic/TraversableFactory
   public final #214= #87 of #15; //$anonfun$tabulate$4=class scala/collection/generic/TraversableFactory$$anonfun$tabulate$4 of class scala/collection/generic/TraversableFactory
   public final #215= #127 of #15; //$anonfun$tabulate$1=class scala/collection/generic/TraversableFactory$$anonfun$tabulate$1 of class scala/collection/generic/TraversableFactory
   public final #216= #104 of #15; //$anonfun$tabulate$3=class scala/collection/generic/TraversableFactory$$anonfun$tabulate$3 of class scala/collection/generic/TraversableFactory
   public #219= #218 of #15; //VirtualBuilderFactory=class scala/collection/generic/TraversableFactory$VirtualBuilderFactory of class scala/collection/generic/TraversableFactory
  minor version: 0
  major version: 49
  Constant pool:
const #1 = Asciz	SourceFile;
const #2 = Asciz	TraversableFactory.scala;
const #3 = Asciz	<init>;
const #4 = Asciz	()V;
const #5 = Asciz	Code;
const #6 = Asciz	LineNumberTable;
const #7 = Asciz	scala/collection/generic/Companion;
const #8 = class	#7;	//  scala/collection/generic/Companion
const #9 = NameAndType	#3:#4;//  "<init>":()V
const #10 = Method	#8.#9;	//  scala/collection/generic/Companion."<init>":()V
const #11 = Asciz	Signature;
const #12 = Asciz	iterate;
const #13 = Asciz	(Ljava/lang/Object;ILscala/Function1;)Lscala/collection/Traversable;;
const #14 = Asciz	scala/collection/generic/TraversableFactory;
const #15 = class	#14;	//  scala/collection/generic/TraversableFactory
const #16 = Asciz	newBuilder;
const #17 = Asciz	()Lscala/collection/generic/Builder;;
const #18 = NameAndType	#16:#17;//  newBuilder:()Lscala/collection/generic/Builder;
const #19 = Method	#15.#18;	//  scala/collection/generic/TraversableFactory.newBuilder:()Lscala/collection/generic/Builder;
const #20 = Asciz	scala/collection/generic/Builder;
const #21 = class	#20;	//  scala/collection/generic/Builder
const #22 = Asciz	$plus$eq;
const #23 = Asciz	(Ljava/lang/Object;)Lscala/collection/generic/Builder;;
const #24 = NameAndType	#22:#23;//  $plus$eq:(Ljava/lang/Object;)Lscala/collection/generic/Builder;
const #25 = InterfaceMethod	#21.#24;	//  scala/collection/generic/Builder.$plus$eq:(Ljava/lang/Object;)Lscala/collection/generic/Builder;
const #26 = Asciz	scala/Function1;
const #27 = class	#26;	//  scala/Function1
const #28 = Asciz	apply;
const #29 = Asciz	(Ljava/lang/Object;)Ljava/lang/Object;;
const #30 = NameAndType	#28:#29;//  apply:(Ljava/lang/Object;)Ljava/lang/Object;
const #31 = InterfaceMethod	#27.#30;	//  scala/Function1.apply:(Ljava/lang/Object;)Ljava/lang/Object;
const #32 = Asciz	result;
const #33 = Asciz	()Ljava/lang/Object;;
const #34 = NameAndType	#32:#33;//  result:()Ljava/lang/Object;
const #35 = InterfaceMethod	#21.#34;	//  scala/collection/generic/Builder.result:()Ljava/lang/Object;
const #36 = Asciz	scala/collection/Traversable;
const #37 = class	#36;	//  scala/collection/Traversable
const #38 = Asciz	scala/runtime/ScalaRunTime$;
const #39 = class	#38;	//  scala/runtime/ScalaRunTime$
const #40 = Asciz	MODULE$;
const #41 = Asciz	Lscala/runtime/ScalaRunTime$;;
const #42 = NameAndType	#40:#41;//  MODULE$:Lscala/runtime/ScalaRunTime$;
const #43 = Field	#39.#42;	//  scala/runtime/ScalaRunTime$.MODULE$:Lscala/runtime/ScalaRunTime$;
const #44 = Asciz	boxArray;
const #45 = Asciz	(Ljava/lang/Object;)Lscala/runtime/BoxedArray;;
const #46 = NameAndType	#44:#45;//  boxArray:(Ljava/lang/Object;)Lscala/runtime/BoxedArray;
const #47 = Method	#39.#46;	//  scala/runtime/ScalaRunTime$.boxArray:(Ljava/lang/Object;)Lscala/runtime/BoxedArray;
const #48 = Asciz	this;
const #49 = Asciz	Lscala/collection/generic/TraversableFactory;;
const #50 = Asciz	start;
const #51 = Asciz	Ljava/lang/Object;;
const #52 = Asciz	len;
const #53 = Asciz	I;
const #54 = Asciz	f;
const #55 = Asciz	Lscala/Function1;;
const #56 = Asciz	b;
const #57 = Asciz	Lscala/collection/generic/Builder;;
const #58 = Asciz	acc;
const #59 = Asciz	i;
const #60 = Asciz	LocalVariableTable;
const #61 = Asciz	<A:Ljava/lang/Object;>(TA;ILscala/Function1<TA;TA;>;)TCC;;
const #62 = Asciz	range;
const #63 = Asciz	(III)Lscala/collection/Traversable;;
const #64 = Asciz	java/lang/IllegalArgumentException;
const #65 = class	#64;	//  java/lang/IllegalArgumentException
const #66 = Asciz	zero step;
const #67 = String	#66;	//  zero step
const #68 = Asciz	(Ljava/lang/String;)V;
const #69 = NameAndType	#3:#68;//  "<init>":(Ljava/lang/String;)V
const #70 = Method	#65.#69;	//  java/lang/IllegalArgumentException."<init>":(Ljava/lang/String;)V
const #71 = Asciz	scala/runtime/BoxesRunTime;
const #72 = class	#71;	//  scala/runtime/BoxesRunTime
const #73 = Asciz	boxToInteger;
const #74 = Asciz	(I)Ljava/lang/Integer;;
const #75 = NameAndType	#73:#74;//  boxToInteger:(I)Ljava/lang/Integer;
const #76 = Method	#72.#75;	//  scala/runtime/BoxesRunTime.boxToInteger:(I)Ljava/lang/Integer;
const #77 = Asciz	end;
const #78 = Asciz	step;
const #79 = Asciz	(III)TCC;;
const #80 = Asciz	(II)Lscala/collection/Traversable;;
const #81 = NameAndType	#62:#63;//  range:(III)Lscala/collection/Traversable;
const #82 = Method	#15.#81;	//  scala/collection/generic/TraversableFactory.range:(III)Lscala/collection/Traversable;
const #83 = Asciz	<A:Ljava/lang/Object;>(II)TCC;;
const #84 = Asciz	tabulate;
const #85 = Asciz	(IIIIILscala/Function5;)Lscala/collection/Traversable;;
const #86 = Asciz	scala/collection/generic/TraversableFactory$$anonfun$tabulate$4;
const #87 = class	#86;	//  scala/collection/generic/TraversableFactory$$anonfun$tabulate$4
const #88 = Asciz	(Lscala/collection/generic/TraversableFactory;IIIILscala/Function5;)V;
const #89 = NameAndType	#3:#88;//  "<init>":(Lscala/collection/generic/TraversableFactory;IIIILscala/Function5;)V
const #90 = Method	#87.#89;	//  scala/collection/generic/TraversableFactory$$anonfun$tabulate$4."<init>":(Lscala/collection/generic/TraversableFactory;IIIILscala/Function5;)V
const #91 = Asciz	(ILscala/Function1;)Lscala/collection/Traversable;;
const #92 = NameAndType	#84:#91;//  tabulate:(ILscala/Function1;)Lscala/collection/Traversable;
const #93 = Method	#15.#92;	//  scala/collection/generic/TraversableFactory.tabulate:(ILscala/Function1;)Lscala/collection/Traversable;
const #94 = Asciz	n1;
const #95 = Asciz	n2$2;
const #96 = Asciz	n3$1;
const #97 = Asciz	n4$1;
const #98 = Asciz	n5$1;
const #99 = Asciz	f$1;
const #100 = Asciz	Lscala/Function5;;
const #101 = Asciz	<A:Ljava/lang/Object;>(IIIIILscala/Function5<Ljava/lang/Integer;Ljava/lang/Integer;Ljava/lang/Integer;Ljava/lang/Integer;Ljava/lang/Integer;TA;>;)TCC;;
const #102 = Asciz	(IIIILscala/Function4;)Lscala/collection/Traversable;;
const #103 = Asciz	scala/collection/generic/TraversableFactory$$anonfun$tabulate$3;
const #104 = class	#103;	//  scala/collection/generic/TraversableFactory$$anonfun$tabulate$3
const #105 = Asciz	(Lscala/collection/generic/TraversableFactory;IIILscala/Function4;)V;
const #106 = NameAndType	#3:#105;//  "<init>":(Lscala/collection/generic/TraversableFactory;IIILscala/Function4;)V
const #107 = Method	#104.#106;	//  scala/collection/generic/TraversableFactory$$anonfun$tabulate$3."<init>":(Lscala/collection/generic/TraversableFactory;IIILscala/Function4;)V
const #108 = Asciz	n2$3;
const #109 = Asciz	n3$2;
const #110 = Asciz	n4$2;
const #111 = Asciz	f$2;
const #112 = Asciz	Lscala/Function4;;
const #113 = Asciz	<A:Ljava/lang/Object;>(IIIILscala/Function4<Ljava/lang/Integer;Ljava/lang/Integer;Ljava/lang/Integer;Ljava/lang/Integer;TA;>;)TCC;;
const #114 = Asciz	(IIILscala/Function3;)Lscala/collection/Traversable;;
const #115 = Asciz	scala/collection/generic/TraversableFactory$$anonfun$tabulate$2;
const #116 = class	#115;	//  scala/collection/generic/TraversableFactory$$anonfun$tabulate$2
const #117 = Asciz	(Lscala/collection/generic/TraversableFactory;IILscala/Function3;)V;
const #118 = NameAndType	#3:#117;//  "<init>":(Lscala/collection/generic/TraversableFactory;IILscala/Function3;)V
const #119 = Method	#116.#118;	//  scala/collection/generic/TraversableFactory$$anonfun$tabulate$2."<init>":(Lscala/collection/generic/TraversableFactory;IILscala/Function3;)V
const #120 = Asciz	n2$4;
const #121 = Asciz	n3$3;
const #122 = Asciz	f$3;
const #123 = Asciz	Lscala/Function3;;
const #124 = Asciz	<A:Ljava/lang/Object;>(IIILscala/Function3<Ljava/lang/Integer;Ljava/lang/Integer;Ljava/lang/Integer;TA;>;)TCC;;
const #125 = Asciz	(IILscala/Function2;)Lscala/collection/Traversable;;
const #126 = Asciz	scala/collection/generic/TraversableFactory$$anonfun$tabulate$1;
const #127 = class	#126;	//  scala/collection/generic/TraversableFactory$$anonfun$tabulate$1
const #128 = Asciz	(Lscala/collection/generic/TraversableFactory;ILscala/Function2;)V;
const #129 = NameAndType	#3:#128;//  "<init>":(Lscala/collection/generic/TraversableFactory;ILscala/Function2;)V
const #130 = Method	#127.#129;	//  scala/collection/generic/TraversableFactory$$anonfun$tabulate$1."<init>":(Lscala/collection/generic/TraversableFactory;ILscala/Function2;)V
const #131 = Asciz	n2$5;
const #132 = Asciz	f$4;
const #133 = Asciz	Lscala/Function2;;
const #134 = Asciz	<A:Ljava/lang/Object;>(IILscala/Function2<Ljava/lang/Integer;Ljava/lang/Integer;TA;>;)TCC;;
const #135 = Asciz	n;
const #136 = Asciz	<A:Ljava/lang/Object;>(ILscala/Function1<Ljava/lang/Integer;TA;>;)TCC;;
const #137 = Asciz	fill;
const #138 = Asciz	(IIIIILscala/Function0;)Lscala/collection/Traversable;;
const #139 = Asciz	scala/collection/generic/TraversableFactory$$anonfun$fill$4;
const #140 = class	#139;	//  scala/collection/generic/TraversableFactory$$anonfun$fill$4
const #141 = Asciz	(Lscala/collection/generic/TraversableFactory;IIIILscala/Function0;)V;
const #142 = NameAndType	#3:#141;//  "<init>":(Lscala/collection/generic/TraversableFactory;IIIILscala/Function0;)V
const #143 = Method	#140.#142;	//  scala/collection/generic/TraversableFactory$$anonfun$fill$4."<init>":(Lscala/collection/generic/TraversableFactory;IIIILscala/Function0;)V
const #144 = Asciz	n2$6;
const #145 = Asciz	n3$4;
const #146 = Asciz	n4$3;
const #147 = Asciz	n5$2;
const #148 = Asciz	elem$2;
const #149 = Asciz	Lscala/Function0;;
const #150 = Asciz	<A:Ljava/lang/Object;>(IIIIILscala/Function0<TA;>;)TCC;;
const #151 = Asciz	(IIIILscala/Function0;)Lscala/collection/Traversable;;
const #152 = Asciz	scala/collection/generic/TraversableFactory$$anonfun$fill$3;
const #153 = class	#152;	//  scala/collection/generic/TraversableFactory$$anonfun$fill$3
const #154 = Asciz	(Lscala/collection/generic/TraversableFactory;IIILscala/Function0;)V;
const #155 = NameAndType	#3:#154;//  "<init>":(Lscala/collection/generic/TraversableFactory;IIILscala/Function0;)V
const #156 = Method	#153.#155;	//  scala/collection/generic/TraversableFactory$$anonfun$fill$3."<init>":(Lscala/collection/generic/TraversableFactory;IIILscala/Function0;)V
const #157 = Asciz	n2$7;
const #158 = Asciz	n3$5;
const #159 = Asciz	n4$4;
const #160 = Asciz	elem$3;
const #161 = Asciz	<A:Ljava/lang/Object;>(IIIILscala/Function0<TA;>;)TCC;;
const #162 = Asciz	(IIILscala/Function0;)Lscala/collection/Traversable;;
const #163 = Asciz	scala/collection/generic/TraversableFactory$$anonfun$fill$2;
const #164 = class	#163;	//  scala/collection/generic/TraversableFactory$$anonfun$fill$2
const #165 = Asciz	(Lscala/collection/generic/TraversableFactory;IILscala/Function0;)V;
const #166 = NameAndType	#3:#165;//  "<init>":(Lscala/collection/generic/TraversableFactory;IILscala/Function0;)V
const #167 = Method	#164.#166;	//  scala/collection/generic/TraversableFactory$$anonfun$fill$2."<init>":(Lscala/collection/generic/TraversableFactory;IILscala/Function0;)V
const #168 = Asciz	n2$8;
const #169 = Asciz	n3$6;
const #170 = Asciz	elem$4;
const #171 = Asciz	<A:Ljava/lang/Object;>(IIILscala/Function0<TA;>;)TCC;;
const #172 = Asciz	(IILscala/Function0;)Lscala/collection/Traversable;;
const #173 = Asciz	scala/collection/generic/TraversableFactory$$anonfun$fill$1;
const #174 = class	#173;	//  scala/collection/generic/TraversableFactory$$anonfun$fill$1
const #175 = Asciz	(Lscala/collection/generic/TraversableFactory;ILscala/Function0;)V;
const #176 = NameAndType	#3:#175;//  "<init>":(Lscala/collection/generic/TraversableFactory;ILscala/Function0;)V
const #177 = Method	#174.#176;	//  scala/collection/generic/TraversableFactory$$anonfun$fill$1."<init>":(Lscala/collection/generic/TraversableFactory;ILscala/Function0;)V
const #178 = Asciz	n2$1;
const #179 = Asciz	elem$1;
const #180 = Asciz	<A:Ljava/lang/Object;>(IILscala/Function0<TA;>;)TCC;;
const #181 = Asciz	(ILscala/Function0;)Lscala/collection/Traversable;;
const #182 = Asciz	scala/Function0;
const #183 = class	#182;	//  scala/Function0
const #184 = NameAndType	#28:#33;//  apply:()Ljava/lang/Object;
const #185 = InterfaceMethod	#183.#184;	//  scala/Function0.apply:()Ljava/lang/Object;
const #186 = Asciz	elem;
const #187 = Asciz	<A:Ljava/lang/Object;>(ILscala/Function0<TA;>;)TCC;;
const #188 = Asciz	concat;
const #189 = Asciz	(Lscala/collection/Sequence;)Lscala/collection/Traversable;;
const #190 = Asciz	scala/collection/generic/TraversableFactory$$anonfun$concat$1;
const #191 = class	#190;	//  scala/collection/generic/TraversableFactory$$anonfun$concat$1
const #192 = Asciz	(Lscala/collection/generic/TraversableFactory;Lscala/collection/generic/Builder;)V;
const #193 = NameAndType	#3:#192;//  "<init>":(Lscala/collection/generic/TraversableFactory;Lscala/collection/generic/Builder;)V
const #194 = Method	#191.#193;	//  scala/collection/generic/TraversableFactory$$anonfun$concat$1."<init>":(Lscala/collection/generic/TraversableFactory;Lscala/collection/generic/Builder;)V
const #195 = Asciz	scala/collection/generic/IterableTemplate;
const #196 = class	#195;	//  scala/collection/generic/IterableTemplate
const #197 = Asciz	foreach;
const #198 = Asciz	(Lscala/Function1;)V;
const #199 = NameAndType	#197:#198;//  foreach:(Lscala/Function1;)V
const #200 = InterfaceMethod	#196.#199;	//  scala/collection/generic/IterableTemplate.foreach:(Lscala/Function1;)V
const #201 = Asciz	xss;
const #202 = Asciz	Lscala/collection/Sequence;;
const #203 = Asciz	b$1;
const #204 = Asciz	<A:Ljava/lang/Object;>(Lscala/collection/Sequence<Lscala/collection/Traversable<TA;>;>;)TCC;;
const #205 = Asciz	<CC:Lscala/collection/Traversable<Ljava/lang/Object;>;>Lscala/collection/generic/Companion<TCC;>;Lscala/ScalaObject;;
const #206 = Asciz	ScalaSig;
const #207 = Asciz	InnerClasses;
const #208 = Asciz	$anonfun$fill$2;
const #209 = Asciz	$anonfun$fill$4;
const #210 = Asciz	$anonfun$fill$1;
const #211 = Asciz	$anonfun$fill$3;
const #212 = Asciz	$anonfun$concat$1;
const #213 = Asciz	$anonfun$tabulate$2;
const #214 = Asciz	$anonfun$tabulate$4;
const #215 = Asciz	$anonfun$tabulate$1;
const #216 = Asciz	$anonfun$tabulate$3;
const #217 = Asciz	scala/collection/generic/TraversableFactory$VirtualBuilderFactory;
const #218 = class	#217;	//  scala/collection/generic/TraversableFactory$VirtualBuilderFactory
const #219 = Asciz	VirtualBuilderFactory;
const #220 = Asciz	scala/ScalaObject;
const #221 = class	#220;	//  scala/ScalaObject

{
public scala.collection.generic.TraversableFactory();
  Code:
   Stack=1, Locals=1, Args_size=1
   0:	aload_0
   1:	invokespecial	#10; //Method scala/collection/generic/Companion."<init>":()V
   4:	return
  LineNumberTable: 
   line 20: 0

  Signature: length = 0x2
   00 04 

public scala.collection.Traversable iterate(java.lang.Object, int, scala.Function1);
  Code:
   Stack=2, Locals=8, Args_size=4
   0:	aload_0
   1:	invokevirtual	#19; //Method newBuilder:()Lscala/collection/generic/Builder;
   4:	astore	4
   6:	aload_1
   7:	astore	5
   9:	iconst_0
   10:	istore	6
   12:	iload	6
   14:	iload_2
   15:	if_icmpge	47
   18:	aload	4
   20:	aload	5
   22:	invokeinterface	#25,  2; //InterfaceMethod scala/collection/generic/Builder.$plus$eq:(Ljava/lang/Object;)Lscala/collection/generic/Builder;
   27:	pop
   28:	aload_3
   29:	aload	5
   31:	invokeinterface	#31,  2; //InterfaceMethod scala/Function1.apply:(Ljava/lang/Object;)Ljava/lang/Object;
   36:	astore	5
   38:	iload	6
   40:	iconst_1
   41:	iadd
   42:	istore	6
   44:	goto	12
   47:	aload	4
   49:	invokeinterface	#35,  1; //InterfaceMethod scala/collection/generic/Builder.result:()Ljava/lang/Object;
   54:	astore	7
   56:	aload	7
   58:	instanceof	#37; //class scala/collection/Traversable
   61:	ifeq	69
   64:	aload	7
   66:	goto	77
   69:	getstatic	#43; //Field scala/runtime/ScalaRunTime$.MODULE$:Lscala/runtime/ScalaRunTime$;
   72:	aload	7
   74:	invokevirtual	#47; //Method scala/runtime/ScalaRunTime$.boxArray:(Ljava/lang/Object;)Lscala/runtime/BoxedArray;
   77:	checkcast	#37; //class scala/collection/Traversable
   80:	areturn
  LineNumberTable: 
   line 177: 0
   line 178: 6
   line 179: 9
   line 180: 12
   line 181: 18
   line 182: 28
   line 183: 38
   line 180: 44
   line 185: 47

  LocalVariableTable: 
   Start  Length  Slot  Name   Signature
   0      81      0    this       Lscala/collection/generic/TraversableFactory;
   0      81      1    start       Ljava/lang/Object;
   0      81      2    len       I
   0      81      3    f       Lscala/Function1;
   6      74      4    b       Lscala/collection/generic/Builder;
   9      71      5    acc       Ljava/lang/Object;
   12      68      6    i       I

  Signature: length = 0x2
   00 3D 

public scala.collection.Traversable range(int, int, int);
  Code:
   Stack=3, Locals=7, Args_size=4
   0:	iload_3
   1:	iconst_0
   2:	if_icmpne	15
   5:	new	#65; //class java/lang/IllegalArgumentException
   8:	dup
   9:	ldc	#67; //String zero step
   11:	invokespecial	#70; //Method java/lang/IllegalArgumentException."<init>":(Ljava/lang/String;)V
   14:	athrow
   15:	aload_0
   16:	invokevirtual	#19; //Method newBuilder:()Lscala/collection/generic/Builder;
   19:	astore	4
   21:	iload_1
   22:	istore	5
   24:	iload_3
   25:	iconst_0
   26:	if_icmpge	43
   29:	iload_2
   30:	iload	5
   32:	if_icmpge	39
   35:	iconst_1
   36:	goto	54
   39:	iconst_0
   40:	goto	54
   43:	iload	5
   45:	iload_2
   46:	if_icmpge	53
   49:	iconst_1
   50:	goto	54
   53:	iconst_0
   54:	ifeq	79
   57:	aload	4
   59:	iload	5
   61:	invokestatic	#76; //Method scala/runtime/BoxesRunTime.boxToInteger:(I)Ljava/lang/Integer;
   64:	invokeinterface	#25,  2; //InterfaceMethod scala/collection/generic/Builder.$plus$eq:(Ljava/lang/Object;)Lscala/collection/generic/Builder;
   69:	pop
   70:	iload	5
   72:	iload_3
   73:	iadd
   74:	istore	5
   76:	goto	24
   79:	aload	4
   81:	invokeinterface	#35,  1; //InterfaceMethod scala/collection/generic/Builder.result:()Ljava/lang/Object;
   86:	astore	6
   88:	aload	6
   90:	instanceof	#37; //class scala/collection/Traversable
   93:	ifeq	101
   96:	aload	6
   98:	goto	109
   101:	getstatic	#43; //Field scala/runtime/ScalaRunTime$.MODULE$:Lscala/runtime/ScalaRunTime$;
   104:	aload	6
   106:	invokevirtual	#47; //Method scala/runtime/ScalaRunTime$.boxArray:(Ljava/lang/Object;)Lscala/runtime/BoxedArray;
   109:	checkcast	#37; //class scala/collection/Traversable
   112:	areturn
  LineNumberTable: 
   line 159: 0
   line 160: 15
   line 161: 21
   line 162: 24
   line 163: 57
   line 164: 70
   line 162: 76
   line 166: 79

  LocalVariableTable: 
   Start  Length  Slot  Name   Signature
   0      113      0    this       Lscala/collection/generic/TraversableFactory;
   0      113      1    start       I
   0      113      2    end       I
   0      113      3    step       I
   21      91      4    b       Lscala/collection/generic/Builder;
   24      88      5    i       I

  Signature: length = 0x2
   00 4F 

public scala.collection.Traversable range(int, int);
  Code:
   Stack=4, Locals=3, Args_size=3
   0:	aload_0
   1:	iload_1
   2:	iload_2
   3:	iconst_1
   4:	invokevirtual	#82; //Method range:(III)Lscala/collection/Traversable;
   7:	areturn
  LineNumberTable: 
   line 149: 0

  LocalVariableTable: 
   Start  Length  Slot  Name   Signature
   0      8      0    this       Lscala/collection/generic/TraversableFactory;
   0      8      1    start       I
   0      8      2    end       I

  Signature: length = 0x2
   00 53 

public scala.collection.Traversable tabulate(int, int, int, int, int, scala.Function5);
  Code:
   Stack=10, Locals=7, Args_size=7
   0:	aload_0
   1:	iload_1
   2:	new	#87; //class scala/collection/generic/TraversableFactory$$anonfun$tabulate$4
   5:	dup
   6:	aload_0
   7:	iload_2
   8:	iload_3
   9:	iload	4
   11:	iload	5
   13:	aload	6
   15:	invokespecial	#90; //Method scala/collection/generic/TraversableFactory$$anonfun$tabulate$4."<init>":(Lscala/collection/generic/TraversableFactory;IIIILscala/Function5;)V
   18:	invokevirtual	#93; //Method tabulate:(ILscala/Function1;)Lscala/collection/Traversable;
   21:	areturn
  LineNumberTable: 
   line 140: 0

  LocalVariableTable: 
   Start  Length  Slot  Name   Signature
   0      22      0    this       Lscala/collection/generic/TraversableFactory;
   0      22      1    n1       I
   0      22      2    n2$2       I
   0      22      3    n3$1       I
   0      22      4    n4$1       I
   0      22      5    n5$1       I
   0      22      6    f$1       Lscala/Function5;

  Signature: length = 0x2
   00 65 

public scala.collection.Traversable tabulate(int, int, int, int, scala.Function4);
  Code:
   Stack=9, Locals=6, Args_size=6
   0:	aload_0
   1:	iload_1
   2:	new	#104; //class scala/collection/generic/TraversableFactory$$anonfun$tabulate$3
   5:	dup
   6:	aload_0
   7:	iload_2
   8:	iload_3
   9:	iload	4
   11:	aload	5
   13:	invokespecial	#107; //Method scala/collection/generic/TraversableFactory$$anonfun$tabulate$3."<init>":(Lscala/collection/generic/TraversableFactory;IIILscala/Function4;)V
   16:	invokevirtual	#93; //Method tabulate:(ILscala/Function1;)Lscala/collection/Traversable;
   19:	areturn
  LineNumberTable: 
   line 129: 0

  LocalVariableTable: 
   Start  Length  Slot  Name   Signature
   0      20      0    this       Lscala/collection/generic/TraversableFactory;
   0      20      1    n1       I
   0      20      2    n2$3       I
   0      20      3    n3$2       I
   0      20      4    n4$2       I
   0      20      5    f$2       Lscala/Function4;

  Signature: length = 0x2
   00 71 

public scala.collection.Traversable tabulate(int, int, int, scala.Function3);
  Code:
   Stack=8, Locals=5, Args_size=5
   0:	aload_0
   1:	iload_1
   2:	new	#116; //class scala/collection/generic/TraversableFactory$$anonfun$tabulate$2
   5:	dup
   6:	aload_0
   7:	iload_2
   8:	iload_3
   9:	aload	4
   11:	invokespecial	#119; //Method scala/collection/generic/TraversableFactory$$anonfun$tabulate$2."<init>":(Lscala/collection/generic/TraversableFactory;IILscala/Function3;)V
   14:	invokevirtual	#93; //Method tabulate:(ILscala/Function1;)Lscala/collection/Traversable;
   17:	areturn
  LineNumberTable: 
   line 119: 0

  LocalVariableTable: 
   Start  Length  Slot  Name   Signature
   0      18      0    this       Lscala/collection/generic/TraversableFactory;
   0      18      1    n1       I
   0      18      2    n2$4       I
   0      18      3    n3$3       I
   0      18      4    f$3       Lscala/Function3;

  Signature: length = 0x2
   00 7C 

public scala.collection.Traversable tabulate(int, int, scala.Function2);
  Code:
   Stack=7, Locals=4, Args_size=4
   0:	aload_0
   1:	iload_1
   2:	new	#127; //class scala/collection/generic/TraversableFactory$$anonfun$tabulate$1
   5:	dup
   6:	aload_0
   7:	iload_2
   8:	aload_3
   9:	invokespecial	#130; //Method scala/collection/generic/TraversableFactory$$anonfun$tabulate$1."<init>":(Lscala/collection/generic/TraversableFactory;ILscala/Function2;)V
   12:	invokevirtual	#93; //Method tabulate:(ILscala/Function1;)Lscala/collection/Traversable;
   15:	areturn
  LineNumberTable: 
   line 110: 0

  LocalVariableTable: 
   Start  Length  Slot  Name   Signature
   0      16      0    this       Lscala/collection/generic/TraversableFactory;
   0      16      1    n1       I
   0      16      2    n2$5       I
   0      16      3    f$4       Lscala/Function2;

  Signature: length = 0x2
   00 FFFFFF86 

public scala.collection.Traversable tabulate(int, scala.Function1);
  Code:
   Stack=3, Locals=6, Args_size=3
   0:	aload_0
   1:	invokevirtual	#19; //Method newBuilder:()Lscala/collection/generic/Builder;
   4:	astore_3
   5:	iconst_0
   6:	istore	4
   8:	iload	4
   10:	iload_1
   11:	if_icmpge	41
   14:	aload_3
   15:	aload_2
   16:	iload	4
   18:	invokestatic	#76; //Method scala/runtime/BoxesRunTime.boxToInteger:(I)Ljava/lang/Integer;
   21:	invokeinterface	#31,  2; //InterfaceMethod scala/Function1.apply:(Ljava/lang/Object;)Ljava/lang/Object;
   26:	invokeinterface	#25,  2; //InterfaceMethod scala/collection/generic/Builder.$plus$eq:(Ljava/lang/Object;)Lscala/collection/generic/Builder;
   31:	pop
   32:	iload	4
   34:	iconst_1
   35:	iadd
   36:	istore	4
   38:	goto	8
   41:	aload_3
   42:	invokeinterface	#35,  1; //InterfaceMethod scala/collection/generic/Builder.result:()Ljava/lang/Object;
   47:	astore	5
   49:	aload	5
   51:	instanceof	#37; //class scala/collection/Traversable
   54:	ifeq	62
   57:	aload	5
   59:	goto	70
   62:	getstatic	#43; //Field scala/runtime/ScalaRunTime$.MODULE$:Lscala/runtime/ScalaRunTime$;
   65:	aload	5
   67:	invokevirtual	#47; //Method scala/runtime/ScalaRunTime$.boxArray:(Ljava/lang/Object;)Lscala/runtime/BoxedArray;
   70:	checkcast	#37; //class scala/collection/Traversable
   73:	areturn
  LineNumberTable: 
   line 95: 0
   line 96: 5
   line 97: 8
   line 98: 14
   line 99: 32
   line 97: 38
   line 101: 41

  LocalVariableTable: 
   Start  Length  Slot  Name   Signature
   0      74      0    this       Lscala/collection/generic/TraversableFactory;
   0      74      1    n       I
   0      74      2    f       Lscala/Function1;
   5      68      3    b       Lscala/collection/generic/Builder;
   8      65      4    i       I

  Signature: length = 0x2
   00 FFFFFF88 

public scala.collection.Traversable fill(int, int, int, int, int, scala.Function0);
  Code:
   Stack=10, Locals=7, Args_size=7
   0:	aload_0
   1:	iload_1
   2:	new	#140; //class scala/collection/generic/TraversableFactory$$anonfun$fill$4
   5:	dup
   6:	aload_0
   7:	iload_2
   8:	iload_3
   9:	iload	4
   11:	iload	5
   13:	aload	6
   15:	invokespecial	#143; //Method scala/collection/generic/TraversableFactory$$anonfun$fill$4."<init>":(Lscala/collection/generic/TraversableFactory;IIIILscala/Function0;)V
   18:	invokevirtual	#93; //Method tabulate:(ILscala/Function1;)Lscala/collection/Traversable;
   21:	areturn
  LineNumberTable: 
   line 87: 0

  LocalVariableTable: 
   Start  Length  Slot  Name   Signature
   0      22      0    this       Lscala/collection/generic/TraversableFactory;
   0      22      1    n1       I
   0      22      2    n2$6       I
   0      22      3    n3$4       I
   0      22      4    n4$3       I
   0      22      5    n5$2       I
   0      22      6    elem$2       Lscala/Function0;

  Signature: length = 0x2
   00 FFFFFF96 

public scala.collection.Traversable fill(int, int, int, int, scala.Function0);
  Code:
   Stack=9, Locals=6, Args_size=6
   0:	aload_0
   1:	iload_1
   2:	new	#153; //class scala/collection/generic/TraversableFactory$$anonfun$fill$3
   5:	dup
   6:	aload_0
   7:	iload_2
   8:	iload_3
   9:	iload	4
   11:	aload	5
   13:	invokespecial	#156; //Method scala/collection/generic/TraversableFactory$$anonfun$fill$3."<init>":(Lscala/collection/generic/TraversableFactory;IIILscala/Function0;)V
   16:	invokevirtual	#93; //Method tabulate:(ILscala/Function1;)Lscala/collection/Traversable;
   19:	areturn
  LineNumberTable: 
   line 76: 0

  LocalVariableTable: 
   Start  Length  Slot  Name   Signature
   0      20      0    this       Lscala/collection/generic/TraversableFactory;
   0      20      1    n1       I
   0      20      2    n2$7       I
   0      20      3    n3$5       I
   0      20      4    n4$4       I
   0      20      5    elem$3       Lscala/Function0;

  Signature: length = 0x2
   00 FFFFFFA1 

public scala.collection.Traversable fill(int, int, int, scala.Function0);
  Code:
   Stack=8, Locals=5, Args_size=5
   0:	aload_0
   1:	iload_1
   2:	new	#164; //class scala/collection/generic/TraversableFactory$$anonfun$fill$2
   5:	dup
   6:	aload_0
   7:	iload_2
   8:	iload_3
   9:	aload	4
   11:	invokespecial	#167; //Method scala/collection/generic/TraversableFactory$$anonfun$fill$2."<init>":(Lscala/collection/generic/TraversableFactory;IILscala/Function0;)V
   14:	invokevirtual	#93; //Method tabulate:(ILscala/Function1;)Lscala/collection/Traversable;
   17:	areturn
  LineNumberTable: 
   line 66: 0

  LocalVariableTable: 
   Start  Length  Slot  Name   Signature
   0      18      0    this       Lscala/collection/generic/TraversableFactory;
   0      18      1    n1       I
   0      18      2    n2$8       I
   0      18      3    n3$6       I
   0      18      4    elem$4       Lscala/Function0;

  Signature: length = 0x2
   00 FFFFFFAB 

public scala.collection.Traversable fill(int, int, scala.Function0);
  Code:
   Stack=7, Locals=4, Args_size=4
   0:	aload_0
   1:	iload_1
   2:	new	#174; //class scala/collection/generic/TraversableFactory$$anonfun$fill$1
   5:	dup
   6:	aload_0
   7:	iload_2
   8:	aload_3
   9:	invokespecial	#177; //Method scala/collection/generic/TraversableFactory$$anonfun$fill$1."<init>":(Lscala/collection/generic/TraversableFactory;ILscala/Function0;)V
   12:	invokevirtual	#93; //Method tabulate:(ILscala/Function1;)Lscala/collection/Traversable;
   15:	areturn
  LineNumberTable: 
   line 57: 0

  LocalVariableTable: 
   Start  Length  Slot  Name   Signature
   0      16      0    this       Lscala/collection/generic/TraversableFactory;
   0      16      1    n1       I
   0      16      2    n2$1       I
   0      16      3    elem$1       Lscala/Function0;

  Signature: length = 0x2
   00 FFFFFFB4 

public scala.collection.Traversable fill(int, scala.Function0);
  Code:
   Stack=2, Locals=6, Args_size=3
   0:	aload_0
   1:	invokevirtual	#19; //Method newBuilder:()Lscala/collection/generic/Builder;
   4:	astore_3
   5:	iconst_0
   6:	istore	4
   8:	iload	4
   10:	iload_1
   11:	if_icmpge	36
   14:	aload_3
   15:	aload_2
   16:	invokeinterface	#185,  1; //InterfaceMethod scala/Function0.apply:()Ljava/lang/Object;
   21:	invokeinterface	#25,  2; //InterfaceMethod scala/collection/generic/Builder.$plus$eq:(Ljava/lang/Object;)Lscala/collection/generic/Builder;
   26:	pop
   27:	iload	4
   29:	iconst_1
   30:	iadd
   31:	istore	4
   33:	goto	8
   36:	aload_3
   37:	invokeinterface	#35,  1; //InterfaceMethod scala/collection/generic/Builder.result:()Ljava/lang/Object;
   42:	astore	5
   44:	aload	5
   46:	instanceof	#37; //class scala/collection/Traversable
   49:	ifeq	57
   52:	aload	5
   54:	goto	65
   57:	getstatic	#43; //Field scala/runtime/ScalaRunTime$.MODULE$:Lscala/runtime/ScalaRunTime$;
   60:	aload	5
   62:	invokevirtual	#47; //Method scala/runtime/ScalaRunTime$.boxArray:(Ljava/lang/Object;)Lscala/runtime/BoxedArray;
   65:	checkcast	#37; //class scala/collection/Traversable
   68:	areturn
  LineNumberTable: 
   line 42: 0
   line 43: 5
   line 44: 8
   line 45: 14
   line 46: 27
   line 44: 33
   line 48: 36

  LocalVariableTable: 
   Start  Length  Slot  Name   Signature
   0      69      0    this       Lscala/collection/generic/TraversableFactory;
   0      69      1    n       I
   0      69      2    elem       Lscala/Function0;
   5      63      3    b       Lscala/collection/generic/Builder;
   8      60      4    i       I

  Signature: length = 0x2
   00 FFFFFFBB 

public scala.collection.Traversable concat(scala.collection.Sequence);
  Code:
   Stack=5, Locals=4, Args_size=2
   0:	aload_0
   1:	invokevirtual	#19; //Method newBuilder:()Lscala/collection/generic/Builder;
   4:	astore_2
   5:	aload_1
   6:	new	#191; //class scala/collection/generic/TraversableFactory$$anonfun$concat$1
   9:	dup
   10:	aload_0
   11:	aload_2
   12:	invokespecial	#194; //Method scala/collection/generic/TraversableFactory$$anonfun$concat$1."<init>":(Lscala/collection/generic/TraversableFactory;Lscala/collection/generic/Builder;)V
   15:	invokeinterface	#200,  2; //InterfaceMethod scala/collection/generic/IterableTemplate.foreach:(Lscala/Function1;)V
   20:	aload_2
   21:	invokeinterface	#35,  1; //InterfaceMethod scala/collection/generic/Builder.result:()Ljava/lang/Object;
   26:	astore_3
   27:	aload_3
   28:	instanceof	#37; //class scala/collection/Traversable
   31:	ifeq	38
   34:	aload_3
   35:	goto	45
   38:	getstatic	#43; //Field scala/runtime/ScalaRunTime$.MODULE$:Lscala/runtime/ScalaRunTime$;
   41:	aload_3
   42:	invokevirtual	#47; //Method scala/runtime/ScalaRunTime$.boxArray:(Ljava/lang/Object;)Lscala/runtime/BoxedArray;
   45:	checkcast	#37; //class scala/collection/Traversable
   48:	areturn
  LineNumberTable: 
   line 32: 0
   line 33: 5
   line 34: 20

  LocalVariableTable: 
   Start  Length  Slot  Name   Signature
   0      49      0    this       Lscala/collection/generic/TraversableFactory;
   0      49      1    xss       Lscala/collection/Sequence;
   5      43      2    b$1       Lscala/collection/generic/Builder;

  Signature: length = 0x2
   00 FFFFFFCC 

}

