Compiled from "TraversableViewTemplate.scala"
public abstract class scala.collection.generic.TraversableViewTemplate$class extends java.lang.Object
  SourceFile: "TraversableViewTemplate.scala"
  Scala: length = 0x
   
  InnerClass: 
   public final #209= #144 of #15; //$anon$4=class scala/collection/generic/TraversableViewTemplate$$anon$4 of class scala/collection/generic/TraversableViewTemplate
   public final #210= #132 of #15; //$anon$6=class scala/collection/generic/TraversableViewTemplate$$anon$6 of class scala/collection/generic/TraversableViewTemplate
   public final #211= #152 of #15; //$anon$2=class scala/collection/generic/TraversableViewTemplate$$anon$2 of class scala/collection/generic/TraversableViewTemplate
   public final #212= #126 of #15; //$anon$7=class scala/collection/generic/TraversableViewTemplate$$anon$7 of class scala/collection/generic/TraversableViewTemplate
   public final #213= #148 of #15; //$anon$3=class scala/collection/generic/TraversableViewTemplate$$anon$3 of class scala/collection/generic/TraversableViewTemplate
   public final #214= #137 of #15; //$anon$5=class scala/collection/generic/TraversableViewTemplate$$anon$5 of class scala/collection/generic/TraversableViewTemplate
   public final #215= #157 of #15; //$anon$1=class scala/collection/generic/TraversableViewTemplate$$anon$1 of class scala/collection/generic/TraversableViewTemplate
   public abstract #218= #217 of #15; //Transformed=class scala/collection/generic/TraversableViewTemplate$Transformed of class scala/collection/generic/TraversableViewTemplate
  minor version: 0
  major version: 49
  Constant pool:
const #1 = Asciz	SourceFile;
const #2 = Asciz	TraversableViewTemplate.scala;
const #3 = Asciz	$init$;
const #4 = Asciz	(Lscala/collection/generic/TraversableViewTemplate;)V;
const #5 = Asciz	Code;
const #6 = Asciz	LineNumberTable;
const #7 = Asciz	$this;
const #8 = Asciz	Lscala/collection/generic/TraversableViewTemplate;;
const #9 = Asciz	LocalVariableTable;
const #10 = Asciz	splitAt;
const #11 = Asciz	(Lscala/collection/generic/TraversableViewTemplate;I)Lscala/Tuple2;;
const #12 = Asciz	scala/Tuple2;
const #13 = class	#12;	//  scala/Tuple2
const #14 = Asciz	scala/collection/generic/TraversableViewTemplate;
const #15 = class	#14;	//  scala/collection/generic/TraversableViewTemplate
const #16 = Asciz	take;
const #17 = Asciz	(I)Lscala/collection/generic/TraversableView;;
const #18 = NameAndType	#16:#17;//  take:(I)Lscala/collection/generic/TraversableView;
const #19 = InterfaceMethod	#15.#18;	//  scala/collection/generic/TraversableViewTemplate.take:(I)Lscala/collection/generic/TraversableView;
const #20 = Asciz	drop;
const #21 = NameAndType	#20:#17;//  drop:(I)Lscala/collection/generic/TraversableView;
const #22 = InterfaceMethod	#15.#21;	//  scala/collection/generic/TraversableViewTemplate.drop:(I)Lscala/collection/generic/TraversableView;
const #23 = Asciz	<init>;
const #24 = Asciz	(Ljava/lang/Object;Ljava/lang/Object;)V;
const #25 = NameAndType	#23:#24;//  "<init>":(Ljava/lang/Object;Ljava/lang/Object;)V
const #26 = Method	#13.#25;	//  scala/Tuple2."<init>":(Ljava/lang/Object;Ljava/lang/Object;)V
const #27 = Asciz	n;
const #28 = Asciz	I;
const #29 = Asciz	span;
const #30 = Asciz	(Lscala/collection/generic/TraversableViewTemplate;Lscala/Function1;)Lscala/Tuple2;;
const #31 = Asciz	takeWhile;
const #32 = Asciz	(Lscala/Function1;)Lscala/collection/generic/TraversableView;;
const #33 = NameAndType	#31:#32;//  takeWhile:(Lscala/Function1;)Lscala/collection/generic/TraversableView;
const #34 = InterfaceMethod	#15.#33;	//  scala/collection/generic/TraversableViewTemplate.takeWhile:(Lscala/Function1;)Lscala/collection/generic/TraversableView;
const #35 = Asciz	dropWhile;
const #36 = NameAndType	#35:#32;//  dropWhile:(Lscala/Function1;)Lscala/collection/generic/TraversableView;
const #37 = InterfaceMethod	#15.#36;	//  scala/collection/generic/TraversableViewTemplate.dropWhile:(Lscala/Function1;)Lscala/collection/generic/TraversableView;
const #38 = Asciz	p;
const #39 = Asciz	Lscala/Function1;;
const #40 = Asciz	(Lscala/collection/generic/TraversableViewTemplate;Lscala/Function1;)Lscala/collection/generic/TraversableView;;
const #41 = Asciz	newTakenWhile;
const #42 = Asciz	(Lscala/Function1;)Lscala/collection/generic/TraversableViewTemplate$Transformed;;
const #43 = NameAndType	#41:#42;//  newTakenWhile:(Lscala/Function1;)Lscala/collection/generic/TraversableViewTemplate$Transformed;
const #44 = InterfaceMethod	#15.#43;	//  scala/collection/generic/TraversableViewTemplate.newTakenWhile:(Lscala/Function1;)Lscala/collection/generic/TraversableViewTemplate$Transformed;
const #45 = Asciz	newDroppedWhile;
const #46 = NameAndType	#45:#42;//  newDroppedWhile:(Lscala/Function1;)Lscala/collection/generic/TraversableViewTemplate$Transformed;
const #47 = InterfaceMethod	#15.#46;	//  scala/collection/generic/TraversableViewTemplate.newDroppedWhile:(Lscala/Function1;)Lscala/collection/generic/TraversableViewTemplate$Transformed;
const #48 = Asciz	slice;
const #49 = Asciz	(Lscala/collection/generic/TraversableViewTemplate;II)Lscala/collection/generic/TraversableView;;
const #50 = Asciz	scala/Predef$;
const #51 = class	#50;	//  scala/Predef$
const #52 = Asciz	MODULE$;
const #53 = Asciz	Lscala/Predef$;;
const #54 = NameAndType	#52:#53;//  MODULE$:Lscala/Predef$;
const #55 = Field	#51.#54;	//  scala/Predef$.MODULE$:Lscala/Predef$;
const #56 = Asciz	intWrapper;
const #57 = Asciz	(I)Lscala/runtime/RichInt;;
const #58 = NameAndType	#56:#57;//  intWrapper:(I)Lscala/runtime/RichInt;
const #59 = Method	#51.#58;	//  scala/Predef$.intWrapper:(I)Lscala/runtime/RichInt;
const #60 = Asciz	scala/runtime/RichInt;
const #61 = class	#60;	//  scala/runtime/RichInt
const #62 = Asciz	max;
const #63 = Asciz	(I)I;
const #64 = NameAndType	#62:#63;//  max:(I)I
const #65 = Method	#61.#64;	//  scala/runtime/RichInt.max:(I)I
const #66 = Asciz	newSliced;
const #67 = Asciz	(II)Lscala/collection/generic/TraversableViewTemplate$Transformed;;
const #68 = NameAndType	#66:#67;//  newSliced:(II)Lscala/collection/generic/TraversableViewTemplate$Transformed;
const #69 = InterfaceMethod	#15.#68;	//  scala/collection/generic/TraversableViewTemplate.newSliced:(II)Lscala/collection/generic/TraversableViewTemplate$Transformed;
const #70 = Asciz	from;
const #71 = Asciz	until;
const #72 = Asciz	(Lscala/collection/generic/TraversableViewTemplate;I)Lscala/collection/generic/TraversableView;;
const #73 = Asciz	scala/Math$;
const #74 = class	#73;	//  scala/Math$
const #75 = Asciz	Lscala/Math$;;
const #76 = NameAndType	#52:#75;//  MODULE$:Lscala/Math$;
const #77 = Field	#74.#76;	//  scala/Math$.MODULE$:Lscala/Math$;
const #78 = Asciz	MAX_INT;
const #79 = Asciz	()I;
const #80 = NameAndType	#78:#79;//  MAX_INT:()I
const #81 = Method	#74.#80;	//  scala/Math$.MAX_INT:()I
const #82 = Asciz	init;
const #83 = Asciz	(Lscala/collection/generic/TraversableViewTemplate;)Lscala/collection/generic/TraversableView;;
const #84 = Asciz	scala/collection/generic/TraversableTemplate;
const #85 = class	#84;	//  scala/collection/generic/TraversableTemplate
const #86 = Asciz	size;
const #87 = NameAndType	#86:#79;//  size:()I
const #88 = InterfaceMethod	#85.#87;	//  scala/collection/generic/TraversableTemplate.size:()I
const #89 = Asciz	filter;
const #90 = Asciz	newFiltered;
const #91 = NameAndType	#90:#42;//  newFiltered:(Lscala/Function1;)Lscala/collection/generic/TraversableViewTemplate$Transformed;
const #92 = InterfaceMethod	#15.#91;	//  scala/collection/generic/TraversableViewTemplate.newFiltered:(Lscala/Function1;)Lscala/collection/generic/TraversableViewTemplate$Transformed;
const #93 = Asciz	flatMap;
const #94 = Asciz	(Lscala/collection/generic/TraversableViewTemplate;Lscala/Function1;Lscala/collection/generic/BuilderFactory;)Ljava/lang/Object;;
const #95 = Asciz	newFlatMapped;
const #96 = NameAndType	#95:#42;//  newFlatMapped:(Lscala/Function1;)Lscala/collection/generic/TraversableViewTemplate$Transformed;
const #97 = InterfaceMethod	#15.#96;	//  scala/collection/generic/TraversableViewTemplate.newFlatMapped:(Lscala/Function1;)Lscala/collection/generic/TraversableViewTemplate$Transformed;
const #98 = Asciz	f;
const #99 = Asciz	bf;
const #100 = Asciz	Lscala/collection/generic/BuilderFactory;;
const #101 = Asciz	map;
const #102 = Asciz	newMapped;
const #103 = NameAndType	#102:#42;//  newMapped:(Lscala/Function1;)Lscala/collection/generic/TraversableViewTemplate$Transformed;
const #104 = InterfaceMethod	#15.#103;	//  scala/collection/generic/TraversableViewTemplate.newMapped:(Lscala/Function1;)Lscala/collection/generic/TraversableViewTemplate$Transformed;
const #105 = Asciz	$plus$plus;
const #106 = Asciz	(Lscala/collection/generic/TraversableViewTemplate;Lscala/collection/Iterator;Lscala/collection/generic/BuilderFactory;)Ljava/lang/Object;;
const #107 = Asciz	scala/collection/Iterator;
const #108 = class	#107;	//  scala/collection/Iterator
const #109 = Asciz	toStream;
const #110 = Asciz	()Lscala/collection/immutable/Stream;;
const #111 = NameAndType	#109:#110;//  toStream:()Lscala/collection/immutable/Stream;
const #112 = InterfaceMethod	#108.#111;	//  scala/collection/Iterator.toStream:()Lscala/collection/immutable/Stream;
const #113 = Asciz	(Lscala/collection/Traversable;Lscala/collection/generic/BuilderFactory;)Ljava/lang/Object;;
const #114 = NameAndType	#105:#113;//  $plus$plus:(Lscala/collection/Traversable;Lscala/collection/generic/BuilderFactory;)Ljava/lang/Object;
const #115 = InterfaceMethod	#15.#114;	//  scala/collection/generic/TraversableViewTemplate.$plus$plus:(Lscala/collection/Traversable;Lscala/collection/generic/BuilderFactory;)Ljava/lang/Object;
const #116 = Asciz	that;
const #117 = Asciz	Lscala/collection/Iterator;;
const #118 = Asciz	(Lscala/collection/generic/TraversableViewTemplate;Lscala/collection/Traversable;Lscala/collection/generic/BuilderFactory;)Ljava/lang/Object;;
const #119 = Asciz	newAppended;
const #120 = Asciz	(Lscala/collection/Traversable;)Lscala/collection/generic/TraversableViewTemplate$Transformed;;
const #121 = NameAndType	#119:#120;//  newAppended:(Lscala/collection/Traversable;)Lscala/collection/generic/TraversableViewTemplate$Transformed;
const #122 = InterfaceMethod	#15.#121;	//  scala/collection/generic/TraversableViewTemplate.newAppended:(Lscala/collection/Traversable;)Lscala/collection/generic/TraversableViewTemplate$Transformed;
const #123 = Asciz	Lscala/collection/Traversable;;
const #124 = Asciz	(Lscala/collection/generic/TraversableViewTemplate;Lscala/Function1;)Lscala/collection/generic/TraversableViewTemplate$Transformed;;
const #125 = Asciz	scala/collection/generic/TraversableViewTemplate$$anon$7;
const #126 = class	#125;	//  scala/collection/generic/TraversableViewTemplate$$anon$7
const #127 = Asciz	(Lscala/collection/generic/TraversableViewTemplate;Lscala/Function1;)V;
const #128 = NameAndType	#23:#127;//  "<init>":(Lscala/collection/generic/TraversableViewTemplate;Lscala/Function1;)V
const #129 = Method	#126.#128;	//  scala/collection/generic/TraversableViewTemplate$$anon$7."<init>":(Lscala/collection/generic/TraversableViewTemplate;Lscala/Function1;)V
const #130 = Asciz	p$3;
const #131 = Asciz	scala/collection/generic/TraversableViewTemplate$$anon$6;
const #132 = class	#131;	//  scala/collection/generic/TraversableViewTemplate$$anon$6
const #133 = Method	#132.#128;	//  scala/collection/generic/TraversableViewTemplate$$anon$6."<init>":(Lscala/collection/generic/TraversableViewTemplate;Lscala/Function1;)V
const #134 = Asciz	p$2;
const #135 = Asciz	(Lscala/collection/generic/TraversableViewTemplate;II)Lscala/collection/generic/TraversableViewTemplate$Transformed;;
const #136 = Asciz	scala/collection/generic/TraversableViewTemplate$$anon$5;
const #137 = class	#136;	//  scala/collection/generic/TraversableViewTemplate$$anon$5
const #138 = Asciz	(Lscala/collection/generic/TraversableViewTemplate;II)V;
const #139 = NameAndType	#23:#138;//  "<init>":(Lscala/collection/generic/TraversableViewTemplate;II)V
const #140 = Method	#137.#139;	//  scala/collection/generic/TraversableViewTemplate$$anon$5."<init>":(Lscala/collection/generic/TraversableViewTemplate;II)V
const #141 = Asciz	_from$1;
const #142 = Asciz	_until$1;
const #143 = Asciz	scala/collection/generic/TraversableViewTemplate$$anon$4;
const #144 = class	#143;	//  scala/collection/generic/TraversableViewTemplate$$anon$4
const #145 = Method	#144.#128;	//  scala/collection/generic/TraversableViewTemplate$$anon$4."<init>":(Lscala/collection/generic/TraversableViewTemplate;Lscala/Function1;)V
const #146 = Asciz	p$1;
const #147 = Asciz	scala/collection/generic/TraversableViewTemplate$$anon$3;
const #148 = class	#147;	//  scala/collection/generic/TraversableViewTemplate$$anon$3
const #149 = Method	#148.#128;	//  scala/collection/generic/TraversableViewTemplate$$anon$3."<init>":(Lscala/collection/generic/TraversableViewTemplate;Lscala/Function1;)V
const #150 = Asciz	f$2;
const #151 = Asciz	scala/collection/generic/TraversableViewTemplate$$anon$2;
const #152 = class	#151;	//  scala/collection/generic/TraversableViewTemplate$$anon$2
const #153 = Method	#152.#128;	//  scala/collection/generic/TraversableViewTemplate$$anon$2."<init>":(Lscala/collection/generic/TraversableViewTemplate;Lscala/Function1;)V
const #154 = Asciz	f$1;
const #155 = Asciz	(Lscala/collection/generic/TraversableViewTemplate;Lscala/collection/Traversable;)Lscala/collection/generic/TraversableViewTemplate$Transformed;;
const #156 = Asciz	scala/collection/generic/TraversableViewTemplate$$anon$1;
const #157 = class	#156;	//  scala/collection/generic/TraversableViewTemplate$$anon$1
const #158 = Asciz	(Lscala/collection/generic/TraversableViewTemplate;Lscala/collection/Traversable;)V;
const #159 = NameAndType	#23:#158;//  "<init>":(Lscala/collection/generic/TraversableViewTemplate;Lscala/collection/Traversable;)V
const #160 = Method	#157.#159;	//  scala/collection/generic/TraversableViewTemplate$$anon$1."<init>":(Lscala/collection/generic/TraversableViewTemplate;Lscala/collection/Traversable;)V
const #161 = Asciz	that$1;
const #162 = Asciz	force;
const #163 = Asciz	(Lscala/collection/generic/TraversableViewTemplate;Lscala/collection/generic/BuilderFactory;)Ljava/lang/Object;;
const #164 = Asciz	underlying;
const #165 = Asciz	()Lscala/collection/Traversable;;
const #166 = NameAndType	#164:#165;//  underlying:()Lscala/collection/Traversable;
const #167 = InterfaceMethod	#15.#166;	//  scala/collection/generic/TraversableViewTemplate.underlying:()Lscala/collection/Traversable;
const #168 = Asciz	scala/collection/generic/BuilderFactory;
const #169 = class	#168;	//  scala/collection/generic/BuilderFactory
const #170 = Asciz	apply;
const #171 = Asciz	(Ljava/lang/Object;)Lscala/collection/generic/Builder;;
const #172 = NameAndType	#170:#171;//  apply:(Ljava/lang/Object;)Lscala/collection/generic/Builder;
const #173 = InterfaceMethod	#169.#172;	//  scala/collection/generic/BuilderFactory.apply:(Ljava/lang/Object;)Lscala/collection/generic/Builder;
const #174 = Asciz	scala/collection/generic/Growable;
const #175 = class	#174;	//  scala/collection/generic/Growable
const #176 = Asciz	$plus$plus$eq;
const #177 = Asciz	(Lscala/collection/Traversable;)Lscala/collection/generic/Growable;;
const #178 = NameAndType	#176:#177;//  $plus$plus$eq:(Lscala/collection/Traversable;)Lscala/collection/generic/Growable;
const #179 = InterfaceMethod	#175.#178;	//  scala/collection/generic/Growable.$plus$plus$eq:(Lscala/collection/Traversable;)Lscala/collection/generic/Growable;
const #180 = Asciz	scala/collection/generic/Builder;
const #181 = class	#180;	//  scala/collection/generic/Builder
const #182 = Asciz	result;
const #183 = Asciz	()Ljava/lang/Object;;
const #184 = NameAndType	#182:#183;//  result:()Ljava/lang/Object;
const #185 = InterfaceMethod	#181.#184;	//  scala/collection/generic/Builder.result:()Ljava/lang/Object;
const #186 = Asciz	b;
const #187 = Asciz	Lscala/collection/generic/Builder;;
const #188 = Asciz	newBuilder;
const #189 = Asciz	(Lscala/collection/generic/TraversableViewTemplate;)Lscala/collection/generic/Builder;;
const #190 = Asciz	java/lang/UnsupportedOperationException;
const #191 = class	#190;	//  java/lang/UnsupportedOperationException
const #192 = Asciz	any2stringadd;
const #193 = Asciz	(Ljava/lang/Object;)Lscala/runtime/StringAdd;;
const #194 = NameAndType	#192:#193;//  any2stringadd:(Ljava/lang/Object;)Lscala/runtime/StringAdd;
const #195 = Method	#51.#194;	//  scala/Predef$.any2stringadd:(Ljava/lang/Object;)Lscala/runtime/StringAdd;
const #196 = Asciz	.newBuilder;
const #197 = String	#196;	//  .newBuilder
const #198 = Asciz	scala/runtime/StringAdd;
const #199 = class	#198;	//  scala/runtime/StringAdd
const #200 = Asciz	$plus;
const #201 = Asciz	(Ljava/lang/String;)Ljava/lang/String;;
const #202 = NameAndType	#200:#201;//  $plus:(Ljava/lang/String;)Ljava/lang/String;
const #203 = Method	#199.#202;	//  scala/runtime/StringAdd.$plus:(Ljava/lang/String;)Ljava/lang/String;
const #204 = Asciz	(Ljava/lang/String;)V;
const #205 = NameAndType	#23:#204;//  "<init>":(Ljava/lang/String;)V
const #206 = Method	#191.#205;	//  java/lang/UnsupportedOperationException."<init>":(Ljava/lang/String;)V
const #207 = Asciz	Scala;
const #208 = Asciz	InnerClasses;
const #209 = Asciz	$anon$4;
const #210 = Asciz	$anon$6;
const #211 = Asciz	$anon$2;
const #212 = Asciz	$anon$7;
const #213 = Asciz	$anon$3;
const #214 = Asciz	$anon$5;
const #215 = Asciz	$anon$1;
const #216 = Asciz	scala/collection/generic/TraversableViewTemplate$Transformed;
const #217 = class	#216;	//  scala/collection/generic/TraversableViewTemplate$Transformed
const #218 = Asciz	Transformed;
const #219 = Asciz	scala/collection/generic/TraversableViewTemplate$class;
const #220 = class	#219;	//  scala/collection/generic/TraversableViewTemplate$class
const #221 = Asciz	java/lang/Object;
const #222 = class	#221;	//  java/lang/Object

{
public static void $init$(scala.collection.generic.TraversableViewTemplate);
  Code:
   Stack=0, Locals=1, Args_size=1
   0:	return
  LineNumberTable: 
   line 36: 0

  LocalVariableTable: 
   Start  Length  Slot  Name   Signature
   0      1      0    $this       Lscala/collection/generic/TraversableViewTemplate;


public static scala.Tuple2 splitAt(scala.collection.generic.TraversableViewTemplate, int);
  Code:
   Stack=5, Locals=2, Args_size=2
   0:	new	#13; //class scala/Tuple2
   3:	dup
   4:	aload_0
   5:	iload_1
   6:	invokeinterface	#19,  2; //InterfaceMethod scala/collection/generic/TraversableViewTemplate.take:(I)Lscala/collection/generic/TraversableView;
   11:	aload_0
   12:	iload_1
   13:	invokeinterface	#22,  2; //InterfaceMethod scala/collection/generic/TraversableViewTemplate.drop:(I)Lscala/collection/generic/TraversableView;
   18:	invokespecial	#26; //Method scala/Tuple2."<init>":(Ljava/lang/Object;Ljava/lang/Object;)V
   21:	areturn
  LineNumberTable: 
   line 176: 0

  LocalVariableTable: 
   Start  Length  Slot  Name   Signature
   0      22      0    $this       Lscala/collection/generic/TraversableViewTemplate;
   0      22      1    n       I


public static scala.Tuple2 span(scala.collection.generic.TraversableViewTemplate, scala.Function1);
  Code:
   Stack=5, Locals=2, Args_size=2
   0:	new	#13; //class scala/Tuple2
   3:	dup
   4:	aload_0
   5:	aload_1
   6:	invokeinterface	#34,  2; //InterfaceMethod scala/collection/generic/TraversableViewTemplate.takeWhile:(Lscala/Function1;)Lscala/collection/generic/TraversableView;
   11:	aload_0
   12:	aload_1
   13:	invokeinterface	#37,  2; //InterfaceMethod scala/collection/generic/TraversableViewTemplate.dropWhile:(Lscala/Function1;)Lscala/collection/generic/TraversableView;
   18:	invokespecial	#26; //Method scala/Tuple2."<init>":(Ljava/lang/Object;Ljava/lang/Object;)V
   21:	areturn
  LineNumberTable: 
   line 175: 0

  LocalVariableTable: 
   Start  Length  Slot  Name   Signature
   0      22      0    $this       Lscala/collection/generic/TraversableViewTemplate;
   0      22      1    p       Lscala/Function1;


public static scala.collection.generic.TraversableView takeWhile(scala.collection.generic.TraversableViewTemplate, scala.Function1);
  Code:
   Stack=2, Locals=2, Args_size=2
   0:	aload_0
   1:	aload_1
   2:	invokeinterface	#44,  2; //InterfaceMethod scala/collection/generic/TraversableViewTemplate.newTakenWhile:(Lscala/Function1;)Lscala/collection/generic/TraversableViewTemplate$Transformed;
   7:	areturn
  LineNumberTable: 
   line 174: 0

  LocalVariableTable: 
   Start  Length  Slot  Name   Signature
   0      8      0    $this       Lscala/collection/generic/TraversableViewTemplate;
   0      8      1    p       Lscala/Function1;


public static scala.collection.generic.TraversableView dropWhile(scala.collection.generic.TraversableViewTemplate, scala.Function1);
  Code:
   Stack=2, Locals=2, Args_size=2
   0:	aload_0
   1:	aload_1
   2:	invokeinterface	#47,  2; //InterfaceMethod scala/collection/generic/TraversableViewTemplate.newDroppedWhile:(Lscala/Function1;)Lscala/collection/generic/TraversableViewTemplate$Transformed;
   7:	areturn
  LineNumberTable: 
   line 173: 0

  LocalVariableTable: 
   Start  Length  Slot  Name   Signature
   0      8      0    $this       Lscala/collection/generic/TraversableViewTemplate;
   0      8      1    p       Lscala/Function1;


public static scala.collection.generic.TraversableView slice(scala.collection.generic.TraversableViewTemplate, int, int);
  Code:
   Stack=3, Locals=3, Args_size=3
   0:	aload_0
   1:	getstatic	#55; //Field scala/Predef$.MODULE$:Lscala/Predef$;
   4:	iload_1
   5:	invokevirtual	#59; //Method scala/Predef$.intWrapper:(I)Lscala/runtime/RichInt;
   8:	iconst_0
   9:	invokevirtual	#65; //Method scala/runtime/RichInt.max:(I)I
   12:	iload_2
   13:	invokeinterface	#69,  3; //InterfaceMethod scala/collection/generic/TraversableViewTemplate.newSliced:(II)Lscala/collection/generic/TraversableViewTemplate$Transformed;
   18:	areturn
  LineNumberTable: 
   line 172: 0

  LocalVariableTable: 
   Start  Length  Slot  Name   Signature
   0      19      0    $this       Lscala/collection/generic/TraversableViewTemplate;
   0      19      1    from       I
   0      19      2    until       I


public static scala.collection.generic.TraversableView take(scala.collection.generic.TraversableViewTemplate, int);
  Code:
   Stack=3, Locals=2, Args_size=2
   0:	aload_0
   1:	iconst_0
   2:	iload_1
   3:	invokeinterface	#69,  3; //InterfaceMethod scala/collection/generic/TraversableViewTemplate.newSliced:(II)Lscala/collection/generic/TraversableViewTemplate$Transformed;
   8:	areturn
  LineNumberTable: 
   line 171: 0

  LocalVariableTable: 
   Start  Length  Slot  Name   Signature
   0      9      0    $this       Lscala/collection/generic/TraversableViewTemplate;
   0      9      1    n       I


public static scala.collection.generic.TraversableView drop(scala.collection.generic.TraversableViewTemplate, int);
  Code:
   Stack=3, Locals=2, Args_size=2
   0:	aload_0
   1:	getstatic	#55; //Field scala/Predef$.MODULE$:Lscala/Predef$;
   4:	iload_1
   5:	invokevirtual	#59; //Method scala/Predef$.intWrapper:(I)Lscala/runtime/RichInt;
   8:	iconst_0
   9:	invokevirtual	#65; //Method scala/runtime/RichInt.max:(I)I
   12:	getstatic	#77; //Field scala/Math$.MODULE$:Lscala/Math$;
   15:	invokevirtual	#81; //Method scala/Math$.MAX_INT:()I
   18:	invokeinterface	#69,  3; //InterfaceMethod scala/collection/generic/TraversableViewTemplate.newSliced:(II)Lscala/collection/generic/TraversableViewTemplate$Transformed;
   23:	areturn
  LineNumberTable: 
   line 170: 0

  LocalVariableTable: 
   Start  Length  Slot  Name   Signature
   0      24      0    $this       Lscala/collection/generic/TraversableViewTemplate;
   0      24      1    n       I


public static scala.collection.generic.TraversableView init(scala.collection.generic.TraversableViewTemplate);
  Code:
   Stack=4, Locals=1, Args_size=1
   0:	aload_0
   1:	iconst_0
   2:	aload_0
   3:	invokeinterface	#88,  1; //InterfaceMethod scala/collection/generic/TraversableTemplate.size:()I
   8:	iconst_1
   9:	isub
   10:	invokeinterface	#69,  3; //InterfaceMethod scala/collection/generic/TraversableViewTemplate.newSliced:(II)Lscala/collection/generic/TraversableViewTemplate$Transformed;
   15:	areturn
  LineNumberTable: 
   line 169: 0

  LocalVariableTable: 
   Start  Length  Slot  Name   Signature
   0      16      0    $this       Lscala/collection/generic/TraversableViewTemplate;


public static scala.collection.generic.TraversableView filter(scala.collection.generic.TraversableViewTemplate, scala.Function1);
  Code:
   Stack=2, Locals=2, Args_size=2
   0:	aload_0
   1:	aload_1
   2:	invokeinterface	#92,  2; //InterfaceMethod scala/collection/generic/TraversableViewTemplate.newFiltered:(Lscala/Function1;)Lscala/collection/generic/TraversableViewTemplate$Transformed;
   7:	areturn
  LineNumberTable: 
   line 168: 0

  LocalVariableTable: 
   Start  Length  Slot  Name   Signature
   0      8      0    $this       Lscala/collection/generic/TraversableViewTemplate;
   0      8      1    p       Lscala/Function1;


public static java.lang.Object flatMap(scala.collection.generic.TraversableViewTemplate, scala.Function1, scala.collection.generic.BuilderFactory);
  Code:
   Stack=2, Locals=3, Args_size=3
   0:	aload_0
   1:	aload_1
   2:	invokeinterface	#97,  2; //InterfaceMethod scala/collection/generic/TraversableViewTemplate.newFlatMapped:(Lscala/Function1;)Lscala/collection/generic/TraversableViewTemplate$Transformed;
   7:	areturn
  LineNumberTable: 
   line 162: 0

  LocalVariableTable: 
   Start  Length  Slot  Name   Signature
   0      8      0    $this       Lscala/collection/generic/TraversableViewTemplate;
   0      8      1    f       Lscala/Function1;
   0      8      2    bf       Lscala/collection/generic/BuilderFactory;


public static java.lang.Object map(scala.collection.generic.TraversableViewTemplate, scala.Function1, scala.collection.generic.BuilderFactory);
  Code:
   Stack=2, Locals=3, Args_size=3
   0:	aload_0
   1:	aload_1
   2:	invokeinterface	#104,  2; //InterfaceMethod scala/collection/generic/TraversableViewTemplate.newMapped:(Lscala/Function1;)Lscala/collection/generic/TraversableViewTemplate$Transformed;
   7:	areturn
  LineNumberTable: 
   line 155: 0

  LocalVariableTable: 
   Start  Length  Slot  Name   Signature
   0      8      0    $this       Lscala/collection/generic/TraversableViewTemplate;
   0      8      1    f       Lscala/Function1;
   0      8      2    bf       Lscala/collection/generic/BuilderFactory;


public static java.lang.Object $plus$plus(scala.collection.generic.TraversableViewTemplate, scala.collection.Iterator, scala.collection.generic.BuilderFactory);
  Code:
   Stack=3, Locals=3, Args_size=3
   0:	aload_0
   1:	aload_1
   2:	invokeinterface	#112,  1; //InterfaceMethod scala/collection/Iterator.toStream:()Lscala/collection/immutable/Stream;
   7:	aload_2
   8:	invokeinterface	#115,  3; //InterfaceMethod scala/collection/generic/TraversableViewTemplate.$plus$plus:(Lscala/collection/Traversable;Lscala/collection/generic/BuilderFactory;)Ljava/lang/Object;
   13:	areturn
  LineNumberTable: 
   line 152: 0

  LocalVariableTable: 
   Start  Length  Slot  Name   Signature
   0      14      0    $this       Lscala/collection/generic/TraversableViewTemplate;
   0      14      1    that       Lscala/collection/Iterator;
   0      14      2    bf       Lscala/collection/generic/BuilderFactory;


public static java.lang.Object $plus$plus(scala.collection.generic.TraversableViewTemplate, scala.collection.Traversable, scala.collection.generic.BuilderFactory);
  Code:
   Stack=2, Locals=3, Args_size=3
   0:	aload_0
   1:	aload_1
   2:	invokeinterface	#122,  2; //InterfaceMethod scala/collection/generic/TraversableViewTemplate.newAppended:(Lscala/collection/Traversable;)Lscala/collection/generic/TraversableViewTemplate$Transformed;
   7:	areturn
  LineNumberTable: 
   line 146: 0

  LocalVariableTable: 
   Start  Length  Slot  Name   Signature
   0      8      0    $this       Lscala/collection/generic/TraversableViewTemplate;
   0      8      1    that       Lscala/collection/Traversable;
   0      8      2    bf       Lscala/collection/generic/BuilderFactory;


public static scala.collection.generic.TraversableViewTemplate$Transformed newTakenWhile(scala.collection.generic.TraversableViewTemplate, scala.Function1);
  Code:
   Stack=4, Locals=2, Args_size=2
   0:	new	#126; //class scala/collection/generic/TraversableViewTemplate$$anon$7
   3:	dup
   4:	aload_0
   5:	aload_1
   6:	invokespecial	#129; //Method scala/collection/generic/TraversableViewTemplate$$anon$7."<init>":(Lscala/collection/generic/TraversableViewTemplate;Lscala/Function1;)V
   9:	areturn
  LineNumberTable: 
   line 143: 0

  LocalVariableTable: 
   Start  Length  Slot  Name   Signature
   0      10      0    $this       Lscala/collection/generic/TraversableViewTemplate;
   0      10      1    p$3       Lscala/Function1;


public static scala.collection.generic.TraversableViewTemplate$Transformed newDroppedWhile(scala.collection.generic.TraversableViewTemplate, scala.Function1);
  Code:
   Stack=4, Locals=2, Args_size=2
   0:	new	#132; //class scala/collection/generic/TraversableViewTemplate$$anon$6
   3:	dup
   4:	aload_0
   5:	aload_1
   6:	invokespecial	#133; //Method scala/collection/generic/TraversableViewTemplate$$anon$6."<init>":(Lscala/collection/generic/TraversableViewTemplate;Lscala/Function1;)V
   9:	areturn
  LineNumberTable: 
   line 142: 0

  LocalVariableTable: 
   Start  Length  Slot  Name   Signature
   0      10      0    $this       Lscala/collection/generic/TraversableViewTemplate;
   0      10      1    p$2       Lscala/Function1;


public static scala.collection.generic.TraversableViewTemplate$Transformed newSliced(scala.collection.generic.TraversableViewTemplate, int, int);
  Code:
   Stack=5, Locals=3, Args_size=3
   0:	new	#137; //class scala/collection/generic/TraversableViewTemplate$$anon$5
   3:	dup
   4:	aload_0
   5:	iload_1
   6:	iload_2
   7:	invokespecial	#140; //Method scala/collection/generic/TraversableViewTemplate$$anon$5."<init>":(Lscala/collection/generic/TraversableViewTemplate;II)V
   10:	areturn
  LineNumberTable: 
   line 141: 0

  LocalVariableTable: 
   Start  Length  Slot  Name   Signature
   0      11      0    $this       Lscala/collection/generic/TraversableViewTemplate;
   0      11      1    _from$1       I
   0      11      2    _until$1       I


public static scala.collection.generic.TraversableViewTemplate$Transformed newFiltered(scala.collection.generic.TraversableViewTemplate, scala.Function1);
  Code:
   Stack=4, Locals=2, Args_size=2
   0:	new	#144; //class scala/collection/generic/TraversableViewTemplate$$anon$4
   3:	dup
   4:	aload_0
   5:	aload_1
   6:	invokespecial	#145; //Method scala/collection/generic/TraversableViewTemplate$$anon$4."<init>":(Lscala/collection/generic/TraversableViewTemplate;Lscala/Function1;)V
   9:	areturn
  LineNumberTable: 
   line 140: 0

  LocalVariableTable: 
   Start  Length  Slot  Name   Signature
   0      10      0    $this       Lscala/collection/generic/TraversableViewTemplate;
   0      10      1    p$1       Lscala/Function1;


public static scala.collection.generic.TraversableViewTemplate$Transformed newFlatMapped(scala.collection.generic.TraversableViewTemplate, scala.Function1);
  Code:
   Stack=4, Locals=2, Args_size=2
   0:	new	#148; //class scala/collection/generic/TraversableViewTemplate$$anon$3
   3:	dup
   4:	aload_0
   5:	aload_1
   6:	invokespecial	#149; //Method scala/collection/generic/TraversableViewTemplate$$anon$3."<init>":(Lscala/collection/generic/TraversableViewTemplate;Lscala/Function1;)V
   9:	areturn
  LineNumberTable: 
   line 139: 0

  LocalVariableTable: 
   Start  Length  Slot  Name   Signature
   0      10      0    $this       Lscala/collection/generic/TraversableViewTemplate;
   0      10      1    f$2       Lscala/Function1;


public static scala.collection.generic.TraversableViewTemplate$Transformed newMapped(scala.collection.generic.TraversableViewTemplate, scala.Function1);
  Code:
   Stack=4, Locals=2, Args_size=2
   0:	new	#152; //class scala/collection/generic/TraversableViewTemplate$$anon$2
   3:	dup
   4:	aload_0
   5:	aload_1
   6:	invokespecial	#153; //Method scala/collection/generic/TraversableViewTemplate$$anon$2."<init>":(Lscala/collection/generic/TraversableViewTemplate;Lscala/Function1;)V
   9:	areturn
  LineNumberTable: 
   line 138: 0

  LocalVariableTable: 
   Start  Length  Slot  Name   Signature
   0      10      0    $this       Lscala/collection/generic/TraversableViewTemplate;
   0      10      1    f$1       Lscala/Function1;


public static scala.collection.generic.TraversableViewTemplate$Transformed newAppended(scala.collection.generic.TraversableViewTemplate, scala.collection.Traversable);
  Code:
   Stack=4, Locals=2, Args_size=2
   0:	new	#157; //class scala/collection/generic/TraversableViewTemplate$$anon$1
   3:	dup
   4:	aload_0
   5:	aload_1
   6:	invokespecial	#160; //Method scala/collection/generic/TraversableViewTemplate$$anon$1."<init>":(Lscala/collection/generic/TraversableViewTemplate;Lscala/collection/Traversable;)V
   9:	areturn
  LineNumberTable: 
   line 137: 0

  LocalVariableTable: 
   Start  Length  Slot  Name   Signature
   0      10      0    $this       Lscala/collection/generic/TraversableViewTemplate;
   0      10      1    that$1       Lscala/collection/Traversable;


public static java.lang.Object force(scala.collection.generic.TraversableViewTemplate, scala.collection.generic.BuilderFactory);
  Code:
   Stack=2, Locals=3, Args_size=2
   0:	aload_1
   1:	aload_0
   2:	invokeinterface	#167,  1; //InterfaceMethod scala/collection/generic/TraversableViewTemplate.underlying:()Lscala/collection/Traversable;
   7:	invokeinterface	#173,  2; //InterfaceMethod scala/collection/generic/BuilderFactory.apply:(Ljava/lang/Object;)Lscala/collection/generic/Builder;
   12:	astore_2
   13:	aload_2
   14:	aload_0
   15:	invokeinterface	#179,  2; //InterfaceMethod scala/collection/generic/Growable.$plus$plus$eq:(Lscala/collection/Traversable;)Lscala/collection/generic/Growable;
   20:	pop
   21:	aload_2
   22:	invokeinterface	#185,  1; //InterfaceMethod scala/collection/generic/Builder.result:()Ljava/lang/Object;
   27:	areturn
  LineNumberTable: 
   line 45: 0
   line 46: 13
   line 47: 21

  LocalVariableTable: 
   Start  Length  Slot  Name   Signature
   0      28      0    $this       Lscala/collection/generic/TraversableViewTemplate;
   0      28      1    bf       Lscala/collection/generic/BuilderFactory;
   13      14      2    b       Lscala/collection/generic/Builder;


public static scala.collection.generic.Builder newBuilder(scala.collection.generic.TraversableViewTemplate);
  Code:
   Stack=4, Locals=1, Args_size=1
   0:	new	#191; //class java/lang/UnsupportedOperationException
   3:	dup
   4:	getstatic	#55; //Field scala/Predef$.MODULE$:Lscala/Predef$;
   7:	aload_0
   8:	invokevirtual	#195; //Method scala/Predef$.any2stringadd:(Ljava/lang/Object;)Lscala/runtime/StringAdd;
   11:	ldc	#197; //String .newBuilder
   13:	invokevirtual	#203; //Method scala/runtime/StringAdd.$plus:(Ljava/lang/String;)Ljava/lang/String;
   16:	invokespecial	#206; //Method java/lang/UnsupportedOperationException."<init>":(Ljava/lang/String;)V
   19:	athrow
  LineNumberTable: 
   line 40: 0

  LocalVariableTable: 
   Start  Length  Slot  Name   Signature
   0      20      0    $this       Lscala/collection/generic/TraversableViewTemplate;


}

