Compiled from "TraversableViewTemplate.scala"
public abstract class scala.collection.generic.TraversableViewTemplate$Transformed$class extends java.lang.Object
  SourceFile: "TraversableViewTemplate.scala"
  Scala: length = 0x
   
  InnerClass: 
   public abstract #25= #13 of #19; //Transformed=class scala/collection/generic/TraversableViewTemplate$Transformed of class scala/collection/generic/TraversableViewTemplate
  minor version: 0
  major version: 49
  Constant pool:
const #1 = Asciz	SourceFile;
const #2 = Asciz	TraversableViewTemplate.scala;
const #3 = Asciz	$init$;
const #4 = Asciz	(Lscala/collection/generic/TraversableViewTemplate$Transformed;)V;
const #5 = Asciz	Code;
const #6 = Asciz	LineNumberTable;
const #7 = Asciz	$this;
const #8 = Asciz	Lscala/collection/generic/TraversableViewTemplate$Transformed;;
const #9 = Asciz	LocalVariableTable;
const #10 = Asciz	underlying;
const #11 = Asciz	(Lscala/collection/generic/TraversableViewTemplate$Transformed;)Lscala/collection/Traversable;;
const #12 = Asciz	scala/collection/generic/TraversableViewTemplate$Transformed;
const #13 = class	#12;	//  scala/collection/generic/TraversableViewTemplate$Transformed
const #14 = Asciz	scala$collection$generic$TraversableViewTemplate$Transformed$$$outer;
const #15 = Asciz	()Lscala/collection/generic/TraversableViewTemplate;;
const #16 = NameAndType	#14:#15;//  scala$collection$generic$TraversableViewTemplate$Transformed$$$outer:()Lscala/collection/generic/TraversableViewTemplate;
const #17 = InterfaceMethod	#13.#16;	//  scala/collection/generic/TraversableViewTemplate$Transformed.scala$collection$generic$TraversableViewTemplate$Transformed$$$outer:()Lscala/collection/generic/TraversableViewTemplate;
const #18 = Asciz	scala/collection/generic/TraversableViewTemplate;
const #19 = class	#18;	//  scala/collection/generic/TraversableViewTemplate
const #20 = Asciz	()Lscala/collection/Traversable;;
const #21 = NameAndType	#10:#20;//  underlying:()Lscala/collection/Traversable;
const #22 = InterfaceMethod	#19.#21;	//  scala/collection/generic/TraversableViewTemplate.underlying:()Lscala/collection/Traversable;
const #23 = Asciz	Scala;
const #24 = Asciz	InnerClasses;
const #25 = Asciz	Transformed;
const #26 = Asciz	scala/collection/generic/TraversableViewTemplate$Transformed$class;
const #27 = class	#26;	//  scala/collection/generic/TraversableViewTemplate$Transformed$class
const #28 = Asciz	java/lang/Object;
const #29 = class	#28;	//  java/lang/Object

{
public static void $init$(scala.collection.generic.TraversableViewTemplate$Transformed);
  Code:
   Stack=0, Locals=1, Args_size=1
   0:	return
  LineNumberTable: 
   line 50: 0

  LocalVariableTable: 
   Start  Length  Slot  Name   Signature
   0      1      0    $this       Lscala/collection/generic/TraversableViewTemplate$Transformed;


public static scala.collection.Traversable underlying(scala.collection.generic.TraversableViewTemplate$Transformed);
  Code:
   Stack=1, Locals=1, Args_size=1
   0:	aload_0
   1:	invokeinterface	#17,  1; //InterfaceMethod scala/collection/generic/TraversableViewTemplate$Transformed.scala$collection$generic$TraversableViewTemplate$Transformed$$$outer:()Lscala/collection/generic/TraversableViewTemplate;
   6:	invokeinterface	#22,  1; //InterfaceMethod scala/collection/generic/TraversableViewTemplate.underlying:()Lscala/collection/Traversable;
   11:	areturn
  LineNumberTable: 
   line 51: 0

  LocalVariableTable: 
   Start  Length  Slot  Name   Signature
   0      12      0    $this       Lscala/collection/generic/TraversableViewTemplate$Transformed;


}

