Compiled from "TraversableTemplate.scala"
public final class scala.collection.generic.TraversableTemplate$$anonfun$groupBy$1 extends java.lang.Object implements scala.Function1,scala.ScalaObject,java.io.Serializable
  SourceFile: "TraversableTemplate.scala"
  Scala: length = 0x
   
  InnerClass: 
   public final #132= #19 of #75; //$anonfun$groupBy$1=class scala/collection/generic/TraversableTemplate$$anonfun$groupBy$1 of class scala/collection/generic/TraversableTemplate
  minor version: 0
  major version: 49
  Constant pool:
const #1 = Asciz	SourceFile;
const #2 = Asciz	TraversableTemplate.scala;
const #3 = Asciz	m$1;
const #4 = Asciz	Lscala/runtime/ObjectRef;;
const #5 = Asciz	f$3;
const #6 = Asciz	Lscala/Function1;;
const #7 = Asciz	$outer;
const #8 = Asciz	Lscala/collection/generic/TraversableTemplate;;
const #9 = Asciz	<init>;
const #10 = Asciz	(Lscala/collection/generic/TraversableTemplate;Lscala/Function1;Lscala/runtime/ObjectRef;)V;
const #11 = Asciz	Code;
const #12 = Asciz	LineNumberTable;
const #13 = Asciz	java/lang/NullPointerException;
const #14 = class	#13;	//  java/lang/NullPointerException
const #15 = Asciz	()V;
const #16 = NameAndType	#9:#15;//  "<init>":()V
const #17 = Method	#14.#16;	//  java/lang/NullPointerException."<init>":()V
const #18 = Asciz	scala/collection/generic/TraversableTemplate$$anonfun$groupBy$1;
const #19 = class	#18;	//  scala/collection/generic/TraversableTemplate$$anonfun$groupBy$1
const #20 = NameAndType	#7:#8;//  $outer:Lscala/collection/generic/TraversableTemplate;
const #21 = Field	#19.#20;	//  scala/collection/generic/TraversableTemplate$$anonfun$groupBy$1.$outer:Lscala/collection/generic/TraversableTemplate;
const #22 = NameAndType	#5:#6;//  f$3:Lscala/Function1;
const #23 = Field	#19.#22;	//  scala/collection/generic/TraversableTemplate$$anonfun$groupBy$1.f$3:Lscala/Function1;
const #24 = NameAndType	#3:#4;//  m$1:Lscala/runtime/ObjectRef;
const #25 = Field	#19.#24;	//  scala/collection/generic/TraversableTemplate$$anonfun$groupBy$1.m$1:Lscala/runtime/ObjectRef;
const #26 = Asciz	java/lang/Object;
const #27 = class	#26;	//  java/lang/Object
const #28 = Method	#27.#16;	//  java/lang/Object."<init>":()V
const #29 = Asciz	scala/Function1$class;
const #30 = class	#29;	//  scala/Function1$class
const #31 = Asciz	$init$;
const #32 = Asciz	(Lscala/Function1;)V;
const #33 = NameAndType	#31:#32;//  $init$:(Lscala/Function1;)V
const #34 = Method	#30.#33;	//  scala/Function1$class.$init$:(Lscala/Function1;)V
const #35 = Asciz	this;
const #36 = Asciz	Lscala/collection/generic/TraversableTemplate$$anonfun$groupBy$1;;
const #37 = Asciz	LocalVariableTable;
const #38 = Asciz	(Lscala/collection/generic/TraversableTemplate<TA;TThis;>;)V;
const #39 = Asciz	Signature;
const #40 = Asciz	apply;
const #41 = Asciz	(Ljava/lang/Object;)Ljava/lang/Object;;
const #42 = Asciz	(Ljava/lang/Object;)Lscala/collection/generic/Builder;;
const #43 = NameAndType	#40:#42;//  apply:(Ljava/lang/Object;)Lscala/collection/generic/Builder;
const #44 = Method	#19.#43;	//  scala/collection/generic/TraversableTemplate$$anonfun$groupBy$1.apply:(Ljava/lang/Object;)Lscala/collection/generic/Builder;
const #45 = Asciz	v1;
const #46 = Asciz	Ljava/lang/Object;;
const #47 = Asciz	scala/Function1;
const #48 = class	#47;	//  scala/Function1
const #49 = NameAndType	#40:#41;//  apply:(Ljava/lang/Object;)Ljava/lang/Object;
const #50 = InterfaceMethod	#48.#49;	//  scala/Function1.apply:(Ljava/lang/Object;)Ljava/lang/Object;
const #51 = Asciz	scala/runtime/ObjectRef;
const #52 = class	#51;	//  scala/runtime/ObjectRef
const #53 = Asciz	elem;
const #54 = NameAndType	#53:#46;//  elem:Ljava/lang/Object;
const #55 = Field	#52.#54;	//  scala/runtime/ObjectRef.elem:Ljava/lang/Object;
const #56 = Asciz	scala/collection/immutable/Map;
const #57 = class	#56;	//  scala/collection/immutable/Map
const #58 = Asciz	scala/collection/generic/MapTemplate;
const #59 = class	#58;	//  scala/collection/generic/MapTemplate
const #60 = Asciz	get;
const #61 = Asciz	(Ljava/lang/Object;)Lscala/Option;;
const #62 = NameAndType	#60:#61;//  get:(Ljava/lang/Object;)Lscala/Option;
const #63 = InterfaceMethod	#59.#62;	//  scala/collection/generic/MapTemplate.get:(Ljava/lang/Object;)Lscala/Option;
const #64 = Asciz	scala/None$;
const #65 = class	#64;	//  scala/None$
const #66 = Asciz	MODULE$;
const #67 = Asciz	Lscala/None$;;
const #68 = NameAndType	#66:#67;//  MODULE$:Lscala/None$;
const #69 = Field	#65.#68;	//  scala/None$.MODULE$:Lscala/None$;
const #70 = Asciz	equals;
const #71 = Asciz	(Ljava/lang/Object;)Z;
const #72 = NameAndType	#70:#71;//  equals:(Ljava/lang/Object;)Z
const #73 = Method	#27.#72;	//  java/lang/Object.equals:(Ljava/lang/Object;)Z
const #74 = Asciz	scala/collection/generic/TraversableTemplate;
const #75 = class	#74;	//  scala/collection/generic/TraversableTemplate
const #76 = Asciz	newBuilder;
const #77 = Asciz	()Lscala/collection/generic/Builder;;
const #78 = NameAndType	#76:#77;//  newBuilder:()Lscala/collection/generic/Builder;
const #79 = InterfaceMethod	#75.#78;	//  scala/collection/generic/TraversableTemplate.newBuilder:()Lscala/collection/generic/Builder;
const #80 = Asciz	scala/collection/generic/ImmutableMapTemplate;
const #81 = class	#80;	//  scala/collection/generic/ImmutableMapTemplate
const #82 = Asciz	updated;
const #83 = Asciz	(Ljava/lang/Object;Ljava/lang/Object;)Lscala/collection/immutable/Map;;
const #84 = NameAndType	#82:#83;//  updated:(Ljava/lang/Object;Ljava/lang/Object;)Lscala/collection/immutable/Map;
const #85 = InterfaceMethod	#81.#84;	//  scala/collection/generic/ImmutableMapTemplate.updated:(Ljava/lang/Object;Ljava/lang/Object;)Lscala/collection/immutable/Map;
const #86 = Asciz	scala/Some;
const #87 = class	#86;	//  scala/Some
const #88 = Asciz	x;
const #89 = Asciz	()Ljava/lang/Object;;
const #90 = NameAndType	#88:#89;//  x:()Ljava/lang/Object;
const #91 = Method	#87.#90;	//  scala/Some.x:()Ljava/lang/Object;
const #92 = Asciz	scala/collection/generic/Builder;
const #93 = class	#92;	//  scala/collection/generic/Builder
const #94 = Asciz	$plus$eq;
const #95 = NameAndType	#94:#42;//  $plus$eq:(Ljava/lang/Object;)Lscala/collection/generic/Builder;
const #96 = InterfaceMethod	#93.#95;	//  scala/collection/generic/Builder.$plus$eq:(Ljava/lang/Object;)Lscala/collection/generic/Builder;
const #97 = Asciz	scala/MatchError;
const #98 = class	#97;	//  scala/MatchError
const #99 = Asciz	scala/Option;
const #100 = class	#99;	//  scala/Option
const #101 = Asciz	toString;
const #102 = Asciz	()Ljava/lang/String;;
const #103 = NameAndType	#101:#102;//  toString:()Ljava/lang/String;
const #104 = Method	#100.#103;	//  scala/Option.toString:()Ljava/lang/String;
const #105 = Asciz	(Ljava/lang/String;)V;
const #106 = NameAndType	#9:#105;//  "<init>":(Ljava/lang/String;)V
const #107 = Method	#98.#106;	//  scala/MatchError."<init>":(Ljava/lang/String;)V
const #108 = Asciz	key;
const #109 = Asciz	bldr;
const #110 = Asciz	Lscala/collection/generic/Builder;;
const #111 = Asciz	temp1;
const #112 = Asciz	Lscala/Option;;
const #113 = Asciz	b;
const #114 = Asciz	temp3;
const #115 = Asciz	Lscala/Some;;
const #116 = Asciz	temp4;
const #117 = Asciz	(TA;)Lscala/collection/generic/Builder<TA;TThis;>;;
const #118 = Asciz	andThen;
const #119 = Asciz	(Lscala/Function1;)Lscala/Function1;;
const #120 = Asciz	(Lscala/Function1;Lscala/Function1;)Lscala/Function1;;
const #121 = NameAndType	#118:#120;//  andThen:(Lscala/Function1;Lscala/Function1;)Lscala/Function1;
const #122 = Method	#30.#121;	//  scala/Function1$class.andThen:(Lscala/Function1;Lscala/Function1;)Lscala/Function1;
const #123 = Asciz	g;
const #124 = Asciz	compose;
const #125 = NameAndType	#124:#120;//  compose:(Lscala/Function1;Lscala/Function1;)Lscala/Function1;
const #126 = Method	#30.#125;	//  scala/Function1$class.compose:(Lscala/Function1;Lscala/Function1;)Lscala/Function1;
const #127 = Asciz	(Lscala/Function1;)Ljava/lang/String;;
const #128 = NameAndType	#101:#127;//  toString:(Lscala/Function1;)Ljava/lang/String;
const #129 = Method	#30.#128;	//  scala/Function1$class.toString:(Lscala/Function1;)Ljava/lang/String;
const #130 = Asciz	Scala;
const #131 = Asciz	InnerClasses;
const #132 = Asciz	$anonfun$groupBy$1;
const #133 = Asciz	scala/ScalaObject;
const #134 = class	#133;	//  scala/ScalaObject
const #135 = Asciz	java/io/Serializable;
const #136 = class	#135;	//  java/io/Serializable

{
public scala.collection.generic.TraversableTemplate$$anonfun$groupBy$1(scala.collection.generic.TraversableTemplate, scala.Function1, scala.runtime.ObjectRef);
  Code:
   Stack=2, Locals=4, Args_size=4
   0:	aload_1
   1:	ifnonnull	12
   4:	new	#14; //class java/lang/NullPointerException
   7:	dup
   8:	invokespecial	#17; //Method java/lang/NullPointerException."<init>":()V
   11:	athrow
   12:	aload_0
   13:	aload_1
   14:	putfield	#21; //Field $outer:Lscala/collection/generic/TraversableTemplate;
   17:	aload_0
   18:	aload_2
   19:	putfield	#23; //Field f$3:Lscala/Function1;
   22:	aload_0
   23:	aload_3
   24:	putfield	#25; //Field m$1:Lscala/runtime/ObjectRef;
   27:	aload_0
   28:	invokespecial	#28; //Method java/lang/Object."<init>":()V
   31:	aload_0
   32:	invokestatic	#34; //Method scala/Function1$class.$init$:(Lscala/Function1;)V
   35:	return
  LineNumberTable: 
   line 259: 0

  LocalVariableTable: 
   Start  Length  Slot  Name   Signature
   0      36      0    this       Lscala/collection/generic/TraversableTemplate$$anonfun$groupBy$1;
   0      36      1    $outer       Lscala/collection/generic/TraversableTemplate;

  Signature: length = 0x2
   00 26 

public final java.lang.Object apply(java.lang.Object);
  Code:
   Stack=2, Locals=3, Args_size=2
   0:	aload_0
   1:	getfield	#21; //Field $outer:Lscala/collection/generic/TraversableTemplate;
   4:	astore_2
   5:	aload_0
   6:	aload_1
   7:	invokevirtual	#44; //Method apply:(Ljava/lang/Object;)Lscala/collection/generic/Builder;
   10:	areturn
  LineNumberTable: 
   line 259: 0

  LocalVariableTable: 
   Start  Length  Slot  Name   Signature
   0      11      0    this       Lscala/collection/generic/TraversableTemplate$$anonfun$groupBy$1;
   5      6      1    v1       Ljava/lang/Object;


public final scala.collection.generic.Builder apply(java.lang.Object);
  Code:
   Stack=4, Locals=10, Args_size=2
   0:	aload_0
   1:	getfield	#21; //Field $outer:Lscala/collection/generic/TraversableTemplate;
   4:	astore	9
   6:	aload_0
   7:	getfield	#23; //Field f$3:Lscala/Function1;
   10:	aload_1
   11:	invokeinterface	#50,  2; //InterfaceMethod scala/Function1.apply:(Ljava/lang/Object;)Ljava/lang/Object;
   16:	astore_2
   17:	aload_0
   18:	getfield	#25; //Field m$1:Lscala/runtime/ObjectRef;
   21:	getfield	#55; //Field scala/runtime/ObjectRef.elem:Ljava/lang/Object;
   24:	checkcast	#57; //class scala/collection/immutable/Map
   27:	aload_2
   28:	invokeinterface	#63,  2; //InterfaceMethod scala/collection/generic/MapTemplate.get:(Ljava/lang/Object;)Lscala/Option;
   33:	astore	4
   35:	getstatic	#69; //Field scala/None$.MODULE$:Lscala/None$;
   38:	aload	4
   40:	astore	5
   42:	dup
   43:	ifnonnull	55
   46:	pop
   47:	aload	5
   49:	ifnull	63
   52:	goto	112
   55:	aload	5
   57:	invokevirtual	#73; //Method java/lang/Object.equals:(Ljava/lang/Object;)Z
   60:	ifeq	112
   63:	aload	4
   65:	instanceof	#65; //class scala/None$
   68:	ifeq	112
   71:	aload_0
   72:	getfield	#21; //Field $outer:Lscala/collection/generic/TraversableTemplate;
   75:	invokeinterface	#79,  1; //InterfaceMethod scala/collection/generic/TraversableTemplate.newBuilder:()Lscala/collection/generic/Builder;
   80:	astore	6
   82:	aload_0
   83:	getfield	#25; //Field m$1:Lscala/runtime/ObjectRef;
   86:	aload_0
   87:	getfield	#25; //Field m$1:Lscala/runtime/ObjectRef;
   90:	getfield	#55; //Field scala/runtime/ObjectRef.elem:Ljava/lang/Object;
   93:	checkcast	#57; //class scala/collection/immutable/Map
   96:	aload_2
   97:	aload	6
   99:	invokeinterface	#85,  3; //InterfaceMethod scala/collection/generic/ImmutableMapTemplate.updated:(Ljava/lang/Object;Ljava/lang/Object;)Lscala/collection/immutable/Map;
   104:	putfield	#55; //Field scala/runtime/ObjectRef.elem:Ljava/lang/Object;
   107:	aload	6
   109:	goto	139
   112:	aload	4
   114:	instanceof	#87; //class scala/Some
   117:	ifeq	148
   120:	aload	4
   122:	checkcast	#87; //class scala/Some
   125:	astore	7
   127:	aload	7
   129:	invokevirtual	#91; //Method scala/Some.x:()Ljava/lang/Object;
   132:	checkcast	#93; //class scala/collection/generic/Builder
   135:	astore	8
   137:	aload	8
   139:	astore_3
   140:	aload_3
   141:	aload_1
   142:	invokeinterface	#96,  2; //InterfaceMethod scala/collection/generic/Builder.$plus$eq:(Ljava/lang/Object;)Lscala/collection/generic/Builder;
   147:	areturn
   148:	new	#98; //class scala/MatchError
   151:	dup
   152:	aload	4
   154:	invokevirtual	#104; //Method scala/Option.toString:()Ljava/lang/String;
   157:	invokespecial	#107; //Method scala/MatchError."<init>":(Ljava/lang/String;)V
   160:	athrow
  LineNumberTable: 
   line 260: 0
   line 261: 17
   line 262: 71
   line 261: 112
   line 263: 137
   line 261: 139
   line 265: 140
   line 261: 148

  LocalVariableTable: 
   Start  Length  Slot  Name   Signature
   0      161      0    this       Lscala/collection/generic/TraversableTemplate$$anonfun$groupBy$1;
   6      155      1    elem       Ljava/lang/Object;
   17      130      2    key       Ljava/lang/Object;
   148      13      2    key       Ljava/lang/Object;
   140      7      3    bldr       Lscala/collection/generic/Builder;
   35      126      4    temp1       Lscala/Option;
   82      27      6    b       Lscala/collection/generic/Builder;
   127      12      7    temp3       Lscala/Some;
   137      2      8    temp4       Lscala/collection/generic/Builder;

  Signature: length = 0x2
   00 75 

public scala.Function1 andThen(scala.Function1);
  Code:
   Stack=2, Locals=2, Args_size=2
   0:	aload_0
   1:	aload_1
   2:	invokestatic	#122; //Method scala/Function1$class.andThen:(Lscala/Function1;Lscala/Function1;)Lscala/Function1;
   5:	areturn
  LineNumberTable: 
   line 259: 0

  LocalVariableTable: 
   Start  Length  Slot  Name   Signature
   0      6      0    this       Lscala/collection/generic/TraversableTemplate$$anonfun$groupBy$1;
   0      6      1    g       Lscala/Function1;


public scala.Function1 compose(scala.Function1);
  Code:
   Stack=2, Locals=2, Args_size=2
   0:	aload_0
   1:	aload_1
   2:	invokestatic	#126; //Method scala/Function1$class.compose:(Lscala/Function1;Lscala/Function1;)Lscala/Function1;
   5:	areturn
  LineNumberTable: 
   line 259: 0

  LocalVariableTable: 
   Start  Length  Slot  Name   Signature
   0      6      0    this       Lscala/collection/generic/TraversableTemplate$$anonfun$groupBy$1;
   0      6      1    g       Lscala/Function1;


public java.lang.String toString();
  Code:
   Stack=1, Locals=1, Args_size=1
   0:	aload_0
   1:	invokestatic	#129; //Method scala/Function1$class.toString:(Lscala/Function1;)Ljava/lang/String;
   4:	areturn
  LineNumberTable: 
   line 259: 0


}

