Compiled from "TraversableFactory.scala"
public class scala.collection.generic.TraversableFactory$VirtualBuilderFactory extends java.lang.Object implements scala.collection.generic.BuilderFactory,scala.ScalaObject
  SourceFile: "TraversableFactory.scala"
  Signature: length = 0x2
   00 37 
  Scala: length = 0x
   
  InnerClass: 
   public #60= #15 of #59; //VirtualBuilderFactory=class scala/collection/generic/TraversableFactory$VirtualBuilderFactory of class scala/collection/generic/TraversableFactory
  minor version: 0
  major version: 49
  Constant pool:
const #1 = Asciz	SourceFile;
const #2 = Asciz	TraversableFactory.scala;
const #3 = Asciz	$outer;
const #4 = Asciz	Lscala/collection/generic/TraversableFactory;;
const #5 = Asciz	<init>;
const #6 = Asciz	(Lscala/collection/generic/TraversableFactory;)V;
const #7 = Asciz	Code;
const #8 = Asciz	LineNumberTable;
const #9 = Asciz	java/lang/NullPointerException;
const #10 = class	#9;	//  java/lang/NullPointerException
const #11 = Asciz	()V;
const #12 = NameAndType	#5:#11;//  "<init>":()V
const #13 = Method	#10.#12;	//  java/lang/NullPointerException."<init>":()V
const #14 = Asciz	scala/collection/generic/TraversableFactory$VirtualBuilderFactory;
const #15 = class	#14;	//  scala/collection/generic/TraversableFactory$VirtualBuilderFactory
const #16 = NameAndType	#3:#4;//  $outer:Lscala/collection/generic/TraversableFactory;
const #17 = Field	#15.#16;	//  scala/collection/generic/TraversableFactory$VirtualBuilderFactory.$outer:Lscala/collection/generic/TraversableFactory;
const #18 = Asciz	java/lang/Object;
const #19 = class	#18;	//  java/lang/Object
const #20 = Method	#19.#12;	//  java/lang/Object."<init>":()V
const #21 = Asciz	this;
const #22 = Asciz	Lscala/collection/generic/TraversableFactory$VirtualBuilderFactory;;
const #23 = Asciz	LocalVariableTable;
const #24 = Asciz	(Lscala/collection/generic/TraversableFactory<TCC;>;)V;
const #25 = Asciz	Signature;
const #26 = Asciz	apply;
const #27 = Asciz	(Ljava/lang/Object;)Lscala/collection/generic/Builder;;
const #28 = Asciz	scala/collection/Traversable;
const #29 = class	#28;	//  scala/collection/Traversable
const #30 = Asciz	scala/runtime/ScalaRunTime$;
const #31 = class	#30;	//  scala/runtime/ScalaRunTime$
const #32 = Asciz	MODULE$;
const #33 = Asciz	Lscala/runtime/ScalaRunTime$;;
const #34 = NameAndType	#32:#33;//  MODULE$:Lscala/runtime/ScalaRunTime$;
const #35 = Field	#31.#34;	//  scala/runtime/ScalaRunTime$.MODULE$:Lscala/runtime/ScalaRunTime$;
const #36 = Asciz	boxArray;
const #37 = Asciz	(Ljava/lang/Object;)Lscala/runtime/BoxedArray;;
const #38 = NameAndType	#36:#37;//  boxArray:(Ljava/lang/Object;)Lscala/runtime/BoxedArray;
const #39 = Method	#31.#38;	//  scala/runtime/ScalaRunTime$.boxArray:(Ljava/lang/Object;)Lscala/runtime/BoxedArray;
const #40 = Asciz	(Lscala/collection/Traversable;)Lscala/collection/generic/Builder;;
const #41 = NameAndType	#26:#40;//  apply:(Lscala/collection/Traversable;)Lscala/collection/generic/Builder;
const #42 = Method	#15.#41;	//  scala/collection/generic/TraversableFactory$VirtualBuilderFactory.apply:(Lscala/collection/Traversable;)Lscala/collection/generic/Builder;
const #43 = Asciz	from;
const #44 = Asciz	Ljava/lang/Object;;
const #45 = Asciz	scala$collection$generic$TraversableFactory$VirtualBuilderFactory$$$outer;
const #46 = Asciz	()Lscala/collection/generic/TraversableFactory;;
const #47 = Asciz	scala/collection/generic/TraversableClass;
const #48 = class	#47;	//  scala/collection/generic/TraversableClass
const #49 = Asciz	genericBuilder;
const #50 = Asciz	()Lscala/collection/generic/Builder;;
const #51 = NameAndType	#49:#50;//  genericBuilder:()Lscala/collection/generic/Builder;
const #52 = InterfaceMethod	#48.#51;	//  scala/collection/generic/TraversableClass.genericBuilder:()Lscala/collection/generic/Builder;
const #53 = Asciz	Lscala/collection/Traversable;;
const #54 = Asciz	(TCC;)Lscala/collection/generic/Builder<TA;TCC;>;;
const #55 = Asciz	<A:Ljava/lang/Object;>Ljava/lang/Object;Lscala/collection/generic/BuilderFactory<TA;TCC;TCC;>;Lscala/ScalaObject;;
const #56 = Asciz	Scala;
const #57 = Asciz	InnerClasses;
const #58 = Asciz	scala/collection/generic/TraversableFactory;
const #59 = class	#58;	//  scala/collection/generic/TraversableFactory
const #60 = Asciz	VirtualBuilderFactory;
const #61 = Asciz	scala/collection/generic/BuilderFactory;
const #62 = class	#61;	//  scala/collection/generic/BuilderFactory
const #63 = Asciz	scala/ScalaObject;
const #64 = class	#63;	//  scala/ScalaObject

{
public final scala.collection.generic.TraversableFactory $outer;

public scala.collection.generic.TraversableFactory$VirtualBuilderFactory(scala.collection.generic.TraversableFactory);
  Code:
   Stack=2, Locals=2, Args_size=2
   0:	aload_1
   1:	ifnonnull	12
   4:	new	#10; //class java/lang/NullPointerException
   7:	dup
   8:	invokespecial	#13; //Method java/lang/NullPointerException."<init>":()V
   11:	athrow
   12:	aload_0
   13:	aload_1
   14:	putfield	#17; //Field $outer:Lscala/collection/generic/TraversableFactory;
   17:	aload_0
   18:	invokespecial	#20; //Method java/lang/Object."<init>":()V
   21:	return
  LineNumberTable: 
   line 22: 0

  LocalVariableTable: 
   Start  Length  Slot  Name   Signature
   0      22      0    this       Lscala/collection/generic/TraversableFactory$VirtualBuilderFactory;
   0      22      1    $outer       Lscala/collection/generic/TraversableFactory;

  Signature: length = 0x2
   00 18 

public scala.collection.generic.Builder apply(java.lang.Object);
  Code:
   Stack=3, Locals=2, Args_size=2
   0:	aload_0
   1:	aload_1
   2:	instanceof	#29; //class scala/collection/Traversable
   5:	ifeq	12
   8:	aload_1
   9:	goto	19
   12:	getstatic	#35; //Field scala/runtime/ScalaRunTime$.MODULE$:Lscala/runtime/ScalaRunTime$;
   15:	aload_1
   16:	invokevirtual	#39; //Method scala/runtime/ScalaRunTime$.boxArray:(Ljava/lang/Object;)Lscala/runtime/BoxedArray;
   19:	checkcast	#29; //class scala/collection/Traversable
   22:	invokevirtual	#42; //Method apply:(Lscala/collection/Traversable;)Lscala/collection/generic/Builder;
   25:	areturn
  LineNumberTable: 
   line 22: 0

  LocalVariableTable: 
   Start  Length  Slot  Name   Signature
   0      26      0    this       Lscala/collection/generic/TraversableFactory$VirtualBuilderFactory;
   0      26      1    from       Ljava/lang/Object;


public scala.collection.generic.TraversableFactory scala$collection$generic$TraversableFactory$VirtualBuilderFactory$$$outer();
  Code:
   Stack=1, Locals=1, Args_size=1
   0:	aload_0
   1:	getfield	#17; //Field $outer:Lscala/collection/generic/TraversableFactory;
   4:	areturn
  LineNumberTable: 
   line 22: 0


public scala.collection.generic.Builder apply(scala.collection.Traversable);
  Code:
   Stack=1, Locals=2, Args_size=2
   0:	aload_1
   1:	invokeinterface	#52,  1; //InterfaceMethod scala/collection/generic/TraversableClass.genericBuilder:()Lscala/collection/generic/Builder;
   6:	areturn
  LineNumberTable: 
   line 23: 0

  LocalVariableTable: 
   Start  Length  Slot  Name   Signature
   0      7      0    this       Lscala/collection/generic/TraversableFactory$VirtualBuilderFactory;
   0      7      1    from       Lscala/collection/Traversable;

  Signature: length = 0x2
   00 36 

}

