Compiled from "TraversableFactory.scala"
public class scala.collection.generic.TraversableFactory$GenericCanBuildFrom extends java.lang.Object implements scala.collection.generic.CanBuildFrom,scala.ScalaObject
  SourceFile: "TraversableFactory.scala"
  Signature: length = 0x2
   00 35 
  Scala: length = 0x
   
  InnerClass: 
   public #56= #15 of #41; //GenericCanBuildFrom=class scala/collection/generic/TraversableFactory$GenericCanBuildFrom of class scala/collection/generic/TraversableFactory
  minor version: 0
  major version: 49
  Constant pool:
const #1 = Asciz	SourceFile;
const #2 = Asciz	TraversableFactory.scala;
const #3 = Asciz	$outer;
const #4 = Asciz	Lscala/collection/generic/TraversableFactory;;
const #5 = Asciz	<init>;
const #6 = Asciz	(Lscala/collection/generic/TraversableFactory;)V;
const #7 = Asciz	Code;
const #8 = Asciz	LineNumberTable;
const #9 = Asciz	java/lang/NullPointerException;
const #10 = class	#9;	//  java/lang/NullPointerException
const #11 = Asciz	()V;
const #12 = NameAndType	#5:#11;//  "<init>":()V
const #13 = Method	#10.#12;	//  java/lang/NullPointerException."<init>":()V
const #14 = Asciz	scala/collection/generic/TraversableFactory$GenericCanBuildFrom;
const #15 = class	#14;	//  scala/collection/generic/TraversableFactory$GenericCanBuildFrom
const #16 = NameAndType	#3:#4;//  $outer:Lscala/collection/generic/TraversableFactory;
const #17 = Field	#15.#16;	//  scala/collection/generic/TraversableFactory$GenericCanBuildFrom.$outer:Lscala/collection/generic/TraversableFactory;
const #18 = Asciz	java/lang/Object;
const #19 = class	#18;	//  java/lang/Object
const #20 = Method	#19.#12;	//  java/lang/Object."<init>":()V
const #21 = Asciz	this;
const #22 = Asciz	Lscala/collection/generic/TraversableFactory$GenericCanBuildFrom;;
const #23 = Asciz	LocalVariableTable;
const #24 = Asciz	(Lscala/collection/generic/TraversableFactory<TCC;>;)V;
const #25 = Asciz	Signature;
const #26 = Asciz	apply;
const #27 = Asciz	(Ljava/lang/Object;)Lscala/collection/mutable/Builder;;
const #28 = Asciz	scala/collection/Traversable;
const #29 = class	#28;	//  scala/collection/Traversable
const #30 = Asciz	(Lscala/collection/Traversable;)Lscala/collection/mutable/Builder;;
const #31 = NameAndType	#26:#30;//  apply:(Lscala/collection/Traversable;)Lscala/collection/mutable/Builder;
const #32 = Method	#15.#31;	//  scala/collection/generic/TraversableFactory$GenericCanBuildFrom.apply:(Lscala/collection/Traversable;)Lscala/collection/mutable/Builder;
const #33 = Asciz	from;
const #34 = Asciz	Ljava/lang/Object;;
const #35 = Asciz	scala$collection$generic$TraversableFactory$GenericCanBuildFrom$$$outer;
const #36 = Asciz	()Lscala/collection/generic/TraversableFactory;;
const #37 = Asciz	()Lscala/collection/mutable/Builder;;
const #38 = NameAndType	#35:#36;//  scala$collection$generic$TraversableFactory$GenericCanBuildFrom$$$outer:()Lscala/collection/generic/TraversableFactory;
const #39 = Method	#15.#38;	//  scala/collection/generic/TraversableFactory$GenericCanBuildFrom.scala$collection$generic$TraversableFactory$GenericCanBuildFrom$$$outer:()Lscala/collection/generic/TraversableFactory;
const #40 = Asciz	scala/collection/generic/TraversableFactory;
const #41 = class	#40;	//  scala/collection/generic/TraversableFactory
const #42 = Asciz	newBuilder;
const #43 = NameAndType	#42:#37;//  newBuilder:()Lscala/collection/mutable/Builder;
const #44 = Method	#41.#43;	//  scala/collection/generic/TraversableFactory.newBuilder:()Lscala/collection/mutable/Builder;
const #45 = Asciz	()Lscala/collection/mutable/Builder<TA;TCC;>;;
const #46 = Asciz	scala/collection/generic/GenericTraversableTemplate;
const #47 = class	#46;	//  scala/collection/generic/GenericTraversableTemplate
const #48 = Asciz	genericBuilder;
const #49 = NameAndType	#48:#37;//  genericBuilder:()Lscala/collection/mutable/Builder;
const #50 = InterfaceMethod	#47.#49;	//  scala/collection/generic/GenericTraversableTemplate.genericBuilder:()Lscala/collection/mutable/Builder;
const #51 = Asciz	Lscala/collection/Traversable;;
const #52 = Asciz	(TCC;)Lscala/collection/mutable/Builder<TA;TCC;>;;
const #53 = Asciz	<A:Ljava/lang/Object;>Ljava/lang/Object;Lscala/collection/generic/CanBuildFrom<TCC;TA;TCC;>;Lscala/ScalaObject;;
const #54 = Asciz	Scala;
const #55 = Asciz	InnerClasses;
const #56 = Asciz	GenericCanBuildFrom;
const #57 = Asciz	scala/collection/generic/CanBuildFrom;
const #58 = class	#57;	//  scala/collection/generic/CanBuildFrom
const #59 = Asciz	scala/ScalaObject;
const #60 = class	#59;	//  scala/ScalaObject

{
public final scala.collection.generic.TraversableFactory $outer;

public scala.collection.generic.TraversableFactory$GenericCanBuildFrom(scala.collection.generic.TraversableFactory);
  Code:
   Stack=2, Locals=2, Args_size=2
   0:	aload_1
   1:	ifnonnull	12
   4:	new	#10; //class java/lang/NullPointerException
   7:	dup
   8:	invokespecial	#13; //Method java/lang/NullPointerException."<init>":()V
   11:	athrow
   12:	aload_0
   13:	aload_1
   14:	putfield	#17; //Field $outer:Lscala/collection/generic/TraversableFactory;
   17:	aload_0
   18:	invokespecial	#20; //Method java/lang/Object."<init>":()V
   21:	return
  LineNumberTable: 
   line 45: 0

  LocalVariableTable: 
   Start  Length  Slot  Name   Signature
   0      22      0    this       Lscala/collection/generic/TraversableFactory$GenericCanBuildFrom;
   0      22      1    $outer       Lscala/collection/generic/TraversableFactory;

  Signature: length = 0x2
   00 18 

public scala.collection.mutable.Builder apply(java.lang.Object);
  Code:
   Stack=2, Locals=2, Args_size=2
   0:	aload_0
   1:	aload_1
   2:	checkcast	#29; //class scala/collection/Traversable
   5:	invokevirtual	#32; //Method apply:(Lscala/collection/Traversable;)Lscala/collection/mutable/Builder;
   8:	areturn
  LineNumberTable: 
   line 45: 0

  LocalVariableTable: 
   Start  Length  Slot  Name   Signature
   0      9      0    this       Lscala/collection/generic/TraversableFactory$GenericCanBuildFrom;
   0      9      1    from       Ljava/lang/Object;


public scala.collection.generic.TraversableFactory scala$collection$generic$TraversableFactory$GenericCanBuildFrom$$$outer();
  Code:
   Stack=1, Locals=1, Args_size=1
   0:	aload_0
   1:	getfield	#17; //Field $outer:Lscala/collection/generic/TraversableFactory;
   4:	areturn
  LineNumberTable: 
   line 45: 0


public scala.collection.mutable.Builder apply();
  Code:
   Stack=1, Locals=1, Args_size=1
   0:	aload_0
   1:	invokevirtual	#39; //Method scala$collection$generic$TraversableFactory$GenericCanBuildFrom$$$outer:()Lscala/collection/generic/TraversableFactory;
   4:	invokevirtual	#44; //Method scala/collection/generic/TraversableFactory.newBuilder:()Lscala/collection/mutable/Builder;
   7:	areturn
  LineNumberTable: 
   line 55: 0

  Signature: length = 0x2
   00 2D 

public scala.collection.mutable.Builder apply(scala.collection.Traversable);
  Code:
   Stack=1, Locals=2, Args_size=2
   0:	aload_1
   1:	invokeinterface	#50,  1; //InterfaceMethod scala/collection/generic/GenericTraversableTemplate.genericBuilder:()Lscala/collection/mutable/Builder;
   6:	areturn
  LineNumberTable: 
   line 50: 0

  LocalVariableTable: 
   Start  Length  Slot  Name   Signature
   0      7      0    this       Lscala/collection/generic/TraversableFactory$GenericCanBuildFrom;
   0      7      1    from       Lscala/collection/Traversable;

  Signature: length = 0x2
   00 34 

}

