Compiled from "TraversableTemplate.scala"
public abstract class scala.collection.generic.TraversableTemplate$class extends java.lang.Object
  SourceFile: "TraversableTemplate.scala"
  Scala: length = 0x
   
  InnerClass: 
   public final #651= #28 of #13; //$anon$1=class scala/collection/generic/TraversableTemplate$$anon$1 of class scala/collection/generic/TraversableTemplate
   public final #652= #418 of #13; //$anonfun$1=class scala/collection/generic/TraversableTemplate$$anonfun$1 of class scala/collection/generic/TraversableTemplate
   public final #653= #621 of #13; //$anonfun$map$1=class scala/collection/generic/TraversableTemplate$$anonfun$map$1 of class scala/collection/generic/TraversableTemplate
   public final #654= #381 of #13; //$anonfun$init$1=class scala/collection/generic/TraversableTemplate$$anonfun$init$1 of class scala/collection/generic/TraversableTemplate
   public final #655= #305 of #13; //$anonfun$span$1=class scala/collection/generic/TraversableTemplate$$anonfun$span$1 of class scala/collection/generic/TraversableTemplate
   public final #656= #501 of #13; //$anonfun$find$1=class scala/collection/generic/TraversableTemplate$$anonfun$find$1 of class scala/collection/generic/TraversableTemplate
   public final #657= #345 of #13; //$anonfun$drop$1=class scala/collection/generic/TraversableTemplate$$anonfun$drop$1 of class scala/collection/generic/TraversableTemplate
   public final #658= #637 of #13; //$anonfun$size$1=class scala/collection/generic/TraversableTemplate$$anonfun$size$1 of class scala/collection/generic/TraversableTemplate
   public final #659= #403 of #13; //$anonfun$last$1=class scala/collection/generic/TraversableTemplate$$anonfun$last$1 of class scala/collection/generic/TraversableTemplate
   public final #660= #421 of #13; //$anonfun$head$1=class scala/collection/generic/TraversableTemplate$$anonfun$head$1 of class scala/collection/generic/TraversableTemplate
   public final #661= #354 of #13; //$anonfun$take$1=class scala/collection/generic/TraversableTemplate$$anonfun$take$1 of class scala/collection/generic/TraversableTemplate
   public final #662= #334 of #13; //$anonfun$slice$1=class scala/collection/generic/TraversableTemplate$$anonfun$slice$1 of class scala/collection/generic/TraversableTemplate
   public final #663= #512 of #13; //$anonfun$count$1=class scala/collection/generic/TraversableTemplate$$anonfun$count$1 of class scala/collection/generic/TraversableTemplate
   public final #664= #523 of #13; //$anonfun$exists$1=class scala/collection/generic/TraversableTemplate$$anonfun$exists$1 of class scala/collection/generic/TraversableTemplate
   public final #665= #534 of #13; //$anonfun$forall$1=class scala/collection/generic/TraversableTemplate$$anonfun$forall$1 of class scala/collection/generic/TraversableTemplate
   public final #666= #608 of #13; //$anonfun$filter$1=class scala/collection/generic/TraversableTemplate$$anonfun$filter$1 of class scala/collection/generic/TraversableTemplate
   public final #667= #615 of #13; //$anonfun$flatMap$1=class scala/collection/generic/TraversableTemplate$$anonfun$flatMap$1 of class scala/collection/generic/TraversableTemplate
   public final #668= #551 of #13; //$anonfun$groupBy$1=class scala/collection/generic/TraversableTemplate$$anonfun$groupBy$1 of class scala/collection/generic/TraversableTemplate
   public final #669= #284 of #13; //$anonfun$splitAt$1=class scala/collection/generic/TraversableTemplate$$anonfun$splitAt$1 of class scala/collection/generic/TraversableTemplate
   public final #670= #554 of #13; //$anonfun$groupBy$2=class scala/collection/generic/TraversableTemplate$$anonfun$groupBy$2 of class scala/collection/generic/TraversableTemplate
   public final #671= #644 of #13; //$anonfun$isEmpty$1=class scala/collection/generic/TraversableTemplate$$anonfun$isEmpty$1 of class scala/collection/generic/TraversableTemplate
   public final #672= #492 of #13; //$anonfun$foldLeft$1=class scala/collection/generic/TraversableTemplate$$anonfun$foldLeft$1 of class scala/collection/generic/TraversableTemplate
   public final #673= #482 of #13; //$anonfun$foldRight$2=class scala/collection/generic/TraversableTemplate$$anonfun$foldRight$2 of class scala/collection/generic/TraversableTemplate
   public final #674= #568 of #13; //$anonfun$partition$1=class scala/collection/generic/TraversableTemplate$$anonfun$partition$1 of class scala/collection/generic/TraversableTemplate
   public final #675= #326 of #13; //$anonfun$takeWhile$1=class scala/collection/generic/TraversableTemplate$$anonfun$takeWhile$1 of class scala/collection/generic/TraversableTemplate
   public final #676= #598 of #13; //$anonfun$filterMap$1=class scala/collection/generic/TraversableTemplate$$anonfun$filterMap$1 of class scala/collection/generic/TraversableTemplate
   public final #677= #120 of #13; //$anonfun$addString$1=class scala/collection/generic/TraversableTemplate$$anonfun$addString$1 of class scala/collection/generic/TraversableTemplate
   public final #678= #582 of #13; //$anonfun$filterNot$1=class scala/collection/generic/TraversableTemplate$$anonfun$filterNot$1 of class scala/collection/generic/TraversableTemplate
   public final #679= #317 of #13; //$anonfun$dropWhile$1=class scala/collection/generic/TraversableTemplate$$anonfun$dropWhile$1 of class scala/collection/generic/TraversableTemplate
   public final #680= #479 of #13; //$anonfun$foldRight$1=class scala/collection/generic/TraversableTemplate$$anonfun$foldRight$1 of class scala/collection/generic/TraversableTemplate
   public final #681= #464 of #13; //$anonfun$reduceLeft$1=class scala/collection/generic/TraversableTemplate$$anonfun$reduceLeft$1 of class scala/collection/generic/TraversableTemplate
   public final #682= #445 of #13; //$anonfun$reduceRight$1=class scala/collection/generic/TraversableTemplate$$anonfun$reduceRight$1 of class scala/collection/generic/TraversableTemplate
   public final #683= #448 of #13; //$anonfun$reduceRight$2=class scala/collection/generic/TraversableTemplate$$anonfun$reduceRight$2 of class scala/collection/generic/TraversableTemplate
   public final #684= #254 of #13; //$anonfun$copyToArray$1=class scala/collection/generic/TraversableTemplate$$anonfun$copyToArray$1 of class scala/collection/generic/TraversableTemplate
   public final #685= #272 of #13; //$anonfun$copyToBuffer$1=class scala/collection/generic/TraversableTemplate$$anonfun$copyToBuffer$1 of class scala/collection/generic/TraversableTemplate
  minor version: 0
  major version: 49
  Constant pool:
const #1 = Asciz	SourceFile;
const #2 = Asciz	TraversableTemplate.scala;
const #3 = Asciz	$init$;
const #4 = Asciz	(Lscala/collection/generic/TraversableTemplate;)V;
const #5 = Asciz	Code;
const #6 = Asciz	LineNumberTable;
const #7 = Asciz	$this;
const #8 = Asciz	Lscala/collection/generic/TraversableTemplate;;
const #9 = Asciz	LocalVariableTable;
const #10 = Asciz	view;
const #11 = Asciz	(Lscala/collection/generic/TraversableTemplate;II)Lscala/collection/generic/TraversableView;;
const #12 = Asciz	scala/collection/generic/TraversableTemplate;
const #13 = class	#12;	//  scala/collection/generic/TraversableTemplate
const #14 = Asciz	()Ljava/lang/Object;;
const #15 = NameAndType	#10:#14;//  view:()Ljava/lang/Object;
const #16 = InterfaceMethod	#13.#15;	//  scala/collection/generic/TraversableTemplate.view:()Ljava/lang/Object;
const #17 = Asciz	scala/collection/generic/TraversableViewTemplate;
const #18 = class	#17;	//  scala/collection/generic/TraversableViewTemplate
const #19 = Asciz	slice;
const #20 = Asciz	(II)Lscala/collection/generic/TraversableView;;
const #21 = NameAndType	#19:#20;//  slice:(II)Lscala/collection/generic/TraversableView;
const #22 = InterfaceMethod	#18.#21;	//  scala/collection/generic/TraversableViewTemplate.slice:(II)Lscala/collection/generic/TraversableView;
const #23 = Asciz	from;
const #24 = Asciz	I;
const #25 = Asciz	until;
const #26 = Asciz	(Lscala/collection/generic/TraversableTemplate;)Ljava/lang/Object;;
const #27 = Asciz	scala/collection/generic/TraversableTemplate$$anon$1;
const #28 = class	#27;	//  scala/collection/generic/TraversableTemplate$$anon$1
const #29 = Asciz	<init>;
const #30 = NameAndType	#29:#4;//  "<init>":(Lscala/collection/generic/TraversableTemplate;)V
const #31 = Method	#28.#30;	//  scala/collection/generic/TraversableTemplate$$anon$1."<init>":(Lscala/collection/generic/TraversableTemplate;)V
const #32 = Asciz	stringPrefix;
const #33 = Asciz	(Lscala/collection/generic/TraversableTemplate;)Ljava/lang/String;;
const #34 = Asciz	thisCollection;
const #35 = Asciz	()Lscala/collection/generic/TraversableTemplate;;
const #36 = NameAndType	#34:#35;//  thisCollection:()Lscala/collection/generic/TraversableTemplate;
const #37 = InterfaceMethod	#13.#36;	//  scala/collection/generic/TraversableTemplate.thisCollection:()Lscala/collection/generic/TraversableTemplate;
const #38 = Asciz	java/lang/Object;
const #39 = class	#38;	//  java/lang/Object
const #40 = Asciz	getClass;
const #41 = Asciz	()Ljava/lang/Class;;
const #42 = NameAndType	#40:#41;//  getClass:()Ljava/lang/Class;
const #43 = Method	#39.#42;	//  java/lang/Object.getClass:()Ljava/lang/Class;
const #44 = Asciz	java/lang/Class;
const #45 = class	#44;	//  java/lang/Class
const #46 = Asciz	getName;
const #47 = Asciz	()Ljava/lang/String;;
const #48 = NameAndType	#46:#47;//  getName:()Ljava/lang/String;
const #49 = Method	#45.#48;	//  java/lang/Class.getName:()Ljava/lang/String;
const #50 = int	46;
const #51 = Asciz	java/lang/String;
const #52 = class	#51;	//  java/lang/String
const #53 = Asciz	lastIndexOf;
const #54 = Asciz	(I)I;
const #55 = NameAndType	#53:#54;//  lastIndexOf:(I)I
const #56 = Method	#52.#55;	//  java/lang/String.lastIndexOf:(I)I
const #57 = Asciz	substring;
const #58 = Asciz	(I)Ljava/lang/String;;
const #59 = NameAndType	#57:#58;//  substring:(I)Ljava/lang/String;
const #60 = Method	#52.#59;	//  java/lang/String.substring:(I)Ljava/lang/String;
const #61 = int	36;
const #62 = Asciz	indexOf;
const #63 = NameAndType	#62:#54;//  indexOf:(I)I
const #64 = Method	#52.#63;	//  java/lang/String.indexOf:(I)I
const #65 = Asciz	(II)Ljava/lang/String;;
const #66 = NameAndType	#57:#65;//  substring:(II)Ljava/lang/String;
const #67 = Method	#52.#66;	//  java/lang/String.substring:(II)Ljava/lang/String;
const #68 = Asciz	string;
const #69 = Asciz	Ljava/lang/String;;
const #70 = Asciz	idx1;
const #71 = Asciz	idx2;
const #72 = Asciz	toString;
const #73 = Asciz	scala/collection/mutable/StringBuilder;
const #74 = class	#73;	//  scala/collection/mutable/StringBuilder
const #75 = Asciz	()V;
const #76 = NameAndType	#29:#75;//  "<init>":()V
const #77 = Method	#74.#76;	//  scala/collection/mutable/StringBuilder."<init>":()V
const #78 = NameAndType	#32:#47;//  stringPrefix:()Ljava/lang/String;
const #79 = InterfaceMethod	#13.#78;	//  scala/collection/generic/TraversableTemplate.stringPrefix:()Ljava/lang/String;
const #80 = Asciz	append;
const #81 = Asciz	(Ljava/lang/Object;)Lscala/collection/mutable/StringBuilder;;
const #82 = NameAndType	#80:#81;//  append:(Ljava/lang/Object;)Lscala/collection/mutable/StringBuilder;
const #83 = Method	#74.#82;	//  scala/collection/mutable/StringBuilder.append:(Ljava/lang/Object;)Lscala/collection/mutable/StringBuilder;
const #84 = Asciz	(;
const #85 = String	#84;	//  (
const #86 = NameAndType	#72:#47;//  toString:()Ljava/lang/String;
const #87 = Method	#74.#86;	//  scala/collection/mutable/StringBuilder.toString:()Ljava/lang/String;
const #88 = Asciz	, ;
const #89 = String	#88;	//  , 
const #90 = Asciz	);
const #91 = String	#90;	//  )
const #92 = Asciz	mkString;
const #93 = Asciz	(Ljava/lang/String;Ljava/lang/String;Ljava/lang/String;)Ljava/lang/String;;
const #94 = NameAndType	#92:#93;//  mkString:(Ljava/lang/String;Ljava/lang/String;Ljava/lang/String;)Ljava/lang/String;
const #95 = InterfaceMethod	#13.#94;	//  scala/collection/generic/TraversableTemplate.mkString:(Ljava/lang/String;Ljava/lang/String;Ljava/lang/String;)Ljava/lang/String;
const #96 = Asciz	addString;
const #97 = Asciz	(Lscala/collection/generic/TraversableTemplate;Lscala/collection/mutable/StringBuilder;)Lscala/collection/mutable/StringBuilder;;
const #98 = Asciz	;
const #99 = String	#98;	//  
const #100 = Asciz	(Lscala/collection/mutable/StringBuilder;Ljava/lang/String;)Lscala/collection/mutable/StringBuilder;;
const #101 = NameAndType	#96:#100;//  addString:(Lscala/collection/mutable/StringBuilder;Ljava/lang/String;)Lscala/collection/mutable/StringBuilder;
const #102 = InterfaceMethod	#13.#101;	//  scala/collection/generic/TraversableTemplate.addString:(Lscala/collection/mutable/StringBuilder;Ljava/lang/String;)Lscala/collection/mutable/StringBuilder;
const #103 = Asciz	b;
const #104 = Asciz	Lscala/collection/mutable/StringBuilder;;
const #105 = Asciz	(Lscala/collection/generic/TraversableTemplate;Lscala/collection/mutable/StringBuilder;Ljava/lang/String;)Lscala/collection/mutable/StringBuilder;;
const #106 = Asciz	(Lscala/collection/mutable/StringBuilder;Ljava/lang/String;Ljava/lang/String;Ljava/lang/String;)Lscala/collection/mutable/StringBuilder;;
const #107 = NameAndType	#96:#106;//  addString:(Lscala/collection/mutable/StringBuilder;Ljava/lang/String;Ljava/lang/String;Ljava/lang/String;)Lscala/collection/mutable/StringBuilder;
const #108 = InterfaceMethod	#13.#107;	//  scala/collection/generic/TraversableTemplate.addString:(Lscala/collection/mutable/StringBuilder;Ljava/lang/String;Ljava/lang/String;Ljava/lang/String;)Lscala/collection/mutable/StringBuilder;
const #109 = Asciz	sep;
const #110 = Asciz	(Lscala/collection/generic/TraversableTemplate;Lscala/collection/mutable/StringBuilder;Ljava/lang/String;Ljava/lang/String;Ljava/lang/String;)Lscala/collection/mutable/StringBuilder;;
const #111 = Asciz	(Ljava/lang/String;)Lscala/collection/mutable/StringBuilder;;
const #112 = NameAndType	#80:#111;//  append:(Ljava/lang/String;)Lscala/collection/mutable/StringBuilder;
const #113 = Method	#74.#112;	//  scala/collection/mutable/StringBuilder.append:(Ljava/lang/String;)Lscala/collection/mutable/StringBuilder;
const #114 = Asciz	scala/runtime/BooleanRef;
const #115 = class	#114;	//  scala/runtime/BooleanRef
const #116 = Asciz	(Z)V;
const #117 = NameAndType	#29:#116;//  "<init>":(Z)V
const #118 = Method	#115.#117;	//  scala/runtime/BooleanRef."<init>":(Z)V
const #119 = Asciz	scala/collection/generic/TraversableTemplate$$anonfun$addString$1;
const #120 = class	#119;	//  scala/collection/generic/TraversableTemplate$$anonfun$addString$1
const #121 = Asciz	(Lscala/collection/generic/TraversableTemplate;Lscala/collection/mutable/StringBuilder;Ljava/lang/String;Lscala/runtime/BooleanRef;)V;
const #122 = NameAndType	#29:#121;//  "<init>":(Lscala/collection/generic/TraversableTemplate;Lscala/collection/mutable/StringBuilder;Ljava/lang/String;Lscala/runtime/BooleanRef;)V
const #123 = Method	#120.#122;	//  scala/collection/generic/TraversableTemplate$$anonfun$addString$1."<init>":(Lscala/collection/generic/TraversableTemplate;Lscala/collection/mutable/StringBuilder;Ljava/lang/String;Lscala/runtime/BooleanRef;)V
const #124 = Asciz	foreach;
const #125 = Asciz	(Lscala/Function1;)V;
const #126 = NameAndType	#124:#125;//  foreach:(Lscala/Function1;)V
const #127 = InterfaceMethod	#13.#126;	//  scala/collection/generic/TraversableTemplate.foreach:(Lscala/Function1;)V
const #128 = Asciz	b$1;
const #129 = Asciz	start;
const #130 = Asciz	sep$1;
const #131 = Asciz	end;
const #132 = Asciz	first$2;
const #133 = Asciz	Lscala/runtime/BooleanRef;;
const #134 = Method	#74.#76;	//  scala/collection/mutable/StringBuilder."<init>":()V
const #135 = Asciz	(Lscala/collection/mutable/StringBuilder;)Lscala/collection/mutable/StringBuilder;;
const #136 = NameAndType	#96:#135;//  addString:(Lscala/collection/mutable/StringBuilder;)Lscala/collection/mutable/StringBuilder;
const #137 = InterfaceMethod	#13.#136;	//  scala/collection/generic/TraversableTemplate.addString:(Lscala/collection/mutable/StringBuilder;)Lscala/collection/mutable/StringBuilder;
const #138 = Method	#74.#86;	//  scala/collection/mutable/StringBuilder.toString:()Ljava/lang/String;
const #139 = Asciz	(Lscala/collection/generic/TraversableTemplate;Ljava/lang/String;)Ljava/lang/String;;
const #140 = Asciz	(Lscala/collection/generic/TraversableTemplate;Ljava/lang/String;Ljava/lang/String;Ljava/lang/String;)Ljava/lang/String;;
const #141 = Asciz	toSet;
const #142 = Asciz	(Lscala/collection/generic/TraversableTemplate;)Lscala/collection/immutable/Set;;
const #143 = Asciz	scala/collection/immutable/Set$;
const #144 = class	#143;	//  scala/collection/immutable/Set$
const #145 = Asciz	MODULE$;
const #146 = Asciz	Lscala/collection/immutable/Set$;;
const #147 = NameAndType	#145:#146;//  MODULE$:Lscala/collection/immutable/Set$;
const #148 = Field	#144.#147;	//  scala/collection/immutable/Set$.MODULE$:Lscala/collection/immutable/Set$;
const #149 = Asciz	scala/runtime/ScalaRunTime$;
const #150 = class	#149;	//  scala/runtime/ScalaRunTime$
const #151 = Asciz	Lscala/runtime/ScalaRunTime$;;
const #152 = NameAndType	#145:#151;//  MODULE$:Lscala/runtime/ScalaRunTime$;
const #153 = Field	#150.#152;	//  scala/runtime/ScalaRunTime$.MODULE$:Lscala/runtime/ScalaRunTime$;
const #154 = Asciz	boxArray;
const #155 = Asciz	(Ljava/lang/Object;)Lscala/runtime/BoxedArray;;
const #156 = NameAndType	#154:#155;//  boxArray:(Ljava/lang/Object;)Lscala/runtime/BoxedArray;
const #157 = Method	#150.#156;	//  scala/runtime/ScalaRunTime$.boxArray:(Ljava/lang/Object;)Lscala/runtime/BoxedArray;
const #158 = Asciz	apply;
const #159 = Asciz	(Lscala/collection/Sequence;)Lscala/collection/Traversable;;
const #160 = NameAndType	#158:#159;//  apply:(Lscala/collection/Sequence;)Lscala/collection/Traversable;
const #161 = Method	#144.#160;	//  scala/collection/immutable/Set$.apply:(Lscala/collection/Sequence;)Lscala/collection/Traversable;
const #162 = Asciz	scala/collection/generic/Addable;
const #163 = class	#162;	//  scala/collection/generic/Addable
const #164 = Asciz	scala/collection/Traversable;
const #165 = class	#164;	//  scala/collection/Traversable
const #166 = Asciz	$plus$plus;
const #167 = Asciz	(Lscala/collection/Traversable;)Lscala/collection/generic/Addable;;
const #168 = NameAndType	#166:#167;//  $plus$plus:(Lscala/collection/Traversable;)Lscala/collection/generic/Addable;
const #169 = InterfaceMethod	#163.#168;	//  scala/collection/generic/Addable.$plus$plus:(Lscala/collection/Traversable;)Lscala/collection/generic/Addable;
const #170 = Asciz	scala/collection/immutable/Set;
const #171 = class	#170;	//  scala/collection/immutable/Set
const #172 = Asciz	toStream;
const #173 = Asciz	(Lscala/collection/generic/TraversableTemplate;)Lscala/collection/immutable/Stream;;
const #174 = Asciz	toList;
const #175 = Asciz	()Lscala/collection/immutable/List;;
const #176 = NameAndType	#174:#175;//  toList:()Lscala/collection/immutable/List;
const #177 = InterfaceMethod	#13.#176;	//  scala/collection/generic/TraversableTemplate.toList:()Lscala/collection/immutable/List;
const #178 = Asciz	scala/collection/immutable/List;
const #179 = class	#178;	//  scala/collection/immutable/List
const #180 = Asciz	()Lscala/collection/immutable/Stream;;
const #181 = NameAndType	#172:#180;//  toStream:()Lscala/collection/immutable/Stream;
const #182 = Method	#179.#181;	//  scala/collection/immutable/List.toStream:()Lscala/collection/immutable/Stream;
const #183 = Asciz	toSequence;
const #184 = Asciz	(Lscala/collection/generic/TraversableTemplate;)Lscala/collection/Sequence;;
const #185 = Asciz	toIterable;
const #186 = Asciz	(Lscala/collection/generic/TraversableTemplate;)Lscala/collection/Iterable;;
const #187 = InterfaceMethod	#13.#181;	//  scala/collection/generic/TraversableTemplate.toStream:()Lscala/collection/immutable/Stream;
const #188 = Asciz	(Lscala/collection/generic/TraversableTemplate;)Lscala/collection/immutable/List;;
const #189 = Asciz	scala/collection/mutable/ListBuffer;
const #190 = class	#189;	//  scala/collection/mutable/ListBuffer
const #191 = Method	#190.#76;	//  scala/collection/mutable/ListBuffer."<init>":()V
const #192 = Asciz	scala/collection/generic/Growable;
const #193 = class	#192;	//  scala/collection/generic/Growable
const #194 = Asciz	$plus$plus$eq;
const #195 = Asciz	(Lscala/collection/Traversable;)Lscala/collection/generic/Growable;;
const #196 = NameAndType	#194:#195;//  $plus$plus$eq:(Lscala/collection/Traversable;)Lscala/collection/generic/Growable;
const #197 = InterfaceMethod	#193.#196;	//  scala/collection/generic/Growable.$plus$plus$eq:(Lscala/collection/Traversable;)Lscala/collection/generic/Growable;
const #198 = Method	#190.#176;	//  scala/collection/mutable/ListBuffer.toList:()Lscala/collection/immutable/List;
const #199 = Asciz	toArray;
const #200 = Asciz	(Lscala/collection/generic/TraversableTemplate;)Lscala/runtime/BoxedArray;;
const #201 = Asciz	scala/runtime/BoxedAnyArray;
const #202 = class	#201;	//  scala/runtime/BoxedAnyArray
const #203 = Asciz	size;
const #204 = Asciz	()I;
const #205 = NameAndType	#203:#204;//  size:()I
const #206 = InterfaceMethod	#13.#205;	//  scala/collection/generic/TraversableTemplate.size:()I
const #207 = Asciz	(I)V;
const #208 = NameAndType	#29:#207;//  "<init>":(I)V
const #209 = Method	#202.#208;	//  scala/runtime/BoxedAnyArray."<init>":(I)V
const #210 = Asciz	copyToArray;
const #211 = Asciz	(Lscala/runtime/BoxedArray;I)V;
const #212 = NameAndType	#210:#211;//  copyToArray:(Lscala/runtime/BoxedArray;I)V
const #213 = InterfaceMethod	#13.#212;	//  scala/collection/generic/TraversableTemplate.copyToArray:(Lscala/runtime/BoxedArray;I)V
const #214 = Asciz	result;
const #215 = Asciz	Lscala/runtime/BoxedArray;;
const #216 = Asciz	(Lscala/collection/generic/TraversableTemplate;Lscala/runtime/BoxedArray;I)V;
const #217 = Asciz	scala/runtime/BoxedArray;
const #218 = class	#217;	//  scala/runtime/BoxedArray
const #219 = Asciz	length;
const #220 = NameAndType	#219:#204;//  length:()I
const #221 = Method	#218.#220;	//  scala/runtime/BoxedArray.length:()I
const #222 = Asciz	(Lscala/runtime/BoxedArray;II)V;
const #223 = NameAndType	#210:#222;//  copyToArray:(Lscala/runtime/BoxedArray;II)V
const #224 = InterfaceMethod	#13.#223;	//  scala/collection/generic/TraversableTemplate.copyToArray:(Lscala/runtime/BoxedArray;II)V
const #225 = Asciz	xs;
const #226 = Asciz	(Lscala/collection/generic/TraversableTemplate;Lscala/runtime/BoxedArray;II)V;
const #227 = Asciz	scala/runtime/IntRef;
const #228 = class	#227;	//  scala/runtime/IntRef
const #229 = Method	#228.#208;	//  scala/runtime/IntRef."<init>":(I)V
const #230 = Asciz	scala/Predef$;
const #231 = class	#230;	//  scala/Predef$
const #232 = Asciz	Lscala/Predef$;;
const #233 = NameAndType	#145:#232;//  MODULE$:Lscala/Predef$;
const #234 = Field	#231.#233;	//  scala/Predef$.MODULE$:Lscala/Predef$;
const #235 = Asciz	intWrapper;
const #236 = Asciz	(I)Lscala/runtime/RichInt;;
const #237 = NameAndType	#235:#236;//  intWrapper:(I)Lscala/runtime/RichInt;
const #238 = Method	#231.#237;	//  scala/Predef$.intWrapper:(I)Lscala/runtime/RichInt;
const #239 = Asciz	scala/runtime/RichInt;
const #240 = class	#239;	//  scala/runtime/RichInt
const #241 = Asciz	min;
const #242 = NameAndType	#241:#54;//  min:(I)I
const #243 = Method	#240.#242;	//  scala/runtime/RichInt.min:(I)I
const #244 = Asciz	scala/collection/Traversable$;
const #245 = class	#244;	//  scala/collection/Traversable$
const #246 = Asciz	Lscala/collection/Traversable$;;
const #247 = NameAndType	#145:#246;//  MODULE$:Lscala/collection/Traversable$;
const #248 = Field	#245.#247;	//  scala/collection/Traversable$.MODULE$:Lscala/collection/Traversable$;
const #249 = Asciz	breaks;
const #250 = Asciz	()Lscala/util/control/Breaks;;
const #251 = NameAndType	#249:#250;//  breaks:()Lscala/util/control/Breaks;
const #252 = Method	#245.#251;	//  scala/collection/Traversable$.breaks:()Lscala/util/control/Breaks;
const #253 = Asciz	scala/collection/generic/TraversableTemplate$$anonfun$copyToArray$1;
const #254 = class	#253;	//  scala/collection/generic/TraversableTemplate$$anonfun$copyToArray$1
const #255 = Asciz	(Lscala/collection/generic/TraversableTemplate;Lscala/runtime/BoxedArray;Lscala/runtime/IntRef;I)V;
const #256 = NameAndType	#29:#255;//  "<init>":(Lscala/collection/generic/TraversableTemplate;Lscala/runtime/BoxedArray;Lscala/runtime/IntRef;I)V
const #257 = Method	#254.#256;	//  scala/collection/generic/TraversableTemplate$$anonfun$copyToArray$1."<init>":(Lscala/collection/generic/TraversableTemplate;Lscala/runtime/BoxedArray;Lscala/runtime/IntRef;I)V
const #258 = Asciz	scala/util/control/Breaks;
const #259 = class	#258;	//  scala/util/control/Breaks
const #260 = Asciz	breakable;
const #261 = Asciz	(Lscala/Function0;)V;
const #262 = NameAndType	#260:#261;//  breakable:(Lscala/Function0;)V
const #263 = Method	#259.#262;	//  scala/util/control/Breaks.breakable:(Lscala/Function0;)V
const #264 = Asciz	xs$1;
const #265 = Asciz	len;
const #266 = Asciz	i$5;
const #267 = Asciz	Lscala/runtime/IntRef;;
const #268 = Asciz	end$1;
const #269 = Asciz	copyToBuffer;
const #270 = Asciz	(Lscala/collection/generic/TraversableTemplate;Lscala/collection/mutable/Buffer;)V;
const #271 = Asciz	scala/collection/generic/TraversableTemplate$$anonfun$copyToBuffer$1;
const #272 = class	#271;	//  scala/collection/generic/TraversableTemplate$$anonfun$copyToBuffer$1
const #273 = NameAndType	#29:#270;//  "<init>":(Lscala/collection/generic/TraversableTemplate;Lscala/collection/mutable/Buffer;)V
const #274 = Method	#272.#273;	//  scala/collection/generic/TraversableTemplate$$anonfun$copyToBuffer$1."<init>":(Lscala/collection/generic/TraversableTemplate;Lscala/collection/mutable/Buffer;)V
const #275 = Asciz	dest$1;
const #276 = Asciz	Lscala/collection/mutable/Buffer;;
const #277 = Asciz	splitAt;
const #278 = Asciz	(Lscala/collection/generic/TraversableTemplate;I)Lscala/Tuple2;;
const #279 = Asciz	newBuilder;
const #280 = Asciz	()Lscala/collection/generic/Builder;;
const #281 = NameAndType	#279:#280;//  newBuilder:()Lscala/collection/generic/Builder;
const #282 = InterfaceMethod	#13.#281;	//  scala/collection/generic/TraversableTemplate.newBuilder:()Lscala/collection/generic/Builder;
const #283 = Asciz	scala/collection/generic/TraversableTemplate$$anonfun$splitAt$1;
const #284 = class	#283;	//  scala/collection/generic/TraversableTemplate$$anonfun$splitAt$1
const #285 = Asciz	(Lscala/collection/generic/TraversableTemplate;ILscala/collection/generic/Builder;Lscala/collection/generic/Builder;Lscala/runtime/IntRef;)V;
const #286 = NameAndType	#29:#285;//  "<init>":(Lscala/collection/generic/TraversableTemplate;ILscala/collection/generic/Builder;Lscala/collection/generic/Builder;Lscala/runtime/IntRef;)V
const #287 = Method	#284.#286;	//  scala/collection/generic/TraversableTemplate$$anonfun$splitAt$1."<init>":(Lscala/collection/generic/TraversableTemplate;ILscala/collection/generic/Builder;Lscala/collection/generic/Builder;Lscala/runtime/IntRef;)V
const #288 = Asciz	scala/Tuple2;
const #289 = class	#288;	//  scala/Tuple2
const #290 = Asciz	scala/collection/generic/Builder;
const #291 = class	#290;	//  scala/collection/generic/Builder
const #292 = NameAndType	#214:#14;//  result:()Ljava/lang/Object;
const #293 = InterfaceMethod	#291.#292;	//  scala/collection/generic/Builder.result:()Ljava/lang/Object;
const #294 = Asciz	(Ljava/lang/Object;Ljava/lang/Object;)V;
const #295 = NameAndType	#29:#294;//  "<init>":(Ljava/lang/Object;Ljava/lang/Object;)V
const #296 = Method	#289.#295;	//  scala/Tuple2."<init>":(Ljava/lang/Object;Ljava/lang/Object;)V
const #297 = Asciz	n$3;
const #298 = Asciz	l$3;
const #299 = Asciz	Lscala/collection/generic/Builder;;
const #300 = Asciz	r$3;
const #301 = Asciz	i$4;
const #302 = Asciz	span;
const #303 = Asciz	(Lscala/collection/generic/TraversableTemplate;Lscala/Function1;)Lscala/Tuple2;;
const #304 = Asciz	scala/collection/generic/TraversableTemplate$$anonfun$span$1;
const #305 = class	#304;	//  scala/collection/generic/TraversableTemplate$$anonfun$span$1
const #306 = Asciz	(Lscala/collection/generic/TraversableTemplate;Lscala/Function1;Lscala/collection/generic/Builder;Lscala/collection/generic/Builder;Lscala/runtime/BooleanRef;)V;
const #307 = NameAndType	#29:#306;//  "<init>":(Lscala/collection/generic/TraversableTemplate;Lscala/Function1;Lscala/collection/generic/Builder;Lscala/collection/generic/Builder;Lscala/runtime/BooleanRef;)V
const #308 = Method	#305.#307;	//  scala/collection/generic/TraversableTemplate$$anonfun$span$1."<init>":(Lscala/collection/generic/TraversableTemplate;Lscala/Function1;Lscala/collection/generic/Builder;Lscala/collection/generic/Builder;Lscala/runtime/BooleanRef;)V
const #309 = Asciz	p$3;
const #310 = Asciz	Lscala/Function1;;
const #311 = Asciz	l$2;
const #312 = Asciz	r$2;
const #313 = Asciz	toLeft$1;
const #314 = Asciz	dropWhile;
const #315 = Asciz	(Lscala/collection/generic/TraversableTemplate;Lscala/Function1;)Lscala/collection/generic/TraversableTemplate;;
const #316 = Asciz	scala/collection/generic/TraversableTemplate$$anonfun$dropWhile$1;
const #317 = class	#316;	//  scala/collection/generic/TraversableTemplate$$anonfun$dropWhile$1
const #318 = Asciz	(Lscala/collection/generic/TraversableTemplate;Lscala/Function1;Lscala/collection/generic/Builder;Lscala/runtime/BooleanRef;)V;
const #319 = NameAndType	#29:#318;//  "<init>":(Lscala/collection/generic/TraversableTemplate;Lscala/Function1;Lscala/collection/generic/Builder;Lscala/runtime/BooleanRef;)V
const #320 = Method	#317.#319;	//  scala/collection/generic/TraversableTemplate$$anonfun$dropWhile$1."<init>":(Lscala/collection/generic/TraversableTemplate;Lscala/Function1;Lscala/collection/generic/Builder;Lscala/runtime/BooleanRef;)V
const #321 = Asciz	p$2;
const #322 = Asciz	b$11;
const #323 = Asciz	go$1;
const #324 = Asciz	takeWhile;
const #325 = Asciz	scala/collection/generic/TraversableTemplate$$anonfun$takeWhile$1;
const #326 = class	#325;	//  scala/collection/generic/TraversableTemplate$$anonfun$takeWhile$1
const #327 = Asciz	(Lscala/collection/generic/TraversableTemplate;Lscala/Function1;Lscala/collection/generic/Builder;)V;
const #328 = NameAndType	#29:#327;//  "<init>":(Lscala/collection/generic/TraversableTemplate;Lscala/Function1;Lscala/collection/generic/Builder;)V
const #329 = Method	#326.#328;	//  scala/collection/generic/TraversableTemplate$$anonfun$takeWhile$1."<init>":(Lscala/collection/generic/TraversableTemplate;Lscala/Function1;Lscala/collection/generic/Builder;)V
const #330 = Asciz	p$1;
const #331 = Asciz	b$10;
const #332 = Asciz	(Lscala/collection/generic/TraversableTemplate;II)Lscala/collection/generic/TraversableTemplate;;
const #333 = Asciz	scala/collection/generic/TraversableTemplate$$anonfun$slice$1;
const #334 = class	#333;	//  scala/collection/generic/TraversableTemplate$$anonfun$slice$1
const #335 = Asciz	(Lscala/collection/generic/TraversableTemplate;IILscala/collection/generic/Builder;Lscala/runtime/IntRef;)V;
const #336 = NameAndType	#29:#335;//  "<init>":(Lscala/collection/generic/TraversableTemplate;IILscala/collection/generic/Builder;Lscala/runtime/IntRef;)V
const #337 = Method	#334.#336;	//  scala/collection/generic/TraversableTemplate$$anonfun$slice$1."<init>":(Lscala/collection/generic/TraversableTemplate;IILscala/collection/generic/Builder;Lscala/runtime/IntRef;)V
const #338 = Asciz	from$1;
const #339 = Asciz	until$1;
const #340 = Asciz	b$9;
const #341 = Asciz	i$3;
const #342 = Asciz	drop;
const #343 = Asciz	(Lscala/collection/generic/TraversableTemplate;I)Lscala/collection/generic/TraversableTemplate;;
const #344 = Asciz	scala/collection/generic/TraversableTemplate$$anonfun$drop$1;
const #345 = class	#344;	//  scala/collection/generic/TraversableTemplate$$anonfun$drop$1
const #346 = Asciz	(Lscala/collection/generic/TraversableTemplate;ILscala/collection/generic/Builder;Lscala/runtime/IntRef;)V;
const #347 = NameAndType	#29:#346;//  "<init>":(Lscala/collection/generic/TraversableTemplate;ILscala/collection/generic/Builder;Lscala/runtime/IntRef;)V
const #348 = Method	#345.#347;	//  scala/collection/generic/TraversableTemplate$$anonfun$drop$1."<init>":(Lscala/collection/generic/TraversableTemplate;ILscala/collection/generic/Builder;Lscala/runtime/IntRef;)V
const #349 = Asciz	n$2;
const #350 = Asciz	b$8;
const #351 = Asciz	i$2;
const #352 = Asciz	take;
const #353 = Asciz	scala/collection/generic/TraversableTemplate$$anonfun$take$1;
const #354 = class	#353;	//  scala/collection/generic/TraversableTemplate$$anonfun$take$1
const #355 = Method	#354.#347;	//  scala/collection/generic/TraversableTemplate$$anonfun$take$1."<init>":(Lscala/collection/generic/TraversableTemplate;ILscala/collection/generic/Builder;Lscala/runtime/IntRef;)V
const #356 = Asciz	n$1;
const #357 = Asciz	b$7;
const #358 = Asciz	i$1;
const #359 = Asciz	init;
const #360 = Asciz	(Lscala/collection/generic/TraversableTemplate;)Lscala/collection/generic/TraversableTemplate;;
const #361 = Asciz	isEmpty;
const #362 = Asciz	()Z;
const #363 = NameAndType	#361:#362;//  isEmpty:()Z
const #364 = InterfaceMethod	#13.#363;	//  scala/collection/generic/TraversableTemplate.isEmpty:()Z
const #365 = Asciz	java/lang/UnsupportedOperationException;
const #366 = class	#365;	//  java/lang/UnsupportedOperationException
const #367 = Asciz	empty.init;
const #368 = String	#367;	//  empty.init
const #369 = Asciz	(Ljava/lang/String;)V;
const #370 = NameAndType	#29:#369;//  "<init>":(Ljava/lang/String;)V
const #371 = Method	#366.#370;	//  java/lang/UnsupportedOperationException."<init>":(Ljava/lang/String;)V
const #372 = Asciz	scala/runtime/ObjectRef;
const #373 = class	#372;	//  scala/runtime/ObjectRef
const #374 = Asciz	head;
const #375 = NameAndType	#374:#14;//  head:()Ljava/lang/Object;
const #376 = InterfaceMethod	#13.#375;	//  scala/collection/generic/TraversableTemplate.head:()Ljava/lang/Object;
const #377 = Asciz	(Ljava/lang/Object;)V;
const #378 = NameAndType	#29:#377;//  "<init>":(Ljava/lang/Object;)V
const #379 = Method	#373.#378;	//  scala/runtime/ObjectRef."<init>":(Ljava/lang/Object;)V
const #380 = Asciz	scala/collection/generic/TraversableTemplate$$anonfun$init$1;
const #381 = class	#380;	//  scala/collection/generic/TraversableTemplate$$anonfun$init$1
const #382 = Asciz	(Lscala/collection/generic/TraversableTemplate;Lscala/runtime/ObjectRef;Lscala/runtime/BooleanRef;Lscala/collection/generic/Builder;)V;
const #383 = NameAndType	#29:#382;//  "<init>":(Lscala/collection/generic/TraversableTemplate;Lscala/runtime/ObjectRef;Lscala/runtime/BooleanRef;Lscala/collection/generic/Builder;)V
const #384 = Method	#381.#383;	//  scala/collection/generic/TraversableTemplate$$anonfun$init$1."<init>":(Lscala/collection/generic/TraversableTemplate;Lscala/runtime/ObjectRef;Lscala/runtime/BooleanRef;Lscala/collection/generic/Builder;)V
const #385 = Asciz	lst$2;
const #386 = Asciz	Lscala/runtime/ObjectRef;;
const #387 = Asciz	follow$1;
const #388 = Asciz	b$6;
const #389 = Asciz	lastOption;
const #390 = Asciz	(Lscala/collection/generic/TraversableTemplate;)Lscala/Option;;
const #391 = Asciz	scala/None$;
const #392 = class	#391;	//  scala/None$
const #393 = Asciz	Lscala/None$;;
const #394 = NameAndType	#145:#393;//  MODULE$:Lscala/None$;
const #395 = Field	#392.#394;	//  scala/None$.MODULE$:Lscala/None$;
const #396 = Asciz	scala/Some;
const #397 = class	#396;	//  scala/Some
const #398 = Asciz	last;
const #399 = NameAndType	#398:#14;//  last:()Ljava/lang/Object;
const #400 = InterfaceMethod	#13.#399;	//  scala/collection/generic/TraversableTemplate.last:()Ljava/lang/Object;
const #401 = Method	#397.#378;	//  scala/Some."<init>":(Ljava/lang/Object;)V
const #402 = Asciz	scala/collection/generic/TraversableTemplate$$anonfun$last$1;
const #403 = class	#402;	//  scala/collection/generic/TraversableTemplate$$anonfun$last$1
const #404 = Asciz	(Lscala/collection/generic/TraversableTemplate;Lscala/runtime/ObjectRef;)V;
const #405 = NameAndType	#29:#404;//  "<init>":(Lscala/collection/generic/TraversableTemplate;Lscala/runtime/ObjectRef;)V
const #406 = Method	#403.#405;	//  scala/collection/generic/TraversableTemplate$$anonfun$last$1."<init>":(Lscala/collection/generic/TraversableTemplate;Lscala/runtime/ObjectRef;)V
const #407 = Asciz	elem;
const #408 = Asciz	Ljava/lang/Object;;
const #409 = NameAndType	#407:#408;//  elem:Ljava/lang/Object;
const #410 = Field	#373.#409;	//  scala/runtime/ObjectRef.elem:Ljava/lang/Object;
const #411 = Asciz	lst$1;
const #412 = Asciz	tail;
const #413 = Asciz	(I)Lscala/collection/generic/TraversableTemplate;;
const #414 = NameAndType	#342:#413;//  drop:(I)Lscala/collection/generic/TraversableTemplate;
const #415 = InterfaceMethod	#13.#414;	//  scala/collection/generic/TraversableTemplate.drop:(I)Lscala/collection/generic/TraversableTemplate;
const #416 = Asciz	headOption;
const #417 = Asciz	scala/collection/generic/TraversableTemplate$$anonfun$1;
const #418 = class	#417;	//  scala/collection/generic/TraversableTemplate$$anonfun$1
const #419 = Method	#418.#30;	//  scala/collection/generic/TraversableTemplate$$anonfun$1."<init>":(Lscala/collection/generic/TraversableTemplate;)V
const #420 = Asciz	scala/collection/generic/TraversableTemplate$$anonfun$head$1;
const #421 = class	#420;	//  scala/collection/generic/TraversableTemplate$$anonfun$head$1
const #422 = Method	#421.#405;	//  scala/collection/generic/TraversableTemplate$$anonfun$head$1."<init>":(Lscala/collection/generic/TraversableTemplate;Lscala/runtime/ObjectRef;)V
const #423 = Asciz	scala/Function0;
const #424 = class	#423;	//  scala/Function0
const #425 = NameAndType	#158:#14;//  apply:()Ljava/lang/Object;
const #426 = InterfaceMethod	#424.#425;	//  scala/Function0.apply:()Ljava/lang/Object;
const #427 = Asciz	result$8;
const #428 = Asciz	reduceRightOption;
const #429 = Asciz	(Lscala/collection/generic/TraversableTemplate;Lscala/Function2;)Lscala/Option;;
const #430 = Asciz	reduceRight;
const #431 = Asciz	(Lscala/Function2;)Ljava/lang/Object;;
const #432 = NameAndType	#430:#431;//  reduceRight:(Lscala/Function2;)Ljava/lang/Object;
const #433 = InterfaceMethod	#13.#432;	//  scala/collection/generic/TraversableTemplate.reduceRight:(Lscala/Function2;)Ljava/lang/Object;
const #434 = Asciz	op;
const #435 = Asciz	Lscala/Function2;;
const #436 = Asciz	(Lscala/collection/generic/TraversableTemplate;Lscala/Function2;)Ljava/lang/Object;;
const #437 = Asciz	empty.reduceRight;
const #438 = String	#437;	//  empty.reduceRight
const #439 = Asciz	scala/collection/immutable/Nil$;
const #440 = class	#439;	//  scala/collection/immutable/Nil$
const #441 = Asciz	Lscala/collection/immutable/Nil$;;
const #442 = NameAndType	#145:#441;//  MODULE$:Lscala/collection/immutable/Nil$;
const #443 = Field	#440.#442;	//  scala/collection/immutable/Nil$.MODULE$:Lscala/collection/immutable/Nil$;
const #444 = Asciz	scala/collection/generic/TraversableTemplate$$anonfun$reduceRight$1;
const #445 = class	#444;	//  scala/collection/generic/TraversableTemplate$$anonfun$reduceRight$1
const #446 = Method	#445.#405;	//  scala/collection/generic/TraversableTemplate$$anonfun$reduceRight$1."<init>":(Lscala/collection/generic/TraversableTemplate;Lscala/runtime/ObjectRef;)V
const #447 = Asciz	scala/collection/generic/TraversableTemplate$$anonfun$reduceRight$2;
const #448 = class	#447;	//  scala/collection/generic/TraversableTemplate$$anonfun$reduceRight$2
const #449 = Asciz	(Lscala/collection/generic/TraversableTemplate;Lscala/Function2;)V;
const #450 = NameAndType	#29:#449;//  "<init>":(Lscala/collection/generic/TraversableTemplate;Lscala/Function2;)V
const #451 = Method	#448.#450;	//  scala/collection/generic/TraversableTemplate$$anonfun$reduceRight$2."<init>":(Lscala/collection/generic/TraversableTemplate;Lscala/Function2;)V
const #452 = Asciz	scala/collection/generic/LinearSequenceTemplate;
const #453 = class	#452;	//  scala/collection/generic/LinearSequenceTemplate
const #454 = Asciz	reduceLeft;
const #455 = NameAndType	#454:#431;//  reduceLeft:(Lscala/Function2;)Ljava/lang/Object;
const #456 = InterfaceMethod	#453.#455;	//  scala/collection/generic/LinearSequenceTemplate.reduceLeft:(Lscala/Function2;)Ljava/lang/Object;
const #457 = Asciz	op$4;
const #458 = Asciz	elems$2;
const #459 = Asciz	reduceLeftOption;
const #460 = InterfaceMethod	#13.#455;	//  scala/collection/generic/TraversableTemplate.reduceLeft:(Lscala/Function2;)Ljava/lang/Object;
const #461 = Asciz	empty.reduceLeft;
const #462 = String	#461;	//  empty.reduceLeft
const #463 = Asciz	scala/collection/generic/TraversableTemplate$$anonfun$reduceLeft$1;
const #464 = class	#463;	//  scala/collection/generic/TraversableTemplate$$anonfun$reduceLeft$1
const #465 = Asciz	(Lscala/collection/generic/TraversableTemplate;Lscala/Function2;Lscala/runtime/ObjectRef;Lscala/runtime/BooleanRef;)V;
const #466 = NameAndType	#29:#465;//  "<init>":(Lscala/collection/generic/TraversableTemplate;Lscala/Function2;Lscala/runtime/ObjectRef;Lscala/runtime/BooleanRef;)V
const #467 = Method	#464.#466;	//  scala/collection/generic/TraversableTemplate$$anonfun$reduceLeft$1."<init>":(Lscala/collection/generic/TraversableTemplate;Lscala/Function2;Lscala/runtime/ObjectRef;Lscala/runtime/BooleanRef;)V
const #468 = Asciz	op$3;
const #469 = Asciz	result$7;
const #470 = Asciz	first$1;
const #471 = Asciz	$colon$bslash;
const #472 = Asciz	(Lscala/collection/generic/TraversableTemplate;Ljava/lang/Object;Lscala/Function2;)Ljava/lang/Object;;
const #473 = Asciz	foldRight;
const #474 = Asciz	(Ljava/lang/Object;Lscala/Function2;)Ljava/lang/Object;;
const #475 = NameAndType	#473:#474;//  foldRight:(Ljava/lang/Object;Lscala/Function2;)Ljava/lang/Object;
const #476 = InterfaceMethod	#13.#475;	//  scala/collection/generic/TraversableTemplate.foldRight:(Ljava/lang/Object;Lscala/Function2;)Ljava/lang/Object;
const #477 = Asciz	z;
const #478 = Asciz	scala/collection/generic/TraversableTemplate$$anonfun$foldRight$1;
const #479 = class	#478;	//  scala/collection/generic/TraversableTemplate$$anonfun$foldRight$1
const #480 = Method	#479.#405;	//  scala/collection/generic/TraversableTemplate$$anonfun$foldRight$1."<init>":(Lscala/collection/generic/TraversableTemplate;Lscala/runtime/ObjectRef;)V
const #481 = Asciz	scala/collection/generic/TraversableTemplate$$anonfun$foldRight$2;
const #482 = class	#481;	//  scala/collection/generic/TraversableTemplate$$anonfun$foldRight$2
const #483 = Method	#482.#450;	//  scala/collection/generic/TraversableTemplate$$anonfun$foldRight$2."<init>":(Lscala/collection/generic/TraversableTemplate;Lscala/Function2;)V
const #484 = Asciz	foldLeft;
const #485 = NameAndType	#484:#474;//  foldLeft:(Ljava/lang/Object;Lscala/Function2;)Ljava/lang/Object;
const #486 = InterfaceMethod	#453.#485;	//  scala/collection/generic/LinearSequenceTemplate.foldLeft:(Ljava/lang/Object;Lscala/Function2;)Ljava/lang/Object;
const #487 = Asciz	op$1;
const #488 = Asciz	elems$1;
const #489 = Asciz	$div$colon;
const #490 = InterfaceMethod	#13.#485;	//  scala/collection/generic/TraversableTemplate.foldLeft:(Ljava/lang/Object;Lscala/Function2;)Ljava/lang/Object;
const #491 = Asciz	scala/collection/generic/TraversableTemplate$$anonfun$foldLeft$1;
const #492 = class	#491;	//  scala/collection/generic/TraversableTemplate$$anonfun$foldLeft$1
const #493 = Asciz	(Lscala/collection/generic/TraversableTemplate;Lscala/Function2;Lscala/runtime/ObjectRef;)V;
const #494 = NameAndType	#29:#493;//  "<init>":(Lscala/collection/generic/TraversableTemplate;Lscala/Function2;Lscala/runtime/ObjectRef;)V
const #495 = Method	#492.#494;	//  scala/collection/generic/TraversableTemplate$$anonfun$foldLeft$1."<init>":(Lscala/collection/generic/TraversableTemplate;Lscala/Function2;Lscala/runtime/ObjectRef;)V
const #496 = Asciz	op$2;
const #497 = Asciz	result$6;
const #498 = Asciz	find;
const #499 = Asciz	(Lscala/collection/generic/TraversableTemplate;Lscala/Function1;)Lscala/Option;;
const #500 = Asciz	scala/collection/generic/TraversableTemplate$$anonfun$find$1;
const #501 = class	#500;	//  scala/collection/generic/TraversableTemplate$$anonfun$find$1
const #502 = Asciz	(Lscala/collection/generic/TraversableTemplate;Lscala/Function1;Lscala/runtime/ObjectRef;)V;
const #503 = NameAndType	#29:#502;//  "<init>":(Lscala/collection/generic/TraversableTemplate;Lscala/Function1;Lscala/runtime/ObjectRef;)V
const #504 = Method	#501.#503;	//  scala/collection/generic/TraversableTemplate$$anonfun$find$1."<init>":(Lscala/collection/generic/TraversableTemplate;Lscala/Function1;Lscala/runtime/ObjectRef;)V
const #505 = Asciz	scala/Option;
const #506 = class	#505;	//  scala/Option
const #507 = Asciz	p$9;
const #508 = Asciz	result$5;
const #509 = Asciz	count;
const #510 = Asciz	(Lscala/collection/generic/TraversableTemplate;Lscala/Function1;)I;
const #511 = Asciz	scala/collection/generic/TraversableTemplate$$anonfun$count$1;
const #512 = class	#511;	//  scala/collection/generic/TraversableTemplate$$anonfun$count$1
const #513 = Asciz	(Lscala/collection/generic/TraversableTemplate;Lscala/Function1;Lscala/runtime/IntRef;)V;
const #514 = NameAndType	#29:#513;//  "<init>":(Lscala/collection/generic/TraversableTemplate;Lscala/Function1;Lscala/runtime/IntRef;)V
const #515 = Method	#512.#514;	//  scala/collection/generic/TraversableTemplate$$anonfun$count$1."<init>":(Lscala/collection/generic/TraversableTemplate;Lscala/Function1;Lscala/runtime/IntRef;)V
const #516 = NameAndType	#407:#24;//  elem:I
const #517 = Field	#228.#516;	//  scala/runtime/IntRef.elem:I
const #518 = Asciz	p$5;
const #519 = Asciz	cnt$1;
const #520 = Asciz	exists;
const #521 = Asciz	(Lscala/collection/generic/TraversableTemplate;Lscala/Function1;)Z;
const #522 = Asciz	scala/collection/generic/TraversableTemplate$$anonfun$exists$1;
const #523 = class	#522;	//  scala/collection/generic/TraversableTemplate$$anonfun$exists$1
const #524 = Asciz	(Lscala/collection/generic/TraversableTemplate;Lscala/Function1;Lscala/runtime/BooleanRef;)V;
const #525 = NameAndType	#29:#524;//  "<init>":(Lscala/collection/generic/TraversableTemplate;Lscala/Function1;Lscala/runtime/BooleanRef;)V
const #526 = Method	#523.#525;	//  scala/collection/generic/TraversableTemplate$$anonfun$exists$1."<init>":(Lscala/collection/generic/TraversableTemplate;Lscala/Function1;Lscala/runtime/BooleanRef;)V
const #527 = Asciz	Z;
const #528 = NameAndType	#407:#527;//  elem:Z
const #529 = Field	#115.#528;	//  scala/runtime/BooleanRef.elem:Z
const #530 = Asciz	p$8;
const #531 = Asciz	result$4;
const #532 = Asciz	forall;
const #533 = Asciz	scala/collection/generic/TraversableTemplate$$anonfun$forall$1;
const #534 = class	#533;	//  scala/collection/generic/TraversableTemplate$$anonfun$forall$1
const #535 = Method	#534.#525;	//  scala/collection/generic/TraversableTemplate$$anonfun$forall$1."<init>":(Lscala/collection/generic/TraversableTemplate;Lscala/Function1;Lscala/runtime/BooleanRef;)V
const #536 = Asciz	p$6;
const #537 = Asciz	result$3;
const #538 = Asciz	groupBy;
const #539 = Asciz	(Lscala/collection/generic/TraversableTemplate;Lscala/Function1;)Lscala/collection/Map;;
const #540 = Asciz	scala/collection/Map$;
const #541 = class	#540;	//  scala/collection/Map$
const #542 = Asciz	Lscala/collection/Map$;;
const #543 = NameAndType	#145:#542;//  MODULE$:Lscala/collection/Map$;
const #544 = Field	#541.#543;	//  scala/collection/Map$.MODULE$:Lscala/collection/Map$;
const #545 = Asciz	(Lscala/collection/Sequence;)Lscala/collection/Map;;
const #546 = NameAndType	#158:#545;//  apply:(Lscala/collection/Sequence;)Lscala/collection/Map;
const #547 = Method	#541.#546;	//  scala/collection/Map$.apply:(Lscala/collection/Sequence;)Lscala/collection/Map;
const #548 = Asciz	scala/collection/immutable/Map;
const #549 = class	#548;	//  scala/collection/immutable/Map
const #550 = Asciz	scala/collection/generic/TraversableTemplate$$anonfun$groupBy$1;
const #551 = class	#550;	//  scala/collection/generic/TraversableTemplate$$anonfun$groupBy$1
const #552 = Method	#551.#503;	//  scala/collection/generic/TraversableTemplate$$anonfun$groupBy$1."<init>":(Lscala/collection/generic/TraversableTemplate;Lscala/Function1;Lscala/runtime/ObjectRef;)V
const #553 = Asciz	scala/collection/generic/TraversableTemplate$$anonfun$groupBy$2;
const #554 = class	#553;	//  scala/collection/generic/TraversableTemplate$$anonfun$groupBy$2
const #555 = Method	#554.#30;	//  scala/collection/generic/TraversableTemplate$$anonfun$groupBy$2."<init>":(Lscala/collection/generic/TraversableTemplate;)V
const #556 = Asciz	scala/collection/generic/MapTemplate;
const #557 = class	#556;	//  scala/collection/generic/MapTemplate
const #558 = Asciz	mapValues;
const #559 = Asciz	(Lscala/Function1;)Ljava/lang/Object;;
const #560 = NameAndType	#558:#559;//  mapValues:(Lscala/Function1;)Ljava/lang/Object;
const #561 = InterfaceMethod	#557.#560;	//  scala/collection/generic/MapTemplate.mapValues:(Lscala/Function1;)Ljava/lang/Object;
const #562 = Asciz	scala/collection/Map;
const #563 = class	#562;	//  scala/collection/Map
const #564 = Asciz	f$3;
const #565 = Asciz	m$1;
const #566 = Asciz	partition;
const #567 = Asciz	scala/collection/generic/TraversableTemplate$$anonfun$partition$1;
const #568 = class	#567;	//  scala/collection/generic/TraversableTemplate$$anonfun$partition$1
const #569 = Asciz	(Lscala/collection/generic/TraversableTemplate;Lscala/Function1;Lscala/collection/generic/Builder;Lscala/collection/generic/Builder;)V;
const #570 = NameAndType	#29:#569;//  "<init>":(Lscala/collection/generic/TraversableTemplate;Lscala/Function1;Lscala/collection/generic/Builder;Lscala/collection/generic/Builder;)V
const #571 = Method	#568.#570;	//  scala/collection/generic/TraversableTemplate$$anonfun$partition$1."<init>":(Lscala/collection/generic/TraversableTemplate;Lscala/Function1;Lscala/collection/generic/Builder;Lscala/collection/generic/Builder;)V
const #572 = Asciz	p$10;
const #573 = Asciz	l$1;
const #574 = Asciz	r$1;
const #575 = Asciz	remove;
const #576 = Asciz	filterNot;
const #577 = Asciz	(Lscala/Function1;)Lscala/collection/generic/TraversableTemplate;;
const #578 = NameAndType	#576:#577;//  filterNot:(Lscala/Function1;)Lscala/collection/generic/TraversableTemplate;
const #579 = InterfaceMethod	#13.#578;	//  scala/collection/generic/TraversableTemplate.filterNot:(Lscala/Function1;)Lscala/collection/generic/TraversableTemplate;
const #580 = Asciz	p;
const #581 = Asciz	scala/collection/generic/TraversableTemplate$$anonfun$filterNot$1;
const #582 = class	#581;	//  scala/collection/generic/TraversableTemplate$$anonfun$filterNot$1
const #583 = Asciz	(Lscala/collection/generic/TraversableTemplate;Lscala/Function1;)V;
const #584 = NameAndType	#29:#583;//  "<init>":(Lscala/collection/generic/TraversableTemplate;Lscala/Function1;)V
const #585 = Method	#582.#584;	//  scala/collection/generic/TraversableTemplate$$anonfun$filterNot$1."<init>":(Lscala/collection/generic/TraversableTemplate;Lscala/Function1;)V
const #586 = Asciz	filter;
const #587 = NameAndType	#586:#577;//  filter:(Lscala/Function1;)Lscala/collection/generic/TraversableTemplate;
const #588 = InterfaceMethod	#13.#587;	//  scala/collection/generic/TraversableTemplate.filter:(Lscala/Function1;)Lscala/collection/generic/TraversableTemplate;
const #589 = Asciz	p$7;
const #590 = Asciz	filterMap;
const #591 = Asciz	(Lscala/collection/generic/TraversableTemplate;Lscala/PartialFunction;Lscala/collection/generic/BuilderFactory;)Ljava/lang/Object;;
const #592 = Asciz	scala/collection/generic/BuilderFactory;
const #593 = class	#592;	//  scala/collection/generic/BuilderFactory
const #594 = Asciz	(Ljava/lang/Object;)Lscala/collection/generic/Builder;;
const #595 = NameAndType	#158:#594;//  apply:(Ljava/lang/Object;)Lscala/collection/generic/Builder;
const #596 = InterfaceMethod	#593.#595;	//  scala/collection/generic/BuilderFactory.apply:(Ljava/lang/Object;)Lscala/collection/generic/Builder;
const #597 = Asciz	scala/collection/generic/TraversableTemplate$$anonfun$filterMap$1;
const #598 = class	#597;	//  scala/collection/generic/TraversableTemplate$$anonfun$filterMap$1
const #599 = Asciz	(Lscala/collection/generic/TraversableTemplate;Lscala/PartialFunction;Lscala/collection/generic/Builder;)V;
const #600 = NameAndType	#29:#599;//  "<init>":(Lscala/collection/generic/TraversableTemplate;Lscala/PartialFunction;Lscala/collection/generic/Builder;)V
const #601 = Method	#598.#600;	//  scala/collection/generic/TraversableTemplate$$anonfun$filterMap$1."<init>":(Lscala/collection/generic/TraversableTemplate;Lscala/PartialFunction;Lscala/collection/generic/Builder;)V
const #602 = Asciz	pf$1;
const #603 = Asciz	Lscala/PartialFunction;;
const #604 = Asciz	bf;
const #605 = Asciz	Lscala/collection/generic/BuilderFactory;;
const #606 = Asciz	b$5;
const #607 = Asciz	scala/collection/generic/TraversableTemplate$$anonfun$filter$1;
const #608 = class	#607;	//  scala/collection/generic/TraversableTemplate$$anonfun$filter$1
const #609 = Method	#608.#328;	//  scala/collection/generic/TraversableTemplate$$anonfun$filter$1."<init>":(Lscala/collection/generic/TraversableTemplate;Lscala/Function1;Lscala/collection/generic/Builder;)V
const #610 = Asciz	p$4;
const #611 = Asciz	b$4;
const #612 = Asciz	flatMap;
const #613 = Asciz	(Lscala/collection/generic/TraversableTemplate;Lscala/Function1;Lscala/collection/generic/BuilderFactory;)Ljava/lang/Object;;
const #614 = Asciz	scala/collection/generic/TraversableTemplate$$anonfun$flatMap$1;
const #615 = class	#614;	//  scala/collection/generic/TraversableTemplate$$anonfun$flatMap$1
const #616 = Method	#615.#328;	//  scala/collection/generic/TraversableTemplate$$anonfun$flatMap$1."<init>":(Lscala/collection/generic/TraversableTemplate;Lscala/Function1;Lscala/collection/generic/Builder;)V
const #617 = Asciz	f$2;
const #618 = Asciz	b$3;
const #619 = Asciz	map;
const #620 = Asciz	scala/collection/generic/TraversableTemplate$$anonfun$map$1;
const #621 = class	#620;	//  scala/collection/generic/TraversableTemplate$$anonfun$map$1
const #622 = Method	#621.#328;	//  scala/collection/generic/TraversableTemplate$$anonfun$map$1."<init>":(Lscala/collection/generic/TraversableTemplate;Lscala/Function1;Lscala/collection/generic/Builder;)V
const #623 = Asciz	f$1;
const #624 = Asciz	b$2;
const #625 = Asciz	(Lscala/collection/generic/TraversableTemplate;Lscala/collection/Iterator;Lscala/collection/generic/BuilderFactory;)Ljava/lang/Object;;
const #626 = Asciz	(Lscala/collection/Iterator;)Lscala/collection/generic/Growable;;
const #627 = NameAndType	#194:#626;//  $plus$plus$eq:(Lscala/collection/Iterator;)Lscala/collection/generic/Growable;
const #628 = InterfaceMethod	#193.#627;	//  scala/collection/generic/Growable.$plus$plus$eq:(Lscala/collection/Iterator;)Lscala/collection/generic/Growable;
const #629 = Asciz	that;
const #630 = Asciz	Lscala/collection/Iterator;;
const #631 = Asciz	(Lscala/collection/generic/TraversableTemplate;Lscala/collection/Traversable;Lscala/collection/generic/BuilderFactory;)Ljava/lang/Object;;
const #632 = Asciz	Lscala/collection/Traversable;;
const #633 = Asciz	hasDefiniteSize;
const #634 = Asciz	(Lscala/collection/generic/TraversableTemplate;)Z;
const #635 = Asciz	(Lscala/collection/generic/TraversableTemplate;)I;
const #636 = Asciz	scala/collection/generic/TraversableTemplate$$anonfun$size$1;
const #637 = class	#636;	//  scala/collection/generic/TraversableTemplate$$anonfun$size$1
const #638 = Asciz	(Lscala/collection/generic/TraversableTemplate;Lscala/runtime/IntRef;)V;
const #639 = NameAndType	#29:#638;//  "<init>":(Lscala/collection/generic/TraversableTemplate;Lscala/runtime/IntRef;)V
const #640 = Method	#637.#639;	//  scala/collection/generic/TraversableTemplate$$anonfun$size$1."<init>":(Lscala/collection/generic/TraversableTemplate;Lscala/runtime/IntRef;)V
const #641 = Asciz	result$2;
const #642 = Asciz	nonEmpty;
const #643 = Asciz	scala/collection/generic/TraversableTemplate$$anonfun$isEmpty$1;
const #644 = class	#643;	//  scala/collection/generic/TraversableTemplate$$anonfun$isEmpty$1
const #645 = Asciz	(Lscala/collection/generic/TraversableTemplate;Lscala/runtime/BooleanRef;)V;
const #646 = NameAndType	#29:#645;//  "<init>":(Lscala/collection/generic/TraversableTemplate;Lscala/runtime/BooleanRef;)V
const #647 = Method	#644.#646;	//  scala/collection/generic/TraversableTemplate$$anonfun$isEmpty$1."<init>":(Lscala/collection/generic/TraversableTemplate;Lscala/runtime/BooleanRef;)V
const #648 = Asciz	result$1;
const #649 = Asciz	Scala;
const #650 = Asciz	InnerClasses;
const #651 = Asciz	$anon$1;
const #652 = Asciz	$anonfun$1;
const #653 = Asciz	$anonfun$map$1;
const #654 = Asciz	$anonfun$init$1;
const #655 = Asciz	$anonfun$span$1;
const #656 = Asciz	$anonfun$find$1;
const #657 = Asciz	$anonfun$drop$1;
const #658 = Asciz	$anonfun$size$1;
const #659 = Asciz	$anonfun$last$1;
const #660 = Asciz	$anonfun$head$1;
const #661 = Asciz	$anonfun$take$1;
const #662 = Asciz	$anonfun$slice$1;
const #663 = Asciz	$anonfun$count$1;
const #664 = Asciz	$anonfun$exists$1;
const #665 = Asciz	$anonfun$forall$1;
const #666 = Asciz	$anonfun$filter$1;
const #667 = Asciz	$anonfun$flatMap$1;
const #668 = Asciz	$anonfun$groupBy$1;
const #669 = Asciz	$anonfun$splitAt$1;
const #670 = Asciz	$anonfun$groupBy$2;
const #671 = Asciz	$anonfun$isEmpty$1;
const #672 = Asciz	$anonfun$foldLeft$1;
const #673 = Asciz	$anonfun$foldRight$2;
const #674 = Asciz	$anonfun$partition$1;
const #675 = Asciz	$anonfun$takeWhile$1;
const #676 = Asciz	$anonfun$filterMap$1;
const #677 = Asciz	$anonfun$addString$1;
const #678 = Asciz	$anonfun$filterNot$1;
const #679 = Asciz	$anonfun$dropWhile$1;
const #680 = Asciz	$anonfun$foldRight$1;
const #681 = Asciz	$anonfun$reduceLeft$1;
const #682 = Asciz	$anonfun$reduceRight$1;
const #683 = Asciz	$anonfun$reduceRight$2;
const #684 = Asciz	$anonfun$copyToArray$1;
const #685 = Asciz	$anonfun$copyToBuffer$1;
const #686 = Asciz	scala/collection/generic/TraversableTemplate$class;
const #687 = class	#686;	//  scala/collection/generic/TraversableTemplate$class

{
public static void $init$(scala.collection.generic.TraversableTemplate);
  Code:
   Stack=0, Locals=1, Args_size=1
   0:	return
  LineNumberTable: 
   line 64: 0

  LocalVariableTable: 
   Start  Length  Slot  Name   Signature
   0      1      0    $this       Lscala/collection/generic/TraversableTemplate;


public static scala.collection.generic.TraversableView view(scala.collection.generic.TraversableTemplate, int, int);
  Code:
   Stack=3, Locals=3, Args_size=3
   0:	aload_0
   1:	invokeinterface	#16,  1; //InterfaceMethod scala/collection/generic/TraversableTemplate.view:()Ljava/lang/Object;
   6:	checkcast	#18; //class scala/collection/generic/TraversableViewTemplate
   9:	iload_1
   10:	iload_2
   11:	invokeinterface	#22,  3; //InterfaceMethod scala/collection/generic/TraversableViewTemplate.slice:(II)Lscala/collection/generic/TraversableView;
   16:	areturn
  LineNumberTable: 
   line 834: 0

  LocalVariableTable: 
   Start  Length  Slot  Name   Signature
   0      17      0    $this       Lscala/collection/generic/TraversableTemplate;
   0      17      1    from       I
   0      17      2    until       I


public static java.lang.Object view(scala.collection.generic.TraversableTemplate);
  Code:
   Stack=3, Locals=1, Args_size=1
   0:	new	#28; //class scala/collection/generic/TraversableTemplate$$anon$1
   3:	dup
   4:	aload_0
   5:	invokespecial	#31; //Method scala/collection/generic/TraversableTemplate$$anon$1."<init>":(Lscala/collection/generic/TraversableTemplate;)V
   8:	areturn
  LineNumberTable: 
   line 818: 0

  LocalVariableTable: 
   Start  Length  Slot  Name   Signature
   0      9      0    $this       Lscala/collection/generic/TraversableTemplate;


public static java.lang.String stringPrefix(scala.collection.generic.TraversableTemplate);
  Code:
   Stack=3, Locals=4, Args_size=1
   0:	aload_0
   1:	invokeinterface	#37,  1; //InterfaceMethod scala/collection/generic/TraversableTemplate.thisCollection:()Lscala/collection/generic/TraversableTemplate;
   6:	invokevirtual	#43; //Method java/lang/Object.getClass:()Ljava/lang/Class;
   9:	invokevirtual	#49; //Method java/lang/Class.getName:()Ljava/lang/String;
   12:	astore_1
   13:	aload_1
   14:	ldc	#50; //int 46
   16:	invokevirtual	#56; //Method java/lang/String.lastIndexOf:(I)I
   19:	istore_2
   20:	iload_2
   21:	iconst_m1
   22:	if_icmpeq	33
   25:	aload_1
   26:	iload_2
   27:	iconst_1
   28:	iadd
   29:	invokevirtual	#60; //Method java/lang/String.substring:(I)Ljava/lang/String;
   32:	astore_1
   33:	aload_1
   34:	ldc	#61; //int 36
   36:	invokevirtual	#64; //Method java/lang/String.indexOf:(I)I
   39:	istore_3
   40:	iload_3
   41:	iconst_m1
   42:	if_icmpeq	52
   45:	aload_1
   46:	iconst_0
   47:	iload_3
   48:	invokevirtual	#67; //Method java/lang/String.substring:(II)Ljava/lang/String;
   51:	astore_1
   52:	aload_1
   53:	areturn
  LineNumberTable: 
   line 808: 0
   line 809: 13
   line 810: 20
   line 811: 33
   line 812: 40
   line 813: 52

  LocalVariableTable: 
   Start  Length  Slot  Name   Signature
   0      54      0    $this       Lscala/collection/generic/TraversableTemplate;
   13      40      1    string       Ljava/lang/String;
   20      33      2    idx1       I
   40      13      3    idx2       I


public static java.lang.String toString(scala.collection.generic.TraversableTemplate);
  Code:
   Stack=4, Locals=1, Args_size=1
   0:	aload_0
   1:	new	#74; //class scala/collection/mutable/StringBuilder
   4:	dup
   5:	invokespecial	#77; //Method scala/collection/mutable/StringBuilder."<init>":()V
   8:	aload_0
   9:	invokeinterface	#79,  1; //InterfaceMethod scala/collection/generic/TraversableTemplate.stringPrefix:()Ljava/lang/String;
   14:	invokevirtual	#83; //Method scala/collection/mutable/StringBuilder.append:(Ljava/lang/Object;)Lscala/collection/mutable/StringBuilder;
   17:	ldc	#85; //String (
   19:	invokevirtual	#83; //Method scala/collection/mutable/StringBuilder.append:(Ljava/lang/Object;)Lscala/collection/mutable/StringBuilder;
   22:	invokevirtual	#87; //Method scala/collection/mutable/StringBuilder.toString:()Ljava/lang/String;
   25:	ldc	#89; //String , 
   27:	ldc	#91; //String )
   29:	invokeinterface	#95,  4; //InterfaceMethod scala/collection/generic/TraversableTemplate.mkString:(Ljava/lang/String;Ljava/lang/String;Ljava/lang/String;)Ljava/lang/String;
   34:	areturn
  LineNumberTable: 
   line 803: 0

  LocalVariableTable: 
   Start  Length  Slot  Name   Signature
   0      35      0    $this       Lscala/collection/generic/TraversableTemplate;


public static scala.collection.mutable.StringBuilder addString(scala.collection.generic.TraversableTemplate, scala.collection.mutable.StringBuilder);
  Code:
   Stack=3, Locals=2, Args_size=2
   0:	aload_0
   1:	aload_1
   2:	ldc	#99; //String 
   4:	invokeinterface	#102,  3; //InterfaceMethod scala/collection/generic/TraversableTemplate.addString:(Lscala/collection/mutable/StringBuilder;Ljava/lang/String;)Lscala/collection/mutable/StringBuilder;
   9:	areturn
  LineNumberTable: 
   line 801: 0

  LocalVariableTable: 
   Start  Length  Slot  Name   Signature
   0      10      0    $this       Lscala/collection/generic/TraversableTemplate;
   0      10      1    b       Lscala/collection/mutable/StringBuilder;


public static scala.collection.mutable.StringBuilder addString(scala.collection.generic.TraversableTemplate, scala.collection.mutable.StringBuilder, java.lang.String);
  Code:
   Stack=5, Locals=3, Args_size=3
   0:	aload_0
   1:	aload_1
   2:	ldc	#99; //String 
   4:	aload_2
   5:	ldc	#99; //String 
   7:	invokeinterface	#108,  5; //InterfaceMethod scala/collection/generic/TraversableTemplate.addString:(Lscala/collection/mutable/StringBuilder;Ljava/lang/String;Ljava/lang/String;Ljava/lang/String;)Lscala/collection/mutable/StringBuilder;
   12:	areturn
  LineNumberTable: 
   line 796: 0

  LocalVariableTable: 
   Start  Length  Slot  Name   Signature
   0      13      0    $this       Lscala/collection/generic/TraversableTemplate;
   0      13      1    b       Lscala/collection/mutable/StringBuilder;
   0      13      2    sep       Ljava/lang/String;


public static scala.collection.mutable.StringBuilder addString(scala.collection.generic.TraversableTemplate, scala.collection.mutable.StringBuilder, java.lang.String, java.lang.String, java.lang.String);
  Code:
   Stack=7, Locals=6, Args_size=5
   0:	aload_1
   1:	aload_2
   2:	invokevirtual	#113; //Method scala/collection/mutable/StringBuilder.append:(Ljava/lang/String;)Lscala/collection/mutable/StringBuilder;
   5:	pop
   6:	new	#115; //class scala/runtime/BooleanRef
   9:	dup
   10:	iconst_1
   11:	invokespecial	#118; //Method scala/runtime/BooleanRef."<init>":(Z)V
   14:	astore	5
   16:	aload_0
   17:	new	#120; //class scala/collection/generic/TraversableTemplate$$anonfun$addString$1
   20:	dup
   21:	aload_0
   22:	aload_1
   23:	aload_3
   24:	aload	5
   26:	invokespecial	#123; //Method scala/collection/generic/TraversableTemplate$$anonfun$addString$1."<init>":(Lscala/collection/generic/TraversableTemplate;Lscala/collection/mutable/StringBuilder;Ljava/lang/String;Lscala/runtime/BooleanRef;)V
   29:	invokeinterface	#127,  2; //InterfaceMethod scala/collection/generic/TraversableTemplate.foreach:(Lscala/Function1;)V
   34:	aload_1
   35:	aload	4
   37:	invokevirtual	#113; //Method scala/collection/mutable/StringBuilder.append:(Ljava/lang/String;)Lscala/collection/mutable/StringBuilder;
   40:	areturn
  LineNumberTable: 
   line 782: 0
   line 783: 6
   line 784: 16
   line 789: 34

  LocalVariableTable: 
   Start  Length  Slot  Name   Signature
   0      41      0    $this       Lscala/collection/generic/TraversableTemplate;
   0      41      1    b$1       Lscala/collection/mutable/StringBuilder;
   0      41      2    start       Ljava/lang/String;
   0      41      3    sep$1       Ljava/lang/String;
   0      41      4    end       Ljava/lang/String;
   16      24      5    first$2       Lscala/runtime/BooleanRef;


public static java.lang.String mkString(scala.collection.generic.TraversableTemplate);
  Code:
   Stack=3, Locals=1, Args_size=1
   0:	aload_0
   1:	new	#74; //class scala/collection/mutable/StringBuilder
   4:	dup
   5:	invokespecial	#134; //Method scala/collection/mutable/StringBuilder."<init>":()V
   8:	invokeinterface	#137,  2; //InterfaceMethod scala/collection/generic/TraversableTemplate.addString:(Lscala/collection/mutable/StringBuilder;)Lscala/collection/mutable/StringBuilder;
   13:	invokevirtual	#138; //Method scala/collection/mutable/StringBuilder.toString:()Ljava/lang/String;
   16:	areturn
  LineNumberTable: 
   line 773: 0

  LocalVariableTable: 
   Start  Length  Slot  Name   Signature
   0      17      0    $this       Lscala/collection/generic/TraversableTemplate;


public static java.lang.String mkString(scala.collection.generic.TraversableTemplate, java.lang.String);
  Code:
   Stack=3, Locals=2, Args_size=2
   0:	aload_0
   1:	new	#74; //class scala/collection/mutable/StringBuilder
   4:	dup
   5:	invokespecial	#134; //Method scala/collection/mutable/StringBuilder."<init>":()V
   8:	aload_1
   9:	invokeinterface	#102,  3; //InterfaceMethod scala/collection/generic/TraversableTemplate.addString:(Lscala/collection/mutable/StringBuilder;Ljava/lang/String;)Lscala/collection/mutable/StringBuilder;
   14:	invokevirtual	#138; //Method scala/collection/mutable/StringBuilder.toString:()Ljava/lang/String;
   17:	areturn
  LineNumberTable: 
   line 766: 0

  LocalVariableTable: 
   Start  Length  Slot  Name   Signature
   0      18      0    $this       Lscala/collection/generic/TraversableTemplate;
   0      18      1    sep       Ljava/lang/String;


public static java.lang.String mkString(scala.collection.generic.TraversableTemplate, java.lang.String, java.lang.String, java.lang.String);
  Code:
   Stack=5, Locals=4, Args_size=4
   0:	aload_0
   1:	new	#74; //class scala/collection/mutable/StringBuilder
   4:	dup
   5:	invokespecial	#134; //Method scala/collection/mutable/StringBuilder."<init>":()V
   8:	aload_1
   9:	aload_2
   10:	aload_3
   11:	invokeinterface	#108,  5; //InterfaceMethod scala/collection/generic/TraversableTemplate.addString:(Lscala/collection/mutable/StringBuilder;Ljava/lang/String;Ljava/lang/String;Ljava/lang/String;)Lscala/collection/mutable/StringBuilder;
   16:	invokevirtual	#138; //Method scala/collection/mutable/StringBuilder.toString:()Ljava/lang/String;
   19:	areturn
  LineNumberTable: 
   line 756: 0

  LocalVariableTable: 
   Start  Length  Slot  Name   Signature
   0      20      0    $this       Lscala/collection/generic/TraversableTemplate;
   0      20      1    start       Ljava/lang/String;
   0      20      2    sep       Ljava/lang/String;
   0      20      3    end       Ljava/lang/String;


public static scala.collection.immutable.Set toSet(scala.collection.generic.TraversableTemplate);
  Code:
   Stack=3, Locals=1, Args_size=1
   0:	getstatic	#148; //Field scala/collection/immutable/Set$.MODULE$:Lscala/collection/immutable/Set$;
   3:	getstatic	#153; //Field scala/runtime/ScalaRunTime$.MODULE$:Lscala/runtime/ScalaRunTime$;
   6:	iconst_0
   7:	anewarray	#39; //class java/lang/Object
   10:	invokevirtual	#157; //Method scala/runtime/ScalaRunTime$.boxArray:(Ljava/lang/Object;)Lscala/runtime/BoxedArray;
   13:	invokevirtual	#161; //Method scala/collection/immutable/Set$.apply:(Lscala/collection/Sequence;)Lscala/collection/Traversable;
   16:	checkcast	#163; //class scala/collection/generic/Addable
   19:	aload_0
   20:	invokeinterface	#37,  1; //InterfaceMethod scala/collection/generic/TraversableTemplate.thisCollection:()Lscala/collection/generic/TraversableTemplate;
   25:	checkcast	#165; //class scala/collection/Traversable
   28:	invokeinterface	#169,  2; //InterfaceMethod scala/collection/generic/Addable.$plus$plus:(Lscala/collection/Traversable;)Lscala/collection/generic/Addable;
   33:	checkcast	#171; //class scala/collection/immutable/Set
   36:	areturn
  LineNumberTable: 
   line 717: 0

  LocalVariableTable: 
   Start  Length  Slot  Name   Signature
   0      37      0    $this       Lscala/collection/generic/TraversableTemplate;


public static scala.collection.immutable.Stream toStream(scala.collection.generic.TraversableTemplate);
  Code:
   Stack=1, Locals=1, Args_size=1
   0:	aload_0
   1:	invokeinterface	#177,  1; //InterfaceMethod scala/collection/generic/TraversableTemplate.toList:()Lscala/collection/immutable/List;
   6:	invokevirtual	#182; //Method scala/collection/immutable/List.toStream:()Lscala/collection/immutable/Stream;
   9:	areturn
  LineNumberTable: 
   line 712: 0

  LocalVariableTable: 
   Start  Length  Slot  Name   Signature
   0      10      0    $this       Lscala/collection/generic/TraversableTemplate;


public static scala.collection.Sequence toSequence(scala.collection.generic.TraversableTemplate);
  Code:
   Stack=1, Locals=1, Args_size=1
   0:	aload_0
   1:	invokeinterface	#177,  1; //InterfaceMethod scala/collection/generic/TraversableTemplate.toList:()Lscala/collection/immutable/List;
   6:	areturn
  LineNumberTable: 
   line 708: 0

  LocalVariableTable: 
   Start  Length  Slot  Name   Signature
   0      7      0    $this       Lscala/collection/generic/TraversableTemplate;


public static scala.collection.Iterable toIterable(scala.collection.generic.TraversableTemplate);
  Code:
   Stack=1, Locals=1, Args_size=1
   0:	aload_0
   1:	invokeinterface	#187,  1; //InterfaceMethod scala/collection/generic/TraversableTemplate.toStream:()Lscala/collection/immutable/Stream;
   6:	areturn
  LineNumberTable: 
   line 703: 0

  LocalVariableTable: 
   Start  Length  Slot  Name   Signature
   0      7      0    $this       Lscala/collection/generic/TraversableTemplate;


public static scala.collection.immutable.List toList(scala.collection.generic.TraversableTemplate);
  Code:
   Stack=2, Locals=1, Args_size=1
   0:	new	#190; //class scala/collection/mutable/ListBuffer
   3:	dup
   4:	invokespecial	#191; //Method scala/collection/mutable/ListBuffer."<init>":()V
   7:	aload_0
   8:	invokeinterface	#37,  1; //InterfaceMethod scala/collection/generic/TraversableTemplate.thisCollection:()Lscala/collection/generic/TraversableTemplate;
   13:	checkcast	#165; //class scala/collection/Traversable
   16:	invokeinterface	#197,  2; //InterfaceMethod scala/collection/generic/Growable.$plus$plus$eq:(Lscala/collection/Traversable;)Lscala/collection/generic/Growable;
   21:	checkcast	#190; //class scala/collection/mutable/ListBuffer
   24:	invokevirtual	#198; //Method scala/collection/mutable/ListBuffer.toList:()Lscala/collection/immutable/List;
   27:	areturn
  LineNumberTable: 
   line 698: 0

  LocalVariableTable: 
   Start  Length  Slot  Name   Signature
   0      28      0    $this       Lscala/collection/generic/TraversableTemplate;


public static scala.runtime.BoxedArray toArray(scala.collection.generic.TraversableTemplate);
  Code:
   Stack=3, Locals=2, Args_size=1
   0:	new	#202; //class scala/runtime/BoxedAnyArray
   3:	dup
   4:	aload_0
   5:	invokeinterface	#206,  1; //InterfaceMethod scala/collection/generic/TraversableTemplate.size:()I
   10:	invokespecial	#209; //Method scala/runtime/BoxedAnyArray."<init>":(I)V
   13:	astore_1
   14:	aload_0
   15:	aload_1
   16:	iconst_0
   17:	invokeinterface	#213,  3; //InterfaceMethod scala/collection/generic/TraversableTemplate.copyToArray:(Lscala/runtime/BoxedArray;I)V
   22:	aload_1
   23:	areturn
  LineNumberTable: 
   line 690: 0
   line 691: 14
   line 692: 22

  LocalVariableTable: 
   Start  Length  Slot  Name   Signature
   0      24      0    $this       Lscala/collection/generic/TraversableTemplate;
   14      9      1    result       Lscala/runtime/BoxedArray;


public static void copyToArray(scala.collection.generic.TraversableTemplate, scala.runtime.BoxedArray, int);
  Code:
   Stack=5, Locals=3, Args_size=3
   0:	aload_0
   1:	aload_1
   2:	iload_2
   3:	aload_1
   4:	invokevirtual	#221; //Method scala/runtime/BoxedArray.length:()I
   7:	iload_2
   8:	isub
   9:	invokeinterface	#224,  4; //InterfaceMethod scala/collection/generic/TraversableTemplate.copyToArray:(Lscala/runtime/BoxedArray;II)V
   14:	return
  LineNumberTable: 
   line 683: 0

  LocalVariableTable: 
   Start  Length  Slot  Name   Signature
   0      15      0    $this       Lscala/collection/generic/TraversableTemplate;
   0      15      1    xs       Lscala/runtime/BoxedArray;
   0      15      2    start       I


public static void copyToArray(scala.collection.generic.TraversableTemplate, scala.runtime.BoxedArray, int, int);
  Code:
   Stack=7, Locals=6, Args_size=4
   0:	new	#228; //class scala/runtime/IntRef
   3:	dup
   4:	iload_2
   5:	invokespecial	#229; //Method scala/runtime/IntRef."<init>":(I)V
   8:	astore	4
   10:	getstatic	#234; //Field scala/Predef$.MODULE$:Lscala/Predef$;
   13:	iload_2
   14:	iload_3
   15:	iadd
   16:	invokevirtual	#238; //Method scala/Predef$.intWrapper:(I)Lscala/runtime/RichInt;
   19:	aload_1
   20:	invokevirtual	#221; //Method scala/runtime/BoxedArray.length:()I
   23:	invokevirtual	#243; //Method scala/runtime/RichInt.min:(I)I
   26:	istore	5
   28:	getstatic	#248; //Field scala/collection/Traversable$.MODULE$:Lscala/collection/Traversable$;
   31:	invokevirtual	#252; //Method scala/collection/Traversable$.breaks:()Lscala/util/control/Breaks;
   34:	new	#254; //class scala/collection/generic/TraversableTemplate$$anonfun$copyToArray$1
   37:	dup
   38:	aload_0
   39:	aload_1
   40:	aload	4
   42:	iload	5
   44:	invokespecial	#257; //Method scala/collection/generic/TraversableTemplate$$anonfun$copyToArray$1."<init>":(Lscala/collection/generic/TraversableTemplate;Lscala/runtime/BoxedArray;Lscala/runtime/IntRef;I)V
   47:	invokevirtual	#263; //Method scala/util/control/Breaks.breakable:(Lscala/Function0;)V
   50:	return
  LineNumberTable: 
   line 662: 0
   line 663: 10
   line 664: 28
   line 665: 34
   line 664: 47

  LocalVariableTable: 
   Start  Length  Slot  Name   Signature
   0      51      0    $this       Lscala/collection/generic/TraversableTemplate;
   0      51      1    xs$1       Lscala/runtime/BoxedArray;
   0      51      2    start       I
   0      51      3    len       I
   10      40      4    i$5       Lscala/runtime/IntRef;
   28      22      5    end$1       I


public static void copyToBuffer(scala.collection.generic.TraversableTemplate, scala.collection.mutable.Buffer);
  Code:
   Stack=5, Locals=2, Args_size=2
   0:	aload_0
   1:	new	#272; //class scala/collection/generic/TraversableTemplate$$anonfun$copyToBuffer$1
   4:	dup
   5:	aload_0
   6:	aload_1
   7:	invokespecial	#274; //Method scala/collection/generic/TraversableTemplate$$anonfun$copyToBuffer$1."<init>":(Lscala/collection/generic/TraversableTemplate;Lscala/collection/mutable/Buffer;)V
   10:	invokeinterface	#127,  2; //InterfaceMethod scala/collection/generic/TraversableTemplate.foreach:(Lscala/Function1;)V
   15:	return
  LineNumberTable: 
   line 648: 0

  LocalVariableTable: 
   Start  Length  Slot  Name   Signature
   0      16      0    $this       Lscala/collection/generic/TraversableTemplate;
   0      16      1    dest$1       Lscala/collection/mutable/Buffer;


public static scala.Tuple2 splitAt(scala.collection.generic.TraversableTemplate, int);
  Code:
   Stack=8, Locals=5, Args_size=2
   0:	aload_0
   1:	invokeinterface	#282,  1; //InterfaceMethod scala/collection/generic/TraversableTemplate.newBuilder:()Lscala/collection/generic/Builder;
   6:	astore_2
   7:	aload_0
   8:	invokeinterface	#282,  1; //InterfaceMethod scala/collection/generic/TraversableTemplate.newBuilder:()Lscala/collection/generic/Builder;
   13:	astore_3
   14:	new	#228; //class scala/runtime/IntRef
   17:	dup
   18:	iconst_0
   19:	invokespecial	#229; //Method scala/runtime/IntRef."<init>":(I)V
   22:	astore	4
   24:	aload_0
   25:	new	#284; //class scala/collection/generic/TraversableTemplate$$anonfun$splitAt$1
   28:	dup
   29:	aload_0
   30:	iload_1
   31:	aload_2
   32:	aload_3
   33:	aload	4
   35:	invokespecial	#287; //Method scala/collection/generic/TraversableTemplate$$anonfun$splitAt$1."<init>":(Lscala/collection/generic/TraversableTemplate;ILscala/collection/generic/Builder;Lscala/collection/generic/Builder;Lscala/runtime/IntRef;)V
   38:	invokeinterface	#127,  2; //InterfaceMethod scala/collection/generic/TraversableTemplate.foreach:(Lscala/Function1;)V
   43:	new	#289; //class scala/Tuple2
   46:	dup
   47:	aload_2
   48:	invokeinterface	#293,  1; //InterfaceMethod scala/collection/generic/Builder.result:()Ljava/lang/Object;
   53:	aload_3
   54:	invokeinterface	#293,  1; //InterfaceMethod scala/collection/generic/Builder.result:()Ljava/lang/Object;
   59:	invokespecial	#296; //Method scala/Tuple2."<init>":(Ljava/lang/Object;Ljava/lang/Object;)V
   62:	areturn
  LineNumberTable: 
   line 634: 0
   line 635: 14
   line 636: 24
   line 640: 43

  LocalVariableTable: 
   Start  Length  Slot  Name   Signature
   0      63      0    $this       Lscala/collection/generic/TraversableTemplate;
   0      63      1    n$3       I
   7      55      2    l$3       Lscala/collection/generic/Builder;
   14      48      3    r$3       Lscala/collection/generic/Builder;
   24      38      4    i$4       Lscala/runtime/IntRef;


public static scala.Tuple2 span(scala.collection.generic.TraversableTemplate, scala.Function1);
  Code:
   Stack=8, Locals=5, Args_size=2
   0:	aload_0
   1:	invokeinterface	#282,  1; //InterfaceMethod scala/collection/generic/TraversableTemplate.newBuilder:()Lscala/collection/generic/Builder;
   6:	astore_2
   7:	aload_0
   8:	invokeinterface	#282,  1; //InterfaceMethod scala/collection/generic/TraversableTemplate.newBuilder:()Lscala/collection/generic/Builder;
   13:	astore_3
   14:	new	#115; //class scala/runtime/BooleanRef
   17:	dup
   18:	iconst_1
   19:	invokespecial	#118; //Method scala/runtime/BooleanRef."<init>":(Z)V
   22:	astore	4
   24:	aload_0
   25:	new	#305; //class scala/collection/generic/TraversableTemplate$$anonfun$span$1
   28:	dup
   29:	aload_0
   30:	aload_1
   31:	aload_2
   32:	aload_3
   33:	aload	4
   35:	invokespecial	#308; //Method scala/collection/generic/TraversableTemplate$$anonfun$span$1."<init>":(Lscala/collection/generic/TraversableTemplate;Lscala/Function1;Lscala/collection/generic/Builder;Lscala/collection/generic/Builder;Lscala/runtime/BooleanRef;)V
   38:	invokeinterface	#127,  2; //InterfaceMethod scala/collection/generic/TraversableTemplate.foreach:(Lscala/Function1;)V
   43:	new	#289; //class scala/Tuple2
   46:	dup
   47:	aload_2
   48:	invokeinterface	#293,  1; //InterfaceMethod scala/collection/generic/Builder.result:()Ljava/lang/Object;
   53:	aload_3
   54:	invokeinterface	#293,  1; //InterfaceMethod scala/collection/generic/Builder.result:()Ljava/lang/Object;
   59:	invokespecial	#296; //Method scala/Tuple2."<init>":(Ljava/lang/Object;Ljava/lang/Object;)V
   62:	areturn
  LineNumberTable: 
   line 616: 0
   line 617: 14
   line 618: 24
   line 622: 43

  LocalVariableTable: 
   Start  Length  Slot  Name   Signature
   0      63      0    $this       Lscala/collection/generic/TraversableTemplate;
   0      63      1    p$3       Lscala/Function1;
   7      55      2    l$2       Lscala/collection/generic/Builder;
   14      48      3    r$2       Lscala/collection/generic/Builder;
   24      38      4    toLeft$1       Lscala/runtime/BooleanRef;


public static scala.collection.generic.TraversableTemplate dropWhile(scala.collection.generic.TraversableTemplate, scala.Function1);
  Code:
   Stack=7, Locals=5, Args_size=2
   0:	aload_0
   1:	invokeinterface	#282,  1; //InterfaceMethod scala/collection/generic/TraversableTemplate.newBuilder:()Lscala/collection/generic/Builder;
   6:	astore_2
   7:	new	#115; //class scala/runtime/BooleanRef
   10:	dup
   11:	iconst_0
   12:	invokespecial	#118; //Method scala/runtime/BooleanRef."<init>":(Z)V
   15:	astore_3
   16:	aload_0
   17:	new	#317; //class scala/collection/generic/TraversableTemplate$$anonfun$dropWhile$1
   20:	dup
   21:	aload_0
   22:	aload_1
   23:	aload_2
   24:	aload_3
   25:	invokespecial	#320; //Method scala/collection/generic/TraversableTemplate$$anonfun$dropWhile$1."<init>":(Lscala/collection/generic/TraversableTemplate;Lscala/Function1;Lscala/collection/generic/Builder;Lscala/runtime/BooleanRef;)V
   28:	invokeinterface	#127,  2; //InterfaceMethod scala/collection/generic/TraversableTemplate.foreach:(Lscala/Function1;)V
   33:	aload_2
   34:	invokeinterface	#293,  1; //InterfaceMethod scala/collection/generic/Builder.result:()Ljava/lang/Object;
   39:	astore	4
   41:	aload	4
   43:	instanceof	#13; //class scala/collection/generic/TraversableTemplate
   46:	ifeq	54
   49:	aload	4
   51:	goto	62
   54:	getstatic	#153; //Field scala/runtime/ScalaRunTime$.MODULE$:Lscala/runtime/ScalaRunTime$;
   57:	aload	4
   59:	invokevirtual	#157; //Method scala/runtime/ScalaRunTime$.boxArray:(Ljava/lang/Object;)Lscala/runtime/BoxedArray;
   62:	checkcast	#13; //class scala/collection/generic/TraversableTemplate
   65:	areturn
  LineNumberTable: 
   line 598: 0
   line 599: 7
   line 600: 16
   line 604: 33

  LocalVariableTable: 
   Start  Length  Slot  Name   Signature
   0      66      0    $this       Lscala/collection/generic/TraversableTemplate;
   0      66      1    p$2       Lscala/Function1;
   7      58      2    b$11       Lscala/collection/generic/Builder;
   16      49      3    go$1       Lscala/runtime/BooleanRef;


public static scala.collection.generic.TraversableTemplate takeWhile(scala.collection.generic.TraversableTemplate, scala.Function1);
  Code:
   Stack=6, Locals=4, Args_size=2
   0:	aload_0
   1:	invokeinterface	#282,  1; //InterfaceMethod scala/collection/generic/TraversableTemplate.newBuilder:()Lscala/collection/generic/Builder;
   6:	astore_2
   7:	getstatic	#248; //Field scala/collection/Traversable$.MODULE$:Lscala/collection/Traversable$;
   10:	invokevirtual	#252; //Method scala/collection/Traversable$.breaks:()Lscala/util/control/Breaks;
   13:	new	#326; //class scala/collection/generic/TraversableTemplate$$anonfun$takeWhile$1
   16:	dup
   17:	aload_0
   18:	aload_1
   19:	aload_2
   20:	invokespecial	#329; //Method scala/collection/generic/TraversableTemplate$$anonfun$takeWhile$1."<init>":(Lscala/collection/generic/TraversableTemplate;Lscala/Function1;Lscala/collection/generic/Builder;)V
   23:	invokevirtual	#263; //Method scala/util/control/Breaks.breakable:(Lscala/Function0;)V
   26:	aload_2
   27:	invokeinterface	#293,  1; //InterfaceMethod scala/collection/generic/Builder.result:()Ljava/lang/Object;
   32:	astore_3
   33:	aload_3
   34:	instanceof	#13; //class scala/collection/generic/TraversableTemplate
   37:	ifeq	44
   40:	aload_3
   41:	goto	51
   44:	getstatic	#153; //Field scala/runtime/ScalaRunTime$.MODULE$:Lscala/runtime/ScalaRunTime$;
   47:	aload_3
   48:	invokevirtual	#157; //Method scala/runtime/ScalaRunTime$.boxArray:(Ljava/lang/Object;)Lscala/runtime/BoxedArray;
   51:	checkcast	#13; //class scala/collection/generic/TraversableTemplate
   54:	areturn
  LineNumberTable: 
   line 581: 0
   line 582: 7
   line 583: 13
   line 582: 23
   line 588: 26

  LocalVariableTable: 
   Start  Length  Slot  Name   Signature
   0      55      0    $this       Lscala/collection/generic/TraversableTemplate;
   0      55      1    p$1       Lscala/Function1;
   7      47      2    b$10       Lscala/collection/generic/Builder;


public static scala.collection.generic.TraversableTemplate slice(scala.collection.generic.TraversableTemplate, int, int);
  Code:
   Stack=8, Locals=6, Args_size=3
   0:	aload_0
   1:	invokeinterface	#282,  1; //InterfaceMethod scala/collection/generic/TraversableTemplate.newBuilder:()Lscala/collection/generic/Builder;
   6:	astore_3
   7:	new	#228; //class scala/runtime/IntRef
   10:	dup
   11:	iconst_0
   12:	invokespecial	#229; //Method scala/runtime/IntRef."<init>":(I)V
   15:	astore	4
   17:	getstatic	#248; //Field scala/collection/Traversable$.MODULE$:Lscala/collection/Traversable$;
   20:	invokevirtual	#252; //Method scala/collection/Traversable$.breaks:()Lscala/util/control/Breaks;
   23:	new	#334; //class scala/collection/generic/TraversableTemplate$$anonfun$slice$1
   26:	dup
   27:	aload_0
   28:	iload_1
   29:	iload_2
   30:	aload_3
   31:	aload	4
   33:	invokespecial	#337; //Method scala/collection/generic/TraversableTemplate$$anonfun$slice$1."<init>":(Lscala/collection/generic/TraversableTemplate;IILscala/collection/generic/Builder;Lscala/runtime/IntRef;)V
   36:	invokevirtual	#263; //Method scala/util/control/Breaks.breakable:(Lscala/Function0;)V
   39:	aload_3
   40:	invokeinterface	#293,  1; //InterfaceMethod scala/collection/generic/Builder.result:()Ljava/lang/Object;
   45:	astore	5
   47:	aload	5
   49:	instanceof	#13; //class scala/collection/generic/TraversableTemplate
   52:	ifeq	60
   55:	aload	5
   57:	goto	68
   60:	getstatic	#153; //Field scala/runtime/ScalaRunTime$.MODULE$:Lscala/runtime/ScalaRunTime$;
   63:	aload	5
   65:	invokevirtual	#157; //Method scala/runtime/ScalaRunTime$.boxArray:(Ljava/lang/Object;)Lscala/runtime/BoxedArray;
   68:	checkcast	#13; //class scala/collection/generic/TraversableTemplate
   71:	areturn
  LineNumberTable: 
   line 562: 0
   line 563: 7
   line 564: 17
   line 565: 23
   line 564: 36
   line 571: 39

  LocalVariableTable: 
   Start  Length  Slot  Name   Signature
   0      72      0    $this       Lscala/collection/generic/TraversableTemplate;
   0      72      1    from$1       I
   0      72      2    until$1       I
   7      64      3    b$9       Lscala/collection/generic/Builder;
   17      54      4    i$3       Lscala/runtime/IntRef;


public static scala.collection.generic.TraversableTemplate drop(scala.collection.generic.TraversableTemplate, int);
  Code:
   Stack=7, Locals=5, Args_size=2
   0:	aload_0
   1:	invokeinterface	#282,  1; //InterfaceMethod scala/collection/generic/TraversableTemplate.newBuilder:()Lscala/collection/generic/Builder;
   6:	astore_2
   7:	new	#228; //class scala/runtime/IntRef
   10:	dup
   11:	iconst_0
   12:	invokespecial	#229; //Method scala/runtime/IntRef."<init>":(I)V
   15:	astore_3
   16:	aload_0
   17:	new	#345; //class scala/collection/generic/TraversableTemplate$$anonfun$drop$1
   20:	dup
   21:	aload_0
   22:	iload_1
   23:	aload_2
   24:	aload_3
   25:	invokespecial	#348; //Method scala/collection/generic/TraversableTemplate$$anonfun$drop$1."<init>":(Lscala/collection/generic/TraversableTemplate;ILscala/collection/generic/Builder;Lscala/runtime/IntRef;)V
   28:	invokeinterface	#127,  2; //InterfaceMethod scala/collection/generic/TraversableTemplate.foreach:(Lscala/Function1;)V
   33:	aload_2
   34:	invokeinterface	#293,  1; //InterfaceMethod scala/collection/generic/Builder.result:()Ljava/lang/Object;
   39:	astore	4
   41:	aload	4
   43:	instanceof	#13; //class scala/collection/generic/TraversableTemplate
   46:	ifeq	54
   49:	aload	4
   51:	goto	62
   54:	getstatic	#153; //Field scala/runtime/ScalaRunTime$.MODULE$:Lscala/runtime/ScalaRunTime$;
   57:	aload	4
   59:	invokevirtual	#157; //Method scala/runtime/ScalaRunTime$.boxArray:(Ljava/lang/Object;)Lscala/runtime/BoxedArray;
   62:	checkcast	#13; //class scala/collection/generic/TraversableTemplate
   65:	areturn
  LineNumberTable: 
   line 542: 0
   line 543: 7
   line 544: 16
   line 548: 33

  LocalVariableTable: 
   Start  Length  Slot  Name   Signature
   0      66      0    $this       Lscala/collection/generic/TraversableTemplate;
   0      66      1    n$2       I
   7      58      2    b$8       Lscala/collection/generic/Builder;
   16      49      3    i$2       Lscala/runtime/IntRef;


public static scala.collection.generic.TraversableTemplate take(scala.collection.generic.TraversableTemplate, int);
  Code:
   Stack=7, Locals=5, Args_size=2
   0:	aload_0
   1:	invokeinterface	#282,  1; //InterfaceMethod scala/collection/generic/TraversableTemplate.newBuilder:()Lscala/collection/generic/Builder;
   6:	astore_2
   7:	new	#228; //class scala/runtime/IntRef
   10:	dup
   11:	iconst_0
   12:	invokespecial	#229; //Method scala/runtime/IntRef."<init>":(I)V
   15:	astore_3
   16:	getstatic	#248; //Field scala/collection/Traversable$.MODULE$:Lscala/collection/Traversable$;
   19:	invokevirtual	#252; //Method scala/collection/Traversable$.breaks:()Lscala/util/control/Breaks;
   22:	new	#354; //class scala/collection/generic/TraversableTemplate$$anonfun$take$1
   25:	dup
   26:	aload_0
   27:	iload_1
   28:	aload_2
   29:	aload_3
   30:	invokespecial	#355; //Method scala/collection/generic/TraversableTemplate$$anonfun$take$1."<init>":(Lscala/collection/generic/TraversableTemplate;ILscala/collection/generic/Builder;Lscala/runtime/IntRef;)V
   33:	invokevirtual	#263; //Method scala/util/control/Breaks.breakable:(Lscala/Function0;)V
   36:	aload_2
   37:	invokeinterface	#293,  1; //InterfaceMethod scala/collection/generic/Builder.result:()Ljava/lang/Object;
   42:	astore	4
   44:	aload	4
   46:	instanceof	#13; //class scala/collection/generic/TraversableTemplate
   49:	ifeq	57
   52:	aload	4
   54:	goto	65
   57:	getstatic	#153; //Field scala/runtime/ScalaRunTime$.MODULE$:Lscala/runtime/ScalaRunTime$;
   60:	aload	4
   62:	invokevirtual	#157; //Method scala/runtime/ScalaRunTime$.boxArray:(Ljava/lang/Object;)Lscala/runtime/BoxedArray;
   65:	checkcast	#13; //class scala/collection/generic/TraversableTemplate
   68:	areturn
  LineNumberTable: 
   line 521: 0
   line 522: 7
   line 523: 16
   line 524: 22
   line 523: 33
   line 530: 36

  LocalVariableTable: 
   Start  Length  Slot  Name   Signature
   0      69      0    $this       Lscala/collection/generic/TraversableTemplate;
   0      69      1    n$1       I
   7      61      2    b$7       Lscala/collection/generic/Builder;
   16      52      3    i$1       Lscala/runtime/IntRef;


public static scala.collection.generic.TraversableTemplate init(scala.collection.generic.TraversableTemplate);
  Code:
   Stack=7, Locals=5, Args_size=1
   0:	aload_0
   1:	invokeinterface	#364,  1; //InterfaceMethod scala/collection/generic/TraversableTemplate.isEmpty:()Z
   6:	ifeq	20
   9:	new	#366; //class java/lang/UnsupportedOperationException
   12:	dup
   13:	ldc_w	#368; //String empty.init
   16:	invokespecial	#371; //Method java/lang/UnsupportedOperationException."<init>":(Ljava/lang/String;)V
   19:	athrow
   20:	new	#373; //class scala/runtime/ObjectRef
   23:	dup
   24:	aload_0
   25:	invokeinterface	#376,  1; //InterfaceMethod scala/collection/generic/TraversableTemplate.head:()Ljava/lang/Object;
   30:	invokespecial	#379; //Method scala/runtime/ObjectRef."<init>":(Ljava/lang/Object;)V
   33:	astore_1
   34:	new	#115; //class scala/runtime/BooleanRef
   37:	dup
   38:	iconst_0
   39:	invokespecial	#118; //Method scala/runtime/BooleanRef."<init>":(Z)V
   42:	astore_2
   43:	aload_0
   44:	invokeinterface	#282,  1; //InterfaceMethod scala/collection/generic/TraversableTemplate.newBuilder:()Lscala/collection/generic/Builder;
   49:	astore_3
   50:	aload_0
   51:	new	#381; //class scala/collection/generic/TraversableTemplate$$anonfun$init$1
   54:	dup
   55:	aload_0
   56:	aload_1
   57:	aload_2
   58:	aload_3
   59:	invokespecial	#384; //Method scala/collection/generic/TraversableTemplate$$anonfun$init$1."<init>":(Lscala/collection/generic/TraversableTemplate;Lscala/runtime/ObjectRef;Lscala/runtime/BooleanRef;Lscala/collection/generic/Builder;)V
   62:	invokeinterface	#127,  2; //InterfaceMethod scala/collection/generic/TraversableTemplate.foreach:(Lscala/Function1;)V
   67:	aload_3
   68:	invokeinterface	#293,  1; //InterfaceMethod scala/collection/generic/Builder.result:()Ljava/lang/Object;
   73:	astore	4
   75:	aload	4
   77:	instanceof	#13; //class scala/collection/generic/TraversableTemplate
   80:	ifeq	88
   83:	aload	4
   85:	goto	96
   88:	getstatic	#153; //Field scala/runtime/ScalaRunTime$.MODULE$:Lscala/runtime/ScalaRunTime$;
   91:	aload	4
   93:	invokevirtual	#157; //Method scala/runtime/ScalaRunTime$.boxArray:(Ljava/lang/Object;)Lscala/runtime/BoxedArray;
   96:	checkcast	#13; //class scala/collection/generic/TraversableTemplate
   99:	areturn
  LineNumberTable: 
   line 501: 0
   line 502: 20
   line 503: 34
   line 504: 43
   line 505: 50
   line 510: 67

  LocalVariableTable: 
   Start  Length  Slot  Name   Signature
   0      100      0    $this       Lscala/collection/generic/TraversableTemplate;
   34      65      1    lst$2       Lscala/runtime/ObjectRef;
   43      56      2    follow$1       Lscala/runtime/BooleanRef;
   50      49      3    b$6       Lscala/collection/generic/Builder;


public static scala.Option lastOption(scala.collection.generic.TraversableTemplate);
  Code:
   Stack=3, Locals=1, Args_size=1
   0:	aload_0
   1:	invokeinterface	#364,  1; //InterfaceMethod scala/collection/generic/TraversableTemplate.isEmpty:()Z
   6:	ifeq	15
   9:	getstatic	#395; //Field scala/None$.MODULE$:Lscala/None$;
   12:	goto	28
   15:	new	#397; //class scala/Some
   18:	dup
   19:	aload_0
   20:	invokeinterface	#400,  1; //InterfaceMethod scala/collection/generic/TraversableTemplate.last:()Ljava/lang/Object;
   25:	invokespecial	#401; //Method scala/Some."<init>":(Ljava/lang/Object;)V
   28:	areturn
  LineNumberTable: 
   line 494: 0

  LocalVariableTable: 
   Start  Length  Slot  Name   Signature
   0      29      0    $this       Lscala/collection/generic/TraversableTemplate;


public static java.lang.Object last(scala.collection.generic.TraversableTemplate);
  Code:
   Stack=5, Locals=2, Args_size=1
   0:	new	#373; //class scala/runtime/ObjectRef
   3:	dup
   4:	aload_0
   5:	invokeinterface	#376,  1; //InterfaceMethod scala/collection/generic/TraversableTemplate.head:()Ljava/lang/Object;
   10:	invokespecial	#379; //Method scala/runtime/ObjectRef."<init>":(Ljava/lang/Object;)V
   13:	astore_1
   14:	aload_0
   15:	new	#403; //class scala/collection/generic/TraversableTemplate$$anonfun$last$1
   18:	dup
   19:	aload_0
   20:	aload_1
   21:	invokespecial	#406; //Method scala/collection/generic/TraversableTemplate$$anonfun$last$1."<init>":(Lscala/collection/generic/TraversableTemplate;Lscala/runtime/ObjectRef;)V
   24:	invokeinterface	#127,  2; //InterfaceMethod scala/collection/generic/TraversableTemplate.foreach:(Lscala/Function1;)V
   29:	aload_1
   30:	getfield	#410; //Field scala/runtime/ObjectRef.elem:Ljava/lang/Object;
   33:	areturn
  LineNumberTable: 
   line 482: 0
   line 483: 14
   line 485: 29

  LocalVariableTable: 
   Start  Length  Slot  Name   Signature
   0      34      0    $this       Lscala/collection/generic/TraversableTemplate;
   14      19      1    lst$1       Lscala/runtime/ObjectRef;


public static scala.collection.generic.TraversableTemplate tail(scala.collection.generic.TraversableTemplate);
  Code:
   Stack=2, Locals=1, Args_size=1
   0:	aload_0
   1:	iconst_1
   2:	invokeinterface	#415,  2; //InterfaceMethod scala/collection/generic/TraversableTemplate.drop:(I)Lscala/collection/generic/TraversableTemplate;
   7:	areturn
  LineNumberTable: 
   line 474: 0

  LocalVariableTable: 
   Start  Length  Slot  Name   Signature
   0      8      0    $this       Lscala/collection/generic/TraversableTemplate;


public static scala.Option headOption(scala.collection.generic.TraversableTemplate);
  Code:
   Stack=3, Locals=1, Args_size=1
   0:	aload_0
   1:	invokeinterface	#364,  1; //InterfaceMethod scala/collection/generic/TraversableTemplate.isEmpty:()Z
   6:	ifeq	15
   9:	getstatic	#395; //Field scala/None$.MODULE$:Lscala/None$;
   12:	goto	28
   15:	new	#397; //class scala/Some
   18:	dup
   19:	aload_0
   20:	invokeinterface	#376,  1; //InterfaceMethod scala/collection/generic/TraversableTemplate.head:()Ljava/lang/Object;
   25:	invokespecial	#401; //Method scala/Some."<init>":(Ljava/lang/Object;)V
   28:	areturn
  LineNumberTable: 
   line 468: 0

  LocalVariableTable: 
   Start  Length  Slot  Name   Signature
   0      29      0    $this       Lscala/collection/generic/TraversableTemplate;


public static java.lang.Object head(scala.collection.generic.TraversableTemplate);
  Code:
   Stack=5, Locals=2, Args_size=1
   0:	new	#373; //class scala/runtime/ObjectRef
   3:	dup
   4:	new	#418; //class scala/collection/generic/TraversableTemplate$$anonfun$1
   7:	dup
   8:	aload_0
   9:	invokespecial	#419; //Method scala/collection/generic/TraversableTemplate$$anonfun$1."<init>":(Lscala/collection/generic/TraversableTemplate;)V
   12:	invokespecial	#379; //Method scala/runtime/ObjectRef."<init>":(Ljava/lang/Object;)V
   15:	astore_1
   16:	getstatic	#248; //Field scala/collection/Traversable$.MODULE$:Lscala/collection/Traversable$;
   19:	invokevirtual	#252; //Method scala/collection/Traversable$.breaks:()Lscala/util/control/Breaks;
   22:	new	#421; //class scala/collection/generic/TraversableTemplate$$anonfun$head$1
   25:	dup
   26:	aload_0
   27:	aload_1
   28:	invokespecial	#422; //Method scala/collection/generic/TraversableTemplate$$anonfun$head$1."<init>":(Lscala/collection/generic/TraversableTemplate;Lscala/runtime/ObjectRef;)V
   31:	invokevirtual	#263; //Method scala/util/control/Breaks.breakable:(Lscala/Function0;)V
   34:	aload_1
   35:	getfield	#410; //Field scala/runtime/ObjectRef.elem:Ljava/lang/Object;
   38:	checkcast	#424; //class scala/Function0
   41:	invokeinterface	#426,  1; //InterfaceMethod scala/Function0.apply:()Ljava/lang/Object;
   46:	areturn
  LineNumberTable: 
   line 454: 0
   line 455: 16
   line 456: 22
   line 455: 31
   line 461: 34

  LocalVariableTable: 
   Start  Length  Slot  Name   Signature
   0      47      0    $this       Lscala/collection/generic/TraversableTemplate;
   16      30      1    result$8       Lscala/runtime/ObjectRef;


public static scala.Option reduceRightOption(scala.collection.generic.TraversableTemplate, scala.Function2);
  Code:
   Stack=4, Locals=2, Args_size=2
   0:	aload_0
   1:	invokeinterface	#364,  1; //InterfaceMethod scala/collection/generic/TraversableTemplate.isEmpty:()Z
   6:	ifeq	15
   9:	getstatic	#395; //Field scala/None$.MODULE$:Lscala/None$;
   12:	goto	29
   15:	new	#397; //class scala/Some
   18:	dup
   19:	aload_0
   20:	aload_1
   21:	invokeinterface	#433,  2; //InterfaceMethod scala/collection/generic/TraversableTemplate.reduceRight:(Lscala/Function2;)Ljava/lang/Object;
   26:	invokespecial	#401; //Method scala/Some."<init>":(Ljava/lang/Object;)V
   29:	areturn
  LineNumberTable: 
   line 445: 0

  LocalVariableTable: 
   Start  Length  Slot  Name   Signature
   0      30      0    $this       Lscala/collection/generic/TraversableTemplate;
   0      30      1    op       Lscala/Function2;


public static java.lang.Object reduceRight(scala.collection.generic.TraversableTemplate, scala.Function2);
  Code:
   Stack=5, Locals=3, Args_size=2
   0:	aload_0
   1:	invokeinterface	#364,  1; //InterfaceMethod scala/collection/generic/TraversableTemplate.isEmpty:()Z
   6:	ifeq	20
   9:	new	#366; //class java/lang/UnsupportedOperationException
   12:	dup
   13:	ldc_w	#438; //String empty.reduceRight
   16:	invokespecial	#371; //Method java/lang/UnsupportedOperationException."<init>":(Ljava/lang/String;)V
   19:	athrow
   20:	new	#373; //class scala/runtime/ObjectRef
   23:	dup
   24:	getstatic	#443; //Field scala/collection/immutable/Nil$.MODULE$:Lscala/collection/immutable/Nil$;
   27:	invokespecial	#379; //Method scala/runtime/ObjectRef."<init>":(Ljava/lang/Object;)V
   30:	astore_2
   31:	aload_0
   32:	new	#445; //class scala/collection/generic/TraversableTemplate$$anonfun$reduceRight$1
   35:	dup
   36:	aload_0
   37:	aload_2
   38:	invokespecial	#446; //Method scala/collection/generic/TraversableTemplate$$anonfun$reduceRight$1."<init>":(Lscala/collection/generic/TraversableTemplate;Lscala/runtime/ObjectRef;)V
   41:	invokeinterface	#127,  2; //InterfaceMethod scala/collection/generic/TraversableTemplate.foreach:(Lscala/Function1;)V
   46:	aload_2
   47:	getfield	#410; //Field scala/runtime/ObjectRef.elem:Ljava/lang/Object;
   50:	checkcast	#179; //class scala/collection/immutable/List
   53:	new	#448; //class scala/collection/generic/TraversableTemplate$$anonfun$reduceRight$2
   56:	dup
   57:	aload_0
   58:	aload_1
   59:	invokespecial	#451; //Method scala/collection/generic/TraversableTemplate$$anonfun$reduceRight$2."<init>":(Lscala/collection/generic/TraversableTemplate;Lscala/Function2;)V
   62:	invokeinterface	#456,  2; //InterfaceMethod scala/collection/generic/LinearSequenceTemplate.reduceLeft:(Lscala/Function2;)Ljava/lang/Object;
   67:	areturn
  LineNumberTable: 
   line 430: 0
   line 431: 20
   line 432: 31
   line 433: 46

  LocalVariableTable: 
   Start  Length  Slot  Name   Signature
   0      68      0    $this       Lscala/collection/generic/TraversableTemplate;
   0      68      1    op$4       Lscala/Function2;
   31      36      2    elems$2       Lscala/runtime/ObjectRef;


public static scala.Option reduceLeftOption(scala.collection.generic.TraversableTemplate, scala.Function2);
  Code:
   Stack=4, Locals=2, Args_size=2
   0:	aload_0
   1:	invokeinterface	#364,  1; //InterfaceMethod scala/collection/generic/TraversableTemplate.isEmpty:()Z
   6:	ifeq	15
   9:	getstatic	#395; //Field scala/None$.MODULE$:Lscala/None$;
   12:	goto	29
   15:	new	#397; //class scala/Some
   18:	dup
   19:	aload_0
   20:	aload_1
   21:	invokeinterface	#460,  2; //InterfaceMethod scala/collection/generic/TraversableTemplate.reduceLeft:(Lscala/Function2;)Ljava/lang/Object;
   26:	invokespecial	#401; //Method scala/Some."<init>":(Ljava/lang/Object;)V
   29:	areturn
  LineNumberTable: 
   line 413: 0

  LocalVariableTable: 
   Start  Length  Slot  Name   Signature
   0      30      0    $this       Lscala/collection/generic/TraversableTemplate;
   0      30      1    op       Lscala/Function2;


public static java.lang.Object reduceLeft(scala.collection.generic.TraversableTemplate, scala.Function2);
  Code:
   Stack=7, Locals=4, Args_size=2
   0:	aload_0
   1:	invokeinterface	#364,  1; //InterfaceMethod scala/collection/generic/TraversableTemplate.isEmpty:()Z
   6:	ifeq	20
   9:	new	#366; //class java/lang/UnsupportedOperationException
   12:	dup
   13:	ldc_w	#462; //String empty.reduceLeft
   16:	invokespecial	#371; //Method java/lang/UnsupportedOperationException."<init>":(Ljava/lang/String;)V
   19:	athrow
   20:	new	#373; //class scala/runtime/ObjectRef
   23:	dup
   24:	aload_0
   25:	invokeinterface	#376,  1; //InterfaceMethod scala/collection/generic/TraversableTemplate.head:()Ljava/lang/Object;
   30:	invokespecial	#379; //Method scala/runtime/ObjectRef."<init>":(Ljava/lang/Object;)V
   33:	astore_2
   34:	new	#115; //class scala/runtime/BooleanRef
   37:	dup
   38:	iconst_1
   39:	invokespecial	#118; //Method scala/runtime/BooleanRef."<init>":(Z)V
   42:	astore_3
   43:	aload_0
   44:	new	#464; //class scala/collection/generic/TraversableTemplate$$anonfun$reduceLeft$1
   47:	dup
   48:	aload_0
   49:	aload_1
   50:	aload_2
   51:	aload_3
   52:	invokespecial	#467; //Method scala/collection/generic/TraversableTemplate$$anonfun$reduceLeft$1."<init>":(Lscala/collection/generic/TraversableTemplate;Lscala/Function2;Lscala/runtime/ObjectRef;Lscala/runtime/BooleanRef;)V
   55:	invokeinterface	#127,  2; //InterfaceMethod scala/collection/generic/TraversableTemplate.foreach:(Lscala/Function1;)V
   60:	aload_2
   61:	getfield	#410; //Field scala/runtime/ObjectRef.elem:Ljava/lang/Object;
   64:	areturn
  LineNumberTable: 
   line 395: 0
   line 396: 20
   line 397: 34
   line 398: 43
   line 401: 60

  LocalVariableTable: 
   Start  Length  Slot  Name   Signature
   0      65      0    $this       Lscala/collection/generic/TraversableTemplate;
   0      65      1    op$3       Lscala/Function2;
   34      30      2    result$7       Lscala/runtime/ObjectRef;
   43      21      3    first$1       Lscala/runtime/BooleanRef;


public static java.lang.Object $colon$bslash(scala.collection.generic.TraversableTemplate, java.lang.Object, scala.Function2);
  Code:
   Stack=3, Locals=3, Args_size=3
   0:	aload_0
   1:	aload_1
   2:	aload_2
   3:	invokeinterface	#476,  3; //InterfaceMethod scala/collection/generic/TraversableTemplate.foldRight:(Ljava/lang/Object;Lscala/Function2;)Ljava/lang/Object;
   8:	areturn
  LineNumberTable: 
   line 381: 0

  LocalVariableTable: 
   Start  Length  Slot  Name   Signature
   0      9      0    $this       Lscala/collection/generic/TraversableTemplate;
   0      9      1    z       Ljava/lang/Object;
   0      9      2    op       Lscala/Function2;


public static java.lang.Object foldRight(scala.collection.generic.TraversableTemplate, java.lang.Object, scala.Function2);
  Code:
   Stack=6, Locals=4, Args_size=3
   0:	new	#373; //class scala/runtime/ObjectRef
   3:	dup
   4:	getstatic	#443; //Field scala/collection/immutable/Nil$.MODULE$:Lscala/collection/immutable/Nil$;
   7:	invokespecial	#379; //Method scala/runtime/ObjectRef."<init>":(Ljava/lang/Object;)V
   10:	astore_3
   11:	aload_0
   12:	new	#479; //class scala/collection/generic/TraversableTemplate$$anonfun$foldRight$1
   15:	dup
   16:	aload_0
   17:	aload_3
   18:	invokespecial	#480; //Method scala/collection/generic/TraversableTemplate$$anonfun$foldRight$1."<init>":(Lscala/collection/generic/TraversableTemplate;Lscala/runtime/ObjectRef;)V
   21:	invokeinterface	#127,  2; //InterfaceMethod scala/collection/generic/TraversableTemplate.foreach:(Lscala/Function1;)V
   26:	aload_3
   27:	getfield	#410; //Field scala/runtime/ObjectRef.elem:Ljava/lang/Object;
   30:	checkcast	#179; //class scala/collection/immutable/List
   33:	aload_1
   34:	new	#482; //class scala/collection/generic/TraversableTemplate$$anonfun$foldRight$2
   37:	dup
   38:	aload_0
   39:	aload_2
   40:	invokespecial	#483; //Method scala/collection/generic/TraversableTemplate$$anonfun$foldRight$2."<init>":(Lscala/collection/generic/TraversableTemplate;Lscala/Function2;)V
   43:	invokeinterface	#486,  3; //InterfaceMethod scala/collection/generic/LinearSequenceTemplate.foldLeft:(Ljava/lang/Object;Lscala/Function2;)Ljava/lang/Object;
   48:	areturn
  LineNumberTable: 
   line 370: 0
   line 371: 11
   line 372: 26

  LocalVariableTable: 
   Start  Length  Slot  Name   Signature
   0      49      0    $this       Lscala/collection/generic/TraversableTemplate;
   0      49      1    z       Ljava/lang/Object;
   0      49      2    op$1       Lscala/Function2;
   11      37      3    elems$1       Lscala/runtime/ObjectRef;


public static java.lang.Object $div$colon(scala.collection.generic.TraversableTemplate, java.lang.Object, scala.Function2);
  Code:
   Stack=3, Locals=3, Args_size=3
   0:	aload_0
   1:	aload_1
   2:	aload_2
   3:	invokeinterface	#490,  3; //InterfaceMethod scala/collection/generic/TraversableTemplate.foldLeft:(Ljava/lang/Object;Lscala/Function2;)Ljava/lang/Object;
   8:	areturn
  LineNumberTable: 
   line 357: 0

  LocalVariableTable: 
   Start  Length  Slot  Name   Signature
   0      9      0    $this       Lscala/collection/generic/TraversableTemplate;
   0      9      1    z       Ljava/lang/Object;
   0      9      2    op       Lscala/Function2;


public static java.lang.Object foldLeft(scala.collection.generic.TraversableTemplate, java.lang.Object, scala.Function2);
  Code:
   Stack=6, Locals=4, Args_size=3
   0:	new	#373; //class scala/runtime/ObjectRef
   3:	dup
   4:	aload_1
   5:	invokespecial	#379; //Method scala/runtime/ObjectRef."<init>":(Ljava/lang/Object;)V
   8:	astore_3
   9:	aload_0
   10:	new	#492; //class scala/collection/generic/TraversableTemplate$$anonfun$foldLeft$1
   13:	dup
   14:	aload_0
   15:	aload_2
   16:	aload_3
   17:	invokespecial	#495; //Method scala/collection/generic/TraversableTemplate$$anonfun$foldLeft$1."<init>":(Lscala/collection/generic/TraversableTemplate;Lscala/Function2;Lscala/runtime/ObjectRef;)V
   20:	invokeinterface	#127,  2; //InterfaceMethod scala/collection/generic/TraversableTemplate.foreach:(Lscala/Function1;)V
   25:	aload_3
   26:	getfield	#410; //Field scala/runtime/ObjectRef.elem:Ljava/lang/Object;
   29:	areturn
  LineNumberTable: 
   line 344: 0
   line 345: 9
   line 347: 25

  LocalVariableTable: 
   Start  Length  Slot  Name   Signature
   0      30      0    $this       Lscala/collection/generic/TraversableTemplate;
   0      30      1    z       Ljava/lang/Object;
   0      30      2    op$2       Lscala/Function2;
   9      20      3    result$6       Lscala/runtime/ObjectRef;


public static scala.Option find(scala.collection.generic.TraversableTemplate, scala.Function1);
  Code:
   Stack=6, Locals=3, Args_size=2
   0:	new	#373; //class scala/runtime/ObjectRef
   3:	dup
   4:	getstatic	#395; //Field scala/None$.MODULE$:Lscala/None$;
   7:	invokespecial	#379; //Method scala/runtime/ObjectRef."<init>":(Ljava/lang/Object;)V
   10:	astore_2
   11:	getstatic	#248; //Field scala/collection/Traversable$.MODULE$:Lscala/collection/Traversable$;
   14:	invokevirtual	#252; //Method scala/collection/Traversable$.breaks:()Lscala/util/control/Breaks;
   17:	new	#501; //class scala/collection/generic/TraversableTemplate$$anonfun$find$1
   20:	dup
   21:	aload_0
   22:	aload_1
   23:	aload_2
   24:	invokespecial	#504; //Method scala/collection/generic/TraversableTemplate$$anonfun$find$1."<init>":(Lscala/collection/generic/TraversableTemplate;Lscala/Function1;Lscala/runtime/ObjectRef;)V
   27:	invokevirtual	#263; //Method scala/util/control/Breaks.breakable:(Lscala/Function0;)V
   30:	aload_2
   31:	getfield	#410; //Field scala/runtime/ObjectRef.elem:Ljava/lang/Object;
   34:	checkcast	#506; //class scala/Option
   37:	areturn
  LineNumberTable: 
   line 324: 0
   line 325: 11
   line 326: 17
   line 325: 27
   line 329: 30

  LocalVariableTable: 
   Start  Length  Slot  Name   Signature
   0      38      0    $this       Lscala/collection/generic/TraversableTemplate;
   0      38      1    p$9       Lscala/Function1;
   11      26      2    result$5       Lscala/runtime/ObjectRef;


public static int count(scala.collection.generic.TraversableTemplate, scala.Function1);
  Code:
   Stack=6, Locals=3, Args_size=2
   0:	new	#228; //class scala/runtime/IntRef
   3:	dup
   4:	iconst_0
   5:	invokespecial	#229; //Method scala/runtime/IntRef."<init>":(I)V
   8:	astore_2
   9:	aload_0
   10:	new	#512; //class scala/collection/generic/TraversableTemplate$$anonfun$count$1
   13:	dup
   14:	aload_0
   15:	aload_1
   16:	aload_2
   17:	invokespecial	#515; //Method scala/collection/generic/TraversableTemplate$$anonfun$count$1."<init>":(Lscala/collection/generic/TraversableTemplate;Lscala/Function1;Lscala/runtime/IntRef;)V
   20:	invokeinterface	#127,  2; //InterfaceMethod scala/collection/generic/TraversableTemplate.foreach:(Lscala/Function1;)V
   25:	aload_2
   26:	getfield	#517; //Field scala/runtime/IntRef.elem:I
   29:	ireturn
  LineNumberTable: 
   line 307: 0
   line 308: 9
   line 311: 25

  LocalVariableTable: 
   Start  Length  Slot  Name   Signature
   0      30      0    $this       Lscala/collection/generic/TraversableTemplate;
   0      30      1    p$5       Lscala/Function1;
   9      20      2    cnt$1       Lscala/runtime/IntRef;


public static boolean exists(scala.collection.generic.TraversableTemplate, scala.Function1);
  Code:
   Stack=6, Locals=3, Args_size=2
   0:	new	#115; //class scala/runtime/BooleanRef
   3:	dup
   4:	iconst_0
   5:	invokespecial	#118; //Method scala/runtime/BooleanRef."<init>":(Z)V
   8:	astore_2
   9:	getstatic	#248; //Field scala/collection/Traversable$.MODULE$:Lscala/collection/Traversable$;
   12:	invokevirtual	#252; //Method scala/collection/Traversable$.breaks:()Lscala/util/control/Breaks;
   15:	new	#523; //class scala/collection/generic/TraversableTemplate$$anonfun$exists$1
   18:	dup
   19:	aload_0
   20:	aload_1
   21:	aload_2
   22:	invokespecial	#526; //Method scala/collection/generic/TraversableTemplate$$anonfun$exists$1."<init>":(Lscala/collection/generic/TraversableTemplate;Lscala/Function1;Lscala/runtime/BooleanRef;)V
   25:	invokevirtual	#263; //Method scala/util/control/Breaks.breakable:(Lscala/Function0;)V
   28:	aload_2
   29:	getfield	#529; //Field scala/runtime/BooleanRef.elem:Z
   32:	ireturn
  LineNumberTable: 
   line 292: 0
   line 293: 9
   line 294: 15
   line 293: 25
   line 297: 28

  LocalVariableTable: 
   Start  Length  Slot  Name   Signature
   0      33      0    $this       Lscala/collection/generic/TraversableTemplate;
   0      33      1    p$8       Lscala/Function1;
   9      23      2    result$4       Lscala/runtime/BooleanRef;


public static boolean forall(scala.collection.generic.TraversableTemplate, scala.Function1);
  Code:
   Stack=6, Locals=3, Args_size=2
   0:	new	#115; //class scala/runtime/BooleanRef
   3:	dup
   4:	iconst_1
   5:	invokespecial	#118; //Method scala/runtime/BooleanRef."<init>":(Z)V
   8:	astore_2
   9:	getstatic	#248; //Field scala/collection/Traversable$.MODULE$:Lscala/collection/Traversable$;
   12:	invokevirtual	#252; //Method scala/collection/Traversable$.breaks:()Lscala/util/control/Breaks;
   15:	new	#534; //class scala/collection/generic/TraversableTemplate$$anonfun$forall$1
   18:	dup
   19:	aload_0
   20:	aload_1
   21:	aload_2
   22:	invokespecial	#535; //Method scala/collection/generic/TraversableTemplate$$anonfun$forall$1."<init>":(Lscala/collection/generic/TraversableTemplate;Lscala/Function1;Lscala/runtime/BooleanRef;)V
   25:	invokevirtual	#263; //Method scala/util/control/Breaks.breakable:(Lscala/Function0;)V
   28:	aload_2
   29:	getfield	#529; //Field scala/runtime/BooleanRef.elem:Z
   32:	ireturn
  LineNumberTable: 
   line 277: 0
   line 278: 9
   line 279: 15
   line 278: 25
   line 282: 28

  LocalVariableTable: 
   Start  Length  Slot  Name   Signature
   0      33      0    $this       Lscala/collection/generic/TraversableTemplate;
   0      33      1    p$6       Lscala/Function1;
   9      23      2    result$3       Lscala/runtime/BooleanRef;


public static scala.collection.Map groupBy(scala.collection.generic.TraversableTemplate, scala.Function1);
  Code:
   Stack=6, Locals=3, Args_size=2
   0:	new	#373; //class scala/runtime/ObjectRef
   3:	dup
   4:	getstatic	#544; //Field scala/collection/Map$.MODULE$:Lscala/collection/Map$;
   7:	getstatic	#153; //Field scala/runtime/ScalaRunTime$.MODULE$:Lscala/runtime/ScalaRunTime$;
   10:	iconst_0
   11:	anewarray	#289; //class scala/Tuple2
   14:	invokevirtual	#157; //Method scala/runtime/ScalaRunTime$.boxArray:(Ljava/lang/Object;)Lscala/runtime/BoxedArray;
   17:	invokevirtual	#547; //Method scala/collection/Map$.apply:(Lscala/collection/Sequence;)Lscala/collection/Map;
   20:	checkcast	#549; //class scala/collection/immutable/Map
   23:	invokespecial	#379; //Method scala/runtime/ObjectRef."<init>":(Ljava/lang/Object;)V
   26:	astore_2
   27:	aload_0
   28:	new	#551; //class scala/collection/generic/TraversableTemplate$$anonfun$groupBy$1
   31:	dup
   32:	aload_0
   33:	aload_1
   34:	aload_2
   35:	invokespecial	#552; //Method scala/collection/generic/TraversableTemplate$$anonfun$groupBy$1."<init>":(Lscala/collection/generic/TraversableTemplate;Lscala/Function1;Lscala/runtime/ObjectRef;)V
   38:	invokeinterface	#127,  2; //InterfaceMethod scala/collection/generic/TraversableTemplate.foreach:(Lscala/Function1;)V
   43:	aload_2
   44:	getfield	#410; //Field scala/runtime/ObjectRef.elem:Ljava/lang/Object;
   47:	checkcast	#549; //class scala/collection/immutable/Map
   50:	new	#554; //class scala/collection/generic/TraversableTemplate$$anonfun$groupBy$2
   53:	dup
   54:	aload_0
   55:	invokespecial	#555; //Method scala/collection/generic/TraversableTemplate$$anonfun$groupBy$2."<init>":(Lscala/collection/generic/TraversableTemplate;)V
   58:	invokeinterface	#561,  2; //InterfaceMethod scala/collection/generic/MapTemplate.mapValues:(Lscala/Function1;)Ljava/lang/Object;
   63:	checkcast	#563; //class scala/collection/Map
   66:	areturn
  LineNumberTable: 
   line 258: 0
   line 259: 27
   line 267: 43

  LocalVariableTable: 
   Start  Length  Slot  Name   Signature
   0      67      0    $this       Lscala/collection/generic/TraversableTemplate;
   0      67      1    f$3       Lscala/Function1;
   27      39      2    m$1       Lscala/runtime/ObjectRef;


public static scala.Tuple2 partition(scala.collection.generic.TraversableTemplate, scala.Function1);
  Code:
   Stack=7, Locals=4, Args_size=2
   0:	aload_0
   1:	invokeinterface	#282,  1; //InterfaceMethod scala/collection/generic/TraversableTemplate.newBuilder:()Lscala/collection/generic/Builder;
   6:	astore_2
   7:	aload_0
   8:	invokeinterface	#282,  1; //InterfaceMethod scala/collection/generic/TraversableTemplate.newBuilder:()Lscala/collection/generic/Builder;
   13:	astore_3
   14:	aload_0
   15:	new	#568; //class scala/collection/generic/TraversableTemplate$$anonfun$partition$1
   18:	dup
   19:	aload_0
   20:	aload_1
   21:	aload_2
   22:	aload_3
   23:	invokespecial	#571; //Method scala/collection/generic/TraversableTemplate$$anonfun$partition$1."<init>":(Lscala/collection/generic/TraversableTemplate;Lscala/Function1;Lscala/collection/generic/Builder;Lscala/collection/generic/Builder;)V
   26:	invokeinterface	#127,  2; //InterfaceMethod scala/collection/generic/TraversableTemplate.foreach:(Lscala/Function1;)V
   31:	new	#289; //class scala/Tuple2
   34:	dup
   35:	aload_2
   36:	invokeinterface	#293,  1; //InterfaceMethod scala/collection/generic/Builder.result:()Ljava/lang/Object;
   41:	aload_3
   42:	invokeinterface	#293,  1; //InterfaceMethod scala/collection/generic/Builder.result:()Ljava/lang/Object;
   47:	invokespecial	#296; //Method scala/Tuple2."<init>":(Ljava/lang/Object;Ljava/lang/Object;)V
   50:	areturn
  LineNumberTable: 
   line 244: 0
   line 245: 14
   line 246: 31

  LocalVariableTable: 
   Start  Length  Slot  Name   Signature
   0      51      0    $this       Lscala/collection/generic/TraversableTemplate;
   0      51      1    p$10       Lscala/Function1;
   7      43      2    l$1       Lscala/collection/generic/Builder;
   14      36      3    r$1       Lscala/collection/generic/Builder;


public static scala.collection.generic.TraversableTemplate remove(scala.collection.generic.TraversableTemplate, scala.Function1);
  Code:
   Stack=2, Locals=2, Args_size=2
   0:	aload_0
   1:	aload_1
   2:	invokeinterface	#579,  2; //InterfaceMethod scala/collection/generic/TraversableTemplate.filterNot:(Lscala/Function1;)Lscala/collection/generic/TraversableTemplate;
   7:	areturn
  LineNumberTable: 
   line 233: 0

  LocalVariableTable: 
   Start  Length  Slot  Name   Signature
   0      8      0    $this       Lscala/collection/generic/TraversableTemplate;
   0      8      1    p       Lscala/Function1;


public static scala.collection.generic.TraversableTemplate filterNot(scala.collection.generic.TraversableTemplate, scala.Function1);
  Code:
   Stack=5, Locals=2, Args_size=2
   0:	aload_0
   1:	new	#582; //class scala/collection/generic/TraversableTemplate$$anonfun$filterNot$1
   4:	dup
   5:	aload_0
   6:	aload_1
   7:	invokespecial	#585; //Method scala/collection/generic/TraversableTemplate$$anonfun$filterNot$1."<init>":(Lscala/collection/generic/TraversableTemplate;Lscala/Function1;)V
   10:	invokeinterface	#588,  2; //InterfaceMethod scala/collection/generic/TraversableTemplate.filter:(Lscala/Function1;)Lscala/collection/generic/TraversableTemplate;
   15:	areturn
  LineNumberTable: 
   line 224: 0

  LocalVariableTable: 
   Start  Length  Slot  Name   Signature
   0      16      0    $this       Lscala/collection/generic/TraversableTemplate;
   0      16      1    p$7       Lscala/Function1;


public static java.lang.Object filterMap(scala.collection.generic.TraversableTemplate, scala.PartialFunction, scala.collection.generic.BuilderFactory);
  Code:
   Stack=6, Locals=4, Args_size=3
   0:	aload_2
   1:	aload_0
   2:	invokeinterface	#37,  1; //InterfaceMethod scala/collection/generic/TraversableTemplate.thisCollection:()Lscala/collection/generic/TraversableTemplate;
   7:	invokeinterface	#596,  2; //InterfaceMethod scala/collection/generic/BuilderFactory.apply:(Ljava/lang/Object;)Lscala/collection/generic/Builder;
   12:	astore_3
   13:	aload_0
   14:	new	#598; //class scala/collection/generic/TraversableTemplate$$anonfun$filterMap$1
   17:	dup
   18:	aload_0
   19:	aload_1
   20:	aload_3
   21:	invokespecial	#601; //Method scala/collection/generic/TraversableTemplate$$anonfun$filterMap$1."<init>":(Lscala/collection/generic/TraversableTemplate;Lscala/PartialFunction;Lscala/collection/generic/Builder;)V
   24:	invokeinterface	#127,  2; //InterfaceMethod scala/collection/generic/TraversableTemplate.foreach:(Lscala/Function1;)V
   29:	aload_3
   30:	invokeinterface	#293,  1; //InterfaceMethod scala/collection/generic/Builder.result:()Ljava/lang/Object;
   35:	areturn
  LineNumberTable: 
   line 213: 0
   line 214: 13
   line 215: 29

  LocalVariableTable: 
   Start  Length  Slot  Name   Signature
   0      36      0    $this       Lscala/collection/generic/TraversableTemplate;
   0      36      1    pf$1       Lscala/PartialFunction;
   0      36      2    bf       Lscala/collection/generic/BuilderFactory;
   13      22      3    b$5       Lscala/collection/generic/Builder;


public static scala.collection.generic.TraversableTemplate filter(scala.collection.generic.TraversableTemplate, scala.Function1);
  Code:
   Stack=6, Locals=4, Args_size=2
   0:	aload_0
   1:	invokeinterface	#282,  1; //InterfaceMethod scala/collection/generic/TraversableTemplate.newBuilder:()Lscala/collection/generic/Builder;
   6:	astore_2
   7:	aload_0
   8:	new	#608; //class scala/collection/generic/TraversableTemplate$$anonfun$filter$1
   11:	dup
   12:	aload_0
   13:	aload_1
   14:	aload_2
   15:	invokespecial	#609; //Method scala/collection/generic/TraversableTemplate$$anonfun$filter$1."<init>":(Lscala/collection/generic/TraversableTemplate;Lscala/Function1;Lscala/collection/generic/Builder;)V
   18:	invokeinterface	#127,  2; //InterfaceMethod scala/collection/generic/TraversableTemplate.foreach:(Lscala/Function1;)V
   23:	aload_2
   24:	invokeinterface	#293,  1; //InterfaceMethod scala/collection/generic/Builder.result:()Ljava/lang/Object;
   29:	astore_3
   30:	aload_3
   31:	instanceof	#13; //class scala/collection/generic/TraversableTemplate
   34:	ifeq	41
   37:	aload_3
   38:	goto	48
   41:	getstatic	#153; //Field scala/runtime/ScalaRunTime$.MODULE$:Lscala/runtime/ScalaRunTime$;
   44:	aload_3
   45:	invokevirtual	#157; //Method scala/runtime/ScalaRunTime$.boxArray:(Ljava/lang/Object;)Lscala/runtime/BoxedArray;
   48:	checkcast	#13; //class scala/collection/generic/TraversableTemplate
   51:	areturn
  LineNumberTable: 
   line 199: 0
   line 200: 7
   line 202: 23

  LocalVariableTable: 
   Start  Length  Slot  Name   Signature
   0      52      0    $this       Lscala/collection/generic/TraversableTemplate;
   0      52      1    p$4       Lscala/Function1;
   7      44      2    b$4       Lscala/collection/generic/Builder;


public static java.lang.Object flatMap(scala.collection.generic.TraversableTemplate, scala.Function1, scala.collection.generic.BuilderFactory);
  Code:
   Stack=6, Locals=4, Args_size=3
   0:	aload_2
   1:	aload_0
   2:	invokeinterface	#37,  1; //InterfaceMethod scala/collection/generic/TraversableTemplate.thisCollection:()Lscala/collection/generic/TraversableTemplate;
   7:	invokeinterface	#596,  2; //InterfaceMethod scala/collection/generic/BuilderFactory.apply:(Ljava/lang/Object;)Lscala/collection/generic/Builder;
   12:	astore_3
   13:	aload_0
   14:	new	#615; //class scala/collection/generic/TraversableTemplate$$anonfun$flatMap$1
   17:	dup
   18:	aload_0
   19:	aload_1
   20:	aload_3
   21:	invokespecial	#616; //Method scala/collection/generic/TraversableTemplate$$anonfun$flatMap$1."<init>":(Lscala/collection/generic/TraversableTemplate;Lscala/Function1;Lscala/collection/generic/Builder;)V
   24:	invokeinterface	#127,  2; //InterfaceMethod scala/collection/generic/TraversableTemplate.foreach:(Lscala/Function1;)V
   29:	aload_3
   30:	invokeinterface	#293,  1; //InterfaceMethod scala/collection/generic/Builder.result:()Ljava/lang/Object;
   35:	areturn
  LineNumberTable: 
   line 188: 0
   line 189: 13
   line 190: 29

  LocalVariableTable: 
   Start  Length  Slot  Name   Signature
   0      36      0    $this       Lscala/collection/generic/TraversableTemplate;
   0      36      1    f$2       Lscala/Function1;
   0      36      2    bf       Lscala/collection/generic/BuilderFactory;
   13      22      3    b$3       Lscala/collection/generic/Builder;


public static java.lang.Object map(scala.collection.generic.TraversableTemplate, scala.Function1, scala.collection.generic.BuilderFactory);
  Code:
   Stack=6, Locals=4, Args_size=3
   0:	aload_2
   1:	aload_0
   2:	invokeinterface	#37,  1; //InterfaceMethod scala/collection/generic/TraversableTemplate.thisCollection:()Lscala/collection/generic/TraversableTemplate;
   7:	invokeinterface	#596,  2; //InterfaceMethod scala/collection/generic/BuilderFactory.apply:(Ljava/lang/Object;)Lscala/collection/generic/Builder;
   12:	astore_3
   13:	aload_0
   14:	new	#621; //class scala/collection/generic/TraversableTemplate$$anonfun$map$1
   17:	dup
   18:	aload_0
   19:	aload_1
   20:	aload_3
   21:	invokespecial	#622; //Method scala/collection/generic/TraversableTemplate$$anonfun$map$1."<init>":(Lscala/collection/generic/TraversableTemplate;Lscala/Function1;Lscala/collection/generic/Builder;)V
   24:	invokeinterface	#127,  2; //InterfaceMethod scala/collection/generic/TraversableTemplate.foreach:(Lscala/Function1;)V
   29:	aload_3
   30:	invokeinterface	#293,  1; //InterfaceMethod scala/collection/generic/Builder.result:()Ljava/lang/Object;
   35:	areturn
  LineNumberTable: 
   line 177: 0
   line 178: 13
   line 179: 29

  LocalVariableTable: 
   Start  Length  Slot  Name   Signature
   0      36      0    $this       Lscala/collection/generic/TraversableTemplate;
   0      36      1    f$1       Lscala/Function1;
   0      36      2    bf       Lscala/collection/generic/BuilderFactory;
   13      22      3    b$2       Lscala/collection/generic/Builder;


public static java.lang.Object $plus$plus(scala.collection.generic.TraversableTemplate, scala.collection.Iterator, scala.collection.generic.BuilderFactory);
  Code:
   Stack=2, Locals=4, Args_size=3
   0:	aload_2
   1:	aload_0
   2:	invokeinterface	#37,  1; //InterfaceMethod scala/collection/generic/TraversableTemplate.thisCollection:()Lscala/collection/generic/TraversableTemplate;
   7:	invokeinterface	#596,  2; //InterfaceMethod scala/collection/generic/BuilderFactory.apply:(Ljava/lang/Object;)Lscala/collection/generic/Builder;
   12:	astore_3
   13:	aload_3
   14:	aload_0
   15:	invokeinterface	#37,  1; //InterfaceMethod scala/collection/generic/TraversableTemplate.thisCollection:()Lscala/collection/generic/TraversableTemplate;
   20:	checkcast	#165; //class scala/collection/Traversable
   23:	invokeinterface	#197,  2; //InterfaceMethod scala/collection/generic/Growable.$plus$plus$eq:(Lscala/collection/Traversable;)Lscala/collection/generic/Growable;
   28:	pop
   29:	aload_3
   30:	aload_1
   31:	invokeinterface	#628,  2; //InterfaceMethod scala/collection/generic/Growable.$plus$plus$eq:(Lscala/collection/Iterator;)Lscala/collection/generic/Growable;
   36:	pop
   37:	aload_3
   38:	invokeinterface	#293,  1; //InterfaceMethod scala/collection/generic/Builder.result:()Ljava/lang/Object;
   43:	areturn
  LineNumberTable: 
   line 164: 0
   line 165: 13
   line 166: 29
   line 167: 37

  LocalVariableTable: 
   Start  Length  Slot  Name   Signature
   0      44      0    $this       Lscala/collection/generic/TraversableTemplate;
   0      44      1    that       Lscala/collection/Iterator;
   0      44      2    bf       Lscala/collection/generic/BuilderFactory;
   13      30      3    b       Lscala/collection/generic/Builder;


public static java.lang.Object $plus$plus(scala.collection.generic.TraversableTemplate, scala.collection.Traversable, scala.collection.generic.BuilderFactory);
  Code:
   Stack=2, Locals=4, Args_size=3
   0:	aload_2
   1:	aload_0
   2:	invokeinterface	#37,  1; //InterfaceMethod scala/collection/generic/TraversableTemplate.thisCollection:()Lscala/collection/generic/TraversableTemplate;
   7:	invokeinterface	#596,  2; //InterfaceMethod scala/collection/generic/BuilderFactory.apply:(Ljava/lang/Object;)Lscala/collection/generic/Builder;
   12:	astore_3
   13:	aload_3
   14:	aload_0
   15:	invokeinterface	#37,  1; //InterfaceMethod scala/collection/generic/TraversableTemplate.thisCollection:()Lscala/collection/generic/TraversableTemplate;
   20:	checkcast	#165; //class scala/collection/Traversable
   23:	invokeinterface	#197,  2; //InterfaceMethod scala/collection/generic/Growable.$plus$plus$eq:(Lscala/collection/Traversable;)Lscala/collection/generic/Growable;
   28:	pop
   29:	aload_3
   30:	aload_1
   31:	invokeinterface	#197,  2; //InterfaceMethod scala/collection/generic/Growable.$plus$plus$eq:(Lscala/collection/Traversable;)Lscala/collection/generic/Growable;
   36:	pop
   37:	aload_3
   38:	invokeinterface	#293,  1; //InterfaceMethod scala/collection/generic/Builder.result:()Ljava/lang/Object;
   43:	areturn
  LineNumberTable: 
   line 152: 0
   line 153: 13
   line 154: 29
   line 155: 37

  LocalVariableTable: 
   Start  Length  Slot  Name   Signature
   0      44      0    $this       Lscala/collection/generic/TraversableTemplate;
   0      44      1    that       Lscala/collection/Traversable;
   0      44      2    bf       Lscala/collection/generic/BuilderFactory;
   13      30      3    b       Lscala/collection/generic/Builder;


public static boolean hasDefiniteSize(scala.collection.generic.TraversableTemplate);
  Code:
   Stack=1, Locals=1, Args_size=1
   0:	iconst_1
   1:	ireturn
  LineNumberTable: 
   line 144: 0

  LocalVariableTable: 
   Start  Length  Slot  Name   Signature
   0      2      0    $this       Lscala/collection/generic/TraversableTemplate;


public static int size(scala.collection.generic.TraversableTemplate);
  Code:
   Stack=5, Locals=2, Args_size=1
   0:	new	#228; //class scala/runtime/IntRef
   3:	dup
   4:	iconst_0
   5:	invokespecial	#229; //Method scala/runtime/IntRef."<init>":(I)V
   8:	astore_1
   9:	aload_0
   10:	new	#637; //class scala/collection/generic/TraversableTemplate$$anonfun$size$1
   13:	dup
   14:	aload_0
   15:	aload_1
   16:	invokespecial	#640; //Method scala/collection/generic/TraversableTemplate$$anonfun$size$1."<init>":(Lscala/collection/generic/TraversableTemplate;Lscala/runtime/IntRef;)V
   19:	invokeinterface	#127,  2; //InterfaceMethod scala/collection/generic/TraversableTemplate.foreach:(Lscala/Function1;)V
   24:	aload_1
   25:	getfield	#517; //Field scala/runtime/IntRef.elem:I
   28:	ireturn
  LineNumberTable: 
   line 132: 0
   line 133: 9
   line 134: 24

  LocalVariableTable: 
   Start  Length  Slot  Name   Signature
   0      29      0    $this       Lscala/collection/generic/TraversableTemplate;
   9      19      1    result$2       Lscala/runtime/IntRef;


public static boolean nonEmpty(scala.collection.generic.TraversableTemplate);
  Code:
   Stack=1, Locals=1, Args_size=1
   0:	aload_0
   1:	invokeinterface	#364,  1; //InterfaceMethod scala/collection/generic/TraversableTemplate.isEmpty:()Z
   6:	ifeq	13
   9:	iconst_0
   10:	goto	14
   13:	iconst_1
   14:	ireturn
  LineNumberTable: 
   line 127: 0

  LocalVariableTable: 
   Start  Length  Slot  Name   Signature
   0      15      0    $this       Lscala/collection/generic/TraversableTemplate;


public static boolean isEmpty(scala.collection.generic.TraversableTemplate);
  Code:
   Stack=5, Locals=2, Args_size=1
   0:	new	#115; //class scala/runtime/BooleanRef
   3:	dup
   4:	iconst_1
   5:	invokespecial	#118; //Method scala/runtime/BooleanRef."<init>":(Z)V
   8:	astore_1
   9:	getstatic	#248; //Field scala/collection/Traversable$.MODULE$:Lscala/collection/Traversable$;
   12:	invokevirtual	#252; //Method scala/collection/Traversable$.breaks:()Lscala/util/control/Breaks;
   15:	new	#644; //class scala/collection/generic/TraversableTemplate$$anonfun$isEmpty$1
   18:	dup
   19:	aload_0
   20:	aload_1
   21:	invokespecial	#647; //Method scala/collection/generic/TraversableTemplate$$anonfun$isEmpty$1."<init>":(Lscala/collection/generic/TraversableTemplate;Lscala/runtime/BooleanRef;)V
   24:	invokevirtual	#263; //Method scala/util/control/Breaks.breakable:(Lscala/Function0;)V
   27:	aload_1
   28:	getfield	#529; //Field scala/runtime/BooleanRef.elem:Z
   31:	ireturn
  LineNumberTable: 
   line 115: 0
   line 116: 9
   line 117: 15
   line 116: 24
   line 122: 27

  LocalVariableTable: 
   Start  Length  Slot  Name   Signature
   0      32      0    $this       Lscala/collection/generic/TraversableTemplate;
   9      22      1    result$1       Lscala/runtime/BooleanRef;


public static scala.collection.generic.TraversableTemplate thisCollection(scala.collection.generic.TraversableTemplate);
  Code:
   Stack=1, Locals=1, Args_size=1
   0:	aload_0
   1:	areturn
  LineNumberTable: 
   line 95: 0

  LocalVariableTable: 
   Start  Length  Slot  Name   Signature
   0      2      0    $this       Lscala/collection/generic/TraversableTemplate;


}

