Compiled from "TraversableViewTemplate.scala"
public abstract class scala.collection.generic.TraversableViewTemplate$Sliced$class extends java.lang.Object
  SourceFile: "TraversableViewTemplate.scala"
  Scala: length = 0x
   
  InnerClass: 
   public abstract #102= #46 of #29; //Sliced=class scala/collection/generic/TraversableViewTemplate$Sliced of class scala/collection/generic/TraversableViewTemplate
   public abstract #105= #104 of #29; //Transformed=class scala/collection/generic/TraversableViewTemplate$Transformed of class scala/collection/generic/TraversableViewTemplate
   public final #106= #76 of #46; //$anonfun$foreach$1=class scala/collection/generic/TraversableViewTemplate$Sliced$$anonfun$foreach$1 of class scala/collection/generic/TraversableViewTemplate$Sliced
  minor version: 0
  major version: 49
  Constant pool:
const #1 = Asciz	SourceFile;
const #2 = Asciz	TraversableViewTemplate.scala;
const #3 = Asciz	$init$;
const #4 = Asciz	(Lscala/collection/generic/TraversableViewTemplate$Sliced;)V;
const #5 = Asciz	Code;
const #6 = Asciz	LineNumberTable;
const #7 = Asciz	$this;
const #8 = Asciz	Lscala/collection/generic/TraversableViewTemplate$Sliced;;
const #9 = Asciz	LocalVariableTable;
const #10 = Asciz	slice;
const #11 = Asciz	(Lscala/collection/generic/TraversableViewTemplate$Sliced;II)Lscala/collection/generic/TraversableView;;
const #12 = Asciz	scala/Predef$;
const #13 = class	#12;	//  scala/Predef$
const #14 = Asciz	MODULE$;
const #15 = Asciz	Lscala/Predef$;;
const #16 = NameAndType	#14:#15;//  MODULE$:Lscala/Predef$;
const #17 = Field	#13.#16;	//  scala/Predef$.MODULE$:Lscala/Predef$;
const #18 = Asciz	intWrapper;
const #19 = Asciz	(I)Lscala/runtime/RichInt;;
const #20 = NameAndType	#18:#19;//  intWrapper:(I)Lscala/runtime/RichInt;
const #21 = Method	#13.#20;	//  scala/Predef$.intWrapper:(I)Lscala/runtime/RichInt;
const #22 = Asciz	scala/runtime/RichInt;
const #23 = class	#22;	//  scala/runtime/RichInt
const #24 = Asciz	max;
const #25 = Asciz	(I)I;
const #26 = NameAndType	#24:#25;//  max:(I)I
const #27 = Method	#23.#26;	//  scala/runtime/RichInt.max:(I)I
const #28 = Asciz	scala/collection/generic/TraversableViewTemplate;
const #29 = class	#28;	//  scala/collection/generic/TraversableViewTemplate
const #30 = Asciz	newSliced;
const #31 = Asciz	(II)Lscala/collection/generic/TraversableViewTemplate$Transformed;;
const #32 = NameAndType	#30:#31;//  newSliced:(II)Lscala/collection/generic/TraversableViewTemplate$Transformed;
const #33 = InterfaceMethod	#29.#32;	//  scala/collection/generic/TraversableViewTemplate.newSliced:(II)Lscala/collection/generic/TraversableViewTemplate$Transformed;
const #34 = Asciz	from1;
const #35 = Asciz	I;
const #36 = Asciz	until1;
const #37 = Asciz	stringPrefix;
const #38 = Asciz	(Lscala/collection/generic/TraversableViewTemplate$Sliced;)Ljava/lang/String;;
const #39 = Asciz	scala/collection/mutable/StringBuilder;
const #40 = class	#39;	//  scala/collection/mutable/StringBuilder
const #41 = Asciz	<init>;
const #42 = Asciz	()V;
const #43 = NameAndType	#41:#42;//  "<init>":()V
const #44 = Method	#40.#43;	//  scala/collection/mutable/StringBuilder."<init>":()V
const #45 = Asciz	scala/collection/generic/TraversableViewTemplate$Sliced;
const #46 = class	#45;	//  scala/collection/generic/TraversableViewTemplate$Sliced
const #47 = Asciz	scala$collection$generic$TraversableViewTemplate$Sliced$$$outer;
const #48 = Asciz	()Lscala/collection/generic/TraversableViewTemplate;;
const #49 = NameAndType	#47:#48;//  scala$collection$generic$TraversableViewTemplate$Sliced$$$outer:()Lscala/collection/generic/TraversableViewTemplate;
const #50 = InterfaceMethod	#46.#49;	//  scala/collection/generic/TraversableViewTemplate$Sliced.scala$collection$generic$TraversableViewTemplate$Sliced$$$outer:()Lscala/collection/generic/TraversableViewTemplate;
const #51 = Asciz	scala/collection/generic/TraversableTemplate;
const #52 = class	#51;	//  scala/collection/generic/TraversableTemplate
const #53 = Asciz	()Ljava/lang/String;;
const #54 = NameAndType	#37:#53;//  stringPrefix:()Ljava/lang/String;
const #55 = InterfaceMethod	#52.#54;	//  scala/collection/generic/TraversableTemplate.stringPrefix:()Ljava/lang/String;
const #56 = Asciz	append;
const #57 = Asciz	(Ljava/lang/Object;)Lscala/collection/mutable/StringBuilder;;
const #58 = NameAndType	#56:#57;//  append:(Ljava/lang/Object;)Lscala/collection/mutable/StringBuilder;
const #59 = Method	#40.#58;	//  scala/collection/mutable/StringBuilder.append:(Ljava/lang/Object;)Lscala/collection/mutable/StringBuilder;
const #60 = Asciz	S;
const #61 = String	#60;	//  S
const #62 = Asciz	toString;
const #63 = NameAndType	#62:#53;//  toString:()Ljava/lang/String;
const #64 = Method	#40.#63;	//  scala/collection/mutable/StringBuilder.toString:()Ljava/lang/String;
const #65 = Asciz	foreach;
const #66 = Asciz	(Lscala/collection/generic/TraversableViewTemplate$Sliced;Lscala/Function1;)V;
const #67 = Asciz	java/lang/Object;
const #68 = class	#67;	//  java/lang/Object
const #69 = Method	#68.#43;	//  java/lang/Object."<init>":()V
const #70 = Asciz	scala/runtime/IntRef;
const #71 = class	#70;	//  scala/runtime/IntRef
const #72 = Asciz	(I)V;
const #73 = NameAndType	#41:#72;//  "<init>":(I)V
const #74 = Method	#71.#73;	//  scala/runtime/IntRef."<init>":(I)V
const #75 = Asciz	scala/collection/generic/TraversableViewTemplate$Sliced$$anonfun$foreach$1;
const #76 = class	#75;	//  scala/collection/generic/TraversableViewTemplate$Sliced$$anonfun$foreach$1
const #77 = Asciz	(Lscala/collection/generic/TraversableViewTemplate$Sliced;Lscala/Function1;Lscala/runtime/IntRef;Ljava/lang/Object;)V;
const #78 = NameAndType	#41:#77;//  "<init>":(Lscala/collection/generic/TraversableViewTemplate$Sliced;Lscala/Function1;Lscala/runtime/IntRef;Ljava/lang/Object;)V
const #79 = Method	#76.#78;	//  scala/collection/generic/TraversableViewTemplate$Sliced$$anonfun$foreach$1."<init>":(Lscala/collection/generic/TraversableViewTemplate$Sliced;Lscala/Function1;Lscala/runtime/IntRef;Ljava/lang/Object;)V
const #80 = Asciz	scala/collection/generic/TraversableClass;
const #81 = class	#80;	//  scala/collection/generic/TraversableClass
const #82 = Asciz	(Lscala/Function1;)V;
const #83 = NameAndType	#65:#82;//  foreach:(Lscala/Function1;)V
const #84 = InterfaceMethod	#81.#83;	//  scala/collection/generic/TraversableClass.foreach:(Lscala/Function1;)V
const #85 = Asciz	scala/runtime/NonLocalReturnException;
const #86 = class	#85;	//  scala/runtime/NonLocalReturnException
const #87 = Asciz	key;
const #88 = Asciz	()Ljava/lang/Object;;
const #89 = NameAndType	#87:#88;//  key:()Ljava/lang/Object;
const #90 = Method	#86.#89;	//  scala/runtime/NonLocalReturnException.key:()Ljava/lang/Object;
const #91 = Asciz	value;
const #92 = NameAndType	#91:#88;//  value:()Ljava/lang/Object;
const #93 = Method	#86.#92;	//  scala/runtime/NonLocalReturnException.value:()Ljava/lang/Object;
const #94 = Asciz	scala/runtime/BoxedUnit;
const #95 = class	#94;	//  scala/runtime/BoxedUnit
const #96 = Asciz	f$3;
const #97 = Asciz	Lscala/Function1;;
const #98 = Asciz	index$1;
const #99 = Asciz	Lscala/runtime/IntRef;;
const #100 = Asciz	Scala;
const #101 = Asciz	InnerClasses;
const #102 = Asciz	Sliced;
const #103 = Asciz	scala/collection/generic/TraversableViewTemplate$Transformed;
const #104 = class	#103;	//  scala/collection/generic/TraversableViewTemplate$Transformed
const #105 = Asciz	Transformed;
const #106 = Asciz	$anonfun$foreach$1;
const #107 = Asciz	scala/collection/generic/TraversableViewTemplate$Sliced$class;
const #108 = class	#107;	//  scala/collection/generic/TraversableViewTemplate$Sliced$class

{
public static void $init$(scala.collection.generic.TraversableViewTemplate$Sliced);
  Code:
   Stack=0, Locals=1, Args_size=1
   0:	return
  LineNumberTable: 
   line 56: 0

  LocalVariableTable: 
   Start  Length  Slot  Name   Signature
   0      1      0    $this       Lscala/collection/generic/TraversableViewTemplate$Sliced;


public static scala.collection.generic.TraversableView slice(scala.collection.generic.TraversableViewTemplate$Sliced, int, int);
  Code:
   Stack=4, Locals=3, Args_size=3
   0:	aload_0
   1:	getstatic	#17; //Field scala/Predef$.MODULE$:Lscala/Predef$;
   4:	iload_1
   5:	invokevirtual	#21; //Method scala/Predef$.intWrapper:(I)Lscala/runtime/RichInt;
   8:	iconst_0
   9:	invokevirtual	#27; //Method scala/runtime/RichInt.max:(I)I
   12:	getstatic	#17; //Field scala/Predef$.MODULE$:Lscala/Predef$;
   15:	iload_2
   16:	invokevirtual	#21; //Method scala/Predef$.intWrapper:(I)Lscala/runtime/RichInt;
   19:	iconst_0
   20:	invokevirtual	#27; //Method scala/runtime/RichInt.max:(I)I
   23:	invokeinterface	#33,  3; //InterfaceMethod scala/collection/generic/TraversableViewTemplate.newSliced:(II)Lscala/collection/generic/TraversableViewTemplate$Transformed;
   28:	areturn
  LineNumberTable: 
   line 71: 0

  LocalVariableTable: 
   Start  Length  Slot  Name   Signature
   0      29      0    $this       Lscala/collection/generic/TraversableViewTemplate$Sliced;
   0      29      1    from1       I
   0      29      2    until1       I


public static java.lang.String stringPrefix(scala.collection.generic.TraversableViewTemplate$Sliced);
  Code:
   Stack=2, Locals=1, Args_size=1
   0:	new	#40; //class scala/collection/mutable/StringBuilder
   3:	dup
   4:	invokespecial	#44; //Method scala/collection/mutable/StringBuilder."<init>":()V
   7:	aload_0
   8:	invokeinterface	#50,  1; //InterfaceMethod scala/collection/generic/TraversableViewTemplate$Sliced.scala$collection$generic$TraversableViewTemplate$Sliced$$$outer:()Lscala/collection/generic/TraversableViewTemplate;
   13:	invokeinterface	#55,  1; //InterfaceMethod scala/collection/generic/TraversableTemplate.stringPrefix:()Ljava/lang/String;
   18:	invokevirtual	#59; //Method scala/collection/mutable/StringBuilder.append:(Ljava/lang/Object;)Lscala/collection/mutable/StringBuilder;
   21:	ldc	#61; //String S
   23:	invokevirtual	#59; //Method scala/collection/mutable/StringBuilder.append:(Ljava/lang/Object;)Lscala/collection/mutable/StringBuilder;
   26:	invokevirtual	#64; //Method scala/collection/mutable/StringBuilder.toString:()Ljava/lang/String;
   29:	areturn
  LineNumberTable: 
   line 69: 0

  LocalVariableTable: 
   Start  Length  Slot  Name   Signature
   0      30      0    $this       Lscala/collection/generic/TraversableViewTemplate$Sliced;


public static void foreach(scala.collection.generic.TraversableViewTemplate$Sliced, scala.Function1);
  Code:
   Stack=7, Locals=5, Args_size=2
   0:	new	#68; //class java/lang/Object
   3:	dup
   4:	invokespecial	#69; //Method java/lang/Object."<init>":()V
   7:	astore_2
   8:	new	#71; //class scala/runtime/IntRef
   11:	dup
   12:	iconst_0
   13:	invokespecial	#74; //Method scala/runtime/IntRef."<init>":(I)V
   16:	astore	4
   18:	aload_0
   19:	invokeinterface	#50,  1; //InterfaceMethod scala/collection/generic/TraversableViewTemplate$Sliced.scala$collection$generic$TraversableViewTemplate$Sliced$$$outer:()Lscala/collection/generic/TraversableViewTemplate;
   24:	new	#76; //class scala/collection/generic/TraversableViewTemplate$Sliced$$anonfun$foreach$1
   27:	dup
   28:	aload_0
   29:	aload_1
   30:	aload	4
   32:	aload_2
   33:	invokespecial	#79; //Method scala/collection/generic/TraversableViewTemplate$Sliced$$anonfun$foreach$1."<init>":(Lscala/collection/generic/TraversableViewTemplate$Sliced;Lscala/Function1;Lscala/runtime/IntRef;Ljava/lang/Object;)V
   36:	invokeinterface	#84,  2; //InterfaceMethod scala/collection/generic/TraversableClass.foreach:(Lscala/Function1;)V
   41:	goto	61
   44:	astore_3
   45:	aload_3
   46:	invokevirtual	#90; //Method scala/runtime/NonLocalReturnException.key:()Ljava/lang/Object;
   49:	aload_2
   50:	if_acmpne	62
   53:	aload_3
   54:	invokevirtual	#93; //Method scala/runtime/NonLocalReturnException.value:()Ljava/lang/Object;
   57:	checkcast	#95; //class scala/runtime/BoxedUnit
   60:	pop
   61:	return
   62:	aload_3
   63:	athrow
  Exception table:
   from   to  target type
     8    44    44   Class scala/runtime/NonLocalReturnException

  LineNumberTable: 
   line 59: 0
   line 60: 8
   line 61: 18
   line 59: 44

  LocalVariableTable: 
   Start  Length  Slot  Name   Signature
   0      64      0    $this       Lscala/collection/generic/TraversableViewTemplate$Sliced;
   0      64      1    f$3       Lscala/Function1;
   18      23      4    index$1       Lscala/runtime/IntRef;


}

