Compiled from "VectorView.scala"
public final class scala.collection.generic.VectorView$ extends java.lang.Object implements scala.ScalaObject
  SourceFile: "VectorView.scala"
  Scala: length = 0x
   
  InnerClass: 
   public final #30= #23 of #29; //$anon$1=class scala/collection/generic/VectorView$$anon$1 of class scala/collection/generic/VectorView
  minor version: 0
  major version: 49
  Constant pool:
const #1 = Asciz	SourceFile;
const #2 = Asciz	VectorView.scala;
const #3 = Asciz	Scala;
const #4 = Asciz	MODULE$;
const #5 = Asciz	Lscala/collection/generic/VectorView$;;
const #6 = Asciz	<clinit>;
const #7 = Asciz	()V;
const #8 = Asciz	Code;
const #9 = Asciz	scala/collection/generic/VectorView$;
const #10 = class	#9;	//  scala/collection/generic/VectorView$
const #11 = Asciz	<init>;
const #12 = NameAndType	#11:#7;//  "<init>":()V
const #13 = Method	#10.#12;	//  scala/collection/generic/VectorView$."<init>":()V
const #14 = Asciz	LineNumberTable;
const #15 = Asciz	java/lang/Object;
const #16 = class	#15;	//  java/lang/Object
const #17 = Method	#16.#12;	//  java/lang/Object."<init>":()V
const #18 = NameAndType	#4:#5;//  MODULE$:Lscala/collection/generic/VectorView$;
const #19 = Field	#10.#18;	//  scala/collection/generic/VectorView$.MODULE$:Lscala/collection/generic/VectorView$;
const #20 = Asciz	builderFactory;
const #21 = Asciz	()Lscala/collection/generic/BuilderFactory;;
const #22 = Asciz	scala/collection/generic/VectorView$$anon$1;
const #23 = class	#22;	//  scala/collection/generic/VectorView$$anon$1
const #24 = Method	#23.#12;	//  scala/collection/generic/VectorView$$anon$1."<init>":()V
const #25 = Asciz	<A:Ljava/lang/Object;>()Lscala/collection/generic/BuilderFactory<TA;Lscala/collection/generic/VectorView<TA;Lscala/collection/Vector<*>;>;Lscala/collection/generic/TraversableView<**>;>;;
const #26 = Asciz	Signature;
const #27 = Asciz	InnerClasses;
const #28 = Asciz	scala/collection/generic/VectorView;
const #29 = class	#28;	//  scala/collection/generic/VectorView
const #30 = Asciz	$anon$1;
const #31 = Asciz	scala/ScalaObject;
const #32 = class	#31;	//  scala/ScalaObject

{
public static final scala.collection.generic.VectorView$ MODULE$;

public static {};
  Code:
   Stack=1, Locals=0, Args_size=0
   0:	new	#10; //class scala/collection/generic/VectorView$
   3:	invokespecial	#13; //Method "<init>":()V
   6:	return

public scala.collection.generic.BuilderFactory builderFactory();
  Code:
   Stack=2, Locals=1, Args_size=1
   0:	new	#23; //class scala/collection/generic/VectorView$$anon$1
   3:	dup
   4:	invokespecial	#24; //Method scala/collection/generic/VectorView$$anon$1."<init>":()V
   7:	areturn
  LineNumberTable: 
   line 27: 0

  Signature: length = 0x2
   00 19 

}

