Compiled from "VectorViewTemplate.scala"
public abstract class scala.collection.generic.VectorViewTemplate$class extends java.lang.Object
  SourceFile: "VectorViewTemplate.scala"
  Scala: length = 0x
   
  InnerClass: 
   public final #88= #34 of #87; //$anon$8=class scala/collection/generic/VectorViewTemplate$$anon$8 of class scala/collection/generic/VectorViewTemplate
   public final #89= #62 of #87; //$anon$4=class scala/collection/generic/VectorViewTemplate$$anon$4 of class scala/collection/generic/VectorViewTemplate
   public final #90= #48 of #87; //$anon$6=class scala/collection/generic/VectorViewTemplate$$anon$6 of class scala/collection/generic/VectorViewTemplate
   public final #91= #72 of #87; //$anon$2=class scala/collection/generic/VectorViewTemplate$$anon$2 of class scala/collection/generic/VectorViewTemplate
   public final #92= #40 of #87; //$anon$7=class scala/collection/generic/VectorViewTemplate$$anon$7 of class scala/collection/generic/VectorViewTemplate
   public final #93= #67 of #87; //$anon$3=class scala/collection/generic/VectorViewTemplate$$anon$3 of class scala/collection/generic/VectorViewTemplate
   public final #94= #54 of #87; //$anon$5=class scala/collection/generic/VectorViewTemplate$$anon$5 of class scala/collection/generic/VectorViewTemplate
   public final #95= #23 of #87; //$anon$9=class scala/collection/generic/VectorViewTemplate$$anon$9 of class scala/collection/generic/VectorViewTemplate
   public final #96= #78 of #87; //$anon$1=class scala/collection/generic/VectorViewTemplate$$anon$1 of class scala/collection/generic/VectorViewTemplate
   public final #97= #13 of #87; //$anon$10=class scala/collection/generic/VectorViewTemplate$$anon$10 of class scala/collection/generic/VectorViewTemplate
   public abstract #100= #99 of #87; //Transformed=class scala/collection/generic/VectorViewTemplate$Transformed of class scala/collection/generic/VectorViewTemplate
  minor version: 0
  major version: 49
  Constant pool:
const #1 = Asciz	SourceFile;
const #2 = Asciz	VectorViewTemplate.scala;
const #3 = Asciz	$init$;
const #4 = Asciz	(Lscala/collection/generic/VectorViewTemplate;)V;
const #5 = Asciz	Code;
const #6 = Asciz	LineNumberTable;
const #7 = Asciz	$this;
const #8 = Asciz	Lscala/collection/generic/VectorViewTemplate;;
const #9 = Asciz	LocalVariableTable;
const #10 = Asciz	newZipped;
const #11 = Asciz	(Lscala/collection/generic/VectorViewTemplate;Lscala/collection/Sequence;)Lscala/collection/generic/VectorViewTemplate$Transformed;;
const #12 = Asciz	scala/collection/generic/VectorViewTemplate$$anon$10;
const #13 = class	#12;	//  scala/collection/generic/VectorViewTemplate$$anon$10
const #14 = Asciz	<init>;
const #15 = Asciz	(Lscala/collection/generic/VectorViewTemplate;Lscala/collection/Sequence;)V;
const #16 = NameAndType	#14:#15;//  "<init>":(Lscala/collection/generic/VectorViewTemplate;Lscala/collection/Sequence;)V
const #17 = Method	#13.#16;	//  scala/collection/generic/VectorViewTemplate$$anon$10."<init>":(Lscala/collection/generic/VectorViewTemplate;Lscala/collection/Sequence;)V
const #18 = Asciz	that$2;
const #19 = Asciz	Lscala/collection/Sequence;;
const #20 = Asciz	newPatched;
const #21 = Asciz	(Lscala/collection/generic/VectorViewTemplate;ILscala/collection/Sequence;I)Lscala/collection/generic/VectorViewTemplate$Transformed;;
const #22 = Asciz	scala/collection/generic/VectorViewTemplate$$anon$9;
const #23 = class	#22;	//  scala/collection/generic/VectorViewTemplate$$anon$9
const #24 = Asciz	(Lscala/collection/generic/VectorViewTemplate;ILscala/collection/Sequence;I)V;
const #25 = NameAndType	#14:#24;//  "<init>":(Lscala/collection/generic/VectorViewTemplate;ILscala/collection/Sequence;I)V
const #26 = Method	#23.#25;	//  scala/collection/generic/VectorViewTemplate$$anon$9."<init>":(Lscala/collection/generic/VectorViewTemplate;ILscala/collection/Sequence;I)V
const #27 = Asciz	_from$2;
const #28 = Asciz	I;
const #29 = Asciz	_patch$1;
const #30 = Asciz	_replaced$1;
const #31 = Asciz	newReversed;
const #32 = Asciz	(Lscala/collection/generic/VectorViewTemplate;)Lscala/collection/generic/VectorViewTemplate$Transformed;;
const #33 = Asciz	scala/collection/generic/VectorViewTemplate$$anon$8;
const #34 = class	#33;	//  scala/collection/generic/VectorViewTemplate$$anon$8
const #35 = NameAndType	#14:#4;//  "<init>":(Lscala/collection/generic/VectorViewTemplate;)V
const #36 = Method	#34.#35;	//  scala/collection/generic/VectorViewTemplate$$anon$8."<init>":(Lscala/collection/generic/VectorViewTemplate;)V
const #37 = Asciz	newTakenWhile;
const #38 = Asciz	(Lscala/collection/generic/VectorViewTemplate;Lscala/Function1;)Lscala/collection/generic/VectorViewTemplate$Transformed;;
const #39 = Asciz	scala/collection/generic/VectorViewTemplate$$anon$7;
const #40 = class	#39;	//  scala/collection/generic/VectorViewTemplate$$anon$7
const #41 = Asciz	(Lscala/collection/generic/VectorViewTemplate;Lscala/Function1;)V;
const #42 = NameAndType	#14:#41;//  "<init>":(Lscala/collection/generic/VectorViewTemplate;Lscala/Function1;)V
const #43 = Method	#40.#42;	//  scala/collection/generic/VectorViewTemplate$$anon$7."<init>":(Lscala/collection/generic/VectorViewTemplate;Lscala/Function1;)V
const #44 = Asciz	p$3;
const #45 = Asciz	Lscala/Function1;;
const #46 = Asciz	newDroppedWhile;
const #47 = Asciz	scala/collection/generic/VectorViewTemplate$$anon$6;
const #48 = class	#47;	//  scala/collection/generic/VectorViewTemplate$$anon$6
const #49 = Method	#48.#42;	//  scala/collection/generic/VectorViewTemplate$$anon$6."<init>":(Lscala/collection/generic/VectorViewTemplate;Lscala/Function1;)V
const #50 = Asciz	p$2;
const #51 = Asciz	newSliced;
const #52 = Asciz	(Lscala/collection/generic/VectorViewTemplate;II)Lscala/collection/generic/VectorViewTemplate$Transformed;;
const #53 = Asciz	scala/collection/generic/VectorViewTemplate$$anon$5;
const #54 = class	#53;	//  scala/collection/generic/VectorViewTemplate$$anon$5
const #55 = Asciz	(Lscala/collection/generic/VectorViewTemplate;II)V;
const #56 = NameAndType	#14:#55;//  "<init>":(Lscala/collection/generic/VectorViewTemplate;II)V
const #57 = Method	#54.#56;	//  scala/collection/generic/VectorViewTemplate$$anon$5."<init>":(Lscala/collection/generic/VectorViewTemplate;II)V
const #58 = Asciz	_from$1;
const #59 = Asciz	_until$1;
const #60 = Asciz	newFiltered;
const #61 = Asciz	scala/collection/generic/VectorViewTemplate$$anon$4;
const #62 = class	#61;	//  scala/collection/generic/VectorViewTemplate$$anon$4
const #63 = Method	#62.#42;	//  scala/collection/generic/VectorViewTemplate$$anon$4."<init>":(Lscala/collection/generic/VectorViewTemplate;Lscala/Function1;)V
const #64 = Asciz	p$1;
const #65 = Asciz	newFlatMapped;
const #66 = Asciz	scala/collection/generic/VectorViewTemplate$$anon$3;
const #67 = class	#66;	//  scala/collection/generic/VectorViewTemplate$$anon$3
const #68 = Method	#67.#42;	//  scala/collection/generic/VectorViewTemplate$$anon$3."<init>":(Lscala/collection/generic/VectorViewTemplate;Lscala/Function1;)V
const #69 = Asciz	f$2;
const #70 = Asciz	newMapped;
const #71 = Asciz	scala/collection/generic/VectorViewTemplate$$anon$2;
const #72 = class	#71;	//  scala/collection/generic/VectorViewTemplate$$anon$2
const #73 = Method	#72.#42;	//  scala/collection/generic/VectorViewTemplate$$anon$2."<init>":(Lscala/collection/generic/VectorViewTemplate;Lscala/Function1;)V
const #74 = Asciz	f$1;
const #75 = Asciz	newAppended;
const #76 = Asciz	(Lscala/collection/generic/VectorViewTemplate;Lscala/collection/Traversable;)Lscala/collection/generic/VectorViewTemplate$Transformed;;
const #77 = Asciz	scala/collection/generic/VectorViewTemplate$$anon$1;
const #78 = class	#77;	//  scala/collection/generic/VectorViewTemplate$$anon$1
const #79 = Asciz	(Lscala/collection/generic/VectorViewTemplate;Lscala/collection/Traversable;)V;
const #80 = NameAndType	#14:#79;//  "<init>":(Lscala/collection/generic/VectorViewTemplate;Lscala/collection/Traversable;)V
const #81 = Method	#78.#80;	//  scala/collection/generic/VectorViewTemplate$$anon$1."<init>":(Lscala/collection/generic/VectorViewTemplate;Lscala/collection/Traversable;)V
const #82 = Asciz	that$1;
const #83 = Asciz	Lscala/collection/Traversable;;
const #84 = Asciz	Scala;
const #85 = Asciz	InnerClasses;
const #86 = Asciz	scala/collection/generic/VectorViewTemplate;
const #87 = class	#86;	//  scala/collection/generic/VectorViewTemplate
const #88 = Asciz	$anon$8;
const #89 = Asciz	$anon$4;
const #90 = Asciz	$anon$6;
const #91 = Asciz	$anon$2;
const #92 = Asciz	$anon$7;
const #93 = Asciz	$anon$3;
const #94 = Asciz	$anon$5;
const #95 = Asciz	$anon$9;
const #96 = Asciz	$anon$1;
const #97 = Asciz	$anon$10;
const #98 = Asciz	scala/collection/generic/VectorViewTemplate$Transformed;
const #99 = class	#98;	//  scala/collection/generic/VectorViewTemplate$Transformed
const #100 = Asciz	Transformed;
const #101 = Asciz	scala/collection/generic/VectorViewTemplate$class;
const #102 = class	#101;	//  scala/collection/generic/VectorViewTemplate$class
const #103 = Asciz	java/lang/Object;
const #104 = class	#103;	//  java/lang/Object

{
public static void $init$(scala.collection.generic.VectorViewTemplate);
  Code:
   Stack=0, Locals=1, Args_size=1
   0:	return
  LineNumberTable: 
   line 26: 0

  LocalVariableTable: 
   Start  Length  Slot  Name   Signature
   0      1      0    $this       Lscala/collection/generic/VectorViewTemplate;


public static scala.collection.generic.VectorViewTemplate$Transformed newZipped(scala.collection.generic.VectorViewTemplate, scala.collection.Sequence);
  Code:
   Stack=4, Locals=2, Args_size=2
   0:	new	#13; //class scala/collection/generic/VectorViewTemplate$$anon$10
   3:	dup
   4:	aload_0
   5:	aload_1
   6:	invokespecial	#17; //Method scala/collection/generic/VectorViewTemplate$$anon$10."<init>":(Lscala/collection/generic/VectorViewTemplate;Lscala/collection/Sequence;)V
   9:	areturn
  LineNumberTable: 
   line 84: 0

  LocalVariableTable: 
   Start  Length  Slot  Name   Signature
   0      10      0    $this       Lscala/collection/generic/VectorViewTemplate;
   0      10      1    that$2       Lscala/collection/Sequence;


public static scala.collection.generic.VectorViewTemplate$Transformed newPatched(scala.collection.generic.VectorViewTemplate, int, scala.collection.Sequence, int);
  Code:
   Stack=6, Locals=4, Args_size=4
   0:	new	#23; //class scala/collection/generic/VectorViewTemplate$$anon$9
   3:	dup
   4:	aload_0
   5:	iload_1
   6:	aload_2
   7:	iload_3
   8:	invokespecial	#26; //Method scala/collection/generic/VectorViewTemplate$$anon$9."<init>":(Lscala/collection/generic/VectorViewTemplate;ILscala/collection/Sequence;I)V
   11:	areturn
  LineNumberTable: 
   line 81: 0

  LocalVariableTable: 
   Start  Length  Slot  Name   Signature
   0      12      0    $this       Lscala/collection/generic/VectorViewTemplate;
   0      12      1    _from$2       I
   0      12      2    _patch$1       Lscala/collection/Sequence;
   0      12      3    _replaced$1       I


public static scala.collection.generic.VectorViewTemplate$Transformed newReversed(scala.collection.generic.VectorViewTemplate);
  Code:
   Stack=3, Locals=1, Args_size=1
   0:	new	#34; //class scala/collection/generic/VectorViewTemplate$$anon$8
   3:	dup
   4:	aload_0
   5:	invokespecial	#36; //Method scala/collection/generic/VectorViewTemplate$$anon$8."<init>":(Lscala/collection/generic/VectorViewTemplate;)V
   8:	areturn
  LineNumberTable: 
   line 80: 0

  LocalVariableTable: 
   Start  Length  Slot  Name   Signature
   0      9      0    $this       Lscala/collection/generic/VectorViewTemplate;


public static scala.collection.generic.VectorViewTemplate$Transformed newTakenWhile(scala.collection.generic.VectorViewTemplate, scala.Function1);
  Code:
   Stack=4, Locals=2, Args_size=2
   0:	new	#40; //class scala/collection/generic/VectorViewTemplate$$anon$7
   3:	dup
   4:	aload_0
   5:	aload_1
   6:	invokespecial	#43; //Method scala/collection/generic/VectorViewTemplate$$anon$7."<init>":(Lscala/collection/generic/VectorViewTemplate;Lscala/Function1;)V
   9:	areturn
  LineNumberTable: 
   line 79: 0

  LocalVariableTable: 
   Start  Length  Slot  Name   Signature
   0      10      0    $this       Lscala/collection/generic/VectorViewTemplate;
   0      10      1    p$3       Lscala/Function1;


public static scala.collection.generic.VectorViewTemplate$Transformed newDroppedWhile(scala.collection.generic.VectorViewTemplate, scala.Function1);
  Code:
   Stack=4, Locals=2, Args_size=2
   0:	new	#48; //class scala/collection/generic/VectorViewTemplate$$anon$6
   3:	dup
   4:	aload_0
   5:	aload_1
   6:	invokespecial	#49; //Method scala/collection/generic/VectorViewTemplate$$anon$6."<init>":(Lscala/collection/generic/VectorViewTemplate;Lscala/Function1;)V
   9:	areturn
  LineNumberTable: 
   line 78: 0

  LocalVariableTable: 
   Start  Length  Slot  Name   Signature
   0      10      0    $this       Lscala/collection/generic/VectorViewTemplate;
   0      10      1    p$2       Lscala/Function1;


public static scala.collection.generic.VectorViewTemplate$Transformed newSliced(scala.collection.generic.VectorViewTemplate, int, int);
  Code:
   Stack=5, Locals=3, Args_size=3
   0:	new	#54; //class scala/collection/generic/VectorViewTemplate$$anon$5
   3:	dup
   4:	aload_0
   5:	iload_1
   6:	iload_2
   7:	invokespecial	#57; //Method scala/collection/generic/VectorViewTemplate$$anon$5."<init>":(Lscala/collection/generic/VectorViewTemplate;II)V
   10:	areturn
  LineNumberTable: 
   line 77: 0

  LocalVariableTable: 
   Start  Length  Slot  Name   Signature
   0      11      0    $this       Lscala/collection/generic/VectorViewTemplate;
   0      11      1    _from$1       I
   0      11      2    _until$1       I


public static scala.collection.generic.VectorViewTemplate$Transformed newFiltered(scala.collection.generic.VectorViewTemplate, scala.Function1);
  Code:
   Stack=4, Locals=2, Args_size=2
   0:	new	#62; //class scala/collection/generic/VectorViewTemplate$$anon$4
   3:	dup
   4:	aload_0
   5:	aload_1
   6:	invokespecial	#63; //Method scala/collection/generic/VectorViewTemplate$$anon$4."<init>":(Lscala/collection/generic/VectorViewTemplate;Lscala/Function1;)V
   9:	areturn
  LineNumberTable: 
   line 76: 0

  LocalVariableTable: 
   Start  Length  Slot  Name   Signature
   0      10      0    $this       Lscala/collection/generic/VectorViewTemplate;
   0      10      1    p$1       Lscala/Function1;


public static scala.collection.generic.VectorViewTemplate$Transformed newFlatMapped(scala.collection.generic.VectorViewTemplate, scala.Function1);
  Code:
   Stack=4, Locals=2, Args_size=2
   0:	new	#67; //class scala/collection/generic/VectorViewTemplate$$anon$3
   3:	dup
   4:	aload_0
   5:	aload_1
   6:	invokespecial	#68; //Method scala/collection/generic/VectorViewTemplate$$anon$3."<init>":(Lscala/collection/generic/VectorViewTemplate;Lscala/Function1;)V
   9:	areturn
  LineNumberTable: 
   line 75: 0

  LocalVariableTable: 
   Start  Length  Slot  Name   Signature
   0      10      0    $this       Lscala/collection/generic/VectorViewTemplate;
   0      10      1    f$2       Lscala/Function1;


public static scala.collection.generic.VectorViewTemplate$Transformed newMapped(scala.collection.generic.VectorViewTemplate, scala.Function1);
  Code:
   Stack=4, Locals=2, Args_size=2
   0:	new	#72; //class scala/collection/generic/VectorViewTemplate$$anon$2
   3:	dup
   4:	aload_0
   5:	aload_1
   6:	invokespecial	#73; //Method scala/collection/generic/VectorViewTemplate$$anon$2."<init>":(Lscala/collection/generic/VectorViewTemplate;Lscala/Function1;)V
   9:	areturn
  LineNumberTable: 
   line 74: 0

  LocalVariableTable: 
   Start  Length  Slot  Name   Signature
   0      10      0    $this       Lscala/collection/generic/VectorViewTemplate;
   0      10      1    f$1       Lscala/Function1;


public static scala.collection.generic.VectorViewTemplate$Transformed newAppended(scala.collection.generic.VectorViewTemplate, scala.collection.Traversable);
  Code:
   Stack=4, Locals=2, Args_size=2
   0:	new	#78; //class scala/collection/generic/VectorViewTemplate$$anon$1
   3:	dup
   4:	aload_0
   5:	aload_1
   6:	invokespecial	#81; //Method scala/collection/generic/VectorViewTemplate$$anon$1."<init>":(Lscala/collection/generic/VectorViewTemplate;Lscala/collection/Traversable;)V
   9:	areturn
  LineNumberTable: 
   line 73: 0

  LocalVariableTable: 
   Start  Length  Slot  Name   Signature
   0      10      0    $this       Lscala/collection/generic/VectorViewTemplate;
   0      10      1    that$1       Lscala/collection/Traversable;


}

