Compiled from "VectorTemplate.scala"
public abstract class scala.collection.generic.VectorTemplate$class extends java.lang.Object
  SourceFile: "VectorTemplate.scala"
  Scala: length = 0x
   
  InnerClass: 
   public final #344= #103 of #13; //$anon$2=class scala/collection/generic/VectorTemplate$$anon$2 of class scala/collection/generic/VectorTemplate
   public final #345= #30 of #13; //$anon$1=class scala/collection/generic/VectorTemplate$$anon$1 of class scala/collection/generic/VectorTemplate
   public #346= #338 of #13; //Elements=class scala/collection/generic/VectorTemplate$Elements of class scala/collection/generic/VectorTemplate
   public final #347= #310 of #13; //$anonfun$1=class scala/collection/generic/VectorTemplate$$anonfun$1 of class scala/collection/generic/VectorTemplate
   public final #348= #331 of #13; //$anonfun$forall$1=class scala/collection/generic/VectorTemplate$$anonfun$forall$1 of class scala/collection/generic/VectorTemplate
   public final #349= #326 of #13; //$anonfun$exists$1=class scala/collection/generic/VectorTemplate$$anonfun$exists$1 of class scala/collection/generic/VectorTemplate
   public final #350= #159 of #13; //$anonfun$indexWhere$1=class scala/collection/generic/VectorTemplate$$anonfun$indexWhere$1 of class scala/collection/generic/VectorTemplate
  minor version: 0
  major version: 49
  Constant pool:
const #1 = Asciz	SourceFile;
const #2 = Asciz	VectorTemplate.scala;
const #3 = Asciz	$init$;
const #4 = Asciz	(Lscala/collection/generic/VectorTemplate;)V;
const #5 = Asciz	Code;
const #6 = Asciz	LineNumberTable;
const #7 = Asciz	$this;
const #8 = Asciz	Lscala/collection/generic/VectorTemplate;;
const #9 = Asciz	LocalVariableTable;
const #10 = Asciz	view;
const #11 = Asciz	(Lscala/collection/generic/VectorTemplate;II)Lscala/collection/generic/VectorView;;
const #12 = Asciz	scala/collection/generic/VectorTemplate;
const #13 = class	#12;	//  scala/collection/generic/VectorTemplate
const #14 = Asciz	()Ljava/lang/Object;;
const #15 = NameAndType	#10:#14;//  view:()Ljava/lang/Object;
const #16 = InterfaceMethod	#13.#15;	//  scala/collection/generic/VectorTemplate.view:()Ljava/lang/Object;
const #17 = Asciz	scala/collection/generic/TraversableViewTemplate;
const #18 = class	#17;	//  scala/collection/generic/TraversableViewTemplate
const #19 = Asciz	slice;
const #20 = Asciz	(II)Lscala/collection/generic/TraversableView;;
const #21 = NameAndType	#19:#20;//  slice:(II)Lscala/collection/generic/TraversableView;
const #22 = InterfaceMethod	#18.#21;	//  scala/collection/generic/TraversableViewTemplate.slice:(II)Lscala/collection/generic/TraversableView;
const #23 = Asciz	scala/collection/generic/VectorView;
const #24 = class	#23;	//  scala/collection/generic/VectorView
const #25 = Asciz	from;
const #26 = Asciz	I;
const #27 = Asciz	until;
const #28 = Asciz	(Lscala/collection/generic/VectorTemplate;)Ljava/lang/Object;;
const #29 = Asciz	scala/collection/generic/VectorTemplate$$anon$1;
const #30 = class	#29;	//  scala/collection/generic/VectorTemplate$$anon$1
const #31 = Asciz	<init>;
const #32 = NameAndType	#31:#4;//  "<init>":(Lscala/collection/generic/VectorTemplate;)V
const #33 = Method	#30.#32;	//  scala/collection/generic/VectorTemplate$$anon$1."<init>":(Lscala/collection/generic/VectorTemplate;)V
const #34 = Asciz	equals;
const #35 = Asciz	(Lscala/collection/generic/VectorTemplate;Ljava/lang/Object;)Z;
const #36 = Asciz	scala/collection/Vector;
const #37 = class	#36;	//  scala/collection/Vector
const #38 = Asciz	scala/collection/generic/SequenceTemplate;
const #39 = class	#38;	//  scala/collection/generic/SequenceTemplate
const #40 = Asciz	length;
const #41 = Asciz	()I;
const #42 = NameAndType	#40:#41;//  length:()I
const #43 = InterfaceMethod	#39.#42;	//  scala/collection/generic/SequenceTemplate.length:()I
const #44 = Asciz	startsWith;
const #45 = Asciz	(Lscala/collection/Sequence;I)Z;
const #46 = NameAndType	#44:#45;//  startsWith:(Lscala/collection/Sequence;I)Z
const #47 = InterfaceMethod	#13.#46;	//  scala/collection/generic/VectorTemplate.startsWith:(Lscala/collection/Sequence;I)Z
const #48 = Asciz	scala$collection$generic$VectorTemplate$$super$equals;
const #49 = Asciz	(Ljava/lang/Object;)Z;
const #50 = NameAndType	#48:#49;//  scala$collection$generic$VectorTemplate$$super$equals:(Ljava/lang/Object;)Z
const #51 = InterfaceMethod	#13.#50;	//  scala/collection/generic/VectorTemplate.scala$collection$generic$VectorTemplate$$super$equals:(Ljava/lang/Object;)Z
const #52 = Asciz	that;
const #53 = Asciz	Ljava/lang/Object;;
const #54 = Asciz	temp9;
const #55 = Asciz	temp10;
const #56 = Asciz	Lscala/collection/Vector;;
const #57 = Asciz	endsWith;
const #58 = Asciz	(Lscala/collection/generic/VectorTemplate;Lscala/collection/Sequence;)Z;
const #59 = Asciz	apply;
const #60 = Asciz	(I)Ljava/lang/Object;;
const #61 = NameAndType	#59:#60;//  apply:(I)Ljava/lang/Object;
const #62 = InterfaceMethod	#39.#61;	//  scala/collection/generic/SequenceTemplate.apply:(I)Ljava/lang/Object;
const #63 = Asciz	scala/runtime/BoxesRunTime;
const #64 = class	#63;	//  scala/runtime/BoxesRunTime
const #65 = Asciz	(Ljava/lang/Object;Ljava/lang/Object;)Z;
const #66 = NameAndType	#34:#65;//  equals:(Ljava/lang/Object;Ljava/lang/Object;)Z
const #67 = Method	#64.#66;	//  scala/runtime/BoxesRunTime.equals:(Ljava/lang/Object;Ljava/lang/Object;)Z
const #68 = Asciz	scala$collection$generic$VectorTemplate$$super$endsWith;
const #69 = Asciz	(Lscala/collection/Sequence;)Z;
const #70 = NameAndType	#68:#69;//  scala$collection$generic$VectorTemplate$$super$endsWith:(Lscala/collection/Sequence;)Z
const #71 = InterfaceMethod	#13.#70;	//  scala/collection/generic/VectorTemplate.scala$collection$generic$VectorTemplate$$super$endsWith:(Lscala/collection/Sequence;)Z
const #72 = Asciz	Lscala/collection/Sequence;;
const #73 = Asciz	temp7;
const #74 = Asciz	temp8;
const #75 = Asciz	i;
const #76 = Asciz	j;
const #77 = Asciz	(Lscala/collection/generic/VectorTemplate;Lscala/collection/Sequence;I)Z;
const #78 = Asciz	scala/collection/generic/IterableTemplate;
const #79 = class	#78;	//  scala/collection/generic/IterableTemplate
const #80 = Asciz	iterator;
const #81 = Asciz	()Lscala/collection/Iterator;;
const #82 = NameAndType	#80:#81;//  iterator:()Lscala/collection/Iterator;
const #83 = InterfaceMethod	#79.#82;	//  scala/collection/generic/IterableTemplate.iterator:()Lscala/collection/Iterator;
const #84 = Asciz	scala/collection/Iterator;
const #85 = class	#84;	//  scala/collection/Iterator
const #86 = Asciz	hasNext;
const #87 = Asciz	()Z;
const #88 = NameAndType	#86:#87;//  hasNext:()Z
const #89 = InterfaceMethod	#85.#88;	//  scala/collection/Iterator.hasNext:()Z
const #90 = Asciz	next;
const #91 = NameAndType	#90:#14;//  next:()Ljava/lang/Object;
const #92 = InterfaceMethod	#85.#91;	//  scala/collection/Iterator.next:()Ljava/lang/Object;
const #93 = Asciz	offset;
const #94 = Asciz	temp5;
const #95 = Asciz	temp6;
const #96 = Asciz	thisLen;
const #97 = Asciz	thatLen;
const #98 = Asciz	thatElems;
const #99 = Asciz	Lscala/collection/Iterator;;
const #100 = Asciz	reverseIterator;
const #101 = Asciz	(Lscala/collection/generic/VectorTemplate;)Lscala/collection/Iterator;;
const #102 = Asciz	scala/collection/generic/VectorTemplate$$anon$2;
const #103 = class	#102;	//  scala/collection/generic/VectorTemplate$$anon$2
const #104 = Method	#103.#32;	//  scala/collection/generic/VectorTemplate$$anon$2."<init>":(Lscala/collection/generic/VectorTemplate;)V
const #105 = Asciz	reverse;
const #106 = Asciz	(Lscala/collection/generic/VectorTemplate;)Lscala/collection/generic/VectorTemplate;;
const #107 = Asciz	scala/collection/generic/TraversableTemplate;
const #108 = class	#107;	//  scala/collection/generic/TraversableTemplate
const #109 = Asciz	newBuilder;
const #110 = Asciz	()Lscala/collection/generic/Builder;;
const #111 = NameAndType	#109:#110;//  newBuilder:()Lscala/collection/generic/Builder;
const #112 = InterfaceMethod	#108.#111;	//  scala/collection/generic/TraversableTemplate.newBuilder:()Lscala/collection/generic/Builder;
const #113 = Asciz	scala/collection/generic/Builder;
const #114 = class	#113;	//  scala/collection/generic/Builder
const #115 = Asciz	sizeHint;
const #116 = Asciz	(I)V;
const #117 = NameAndType	#115:#116;//  sizeHint:(I)V
const #118 = InterfaceMethod	#114.#117;	//  scala/collection/generic/Builder.sizeHint:(I)V
const #119 = Asciz	$plus$eq;
const #120 = Asciz	(Ljava/lang/Object;)Lscala/collection/generic/Builder;;
const #121 = NameAndType	#119:#120;//  $plus$eq:(Ljava/lang/Object;)Lscala/collection/generic/Builder;
const #122 = InterfaceMethod	#114.#121;	//  scala/collection/generic/Builder.$plus$eq:(Ljava/lang/Object;)Lscala/collection/generic/Builder;
const #123 = Asciz	result;
const #124 = NameAndType	#123:#14;//  result:()Ljava/lang/Object;
const #125 = InterfaceMethod	#114.#124;	//  scala/collection/generic/Builder.result:()Ljava/lang/Object;
const #126 = Asciz	b;
const #127 = Asciz	Lscala/collection/generic/Builder;;
const #128 = Asciz	lastIndexWhere;
const #129 = Asciz	(Lscala/collection/generic/VectorTemplate;Lscala/Function1;I)I;
const #130 = Asciz	scala/Function1;
const #131 = class	#130;	//  scala/Function1
const #132 = Asciz	(Ljava/lang/Object;)Ljava/lang/Object;;
const #133 = NameAndType	#59:#132;//  apply:(Ljava/lang/Object;)Ljava/lang/Object;
const #134 = InterfaceMethod	#131.#133;	//  scala/Function1.apply:(Ljava/lang/Object;)Ljava/lang/Object;
const #135 = Asciz	unboxToBoolean;
const #136 = NameAndType	#135:#49;//  unboxToBoolean:(Ljava/lang/Object;)Z
const #137 = Method	#64.#136;	//  scala/runtime/BoxesRunTime.unboxToBoolean:(Ljava/lang/Object;)Z
const #138 = Asciz	p;
const #139 = Asciz	Lscala/Function1;;
const #140 = Asciz	end;
const #141 = Asciz	indexWhere;
const #142 = Asciz	scala/Predef$;
const #143 = class	#142;	//  scala/Predef$
const #144 = Asciz	MODULE$;
const #145 = Asciz	Lscala/Predef$;;
const #146 = NameAndType	#144:#145;//  MODULE$:Lscala/Predef$;
const #147 = Field	#143.#146;	//  scala/Predef$.MODULE$:Lscala/Predef$;
const #148 = Asciz	intWrapper;
const #149 = Asciz	(I)Lscala/runtime/RichInt;;
const #150 = NameAndType	#148:#149;//  intWrapper:(I)Lscala/runtime/RichInt;
const #151 = Method	#143.#150;	//  scala/Predef$.intWrapper:(I)Lscala/runtime/RichInt;
const #152 = Asciz	scala/runtime/RichInt;
const #153 = class	#152;	//  scala/runtime/RichInt
const #154 = Asciz	max;
const #155 = Asciz	(I)I;
const #156 = NameAndType	#154:#155;//  max:(I)I
const #157 = Method	#153.#156;	//  scala/runtime/RichInt.max:(I)I
const #158 = Asciz	scala/collection/generic/VectorTemplate$$anonfun$indexWhere$1;
const #159 = class	#158;	//  scala/collection/generic/VectorTemplate$$anonfun$indexWhere$1
const #160 = Asciz	(Lscala/collection/generic/VectorTemplate;Lscala/Function1;)V;
const #161 = NameAndType	#31:#160;//  "<init>":(Lscala/collection/generic/VectorTemplate;Lscala/Function1;)V
const #162 = Method	#159.#161;	//  scala/collection/generic/VectorTemplate$$anonfun$indexWhere$1."<init>":(Lscala/collection/generic/VectorTemplate;Lscala/Function1;)V
const #163 = Asciz	segmentLength;
const #164 = Asciz	(Lscala/Function1;I)I;
const #165 = NameAndType	#163:#164;//  segmentLength:(Lscala/Function1;I)I
const #166 = InterfaceMethod	#13.#165;	//  scala/collection/generic/VectorTemplate.segmentLength:(Lscala/Function1;I)I
const #167 = Asciz	scala/collection/generic/VectorTemplate$class;
const #168 = class	#167;	//  scala/collection/generic/VectorTemplate$class
const #169 = Asciz	negLength;
const #170 = Asciz	(Lscala/collection/generic/VectorTemplate;I)I;
const #171 = NameAndType	#169:#170;//  negLength:(Lscala/collection/generic/VectorTemplate;I)I
const #172 = Method	#168.#171;	//  scala/collection/generic/VectorTemplate$class.negLength:(Lscala/collection/generic/VectorTemplate;I)I
const #173 = Asciz	p$4;
const #174 = Asciz	start;
const #175 = Asciz	n;
const #176 = Asciz	len;
const #177 = Asciz	lengthCompare;
const #178 = Asciz	copyToArray;
const #179 = Asciz	(Lscala/collection/generic/VectorTemplate;Lscala/runtime/BoxedArray;II)V;
const #180 = Asciz	min;
const #181 = NameAndType	#180:#155;//  min:(I)I
const #182 = Method	#153.#181;	//  scala/runtime/RichInt.min:(I)I
const #183 = Asciz	scala/runtime/BoxedArray;
const #184 = class	#183;	//  scala/runtime/BoxedArray
const #185 = Method	#184.#42;	//  scala/runtime/BoxedArray.length:()I
const #186 = Asciz	update;
const #187 = Asciz	(ILjava/lang/Object;)V;
const #188 = NameAndType	#186:#187;//  update:(ILjava/lang/Object;)V
const #189 = Method	#184.#188;	//  scala/runtime/BoxedArray.update:(ILjava/lang/Object;)V
const #190 = Asciz	xs;
const #191 = Asciz	Lscala/runtime/BoxedArray;;
const #192 = Asciz	sameElements;
const #193 = Asciz	(Lscala/collection/generic/VectorTemplate;Lscala/collection/Iterable;)Z;
const #194 = Asciz	scala$collection$generic$VectorTemplate$$super$sameElements;
const #195 = Asciz	(Lscala/collection/Iterable;)Z;
const #196 = NameAndType	#194:#195;//  scala$collection$generic$VectorTemplate$$super$sameElements:(Lscala/collection/Iterable;)Z
const #197 = InterfaceMethod	#13.#196;	//  scala/collection/generic/VectorTemplate.scala$collection$generic$VectorTemplate$$super$sameElements:(Lscala/collection/Iterable;)Z
const #198 = Asciz	Lscala/collection/Iterable;;
const #199 = Asciz	temp3;
const #200 = Asciz	temp4;
const #201 = Asciz	span;
const #202 = Asciz	(Lscala/collection/generic/VectorTemplate;Lscala/Function1;)Lscala/Tuple2;;
const #203 = Asciz	prefixLength;
const #204 = Asciz	(Lscala/Function1;)I;
const #205 = NameAndType	#203:#204;//  prefixLength:(Lscala/Function1;)I
const #206 = InterfaceMethod	#39.#205;	//  scala/collection/generic/SequenceTemplate.prefixLength:(Lscala/Function1;)I
const #207 = Asciz	splitAt;
const #208 = Asciz	(I)Lscala/Tuple2;;
const #209 = NameAndType	#207:#208;//  splitAt:(I)Lscala/Tuple2;
const #210 = InterfaceMethod	#13.#209;	//  scala/collection/generic/VectorTemplate.splitAt:(I)Lscala/Tuple2;
const #211 = Asciz	dropWhile;
const #212 = Asciz	(Lscala/collection/generic/VectorTemplate;Lscala/Function1;)Lscala/collection/generic/VectorTemplate;;
const #213 = Asciz	drop;
const #214 = Asciz	(I)Lscala/collection/generic/VectorTemplate;;
const #215 = NameAndType	#213:#214;//  drop:(I)Lscala/collection/generic/VectorTemplate;
const #216 = InterfaceMethod	#13.#215;	//  scala/collection/generic/VectorTemplate.drop:(I)Lscala/collection/generic/VectorTemplate;
const #217 = Asciz	takeWhile;
const #218 = Asciz	take;
const #219 = NameAndType	#218:#214;//  take:(I)Lscala/collection/generic/VectorTemplate;
const #220 = InterfaceMethod	#13.#219;	//  scala/collection/generic/VectorTemplate.take:(I)Lscala/collection/generic/VectorTemplate;
const #221 = Asciz	(Lscala/collection/generic/VectorTemplate;I)Lscala/Tuple2;;
const #222 = Asciz	scala/Tuple2;
const #223 = class	#222;	//  scala/Tuple2
const #224 = Asciz	(Ljava/lang/Object;Ljava/lang/Object;)V;
const #225 = NameAndType	#31:#224;//  "<init>":(Ljava/lang/Object;Ljava/lang/Object;)V
const #226 = Method	#223.#225;	//  scala/Tuple2."<init>":(Ljava/lang/Object;Ljava/lang/Object;)V
const #227 = Asciz	dropRight;
const #228 = Asciz	(Lscala/collection/generic/VectorTemplate;I)Lscala/collection/generic/VectorTemplate;;
const #229 = Asciz	(II)Lscala/collection/generic/VectorTemplate;;
const #230 = NameAndType	#19:#229;//  slice:(II)Lscala/collection/generic/VectorTemplate;
const #231 = InterfaceMethod	#13.#230;	//  scala/collection/generic/VectorTemplate.slice:(II)Lscala/collection/generic/VectorTemplate;
const #232 = Asciz	takeRight;
const #233 = Asciz	init;
const #234 = Asciz	scala$collection$generic$VectorTemplate$$super$init;
const #235 = Asciz	()Lscala/collection/generic/VectorTemplate;;
const #236 = NameAndType	#234:#235;//  scala$collection$generic$VectorTemplate$$super$init:()Lscala/collection/generic/VectorTemplate;
const #237 = InterfaceMethod	#13.#236;	//  scala/collection/generic/VectorTemplate.scala$collection$generic$VectorTemplate$$super$init:()Lscala/collection/generic/VectorTemplate;
const #238 = Asciz	last;
const #239 = Asciz	scala$collection$generic$VectorTemplate$$super$last;
const #240 = NameAndType	#239:#14;//  scala$collection$generic$VectorTemplate$$super$last:()Ljava/lang/Object;
const #241 = InterfaceMethod	#13.#240;	//  scala/collection/generic/VectorTemplate.scala$collection$generic$VectorTemplate$$super$last:()Ljava/lang/Object;
const #242 = Asciz	tail;
const #243 = Asciz	head;
const #244 = Asciz	isEmpty;
const #245 = NameAndType	#244:#87;//  isEmpty:()Z
const #246 = InterfaceMethod	#13.#245;	//  scala/collection/generic/VectorTemplate.isEmpty:()Z
const #247 = Asciz	scala$collection$generic$VectorTemplate$$super$head;
const #248 = NameAndType	#247:#14;//  scala$collection$generic$VectorTemplate$$super$head:()Ljava/lang/Object;
const #249 = InterfaceMethod	#13.#248;	//  scala/collection/generic/VectorTemplate.scala$collection$generic$VectorTemplate$$super$head:()Ljava/lang/Object;
const #250 = Asciz	(Lscala/collection/generic/VectorTemplate;II)Lscala/collection/generic/VectorTemplate;;
const #251 = Asciz	zipWithIndex;
const #252 = Asciz	(Lscala/collection/generic/VectorTemplate;Lscala/collection/generic/BuilderFactory;)Ljava/lang/Object;;
const #253 = Asciz	thisCollection;
const #254 = Asciz	()Lscala/collection/generic/TraversableTemplate;;
const #255 = NameAndType	#253:#254;//  thisCollection:()Lscala/collection/generic/TraversableTemplate;
const #256 = InterfaceMethod	#108.#255;	//  scala/collection/generic/TraversableTemplate.thisCollection:()Lscala/collection/generic/TraversableTemplate;
const #257 = Asciz	scala/collection/generic/BuilderFactory;
const #258 = class	#257;	//  scala/collection/generic/BuilderFactory
const #259 = NameAndType	#59:#120;//  apply:(Ljava/lang/Object;)Lscala/collection/generic/Builder;
const #260 = InterfaceMethod	#258.#259;	//  scala/collection/generic/BuilderFactory.apply:(Ljava/lang/Object;)Lscala/collection/generic/Builder;
const #261 = Asciz	boxToInteger;
const #262 = Asciz	(I)Ljava/lang/Integer;;
const #263 = NameAndType	#261:#262;//  boxToInteger:(I)Ljava/lang/Integer;
const #264 = Method	#64.#263;	//  scala/runtime/BoxesRunTime.boxToInteger:(I)Ljava/lang/Integer;
const #265 = Asciz	bf;
const #266 = Asciz	Lscala/collection/generic/BuilderFactory;;
const #267 = Asciz	zip;
const #268 = Asciz	(Lscala/collection/generic/VectorTemplate;Lscala/collection/Sequence;Lscala/collection/generic/BuilderFactory;)Ljava/lang/Object;;
const #269 = Asciz	scala$collection$generic$VectorTemplate$$super$zip;
const #270 = Asciz	(Lscala/collection/Sequence;Lscala/collection/generic/BuilderFactory;)Ljava/lang/Object;;
const #271 = NameAndType	#269:#270;//  scala$collection$generic$VectorTemplate$$super$zip:(Lscala/collection/Sequence;Lscala/collection/generic/BuilderFactory;)Ljava/lang/Object;
const #272 = InterfaceMethod	#13.#271;	//  scala/collection/generic/VectorTemplate.scala$collection$generic$VectorTemplate$$super$zip:(Lscala/collection/Sequence;Lscala/collection/generic/BuilderFactory;)Ljava/lang/Object;
const #273 = Asciz	temp1;
const #274 = Asciz	temp2;
const #275 = Asciz	reduceRight;
const #276 = Asciz	(Lscala/collection/generic/VectorTemplate;Lscala/Function2;)Ljava/lang/Object;;
const #277 = Asciz	foldr;
const #278 = Asciz	(Lscala/collection/generic/VectorTemplate;IILjava/lang/Object;Lscala/Function2;)Ljava/lang/Object;;
const #279 = NameAndType	#277:#278;//  foldr:(Lscala/collection/generic/VectorTemplate;IILjava/lang/Object;Lscala/Function2;)Ljava/lang/Object;
const #280 = Method	#168.#279;	//  scala/collection/generic/VectorTemplate$class.foldr:(Lscala/collection/generic/VectorTemplate;IILjava/lang/Object;Lscala/Function2;)Ljava/lang/Object;
const #281 = Asciz	scala$collection$generic$VectorTemplate$$super$reduceRight;
const #282 = Asciz	(Lscala/Function2;)Ljava/lang/Object;;
const #283 = NameAndType	#281:#282;//  scala$collection$generic$VectorTemplate$$super$reduceRight:(Lscala/Function2;)Ljava/lang/Object;
const #284 = InterfaceMethod	#13.#283;	//  scala/collection/generic/VectorTemplate.scala$collection$generic$VectorTemplate$$super$reduceRight:(Lscala/Function2;)Ljava/lang/Object;
const #285 = Asciz	op;
const #286 = Asciz	Lscala/Function2;;
const #287 = Asciz	reduceLeft;
const #288 = Asciz	foldl;
const #289 = Asciz	(Lscala/collection/generic/VectorTemplate;ILjava/lang/Object;Lscala/Function2;)Ljava/lang/Object;;
const #290 = NameAndType	#288:#289;//  foldl:(Lscala/collection/generic/VectorTemplate;ILjava/lang/Object;Lscala/Function2;)Ljava/lang/Object;
const #291 = Method	#168.#290;	//  scala/collection/generic/VectorTemplate$class.foldl:(Lscala/collection/generic/VectorTemplate;ILjava/lang/Object;Lscala/Function2;)Ljava/lang/Object;
const #292 = Asciz	scala$collection$generic$VectorTemplate$$super$reduceLeft;
const #293 = NameAndType	#292:#282;//  scala$collection$generic$VectorTemplate$$super$reduceLeft:(Lscala/Function2;)Ljava/lang/Object;
const #294 = InterfaceMethod	#13.#293;	//  scala/collection/generic/VectorTemplate.scala$collection$generic$VectorTemplate$$super$reduceLeft:(Lscala/Function2;)Ljava/lang/Object;
const #295 = Asciz	foldRight;
const #296 = Asciz	(Lscala/collection/generic/VectorTemplate;Ljava/lang/Object;Lscala/Function2;)Ljava/lang/Object;;
const #297 = Asciz	z;
const #298 = Asciz	foldLeft;
const #299 = Asciz	scala/Function2;
const #300 = class	#299;	//  scala/Function2
const #301 = Asciz	(Ljava/lang/Object;Ljava/lang/Object;)Ljava/lang/Object;;
const #302 = NameAndType	#59:#301;//  apply:(Ljava/lang/Object;Ljava/lang/Object;)Ljava/lang/Object;
const #303 = InterfaceMethod	#300.#302;	//  scala/Function2.apply:(Ljava/lang/Object;Ljava/lang/Object;)Ljava/lang/Object;
const #304 = Asciz	<B:Ljava/lang/Object;>(IITB;Lscala/Function2<TA;TB;TB;>;)TB;;
const #305 = Asciz	Signature;
const #306 = Asciz	<B:Ljava/lang/Object;>(ITB;Lscala/Function2<TB;TA;TB;>;)TB;;
const #307 = Asciz	find;
const #308 = Asciz	(Lscala/collection/generic/VectorTemplate;Lscala/Function1;)Lscala/Option;;
const #309 = Asciz	scala/collection/generic/VectorTemplate$$anonfun$1;
const #310 = class	#309;	//  scala/collection/generic/VectorTemplate$$anonfun$1
const #311 = Method	#310.#161;	//  scala/collection/generic/VectorTemplate$$anonfun$1."<init>":(Lscala/collection/generic/VectorTemplate;Lscala/Function1;)V
const #312 = Asciz	scala/Some;
const #313 = class	#312;	//  scala/Some
const #314 = Asciz	(Ljava/lang/Object;)V;
const #315 = NameAndType	#31:#314;//  "<init>":(Ljava/lang/Object;)V
const #316 = Method	#313.#315;	//  scala/Some."<init>":(Ljava/lang/Object;)V
const #317 = Asciz	scala/None$;
const #318 = class	#317;	//  scala/None$
const #319 = Asciz	Lscala/None$;;
const #320 = NameAndType	#144:#319;//  MODULE$:Lscala/None$;
const #321 = Field	#318.#320;	//  scala/None$.MODULE$:Lscala/None$;
const #322 = Asciz	p$3;
const #323 = Asciz	exists;
const #324 = Asciz	(Lscala/collection/generic/VectorTemplate;Lscala/Function1;)Z;
const #325 = Asciz	scala/collection/generic/VectorTemplate$$anonfun$exists$1;
const #326 = class	#325;	//  scala/collection/generic/VectorTemplate$$anonfun$exists$1
const #327 = Method	#326.#161;	//  scala/collection/generic/VectorTemplate$$anonfun$exists$1."<init>":(Lscala/collection/generic/VectorTemplate;Lscala/Function1;)V
const #328 = Asciz	p$2;
const #329 = Asciz	forall;
const #330 = Asciz	scala/collection/generic/VectorTemplate$$anonfun$forall$1;
const #331 = class	#330;	//  scala/collection/generic/VectorTemplate$$anonfun$forall$1
const #332 = Method	#331.#161;	//  scala/collection/generic/VectorTemplate$$anonfun$forall$1."<init>":(Lscala/collection/generic/VectorTemplate;Lscala/Function1;)V
const #333 = Asciz	p$1;
const #334 = Asciz	foreach;
const #335 = Asciz	f;
const #336 = Asciz	(Lscala/collection/generic/VectorTemplate;)Z;
const #337 = Asciz	scala/collection/generic/VectorTemplate$Elements;
const #338 = class	#337;	//  scala/collection/generic/VectorTemplate$Elements
const #339 = Asciz	(Lscala/collection/generic/VectorTemplate;II)V;
const #340 = NameAndType	#31:#339;//  "<init>":(Lscala/collection/generic/VectorTemplate;II)V
const #341 = Method	#338.#340;	//  scala/collection/generic/VectorTemplate$Elements."<init>":(Lscala/collection/generic/VectorTemplate;II)V
const #342 = Asciz	Scala;
const #343 = Asciz	InnerClasses;
const #344 = Asciz	$anon$2;
const #345 = Asciz	$anon$1;
const #346 = Asciz	Elements;
const #347 = Asciz	$anonfun$1;
const #348 = Asciz	$anonfun$forall$1;
const #349 = Asciz	$anonfun$exists$1;
const #350 = Asciz	$anonfun$indexWhere$1;
const #351 = Asciz	java/lang/Object;
const #352 = class	#351;	//  java/lang/Object

{
public static void $init$(scala.collection.generic.VectorTemplate);
  Code:
   Stack=0, Locals=1, Args_size=1
   0:	return
  LineNumberTable: 
   line 24: 0

  LocalVariableTable: 
   Start  Length  Slot  Name   Signature
   0      1      0    $this       Lscala/collection/generic/VectorTemplate;


public static scala.collection.generic.VectorView view(scala.collection.generic.VectorTemplate, int, int);
  Code:
   Stack=3, Locals=3, Args_size=3
   0:	aload_0
   1:	invokeinterface	#16,  1; //InterfaceMethod scala/collection/generic/VectorTemplate.view:()Ljava/lang/Object;
   6:	checkcast	#18; //class scala/collection/generic/TraversableViewTemplate
   9:	iload_1
   10:	iload_2
   11:	invokeinterface	#22,  3; //InterfaceMethod scala/collection/generic/TraversableViewTemplate.slice:(II)Lscala/collection/generic/TraversableView;
   16:	checkcast	#24; //class scala/collection/generic/VectorView
   19:	areturn
  LineNumberTable: 
   line 274: 0

  LocalVariableTable: 
   Start  Length  Slot  Name   Signature
   0      20      0    $this       Lscala/collection/generic/VectorTemplate;
   0      20      1    from       I
   0      20      2    until       I


public static java.lang.Object view(scala.collection.generic.VectorTemplate);
  Code:
   Stack=3, Locals=1, Args_size=1
   0:	new	#30; //class scala/collection/generic/VectorTemplate$$anon$1
   3:	dup
   4:	aload_0
   5:	invokespecial	#33; //Method scala/collection/generic/VectorTemplate$$anon$1."<init>":(Lscala/collection/generic/VectorTemplate;)V
   8:	areturn
  LineNumberTable: 
   line 267: 0

  LocalVariableTable: 
   Start  Length  Slot  Name   Signature
   0      9      0    $this       Lscala/collection/generic/VectorTemplate;


public static boolean equals(scala.collection.generic.VectorTemplate, java.lang.Object);
  Code:
   Stack=3, Locals=5, Args_size=2
   0:	aload_1
   1:	astore_2
   2:	aload_2
   3:	instanceof	#37; //class scala/collection/Vector
   6:	ifeq	53
   9:	aload_2
   10:	checkcast	#37; //class scala/collection/Vector
   13:	astore_3
   14:	aload_3
   15:	astore	4
   17:	aload_0
   18:	invokeinterface	#43,  1; //InterfaceMethod scala/collection/generic/SequenceTemplate.length:()I
   23:	aload	4
   25:	invokeinterface	#43,  1; //InterfaceMethod scala/collection/generic/SequenceTemplate.length:()I
   30:	if_icmpne	49
   33:	aload_0
   34:	aload	4
   36:	iconst_0
   37:	invokeinterface	#47,  3; //InterfaceMethod scala/collection/generic/VectorTemplate.startsWith:(Lscala/collection/Sequence;I)Z
   42:	ifeq	49
   45:	iconst_1
   46:	goto	60
   49:	iconst_0
   50:	goto	60
   53:	aload_0
   54:	aload_1
   55:	invokeinterface	#51,  2; //InterfaceMethod scala/collection/generic/VectorTemplate.scala$collection$generic$VectorTemplate$$super$equals:(Ljava/lang/Object;)Z
   60:	ireturn
  LineNumberTable: 
   line 262: 0
   line 263: 14
   line 264: 53
   line 262: 60

  LocalVariableTable: 
   Start  Length  Slot  Name   Signature
   0      61      0    $this       Lscala/collection/generic/VectorTemplate;
   0      61      1    that       Ljava/lang/Object;
   2      59      2    temp9       Ljava/lang/Object;
   14      39      3    temp10       Lscala/collection/Vector;
   17      36      4    that       Lscala/collection/Vector;


public static boolean endsWith(scala.collection.generic.VectorTemplate, scala.collection.Sequence);
  Code:
   Stack=3, Locals=7, Args_size=2
   0:	aload_1
   1:	astore_2
   2:	aload_2
   3:	instanceof	#37; //class scala/collection/Vector
   6:	ifeq	103
   9:	aload_2
   10:	checkcast	#37; //class scala/collection/Vector
   13:	astore_3
   14:	aload_3
   15:	astore	4
   17:	aload_0
   18:	invokeinterface	#43,  1; //InterfaceMethod scala/collection/generic/SequenceTemplate.length:()I
   23:	iconst_1
   24:	isub
   25:	istore	5
   27:	aload	4
   29:	invokeinterface	#43,  1; //InterfaceMethod scala/collection/generic/SequenceTemplate.length:()I
   34:	iconst_1
   35:	isub
   36:	istore	6
   38:	iload	6
   40:	iload	5
   42:	if_icmpgt	99
   45:	iload	6
   47:	iconst_0
   48:	if_icmplt	91
   51:	aload_0
   52:	iload	5
   54:	invokeinterface	#62,  2; //InterfaceMethod scala/collection/generic/SequenceTemplate.apply:(I)Ljava/lang/Object;
   59:	aload	4
   61:	iload	6
   63:	invokeinterface	#62,  2; //InterfaceMethod scala/collection/generic/SequenceTemplate.apply:(I)Ljava/lang/Object;
   68:	invokestatic	#67; //Method scala/runtime/BoxesRunTime.equals:(Ljava/lang/Object;Ljava/lang/Object;)Z
   71:	ifeq	89
   74:	iload	5
   76:	iconst_1
   77:	isub
   78:	istore	5
   80:	iload	6
   82:	iconst_1
   83:	isub
   84:	istore	6
   86:	goto	45
   89:	iconst_0
   90:	ireturn
   91:	iconst_1
   92:	ifeq	99
   95:	iconst_1
   96:	goto	110
   99:	iconst_0
   100:	goto	110
   103:	aload_0
   104:	aload_1
   105:	invokeinterface	#71,  2; //InterfaceMethod scala/collection/generic/VectorTemplate.scala$collection$generic$VectorTemplate$$super$endsWith:(Lscala/collection/Sequence;)Z
   110:	ireturn
  LineNumberTable: 
   line 244: 0
   line 245: 14
   line 246: 17
   line 247: 27
   line 249: 38
   line 250: 45
   line 251: 51
   line 253: 74
   line 254: 80
   line 250: 86
   line 252: 89
   line 256: 91
   line 249: 92
   line 259: 103
   line 244: 110

  LocalVariableTable: 
   Start  Length  Slot  Name   Signature
   0      111      0    $this       Lscala/collection/generic/VectorTemplate;
   0      111      1    that       Lscala/collection/Sequence;
   2      109      2    temp7       Lscala/collection/Sequence;
   14      89      3    temp8       Lscala/collection/Vector;
   17      86      4    that       Lscala/collection/Vector;
   27      76      5    i       I
   38      65      6    j       I


public static boolean startsWith(scala.collection.generic.VectorTemplate, scala.collection.Sequence, int);
  Code:
   Stack=3, Locals=13, Args_size=3
   0:	aload_1
   1:	astore_3
   2:	aload_3
   3:	instanceof	#37; //class scala/collection/Vector
   6:	ifeq	109
   9:	aload_3
   10:	checkcast	#37; //class scala/collection/Vector
   13:	astore	4
   15:	aload	4
   17:	astore	5
   19:	iload_2
   20:	istore	6
   22:	iconst_0
   23:	istore	7
   25:	aload_0
   26:	invokeinterface	#43,  1; //InterfaceMethod scala/collection/generic/SequenceTemplate.length:()I
   31:	istore	8
   33:	aload	5
   35:	invokeinterface	#43,  1; //InterfaceMethod scala/collection/generic/SequenceTemplate.length:()I
   40:	istore	9
   42:	iload	6
   44:	iload	8
   46:	if_icmpge	94
   49:	iload	7
   51:	iload	9
   53:	if_icmpge	94
   56:	aload_0
   57:	iload	6
   59:	invokeinterface	#62,  2; //InterfaceMethod scala/collection/generic/SequenceTemplate.apply:(I)Ljava/lang/Object;
   64:	aload	5
   66:	iload	7
   68:	invokeinterface	#62,  2; //InterfaceMethod scala/collection/generic/SequenceTemplate.apply:(I)Ljava/lang/Object;
   73:	invokestatic	#67; //Method scala/runtime/BoxesRunTime.equals:(Ljava/lang/Object;Ljava/lang/Object;)Z
   76:	ifeq	94
   79:	iload	6
   81:	iconst_1
   82:	iadd
   83:	istore	6
   85:	iload	7
   87:	iconst_1
   88:	iadd
   89:	istore	7
   91:	goto	42
   94:	iload	7
   96:	iload	9
   98:	if_icmpne	105
   101:	iconst_1
   102:	goto	192
   105:	iconst_0
   106:	goto	192
   109:	iload_2
   110:	istore	10
   112:	aload_0
   113:	invokeinterface	#43,  1; //InterfaceMethod scala/collection/generic/SequenceTemplate.length:()I
   118:	istore	11
   120:	aload_1
   121:	invokeinterface	#83,  1; //InterfaceMethod scala/collection/generic/IterableTemplate.iterator:()Lscala/collection/Iterator;
   126:	astore	12
   128:	iload	10
   130:	iload	11
   132:	if_icmpge	177
   135:	aload	12
   137:	invokeinterface	#89,  1; //InterfaceMethod scala/collection/Iterator.hasNext:()Z
   142:	ifeq	177
   145:	aload_0
   146:	iload	10
   148:	invokeinterface	#62,  2; //InterfaceMethod scala/collection/generic/SequenceTemplate.apply:(I)Ljava/lang/Object;
   153:	aload	12
   155:	invokeinterface	#92,  1; //InterfaceMethod scala/collection/Iterator.next:()Ljava/lang/Object;
   160:	invokestatic	#67; //Method scala/runtime/BoxesRunTime.equals:(Ljava/lang/Object;Ljava/lang/Object;)Z
   163:	ifeq	175
   166:	iload	10
   168:	iconst_1
   169:	iadd
   170:	istore	10
   172:	goto	128
   175:	iconst_0
   176:	ireturn
   177:	aload	12
   179:	invokeinterface	#89,  1; //InterfaceMethod scala/collection/Iterator.hasNext:()Z
   184:	ifeq	191
   187:	iconst_0
   188:	goto	192
   191:	iconst_1
   192:	ireturn
  LineNumberTable: 
   line 220: 0
   line 221: 15
   line 222: 19
   line 223: 22
   line 224: 25
   line 225: 33
   line 226: 42
   line 227: 79
   line 228: 85
   line 226: 91
   line 230: 94
   line 232: 109
   line 233: 112
   line 234: 120
   line 235: 128
   line 236: 145
   line 239: 166
   line 235: 172
   line 237: 175
   line 241: 177
   line 220: 192

  LocalVariableTable: 
   Start  Length  Slot  Name   Signature
   0      193      0    $this       Lscala/collection/generic/VectorTemplate;
   0      193      1    that       Lscala/collection/Sequence;
   0      193      2    offset       I
   2      191      3    temp5       Lscala/collection/Sequence;
   15      94      4    temp6       Lscala/collection/Vector;
   19      90      5    that       Lscala/collection/Vector;
   22      87      6    i       I
   25      84      7    j       I
   33      76      8    thisLen       I
   42      67      9    thatLen       I
   112      80      10    i       I
   120      72      11    thisLen       I
   128      64      12    thatElems       Lscala/collection/Iterator;


public static scala.collection.Iterator reverseIterator(scala.collection.generic.VectorTemplate);
  Code:
   Stack=3, Locals=1, Args_size=1
   0:	new	#103; //class scala/collection/generic/VectorTemplate$$anon$2
   3:	dup
   4:	aload_0
   5:	invokespecial	#104; //Method scala/collection/generic/VectorTemplate$$anon$2."<init>":(Lscala/collection/generic/VectorTemplate;)V
   8:	areturn
  LineNumberTable: 
   line 210: 0

  LocalVariableTable: 
   Start  Length  Slot  Name   Signature
   0      9      0    $this       Lscala/collection/generic/VectorTemplate;


public static scala.collection.generic.VectorTemplate reverse(scala.collection.generic.VectorTemplate);
  Code:
   Stack=3, Locals=3, Args_size=1
   0:	aload_0
   1:	invokeinterface	#112,  1; //InterfaceMethod scala/collection/generic/TraversableTemplate.newBuilder:()Lscala/collection/generic/Builder;
   6:	astore_1
   7:	aload_1
   8:	aload_0
   9:	invokeinterface	#43,  1; //InterfaceMethod scala/collection/generic/SequenceTemplate.length:()I
   14:	invokeinterface	#118,  2; //InterfaceMethod scala/collection/generic/Builder.sizeHint:(I)V
   19:	aload_0
   20:	invokeinterface	#43,  1; //InterfaceMethod scala/collection/generic/SequenceTemplate.length:()I
   25:	istore_2
   26:	iconst_0
   27:	iload_2
   28:	if_icmpge	52
   31:	iload_2
   32:	iconst_1
   33:	isub
   34:	istore_2
   35:	aload_1
   36:	aload_0
   37:	iload_2
   38:	invokeinterface	#62,  2; //InterfaceMethod scala/collection/generic/SequenceTemplate.apply:(I)Ljava/lang/Object;
   43:	invokeinterface	#122,  2; //InterfaceMethod scala/collection/generic/Builder.$plus$eq:(Ljava/lang/Object;)Lscala/collection/generic/Builder;
   48:	pop
   49:	goto	26
   52:	aload_1
   53:	invokeinterface	#125,  1; //InterfaceMethod scala/collection/generic/Builder.result:()Ljava/lang/Object;
   58:	checkcast	#13; //class scala/collection/generic/VectorTemplate
   61:	areturn
  LineNumberTable: 
   line 200: 0
   line 201: 7
   line 202: 19
   line 203: 26
   line 204: 31
   line 205: 35
   line 203: 49
   line 207: 52

  LocalVariableTable: 
   Start  Length  Slot  Name   Signature
   0      62      0    $this       Lscala/collection/generic/VectorTemplate;
   7      54      1    b       Lscala/collection/generic/Builder;
   26      35      2    i       I


public static int lastIndexWhere(scala.collection.generic.VectorTemplate, scala.Function1, int);
  Code:
   Stack=3, Locals=4, Args_size=3
   0:	iload_2
   1:	istore_3
   2:	iload_3
   3:	iconst_0
   4:	if_icmplt	33
   7:	aload_1
   8:	aload_0
   9:	iload_3
   10:	invokeinterface	#62,  2; //InterfaceMethod scala/collection/generic/SequenceTemplate.apply:(I)Ljava/lang/Object;
   15:	invokeinterface	#134,  2; //InterfaceMethod scala/Function1.apply:(Ljava/lang/Object;)Ljava/lang/Object;
   20:	invokestatic	#137; //Method scala/runtime/BoxesRunTime.unboxToBoolean:(Ljava/lang/Object;)Z
   23:	ifne	33
   26:	iload_3
   27:	iconst_1
   28:	isub
   29:	istore_3
   30:	goto	2
   33:	iload_3
   34:	ireturn
  LineNumberTable: 
   line 194: 0
   line 195: 2
   line 196: 33

  LocalVariableTable: 
   Start  Length  Slot  Name   Signature
   0      35      0    $this       Lscala/collection/generic/VectorTemplate;
   0      35      1    p       Lscala/Function1;
   0      35      2    end       I
   2      32      3    i       I


public static int indexWhere(scala.collection.generic.VectorTemplate, scala.Function1, int);
  Code:
   Stack=7, Locals=4, Args_size=3
   0:	getstatic	#147; //Field scala/Predef$.MODULE$:Lscala/Predef$;
   3:	iload_2
   4:	invokevirtual	#151; //Method scala/Predef$.intWrapper:(I)Lscala/runtime/RichInt;
   7:	iconst_0
   8:	invokevirtual	#157; //Method scala/runtime/RichInt.max:(I)I
   11:	istore_3
   12:	aload_0
   13:	iload_3
   14:	aload_0
   15:	new	#159; //class scala/collection/generic/VectorTemplate$$anonfun$indexWhere$1
   18:	dup
   19:	aload_0
   20:	aload_1
   21:	invokespecial	#162; //Method scala/collection/generic/VectorTemplate$$anonfun$indexWhere$1."<init>":(Lscala/collection/generic/VectorTemplate;Lscala/Function1;)V
   24:	iload_3
   25:	invokeinterface	#166,  3; //InterfaceMethod scala/collection/generic/VectorTemplate.segmentLength:(Lscala/Function1;I)I
   30:	iadd
   31:	invokestatic	#172; //Method negLength:(Lscala/collection/generic/VectorTemplate;I)I
   34:	ireturn
  LineNumberTable: 
   line 189: 0
   line 190: 12

  LocalVariableTable: 
   Start  Length  Slot  Name   Signature
   0      35      0    $this       Lscala/collection/generic/VectorTemplate;
   0      35      1    p$4       Lscala/Function1;
   0      35      2    from       I
   12      22      3    start       I


public static int segmentLength(scala.collection.generic.VectorTemplate, scala.Function1, int);
  Code:
   Stack=3, Locals=6, Args_size=3
   0:	iload_2
   1:	istore_3
   2:	aload_0
   3:	invokeinterface	#43,  1; //InterfaceMethod scala/collection/generic/SequenceTemplate.length:()I
   8:	istore	4
   10:	iload_3
   11:	istore	5
   13:	iload	5
   15:	iload	4
   17:	if_icmpge	49
   20:	aload_1
   21:	aload_0
   22:	iload	5
   24:	invokeinterface	#62,  2; //InterfaceMethod scala/collection/generic/SequenceTemplate.apply:(I)Ljava/lang/Object;
   29:	invokeinterface	#134,  2; //InterfaceMethod scala/Function1.apply:(Ljava/lang/Object;)Ljava/lang/Object;
   34:	invokestatic	#137; //Method scala/runtime/BoxesRunTime.unboxToBoolean:(Ljava/lang/Object;)Z
   37:	ifeq	49
   40:	iload	5
   42:	iconst_1
   43:	iadd
   44:	istore	5
   46:	goto	13
   49:	iload	5
   51:	iload_3
   52:	isub
   53:	ireturn
  LineNumberTable: 
   line 179: 0
   line 180: 2
   line 181: 10
   line 182: 13
   line 183: 49

  LocalVariableTable: 
   Start  Length  Slot  Name   Signature
   0      54      0    $this       Lscala/collection/generic/VectorTemplate;
   0      54      1    p       Lscala/Function1;
   0      54      2    from       I
   2      51      3    start       I
   10      43      4    len       I
   13      40      5    i       I


public static int lengthCompare(scala.collection.generic.VectorTemplate, int);
  Code:
   Stack=2, Locals=2, Args_size=2
   0:	aload_0
   1:	invokeinterface	#43,  1; //InterfaceMethod scala/collection/generic/SequenceTemplate.length:()I
   6:	iload_1
   7:	isub
   8:	ireturn
  LineNumberTable: 
   line 176: 0

  LocalVariableTable: 
   Start  Length  Slot  Name   Signature
   0      9      0    $this       Lscala/collection/generic/VectorTemplate;
   0      9      1    len       I


public static void copyToArray(scala.collection.generic.VectorTemplate, scala.runtime.BoxedArray, int, int);
  Code:
   Stack=4, Locals=7, Args_size=4
   0:	iconst_0
   1:	istore	4
   3:	iload_2
   4:	istore	5
   6:	getstatic	#147; //Field scala/Predef$.MODULE$:Lscala/Predef$;
   9:	getstatic	#147; //Field scala/Predef$.MODULE$:Lscala/Predef$;
   12:	aload_0
   13:	invokeinterface	#43,  1; //InterfaceMethod scala/collection/generic/SequenceTemplate.length:()I
   18:	invokevirtual	#151; //Method scala/Predef$.intWrapper:(I)Lscala/runtime/RichInt;
   21:	iload_3
   22:	invokevirtual	#182; //Method scala/runtime/RichInt.min:(I)I
   25:	invokevirtual	#151; //Method scala/Predef$.intWrapper:(I)Lscala/runtime/RichInt;
   28:	aload_1
   29:	invokevirtual	#185; //Method scala/runtime/BoxedArray.length:()I
   32:	iload_2
   33:	isub
   34:	invokevirtual	#182; //Method scala/runtime/RichInt.min:(I)I
   37:	istore	6
   39:	iload	4
   41:	iload	6
   43:	if_icmpge	75
   46:	aload_1
   47:	iload	5
   49:	aload_0
   50:	iload	4
   52:	invokeinterface	#62,  2; //InterfaceMethod scala/collection/generic/SequenceTemplate.apply:(I)Ljava/lang/Object;
   57:	invokevirtual	#189; //Method scala/runtime/BoxedArray.update:(ILjava/lang/Object;)V
   60:	iload	4
   62:	iconst_1
   63:	iadd
   64:	istore	4
   66:	iload	5
   68:	iconst_1
   69:	iadd
   70:	istore	5
   72:	goto	39
   75:	return
  LineNumberTable: 
   line 164: 0
   line 165: 3
   line 166: 6
   line 167: 39
   line 168: 46
   line 169: 60
   line 170: 66
   line 167: 72
   line 163: 75

  LocalVariableTable: 
   Start  Length  Slot  Name   Signature
   0      76      0    $this       Lscala/collection/generic/VectorTemplate;
   0      76      1    xs       Lscala/runtime/BoxedArray;
   0      76      2    start       I
   0      76      3    len       I
   3      73      4    i       I
   6      70      5    j       I
   39      37      6    end       I


public static boolean sameElements(scala.collection.generic.VectorTemplate, scala.collection.Iterable);
  Code:
   Stack=3, Locals=7, Args_size=2
   0:	aload_1
   1:	astore_2
   2:	aload_2
   3:	instanceof	#37; //class scala/collection/Vector
   6:	ifeq	102
   9:	aload_2
   10:	checkcast	#37; //class scala/collection/Vector
   13:	astore_3
   14:	aload_3
   15:	astore	4
   17:	aload_0
   18:	invokeinterface	#43,  1; //InterfaceMethod scala/collection/generic/SequenceTemplate.length:()I
   23:	istore	5
   25:	iload	5
   27:	aload	4
   29:	invokeinterface	#43,  1; //InterfaceMethod scala/collection/generic/SequenceTemplate.length:()I
   34:	if_icmpne	98
   37:	iconst_0
   38:	istore	6
   40:	iload	6
   42:	iload	5
   44:	if_icmpge	79
   47:	aload_0
   48:	iload	6
   50:	invokeinterface	#62,  2; //InterfaceMethod scala/collection/generic/SequenceTemplate.apply:(I)Ljava/lang/Object;
   55:	aload	4
   57:	iload	6
   59:	invokeinterface	#62,  2; //InterfaceMethod scala/collection/generic/SequenceTemplate.apply:(I)Ljava/lang/Object;
   64:	invokestatic	#67; //Method scala/runtime/BoxesRunTime.equals:(Ljava/lang/Object;Ljava/lang/Object;)Z
   67:	ifeq	79
   70:	iload	6
   72:	iconst_1
   73:	iadd
   74:	istore	6
   76:	goto	40
   79:	iload	6
   81:	iload	5
   83:	if_icmpne	90
   86:	iconst_1
   87:	goto	91
   90:	iconst_0
   91:	ifeq	98
   94:	iconst_1
   95:	goto	109
   98:	iconst_0
   99:	goto	109
   102:	aload_0
   103:	aload_1
   104:	invokeinterface	#197,  2; //InterfaceMethod scala/collection/generic/VectorTemplate.scala$collection$generic$VectorTemplate$$super$sameElements:(Lscala/collection/Iterable;)Z
   109:	ireturn
  LineNumberTable: 
   line 151: 0
   line 152: 14
   line 153: 17
   line 154: 25
   line 155: 37
   line 156: 40
   line 157: 79
   line 154: 91
   line 160: 102
   line 151: 109

  LocalVariableTable: 
   Start  Length  Slot  Name   Signature
   0      110      0    $this       Lscala/collection/generic/VectorTemplate;
   0      110      1    that       Lscala/collection/Iterable;
   2      108      2    temp3       Lscala/collection/Iterable;
   14      88      3    temp4       Lscala/collection/Vector;
   17      85      4    that       Lscala/collection/Vector;
   25      77      5    len       I
   40      54      6    i       I


public static scala.Tuple2 span(scala.collection.generic.VectorTemplate, scala.Function1);
  Code:
   Stack=3, Locals=2, Args_size=2
   0:	aload_0
   1:	aload_0
   2:	aload_1
   3:	invokeinterface	#206,  2; //InterfaceMethod scala/collection/generic/SequenceTemplate.prefixLength:(Lscala/Function1;)I
   8:	invokeinterface	#210,  2; //InterfaceMethod scala/collection/generic/VectorTemplate.splitAt:(I)Lscala/Tuple2;
   13:	areturn
  LineNumberTable: 
   line 149: 0

  LocalVariableTable: 
   Start  Length  Slot  Name   Signature
   0      14      0    $this       Lscala/collection/generic/VectorTemplate;
   0      14      1    p       Lscala/Function1;


public static scala.collection.generic.VectorTemplate dropWhile(scala.collection.generic.VectorTemplate, scala.Function1);
  Code:
   Stack=3, Locals=2, Args_size=2
   0:	aload_0
   1:	aload_0
   2:	aload_1
   3:	invokeinterface	#206,  2; //InterfaceMethod scala/collection/generic/SequenceTemplate.prefixLength:(Lscala/Function1;)I
   8:	invokeinterface	#216,  2; //InterfaceMethod scala/collection/generic/VectorTemplate.drop:(I)Lscala/collection/generic/VectorTemplate;
   13:	areturn
  LineNumberTable: 
   line 148: 0

  LocalVariableTable: 
   Start  Length  Slot  Name   Signature
   0      14      0    $this       Lscala/collection/generic/VectorTemplate;
   0      14      1    p       Lscala/Function1;


public static scala.collection.generic.VectorTemplate takeWhile(scala.collection.generic.VectorTemplate, scala.Function1);
  Code:
   Stack=3, Locals=2, Args_size=2
   0:	aload_0
   1:	aload_0
   2:	aload_1
   3:	invokeinterface	#206,  2; //InterfaceMethod scala/collection/generic/SequenceTemplate.prefixLength:(Lscala/Function1;)I
   8:	invokeinterface	#220,  2; //InterfaceMethod scala/collection/generic/VectorTemplate.take:(I)Lscala/collection/generic/VectorTemplate;
   13:	areturn
  LineNumberTable: 
   line 147: 0

  LocalVariableTable: 
   Start  Length  Slot  Name   Signature
   0      14      0    $this       Lscala/collection/generic/VectorTemplate;
   0      14      1    p       Lscala/Function1;


public static scala.Tuple2 splitAt(scala.collection.generic.VectorTemplate, int);
  Code:
   Stack=5, Locals=2, Args_size=2
   0:	new	#223; //class scala/Tuple2
   3:	dup
   4:	aload_0
   5:	iload_1
   6:	invokeinterface	#220,  2; //InterfaceMethod scala/collection/generic/VectorTemplate.take:(I)Lscala/collection/generic/VectorTemplate;
   11:	aload_0
   12:	iload_1
   13:	invokeinterface	#216,  2; //InterfaceMethod scala/collection/generic/VectorTemplate.drop:(I)Lscala/collection/generic/VectorTemplate;
   18:	invokespecial	#226; //Method scala/Tuple2."<init>":(Ljava/lang/Object;Ljava/lang/Object;)V
   21:	areturn
  LineNumberTable: 
   line 146: 0

  LocalVariableTable: 
   Start  Length  Slot  Name   Signature
   0      22      0    $this       Lscala/collection/generic/VectorTemplate;
   0      22      1    n       I


public static scala.collection.generic.VectorTemplate dropRight(scala.collection.generic.VectorTemplate, int);
  Code:
   Stack=4, Locals=2, Args_size=2
   0:	aload_0
   1:	iconst_0
   2:	aload_0
   3:	invokeinterface	#43,  1; //InterfaceMethod scala/collection/generic/SequenceTemplate.length:()I
   8:	iload_1
   9:	isub
   10:	invokeinterface	#231,  3; //InterfaceMethod scala/collection/generic/VectorTemplate.slice:(II)Lscala/collection/generic/VectorTemplate;
   15:	areturn
  LineNumberTable: 
   line 145: 0

  LocalVariableTable: 
   Start  Length  Slot  Name   Signature
   0      16      0    $this       Lscala/collection/generic/VectorTemplate;
   0      16      1    n       I


public static scala.collection.generic.VectorTemplate takeRight(scala.collection.generic.VectorTemplate, int);
  Code:
   Stack=3, Locals=2, Args_size=2
   0:	aload_0
   1:	aload_0
   2:	invokeinterface	#43,  1; //InterfaceMethod scala/collection/generic/SequenceTemplate.length:()I
   7:	iload_1
   8:	isub
   9:	aload_0
   10:	invokeinterface	#43,  1; //InterfaceMethod scala/collection/generic/SequenceTemplate.length:()I
   15:	invokeinterface	#231,  3; //InterfaceMethod scala/collection/generic/VectorTemplate.slice:(II)Lscala/collection/generic/VectorTemplate;
   20:	areturn
  LineNumberTable: 
   line 144: 0

  LocalVariableTable: 
   Start  Length  Slot  Name   Signature
   0      21      0    $this       Lscala/collection/generic/VectorTemplate;
   0      21      1    n       I


public static scala.collection.generic.VectorTemplate drop(scala.collection.generic.VectorTemplate, int);
  Code:
   Stack=3, Locals=2, Args_size=2
   0:	aload_0
   1:	iload_1
   2:	aload_0
   3:	invokeinterface	#43,  1; //InterfaceMethod scala/collection/generic/SequenceTemplate.length:()I
   8:	invokeinterface	#231,  3; //InterfaceMethod scala/collection/generic/VectorTemplate.slice:(II)Lscala/collection/generic/VectorTemplate;
   13:	areturn
  LineNumberTable: 
   line 143: 0

  LocalVariableTable: 
   Start  Length  Slot  Name   Signature
   0      14      0    $this       Lscala/collection/generic/VectorTemplate;
   0      14      1    n       I


public static scala.collection.generic.VectorTemplate take(scala.collection.generic.VectorTemplate, int);
  Code:
   Stack=3, Locals=2, Args_size=2
   0:	aload_0
   1:	iconst_0
   2:	iload_1
   3:	invokeinterface	#231,  3; //InterfaceMethod scala/collection/generic/VectorTemplate.slice:(II)Lscala/collection/generic/VectorTemplate;
   8:	areturn
  LineNumberTable: 
   line 142: 0

  LocalVariableTable: 
   Start  Length  Slot  Name   Signature
   0      9      0    $this       Lscala/collection/generic/VectorTemplate;
   0      9      1    n       I


public static scala.collection.generic.VectorTemplate init(scala.collection.generic.VectorTemplate);
  Code:
   Stack=4, Locals=1, Args_size=1
   0:	aload_0
   1:	invokeinterface	#43,  1; //InterfaceMethod scala/collection/generic/SequenceTemplate.length:()I
   6:	iconst_0
   7:	if_icmple	28
   10:	aload_0
   11:	iconst_0
   12:	aload_0
   13:	invokeinterface	#43,  1; //InterfaceMethod scala/collection/generic/SequenceTemplate.length:()I
   18:	iconst_1
   19:	isub
   20:	invokeinterface	#231,  3; //InterfaceMethod scala/collection/generic/VectorTemplate.slice:(II)Lscala/collection/generic/VectorTemplate;
   25:	goto	34
   28:	aload_0
   29:	invokeinterface	#237,  1; //InterfaceMethod scala/collection/generic/VectorTemplate.scala$collection$generic$VectorTemplate$$super$init:()Lscala/collection/generic/VectorTemplate;
   34:	areturn
  LineNumberTable: 
   line 141: 0

  LocalVariableTable: 
   Start  Length  Slot  Name   Signature
   0      35      0    $this       Lscala/collection/generic/VectorTemplate;


public static java.lang.Object last(scala.collection.generic.VectorTemplate);
  Code:
   Stack=3, Locals=1, Args_size=1
   0:	aload_0
   1:	invokeinterface	#43,  1; //InterfaceMethod scala/collection/generic/SequenceTemplate.length:()I
   6:	iconst_0
   7:	if_icmple	27
   10:	aload_0
   11:	aload_0
   12:	invokeinterface	#43,  1; //InterfaceMethod scala/collection/generic/SequenceTemplate.length:()I
   17:	iconst_1
   18:	isub
   19:	invokeinterface	#62,  2; //InterfaceMethod scala/collection/generic/SequenceTemplate.apply:(I)Ljava/lang/Object;
   24:	goto	33
   27:	aload_0
   28:	invokeinterface	#241,  1; //InterfaceMethod scala/collection/generic/VectorTemplate.scala$collection$generic$VectorTemplate$$super$last:()Ljava/lang/Object;
   33:	areturn
  LineNumberTable: 
   line 140: 0

  LocalVariableTable: 
   Start  Length  Slot  Name   Signature
   0      34      0    $this       Lscala/collection/generic/VectorTemplate;


public static scala.collection.generic.VectorTemplate tail(scala.collection.generic.VectorTemplate);
  Code:
   Stack=3, Locals=1, Args_size=1
   0:	aload_0
   1:	iconst_1
   2:	aload_0
   3:	invokeinterface	#43,  1; //InterfaceMethod scala/collection/generic/SequenceTemplate.length:()I
   8:	invokeinterface	#231,  3; //InterfaceMethod scala/collection/generic/VectorTemplate.slice:(II)Lscala/collection/generic/VectorTemplate;
   13:	areturn
  LineNumberTable: 
   line 139: 0

  LocalVariableTable: 
   Start  Length  Slot  Name   Signature
   0      14      0    $this       Lscala/collection/generic/VectorTemplate;


public static java.lang.Object head(scala.collection.generic.VectorTemplate);
  Code:
   Stack=2, Locals=1, Args_size=1
   0:	aload_0
   1:	invokeinterface	#246,  1; //InterfaceMethod scala/collection/generic/VectorTemplate.isEmpty:()Z
   6:	ifeq	18
   9:	aload_0
   10:	invokeinterface	#249,  1; //InterfaceMethod scala/collection/generic/VectorTemplate.scala$collection$generic$VectorTemplate$$super$head:()Ljava/lang/Object;
   15:	goto	25
   18:	aload_0
   19:	iconst_0
   20:	invokeinterface	#62,  2; //InterfaceMethod scala/collection/generic/SequenceTemplate.apply:(I)Ljava/lang/Object;
   25:	areturn
  LineNumberTable: 
   line 138: 0

  LocalVariableTable: 
   Start  Length  Slot  Name   Signature
   0      26      0    $this       Lscala/collection/generic/VectorTemplate;


public static scala.collection.generic.VectorTemplate slice(scala.collection.generic.VectorTemplate, int, int);
  Code:
   Stack=3, Locals=6, Args_size=3
   0:	getstatic	#147; //Field scala/Predef$.MODULE$:Lscala/Predef$;
   3:	iload_1
   4:	invokevirtual	#151; //Method scala/Predef$.intWrapper:(I)Lscala/runtime/RichInt;
   7:	iconst_0
   8:	invokevirtual	#157; //Method scala/runtime/RichInt.max:(I)I
   11:	istore_3
   12:	getstatic	#147; //Field scala/Predef$.MODULE$:Lscala/Predef$;
   15:	iload_2
   16:	invokevirtual	#151; //Method scala/Predef$.intWrapper:(I)Lscala/runtime/RichInt;
   19:	aload_0
   20:	invokeinterface	#43,  1; //InterfaceMethod scala/collection/generic/SequenceTemplate.length:()I
   25:	invokevirtual	#182; //Method scala/runtime/RichInt.min:(I)I
   28:	istore	4
   30:	aload_0
   31:	invokeinterface	#112,  1; //InterfaceMethod scala/collection/generic/TraversableTemplate.newBuilder:()Lscala/collection/generic/Builder;
   36:	astore	5
   38:	aload	5
   40:	iload	4
   42:	iload_3
   43:	isub
   44:	invokeinterface	#118,  2; //InterfaceMethod scala/collection/generic/Builder.sizeHint:(I)V
   49:	iload_3
   50:	iload	4
   52:	if_icmpge	77
   55:	aload	5
   57:	aload_0
   58:	iload_3
   59:	invokeinterface	#62,  2; //InterfaceMethod scala/collection/generic/SequenceTemplate.apply:(I)Ljava/lang/Object;
   64:	invokeinterface	#122,  2; //InterfaceMethod scala/collection/generic/Builder.$plus$eq:(Ljava/lang/Object;)Lscala/collection/generic/Builder;
   69:	pop
   70:	iload_3
   71:	iconst_1
   72:	iadd
   73:	istore_3
   74:	goto	49
   77:	aload	5
   79:	invokeinterface	#125,  1; //InterfaceMethod scala/collection/generic/Builder.result:()Ljava/lang/Object;
   84:	checkcast	#13; //class scala/collection/generic/VectorTemplate
   87:	areturn
  LineNumberTable: 
   line 127: 0
   line 128: 12
   line 129: 30
   line 130: 38
   line 131: 49
   line 132: 55
   line 133: 70
   line 131: 74
   line 135: 77

  LocalVariableTable: 
   Start  Length  Slot  Name   Signature
   0      88      0    $this       Lscala/collection/generic/VectorTemplate;
   0      88      1    from       I
   0      88      2    until       I
   12      75      3    i       I
   30      57      4    end       I
   38      49      5    b       Lscala/collection/generic/Builder;


public static java.lang.Object zipWithIndex(scala.collection.generic.VectorTemplate, scala.collection.generic.BuilderFactory);
  Code:
   Stack=5, Locals=5, Args_size=2
   0:	aload_1
   1:	aload_0
   2:	invokeinterface	#256,  1; //InterfaceMethod scala/collection/generic/TraversableTemplate.thisCollection:()Lscala/collection/generic/TraversableTemplate;
   7:	invokeinterface	#260,  2; //InterfaceMethod scala/collection/generic/BuilderFactory.apply:(Ljava/lang/Object;)Lscala/collection/generic/Builder;
   12:	astore_2
   13:	aload_0
   14:	invokeinterface	#43,  1; //InterfaceMethod scala/collection/generic/SequenceTemplate.length:()I
   19:	istore_3
   20:	aload_2
   21:	iload_3
   22:	invokeinterface	#118,  2; //InterfaceMethod scala/collection/generic/Builder.sizeHint:(I)V
   27:	iconst_0
   28:	istore	4
   30:	iload	4
   32:	iload_3
   33:	if_icmpge	72
   36:	aload_2
   37:	new	#223; //class scala/Tuple2
   40:	dup
   41:	aload_0
   42:	iload	4
   44:	invokeinterface	#62,  2; //InterfaceMethod scala/collection/generic/SequenceTemplate.apply:(I)Ljava/lang/Object;
   49:	iload	4
   51:	invokestatic	#264; //Method scala/runtime/BoxesRunTime.boxToInteger:(I)Ljava/lang/Integer;
   54:	invokespecial	#226; //Method scala/Tuple2."<init>":(Ljava/lang/Object;Ljava/lang/Object;)V
   57:	invokeinterface	#122,  2; //InterfaceMethod scala/collection/generic/Builder.$plus$eq:(Ljava/lang/Object;)Lscala/collection/generic/Builder;
   62:	pop
   63:	iload	4
   65:	iconst_1
   66:	iadd
   67:	istore	4
   69:	goto	30
   72:	aload_2
   73:	invokeinterface	#125,  1; //InterfaceMethod scala/collection/generic/Builder.result:()Ljava/lang/Object;
   78:	areturn
  LineNumberTable: 
   line 115: 0
   line 116: 13
   line 117: 20
   line 118: 27
   line 119: 30
   line 120: 36
   line 121: 63
   line 119: 69
   line 123: 72

  LocalVariableTable: 
   Start  Length  Slot  Name   Signature
   0      79      0    $this       Lscala/collection/generic/VectorTemplate;
   0      79      1    bf       Lscala/collection/generic/BuilderFactory;
   13      65      2    b       Lscala/collection/generic/Builder;
   20      58      3    len       I
   30      48      4    i       I


public static java.lang.Object zip(scala.collection.generic.VectorTemplate, scala.collection.Sequence, scala.collection.generic.BuilderFactory);
  Code:
   Stack=6, Locals=9, Args_size=3
   0:	aload_1
   1:	astore_3
   2:	aload_3
   3:	instanceof	#37; //class scala/collection/Vector
   6:	ifeq	127
   9:	aload_3
   10:	checkcast	#37; //class scala/collection/Vector
   13:	astore	4
   15:	aload	4
   17:	astore	5
   19:	aload_2
   20:	aload_0
   21:	invokeinterface	#256,  1; //InterfaceMethod scala/collection/generic/TraversableTemplate.thisCollection:()Lscala/collection/generic/TraversableTemplate;
   26:	invokeinterface	#260,  2; //InterfaceMethod scala/collection/generic/BuilderFactory.apply:(Ljava/lang/Object;)Lscala/collection/generic/Builder;
   31:	astore	6
   33:	iconst_0
   34:	istore	7
   36:	getstatic	#147; //Field scala/Predef$.MODULE$:Lscala/Predef$;
   39:	aload_0
   40:	invokeinterface	#43,  1; //InterfaceMethod scala/collection/generic/SequenceTemplate.length:()I
   45:	invokevirtual	#151; //Method scala/Predef$.intWrapper:(I)Lscala/runtime/RichInt;
   48:	aload	5
   50:	invokeinterface	#43,  1; //InterfaceMethod scala/collection/generic/SequenceTemplate.length:()I
   55:	invokevirtual	#182; //Method scala/runtime/RichInt.min:(I)I
   58:	istore	8
   60:	aload	6
   62:	iload	8
   64:	invokeinterface	#118,  2; //InterfaceMethod scala/collection/generic/Builder.sizeHint:(I)V
   69:	iload	7
   71:	iload	8
   73:	if_icmpge	117
   76:	aload	6
   78:	new	#223; //class scala/Tuple2
   81:	dup
   82:	aload_0
   83:	iload	7
   85:	invokeinterface	#62,  2; //InterfaceMethod scala/collection/generic/SequenceTemplate.apply:(I)Ljava/lang/Object;
   90:	aload	5
   92:	iload	7
   94:	invokeinterface	#62,  2; //InterfaceMethod scala/collection/generic/SequenceTemplate.apply:(I)Ljava/lang/Object;
   99:	invokespecial	#226; //Method scala/Tuple2."<init>":(Ljava/lang/Object;Ljava/lang/Object;)V
   102:	invokeinterface	#122,  2; //InterfaceMethod scala/collection/generic/Builder.$plus$eq:(Ljava/lang/Object;)Lscala/collection/generic/Builder;
   107:	pop
   108:	iload	7
   110:	iconst_1
   111:	iadd
   112:	istore	7
   114:	goto	69
   117:	aload	6
   119:	invokeinterface	#125,  1; //InterfaceMethod scala/collection/generic/Builder.result:()Ljava/lang/Object;
   124:	goto	135
   127:	aload_0
   128:	aload_1
   129:	aload_2
   130:	invokeinterface	#272,  3; //InterfaceMethod scala/collection/generic/VectorTemplate.scala$collection$generic$VectorTemplate$$super$zip:(Lscala/collection/Sequence;Lscala/collection/generic/BuilderFactory;)Ljava/lang/Object;
   135:	areturn
  LineNumberTable: 
   line 99: 0
   line 100: 15
   line 101: 19
   line 102: 33
   line 103: 36
   line 104: 60
   line 105: 69
   line 106: 76
   line 107: 108
   line 105: 114
   line 109: 117
   line 111: 127
   line 99: 135

  LocalVariableTable: 
   Start  Length  Slot  Name   Signature
   0      136      0    $this       Lscala/collection/generic/VectorTemplate;
   0      136      1    that       Lscala/collection/Sequence;
   0      136      2    bf       Lscala/collection/generic/BuilderFactory;
   2      134      3    temp1       Lscala/collection/Sequence;
   15      109      4    temp2       Lscala/collection/Vector;
   19      105      5    that       Lscala/collection/Vector;
   33      91      6    b       Lscala/collection/generic/Builder;
   36      88      7    i       I
   60      64      8    len       I


public static java.lang.Object reduceRight(scala.collection.generic.VectorTemplate, scala.Function2);
  Code:
   Stack=6, Locals=2, Args_size=2
   0:	aload_0
   1:	invokeinterface	#43,  1; //InterfaceMethod scala/collection/generic/SequenceTemplate.length:()I
   6:	iconst_0
   7:	if_icmple	41
   10:	aload_0
   11:	iconst_0
   12:	aload_0
   13:	invokeinterface	#43,  1; //InterfaceMethod scala/collection/generic/SequenceTemplate.length:()I
   18:	iconst_1
   19:	isub
   20:	aload_0
   21:	aload_0
   22:	invokeinterface	#43,  1; //InterfaceMethod scala/collection/generic/SequenceTemplate.length:()I
   27:	iconst_1
   28:	isub
   29:	invokeinterface	#62,  2; //InterfaceMethod scala/collection/generic/SequenceTemplate.apply:(I)Ljava/lang/Object;
   34:	aload_1
   35:	invokestatic	#280; //Method foldr:(Lscala/collection/generic/VectorTemplate;IILjava/lang/Object;Lscala/Function2;)Ljava/lang/Object;
   38:	goto	48
   41:	aload_0
   42:	aload_1
   43:	invokeinterface	#284,  2; //InterfaceMethod scala/collection/generic/VectorTemplate.scala$collection$generic$VectorTemplate$$super$reduceRight:(Lscala/Function2;)Ljava/lang/Object;
   48:	areturn
  LineNumberTable: 
   line 97: 0

  LocalVariableTable: 
   Start  Length  Slot  Name   Signature
   0      49      0    $this       Lscala/collection/generic/VectorTemplate;
   0      49      1    op       Lscala/Function2;


public static java.lang.Object reduceLeft(scala.collection.generic.VectorTemplate, scala.Function2);
  Code:
   Stack=4, Locals=2, Args_size=2
   0:	aload_0
   1:	invokeinterface	#43,  1; //InterfaceMethod scala/collection/generic/SequenceTemplate.length:()I
   6:	iconst_0
   7:	if_icmple	26
   10:	aload_0
   11:	iconst_1
   12:	aload_0
   13:	iconst_0
   14:	invokeinterface	#62,  2; //InterfaceMethod scala/collection/generic/SequenceTemplate.apply:(I)Ljava/lang/Object;
   19:	aload_1
   20:	invokestatic	#291; //Method foldl:(Lscala/collection/generic/VectorTemplate;ILjava/lang/Object;Lscala/Function2;)Ljava/lang/Object;
   23:	goto	33
   26:	aload_0
   27:	aload_1
   28:	invokeinterface	#294,  2; //InterfaceMethod scala/collection/generic/VectorTemplate.scala$collection$generic$VectorTemplate$$super$reduceLeft:(Lscala/Function2;)Ljava/lang/Object;
   33:	areturn
  LineNumberTable: 
   line 95: 0

  LocalVariableTable: 
   Start  Length  Slot  Name   Signature
   0      34      0    $this       Lscala/collection/generic/VectorTemplate;
   0      34      1    op       Lscala/Function2;


public static java.lang.Object foldRight(scala.collection.generic.VectorTemplate, java.lang.Object, scala.Function2);
  Code:
   Stack=5, Locals=3, Args_size=3
   0:	aload_0
   1:	iconst_0
   2:	aload_0
   3:	invokeinterface	#43,  1; //InterfaceMethod scala/collection/generic/SequenceTemplate.length:()I
   8:	aload_1
   9:	aload_2
   10:	invokestatic	#280; //Method foldr:(Lscala/collection/generic/VectorTemplate;IILjava/lang/Object;Lscala/Function2;)Ljava/lang/Object;
   13:	areturn
  LineNumberTable: 
   line 93: 0

  LocalVariableTable: 
   Start  Length  Slot  Name   Signature
   0      14      0    $this       Lscala/collection/generic/VectorTemplate;
   0      14      1    z       Ljava/lang/Object;
   0      14      2    op       Lscala/Function2;


public static java.lang.Object foldLeft(scala.collection.generic.VectorTemplate, java.lang.Object, scala.Function2);
  Code:
   Stack=4, Locals=3, Args_size=3
   0:	aload_0
   1:	iconst_0
   2:	aload_1
   3:	aload_2
   4:	invokestatic	#291; //Method foldl:(Lscala/collection/generic/VectorTemplate;ILjava/lang/Object;Lscala/Function2;)Ljava/lang/Object;
   7:	areturn
  LineNumberTable: 
   line 91: 0

  LocalVariableTable: 
   Start  Length  Slot  Name   Signature
   0      8      0    $this       Lscala/collection/generic/VectorTemplate;
   0      8      1    z       Ljava/lang/Object;
   0      8      2    op       Lscala/Function2;


public static scala.Option find(scala.collection.generic.VectorTemplate, scala.Function1);
  Code:
   Stack=5, Locals=3, Args_size=2
   0:	aload_0
   1:	new	#310; //class scala/collection/generic/VectorTemplate$$anonfun$1
   4:	dup
   5:	aload_0
   6:	aload_1
   7:	invokespecial	#311; //Method scala/collection/generic/VectorTemplate$$anonfun$1."<init>":(Lscala/collection/generic/VectorTemplate;Lscala/Function1;)V
   10:	invokeinterface	#206,  2; //InterfaceMethod scala/collection/generic/SequenceTemplate.prefixLength:(Lscala/Function1;)I
   15:	istore_2
   16:	iload_2
   17:	aload_0
   18:	invokeinterface	#43,  1; //InterfaceMethod scala/collection/generic/SequenceTemplate.length:()I
   23:	if_icmpge	43
   26:	new	#313; //class scala/Some
   29:	dup
   30:	aload_0
   31:	iload_2
   32:	invokeinterface	#62,  2; //InterfaceMethod scala/collection/generic/SequenceTemplate.apply:(I)Ljava/lang/Object;
   37:	invokespecial	#316; //Method scala/Some."<init>":(Ljava/lang/Object;)V
   40:	goto	46
   43:	getstatic	#321; //Field scala/None$.MODULE$:Lscala/None$;
   46:	areturn
  LineNumberTable: 
   line 71: 0
   line 72: 16
   line 70: 46

  LocalVariableTable: 
   Start  Length  Slot  Name   Signature
   0      47      0    $this       Lscala/collection/generic/VectorTemplate;
   0      47      1    p$3       Lscala/Function1;
   16      31      2    i       I


public static boolean exists(scala.collection.generic.VectorTemplate, scala.Function1);
  Code:
   Stack=5, Locals=2, Args_size=2
   0:	aload_0
   1:	new	#326; //class scala/collection/generic/VectorTemplate$$anonfun$exists$1
   4:	dup
   5:	aload_0
   6:	aload_1
   7:	invokespecial	#327; //Method scala/collection/generic/VectorTemplate$$anonfun$exists$1."<init>":(Lscala/collection/generic/VectorTemplate;Lscala/Function1;)V
   10:	invokeinterface	#206,  2; //InterfaceMethod scala/collection/generic/SequenceTemplate.prefixLength:(Lscala/Function1;)I
   15:	aload_0
   16:	invokeinterface	#43,  1; //InterfaceMethod scala/collection/generic/SequenceTemplate.length:()I
   21:	if_icmpeq	28
   24:	iconst_1
   25:	goto	29
   28:	iconst_0
   29:	ireturn
  LineNumberTable: 
   line 68: 0

  LocalVariableTable: 
   Start  Length  Slot  Name   Signature
   0      30      0    $this       Lscala/collection/generic/VectorTemplate;
   0      30      1    p$2       Lscala/Function1;


public static boolean forall(scala.collection.generic.VectorTemplate, scala.Function1);
  Code:
   Stack=5, Locals=2, Args_size=2
   0:	aload_0
   1:	new	#331; //class scala/collection/generic/VectorTemplate$$anonfun$forall$1
   4:	dup
   5:	aload_0
   6:	aload_1
   7:	invokespecial	#332; //Method scala/collection/generic/VectorTemplate$$anonfun$forall$1."<init>":(Lscala/collection/generic/VectorTemplate;Lscala/Function1;)V
   10:	invokeinterface	#206,  2; //InterfaceMethod scala/collection/generic/SequenceTemplate.prefixLength:(Lscala/Function1;)I
   15:	aload_0
   16:	invokeinterface	#43,  1; //InterfaceMethod scala/collection/generic/SequenceTemplate.length:()I
   21:	if_icmpne	28
   24:	iconst_1
   25:	goto	29
   28:	iconst_0
   29:	ireturn
  LineNumberTable: 
   line 67: 0

  LocalVariableTable: 
   Start  Length  Slot  Name   Signature
   0      30      0    $this       Lscala/collection/generic/VectorTemplate;
   0      30      1    p$1       Lscala/Function1;


public static void foreach(scala.collection.generic.VectorTemplate, scala.Function1);
  Code:
   Stack=3, Locals=4, Args_size=2
   0:	iconst_0
   1:	istore_2
   2:	aload_0
   3:	invokeinterface	#43,  1; //InterfaceMethod scala/collection/generic/SequenceTemplate.length:()I
   8:	istore_3
   9:	iload_2
   10:	iload_3
   11:	if_icmpge	35
   14:	aload_1
   15:	aload_0
   16:	iload_2
   17:	invokeinterface	#62,  2; //InterfaceMethod scala/collection/generic/SequenceTemplate.apply:(I)Ljava/lang/Object;
   22:	invokeinterface	#134,  2; //InterfaceMethod scala/Function1.apply:(Ljava/lang/Object;)Ljava/lang/Object;
   27:	pop
   28:	iload_2
   29:	iconst_1
   30:	iadd
   31:	istore_2
   32:	goto	9
   35:	return
  LineNumberTable: 
   line 62: 0
   line 63: 2
   line 64: 9
   line 61: 35

  LocalVariableTable: 
   Start  Length  Slot  Name   Signature
   0      36      0    $this       Lscala/collection/generic/VectorTemplate;
   0      36      1    f       Lscala/Function1;
   2      34      2    i       I
   9      27      3    len       I


public static boolean isEmpty(scala.collection.generic.VectorTemplate);
  Code:
   Stack=2, Locals=1, Args_size=1
   0:	aload_0
   1:	invokeinterface	#43,  1; //InterfaceMethod scala/collection/generic/SequenceTemplate.length:()I
   6:	iconst_0
   7:	if_icmpne	14
   10:	iconst_1
   11:	goto	15
   14:	iconst_0
   15:	ireturn
  LineNumberTable: 
   line 59: 0

  LocalVariableTable: 
   Start  Length  Slot  Name   Signature
   0      16      0    $this       Lscala/collection/generic/VectorTemplate;


public static scala.collection.Iterator iterator(scala.collection.generic.VectorTemplate);
  Code:
   Stack=5, Locals=1, Args_size=1
   0:	new	#338; //class scala/collection/generic/VectorTemplate$Elements
   3:	dup
   4:	aload_0
   5:	iconst_0
   6:	aload_0
   7:	invokeinterface	#43,  1; //InterfaceMethod scala/collection/generic/SequenceTemplate.length:()I
   12:	invokespecial	#341; //Method scala/collection/generic/VectorTemplate$Elements."<init>":(Lscala/collection/generic/VectorTemplate;II)V
   15:	areturn
  LineNumberTable: 
   line 57: 0

  LocalVariableTable: 
   Start  Length  Slot  Name   Signature
   0      16      0    $this       Lscala/collection/generic/VectorTemplate;


}

