Compiled from "Utility.scala"
public final class scala.net.Utility$$anonfun$parseURL$1 extends java.lang.Object implements scala.Function0,scala.ScalaObject,java.io.Serializable
  SourceFile: "Utility.scala"
  Scala: length = 0x
   
  InnerClass: 
   public final #42= #10 of #41; //$anonfun$parseURL$1=class scala/net/Utility$$anonfun$parseURL$1 of class scala/net/Utility
  minor version: 0
  major version: 49
  Constant pool:
const #1 = Asciz	SourceFile;
const #2 = Asciz	Utility.scala;
const #3 = Asciz	s$1;
const #4 = Asciz	Ljava/lang/String;;
const #5 = Asciz	<init>;
const #6 = Asciz	(Ljava/lang/String;)V;
const #7 = Asciz	Code;
const #8 = Asciz	LineNumberTable;
const #9 = Asciz	scala/net/Utility$$anonfun$parseURL$1;
const #10 = class	#9;	//  scala/net/Utility$$anonfun$parseURL$1
const #11 = NameAndType	#3:#4;//  s$1:Ljava/lang/String;
const #12 = Field	#10.#11;	//  scala/net/Utility$$anonfun$parseURL$1.s$1:Ljava/lang/String;
const #13 = Asciz	java/lang/Object;
const #14 = class	#13;	//  java/lang/Object
const #15 = Asciz	()V;
const #16 = NameAndType	#5:#15;//  "<init>":()V
const #17 = Method	#14.#16;	//  java/lang/Object."<init>":()V
const #18 = Asciz	scala/Function0$class;
const #19 = class	#18;	//  scala/Function0$class
const #20 = Asciz	$init$;
const #21 = Asciz	(Lscala/Function0;)V;
const #22 = NameAndType	#20:#21;//  $init$:(Lscala/Function0;)V
const #23 = Method	#19.#22;	//  scala/Function0$class.$init$:(Lscala/Function0;)V
const #24 = Asciz	apply;
const #25 = Asciz	()Ljava/lang/Object;;
const #26 = Asciz	()Ljava/net/URL;;
const #27 = NameAndType	#24:#26;//  apply:()Ljava/net/URL;
const #28 = Method	#10.#27;	//  scala/net/Utility$$anonfun$parseURL$1.apply:()Ljava/net/URL;
const #29 = Asciz	java/net/URL;
const #30 = class	#29;	//  java/net/URL
const #31 = NameAndType	#5:#6;//  "<init>":(Ljava/lang/String;)V
const #32 = Method	#30.#31;	//  java/net/URL."<init>":(Ljava/lang/String;)V
const #33 = Asciz	toString;
const #34 = Asciz	()Ljava/lang/String;;
const #35 = Asciz	(Lscala/Function0;)Ljava/lang/String;;
const #36 = NameAndType	#33:#35;//  toString:(Lscala/Function0;)Ljava/lang/String;
const #37 = Method	#19.#36;	//  scala/Function0$class.toString:(Lscala/Function0;)Ljava/lang/String;
const #38 = Asciz	Scala;
const #39 = Asciz	InnerClasses;
const #40 = Asciz	scala/net/Utility;
const #41 = class	#40;	//  scala/net/Utility
const #42 = Asciz	$anonfun$parseURL$1;
const #43 = Asciz	scala/Function0;
const #44 = class	#43;	//  scala/Function0
const #45 = Asciz	scala/ScalaObject;
const #46 = class	#45;	//  scala/ScalaObject
const #47 = Asciz	java/io/Serializable;
const #48 = class	#47;	//  java/io/Serializable

{
public scala.net.Utility$$anonfun$parseURL$1(java.lang.String);
  Code:
   Stack=2, Locals=2, Args_size=2
   0:	aload_0
   1:	aload_1
   2:	putfield	#12; //Field s$1:Ljava/lang/String;
   5:	aload_0
   6:	invokespecial	#17; //Method java/lang/Object."<init>":()V
   9:	aload_0
   10:	invokestatic	#23; //Method scala/Function0$class.$init$:(Lscala/Function0;)V
   13:	return
  LineNumberTable: 
   line 18: 0


public final java.lang.Object apply();
  Code:
   Stack=1, Locals=1, Args_size=1
   0:	aload_0
   1:	invokevirtual	#28; //Method apply:()Ljava/net/URL;
   4:	areturn
  LineNumberTable: 
   line 18: 0


public final java.net.URL apply();
  Code:
   Stack=3, Locals=1, Args_size=1
   0:	new	#30; //class java/net/URL
   3:	dup
   4:	aload_0
   5:	getfield	#12; //Field s$1:Ljava/lang/String;
   8:	invokespecial	#32; //Method java/net/URL."<init>":(Ljava/lang/String;)V
   11:	areturn
  LineNumberTable: 
   line 18: 0


public java.lang.String toString();
  Code:
   Stack=1, Locals=1, Args_size=1
   0:	aload_0
   1:	invokestatic	#37; //Method scala/Function0$class.toString:(Lscala/Function0;)Ljava/lang/String;
   4:	areturn
  LineNumberTable: 
   line 18: 0


}

