Compiled from "Utility.scala"
public final class scala.net.Utility extends java.lang.Object
  SourceFile: "Utility.scala"
  ScalaSig: length = 0xFF
   05 00 2F 07 05 01 02 FFFFFF88 02 07 01 07 55 74 69 6C
   69 74 79 0A 02 03 04 01 03 6E 65 74 0A 01 05 01
   05 73 63 61 6C 61 03 00 10 02 08 09 0D 01 02 06
   08 0A 02 FFFFFF84 FFFFFF80 FFFFFF80 FFFFFF88 02 0B 02 07 55 74 69 6C 69
   74 79 13 03 09 0C 14 10 02 0D 12 0D 01 0E 0A 02
   0F 10 01 04 6C 61 6E 67 0A 01 11 01 04 6A 61 76
   61 09 02 13 0E 02 06 4F 62 6A 65 63 74 10 02 15
   16 0D 01 04 09 02 17 04 02 0B 53 63 61 6C 61 4F
   62 6A 65 63 74 08 05 19 09 FFFFFF84 00 1A 01 06 3C 69
   6E 69 74 3E 14 01 07 08 05 1C 09 FFFFFF84 00 1D 01 08
   70 61 72 73 65 55 52 4C 14 02 1E 26 10 03 15 1F
   21 09 02 20 04 02 06 4F 70 74 69 6F 6E 10 02 22
   24 0D 01 23 0A 02 03 10 09 02 25 23 02 03 55 52
   4C 08 05 27 1B FFFFFFC0 00 28 01 01 73 10 02 29 2C 0E
   02 15 2A 09 02 2B 04 01 06 50 72 65 64 65 66 09
   02 2D 2E 02 06 53 74 72 69 6E 67 0A 02 2B 04 
  InnerClass: 
   public final #22= #19 of #21; //$anonfun$parseURL$1=class scala/net/Utility$$anonfun$parseURL$1 of class scala/net/Utility
  minor version: 0
  major version: 49
  Constant pool:
const #1 = Asciz	SourceFile;
const #2 = Asciz	Utility.scala;
const #3 = Asciz	parseURL;
const #4 = Asciz	(Ljava/lang/String;)Lscala/Option;;
const #5 = Asciz	Code;
const #6 = Asciz	scala/net/Utility$;
const #7 = class	#6;	//  scala/net/Utility$
const #8 = Asciz	MODULE$;
const #9 = Asciz	Lscala/net/Utility$;;
const #10 = NameAndType	#8:#9;//  MODULE$:Lscala/net/Utility$;
const #11 = Field	#7.#10;	//  scala/net/Utility$.MODULE$:Lscala/net/Utility$;
const #12 = NameAndType	#3:#4;//  parseURL:(Ljava/lang/String;)Lscala/Option;
const #13 = Method	#7.#12;	//  scala/net/Utility$.parseURL:(Ljava/lang/String;)Lscala/Option;
const #14 = Asciz	(Ljava/lang/String;)Lscala/Option<Ljava/net/URL;>;;
const #15 = Asciz	Signature;
const #16 = Asciz	ScalaSig;
const #17 = Asciz	InnerClasses;
const #18 = Asciz	scala/net/Utility$$anonfun$parseURL$1;
const #19 = class	#18;	//  scala/net/Utility$$anonfun$parseURL$1
const #20 = Asciz	scala/net/Utility;
const #21 = class	#20;	//  scala/net/Utility
const #22 = Asciz	$anonfun$parseURL$1;
const #23 = Asciz	java/lang/Object;
const #24 = class	#23;	//  java/lang/Object

{
public static final scala.Option parseURL(java.lang.String);
  Code:
   Stack=2, Locals=1, Args_size=1
   0:	getstatic	#11; //Field scala/net/Utility$.MODULE$:Lscala/net/Utility$;
   3:	aload_0
   4:	invokevirtual	#13; //Method scala/net/Utility$.parseURL:(Ljava/lang/String;)Lscala/Option;
   7:	areturn
  Signature: length = 0x2
   00 0E 

}

