Compiled from "Utility.scala"
public final class scala.net.Utility$ extends java.lang.Object implements scala.ScalaObject
  SourceFile: "Utility.scala"
  Scala: length = 0x
   
  InnerClass: 
   public #64= #50 of #63; //Catch=class scala/util/control/Exception$Catch of class scala/util/control/Exception
   public final #67= #45 of #66; //$anonfun$parseURL$1=class scala/net/Utility$$anonfun$parseURL$1 of class scala/net/Utility
  minor version: 0
  major version: 49
  Constant pool:
const #1 = Asciz	SourceFile;
const #2 = Asciz	Utility.scala;
const #3 = Asciz	Scala;
const #4 = Asciz	MODULE$;
const #5 = Asciz	Lscala/net/Utility$;;
const #6 = Asciz	<clinit>;
const #7 = Asciz	()V;
const #8 = Asciz	Code;
const #9 = Asciz	scala/net/Utility$;
const #10 = class	#9;	//  scala/net/Utility$
const #11 = Asciz	<init>;
const #12 = NameAndType	#11:#7;//  "<init>":()V
const #13 = Method	#10.#12;	//  scala/net/Utility$."<init>":()V
const #14 = Asciz	LineNumberTable;
const #15 = Asciz	java/lang/Object;
const #16 = class	#15;	//  java/lang/Object
const #17 = Method	#16.#12;	//  java/lang/Object."<init>":()V
const #18 = NameAndType	#4:#5;//  MODULE$:Lscala/net/Utility$;
const #19 = Field	#10.#18;	//  scala/net/Utility$.MODULE$:Lscala/net/Utility$;
const #20 = Asciz	parseURL;
const #21 = Asciz	(Ljava/lang/String;)Lscala/Option;;
const #22 = Asciz	scala/util/control/Exception$;
const #23 = class	#22;	//  scala/util/control/Exception$
const #24 = Asciz	Lscala/util/control/Exception$;;
const #25 = NameAndType	#4:#24;//  MODULE$:Lscala/util/control/Exception$;
const #26 = Field	#23.#25;	//  scala/util/control/Exception$.MODULE$:Lscala/util/control/Exception$;
const #27 = Asciz	scala/runtime/ScalaRunTime$;
const #28 = class	#27;	//  scala/runtime/ScalaRunTime$
const #29 = Asciz	Lscala/runtime/ScalaRunTime$;;
const #30 = NameAndType	#4:#29;//  MODULE$:Lscala/runtime/ScalaRunTime$;
const #31 = Field	#28.#30;	//  scala/runtime/ScalaRunTime$.MODULE$:Lscala/runtime/ScalaRunTime$;
const #32 = Asciz	java/lang/Class;
const #33 = class	#32;	//  java/lang/Class
const #34 = Asciz	java/net/MalformedURLException;
const #35 = class	#34;	//  java/net/MalformedURLException
const #36 = Asciz	boxArray;
const #37 = Asciz	(Ljava/lang/Object;)Lscala/runtime/BoxedArray;;
const #38 = NameAndType	#36:#37;//  boxArray:(Ljava/lang/Object;)Lscala/runtime/BoxedArray;
const #39 = Method	#28.#38;	//  scala/runtime/ScalaRunTime$.boxArray:(Ljava/lang/Object;)Lscala/runtime/BoxedArray;
const #40 = Asciz	catching;
const #41 = Asciz	(Lscala/collection/Sequence;)Lscala/util/control/Exception$Catch;;
const #42 = NameAndType	#40:#41;//  catching:(Lscala/collection/Sequence;)Lscala/util/control/Exception$Catch;
const #43 = Method	#23.#42;	//  scala/util/control/Exception$.catching:(Lscala/collection/Sequence;)Lscala/util/control/Exception$Catch;
const #44 = Asciz	scala/net/Utility$$anonfun$parseURL$1;
const #45 = class	#44;	//  scala/net/Utility$$anonfun$parseURL$1
const #46 = Asciz	(Ljava/lang/String;)V;
const #47 = NameAndType	#11:#46;//  "<init>":(Ljava/lang/String;)V
const #48 = Method	#45.#47;	//  scala/net/Utility$$anonfun$parseURL$1."<init>":(Ljava/lang/String;)V
const #49 = Asciz	scala/util/control/Exception$Catch;
const #50 = class	#49;	//  scala/util/control/Exception$Catch
const #51 = Asciz	opt;
const #52 = Asciz	(Lscala/Function0;)Lscala/Option;;
const #53 = NameAndType	#51:#52;//  opt:(Lscala/Function0;)Lscala/Option;
const #54 = Method	#50.#53;	//  scala/util/control/Exception$Catch.opt:(Lscala/Function0;)Lscala/Option;
const #55 = Asciz	this;
const #56 = Asciz	s$1;
const #57 = Asciz	Ljava/lang/String;;
const #58 = Asciz	LocalVariableTable;
const #59 = Asciz	(Ljava/lang/String;)Lscala/Option<Ljava/net/URL;>;;
const #60 = Asciz	Signature;
const #61 = Asciz	InnerClasses;
const #62 = Asciz	scala/util/control/Exception;
const #63 = class	#62;	//  scala/util/control/Exception
const #64 = Asciz	Catch;
const #65 = Asciz	scala/net/Utility;
const #66 = class	#65;	//  scala/net/Utility
const #67 = Asciz	$anonfun$parseURL$1;
const #68 = Asciz	scala/ScalaObject;
const #69 = class	#68;	//  scala/ScalaObject

{
public static final scala.net.Utility$ MODULE$;

public static {};
  Code:
   Stack=1, Locals=0, Args_size=0
   0:	new	#10; //class scala/net/Utility$
   3:	invokespecial	#13; //Method "<init>":()V
   6:	return

public scala.Option parseURL(java.lang.String);
  Code:
   Stack=6, Locals=2, Args_size=2
   0:	getstatic	#26; //Field scala/util/control/Exception$.MODULE$:Lscala/util/control/Exception$;
   3:	getstatic	#31; //Field scala/runtime/ScalaRunTime$.MODULE$:Lscala/runtime/ScalaRunTime$;
   6:	iconst_1
   7:	anewarray	#33; //class java/lang/Class
   10:	dup
   11:	iconst_0
   12:	ldc	#35; //class java/net/MalformedURLException
   14:	aastore
   15:	invokevirtual	#39; //Method scala/runtime/ScalaRunTime$.boxArray:(Ljava/lang/Object;)Lscala/runtime/BoxedArray;
   18:	invokevirtual	#43; //Method scala/util/control/Exception$.catching:(Lscala/collection/Sequence;)Lscala/util/control/Exception$Catch;
   21:	new	#45; //class scala/net/Utility$$anonfun$parseURL$1
   24:	dup
   25:	aload_1
   26:	invokespecial	#48; //Method scala/net/Utility$$anonfun$parseURL$1."<init>":(Ljava/lang/String;)V
   29:	invokevirtual	#54; //Method scala/util/control/Exception$Catch.opt:(Lscala/Function0;)Lscala/Option;
   32:	areturn
  LineNumberTable: 
   line 18: 0

  LocalVariableTable: 
   Start  Length  Slot  Name   Signature
   0      33      0    this       Lscala/net/Utility$;
   0      33      1    s$1       Ljava/lang/String;

  Signature: length = 0x2
   00 3B 

}

