Compiled from "Base.scala"
public final class scala.util.regexp.Base$Eps$ extends scala.util.regexp.Base$RegExp implements scala.ScalaObject,scala.Product,java.io.Serializable
  SourceFile: "Base.scala"
  Scala: length = 0x
   
  InnerClass: 
   public abstract RegExp=class scala/util/regexp/Base$RegExp of class scala/util/regexp/Base
  minor version: 0
  major version: 49
  Constant pool:
Asciz	SourceFile;
Asciz	Base.scala;
Asciz	Scala;
Asciz	bitmap$0;
Asciz	I;
Asciz	isNullable;
Asciz	Z;
Asciz	<init>;
Asciz	(Lscala/util/regexp/Base;)V;
Asciz	Code;
Asciz	LineNumberTable;
Asciz	scala/util/regexp/Base$RegExp;
class	scala/util/regexp/Base$RegExp
NameAndType	"<init>":(Lscala/util/regexp/Base;)V
Method	scala/util/regexp/Base$RegExp."<init>":(Lscala/util/regexp/Base;)V
Asciz	scala/Product$class;
class	scala/Product$class
Asciz	$init$;
Asciz	(Lscala/Product;)V;
NameAndType	$init$:(Lscala/Product;)V
Method	scala/Product$class.$init$:(Lscala/Product;)V
Asciz	this;
Asciz	Lscala/util/regexp/Base$Eps$;;
Asciz	$outer;
Asciz	Lscala/util/regexp/Base;;
Asciz	LocalVariableTable;
Asciz	scala$util$regexp$Base$Eps$$$outer;
Asciz	()Lscala/util/regexp/Base;;
NameAndType	$outer:Lscala/util/regexp/Base;
Field	scala/util/regexp/Base$RegExp.$outer:Lscala/util/regexp/Base;
Asciz	readResolve;
Asciz	()Ljava/lang/Object;;
Asciz	scala/util/regexp/Base$Eps$;
class	scala/util/regexp/Base$Eps$
NameAndType	scala$util$regexp$Base$Eps$$$outer:()Lscala/util/regexp/Base;
Method	scala/util/regexp/Base$Eps$.scala$util$regexp$Base$Eps$$$outer:()Lscala/util/regexp/Base;
Asciz	scala/util/regexp/Base;
class	scala/util/regexp/Base
Asciz	Eps;
Asciz	()Lscala/util/regexp/Base$Eps$;;
NameAndType	Eps:()Lscala/util/regexp/Base$Eps$;
Method	scala/util/regexp/Base.Eps:()Lscala/util/regexp/Base$Eps$;
Asciz	canEqual;
Asciz	(Ljava/lang/Object;)Z;
Asciz	productElement;
Asciz	(I)Ljava/lang/Object;;
Asciz	java/lang/IndexOutOfBoundsException;
class	java/lang/IndexOutOfBoundsException
Asciz	scala/runtime/BoxesRunTime;
class	scala/runtime/BoxesRunTime
Asciz	boxToInteger;
Asciz	(I)Ljava/lang/Integer;;
NameAndType	boxToInteger:(I)Ljava/lang/Integer;
Method	scala/runtime/BoxesRunTime.boxToInteger:(I)Ljava/lang/Integer;
Asciz	java/lang/Object;
class	java/lang/Object
Asciz	toString;
Asciz	()Ljava/lang/String;;
NameAndType	toString:()Ljava/lang/String;
Method	java/lang/Object.toString:()Ljava/lang/String;
Asciz	(Ljava/lang/String;)V;
NameAndType	"<init>":(Ljava/lang/String;)V
Method	java/lang/IndexOutOfBoundsException."<init>":(Ljava/lang/String;)V
Asciz	scala/MatchError;
class	scala/MatchError
Method	scala/MatchError."<init>":(Ljava/lang/String;)V
Asciz	productArity;
Asciz	()I;
Asciz	productPrefix;
String	Eps
Asciz	()Z;
NameAndType	bitmap$0:I
Field	scala/util/regexp/Base$Eps$.bitmap$0:I
NameAndType	isNullable:Z
Field	scala/util/regexp/Base$Eps$.isNullable:Z
Asciz	java/lang/Throwable;
class	java/lang/Throwable
Asciz	productElements;
Asciz	()Lscala/collection/Iterator;;
Asciz	(Lscala/Product;)Lscala/collection/Iterator;;
NameAndType	productElements:(Lscala/Product;)Lscala/collection/Iterator;
Method	scala/Product$class.productElements:(Lscala/Product;)Lscala/collection/Iterator;
Asciz	productIterator;
NameAndType	productIterator:(Lscala/Product;)Lscala/collection/Iterator;
Method	scala/Product$class.productIterator:(Lscala/Product;)Lscala/collection/Iterator;
Asciz	InnerClasses;
Asciz	RegExp;
Asciz	scala/ScalaObject;
class	scala/ScalaObject
Asciz	scala/Product;
class	scala/Product
Asciz	java/io/Serializable;
class	java/io/Serializable

{
public volatile int bitmap$0;
  Signature: I

private final boolean isNullable;
  Signature: Z

public scala.util.regexp.Base$Eps$(scala.util.regexp.Base);
  Signature: (Lscala/util/regexp/Base;)V
  Code:
   Stack=2, Locals=2, Args_size=2
	aload_0
	aload_1
	invokespecial	Method scala/util/regexp/Base$RegExp."<init>":(Lscala/util/regexp/Base;)V
	aload_0
	invokestatic	Method scala/Product$class.$init$:(Lscala/Product;)V
	return
  Labels:
  LocalVariableTable: 
   Start  Length  Slot  Name   Signature
   0      10      0    this       Lscala/util/regexp/Base$Eps$;
   0      10      1    $outer       Lscala/util/regexp/Base;


public scala.util.regexp.Base scala$util$regexp$Base$Eps$$$outer();
  Signature: ()Lscala/util/regexp/Base;
  Code:
   Stack=1, Locals=1, Args_size=1
	aload_0
	getfield	Field scala/util/regexp/Base$RegExp.$outer:Lscala/util/regexp/Base;
	areturn
  Labels:

public java.lang.Object readResolve();
  Signature: ()Ljava/lang/Object;
  Code:
   Stack=1, Locals=1, Args_size=1
	aload_0
	invokevirtual	Method scala$util$regexp$Base$Eps$$$outer:()Lscala/util/regexp/Base;
	invokevirtual	Method scala/util/regexp/Base.Eps:()Lscala/util/regexp/Base$Eps$;
	areturn
  Labels:

public boolean canEqual(java.lang.Object);
  Signature: (Ljava/lang/Object;)Z
  Code:
   Stack=1, Locals=2, Args_size=2
	aload_1
	instanceof	class scala/util/regexp/Base$Eps$
	ireturn
  Labels:

public java.lang.Object productElement(int);
  Signature: (I)Ljava/lang/Object;
  Code:
   Stack=3, Locals=2, Args_size=2
	iconst_1
	ifeq	l1 // new
	new	class java/lang/IndexOutOfBoundsException
	dup
	iload_1
	invokestatic	Method scala/runtime/BoxesRunTime.boxToInteger:(I)Ljava/lang/Integer;
	invokevirtual	Method java/lang/Object.toString:()Ljava/lang/String;
	invokespecial	Method java/lang/IndexOutOfBoundsException."<init>":(Ljava/lang/String;)V
	athrow
l1	new	class scala/MatchError
	dup
	iload_1
	invokestatic	Method scala/runtime/BoxesRunTime.boxToInteger:(I)Ljava/lang/Integer;
	invokevirtual	Method java/lang/Object.toString:()Ljava/lang/String;
	invokespecial	Method scala/MatchError."<init>":(Ljava/lang/String;)V
	athrow
  Labels:
   	l1 = 19 // new

public int productArity();
  Signature: ()I
  Code:
   Stack=1, Locals=1, Args_size=1
	iconst_0
	ireturn
  Labels:

public java.lang.String productPrefix();
  Signature: ()Ljava/lang/String;
  Code:
   Stack=1, Locals=1, Args_size=1
	ldc	String Eps
	areturn
  Labels:

public java.lang.String toString();
  Signature: ()Ljava/lang/String;
  Code:
   Stack=1, Locals=1, Args_size=1
	ldc	String Eps
	areturn
  Labels:

public final boolean isNullable();
  Signature: ()Z
  Code:
   Stack=3, Locals=1, Args_size=1
	aload_0
	getfield	Field bitmap$0:I
	iconst_1
	iand
	iconst_0
	if_icmpne	l1 // aload_0
	aload_0
	dup
	pop
	monitorenter
	aload_0
	getfield	Field bitmap$0:I
	iconst_1
	iand
	iconst_0
	if_icmpne	l2 // aload_0
	aload_0
	iconst_1
	putfield	Field isNullable:Z
	aload_0
	aload_0
	getfield	Field bitmap$0:I
	iconst_1
	ior
	putfield	Field bitmap$0:I
l2	aload_0
	monitorexit
l1	aload_0
	getfield	Field isNullable:Z
	ireturn
	aload_0
	monitorexit
	athrow
  Labels:
   	l2 = 39 // aload_0
   	l1 = 41 // aload_0
  Exception table:
   from   to  target type
    14    41    46   Class java/lang/Throwable


public scala.collection.Iterator productElements();
  Signature: ()Lscala/collection/Iterator;
  Code:
   Stack=1, Locals=1, Args_size=1
	aload_0
	invokestatic	Method scala/Product$class.productElements:(Lscala/Product;)Lscala/collection/Iterator;
	areturn
  Labels:

public scala.collection.Iterator productIterator();
  Signature: ()Lscala/collection/Iterator;
  Code:
   Stack=1, Locals=1, Args_size=1
	aload_0
	invokestatic	Method scala/Product$class.productIterator:(Lscala/Product;)Lscala/collection/Iterator;
	areturn
  Labels:

}

