Compiled from "Base.scala"
public abstract class scala.util.regexp.Base extends java.lang.Object implements scala.ScalaObject
  SourceFile: "Base.scala"
  ScalaSig: length = 0x7E2
   05 00 FFFFFF82 0D 06 08 01 02 FFFFFF84 FFFFFF80 FFFFFF80 FFFFFF81 00 09 02 04
   42 61 73 65 0A 02 03 04 01 06 72 65 67 65 78 70
   0A 02 05 06 01 04 75 74 69 6C 0A 01 07 01 05 73
   63 61 6C 61 03 00 13 03 00 0A 12 10 02 0B 10 0D
   01 0C 0A 02 0D 0E 01 04 6C 61 6E 67 0A 01 0F 01
   04 6A 61 76 61 09 02 11 0C 02 06 4F 62 6A 65 63
   74 10 02 13 14 0D 01 06 09 02 15 06 02 0B 53 63
   61 6C 61 4F 62 6A 65 63 74 08 05 17 00 FFFFFF84 00 18
   01 06 3C 69 6E 69 74 3E 14 01 19 10 02 1A 00 0D
   01 02 04 08 1C 00 FFFFFF84 FFFFFF80 FFFFFF80 FFFFFF82 00 1D 02 08 5F 72
   65 67 65 78 70 54 11 02 1E 21 10 02 13 1F 09 02
   20 06 02 07 4E 6F 74 68 69 6E 67 10 02 22 23 0D
   01 00 06 08 24 00 FFFFFF84 FFFFFF80 FFFFFF80 FFFFFF81 00 25 02 06 52 65
   67 45 78 70 13 03 23 0A 12 08 05 17 23 FFFFFF84 00 27
   14 01 21 08 07 29 23 FFFFFFC2 FFFFFF80 FFFFFF86 00 2A 01 0A 69 73
   4E 75 6C 6C 61 62 6C 65 15 01 2B 10 02 13 2C 09
   02 2D 06 02 07 42 6F 6F 6C 65 61 6E 06 08 2F 00
   FFFFFF84 FFFFFF80 FFFFFF80 FFFFFF80 40 30 02 03 41 6C 74 13 04 2E 21 12
   31 10 02 13 32 09 02 33 06 02 07 50 72 6F 64 75
   63 74 08 08 35 2E FFFFFF82 FFFFFFCA FFFFFF80 FFFFFF84 00 36 01 02 72 73
   15 01 37 10 03 13 38 3A 09 02 39 06 02 0A 3C 72
   65 70 65 61 74 65 64 3E 10 02 22 1B 08 08 3C 2E
   FFFFFF82 FFFFFF88 FFFFFFA0 FFFFFF80 04 37 01 03 72 73 20 08 05 17 2E FFFFFF84
   00 3E 14 02 3F 40 10 02 22 2E 08 05 35 3D FFFFFFC0 00
   37 08 07 29 2E FFFFFFC2 FFFFFF80 FFFFFF84 02 2A 08 06 43 2E FFFFFFA0 FFFFFF80
   06 2B 01 0B 69 73 4E 75 6C 6C 61 62 6C 65 20 08
   08 45 2E FFFFFF84 FFFFFF80 FFFFFF80 FFFFFF84 20 46 01 08 68 61 73 68 43
   6F 64 65 14 01 47 10 02 13 48 09 02 49 06 02 03
   49 6E 74 08 08 4B 2E FFFFFF84 FFFFFF80 FFFFFF80 FFFFFF84 20 4C 01 08 74
   6F 53 74 72 69 6E 67 14 01 4D 10 02 4E 51 0E 02
   13 4F 09 02 50 06 01 06 50 72 65 64 65 66 09 02
   52 53 02 06 53 74 72 69 6E 67 0A 02 50 06 08 08
   55 2E FFFFFF84 FFFFFF80 FFFFFF80 FFFFFF84 20 56 01 06 65 71 75 61 6C 73
   14 02 2B 57 08 07 58 54 FFFFFF81 FFFFFF80 FFFFFFC0 00 59 01 03 78
   24 31 10 02 13 5A 09 02 5B 06 02 03 41 6E 79 08
   08 5D 2E FFFFFF84 FFFFFF80 FFFFFF80 FFFFFF84 20 5E 01 0D 70 72 6F 64 75
   63 74 50 72 65 66 69 78 15 01 5F 10 02 0B 60 09
   02 52 0C 08 08 62 2E FFFFFF84 FFFFFF80 FFFFFF80 FFFFFF84 20 63 01 0C 70
   72 6F 64 75 63 74 41 72 69 74 79 15 01 47 08 08
   65 2E FFFFFF84 FFFFFF80 FFFFFF80 FFFFFF84 20 66 01 0E 70 72 6F 64 75 63
   74 45 6C 65 6D 65 6E 74 14 02 59 67 08 07 58 64
   FFFFFF81 FFFFFF80 FFFFFFC0 00 47 08 08 69 2E FFFFFF84 FFFFFF80 FFFFFF80 FFFFFF84 20 6A 01
   08 63 61 6E 45 71 75 61 6C 14 02 2B 6B 08 07 58
   68 FFFFFF81 FFFFFF80 FFFFFFC0 00 59 28 02 2E 6D 10 02 13 6E 09 02
   6F 06 02 0C 73 65 72 69 61 6C 69 7A 61 62 6C 65
   07 07 71 00 FFFFFF81 FFFFFF80 FFFFFF88 02 72 01 03 41 6C 74 10 02
   22 73 06 08 2F 00 FFFFFF84 FFFFFF81 FFFFFF80 FFFFFF88 02 74 13 04 73 0A
   75 12 10 04 13 76 37 3F 09 02 77 06 02 09 46 75
   6E 63 74 69 6F 6E 31 08 05 17 73 FFFFFF84 00 79 14 01
   72 08 07 7B 73 FFFFFF81 FFFFFF80 FFFFFF84 40 7C 01 05 61 70 70 6C
   79 14 02 3F 7D 08 05 35 7A FFFFFFC0 00 37 08 08 7F 73
   FFFFFF81 FFFFFF80 FFFFFF84 40 FFFFFF81 00 01 0A 75 6E 61 70 70 6C 79 53
   65 71 14 04 FFFFFF81 01 FFFFFF81 0A 10 05 13 FFFFFF81 02 FFFFFF81 04 09
   03 FFFFFF81 03 06 02 04 53 6F 6D 65 10 05 FFFFFF81 05 FFFFFF81 08
   3A 0D 02 FFFFFF81 06 0A 03 FFFFFF81 07 06 01 0A 63 6F 6C 6C
   65 63 74 69 6F 6E 09 04 FFFFFF81 09 FFFFFF81 06 02 08 53 65
   71 75 65 6E 63 65 08 06 FFFFFF81 0B 7E FFFFFFC0 00 3F 01 03
   78 24 30 06 0A FFFFFF81 0D 00 FFFFFF84 FFFFFF80 FFFFFF80 FFFFFF80 40 FFFFFF81 0E 02
   04 53 65 71 75 13 05 FFFFFF81 0C 21 12 31 08 09 35 FFFFFF81
   0C FFFFFF82 FFFFFFCA FFFFFF80 FFFFFF84 00 36 08 09 3C FFFFFF81 0C FFFFFF82 FFFFFF88 FFFFFFA0 FFFFFF80
   04 37 08 07 17 FFFFFF81 0C FFFFFF84 00 FFFFFF81 12 14 04 FFFFFF81 13 FFFFFF81
   14 10 03 22 FFFFFF81 0C 08 06 35 FFFFFF81 11 FFFFFFC0 00 37 08 08
   29 FFFFFF81 0C FFFFFFC2 FFFFFF80 FFFFFF84 02 2A 08 07 43 FFFFFF81 0C FFFFFFA0 FFFFFF80 06
   2B 08 09 45 FFFFFF81 0C FFFFFF84 FFFFFF80 FFFFFF80 FFFFFF84 20 46 08 09 4B FFFFFF81
   0C FFFFFF84 FFFFFF80 FFFFFF80 FFFFFF84 20 4C 08 0A 55 FFFFFF81 0C FFFFFF84 FFFFFF80 FFFFFF80 FFFFFF84
   20 FFFFFF81 1A 14 03 2B FFFFFF81 1B 08 08 58 FFFFFF81 19 FFFFFF81 FFFFFF80 FFFFFFC0
   00 59 08 09 5D FFFFFF81 0C FFFFFF84 FFFFFF80 FFFFFF80 FFFFFF84 20 5E 08 09 62
   FFFFFF81 0C FFFFFF84 FFFFFF80 FFFFFF80 FFFFFF84 20 63 08 0A 65 FFFFFF81 0C FFFFFF84 FFFFFF80 FFFFFF80
   FFFFFF84 20 FFFFFF81 1F 14 03 59 FFFFFF81 20 08 08 58 FFFFFF81 1E FFFFFF81 FFFFFF80
   FFFFFFC0 00 47 08 0A 69 FFFFFF81 0C FFFFFF84 FFFFFF80 FFFFFF80 FFFFFF84 20 FFFFFF81 22 14
   03 2B FFFFFF81 23 08 08 58 FFFFFF81 21 FFFFFF81 FFFFFF80 FFFFFFC0 00 59 28 03
   FFFFFF81 0C 6D 07 09 FFFFFF81 26 00 FFFFFF81 FFFFFF80 FFFFFF88 02 FFFFFF81 27 01 04
   53 65 71 75 10 03 22 FFFFFF81 28 06 0A FFFFFF81 0D 00 FFFFFF84 FFFFFF81
   FFFFFF80 FFFFFF88 02 FFFFFF81 29 13 06 FFFFFF81 28 0A FFFFFF81 2A 12 10 05 13
   76 37 FFFFFF81 13 08 07 17 FFFFFF81 28 FFFFFF84 00 FFFFFF81 2C 14 02 FFFFFF81
   27 08 09 7B FFFFFF81 28 FFFFFF81 FFFFFF80 FFFFFF84 40 FFFFFF81 2E 14 04 FFFFFF81 13
   FFFFFF81 2F 08 06 35 FFFFFF81 2D FFFFFFC0 00 37 08 09 7F FFFFFF81 28 FFFFFF81
   FFFFFF80 FFFFFF84 40 FFFFFF81 31 14 04 FFFFFF81 01 FFFFFF81 32 08 08 FFFFFF81 0B FFFFFF81
   30 FFFFFFC0 00 FFFFFF81 13 06 0A FFFFFF81 34 00 FFFFFF84 FFFFFF80 FFFFFF80 FFFFFF80 40 FFFFFF81
   35 02 04 53 74 61 72 13 05 FFFFFF81 33 21 12 31 08 0B
   FFFFFF81 37 FFFFFF81 33 FFFFFF82 FFFFFFCA FFFFFF80 FFFFFF84 00 FFFFFF81 38 01 01 72 15 01
   3A 08 0A FFFFFF81 3A FFFFFF81 33 FFFFFF82 FFFFFF88 FFFFFFA0 FFFFFF80 04 3A 01 02 72
   20 08 07 17 FFFFFF81 33 FFFFFF84 00 FFFFFF81 3C 14 04 FFFFFF81 3D FFFFFF81 3E
   10 03 22 FFFFFF81 33 08 07 FFFFFF81 37 FFFFFF81 3B FFFFFFC0 00 3A 08 09
   29 FFFFFF81 33 FFFFFF88 FFFFFFC2 FFFFFF80 FFFFFF84 02 2A 08 09 43 FFFFFF81 33 FFFFFF88 FFFFFF80
   FFFFFFA0 FFFFFFA0 06 2B 08 0A FFFFFF81 42 FFFFFF81 33 FFFFFF81 FFFFFF80 FFFFFF84 00 FFFFFF81 43
   01 04 63 6F 70 79 14 04 FFFFFF81 3D FFFFFF81 44 08 0B FFFFFF81 45
   FFFFFF81 37 FFFFFF81 41 FFFFFF90 FFFFFF80 FFFFFFC0 00 3A 08 0A FFFFFF81 46 FFFFFF81 33 FFFFFF91
   FFFFFF80 FFFFFF84 00 FFFFFF81 38 01 0E 63 6F 70 79 24 64 65 66 61
   75 6C 74 24 31 08 09 45 FFFFFF81 33 FFFFFF84 FFFFFF80 FFFFFF80 FFFFFF84 20 46
   08 09 4B FFFFFF81 33 FFFFFF84 FFFFFF80 FFFFFF80 FFFFFF84 20 4C 08 0A 55 FFFFFF81 33
   FFFFFF84 FFFFFF80 FFFFFF80 FFFFFF84 20 FFFFFF81 4A 14 03 2B FFFFFF81 4B 08 08 58 FFFFFF81
   49 FFFFFF81 FFFFFF80 FFFFFFC0 00 59 08 09 5D FFFFFF81 33 FFFFFF84 FFFFFF80 FFFFFF80 FFFFFF84 20
   5E 08 09 62 FFFFFF81 33 FFFFFF84 FFFFFF80 FFFFFF80 FFFFFF84 20 63 08 0A 65 FFFFFF81
   33 FFFFFF84 FFFFFF80 FFFFFF80 FFFFFF84 20 FFFFFF81 4F 14 03 59 FFFFFF81 50 08 08 58
   FFFFFF81 4E FFFFFF81 FFFFFF80 FFFFFFC0 00 47 08 0A 69 FFFFFF81 33 FFFFFF84 FFFFFF80 FFFFFF80 FFFFFF84
   20 FFFFFF81 52 14 03 2B FFFFFF81 53 08 08 58 FFFFFF81 51 FFFFFF81 FFFFFF80 FFFFFFC0
   00 59 28 03 FFFFFF81 33 6D 07 09 FFFFFF81 56 00 FFFFFF81 FFFFFF80 FFFFFF88 02
   FFFFFF81 57 01 04 53 74 61 72 10 03 22 FFFFFF81 58 06 0A FFFFFF81
   34 00 FFFFFF84 FFFFFF81 FFFFFF80 FFFFFF88 02 FFFFFF81 59 13 06 FFFFFF81 58 0A FFFFFF81 5A
   12 10 05 13 76 3A FFFFFF81 3D 08 07 17 FFFFFF81 58 FFFFFF84 00 FFFFFF81
   5C 14 02 FFFFFF81 57 08 09 7B FFFFFF81 58 FFFFFF81 FFFFFF80 FFFFFF84 40 FFFFFF81 5E
   14 04 FFFFFF81 3D FFFFFF81 5F 08 07 FFFFFF81 37 FFFFFF81 5D FFFFFFC0 00 3A 08
   0A FFFFFF81 61 FFFFFF81 58 FFFFFF81 FFFFFF80 FFFFFF84 40 FFFFFF81 62 01 07 75 6E 61
   70 70 6C 79 14 04 FFFFFF81 63 FFFFFF81 64 10 04 13 FFFFFF81 02 3A
   08 08 FFFFFF81 0B FFFFFF81 60 FFFFFFC0 00 FFFFFF81 3D 07 07 FFFFFF81 66 00 FFFFFF88
   42 FFFFFF81 67 01 03 45 70 73 10 03 22 FFFFFF81 68 06 0A FFFFFF81
   69 00 FFFFFF84 FFFFFF80 FFFFFF80 FFFFFF88 42 FFFFFF81 6A 02 03 45 70 73 13 05
   FFFFFF81 68 21 12 31 08 07 17 FFFFFF81 68 FFFFFF84 00 FFFFFF81 6C 14 02
   FFFFFF81 67 08 09 29 FFFFFF81 68 FFFFFF88 FFFFFFC2 FFFFFF80 FFFFFF84 02 2A 08 09 43
   FFFFFF81 68 FFFFFF88 FFFFFF80 FFFFFFA0 FFFFFFA0 06 2B 08 07 4B FFFFFF81 68 FFFFFF84 20 FFFFFF81
   70 14 01 5F 08 09 5D FFFFFF81 68 FFFFFF84 FFFFFF80 FFFFFF80 FFFFFF84 20 5E 08
   09 62 FFFFFF81 68 FFFFFF84 FFFFFF80 FFFFFF80 FFFFFF84 20 63 08 0A 65 FFFFFF81 68 FFFFFF84
   FFFFFF80 FFFFFF80 FFFFFF84 20 FFFFFF81 74 14 03 59 FFFFFF81 75 08 08 58 FFFFFF81 73
   FFFFFF81 FFFFFF80 FFFFFFC0 00 47 08 0A 69 FFFFFF81 68 FFFFFF84 FFFFFF80 FFFFFF80 FFFFFF84 20 FFFFFF81
   77 14 03 2B FFFFFF81 78 08 08 58 FFFFFF81 76 FFFFFF81 FFFFFF80 FFFFFFC0 00 59
   08 0B FFFFFF81 7A FFFFFF81 68 FFFFFF84 FFFFFF80 FFFFFF80 FFFFFF84 08 FFFFFF81 7B 01 0B 72
   65 61 64 52 65 73 6F 6C 76 65 14 01 0A 28 03 FFFFFF81
   68 6D 06 0A FFFFFF81 7E 00 FFFFFF84 FFFFFF80 FFFFFF80 FFFFFF80 00 FFFFFF81 7F 02 04
   4D 65 74 61 13 04 FFFFFF81 7D 21 12 08 0A FFFFFF82 01 FFFFFF81 7D
   FFFFFF82 FFFFFF80 FFFFFFA0 FFFFFF80 04 3A 01 02 72 31 08 07 17 FFFFFF81 7D FFFFFF84
   00 FFFFFF82 03 14 04 FFFFFF82 04 FFFFFF82 05 10 03 22 FFFFFF81 7D 08 07
   FFFFFF82 01 FFFFFF82 02 FFFFFFC0 00 3A 08 08 29 FFFFFF81 7D FFFFFFC2 FFFFFF80 FFFFFF84 02
   2A 08 07 43 FFFFFF81 7D FFFFFFA0 FFFFFF80 06 2B 08 08 FFFFFF81 37 FFFFFF81 7D
   FFFFFF84 00 FFFFFF81 38 08 07 FFFFFF82 0A 00 FFFFFF84 02 FFFFFF82 0B 01 06 6D
   6B 53 65 71 75 14 03 21 FFFFFF82 0C 08 06 35 FFFFFF82 09 FFFFFFC0
   00 37 
  InnerClass: 
   public #19= #76 of #22; //Alt=class scala/util/regexp/Base$Alt of class scala/util/regexp/Base
   public #30= #57 of #22; //Sequ=class scala/util/regexp/Base$Sequ of class scala/util/regexp/Base
   public #37= #78 of #22; //Star=class scala/util/regexp/Base$Star of class scala/util/regexp/Base
   public #81= #80 of #22; //Meta=class scala/util/regexp/Base$Meta of class scala/util/regexp/Base
   public abstract #84= #83 of #22; //RegExp=class scala/util/regexp/Base$RegExp of class scala/util/regexp/Base
  minor version: 0
  major version: 49
  Constant pool:
const #1 = Asciz	SourceFile;
const #2 = Asciz	Base.scala;
const #3 = Asciz	Alt$module;
const #4 = Asciz	Lscala/util/regexp/Base$Alt$;;
const #5 = Asciz	Sequ$module;
const #6 = Asciz	Lscala/util/regexp/Base$Sequ$;;
const #7 = Asciz	Star$module;
const #8 = Asciz	Lscala/util/regexp/Base$Star$;;
const #9 = Asciz	Eps$module;
const #10 = Asciz	Lscala/util/regexp/Base$Eps$;;
const #11 = Asciz	<init>;
const #12 = Asciz	()V;
const #13 = Asciz	Code;
const #14 = Asciz	LineNumberTable;
const #15 = Asciz	java/lang/Object;
const #16 = class	#15;	//  java/lang/Object
const #17 = NameAndType	#11:#12;//  "<init>":()V
const #18 = Method	#16.#17;	//  java/lang/Object."<init>":()V
const #19 = Asciz	Alt;
const #20 = Asciz	()Lscala/util/regexp/Base$Alt$;;
const #21 = Asciz	scala/util/regexp/Base;
const #22 = class	#21;	//  scala/util/regexp/Base
const #23 = NameAndType	#3:#4;//  Alt$module:Lscala/util/regexp/Base$Alt$;
const #24 = Field	#22.#23;	//  scala/util/regexp/Base.Alt$module:Lscala/util/regexp/Base$Alt$;
const #25 = Asciz	scala/util/regexp/Base$Alt$;
const #26 = class	#25;	//  scala/util/regexp/Base$Alt$
const #27 = Asciz	(Lscala/util/regexp/Base;)V;
const #28 = NameAndType	#11:#27;//  "<init>":(Lscala/util/regexp/Base;)V
const #29 = Method	#26.#28;	//  scala/util/regexp/Base$Alt$."<init>":(Lscala/util/regexp/Base;)V
const #30 = Asciz	Sequ;
const #31 = Asciz	()Lscala/util/regexp/Base$Sequ$;;
const #32 = NameAndType	#5:#6;//  Sequ$module:Lscala/util/regexp/Base$Sequ$;
const #33 = Field	#22.#32;	//  scala/util/regexp/Base.Sequ$module:Lscala/util/regexp/Base$Sequ$;
const #34 = Asciz	scala/util/regexp/Base$Sequ$;
const #35 = class	#34;	//  scala/util/regexp/Base$Sequ$
const #36 = Method	#35.#28;	//  scala/util/regexp/Base$Sequ$."<init>":(Lscala/util/regexp/Base;)V
const #37 = Asciz	Star;
const #38 = Asciz	()Lscala/util/regexp/Base$Star$;;
const #39 = NameAndType	#7:#8;//  Star$module:Lscala/util/regexp/Base$Star$;
const #40 = Field	#22.#39;	//  scala/util/regexp/Base.Star$module:Lscala/util/regexp/Base$Star$;
const #41 = Asciz	scala/util/regexp/Base$Star$;
const #42 = class	#41;	//  scala/util/regexp/Base$Star$
const #43 = Method	#42.#28;	//  scala/util/regexp/Base$Star$."<init>":(Lscala/util/regexp/Base;)V
const #44 = Asciz	mkSequ;
const #45 = Asciz	(Lscala/collection/Sequence;)Lscala/util/regexp/Base$RegExp;;
const #46 = Asciz	scala/collection/generic/IterableTemplate;
const #47 = class	#46;	//  scala/collection/generic/IterableTemplate
const #48 = Asciz	isEmpty;
const #49 = Asciz	()Z;
const #50 = NameAndType	#48:#49;//  isEmpty:()Z
const #51 = InterfaceMethod	#47.#50;	//  scala/collection/generic/IterableTemplate.isEmpty:()Z
const #52 = Asciz	Eps;
const #53 = Asciz	()Lscala/util/regexp/Base$Eps$;;
const #54 = NameAndType	#52:#53;//  Eps:()Lscala/util/regexp/Base$Eps$;
const #55 = Method	#22.#54;	//  scala/util/regexp/Base.Eps:()Lscala/util/regexp/Base$Eps$;
const #56 = Asciz	scala/util/regexp/Base$Sequ;
const #57 = class	#56;	//  scala/util/regexp/Base$Sequ
const #58 = Asciz	(Lscala/util/regexp/Base;Lscala/collection/Sequence;)V;
const #59 = NameAndType	#11:#58;//  "<init>":(Lscala/util/regexp/Base;Lscala/collection/Sequence;)V
const #60 = Method	#57.#59;	//  scala/util/regexp/Base$Sequ."<init>":(Lscala/util/regexp/Base;Lscala/collection/Sequence;)V
const #61 = Asciz	this;
const #62 = Asciz	Lscala/util/regexp/Base;;
const #63 = Asciz	rs;
const #64 = Asciz	Lscala/collection/Sequence;;
const #65 = Asciz	LocalVariableTable;
const #66 = Asciz	(Lscala/collection/Sequence<Lscala/util/regexp/Base$RegExp;>;)Lscala/util/regexp/Base$RegExp;;
const #67 = Asciz	Signature;
const #68 = NameAndType	#9:#10;//  Eps$module:Lscala/util/regexp/Base$Eps$;
const #69 = Field	#22.#68;	//  scala/util/regexp/Base.Eps$module:Lscala/util/regexp/Base$Eps$;
const #70 = Asciz	scala/util/regexp/Base$Eps$;
const #71 = class	#70;	//  scala/util/regexp/Base$Eps$
const #72 = Method	#71.#28;	//  scala/util/regexp/Base$Eps$."<init>":(Lscala/util/regexp/Base;)V
const #73 = Asciz	ScalaSig;
const #74 = Asciz	InnerClasses;
const #75 = Asciz	scala/util/regexp/Base$Alt;
const #76 = class	#75;	//  scala/util/regexp/Base$Alt
const #77 = Asciz	scala/util/regexp/Base$Star;
const #78 = class	#77;	//  scala/util/regexp/Base$Star
const #79 = Asciz	scala/util/regexp/Base$Meta;
const #80 = class	#79;	//  scala/util/regexp/Base$Meta
const #81 = Asciz	Meta;
const #82 = Asciz	scala/util/regexp/Base$RegExp;
const #83 = class	#82;	//  scala/util/regexp/Base$RegExp
const #84 = Asciz	RegExp;
const #85 = Asciz	scala/ScalaObject;
const #86 = class	#85;	//  scala/ScalaObject

{
public scala.util.regexp.Base();
  Code:
   Stack=1, Locals=1, Args_size=1
   0:	aload_0
   1:	invokespecial	#18; //Method java/lang/Object."<init>":()V
   4:	return
  LineNumberTable: 
   line 20: 0


public final scala.util.regexp.Base$Alt$ Alt();
  Code:
   Stack=4, Locals=1, Args_size=1
   0:	aload_0
   1:	getfield	#24; //Field Alt$module:Lscala/util/regexp/Base$Alt$;
   4:	ifnonnull	19
   7:	aload_0
   8:	new	#26; //class scala/util/regexp/Base$Alt$
   11:	dup
   12:	aload_0
   13:	invokespecial	#29; //Method scala/util/regexp/Base$Alt$."<init>":(Lscala/util/regexp/Base;)V
   16:	putfield	#24; //Field Alt$module:Lscala/util/regexp/Base$Alt$;
   19:	aload_0
   20:	getfield	#24; //Field Alt$module:Lscala/util/regexp/Base$Alt$;
   23:	areturn
  LineNumberTable: 
   line 28: 0


public final scala.util.regexp.Base$Sequ$ Sequ();
  Code:
   Stack=4, Locals=1, Args_size=1
   0:	aload_0
   1:	getfield	#33; //Field Sequ$module:Lscala/util/regexp/Base$Sequ$;
   4:	ifnonnull	19
   7:	aload_0
   8:	new	#35; //class scala/util/regexp/Base$Sequ$
   11:	dup
   12:	aload_0
   13:	invokespecial	#36; //Method scala/util/regexp/Base$Sequ$."<init>":(Lscala/util/regexp/Base;)V
   16:	putfield	#33; //Field Sequ$module:Lscala/util/regexp/Base$Sequ$;
   19:	aload_0
   20:	getfield	#33; //Field Sequ$module:Lscala/util/regexp/Base$Sequ$;
   23:	areturn
  LineNumberTable: 
   line 37: 0


public final scala.util.regexp.Base$Star$ Star();
  Code:
   Stack=4, Locals=1, Args_size=1
   0:	aload_0
   1:	getfield	#40; //Field Star$module:Lscala/util/regexp/Base$Star$;
   4:	ifnonnull	19
   7:	aload_0
   8:	new	#42; //class scala/util/regexp/Base$Star$
   11:	dup
   12:	aload_0
   13:	invokespecial	#43; //Method scala/util/regexp/Base$Star$."<init>":(Lscala/util/regexp/Base;)V
   16:	putfield	#40; //Field Star$module:Lscala/util/regexp/Base$Star$;
   19:	aload_0
   20:	getfield	#40; //Field Star$module:Lscala/util/regexp/Base$Star$;
   23:	areturn
  LineNumberTable: 
   line 46: 0


public final scala.util.regexp.Base$RegExp mkSequ(scala.collection.Sequence);
  Code:
   Stack=4, Locals=2, Args_size=2
   0:	aload_1
   1:	invokeinterface	#51,  1; //InterfaceMethod scala/collection/generic/IterableTemplate.isEmpty:()Z
   6:	ifeq	16
   9:	aload_0
   10:	invokevirtual	#55; //Method Eps:()Lscala/util/regexp/Base$Eps$;
   13:	goto	25
   16:	new	#57; //class scala/util/regexp/Base$Sequ
   19:	dup
   20:	aload_0
   21:	aload_1
   22:	invokespecial	#60; //Method scala/util/regexp/Base$Sequ."<init>":(Lscala/util/regexp/Base;Lscala/collection/Sequence;)V
   25:	areturn
  LineNumberTable: 
   line 62: 0

  LocalVariableTable: 
   Start  Length  Slot  Name   Signature
   0      26      0    this       Lscala/util/regexp/Base;
   0      26      1    rs       Lscala/collection/Sequence;

  Signature: length = 0x2
   00 42 

public final scala.util.regexp.Base$Eps$ Eps();
  Code:
   Stack=4, Locals=1, Args_size=1
   0:	aload_0
   1:	getfield	#69; //Field Eps$module:Lscala/util/regexp/Base$Eps$;
   4:	ifnonnull	19
   7:	aload_0
   8:	new	#71; //class scala/util/regexp/Base$Eps$
   11:	dup
   12:	aload_0
   13:	invokespecial	#72; //Method scala/util/regexp/Base$Eps$."<init>":(Lscala/util/regexp/Base;)V
   16:	putfield	#69; //Field Eps$module:Lscala/util/regexp/Base$Eps$;
   19:	aload_0
   20:	getfield	#69; //Field Eps$module:Lscala/util/regexp/Base$Eps$;
   23:	areturn
  LineNumberTable: 
   line 50: 0


}

