Compiled from "Base.scala"
public final class scala.util.regexp.Base$Sequ$ extends java.lang.Object implements scala.ScalaObject
  SourceFile: "Base.scala"
  Scala: length = 0x
   
  InnerClass: 
   public Sequ=class scala/util/regexp/Base$Sequ of class scala/util/regexp/Base
   public abstract RegExp=class scala/util/regexp/Base$RegExp of class scala/util/regexp/Base
   public final $anonfun$2=class scala/util/regexp/Base$Sequ$$anonfun$2 of class scala/util/regexp/Base$Sequ
  minor version: 0
  major version: 49
  Constant pool:
Asciz	SourceFile;
Asciz	Base.scala;
Asciz	$outer;
Asciz	Lscala/util/regexp/Base;;
Asciz	apply;
Asciz	(Lscala/collection/Seq;)Lscala/util/regexp/Base$RegExp;;
Asciz	Code;
Asciz	LineNumberTable;
Asciz	scala/collection/IterableLike;
class	scala/collection/IterableLike
Asciz	isEmpty;
Asciz	()Z;
NameAndType	isEmpty:()Z
InterfaceMethod	scala/collection/IterableLike.isEmpty:()Z
Asciz	scala/util/regexp/Base$Sequ$;
class	scala/util/regexp/Base$Sequ$
NameAndType	$outer:Lscala/util/regexp/Base;
Field	scala/util/regexp/Base$Sequ$.$outer:Lscala/util/regexp/Base;
Asciz	scala/util/regexp/Base;
class	scala/util/regexp/Base
Asciz	Eps;
Asciz	()Lscala/util/regexp/Base$Eps$;;
NameAndType	Eps:()Lscala/util/regexp/Base$Eps$;
Method	scala/util/regexp/Base.Eps:()Lscala/util/regexp/Base$Eps$;
Asciz	scala/util/regexp/Base$Sequ;
class	scala/util/regexp/Base$Sequ
Asciz	<init>;
Asciz	(Lscala/util/regexp/Base;Lscala/collection/Seq;)V;
NameAndType	"<init>":(Lscala/util/regexp/Base;Lscala/collection/Seq;)V
Method	scala/util/regexp/Base$Sequ."<init>":(Lscala/util/regexp/Base;Lscala/collection/Seq;)V
Asciz	this;
Asciz	Lscala/util/regexp/Base$Sequ$;;
Asciz	rs;
Asciz	Lscala/collection/Seq;;
Asciz	LocalVariableTable;
Asciz	(Lscala/collection/Seq<Lscala/util/regexp/Base$RegExp;>;)Lscala/util/regexp/Base$RegExp;;
Asciz	Signature;
Asciz	unapplySeq;
Asciz	(Lscala/util/regexp/Base$Sequ;)Lscala/Some;;
Asciz	scala/Some;
class	scala/Some
Asciz	()Lscala/collection/Seq;;
NameAndType	rs:()Lscala/collection/Seq;
Method	scala/util/regexp/Base$Sequ.rs:()Lscala/collection/Seq;
Asciz	(Ljava/lang/Object;)V;
NameAndType	"<init>":(Ljava/lang/Object;)V
Method	scala/Some."<init>":(Ljava/lang/Object;)V
Asciz	x;
Asciz	Lscala/util/regexp/Base$Sequ;;
Asciz	(Lscala/util/regexp/Base$Sequ;)Lscala/Some<Lscala/collection/Seq<Lscala/util/regexp/Base$RegExp;>;>;;
Asciz	(Lscala/util/regexp/Base;)V;
Asciz	java/lang/NullPointerException;
class	java/lang/NullPointerException
Asciz	()V;
NameAndType	"<init>":()V
Method	java/lang/NullPointerException."<init>":()V
Asciz	java/lang/Object;
class	java/lang/Object
Method	java/lang/Object."<init>":()V
Asciz	Scala;
Asciz	InnerClasses;
Asciz	Sequ;
Asciz	scala/util/regexp/Base$RegExp;
class	scala/util/regexp/Base$RegExp
Asciz	RegExp;
Asciz	scala/util/regexp/Base$Sequ$$anonfun$2;
class	scala/util/regexp/Base$Sequ$$anonfun$2
Asciz	$anonfun$2;
Asciz	scala/ScalaObject;
class	scala/ScalaObject

{
public final scala.util.regexp.Base $outer;
  Signature: Lscala/util/regexp/Base;

public scala.util.regexp.Base$RegExp apply(scala.collection.Seq);
  Signature: (Lscala/collection/Seq;)Lscala/util/regexp/Base$RegExp;
  Code:
   Stack=4, Locals=2, Args_size=2
	aload_1
	invokeinterface	InterfaceMethod scala/collection/IterableLike.isEmpty:()Z
	ifeq	l1 // new
	aload_0
	getfield	Field $outer:Lscala/util/regexp/Base;
	invokevirtual	Method scala/util/regexp/Base.Eps:()Lscala/util/regexp/Base$Eps$;
	goto	l2 // areturn
l1	new	class scala/util/regexp/Base$Sequ
	dup
	aload_0
	getfield	Field $outer:Lscala/util/regexp/Base;
	aload_1
	invokespecial	Method scala/util/regexp/Base$Sequ."<init>":(Lscala/util/regexp/Base;Lscala/collection/Seq;)V
l2	areturn
  Labels:
   	l1 = 19 // new
   	l2 = 31 // areturn
  LocalVariableTable: 
   Start  Length  Slot  Name   Signature
   0      32      0    this       Lscala/util/regexp/Base$Sequ$;
   0      32      1    rs       Lscala/collection/Seq;

  Signature: length = 0x2
   00 24 

public scala.Some unapplySeq(scala.util.regexp.Base$Sequ);
  Signature: (Lscala/util/regexp/Base$Sequ;)Lscala/Some;
  Code:
   Stack=3, Locals=2, Args_size=2
	new	class scala/Some
	dup
	aload_1
	invokevirtual	Method scala/util/regexp/Base$Sequ.rs:()Lscala/collection/Seq;
	invokespecial	Method scala/Some."<init>":(Ljava/lang/Object;)V
	areturn
  Labels:
  LocalVariableTable: 
   Start  Length  Slot  Name   Signature
   0      12      0    this       Lscala/util/regexp/Base$Sequ$;
   0      12      1    x       Lscala/util/regexp/Base$Sequ;

  Signature: length = 0x2
   00 32 

public scala.util.regexp.Base$Sequ$(scala.util.regexp.Base);
  Signature: (Lscala/util/regexp/Base;)V
  Code:
   Stack=2, Locals=2, Args_size=2
	aload_1
	ifnonnull	l1 // aload_0
	new	class java/lang/NullPointerException
	dup
	invokespecial	Method java/lang/NullPointerException."<init>":()V
	athrow
l1	aload_0
	aload_1
	putfield	Field $outer:Lscala/util/regexp/Base;
	aload_0
	invokespecial	Method java/lang/Object."<init>":()V
	return
  Labels:
   	l1 = 12 // aload_0
  LocalVariableTable: 
   Start  Length  Slot  Name   Signature
   0      22      0    this       Lscala/util/regexp/Base$Sequ$;
   0      22      1    $outer       Lscala/util/regexp/Base;


}

