Compiled from "Base.scala"
public class scala.util.regexp.Base$Star extends scala.util.regexp.Base$RegExp implements scala.ScalaObject,scala.Product,java.io.Serializable
  SourceFile: "Base.scala"
  Scala: length = 0x
   
  InnerClass: 
   public Star=class scala/util/regexp/Base$Star of class scala/util/regexp/Base
   public abstract RegExp=class scala/util/regexp/Base$RegExp of class scala/util/regexp/Base
  minor version: 0
  major version: 49
  Constant pool:
Asciz	SourceFile;
Asciz	Base.scala;
Asciz	bitmap$0;
Asciz	I;
Asciz	isNullable;
Asciz	Z;
Asciz	r;
Asciz	Lscala/util/regexp/Base$RegExp;;
Asciz	<init>;
Asciz	(Lscala/util/regexp/Base;Lscala/util/regexp/Base$RegExp;)V;
Asciz	Code;
Asciz	LineNumberTable;
Asciz	scala/util/regexp/Base$Star;
class	scala/util/regexp/Base$Star
NameAndType	r:Lscala/util/regexp/Base$RegExp;
Field	scala/util/regexp/Base$Star.r:Lscala/util/regexp/Base$RegExp;
Asciz	scala/util/regexp/Base$RegExp;
class	scala/util/regexp/Base$RegExp
Asciz	(Lscala/util/regexp/Base;)V;
NameAndType	"<init>":(Lscala/util/regexp/Base;)V
Method	scala/util/regexp/Base$RegExp."<init>":(Lscala/util/regexp/Base;)V
Asciz	scala/Product$class;
class	scala/Product$class
Asciz	$init$;
Asciz	(Lscala/Product;)V;
NameAndType	$init$:(Lscala/Product;)V
Method	scala/Product$class.$init$:(Lscala/Product;)V
Asciz	this;
Asciz	Lscala/util/regexp/Base$Star;;
Asciz	$outer;
Asciz	Lscala/util/regexp/Base;;
Asciz	LocalVariableTable;
Asciz	gd1$1;
Asciz	(Lscala/util/regexp/Base$RegExp;)Z;
Asciz	()Lscala/util/regexp/Base$RegExp;;
NameAndType	r:()Lscala/util/regexp/Base$RegExp;
Method	scala/util/regexp/Base$Star.r:()Lscala/util/regexp/Base$RegExp;
Asciz	java/lang/Object;
class	java/lang/Object
Asciz	equals;
Asciz	(Ljava/lang/Object;)Z;
NameAndType	equals:(Ljava/lang/Object;)Z
Method	java/lang/Object.equals:(Ljava/lang/Object;)Z
Asciz	scala$util$regexp$Base$Star$$$outer;
Asciz	()Lscala/util/regexp/Base;;
NameAndType	$outer:Lscala/util/regexp/Base;
Field	scala/util/regexp/Base$RegExp.$outer:Lscala/util/regexp/Base;
Asciz	canEqual;
Asciz	productElement;
Asciz	(I)Ljava/lang/Object;;
Asciz	scala/MatchError;
class	scala/MatchError
Asciz	scala/runtime/BoxesRunTime;
class	scala/runtime/BoxesRunTime
Asciz	boxToInteger;
Asciz	(I)Ljava/lang/Integer;;
NameAndType	boxToInteger:(I)Ljava/lang/Integer;
Method	scala/runtime/BoxesRunTime.boxToInteger:(I)Ljava/lang/Integer;
Asciz	toString;
Asciz	()Ljava/lang/String;;
NameAndType	toString:()Ljava/lang/String;
Method	java/lang/Object.toString:()Ljava/lang/String;
Asciz	(Ljava/lang/String;)V;
NameAndType	"<init>":(Ljava/lang/String;)V
Method	scala/MatchError."<init>":(Ljava/lang/String;)V
Asciz	java/lang/IndexOutOfBoundsException;
class	java/lang/IndexOutOfBoundsException
Method	java/lang/IndexOutOfBoundsException."<init>":(Ljava/lang/String;)V
Asciz	productArity;
Asciz	()I;
Asciz	productPrefix;
Asciz	Star;
String	Star
NameAndType	scala$util$regexp$Base$Star$$$outer:()Lscala/util/regexp/Base;
Method	scala/util/regexp/Base$Star.scala$util$regexp$Base$Star$$$outer:()Lscala/util/regexp/Base;
NameAndType	gd1$1:(Lscala/util/regexp/Base$RegExp;)Z
Method	scala/util/regexp/Base$Star.gd1$1:(Lscala/util/regexp/Base$RegExp;)Z
Asciz	scala/Equals;
class	scala/Equals
NameAndType	canEqual:(Ljava/lang/Object;)Z
InterfaceMethod	scala/Equals.canEqual:(Ljava/lang/Object;)Z
Asciz	temp2;
Asciz	temp3;
Asciz	scala/runtime/ScalaRunTime$;
class	scala/runtime/ScalaRunTime$
Asciz	MODULE$;
Asciz	Lscala/runtime/ScalaRunTime$;;
NameAndType	MODULE$:Lscala/runtime/ScalaRunTime$;
Field	scala/runtime/ScalaRunTime$.MODULE$:Lscala/runtime/ScalaRunTime$;
Asciz	_toString;
Asciz	(Lscala/Product;)Ljava/lang/String;;
NameAndType	_toString:(Lscala/Product;)Ljava/lang/String;
Method	scala/runtime/ScalaRunTime$._toString:(Lscala/Product;)Ljava/lang/String;
Asciz	hashCode;
Asciz	_hashCode;
Asciz	(Lscala/Product;)I;
NameAndType	_hashCode:(Lscala/Product;)I
Method	scala/runtime/ScalaRunTime$._hashCode:(Lscala/Product;)I
Asciz	copy;
Asciz	(Lscala/util/regexp/Base$RegExp;)Lscala/util/regexp/Base$Star;;
NameAndType	"<init>":(Lscala/util/regexp/Base;Lscala/util/regexp/Base$RegExp;)V
Method	scala/util/regexp/Base$Star."<init>":(Lscala/util/regexp/Base;Lscala/util/regexp/Base$RegExp;)V
Asciz	()Z;
NameAndType	bitmap$0:I
Field	scala/util/regexp/Base$Star.bitmap$0:I
NameAndType	isNullable:Z
Field	scala/util/regexp/Base$Star.isNullable:Z
Asciz	copy$default$1;
Asciz	productElements;
Asciz	()Lscala/collection/Iterator;;
Asciz	(Lscala/Product;)Lscala/collection/Iterator;;
NameAndType	productElements:(Lscala/Product;)Lscala/collection/Iterator;
Method	scala/Product$class.productElements:(Lscala/Product;)Lscala/collection/Iterator;
Asciz	productIterator;
NameAndType	productIterator:(Lscala/Product;)Lscala/collection/Iterator;
Method	scala/Product$class.productIterator:(Lscala/Product;)Lscala/collection/Iterator;
Asciz	Scala;
Asciz	InnerClasses;
Asciz	scala/util/regexp/Base;
class	scala/util/regexp/Base
Asciz	RegExp;
Asciz	scala/ScalaObject;
class	scala/ScalaObject
Asciz	scala/Product;
class	scala/Product
Asciz	java/io/Serializable;
class	java/io/Serializable

{
public volatile int bitmap$0;
  Signature: I

private final boolean isNullable;
  Signature: Z

private final scala.util.regexp.Base$RegExp r;
  Signature: Lscala/util/regexp/Base$RegExp;

public scala.util.regexp.Base$Star(scala.util.regexp.Base, scala.util.regexp.Base$RegExp);
  Signature: (Lscala/util/regexp/Base;Lscala/util/regexp/Base$RegExp;)V
  Code:
   Stack=2, Locals=3, Args_size=3
	aload_0
	aload_2
	putfield	Field r:Lscala/util/regexp/Base$RegExp;
	aload_0
	aload_1
	invokespecial	Method scala/util/regexp/Base$RegExp."<init>":(Lscala/util/regexp/Base;)V
	aload_0
	invokestatic	Method scala/Product$class.$init$:(Lscala/Product;)V
	return
  Labels:
  LocalVariableTable: 
   Start  Length  Slot  Name   Signature
   0      15      0    this       Lscala/util/regexp/Base$Star;
   0      15      1    $outer       Lscala/util/regexp/Base;
   0      15      2    r       Lscala/util/regexp/Base$RegExp;


private final boolean gd1$1(scala.util.regexp.Base$RegExp);
  Signature: (Lscala/util/regexp/Base$RegExp;)Z
  Code:
   Stack=2, Locals=3, Args_size=2
	aload_1
	aload_0
	invokevirtual	Method r:()Lscala/util/regexp/Base$RegExp;
	astore_2
	dup
	ifnonnull	l1 // aload_2
	pop
	aload_2
	ifnull	l2 // iconst_1
	goto	l3 // iconst_0
l1	aload_2
	invokevirtual	Method java/lang/Object.equals:(Ljava/lang/Object;)Z
	ifeq	l3 // iconst_0
l2	iconst_1
	goto	l4 // ireturn
l3	iconst_0
l4	ireturn
  Labels:
   	l1 = 18 // aload_2
   	l2 = 25 // iconst_1
   	l3 = 29 // iconst_0
   	l4 = 30 // ireturn

public scala.util.regexp.Base scala$util$regexp$Base$Star$$$outer();
  Signature: ()Lscala/util/regexp/Base;
  Code:
   Stack=1, Locals=1, Args_size=1
	aload_0
	getfield	Field scala/util/regexp/Base$RegExp.$outer:Lscala/util/regexp/Base;
	areturn
  Labels:

public boolean canEqual(java.lang.Object);
  Signature: (Ljava/lang/Object;)Z
  Code:
   Stack=1, Locals=2, Args_size=2
	aload_1
	instanceof	class scala/util/regexp/Base$Star
	ireturn
  Labels:

public java.lang.Object productElement(int);
  Signature: (I)Ljava/lang/Object;
  Code:
   Stack=3, Locals=2, Args_size=2
	iload_1
	iconst_0
	if_icmpne	l1 // iconst_1
	iconst_1
	ifeq	l2 // new
	aload_0
	invokevirtual	Method r:()Lscala/util/regexp/Base$RegExp;
	areturn
l2	new	class scala/MatchError
	dup
	iload_1
	invokestatic	Method scala/runtime/BoxesRunTime.boxToInteger:(I)Ljava/lang/Integer;
	invokevirtual	Method java/lang/Object.toString:()Ljava/lang/String;
	invokespecial	Method scala/MatchError."<init>":(Ljava/lang/String;)V
	athrow
l1	iconst_1
	ifeq	l3 // new
	new	class java/lang/IndexOutOfBoundsException
	dup
	iload_1
	invokestatic	Method scala/runtime/BoxesRunTime.boxToInteger:(I)Ljava/lang/Integer;
	invokevirtual	Method java/lang/Object.toString:()Ljava/lang/String;
	invokespecial	Method java/lang/IndexOutOfBoundsException."<init>":(Ljava/lang/String;)V
	athrow
l3	new	class scala/MatchError
	dup
	iload_1
	invokestatic	Method scala/runtime/BoxesRunTime.boxToInteger:(I)Ljava/lang/Integer;
	invokevirtual	Method java/lang/Object.toString:()Ljava/lang/String;
	invokespecial	Method scala/MatchError."<init>":(Ljava/lang/String;)V
	athrow
  Labels:
   	l2 = 14 // new
   	l1 = 29 // iconst_1
   	l3 = 48 // new

public int productArity();
  Signature: ()I
  Code:
   Stack=1, Locals=1, Args_size=1
	iconst_1
	ireturn
  Labels:

public java.lang.String productPrefix();
  Signature: ()Ljava/lang/String;
  Code:
   Stack=1, Locals=1, Args_size=1
	ldc	String Star
	areturn
  Labels:

public boolean equals(java.lang.Object);
  Signature: (Ljava/lang/Object;)Z
  Code:
   Stack=3, Locals=4, Args_size=2
	aload_0
	aload_1
	if_acmpeq	l1 // iconst_1
	aload_1
	instanceof	class scala/util/regexp/Base$Star
	ifeq	l2 // iconst_1
	aload_1
	checkcast	class scala/util/regexp/Base$Star
	invokevirtual	Method scala$util$regexp$Base$Star$$$outer:()Lscala/util/regexp/Base;
	aload_0
	invokevirtual	Method scala$util$regexp$Base$Star$$$outer:()Lscala/util/regexp/Base;
	if_acmpne	l2 // iconst_1
	aload_1
	checkcast	class scala/util/regexp/Base$Star
	astore_2
	aload_2
	invokevirtual	Method r:()Lscala/util/regexp/Base$RegExp;
	astore_3
	aload_0
	aload_3
	invokespecial	Method gd1$1:(Lscala/util/regexp/Base$RegExp;)Z
	ifeq	l3 // iconst_1
	aload_1
	checkcast	class scala/util/regexp/Base$Star
	aload_0
	invokeinterface	InterfaceMethod scala/Equals.canEqual:(Ljava/lang/Object;)Z
	goto	l4 // ifeq
l3	iconst_1
	ifeq	l5 // new
	iconst_0
	goto	l4 // ifeq
l5	new	class scala/MatchError
	dup
	aload_1
	invokevirtual	Method java/lang/Object.toString:()Ljava/lang/String;
	invokespecial	Method scala/MatchError."<init>":(Ljava/lang/String;)V
	athrow
l2	iconst_1
	ifeq	l6 // new
	iconst_0
l4	ifeq	l7 // iconst_0
l1	iconst_1
	goto	l8 // ireturn
l7	iconst_0
l8	ireturn
l6	new	class scala/MatchError
	dup
	aload_1
	invokevirtual	Method java/lang/Object.toString:()Ljava/lang/String;
	invokespecial	Method scala/MatchError."<init>":(Ljava/lang/String;)V
	athrow
  Labels:
   	l3 = 57 // iconst_1
   	l5 = 65 // new
   	l2 = 77 // iconst_1
   	l4 = 82 // ifeq
   	l1 = 85 // iconst_1
   	l7 = 89 // iconst_0
   	l8 = 90 // ireturn
   	l6 = 91 // new
  LocalVariableTable: 
   Start  Length  Slot  Name   Signature
   0      103      0    this       Lscala/util/regexp/Base$Star;
   31      46      2    temp2       Lscala/util/regexp/Base$Star;
   36      41      3    temp3       Lscala/util/regexp/Base$RegExp;


public java.lang.String toString();
  Signature: ()Ljava/lang/String;
  Code:
   Stack=2, Locals=1, Args_size=1
	getstatic	Field scala/runtime/ScalaRunTime$.MODULE$:Lscala/runtime/ScalaRunTime$;
	aload_0
	invokevirtual	Method scala/runtime/ScalaRunTime$._toString:(Lscala/Product;)Ljava/lang/String;
	areturn
  Labels:

public int hashCode();
  Signature: ()I
  Code:
   Stack=2, Locals=1, Args_size=1
	getstatic	Field scala/runtime/ScalaRunTime$.MODULE$:Lscala/runtime/ScalaRunTime$;
	aload_0
	invokevirtual	Method scala/runtime/ScalaRunTime$._hashCode:(Lscala/Product;)I
	ireturn
  Labels:

public scala.util.regexp.Base$Star copy(scala.util.regexp.Base$RegExp);
  Signature: (Lscala/util/regexp/Base$RegExp;)Lscala/util/regexp/Base$Star;
  Code:
   Stack=4, Locals=2, Args_size=2
	new	class scala/util/regexp/Base$Star
	dup
	aload_0
	invokevirtual	Method scala$util$regexp$Base$Star$$$outer:()Lscala/util/regexp/Base;
	aload_1
	invokespecial	Method "<init>":(Lscala/util/regexp/Base;Lscala/util/regexp/Base$RegExp;)V
	areturn
  Labels:
  LocalVariableTable: 
   Start  Length  Slot  Name   Signature
   0      13      0    this       Lscala/util/regexp/Base$Star;
   0      13      1    r       Lscala/util/regexp/Base$RegExp;


public final boolean isNullable();
  Signature: ()Z
  Code:
   Stack=3, Locals=1, Args_size=1
	aload_0
	getfield	Field bitmap$0:I
	iconst_1
	iand
	iconst_0
	if_icmpne	l1 // aload_0
	aload_0
	dup
	pop
	monitorenter
	aload_0
	getfield	Field bitmap$0:I
	iconst_1
	iand
	iconst_0
	if_icmpne	l2 // aload_0
	aload_0
	iconst_1
	putfield	Field isNullable:Z
	aload_0
	aload_0
	getfield	Field bitmap$0:I
	iconst_1
	ior
	putfield	Field bitmap$0:I
l2	aload_0
	monitorexit
l1	aload_0
	getfield	Field isNullable:Z
	ireturn
	aload_0
	monitorexit
	athrow
  Labels:
   	l2 = 39 // aload_0
   	l1 = 41 // aload_0
  Exception table:
   from   to  target type
    14    41    46   any

public scala.util.regexp.Base$RegExp r();
  Signature: ()Lscala/util/regexp/Base$RegExp;
  Code:
   Stack=1, Locals=1, Args_size=1
	aload_0
	getfield	Field r:Lscala/util/regexp/Base$RegExp;
	areturn
  Labels:

public scala.util.regexp.Base$RegExp copy$default$1();
  Signature: ()Lscala/util/regexp/Base$RegExp;
  Code:
   Stack=1, Locals=1, Args_size=1
	aload_0
	invokevirtual	Method r:()Lscala/util/regexp/Base$RegExp;
	areturn
  Labels:

public scala.collection.Iterator productElements();
  Signature: ()Lscala/collection/Iterator;
  Code:
   Stack=1, Locals=1, Args_size=1
	aload_0
	invokestatic	Method scala/Product$class.productElements:(Lscala/Product;)Lscala/collection/Iterator;
	areturn
  Labels:

public scala.collection.Iterator productIterator();
  Signature: ()Lscala/collection/Iterator;
  Code:
   Stack=1, Locals=1, Args_size=1
	aload_0
	invokestatic	Method scala/Product$class.productIterator:(Lscala/Product;)Lscala/collection/Iterator;
	areturn
  Labels:

}

