Compiled from "Base.scala"
public final class scala.util.regexp.Base$Star$ extends java.lang.Object implements scala.Function1,scala.ScalaObject
  SourceFile: "Base.scala"
  Scala: length = 0x
   
  InnerClass: 
   public Star=class scala/util/regexp/Base$Star of class scala/util/regexp/Base
   public abstract RegExp=class scala/util/regexp/Base$RegExp of class scala/util/regexp/Base
  minor version: 0
  major version: 49
  Constant pool:
Asciz	SourceFile;
Asciz	Base.scala;
Asciz	Scala;
Asciz	$outer;
Asciz	Lscala/util/regexp/Base;;
Asciz	toString;
Asciz	()Ljava/lang/String;;
Asciz	Code;
Asciz	LineNumberTable;
Asciz	scala/Function1$class;
class	scala/Function1$class
Asciz	(Lscala/Function1;)Ljava/lang/String;;
NameAndType	toString:(Lscala/Function1;)Ljava/lang/String;
Method	scala/Function1$class.toString:(Lscala/Function1;)Ljava/lang/String;
Asciz	compose;
Asciz	(Lscala/Function1;)Lscala/Function1;;
Asciz	(Lscala/Function1;Lscala/Function1;)Lscala/Function1;;
NameAndType	compose:(Lscala/Function1;Lscala/Function1;)Lscala/Function1;
Method	scala/Function1$class.compose:(Lscala/Function1;Lscala/Function1;)Lscala/Function1;
Asciz	this;
Asciz	Lscala/util/regexp/Base$Star$;;
Asciz	g;
Asciz	Lscala/Function1;;
Asciz	LocalVariableTable;
Asciz	andThen;
NameAndType	andThen:(Lscala/Function1;Lscala/Function1;)Lscala/Function1;
Method	scala/Function1$class.andThen:(Lscala/Function1;Lscala/Function1;)Lscala/Function1;
Asciz	unapply;
Asciz	(Lscala/util/regexp/Base$Star;)Lscala/Option;;
Asciz	java/lang/Object;
class	java/lang/Object
Asciz	equals;
Asciz	(Ljava/lang/Object;)Z;
NameAndType	equals:(Ljava/lang/Object;)Z
Method	java/lang/Object.equals:(Ljava/lang/Object;)Z
Asciz	scala/None$;
class	scala/None$
Asciz	MODULE$;
Asciz	Lscala/None$;;
NameAndType	MODULE$:Lscala/None$;
Field	scala/None$.MODULE$:Lscala/None$;
Asciz	scala/Some;
class	scala/Some
Asciz	scala/util/regexp/Base$Star;
class	scala/util/regexp/Base$Star
Asciz	r;
Asciz	()Lscala/util/regexp/Base$RegExp;;
NameAndType	r:()Lscala/util/regexp/Base$RegExp;
Method	scala/util/regexp/Base$Star.r:()Lscala/util/regexp/Base$RegExp;
Asciz	<init>;
Asciz	(Ljava/lang/Object;)V;
NameAndType	"<init>":(Ljava/lang/Object;)V
Method	scala/Some."<init>":(Ljava/lang/Object;)V
Asciz	x$0;
Asciz	Lscala/util/regexp/Base$Star;;
Asciz	apply;
Asciz	(Lscala/util/regexp/Base$RegExp;)Lscala/util/regexp/Base$Star;;
Asciz	scala/util/regexp/Base$Star$;
class	scala/util/regexp/Base$Star$
NameAndType	$outer:Lscala/util/regexp/Base;
Field	scala/util/regexp/Base$Star$.$outer:Lscala/util/regexp/Base;
Asciz	(Lscala/util/regexp/Base;Lscala/util/regexp/Base$RegExp;)V;
NameAndType	"<init>":(Lscala/util/regexp/Base;Lscala/util/regexp/Base$RegExp;)V
Method	scala/util/regexp/Base$Star."<init>":(Lscala/util/regexp/Base;Lscala/util/regexp/Base$RegExp;)V
Asciz	Lscala/util/regexp/Base$RegExp;;
Asciz	(Ljava/lang/Object;)Ljava/lang/Object;;
Asciz	scala/util/regexp/Base$RegExp;
class	scala/util/regexp/Base$RegExp
NameAndType	apply:(Lscala/util/regexp/Base$RegExp;)Lscala/util/regexp/Base$Star;
Method	scala/util/regexp/Base$Star$.apply:(Lscala/util/regexp/Base$RegExp;)Lscala/util/regexp/Base$Star;
Asciz	v1;
Asciz	Ljava/lang/Object;;
Asciz	(Lscala/util/regexp/Base;)V;
Asciz	java/lang/NullPointerException;
class	java/lang/NullPointerException
Asciz	()V;
NameAndType	"<init>":()V
Method	java/lang/NullPointerException."<init>":()V
Method	java/lang/Object."<init>":()V
Asciz	$init$;
Asciz	(Lscala/Function1;)V;
NameAndType	$init$:(Lscala/Function1;)V
Method	scala/Function1$class.$init$:(Lscala/Function1;)V
Asciz	InnerClasses;
Asciz	scala/util/regexp/Base;
class	scala/util/regexp/Base
Asciz	Star;
Asciz	RegExp;
Asciz	scala/Function1;
class	scala/Function1
Asciz	scala/ScalaObject;
class	scala/ScalaObject

{
public final scala.util.regexp.Base $outer;
  Signature: Lscala/util/regexp/Base;

public java.lang.String toString();
  Signature: ()Ljava/lang/String;
  Code:
   Stack=1, Locals=1, Args_size=1
	aload_0
	invokestatic	Method scala/Function1$class.toString:(Lscala/Function1;)Ljava/lang/String;
	areturn
  Labels:

public scala.Function1 compose(scala.Function1);
  Signature: (Lscala/Function1;)Lscala/Function1;
  Code:
   Stack=2, Locals=2, Args_size=2
	aload_0
	aload_1
	invokestatic	Method scala/Function1$class.compose:(Lscala/Function1;Lscala/Function1;)Lscala/Function1;
	areturn
  Labels:
  LocalVariableTable: 
   Start  Length  Slot  Name   Signature
   0      6      0    this       Lscala/util/regexp/Base$Star$;
   0      6      1    g       Lscala/Function1;


public scala.Function1 andThen(scala.Function1);
  Signature: (Lscala/Function1;)Lscala/Function1;
  Code:
   Stack=2, Locals=2, Args_size=2
	aload_0
	aload_1
	invokestatic	Method scala/Function1$class.andThen:(Lscala/Function1;Lscala/Function1;)Lscala/Function1;
	areturn
  Labels:
  LocalVariableTable: 
   Start  Length  Slot  Name   Signature
   0      6      0    this       Lscala/util/regexp/Base$Star$;
   0      6      1    g       Lscala/Function1;


public scala.Option unapply(scala.util.regexp.Base$Star);
  Signature: (Lscala/util/regexp/Base$Star;)Lscala/Option;
  Code:
   Stack=3, Locals=2, Args_size=2
	aload_1
	dup
	pop
	ifnull	l1 // getstatic
	aload_1
	aconst_null
	invokevirtual	Method java/lang/Object.equals:(Ljava/lang/Object;)Z
	ifeq	l2 // new
l1	getstatic	Field scala/None$.MODULE$:Lscala/None$;
	goto	l3 // areturn
l2	new	class scala/Some
	dup
	aload_1
	invokevirtual	Method scala/util/regexp/Base$Star.r:()Lscala/util/regexp/Base$RegExp;
	invokespecial	Method scala/Some."<init>":(Ljava/lang/Object;)V
l3	areturn
  Labels:
   	l1 = 14 // getstatic
   	l2 = 20 // new
   	l3 = 31 // areturn
  LocalVariableTable: 
   Start  Length  Slot  Name   Signature
   0      32      0    this       Lscala/util/regexp/Base$Star$;
   0      32      1    x$0       Lscala/util/regexp/Base$Star;


public scala.util.regexp.Base$Star apply(scala.util.regexp.Base$RegExp);
  Signature: (Lscala/util/regexp/Base$RegExp;)Lscala/util/regexp/Base$Star;
  Code:
   Stack=4, Locals=3, Args_size=2
	aload_0
	getfield	Field $outer:Lscala/util/regexp/Base;
	astore_2
	new	class scala/util/regexp/Base$Star
	dup
	aload_0
	getfield	Field $outer:Lscala/util/regexp/Base;
	aload_1
	invokespecial	Method scala/util/regexp/Base$Star."<init>":(Lscala/util/regexp/Base;Lscala/util/regexp/Base$RegExp;)V
	areturn
  Labels:
  LocalVariableTable: 
   Start  Length  Slot  Name   Signature
   0      18      0    this       Lscala/util/regexp/Base$Star$;
   5      13      1    r       Lscala/util/regexp/Base$RegExp;


public java.lang.Object apply(java.lang.Object);
  Signature: (Ljava/lang/Object;)Ljava/lang/Object;
  Code:
   Stack=2, Locals=3, Args_size=2
	aload_0
	getfield	Field $outer:Lscala/util/regexp/Base;
	astore_2
	aload_0
	aload_1
	checkcast	class scala/util/regexp/Base$RegExp
	invokevirtual	Method apply:(Lscala/util/regexp/Base$RegExp;)Lscala/util/regexp/Base$Star;
	areturn
  Labels:
  LocalVariableTable: 
   Start  Length  Slot  Name   Signature
   0      14      0    this       Lscala/util/regexp/Base$Star$;
   5      9      1    v1       Ljava/lang/Object;


public scala.util.regexp.Base$Star$(scala.util.regexp.Base);
  Signature: (Lscala/util/regexp/Base;)V
  Code:
   Stack=2, Locals=2, Args_size=2
	aload_1
	ifnonnull	l1 // aload_0
	new	class java/lang/NullPointerException
	dup
	invokespecial	Method java/lang/NullPointerException."<init>":()V
	athrow
l1	aload_0
	aload_1
	putfield	Field $outer:Lscala/util/regexp/Base;
	aload_0
	invokespecial	Method java/lang/Object."<init>":()V
	aload_0
	invokestatic	Method scala/Function1$class.$init$:(Lscala/Function1;)V
	return
  Labels:
   	l1 = 12 // aload_0
  LocalVariableTable: 
   Start  Length  Slot  Name   Signature
   0      26      0    this       Lscala/util/regexp/Base$Star$;
   0      26      1    $outer       Lscala/util/regexp/Base;


}

