Compiled from "Base.scala"
public abstract class scala.util.regexp.Base extends java.lang.Object implements scala.ScalaObject
  SourceFile: "Base.scala"
  ScalaSig: length = 0x6E4
   05 00 FFFFFF81 77 06 08 01 02 FFFFFF84 FFFFFF80 FFFFFF80 FFFFFF81 00 09 02 04
   42 61 73 65 0A 02 03 04 01 06 72 65 67 65 78 70
   0A 02 05 06 01 04 75 74 69 6C 0A 01 07 01 05 73
   63 61 6C 61 03 00 13 03 00 0A 12 10 02 0B 10 0D
   01 0C 0A 02 0D 0E 01 04 6C 61 6E 67 0A 01 0F 01
   04 6A 61 76 61 09 02 11 0C 02 06 4F 62 6A 65 63
   74 10 02 13 14 0D 01 06 09 02 15 06 02 0B 53 63
   61 6C 61 4F 62 6A 65 63 74 08 05 17 00 FFFFFF84 00 18
   01 06 3C 69 6E 69 74 3E 14 01 19 10 02 1A 00 0D
   01 02 04 08 1C 00 FFFFFF84 FFFFFF80 FFFFFF80 FFFFFF82 00 1D 02 08 5F 72
   65 67 65 78 70 54 11 02 1E 21 10 02 13 1F 09 02
   20 06 02 07 4E 6F 74 68 69 6E 67 10 02 22 23 0D
   01 00 06 08 24 00 FFFFFF84 FFFFFF80 FFFFFF80 FFFFFF81 00 25 02 06 52 65
   67 45 78 70 13 03 23 0A 12 08 05 17 23 FFFFFF84 00 27
   14 01 21 08 07 29 23 FFFFFFC2 FFFFFF80 FFFFFF86 00 2A 01 0A 69 73
   4E 75 6C 6C 61 62 6C 65 15 01 2B 10 02 13 2C 09
   02 2D 06 02 07 42 6F 6F 6C 65 61 6E 07 05 2F 00
   FFFFFF88 02 30 01 03 41 6C 74 10 02 22 31 06 08 32 00
   FFFFFF84 FFFFFF80 FFFFFF80 FFFFFF88 02 33 02 03 41 6C 74 13 03 31 0A 12
   08 05 17 31 FFFFFF84 00 35 14 01 30 08 05 37 31 FFFFFF84 00
   38 01 05 61 70 70 6C 79 14 02 39 4B 10 02 22 3A
   06 08 32 00 FFFFFF84 FFFFFF80 FFFFFF80 FFFFFF80 00 3B 13 03 3A 21 12 08
   08 3D 3A FFFFFF82 FFFFFFC2 FFFFFF80 FFFFFF84 00 3E 01 02 72 73 15 01 3F
   10 03 13 40 42 09 02 41 06 02 0A 3C 72 65 70 65
   61 74 65 64 3E 10 02 22 1B 08 08 44 3A FFFFFF82 FFFFFF80 FFFFFFA0
   FFFFFF80 04 3F 01 03 72 73 20 08 05 17 3A FFFFFF84 04 46 14
   02 39 47 08 05 3D 45 FFFFFFC0 00 3F 08 07 29 3A FFFFFFC2 FFFFFF80
   FFFFFF84 02 2A 08 06 4A 3A FFFFFFA0 FFFFFF80 06 2B 01 0B 69 73 4E
   75 6C 6C 61 62 6C 65 20 08 05 3D 36 FFFFFFC0 00 3F 08
   05 4D 31 FFFFFF84 00 4E 01 0A 75 6E 61 70 70 6C 79 53
   65 71 14 02 4F 58 10 03 13 50 52 09 02 51 06 02
   04 53 6F 6D 65 10 03 53 56 42 0D 01 54 0A 02 55
   06 01 0A 63 6F 6C 6C 65 63 74 69 6F 6E 09 02 57
   54 02 03 53 65 71 08 05 59 4C FFFFFFC0 00 39 01 01 78
   07 05 5B 00 FFFFFF88 02 5C 01 04 53 65 71 75 10 02 22
   5D 06 08 5E 00 FFFFFF84 FFFFFF80 FFFFFF80 FFFFFF88 02 5F 02 04 53 65 71
   75 13 03 5D 0A 12 08 05 17 5D FFFFFF84 00 61 14 01 5C
   08 05 37 5D FFFFFF84 00 63 14 02 21 64 08 05 3D 62 FFFFFFC0
   00 3F 08 05 4D 5D FFFFFF84 00 66 14 02 4F 67 08 05 59
   65 FFFFFFC0 00 68 10 02 22 69 06 08 5E 00 FFFFFF84 FFFFFF80 FFFFFF80 FFFFFF80
   00 6A 13 03 69 21 12 08 08 3D 69 FFFFFF82 FFFFFFC2 FFFFFF80 FFFFFF84 00
   3E 08 08 44 69 FFFFFF82 FFFFFF80 FFFFFFA0 FFFFFF80 04 3F 08 05 17 69 FFFFFF84
   04 6E 14 02 68 6F 08 05 3D 6D FFFFFFC0 00 3F 08 07 29
   69 FFFFFFC2 FFFFFF80 FFFFFF84 02 2A 08 06 4A 69 FFFFFFA0 FFFFFF80 06 2B 06 08
   73 00 FFFFFF84 FFFFFF80 FFFFFF80 FFFFFF80 40 74 02 04 53 74 61 72 13 04
   72 21 12 75 10 02 13 76 09 02 77 06 02 07 50 72
   6F 64 75 63 74 08 08 79 72 FFFFFF82 FFFFFFCA FFFFFF80 FFFFFF84 00 7A 01
   01 72 15 01 42 08 08 7C 72 FFFFFF82 FFFFFF88 FFFFFFA0 FFFFFF80 04 42 01
   02 72 20 08 05 17 72 FFFFFF84 00 7E 14 03 7F FFFFFF81 00 10
   02 22 72 08 05 79 7D FFFFFFC0 00 42 08 08 29 72 FFFFFF88 FFFFFFC2
   FFFFFF80 FFFFFF84 02 2A 08 08 4A 72 FFFFFF88 FFFFFF80 FFFFFFA0 FFFFFFA0 06 2B 08 09
   FFFFFF81 04 72 FFFFFF81 FFFFFF80 FFFFFF84 00 FFFFFF81 05 01 04 63 6F 70 79 14
   03 7F FFFFFF81 06 08 08 79 FFFFFF81 03 FFFFFF90 FFFFFF80 FFFFFFC0 00 42 08 09
   FFFFFF81 08 72 FFFFFF91 FFFFFF80 FFFFFF84 00 FFFFFF81 09 01 0E 63 6F 70 79 24
   64 65 66 61 75 6C 74 24 31 15 02 FFFFFF81 0A 2A 03 42
   FFFFFF81 0B 2B 02 FFFFFF81 0C 10 04 FFFFFF81 0D FFFFFF81 12 0D 02 FFFFFF81 0E
   0A 04 FFFFFF81 0F FFFFFF81 10 01 09 75 6E 63 68 65 63 6B 65
   64 0A 03 FFFFFF81 11 06 01 0A 61 6E 6E 6F 74 61 74 69
   6F 6E 09 04 FFFFFF81 13 FFFFFF81 0E 02 11 75 6E 63 68 65 63
   6B 65 64 56 61 72 69 61 6E 63 65 08 0A FFFFFF81 15 72
   FFFFFF84 FFFFFF80 FFFFFF80 FFFFFF84 20 FFFFFF81 16 01 08 68 61 73 68 43 6F 64
   65 14 02 FFFFFF81 17 10 03 13 FFFFFF81 18 09 03 FFFFFF81 19 06 02
   03 49 6E 74 08 0A FFFFFF81 1B 72 FFFFFF84 FFFFFF80 FFFFFF80 FFFFFF84 20 FFFFFF81 1C
   01 08 74 6F 53 74 72 69 6E 67 14 02 FFFFFF81 1D 10 04
   FFFFFF81 1E FFFFFF81 21 0E 03 13 FFFFFF81 1F 09 03 FFFFFF81 20 06 01 06
   50 72 65 64 65 66 09 04 FFFFFF81 22 FFFFFF81 23 02 06 53 74
   72 69 6E 67 0A 03 FFFFFF81 20 06 08 0A FFFFFF81 25 72 FFFFFF84 FFFFFF80
   FFFFFF80 FFFFFF84 20 FFFFFF81 26 01 06 65 71 75 61 6C 73 14 03 2B
   FFFFFF81 27 08 0A FFFFFF81 28 FFFFFF81 24 FFFFFF81 FFFFFF80 FFFFFFC0 00 FFFFFF81 29 01 03
   78 24 31 10 03 13 FFFFFF81 2A 09 03 FFFFFF81 2B 06 02 03 41
   6E 79 08 0A FFFFFF81 2D 72 FFFFFF84 FFFFFF80 FFFFFF80 FFFFFF84 20 FFFFFF81 2E 01 0D
   70 72 6F 64 75 63 74 50 72 65 66 69 78 15 02 FFFFFF81
   2F 10 03 0B FFFFFF81 30 09 03 FFFFFF81 22 0C 08 0A FFFFFF81 32 72
   FFFFFF84 FFFFFF80 FFFFFF80 FFFFFF84 20 FFFFFF81 33 01 0C 70 72 6F 64 75 63 74
   41 72 69 74 79 15 02 FFFFFF81 17 08 0A FFFFFF81 35 72 FFFFFF84 FFFFFF80
   FFFFFF80 FFFFFF84 20 FFFFFF81 36 01 0E 70 72 6F 64 75 63 74 45 6C
   65 6D 65 6E 74 14 04 FFFFFF81 29 FFFFFF81 37 08 0A FFFFFF81 28 FFFFFF81
   34 FFFFFF81 FFFFFF80 FFFFFFC0 00 FFFFFF81 17 08 0A FFFFFF81 39 72 FFFFFF84 FFFFFF80 FFFFFF80 FFFFFF84
   20 FFFFFF81 3A 01 08 63 61 6E 45 71 75 61 6C 14 03 2B
   FFFFFF81 3B 08 0A FFFFFF81 28 FFFFFF81 38 FFFFFF81 FFFFFF80 FFFFFFC0 00 FFFFFF81 29 28 03
   72 FFFFFF81 3D 10 03 13 FFFFFF81 3E 09 03 FFFFFF81 3F 06 02 0C 73
   65 72 69 61 6C 69 7A 61 62 6C 65 07 09 FFFFFF81 41 00
   FFFFFF81 FFFFFF80 FFFFFF88 02 FFFFFF81 42 01 04 53 74 61 72 10 03 22 FFFFFF81
   43 06 09 73 00 FFFFFF84 FFFFFF81 FFFFFF80 FFFFFF88 02 FFFFFF81 44 13 06 FFFFFF81 43
   0A FFFFFF81 45 12 10 05 13 FFFFFF81 46 42 7F 09 03 FFFFFF81 47 06
   02 09 46 75 6E 63 74 69 6F 6E 31 08 07 17 FFFFFF81 43
   FFFFFF84 00 FFFFFF81 49 14 02 FFFFFF81 42 08 09 37 FFFFFF81 43 FFFFFF81 FFFFFF80 FFFFFF84
   40 FFFFFF81 4B 14 03 7F FFFFFF81 4C 08 06 79 FFFFFF81 4A FFFFFFC0 00 42
   08 0A FFFFFF81 4E FFFFFF81 43 FFFFFF81 FFFFFF80 FFFFFF84 40 FFFFFF81 4F 01 07 75 6E
   61 70 70 6C 79 14 04 FFFFFF81 50 FFFFFF81 51 10 03 13 50 42
   08 07 FFFFFF81 52 FFFFFF81 4D FFFFFFC0 00 7F 01 03 78 24 30 07 07
   FFFFFF81 54 00 FFFFFF88 42 FFFFFF81 55 01 03 45 70 73 10 03 22 FFFFFF81
   56 06 0A FFFFFF81 57 00 FFFFFF84 FFFFFF80 FFFFFF80 FFFFFF88 42 FFFFFF81 58 02 03 45
   70 73 13 05 FFFFFF81 56 21 12 75 08 07 17 FFFFFF81 56 FFFFFF84 00
   FFFFFF81 5A 14 02 FFFFFF81 55 08 09 29 FFFFFF81 56 FFFFFF88 FFFFFFC2 FFFFFF80 FFFFFF84 02
   2A 08 09 4A FFFFFF81 56 FFFFFF88 FFFFFF80 FFFFFFA0 FFFFFFA0 06 2B 08 08 FFFFFF81 1B
   FFFFFF81 56 FFFFFF84 20 FFFFFF81 5E 14 02 FFFFFF81 2F 08 0B FFFFFF81 2D FFFFFF81 56
   FFFFFF84 FFFFFF80 FFFFFF80 FFFFFF84 20 FFFFFF81 2E 08 0B FFFFFF81 32 FFFFFF81 56 FFFFFF84 FFFFFF80 FFFFFF80
   FFFFFF84 20 FFFFFF81 33 08 0B FFFFFF81 35 FFFFFF81 56 FFFFFF84 FFFFFF80 FFFFFF80 FFFFFF84 20 FFFFFF81
   62 14 04 FFFFFF81 29 FFFFFF81 63 08 0A FFFFFF81 28 FFFFFF81 61 FFFFFF81 FFFFFF80 FFFFFFC0
   00 FFFFFF81 17 08 0B FFFFFF81 39 FFFFFF81 56 FFFFFF84 FFFFFF80 FFFFFF80 FFFFFF84 20 FFFFFF81 65
   14 03 2B FFFFFF81 66 08 0A FFFFFF81 28 FFFFFF81 64 FFFFFF81 FFFFFF80 FFFFFFC0 00 FFFFFF81
   29 08 0B FFFFFF81 68 FFFFFF81 56 FFFFFF84 FFFFFF80 FFFFFF80 FFFFFF84 08 FFFFFF81 69 01 0B
   72 65 61 64 52 65 73 6F 6C 76 65 14 01 0A 28 04
   FFFFFF81 56 FFFFFF81 3D 06 0A FFFFFF81 6C 00 FFFFFF84 FFFFFF80 FFFFFF80 FFFFFF80 00 FFFFFF81 6D
   02 04 4D 65 74 61 13 04 FFFFFF81 6B 21 12 08 0A FFFFFF81 6F
   FFFFFF81 6B FFFFFF82 FFFFFF80 FFFFFFA0 FFFFFF80 04 42 01 02 72 31 08 07 17 FFFFFF81
   6B FFFFFF84 00 FFFFFF81 71 14 04 FFFFFF81 72 FFFFFF81 73 10 03 22 FFFFFF81 6B
   08 07 FFFFFF81 6F FFFFFF81 70 FFFFFFC0 00 42 08 08 29 FFFFFF81 6B FFFFFFC2 FFFFFF80
   FFFFFF84 02 2A 08 07 4A FFFFFF81 6B FFFFFFA0 FFFFFF80 06 2B 08 06 79 FFFFFF81
   6B FFFFFF84 00 7A 
  InnerClass: 
   public Alt=class scala/util/regexp/Base$Alt of class scala/util/regexp/Base
   public Meta=class scala/util/regexp/Base$Meta of class scala/util/regexp/Base
   public Star=class scala/util/regexp/Base$Star of class scala/util/regexp/Base
   public Sequ=class scala/util/regexp/Base$Sequ of class scala/util/regexp/Base
   public abstract RegExp=class scala/util/regexp/Base$RegExp of class scala/util/regexp/Base
  minor version: 0
  major version: 49
  Constant pool:
Asciz	SourceFile;
Asciz	Base.scala;
Asciz	Star$module;
Asciz	Lscala/util/regexp/Base$Star$;;
Asciz	Eps$module;
Asciz	Lscala/util/regexp/Base$Eps$;;
Asciz	Sequ$module;
Asciz	Lscala/util/regexp/Base$Sequ$;;
Asciz	Alt$module;
Asciz	Lscala/util/regexp/Base$Alt$;;
Asciz	<init>;
Asciz	()V;
Asciz	Code;
Asciz	LineNumberTable;
Asciz	java/lang/Object;
class	java/lang/Object
NameAndType	"<init>":()V
Method	java/lang/Object."<init>":()V
Asciz	Star;
Asciz	()Lscala/util/regexp/Base$Star$;;
Asciz	scala/util/regexp/Base;
class	scala/util/regexp/Base
NameAndType	Star$module:Lscala/util/regexp/Base$Star$;
Field	scala/util/regexp/Base.Star$module:Lscala/util/regexp/Base$Star$;
Asciz	scala/util/regexp/Base$Star$;
class	scala/util/regexp/Base$Star$
Asciz	(Lscala/util/regexp/Base;)V;
NameAndType	"<init>":(Lscala/util/regexp/Base;)V
Method	scala/util/regexp/Base$Star$."<init>":(Lscala/util/regexp/Base;)V
Asciz	Eps;
Asciz	()Lscala/util/regexp/Base$Eps$;;
NameAndType	Eps$module:Lscala/util/regexp/Base$Eps$;
Field	scala/util/regexp/Base.Eps$module:Lscala/util/regexp/Base$Eps$;
Asciz	scala/util/regexp/Base$Eps$;
class	scala/util/regexp/Base$Eps$
Method	scala/util/regexp/Base$Eps$."<init>":(Lscala/util/regexp/Base;)V
Asciz	Sequ;
Asciz	()Lscala/util/regexp/Base$Sequ$;;
NameAndType	Sequ$module:Lscala/util/regexp/Base$Sequ$;
Field	scala/util/regexp/Base.Sequ$module:Lscala/util/regexp/Base$Sequ$;
Asciz	scala/util/regexp/Base$Sequ$;
class	scala/util/regexp/Base$Sequ$
Method	scala/util/regexp/Base$Sequ$."<init>":(Lscala/util/regexp/Base;)V
Asciz	Alt;
Asciz	()Lscala/util/regexp/Base$Alt$;;
NameAndType	Alt$module:Lscala/util/regexp/Base$Alt$;
Field	scala/util/regexp/Base.Alt$module:Lscala/util/regexp/Base$Alt$;
Asciz	scala/util/regexp/Base$Alt$;
class	scala/util/regexp/Base$Alt$
Method	scala/util/regexp/Base$Alt$."<init>":(Lscala/util/regexp/Base;)V
Asciz	ScalaSig;
Asciz	InnerClasses;
Asciz	scala/util/regexp/Base$Alt;
class	scala/util/regexp/Base$Alt
Asciz	scala/util/regexp/Base$Meta;
class	scala/util/regexp/Base$Meta
Asciz	Meta;
Asciz	scala/util/regexp/Base$Star;
class	scala/util/regexp/Base$Star
Asciz	scala/util/regexp/Base$Sequ;
class	scala/util/regexp/Base$Sequ
Asciz	scala/util/regexp/Base$RegExp;
class	scala/util/regexp/Base$RegExp
Asciz	RegExp;
Asciz	scala/ScalaObject;
class	scala/ScalaObject

{
private scala.util.regexp.Base$Star$ Star$module;
  Signature: Lscala/util/regexp/Base$Star$;

public scala.util.regexp.Base$Eps$ Eps$module;
  Signature: Lscala/util/regexp/Base$Eps$;

private scala.util.regexp.Base$Sequ$ Sequ$module;
  Signature: Lscala/util/regexp/Base$Sequ$;

private scala.util.regexp.Base$Alt$ Alt$module;
  Signature: Lscala/util/regexp/Base$Alt$;

public scala.util.regexp.Base();
  Signature: ()V
  Code:
   Stack=1, Locals=1, Args_size=1
	aload_0
	invokespecial	Method java/lang/Object."<init>":()V
	return
  Labels:

public final scala.util.regexp.Base$Star$ Star();
  Signature: ()Lscala/util/regexp/Base$Star$;
  Code:
   Stack=4, Locals=1, Args_size=1
	aload_0
	getfield	Field Star$module:Lscala/util/regexp/Base$Star$;
	ifnonnull	l1 // aload_0
	aload_0
	new	class scala/util/regexp/Base$Star$
	dup
	aload_0
	invokespecial	Method scala/util/regexp/Base$Star$."<init>":(Lscala/util/regexp/Base;)V
	putfield	Field Star$module:Lscala/util/regexp/Base$Star$;
l1	aload_0
	getfield	Field Star$module:Lscala/util/regexp/Base$Star$;
	areturn
  Labels:
   	l1 = 19 // aload_0

public final scala.util.regexp.Base$Eps$ Eps();
  Signature: ()Lscala/util/regexp/Base$Eps$;
  Code:
   Stack=4, Locals=1, Args_size=1
	aload_0
	getfield	Field Eps$module:Lscala/util/regexp/Base$Eps$;
	ifnonnull	l1 // aload_0
	aload_0
	new	class scala/util/regexp/Base$Eps$
	dup
	aload_0
	invokespecial	Method scala/util/regexp/Base$Eps$."<init>":(Lscala/util/regexp/Base;)V
	putfield	Field Eps$module:Lscala/util/regexp/Base$Eps$;
l1	aload_0
	getfield	Field Eps$module:Lscala/util/regexp/Base$Eps$;
	areturn
  Labels:
   	l1 = 19 // aload_0

public final scala.util.regexp.Base$Sequ$ Sequ();
  Signature: ()Lscala/util/regexp/Base$Sequ$;
  Code:
   Stack=4, Locals=1, Args_size=1
	aload_0
	getfield	Field Sequ$module:Lscala/util/regexp/Base$Sequ$;
	ifnonnull	l1 // aload_0
	aload_0
	new	class scala/util/regexp/Base$Sequ$
	dup
	aload_0
	invokespecial	Method scala/util/regexp/Base$Sequ$."<init>":(Lscala/util/regexp/Base;)V
	putfield	Field Sequ$module:Lscala/util/regexp/Base$Sequ$;
l1	aload_0
	getfield	Field Sequ$module:Lscala/util/regexp/Base$Sequ$;
	areturn
  Labels:
   	l1 = 19 // aload_0

public final scala.util.regexp.Base$Alt$ Alt();
  Signature: ()Lscala/util/regexp/Base$Alt$;
  Code:
   Stack=4, Locals=1, Args_size=1
	aload_0
	getfield	Field Alt$module:Lscala/util/regexp/Base$Alt$;
	ifnonnull	l1 // aload_0
	aload_0
	new	class scala/util/regexp/Base$Alt$
	dup
	aload_0
	invokespecial	Method scala/util/regexp/Base$Alt$."<init>":(Lscala/util/regexp/Base;)V
	putfield	Field Alt$module:Lscala/util/regexp/Base$Alt$;
l1	aload_0
	getfield	Field Alt$module:Lscala/util/regexp/Base$Alt$;
	areturn
  Labels:
   	l1 = 19 // aload_0

}

