Compiled from "PointedHedgeExp.scala"
public final class scala.util.regexp.PointedHedgeExp$TopIter$ extends scala.runtime.AbstractFunction2 implements scala.ScalaObject
  SourceFile: "PointedHedgeExp.scala"
  Scala: length = 0x
   
  InnerClass: 
   public abstract RegExp=class scala/util/regexp/Base$RegExp of class scala/util/regexp/Base
   public TopIter=class scala/util/regexp/PointedHedgeExp$TopIter of class scala/util/regexp/PointedHedgeExp
  minor version: 0
  major version: 49
  Constant pool:
Asciz	SourceFile;
Asciz	PointedHedgeExp.scala;
Asciz	$outer;
Asciz	Lscala/util/regexp/PointedHedgeExp;;
Asciz	unapply;
Asciz	(Lscala/util/regexp/PointedHedgeExp$TopIter;)Lscala/Option;;
Asciz	Code;
Asciz	LineNumberTable;
Asciz	scala/None$;
class	scala/None$
Asciz	MODULE$;
Asciz	Lscala/None$;;
NameAndType	MODULE$:Lscala/None$;
Field	scala/None$.MODULE$:Lscala/None$;
Asciz	scala/Some;
class	scala/Some
Asciz	scala/Tuple2;
class	scala/Tuple2
Asciz	scala/util/regexp/PointedHedgeExp$TopIter;
class	scala/util/regexp/PointedHedgeExp$TopIter
Asciz	r1;
Asciz	()Lscala/util/regexp/Base$RegExp;;
NameAndType	r1:()Lscala/util/regexp/Base$RegExp;
Method	scala/util/regexp/PointedHedgeExp$TopIter.r1:()Lscala/util/regexp/Base$RegExp;
Asciz	r2;
NameAndType	r2:()Lscala/util/regexp/Base$RegExp;
Method	scala/util/regexp/PointedHedgeExp$TopIter.r2:()Lscala/util/regexp/Base$RegExp;
Asciz	<init>;
Asciz	(Ljava/lang/Object;Ljava/lang/Object;)V;
NameAndType	"<init>":(Ljava/lang/Object;Ljava/lang/Object;)V
Method	scala/Tuple2."<init>":(Ljava/lang/Object;Ljava/lang/Object;)V
Asciz	(Ljava/lang/Object;)V;
NameAndType	"<init>":(Ljava/lang/Object;)V
Method	scala/Some."<init>":(Ljava/lang/Object;)V
Asciz	this;
Asciz	Lscala/util/regexp/PointedHedgeExp$TopIter$;;
Asciz	x$0;
Asciz	Lscala/util/regexp/PointedHedgeExp$TopIter;;
Asciz	LocalVariableTable;
Asciz	apply;
Asciz	(Lscala/util/regexp/Base$RegExp;Lscala/util/regexp/Base$RegExp;)Lscala/util/regexp/PointedHedgeExp$TopIter;;
Asciz	scala/util/regexp/PointedHedgeExp$TopIter$;
class	scala/util/regexp/PointedHedgeExp$TopIter$
NameAndType	$outer:Lscala/util/regexp/PointedHedgeExp;
Field	scala/util/regexp/PointedHedgeExp$TopIter$.$outer:Lscala/util/regexp/PointedHedgeExp;
Asciz	(Lscala/util/regexp/PointedHedgeExp;Lscala/util/regexp/Base$RegExp;Lscala/util/regexp/Base$RegExp;)V;
NameAndType	"<init>":(Lscala/util/regexp/PointedHedgeExp;Lscala/util/regexp/Base$RegExp;Lscala/util/regexp/Base$RegExp;)V
Method	scala/util/regexp/PointedHedgeExp$TopIter."<init>":(Lscala/util/regexp/PointedHedgeExp;Lscala/util/regexp/Base$RegExp;Lscala/util/regexp/Base$RegExp;)V
Asciz	Lscala/util/regexp/Base$RegExp;;
Asciz	(Ljava/lang/Object;Ljava/lang/Object;)Ljava/lang/Object;;
Asciz	scala/util/regexp/Base$RegExp;
class	scala/util/regexp/Base$RegExp
NameAndType	apply:(Lscala/util/regexp/Base$RegExp;Lscala/util/regexp/Base$RegExp;)Lscala/util/regexp/PointedHedgeExp$TopIter;
Method	scala/util/regexp/PointedHedgeExp$TopIter$.apply:(Lscala/util/regexp/Base$RegExp;Lscala/util/regexp/Base$RegExp;)Lscala/util/regexp/PointedHedgeExp$TopIter;
Asciz	v1;
Asciz	Ljava/lang/Object;;
Asciz	v2;
Asciz	(Lscala/util/regexp/PointedHedgeExp;)V;
Asciz	java/lang/NullPointerException;
class	java/lang/NullPointerException
Asciz	()V;
NameAndType	"<init>":()V
Method	java/lang/NullPointerException."<init>":()V
Asciz	scala/runtime/AbstractFunction2;
class	scala/runtime/AbstractFunction2
Method	scala/runtime/AbstractFunction2."<init>":()V
Asciz	Scala;
Asciz	InnerClasses;
Asciz	scala/util/regexp/Base;
class	scala/util/regexp/Base
Asciz	RegExp;
Asciz	scala/util/regexp/PointedHedgeExp;
class	scala/util/regexp/PointedHedgeExp
Asciz	TopIter;
Asciz	scala/ScalaObject;
class	scala/ScalaObject

{
public final scala.util.regexp.PointedHedgeExp $outer;
  Signature: Lscala/util/regexp/PointedHedgeExp;

public scala.Option unapply(scala.util.regexp.PointedHedgeExp$TopIter);
  Signature: (Lscala/util/regexp/PointedHedgeExp$TopIter;)Lscala/Option;
  Code:
   Stack=6, Locals=2, Args_size=2
	aload_1
	ifnonnull	l1 // new
	getstatic	Field scala/None$.MODULE$:Lscala/None$;
	goto	l2 // areturn
l1	new	class scala/Some
	dup
	new	class scala/Tuple2
	dup
	aload_1
	invokevirtual	Method scala/util/regexp/PointedHedgeExp$TopIter.r1:()Lscala/util/regexp/Base$RegExp;
	aload_1
	invokevirtual	Method scala/util/regexp/PointedHedgeExp$TopIter.r2:()Lscala/util/regexp/Base$RegExp;
	invokespecial	Method scala/Tuple2."<init>":(Ljava/lang/Object;Ljava/lang/Object;)V
	invokespecial	Method scala/Some."<init>":(Ljava/lang/Object;)V
l2	areturn
  Labels:
   	l1 = 10 // new
   	l2 = 32 // areturn
  LocalVariableTable: 
   Start  Length  Slot  Name   Signature
   0      33      0    this       Lscala/util/regexp/PointedHedgeExp$TopIter$;
   0      33      1    x$0       Lscala/util/regexp/PointedHedgeExp$TopIter;


public scala.util.regexp.PointedHedgeExp$TopIter apply(scala.util.regexp.Base$RegExp, scala.util.regexp.Base$RegExp);
  Signature: (Lscala/util/regexp/Base$RegExp;Lscala/util/regexp/Base$RegExp;)Lscala/util/regexp/PointedHedgeExp$TopIter;
  Code:
   Stack=5, Locals=3, Args_size=3
	new	class scala/util/regexp/PointedHedgeExp$TopIter
	dup
	aload_0
	getfield	Field $outer:Lscala/util/regexp/PointedHedgeExp;
	aload_1
	aload_2
	invokespecial	Method scala/util/regexp/PointedHedgeExp$TopIter."<init>":(Lscala/util/regexp/PointedHedgeExp;Lscala/util/regexp/Base$RegExp;Lscala/util/regexp/Base$RegExp;)V
	areturn
  Labels:
  LocalVariableTable: 
   Start  Length  Slot  Name   Signature
   0      14      0    this       Lscala/util/regexp/PointedHedgeExp$TopIter$;
   0      14      1    r1       Lscala/util/regexp/Base$RegExp;
   0      14      2    r2       Lscala/util/regexp/Base$RegExp;


public java.lang.Object apply(java.lang.Object, java.lang.Object);
  Signature: (Ljava/lang/Object;Ljava/lang/Object;)Ljava/lang/Object;
  Code:
   Stack=3, Locals=3, Args_size=3
	aload_0
	aload_1
	checkcast	class scala/util/regexp/Base$RegExp
	aload_2
	checkcast	class scala/util/regexp/Base$RegExp
	invokevirtual	Method apply:(Lscala/util/regexp/Base$RegExp;Lscala/util/regexp/Base$RegExp;)Lscala/util/regexp/PointedHedgeExp$TopIter;
	areturn
  Labels:
  LocalVariableTable: 
   Start  Length  Slot  Name   Signature
   0      13      0    this       Lscala/util/regexp/PointedHedgeExp$TopIter$;
   0      13      1    v1       Ljava/lang/Object;
   0      13      2    v2       Ljava/lang/Object;


public scala.util.regexp.PointedHedgeExp$TopIter$(scala.util.regexp.PointedHedgeExp);
  Signature: (Lscala/util/regexp/PointedHedgeExp;)V
  Code:
   Stack=2, Locals=2, Args_size=2
	aload_1
	ifnonnull	l1 // aload_0
	new	class java/lang/NullPointerException
	dup
	invokespecial	Method java/lang/NullPointerException."<init>":()V
	athrow
l1	aload_0
	aload_1
	putfield	Field $outer:Lscala/util/regexp/PointedHedgeExp;
	aload_0
	invokespecial	Method scala/runtime/AbstractFunction2."<init>":()V
	return
  Labels:
   	l1 = 12 // aload_0
  LocalVariableTable: 
   Start  Length  Slot  Name   Signature
   0      22      0    this       Lscala/util/regexp/PointedHedgeExp$TopIter$;
   0      22      1    $outer       Lscala/util/regexp/PointedHedgeExp;


}

