Compiled from "PointedHedgeExp.scala"
public final class scala.util.regexp.PointedHedgeExp$Point$ extends scala.util.regexp.Base$RegExp implements scala.ScalaObject,scala.Product,java.io.Serializable
  SourceFile: "PointedHedgeExp.scala"
  Scala: length = 0x
   
  InnerClass: 
   public abstract RegExp=class scala/util/regexp/Base$RegExp of class scala/util/regexp/Base
  minor version: 0
  major version: 49
  Constant pool:
Asciz	SourceFile;
Asciz	PointedHedgeExp.scala;
Asciz	Scala;
Asciz	$outer;
Asciz	Lscala/util/regexp/PointedHedgeExp;;
Asciz	isNullable;
Asciz	Z;
Asciz	productIterator;
Asciz	()Lscala/collection/Iterator;;
Asciz	Code;
Asciz	LineNumberTable;
Asciz	scala/Product$class;
class	scala/Product$class
Asciz	(Lscala/Product;)Lscala/collection/Iterator;;
NameAndType	productIterator:(Lscala/Product;)Lscala/collection/Iterator;
Method	scala/Product$class.productIterator:(Lscala/Product;)Lscala/collection/Iterator;
Asciz	productElements;
NameAndType	productElements:(Lscala/Product;)Lscala/collection/Iterator;
Method	scala/Product$class.productElements:(Lscala/Product;)Lscala/collection/Iterator;
Asciz	Deprecated;
Asciz	()Z;
Asciz	toString;
Asciz	()Ljava/lang/String;;
Asciz	Point;
String	Point
Asciz	productPrefix;
Asciz	productArity;
Asciz	()I;
Asciz	productElement;
Asciz	(I)Ljava/lang/Object;;
Asciz	java/lang/IndexOutOfBoundsException;
class	java/lang/IndexOutOfBoundsException
Asciz	scala/runtime/BoxesRunTime;
class	scala/runtime/BoxesRunTime
Asciz	boxToInteger;
Asciz	(I)Ljava/lang/Integer;;
NameAndType	boxToInteger:(I)Ljava/lang/Integer;
Method	scala/runtime/BoxesRunTime.boxToInteger:(I)Ljava/lang/Integer;
Asciz	java/lang/Object;
class	java/lang/Object
NameAndType	toString:()Ljava/lang/String;
Method	java/lang/Object.toString:()Ljava/lang/String;
Asciz	<init>;
Asciz	(Ljava/lang/String;)V;
NameAndType	"<init>":(Ljava/lang/String;)V
Method	java/lang/IndexOutOfBoundsException."<init>":(Ljava/lang/String;)V
Asciz	productElementName;
Asciz	(I)Ljava/lang/String;;
Asciz	canEqual;
Asciz	(Ljava/lang/Object;)Z;
Asciz	scala/util/regexp/PointedHedgeExp$Point$;
class	scala/util/regexp/PointedHedgeExp$Point$
Asciz	readResolve;
Asciz	()Ljava/lang/Object;;
NameAndType	$outer:Lscala/util/regexp/PointedHedgeExp;
Field	scala/util/regexp/PointedHedgeExp$Point$.$outer:Lscala/util/regexp/PointedHedgeExp;
Asciz	scala/util/regexp/PointedHedgeExp;
class	scala/util/regexp/PointedHedgeExp
Asciz	()Lscala/util/regexp/PointedHedgeExp$Point$;;
NameAndType	Point:()Lscala/util/regexp/PointedHedgeExp$Point$;
Method	scala/util/regexp/PointedHedgeExp.Point:()Lscala/util/regexp/PointedHedgeExp$Point$;
Asciz	(Lscala/util/regexp/PointedHedgeExp;)V;
Asciz	java/lang/NullPointerException;
class	java/lang/NullPointerException
Asciz	()V;
NameAndType	"<init>":()V
Method	java/lang/NullPointerException."<init>":()V
Asciz	scala/util/regexp/Base$RegExp;
class	scala/util/regexp/Base$RegExp
Asciz	(Lscala/util/regexp/Base;)V;
NameAndType	"<init>":(Lscala/util/regexp/Base;)V
Method	scala/util/regexp/Base$RegExp."<init>":(Lscala/util/regexp/Base;)V
Asciz	$init$;
Asciz	(Lscala/Product;)V;
NameAndType	$init$:(Lscala/Product;)V
Method	scala/Product$class.$init$:(Lscala/Product;)V
Asciz	this;
Asciz	Lscala/util/regexp/PointedHedgeExp$Point$;;
Asciz	LocalVariableTable;
Asciz	InnerClasses;
Asciz	scala/util/regexp/Base;
class	scala/util/regexp/Base
Asciz	RegExp;
Asciz	scala/ScalaObject;
class	scala/ScalaObject
Asciz	scala/Product;
class	scala/Product
Asciz	java/io/Serializable;
class	java/io/Serializable

{
private final scala.util.regexp.PointedHedgeExp $outer;
  Signature: Lscala/util/regexp/PointedHedgeExp;

private final boolean isNullable;
  Signature: Z

public scala.collection.Iterator productIterator();
  Signature: ()Lscala/collection/Iterator;
  Code:
   Stack=1, Locals=1, Args_size=1
	aload_0
	invokestatic	Method scala/Product$class.productIterator:(Lscala/Product;)Lscala/collection/Iterator;
	areturn
  Labels:

public scala.collection.Iterator productElements();
  Signature: ()Lscala/collection/Iterator;
  Code:
   Stack=1, Locals=1, Args_size=1
	aload_0
	invokestatic	Method scala/Product$class.productElements:(Lscala/Product;)Lscala/collection/Iterator;
	areturn
  Labels:
  Deprecated: true

public final boolean isNullable();
  Signature: ()Z
  Code:
   Stack=1, Locals=1, Args_size=1
	iconst_0
	ireturn
  Labels:

public final java.lang.String toString();
  Signature: ()Ljava/lang/String;
  Code:
   Stack=1, Locals=1, Args_size=1
	ldc	String Point
	areturn
  Labels:

public java.lang.String productPrefix();
  Signature: ()Ljava/lang/String;
  Code:
   Stack=1, Locals=1, Args_size=1
	ldc	String Point
	areturn
  Labels:

public int productArity();
  Signature: ()I
  Code:
   Stack=1, Locals=1, Args_size=1
	iconst_0
	ireturn
  Labels:

public java.lang.Object productElement(int);
  Signature: (I)Ljava/lang/Object;
  Code:
   Stack=3, Locals=2, Args_size=2
	new	class java/lang/IndexOutOfBoundsException
	dup
	iload_1
	invokestatic	Method scala/runtime/BoxesRunTime.boxToInteger:(I)Ljava/lang/Integer;
	invokevirtual	Method java/lang/Object.toString:()Ljava/lang/String;
	invokespecial	Method java/lang/IndexOutOfBoundsException."<init>":(Ljava/lang/String;)V
	athrow
  Labels:

public java.lang.String productElementName(int);
  Signature: (I)Ljava/lang/String;
  Code:
   Stack=3, Locals=2, Args_size=2
	new	class java/lang/IndexOutOfBoundsException
	dup
	iload_1
	invokestatic	Method scala/runtime/BoxesRunTime.boxToInteger:(I)Ljava/lang/Integer;
	invokevirtual	Method java/lang/Object.toString:()Ljava/lang/String;
	invokespecial	Method java/lang/IndexOutOfBoundsException."<init>":(Ljava/lang/String;)V
	athrow
  Labels:

public boolean canEqual(java.lang.Object);
  Signature: (Ljava/lang/Object;)Z
  Code:
   Stack=1, Locals=2, Args_size=2
	aload_1
	instanceof	class scala/util/regexp/PointedHedgeExp$Point$
	ireturn
  Labels:

public java.lang.Object readResolve();
  Signature: ()Ljava/lang/Object;
  Code:
   Stack=1, Locals=1, Args_size=1
	aload_0
	getfield	Field $outer:Lscala/util/regexp/PointedHedgeExp;
	invokevirtual	Method scala/util/regexp/PointedHedgeExp.Point:()Lscala/util/regexp/PointedHedgeExp$Point$;
	areturn
  Labels:

public scala.util.regexp.PointedHedgeExp$Point$(scala.util.regexp.PointedHedgeExp);
  Signature: (Lscala/util/regexp/PointedHedgeExp;)V
  Code:
   Stack=2, Locals=2, Args_size=2
	aload_1
	ifnonnull	l1 // aload_0
	new	class java/lang/NullPointerException
	dup
	invokespecial	Method java/lang/NullPointerException."<init>":()V
	athrow
l1	aload_0
	aload_1
	putfield	Field $outer:Lscala/util/regexp/PointedHedgeExp;
	aload_0
	aload_1
	invokespecial	Method scala/util/regexp/Base$RegExp."<init>":(Lscala/util/regexp/Base;)V
	aload_0
	invokestatic	Method scala/Product$class.$init$:(Lscala/Product;)V
	return
  Labels:
   	l1 = 12 // aload_0
  LocalVariableTable: 
   Start  Length  Slot  Name   Signature
   0      27      0    this       Lscala/util/regexp/PointedHedgeExp$Point$;
   0      27      1    $outer       Lscala/util/regexp/PointedHedgeExp;


}

