Compiled from "PointedHedgeExp.scala"
public abstract class scala.util.regexp.PointedHedgeExp extends scala.util.regexp.Base implements scala.ScalaObject
  SourceFile: "PointedHedgeExp.scala"
  ScalaSig: length = 0x743
   05 00 FFFFFF81 78 06 08 01 02 FFFFFF84 FFFFFF80 FFFFFF80 FFFFFF81 00 09 02 0F
   50 6F 69 6E 74 65 64 48 65 64 67 65 45 78 70 0A
   02 03 04 01 06 72 65 67 65 78 70 0A 02 05 06 01
   04 75 74 69 6C 0A 01 07 01 05 73 63 61 6C 61 03
   00 13 03 00 0A 0E 10 02 0B 0C 0D 01 02 09 02 0D
   02 02 04 42 61 73 65 10 02 0F 10 0D 01 06 09 02
   11 06 02 0B 53 63 61 6C 61 4F 62 6A 65 63 74 08
   05 13 00 FFFFFF84 00 14 01 06 3C 69 6E 69 74 3E 14 01
   15 10 02 0B 00 04 08 17 00 FFFFFF84 FFFFFF80 FFFFFF80 FFFFFF82 00 18 02
   08 5F 72 65 67 65 78 70 54 11 02 19 1C 10 02 0F
   1A 09 02 1B 06 02 07 4E 6F 74 68 69 6E 67 10 02
   1D 1E 0D 01 00 09 02 1F 0C 02 06 52 65 67 45 78
   70 04 08 21 00 FFFFFF84 FFFFFF80 FFFFFF80 FFFFFF82 00 22 02 07 5F 6C 61
   62 65 6C 54 11 02 19 23 10 02 0F 24 09 02 25 06
   02 03 41 6E 79 06 08 27 00 FFFFFF84 FFFFFF80 FFFFFF80 FFFFFF80 40 28 02
   04 4E 6F 64 65 13 04 26 1C 0E 29 10 02 0F 2A 09
   02 2B 06 02 07 50 72 6F 64 75 63 74 08 08 2D 26
   FFFFFF82 FFFFFFCA FFFFFF80 FFFFFF84 00 2E 01 05 6C 61 62 65 6C 15 01 2F
   10 02 1D 20 08 08 31 26 FFFFFF82 FFFFFF88 FFFFFFA0 FFFFFF80 04 2F 01 06
   6C 61 62 65 6C 20 08 08 33 26 FFFFFF82 FFFFFFCA FFFFFF80 FFFFFF84 00 34
   01 01 72 15 01 35 10 02 1D 16 08 08 37 26 FFFFFF82 FFFFFF88
   FFFFFFA0 FFFFFF80 04 35 01 02 72 20 08 05 13 26 FFFFFF84 00 39 14
   03 3A 3B 3C 10 02 1D 26 08 05 2D 38 FFFFFFC0 00 2F 08
   05 33 38 FFFFFFC0 00 35 08 07 3E 26 FFFFFFC2 FFFFFF80 FFFFFF84 02 3F 01
   0A 69 73 4E 75 6C 6C 61 62 6C 65 15 01 40 0F 01
   41 19 01 00 08 06 43 26 FFFFFFA0 FFFFFF80 06 40 01 0B 69 73
   4E 75 6C 6C 61 62 6C 65 20 08 07 45 26 FFFFFF81 FFFFFF80 FFFFFF84
   00 46 01 04 63 6F 70 79 14 03 3A 47 48 08 07 2D
   44 FFFFFF90 FFFFFF80 FFFFFFC0 00 2F 08 07 33 44 FFFFFF90 FFFFFF80 FFFFFFC0 00 35 08
   07 4A 26 FFFFFF91 FFFFFF80 FFFFFF84 00 4B 01 0E 63 6F 70 79 24 64
   65 66 61 75 6C 74 24 31 15 01 4C 2A 02 2F 4D 2B
   01 4E 10 02 4F 54 0D 01 50 0A 02 51 52 01 09 75
   6E 63 68 65 63 6B 65 64 0A 02 53 06 01 0A 61 6E
   6E 6F 74 61 74 69 6F 6E 09 02 55 50 02 11 75 6E
   63 68 65 63 6B 65 64 56 61 72 69 61 6E 63 65 08
   07 57 26 FFFFFF91 FFFFFF80 FFFFFF84 00 58 01 0E 63 6F 70 79 24 64
   65 66 61 75 6C 74 24 32 15 01 59 2A 02 35 4D 08
   08 5B 26 FFFFFF84 FFFFFF80 FFFFFF80 FFFFFF84 20 5C 01 08 68 61 73 68 43
   6F 64 65 14 01 5D 10 02 0F 5E 09 02 5F 06 02 03
   49 6E 74 08 08 61 26 FFFFFF84 FFFFFF80 FFFFFF80 FFFFFF84 20 62 01 08 74
   6F 53 74 72 69 6E 67 14 01 63 10 02 64 67 0E 02
   0F 65 09 02 66 06 01 06 50 72 65 64 65 66 09 02
   68 69 02 06 53 74 72 69 6E 67 0A 02 66 06 08 08
   6B 26 FFFFFF84 FFFFFF80 FFFFFF80 FFFFFF84 20 6C 01 06 65 71 75 61 6C 73
   14 02 6D 70 10 02 0F 6E 09 02 6F 06 02 07 42 6F
   6F 6C 65 61 6E 08 07 71 6A FFFFFF81 FFFFFF80 FFFFFFC0 00 23 01 03
   78 24 31 08 08 73 26 FFFFFF84 FFFFFF80 FFFFFF80 FFFFFF84 20 74 01 0D 70
   72 6F 64 75 63 74 50 72 65 66 69 78 15 01 75 10
   02 76 7B 0D 01 77 0A 02 78 79 01 04 6C 61 6E 67
   0A 01 7A 01 04 6A 61 76 61 09 02 68 77 08 08 7D
   26 FFFFFF84 FFFFFF80 FFFFFF80 FFFFFF84 20 7E 01 0C 70 72 6F 64 75 63 74
   41 72 69 74 79 15 01 5D 08 0A FFFFFF81 00 26 FFFFFF84 FFFFFF80 FFFFFF80
   FFFFFF84 20 FFFFFF81 01 01 0E 70 72 6F 64 75 63 74 45 6C 65
   6D 65 6E 74 14 03 23 FFFFFF81 02 08 07 71 7F FFFFFF81 FFFFFF80 FFFFFFC0
   00 5D 08 0A FFFFFF81 04 26 FFFFFF84 FFFFFF80 FFFFFF80 FFFFFF84 20 FFFFFF81 05 01 08
   63 61 6E 45 71 75 61 6C 14 03 6D FFFFFF81 06 08 08 71
   FFFFFF81 03 FFFFFF81 FFFFFF80 FFFFFFC0 00 23 28 03 26 FFFFFF81 08 10 03 0F FFFFFF81
   09 09 03 FFFFFF81 0A 06 02 0C 73 65 72 69 61 6C 69 7A
   61 62 6C 65 07 09 FFFFFF81 0C 00 FFFFFF81 FFFFFF80 FFFFFF88 02 FFFFFF81 0D 01
   04 4E 6F 64 65 10 03 1D FFFFFF81 0E 06 09 27 00 FFFFFF84 FFFFFF81
   FFFFFF80 FFFFFF88 02 FFFFFF81 0F 13 07 FFFFFF81 0E FFFFFF81 10 FFFFFF81 13 0E 10 03
   76 FFFFFF81 11 09 03 FFFFFF81 12 77 02 06 4F 62 6A 65 63 74
   10 06 0F FFFFFF81 14 2F 35 3A 09 03 FFFFFF81 15 06 02 09 46
   75 6E 63 74 69 6F 6E 32 08 07 13 FFFFFF81 0E FFFFFF84 00 FFFFFF81
   17 14 02 FFFFFF81 0D 08 0A FFFFFF81 19 FFFFFF81 0E FFFFFF81 FFFFFF80 FFFFFF84 40 FFFFFF81
   1A 01 05 61 70 70 6C 79 14 05 3A FFFFFF81 1B FFFFFF81 1C 08
   06 2D FFFFFF81 18 FFFFFFC0 00 2F 08 06 33 FFFFFF81 18 FFFFFFC0 00 35 08
   0A FFFFFF81 1E FFFFFF81 0E FFFFFF81 FFFFFF80 FFFFFF84 40 FFFFFF81 1F 01 07 75 6E 61
   70 70 6C 79 14 04 FFFFFF81 20 FFFFFF81 26 10 05 0F FFFFFF81 21 FFFFFF81
   23 09 03 FFFFFF81 22 06 02 06 4F 70 74 69 6F 6E 10 05
   0F FFFFFF81 24 2F 35 09 03 FFFFFF81 25 06 02 06 54 75 70 6C
   65 32 08 07 FFFFFF81 27 FFFFFF81 1D FFFFFFC0 00 3A 01 03 78 24 30
   06 0A FFFFFF81 29 00 FFFFFF84 FFFFFF80 FFFFFF80 FFFFFF80 40 FFFFFF81 2A 02 07 54 6F
   70 49 74 65 72 13 05 FFFFFF81 28 1C 0E 29 08 0A FFFFFF81 2C
   FFFFFF81 28 FFFFFF82 FFFFFFCA FFFFFF80 FFFFFF84 00 34 01 02 72 31 08 0A FFFFFF81 2E
   FFFFFF81 28 FFFFFF82 FFFFFF88 FFFFFFA0 FFFFFF80 04 35 01 03 72 31 20 08 0A FFFFFF81
   30 FFFFFF81 28 FFFFFF82 FFFFFFCA FFFFFF80 FFFFFF84 00 34 01 02 72 32 08 0A FFFFFF81
   32 FFFFFF81 28 FFFFFF82 FFFFFF88 FFFFFFA0 FFFFFF80 04 35 01 03 72 32 20 08 07
   13 FFFFFF81 28 FFFFFF84 00 FFFFFF81 34 14 06 FFFFFF81 35 FFFFFF81 36 FFFFFF81 37 10
   03 1D FFFFFF81 28 08 07 FFFFFF81 2C FFFFFF81 33 FFFFFFC0 00 35 08 07 FFFFFF81
   30 FFFFFF81 33 FFFFFFC0 00 35 08 09 3E FFFFFF81 28 FFFFFFC2 FFFFFF80 FFFFFF84 02 FFFFFF81
   39 15 01 6D 08 07 43 FFFFFF81 28 FFFFFFA0 FFFFFF80 06 6D 08 09 45
   FFFFFF81 28 FFFFFF81 FFFFFF80 FFFFFF84 00 FFFFFF81 3C 14 06 FFFFFF81 35 FFFFFF81 3D FFFFFF81 3E
   08 09 FFFFFF81 2C FFFFFF81 3B FFFFFF90 FFFFFF80 FFFFFFC0 00 35 08 09 FFFFFF81 30 FFFFFF81
   3B FFFFFF90 FFFFFF80 FFFFFFC0 00 35 08 08 4A FFFFFF81 28 FFFFFF91 FFFFFF80 FFFFFF84 00 58
   08 08 57 FFFFFF81 28 FFFFFF91 FFFFFF80 FFFFFF84 00 58 08 09 5B FFFFFF81 28 FFFFFF84
   FFFFFF80 FFFFFF80 FFFFFF84 20 5C 08 09 61 FFFFFF81 28 FFFFFF84 FFFFFF80 FFFFFF80 FFFFFF84 20 62
   08 0A 6B FFFFFF81 28 FFFFFF84 FFFFFF80 FFFFFF80 FFFFFF84 20 FFFFFF81 44 14 03 6D FFFFFF81
   45 08 08 71 FFFFFF81 43 FFFFFF81 FFFFFF80 FFFFFFC0 00 23 08 09 73 FFFFFF81 28
   FFFFFF84 FFFFFF80 FFFFFF80 FFFFFF84 20 74 08 09 7D FFFFFF81 28 FFFFFF84 FFFFFF80 FFFFFF80 FFFFFF84 20
   7E 08 0B FFFFFF81 00 FFFFFF81 28 FFFFFF84 FFFFFF80 FFFFFF80 FFFFFF84 20 FFFFFF81 49 14 03
   23 FFFFFF81 4A 08 08 71 FFFFFF81 48 FFFFFF81 FFFFFF80 FFFFFFC0 00 5D 08 0B FFFFFF81
   04 FFFFFF81 28 FFFFFF84 FFFFFF80 FFFFFF80 FFFFFF84 20 FFFFFF81 4C 14 03 6D FFFFFF81 4D 08
   08 71 FFFFFF81 4B FFFFFF81 FFFFFF80 FFFFFFC0 00 23 28 04 FFFFFF81 28 FFFFFF81 08 07
   09 FFFFFF81 50 00 FFFFFF81 FFFFFF80 FFFFFF88 02 FFFFFF81 51 01 07 54 6F 70 49
   74 65 72 10 03 1D FFFFFF81 52 06 0A FFFFFF81 29 00 FFFFFF84 FFFFFF81 FFFFFF80
   FFFFFF88 02 FFFFFF81 53 13 07 FFFFFF81 52 FFFFFF81 10 FFFFFF81 54 0E 10 07 0F
   FFFFFF81 14 35 35 FFFFFF81 35 08 07 13 FFFFFF81 52 FFFFFF84 00 FFFFFF81 56 14
   02 FFFFFF81 51 08 0A FFFFFF81 19 FFFFFF81 52 FFFFFF81 FFFFFF80 FFFFFF84 40 FFFFFF81 58 14
   06 FFFFFF81 35 FFFFFF81 59 FFFFFF81 5A 08 07 FFFFFF81 2C FFFFFF81 57 FFFFFFC0 00 35
   08 07 FFFFFF81 30 FFFFFF81 57 FFFFFFC0 00 35 08 0A FFFFFF81 1E FFFFFF81 52 FFFFFF81
   FFFFFF80 FFFFFF84 40 FFFFFF81 5C 14 04 FFFFFF81 5D FFFFFF81 5F 10 05 0F FFFFFF81 21
   FFFFFF81 5E 10 05 0F FFFFFF81 24 35 35 08 08 FFFFFF81 27 FFFFFF81 5B FFFFFFC0
   00 FFFFFF81 35 07 07 FFFFFF81 61 00 FFFFFF88 42 FFFFFF81 62 01 05 50 6F
   69 6E 74 10 03 1D FFFFFF81 63 06 0A FFFFFF81 64 00 FFFFFF84 FFFFFF80 FFFFFF80
   FFFFFF88 42 FFFFFF81 65 02 05 50 6F 69 6E 74 13 05 FFFFFF81 63 1C
   0E 29 08 07 13 FFFFFF81 63 FFFFFF84 00 FFFFFF81 67 14 02 FFFFFF81 62 08
   08 3E FFFFFF81 63 FFFFFFC2 FFFFFF80 FFFFFF84 02 3F 08 07 43 FFFFFF81 63 FFFFFFA0 FFFFFF80
   06 40 08 0A 61 FFFFFF81 63 FFFFFF84 FFFFFF80 FFFFFF80 FFFFFF84 22 FFFFFF81 6B 14 01
   75 08 09 73 FFFFFF81 63 FFFFFF84 FFFFFF80 FFFFFF80 FFFFFF84 20 74 08 09 7D FFFFFF81
   63 FFFFFF84 FFFFFF80 FFFFFF80 FFFFFF84 20 7E 08 0B FFFFFF81 00 FFFFFF81 63 FFFFFF84 FFFFFF80 FFFFFF80
   FFFFFF84 20 FFFFFF81 6F 14 03 23 FFFFFF81 70 08 08 71 FFFFFF81 6E FFFFFF81 FFFFFF80
   FFFFFFC0 00 5D 08 0B FFFFFF81 04 FFFFFF81 63 FFFFFF84 FFFFFF80 FFFFFF80 FFFFFF84 20 FFFFFF81 72
   14 03 6D FFFFFF81 73 08 08 71 FFFFFF81 71 FFFFFF81 FFFFFF80 FFFFFFC0 00 23 08
   0B FFFFFF81 75 FFFFFF81 63 FFFFFF84 FFFFFF80 FFFFFF80 FFFFFF84 08 FFFFFF81 76 01 0B 72 65
   61 64 52 65 73 6F 6C 76 65 14 02 FFFFFF81 10 28 04 FFFFFF81
   63 FFFFFF81 08 
  InnerClass: 
   public Node=class scala/util/regexp/PointedHedgeExp$Node of class scala/util/regexp/PointedHedgeExp
   public TopIter=class scala/util/regexp/PointedHedgeExp$TopIter of class scala/util/regexp/PointedHedgeExp
  minor version: 0
  major version: 49
  Constant pool:
Asciz	SourceFile;
Asciz	PointedHedgeExp.scala;
Asciz	Node$module;
Asciz	Lscala/util/regexp/PointedHedgeExp$Node$;;
Asciz	TopIter$module;
Asciz	Lscala/util/regexp/PointedHedgeExp$TopIter$;;
Asciz	Point$module;
Asciz	Lscala/util/regexp/PointedHedgeExp$Point$;;
Asciz	Point;
Asciz	()Lscala/util/regexp/PointedHedgeExp$Point$;;
Asciz	Code;
Asciz	LineNumberTable;
Asciz	scala/util/regexp/PointedHedgeExp;
class	scala/util/regexp/PointedHedgeExp
NameAndType	Point$module:Lscala/util/regexp/PointedHedgeExp$Point$;
Field	scala/util/regexp/PointedHedgeExp.Point$module:Lscala/util/regexp/PointedHedgeExp$Point$;
Asciz	scala/util/regexp/PointedHedgeExp$Point$;
class	scala/util/regexp/PointedHedgeExp$Point$
Asciz	<init>;
Asciz	(Lscala/util/regexp/PointedHedgeExp;)V;
NameAndType	"<init>":(Lscala/util/regexp/PointedHedgeExp;)V
Method	scala/util/regexp/PointedHedgeExp$Point$."<init>":(Lscala/util/regexp/PointedHedgeExp;)V
Asciz	TopIter;
Asciz	()Lscala/util/regexp/PointedHedgeExp$TopIter$;;
NameAndType	TopIter$module:Lscala/util/regexp/PointedHedgeExp$TopIter$;
Field	scala/util/regexp/PointedHedgeExp.TopIter$module:Lscala/util/regexp/PointedHedgeExp$TopIter$;
Asciz	scala/util/regexp/PointedHedgeExp$TopIter$;
class	scala/util/regexp/PointedHedgeExp$TopIter$
Method	scala/util/regexp/PointedHedgeExp$TopIter$."<init>":(Lscala/util/regexp/PointedHedgeExp;)V
Asciz	Node;
Asciz	()Lscala/util/regexp/PointedHedgeExp$Node$;;
NameAndType	Node$module:Lscala/util/regexp/PointedHedgeExp$Node$;
Field	scala/util/regexp/PointedHedgeExp.Node$module:Lscala/util/regexp/PointedHedgeExp$Node$;
Asciz	scala/util/regexp/PointedHedgeExp$Node$;
class	scala/util/regexp/PointedHedgeExp$Node$
Method	scala/util/regexp/PointedHedgeExp$Node$."<init>":(Lscala/util/regexp/PointedHedgeExp;)V
Asciz	()V;
Asciz	scala/util/regexp/Base;
class	scala/util/regexp/Base
NameAndType	"<init>":()V
Method	scala/util/regexp/Base."<init>":()V
Asciz	ScalaSig;
Asciz	InnerClasses;
Asciz	scala/util/regexp/PointedHedgeExp$Node;
class	scala/util/regexp/PointedHedgeExp$Node
Asciz	scala/util/regexp/PointedHedgeExp$TopIter;
class	scala/util/regexp/PointedHedgeExp$TopIter
Asciz	scala/ScalaObject;
class	scala/ScalaObject

{
private scala.util.regexp.PointedHedgeExp$Node$ Node$module;
  Signature: Lscala/util/regexp/PointedHedgeExp$Node$;

private scala.util.regexp.PointedHedgeExp$TopIter$ TopIter$module;
  Signature: Lscala/util/regexp/PointedHedgeExp$TopIter$;

public scala.util.regexp.PointedHedgeExp$Point$ Point$module;
  Signature: Lscala/util/regexp/PointedHedgeExp$Point$;

public final scala.util.regexp.PointedHedgeExp$Point$ Point();
  Signature: ()Lscala/util/regexp/PointedHedgeExp$Point$;
  Code:
   Stack=4, Locals=1, Args_size=1
	aload_0
	getfield	Field Point$module:Lscala/util/regexp/PointedHedgeExp$Point$;
	ifnonnull	l1 // aload_0
	aload_0
	new	class scala/util/regexp/PointedHedgeExp$Point$
	dup
	aload_0
	invokespecial	Method scala/util/regexp/PointedHedgeExp$Point$."<init>":(Lscala/util/regexp/PointedHedgeExp;)V
	putfield	Field Point$module:Lscala/util/regexp/PointedHedgeExp$Point$;
l1	aload_0
	getfield	Field Point$module:Lscala/util/regexp/PointedHedgeExp$Point$;
	areturn
  Labels:
   	l1 = 19 // aload_0

public final scala.util.regexp.PointedHedgeExp$TopIter$ TopIter();
  Signature: ()Lscala/util/regexp/PointedHedgeExp$TopIter$;
  Code:
   Stack=4, Locals=1, Args_size=1
	aload_0
	getfield	Field TopIter$module:Lscala/util/regexp/PointedHedgeExp$TopIter$;
	ifnonnull	l1 // aload_0
	aload_0
	new	class scala/util/regexp/PointedHedgeExp$TopIter$
	dup
	aload_0
	invokespecial	Method scala/util/regexp/PointedHedgeExp$TopIter$."<init>":(Lscala/util/regexp/PointedHedgeExp;)V
	putfield	Field TopIter$module:Lscala/util/regexp/PointedHedgeExp$TopIter$;
l1	aload_0
	getfield	Field TopIter$module:Lscala/util/regexp/PointedHedgeExp$TopIter$;
	areturn
  Labels:
   	l1 = 19 // aload_0

public final scala.util.regexp.PointedHedgeExp$Node$ Node();
  Signature: ()Lscala/util/regexp/PointedHedgeExp$Node$;
  Code:
   Stack=4, Locals=1, Args_size=1
	aload_0
	getfield	Field Node$module:Lscala/util/regexp/PointedHedgeExp$Node$;
	ifnonnull	l1 // aload_0
	aload_0
	new	class scala/util/regexp/PointedHedgeExp$Node$
	dup
	aload_0
	invokespecial	Method scala/util/regexp/PointedHedgeExp$Node$."<init>":(Lscala/util/regexp/PointedHedgeExp;)V
	putfield	Field Node$module:Lscala/util/regexp/PointedHedgeExp$Node$;
l1	aload_0
	getfield	Field Node$module:Lscala/util/regexp/PointedHedgeExp$Node$;
	areturn
  Labels:
   	l1 = 19 // aload_0

public scala.util.regexp.PointedHedgeExp();
  Signature: ()V
  Code:
   Stack=1, Locals=1, Args_size=1
	aload_0
	invokespecial	Method scala/util/regexp/Base."<init>":()V
	return
  Labels:

}

