Compiled from "PointedHedgeExp.scala"
public class scala.util.regexp.PointedHedgeExp$Node extends scala.util.regexp.Base$RegExp implements scala.ScalaObject,scala.Product,java.io.Serializable
  SourceFile: "PointedHedgeExp.scala"
  Scala: length = 0x
   
  InnerClass: 
   public abstract #138= #29 of #137; //RegExp=class scala/util/regexp/Base$RegExp of class scala/util/regexp/Base
   public #91= #16 of #140; //Node=class scala/util/regexp/PointedHedgeExp$Node of class scala/util/regexp/PointedHedgeExp
  minor version: 0
  major version: 49
  Constant pool:
const #1 = Asciz	SourceFile;
const #2 = Asciz	PointedHedgeExp.scala;
const #3 = Asciz	$outer;
const #4 = Asciz	Lscala/util/regexp/PointedHedgeExp;;
const #5 = Asciz	isNullable;
const #6 = Asciz	Z;
const #7 = Asciz	r;
const #8 = Asciz	Lscala/util/regexp/Base$RegExp;;
const #9 = Asciz	label;
const #10 = Asciz	Ljava/lang/Object;;
const #11 = Asciz	<init>;
const #12 = Asciz	(Lscala/util/regexp/PointedHedgeExp;Ljava/lang/Object;Lscala/util/regexp/Base$RegExp;)V;
const #13 = Asciz	Code;
const #14 = Asciz	LineNumberTable;
const #15 = Asciz	scala/util/regexp/PointedHedgeExp$Node;
const #16 = class	#15;	//  scala/util/regexp/PointedHedgeExp$Node
const #17 = NameAndType	#9:#10;//  label:Ljava/lang/Object;
const #18 = Field	#16.#17;	//  scala/util/regexp/PointedHedgeExp$Node.label:Ljava/lang/Object;
const #19 = NameAndType	#7:#8;//  r:Lscala/util/regexp/Base$RegExp;
const #20 = Field	#16.#19;	//  scala/util/regexp/PointedHedgeExp$Node.r:Lscala/util/regexp/Base$RegExp;
const #21 = Asciz	java/lang/NullPointerException;
const #22 = class	#21;	//  java/lang/NullPointerException
const #23 = Asciz	()V;
const #24 = NameAndType	#11:#23;//  "<init>":()V
const #25 = Method	#22.#24;	//  java/lang/NullPointerException."<init>":()V
const #26 = NameAndType	#3:#4;//  $outer:Lscala/util/regexp/PointedHedgeExp;
const #27 = Field	#16.#26;	//  scala/util/regexp/PointedHedgeExp$Node.$outer:Lscala/util/regexp/PointedHedgeExp;
const #28 = Asciz	scala/util/regexp/Base$RegExp;
const #29 = class	#28;	//  scala/util/regexp/Base$RegExp
const #30 = Asciz	(Lscala/util/regexp/Base;)V;
const #31 = NameAndType	#11:#30;//  "<init>":(Lscala/util/regexp/Base;)V
const #32 = Method	#29.#31;	//  scala/util/regexp/Base$RegExp."<init>":(Lscala/util/regexp/Base;)V
const #33 = Asciz	scala/Product$class;
const #34 = class	#33;	//  scala/Product$class
const #35 = Asciz	$init$;
const #36 = Asciz	(Lscala/Product;)V;
const #37 = NameAndType	#35:#36;//  $init$:(Lscala/Product;)V
const #38 = Method	#34.#37;	//  scala/Product$class.$init$:(Lscala/Product;)V
const #39 = Asciz	this;
const #40 = Asciz	Lscala/util/regexp/PointedHedgeExp$Node;;
const #41 = Asciz	LocalVariableTable;
const #42 = Asciz	gd1$1;
const #43 = Asciz	(Ljava/lang/Object;Lscala/util/regexp/Base$RegExp;)Z;
const #44 = Asciz	()Ljava/lang/Object;;
const #45 = NameAndType	#9:#44;//  label:()Ljava/lang/Object;
const #46 = Method	#16.#45;	//  scala/util/regexp/PointedHedgeExp$Node.label:()Ljava/lang/Object;
const #47 = Asciz	java/lang/Number;
const #48 = class	#47;	//  java/lang/Number
const #49 = Asciz	java/lang/Character;
const #50 = class	#49;	//  java/lang/Character
const #51 = Asciz	scala/runtime/BoxesRunTime;
const #52 = class	#51;	//  scala/runtime/BoxesRunTime
const #53 = Asciz	equals2;
const #54 = Asciz	(Ljava/lang/Object;Ljava/lang/Object;)Z;
const #55 = NameAndType	#53:#54;//  equals2:(Ljava/lang/Object;Ljava/lang/Object;)Z
const #56 = Method	#52.#55;	//  scala/runtime/BoxesRunTime.equals2:(Ljava/lang/Object;Ljava/lang/Object;)Z
const #57 = Asciz	java/lang/Object;
const #58 = class	#57;	//  java/lang/Object
const #59 = Asciz	equals;
const #60 = Asciz	(Ljava/lang/Object;)Z;
const #61 = NameAndType	#59:#60;//  equals:(Ljava/lang/Object;)Z
const #62 = Method	#58.#61;	//  java/lang/Object.equals:(Ljava/lang/Object;)Z
const #63 = Asciz	()Lscala/util/regexp/Base$RegExp;;
const #64 = NameAndType	#7:#63;//  r:()Lscala/util/regexp/Base$RegExp;
const #65 = Method	#16.#64;	//  scala/util/regexp/PointedHedgeExp$Node.r:()Lscala/util/regexp/Base$RegExp;
const #66 = Asciz	y0;
const #67 = Asciz	scala$util$regexp$PointedHedgeExp$Node$$$outer;
const #68 = Asciz	()Lscala/util/regexp/PointedHedgeExp;;
const #69 = Asciz	canEqual;
const #70 = Asciz	productElement;
const #71 = Asciz	(I)Ljava/lang/Object;;
const #72 = Asciz	java/lang/IndexOutOfBoundsException;
const #73 = class	#72;	//  java/lang/IndexOutOfBoundsException
const #74 = Asciz	boxToInteger;
const #75 = Asciz	(I)Ljava/lang/Integer;;
const #76 = NameAndType	#74:#75;//  boxToInteger:(I)Ljava/lang/Integer;
const #77 = Method	#52.#76;	//  scala/runtime/BoxesRunTime.boxToInteger:(I)Ljava/lang/Integer;
const #78 = Asciz	toString;
const #79 = Asciz	()Ljava/lang/String;;
const #80 = NameAndType	#78:#79;//  toString:()Ljava/lang/String;
const #81 = Method	#58.#80;	//  java/lang/Object.toString:()Ljava/lang/String;
const #82 = Asciz	(Ljava/lang/String;)V;
const #83 = NameAndType	#11:#82;//  "<init>":(Ljava/lang/String;)V
const #84 = Method	#73.#83;	//  java/lang/IndexOutOfBoundsException."<init>":(Ljava/lang/String;)V
const #85 = Asciz	scala/MatchError;
const #86 = class	#85;	//  scala/MatchError
const #87 = Method	#86.#83;	//  scala/MatchError."<init>":(Ljava/lang/String;)V
const #88 = Asciz	productArity;
const #89 = Asciz	()I;
const #90 = Asciz	productPrefix;
const #91 = Asciz	Node;
const #92 = String	#91;	//  Node
const #93 = NameAndType	#67:#68;//  scala$util$regexp$PointedHedgeExp$Node$$$outer:()Lscala/util/regexp/PointedHedgeExp;
const #94 = Method	#16.#93;	//  scala/util/regexp/PointedHedgeExp$Node.scala$util$regexp$PointedHedgeExp$Node$$$outer:()Lscala/util/regexp/PointedHedgeExp;
const #95 = NameAndType	#42:#43;//  gd1$1:(Ljava/lang/Object;Lscala/util/regexp/Base$RegExp;)Z
const #96 = Method	#16.#95;	//  scala/util/regexp/PointedHedgeExp$Node.gd1$1:(Ljava/lang/Object;Lscala/util/regexp/Base$RegExp;)Z
const #97 = Asciz	scala/Equals;
const #98 = class	#97;	//  scala/Equals
const #99 = NameAndType	#69:#60;//  canEqual:(Ljava/lang/Object;)Z
const #100 = InterfaceMethod	#98.#99;	//  scala/Equals.canEqual:(Ljava/lang/Object;)Z
const #101 = Asciz	temp2;
const #102 = Asciz	temp3;
const #103 = Asciz	temp4;
const #104 = Asciz	scala/runtime/ScalaRunTime$;
const #105 = class	#104;	//  scala/runtime/ScalaRunTime$
const #106 = Asciz	MODULE$;
const #107 = Asciz	Lscala/runtime/ScalaRunTime$;;
const #108 = NameAndType	#106:#107;//  MODULE$:Lscala/runtime/ScalaRunTime$;
const #109 = Field	#105.#108;	//  scala/runtime/ScalaRunTime$.MODULE$:Lscala/runtime/ScalaRunTime$;
const #110 = Asciz	_toString;
const #111 = Asciz	(Lscala/Product;)Ljava/lang/String;;
const #112 = NameAndType	#110:#111;//  _toString:(Lscala/Product;)Ljava/lang/String;
const #113 = Method	#105.#112;	//  scala/runtime/ScalaRunTime$._toString:(Lscala/Product;)Ljava/lang/String;
const #114 = Asciz	hashCode;
const #115 = Asciz	_hashCode;
const #116 = Asciz	(Lscala/Product;)I;
const #117 = NameAndType	#115:#116;//  _hashCode:(Lscala/Product;)I
const #118 = Method	#105.#117;	//  scala/runtime/ScalaRunTime$._hashCode:(Lscala/Product;)I
const #119 = Asciz	copy;
const #120 = Asciz	(Ljava/lang/Object;Lscala/util/regexp/Base$RegExp;)Lscala/util/regexp/PointedHedgeExp$Node;;
const #121 = NameAndType	#11:#12;//  "<init>":(Lscala/util/regexp/PointedHedgeExp;Ljava/lang/Object;Lscala/util/regexp/Base$RegExp;)V
const #122 = Method	#16.#121;	//  scala/util/regexp/PointedHedgeExp$Node."<init>":(Lscala/util/regexp/PointedHedgeExp;Ljava/lang/Object;Lscala/util/regexp/Base$RegExp;)V
const #123 = Asciz	()Z;
const #124 = Asciz	copy$default$1;
const #125 = Asciz	copy$default$2;
const #126 = Asciz	productElements;
const #127 = Asciz	()Lscala/collection/Iterator;;
const #128 = Asciz	(Lscala/Product;)Lscala/collection/Iterator;;
const #129 = NameAndType	#126:#128;//  productElements:(Lscala/Product;)Lscala/collection/Iterator;
const #130 = Method	#34.#129;	//  scala/Product$class.productElements:(Lscala/Product;)Lscala/collection/Iterator;
const #131 = Asciz	productIterator;
const #132 = NameAndType	#131:#128;//  productIterator:(Lscala/Product;)Lscala/collection/Iterator;
const #133 = Method	#34.#132;	//  scala/Product$class.productIterator:(Lscala/Product;)Lscala/collection/Iterator;
const #134 = Asciz	Scala;
const #135 = Asciz	InnerClasses;
const #136 = Asciz	scala/util/regexp/Base;
const #137 = class	#136;	//  scala/util/regexp/Base
const #138 = Asciz	RegExp;
const #139 = Asciz	scala/util/regexp/PointedHedgeExp;
const #140 = class	#139;	//  scala/util/regexp/PointedHedgeExp
const #141 = Asciz	scala/ScalaObject;
const #142 = class	#141;	//  scala/ScalaObject
const #143 = Asciz	scala/Product;
const #144 = class	#143;	//  scala/Product
const #145 = Asciz	java/io/Serializable;
const #146 = class	#145;	//  java/io/Serializable

{
public final scala.util.regexp.PointedHedgeExp $outer;

public scala.util.regexp.PointedHedgeExp$Node(scala.util.regexp.PointedHedgeExp, java.lang.Object, scala.util.regexp.Base$RegExp);
  Code:
   Stack=2, Locals=4, Args_size=4
   0:	aload_0
   1:	aload_2
   2:	putfield	#18; //Field label:Ljava/lang/Object;
   5:	aload_0
   6:	aload_3
   7:	putfield	#20; //Field r:Lscala/util/regexp/Base$RegExp;
   10:	aload_1
   11:	ifnonnull	22
   14:	new	#22; //class java/lang/NullPointerException
   17:	dup
   18:	invokespecial	#25; //Method java/lang/NullPointerException."<init>":()V
   21:	athrow
   22:	aload_0
   23:	aload_1
   24:	putfield	#27; //Field $outer:Lscala/util/regexp/PointedHedgeExp;
   27:	aload_0
   28:	aload_1
   29:	invokespecial	#32; //Method scala/util/regexp/Base$RegExp."<init>":(Lscala/util/regexp/Base;)V
   32:	aload_0
   33:	invokestatic	#38; //Method scala/Product$class.$init$:(Lscala/Product;)V
   36:	return
  LineNumberTable: 
   line 25: 0

  LocalVariableTable: 
   Start  Length  Slot  Name   Signature
   0      37      0    this       Lscala/util/regexp/PointedHedgeExp$Node;
   0      37      1    $outer       Lscala/util/regexp/PointedHedgeExp;
   0      37      2    label       Ljava/lang/Object;
   0      37      3    r       Lscala/util/regexp/Base$RegExp;


public scala.util.regexp.PointedHedgeExp scala$util$regexp$PointedHedgeExp$Node$$$outer();
  Code:
   Stack=1, Locals=1, Args_size=1
   0:	aload_0
   1:	getfield	#27; //Field $outer:Lscala/util/regexp/PointedHedgeExp;
   4:	areturn
  LineNumberTable: 
   line 25: 0


public boolean canEqual(java.lang.Object);
  Code:
   Stack=1, Locals=2, Args_size=2
   0:	aload_1
   1:	instanceof	#16; //class scala/util/regexp/PointedHedgeExp$Node
   4:	ireturn
  LineNumberTable: 
   line 25: 0


public java.lang.Object productElement(int);
  Code:
   Stack=3, Locals=2, Args_size=2
   0:	iload_1
   1:	tableswitch{ //0 to 1
		0: 84;
		1: 58;
		default: 24 }
   24:	iconst_1
   25:	ifeq	43
   28:	new	#73; //class java/lang/IndexOutOfBoundsException
   31:	dup
   32:	iload_1
   33:	invokestatic	#77; //Method scala/runtime/BoxesRunTime.boxToInteger:(I)Ljava/lang/Integer;
   36:	invokevirtual	#81; //Method java/lang/Object.toString:()Ljava/lang/String;
   39:	invokespecial	#84; //Method java/lang/IndexOutOfBoundsException."<init>":(Ljava/lang/String;)V
   42:	athrow
   43:	new	#86; //class scala/MatchError
   46:	dup
   47:	iload_1
   48:	invokestatic	#77; //Method scala/runtime/BoxesRunTime.boxToInteger:(I)Ljava/lang/Integer;
   51:	invokevirtual	#81; //Method java/lang/Object.toString:()Ljava/lang/String;
   54:	invokespecial	#87; //Method scala/MatchError."<init>":(Ljava/lang/String;)V
   57:	athrow
   58:	iconst_1
   59:	ifeq	69
   62:	aload_0
   63:	invokevirtual	#65; //Method r:()Lscala/util/regexp/Base$RegExp;
   66:	goto	92
   69:	new	#86; //class scala/MatchError
   72:	dup
   73:	iload_1
   74:	invokestatic	#77; //Method scala/runtime/BoxesRunTime.boxToInteger:(I)Ljava/lang/Integer;
   77:	invokevirtual	#81; //Method java/lang/Object.toString:()Ljava/lang/String;
   80:	invokespecial	#87; //Method scala/MatchError."<init>":(Ljava/lang/String;)V
   83:	athrow
   84:	iconst_1
   85:	ifeq	93
   88:	aload_0
   89:	invokevirtual	#46; //Method label:()Ljava/lang/Object;
   92:	areturn
   93:	new	#86; //class scala/MatchError
   96:	dup
   97:	iload_1
   98:	invokestatic	#77; //Method scala/runtime/BoxesRunTime.boxToInteger:(I)Ljava/lang/Integer;
   101:	invokevirtual	#81; //Method java/lang/Object.toString:()Ljava/lang/String;
   104:	invokespecial	#87; //Method scala/MatchError."<init>":(Ljava/lang/String;)V
   107:	athrow
  LineNumberTable: 
   line 25: 0
   line 21: 24
   line 25: 28
   line 21: 58
   line 25: 62
   line 21: 84
   line 25: 88


public int productArity();
  Code:
   Stack=1, Locals=1, Args_size=1
   0:	iconst_2
   1:	ireturn
  LineNumberTable: 
   line 25: 0


public java.lang.String productPrefix();
  Code:
   Stack=1, Locals=1, Args_size=1
   0:	ldc	#92; //String Node
   2:	areturn
  LineNumberTable: 
   line 25: 0


public boolean equals(java.lang.Object);
  Code:
   Stack=3, Locals=5, Args_size=2
   0:	aload_0
   1:	aload_1
   2:	if_acmpeq	93
   5:	aload_1
   6:	instanceof	#16; //class scala/util/regexp/PointedHedgeExp$Node
   9:	ifeq	85
   12:	aload_1
   13:	checkcast	#16; //class scala/util/regexp/PointedHedgeExp$Node
   16:	invokevirtual	#94; //Method scala$util$regexp$PointedHedgeExp$Node$$$outer:()Lscala/util/regexp/PointedHedgeExp;
   19:	aload_0
   20:	invokevirtual	#94; //Method scala$util$regexp$PointedHedgeExp$Node$$$outer:()Lscala/util/regexp/PointedHedgeExp;
   23:	if_acmpne	85
   26:	aload_1
   27:	checkcast	#16; //class scala/util/regexp/PointedHedgeExp$Node
   30:	astore_2
   31:	aload_2
   32:	invokevirtual	#46; //Method label:()Ljava/lang/Object;
   35:	astore_3
   36:	aload_2
   37:	invokevirtual	#65; //Method r:()Lscala/util/regexp/Base$RegExp;
   40:	astore	4
   42:	aload_0
   43:	aload_3
   44:	aload	4
   46:	invokespecial	#96; //Method gd1$1:(Ljava/lang/Object;Lscala/util/regexp/Base$RegExp;)Z
   49:	ifeq	65
   52:	aload_1
   53:	checkcast	#16; //class scala/util/regexp/PointedHedgeExp$Node
   56:	aload_0
   57:	invokeinterface	#100,  2; //InterfaceMethod scala/Equals.canEqual:(Ljava/lang/Object;)Z
   62:	goto	90
   65:	iconst_1
   66:	ifeq	73
   69:	iconst_0
   70:	goto	90
   73:	new	#86; //class scala/MatchError
   76:	dup
   77:	aload_1
   78:	invokevirtual	#81; //Method java/lang/Object.toString:()Ljava/lang/String;
   81:	invokespecial	#87; //Method scala/MatchError."<init>":(Ljava/lang/String;)V
   84:	athrow
   85:	iconst_1
   86:	ifeq	99
   89:	iconst_0
   90:	ifeq	97
   93:	iconst_1
   94:	goto	98
   97:	iconst_0
   98:	ireturn
   99:	new	#86; //class scala/MatchError
   102:	dup
   103:	aload_1
   104:	invokevirtual	#81; //Method java/lang/Object.toString:()Ljava/lang/String;
   107:	invokespecial	#87; //Method scala/MatchError."<init>":(Ljava/lang/String;)V
   110:	athrow
  LineNumberTable: 
   line 25: 0
   line 21: 65
   line 25: 73
   line 21: 85
   line 25: 90

  LocalVariableTable: 
   Start  Length  Slot  Name   Signature
   0      111      0    this       Lscala/util/regexp/PointedHedgeExp$Node;
   31      54      2    temp2       Lscala/util/regexp/PointedHedgeExp$Node;
   36      49      3    temp3       Ljava/lang/Object;
   42      43      4    temp4       Lscala/util/regexp/Base$RegExp;


public java.lang.String toString();
  Code:
   Stack=2, Locals=1, Args_size=1
   0:	getstatic	#109; //Field scala/runtime/ScalaRunTime$.MODULE$:Lscala/runtime/ScalaRunTime$;
   3:	aload_0
   4:	invokevirtual	#113; //Method scala/runtime/ScalaRunTime$._toString:(Lscala/Product;)Ljava/lang/String;
   7:	areturn
  LineNumberTable: 
   line 25: 0


public int hashCode();
  Code:
   Stack=2, Locals=1, Args_size=1
   0:	getstatic	#109; //Field scala/runtime/ScalaRunTime$.MODULE$:Lscala/runtime/ScalaRunTime$;
   3:	aload_0
   4:	invokevirtual	#118; //Method scala/runtime/ScalaRunTime$._hashCode:(Lscala/Product;)I
   7:	ireturn
  LineNumberTable: 
   line 25: 0


public scala.util.regexp.PointedHedgeExp$Node copy(java.lang.Object, scala.util.regexp.Base$RegExp);
  Code:
   Stack=5, Locals=3, Args_size=3
   0:	new	#16; //class scala/util/regexp/PointedHedgeExp$Node
   3:	dup
   4:	aload_0
   5:	invokevirtual	#94; //Method scala$util$regexp$PointedHedgeExp$Node$$$outer:()Lscala/util/regexp/PointedHedgeExp;
   8:	aload_1
   9:	aload_2
   10:	invokespecial	#122; //Method "<init>":(Lscala/util/regexp/PointedHedgeExp;Ljava/lang/Object;Lscala/util/regexp/Base$RegExp;)V
   13:	areturn
  LineNumberTable: 
   line 25: 0

  LocalVariableTable: 
   Start  Length  Slot  Name   Signature
   0      14      0    this       Lscala/util/regexp/PointedHedgeExp$Node;
   0      14      1    label       Ljava/lang/Object;
   0      14      2    r       Lscala/util/regexp/Base$RegExp;


public final boolean isNullable();
  Code:
   Stack=1, Locals=1, Args_size=1
   0:	iconst_0
   1:	ireturn
  LineNumberTable: 
   line 26: 0


public scala.util.regexp.Base$RegExp r();
  Code:
   Stack=1, Locals=1, Args_size=1
   0:	aload_0
   1:	getfield	#20; //Field r:Lscala/util/regexp/Base$RegExp;
   4:	areturn
  LineNumberTable: 
   line 25: 0


public java.lang.Object label();
  Code:
   Stack=1, Locals=1, Args_size=1
   0:	aload_0
   1:	getfield	#18; //Field label:Ljava/lang/Object;
   4:	areturn
  LineNumberTable: 
   line 25: 0


public java.lang.Object copy$default$1();
  Code:
   Stack=1, Locals=1, Args_size=1
   0:	aload_0
   1:	invokevirtual	#46; //Method label:()Ljava/lang/Object;
   4:	areturn
  LineNumberTable: 
   line 25: 0


public scala.util.regexp.Base$RegExp copy$default$2();
  Code:
   Stack=1, Locals=1, Args_size=1
   0:	aload_0
   1:	invokevirtual	#65; //Method r:()Lscala/util/regexp/Base$RegExp;
   4:	areturn
  LineNumberTable: 
   line 25: 0


public scala.collection.Iterator productElements();
  Code:
   Stack=1, Locals=1, Args_size=1
   0:	aload_0
   1:	invokestatic	#130; //Method scala/Product$class.productElements:(Lscala/Product;)Lscala/collection/Iterator;
   4:	areturn
  LineNumberTable: 
   line 25: 0


public scala.collection.Iterator productIterator();
  Code:
   Stack=1, Locals=1, Args_size=1
   0:	aload_0
   1:	invokestatic	#133; //Method scala/Product$class.productIterator:(Lscala/Product;)Lscala/collection/Iterator;
   4:	areturn
  LineNumberTable: 
   line 25: 0


}

