Compiled from "PointedHedgeExp.scala"
public final class scala.util.regexp.PointedHedgeExp$Node$ extends java.lang.Object implements scala.Function2,scala.ScalaObject
  SourceFile: "PointedHedgeExp.scala"
  Scala: length = 0x
   
  InnerClass: 
   public abstract RegExp=class scala/util/regexp/Base$RegExp of class scala/util/regexp/Base
   public Node=class scala/util/regexp/PointedHedgeExp$Node of class scala/util/regexp/PointedHedgeExp
  minor version: 0
  major version: 49
  Constant pool:
Asciz	SourceFile;
Asciz	PointedHedgeExp.scala;
Asciz	Scala;
Asciz	$outer;
Asciz	Lscala/util/regexp/PointedHedgeExp;;
Asciz	toString;
Asciz	()Ljava/lang/String;;
Asciz	Code;
Asciz	LineNumberTable;
Asciz	scala/Function2$class;
class	scala/Function2$class
Asciz	(Lscala/Function2;)Ljava/lang/String;;
NameAndType	toString:(Lscala/Function2;)Ljava/lang/String;
Method	scala/Function2$class.toString:(Lscala/Function2;)Ljava/lang/String;
Asciz	curried;
Asciz	()Lscala/Function1;;
Asciz	(Lscala/Function2;)Lscala/Function1;;
NameAndType	curried:(Lscala/Function2;)Lscala/Function1;
Method	scala/Function2$class.curried:(Lscala/Function2;)Lscala/Function1;
Asciz	curry;
NameAndType	curry:(Lscala/Function2;)Lscala/Function1;
Method	scala/Function2$class.curry:(Lscala/Function2;)Lscala/Function1;
Asciz	Deprecated;
Asciz	tupled;
NameAndType	tupled:(Lscala/Function2;)Lscala/Function1;
Method	scala/Function2$class.tupled:(Lscala/Function2;)Lscala/Function1;
Asciz	unapply;
Asciz	(Lscala/util/regexp/PointedHedgeExp$Node;)Lscala/Option;;
Asciz	java/lang/Object;
class	java/lang/Object
Asciz	equals;
Asciz	(Ljava/lang/Object;)Z;
NameAndType	equals:(Ljava/lang/Object;)Z
Method	java/lang/Object.equals:(Ljava/lang/Object;)Z
Asciz	scala/None$;
class	scala/None$
Asciz	MODULE$;
Asciz	Lscala/None$;;
NameAndType	MODULE$:Lscala/None$;
Field	scala/None$.MODULE$:Lscala/None$;
Asciz	scala/Some;
class	scala/Some
Asciz	scala/Tuple2;
class	scala/Tuple2
Asciz	scala/util/regexp/PointedHedgeExp$Node;
class	scala/util/regexp/PointedHedgeExp$Node
Asciz	label;
Asciz	()Ljava/lang/Object;;
NameAndType	label:()Ljava/lang/Object;
Method	scala/util/regexp/PointedHedgeExp$Node.label:()Ljava/lang/Object;
Asciz	r;
Asciz	()Lscala/util/regexp/Base$RegExp;;
NameAndType	r:()Lscala/util/regexp/Base$RegExp;
Method	scala/util/regexp/PointedHedgeExp$Node.r:()Lscala/util/regexp/Base$RegExp;
Asciz	<init>;
Asciz	(Ljava/lang/Object;Ljava/lang/Object;)V;
NameAndType	"<init>":(Ljava/lang/Object;Ljava/lang/Object;)V
Method	scala/Tuple2."<init>":(Ljava/lang/Object;Ljava/lang/Object;)V
Asciz	(Ljava/lang/Object;)V;
NameAndType	"<init>":(Ljava/lang/Object;)V
Method	scala/Some."<init>":(Ljava/lang/Object;)V
Asciz	this;
Asciz	Lscala/util/regexp/PointedHedgeExp$Node$;;
Asciz	x$0;
Asciz	Lscala/util/regexp/PointedHedgeExp$Node;;
Asciz	LocalVariableTable;
Asciz	apply;
Asciz	(Ljava/lang/Object;Lscala/util/regexp/Base$RegExp;)Lscala/util/regexp/PointedHedgeExp$Node;;
Asciz	scala/util/regexp/PointedHedgeExp$Node$;
class	scala/util/regexp/PointedHedgeExp$Node$
NameAndType	$outer:Lscala/util/regexp/PointedHedgeExp;
Field	scala/util/regexp/PointedHedgeExp$Node$.$outer:Lscala/util/regexp/PointedHedgeExp;
Asciz	(Lscala/util/regexp/PointedHedgeExp;Ljava/lang/Object;Lscala/util/regexp/Base$RegExp;)V;
NameAndType	"<init>":(Lscala/util/regexp/PointedHedgeExp;Ljava/lang/Object;Lscala/util/regexp/Base$RegExp;)V
Method	scala/util/regexp/PointedHedgeExp$Node."<init>":(Lscala/util/regexp/PointedHedgeExp;Ljava/lang/Object;Lscala/util/regexp/Base$RegExp;)V
Asciz	Ljava/lang/Object;;
Asciz	Lscala/util/regexp/Base$RegExp;;
Asciz	(Ljava/lang/Object;Ljava/lang/Object;)Ljava/lang/Object;;
Asciz	scala/util/regexp/Base$RegExp;
class	scala/util/regexp/Base$RegExp
NameAndType	apply:(Ljava/lang/Object;Lscala/util/regexp/Base$RegExp;)Lscala/util/regexp/PointedHedgeExp$Node;
Method	scala/util/regexp/PointedHedgeExp$Node$.apply:(Ljava/lang/Object;Lscala/util/regexp/Base$RegExp;)Lscala/util/regexp/PointedHedgeExp$Node;
Asciz	v1;
Asciz	v2;
Asciz	(Lscala/util/regexp/PointedHedgeExp;)V;
Asciz	java/lang/NullPointerException;
class	java/lang/NullPointerException
Asciz	()V;
NameAndType	"<init>":()V
Method	java/lang/NullPointerException."<init>":()V
Method	java/lang/Object."<init>":()V
Asciz	$init$;
Asciz	(Lscala/Function2;)V;
NameAndType	$init$:(Lscala/Function2;)V
Method	scala/Function2$class.$init$:(Lscala/Function2;)V
Asciz	InnerClasses;
Asciz	scala/util/regexp/Base;
class	scala/util/regexp/Base
Asciz	RegExp;
Asciz	scala/util/regexp/PointedHedgeExp;
class	scala/util/regexp/PointedHedgeExp
Asciz	Node;
Asciz	scala/Function2;
class	scala/Function2
Asciz	scala/ScalaObject;
class	scala/ScalaObject

{
public final scala.util.regexp.PointedHedgeExp $outer;
  Signature: Lscala/util/regexp/PointedHedgeExp;

public java.lang.String toString();
  Signature: ()Ljava/lang/String;
  Code:
   Stack=1, Locals=1, Args_size=1
	aload_0
	invokestatic	Method scala/Function2$class.toString:(Lscala/Function2;)Ljava/lang/String;
	areturn
  Labels:

public scala.Function1 curried();
  Signature: ()Lscala/Function1;
  Code:
   Stack=1, Locals=1, Args_size=1
	aload_0
	invokestatic	Method scala/Function2$class.curried:(Lscala/Function2;)Lscala/Function1;
	areturn
  Labels:

public scala.Function1 curry();
  Signature: ()Lscala/Function1;
  Code:
   Stack=1, Locals=1, Args_size=1
	aload_0
	invokestatic	Method scala/Function2$class.curry:(Lscala/Function2;)Lscala/Function1;
	areturn
  Labels:
  Deprecated: true

public scala.Function1 tupled();
  Signature: ()Lscala/Function1;
  Code:
   Stack=1, Locals=1, Args_size=1
	aload_0
	invokestatic	Method scala/Function2$class.tupled:(Lscala/Function2;)Lscala/Function1;
	areturn
  Labels:

public scala.Option unapply(scala.util.regexp.PointedHedgeExp$Node);
  Signature: (Lscala/util/regexp/PointedHedgeExp$Node;)Lscala/Option;
  Code:
   Stack=6, Locals=2, Args_size=2
	aload_1
	dup
	pop
	ifnull	l1 // getstatic
	aload_1
	aconst_null
	invokevirtual	Method java/lang/Object.equals:(Ljava/lang/Object;)Z
	ifeq	l2 // new
l1	getstatic	Field scala/None$.MODULE$:Lscala/None$;
	goto	l3 // areturn
l2	new	class scala/Some
	dup
	new	class scala/Tuple2
	dup
	aload_1
	invokevirtual	Method scala/util/regexp/PointedHedgeExp$Node.label:()Ljava/lang/Object;
	aload_1
	invokevirtual	Method scala/util/regexp/PointedHedgeExp$Node.r:()Lscala/util/regexp/Base$RegExp;
	invokespecial	Method scala/Tuple2."<init>":(Ljava/lang/Object;Ljava/lang/Object;)V
	invokespecial	Method scala/Some."<init>":(Ljava/lang/Object;)V
l3	areturn
  Labels:
   	l1 = 14 // getstatic
   	l2 = 20 // new
   	l3 = 42 // areturn
  LocalVariableTable: 
   Start  Length  Slot  Name   Signature
   0      43      0    this       Lscala/util/regexp/PointedHedgeExp$Node$;
   0      43      1    x$0       Lscala/util/regexp/PointedHedgeExp$Node;


public scala.util.regexp.PointedHedgeExp$Node apply(java.lang.Object, scala.util.regexp.Base$RegExp);
  Signature: (Ljava/lang/Object;Lscala/util/regexp/Base$RegExp;)Lscala/util/regexp/PointedHedgeExp$Node;
  Code:
   Stack=5, Locals=4, Args_size=3
	aload_0
	getfield	Field $outer:Lscala/util/regexp/PointedHedgeExp;
	astore_3
	new	class scala/util/regexp/PointedHedgeExp$Node
	dup
	aload_0
	getfield	Field $outer:Lscala/util/regexp/PointedHedgeExp;
	aload_1
	aload_2
	invokespecial	Method scala/util/regexp/PointedHedgeExp$Node."<init>":(Lscala/util/regexp/PointedHedgeExp;Ljava/lang/Object;Lscala/util/regexp/Base$RegExp;)V
	areturn
  Labels:
  LocalVariableTable: 
   Start  Length  Slot  Name   Signature
   0      19      0    this       Lscala/util/regexp/PointedHedgeExp$Node$;
   5      14      1    label       Ljava/lang/Object;
   5      14      2    r       Lscala/util/regexp/Base$RegExp;


public java.lang.Object apply(java.lang.Object, java.lang.Object);
  Signature: (Ljava/lang/Object;Ljava/lang/Object;)Ljava/lang/Object;
  Code:
   Stack=3, Locals=4, Args_size=3
	aload_0
	getfield	Field $outer:Lscala/util/regexp/PointedHedgeExp;
	astore_3
	aload_0
	aload_1
	aload_2
	checkcast	class scala/util/regexp/Base$RegExp
	invokevirtual	Method apply:(Ljava/lang/Object;Lscala/util/regexp/Base$RegExp;)Lscala/util/regexp/PointedHedgeExp$Node;
	areturn
  Labels:
  LocalVariableTable: 
   Start  Length  Slot  Name   Signature
   0      15      0    this       Lscala/util/regexp/PointedHedgeExp$Node$;
   5      10      1    v1       Ljava/lang/Object;
   5      10      2    v2       Ljava/lang/Object;


public scala.util.regexp.PointedHedgeExp$Node$(scala.util.regexp.PointedHedgeExp);
  Signature: (Lscala/util/regexp/PointedHedgeExp;)V
  Code:
   Stack=2, Locals=2, Args_size=2
	aload_1
	ifnonnull	l1 // aload_0
	new	class java/lang/NullPointerException
	dup
	invokespecial	Method java/lang/NullPointerException."<init>":()V
	athrow
l1	aload_0
	aload_1
	putfield	Field $outer:Lscala/util/regexp/PointedHedgeExp;
	aload_0
	invokespecial	Method java/lang/Object."<init>":()V
	aload_0
	invokestatic	Method scala/Function2$class.$init$:(Lscala/Function2;)V
	return
  Labels:
   	l1 = 12 // aload_0
  LocalVariableTable: 
   Start  Length  Slot  Name   Signature
   0      26      0    this       Lscala/util/regexp/PointedHedgeExp$Node$;
   0      26      1    $outer       Lscala/util/regexp/PointedHedgeExp;


}

