Compiled from "SyntaxError.scala"
public class scala.util.regexp.SyntaxError extends java.lang.RuntimeException implements scala.ScalaObject
  SourceFile: "SyntaxError.scala"
  ScalaSig: length = 0xDB
   05 00 25 06 08 01 02 FFFFFF84 FFFFFF80 FFFFFF80 FFFFFF80 00 09 02 0B 53
   79 6E 74 61 78 45 72 72 6F 72 0A 02 03 04 01 06
   72 65 67 65 78 70 0A 02 05 06 01 04 75 74 69 6C
   0A 01 07 01 05 73 63 61 6C 61 03 00 13 03 00 0A
   12 10 02 0B 10 0D 01 0C 0A 02 0D 0E 01 04 6C 61
   6E 67 0A 01 0F 01 04 6A 61 76 61 09 02 11 0C 02
   10 52 75 6E 74 69 6D 65 45 78 63 65 70 74 69 6F
   6E 10 02 13 14 0D 01 06 09 02 15 06 02 0B 53 63
   61 6C 61 4F 62 6A 65 63 74 08 08 17 00 FFFFFF82 FFFFFF80 FFFFFFA0
   FFFFFF80 04 18 01 01 65 10 02 19 1C 0E 02 13 1A 09 02
   1B 06 01 06 50 72 65 64 65 66 09 02 1D 1E 02 06
   53 74 72 69 6E 67 0A 02 1B 06 08 05 20 00 FFFFFF84 00
   21 01 06 3C 69 6E 69 74 3E 14 02 22 24 10 02 23
   00 0D 01 02 08 05 17 1F FFFFFFC0 00 18 
  minor version: 0
  major version: 49
  Constant pool:
const #1 = Asciz	SourceFile;
const #2 = Asciz	SyntaxError.scala;
const #3 = Asciz	<init>;
const #4 = Asciz	(Ljava/lang/String;)V;
const #5 = Asciz	Code;
const #6 = Asciz	LineNumberTable;
const #7 = Asciz	java/lang/RuntimeException;
const #8 = class	#7;	//  java/lang/RuntimeException
const #9 = NameAndType	#3:#4;//  "<init>":(Ljava/lang/String;)V
const #10 = Method	#8.#9;	//  java/lang/RuntimeException."<init>":(Ljava/lang/String;)V
const #11 = Asciz	this;
const #12 = Asciz	Lscala/util/regexp/SyntaxError;;
const #13 = Asciz	e;
const #14 = Asciz	Ljava/lang/String;;
const #15 = Asciz	LocalVariableTable;
const #16 = Asciz	ScalaSig;
const #17 = Asciz	scala/util/regexp/SyntaxError;
const #18 = class	#17;	//  scala/util/regexp/SyntaxError
const #19 = Asciz	scala/ScalaObject;
const #20 = class	#19;	//  scala/ScalaObject

{
public scala.util.regexp.SyntaxError(java.lang.String);
  Code:
   Stack=2, Locals=2, Args_size=2
   0:	aload_0
   1:	aload_1
   2:	invokespecial	#10; //Method java/lang/RuntimeException."<init>":(Ljava/lang/String;)V
   5:	return
  LineNumberTable: 
   line 20: 0

  LocalVariableTable: 
   Start  Length  Slot  Name   Signature
   0      6      0    this       Lscala/util/regexp/SyntaxError;
   0      6      1    e       Ljava/lang/String;


}

