Compiled from "WordExp.scala"
public final class scala.util.regexp.WordExp$Letter$ extends java.lang.Object implements scala.Function1,scala.ScalaObject
  SourceFile: "WordExp.scala"
  Scala: length = 0x
   
  InnerClass: 
   public abstract Label=class scala/util/regexp/WordExp$Label of class scala/util/regexp/WordExp
   public Letter=class scala/util/regexp/WordExp$Letter of class scala/util/regexp/WordExp
  minor version: 0
  major version: 49
  Constant pool:
Asciz	SourceFile;
Asciz	WordExp.scala;
Asciz	Scala;
Asciz	$outer;
Asciz	Lscala/util/regexp/WordExp;;
Asciz	toString;
Asciz	()Ljava/lang/String;;
Asciz	Code;
Asciz	LineNumberTable;
Asciz	scala/Function1$class;
class	scala/Function1$class
Asciz	(Lscala/Function1;)Ljava/lang/String;;
NameAndType	toString:(Lscala/Function1;)Ljava/lang/String;
Method	scala/Function1$class.toString:(Lscala/Function1;)Ljava/lang/String;
Asciz	compose;
Asciz	(Lscala/Function1;)Lscala/Function1;;
Asciz	(Lscala/Function1;Lscala/Function1;)Lscala/Function1;;
NameAndType	compose:(Lscala/Function1;Lscala/Function1;)Lscala/Function1;
Method	scala/Function1$class.compose:(Lscala/Function1;Lscala/Function1;)Lscala/Function1;
Asciz	this;
Asciz	Lscala/util/regexp/WordExp$Letter$;;
Asciz	g;
Asciz	Lscala/Function1;;
Asciz	LocalVariableTable;
Asciz	andThen;
NameAndType	andThen:(Lscala/Function1;Lscala/Function1;)Lscala/Function1;
Method	scala/Function1$class.andThen:(Lscala/Function1;Lscala/Function1;)Lscala/Function1;
Asciz	unapply;
Asciz	(Lscala/util/regexp/WordExp$Letter;)Lscala/Option;;
Asciz	java/lang/Object;
class	java/lang/Object
Asciz	equals;
Asciz	(Ljava/lang/Object;)Z;
NameAndType	equals:(Ljava/lang/Object;)Z
Method	java/lang/Object.equals:(Ljava/lang/Object;)Z
Asciz	scala/None$;
class	scala/None$
Asciz	MODULE$;
Asciz	Lscala/None$;;
NameAndType	MODULE$:Lscala/None$;
Field	scala/None$.MODULE$:Lscala/None$;
Asciz	scala/Some;
class	scala/Some
Asciz	scala/util/regexp/WordExp$Letter;
class	scala/util/regexp/WordExp$Letter
Asciz	a;
Asciz	()Lscala/util/regexp/WordExp$Label;;
NameAndType	a:()Lscala/util/regexp/WordExp$Label;
Method	scala/util/regexp/WordExp$Letter.a:()Lscala/util/regexp/WordExp$Label;
Asciz	<init>;
Asciz	(Ljava/lang/Object;)V;
NameAndType	"<init>":(Ljava/lang/Object;)V
Method	scala/Some."<init>":(Ljava/lang/Object;)V
Asciz	x$0;
Asciz	Lscala/util/regexp/WordExp$Letter;;
Asciz	apply;
Asciz	(Lscala/util/regexp/WordExp$Label;)Lscala/util/regexp/WordExp$Letter;;
Asciz	scala/util/regexp/WordExp$Letter$;
class	scala/util/regexp/WordExp$Letter$
NameAndType	$outer:Lscala/util/regexp/WordExp;
Field	scala/util/regexp/WordExp$Letter$.$outer:Lscala/util/regexp/WordExp;
Asciz	(Lscala/util/regexp/WordExp;Lscala/util/regexp/WordExp$Label;)V;
NameAndType	"<init>":(Lscala/util/regexp/WordExp;Lscala/util/regexp/WordExp$Label;)V
Method	scala/util/regexp/WordExp$Letter."<init>":(Lscala/util/regexp/WordExp;Lscala/util/regexp/WordExp$Label;)V
Asciz	Lscala/util/regexp/WordExp$Label;;
Asciz	(Ljava/lang/Object;)Ljava/lang/Object;;
Asciz	scala/util/regexp/WordExp$Label;
class	scala/util/regexp/WordExp$Label
NameAndType	apply:(Lscala/util/regexp/WordExp$Label;)Lscala/util/regexp/WordExp$Letter;
Method	scala/util/regexp/WordExp$Letter$.apply:(Lscala/util/regexp/WordExp$Label;)Lscala/util/regexp/WordExp$Letter;
Asciz	v1;
Asciz	Ljava/lang/Object;;
Asciz	(Lscala/util/regexp/WordExp;)V;
Asciz	java/lang/NullPointerException;
class	java/lang/NullPointerException
Asciz	()V;
NameAndType	"<init>":()V
Method	java/lang/NullPointerException."<init>":()V
Method	java/lang/Object."<init>":()V
Asciz	$init$;
Asciz	(Lscala/Function1;)V;
NameAndType	$init$:(Lscala/Function1;)V
Method	scala/Function1$class.$init$:(Lscala/Function1;)V
Asciz	InnerClasses;
Asciz	scala/util/regexp/WordExp;
class	scala/util/regexp/WordExp
Asciz	Label;
Asciz	Letter;
Asciz	scala/Function1;
class	scala/Function1
Asciz	scala/ScalaObject;
class	scala/ScalaObject

{
public final scala.util.regexp.WordExp $outer;
  Signature: Lscala/util/regexp/WordExp;

public java.lang.String toString();
  Signature: ()Ljava/lang/String;
  Code:
   Stack=1, Locals=1, Args_size=1
	aload_0
	invokestatic	Method scala/Function1$class.toString:(Lscala/Function1;)Ljava/lang/String;
	areturn
  Labels:

public scala.Function1 compose(scala.Function1);
  Signature: (Lscala/Function1;)Lscala/Function1;
  Code:
   Stack=2, Locals=2, Args_size=2
	aload_0
	aload_1
	invokestatic	Method scala/Function1$class.compose:(Lscala/Function1;Lscala/Function1;)Lscala/Function1;
	areturn
  Labels:
  LocalVariableTable: 
   Start  Length  Slot  Name   Signature
   0      6      0    this       Lscala/util/regexp/WordExp$Letter$;
   0      6      1    g       Lscala/Function1;


public scala.Function1 andThen(scala.Function1);
  Signature: (Lscala/Function1;)Lscala/Function1;
  Code:
   Stack=2, Locals=2, Args_size=2
	aload_0
	aload_1
	invokestatic	Method scala/Function1$class.andThen:(Lscala/Function1;Lscala/Function1;)Lscala/Function1;
	areturn
  Labels:
  LocalVariableTable: 
   Start  Length  Slot  Name   Signature
   0      6      0    this       Lscala/util/regexp/WordExp$Letter$;
   0      6      1    g       Lscala/Function1;


public scala.Option unapply(scala.util.regexp.WordExp$Letter);
  Signature: (Lscala/util/regexp/WordExp$Letter;)Lscala/Option;
  Code:
   Stack=3, Locals=2, Args_size=2
	aload_1
	dup
	pop
	ifnull	l1 // getstatic
	aload_1
	aconst_null
	invokevirtual	Method java/lang/Object.equals:(Ljava/lang/Object;)Z
	ifeq	l2 // new
l1	getstatic	Field scala/None$.MODULE$:Lscala/None$;
	goto	l3 // areturn
l2	new	class scala/Some
	dup
	aload_1
	invokevirtual	Method scala/util/regexp/WordExp$Letter.a:()Lscala/util/regexp/WordExp$Label;
	invokespecial	Method scala/Some."<init>":(Ljava/lang/Object;)V
l3	areturn
  Labels:
   	l1 = 14 // getstatic
   	l2 = 20 // new
   	l3 = 31 // areturn
  LocalVariableTable: 
   Start  Length  Slot  Name   Signature
   0      32      0    this       Lscala/util/regexp/WordExp$Letter$;
   0      32      1    x$0       Lscala/util/regexp/WordExp$Letter;


public scala.util.regexp.WordExp$Letter apply(scala.util.regexp.WordExp$Label);
  Signature: (Lscala/util/regexp/WordExp$Label;)Lscala/util/regexp/WordExp$Letter;
  Code:
   Stack=4, Locals=3, Args_size=2
	aload_0
	getfield	Field $outer:Lscala/util/regexp/WordExp;
	astore_2
	new	class scala/util/regexp/WordExp$Letter
	dup
	aload_0
	getfield	Field $outer:Lscala/util/regexp/WordExp;
	aload_1
	invokespecial	Method scala/util/regexp/WordExp$Letter."<init>":(Lscala/util/regexp/WordExp;Lscala/util/regexp/WordExp$Label;)V
	areturn
  Labels:
  LocalVariableTable: 
   Start  Length  Slot  Name   Signature
   0      18      0    this       Lscala/util/regexp/WordExp$Letter$;
   5      13      1    a       Lscala/util/regexp/WordExp$Label;


public java.lang.Object apply(java.lang.Object);
  Signature: (Ljava/lang/Object;)Ljava/lang/Object;
  Code:
   Stack=2, Locals=3, Args_size=2
	aload_0
	getfield	Field $outer:Lscala/util/regexp/WordExp;
	astore_2
	aload_0
	aload_1
	checkcast	class scala/util/regexp/WordExp$Label
	invokevirtual	Method apply:(Lscala/util/regexp/WordExp$Label;)Lscala/util/regexp/WordExp$Letter;
	areturn
  Labels:
  LocalVariableTable: 
   Start  Length  Slot  Name   Signature
   0      14      0    this       Lscala/util/regexp/WordExp$Letter$;
   5      9      1    v1       Ljava/lang/Object;


public scala.util.regexp.WordExp$Letter$(scala.util.regexp.WordExp);
  Signature: (Lscala/util/regexp/WordExp;)V
  Code:
   Stack=2, Locals=2, Args_size=2
	aload_1
	ifnonnull	l1 // aload_0
	new	class java/lang/NullPointerException
	dup
	invokespecial	Method java/lang/NullPointerException."<init>":()V
	athrow
l1	aload_0
	aload_1
	putfield	Field $outer:Lscala/util/regexp/WordExp;
	aload_0
	invokespecial	Method java/lang/Object."<init>":()V
	aload_0
	invokestatic	Method scala/Function1$class.$init$:(Lscala/Function1;)V
	return
  Labels:
   	l1 = 12 // aload_0
  LocalVariableTable: 
   Start  Length  Slot  Name   Signature
   0      26      0    this       Lscala/util/regexp/WordExp$Letter$;
   0      26      1    $outer       Lscala/util/regexp/WordExp;


}

