Compiled from "WordExp.scala"
public final class scala.util.regexp.WordExp$Wildcard$ extends java.lang.Object implements scala.Function0,scala.ScalaObject
  SourceFile: "WordExp.scala"
  Scala: length = 0x
   
  InnerClass: 
   public #52= #37 of #51; //Wildcard=class scala/util/regexp/WordExp$Wildcard of class scala/util/regexp/WordExp
  minor version: 0
  major version: 49
  Constant pool:
const #1 = Asciz	SourceFile;
const #2 = Asciz	WordExp.scala;
const #3 = Asciz	Scala;
const #4 = Asciz	$outer;
const #5 = Asciz	Lscala/util/regexp/WordExp;;
const #6 = Asciz	<init>;
const #7 = Asciz	(Lscala/util/regexp/WordExp;)V;
const #8 = Asciz	Code;
const #9 = Asciz	LineNumberTable;
const #10 = Asciz	java/lang/NullPointerException;
const #11 = class	#10;	//  java/lang/NullPointerException
const #12 = Asciz	()V;
const #13 = NameAndType	#6:#12;//  "<init>":()V
const #14 = Method	#11.#13;	//  java/lang/NullPointerException."<init>":()V
const #15 = Asciz	scala/util/regexp/WordExp$Wildcard$;
const #16 = class	#15;	//  scala/util/regexp/WordExp$Wildcard$
const #17 = NameAndType	#4:#5;//  $outer:Lscala/util/regexp/WordExp;
const #18 = Field	#16.#17;	//  scala/util/regexp/WordExp$Wildcard$.$outer:Lscala/util/regexp/WordExp;
const #19 = Asciz	java/lang/Object;
const #20 = class	#19;	//  java/lang/Object
const #21 = Method	#20.#13;	//  java/lang/Object."<init>":()V
const #22 = Asciz	scala/Function0$class;
const #23 = class	#22;	//  scala/Function0$class
const #24 = Asciz	$init$;
const #25 = Asciz	(Lscala/Function0;)V;
const #26 = NameAndType	#24:#25;//  $init$:(Lscala/Function0;)V
const #27 = Method	#23.#26;	//  scala/Function0$class.$init$:(Lscala/Function0;)V
const #28 = Asciz	this;
const #29 = Asciz	Lscala/util/regexp/WordExp$Wildcard$;;
const #30 = Asciz	LocalVariableTable;
const #31 = Asciz	apply;
const #32 = Asciz	()Ljava/lang/Object;;
const #33 = Asciz	()Lscala/util/regexp/WordExp$Wildcard;;
const #34 = NameAndType	#31:#33;//  apply:()Lscala/util/regexp/WordExp$Wildcard;
const #35 = Method	#16.#34;	//  scala/util/regexp/WordExp$Wildcard$.apply:()Lscala/util/regexp/WordExp$Wildcard;
const #36 = Asciz	scala/util/regexp/WordExp$Wildcard;
const #37 = class	#36;	//  scala/util/regexp/WordExp$Wildcard
const #38 = NameAndType	#6:#7;//  "<init>":(Lscala/util/regexp/WordExp;)V
const #39 = Method	#37.#38;	//  scala/util/regexp/WordExp$Wildcard."<init>":(Lscala/util/regexp/WordExp;)V
const #40 = Asciz	unapply;
const #41 = Asciz	(Lscala/util/regexp/WordExp$Wildcard;)Z;
const #42 = Asciz	x$0;
const #43 = Asciz	Lscala/util/regexp/WordExp$Wildcard;;
const #44 = Asciz	toString;
const #45 = Asciz	()Ljava/lang/String;;
const #46 = Asciz	(Lscala/Function0;)Ljava/lang/String;;
const #47 = NameAndType	#44:#46;//  toString:(Lscala/Function0;)Ljava/lang/String;
const #48 = Method	#23.#47;	//  scala/Function0$class.toString:(Lscala/Function0;)Ljava/lang/String;
const #49 = Asciz	InnerClasses;
const #50 = Asciz	scala/util/regexp/WordExp;
const #51 = class	#50;	//  scala/util/regexp/WordExp
const #52 = Asciz	Wildcard;
const #53 = Asciz	scala/Function0;
const #54 = class	#53;	//  scala/Function0
const #55 = Asciz	scala/ScalaObject;
const #56 = class	#55;	//  scala/ScalaObject

{
public scala.util.regexp.WordExp$Wildcard$(scala.util.regexp.WordExp);
  Code:
   Stack=2, Locals=2, Args_size=2
   0:	aload_1
   1:	ifnonnull	12
   4:	new	#11; //class java/lang/NullPointerException
   7:	dup
   8:	invokespecial	#14; //Method java/lang/NullPointerException."<init>":()V
   11:	athrow
   12:	aload_0
   13:	aload_1
   14:	putfield	#18; //Field $outer:Lscala/util/regexp/WordExp;
   17:	aload_0
   18:	invokespecial	#21; //Method java/lang/Object."<init>":()V
   21:	aload_0
   22:	invokestatic	#27; //Method scala/Function0$class.$init$:(Lscala/Function0;)V
   25:	return
  LineNumberTable: 
   line 52: 0

  LocalVariableTable: 
   Start  Length  Slot  Name   Signature
   0      26      0    this       Lscala/util/regexp/WordExp$Wildcard$;
   0      26      1    $outer       Lscala/util/regexp/WordExp;


public java.lang.Object apply();
  Code:
   Stack=1, Locals=2, Args_size=1
   0:	aload_0
   1:	getfield	#18; //Field $outer:Lscala/util/regexp/WordExp;
   4:	astore_1
   5:	aload_0
   6:	invokevirtual	#35; //Method apply:()Lscala/util/regexp/WordExp$Wildcard;
   9:	areturn
  LineNumberTable: 
   line 52: 0

  LocalVariableTable: 
   Start  Length  Slot  Name   Signature
   0      10      0    this       Lscala/util/regexp/WordExp$Wildcard$;


public scala.util.regexp.WordExp$Wildcard apply();
  Code:
   Stack=3, Locals=2, Args_size=1
   0:	aload_0
   1:	getfield	#18; //Field $outer:Lscala/util/regexp/WordExp;
   4:	astore_1
   5:	new	#37; //class scala/util/regexp/WordExp$Wildcard
   8:	dup
   9:	aload_0
   10:	getfield	#18; //Field $outer:Lscala/util/regexp/WordExp;
   13:	invokespecial	#39; //Method scala/util/regexp/WordExp$Wildcard."<init>":(Lscala/util/regexp/WordExp;)V
   16:	areturn
  LineNumberTable: 
   line 52: 0

  LocalVariableTable: 
   Start  Length  Slot  Name   Signature
   0      17      0    this       Lscala/util/regexp/WordExp$Wildcard$;


public boolean unapply(scala.util.regexp.WordExp$Wildcard);
  Code:
   Stack=1, Locals=2, Args_size=2
   0:	iconst_1
   1:	ireturn
  LineNumberTable: 
   line 64: 0

  LocalVariableTable: 
   Start  Length  Slot  Name   Signature
   0      2      0    this       Lscala/util/regexp/WordExp$Wildcard$;
   0      2      1    x$0       Lscala/util/regexp/WordExp$Wildcard;


public java.lang.String toString();
  Code:
   Stack=1, Locals=1, Args_size=1
   0:	aload_0
   1:	invokestatic	#48; //Method scala/Function0$class.toString:(Lscala/Function0;)Ljava/lang/String;
   4:	areturn
  LineNumberTable: 
   line 52: 0


}

