Compiled from "WordExp.scala"
public class scala.util.regexp.WordExp$Wildcard extends scala.util.regexp.Base$RegExp implements scala.ScalaObject,scala.Product,java.io.Serializable
  SourceFile: "WordExp.scala"
  Scala: length = 0x
   
  InnerClass: 
   public abstract RegExp=class scala/util/regexp/Base$RegExp of class scala/util/regexp/Base
   public Wildcard=class scala/util/regexp/WordExp$Wildcard of class scala/util/regexp/WordExp
  minor version: 0
  major version: 49
  Constant pool:
Asciz	SourceFile;
Asciz	WordExp.scala;
Asciz	bitmap$0;
Asciz	I;
Asciz	$outer;
Asciz	Lscala/util/regexp/WordExp;;
Asciz	pos;
Asciz	isNullable;
Asciz	Z;
Asciz	<init>;
Asciz	(Lscala/util/regexp/WordExp;)V;
Asciz	Code;
Asciz	LineNumberTable;
Asciz	java/lang/NullPointerException;
class	java/lang/NullPointerException
Asciz	()V;
NameAndType	"<init>":()V
Method	java/lang/NullPointerException."<init>":()V
Asciz	scala/util/regexp/WordExp$Wildcard;
class	scala/util/regexp/WordExp$Wildcard
NameAndType	$outer:Lscala/util/regexp/WordExp;
Field	scala/util/regexp/WordExp$Wildcard.$outer:Lscala/util/regexp/WordExp;
Asciz	scala/util/regexp/Base$RegExp;
class	scala/util/regexp/Base$RegExp
Asciz	(Lscala/util/regexp/Base;)V;
NameAndType	"<init>":(Lscala/util/regexp/Base;)V
Method	scala/util/regexp/Base$RegExp."<init>":(Lscala/util/regexp/Base;)V
Asciz	scala/Product$class;
class	scala/Product$class
Asciz	$init$;
Asciz	(Lscala/Product;)V;
NameAndType	$init$:(Lscala/Product;)V
Method	scala/Product$class.$init$:(Lscala/Product;)V
NameAndType	pos:I
Field	scala/util/regexp/WordExp$Wildcard.pos:I
Asciz	this;
Asciz	Lscala/util/regexp/WordExp$Wildcard;;
Asciz	LocalVariableTable;
Asciz	scala$util$regexp$WordExp$Wildcard$$$outer;
Asciz	()Lscala/util/regexp/WordExp;;
Asciz	canEqual;
Asciz	(Ljava/lang/Object;)Z;
Asciz	productElement;
Asciz	(I)Ljava/lang/Object;;
Asciz	java/lang/IndexOutOfBoundsException;
class	java/lang/IndexOutOfBoundsException
Asciz	scala/runtime/BoxesRunTime;
class	scala/runtime/BoxesRunTime
Asciz	boxToInteger;
Asciz	(I)Ljava/lang/Integer;;
NameAndType	boxToInteger:(I)Ljava/lang/Integer;
Method	scala/runtime/BoxesRunTime.boxToInteger:(I)Ljava/lang/Integer;
Asciz	java/lang/Object;
class	java/lang/Object
Asciz	toString;
Asciz	()Ljava/lang/String;;
NameAndType	toString:()Ljava/lang/String;
Method	java/lang/Object.toString:()Ljava/lang/String;
Asciz	(Ljava/lang/String;)V;
NameAndType	"<init>":(Ljava/lang/String;)V
Method	java/lang/IndexOutOfBoundsException."<init>":(Ljava/lang/String;)V
Asciz	scala/MatchError;
class	scala/MatchError
Method	scala/MatchError."<init>":(Ljava/lang/String;)V
Asciz	productArity;
Asciz	()I;
Asciz	productPrefix;
Asciz	Wildcard;
String	Wildcard
Asciz	equals;
NameAndType	scala$util$regexp$WordExp$Wildcard$$$outer:()Lscala/util/regexp/WordExp;
Method	scala/util/regexp/WordExp$Wildcard.scala$util$regexp$WordExp$Wildcard$$$outer:()Lscala/util/regexp/WordExp;
Asciz	scala/Equals;
class	scala/Equals
NameAndType	canEqual:(Ljava/lang/Object;)Z
InterfaceMethod	scala/Equals.canEqual:(Ljava/lang/Object;)Z
Asciz	scala/runtime/ScalaRunTime$;
class	scala/runtime/ScalaRunTime$
Asciz	MODULE$;
Asciz	Lscala/runtime/ScalaRunTime$;;
NameAndType	MODULE$:Lscala/runtime/ScalaRunTime$;
Field	scala/runtime/ScalaRunTime$.MODULE$:Lscala/runtime/ScalaRunTime$;
Asciz	_toString;
Asciz	(Lscala/Product;)Ljava/lang/String;;
NameAndType	_toString:(Lscala/Product;)Ljava/lang/String;
Method	scala/runtime/ScalaRunTime$._toString:(Lscala/Product;)Ljava/lang/String;
Asciz	hashCode;
Asciz	_hashCode;
Asciz	(Lscala/Product;)I;
NameAndType	_hashCode:(Lscala/Product;)I
Method	scala/runtime/ScalaRunTime$._hashCode:(Lscala/Product;)I
Asciz	pos_$eq;
Asciz	(I)V;
Asciz	()Z;
NameAndType	bitmap$0:I
Field	scala/util/regexp/WordExp$Wildcard.bitmap$0:I
NameAndType	isNullable:Z
Field	scala/util/regexp/WordExp$Wildcard.isNullable:Z
Asciz	productElements;
Asciz	()Lscala/collection/Iterator;;
Asciz	(Lscala/Product;)Lscala/collection/Iterator;;
NameAndType	productElements:(Lscala/Product;)Lscala/collection/Iterator;
Method	scala/Product$class.productElements:(Lscala/Product;)Lscala/collection/Iterator;
Asciz	Deprecated;
Asciz	productIterator;
NameAndType	productIterator:(Lscala/Product;)Lscala/collection/Iterator;
Method	scala/Product$class.productIterator:(Lscala/Product;)Lscala/collection/Iterator;
Asciz	Scala;
Asciz	InnerClasses;
Asciz	scala/util/regexp/Base;
class	scala/util/regexp/Base
Asciz	RegExp;
Asciz	scala/util/regexp/WordExp;
class	scala/util/regexp/WordExp
Asciz	scala/ScalaObject;
class	scala/ScalaObject
Asciz	scala/Product;
class	scala/Product
Asciz	java/io/Serializable;
class	java/io/Serializable

{
public volatile int bitmap$0;
  Signature: I

public final scala.util.regexp.WordExp $outer;
  Signature: Lscala/util/regexp/WordExp;

private int pos;
  Signature: I

private final boolean isNullable;
  Signature: Z

public scala.util.regexp.WordExp$Wildcard(scala.util.regexp.WordExp);
  Signature: (Lscala/util/regexp/WordExp;)V
  Code:
   Stack=2, Locals=2, Args_size=2
	aload_1
	ifnonnull	l1 // aload_0
	new	class java/lang/NullPointerException
	dup
	invokespecial	Method java/lang/NullPointerException."<init>":()V
	athrow
l1	aload_0
	aload_1
	putfield	Field $outer:Lscala/util/regexp/WordExp;
	aload_0
	aload_1
	invokespecial	Method scala/util/regexp/Base$RegExp."<init>":(Lscala/util/regexp/Base;)V
	aload_0
	invokestatic	Method scala/Product$class.$init$:(Lscala/Product;)V
	aload_0
	iconst_m1
	putfield	Field pos:I
	return
  Labels:
   	l1 = 12 // aload_0
  LocalVariableTable: 
   Start  Length  Slot  Name   Signature
   0      32      0    this       Lscala/util/regexp/WordExp$Wildcard;
   0      32      1    $outer       Lscala/util/regexp/WordExp;


public scala.util.regexp.WordExp scala$util$regexp$WordExp$Wildcard$$$outer();
  Signature: ()Lscala/util/regexp/WordExp;
  Code:
   Stack=1, Locals=1, Args_size=1
	aload_0
	getfield	Field $outer:Lscala/util/regexp/WordExp;
	areturn
  Labels:

public boolean canEqual(java.lang.Object);
  Signature: (Ljava/lang/Object;)Z
  Code:
   Stack=1, Locals=2, Args_size=2
	aload_1
	instanceof	class scala/util/regexp/WordExp$Wildcard
	ireturn
  Labels:

public java.lang.Object productElement(int);
  Signature: (I)Ljava/lang/Object;
  Code:
   Stack=3, Locals=2, Args_size=2
	iconst_1
	ifeq	l1 // new
	new	class java/lang/IndexOutOfBoundsException
	dup
	iload_1
	invokestatic	Method scala/runtime/BoxesRunTime.boxToInteger:(I)Ljava/lang/Integer;
	invokevirtual	Method java/lang/Object.toString:()Ljava/lang/String;
	invokespecial	Method java/lang/IndexOutOfBoundsException."<init>":(Ljava/lang/String;)V
	athrow
l1	new	class scala/MatchError
	dup
	iload_1
	invokestatic	Method scala/runtime/BoxesRunTime.boxToInteger:(I)Ljava/lang/Integer;
	invokevirtual	Method java/lang/Object.toString:()Ljava/lang/String;
	invokespecial	Method scala/MatchError."<init>":(Ljava/lang/String;)V
	athrow
  Labels:
   	l1 = 19 // new

public int productArity();
  Signature: ()I
  Code:
   Stack=1, Locals=1, Args_size=1
	iconst_0
	ireturn
  Labels:

public java.lang.String productPrefix();
  Signature: ()Ljava/lang/String;
  Code:
   Stack=1, Locals=1, Args_size=1
	ldc	String Wildcard
	areturn
  Labels:

public boolean equals(java.lang.Object);
  Signature: (Ljava/lang/Object;)Z
  Code:
   Stack=3, Locals=2, Args_size=2
	aload_0
	aload_1
	if_acmpeq	l1 // iconst_1
	aload_1
	instanceof	class scala/util/regexp/WordExp$Wildcard
	ifeq	l2 // iconst_1
	aload_1
	checkcast	class scala/util/regexp/WordExp$Wildcard
	invokevirtual	Method scala$util$regexp$WordExp$Wildcard$$$outer:()Lscala/util/regexp/WordExp;
	aload_0
	invokevirtual	Method scala$util$regexp$WordExp$Wildcard$$$outer:()Lscala/util/regexp/WordExp;
	if_acmpne	l2 // iconst_1
	iconst_1
	ifeq	l3 // new
	aload_1
	checkcast	class scala/util/regexp/WordExp$Wildcard
	aload_0
	invokeinterface	InterfaceMethod scala/Equals.canEqual:(Ljava/lang/Object;)Z
	goto	l4 // ifeq
l3	new	class scala/MatchError
	dup
	aload_1
	invokevirtual	Method java/lang/Object.toString:()Ljava/lang/String;
	invokespecial	Method scala/MatchError."<init>":(Ljava/lang/String;)V
	athrow
l2	iconst_1
	ifeq	l5 // new
	iconst_0
l4	ifeq	l6 // iconst_0
l1	iconst_1
	goto	l7 // ireturn
l6	iconst_0
l7	ireturn
l5	new	class scala/MatchError
	dup
	aload_1
	invokevirtual	Method java/lang/Object.toString:()Ljava/lang/String;
	invokespecial	Method scala/MatchError."<init>":(Ljava/lang/String;)V
	athrow
  Labels:
   	l3 = 43 // new
   	l2 = 55 // iconst_1
   	l4 = 60 // ifeq
   	l1 = 63 // iconst_1
   	l6 = 67 // iconst_0
   	l7 = 68 // ireturn
   	l5 = 69 // new

public java.lang.String toString();
  Signature: ()Ljava/lang/String;
  Code:
   Stack=2, Locals=1, Args_size=1
	getstatic	Field scala/runtime/ScalaRunTime$.MODULE$:Lscala/runtime/ScalaRunTime$;
	aload_0
	invokevirtual	Method scala/runtime/ScalaRunTime$._toString:(Lscala/Product;)Ljava/lang/String;
	areturn
  Labels:

public int hashCode();
  Signature: ()I
  Code:
   Stack=2, Locals=1, Args_size=1
	getstatic	Field scala/runtime/ScalaRunTime$.MODULE$:Lscala/runtime/ScalaRunTime$;
	aload_0
	invokevirtual	Method scala/runtime/ScalaRunTime$._hashCode:(Lscala/Product;)I
	ireturn
  Labels:

public void pos_$eq(int);
  Signature: (I)V
  Code:
   Stack=2, Locals=2, Args_size=2
	aload_0
	iload_1
	putfield	Field pos:I
	return
  Labels:

public int pos();
  Signature: ()I
  Code:
   Stack=1, Locals=1, Args_size=1
	aload_0
	getfield	Field pos:I
	ireturn
  Labels:

public final boolean isNullable();
  Signature: ()Z
  Code:
   Stack=3, Locals=1, Args_size=1
	aload_0
	getfield	Field bitmap$0:I
	iconst_1
	iand
	iconst_0
	if_icmpne	l1 // aload_0
	aload_0
	dup
	pop
	monitorenter
	aload_0
	getfield	Field bitmap$0:I
	iconst_1
	iand
	iconst_0
	if_icmpne	l2 // aload_0
	aload_0
	iconst_0
	putfield	Field isNullable:Z
	aload_0
	aload_0
	getfield	Field bitmap$0:I
	iconst_1
	ior
	putfield	Field bitmap$0:I
l2	aload_0
	monitorexit
l1	aload_0
	getfield	Field isNullable:Z
	ireturn
	aload_0
	monitorexit
	athrow
  Labels:
   	l2 = 39 // aload_0
   	l1 = 41 // aload_0
  Exception table:
   from   to  target type
    14    41    46   any

public scala.collection.Iterator productElements();
  Signature: ()Lscala/collection/Iterator;
  Code:
   Stack=1, Locals=1, Args_size=1
	aload_0
	invokestatic	Method scala/Product$class.productElements:(Lscala/Product;)Lscala/collection/Iterator;
	areturn
  Labels:
  Deprecated: true

public scala.collection.Iterator productIterator();
  Signature: ()Lscala/collection/Iterator;
  Code:
   Stack=1, Locals=1, Args_size=1
	aload_0
	invokestatic	Method scala/Product$class.productIterator:(Lscala/Product;)Lscala/collection/Iterator;
	areturn
  Labels:

}

