Compiled from "WordExp.scala"
public abstract class scala.util.regexp.WordExp$Label extends java.lang.Object implements scala.ScalaObject
  SourceFile: "WordExp.scala"
  Scala: length = 0x
   
  InnerClass: 
   public abstract #30= #15 of #29; //Label=class scala/util/regexp/WordExp$Label of class scala/util/regexp/WordExp
  minor version: 0
  major version: 49
  Constant pool:
const #1 = Asciz	SourceFile;
const #2 = Asciz	WordExp.scala;
const #3 = Asciz	$outer;
const #4 = Asciz	Lscala/util/regexp/WordExp;;
const #5 = Asciz	<init>;
const #6 = Asciz	(Lscala/util/regexp/WordExp;)V;
const #7 = Asciz	Code;
const #8 = Asciz	LineNumberTable;
const #9 = Asciz	java/lang/NullPointerException;
const #10 = class	#9;	//  java/lang/NullPointerException
const #11 = Asciz	()V;
const #12 = NameAndType	#5:#11;//  "<init>":()V
const #13 = Method	#10.#12;	//  java/lang/NullPointerException."<init>":()V
const #14 = Asciz	scala/util/regexp/WordExp$Label;
const #15 = class	#14;	//  scala/util/regexp/WordExp$Label
const #16 = NameAndType	#3:#4;//  $outer:Lscala/util/regexp/WordExp;
const #17 = Field	#15.#16;	//  scala/util/regexp/WordExp$Label.$outer:Lscala/util/regexp/WordExp;
const #18 = Asciz	java/lang/Object;
const #19 = class	#18;	//  java/lang/Object
const #20 = Method	#19.#12;	//  java/lang/Object."<init>":()V
const #21 = Asciz	this;
const #22 = Asciz	Lscala/util/regexp/WordExp$Label;;
const #23 = Asciz	LocalVariableTable;
const #24 = Asciz	scala$util$regexp$WordExp$Label$$$outer;
const #25 = Asciz	()Lscala/util/regexp/WordExp;;
const #26 = Asciz	Scala;
const #27 = Asciz	InnerClasses;
const #28 = Asciz	scala/util/regexp/WordExp;
const #29 = class	#28;	//  scala/util/regexp/WordExp
const #30 = Asciz	Label;
const #31 = Asciz	scala/ScalaObject;
const #32 = class	#31;	//  scala/ScalaObject

{
public final scala.util.regexp.WordExp $outer;

public scala.util.regexp.WordExp$Label(scala.util.regexp.WordExp);
  Code:
   Stack=2, Locals=2, Args_size=2
   0:	aload_1
   1:	ifnonnull	12
   4:	new	#10; //class java/lang/NullPointerException
   7:	dup
   8:	invokespecial	#13; //Method java/lang/NullPointerException."<init>":()V
   11:	athrow
   12:	aload_0
   13:	aload_1
   14:	putfield	#17; //Field $outer:Lscala/util/regexp/WordExp;
   17:	aload_0
   18:	invokespecial	#20; //Method java/lang/Object."<init>":()V
   21:	return
  LineNumberTable: 
   line 42: 0
   line 44: 17

  LocalVariableTable: 
   Start  Length  Slot  Name   Signature
   0      22      0    this       Lscala/util/regexp/WordExp$Label;
   0      22      1    $outer       Lscala/util/regexp/WordExp;


public scala.util.regexp.WordExp scala$util$regexp$WordExp$Label$$$outer();
  Code:
   Stack=1, Locals=1, Args_size=1
   0:	aload_0
   1:	getfield	#17; //Field $outer:Lscala/util/regexp/WordExp;
   4:	areturn
  LineNumberTable: 
   line 42: 0


}

