Compiled from "WordExp.scala"
public final class scala.util.regexp.WordExp$Wildcard$ extends java.lang.Object implements scala.Function0,scala.ScalaObject
  SourceFile: "WordExp.scala"
  Scala: length = 0x
   
  InnerClass: 
   public Wildcard=class scala/util/regexp/WordExp$Wildcard of class scala/util/regexp/WordExp
  minor version: 0
  major version: 49
  Constant pool:
Asciz	SourceFile;
Asciz	WordExp.scala;
Asciz	$outer;
Asciz	Lscala/util/regexp/WordExp;;
Asciz	toString;
Asciz	()Ljava/lang/String;;
Asciz	Code;
Asciz	LineNumberTable;
Asciz	scala/Function0$class;
class	scala/Function0$class
Asciz	(Lscala/Function0;)Ljava/lang/String;;
NameAndType	toString:(Lscala/Function0;)Ljava/lang/String;
Method	scala/Function0$class.toString:(Lscala/Function0;)Ljava/lang/String;
Asciz	unapply;
Asciz	(Lscala/util/regexp/WordExp$Wildcard;)Z;
Asciz	this;
Asciz	Lscala/util/regexp/WordExp$Wildcard$;;
Asciz	x$0;
Asciz	Lscala/util/regexp/WordExp$Wildcard;;
Asciz	LocalVariableTable;
Asciz	apply;
Asciz	()Lscala/util/regexp/WordExp$Wildcard;;
Asciz	scala/util/regexp/WordExp$Wildcard$;
class	scala/util/regexp/WordExp$Wildcard$
NameAndType	$outer:Lscala/util/regexp/WordExp;
Field	scala/util/regexp/WordExp$Wildcard$.$outer:Lscala/util/regexp/WordExp;
Asciz	scala/util/regexp/WordExp$Wildcard;
class	scala/util/regexp/WordExp$Wildcard
Asciz	<init>;
Asciz	(Lscala/util/regexp/WordExp;)V;
NameAndType	"<init>":(Lscala/util/regexp/WordExp;)V
Method	scala/util/regexp/WordExp$Wildcard."<init>":(Lscala/util/regexp/WordExp;)V
Asciz	()Ljava/lang/Object;;
NameAndType	apply:()Lscala/util/regexp/WordExp$Wildcard;
Method	scala/util/regexp/WordExp$Wildcard$.apply:()Lscala/util/regexp/WordExp$Wildcard;
Asciz	java/lang/NullPointerException;
class	java/lang/NullPointerException
Asciz	()V;
NameAndType	"<init>":()V
Method	java/lang/NullPointerException."<init>":()V
Asciz	java/lang/Object;
class	java/lang/Object
Method	java/lang/Object."<init>":()V
Asciz	$init$;
Asciz	(Lscala/Function0;)V;
NameAndType	$init$:(Lscala/Function0;)V
Method	scala/Function0$class.$init$:(Lscala/Function0;)V
Asciz	Scala;
Asciz	InnerClasses;
Asciz	scala/util/regexp/WordExp;
class	scala/util/regexp/WordExp
Asciz	Wildcard;
Asciz	scala/Function0;
class	scala/Function0
Asciz	scala/ScalaObject;
class	scala/ScalaObject

{
public final scala.util.regexp.WordExp $outer;
  Signature: Lscala/util/regexp/WordExp;

public java.lang.String toString();
  Signature: ()Ljava/lang/String;
  Code:
   Stack=1, Locals=1, Args_size=1
	aload_0
	invokestatic	Method scala/Function0$class.toString:(Lscala/Function0;)Ljava/lang/String;
	areturn
  Labels:

public boolean unapply(scala.util.regexp.WordExp$Wildcard);
  Signature: (Lscala/util/regexp/WordExp$Wildcard;)Z
  Code:
   Stack=1, Locals=2, Args_size=2
	aload_1
	ifnonnull	l1 // iconst_1
	iconst_0
	goto	l2 // ireturn
l1	iconst_1
l2	ireturn
  Labels:
   	l1 = 8 // iconst_1
   	l2 = 9 // ireturn
  LocalVariableTable: 
   Start  Length  Slot  Name   Signature
   0      10      0    this       Lscala/util/regexp/WordExp$Wildcard$;
   0      10      1    x$0       Lscala/util/regexp/WordExp$Wildcard;


public scala.util.regexp.WordExp$Wildcard apply();
  Signature: ()Lscala/util/regexp/WordExp$Wildcard;
  Code:
   Stack=3, Locals=2, Args_size=1
	aload_0
	getfield	Field $outer:Lscala/util/regexp/WordExp;
	astore_1
	new	class scala/util/regexp/WordExp$Wildcard
	dup
	aload_0
	getfield	Field $outer:Lscala/util/regexp/WordExp;
	invokespecial	Method scala/util/regexp/WordExp$Wildcard."<init>":(Lscala/util/regexp/WordExp;)V
	areturn
  Labels:
  LocalVariableTable: 
   Start  Length  Slot  Name   Signature
   0      17      0    this       Lscala/util/regexp/WordExp$Wildcard$;


public java.lang.Object apply();
  Signature: ()Ljava/lang/Object;
  Code:
   Stack=1, Locals=2, Args_size=1
	aload_0
	getfield	Field $outer:Lscala/util/regexp/WordExp;
	astore_1
	aload_0
	invokevirtual	Method apply:()Lscala/util/regexp/WordExp$Wildcard;
	areturn
  Labels:
  LocalVariableTable: 
   Start  Length  Slot  Name   Signature
   0      10      0    this       Lscala/util/regexp/WordExp$Wildcard$;


public scala.util.regexp.WordExp$Wildcard$(scala.util.regexp.WordExp);
  Signature: (Lscala/util/regexp/WordExp;)V
  Code:
   Stack=2, Locals=2, Args_size=2
	aload_1
	ifnonnull	l1 // aload_0
	new	class java/lang/NullPointerException
	dup
	invokespecial	Method java/lang/NullPointerException."<init>":()V
	athrow
l1	aload_0
	aload_1
	putfield	Field $outer:Lscala/util/regexp/WordExp;
	aload_0
	invokespecial	Method java/lang/Object."<init>":()V
	aload_0
	invokestatic	Method scala/Function0$class.$init$:(Lscala/Function0;)V
	return
  Labels:
   	l1 = 12 // aload_0
  LocalVariableTable: 
   Start  Length  Slot  Name   Signature
   0      26      0    this       Lscala/util/regexp/WordExp$Wildcard$;
   0      26      1    $outer       Lscala/util/regexp/WordExp;


}

