Compiled from "BasicTransformer.scala"
public abstract class scala.xml.transform.BasicTransformer extends java.lang.Object implements scala.Function1,scala.ScalaObject
  SourceFile: "BasicTransformer.scala"
  ScalaSig: length = 0x3
   05 00 00 
  Signature: length = 0x2
   01 6D 
  RuntimeVisibleAnnotations: length = 0xB
   00 01 01 6E 00 01 01 6F 73 01 70 
  InnerClass: 
   public final $anonfun$1=class scala/xml/transform/BasicTransformer$$anonfun$1 of class scala/xml/transform/BasicTransformer
   public final $anonfun$transform$1=class scala/xml/transform/BasicTransformer$$anonfun$transform$1 of class scala/xml/transform/BasicTransformer
   public GenericCanBuildFrom=class scala/collection/generic/TraversableFactory$GenericCanBuildFrom of class scala/collection/generic/TraversableFactory
  minor version: 0
  major version: 49
  Constant pool:
Asciz	SourceFile;
Asciz	BasicTransformer.scala;
Asciz	apply$mcVI$sp;
Asciz	(I)V;
Asciz	Code;
Asciz	LineNumberTable;
Asciz	scala/Function1$class;
class	scala/Function1$class
Asciz	(Lscala/Function1;I)V;
NameAndType	apply$mcVI$sp:(Lscala/Function1;I)V
Method	scala/Function1$class.apply$mcVI$sp:(Lscala/Function1;I)V
Asciz	this;
Asciz	Lscala/xml/transform/BasicTransformer;;
Asciz	v1;
Asciz	I;
Asciz	LocalVariableTable;
Asciz	apply$mcZI$sp;
Asciz	(I)Z;
Asciz	(Lscala/Function1;I)Z;
NameAndType	apply$mcZI$sp:(Lscala/Function1;I)Z
Method	scala/Function1$class.apply$mcZI$sp:(Lscala/Function1;I)Z
Asciz	apply$mcII$sp;
Asciz	(I)I;
Asciz	(Lscala/Function1;I)I;
NameAndType	apply$mcII$sp:(Lscala/Function1;I)I
Method	scala/Function1$class.apply$mcII$sp:(Lscala/Function1;I)I
Asciz	apply$mcLI$sp;
Asciz	(I)J;
Asciz	(Lscala/Function1;I)J;
NameAndType	apply$mcLI$sp:(Lscala/Function1;I)J
Method	scala/Function1$class.apply$mcLI$sp:(Lscala/Function1;I)J
Asciz	apply$mcDI$sp;
Asciz	(I)D;
Asciz	(Lscala/Function1;I)D;
NameAndType	apply$mcDI$sp:(Lscala/Function1;I)D
Method	scala/Function1$class.apply$mcDI$sp:(Lscala/Function1;I)D
Asciz	apply$mcVL$sp;
Asciz	(J)V;
Asciz	(Lscala/Function1;J)V;
NameAndType	apply$mcVL$sp:(Lscala/Function1;J)V
Method	scala/Function1$class.apply$mcVL$sp:(Lscala/Function1;J)V
Asciz	J;
Asciz	apply$mcZL$sp;
Asciz	(J)Z;
Asciz	(Lscala/Function1;J)Z;
NameAndType	apply$mcZL$sp:(Lscala/Function1;J)Z
Method	scala/Function1$class.apply$mcZL$sp:(Lscala/Function1;J)Z
Asciz	apply$mcIL$sp;
Asciz	(J)I;
Asciz	(Lscala/Function1;J)I;
NameAndType	apply$mcIL$sp:(Lscala/Function1;J)I
Method	scala/Function1$class.apply$mcIL$sp:(Lscala/Function1;J)I
Asciz	apply$mcLL$sp;
Asciz	(J)J;
Asciz	(Lscala/Function1;J)J;
NameAndType	apply$mcLL$sp:(Lscala/Function1;J)J
Method	scala/Function1$class.apply$mcLL$sp:(Lscala/Function1;J)J
Asciz	apply$mcDL$sp;
Asciz	(J)D;
Asciz	(Lscala/Function1;J)D;
NameAndType	apply$mcDL$sp:(Lscala/Function1;J)D
Method	scala/Function1$class.apply$mcDL$sp:(Lscala/Function1;J)D
Asciz	apply$mcVD$sp;
Asciz	(D)V;
Asciz	(Lscala/Function1;D)V;
NameAndType	apply$mcVD$sp:(Lscala/Function1;D)V
Method	scala/Function1$class.apply$mcVD$sp:(Lscala/Function1;D)V
Asciz	D;
Asciz	apply$mcZD$sp;
Asciz	(D)Z;
Asciz	(Lscala/Function1;D)Z;
NameAndType	apply$mcZD$sp:(Lscala/Function1;D)Z
Method	scala/Function1$class.apply$mcZD$sp:(Lscala/Function1;D)Z
Asciz	apply$mcID$sp;
Asciz	(D)I;
Asciz	(Lscala/Function1;D)I;
NameAndType	apply$mcID$sp:(Lscala/Function1;D)I
Method	scala/Function1$class.apply$mcID$sp:(Lscala/Function1;D)I
Asciz	apply$mcLD$sp;
Asciz	(D)J;
Asciz	(Lscala/Function1;D)J;
NameAndType	apply$mcLD$sp:(Lscala/Function1;D)J
Method	scala/Function1$class.apply$mcLD$sp:(Lscala/Function1;D)J
Asciz	apply$mcDD$sp;
Asciz	(D)D;
Asciz	(Lscala/Function1;D)D;
NameAndType	apply$mcDD$sp:(Lscala/Function1;D)D
Method	scala/Function1$class.apply$mcDD$sp:(Lscala/Function1;D)D
Asciz	toString;
Asciz	()Ljava/lang/String;;
Asciz	(Lscala/Function1;)Ljava/lang/String;;
NameAndType	toString:(Lscala/Function1;)Ljava/lang/String;
Method	scala/Function1$class.toString:(Lscala/Function1;)Ljava/lang/String;
Asciz	compose;
Asciz	(Lscala/Function1;)Lscala/Function1;;
Asciz	(Lscala/Function1;Lscala/Function1;)Lscala/Function1;;
NameAndType	compose:(Lscala/Function1;Lscala/Function1;)Lscala/Function1;
Method	scala/Function1$class.compose:(Lscala/Function1;Lscala/Function1;)Lscala/Function1;
Asciz	g;
Asciz	Lscala/Function1;;
Asciz	compose$mcVI$sp;
NameAndType	compose$mcVI$sp:(Lscala/Function1;Lscala/Function1;)Lscala/Function1;
Method	scala/Function1$class.compose$mcVI$sp:(Lscala/Function1;Lscala/Function1;)Lscala/Function1;
Asciz	compose$mcZI$sp;
NameAndType	compose$mcZI$sp:(Lscala/Function1;Lscala/Function1;)Lscala/Function1;
Method	scala/Function1$class.compose$mcZI$sp:(Lscala/Function1;Lscala/Function1;)Lscala/Function1;
Asciz	compose$mcII$sp;
NameAndType	compose$mcII$sp:(Lscala/Function1;Lscala/Function1;)Lscala/Function1;
Method	scala/Function1$class.compose$mcII$sp:(Lscala/Function1;Lscala/Function1;)Lscala/Function1;
Asciz	compose$mcLI$sp;
NameAndType	compose$mcLI$sp:(Lscala/Function1;Lscala/Function1;)Lscala/Function1;
Method	scala/Function1$class.compose$mcLI$sp:(Lscala/Function1;Lscala/Function1;)Lscala/Function1;
Asciz	compose$mcDI$sp;
NameAndType	compose$mcDI$sp:(Lscala/Function1;Lscala/Function1;)Lscala/Function1;
Method	scala/Function1$class.compose$mcDI$sp:(Lscala/Function1;Lscala/Function1;)Lscala/Function1;
Asciz	compose$mcVL$sp;
NameAndType	compose$mcVL$sp:(Lscala/Function1;Lscala/Function1;)Lscala/Function1;
Method	scala/Function1$class.compose$mcVL$sp:(Lscala/Function1;Lscala/Function1;)Lscala/Function1;
Asciz	compose$mcZL$sp;
NameAndType	compose$mcZL$sp:(Lscala/Function1;Lscala/Function1;)Lscala/Function1;
Method	scala/Function1$class.compose$mcZL$sp:(Lscala/Function1;Lscala/Function1;)Lscala/Function1;
Asciz	compose$mcIL$sp;
NameAndType	compose$mcIL$sp:(Lscala/Function1;Lscala/Function1;)Lscala/Function1;
Method	scala/Function1$class.compose$mcIL$sp:(Lscala/Function1;Lscala/Function1;)Lscala/Function1;
Asciz	compose$mcLL$sp;
NameAndType	compose$mcLL$sp:(Lscala/Function1;Lscala/Function1;)Lscala/Function1;
Method	scala/Function1$class.compose$mcLL$sp:(Lscala/Function1;Lscala/Function1;)Lscala/Function1;
Asciz	compose$mcDL$sp;
NameAndType	compose$mcDL$sp:(Lscala/Function1;Lscala/Function1;)Lscala/Function1;
Method	scala/Function1$class.compose$mcDL$sp:(Lscala/Function1;Lscala/Function1;)Lscala/Function1;
Asciz	compose$mcVD$sp;
NameAndType	compose$mcVD$sp:(Lscala/Function1;Lscala/Function1;)Lscala/Function1;
Method	scala/Function1$class.compose$mcVD$sp:(Lscala/Function1;Lscala/Function1;)Lscala/Function1;
Asciz	compose$mcZD$sp;
NameAndType	compose$mcZD$sp:(Lscala/Function1;Lscala/Function1;)Lscala/Function1;
Method	scala/Function1$class.compose$mcZD$sp:(Lscala/Function1;Lscala/Function1;)Lscala/Function1;
Asciz	compose$mcID$sp;
NameAndType	compose$mcID$sp:(Lscala/Function1;Lscala/Function1;)Lscala/Function1;
Method	scala/Function1$class.compose$mcID$sp:(Lscala/Function1;Lscala/Function1;)Lscala/Function1;
Asciz	compose$mcLD$sp;
NameAndType	compose$mcLD$sp:(Lscala/Function1;Lscala/Function1;)Lscala/Function1;
Method	scala/Function1$class.compose$mcLD$sp:(Lscala/Function1;Lscala/Function1;)Lscala/Function1;
Asciz	compose$mcDD$sp;
NameAndType	compose$mcDD$sp:(Lscala/Function1;Lscala/Function1;)Lscala/Function1;
Method	scala/Function1$class.compose$mcDD$sp:(Lscala/Function1;Lscala/Function1;)Lscala/Function1;
Asciz	andThen;
NameAndType	andThen:(Lscala/Function1;Lscala/Function1;)Lscala/Function1;
Method	scala/Function1$class.andThen:(Lscala/Function1;Lscala/Function1;)Lscala/Function1;
Asciz	andThen$mcVI$sp;
NameAndType	andThen$mcVI$sp:(Lscala/Function1;Lscala/Function1;)Lscala/Function1;
Method	scala/Function1$class.andThen$mcVI$sp:(Lscala/Function1;Lscala/Function1;)Lscala/Function1;
Asciz	andThen$mcZI$sp;
NameAndType	andThen$mcZI$sp:(Lscala/Function1;Lscala/Function1;)Lscala/Function1;
Method	scala/Function1$class.andThen$mcZI$sp:(Lscala/Function1;Lscala/Function1;)Lscala/Function1;
Asciz	andThen$mcII$sp;
NameAndType	andThen$mcII$sp:(Lscala/Function1;Lscala/Function1;)Lscala/Function1;
Method	scala/Function1$class.andThen$mcII$sp:(Lscala/Function1;Lscala/Function1;)Lscala/Function1;
Asciz	andThen$mcLI$sp;
NameAndType	andThen$mcLI$sp:(Lscala/Function1;Lscala/Function1;)Lscala/Function1;
Method	scala/Function1$class.andThen$mcLI$sp:(Lscala/Function1;Lscala/Function1;)Lscala/Function1;
Asciz	andThen$mcDI$sp;
NameAndType	andThen$mcDI$sp:(Lscala/Function1;Lscala/Function1;)Lscala/Function1;
Method	scala/Function1$class.andThen$mcDI$sp:(Lscala/Function1;Lscala/Function1;)Lscala/Function1;
Asciz	andThen$mcVL$sp;
NameAndType	andThen$mcVL$sp:(Lscala/Function1;Lscala/Function1;)Lscala/Function1;
Method	scala/Function1$class.andThen$mcVL$sp:(Lscala/Function1;Lscala/Function1;)Lscala/Function1;
Asciz	andThen$mcZL$sp;
NameAndType	andThen$mcZL$sp:(Lscala/Function1;Lscala/Function1;)Lscala/Function1;
Method	scala/Function1$class.andThen$mcZL$sp:(Lscala/Function1;Lscala/Function1;)Lscala/Function1;
Asciz	andThen$mcIL$sp;
NameAndType	andThen$mcIL$sp:(Lscala/Function1;Lscala/Function1;)Lscala/Function1;
Method	scala/Function1$class.andThen$mcIL$sp:(Lscala/Function1;Lscala/Function1;)Lscala/Function1;
Asciz	andThen$mcLL$sp;
NameAndType	andThen$mcLL$sp:(Lscala/Function1;Lscala/Function1;)Lscala/Function1;
Method	scala/Function1$class.andThen$mcLL$sp:(Lscala/Function1;Lscala/Function1;)Lscala/Function1;
Asciz	andThen$mcDL$sp;
NameAndType	andThen$mcDL$sp:(Lscala/Function1;Lscala/Function1;)Lscala/Function1;
Method	scala/Function1$class.andThen$mcDL$sp:(Lscala/Function1;Lscala/Function1;)Lscala/Function1;
Asciz	andThen$mcVD$sp;
NameAndType	andThen$mcVD$sp:(Lscala/Function1;Lscala/Function1;)Lscala/Function1;
Method	scala/Function1$class.andThen$mcVD$sp:(Lscala/Function1;Lscala/Function1;)Lscala/Function1;
Asciz	andThen$mcZD$sp;
NameAndType	andThen$mcZD$sp:(Lscala/Function1;Lscala/Function1;)Lscala/Function1;
Method	scala/Function1$class.andThen$mcZD$sp:(Lscala/Function1;Lscala/Function1;)Lscala/Function1;
Asciz	andThen$mcID$sp;
NameAndType	andThen$mcID$sp:(Lscala/Function1;Lscala/Function1;)Lscala/Function1;
Method	scala/Function1$class.andThen$mcID$sp:(Lscala/Function1;Lscala/Function1;)Lscala/Function1;
Asciz	andThen$mcLD$sp;
NameAndType	andThen$mcLD$sp:(Lscala/Function1;Lscala/Function1;)Lscala/Function1;
Method	scala/Function1$class.andThen$mcLD$sp:(Lscala/Function1;Lscala/Function1;)Lscala/Function1;
Asciz	andThen$mcDD$sp;
NameAndType	andThen$mcDD$sp:(Lscala/Function1;Lscala/Function1;)Lscala/Function1;
Method	scala/Function1$class.andThen$mcDD$sp:(Lscala/Function1;Lscala/Function1;)Lscala/Function1;
Asciz	unchanged;
Asciz	(Lscala/xml/Node;Lscala/collection/Seq;)Z;
Asciz	scala/collection/SeqLike;
class	scala/collection/SeqLike
Asciz	length;
Asciz	()I;
NameAndType	length:()I
InterfaceMethod	scala/collection/SeqLike.length:()I
Asciz	scala/collection/IterableLike;
class	scala/collection/IterableLike
Asciz	head;
Asciz	()Ljava/lang/Object;;
NameAndType	head:()Ljava/lang/Object;
InterfaceMethod	scala/collection/IterableLike.head:()Ljava/lang/Object;
Asciz	java/lang/Object;
class	java/lang/Object
Asciz	equals;
Asciz	(Ljava/lang/Object;)Z;
NameAndType	equals:(Ljava/lang/Object;)Z
Method	java/lang/Object.equals:(Ljava/lang/Object;)Z
Asciz	n;
Asciz	Lscala/xml/Node;;
Asciz	ns;
Asciz	Lscala/collection/Seq;;
Asciz	(Lscala/xml/Node;Lscala/collection/Seq<Lscala/xml/Node;>;)Z;
Asciz	Signature;
Asciz	transform;
Asciz	(Lscala/collection/Iterator;Lscala/xml/NodeBuffer;)Lscala/collection/Seq;;
Asciz	scala/xml/transform/BasicTransformer$$anonfun$transform$1;
class	scala/xml/transform/BasicTransformer$$anonfun$transform$1
Asciz	<init>;
Asciz	(Lscala/xml/transform/BasicTransformer;)V;
NameAndType	"<init>":(Lscala/xml/transform/BasicTransformer;)V
Method	scala/xml/transform/BasicTransformer$$anonfun$transform$1."<init>":(Lscala/xml/transform/BasicTransformer;)V
Asciz	scala/collection/TraversableOnce;
class	scala/collection/TraversableOnce
Asciz	foldLeft;
Asciz	(Ljava/lang/Object;Lscala/Function2;)Ljava/lang/Object;;
NameAndType	foldLeft:(Ljava/lang/Object;Lscala/Function2;)Ljava/lang/Object;
InterfaceMethod	scala/collection/TraversableOnce.foldLeft:(Ljava/lang/Object;Lscala/Function2;)Ljava/lang/Object;
Asciz	toSeq;
Asciz	()Lscala/collection/Seq;;
NameAndType	toSeq:()Lscala/collection/Seq;
InterfaceMethod	scala/collection/SeqLike.toSeq:()Lscala/collection/Seq;
Asciz	it;
Asciz	Lscala/collection/Iterator;;
Asciz	nb;
Asciz	Lscala/xml/NodeBuffer;;
Asciz	(Lscala/collection/Iterator<Lscala/xml/Node;>;Lscala/xml/NodeBuffer;)Lscala/collection/Seq<Lscala/xml/Node;>;;
Asciz	(Lscala/collection/Seq;)Lscala/collection/Seq;;
Asciz	scala/xml/transform/BasicTransformer$$anonfun$1;
class	scala/xml/transform/BasicTransformer$$anonfun$1
Method	scala/xml/transform/BasicTransformer$$anonfun$1."<init>":(Lscala/xml/transform/BasicTransformer;)V
Asciz	scala/collection/TraversableLike;
class	scala/collection/TraversableLike
Asciz	span;
Asciz	(Lscala/Function1;)Lscala/Tuple2;;
NameAndType	span:(Lscala/Function1;)Lscala/Tuple2;
InterfaceMethod	scala/collection/TraversableLike.span:(Lscala/Function1;)Lscala/Tuple2;
Asciz	scala/Tuple2;
class	scala/Tuple2
Asciz	_1;
NameAndType	_1:()Ljava/lang/Object;
Method	scala/Tuple2._1:()Ljava/lang/Object;
Asciz	_2;
NameAndType	_2:()Ljava/lang/Object;
Method	scala/Tuple2._2:()Ljava/lang/Object;
Asciz	(Ljava/lang/Object;Ljava/lang/Object;)V;
NameAndType	"<init>":(Ljava/lang/Object;Ljava/lang/Object;)V
Method	scala/Tuple2."<init>":(Ljava/lang/Object;Ljava/lang/Object;)V
Asciz	scala/collection/Seq;
class	scala/collection/Seq
Asciz	isEmpty;
Asciz	()Z;
NameAndType	isEmpty:()Z
InterfaceMethod	scala/collection/IterableLike.isEmpty:()Z
Asciz	scala/xml/Node;
class	scala/xml/Node
Asciz	scala/xml/transform/BasicTransformer;
class	scala/xml/transform/BasicTransformer
Asciz	(Lscala/xml/Node;)Lscala/collection/Seq;;
NameAndType	transform:(Lscala/xml/Node;)Lscala/collection/Seq;
Method	scala/xml/transform/BasicTransformer.transform:(Lscala/xml/Node;)Lscala/collection/Seq;
Asciz	scala/collection/Seq$;
class	scala/collection/Seq$
Asciz	MODULE$;
Asciz	Lscala/collection/Seq$;;
NameAndType	MODULE$:Lscala/collection/Seq$;
Field	scala/collection/Seq$.MODULE$:Lscala/collection/Seq$;
Asciz	scala/collection/generic/TraversableFactory$GenericCanBuildFrom;
class	scala/collection/generic/TraversableFactory$GenericCanBuildFrom
Asciz	(Lscala/collection/generic/TraversableFactory;)V;
NameAndType	"<init>":(Lscala/collection/generic/TraversableFactory;)V
Method	scala/collection/generic/TraversableFactory$GenericCanBuildFrom."<init>":(Lscala/collection/generic/TraversableFactory;)V
Asciz	$plus$plus;
Asciz	(Lscala/collection/TraversableOnce;Lscala/collection/generic/CanBuildFrom;)Ljava/lang/Object;;
NameAndType	$plus$plus:(Lscala/collection/TraversableOnce;Lscala/collection/generic/CanBuildFrom;)Ljava/lang/Object;
InterfaceMethod	scala/collection/TraversableLike.$plus$plus:(Lscala/collection/TraversableOnce;Lscala/collection/generic/CanBuildFrom;)Ljava/lang/Object;
Asciz	tail;
NameAndType	tail:()Ljava/lang/Object;
InterfaceMethod	scala/collection/TraversableLike.tail:()Ljava/lang/Object;
NameAndType	transform:(Lscala/collection/Seq;)Lscala/collection/Seq;
Method	scala/xml/transform/BasicTransformer.transform:(Lscala/collection/Seq;)Lscala/collection/Seq;
Asciz	scala/MatchError;
class	scala/MatchError
Asciz	(Ljava/lang/Object;)V;
NameAndType	"<init>":(Ljava/lang/Object;)V
Method	scala/MatchError."<init>":(Ljava/lang/Object;)V
Asciz	xs1;
Asciz	xs2;
Asciz	temp1;
Asciz	Lscala/Tuple2;;
Asciz	(Lscala/collection/Seq<Lscala/xml/Node;>;)Lscala/collection/Seq<Lscala/xml/Node;>;;
Asciz	doTransform;
NameAndType	doTransform:()Z
Method	scala/xml/Node.doTransform:()Z
Asciz	scala/xml/Group;
class	scala/xml/Group
Asciz	nodes;
NameAndType	nodes:Lscala/collection/Seq;
Field	scala/xml/Group.nodes:Lscala/collection/Seq;
Asciz	(Lscala/collection/Seq;)V;
NameAndType	"<init>":(Lscala/collection/Seq;)V
Method	scala/xml/Group."<init>":(Lscala/collection/Seq;)V
Asciz	child;
NameAndType	child:()Lscala/collection/Seq;
Method	scala/xml/Node.child:()Lscala/collection/Seq;
Asciz	prefix;
NameAndType	prefix:()Ljava/lang/String;
Method	scala/xml/Node.prefix:()Ljava/lang/String;
Asciz	label;
NameAndType	label:()Ljava/lang/String;
Method	scala/xml/Node.label:()Ljava/lang/String;
Asciz	attributes;
Asciz	()Lscala/xml/MetaData;;
NameAndType	attributes:()Lscala/xml/MetaData;
Method	scala/xml/Node.attributes:()Lscala/xml/MetaData;
Asciz	scope;
Asciz	()Lscala/xml/NamespaceBinding;;
NameAndType	scope:()Lscala/xml/NamespaceBinding;
Method	scala/xml/Node.scope:()Lscala/xml/NamespaceBinding;
Asciz	scala/xml/Elem;
class	scala/xml/Elem
Asciz	(Ljava/lang/String;Ljava/lang/String;Lscala/xml/MetaData;Lscala/xml/NamespaceBinding;Lscala/collection/Seq;)V;
NameAndType	"<init>":(Ljava/lang/String;Ljava/lang/String;Lscala/xml/MetaData;Lscala/xml/NamespaceBinding;Lscala/collection/Seq;)V
Method	scala/xml/Elem."<init>":(Ljava/lang/String;Ljava/lang/String;Lscala/xml/MetaData;Lscala/xml/NamespaceBinding;Lscala/collection/Seq;)V
Asciz	ch;
Asciz	nch;
Asciz	(Lscala/xml/Node;)Lscala/collection/Seq<Lscala/xml/Node;>;;
Asciz	apply;
Asciz	(Lscala/xml/Node;)Lscala/xml/Node;;
Asciz	java/lang/UnsupportedOperationException;
class	java/lang/UnsupportedOperationException
Asciz	transform must return single node for root;
String	transform must return single node for root
Asciz	(Ljava/lang/String;)V;
NameAndType	"<init>":(Ljava/lang/String;)V
Method	java/lang/UnsupportedOperationException."<init>":(Ljava/lang/String;)V
Asciz	seq;
Asciz	(Ljava/lang/Object;)Ljava/lang/Object;;
NameAndType	apply:(Lscala/xml/Node;)Lscala/xml/Node;
Method	scala/xml/transform/BasicTransformer.apply:(Lscala/xml/Node;)Lscala/xml/Node;
Asciz	Ljava/lang/Object;;
Asciz	()V;
NameAndType	"<init>":()V
Method	java/lang/Object."<init>":()V
Asciz	$init$;
Asciz	(Lscala/Function1;)V;
NameAndType	$init$:(Lscala/Function1;)V
Method	scala/Function1$class.$init$:(Lscala/Function1;)V
Asciz	ScalaSig;
Asciz	Ljava/lang/Object;Lscala/Function1<Lscala/xml/Node;Lscala/xml/Node;>;Lscala/ScalaObject;;
Asciz	Lscala/reflect/ScalaSignature;;
Asciz	bytes;
Asciz	93\"\r\t!n+sC:hm:nKJT!aQM\:g_Jl'BA\rAX)1oY1mC1%i\"a\t1Q!!\t1gn!!.<b\t\tBBPE*,7\r\t'Q1b#D\t)bAAGk:G/[8ocAqG\t%>$W\r7%AD'G.Y(cUGCq$=S:LGOAAA!)1C\tIIQO\2iC:<W\rK!RCA\n'\t9cAAC_>dW-8\t%9DQaA1\n!A\:5*dC/g9qFMa)CyI|w \nI!A7m[1hK&ag'(B\":)\ra#hwa\rPSR2!L\tqtGJi\r^8s1B\tq'\r&1\t>$WMQ;gM\"B\t)ECGYC\t1-\"I)\ta\nC*aCLA*AbaBd\")Fa-;
Asciz	RuntimeVisibleAnnotations;
Asciz	InnerClasses;
Asciz	$anonfun$1;
Asciz	$anonfun$transform$1;
Asciz	scala/collection/generic/TraversableFactory;
class	scala/collection/generic/TraversableFactory
Asciz	GenericCanBuildFrom;
Asciz	scala/Function1;
class	scala/Function1
Asciz	scala/ScalaObject;
class	scala/ScalaObject

{
public void apply$mcVI$sp(int);
  Signature: (I)V
  Code:
   Stack=2, Locals=2, Args_size=2
	aload_0
	iload_1
	invokestatic	Method scala/Function1$class.apply$mcVI$sp:(Lscala/Function1;I)V
	return
  Labels:
  LocalVariableTable: 
   Start  Length  Slot  Name   Signature
   0      6      0    this       Lscala/xml/transform/BasicTransformer;
   0      6      1    v1       I


public boolean apply$mcZI$sp(int);
  Signature: (I)Z
  Code:
   Stack=2, Locals=2, Args_size=2
	aload_0
	iload_1
	invokestatic	Method scala/Function1$class.apply$mcZI$sp:(Lscala/Function1;I)Z
	ireturn
  Labels:
  LocalVariableTable: 
   Start  Length  Slot  Name   Signature
   0      6      0    this       Lscala/xml/transform/BasicTransformer;
   0      6      1    v1       I


public int apply$mcII$sp(int);
  Signature: (I)I
  Code:
   Stack=2, Locals=2, Args_size=2
	aload_0
	iload_1
	invokestatic	Method scala/Function1$class.apply$mcII$sp:(Lscala/Function1;I)I
	ireturn
  Labels:
  LocalVariableTable: 
   Start  Length  Slot  Name   Signature
   0      6      0    this       Lscala/xml/transform/BasicTransformer;
   0      6      1    v1       I


public long apply$mcLI$sp(int);
  Signature: (I)J
  Code:
   Stack=2, Locals=2, Args_size=2
	aload_0
	iload_1
	invokestatic	Method scala/Function1$class.apply$mcLI$sp:(Lscala/Function1;I)J
	lreturn
  Labels:
  LocalVariableTable: 
   Start  Length  Slot  Name   Signature
   0      6      0    this       Lscala/xml/transform/BasicTransformer;
   0      6      1    v1       I


public double apply$mcDI$sp(int);
  Signature: (I)D
  Code:
   Stack=2, Locals=2, Args_size=2
	aload_0
	iload_1
	invokestatic	Method scala/Function1$class.apply$mcDI$sp:(Lscala/Function1;I)D
	dreturn
  Labels:
  LocalVariableTable: 
   Start  Length  Slot  Name   Signature
   0      6      0    this       Lscala/xml/transform/BasicTransformer;
   0      6      1    v1       I


public void apply$mcVL$sp(long);
  Signature: (J)V
  Code:
   Stack=3, Locals=3, Args_size=2
	aload_0
	lload_1
	invokestatic	Method scala/Function1$class.apply$mcVL$sp:(Lscala/Function1;J)V
	return
  Labels:
  LocalVariableTable: 
   Start  Length  Slot  Name   Signature
   0      6      0    this       Lscala/xml/transform/BasicTransformer;
   0      6      1    v1       J


public boolean apply$mcZL$sp(long);
  Signature: (J)Z
  Code:
   Stack=3, Locals=3, Args_size=2
	aload_0
	lload_1
	invokestatic	Method scala/Function1$class.apply$mcZL$sp:(Lscala/Function1;J)Z
	ireturn
  Labels:
  LocalVariableTable: 
   Start  Length  Slot  Name   Signature
   0      6      0    this       Lscala/xml/transform/BasicTransformer;
   0      6      1    v1       J


public int apply$mcIL$sp(long);
  Signature: (J)I
  Code:
   Stack=3, Locals=3, Args_size=2
	aload_0
	lload_1
	invokestatic	Method scala/Function1$class.apply$mcIL$sp:(Lscala/Function1;J)I
	ireturn
  Labels:
  LocalVariableTable: 
   Start  Length  Slot  Name   Signature
   0      6      0    this       Lscala/xml/transform/BasicTransformer;
   0      6      1    v1       J


public long apply$mcLL$sp(long);
  Signature: (J)J
  Code:
   Stack=3, Locals=3, Args_size=2
	aload_0
	lload_1
	invokestatic	Method scala/Function1$class.apply$mcLL$sp:(Lscala/Function1;J)J
	lreturn
  Labels:
  LocalVariableTable: 
   Start  Length  Slot  Name   Signature
   0      6      0    this       Lscala/xml/transform/BasicTransformer;
   0      6      1    v1       J


public double apply$mcDL$sp(long);
  Signature: (J)D
  Code:
   Stack=3, Locals=3, Args_size=2
	aload_0
	lload_1
	invokestatic	Method scala/Function1$class.apply$mcDL$sp:(Lscala/Function1;J)D
	dreturn
  Labels:
  LocalVariableTable: 
   Start  Length  Slot  Name   Signature
   0      6      0    this       Lscala/xml/transform/BasicTransformer;
   0      6      1    v1       J


public void apply$mcVD$sp(double);
  Signature: (D)V
  Code:
   Stack=3, Locals=3, Args_size=2
	aload_0
	dload_1
	invokestatic	Method scala/Function1$class.apply$mcVD$sp:(Lscala/Function1;D)V
	return
  Labels:
  LocalVariableTable: 
   Start  Length  Slot  Name   Signature
   0      6      0    this       Lscala/xml/transform/BasicTransformer;
   0      6      1    v1       D


public boolean apply$mcZD$sp(double);
  Signature: (D)Z
  Code:
   Stack=3, Locals=3, Args_size=2
	aload_0
	dload_1
	invokestatic	Method scala/Function1$class.apply$mcZD$sp:(Lscala/Function1;D)Z
	ireturn
  Labels:
  LocalVariableTable: 
   Start  Length  Slot  Name   Signature
   0      6      0    this       Lscala/xml/transform/BasicTransformer;
   0      6      1    v1       D


public int apply$mcID$sp(double);
  Signature: (D)I
  Code:
   Stack=3, Locals=3, Args_size=2
	aload_0
	dload_1
	invokestatic	Method scala/Function1$class.apply$mcID$sp:(Lscala/Function1;D)I
	ireturn
  Labels:
  LocalVariableTable: 
   Start  Length  Slot  Name   Signature
   0      6      0    this       Lscala/xml/transform/BasicTransformer;
   0      6      1    v1       D


public long apply$mcLD$sp(double);
  Signature: (D)J
  Code:
   Stack=3, Locals=3, Args_size=2
	aload_0
	dload_1
	invokestatic	Method scala/Function1$class.apply$mcLD$sp:(Lscala/Function1;D)J
	lreturn
  Labels:
  LocalVariableTable: 
   Start  Length  Slot  Name   Signature
   0      6      0    this       Lscala/xml/transform/BasicTransformer;
   0      6      1    v1       D


public double apply$mcDD$sp(double);
  Signature: (D)D
  Code:
   Stack=3, Locals=3, Args_size=2
	aload_0
	dload_1
	invokestatic	Method scala/Function1$class.apply$mcDD$sp:(Lscala/Function1;D)D
	dreturn
  Labels:
  LocalVariableTable: 
   Start  Length  Slot  Name   Signature
   0      6      0    this       Lscala/xml/transform/BasicTransformer;
   0      6      1    v1       D


public java.lang.String toString();
  Signature: ()Ljava/lang/String;
  Code:
   Stack=1, Locals=1, Args_size=1
	aload_0
	invokestatic	Method scala/Function1$class.toString:(Lscala/Function1;)Ljava/lang/String;
	areturn
  Labels:

public scala.Function1 compose(scala.Function1);
  Signature: (Lscala/Function1;)Lscala/Function1;
  Code:
   Stack=2, Locals=2, Args_size=2
	aload_0
	aload_1
	invokestatic	Method scala/Function1$class.compose:(Lscala/Function1;Lscala/Function1;)Lscala/Function1;
	areturn
  Labels:
  LocalVariableTable: 
   Start  Length  Slot  Name   Signature
   0      6      0    this       Lscala/xml/transform/BasicTransformer;
   0      6      1    g       Lscala/Function1;


public scala.Function1 compose$mcVI$sp(scala.Function1);
  Signature: (Lscala/Function1;)Lscala/Function1;
  Code:
   Stack=2, Locals=2, Args_size=2
	aload_0
	aload_1
	invokestatic	Method scala/Function1$class.compose$mcVI$sp:(Lscala/Function1;Lscala/Function1;)Lscala/Function1;
	areturn
  Labels:
  LocalVariableTable: 
   Start  Length  Slot  Name   Signature
   0      6      0    this       Lscala/xml/transform/BasicTransformer;
   0      6      1    g       Lscala/Function1;


public scala.Function1 compose$mcZI$sp(scala.Function1);
  Signature: (Lscala/Function1;)Lscala/Function1;
  Code:
   Stack=2, Locals=2, Args_size=2
	aload_0
	aload_1
	invokestatic	Method scala/Function1$class.compose$mcZI$sp:(Lscala/Function1;Lscala/Function1;)Lscala/Function1;
	areturn
  Labels:
  LocalVariableTable: 
   Start  Length  Slot  Name   Signature
   0      6      0    this       Lscala/xml/transform/BasicTransformer;
   0      6      1    g       Lscala/Function1;


public scala.Function1 compose$mcII$sp(scala.Function1);
  Signature: (Lscala/Function1;)Lscala/Function1;
  Code:
   Stack=2, Locals=2, Args_size=2
	aload_0
	aload_1
	invokestatic	Method scala/Function1$class.compose$mcII$sp:(Lscala/Function1;Lscala/Function1;)Lscala/Function1;
	areturn
  Labels:
  LocalVariableTable: 
   Start  Length  Slot  Name   Signature
   0      6      0    this       Lscala/xml/transform/BasicTransformer;
   0      6      1    g       Lscala/Function1;


public scala.Function1 compose$mcLI$sp(scala.Function1);
  Signature: (Lscala/Function1;)Lscala/Function1;
  Code:
   Stack=2, Locals=2, Args_size=2
	aload_0
	aload_1
	invokestatic	Method scala/Function1$class.compose$mcLI$sp:(Lscala/Function1;Lscala/Function1;)Lscala/Function1;
	areturn
  Labels:
  LocalVariableTable: 
   Start  Length  Slot  Name   Signature
   0      6      0    this       Lscala/xml/transform/BasicTransformer;
   0      6      1    g       Lscala/Function1;


public scala.Function1 compose$mcDI$sp(scala.Function1);
  Signature: (Lscala/Function1;)Lscala/Function1;
  Code:
   Stack=2, Locals=2, Args_size=2
	aload_0
	aload_1
	invokestatic	Method scala/Function1$class.compose$mcDI$sp:(Lscala/Function1;Lscala/Function1;)Lscala/Function1;
	areturn
  Labels:
  LocalVariableTable: 
   Start  Length  Slot  Name   Signature
   0      6      0    this       Lscala/xml/transform/BasicTransformer;
   0      6      1    g       Lscala/Function1;


public scala.Function1 compose$mcVL$sp(scala.Function1);
  Signature: (Lscala/Function1;)Lscala/Function1;
  Code:
   Stack=2, Locals=2, Args_size=2
	aload_0
	aload_1
	invokestatic	Method scala/Function1$class.compose$mcVL$sp:(Lscala/Function1;Lscala/Function1;)Lscala/Function1;
	areturn
  Labels:
  LocalVariableTable: 
   Start  Length  Slot  Name   Signature
   0      6      0    this       Lscala/xml/transform/BasicTransformer;
   0      6      1    g       Lscala/Function1;


public scala.Function1 compose$mcZL$sp(scala.Function1);
  Signature: (Lscala/Function1;)Lscala/Function1;
  Code:
   Stack=2, Locals=2, Args_size=2
	aload_0
	aload_1
	invokestatic	Method scala/Function1$class.compose$mcZL$sp:(Lscala/Function1;Lscala/Function1;)Lscala/Function1;
	areturn
  Labels:
  LocalVariableTable: 
   Start  Length  Slot  Name   Signature
   0      6      0    this       Lscala/xml/transform/BasicTransformer;
   0      6      1    g       Lscala/Function1;


public scala.Function1 compose$mcIL$sp(scala.Function1);
  Signature: (Lscala/Function1;)Lscala/Function1;
  Code:
   Stack=2, Locals=2, Args_size=2
	aload_0
	aload_1
	invokestatic	Method scala/Function1$class.compose$mcIL$sp:(Lscala/Function1;Lscala/Function1;)Lscala/Function1;
	areturn
  Labels:
  LocalVariableTable: 
   Start  Length  Slot  Name   Signature
   0      6      0    this       Lscala/xml/transform/BasicTransformer;
   0      6      1    g       Lscala/Function1;


public scala.Function1 compose$mcLL$sp(scala.Function1);
  Signature: (Lscala/Function1;)Lscala/Function1;
  Code:
   Stack=2, Locals=2, Args_size=2
	aload_0
	aload_1
	invokestatic	Method scala/Function1$class.compose$mcLL$sp:(Lscala/Function1;Lscala/Function1;)Lscala/Function1;
	areturn
  Labels:
  LocalVariableTable: 
   Start  Length  Slot  Name   Signature
   0      6      0    this       Lscala/xml/transform/BasicTransformer;
   0      6      1    g       Lscala/Function1;


public scala.Function1 compose$mcDL$sp(scala.Function1);
  Signature: (Lscala/Function1;)Lscala/Function1;
  Code:
   Stack=2, Locals=2, Args_size=2
	aload_0
	aload_1
	invokestatic	Method scala/Function1$class.compose$mcDL$sp:(Lscala/Function1;Lscala/Function1;)Lscala/Function1;
	areturn
  Labels:
  LocalVariableTable: 
   Start  Length  Slot  Name   Signature
   0      6      0    this       Lscala/xml/transform/BasicTransformer;
   0      6      1    g       Lscala/Function1;


public scala.Function1 compose$mcVD$sp(scala.Function1);
  Signature: (Lscala/Function1;)Lscala/Function1;
  Code:
   Stack=2, Locals=2, Args_size=2
	aload_0
	aload_1
	invokestatic	Method scala/Function1$class.compose$mcVD$sp:(Lscala/Function1;Lscala/Function1;)Lscala/Function1;
	areturn
  Labels:
  LocalVariableTable: 
   Start  Length  Slot  Name   Signature
   0      6      0    this       Lscala/xml/transform/BasicTransformer;
   0      6      1    g       Lscala/Function1;


public scala.Function1 compose$mcZD$sp(scala.Function1);
  Signature: (Lscala/Function1;)Lscala/Function1;
  Code:
   Stack=2, Locals=2, Args_size=2
	aload_0
	aload_1
	invokestatic	Method scala/Function1$class.compose$mcZD$sp:(Lscala/Function1;Lscala/Function1;)Lscala/Function1;
	areturn
  Labels:
  LocalVariableTable: 
   Start  Length  Slot  Name   Signature
   0      6      0    this       Lscala/xml/transform/BasicTransformer;
   0      6      1    g       Lscala/Function1;


public scala.Function1 compose$mcID$sp(scala.Function1);
  Signature: (Lscala/Function1;)Lscala/Function1;
  Code:
   Stack=2, Locals=2, Args_size=2
	aload_0
	aload_1
	invokestatic	Method scala/Function1$class.compose$mcID$sp:(Lscala/Function1;Lscala/Function1;)Lscala/Function1;
	areturn
  Labels:
  LocalVariableTable: 
   Start  Length  Slot  Name   Signature
   0      6      0    this       Lscala/xml/transform/BasicTransformer;
   0      6      1    g       Lscala/Function1;


public scala.Function1 compose$mcLD$sp(scala.Function1);
  Signature: (Lscala/Function1;)Lscala/Function1;
  Code:
   Stack=2, Locals=2, Args_size=2
	aload_0
	aload_1
	invokestatic	Method scala/Function1$class.compose$mcLD$sp:(Lscala/Function1;Lscala/Function1;)Lscala/Function1;
	areturn
  Labels:
  LocalVariableTable: 
   Start  Length  Slot  Name   Signature
   0      6      0    this       Lscala/xml/transform/BasicTransformer;
   0      6      1    g       Lscala/Function1;


public scala.Function1 compose$mcDD$sp(scala.Function1);
  Signature: (Lscala/Function1;)Lscala/Function1;
  Code:
   Stack=2, Locals=2, Args_size=2
	aload_0
	aload_1
	invokestatic	Method scala/Function1$class.compose$mcDD$sp:(Lscala/Function1;Lscala/Function1;)Lscala/Function1;
	areturn
  Labels:
  LocalVariableTable: 
   Start  Length  Slot  Name   Signature
   0      6      0    this       Lscala/xml/transform/BasicTransformer;
   0      6      1    g       Lscala/Function1;


public scala.Function1 andThen(scala.Function1);
  Signature: (Lscala/Function1;)Lscala/Function1;
  Code:
   Stack=2, Locals=2, Args_size=2
	aload_0
	aload_1
	invokestatic	Method scala/Function1$class.andThen:(Lscala/Function1;Lscala/Function1;)Lscala/Function1;
	areturn
  Labels:
  LocalVariableTable: 
   Start  Length  Slot  Name   Signature
   0      6      0    this       Lscala/xml/transform/BasicTransformer;
   0      6      1    g       Lscala/Function1;


public scala.Function1 andThen$mcVI$sp(scala.Function1);
  Signature: (Lscala/Function1;)Lscala/Function1;
  Code:
   Stack=2, Locals=2, Args_size=2
	aload_0
	aload_1
	invokestatic	Method scala/Function1$class.andThen$mcVI$sp:(Lscala/Function1;Lscala/Function1;)Lscala/Function1;
	areturn
  Labels:
  LocalVariableTable: 
   Start  Length  Slot  Name   Signature
   0      6      0    this       Lscala/xml/transform/BasicTransformer;
   0      6      1    g       Lscala/Function1;


public scala.Function1 andThen$mcZI$sp(scala.Function1);
  Signature: (Lscala/Function1;)Lscala/Function1;
  Code:
   Stack=2, Locals=2, Args_size=2
	aload_0
	aload_1
	invokestatic	Method scala/Function1$class.andThen$mcZI$sp:(Lscala/Function1;Lscala/Function1;)Lscala/Function1;
	areturn
  Labels:
  LocalVariableTable: 
   Start  Length  Slot  Name   Signature
   0      6      0    this       Lscala/xml/transform/BasicTransformer;
   0      6      1    g       Lscala/Function1;


public scala.Function1 andThen$mcII$sp(scala.Function1);
  Signature: (Lscala/Function1;)Lscala/Function1;
  Code:
   Stack=2, Locals=2, Args_size=2
	aload_0
	aload_1
	invokestatic	Method scala/Function1$class.andThen$mcII$sp:(Lscala/Function1;Lscala/Function1;)Lscala/Function1;
	areturn
  Labels:
  LocalVariableTable: 
   Start  Length  Slot  Name   Signature
   0      6      0    this       Lscala/xml/transform/BasicTransformer;
   0      6      1    g       Lscala/Function1;


public scala.Function1 andThen$mcLI$sp(scala.Function1);
  Signature: (Lscala/Function1;)Lscala/Function1;
  Code:
   Stack=2, Locals=2, Args_size=2
	aload_0
	aload_1
	invokestatic	Method scala/Function1$class.andThen$mcLI$sp:(Lscala/Function1;Lscala/Function1;)Lscala/Function1;
	areturn
  Labels:
  LocalVariableTable: 
   Start  Length  Slot  Name   Signature
   0      6      0    this       Lscala/xml/transform/BasicTransformer;
   0      6      1    g       Lscala/Function1;


public scala.Function1 andThen$mcDI$sp(scala.Function1);
  Signature: (Lscala/Function1;)Lscala/Function1;
  Code:
   Stack=2, Locals=2, Args_size=2
	aload_0
	aload_1
	invokestatic	Method scala/Function1$class.andThen$mcDI$sp:(Lscala/Function1;Lscala/Function1;)Lscala/Function1;
	areturn
  Labels:
  LocalVariableTable: 
   Start  Length  Slot  Name   Signature
   0      6      0    this       Lscala/xml/transform/BasicTransformer;
   0      6      1    g       Lscala/Function1;


public scala.Function1 andThen$mcVL$sp(scala.Function1);
  Signature: (Lscala/Function1;)Lscala/Function1;
  Code:
   Stack=2, Locals=2, Args_size=2
	aload_0
	aload_1
	invokestatic	Method scala/Function1$class.andThen$mcVL$sp:(Lscala/Function1;Lscala/Function1;)Lscala/Function1;
	areturn
  Labels:
  LocalVariableTable: 
   Start  Length  Slot  Name   Signature
   0      6      0    this       Lscala/xml/transform/BasicTransformer;
   0      6      1    g       Lscala/Function1;


public scala.Function1 andThen$mcZL$sp(scala.Function1);
  Signature: (Lscala/Function1;)Lscala/Function1;
  Code:
   Stack=2, Locals=2, Args_size=2
	aload_0
	aload_1
	invokestatic	Method scala/Function1$class.andThen$mcZL$sp:(Lscala/Function1;Lscala/Function1;)Lscala/Function1;
	areturn
  Labels:
  LocalVariableTable: 
   Start  Length  Slot  Name   Signature
   0      6      0    this       Lscala/xml/transform/BasicTransformer;
   0      6      1    g       Lscala/Function1;


public scala.Function1 andThen$mcIL$sp(scala.Function1);
  Signature: (Lscala/Function1;)Lscala/Function1;
  Code:
   Stack=2, Locals=2, Args_size=2
	aload_0
	aload_1
	invokestatic	Method scala/Function1$class.andThen$mcIL$sp:(Lscala/Function1;Lscala/Function1;)Lscala/Function1;
	areturn
  Labels:
  LocalVariableTable: 
   Start  Length  Slot  Name   Signature
   0      6      0    this       Lscala/xml/transform/BasicTransformer;
   0      6      1    g       Lscala/Function1;


public scala.Function1 andThen$mcLL$sp(scala.Function1);
  Signature: (Lscala/Function1;)Lscala/Function1;
  Code:
   Stack=2, Locals=2, Args_size=2
	aload_0
	aload_1
	invokestatic	Method scala/Function1$class.andThen$mcLL$sp:(Lscala/Function1;Lscala/Function1;)Lscala/Function1;
	areturn
  Labels:
  LocalVariableTable: 
   Start  Length  Slot  Name   Signature
   0      6      0    this       Lscala/xml/transform/BasicTransformer;
   0      6      1    g       Lscala/Function1;


public scala.Function1 andThen$mcDL$sp(scala.Function1);
  Signature: (Lscala/Function1;)Lscala/Function1;
  Code:
   Stack=2, Locals=2, Args_size=2
	aload_0
	aload_1
	invokestatic	Method scala/Function1$class.andThen$mcDL$sp:(Lscala/Function1;Lscala/Function1;)Lscala/Function1;
	areturn
  Labels:
  LocalVariableTable: 
   Start  Length  Slot  Name   Signature
   0      6      0    this       Lscala/xml/transform/BasicTransformer;
   0      6      1    g       Lscala/Function1;


public scala.Function1 andThen$mcVD$sp(scala.Function1);
  Signature: (Lscala/Function1;)Lscala/Function1;
  Code:
   Stack=2, Locals=2, Args_size=2
	aload_0
	aload_1
	invokestatic	Method scala/Function1$class.andThen$mcVD$sp:(Lscala/Function1;Lscala/Function1;)Lscala/Function1;
	areturn
  Labels:
  LocalVariableTable: 
   Start  Length  Slot  Name   Signature
   0      6      0    this       Lscala/xml/transform/BasicTransformer;
   0      6      1    g       Lscala/Function1;


public scala.Function1 andThen$mcZD$sp(scala.Function1);
  Signature: (Lscala/Function1;)Lscala/Function1;
  Code:
   Stack=2, Locals=2, Args_size=2
	aload_0
	aload_1
	invokestatic	Method scala/Function1$class.andThen$mcZD$sp:(Lscala/Function1;Lscala/Function1;)Lscala/Function1;
	areturn
  Labels:
  LocalVariableTable: 
   Start  Length  Slot  Name   Signature
   0      6      0    this       Lscala/xml/transform/BasicTransformer;
   0      6      1    g       Lscala/Function1;


public scala.Function1 andThen$mcID$sp(scala.Function1);
  Signature: (Lscala/Function1;)Lscala/Function1;
  Code:
   Stack=2, Locals=2, Args_size=2
	aload_0
	aload_1
	invokestatic	Method scala/Function1$class.andThen$mcID$sp:(Lscala/Function1;Lscala/Function1;)Lscala/Function1;
	areturn
  Labels:
  LocalVariableTable: 
   Start  Length  Slot  Name   Signature
   0      6      0    this       Lscala/xml/transform/BasicTransformer;
   0      6      1    g       Lscala/Function1;


public scala.Function1 andThen$mcLD$sp(scala.Function1);
  Signature: (Lscala/Function1;)Lscala/Function1;
  Code:
   Stack=2, Locals=2, Args_size=2
	aload_0
	aload_1
	invokestatic	Method scala/Function1$class.andThen$mcLD$sp:(Lscala/Function1;Lscala/Function1;)Lscala/Function1;
	areturn
  Labels:
  LocalVariableTable: 
   Start  Length  Slot  Name   Signature
   0      6      0    this       Lscala/xml/transform/BasicTransformer;
   0      6      1    g       Lscala/Function1;


public scala.Function1 andThen$mcDD$sp(scala.Function1);
  Signature: (Lscala/Function1;)Lscala/Function1;
  Code:
   Stack=2, Locals=2, Args_size=2
	aload_0
	aload_1
	invokestatic	Method scala/Function1$class.andThen$mcDD$sp:(Lscala/Function1;Lscala/Function1;)Lscala/Function1;
	areturn
  Labels:
  LocalVariableTable: 
   Start  Length  Slot  Name   Signature
   0      6      0    this       Lscala/xml/transform/BasicTransformer;
   0      6      1    g       Lscala/Function1;


public boolean unchanged(scala.xml.Node, scala.collection.Seq);
  Signature: (Lscala/xml/Node;Lscala/collection/Seq;)Z
  Code:
   Stack=2, Locals=3, Args_size=3
	aload_2
	invokeinterface	InterfaceMethod scala/collection/SeqLike.length:()I
	iconst_1
	if_icmpne	l1 // iconst_0
	aload_2
	invokeinterface	InterfaceMethod scala/collection/IterableLike.head:()Ljava/lang/Object;
	dup
	ifnonnull	l2 // aload_1
	pop
	aload_1
	ifnull	l3 // iconst_1
	goto	l1 // iconst_0
l2	aload_1
	invokevirtual	Method java/lang/Object.equals:(Ljava/lang/Object;)Z
	ifeq	l1 // iconst_0
l3	iconst_1
	goto	l4 // ireturn
l1	iconst_0
l4	ireturn
  Labels:
   	l2 = 28 // aload_1
   	l3 = 35 // iconst_1
   	l1 = 39 // iconst_0
   	l4 = 40 // ireturn
  LocalVariableTable: 
   Start  Length  Slot  Name   Signature
   0      41      0    this       Lscala/xml/transform/BasicTransformer;
   0      41      1    n       Lscala/xml/Node;
   0      41      2    ns       Lscala/collection/Seq;

  Signature: length = 0x2
   00 FFFFFFDA 

public scala.collection.Seq transform(scala.collection.Iterator, scala.xml.NodeBuffer);
  Signature: (Lscala/collection/Iterator;Lscala/xml/NodeBuffer;)Lscala/collection/Seq;
  Code:
   Stack=5, Locals=3, Args_size=3
	aload_1
	aload_2
	new	class scala/xml/transform/BasicTransformer$$anonfun$transform$1
	dup
	aload_0
	invokespecial	Method scala/xml/transform/BasicTransformer$$anonfun$transform$1."<init>":(Lscala/xml/transform/BasicTransformer;)V
	invokeinterface	InterfaceMethod scala/collection/TraversableOnce.foldLeft:(Ljava/lang/Object;Lscala/Function2;)Ljava/lang/Object;
	checkcast	class scala/collection/SeqLike
	invokeinterface	InterfaceMethod scala/collection/SeqLike.toSeq:()Lscala/collection/Seq;
	areturn
  Labels:
  LocalVariableTable: 
   Start  Length  Slot  Name   Signature
   0      24      0    this       Lscala/xml/transform/BasicTransformer;
   0      24      1    it       Lscala/collection/Iterator;
   0      24      2    nb       Lscala/xml/NodeBuffer;

  Signature: length = 0x2
   00 FFFFFFF2 

public scala.collection.Seq transform(scala.collection.Seq);
  Signature: (Lscala/collection/Seq;)Lscala/collection/Seq;
  Code:
   Stack=5, Locals=8, Args_size=2
	aload_1
	new	class scala/xml/transform/BasicTransformer$$anonfun$1
	dup
	aload_0
	invokespecial	Method scala/xml/transform/BasicTransformer$$anonfun$1."<init>":(Lscala/xml/transform/BasicTransformer;)V
	invokeinterface	InterfaceMethod scala/collection/TraversableLike.span:(Lscala/Function1;)Lscala/Tuple2;
	astore	7
	aload	7
	ifnull	l1 // new
	new	class scala/Tuple2
	dup
	aload	7
	invokevirtual	Method scala/Tuple2._1:()Ljava/lang/Object;
	aload	7
	invokevirtual	Method scala/Tuple2._2:()Ljava/lang/Object;
	invokespecial	Method scala/Tuple2."<init>":(Ljava/lang/Object;Ljava/lang/Object;)V
	astore_2
	aload_2
	invokevirtual	Method scala/Tuple2._1:()Ljava/lang/Object;
	checkcast	class scala/collection/Seq
	astore_3
	aload_2
	invokevirtual	Method scala/Tuple2._2:()Ljava/lang/Object;
	checkcast	class scala/collection/Seq
	astore	5
	aload	5
	invokeinterface	InterfaceMethod scala/collection/IterableLike.isEmpty:()Z
	ifeq	l2 // aload_3
	aload_1
	goto	l3 // areturn
l2	aload_3
	aload_0
	aload	5
	invokeinterface	InterfaceMethod scala/collection/IterableLike.head:()Ljava/lang/Object;
	checkcast	class scala/xml/Node
	invokevirtual	Method transform:(Lscala/xml/Node;)Lscala/collection/Seq;
	getstatic	Field scala/collection/Seq$.MODULE$:Lscala/collection/Seq$;
	astore	4
	new	class scala/collection/generic/TraversableFactory$GenericCanBuildFrom
	dup
	aload	4
	invokespecial	Method scala/collection/generic/TraversableFactory$GenericCanBuildFrom."<init>":(Lscala/collection/generic/TraversableFactory;)V
	invokeinterface	InterfaceMethod scala/collection/TraversableLike.$plus$plus:(Lscala/collection/TraversableOnce;Lscala/collection/generic/CanBuildFrom;)Ljava/lang/Object;
	checkcast	class scala/collection/TraversableLike
	aload_0
	aload	5
	invokeinterface	InterfaceMethod scala/collection/TraversableLike.tail:()Ljava/lang/Object;
	checkcast	class scala/collection/Seq
	invokevirtual	Method transform:(Lscala/collection/Seq;)Lscala/collection/Seq;
	getstatic	Field scala/collection/Seq$.MODULE$:Lscala/collection/Seq$;
	astore	6
	new	class scala/collection/generic/TraversableFactory$GenericCanBuildFrom
	dup
	aload	6
	invokespecial	Method scala/collection/generic/TraversableFactory$GenericCanBuildFrom."<init>":(Lscala/collection/generic/TraversableFactory;)V
	invokeinterface	InterfaceMethod scala/collection/TraversableLike.$plus$plus:(Lscala/collection/TraversableOnce;Lscala/collection/generic/CanBuildFrom;)Ljava/lang/Object;
	checkcast	class scala/collection/Seq
l3	areturn
l1	new	class scala/MatchError
	dup
	aload	7
	invokespecial	Method scala/MatchError."<init>":(Ljava/lang/Object;)V
	athrow
  Labels:
   	l2 = 70 // aload_3
   	l3 = 143 // areturn
   	l1 = 144 // new
  LocalVariableTable: 
   Start  Length  Slot  Name   Signature
   0      154      0    this       Lscala/xml/transform/BasicTransformer;
   0      154      1    ns       Lscala/collection/Seq;
   47      97      3    xs1       Lscala/collection/Seq;
   56      88      5    xs2       Lscala/collection/Seq;
   16      50      7    temp1       Lscala/Tuple2;
   144      10      7    temp1       Lscala/Tuple2;

  Signature: length = 0x2
   01 32 

public scala.collection.Seq transform(scala.xml.Node);
  Signature: (Lscala/xml/Node;)Lscala/collection/Seq;
  Code:
   Stack=7, Locals=9, Args_size=2
	aload_1
	invokevirtual	Method scala/xml/Node.doTransform:()Z
	ifeq	l1 // aload_1
	aload_1
	instanceof	class scala/xml/Group
	ifeq	l2 // aload_1
	new	class scala/xml/Group
	dup
	aload_0
	aload_1
	checkcast	class scala/xml/Group
	astore_2
	aload_2
	getfield	Field scala/xml/Group.nodes:Lscala/collection/Seq;
	invokevirtual	Method transform:(Lscala/collection/Seq;)Lscala/collection/Seq;
	invokespecial	Method scala/xml/Group."<init>":(Lscala/collection/Seq;)V
	goto	l3 // areturn
l2	aload_1
	invokevirtual	Method scala/xml/Node.child:()Lscala/collection/Seq;
	astore_3
	aload_0
	aload_3
	invokevirtual	Method transform:(Lscala/collection/Seq;)Lscala/collection/Seq;
	astore	8
	aload_3
	aload	8
	if_acmpne	l4 // aload_1
	aload_1
	goto	l3 // areturn
l4	aload_1
	invokevirtual	Method scala/xml/Node.prefix:()Ljava/lang/String;
	aload_1
	invokevirtual	Method scala/xml/Node.label:()Ljava/lang/String;
	aload_1
	invokevirtual	Method scala/xml/Node.attributes:()Lscala/xml/MetaData;
	aload_1
	invokevirtual	Method scala/xml/Node.scope:()Lscala/xml/NamespaceBinding;
	astore	7
	astore	6
	astore	5
	astore	4
	new	class scala/xml/Elem
	dup
	aload	4
	aload	5
	aload	6
	aload	7
	aload	8
	invokespecial	Method scala/xml/Elem."<init>":(Ljava/lang/String;Ljava/lang/String;Lscala/xml/MetaData;Lscala/xml/NamespaceBinding;Lscala/collection/Seq;)V
	goto	l3 // areturn
l1	aload_1
l3	areturn
  Labels:
   	l2 = 37 // aload_1
   	l4 = 59 // aload_1
   	l1 = 103 // aload_1
   	l3 = 104 // areturn
  LocalVariableTable: 
   Start  Length  Slot  Name   Signature
   0      105      0    this       Lscala/xml/transform/BasicTransformer;
   0      105      1    n       Lscala/xml/Node;
   42      61      3    ch       Lscala/collection/Seq;
   49      54      8    nch       Lscala/collection/Seq;

  Signature: length = 0x2
   01 56 

public scala.xml.Node apply(scala.xml.Node);
  Signature: (Lscala/xml/Node;)Lscala/xml/Node;
  Code:
   Stack=3, Locals=3, Args_size=2
	aload_0
	aload_1
	invokevirtual	Method transform:(Lscala/xml/Node;)Lscala/collection/Seq;
	astore_2
	aload_2
	invokeinterface	InterfaceMethod scala/collection/SeqLike.length:()I
	iconst_1
	if_icmple	l1 // aload_2
	new	class java/lang/UnsupportedOperationException
	dup
	ldc_w	String transform must return single node for root
	invokespecial	Method java/lang/UnsupportedOperationException."<init>":(Ljava/lang/String;)V
	athrow
l1	aload_2
	invokeinterface	InterfaceMethod scala/collection/IterableLike.head:()Ljava/lang/Object;
	checkcast	class scala/xml/Node
	areturn
  Labels:
   	l1 = 27 // aload_2
  LocalVariableTable: 
   Start  Length  Slot  Name   Signature
   0      37      0    this       Lscala/xml/transform/BasicTransformer;
   0      37      1    n       Lscala/xml/Node;
   6      31      2    seq       Lscala/collection/Seq;


public java.lang.Object apply(java.lang.Object);
  Signature: (Ljava/lang/Object;)Ljava/lang/Object;
  Code:
   Stack=2, Locals=2, Args_size=2
	aload_0
	aload_1
	checkcast	class scala/xml/Node
	invokevirtual	Method apply:(Lscala/xml/Node;)Lscala/xml/Node;
	areturn
  Labels:
  LocalVariableTable: 
   Start  Length  Slot  Name   Signature
   0      9      0    this       Lscala/xml/transform/BasicTransformer;
   0      9      1    v1       Ljava/lang/Object;


public scala.xml.transform.BasicTransformer();
  Signature: ()V
  Code:
   Stack=1, Locals=1, Args_size=1
	aload_0
	invokespecial	Method java/lang/Object."<init>":()V
	aload_0
	invokestatic	Method scala/Function1$class.$init$:(Lscala/Function1;)V
	return
  Labels:

}

