Compiled from "BasicTransformer.scala"
public final class scala.xml.transform.BasicTransformer$$anonfun$1 extends java.lang.Object implements scala.Function1,scala.ScalaObject,java.io.Serializable
  SourceFile: "BasicTransformer.scala"
  Scala: length = 0x
   
  InnerClass: 
   public final $anonfun$1=class scala/xml/transform/BasicTransformer$$anonfun$1 of class scala/xml/transform/BasicTransformer
  minor version: 0
  major version: 49
  Constant pool:
Asciz	SourceFile;
Asciz	BasicTransformer.scala;
Asciz	<clinit>;
Asciz	()V;
Asciz	Code;
Asciz	serialVersionUID;
Asciz	J;
Asciz	scala/xml/transform/BasicTransformer$$anonfun$1;
class	scala/xml/transform/BasicTransformer$$anonfun$1
NameAndType	serialVersionUID:J
Field	scala/xml/transform/BasicTransformer$$anonfun$1.serialVersionUID:J
Asciz	$outer;
Asciz	Lscala/xml/transform/BasicTransformer;;
Asciz	<init>;
Asciz	(Lscala/xml/transform/BasicTransformer;)V;
Asciz	LineNumberTable;
Asciz	java/lang/NullPointerException;
class	java/lang/NullPointerException
NameAndType	"<init>":()V
Method	java/lang/NullPointerException."<init>":()V
NameAndType	$outer:Lscala/xml/transform/BasicTransformer;
Field	scala/xml/transform/BasicTransformer$$anonfun$1.$outer:Lscala/xml/transform/BasicTransformer;
Asciz	java/lang/Object;
class	java/lang/Object
Method	java/lang/Object."<init>":()V
Asciz	scala/Function1$class;
class	scala/Function1$class
Asciz	$init$;
Asciz	(Lscala/Function1;)V;
NameAndType	$init$:(Lscala/Function1;)V
Method	scala/Function1$class.$init$:(Lscala/Function1;)V
Asciz	this;
Asciz	Lscala/xml/transform/BasicTransformer$$anonfun$1;;
Asciz	LocalVariableTable;
Asciz	apply;
Asciz	(Ljava/lang/Object;)Ljava/lang/Object;;
Asciz	scala/xml/Node;
class	scala/xml/Node
Asciz	(Lscala/xml/Node;)Z;
NameAndType	apply:(Lscala/xml/Node;)Z
Method	scala/xml/transform/BasicTransformer$$anonfun$1.apply:(Lscala/xml/Node;)Z
Asciz	scala/runtime/BoxesRunTime;
class	scala/runtime/BoxesRunTime
Asciz	boxToBoolean;
Asciz	(Z)Ljava/lang/Boolean;;
NameAndType	boxToBoolean:(Z)Ljava/lang/Boolean;
Method	scala/runtime/BoxesRunTime.boxToBoolean:(Z)Ljava/lang/Boolean;
Asciz	v1;
Asciz	Ljava/lang/Object;;
Asciz	scala/xml/transform/BasicTransformer;
class	scala/xml/transform/BasicTransformer
Asciz	transform;
Asciz	(Lscala/xml/Node;)Lscala/collection/Seq;;
NameAndType	transform:(Lscala/xml/Node;)Lscala/collection/Seq;
Method	scala/xml/transform/BasicTransformer.transform:(Lscala/xml/Node;)Lscala/collection/Seq;
Asciz	unchanged;
Asciz	(Lscala/xml/Node;Lscala/collection/Seq;)Z;
NameAndType	unchanged:(Lscala/xml/Node;Lscala/collection/Seq;)Z
Method	scala/xml/transform/BasicTransformer.unchanged:(Lscala/xml/Node;Lscala/collection/Seq;)Z
Asciz	n;
Asciz	Lscala/xml/Node;;
Asciz	andThen;
Asciz	(Lscala/Function1;)Lscala/Function1;;
Asciz	(Lscala/Function1;Lscala/Function1;)Lscala/Function1;;
NameAndType	andThen:(Lscala/Function1;Lscala/Function1;)Lscala/Function1;
Method	scala/Function1$class.andThen:(Lscala/Function1;Lscala/Function1;)Lscala/Function1;
Asciz	g;
Asciz	Lscala/Function1;;
Asciz	compose;
NameAndType	compose:(Lscala/Function1;Lscala/Function1;)Lscala/Function1;
Method	scala/Function1$class.compose:(Lscala/Function1;Lscala/Function1;)Lscala/Function1;
Asciz	toString;
Asciz	()Ljava/lang/String;;
Asciz	(Lscala/Function1;)Ljava/lang/String;;
NameAndType	toString:(Lscala/Function1;)Ljava/lang/String;
Method	scala/Function1$class.toString:(Lscala/Function1;)Ljava/lang/String;
Asciz	Scala;
Asciz	InnerClasses;
Asciz	$anonfun$1;
Asciz	scala/Function1;
class	scala/Function1
Asciz	scala/ScalaObject;
class	scala/ScalaObject
Asciz	java/io/Serializable;
class	java/io/Serializable

{
public static final long serialVersionUID;
  Signature: J

private final scala.xml.transform.BasicTransformer $outer;
  Signature: Lscala/xml/transform/BasicTransformer;

public static {};
  Signature: ()V
  Code:
   Stack=2, Locals=0, Args_size=0
	lconst_0
	putstatic	Field serialVersionUID:J
	return
  Labels:

public scala.xml.transform.BasicTransformer$$anonfun$1(scala.xml.transform.BasicTransformer);
  Signature: (Lscala/xml/transform/BasicTransformer;)V
  Code:
   Stack=2, Locals=2, Args_size=2
	aload_1
	ifnonnull	l1 // aload_0
	new	class java/lang/NullPointerException
	dup
	invokespecial	Method java/lang/NullPointerException."<init>":()V
	athrow
l1	aload_0
	aload_1
	putfield	Field $outer:Lscala/xml/transform/BasicTransformer;
	aload_0
	invokespecial	Method java/lang/Object."<init>":()V
	aload_0
	invokestatic	Method scala/Function1$class.$init$:(Lscala/Function1;)V
	return
  Labels:
   	l1 = 12 // aload_0
  LocalVariableTable: 
   Start  Length  Slot  Name   Signature
   0      26      0    this       Lscala/xml/transform/BasicTransformer$$anonfun$1;
   0      26      1    $outer       Lscala/xml/transform/BasicTransformer;


public final java.lang.Object apply(java.lang.Object);
  Signature: (Ljava/lang/Object;)Ljava/lang/Object;
  Code:
   Stack=2, Locals=4, Args_size=2
	aload_0
	getfield	Field $outer:Lscala/xml/transform/BasicTransformer;
	astore_3
	aload_0
	aload_1
	checkcast	class scala/xml/Node
	invokevirtual	Method apply:(Lscala/xml/Node;)Z
	istore_2
	iload_2
	invokestatic	Method scala/runtime/BoxesRunTime.boxToBoolean:(Z)Ljava/lang/Boolean;
	areturn
  Labels:
  LocalVariableTable: 
   Start  Length  Slot  Name   Signature
   0      19      0    this       Lscala/xml/transform/BasicTransformer$$anonfun$1;
   5      14      1    v1       Ljava/lang/Object;


public final boolean apply(scala.xml.Node);
  Signature: (Lscala/xml/Node;)Z
  Code:
   Stack=4, Locals=3, Args_size=2
	aload_0
	getfield	Field $outer:Lscala/xml/transform/BasicTransformer;
	astore_2
	aload_0
	getfield	Field $outer:Lscala/xml/transform/BasicTransformer;
	aload_1
	aload_0
	getfield	Field $outer:Lscala/xml/transform/BasicTransformer;
	aload_1
	invokevirtual	Method scala/xml/transform/BasicTransformer.transform:(Lscala/xml/Node;)Lscala/collection/Seq;
	invokevirtual	Method scala/xml/transform/BasicTransformer.unchanged:(Lscala/xml/Node;Lscala/collection/Seq;)Z
	ireturn
  Labels:
  LocalVariableTable: 
   Start  Length  Slot  Name   Signature
   0      22      0    this       Lscala/xml/transform/BasicTransformer$$anonfun$1;
   5      17      1    n       Lscala/xml/Node;


public scala.Function1 andThen(scala.Function1);
  Signature: (Lscala/Function1;)Lscala/Function1;
  Code:
   Stack=2, Locals=2, Args_size=2
	aload_0
	aload_1
	invokestatic	Method scala/Function1$class.andThen:(Lscala/Function1;Lscala/Function1;)Lscala/Function1;
	areturn
  Labels:
  LocalVariableTable: 
   Start  Length  Slot  Name   Signature
   0      6      0    this       Lscala/xml/transform/BasicTransformer$$anonfun$1;
   0      6      1    g       Lscala/Function1;


public scala.Function1 compose(scala.Function1);
  Signature: (Lscala/Function1;)Lscala/Function1;
  Code:
   Stack=2, Locals=2, Args_size=2
	aload_0
	aload_1
	invokestatic	Method scala/Function1$class.compose:(Lscala/Function1;Lscala/Function1;)Lscala/Function1;
	areturn
  Labels:
  LocalVariableTable: 
   Start  Length  Slot  Name   Signature
   0      6      0    this       Lscala/xml/transform/BasicTransformer$$anonfun$1;
   0      6      1    g       Lscala/Function1;


public java.lang.String toString();
  Signature: ()Ljava/lang/String;
  Code:
   Stack=1, Locals=1, Args_size=1
	aload_0
	invokestatic	Method scala/Function1$class.toString:(Lscala/Function1;)Ljava/lang/String;
	areturn
  Labels:

}

