Compiled from "BasicTransformer.scala"
public final class scala.xml.transform.BasicTransformer$$anonfun$transform$1 extends scala.runtime.AbstractFunction2 implements java.io.Serializable
  SourceFile: "BasicTransformer.scala"
  Scala: length = 0x
   
  InnerClass: 
   public final $anonfun$transform$1=class scala/xml/transform/BasicTransformer$$anonfun$transform$1 of class scala/xml/transform/BasicTransformer
  minor version: 0
  major version: 49
  Constant pool:
Asciz	SourceFile;
Asciz	BasicTransformer.scala;
Asciz	<clinit>;
Asciz	()V;
Asciz	Code;
Asciz	serialVersionUID;
Asciz	J;
Asciz	scala/xml/transform/BasicTransformer$$anonfun$transform$1;
class	scala/xml/transform/BasicTransformer$$anonfun$transform$1
NameAndType	serialVersionUID:J
Field	scala/xml/transform/BasicTransformer$$anonfun$transform$1.serialVersionUID:J
Asciz	$outer;
Asciz	Lscala/xml/transform/BasicTransformer;;
Asciz	<init>;
Asciz	(Lscala/xml/transform/BasicTransformer;)V;
Asciz	LineNumberTable;
Asciz	java/lang/NullPointerException;
class	java/lang/NullPointerException
NameAndType	"<init>":()V
Method	java/lang/NullPointerException."<init>":()V
NameAndType	$outer:Lscala/xml/transform/BasicTransformer;
Field	scala/xml/transform/BasicTransformer$$anonfun$transform$1.$outer:Lscala/xml/transform/BasicTransformer;
Asciz	scala/runtime/AbstractFunction2;
class	scala/runtime/AbstractFunction2
Method	scala/runtime/AbstractFunction2."<init>":()V
Asciz	this;
Asciz	Lscala/xml/transform/BasicTransformer$$anonfun$transform$1;;
Asciz	LocalVariableTable;
Asciz	apply;
Asciz	(Ljava/lang/Object;Ljava/lang/Object;)Ljava/lang/Object;;
Asciz	scala/xml/NodeBuffer;
class	scala/xml/NodeBuffer
Asciz	scala/xml/Node;
class	scala/xml/Node
Asciz	(Lscala/xml/NodeBuffer;Lscala/xml/Node;)Lscala/xml/NodeBuffer;;
NameAndType	apply:(Lscala/xml/NodeBuffer;Lscala/xml/Node;)Lscala/xml/NodeBuffer;
Method	scala/xml/transform/BasicTransformer$$anonfun$transform$1.apply:(Lscala/xml/NodeBuffer;Lscala/xml/Node;)Lscala/xml/NodeBuffer;
Asciz	v1;
Asciz	Ljava/lang/Object;;
Asciz	v2;
Asciz	scala/xml/transform/BasicTransformer;
class	scala/xml/transform/BasicTransformer
Asciz	transform;
Asciz	(Lscala/xml/Node;)Lscala/collection/Seq;;
NameAndType	transform:(Lscala/xml/Node;)Lscala/collection/Seq;
Method	scala/xml/transform/BasicTransformer.transform:(Lscala/xml/Node;)Lscala/collection/Seq;
Asciz	$plus$plus$eq;
Asciz	(Lscala/collection/Traversable;)Lscala/collection/mutable/ArrayBuffer;;
NameAndType	$plus$plus$eq:(Lscala/collection/Traversable;)Lscala/collection/mutable/ArrayBuffer;
Method	scala/xml/NodeBuffer.$plus$plus$eq:(Lscala/collection/Traversable;)Lscala/collection/mutable/ArrayBuffer;
Asciz	Scala;
Asciz	InnerClasses;
Asciz	$anonfun$transform$1;
Asciz	java/io/Serializable;
class	java/io/Serializable

{
public static final long serialVersionUID;
  Signature: J

private final scala.xml.transform.BasicTransformer $outer;
  Signature: Lscala/xml/transform/BasicTransformer;

public static {};
  Signature: ()V
  Code:
   Stack=2, Locals=0, Args_size=0
	lconst_0
	putstatic	Field serialVersionUID:J
	return
  Labels:

public scala.xml.transform.BasicTransformer$$anonfun$transform$1(scala.xml.transform.BasicTransformer);
  Signature: (Lscala/xml/transform/BasicTransformer;)V
  Code:
   Stack=2, Locals=2, Args_size=2
	aload_1
	ifnonnull	l1 // aload_0
	new	class java/lang/NullPointerException
	dup
	invokespecial	Method java/lang/NullPointerException."<init>":()V
	athrow
l1	aload_0
	aload_1
	putfield	Field $outer:Lscala/xml/transform/BasicTransformer;
	aload_0
	invokespecial	Method scala/runtime/AbstractFunction2."<init>":()V
	return
  Labels:
   	l1 = 12 // aload_0
  LocalVariableTable: 
   Start  Length  Slot  Name   Signature
   0      22      0    this       Lscala/xml/transform/BasicTransformer$$anonfun$transform$1;
   0      22      1    $outer       Lscala/xml/transform/BasicTransformer;


public final java.lang.Object apply(java.lang.Object, java.lang.Object);
  Signature: (Ljava/lang/Object;Ljava/lang/Object;)Ljava/lang/Object;
  Code:
   Stack=3, Locals=3, Args_size=3
	aload_0
	aload_1
	checkcast	class scala/xml/NodeBuffer
	aload_2
	checkcast	class scala/xml/Node
	invokevirtual	Method apply:(Lscala/xml/NodeBuffer;Lscala/xml/Node;)Lscala/xml/NodeBuffer;
	areturn
  Labels:
  LocalVariableTable: 
   Start  Length  Slot  Name   Signature
   0      13      0    this       Lscala/xml/transform/BasicTransformer$$anonfun$transform$1;
   0      13      1    v1       Ljava/lang/Object;
   0      13      2    v2       Ljava/lang/Object;


public final scala.xml.NodeBuffer apply(scala.xml.NodeBuffer, scala.xml.Node);
  Signature: (Lscala/xml/NodeBuffer;Lscala/xml/Node;)Lscala/xml/NodeBuffer;
  Code:
   Stack=3, Locals=3, Args_size=3
	aload_1
	aload_0
	getfield	Field $outer:Lscala/xml/transform/BasicTransformer;
	aload_2
	invokevirtual	Method scala/xml/transform/BasicTransformer.transform:(Lscala/xml/Node;)Lscala/collection/Seq;
	invokevirtual	Method scala/xml/NodeBuffer.$plus$plus$eq:(Lscala/collection/Traversable;)Lscala/collection/mutable/ArrayBuffer;
	checkcast	class scala/xml/NodeBuffer
	areturn
  Labels:

}

