Compiled from "BasicTransformer.scala"
public final class scala.xml.transform.BasicTransformer$$anonfun$1 extends java.lang.Object implements scala.Function1,scala.ScalaObject,java.io.Serializable
  SourceFile: "BasicTransformer.scala"
  Scala: length = 0x
   
  InnerClass: 
   public final #79= #9 of #51; //$anonfun$1=class scala/xml/transform/BasicTransformer$$anonfun$1 of class scala/xml/transform/BasicTransformer
  minor version: 0
  major version: 49
  Constant pool:
const #1 = Asciz	SourceFile;
const #2 = Asciz	BasicTransformer.scala;
const #3 = Asciz	<clinit>;
const #4 = Asciz	()V;
const #5 = Asciz	Code;
const #6 = Asciz	serialVersionUID;
const #7 = Asciz	J;
const #8 = Asciz	scala/xml/transform/BasicTransformer$$anonfun$1;
const #9 = class	#8;	//  scala/xml/transform/BasicTransformer$$anonfun$1
const #10 = NameAndType	#6:#7;//  serialVersionUID:J
const #11 = Field	#9.#10;	//  scala/xml/transform/BasicTransformer$$anonfun$1.serialVersionUID:J
const #12 = Asciz	$outer;
const #13 = Asciz	Lscala/xml/transform/BasicTransformer;;
const #14 = Asciz	<init>;
const #15 = Asciz	(Lscala/xml/transform/BasicTransformer;)V;
const #16 = Asciz	LineNumberTable;
const #17 = Asciz	java/lang/NullPointerException;
const #18 = class	#17;	//  java/lang/NullPointerException
const #19 = NameAndType	#14:#4;//  "<init>":()V
const #20 = Method	#18.#19;	//  java/lang/NullPointerException."<init>":()V
const #21 = NameAndType	#12:#13;//  $outer:Lscala/xml/transform/BasicTransformer;
const #22 = Field	#9.#21;	//  scala/xml/transform/BasicTransformer$$anonfun$1.$outer:Lscala/xml/transform/BasicTransformer;
const #23 = Asciz	java/lang/Object;
const #24 = class	#23;	//  java/lang/Object
const #25 = Method	#24.#19;	//  java/lang/Object."<init>":()V
const #26 = Asciz	scala/Function1$class;
const #27 = class	#26;	//  scala/Function1$class
const #28 = Asciz	$init$;
const #29 = Asciz	(Lscala/Function1;)V;
const #30 = NameAndType	#28:#29;//  $init$:(Lscala/Function1;)V
const #31 = Method	#27.#30;	//  scala/Function1$class.$init$:(Lscala/Function1;)V
const #32 = Asciz	this;
const #33 = Asciz	Lscala/xml/transform/BasicTransformer$$anonfun$1;;
const #34 = Asciz	LocalVariableTable;
const #35 = Asciz	apply;
const #36 = Asciz	(Ljava/lang/Object;)Ljava/lang/Object;;
const #37 = Asciz	scala/xml/Node;
const #38 = class	#37;	//  scala/xml/Node
const #39 = Asciz	(Lscala/xml/Node;)Z;
const #40 = NameAndType	#35:#39;//  apply:(Lscala/xml/Node;)Z
const #41 = Method	#9.#40;	//  scala/xml/transform/BasicTransformer$$anonfun$1.apply:(Lscala/xml/Node;)Z
const #42 = Asciz	scala/runtime/BoxesRunTime;
const #43 = class	#42;	//  scala/runtime/BoxesRunTime
const #44 = Asciz	boxToBoolean;
const #45 = Asciz	(Z)Ljava/lang/Boolean;;
const #46 = NameAndType	#44:#45;//  boxToBoolean:(Z)Ljava/lang/Boolean;
const #47 = Method	#43.#46;	//  scala/runtime/BoxesRunTime.boxToBoolean:(Z)Ljava/lang/Boolean;
const #48 = Asciz	v1;
const #49 = Asciz	Ljava/lang/Object;;
const #50 = Asciz	scala/xml/transform/BasicTransformer;
const #51 = class	#50;	//  scala/xml/transform/BasicTransformer
const #52 = Asciz	transform;
const #53 = Asciz	(Lscala/xml/Node;)Lscala/collection/Seq;;
const #54 = NameAndType	#52:#53;//  transform:(Lscala/xml/Node;)Lscala/collection/Seq;
const #55 = Method	#51.#54;	//  scala/xml/transform/BasicTransformer.transform:(Lscala/xml/Node;)Lscala/collection/Seq;
const #56 = Asciz	unchanged;
const #57 = Asciz	(Lscala/xml/Node;Lscala/collection/Seq;)Z;
const #58 = NameAndType	#56:#57;//  unchanged:(Lscala/xml/Node;Lscala/collection/Seq;)Z
const #59 = Method	#51.#58;	//  scala/xml/transform/BasicTransformer.unchanged:(Lscala/xml/Node;Lscala/collection/Seq;)Z
const #60 = Asciz	n;
const #61 = Asciz	Lscala/xml/Node;;
const #62 = Asciz	andThen;
const #63 = Asciz	(Lscala/Function1;)Lscala/Function1;;
const #64 = Asciz	(Lscala/Function1;Lscala/Function1;)Lscala/Function1;;
const #65 = NameAndType	#62:#64;//  andThen:(Lscala/Function1;Lscala/Function1;)Lscala/Function1;
const #66 = Method	#27.#65;	//  scala/Function1$class.andThen:(Lscala/Function1;Lscala/Function1;)Lscala/Function1;
const #67 = Asciz	g;
const #68 = Asciz	Lscala/Function1;;
const #69 = Asciz	compose;
const #70 = NameAndType	#69:#64;//  compose:(Lscala/Function1;Lscala/Function1;)Lscala/Function1;
const #71 = Method	#27.#70;	//  scala/Function1$class.compose:(Lscala/Function1;Lscala/Function1;)Lscala/Function1;
const #72 = Asciz	toString;
const #73 = Asciz	()Ljava/lang/String;;
const #74 = Asciz	(Lscala/Function1;)Ljava/lang/String;;
const #75 = NameAndType	#72:#74;//  toString:(Lscala/Function1;)Ljava/lang/String;
const #76 = Method	#27.#75;	//  scala/Function1$class.toString:(Lscala/Function1;)Ljava/lang/String;
const #77 = Asciz	Scala;
const #78 = Asciz	InnerClasses;
const #79 = Asciz	$anonfun$1;
const #80 = Asciz	scala/Function1;
const #81 = class	#80;	//  scala/Function1
const #82 = Asciz	scala/ScalaObject;
const #83 = class	#82;	//  scala/ScalaObject
const #84 = Asciz	java/io/Serializable;
const #85 = class	#84;	//  java/io/Serializable

{
public static final long serialVersionUID;

public static {};
  Code:
   Stack=2, Locals=0, Args_size=0
   0:	lconst_0
   1:	putstatic	#11; //Field serialVersionUID:J
   4:	return

public scala.xml.transform.BasicTransformer$$anonfun$1(scala.xml.transform.BasicTransformer);
  Code:
   Stack=2, Locals=2, Args_size=2
   0:	aload_1
   1:	ifnonnull	12
   4:	new	#18; //class java/lang/NullPointerException
   7:	dup
   8:	invokespecial	#20; //Method java/lang/NullPointerException."<init>":()V
   11:	athrow
   12:	aload_0
   13:	aload_1
   14:	putfield	#22; //Field $outer:Lscala/xml/transform/BasicTransformer;
   17:	aload_0
   18:	invokespecial	#25; //Method java/lang/Object."<init>":()V
   21:	aload_0
   22:	invokestatic	#31; //Method scala/Function1$class.$init$:(Lscala/Function1;)V
   25:	return
  LineNumberTable: 
   line 40: 0

  LocalVariableTable: 
   Start  Length  Slot  Name   Signature
   0      26      0    this       Lscala/xml/transform/BasicTransformer$$anonfun$1;
   0      26      1    $outer       Lscala/xml/transform/BasicTransformer;


public final java.lang.Object apply(java.lang.Object);
  Code:
   Stack=2, Locals=4, Args_size=2
   0:	aload_0
   1:	getfield	#22; //Field $outer:Lscala/xml/transform/BasicTransformer;
   4:	astore_3
   5:	aload_0
   6:	aload_1
   7:	checkcast	#38; //class scala/xml/Node
   10:	invokevirtual	#41; //Method apply:(Lscala/xml/Node;)Z
   13:	istore_2
   14:	iload_2
   15:	invokestatic	#47; //Method scala/runtime/BoxesRunTime.boxToBoolean:(Z)Ljava/lang/Boolean;
   18:	areturn
  LineNumberTable: 
   line 40: 0

  LocalVariableTable: 
   Start  Length  Slot  Name   Signature
   0      19      0    this       Lscala/xml/transform/BasicTransformer$$anonfun$1;
   5      14      1    v1       Ljava/lang/Object;


public final boolean apply(scala.xml.Node);
  Code:
   Stack=4, Locals=3, Args_size=2
   0:	aload_0
   1:	getfield	#22; //Field $outer:Lscala/xml/transform/BasicTransformer;
   4:	astore_2
   5:	aload_0
   6:	getfield	#22; //Field $outer:Lscala/xml/transform/BasicTransformer;
   9:	aload_1
   10:	aload_0
   11:	getfield	#22; //Field $outer:Lscala/xml/transform/BasicTransformer;
   14:	aload_1
   15:	invokevirtual	#55; //Method scala/xml/transform/BasicTransformer.transform:(Lscala/xml/Node;)Lscala/collection/Seq;
   18:	invokevirtual	#59; //Method scala/xml/transform/BasicTransformer.unchanged:(Lscala/xml/Node;Lscala/collection/Seq;)Z
   21:	ireturn
  LineNumberTable: 
   line 40: 0

  LocalVariableTable: 
   Start  Length  Slot  Name   Signature
   0      22      0    this       Lscala/xml/transform/BasicTransformer$$anonfun$1;
   5      17      1    n       Lscala/xml/Node;


public scala.Function1 andThen(scala.Function1);
  Code:
   Stack=2, Locals=2, Args_size=2
   0:	aload_0
   1:	aload_1
   2:	invokestatic	#66; //Method scala/Function1$class.andThen:(Lscala/Function1;Lscala/Function1;)Lscala/Function1;
   5:	areturn
  LineNumberTable: 
   line 40: 0

  LocalVariableTable: 
   Start  Length  Slot  Name   Signature
   0      6      0    this       Lscala/xml/transform/BasicTransformer$$anonfun$1;
   0      6      1    g       Lscala/Function1;


public scala.Function1 compose(scala.Function1);
  Code:
   Stack=2, Locals=2, Args_size=2
   0:	aload_0
   1:	aload_1
   2:	invokestatic	#71; //Method scala/Function1$class.compose:(Lscala/Function1;Lscala/Function1;)Lscala/Function1;
   5:	areturn
  LineNumberTable: 
   line 40: 0

  LocalVariableTable: 
   Start  Length  Slot  Name   Signature
   0      6      0    this       Lscala/xml/transform/BasicTransformer$$anonfun$1;
   0      6      1    g       Lscala/Function1;


public java.lang.String toString();
  Code:
   Stack=1, Locals=1, Args_size=1
   0:	aload_0
   1:	invokestatic	#76; //Method scala/Function1$class.toString:(Lscala/Function1;)Ljava/lang/String;
   4:	areturn
  LineNumberTable: 
   line 40: 0


}

