Compiled from "BasicTransformer.scala"
public final class scala.xml.transform.BasicTransformer$$anonfun$transform$2 extends java.lang.Object implements scala.Function1,scala.ScalaObject,java.io.Serializable
  SourceFile: "BasicTransformer.scala"
  Scala: length = 0x
   
  InnerClass: 
   public final #118= #19 of #70; //$anonfun$transform$2=class scala/xml/transform/BasicTransformer$$anonfun$transform$2 of class scala/xml/transform/BasicTransformer
   public final #119= #76 of #19; //$anonfun$apply$1=class scala/xml/transform/BasicTransformer$$anonfun$transform$2$$anonfun$apply$1 of class scala/xml/transform/BasicTransformer$$anonfun$transform$2
  minor version: 0
  major version: 49
  Constant pool:
const #1 = Asciz	SourceFile;
const #2 = Asciz	BasicTransformer.scala;
const #3 = Asciz	nonLocalReturnKey1$1;
const #4 = Asciz	Ljava/lang/Object;;
const #5 = Asciz	ns$1;
const #6 = Asciz	Lscala/collection/Sequence;;
const #7 = Asciz	$outer;
const #8 = Asciz	Lscala/xml/transform/BasicTransformer;;
const #9 = Asciz	<init>;
const #10 = Asciz	(Lscala/xml/transform/BasicTransformer;Lscala/collection/Sequence;Ljava/lang/Object;)V;
const #11 = Asciz	Code;
const #12 = Asciz	LineNumberTable;
const #13 = Asciz	java/lang/NullPointerException;
const #14 = class	#13;	//  java/lang/NullPointerException
const #15 = Asciz	()V;
const #16 = NameAndType	#9:#15;//  "<init>":()V
const #17 = Method	#14.#16;	//  java/lang/NullPointerException."<init>":()V
const #18 = Asciz	scala/xml/transform/BasicTransformer$$anonfun$transform$2;
const #19 = class	#18;	//  scala/xml/transform/BasicTransformer$$anonfun$transform$2
const #20 = NameAndType	#7:#8;//  $outer:Lscala/xml/transform/BasicTransformer;
const #21 = Field	#19.#20;	//  scala/xml/transform/BasicTransformer$$anonfun$transform$2.$outer:Lscala/xml/transform/BasicTransformer;
const #22 = NameAndType	#5:#6;//  ns$1:Lscala/collection/Sequence;
const #23 = Field	#19.#22;	//  scala/xml/transform/BasicTransformer$$anonfun$transform$2.ns$1:Lscala/collection/Sequence;
const #24 = NameAndType	#3:#4;//  nonLocalReturnKey1$1:Ljava/lang/Object;
const #25 = Field	#19.#24;	//  scala/xml/transform/BasicTransformer$$anonfun$transform$2.nonLocalReturnKey1$1:Ljava/lang/Object;
const #26 = Asciz	java/lang/Object;
const #27 = class	#26;	//  java/lang/Object
const #28 = Method	#27.#16;	//  java/lang/Object."<init>":()V
const #29 = Asciz	scala/Function1$class;
const #30 = class	#29;	//  scala/Function1$class
const #31 = Asciz	$init$;
const #32 = Asciz	(Lscala/Function1;)V;
const #33 = NameAndType	#31:#32;//  $init$:(Lscala/Function1;)V
const #34 = Method	#30.#33;	//  scala/Function1$class.$init$:(Lscala/Function1;)V
const #35 = Asciz	this;
const #36 = Asciz	Lscala/xml/transform/BasicTransformer$$anonfun$transform$2;;
const #37 = Asciz	LocalVariableTable;
const #38 = Asciz	apply;
const #39 = Asciz	(Ljava/lang/Object;)Ljava/lang/Object;;
const #40 = Asciz	scala/Tuple2;
const #41 = class	#40;	//  scala/Tuple2
const #42 = Asciz	(Lscala/Tuple2;)V;
const #43 = NameAndType	#38:#42;//  apply:(Lscala/Tuple2;)V
const #44 = Method	#19.#43;	//  scala/xml/transform/BasicTransformer$$anonfun$transform$2.apply:(Lscala/Tuple2;)V
const #45 = Asciz	scala/runtime/BoxedUnit;
const #46 = class	#45;	//  scala/runtime/BoxedUnit
const #47 = Asciz	UNIT;
const #48 = Asciz	Lscala/runtime/BoxedUnit;;
const #49 = NameAndType	#47:#48;//  UNIT:Lscala/runtime/BoxedUnit;
const #50 = Field	#46.#49;	//  scala/runtime/BoxedUnit.UNIT:Lscala/runtime/BoxedUnit;
const #51 = Asciz	v1;
const #52 = Asciz	scala$xml$transform$BasicTransformer$$anonfun$$$outer;
const #53 = Asciz	()Lscala/xml/transform/BasicTransformer;;
const #54 = Asciz	_1;
const #55 = Asciz	()Ljava/lang/Object;;
const #56 = NameAndType	#54:#55;//  _1:()Ljava/lang/Object;
const #57 = Method	#41.#56;	//  scala/Tuple2._1:()Ljava/lang/Object;
const #58 = Asciz	scala/xml/Node;
const #59 = class	#58;	//  scala/xml/Node
const #60 = Asciz	_2;
const #61 = NameAndType	#60:#55;//  _2:()Ljava/lang/Object;
const #62 = Method	#41.#61;	//  scala/Tuple2._2:()Ljava/lang/Object;
const #63 = Asciz	scala/runtime/BoxesRunTime;
const #64 = class	#63;	//  scala/runtime/BoxesRunTime
const #65 = Asciz	unboxToInt;
const #66 = Asciz	(Ljava/lang/Object;)I;
const #67 = NameAndType	#65:#66;//  unboxToInt:(Ljava/lang/Object;)I
const #68 = Method	#64.#67;	//  scala/runtime/BoxesRunTime.unboxToInt:(Ljava/lang/Object;)I
const #69 = Asciz	scala/xml/transform/BasicTransformer;
const #70 = class	#69;	//  scala/xml/transform/BasicTransformer
const #71 = Asciz	testForChange$1;
const #72 = Asciz	(Lscala/xml/Node;)Lscala/Option;;
const #73 = NameAndType	#71:#72;//  testForChange$1:(Lscala/xml/Node;)Lscala/Option;
const #74 = Method	#70.#73;	//  scala/xml/transform/BasicTransformer.testForChange$1:(Lscala/xml/Node;)Lscala/Option;
const #75 = Asciz	scala/xml/transform/BasicTransformer$$anonfun$transform$2$$anonfun$apply$1;
const #76 = class	#75;	//  scala/xml/transform/BasicTransformer$$anonfun$transform$2$$anonfun$apply$1
const #77 = Asciz	(Lscala/xml/transform/BasicTransformer$$anonfun$transform$2;I)V;
const #78 = NameAndType	#9:#77;//  "<init>":(Lscala/xml/transform/BasicTransformer$$anonfun$transform$2;I)V
const #79 = Method	#76.#78;	//  scala/xml/transform/BasicTransformer$$anonfun$transform$2$$anonfun$apply$1."<init>":(Lscala/xml/transform/BasicTransformer$$anonfun$transform$2;I)V
const #80 = Asciz	scala/Option;
const #81 = class	#80;	//  scala/Option
const #82 = Asciz	foreach;
const #83 = NameAndType	#82:#32;//  foreach:(Lscala/Function1;)V
const #84 = Method	#81.#83;	//  scala/Option.foreach:(Lscala/Function1;)V
const #85 = Asciz	scala/MatchError;
const #86 = class	#85;	//  scala/MatchError
const #87 = Asciz	toString;
const #88 = Asciz	()Ljava/lang/String;;
const #89 = NameAndType	#87:#88;//  toString:()Ljava/lang/String;
const #90 = Method	#41.#89;	//  scala/Tuple2.toString:()Ljava/lang/String;
const #91 = Asciz	(Ljava/lang/String;)V;
const #92 = NameAndType	#9:#91;//  "<init>":(Ljava/lang/String;)V
const #93 = Method	#86.#92;	//  scala/MatchError."<init>":(Ljava/lang/String;)V
const #94 = Asciz	temp1;
const #95 = Asciz	Lscala/Tuple2;;
const #96 = Asciz	temp2;
const #97 = Asciz	Lscala/xml/Node;;
const #98 = Asciz	temp3;
const #99 = Asciz	I;
const #100 = Asciz	i$1;
const #101 = Asciz	(Lscala/Tuple2<Lscala/xml/Node;Ljava/lang/Integer;>;)V;
const #102 = Asciz	Signature;
const #103 = Asciz	andThen;
const #104 = Asciz	(Lscala/Function1;)Lscala/Function1;;
const #105 = Asciz	(Lscala/Function1;Lscala/Function1;)Lscala/Function1;;
const #106 = NameAndType	#103:#105;//  andThen:(Lscala/Function1;Lscala/Function1;)Lscala/Function1;
const #107 = Method	#30.#106;	//  scala/Function1$class.andThen:(Lscala/Function1;Lscala/Function1;)Lscala/Function1;
const #108 = Asciz	g;
const #109 = Asciz	Lscala/Function1;;
const #110 = Asciz	compose;
const #111 = NameAndType	#110:#105;//  compose:(Lscala/Function1;Lscala/Function1;)Lscala/Function1;
const #112 = Method	#30.#111;	//  scala/Function1$class.compose:(Lscala/Function1;Lscala/Function1;)Lscala/Function1;
const #113 = Asciz	(Lscala/Function1;)Ljava/lang/String;;
const #114 = NameAndType	#87:#113;//  toString:(Lscala/Function1;)Ljava/lang/String;
const #115 = Method	#30.#114;	//  scala/Function1$class.toString:(Lscala/Function1;)Ljava/lang/String;
const #116 = Asciz	Scala;
const #117 = Asciz	InnerClasses;
const #118 = Asciz	$anonfun$transform$2;
const #119 = Asciz	$anonfun$apply$1;
const #120 = Asciz	scala/Function1;
const #121 = class	#120;	//  scala/Function1
const #122 = Asciz	scala/ScalaObject;
const #123 = class	#122;	//  scala/ScalaObject
const #124 = Asciz	java/io/Serializable;
const #125 = class	#124;	//  java/io/Serializable

{
public final java.lang.Object nonLocalReturnKey1$1;

public final scala.collection.Sequence ns$1;

public scala.xml.transform.BasicTransformer$$anonfun$transform$2(scala.xml.transform.BasicTransformer, scala.collection.Sequence, java.lang.Object);
  Code:
   Stack=2, Locals=4, Args_size=4
   0:	aload_1
   1:	ifnonnull	12
   4:	new	#14; //class java/lang/NullPointerException
   7:	dup
   8:	invokespecial	#17; //Method java/lang/NullPointerException."<init>":()V
   11:	athrow
   12:	aload_0
   13:	aload_1
   14:	putfield	#21; //Field $outer:Lscala/xml/transform/BasicTransformer;
   17:	aload_0
   18:	aload_2
   19:	putfield	#23; //Field ns$1:Lscala/collection/Sequence;
   22:	aload_0
   23:	aload_3
   24:	putfield	#25; //Field nonLocalReturnKey1$1:Ljava/lang/Object;
   27:	aload_0
   28:	invokespecial	#28; //Method java/lang/Object."<init>":()V
   31:	aload_0
   32:	invokestatic	#34; //Method scala/Function1$class.$init$:(Lscala/Function1;)V
   35:	return
  LineNumberTable: 
   line 47: 0

  LocalVariableTable: 
   Start  Length  Slot  Name   Signature
   0      36      0    this       Lscala/xml/transform/BasicTransformer$$anonfun$transform$2;
   0      36      1    $outer       Lscala/xml/transform/BasicTransformer;


public final java.lang.Object apply(java.lang.Object);
  Code:
   Stack=2, Locals=3, Args_size=2
   0:	aload_0
   1:	getfield	#21; //Field $outer:Lscala/xml/transform/BasicTransformer;
   4:	astore_2
   5:	aload_0
   6:	aload_1
   7:	checkcast	#41; //class scala/Tuple2
   10:	invokevirtual	#44; //Method apply:(Lscala/Tuple2;)V
   13:	getstatic	#50; //Field scala/runtime/BoxedUnit.UNIT:Lscala/runtime/BoxedUnit;
   16:	areturn
  LineNumberTable: 
   line 47: 0

  LocalVariableTable: 
   Start  Length  Slot  Name   Signature
   0      17      0    this       Lscala/xml/transform/BasicTransformer$$anonfun$transform$2;
   5      12      1    v1       Ljava/lang/Object;


public scala.xml.transform.BasicTransformer scala$xml$transform$BasicTransformer$$anonfun$$$outer();
  Code:
   Stack=1, Locals=1, Args_size=1
   0:	aload_0
   1:	getfield	#21; //Field $outer:Lscala/xml/transform/BasicTransformer;
   4:	areturn
  LineNumberTable: 
   line 47: 0


public final void apply(scala.Tuple2);
  Code:
   Stack=5, Locals=7, Args_size=2
   0:	aload_0
   1:	getfield	#21; //Field $outer:Lscala/xml/transform/BasicTransformer;
   4:	astore	6
   6:	aload_1
   7:	astore_2
   8:	aload_2
   9:	ifnull	55
   12:	aload_2
   13:	invokevirtual	#57; //Method scala/Tuple2._1:()Ljava/lang/Object;
   16:	checkcast	#59; //class scala/xml/Node
   19:	astore_3
   20:	aload_2
   21:	invokevirtual	#62; //Method scala/Tuple2._2:()Ljava/lang/Object;
   24:	invokestatic	#68; //Method scala/runtime/BoxesRunTime.unboxToInt:(Ljava/lang/Object;)I
   27:	istore	4
   29:	iload	4
   31:	istore	5
   33:	aload_0
   34:	getfield	#21; //Field $outer:Lscala/xml/transform/BasicTransformer;
   37:	aload_3
   38:	invokevirtual	#74; //Method scala/xml/transform/BasicTransformer.testForChange$1:(Lscala/xml/Node;)Lscala/Option;
   41:	new	#76; //class scala/xml/transform/BasicTransformer$$anonfun$transform$2$$anonfun$apply$1
   44:	dup
   45:	aload_0
   46:	iload	5
   48:	invokespecial	#79; //Method scala/xml/transform/BasicTransformer$$anonfun$transform$2$$anonfun$apply$1."<init>":(Lscala/xml/transform/BasicTransformer$$anonfun$transform$2;I)V
   51:	invokevirtual	#84; //Method scala/Option.foreach:(Lscala/Function1;)V
   54:	return
   55:	new	#86; //class scala/MatchError
   58:	dup
   59:	aload_2
   60:	invokevirtual	#90; //Method scala/Tuple2.toString:()Ljava/lang/String;
   63:	invokespecial	#93; //Method scala/MatchError."<init>":(Ljava/lang/String;)V
   66:	athrow
  LineNumberTable: 
   line 47: 0

  LocalVariableTable: 
   Start  Length  Slot  Name   Signature
   0      67      0    this       Lscala/xml/transform/BasicTransformer$$anonfun$transform$2;
   8      59      2    temp1       Lscala/Tuple2;
   20      34      3    temp2       Lscala/xml/Node;
   29      25      4    temp3       I
   33      21      5    i$1       I

  Signature: length = 0x2
   00 65 

public scala.Function1 andThen(scala.Function1);
  Code:
   Stack=2, Locals=2, Args_size=2
   0:	aload_0
   1:	aload_1
   2:	invokestatic	#107; //Method scala/Function1$class.andThen:(Lscala/Function1;Lscala/Function1;)Lscala/Function1;
   5:	areturn
  LineNumberTable: 
   line 47: 0

  LocalVariableTable: 
   Start  Length  Slot  Name   Signature
   0      6      0    this       Lscala/xml/transform/BasicTransformer$$anonfun$transform$2;
   0      6      1    g       Lscala/Function1;


public scala.Function1 compose(scala.Function1);
  Code:
   Stack=2, Locals=2, Args_size=2
   0:	aload_0
   1:	aload_1
   2:	invokestatic	#112; //Method scala/Function1$class.compose:(Lscala/Function1;Lscala/Function1;)Lscala/Function1;
   5:	areturn
  LineNumberTable: 
   line 47: 0

  LocalVariableTable: 
   Start  Length  Slot  Name   Signature
   0      6      0    this       Lscala/xml/transform/BasicTransformer$$anonfun$transform$2;
   0      6      1    g       Lscala/Function1;


public java.lang.String toString();
  Code:
   Stack=1, Locals=1, Args_size=1
   0:	aload_0
   1:	invokestatic	#115; //Method scala/Function1$class.toString:(Lscala/Function1;)Ljava/lang/String;
   4:	areturn
  LineNumberTable: 
   line 47: 0


}

