Compiled from "RuleTransformer.scala"
public class scala.xml.transform.RuleTransformer extends scala.xml.transform.BasicTransformer implements scala.ScalaObject
  SourceFile: "RuleTransformer.scala"
  ScalaSig: length = 0x134
   05 00 33 06 08 01 02 FFFFFF84 FFFFFF80 FFFFFF80 FFFFFF80 00 09 02 0F 52
   75 6C 65 54 72 61 6E 73 66 6F 72 6D 65 72 0A 02
   03 04 01 09 74 72 61 6E 73 66 6F 72 6D 0A 02 05
   06 01 03 78 6D 6C 0A 01 07 01 05 73 63 61 6C 61
   03 00 13 03 00 0A 0E 10 02 0B 0C 0D 01 02 09 02
   0D 02 02 10 42 61 73 69 63 54 72 61 6E 73 66 6F
   72 6D 65 72 10 02 0F 10 0D 01 06 09 02 11 06 02
   0B 53 63 61 6C 61 4F 62 6A 65 63 74 08 08 13 00
   FFFFFF82 FFFFFF80 FFFFFFA0 FFFFFF80 04 14 01 05 72 75 6C 65 73 10 03 0F
   15 17 09 02 16 06 02 0A 3C 72 65 70 65 61 74 65
   64 3E 10 02 0B 18 09 02 19 02 02 0B 52 65 77 72
   69 74 65 52 75 6C 65 08 05 1B 00 FFFFFF84 00 1C 01 06
   3C 69 6E 69 74 3E 14 02 1D 1E 10 02 0B 00 08 05
   13 1A FFFFFFC0 00 14 08 05 03 00 FFFFFF84 20 20 14 02 21 31
   10 03 22 2A 2D 0E 02 23 28 0E 02 24 27 0D 01 25
   0A 02 26 08 01 06 3C 72 6F 6F 74 3E 09 01 07 09
   02 29 06 01 07 70 61 63 6B 61 67 65 09 02 2B 2C
   02 03 53 65 71 0A 02 29 06 10 02 2E 2F 0D 01 04
   09 02 30 04 02 04 4E 6F 64 65 08 05 32 1F FFFFFFC0 00
   2D 01 01 6E 
  InnerClass: 
   public final $anonfun$transform$1=class scala/xml/transform/RuleTransformer$$anonfun$transform$1 of class scala/xml/transform/RuleTransformer
  minor version: 0
  major version: 49
  Constant pool:
Asciz	SourceFile;
Asciz	RuleTransformer.scala;
Asciz	rules;
Asciz	Lscala/collection/Seq;;
Asciz	Lscala/collection/Seq<Lscala/xml/transform/RewriteRule;>;;
Asciz	Signature;
Asciz	<init>;
Asciz	(Lscala/collection/Seq;)V;
Asciz	Code;
Asciz	LineNumberTable;
Asciz	scala/xml/transform/RuleTransformer;
class	scala/xml/transform/RuleTransformer
NameAndType	rules:Lscala/collection/Seq;
Field	scala/xml/transform/RuleTransformer.rules:Lscala/collection/Seq;
Asciz	scala/xml/transform/BasicTransformer;
class	scala/xml/transform/BasicTransformer
Asciz	()V;
NameAndType	"<init>":()V
Method	scala/xml/transform/BasicTransformer."<init>":()V
Asciz	this;
Asciz	Lscala/xml/transform/RuleTransformer;;
Asciz	LocalVariableTable;
Asciz	(Lscala/collection/Seq<Lscala/xml/transform/RewriteRule;>;)V;
Asciz	transform;
Asciz	(Lscala/xml/Node;)Lscala/collection/Seq;;
NameAndType	transform:(Lscala/xml/Node;)Lscala/collection/Seq;
Method	scala/xml/transform/BasicTransformer.transform:(Lscala/xml/Node;)Lscala/collection/Seq;
Asciz	scala/xml/transform/RuleTransformer$$anonfun$transform$1;
class	scala/xml/transform/RuleTransformer$$anonfun$transform$1
Asciz	(Lscala/xml/transform/RuleTransformer;)V;
NameAndType	"<init>":(Lscala/xml/transform/RuleTransformer;)V
Method	scala/xml/transform/RuleTransformer$$anonfun$transform$1."<init>":(Lscala/xml/transform/RuleTransformer;)V
Asciz	scala/collection/TraversableLike;
class	scala/collection/TraversableLike
Asciz	foldLeft;
Asciz	(Ljava/lang/Object;Lscala/Function2;)Ljava/lang/Object;;
NameAndType	foldLeft:(Ljava/lang/Object;Lscala/Function2;)Ljava/lang/Object;
InterfaceMethod	scala/collection/TraversableLike.foldLeft:(Ljava/lang/Object;Lscala/Function2;)Ljava/lang/Object;
Asciz	scala/collection/Seq;
class	scala/collection/Seq
Asciz	n;
Asciz	Lscala/xml/Node;;
Asciz	(Lscala/xml/Node;)Lscala/collection/Seq<Lscala/xml/Node;>;;
Asciz	ScalaSig;
Asciz	InnerClasses;
Asciz	$anonfun$transform$1;
Asciz	scala/ScalaObject;
class	scala/ScalaObject

{
private final scala.collection.Seq rules;
  Signature: Lscala/collection/Seq;
  Signature: length = 0x2
   00 05 

public scala.xml.transform.RuleTransformer(scala.collection.Seq);
  Signature: (Lscala/collection/Seq;)V
  Code:
   Stack=2, Locals=2, Args_size=2
	aload_0
	aload_1
	putfield	Field rules:Lscala/collection/Seq;
	aload_0
	invokespecial	Method scala/xml/transform/BasicTransformer."<init>":()V
	return
  Labels:
  LocalVariableTable: 
   Start  Length  Slot  Name   Signature
   0      10      0    this       Lscala/xml/transform/RuleTransformer;
   0      10      1    rules       Lscala/collection/Seq;

  Signature: length = 0x2
   00 17 

public scala.collection.Seq transform(scala.xml.Node);
  Signature: (Lscala/xml/Node;)Lscala/collection/Seq;
  Code:
   Stack=5, Locals=2, Args_size=2
	aload_0
	getfield	Field rules:Lscala/collection/Seq;
	aload_0
	aload_1
	invokespecial	Method scala/xml/transform/BasicTransformer.transform:(Lscala/xml/Node;)Lscala/collection/Seq;
	new	class scala/xml/transform/RuleTransformer$$anonfun$transform$1
	dup
	aload_0
	invokespecial	Method scala/xml/transform/RuleTransformer$$anonfun$transform$1."<init>":(Lscala/xml/transform/RuleTransformer;)V
	invokeinterface	InterfaceMethod scala/collection/TraversableLike.foldLeft:(Ljava/lang/Object;Lscala/Function2;)Ljava/lang/Object;
	checkcast	class scala/collection/Seq
	areturn
  Labels:
  LocalVariableTable: 
   Start  Length  Slot  Name   Signature
   0      26      0    this       Lscala/xml/transform/RuleTransformer;
   0      26      1    n       Lscala/xml/Node;

  Signature: length = 0x2
   00 2B 

}

