Compiled from "RuleTransformer.scala"
public final class scala.xml.transform.RuleTransformer$$anonfun$transform$1 extends java.lang.Object implements scala.Function2,scala.ScalaObject,java.io.Serializable
  SourceFile: "RuleTransformer.scala"
  Scala: length = 0x
   
  InnerClass: 
   public final #71= #40 of #70; //$anonfun$transform$1=class scala/xml/transform/RuleTransformer$$anonfun$transform$1 of class scala/xml/transform/RuleTransformer
  minor version: 0
  major version: 49
  Constant pool:
const #1 = Asciz	SourceFile;
const #2 = Asciz	RuleTransformer.scala;
const #3 = Asciz	<init>;
const #4 = Asciz	(Lscala/xml/transform/RuleTransformer;)V;
const #5 = Asciz	Code;
const #6 = Asciz	LineNumberTable;
const #7 = Asciz	java/lang/Object;
const #8 = class	#7;	//  java/lang/Object
const #9 = Asciz	()V;
const #10 = NameAndType	#3:#9;//  "<init>":()V
const #11 = Method	#8.#10;	//  java/lang/Object."<init>":()V
const #12 = Asciz	scala/Function2$class;
const #13 = class	#12;	//  scala/Function2$class
const #14 = Asciz	$init$;
const #15 = Asciz	(Lscala/Function2;)V;
const #16 = NameAndType	#14:#15;//  $init$:(Lscala/Function2;)V
const #17 = Method	#13.#16;	//  scala/Function2$class.$init$:(Lscala/Function2;)V
const #18 = Asciz	this;
const #19 = Asciz	Lscala/xml/transform/RuleTransformer$$anonfun$transform$1;;
const #20 = Asciz	$outer;
const #21 = Asciz	Lscala/xml/transform/RuleTransformer;;
const #22 = Asciz	LocalVariableTable;
const #23 = Asciz	apply;
const #24 = Asciz	(Ljava/lang/Object;Ljava/lang/Object;)Ljava/lang/Object;;
const #25 = Asciz	scala/collection/Sequence;
const #26 = class	#25;	//  scala/collection/Sequence
const #27 = Asciz	scala/runtime/ScalaRunTime$;
const #28 = class	#27;	//  scala/runtime/ScalaRunTime$
const #29 = Asciz	MODULE$;
const #30 = Asciz	Lscala/runtime/ScalaRunTime$;;
const #31 = NameAndType	#29:#30;//  MODULE$:Lscala/runtime/ScalaRunTime$;
const #32 = Field	#28.#31;	//  scala/runtime/ScalaRunTime$.MODULE$:Lscala/runtime/ScalaRunTime$;
const #33 = Asciz	boxArray;
const #34 = Asciz	(Ljava/lang/Object;)Lscala/runtime/BoxedArray;;
const #35 = NameAndType	#33:#34;//  boxArray:(Ljava/lang/Object;)Lscala/runtime/BoxedArray;
const #36 = Method	#28.#35;	//  scala/runtime/ScalaRunTime$.boxArray:(Ljava/lang/Object;)Lscala/runtime/BoxedArray;
const #37 = Asciz	scala/xml/transform/RewriteRule;
const #38 = class	#37;	//  scala/xml/transform/RewriteRule
const #39 = Asciz	scala/xml/transform/RuleTransformer$$anonfun$transform$1;
const #40 = class	#39;	//  scala/xml/transform/RuleTransformer$$anonfun$transform$1
const #41 = Asciz	(Lscala/collection/Sequence;Lscala/xml/transform/RewriteRule;)Lscala/collection/Sequence;;
const #42 = NameAndType	#23:#41;//  apply:(Lscala/collection/Sequence;Lscala/xml/transform/RewriteRule;)Lscala/collection/Sequence;
const #43 = Method	#40.#42;	//  scala/xml/transform/RuleTransformer$$anonfun$transform$1.apply:(Lscala/collection/Sequence;Lscala/xml/transform/RewriteRule;)Lscala/collection/Sequence;
const #44 = Asciz	v1;
const #45 = Asciz	Ljava/lang/Object;;
const #46 = Asciz	v2;
const #47 = Asciz	transform;
const #48 = Asciz	(Lscala/collection/Sequence;)Lscala/collection/Sequence;;
const #49 = NameAndType	#47:#48;//  transform:(Lscala/collection/Sequence;)Lscala/collection/Sequence;
const #50 = Method	#38.#49;	//  scala/xml/transform/RewriteRule.transform:(Lscala/collection/Sequence;)Lscala/collection/Sequence;
const #51 = Asciz	res;
const #52 = Asciz	Lscala/collection/Sequence;;
const #53 = Asciz	rule;
const #54 = Asciz	Lscala/xml/transform/RewriteRule;;
const #55 = Asciz	(Lscala/collection/Sequence<Lscala/xml/Node;>;Lscala/xml/transform/RewriteRule;)Lscala/collection/Sequence<Lscala/xml/Node;>;;
const #56 = Asciz	Signature;
const #57 = Asciz	curry;
const #58 = Asciz	()Lscala/Function1;;
const #59 = Asciz	(Lscala/Function2;)Lscala/Function1;;
const #60 = NameAndType	#57:#59;//  curry:(Lscala/Function2;)Lscala/Function1;
const #61 = Method	#13.#60;	//  scala/Function2$class.curry:(Lscala/Function2;)Lscala/Function1;
const #62 = Asciz	toString;
const #63 = Asciz	()Ljava/lang/String;;
const #64 = Asciz	(Lscala/Function2;)Ljava/lang/String;;
const #65 = NameAndType	#62:#64;//  toString:(Lscala/Function2;)Ljava/lang/String;
const #66 = Method	#13.#65;	//  scala/Function2$class.toString:(Lscala/Function2;)Ljava/lang/String;
const #67 = Asciz	Scala;
const #68 = Asciz	InnerClasses;
const #69 = Asciz	scala/xml/transform/RuleTransformer;
const #70 = class	#69;	//  scala/xml/transform/RuleTransformer
const #71 = Asciz	$anonfun$transform$1;
const #72 = Asciz	scala/Function2;
const #73 = class	#72;	//  scala/Function2
const #74 = Asciz	scala/ScalaObject;
const #75 = class	#74;	//  scala/ScalaObject
const #76 = Asciz	java/io/Serializable;
const #77 = class	#76;	//  java/io/Serializable

{
public scala.xml.transform.RuleTransformer$$anonfun$transform$1(scala.xml.transform.RuleTransformer);
  Code:
   Stack=1, Locals=2, Args_size=2
   0:	aload_0
   1:	invokespecial	#11; //Method java/lang/Object."<init>":()V
   4:	aload_0
   5:	invokestatic	#17; //Method scala/Function2$class.$init$:(Lscala/Function2;)V
   8:	return
  LineNumberTable: 
   line 17: 0

  LocalVariableTable: 
   Start  Length  Slot  Name   Signature
   0      9      0    this       Lscala/xml/transform/RuleTransformer$$anonfun$transform$1;
   0      9      1    $outer       Lscala/xml/transform/RuleTransformer;


public final java.lang.Object apply(java.lang.Object, java.lang.Object);
  Code:
   Stack=3, Locals=3, Args_size=3
   0:	aload_0
   1:	aload_1
   2:	instanceof	#26; //class scala/collection/Sequence
   5:	ifeq	12
   8:	aload_1
   9:	goto	19
   12:	getstatic	#32; //Field scala/runtime/ScalaRunTime$.MODULE$:Lscala/runtime/ScalaRunTime$;
   15:	aload_1
   16:	invokevirtual	#36; //Method scala/runtime/ScalaRunTime$.boxArray:(Ljava/lang/Object;)Lscala/runtime/BoxedArray;
   19:	checkcast	#26; //class scala/collection/Sequence
   22:	aload_2
   23:	checkcast	#38; //class scala/xml/transform/RewriteRule
   26:	invokevirtual	#43; //Method apply:(Lscala/collection/Sequence;Lscala/xml/transform/RewriteRule;)Lscala/collection/Sequence;
   29:	areturn
  LineNumberTable: 
   line 17: 0

  LocalVariableTable: 
   Start  Length  Slot  Name   Signature
   0      30      0    this       Lscala/xml/transform/RuleTransformer$$anonfun$transform$1;
   0      30      1    v1       Ljava/lang/Object;
   0      30      2    v2       Ljava/lang/Object;


public final scala.collection.Sequence apply(scala.collection.Sequence, scala.xml.transform.RewriteRule);
  Code:
   Stack=2, Locals=3, Args_size=3
   0:	aload_2
   1:	aload_1
   2:	invokevirtual	#50; //Method scala/xml/transform/RewriteRule.transform:(Lscala/collection/Sequence;)Lscala/collection/Sequence;
   5:	areturn
  LineNumberTable: 
   line 17: 0

  LocalVariableTable: 
   Start  Length  Slot  Name   Signature
   0      6      0    this       Lscala/xml/transform/RuleTransformer$$anonfun$transform$1;
   0      6      1    res       Lscala/collection/Sequence;
   0      6      2    rule       Lscala/xml/transform/RewriteRule;

  Signature: length = 0x2
   00 37 

public scala.Function1 curry();
  Code:
   Stack=1, Locals=1, Args_size=1
   0:	aload_0
   1:	invokestatic	#61; //Method scala/Function2$class.curry:(Lscala/Function2;)Lscala/Function1;
   4:	areturn
  LineNumberTable: 
   line 17: 0


public java.lang.String toString();
  Code:
   Stack=1, Locals=1, Args_size=1
   0:	aload_0
   1:	invokestatic	#66; //Method scala/Function2$class.toString:(Lscala/Function2;)Ljava/lang/String;
   4:	areturn
  LineNumberTable: 
   line 17: 0


}

