Compiled from "ForkJoinPool.java"
class scala.concurrent.forkjoin.ForkJoinPool$DefaultForkJoinWorkerThreadFactory extends java.lang.Object implements scala.concurrent.forkjoin.ForkJoinPool$ForkJoinWorkerThreadFactory
  SourceFile: "ForkJoinPool.java"
  InnerClass: 
   #14= #5 of #29; //DefaultForkJoinWorkerThreadFactory=class scala/concurrent/forkjoin/ForkJoinPool$DefaultForkJoinWorkerThreadFactory of class scala/concurrent/forkjoin/ForkJoinPool
   public abstract #33= #7 of #29; //ForkJoinWorkerThreadFactory=class scala/concurrent/forkjoin/ForkJoinPool$ForkJoinWorkerThreadFactory of class scala/concurrent/forkjoin/ForkJoinPool
  minor version: 0
  major version: 49
  Constant pool:
const #1 = Method	#6.#25;	//  java/lang/Object."<init>":()V
const #2 = class	#26;	//  scala/concurrent/forkjoin/ForkJoinWorkerThread
const #3 = Method	#2.#27;	//  scala/concurrent/forkjoin/ForkJoinWorkerThread."<init>":(Lscala/concurrent/forkjoin/ForkJoinPool;)V
const #4 = class	#28;	//  java/lang/OutOfMemoryError
const #5 = class	#30;	//  scala/concurrent/forkjoin/ForkJoinPool$DefaultForkJoinWorkerThreadFactory
const #6 = class	#31;	//  java/lang/Object
const #7 = class	#32;	//  scala/concurrent/forkjoin/ForkJoinPool$ForkJoinWorkerThreadFactory
const #8 = Asciz	<init>;
const #9 = Asciz	()V;
const #10 = Asciz	Code;
const #11 = Asciz	LineNumberTable;
const #12 = Asciz	LocalVariableTable;
const #13 = Asciz	this;
const #14 = Asciz	DefaultForkJoinWorkerThreadFactory;
const #15 = Asciz	InnerClasses;
const #16 = Asciz	Lscala/concurrent/forkjoin/ForkJoinPool$DefaultForkJoinWorkerThreadFactory;;
const #17 = Asciz	newThread;
const #18 = Asciz	(Lscala/concurrent/forkjoin/ForkJoinPool;)Lscala/concurrent/forkjoin/ForkJoinWorkerThread;;
const #19 = Asciz	oom;
const #20 = Asciz	Ljava/lang/OutOfMemoryError;;
const #21 = Asciz	pool;
const #22 = Asciz	Lscala/concurrent/forkjoin/ForkJoinPool;;
const #23 = Asciz	SourceFile;
const #24 = Asciz	ForkJoinPool.java;
const #25 = NameAndType	#8:#9;//  "<init>":()V
const #26 = Asciz	scala/concurrent/forkjoin/ForkJoinWorkerThread;
const #27 = NameAndType	#8:#34;//  "<init>":(Lscala/concurrent/forkjoin/ForkJoinPool;)V
const #28 = Asciz	java/lang/OutOfMemoryError;
const #29 = class	#35;	//  scala/concurrent/forkjoin/ForkJoinPool
const #30 = Asciz	scala/concurrent/forkjoin/ForkJoinPool$DefaultForkJoinWorkerThreadFactory;
const #31 = Asciz	java/lang/Object;
const #32 = Asciz	scala/concurrent/forkjoin/ForkJoinPool$ForkJoinWorkerThreadFactory;
const #33 = Asciz	ForkJoinWorkerThreadFactory;
const #34 = Asciz	(Lscala/concurrent/forkjoin/ForkJoinPool;)V;
const #35 = Asciz	scala/concurrent/forkjoin/ForkJoinPool;

{
scala.concurrent.forkjoin.ForkJoinPool$DefaultForkJoinWorkerThreadFactory();
  Code:
   Stack=1, Locals=1, Args_size=1
   0:	aload_0
   1:	invokespecial	#1; //Method java/lang/Object."<init>":()V
   4:	return
  LineNumberTable: 
   line 97: 0

  LocalVariableTable: 
   Start  Length  Slot  Name   Signature
   0      5      0    this       Lscala/concurrent/forkjoin/ForkJoinPool$DefaultForkJoinWorkerThreadFactory;


public scala.concurrent.forkjoin.ForkJoinWorkerThread newThread(scala.concurrent.forkjoin.ForkJoinPool);
  Code:
   Stack=3, Locals=3, Args_size=2
   0:	new	#2; //class scala/concurrent/forkjoin/ForkJoinWorkerThread
   3:	dup
   4:	aload_1
   5:	invokespecial	#3; //Method scala/concurrent/forkjoin/ForkJoinWorkerThread."<init>":(Lscala/concurrent/forkjoin/ForkJoinPool;)V
   8:	areturn
   9:	astore_2
   10:	aconst_null
   11:	areturn
  Exception table:
   from   to  target type
     0     8     9   Class java/lang/OutOfMemoryError

  LineNumberTable: 
   line 101: 0
   line 102: 9
   line 103: 10

  LocalVariableTable: 
   Start  Length  Slot  Name   Signature
   10      2      2    oom       Ljava/lang/OutOfMemoryError;
   0      12      0    this       Lscala/concurrent/forkjoin/ForkJoinPool$DefaultForkJoinWorkerThreadFactory;
   0      12      1    pool       Lscala/concurrent/forkjoin/ForkJoinPool;


}

