Compiled from "ForkJoinPool.java"
final class scala.concurrent.forkjoin.ForkJoinPool$InvokeAll extends scala.concurrent.forkjoin.RecursiveAction
  Signature: length = 0x2
   00 1B 
  SourceFile: "ForkJoinPool.java"
  InnerClass: 
   final #17= #5 of #34; //InvokeAll=class scala/concurrent/forkjoin/ForkJoinPool$InvokeAll of class scala/concurrent/forkjoin/ForkJoinPool
  minor version: 0
  major version: 49
  Constant pool:
const #1 = Method	#6.#30;	//  scala/concurrent/forkjoin/RecursiveAction."<init>":()V
const #2 = Field	#5.#31;	//  scala/concurrent/forkjoin/ForkJoinPool$InvokeAll.tasks:Ljava/util/ArrayList;
const #3 = Method	#5.#32;	//  scala/concurrent/forkjoin/ForkJoinPool$InvokeAll.invokeAll:(Ljava/util/Collection;)V
const #4 = class	#33;	//  java/lang/Exception
const #5 = class	#35;	//  scala/concurrent/forkjoin/ForkJoinPool$InvokeAll
const #6 = class	#36;	//  scala/concurrent/forkjoin/RecursiveAction
const #7 = Asciz	tasks;
const #8 = Asciz	Ljava/util/ArrayList;;
const #9 = Asciz	Signature;
const #10 = Asciz	Ljava/util/ArrayList<Lscala/concurrent/forkjoin/ForkJoinTask<TT;>;>;;
const #11 = Asciz	<init>;
const #12 = Asciz	(Ljava/util/ArrayList;)V;
const #13 = Asciz	Code;
const #14 = Asciz	LineNumberTable;
const #15 = Asciz	LocalVariableTable;
const #16 = Asciz	this;
const #17 = Asciz	InvokeAll;
const #18 = Asciz	InnerClasses;
const #19 = Asciz	Lscala/concurrent/forkjoin/ForkJoinPool$InvokeAll;;
const #20 = Asciz	LocalVariableTypeTable;
const #21 = Asciz	Lscala/concurrent/forkjoin/ForkJoinPool$InvokeAll<TT;>;;
const #22 = Asciz	(Ljava/util/ArrayList<Lscala/concurrent/forkjoin/ForkJoinTask<TT;>;>;)V;
const #23 = Asciz	compute;
const #24 = Asciz	()V;
const #25 = Asciz	ignore;
const #26 = Asciz	Ljava/lang/Exception;;
const #27 = Asciz	<T:Ljava/lang/Object;>Lscala/concurrent/forkjoin/RecursiveAction;;
const #28 = Asciz	SourceFile;
const #29 = Asciz	ForkJoinPool.java;
const #30 = NameAndType	#11:#24;//  "<init>":()V
const #31 = NameAndType	#7:#8;//  tasks:Ljava/util/ArrayList;
const #32 = NameAndType	#37:#38;//  invokeAll:(Ljava/util/Collection;)V
const #33 = Asciz	java/lang/Exception;
const #34 = class	#39;	//  scala/concurrent/forkjoin/ForkJoinPool
const #35 = Asciz	scala/concurrent/forkjoin/ForkJoinPool$InvokeAll;
const #36 = Asciz	scala/concurrent/forkjoin/RecursiveAction;
const #37 = Asciz	invokeAll;
const #38 = Asciz	(Ljava/util/Collection;)V;
const #39 = Asciz	scala/concurrent/forkjoin/ForkJoinPool;

{
final java.util.ArrayList tasks;
  Signature: length = 0x2
   00 0A 

scala.concurrent.forkjoin.ForkJoinPool$InvokeAll(java.util.ArrayList);
  Code:
   Stack=2, Locals=2, Args_size=2
   0:	aload_0
   1:	invokespecial	#1; //Method scala/concurrent/forkjoin/RecursiveAction."<init>":()V
   4:	aload_0
   5:	aload_1
   6:	putfield	#2; //Field tasks:Ljava/util/ArrayList;
   9:	return
  LineNumberTable: 
   line 657: 0

  LocalVariableTable: 
   Start  Length  Slot  Name   Signature
   0      10      0    this       Lscala/concurrent/forkjoin/ForkJoinPool$InvokeAll;
   0      10      1    tasks       Ljava/util/ArrayList;

  LocalVariableTypeTable: length = 0x16
   00 02 00 00 00 0A 00 10 00 15 00 00 00 00 00 0A
   00 07 00 0A 00 01 
  Signature: length = 0x2
   00 16 

public void compute();
  Code:
   Stack=1, Locals=2, Args_size=1
   0:	aload_0
   1:	getfield	#2; //Field tasks:Ljava/util/ArrayList;
   4:	invokestatic	#3; //Method invokeAll:(Ljava/util/Collection;)V
   7:	goto	11
   10:	astore_1
   11:	return
  Exception table:
   from   to  target type
     0     7    10   Class java/lang/Exception

  LineNumberTable: 
   line 659: 0
   line 660: 11

  LocalVariableTable: 
   Start  Length  Slot  Name   Signature
   11      0      1    ignore       Ljava/lang/Exception;
   0      12      0    this       Lscala/concurrent/forkjoin/ForkJoinPool$InvokeAll;

  LocalVariableTypeTable: length = 0xC
   00 01 00 00 00 0C 00 10 00 15 00 00 

}

