Compiled from "ForkJoinPool.java"
final class scala.concurrent.forkjoin.ForkJoinPool$AdaptedRunnable extends scala.concurrent.forkjoin.ForkJoinTask implements scala.concurrent.forkjoin.ForkJoinPool$RunnableFuture
  Signature: length = 0x2
   00 2B 
  SourceFile: "ForkJoinPool.java"
  InnerClass: 
   final AdaptedRunnable=class scala/concurrent/forkjoin/ForkJoinPool$AdaptedRunnable of class scala/concurrent/forkjoin/ForkJoinPool
   abstract RunnableFuture=class scala/concurrent/forkjoin/ForkJoinPool$RunnableFuture of class scala/concurrent/forkjoin/ForkJoinPool
  minor version: 0
  major version: 49
  Constant pool:
Method	scala/concurrent/forkjoin/ForkJoinTask."<init>":()V
class	java/lang/NullPointerException
Method	java/lang/NullPointerException."<init>":()V
Field	scala/concurrent/forkjoin/ForkJoinPool$AdaptedRunnable.runnable:Ljava/lang/Runnable;
Field	scala/concurrent/forkjoin/ForkJoinPool$AdaptedRunnable.resultOnCompletion:Ljava/lang/Object;
Field	scala/concurrent/forkjoin/ForkJoinPool$AdaptedRunnable.result:Ljava/lang/Object;
InterfaceMethod	java/lang/Runnable.run:()V
Method	scala/concurrent/forkjoin/ForkJoinPool$AdaptedRunnable.invoke:()Ljava/lang/Object;
class	scala/concurrent/forkjoin/ForkJoinPool$AdaptedRunnable
class	scala/concurrent/forkjoin/ForkJoinTask
class	scala/concurrent/forkjoin/ForkJoinPool$RunnableFuture
Asciz	runnable;
Asciz	Ljava/lang/Runnable;;
Asciz	resultOnCompletion;
Asciz	Ljava/lang/Object;;
Asciz	Signature;
Asciz	TT;;
Asciz	result;
Asciz	<init>;
Asciz	(Ljava/lang/Runnable;Ljava/lang/Object;)V;
Asciz	Code;
Asciz	LineNumberTable;
Asciz	LocalVariableTable;
Asciz	this;
Asciz	AdaptedRunnable;
Asciz	InnerClasses;
Asciz	Lscala/concurrent/forkjoin/ForkJoinPool$AdaptedRunnable;;
Asciz	LocalVariableTypeTable;
Asciz	Lscala/concurrent/forkjoin/ForkJoinPool$AdaptedRunnable<TT;>;;
Asciz	(Ljava/lang/Runnable;TT;)V;
Asciz	getRawResult;
Asciz	()Ljava/lang/Object;;
Asciz	()TT;;
Asciz	setRawResult;
Asciz	(Ljava/lang/Object;)V;
Asciz	v;
Asciz	(TT;)V;
Asciz	exec;
Asciz	()Z;
Asciz	run;
Asciz	()V;
Asciz	RunnableFuture;
Asciz	<T:Ljava/lang/Object;>Lscala/concurrent/forkjoin/ForkJoinTask<TT;>;Lscala/concurrent/forkjoin/ForkJoinPool$RunnableFuture<TT;>;;
Asciz	SourceFile;
Asciz	ForkJoinPool.java;
NameAndType	"<init>":()V
Asciz	java/lang/NullPointerException;
NameAndType	runnable:Ljava/lang/Runnable;
NameAndType	resultOnCompletion:Ljava/lang/Object;
NameAndType	result:Ljava/lang/Object;
class	java/lang/Runnable
NameAndType	run:()V
NameAndType	invoke:()Ljava/lang/Object;
class	scala/concurrent/forkjoin/ForkJoinPool
Asciz	scala/concurrent/forkjoin/ForkJoinPool$AdaptedRunnable;
Asciz	scala/concurrent/forkjoin/ForkJoinTask;
Asciz	scala/concurrent/forkjoin/ForkJoinPool$RunnableFuture;
Asciz	java/lang/Runnable;
Asciz	invoke;
Asciz	scala/concurrent/forkjoin/ForkJoinPool;

{
final java.lang.Runnable runnable;
  Signature: Ljava/lang/Runnable;

final java.lang.Object resultOnCompletion;
  Signature: Ljava/lang/Object;
  Signature: length = 0x2
   00 11 

java.lang.Object result;
  Signature: Ljava/lang/Object;
  Signature: length = 0x2
   00 11 

scala.concurrent.forkjoin.ForkJoinPool$AdaptedRunnable(java.lang.Runnable, java.lang.Object);
  Signature: (Ljava/lang/Runnable;Ljava/lang/Object;)V
  Code:
   Stack=2, Locals=3, Args_size=3
	aload_0
	invokespecial	Method scala/concurrent/forkjoin/ForkJoinTask."<init>":()V
	aload_1
	ifnonnull	l1 // aload_0
	new	class java/lang/NullPointerException
	dup
	invokespecial	Method java/lang/NullPointerException."<init>":()V
	athrow
l1	aload_0
	aload_1
	putfield	Field runnable:Ljava/lang/Runnable;
	aload_0
	aload_2
	putfield	Field resultOnCompletion:Ljava/lang/Object;
	return
  Labels:
   	l1 = 16 // aload_0
  LocalVariableTable: 
   Start  Length  Slot  Name   Signature
   0      27      0    this       Lscala/concurrent/forkjoin/ForkJoinPool$AdaptedRunnable;
   0      27      1    runnable       Ljava/lang/Runnable;
   0      27      2    result       Ljava/lang/Object;

  LocalVariableTypeTable: length = 0x16
   00 02 00 00 00 1B 00 18 00 1D 00 00 00 00 00 1B
   00 12 00 11 00 02 
  Signature: length = 0x2
   00 1E 

public java.lang.Object getRawResult();
  Signature: ()Ljava/lang/Object;
  Code:
   Stack=1, Locals=1, Args_size=1
	aload_0
	getfield	Field result:Ljava/lang/Object;
	areturn
  Labels:
  LocalVariableTable: 
   Start  Length  Slot  Name   Signature
   0      5      0    this       Lscala/concurrent/forkjoin/ForkJoinPool$AdaptedRunnable;

  LocalVariableTypeTable: length = 0xC
   00 01 00 00 00 05 00 18 00 1D 00 00 
  Signature: length = 0x2
   00 21 

public void setRawResult(java.lang.Object);
  Signature: (Ljava/lang/Object;)V
  Code:
   Stack=2, Locals=2, Args_size=2
	aload_0
	aload_1
	putfield	Field result:Ljava/lang/Object;
	return
  Labels:
  LocalVariableTable: 
   Start  Length  Slot  Name   Signature
   0      6      0    this       Lscala/concurrent/forkjoin/ForkJoinPool$AdaptedRunnable;
   0      6      1    v       Ljava/lang/Object;

  LocalVariableTypeTable: length = 0x16
   00 02 00 00 00 06 00 18 00 1D 00 00 00 00 00 06
   00 24 00 11 00 01 
  Signature: length = 0x2
   00 25 

public boolean exec();
  Signature: ()Z
  Code:
   Stack=2, Locals=1, Args_size=1
	aload_0
	getfield	Field runnable:Ljava/lang/Runnable;
	invokeinterface	InterfaceMethod java/lang/Runnable.run:()V
	aload_0
	aload_0
	getfield	Field resultOnCompletion:Ljava/lang/Object;
	putfield	Field result:Ljava/lang/Object;
	iconst_1
	ireturn
  Labels:
  LocalVariableTable: 
   Start  Length  Slot  Name   Signature
   0      19      0    this       Lscala/concurrent/forkjoin/ForkJoinPool$AdaptedRunnable;

  LocalVariableTypeTable: length = 0xC
   00 01 00 00 00 13 00 18 00 1D 00 00 

public void run();
  Signature: ()V
  Code:
   Stack=1, Locals=1, Args_size=1
	aload_0
	invokevirtual	Method invoke:()Ljava/lang/Object;
	pop
	return
  Labels:
  LocalVariableTable: 
   Start  Length  Slot  Name   Signature
   0      6      0    this       Lscala/concurrent/forkjoin/ForkJoinPool$AdaptedRunnable;

  LocalVariableTypeTable: length = 0xC
   00 01 00 00 00 06 00 18 00 1D 00 00 

}

