Compiled from "ForkJoinPool.java"
final class scala.concurrent.forkjoin.ForkJoinPool$1 extends java.lang.Object implements java.security.PrivilegedExceptionAction
  Signature: length = 0x2
   00 16 
  SourceFile: "ForkJoinPool.java"
  EnclosingMethod: length = 0x4
   00 1A 00 1B 
  InnerClass: 
   #4; //class scala/concurrent/forkjoin/ForkJoinPool$1
  minor version: 0
  major version: 49
  Constant pool:
const #1 = Method	#5.#28;	//  java/lang/Object."<init>":()V
const #2 = Method	#26.#29;	//  scala/concurrent/forkjoin/ForkJoinPool.access$000:()Lsun/misc/Unsafe;
const #3 = Method	#4.#30;	//  scala/concurrent/forkjoin/ForkJoinPool$1.run:()Lsun/misc/Unsafe;
const #4 = class	#31;	//  scala/concurrent/forkjoin/ForkJoinPool$1
const #5 = class	#32;	//  java/lang/Object
const #6 = class	#33;	//  java/security/PrivilegedExceptionAction
const #7 = Asciz	<init>;
const #8 = Asciz	()V;
const #9 = Asciz	Code;
const #10 = Asciz	LineNumberTable;
const #11 = Asciz	LocalVariableTable;
const #12 = Asciz	this;
const #13 = Asciz	;
const #14 = Asciz	InnerClasses;
const #15 = Asciz	Lscala/concurrent/forkjoin/ForkJoinPool$1;;
const #16 = Asciz	run;
const #17 = Asciz	()Lsun/misc/Unsafe;;
const #18 = Asciz	Exceptions;
const #19 = class	#34;	//  java/lang/Exception
const #20 = Asciz	()Ljava/lang/Object;;
const #21 = Asciz	Signature;
const #22 = Asciz	Ljava/lang/Object;Ljava/security/PrivilegedExceptionAction<Lsun/misc/Unsafe;>;;
const #23 = Asciz	SourceFile;
const #24 = Asciz	ForkJoinPool.java;
const #25 = Asciz	EnclosingMethod;
const #26 = class	#35;	//  scala/concurrent/forkjoin/ForkJoinPool
const #27 = NameAndType	#36:#17;//  getUnsafe:()Lsun/misc/Unsafe;
const #28 = NameAndType	#7:#8;//  "<init>":()V
const #29 = NameAndType	#37:#17;//  access$000:()Lsun/misc/Unsafe;
const #30 = NameAndType	#16:#17;//  run:()Lsun/misc/Unsafe;
const #31 = Asciz	scala/concurrent/forkjoin/ForkJoinPool$1;
const #32 = Asciz	java/lang/Object;
const #33 = Asciz	java/security/PrivilegedExceptionAction;
const #34 = Asciz	java/lang/Exception;
const #35 = Asciz	scala/concurrent/forkjoin/ForkJoinPool;
const #36 = Asciz	getUnsafe;
const #37 = Asciz	access$000;

{
scala.concurrent.forkjoin.ForkJoinPool$1();
  Code:
   Stack=1, Locals=1, Args_size=1
   0:	aload_0
   1:	invokespecial	#1; //Method java/lang/Object."<init>":()V
   4:	return
  LineNumberTable: 
   line 1812: 0

  LocalVariableTable: 
   Start  Length  Slot  Name   Signature
   0      5      0    this       Lscala/concurrent/forkjoin/ForkJoinPool$1;


public sun.misc.Unsafe run()   throws java.lang.Exception;
  Code:
   Stack=1, Locals=1, Args_size=1
   0:	invokestatic	#2; //Method scala/concurrent/forkjoin/ForkJoinPool.access$000:()Lsun/misc/Unsafe;
   3:	areturn
  LineNumberTable: 
   line 1814: 0

  LocalVariableTable: 
   Start  Length  Slot  Name   Signature
   0      4      0    this       Lscala/concurrent/forkjoin/ForkJoinPool$1;

  Exceptions: 
   throws java.lang.Exception
public java.lang.Object run()   throws java.lang.Exception;
  Code:
   Stack=1, Locals=1, Args_size=1
   0:	aload_0
   1:	invokevirtual	#3; //Method run:()Lsun/misc/Unsafe;
   4:	areturn
  LineNumberTable: 
   line 1812: 0

  LocalVariableTable: 
   Start  Length  Slot  Name   Signature
   0      5      0    this       Lscala/concurrent/forkjoin/ForkJoinPool$1;

  Exceptions: 
   throws java.lang.Exception
}

