Compiled from "ForkJoinPool.java"
final class scala.concurrent.forkjoin.ForkJoinPool$AdaptedCallable extends scala.concurrent.forkjoin.ForkJoinTask implements scala.concurrent.forkjoin.ForkJoinPool$RunnableFuture
  Signature: length = 0x2
   00 34 
  SourceFile: "ForkJoinPool.java"
  InnerClass: 
   final AdaptedCallable=class scala/concurrent/forkjoin/ForkJoinPool$AdaptedCallable of class scala/concurrent/forkjoin/ForkJoinPool
   abstract RunnableFuture=class scala/concurrent/forkjoin/ForkJoinPool$RunnableFuture of class scala/concurrent/forkjoin/ForkJoinPool
  minor version: 0
  major version: 49
  Constant pool:
Method	scala/concurrent/forkjoin/ForkJoinTask."<init>":()V
class	java/lang/NullPointerException
Method	java/lang/NullPointerException."<init>":()V
Field	scala/concurrent/forkjoin/ForkJoinPool$AdaptedCallable.callable:Ljava/util/concurrent/Callable;
Field	scala/concurrent/forkjoin/ForkJoinPool$AdaptedCallable.result:Ljava/lang/Object;
InterfaceMethod	java/util/concurrent/Callable.call:()Ljava/lang/Object;
class	java/lang/Error
class	java/lang/RuntimeException
class	java/lang/Exception
Method	java/lang/RuntimeException."<init>":(Ljava/lang/Throwable;)V
Method	scala/concurrent/forkjoin/ForkJoinPool$AdaptedCallable.invoke:()Ljava/lang/Object;
class	scala/concurrent/forkjoin/ForkJoinPool$AdaptedCallable
class	scala/concurrent/forkjoin/ForkJoinTask
class	scala/concurrent/forkjoin/ForkJoinPool$RunnableFuture
Asciz	callable;
Asciz	Ljava/util/concurrent/Callable;;
Asciz	Signature;
Asciz	Ljava/util/concurrent/Callable<TT;>;;
Asciz	result;
Asciz	Ljava/lang/Object;;
Asciz	TT;;
Asciz	<init>;
Asciz	(Ljava/util/concurrent/Callable;)V;
Asciz	Code;
Asciz	LineNumberTable;
Asciz	LocalVariableTable;
Asciz	this;
Asciz	AdaptedCallable;
Asciz	InnerClasses;
Asciz	Lscala/concurrent/forkjoin/ForkJoinPool$AdaptedCallable;;
Asciz	LocalVariableTypeTable;
Asciz	Lscala/concurrent/forkjoin/ForkJoinPool$AdaptedCallable<TT;>;;
Asciz	(Ljava/util/concurrent/Callable<TT;>;)V;
Asciz	getRawResult;
Asciz	()Ljava/lang/Object;;
Asciz	()TT;;
Asciz	setRawResult;
Asciz	(Ljava/lang/Object;)V;
Asciz	v;
Asciz	(TT;)V;
Asciz	exec;
Asciz	()Z;
Asciz	err;
Asciz	Ljava/lang/Error;;
Asciz	rex;
Asciz	Ljava/lang/RuntimeException;;
Asciz	ex;
Asciz	Ljava/lang/Exception;;
Asciz	run;
Asciz	()V;
Asciz	RunnableFuture;
Asciz	<T:Ljava/lang/Object;>Lscala/concurrent/forkjoin/ForkJoinTask<TT;>;Lscala/concurrent/forkjoin/ForkJoinPool$RunnableFuture<TT;>;;
Asciz	SourceFile;
Asciz	ForkJoinPool.java;
NameAndType	"<init>":()V
Asciz	java/lang/NullPointerException;
NameAndType	callable:Ljava/util/concurrent/Callable;
NameAndType	result:Ljava/lang/Object;
class	java/util/concurrent/Callable
NameAndType	call:()Ljava/lang/Object;
Asciz	java/lang/Error;
Asciz	java/lang/RuntimeException;
Asciz	java/lang/Exception;
NameAndType	"<init>":(Ljava/lang/Throwable;)V
NameAndType	invoke:()Ljava/lang/Object;
class	scala/concurrent/forkjoin/ForkJoinPool
Asciz	scala/concurrent/forkjoin/ForkJoinPool$AdaptedCallable;
Asciz	scala/concurrent/forkjoin/ForkJoinTask;
Asciz	scala/concurrent/forkjoin/ForkJoinPool$RunnableFuture;
Asciz	java/util/concurrent/Callable;
Asciz	call;
Asciz	(Ljava/lang/Throwable;)V;
Asciz	invoke;
Asciz	scala/concurrent/forkjoin/ForkJoinPool;

{
final java.util.concurrent.Callable callable;
  Signature: Ljava/util/concurrent/Callable;
  Signature: length = 0x2
   00 12 

java.lang.Object result;
  Signature: Ljava/lang/Object;
  Signature: length = 0x2
   00 15 

scala.concurrent.forkjoin.ForkJoinPool$AdaptedCallable(java.util.concurrent.Callable);
  Signature: (Ljava/util/concurrent/Callable;)V
  Code:
   Stack=2, Locals=2, Args_size=2
	aload_0
	invokespecial	Method scala/concurrent/forkjoin/ForkJoinTask."<init>":()V
	aload_1
	ifnonnull	l1 // aload_0
	new	class java/lang/NullPointerException
	dup
	invokespecial	Method java/lang/NullPointerException."<init>":()V
	athrow
l1	aload_0
	aload_1
	putfield	Field callable:Ljava/util/concurrent/Callable;
	return
  Labels:
   	l1 = 16 // aload_0
  LocalVariableTable: 
   Start  Length  Slot  Name   Signature
   0      22      0    this       Lscala/concurrent/forkjoin/ForkJoinPool$AdaptedCallable;
   0      22      1    callable       Ljava/util/concurrent/Callable;

  LocalVariableTypeTable: length = 0x16
   00 02 00 00 00 16 00 1B 00 20 00 00 00 00 00 16
   00 0F 00 12 00 01 
  Signature: length = 0x2
   00 21 

public java.lang.Object getRawResult();
  Signature: ()Ljava/lang/Object;
  Code:
   Stack=1, Locals=1, Args_size=1
	aload_0
	getfield	Field result:Ljava/lang/Object;
	areturn
  Labels:
  LocalVariableTable: 
   Start  Length  Slot  Name   Signature
   0      5      0    this       Lscala/concurrent/forkjoin/ForkJoinPool$AdaptedCallable;

  LocalVariableTypeTable: length = 0xC
   00 01 00 00 00 05 00 1B 00 20 00 00 
  Signature: length = 0x2
   00 24 

public void setRawResult(java.lang.Object);
  Signature: (Ljava/lang/Object;)V
  Code:
   Stack=2, Locals=2, Args_size=2
	aload_0
	aload_1
	putfield	Field result:Ljava/lang/Object;
	return
  Labels:
  LocalVariableTable: 
   Start  Length  Slot  Name   Signature
   0      6      0    this       Lscala/concurrent/forkjoin/ForkJoinPool$AdaptedCallable;
   0      6      1    v       Ljava/lang/Object;

  LocalVariableTypeTable: length = 0x16
   00 02 00 00 00 06 00 1B 00 20 00 00 00 00 00 06
   00 27 00 15 00 01 
  Signature: length = 0x2
   00 28 

public boolean exec();
  Signature: ()Z
  Code:
   Stack=3, Locals=2, Args_size=1
	aload_0
	aload_0
	getfield	Field callable:Ljava/util/concurrent/Callable;
	invokeinterface	InterfaceMethod java/util/concurrent/Callable.call:()Ljava/lang/Object;
	putfield	Field result:Ljava/lang/Object;
	iconst_1
	ireturn
	astore_1
	aload_1
	athrow
	astore_1
	aload_1
	athrow
	astore_1
	new	class java/lang/RuntimeException
	dup
	aload_1
	invokespecial	Method java/lang/RuntimeException."<init>":(Ljava/lang/Throwable;)V
	athrow
  Labels:
  Exception table:
   from   to  target type
     0    14    15   Class java/lang/Error

     0    14    18   Class java/lang/RuntimeException

     0    14    21   Class java/lang/Exception

  LocalVariableTable: 
   Start  Length  Slot  Name   Signature
   16      2      1    err       Ljava/lang/Error;
   19      2      1    rex       Ljava/lang/RuntimeException;
   22      9      1    ex       Ljava/lang/Exception;
   0      31      0    this       Lscala/concurrent/forkjoin/ForkJoinPool$AdaptedCallable;

  LocalVariableTypeTable: length = 0xC
   00 01 00 00 00 1F 00 1B 00 20 00 00 

public void run();
  Signature: ()V
  Code:
   Stack=1, Locals=1, Args_size=1
	aload_0
	invokevirtual	Method invoke:()Ljava/lang/Object;
	pop
	return
  Labels:
  LocalVariableTable: 
   Start  Length  Slot  Name   Signature
   0      6      0    this       Lscala/concurrent/forkjoin/ForkJoinPool$AdaptedCallable;

  LocalVariableTypeTable: length = 0xC
   00 01 00 00 00 06 00 1B 00 20 00 00 

}

