Compiled from "ForkJoinWorkerThread.java"
public class scala.concurrent.forkjoin.ForkJoinWorkerThread extends java.lang.Thread
  SourceFile: "ForkJoinWorkerThread.java"
  InnerClass: 
   class scala/concurrent/forkjoin/ForkJoinWorkerThread$1
  minor version: 0
  major version: 49
  Constant pool:
Method	scala/concurrent/forkjoin/ForkJoinWorkerThread.getUnsafePrivileged:()Lsun/misc/Unsafe;
Method	java/lang/Thread."<init>":()V
class	java/lang/NullPointerException
Method	java/lang/NullPointerException."<init>":()V
Field	scala/concurrent/forkjoin/ForkJoinWorkerThread.pool:Lscala/concurrent/forkjoin/ForkJoinPool;
Field	scala/concurrent/forkjoin/ForkJoinWorkerThread.poolIndex:I
Field	scala/concurrent/forkjoin/ForkJoinWorkerThread.locallyFifo:Z
Field	scala/concurrent/forkjoin/ForkJoinWorkerThread.runState:I
Method	scala/concurrent/forkjoin/ForkJoinWorkerThread.transitionRunStateTo:(I)Z
Field	scala/concurrent/forkjoin/ForkJoinWorkerThread._unsafe:Lsun/misc/Unsafe;
Field	scala/concurrent/forkjoin/ForkJoinWorkerThread.runStateOffset:J
Method	sun/misc/Unsafe.compareAndSwapInt:(Ljava/lang/Object;JII)Z
Field	scala/concurrent/forkjoin/ForkJoinWorkerThread.active:Z
Method	scala/concurrent/forkjoin/ForkJoinPool.tryIncrementActiveCount:()Z
Method	scala/concurrent/forkjoin/ForkJoinPool.tryDecrementActiveCount:()Z
Method	scala/concurrent/forkjoin/ForkJoinWorkerThread.onStart:()V
Method	scala/concurrent/forkjoin/ForkJoinPool.sync:(Lscala/concurrent/forkjoin/ForkJoinWorkerThread;)V
Method	scala/concurrent/forkjoin/ForkJoinWorkerThread.mainLoop:()V
Method	scala/concurrent/forkjoin/ForkJoinWorkerThread.onTermination:(Ljava/lang/Throwable;)V
class	java/lang/Throwable
Method	scala/concurrent/forkjoin/ForkJoinWorkerThread.isShutdown:()Z
Method	scala/concurrent/forkjoin/ForkJoinWorkerThread.pollTask:()Lscala/concurrent/forkjoin/ForkJoinTask;
Method	scala/concurrent/forkjoin/ForkJoinWorkerThread.pollSubmission:()Lscala/concurrent/forkjoin/ForkJoinTask;
Method	scala/concurrent/forkjoin/ForkJoinTask.quietlyExec:()V
Method	scala/concurrent/forkjoin/ForkJoinWorkerThread.tryInactivate:()Z
class	scala/concurrent/forkjoin/ForkJoinTask
Field	scala/concurrent/forkjoin/ForkJoinWorkerThread.queue:[Lscala/concurrent/forkjoin/ForkJoinTask;
Field	scala/concurrent/forkjoin/ForkJoinWorkerThread.seed:I
Method	scala/concurrent/forkjoin/ForkJoinPool.isTerminating:()Z
Field	scala/concurrent/forkjoin/ForkJoinWorkerThread.base:I
Field	scala/concurrent/forkjoin/ForkJoinWorkerThread.sp:I
Method	scala/concurrent/forkjoin/ForkJoinWorkerThread.popTask:()Lscala/concurrent/forkjoin/ForkJoinTask;
Method	scala/concurrent/forkjoin/ForkJoinWorkerThread.cancelTasks:()V
Method	scala/concurrent/forkjoin/ForkJoinPool.workerTerminated:(Lscala/concurrent/forkjoin/ForkJoinWorkerThread;)V
Method	scala/concurrent/forkjoin/ForkJoinTask.rethrowException:(Ljava/lang/Throwable;)V
Field	scala/concurrent/forkjoin/ForkJoinWorkerThread.qShift:I
Field	scala/concurrent/forkjoin/ForkJoinWorkerThread.qBase:J
Method	sun/misc/Unsafe.putOrderedObject:(Ljava/lang/Object;JLjava/lang/Object;)V
Method	sun/misc/Unsafe.compareAndSwapObject:(Ljava/lang/Object;JLjava/lang/Object;Ljava/lang/Object;)Z
Field	scala/concurrent/forkjoin/ForkJoinWorkerThread.spOffset:J
Method	sun/misc/Unsafe.putOrderedInt:(Ljava/lang/Object;JI)V
Method	scala/concurrent/forkjoin/ForkJoinWorkerThread.setSlot:([Lscala/concurrent/forkjoin/ForkJoinTask;ILscala/concurrent/forkjoin/ForkJoinTask;)V
Method	scala/concurrent/forkjoin/ForkJoinWorkerThread.storeSp:(I)V
Method	scala/concurrent/forkjoin/ForkJoinPool.signalWork:()V
Method	scala/concurrent/forkjoin/ForkJoinWorkerThread.growQueue:()V
Method	scala/concurrent/forkjoin/ForkJoinWorkerThread.casSlotNull:([Lscala/concurrent/forkjoin/ForkJoinTask;ILscala/concurrent/forkjoin/ForkJoinTask;)Z
Method	scala/concurrent/forkjoin/ForkJoinWorkerThread.tryActivate:()Z
int	268435456;
class	java/util/concurrent/RejectedExecutionException
String	Queue capacity exceeded
Method	java/util/concurrent/RejectedExecutionException."<init>":(Ljava/lang/String;)V
Field	scala/concurrent/forkjoin/ForkJoinPool.workers:[Lscala/concurrent/forkjoin/ForkJoinWorkerThread;
Method	scala/concurrent/forkjoin/ForkJoinWorkerThread.xorShift:(I)I
Method	scala/concurrent/forkjoin/ForkJoinWorkerThread.deqTask:()Lscala/concurrent/forkjoin/ForkJoinTask;
Method	scala/concurrent/forkjoin/ForkJoinPool.hasNewSyncEvent:(Lscala/concurrent/forkjoin/ForkJoinWorkerThread;)Z
Method	scala/concurrent/forkjoin/ForkJoinWorkerThread.scan:()Lscala/concurrent/forkjoin/ForkJoinTask;
Field	scala/concurrent/forkjoin/ForkJoinWorkerThread.stealCount:I
Method	scala/concurrent/forkjoin/ForkJoinPool.hasQueuedSubmissions:()Z
Method	scala/concurrent/forkjoin/ForkJoinPool.pollSubmission:()Lscala/concurrent/forkjoin/ForkJoinTask;
Method	scala/concurrent/forkjoin/ForkJoinTask.cancelIgnoringExceptions:()V
InterfaceMethod	java/util/Collection.add:(Ljava/lang/Object;)Z
Method	scala/concurrent/forkjoin/ForkJoinPool.getIdleThreadCount:()I
Field	scala/concurrent/forkjoin/ForkJoinTask.status:I
Method	scala/concurrent/forkjoin/ForkJoinWorkerThread.pushTask:(Lscala/concurrent/forkjoin/ForkJoinTask;)V
Method	scala/concurrent/forkjoin/ForkJoinPool.isQuiescent:()Z
Method	sun/misc/Unsafe.getUnsafe:()Lsun/misc/Unsafe;
class	java/lang/SecurityException
class	scala/concurrent/forkjoin/ForkJoinWorkerThread$1
Method	scala/concurrent/forkjoin/ForkJoinWorkerThread$1."<init>":()V
Method	java/security/AccessController.doPrivileged:(Ljava/security/PrivilegedExceptionAction;)Ljava/lang/Object;
class	sun/misc/Unsafe
class	java/security/PrivilegedActionException
Method	java/security/PrivilegedActionException.getCause:()Ljava/lang/Throwable;
String	theUnsafe
Method	java/lang/Class.getDeclaredField:(Ljava/lang/String;)Ljava/lang/reflect/Field;
Method	java/lang/reflect/Field.setAccessible:(Z)V
Method	java/lang/reflect/Field.get:(Ljava/lang/Object;)Ljava/lang/Object;
class	scala/concurrent/forkjoin/ForkJoinWorkerThread
Method	sun/misc/Unsafe.objectFieldOffset:(Ljava/lang/reflect/Field;)J
Method	scala/concurrent/forkjoin/ForkJoinWorkerThread.getUnsafe:()Lsun/misc/Unsafe;
String	base
Method	scala/concurrent/forkjoin/ForkJoinWorkerThread.fieldOffset:(Ljava/lang/String;)J
Field	scala/concurrent/forkjoin/ForkJoinWorkerThread.baseOffset:J
String	sp
String	runState
class	"[Lscala/concurrent/forkjoin/ForkJoinTask;"
Method	sun/misc/Unsafe.arrayBaseOffset:(Ljava/lang/Class;)I
Method	sun/misc/Unsafe.arrayIndexScale:(Ljava/lang/Class;)I
class	java/lang/Error
String	data type scale not a power of two
Method	java/lang/Error."<init>":(Ljava/lang/String;)V
Method	java/lang/Integer.numberOfLeadingZeros:(I)I
class	java/lang/RuntimeException
String	Could not initialize intrinsics
Method	java/lang/RuntimeException."<init>":(Ljava/lang/String;Ljava/lang/Throwable;)V
class	java/lang/Thread
Asciz	INITIAL_QUEUE_CAPACITY;
Asciz	I;
Asciz	ConstantValue;
int	8192;
Asciz	MAXIMUM_QUEUE_CAPACITY;
Asciz	pool;
Asciz	Lscala/concurrent/forkjoin/ForkJoinPool;;
Asciz	queue;
Asciz	[Lscala/concurrent/forkjoin/ForkJoinTask;;
Asciz	Signature;
Asciz	[Lscala/concurrent/forkjoin/ForkJoinTask<*>;;
Asciz	sp;
Asciz	base;
Asciz	active;
Asciz	Z;
Asciz	runState;
Asciz	seed;
Asciz	stealCount;
Asciz	poolIndex;
Asciz	lastEventCount;
Asciz	J;
Asciz	locallyFifo;
Asciz	RUNNING;
int	0;
Asciz	SHUTDOWN;
int	1;
Asciz	TERMINATING;
int	2;
Asciz	TERMINATED;
int	3;
Asciz	_unsafe;
Asciz	Lsun/misc/Unsafe;;
Asciz	baseOffset;
Asciz	spOffset;
Asciz	runStateOffset;
Asciz	qBase;
Asciz	qShift;
Asciz	<init>;
Asciz	(Lscala/concurrent/forkjoin/ForkJoinPool;)V;
Asciz	Code;
Asciz	LineNumberTable;
Asciz	LocalVariableTable;
Asciz	this;
Asciz	Lscala/concurrent/forkjoin/ForkJoinWorkerThread;;
Asciz	getPool;
Asciz	()Lscala/concurrent/forkjoin/ForkJoinPool;;
Asciz	getPoolIndex;
Asciz	()I;
Asciz	setAsyncMode;
Asciz	(Z)V;
Asciz	async;
Asciz	isShutdown;
Asciz	()Z;
Asciz	isTerminating;
Asciz	isTerminated;
Asciz	shutdown;
Asciz	shutdownNow;
Asciz	transitionRunStateTo;
Asciz	(I)Z;
Asciz	s;
Asciz	state;
Asciz	tryActivate;
Asciz	tryInactivate;
Asciz	xorShift;
Asciz	(I)I;
Asciz	r;
Asciz	run;
Asciz	()V;
Asciz	ex;
Asciz	Ljava/lang/Throwable;;
Asciz	exception;
Asciz	mainLoop;
Asciz	t;
Asciz	Lscala/concurrent/forkjoin/ForkJoinTask;;
Asciz	LocalVariableTypeTable;
Asciz	Lscala/concurrent/forkjoin/ForkJoinTask<*>;;
Asciz	onStart;
Asciz	p;
Asciz	onTermination;
Asciz	(Ljava/lang/Throwable;)V;
Asciz	setSlot;
Asciz	([Lscala/concurrent/forkjoin/ForkJoinTask;ILscala/concurrent/forkjoin/ForkJoinTask;)V;
Asciz	q;
Asciz	i;
Asciz	([Lscala/concurrent/forkjoin/ForkJoinTask<*>;ILscala/concurrent/forkjoin/ForkJoinTask<*>;)V;
Asciz	casSlotNull;
Asciz	([Lscala/concurrent/forkjoin/ForkJoinTask;ILscala/concurrent/forkjoin/ForkJoinTask;)Z;
Asciz	([Lscala/concurrent/forkjoin/ForkJoinTask<*>;ILscala/concurrent/forkjoin/ForkJoinTask<*>;)Z;
Asciz	storeSp;
Asciz	(I)V;
Asciz	pushTask;
Asciz	(Lscala/concurrent/forkjoin/ForkJoinTask;)V;
Asciz	mask;
Asciz	(Lscala/concurrent/forkjoin/ForkJoinTask<*>;)V;
Asciz	deqTask;
Asciz	()Lscala/concurrent/forkjoin/ForkJoinTask;;
Asciz	b;
Asciz	()Lscala/concurrent/forkjoin/ForkJoinTask<*>;;
Asciz	popTask;
Asciz	unpushTask;
Asciz	(Lscala/concurrent/forkjoin/ForkJoinTask;)Z;
Asciz	(Lscala/concurrent/forkjoin/ForkJoinTask<*>;)Z;
Asciz	peekTask;
Asciz	growQueue;
Asciz	oldIndex;
Asciz	oldQ;
Asciz	oldSize;
Asciz	newSize;
Asciz	newQ;
Asciz	bf;
Asciz	oldMask;
Asciz	newMask;
Asciz	scan;
Asciz	v;
Asciz	idx;
Asciz	probes;
Asciz	ws;
Asciz	[Lscala/concurrent/forkjoin/ForkJoinWorkerThread;;
Asciz	pollTask;
Asciz	pollLocalTask;
Asciz	pollSubmission;
Asciz	cancelTasks;
Asciz	drainTasksTo;
Asciz	(Ljava/util/Collection;)I;
Asciz	c;
Asciz	Ljava/util/Collection;;
Asciz	n;
Asciz	Ljava/util/Collection<Lscala/concurrent/forkjoin/ForkJoinTask<*>;>;;
Asciz	(Ljava/util/Collection<Lscala/concurrent/forkjoin/ForkJoinTask<*>;>;)I;
Asciz	getAndClearStealCount;
Asciz	sc;
Asciz	hasQueuedTasks;
Asciz	([Lscala/concurrent/forkjoin/ForkJoinWorkerThread;)Z;
Asciz	w;
Asciz	j;
Asciz	len;
Asciz	getQueueSize;
Asciz	getEstimatedSurplusTaskCount;
Asciz	scanWhileJoining;
Asciz	(Lscala/concurrent/forkjoin/ForkJoinTask;)Lscala/concurrent/forkjoin/ForkJoinTask;;
Asciz	joinMe;
Asciz	(Lscala/concurrent/forkjoin/ForkJoinTask<*>;)Lscala/concurrent/forkjoin/ForkJoinTask<*>;;
Asciz	helpQuiescePool;
Asciz	getUnsafe;
Asciz	()Lsun/misc/Unsafe;;
Asciz	e;
Asciz	Ljava/security/PrivilegedActionException;;
Asciz	se;
Asciz	Ljava/lang/SecurityException;;
Asciz	Exceptions;
Asciz	getUnsafePrivileged;
Asciz	f;
Asciz	Ljava/lang/reflect/Field;;
class	java/lang/NoSuchFieldException
class	java/lang/IllegalAccessException
Asciz	fieldOffset;
Asciz	(Ljava/lang/String;)J;
Asciz	fieldName;
Asciz	Ljava/lang/String;;
Asciz	access$000;
Asciz	<clinit>;
Asciz	SourceFile;
Asciz	ForkJoinWorkerThread.java;
NameAndType	getUnsafePrivileged:()Lsun/misc/Unsafe;
NameAndType	"<init>":()V
Asciz	java/lang/NullPointerException;
NameAndType	pool:Lscala/concurrent/forkjoin/ForkJoinPool;
NameAndType	poolIndex:I
NameAndType	locallyFifo:Z
NameAndType	runState:I
NameAndType	transitionRunStateTo:(I)Z
NameAndType	_unsafe:Lsun/misc/Unsafe;
NameAndType	runStateOffset:J
NameAndType	compareAndSwapInt:(Ljava/lang/Object;JII)Z
NameAndType	active:Z
class	scala/concurrent/forkjoin/ForkJoinPool
NameAndType	tryIncrementActiveCount:()Z
NameAndType	tryDecrementActiveCount:()Z
NameAndType	onStart:()V
NameAndType	sync:(Lscala/concurrent/forkjoin/ForkJoinWorkerThread;)V
NameAndType	mainLoop:()V
NameAndType	onTermination:(Ljava/lang/Throwable;)V
Asciz	java/lang/Throwable;
NameAndType	isShutdown:()Z
NameAndType	pollTask:()Lscala/concurrent/forkjoin/ForkJoinTask;
NameAndType	pollSubmission:()Lscala/concurrent/forkjoin/ForkJoinTask;
NameAndType	quietlyExec:()V
NameAndType	tryInactivate:()Z
Asciz	scala/concurrent/forkjoin/ForkJoinTask;
NameAndType	queue:[Lscala/concurrent/forkjoin/ForkJoinTask;
NameAndType	seed:I
NameAndType	isTerminating:()Z
NameAndType	base:I
NameAndType	sp:I
NameAndType	popTask:()Lscala/concurrent/forkjoin/ForkJoinTask;
NameAndType	cancelTasks:()V
NameAndType	workerTerminated:(Lscala/concurrent/forkjoin/ForkJoinWorkerThread;)V
NameAndType	rethrowException:(Ljava/lang/Throwable;)V
NameAndType	qShift:I
NameAndType	qBase:J
NameAndType	putOrderedObject:(Ljava/lang/Object;JLjava/lang/Object;)V
NameAndType	compareAndSwapObject:(Ljava/lang/Object;JLjava/lang/Object;Ljava/lang/Object;)Z
NameAndType	spOffset:J
NameAndType	putOrderedInt:(Ljava/lang/Object;JI)V
NameAndType	setSlot:([Lscala/concurrent/forkjoin/ForkJoinTask;ILscala/concurrent/forkjoin/ForkJoinTask;)V
NameAndType	storeSp:(I)V
NameAndType	signalWork:()V
NameAndType	growQueue:()V
NameAndType	casSlotNull:([Lscala/concurrent/forkjoin/ForkJoinTask;ILscala/concurrent/forkjoin/ForkJoinTask;)Z
NameAndType	tryActivate:()Z
Asciz	java/util/concurrent/RejectedExecutionException;
Asciz	Queue capacity exceeded;
NameAndType	"<init>":(Ljava/lang/String;)V
NameAndType	workers:[Lscala/concurrent/forkjoin/ForkJoinWorkerThread;
NameAndType	xorShift:(I)I
NameAndType	deqTask:()Lscala/concurrent/forkjoin/ForkJoinTask;
NameAndType	hasNewSyncEvent:(Lscala/concurrent/forkjoin/ForkJoinWorkerThread;)Z
NameAndType	scan:()Lscala/concurrent/forkjoin/ForkJoinTask;
NameAndType	stealCount:I
NameAndType	hasQueuedSubmissions:()Z
NameAndType	cancelIgnoringExceptions:()V
class	java/util/Collection
NameAndType	add:(Ljava/lang/Object;)Z
NameAndType	getIdleThreadCount:()I
NameAndType	status:I
NameAndType	pushTask:(Lscala/concurrent/forkjoin/ForkJoinTask;)V
NameAndType	isQuiescent:()Z
NameAndType	getUnsafe:()Lsun/misc/Unsafe;
Asciz	java/lang/SecurityException;
Asciz	scala/concurrent/forkjoin/ForkJoinWorkerThread$1;
Asciz	;
Asciz	InnerClasses;
class	java/security/AccessController
NameAndType	doPrivileged:(Ljava/security/PrivilegedExceptionAction;)Ljava/lang/Object;
Asciz	sun/misc/Unsafe;
Asciz	java/security/PrivilegedActionException;
NameAndType	getCause:()Ljava/lang/Throwable;
Asciz	theUnsafe;
class	java/lang/Class
NameAndType	getDeclaredField:(Ljava/lang/String;)Ljava/lang/reflect/Field;
class	java/lang/reflect/Field
NameAndType	setAccessible:(Z)V
NameAndType	get:(Ljava/lang/Object;)Ljava/lang/Object;
Asciz	scala/concurrent/forkjoin/ForkJoinWorkerThread;
NameAndType	objectFieldOffset:(Ljava/lang/reflect/Field;)J
NameAndType	fieldOffset:(Ljava/lang/String;)J
NameAndType	baseOffset:J
NameAndType	arrayBaseOffset:(Ljava/lang/Class;)I
NameAndType	arrayIndexScale:(Ljava/lang/Class;)I
Asciz	java/lang/Error;
Asciz	data type scale not a power of two;
class	java/lang/Integer
NameAndType	numberOfLeadingZeros:(I)I
Asciz	java/lang/RuntimeException;
Asciz	Could not initialize intrinsics;
NameAndType	"<init>":(Ljava/lang/String;Ljava/lang/Throwable;)V
Asciz	java/lang/Thread;
Asciz	java/lang/NoSuchFieldException;
Asciz	java/lang/IllegalAccessException;
Asciz	compareAndSwapInt;
Asciz	(Ljava/lang/Object;JII)Z;
Asciz	scala/concurrent/forkjoin/ForkJoinPool;
Asciz	tryIncrementActiveCount;
Asciz	tryDecrementActiveCount;
Asciz	sync;
Asciz	(Lscala/concurrent/forkjoin/ForkJoinWorkerThread;)V;
Asciz	quietlyExec;
Asciz	workerTerminated;
Asciz	rethrowException;
Asciz	putOrderedObject;
Asciz	(Ljava/lang/Object;JLjava/lang/Object;)V;
Asciz	compareAndSwapObject;
Asciz	(Ljava/lang/Object;JLjava/lang/Object;Ljava/lang/Object;)Z;
Asciz	putOrderedInt;
Asciz	(Ljava/lang/Object;JI)V;
Asciz	signalWork;
Asciz	(Ljava/lang/String;)V;
Asciz	workers;
Asciz	hasNewSyncEvent;
Asciz	(Lscala/concurrent/forkjoin/ForkJoinWorkerThread;)Z;
Asciz	hasQueuedSubmissions;
Asciz	cancelIgnoringExceptions;
Asciz	java/util/Collection;
Asciz	add;
Asciz	(Ljava/lang/Object;)Z;
Asciz	getIdleThreadCount;
Asciz	status;
Asciz	isQuiescent;
Asciz	java/security/AccessController;
Asciz	doPrivileged;
Asciz	(Ljava/security/PrivilegedExceptionAction;)Ljava/lang/Object;;
Asciz	getCause;
Asciz	()Ljava/lang/Throwable;;
Asciz	java/lang/Class;
Asciz	getDeclaredField;
Asciz	(Ljava/lang/String;)Ljava/lang/reflect/Field;;
Asciz	java/lang/reflect/Field;
Asciz	setAccessible;
Asciz	get;
Asciz	(Ljava/lang/Object;)Ljava/lang/Object;;
Asciz	objectFieldOffset;
Asciz	(Ljava/lang/reflect/Field;)J;
Asciz	arrayBaseOffset;
Asciz	(Ljava/lang/Class;)I;
Asciz	arrayIndexScale;
Asciz	java/lang/Integer;
Asciz	numberOfLeadingZeros;
Asciz	(Ljava/lang/String;Ljava/lang/Throwable;)V;

{
private static final int INITIAL_QUEUE_CAPACITY;
  Signature: I
  Constant value: int 8192
private static final int MAXIMUM_QUEUE_CAPACITY;
  Signature: I
  Constant value: int 268435456
final scala.concurrent.forkjoin.ForkJoinPool pool;
  Signature: Lscala/concurrent/forkjoin/ForkJoinPool;

private scala.concurrent.forkjoin.ForkJoinTask[] queue;
  Signature: [Lscala/concurrent/forkjoin/ForkJoinTask;
  Signature: length = 0x2
   00 6B 

private volatile int sp;
  Signature: I

private volatile int base;
  Signature: I

private boolean active;
  Signature: Z

private volatile int runState;
  Signature: I

private int seed;
  Signature: I

private int stealCount;
  Signature: I

int poolIndex;
  Signature: I

long lastEventCount;
  Signature: J

private boolean locallyFifo;
  Signature: Z

private static final int RUNNING;
  Signature: I
  Constant value: int 0
private static final int SHUTDOWN;
  Signature: I
  Constant value: int 1
private static final int TERMINATING;
  Signature: I
  Constant value: int 2
private static final int TERMINATED;
  Signature: I
  Constant value: int 3
static final sun.misc.Unsafe _unsafe;
  Signature: Lsun/misc/Unsafe;

static final long baseOffset;
  Signature: J

static final long spOffset;
  Signature: J

static final long runStateOffset;
  Signature: J

static final long qBase;
  Signature: J

static final int qShift;
  Signature: I

protected scala.concurrent.forkjoin.ForkJoinWorkerThread(scala.concurrent.forkjoin.ForkJoinPool);
  Signature: (Lscala/concurrent/forkjoin/ForkJoinPool;)V
  Code:
   Stack=2, Locals=2, Args_size=2
	aload_0
	invokespecial	Method java/lang/Thread."<init>":()V
	aload_1
	ifnonnull	l1 // aload_0
	new	class java/lang/NullPointerException
	dup
	invokespecial	Method java/lang/NullPointerException."<init>":()V
	athrow
l1	aload_0
	aload_1
	putfield	Field pool:Lscala/concurrent/forkjoin/ForkJoinPool;
	return
  Labels:
   	l1 = 16 // aload_0
  LocalVariableTable: 
   Start  Length  Slot  Name   Signature
   0      22      0    this       Lscala/concurrent/forkjoin/ForkJoinWorkerThread;
   0      22      1    pool       Lscala/concurrent/forkjoin/ForkJoinPool;


public scala.concurrent.forkjoin.ForkJoinPool getPool();
  Signature: ()Lscala/concurrent/forkjoin/ForkJoinPool;
  Code:
   Stack=1, Locals=1, Args_size=1
	aload_0
	getfield	Field pool:Lscala/concurrent/forkjoin/ForkJoinPool;
	areturn
  Labels:
  LocalVariableTable: 
   Start  Length  Slot  Name   Signature
   0      5      0    this       Lscala/concurrent/forkjoin/ForkJoinWorkerThread;


public int getPoolIndex();
  Signature: ()I
  Code:
   Stack=1, Locals=1, Args_size=1
	aload_0
	getfield	Field poolIndex:I
	ireturn
  Labels:
  LocalVariableTable: 
   Start  Length  Slot  Name   Signature
   0      5      0    this       Lscala/concurrent/forkjoin/ForkJoinWorkerThread;


void setAsyncMode(boolean);
  Signature: (Z)V
  Code:
   Stack=2, Locals=2, Args_size=2
	aload_0
	iload_1
	putfield	Field locallyFifo:Z
	return
  Labels:
  LocalVariableTable: 
   Start  Length  Slot  Name   Signature
   0      6      0    this       Lscala/concurrent/forkjoin/ForkJoinWorkerThread;
   0      6      1    async       Z


final boolean isShutdown();
  Signature: ()Z
  Code:
   Stack=2, Locals=1, Args_size=1
	aload_0
	getfield	Field runState:I
	iconst_1
	if_icmplt	l1 // iconst_0
	iconst_1
	goto	l2 // ireturn
l1	iconst_0
l2	ireturn
  Labels:
   	l1 = 12 // iconst_0
   	l2 = 13 // ireturn
  LocalVariableTable: 
   Start  Length  Slot  Name   Signature
   0      14      0    this       Lscala/concurrent/forkjoin/ForkJoinWorkerThread;


final boolean isTerminating();
  Signature: ()Z
  Code:
   Stack=2, Locals=1, Args_size=1
	aload_0
	getfield	Field runState:I
	iconst_2
	if_icmplt	l1 // iconst_0
	iconst_1
	goto	l2 // ireturn
l1	iconst_0
l2	ireturn
  Labels:
   	l1 = 12 // iconst_0
   	l2 = 13 // ireturn
  LocalVariableTable: 
   Start  Length  Slot  Name   Signature
   0      14      0    this       Lscala/concurrent/forkjoin/ForkJoinWorkerThread;


final boolean isTerminated();
  Signature: ()Z
  Code:
   Stack=2, Locals=1, Args_size=1
	aload_0
	getfield	Field runState:I
	iconst_3
	if_icmpne	l1 // iconst_0
	iconst_1
	goto	l2 // ireturn
l1	iconst_0
l2	ireturn
  Labels:
   	l1 = 12 // iconst_0
   	l2 = 13 // ireturn
  LocalVariableTable: 
   Start  Length  Slot  Name   Signature
   0      14      0    this       Lscala/concurrent/forkjoin/ForkJoinWorkerThread;


final boolean shutdown();
  Signature: ()Z
  Code:
   Stack=2, Locals=1, Args_size=1
	aload_0
	iconst_1
	invokespecial	Method transitionRunStateTo:(I)Z
	ireturn
  Labels:
  LocalVariableTable: 
   Start  Length  Slot  Name   Signature
   0      6      0    this       Lscala/concurrent/forkjoin/ForkJoinWorkerThread;


final boolean shutdownNow();
  Signature: ()Z
  Code:
   Stack=2, Locals=1, Args_size=1
	aload_0
	iconst_2
	invokespecial	Method transitionRunStateTo:(I)Z
	ireturn
  Labels:
  LocalVariableTable: 
   Start  Length  Slot  Name   Signature
   0      6      0    this       Lscala/concurrent/forkjoin/ForkJoinWorkerThread;


private boolean transitionRunStateTo(int);
  Signature: (I)Z
  Code:
   Stack=6, Locals=3, Args_size=2
l3	aload_0
	getfield	Field runState:I
	istore_2
	iload_2
	iload_1
	if_icmplt	l1 // getstatic
	iconst_0
	ireturn
l1	getstatic	Field _unsafe:Lsun/misc/Unsafe;
	aload_0
	getstatic	Field runStateOffset:J
	iload_2
	iload_1
	invokevirtual	Method sun/misc/Unsafe.compareAndSwapInt:(Ljava/lang/Object;JII)Z
	ifeq	l2 // goto
	iconst_1
	ireturn
l2	goto	l3 // aload_0
  Labels:
   	l3 = 0 // aload_0
   	l1 = 12 // getstatic
   	l2 = 29 // goto
  LocalVariableTable: 
   Start  Length  Slot  Name   Signature
   5      24      2    s       I
   0      32      0    this       Lscala/concurrent/forkjoin/ForkJoinWorkerThread;
   0      32      1    state       I


private boolean tryActivate();
  Signature: ()Z
  Code:
   Stack=2, Locals=1, Args_size=1
	aload_0
	getfield	Field active:Z
	ifne	l1 // iconst_1
	aload_0
	getfield	Field pool:Lscala/concurrent/forkjoin/ForkJoinPool;
	invokevirtual	Method scala/concurrent/forkjoin/ForkJoinPool.tryIncrementActiveCount:()Z
	ifne	l2 // aload_0
	iconst_0
	ireturn
l2	aload_0
	iconst_1
	putfield	Field active:Z
l1	iconst_1
	ireturn
  Labels:
   	l2 = 19 // aload_0
   	l1 = 24 // iconst_1
  LocalVariableTable: 
   Start  Length  Slot  Name   Signature
   0      26      0    this       Lscala/concurrent/forkjoin/ForkJoinWorkerThread;


private boolean tryInactivate();
  Signature: ()Z
  Code:
   Stack=2, Locals=1, Args_size=1
	aload_0
	getfield	Field active:Z
	ifeq	l1 // iconst_1
	aload_0
	getfield	Field pool:Lscala/concurrent/forkjoin/ForkJoinPool;
	invokevirtual	Method scala/concurrent/forkjoin/ForkJoinPool.tryDecrementActiveCount:()Z
	ifne	l2 // aload_0
	iconst_0
	ireturn
l2	aload_0
	iconst_0
	putfield	Field active:Z
l1	iconst_1
	ireturn
  Labels:
   	l2 = 19 // aload_0
   	l1 = 24 // iconst_1
  LocalVariableTable: 
   Start  Length  Slot  Name   Signature
   0      26      0    this       Lscala/concurrent/forkjoin/ForkJoinWorkerThread;


private static int xorShift(int);
  Signature: (I)I
  Code:
   Stack=3, Locals=1, Args_size=1
	iload_0
	iload_0
	iconst_1
	ishl
	ixor
	istore_0
	iload_0
	iload_0
	iconst_3
	iushr
	ixor
	istore_0
	iload_0
	iload_0
	bipush	10
	ishl
	ixor
	istore_0
	iload_0
	ireturn
  Labels:
  LocalVariableTable: 
   Start  Length  Slot  Name   Signature
   0      21      0    r       I


public void run();
  Signature: ()V
  Code:
   Stack=2, Locals=4, Args_size=1
	aconst_null
	astore_1
	aload_0
	invokevirtual	Method onStart:()V
	aload_0
	getfield	Field pool:Lscala/concurrent/forkjoin/ForkJoinPool;
	aload_0
	invokevirtual	Method scala/concurrent/forkjoin/ForkJoinPool.sync:(Lscala/concurrent/forkjoin/ForkJoinWorkerThread;)V
	aload_0
	invokespecial	Method mainLoop:()V
	aload_0
	aload_1
	invokevirtual	Method onTermination:(Ljava/lang/Throwable;)V
	goto	l1 // return
	astore_2
	aload_2
	astore_1
	aload_0
	aload_1
	invokevirtual	Method onTermination:(Ljava/lang/Throwable;)V
	goto	l1 // return
	astore_3
	aload_0
	aload_1
	invokevirtual	Method onTermination:(Ljava/lang/Throwable;)V
	aload_3
	athrow
l1	return
  Labels:
   	l1 = 45 // return
  Exception table:
   from   to  target type
     2    18    26   Class java/lang/Throwable

     2    18    37   any
    26    29    37   any
    37    38    37   any
  LocalVariableTable: 
   Start  Length  Slot  Name   Signature
   27      2      2    ex       Ljava/lang/Throwable;
   0      46      0    this       Lscala/concurrent/forkjoin/ForkJoinWorkerThread;
   2      44      1    exception       Ljava/lang/Throwable;


private void mainLoop();
  Signature: ()V
  Code:
   Stack=2, Locals=2, Args_size=1
l5	aload_0
	invokevirtual	Method isShutdown:()Z
	ifne	l1 // return
	aload_0
	invokevirtual	Method pollTask:()Lscala/concurrent/forkjoin/ForkJoinTask;
	astore_1
	aload_1
	ifnonnull	l2 // aload_1
	aload_0
	invokespecial	Method pollSubmission:()Lscala/concurrent/forkjoin/ForkJoinTask;
	dup
	astore_1
	ifnull	l3 // aload_0
l2	aload_1
	invokevirtual	Method scala/concurrent/forkjoin/ForkJoinTask.quietlyExec:()V
	goto	l4 // goto
l3	aload_0
	invokespecial	Method tryInactivate:()Z
	ifeq	l4 // goto
	aload_0
	getfield	Field pool:Lscala/concurrent/forkjoin/ForkJoinPool;
	aload_0
	invokevirtual	Method scala/concurrent/forkjoin/ForkJoinPool.sync:(Lscala/concurrent/forkjoin/ForkJoinWorkerThread;)V
l4	goto	l5 // aload_0
l1	return
  Labels:
   	l5 = 0 // aload_0
   	l2 = 25 // aload_1
   	l3 = 32 // aload_0
   	l4 = 47 // goto
   	l1 = 50 // return
  LocalVariableTable: 
   Start  Length  Slot  Name   Signature
   12      35      1    t       Lscala/concurrent/forkjoin/ForkJoinTask;
   0      51      0    this       Lscala/concurrent/forkjoin/ForkJoinWorkerThread;

  LocalVariableTypeTable: length = 0xC
   00 01 00 0C 00 23 00 FFFFFFA9 00 FFFFFFAC 00 01 

protected void onStart();
  Signature: ()V
  Code:
   Stack=4, Locals=2, Args_size=1
	aload_0
	sipush	8192
	anewarray	class scala/concurrent/forkjoin/ForkJoinTask
	putfield	Field queue:[Lscala/concurrent/forkjoin/ForkJoinTask;
	aload_0
	getfield	Field poolIndex:I
	iconst_1
	iadd
	istore_1
	aload_0
	iload_1
	iload_1
	bipush	8
	ishl
	iadd
	iload_1
	bipush	16
	ishl
	iadd
	iload_1
	bipush	24
	ishl
	iadd
	putfield	Field seed:I
	return
  Labels:
  LocalVariableTable: 
   Start  Length  Slot  Name   Signature
   0      38      0    this       Lscala/concurrent/forkjoin/ForkJoinWorkerThread;
   17      21      1    p       I


protected void onTermination(java.lang.Throwable);
  Signature: (Ljava/lang/Throwable;)V
  Code:
   Stack=2, Locals=4, Args_size=2
l3	aload_1
	ifnonnull	l1 // aload_0
	aload_0
	getfield	Field pool:Lscala/concurrent/forkjoin/ForkJoinPool;
	invokevirtual	Method scala/concurrent/forkjoin/ForkJoinPool.isTerminating:()Z
	ifne	l1 // aload_0
	aload_0
	getfield	Field base:I
	aload_0
	getfield	Field sp:I
	if_icmpeq	l1 // aload_0
	aload_0
	invokevirtual	Method popTask:()Lscala/concurrent/forkjoin/ForkJoinTask;
	astore_2
	aload_2
	ifnull	l2 // goto
	aload_2
	invokevirtual	Method scala/concurrent/forkjoin/ForkJoinTask.quietlyExec:()V
l2	goto	l3 // aload_1
	astore_2
	aload_2
	astore_1
	goto	l3 // aload_1
l1	aload_0
	invokespecial	Method tryInactivate:()Z
	ifeq	l1 // aload_0
	aload_0
	invokevirtual	Method cancelTasks:()V
	aload_0
	iconst_3
	putfield	Field runState:I
	aload_0
	getfield	Field pool:Lscala/concurrent/forkjoin/ForkJoinPool;
	aload_0
	invokevirtual	Method scala/concurrent/forkjoin/ForkJoinPool.workerTerminated:(Lscala/concurrent/forkjoin/ForkJoinWorkerThread;)V
	aload_1
	ifnull	l4 // return
	aload_1
	invokestatic	Method scala/concurrent/forkjoin/ForkJoinTask.rethrowException:(Ljava/lang/Throwable;)V
	goto	l4 // return
	astore_2
	aload_1
	ifnonnull	l5 // aload_1
	aload_2
	astore_1
l5	aload_1
	ifnull	l4 // return
	aload_1
	invokestatic	Method scala/concurrent/forkjoin/ForkJoinTask.rethrowException:(Ljava/lang/Throwable;)V
	goto	l4 // return
	astore_3
	aload_1
	ifnull	l6 // aload_3
	aload_1
	invokestatic	Method scala/concurrent/forkjoin/ForkJoinTask.rethrowException:(Ljava/lang/Throwable;)V
l6	aload_3
	athrow
l4	return
  Labels:
   	l3 = 0 // aload_1
   	l2 = 38 // goto
   	l1 = 47 // aload_0
   	l5 = 89 // aload_1
   	l6 = 109 // aload_3
   	l4 = 111 // return
  Exception table:
   from   to  target type
    25    38    41   Class java/lang/Throwable

    47    71    82   Class java/lang/Throwable

    47    71   100   any
    82    89   100   any
   100   101   100   any
  LocalVariableTable: 
   Start  Length  Slot  Name   Signature
   30      8      2    t       Lscala/concurrent/forkjoin/ForkJoinTask;
   42      2      2    ex       Ljava/lang/Throwable;
   83      6      2    ex       Ljava/lang/Throwable;
   0      112      0    this       Lscala/concurrent/forkjoin/ForkJoinWorkerThread;
   0      112      1    exception       Ljava/lang/Throwable;

  LocalVariableTypeTable: length = 0xC
   00 01 00 1E 00 08 00 FFFFFFA9 00 FFFFFFAC 00 02 

private static void setSlot(scala.concurrent.forkjoin.ForkJoinTask[], int, scala.concurrent.forkjoin.ForkJoinTask);
  Signature: ([Lscala/concurrent/forkjoin/ForkJoinTask;ILscala/concurrent/forkjoin/ForkJoinTask;)V
  Code:
   Stack=6, Locals=3, Args_size=3
	getstatic	Field _unsafe:Lsun/misc/Unsafe;
	aload_0
	iload_1
	getstatic	Field qShift:I
	ishl
	i2l
	getstatic	Field qBase:J
	ladd
	aload_2
	invokevirtual	Method sun/misc/Unsafe.putOrderedObject:(Ljava/lang/Object;JLjava/lang/Object;)V
	return
  Labels:
  LocalVariableTable: 
   Start  Length  Slot  Name   Signature
   0      19      0    q       [Lscala/concurrent/forkjoin/ForkJoinTask;
   0      19      1    i       I
   0      19      2    t       Lscala/concurrent/forkjoin/ForkJoinTask;

  LocalVariableTypeTable: length = 0x16
   00 02 00 00 00 13 00 FFFFFFB3 00 6B 00 00 00 00 00 13
   00 FFFFFFA9 00 FFFFFFAC 00 02 
  Signature: length = 0x2
   00 FFFFFFB5 

private static boolean casSlotNull(scala.concurrent.forkjoin.ForkJoinTask[], int, scala.concurrent.forkjoin.ForkJoinTask);
  Signature: ([Lscala/concurrent/forkjoin/ForkJoinTask;ILscala/concurrent/forkjoin/ForkJoinTask;)Z
  Code:
   Stack=6, Locals=3, Args_size=3
	getstatic	Field _unsafe:Lsun/misc/Unsafe;
	aload_0
	iload_1
	getstatic	Field qShift:I
	ishl
	i2l
	getstatic	Field qBase:J
	ladd
	aload_2
	aconst_null
	invokevirtual	Method sun/misc/Unsafe.compareAndSwapObject:(Ljava/lang/Object;JLjava/lang/Object;Ljava/lang/Object;)Z
	ireturn
  Labels:
  LocalVariableTable: 
   Start  Length  Slot  Name   Signature
   0      20      0    q       [Lscala/concurrent/forkjoin/ForkJoinTask;
   0      20      1    i       I
   0      20      2    t       Lscala/concurrent/forkjoin/ForkJoinTask;

  LocalVariableTypeTable: length = 0x16
   00 02 00 00 00 14 00 FFFFFFB3 00 6B 00 00 00 00 00 14
   00 FFFFFFA9 00 FFFFFFAC 00 02 
  Signature: length = 0x2
   00 FFFFFFB8 

private void storeSp(int);
  Signature: (I)V
  Code:
   Stack=5, Locals=2, Args_size=2
	getstatic	Field _unsafe:Lsun/misc/Unsafe;
	aload_0
	getstatic	Field spOffset:J
	iload_1
	invokevirtual	Method sun/misc/Unsafe.putOrderedInt:(Ljava/lang/Object;JI)V
	return
  Labels:
  LocalVariableTable: 
   Start  Length  Slot  Name   Signature
   0      12      0    this       Lscala/concurrent/forkjoin/ForkJoinWorkerThread;
   0      12      1    s       I


final void pushTask(scala.concurrent.forkjoin.ForkJoinTask);
  Signature: (Lscala/concurrent/forkjoin/ForkJoinTask;)V
  Code:
   Stack=3, Locals=5, Args_size=2
	aload_0
	getfield	Field queue:[Lscala/concurrent/forkjoin/ForkJoinTask;
	astore_2
	aload_2
	arraylength
	iconst_1
	isub
	istore_3
	aload_0
	getfield	Field sp:I
	istore	4
	aload_2
	iload	4
	iload_3
	iand
	aload_1
	invokestatic	Method setSlot:([Lscala/concurrent/forkjoin/ForkJoinTask;ILscala/concurrent/forkjoin/ForkJoinTask;)V
	aload_0
	iinc	4, 1
	iload	4
	invokespecial	Method storeSp:(I)V
	iload	4
	aload_0
	getfield	Field base:I
	isub
	dup
	istore	4
	iconst_1
	if_icmpne	l1 // iload
	aload_0
	getfield	Field pool:Lscala/concurrent/forkjoin/ForkJoinPool;
	invokevirtual	Method scala/concurrent/forkjoin/ForkJoinPool.signalWork:()V
	goto	l2 // return
l1	iload	4
	iload_3
	if_icmplt	l2 // return
	aload_0
	invokespecial	Method growQueue:()V
l2	return
  Labels:
   	l1 = 58 // iload
   	l2 = 68 // return
  LocalVariableTable: 
   Start  Length  Slot  Name   Signature
   0      69      0    this       Lscala/concurrent/forkjoin/ForkJoinWorkerThread;
   0      69      1    t       Lscala/concurrent/forkjoin/ForkJoinTask;
   5      64      2    q       [Lscala/concurrent/forkjoin/ForkJoinTask;
   10      59      3    mask       I
   16      53      4    s       I

  LocalVariableTypeTable: length = 0x16
   00 02 00 00 00 45 00 FFFFFFA9 00 FFFFFFAC 00 01 00 05 00 40
   00 FFFFFFB3 00 6B 00 02 
  Signature: length = 0x2
   00 FFFFFFBE 

final scala.concurrent.forkjoin.ForkJoinTask deqTask();
  Signature: ()Lscala/concurrent/forkjoin/ForkJoinTask;
  Code:
   Stack=3, Locals=5, Args_size=1
	aload_0
	getfield	Field sp:I
	aload_0
	getfield	Field base:I
	dup
	istore	4
	if_icmpeq	l1 // aconst_null
	aload_0
	getfield	Field queue:[Lscala/concurrent/forkjoin/ForkJoinTask;
	dup
	astore_2
	ifnull	l1 // aconst_null
	aload_2
	aload_2
	arraylength
	iconst_1
	isub
	iload	4
	iand
	dup
	istore_3
	aaload
	dup
	astore_1
	ifnull	l1 // aconst_null
	aload_2
	iload_3
	aload_1
	invokestatic	Method casSlotNull:([Lscala/concurrent/forkjoin/ForkJoinTask;ILscala/concurrent/forkjoin/ForkJoinTask;)Z
	ifeq	l1 // aconst_null
	aload_0
	iload	4
	iconst_1
	iadd
	putfield	Field base:I
	aload_1
	areturn
l1	aconst_null
	areturn
  Labels:
   	l1 = 58 // aconst_null
  LocalVariableTable: 
   Start  Length  Slot  Name   Signature
   36      22      1    t       Lscala/concurrent/forkjoin/ForkJoinTask;
   20      38      2    q       [Lscala/concurrent/forkjoin/ForkJoinTask;
   33      25      3    i       I
   0      60      0    this       Lscala/concurrent/forkjoin/ForkJoinWorkerThread;
   11      49      4    b       I

  LocalVariableTypeTable: length = 0x16
   00 02 00 24 00 16 00 FFFFFFA9 00 FFFFFFAC 00 01 00 14 00 26
   00 FFFFFFB3 00 6B 00 02 
  Signature: length = 0x2
   00 FFFFFFC2 

final scala.concurrent.forkjoin.ForkJoinTask popTask();
  Signature: ()Lscala/concurrent/forkjoin/ForkJoinTask;
  Code:
   Stack=3, Locals=6, Args_size=1
	aload_0
	getfield	Field sp:I
	istore_1
l2	iload_1
	aload_0
	getfield	Field base:I
	if_icmpeq	l1 // aconst_null
	aload_0
	invokespecial	Method tryActivate:()Z
	ifeq	l2 // iload_1
	aload_0
	getfield	Field queue:[Lscala/concurrent/forkjoin/ForkJoinTask;
	astore_2
	aload_2
	arraylength
	iconst_1
	isub
	istore_3
	iload_1
	iconst_1
	isub
	iload_3
	iand
	istore	4
	aload_2
	iload	4
	aaload
	astore	5
	aload	5
	ifnull	l1 // aconst_null
	aload_2
	iload	4
	aload	5
	invokestatic	Method casSlotNull:([Lscala/concurrent/forkjoin/ForkJoinTask;ILscala/concurrent/forkjoin/ForkJoinTask;)Z
	ifne	l3 // aload_0
	goto	l1 // aconst_null
l3	aload_0
	iload_1
	iconst_1
	isub
	invokespecial	Method storeSp:(I)V
	aload	5
	areturn
l1	aconst_null
	areturn
  Labels:
   	l2 = 5 // iload_1
   	l3 = 62 // aload_0
   	l1 = 72 // aconst_null
  LocalVariableTable: 
   Start  Length  Slot  Name   Signature
   25      47      2    q       [Lscala/concurrent/forkjoin/ForkJoinTask;
   30      42      3    mask       I
   37      35      4    i       I
   43      29      5    t       Lscala/concurrent/forkjoin/ForkJoinTask;
   0      74      0    this       Lscala/concurrent/forkjoin/ForkJoinWorkerThread;
   5      69      1    s       I

  LocalVariableTypeTable: length = 0x16
   00 02 00 19 00 2F 00 FFFFFFB3 00 6B 00 02 00 2B 00 1D
   00 FFFFFFA9 00 FFFFFFAC 00 05 
  Signature: length = 0x2
   00 FFFFFFC2 

final boolean unpushTask(scala.concurrent.forkjoin.ForkJoinTask);
  Signature: (Lscala/concurrent/forkjoin/ForkJoinTask;)Z
  Code:
   Stack=3, Locals=5, Args_size=2
	aload_0
	getfield	Field queue:[Lscala/concurrent/forkjoin/ForkJoinTask;
	astore_2
	aload_2
	arraylength
	iconst_1
	isub
	istore_3
	aload_0
	getfield	Field sp:I
	iconst_1
	isub
	istore	4
	aload_2
	iload	4
	iload_3
	iand
	aload_1
	invokestatic	Method casSlotNull:([Lscala/concurrent/forkjoin/ForkJoinTask;ILscala/concurrent/forkjoin/ForkJoinTask;)Z
	ifeq	l1 // iconst_0
	aload_0
	iload	4
	invokespecial	Method storeSp:(I)V
	iconst_1
	ireturn
l1	iconst_0
	ireturn
  Labels:
   	l1 = 38 // iconst_0
  LocalVariableTable: 
   Start  Length  Slot  Name   Signature
   0      40      0    this       Lscala/concurrent/forkjoin/ForkJoinWorkerThread;
   0      40      1    t       Lscala/concurrent/forkjoin/ForkJoinTask;
   5      35      2    q       [Lscala/concurrent/forkjoin/ForkJoinTask;
   10      30      3    mask       I
   18      22      4    s       I

  LocalVariableTypeTable: length = 0x16
   00 02 00 00 00 28 00 FFFFFFA9 00 FFFFFFAC 00 01 00 05 00 23
   00 FFFFFFB3 00 6B 00 02 
  Signature: length = 0x2
   00 FFFFFFC6 

final scala.concurrent.forkjoin.ForkJoinTask peekTask();
  Signature: ()Lscala/concurrent/forkjoin/ForkJoinTask;
  Code:
   Stack=3, Locals=4, Args_size=1
	aload_0
	getfield	Field queue:[Lscala/concurrent/forkjoin/ForkJoinTask;
	astore_1
	aload_1
	ifnonnull	l1 // aload_1
	aconst_null
	areturn
l1	aload_1
	arraylength
	iconst_1
	isub
	istore_2
	aload_0
	getfield	Field locallyFifo:Z
	ifeq	l2 // aload_0
	aload_0
	getfield	Field base:I
	goto	l3 // istore_3
l2	aload_0
	getfield	Field sp:I
	iconst_1
	isub
l3	istore_3
	aload_1
	iload_3
	iload_2
	iand
	aaload
	areturn
  Labels:
   	l1 = 11 // aload_1
   	l2 = 30 // aload_0
   	l3 = 36 // istore_3
  LocalVariableTable: 
   Start  Length  Slot  Name   Signature
   0      43      0    this       Lscala/concurrent/forkjoin/ForkJoinWorkerThread;
   5      38      1    q       [Lscala/concurrent/forkjoin/ForkJoinTask;
   16      27      2    mask       I
   37      6      3    i       I

  LocalVariableTypeTable: length = 0xC
   00 01 00 05 00 26 00 FFFFFFB3 00 6B 00 01 
  Signature: length = 0x2
   00 FFFFFFC2 

private void growQueue();
  Signature: ()V
  Code:
   Stack=3, Locals=11, Args_size=1
	aload_0
	getfield	Field queue:[Lscala/concurrent/forkjoin/ForkJoinTask;
	astore_1
	aload_1
	arraylength
	istore_2
	iload_2
	iconst_1
	ishl
	istore_3
	iload_3
	ldc	int 268435456
	if_icmple	l1 // aload_0
	new	class java/util/concurrent/RejectedExecutionException
	dup
	ldc	String Queue capacity exceeded
	invokespecial	Method java/util/concurrent/RejectedExecutionException."<init>":(Ljava/lang/String;)V
	athrow
l1	aload_0
	iload_3
	anewarray	class scala/concurrent/forkjoin/ForkJoinTask
	dup_x1
	putfield	Field queue:[Lscala/concurrent/forkjoin/ForkJoinTask;
	astore	4
	aload_0
	getfield	Field base:I
	istore	5
	iload	5
	iload_2
	iadd
	istore	6
	iload_2
	iconst_1
	isub
	istore	7
	iload_3
	iconst_1
	isub
	istore	8
l3	iload	5
	iload	7
	iand
	istore	9
	aload_1
	iload	9
	aaload
	astore	10
	aload	10
	ifnull	l2 // aload
	aload_1
	iload	9
	aload	10
	invokestatic	Method casSlotNull:([Lscala/concurrent/forkjoin/ForkJoinTask;ILscala/concurrent/forkjoin/ForkJoinTask;)Z
	ifne	l2 // aload
	aconst_null
	astore	10
l2	aload	4
	iload	5
	iload	8
	iand
	aload	10
	invokestatic	Method setSlot:([Lscala/concurrent/forkjoin/ForkJoinTask;ILscala/concurrent/forkjoin/ForkJoinTask;)V
	iinc	5, 1
	iload	5
	iload	6
	if_icmpne	l3 // iload
	aload_0
	getfield	Field pool:Lscala/concurrent/forkjoin/ForkJoinPool;
	invokevirtual	Method scala/concurrent/forkjoin/ForkJoinPool.signalWork:()V
	return
  Labels:
   	l1 = 28 // aload_0
   	l3 = 61 // iload
   	l2 = 93 // aload
  LocalVariableTable: 
   Start  Length  Slot  Name   Signature
   68      37      9    oldIndex       I
   74      31      10    t       Lscala/concurrent/forkjoin/ForkJoinTask;
   0      123      0    this       Lscala/concurrent/forkjoin/ForkJoinWorkerThread;
   5      118      1    oldQ       [Lscala/concurrent/forkjoin/ForkJoinTask;
   8      115      2    oldSize       I
   12      111      3    newSize       I
   39      84      4    newQ       [Lscala/concurrent/forkjoin/ForkJoinTask;
   45      78      5    b       I
   51      72      6    bf       I
   56      67      7    oldMask       I
   61      62      8    newMask       I

  LocalVariableTypeTable: length = 0x20
   00 03 00 4A 00 1F 00 FFFFFFA9 00 FFFFFFAC 00 0A 00 05 00 76
   00 FFFFFFCA 00 6B 00 01 00 27 00 54 00 FFFFFFCD 00 6B 00 04
   

private scala.concurrent.forkjoin.ForkJoinTask scan();
  Signature: ()Lscala/concurrent/forkjoin/ForkJoinTask;
  Code:
   Stack=3, Locals=8, Args_size=1
	aconst_null
	astore_1
	aload_0
	getfield	Field seed:I
	istore_2
l9	aload_0
	getfield	Field pool:Lscala/concurrent/forkjoin/ForkJoinPool;
	getfield	Field scala/concurrent/forkjoin/ForkJoinPool.workers:[Lscala/concurrent/forkjoin/ForkJoinWorkerThread;
	dup
	astore_3
	ifnull	l1 // aload_0
	aload_3
	arraylength
	iconst_1
	isub
	dup
	istore	4
	ifle	l1 // aload_0
	iload_2
	istore	5
	iload	4
	iconst_m1
	ixor
	istore	6
l8	iload_2
	invokestatic	Method xorShift:(I)I
	istore_2
	aload_3
	iload	4
	iload	5
	iand
	aaload
	astore	7
	aload	7
	ifnull	l2 // iload
	aload	7
	getfield	Field sp:I
	aload	7
	getfield	Field base:I
	if_icmpne	l3 // aload_0
l2	iload	6
	iload	4
	if_icmpgt	l1 // aload_0
	iload	6
	iinc	6, 1
	ifge	l4 // iload
	iload_2
	goto	l5 // istore
l4	iload	5
	iconst_1
	iadd
l5	istore	5
	goto	l6 // goto
l3	aload_0
	invokespecial	Method tryActivate:()Z
	ifeq	l1 // aload_0
	aload	7
	invokevirtual	Method deqTask:()Lscala/concurrent/forkjoin/ForkJoinTask;
	dup
	astore_1
	ifnonnull	l7 // aload_0
	goto	l1 // aload_0
l6	goto	l8 // iload_2
l1	aload_0
	getfield	Field pool:Lscala/concurrent/forkjoin/ForkJoinPool;
	aload_0
	invokevirtual	Method scala/concurrent/forkjoin/ForkJoinPool.hasNewSyncEvent:(Lscala/concurrent/forkjoin/ForkJoinWorkerThread;)Z
	ifne	l9 // aload_0
l7	aload_0
	iload_2
	putfield	Field seed:I
	aload_1
	areturn
  Labels:
   	l9 = 7 // aload_0
   	l8 = 38 // iload_2
   	l2 = 70 // iload
   	l4 = 89 // iload
   	l5 = 93 // istore
   	l3 = 98 // aload_0
   	l6 = 118 // goto
   	l1 = 121 // aload_0
   	l7 = 132 // aload_0
  LocalVariableTable: 
   Start  Length  Slot  Name   Signature
   52      66      7    v       Lscala/concurrent/forkjoin/ForkJoinWorkerThread;
   32      89      5    idx       I
   38      83      6    probes       I
   26      95      4    mask       I
   0      139      0    this       Lscala/concurrent/forkjoin/ForkJoinWorkerThread;
   2      137      1    t       Lscala/concurrent/forkjoin/ForkJoinTask;
   7      132      2    r       I
   16      123      3    ws       [Lscala/concurrent/forkjoin/ForkJoinWorkerThread;

  LocalVariableTypeTable: length = 0xC
   00 01 00 02 00 FFFFFF89 00 FFFFFFA9 00 FFFFFFAC 00 01 
  Signature: length = 0x2
   00 FFFFFFC2 

final scala.concurrent.forkjoin.ForkJoinTask pollTask();
  Signature: ()Lscala/concurrent/forkjoin/ForkJoinTask;
  Code:
   Stack=3, Locals=2, Args_size=1
	aload_0
	getfield	Field locallyFifo:Z
	ifeq	l1 // aload_0
	aload_0
	invokevirtual	Method deqTask:()Lscala/concurrent/forkjoin/ForkJoinTask;
	goto	l2 // astore_1
l1	aload_0
	invokevirtual	Method popTask:()Lscala/concurrent/forkjoin/ForkJoinTask;
l2	astore_1
	aload_1
	ifnonnull	l3 // aload_1
	aload_0
	invokespecial	Method scan:()Lscala/concurrent/forkjoin/ForkJoinTask;
	dup
	astore_1
	ifnull	l3 // aload_1
	aload_0
	dup
	getfield	Field stealCount:I
	iconst_1
	iadd
	putfield	Field stealCount:I
l3	aload_1
	areturn
  Labels:
   	l1 = 14 // aload_0
   	l2 = 18 // astore_1
   	l3 = 42 // aload_1
  LocalVariableTable: 
   Start  Length  Slot  Name   Signature
   0      44      0    this       Lscala/concurrent/forkjoin/ForkJoinWorkerThread;
   19      25      1    t       Lscala/concurrent/forkjoin/ForkJoinTask;

  LocalVariableTypeTable: length = 0xC
   00 01 00 13 00 19 00 FFFFFFA9 00 FFFFFFAC 00 01 
  Signature: length = 0x2
   00 FFFFFFC2 

final scala.concurrent.forkjoin.ForkJoinTask pollLocalTask();
  Signature: ()Lscala/concurrent/forkjoin/ForkJoinTask;
  Code:
   Stack=1, Locals=1, Args_size=1
	aload_0
	getfield	Field locallyFifo:Z
	ifeq	l1 // aload_0
	aload_0
	invokevirtual	Method deqTask:()Lscala/concurrent/forkjoin/ForkJoinTask;
	goto	l2 // areturn
l1	aload_0
	invokevirtual	Method popTask:()Lscala/concurrent/forkjoin/ForkJoinTask;
l2	areturn
  Labels:
   	l1 = 14 // aload_0
   	l2 = 18 // areturn
  LocalVariableTable: 
   Start  Length  Slot  Name   Signature
   0      19      0    this       Lscala/concurrent/forkjoin/ForkJoinWorkerThread;

  Signature: length = 0x2
   00 FFFFFFC2 

private scala.concurrent.forkjoin.ForkJoinTask pollSubmission();
  Signature: ()Lscala/concurrent/forkjoin/ForkJoinTask;
  Code:
   Stack=2, Locals=3, Args_size=1
	aload_0
	getfield	Field pool:Lscala/concurrent/forkjoin/ForkJoinPool;
	astore_1
l3	aload_1
	invokevirtual	Method scala/concurrent/forkjoin/ForkJoinPool.hasQueuedSubmissions:()Z
	ifeq	l1 // aconst_null
	aload_0
	invokespecial	Method tryActivate:()Z
	ifeq	l2 // goto
	aload_1
	invokevirtual	Method scala/concurrent/forkjoin/ForkJoinPool.pollSubmission:()Lscala/concurrent/forkjoin/ForkJoinTask;
	dup
	astore_2
	ifnull	l2 // goto
	aload_2
	areturn
l2	goto	l3 // aload_1
l1	aconst_null
	areturn
  Labels:
   	l3 = 5 // aload_1
   	l2 = 30 // goto
   	l1 = 33 // aconst_null
  LocalVariableTable: 
   Start  Length  Slot  Name   Signature
   25      5      2    t       Lscala/concurrent/forkjoin/ForkJoinTask;
   0      35      0    this       Lscala/concurrent/forkjoin/ForkJoinWorkerThread;
   5      30      1    p       Lscala/concurrent/forkjoin/ForkJoinPool;

  LocalVariableTypeTable: length = 0xC
   00 01 00 19 00 05 00 FFFFFFA9 00 FFFFFFAC 00 02 
  Signature: length = 0x2
   00 FFFFFFC2 

final void cancelTasks();
  Signature: ()V
  Code:
   Stack=2, Locals=2, Args_size=1
l2	aload_0
	getfield	Field base:I
	aload_0
	getfield	Field sp:I
	if_icmpeq	l1 // return
	aload_0
	invokevirtual	Method deqTask:()Lscala/concurrent/forkjoin/ForkJoinTask;
	dup
	astore_1
	ifnull	l1 // return
	aload_1
	invokevirtual	Method scala/concurrent/forkjoin/ForkJoinTask.cancelIgnoringExceptions:()V
	goto	l2 // aload_0
l1	return
  Labels:
   	l2 = 0 // aload_0
   	l1 = 27 // return
  LocalVariableTable: 
   Start  Length  Slot  Name   Signature
   17      10      1    t       Lscala/concurrent/forkjoin/ForkJoinTask;
   0      28      0    this       Lscala/concurrent/forkjoin/ForkJoinWorkerThread;

  LocalVariableTypeTable: length = 0xC
   00 01 00 11 00 0A 00 FFFFFFA9 00 FFFFFFAC 00 01 

final int drainTasksTo(java.util.Collection);
  Signature: (Ljava/util/Collection;)I
  Code:
   Stack=2, Locals=4, Args_size=2
	iconst_0
	istore_2
l2	aload_0
	getfield	Field base:I
	aload_0
	getfield	Field sp:I
	if_icmpeq	l1 // iload_2
	aload_0
	invokevirtual	Method deqTask:()Lscala/concurrent/forkjoin/ForkJoinTask;
	dup
	astore_3
	ifnull	l1 // iload_2
	aload_1
	aload_3
	invokeinterface	InterfaceMethod java/util/Collection.add:(Ljava/lang/Object;)Z
	pop
	iinc	2, 1
	goto	l2 // aload_0
l1	iload_2
	ireturn
  Labels:
   	l2 = 2 // aload_0
   	l1 = 36 // iload_2
  LocalVariableTable: 
   Start  Length  Slot  Name   Signature
   19      17      3    t       Lscala/concurrent/forkjoin/ForkJoinTask;
   0      38      0    this       Lscala/concurrent/forkjoin/ForkJoinWorkerThread;
   0      38      1    c       Ljava/util/Collection;
   2      36      2    n       I

  LocalVariableTypeTable: length = 0x16
   00 02 00 13 00 11 00 FFFFFFA9 00 FFFFFFAC 00 03 00 00 00 26
   00 FFFFFFDD 00 FFFFFFE0 00 01 
  Signature: length = 0x2
   00 FFFFFFE1 

final int getAndClearStealCount();
  Signature: ()I
  Code:
   Stack=2, Locals=2, Args_size=1
	aload_0
	getfield	Field stealCount:I
	istore_1
	aload_0
	iconst_0
	putfield	Field stealCount:I
	iload_1
	ireturn
  Labels:
  LocalVariableTable: 
   Start  Length  Slot  Name   Signature
   0      12      0    this       Lscala/concurrent/forkjoin/ForkJoinWorkerThread;
   5      7      1    sc       I


static boolean hasQueuedTasks(scala.concurrent.forkjoin.ForkJoinWorkerThread[]);
  Signature: ([Lscala/concurrent/forkjoin/ForkJoinWorkerThread;)Z
  Code:
   Stack=2, Locals=5, Args_size=1
	aload_0
	ifnull	l1 // iconst_0
	aload_0
	arraylength
	istore_1
	iconst_0
	istore_2
l5	iload_2
	iconst_2
	if_icmpge	l1 // iconst_0
	iconst_0
	istore_3
l4	iload_3
	iload_1
	if_icmpge	l2 // iinc
	aload_0
	iload_3
	aaload
	astore	4
	aload	4
	ifnull	l3 // iinc
	aload	4
	getfield	Field sp:I
	aload	4
	getfield	Field base:I
	if_icmpeq	l3 // iinc
	iconst_1
	ireturn
l3	iinc	3, 1
	goto	l4 // iload_3
l2	iinc	2, 1
	goto	l5 // iload_2
l1	iconst_0
	ireturn
  Labels:
   	l5 = 9 // iload_2
   	l4 = 16 // iload_3
   	l3 = 46 // iinc
   	l2 = 52 // iinc
   	l1 = 58 // iconst_0
  LocalVariableTable: 
   Start  Length  Slot  Name   Signature
   26      20      4    w       Lscala/concurrent/forkjoin/ForkJoinWorkerThread;
   16      36      3    i       I
   9      49      2    j       I
   7      51      1    len       I
   0      60      0    ws       [Lscala/concurrent/forkjoin/ForkJoinWorkerThread;


final int getQueueSize();
  Signature: ()I
  Code:
   Stack=2, Locals=2, Args_size=1
	aload_0
	getfield	Field sp:I
	aload_0
	getfield	Field base:I
	isub
	istore_1
	iload_1
	ifge	l1 // iload_1
	iconst_0
	goto	l2 // ireturn
l1	iload_1
l2	ireturn
  Labels:
   	l1 = 18 // iload_1
   	l2 = 19 // ireturn
  LocalVariableTable: 
   Start  Length  Slot  Name   Signature
   0      20      0    this       Lscala/concurrent/forkjoin/ForkJoinWorkerThread;
   10      10      1    n       I


final int getEstimatedSurplusTaskCount();
  Signature: ()I
  Code:
   Stack=3, Locals=1, Args_size=1
	aload_0
	getfield	Field sp:I
	aload_0
	getfield	Field base:I
	isub
	aload_0
	getfield	Field pool:Lscala/concurrent/forkjoin/ForkJoinPool;
	invokevirtual	Method scala/concurrent/forkjoin/ForkJoinPool.getIdleThreadCount:()I
	iconst_1
	iushr
	isub
	ireturn
  Labels:
  LocalVariableTable: 
   Start  Length  Slot  Name   Signature
   0      20      0    this       Lscala/concurrent/forkjoin/ForkJoinWorkerThread;


final scala.concurrent.forkjoin.ForkJoinTask scanWhileJoining(scala.concurrent.forkjoin.ForkJoinTask);
  Signature: (Lscala/concurrent/forkjoin/ForkJoinTask;)Lscala/concurrent/forkjoin/ForkJoinTask;
  Code:
   Stack=2, Locals=3, Args_size=2
	aload_0
	invokevirtual	Method pollTask:()Lscala/concurrent/forkjoin/ForkJoinTask;
	astore_2
	aload_2
	ifnull	l1 // aload_2
	aload_1
	getfield	Field scala/concurrent/forkjoin/ForkJoinTask.status:I
	ifge	l1 // aload_2
	aload_0
	getfield	Field sp:I
	aload_0
	getfield	Field base:I
	if_icmpne	l1 // aload_2
	aload_0
	aload_2
	invokevirtual	Method pushTask:(Lscala/concurrent/forkjoin/ForkJoinTask;)V
	aconst_null
	astore_2
l1	aload_2
	areturn
  Labels:
   	l1 = 34 // aload_2
  LocalVariableTable: 
   Start  Length  Slot  Name   Signature
   0      36      0    this       Lscala/concurrent/forkjoin/ForkJoinWorkerThread;
   0      36      1    joinMe       Lscala/concurrent/forkjoin/ForkJoinTask;
   5      31      2    t       Lscala/concurrent/forkjoin/ForkJoinTask;

  LocalVariableTypeTable: length = 0x16
   00 02 00 00 00 24 00 FFFFFFED 00 FFFFFFAC 00 01 00 05 00 1F
   00 FFFFFFA9 00 FFFFFFAC 00 02 
  Signature: length = 0x2
   00 FFFFFFEE 

final void helpQuiescePool();
  Signature: ()V
  Code:
   Stack=1, Locals=2, Args_size=1
l4	aload_0
	invokevirtual	Method pollTask:()Lscala/concurrent/forkjoin/ForkJoinTask;
	astore_1
	aload_1
	ifnull	l1 // aload_0
	aload_1
	invokevirtual	Method scala/concurrent/forkjoin/ForkJoinTask.quietlyExec:()V
	goto	l2 // goto
l1	aload_0
	invokespecial	Method tryInactivate:()Z
	ifeq	l2 // goto
	aload_0
	getfield	Field pool:Lscala/concurrent/forkjoin/ForkJoinPool;
	invokevirtual	Method scala/concurrent/forkjoin/ForkJoinPool.isQuiescent:()Z
	ifeq	l2 // goto
	goto	l3 // aload_0
l2	goto	l4 // aload_0
l3	aload_0
	invokespecial	Method tryActivate:()Z
	ifeq	l3 // aload_0
	return
  Labels:
   	l4 = 0 // aload_0
   	l1 = 16 // aload_0
   	l2 = 36 // goto
   	l3 = 39 // aload_0
  LocalVariableTable: 
   Start  Length  Slot  Name   Signature
   5      31      1    t       Lscala/concurrent/forkjoin/ForkJoinTask;
   0      47      0    this       Lscala/concurrent/forkjoin/ForkJoinWorkerThread;

  LocalVariableTypeTable: length = 0xC
   00 01 00 05 00 1F 00 FFFFFFA9 00 FFFFFFAC 00 01 

private static sun.misc.Unsafe getUnsafe()   throws java.lang.Throwable;
  Signature: ()Lsun/misc/Unsafe;
  Code:
   Stack=2, Locals=2, Args_size=0
	invokestatic	Method sun/misc/Unsafe.getUnsafe:()Lsun/misc/Unsafe;
	areturn
	astore_0
	new	class scala/concurrent/forkjoin/ForkJoinWorkerThread$1
	dup
	invokespecial	Method scala/concurrent/forkjoin/ForkJoinWorkerThread$1."<init>":()V
	invokestatic	Method java/security/AccessController.doPrivileged:(Ljava/security/PrivilegedExceptionAction;)Ljava/lang/Object;
	checkcast	class sun/misc/Unsafe
	areturn
	astore_1
	aload_1
	invokevirtual	Method java/security/PrivilegedActionException.getCause:()Ljava/lang/Throwable;
	athrow
  Labels:
  Exception table:
   from   to  target type
     0     3     4   Class java/lang/SecurityException

     5    18    19   Class java/security/PrivilegedActionException

  LocalVariableTable: 
   Start  Length  Slot  Name   Signature
   20      5      1    e       Ljava/security/PrivilegedActionException;
   5      20      0    se       Ljava/lang/SecurityException;

  Exceptions: 
   throws java.lang.Throwable
private static sun.misc.Unsafe getUnsafePrivileged()   throws java.lang.NoSuchFieldException, java.lang.IllegalAccessException;
  Signature: ()Lsun/misc/Unsafe;
  Code:
   Stack=2, Locals=1, Args_size=0
	ldc_w	class sun/misc/Unsafe
	ldc	String theUnsafe
	invokevirtual	Method java/lang/Class.getDeclaredField:(Ljava/lang/String;)Ljava/lang/reflect/Field;
	astore_0
	aload_0
	iconst_1
	invokevirtual	Method java/lang/reflect/Field.setAccessible:(Z)V
	aload_0
	aconst_null
	invokevirtual	Method java/lang/reflect/Field.get:(Ljava/lang/Object;)Ljava/lang/Object;
	checkcast	class sun/misc/Unsafe
	areturn
  Labels:
  LocalVariableTable: 
   Start  Length  Slot  Name   Signature
   9      14      0    f       Ljava/lang/reflect/Field;

  Exceptions: 
   throws java.lang.NoSuchFieldException, java.lang.IllegalAccessException
private static long fieldOffset(java.lang.String)   throws java.lang.NoSuchFieldException;
  Signature: (Ljava/lang/String;)J
  Code:
   Stack=3, Locals=1, Args_size=1
	getstatic	Field _unsafe:Lsun/misc/Unsafe;
	ldc_w	class scala/concurrent/forkjoin/ForkJoinWorkerThread
	aload_0
	invokevirtual	Method java/lang/Class.getDeclaredField:(Ljava/lang/String;)Ljava/lang/reflect/Field;
	invokevirtual	Method sun/misc/Unsafe.objectFieldOffset:(Ljava/lang/reflect/Field;)J
	lreturn
  Labels:
  LocalVariableTable: 
   Start  Length  Slot  Name   Signature
   0      14      0    fieldName       Ljava/lang/String;

  Exceptions: 
   throws java.lang.NoSuchFieldException
static sun.misc.Unsafe access$000()   throws java.lang.NoSuchFieldException, java.lang.IllegalAccessException;
  Signature: ()Lsun/misc/Unsafe;
  Code:
   Stack=1, Locals=0, Args_size=0
	invokestatic	Method getUnsafePrivileged:()Lsun/misc/Unsafe;
	areturn
  Labels:
  Exceptions: 
   throws java.lang.NoSuchFieldException, java.lang.IllegalAccessException
static {};
  Signature: ()V
  Code:
   Stack=4, Locals=1, Args_size=0
	invokestatic	Method getUnsafe:()Lsun/misc/Unsafe;
	putstatic	Field _unsafe:Lsun/misc/Unsafe;
	ldc	String base
	invokestatic	Method fieldOffset:(Ljava/lang/String;)J
	putstatic	Field baseOffset:J
	ldc	String sp
	invokestatic	Method fieldOffset:(Ljava/lang/String;)J
	putstatic	Field spOffset:J
	ldc	String runState
	invokestatic	Method fieldOffset:(Ljava/lang/String;)J
	putstatic	Field runStateOffset:J
	getstatic	Field _unsafe:Lsun/misc/Unsafe;
	ldc_w	class "[Lscala/concurrent/forkjoin/ForkJoinTask;"
	invokevirtual	Method sun/misc/Unsafe.arrayBaseOffset:(Ljava/lang/Class;)I
	i2l
	putstatic	Field qBase:J
	getstatic	Field _unsafe:Lsun/misc/Unsafe;
	ldc_w	class "[Lscala/concurrent/forkjoin/ForkJoinTask;"
	invokevirtual	Method sun/misc/Unsafe.arrayIndexScale:(Ljava/lang/Class;)I
	istore_0
	iload_0
	iload_0
	iconst_1
	isub
	iand
	ifeq	l1 // bipush
	new	class java/lang/Error
	dup
	ldc	String data type scale not a power of two
	invokespecial	Method java/lang/Error."<init>":(Ljava/lang/String;)V
	athrow
l1	bipush	31
	iload_0
	invokestatic	Method java/lang/Integer.numberOfLeadingZeros:(I)I
	isub
	putstatic	Field qShift:I
	goto	l2 // return
	astore_0
	new	class java/lang/RuntimeException
	dup
	ldc	String Could not initialize intrinsics
	aload_0
	invokespecial	Method java/lang/RuntimeException."<init>":(Ljava/lang/String;Ljava/lang/Throwable;)V
	athrow
l2	return
  Labels:
   	l1 = 71 // bipush
   	l2 = 96 // return
  Exception table:
   from   to  target type
     0    81    84   Class java/lang/Throwable

  LocalVariableTable: 
   Start  Length  Slot  Name   Signature
   53      28      0    s       I
   85      11      0    e       Ljava/lang/Throwable;


}

