Compiled from "ForkJoinPool.java"
final class scala.concurrent.forkjoin.ForkJoinPool$WaitQueueNode extends java.lang.Object
  SourceFile: "ForkJoinPool.java"
  InnerClass: 
   final #11= #8 of #42; //WaitQueueNode=class scala/concurrent/forkjoin/ForkJoinPool$WaitQueueNode of class scala/concurrent/forkjoin/ForkJoinPool
  minor version: 0
  major version: 49
  Constant pool:
const #1 = Method	#9.#37;	//  java/lang/Object."<init>":()V
const #2 = Field	#8.#38;	//  scala/concurrent/forkjoin/ForkJoinPool$WaitQueueNode.count:J
const #3 = Field	#8.#39;	//  scala/concurrent/forkjoin/ForkJoinPool$WaitQueueNode.thread:Lscala/concurrent/forkjoin/ForkJoinWorkerThread;
const #4 = Method	#40.#41;	//  java/util/concurrent/locks/LockSupport.unpark:(Ljava/lang/Thread;)V
const #5 = Method	#42.#43;	//  scala/concurrent/forkjoin/ForkJoinPool.syncIsReleasable:(Lscala/concurrent/forkjoin/ForkJoinPool$WaitQueueNode;)Z
const #6 = Method	#40.#44;	//  java/util/concurrent/locks/LockSupport.park:(Ljava/lang/Object;)V
const #7 = Method	#45.#46;	//  java/lang/Thread.interrupted:()Z
const #8 = class	#47;	//  scala/concurrent/forkjoin/ForkJoinPool$WaitQueueNode
const #9 = class	#48;	//  java/lang/Object
const #10 = Asciz	next;
const #11 = Asciz	WaitQueueNode;
const #12 = Asciz	InnerClasses;
const #13 = Asciz	Lscala/concurrent/forkjoin/ForkJoinPool$WaitQueueNode;;
const #14 = Asciz	thread;
const #15 = Asciz	Lscala/concurrent/forkjoin/ForkJoinWorkerThread;;
const #16 = Asciz	count;
const #17 = Asciz	J;
const #18 = Asciz	<init>;
const #19 = Asciz	(JLscala/concurrent/forkjoin/ForkJoinWorkerThread;)V;
const #20 = Asciz	Code;
const #21 = Asciz	LineNumberTable;
const #22 = Asciz	LocalVariableTable;
const #23 = Asciz	this;
const #24 = Asciz	c;
const #25 = Asciz	w;
const #26 = Asciz	signal;
const #27 = Asciz	()Z;
const #28 = Asciz	t;
const #29 = Asciz	awaitSyncRelease;
const #30 = Asciz	(Lscala/concurrent/forkjoin/ForkJoinPool;)V;
const #31 = Asciz	p;
const #32 = Asciz	Lscala/concurrent/forkjoin/ForkJoinPool;;
const #33 = Asciz	awaitSpareRelease;
const #34 = Asciz	()V;
const #35 = Asciz	SourceFile;
const #36 = Asciz	ForkJoinPool.java;
const #37 = NameAndType	#18:#34;//  "<init>":()V
const #38 = NameAndType	#16:#17;//  count:J
const #39 = NameAndType	#14:#15;//  thread:Lscala/concurrent/forkjoin/ForkJoinWorkerThread;
const #40 = class	#49;	//  java/util/concurrent/locks/LockSupport
const #41 = NameAndType	#50:#51;//  unpark:(Ljava/lang/Thread;)V
const #42 = class	#52;	//  scala/concurrent/forkjoin/ForkJoinPool
const #43 = NameAndType	#53:#54;//  syncIsReleasable:(Lscala/concurrent/forkjoin/ForkJoinPool$WaitQueueNode;)Z
const #44 = NameAndType	#55:#56;//  park:(Ljava/lang/Object;)V
const #45 = class	#57;	//  java/lang/Thread
const #46 = NameAndType	#58:#27;//  interrupted:()Z
const #47 = Asciz	scala/concurrent/forkjoin/ForkJoinPool$WaitQueueNode;
const #48 = Asciz	java/lang/Object;
const #49 = Asciz	java/util/concurrent/locks/LockSupport;
const #50 = Asciz	unpark;
const #51 = Asciz	(Ljava/lang/Thread;)V;
const #52 = Asciz	scala/concurrent/forkjoin/ForkJoinPool;
const #53 = Asciz	syncIsReleasable;
const #54 = Asciz	(Lscala/concurrent/forkjoin/ForkJoinPool$WaitQueueNode;)Z;
const #55 = Asciz	park;
const #56 = Asciz	(Ljava/lang/Object;)V;
const #57 = Asciz	java/lang/Thread;
const #58 = Asciz	interrupted;

{
scala.concurrent.forkjoin.ForkJoinPool$WaitQueueNode next;

volatile scala.concurrent.forkjoin.ForkJoinWorkerThread thread;

final long count;

scala.concurrent.forkjoin.ForkJoinPool$WaitQueueNode(long, scala.concurrent.forkjoin.ForkJoinWorkerThread);
  Code:
   Stack=3, Locals=4, Args_size=3
   0:	aload_0
   1:	invokespecial	#1; //Method java/lang/Object."<init>":()V
   4:	aload_0
   5:	lload_1
   6:	putfield	#2; //Field count:J
   9:	aload_0
   10:	aload_3
   11:	putfield	#3; //Field thread:Lscala/concurrent/forkjoin/ForkJoinWorkerThread;
   14:	return
  LineNumberTable: 
   line 1318: 0
   line 1319: 4
   line 1320: 9
   line 1321: 14

  LocalVariableTable: 
   Start  Length  Slot  Name   Signature
   0      15      0    this       Lscala/concurrent/forkjoin/ForkJoinPool$WaitQueueNode;
   0      15      1    c       J
   0      15      3    w       Lscala/concurrent/forkjoin/ForkJoinWorkerThread;


boolean signal();
  Code:
   Stack=2, Locals=2, Args_size=1
   0:	aload_0
   1:	getfield	#3; //Field thread:Lscala/concurrent/forkjoin/ForkJoinWorkerThread;
   4:	astore_1
   5:	aload_1
   6:	ifnonnull	11
   9:	iconst_0
   10:	ireturn
   11:	aload_0
   12:	aconst_null
   13:	putfield	#3; //Field thread:Lscala/concurrent/forkjoin/ForkJoinWorkerThread;
   16:	aload_1
   17:	invokestatic	#4; //Method java/util/concurrent/locks/LockSupport.unpark:(Ljava/lang/Thread;)V
   20:	iconst_1
   21:	ireturn
  LineNumberTable: 
   line 1327: 0
   line 1328: 5
   line 1329: 9
   line 1330: 11
   line 1331: 16
   line 1332: 20

  LocalVariableTable: 
   Start  Length  Slot  Name   Signature
   0      22      0    this       Lscala/concurrent/forkjoin/ForkJoinPool$WaitQueueNode;
   5      17      1    t       Lscala/concurrent/forkjoin/ForkJoinWorkerThread;


void awaitSyncRelease(scala.concurrent.forkjoin.ForkJoinPool);
  Code:
   Stack=2, Locals=2, Args_size=2
   0:	aload_0
   1:	getfield	#3; //Field thread:Lscala/concurrent/forkjoin/ForkJoinWorkerThread;
   4:	ifnull	22
   7:	aload_1
   8:	aload_0
   9:	invokevirtual	#5; //Method scala/concurrent/forkjoin/ForkJoinPool.syncIsReleasable:(Lscala/concurrent/forkjoin/ForkJoinPool$WaitQueueNode;)Z
   12:	ifne	22
   15:	aload_0
   16:	invokestatic	#6; //Method java/util/concurrent/locks/LockSupport.park:(Ljava/lang/Object;)V
   19:	goto	0
   22:	return
  LineNumberTable: 
   line 1339: 0
   line 1340: 15
   line 1341: 22

  LocalVariableTable: 
   Start  Length  Slot  Name   Signature
   0      23      0    this       Lscala/concurrent/forkjoin/ForkJoinPool$WaitQueueNode;
   0      23      1    p       Lscala/concurrent/forkjoin/ForkJoinPool;


void awaitSpareRelease();
  Code:
   Stack=1, Locals=1, Args_size=1
   0:	aload_0
   1:	getfield	#3; //Field thread:Lscala/concurrent/forkjoin/ForkJoinWorkerThread;
   4:	ifnull	20
   7:	invokestatic	#7; //Method java/lang/Thread.interrupted:()Z
   10:	ifne	0
   13:	aload_0
   14:	invokestatic	#6; //Method java/util/concurrent/locks/LockSupport.park:(Ljava/lang/Object;)V
   17:	goto	0
   20:	return
  LineNumberTable: 
   line 1347: 0
   line 1348: 7
   line 1349: 13
   line 1351: 20

  LocalVariableTable: 
   Start  Length  Slot  Name   Signature
   0      21      0    this       Lscala/concurrent/forkjoin/ForkJoinPool$WaitQueueNode;


}

