Compiled from "ForkJoinPool.java"
final class scala.concurrent.forkjoin.ForkJoinPool$AdaptedCallable extends scala.concurrent.forkjoin.ForkJoinTask implements scala.concurrent.forkjoin.ForkJoinPool$RunnableFuture
  Signature: length = 0x2
   00 34 
  SourceFile: "ForkJoinPool.java"
  InnerClass: 
   final #28= #12 of #66; //AdaptedCallable=class scala/concurrent/forkjoin/ForkJoinPool$AdaptedCallable of class scala/concurrent/forkjoin/ForkJoinPool
   abstract #51= #14 of #66; //RunnableFuture=class scala/concurrent/forkjoin/ForkJoinPool$RunnableFuture of class scala/concurrent/forkjoin/ForkJoinPool
  minor version: 0
  major version: 49
  Constant pool:
const #1 = Method	#13.#55;	//  scala/concurrent/forkjoin/ForkJoinTask."<init>":()V
const #2 = class	#56;	//  java/lang/NullPointerException
const #3 = Method	#2.#55;	//  java/lang/NullPointerException."<init>":()V
const #4 = Field	#12.#57;	//  scala/concurrent/forkjoin/ForkJoinPool$AdaptedCallable.callable:Ljava/util/concurrent/Callable;
const #5 = Field	#12.#58;	//  scala/concurrent/forkjoin/ForkJoinPool$AdaptedCallable.result:Ljava/lang/Object;
const #6 = InterfaceMethod	#59.#60;	//  java/util/concurrent/Callable.call:()Ljava/lang/Object;
const #7 = class	#61;	//  java/lang/Error
const #8 = class	#62;	//  java/lang/RuntimeException
const #9 = class	#63;	//  java/lang/Exception
const #10 = Method	#8.#64;	//  java/lang/RuntimeException."<init>":(Ljava/lang/Throwable;)V
const #11 = Method	#12.#65;	//  scala/concurrent/forkjoin/ForkJoinPool$AdaptedCallable.invoke:()Ljava/lang/Object;
const #12 = class	#67;	//  scala/concurrent/forkjoin/ForkJoinPool$AdaptedCallable
const #13 = class	#68;	//  scala/concurrent/forkjoin/ForkJoinTask
const #14 = class	#69;	//  scala/concurrent/forkjoin/ForkJoinPool$RunnableFuture
const #15 = Asciz	callable;
const #16 = Asciz	Ljava/util/concurrent/Callable;;
const #17 = Asciz	Signature;
const #18 = Asciz	Ljava/util/concurrent/Callable<TT;>;;
const #19 = Asciz	result;
const #20 = Asciz	Ljava/lang/Object;;
const #21 = Asciz	TT;;
const #22 = Asciz	<init>;
const #23 = Asciz	(Ljava/util/concurrent/Callable;)V;
const #24 = Asciz	Code;
const #25 = Asciz	LineNumberTable;
const #26 = Asciz	LocalVariableTable;
const #27 = Asciz	this;
const #28 = Asciz	AdaptedCallable;
const #29 = Asciz	InnerClasses;
const #30 = Asciz	Lscala/concurrent/forkjoin/ForkJoinPool$AdaptedCallable;;
const #31 = Asciz	LocalVariableTypeTable;
const #32 = Asciz	Lscala/concurrent/forkjoin/ForkJoinPool$AdaptedCallable<TT;>;;
const #33 = Asciz	(Ljava/util/concurrent/Callable<TT;>;)V;
const #34 = Asciz	getRawResult;
const #35 = Asciz	()Ljava/lang/Object;;
const #36 = Asciz	()TT;;
const #37 = Asciz	setRawResult;
const #38 = Asciz	(Ljava/lang/Object;)V;
const #39 = Asciz	v;
const #40 = Asciz	(TT;)V;
const #41 = Asciz	exec;
const #42 = Asciz	()Z;
const #43 = Asciz	err;
const #44 = Asciz	Ljava/lang/Error;;
const #45 = Asciz	rex;
const #46 = Asciz	Ljava/lang/RuntimeException;;
const #47 = Asciz	ex;
const #48 = Asciz	Ljava/lang/Exception;;
const #49 = Asciz	run;
const #50 = Asciz	()V;
const #51 = Asciz	RunnableFuture;
const #52 = Asciz	<T:Ljava/lang/Object;>Lscala/concurrent/forkjoin/ForkJoinTask<TT;>;Lscala/concurrent/forkjoin/ForkJoinPool$RunnableFuture<TT;>;;
const #53 = Asciz	SourceFile;
const #54 = Asciz	ForkJoinPool.java;
const #55 = NameAndType	#22:#50;//  "<init>":()V
const #56 = Asciz	java/lang/NullPointerException;
const #57 = NameAndType	#15:#16;//  callable:Ljava/util/concurrent/Callable;
const #58 = NameAndType	#19:#20;//  result:Ljava/lang/Object;
const #59 = class	#70;	//  java/util/concurrent/Callable
const #60 = NameAndType	#71:#35;//  call:()Ljava/lang/Object;
const #61 = Asciz	java/lang/Error;
const #62 = Asciz	java/lang/RuntimeException;
const #63 = Asciz	java/lang/Exception;
const #64 = NameAndType	#22:#72;//  "<init>":(Ljava/lang/Throwable;)V
const #65 = NameAndType	#73:#35;//  invoke:()Ljava/lang/Object;
const #66 = class	#74;	//  scala/concurrent/forkjoin/ForkJoinPool
const #67 = Asciz	scala/concurrent/forkjoin/ForkJoinPool$AdaptedCallable;
const #68 = Asciz	scala/concurrent/forkjoin/ForkJoinTask;
const #69 = Asciz	scala/concurrent/forkjoin/ForkJoinPool$RunnableFuture;
const #70 = Asciz	java/util/concurrent/Callable;
const #71 = Asciz	call;
const #72 = Asciz	(Ljava/lang/Throwable;)V;
const #73 = Asciz	invoke;
const #74 = Asciz	scala/concurrent/forkjoin/ForkJoinPool;

{
final java.util.concurrent.Callable callable;
  Signature: length = 0x2
   00 12 

java.lang.Object result;
  Signature: length = 0x2
   00 15 

scala.concurrent.forkjoin.ForkJoinPool$AdaptedCallable(java.util.concurrent.Callable);
  Code:
   Stack=2, Locals=2, Args_size=2
   0:	aload_0
   1:	invokespecial	#1; //Method scala/concurrent/forkjoin/ForkJoinTask."<init>":()V
   4:	aload_1
   5:	ifnonnull	16
   8:	new	#2; //class java/lang/NullPointerException
   11:	dup
   12:	invokespecial	#3; //Method java/lang/NullPointerException."<init>":()V
   15:	athrow
   16:	aload_0
   17:	aload_1
   18:	putfield	#4; //Field callable:Ljava/util/concurrent/Callable;
   21:	return
  LineNumberTable: 
   line 625: 0
   line 626: 4
   line 627: 16
   line 628: 21

  LocalVariableTable: 
   Start  Length  Slot  Name   Signature
   0      22      0    this       Lscala/concurrent/forkjoin/ForkJoinPool$AdaptedCallable;
   0      22      1    callable       Ljava/util/concurrent/Callable;

  LocalVariableTypeTable: length = 0x16
   00 02 00 00 00 16 00 1B 00 20 00 00 00 00 00 16
   00 0F 00 12 00 01 
  Signature: length = 0x2
   00 21 

public java.lang.Object getRawResult();
  Code:
   Stack=1, Locals=1, Args_size=1
   0:	aload_0
   1:	getfield	#5; //Field result:Ljava/lang/Object;
   4:	areturn
  LineNumberTable: 
   line 629: 0

  LocalVariableTable: 
   Start  Length  Slot  Name   Signature
   0      5      0    this       Lscala/concurrent/forkjoin/ForkJoinPool$AdaptedCallable;

  LocalVariableTypeTable: length = 0xC
   00 01 00 00 00 05 00 1B 00 20 00 00 
  Signature: length = 0x2
   00 24 

public void setRawResult(java.lang.Object);
  Code:
   Stack=2, Locals=2, Args_size=2
   0:	aload_0
   1:	aload_1
   2:	putfield	#5; //Field result:Ljava/lang/Object;
   5:	return
  LineNumberTable: 
   line 630: 0

  LocalVariableTable: 
   Start  Length  Slot  Name   Signature
   0      6      0    this       Lscala/concurrent/forkjoin/ForkJoinPool$AdaptedCallable;
   0      6      1    v       Ljava/lang/Object;

  LocalVariableTypeTable: length = 0x16
   00 02 00 00 00 06 00 1B 00 20 00 00 00 00 00 06
   00 27 00 15 00 01 
  Signature: length = 0x2
   00 28 

public boolean exec();
  Code:
   Stack=3, Locals=2, Args_size=1
   0:	aload_0
   1:	aload_0
   2:	getfield	#4; //Field callable:Ljava/util/concurrent/Callable;
   5:	invokeinterface	#6,  1; //InterfaceMethod java/util/concurrent/Callable.call:()Ljava/lang/Object;
   10:	putfield	#5; //Field result:Ljava/lang/Object;
   13:	iconst_1
   14:	ireturn
   15:	astore_1
   16:	aload_1
   17:	athrow
   18:	astore_1
   19:	aload_1
   20:	athrow
   21:	astore_1
   22:	new	#8; //class java/lang/RuntimeException
   25:	dup
   26:	aload_1
   27:	invokespecial	#10; //Method java/lang/RuntimeException."<init>":(Ljava/lang/Throwable;)V
   30:	athrow
  Exception table:
   from   to  target type
     0    14    15   Class java/lang/Error

     0    14    18   Class java/lang/RuntimeException

     0    14    21   Class java/lang/Exception

  LineNumberTable: 
   line 633: 0
   line 634: 13
   line 635: 15
   line 636: 16
   line 637: 18
   line 638: 19
   line 639: 21
   line 640: 22

  LocalVariableTable: 
   Start  Length  Slot  Name   Signature
   16      2      1    err       Ljava/lang/Error;
   19      2      1    rex       Ljava/lang/RuntimeException;
   22      9      1    ex       Ljava/lang/Exception;
   0      31      0    this       Lscala/concurrent/forkjoin/ForkJoinPool$AdaptedCallable;

  LocalVariableTypeTable: length = 0xC
   00 01 00 00 00 1F 00 1B 00 20 00 00 

public void run();
  Code:
   Stack=1, Locals=1, Args_size=1
   0:	aload_0
   1:	invokevirtual	#11; //Method invoke:()Ljava/lang/Object;
   4:	pop
   5:	return
  LineNumberTable: 
   line 643: 0

  LocalVariableTable: 
   Start  Length  Slot  Name   Signature
   0      6      0    this       Lscala/concurrent/forkjoin/ForkJoinPool$AdaptedCallable;

  LocalVariableTypeTable: length = 0xC
   00 01 00 00 00 06 00 1B 00 20 00 00 

}

