public class scala.concurrent.forkjoin.LinkedTransferQueue extends java.util.AbstractQueue implements scala.concurrent.forkjoin.TransferQueue,java.io.Serializable
  Signature: length = 0x2
   00 FFFFFFCA 
  InnerClass: 
   Itr=class scala/concurrent/forkjoin/LinkedTransferQueue$Itr of class scala/concurrent/forkjoin/LinkedTransferQueue
   final PaddedAtomicReference=class scala/concurrent/forkjoin/LinkedTransferQueue$PaddedAtomicReference of class scala/concurrent/forkjoin/LinkedTransferQueue
   final QNode=class scala/concurrent/forkjoin/LinkedTransferQueue$QNode of class scala/concurrent/forkjoin/LinkedTransferQueue
   class scala/concurrent/forkjoin/LinkedTransferQueue$1
  minor version: 0
  major version: 49
  Constant pool:
Method	scala/concurrent/forkjoin/LinkedTransferQueue.getUnsafePrivileged:()Lsun/misc/Unsafe;
Method	scala/concurrent/forkjoin/LinkedTransferQueue.clean:(Lscala/concurrent/forkjoin/LinkedTransferQueue$QNode;Lscala/concurrent/forkjoin/LinkedTransferQueue$QNode;)V
Method	scala/concurrent/forkjoin/LinkedTransferQueue.traversalHead:()Lscala/concurrent/forkjoin/LinkedTransferQueue$QNode;
Field	scala/concurrent/forkjoin/LinkedTransferQueue.head:Lscala/concurrent/forkjoin/LinkedTransferQueue$PaddedAtomicReference;
Method	scala/concurrent/forkjoin/LinkedTransferQueue$PaddedAtomicReference.get:()Ljava/lang/Object;
Method	scala/concurrent/forkjoin/LinkedTransferQueue$PaddedAtomicReference.compareAndSet:(Ljava/lang/Object;Ljava/lang/Object;)Z
Method	scala/concurrent/forkjoin/LinkedTransferQueue$QNode.clearNext:()V
Field	scala/concurrent/forkjoin/LinkedTransferQueue.tail:Lscala/concurrent/forkjoin/LinkedTransferQueue$PaddedAtomicReference;
class	scala/concurrent/forkjoin/LinkedTransferQueue$QNode
Field	scala/concurrent/forkjoin/LinkedTransferQueue$QNode.isData:Z
Method	scala/concurrent/forkjoin/LinkedTransferQueue$QNode."<init>":(Ljava/lang/Object;Z)V
Field	scala/concurrent/forkjoin/LinkedTransferQueue$QNode.next:Lscala/concurrent/forkjoin/LinkedTransferQueue$QNode;
Method	scala/concurrent/forkjoin/LinkedTransferQueue$QNode.casNext:(Lscala/concurrent/forkjoin/LinkedTransferQueue$QNode;Lscala/concurrent/forkjoin/LinkedTransferQueue$QNode;)Z
Method	scala/concurrent/forkjoin/LinkedTransferQueue.awaitFulfill:(Lscala/concurrent/forkjoin/LinkedTransferQueue$QNode;Lscala/concurrent/forkjoin/LinkedTransferQueue$QNode;Ljava/lang/Object;IJ)Ljava/lang/Object;
Method	scala/concurrent/forkjoin/LinkedTransferQueue.advanceHead:(Lscala/concurrent/forkjoin/LinkedTransferQueue$QNode;Lscala/concurrent/forkjoin/LinkedTransferQueue$QNode;)Z
Method	scala/concurrent/forkjoin/LinkedTransferQueue$QNode.get:()Ljava/lang/Object;
Method	scala/concurrent/forkjoin/LinkedTransferQueue$QNode.compareAndSet:(Ljava/lang/Object;Ljava/lang/Object;)Z
Field	scala/concurrent/forkjoin/LinkedTransferQueue$QNode.waiter:Ljava/lang/Thread;
Method	java/util/concurrent/locks/LockSupport.unpark:(Ljava/lang/Thread;)V
Method	java/lang/System.nanoTime:()J
Method	java/lang/Thread.currentThread:()Ljava/lang/Thread;
Method	java/lang/Thread.isInterrupted:()Z
Method	scala/concurrent/forkjoin/LinkedTransferQueue$QNode.set:(Ljava/lang/Object;)V
Field	scala/concurrent/forkjoin/LinkedTransferQueue.maxTimedSpins:I
Field	scala/concurrent/forkjoin/LinkedTransferQueue.maxUntimedSpins:I
Method	java/util/concurrent/locks/LockSupport.park:(Ljava/lang/Object;)V
long	1000l;
Method	java/util/concurrent/locks/LockSupport.parkNanos:(Ljava/lang/Object;J)V
Method	scala/concurrent/forkjoin/LinkedTransferQueue.reclean:()Lscala/concurrent/forkjoin/LinkedTransferQueue$QNode;
Method	scala/concurrent/forkjoin/LinkedTransferQueue.getValidatedTail:()Lscala/concurrent/forkjoin/LinkedTransferQueue$QNode;
Field	scala/concurrent/forkjoin/LinkedTransferQueue.cleanMe:Lscala/concurrent/forkjoin/LinkedTransferQueue$PaddedAtomicReference;
Method	java/util/AbstractQueue."<init>":()V
class	scala/concurrent/forkjoin/LinkedTransferQueue$PaddedAtomicReference
Method	scala/concurrent/forkjoin/LinkedTransferQueue$PaddedAtomicReference."<init>":(Ljava/lang/Object;)V
Method	scala/concurrent/forkjoin/LinkedTransferQueue."<init>":()V
Method	scala/concurrent/forkjoin/LinkedTransferQueue.addAll:(Ljava/util/Collection;)Z
class	java/lang/NullPointerException
Method	java/lang/NullPointerException."<init>":()V
Method	java/lang/Thread.interrupted:()Z
class	java/lang/InterruptedException
Method	java/lang/InterruptedException."<init>":()V
Method	scala/concurrent/forkjoin/LinkedTransferQueue.xfer:(Ljava/lang/Object;IJ)Ljava/lang/Object;
Method	java/util/concurrent/TimeUnit.toNanos:(J)J
Method	scala/concurrent/forkjoin/LinkedTransferQueue.fulfill:(Ljava/lang/Object;)Ljava/lang/Object;
class	java/lang/IllegalArgumentException
Method	java/lang/IllegalArgumentException."<init>":()V
Method	scala/concurrent/forkjoin/LinkedTransferQueue.poll:()Ljava/lang/Object;
InterfaceMethod	java/util/Collection.add:(Ljava/lang/Object;)Z
class	scala/concurrent/forkjoin/LinkedTransferQueue$Itr
Method	scala/concurrent/forkjoin/LinkedTransferQueue$Itr."<init>":(Lscala/concurrent/forkjoin/LinkedTransferQueue;)V
int	2147483647;
Method	java/lang/Object.equals:(Ljava/lang/Object;)Z
Method	java/io/ObjectOutputStream.defaultWriteObject:()V
Method	scala/concurrent/forkjoin/LinkedTransferQueue.iterator:()Ljava/util/Iterator;
InterfaceMethod	java/util/Iterator.hasNext:()Z
InterfaceMethod	java/util/Iterator.next:()Ljava/lang/Object;
Method	java/io/ObjectOutputStream.writeObject:(Ljava/lang/Object;)V
Method	java/io/ObjectInputStream.defaultReadObject:()V
Method	scala/concurrent/forkjoin/LinkedTransferQueue.resetHeadAndTail:()V
Method	java/io/ObjectInputStream.readObject:()Ljava/lang/Object;
Method	scala/concurrent/forkjoin/LinkedTransferQueue.offer:(Ljava/lang/Object;)Z
Field	scala/concurrent/forkjoin/LinkedTransferQueue._unsafe:Lsun/misc/Unsafe;
Field	scala/concurrent/forkjoin/LinkedTransferQueue.headOffset:J
Method	sun/misc/Unsafe.putObjectVolatile:(Ljava/lang/Object;JLjava/lang/Object;)V
Field	scala/concurrent/forkjoin/LinkedTransferQueue.tailOffset:J
Field	scala/concurrent/forkjoin/LinkedTransferQueue.cleanMeOffset:J
Method	sun/misc/Unsafe.getUnsafe:()Lsun/misc/Unsafe;
class	java/lang/SecurityException
class	scala/concurrent/forkjoin/LinkedTransferQueue$1
Method	scala/concurrent/forkjoin/LinkedTransferQueue$1."<init>":()V
Method	java/security/AccessController.doPrivileged:(Ljava/security/PrivilegedExceptionAction;)Ljava/lang/Object;
class	sun/misc/Unsafe
class	java/security/PrivilegedActionException
Method	java/security/PrivilegedActionException.getCause:()Ljava/lang/Throwable;
String	theUnsafe
Method	java/lang/Class.getDeclaredField:(Ljava/lang/String;)Ljava/lang/reflect/Field;
Method	java/lang/reflect/Field.setAccessible:(Z)V
Method	java/lang/reflect/Field.get:(Ljava/lang/Object;)Ljava/lang/Object;
class	scala/concurrent/forkjoin/LinkedTransferQueue
Method	sun/misc/Unsafe.objectFieldOffset:(Ljava/lang/reflect/Field;)J
Method	java/lang/Runtime.getRuntime:()Ljava/lang/Runtime;
Method	java/lang/Runtime.availableProcessors:()I
Field	scala/concurrent/forkjoin/LinkedTransferQueue.NCPUS:I
Method	scala/concurrent/forkjoin/LinkedTransferQueue.getUnsafe:()Lsun/misc/Unsafe;
String	head
Method	scala/concurrent/forkjoin/LinkedTransferQueue.fieldOffset:(Ljava/lang/String;)J
String	tail
String	cleanMe
class	java/lang/Throwable
class	java/lang/RuntimeException
String	Could not initialize intrinsics
Method	java/lang/RuntimeException."<init>":(Ljava/lang/String;Ljava/lang/Throwable;)V
class	java/util/AbstractQueue
class	scala/concurrent/forkjoin/TransferQueue
class	java/io/Serializable
Asciz	Itr;
Asciz	InnerClasses;
Asciz	PaddedAtomicReference;
Asciz	QNode;
Asciz	serialVersionUID;
Asciz	J;
Asciz	ConstantValue;
long	-3223113410248163686l;
Asciz	NOWAIT;
Asciz	I;
int	0;
Asciz	TIMEOUT;
int	1;
Asciz	WAIT;
int	2;
Asciz	NCPUS;
Asciz	maxTimedSpins;
Asciz	maxUntimedSpins;
Asciz	spinForTimeoutThreshold;
Asciz	head;
Asciz	Lscala/concurrent/forkjoin/LinkedTransferQueue$PaddedAtomicReference;;
Asciz	Signature;
Asciz	Lscala/concurrent/forkjoin/LinkedTransferQueue$PaddedAtomicReference<Lscala/concurrent/forkjoin/LinkedTransferQueue$QNode;>;;
Asciz	tail;
Asciz	cleanMe;
Asciz	_unsafe;
Asciz	Lsun/misc/Unsafe;;
Asciz	headOffset;
Asciz	tailOffset;
Asciz	cleanMeOffset;
Asciz	advanceHead;
Asciz	(Lscala/concurrent/forkjoin/LinkedTransferQueue$QNode;Lscala/concurrent/forkjoin/LinkedTransferQueue$QNode;)Z;
Asciz	Code;
Asciz	xfer;
Asciz	(Ljava/lang/Object;IJ)Ljava/lang/Object;;
Asciz	fulfill;
Asciz	(Ljava/lang/Object;)Ljava/lang/Object;;
Asciz	awaitFulfill;
Asciz	(Lscala/concurrent/forkjoin/LinkedTransferQueue$QNode;Lscala/concurrent/forkjoin/LinkedTransferQueue$QNode;Ljava/lang/Object;IJ)Ljava/lang/Object;;
Asciz	getValidatedTail;
Asciz	()Lscala/concurrent/forkjoin/LinkedTransferQueue$QNode;;
Asciz	clean;
Asciz	(Lscala/concurrent/forkjoin/LinkedTransferQueue$QNode;Lscala/concurrent/forkjoin/LinkedTransferQueue$QNode;)V;
Asciz	reclean;
Asciz	<init>;
Asciz	()V;
Asciz	(Ljava/util/Collection;)V;
Asciz	(Ljava/util/Collection<+TE;>;)V;
Asciz	put;
Asciz	(Ljava/lang/Object;)V;
Asciz	Exceptions;
Asciz	(TE;)V;
Asciz	offer;
Asciz	(Ljava/lang/Object;JLjava/util/concurrent/TimeUnit;)Z;
Asciz	(TE;JLjava/util/concurrent/TimeUnit;)Z;
Asciz	(Ljava/lang/Object;)Z;
Asciz	(TE;)Z;
Asciz	add;
Asciz	transfer;
Asciz	tryTransfer;
Asciz	take;
Asciz	()Ljava/lang/Object;;
Asciz	()TE;;
Asciz	poll;
Asciz	(JLjava/util/concurrent/TimeUnit;)Ljava/lang/Object;;
Asciz	(JLjava/util/concurrent/TimeUnit;)TE;;
Asciz	drainTo;
Asciz	(Ljava/util/Collection;)I;
Asciz	(Ljava/util/Collection<-TE;>;)I;
Asciz	(Ljava/util/Collection;I)I;
Asciz	(Ljava/util/Collection<-TE;>;I)I;
Asciz	traversalHead;
Asciz	iterator;
Asciz	()Ljava/util/Iterator;;
Asciz	()Ljava/util/Iterator<TE;>;;
Asciz	peek;
Asciz	isEmpty;
Asciz	()Z;
Asciz	hasWaitingConsumer;
Asciz	size;
Asciz	()I;
Asciz	getWaitingConsumerCount;
Asciz	remainingCapacity;
Asciz	remove;
Asciz	writeObject;
Asciz	(Ljava/io/ObjectOutputStream;)V;
class	java/io/IOException
Asciz	readObject;
Asciz	(Ljava/io/ObjectInputStream;)V;
class	java/lang/ClassNotFoundException
Asciz	resetHeadAndTail;
Asciz	getUnsafe;
Asciz	()Lsun/misc/Unsafe;;
Asciz	getUnsafePrivileged;
class	java/lang/NoSuchFieldException
class	java/lang/IllegalAccessException
Asciz	fieldOffset;
Asciz	(Ljava/lang/String;)J;
Asciz	access$000;
Asciz	(Lscala/concurrent/forkjoin/LinkedTransferQueue;)Lscala/concurrent/forkjoin/LinkedTransferQueue$QNode;;
Asciz	access$100;
Asciz	(Lscala/concurrent/forkjoin/LinkedTransferQueue;Lscala/concurrent/forkjoin/LinkedTransferQueue$QNode;Lscala/concurrent/forkjoin/LinkedTransferQueue$QNode;)V;
Asciz	access$200;
Asciz	<clinit>;
Asciz	<E:Ljava/lang/Object;>Ljava/util/AbstractQueue<TE;>;Lscala/concurrent/forkjoin/TransferQueue<TE;>;Ljava/io/Serializable;;
NameAndType	getUnsafePrivileged:()Lsun/misc/Unsafe;
NameAndType	clean:(Lscala/concurrent/forkjoin/LinkedTransferQueue$QNode;Lscala/concurrent/forkjoin/LinkedTransferQueue$QNode;)V
NameAndType	traversalHead:()Lscala/concurrent/forkjoin/LinkedTransferQueue$QNode;
NameAndType	head:Lscala/concurrent/forkjoin/LinkedTransferQueue$PaddedAtomicReference;
NameAndType	get:()Ljava/lang/Object;
NameAndType	compareAndSet:(Ljava/lang/Object;Ljava/lang/Object;)Z
NameAndType	clearNext:()V
NameAndType	tail:Lscala/concurrent/forkjoin/LinkedTransferQueue$PaddedAtomicReference;
Asciz	scala/concurrent/forkjoin/LinkedTransferQueue$QNode;
NameAndType	isData:Z
NameAndType	"<init>":(Ljava/lang/Object;Z)V
NameAndType	next:Lscala/concurrent/forkjoin/LinkedTransferQueue$QNode;
NameAndType	casNext:(Lscala/concurrent/forkjoin/LinkedTransferQueue$QNode;Lscala/concurrent/forkjoin/LinkedTransferQueue$QNode;)Z
NameAndType	awaitFulfill:(Lscala/concurrent/forkjoin/LinkedTransferQueue$QNode;Lscala/concurrent/forkjoin/LinkedTransferQueue$QNode;Ljava/lang/Object;IJ)Ljava/lang/Object;
NameAndType	advanceHead:(Lscala/concurrent/forkjoin/LinkedTransferQueue$QNode;Lscala/concurrent/forkjoin/LinkedTransferQueue$QNode;)Z
NameAndType	waiter:Ljava/lang/Thread;
class	java/util/concurrent/locks/LockSupport
NameAndType	unpark:(Ljava/lang/Thread;)V
class	java/lang/System
NameAndType	nanoTime:()J
class	java/lang/Thread
NameAndType	currentThread:()Ljava/lang/Thread;
NameAndType	isInterrupted:()Z
NameAndType	set:(Ljava/lang/Object;)V
NameAndType	maxTimedSpins:I
NameAndType	maxUntimedSpins:I
NameAndType	park:(Ljava/lang/Object;)V
NameAndType	parkNanos:(Ljava/lang/Object;J)V
NameAndType	reclean:()Lscala/concurrent/forkjoin/LinkedTransferQueue$QNode;
NameAndType	getValidatedTail:()Lscala/concurrent/forkjoin/LinkedTransferQueue$QNode;
NameAndType	cleanMe:Lscala/concurrent/forkjoin/LinkedTransferQueue$PaddedAtomicReference;
NameAndType	"<init>":()V
Asciz	scala/concurrent/forkjoin/LinkedTransferQueue$PaddedAtomicReference;
NameAndType	"<init>":(Ljava/lang/Object;)V
NameAndType	addAll:(Ljava/util/Collection;)Z
Asciz	java/lang/NullPointerException;
NameAndType	interrupted:()Z
Asciz	java/lang/InterruptedException;
NameAndType	xfer:(Ljava/lang/Object;IJ)Ljava/lang/Object;
class	java/util/concurrent/TimeUnit
NameAndType	toNanos:(J)J
NameAndType	fulfill:(Ljava/lang/Object;)Ljava/lang/Object;
Asciz	java/lang/IllegalArgumentException;
NameAndType	poll:()Ljava/lang/Object;
class	java/util/Collection
NameAndType	add:(Ljava/lang/Object;)Z
Asciz	scala/concurrent/forkjoin/LinkedTransferQueue$Itr;
NameAndType	"<init>":(Lscala/concurrent/forkjoin/LinkedTransferQueue;)V
class	java/lang/Object
NameAndType	equals:(Ljava/lang/Object;)Z
class	java/io/ObjectOutputStream
NameAndType	defaultWriteObject:()V
NameAndType	iterator:()Ljava/util/Iterator;
class	java/util/Iterator
NameAndType	hasNext:()Z
NameAndType	next:()Ljava/lang/Object;
NameAndType	writeObject:(Ljava/lang/Object;)V
class	java/io/ObjectInputStream
NameAndType	defaultReadObject:()V
NameAndType	resetHeadAndTail:()V
NameAndType	readObject:()Ljava/lang/Object;
NameAndType	offer:(Ljava/lang/Object;)Z
NameAndType	_unsafe:Lsun/misc/Unsafe;
NameAndType	headOffset:J
NameAndType	putObjectVolatile:(Ljava/lang/Object;JLjava/lang/Object;)V
NameAndType	tailOffset:J
NameAndType	cleanMeOffset:J
NameAndType	getUnsafe:()Lsun/misc/Unsafe;
Asciz	java/lang/SecurityException;
Asciz	scala/concurrent/forkjoin/LinkedTransferQueue$1;
Asciz	;
class	java/security/AccessController
NameAndType	doPrivileged:(Ljava/security/PrivilegedExceptionAction;)Ljava/lang/Object;
Asciz	sun/misc/Unsafe;
Asciz	java/security/PrivilegedActionException;
NameAndType	getCause:()Ljava/lang/Throwable;
Asciz	theUnsafe;
class	java/lang/Class
NameAndType	getDeclaredField:(Ljava/lang/String;)Ljava/lang/reflect/Field;
class	java/lang/reflect/Field
NameAndType	setAccessible:(Z)V
NameAndType	get:(Ljava/lang/Object;)Ljava/lang/Object;
Asciz	scala/concurrent/forkjoin/LinkedTransferQueue;
NameAndType	objectFieldOffset:(Ljava/lang/reflect/Field;)J
class	java/lang/Runtime
NameAndType	getRuntime:()Ljava/lang/Runtime;
NameAndType	availableProcessors:()I
NameAndType	NCPUS:I
NameAndType	fieldOffset:(Ljava/lang/String;)J
Asciz	java/lang/Throwable;
Asciz	java/lang/RuntimeException;
Asciz	Could not initialize intrinsics;
NameAndType	"<init>":(Ljava/lang/String;Ljava/lang/Throwable;)V
Asciz	java/util/AbstractQueue;
Asciz	scala/concurrent/forkjoin/TransferQueue;
Asciz	java/io/Serializable;
Asciz	java/io/IOException;
Asciz	java/lang/ClassNotFoundException;
Asciz	java/lang/NoSuchFieldException;
Asciz	java/lang/IllegalAccessException;
Asciz	get;
Asciz	compareAndSet;
Asciz	(Ljava/lang/Object;Ljava/lang/Object;)Z;
Asciz	clearNext;
Asciz	isData;
Asciz	Z;
Asciz	(Ljava/lang/Object;Z)V;
Asciz	next;
Asciz	Lscala/concurrent/forkjoin/LinkedTransferQueue$QNode;;
Asciz	casNext;
Asciz	waiter;
Asciz	Ljava/lang/Thread;;
Asciz	java/util/concurrent/locks/LockSupport;
Asciz	unpark;
Asciz	(Ljava/lang/Thread;)V;
Asciz	java/lang/System;
Asciz	nanoTime;
Asciz	()J;
Asciz	java/lang/Thread;
Asciz	currentThread;
Asciz	()Ljava/lang/Thread;;
Asciz	isInterrupted;
Asciz	set;
Asciz	park;
Asciz	parkNanos;
Asciz	(Ljava/lang/Object;J)V;
Asciz	addAll;
Asciz	(Ljava/util/Collection;)Z;
Asciz	interrupted;
Asciz	java/util/concurrent/TimeUnit;
Asciz	toNanos;
Asciz	(J)J;
Asciz	java/util/Collection;
Asciz	(Lscala/concurrent/forkjoin/LinkedTransferQueue;)V;
Asciz	java/lang/Object;
Asciz	equals;
Asciz	java/io/ObjectOutputStream;
Asciz	defaultWriteObject;
Asciz	java/util/Iterator;
Asciz	hasNext;
Asciz	java/io/ObjectInputStream;
Asciz	defaultReadObject;
Asciz	putObjectVolatile;
Asciz	(Ljava/lang/Object;JLjava/lang/Object;)V;
Asciz	java/security/AccessController;
Asciz	doPrivileged;
Asciz	(Ljava/security/PrivilegedExceptionAction;)Ljava/lang/Object;;
Asciz	getCause;
Asciz	()Ljava/lang/Throwable;;
Asciz	java/lang/Class;
Asciz	getDeclaredField;
Asciz	(Ljava/lang/String;)Ljava/lang/reflect/Field;;
Asciz	java/lang/reflect/Field;
Asciz	setAccessible;
Asciz	(Z)V;
Asciz	objectFieldOffset;
Asciz	(Ljava/lang/reflect/Field;)J;
Asciz	java/lang/Runtime;
Asciz	getRuntime;
Asciz	()Ljava/lang/Runtime;;
Asciz	availableProcessors;
Asciz	(Ljava/lang/String;Ljava/lang/Throwable;)V;

{
private static final long serialVersionUID;
  Signature: J
  Constant value: long -3223113410248163686l
static final int NOWAIT;
  Signature: I
  Constant value: int 0
static final int TIMEOUT;
  Signature: I
  Constant value: int 1
static final int WAIT;
  Signature: I
  Constant value: int 2
static final int NCPUS;
  Signature: I

static final int maxTimedSpins;
  Signature: I

static final int maxUntimedSpins;
  Signature: I

static final long spinForTimeoutThreshold;
  Signature: J
  Constant value: long 1000l
private final transient scala.concurrent.forkjoin.LinkedTransferQueue$PaddedAtomicReference head;
  Signature: Lscala/concurrent/forkjoin/LinkedTransferQueue$PaddedAtomicReference;
  Signature: length = 0x2
   00 78 

private final transient scala.concurrent.forkjoin.LinkedTransferQueue$PaddedAtomicReference tail;
  Signature: Lscala/concurrent/forkjoin/LinkedTransferQueue$PaddedAtomicReference;
  Signature: length = 0x2
   00 78 

private final transient scala.concurrent.forkjoin.LinkedTransferQueue$PaddedAtomicReference cleanMe;
  Signature: Lscala/concurrent/forkjoin/LinkedTransferQueue$PaddedAtomicReference;
  Signature: length = 0x2
   00 78 

private static final sun.misc.Unsafe _unsafe;
  Signature: Lsun/misc/Unsafe;

private static final long headOffset;
  Signature: J

private static final long tailOffset;
  Signature: J

private static final long cleanMeOffset;
  Signature: J

private boolean advanceHead(scala.concurrent.forkjoin.LinkedTransferQueue$QNode, scala.concurrent.forkjoin.LinkedTransferQueue$QNode);
  Signature: (Lscala/concurrent/forkjoin/LinkedTransferQueue$QNode;Lscala/concurrent/forkjoin/LinkedTransferQueue$QNode;)Z
  Code:
   Stack=3, Locals=3, Args_size=3
	aload_1
	aload_0
	getfield	Field head:Lscala/concurrent/forkjoin/LinkedTransferQueue$PaddedAtomicReference;
	invokevirtual	Method scala/concurrent/forkjoin/LinkedTransferQueue$PaddedAtomicReference.get:()Ljava/lang/Object;
	if_acmpne	l1 // iconst_0
	aload_0
	getfield	Field head:Lscala/concurrent/forkjoin/LinkedTransferQueue$PaddedAtomicReference;
	aload_1
	aload_2
	invokevirtual	Method scala/concurrent/forkjoin/LinkedTransferQueue$PaddedAtomicReference.compareAndSet:(Ljava/lang/Object;Ljava/lang/Object;)Z
	ifeq	l1 // iconst_0
	aload_1
	invokevirtual	Method scala/concurrent/forkjoin/LinkedTransferQueue$QNode.clearNext:()V
	iconst_1
	ireturn
l1	iconst_0
	ireturn
  Labels:
   	l1 = 29 // iconst_0

private java.lang.Object xfer(java.lang.Object, int, long);
  Signature: (Ljava/lang/Object;IJ)Ljava/lang/Object;
  Code:
   Stack=7, Locals=13, Args_size=4
	aload_1
	ifnull	l1 // iconst_0
	iconst_1
	goto	l2 // istore
l1	iconst_0
l2	istore	5
	aconst_null
	astore	6
	aload_0
	getfield	Field head:Lscala/concurrent/forkjoin/LinkedTransferQueue$PaddedAtomicReference;
	astore	7
	aload_0
	getfield	Field tail:Lscala/concurrent/forkjoin/LinkedTransferQueue$PaddedAtomicReference;
	astore	8
l11	aload	8
	invokevirtual	Method scala/concurrent/forkjoin/LinkedTransferQueue$PaddedAtomicReference.get:()Ljava/lang/Object;
	checkcast	class scala/concurrent/forkjoin/LinkedTransferQueue$QNode
	astore	9
	aload	7
	invokevirtual	Method scala/concurrent/forkjoin/LinkedTransferQueue$PaddedAtomicReference.get:()Ljava/lang/Object;
	checkcast	class scala/concurrent/forkjoin/LinkedTransferQueue$QNode
	astore	10
	aload	9
	ifnull	l3 // aload
	aload	9
	aload	10
	if_acmpeq	l4 // aload
	aload	9
	getfield	Field scala/concurrent/forkjoin/LinkedTransferQueue$QNode.isData:Z
	iload	5
	if_icmpne	l3 // aload
l4	aload	6
	ifnonnull	l5 // aload
	new	class scala/concurrent/forkjoin/LinkedTransferQueue$QNode
	dup
	aload_1
	iload	5
	invokespecial	Method scala/concurrent/forkjoin/LinkedTransferQueue$QNode."<init>":(Ljava/lang/Object;Z)V
	astore	6
l5	aload	9
	getfield	Field scala/concurrent/forkjoin/LinkedTransferQueue$QNode.next:Lscala/concurrent/forkjoin/LinkedTransferQueue$QNode;
	astore	11
	aload	11
	ifnull	l6 // aload
	aload	9
	aload	8
	invokevirtual	Method scala/concurrent/forkjoin/LinkedTransferQueue$PaddedAtomicReference.get:()Ljava/lang/Object;
	if_acmpne	l7 // goto
	aload	8
	aload	9
	aload	11
	invokevirtual	Method scala/concurrent/forkjoin/LinkedTransferQueue$PaddedAtomicReference.compareAndSet:(Ljava/lang/Object;Ljava/lang/Object;)Z
	pop
	goto	l7 // goto
l6	aload	9
	aconst_null
	aload	6
	invokevirtual	Method scala/concurrent/forkjoin/LinkedTransferQueue$QNode.casNext:(Lscala/concurrent/forkjoin/LinkedTransferQueue$QNode;Lscala/concurrent/forkjoin/LinkedTransferQueue$QNode;)Z
	ifeq	l7 // goto
	aload	8
	aload	9
	aload	6
	invokevirtual	Method scala/concurrent/forkjoin/LinkedTransferQueue$PaddedAtomicReference.compareAndSet:(Ljava/lang/Object;Ljava/lang/Object;)Z
	pop
	aload_0
	aload	9
	aload	6
	aload_1
	iload_2
	lload_3
	invokespecial	Method awaitFulfill:(Lscala/concurrent/forkjoin/LinkedTransferQueue$QNode;Lscala/concurrent/forkjoin/LinkedTransferQueue$QNode;Ljava/lang/Object;IJ)Ljava/lang/Object;
	areturn
l7	goto	l8 // goto
l3	aload	10
	ifnull	l8 // goto
	aload	10
	getfield	Field scala/concurrent/forkjoin/LinkedTransferQueue$QNode.next:Lscala/concurrent/forkjoin/LinkedTransferQueue$QNode;
	astore	11
	aload	9
	aload	8
	invokevirtual	Method scala/concurrent/forkjoin/LinkedTransferQueue$PaddedAtomicReference.get:()Ljava/lang/Object;
	if_acmpne	l8 // goto
	aload	11
	ifnull	l8 // goto
	aload_0
	aload	10
	aload	11
	invokespecial	Method advanceHead:(Lscala/concurrent/forkjoin/LinkedTransferQueue$QNode;Lscala/concurrent/forkjoin/LinkedTransferQueue$QNode;)Z
	ifeq	l8 // goto
	aload	11
	invokevirtual	Method scala/concurrent/forkjoin/LinkedTransferQueue$QNode.get:()Ljava/lang/Object;
	astore	12
	aload	12
	aload	11
	if_acmpeq	l8 // goto
	aload	11
	aload	12
	aload_1
	invokevirtual	Method scala/concurrent/forkjoin/LinkedTransferQueue$QNode.compareAndSet:(Ljava/lang/Object;Ljava/lang/Object;)Z
	ifeq	l8 // goto
	aload	11
	getfield	Field scala/concurrent/forkjoin/LinkedTransferQueue$QNode.waiter:Ljava/lang/Thread;
	invokestatic	Method java/util/concurrent/locks/LockSupport.unpark:(Ljava/lang/Thread;)V
	iload	5
	ifeq	l9 // aload
	aload_1
	goto	l10 // areturn
l9	aload	12
l10	areturn
l8	goto	l11 // aload
  Labels:
   	l1 = 8 // iconst_0
   	l2 = 9 // istore
   	l11 = 26 // aload
   	l4 = 68 // aload
   	l5 = 85 // aload
   	l6 = 120 // aload
   	l7 = 153 // goto
   	l3 = 156 // aload
   	l9 = 236 // aload
   	l10 = 238 // areturn
   	l8 = 239 // goto

private java.lang.Object fulfill(java.lang.Object);
  Signature: (Ljava/lang/Object;)Ljava/lang/Object;
  Code:
   Stack=3, Locals=9, Args_size=2
	aload_1
	ifnull	l1 // iconst_0
	iconst_1
	goto	l2 // istore_2
l1	iconst_0
l2	istore_2
	aload_0
	getfield	Field head:Lscala/concurrent/forkjoin/LinkedTransferQueue$PaddedAtomicReference;
	astore_3
	aload_0
	getfield	Field tail:Lscala/concurrent/forkjoin/LinkedTransferQueue$PaddedAtomicReference;
	astore	4
l10	aload	4
	invokevirtual	Method scala/concurrent/forkjoin/LinkedTransferQueue$PaddedAtomicReference.get:()Ljava/lang/Object;
	checkcast	class scala/concurrent/forkjoin/LinkedTransferQueue$QNode
	astore	5
	aload_3
	invokevirtual	Method scala/concurrent/forkjoin/LinkedTransferQueue$PaddedAtomicReference.get:()Ljava/lang/Object;
	checkcast	class scala/concurrent/forkjoin/LinkedTransferQueue$QNode
	astore	6
	aload	5
	ifnull	l3 // aload
	aload	5
	aload	6
	if_acmpeq	l4 // aload
	aload	5
	getfield	Field scala/concurrent/forkjoin/LinkedTransferQueue$QNode.isData:Z
	iload_2
	if_icmpne	l3 // aload
l4	aload	5
	getfield	Field scala/concurrent/forkjoin/LinkedTransferQueue$QNode.next:Lscala/concurrent/forkjoin/LinkedTransferQueue$QNode;
	astore	7
	aload	5
	aload	4
	invokevirtual	Method scala/concurrent/forkjoin/LinkedTransferQueue$PaddedAtomicReference.get:()Ljava/lang/Object;
	if_acmpne	l5 // goto
	aload	7
	ifnull	l6 // aconst_null
	aload	4
	aload	5
	aload	7
	invokevirtual	Method scala/concurrent/forkjoin/LinkedTransferQueue$PaddedAtomicReference.compareAndSet:(Ljava/lang/Object;Ljava/lang/Object;)Z
	pop
	goto	l5 // goto
l6	aconst_null
	areturn
l5	goto	l7 // goto
l3	aload	6
	ifnull	l7 // goto
	aload	6
	getfield	Field scala/concurrent/forkjoin/LinkedTransferQueue$QNode.next:Lscala/concurrent/forkjoin/LinkedTransferQueue$QNode;
	astore	7
	aload	5
	aload	4
	invokevirtual	Method scala/concurrent/forkjoin/LinkedTransferQueue$PaddedAtomicReference.get:()Ljava/lang/Object;
	if_acmpne	l7 // goto
	aload	7
	ifnull	l7 // goto
	aload_0
	aload	6
	aload	7
	invokespecial	Method advanceHead:(Lscala/concurrent/forkjoin/LinkedTransferQueue$QNode;Lscala/concurrent/forkjoin/LinkedTransferQueue$QNode;)Z
	ifeq	l7 // goto
	aload	7
	invokevirtual	Method scala/concurrent/forkjoin/LinkedTransferQueue$QNode.get:()Ljava/lang/Object;
	astore	8
	aload	8
	aload	7
	if_acmpeq	l7 // goto
	aload	7
	aload	8
	aload_1
	invokevirtual	Method scala/concurrent/forkjoin/LinkedTransferQueue$QNode.compareAndSet:(Ljava/lang/Object;Ljava/lang/Object;)Z
	ifeq	l7 // goto
	aload	7
	getfield	Field scala/concurrent/forkjoin/LinkedTransferQueue$QNode.waiter:Ljava/lang/Thread;
	invokestatic	Method java/util/concurrent/locks/LockSupport.unpark:(Ljava/lang/Thread;)V
	iload_2
	ifeq	l8 // aload
	aload_1
	goto	l9 // areturn
l8	aload	8
l9	areturn
l7	goto	l10 // aload
  Labels:
   	l1 = 8 // iconst_0
   	l2 = 9 // istore_2
   	l10 = 21 // aload
   	l4 = 61 // aload
   	l6 = 96 // aconst_null
   	l5 = 98 // goto
   	l3 = 101 // aload
   	l8 = 180 // aload
   	l9 = 182 // areturn
   	l7 = 183 // goto

private java.lang.Object awaitFulfill(scala.concurrent.forkjoin.LinkedTransferQueue$QNode, scala.concurrent.forkjoin.LinkedTransferQueue$QNode, java.lang.Object, int, long);
  Signature: (Lscala/concurrent/forkjoin/LinkedTransferQueue$QNode;Lscala/concurrent/forkjoin/LinkedTransferQueue$QNode;Ljava/lang/Object;IJ)Ljava/lang/Object;
  Code:
   Stack=6, Locals=14, Args_size=6
	iload	4
	ifne	l1 // iload
	aconst_null
	areturn
l1	iload	4
	iconst_1
	if_icmpne	l2 // lconst_0
	invokestatic	Method java/lang/System.nanoTime:()J
	goto	l3 // lstore
l2	lconst_0
l3	lstore	7
	invokestatic	Method java/lang/Thread.currentThread:()Ljava/lang/Thread;
	astore	9
	iconst_m1
	istore	10
l9	aload	9
	invokevirtual	Method java/lang/Thread.isInterrupted:()Z
	ifeq	l4 // aload_2
	aload_2
	aload_3
	aload_2
	invokevirtual	Method scala/concurrent/forkjoin/LinkedTransferQueue$QNode.compareAndSet:(Ljava/lang/Object;Ljava/lang/Object;)Z
	pop
l4	aload_2
	invokevirtual	Method scala/concurrent/forkjoin/LinkedTransferQueue$QNode.get:()Ljava/lang/Object;
	astore	11
	aload	11
	aload_3
	if_acmpeq	l5 // iload
	aload_0
	aload_1
	aload_2
	invokespecial	Method advanceHead:(Lscala/concurrent/forkjoin/LinkedTransferQueue$QNode;Lscala/concurrent/forkjoin/LinkedTransferQueue$QNode;)Z
	pop
	aload	11
	aload_2
	if_acmpne	l6 // aload
	aload_0
	aload_1
	aload_2
	invokespecial	Method clean:(Lscala/concurrent/forkjoin/LinkedTransferQueue$QNode;Lscala/concurrent/forkjoin/LinkedTransferQueue$QNode;)V
	aconst_null
	areturn
l6	aload	11
	ifnull	l7 // aload_3
	aload_2
	aload_2
	invokevirtual	Method scala/concurrent/forkjoin/LinkedTransferQueue$QNode.set:(Ljava/lang/Object;)V
	aload	11
	areturn
l7	aload_3
	areturn
l5	iload	4
	iconst_1
	if_icmpne	l8 // iload
	invokestatic	Method java/lang/System.nanoTime:()J
	lstore	12
	lload	5
	lload	12
	lload	7
	lsub
	lsub
	lstore	5
	lload	12
	lstore	7
	lload	5
	lconst_0
	lcmp
	ifgt	l8 // iload
	aload_2
	aload_3
	aload_2
	invokevirtual	Method scala/concurrent/forkjoin/LinkedTransferQueue$QNode.compareAndSet:(Ljava/lang/Object;Ljava/lang/Object;)Z
	pop
	goto	l9 // aload
l8	iload	10
	ifge	l10 // iload
	aload_0
	getfield	Field head:Lscala/concurrent/forkjoin/LinkedTransferQueue$PaddedAtomicReference;
	invokevirtual	Method scala/concurrent/forkjoin/LinkedTransferQueue$PaddedAtomicReference.get:()Ljava/lang/Object;
	checkcast	class scala/concurrent/forkjoin/LinkedTransferQueue$QNode
	astore	12
	aload	12
	ifnull	l11 // iconst_0
	aload	12
	getfield	Field scala/concurrent/forkjoin/LinkedTransferQueue$QNode.next:Lscala/concurrent/forkjoin/LinkedTransferQueue$QNode;
	aload_2
	if_acmpne	l11 // iconst_0
	iload	4
	iconst_1
	if_icmpne	l12 // getstatic
	getstatic	Field maxTimedSpins:I
	goto	l13 // istore
l12	getstatic	Field maxUntimedSpins:I
	goto	l13 // istore
l11	iconst_0
l13	istore	10
l10	iload	10
	ifle	l14 // aload_2
	iinc	10, -1
	goto	l15 // goto
l14	aload_2
	getfield	Field scala/concurrent/forkjoin/LinkedTransferQueue$QNode.waiter:Ljava/lang/Thread;
	ifnonnull	l16 // iload
	aload_2
	aload	9
	putfield	Field scala/concurrent/forkjoin/LinkedTransferQueue$QNode.waiter:Ljava/lang/Thread;
	goto	l15 // goto
l16	iload	4
	iconst_1
	if_icmpeq	l17 // lload
	aload_0
	invokestatic	Method java/util/concurrent/locks/LockSupport.park:(Ljava/lang/Object;)V
	aload_2
	aconst_null
	putfield	Field scala/concurrent/forkjoin/LinkedTransferQueue$QNode.waiter:Ljava/lang/Thread;
	iconst_m1
	istore	10
	goto	l15 // goto
l17	lload	5
	ldc2_w	long 1000l
	lcmp
	ifle	l15 // goto
	aload_0
	lload	5
	invokestatic	Method java/util/concurrent/locks/LockSupport.parkNanos:(Ljava/lang/Object;J)V
	aload_2
	aconst_null
	putfield	Field scala/concurrent/forkjoin/LinkedTransferQueue$QNode.waiter:Ljava/lang/Thread;
	iconst_m1
	istore	10
l15	goto	l9 // aload
  Labels:
   	l1 = 7 // iload
   	l2 = 19 // lconst_0
   	l3 = 20 // lstore
   	l9 = 30 // aload
   	l4 = 45 // aload_2
   	l6 = 78 // aload
   	l7 = 91 // aload_3
   	l5 = 93 // iload
   	l8 = 135 // iload
   	l12 = 178 // getstatic
   	l11 = 184 // iconst_0
   	l13 = 185 // istore
   	l10 = 187 // iload
   	l14 = 198 // aload_2
   	l16 = 214 // iload
   	l17 = 235 // lload
   	l15 = 258 // goto

private scala.concurrent.forkjoin.LinkedTransferQueue$QNode getValidatedTail();
  Signature: ()Lscala/concurrent/forkjoin/LinkedTransferQueue$QNode;
  Code:
   Stack=3, Locals=5, Args_size=1
l2	aload_0
	getfield	Field head:Lscala/concurrent/forkjoin/LinkedTransferQueue$PaddedAtomicReference;
	invokevirtual	Method scala/concurrent/forkjoin/LinkedTransferQueue$PaddedAtomicReference.get:()Ljava/lang/Object;
	checkcast	class scala/concurrent/forkjoin/LinkedTransferQueue$QNode
	astore_1
	aload_1
	getfield	Field scala/concurrent/forkjoin/LinkedTransferQueue$QNode.next:Lscala/concurrent/forkjoin/LinkedTransferQueue$QNode;
	astore_2
	aload_2
	ifnull	l1 // aload_0
	aload_2
	getfield	Field scala/concurrent/forkjoin/LinkedTransferQueue$QNode.next:Lscala/concurrent/forkjoin/LinkedTransferQueue$QNode;
	aload_2
	if_acmpne	l1 // aload_0
	aload_0
	aload_1
	aload_2
	invokespecial	Method advanceHead:(Lscala/concurrent/forkjoin/LinkedTransferQueue$QNode;Lscala/concurrent/forkjoin/LinkedTransferQueue$QNode;)Z
	pop
	goto	l2 // aload_0
l1	aload_0
	getfield	Field tail:Lscala/concurrent/forkjoin/LinkedTransferQueue$PaddedAtomicReference;
	invokevirtual	Method scala/concurrent/forkjoin/LinkedTransferQueue$PaddedAtomicReference.get:()Ljava/lang/Object;
	checkcast	class scala/concurrent/forkjoin/LinkedTransferQueue$QNode
	astore_3
	aload_3
	getfield	Field scala/concurrent/forkjoin/LinkedTransferQueue$QNode.next:Lscala/concurrent/forkjoin/LinkedTransferQueue$QNode;
	astore	4
	aload_3
	aload_0
	getfield	Field tail:Lscala/concurrent/forkjoin/LinkedTransferQueue$PaddedAtomicReference;
	invokevirtual	Method scala/concurrent/forkjoin/LinkedTransferQueue$PaddedAtomicReference.get:()Ljava/lang/Object;
	if_acmpne	l3 // goto
	aload	4
	ifnull	l4 // aload_3
	aload_0
	getfield	Field tail:Lscala/concurrent/forkjoin/LinkedTransferQueue$PaddedAtomicReference;
	aload_3
	aload	4
	invokevirtual	Method scala/concurrent/forkjoin/LinkedTransferQueue$PaddedAtomicReference.compareAndSet:(Ljava/lang/Object;Ljava/lang/Object;)Z
	pop
	goto	l3 // goto
l4	aload_3
	areturn
l3	goto	l2 // aload_0
  Labels:
   	l2 = 0 // aload_0
   	l1 = 38 // aload_0
   	l4 = 85 // aload_3
   	l3 = 87 // goto

private void clean(scala.concurrent.forkjoin.LinkedTransferQueue$QNode, scala.concurrent.forkjoin.LinkedTransferQueue$QNode);
  Signature: (Lscala/concurrent/forkjoin/LinkedTransferQueue$QNode;Lscala/concurrent/forkjoin/LinkedTransferQueue$QNode;)V
  Code:
   Stack=3, Locals=7, Args_size=3
	aload_2
	getfield	Field scala/concurrent/forkjoin/LinkedTransferQueue$QNode.waiter:Ljava/lang/Thread;
	astore_3
	aload_3
	ifnull	l1 // aload_1
	aload_2
	aconst_null
	putfield	Field scala/concurrent/forkjoin/LinkedTransferQueue$QNode.waiter:Ljava/lang/Thread;
	aload_3
	invokestatic	Method java/lang/Thread.currentThread:()Ljava/lang/Thread;
	if_acmpeq	l1 // aload_1
	aload_3
	invokestatic	Method java/util/concurrent/locks/LockSupport.unpark:(Ljava/lang/Thread;)V
l1	aload_1
	ifnonnull	l2 // aload_1
	return
l2	aload_1
	getfield	Field scala/concurrent/forkjoin/LinkedTransferQueue$QNode.next:Lscala/concurrent/forkjoin/LinkedTransferQueue$QNode;
	aload_2
	if_acmpne	l3 // return
	aload_0
	invokespecial	Method reclean:()Lscala/concurrent/forkjoin/LinkedTransferQueue$QNode;
	astore	4
	aload_0
	invokespecial	Method getValidatedTail:()Lscala/concurrent/forkjoin/LinkedTransferQueue$QNode;
	astore	5
	aload_2
	aload	5
	if_acmpeq	l4 // aload
	aload_2
	getfield	Field scala/concurrent/forkjoin/LinkedTransferQueue$QNode.next:Lscala/concurrent/forkjoin/LinkedTransferQueue$QNode;
	astore	6
	aload	6
	aload_2
	if_acmpeq	l3 // return
	aload_1
	aload_2
	aload	6
	invokevirtual	Method scala/concurrent/forkjoin/LinkedTransferQueue$QNode.casNext:(Lscala/concurrent/forkjoin/LinkedTransferQueue$QNode;Lscala/concurrent/forkjoin/LinkedTransferQueue$QNode;)Z
	ifeq	l5 // goto
	goto	l3 // return
l5	goto	l6 // goto
l4	aload	4
	aload_1
	if_acmpeq	l3 // return
	aload	4
	ifnonnull	l6 // goto
	aload_0
	getfield	Field cleanMe:Lscala/concurrent/forkjoin/LinkedTransferQueue$PaddedAtomicReference;
	aconst_null
	aload_1
	invokevirtual	Method scala/concurrent/forkjoin/LinkedTransferQueue$PaddedAtomicReference.compareAndSet:(Ljava/lang/Object;Ljava/lang/Object;)Z
	ifeq	l6 // goto
	goto	l3 // return
l6	goto	l2 // aload_1
l3	return
  Labels:
   	l1 = 25 // aload_1
   	l2 = 30 // aload_1
   	l5 = 81 // goto
   	l4 = 84 // aload
   	l6 = 110 // goto
   	l3 = 113 // return

private scala.concurrent.forkjoin.LinkedTransferQueue$QNode reclean();
  Signature: ()Lscala/concurrent/forkjoin/LinkedTransferQueue$QNode;
  Code:
   Stack=3, Locals=5, Args_size=1
l4	aload_0
	getfield	Field cleanMe:Lscala/concurrent/forkjoin/LinkedTransferQueue$PaddedAtomicReference;
	invokevirtual	Method scala/concurrent/forkjoin/LinkedTransferQueue$PaddedAtomicReference.get:()Ljava/lang/Object;
	checkcast	class scala/concurrent/forkjoin/LinkedTransferQueue$QNode
	dup
	astore_1
	ifnull	l1 // aload_1
	aload_0
	invokespecial	Method getValidatedTail:()Lscala/concurrent/forkjoin/LinkedTransferQueue$QNode;
	astore_2
	aload_1
	getfield	Field scala/concurrent/forkjoin/LinkedTransferQueue$QNode.next:Lscala/concurrent/forkjoin/LinkedTransferQueue$QNode;
	astore_3
	aload_3
	aload_2
	if_acmpeq	l1 // aload_1
	aload_3
	ifnull	l2 // aload_0
	aload_3
	aload_1
	if_acmpeq	l2 // aload_0
	aload_3
	invokevirtual	Method scala/concurrent/forkjoin/LinkedTransferQueue$QNode.get:()Ljava/lang/Object;
	aload_3
	if_acmpne	l2 // aload_0
	aload_3
	getfield	Field scala/concurrent/forkjoin/LinkedTransferQueue$QNode.next:Lscala/concurrent/forkjoin/LinkedTransferQueue$QNode;
	dup
	astore	4
	aload_3
	if_acmpeq	l2 // aload_0
	aload_1
	aload_3
	aload	4
	invokevirtual	Method scala/concurrent/forkjoin/LinkedTransferQueue$QNode.casNext:(Lscala/concurrent/forkjoin/LinkedTransferQueue$QNode;Lscala/concurrent/forkjoin/LinkedTransferQueue$QNode;)Z
	ifeq	l3 // goto
l2	aload_0
	getfield	Field cleanMe:Lscala/concurrent/forkjoin/LinkedTransferQueue$PaddedAtomicReference;
	aload_1
	aconst_null
	invokevirtual	Method scala/concurrent/forkjoin/LinkedTransferQueue$PaddedAtomicReference.compareAndSet:(Ljava/lang/Object;Ljava/lang/Object;)Z
	pop
l3	goto	l4 // aload_0
l1	aload_1
	areturn
  Labels:
   	l4 = 0 // aload_0
   	l2 = 68 // aload_0
   	l3 = 78 // goto
   	l1 = 81 // aload_1

public scala.concurrent.forkjoin.LinkedTransferQueue();
  Signature: ()V
  Code:
   Stack=4, Locals=2, Args_size=1
	aload_0
	invokespecial	Method java/util/AbstractQueue."<init>":()V
	new	class scala/concurrent/forkjoin/LinkedTransferQueue$QNode
	dup
	aconst_null
	iconst_0
	invokespecial	Method scala/concurrent/forkjoin/LinkedTransferQueue$QNode."<init>":(Ljava/lang/Object;Z)V
	astore_1
	aload_0
	new	class scala/concurrent/forkjoin/LinkedTransferQueue$PaddedAtomicReference
	dup
	aload_1
	invokespecial	Method scala/concurrent/forkjoin/LinkedTransferQueue$PaddedAtomicReference."<init>":(Ljava/lang/Object;)V
	putfield	Field head:Lscala/concurrent/forkjoin/LinkedTransferQueue$PaddedAtomicReference;
	aload_0
	new	class scala/concurrent/forkjoin/LinkedTransferQueue$PaddedAtomicReference
	dup
	aload_1
	invokespecial	Method scala/concurrent/forkjoin/LinkedTransferQueue$PaddedAtomicReference."<init>":(Ljava/lang/Object;)V
	putfield	Field tail:Lscala/concurrent/forkjoin/LinkedTransferQueue$PaddedAtomicReference;
	aload_0
	new	class scala/concurrent/forkjoin/LinkedTransferQueue$PaddedAtomicReference
	dup
	aconst_null
	invokespecial	Method scala/concurrent/forkjoin/LinkedTransferQueue$PaddedAtomicReference."<init>":(Ljava/lang/Object;)V
	putfield	Field cleanMe:Lscala/concurrent/forkjoin/LinkedTransferQueue$PaddedAtomicReference;
	return
  Labels:

public scala.concurrent.forkjoin.LinkedTransferQueue(java.util.Collection);
  Signature: (Ljava/util/Collection;)V
  Code:
   Stack=2, Locals=2, Args_size=2
	aload_0
	invokespecial	Method "<init>":()V
	aload_0
	aload_1
	invokevirtual	Method addAll:(Ljava/util/Collection;)Z
	pop
	return
  Labels:
  Signature: length = 0x2
   00 FFFFFF91 

public void put(java.lang.Object)   throws java.lang.InterruptedException;
  Signature: (Ljava/lang/Object;)V
  Code:
   Stack=5, Locals=2, Args_size=2
	aload_1
	ifnonnull	l1 // invokestatic
	new	class java/lang/NullPointerException
	dup
	invokespecial	Method java/lang/NullPointerException."<init>":()V
	athrow
l1	invokestatic	Method java/lang/Thread.interrupted:()Z
	ifeq	l2 // aload_0
	new	class java/lang/InterruptedException
	dup
	invokespecial	Method java/lang/InterruptedException."<init>":()V
	athrow
l2	aload_0
	aload_1
	iconst_0
	lconst_0
	invokespecial	Method xfer:(Ljava/lang/Object;IJ)Ljava/lang/Object;
	pop
	return
  Labels:
   	l1 = 12 // invokestatic
   	l2 = 26 // aload_0
  Exceptions: 
   throws java.lang.InterruptedException  Signature: length = 0x2
   00 FFFFFF95 

public boolean offer(java.lang.Object, long, java.util.concurrent.TimeUnit)   throws java.lang.InterruptedException;
  Signature: (Ljava/lang/Object;JLjava/util/concurrent/TimeUnit;)Z
  Code:
   Stack=5, Locals=5, Args_size=4
	aload_1
	ifnonnull	l1 // invokestatic
	new	class java/lang/NullPointerException
	dup
	invokespecial	Method java/lang/NullPointerException."<init>":()V
	athrow
l1	invokestatic	Method java/lang/Thread.interrupted:()Z
	ifeq	l2 // aload_0
	new	class java/lang/InterruptedException
	dup
	invokespecial	Method java/lang/InterruptedException."<init>":()V
	athrow
l2	aload_0
	aload_1
	iconst_0
	lconst_0
	invokespecial	Method xfer:(Ljava/lang/Object;IJ)Ljava/lang/Object;
	pop
	iconst_1
	ireturn
  Labels:
   	l1 = 12 // invokestatic
   	l2 = 26 // aload_0
  Exceptions: 
   throws java.lang.InterruptedException  Signature: length = 0x2
   00 FFFFFF98 

public boolean offer(java.lang.Object);
  Signature: (Ljava/lang/Object;)Z
  Code:
   Stack=5, Locals=2, Args_size=2
	aload_1
	ifnonnull	l1 // aload_0
	new	class java/lang/NullPointerException
	dup
	invokespecial	Method java/lang/NullPointerException."<init>":()V
	athrow
l1	aload_0
	aload_1
	iconst_0
	lconst_0
	invokespecial	Method xfer:(Ljava/lang/Object;IJ)Ljava/lang/Object;
	pop
	iconst_1
	ireturn
  Labels:
   	l1 = 12 // aload_0
  Signature: length = 0x2
   00 FFFFFF9A 

public boolean add(java.lang.Object);
  Signature: (Ljava/lang/Object;)Z
  Code:
   Stack=5, Locals=2, Args_size=2
	aload_1
	ifnonnull	l1 // aload_0
	new	class java/lang/NullPointerException
	dup
	invokespecial	Method java/lang/NullPointerException."<init>":()V
	athrow
l1	aload_0
	aload_1
	iconst_0
	lconst_0
	invokespecial	Method xfer:(Ljava/lang/Object;IJ)Ljava/lang/Object;
	pop
	iconst_1
	ireturn
  Labels:
   	l1 = 12 // aload_0
  Signature: length = 0x2
   00 FFFFFF9A 

public void transfer(java.lang.Object)   throws java.lang.InterruptedException;
  Signature: (Ljava/lang/Object;)V
  Code:
   Stack=5, Locals=2, Args_size=2
	aload_1
	ifnonnull	l1 // aload_0
	new	class java/lang/NullPointerException
	dup
	invokespecial	Method java/lang/NullPointerException."<init>":()V
	athrow
l1	aload_0
	aload_1
	iconst_2
	lconst_0
	invokespecial	Method xfer:(Ljava/lang/Object;IJ)Ljava/lang/Object;
	ifnonnull	l2 // return
	invokestatic	Method java/lang/Thread.interrupted:()Z
	pop
	new	class java/lang/InterruptedException
	dup
	invokespecial	Method java/lang/InterruptedException."<init>":()V
	athrow
l2	return
  Labels:
   	l1 = 12 // aload_0
   	l2 = 34 // return
  Exceptions: 
   throws java.lang.InterruptedException  Signature: length = 0x2
   00 FFFFFF95 

public boolean tryTransfer(java.lang.Object, long, java.util.concurrent.TimeUnit)   throws java.lang.InterruptedException;
  Signature: (Ljava/lang/Object;JLjava/util/concurrent/TimeUnit;)Z
  Code:
   Stack=6, Locals=5, Args_size=4
	aload_1
	ifnonnull	l1 // aload_0
	new	class java/lang/NullPointerException
	dup
	invokespecial	Method java/lang/NullPointerException."<init>":()V
	athrow
l1	aload_0
	aload_1
	iconst_1
	aload	4
	lload_2
	invokevirtual	Method java/util/concurrent/TimeUnit.toNanos:(J)J
	invokespecial	Method xfer:(Ljava/lang/Object;IJ)Ljava/lang/Object;
	ifnull	l2 // invokestatic
	iconst_1
	ireturn
l2	invokestatic	Method java/lang/Thread.interrupted:()Z
	ifne	l3 // new
	iconst_0
	ireturn
l3	new	class java/lang/InterruptedException
	dup
	invokespecial	Method java/lang/InterruptedException."<init>":()V
	athrow
  Labels:
   	l1 = 12 // aload_0
   	l2 = 29 // invokestatic
   	l3 = 37 // new
  Exceptions: 
   throws java.lang.InterruptedException  Signature: length = 0x2
   00 FFFFFF98 

public boolean tryTransfer(java.lang.Object);
  Signature: (Ljava/lang/Object;)Z
  Code:
   Stack=2, Locals=2, Args_size=2
	aload_1
	ifnonnull	l1 // aload_0
	new	class java/lang/NullPointerException
	dup
	invokespecial	Method java/lang/NullPointerException."<init>":()V
	athrow
l1	aload_0
	aload_1
	invokespecial	Method fulfill:(Ljava/lang/Object;)Ljava/lang/Object;
	ifnull	l2 // iconst_0
	iconst_1
	goto	l3 // ireturn
l2	iconst_0
l3	ireturn
  Labels:
   	l1 = 12 // aload_0
   	l2 = 24 // iconst_0
   	l3 = 25 // ireturn
  Signature: length = 0x2
   00 FFFFFF9A 

public java.lang.Object take()   throws java.lang.InterruptedException;
  Signature: ()Ljava/lang/Object;
  Code:
   Stack=5, Locals=2, Args_size=1
	aload_0
	aconst_null
	iconst_2
	lconst_0
	invokespecial	Method xfer:(Ljava/lang/Object;IJ)Ljava/lang/Object;
	astore_1
	aload_1
	ifnull	l1 // invokestatic
	aload_1
	areturn
l1	invokestatic	Method java/lang/Thread.interrupted:()Z
	pop
	new	class java/lang/InterruptedException
	dup
	invokespecial	Method java/lang/InterruptedException."<init>":()V
	athrow
  Labels:
   	l1 = 14 // invokestatic
  Exceptions: 
   throws java.lang.InterruptedException  Signature: length = 0x2
   00 FFFFFFA0 

public java.lang.Object poll(long, java.util.concurrent.TimeUnit)   throws java.lang.InterruptedException;
  Signature: (JLjava/util/concurrent/TimeUnit;)Ljava/lang/Object;
  Code:
   Stack=6, Locals=5, Args_size=3
	aload_0
	aconst_null
	iconst_1
	aload_3
	lload_1
	invokevirtual	Method java/util/concurrent/TimeUnit.toNanos:(J)J
	invokespecial	Method xfer:(Ljava/lang/Object;IJ)Ljava/lang/Object;
	astore	4
	aload	4
	ifnonnull	l1 // aload
	invokestatic	Method java/lang/Thread.interrupted:()Z
	ifne	l2 // new
l1	aload	4
	areturn
l2	new	class java/lang/InterruptedException
	dup
	invokespecial	Method java/lang/InterruptedException."<init>":()V
	athrow
  Labels:
   	l1 = 24 // aload
   	l2 = 27 // new
  Exceptions: 
   throws java.lang.InterruptedException  Signature: length = 0x2
   00 FFFFFFA3 

public java.lang.Object poll();
  Signature: ()Ljava/lang/Object;
  Code:
   Stack=2, Locals=1, Args_size=1
	aload_0
	aconst_null
	invokespecial	Method fulfill:(Ljava/lang/Object;)Ljava/lang/Object;
	areturn
  Labels:
  Signature: length = 0x2
   00 FFFFFFA0 

public int drainTo(java.util.Collection);
  Signature: (Ljava/util/Collection;)I
  Code:
   Stack=2, Locals=4, Args_size=2
	aload_1
	ifnonnull	l1 // aload_1
	new	class java/lang/NullPointerException
	dup
	invokespecial	Method java/lang/NullPointerException."<init>":()V
	athrow
l1	aload_1
	aload_0
	if_acmpne	l2 // iconst_0
	new	class java/lang/IllegalArgumentException
	dup
	invokespecial	Method java/lang/IllegalArgumentException."<init>":()V
	athrow
l2	iconst_0
	istore_2
l4	aload_0
	invokevirtual	Method poll:()Ljava/lang/Object;
	dup
	astore_3
	ifnull	l3 // iload_2
	aload_1
	aload_3
	invokeinterface	InterfaceMethod java/util/Collection.add:(Ljava/lang/Object;)Z
	pop
	iinc	2, 1
	goto	l4 // aload_0
l3	iload_2
	ireturn
  Labels:
   	l1 = 12 // aload_1
   	l2 = 25 // iconst_0
   	l4 = 27 // aload_0
   	l3 = 50 // iload_2
  Signature: length = 0x2
   00 FFFFFFA6 

public int drainTo(java.util.Collection, int);
  Signature: (Ljava/util/Collection;I)I
  Code:
   Stack=2, Locals=5, Args_size=3
	aload_1
	ifnonnull	l1 // aload_1
	new	class java/lang/NullPointerException
	dup
	invokespecial	Method java/lang/NullPointerException."<init>":()V
	athrow
l1	aload_1
	aload_0
	if_acmpne	l2 // iconst_0
	new	class java/lang/IllegalArgumentException
	dup
	invokespecial	Method java/lang/IllegalArgumentException."<init>":()V
	athrow
l2	iconst_0
	istore_3
l4	iload_3
	iload_2
	if_icmpge	l3 // iload_3
	aload_0
	invokevirtual	Method poll:()Ljava/lang/Object;
	dup
	astore	4
	ifnull	l3 // iload_3
	aload_1
	aload	4
	invokeinterface	InterfaceMethod java/util/Collection.add:(Ljava/lang/Object;)Z
	pop
	iinc	3, 1
	goto	l4 // iload_3
l3	iload_3
	ireturn
  Labels:
   	l1 = 12 // aload_1
   	l2 = 25 // iconst_0
   	l4 = 27 // iload_3
   	l3 = 57 // iload_3
  Signature: length = 0x2
   00 FFFFFFA8 

private scala.concurrent.forkjoin.LinkedTransferQueue$QNode traversalHead();
  Signature: ()Lscala/concurrent/forkjoin/LinkedTransferQueue$QNode;
  Code:
   Stack=3, Locals=6, Args_size=1
l6	aload_0
	getfield	Field tail:Lscala/concurrent/forkjoin/LinkedTransferQueue$PaddedAtomicReference;
	invokevirtual	Method scala/concurrent/forkjoin/LinkedTransferQueue$PaddedAtomicReference.get:()Ljava/lang/Object;
	checkcast	class scala/concurrent/forkjoin/LinkedTransferQueue$QNode
	astore_1
	aload_0
	getfield	Field head:Lscala/concurrent/forkjoin/LinkedTransferQueue$PaddedAtomicReference;
	invokevirtual	Method scala/concurrent/forkjoin/LinkedTransferQueue$PaddedAtomicReference.get:()Ljava/lang/Object;
	checkcast	class scala/concurrent/forkjoin/LinkedTransferQueue$QNode
	astore_2
	aload_2
	ifnull	l1 // aload_0
	aload_1
	ifnull	l1 // aload_0
	aload_1
	getfield	Field scala/concurrent/forkjoin/LinkedTransferQueue$QNode.next:Lscala/concurrent/forkjoin/LinkedTransferQueue$QNode;
	astore_3
	aload_2
	getfield	Field scala/concurrent/forkjoin/LinkedTransferQueue$QNode.next:Lscala/concurrent/forkjoin/LinkedTransferQueue$QNode;
	astore	4
	aload_1
	aload_0
	getfield	Field tail:Lscala/concurrent/forkjoin/LinkedTransferQueue$PaddedAtomicReference;
	invokevirtual	Method scala/concurrent/forkjoin/LinkedTransferQueue$PaddedAtomicReference.get:()Ljava/lang/Object;
	if_acmpne	l1 // aload_0
	aload_3
	ifnull	l2 // aload
	aload_0
	getfield	Field tail:Lscala/concurrent/forkjoin/LinkedTransferQueue$PaddedAtomicReference;
	aload_1
	aload_3
	invokevirtual	Method scala/concurrent/forkjoin/LinkedTransferQueue$PaddedAtomicReference.compareAndSet:(Ljava/lang/Object;Ljava/lang/Object;)Z
	pop
	goto	l1 // aload_0
l2	aload	4
	ifnull	l3 // aload_2
	aload	4
	invokevirtual	Method scala/concurrent/forkjoin/LinkedTransferQueue$QNode.get:()Ljava/lang/Object;
	astore	5
	aload	5
	aload	4
	if_acmpne	l4 // aload_2
	aload_0
	aload_2
	aload	4
	invokespecial	Method advanceHead:(Lscala/concurrent/forkjoin/LinkedTransferQueue$QNode;Lscala/concurrent/forkjoin/LinkedTransferQueue$QNode;)Z
	pop
	goto	l5 // goto
l4	aload_2
	areturn
l5	goto	l1 // aload_0
l3	aload_2
	areturn
l1	aload_0
	invokespecial	Method reclean:()Lscala/concurrent/forkjoin/LinkedTransferQueue$QNode;
	pop
	goto	l6 // aload_0
  Labels:
   	l6 = 0 // aload_0
   	l2 = 69 // aload
   	l4 = 99 // aload_2
   	l5 = 101 // goto
   	l3 = 104 // aload_2
   	l1 = 106 // aload_0

public java.util.Iterator iterator();
  Signature: ()Ljava/util/Iterator;
  Code:
   Stack=3, Locals=1, Args_size=1
	new	class scala/concurrent/forkjoin/LinkedTransferQueue$Itr
	dup
	aload_0
	invokespecial	Method scala/concurrent/forkjoin/LinkedTransferQueue$Itr."<init>":(Lscala/concurrent/forkjoin/LinkedTransferQueue;)V
	areturn
  Labels:
  Signature: length = 0x2
   00 FFFFFFAC 

public java.lang.Object peek();
  Signature: ()Ljava/lang/Object;
  Code:
   Stack=2, Locals=4, Args_size=1
l4	aload_0
	invokespecial	Method traversalHead:()Lscala/concurrent/forkjoin/LinkedTransferQueue$QNode;
	astore_1
	aload_1
	getfield	Field scala/concurrent/forkjoin/LinkedTransferQueue$QNode.next:Lscala/concurrent/forkjoin/LinkedTransferQueue$QNode;
	astore_2
	aload_2
	ifnonnull	l1 // aload_2
	aconst_null
	areturn
l1	aload_2
	invokevirtual	Method scala/concurrent/forkjoin/LinkedTransferQueue$QNode.get:()Ljava/lang/Object;
	astore_3
	aload_2
	aload_3
	if_acmpeq	l2 // goto
	aload_2
	getfield	Field scala/concurrent/forkjoin/LinkedTransferQueue$QNode.isData:Z
	ifne	l3 // aload_3
	aconst_null
	areturn
l3	aload_3
	ifnull	l2 // goto
	aload_3
	areturn
l2	goto	l4 // aload_0
  Labels:
   	l4 = 0 // aload_0
   	l1 = 16 // aload_2
   	l3 = 35 // aload_3
   	l2 = 41 // goto
  Signature: length = 0x2
   00 FFFFFFA0 

public boolean isEmpty();
  Signature: ()Z
  Code:
   Stack=2, Locals=4, Args_size=1
l4	aload_0
	invokespecial	Method traversalHead:()Lscala/concurrent/forkjoin/LinkedTransferQueue$QNode;
	astore_1
	aload_1
	getfield	Field scala/concurrent/forkjoin/LinkedTransferQueue$QNode.next:Lscala/concurrent/forkjoin/LinkedTransferQueue$QNode;
	astore_2
	aload_2
	ifnonnull	l1 // aload_2
	iconst_1
	ireturn
l1	aload_2
	invokevirtual	Method scala/concurrent/forkjoin/LinkedTransferQueue$QNode.get:()Ljava/lang/Object;
	astore_3
	aload_2
	aload_3
	if_acmpeq	l2 // goto
	aload_2
	getfield	Field scala/concurrent/forkjoin/LinkedTransferQueue$QNode.isData:Z
	ifne	l3 // aload_3
	iconst_1
	ireturn
l3	aload_3
	ifnull	l2 // goto
	iconst_0
	ireturn
l2	goto	l4 // aload_0
  Labels:
   	l4 = 0 // aload_0
   	l1 = 16 // aload_2
   	l3 = 35 // aload_3
   	l2 = 41 // goto

public boolean hasWaitingConsumer();
  Signature: ()Z
  Code:
   Stack=2, Locals=4, Args_size=1
l5	aload_0
	invokespecial	Method traversalHead:()Lscala/concurrent/forkjoin/LinkedTransferQueue$QNode;
	astore_1
	aload_1
	getfield	Field scala/concurrent/forkjoin/LinkedTransferQueue$QNode.next:Lscala/concurrent/forkjoin/LinkedTransferQueue$QNode;
	astore_2
	aload_2
	ifnonnull	l1 // aload_2
	iconst_0
	ireturn
l1	aload_2
	invokevirtual	Method scala/concurrent/forkjoin/LinkedTransferQueue$QNode.get:()Ljava/lang/Object;
	astore_3
	aload_2
	aload_3
	if_acmpeq	l2 // goto
	aload_2
	getfield	Field scala/concurrent/forkjoin/LinkedTransferQueue$QNode.isData:Z
	ifne	l3 // iconst_0
	iconst_1
	goto	l4 // ireturn
l3	iconst_0
l4	ireturn
l2	goto	l5 // aload_0
  Labels:
   	l5 = 0 // aload_0
   	l1 = 16 // aload_2
   	l3 = 37 // iconst_0
   	l4 = 38 // ireturn
   	l2 = 39 // goto

public int size();
  Signature: ()I
  Code:
   Stack=2, Locals=5, Args_size=1
	iconst_0
	istore_1
	aload_0
	invokespecial	Method traversalHead:()Lscala/concurrent/forkjoin/LinkedTransferQueue$QNode;
	astore_2
	aload_2
	getfield	Field scala/concurrent/forkjoin/LinkedTransferQueue$QNode.next:Lscala/concurrent/forkjoin/LinkedTransferQueue$QNode;
	astore_3
l3	aload_3
	ifnull	l1 // iload_1
	aload_3
	getfield	Field scala/concurrent/forkjoin/LinkedTransferQueue$QNode.isData:Z
	ifeq	l1 // iload_1
	aload_3
	invokevirtual	Method scala/concurrent/forkjoin/LinkedTransferQueue$QNode.get:()Ljava/lang/Object;
	astore	4
	aload	4
	ifnull	l2 // aload_3
	aload	4
	aload_3
	if_acmpeq	l2 // aload_3
	iinc	1, 1
	iload_1
	ldc	int 2147483647
	if_icmpne	l2 // aload_3
	goto	l1 // iload_1
l2	aload_3
	getfield	Field scala/concurrent/forkjoin/LinkedTransferQueue$QNode.next:Lscala/concurrent/forkjoin/LinkedTransferQueue$QNode;
	astore_3
	goto	l3 // aload_3
l1	iload_1
	ireturn
  Labels:
   	l3 = 12 // aload_3
   	l2 = 52 // aload_3
   	l1 = 60 // iload_1

public int getWaitingConsumerCount();
  Signature: ()I
  Code:
   Stack=2, Locals=4, Args_size=1
	iconst_0
	istore_1
	aload_0
	invokespecial	Method traversalHead:()Lscala/concurrent/forkjoin/LinkedTransferQueue$QNode;
	astore_2
	aload_2
	getfield	Field scala/concurrent/forkjoin/LinkedTransferQueue$QNode.next:Lscala/concurrent/forkjoin/LinkedTransferQueue$QNode;
	astore_3
l3	aload_3
	ifnull	l1 // iload_1
	aload_3
	getfield	Field scala/concurrent/forkjoin/LinkedTransferQueue$QNode.isData:Z
	ifne	l1 // iload_1
	aload_3
	invokevirtual	Method scala/concurrent/forkjoin/LinkedTransferQueue$QNode.get:()Ljava/lang/Object;
	ifnonnull	l2 // aload_3
	iinc	1, 1
	iload_1
	ldc	int 2147483647
	if_icmpne	l2 // aload_3
	goto	l1 // iload_1
l2	aload_3
	getfield	Field scala/concurrent/forkjoin/LinkedTransferQueue$QNode.next:Lscala/concurrent/forkjoin/LinkedTransferQueue$QNode;
	astore_3
	goto	l3 // aload_3
l1	iload_1
	ireturn
  Labels:
   	l3 = 12 // aload_3
   	l2 = 42 // aload_3
   	l1 = 50 // iload_1

public int remainingCapacity();
  Signature: ()I
  Code:
   Stack=1, Locals=1, Args_size=1
	ldc	int 2147483647
	ireturn
  Labels:

public boolean remove(java.lang.Object);
  Signature: (Ljava/lang/Object;)Z
  Code:
   Stack=3, Locals=5, Args_size=2
	aload_1
	ifnonnull	l1 // aload_0
	iconst_0
	ireturn
l1	aload_0
	invokespecial	Method traversalHead:()Lscala/concurrent/forkjoin/LinkedTransferQueue$QNode;
	astore_2
l7	aload_2
	getfield	Field scala/concurrent/forkjoin/LinkedTransferQueue$QNode.next:Lscala/concurrent/forkjoin/LinkedTransferQueue$QNode;
	astore_3
	aload_3
	ifnull	l2 // iconst_0
	aload_3
	getfield	Field scala/concurrent/forkjoin/LinkedTransferQueue$QNode.isData:Z
	ifne	l3 // aload_3
l2	iconst_0
	ireturn
l3	aload_3
	aload_2
	if_acmpne	l4 // aload_3
	goto	l5 // goto
l4	aload_3
	invokevirtual	Method scala/concurrent/forkjoin/LinkedTransferQueue$QNode.get:()Ljava/lang/Object;
	astore	4
	aload	4
	ifnull	l6 // aload_3
	aload	4
	aload_3
	if_acmpeq	l6 // aload_3
	aload_1
	aload	4
	invokevirtual	Method java/lang/Object.equals:(Ljava/lang/Object;)Z
	ifeq	l6 // aload_3
	aload_3
	aload	4
	aload_3
	invokevirtual	Method scala/concurrent/forkjoin/LinkedTransferQueue$QNode.compareAndSet:(Ljava/lang/Object;Ljava/lang/Object;)Z
	ifeq	l6 // aload_3
	aload_0
	aload_2
	aload_3
	invokespecial	Method clean:(Lscala/concurrent/forkjoin/LinkedTransferQueue$QNode;Lscala/concurrent/forkjoin/LinkedTransferQueue$QNode;)V
	iconst_1
	ireturn
l6	aload_3
	astore_2
	goto	l7 // aload_2
l5	goto	l1 // aload_0
  Labels:
   	l1 = 6 // aload_0
   	l7 = 11 // aload_2
   	l2 = 27 // iconst_0
   	l3 = 29 // aload_3
   	l4 = 37 // aload_3
   	l6 = 81 // aload_3
   	l5 = 86 // goto

private void writeObject(java.io.ObjectOutputStream)   throws java.io.IOException;
  Signature: (Ljava/io/ObjectOutputStream;)V
  Code:
   Stack=2, Locals=4, Args_size=2
	aload_1
	invokevirtual	Method java/io/ObjectOutputStream.defaultWriteObject:()V
	aload_0
	invokevirtual	Method iterator:()Ljava/util/Iterator;
	astore_2
l2	aload_2
	invokeinterface	InterfaceMethod java/util/Iterator.hasNext:()Z
	ifeq	l1 // aload_1
	aload_2
	invokeinterface	InterfaceMethod java/util/Iterator.next:()Ljava/lang/Object;
	astore_3
	aload_1
	aload_3
	invokevirtual	Method java/io/ObjectOutputStream.writeObject:(Ljava/lang/Object;)V
	goto	l2 // aload_2
l1	aload_1
	aconst_null
	invokevirtual	Method java/io/ObjectOutputStream.writeObject:(Ljava/lang/Object;)V
	return
  Labels:
   	l2 = 9 // aload_2
   	l1 = 33 // aload_1
  Exceptions: 
   throws java.io.IOException
private void readObject(java.io.ObjectInputStream)   throws java.io.IOException, java.lang.ClassNotFoundException;
  Signature: (Ljava/io/ObjectInputStream;)V
  Code:
   Stack=2, Locals=3, Args_size=2
	aload_1
	invokevirtual	Method java/io/ObjectInputStream.defaultReadObject:()V
	aload_0
	invokespecial	Method resetHeadAndTail:()V
l3	aload_1
	invokevirtual	Method java/io/ObjectInputStream.readObject:()Ljava/lang/Object;
	astore_2
	aload_2
	ifnonnull	l1 // aload_0
	goto	l2 // return
l1	aload_0
	aload_2
	invokevirtual	Method offer:(Ljava/lang/Object;)Z
	pop
	goto	l3 // aload_1
l2	return
  Labels:
   	l3 = 8 // aload_1
   	l1 = 20 // aload_0
   	l2 = 29 // return
  Exceptions: 
   throws java.io.IOException, java.lang.ClassNotFoundException
private void resetHeadAndTail();
  Signature: ()V
  Code:
   Stack=7, Locals=2, Args_size=1
	new	class scala/concurrent/forkjoin/LinkedTransferQueue$QNode
	dup
	aconst_null
	iconst_0
	invokespecial	Method scala/concurrent/forkjoin/LinkedTransferQueue$QNode."<init>":(Ljava/lang/Object;Z)V
	astore_1
	getstatic	Field _unsafe:Lsun/misc/Unsafe;
	aload_0
	getstatic	Field headOffset:J
	new	class scala/concurrent/forkjoin/LinkedTransferQueue$PaddedAtomicReference
	dup
	aload_1
	invokespecial	Method scala/concurrent/forkjoin/LinkedTransferQueue$PaddedAtomicReference."<init>":(Ljava/lang/Object;)V
	invokevirtual	Method sun/misc/Unsafe.putObjectVolatile:(Ljava/lang/Object;JLjava/lang/Object;)V
	getstatic	Field _unsafe:Lsun/misc/Unsafe;
	aload_0
	getstatic	Field tailOffset:J
	new	class scala/concurrent/forkjoin/LinkedTransferQueue$PaddedAtomicReference
	dup
	aload_1
	invokespecial	Method scala/concurrent/forkjoin/LinkedTransferQueue$PaddedAtomicReference."<init>":(Ljava/lang/Object;)V
	invokevirtual	Method sun/misc/Unsafe.putObjectVolatile:(Ljava/lang/Object;JLjava/lang/Object;)V
	getstatic	Field _unsafe:Lsun/misc/Unsafe;
	aload_0
	getstatic	Field cleanMeOffset:J
	new	class scala/concurrent/forkjoin/LinkedTransferQueue$PaddedAtomicReference
	dup
	aconst_null
	invokespecial	Method scala/concurrent/forkjoin/LinkedTransferQueue$PaddedAtomicReference."<init>":(Ljava/lang/Object;)V
	invokevirtual	Method sun/misc/Unsafe.putObjectVolatile:(Ljava/lang/Object;JLjava/lang/Object;)V
	return
  Labels:

private static sun.misc.Unsafe getUnsafe()   throws java.lang.Throwable;
  Signature: ()Lsun/misc/Unsafe;
  Code:
   Stack=2, Locals=2, Args_size=0
	invokestatic	Method sun/misc/Unsafe.getUnsafe:()Lsun/misc/Unsafe;
	areturn
	astore_0
	new	class scala/concurrent/forkjoin/LinkedTransferQueue$1
	dup
	invokespecial	Method scala/concurrent/forkjoin/LinkedTransferQueue$1."<init>":()V
	invokestatic	Method java/security/AccessController.doPrivileged:(Ljava/security/PrivilegedExceptionAction;)Ljava/lang/Object;
	checkcast	class sun/misc/Unsafe
	areturn
	astore_1
	aload_1
	invokevirtual	Method java/security/PrivilegedActionException.getCause:()Ljava/lang/Throwable;
	athrow
  Labels:
  Exception table:
   from   to  target type
     0     3     4   Class java/lang/SecurityException

     5    18    19   Class java/security/PrivilegedActionException

  Exceptions: 
   throws java.lang.Throwable
private static sun.misc.Unsafe getUnsafePrivileged()   throws java.lang.NoSuchFieldException, java.lang.IllegalAccessException;
  Signature: ()Lsun/misc/Unsafe;
  Code:
   Stack=2, Locals=1, Args_size=0
	ldc_w	class sun/misc/Unsafe
	ldc	String theUnsafe
	invokevirtual	Method java/lang/Class.getDeclaredField:(Ljava/lang/String;)Ljava/lang/reflect/Field;
	astore_0
	aload_0
	iconst_1
	invokevirtual	Method java/lang/reflect/Field.setAccessible:(Z)V
	aload_0
	aconst_null
	invokevirtual	Method java/lang/reflect/Field.get:(Ljava/lang/Object;)Ljava/lang/Object;
	checkcast	class sun/misc/Unsafe
	areturn
  Labels:
  Exceptions: 
   throws java.lang.NoSuchFieldException, java.lang.IllegalAccessException
private static long fieldOffset(java.lang.String)   throws java.lang.NoSuchFieldException;
  Signature: (Ljava/lang/String;)J
  Code:
   Stack=3, Locals=1, Args_size=1
	getstatic	Field _unsafe:Lsun/misc/Unsafe;
	ldc_w	class scala/concurrent/forkjoin/LinkedTransferQueue
	aload_0
	invokevirtual	Method java/lang/Class.getDeclaredField:(Ljava/lang/String;)Ljava/lang/reflect/Field;
	invokevirtual	Method sun/misc/Unsafe.objectFieldOffset:(Ljava/lang/reflect/Field;)J
	lreturn
  Labels:
  Exceptions: 
   throws java.lang.NoSuchFieldException
static scala.concurrent.forkjoin.LinkedTransferQueue$QNode access$000(scala.concurrent.forkjoin.LinkedTransferQueue);
  Signature: (Lscala/concurrent/forkjoin/LinkedTransferQueue;)Lscala/concurrent/forkjoin/LinkedTransferQueue$QNode;
  Code:
   Stack=1, Locals=1, Args_size=1
	aload_0
	invokespecial	Method traversalHead:()Lscala/concurrent/forkjoin/LinkedTransferQueue$QNode;
	areturn
  Labels:

static void access$100(scala.concurrent.forkjoin.LinkedTransferQueue, scala.concurrent.forkjoin.LinkedTransferQueue$QNode, scala.concurrent.forkjoin.LinkedTransferQueue$QNode);
  Signature: (Lscala/concurrent/forkjoin/LinkedTransferQueue;Lscala/concurrent/forkjoin/LinkedTransferQueue$QNode;Lscala/concurrent/forkjoin/LinkedTransferQueue$QNode;)V
  Code:
   Stack=3, Locals=3, Args_size=3
	aload_0
	aload_1
	aload_2
	invokespecial	Method clean:(Lscala/concurrent/forkjoin/LinkedTransferQueue$QNode;Lscala/concurrent/forkjoin/LinkedTransferQueue$QNode;)V
	return
  Labels:

static sun.misc.Unsafe access$200()   throws java.lang.NoSuchFieldException, java.lang.IllegalAccessException;
  Signature: ()Lsun/misc/Unsafe;
  Code:
   Stack=1, Locals=0, Args_size=0
	invokestatic	Method getUnsafePrivileged:()Lsun/misc/Unsafe;
	areturn
  Labels:
  Exceptions: 
   throws java.lang.NoSuchFieldException, java.lang.IllegalAccessException
static {};
  Signature: ()V
  Code:
   Stack=4, Locals=1, Args_size=0
	invokestatic	Method java/lang/Runtime.getRuntime:()Ljava/lang/Runtime;
	invokevirtual	Method java/lang/Runtime.availableProcessors:()I
	putstatic	Field NCPUS:I
	getstatic	Field NCPUS:I
	iconst_2
	if_icmpge	l1 // bipush
	iconst_0
	goto	l2 // putstatic
l1	bipush	32
l2	putstatic	Field maxTimedSpins:I
	getstatic	Field maxTimedSpins:I
	bipush	16
	imul
	putstatic	Field maxUntimedSpins:I
	invokestatic	Method getUnsafe:()Lsun/misc/Unsafe;
	putstatic	Field _unsafe:Lsun/misc/Unsafe;
	ldc	String head
	invokestatic	Method fieldOffset:(Ljava/lang/String;)J
	putstatic	Field headOffset:J
	ldc	String tail
	invokestatic	Method fieldOffset:(Ljava/lang/String;)J
	putstatic	Field tailOffset:J
	ldc	String cleanMe
	invokestatic	Method fieldOffset:(Ljava/lang/String;)J
	putstatic	Field cleanMeOffset:J
	goto	l3 // return
	astore_0
	new	class java/lang/RuntimeException
	dup
	ldc	String Could not initialize intrinsics
	aload_0
	invokespecial	Method java/lang/RuntimeException."<init>":(Ljava/lang/String;Ljava/lang/Throwable;)V
	athrow
l3	return
  Labels:
   	l1 = 20 // bipush
   	l2 = 22 // putstatic
   	l3 = 79 // return
  Exception table:
   from   to  target type
    34    64    67   Class java/lang/Throwable


}

