Compiled from "LinkedTransferQueue.java"
final class scala.concurrent.forkjoin.LinkedTransferQueue$QNode extends java.util.concurrent.atomic.AtomicReference
  Signature: length = 0x2
   00 25 
  SourceFile: "LinkedTransferQueue.java"
  InnerClass: 
   final #11= #6 of #46; //QNode=class scala/concurrent/forkjoin/LinkedTransferQueue$QNode of class scala/concurrent/forkjoin/LinkedTransferQueue
  minor version: 0
  major version: 49
  Constant pool:
const #1 = Method	#9.#40;	//  java/util/concurrent/atomic/AtomicReference."<init>":(Ljava/lang/Object;)V
const #2 = Field	#6.#41;	//  scala/concurrent/forkjoin/LinkedTransferQueue$QNode.isData:Z
const #3 = Field	#6.#42;	//  scala/concurrent/forkjoin/LinkedTransferQueue$QNode.nextUpdater:Ljava/util/concurrent/atomic/AtomicReferenceFieldUpdater;
const #4 = Method	#43.#44;	//  java/util/concurrent/atomic/AtomicReferenceFieldUpdater.compareAndSet:(Ljava/lang/Object;Ljava/lang/Object;Ljava/lang/Object;)Z
const #5 = Method	#43.#45;	//  java/util/concurrent/atomic/AtomicReferenceFieldUpdater.lazySet:(Ljava/lang/Object;Ljava/lang/Object;)V
const #6 = class	#47;	//  scala/concurrent/forkjoin/LinkedTransferQueue$QNode
const #7 = String	#10;	//  next
const #8 = Method	#43.#48;	//  java/util/concurrent/atomic/AtomicReferenceFieldUpdater.newUpdater:(Ljava/lang/Class;Ljava/lang/Class;Ljava/lang/String;)Ljava/util/concurrent/atomic/AtomicReferenceFieldUpdater;
const #9 = class	#49;	//  java/util/concurrent/atomic/AtomicReference
const #10 = Asciz	next;
const #11 = Asciz	QNode;
const #12 = Asciz	InnerClasses;
const #13 = Asciz	Lscala/concurrent/forkjoin/LinkedTransferQueue$QNode;;
const #14 = Asciz	waiter;
const #15 = Asciz	Ljava/lang/Thread;;
const #16 = Asciz	isData;
const #17 = Asciz	Z;
const #18 = Asciz	nextUpdater;
const #19 = Asciz	Ljava/util/concurrent/atomic/AtomicReferenceFieldUpdater;;
const #20 = Asciz	Signature;
const #21 = Asciz	Ljava/util/concurrent/atomic/AtomicReferenceFieldUpdater<Lscala/concurrent/forkjoin/LinkedTransferQueue$QNode;Lscala/concurrent/forkjoin/LinkedTransferQueue$QNode;>;;
const #22 = Asciz	<init>;
const #23 = Asciz	(Ljava/lang/Object;Z)V;
const #24 = Asciz	Code;
const #25 = Asciz	LineNumberTable;
const #26 = Asciz	LocalVariableTable;
const #27 = Asciz	this;
const #28 = Asciz	item;
const #29 = Asciz	Ljava/lang/Object;;
const #30 = Asciz	casNext;
const #31 = Asciz	(Lscala/concurrent/forkjoin/LinkedTransferQueue$QNode;Lscala/concurrent/forkjoin/LinkedTransferQueue$QNode;)Z;
const #32 = Asciz	cmp;
const #33 = Asciz	val;
const #34 = Asciz	clearNext;
const #35 = Asciz	()V;
const #36 = Asciz	<clinit>;
const #37 = Asciz	Ljava/util/concurrent/atomic/AtomicReference<Ljava/lang/Object;>;;
const #38 = Asciz	SourceFile;
const #39 = Asciz	LinkedTransferQueue.java;
const #40 = NameAndType	#22:#50;//  "<init>":(Ljava/lang/Object;)V
const #41 = NameAndType	#16:#17;//  isData:Z
const #42 = NameAndType	#18:#19;//  nextUpdater:Ljava/util/concurrent/atomic/AtomicReferenceFieldUpdater;
const #43 = class	#51;	//  java/util/concurrent/atomic/AtomicReferenceFieldUpdater
const #44 = NameAndType	#52:#53;//  compareAndSet:(Ljava/lang/Object;Ljava/lang/Object;Ljava/lang/Object;)Z
const #45 = NameAndType	#54:#55;//  lazySet:(Ljava/lang/Object;Ljava/lang/Object;)V
const #46 = class	#56;	//  scala/concurrent/forkjoin/LinkedTransferQueue
const #47 = Asciz	scala/concurrent/forkjoin/LinkedTransferQueue$QNode;
const #48 = NameAndType	#57:#58;//  newUpdater:(Ljava/lang/Class;Ljava/lang/Class;Ljava/lang/String;)Ljava/util/concurrent/atomic/AtomicReferenceFieldUpdater;
const #49 = Asciz	java/util/concurrent/atomic/AtomicReference;
const #50 = Asciz	(Ljava/lang/Object;)V;
const #51 = Asciz	java/util/concurrent/atomic/AtomicReferenceFieldUpdater;
const #52 = Asciz	compareAndSet;
const #53 = Asciz	(Ljava/lang/Object;Ljava/lang/Object;Ljava/lang/Object;)Z;
const #54 = Asciz	lazySet;
const #55 = Asciz	(Ljava/lang/Object;Ljava/lang/Object;)V;
const #56 = Asciz	scala/concurrent/forkjoin/LinkedTransferQueue;
const #57 = Asciz	newUpdater;
const #58 = Asciz	(Ljava/lang/Class;Ljava/lang/Class;Ljava/lang/String;)Ljava/util/concurrent/atomic/AtomicReferenceFieldUpdater;;

{
volatile scala.concurrent.forkjoin.LinkedTransferQueue$QNode next;

volatile java.lang.Thread waiter;

final boolean isData;

static final java.util.concurrent.atomic.AtomicReferenceFieldUpdater nextUpdater;
  Signature: length = 0x2
   00 15 

scala.concurrent.forkjoin.LinkedTransferQueue$QNode(java.lang.Object, boolean);
  Code:
   Stack=2, Locals=3, Args_size=3
   0:	aload_0
   1:	aload_1
   2:	invokespecial	#1; //Method java/util/concurrent/atomic/AtomicReference."<init>":(Ljava/lang/Object;)V
   5:	aload_0
   6:	iload_2
   7:	putfield	#2; //Field isData:Z
   10:	return
  LineNumberTable: 
   line 111: 0
   line 112: 5
   line 113: 10

  LocalVariableTable: 
   Start  Length  Slot  Name   Signature
   0      11      0    this       Lscala/concurrent/forkjoin/LinkedTransferQueue$QNode;
   0      11      1    item       Ljava/lang/Object;
   0      11      2    isData       Z


final boolean casNext(scala.concurrent.forkjoin.LinkedTransferQueue$QNode, scala.concurrent.forkjoin.LinkedTransferQueue$QNode);
  Code:
   Stack=4, Locals=3, Args_size=3
   0:	getstatic	#3; //Field nextUpdater:Ljava/util/concurrent/atomic/AtomicReferenceFieldUpdater;
   3:	aload_0
   4:	aload_1
   5:	aload_2
   6:	invokevirtual	#4; //Method java/util/concurrent/atomic/AtomicReferenceFieldUpdater.compareAndSet:(Ljava/lang/Object;Ljava/lang/Object;Ljava/lang/Object;)Z
   9:	ireturn
  LineNumberTable: 
   line 120: 0

  LocalVariableTable: 
   Start  Length  Slot  Name   Signature
   0      10      0    this       Lscala/concurrent/forkjoin/LinkedTransferQueue$QNode;
   0      10      1    cmp       Lscala/concurrent/forkjoin/LinkedTransferQueue$QNode;
   0      10      2    val       Lscala/concurrent/forkjoin/LinkedTransferQueue$QNode;


final void clearNext();
  Code:
   Stack=3, Locals=1, Args_size=1
   0:	getstatic	#3; //Field nextUpdater:Ljava/util/concurrent/atomic/AtomicReferenceFieldUpdater;
   3:	aload_0
   4:	aload_0
   5:	invokevirtual	#5; //Method java/util/concurrent/atomic/AtomicReferenceFieldUpdater.lazySet:(Ljava/lang/Object;Ljava/lang/Object;)V
   8:	return
  LineNumberTable: 
   line 124: 0
   line 125: 8

  LocalVariableTable: 
   Start  Length  Slot  Name   Signature
   0      9      0    this       Lscala/concurrent/forkjoin/LinkedTransferQueue$QNode;


static {};
  Code:
   Stack=3, Locals=0, Args_size=0
   0:	ldc_w	#6; //class scala/concurrent/forkjoin/LinkedTransferQueue$QNode
   3:	ldc_w	#6; //class scala/concurrent/forkjoin/LinkedTransferQueue$QNode
   6:	ldc	#7; //String next
   8:	invokestatic	#8; //Method java/util/concurrent/atomic/AtomicReferenceFieldUpdater.newUpdater:(Ljava/lang/Class;Ljava/lang/Class;Ljava/lang/String;)Ljava/util/concurrent/atomic/AtomicReferenceFieldUpdater;
   11:	putstatic	#3; //Field nextUpdater:Ljava/util/concurrent/atomic/AtomicReferenceFieldUpdater;
   14:	return
  LineNumberTable: 
   line 116: 0


}

