final class scala.concurrent.forkjoin.LinkedTransferQueue$QNode extends java.util.concurrent.atomic.AtomicReference
  Signature: length = 0x2
   00 1E 
  InnerClass: 
   final QNode=class scala/concurrent/forkjoin/LinkedTransferQueue$QNode of class scala/concurrent/forkjoin/LinkedTransferQueue
  minor version: 0
  major version: 49
  Constant pool:
Method	java/util/concurrent/atomic/AtomicReference."<init>":(Ljava/lang/Object;)V
Field	scala/concurrent/forkjoin/LinkedTransferQueue$QNode.isData:Z
Field	scala/concurrent/forkjoin/LinkedTransferQueue$QNode.nextUpdater:Ljava/util/concurrent/atomic/AtomicReferenceFieldUpdater;
Method	java/util/concurrent/atomic/AtomicReferenceFieldUpdater.compareAndSet:(Ljava/lang/Object;Ljava/lang/Object;Ljava/lang/Object;)Z
Method	java/util/concurrent/atomic/AtomicReferenceFieldUpdater.lazySet:(Ljava/lang/Object;Ljava/lang/Object;)V
class	scala/concurrent/forkjoin/LinkedTransferQueue$QNode
String	next
Method	java/util/concurrent/atomic/AtomicReferenceFieldUpdater.newUpdater:(Ljava/lang/Class;Ljava/lang/Class;Ljava/lang/String;)Ljava/util/concurrent/atomic/AtomicReferenceFieldUpdater;
class	java/util/concurrent/atomic/AtomicReference
Asciz	next;
Asciz	QNode;
Asciz	InnerClasses;
Asciz	Lscala/concurrent/forkjoin/LinkedTransferQueue$QNode;;
Asciz	waiter;
Asciz	Ljava/lang/Thread;;
Asciz	isData;
Asciz	Z;
Asciz	nextUpdater;
Asciz	Ljava/util/concurrent/atomic/AtomicReferenceFieldUpdater;;
Asciz	Signature;
Asciz	Ljava/util/concurrent/atomic/AtomicReferenceFieldUpdater<Lscala/concurrent/forkjoin/LinkedTransferQueue$QNode;Lscala/concurrent/forkjoin/LinkedTransferQueue$QNode;>;;
Asciz	<init>;
Asciz	(Ljava/lang/Object;Z)V;
Asciz	Code;
Asciz	casNext;
Asciz	(Lscala/concurrent/forkjoin/LinkedTransferQueue$QNode;Lscala/concurrent/forkjoin/LinkedTransferQueue$QNode;)Z;
Asciz	clearNext;
Asciz	()V;
Asciz	<clinit>;
Asciz	Ljava/util/concurrent/atomic/AtomicReference<Ljava/lang/Object;>;;
NameAndType	"<init>":(Ljava/lang/Object;)V
NameAndType	isData:Z
NameAndType	nextUpdater:Ljava/util/concurrent/atomic/AtomicReferenceFieldUpdater;
class	java/util/concurrent/atomic/AtomicReferenceFieldUpdater
NameAndType	compareAndSet:(Ljava/lang/Object;Ljava/lang/Object;Ljava/lang/Object;)Z
NameAndType	lazySet:(Ljava/lang/Object;Ljava/lang/Object;)V
class	scala/concurrent/forkjoin/LinkedTransferQueue
Asciz	scala/concurrent/forkjoin/LinkedTransferQueue$QNode;
NameAndType	newUpdater:(Ljava/lang/Class;Ljava/lang/Class;Ljava/lang/String;)Ljava/util/concurrent/atomic/AtomicReferenceFieldUpdater;
Asciz	java/util/concurrent/atomic/AtomicReference;
Asciz	(Ljava/lang/Object;)V;
Asciz	java/util/concurrent/atomic/AtomicReferenceFieldUpdater;
Asciz	compareAndSet;
Asciz	(Ljava/lang/Object;Ljava/lang/Object;Ljava/lang/Object;)Z;
Asciz	lazySet;
Asciz	(Ljava/lang/Object;Ljava/lang/Object;)V;
Asciz	scala/concurrent/forkjoin/LinkedTransferQueue;
Asciz	newUpdater;
Asciz	(Ljava/lang/Class;Ljava/lang/Class;Ljava/lang/String;)Ljava/util/concurrent/atomic/AtomicReferenceFieldUpdater;;

{
volatile scala.concurrent.forkjoin.LinkedTransferQueue$QNode next;
  Signature: Lscala/concurrent/forkjoin/LinkedTransferQueue$QNode;

volatile java.lang.Thread waiter;
  Signature: Ljava/lang/Thread;

final boolean isData;
  Signature: Z

static final java.util.concurrent.atomic.AtomicReferenceFieldUpdater nextUpdater;
  Signature: Ljava/util/concurrent/atomic/AtomicReferenceFieldUpdater;
  Signature: length = 0x2
   00 15 

scala.concurrent.forkjoin.LinkedTransferQueue$QNode(java.lang.Object, boolean);
  Signature: (Ljava/lang/Object;Z)V
  Code:
   Stack=2, Locals=3, Args_size=3
	aload_0
	aload_1
	invokespecial	Method java/util/concurrent/atomic/AtomicReference."<init>":(Ljava/lang/Object;)V
	aload_0
	iload_2
	putfield	Field isData:Z
	return
  Labels:

final boolean casNext(scala.concurrent.forkjoin.LinkedTransferQueue$QNode, scala.concurrent.forkjoin.LinkedTransferQueue$QNode);
  Signature: (Lscala/concurrent/forkjoin/LinkedTransferQueue$QNode;Lscala/concurrent/forkjoin/LinkedTransferQueue$QNode;)Z
  Code:
   Stack=4, Locals=3, Args_size=3
	getstatic	Field nextUpdater:Ljava/util/concurrent/atomic/AtomicReferenceFieldUpdater;
	aload_0
	aload_1
	aload_2
	invokevirtual	Method java/util/concurrent/atomic/AtomicReferenceFieldUpdater.compareAndSet:(Ljava/lang/Object;Ljava/lang/Object;Ljava/lang/Object;)Z
	ireturn
  Labels:

final void clearNext();
  Signature: ()V
  Code:
   Stack=3, Locals=1, Args_size=1
	getstatic	Field nextUpdater:Ljava/util/concurrent/atomic/AtomicReferenceFieldUpdater;
	aload_0
	aload_0
	invokevirtual	Method java/util/concurrent/atomic/AtomicReferenceFieldUpdater.lazySet:(Ljava/lang/Object;Ljava/lang/Object;)V
	return
  Labels:

static {};
  Signature: ()V
  Code:
   Stack=3, Locals=0, Args_size=0
	ldc_w	class scala/concurrent/forkjoin/LinkedTransferQueue$QNode
	ldc_w	class scala/concurrent/forkjoin/LinkedTransferQueue$QNode
	ldc	String next
	invokestatic	Method java/util/concurrent/atomic/AtomicReferenceFieldUpdater.newUpdater:(Ljava/lang/Class;Ljava/lang/Class;Ljava/lang/String;)Ljava/util/concurrent/atomic/AtomicReferenceFieldUpdater;
	putstatic	Field nextUpdater:Ljava/util/concurrent/atomic/AtomicReferenceFieldUpdater;
	return
  Labels:

}

