Compiled from "RecursiveAction.java"
public abstract class scala.concurrent.forkjoin.RecursiveAction extends scala.concurrent.forkjoin.ForkJoinTask
  Signature: length = 0x2
   00 1D 
  SourceFile: "RecursiveAction.java"
  minor version: 0
  major version: 49
  Constant pool:
const #1 = Method	#7.#32;	//  scala/concurrent/forkjoin/ForkJoinTask."<init>":()V
const #2 = Method	#6.#33;	//  scala/concurrent/forkjoin/RecursiveAction.compute:()V
const #3 = class	#34;	//  java/lang/Void
const #4 = Method	#6.#35;	//  scala/concurrent/forkjoin/RecursiveAction.setRawResult:(Ljava/lang/Void;)V
const #5 = Method	#6.#36;	//  scala/concurrent/forkjoin/RecursiveAction.getRawResult:()Ljava/lang/Void;
const #6 = class	#37;	//  scala/concurrent/forkjoin/RecursiveAction
const #7 = class	#38;	//  scala/concurrent/forkjoin/ForkJoinTask
const #8 = Asciz	<init>;
const #9 = Asciz	()V;
const #10 = Asciz	Code;
const #11 = Asciz	LineNumberTable;
const #12 = Asciz	LocalVariableTable;
const #13 = Asciz	this;
const #14 = Asciz	Lscala/concurrent/forkjoin/RecursiveAction;;
const #15 = Asciz	compute;
const #16 = Asciz	getRawResult;
const #17 = Asciz	()Ljava/lang/Void;;
const #18 = Asciz	setRawResult;
const #19 = Asciz	(Ljava/lang/Void;)V;
const #20 = Asciz	mustBeNull;
const #21 = Asciz	Ljava/lang/Void;;
const #22 = Asciz	exec;
const #23 = Asciz	()Z;
const #24 = Asciz	(Ljava/lang/Object;)V;
const #25 = Asciz	x0;
const #26 = Asciz	Ljava/lang/Object;;
const #27 = Asciz	()Ljava/lang/Object;;
const #28 = Asciz	Signature;
const #29 = Asciz	Lscala/concurrent/forkjoin/ForkJoinTask<Ljava/lang/Void;>;;
const #30 = Asciz	SourceFile;
const #31 = Asciz	RecursiveAction.java;
const #32 = NameAndType	#8:#9;//  "<init>":()V
const #33 = NameAndType	#15:#9;//  compute:()V
const #34 = Asciz	java/lang/Void;
const #35 = NameAndType	#18:#19;//  setRawResult:(Ljava/lang/Void;)V
const #36 = NameAndType	#16:#17;//  getRawResult:()Ljava/lang/Void;
const #37 = Asciz	scala/concurrent/forkjoin/RecursiveAction;
const #38 = Asciz	scala/concurrent/forkjoin/ForkJoinTask;

{
public scala.concurrent.forkjoin.RecursiveAction();
  Code:
   Stack=1, Locals=1, Args_size=1
   0:	aload_0
   1:	invokespecial	#1; //Method scala/concurrent/forkjoin/ForkJoinTask."<init>":()V
   4:	return
  LineNumberTable: 
   line 126: 0

  LocalVariableTable: 
   Start  Length  Slot  Name   Signature
   0      5      0    this       Lscala/concurrent/forkjoin/RecursiveAction;


protected abstract void compute();

public final java.lang.Void getRawResult();
  Code:
   Stack=1, Locals=1, Args_size=1
   0:	aconst_null
   1:	areturn
  LineNumberTable: 
   line 136: 0

  LocalVariableTable: 
   Start  Length  Slot  Name   Signature
   0      2      0    this       Lscala/concurrent/forkjoin/RecursiveAction;


protected final void setRawResult(java.lang.Void);
  Code:
   Stack=0, Locals=2, Args_size=2
   0:	return
  LineNumberTable: 
   line 141: 0

  LocalVariableTable: 
   Start  Length  Slot  Name   Signature
   0      1      0    this       Lscala/concurrent/forkjoin/RecursiveAction;
   0      1      1    mustBeNull       Ljava/lang/Void;


protected final boolean exec();
  Code:
   Stack=1, Locals=1, Args_size=1
   0:	aload_0
   1:	invokevirtual	#2; //Method compute:()V
   4:	iconst_1
   5:	ireturn
  LineNumberTable: 
   line 147: 0
   line 148: 4

  LocalVariableTable: 
   Start  Length  Slot  Name   Signature
   0      6      0    this       Lscala/concurrent/forkjoin/RecursiveAction;


protected void setRawResult(java.lang.Object);
  Code:
   Stack=2, Locals=2, Args_size=2
   0:	aload_0
   1:	aload_1
   2:	checkcast	#3; //class java/lang/Void
   5:	invokevirtual	#4; //Method setRawResult:(Ljava/lang/Void;)V
   8:	return
  LineNumberTable: 
   line 126: 0

  LocalVariableTable: 
   Start  Length  Slot  Name   Signature
   0      9      0    this       Lscala/concurrent/forkjoin/RecursiveAction;
   0      9      1    x0       Ljava/lang/Object;


public java.lang.Object getRawResult();
  Code:
   Stack=1, Locals=1, Args_size=1
   0:	aload_0
   1:	invokevirtual	#5; //Method getRawResult:()Ljava/lang/Void;
   4:	areturn
  LineNumberTable: 
   line 126: 0

  LocalVariableTable: 
   Start  Length  Slot  Name   Signature
   0      5      0    this       Lscala/concurrent/forkjoin/RecursiveAction;


}

