Compiled from "Location.scala"
public final class scala.collection.script.End extends java.lang.Object
  SourceFile: "Location.scala"
  ScalaSig: length = 0x1D0
   05 00 48 07 05 01 02 FFFFFF88 42 09 01 03 45 6E 64 0A
   02 03 04 01 06 73 63 72 69 70 74 0A 02 05 06 01
   0A 63 6F 6C 6C 65 63 74 69 6F 6E 0A 01 07 01 05
   73 63 61 6C 61 03 00 10 02 0A 0B 0D 01 02 06 08
   0C 02 FFFFFF84 FFFFFF80 FFFFFF80 FFFFFF88 42 0D 02 03 45 6E 64 13 04 0B
   0E 11 15 10 02 0A 0F 09 02 10 02 02 08 4C 6F 63
   61 74 69 6F 6E 10 02 12 13 0D 01 06 09 02 14 06
   02 0B 53 63 61 6C 61 4F 62 6A 65 63 74 10 02 12
   16 09 02 17 06 02 07 50 72 6F 64 75 63 74 08 05
   19 0B FFFFFF84 00 1A 01 06 3C 69 6E 69 74 3E 14 01 09
   08 08 1C 0B FFFFFF84 FFFFFF80 FFFFFF80 FFFFFF84 22 1D 01 08 74 6F 53 74
   72 69 6E 67 14 01 1E 10 02 1F 24 0D 01 20 0A 02
   21 22 01 04 6C 61 6E 67 0A 01 23 01 04 6A 61 76
   61 09 02 25 20 02 06 53 74 72 69 6E 67 08 08 27
   0B FFFFFF84 FFFFFF80 FFFFFF80 FFFFFF84 20 28 01 0D 70 72 6F 64 75 63 74
   50 72 65 66 69 78 15 01 1E 08 08 2A 0B FFFFFF84 FFFFFF80 FFFFFF80
   FFFFFF84 20 2B 01 0C 70 72 6F 64 75 63 74 41 72 69 74
   79 15 01 2C 10 02 12 2D 09 02 2E 06 02 03 49 6E
   74 08 08 30 0B FFFFFF84 FFFFFF80 FFFFFF80 FFFFFF84 20 31 01 0E 70 72 6F
   64 75 63 74 45 6C 65 6D 65 6E 74 14 02 32 35 10
   02 12 33 09 02 34 06 02 03 41 6E 79 08 07 36 2F
   FFFFFF81 FFFFFF80 FFFFFFC0 00 2C 01 03 78 24 31 08 08 38 0B FFFFFF84 FFFFFF80
   FFFFFF80 FFFFFF84 20 39 01 08 63 61 6E 45 71 75 61 6C 14 02
   3A 3D 10 02 12 3B 09 02 3C 06 02 07 42 6F 6F 6C
   65 61 6E 08 07 36 37 FFFFFF81 FFFFFF80 FFFFFFC0 00 32 08 08 3F 0B
   FFFFFF84 FFFFFF80 FFFFFF80 FFFFFF84 08 40 01 0B 72 65 61 64 52 65 73 6F
   6C 76 65 14 01 41 10 02 1F 42 09 02 43 20 02 06
   4F 62 6A 65 63 74 28 02 0B 45 10 02 12 46 09 02
   47 06 02 0C 73 65 72 69 61 6C 69 7A 61 62 6C 65
   
  minor version: 0
  major version: 49
  Constant pool:
Asciz	SourceFile;
Asciz	Location.scala;
Asciz	productElements;
Asciz	()Lscala/collection/Iterator;;
Asciz	Code;
Asciz	scala/collection/script/End$;
class	scala/collection/script/End$
Asciz	MODULE$;
Asciz	Lscala/collection/script/End$;;
NameAndType	MODULE$:Lscala/collection/script/End$;
Field	scala/collection/script/End$.MODULE$:Lscala/collection/script/End$;
NameAndType	productElements:()Lscala/collection/Iterator;
Method	scala/collection/script/End$.productElements:()Lscala/collection/Iterator;
Asciz	Deprecated;
Asciz	productIterator;
NameAndType	productIterator:()Lscala/collection/Iterator;
Method	scala/collection/script/End$.productIterator:()Lscala/collection/Iterator;
Asciz	productElementName;
Asciz	(I)Ljava/lang/String;;
NameAndType	productElementName:(I)Ljava/lang/String;
Method	scala/collection/script/End$.productElementName:(I)Ljava/lang/String;
Asciz	canEqual;
Asciz	(Ljava/lang/Object;)Z;
NameAndType	canEqual:(Ljava/lang/Object;)Z
Method	scala/collection/script/End$.canEqual:(Ljava/lang/Object;)Z
Asciz	productElement;
Asciz	(I)Ljava/lang/Object;;
NameAndType	productElement:(I)Ljava/lang/Object;
Method	scala/collection/script/End$.productElement:(I)Ljava/lang/Object;
Asciz	productArity;
Asciz	()I;
NameAndType	productArity:()I
Method	scala/collection/script/End$.productArity:()I
Asciz	productPrefix;
Asciz	()Ljava/lang/String;;
NameAndType	productPrefix:()Ljava/lang/String;
Method	scala/collection/script/End$.productPrefix:()Ljava/lang/String;
Asciz	ScalaSig;
Asciz	scala/collection/script/End;
class	scala/collection/script/End
Asciz	java/lang/Object;
class	java/lang/Object

{
public static final scala.collection.Iterator productElements();
  Signature: ()Lscala/collection/Iterator;
  Code:
   Stack=1, Locals=0, Args_size=0
	getstatic	Field scala/collection/script/End$.MODULE$:Lscala/collection/script/End$;
	invokevirtual	Method scala/collection/script/End$.productElements:()Lscala/collection/Iterator;
	areturn
  Labels:
  Deprecated: true

public static final scala.collection.Iterator productIterator();
  Signature: ()Lscala/collection/Iterator;
  Code:
   Stack=1, Locals=0, Args_size=0
	getstatic	Field scala/collection/script/End$.MODULE$:Lscala/collection/script/End$;
	invokevirtual	Method scala/collection/script/End$.productIterator:()Lscala/collection/Iterator;
	areturn
  Labels:

public static final java.lang.String productElementName(int);
  Signature: (I)Ljava/lang/String;
  Code:
   Stack=2, Locals=1, Args_size=1
	getstatic	Field scala/collection/script/End$.MODULE$:Lscala/collection/script/End$;
	iload_0
	invokevirtual	Method scala/collection/script/End$.productElementName:(I)Ljava/lang/String;
	areturn
  Labels:

public static final boolean canEqual(java.lang.Object);
  Signature: (Ljava/lang/Object;)Z
  Code:
   Stack=2, Locals=1, Args_size=1
	getstatic	Field scala/collection/script/End$.MODULE$:Lscala/collection/script/End$;
	aload_0
	invokevirtual	Method scala/collection/script/End$.canEqual:(Ljava/lang/Object;)Z
	ireturn
  Labels:

public static final java.lang.Object productElement(int);
  Signature: (I)Ljava/lang/Object;
  Code:
   Stack=2, Locals=1, Args_size=1
	getstatic	Field scala/collection/script/End$.MODULE$:Lscala/collection/script/End$;
	iload_0
	invokevirtual	Method scala/collection/script/End$.productElement:(I)Ljava/lang/Object;
	areturn
  Labels:

public static final int productArity();
  Signature: ()I
  Code:
   Stack=1, Locals=0, Args_size=0
	getstatic	Field scala/collection/script/End$.MODULE$:Lscala/collection/script/End$;
	invokevirtual	Method scala/collection/script/End$.productArity:()I
	ireturn
  Labels:

public static final java.lang.String productPrefix();
  Signature: ()Ljava/lang/String;
  Code:
   Stack=1, Locals=0, Args_size=0
	getstatic	Field scala/collection/script/End$.MODULE$:Lscala/collection/script/End$;
	invokevirtual	Method scala/collection/script/End$.productPrefix:()Ljava/lang/String;
	areturn
  Labels:

}

