Compiled from "Location.scala"
public final class scala.collection.script.NoLo extends java.lang.Object
  SourceFile: "Location.scala"
  ScalaSig: length = 0x3
   05 00 00 
  RuntimeVisibleAnnotations: length = 0xB
   00 01 00 27 00 01 00 28 73 00 29 
  minor version: 0
  major version: 49
  Constant pool:
Asciz	SourceFile;
Asciz	Location.scala;
Asciz	productElements;
Asciz	()Lscala/collection/Iterator;;
Asciz	Code;
Asciz	scala/collection/script/NoLo$;
class	scala/collection/script/NoLo$
Asciz	MODULE$;
Asciz	Lscala/collection/script/NoLo$;;
NameAndType	MODULE$:Lscala/collection/script/NoLo$;
Field	scala/collection/script/NoLo$.MODULE$:Lscala/collection/script/NoLo$;
NameAndType	productElements:()Lscala/collection/Iterator;
Method	scala/collection/script/NoLo$.productElements:()Lscala/collection/Iterator;
Asciz	Deprecated;
Asciz	productIterator;
NameAndType	productIterator:()Lscala/collection/Iterator;
Method	scala/collection/script/NoLo$.productIterator:()Lscala/collection/Iterator;
Asciz	productElementName;
Asciz	(I)Ljava/lang/String;;
NameAndType	productElementName:(I)Ljava/lang/String;
Method	scala/collection/script/NoLo$.productElementName:(I)Ljava/lang/String;
Asciz	canEqual;
Asciz	(Ljava/lang/Object;)Z;
NameAndType	canEqual:(Ljava/lang/Object;)Z
Method	scala/collection/script/NoLo$.canEqual:(Ljava/lang/Object;)Z
Asciz	productElement;
Asciz	(I)Ljava/lang/Object;;
NameAndType	productElement:(I)Ljava/lang/Object;
Method	scala/collection/script/NoLo$.productElement:(I)Ljava/lang/Object;
Asciz	productArity;
Asciz	()I;
NameAndType	productArity:()I
Method	scala/collection/script/NoLo$.productArity:()I
Asciz	productPrefix;
Asciz	()Ljava/lang/String;;
NameAndType	productPrefix:()Ljava/lang/String;
Method	scala/collection/script/NoLo$.productPrefix:()Ljava/lang/String;
Asciz	ScalaSig;
Asciz	Lscala/reflect/ScalaSignature;;
Asciz	bytes;
Asciz	!;Q!\t&\tAAT8M_*1Bg;1AC2pY2,7\r^5p]*\tq!AtGdm)YQ\"1A!A\t6AAT8M_N!1BD\t!\tQq\"\tAAj\2bi&|g'5\ta!\r\tY1kY1mC>'.Z2u!\tb#\r\t9K]8ek$\"B\r\tQAj]&$hF\n!a2\"A\nj;p'RN\4y\"aR!!\t\t1gnG!!.<b\t)ETiJLgn\tO-!\t!C!QiO]8ek$K]3gSb,A\tU-!\t!C!WaO]8ek$I]5usV\tA[%aF:$\tIIAxZ;dicW-\3oiR!'\t%MJ!sC7_\ta$9\t\":!M\#rkdGC>!\t2(=\r\t9!i\8mKtb8\rA\r\t-!\t!C\tY!/Z1e%x<f)\tCAC\tEPE*,7\r\"A$\n3!D:fe&G.>bE2,;
Asciz	RuntimeVisibleAnnotations;
Asciz	scala/collection/script/NoLo;
class	scala/collection/script/NoLo
Asciz	java/lang/Object;
class	java/lang/Object

{
public static final scala.collection.Iterator productElements();
  Signature: ()Lscala/collection/Iterator;
  Code:
   Stack=1, Locals=0, Args_size=0
	getstatic	Field scala/collection/script/NoLo$.MODULE$:Lscala/collection/script/NoLo$;
	invokevirtual	Method scala/collection/script/NoLo$.productElements:()Lscala/collection/Iterator;
	areturn
  Labels:
  Deprecated: true

public static final scala.collection.Iterator productIterator();
  Signature: ()Lscala/collection/Iterator;
  Code:
   Stack=1, Locals=0, Args_size=0
	getstatic	Field scala/collection/script/NoLo$.MODULE$:Lscala/collection/script/NoLo$;
	invokevirtual	Method scala/collection/script/NoLo$.productIterator:()Lscala/collection/Iterator;
	areturn
  Labels:

public static final java.lang.String productElementName(int);
  Signature: (I)Ljava/lang/String;
  Code:
   Stack=2, Locals=1, Args_size=1
	getstatic	Field scala/collection/script/NoLo$.MODULE$:Lscala/collection/script/NoLo$;
	iload_0
	invokevirtual	Method scala/collection/script/NoLo$.productElementName:(I)Ljava/lang/String;
	areturn
  Labels:

public static final boolean canEqual(java.lang.Object);
  Signature: (Ljava/lang/Object;)Z
  Code:
   Stack=2, Locals=1, Args_size=1
	getstatic	Field scala/collection/script/NoLo$.MODULE$:Lscala/collection/script/NoLo$;
	aload_0
	invokevirtual	Method scala/collection/script/NoLo$.canEqual:(Ljava/lang/Object;)Z
	ireturn
  Labels:

public static final java.lang.Object productElement(int);
  Signature: (I)Ljava/lang/Object;
  Code:
   Stack=2, Locals=1, Args_size=1
	getstatic	Field scala/collection/script/NoLo$.MODULE$:Lscala/collection/script/NoLo$;
	iload_0
	invokevirtual	Method scala/collection/script/NoLo$.productElement:(I)Ljava/lang/Object;
	areturn
  Labels:

public static final int productArity();
  Signature: ()I
  Code:
   Stack=1, Locals=0, Args_size=0
	getstatic	Field scala/collection/script/NoLo$.MODULE$:Lscala/collection/script/NoLo$;
	invokevirtual	Method scala/collection/script/NoLo$.productArity:()I
	ireturn
  Labels:

public static final java.lang.String productPrefix();
  Signature: ()Ljava/lang/String;
  Code:
   Stack=1, Locals=0, Args_size=0
	getstatic	Field scala/collection/script/NoLo$.MODULE$:Lscala/collection/script/NoLo$;
	invokevirtual	Method scala/collection/script/NoLo$.productPrefix:()Ljava/lang/String;
	areturn
  Labels:

}

