Compiled from "Message.scala"
public class scala.collection.script.Remove extends java.lang.Object implements scala.collection.script.Message,scala.ScalaObject,scala.Product,java.io.Serializable
  SourceFile: "Message.scala"
  Signature: length = 0x2
   00 7D 
  ScalaSig: length = 0x472
   05 00 FFFFFF81 26 06 04 01 02 40 09 02 06 52 65 6D 6F
   76 65 0A 02 03 04 01 06 73 63 72 69 70 74 0A 02
   05 06 01 0A 63 6F 6C 6C 65 63 74 69 6F 6E 0A 01
   07 01 05 73 63 61 6C 61 03 00 15 02 0A 19 13 05
   00 0B 13 23 26 10 02 0C 11 0D 01 0D 0A 02 0E 0F
   01 04 6C 61 6E 67 0A 01 10 01 04 6A 61 76 61 09
   02 12 0D 02 06 4F 62 6A 65 63 74 10 03 14 15 17
   0D 01 02 09 02 16 02 02 07 4D 65 73 73 61 67 65
   10 02 18 19 0C 00 04 08 1A 00 FFFFFF84 FFFFFF80 FFFFFF84 FFFFFFC2 00 1B
   02 01 41 11 02 1C 20 10 02 1D 1E 0D 01 06 09 02
   1F 06 02 07 4E 6F 74 68 69 6E 67 10 02 1D 21 09
   02 22 06 02 03 41 6E 79 10 02 1D 24 09 02 25 06
   02 0B 53 63 61 6C 61 4F 62 6A 65 63 74 10 02 1D
   27 09 02 28 06 02 07 50 72 6F 64 75 63 74 08 08
   2A 00 FFFFFF82 FFFFFFCA FFFFFF80 FFFFFF84 00 2B 01 08 6C 6F 63 61 74 69
   6F 6E 15 01 2C 10 02 14 2D 09 02 2E 02 02 08 4C
   6F 63 61 74 69 6F 6E 08 08 30 00 FFFFFF82 FFFFFF88 FFFFFFA0 FFFFFF80 04
   2C 01 09 6C 6F 63 61 74 69 6F 6E 20 08 08 32 00
   FFFFFF82 FFFFFFCA FFFFFF80 FFFFFF84 00 33 01 04 65 6C 65 6D 15 01 17 08
   08 35 00 FFFFFF82 FFFFFF88 FFFFFFA0 FFFFFF80 04 17 01 05 65 6C 65 6D 20
   08 05 37 00 FFFFFF84 00 38 01 06 3C 69 6E 69 74 3E 14
   03 39 3A 3B 10 03 14 00 17 08 05 2A 36 FFFFFFC0 00 2C
   08 05 32 36 FFFFFFC0 00 17 08 05 37 00 FFFFFF84 00 3D 14 02
   39 3E 08 05 32 3C FFFFFFC0 00 17 08 07 40 00 FFFFFF81 FFFFFF80 FFFFFF84
   00 41 01 04 63 6F 70 79 15 02 42 45 14 03 43 46
   47 10 03 14 00 44 10 02 18 45 04 08 1A 3F FFFFFF84 FFFFFF80
   FFFFFF80 FFFFFFC2 00 1B 08 07 2A 3F FFFFFF90 FFFFFF80 FFFFFFC0 00 2C 08 07 32
   3F FFFFFF90 FFFFFF80 FFFFFFC0 00 44 08 07 49 00 FFFFFF91 FFFFFF80 FFFFFF84 00 4A 01
   0E 63 6F 70 79 24 64 65 66 61 75 6C 74 24 31 15
   02 4B 55 2A 02 2C 4C 2B 01 4D 10 02 4E 53 0D 01
   4F 0A 02 50 51 01 09 75 6E 63 68 65 63 6B 65 64
   0A 02 52 06 01 0A 61 6E 6E 6F 74 61 74 69 6F 6E
   09 02 54 4F 02 11 75 6E 63 68 65 63 6B 65 64 56
   61 72 69 61 6E 63 65 04 08 1A 48 FFFFFF84 FFFFFF80 FFFFFF80 FFFFFFC2 00
   1B 08 07 57 00 FFFFFF91 FFFFFF80 FFFFFF84 00 58 01 0E 63 6F 70 79
   24 64 65 66 61 75 6C 74 24 32 15 02 59 5A 2A 02
   17 4C 04 08 1A 56 FFFFFF84 FFFFFF80 FFFFFF80 FFFFFFC2 00 1B 08 08 5C 00
   FFFFFF84 FFFFFF80 FFFFFF80 FFFFFF84 20 5D 01 08 68 61 73 68 43 6F 64 65
   14 01 5E 10 02 1D 5F 09 02 60 06 02 03 49 6E 74
   08 08 62 00 FFFFFF84 FFFFFF80 FFFFFF80 FFFFFF84 20 63 01 08 74 6F 53 74
   72 69 6E 67 14 01 64 10 02 65 68 0E 02 1D 66 09
   02 67 06 01 06 50 72 65 64 65 66 09 02 69 6A 02
   06 53 74 72 69 6E 67 0A 02 67 06 08 08 6C 00 FFFFFF84
   FFFFFF80 FFFFFF80 FFFFFF84 20 6D 01 06 65 71 75 61 6C 73 14 02 6E
   71 10 02 1D 6F 09 02 70 06 02 07 42 6F 6F 6C 65
   61 6E 08 07 72 6B FFFFFF81 FFFFFF80 FFFFFFC0 00 20 01 03 78 24 31
   08 08 74 00 FFFFFF84 FFFFFF80 FFFFFF80 FFFFFF84 20 75 01 0D 70 72 6F 64
   75 63 74 50 72 65 66 69 78 15 01 76 10 02 0C 77
   09 02 69 0D 08 08 79 00 FFFFFF84 FFFFFF80 FFFFFF80 FFFFFF84 20 7A 01 0C
   70 72 6F 64 75 63 74 41 72 69 74 79 15 01 5E 08
   08 7C 00 FFFFFF84 FFFFFF80 FFFFFF80 FFFFFF84 20 7D 01 0E 70 72 6F 64 75
   63 74 45 6C 65 6D 65 6E 74 14 02 20 7E 08 07 72
   7B FFFFFF81 FFFFFF80 FFFFFFC0 00 5E 08 0A FFFFFF81 00 00 FFFFFF84 FFFFFF80 FFFFFF80 FFFFFF84 20
   FFFFFF81 01 01 08 63 61 6E 45 71 75 61 6C 14 03 6E FFFFFF81
   02 08 07 72 7F FFFFFF81 FFFFFF80 FFFFFFC0 00 20 28 03 00 FFFFFF81 04 10
   03 1D FFFFFF81 05 09 03 FFFFFF81 06 06 02 0C 73 65 72 69 61
   6C 69 7A 61 62 6C 65 07 09 FFFFFF81 08 02 FFFFFF81 FFFFFF80 FFFFFF88 02
   FFFFFF81 09 01 06 52 65 6D 6F 76 65 10 03 14 FFFFFF81 0A 06
   09 01 02 FFFFFF84 FFFFFF81 FFFFFF80 FFFFFF88 02 FFFFFF81 0B 13 04 FFFFFF81 0A 0B 23
   08 07 37 FFFFFF81 0A FFFFFF84 00 FFFFFF81 0D 14 02 FFFFFF81 09 08 0A FFFFFF81
   0F FFFFFF81 0A FFFFFF81 FFFFFF80 FFFFFF84 40 FFFFFF81 10 01 05 61 70 70 6C 79
   15 04 FFFFFF81 11 FFFFFF81 14 14 06 FFFFFF81 12 FFFFFF81 15 FFFFFF81 16 10 04
   14 00 FFFFFF81 13 10 03 18 FFFFFF81 14 04 09 1A FFFFFF81 0E FFFFFF84 FFFFFF80
   FFFFFF80 FFFFFFC2 00 1B 08 06 2A FFFFFF81 0E FFFFFFC0 00 2C 08 07 32 FFFFFF81
   0E FFFFFFC0 00 FFFFFF81 13 08 0A FFFFFF81 18 FFFFFF81 0A FFFFFF81 FFFFFF80 FFFFFF84 40 FFFFFF81
   19 01 07 75 6E 61 70 70 6C 79 15 04 FFFFFF81 1A FFFFFF81 22
   14 04 FFFFFF81 1B FFFFFF81 23 10 05 1D FFFFFF81 1C FFFFFF81 1E 09 03 FFFFFF81
   1D 06 02 04 53 6F 6D 65 10 06 1D FFFFFF81 1F 2C FFFFFF81 21
   09 03 FFFFFF81 20 06 02 06 54 75 70 6C 65 32 10 03 18
   FFFFFF81 22 04 09 1A FFFFFF81 17 FFFFFF84 FFFFFF80 FFFFFF80 FFFFFFC2 00 1B 08 08 FFFFFF81
   24 FFFFFF81 17 FFFFFFC0 00 FFFFFF81 25 01 03 78 24 30 10 04 14 00
   FFFFFF81 21 
  minor version: 0
  major version: 49
  Constant pool:
Asciz	SourceFile;
Asciz	Message.scala;
Asciz	elem;
Asciz	Ljava/lang/Object;;
Asciz	TA;;
Asciz	Signature;
Asciz	location;
Asciz	Lscala/collection/script/Location;;
Asciz	<init>;
Asciz	(Lscala/collection/script/Location;Ljava/lang/Object;)V;
Asciz	Code;
Asciz	LineNumberTable;
Asciz	scala/collection/script/Remove;
class	scala/collection/script/Remove
NameAndType	location:Lscala/collection/script/Location;
Field	scala/collection/script/Remove.location:Lscala/collection/script/Location;
NameAndType	elem:Ljava/lang/Object;
Field	scala/collection/script/Remove.elem:Ljava/lang/Object;
Asciz	java/lang/Object;
class	java/lang/Object
Asciz	()V;
NameAndType	"<init>":()V
Method	java/lang/Object."<init>":()V
Asciz	scala/Product$class;
class	scala/Product$class
Asciz	$init$;
Asciz	(Lscala/Product;)V;
NameAndType	$init$:(Lscala/Product;)V
Method	scala/Product$class.$init$:(Lscala/Product;)V
Asciz	this;
Asciz	Lscala/collection/script/Remove;;
Asciz	LocalVariableTable;
Asciz	(Lscala/collection/script/Location;TA;)V;
Asciz	gd3$1;
Asciz	(Lscala/collection/script/Location;Ljava/lang/Object;)Z;
Asciz	()Lscala/collection/script/Location;;
NameAndType	location:()Lscala/collection/script/Location;
Method	scala/collection/script/Remove.location:()Lscala/collection/script/Location;
Asciz	equals;
Asciz	(Ljava/lang/Object;)Z;
NameAndType	equals:(Ljava/lang/Object;)Z
Method	java/lang/Object.equals:(Ljava/lang/Object;)Z
Asciz	()Ljava/lang/Object;;
NameAndType	elem:()Ljava/lang/Object;
Method	scala/collection/script/Remove.elem:()Ljava/lang/Object;
Asciz	java/lang/Number;
class	java/lang/Number
Asciz	java/lang/Character;
class	java/lang/Character
Asciz	scala/runtime/BoxesRunTime;
class	scala/runtime/BoxesRunTime
Asciz	equals2;
Asciz	(Ljava/lang/Object;Ljava/lang/Object;)Z;
NameAndType	equals2:(Ljava/lang/Object;Ljava/lang/Object;)Z
Method	scala/runtime/BoxesRunTime.equals2:(Ljava/lang/Object;Ljava/lang/Object;)Z
Asciz	y0;
Asciz	canEqual;
Asciz	productElement;
Asciz	(I)Ljava/lang/Object;;
Asciz	java/lang/IndexOutOfBoundsException;
class	java/lang/IndexOutOfBoundsException
Asciz	boxToInteger;
Asciz	(I)Ljava/lang/Integer;;
NameAndType	boxToInteger:(I)Ljava/lang/Integer;
Method	scala/runtime/BoxesRunTime.boxToInteger:(I)Ljava/lang/Integer;
Asciz	toString;
Asciz	()Ljava/lang/String;;
NameAndType	toString:()Ljava/lang/String;
Method	java/lang/Object.toString:()Ljava/lang/String;
Asciz	(Ljava/lang/String;)V;
NameAndType	"<init>":(Ljava/lang/String;)V
Method	java/lang/IndexOutOfBoundsException."<init>":(Ljava/lang/String;)V
Asciz	productArity;
Asciz	()I;
Asciz	productPrefix;
Asciz	Remove;
String	Remove
NameAndType	gd3$1:(Lscala/collection/script/Location;Ljava/lang/Object;)Z
Method	scala/collection/script/Remove.gd3$1:(Lscala/collection/script/Location;Ljava/lang/Object;)Z
Asciz	scala/Equals;
class	scala/Equals
NameAndType	canEqual:(Ljava/lang/Object;)Z
InterfaceMethod	scala/Equals.canEqual:(Ljava/lang/Object;)Z
Asciz	temp12;
Asciz	temp13;
Asciz	temp14;
Asciz	scala/runtime/ScalaRunTime$;
class	scala/runtime/ScalaRunTime$
Asciz	MODULE$;
Asciz	Lscala/runtime/ScalaRunTime$;;
NameAndType	MODULE$:Lscala/runtime/ScalaRunTime$;
Field	scala/runtime/ScalaRunTime$.MODULE$:Lscala/runtime/ScalaRunTime$;
Asciz	_toString;
Asciz	(Lscala/Product;)Ljava/lang/String;;
NameAndType	_toString:(Lscala/Product;)Ljava/lang/String;
Method	scala/runtime/ScalaRunTime$._toString:(Lscala/Product;)Ljava/lang/String;
Asciz	hashCode;
Asciz	_hashCode;
Asciz	(Lscala/Product;)I;
NameAndType	_hashCode:(Lscala/Product;)I
Method	scala/runtime/ScalaRunTime$._hashCode:(Lscala/Product;)I
Asciz	copy;
Asciz	(Lscala/collection/script/Location;Ljava/lang/Object;)Lscala/collection/script/Remove;;
NameAndType	"<init>":(Lscala/collection/script/Location;Ljava/lang/Object;)V
Method	scala/collection/script/Remove."<init>":(Lscala/collection/script/Location;Ljava/lang/Object;)V
Asciz	(Ljava/lang/Object;)V;
Asciz	scala/collection/script/NoLo$;
class	scala/collection/script/NoLo$
Asciz	Lscala/collection/script/NoLo$;;
NameAndType	MODULE$:Lscala/collection/script/NoLo$;
Field	scala/collection/script/NoLo$.MODULE$:Lscala/collection/script/NoLo$;
Asciz	(TA;)V;
Asciz	()TA;;
Asciz	copy$default$1;
Asciz	copy$default$2;
Asciz	productElements;
Asciz	()Lscala/collection/Iterator;;
Asciz	(Lscala/Product;)Lscala/collection/Iterator;;
NameAndType	productElements:(Lscala/Product;)Lscala/collection/Iterator;
Method	scala/Product$class.productElements:(Lscala/Product;)Lscala/collection/Iterator;
Asciz	Deprecated;
Asciz	productIterator;
NameAndType	productIterator:(Lscala/Product;)Lscala/collection/Iterator;
Method	scala/Product$class.productIterator:(Lscala/Product;)Lscala/collection/Iterator;
Asciz	<A:Ljava/lang/Object;>Ljava/lang/Object;Lscala/collection/script/Message<TA;>;Lscala/ScalaObject;Lscala/Product;;
Asciz	ScalaSig;
Asciz	scala/collection/script/Message;
class	scala/collection/script/Message
Asciz	scala/ScalaObject;
class	scala/ScalaObject
Asciz	scala/Product;
class	scala/Product
Asciz	java/io/Serializable;
class	java/io/Serializable

{
private final java.lang.Object elem;
  Signature: Ljava/lang/Object;
  Signature: length = 0x2
   00 05 

private final scala.collection.script.Location location;
  Signature: Lscala/collection/script/Location;

public scala.collection.script.Remove(scala.collection.script.Location, java.lang.Object);
  Signature: (Lscala/collection/script/Location;Ljava/lang/Object;)V
  Code:
   Stack=2, Locals=3, Args_size=3
	aload_0
	aload_1
	putfield	Field location:Lscala/collection/script/Location;
	aload_0
	aload_2
	putfield	Field elem:Ljava/lang/Object;
	aload_0
	invokespecial	Method java/lang/Object."<init>":()V
	aload_0
	invokestatic	Method scala/Product$class.$init$:(Lscala/Product;)V
	return
  Labels:
  LocalVariableTable: 
   Start  Length  Slot  Name   Signature
   0      19      0    this       Lscala/collection/script/Remove;
   0      19      1    location       Lscala/collection/script/Location;
   0      19      2    elem       Ljava/lang/Object;

  Signature: length = 0x2
   00 21 

private final boolean gd3$1(scala.collection.script.Location, java.lang.Object);
  Signature: (Lscala/collection/script/Location;Ljava/lang/Object;)Z
  Code:
   Stack=2, Locals=5, Args_size=3
	aload_1
	aload_0
	invokevirtual	Method location:()Lscala/collection/script/Location;
	astore_3
	dup
	ifnonnull	l1 // aload_3
	pop
	aload_3
	ifnull	l2 // aload_0
	goto	l3 // iconst_0
l1	aload_3
	invokevirtual	Method java/lang/Object.equals:(Ljava/lang/Object;)Z
	ifeq	l3 // iconst_0
l2	aload_0
	invokevirtual	Method elem:()Ljava/lang/Object;
	astore	4
	aload_2
	aload	4
	if_acmpne	l4 // aload_2
	iconst_1
	goto	l5 // ifeq
l4	aload_2
	ifnonnull	l6 // aload_2
	iconst_0
	goto	l5 // ifeq
l6	aload_2
	instanceof	class java/lang/Number
	ifne	l7 // aload_2
	aload_2
	instanceof	class java/lang/Character
	ifeq	l8 // aload_2
l7	aload_2
	aload	4
	invokestatic	Method scala/runtime/BoxesRunTime.equals2:(Ljava/lang/Object;Ljava/lang/Object;)Z
	goto	l5 // ifeq
l8	aload_2
	aload	4
	invokevirtual	Method java/lang/Object.equals:(Ljava/lang/Object;)Z
l5	ifeq	l3 // iconst_0
	iconst_1
	goto	l9 // ireturn
l3	iconst_0
l9	ireturn
  Labels:
   	l1 = 18 // aload_3
   	l2 = 25 // aload_0
   	l4 = 41 // aload_2
   	l6 = 49 // aload_2
   	l7 = 63 // aload_2
   	l8 = 72 // aload_2
   	l5 = 78 // ifeq
   	l3 = 85 // iconst_0
   	l9 = 86 // ireturn
  LocalVariableTable: 
   Start  Length  Slot  Name   Signature
   0      87      0    this       Lscala/collection/script/Remove;
   37      44      4    y0       Ljava/lang/Object;


public boolean canEqual(java.lang.Object);
  Signature: (Ljava/lang/Object;)Z
  Code:
   Stack=1, Locals=2, Args_size=2
	aload_1
	instanceof	class scala/collection/script/Remove
	ireturn
  Labels:

public java.lang.Object productElement(int);
  Signature: (I)Ljava/lang/Object;
  Code:
   Stack=3, Locals=2, Args_size=2
	iload_1
	tableswitch{ //0 to 1
		0: 46;
		1: 39;
		default: 24 }
	new	class java/lang/IndexOutOfBoundsException
	dup
	iload_1
	invokestatic	Method scala/runtime/BoxesRunTime.boxToInteger:(I)Ljava/lang/Integer;
	invokevirtual	Method java/lang/Object.toString:()Ljava/lang/String;
	invokespecial	Method java/lang/IndexOutOfBoundsException."<init>":(Ljava/lang/String;)V
	athrow
	aload_0
	invokevirtual	Method elem:()Ljava/lang/Object;
	goto	l1 // areturn
	aload_0
	invokevirtual	Method location:()Lscala/collection/script/Location;
l1	areturn
  Labels:
   	l1 = 50 // areturn

public int productArity();
  Signature: ()I
  Code:
   Stack=1, Locals=1, Args_size=1
	iconst_2
	ireturn
  Labels:

public java.lang.String productPrefix();
  Signature: ()Ljava/lang/String;
  Code:
   Stack=1, Locals=1, Args_size=1
	ldc	String Remove
	areturn
  Labels:

public boolean equals(java.lang.Object);
  Signature: (Ljava/lang/Object;)Z
  Code:
   Stack=3, Locals=5, Args_size=2
	aload_0
	aload_1
	if_acmpeq	l1 // iconst_1
	aload_1
	instanceof	class scala/collection/script/Remove
	ifeq	l2 // iconst_0
	aload_1
	checkcast	class scala/collection/script/Remove
	astore_2
	aload_2
	invokevirtual	Method location:()Lscala/collection/script/Location;
	astore_3
	aload_2
	invokevirtual	Method elem:()Ljava/lang/Object;
	astore	4
	aload_0
	aload_3
	aload	4
	invokespecial	Method gd3$1:(Lscala/collection/script/Location;Ljava/lang/Object;)Z
	ifeq	l3 // iconst_0
	aload_1
	checkcast	class scala/collection/script/Remove
	aload_0
	invokeinterface	InterfaceMethod scala/Equals.canEqual:(Ljava/lang/Object;)Z
	goto	l4 // ifeq
l3	iconst_0
	goto	l4 // ifeq
l2	iconst_0
l4	ifeq	l5 // iconst_0
l1	iconst_1
	goto	l6 // ireturn
l5	iconst_0
l6	ireturn
  Labels:
   	l3 = 51 // iconst_0
   	l2 = 55 // iconst_0
   	l4 = 56 // ifeq
   	l1 = 59 // iconst_1
   	l5 = 63 // iconst_0
   	l6 = 64 // ireturn
  LocalVariableTable: 
   Start  Length  Slot  Name   Signature
   0      65      0    this       Lscala/collection/script/Remove;
   17      38      2    temp12       Lscala/collection/script/Remove;
   22      33      3    temp13       Lscala/collection/script/Location;
   28      27      4    temp14       Ljava/lang/Object;


public java.lang.String toString();
  Signature: ()Ljava/lang/String;
  Code:
   Stack=2, Locals=1, Args_size=1
	getstatic	Field scala/runtime/ScalaRunTime$.MODULE$:Lscala/runtime/ScalaRunTime$;
	aload_0
	invokevirtual	Method scala/runtime/ScalaRunTime$._toString:(Lscala/Product;)Ljava/lang/String;
	areturn
  Labels:

public int hashCode();
  Signature: ()I
  Code:
   Stack=2, Locals=1, Args_size=1
	getstatic	Field scala/runtime/ScalaRunTime$.MODULE$:Lscala/runtime/ScalaRunTime$;
	aload_0
	invokevirtual	Method scala/runtime/ScalaRunTime$._hashCode:(Lscala/Product;)I
	ireturn
  Labels:

public scala.collection.script.Remove copy(scala.collection.script.Location, java.lang.Object);
  Signature: (Lscala/collection/script/Location;Ljava/lang/Object;)Lscala/collection/script/Remove;
  Code:
   Stack=4, Locals=3, Args_size=3
	new	class scala/collection/script/Remove
	dup
	aload_1
	aload_2
	invokespecial	Method "<init>":(Lscala/collection/script/Location;Ljava/lang/Object;)V
	areturn
  Labels:
  LocalVariableTable: 
   Start  Length  Slot  Name   Signature
   0      10      0    this       Lscala/collection/script/Remove;
   0      10      1    location       Lscala/collection/script/Location;
   0      10      2    elem       Ljava/lang/Object;


public scala.collection.script.Remove(java.lang.Object);
  Signature: (Ljava/lang/Object;)V
  Code:
   Stack=3, Locals=2, Args_size=2
	aload_0
	getstatic	Field scala/collection/script/NoLo$.MODULE$:Lscala/collection/script/NoLo$;
	aload_1
	invokespecial	Method "<init>":(Lscala/collection/script/Location;Ljava/lang/Object;)V
	return
  Labels:
  LocalVariableTable: 
   Start  Length  Slot  Name   Signature
   0      9      0    this       Lscala/collection/script/Remove;
   0      9      1    elem       Ljava/lang/Object;

  Signature: length = 0x2
   00 70 

public java.lang.Object elem();
  Signature: ()Ljava/lang/Object;
  Code:
   Stack=1, Locals=1, Args_size=1
	aload_0
	getfield	Field elem:Ljava/lang/Object;
	areturn
  Labels:
  Signature: length = 0x2
   00 71 

public scala.collection.script.Location location();
  Signature: ()Lscala/collection/script/Location;
  Code:
   Stack=1, Locals=1, Args_size=1
	aload_0
	getfield	Field location:Lscala/collection/script/Location;
	areturn
  Labels:

public scala.collection.script.Location copy$default$1();
  Signature: ()Lscala/collection/script/Location;
  Code:
   Stack=1, Locals=1, Args_size=1
	aload_0
	invokevirtual	Method location:()Lscala/collection/script/Location;
	areturn
  Labels:

public java.lang.Object copy$default$2();
  Signature: ()Ljava/lang/Object;
  Code:
   Stack=1, Locals=1, Args_size=1
	aload_0
	invokevirtual	Method elem:()Ljava/lang/Object;
	areturn
  Labels:

public scala.collection.Iterator productElements();
  Signature: ()Lscala/collection/Iterator;
  Code:
   Stack=1, Locals=1, Args_size=1
	aload_0
	invokestatic	Method scala/Product$class.productElements:(Lscala/Product;)Lscala/collection/Iterator;
	areturn
  Labels:
  Deprecated: true

public scala.collection.Iterator productIterator();
  Signature: ()Lscala/collection/Iterator;
  Code:
   Stack=1, Locals=1, Args_size=1
	aload_0
	invokestatic	Method scala/Product$class.productIterator:(Lscala/Product;)Lscala/collection/Iterator;
	areturn
  Labels:

}

