Compiled from "Message.scala"
public class scala.collection.script.Script extends scala.collection.mutable.ArrayBuffer implements scala.collection.script.Message,scala.ScalaObject
  SourceFile: "Message.scala"
  Signature: length = 0x2
   00 49 
  ScalaSig: length = 0x13B
   05 00 38 06 04 01 02 00 09 02 06 53 63 72 69 70
   74 0A 02 03 04 01 06 73 63 72 69 70 74 0A 02 05
   06 01 0A 63 6F 6C 6C 65 63 74 69 6F 6E 0A 01 07
   01 05 73 63 61 6C 61 03 00 15 02 0A 17 13 04 00
   0B 11 21 10 03 0C 0F 11 0D 01 0D 0A 02 0E 04 01
   07 6D 75 74 61 62 6C 65 09 02 10 0D 02 0B 41 72
   72 61 79 42 75 66 66 65 72 10 03 12 13 15 0D 01
   02 09 02 14 02 02 07 4D 65 73 73 61 67 65 10 02
   16 17 0C 00 04 08 18 00 FFFFFF84 FFFFFF80 FFFFFF80 FFFFFFC2 00 19 02 01
   41 11 02 1A 1E 10 02 1B 1C 0D 01 06 09 02 1D 06
   02 07 4E 6F 74 68 69 6E 67 10 02 1B 1F 09 02 20
   06 02 03 41 6E 79 10 02 1B 22 09 02 23 06 02 0B
   53 63 61 6C 61 4F 62 6A 65 63 74 08 05 25 00 FFFFFF84
   00 26 01 06 3C 69 6E 69 74 3E 14 01 27 10 03 12
   00 15 08 05 29 00 FFFFFF84 20 2A 01 08 74 6F 53 74 72
   69 6E 67 14 01 2B 10 02 2C 2F 0E 02 1B 2D 09 02
   2E 06 01 06 50 72 65 64 65 66 09 02 30 31 02 06
   53 74 72 69 6E 67 0A 02 2E 06 08 05 33 00 FFFFFF84 20
   34 01 08 68 61 73 68 43 6F 64 65 14 01 35 10 02
   1B 36 09 02 37 06 02 03 49 6E 74 
  minor version: 0
  major version: 49
  Constant pool:
const #1 = Asciz	SourceFile;
const #2 = Asciz	Message.scala;
const #3 = Asciz	<init>;
const #4 = Asciz	()V;
const #5 = Asciz	Code;
const #6 = Asciz	LineNumberTable;
const #7 = Asciz	scala/collection/mutable/ArrayBuffer;
const #8 = class	#7;	//  scala/collection/mutable/ArrayBuffer
const #9 = NameAndType	#3:#4;//  "<init>":()V
const #10 = Method	#8.#9;	//  scala/collection/mutable/ArrayBuffer."<init>":()V
const #11 = Asciz	Signature;
const #12 = Asciz	hashCode;
const #13 = Asciz	()I;
const #14 = Asciz	java/lang/UnsupportedOperationException;
const #15 = class	#14;	//  java/lang/UnsupportedOperationException
const #16 = Asciz	scripts are not suitable as hash keys;
const #17 = String	#16;	//  scripts are not suitable as hash keys
const #18 = Asciz	(Ljava/lang/String;)V;
const #19 = NameAndType	#3:#18;//  "<init>":(Ljava/lang/String;)V
const #20 = Method	#15.#19;	//  java/lang/UnsupportedOperationException."<init>":(Ljava/lang/String;)V
const #21 = Asciz	toString;
const #22 = Asciz	()Ljava/lang/String;;
const #23 = Asciz	Script(;
const #24 = String	#23;	//  Script(
const #25 = Asciz	scala/collection/generic/VectorTemplate;
const #26 = class	#25;	//  scala/collection/generic/VectorTemplate
const #27 = Asciz	iterator;
const #28 = Asciz	()Lscala/collection/Iterator;;
const #29 = NameAndType	#27:#28;//  iterator:()Lscala/collection/Iterator;
const #30 = InterfaceMethod	#26.#29;	//  scala/collection/generic/VectorTemplate.iterator:()Lscala/collection/Iterator;
const #31 = Asciz	scala/collection/Iterator;
const #32 = class	#31;	//  scala/collection/Iterator
const #33 = Asciz	hasNext;
const #34 = Asciz	()Z;
const #35 = NameAndType	#33:#34;//  hasNext:()Z
const #36 = InterfaceMethod	#32.#35;	//  scala/collection/Iterator.hasNext:()Z
const #37 = Asciz	scala/collection/mutable/StringBuilder;
const #38 = class	#37;	//  scala/collection/mutable/StringBuilder
const #39 = Method	#38.#9;	//  scala/collection/mutable/StringBuilder."<init>":()V
const #40 = Asciz	append;
const #41 = Asciz	(Ljava/lang/Object;)Lscala/collection/mutable/StringBuilder;;
const #42 = NameAndType	#40:#41;//  append:(Ljava/lang/Object;)Lscala/collection/mutable/StringBuilder;
const #43 = Method	#38.#42;	//  scala/collection/mutable/StringBuilder.append:(Ljava/lang/Object;)Lscala/collection/mutable/StringBuilder;
const #44 = Asciz	, ;
const #45 = String	#44;	//  , 
const #46 = NameAndType	#21:#22;//  toString:()Ljava/lang/String;
const #47 = Method	#38.#46;	//  scala/collection/mutable/StringBuilder.toString:()Ljava/lang/String;
const #48 = Asciz	[;
const #49 = String	#48;	//  [
const #50 = Asciz	scala/runtime/BoxesRunTime;
const #51 = class	#50;	//  scala/runtime/BoxesRunTime
const #52 = Asciz	boxToInteger;
const #53 = Asciz	(I)Ljava/lang/Integer;;
const #54 = NameAndType	#52:#53;//  boxToInteger:(I)Ljava/lang/Integer;
const #55 = Method	#51.#54;	//  scala/runtime/BoxesRunTime.boxToInteger:(I)Ljava/lang/Integer;
const #56 = Asciz	] ;
const #57 = String	#56;	//  ] 
const #58 = Asciz	next;
const #59 = Asciz	()Ljava/lang/Object;;
const #60 = NameAndType	#58:#59;//  next:()Ljava/lang/Object;
const #61 = InterfaceMethod	#32.#60;	//  scala/collection/Iterator.next:()Ljava/lang/Object;
const #62 = Asciz	);
const #63 = String	#62;	//  )
const #64 = Asciz	this;
const #65 = Asciz	Lscala/collection/script/Script;;
const #66 = Asciz	res;
const #67 = Asciz	Ljava/lang/String;;
const #68 = Asciz	it;
const #69 = Asciz	Lscala/collection/Iterator;;
const #70 = Asciz	i;
const #71 = Asciz	I;
const #72 = Asciz	LocalVariableTable;
const #73 = Asciz	<A:Ljava/lang/Object;>Lscala/collection/mutable/ArrayBuffer<Lscala/collection/script/Message<TA;>;>;Lscala/collection/script/Message<TA;>;Lscala/ScalaObject;;
const #74 = Asciz	ScalaSig;
const #75 = Asciz	scala/collection/script/Script;
const #76 = class	#75;	//  scala/collection/script/Script
const #77 = Asciz	scala/collection/script/Message;
const #78 = class	#77;	//  scala/collection/script/Message
const #79 = Asciz	scala/ScalaObject;
const #80 = class	#79;	//  scala/ScalaObject

{
public scala.collection.script.Script();
  Code:
   Stack=1, Locals=1, Args_size=1
   0:	aload_0
   1:	invokespecial	#10; //Method scala/collection/mutable/ArrayBuffer."<init>":()V
   4:	return
  LineNumberTable: 
   line 72: 0

  Signature: length = 0x2
   00 04 

public int hashCode();
  Code:
   Stack=3, Locals=1, Args_size=1
   0:	new	#15; //class java/lang/UnsupportedOperationException
   3:	dup
   4:	ldc	#17; //String scripts are not suitable as hash keys
   6:	invokespecial	#20; //Method java/lang/UnsupportedOperationException."<init>":(Ljava/lang/String;)V
   9:	athrow
  LineNumberTable: 
   line 88: 0


public java.lang.String toString();
  Code:
   Stack=2, Locals=4, Args_size=1
   0:	ldc	#24; //String Script(
   2:	astore_1
   3:	aload_0
   4:	invokeinterface	#30,  1; //InterfaceMethod scala/collection/generic/VectorTemplate.iterator:()Lscala/collection/Iterator;
   9:	astore_2
   10:	iconst_1
   11:	istore_3
   12:	aload_2
   13:	invokeinterface	#36,  1; //InterfaceMethod scala/collection/Iterator.hasNext:()Z
   18:	ifeq	94
   21:	iload_3
   22:	iconst_1
   23:	if_icmple	46
   26:	new	#38; //class scala/collection/mutable/StringBuilder
   29:	dup
   30:	invokespecial	#39; //Method scala/collection/mutable/StringBuilder."<init>":()V
   33:	aload_1
   34:	invokevirtual	#43; //Method scala/collection/mutable/StringBuilder.append:(Ljava/lang/Object;)Lscala/collection/mutable/StringBuilder;
   37:	ldc	#45; //String , 
   39:	invokevirtual	#43; //Method scala/collection/mutable/StringBuilder.append:(Ljava/lang/Object;)Lscala/collection/mutable/StringBuilder;
   42:	invokevirtual	#47; //Method scala/collection/mutable/StringBuilder.toString:()Ljava/lang/String;
   45:	astore_1
   46:	new	#38; //class scala/collection/mutable/StringBuilder
   49:	dup
   50:	invokespecial	#39; //Method scala/collection/mutable/StringBuilder."<init>":()V
   53:	aload_1
   54:	invokevirtual	#43; //Method scala/collection/mutable/StringBuilder.append:(Ljava/lang/Object;)Lscala/collection/mutable/StringBuilder;
   57:	ldc	#49; //String [
   59:	invokevirtual	#43; //Method scala/collection/mutable/StringBuilder.append:(Ljava/lang/Object;)Lscala/collection/mutable/StringBuilder;
   62:	iload_3
   63:	invokestatic	#55; //Method scala/runtime/BoxesRunTime.boxToInteger:(I)Ljava/lang/Integer;
   66:	invokevirtual	#43; //Method scala/collection/mutable/StringBuilder.append:(Ljava/lang/Object;)Lscala/collection/mutable/StringBuilder;
   69:	ldc	#57; //String ] 
   71:	invokevirtual	#43; //Method scala/collection/mutable/StringBuilder.append:(Ljava/lang/Object;)Lscala/collection/mutable/StringBuilder;
   74:	aload_2
   75:	invokeinterface	#61,  1; //InterfaceMethod scala/collection/Iterator.next:()Ljava/lang/Object;
   80:	invokevirtual	#43; //Method scala/collection/mutable/StringBuilder.append:(Ljava/lang/Object;)Lscala/collection/mutable/StringBuilder;
   83:	invokevirtual	#47; //Method scala/collection/mutable/StringBuilder.toString:()Ljava/lang/String;
   86:	astore_1
   87:	iload_3
   88:	iconst_1
   89:	iadd
   90:	istore_3
   91:	goto	12
   94:	new	#38; //class scala/collection/mutable/StringBuilder
   97:	dup
   98:	invokespecial	#39; //Method scala/collection/mutable/StringBuilder."<init>":()V
   101:	aload_1
   102:	invokevirtual	#43; //Method scala/collection/mutable/StringBuilder.append:(Ljava/lang/Object;)Lscala/collection/mutable/StringBuilder;
   105:	ldc	#63; //String )
   107:	invokevirtual	#43; //Method scala/collection/mutable/StringBuilder.append:(Ljava/lang/Object;)Lscala/collection/mutable/StringBuilder;
   110:	invokevirtual	#47; //Method scala/collection/mutable/StringBuilder.toString:()Ljava/lang/String;
   113:	areturn
  LineNumberTable: 
   line 75: 0
   line 76: 3
   line 77: 10
   line 78: 12
   line 79: 21
   line 80: 26
   line 81: 46
   line 82: 87
   line 78: 91
   line 84: 94

  LocalVariableTable: 
   Start  Length  Slot  Name   Signature
   0      114      0    this       Lscala/collection/script/Script;
   3      110      1    res       Ljava/lang/String;
   10      103      2    it       Lscala/collection/Iterator;
   12      101      3    i       I


}

