Compiled from "Location.scala"
public final class scala.collection.script.Start extends java.lang.Object
  SourceFile: "Location.scala"
  ScalaSig: length = 0x3
   05 00 00 
  RuntimeVisibleAnnotations: length = 0xB
   00 01 00 27 00 01 00 28 73 00 29 
  minor version: 0
  major version: 49
  Constant pool:
Asciz	SourceFile;
Asciz	Location.scala;
Asciz	productElements;
Asciz	()Lscala/collection/Iterator;;
Asciz	Code;
Asciz	scala/collection/script/Start$;
class	scala/collection/script/Start$
Asciz	MODULE$;
Asciz	Lscala/collection/script/Start$;;
NameAndType	MODULE$:Lscala/collection/script/Start$;
Field	scala/collection/script/Start$.MODULE$:Lscala/collection/script/Start$;
NameAndType	productElements:()Lscala/collection/Iterator;
Method	scala/collection/script/Start$.productElements:()Lscala/collection/Iterator;
Asciz	Deprecated;
Asciz	productIterator;
NameAndType	productIterator:()Lscala/collection/Iterator;
Method	scala/collection/script/Start$.productIterator:()Lscala/collection/Iterator;
Asciz	productElementName;
Asciz	(I)Ljava/lang/String;;
NameAndType	productElementName:(I)Ljava/lang/String;
Method	scala/collection/script/Start$.productElementName:(I)Ljava/lang/String;
Asciz	canEqual;
Asciz	(Ljava/lang/Object;)Z;
NameAndType	canEqual:(Ljava/lang/Object;)Z
Method	scala/collection/script/Start$.canEqual:(Ljava/lang/Object;)Z
Asciz	productElement;
Asciz	(I)Ljava/lang/Object;;
NameAndType	productElement:(I)Ljava/lang/Object;
Method	scala/collection/script/Start$.productElement:(I)Ljava/lang/Object;
Asciz	productArity;
Asciz	()I;
NameAndType	productArity:()I
Method	scala/collection/script/Start$.productArity:()I
Asciz	productPrefix;
Asciz	()Ljava/lang/String;;
NameAndType	productPrefix:()Ljava/lang/String;
Method	scala/collection/script/Start$.productPrefix:()Ljava/lang/String;
Asciz	ScalaSig;
Asciz	Lscala/reflect/ScalaSignature;;
Asciz	bytes;
Asciz	!;Q!\t&\tQa;beRT!a\rM'/9u\t)a!d_2dWm;j_:TaBgG.Y!\tQ1\"D\r!a!\"Ak!!B*uCJ$8B#U\"AC\nA!'pG$n8IR\"\nQ1!aC*dC2wJ6fGR\"A\n]1!a)s_,8\r3-!\tAGy%t %AH%)%H\ti>FO]5oOR\ta I5\tE\"E!A.8h6bmL!!\n\rM#(/8h!93\"A\nB!9s_,8\r)sKL0F!Q3\"A\nZ9s_,8\r^!sSRLX#IiB\rIe\ta-!\t!C!cqO]8ek$X\t\3nK:$HC6!\t2'5\r\tI\=\tYz!aYJ\taZA!ABe\nbY1oF,\ruu\"AE\nq2!a\"p_2,Mm]\n\t13!y4\"A\n#a:fCVm]8mm$!\t?\tK!a\r='.Z2uQ\tYQ\t\r&qI\rg.7juG.;
Asciz	RuntimeVisibleAnnotations;
Asciz	scala/collection/script/Start;
class	scala/collection/script/Start
Asciz	java/lang/Object;
class	java/lang/Object

{
public static final scala.collection.Iterator productElements();
  Signature: ()Lscala/collection/Iterator;
  Code:
   Stack=1, Locals=0, Args_size=0
	getstatic	Field scala/collection/script/Start$.MODULE$:Lscala/collection/script/Start$;
	invokevirtual	Method scala/collection/script/Start$.productElements:()Lscala/collection/Iterator;
	areturn
  Labels:
  Deprecated: true

public static final scala.collection.Iterator productIterator();
  Signature: ()Lscala/collection/Iterator;
  Code:
   Stack=1, Locals=0, Args_size=0
	getstatic	Field scala/collection/script/Start$.MODULE$:Lscala/collection/script/Start$;
	invokevirtual	Method scala/collection/script/Start$.productIterator:()Lscala/collection/Iterator;
	areturn
  Labels:

public static final java.lang.String productElementName(int);
  Signature: (I)Ljava/lang/String;
  Code:
   Stack=2, Locals=1, Args_size=1
	getstatic	Field scala/collection/script/Start$.MODULE$:Lscala/collection/script/Start$;
	iload_0
	invokevirtual	Method scala/collection/script/Start$.productElementName:(I)Ljava/lang/String;
	areturn
  Labels:

public static final boolean canEqual(java.lang.Object);
  Signature: (Ljava/lang/Object;)Z
  Code:
   Stack=2, Locals=1, Args_size=1
	getstatic	Field scala/collection/script/Start$.MODULE$:Lscala/collection/script/Start$;
	aload_0
	invokevirtual	Method scala/collection/script/Start$.canEqual:(Ljava/lang/Object;)Z
	ireturn
  Labels:

public static final java.lang.Object productElement(int);
  Signature: (I)Ljava/lang/Object;
  Code:
   Stack=2, Locals=1, Args_size=1
	getstatic	Field scala/collection/script/Start$.MODULE$:Lscala/collection/script/Start$;
	iload_0
	invokevirtual	Method scala/collection/script/Start$.productElement:(I)Ljava/lang/Object;
	areturn
  Labels:

public static final int productArity();
  Signature: ()I
  Code:
   Stack=1, Locals=0, Args_size=0
	getstatic	Field scala/collection/script/Start$.MODULE$:Lscala/collection/script/Start$;
	invokevirtual	Method scala/collection/script/Start$.productArity:()I
	ireturn
  Labels:

public static final java.lang.String productPrefix();
  Signature: ()Ljava/lang/String;
  Code:
   Stack=1, Locals=0, Args_size=0
	getstatic	Field scala/collection/script/Start$.MODULE$:Lscala/collection/script/Start$;
	invokevirtual	Method scala/collection/script/Start$.productPrefix:()Ljava/lang/String;
	areturn
  Labels:

}

