Compiled from "BigDecimal.scala"
public final class scala.math.BigDecimal$RoundingMode$ extends scala.Enumeration implements scala.ScalaObject,java.io.Serializable
  SourceFile: "BigDecimal.scala"
  Scala: length = 0x
   
  InnerClass: 
   public abstract #83= #107 of #77; //Value=class scala/Enumeration$Value of class scala/Enumeration
   public final #108= #42 of #10; //$anonfun$$init$$1=class scala/math/BigDecimal$RoundingMode$$anonfun$$init$$1 of class scala/math/BigDecimal$RoundingMode$
  minor version: 0
  major version: 49
  Constant pool:
const #1 = Asciz	SourceFile;
const #2 = Asciz	BigDecimal.scala;
const #3 = Asciz	Scala;
const #4 = Asciz	MODULE$;
const #5 = Asciz	Lscala/math/BigDecimal$RoundingMode$;;
const #6 = Asciz	<clinit>;
const #7 = Asciz	()V;
const #8 = Asciz	Code;
const #9 = Asciz	scala/math/BigDecimal$RoundingMode$;
const #10 = class	#9;	//  scala/math/BigDecimal$RoundingMode$
const #11 = Asciz	<init>;
const #12 = NameAndType	#11:#7;//  "<init>":()V
const #13 = Method	#10.#12;	//  scala/math/BigDecimal$RoundingMode$."<init>":()V
const #14 = Asciz	UNNECESSARY;
const #15 = Asciz	Lscala/Enumeration$Value;;
const #16 = Asciz	HALF_EVEN;
const #17 = Asciz	HALF_DOWN;
const #18 = Asciz	HALF_UP;
const #19 = Asciz	FLOOR;
const #20 = Asciz	CEILING;
const #21 = Asciz	DOWN;
const #22 = Asciz	UP;
const #23 = Asciz	LineNumberTable;
const #24 = Asciz	scala/Predef$;
const #25 = class	#24;	//  scala/Predef$
const #26 = Asciz	Lscala/Predef$;;
const #27 = NameAndType	#4:#26;//  MODULE$:Lscala/Predef$;
const #28 = Field	#25.#27;	//  scala/Predef$.MODULE$:Lscala/Predef$;
const #29 = Asciz	java/math/RoundingMode;
const #30 = class	#29;	//  java/math/RoundingMode
const #31 = Asciz	values;
const #32 = Asciz	()[Ljava/math/RoundingMode;;
const #33 = NameAndType	#31:#32;//  values:()[Ljava/math/RoundingMode;
const #34 = Method	#30.#33;	//  java/math/RoundingMode.values:()[Ljava/math/RoundingMode;
const #35 = Asciz	[Ljava/lang/Object;;
const #36 = class	#35;	//  "[Ljava/lang/Object;"
const #37 = Asciz	refArrayOps;
const #38 = Asciz	([Ljava/lang/Object;)Lscala/collection/mutable/ArrayOps;;
const #39 = NameAndType	#37:#38;//  refArrayOps:([Ljava/lang/Object;)Lscala/collection/mutable/ArrayOps;
const #40 = Method	#25.#39;	//  scala/Predef$.refArrayOps:([Ljava/lang/Object;)Lscala/collection/mutable/ArrayOps;
const #41 = Asciz	scala/math/BigDecimal$RoundingMode$$anonfun$$init$$1;
const #42 = class	#41;	//  scala/math/BigDecimal$RoundingMode$$anonfun$$init$$1
const #43 = Method	#42.#12;	//  scala/math/BigDecimal$RoundingMode$$anonfun$$init$$1."<init>":()V
const #44 = Asciz	scala/Array$;
const #45 = class	#44;	//  scala/Array$
const #46 = Asciz	Lscala/Array$;;
const #47 = NameAndType	#4:#46;//  MODULE$:Lscala/Array$;
const #48 = Field	#45.#47;	//  scala/Array$.MODULE$:Lscala/Array$;
const #49 = Asciz	scala/reflect/ClassManifest$;
const #50 = class	#49;	//  scala/reflect/ClassManifest$
const #51 = Asciz	Lscala/reflect/ClassManifest$;;
const #52 = NameAndType	#4:#51;//  MODULE$:Lscala/reflect/ClassManifest$;
const #53 = Field	#50.#52;	//  scala/reflect/ClassManifest$.MODULE$:Lscala/reflect/ClassManifest$;
const #54 = Asciz	java/lang/String;
const #55 = class	#54;	//  java/lang/String
const #56 = Asciz	classType;
const #57 = Asciz	(Ljava/lang/Class;)Lscala/reflect/ClassManifest;;
const #58 = NameAndType	#56:#57;//  classType:(Ljava/lang/Class;)Lscala/reflect/ClassManifest;
const #59 = Method	#50.#58;	//  scala/reflect/ClassManifest$.classType:(Ljava/lang/Class;)Lscala/reflect/ClassManifest;
const #60 = Asciz	canBuildFrom;
const #61 = Asciz	(Lscala/reflect/ClassManifest;)Lscala/collection/generic/CanBuildFrom;;
const #62 = NameAndType	#60:#61;//  canBuildFrom:(Lscala/reflect/ClassManifest;)Lscala/collection/generic/CanBuildFrom;
const #63 = Method	#45.#62;	//  scala/Array$.canBuildFrom:(Lscala/reflect/ClassManifest;)Lscala/collection/generic/CanBuildFrom;
const #64 = Asciz	scala/collection/TraversableLike;
const #65 = class	#64;	//  scala/collection/TraversableLike
const #66 = Asciz	map;
const #67 = Asciz	(Lscala/Function1;Lscala/collection/generic/CanBuildFrom;)Ljava/lang/Object;;
const #68 = NameAndType	#66:#67;//  map:(Lscala/Function1;Lscala/collection/generic/CanBuildFrom;)Ljava/lang/Object;
const #69 = InterfaceMethod	#65.#68;	//  scala/collection/TraversableLike.map:(Lscala/Function1;Lscala/collection/generic/CanBuildFrom;)Ljava/lang/Object;
const #70 = Asciz	[Ljava/lang/String;;
const #71 = class	#70;	//  "[Ljava/lang/String;"
const #72 = Asciz	wrapRefArray;
const #73 = Asciz	([Ljava/lang/Object;)Lscala/collection/mutable/WrappedArray;;
const #74 = NameAndType	#72:#73;//  wrapRefArray:([Ljava/lang/Object;)Lscala/collection/mutable/WrappedArray;
const #75 = Method	#25.#74;	//  scala/Predef$.wrapRefArray:([Ljava/lang/Object;)Lscala/collection/mutable/WrappedArray;
const #76 = Asciz	scala/Enumeration;
const #77 = class	#76;	//  scala/Enumeration
const #78 = Asciz	(Lscala/collection/Seq;)V;
const #79 = NameAndType	#11:#78;//  "<init>":(Lscala/collection/Seq;)V
const #80 = Method	#77.#79;	//  scala/Enumeration."<init>":(Lscala/collection/Seq;)V
const #81 = NameAndType	#4:#5;//  MODULE$:Lscala/math/BigDecimal$RoundingMode$;
const #82 = Field	#10.#81;	//  scala/math/BigDecimal$RoundingMode$.MODULE$:Lscala/math/BigDecimal$RoundingMode$;
const #83 = Asciz	Value;
const #84 = Asciz	()Lscala/Enumeration$Value;;
const #85 = NameAndType	#83:#84;//  Value:()Lscala/Enumeration$Value;
const #86 = Method	#10.#85;	//  scala/math/BigDecimal$RoundingMode$.Value:()Lscala/Enumeration$Value;
const #87 = NameAndType	#22:#15;//  UP:Lscala/Enumeration$Value;
const #88 = Field	#10.#87;	//  scala/math/BigDecimal$RoundingMode$.UP:Lscala/Enumeration$Value;
const #89 = NameAndType	#21:#15;//  DOWN:Lscala/Enumeration$Value;
const #90 = Field	#10.#89;	//  scala/math/BigDecimal$RoundingMode$.DOWN:Lscala/Enumeration$Value;
const #91 = NameAndType	#20:#15;//  CEILING:Lscala/Enumeration$Value;
const #92 = Field	#10.#91;	//  scala/math/BigDecimal$RoundingMode$.CEILING:Lscala/Enumeration$Value;
const #93 = NameAndType	#19:#15;//  FLOOR:Lscala/Enumeration$Value;
const #94 = Field	#10.#93;	//  scala/math/BigDecimal$RoundingMode$.FLOOR:Lscala/Enumeration$Value;
const #95 = NameAndType	#18:#15;//  HALF_UP:Lscala/Enumeration$Value;
const #96 = Field	#10.#95;	//  scala/math/BigDecimal$RoundingMode$.HALF_UP:Lscala/Enumeration$Value;
const #97 = NameAndType	#17:#15;//  HALF_DOWN:Lscala/Enumeration$Value;
const #98 = Field	#10.#97;	//  scala/math/BigDecimal$RoundingMode$.HALF_DOWN:Lscala/Enumeration$Value;
const #99 = NameAndType	#16:#15;//  HALF_EVEN:Lscala/Enumeration$Value;
const #100 = Field	#10.#99;	//  scala/math/BigDecimal$RoundingMode$.HALF_EVEN:Lscala/Enumeration$Value;
const #101 = NameAndType	#14:#15;//  UNNECESSARY:Lscala/Enumeration$Value;
const #102 = Field	#10.#101;	//  scala/math/BigDecimal$RoundingMode$.UNNECESSARY:Lscala/Enumeration$Value;
const #103 = Asciz	readResolve;
const #104 = Asciz	()Ljava/lang/Object;;
const #105 = Asciz	InnerClasses;
const #106 = Asciz	scala/Enumeration$Value;
const #107 = class	#106;	//  scala/Enumeration$Value
const #108 = Asciz	$anonfun$$init$$1;
const #109 = Asciz	scala/ScalaObject;
const #110 = class	#109;	//  scala/ScalaObject
const #111 = Asciz	java/io/Serializable;
const #112 = class	#111;	//  java/io/Serializable

{
public static final scala.math.BigDecimal$RoundingMode$ MODULE$;

public static {};
  Code:
   Stack=1, Locals=0, Args_size=0
   0:	new	#10; //class scala/math/BigDecimal$RoundingMode$
   3:	invokespecial	#13; //Method "<init>":()V
   6:	return

public scala.math.BigDecimal$RoundingMode$();
  Code:
   Stack=7, Locals=1, Args_size=1
   0:	aload_0
   1:	getstatic	#28; //Field scala/Predef$.MODULE$:Lscala/Predef$;
   4:	getstatic	#28; //Field scala/Predef$.MODULE$:Lscala/Predef$;
   7:	invokestatic	#34; //Method java/math/RoundingMode.values:()[Ljava/math/RoundingMode;
   10:	checkcast	#36; //class "[Ljava/lang/Object;"
   13:	invokevirtual	#40; //Method scala/Predef$.refArrayOps:([Ljava/lang/Object;)Lscala/collection/mutable/ArrayOps;
   16:	new	#42; //class scala/math/BigDecimal$RoundingMode$$anonfun$$init$$1
   19:	dup
   20:	invokespecial	#43; //Method scala/math/BigDecimal$RoundingMode$$anonfun$$init$$1."<init>":()V
   23:	getstatic	#48; //Field scala/Array$.MODULE$:Lscala/Array$;
   26:	getstatic	#53; //Field scala/reflect/ClassManifest$.MODULE$:Lscala/reflect/ClassManifest$;
   29:	ldc	#55; //class java/lang/String
   31:	invokevirtual	#59; //Method scala/reflect/ClassManifest$.classType:(Ljava/lang/Class;)Lscala/reflect/ClassManifest;
   34:	invokevirtual	#63; //Method scala/Array$.canBuildFrom:(Lscala/reflect/ClassManifest;)Lscala/collection/generic/CanBuildFrom;
   37:	invokeinterface	#69,  3; //InterfaceMethod scala/collection/TraversableLike.map:(Lscala/Function1;Lscala/collection/generic/CanBuildFrom;)Ljava/lang/Object;
   42:	checkcast	#71; //class "[Ljava/lang/String;"
   45:	checkcast	#36; //class "[Ljava/lang/Object;"
   48:	invokevirtual	#75; //Method scala/Predef$.wrapRefArray:([Ljava/lang/Object;)Lscala/collection/mutable/WrappedArray;
   51:	invokespecial	#80; //Method scala/Enumeration."<init>":(Lscala/collection/Seq;)V
   54:	aload_0
   55:	putstatic	#82; //Field MODULE$:Lscala/math/BigDecimal$RoundingMode$;
   58:	aload_0
   59:	aload_0
   60:	invokevirtual	#86; //Method Value:()Lscala/Enumeration$Value;
   63:	putfield	#88; //Field UP:Lscala/Enumeration$Value;
   66:	aload_0
   67:	aload_0
   68:	invokevirtual	#86; //Method Value:()Lscala/Enumeration$Value;
   71:	putfield	#90; //Field DOWN:Lscala/Enumeration$Value;
   74:	aload_0
   75:	aload_0
   76:	invokevirtual	#86; //Method Value:()Lscala/Enumeration$Value;
   79:	putfield	#92; //Field CEILING:Lscala/Enumeration$Value;
   82:	aload_0
   83:	aload_0
   84:	invokevirtual	#86; //Method Value:()Lscala/Enumeration$Value;
   87:	putfield	#94; //Field FLOOR:Lscala/Enumeration$Value;
   90:	aload_0
   91:	aload_0
   92:	invokevirtual	#86; //Method Value:()Lscala/Enumeration$Value;
   95:	putfield	#96; //Field HALF_UP:Lscala/Enumeration$Value;
   98:	aload_0
   99:	aload_0
   100:	invokevirtual	#86; //Method Value:()Lscala/Enumeration$Value;
   103:	putfield	#98; //Field HALF_DOWN:Lscala/Enumeration$Value;
   106:	aload_0
   107:	aload_0
   108:	invokevirtual	#86; //Method Value:()Lscala/Enumeration$Value;
   111:	putfield	#100; //Field HALF_EVEN:Lscala/Enumeration$Value;
   114:	aload_0
   115:	aload_0
   116:	invokevirtual	#86; //Method Value:()Lscala/Enumeration$Value;
   119:	putfield	#102; //Field UNNECESSARY:Lscala/Enumeration$Value;
   122:	return
  LineNumberTable: 
   line 25: 0
   line 27: 58


public java.lang.Object readResolve();
  Code:
   Stack=1, Locals=1, Args_size=1
   0:	getstatic	#82; //Field MODULE$:Lscala/math/BigDecimal$RoundingMode$;
   3:	areturn
  LineNumberTable: 
   line 25: 0


public scala.Enumeration$Value UNNECESSARY();
  Code:
   Stack=1, Locals=1, Args_size=1
   0:	aload_0
   1:	getfield	#102; //Field UNNECESSARY:Lscala/Enumeration$Value;
   4:	areturn
  LineNumberTable: 
   line 27: 0


public scala.Enumeration$Value HALF_EVEN();
  Code:
   Stack=1, Locals=1, Args_size=1
   0:	aload_0
   1:	getfield	#100; //Field HALF_EVEN:Lscala/Enumeration$Value;
   4:	areturn
  LineNumberTable: 
   line 27: 0


public scala.Enumeration$Value HALF_DOWN();
  Code:
   Stack=1, Locals=1, Args_size=1
   0:	aload_0
   1:	getfield	#98; //Field HALF_DOWN:Lscala/Enumeration$Value;
   4:	areturn
  LineNumberTable: 
   line 27: 0


public scala.Enumeration$Value HALF_UP();
  Code:
   Stack=1, Locals=1, Args_size=1
   0:	aload_0
   1:	getfield	#96; //Field HALF_UP:Lscala/Enumeration$Value;
   4:	areturn
  LineNumberTable: 
   line 27: 0


public scala.Enumeration$Value FLOOR();
  Code:
   Stack=1, Locals=1, Args_size=1
   0:	aload_0
   1:	getfield	#94; //Field FLOOR:Lscala/Enumeration$Value;
   4:	areturn
  LineNumberTable: 
   line 27: 0


public scala.Enumeration$Value CEILING();
  Code:
   Stack=1, Locals=1, Args_size=1
   0:	aload_0
   1:	getfield	#92; //Field CEILING:Lscala/Enumeration$Value;
   4:	areturn
  LineNumberTable: 
   line 27: 0


public scala.Enumeration$Value DOWN();
  Code:
   Stack=1, Locals=1, Args_size=1
   0:	aload_0
   1:	getfield	#90; //Field DOWN:Lscala/Enumeration$Value;
   4:	areturn
  LineNumberTable: 
   line 27: 0


public scala.Enumeration$Value UP();
  Code:
   Stack=1, Locals=1, Args_size=1
   0:	aload_0
   1:	getfield	#88; //Field UP:Lscala/Enumeration$Value;
   4:	areturn
  LineNumberTable: 
   line 27: 0


}

