Compiled from "BigDecimal.scala"
public final class scala.math.BigDecimal$RoundingMode$ extends scala.Enumeration implements scala.ScalaObject,java.io.Serializable
  SourceFile: "BigDecimal.scala"
  Scala: length = 0x
   
  InnerClass: 
   public abstract Value=class scala/Enumeration$Value of class scala/Enumeration
   public final $anonfun$$init$$1=class scala/math/BigDecimal$RoundingMode$$anonfun$$init$$1 of class scala/math/BigDecimal$RoundingMode$
  minor version: 0
  major version: 49
  Constant pool:
Asciz	SourceFile;
Asciz	BigDecimal.scala;
Asciz	Scala;
Asciz	MODULE$;
Asciz	Lscala/math/BigDecimal$RoundingMode$;;
Asciz	<clinit>;
Asciz	()V;
Asciz	Code;
Asciz	scala/math/BigDecimal$RoundingMode$;
class	scala/math/BigDecimal$RoundingMode$
Asciz	<init>;
NameAndType	"<init>":()V
Method	scala/math/BigDecimal$RoundingMode$."<init>":()V
Asciz	UNNECESSARY;
Asciz	Lscala/Enumeration$Value;;
Asciz	HALF_EVEN;
Asciz	HALF_DOWN;
Asciz	HALF_UP;
Asciz	FLOOR;
Asciz	CEILING;
Asciz	DOWN;
Asciz	UP;
Asciz	LineNumberTable;
Asciz	scala/Predef$;
class	scala/Predef$
Asciz	Lscala/Predef$;;
NameAndType	MODULE$:Lscala/Predef$;
Field	scala/Predef$.MODULE$:Lscala/Predef$;
Asciz	java/math/RoundingMode;
class	java/math/RoundingMode
Asciz	values;
Asciz	()[Ljava/math/RoundingMode;;
NameAndType	values:()[Ljava/math/RoundingMode;
Method	java/math/RoundingMode.values:()[Ljava/math/RoundingMode;
Asciz	[Ljava/lang/Object;;
class	"[Ljava/lang/Object;"
Asciz	refArrayOps;
Asciz	([Ljava/lang/Object;)Lscala/collection/mutable/ArrayOps;;
NameAndType	refArrayOps:([Ljava/lang/Object;)Lscala/collection/mutable/ArrayOps;
Method	scala/Predef$.refArrayOps:([Ljava/lang/Object;)Lscala/collection/mutable/ArrayOps;
Asciz	scala/math/BigDecimal$RoundingMode$$anonfun$$init$$1;
class	scala/math/BigDecimal$RoundingMode$$anonfun$$init$$1
Method	scala/math/BigDecimal$RoundingMode$$anonfun$$init$$1."<init>":()V
Asciz	scala/Array$;
class	scala/Array$
Asciz	Lscala/Array$;;
NameAndType	MODULE$:Lscala/Array$;
Field	scala/Array$.MODULE$:Lscala/Array$;
Asciz	scala/reflect/ClassManifest$;
class	scala/reflect/ClassManifest$
Asciz	Lscala/reflect/ClassManifest$;;
NameAndType	MODULE$:Lscala/reflect/ClassManifest$;
Field	scala/reflect/ClassManifest$.MODULE$:Lscala/reflect/ClassManifest$;
Asciz	java/lang/String;
class	java/lang/String
Asciz	classType;
Asciz	(Ljava/lang/Class;)Lscala/reflect/ClassManifest;;
NameAndType	classType:(Ljava/lang/Class;)Lscala/reflect/ClassManifest;
Method	scala/reflect/ClassManifest$.classType:(Ljava/lang/Class;)Lscala/reflect/ClassManifest;
Asciz	canBuildFrom;
Asciz	(Lscala/reflect/ClassManifest;)Lscala/collection/generic/CanBuildFrom;;
NameAndType	canBuildFrom:(Lscala/reflect/ClassManifest;)Lscala/collection/generic/CanBuildFrom;
Method	scala/Array$.canBuildFrom:(Lscala/reflect/ClassManifest;)Lscala/collection/generic/CanBuildFrom;
Asciz	scala/collection/TraversableLike;
class	scala/collection/TraversableLike
Asciz	map;
Asciz	(Lscala/Function1;Lscala/collection/generic/CanBuildFrom;)Ljava/lang/Object;;
NameAndType	map:(Lscala/Function1;Lscala/collection/generic/CanBuildFrom;)Ljava/lang/Object;
InterfaceMethod	scala/collection/TraversableLike.map:(Lscala/Function1;Lscala/collection/generic/CanBuildFrom;)Ljava/lang/Object;
Asciz	[Ljava/lang/String;;
class	"[Ljava/lang/String;"
Asciz	wrapRefArray;
Asciz	([Ljava/lang/Object;)Lscala/collection/mutable/WrappedArray;;
NameAndType	wrapRefArray:([Ljava/lang/Object;)Lscala/collection/mutable/WrappedArray;
Method	scala/Predef$.wrapRefArray:([Ljava/lang/Object;)Lscala/collection/mutable/WrappedArray;
Asciz	scala/Enumeration;
class	scala/Enumeration
Asciz	(Lscala/collection/Seq;)V;
NameAndType	"<init>":(Lscala/collection/Seq;)V
Method	scala/Enumeration."<init>":(Lscala/collection/Seq;)V
NameAndType	MODULE$:Lscala/math/BigDecimal$RoundingMode$;
Field	scala/math/BigDecimal$RoundingMode$.MODULE$:Lscala/math/BigDecimal$RoundingMode$;
Asciz	Value;
Asciz	()Lscala/Enumeration$Value;;
NameAndType	Value:()Lscala/Enumeration$Value;
Method	scala/math/BigDecimal$RoundingMode$.Value:()Lscala/Enumeration$Value;
NameAndType	UP:Lscala/Enumeration$Value;
Field	scala/math/BigDecimal$RoundingMode$.UP:Lscala/Enumeration$Value;
NameAndType	DOWN:Lscala/Enumeration$Value;
Field	scala/math/BigDecimal$RoundingMode$.DOWN:Lscala/Enumeration$Value;
NameAndType	CEILING:Lscala/Enumeration$Value;
Field	scala/math/BigDecimal$RoundingMode$.CEILING:Lscala/Enumeration$Value;
NameAndType	FLOOR:Lscala/Enumeration$Value;
Field	scala/math/BigDecimal$RoundingMode$.FLOOR:Lscala/Enumeration$Value;
NameAndType	HALF_UP:Lscala/Enumeration$Value;
Field	scala/math/BigDecimal$RoundingMode$.HALF_UP:Lscala/Enumeration$Value;
NameAndType	HALF_DOWN:Lscala/Enumeration$Value;
Field	scala/math/BigDecimal$RoundingMode$.HALF_DOWN:Lscala/Enumeration$Value;
NameAndType	HALF_EVEN:Lscala/Enumeration$Value;
Field	scala/math/BigDecimal$RoundingMode$.HALF_EVEN:Lscala/Enumeration$Value;
NameAndType	UNNECESSARY:Lscala/Enumeration$Value;
Field	scala/math/BigDecimal$RoundingMode$.UNNECESSARY:Lscala/Enumeration$Value;
Asciz	readResolve;
Asciz	()Ljava/lang/Object;;
Asciz	InnerClasses;
Asciz	scala/Enumeration$Value;
class	scala/Enumeration$Value
Asciz	$anonfun$$init$$1;
Asciz	scala/ScalaObject;
class	scala/ScalaObject
Asciz	java/io/Serializable;
class	java/io/Serializable

{
public static final scala.math.BigDecimal$RoundingMode$ MODULE$;
  Signature: Lscala/math/BigDecimal$RoundingMode$;

private final scala.Enumeration$Value UNNECESSARY;
  Signature: Lscala/Enumeration$Value;

private final scala.Enumeration$Value HALF_EVEN;
  Signature: Lscala/Enumeration$Value;

private final scala.Enumeration$Value HALF_DOWN;
  Signature: Lscala/Enumeration$Value;

private final scala.Enumeration$Value HALF_UP;
  Signature: Lscala/Enumeration$Value;

private final scala.Enumeration$Value FLOOR;
  Signature: Lscala/Enumeration$Value;

private final scala.Enumeration$Value CEILING;
  Signature: Lscala/Enumeration$Value;

private final scala.Enumeration$Value DOWN;
  Signature: Lscala/Enumeration$Value;

private final scala.Enumeration$Value UP;
  Signature: Lscala/Enumeration$Value;

public static {};
  Signature: ()V
  Code:
   Stack=1, Locals=0, Args_size=0
	new	class scala/math/BigDecimal$RoundingMode$
	invokespecial	Method "<init>":()V
	return
  Labels:

public scala.math.BigDecimal$RoundingMode$();
  Signature: ()V
  Code:
   Stack=7, Locals=1, Args_size=1
	aload_0
	getstatic	Field scala/Predef$.MODULE$:Lscala/Predef$;
	getstatic	Field scala/Predef$.MODULE$:Lscala/Predef$;
	invokestatic	Method java/math/RoundingMode.values:()[Ljava/math/RoundingMode;
	checkcast	class "[Ljava/lang/Object;"
	invokevirtual	Method scala/Predef$.refArrayOps:([Ljava/lang/Object;)Lscala/collection/mutable/ArrayOps;
	new	class scala/math/BigDecimal$RoundingMode$$anonfun$$init$$1
	dup
	invokespecial	Method scala/math/BigDecimal$RoundingMode$$anonfun$$init$$1."<init>":()V
	getstatic	Field scala/Array$.MODULE$:Lscala/Array$;
	getstatic	Field scala/reflect/ClassManifest$.MODULE$:Lscala/reflect/ClassManifest$;
	ldc	class java/lang/String
	invokevirtual	Method scala/reflect/ClassManifest$.classType:(Ljava/lang/Class;)Lscala/reflect/ClassManifest;
	invokevirtual	Method scala/Array$.canBuildFrom:(Lscala/reflect/ClassManifest;)Lscala/collection/generic/CanBuildFrom;
	invokeinterface	InterfaceMethod scala/collection/TraversableLike.map:(Lscala/Function1;Lscala/collection/generic/CanBuildFrom;)Ljava/lang/Object;
	checkcast	class "[Ljava/lang/String;"
	checkcast	class "[Ljava/lang/Object;"
	invokevirtual	Method scala/Predef$.wrapRefArray:([Ljava/lang/Object;)Lscala/collection/mutable/WrappedArray;
	invokespecial	Method scala/Enumeration."<init>":(Lscala/collection/Seq;)V
	aload_0
	putstatic	Field MODULE$:Lscala/math/BigDecimal$RoundingMode$;
	aload_0
	aload_0
	invokevirtual	Method Value:()Lscala/Enumeration$Value;
	putfield	Field UP:Lscala/Enumeration$Value;
	aload_0
	aload_0
	invokevirtual	Method Value:()Lscala/Enumeration$Value;
	putfield	Field DOWN:Lscala/Enumeration$Value;
	aload_0
	aload_0
	invokevirtual	Method Value:()Lscala/Enumeration$Value;
	putfield	Field CEILING:Lscala/Enumeration$Value;
	aload_0
	aload_0
	invokevirtual	Method Value:()Lscala/Enumeration$Value;
	putfield	Field FLOOR:Lscala/Enumeration$Value;
	aload_0
	aload_0
	invokevirtual	Method Value:()Lscala/Enumeration$Value;
	putfield	Field HALF_UP:Lscala/Enumeration$Value;
	aload_0
	aload_0
	invokevirtual	Method Value:()Lscala/Enumeration$Value;
	putfield	Field HALF_DOWN:Lscala/Enumeration$Value;
	aload_0
	aload_0
	invokevirtual	Method Value:()Lscala/Enumeration$Value;
	putfield	Field HALF_EVEN:Lscala/Enumeration$Value;
	aload_0
	aload_0
	invokevirtual	Method Value:()Lscala/Enumeration$Value;
	putfield	Field UNNECESSARY:Lscala/Enumeration$Value;
	return
  Labels:

public java.lang.Object readResolve();
  Signature: ()Ljava/lang/Object;
  Code:
   Stack=1, Locals=1, Args_size=1
	getstatic	Field MODULE$:Lscala/math/BigDecimal$RoundingMode$;
	areturn
  Labels:

public scala.Enumeration$Value UNNECESSARY();
  Signature: ()Lscala/Enumeration$Value;
  Code:
   Stack=1, Locals=1, Args_size=1
	aload_0
	getfield	Field UNNECESSARY:Lscala/Enumeration$Value;
	areturn
  Labels:

public scala.Enumeration$Value HALF_EVEN();
  Signature: ()Lscala/Enumeration$Value;
  Code:
   Stack=1, Locals=1, Args_size=1
	aload_0
	getfield	Field HALF_EVEN:Lscala/Enumeration$Value;
	areturn
  Labels:

public scala.Enumeration$Value HALF_DOWN();
  Signature: ()Lscala/Enumeration$Value;
  Code:
   Stack=1, Locals=1, Args_size=1
	aload_0
	getfield	Field HALF_DOWN:Lscala/Enumeration$Value;
	areturn
  Labels:

public scala.Enumeration$Value HALF_UP();
  Signature: ()Lscala/Enumeration$Value;
  Code:
   Stack=1, Locals=1, Args_size=1
	aload_0
	getfield	Field HALF_UP:Lscala/Enumeration$Value;
	areturn
  Labels:

public scala.Enumeration$Value FLOOR();
  Signature: ()Lscala/Enumeration$Value;
  Code:
   Stack=1, Locals=1, Args_size=1
	aload_0
	getfield	Field FLOOR:Lscala/Enumeration$Value;
	areturn
  Labels:

public scala.Enumeration$Value CEILING();
  Signature: ()Lscala/Enumeration$Value;
  Code:
   Stack=1, Locals=1, Args_size=1
	aload_0
	getfield	Field CEILING:Lscala/Enumeration$Value;
	areturn
  Labels:

public scala.Enumeration$Value DOWN();
  Signature: ()Lscala/Enumeration$Value;
  Code:
   Stack=1, Locals=1, Args_size=1
	aload_0
	getfield	Field DOWN:Lscala/Enumeration$Value;
	areturn
  Labels:

public scala.Enumeration$Value UP();
  Signature: ()Lscala/Enumeration$Value;
  Code:
   Stack=1, Locals=1, Args_size=1
	aload_0
	getfield	Field UP:Lscala/Enumeration$Value;
	areturn
  Labels:

}

