Compiled from "Fractional.scala"
public abstract class scala.math.Fractional$class extends java.lang.Object
  SourceFile: "Fractional.scala"
  Scala: length = 0x
   
  InnerClass: 
   public #24= #13 of #23; //FractionalOps=class scala/math/Fractional$FractionalOps of class scala/math/Fractional
  minor version: 0
  major version: 49
  Constant pool:
const #1 = Asciz	SourceFile;
const #2 = Asciz	Fractional.scala;
const #3 = Asciz	$init$;
const #4 = Asciz	(Lscala/math/Fractional;)V;
const #5 = Asciz	Code;
const #6 = Asciz	LineNumberTable;
const #7 = Asciz	$this;
const #8 = Asciz	Lscala/math/Fractional;;
const #9 = Asciz	LocalVariableTable;
const #10 = Asciz	mkNumericOps;
const #11 = Asciz	(Lscala/math/Fractional;Ljava/lang/Object;)Lscala/math/Fractional$FractionalOps;;
const #12 = Asciz	scala/math/Fractional$FractionalOps;
const #13 = class	#12;	//  scala/math/Fractional$FractionalOps
const #14 = Asciz	<init>;
const #15 = Asciz	(Lscala/math/Fractional;Ljava/lang/Object;)V;
const #16 = NameAndType	#14:#15;//  "<init>":(Lscala/math/Fractional;Ljava/lang/Object;)V
const #17 = Method	#13.#16;	//  scala/math/Fractional$FractionalOps."<init>":(Lscala/math/Fractional;Ljava/lang/Object;)V
const #18 = Asciz	lhs;
const #19 = Asciz	Ljava/lang/Object;;
const #20 = Asciz	Scala;
const #21 = Asciz	InnerClasses;
const #22 = Asciz	scala/math/Fractional;
const #23 = class	#22;	//  scala/math/Fractional
const #24 = Asciz	FractionalOps;
const #25 = Asciz	scala/math/Fractional$class;
const #26 = class	#25;	//  scala/math/Fractional$class
const #27 = Asciz	java/lang/Object;
const #28 = class	#27;	//  java/lang/Object

{
public static void $init$(scala.math.Fractional);
  Code:
   Stack=0, Locals=1, Args_size=1
   0:	return
  LineNumberTable: 
   line 17: 0

  LocalVariableTable: 
   Start  Length  Slot  Name   Signature
   0      1      0    $this       Lscala/math/Fractional;


public static scala.math.Fractional$FractionalOps mkNumericOps(scala.math.Fractional, java.lang.Object);
  Code:
   Stack=4, Locals=2, Args_size=2
   0:	new	#13; //class scala/math/Fractional$FractionalOps
   3:	dup
   4:	aload_0
   5:	aload_1
   6:	invokespecial	#17; //Method scala/math/Fractional$FractionalOps."<init>":(Lscala/math/Fractional;Ljava/lang/Object;)V
   9:	areturn
  LineNumberTable: 
   line 24: 0

  LocalVariableTable: 
   Start  Length  Slot  Name   Signature
   0      10      0    $this       Lscala/math/Fractional;
   0      10      1    lhs       Ljava/lang/Object;


}

