Compiled from "Integral.scala"
public abstract class scala.math.Integral$class extends java.lang.Object
  SourceFile: "Integral.scala"
  Scala: length = 0x
   
  InnerClass: 
   public #24= #13 of #23; //IntegralOps=class scala/math/Integral$IntegralOps of class scala/math/Integral
  minor version: 0
  major version: 49
  Constant pool:
const #1 = Asciz	SourceFile;
const #2 = Asciz	Integral.scala;
const #3 = Asciz	$init$;
const #4 = Asciz	(Lscala/math/Integral;)V;
const #5 = Asciz	Code;
const #6 = Asciz	LineNumberTable;
const #7 = Asciz	$this;
const #8 = Asciz	Lscala/math/Integral;;
const #9 = Asciz	LocalVariableTable;
const #10 = Asciz	mkNumericOps;
const #11 = Asciz	(Lscala/math/Integral;Ljava/lang/Object;)Lscala/math/Integral$IntegralOps;;
const #12 = Asciz	scala/math/Integral$IntegralOps;
const #13 = class	#12;	//  scala/math/Integral$IntegralOps
const #14 = Asciz	<init>;
const #15 = Asciz	(Lscala/math/Integral;Ljava/lang/Object;)V;
const #16 = NameAndType	#14:#15;//  "<init>":(Lscala/math/Integral;Ljava/lang/Object;)V
const #17 = Method	#13.#16;	//  scala/math/Integral$IntegralOps."<init>":(Lscala/math/Integral;Ljava/lang/Object;)V
const #18 = Asciz	lhs;
const #19 = Asciz	Ljava/lang/Object;;
const #20 = Asciz	Scala;
const #21 = Asciz	InnerClasses;
const #22 = Asciz	scala/math/Integral;
const #23 = class	#22;	//  scala/math/Integral
const #24 = Asciz	IntegralOps;
const #25 = Asciz	scala/math/Integral$class;
const #26 = class	#25;	//  scala/math/Integral$class
const #27 = Asciz	java/lang/Object;
const #28 = class	#27;	//  java/lang/Object

{
public static void $init$(scala.math.Integral);
  Code:
   Stack=0, Locals=1, Args_size=1
   0:	return
  LineNumberTable: 
   line 17: 0

  LocalVariableTable: 
   Start  Length  Slot  Name   Signature
   0      1      0    $this       Lscala/math/Integral;


public static scala.math.Integral$IntegralOps mkNumericOps(scala.math.Integral, java.lang.Object);
  Code:
   Stack=4, Locals=2, Args_size=2
   0:	new	#13; //class scala/math/Integral$IntegralOps
   3:	dup
   4:	aload_0
   5:	aload_1
   6:	invokespecial	#17; //Method scala/math/Integral$IntegralOps."<init>":(Lscala/math/Integral;Ljava/lang/Object;)V
   9:	areturn
  LineNumberTable: 
   line 26: 0

  LocalVariableTable: 
   Start  Length  Slot  Name   Signature
   0      10      0    $this       Lscala/math/Integral;
   0      10      1    lhs       Ljava/lang/Object;


}

