Compiled from "Ordering.scala"
public abstract class scala.math.LowPriorityOrderingImplicits$class extends java.lang.Object
  SourceFile: "Ordering.scala"
  Scala: length = 0x
   
  InnerClass: 
   public final #21= #13 of #20; //$anon$3=class scala/math/LowPriorityOrderingImplicits$$anon$3 of class scala/math/LowPriorityOrderingImplicits
  minor version: 0
  major version: 49
  Constant pool:
const #1 = Asciz	SourceFile;
const #2 = Asciz	Ordering.scala;
const #3 = Asciz	$init$;
const #4 = Asciz	(Lscala/math/LowPriorityOrderingImplicits;)V;
const #5 = Asciz	Code;
const #6 = Asciz	LineNumberTable;
const #7 = Asciz	$this;
const #8 = Asciz	Lscala/math/LowPriorityOrderingImplicits;;
const #9 = Asciz	LocalVariableTable;
const #10 = Asciz	ordered;
const #11 = Asciz	(Lscala/math/LowPriorityOrderingImplicits;)Lscala/math/Ordering;;
const #12 = Asciz	scala/math/LowPriorityOrderingImplicits$$anon$3;
const #13 = class	#12;	//  scala/math/LowPriorityOrderingImplicits$$anon$3
const #14 = Asciz	<init>;
const #15 = NameAndType	#14:#4;//  "<init>":(Lscala/math/LowPriorityOrderingImplicits;)V
const #16 = Method	#13.#15;	//  scala/math/LowPriorityOrderingImplicits$$anon$3."<init>":(Lscala/math/LowPriorityOrderingImplicits;)V
const #17 = Asciz	Scala;
const #18 = Asciz	InnerClasses;
const #19 = Asciz	scala/math/LowPriorityOrderingImplicits;
const #20 = class	#19;	//  scala/math/LowPriorityOrderingImplicits
const #21 = Asciz	$anon$3;
const #22 = Asciz	scala/math/LowPriorityOrderingImplicits$class;
const #23 = class	#22;	//  scala/math/LowPriorityOrderingImplicits$class
const #24 = Asciz	java/lang/Object;
const #25 = class	#24;	//  java/lang/Object

{
public static void $init$(scala.math.LowPriorityOrderingImplicits);
  Code:
   Stack=0, Locals=1, Args_size=1
   0:	return
  LineNumberTable: 
   line 117: 0

  LocalVariableTable: 
   Start  Length  Slot  Name   Signature
   0      1      0    $this       Lscala/math/LowPriorityOrderingImplicits;


public static scala.math.Ordering ordered(scala.math.LowPriorityOrderingImplicits);
  Code:
   Stack=3, Locals=1, Args_size=1
   0:	new	#13; //class scala/math/LowPriorityOrderingImplicits$$anon$3
   3:	dup
   4:	aload_0
   5:	invokespecial	#16; //Method scala/math/LowPriorityOrderingImplicits$$anon$3."<init>":(Lscala/math/LowPriorityOrderingImplicits;)V
   8:	areturn
  LineNumberTable: 
   line 118: 0

  LocalVariableTable: 
   Start  Length  Slot  Name   Signature
   0      9      0    $this       Lscala/math/LowPriorityOrderingImplicits;


}

