Compiled from "Numeric.scala"
public final class scala.math.Numeric$BigDecimalAsIfIntegral$ extends java.lang.Object implements scala.math.Numeric$BigDecimalAsIfIntegral,scala.math.Ordering$BigDecimalOrdering,scala.ScalaObject
  SourceFile: "Numeric.scala"
  Scala: length = 0x
   
  InnerClass: 
   public Ops=class scala/math/Numeric$Ops of class scala/math/Numeric
   public Ops=class scala/math/Ordering$Ops of class scala/math/Ordering
   public IntegralOps=class scala/math/Integral$IntegralOps of class scala/math/Integral
   public abstract BigDecimalOrdering=class scala/math/Ordering$BigDecimalOrdering of class scala/math/Ordering
   public abstract BigDecimalIsConflicted=class scala/math/Numeric$BigDecimalIsConflicted of class scala/math/Numeric
   public abstract BigDecimalAsIfIntegral=class scala/math/Numeric$BigDecimalAsIfIntegral of class scala/math/Numeric
  minor version: 0
  major version: 49
  Constant pool:
Asciz	SourceFile;
Asciz	Numeric.scala;
Asciz	MODULE$;
Asciz	Lscala/math/Numeric$BigDecimalAsIfIntegral$;;
Asciz	<clinit>;
Asciz	()V;
Asciz	Code;
Asciz	scala/math/Numeric$BigDecimalAsIfIntegral$;
class	scala/math/Numeric$BigDecimalAsIfIntegral$
Asciz	<init>;
NameAndType	"<init>":()V
Method	scala/math/Numeric$BigDecimalAsIfIntegral$."<init>":()V
Asciz	compare;
Asciz	(Lscala/math/BigDecimal;Lscala/math/BigDecimal;)I;
Asciz	LineNumberTable;
Asciz	scala/math/Ordering$BigDecimalOrdering$class;
class	scala/math/Ordering$BigDecimalOrdering$class
Asciz	(Lscala/math/Ordering$BigDecimalOrdering;Lscala/math/BigDecimal;Lscala/math/BigDecimal;)I;
NameAndType	compare:(Lscala/math/Ordering$BigDecimalOrdering;Lscala/math/BigDecimal;Lscala/math/BigDecimal;)I
Method	scala/math/Ordering$BigDecimalOrdering$class.compare:(Lscala/math/Ordering$BigDecimalOrdering;Lscala/math/BigDecimal;Lscala/math/BigDecimal;)I
Asciz	this;
Asciz	x;
Asciz	Lscala/math/BigDecimal;;
Asciz	y;
Asciz	LocalVariableTable;
Asciz	quot;
Asciz	(Lscala/math/BigDecimal;Lscala/math/BigDecimal;)Lscala/math/BigDecimal;;
Asciz	scala/math/Numeric$BigDecimalAsIfIntegral$class;
class	scala/math/Numeric$BigDecimalAsIfIntegral$class
Asciz	(Lscala/math/Numeric$BigDecimalAsIfIntegral;Lscala/math/BigDecimal;Lscala/math/BigDecimal;)Lscala/math/BigDecimal;;
NameAndType	quot:(Lscala/math/Numeric$BigDecimalAsIfIntegral;Lscala/math/BigDecimal;Lscala/math/BigDecimal;)Lscala/math/BigDecimal;
Method	scala/math/Numeric$BigDecimalAsIfIntegral$class.quot:(Lscala/math/Numeric$BigDecimalAsIfIntegral;Lscala/math/BigDecimal;Lscala/math/BigDecimal;)Lscala/math/BigDecimal;
Asciz	rem;
NameAndType	rem:(Lscala/math/Numeric$BigDecimalAsIfIntegral;Lscala/math/BigDecimal;Lscala/math/BigDecimal;)Lscala/math/BigDecimal;
Method	scala/math/Numeric$BigDecimalAsIfIntegral$class.rem:(Lscala/math/Numeric$BigDecimalAsIfIntegral;Lscala/math/BigDecimal;Lscala/math/BigDecimal;)Lscala/math/BigDecimal;
Asciz	mkNumericOps;
Asciz	(Ljava/lang/Object;)Lscala/math/Integral$IntegralOps;;
Asciz	scala/math/Integral$class;
class	scala/math/Integral$class
Asciz	(Lscala/math/Integral;Ljava/lang/Object;)Lscala/math/Integral$IntegralOps;;
NameAndType	mkNumericOps:(Lscala/math/Integral;Ljava/lang/Object;)Lscala/math/Integral$IntegralOps;
Method	scala/math/Integral$class.mkNumericOps:(Lscala/math/Integral;Ljava/lang/Object;)Lscala/math/Integral$IntegralOps;
Asciz	lhs;
Asciz	Ljava/lang/Object;;
Asciz	Signature;
Asciz	plus;
Asciz	scala/math/Numeric$BigDecimalIsConflicted$class;
class	scala/math/Numeric$BigDecimalIsConflicted$class
Asciz	(Lscala/math/Numeric$BigDecimalIsConflicted;Lscala/math/BigDecimal;Lscala/math/BigDecimal;)Lscala/math/BigDecimal;;
NameAndType	plus:(Lscala/math/Numeric$BigDecimalIsConflicted;Lscala/math/BigDecimal;Lscala/math/BigDecimal;)Lscala/math/BigDecimal;
Method	scala/math/Numeric$BigDecimalIsConflicted$class.plus:(Lscala/math/Numeric$BigDecimalIsConflicted;Lscala/math/BigDecimal;Lscala/math/BigDecimal;)Lscala/math/BigDecimal;
Asciz	minus;
NameAndType	minus:(Lscala/math/Numeric$BigDecimalIsConflicted;Lscala/math/BigDecimal;Lscala/math/BigDecimal;)Lscala/math/BigDecimal;
Method	scala/math/Numeric$BigDecimalIsConflicted$class.minus:(Lscala/math/Numeric$BigDecimalIsConflicted;Lscala/math/BigDecimal;Lscala/math/BigDecimal;)Lscala/math/BigDecimal;
Asciz	times;
NameAndType	times:(Lscala/math/Numeric$BigDecimalIsConflicted;Lscala/math/BigDecimal;Lscala/math/BigDecimal;)Lscala/math/BigDecimal;
Method	scala/math/Numeric$BigDecimalIsConflicted$class.times:(Lscala/math/Numeric$BigDecimalIsConflicted;Lscala/math/BigDecimal;Lscala/math/BigDecimal;)Lscala/math/BigDecimal;
Asciz	negate;
Asciz	(Lscala/math/BigDecimal;)Lscala/math/BigDecimal;;
Asciz	(Lscala/math/Numeric$BigDecimalIsConflicted;Lscala/math/BigDecimal;)Lscala/math/BigDecimal;;
NameAndType	negate:(Lscala/math/Numeric$BigDecimalIsConflicted;Lscala/math/BigDecimal;)Lscala/math/BigDecimal;
Method	scala/math/Numeric$BigDecimalIsConflicted$class.negate:(Lscala/math/Numeric$BigDecimalIsConflicted;Lscala/math/BigDecimal;)Lscala/math/BigDecimal;
Asciz	fromInt;
Asciz	(I)Lscala/math/BigDecimal;;
Asciz	(Lscala/math/Numeric$BigDecimalIsConflicted;I)Lscala/math/BigDecimal;;
NameAndType	fromInt:(Lscala/math/Numeric$BigDecimalIsConflicted;I)Lscala/math/BigDecimal;
Method	scala/math/Numeric$BigDecimalIsConflicted$class.fromInt:(Lscala/math/Numeric$BigDecimalIsConflicted;I)Lscala/math/BigDecimal;
Asciz	I;
Asciz	toInt;
Asciz	(Lscala/math/BigDecimal;)I;
Asciz	(Lscala/math/Numeric$BigDecimalIsConflicted;Lscala/math/BigDecimal;)I;
NameAndType	toInt:(Lscala/math/Numeric$BigDecimalIsConflicted;Lscala/math/BigDecimal;)I
Method	scala/math/Numeric$BigDecimalIsConflicted$class.toInt:(Lscala/math/Numeric$BigDecimalIsConflicted;Lscala/math/BigDecimal;)I
Asciz	toLong;
Asciz	(Lscala/math/BigDecimal;)J;
Asciz	(Lscala/math/Numeric$BigDecimalIsConflicted;Lscala/math/BigDecimal;)J;
NameAndType	toLong:(Lscala/math/Numeric$BigDecimalIsConflicted;Lscala/math/BigDecimal;)J
Method	scala/math/Numeric$BigDecimalIsConflicted$class.toLong:(Lscala/math/Numeric$BigDecimalIsConflicted;Lscala/math/BigDecimal;)J
Asciz	toFloat;
Asciz	(Lscala/math/BigDecimal;)F;
Asciz	(Lscala/math/Numeric$BigDecimalIsConflicted;Lscala/math/BigDecimal;)F;
NameAndType	toFloat:(Lscala/math/Numeric$BigDecimalIsConflicted;Lscala/math/BigDecimal;)F
Method	scala/math/Numeric$BigDecimalIsConflicted$class.toFloat:(Lscala/math/Numeric$BigDecimalIsConflicted;Lscala/math/BigDecimal;)F
Asciz	toDouble;
Asciz	(Lscala/math/BigDecimal;)D;
Asciz	(Lscala/math/Numeric$BigDecimalIsConflicted;Lscala/math/BigDecimal;)D;
NameAndType	toDouble:(Lscala/math/Numeric$BigDecimalIsConflicted;Lscala/math/BigDecimal;)D
Method	scala/math/Numeric$BigDecimalIsConflicted$class.toDouble:(Lscala/math/Numeric$BigDecimalIsConflicted;Lscala/math/BigDecimal;)D
Asciz	zero;
Asciz	()Ljava/lang/Object;;
Asciz	scala/math/Numeric$class;
class	scala/math/Numeric$class
Asciz	(Lscala/math/Numeric;)Ljava/lang/Object;;
NameAndType	zero:(Lscala/math/Numeric;)Ljava/lang/Object;
Method	scala/math/Numeric$class.zero:(Lscala/math/Numeric;)Ljava/lang/Object;
Asciz	one;
NameAndType	one:(Lscala/math/Numeric;)Ljava/lang/Object;
Method	scala/math/Numeric$class.one:(Lscala/math/Numeric;)Ljava/lang/Object;
Asciz	abs;
Asciz	(Ljava/lang/Object;)Ljava/lang/Object;;
Asciz	(Lscala/math/Numeric;Ljava/lang/Object;)Ljava/lang/Object;;
NameAndType	abs:(Lscala/math/Numeric;Ljava/lang/Object;)Ljava/lang/Object;
Method	scala/math/Numeric$class.abs:(Lscala/math/Numeric;Ljava/lang/Object;)Ljava/lang/Object;
Asciz	signum;
Asciz	(Ljava/lang/Object;)I;
Asciz	(Lscala/math/Numeric;Ljava/lang/Object;)I;
NameAndType	signum:(Lscala/math/Numeric;Ljava/lang/Object;)I
Method	scala/math/Numeric$class.signum:(Lscala/math/Numeric;Ljava/lang/Object;)I
Asciz	tryCompare;
Asciz	(Ljava/lang/Object;Ljava/lang/Object;)Lscala/Some;;
Asciz	scala/math/Ordering$class;
class	scala/math/Ordering$class
Asciz	(Lscala/math/Ordering;Ljava/lang/Object;Ljava/lang/Object;)Lscala/Some;;
NameAndType	tryCompare:(Lscala/math/Ordering;Ljava/lang/Object;Ljava/lang/Object;)Lscala/Some;
Method	scala/math/Ordering$class.tryCompare:(Lscala/math/Ordering;Ljava/lang/Object;Ljava/lang/Object;)Lscala/Some;
Asciz	lteq;
Asciz	(Ljava/lang/Object;Ljava/lang/Object;)Z;
Asciz	(Lscala/math/Ordering;Ljava/lang/Object;Ljava/lang/Object;)Z;
NameAndType	lteq:(Lscala/math/Ordering;Ljava/lang/Object;Ljava/lang/Object;)Z
Method	scala/math/Ordering$class.lteq:(Lscala/math/Ordering;Ljava/lang/Object;Ljava/lang/Object;)Z
Asciz	gteq;
NameAndType	gteq:(Lscala/math/Ordering;Ljava/lang/Object;Ljava/lang/Object;)Z
Method	scala/math/Ordering$class.gteq:(Lscala/math/Ordering;Ljava/lang/Object;Ljava/lang/Object;)Z
Asciz	lt;
NameAndType	lt:(Lscala/math/Ordering;Ljava/lang/Object;Ljava/lang/Object;)Z
Method	scala/math/Ordering$class.lt:(Lscala/math/Ordering;Ljava/lang/Object;Ljava/lang/Object;)Z
Asciz	gt;
NameAndType	gt:(Lscala/math/Ordering;Ljava/lang/Object;Ljava/lang/Object;)Z
Method	scala/math/Ordering$class.gt:(Lscala/math/Ordering;Ljava/lang/Object;Ljava/lang/Object;)Z
Asciz	equiv;
NameAndType	equiv:(Lscala/math/Ordering;Ljava/lang/Object;Ljava/lang/Object;)Z
Method	scala/math/Ordering$class.equiv:(Lscala/math/Ordering;Ljava/lang/Object;Ljava/lang/Object;)Z
Asciz	max;
Asciz	(Ljava/lang/Object;Ljava/lang/Object;)Ljava/lang/Object;;
Asciz	(Lscala/math/Ordering;Ljava/lang/Object;Ljava/lang/Object;)Ljava/lang/Object;;
NameAndType	max:(Lscala/math/Ordering;Ljava/lang/Object;Ljava/lang/Object;)Ljava/lang/Object;
Method	scala/math/Ordering$class.max:(Lscala/math/Ordering;Ljava/lang/Object;Ljava/lang/Object;)Ljava/lang/Object;
Asciz	min;
NameAndType	min:(Lscala/math/Ordering;Ljava/lang/Object;Ljava/lang/Object;)Ljava/lang/Object;
Method	scala/math/Ordering$class.min:(Lscala/math/Ordering;Ljava/lang/Object;Ljava/lang/Object;)Ljava/lang/Object;
Asciz	reverse;
Asciz	()Lscala/math/Ordering;;
Asciz	(Lscala/math/Ordering;)Lscala/math/Ordering;;
NameAndType	reverse:(Lscala/math/Ordering;)Lscala/math/Ordering;
Method	scala/math/Ordering$class.reverse:(Lscala/math/Ordering;)Lscala/math/Ordering;
Asciz	on;
Asciz	(Lscala/Function1;)Lscala/math/Ordering;;
Asciz	(Lscala/math/Ordering;Lscala/Function1;)Lscala/math/Ordering;;
NameAndType	on:(Lscala/math/Ordering;Lscala/Function1;)Lscala/math/Ordering;
Method	scala/math/Ordering$class.on:(Lscala/math/Ordering;Lscala/Function1;)Lscala/math/Ordering;
Asciz	f;
Asciz	Lscala/Function1;;
Asciz	mkOrderingOps;
Asciz	(Ljava/lang/Object;)Lscala/math/Ordering$Ops;;
Asciz	(Lscala/math/Ordering;Ljava/lang/Object;)Lscala/math/Ordering$Ops;;
NameAndType	mkOrderingOps:(Lscala/math/Ordering;Ljava/lang/Object;)Lscala/math/Ordering$Ops;
Method	scala/math/Ordering$class.mkOrderingOps:(Lscala/math/Ordering;Ljava/lang/Object;)Lscala/math/Ordering$Ops;
Asciz	()Lscala/math/PartialOrdering;;
Asciz	scala/math/Ordering;
class	scala/math/Ordering
NameAndType	reverse:()Lscala/math/Ordering;
InterfaceMethod	scala/math/Ordering.reverse:()Lscala/math/Ordering;
Asciz	(Ljava/lang/Object;Ljava/lang/Object;)Lscala/Option;;
NameAndType	tryCompare:(Ljava/lang/Object;Ljava/lang/Object;)Lscala/Some;
InterfaceMethod	scala/math/Ordering.tryCompare:(Ljava/lang/Object;Ljava/lang/Object;)Lscala/Some;
Asciz	(Ljava/lang/Object;)D;
Asciz	scala/math/BigDecimal;
class	scala/math/BigDecimal
Asciz	scala/math/Numeric$BigDecimalIsConflicted;
class	scala/math/Numeric$BigDecimalIsConflicted
NameAndType	toDouble:(Lscala/math/BigDecimal;)D
InterfaceMethod	scala/math/Numeric$BigDecimalIsConflicted.toDouble:(Lscala/math/BigDecimal;)D
Asciz	(Ljava/lang/Object;)F;
NameAndType	toFloat:(Lscala/math/BigDecimal;)F
InterfaceMethod	scala/math/Numeric$BigDecimalIsConflicted.toFloat:(Lscala/math/BigDecimal;)F
Asciz	(Ljava/lang/Object;)J;
NameAndType	toLong:(Lscala/math/BigDecimal;)J
InterfaceMethod	scala/math/Numeric$BigDecimalIsConflicted.toLong:(Lscala/math/BigDecimal;)J
NameAndType	toInt:(Lscala/math/BigDecimal;)I
InterfaceMethod	scala/math/Numeric$BigDecimalIsConflicted.toInt:(Lscala/math/BigDecimal;)I
Asciz	(I)Ljava/lang/Object;;
NameAndType	fromInt:(I)Lscala/math/BigDecimal;
InterfaceMethod	scala/math/Numeric$BigDecimalIsConflicted.fromInt:(I)Lscala/math/BigDecimal;
NameAndType	negate:(Lscala/math/BigDecimal;)Lscala/math/BigDecimal;
InterfaceMethod	scala/math/Numeric$BigDecimalIsConflicted.negate:(Lscala/math/BigDecimal;)Lscala/math/BigDecimal;
NameAndType	times:(Lscala/math/BigDecimal;Lscala/math/BigDecimal;)Lscala/math/BigDecimal;
InterfaceMethod	scala/math/Numeric$BigDecimalIsConflicted.times:(Lscala/math/BigDecimal;Lscala/math/BigDecimal;)Lscala/math/BigDecimal;
NameAndType	minus:(Lscala/math/BigDecimal;Lscala/math/BigDecimal;)Lscala/math/BigDecimal;
InterfaceMethod	scala/math/Numeric$BigDecimalIsConflicted.minus:(Lscala/math/BigDecimal;Lscala/math/BigDecimal;)Lscala/math/BigDecimal;
NameAndType	plus:(Lscala/math/BigDecimal;Lscala/math/BigDecimal;)Lscala/math/BigDecimal;
InterfaceMethod	scala/math/Numeric$BigDecimalIsConflicted.plus:(Lscala/math/BigDecimal;Lscala/math/BigDecimal;)Lscala/math/BigDecimal;
Asciz	(Ljava/lang/Object;)Lscala/math/Numeric$Ops;;
Asciz	scala/math/Integral;
class	scala/math/Integral
NameAndType	mkNumericOps:(Ljava/lang/Object;)Lscala/math/Integral$IntegralOps;
InterfaceMethod	scala/math/Integral.mkNumericOps:(Ljava/lang/Object;)Lscala/math/Integral$IntegralOps;
Asciz	scala/math/Numeric$BigDecimalAsIfIntegral;
class	scala/math/Numeric$BigDecimalAsIfIntegral
NameAndType	rem:(Lscala/math/BigDecimal;Lscala/math/BigDecimal;)Lscala/math/BigDecimal;
InterfaceMethod	scala/math/Numeric$BigDecimalAsIfIntegral.rem:(Lscala/math/BigDecimal;Lscala/math/BigDecimal;)Lscala/math/BigDecimal;
NameAndType	quot:(Lscala/math/BigDecimal;Lscala/math/BigDecimal;)Lscala/math/BigDecimal;
InterfaceMethod	scala/math/Numeric$BigDecimalAsIfIntegral.quot:(Lscala/math/BigDecimal;Lscala/math/BigDecimal;)Lscala/math/BigDecimal;
Asciz	(Ljava/lang/Object;Ljava/lang/Object;)I;
Asciz	scala/math/Ordering$BigDecimalOrdering;
class	scala/math/Ordering$BigDecimalOrdering
NameAndType	compare:(Lscala/math/BigDecimal;Lscala/math/BigDecimal;)I
InterfaceMethod	scala/math/Ordering$BigDecimalOrdering.compare:(Lscala/math/BigDecimal;Lscala/math/BigDecimal;)I
Asciz	java/lang/Object;
class	java/lang/Object
Method	java/lang/Object."<init>":()V
NameAndType	MODULE$:Lscala/math/Numeric$BigDecimalAsIfIntegral$;
Field	scala/math/Numeric$BigDecimalAsIfIntegral$.MODULE$:Lscala/math/Numeric$BigDecimalAsIfIntegral$;
Asciz	scala/math/PartialOrdering$class;
class	scala/math/PartialOrdering$class
Asciz	$init$;
Asciz	(Lscala/math/PartialOrdering;)V;
NameAndType	$init$:(Lscala/math/PartialOrdering;)V
Method	scala/math/PartialOrdering$class.$init$:(Lscala/math/PartialOrdering;)V
Asciz	(Lscala/math/Ordering;)V;
NameAndType	$init$:(Lscala/math/Ordering;)V
Method	scala/math/Ordering$class.$init$:(Lscala/math/Ordering;)V
Asciz	(Lscala/math/Numeric;)V;
NameAndType	$init$:(Lscala/math/Numeric;)V
Method	scala/math/Numeric$class.$init$:(Lscala/math/Numeric;)V
Asciz	(Lscala/math/Numeric$BigDecimalIsConflicted;)V;
NameAndType	$init$:(Lscala/math/Numeric$BigDecimalIsConflicted;)V
Method	scala/math/Numeric$BigDecimalIsConflicted$class.$init$:(Lscala/math/Numeric$BigDecimalIsConflicted;)V
Asciz	(Lscala/math/Integral;)V;
NameAndType	$init$:(Lscala/math/Integral;)V
Method	scala/math/Integral$class.$init$:(Lscala/math/Integral;)V
Asciz	(Lscala/math/Numeric$BigDecimalAsIfIntegral;)V;
NameAndType	$init$:(Lscala/math/Numeric$BigDecimalAsIfIntegral;)V
Method	scala/math/Numeric$BigDecimalAsIfIntegral$class.$init$:(Lscala/math/Numeric$BigDecimalAsIfIntegral;)V
Asciz	(Lscala/math/Ordering$BigDecimalOrdering;)V;
NameAndType	$init$:(Lscala/math/Ordering$BigDecimalOrdering;)V
Method	scala/math/Ordering$BigDecimalOrdering$class.$init$:(Lscala/math/Ordering$BigDecimalOrdering;)V
Asciz	Scala;
Asciz	InnerClasses;
Asciz	scala/math/Numeric$Ops;
class	scala/math/Numeric$Ops
Asciz	scala/math/Numeric;
class	scala/math/Numeric
Asciz	Ops;
Asciz	scala/math/Ordering$Ops;
class	scala/math/Ordering$Ops
Asciz	scala/math/Integral$IntegralOps;
class	scala/math/Integral$IntegralOps
Asciz	IntegralOps;
Asciz	BigDecimalOrdering;
Asciz	BigDecimalIsConflicted;
Asciz	BigDecimalAsIfIntegral;
Asciz	scala/ScalaObject;
class	scala/ScalaObject

{
public static final scala.math.Numeric$BigDecimalAsIfIntegral$ MODULE$;
  Signature: Lscala/math/Numeric$BigDecimalAsIfIntegral$;

public static {};
  Signature: ()V
  Code:
   Stack=1, Locals=0, Args_size=0
	new	class scala/math/Numeric$BigDecimalAsIfIntegral$
	invokespecial	Method "<init>":()V
	return
  Labels:

public int compare(scala.math.BigDecimal, scala.math.BigDecimal);
  Signature: (Lscala/math/BigDecimal;Lscala/math/BigDecimal;)I
  Code:
   Stack=3, Locals=3, Args_size=3
	aload_0
	aload_1
	aload_2
	invokestatic	Method scala/math/Ordering$BigDecimalOrdering$class.compare:(Lscala/math/Ordering$BigDecimalOrdering;Lscala/math/BigDecimal;Lscala/math/BigDecimal;)I
	ireturn
  Labels:
  LocalVariableTable: 
   Start  Length  Slot  Name   Signature
   0      7      0    this       Lscala/math/Numeric$BigDecimalAsIfIntegral$;
   0      7      1    x       Lscala/math/BigDecimal;
   0      7      2    y       Lscala/math/BigDecimal;


public scala.math.BigDecimal quot(scala.math.BigDecimal, scala.math.BigDecimal);
  Signature: (Lscala/math/BigDecimal;Lscala/math/BigDecimal;)Lscala/math/BigDecimal;
  Code:
   Stack=3, Locals=3, Args_size=3
	aload_0
	aload_1
	aload_2
	invokestatic	Method scala/math/Numeric$BigDecimalAsIfIntegral$class.quot:(Lscala/math/Numeric$BigDecimalAsIfIntegral;Lscala/math/BigDecimal;Lscala/math/BigDecimal;)Lscala/math/BigDecimal;
	areturn
  Labels:
  LocalVariableTable: 
   Start  Length  Slot  Name   Signature
   0      7      0    this       Lscala/math/Numeric$BigDecimalAsIfIntegral$;
   0      7      1    x       Lscala/math/BigDecimal;
   0      7      2    y       Lscala/math/BigDecimal;


public scala.math.BigDecimal rem(scala.math.BigDecimal, scala.math.BigDecimal);
  Signature: (Lscala/math/BigDecimal;Lscala/math/BigDecimal;)Lscala/math/BigDecimal;
  Code:
   Stack=3, Locals=3, Args_size=3
	aload_0
	aload_1
	aload_2
	invokestatic	Method scala/math/Numeric$BigDecimalAsIfIntegral$class.rem:(Lscala/math/Numeric$BigDecimalAsIfIntegral;Lscala/math/BigDecimal;Lscala/math/BigDecimal;)Lscala/math/BigDecimal;
	areturn
  Labels:
  LocalVariableTable: 
   Start  Length  Slot  Name   Signature
   0      7      0    this       Lscala/math/Numeric$BigDecimalAsIfIntegral$;
   0      7      1    x       Lscala/math/BigDecimal;
   0      7      2    y       Lscala/math/BigDecimal;


public scala.math.Integral$IntegralOps mkNumericOps(java.lang.Object);
  Signature: (Ljava/lang/Object;)Lscala/math/Integral$IntegralOps;
  Code:
   Stack=2, Locals=2, Args_size=2
	aload_0
	aload_1
	invokestatic	Method scala/math/Integral$class.mkNumericOps:(Lscala/math/Integral;Ljava/lang/Object;)Lscala/math/Integral$IntegralOps;
	areturn
  Labels:
  LocalVariableTable: 
   Start  Length  Slot  Name   Signature
   0      6      0    this       Lscala/math/Numeric$BigDecimalAsIfIntegral$;
   0      6      1    lhs       Ljava/lang/Object;

  Signature: length = 0x2
   00 25 

public scala.math.BigDecimal plus(scala.math.BigDecimal, scala.math.BigDecimal);
  Signature: (Lscala/math/BigDecimal;Lscala/math/BigDecimal;)Lscala/math/BigDecimal;
  Code:
   Stack=3, Locals=3, Args_size=3
	aload_0
	aload_1
	aload_2
	invokestatic	Method scala/math/Numeric$BigDecimalIsConflicted$class.plus:(Lscala/math/Numeric$BigDecimalIsConflicted;Lscala/math/BigDecimal;Lscala/math/BigDecimal;)Lscala/math/BigDecimal;
	areturn
  Labels:
  LocalVariableTable: 
   Start  Length  Slot  Name   Signature
   0      7      0    this       Lscala/math/Numeric$BigDecimalAsIfIntegral$;
   0      7      1    x       Lscala/math/BigDecimal;
   0      7      2    y       Lscala/math/BigDecimal;


public scala.math.BigDecimal minus(scala.math.BigDecimal, scala.math.BigDecimal);
  Signature: (Lscala/math/BigDecimal;Lscala/math/BigDecimal;)Lscala/math/BigDecimal;
  Code:
   Stack=3, Locals=3, Args_size=3
	aload_0
	aload_1
	aload_2
	invokestatic	Method scala/math/Numeric$BigDecimalIsConflicted$class.minus:(Lscala/math/Numeric$BigDecimalIsConflicted;Lscala/math/BigDecimal;Lscala/math/BigDecimal;)Lscala/math/BigDecimal;
	areturn
  Labels:
  LocalVariableTable: 
   Start  Length  Slot  Name   Signature
   0      7      0    this       Lscala/math/Numeric$BigDecimalAsIfIntegral$;
   0      7      1    x       Lscala/math/BigDecimal;
   0      7      2    y       Lscala/math/BigDecimal;


public scala.math.BigDecimal times(scala.math.BigDecimal, scala.math.BigDecimal);
  Signature: (Lscala/math/BigDecimal;Lscala/math/BigDecimal;)Lscala/math/BigDecimal;
  Code:
   Stack=3, Locals=3, Args_size=3
	aload_0
	aload_1
	aload_2
	invokestatic	Method scala/math/Numeric$BigDecimalIsConflicted$class.times:(Lscala/math/Numeric$BigDecimalIsConflicted;Lscala/math/BigDecimal;Lscala/math/BigDecimal;)Lscala/math/BigDecimal;
	areturn
  Labels:
  LocalVariableTable: 
   Start  Length  Slot  Name   Signature
   0      7      0    this       Lscala/math/Numeric$BigDecimalAsIfIntegral$;
   0      7      1    x       Lscala/math/BigDecimal;
   0      7      2    y       Lscala/math/BigDecimal;


public scala.math.BigDecimal negate(scala.math.BigDecimal);
  Signature: (Lscala/math/BigDecimal;)Lscala/math/BigDecimal;
  Code:
   Stack=2, Locals=2, Args_size=2
	aload_0
	aload_1
	invokestatic	Method scala/math/Numeric$BigDecimalIsConflicted$class.negate:(Lscala/math/Numeric$BigDecimalIsConflicted;Lscala/math/BigDecimal;)Lscala/math/BigDecimal;
	areturn
  Labels:
  LocalVariableTable: 
   Start  Length  Slot  Name   Signature
   0      6      0    this       Lscala/math/Numeric$BigDecimalAsIfIntegral$;
   0      6      1    x       Lscala/math/BigDecimal;


public scala.math.BigDecimal fromInt(int);
  Signature: (I)Lscala/math/BigDecimal;
  Code:
   Stack=2, Locals=2, Args_size=2
	aload_0
	iload_1
	invokestatic	Method scala/math/Numeric$BigDecimalIsConflicted$class.fromInt:(Lscala/math/Numeric$BigDecimalIsConflicted;I)Lscala/math/BigDecimal;
	areturn
  Labels:
  LocalVariableTable: 
   Start  Length  Slot  Name   Signature
   0      6      0    this       Lscala/math/Numeric$BigDecimalAsIfIntegral$;
   0      6      1    x       I


public int toInt(scala.math.BigDecimal);
  Signature: (Lscala/math/BigDecimal;)I
  Code:
   Stack=2, Locals=2, Args_size=2
	aload_0
	aload_1
	invokestatic	Method scala/math/Numeric$BigDecimalIsConflicted$class.toInt:(Lscala/math/Numeric$BigDecimalIsConflicted;Lscala/math/BigDecimal;)I
	ireturn
  Labels:
  LocalVariableTable: 
   Start  Length  Slot  Name   Signature
   0      6      0    this       Lscala/math/Numeric$BigDecimalAsIfIntegral$;
   0      6      1    x       Lscala/math/BigDecimal;


public long toLong(scala.math.BigDecimal);
  Signature: (Lscala/math/BigDecimal;)J
  Code:
   Stack=2, Locals=2, Args_size=2
	aload_0
	aload_1
	invokestatic	Method scala/math/Numeric$BigDecimalIsConflicted$class.toLong:(Lscala/math/Numeric$BigDecimalIsConflicted;Lscala/math/BigDecimal;)J
	lreturn
  Labels:
  LocalVariableTable: 
   Start  Length  Slot  Name   Signature
   0      6      0    this       Lscala/math/Numeric$BigDecimalAsIfIntegral$;
   0      6      1    x       Lscala/math/BigDecimal;


public float toFloat(scala.math.BigDecimal);
  Signature: (Lscala/math/BigDecimal;)F
  Code:
   Stack=2, Locals=2, Args_size=2
	aload_0
	aload_1
	invokestatic	Method scala/math/Numeric$BigDecimalIsConflicted$class.toFloat:(Lscala/math/Numeric$BigDecimalIsConflicted;Lscala/math/BigDecimal;)F
	freturn
  Labels:
  LocalVariableTable: 
   Start  Length  Slot  Name   Signature
   0      6      0    this       Lscala/math/Numeric$BigDecimalAsIfIntegral$;
   0      6      1    x       Lscala/math/BigDecimal;


public double toDouble(scala.math.BigDecimal);
  Signature: (Lscala/math/BigDecimal;)D
  Code:
   Stack=2, Locals=2, Args_size=2
	aload_0
	aload_1
	invokestatic	Method scala/math/Numeric$BigDecimalIsConflicted$class.toDouble:(Lscala/math/Numeric$BigDecimalIsConflicted;Lscala/math/BigDecimal;)D
	dreturn
  Labels:
  LocalVariableTable: 
   Start  Length  Slot  Name   Signature
   0      6      0    this       Lscala/math/Numeric$BigDecimalAsIfIntegral$;
   0      6      1    x       Lscala/math/BigDecimal;


public java.lang.Object zero();
  Signature: ()Ljava/lang/Object;
  Code:
   Stack=1, Locals=1, Args_size=1
	aload_0
	invokestatic	Method scala/math/Numeric$class.zero:(Lscala/math/Numeric;)Ljava/lang/Object;
	areturn
  Labels:

public java.lang.Object one();
  Signature: ()Ljava/lang/Object;
  Code:
   Stack=1, Locals=1, Args_size=1
	aload_0
	invokestatic	Method scala/math/Numeric$class.one:(Lscala/math/Numeric;)Ljava/lang/Object;
	areturn
  Labels:

public java.lang.Object abs(java.lang.Object);
  Signature: (Ljava/lang/Object;)Ljava/lang/Object;
  Code:
   Stack=2, Locals=2, Args_size=2
	aload_0
	aload_1
	invokestatic	Method scala/math/Numeric$class.abs:(Lscala/math/Numeric;Ljava/lang/Object;)Ljava/lang/Object;
	areturn
  Labels:
  LocalVariableTable: 
   Start  Length  Slot  Name   Signature
   0      6      0    this       Lscala/math/Numeric$BigDecimalAsIfIntegral$;
   0      6      1    x       Ljava/lang/Object;


public int signum(java.lang.Object);
  Signature: (Ljava/lang/Object;)I
  Code:
   Stack=2, Locals=2, Args_size=2
	aload_0
	aload_1
	invokestatic	Method scala/math/Numeric$class.signum:(Lscala/math/Numeric;Ljava/lang/Object;)I
	ireturn
  Labels:
  LocalVariableTable: 
   Start  Length  Slot  Name   Signature
   0      6      0    this       Lscala/math/Numeric$BigDecimalAsIfIntegral$;
   0      6      1    x       Ljava/lang/Object;


public scala.Some tryCompare(java.lang.Object, java.lang.Object);
  Signature: (Ljava/lang/Object;Ljava/lang/Object;)Lscala/Some;
  Code:
   Stack=3, Locals=3, Args_size=3
	aload_0
	aload_1
	aload_2
	invokestatic	Method scala/math/Ordering$class.tryCompare:(Lscala/math/Ordering;Ljava/lang/Object;Ljava/lang/Object;)Lscala/Some;
	areturn
  Labels:
  LocalVariableTable: 
   Start  Length  Slot  Name   Signature
   0      7      0    this       Lscala/math/Numeric$BigDecimalAsIfIntegral$;
   0      7      1    x       Ljava/lang/Object;
   0      7      2    y       Ljava/lang/Object;


public boolean lteq(java.lang.Object, java.lang.Object);
  Signature: (Ljava/lang/Object;Ljava/lang/Object;)Z
  Code:
   Stack=3, Locals=3, Args_size=3
	aload_0
	aload_1
	aload_2
	invokestatic	Method scala/math/Ordering$class.lteq:(Lscala/math/Ordering;Ljava/lang/Object;Ljava/lang/Object;)Z
	ireturn
  Labels:
  LocalVariableTable: 
   Start  Length  Slot  Name   Signature
   0      7      0    this       Lscala/math/Numeric$BigDecimalAsIfIntegral$;
   0      7      1    x       Ljava/lang/Object;
   0      7      2    y       Ljava/lang/Object;


public boolean gteq(java.lang.Object, java.lang.Object);
  Signature: (Ljava/lang/Object;Ljava/lang/Object;)Z
  Code:
   Stack=3, Locals=3, Args_size=3
	aload_0
	aload_1
	aload_2
	invokestatic	Method scala/math/Ordering$class.gteq:(Lscala/math/Ordering;Ljava/lang/Object;Ljava/lang/Object;)Z
	ireturn
  Labels:
  LocalVariableTable: 
   Start  Length  Slot  Name   Signature
   0      7      0    this       Lscala/math/Numeric$BigDecimalAsIfIntegral$;
   0      7      1    x       Ljava/lang/Object;
   0      7      2    y       Ljava/lang/Object;


public boolean lt(java.lang.Object, java.lang.Object);
  Signature: (Ljava/lang/Object;Ljava/lang/Object;)Z
  Code:
   Stack=3, Locals=3, Args_size=3
	aload_0
	aload_1
	aload_2
	invokestatic	Method scala/math/Ordering$class.lt:(Lscala/math/Ordering;Ljava/lang/Object;Ljava/lang/Object;)Z
	ireturn
  Labels:
  LocalVariableTable: 
   Start  Length  Slot  Name   Signature
   0      7      0    this       Lscala/math/Numeric$BigDecimalAsIfIntegral$;
   0      7      1    x       Ljava/lang/Object;
   0      7      2    y       Ljava/lang/Object;


public boolean gt(java.lang.Object, java.lang.Object);
  Signature: (Ljava/lang/Object;Ljava/lang/Object;)Z
  Code:
   Stack=3, Locals=3, Args_size=3
	aload_0
	aload_1
	aload_2
	invokestatic	Method scala/math/Ordering$class.gt:(Lscala/math/Ordering;Ljava/lang/Object;Ljava/lang/Object;)Z
	ireturn
  Labels:
  LocalVariableTable: 
   Start  Length  Slot  Name   Signature
   0      7      0    this       Lscala/math/Numeric$BigDecimalAsIfIntegral$;
   0      7      1    x       Ljava/lang/Object;
   0      7      2    y       Ljava/lang/Object;


public boolean equiv(java.lang.Object, java.lang.Object);
  Signature: (Ljava/lang/Object;Ljava/lang/Object;)Z
  Code:
   Stack=3, Locals=3, Args_size=3
	aload_0
	aload_1
	aload_2
	invokestatic	Method scala/math/Ordering$class.equiv:(Lscala/math/Ordering;Ljava/lang/Object;Ljava/lang/Object;)Z
	ireturn
  Labels:
  LocalVariableTable: 
   Start  Length  Slot  Name   Signature
   0      7      0    this       Lscala/math/Numeric$BigDecimalAsIfIntegral$;
   0      7      1    x       Ljava/lang/Object;
   0      7      2    y       Ljava/lang/Object;


public java.lang.Object max(java.lang.Object, java.lang.Object);
  Signature: (Ljava/lang/Object;Ljava/lang/Object;)Ljava/lang/Object;
  Code:
   Stack=3, Locals=3, Args_size=3
	aload_0
	aload_1
	aload_2
	invokestatic	Method scala/math/Ordering$class.max:(Lscala/math/Ordering;Ljava/lang/Object;Ljava/lang/Object;)Ljava/lang/Object;
	areturn
  Labels:
  LocalVariableTable: 
   Start  Length  Slot  Name   Signature
   0      7      0    this       Lscala/math/Numeric$BigDecimalAsIfIntegral$;
   0      7      1    x       Ljava/lang/Object;
   0      7      2    y       Ljava/lang/Object;


public java.lang.Object min(java.lang.Object, java.lang.Object);
  Signature: (Ljava/lang/Object;Ljava/lang/Object;)Ljava/lang/Object;
  Code:
   Stack=3, Locals=3, Args_size=3
	aload_0
	aload_1
	aload_2
	invokestatic	Method scala/math/Ordering$class.min:(Lscala/math/Ordering;Ljava/lang/Object;Ljava/lang/Object;)Ljava/lang/Object;
	areturn
  Labels:
  LocalVariableTable: 
   Start  Length  Slot  Name   Signature
   0      7      0    this       Lscala/math/Numeric$BigDecimalAsIfIntegral$;
   0      7      1    x       Ljava/lang/Object;
   0      7      2    y       Ljava/lang/Object;


public scala.math.Ordering reverse();
  Signature: ()Lscala/math/Ordering;
  Code:
   Stack=1, Locals=1, Args_size=1
	aload_0
	invokestatic	Method scala/math/Ordering$class.reverse:(Lscala/math/Ordering;)Lscala/math/Ordering;
	areturn
  Labels:

public scala.math.Ordering on(scala.Function1);
  Signature: (Lscala/Function1;)Lscala/math/Ordering;
  Code:
   Stack=2, Locals=2, Args_size=2
	aload_0
	aload_1
	invokestatic	Method scala/math/Ordering$class.on:(Lscala/math/Ordering;Lscala/Function1;)Lscala/math/Ordering;
	areturn
  Labels:
  LocalVariableTable: 
   Start  Length  Slot  Name   Signature
   0      6      0    this       Lscala/math/Numeric$BigDecimalAsIfIntegral$;
   0      6      1    f       Lscala/Function1;


public scala.math.Ordering$Ops mkOrderingOps(java.lang.Object);
  Signature: (Ljava/lang/Object;)Lscala/math/Ordering$Ops;
  Code:
   Stack=2, Locals=2, Args_size=2
	aload_0
	aload_1
	invokestatic	Method scala/math/Ordering$class.mkOrderingOps:(Lscala/math/Ordering;Ljava/lang/Object;)Lscala/math/Ordering$Ops;
	areturn
  Labels:
  LocalVariableTable: 
   Start  Length  Slot  Name   Signature
   0      6      0    this       Lscala/math/Numeric$BigDecimalAsIfIntegral$;
   0      6      1    lhs       Ljava/lang/Object;

  Signature: length = 0x2
   00 FFFFFF9A 

public scala.math.PartialOrdering reverse();
  Signature: ()Lscala/math/PartialOrdering;
  Code:
   Stack=1, Locals=1, Args_size=1
	aload_0
	invokeinterface	InterfaceMethod scala/math/Ordering.reverse:()Lscala/math/Ordering;
	areturn
  Labels:

public scala.Option tryCompare(java.lang.Object, java.lang.Object);
  Signature: (Ljava/lang/Object;Ljava/lang/Object;)Lscala/Option;
  Code:
   Stack=3, Locals=3, Args_size=3
	aload_0
	aload_1
	aload_2
	invokeinterface	InterfaceMethod scala/math/Ordering.tryCompare:(Ljava/lang/Object;Ljava/lang/Object;)Lscala/Some;
	areturn
  Labels:
  LocalVariableTable: 
   Start  Length  Slot  Name   Signature
   0      9      0    this       Lscala/math/Numeric$BigDecimalAsIfIntegral$;
   0      9      1    x       Ljava/lang/Object;
   0      9      2    y       Ljava/lang/Object;


public double toDouble(java.lang.Object);
  Signature: (Ljava/lang/Object;)D
  Code:
   Stack=2, Locals=2, Args_size=2
	aload_0
	aload_1
	checkcast	class scala/math/BigDecimal
	invokeinterface	InterfaceMethod scala/math/Numeric$BigDecimalIsConflicted.toDouble:(Lscala/math/BigDecimal;)D
	dreturn
  Labels:
  LocalVariableTable: 
   Start  Length  Slot  Name   Signature
   0      11      0    this       Lscala/math/Numeric$BigDecimalAsIfIntegral$;
   0      11      1    x       Ljava/lang/Object;


public float toFloat(java.lang.Object);
  Signature: (Ljava/lang/Object;)F
  Code:
   Stack=2, Locals=2, Args_size=2
	aload_0
	aload_1
	checkcast	class scala/math/BigDecimal
	invokeinterface	InterfaceMethod scala/math/Numeric$BigDecimalIsConflicted.toFloat:(Lscala/math/BigDecimal;)F
	freturn
  Labels:
  LocalVariableTable: 
   Start  Length  Slot  Name   Signature
   0      11      0    this       Lscala/math/Numeric$BigDecimalAsIfIntegral$;
   0      11      1    x       Ljava/lang/Object;


public long toLong(java.lang.Object);
  Signature: (Ljava/lang/Object;)J
  Code:
   Stack=2, Locals=2, Args_size=2
	aload_0
	aload_1
	checkcast	class scala/math/BigDecimal
	invokeinterface	InterfaceMethod scala/math/Numeric$BigDecimalIsConflicted.toLong:(Lscala/math/BigDecimal;)J
	lreturn
  Labels:
  LocalVariableTable: 
   Start  Length  Slot  Name   Signature
   0      11      0    this       Lscala/math/Numeric$BigDecimalAsIfIntegral$;
   0      11      1    x       Ljava/lang/Object;


public int toInt(java.lang.Object);
  Signature: (Ljava/lang/Object;)I
  Code:
   Stack=2, Locals=2, Args_size=2
	aload_0
	aload_1
	checkcast	class scala/math/BigDecimal
	invokeinterface	InterfaceMethod scala/math/Numeric$BigDecimalIsConflicted.toInt:(Lscala/math/BigDecimal;)I
	ireturn
  Labels:
  LocalVariableTable: 
   Start  Length  Slot  Name   Signature
   0      11      0    this       Lscala/math/Numeric$BigDecimalAsIfIntegral$;
   0      11      1    x       Ljava/lang/Object;


public java.lang.Object fromInt(int);
  Signature: (I)Ljava/lang/Object;
  Code:
   Stack=2, Locals=2, Args_size=2
	aload_0
	iload_1
	invokeinterface	InterfaceMethod scala/math/Numeric$BigDecimalIsConflicted.fromInt:(I)Lscala/math/BigDecimal;
	areturn
  Labels:
  LocalVariableTable: 
   Start  Length  Slot  Name   Signature
   0      8      0    this       Lscala/math/Numeric$BigDecimalAsIfIntegral$;
   0      8      1    x       I


public java.lang.Object negate(java.lang.Object);
  Signature: (Ljava/lang/Object;)Ljava/lang/Object;
  Code:
   Stack=2, Locals=2, Args_size=2
	aload_0
	aload_1
	checkcast	class scala/math/BigDecimal
	invokeinterface	InterfaceMethod scala/math/Numeric$BigDecimalIsConflicted.negate:(Lscala/math/BigDecimal;)Lscala/math/BigDecimal;
	areturn
  Labels:
  LocalVariableTable: 
   Start  Length  Slot  Name   Signature
   0      11      0    this       Lscala/math/Numeric$BigDecimalAsIfIntegral$;
   0      11      1    x       Ljava/lang/Object;


public java.lang.Object times(java.lang.Object, java.lang.Object);
  Signature: (Ljava/lang/Object;Ljava/lang/Object;)Ljava/lang/Object;
  Code:
   Stack=3, Locals=3, Args_size=3
	aload_0
	aload_1
	checkcast	class scala/math/BigDecimal
	aload_2
	checkcast	class scala/math/BigDecimal
	invokeinterface	InterfaceMethod scala/math/Numeric$BigDecimalIsConflicted.times:(Lscala/math/BigDecimal;Lscala/math/BigDecimal;)Lscala/math/BigDecimal;
	areturn
  Labels:
  LocalVariableTable: 
   Start  Length  Slot  Name   Signature
   0      15      0    this       Lscala/math/Numeric$BigDecimalAsIfIntegral$;
   0      15      1    x       Ljava/lang/Object;
   0      15      2    y       Ljava/lang/Object;


public java.lang.Object minus(java.lang.Object, java.lang.Object);
  Signature: (Ljava/lang/Object;Ljava/lang/Object;)Ljava/lang/Object;
  Code:
   Stack=3, Locals=3, Args_size=3
	aload_0
	aload_1
	checkcast	class scala/math/BigDecimal
	aload_2
	checkcast	class scala/math/BigDecimal
	invokeinterface	InterfaceMethod scala/math/Numeric$BigDecimalIsConflicted.minus:(Lscala/math/BigDecimal;Lscala/math/BigDecimal;)Lscala/math/BigDecimal;
	areturn
  Labels:
  LocalVariableTable: 
   Start  Length  Slot  Name   Signature
   0      15      0    this       Lscala/math/Numeric$BigDecimalAsIfIntegral$;
   0      15      1    x       Ljava/lang/Object;
   0      15      2    y       Ljava/lang/Object;


public java.lang.Object plus(java.lang.Object, java.lang.Object);
  Signature: (Ljava/lang/Object;Ljava/lang/Object;)Ljava/lang/Object;
  Code:
   Stack=3, Locals=3, Args_size=3
	aload_0
	aload_1
	checkcast	class scala/math/BigDecimal
	aload_2
	checkcast	class scala/math/BigDecimal
	invokeinterface	InterfaceMethod scala/math/Numeric$BigDecimalIsConflicted.plus:(Lscala/math/BigDecimal;Lscala/math/BigDecimal;)Lscala/math/BigDecimal;
	areturn
  Labels:
  LocalVariableTable: 
   Start  Length  Slot  Name   Signature
   0      15      0    this       Lscala/math/Numeric$BigDecimalAsIfIntegral$;
   0      15      1    x       Ljava/lang/Object;
   0      15      2    y       Ljava/lang/Object;


public scala.math.Numeric$Ops mkNumericOps(java.lang.Object);
  Signature: (Ljava/lang/Object;)Lscala/math/Numeric$Ops;
  Code:
   Stack=2, Locals=2, Args_size=2
	aload_0
	aload_1
	invokeinterface	InterfaceMethod scala/math/Integral.mkNumericOps:(Ljava/lang/Object;)Lscala/math/Integral$IntegralOps;
	areturn
  Labels:
  LocalVariableTable: 
   Start  Length  Slot  Name   Signature
   0      8      0    this       Lscala/math/Numeric$BigDecimalAsIfIntegral$;
   0      8      1    lhs       Ljava/lang/Object;

  Signature: length = 0x2
   00 FFFFFFC0 

public java.lang.Object rem(java.lang.Object, java.lang.Object);
  Signature: (Ljava/lang/Object;Ljava/lang/Object;)Ljava/lang/Object;
  Code:
   Stack=3, Locals=3, Args_size=3
	aload_0
	aload_1
	checkcast	class scala/math/BigDecimal
	aload_2
	checkcast	class scala/math/BigDecimal
	invokeinterface	InterfaceMethod scala/math/Numeric$BigDecimalAsIfIntegral.rem:(Lscala/math/BigDecimal;Lscala/math/BigDecimal;)Lscala/math/BigDecimal;
	areturn
  Labels:
  LocalVariableTable: 
   Start  Length  Slot  Name   Signature
   0      15      0    this       Lscala/math/Numeric$BigDecimalAsIfIntegral$;
   0      15      1    x       Ljava/lang/Object;
   0      15      2    y       Ljava/lang/Object;


public java.lang.Object quot(java.lang.Object, java.lang.Object);
  Signature: (Ljava/lang/Object;Ljava/lang/Object;)Ljava/lang/Object;
  Code:
   Stack=3, Locals=3, Args_size=3
	aload_0
	aload_1
	checkcast	class scala/math/BigDecimal
	aload_2
	checkcast	class scala/math/BigDecimal
	invokeinterface	InterfaceMethod scala/math/Numeric$BigDecimalAsIfIntegral.quot:(Lscala/math/BigDecimal;Lscala/math/BigDecimal;)Lscala/math/BigDecimal;
	areturn
  Labels:
  LocalVariableTable: 
   Start  Length  Slot  Name   Signature
   0      15      0    this       Lscala/math/Numeric$BigDecimalAsIfIntegral$;
   0      15      1    x       Ljava/lang/Object;
   0      15      2    y       Ljava/lang/Object;


public int compare(java.lang.Object, java.lang.Object);
  Signature: (Ljava/lang/Object;Ljava/lang/Object;)I
  Code:
   Stack=3, Locals=3, Args_size=3
	aload_0
	aload_1
	checkcast	class scala/math/BigDecimal
	aload_2
	checkcast	class scala/math/BigDecimal
	invokeinterface	InterfaceMethod scala/math/Ordering$BigDecimalOrdering.compare:(Lscala/math/BigDecimal;Lscala/math/BigDecimal;)I
	ireturn
  Labels:
  LocalVariableTable: 
   Start  Length  Slot  Name   Signature
   0      15      0    this       Lscala/math/Numeric$BigDecimalAsIfIntegral$;
   0      15      1    x       Ljava/lang/Object;
   0      15      2    y       Ljava/lang/Object;


public scala.math.Numeric$BigDecimalAsIfIntegral$();
  Signature: ()V
  Code:
   Stack=1, Locals=1, Args_size=1
	aload_0
	invokespecial	Method java/lang/Object."<init>":()V
	aload_0
	putstatic	Field MODULE$:Lscala/math/Numeric$BigDecimalAsIfIntegral$;
	aload_0
	invokestatic	Method scala/math/PartialOrdering$class.$init$:(Lscala/math/PartialOrdering;)V
	aload_0
	invokestatic	Method scala/math/Ordering$class.$init$:(Lscala/math/Ordering;)V
	aload_0
	invokestatic	Method scala/math/Numeric$class.$init$:(Lscala/math/Numeric;)V
	aload_0
	invokestatic	Method scala/math/Numeric$BigDecimalIsConflicted$class.$init$:(Lscala/math/Numeric$BigDecimalIsConflicted;)V
	aload_0
	invokestatic	Method scala/math/Integral$class.$init$:(Lscala/math/Integral;)V
	aload_0
	invokestatic	Method scala/math/Numeric$BigDecimalAsIfIntegral$class.$init$:(Lscala/math/Numeric$BigDecimalAsIfIntegral;)V
	aload_0
	invokestatic	Method scala/math/Ordering$BigDecimalOrdering$class.$init$:(Lscala/math/Ordering$BigDecimalOrdering;)V
	return
  Labels:

}

