Compiled from "Numeric.scala"
public abstract class scala.math.Numeric$BigDecimalAsIfIntegral$class extends java.lang.Object
  SourceFile: "Numeric.scala"
  Scala: length = 0x
   
  InnerClass: 
   public abstract #31= #28 of #30; //BigDecimalAsIfIntegral=class scala/math/Numeric$BigDecimalAsIfIntegral of class scala/math/Numeric
  minor version: 0
  major version: 49
  Constant pool:
const #1 = Asciz	SourceFile;
const #2 = Asciz	Numeric.scala;
const #3 = Asciz	$init$;
const #4 = Asciz	(Lscala/math/Numeric$BigDecimalAsIfIntegral;)V;
const #5 = Asciz	Code;
const #6 = Asciz	LineNumberTable;
const #7 = Asciz	$this;
const #8 = Asciz	Lscala/math/Numeric$BigDecimalAsIfIntegral;;
const #9 = Asciz	LocalVariableTable;
const #10 = Asciz	rem;
const #11 = Asciz	(Lscala/math/Numeric$BigDecimalAsIfIntegral;Lscala/math/BigDecimal;Lscala/math/BigDecimal;)Lscala/math/BigDecimal;;
const #12 = Asciz	scala/math/BigDecimal;
const #13 = class	#12;	//  scala/math/BigDecimal
const #14 = Asciz	remainder;
const #15 = Asciz	(Lscala/math/BigDecimal;)Lscala/math/BigDecimal;;
const #16 = NameAndType	#14:#15;//  remainder:(Lscala/math/BigDecimal;)Lscala/math/BigDecimal;
const #17 = Method	#13.#16;	//  scala/math/BigDecimal.remainder:(Lscala/math/BigDecimal;)Lscala/math/BigDecimal;
const #18 = Asciz	x;
const #19 = Asciz	Lscala/math/BigDecimal;;
const #20 = Asciz	y;
const #21 = Asciz	quot;
const #22 = Asciz	$div;
const #23 = NameAndType	#22:#15;//  $div:(Lscala/math/BigDecimal;)Lscala/math/BigDecimal;
const #24 = Method	#13.#23;	//  scala/math/BigDecimal.$div:(Lscala/math/BigDecimal;)Lscala/math/BigDecimal;
const #25 = Asciz	Scala;
const #26 = Asciz	InnerClasses;
const #27 = Asciz	scala/math/Numeric$BigDecimalAsIfIntegral;
const #28 = class	#27;	//  scala/math/Numeric$BigDecimalAsIfIntegral
const #29 = Asciz	scala/math/Numeric;
const #30 = class	#29;	//  scala/math/Numeric
const #31 = Asciz	BigDecimalAsIfIntegral;
const #32 = Asciz	scala/math/Numeric$BigDecimalAsIfIntegral$class;
const #33 = class	#32;	//  scala/math/Numeric$BigDecimalAsIfIntegral$class
const #34 = Asciz	java/lang/Object;
const #35 = class	#34;	//  java/lang/Object

{
public static void $init$(scala.math.Numeric$BigDecimalAsIfIntegral);
  Code:
   Stack=0, Locals=1, Args_size=1
   0:	return
  LineNumberTable: 
   line 141: 0

  LocalVariableTable: 
   Start  Length  Slot  Name   Signature
   0      1      0    $this       Lscala/math/Numeric$BigDecimalAsIfIntegral;


public static scala.math.BigDecimal rem(scala.math.Numeric$BigDecimalAsIfIntegral, scala.math.BigDecimal, scala.math.BigDecimal);
  Code:
   Stack=2, Locals=3, Args_size=3
   0:	aload_1
   1:	aload_2
   2:	invokevirtual	#17; //Method scala/math/BigDecimal.remainder:(Lscala/math/BigDecimal;)Lscala/math/BigDecimal;
   5:	areturn
  LineNumberTable: 
   line 143: 0

  LocalVariableTable: 
   Start  Length  Slot  Name   Signature
   0      6      0    $this       Lscala/math/Numeric$BigDecimalAsIfIntegral;
   0      6      1    x       Lscala/math/BigDecimal;
   0      6      2    y       Lscala/math/BigDecimal;


public static scala.math.BigDecimal quot(scala.math.Numeric$BigDecimalAsIfIntegral, scala.math.BigDecimal, scala.math.BigDecimal);
  Code:
   Stack=2, Locals=3, Args_size=3
   0:	aload_1
   1:	aload_2
   2:	invokevirtual	#24; //Method scala/math/BigDecimal.$div:(Lscala/math/BigDecimal;)Lscala/math/BigDecimal;
   5:	areturn
  LineNumberTable: 
   line 142: 0

  LocalVariableTable: 
   Start  Length  Slot  Name   Signature
   0      6      0    $this       Lscala/math/Numeric$BigDecimalAsIfIntegral;
   0      6      1    x       Lscala/math/BigDecimal;
   0      6      2    y       Lscala/math/BigDecimal;


}

