Compiled from "Numeric.scala"
public abstract class scala.math.Numeric$class extends java.lang.Object
  SourceFile: "Numeric.scala"
  Scala: length = 0x
   
  InnerClass: 
   public Ops=class scala/math/Numeric$Ops of class scala/math/Numeric
  minor version: 0
  major version: 49
  Constant pool:
Asciz	SourceFile;
Asciz	Numeric.scala;
Asciz	$init$;
Asciz	(Lscala/math/Numeric;)V;
Asciz	Code;
Asciz	LineNumberTable;
Asciz	$this;
Asciz	Lscala/math/Numeric;;
Asciz	LocalVariableTable;
Asciz	mkNumericOps;
Asciz	(Lscala/math/Numeric;Ljava/lang/Object;)Lscala/math/Numeric$Ops;;
Asciz	scala/math/Numeric$Ops;
class	scala/math/Numeric$Ops
Asciz	<init>;
Asciz	(Lscala/math/Numeric;Ljava/lang/Object;)V;
NameAndType	"<init>":(Lscala/math/Numeric;Ljava/lang/Object;)V
Method	scala/math/Numeric$Ops."<init>":(Lscala/math/Numeric;Ljava/lang/Object;)V
Asciz	lhs;
Asciz	Ljava/lang/Object;;
Asciz	signum;
Asciz	(Lscala/math/Numeric;Ljava/lang/Object;)I;
Asciz	scala/math/Numeric;
class	scala/math/Numeric
Asciz	zero;
Asciz	()Ljava/lang/Object;;
NameAndType	zero:()Ljava/lang/Object;
InterfaceMethod	scala/math/Numeric.zero:()Ljava/lang/Object;
Asciz	scala/math/Ordering;
class	scala/math/Ordering
Asciz	lt;
Asciz	(Ljava/lang/Object;Ljava/lang/Object;)Z;
NameAndType	lt:(Ljava/lang/Object;Ljava/lang/Object;)Z
InterfaceMethod	scala/math/Ordering.lt:(Ljava/lang/Object;Ljava/lang/Object;)Z
Asciz	gt;
NameAndType	gt:(Ljava/lang/Object;Ljava/lang/Object;)Z
InterfaceMethod	scala/math/Ordering.gt:(Ljava/lang/Object;Ljava/lang/Object;)Z
Asciz	x;
Asciz	abs;
Asciz	(Lscala/math/Numeric;Ljava/lang/Object;)Ljava/lang/Object;;
Asciz	negate;
Asciz	(Ljava/lang/Object;)Ljava/lang/Object;;
NameAndType	negate:(Ljava/lang/Object;)Ljava/lang/Object;
InterfaceMethod	scala/math/Numeric.negate:(Ljava/lang/Object;)Ljava/lang/Object;
Asciz	one;
Asciz	(Lscala/math/Numeric;)Ljava/lang/Object;;
Asciz	fromInt;
Asciz	(I)Ljava/lang/Object;;
NameAndType	fromInt:(I)Ljava/lang/Object;
InterfaceMethod	scala/math/Numeric.fromInt:(I)Ljava/lang/Object;
Asciz	Scala;
Asciz	InnerClasses;
Asciz	Ops;
Asciz	scala/math/Numeric$class;
class	scala/math/Numeric$class
Asciz	java/lang/Object;
class	java/lang/Object

{
public static void $init$(scala.math.Numeric);
  Signature: (Lscala/math/Numeric;)V
  Code:
   Stack=0, Locals=1, Args_size=1
	return
  Labels:
  LocalVariableTable: 
   Start  Length  Slot  Name   Signature
   0      1      0    $this       Lscala/math/Numeric;


public static scala.math.Numeric$Ops mkNumericOps(scala.math.Numeric, java.lang.Object);
  Signature: (Lscala/math/Numeric;Ljava/lang/Object;)Lscala/math/Numeric$Ops;
  Code:
   Stack=4, Locals=2, Args_size=2
	new	class scala/math/Numeric$Ops
	dup
	aload_0
	aload_1
	invokespecial	Method scala/math/Numeric$Ops."<init>":(Lscala/math/Numeric;Ljava/lang/Object;)V
	areturn
  Labels:
  LocalVariableTable: 
   Start  Length  Slot  Name   Signature
   0      10      0    $this       Lscala/math/Numeric;
   0      10      1    lhs       Ljava/lang/Object;


public static int signum(scala.math.Numeric, java.lang.Object);
  Signature: (Lscala/math/Numeric;Ljava/lang/Object;)I
  Code:
   Stack=3, Locals=2, Args_size=2
	aload_0
	aload_1
	aload_0
	invokeinterface	InterfaceMethod scala/math/Numeric.zero:()Ljava/lang/Object;
	invokeinterface	InterfaceMethod scala/math/Ordering.lt:(Ljava/lang/Object;Ljava/lang/Object;)Z
	ifeq	l1 // aload_0
	iconst_m1
	goto	l2 // ireturn
l1	aload_0
	aload_1
	aload_0
	invokeinterface	InterfaceMethod scala/math/Numeric.zero:()Ljava/lang/Object;
	invokeinterface	InterfaceMethod scala/math/Ordering.gt:(Ljava/lang/Object;Ljava/lang/Object;)Z
	ifeq	l3 // iconst_0
	iconst_1
	goto	l2 // ireturn
l3	iconst_0
l2	ireturn
  Labels:
   	l1 = 20 // aload_0
   	l3 = 40 // iconst_0
   	l2 = 41 // ireturn
  LocalVariableTable: 
   Start  Length  Slot  Name   Signature
   0      42      0    $this       Lscala/math/Numeric;
   0      42      1    x       Ljava/lang/Object;


public static java.lang.Object abs(scala.math.Numeric, java.lang.Object);
  Signature: (Lscala/math/Numeric;Ljava/lang/Object;)Ljava/lang/Object;
  Code:
   Stack=3, Locals=2, Args_size=2
	aload_0
	aload_1
	aload_0
	invokeinterface	InterfaceMethod scala/math/Numeric.zero:()Ljava/lang/Object;
	invokeinterface	InterfaceMethod scala/math/Ordering.lt:(Ljava/lang/Object;Ljava/lang/Object;)Z
	ifeq	l1 // aload_1
	aload_0
	aload_1
	invokeinterface	InterfaceMethod scala/math/Numeric.negate:(Ljava/lang/Object;)Ljava/lang/Object;
	goto	l2 // areturn
l1	aload_1
l2	areturn
  Labels:
   	l1 = 26 // aload_1
   	l2 = 27 // areturn
  LocalVariableTable: 
   Start  Length  Slot  Name   Signature
   0      28      0    $this       Lscala/math/Numeric;
   0      28      1    x       Ljava/lang/Object;


public static java.lang.Object one(scala.math.Numeric);
  Signature: (Lscala/math/Numeric;)Ljava/lang/Object;
  Code:
   Stack=2, Locals=1, Args_size=1
	aload_0
	iconst_1
	invokeinterface	InterfaceMethod scala/math/Numeric.fromInt:(I)Ljava/lang/Object;
	areturn
  Labels:
  LocalVariableTable: 
   Start  Length  Slot  Name   Signature
   0      8      0    $this       Lscala/math/Numeric;


public static java.lang.Object zero(scala.math.Numeric);
  Signature: (Lscala/math/Numeric;)Ljava/lang/Object;
  Code:
   Stack=2, Locals=1, Args_size=1
	aload_0
	iconst_0
	invokeinterface	InterfaceMethod scala/math/Numeric.fromInt:(I)Ljava/lang/Object;
	areturn
  Labels:
  LocalVariableTable: 
   Start  Length  Slot  Name   Signature
   0      8      0    $this       Lscala/math/Numeric;


}

