Compiled from "Numeric.scala"
public final class scala.math.Numeric$ extends java.lang.Object implements scala.ScalaObject
  SourceFile: "Numeric.scala"
  Scala: length = 0x
   
  InnerClass: 
   public #25= #22 of #24; //Ops=class scala/math/Numeric$Ops of class scala/math/Numeric
   public abstract #28= #27 of #24; //IntIsIntegral=class scala/math/Numeric$IntIsIntegral of class scala/math/Numeric
   public abstract #31= #30 of #24; //LongIsIntegral=class scala/math/Numeric$LongIsIntegral of class scala/math/Numeric
   public abstract #34= #33 of #24; //ByteIsIntegral=class scala/math/Numeric$ByteIsIntegral of class scala/math/Numeric
   public abstract #37= #36 of #24; //ShortIsIntegral=class scala/math/Numeric$ShortIsIntegral of class scala/math/Numeric
   public abstract #40= #39 of #24; //BigIntIsIntegral=class scala/math/Numeric$BigIntIsIntegral of class scala/math/Numeric
   public abstract #43= #42 of #24; //FloatIsFractional=class scala/math/Numeric$FloatIsFractional of class scala/math/Numeric
   public abstract #46= #45 of #24; //DoubleAsIfIntegral=class scala/math/Numeric$DoubleAsIfIntegral of class scala/math/Numeric
   public abstract #49= #48 of #24; //DoubleIsFractional=class scala/math/Numeric$DoubleIsFractional of class scala/math/Numeric
   public abstract #52= #51 of #24; //DoubleIsConflicted=class scala/math/Numeric$DoubleIsConflicted of class scala/math/Numeric
   public abstract #55= #54 of #24; //IntIsIntegral$class=class scala/math/Numeric$IntIsIntegral$class of class scala/math/Numeric
   public abstract #58= #57 of #24; //ByteIsIntegral$class=class scala/math/Numeric$ByteIsIntegral$class of class scala/math/Numeric
   public abstract #61= #60 of #24; //LongIsIntegral$class=class scala/math/Numeric$LongIsIntegral$class of class scala/math/Numeric
   public abstract #64= #63 of #24; //ShortIsIntegral$class=class scala/math/Numeric$ShortIsIntegral$class of class scala/math/Numeric
   public abstract #67= #66 of #24; //BigIntIsIntegral$class=class scala/math/Numeric$BigIntIsIntegral$class of class scala/math/Numeric
   public abstract #70= #69 of #24; //BigDecimalAsIfIntegral=class scala/math/Numeric$BigDecimalAsIfIntegral of class scala/math/Numeric
   public abstract #73= #72 of #24; //BigDecimalIsFractional=class scala/math/Numeric$BigDecimalIsFractional of class scala/math/Numeric
   public abstract #76= #75 of #24; //BigDecimalIsConflicted=class scala/math/Numeric$BigDecimalIsConflicted of class scala/math/Numeric
   public abstract #79= #78 of #24; //FloatIsFractional$class=class scala/math/Numeric$FloatIsFractional$class of class scala/math/Numeric
   public abstract #82= #81 of #24; //DoubleIsFractional$class=class scala/math/Numeric$DoubleIsFractional$class of class scala/math/Numeric
   public abstract #85= #84 of #24; //DoubleIsConflicted$class=class scala/math/Numeric$DoubleIsConflicted$class of class scala/math/Numeric
   public abstract #88= #87 of #24; //DoubleAsIfIntegral$class=class scala/math/Numeric$DoubleAsIfIntegral$class of class scala/math/Numeric
   public abstract #91= #90 of #24; //BigDecimalIsFractional$class=class scala/math/Numeric$BigDecimalIsFractional$class of class scala/math/Numeric
   public abstract #94= #93 of #24; //BigDecimalIsConflicted$class=class scala/math/Numeric$BigDecimalIsConflicted$class of class scala/math/Numeric
   public abstract #97= #96 of #24; //BigDecimalAsIfIntegral$class=class scala/math/Numeric$BigDecimalAsIfIntegral$class of class scala/math/Numeric
  minor version: 0
  major version: 49
  Constant pool:
const #1 = Asciz	SourceFile;
const #2 = Asciz	Numeric.scala;
const #3 = Asciz	Scala;
const #4 = Asciz	MODULE$;
const #5 = Asciz	Lscala/math/Numeric$;;
const #6 = Asciz	<clinit>;
const #7 = Asciz	()V;
const #8 = Asciz	Code;
const #9 = Asciz	scala/math/Numeric$;
const #10 = class	#9;	//  scala/math/Numeric$
const #11 = Asciz	<init>;
const #12 = NameAndType	#11:#7;//  "<init>":()V
const #13 = Method	#10.#12;	//  scala/math/Numeric$."<init>":()V
const #14 = Asciz	LineNumberTable;
const #15 = Asciz	java/lang/Object;
const #16 = class	#15;	//  java/lang/Object
const #17 = Method	#16.#12;	//  java/lang/Object."<init>":()V
const #18 = NameAndType	#4:#5;//  MODULE$:Lscala/math/Numeric$;
const #19 = Field	#10.#18;	//  scala/math/Numeric$.MODULE$:Lscala/math/Numeric$;
const #20 = Asciz	InnerClasses;
const #21 = Asciz	scala/math/Numeric$Ops;
const #22 = class	#21;	//  scala/math/Numeric$Ops
const #23 = Asciz	scala/math/Numeric;
const #24 = class	#23;	//  scala/math/Numeric
const #25 = Asciz	Ops;
const #26 = Asciz	scala/math/Numeric$IntIsIntegral;
const #27 = class	#26;	//  scala/math/Numeric$IntIsIntegral
const #28 = Asciz	IntIsIntegral;
const #29 = Asciz	scala/math/Numeric$LongIsIntegral;
const #30 = class	#29;	//  scala/math/Numeric$LongIsIntegral
const #31 = Asciz	LongIsIntegral;
const #32 = Asciz	scala/math/Numeric$ByteIsIntegral;
const #33 = class	#32;	//  scala/math/Numeric$ByteIsIntegral
const #34 = Asciz	ByteIsIntegral;
const #35 = Asciz	scala/math/Numeric$ShortIsIntegral;
const #36 = class	#35;	//  scala/math/Numeric$ShortIsIntegral
const #37 = Asciz	ShortIsIntegral;
const #38 = Asciz	scala/math/Numeric$BigIntIsIntegral;
const #39 = class	#38;	//  scala/math/Numeric$BigIntIsIntegral
const #40 = Asciz	BigIntIsIntegral;
const #41 = Asciz	scala/math/Numeric$FloatIsFractional;
const #42 = class	#41;	//  scala/math/Numeric$FloatIsFractional
const #43 = Asciz	FloatIsFractional;
const #44 = Asciz	scala/math/Numeric$DoubleAsIfIntegral;
const #45 = class	#44;	//  scala/math/Numeric$DoubleAsIfIntegral
const #46 = Asciz	DoubleAsIfIntegral;
const #47 = Asciz	scala/math/Numeric$DoubleIsFractional;
const #48 = class	#47;	//  scala/math/Numeric$DoubleIsFractional
const #49 = Asciz	DoubleIsFractional;
const #50 = Asciz	scala/math/Numeric$DoubleIsConflicted;
const #51 = class	#50;	//  scala/math/Numeric$DoubleIsConflicted
const #52 = Asciz	DoubleIsConflicted;
const #53 = Asciz	scala/math/Numeric$IntIsIntegral$class;
const #54 = class	#53;	//  scala/math/Numeric$IntIsIntegral$class
const #55 = Asciz	IntIsIntegral$class;
const #56 = Asciz	scala/math/Numeric$ByteIsIntegral$class;
const #57 = class	#56;	//  scala/math/Numeric$ByteIsIntegral$class
const #58 = Asciz	ByteIsIntegral$class;
const #59 = Asciz	scala/math/Numeric$LongIsIntegral$class;
const #60 = class	#59;	//  scala/math/Numeric$LongIsIntegral$class
const #61 = Asciz	LongIsIntegral$class;
const #62 = Asciz	scala/math/Numeric$ShortIsIntegral$class;
const #63 = class	#62;	//  scala/math/Numeric$ShortIsIntegral$class
const #64 = Asciz	ShortIsIntegral$class;
const #65 = Asciz	scala/math/Numeric$BigIntIsIntegral$class;
const #66 = class	#65;	//  scala/math/Numeric$BigIntIsIntegral$class
const #67 = Asciz	BigIntIsIntegral$class;
const #68 = Asciz	scala/math/Numeric$BigDecimalAsIfIntegral;
const #69 = class	#68;	//  scala/math/Numeric$BigDecimalAsIfIntegral
const #70 = Asciz	BigDecimalAsIfIntegral;
const #71 = Asciz	scala/math/Numeric$BigDecimalIsFractional;
const #72 = class	#71;	//  scala/math/Numeric$BigDecimalIsFractional
const #73 = Asciz	BigDecimalIsFractional;
const #74 = Asciz	scala/math/Numeric$BigDecimalIsConflicted;
const #75 = class	#74;	//  scala/math/Numeric$BigDecimalIsConflicted
const #76 = Asciz	BigDecimalIsConflicted;
const #77 = Asciz	scala/math/Numeric$FloatIsFractional$class;
const #78 = class	#77;	//  scala/math/Numeric$FloatIsFractional$class
const #79 = Asciz	FloatIsFractional$class;
const #80 = Asciz	scala/math/Numeric$DoubleIsFractional$class;
const #81 = class	#80;	//  scala/math/Numeric$DoubleIsFractional$class
const #82 = Asciz	DoubleIsFractional$class;
const #83 = Asciz	scala/math/Numeric$DoubleIsConflicted$class;
const #84 = class	#83;	//  scala/math/Numeric$DoubleIsConflicted$class
const #85 = Asciz	DoubleIsConflicted$class;
const #86 = Asciz	scala/math/Numeric$DoubleAsIfIntegral$class;
const #87 = class	#86;	//  scala/math/Numeric$DoubleAsIfIntegral$class
const #88 = Asciz	DoubleAsIfIntegral$class;
const #89 = Asciz	scala/math/Numeric$BigDecimalIsFractional$class;
const #90 = class	#89;	//  scala/math/Numeric$BigDecimalIsFractional$class
const #91 = Asciz	BigDecimalIsFractional$class;
const #92 = Asciz	scala/math/Numeric$BigDecimalIsConflicted$class;
const #93 = class	#92;	//  scala/math/Numeric$BigDecimalIsConflicted$class
const #94 = Asciz	BigDecimalIsConflicted$class;
const #95 = Asciz	scala/math/Numeric$BigDecimalAsIfIntegral$class;
const #96 = class	#95;	//  scala/math/Numeric$BigDecimalAsIfIntegral$class
const #97 = Asciz	BigDecimalAsIfIntegral$class;
const #98 = Asciz	scala/ScalaObject;
const #99 = class	#98;	//  scala/ScalaObject

{
public static final scala.math.Numeric$ MODULE$;

public static {};
  Code:
   Stack=1, Locals=0, Args_size=0
   0:	new	#10; //class scala/math/Numeric$
   3:	invokespecial	#13; //Method "<init>":()V
   6:	return

}

