Compiled from "Numeric.scala"
public class scala.math.Numeric$Ops extends java.lang.Object implements scala.ScalaObject
  SourceFile: "Numeric.scala"
  Scala: length = 0x
   
  InnerClass: 
   public #87= #14 of #38; //Ops=class scala/math/Numeric$Ops of class scala/math/Numeric
  minor version: 0
  major version: 49
  Constant pool:
const #1 = Asciz	SourceFile;
const #2 = Asciz	Numeric.scala;
const #3 = Asciz	$outer;
const #4 = Asciz	Lscala/math/Numeric;;
const #5 = Asciz	lhs;
const #6 = Asciz	Ljava/lang/Object;;
const #7 = Asciz	TT;;
const #8 = Asciz	Signature;
const #9 = Asciz	<init>;
const #10 = Asciz	(Lscala/math/Numeric;Ljava/lang/Object;)V;
const #11 = Asciz	Code;
const #12 = Asciz	LineNumberTable;
const #13 = Asciz	scala/math/Numeric$Ops;
const #14 = class	#13;	//  scala/math/Numeric$Ops
const #15 = NameAndType	#5:#6;//  lhs:Ljava/lang/Object;
const #16 = Field	#14.#15;	//  scala/math/Numeric$Ops.lhs:Ljava/lang/Object;
const #17 = Asciz	java/lang/NullPointerException;
const #18 = class	#17;	//  java/lang/NullPointerException
const #19 = Asciz	()V;
const #20 = NameAndType	#9:#19;//  "<init>":()V
const #21 = Method	#18.#20;	//  java/lang/NullPointerException."<init>":()V
const #22 = NameAndType	#3:#4;//  $outer:Lscala/math/Numeric;
const #23 = Field	#14.#22;	//  scala/math/Numeric$Ops.$outer:Lscala/math/Numeric;
const #24 = Asciz	java/lang/Object;
const #25 = class	#24;	//  java/lang/Object
const #26 = Method	#25.#20;	//  java/lang/Object."<init>":()V
const #27 = Asciz	this;
const #28 = Asciz	Lscala/math/Numeric$Ops;;
const #29 = Asciz	LocalVariableTable;
const #30 = Asciz	(Lscala/math/Numeric<TT;>;TT;)V;
const #31 = Asciz	scala$math$Numeric$Ops$$$outer;
const #32 = Asciz	()Lscala/math/Numeric;;
const #33 = Asciz	toDouble;
const #34 = Asciz	()D;
const #35 = NameAndType	#31:#32;//  scala$math$Numeric$Ops$$$outer:()Lscala/math/Numeric;
const #36 = Method	#14.#35;	//  scala/math/Numeric$Ops.scala$math$Numeric$Ops$$$outer:()Lscala/math/Numeric;
const #37 = Asciz	scala/math/Numeric;
const #38 = class	#37;	//  scala/math/Numeric
const #39 = Asciz	(Ljava/lang/Object;)D;
const #40 = NameAndType	#33:#39;//  toDouble:(Ljava/lang/Object;)D
const #41 = InterfaceMethod	#38.#40;	//  scala/math/Numeric.toDouble:(Ljava/lang/Object;)D
const #42 = Asciz	toFloat;
const #43 = Asciz	()F;
const #44 = Asciz	(Ljava/lang/Object;)F;
const #45 = NameAndType	#42:#44;//  toFloat:(Ljava/lang/Object;)F
const #46 = InterfaceMethod	#38.#45;	//  scala/math/Numeric.toFloat:(Ljava/lang/Object;)F
const #47 = Asciz	toLong;
const #48 = Asciz	()J;
const #49 = Asciz	(Ljava/lang/Object;)J;
const #50 = NameAndType	#47:#49;//  toLong:(Ljava/lang/Object;)J
const #51 = InterfaceMethod	#38.#50;	//  scala/math/Numeric.toLong:(Ljava/lang/Object;)J
const #52 = Asciz	toInt;
const #53 = Asciz	()I;
const #54 = Asciz	(Ljava/lang/Object;)I;
const #55 = NameAndType	#52:#54;//  toInt:(Ljava/lang/Object;)I
const #56 = InterfaceMethod	#38.#55;	//  scala/math/Numeric.toInt:(Ljava/lang/Object;)I
const #57 = Asciz	signum;
const #58 = NameAndType	#57:#54;//  signum:(Ljava/lang/Object;)I
const #59 = InterfaceMethod	#38.#58;	//  scala/math/Numeric.signum:(Ljava/lang/Object;)I
const #60 = Asciz	abs;
const #61 = Asciz	()Ljava/lang/Object;;
const #62 = Asciz	(Ljava/lang/Object;)Ljava/lang/Object;;
const #63 = NameAndType	#60:#62;//  abs:(Ljava/lang/Object;)Ljava/lang/Object;
const #64 = InterfaceMethod	#38.#63;	//  scala/math/Numeric.abs:(Ljava/lang/Object;)Ljava/lang/Object;
const #65 = Asciz	()TT;;
const #66 = Asciz	unary_$minus;
const #67 = Asciz	negate;
const #68 = NameAndType	#67:#62;//  negate:(Ljava/lang/Object;)Ljava/lang/Object;
const #69 = InterfaceMethod	#38.#68;	//  scala/math/Numeric.negate:(Ljava/lang/Object;)Ljava/lang/Object;
const #70 = Asciz	$times;
const #71 = Asciz	times;
const #72 = Asciz	(Ljava/lang/Object;Ljava/lang/Object;)Ljava/lang/Object;;
const #73 = NameAndType	#71:#72;//  times:(Ljava/lang/Object;Ljava/lang/Object;)Ljava/lang/Object;
const #74 = InterfaceMethod	#38.#73;	//  scala/math/Numeric.times:(Ljava/lang/Object;Ljava/lang/Object;)Ljava/lang/Object;
const #75 = Asciz	rhs;
const #76 = Asciz	(TT;)TT;;
const #77 = Asciz	$minus;
const #78 = Asciz	minus;
const #79 = NameAndType	#78:#72;//  minus:(Ljava/lang/Object;Ljava/lang/Object;)Ljava/lang/Object;
const #80 = InterfaceMethod	#38.#79;	//  scala/math/Numeric.minus:(Ljava/lang/Object;Ljava/lang/Object;)Ljava/lang/Object;
const #81 = Asciz	$plus;
const #82 = Asciz	plus;
const #83 = NameAndType	#82:#72;//  plus:(Ljava/lang/Object;Ljava/lang/Object;)Ljava/lang/Object;
const #84 = InterfaceMethod	#38.#83;	//  scala/math/Numeric.plus:(Ljava/lang/Object;Ljava/lang/Object;)Ljava/lang/Object;
const #85 = Asciz	Scala;
const #86 = Asciz	InnerClasses;
const #87 = Asciz	Ops;
const #88 = Asciz	scala/ScalaObject;
const #89 = class	#88;	//  scala/ScalaObject

{
public final scala.math.Numeric $outer;

public scala.math.Numeric$Ops(scala.math.Numeric, java.lang.Object);
  Code:
   Stack=2, Locals=3, Args_size=3
   0:	aload_0
   1:	aload_2
   2:	putfield	#16; //Field lhs:Ljava/lang/Object;
   5:	aload_1
   6:	ifnonnull	17
   9:	new	#18; //class java/lang/NullPointerException
   12:	dup
   13:	invokespecial	#21; //Method java/lang/NullPointerException."<init>":()V
   16:	athrow
   17:	aload_0
   18:	aload_1
   19:	putfield	#23; //Field $outer:Lscala/math/Numeric;
   22:	aload_0
   23:	invokespecial	#26; //Method java/lang/Object."<init>":()V
   26:	return
  LineNumberTable: 
   line 175: 0

  LocalVariableTable: 
   Start  Length  Slot  Name   Signature
   0      27      0    this       Lscala/math/Numeric$Ops;
   0      27      1    $outer       Lscala/math/Numeric;
   0      27      2    lhs       Ljava/lang/Object;

  Signature: length = 0x2
   00 1E 

public scala.math.Numeric scala$math$Numeric$Ops$$$outer();
  Code:
   Stack=1, Locals=1, Args_size=1
   0:	aload_0
   1:	getfield	#23; //Field $outer:Lscala/math/Numeric;
   4:	areturn
  LineNumberTable: 
   line 175: 0


public double toDouble();
  Code:
   Stack=2, Locals=1, Args_size=1
   0:	aload_0
   1:	invokevirtual	#36; //Method scala$math$Numeric$Ops$$$outer:()Lscala/math/Numeric;
   4:	aload_0
   5:	getfield	#16; //Field lhs:Ljava/lang/Object;
   8:	invokeinterface	#41,  2; //InterfaceMethod scala/math/Numeric.toDouble:(Ljava/lang/Object;)D
   13:	dreturn
  LineNumberTable: 
   line 185: 0


public float toFloat();
  Code:
   Stack=2, Locals=1, Args_size=1
   0:	aload_0
   1:	invokevirtual	#36; //Method scala$math$Numeric$Ops$$$outer:()Lscala/math/Numeric;
   4:	aload_0
   5:	getfield	#16; //Field lhs:Ljava/lang/Object;
   8:	invokeinterface	#46,  2; //InterfaceMethod scala/math/Numeric.toFloat:(Ljava/lang/Object;)F
   13:	freturn
  LineNumberTable: 
   line 184: 0


public long toLong();
  Code:
   Stack=2, Locals=1, Args_size=1
   0:	aload_0
   1:	invokevirtual	#36; //Method scala$math$Numeric$Ops$$$outer:()Lscala/math/Numeric;
   4:	aload_0
   5:	getfield	#16; //Field lhs:Ljava/lang/Object;
   8:	invokeinterface	#51,  2; //InterfaceMethod scala/math/Numeric.toLong:(Ljava/lang/Object;)J
   13:	lreturn
  LineNumberTable: 
   line 183: 0


public int toInt();
  Code:
   Stack=2, Locals=1, Args_size=1
   0:	aload_0
   1:	invokevirtual	#36; //Method scala$math$Numeric$Ops$$$outer:()Lscala/math/Numeric;
   4:	aload_0
   5:	getfield	#16; //Field lhs:Ljava/lang/Object;
   8:	invokeinterface	#56,  2; //InterfaceMethod scala/math/Numeric.toInt:(Ljava/lang/Object;)I
   13:	ireturn
  LineNumberTable: 
   line 182: 0


public int signum();
  Code:
   Stack=2, Locals=1, Args_size=1
   0:	aload_0
   1:	invokevirtual	#36; //Method scala$math$Numeric$Ops$$$outer:()Lscala/math/Numeric;
   4:	aload_0
   5:	getfield	#16; //Field lhs:Ljava/lang/Object;
   8:	invokeinterface	#59,  2; //InterfaceMethod scala/math/Numeric.signum:(Ljava/lang/Object;)I
   13:	ireturn
  LineNumberTable: 
   line 181: 0


public java.lang.Object abs();
  Code:
   Stack=2, Locals=1, Args_size=1
   0:	aload_0
   1:	invokevirtual	#36; //Method scala$math$Numeric$Ops$$$outer:()Lscala/math/Numeric;
   4:	aload_0
   5:	getfield	#16; //Field lhs:Ljava/lang/Object;
   8:	invokeinterface	#64,  2; //InterfaceMethod scala/math/Numeric.abs:(Ljava/lang/Object;)Ljava/lang/Object;
   13:	areturn
  LineNumberTable: 
   line 180: 0

  Signature: length = 0x2
   00 41 

public java.lang.Object unary_$minus();
  Code:
   Stack=2, Locals=1, Args_size=1
   0:	aload_0
   1:	invokevirtual	#36; //Method scala$math$Numeric$Ops$$$outer:()Lscala/math/Numeric;
   4:	aload_0
   5:	getfield	#16; //Field lhs:Ljava/lang/Object;
   8:	invokeinterface	#69,  2; //InterfaceMethod scala/math/Numeric.negate:(Ljava/lang/Object;)Ljava/lang/Object;
   13:	areturn
  LineNumberTable: 
   line 179: 0

  Signature: length = 0x2
   00 41 

public java.lang.Object $times(java.lang.Object);
  Code:
   Stack=3, Locals=2, Args_size=2
   0:	aload_0
   1:	invokevirtual	#36; //Method scala$math$Numeric$Ops$$$outer:()Lscala/math/Numeric;
   4:	aload_0
   5:	getfield	#16; //Field lhs:Ljava/lang/Object;
   8:	aload_1
   9:	invokeinterface	#74,  3; //InterfaceMethod scala/math/Numeric.times:(Ljava/lang/Object;Ljava/lang/Object;)Ljava/lang/Object;
   14:	areturn
  LineNumberTable: 
   line 178: 0

  LocalVariableTable: 
   Start  Length  Slot  Name   Signature
   0      15      0    this       Lscala/math/Numeric$Ops;
   0      15      1    rhs       Ljava/lang/Object;

  Signature: length = 0x2
   00 4C 

public java.lang.Object $minus(java.lang.Object);
  Code:
   Stack=3, Locals=2, Args_size=2
   0:	aload_0
   1:	invokevirtual	#36; //Method scala$math$Numeric$Ops$$$outer:()Lscala/math/Numeric;
   4:	aload_0
   5:	getfield	#16; //Field lhs:Ljava/lang/Object;
   8:	aload_1
   9:	invokeinterface	#80,  3; //InterfaceMethod scala/math/Numeric.minus:(Ljava/lang/Object;Ljava/lang/Object;)Ljava/lang/Object;
   14:	areturn
  LineNumberTable: 
   line 177: 0

  LocalVariableTable: 
   Start  Length  Slot  Name   Signature
   0      15      0    this       Lscala/math/Numeric$Ops;
   0      15      1    rhs       Ljava/lang/Object;

  Signature: length = 0x2
   00 4C 

public java.lang.Object $plus(java.lang.Object);
  Code:
   Stack=3, Locals=2, Args_size=2
   0:	aload_0
   1:	invokevirtual	#36; //Method scala$math$Numeric$Ops$$$outer:()Lscala/math/Numeric;
   4:	aload_0
   5:	getfield	#16; //Field lhs:Ljava/lang/Object;
   8:	aload_1
   9:	invokeinterface	#84,  3; //InterfaceMethod scala/math/Numeric.plus:(Ljava/lang/Object;Ljava/lang/Object;)Ljava/lang/Object;
   14:	areturn
  LineNumberTable: 
   line 176: 0

  LocalVariableTable: 
   Start  Length  Slot  Name   Signature
   0      15      0    this       Lscala/math/Numeric$Ops;
   0      15      1    rhs       Ljava/lang/Object;

  Signature: length = 0x2
   00 4C 

}

