Compiled from "Numeric.scala"
public final class scala.math.Numeric$DoubleAsIfIntegral$ extends java.lang.Object implements scala.math.Numeric$DoubleAsIfIntegral,scala.math.Ordering$DoubleOrdering,scala.ScalaObject
  SourceFile: "Numeric.scala"
  Scala: length = 0x
   
  InnerClass: 
   public Ops=class scala/math/Numeric$Ops of class scala/math/Numeric
   public Ops=class scala/math/Ordering$Ops of class scala/math/Ordering
   public IntegralOps=class scala/math/Integral$IntegralOps of class scala/math/Integral
   public abstract DoubleOrdering=class scala/math/Ordering$DoubleOrdering of class scala/math/Ordering
   public abstract DoubleIsConflicted=class scala/math/Numeric$DoubleIsConflicted of class scala/math/Numeric
   public abstract DoubleAsIfIntegral=class scala/math/Numeric$DoubleAsIfIntegral of class scala/math/Numeric
  minor version: 0
  major version: 49
  Constant pool:
Asciz	SourceFile;
Asciz	Numeric.scala;
Asciz	Scala;
Asciz	MODULE$;
Asciz	Lscala/math/Numeric$DoubleAsIfIntegral$;;
Asciz	<clinit>;
Asciz	()V;
Asciz	Code;
Asciz	scala/math/Numeric$DoubleAsIfIntegral$;
class	scala/math/Numeric$DoubleAsIfIntegral$
Asciz	<init>;
NameAndType	"<init>":()V
Method	scala/math/Numeric$DoubleAsIfIntegral$."<init>":()V
Asciz	compare;
Asciz	(DD)I;
Asciz	LineNumberTable;
Asciz	scala/math/Ordering$DoubleOrdering$class;
class	scala/math/Ordering$DoubleOrdering$class
Asciz	(Lscala/math/Ordering$DoubleOrdering;DD)I;
NameAndType	compare:(Lscala/math/Ordering$DoubleOrdering;DD)I
Method	scala/math/Ordering$DoubleOrdering$class.compare:(Lscala/math/Ordering$DoubleOrdering;DD)I
Asciz	this;
Asciz	x;
Asciz	D;
Asciz	y;
Asciz	LocalVariableTable;
Asciz	quot;
Asciz	(DD)D;
Asciz	scala/math/Numeric$DoubleAsIfIntegral$class;
class	scala/math/Numeric$DoubleAsIfIntegral$class
Asciz	(Lscala/math/Numeric$DoubleAsIfIntegral;DD)D;
NameAndType	quot:(Lscala/math/Numeric$DoubleAsIfIntegral;DD)D
Method	scala/math/Numeric$DoubleAsIfIntegral$class.quot:(Lscala/math/Numeric$DoubleAsIfIntegral;DD)D
Asciz	rem;
NameAndType	rem:(Lscala/math/Numeric$DoubleAsIfIntegral;DD)D
Method	scala/math/Numeric$DoubleAsIfIntegral$class.rem:(Lscala/math/Numeric$DoubleAsIfIntegral;DD)D
Asciz	mkNumericOps;
Asciz	(Ljava/lang/Object;)Lscala/math/Integral$IntegralOps;;
Asciz	scala/math/Integral$class;
class	scala/math/Integral$class
Asciz	(Lscala/math/Integral;Ljava/lang/Object;)Lscala/math/Integral$IntegralOps;;
NameAndType	mkNumericOps:(Lscala/math/Integral;Ljava/lang/Object;)Lscala/math/Integral$IntegralOps;
Method	scala/math/Integral$class.mkNumericOps:(Lscala/math/Integral;Ljava/lang/Object;)Lscala/math/Integral$IntegralOps;
Asciz	lhs;
Asciz	Ljava/lang/Object;;
Asciz	Signature;
Asciz	plus;
Asciz	scala/math/Numeric$DoubleIsConflicted$class;
class	scala/math/Numeric$DoubleIsConflicted$class
Asciz	(Lscala/math/Numeric$DoubleIsConflicted;DD)D;
NameAndType	plus:(Lscala/math/Numeric$DoubleIsConflicted;DD)D
Method	scala/math/Numeric$DoubleIsConflicted$class.plus:(Lscala/math/Numeric$DoubleIsConflicted;DD)D
Asciz	minus;
NameAndType	minus:(Lscala/math/Numeric$DoubleIsConflicted;DD)D
Method	scala/math/Numeric$DoubleIsConflicted$class.minus:(Lscala/math/Numeric$DoubleIsConflicted;DD)D
Asciz	times;
NameAndType	times:(Lscala/math/Numeric$DoubleIsConflicted;DD)D
Method	scala/math/Numeric$DoubleIsConflicted$class.times:(Lscala/math/Numeric$DoubleIsConflicted;DD)D
Asciz	negate;
Asciz	(D)D;
Asciz	(Lscala/math/Numeric$DoubleIsConflicted;D)D;
NameAndType	negate:(Lscala/math/Numeric$DoubleIsConflicted;D)D
Method	scala/math/Numeric$DoubleIsConflicted$class.negate:(Lscala/math/Numeric$DoubleIsConflicted;D)D
Asciz	fromInt;
Asciz	(I)D;
Asciz	(Lscala/math/Numeric$DoubleIsConflicted;I)D;
NameAndType	fromInt:(Lscala/math/Numeric$DoubleIsConflicted;I)D
Method	scala/math/Numeric$DoubleIsConflicted$class.fromInt:(Lscala/math/Numeric$DoubleIsConflicted;I)D
Asciz	I;
Asciz	toInt;
Asciz	(D)I;
Asciz	(Lscala/math/Numeric$DoubleIsConflicted;D)I;
NameAndType	toInt:(Lscala/math/Numeric$DoubleIsConflicted;D)I
Method	scala/math/Numeric$DoubleIsConflicted$class.toInt:(Lscala/math/Numeric$DoubleIsConflicted;D)I
Asciz	toLong;
Asciz	(D)J;
Asciz	(Lscala/math/Numeric$DoubleIsConflicted;D)J;
NameAndType	toLong:(Lscala/math/Numeric$DoubleIsConflicted;D)J
Method	scala/math/Numeric$DoubleIsConflicted$class.toLong:(Lscala/math/Numeric$DoubleIsConflicted;D)J
Asciz	toFloat;
Asciz	(D)F;
Asciz	(Lscala/math/Numeric$DoubleIsConflicted;D)F;
NameAndType	toFloat:(Lscala/math/Numeric$DoubleIsConflicted;D)F
Method	scala/math/Numeric$DoubleIsConflicted$class.toFloat:(Lscala/math/Numeric$DoubleIsConflicted;D)F
Asciz	toDouble;
NameAndType	toDouble:(Lscala/math/Numeric$DoubleIsConflicted;D)D
Method	scala/math/Numeric$DoubleIsConflicted$class.toDouble:(Lscala/math/Numeric$DoubleIsConflicted;D)D
Asciz	zero;
Asciz	()Ljava/lang/Object;;
Asciz	scala/math/Numeric$class;
class	scala/math/Numeric$class
Asciz	(Lscala/math/Numeric;)Ljava/lang/Object;;
NameAndType	zero:(Lscala/math/Numeric;)Ljava/lang/Object;
Method	scala/math/Numeric$class.zero:(Lscala/math/Numeric;)Ljava/lang/Object;
Asciz	one;
NameAndType	one:(Lscala/math/Numeric;)Ljava/lang/Object;
Method	scala/math/Numeric$class.one:(Lscala/math/Numeric;)Ljava/lang/Object;
Asciz	abs;
Asciz	(Ljava/lang/Object;)Ljava/lang/Object;;
Asciz	(Lscala/math/Numeric;Ljava/lang/Object;)Ljava/lang/Object;;
NameAndType	abs:(Lscala/math/Numeric;Ljava/lang/Object;)Ljava/lang/Object;
Method	scala/math/Numeric$class.abs:(Lscala/math/Numeric;Ljava/lang/Object;)Ljava/lang/Object;
Asciz	signum;
Asciz	(Ljava/lang/Object;)I;
Asciz	(Lscala/math/Numeric;Ljava/lang/Object;)I;
NameAndType	signum:(Lscala/math/Numeric;Ljava/lang/Object;)I
Method	scala/math/Numeric$class.signum:(Lscala/math/Numeric;Ljava/lang/Object;)I
Asciz	tryCompare;
Asciz	(Ljava/lang/Object;Ljava/lang/Object;)Lscala/Some;;
Asciz	scala/math/Ordering$class;
class	scala/math/Ordering$class
Asciz	(Lscala/math/Ordering;Ljava/lang/Object;Ljava/lang/Object;)Lscala/Some;;
NameAndType	tryCompare:(Lscala/math/Ordering;Ljava/lang/Object;Ljava/lang/Object;)Lscala/Some;
Method	scala/math/Ordering$class.tryCompare:(Lscala/math/Ordering;Ljava/lang/Object;Ljava/lang/Object;)Lscala/Some;
Asciz	lteq;
Asciz	(Ljava/lang/Object;Ljava/lang/Object;)Z;
Asciz	(Lscala/math/Ordering;Ljava/lang/Object;Ljava/lang/Object;)Z;
NameAndType	lteq:(Lscala/math/Ordering;Ljava/lang/Object;Ljava/lang/Object;)Z
Method	scala/math/Ordering$class.lteq:(Lscala/math/Ordering;Ljava/lang/Object;Ljava/lang/Object;)Z
Asciz	gteq;
NameAndType	gteq:(Lscala/math/Ordering;Ljava/lang/Object;Ljava/lang/Object;)Z
Method	scala/math/Ordering$class.gteq:(Lscala/math/Ordering;Ljava/lang/Object;Ljava/lang/Object;)Z
Asciz	lt;
NameAndType	lt:(Lscala/math/Ordering;Ljava/lang/Object;Ljava/lang/Object;)Z
Method	scala/math/Ordering$class.lt:(Lscala/math/Ordering;Ljava/lang/Object;Ljava/lang/Object;)Z
Asciz	gt;
NameAndType	gt:(Lscala/math/Ordering;Ljava/lang/Object;Ljava/lang/Object;)Z
Method	scala/math/Ordering$class.gt:(Lscala/math/Ordering;Ljava/lang/Object;Ljava/lang/Object;)Z
Asciz	equiv;
NameAndType	equiv:(Lscala/math/Ordering;Ljava/lang/Object;Ljava/lang/Object;)Z
Method	scala/math/Ordering$class.equiv:(Lscala/math/Ordering;Ljava/lang/Object;Ljava/lang/Object;)Z
Asciz	max;
Asciz	(Ljava/lang/Object;Ljava/lang/Object;)Ljava/lang/Object;;
Asciz	(Lscala/math/Ordering;Ljava/lang/Object;Ljava/lang/Object;)Ljava/lang/Object;;
NameAndType	max:(Lscala/math/Ordering;Ljava/lang/Object;Ljava/lang/Object;)Ljava/lang/Object;
Method	scala/math/Ordering$class.max:(Lscala/math/Ordering;Ljava/lang/Object;Ljava/lang/Object;)Ljava/lang/Object;
Asciz	min;
NameAndType	min:(Lscala/math/Ordering;Ljava/lang/Object;Ljava/lang/Object;)Ljava/lang/Object;
Method	scala/math/Ordering$class.min:(Lscala/math/Ordering;Ljava/lang/Object;Ljava/lang/Object;)Ljava/lang/Object;
Asciz	reverse;
Asciz	()Lscala/math/Ordering;;
Asciz	(Lscala/math/Ordering;)Lscala/math/Ordering;;
NameAndType	reverse:(Lscala/math/Ordering;)Lscala/math/Ordering;
Method	scala/math/Ordering$class.reverse:(Lscala/math/Ordering;)Lscala/math/Ordering;
Asciz	on;
Asciz	(Lscala/Function1;)Lscala/math/Ordering;;
Asciz	(Lscala/math/Ordering;Lscala/Function1;)Lscala/math/Ordering;;
NameAndType	on:(Lscala/math/Ordering;Lscala/Function1;)Lscala/math/Ordering;
Method	scala/math/Ordering$class.on:(Lscala/math/Ordering;Lscala/Function1;)Lscala/math/Ordering;
Asciz	f;
Asciz	Lscala/Function1;;
Asciz	mkOrderingOps;
Asciz	(Ljava/lang/Object;)Lscala/math/Ordering$Ops;;
Asciz	(Lscala/math/Ordering;Ljava/lang/Object;)Lscala/math/Ordering$Ops;;
NameAndType	mkOrderingOps:(Lscala/math/Ordering;Ljava/lang/Object;)Lscala/math/Ordering$Ops;
Method	scala/math/Ordering$class.mkOrderingOps:(Lscala/math/Ordering;Ljava/lang/Object;)Lscala/math/Ordering$Ops;
Asciz	()Lscala/math/PartialOrdering;;
Asciz	scala/math/Ordering;
class	scala/math/Ordering
NameAndType	reverse:()Lscala/math/Ordering;
InterfaceMethod	scala/math/Ordering.reverse:()Lscala/math/Ordering;
Asciz	(Ljava/lang/Object;Ljava/lang/Object;)Lscala/Option;;
NameAndType	tryCompare:(Ljava/lang/Object;Ljava/lang/Object;)Lscala/Some;
InterfaceMethod	scala/math/Ordering.tryCompare:(Ljava/lang/Object;Ljava/lang/Object;)Lscala/Some;
Asciz	(Ljava/lang/Object;)D;
Asciz	scala/runtime/BoxesRunTime;
class	scala/runtime/BoxesRunTime
Asciz	unboxToDouble;
NameAndType	unboxToDouble:(Ljava/lang/Object;)D
Method	scala/runtime/BoxesRunTime.unboxToDouble:(Ljava/lang/Object;)D
Asciz	scala/math/Numeric$DoubleIsConflicted;
class	scala/math/Numeric$DoubleIsConflicted
NameAndType	toDouble:(D)D
InterfaceMethod	scala/math/Numeric$DoubleIsConflicted.toDouble:(D)D
Asciz	(Ljava/lang/Object;)F;
NameAndType	toFloat:(D)F
InterfaceMethod	scala/math/Numeric$DoubleIsConflicted.toFloat:(D)F
Asciz	(Ljava/lang/Object;)J;
NameAndType	toLong:(D)J
InterfaceMethod	scala/math/Numeric$DoubleIsConflicted.toLong:(D)J
NameAndType	toInt:(D)I
InterfaceMethod	scala/math/Numeric$DoubleIsConflicted.toInt:(D)I
Asciz	(I)Ljava/lang/Object;;
NameAndType	fromInt:(I)D
InterfaceMethod	scala/math/Numeric$DoubleIsConflicted.fromInt:(I)D
Asciz	boxToDouble;
Asciz	(D)Ljava/lang/Double;;
NameAndType	boxToDouble:(D)Ljava/lang/Double;
Method	scala/runtime/BoxesRunTime.boxToDouble:(D)Ljava/lang/Double;
NameAndType	negate:(D)D
InterfaceMethod	scala/math/Numeric$DoubleIsConflicted.negate:(D)D
NameAndType	times:(DD)D
InterfaceMethod	scala/math/Numeric$DoubleIsConflicted.times:(DD)D
NameAndType	minus:(DD)D
InterfaceMethod	scala/math/Numeric$DoubleIsConflicted.minus:(DD)D
NameAndType	plus:(DD)D
InterfaceMethod	scala/math/Numeric$DoubleIsConflicted.plus:(DD)D
Asciz	(Ljava/lang/Object;)Lscala/math/Numeric$Ops;;
Asciz	scala/math/Integral;
class	scala/math/Integral
NameAndType	mkNumericOps:(Ljava/lang/Object;)Lscala/math/Integral$IntegralOps;
InterfaceMethod	scala/math/Integral.mkNumericOps:(Ljava/lang/Object;)Lscala/math/Integral$IntegralOps;
Asciz	scala/math/Numeric$DoubleAsIfIntegral;
class	scala/math/Numeric$DoubleAsIfIntegral
NameAndType	rem:(DD)D
InterfaceMethod	scala/math/Numeric$DoubleAsIfIntegral.rem:(DD)D
NameAndType	quot:(DD)D
InterfaceMethod	scala/math/Numeric$DoubleAsIfIntegral.quot:(DD)D
Asciz	(Ljava/lang/Object;Ljava/lang/Object;)I;
Asciz	scala/math/Ordering$DoubleOrdering;
class	scala/math/Ordering$DoubleOrdering
NameAndType	compare:(DD)I
InterfaceMethod	scala/math/Ordering$DoubleOrdering.compare:(DD)I
Asciz	java/lang/Object;
class	java/lang/Object
Method	java/lang/Object."<init>":()V
NameAndType	MODULE$:Lscala/math/Numeric$DoubleAsIfIntegral$;
Field	scala/math/Numeric$DoubleAsIfIntegral$.MODULE$:Lscala/math/Numeric$DoubleAsIfIntegral$;
Asciz	scala/math/PartialOrdering$class;
class	scala/math/PartialOrdering$class
Asciz	$init$;
Asciz	(Lscala/math/PartialOrdering;)V;
NameAndType	$init$:(Lscala/math/PartialOrdering;)V
Method	scala/math/PartialOrdering$class.$init$:(Lscala/math/PartialOrdering;)V
Asciz	(Lscala/math/Ordering;)V;
NameAndType	$init$:(Lscala/math/Ordering;)V
Method	scala/math/Ordering$class.$init$:(Lscala/math/Ordering;)V
Asciz	(Lscala/math/Numeric;)V;
NameAndType	$init$:(Lscala/math/Numeric;)V
Method	scala/math/Numeric$class.$init$:(Lscala/math/Numeric;)V
Asciz	(Lscala/math/Numeric$DoubleIsConflicted;)V;
NameAndType	$init$:(Lscala/math/Numeric$DoubleIsConflicted;)V
Method	scala/math/Numeric$DoubleIsConflicted$class.$init$:(Lscala/math/Numeric$DoubleIsConflicted;)V
Asciz	(Lscala/math/Integral;)V;
NameAndType	$init$:(Lscala/math/Integral;)V
Method	scala/math/Integral$class.$init$:(Lscala/math/Integral;)V
Asciz	(Lscala/math/Numeric$DoubleAsIfIntegral;)V;
NameAndType	$init$:(Lscala/math/Numeric$DoubleAsIfIntegral;)V
Method	scala/math/Numeric$DoubleAsIfIntegral$class.$init$:(Lscala/math/Numeric$DoubleAsIfIntegral;)V
Asciz	(Lscala/math/Ordering$DoubleOrdering;)V;
NameAndType	$init$:(Lscala/math/Ordering$DoubleOrdering;)V
Method	scala/math/Ordering$DoubleOrdering$class.$init$:(Lscala/math/Ordering$DoubleOrdering;)V
Asciz	InnerClasses;
Asciz	scala/math/Numeric$Ops;
class	scala/math/Numeric$Ops
Asciz	scala/math/Numeric;
class	scala/math/Numeric
Asciz	Ops;
Asciz	scala/math/Ordering$Ops;
class	scala/math/Ordering$Ops
Asciz	scala/math/Integral$IntegralOps;
class	scala/math/Integral$IntegralOps
Asciz	IntegralOps;
Asciz	DoubleOrdering;
Asciz	DoubleIsConflicted;
Asciz	DoubleAsIfIntegral;
Asciz	scala/ScalaObject;
class	scala/ScalaObject

{
public static final scala.math.Numeric$DoubleAsIfIntegral$ MODULE$;
  Signature: Lscala/math/Numeric$DoubleAsIfIntegral$;

public static {};
  Signature: ()V
  Code:
   Stack=1, Locals=0, Args_size=0
	new	class scala/math/Numeric$DoubleAsIfIntegral$
	invokespecial	Method "<init>":()V
	return
  Labels:

public int compare(double, double);
  Signature: (DD)I
  Code:
   Stack=5, Locals=5, Args_size=3
	aload_0
	dload_1
	dload_3
	invokestatic	Method scala/math/Ordering$DoubleOrdering$class.compare:(Lscala/math/Ordering$DoubleOrdering;DD)I
	ireturn
  Labels:
  LocalVariableTable: 
   Start  Length  Slot  Name   Signature
   0      7      0    this       Lscala/math/Numeric$DoubleAsIfIntegral$;
   0      7      1    x       D
   0      7      3    y       D


public double quot(double, double);
  Signature: (DD)D
  Code:
   Stack=5, Locals=5, Args_size=3
	aload_0
	dload_1
	dload_3
	invokestatic	Method scala/math/Numeric$DoubleAsIfIntegral$class.quot:(Lscala/math/Numeric$DoubleAsIfIntegral;DD)D
	dreturn
  Labels:
  LocalVariableTable: 
   Start  Length  Slot  Name   Signature
   0      7      0    this       Lscala/math/Numeric$DoubleAsIfIntegral$;
   0      7      1    x       D
   0      7      3    y       D


public double rem(double, double);
  Signature: (DD)D
  Code:
   Stack=5, Locals=5, Args_size=3
	aload_0
	dload_1
	dload_3
	invokestatic	Method scala/math/Numeric$DoubleAsIfIntegral$class.rem:(Lscala/math/Numeric$DoubleAsIfIntegral;DD)D
	dreturn
  Labels:
  LocalVariableTable: 
   Start  Length  Slot  Name   Signature
   0      7      0    this       Lscala/math/Numeric$DoubleAsIfIntegral$;
   0      7      1    x       D
   0      7      3    y       D


public scala.math.Integral$IntegralOps mkNumericOps(java.lang.Object);
  Signature: (Ljava/lang/Object;)Lscala/math/Integral$IntegralOps;
  Code:
   Stack=2, Locals=2, Args_size=2
	aload_0
	aload_1
	invokestatic	Method scala/math/Integral$class.mkNumericOps:(Lscala/math/Integral;Ljava/lang/Object;)Lscala/math/Integral$IntegralOps;
	areturn
  Labels:
  LocalVariableTable: 
   Start  Length  Slot  Name   Signature
   0      6      0    this       Lscala/math/Numeric$DoubleAsIfIntegral$;
   0      6      1    lhs       Ljava/lang/Object;

  Signature: length = 0x2
   00 26 

public double plus(double, double);
  Signature: (DD)D
  Code:
   Stack=5, Locals=5, Args_size=3
	aload_0
	dload_1
	dload_3
	invokestatic	Method scala/math/Numeric$DoubleIsConflicted$class.plus:(Lscala/math/Numeric$DoubleIsConflicted;DD)D
	dreturn
  Labels:
  LocalVariableTable: 
   Start  Length  Slot  Name   Signature
   0      7      0    this       Lscala/math/Numeric$DoubleAsIfIntegral$;
   0      7      1    x       D
   0      7      3    y       D


public double minus(double, double);
  Signature: (DD)D
  Code:
   Stack=5, Locals=5, Args_size=3
	aload_0
	dload_1
	dload_3
	invokestatic	Method scala/math/Numeric$DoubleIsConflicted$class.minus:(Lscala/math/Numeric$DoubleIsConflicted;DD)D
	dreturn
  Labels:
  LocalVariableTable: 
   Start  Length  Slot  Name   Signature
   0      7      0    this       Lscala/math/Numeric$DoubleAsIfIntegral$;
   0      7      1    x       D
   0      7      3    y       D


public double times(double, double);
  Signature: (DD)D
  Code:
   Stack=5, Locals=5, Args_size=3
	aload_0
	dload_1
	dload_3
	invokestatic	Method scala/math/Numeric$DoubleIsConflicted$class.times:(Lscala/math/Numeric$DoubleIsConflicted;DD)D
	dreturn
  Labels:
  LocalVariableTable: 
   Start  Length  Slot  Name   Signature
   0      7      0    this       Lscala/math/Numeric$DoubleAsIfIntegral$;
   0      7      1    x       D
   0      7      3    y       D


public double negate(double);
  Signature: (D)D
  Code:
   Stack=3, Locals=3, Args_size=2
	aload_0
	dload_1
	invokestatic	Method scala/math/Numeric$DoubleIsConflicted$class.negate:(Lscala/math/Numeric$DoubleIsConflicted;D)D
	dreturn
  Labels:
  LocalVariableTable: 
   Start  Length  Slot  Name   Signature
   0      6      0    this       Lscala/math/Numeric$DoubleAsIfIntegral$;
   0      6      1    x       D


public double fromInt(int);
  Signature: (I)D
  Code:
   Stack=2, Locals=2, Args_size=2
	aload_0
	iload_1
	invokestatic	Method scala/math/Numeric$DoubleIsConflicted$class.fromInt:(Lscala/math/Numeric$DoubleIsConflicted;I)D
	dreturn
  Labels:
  LocalVariableTable: 
   Start  Length  Slot  Name   Signature
   0      6      0    this       Lscala/math/Numeric$DoubleAsIfIntegral$;
   0      6      1    x       I


public int toInt(double);
  Signature: (D)I
  Code:
   Stack=3, Locals=3, Args_size=2
	aload_0
	dload_1
	invokestatic	Method scala/math/Numeric$DoubleIsConflicted$class.toInt:(Lscala/math/Numeric$DoubleIsConflicted;D)I
	ireturn
  Labels:
  LocalVariableTable: 
   Start  Length  Slot  Name   Signature
   0      6      0    this       Lscala/math/Numeric$DoubleAsIfIntegral$;
   0      6      1    x       D


public long toLong(double);
  Signature: (D)J
  Code:
   Stack=3, Locals=3, Args_size=2
	aload_0
	dload_1
	invokestatic	Method scala/math/Numeric$DoubleIsConflicted$class.toLong:(Lscala/math/Numeric$DoubleIsConflicted;D)J
	lreturn
  Labels:
  LocalVariableTable: 
   Start  Length  Slot  Name   Signature
   0      6      0    this       Lscala/math/Numeric$DoubleAsIfIntegral$;
   0      6      1    x       D


public float toFloat(double);
  Signature: (D)F
  Code:
   Stack=3, Locals=3, Args_size=2
	aload_0
	dload_1
	invokestatic	Method scala/math/Numeric$DoubleIsConflicted$class.toFloat:(Lscala/math/Numeric$DoubleIsConflicted;D)F
	freturn
  Labels:
  LocalVariableTable: 
   Start  Length  Slot  Name   Signature
   0      6      0    this       Lscala/math/Numeric$DoubleAsIfIntegral$;
   0      6      1    x       D


public double toDouble(double);
  Signature: (D)D
  Code:
   Stack=3, Locals=3, Args_size=2
	aload_0
	dload_1
	invokestatic	Method scala/math/Numeric$DoubleIsConflicted$class.toDouble:(Lscala/math/Numeric$DoubleIsConflicted;D)D
	dreturn
  Labels:
  LocalVariableTable: 
   Start  Length  Slot  Name   Signature
   0      6      0    this       Lscala/math/Numeric$DoubleAsIfIntegral$;
   0      6      1    x       D


public java.lang.Object zero();
  Signature: ()Ljava/lang/Object;
  Code:
   Stack=1, Locals=1, Args_size=1
	aload_0
	invokestatic	Method scala/math/Numeric$class.zero:(Lscala/math/Numeric;)Ljava/lang/Object;
	areturn
  Labels:

public java.lang.Object one();
  Signature: ()Ljava/lang/Object;
  Code:
   Stack=1, Locals=1, Args_size=1
	aload_0
	invokestatic	Method scala/math/Numeric$class.one:(Lscala/math/Numeric;)Ljava/lang/Object;
	areturn
  Labels:

public java.lang.Object abs(java.lang.Object);
  Signature: (Ljava/lang/Object;)Ljava/lang/Object;
  Code:
   Stack=2, Locals=2, Args_size=2
	aload_0
	aload_1
	invokestatic	Method scala/math/Numeric$class.abs:(Lscala/math/Numeric;Ljava/lang/Object;)Ljava/lang/Object;
	areturn
  Labels:
  LocalVariableTable: 
   Start  Length  Slot  Name   Signature
   0      6      0    this       Lscala/math/Numeric$DoubleAsIfIntegral$;
   0      6      1    x       Ljava/lang/Object;


public int signum(java.lang.Object);
  Signature: (Ljava/lang/Object;)I
  Code:
   Stack=2, Locals=2, Args_size=2
	aload_0
	aload_1
	invokestatic	Method scala/math/Numeric$class.signum:(Lscala/math/Numeric;Ljava/lang/Object;)I
	ireturn
  Labels:
  LocalVariableTable: 
   Start  Length  Slot  Name   Signature
   0      6      0    this       Lscala/math/Numeric$DoubleAsIfIntegral$;
   0      6      1    x       Ljava/lang/Object;


public scala.Some tryCompare(java.lang.Object, java.lang.Object);
  Signature: (Ljava/lang/Object;Ljava/lang/Object;)Lscala/Some;
  Code:
   Stack=3, Locals=3, Args_size=3
	aload_0
	aload_1
	aload_2
	invokestatic	Method scala/math/Ordering$class.tryCompare:(Lscala/math/Ordering;Ljava/lang/Object;Ljava/lang/Object;)Lscala/Some;
	areturn
  Labels:
  LocalVariableTable: 
   Start  Length  Slot  Name   Signature
   0      7      0    this       Lscala/math/Numeric$DoubleAsIfIntegral$;
   0      7      1    x       Ljava/lang/Object;
   0      7      2    y       Ljava/lang/Object;


public boolean lteq(java.lang.Object, java.lang.Object);
  Signature: (Ljava/lang/Object;Ljava/lang/Object;)Z
  Code:
   Stack=3, Locals=3, Args_size=3
	aload_0
	aload_1
	aload_2
	invokestatic	Method scala/math/Ordering$class.lteq:(Lscala/math/Ordering;Ljava/lang/Object;Ljava/lang/Object;)Z
	ireturn
  Labels:
  LocalVariableTable: 
   Start  Length  Slot  Name   Signature
   0      7      0    this       Lscala/math/Numeric$DoubleAsIfIntegral$;
   0      7      1    x       Ljava/lang/Object;
   0      7      2    y       Ljava/lang/Object;


public boolean gteq(java.lang.Object, java.lang.Object);
  Signature: (Ljava/lang/Object;Ljava/lang/Object;)Z
  Code:
   Stack=3, Locals=3, Args_size=3
	aload_0
	aload_1
	aload_2
	invokestatic	Method scala/math/Ordering$class.gteq:(Lscala/math/Ordering;Ljava/lang/Object;Ljava/lang/Object;)Z
	ireturn
  Labels:
  LocalVariableTable: 
   Start  Length  Slot  Name   Signature
   0      7      0    this       Lscala/math/Numeric$DoubleAsIfIntegral$;
   0      7      1    x       Ljava/lang/Object;
   0      7      2    y       Ljava/lang/Object;


public boolean lt(java.lang.Object, java.lang.Object);
  Signature: (Ljava/lang/Object;Ljava/lang/Object;)Z
  Code:
   Stack=3, Locals=3, Args_size=3
	aload_0
	aload_1
	aload_2
	invokestatic	Method scala/math/Ordering$class.lt:(Lscala/math/Ordering;Ljava/lang/Object;Ljava/lang/Object;)Z
	ireturn
  Labels:
  LocalVariableTable: 
   Start  Length  Slot  Name   Signature
   0      7      0    this       Lscala/math/Numeric$DoubleAsIfIntegral$;
   0      7      1    x       Ljava/lang/Object;
   0      7      2    y       Ljava/lang/Object;


public boolean gt(java.lang.Object, java.lang.Object);
  Signature: (Ljava/lang/Object;Ljava/lang/Object;)Z
  Code:
   Stack=3, Locals=3, Args_size=3
	aload_0
	aload_1
	aload_2
	invokestatic	Method scala/math/Ordering$class.gt:(Lscala/math/Ordering;Ljava/lang/Object;Ljava/lang/Object;)Z
	ireturn
  Labels:
  LocalVariableTable: 
   Start  Length  Slot  Name   Signature
   0      7      0    this       Lscala/math/Numeric$DoubleAsIfIntegral$;
   0      7      1    x       Ljava/lang/Object;
   0      7      2    y       Ljava/lang/Object;


public boolean equiv(java.lang.Object, java.lang.Object);
  Signature: (Ljava/lang/Object;Ljava/lang/Object;)Z
  Code:
   Stack=3, Locals=3, Args_size=3
	aload_0
	aload_1
	aload_2
	invokestatic	Method scala/math/Ordering$class.equiv:(Lscala/math/Ordering;Ljava/lang/Object;Ljava/lang/Object;)Z
	ireturn
  Labels:
  LocalVariableTable: 
   Start  Length  Slot  Name   Signature
   0      7      0    this       Lscala/math/Numeric$DoubleAsIfIntegral$;
   0      7      1    x       Ljava/lang/Object;
   0      7      2    y       Ljava/lang/Object;


public java.lang.Object max(java.lang.Object, java.lang.Object);
  Signature: (Ljava/lang/Object;Ljava/lang/Object;)Ljava/lang/Object;
  Code:
   Stack=3, Locals=3, Args_size=3
	aload_0
	aload_1
	aload_2
	invokestatic	Method scala/math/Ordering$class.max:(Lscala/math/Ordering;Ljava/lang/Object;Ljava/lang/Object;)Ljava/lang/Object;
	areturn
  Labels:
  LocalVariableTable: 
   Start  Length  Slot  Name   Signature
   0      7      0    this       Lscala/math/Numeric$DoubleAsIfIntegral$;
   0      7      1    x       Ljava/lang/Object;
   0      7      2    y       Ljava/lang/Object;


public java.lang.Object min(java.lang.Object, java.lang.Object);
  Signature: (Ljava/lang/Object;Ljava/lang/Object;)Ljava/lang/Object;
  Code:
   Stack=3, Locals=3, Args_size=3
	aload_0
	aload_1
	aload_2
	invokestatic	Method scala/math/Ordering$class.min:(Lscala/math/Ordering;Ljava/lang/Object;Ljava/lang/Object;)Ljava/lang/Object;
	areturn
  Labels:
  LocalVariableTable: 
   Start  Length  Slot  Name   Signature
   0      7      0    this       Lscala/math/Numeric$DoubleAsIfIntegral$;
   0      7      1    x       Ljava/lang/Object;
   0      7      2    y       Ljava/lang/Object;


public scala.math.Ordering reverse();
  Signature: ()Lscala/math/Ordering;
  Code:
   Stack=1, Locals=1, Args_size=1
	aload_0
	invokestatic	Method scala/math/Ordering$class.reverse:(Lscala/math/Ordering;)Lscala/math/Ordering;
	areturn
  Labels:

public scala.math.Ordering on(scala.Function1);
  Signature: (Lscala/Function1;)Lscala/math/Ordering;
  Code:
   Stack=2, Locals=2, Args_size=2
	aload_0
	aload_1
	invokestatic	Method scala/math/Ordering$class.on:(Lscala/math/Ordering;Lscala/Function1;)Lscala/math/Ordering;
	areturn
  Labels:
  LocalVariableTable: 
   Start  Length  Slot  Name   Signature
   0      6      0    this       Lscala/math/Numeric$DoubleAsIfIntegral$;
   0      6      1    f       Lscala/Function1;


public scala.math.Ordering$Ops mkOrderingOps(java.lang.Object);
  Signature: (Ljava/lang/Object;)Lscala/math/Ordering$Ops;
  Code:
   Stack=2, Locals=2, Args_size=2
	aload_0
	aload_1
	invokestatic	Method scala/math/Ordering$class.mkOrderingOps:(Lscala/math/Ordering;Ljava/lang/Object;)Lscala/math/Ordering$Ops;
	areturn
  Labels:
  LocalVariableTable: 
   Start  Length  Slot  Name   Signature
   0      6      0    this       Lscala/math/Numeric$DoubleAsIfIntegral$;
   0      6      1    lhs       Ljava/lang/Object;

  Signature: length = 0x2
   00 FFFFFF99 

public scala.math.PartialOrdering reverse();
  Signature: ()Lscala/math/PartialOrdering;
  Code:
   Stack=1, Locals=1, Args_size=1
	aload_0
	invokeinterface	InterfaceMethod scala/math/Ordering.reverse:()Lscala/math/Ordering;
	areturn
  Labels:

public scala.Option tryCompare(java.lang.Object, java.lang.Object);
  Signature: (Ljava/lang/Object;Ljava/lang/Object;)Lscala/Option;
  Code:
   Stack=3, Locals=3, Args_size=3
	aload_0
	aload_1
	aload_2
	invokeinterface	InterfaceMethod scala/math/Ordering.tryCompare:(Ljava/lang/Object;Ljava/lang/Object;)Lscala/Some;
	areturn
  Labels:
  LocalVariableTable: 
   Start  Length  Slot  Name   Signature
   0      9      0    this       Lscala/math/Numeric$DoubleAsIfIntegral$;
   0      9      1    x       Ljava/lang/Object;
   0      9      2    y       Ljava/lang/Object;


public double toDouble(java.lang.Object);
  Signature: (Ljava/lang/Object;)D
  Code:
   Stack=3, Locals=2, Args_size=2
	aload_0
	aload_1
	invokestatic	Method scala/runtime/BoxesRunTime.unboxToDouble:(Ljava/lang/Object;)D
	invokeinterface	InterfaceMethod scala/math/Numeric$DoubleIsConflicted.toDouble:(D)D
	dreturn
  Labels:
  LocalVariableTable: 
   Start  Length  Slot  Name   Signature
   0      11      0    this       Lscala/math/Numeric$DoubleAsIfIntegral$;
   0      11      1    x       Ljava/lang/Object;


public float toFloat(java.lang.Object);
  Signature: (Ljava/lang/Object;)F
  Code:
   Stack=3, Locals=2, Args_size=2
	aload_0
	aload_1
	invokestatic	Method scala/runtime/BoxesRunTime.unboxToDouble:(Ljava/lang/Object;)D
	invokeinterface	InterfaceMethod scala/math/Numeric$DoubleIsConflicted.toFloat:(D)F
	freturn
  Labels:
  LocalVariableTable: 
   Start  Length  Slot  Name   Signature
   0      11      0    this       Lscala/math/Numeric$DoubleAsIfIntegral$;
   0      11      1    x       Ljava/lang/Object;


public long toLong(java.lang.Object);
  Signature: (Ljava/lang/Object;)J
  Code:
   Stack=3, Locals=2, Args_size=2
	aload_0
	aload_1
	invokestatic	Method scala/runtime/BoxesRunTime.unboxToDouble:(Ljava/lang/Object;)D
	invokeinterface	InterfaceMethod scala/math/Numeric$DoubleIsConflicted.toLong:(D)J
	lreturn
  Labels:
  LocalVariableTable: 
   Start  Length  Slot  Name   Signature
   0      11      0    this       Lscala/math/Numeric$DoubleAsIfIntegral$;
   0      11      1    x       Ljava/lang/Object;


public int toInt(java.lang.Object);
  Signature: (Ljava/lang/Object;)I
  Code:
   Stack=3, Locals=2, Args_size=2
	aload_0
	aload_1
	invokestatic	Method scala/runtime/BoxesRunTime.unboxToDouble:(Ljava/lang/Object;)D
	invokeinterface	InterfaceMethod scala/math/Numeric$DoubleIsConflicted.toInt:(D)I
	ireturn
  Labels:
  LocalVariableTable: 
   Start  Length  Slot  Name   Signature
   0      11      0    this       Lscala/math/Numeric$DoubleAsIfIntegral$;
   0      11      1    x       Ljava/lang/Object;


public java.lang.Object fromInt(int);
  Signature: (I)Ljava/lang/Object;
  Code:
   Stack=2, Locals=2, Args_size=2
	aload_0
	iload_1
	invokeinterface	InterfaceMethod scala/math/Numeric$DoubleIsConflicted.fromInt:(I)D
	invokestatic	Method scala/runtime/BoxesRunTime.boxToDouble:(D)Ljava/lang/Double;
	areturn
  Labels:
  LocalVariableTable: 
   Start  Length  Slot  Name   Signature
   0      11      0    this       Lscala/math/Numeric$DoubleAsIfIntegral$;
   0      11      1    x       I


public java.lang.Object negate(java.lang.Object);
  Signature: (Ljava/lang/Object;)Ljava/lang/Object;
  Code:
   Stack=3, Locals=2, Args_size=2
	aload_0
	aload_1
	invokestatic	Method scala/runtime/BoxesRunTime.unboxToDouble:(Ljava/lang/Object;)D
	invokeinterface	InterfaceMethod scala/math/Numeric$DoubleIsConflicted.negate:(D)D
	invokestatic	Method scala/runtime/BoxesRunTime.boxToDouble:(D)Ljava/lang/Double;
	areturn
  Labels:
  LocalVariableTable: 
   Start  Length  Slot  Name   Signature
   0      14      0    this       Lscala/math/Numeric$DoubleAsIfIntegral$;
   0      14      1    x       Ljava/lang/Object;


public java.lang.Object times(java.lang.Object, java.lang.Object);
  Signature: (Ljava/lang/Object;Ljava/lang/Object;)Ljava/lang/Object;
  Code:
   Stack=5, Locals=3, Args_size=3
	aload_0
	aload_1
	invokestatic	Method scala/runtime/BoxesRunTime.unboxToDouble:(Ljava/lang/Object;)D
	aload_2
	invokestatic	Method scala/runtime/BoxesRunTime.unboxToDouble:(Ljava/lang/Object;)D
	invokeinterface	InterfaceMethod scala/math/Numeric$DoubleIsConflicted.times:(DD)D
	invokestatic	Method scala/runtime/BoxesRunTime.boxToDouble:(D)Ljava/lang/Double;
	areturn
  Labels:
  LocalVariableTable: 
   Start  Length  Slot  Name   Signature
   0      18      0    this       Lscala/math/Numeric$DoubleAsIfIntegral$;
   0      18      1    x       Ljava/lang/Object;
   0      18      2    y       Ljava/lang/Object;


public java.lang.Object minus(java.lang.Object, java.lang.Object);
  Signature: (Ljava/lang/Object;Ljava/lang/Object;)Ljava/lang/Object;
  Code:
   Stack=5, Locals=3, Args_size=3
	aload_0
	aload_1
	invokestatic	Method scala/runtime/BoxesRunTime.unboxToDouble:(Ljava/lang/Object;)D
	aload_2
	invokestatic	Method scala/runtime/BoxesRunTime.unboxToDouble:(Ljava/lang/Object;)D
	invokeinterface	InterfaceMethod scala/math/Numeric$DoubleIsConflicted.minus:(DD)D
	invokestatic	Method scala/runtime/BoxesRunTime.boxToDouble:(D)Ljava/lang/Double;
	areturn
  Labels:
  LocalVariableTable: 
   Start  Length  Slot  Name   Signature
   0      18      0    this       Lscala/math/Numeric$DoubleAsIfIntegral$;
   0      18      1    x       Ljava/lang/Object;
   0      18      2    y       Ljava/lang/Object;


public java.lang.Object plus(java.lang.Object, java.lang.Object);
  Signature: (Ljava/lang/Object;Ljava/lang/Object;)Ljava/lang/Object;
  Code:
   Stack=5, Locals=3, Args_size=3
	aload_0
	aload_1
	invokestatic	Method scala/runtime/BoxesRunTime.unboxToDouble:(Ljava/lang/Object;)D
	aload_2
	invokestatic	Method scala/runtime/BoxesRunTime.unboxToDouble:(Ljava/lang/Object;)D
	invokeinterface	InterfaceMethod scala/math/Numeric$DoubleIsConflicted.plus:(DD)D
	invokestatic	Method scala/runtime/BoxesRunTime.boxToDouble:(D)Ljava/lang/Double;
	areturn
  Labels:
  LocalVariableTable: 
   Start  Length  Slot  Name   Signature
   0      18      0    this       Lscala/math/Numeric$DoubleAsIfIntegral$;
   0      18      1    x       Ljava/lang/Object;
   0      18      2    y       Ljava/lang/Object;


public scala.math.Numeric$Ops mkNumericOps(java.lang.Object);
  Signature: (Ljava/lang/Object;)Lscala/math/Numeric$Ops;
  Code:
   Stack=2, Locals=2, Args_size=2
	aload_0
	aload_1
	invokeinterface	InterfaceMethod scala/math/Integral.mkNumericOps:(Ljava/lang/Object;)Lscala/math/Integral$IntegralOps;
	areturn
  Labels:
  LocalVariableTable: 
   Start  Length  Slot  Name   Signature
   0      8      0    this       Lscala/math/Numeric$DoubleAsIfIntegral$;
   0      8      1    lhs       Ljava/lang/Object;

  Signature: length = 0x2
   00 FFFFFFC6 

public java.lang.Object rem(java.lang.Object, java.lang.Object);
  Signature: (Ljava/lang/Object;Ljava/lang/Object;)Ljava/lang/Object;
  Code:
   Stack=5, Locals=3, Args_size=3
	aload_0
	aload_1
	invokestatic	Method scala/runtime/BoxesRunTime.unboxToDouble:(Ljava/lang/Object;)D
	aload_2
	invokestatic	Method scala/runtime/BoxesRunTime.unboxToDouble:(Ljava/lang/Object;)D
	invokeinterface	InterfaceMethod scala/math/Numeric$DoubleAsIfIntegral.rem:(DD)D
	invokestatic	Method scala/runtime/BoxesRunTime.boxToDouble:(D)Ljava/lang/Double;
	areturn
  Labels:
  LocalVariableTable: 
   Start  Length  Slot  Name   Signature
   0      18      0    this       Lscala/math/Numeric$DoubleAsIfIntegral$;
   0      18      1    x       Ljava/lang/Object;
   0      18      2    y       Ljava/lang/Object;


public java.lang.Object quot(java.lang.Object, java.lang.Object);
  Signature: (Ljava/lang/Object;Ljava/lang/Object;)Ljava/lang/Object;
  Code:
   Stack=5, Locals=3, Args_size=3
	aload_0
	aload_1
	invokestatic	Method scala/runtime/BoxesRunTime.unboxToDouble:(Ljava/lang/Object;)D
	aload_2
	invokestatic	Method scala/runtime/BoxesRunTime.unboxToDouble:(Ljava/lang/Object;)D
	invokeinterface	InterfaceMethod scala/math/Numeric$DoubleAsIfIntegral.quot:(DD)D
	invokestatic	Method scala/runtime/BoxesRunTime.boxToDouble:(D)Ljava/lang/Double;
	areturn
  Labels:
  LocalVariableTable: 
   Start  Length  Slot  Name   Signature
   0      18      0    this       Lscala/math/Numeric$DoubleAsIfIntegral$;
   0      18      1    x       Ljava/lang/Object;
   0      18      2    y       Ljava/lang/Object;


public int compare(java.lang.Object, java.lang.Object);
  Signature: (Ljava/lang/Object;Ljava/lang/Object;)I
  Code:
   Stack=5, Locals=3, Args_size=3
	aload_0
	aload_1
	invokestatic	Method scala/runtime/BoxesRunTime.unboxToDouble:(Ljava/lang/Object;)D
	aload_2
	invokestatic	Method scala/runtime/BoxesRunTime.unboxToDouble:(Ljava/lang/Object;)D
	invokeinterface	InterfaceMethod scala/math/Ordering$DoubleOrdering.compare:(DD)I
	ireturn
  Labels:
  LocalVariableTable: 
   Start  Length  Slot  Name   Signature
   0      15      0    this       Lscala/math/Numeric$DoubleAsIfIntegral$;
   0      15      1    x       Ljava/lang/Object;
   0      15      2    y       Ljava/lang/Object;


public scala.math.Numeric$DoubleAsIfIntegral$();
  Signature: ()V
  Code:
   Stack=1, Locals=1, Args_size=1
	aload_0
	invokespecial	Method java/lang/Object."<init>":()V
	aload_0
	putstatic	Field MODULE$:Lscala/math/Numeric$DoubleAsIfIntegral$;
	aload_0
	invokestatic	Method scala/math/PartialOrdering$class.$init$:(Lscala/math/PartialOrdering;)V
	aload_0
	invokestatic	Method scala/math/Ordering$class.$init$:(Lscala/math/Ordering;)V
	aload_0
	invokestatic	Method scala/math/Numeric$class.$init$:(Lscala/math/Numeric;)V
	aload_0
	invokestatic	Method scala/math/Numeric$DoubleIsConflicted$class.$init$:(Lscala/math/Numeric$DoubleIsConflicted;)V
	aload_0
	invokestatic	Method scala/math/Integral$class.$init$:(Lscala/math/Integral;)V
	aload_0
	invokestatic	Method scala/math/Numeric$DoubleAsIfIntegral$class.$init$:(Lscala/math/Numeric$DoubleAsIfIntegral;)V
	aload_0
	invokestatic	Method scala/math/Ordering$DoubleOrdering$class.$init$:(Lscala/math/Ordering$DoubleOrdering;)V
	return
  Labels:

}

