Compiled from "Numeric.scala"
public abstract class scala.math.Numeric$DoubleAsIfIntegral$class extends java.lang.Object
  SourceFile: "Numeric.scala"
  Scala: length = 0x
   
  InnerClass: 
   public abstract #45= #42 of #44; //DoubleAsIfIntegral=class scala/math/Numeric$DoubleAsIfIntegral of class scala/math/Numeric
  minor version: 0
  major version: 49
  Constant pool:
const #1 = Asciz	SourceFile;
const #2 = Asciz	Numeric.scala;
const #3 = Asciz	$init$;
const #4 = Asciz	(Lscala/math/Numeric$DoubleAsIfIntegral;)V;
const #5 = Asciz	Code;
const #6 = Asciz	LineNumberTable;
const #7 = Asciz	$this;
const #8 = Asciz	Lscala/math/Numeric$DoubleAsIfIntegral;;
const #9 = Asciz	LocalVariableTable;
const #10 = Asciz	rem;
const #11 = Asciz	(Lscala/math/Numeric$DoubleAsIfIntegral;DD)D;
const #12 = Asciz	scala/math/BigDecimal$;
const #13 = class	#12;	//  scala/math/BigDecimal$
const #14 = Asciz	MODULE$;
const #15 = Asciz	Lscala/math/BigDecimal$;;
const #16 = NameAndType	#14:#15;//  MODULE$:Lscala/math/BigDecimal$;
const #17 = Field	#13.#16;	//  scala/math/BigDecimal$.MODULE$:Lscala/math/BigDecimal$;
const #18 = Asciz	apply;
const #19 = Asciz	(D)Lscala/math/BigDecimal;;
const #20 = NameAndType	#18:#19;//  apply:(D)Lscala/math/BigDecimal;
const #21 = Method	#13.#20;	//  scala/math/BigDecimal$.apply:(D)Lscala/math/BigDecimal;
const #22 = Asciz	scala/math/BigDecimal;
const #23 = class	#22;	//  scala/math/BigDecimal
const #24 = Asciz	remainder;
const #25 = Asciz	(Lscala/math/BigDecimal;)Lscala/math/BigDecimal;;
const #26 = NameAndType	#24:#25;//  remainder:(Lscala/math/BigDecimal;)Lscala/math/BigDecimal;
const #27 = Method	#23.#26;	//  scala/math/BigDecimal.remainder:(Lscala/math/BigDecimal;)Lscala/math/BigDecimal;
const #28 = Asciz	doubleValue;
const #29 = Asciz	()D;
const #30 = NameAndType	#28:#29;//  doubleValue:()D
const #31 = Method	#23.#30;	//  scala/math/BigDecimal.doubleValue:()D
const #32 = Asciz	x;
const #33 = Asciz	D;
const #34 = Asciz	y;
const #35 = Asciz	quot;
const #36 = Asciz	$div;
const #37 = NameAndType	#36:#25;//  $div:(Lscala/math/BigDecimal;)Lscala/math/BigDecimal;
const #38 = Method	#23.#37;	//  scala/math/BigDecimal.$div:(Lscala/math/BigDecimal;)Lscala/math/BigDecimal;
const #39 = Asciz	Scala;
const #40 = Asciz	InnerClasses;
const #41 = Asciz	scala/math/Numeric$DoubleAsIfIntegral;
const #42 = class	#41;	//  scala/math/Numeric$DoubleAsIfIntegral
const #43 = Asciz	scala/math/Numeric;
const #44 = class	#43;	//  scala/math/Numeric
const #45 = Asciz	DoubleAsIfIntegral;
const #46 = Asciz	scala/math/Numeric$DoubleAsIfIntegral$class;
const #47 = class	#46;	//  scala/math/Numeric$DoubleAsIfIntegral$class
const #48 = Asciz	java/lang/Object;
const #49 = class	#48;	//  java/lang/Object

{
public static void $init$(scala.math.Numeric$DoubleAsIfIntegral);
  Code:
   Stack=0, Locals=1, Args_size=1
   0:	return
  LineNumberTable: 
   line 121: 0

  LocalVariableTable: 
   Start  Length  Slot  Name   Signature
   0      1      0    $this       Lscala/math/Numeric$DoubleAsIfIntegral;


public static double rem(scala.math.Numeric$DoubleAsIfIntegral, double, double);
  Code:
   Stack=4, Locals=5, Args_size=3
   0:	getstatic	#17; //Field scala/math/BigDecimal$.MODULE$:Lscala/math/BigDecimal$;
   3:	dload_1
   4:	invokevirtual	#21; //Method scala/math/BigDecimal$.apply:(D)Lscala/math/BigDecimal;
   7:	getstatic	#17; //Field scala/math/BigDecimal$.MODULE$:Lscala/math/BigDecimal$;
   10:	dload_3
   11:	invokevirtual	#21; //Method scala/math/BigDecimal$.apply:(D)Lscala/math/BigDecimal;
   14:	invokevirtual	#27; //Method scala/math/BigDecimal.remainder:(Lscala/math/BigDecimal;)Lscala/math/BigDecimal;
   17:	invokevirtual	#31; //Method scala/math/BigDecimal.doubleValue:()D
   20:	dreturn
  LineNumberTable: 
   line 123: 0

  LocalVariableTable: 
   Start  Length  Slot  Name   Signature
   0      21      0    $this       Lscala/math/Numeric$DoubleAsIfIntegral;
   0      21      1    x       D
   0      21      3    y       D


public static double quot(scala.math.Numeric$DoubleAsIfIntegral, double, double);
  Code:
   Stack=4, Locals=5, Args_size=3
   0:	getstatic	#17; //Field scala/math/BigDecimal$.MODULE$:Lscala/math/BigDecimal$;
   3:	dload_1
   4:	invokevirtual	#21; //Method scala/math/BigDecimal$.apply:(D)Lscala/math/BigDecimal;
   7:	getstatic	#17; //Field scala/math/BigDecimal$.MODULE$:Lscala/math/BigDecimal$;
   10:	dload_3
   11:	invokevirtual	#21; //Method scala/math/BigDecimal$.apply:(D)Lscala/math/BigDecimal;
   14:	invokevirtual	#38; //Method scala/math/BigDecimal.$div:(Lscala/math/BigDecimal;)Lscala/math/BigDecimal;
   17:	invokevirtual	#31; //Method scala/math/BigDecimal.doubleValue:()D
   20:	dreturn
  LineNumberTable: 
   line 122: 0

  LocalVariableTable: 
   Start  Length  Slot  Name   Signature
   0      21      0    $this       Lscala/math/Numeric$DoubleAsIfIntegral;
   0      21      1    x       D
   0      21      3    y       D


}

