Compiled from "Numeric.scala"
public final class scala.math.Numeric$IntIsIntegral$ extends java.lang.Object implements scala.math.Numeric$IntIsIntegral,scala.math.Ordering$IntOrdering,scala.ScalaObject
  SourceFile: "Numeric.scala"
  Scala: length = 0x
   
  InnerClass: 
   public Ops=class scala/math/Numeric$Ops of class scala/math/Numeric
   public Ops=class scala/math/Ordering$Ops of class scala/math/Ordering
   public IntegralOps=class scala/math/Integral$IntegralOps of class scala/math/Integral
   public abstract IntOrdering=class scala/math/Ordering$IntOrdering of class scala/math/Ordering
   public abstract IntIsIntegral=class scala/math/Numeric$IntIsIntegral of class scala/math/Numeric
  minor version: 0
  major version: 49
  Constant pool:
Asciz	SourceFile;
Asciz	Numeric.scala;
Asciz	Scala;
Asciz	MODULE$;
Asciz	Lscala/math/Numeric$IntIsIntegral$;;
Asciz	<clinit>;
Asciz	()V;
Asciz	Code;
Asciz	scala/math/Numeric$IntIsIntegral$;
class	scala/math/Numeric$IntIsIntegral$
Asciz	<init>;
NameAndType	"<init>":()V
Method	scala/math/Numeric$IntIsIntegral$."<init>":()V
Asciz	compare;
Asciz	(II)I;
Asciz	LineNumberTable;
Asciz	scala/math/Ordering$IntOrdering$class;
class	scala/math/Ordering$IntOrdering$class
Asciz	(Lscala/math/Ordering$IntOrdering;II)I;
NameAndType	compare:(Lscala/math/Ordering$IntOrdering;II)I
Method	scala/math/Ordering$IntOrdering$class.compare:(Lscala/math/Ordering$IntOrdering;II)I
Asciz	this;
Asciz	x;
Asciz	I;
Asciz	y;
Asciz	LocalVariableTable;
Asciz	plus;
Asciz	scala/math/Numeric$IntIsIntegral$class;
class	scala/math/Numeric$IntIsIntegral$class
Asciz	(Lscala/math/Numeric$IntIsIntegral;II)I;
NameAndType	plus:(Lscala/math/Numeric$IntIsIntegral;II)I
Method	scala/math/Numeric$IntIsIntegral$class.plus:(Lscala/math/Numeric$IntIsIntegral;II)I
Asciz	minus;
NameAndType	minus:(Lscala/math/Numeric$IntIsIntegral;II)I
Method	scala/math/Numeric$IntIsIntegral$class.minus:(Lscala/math/Numeric$IntIsIntegral;II)I
Asciz	times;
NameAndType	times:(Lscala/math/Numeric$IntIsIntegral;II)I
Method	scala/math/Numeric$IntIsIntegral$class.times:(Lscala/math/Numeric$IntIsIntegral;II)I
Asciz	quot;
NameAndType	quot:(Lscala/math/Numeric$IntIsIntegral;II)I
Method	scala/math/Numeric$IntIsIntegral$class.quot:(Lscala/math/Numeric$IntIsIntegral;II)I
Asciz	rem;
NameAndType	rem:(Lscala/math/Numeric$IntIsIntegral;II)I
Method	scala/math/Numeric$IntIsIntegral$class.rem:(Lscala/math/Numeric$IntIsIntegral;II)I
Asciz	negate;
Asciz	(I)I;
Asciz	(Lscala/math/Numeric$IntIsIntegral;I)I;
NameAndType	negate:(Lscala/math/Numeric$IntIsIntegral;I)I
Method	scala/math/Numeric$IntIsIntegral$class.negate:(Lscala/math/Numeric$IntIsIntegral;I)I
Asciz	fromInt;
NameAndType	fromInt:(Lscala/math/Numeric$IntIsIntegral;I)I
Method	scala/math/Numeric$IntIsIntegral$class.fromInt:(Lscala/math/Numeric$IntIsIntegral;I)I
Asciz	toInt;
NameAndType	toInt:(Lscala/math/Numeric$IntIsIntegral;I)I
Method	scala/math/Numeric$IntIsIntegral$class.toInt:(Lscala/math/Numeric$IntIsIntegral;I)I
Asciz	toLong;
Asciz	(I)J;
Asciz	(Lscala/math/Numeric$IntIsIntegral;I)J;
NameAndType	toLong:(Lscala/math/Numeric$IntIsIntegral;I)J
Method	scala/math/Numeric$IntIsIntegral$class.toLong:(Lscala/math/Numeric$IntIsIntegral;I)J
Asciz	toFloat;
Asciz	(I)F;
Asciz	(Lscala/math/Numeric$IntIsIntegral;I)F;
NameAndType	toFloat:(Lscala/math/Numeric$IntIsIntegral;I)F
Method	scala/math/Numeric$IntIsIntegral$class.toFloat:(Lscala/math/Numeric$IntIsIntegral;I)F
Asciz	toDouble;
Asciz	(I)D;
Asciz	(Lscala/math/Numeric$IntIsIntegral;I)D;
NameAndType	toDouble:(Lscala/math/Numeric$IntIsIntegral;I)D
Method	scala/math/Numeric$IntIsIntegral$class.toDouble:(Lscala/math/Numeric$IntIsIntegral;I)D
Asciz	mkNumericOps;
Asciz	(Ljava/lang/Object;)Lscala/math/Integral$IntegralOps;;
Asciz	scala/math/Integral$class;
class	scala/math/Integral$class
Asciz	(Lscala/math/Integral;Ljava/lang/Object;)Lscala/math/Integral$IntegralOps;;
NameAndType	mkNumericOps:(Lscala/math/Integral;Ljava/lang/Object;)Lscala/math/Integral$IntegralOps;
Method	scala/math/Integral$class.mkNumericOps:(Lscala/math/Integral;Ljava/lang/Object;)Lscala/math/Integral$IntegralOps;
Asciz	lhs;
Asciz	Ljava/lang/Object;;
Asciz	Signature;
Asciz	zero;
Asciz	()Ljava/lang/Object;;
Asciz	scala/math/Numeric$class;
class	scala/math/Numeric$class
Asciz	(Lscala/math/Numeric;)Ljava/lang/Object;;
NameAndType	zero:(Lscala/math/Numeric;)Ljava/lang/Object;
Method	scala/math/Numeric$class.zero:(Lscala/math/Numeric;)Ljava/lang/Object;
Asciz	one;
NameAndType	one:(Lscala/math/Numeric;)Ljava/lang/Object;
Method	scala/math/Numeric$class.one:(Lscala/math/Numeric;)Ljava/lang/Object;
Asciz	abs;
Asciz	(Ljava/lang/Object;)Ljava/lang/Object;;
Asciz	(Lscala/math/Numeric;Ljava/lang/Object;)Ljava/lang/Object;;
NameAndType	abs:(Lscala/math/Numeric;Ljava/lang/Object;)Ljava/lang/Object;
Method	scala/math/Numeric$class.abs:(Lscala/math/Numeric;Ljava/lang/Object;)Ljava/lang/Object;
Asciz	signum;
Asciz	(Ljava/lang/Object;)I;
Asciz	(Lscala/math/Numeric;Ljava/lang/Object;)I;
NameAndType	signum:(Lscala/math/Numeric;Ljava/lang/Object;)I
Method	scala/math/Numeric$class.signum:(Lscala/math/Numeric;Ljava/lang/Object;)I
Asciz	tryCompare;
Asciz	(Ljava/lang/Object;Ljava/lang/Object;)Lscala/Some;;
Asciz	scala/math/Ordering$class;
class	scala/math/Ordering$class
Asciz	(Lscala/math/Ordering;Ljava/lang/Object;Ljava/lang/Object;)Lscala/Some;;
NameAndType	tryCompare:(Lscala/math/Ordering;Ljava/lang/Object;Ljava/lang/Object;)Lscala/Some;
Method	scala/math/Ordering$class.tryCompare:(Lscala/math/Ordering;Ljava/lang/Object;Ljava/lang/Object;)Lscala/Some;
Asciz	lteq;
Asciz	(Ljava/lang/Object;Ljava/lang/Object;)Z;
Asciz	(Lscala/math/Ordering;Ljava/lang/Object;Ljava/lang/Object;)Z;
NameAndType	lteq:(Lscala/math/Ordering;Ljava/lang/Object;Ljava/lang/Object;)Z
Method	scala/math/Ordering$class.lteq:(Lscala/math/Ordering;Ljava/lang/Object;Ljava/lang/Object;)Z
Asciz	gteq;
NameAndType	gteq:(Lscala/math/Ordering;Ljava/lang/Object;Ljava/lang/Object;)Z
Method	scala/math/Ordering$class.gteq:(Lscala/math/Ordering;Ljava/lang/Object;Ljava/lang/Object;)Z
Asciz	lt;
NameAndType	lt:(Lscala/math/Ordering;Ljava/lang/Object;Ljava/lang/Object;)Z
Method	scala/math/Ordering$class.lt:(Lscala/math/Ordering;Ljava/lang/Object;Ljava/lang/Object;)Z
Asciz	gt;
NameAndType	gt:(Lscala/math/Ordering;Ljava/lang/Object;Ljava/lang/Object;)Z
Method	scala/math/Ordering$class.gt:(Lscala/math/Ordering;Ljava/lang/Object;Ljava/lang/Object;)Z
Asciz	equiv;
NameAndType	equiv:(Lscala/math/Ordering;Ljava/lang/Object;Ljava/lang/Object;)Z
Method	scala/math/Ordering$class.equiv:(Lscala/math/Ordering;Ljava/lang/Object;Ljava/lang/Object;)Z
Asciz	max;
Asciz	(Ljava/lang/Object;Ljava/lang/Object;)Ljava/lang/Object;;
Asciz	(Lscala/math/Ordering;Ljava/lang/Object;Ljava/lang/Object;)Ljava/lang/Object;;
NameAndType	max:(Lscala/math/Ordering;Ljava/lang/Object;Ljava/lang/Object;)Ljava/lang/Object;
Method	scala/math/Ordering$class.max:(Lscala/math/Ordering;Ljava/lang/Object;Ljava/lang/Object;)Ljava/lang/Object;
Asciz	min;
NameAndType	min:(Lscala/math/Ordering;Ljava/lang/Object;Ljava/lang/Object;)Ljava/lang/Object;
Method	scala/math/Ordering$class.min:(Lscala/math/Ordering;Ljava/lang/Object;Ljava/lang/Object;)Ljava/lang/Object;
Asciz	reverse;
Asciz	()Lscala/math/Ordering;;
Asciz	(Lscala/math/Ordering;)Lscala/math/Ordering;;
NameAndType	reverse:(Lscala/math/Ordering;)Lscala/math/Ordering;
Method	scala/math/Ordering$class.reverse:(Lscala/math/Ordering;)Lscala/math/Ordering;
Asciz	on;
Asciz	(Lscala/Function1;)Lscala/math/Ordering;;
Asciz	(Lscala/math/Ordering;Lscala/Function1;)Lscala/math/Ordering;;
NameAndType	on:(Lscala/math/Ordering;Lscala/Function1;)Lscala/math/Ordering;
Method	scala/math/Ordering$class.on:(Lscala/math/Ordering;Lscala/Function1;)Lscala/math/Ordering;
Asciz	f;
Asciz	Lscala/Function1;;
Asciz	mkOrderingOps;
Asciz	(Ljava/lang/Object;)Lscala/math/Ordering$Ops;;
Asciz	(Lscala/math/Ordering;Ljava/lang/Object;)Lscala/math/Ordering$Ops;;
NameAndType	mkOrderingOps:(Lscala/math/Ordering;Ljava/lang/Object;)Lscala/math/Ordering$Ops;
Method	scala/math/Ordering$class.mkOrderingOps:(Lscala/math/Ordering;Ljava/lang/Object;)Lscala/math/Ordering$Ops;
Asciz	()Lscala/math/PartialOrdering;;
Asciz	scala/math/Ordering;
class	scala/math/Ordering
NameAndType	reverse:()Lscala/math/Ordering;
InterfaceMethod	scala/math/Ordering.reverse:()Lscala/math/Ordering;
Asciz	(Ljava/lang/Object;Ljava/lang/Object;)Lscala/Option;;
NameAndType	tryCompare:(Ljava/lang/Object;Ljava/lang/Object;)Lscala/Some;
InterfaceMethod	scala/math/Ordering.tryCompare:(Ljava/lang/Object;Ljava/lang/Object;)Lscala/Some;
Asciz	(Ljava/lang/Object;)Lscala/math/Numeric$Ops;;
Asciz	scala/math/Integral;
class	scala/math/Integral
NameAndType	mkNumericOps:(Ljava/lang/Object;)Lscala/math/Integral$IntegralOps;
InterfaceMethod	scala/math/Integral.mkNumericOps:(Ljava/lang/Object;)Lscala/math/Integral$IntegralOps;
Asciz	(Ljava/lang/Object;)D;
Asciz	scala/runtime/BoxesRunTime;
class	scala/runtime/BoxesRunTime
Asciz	unboxToInt;
NameAndType	unboxToInt:(Ljava/lang/Object;)I
Method	scala/runtime/BoxesRunTime.unboxToInt:(Ljava/lang/Object;)I
Asciz	scala/math/Numeric$IntIsIntegral;
class	scala/math/Numeric$IntIsIntegral
NameAndType	toDouble:(I)D
InterfaceMethod	scala/math/Numeric$IntIsIntegral.toDouble:(I)D
Asciz	(Ljava/lang/Object;)F;
NameAndType	toFloat:(I)F
InterfaceMethod	scala/math/Numeric$IntIsIntegral.toFloat:(I)F
Asciz	(Ljava/lang/Object;)J;
NameAndType	toLong:(I)J
InterfaceMethod	scala/math/Numeric$IntIsIntegral.toLong:(I)J
NameAndType	toInt:(I)I
InterfaceMethod	scala/math/Numeric$IntIsIntegral.toInt:(I)I
Asciz	(I)Ljava/lang/Object;;
NameAndType	fromInt:(I)I
InterfaceMethod	scala/math/Numeric$IntIsIntegral.fromInt:(I)I
Asciz	boxToInteger;
Asciz	(I)Ljava/lang/Integer;;
NameAndType	boxToInteger:(I)Ljava/lang/Integer;
Method	scala/runtime/BoxesRunTime.boxToInteger:(I)Ljava/lang/Integer;
NameAndType	negate:(I)I
InterfaceMethod	scala/math/Numeric$IntIsIntegral.negate:(I)I
NameAndType	rem:(II)I
InterfaceMethod	scala/math/Numeric$IntIsIntegral.rem:(II)I
NameAndType	quot:(II)I
InterfaceMethod	scala/math/Numeric$IntIsIntegral.quot:(II)I
NameAndType	times:(II)I
InterfaceMethod	scala/math/Numeric$IntIsIntegral.times:(II)I
NameAndType	minus:(II)I
InterfaceMethod	scala/math/Numeric$IntIsIntegral.minus:(II)I
NameAndType	plus:(II)I
InterfaceMethod	scala/math/Numeric$IntIsIntegral.plus:(II)I
Asciz	(Ljava/lang/Object;Ljava/lang/Object;)I;
Asciz	scala/math/Ordering$IntOrdering;
class	scala/math/Ordering$IntOrdering
NameAndType	compare:(II)I
InterfaceMethod	scala/math/Ordering$IntOrdering.compare:(II)I
Asciz	java/lang/Object;
class	java/lang/Object
Method	java/lang/Object."<init>":()V
NameAndType	MODULE$:Lscala/math/Numeric$IntIsIntegral$;
Field	scala/math/Numeric$IntIsIntegral$.MODULE$:Lscala/math/Numeric$IntIsIntegral$;
Asciz	scala/math/PartialOrdering$class;
class	scala/math/PartialOrdering$class
Asciz	$init$;
Asciz	(Lscala/math/PartialOrdering;)V;
NameAndType	$init$:(Lscala/math/PartialOrdering;)V
Method	scala/math/PartialOrdering$class.$init$:(Lscala/math/PartialOrdering;)V
Asciz	(Lscala/math/Ordering;)V;
NameAndType	$init$:(Lscala/math/Ordering;)V
Method	scala/math/Ordering$class.$init$:(Lscala/math/Ordering;)V
Asciz	(Lscala/math/Numeric;)V;
NameAndType	$init$:(Lscala/math/Numeric;)V
Method	scala/math/Numeric$class.$init$:(Lscala/math/Numeric;)V
Asciz	(Lscala/math/Integral;)V;
NameAndType	$init$:(Lscala/math/Integral;)V
Method	scala/math/Integral$class.$init$:(Lscala/math/Integral;)V
Asciz	(Lscala/math/Numeric$IntIsIntegral;)V;
NameAndType	$init$:(Lscala/math/Numeric$IntIsIntegral;)V
Method	scala/math/Numeric$IntIsIntegral$class.$init$:(Lscala/math/Numeric$IntIsIntegral;)V
Asciz	(Lscala/math/Ordering$IntOrdering;)V;
NameAndType	$init$:(Lscala/math/Ordering$IntOrdering;)V
Method	scala/math/Ordering$IntOrdering$class.$init$:(Lscala/math/Ordering$IntOrdering;)V
Asciz	InnerClasses;
Asciz	scala/math/Numeric$Ops;
class	scala/math/Numeric$Ops
Asciz	scala/math/Numeric;
class	scala/math/Numeric
Asciz	Ops;
Asciz	scala/math/Ordering$Ops;
class	scala/math/Ordering$Ops
Asciz	scala/math/Integral$IntegralOps;
class	scala/math/Integral$IntegralOps
Asciz	IntegralOps;
Asciz	IntOrdering;
Asciz	IntIsIntegral;
Asciz	scala/ScalaObject;
class	scala/ScalaObject

{
public static final scala.math.Numeric$IntIsIntegral$ MODULE$;
  Signature: Lscala/math/Numeric$IntIsIntegral$;

public static {};
  Signature: ()V
  Code:
   Stack=1, Locals=0, Args_size=0
	new	class scala/math/Numeric$IntIsIntegral$
	invokespecial	Method "<init>":()V
	return
  Labels:

public int compare(int, int);
  Signature: (II)I
  Code:
   Stack=3, Locals=3, Args_size=3
	aload_0
	iload_1
	iload_2
	invokestatic	Method scala/math/Ordering$IntOrdering$class.compare:(Lscala/math/Ordering$IntOrdering;II)I
	ireturn
  Labels:
  LocalVariableTable: 
   Start  Length  Slot  Name   Signature
   0      7      0    this       Lscala/math/Numeric$IntIsIntegral$;
   0      7      1    x       I
   0      7      2    y       I


public int plus(int, int);
  Signature: (II)I
  Code:
   Stack=3, Locals=3, Args_size=3
	aload_0
	iload_1
	iload_2
	invokestatic	Method scala/math/Numeric$IntIsIntegral$class.plus:(Lscala/math/Numeric$IntIsIntegral;II)I
	ireturn
  Labels:
  LocalVariableTable: 
   Start  Length  Slot  Name   Signature
   0      7      0    this       Lscala/math/Numeric$IntIsIntegral$;
   0      7      1    x       I
   0      7      2    y       I


public int minus(int, int);
  Signature: (II)I
  Code:
   Stack=3, Locals=3, Args_size=3
	aload_0
	iload_1
	iload_2
	invokestatic	Method scala/math/Numeric$IntIsIntegral$class.minus:(Lscala/math/Numeric$IntIsIntegral;II)I
	ireturn
  Labels:
  LocalVariableTable: 
   Start  Length  Slot  Name   Signature
   0      7      0    this       Lscala/math/Numeric$IntIsIntegral$;
   0      7      1    x       I
   0      7      2    y       I


public int times(int, int);
  Signature: (II)I
  Code:
   Stack=3, Locals=3, Args_size=3
	aload_0
	iload_1
	iload_2
	invokestatic	Method scala/math/Numeric$IntIsIntegral$class.times:(Lscala/math/Numeric$IntIsIntegral;II)I
	ireturn
  Labels:
  LocalVariableTable: 
   Start  Length  Slot  Name   Signature
   0      7      0    this       Lscala/math/Numeric$IntIsIntegral$;
   0      7      1    x       I
   0      7      2    y       I


public int quot(int, int);
  Signature: (II)I
  Code:
   Stack=3, Locals=3, Args_size=3
	aload_0
	iload_1
	iload_2
	invokestatic	Method scala/math/Numeric$IntIsIntegral$class.quot:(Lscala/math/Numeric$IntIsIntegral;II)I
	ireturn
  Labels:
  LocalVariableTable: 
   Start  Length  Slot  Name   Signature
   0      7      0    this       Lscala/math/Numeric$IntIsIntegral$;
   0      7      1    x       I
   0      7      2    y       I


public int rem(int, int);
  Signature: (II)I
  Code:
   Stack=3, Locals=3, Args_size=3
	aload_0
	iload_1
	iload_2
	invokestatic	Method scala/math/Numeric$IntIsIntegral$class.rem:(Lscala/math/Numeric$IntIsIntegral;II)I
	ireturn
  Labels:
  LocalVariableTable: 
   Start  Length  Slot  Name   Signature
   0      7      0    this       Lscala/math/Numeric$IntIsIntegral$;
   0      7      1    x       I
   0      7      2    y       I


public int negate(int);
  Signature: (I)I
  Code:
   Stack=2, Locals=2, Args_size=2
	aload_0
	iload_1
	invokestatic	Method scala/math/Numeric$IntIsIntegral$class.negate:(Lscala/math/Numeric$IntIsIntegral;I)I
	ireturn
  Labels:
  LocalVariableTable: 
   Start  Length  Slot  Name   Signature
   0      6      0    this       Lscala/math/Numeric$IntIsIntegral$;
   0      6      1    x       I


public int fromInt(int);
  Signature: (I)I
  Code:
   Stack=2, Locals=2, Args_size=2
	aload_0
	iload_1
	invokestatic	Method scala/math/Numeric$IntIsIntegral$class.fromInt:(Lscala/math/Numeric$IntIsIntegral;I)I
	ireturn
  Labels:
  LocalVariableTable: 
   Start  Length  Slot  Name   Signature
   0      6      0    this       Lscala/math/Numeric$IntIsIntegral$;
   0      6      1    x       I


public int toInt(int);
  Signature: (I)I
  Code:
   Stack=2, Locals=2, Args_size=2
	aload_0
	iload_1
	invokestatic	Method scala/math/Numeric$IntIsIntegral$class.toInt:(Lscala/math/Numeric$IntIsIntegral;I)I
	ireturn
  Labels:
  LocalVariableTable: 
   Start  Length  Slot  Name   Signature
   0      6      0    this       Lscala/math/Numeric$IntIsIntegral$;
   0      6      1    x       I


public long toLong(int);
  Signature: (I)J
  Code:
   Stack=2, Locals=2, Args_size=2
	aload_0
	iload_1
	invokestatic	Method scala/math/Numeric$IntIsIntegral$class.toLong:(Lscala/math/Numeric$IntIsIntegral;I)J
	lreturn
  Labels:
  LocalVariableTable: 
   Start  Length  Slot  Name   Signature
   0      6      0    this       Lscala/math/Numeric$IntIsIntegral$;
   0      6      1    x       I


public float toFloat(int);
  Signature: (I)F
  Code:
   Stack=2, Locals=2, Args_size=2
	aload_0
	iload_1
	invokestatic	Method scala/math/Numeric$IntIsIntegral$class.toFloat:(Lscala/math/Numeric$IntIsIntegral;I)F
	freturn
  Labels:
  LocalVariableTable: 
   Start  Length  Slot  Name   Signature
   0      6      0    this       Lscala/math/Numeric$IntIsIntegral$;
   0      6      1    x       I


public double toDouble(int);
  Signature: (I)D
  Code:
   Stack=2, Locals=2, Args_size=2
	aload_0
	iload_1
	invokestatic	Method scala/math/Numeric$IntIsIntegral$class.toDouble:(Lscala/math/Numeric$IntIsIntegral;I)D
	dreturn
  Labels:
  LocalVariableTable: 
   Start  Length  Slot  Name   Signature
   0      6      0    this       Lscala/math/Numeric$IntIsIntegral$;
   0      6      1    x       I


public scala.math.Integral$IntegralOps mkNumericOps(java.lang.Object);
  Signature: (Ljava/lang/Object;)Lscala/math/Integral$IntegralOps;
  Code:
   Stack=2, Locals=2, Args_size=2
	aload_0
	aload_1
	invokestatic	Method scala/math/Integral$class.mkNumericOps:(Lscala/math/Integral;Ljava/lang/Object;)Lscala/math/Integral$IntegralOps;
	areturn
  Labels:
  LocalVariableTable: 
   Start  Length  Slot  Name   Signature
   0      6      0    this       Lscala/math/Numeric$IntIsIntegral$;
   0      6      1    lhs       Ljava/lang/Object;

  Signature: length = 0x2
   00 48 

public java.lang.Object zero();
  Signature: ()Ljava/lang/Object;
  Code:
   Stack=1, Locals=1, Args_size=1
	aload_0
	invokestatic	Method scala/math/Numeric$class.zero:(Lscala/math/Numeric;)Ljava/lang/Object;
	areturn
  Labels:

public java.lang.Object one();
  Signature: ()Ljava/lang/Object;
  Code:
   Stack=1, Locals=1, Args_size=1
	aload_0
	invokestatic	Method scala/math/Numeric$class.one:(Lscala/math/Numeric;)Ljava/lang/Object;
	areturn
  Labels:

public java.lang.Object abs(java.lang.Object);
  Signature: (Ljava/lang/Object;)Ljava/lang/Object;
  Code:
   Stack=2, Locals=2, Args_size=2
	aload_0
	aload_1
	invokestatic	Method scala/math/Numeric$class.abs:(Lscala/math/Numeric;Ljava/lang/Object;)Ljava/lang/Object;
	areturn
  Labels:
  LocalVariableTable: 
   Start  Length  Slot  Name   Signature
   0      6      0    this       Lscala/math/Numeric$IntIsIntegral$;
   0      6      1    x       Ljava/lang/Object;


public int signum(java.lang.Object);
  Signature: (Ljava/lang/Object;)I
  Code:
   Stack=2, Locals=2, Args_size=2
	aload_0
	aload_1
	invokestatic	Method scala/math/Numeric$class.signum:(Lscala/math/Numeric;Ljava/lang/Object;)I
	ireturn
  Labels:
  LocalVariableTable: 
   Start  Length  Slot  Name   Signature
   0      6      0    this       Lscala/math/Numeric$IntIsIntegral$;
   0      6      1    x       Ljava/lang/Object;


public scala.Some tryCompare(java.lang.Object, java.lang.Object);
  Signature: (Ljava/lang/Object;Ljava/lang/Object;)Lscala/Some;
  Code:
   Stack=3, Locals=3, Args_size=3
	aload_0
	aload_1
	aload_2
	invokestatic	Method scala/math/Ordering$class.tryCompare:(Lscala/math/Ordering;Ljava/lang/Object;Ljava/lang/Object;)Lscala/Some;
	areturn
  Labels:
  LocalVariableTable: 
   Start  Length  Slot  Name   Signature
   0      7      0    this       Lscala/math/Numeric$IntIsIntegral$;
   0      7      1    x       Ljava/lang/Object;
   0      7      2    y       Ljava/lang/Object;


public boolean lteq(java.lang.Object, java.lang.Object);
  Signature: (Ljava/lang/Object;Ljava/lang/Object;)Z
  Code:
   Stack=3, Locals=3, Args_size=3
	aload_0
	aload_1
	aload_2
	invokestatic	Method scala/math/Ordering$class.lteq:(Lscala/math/Ordering;Ljava/lang/Object;Ljava/lang/Object;)Z
	ireturn
  Labels:
  LocalVariableTable: 
   Start  Length  Slot  Name   Signature
   0      7      0    this       Lscala/math/Numeric$IntIsIntegral$;
   0      7      1    x       Ljava/lang/Object;
   0      7      2    y       Ljava/lang/Object;


public boolean gteq(java.lang.Object, java.lang.Object);
  Signature: (Ljava/lang/Object;Ljava/lang/Object;)Z
  Code:
   Stack=3, Locals=3, Args_size=3
	aload_0
	aload_1
	aload_2
	invokestatic	Method scala/math/Ordering$class.gteq:(Lscala/math/Ordering;Ljava/lang/Object;Ljava/lang/Object;)Z
	ireturn
  Labels:
  LocalVariableTable: 
   Start  Length  Slot  Name   Signature
   0      7      0    this       Lscala/math/Numeric$IntIsIntegral$;
   0      7      1    x       Ljava/lang/Object;
   0      7      2    y       Ljava/lang/Object;


public boolean lt(java.lang.Object, java.lang.Object);
  Signature: (Ljava/lang/Object;Ljava/lang/Object;)Z
  Code:
   Stack=3, Locals=3, Args_size=3
	aload_0
	aload_1
	aload_2
	invokestatic	Method scala/math/Ordering$class.lt:(Lscala/math/Ordering;Ljava/lang/Object;Ljava/lang/Object;)Z
	ireturn
  Labels:
  LocalVariableTable: 
   Start  Length  Slot  Name   Signature
   0      7      0    this       Lscala/math/Numeric$IntIsIntegral$;
   0      7      1    x       Ljava/lang/Object;
   0      7      2    y       Ljava/lang/Object;


public boolean gt(java.lang.Object, java.lang.Object);
  Signature: (Ljava/lang/Object;Ljava/lang/Object;)Z
  Code:
   Stack=3, Locals=3, Args_size=3
	aload_0
	aload_1
	aload_2
	invokestatic	Method scala/math/Ordering$class.gt:(Lscala/math/Ordering;Ljava/lang/Object;Ljava/lang/Object;)Z
	ireturn
  Labels:
  LocalVariableTable: 
   Start  Length  Slot  Name   Signature
   0      7      0    this       Lscala/math/Numeric$IntIsIntegral$;
   0      7      1    x       Ljava/lang/Object;
   0      7      2    y       Ljava/lang/Object;


public boolean equiv(java.lang.Object, java.lang.Object);
  Signature: (Ljava/lang/Object;Ljava/lang/Object;)Z
  Code:
   Stack=3, Locals=3, Args_size=3
	aload_0
	aload_1
	aload_2
	invokestatic	Method scala/math/Ordering$class.equiv:(Lscala/math/Ordering;Ljava/lang/Object;Ljava/lang/Object;)Z
	ireturn
  Labels:
  LocalVariableTable: 
   Start  Length  Slot  Name   Signature
   0      7      0    this       Lscala/math/Numeric$IntIsIntegral$;
   0      7      1    x       Ljava/lang/Object;
   0      7      2    y       Ljava/lang/Object;


public java.lang.Object max(java.lang.Object, java.lang.Object);
  Signature: (Ljava/lang/Object;Ljava/lang/Object;)Ljava/lang/Object;
  Code:
   Stack=3, Locals=3, Args_size=3
	aload_0
	aload_1
	aload_2
	invokestatic	Method scala/math/Ordering$class.max:(Lscala/math/Ordering;Ljava/lang/Object;Ljava/lang/Object;)Ljava/lang/Object;
	areturn
  Labels:
  LocalVariableTable: 
   Start  Length  Slot  Name   Signature
   0      7      0    this       Lscala/math/Numeric$IntIsIntegral$;
   0      7      1    x       Ljava/lang/Object;
   0      7      2    y       Ljava/lang/Object;


public java.lang.Object min(java.lang.Object, java.lang.Object);
  Signature: (Ljava/lang/Object;Ljava/lang/Object;)Ljava/lang/Object;
  Code:
   Stack=3, Locals=3, Args_size=3
	aload_0
	aload_1
	aload_2
	invokestatic	Method scala/math/Ordering$class.min:(Lscala/math/Ordering;Ljava/lang/Object;Ljava/lang/Object;)Ljava/lang/Object;
	areturn
  Labels:
  LocalVariableTable: 
   Start  Length  Slot  Name   Signature
   0      7      0    this       Lscala/math/Numeric$IntIsIntegral$;
   0      7      1    x       Ljava/lang/Object;
   0      7      2    y       Ljava/lang/Object;


public scala.math.Ordering reverse();
  Signature: ()Lscala/math/Ordering;
  Code:
   Stack=1, Locals=1, Args_size=1
	aload_0
	invokestatic	Method scala/math/Ordering$class.reverse:(Lscala/math/Ordering;)Lscala/math/Ordering;
	areturn
  Labels:

public scala.math.Ordering on(scala.Function1);
  Signature: (Lscala/Function1;)Lscala/math/Ordering;
  Code:
   Stack=2, Locals=2, Args_size=2
	aload_0
	aload_1
	invokestatic	Method scala/math/Ordering$class.on:(Lscala/math/Ordering;Lscala/Function1;)Lscala/math/Ordering;
	areturn
  Labels:
  LocalVariableTable: 
   Start  Length  Slot  Name   Signature
   0      6      0    this       Lscala/math/Numeric$IntIsIntegral$;
   0      6      1    f       Lscala/Function1;


public scala.math.Ordering$Ops mkOrderingOps(java.lang.Object);
  Signature: (Ljava/lang/Object;)Lscala/math/Ordering$Ops;
  Code:
   Stack=2, Locals=2, Args_size=2
	aload_0
	aload_1
	invokestatic	Method scala/math/Ordering$class.mkOrderingOps:(Lscala/math/Ordering;Ljava/lang/Object;)Lscala/math/Ordering$Ops;
	areturn
  Labels:
  LocalVariableTable: 
   Start  Length  Slot  Name   Signature
   0      6      0    this       Lscala/math/Numeric$IntIsIntegral$;
   0      6      1    lhs       Ljava/lang/Object;

  Signature: length = 0x2
   00 FFFFFF92 

public scala.math.PartialOrdering reverse();
  Signature: ()Lscala/math/PartialOrdering;
  Code:
   Stack=1, Locals=1, Args_size=1
	aload_0
	invokeinterface	InterfaceMethod scala/math/Ordering.reverse:()Lscala/math/Ordering;
	areturn
  Labels:

public scala.Option tryCompare(java.lang.Object, java.lang.Object);
  Signature: (Ljava/lang/Object;Ljava/lang/Object;)Lscala/Option;
  Code:
   Stack=3, Locals=3, Args_size=3
	aload_0
	aload_1
	aload_2
	invokeinterface	InterfaceMethod scala/math/Ordering.tryCompare:(Ljava/lang/Object;Ljava/lang/Object;)Lscala/Some;
	areturn
  Labels:
  LocalVariableTable: 
   Start  Length  Slot  Name   Signature
   0      9      0    this       Lscala/math/Numeric$IntIsIntegral$;
   0      9      1    x       Ljava/lang/Object;
   0      9      2    y       Ljava/lang/Object;


public scala.math.Numeric$Ops mkNumericOps(java.lang.Object);
  Signature: (Ljava/lang/Object;)Lscala/math/Numeric$Ops;
  Code:
   Stack=2, Locals=2, Args_size=2
	aload_0
	aload_1
	invokeinterface	InterfaceMethod scala/math/Integral.mkNumericOps:(Ljava/lang/Object;)Lscala/math/Integral$IntegralOps;
	areturn
  Labels:
  LocalVariableTable: 
   Start  Length  Slot  Name   Signature
   0      8      0    this       Lscala/math/Numeric$IntIsIntegral$;
   0      8      1    lhs       Ljava/lang/Object;

  Signature: length = 0x2
   00 FFFFFF9E 

public double toDouble(java.lang.Object);
  Signature: (Ljava/lang/Object;)D
  Code:
   Stack=2, Locals=2, Args_size=2
	aload_0
	aload_1
	invokestatic	Method scala/runtime/BoxesRunTime.unboxToInt:(Ljava/lang/Object;)I
	invokeinterface	InterfaceMethod scala/math/Numeric$IntIsIntegral.toDouble:(I)D
	dreturn
  Labels:
  LocalVariableTable: 
   Start  Length  Slot  Name   Signature
   0      11      0    this       Lscala/math/Numeric$IntIsIntegral$;
   0      11      1    x       Ljava/lang/Object;


public float toFloat(java.lang.Object);
  Signature: (Ljava/lang/Object;)F
  Code:
   Stack=2, Locals=2, Args_size=2
	aload_0
	aload_1
	invokestatic	Method scala/runtime/BoxesRunTime.unboxToInt:(Ljava/lang/Object;)I
	invokeinterface	InterfaceMethod scala/math/Numeric$IntIsIntegral.toFloat:(I)F
	freturn
  Labels:
  LocalVariableTable: 
   Start  Length  Slot  Name   Signature
   0      11      0    this       Lscala/math/Numeric$IntIsIntegral$;
   0      11      1    x       Ljava/lang/Object;


public long toLong(java.lang.Object);
  Signature: (Ljava/lang/Object;)J
  Code:
   Stack=2, Locals=2, Args_size=2
	aload_0
	aload_1
	invokestatic	Method scala/runtime/BoxesRunTime.unboxToInt:(Ljava/lang/Object;)I
	invokeinterface	InterfaceMethod scala/math/Numeric$IntIsIntegral.toLong:(I)J
	lreturn
  Labels:
  LocalVariableTable: 
   Start  Length  Slot  Name   Signature
   0      11      0    this       Lscala/math/Numeric$IntIsIntegral$;
   0      11      1    x       Ljava/lang/Object;


public int toInt(java.lang.Object);
  Signature: (Ljava/lang/Object;)I
  Code:
   Stack=2, Locals=2, Args_size=2
	aload_0
	aload_1
	invokestatic	Method scala/runtime/BoxesRunTime.unboxToInt:(Ljava/lang/Object;)I
	invokeinterface	InterfaceMethod scala/math/Numeric$IntIsIntegral.toInt:(I)I
	ireturn
  Labels:
  LocalVariableTable: 
   Start  Length  Slot  Name   Signature
   0      11      0    this       Lscala/math/Numeric$IntIsIntegral$;
   0      11      1    x       Ljava/lang/Object;


public java.lang.Object fromInt(int);
  Signature: (I)Ljava/lang/Object;
  Code:
   Stack=2, Locals=2, Args_size=2
	aload_0
	iload_1
	invokeinterface	InterfaceMethod scala/math/Numeric$IntIsIntegral.fromInt:(I)I
	invokestatic	Method scala/runtime/BoxesRunTime.boxToInteger:(I)Ljava/lang/Integer;
	areturn
  Labels:
  LocalVariableTable: 
   Start  Length  Slot  Name   Signature
   0      11      0    this       Lscala/math/Numeric$IntIsIntegral$;
   0      11      1    x       I


public java.lang.Object negate(java.lang.Object);
  Signature: (Ljava/lang/Object;)Ljava/lang/Object;
  Code:
   Stack=2, Locals=2, Args_size=2
	aload_0
	aload_1
	invokestatic	Method scala/runtime/BoxesRunTime.unboxToInt:(Ljava/lang/Object;)I
	invokeinterface	InterfaceMethod scala/math/Numeric$IntIsIntegral.negate:(I)I
	invokestatic	Method scala/runtime/BoxesRunTime.boxToInteger:(I)Ljava/lang/Integer;
	areturn
  Labels:
  LocalVariableTable: 
   Start  Length  Slot  Name   Signature
   0      14      0    this       Lscala/math/Numeric$IntIsIntegral$;
   0      14      1    x       Ljava/lang/Object;


public java.lang.Object rem(java.lang.Object, java.lang.Object);
  Signature: (Ljava/lang/Object;Ljava/lang/Object;)Ljava/lang/Object;
  Code:
   Stack=3, Locals=3, Args_size=3
	aload_0
	aload_1
	invokestatic	Method scala/runtime/BoxesRunTime.unboxToInt:(Ljava/lang/Object;)I
	aload_2
	invokestatic	Method scala/runtime/BoxesRunTime.unboxToInt:(Ljava/lang/Object;)I
	invokeinterface	InterfaceMethod scala/math/Numeric$IntIsIntegral.rem:(II)I
	invokestatic	Method scala/runtime/BoxesRunTime.boxToInteger:(I)Ljava/lang/Integer;
	areturn
  Labels:
  LocalVariableTable: 
   Start  Length  Slot  Name   Signature
   0      18      0    this       Lscala/math/Numeric$IntIsIntegral$;
   0      18      1    x       Ljava/lang/Object;
   0      18      2    y       Ljava/lang/Object;


public java.lang.Object quot(java.lang.Object, java.lang.Object);
  Signature: (Ljava/lang/Object;Ljava/lang/Object;)Ljava/lang/Object;
  Code:
   Stack=3, Locals=3, Args_size=3
	aload_0
	aload_1
	invokestatic	Method scala/runtime/BoxesRunTime.unboxToInt:(Ljava/lang/Object;)I
	aload_2
	invokestatic	Method scala/runtime/BoxesRunTime.unboxToInt:(Ljava/lang/Object;)I
	invokeinterface	InterfaceMethod scala/math/Numeric$IntIsIntegral.quot:(II)I
	invokestatic	Method scala/runtime/BoxesRunTime.boxToInteger:(I)Ljava/lang/Integer;
	areturn
  Labels:
  LocalVariableTable: 
   Start  Length  Slot  Name   Signature
   0      18      0    this       Lscala/math/Numeric$IntIsIntegral$;
   0      18      1    x       Ljava/lang/Object;
   0      18      2    y       Ljava/lang/Object;


public java.lang.Object times(java.lang.Object, java.lang.Object);
  Signature: (Ljava/lang/Object;Ljava/lang/Object;)Ljava/lang/Object;
  Code:
   Stack=3, Locals=3, Args_size=3
	aload_0
	aload_1
	invokestatic	Method scala/runtime/BoxesRunTime.unboxToInt:(Ljava/lang/Object;)I
	aload_2
	invokestatic	Method scala/runtime/BoxesRunTime.unboxToInt:(Ljava/lang/Object;)I
	invokeinterface	InterfaceMethod scala/math/Numeric$IntIsIntegral.times:(II)I
	invokestatic	Method scala/runtime/BoxesRunTime.boxToInteger:(I)Ljava/lang/Integer;
	areturn
  Labels:
  LocalVariableTable: 
   Start  Length  Slot  Name   Signature
   0      18      0    this       Lscala/math/Numeric$IntIsIntegral$;
   0      18      1    x       Ljava/lang/Object;
   0      18      2    y       Ljava/lang/Object;


public java.lang.Object minus(java.lang.Object, java.lang.Object);
  Signature: (Ljava/lang/Object;Ljava/lang/Object;)Ljava/lang/Object;
  Code:
   Stack=3, Locals=3, Args_size=3
	aload_0
	aload_1
	invokestatic	Method scala/runtime/BoxesRunTime.unboxToInt:(Ljava/lang/Object;)I
	aload_2
	invokestatic	Method scala/runtime/BoxesRunTime.unboxToInt:(Ljava/lang/Object;)I
	invokeinterface	InterfaceMethod scala/math/Numeric$IntIsIntegral.minus:(II)I
	invokestatic	Method scala/runtime/BoxesRunTime.boxToInteger:(I)Ljava/lang/Integer;
	areturn
  Labels:
  LocalVariableTable: 
   Start  Length  Slot  Name   Signature
   0      18      0    this       Lscala/math/Numeric$IntIsIntegral$;
   0      18      1    x       Ljava/lang/Object;
   0      18      2    y       Ljava/lang/Object;


public java.lang.Object plus(java.lang.Object, java.lang.Object);
  Signature: (Ljava/lang/Object;Ljava/lang/Object;)Ljava/lang/Object;
  Code:
   Stack=3, Locals=3, Args_size=3
	aload_0
	aload_1
	invokestatic	Method scala/runtime/BoxesRunTime.unboxToInt:(Ljava/lang/Object;)I
	aload_2
	invokestatic	Method scala/runtime/BoxesRunTime.unboxToInt:(Ljava/lang/Object;)I
	invokeinterface	InterfaceMethod scala/math/Numeric$IntIsIntegral.plus:(II)I
	invokestatic	Method scala/runtime/BoxesRunTime.boxToInteger:(I)Ljava/lang/Integer;
	areturn
  Labels:
  LocalVariableTable: 
   Start  Length  Slot  Name   Signature
   0      18      0    this       Lscala/math/Numeric$IntIsIntegral$;
   0      18      1    x       Ljava/lang/Object;
   0      18      2    y       Ljava/lang/Object;


public int compare(java.lang.Object, java.lang.Object);
  Signature: (Ljava/lang/Object;Ljava/lang/Object;)I
  Code:
   Stack=3, Locals=3, Args_size=3
	aload_0
	aload_1
	invokestatic	Method scala/runtime/BoxesRunTime.unboxToInt:(Ljava/lang/Object;)I
	aload_2
	invokestatic	Method scala/runtime/BoxesRunTime.unboxToInt:(Ljava/lang/Object;)I
	invokeinterface	InterfaceMethod scala/math/Ordering$IntOrdering.compare:(II)I
	ireturn
  Labels:
  LocalVariableTable: 
   Start  Length  Slot  Name   Signature
   0      15      0    this       Lscala/math/Numeric$IntIsIntegral$;
   0      15      1    x       Ljava/lang/Object;
   0      15      2    y       Ljava/lang/Object;


public scala.math.Numeric$IntIsIntegral$();
  Signature: ()V
  Code:
   Stack=1, Locals=1, Args_size=1
	aload_0
	invokespecial	Method java/lang/Object."<init>":()V
	aload_0
	putstatic	Field MODULE$:Lscala/math/Numeric$IntIsIntegral$;
	aload_0
	invokestatic	Method scala/math/PartialOrdering$class.$init$:(Lscala/math/PartialOrdering;)V
	aload_0
	invokestatic	Method scala/math/Ordering$class.$init$:(Lscala/math/Ordering;)V
	aload_0
	invokestatic	Method scala/math/Numeric$class.$init$:(Lscala/math/Numeric;)V
	aload_0
	invokestatic	Method scala/math/Integral$class.$init$:(Lscala/math/Integral;)V
	aload_0
	invokestatic	Method scala/math/Numeric$IntIsIntegral$class.$init$:(Lscala/math/Numeric$IntIsIntegral;)V
	aload_0
	invokestatic	Method scala/math/Ordering$IntOrdering$class.$init$:(Lscala/math/Ordering$IntOrdering;)V
	return
  Labels:

}

