Compiled from "Numeric.scala"
public abstract class scala.math.Numeric$class extends java.lang.Object
  SourceFile: "Numeric.scala"
  Scala: length = 0x
   
  InnerClass: 
   public #52= #13 of #23; //Ops=class scala/math/Numeric$Ops of class scala/math/Numeric
  minor version: 0
  major version: 49
  Constant pool:
const #1 = Asciz	SourceFile;
const #2 = Asciz	Numeric.scala;
const #3 = Asciz	$init$;
const #4 = Asciz	(Lscala/math/Numeric;)V;
const #5 = Asciz	Code;
const #6 = Asciz	LineNumberTable;
const #7 = Asciz	$this;
const #8 = Asciz	Lscala/math/Numeric;;
const #9 = Asciz	LocalVariableTable;
const #10 = Asciz	mkNumericOps;
const #11 = Asciz	(Lscala/math/Numeric;Ljava/lang/Object;)Lscala/math/Numeric$Ops;;
const #12 = Asciz	scala/math/Numeric$Ops;
const #13 = class	#12;	//  scala/math/Numeric$Ops
const #14 = Asciz	<init>;
const #15 = Asciz	(Lscala/math/Numeric;Ljava/lang/Object;)V;
const #16 = NameAndType	#14:#15;//  "<init>":(Lscala/math/Numeric;Ljava/lang/Object;)V
const #17 = Method	#13.#16;	//  scala/math/Numeric$Ops."<init>":(Lscala/math/Numeric;Ljava/lang/Object;)V
const #18 = Asciz	lhs;
const #19 = Asciz	Ljava/lang/Object;;
const #20 = Asciz	signum;
const #21 = Asciz	(Lscala/math/Numeric;Ljava/lang/Object;)I;
const #22 = Asciz	scala/math/Numeric;
const #23 = class	#22;	//  scala/math/Numeric
const #24 = Asciz	zero;
const #25 = Asciz	()Ljava/lang/Object;;
const #26 = NameAndType	#24:#25;//  zero:()Ljava/lang/Object;
const #27 = InterfaceMethod	#23.#26;	//  scala/math/Numeric.zero:()Ljava/lang/Object;
const #28 = Asciz	scala/math/Ordering;
const #29 = class	#28;	//  scala/math/Ordering
const #30 = Asciz	lt;
const #31 = Asciz	(Ljava/lang/Object;Ljava/lang/Object;)Z;
const #32 = NameAndType	#30:#31;//  lt:(Ljava/lang/Object;Ljava/lang/Object;)Z
const #33 = InterfaceMethod	#29.#32;	//  scala/math/Ordering.lt:(Ljava/lang/Object;Ljava/lang/Object;)Z
const #34 = Asciz	gt;
const #35 = NameAndType	#34:#31;//  gt:(Ljava/lang/Object;Ljava/lang/Object;)Z
const #36 = InterfaceMethod	#29.#35;	//  scala/math/Ordering.gt:(Ljava/lang/Object;Ljava/lang/Object;)Z
const #37 = Asciz	x;
const #38 = Asciz	abs;
const #39 = Asciz	(Lscala/math/Numeric;Ljava/lang/Object;)Ljava/lang/Object;;
const #40 = Asciz	negate;
const #41 = Asciz	(Ljava/lang/Object;)Ljava/lang/Object;;
const #42 = NameAndType	#40:#41;//  negate:(Ljava/lang/Object;)Ljava/lang/Object;
const #43 = InterfaceMethod	#23.#42;	//  scala/math/Numeric.negate:(Ljava/lang/Object;)Ljava/lang/Object;
const #44 = Asciz	one;
const #45 = Asciz	(Lscala/math/Numeric;)Ljava/lang/Object;;
const #46 = Asciz	fromInt;
const #47 = Asciz	(I)Ljava/lang/Object;;
const #48 = NameAndType	#46:#47;//  fromInt:(I)Ljava/lang/Object;
const #49 = InterfaceMethod	#23.#48;	//  scala/math/Numeric.fromInt:(I)Ljava/lang/Object;
const #50 = Asciz	Scala;
const #51 = Asciz	InnerClasses;
const #52 = Asciz	Ops;
const #53 = Asciz	scala/math/Numeric$class;
const #54 = class	#53;	//  scala/math/Numeric$class
const #55 = Asciz	java/lang/Object;
const #56 = class	#55;	//  java/lang/Object

{
public static void $init$(scala.math.Numeric);
  Code:
   Stack=0, Locals=1, Args_size=1
   0:	return
  LineNumberTable: 
   line 155: 0

  LocalVariableTable: 
   Start  Length  Slot  Name   Signature
   0      1      0    $this       Lscala/math/Numeric;


public static scala.math.Numeric$Ops mkNumericOps(scala.math.Numeric, java.lang.Object);
  Code:
   Stack=4, Locals=2, Args_size=2
   0:	new	#13; //class scala/math/Numeric$Ops
   3:	dup
   4:	aload_0
   5:	aload_1
   6:	invokespecial	#17; //Method scala/math/Numeric$Ops."<init>":(Lscala/math/Numeric;Ljava/lang/Object;)V
   9:	areturn
  LineNumberTable: 
   line 187: 0

  LocalVariableTable: 
   Start  Length  Slot  Name   Signature
   0      10      0    $this       Lscala/math/Numeric;
   0      10      1    lhs       Ljava/lang/Object;


public static int signum(scala.math.Numeric, java.lang.Object);
  Code:
   Stack=3, Locals=2, Args_size=2
   0:	aload_0
   1:	aload_1
   2:	aload_0
   3:	invokeinterface	#27,  1; //InterfaceMethod scala/math/Numeric.zero:()Ljava/lang/Object;
   8:	invokeinterface	#33,  3; //InterfaceMethod scala/math/Ordering.lt:(Ljava/lang/Object;Ljava/lang/Object;)Z
   13:	ifeq	20
   16:	iconst_m1
   17:	goto	41
   20:	aload_0
   21:	aload_1
   22:	aload_0
   23:	invokeinterface	#27,  1; //InterfaceMethod scala/math/Numeric.zero:()Ljava/lang/Object;
   28:	invokeinterface	#36,  3; //InterfaceMethod scala/math/Ordering.gt:(Ljava/lang/Object;Ljava/lang/Object;)Z
   33:	ifeq	40
   36:	iconst_1
   37:	goto	41
   40:	iconst_0
   41:	ireturn
  LineNumberTable: 
   line 171: 0
   line 172: 20
   line 173: 40
   line 171: 41

  LocalVariableTable: 
   Start  Length  Slot  Name   Signature
   0      42      0    $this       Lscala/math/Numeric;
   0      42      1    x       Ljava/lang/Object;


public static java.lang.Object abs(scala.math.Numeric, java.lang.Object);
  Code:
   Stack=3, Locals=2, Args_size=2
   0:	aload_0
   1:	aload_1
   2:	aload_0
   3:	invokeinterface	#27,  1; //InterfaceMethod scala/math/Numeric.zero:()Ljava/lang/Object;
   8:	invokeinterface	#33,  3; //InterfaceMethod scala/math/Ordering.lt:(Ljava/lang/Object;Ljava/lang/Object;)Z
   13:	ifeq	26
   16:	aload_0
   17:	aload_1
   18:	invokeinterface	#43,  2; //InterfaceMethod scala/math/Numeric.negate:(Ljava/lang/Object;)Ljava/lang/Object;
   23:	goto	27
   26:	aload_1
   27:	areturn
  LineNumberTable: 
   line 169: 0

  LocalVariableTable: 
   Start  Length  Slot  Name   Signature
   0      28      0    $this       Lscala/math/Numeric;
   0      28      1    x       Ljava/lang/Object;


public static java.lang.Object one(scala.math.Numeric);
  Code:
   Stack=2, Locals=1, Args_size=1
   0:	aload_0
   1:	iconst_1
   2:	invokeinterface	#49,  2; //InterfaceMethod scala/math/Numeric.fromInt:(I)Ljava/lang/Object;
   7:	areturn
  LineNumberTable: 
   line 167: 0

  LocalVariableTable: 
   Start  Length  Slot  Name   Signature
   0      8      0    $this       Lscala/math/Numeric;


public static java.lang.Object zero(scala.math.Numeric);
  Code:
   Stack=2, Locals=1, Args_size=1
   0:	aload_0
   1:	iconst_0
   2:	invokeinterface	#49,  2; //InterfaceMethod scala/math/Numeric.fromInt:(I)Ljava/lang/Object;
   7:	areturn
  LineNumberTable: 
   line 166: 0

  LocalVariableTable: 
   Start  Length  Slot  Name   Signature
   0      8      0    $this       Lscala/math/Numeric;


}

