Compiled from "Numeric.scala"
public abstract class scala.math.Numeric$BigDecimalIsConflicted$class extends java.lang.Object
  SourceFile: "Numeric.scala"
  Scala: length = 0x
   
  InnerClass: 
   public abstract #78= #75 of #77; //BigDecimalIsConflicted=class scala/math/Numeric$BigDecimalIsConflicted of class scala/math/Numeric
  minor version: 0
  major version: 49
  Constant pool:
const #1 = Asciz	SourceFile;
const #2 = Asciz	Numeric.scala;
const #3 = Asciz	$init$;
const #4 = Asciz	(Lscala/math/Numeric$BigDecimalIsConflicted;)V;
const #5 = Asciz	Code;
const #6 = Asciz	LineNumberTable;
const #7 = Asciz	$this;
const #8 = Asciz	Lscala/math/Numeric$BigDecimalIsConflicted;;
const #9 = Asciz	LocalVariableTable;
const #10 = Asciz	toDouble;
const #11 = Asciz	(Lscala/math/Numeric$BigDecimalIsConflicted;Lscala/math/BigDecimal;)D;
const #12 = Asciz	scala/math/BigDecimal;
const #13 = class	#12;	//  scala/math/BigDecimal
const #14 = Asciz	doubleValue;
const #15 = Asciz	()D;
const #16 = NameAndType	#14:#15;//  doubleValue:()D
const #17 = Method	#13.#16;	//  scala/math/BigDecimal.doubleValue:()D
const #18 = Asciz	x;
const #19 = Asciz	Lscala/math/BigDecimal;;
const #20 = Asciz	toFloat;
const #21 = Asciz	(Lscala/math/Numeric$BigDecimalIsConflicted;Lscala/math/BigDecimal;)F;
const #22 = Asciz	floatValue;
const #23 = Asciz	()F;
const #24 = NameAndType	#22:#23;//  floatValue:()F
const #25 = Method	#13.#24;	//  scala/math/BigDecimal.floatValue:()F
const #26 = Asciz	toLong;
const #27 = Asciz	(Lscala/math/Numeric$BigDecimalIsConflicted;Lscala/math/BigDecimal;)J;
const #28 = Asciz	longValue;
const #29 = Asciz	()J;
const #30 = NameAndType	#28:#29;//  longValue:()J
const #31 = Method	#13.#30;	//  scala/math/BigDecimal.longValue:()J
const #32 = Asciz	toInt;
const #33 = Asciz	(Lscala/math/Numeric$BigDecimalIsConflicted;Lscala/math/BigDecimal;)I;
const #34 = Asciz	intValue;
const #35 = Asciz	()I;
const #36 = NameAndType	#34:#35;//  intValue:()I
const #37 = Method	#13.#36;	//  scala/math/BigDecimal.intValue:()I
const #38 = Asciz	fromInt;
const #39 = Asciz	(Lscala/math/Numeric$BigDecimalIsConflicted;I)Lscala/math/BigDecimal;;
const #40 = Asciz	scala/math/BigDecimal$;
const #41 = class	#40;	//  scala/math/BigDecimal$
const #42 = Asciz	MODULE$;
const #43 = Asciz	Lscala/math/BigDecimal$;;
const #44 = NameAndType	#42:#43;//  MODULE$:Lscala/math/BigDecimal$;
const #45 = Field	#41.#44;	//  scala/math/BigDecimal$.MODULE$:Lscala/math/BigDecimal$;
const #46 = Asciz	apply;
const #47 = Asciz	(I)Lscala/math/BigDecimal;;
const #48 = NameAndType	#46:#47;//  apply:(I)Lscala/math/BigDecimal;
const #49 = Method	#41.#48;	//  scala/math/BigDecimal$.apply:(I)Lscala/math/BigDecimal;
const #50 = Asciz	I;
const #51 = Asciz	negate;
const #52 = Asciz	(Lscala/math/Numeric$BigDecimalIsConflicted;Lscala/math/BigDecimal;)Lscala/math/BigDecimal;;
const #53 = Asciz	unary_$minus;
const #54 = Asciz	()Lscala/math/BigDecimal;;
const #55 = NameAndType	#53:#54;//  unary_$minus:()Lscala/math/BigDecimal;
const #56 = Method	#13.#55;	//  scala/math/BigDecimal.unary_$minus:()Lscala/math/BigDecimal;
const #57 = Asciz	times;
const #58 = Asciz	(Lscala/math/Numeric$BigDecimalIsConflicted;Lscala/math/BigDecimal;Lscala/math/BigDecimal;)Lscala/math/BigDecimal;;
const #59 = Asciz	$times;
const #60 = Asciz	(Lscala/math/BigDecimal;)Lscala/math/BigDecimal;;
const #61 = NameAndType	#59:#60;//  $times:(Lscala/math/BigDecimal;)Lscala/math/BigDecimal;
const #62 = Method	#13.#61;	//  scala/math/BigDecimal.$times:(Lscala/math/BigDecimal;)Lscala/math/BigDecimal;
const #63 = Asciz	y;
const #64 = Asciz	minus;
const #65 = Asciz	$minus;
const #66 = NameAndType	#65:#60;//  $minus:(Lscala/math/BigDecimal;)Lscala/math/BigDecimal;
const #67 = Method	#13.#66;	//  scala/math/BigDecimal.$minus:(Lscala/math/BigDecimal;)Lscala/math/BigDecimal;
const #68 = Asciz	plus;
const #69 = Asciz	$plus;
const #70 = NameAndType	#69:#60;//  $plus:(Lscala/math/BigDecimal;)Lscala/math/BigDecimal;
const #71 = Method	#13.#70;	//  scala/math/BigDecimal.$plus:(Lscala/math/BigDecimal;)Lscala/math/BigDecimal;
const #72 = Asciz	Scala;
const #73 = Asciz	InnerClasses;
const #74 = Asciz	scala/math/Numeric$BigDecimalIsConflicted;
const #75 = class	#74;	//  scala/math/Numeric$BigDecimalIsConflicted
const #76 = Asciz	scala/math/Numeric;
const #77 = class	#76;	//  scala/math/Numeric
const #78 = Asciz	BigDecimalIsConflicted;
const #79 = Asciz	scala/math/Numeric$BigDecimalIsConflicted$class;
const #80 = class	#79;	//  scala/math/Numeric$BigDecimalIsConflicted$class
const #81 = Asciz	java/lang/Object;
const #82 = class	#81;	//  java/lang/Object

{
public static void $init$(scala.math.Numeric$BigDecimalIsConflicted);
  Code:
   Stack=0, Locals=1, Args_size=1
   0:	return
  LineNumberTable: 
   line 126: 0

  LocalVariableTable: 
   Start  Length  Slot  Name   Signature
   0      1      0    $this       Lscala/math/Numeric$BigDecimalIsConflicted;


public static double toDouble(scala.math.Numeric$BigDecimalIsConflicted, scala.math.BigDecimal);
  Code:
   Stack=2, Locals=2, Args_size=2
   0:	aload_1
   1:	invokevirtual	#17; //Method scala/math/BigDecimal.doubleValue:()D
   4:	dreturn
  LineNumberTable: 
   line 135: 0

  LocalVariableTable: 
   Start  Length  Slot  Name   Signature
   0      5      0    $this       Lscala/math/Numeric$BigDecimalIsConflicted;
   0      5      1    x       Lscala/math/BigDecimal;


public static float toFloat(scala.math.Numeric$BigDecimalIsConflicted, scala.math.BigDecimal);
  Code:
   Stack=1, Locals=2, Args_size=2
   0:	aload_1
   1:	invokevirtual	#25; //Method scala/math/BigDecimal.floatValue:()F
   4:	freturn
  LineNumberTable: 
   line 134: 0

  LocalVariableTable: 
   Start  Length  Slot  Name   Signature
   0      5      0    $this       Lscala/math/Numeric$BigDecimalIsConflicted;
   0      5      1    x       Lscala/math/BigDecimal;


public static long toLong(scala.math.Numeric$BigDecimalIsConflicted, scala.math.BigDecimal);
  Code:
   Stack=2, Locals=2, Args_size=2
   0:	aload_1
   1:	invokevirtual	#31; //Method scala/math/BigDecimal.longValue:()J
   4:	lreturn
  LineNumberTable: 
   line 133: 0

  LocalVariableTable: 
   Start  Length  Slot  Name   Signature
   0      5      0    $this       Lscala/math/Numeric$BigDecimalIsConflicted;
   0      5      1    x       Lscala/math/BigDecimal;


public static int toInt(scala.math.Numeric$BigDecimalIsConflicted, scala.math.BigDecimal);
  Code:
   Stack=1, Locals=2, Args_size=2
   0:	aload_1
   1:	invokevirtual	#37; //Method scala/math/BigDecimal.intValue:()I
   4:	ireturn
  LineNumberTable: 
   line 132: 0

  LocalVariableTable: 
   Start  Length  Slot  Name   Signature
   0      5      0    $this       Lscala/math/Numeric$BigDecimalIsConflicted;
   0      5      1    x       Lscala/math/BigDecimal;


public static scala.math.BigDecimal fromInt(scala.math.Numeric$BigDecimalIsConflicted, int);
  Code:
   Stack=2, Locals=2, Args_size=2
   0:	getstatic	#45; //Field scala/math/BigDecimal$.MODULE$:Lscala/math/BigDecimal$;
   3:	iload_1
   4:	invokevirtual	#49; //Method scala/math/BigDecimal$.apply:(I)Lscala/math/BigDecimal;
   7:	areturn
  LineNumberTable: 
   line 131: 0

  LocalVariableTable: 
   Start  Length  Slot  Name   Signature
   0      8      0    $this       Lscala/math/Numeric$BigDecimalIsConflicted;
   0      8      1    x       I


public static scala.math.BigDecimal negate(scala.math.Numeric$BigDecimalIsConflicted, scala.math.BigDecimal);
  Code:
   Stack=1, Locals=2, Args_size=2
   0:	aload_1
   1:	invokevirtual	#56; //Method scala/math/BigDecimal.unary_$minus:()Lscala/math/BigDecimal;
   4:	areturn
  LineNumberTable: 
   line 130: 0

  LocalVariableTable: 
   Start  Length  Slot  Name   Signature
   0      5      0    $this       Lscala/math/Numeric$BigDecimalIsConflicted;
   0      5      1    x       Lscala/math/BigDecimal;


public static scala.math.BigDecimal times(scala.math.Numeric$BigDecimalIsConflicted, scala.math.BigDecimal, scala.math.BigDecimal);
  Code:
   Stack=2, Locals=3, Args_size=3
   0:	aload_1
   1:	aload_2
   2:	invokevirtual	#62; //Method scala/math/BigDecimal.$times:(Lscala/math/BigDecimal;)Lscala/math/BigDecimal;
   5:	areturn
  LineNumberTable: 
   line 129: 0

  LocalVariableTable: 
   Start  Length  Slot  Name   Signature
   0      6      0    $this       Lscala/math/Numeric$BigDecimalIsConflicted;
   0      6      1    x       Lscala/math/BigDecimal;
   0      6      2    y       Lscala/math/BigDecimal;


public static scala.math.BigDecimal minus(scala.math.Numeric$BigDecimalIsConflicted, scala.math.BigDecimal, scala.math.BigDecimal);
  Code:
   Stack=2, Locals=3, Args_size=3
   0:	aload_1
   1:	aload_2
   2:	invokevirtual	#67; //Method scala/math/BigDecimal.$minus:(Lscala/math/BigDecimal;)Lscala/math/BigDecimal;
   5:	areturn
  LineNumberTable: 
   line 128: 0

  LocalVariableTable: 
   Start  Length  Slot  Name   Signature
   0      6      0    $this       Lscala/math/Numeric$BigDecimalIsConflicted;
   0      6      1    x       Lscala/math/BigDecimal;
   0      6      2    y       Lscala/math/BigDecimal;


public static scala.math.BigDecimal plus(scala.math.Numeric$BigDecimalIsConflicted, scala.math.BigDecimal, scala.math.BigDecimal);
  Code:
   Stack=2, Locals=3, Args_size=3
   0:	aload_1
   1:	aload_2
   2:	invokevirtual	#71; //Method scala/math/BigDecimal.$plus:(Lscala/math/BigDecimal;)Lscala/math/BigDecimal;
   5:	areturn
  LineNumberTable: 
   line 127: 0

  LocalVariableTable: 
   Start  Length  Slot  Name   Signature
   0      6      0    $this       Lscala/math/Numeric$BigDecimalIsConflicted;
   0      6      1    x       Lscala/math/BigDecimal;
   0      6      2    y       Lscala/math/BigDecimal;


}

