Compiled from "Ordering.scala"
public abstract class scala.math.Ordering$class extends java.lang.Object
  SourceFile: "Ordering.scala"
  Scala: length = 0x
   
  InnerClass: 
   public #72= #13 of #38; //Ops=class scala/math/Ordering$Ops of class scala/math/Ordering
   public final #73= #32 of #38; //$anon$1=class scala/math/Ordering$$anon$1 of class scala/math/Ordering
   public final #74= #23 of #38; //$anon$2=class scala/math/Ordering$$anon$2 of class scala/math/Ordering
  minor version: 0
  major version: 49
  Constant pool:
const #1 = Asciz	SourceFile;
const #2 = Asciz	Ordering.scala;
const #3 = Asciz	$init$;
const #4 = Asciz	(Lscala/math/Ordering;)V;
const #5 = Asciz	Code;
const #6 = Asciz	LineNumberTable;
const #7 = Asciz	$this;
const #8 = Asciz	Lscala/math/Ordering;;
const #9 = Asciz	LocalVariableTable;
const #10 = Asciz	mkOrderingOps;
const #11 = Asciz	(Lscala/math/Ordering;Ljava/lang/Object;)Lscala/math/Ordering$Ops;;
const #12 = Asciz	scala/math/Ordering$Ops;
const #13 = class	#12;	//  scala/math/Ordering$Ops
const #14 = Asciz	<init>;
const #15 = Asciz	(Lscala/math/Ordering;Ljava/lang/Object;)V;
const #16 = NameAndType	#14:#15;//  "<init>":(Lscala/math/Ordering;Ljava/lang/Object;)V
const #17 = Method	#13.#16;	//  scala/math/Ordering$Ops."<init>":(Lscala/math/Ordering;Ljava/lang/Object;)V
const #18 = Asciz	lhs;
const #19 = Asciz	Ljava/lang/Object;;
const #20 = Asciz	on;
const #21 = Asciz	(Lscala/math/Ordering;Lscala/Function1;)Lscala/math/Ordering;;
const #22 = Asciz	scala/math/Ordering$$anon$2;
const #23 = class	#22;	//  scala/math/Ordering$$anon$2
const #24 = Asciz	(Lscala/math/Ordering;Lscala/Function1;)V;
const #25 = NameAndType	#14:#24;//  "<init>":(Lscala/math/Ordering;Lscala/Function1;)V
const #26 = Method	#23.#25;	//  scala/math/Ordering$$anon$2."<init>":(Lscala/math/Ordering;Lscala/Function1;)V
const #27 = Asciz	f$1;
const #28 = Asciz	Lscala/Function1;;
const #29 = Asciz	reverse;
const #30 = Asciz	(Lscala/math/Ordering;)Lscala/math/Ordering;;
const #31 = Asciz	scala/math/Ordering$$anon$1;
const #32 = class	#31;	//  scala/math/Ordering$$anon$1
const #33 = NameAndType	#14:#4;//  "<init>":(Lscala/math/Ordering;)V
const #34 = Method	#32.#33;	//  scala/math/Ordering$$anon$1."<init>":(Lscala/math/Ordering;)V
const #35 = Asciz	min;
const #36 = Asciz	(Lscala/math/Ordering;Ljava/lang/Object;Ljava/lang/Object;)Ljava/lang/Object;;
const #37 = Asciz	scala/math/Ordering;
const #38 = class	#37;	//  scala/math/Ordering
const #39 = Asciz	lteq;
const #40 = Asciz	(Ljava/lang/Object;Ljava/lang/Object;)Z;
const #41 = NameAndType	#39:#40;//  lteq:(Ljava/lang/Object;Ljava/lang/Object;)Z
const #42 = InterfaceMethod	#38.#41;	//  scala/math/Ordering.lteq:(Ljava/lang/Object;Ljava/lang/Object;)Z
const #43 = Asciz	x;
const #44 = Asciz	y;
const #45 = Asciz	max;
const #46 = Asciz	gteq;
const #47 = NameAndType	#46:#40;//  gteq:(Ljava/lang/Object;Ljava/lang/Object;)Z
const #48 = InterfaceMethod	#38.#47;	//  scala/math/Ordering.gteq:(Ljava/lang/Object;Ljava/lang/Object;)Z
const #49 = Asciz	equiv;
const #50 = Asciz	(Lscala/math/Ordering;Ljava/lang/Object;Ljava/lang/Object;)Z;
const #51 = Asciz	compare;
const #52 = Asciz	(Ljava/lang/Object;Ljava/lang/Object;)I;
const #53 = NameAndType	#51:#52;//  compare:(Ljava/lang/Object;Ljava/lang/Object;)I
const #54 = InterfaceMethod	#38.#53;	//  scala/math/Ordering.compare:(Ljava/lang/Object;Ljava/lang/Object;)I
const #55 = Asciz	gt;
const #56 = Asciz	lt;
const #57 = Asciz	tryCompare;
const #58 = Asciz	(Lscala/math/Ordering;Ljava/lang/Object;Ljava/lang/Object;)Lscala/Some;;
const #59 = Asciz	scala/Some;
const #60 = class	#59;	//  scala/Some
const #61 = Asciz	scala/runtime/BoxesRunTime;
const #62 = class	#61;	//  scala/runtime/BoxesRunTime
const #63 = Asciz	boxToInteger;
const #64 = Asciz	(I)Ljava/lang/Integer;;
const #65 = NameAndType	#63:#64;//  boxToInteger:(I)Ljava/lang/Integer;
const #66 = Method	#62.#65;	//  scala/runtime/BoxesRunTime.boxToInteger:(I)Ljava/lang/Integer;
const #67 = Asciz	(Ljava/lang/Object;)V;
const #68 = NameAndType	#14:#67;//  "<init>":(Ljava/lang/Object;)V
const #69 = Method	#60.#68;	//  scala/Some."<init>":(Ljava/lang/Object;)V
const #70 = Asciz	Scala;
const #71 = Asciz	InnerClasses;
const #72 = Asciz	Ops;
const #73 = Asciz	$anon$1;
const #74 = Asciz	$anon$2;
const #75 = Asciz	scala/math/Ordering$class;
const #76 = class	#75;	//  scala/math/Ordering$class
const #77 = Asciz	java/lang/Object;
const #78 = class	#77;	//  java/lang/Object

{
public static void $init$(scala.math.Ordering);
  Code:
   Stack=0, Locals=1, Args_size=1
   0:	return
  LineNumberTable: 
   line 45: 0

  LocalVariableTable: 
   Start  Length  Slot  Name   Signature
   0      1      0    $this       Lscala/math/Ordering;


public static scala.math.Ordering$Ops mkOrderingOps(scala.math.Ordering, java.lang.Object);
  Code:
   Stack=4, Locals=2, Args_size=2
   0:	new	#13; //class scala/math/Ordering$Ops
   3:	dup
   4:	aload_0
   5:	aload_1
   6:	invokespecial	#17; //Method scala/math/Ordering$Ops."<init>":(Lscala/math/Ordering;Ljava/lang/Object;)V
   9:	areturn
  LineNumberTable: 
   line 109: 0

  LocalVariableTable: 
   Start  Length  Slot  Name   Signature
   0      10      0    $this       Lscala/math/Ordering;
   0      10      1    lhs       Ljava/lang/Object;


public static scala.math.Ordering on(scala.math.Ordering, scala.Function1);
  Code:
   Stack=4, Locals=2, Args_size=2
   0:	new	#23; //class scala/math/Ordering$$anon$2
   3:	dup
   4:	aload_0
   5:	aload_1
   6:	invokespecial	#26; //Method scala/math/Ordering$$anon$2."<init>":(Lscala/math/Ordering;Lscala/Function1;)V
   9:	areturn
  LineNumberTable: 
   line 96: 0

  LocalVariableTable: 
   Start  Length  Slot  Name   Signature
   0      10      0    $this       Lscala/math/Ordering;
   0      10      1    f$1       Lscala/Function1;


public static scala.math.Ordering reverse(scala.math.Ordering);
  Code:
   Stack=3, Locals=1, Args_size=1
   0:	new	#32; //class scala/math/Ordering$$anon$1
   3:	dup
   4:	aload_0
   5:	invokespecial	#34; //Method scala/math/Ordering$$anon$1."<init>":(Lscala/math/Ordering;)V
   8:	areturn
  LineNumberTable: 
   line 90: 0

  LocalVariableTable: 
   Start  Length  Slot  Name   Signature
   0      9      0    $this       Lscala/math/Ordering;


public static java.lang.Object min(scala.math.Ordering, java.lang.Object, java.lang.Object);
  Code:
   Stack=3, Locals=3, Args_size=3
   0:	aload_0
   1:	aload_1
   2:	aload_2
   3:	invokeinterface	#42,  3; //InterfaceMethod scala/math/Ordering.lteq:(Ljava/lang/Object;Ljava/lang/Object;)Z
   8:	ifeq	15
   11:	aload_1
   12:	goto	16
   15:	aload_2
   16:	areturn
  LineNumberTable: 
   line 88: 0

  LocalVariableTable: 
   Start  Length  Slot  Name   Signature
   0      17      0    $this       Lscala/math/Ordering;
   0      17      1    x       Ljava/lang/Object;
   0      17      2    y       Ljava/lang/Object;


public static java.lang.Object max(scala.math.Ordering, java.lang.Object, java.lang.Object);
  Code:
   Stack=3, Locals=3, Args_size=3
   0:	aload_0
   1:	aload_1
   2:	aload_2
   3:	invokeinterface	#48,  3; //InterfaceMethod scala/math/Ordering.gteq:(Ljava/lang/Object;Ljava/lang/Object;)Z
   8:	ifeq	15
   11:	aload_1
   12:	goto	16
   15:	aload_2
   16:	areturn
  LineNumberTable: 
   line 85: 0

  LocalVariableTable: 
   Start  Length  Slot  Name   Signature
   0      17      0    $this       Lscala/math/Ordering;
   0      17      1    x       Ljava/lang/Object;
   0      17      2    y       Ljava/lang/Object;


public static boolean equiv(scala.math.Ordering, java.lang.Object, java.lang.Object);
  Code:
   Stack=3, Locals=3, Args_size=3
   0:	aload_0
   1:	aload_1
   2:	aload_2
   3:	invokeinterface	#54,  3; //InterfaceMethod scala/math/Ordering.compare:(Ljava/lang/Object;Ljava/lang/Object;)I
   8:	iconst_0
   9:	if_icmpne	16
   12:	iconst_1
   13:	goto	17
   16:	iconst_0
   17:	ireturn
  LineNumberTable: 
   line 82: 0

  LocalVariableTable: 
   Start  Length  Slot  Name   Signature
   0      18      0    $this       Lscala/math/Ordering;
   0      18      1    x       Ljava/lang/Object;
   0      18      2    y       Ljava/lang/Object;


public static boolean gt(scala.math.Ordering, java.lang.Object, java.lang.Object);
  Code:
   Stack=3, Locals=3, Args_size=3
   0:	aload_0
   1:	aload_1
   2:	aload_2
   3:	invokeinterface	#54,  3; //InterfaceMethod scala/math/Ordering.compare:(Ljava/lang/Object;Ljava/lang/Object;)I
   8:	iconst_0
   9:	if_icmple	16
   12:	iconst_1
   13:	goto	17
   16:	iconst_0
   17:	ireturn
  LineNumberTable: 
   line 77: 0

  LocalVariableTable: 
   Start  Length  Slot  Name   Signature
   0      18      0    $this       Lscala/math/Ordering;
   0      18      1    x       Ljava/lang/Object;
   0      18      2    y       Ljava/lang/Object;


public static boolean lt(scala.math.Ordering, java.lang.Object, java.lang.Object);
  Code:
   Stack=3, Locals=3, Args_size=3
   0:	aload_0
   1:	aload_1
   2:	aload_2
   3:	invokeinterface	#54,  3; //InterfaceMethod scala/math/Ordering.compare:(Ljava/lang/Object;Ljava/lang/Object;)I
   8:	iconst_0
   9:	if_icmpge	16
   12:	iconst_1
   13:	goto	17
   16:	iconst_0
   17:	ireturn
  LineNumberTable: 
   line 72: 0

  LocalVariableTable: 
   Start  Length  Slot  Name   Signature
   0      18      0    $this       Lscala/math/Ordering;
   0      18      1    x       Ljava/lang/Object;
   0      18      2    y       Ljava/lang/Object;


public static boolean gteq(scala.math.Ordering, java.lang.Object, java.lang.Object);
  Code:
   Stack=3, Locals=3, Args_size=3
   0:	aload_0
   1:	aload_1
   2:	aload_2
   3:	invokeinterface	#54,  3; //InterfaceMethod scala/math/Ordering.compare:(Ljava/lang/Object;Ljava/lang/Object;)I
   8:	iconst_0
   9:	if_icmplt	16
   12:	iconst_1
   13:	goto	17
   16:	iconst_0
   17:	ireturn
  LineNumberTable: 
   line 67: 0

  LocalVariableTable: 
   Start  Length  Slot  Name   Signature
   0      18      0    $this       Lscala/math/Ordering;
   0      18      1    x       Ljava/lang/Object;
   0      18      2    y       Ljava/lang/Object;


public static boolean lteq(scala.math.Ordering, java.lang.Object, java.lang.Object);
  Code:
   Stack=3, Locals=3, Args_size=3
   0:	aload_0
   1:	aload_1
   2:	aload_2
   3:	invokeinterface	#54,  3; //InterfaceMethod scala/math/Ordering.compare:(Ljava/lang/Object;Ljava/lang/Object;)I
   8:	iconst_0
   9:	if_icmpgt	16
   12:	iconst_1
   13:	goto	17
   16:	iconst_0
   17:	ireturn
  LineNumberTable: 
   line 62: 0

  LocalVariableTable: 
   Start  Length  Slot  Name   Signature
   0      18      0    $this       Lscala/math/Ordering;
   0      18      1    x       Ljava/lang/Object;
   0      18      2    y       Ljava/lang/Object;


public static scala.Some tryCompare(scala.math.Ordering, java.lang.Object, java.lang.Object);
  Code:
   Stack=5, Locals=4, Args_size=3
   0:	new	#60; //class scala/Some
   3:	dup
   4:	aload_0
   5:	aload_1
   6:	aload_2
   7:	invokeinterface	#54,  3; //InterfaceMethod scala/math/Ordering.compare:(Ljava/lang/Object;Ljava/lang/Object;)I
   12:	istore_3
   13:	iload_3
   14:	invokestatic	#66; //Method scala/runtime/BoxesRunTime.boxToInteger:(I)Ljava/lang/Integer;
   17:	invokespecial	#69; //Method scala/Some."<init>":(Ljava/lang/Object;)V
   20:	areturn
  LineNumberTable: 
   line 49: 0

  LocalVariableTable: 
   Start  Length  Slot  Name   Signature
   0      21      0    $this       Lscala/math/Ordering;
   0      21      1    x       Ljava/lang/Object;
   0      21      2    y       Ljava/lang/Object;


}

