Compiled from "Ordering.scala"
public abstract class scala.math.Ordering$StringOrdering$class extends java.lang.Object
  SourceFile: "Ordering.scala"
  Scala: length = 0x
   
  InnerClass: 
   public abstract #27= #24 of #26; //StringOrdering=class scala/math/Ordering$StringOrdering of class scala/math/Ordering
  minor version: 0
  major version: 49
  Constant pool:
const #1 = Asciz	SourceFile;
const #2 = Asciz	Ordering.scala;
const #3 = Asciz	$init$;
const #4 = Asciz	(Lscala/math/Ordering$StringOrdering;)V;
const #5 = Asciz	Code;
const #6 = Asciz	LineNumberTable;
const #7 = Asciz	$this;
const #8 = Asciz	Lscala/math/Ordering$StringOrdering;;
const #9 = Asciz	LocalVariableTable;
const #10 = Asciz	compare;
const #11 = Asciz	(Lscala/math/Ordering$StringOrdering;Ljava/lang/String;Ljava/lang/String;)I;
const #12 = Asciz	java/lang/String;
const #13 = class	#12;	//  java/lang/String
const #14 = Asciz	compareTo;
const #15 = Asciz	(Ljava/lang/String;)I;
const #16 = NameAndType	#14:#15;//  compareTo:(Ljava/lang/String;)I
const #17 = Method	#13.#16;	//  java/lang/String.compareTo:(Ljava/lang/String;)I
const #18 = Asciz	x;
const #19 = Asciz	Ljava/lang/String;;
const #20 = Asciz	y;
const #21 = Asciz	Scala;
const #22 = Asciz	InnerClasses;
const #23 = Asciz	scala/math/Ordering$StringOrdering;
const #24 = class	#23;	//  scala/math/Ordering$StringOrdering
const #25 = Asciz	scala/math/Ordering;
const #26 = class	#25;	//  scala/math/Ordering
const #27 = Asciz	StringOrdering;
const #28 = Asciz	scala/math/Ordering$StringOrdering$class;
const #29 = class	#28;	//  scala/math/Ordering$StringOrdering$class
const #30 = Asciz	java/lang/Object;
const #31 = class	#30;	//  java/lang/Object

{
public static void $init$(scala.math.Ordering$StringOrdering);
  Code:
   Stack=0, Locals=1, Args_size=1
   0:	return
  LineNumberTable: 
   line 201: 0

  LocalVariableTable: 
   Start  Length  Slot  Name   Signature
   0      1      0    $this       Lscala/math/Ordering$StringOrdering;


public static int compare(scala.math.Ordering$StringOrdering, java.lang.String, java.lang.String);
  Code:
   Stack=2, Locals=3, Args_size=3
   0:	aload_1
   1:	aload_2
   2:	invokevirtual	#17; //Method java/lang/String.compareTo:(Ljava/lang/String;)I
   5:	ireturn
  LineNumberTable: 
   line 202: 0

  LocalVariableTable: 
   Start  Length  Slot  Name   Signature
   0      6      0    $this       Lscala/math/Ordering$StringOrdering;
   0      6      1    x       Ljava/lang/String;
   0      6      2    y       Ljava/lang/String;


}

