Compiled from "Ordering.scala"
public class scala.math.Ordering$Ops extends java.lang.Object implements scala.ScalaObject
  SourceFile: "Ordering.scala"
  Scala: length = 0x
   
  InnerClass: 
   public #71= #14 of #38; //Ops=class scala/math/Ordering$Ops of class scala/math/Ordering
  minor version: 0
  major version: 49
  Constant pool:
const #1 = Asciz	SourceFile;
const #2 = Asciz	Ordering.scala;
const #3 = Asciz	$outer;
const #4 = Asciz	Lscala/math/Ordering;;
const #5 = Asciz	lhs;
const #6 = Asciz	Ljava/lang/Object;;
const #7 = Asciz	TT;;
const #8 = Asciz	Signature;
const #9 = Asciz	<init>;
const #10 = Asciz	(Lscala/math/Ordering;Ljava/lang/Object;)V;
const #11 = Asciz	Code;
const #12 = Asciz	LineNumberTable;
const #13 = Asciz	scala/math/Ordering$Ops;
const #14 = class	#13;	//  scala/math/Ordering$Ops
const #15 = NameAndType	#5:#6;//  lhs:Ljava/lang/Object;
const #16 = Field	#14.#15;	//  scala/math/Ordering$Ops.lhs:Ljava/lang/Object;
const #17 = Asciz	java/lang/NullPointerException;
const #18 = class	#17;	//  java/lang/NullPointerException
const #19 = Asciz	()V;
const #20 = NameAndType	#9:#19;//  "<init>":()V
const #21 = Method	#18.#20;	//  java/lang/NullPointerException."<init>":()V
const #22 = NameAndType	#3:#4;//  $outer:Lscala/math/Ordering;
const #23 = Field	#14.#22;	//  scala/math/Ordering$Ops.$outer:Lscala/math/Ordering;
const #24 = Asciz	java/lang/Object;
const #25 = class	#24;	//  java/lang/Object
const #26 = Method	#25.#20;	//  java/lang/Object."<init>":()V
const #27 = Asciz	this;
const #28 = Asciz	Lscala/math/Ordering$Ops;;
const #29 = Asciz	LocalVariableTable;
const #30 = Asciz	(Lscala/math/Ordering<TT;>;TT;)V;
const #31 = Asciz	scala$math$Ordering$Ops$$$outer;
const #32 = Asciz	()Lscala/math/Ordering;;
const #33 = Asciz	min;
const #34 = Asciz	(Ljava/lang/Object;)Ljava/lang/Object;;
const #35 = NameAndType	#31:#32;//  scala$math$Ordering$Ops$$$outer:()Lscala/math/Ordering;
const #36 = Method	#14.#35;	//  scala/math/Ordering$Ops.scala$math$Ordering$Ops$$$outer:()Lscala/math/Ordering;
const #37 = Asciz	scala/math/Ordering;
const #38 = class	#37;	//  scala/math/Ordering
const #39 = Asciz	(Ljava/lang/Object;Ljava/lang/Object;)Ljava/lang/Object;;
const #40 = NameAndType	#33:#39;//  min:(Ljava/lang/Object;Ljava/lang/Object;)Ljava/lang/Object;
const #41 = InterfaceMethod	#38.#40;	//  scala/math/Ordering.min:(Ljava/lang/Object;Ljava/lang/Object;)Ljava/lang/Object;
const #42 = Asciz	rhs;
const #43 = Asciz	(TT;)TT;;
const #44 = Asciz	max;
const #45 = NameAndType	#44:#39;//  max:(Ljava/lang/Object;Ljava/lang/Object;)Ljava/lang/Object;
const #46 = InterfaceMethod	#38.#45;	//  scala/math/Ordering.max:(Ljava/lang/Object;Ljava/lang/Object;)Ljava/lang/Object;
const #47 = Asciz	equiv;
const #48 = Asciz	(Ljava/lang/Object;)Z;
const #49 = Asciz	(Ljava/lang/Object;Ljava/lang/Object;)Z;
const #50 = NameAndType	#47:#49;//  equiv:(Ljava/lang/Object;Ljava/lang/Object;)Z
const #51 = InterfaceMethod	#38.#50;	//  scala/math/Ordering.equiv:(Ljava/lang/Object;Ljava/lang/Object;)Z
const #52 = Asciz	(TT;)Z;
const #53 = Asciz	$greater$eq;
const #54 = Asciz	gteq;
const #55 = NameAndType	#54:#49;//  gteq:(Ljava/lang/Object;Ljava/lang/Object;)Z
const #56 = InterfaceMethod	#38.#55;	//  scala/math/Ordering.gteq:(Ljava/lang/Object;Ljava/lang/Object;)Z
const #57 = Asciz	$greater;
const #58 = Asciz	gt;
const #59 = NameAndType	#58:#49;//  gt:(Ljava/lang/Object;Ljava/lang/Object;)Z
const #60 = InterfaceMethod	#38.#59;	//  scala/math/Ordering.gt:(Ljava/lang/Object;Ljava/lang/Object;)Z
const #61 = Asciz	$less$eq;
const #62 = Asciz	lteq;
const #63 = NameAndType	#62:#49;//  lteq:(Ljava/lang/Object;Ljava/lang/Object;)Z
const #64 = InterfaceMethod	#38.#63;	//  scala/math/Ordering.lteq:(Ljava/lang/Object;Ljava/lang/Object;)Z
const #65 = Asciz	$less;
const #66 = Asciz	lt;
const #67 = NameAndType	#66:#49;//  lt:(Ljava/lang/Object;Ljava/lang/Object;)Z
const #68 = InterfaceMethod	#38.#67;	//  scala/math/Ordering.lt:(Ljava/lang/Object;Ljava/lang/Object;)Z
const #69 = Asciz	Scala;
const #70 = Asciz	InnerClasses;
const #71 = Asciz	Ops;
const #72 = Asciz	scala/ScalaObject;
const #73 = class	#72;	//  scala/ScalaObject

{
public final scala.math.Ordering $outer;

public scala.math.Ordering$Ops(scala.math.Ordering, java.lang.Object);
  Code:
   Stack=2, Locals=3, Args_size=3
   0:	aload_0
   1:	aload_2
   2:	putfield	#16; //Field lhs:Ljava/lang/Object;
   5:	aload_1
   6:	ifnonnull	17
   9:	new	#18; //class java/lang/NullPointerException
   12:	dup
   13:	invokespecial	#21; //Method java/lang/NullPointerException."<init>":()V
   16:	athrow
   17:	aload_0
   18:	aload_1
   19:	putfield	#23; //Field $outer:Lscala/math/Ordering;
   22:	aload_0
   23:	invokespecial	#26; //Method java/lang/Object."<init>":()V
   26:	return
  LineNumberTable: 
   line 100: 0

  LocalVariableTable: 
   Start  Length  Slot  Name   Signature
   0      27      0    this       Lscala/math/Ordering$Ops;
   0      27      1    $outer       Lscala/math/Ordering;
   0      27      2    lhs       Ljava/lang/Object;

  Signature: length = 0x2
   00 1E 

public scala.math.Ordering scala$math$Ordering$Ops$$$outer();
  Code:
   Stack=1, Locals=1, Args_size=1
   0:	aload_0
   1:	getfield	#23; //Field $outer:Lscala/math/Ordering;
   4:	areturn
  LineNumberTable: 
   line 100: 0


public java.lang.Object min(java.lang.Object);
  Code:
   Stack=3, Locals=2, Args_size=2
   0:	aload_0
   1:	invokevirtual	#36; //Method scala$math$Ordering$Ops$$$outer:()Lscala/math/Ordering;
   4:	aload_0
   5:	getfield	#16; //Field lhs:Ljava/lang/Object;
   8:	aload_1
   9:	invokeinterface	#41,  3; //InterfaceMethod scala/math/Ordering.min:(Ljava/lang/Object;Ljava/lang/Object;)Ljava/lang/Object;
   14:	areturn
  LineNumberTable: 
   line 107: 0

  LocalVariableTable: 
   Start  Length  Slot  Name   Signature
   0      15      0    this       Lscala/math/Ordering$Ops;
   0      15      1    rhs       Ljava/lang/Object;

  Signature: length = 0x2
   00 2B 

public java.lang.Object max(java.lang.Object);
  Code:
   Stack=3, Locals=2, Args_size=2
   0:	aload_0
   1:	invokevirtual	#36; //Method scala$math$Ordering$Ops$$$outer:()Lscala/math/Ordering;
   4:	aload_0
   5:	getfield	#16; //Field lhs:Ljava/lang/Object;
   8:	aload_1
   9:	invokeinterface	#46,  3; //InterfaceMethod scala/math/Ordering.max:(Ljava/lang/Object;Ljava/lang/Object;)Ljava/lang/Object;
   14:	areturn
  LineNumberTable: 
   line 106: 0

  LocalVariableTable: 
   Start  Length  Slot  Name   Signature
   0      15      0    this       Lscala/math/Ordering$Ops;
   0      15      1    rhs       Ljava/lang/Object;

  Signature: length = 0x2
   00 2B 

public boolean equiv(java.lang.Object);
  Code:
   Stack=3, Locals=2, Args_size=2
   0:	aload_0
   1:	invokevirtual	#36; //Method scala$math$Ordering$Ops$$$outer:()Lscala/math/Ordering;
   4:	aload_0
   5:	getfield	#16; //Field lhs:Ljava/lang/Object;
   8:	aload_1
   9:	invokeinterface	#51,  3; //InterfaceMethod scala/math/Ordering.equiv:(Ljava/lang/Object;Ljava/lang/Object;)Z
   14:	ireturn
  LineNumberTable: 
   line 105: 0

  LocalVariableTable: 
   Start  Length  Slot  Name   Signature
   0      15      0    this       Lscala/math/Ordering$Ops;
   0      15      1    rhs       Ljava/lang/Object;

  Signature: length = 0x2
   00 34 

public boolean $greater$eq(java.lang.Object);
  Code:
   Stack=3, Locals=2, Args_size=2
   0:	aload_0
   1:	invokevirtual	#36; //Method scala$math$Ordering$Ops$$$outer:()Lscala/math/Ordering;
   4:	aload_0
   5:	getfield	#16; //Field lhs:Ljava/lang/Object;
   8:	aload_1
   9:	invokeinterface	#56,  3; //InterfaceMethod scala/math/Ordering.gteq:(Ljava/lang/Object;Ljava/lang/Object;)Z
   14:	ireturn
  LineNumberTable: 
   line 104: 0

  LocalVariableTable: 
   Start  Length  Slot  Name   Signature
   0      15      0    this       Lscala/math/Ordering$Ops;
   0      15      1    rhs       Ljava/lang/Object;

  Signature: length = 0x2
   00 34 

public boolean $greater(java.lang.Object);
  Code:
   Stack=3, Locals=2, Args_size=2
   0:	aload_0
   1:	invokevirtual	#36; //Method scala$math$Ordering$Ops$$$outer:()Lscala/math/Ordering;
   4:	aload_0
   5:	getfield	#16; //Field lhs:Ljava/lang/Object;
   8:	aload_1
   9:	invokeinterface	#60,  3; //InterfaceMethod scala/math/Ordering.gt:(Ljava/lang/Object;Ljava/lang/Object;)Z
   14:	ireturn
  LineNumberTable: 
   line 103: 0

  LocalVariableTable: 
   Start  Length  Slot  Name   Signature
   0      15      0    this       Lscala/math/Ordering$Ops;
   0      15      1    rhs       Ljava/lang/Object;

  Signature: length = 0x2
   00 34 

public boolean $less$eq(java.lang.Object);
  Code:
   Stack=3, Locals=2, Args_size=2
   0:	aload_0
   1:	invokevirtual	#36; //Method scala$math$Ordering$Ops$$$outer:()Lscala/math/Ordering;
   4:	aload_0
   5:	getfield	#16; //Field lhs:Ljava/lang/Object;
   8:	aload_1
   9:	invokeinterface	#64,  3; //InterfaceMethod scala/math/Ordering.lteq:(Ljava/lang/Object;Ljava/lang/Object;)Z
   14:	ireturn
  LineNumberTable: 
   line 102: 0

  LocalVariableTable: 
   Start  Length  Slot  Name   Signature
   0      15      0    this       Lscala/math/Ordering$Ops;
   0      15      1    rhs       Ljava/lang/Object;

  Signature: length = 0x2
   00 34 

public boolean $less(java.lang.Object);
  Code:
   Stack=3, Locals=2, Args_size=2
   0:	aload_0
   1:	invokevirtual	#36; //Method scala$math$Ordering$Ops$$$outer:()Lscala/math/Ordering;
   4:	aload_0
   5:	getfield	#16; //Field lhs:Ljava/lang/Object;
   8:	aload_1
   9:	invokeinterface	#68,  3; //InterfaceMethod scala/math/Ordering.lt:(Ljava/lang/Object;Ljava/lang/Object;)Z
   14:	ireturn
  LineNumberTable: 
   line 101: 0

  LocalVariableTable: 
   Start  Length  Slot  Name   Signature
   0      15      0    this       Lscala/math/Ordering$Ops;
   0      15      1    rhs       Ljava/lang/Object;

  Signature: length = 0x2
   00 34 

}

