Compiled from "Ordering.scala"
public final class scala.math.Ordering$$anon$4 extends java.lang.Object implements scala.math.Ordering
  SourceFile: "Ordering.scala"
  Signature: length = 0x2
   00 63 
  Scala: length = 0x
   
  InnerClass: 
   public Ops=class scala/math/Ordering$Ops of class scala/math/Ordering
   public final $anon$4=class scala/math/Ordering$$anon$4 of class scala/math/Ordering
  minor version: 0
  major version: 49
  Constant pool:
Asciz	SourceFile;
Asciz	Ordering.scala;
Asciz	cmp$1;
Asciz	Lscala/Function2;;
Asciz	tryCompare;
Asciz	(Ljava/lang/Object;Ljava/lang/Object;)Lscala/Some;;
Asciz	Code;
Asciz	LineNumberTable;
Asciz	scala/math/Ordering$class;
class	scala/math/Ordering$class
Asciz	(Lscala/math/Ordering;Ljava/lang/Object;Ljava/lang/Object;)Lscala/Some;;
NameAndType	tryCompare:(Lscala/math/Ordering;Ljava/lang/Object;Ljava/lang/Object;)Lscala/Some;
Method	scala/math/Ordering$class.tryCompare:(Lscala/math/Ordering;Ljava/lang/Object;Ljava/lang/Object;)Lscala/Some;
Asciz	this;
Asciz	Lscala/math/Ordering$$anon$4;;
Asciz	x;
Asciz	Ljava/lang/Object;;
Asciz	y;
Asciz	LocalVariableTable;
Asciz	equiv;
Asciz	(Ljava/lang/Object;Ljava/lang/Object;)Z;
Asciz	(Lscala/math/Ordering;Ljava/lang/Object;Ljava/lang/Object;)Z;
NameAndType	equiv:(Lscala/math/Ordering;Ljava/lang/Object;Ljava/lang/Object;)Z
Method	scala/math/Ordering$class.equiv:(Lscala/math/Ordering;Ljava/lang/Object;Ljava/lang/Object;)Z
Asciz	max;
Asciz	(Ljava/lang/Object;Ljava/lang/Object;)Ljava/lang/Object;;
Asciz	(Lscala/math/Ordering;Ljava/lang/Object;Ljava/lang/Object;)Ljava/lang/Object;;
NameAndType	max:(Lscala/math/Ordering;Ljava/lang/Object;Ljava/lang/Object;)Ljava/lang/Object;
Method	scala/math/Ordering$class.max:(Lscala/math/Ordering;Ljava/lang/Object;Ljava/lang/Object;)Ljava/lang/Object;
Asciz	min;
NameAndType	min:(Lscala/math/Ordering;Ljava/lang/Object;Ljava/lang/Object;)Ljava/lang/Object;
Method	scala/math/Ordering$class.min:(Lscala/math/Ordering;Ljava/lang/Object;Ljava/lang/Object;)Ljava/lang/Object;
Asciz	reverse;
Asciz	()Lscala/math/Ordering;;
Asciz	(Lscala/math/Ordering;)Lscala/math/Ordering;;
NameAndType	reverse:(Lscala/math/Ordering;)Lscala/math/Ordering;
Method	scala/math/Ordering$class.reverse:(Lscala/math/Ordering;)Lscala/math/Ordering;
Asciz	on;
Asciz	(Lscala/Function1;)Lscala/math/Ordering;;
Asciz	(Lscala/math/Ordering;Lscala/Function1;)Lscala/math/Ordering;;
NameAndType	on:(Lscala/math/Ordering;Lscala/Function1;)Lscala/math/Ordering;
Method	scala/math/Ordering$class.on:(Lscala/math/Ordering;Lscala/Function1;)Lscala/math/Ordering;
Asciz	f;
Asciz	Lscala/Function1;;
Asciz	mkOrderingOps;
Asciz	(Ljava/lang/Object;)Lscala/math/Ordering$Ops;;
Asciz	(Lscala/math/Ordering;Ljava/lang/Object;)Lscala/math/Ordering$Ops;;
NameAndType	mkOrderingOps:(Lscala/math/Ordering;Ljava/lang/Object;)Lscala/math/Ordering$Ops;
Method	scala/math/Ordering$class.mkOrderingOps:(Lscala/math/Ordering;Ljava/lang/Object;)Lscala/math/Ordering$Ops;
Asciz	lhs;
Asciz	Signature;
Asciz	compare;
Asciz	(Ljava/lang/Object;Ljava/lang/Object;)I;
Asciz	scala/math/Ordering$$anon$4;
class	scala/math/Ordering$$anon$4
NameAndType	cmp$1:Lscala/Function2;
Field	scala/math/Ordering$$anon$4.cmp$1:Lscala/Function2;
Asciz	scala/Function2;
class	scala/Function2
Asciz	apply;
NameAndType	apply:(Ljava/lang/Object;Ljava/lang/Object;)Ljava/lang/Object;
InterfaceMethod	scala/Function2.apply:(Ljava/lang/Object;Ljava/lang/Object;)Ljava/lang/Object;
Asciz	scala/runtime/BoxesRunTime;
class	scala/runtime/BoxesRunTime
Asciz	unboxToBoolean;
Asciz	(Ljava/lang/Object;)Z;
NameAndType	unboxToBoolean:(Ljava/lang/Object;)Z
Method	scala/runtime/BoxesRunTime.unboxToBoolean:(Ljava/lang/Object;)Z
Asciz	(TT;TT;)I;
Asciz	lt;
Asciz	(TT;TT;)Z;
Asciz	gt;
Asciz	gteq;
Asciz	lteq;
Asciz	()Lscala/math/PartialOrdering;;
Asciz	scala/math/Ordering;
class	scala/math/Ordering
NameAndType	reverse:()Lscala/math/Ordering;
InterfaceMethod	scala/math/Ordering.reverse:()Lscala/math/Ordering;
Asciz	(Ljava/lang/Object;Ljava/lang/Object;)Lscala/Option;;
NameAndType	tryCompare:(Ljava/lang/Object;Ljava/lang/Object;)Lscala/Some;
InterfaceMethod	scala/math/Ordering.tryCompare:(Ljava/lang/Object;Ljava/lang/Object;)Lscala/Some;
Asciz	<init>;
Asciz	(Lscala/Function2;)V;
Asciz	java/lang/Object;
class	java/lang/Object
Asciz	()V;
NameAndType	"<init>":()V
Method	java/lang/Object."<init>":()V
Asciz	scala/math/PartialOrdering$class;
class	scala/math/PartialOrdering$class
Asciz	$init$;
Asciz	(Lscala/math/PartialOrdering;)V;
NameAndType	$init$:(Lscala/math/PartialOrdering;)V
Method	scala/math/PartialOrdering$class.$init$:(Lscala/math/PartialOrdering;)V
Asciz	(Lscala/math/Ordering;)V;
NameAndType	$init$:(Lscala/math/Ordering;)V
Method	scala/math/Ordering$class.$init$:(Lscala/math/Ordering;)V
Asciz	Ljava/lang/Object;Lscala/math/Ordering<TT;>;;
Asciz	Scala;
Asciz	InnerClasses;
Asciz	scala/math/Ordering$Ops;
class	scala/math/Ordering$Ops
Asciz	Ops;
Asciz	$anon$4;

{
private final scala.Function2 cmp$1;
  Signature: Lscala/Function2;

public scala.Some tryCompare(java.lang.Object, java.lang.Object);
  Signature: (Ljava/lang/Object;Ljava/lang/Object;)Lscala/Some;
  Code:
   Stack=3, Locals=3, Args_size=3
	aload_0
	aload_1
	aload_2
	invokestatic	Method scala/math/Ordering$class.tryCompare:(Lscala/math/Ordering;Ljava/lang/Object;Ljava/lang/Object;)Lscala/Some;
	areturn
  Labels:
  LocalVariableTable: 
   Start  Length  Slot  Name   Signature
   0      7      0    this       Lscala/math/Ordering$$anon$4;
   0      7      1    x       Ljava/lang/Object;
   0      7      2    y       Ljava/lang/Object;


public boolean equiv(java.lang.Object, java.lang.Object);
  Signature: (Ljava/lang/Object;Ljava/lang/Object;)Z
  Code:
   Stack=3, Locals=3, Args_size=3
	aload_0
	aload_1
	aload_2
	invokestatic	Method scala/math/Ordering$class.equiv:(Lscala/math/Ordering;Ljava/lang/Object;Ljava/lang/Object;)Z
	ireturn
  Labels:
  LocalVariableTable: 
   Start  Length  Slot  Name   Signature
   0      7      0    this       Lscala/math/Ordering$$anon$4;
   0      7      1    x       Ljava/lang/Object;
   0      7      2    y       Ljava/lang/Object;


public java.lang.Object max(java.lang.Object, java.lang.Object);
  Signature: (Ljava/lang/Object;Ljava/lang/Object;)Ljava/lang/Object;
  Code:
   Stack=3, Locals=3, Args_size=3
	aload_0
	aload_1
	aload_2
	invokestatic	Method scala/math/Ordering$class.max:(Lscala/math/Ordering;Ljava/lang/Object;Ljava/lang/Object;)Ljava/lang/Object;
	areturn
  Labels:
  LocalVariableTable: 
   Start  Length  Slot  Name   Signature
   0      7      0    this       Lscala/math/Ordering$$anon$4;
   0      7      1    x       Ljava/lang/Object;
   0      7      2    y       Ljava/lang/Object;


public java.lang.Object min(java.lang.Object, java.lang.Object);
  Signature: (Ljava/lang/Object;Ljava/lang/Object;)Ljava/lang/Object;
  Code:
   Stack=3, Locals=3, Args_size=3
	aload_0
	aload_1
	aload_2
	invokestatic	Method scala/math/Ordering$class.min:(Lscala/math/Ordering;Ljava/lang/Object;Ljava/lang/Object;)Ljava/lang/Object;
	areturn
  Labels:
  LocalVariableTable: 
   Start  Length  Slot  Name   Signature
   0      7      0    this       Lscala/math/Ordering$$anon$4;
   0      7      1    x       Ljava/lang/Object;
   0      7      2    y       Ljava/lang/Object;


public scala.math.Ordering reverse();
  Signature: ()Lscala/math/Ordering;
  Code:
   Stack=1, Locals=1, Args_size=1
	aload_0
	invokestatic	Method scala/math/Ordering$class.reverse:(Lscala/math/Ordering;)Lscala/math/Ordering;
	areturn
  Labels:

public scala.math.Ordering on(scala.Function1);
  Signature: (Lscala/Function1;)Lscala/math/Ordering;
  Code:
   Stack=2, Locals=2, Args_size=2
	aload_0
	aload_1
	invokestatic	Method scala/math/Ordering$class.on:(Lscala/math/Ordering;Lscala/Function1;)Lscala/math/Ordering;
	areturn
  Labels:
  LocalVariableTable: 
   Start  Length  Slot  Name   Signature
   0      6      0    this       Lscala/math/Ordering$$anon$4;
   0      6      1    f       Lscala/Function1;


public scala.math.Ordering$Ops mkOrderingOps(java.lang.Object);
  Signature: (Ljava/lang/Object;)Lscala/math/Ordering$Ops;
  Code:
   Stack=2, Locals=2, Args_size=2
	aload_0
	aload_1
	invokestatic	Method scala/math/Ordering$class.mkOrderingOps:(Lscala/math/Ordering;Ljava/lang/Object;)Lscala/math/Ordering$Ops;
	areturn
  Labels:
  LocalVariableTable: 
   Start  Length  Slot  Name   Signature
   0      6      0    this       Lscala/math/Ordering$$anon$4;
   0      6      1    lhs       Ljava/lang/Object;

  Signature: length = 0x2
   00 2E 

public int compare(java.lang.Object, java.lang.Object);
  Signature: (Ljava/lang/Object;Ljava/lang/Object;)I
  Code:
   Stack=3, Locals=3, Args_size=3
	aload_0
	getfield	Field cmp$1:Lscala/Function2;
	aload_1
	aload_2
	invokeinterface	InterfaceMethod scala/Function2.apply:(Ljava/lang/Object;Ljava/lang/Object;)Ljava/lang/Object;
	invokestatic	Method scala/runtime/BoxesRunTime.unboxToBoolean:(Ljava/lang/Object;)Z
	ifeq	l1 // aload_0
	iconst_m1
	goto	l2 // ireturn
l1	aload_0
	getfield	Field cmp$1:Lscala/Function2;
	aload_2
	aload_1
	invokeinterface	InterfaceMethod scala/Function2.apply:(Ljava/lang/Object;Ljava/lang/Object;)Ljava/lang/Object;
	invokestatic	Method scala/runtime/BoxesRunTime.unboxToBoolean:(Ljava/lang/Object;)Z
	ifeq	l3 // iconst_0
	iconst_1
	goto	l2 // ireturn
l3	iconst_0
l2	ireturn
  Labels:
   	l1 = 21 // aload_0
   	l3 = 42 // iconst_0
   	l2 = 43 // ireturn
  LocalVariableTable: 
   Start  Length  Slot  Name   Signature
   0      44      0    this       Lscala/math/Ordering$$anon$4;
   0      44      1    x       Ljava/lang/Object;
   0      44      2    y       Ljava/lang/Object;

  Signature: length = 0x2
   00 45 

public boolean lt(java.lang.Object, java.lang.Object);
  Signature: (Ljava/lang/Object;Ljava/lang/Object;)Z
  Code:
   Stack=3, Locals=3, Args_size=3
	aload_0
	getfield	Field cmp$1:Lscala/Function2;
	aload_1
	aload_2
	invokeinterface	InterfaceMethod scala/Function2.apply:(Ljava/lang/Object;Ljava/lang/Object;)Ljava/lang/Object;
	invokestatic	Method scala/runtime/BoxesRunTime.unboxToBoolean:(Ljava/lang/Object;)Z
	ireturn
  Labels:
  LocalVariableTable: 
   Start  Length  Slot  Name   Signature
   0      15      0    this       Lscala/math/Ordering$$anon$4;
   0      15      1    x       Ljava/lang/Object;
   0      15      2    y       Ljava/lang/Object;

  Signature: length = 0x2
   00 47 

public boolean gt(java.lang.Object, java.lang.Object);
  Signature: (Ljava/lang/Object;Ljava/lang/Object;)Z
  Code:
   Stack=3, Locals=3, Args_size=3
	aload_0
	getfield	Field cmp$1:Lscala/Function2;
	aload_2
	aload_1
	invokeinterface	InterfaceMethod scala/Function2.apply:(Ljava/lang/Object;Ljava/lang/Object;)Ljava/lang/Object;
	invokestatic	Method scala/runtime/BoxesRunTime.unboxToBoolean:(Ljava/lang/Object;)Z
	ireturn
  Labels:
  LocalVariableTable: 
   Start  Length  Slot  Name   Signature
   0      15      0    this       Lscala/math/Ordering$$anon$4;
   0      15      1    x       Ljava/lang/Object;
   0      15      2    y       Ljava/lang/Object;

  Signature: length = 0x2
   00 47 

public boolean gteq(java.lang.Object, java.lang.Object);
  Signature: (Ljava/lang/Object;Ljava/lang/Object;)Z
  Code:
   Stack=3, Locals=3, Args_size=3
	aload_0
	getfield	Field cmp$1:Lscala/Function2;
	aload_1
	aload_2
	invokeinterface	InterfaceMethod scala/Function2.apply:(Ljava/lang/Object;Ljava/lang/Object;)Ljava/lang/Object;
	invokestatic	Method scala/runtime/BoxesRunTime.unboxToBoolean:(Ljava/lang/Object;)Z
	ifeq	l1 // iconst_1
	iconst_0
	goto	l2 // ireturn
l1	iconst_1
l2	ireturn
  Labels:
   	l1 = 21 // iconst_1
   	l2 = 22 // ireturn
  LocalVariableTable: 
   Start  Length  Slot  Name   Signature
   0      23      0    this       Lscala/math/Ordering$$anon$4;
   0      23      1    x       Ljava/lang/Object;
   0      23      2    y       Ljava/lang/Object;

  Signature: length = 0x2
   00 47 

public boolean lteq(java.lang.Object, java.lang.Object);
  Signature: (Ljava/lang/Object;Ljava/lang/Object;)Z
  Code:
   Stack=3, Locals=3, Args_size=3
	aload_0
	getfield	Field cmp$1:Lscala/Function2;
	aload_2
	aload_1
	invokeinterface	InterfaceMethod scala/Function2.apply:(Ljava/lang/Object;Ljava/lang/Object;)Ljava/lang/Object;
	invokestatic	Method scala/runtime/BoxesRunTime.unboxToBoolean:(Ljava/lang/Object;)Z
	ifeq	l1 // iconst_1
	iconst_0
	goto	l2 // ireturn
l1	iconst_1
l2	ireturn
  Labels:
   	l1 = 21 // iconst_1
   	l2 = 22 // ireturn
  LocalVariableTable: 
   Start  Length  Slot  Name   Signature
   0      23      0    this       Lscala/math/Ordering$$anon$4;
   0      23      1    x       Ljava/lang/Object;
   0      23      2    y       Ljava/lang/Object;

  Signature: length = 0x2
   00 47 

public scala.math.PartialOrdering reverse();
  Signature: ()Lscala/math/PartialOrdering;
  Code:
   Stack=1, Locals=1, Args_size=1
	aload_0
	invokeinterface	InterfaceMethod scala/math/Ordering.reverse:()Lscala/math/Ordering;
	areturn
  Labels:

public scala.Option tryCompare(java.lang.Object, java.lang.Object);
  Signature: (Ljava/lang/Object;Ljava/lang/Object;)Lscala/Option;
  Code:
   Stack=3, Locals=3, Args_size=3
	aload_0
	aload_1
	aload_2
	invokeinterface	InterfaceMethod scala/math/Ordering.tryCompare:(Ljava/lang/Object;Ljava/lang/Object;)Lscala/Some;
	areturn
  Labels:
  LocalVariableTable: 
   Start  Length  Slot  Name   Signature
   0      9      0    this       Lscala/math/Ordering$$anon$4;
   0      9      1    x       Ljava/lang/Object;
   0      9      2    y       Ljava/lang/Object;


public scala.math.Ordering$$anon$4(scala.Function2);
  Signature: (Lscala/Function2;)V
  Code:
   Stack=2, Locals=2, Args_size=2
	aload_0
	aload_1
	putfield	Field cmp$1:Lscala/Function2;
	aload_0
	invokespecial	Method java/lang/Object."<init>":()V
	aload_0
	invokestatic	Method scala/math/PartialOrdering$class.$init$:(Lscala/math/PartialOrdering;)V
	aload_0
	invokestatic	Method scala/math/Ordering$class.$init$:(Lscala/math/Ordering;)V
	return
  Labels:

}

