Compiled from "Ordering.scala"
public final class scala.math.Ordering$$anon$6 extends java.lang.Object implements scala.math.Ordering
  SourceFile: "Ordering.scala"
  Signature: length = 0x2
   00 FFFFFF86 
  Scala: length = 0x
   
  InnerClass: 
   public #139= #138 of #44; //Ops=class scala/math/Ordering$Ops of class scala/math/Ordering
   public final #140= #10 of #44; //$anon$6=class scala/math/Ordering$$anon$6 of class scala/math/Ordering
   public abstract #143= #142 of #44; //BooleanOrdering=class scala/math/Ordering$BooleanOrdering of class scala/math/Ordering
  minor version: 0
  major version: 49
  Constant pool:
const #1 = Asciz	SourceFile;
const #2 = Asciz	Ordering.scala;
const #3 = Asciz	ord$1;
const #4 = Asciz	Lscala/math/Ordering;;
const #5 = Asciz	<init>;
const #6 = Asciz	(Lscala/math/Ordering;)V;
const #7 = Asciz	Code;
const #8 = Asciz	LineNumberTable;
const #9 = Asciz	scala/math/Ordering$$anon$6;
const #10 = class	#9;	//  scala/math/Ordering$$anon$6
const #11 = NameAndType	#3:#4;//  ord$1:Lscala/math/Ordering;
const #12 = Field	#10.#11;	//  scala/math/Ordering$$anon$6.ord$1:Lscala/math/Ordering;
const #13 = Asciz	java/lang/Object;
const #14 = class	#13;	//  java/lang/Object
const #15 = Asciz	()V;
const #16 = NameAndType	#5:#15;//  "<init>":()V
const #17 = Method	#14.#16;	//  java/lang/Object."<init>":()V
const #18 = Asciz	scala/math/PartialOrdering$class;
const #19 = class	#18;	//  scala/math/PartialOrdering$class
const #20 = Asciz	$init$;
const #21 = Asciz	(Lscala/math/PartialOrdering;)V;
const #22 = NameAndType	#20:#21;//  $init$:(Lscala/math/PartialOrdering;)V
const #23 = Method	#19.#22;	//  scala/math/PartialOrdering$class.$init$:(Lscala/math/PartialOrdering;)V
const #24 = Asciz	scala/math/Ordering$class;
const #25 = class	#24;	//  scala/math/Ordering$class
const #26 = NameAndType	#20:#6;//  $init$:(Lscala/math/Ordering;)V
const #27 = Method	#25.#26;	//  scala/math/Ordering$class.$init$:(Lscala/math/Ordering;)V
const #28 = Asciz	compare;
const #29 = Asciz	(Ljava/lang/Object;Ljava/lang/Object;)I;
const #30 = Asciz	scala/collection/Iterable;
const #31 = class	#30;	//  scala/collection/Iterable
const #32 = Asciz	(Lscala/collection/Iterable;Lscala/collection/Iterable;)I;
const #33 = NameAndType	#28:#32;//  compare:(Lscala/collection/Iterable;Lscala/collection/Iterable;)I
const #34 = Method	#10.#33;	//  scala/math/Ordering$$anon$6.compare:(Lscala/collection/Iterable;Lscala/collection/Iterable;)I
const #35 = Asciz	this;
const #36 = Asciz	Lscala/math/Ordering$$anon$6;;
const #37 = Asciz	x;
const #38 = Asciz	Ljava/lang/Object;;
const #39 = Asciz	y;
const #40 = Asciz	LocalVariableTable;
const #41 = Asciz	tryCompare;
const #42 = Asciz	(Ljava/lang/Object;Ljava/lang/Object;)Lscala/Option;;
const #43 = Asciz	scala/math/Ordering;
const #44 = class	#43;	//  scala/math/Ordering
const #45 = Asciz	(Ljava/lang/Object;Ljava/lang/Object;)Lscala/Some;;
const #46 = NameAndType	#41:#45;//  tryCompare:(Ljava/lang/Object;Ljava/lang/Object;)Lscala/Some;
const #47 = InterfaceMethod	#44.#46;	//  scala/math/Ordering.tryCompare:(Ljava/lang/Object;Ljava/lang/Object;)Lscala/Some;
const #48 = Asciz	reverse;
const #49 = Asciz	()Lscala/math/PartialOrdering;;
const #50 = Asciz	()Lscala/math/Ordering;;
const #51 = NameAndType	#48:#50;//  reverse:()Lscala/math/Ordering;
const #52 = InterfaceMethod	#44.#51;	//  scala/math/Ordering.reverse:()Lscala/math/Ordering;
const #53 = Asciz	scala/collection/IterableLike;
const #54 = class	#53;	//  scala/collection/IterableLike
const #55 = Asciz	iterator;
const #56 = Asciz	()Lscala/collection/Iterator;;
const #57 = NameAndType	#55:#56;//  iterator:()Lscala/collection/Iterator;
const #58 = InterfaceMethod	#54.#57;	//  scala/collection/IterableLike.iterator:()Lscala/collection/Iterator;
const #59 = Asciz	scala/collection/Iterator;
const #60 = class	#59;	//  scala/collection/Iterator
const #61 = Asciz	hasNext;
const #62 = Asciz	()Z;
const #63 = NameAndType	#61:#62;//  hasNext:()Z
const #64 = InterfaceMethod	#60.#63;	//  scala/collection/Iterator.hasNext:()Z
const #65 = Asciz	next;
const #66 = Asciz	()Ljava/lang/Object;;
const #67 = NameAndType	#65:#66;//  next:()Ljava/lang/Object;
const #68 = InterfaceMethod	#60.#67;	//  scala/collection/Iterator.next:()Ljava/lang/Object;
const #69 = NameAndType	#28:#29;//  compare:(Ljava/lang/Object;Ljava/lang/Object;)I
const #70 = InterfaceMethod	#44.#69;	//  scala/math/Ordering.compare:(Ljava/lang/Object;Ljava/lang/Object;)I
const #71 = Asciz	scala/math/Ordering$Boolean$;
const #72 = class	#71;	//  scala/math/Ordering$Boolean$
const #73 = Asciz	MODULE$;
const #74 = Asciz	Lscala/math/Ordering$Boolean$;;
const #75 = NameAndType	#73:#74;//  MODULE$:Lscala/math/Ordering$Boolean$;
const #76 = Field	#72.#75;	//  scala/math/Ordering$Boolean$.MODULE$:Lscala/math/Ordering$Boolean$;
const #77 = Asciz	scala/math/Ordering$BooleanOrdering$class;
const #78 = class	#77;	//  scala/math/Ordering$BooleanOrdering$class
const #79 = Asciz	(Lscala/math/Ordering$BooleanOrdering;ZZ)I;
const #80 = NameAndType	#28:#79;//  compare:(Lscala/math/Ordering$BooleanOrdering;ZZ)I
const #81 = Method	#78.#80;	//  scala/math/Ordering$BooleanOrdering$class.compare:(Lscala/math/Ordering$BooleanOrdering;ZZ)I
const #82 = Asciz	Lscala/collection/Iterable;;
const #83 = Asciz	res;
const #84 = Asciz	I;
const #85 = Asciz	xe;
const #86 = Asciz	Lscala/collection/Iterator;;
const #87 = Asciz	ye;
const #88 = Asciz	(Lscala/collection/Iterable<TT;>;Lscala/collection/Iterable<TT;>;)I;
const #89 = Asciz	Signature;
const #90 = Asciz	mkOrderingOps;
const #91 = Asciz	(Ljava/lang/Object;)Lscala/math/Ordering$Ops;;
const #92 = Asciz	(Lscala/math/Ordering;Ljava/lang/Object;)Lscala/math/Ordering$Ops;;
const #93 = NameAndType	#90:#92;//  mkOrderingOps:(Lscala/math/Ordering;Ljava/lang/Object;)Lscala/math/Ordering$Ops;
const #94 = Method	#25.#93;	//  scala/math/Ordering$class.mkOrderingOps:(Lscala/math/Ordering;Ljava/lang/Object;)Lscala/math/Ordering$Ops;
const #95 = Asciz	lhs;
const #96 = Asciz	on;
const #97 = Asciz	(Lscala/Function1;)Lscala/math/Ordering;;
const #98 = Asciz	(Lscala/math/Ordering;Lscala/Function1;)Lscala/math/Ordering;;
const #99 = NameAndType	#96:#98;//  on:(Lscala/math/Ordering;Lscala/Function1;)Lscala/math/Ordering;
const #100 = Method	#25.#99;	//  scala/math/Ordering$class.on:(Lscala/math/Ordering;Lscala/Function1;)Lscala/math/Ordering;
const #101 = Asciz	f;
const #102 = Asciz	Lscala/Function1;;
const #103 = Asciz	(Lscala/math/Ordering;)Lscala/math/Ordering;;
const #104 = NameAndType	#48:#103;//  reverse:(Lscala/math/Ordering;)Lscala/math/Ordering;
const #105 = Method	#25.#104;	//  scala/math/Ordering$class.reverse:(Lscala/math/Ordering;)Lscala/math/Ordering;
const #106 = Asciz	min;
const #107 = Asciz	(Ljava/lang/Object;Ljava/lang/Object;)Ljava/lang/Object;;
const #108 = Asciz	(Lscala/math/Ordering;Ljava/lang/Object;Ljava/lang/Object;)Ljava/lang/Object;;
const #109 = NameAndType	#106:#108;//  min:(Lscala/math/Ordering;Ljava/lang/Object;Ljava/lang/Object;)Ljava/lang/Object;
const #110 = Method	#25.#109;	//  scala/math/Ordering$class.min:(Lscala/math/Ordering;Ljava/lang/Object;Ljava/lang/Object;)Ljava/lang/Object;
const #111 = Asciz	max;
const #112 = NameAndType	#111:#108;//  max:(Lscala/math/Ordering;Ljava/lang/Object;Ljava/lang/Object;)Ljava/lang/Object;
const #113 = Method	#25.#112;	//  scala/math/Ordering$class.max:(Lscala/math/Ordering;Ljava/lang/Object;Ljava/lang/Object;)Ljava/lang/Object;
const #114 = Asciz	equiv;
const #115 = Asciz	(Ljava/lang/Object;Ljava/lang/Object;)Z;
const #116 = Asciz	(Lscala/math/Ordering;Ljava/lang/Object;Ljava/lang/Object;)Z;
const #117 = NameAndType	#114:#116;//  equiv:(Lscala/math/Ordering;Ljava/lang/Object;Ljava/lang/Object;)Z
const #118 = Method	#25.#117;	//  scala/math/Ordering$class.equiv:(Lscala/math/Ordering;Ljava/lang/Object;Ljava/lang/Object;)Z
const #119 = Asciz	gt;
const #120 = NameAndType	#119:#116;//  gt:(Lscala/math/Ordering;Ljava/lang/Object;Ljava/lang/Object;)Z
const #121 = Method	#25.#120;	//  scala/math/Ordering$class.gt:(Lscala/math/Ordering;Ljava/lang/Object;Ljava/lang/Object;)Z
const #122 = Asciz	lt;
const #123 = NameAndType	#122:#116;//  lt:(Lscala/math/Ordering;Ljava/lang/Object;Ljava/lang/Object;)Z
const #124 = Method	#25.#123;	//  scala/math/Ordering$class.lt:(Lscala/math/Ordering;Ljava/lang/Object;Ljava/lang/Object;)Z
const #125 = Asciz	gteq;
const #126 = NameAndType	#125:#116;//  gteq:(Lscala/math/Ordering;Ljava/lang/Object;Ljava/lang/Object;)Z
const #127 = Method	#25.#126;	//  scala/math/Ordering$class.gteq:(Lscala/math/Ordering;Ljava/lang/Object;Ljava/lang/Object;)Z
const #128 = Asciz	lteq;
const #129 = NameAndType	#128:#116;//  lteq:(Lscala/math/Ordering;Ljava/lang/Object;Ljava/lang/Object;)Z
const #130 = Method	#25.#129;	//  scala/math/Ordering$class.lteq:(Lscala/math/Ordering;Ljava/lang/Object;Ljava/lang/Object;)Z
const #131 = Asciz	(Lscala/math/Ordering;Ljava/lang/Object;Ljava/lang/Object;)Lscala/Some;;
const #132 = NameAndType	#41:#131;//  tryCompare:(Lscala/math/Ordering;Ljava/lang/Object;Ljava/lang/Object;)Lscala/Some;
const #133 = Method	#25.#132;	//  scala/math/Ordering$class.tryCompare:(Lscala/math/Ordering;Ljava/lang/Object;Ljava/lang/Object;)Lscala/Some;
const #134 = Asciz	Ljava/lang/Object;Lscala/math/Ordering<Lscala/collection/Iterable<TT;>;>;;
const #135 = Asciz	Scala;
const #136 = Asciz	InnerClasses;
const #137 = Asciz	scala/math/Ordering$Ops;
const #138 = class	#137;	//  scala/math/Ordering$Ops
const #139 = Asciz	Ops;
const #140 = Asciz	$anon$6;
const #141 = Asciz	scala/math/Ordering$BooleanOrdering;
const #142 = class	#141;	//  scala/math/Ordering$BooleanOrdering
const #143 = Asciz	BooleanOrdering;

{
public scala.math.Ordering$$anon$6(scala.math.Ordering);
  Code:
   Stack=2, Locals=2, Args_size=2
   0:	aload_0
   1:	aload_1
   2:	putfield	#12; //Field ord$1:Lscala/math/Ordering;
   5:	aload_0
   6:	invokespecial	#17; //Method java/lang/Object."<init>":()V
   9:	aload_0
   10:	invokestatic	#23; //Method scala/math/PartialOrdering$class.$init$:(Lscala/math/PartialOrdering;)V
   13:	aload_0
   14:	invokestatic	#27; //Method scala/math/Ordering$class.$init$:(Lscala/math/Ordering;)V
   17:	return
  LineNumberTable: 
   line 217: 0


public int compare(java.lang.Object, java.lang.Object);
  Code:
   Stack=3, Locals=3, Args_size=3
   0:	aload_0
   1:	aload_1
   2:	checkcast	#31; //class scala/collection/Iterable
   5:	aload_2
   6:	checkcast	#31; //class scala/collection/Iterable
   9:	invokevirtual	#34; //Method compare:(Lscala/collection/Iterable;Lscala/collection/Iterable;)I
   12:	ireturn
  LineNumberTable: 
   line 217: 0

  LocalVariableTable: 
   Start  Length  Slot  Name   Signature
   0      13      0    this       Lscala/math/Ordering$$anon$6;
   0      13      1    x       Ljava/lang/Object;
   0      13      2    y       Ljava/lang/Object;


public scala.Option tryCompare(java.lang.Object, java.lang.Object);
  Code:
   Stack=3, Locals=3, Args_size=3
   0:	aload_0
   1:	aload_1
   2:	aload_2
   3:	invokeinterface	#47,  3; //InterfaceMethod scala/math/Ordering.tryCompare:(Ljava/lang/Object;Ljava/lang/Object;)Lscala/Some;
   8:	areturn
  LineNumberTable: 
   line 217: 0

  LocalVariableTable: 
   Start  Length  Slot  Name   Signature
   0      9      0    this       Lscala/math/Ordering$$anon$6;
   0      9      1    x       Ljava/lang/Object;
   0      9      2    y       Ljava/lang/Object;


public scala.math.PartialOrdering reverse();
  Code:
   Stack=1, Locals=1, Args_size=1
   0:	aload_0
   1:	invokeinterface	#52,  1; //InterfaceMethod scala/math/Ordering.reverse:()Lscala/math/Ordering;
   6:	areturn
  LineNumberTable: 
   line 217: 0


public int compare(scala.collection.Iterable, scala.collection.Iterable);
  Code:
   Stack=3, Locals=9, Args_size=3
   0:	aload_1
   1:	invokeinterface	#58,  1; //InterfaceMethod scala/collection/IterableLike.iterator:()Lscala/collection/Iterator;
   6:	astore	4
   8:	aload_2
   9:	invokeinterface	#58,  1; //InterfaceMethod scala/collection/IterableLike.iterator:()Lscala/collection/Iterator;
   14:	astore	5
   16:	aload	4
   18:	invokeinterface	#64,  1; //InterfaceMethod scala/collection/Iterator.hasNext:()Z
   23:	ifeq	67
   26:	aload	5
   28:	invokeinterface	#64,  1; //InterfaceMethod scala/collection/Iterator.hasNext:()Z
   33:	ifeq	67
   36:	aload_0
   37:	getfield	#12; //Field ord$1:Lscala/math/Ordering;
   40:	aload	4
   42:	invokeinterface	#68,  1; //InterfaceMethod scala/collection/Iterator.next:()Ljava/lang/Object;
   47:	aload	5
   49:	invokeinterface	#68,  1; //InterfaceMethod scala/collection/Iterator.next:()Ljava/lang/Object;
   54:	invokeinterface	#70,  3; //InterfaceMethod scala/math/Ordering.compare:(Ljava/lang/Object;Ljava/lang/Object;)I
   59:	istore_3
   60:	iload_3
   61:	iconst_0
   62:	if_icmpeq	16
   65:	iload_3
   66:	ireturn
   67:	getstatic	#76; //Field scala/math/Ordering$Boolean$.MODULE$:Lscala/math/Ordering$Boolean$;
   70:	aload	4
   72:	invokeinterface	#64,  1; //InterfaceMethod scala/collection/Iterator.hasNext:()Z
   77:	aload	5
   79:	invokeinterface	#64,  1; //InterfaceMethod scala/collection/Iterator.hasNext:()Z
   84:	istore	8
   86:	istore	7
   88:	astore	6
   90:	aload	6
   92:	iload	7
   94:	iload	8
   96:	invokestatic	#81; //Method scala/math/Ordering$BooleanOrdering$class.compare:(Lscala/math/Ordering$BooleanOrdering;ZZ)I
   99:	ireturn
  LineNumberTable: 
   line 219: 0
   line 220: 8
   line 222: 16
   line 223: 36
   line 224: 60
   line 227: 67

  LocalVariableTable: 
   Start  Length  Slot  Name   Signature
   0      100      0    this       Lscala/math/Ordering$$anon$6;
   0      100      1    x       Lscala/collection/Iterable;
   0      100      2    y       Lscala/collection/Iterable;
   60      7      3    res       I
   8      91      4    xe       Lscala/collection/Iterator;
   16      83      5    ye       Lscala/collection/Iterator;

  Signature: length = 0x2
   00 58 

public scala.math.Ordering$Ops mkOrderingOps(java.lang.Object);
  Code:
   Stack=2, Locals=2, Args_size=2
   0:	aload_0
   1:	aload_1
   2:	invokestatic	#94; //Method scala/math/Ordering$class.mkOrderingOps:(Lscala/math/Ordering;Ljava/lang/Object;)Lscala/math/Ordering$Ops;
   5:	areturn
  LineNumberTable: 
   line 217: 0

  LocalVariableTable: 
   Start  Length  Slot  Name   Signature
   0      6      0    this       Lscala/math/Ordering$$anon$6;
   0      6      1    lhs       Ljava/lang/Object;

  Signature: length = 0x2
   00 5B 

public scala.math.Ordering on(scala.Function1);
  Code:
   Stack=2, Locals=2, Args_size=2
   0:	aload_0
   1:	aload_1
   2:	invokestatic	#100; //Method scala/math/Ordering$class.on:(Lscala/math/Ordering;Lscala/Function1;)Lscala/math/Ordering;
   5:	areturn
  LineNumberTable: 
   line 217: 0

  LocalVariableTable: 
   Start  Length  Slot  Name   Signature
   0      6      0    this       Lscala/math/Ordering$$anon$6;
   0      6      1    f       Lscala/Function1;


public scala.math.Ordering reverse();
  Code:
   Stack=1, Locals=1, Args_size=1
   0:	aload_0
   1:	invokestatic	#105; //Method scala/math/Ordering$class.reverse:(Lscala/math/Ordering;)Lscala/math/Ordering;
   4:	areturn
  LineNumberTable: 
   line 217: 0


public java.lang.Object min(java.lang.Object, java.lang.Object);
  Code:
   Stack=3, Locals=3, Args_size=3
   0:	aload_0
   1:	aload_1
   2:	aload_2
   3:	invokestatic	#110; //Method scala/math/Ordering$class.min:(Lscala/math/Ordering;Ljava/lang/Object;Ljava/lang/Object;)Ljava/lang/Object;
   6:	areturn
  LineNumberTable: 
   line 217: 0

  LocalVariableTable: 
   Start  Length  Slot  Name   Signature
   0      7      0    this       Lscala/math/Ordering$$anon$6;
   0      7      1    x       Ljava/lang/Object;
   0      7      2    y       Ljava/lang/Object;


public java.lang.Object max(java.lang.Object, java.lang.Object);
  Code:
   Stack=3, Locals=3, Args_size=3
   0:	aload_0
   1:	aload_1
   2:	aload_2
   3:	invokestatic	#113; //Method scala/math/Ordering$class.max:(Lscala/math/Ordering;Ljava/lang/Object;Ljava/lang/Object;)Ljava/lang/Object;
   6:	areturn
  LineNumberTable: 
   line 217: 0

  LocalVariableTable: 
   Start  Length  Slot  Name   Signature
   0      7      0    this       Lscala/math/Ordering$$anon$6;
   0      7      1    x       Ljava/lang/Object;
   0      7      2    y       Ljava/lang/Object;


public boolean equiv(java.lang.Object, java.lang.Object);
  Code:
   Stack=3, Locals=3, Args_size=3
   0:	aload_0
   1:	aload_1
   2:	aload_2
   3:	invokestatic	#118; //Method scala/math/Ordering$class.equiv:(Lscala/math/Ordering;Ljava/lang/Object;Ljava/lang/Object;)Z
   6:	ireturn
  LineNumberTable: 
   line 217: 0

  LocalVariableTable: 
   Start  Length  Slot  Name   Signature
   0      7      0    this       Lscala/math/Ordering$$anon$6;
   0      7      1    x       Ljava/lang/Object;
   0      7      2    y       Ljava/lang/Object;


public boolean gt(java.lang.Object, java.lang.Object);
  Code:
   Stack=3, Locals=3, Args_size=3
   0:	aload_0
   1:	aload_1
   2:	aload_2
   3:	invokestatic	#121; //Method scala/math/Ordering$class.gt:(Lscala/math/Ordering;Ljava/lang/Object;Ljava/lang/Object;)Z
   6:	ireturn
  LineNumberTable: 
   line 217: 0

  LocalVariableTable: 
   Start  Length  Slot  Name   Signature
   0      7      0    this       Lscala/math/Ordering$$anon$6;
   0      7      1    x       Ljava/lang/Object;
   0      7      2    y       Ljava/lang/Object;


public boolean lt(java.lang.Object, java.lang.Object);
  Code:
   Stack=3, Locals=3, Args_size=3
   0:	aload_0
   1:	aload_1
   2:	aload_2
   3:	invokestatic	#124; //Method scala/math/Ordering$class.lt:(Lscala/math/Ordering;Ljava/lang/Object;Ljava/lang/Object;)Z
   6:	ireturn
  LineNumberTable: 
   line 217: 0

  LocalVariableTable: 
   Start  Length  Slot  Name   Signature
   0      7      0    this       Lscala/math/Ordering$$anon$6;
   0      7      1    x       Ljava/lang/Object;
   0      7      2    y       Ljava/lang/Object;


public boolean gteq(java.lang.Object, java.lang.Object);
  Code:
   Stack=3, Locals=3, Args_size=3
   0:	aload_0
   1:	aload_1
   2:	aload_2
   3:	invokestatic	#127; //Method scala/math/Ordering$class.gteq:(Lscala/math/Ordering;Ljava/lang/Object;Ljava/lang/Object;)Z
   6:	ireturn
  LineNumberTable: 
   line 217: 0

  LocalVariableTable: 
   Start  Length  Slot  Name   Signature
   0      7      0    this       Lscala/math/Ordering$$anon$6;
   0      7      1    x       Ljava/lang/Object;
   0      7      2    y       Ljava/lang/Object;


public boolean lteq(java.lang.Object, java.lang.Object);
  Code:
   Stack=3, Locals=3, Args_size=3
   0:	aload_0
   1:	aload_1
   2:	aload_2
   3:	invokestatic	#130; //Method scala/math/Ordering$class.lteq:(Lscala/math/Ordering;Ljava/lang/Object;Ljava/lang/Object;)Z
   6:	ireturn
  LineNumberTable: 
   line 217: 0

  LocalVariableTable: 
   Start  Length  Slot  Name   Signature
   0      7      0    this       Lscala/math/Ordering$$anon$6;
   0      7      1    x       Ljava/lang/Object;
   0      7      2    y       Ljava/lang/Object;


public scala.Some tryCompare(java.lang.Object, java.lang.Object);
  Code:
   Stack=3, Locals=3, Args_size=3
   0:	aload_0
   1:	aload_1
   2:	aload_2
   3:	invokestatic	#133; //Method scala/math/Ordering$class.tryCompare:(Lscala/math/Ordering;Ljava/lang/Object;Ljava/lang/Object;)Lscala/Some;
   6:	areturn
  LineNumberTable: 
   line 217: 0

  LocalVariableTable: 
   Start  Length  Slot  Name   Signature
   0      7      0    this       Lscala/math/Ordering$$anon$6;
   0      7      1    x       Ljava/lang/Object;
   0      7      2    y       Ljava/lang/Object;


}

