Compiled from "Ordering.scala"
public abstract class scala.math.Ordering$BigIntOrdering$class extends java.lang.Object
  SourceFile: "Ordering.scala"
  Scala: length = 0x
   
  InnerClass: 
   public abstract #26= #23 of #25; //BigIntOrdering=class scala/math/Ordering$BigIntOrdering of class scala/math/Ordering
  minor version: 0
  major version: 49
  Constant pool:
const #1 = Asciz	SourceFile;
const #2 = Asciz	Ordering.scala;
const #3 = Asciz	$init$;
const #4 = Asciz	(Lscala/math/Ordering$BigIntOrdering;)V;
const #5 = Asciz	Code;
const #6 = Asciz	LineNumberTable;
const #7 = Asciz	$this;
const #8 = Asciz	Lscala/math/Ordering$BigIntOrdering;;
const #9 = Asciz	LocalVariableTable;
const #10 = Asciz	compare;
const #11 = Asciz	(Lscala/math/Ordering$BigIntOrdering;Lscala/math/BigInt;Lscala/math/BigInt;)I;
const #12 = Asciz	scala/math/BigInt;
const #13 = class	#12;	//  scala/math/BigInt
const #14 = Asciz	(Lscala/math/BigInt;)I;
const #15 = NameAndType	#10:#14;//  compare:(Lscala/math/BigInt;)I
const #16 = Method	#13.#15;	//  scala/math/BigInt.compare:(Lscala/math/BigInt;)I
const #17 = Asciz	x;
const #18 = Asciz	Lscala/math/BigInt;;
const #19 = Asciz	y;
const #20 = Asciz	Scala;
const #21 = Asciz	InnerClasses;
const #22 = Asciz	scala/math/Ordering$BigIntOrdering;
const #23 = class	#22;	//  scala/math/Ordering$BigIntOrdering
const #24 = Asciz	scala/math/Ordering;
const #25 = class	#24;	//  scala/math/Ordering
const #26 = Asciz	BigIntOrdering;
const #27 = Asciz	scala/math/Ordering$BigIntOrdering$class;
const #28 = class	#27;	//  scala/math/Ordering$BigIntOrdering$class
const #29 = Asciz	java/lang/Object;
const #30 = class	#29;	//  java/lang/Object

{
public static void $init$(scala.math.Ordering$BigIntOrdering);
  Code:
   Stack=0, Locals=1, Args_size=1
   0:	return
  LineNumberTable: 
   line 191: 0

  LocalVariableTable: 
   Start  Length  Slot  Name   Signature
   0      1      0    $this       Lscala/math/Ordering$BigIntOrdering;


public static int compare(scala.math.Ordering$BigIntOrdering, scala.math.BigInt, scala.math.BigInt);
  Code:
   Stack=2, Locals=3, Args_size=3
   0:	aload_1
   1:	aload_2
   2:	invokevirtual	#16; //Method scala/math/BigInt.compare:(Lscala/math/BigInt;)I
   5:	ireturn
  LineNumberTable: 
   line 192: 0

  LocalVariableTable: 
   Start  Length  Slot  Name   Signature
   0      6      0    $this       Lscala/math/Ordering$BigIntOrdering;
   0      6      1    x       Lscala/math/BigInt;
   0      6      2    y       Lscala/math/BigInt;


}

