Compiled from "package.scala"
public final class scala.math.package extends java.lang.Object
  SourceFile: "package.scala"
  ScalaSig: length = 0x5EF
   05 00 FFFFFF81 66 07 05 01 02 FFFFFF88 02 07 01 07 70 61 63
   6B 61 67 65 0A 02 03 04 01 04 6D 61 74 68 0A 01
   05 01 05 73 63 61 6C 61 03 00 10 02 08 09 0D 01
   02 06 08 0A 02 FFFFFF84 FFFFFF80 FFFFFF80 FFFFFF88 02 0B 02 07 70 61 63
   6B 61 67 65 13 03 09 0C 14 10 02 0D 12 0D 01 0E
   0A 02 0F 10 01 04 6C 61 6E 67 0A 01 11 01 04 6A
   61 76 61 09 02 13 0E 02 06 4F 62 6A 65 63 74 10
   02 15 16 0D 01 04 09 02 17 04 02 0B 53 63 61 6C
   61 4F 62 6A 65 63 74 08 05 19 09 FFFFFF84 00 1A 01 06
   3C 69 6E 69 74 3E 14 01 07 08 07 1C 09 FFFFFFC2 FFFFFF80 FFFFFF84
   00 1D 01 01 45 15 01 1E 10 02 15 1F 09 02 20 04
   02 06 44 6F 75 62 6C 65 08 06 22 09 FFFFFFA0 FFFFFF80 04 1E
   01 02 45 20 08 07 24 09 FFFFFFC2 FFFFFF80 FFFFFF84 00 1D 01 02 50
   69 08 06 26 09 FFFFFFA0 FFFFFF80 04 1E 01 03 50 69 20 08 05
   28 09 FFFFFF84 00 1D 01 06 72 61 6E 64 6F 6D 08 05 2A
   09 FFFFFF84 00 2B 01 03 73 69 6E 14 02 1E 2C 08 05 2D
   29 FFFFFFC0 00 1E 01 01 78 08 05 2F 09 FFFFFF84 00 30 01 03
   63 6F 73 14 02 1E 31 08 05 2D 2E FFFFFFC0 00 1E 08 05
   33 09 FFFFFF84 00 34 01 03 74 61 6E 14 02 1E 35 08 05
   2D 32 FFFFFFC0 00 1E 08 05 37 09 FFFFFF84 00 38 01 04 61 73
   69 6E 14 02 1E 39 08 05 2D 36 FFFFFFC0 00 1E 08 05 3B
   09 FFFFFF84 00 3C 01 04 61 63 6F 73 14 02 1E 3D 08 05
   2D 3A FFFFFFC0 00 1E 08 05 3F 09 FFFFFF84 00 40 01 04 61 74
   61 6E 14 02 1E 41 08 05 2D 3E FFFFFFC0 00 1E 08 05 43
   09 FFFFFF84 00 44 01 09 74 6F 52 61 64 69 61 6E 73 14
   02 1E 45 08 05 2D 42 FFFFFFC0 00 1E 08 05 47 09 FFFFFF84 00
   48 01 09 74 6F 44 65 67 72 65 65 73 14 02 1E 49
   08 05 2D 46 FFFFFFC0 00 1E 08 05 4B 09 FFFFFF84 00 4C 01 03
   65 78 70 14 02 1E 4D 08 05 2D 4A FFFFFFC0 00 1E 08 05
   4F 09 FFFFFF84 00 50 01 03 6C 6F 67 14 02 1E 51 08 05
   2D 4E FFFFFFC0 00 1E 08 05 53 09 FFFFFF84 00 54 01 04 73 71
   72 74 14 02 1E 55 08 05 2D 52 FFFFFFC0 00 1E 08 05 57
   09 FFFFFF84 00 58 01 0D 49 45 45 45 72 65 6D 61 69 6E
   64 65 72 14 03 1E 59 5A 08 05 2D 56 FFFFFFC0 00 1E 08
   05 5B 56 FFFFFFC0 00 1E 01 01 79 08 05 5D 09 FFFFFF84 00 5E
   01 04 63 65 69 6C 14 02 1E 5F 08 05 2D 5C FFFFFFC0 00
   1E 08 05 61 09 FFFFFF84 00 62 01 05 66 6C 6F 6F 72 14
   02 1E 63 08 05 2D 60 FFFFFFC0 00 1E 08 05 65 09 FFFFFF84 00
   66 01 04 72 69 6E 74 14 02 1E 67 08 05 2D 64 FFFFFFC0
   00 1E 08 05 69 09 FFFFFF84 00 6A 01 05 61 74 61 6E 32
   14 03 1E 6B 6C 08 05 5B 68 FFFFFFC0 00 1E 08 05 2D 68
   FFFFFFC0 00 1E 08 05 6E 09 FFFFFF84 00 6F 01 03 70 6F 77 14
   03 1E 70 71 08 05 2D 6D FFFFFFC0 00 1E 08 05 5B 6D FFFFFFC0
   00 1E 08 05 73 09 FFFFFF84 00 74 01 05 72 6F 75 6E 64
   14 02 75 78 10 02 15 76 09 02 77 04 02 03 49 6E
   74 08 05 2D 72 FFFFFFC0 00 79 10 02 15 7A 09 02 7B 04
   02 05 46 6C 6F 61 74 08 05 73 09 FFFFFF84 00 7D 14 03
   7E FFFFFF81 01 10 02 15 7F 09 03 FFFFFF81 00 04 02 04 4C 6F
   6E 67 08 05 2D 7C FFFFFFC0 00 1E 08 07 FFFFFF81 03 09 FFFFFF84 00
   FFFFFF81 04 01 03 61 62 73 14 03 75 FFFFFF81 05 08 06 2D FFFFFF81
   02 FFFFFFC0 00 75 08 07 FFFFFF81 03 09 FFFFFF84 00 FFFFFF81 07 14 03 7E
   FFFFFF81 08 08 06 2D FFFFFF81 06 FFFFFFC0 00 7E 08 07 FFFFFF81 03 09 FFFFFF84
   00 FFFFFF81 0A 14 03 79 FFFFFF81 0B 08 06 2D FFFFFF81 09 FFFFFFC0 00 79
   08 07 FFFFFF81 03 09 FFFFFF84 00 FFFFFF81 0D 14 03 1E FFFFFF81 0E 08 06
   2D FFFFFF81 0C FFFFFFC0 00 1E 08 07 FFFFFF81 10 09 FFFFFF84 00 FFFFFF81 11 01
   03 6D 61 78 14 05 75 FFFFFF81 12 FFFFFF81 13 08 06 2D FFFFFF81 0F
   FFFFFFC0 00 75 08 06 5B FFFFFF81 0F FFFFFFC0 00 75 08 07 FFFFFF81 10 09
   FFFFFF84 00 FFFFFF81 15 14 05 7E FFFFFF81 16 FFFFFF81 17 08 06 2D FFFFFF81 14
   FFFFFFC0 00 7E 08 06 5B FFFFFF81 14 FFFFFFC0 00 7E 08 07 FFFFFF81 10 09
   FFFFFF84 00 FFFFFF81 19 14 05 79 FFFFFF81 1A FFFFFF81 1B 08 06 2D FFFFFF81 18
   FFFFFFC0 00 79 08 06 5B FFFFFF81 18 FFFFFFC0 00 79 08 07 FFFFFF81 10 09
   FFFFFF84 00 FFFFFF81 1D 14 05 1E FFFFFF81 1E FFFFFF81 1F 08 06 2D FFFFFF81 1C
   FFFFFFC0 00 1E 08 06 5B FFFFFF81 1C FFFFFFC0 00 1E 08 07 FFFFFF81 21 09
   FFFFFF84 00 FFFFFF81 22 01 03 6D 69 6E 14 05 75 FFFFFF81 23 FFFFFF81 24
   08 06 2D FFFFFF81 20 FFFFFFC0 00 75 08 06 5B FFFFFF81 20 FFFFFFC0 00 75
   08 07 FFFFFF81 21 09 FFFFFF84 00 FFFFFF81 26 14 05 7E FFFFFF81 27 FFFFFF81 28
   08 06 2D FFFFFF81 25 FFFFFFC0 00 7E 08 06 5B FFFFFF81 25 FFFFFFC0 00 7E
   08 07 FFFFFF81 21 09 FFFFFF84 00 FFFFFF81 2A 14 05 79 FFFFFF81 2B FFFFFF81 2C
   08 06 2D FFFFFF81 29 FFFFFFC0 00 79 08 06 5B FFFFFF81 29 FFFFFFC0 00 79
   08 07 FFFFFF81 21 09 FFFFFF84 00 FFFFFF81 2E 14 05 1E FFFFFF81 2F FFFFFF81 30
   08 06 2D FFFFFF81 2D FFFFFFC0 00 1E 08 06 5B FFFFFF81 2D FFFFFFC0 00 1E
   08 07 FFFFFF81 32 09 FFFFFF84 00 FFFFFF81 33 01 06 73 69 67 6E 75
   6D 14 03 1E FFFFFF81 34 08 06 2D FFFFFF81 31 FFFFFFC0 00 1E 08 07
   FFFFFF81 32 09 FFFFFF84 00 FFFFFF81 36 14 03 79 FFFFFF81 37 08 06 2D FFFFFF81
   35 FFFFFFC0 00 79 08 07 FFFFFF81 32 09 FFFFFF84 00 FFFFFF81 39 14 03 7E
   FFFFFF81 3A 08 06 2D FFFFFF81 38 FFFFFFC0 00 7E 08 07 FFFFFF81 32 09 FFFFFF84
   00 FFFFFF81 3C 14 03 75 FFFFFF81 3D 08 06 2D FFFFFF81 3B FFFFFFC0 00 75
   08 07 FFFFFF81 3F 09 FFFFFF84 00 FFFFFF81 40 01 05 6C 6F 67 31 30
   14 03 1E FFFFFF81 41 08 06 2D FFFFFF81 3E FFFFFFC0 00 1E 08 07 FFFFFF81
   43 09 FFFFFF84 00 FFFFFF81 44 01 04 63 62 72 74 14 03 1E FFFFFF81
   45 08 06 2D FFFFFF81 42 FFFFFFC0 00 1E 08 07 FFFFFF81 47 09 FFFFFF84 00
   FFFFFF81 48 01 03 75 6C 70 14 03 1E FFFFFF81 49 08 06 2D FFFFFF81
   46 FFFFFFC0 00 1E 08 07 FFFFFF81 47 09 FFFFFF84 00 FFFFFF81 4B 14 03 79
   FFFFFF81 4C 08 06 2D FFFFFF81 4A FFFFFFC0 00 79 08 07 FFFFFF81 4E 09 FFFFFF84
   00 FFFFFF81 4F 01 04 73 69 6E 68 14 03 1E FFFFFF81 50 08 06
   2D FFFFFF81 4D FFFFFFC0 00 1E 08 07 FFFFFF81 52 09 FFFFFF84 00 FFFFFF81 53 01
   04 63 6F 73 68 14 03 1E FFFFFF81 54 08 06 2D FFFFFF81 51 FFFFFFC0
   00 1E 08 07 FFFFFF81 56 09 FFFFFF84 00 FFFFFF81 57 01 04 74 61 6E
   68 14 03 1E FFFFFF81 58 08 06 2D FFFFFF81 55 FFFFFFC0 00 1E 08 07
   FFFFFF81 5A 09 FFFFFF84 00 FFFFFF81 5B 01 05 68 79 70 6F 74 14 05
   1E FFFFFF81 5C FFFFFF81 5D 08 06 2D FFFFFF81 59 FFFFFFC0 00 1E 08 06 5B
   FFFFFF81 59 FFFFFFC0 00 1E 08 07 FFFFFF81 5F 09 FFFFFF84 00 FFFFFF81 60 01 05
   65 78 70 6D 31 14 03 1E FFFFFF81 61 08 06 2D FFFFFF81 5E FFFFFFC0
   00 1E 08 07 FFFFFF81 63 09 FFFFFF84 00 FFFFFF81 64 01 05 6C 6F 67
   31 70 14 03 1E FFFFFF81 65 08 06 2D FFFFFF81 62 FFFFFFC0 00 1E 
  minor version: 0
  major version: 49
  Constant pool:
Asciz	SourceFile;
Asciz	package.scala;
Asciz	log1p;
Asciz	(D)D;
Asciz	Code;
Asciz	scala/math/package$;
class	scala/math/package$
Asciz	MODULE$;
Asciz	Lscala/math/package$;;
NameAndType	MODULE$:Lscala/math/package$;
Field	scala/math/package$.MODULE$:Lscala/math/package$;
NameAndType	log1p:(D)D
Method	scala/math/package$.log1p:(D)D
Asciz	expm1;
NameAndType	expm1:(D)D
Method	scala/math/package$.expm1:(D)D
Asciz	hypot;
Asciz	(DD)D;
NameAndType	hypot:(DD)D
Method	scala/math/package$.hypot:(DD)D
Asciz	tanh;
NameAndType	tanh:(D)D
Method	scala/math/package$.tanh:(D)D
Asciz	cosh;
NameAndType	cosh:(D)D
Method	scala/math/package$.cosh:(D)D
Asciz	sinh;
NameAndType	sinh:(D)D
Method	scala/math/package$.sinh:(D)D
Asciz	ulp;
Asciz	(F)F;
NameAndType	ulp:(F)F
Method	scala/math/package$.ulp:(F)F
NameAndType	ulp:(D)D
Method	scala/math/package$.ulp:(D)D
Asciz	cbrt;
NameAndType	cbrt:(D)D
Method	scala/math/package$.cbrt:(D)D
Asciz	log10;
NameAndType	log10:(D)D
Method	scala/math/package$.log10:(D)D
Asciz	signum;
Asciz	(I)I;
NameAndType	signum:(I)I
Method	scala/math/package$.signum:(I)I
Asciz	(J)J;
NameAndType	signum:(J)J
Method	scala/math/package$.signum:(J)J
NameAndType	signum:(F)F
Method	scala/math/package$.signum:(F)F
NameAndType	signum:(D)D
Method	scala/math/package$.signum:(D)D
Asciz	min;
NameAndType	min:(DD)D
Method	scala/math/package$.min:(DD)D
Asciz	(FF)F;
NameAndType	min:(FF)F
Method	scala/math/package$.min:(FF)F
Asciz	(JJ)J;
NameAndType	min:(JJ)J
Method	scala/math/package$.min:(JJ)J
Asciz	(II)I;
NameAndType	min:(II)I
Method	scala/math/package$.min:(II)I
Asciz	max;
NameAndType	max:(DD)D
Method	scala/math/package$.max:(DD)D
NameAndType	max:(FF)F
Method	scala/math/package$.max:(FF)F
NameAndType	max:(JJ)J
Method	scala/math/package$.max:(JJ)J
NameAndType	max:(II)I
Method	scala/math/package$.max:(II)I
Asciz	abs;
NameAndType	abs:(D)D
Method	scala/math/package$.abs:(D)D
NameAndType	abs:(F)F
Method	scala/math/package$.abs:(F)F
NameAndType	abs:(J)J
Method	scala/math/package$.abs:(J)J
NameAndType	abs:(I)I
Method	scala/math/package$.abs:(I)I
Asciz	round;
Asciz	(D)J;
NameAndType	round:(D)J
Method	scala/math/package$.round:(D)J
Asciz	(F)I;
NameAndType	round:(F)I
Method	scala/math/package$.round:(F)I
Asciz	pow;
NameAndType	pow:(DD)D
Method	scala/math/package$.pow:(DD)D
Asciz	atan2;
NameAndType	atan2:(DD)D
Method	scala/math/package$.atan2:(DD)D
Asciz	rint;
NameAndType	rint:(D)D
Method	scala/math/package$.rint:(D)D
Asciz	floor;
NameAndType	floor:(D)D
Method	scala/math/package$.floor:(D)D
Asciz	ceil;
NameAndType	ceil:(D)D
Method	scala/math/package$.ceil:(D)D
Asciz	IEEEremainder;
NameAndType	IEEEremainder:(DD)D
Method	scala/math/package$.IEEEremainder:(DD)D
Asciz	sqrt;
NameAndType	sqrt:(D)D
Method	scala/math/package$.sqrt:(D)D
Asciz	log;
NameAndType	log:(D)D
Method	scala/math/package$.log:(D)D
Asciz	exp;
NameAndType	exp:(D)D
Method	scala/math/package$.exp:(D)D
Asciz	toDegrees;
NameAndType	toDegrees:(D)D
Method	scala/math/package$.toDegrees:(D)D
Asciz	toRadians;
NameAndType	toRadians:(D)D
Method	scala/math/package$.toRadians:(D)D
Asciz	atan;
NameAndType	atan:(D)D
Method	scala/math/package$.atan:(D)D
Asciz	acos;
NameAndType	acos:(D)D
Method	scala/math/package$.acos:(D)D
Asciz	asin;
NameAndType	asin:(D)D
Method	scala/math/package$.asin:(D)D
Asciz	tan;
NameAndType	tan:(D)D
Method	scala/math/package$.tan:(D)D
Asciz	cos;
NameAndType	cos:(D)D
Method	scala/math/package$.cos:(D)D
Asciz	sin;
NameAndType	sin:(D)D
Method	scala/math/package$.sin:(D)D
Asciz	random;
Asciz	()D;
NameAndType	random:()D
Method	scala/math/package$.random:()D
Asciz	Pi;
NameAndType	Pi:()D
Method	scala/math/package$.Pi:()D
Asciz	E;
NameAndType	E:()D
Method	scala/math/package$.E:()D
Asciz	ScalaSig;
Asciz	scala/math/package;
class	scala/math/package
Asciz	java/lang/Object;
class	java/lang/Object

{
public static final double log1p(double);
  Signature: (D)D
  Code:
   Stack=3, Locals=2, Args_size=1
	getstatic	Field scala/math/package$.MODULE$:Lscala/math/package$;
	dload_0
	invokevirtual	Method scala/math/package$.log1p:(D)D
	dreturn
  Labels:

public static final double expm1(double);
  Signature: (D)D
  Code:
   Stack=3, Locals=2, Args_size=1
	getstatic	Field scala/math/package$.MODULE$:Lscala/math/package$;
	dload_0
	invokevirtual	Method scala/math/package$.expm1:(D)D
	dreturn
  Labels:

public static final double hypot(double, double);
  Signature: (DD)D
  Code:
   Stack=5, Locals=4, Args_size=2
	getstatic	Field scala/math/package$.MODULE$:Lscala/math/package$;
	dload_0
	dload_2
	invokevirtual	Method scala/math/package$.hypot:(DD)D
	dreturn
  Labels:

public static final double tanh(double);
  Signature: (D)D
  Code:
   Stack=3, Locals=2, Args_size=1
	getstatic	Field scala/math/package$.MODULE$:Lscala/math/package$;
	dload_0
	invokevirtual	Method scala/math/package$.tanh:(D)D
	dreturn
  Labels:

public static final double cosh(double);
  Signature: (D)D
  Code:
   Stack=3, Locals=2, Args_size=1
	getstatic	Field scala/math/package$.MODULE$:Lscala/math/package$;
	dload_0
	invokevirtual	Method scala/math/package$.cosh:(D)D
	dreturn
  Labels:

public static final double sinh(double);
  Signature: (D)D
  Code:
   Stack=3, Locals=2, Args_size=1
	getstatic	Field scala/math/package$.MODULE$:Lscala/math/package$;
	dload_0
	invokevirtual	Method scala/math/package$.sinh:(D)D
	dreturn
  Labels:

public static final float ulp(float);
  Signature: (F)F
  Code:
   Stack=2, Locals=1, Args_size=1
	getstatic	Field scala/math/package$.MODULE$:Lscala/math/package$;
	fload_0
	invokevirtual	Method scala/math/package$.ulp:(F)F
	freturn
  Labels:

public static final double ulp(double);
  Signature: (D)D
  Code:
   Stack=3, Locals=2, Args_size=1
	getstatic	Field scala/math/package$.MODULE$:Lscala/math/package$;
	dload_0
	invokevirtual	Method scala/math/package$.ulp:(D)D
	dreturn
  Labels:

public static final double cbrt(double);
  Signature: (D)D
  Code:
   Stack=3, Locals=2, Args_size=1
	getstatic	Field scala/math/package$.MODULE$:Lscala/math/package$;
	dload_0
	invokevirtual	Method scala/math/package$.cbrt:(D)D
	dreturn
  Labels:

public static final double log10(double);
  Signature: (D)D
  Code:
   Stack=3, Locals=2, Args_size=1
	getstatic	Field scala/math/package$.MODULE$:Lscala/math/package$;
	dload_0
	invokevirtual	Method scala/math/package$.log10:(D)D
	dreturn
  Labels:

public static final int signum(int);
  Signature: (I)I
  Code:
   Stack=2, Locals=1, Args_size=1
	getstatic	Field scala/math/package$.MODULE$:Lscala/math/package$;
	iload_0
	invokevirtual	Method scala/math/package$.signum:(I)I
	ireturn
  Labels:

public static final long signum(long);
  Signature: (J)J
  Code:
   Stack=3, Locals=2, Args_size=1
	getstatic	Field scala/math/package$.MODULE$:Lscala/math/package$;
	lload_0
	invokevirtual	Method scala/math/package$.signum:(J)J
	lreturn
  Labels:

public static final float signum(float);
  Signature: (F)F
  Code:
   Stack=2, Locals=1, Args_size=1
	getstatic	Field scala/math/package$.MODULE$:Lscala/math/package$;
	fload_0
	invokevirtual	Method scala/math/package$.signum:(F)F
	freturn
  Labels:

public static final double signum(double);
  Signature: (D)D
  Code:
   Stack=3, Locals=2, Args_size=1
	getstatic	Field scala/math/package$.MODULE$:Lscala/math/package$;
	dload_0
	invokevirtual	Method scala/math/package$.signum:(D)D
	dreturn
  Labels:

public static final double min(double, double);
  Signature: (DD)D
  Code:
   Stack=5, Locals=4, Args_size=2
	getstatic	Field scala/math/package$.MODULE$:Lscala/math/package$;
	dload_0
	dload_2
	invokevirtual	Method scala/math/package$.min:(DD)D
	dreturn
  Labels:

public static final float min(float, float);
  Signature: (FF)F
  Code:
   Stack=3, Locals=2, Args_size=2
	getstatic	Field scala/math/package$.MODULE$:Lscala/math/package$;
	fload_0
	fload_1
	invokevirtual	Method scala/math/package$.min:(FF)F
	freturn
  Labels:

public static final long min(long, long);
  Signature: (JJ)J
  Code:
   Stack=5, Locals=4, Args_size=2
	getstatic	Field scala/math/package$.MODULE$:Lscala/math/package$;
	lload_0
	lload_2
	invokevirtual	Method scala/math/package$.min:(JJ)J
	lreturn
  Labels:

public static final int min(int, int);
  Signature: (II)I
  Code:
   Stack=3, Locals=2, Args_size=2
	getstatic	Field scala/math/package$.MODULE$:Lscala/math/package$;
	iload_0
	iload_1
	invokevirtual	Method scala/math/package$.min:(II)I
	ireturn
  Labels:

public static final double max(double, double);
  Signature: (DD)D
  Code:
   Stack=5, Locals=4, Args_size=2
	getstatic	Field scala/math/package$.MODULE$:Lscala/math/package$;
	dload_0
	dload_2
	invokevirtual	Method scala/math/package$.max:(DD)D
	dreturn
  Labels:

public static final float max(float, float);
  Signature: (FF)F
  Code:
   Stack=3, Locals=2, Args_size=2
	getstatic	Field scala/math/package$.MODULE$:Lscala/math/package$;
	fload_0
	fload_1
	invokevirtual	Method scala/math/package$.max:(FF)F
	freturn
  Labels:

public static final long max(long, long);
  Signature: (JJ)J
  Code:
   Stack=5, Locals=4, Args_size=2
	getstatic	Field scala/math/package$.MODULE$:Lscala/math/package$;
	lload_0
	lload_2
	invokevirtual	Method scala/math/package$.max:(JJ)J
	lreturn
  Labels:

public static final int max(int, int);
  Signature: (II)I
  Code:
   Stack=3, Locals=2, Args_size=2
	getstatic	Field scala/math/package$.MODULE$:Lscala/math/package$;
	iload_0
	iload_1
	invokevirtual	Method scala/math/package$.max:(II)I
	ireturn
  Labels:

public static final double abs(double);
  Signature: (D)D
  Code:
   Stack=3, Locals=2, Args_size=1
	getstatic	Field scala/math/package$.MODULE$:Lscala/math/package$;
	dload_0
	invokevirtual	Method scala/math/package$.abs:(D)D
	dreturn
  Labels:

public static final float abs(float);
  Signature: (F)F
  Code:
   Stack=2, Locals=1, Args_size=1
	getstatic	Field scala/math/package$.MODULE$:Lscala/math/package$;
	fload_0
	invokevirtual	Method scala/math/package$.abs:(F)F
	freturn
  Labels:

public static final long abs(long);
  Signature: (J)J
  Code:
   Stack=3, Locals=2, Args_size=1
	getstatic	Field scala/math/package$.MODULE$:Lscala/math/package$;
	lload_0
	invokevirtual	Method scala/math/package$.abs:(J)J
	lreturn
  Labels:

public static final int abs(int);
  Signature: (I)I
  Code:
   Stack=2, Locals=1, Args_size=1
	getstatic	Field scala/math/package$.MODULE$:Lscala/math/package$;
	iload_0
	invokevirtual	Method scala/math/package$.abs:(I)I
	ireturn
  Labels:

public static final long round(double);
  Signature: (D)J
  Code:
   Stack=3, Locals=2, Args_size=1
	getstatic	Field scala/math/package$.MODULE$:Lscala/math/package$;
	dload_0
	invokevirtual	Method scala/math/package$.round:(D)J
	lreturn
  Labels:

public static final int round(float);
  Signature: (F)I
  Code:
   Stack=2, Locals=1, Args_size=1
	getstatic	Field scala/math/package$.MODULE$:Lscala/math/package$;
	fload_0
	invokevirtual	Method scala/math/package$.round:(F)I
	ireturn
  Labels:

public static final double pow(double, double);
  Signature: (DD)D
  Code:
   Stack=5, Locals=4, Args_size=2
	getstatic	Field scala/math/package$.MODULE$:Lscala/math/package$;
	dload_0
	dload_2
	invokevirtual	Method scala/math/package$.pow:(DD)D
	dreturn
  Labels:

public static final double atan2(double, double);
  Signature: (DD)D
  Code:
   Stack=5, Locals=4, Args_size=2
	getstatic	Field scala/math/package$.MODULE$:Lscala/math/package$;
	dload_0
	dload_2
	invokevirtual	Method scala/math/package$.atan2:(DD)D
	dreturn
  Labels:

public static final double rint(double);
  Signature: (D)D
  Code:
   Stack=3, Locals=2, Args_size=1
	getstatic	Field scala/math/package$.MODULE$:Lscala/math/package$;
	dload_0
	invokevirtual	Method scala/math/package$.rint:(D)D
	dreturn
  Labels:

public static final double floor(double);
  Signature: (D)D
  Code:
   Stack=3, Locals=2, Args_size=1
	getstatic	Field scala/math/package$.MODULE$:Lscala/math/package$;
	dload_0
	invokevirtual	Method scala/math/package$.floor:(D)D
	dreturn
  Labels:

public static final double ceil(double);
  Signature: (D)D
  Code:
   Stack=3, Locals=2, Args_size=1
	getstatic	Field scala/math/package$.MODULE$:Lscala/math/package$;
	dload_0
	invokevirtual	Method scala/math/package$.ceil:(D)D
	dreturn
  Labels:

public static final double IEEEremainder(double, double);
  Signature: (DD)D
  Code:
   Stack=5, Locals=4, Args_size=2
	getstatic	Field scala/math/package$.MODULE$:Lscala/math/package$;
	dload_0
	dload_2
	invokevirtual	Method scala/math/package$.IEEEremainder:(DD)D
	dreturn
  Labels:

public static final double sqrt(double);
  Signature: (D)D
  Code:
   Stack=3, Locals=2, Args_size=1
	getstatic	Field scala/math/package$.MODULE$:Lscala/math/package$;
	dload_0
	invokevirtual	Method scala/math/package$.sqrt:(D)D
	dreturn
  Labels:

public static final double log(double);
  Signature: (D)D
  Code:
   Stack=3, Locals=2, Args_size=1
	getstatic	Field scala/math/package$.MODULE$:Lscala/math/package$;
	dload_0
	invokevirtual	Method scala/math/package$.log:(D)D
	dreturn
  Labels:

public static final double exp(double);
  Signature: (D)D
  Code:
   Stack=3, Locals=2, Args_size=1
	getstatic	Field scala/math/package$.MODULE$:Lscala/math/package$;
	dload_0
	invokevirtual	Method scala/math/package$.exp:(D)D
	dreturn
  Labels:

public static final double toDegrees(double);
  Signature: (D)D
  Code:
   Stack=3, Locals=2, Args_size=1
	getstatic	Field scala/math/package$.MODULE$:Lscala/math/package$;
	dload_0
	invokevirtual	Method scala/math/package$.toDegrees:(D)D
	dreturn
  Labels:

public static final double toRadians(double);
  Signature: (D)D
  Code:
   Stack=3, Locals=2, Args_size=1
	getstatic	Field scala/math/package$.MODULE$:Lscala/math/package$;
	dload_0
	invokevirtual	Method scala/math/package$.toRadians:(D)D
	dreturn
  Labels:

public static final double atan(double);
  Signature: (D)D
  Code:
   Stack=3, Locals=2, Args_size=1
	getstatic	Field scala/math/package$.MODULE$:Lscala/math/package$;
	dload_0
	invokevirtual	Method scala/math/package$.atan:(D)D
	dreturn
  Labels:

public static final double acos(double);
  Signature: (D)D
  Code:
   Stack=3, Locals=2, Args_size=1
	getstatic	Field scala/math/package$.MODULE$:Lscala/math/package$;
	dload_0
	invokevirtual	Method scala/math/package$.acos:(D)D
	dreturn
  Labels:

public static final double asin(double);
  Signature: (D)D
  Code:
   Stack=3, Locals=2, Args_size=1
	getstatic	Field scala/math/package$.MODULE$:Lscala/math/package$;
	dload_0
	invokevirtual	Method scala/math/package$.asin:(D)D
	dreturn
  Labels:

public static final double tan(double);
  Signature: (D)D
  Code:
   Stack=3, Locals=2, Args_size=1
	getstatic	Field scala/math/package$.MODULE$:Lscala/math/package$;
	dload_0
	invokevirtual	Method scala/math/package$.tan:(D)D
	dreturn
  Labels:

public static final double cos(double);
  Signature: (D)D
  Code:
   Stack=3, Locals=2, Args_size=1
	getstatic	Field scala/math/package$.MODULE$:Lscala/math/package$;
	dload_0
	invokevirtual	Method scala/math/package$.cos:(D)D
	dreturn
  Labels:

public static final double sin(double);
  Signature: (D)D
  Code:
   Stack=3, Locals=2, Args_size=1
	getstatic	Field scala/math/package$.MODULE$:Lscala/math/package$;
	dload_0
	invokevirtual	Method scala/math/package$.sin:(D)D
	dreturn
  Labels:

public static final double random();
  Signature: ()D
  Code:
   Stack=2, Locals=0, Args_size=0
	getstatic	Field scala/math/package$.MODULE$:Lscala/math/package$;
	invokevirtual	Method scala/math/package$.random:()D
	dreturn
  Labels:

public static final double Pi();
  Signature: ()D
  Code:
   Stack=2, Locals=0, Args_size=0
	getstatic	Field scala/math/package$.MODULE$:Lscala/math/package$;
	invokevirtual	Method scala/math/package$.Pi:()D
	dreturn
  Labels:

public static final double E();
  Signature: ()D
  Code:
   Stack=2, Locals=0, Args_size=0
	getstatic	Field scala/math/package$.MODULE$:Lscala/math/package$;
	invokevirtual	Method scala/math/package$.E:()D
	dreturn
  Labels:

}

