Compiled from "PartiallyOrdered.scala"
public abstract class scala.math.PartiallyOrdered$class extends java.lang.Object
  SourceFile: "PartiallyOrdered.scala"
  Scala: length = 0x
   
  minor version: 0
  major version: 49
  Constant pool:
const #1 = Asciz	SourceFile;
const #2 = Asciz	PartiallyOrdered.scala;
const #3 = Asciz	$init$;
const #4 = Asciz	(Lscala/math/PartiallyOrdered;)V;
const #5 = Asciz	Code;
const #6 = Asciz	LineNumberTable;
const #7 = Asciz	$this;
const #8 = Asciz	Lscala/math/PartiallyOrdered;;
const #9 = Asciz	LocalVariableTable;
const #10 = Asciz	gd4$1;
const #11 = Asciz	(Lscala/math/PartiallyOrdered;I)Z;
const #12 = Asciz	gd3$1;
const #13 = Asciz	gd2$1;
const #14 = Asciz	gd1$1;
const #15 = Asciz	$greater$eq;
const #16 = Asciz	(Lscala/math/PartiallyOrdered;Ljava/lang/Object;Lscala/Function1;)Z;
const #17 = Asciz	scala/math/PartiallyOrdered;
const #18 = class	#17;	//  scala/math/PartiallyOrdered
const #19 = Asciz	tryCompareTo;
const #20 = Asciz	(Ljava/lang/Object;Lscala/Function1;)Lscala/Option;;
const #21 = NameAndType	#19:#20;//  tryCompareTo:(Ljava/lang/Object;Lscala/Function1;)Lscala/Option;
const #22 = InterfaceMethod	#18.#21;	//  scala/math/PartiallyOrdered.tryCompareTo:(Ljava/lang/Object;Lscala/Function1;)Lscala/Option;
const #23 = Asciz	scala/Some;
const #24 = class	#23;	//  scala/Some
const #25 = Asciz	x;
const #26 = Asciz	Ljava/lang/Object;;
const #27 = NameAndType	#25:#26;//  x:Ljava/lang/Object;
const #28 = Field	#24.#27;	//  scala/Some.x:Ljava/lang/Object;
const #29 = Asciz	scala/runtime/BoxesRunTime;
const #30 = class	#29;	//  scala/runtime/BoxesRunTime
const #31 = Asciz	unboxToInt;
const #32 = Asciz	(Ljava/lang/Object;)I;
const #33 = NameAndType	#31:#32;//  unboxToInt:(Ljava/lang/Object;)I
const #34 = Method	#30.#33;	//  scala/runtime/BoxesRunTime.unboxToInt:(Ljava/lang/Object;)I
const #35 = Asciz	scala/math/PartiallyOrdered$class;
const #36 = class	#35;	//  scala/math/PartiallyOrdered$class
const #37 = NameAndType	#10:#11;//  gd4$1:(Lscala/math/PartiallyOrdered;I)Z
const #38 = Method	#36.#37;	//  scala/math/PartiallyOrdered$class.gd4$1:(Lscala/math/PartiallyOrdered;I)Z
const #39 = Asciz	scala/MatchError;
const #40 = class	#39;	//  scala/MatchError
const #41 = Asciz	scala/Option;
const #42 = class	#41;	//  scala/Option
const #43 = Asciz	toString;
const #44 = Asciz	()Ljava/lang/String;;
const #45 = NameAndType	#43:#44;//  toString:()Ljava/lang/String;
const #46 = Method	#42.#45;	//  scala/Option.toString:()Ljava/lang/String;
const #47 = Asciz	<init>;
const #48 = Asciz	(Ljava/lang/String;)V;
const #49 = NameAndType	#47:#48;//  "<init>":(Ljava/lang/String;)V
const #50 = Method	#40.#49;	//  scala/MatchError."<init>":(Ljava/lang/String;)V
const #51 = Asciz	that;
const #52 = Asciz	evidence$5;
const #53 = Asciz	Lscala/Function1;;
const #54 = Asciz	temp10;
const #55 = Asciz	Lscala/Option;;
const #56 = Asciz	$less$eq;
const #57 = NameAndType	#12:#11;//  gd3$1:(Lscala/math/PartiallyOrdered;I)Z
const #58 = Method	#36.#57;	//  scala/math/PartiallyOrdered$class.gd3$1:(Lscala/math/PartiallyOrdered;I)Z
const #59 = Asciz	evidence$4;
const #60 = Asciz	temp7;
const #61 = Asciz	$greater;
const #62 = NameAndType	#13:#11;//  gd2$1:(Lscala/math/PartiallyOrdered;I)Z
const #63 = Method	#36.#62;	//  scala/math/PartiallyOrdered$class.gd2$1:(Lscala/math/PartiallyOrdered;I)Z
const #64 = Asciz	evidence$3;
const #65 = Asciz	temp4;
const #66 = Asciz	$less;
const #67 = NameAndType	#14:#11;//  gd1$1:(Lscala/math/PartiallyOrdered;I)Z
const #68 = Method	#36.#67;	//  scala/math/PartiallyOrdered$class.gd1$1:(Lscala/math/PartiallyOrdered;I)Z
const #69 = Asciz	evidence$2;
const #70 = Asciz	temp1;
const #71 = Asciz	Scala;
const #72 = Asciz	java/lang/Object;
const #73 = class	#72;	//  java/lang/Object

{
public static void $init$(scala.math.PartiallyOrdered);
  Code:
   Stack=0, Locals=1, Args_size=1
   0:	return
  LineNumberTable: 
   line 19: 0

  LocalVariableTable: 
   Start  Length  Slot  Name   Signature
   0      1      0    $this       Lscala/math/PartiallyOrdered;


public static boolean $greater$eq(scala.math.PartiallyOrdered, java.lang.Object, scala.Function1);
  Code:
   Stack=3, Locals=5, Args_size=3
   0:	aload_0
   1:	aload_1
   2:	aload_2
   3:	invokeinterface	#22,  3; //InterfaceMethod scala/math/PartiallyOrdered.tryCompareTo:(Ljava/lang/Object;Lscala/Function1;)Lscala/Option;
   8:	astore	4
   10:	aload	4
   12:	instanceof	#24; //class scala/Some
   15:	ifeq	63
   18:	aload_0
   19:	aload	4
   21:	checkcast	#24; //class scala/Some
   24:	astore_3
   25:	aload_3
   26:	getfield	#28; //Field scala/Some.x:Ljava/lang/Object;
   29:	invokestatic	#34; //Method scala/runtime/BoxesRunTime.unboxToInt:(Ljava/lang/Object;)I
   32:	invokestatic	#38; //Method gd4$1:(Lscala/math/PartiallyOrdered;I)Z
   35:	ifeq	42
   38:	iconst_1
   39:	goto	68
   42:	iconst_1
   43:	ifeq	50
   46:	iconst_0
   47:	goto	68
   50:	new	#40; //class scala/MatchError
   53:	dup
   54:	aload	4
   56:	invokevirtual	#46; //Method scala/Option.toString:()Ljava/lang/String;
   59:	invokespecial	#50; //Method scala/MatchError."<init>":(Ljava/lang/String;)V
   62:	athrow
   63:	iconst_1
   64:	ifeq	69
   67:	iconst_0
   68:	ireturn
   69:	new	#40; //class scala/MatchError
   72:	dup
   73:	aload	4
   75:	invokevirtual	#46; //Method scala/Option.toString:()Ljava/lang/String;
   78:	invokespecial	#50; //Method scala/MatchError."<init>":(Ljava/lang/String;)V
   81:	athrow
  LineNumberTable: 
   line 46: 0
   line 45: 19
   line 46: 32
   line 47: 38
   line 21: 42
   line 48: 46
   line 46: 50
   line 21: 63
   line 48: 67
   line 46: 68

  LocalVariableTable: 
   Start  Length  Slot  Name   Signature
   0      82      0    $this       Lscala/math/PartiallyOrdered;
   0      82      1    that       Ljava/lang/Object;
   0      82      2    evidence$5       Lscala/Function1;
   10      72      4    temp10       Lscala/Option;


public static boolean $less$eq(scala.math.PartiallyOrdered, java.lang.Object, scala.Function1);
  Code:
   Stack=3, Locals=5, Args_size=3
   0:	aload_0
   1:	aload_1
   2:	aload_2
   3:	invokeinterface	#22,  3; //InterfaceMethod scala/math/PartiallyOrdered.tryCompareTo:(Ljava/lang/Object;Lscala/Function1;)Lscala/Option;
   8:	astore	4
   10:	aload	4
   12:	instanceof	#24; //class scala/Some
   15:	ifeq	63
   18:	aload_0
   19:	aload	4
   21:	checkcast	#24; //class scala/Some
   24:	astore_3
   25:	aload_3
   26:	getfield	#28; //Field scala/Some.x:Ljava/lang/Object;
   29:	invokestatic	#34; //Method scala/runtime/BoxesRunTime.unboxToInt:(Ljava/lang/Object;)I
   32:	invokestatic	#58; //Method gd3$1:(Lscala/math/PartiallyOrdered;I)Z
   35:	ifeq	42
   38:	iconst_1
   39:	goto	68
   42:	iconst_1
   43:	ifeq	50
   46:	iconst_0
   47:	goto	68
   50:	new	#40; //class scala/MatchError
   53:	dup
   54:	aload	4
   56:	invokevirtual	#46; //Method scala/Option.toString:()Ljava/lang/String;
   59:	invokespecial	#50; //Method scala/MatchError."<init>":(Ljava/lang/String;)V
   62:	athrow
   63:	iconst_1
   64:	ifeq	69
   67:	iconst_0
   68:	ireturn
   69:	new	#40; //class scala/MatchError
   72:	dup
   73:	aload	4
   75:	invokevirtual	#46; //Method scala/Option.toString:()Ljava/lang/String;
   78:	invokespecial	#50; //Method scala/MatchError."<init>":(Ljava/lang/String;)V
   81:	athrow
  LineNumberTable: 
   line 41: 0
   line 40: 19
   line 41: 32
   line 42: 38
   line 21: 42
   line 43: 46
   line 41: 50
   line 21: 63
   line 43: 67
   line 41: 68

  LocalVariableTable: 
   Start  Length  Slot  Name   Signature
   0      82      0    $this       Lscala/math/PartiallyOrdered;
   0      82      1    that       Ljava/lang/Object;
   0      82      2    evidence$4       Lscala/Function1;
   10      72      4    temp7       Lscala/Option;


public static boolean $greater(scala.math.PartiallyOrdered, java.lang.Object, scala.Function1);
  Code:
   Stack=3, Locals=5, Args_size=3
   0:	aload_0
   1:	aload_1
   2:	aload_2
   3:	invokeinterface	#22,  3; //InterfaceMethod scala/math/PartiallyOrdered.tryCompareTo:(Ljava/lang/Object;Lscala/Function1;)Lscala/Option;
   8:	astore	4
   10:	aload	4
   12:	instanceof	#24; //class scala/Some
   15:	ifeq	63
   18:	aload_0
   19:	aload	4
   21:	checkcast	#24; //class scala/Some
   24:	astore_3
   25:	aload_3
   26:	getfield	#28; //Field scala/Some.x:Ljava/lang/Object;
   29:	invokestatic	#34; //Method scala/runtime/BoxesRunTime.unboxToInt:(Ljava/lang/Object;)I
   32:	invokestatic	#63; //Method gd2$1:(Lscala/math/PartiallyOrdered;I)Z
   35:	ifeq	42
   38:	iconst_1
   39:	goto	68
   42:	iconst_1
   43:	ifeq	50
   46:	iconst_0
   47:	goto	68
   50:	new	#40; //class scala/MatchError
   53:	dup
   54:	aload	4
   56:	invokevirtual	#46; //Method scala/Option.toString:()Ljava/lang/String;
   59:	invokespecial	#50; //Method scala/MatchError."<init>":(Ljava/lang/String;)V
   62:	athrow
   63:	iconst_1
   64:	ifeq	69
   67:	iconst_0
   68:	ireturn
   69:	new	#40; //class scala/MatchError
   72:	dup
   73:	aload	4
   75:	invokevirtual	#46; //Method scala/Option.toString:()Ljava/lang/String;
   78:	invokespecial	#50; //Method scala/MatchError."<init>":(Ljava/lang/String;)V
   81:	athrow
  LineNumberTable: 
   line 36: 0
   line 35: 19
   line 36: 32
   line 37: 38
   line 21: 42
   line 38: 46
   line 36: 50
   line 21: 63
   line 38: 67
   line 36: 68

  LocalVariableTable: 
   Start  Length  Slot  Name   Signature
   0      82      0    $this       Lscala/math/PartiallyOrdered;
   0      82      1    that       Ljava/lang/Object;
   0      82      2    evidence$3       Lscala/Function1;
   10      72      4    temp4       Lscala/Option;


public static boolean $less(scala.math.PartiallyOrdered, java.lang.Object, scala.Function1);
  Code:
   Stack=3, Locals=5, Args_size=3
   0:	aload_0
   1:	aload_1
   2:	aload_2
   3:	invokeinterface	#22,  3; //InterfaceMethod scala/math/PartiallyOrdered.tryCompareTo:(Ljava/lang/Object;Lscala/Function1;)Lscala/Option;
   8:	astore	4
   10:	aload	4
   12:	instanceof	#24; //class scala/Some
   15:	ifeq	63
   18:	aload_0
   19:	aload	4
   21:	checkcast	#24; //class scala/Some
   24:	astore_3
   25:	aload_3
   26:	getfield	#28; //Field scala/Some.x:Ljava/lang/Object;
   29:	invokestatic	#34; //Method scala/runtime/BoxesRunTime.unboxToInt:(Ljava/lang/Object;)I
   32:	invokestatic	#68; //Method gd1$1:(Lscala/math/PartiallyOrdered;I)Z
   35:	ifeq	42
   38:	iconst_1
   39:	goto	68
   42:	iconst_1
   43:	ifeq	50
   46:	iconst_0
   47:	goto	68
   50:	new	#40; //class scala/MatchError
   53:	dup
   54:	aload	4
   56:	invokevirtual	#46; //Method scala/Option.toString:()Ljava/lang/String;
   59:	invokespecial	#50; //Method scala/MatchError."<init>":(Ljava/lang/String;)V
   62:	athrow
   63:	iconst_1
   64:	ifeq	69
   67:	iconst_0
   68:	ireturn
   69:	new	#40; //class scala/MatchError
   72:	dup
   73:	aload	4
   75:	invokevirtual	#46; //Method scala/Option.toString:()Ljava/lang/String;
   78:	invokespecial	#50; //Method scala/MatchError."<init>":(Ljava/lang/String;)V
   81:	athrow
  LineNumberTable: 
   line 31: 0
   line 30: 19
   line 31: 32
   line 32: 38
   line 21: 42
   line 33: 46
   line 31: 50
   line 21: 63
   line 33: 67
   line 31: 68

  LocalVariableTable: 
   Start  Length  Slot  Name   Signature
   0      82      0    $this       Lscala/math/PartiallyOrdered;
   0      82      1    that       Ljava/lang/Object;
   0      82      2    evidence$2       Lscala/Function1;
   10      72      4    temp1       Lscala/Option;


}

