Compiled from "PartialOrdering.scala"
public abstract class scala.math.PartialOrdering$class extends java.lang.Object
  SourceFile: "PartialOrdering.scala"
  Scala: length = 0x
   
  InnerClass: 
   public final #37= #13 of #20; //$anon$1=class scala/math/PartialOrdering$$anon$1 of class scala/math/PartialOrdering
  minor version: 0
  major version: 49
  Constant pool:
const #1 = Asciz	SourceFile;
const #2 = Asciz	PartialOrdering.scala;
const #3 = Asciz	$init$;
const #4 = Asciz	(Lscala/math/PartialOrdering;)V;
const #5 = Asciz	Code;
const #6 = Asciz	LineNumberTable;
const #7 = Asciz	$this;
const #8 = Asciz	Lscala/math/PartialOrdering;;
const #9 = Asciz	LocalVariableTable;
const #10 = Asciz	reverse;
const #11 = Asciz	(Lscala/math/PartialOrdering;)Lscala/math/PartialOrdering;;
const #12 = Asciz	scala/math/PartialOrdering$$anon$1;
const #13 = class	#12;	//  scala/math/PartialOrdering$$anon$1
const #14 = Asciz	<init>;
const #15 = NameAndType	#14:#4;//  "<init>":(Lscala/math/PartialOrdering;)V
const #16 = Method	#13.#15;	//  scala/math/PartialOrdering$$anon$1."<init>":(Lscala/math/PartialOrdering;)V
const #17 = Asciz	equiv;
const #18 = Asciz	(Lscala/math/PartialOrdering;Ljava/lang/Object;Ljava/lang/Object;)Z;
const #19 = Asciz	scala/math/PartialOrdering;
const #20 = class	#19;	//  scala/math/PartialOrdering
const #21 = Asciz	lteq;
const #22 = Asciz	(Ljava/lang/Object;Ljava/lang/Object;)Z;
const #23 = NameAndType	#21:#22;//  lteq:(Ljava/lang/Object;Ljava/lang/Object;)Z
const #24 = InterfaceMethod	#20.#23;	//  scala/math/PartialOrdering.lteq:(Ljava/lang/Object;Ljava/lang/Object;)Z
const #25 = Asciz	x;
const #26 = Asciz	Ljava/lang/Object;;
const #27 = Asciz	y;
const #28 = Asciz	gt;
const #29 = Asciz	gteq;
const #30 = NameAndType	#29:#22;//  gteq:(Ljava/lang/Object;Ljava/lang/Object;)Z
const #31 = InterfaceMethod	#20.#30;	//  scala/math/PartialOrdering.gteq:(Ljava/lang/Object;Ljava/lang/Object;)Z
const #32 = NameAndType	#17:#22;//  equiv:(Ljava/lang/Object;Ljava/lang/Object;)Z
const #33 = InterfaceMethod	#20.#32;	//  scala/math/PartialOrdering.equiv:(Ljava/lang/Object;Ljava/lang/Object;)Z
const #34 = Asciz	lt;
const #35 = Asciz	Scala;
const #36 = Asciz	InnerClasses;
const #37 = Asciz	$anon$1;
const #38 = Asciz	scala/math/PartialOrdering$class;
const #39 = class	#38;	//  scala/math/PartialOrdering$class
const #40 = Asciz	java/lang/Object;
const #41 = class	#40;	//  java/lang/Object

{
public static void $init$(scala.math.PartialOrdering);
  Code:
   Stack=0, Locals=1, Args_size=1
   0:	return
  LineNumberTable: 
   line 44: 0

  LocalVariableTable: 
   Start  Length  Slot  Name   Signature
   0      1      0    $this       Lscala/math/PartialOrdering;


public static scala.math.PartialOrdering reverse(scala.math.PartialOrdering);
  Code:
   Stack=3, Locals=1, Args_size=1
   0:	new	#13; //class scala/math/PartialOrdering$$anon$1
   3:	dup
   4:	aload_0
   5:	invokespecial	#16; //Method scala/math/PartialOrdering$$anon$1."<init>":(Lscala/math/PartialOrdering;)V
   8:	areturn
  LineNumberTable: 
   line 81: 0

  LocalVariableTable: 
   Start  Length  Slot  Name   Signature
   0      9      0    $this       Lscala/math/PartialOrdering;


public static boolean equiv(scala.math.PartialOrdering, java.lang.Object, java.lang.Object);
  Code:
   Stack=3, Locals=3, Args_size=3
   0:	aload_0
   1:	aload_1
   2:	aload_2
   3:	invokeinterface	#24,  3; //InterfaceMethod scala/math/PartialOrdering.lteq:(Ljava/lang/Object;Ljava/lang/Object;)Z
   8:	ifeq	26
   11:	aload_0
   12:	aload_2
   13:	aload_1
   14:	invokeinterface	#24,  3; //InterfaceMethod scala/math/PartialOrdering.lteq:(Ljava/lang/Object;Ljava/lang/Object;)Z
   19:	ifeq	26
   22:	iconst_1
   23:	goto	27
   26:	iconst_0
   27:	ireturn
  LineNumberTable: 
   line 79: 0

  LocalVariableTable: 
   Start  Length  Slot  Name   Signature
   0      28      0    $this       Lscala/math/PartialOrdering;
   0      28      1    x       Ljava/lang/Object;
   0      28      2    y       Ljava/lang/Object;


public static boolean gt(scala.math.PartialOrdering, java.lang.Object, java.lang.Object);
  Code:
   Stack=3, Locals=3, Args_size=3
   0:	aload_0
   1:	aload_1
   2:	aload_2
   3:	invokeinterface	#31,  3; //InterfaceMethod scala/math/PartialOrdering.gteq:(Ljava/lang/Object;Ljava/lang/Object;)Z
   8:	ifeq	26
   11:	aload_0
   12:	aload_1
   13:	aload_2
   14:	invokeinterface	#33,  3; //InterfaceMethod scala/math/PartialOrdering.equiv:(Ljava/lang/Object;Ljava/lang/Object;)Z
   19:	ifne	26
   22:	iconst_1
   23:	goto	27
   26:	iconst_0
   27:	ireturn
  LineNumberTable: 
   line 74: 0

  LocalVariableTable: 
   Start  Length  Slot  Name   Signature
   0      28      0    $this       Lscala/math/PartialOrdering;
   0      28      1    x       Ljava/lang/Object;
   0      28      2    y       Ljava/lang/Object;


public static boolean lt(scala.math.PartialOrdering, java.lang.Object, java.lang.Object);
  Code:
   Stack=3, Locals=3, Args_size=3
   0:	aload_0
   1:	aload_1
   2:	aload_2
   3:	invokeinterface	#24,  3; //InterfaceMethod scala/math/PartialOrdering.lteq:(Ljava/lang/Object;Ljava/lang/Object;)Z
   8:	ifeq	26
   11:	aload_0
   12:	aload_1
   13:	aload_2
   14:	invokeinterface	#33,  3; //InterfaceMethod scala/math/PartialOrdering.equiv:(Ljava/lang/Object;Ljava/lang/Object;)Z
   19:	ifne	26
   22:	iconst_1
   23:	goto	27
   26:	iconst_0
   27:	ireturn
  LineNumberTable: 
   line 69: 0

  LocalVariableTable: 
   Start  Length  Slot  Name   Signature
   0      28      0    $this       Lscala/math/PartialOrdering;
   0      28      1    x       Ljava/lang/Object;
   0      28      2    y       Ljava/lang/Object;


public static boolean gteq(scala.math.PartialOrdering, java.lang.Object, java.lang.Object);
  Code:
   Stack=3, Locals=3, Args_size=3
   0:	aload_0
   1:	aload_2
   2:	aload_1
   3:	invokeinterface	#24,  3; //InterfaceMethod scala/math/PartialOrdering.lteq:(Ljava/lang/Object;Ljava/lang/Object;)Z
   8:	ireturn
  LineNumberTable: 
   line 64: 0

  LocalVariableTable: 
   Start  Length  Slot  Name   Signature
   0      9      0    $this       Lscala/math/PartialOrdering;
   0      9      1    x       Ljava/lang/Object;
   0      9      2    y       Ljava/lang/Object;


}

