Compiled from "ScalaNumericConversions.scala"
public abstract class scala.math.ScalaNumericConversions$class extends java.lang.Object
  SourceFile: "ScalaNumericConversions.scala"
  Scala: length = 0x
   
  minor version: 0
  major version: 49
  Constant pool:
Asciz	SourceFile;
Asciz	ScalaNumericConversions.scala;
Asciz	$init$;
Asciz	(Lscala/math/ScalaNumericConversions;)V;
Asciz	Code;
Asciz	LineNumberTable;
Asciz	$this;
Asciz	Lscala/math/ScalaNumericConversions;;
Asciz	LocalVariableTable;
Asciz	unifiedPrimitiveEquals;
Asciz	(Lscala/math/ScalaNumericConversions;Ljava/lang/Object;)Z;
Asciz	java/lang/Character;
class	java/lang/Character
Asciz	scala/runtime/BoxesRunTime;
class	scala/runtime/BoxesRunTime
Asciz	unboxToChar;
Asciz	(Ljava/lang/Object;)C;
NameAndType	unboxToChar:(Ljava/lang/Object;)C
Method	scala/runtime/BoxesRunTime.unboxToChar:(Ljava/lang/Object;)C
Asciz	scala/math/ScalaNumericConversions;
class	scala/math/ScalaNumericConversions
Asciz	isValidChar;
Asciz	()Z;
NameAndType	isValidChar:()Z
InterfaceMethod	scala/math/ScalaNumericConversions.isValidChar:()Z
Asciz	toInt;
Asciz	()I;
NameAndType	toInt:()I
InterfaceMethod	scala/math/ScalaNumericConversions.toInt:()I
Asciz	scala/MatchError;
class	scala/MatchError
Asciz	java/lang/Object;
class	java/lang/Object
Asciz	toString;
Asciz	()Ljava/lang/String;;
NameAndType	toString:()Ljava/lang/String;
Method	java/lang/Object.toString:()Ljava/lang/String;
Asciz	<init>;
Asciz	(Ljava/lang/String;)V;
NameAndType	"<init>":(Ljava/lang/String;)V
Method	scala/MatchError."<init>":(Ljava/lang/String;)V
Asciz	java/lang/Byte;
class	java/lang/Byte
Asciz	unboxToByte;
Asciz	(Ljava/lang/Object;)B;
NameAndType	unboxToByte:(Ljava/lang/Object;)B
Method	scala/runtime/BoxesRunTime.unboxToByte:(Ljava/lang/Object;)B
Asciz	isValidByte;
NameAndType	isValidByte:()Z
InterfaceMethod	scala/math/ScalaNumericConversions.isValidByte:()Z
Asciz	toByte;
Asciz	()B;
NameAndType	toByte:()B
InterfaceMethod	scala/math/ScalaNumericConversions.toByte:()B
Asciz	java/lang/Short;
class	java/lang/Short
Asciz	unboxToShort;
Asciz	(Ljava/lang/Object;)S;
NameAndType	unboxToShort:(Ljava/lang/Object;)S
Method	scala/runtime/BoxesRunTime.unboxToShort:(Ljava/lang/Object;)S
Asciz	isValidShort;
NameAndType	isValidShort:()Z
InterfaceMethod	scala/math/ScalaNumericConversions.isValidShort:()Z
Asciz	toShort;
Asciz	()S;
NameAndType	toShort:()S
InterfaceMethod	scala/math/ScalaNumericConversions.toShort:()S
Asciz	java/lang/Integer;
class	java/lang/Integer
Asciz	unboxToInt;
Asciz	(Ljava/lang/Object;)I;
NameAndType	unboxToInt:(Ljava/lang/Object;)I
Method	scala/runtime/BoxesRunTime.unboxToInt:(Ljava/lang/Object;)I
Asciz	isValidInt;
NameAndType	isValidInt:()Z
InterfaceMethod	scala/math/ScalaNumericConversions.isValidInt:()Z
Asciz	java/lang/Long;
class	java/lang/Long
Asciz	unboxToLong;
Asciz	(Ljava/lang/Object;)J;
NameAndType	unboxToLong:(Ljava/lang/Object;)J
Method	scala/runtime/BoxesRunTime.unboxToLong:(Ljava/lang/Object;)J
Asciz	toLong;
Asciz	()J;
NameAndType	toLong:()J
InterfaceMethod	scala/math/ScalaNumericConversions.toLong:()J
Asciz	java/lang/Float;
class	java/lang/Float
Asciz	unboxToFloat;
Asciz	(Ljava/lang/Object;)F;
NameAndType	unboxToFloat:(Ljava/lang/Object;)F
Method	scala/runtime/BoxesRunTime.unboxToFloat:(Ljava/lang/Object;)F
Asciz	toFloat;
Asciz	()F;
NameAndType	toFloat:()F
InterfaceMethod	scala/math/ScalaNumericConversions.toFloat:()F
Asciz	java/lang/Double;
class	java/lang/Double
Asciz	unboxToDouble;
Asciz	(Ljava/lang/Object;)D;
NameAndType	unboxToDouble:(Ljava/lang/Object;)D
Method	scala/runtime/BoxesRunTime.unboxToDouble:(Ljava/lang/Object;)D
Asciz	toDouble;
Asciz	()D;
NameAndType	toDouble:()D
InterfaceMethod	scala/math/ScalaNumericConversions.toDouble:()D
Asciz	java/lang/Number;
class	java/lang/Number
Asciz	equals;
Asciz	(Ljava/lang/Object;)Z;
NameAndType	equals:(Ljava/lang/Object;)Z
Method	java/lang/Object.equals:(Ljava/lang/Object;)Z
Asciz	x;
Asciz	Ljava/lang/Object;;
Asciz	temp2;
Asciz	C;
Asciz	temp3;
Asciz	B;
Asciz	temp4;
Asciz	S;
Asciz	temp5;
Asciz	I;
Asciz	temp6;
Asciz	J;
Asciz	temp7;
Asciz	F;
Asciz	temp8;
Asciz	D;
Asciz	temp9;
Asciz	Ljava/lang/Number;;
Asciz	unifiedPrimitiveHashcode;
Asciz	(Lscala/math/ScalaNumericConversions;)I;
long	-2147483648l;
long	2147483647l;
Asciz	boxToLong;
Asciz	(J)Ljava/lang/Long;;
NameAndType	boxToLong:(J)Ljava/lang/Long;
Method	scala/runtime/BoxesRunTime.boxToLong:(J)Ljava/lang/Long;
Asciz	hashCode;
NameAndType	hashCode:()I
Method	java/lang/Object.hashCode:()I
Asciz	lv;
Asciz	(Lscala/math/ScalaNumericConversions;)Z;
Asciz	scala/math/ScalaNumber;
class	scala/math/ScalaNumber
Asciz	isWhole;
NameAndType	isWhole:()Z
Method	scala/math/ScalaNumber.isWhole:()Z
int	65535;
Asciz	(Lscala/math/ScalaNumericConversions;)D;
Asciz	doubleValue;
NameAndType	doubleValue:()D
Method	java/lang/Number.doubleValue:()D
Asciz	(Lscala/math/ScalaNumericConversions;)F;
Asciz	floatValue;
NameAndType	floatValue:()F
Method	java/lang/Number.floatValue:()F
Asciz	(Lscala/math/ScalaNumericConversions;)J;
Asciz	longValue;
NameAndType	longValue:()J
Method	java/lang/Number.longValue:()J
Asciz	intValue;
NameAndType	intValue:()I
Method	java/lang/Number.intValue:()I
Asciz	(Lscala/math/ScalaNumericConversions;)S;
Asciz	shortValue;
NameAndType	shortValue:()S
Method	java/lang/Number.shortValue:()S
Asciz	(Lscala/math/ScalaNumericConversions;)B;
Asciz	byteValue;
NameAndType	byteValue:()B
Method	java/lang/Number.byteValue:()B
Asciz	toChar;
Asciz	(Lscala/math/ScalaNumericConversions;)C;
Asciz	Scala;
Asciz	scala/math/ScalaNumericConversions$class;
class	scala/math/ScalaNumericConversions$class

{
public static void $init$(scala.math.ScalaNumericConversions);
  Signature: (Lscala/math/ScalaNumericConversions;)V
  Code:
   Stack=0, Locals=1, Args_size=1
	return
  Labels:
  LocalVariableTable: 
   Start  Length  Slot  Name   Signature
   0      1      0    $this       Lscala/math/ScalaNumericConversions;


public static boolean unifiedPrimitiveEquals(scala.math.ScalaNumericConversions, java.lang.Object);
  Signature: (Lscala/math/ScalaNumericConversions;Ljava/lang/Object;)Z
  Code:
   Stack=4, Locals=12, Args_size=2
	aload_1
	instanceof	class java/lang/Character
	ifeq	l1 // aload_1
	aload_1
	invokestatic	Method scala/runtime/BoxesRunTime.unboxToChar:(Ljava/lang/Object;)C
	istore_2
	iconst_1
	ifeq	l2 // new
	aload_0
	invokeinterface	InterfaceMethod scala/math/ScalaNumericConversions.isValidChar:()Z
	ifeq	l3 // iconst_0
	aload_0
	invokeinterface	InterfaceMethod scala/math/ScalaNumericConversions.toInt:()I
	iload_2
	if_icmpne	l3 // iconst_0
	iconst_1
	goto	l4 // ireturn
l3	iconst_0
	goto	l4 // ireturn
l2	new	class scala/MatchError
	dup
	aload_1
	invokevirtual	Method java/lang/Object.toString:()Ljava/lang/String;
	invokespecial	Method scala/MatchError."<init>":(Ljava/lang/String;)V
	athrow
l1	aload_1
	instanceof	class java/lang/Byte
	ifeq	l5 // aload_1
	aload_1
	invokestatic	Method scala/runtime/BoxesRunTime.unboxToByte:(Ljava/lang/Object;)B
	istore_3
	iconst_1
	ifeq	l6 // new
	aload_0
	invokeinterface	InterfaceMethod scala/math/ScalaNumericConversions.isValidByte:()Z
	ifeq	l7 // iconst_0
	aload_0
	invokeinterface	InterfaceMethod scala/math/ScalaNumericConversions.toByte:()B
	iload_3
	if_icmpne	l7 // iconst_0
	iconst_1
	goto	l4 // ireturn
l7	iconst_0
	goto	l4 // ireturn
l6	new	class scala/MatchError
	dup
	aload_1
	invokevirtual	Method java/lang/Object.toString:()Ljava/lang/String;
	invokespecial	Method scala/MatchError."<init>":(Ljava/lang/String;)V
	athrow
l5	aload_1
	instanceof	class java/lang/Short
	ifeq	l8 // aload_1
	aload_1
	invokestatic	Method scala/runtime/BoxesRunTime.unboxToShort:(Ljava/lang/Object;)S
	istore	4
	iconst_1
	ifeq	l9 // new
	aload_0
	invokeinterface	InterfaceMethod scala/math/ScalaNumericConversions.isValidShort:()Z
	ifeq	l10 // iconst_0
	aload_0
	invokeinterface	InterfaceMethod scala/math/ScalaNumericConversions.toShort:()S
	iload	4
	if_icmpne	l10 // iconst_0
	iconst_1
	goto	l4 // ireturn
l10	iconst_0
	goto	l4 // ireturn
l9	new	class scala/MatchError
	dup
	aload_1
	invokevirtual	Method java/lang/Object.toString:()Ljava/lang/String;
	invokespecial	Method scala/MatchError."<init>":(Ljava/lang/String;)V
	athrow
l8	aload_1
	instanceof	class java/lang/Integer
	ifeq	l11 // aload_1
	aload_1
	invokestatic	Method scala/runtime/BoxesRunTime.unboxToInt:(Ljava/lang/Object;)I
	istore	5
	iconst_1
	ifeq	l12 // new
	aload_0
	invokeinterface	InterfaceMethod scala/math/ScalaNumericConversions.isValidInt:()Z
	ifeq	l13 // iconst_0
	aload_0
	invokeinterface	InterfaceMethod scala/math/ScalaNumericConversions.toInt:()I
	iload	5
	if_icmpne	l13 // iconst_0
	iconst_1
	goto	l4 // ireturn
l13	iconst_0
	goto	l4 // ireturn
l12	new	class scala/MatchError
	dup
	aload_1
	invokevirtual	Method java/lang/Object.toString:()Ljava/lang/String;
	invokespecial	Method scala/MatchError."<init>":(Ljava/lang/String;)V
	athrow
l11	aload_1
	instanceof	class java/lang/Long
	ifeq	l14 // aload_1
	aload_1
	invokestatic	Method scala/runtime/BoxesRunTime.unboxToLong:(Ljava/lang/Object;)J
	lstore	6
	iconst_1
	ifeq	l15 // new
	aload_0
	invokeinterface	InterfaceMethod scala/math/ScalaNumericConversions.toLong:()J
	lload	6
	lcmp
	ifne	l16 // iconst_0
	iconst_1
	goto	l4 // ireturn
l16	iconst_0
	goto	l4 // ireturn
l15	new	class scala/MatchError
	dup
	aload_1
	invokevirtual	Method java/lang/Object.toString:()Ljava/lang/String;
	invokespecial	Method scala/MatchError."<init>":(Ljava/lang/String;)V
	athrow
l14	aload_1
	instanceof	class java/lang/Float
	ifeq	l17 // aload_1
	aload_1
	invokestatic	Method scala/runtime/BoxesRunTime.unboxToFloat:(Ljava/lang/Object;)F
	fstore	8
	iconst_1
	ifeq	l18 // new
	aload_0
	invokeinterface	InterfaceMethod scala/math/ScalaNumericConversions.toFloat:()F
	fload	8
	fcmpl
	ifne	l19 // iconst_0
	iconst_1
	goto	l4 // ireturn
l19	iconst_0
	goto	l4 // ireturn
l18	new	class scala/MatchError
	dup
	aload_1
	invokevirtual	Method java/lang/Object.toString:()Ljava/lang/String;
	invokespecial	Method scala/MatchError."<init>":(Ljava/lang/String;)V
	athrow
l17	aload_1
	instanceof	class java/lang/Double
	ifeq	l20 // aload_1
	aload_1
	invokestatic	Method scala/runtime/BoxesRunTime.unboxToDouble:(Ljava/lang/Object;)D
	dstore	9
	iconst_1
	ifeq	l21 // new
	aload_0
	invokeinterface	InterfaceMethod scala/math/ScalaNumericConversions.toDouble:()D
	dload	9
	dcmpl
	ifne	l22 // iconst_0
	iconst_1
	goto	l4 // ireturn
l22	iconst_0
	goto	l4 // ireturn
l21	new	class scala/MatchError
	dup
	aload_1
	invokevirtual	Method java/lang/Object.toString:()Ljava/lang/String;
	invokespecial	Method scala/MatchError."<init>":(Ljava/lang/String;)V
	athrow
l20	aload_1
	instanceof	class java/lang/Number
	ifeq	l23 // iconst_1
	aload_1
	checkcast	class java/lang/Number
	astore	11
	iconst_1
	ifeq	l24 // new
	aload_0
	aload	11
	invokevirtual	Method java/lang/Object.equals:(Ljava/lang/Object;)Z
	goto	l4 // ireturn
l24	new	class scala/MatchError
	dup
	aload_1
	invokevirtual	Method java/lang/Object.toString:()Ljava/lang/String;
	invokespecial	Method scala/MatchError."<init>":(Ljava/lang/String;)V
	athrow
l23	iconst_1
	ifeq	l25 // new
	iconst_0
l4	ireturn
l25	new	class scala/MatchError
	dup
	aload_1
	invokevirtual	Method java/lang/Object.toString:()Ljava/lang/String;
	invokespecial	Method scala/MatchError."<init>":(Ljava/lang/String;)V
	athrow
  Labels:
   	l3 = 39 // iconst_0
   	l2 = 43 // new
   	l1 = 55 // aload_1
   	l7 = 94 // iconst_0
   	l6 = 98 // new
   	l5 = 110 // aload_1
   	l10 = 151 // iconst_0
   	l9 = 155 // new
   	l8 = 167 // aload_1
   	l13 = 208 // iconst_0
   	l12 = 212 // new
   	l11 = 224 // aload_1
   	l16 = 257 // iconst_0
   	l15 = 261 // new
   	l14 = 273 // aload_1
   	l19 = 306 // iconst_0
   	l18 = 310 // new
   	l17 = 322 // aload_1
   	l22 = 355 // iconst_0
   	l21 = 359 // new
   	l20 = 371 // aload_1
   	l24 = 397 // new
   	l23 = 409 // iconst_1
   	l4 = 414 // ireturn
   	l25 = 415 // new
  LocalVariableTable: 
   Start  Length  Slot  Name   Signature
   0      427      0    $this       Lscala/math/ScalaNumericConversions;
   0      427      1    x       Ljava/lang/Object;
   12      43      2    temp2       C
   67      43      3    temp3       B
   123      44      4    temp4       S
   180      44      5    temp5       I
   237      36      6    temp6       J
   286      36      8    temp7       F
   335      36      9    temp8       D
   384      25      11    temp9       Ljava/lang/Number;


public static int unifiedPrimitiveHashcode(scala.math.ScalaNumericConversions);
  Signature: (Lscala/math/ScalaNumericConversions;)I
  Code:
   Stack=4, Locals=3, Args_size=1
	aload_0
	invokeinterface	InterfaceMethod scala/math/ScalaNumericConversions.toLong:()J
	lstore_1
	lload_1
	ldc2_w	long -2147483648l
	lcmp
	iflt	l1 // lload_1
	lload_1
	ldc2_w	long 2147483647l
	lcmp
	ifgt	l1 // lload_1
	lload_1
	l2i
	goto	l2 // ireturn
l1	lload_1
	invokestatic	Method scala/runtime/BoxesRunTime.boxToLong:(J)Ljava/lang/Long;
	invokevirtual	Method java/lang/Object.hashCode:()I
l2	ireturn
  Labels:
   	l1 = 28 // lload_1
   	l2 = 35 // ireturn
  LocalVariableTable: 
   Start  Length  Slot  Name   Signature
   0      36      0    $this       Lscala/math/ScalaNumericConversions;
   7      29      1    lv       J


public static boolean isValidChar(scala.math.ScalaNumericConversions);
  Signature: (Lscala/math/ScalaNumericConversions;)Z
  Code:
   Stack=2, Locals=1, Args_size=1
	aload_0
	checkcast	class scala/math/ScalaNumber
	invokevirtual	Method scala/math/ScalaNumber.isWhole:()Z
	ifeq	l1 // iconst_0
	aload_0
	invokeinterface	InterfaceMethod scala/math/ScalaNumericConversions.toInt:()I
	iconst_0
	if_icmplt	l1 // iconst_0
	aload_0
	invokeinterface	InterfaceMethod scala/math/ScalaNumericConversions.toInt:()I
	ldc	int 65535
	if_icmpgt	l1 // iconst_0
	iconst_1
	goto	l2 // ireturn
l1	iconst_0
l2	ireturn
  Labels:
   	l1 = 35 // iconst_0
   	l2 = 36 // ireturn
  LocalVariableTable: 
   Start  Length  Slot  Name   Signature
   0      37      0    $this       Lscala/math/ScalaNumericConversions;


public static boolean isValidInt(scala.math.ScalaNumericConversions);
  Signature: (Lscala/math/ScalaNumericConversions;)Z
  Code:
   Stack=4, Locals=1, Args_size=1
	aload_0
	checkcast	class scala/math/ScalaNumber
	invokevirtual	Method scala/math/ScalaNumber.isWhole:()Z
	ifeq	l1 // iconst_0
	aload_0
	invokeinterface	InterfaceMethod scala/math/ScalaNumericConversions.toInt:()I
	i2l
	aload_0
	invokeinterface	InterfaceMethod scala/math/ScalaNumericConversions.toLong:()J
	lcmp
	ifne	l1 // iconst_0
	iconst_1
	goto	l2 // ireturn
l1	iconst_0
l2	ireturn
  Labels:
   	l1 = 31 // iconst_0
   	l2 = 32 // ireturn
  LocalVariableTable: 
   Start  Length  Slot  Name   Signature
   0      33      0    $this       Lscala/math/ScalaNumericConversions;


public static boolean isValidShort(scala.math.ScalaNumericConversions);
  Signature: (Lscala/math/ScalaNumericConversions;)Z
  Code:
   Stack=2, Locals=1, Args_size=1
	aload_0
	checkcast	class scala/math/ScalaNumber
	invokevirtual	Method scala/math/ScalaNumber.isWhole:()Z
	ifeq	l1 // iconst_0
	aload_0
	invokeinterface	InterfaceMethod scala/math/ScalaNumericConversions.toShort:()S
	aload_0
	invokeinterface	InterfaceMethod scala/math/ScalaNumericConversions.toInt:()I
	if_icmpne	l1 // iconst_0
	iconst_1
	goto	l2 // ireturn
l1	iconst_0
l2	ireturn
  Labels:
   	l1 = 29 // iconst_0
   	l2 = 30 // ireturn
  LocalVariableTable: 
   Start  Length  Slot  Name   Signature
   0      31      0    $this       Lscala/math/ScalaNumericConversions;


public static boolean isValidByte(scala.math.ScalaNumericConversions);
  Signature: (Lscala/math/ScalaNumericConversions;)Z
  Code:
   Stack=2, Locals=1, Args_size=1
	aload_0
	checkcast	class scala/math/ScalaNumber
	invokevirtual	Method scala/math/ScalaNumber.isWhole:()Z
	ifeq	l1 // iconst_0
	aload_0
	invokeinterface	InterfaceMethod scala/math/ScalaNumericConversions.toByte:()B
	aload_0
	invokeinterface	InterfaceMethod scala/math/ScalaNumericConversions.toInt:()I
	if_icmpne	l1 // iconst_0
	iconst_1
	goto	l2 // ireturn
l1	iconst_0
l2	ireturn
  Labels:
   	l1 = 29 // iconst_0
   	l2 = 30 // ireturn
  LocalVariableTable: 
   Start  Length  Slot  Name   Signature
   0      31      0    $this       Lscala/math/ScalaNumericConversions;


public static double toDouble(scala.math.ScalaNumericConversions);
  Signature: (Lscala/math/ScalaNumericConversions;)D
  Code:
   Stack=2, Locals=1, Args_size=1
	aload_0
	checkcast	class java/lang/Number
	invokevirtual	Method java/lang/Number.doubleValue:()D
	dreturn
  Labels:
  LocalVariableTable: 
   Start  Length  Slot  Name   Signature
   0      8      0    $this       Lscala/math/ScalaNumericConversions;


public static float toFloat(scala.math.ScalaNumericConversions);
  Signature: (Lscala/math/ScalaNumericConversions;)F
  Code:
   Stack=1, Locals=1, Args_size=1
	aload_0
	checkcast	class java/lang/Number
	invokevirtual	Method java/lang/Number.floatValue:()F
	freturn
  Labels:
  LocalVariableTable: 
   Start  Length  Slot  Name   Signature
   0      8      0    $this       Lscala/math/ScalaNumericConversions;


public static long toLong(scala.math.ScalaNumericConversions);
  Signature: (Lscala/math/ScalaNumericConversions;)J
  Code:
   Stack=2, Locals=1, Args_size=1
	aload_0
	checkcast	class java/lang/Number
	invokevirtual	Method java/lang/Number.longValue:()J
	lreturn
  Labels:
  LocalVariableTable: 
   Start  Length  Slot  Name   Signature
   0      8      0    $this       Lscala/math/ScalaNumericConversions;


public static int toInt(scala.math.ScalaNumericConversions);
  Signature: (Lscala/math/ScalaNumericConversions;)I
  Code:
   Stack=1, Locals=1, Args_size=1
	aload_0
	checkcast	class java/lang/Number
	invokevirtual	Method java/lang/Number.intValue:()I
	ireturn
  Labels:
  LocalVariableTable: 
   Start  Length  Slot  Name   Signature
   0      8      0    $this       Lscala/math/ScalaNumericConversions;


public static short toShort(scala.math.ScalaNumericConversions);
  Signature: (Lscala/math/ScalaNumericConversions;)S
  Code:
   Stack=1, Locals=1, Args_size=1
	aload_0
	checkcast	class java/lang/Number
	invokevirtual	Method java/lang/Number.shortValue:()S
	ireturn
  Labels:
  LocalVariableTable: 
   Start  Length  Slot  Name   Signature
   0      8      0    $this       Lscala/math/ScalaNumericConversions;


public static byte toByte(scala.math.ScalaNumericConversions);
  Signature: (Lscala/math/ScalaNumericConversions;)B
  Code:
   Stack=1, Locals=1, Args_size=1
	aload_0
	checkcast	class java/lang/Number
	invokevirtual	Method java/lang/Number.byteValue:()B
	ireturn
  Labels:
  LocalVariableTable: 
   Start  Length  Slot  Name   Signature
   0      8      0    $this       Lscala/math/ScalaNumericConversions;


public static char toChar(scala.math.ScalaNumericConversions);
  Signature: (Lscala/math/ScalaNumericConversions;)C
  Code:
   Stack=1, Locals=1, Args_size=1
	aload_0
	checkcast	class java/lang/Number
	invokevirtual	Method java/lang/Number.intValue:()I
	i2c
	ireturn
  Labels:
  LocalVariableTable: 
   Start  Length  Slot  Name   Signature
   0      9      0    $this       Lscala/math/ScalaNumericConversions;


}

