Compiled from "ScalaNumericConversions.scala"
public abstract class scala.math.ScalaNumericConversions$class extends java.lang.Object
  SourceFile: "ScalaNumericConversions.scala"
  Scala: length = 0x
   
  minor version: 0
  major version: 49
  Constant pool:
const #1 = Asciz	SourceFile;
const #2 = Asciz	ScalaNumericConversions.scala;
const #3 = Asciz	$init$;
const #4 = Asciz	(Lscala/math/ScalaNumericConversions;)V;
const #5 = Asciz	Code;
const #6 = Asciz	LineNumberTable;
const #7 = Asciz	$this;
const #8 = Asciz	Lscala/math/ScalaNumericConversions;;
const #9 = Asciz	LocalVariableTable;
const #10 = Asciz	unifiedPrimitiveEquals;
const #11 = Asciz	(Lscala/math/ScalaNumericConversions;Ljava/lang/Object;)Z;
const #12 = Asciz	java/lang/Character;
const #13 = class	#12;	//  java/lang/Character
const #14 = Asciz	scala/runtime/BoxesRunTime;
const #15 = class	#14;	//  scala/runtime/BoxesRunTime
const #16 = Asciz	unboxToChar;
const #17 = Asciz	(Ljava/lang/Object;)C;
const #18 = NameAndType	#16:#17;//  unboxToChar:(Ljava/lang/Object;)C
const #19 = Method	#15.#18;	//  scala/runtime/BoxesRunTime.unboxToChar:(Ljava/lang/Object;)C
const #20 = Asciz	scala/math/ScalaNumericConversions;
const #21 = class	#20;	//  scala/math/ScalaNumericConversions
const #22 = Asciz	isValidChar;
const #23 = Asciz	()Z;
const #24 = NameAndType	#22:#23;//  isValidChar:()Z
const #25 = InterfaceMethod	#21.#24;	//  scala/math/ScalaNumericConversions.isValidChar:()Z
const #26 = Asciz	toInt;
const #27 = Asciz	()I;
const #28 = NameAndType	#26:#27;//  toInt:()I
const #29 = InterfaceMethod	#21.#28;	//  scala/math/ScalaNumericConversions.toInt:()I
const #30 = Asciz	scala/MatchError;
const #31 = class	#30;	//  scala/MatchError
const #32 = Asciz	java/lang/Object;
const #33 = class	#32;	//  java/lang/Object
const #34 = Asciz	toString;
const #35 = Asciz	()Ljava/lang/String;;
const #36 = NameAndType	#34:#35;//  toString:()Ljava/lang/String;
const #37 = Method	#33.#36;	//  java/lang/Object.toString:()Ljava/lang/String;
const #38 = Asciz	<init>;
const #39 = Asciz	(Ljava/lang/String;)V;
const #40 = NameAndType	#38:#39;//  "<init>":(Ljava/lang/String;)V
const #41 = Method	#31.#40;	//  scala/MatchError."<init>":(Ljava/lang/String;)V
const #42 = Asciz	java/lang/Byte;
const #43 = class	#42;	//  java/lang/Byte
const #44 = Asciz	unboxToByte;
const #45 = Asciz	(Ljava/lang/Object;)B;
const #46 = NameAndType	#44:#45;//  unboxToByte:(Ljava/lang/Object;)B
const #47 = Method	#15.#46;	//  scala/runtime/BoxesRunTime.unboxToByte:(Ljava/lang/Object;)B
const #48 = Asciz	isValidByte;
const #49 = NameAndType	#48:#23;//  isValidByte:()Z
const #50 = InterfaceMethod	#21.#49;	//  scala/math/ScalaNumericConversions.isValidByte:()Z
const #51 = Asciz	toByte;
const #52 = Asciz	()B;
const #53 = NameAndType	#51:#52;//  toByte:()B
const #54 = InterfaceMethod	#21.#53;	//  scala/math/ScalaNumericConversions.toByte:()B
const #55 = Asciz	java/lang/Short;
const #56 = class	#55;	//  java/lang/Short
const #57 = Asciz	unboxToShort;
const #58 = Asciz	(Ljava/lang/Object;)S;
const #59 = NameAndType	#57:#58;//  unboxToShort:(Ljava/lang/Object;)S
const #60 = Method	#15.#59;	//  scala/runtime/BoxesRunTime.unboxToShort:(Ljava/lang/Object;)S
const #61 = Asciz	isValidShort;
const #62 = NameAndType	#61:#23;//  isValidShort:()Z
const #63 = InterfaceMethod	#21.#62;	//  scala/math/ScalaNumericConversions.isValidShort:()Z
const #64 = Asciz	toShort;
const #65 = Asciz	()S;
const #66 = NameAndType	#64:#65;//  toShort:()S
const #67 = InterfaceMethod	#21.#66;	//  scala/math/ScalaNumericConversions.toShort:()S
const #68 = Asciz	java/lang/Integer;
const #69 = class	#68;	//  java/lang/Integer
const #70 = Asciz	unboxToInt;
const #71 = Asciz	(Ljava/lang/Object;)I;
const #72 = NameAndType	#70:#71;//  unboxToInt:(Ljava/lang/Object;)I
const #73 = Method	#15.#72;	//  scala/runtime/BoxesRunTime.unboxToInt:(Ljava/lang/Object;)I
const #74 = Asciz	isValidInt;
const #75 = NameAndType	#74:#23;//  isValidInt:()Z
const #76 = InterfaceMethod	#21.#75;	//  scala/math/ScalaNumericConversions.isValidInt:()Z
const #77 = Asciz	java/lang/Long;
const #78 = class	#77;	//  java/lang/Long
const #79 = Asciz	unboxToLong;
const #80 = Asciz	(Ljava/lang/Object;)J;
const #81 = NameAndType	#79:#80;//  unboxToLong:(Ljava/lang/Object;)J
const #82 = Method	#15.#81;	//  scala/runtime/BoxesRunTime.unboxToLong:(Ljava/lang/Object;)J
const #83 = Asciz	toLong;
const #84 = Asciz	()J;
const #85 = NameAndType	#83:#84;//  toLong:()J
const #86 = InterfaceMethod	#21.#85;	//  scala/math/ScalaNumericConversions.toLong:()J
const #87 = Asciz	java/lang/Float;
const #88 = class	#87;	//  java/lang/Float
const #89 = Asciz	unboxToFloat;
const #90 = Asciz	(Ljava/lang/Object;)F;
const #91 = NameAndType	#89:#90;//  unboxToFloat:(Ljava/lang/Object;)F
const #92 = Method	#15.#91;	//  scala/runtime/BoxesRunTime.unboxToFloat:(Ljava/lang/Object;)F
const #93 = Asciz	toFloat;
const #94 = Asciz	()F;
const #95 = NameAndType	#93:#94;//  toFloat:()F
const #96 = InterfaceMethod	#21.#95;	//  scala/math/ScalaNumericConversions.toFloat:()F
const #97 = Asciz	java/lang/Double;
const #98 = class	#97;	//  java/lang/Double
const #99 = Asciz	unboxToDouble;
const #100 = Asciz	(Ljava/lang/Object;)D;
const #101 = NameAndType	#99:#100;//  unboxToDouble:(Ljava/lang/Object;)D
const #102 = Method	#15.#101;	//  scala/runtime/BoxesRunTime.unboxToDouble:(Ljava/lang/Object;)D
const #103 = Asciz	toDouble;
const #104 = Asciz	()D;
const #105 = NameAndType	#103:#104;//  toDouble:()D
const #106 = InterfaceMethod	#21.#105;	//  scala/math/ScalaNumericConversions.toDouble:()D
const #107 = Asciz	java/lang/Number;
const #108 = class	#107;	//  java/lang/Number
const #109 = Asciz	equals;
const #110 = Asciz	(Ljava/lang/Object;)Z;
const #111 = NameAndType	#109:#110;//  equals:(Ljava/lang/Object;)Z
const #112 = Method	#33.#111;	//  java/lang/Object.equals:(Ljava/lang/Object;)Z
const #113 = Asciz	x;
const #114 = Asciz	Ljava/lang/Object;;
const #115 = Asciz	temp2;
const #116 = Asciz	C;
const #117 = Asciz	temp3;
const #118 = Asciz	B;
const #119 = Asciz	temp4;
const #120 = Asciz	S;
const #121 = Asciz	temp5;
const #122 = Asciz	I;
const #123 = Asciz	temp6;
const #124 = Asciz	J;
const #125 = Asciz	temp7;
const #126 = Asciz	F;
const #127 = Asciz	temp8;
const #128 = Asciz	D;
const #129 = Asciz	temp9;
const #130 = Asciz	Ljava/lang/Number;;
const #131 = Asciz	unifiedPrimitiveHashcode;
const #132 = Asciz	(Lscala/math/ScalaNumericConversions;)I;
const #133 = long	-2147483648l;
const #135 = long	2147483647l;
const #137 = Asciz	boxToLong;
const #138 = Asciz	(J)Ljava/lang/Long;;
const #139 = NameAndType	#137:#138;//  boxToLong:(J)Ljava/lang/Long;
const #140 = Method	#15.#139;	//  scala/runtime/BoxesRunTime.boxToLong:(J)Ljava/lang/Long;
const #141 = Asciz	hashCode;
const #142 = NameAndType	#141:#27;//  hashCode:()I
const #143 = Method	#33.#142;	//  java/lang/Object.hashCode:()I
const #144 = Asciz	lv;
const #145 = Asciz	(Lscala/math/ScalaNumericConversions;)Z;
const #146 = Asciz	scala/math/ScalaNumber;
const #147 = class	#146;	//  scala/math/ScalaNumber
const #148 = Asciz	isWhole;
const #149 = NameAndType	#148:#23;//  isWhole:()Z
const #150 = Method	#147.#149;	//  scala/math/ScalaNumber.isWhole:()Z
const #151 = int	65535;
const #152 = Asciz	(Lscala/math/ScalaNumericConversions;)D;
const #153 = Asciz	doubleValue;
const #154 = NameAndType	#153:#104;//  doubleValue:()D
const #155 = Method	#108.#154;	//  java/lang/Number.doubleValue:()D
const #156 = Asciz	(Lscala/math/ScalaNumericConversions;)F;
const #157 = Asciz	floatValue;
const #158 = NameAndType	#157:#94;//  floatValue:()F
const #159 = Method	#108.#158;	//  java/lang/Number.floatValue:()F
const #160 = Asciz	(Lscala/math/ScalaNumericConversions;)J;
const #161 = Asciz	longValue;
const #162 = NameAndType	#161:#84;//  longValue:()J
const #163 = Method	#108.#162;	//  java/lang/Number.longValue:()J
const #164 = Asciz	intValue;
const #165 = NameAndType	#164:#27;//  intValue:()I
const #166 = Method	#108.#165;	//  java/lang/Number.intValue:()I
const #167 = Asciz	(Lscala/math/ScalaNumericConversions;)S;
const #168 = Asciz	shortValue;
const #169 = NameAndType	#168:#65;//  shortValue:()S
const #170 = Method	#108.#169;	//  java/lang/Number.shortValue:()S
const #171 = Asciz	(Lscala/math/ScalaNumericConversions;)B;
const #172 = Asciz	byteValue;
const #173 = NameAndType	#172:#52;//  byteValue:()B
const #174 = Method	#108.#173;	//  java/lang/Number.byteValue:()B
const #175 = Asciz	toChar;
const #176 = Asciz	(Lscala/math/ScalaNumericConversions;)C;
const #177 = Asciz	Scala;
const #178 = Asciz	scala/math/ScalaNumericConversions$class;
const #179 = class	#178;	//  scala/math/ScalaNumericConversions$class

{
public static void $init$(scala.math.ScalaNumericConversions);
  Code:
   Stack=0, Locals=1, Args_size=1
   0:	return
  LineNumberTable: 
   line 16: 0

  LocalVariableTable: 
   Start  Length  Slot  Name   Signature
   0      1      0    $this       Lscala/math/ScalaNumericConversions;


public static boolean unifiedPrimitiveEquals(scala.math.ScalaNumericConversions, java.lang.Object);
  Code:
   Stack=4, Locals=12, Args_size=2
   0:	aload_1
   1:	instanceof	#13; //class java/lang/Character
   4:	ifeq	55
   7:	aload_1
   8:	invokestatic	#19; //Method scala/runtime/BoxesRunTime.unboxToChar:(Ljava/lang/Object;)C
   11:	istore_2
   12:	iconst_1
   13:	ifeq	43
   16:	aload_0
   17:	invokeinterface	#25,  1; //InterfaceMethod scala/math/ScalaNumericConversions.isValidChar:()Z
   22:	ifeq	39
   25:	aload_0
   26:	invokeinterface	#29,  1; //InterfaceMethod scala/math/ScalaNumericConversions.toInt:()I
   31:	iload_2
   32:	if_icmpne	39
   35:	iconst_1
   36:	goto	414
   39:	iconst_0
   40:	goto	414
   43:	new	#31; //class scala/MatchError
   46:	dup
   47:	aload_1
   48:	invokevirtual	#37; //Method java/lang/Object.toString:()Ljava/lang/String;
   51:	invokespecial	#41; //Method scala/MatchError."<init>":(Ljava/lang/String;)V
   54:	athrow
   55:	aload_1
   56:	instanceof	#43; //class java/lang/Byte
   59:	ifeq	110
   62:	aload_1
   63:	invokestatic	#47; //Method scala/runtime/BoxesRunTime.unboxToByte:(Ljava/lang/Object;)B
   66:	istore_3
   67:	iconst_1
   68:	ifeq	98
   71:	aload_0
   72:	invokeinterface	#50,  1; //InterfaceMethod scala/math/ScalaNumericConversions.isValidByte:()Z
   77:	ifeq	94
   80:	aload_0
   81:	invokeinterface	#54,  1; //InterfaceMethod scala/math/ScalaNumericConversions.toByte:()B
   86:	iload_3
   87:	if_icmpne	94
   90:	iconst_1
   91:	goto	414
   94:	iconst_0
   95:	goto	414
   98:	new	#31; //class scala/MatchError
   101:	dup
   102:	aload_1
   103:	invokevirtual	#37; //Method java/lang/Object.toString:()Ljava/lang/String;
   106:	invokespecial	#41; //Method scala/MatchError."<init>":(Ljava/lang/String;)V
   109:	athrow
   110:	aload_1
   111:	instanceof	#56; //class java/lang/Short
   114:	ifeq	167
   117:	aload_1
   118:	invokestatic	#60; //Method scala/runtime/BoxesRunTime.unboxToShort:(Ljava/lang/Object;)S
   121:	istore	4
   123:	iconst_1
   124:	ifeq	155
   127:	aload_0
   128:	invokeinterface	#63,  1; //InterfaceMethod scala/math/ScalaNumericConversions.isValidShort:()Z
   133:	ifeq	151
   136:	aload_0
   137:	invokeinterface	#67,  1; //InterfaceMethod scala/math/ScalaNumericConversions.toShort:()S
   142:	iload	4
   144:	if_icmpne	151
   147:	iconst_1
   148:	goto	414
   151:	iconst_0
   152:	goto	414
   155:	new	#31; //class scala/MatchError
   158:	dup
   159:	aload_1
   160:	invokevirtual	#37; //Method java/lang/Object.toString:()Ljava/lang/String;
   163:	invokespecial	#41; //Method scala/MatchError."<init>":(Ljava/lang/String;)V
   166:	athrow
   167:	aload_1
   168:	instanceof	#69; //class java/lang/Integer
   171:	ifeq	224
   174:	aload_1
   175:	invokestatic	#73; //Method scala/runtime/BoxesRunTime.unboxToInt:(Ljava/lang/Object;)I
   178:	istore	5
   180:	iconst_1
   181:	ifeq	212
   184:	aload_0
   185:	invokeinterface	#76,  1; //InterfaceMethod scala/math/ScalaNumericConversions.isValidInt:()Z
   190:	ifeq	208
   193:	aload_0
   194:	invokeinterface	#29,  1; //InterfaceMethod scala/math/ScalaNumericConversions.toInt:()I
   199:	iload	5
   201:	if_icmpne	208
   204:	iconst_1
   205:	goto	414
   208:	iconst_0
   209:	goto	414
   212:	new	#31; //class scala/MatchError
   215:	dup
   216:	aload_1
   217:	invokevirtual	#37; //Method java/lang/Object.toString:()Ljava/lang/String;
   220:	invokespecial	#41; //Method scala/MatchError."<init>":(Ljava/lang/String;)V
   223:	athrow
   224:	aload_1
   225:	instanceof	#78; //class java/lang/Long
   228:	ifeq	273
   231:	aload_1
   232:	invokestatic	#82; //Method scala/runtime/BoxesRunTime.unboxToLong:(Ljava/lang/Object;)J
   235:	lstore	6
   237:	iconst_1
   238:	ifeq	261
   241:	aload_0
   242:	invokeinterface	#86,  1; //InterfaceMethod scala/math/ScalaNumericConversions.toLong:()J
   247:	lload	6
   249:	lcmp
   250:	ifne	257
   253:	iconst_1
   254:	goto	414
   257:	iconst_0
   258:	goto	414
   261:	new	#31; //class scala/MatchError
   264:	dup
   265:	aload_1
   266:	invokevirtual	#37; //Method java/lang/Object.toString:()Ljava/lang/String;
   269:	invokespecial	#41; //Method scala/MatchError."<init>":(Ljava/lang/String;)V
   272:	athrow
   273:	aload_1
   274:	instanceof	#88; //class java/lang/Float
   277:	ifeq	322
   280:	aload_1
   281:	invokestatic	#92; //Method scala/runtime/BoxesRunTime.unboxToFloat:(Ljava/lang/Object;)F
   284:	fstore	8
   286:	iconst_1
   287:	ifeq	310
   290:	aload_0
   291:	invokeinterface	#96,  1; //InterfaceMethod scala/math/ScalaNumericConversions.toFloat:()F
   296:	fload	8
   298:	fcmpl
   299:	ifne	306
   302:	iconst_1
   303:	goto	414
   306:	iconst_0
   307:	goto	414
   310:	new	#31; //class scala/MatchError
   313:	dup
   314:	aload_1
   315:	invokevirtual	#37; //Method java/lang/Object.toString:()Ljava/lang/String;
   318:	invokespecial	#41; //Method scala/MatchError."<init>":(Ljava/lang/String;)V
   321:	athrow
   322:	aload_1
   323:	instanceof	#98; //class java/lang/Double
   326:	ifeq	371
   329:	aload_1
   330:	invokestatic	#102; //Method scala/runtime/BoxesRunTime.unboxToDouble:(Ljava/lang/Object;)D
   333:	dstore	9
   335:	iconst_1
   336:	ifeq	359
   339:	aload_0
   340:	invokeinterface	#106,  1; //InterfaceMethod scala/math/ScalaNumericConversions.toDouble:()D
   345:	dload	9
   347:	dcmpl
   348:	ifne	355
   351:	iconst_1
   352:	goto	414
   355:	iconst_0
   356:	goto	414
   359:	new	#31; //class scala/MatchError
   362:	dup
   363:	aload_1
   364:	invokevirtual	#37; //Method java/lang/Object.toString:()Ljava/lang/String;
   367:	invokespecial	#41; //Method scala/MatchError."<init>":(Ljava/lang/String;)V
   370:	athrow
   371:	aload_1
   372:	instanceof	#108; //class java/lang/Number
   375:	ifeq	409
   378:	aload_1
   379:	checkcast	#108; //class java/lang/Number
   382:	astore	11
   384:	iconst_1
   385:	ifeq	397
   388:	aload_0
   389:	aload	11
   391:	invokevirtual	#112; //Method java/lang/Object.equals:(Ljava/lang/Object;)Z
   394:	goto	414
   397:	new	#31; //class scala/MatchError
   400:	dup
   401:	aload_1
   402:	invokevirtual	#37; //Method java/lang/Object.toString:()Ljava/lang/String;
   405:	invokespecial	#41; //Method scala/MatchError."<init>":(Ljava/lang/String;)V
   408:	athrow
   409:	iconst_1
   410:	ifeq	415
   413:	iconst_0
   414:	ireturn
   415:	new	#31; //class scala/MatchError
   418:	dup
   419:	aload_1
   420:	invokevirtual	#37; //Method java/lang/Object.toString:()Ljava/lang/String;
   423:	invokespecial	#41; //Method scala/MatchError."<init>":(Ljava/lang/String;)V
   426:	athrow
  LineNumberTable: 
   line 36: 0
   line 21: 12
   line 37: 16
   line 36: 43
   line 21: 67
   line 38: 71
   line 36: 98
   line 21: 123
   line 39: 127
   line 36: 155
   line 21: 180
   line 40: 184
   line 36: 212
   line 21: 237
   line 41: 241
   line 36: 261
   line 21: 286
   line 42: 290
   line 36: 310
   line 21: 335
   line 43: 339
   line 36: 359
   line 21: 384
   line 44: 388
   line 36: 397
   line 21: 409
   line 45: 413
   line 36: 414

  LocalVariableTable: 
   Start  Length  Slot  Name   Signature
   0      427      0    $this       Lscala/math/ScalaNumericConversions;
   0      427      1    x       Ljava/lang/Object;
   12      43      2    temp2       C
   67      43      3    temp3       B
   123      44      4    temp4       S
   180      44      5    temp5       I
   237      36      6    temp6       J
   286      36      8    temp7       F
   335      36      9    temp8       D
   384      25      11    temp9       Ljava/lang/Number;


public static int unifiedPrimitiveHashcode(scala.math.ScalaNumericConversions);
  Code:
   Stack=4, Locals=3, Args_size=1
   0:	aload_0
   1:	invokeinterface	#86,  1; //InterfaceMethod scala/math/ScalaNumericConversions.toLong:()J
   6:	lstore_1
   7:	lload_1
   8:	ldc2_w	#133; //long -2147483648l
   11:	lcmp
   12:	iflt	28
   15:	lload_1
   16:	ldc2_w	#135; //long 2147483647l
   19:	lcmp
   20:	ifgt	28
   23:	lload_1
   24:	l2i
   25:	goto	35
   28:	lload_1
   29:	invokestatic	#140; //Method scala/runtime/BoxesRunTime.boxToLong:(J)Ljava/lang/Long;
   32:	invokevirtual	#143; //Method java/lang/Object.hashCode:()I
   35:	ireturn
  LineNumberTable: 
   line 31: 0
   line 32: 7
   line 33: 28
   line 30: 35

  LocalVariableTable: 
   Start  Length  Slot  Name   Signature
   0      36      0    $this       Lscala/math/ScalaNumericConversions;
   7      29      1    lv       J


public static boolean isValidChar(scala.math.ScalaNumericConversions);
  Code:
   Stack=2, Locals=1, Args_size=1
   0:	aload_0
   1:	checkcast	#147; //class scala/math/ScalaNumber
   4:	invokevirtual	#150; //Method scala/math/ScalaNumber.isWhole:()Z
   7:	ifeq	35
   10:	aload_0
   11:	invokeinterface	#29,  1; //InterfaceMethod scala/math/ScalaNumericConversions.toInt:()I
   16:	iconst_0
   17:	if_icmplt	35
   20:	aload_0
   21:	invokeinterface	#29,  1; //InterfaceMethod scala/math/ScalaNumericConversions.toInt:()I
   26:	ldc	#151; //int 65535
   28:	if_icmpgt	35
   31:	iconst_1
   32:	goto	36
   35:	iconst_0
   36:	ireturn
  LineNumberTable: 
   line 28: 0

  LocalVariableTable: 
   Start  Length  Slot  Name   Signature
   0      37      0    $this       Lscala/math/ScalaNumericConversions;


public static boolean isValidInt(scala.math.ScalaNumericConversions);
  Code:
   Stack=4, Locals=1, Args_size=1
   0:	aload_0
   1:	checkcast	#147; //class scala/math/ScalaNumber
   4:	invokevirtual	#150; //Method scala/math/ScalaNumber.isWhole:()Z
   7:	ifeq	31
   10:	aload_0
   11:	invokeinterface	#29,  1; //InterfaceMethod scala/math/ScalaNumericConversions.toInt:()I
   16:	i2l
   17:	aload_0
   18:	invokeinterface	#86,  1; //InterfaceMethod scala/math/ScalaNumericConversions.toLong:()J
   23:	lcmp
   24:	ifne	31
   27:	iconst_1
   28:	goto	32
   31:	iconst_0
   32:	ireturn
  LineNumberTable: 
   line 27: 0

  LocalVariableTable: 
   Start  Length  Slot  Name   Signature
   0      33      0    $this       Lscala/math/ScalaNumericConversions;


public static boolean isValidShort(scala.math.ScalaNumericConversions);
  Code:
   Stack=2, Locals=1, Args_size=1
   0:	aload_0
   1:	checkcast	#147; //class scala/math/ScalaNumber
   4:	invokevirtual	#150; //Method scala/math/ScalaNumber.isWhole:()Z
   7:	ifeq	29
   10:	aload_0
   11:	invokeinterface	#67,  1; //InterfaceMethod scala/math/ScalaNumericConversions.toShort:()S
   16:	aload_0
   17:	invokeinterface	#29,  1; //InterfaceMethod scala/math/ScalaNumericConversions.toInt:()I
   22:	if_icmpne	29
   25:	iconst_1
   26:	goto	30
   29:	iconst_0
   30:	ireturn
  LineNumberTable: 
   line 26: 0

  LocalVariableTable: 
   Start  Length  Slot  Name   Signature
   0      31      0    $this       Lscala/math/ScalaNumericConversions;


public static boolean isValidByte(scala.math.ScalaNumericConversions);
  Code:
   Stack=2, Locals=1, Args_size=1
   0:	aload_0
   1:	checkcast	#147; //class scala/math/ScalaNumber
   4:	invokevirtual	#150; //Method scala/math/ScalaNumber.isWhole:()Z
   7:	ifeq	29
   10:	aload_0
   11:	invokeinterface	#54,  1; //InterfaceMethod scala/math/ScalaNumericConversions.toByte:()B
   16:	aload_0
   17:	invokeinterface	#29,  1; //InterfaceMethod scala/math/ScalaNumericConversions.toInt:()I
   22:	if_icmpne	29
   25:	iconst_1
   26:	goto	30
   29:	iconst_0
   30:	ireturn
  LineNumberTable: 
   line 25: 0

  LocalVariableTable: 
   Start  Length  Slot  Name   Signature
   0      31      0    $this       Lscala/math/ScalaNumericConversions;


public static double toDouble(scala.math.ScalaNumericConversions);
  Code:
   Stack=2, Locals=1, Args_size=1
   0:	aload_0
   1:	checkcast	#108; //class java/lang/Number
   4:	invokevirtual	#155; //Method java/lang/Number.doubleValue:()D
   7:	dreturn
  LineNumberTable: 
   line 23: 0

  LocalVariableTable: 
   Start  Length  Slot  Name   Signature
   0      8      0    $this       Lscala/math/ScalaNumericConversions;


public static float toFloat(scala.math.ScalaNumericConversions);
  Code:
   Stack=1, Locals=1, Args_size=1
   0:	aload_0
   1:	checkcast	#108; //class java/lang/Number
   4:	invokevirtual	#159; //Method java/lang/Number.floatValue:()F
   7:	freturn
  LineNumberTable: 
   line 22: 0

  LocalVariableTable: 
   Start  Length  Slot  Name   Signature
   0      8      0    $this       Lscala/math/ScalaNumericConversions;


public static long toLong(scala.math.ScalaNumericConversions);
  Code:
   Stack=2, Locals=1, Args_size=1
   0:	aload_0
   1:	checkcast	#108; //class java/lang/Number
   4:	invokevirtual	#163; //Method java/lang/Number.longValue:()J
   7:	lreturn
  LineNumberTable: 
   line 21: 0

  LocalVariableTable: 
   Start  Length  Slot  Name   Signature
   0      8      0    $this       Lscala/math/ScalaNumericConversions;


public static int toInt(scala.math.ScalaNumericConversions);
  Code:
   Stack=1, Locals=1, Args_size=1
   0:	aload_0
   1:	checkcast	#108; //class java/lang/Number
   4:	invokevirtual	#166; //Method java/lang/Number.intValue:()I
   7:	ireturn
  LineNumberTable: 
   line 20: 0

  LocalVariableTable: 
   Start  Length  Slot  Name   Signature
   0      8      0    $this       Lscala/math/ScalaNumericConversions;


public static short toShort(scala.math.ScalaNumericConversions);
  Code:
   Stack=1, Locals=1, Args_size=1
   0:	aload_0
   1:	checkcast	#108; //class java/lang/Number
   4:	invokevirtual	#170; //Method java/lang/Number.shortValue:()S
   7:	ireturn
  LineNumberTable: 
   line 19: 0

  LocalVariableTable: 
   Start  Length  Slot  Name   Signature
   0      8      0    $this       Lscala/math/ScalaNumericConversions;


public static byte toByte(scala.math.ScalaNumericConversions);
  Code:
   Stack=1, Locals=1, Args_size=1
   0:	aload_0
   1:	checkcast	#108; //class java/lang/Number
   4:	invokevirtual	#174; //Method java/lang/Number.byteValue:()B
   7:	ireturn
  LineNumberTable: 
   line 18: 0

  LocalVariableTable: 
   Start  Length  Slot  Name   Signature
   0      8      0    $this       Lscala/math/ScalaNumericConversions;


public static char toChar(scala.math.ScalaNumericConversions);
  Code:
   Stack=1, Locals=1, Args_size=1
   0:	aload_0
   1:	checkcast	#108; //class java/lang/Number
   4:	invokevirtual	#166; //Method java/lang/Number.intValue:()I
   7:	i2c
   8:	ireturn
  LineNumberTable: 
   line 17: 0

  LocalVariableTable: 
   Start  Length  Slot  Name   Signature
   0      9      0    $this       Lscala/math/ScalaNumericConversions;


}

