Compiled from "BitSetLike.scala"
public final class scala.collection.BitSetLike$$anonfun$foreach$1 extends scala.runtime.AbstractFunction1 implements java.io.Serializable
  SourceFile: "BitSetLike.scala"
  Scala: length = 0x
   
  InnerClass: 
   public abstract ByOne=class scala/collection/immutable/Range$ByOne of class scala/collection/immutable/Range
   public final $anonfun$foreach$1=class scala/collection/BitSetLike$$anonfun$foreach$1 of class scala/collection/BitSetLike
   public final $anonfun$apply$1=class scala/collection/BitSetLike$$anonfun$foreach$1$$anonfun$apply$1 of class scala/collection/BitSetLike$$anonfun$foreach$1
  minor version: 0
  major version: 49
  Constant pool:
Asciz	SourceFile;
Asciz	BitSetLike.scala;
Asciz	<clinit>;
Asciz	()V;
Asciz	Code;
Asciz	serialVersionUID;
Asciz	J;
Asciz	scala/collection/BitSetLike$$anonfun$foreach$1;
class	scala/collection/BitSetLike$$anonfun$foreach$1
NameAndType	serialVersionUID:J
Field	scala/collection/BitSetLike$$anonfun$foreach$1.serialVersionUID:J
Asciz	f$1;
Asciz	Lscala/Function1;;
Asciz	$outer;
Asciz	Lscala/collection/BitSetLike;;
Asciz	<init>;
Asciz	(Lscala/collection/BitSetLike;Lscala/Function1;)V;
Asciz	LineNumberTable;
Asciz	java/lang/NullPointerException;
class	java/lang/NullPointerException
NameAndType	"<init>":()V
Method	java/lang/NullPointerException."<init>":()V
NameAndType	$outer:Lscala/collection/BitSetLike;
Field	scala/collection/BitSetLike$$anonfun$foreach$1.$outer:Lscala/collection/BitSetLike;
NameAndType	f$1:Lscala/Function1;
Field	scala/collection/BitSetLike$$anonfun$foreach$1.f$1:Lscala/Function1;
Asciz	scala/runtime/AbstractFunction1;
class	scala/runtime/AbstractFunction1
Method	scala/runtime/AbstractFunction1."<init>":()V
Asciz	this;
Asciz	Lscala/collection/BitSetLike$$anonfun$foreach$1;;
Asciz	LocalVariableTable;
Asciz	(Lscala/collection/BitSetLike<TThis;>;)V;
Asciz	Signature;
Asciz	apply;
Asciz	(Ljava/lang/Object;)Ljava/lang/Object;;
Asciz	scala/runtime/BoxesRunTime;
class	scala/runtime/BoxesRunTime
Asciz	unboxToInt;
Asciz	(Ljava/lang/Object;)I;
NameAndType	unboxToInt:(Ljava/lang/Object;)I
Method	scala/runtime/BoxesRunTime.unboxToInt:(Ljava/lang/Object;)I
Asciz	(I)V;
NameAndType	apply:(I)V
Method	scala/collection/BitSetLike$$anonfun$foreach$1.apply:(I)V
Asciz	scala/runtime/BoxedUnit;
class	scala/runtime/BoxedUnit
Asciz	UNIT;
Asciz	Lscala/runtime/BoxedUnit;;
NameAndType	UNIT:Lscala/runtime/BoxedUnit;
Field	scala/runtime/BoxedUnit.UNIT:Lscala/runtime/BoxedUnit;
Asciz	v1;
Asciz	Ljava/lang/Object;;
Asciz	scala/collection/BitSetLike;
class	scala/collection/BitSetLike
Asciz	word;
Asciz	(I)J;
NameAndType	word:(I)J
InterfaceMethod	scala/collection/BitSetLike.word:(I)J
Asciz	scala/Predef$;
class	scala/Predef$
Asciz	MODULE$;
Asciz	Lscala/Predef$;;
NameAndType	MODULE$:Lscala/Predef$;
Field	scala/Predef$.MODULE$:Lscala/Predef$;
Asciz	scala/collection/BitSetLike$;
class	scala/collection/BitSetLike$
Asciz	Lscala/collection/BitSetLike$;;
NameAndType	MODULE$:Lscala/collection/BitSetLike$;
Field	scala/collection/BitSetLike$.MODULE$:Lscala/collection/BitSetLike$;
Asciz	scala$collection$BitSetLike$$WordLength;
Asciz	()I;
NameAndType	scala$collection$BitSetLike$$WordLength:()I
Method	scala/collection/BitSetLike$.scala$collection$BitSetLike$$WordLength:()I
Asciz	intWrapper;
Asciz	(I)Lscala/runtime/RichInt;;
NameAndType	intWrapper:(I)Lscala/runtime/RichInt;
Method	scala/Predef$.intWrapper:(I)Lscala/runtime/RichInt;
Asciz	scala/runtime/RichInt;
class	scala/runtime/RichInt
Asciz	until;
Asciz	(I)Lscala/collection/immutable/Range$ByOne;;
NameAndType	until:(I)Lscala/collection/immutable/Range$ByOne;
Method	scala/runtime/RichInt.until:(I)Lscala/collection/immutable/Range$ByOne;
Asciz	scala/collection/BitSetLike$$anonfun$foreach$1$$anonfun$apply$1;
class	scala/collection/BitSetLike$$anonfun$foreach$1$$anonfun$apply$1
Asciz	(Lscala/collection/BitSetLike$$anonfun$foreach$1;J)V;
NameAndType	"<init>":(Lscala/collection/BitSetLike$$anonfun$foreach$1;J)V
Method	scala/collection/BitSetLike$$anonfun$foreach$1$$anonfun$apply$1."<init>":(Lscala/collection/BitSetLike$$anonfun$foreach$1;J)V
Asciz	scala/collection/immutable/Range$ByOne;
class	scala/collection/immutable/Range$ByOne
Asciz	foreach;
Asciz	(Lscala/Function1;)V;
NameAndType	foreach:(Lscala/Function1;)V
InterfaceMethod	scala/collection/immutable/Range$ByOne.foreach:(Lscala/Function1;)V
Asciz	i;
Asciz	I;
Asciz	w$1;
Asciz	Scala;
Asciz	InnerClasses;
Asciz	scala/collection/immutable/Range;
class	scala/collection/immutable/Range
Asciz	ByOne;
Asciz	$anonfun$foreach$1;
Asciz	$anonfun$apply$1;
Asciz	java/io/Serializable;
class	java/io/Serializable

{
public static final long serialVersionUID;
  Signature: J

public final scala.Function1 f$1;
  Signature: Lscala/Function1;

private final scala.collection.BitSetLike $outer;
  Signature: Lscala/collection/BitSetLike;

public static {};
  Signature: ()V
  Code:
   Stack=2, Locals=0, Args_size=0
	lconst_0
	putstatic	Field serialVersionUID:J
	return
  Labels:

public scala.collection.BitSetLike$$anonfun$foreach$1(scala.collection.BitSetLike, scala.Function1);
  Signature: (Lscala/collection/BitSetLike;Lscala/Function1;)V
  Code:
   Stack=2, Locals=3, Args_size=3
	aload_1
	ifnonnull	l1 // aload_0
	new	class java/lang/NullPointerException
	dup
	invokespecial	Method java/lang/NullPointerException."<init>":()V
	athrow
l1	aload_0
	aload_1
	putfield	Field $outer:Lscala/collection/BitSetLike;
	aload_0
	aload_2
	putfield	Field f$1:Lscala/Function1;
	aload_0
	invokespecial	Method scala/runtime/AbstractFunction1."<init>":()V
	return
  Labels:
   	l1 = 12 // aload_0
  LocalVariableTable: 
   Start  Length  Slot  Name   Signature
   0      27      0    this       Lscala/collection/BitSetLike$$anonfun$foreach$1;
   0      27      1    $outer       Lscala/collection/BitSetLike;

  Signature: length = 0x2
   00 21 

public final java.lang.Object apply(java.lang.Object);
  Signature: (Ljava/lang/Object;)Ljava/lang/Object;
  Code:
   Stack=2, Locals=2, Args_size=2
	aload_0
	aload_1
	invokestatic	Method scala/runtime/BoxesRunTime.unboxToInt:(Ljava/lang/Object;)I
	invokevirtual	Method apply:(I)V
	getstatic	Field scala/runtime/BoxedUnit.UNIT:Lscala/runtime/BoxedUnit;
	areturn
  Labels:
  LocalVariableTable: 
   Start  Length  Slot  Name   Signature
   0      12      0    this       Lscala/collection/BitSetLike$$anonfun$foreach$1;
   0      12      1    v1       Ljava/lang/Object;


public final void apply(int);
  Signature: (I)V
  Code:
   Stack=6, Locals=4, Args_size=2
	aload_0
	getfield	Field $outer:Lscala/collection/BitSetLike;
	iload_1
	invokeinterface	InterfaceMethod scala/collection/BitSetLike.word:(I)J
	lstore_2
	getstatic	Field scala/Predef$.MODULE$:Lscala/Predef$;
	iload_1
	getstatic	Field scala/collection/BitSetLike$.MODULE$:Lscala/collection/BitSetLike$;
	invokevirtual	Method scala/collection/BitSetLike$.scala$collection$BitSetLike$$WordLength:()I
	imul
	invokevirtual	Method scala/Predef$.intWrapper:(I)Lscala/runtime/RichInt;
	iload_1
	iconst_1
	iadd
	getstatic	Field scala/collection/BitSetLike$.MODULE$:Lscala/collection/BitSetLike$;
	invokevirtual	Method scala/collection/BitSetLike$.scala$collection$BitSetLike$$WordLength:()I
	imul
	invokevirtual	Method scala/runtime/RichInt.until:(I)Lscala/collection/immutable/Range$ByOne;
	new	class scala/collection/BitSetLike$$anonfun$foreach$1$$anonfun$apply$1
	dup
	aload_0
	lload_2
	invokespecial	Method scala/collection/BitSetLike$$anonfun$foreach$1$$anonfun$apply$1."<init>":(Lscala/collection/BitSetLike$$anonfun$foreach$1;J)V
	invokeinterface	InterfaceMethod scala/collection/immutable/Range$ByOne.foreach:(Lscala/Function1;)V
	return
  Labels:
  LocalVariableTable: 
   Start  Length  Slot  Name   Signature
   0      53      0    this       Lscala/collection/BitSetLike$$anonfun$foreach$1;
   0      53      1    i       I
   11      41      2    w$1       J


}

