Compiled from "BitSetLike.scala"
public final class scala.collection.BitSetLike$$anonfun$subSet$1 extends java.lang.Object implements scala.Function1,scala.ScalaObject,java.io.Serializable
  SourceFile: "BitSetLike.scala"
  Scala: length = 0x
   
  InnerClass: 
   public final $anonfun$subSet$1=class scala/collection/BitSetLike$$anonfun$subSet$1 of class scala/collection/BitSetLike
  minor version: 0
  major version: 49
  Constant pool:
Asciz	SourceFile;
Asciz	BitSetLike.scala;
Asciz	<clinit>;
Asciz	()V;
Asciz	Code;
Asciz	serialVersionUID;
Asciz	J;
Asciz	scala/collection/BitSetLike$$anonfun$subSet$1;
class	scala/collection/BitSetLike$$anonfun$subSet$1
NameAndType	serialVersionUID:J
Field	scala/collection/BitSetLike$$anonfun$subSet$1.serialVersionUID:J
Asciz	other$5;
Asciz	Lscala/collection/BitSet;;
Asciz	$outer;
Asciz	Lscala/collection/BitSetLike;;
Asciz	<init>;
Asciz	(Lscala/collection/BitSetLike;Lscala/collection/BitSet;)V;
Asciz	LineNumberTable;
Asciz	java/lang/NullPointerException;
class	java/lang/NullPointerException
NameAndType	"<init>":()V
Method	java/lang/NullPointerException."<init>":()V
NameAndType	$outer:Lscala/collection/BitSetLike;
Field	scala/collection/BitSetLike$$anonfun$subSet$1.$outer:Lscala/collection/BitSetLike;
NameAndType	other$5:Lscala/collection/BitSet;
Field	scala/collection/BitSetLike$$anonfun$subSet$1.other$5:Lscala/collection/BitSet;
Asciz	java/lang/Object;
class	java/lang/Object
Method	java/lang/Object."<init>":()V
Asciz	scala/Function1$class;
class	scala/Function1$class
Asciz	$init$;
Asciz	(Lscala/Function1;)V;
NameAndType	$init$:(Lscala/Function1;)V
Method	scala/Function1$class.$init$:(Lscala/Function1;)V
Asciz	this;
Asciz	Lscala/collection/BitSetLike$$anonfun$subSet$1;;
Asciz	LocalVariableTable;
Asciz	(Lscala/collection/BitSetLike<TThis;>;)V;
Asciz	Signature;
Asciz	apply;
Asciz	(Ljava/lang/Object;)Ljava/lang/Object;;
Asciz	scala/runtime/BoxesRunTime;
class	scala/runtime/BoxesRunTime
Asciz	unboxToInt;
Asciz	(Ljava/lang/Object;)I;
NameAndType	unboxToInt:(Ljava/lang/Object;)I
Method	scala/runtime/BoxesRunTime.unboxToInt:(Ljava/lang/Object;)I
Asciz	(I)Z;
NameAndType	apply:(I)Z
Method	scala/collection/BitSetLike$$anonfun$subSet$1.apply:(I)Z
Asciz	boxToBoolean;
Asciz	(Z)Ljava/lang/Boolean;;
NameAndType	boxToBoolean:(Z)Ljava/lang/Boolean;
Method	scala/runtime/BoxesRunTime.boxToBoolean:(Z)Ljava/lang/Boolean;
Asciz	v1;
Asciz	Ljava/lang/Object;;
Asciz	scala/collection/BitSetLike;
class	scala/collection/BitSetLike
Asciz	word;
Asciz	(I)J;
NameAndType	word:(I)J
InterfaceMethod	scala/collection/BitSetLike.word:(I)J
long	-1l;
Asciz	idx;
Asciz	I;
Asciz	andThen;
Asciz	(Lscala/Function1;)Lscala/Function1;;
Asciz	(Lscala/Function1;Lscala/Function1;)Lscala/Function1;;
NameAndType	andThen:(Lscala/Function1;Lscala/Function1;)Lscala/Function1;
Method	scala/Function1$class.andThen:(Lscala/Function1;Lscala/Function1;)Lscala/Function1;
Asciz	g;
Asciz	Lscala/Function1;;
Asciz	compose;
NameAndType	compose:(Lscala/Function1;Lscala/Function1;)Lscala/Function1;
Method	scala/Function1$class.compose:(Lscala/Function1;Lscala/Function1;)Lscala/Function1;
Asciz	toString;
Asciz	()Ljava/lang/String;;
Asciz	(Lscala/Function1;)Ljava/lang/String;;
NameAndType	toString:(Lscala/Function1;)Ljava/lang/String;
Method	scala/Function1$class.toString:(Lscala/Function1;)Ljava/lang/String;
Asciz	Scala;
Asciz	InnerClasses;
Asciz	$anonfun$subSet$1;
Asciz	scala/Function1;
class	scala/Function1
Asciz	scala/ScalaObject;
class	scala/ScalaObject
Asciz	java/io/Serializable;
class	java/io/Serializable

{
public static final long serialVersionUID;
  Signature: J

private final scala.collection.BitSet other$5;
  Signature: Lscala/collection/BitSet;

private final scala.collection.BitSetLike $outer;
  Signature: Lscala/collection/BitSetLike;

public static {};
  Signature: ()V
  Code:
   Stack=2, Locals=0, Args_size=0
	lconst_0
	putstatic	Field serialVersionUID:J
	return
  Labels:

public scala.collection.BitSetLike$$anonfun$subSet$1(scala.collection.BitSetLike, scala.collection.BitSet);
  Signature: (Lscala/collection/BitSetLike;Lscala/collection/BitSet;)V
  Code:
   Stack=2, Locals=3, Args_size=3
	aload_1
	ifnonnull	l1 // aload_0
	new	class java/lang/NullPointerException
	dup
	invokespecial	Method java/lang/NullPointerException."<init>":()V
	athrow
l1	aload_0
	aload_1
	putfield	Field $outer:Lscala/collection/BitSetLike;
	aload_0
	aload_2
	putfield	Field other$5:Lscala/collection/BitSet;
	aload_0
	invokespecial	Method java/lang/Object."<init>":()V
	aload_0
	invokestatic	Method scala/Function1$class.$init$:(Lscala/Function1;)V
	return
  Labels:
   	l1 = 12 // aload_0
  LocalVariableTable: 
   Start  Length  Slot  Name   Signature
   0      31      0    this       Lscala/collection/BitSetLike$$anonfun$subSet$1;
   0      31      1    $outer       Lscala/collection/BitSetLike;

  Signature: length = 0x2
   00 27 

public final java.lang.Object apply(java.lang.Object);
  Signature: (Ljava/lang/Object;)Ljava/lang/Object;
  Code:
   Stack=2, Locals=4, Args_size=2
	aload_0
	getfield	Field $outer:Lscala/collection/BitSetLike;
	astore_3
	aload_0
	aload_1
	invokestatic	Method scala/runtime/BoxesRunTime.unboxToInt:(Ljava/lang/Object;)I
	invokevirtual	Method apply:(I)Z
	istore_2
	iload_2
	invokestatic	Method scala/runtime/BoxesRunTime.boxToBoolean:(Z)Ljava/lang/Boolean;
	areturn
  Labels:
  LocalVariableTable: 
   Start  Length  Slot  Name   Signature
   0      19      0    this       Lscala/collection/BitSetLike$$anonfun$subSet$1;
   5      14      1    v1       Ljava/lang/Object;


public final boolean apply(int);
  Signature: (I)Z
  Code:
   Stack=6, Locals=3, Args_size=2
	aload_0
	getfield	Field $outer:Lscala/collection/BitSetLike;
	astore_2
	aload_0
	getfield	Field $outer:Lscala/collection/BitSetLike;
	iload_1
	invokeinterface	InterfaceMethod scala/collection/BitSetLike.word:(I)J
	aload_0
	getfield	Field other$5:Lscala/collection/BitSet;
	iload_1
	invokeinterface	InterfaceMethod scala/collection/BitSetLike.word:(I)J
	ldc2_w	long -1l
	lxor
	land
	lconst_0
	lcmp
	ifne	l1 // iconst_0
	iconst_1
	goto	l2 // ireturn
l1	iconst_0
l2	ireturn
  Labels:
   	l1 = 39 // iconst_0
   	l2 = 40 // ireturn
  LocalVariableTable: 
   Start  Length  Slot  Name   Signature
   0      41      0    this       Lscala/collection/BitSetLike$$anonfun$subSet$1;
   5      36      1    idx       I


public scala.Function1 andThen(scala.Function1);
  Signature: (Lscala/Function1;)Lscala/Function1;
  Code:
   Stack=2, Locals=2, Args_size=2
	aload_0
	aload_1
	invokestatic	Method scala/Function1$class.andThen:(Lscala/Function1;Lscala/Function1;)Lscala/Function1;
	areturn
  Labels:
  LocalVariableTable: 
   Start  Length  Slot  Name   Signature
   0      6      0    this       Lscala/collection/BitSetLike$$anonfun$subSet$1;
   0      6      1    g       Lscala/Function1;


public scala.Function1 compose(scala.Function1);
  Signature: (Lscala/Function1;)Lscala/Function1;
  Code:
   Stack=2, Locals=2, Args_size=2
	aload_0
	aload_1
	invokestatic	Method scala/Function1$class.compose:(Lscala/Function1;Lscala/Function1;)Lscala/Function1;
	areturn
  Labels:
  LocalVariableTable: 
   Start  Length  Slot  Name   Signature
   0      6      0    this       Lscala/collection/BitSetLike$$anonfun$subSet$1;
   0      6      1    g       Lscala/Function1;


public java.lang.String toString();
  Signature: ()Ljava/lang/String;
  Code:
   Stack=1, Locals=1, Args_size=1
	aload_0
	invokestatic	Method scala/Function1$class.toString:(Lscala/Function1;)Ljava/lang/String;
	areturn
  Labels:

}

