Compiled from "BitSetLike.scala"
public final class scala.collection.BitSetLike$$anonfun$foreach$1 extends java.lang.Object implements scala.Function1,scala.ScalaObject,java.io.Serializable
  SourceFile: "BitSetLike.scala"
  Scala: length = 0x
   
  InnerClass: 
   public abstract #122= #92 of #121; //ByOne=class scala/collection/immutable/Range$ByOne of class scala/collection/immutable/Range
   public final #123= #9 of #61; //$anonfun$foreach$1=class scala/collection/BitSetLike$$anonfun$foreach$1 of class scala/collection/BitSetLike
   public final #124= #94 of #9; //$anonfun$apply$1=class scala/collection/BitSetLike$$anonfun$foreach$1$$anonfun$apply$1 of class scala/collection/BitSetLike$$anonfun$foreach$1
  minor version: 0
  major version: 49
  Constant pool:
const #1 = Asciz	SourceFile;
const #2 = Asciz	BitSetLike.scala;
const #3 = Asciz	<clinit>;
const #4 = Asciz	()V;
const #5 = Asciz	Code;
const #6 = Asciz	serialVersionUID;
const #7 = Asciz	J;
const #8 = Asciz	scala/collection/BitSetLike$$anonfun$foreach$1;
const #9 = class	#8;	//  scala/collection/BitSetLike$$anonfun$foreach$1
const #10 = NameAndType	#6:#7;//  serialVersionUID:J
const #11 = Field	#9.#10;	//  scala/collection/BitSetLike$$anonfun$foreach$1.serialVersionUID:J
const #12 = Asciz	f$1;
const #13 = Asciz	Lscala/Function1;;
const #14 = Asciz	$outer;
const #15 = Asciz	Lscala/collection/BitSetLike;;
const #16 = Asciz	<init>;
const #17 = Asciz	(Lscala/collection/BitSetLike;Lscala/Function1;)V;
const #18 = Asciz	LineNumberTable;
const #19 = Asciz	java/lang/NullPointerException;
const #20 = class	#19;	//  java/lang/NullPointerException
const #21 = NameAndType	#16:#4;//  "<init>":()V
const #22 = Method	#20.#21;	//  java/lang/NullPointerException."<init>":()V
const #23 = NameAndType	#14:#15;//  $outer:Lscala/collection/BitSetLike;
const #24 = Field	#9.#23;	//  scala/collection/BitSetLike$$anonfun$foreach$1.$outer:Lscala/collection/BitSetLike;
const #25 = NameAndType	#12:#13;//  f$1:Lscala/Function1;
const #26 = Field	#9.#25;	//  scala/collection/BitSetLike$$anonfun$foreach$1.f$1:Lscala/Function1;
const #27 = Asciz	java/lang/Object;
const #28 = class	#27;	//  java/lang/Object
const #29 = Method	#28.#21;	//  java/lang/Object."<init>":()V
const #30 = Asciz	scala/Function1$class;
const #31 = class	#30;	//  scala/Function1$class
const #32 = Asciz	$init$;
const #33 = Asciz	(Lscala/Function1;)V;
const #34 = NameAndType	#32:#33;//  $init$:(Lscala/Function1;)V
const #35 = Method	#31.#34;	//  scala/Function1$class.$init$:(Lscala/Function1;)V
const #36 = Asciz	this;
const #37 = Asciz	Lscala/collection/BitSetLike$$anonfun$foreach$1;;
const #38 = Asciz	LocalVariableTable;
const #39 = Asciz	(Lscala/collection/BitSetLike<TThis;>;)V;
const #40 = Asciz	Signature;
const #41 = Asciz	apply;
const #42 = Asciz	(Ljava/lang/Object;)Ljava/lang/Object;;
const #43 = Asciz	scala/runtime/BoxesRunTime;
const #44 = class	#43;	//  scala/runtime/BoxesRunTime
const #45 = Asciz	unboxToInt;
const #46 = Asciz	(Ljava/lang/Object;)I;
const #47 = NameAndType	#45:#46;//  unboxToInt:(Ljava/lang/Object;)I
const #48 = Method	#44.#47;	//  scala/runtime/BoxesRunTime.unboxToInt:(Ljava/lang/Object;)I
const #49 = Asciz	(I)V;
const #50 = NameAndType	#41:#49;//  apply:(I)V
const #51 = Method	#9.#50;	//  scala/collection/BitSetLike$$anonfun$foreach$1.apply:(I)V
const #52 = Asciz	scala/runtime/BoxedUnit;
const #53 = class	#52;	//  scala/runtime/BoxedUnit
const #54 = Asciz	UNIT;
const #55 = Asciz	Lscala/runtime/BoxedUnit;;
const #56 = NameAndType	#54:#55;//  UNIT:Lscala/runtime/BoxedUnit;
const #57 = Field	#53.#56;	//  scala/runtime/BoxedUnit.UNIT:Lscala/runtime/BoxedUnit;
const #58 = Asciz	v1;
const #59 = Asciz	Ljava/lang/Object;;
const #60 = Asciz	scala/collection/BitSetLike;
const #61 = class	#60;	//  scala/collection/BitSetLike
const #62 = Asciz	word;
const #63 = Asciz	(I)J;
const #64 = NameAndType	#62:#63;//  word:(I)J
const #65 = InterfaceMethod	#61.#64;	//  scala/collection/BitSetLike.word:(I)J
const #66 = Asciz	scala/Predef$;
const #67 = class	#66;	//  scala/Predef$
const #68 = Asciz	MODULE$;
const #69 = Asciz	Lscala/Predef$;;
const #70 = NameAndType	#68:#69;//  MODULE$:Lscala/Predef$;
const #71 = Field	#67.#70;	//  scala/Predef$.MODULE$:Lscala/Predef$;
const #72 = Asciz	scala/collection/BitSetLike$;
const #73 = class	#72;	//  scala/collection/BitSetLike$
const #74 = Asciz	Lscala/collection/BitSetLike$;;
const #75 = NameAndType	#68:#74;//  MODULE$:Lscala/collection/BitSetLike$;
const #76 = Field	#73.#75;	//  scala/collection/BitSetLike$.MODULE$:Lscala/collection/BitSetLike$;
const #77 = Asciz	scala$collection$BitSetLike$$WordLength;
const #78 = Asciz	()I;
const #79 = NameAndType	#77:#78;//  scala$collection$BitSetLike$$WordLength:()I
const #80 = Method	#73.#79;	//  scala/collection/BitSetLike$.scala$collection$BitSetLike$$WordLength:()I
const #81 = Asciz	intWrapper;
const #82 = Asciz	(I)Lscala/runtime/RichInt;;
const #83 = NameAndType	#81:#82;//  intWrapper:(I)Lscala/runtime/RichInt;
const #84 = Method	#67.#83;	//  scala/Predef$.intWrapper:(I)Lscala/runtime/RichInt;
const #85 = Asciz	scala/runtime/RichInt;
const #86 = class	#85;	//  scala/runtime/RichInt
const #87 = Asciz	until;
const #88 = Asciz	(I)Lscala/collection/immutable/Range;;
const #89 = NameAndType	#87:#88;//  until:(I)Lscala/collection/immutable/Range;
const #90 = Method	#86.#89;	//  scala/runtime/RichInt.until:(I)Lscala/collection/immutable/Range;
const #91 = Asciz	scala/collection/immutable/Range$ByOne;
const #92 = class	#91;	//  scala/collection/immutable/Range$ByOne
const #93 = Asciz	scala/collection/BitSetLike$$anonfun$foreach$1$$anonfun$apply$1;
const #94 = class	#93;	//  scala/collection/BitSetLike$$anonfun$foreach$1$$anonfun$apply$1
const #95 = Asciz	(Lscala/collection/BitSetLike$$anonfun$foreach$1;J)V;
const #96 = NameAndType	#16:#95;//  "<init>":(Lscala/collection/BitSetLike$$anonfun$foreach$1;J)V
const #97 = Method	#94.#96;	//  scala/collection/BitSetLike$$anonfun$foreach$1$$anonfun$apply$1."<init>":(Lscala/collection/BitSetLike$$anonfun$foreach$1;J)V
const #98 = Asciz	foreach;
const #99 = NameAndType	#98:#33;//  foreach:(Lscala/Function1;)V
const #100 = InterfaceMethod	#92.#99;	//  scala/collection/immutable/Range$ByOne.foreach:(Lscala/Function1;)V
const #101 = Asciz	i;
const #102 = Asciz	I;
const #103 = Asciz	w$1;
const #104 = Asciz	andThen;
const #105 = Asciz	(Lscala/Function1;)Lscala/Function1;;
const #106 = Asciz	(Lscala/Function1;Lscala/Function1;)Lscala/Function1;;
const #107 = NameAndType	#104:#106;//  andThen:(Lscala/Function1;Lscala/Function1;)Lscala/Function1;
const #108 = Method	#31.#107;	//  scala/Function1$class.andThen:(Lscala/Function1;Lscala/Function1;)Lscala/Function1;
const #109 = Asciz	g;
const #110 = Asciz	compose;
const #111 = NameAndType	#110:#106;//  compose:(Lscala/Function1;Lscala/Function1;)Lscala/Function1;
const #112 = Method	#31.#111;	//  scala/Function1$class.compose:(Lscala/Function1;Lscala/Function1;)Lscala/Function1;
const #113 = Asciz	toString;
const #114 = Asciz	()Ljava/lang/String;;
const #115 = Asciz	(Lscala/Function1;)Ljava/lang/String;;
const #116 = NameAndType	#113:#115;//  toString:(Lscala/Function1;)Ljava/lang/String;
const #117 = Method	#31.#116;	//  scala/Function1$class.toString:(Lscala/Function1;)Ljava/lang/String;
const #118 = Asciz	Scala;
const #119 = Asciz	InnerClasses;
const #120 = Asciz	scala/collection/immutable/Range;
const #121 = class	#120;	//  scala/collection/immutable/Range
const #122 = Asciz	ByOne;
const #123 = Asciz	$anonfun$foreach$1;
const #124 = Asciz	$anonfun$apply$1;
const #125 = Asciz	scala/Function1;
const #126 = class	#125;	//  scala/Function1
const #127 = Asciz	scala/ScalaObject;
const #128 = class	#127;	//  scala/ScalaObject
const #129 = Asciz	java/io/Serializable;
const #130 = class	#129;	//  java/io/Serializable

{
public static final long serialVersionUID;

public final scala.Function1 f$1;

public static {};
  Code:
   Stack=2, Locals=0, Args_size=0
   0:	lconst_0
   1:	putstatic	#11; //Field serialVersionUID:J
   4:	return

public scala.collection.BitSetLike$$anonfun$foreach$1(scala.collection.BitSetLike, scala.Function1);
  Code:
   Stack=2, Locals=3, Args_size=3
   0:	aload_1
   1:	ifnonnull	12
   4:	new	#20; //class java/lang/NullPointerException
   7:	dup
   8:	invokespecial	#22; //Method java/lang/NullPointerException."<init>":()V
   11:	athrow
   12:	aload_0
   13:	aload_1
   14:	putfield	#24; //Field $outer:Lscala/collection/BitSetLike;
   17:	aload_0
   18:	aload_2
   19:	putfield	#26; //Field f$1:Lscala/Function1;
   22:	aload_0
   23:	invokespecial	#29; //Method java/lang/Object."<init>":()V
   26:	aload_0
   27:	invokestatic	#35; //Method scala/Function1$class.$init$:(Lscala/Function1;)V
   30:	return
  LineNumberTable: 
   line 63: 0

  LocalVariableTable: 
   Start  Length  Slot  Name   Signature
   0      31      0    this       Lscala/collection/BitSetLike$$anonfun$foreach$1;
   0      31      1    $outer       Lscala/collection/BitSetLike;

  Signature: length = 0x2
   00 27 

public final java.lang.Object apply(java.lang.Object);
  Code:
   Stack=2, Locals=3, Args_size=2
   0:	aload_0
   1:	getfield	#24; //Field $outer:Lscala/collection/BitSetLike;
   4:	astore_2
   5:	aload_0
   6:	aload_1
   7:	invokestatic	#48; //Method scala/runtime/BoxesRunTime.unboxToInt:(Ljava/lang/Object;)I
   10:	invokevirtual	#51; //Method apply:(I)V
   13:	getstatic	#57; //Field scala/runtime/BoxedUnit.UNIT:Lscala/runtime/BoxedUnit;
   16:	areturn
  LineNumberTable: 
   line 63: 0

  LocalVariableTable: 
   Start  Length  Slot  Name   Signature
   0      17      0    this       Lscala/collection/BitSetLike$$anonfun$foreach$1;
   5      12      1    v1       Ljava/lang/Object;


public final void apply(int);
  Code:
   Stack=6, Locals=5, Args_size=2
   0:	aload_0
   1:	getfield	#24; //Field $outer:Lscala/collection/BitSetLike;
   4:	astore	4
   6:	aload_0
   7:	getfield	#24; //Field $outer:Lscala/collection/BitSetLike;
   10:	iload_1
   11:	invokeinterface	#65,  2; //InterfaceMethod scala/collection/BitSetLike.word:(I)J
   16:	lstore_2
   17:	getstatic	#71; //Field scala/Predef$.MODULE$:Lscala/Predef$;
   20:	iload_1
   21:	getstatic	#76; //Field scala/collection/BitSetLike$.MODULE$:Lscala/collection/BitSetLike$;
   24:	invokevirtual	#80; //Method scala/collection/BitSetLike$.scala$collection$BitSetLike$$WordLength:()I
   27:	imul
   28:	invokevirtual	#84; //Method scala/Predef$.intWrapper:(I)Lscala/runtime/RichInt;
   31:	iload_1
   32:	iconst_1
   33:	iadd
   34:	getstatic	#76; //Field scala/collection/BitSetLike$.MODULE$:Lscala/collection/BitSetLike$;
   37:	invokevirtual	#80; //Method scala/collection/BitSetLike$.scala$collection$BitSetLike$$WordLength:()I
   40:	imul
   41:	invokevirtual	#90; //Method scala/runtime/RichInt.until:(I)Lscala/collection/immutable/Range;
   44:	checkcast	#92; //class scala/collection/immutable/Range$ByOne
   47:	new	#94; //class scala/collection/BitSetLike$$anonfun$foreach$1$$anonfun$apply$1
   50:	dup
   51:	aload_0
   52:	lload_2
   53:	invokespecial	#97; //Method scala/collection/BitSetLike$$anonfun$foreach$1$$anonfun$apply$1."<init>":(Lscala/collection/BitSetLike$$anonfun$foreach$1;J)V
   56:	invokeinterface	#100,  2; //InterfaceMethod scala/collection/immutable/Range$ByOne.foreach:(Lscala/Function1;)V
   61:	return
  LineNumberTable: 
   line 64: 0
   line 65: 17

  LocalVariableTable: 
   Start  Length  Slot  Name   Signature
   0      62      0    this       Lscala/collection/BitSetLike$$anonfun$foreach$1;
   6      56      1    i       I
   17      44      2    w$1       J


public scala.Function1 andThen(scala.Function1);
  Code:
   Stack=2, Locals=2, Args_size=2
   0:	aload_0
   1:	aload_1
   2:	invokestatic	#108; //Method scala/Function1$class.andThen:(Lscala/Function1;Lscala/Function1;)Lscala/Function1;
   5:	areturn
  LineNumberTable: 
   line 63: 0

  LocalVariableTable: 
   Start  Length  Slot  Name   Signature
   0      6      0    this       Lscala/collection/BitSetLike$$anonfun$foreach$1;
   0      6      1    g       Lscala/Function1;


public scala.Function1 compose(scala.Function1);
  Code:
   Stack=2, Locals=2, Args_size=2
   0:	aload_0
   1:	aload_1
   2:	invokestatic	#112; //Method scala/Function1$class.compose:(Lscala/Function1;Lscala/Function1;)Lscala/Function1;
   5:	areturn
  LineNumberTable: 
   line 63: 0

  LocalVariableTable: 
   Start  Length  Slot  Name   Signature
   0      6      0    this       Lscala/collection/BitSetLike$$anonfun$foreach$1;
   0      6      1    g       Lscala/Function1;


public java.lang.String toString();
  Code:
   Stack=1, Locals=1, Args_size=1
   0:	aload_0
   1:	invokestatic	#117; //Method scala/Function1$class.toString:(Lscala/Function1;)Ljava/lang/String;
   4:	areturn
  LineNumberTable: 
   line 63: 0


}

