Compiled from "BufferedIterator.scala"
public abstract class scala.collection.BufferedIterator$class extends java.lang.Object
  SourceFile: "BufferedIterator.scala"
  Scala: length = 0x
   
  minor version: 0
  major version: 49
  Constant pool:
const #1 = Asciz	SourceFile;
const #2 = Asciz	BufferedIterator.scala;
const #3 = Asciz	$init$;
const #4 = Asciz	(Lscala/collection/BufferedIterator;)V;
const #5 = Asciz	Code;
const #6 = Asciz	LineNumberTable;
const #7 = Asciz	$this;
const #8 = Asciz	Lscala/collection/BufferedIterator;;
const #9 = Asciz	LocalVariableTable;
const #10 = Asciz	buffered;
const #11 = Asciz	(Lscala/collection/BufferedIterator;)Lscala/collection/BufferedIterator;;
const #12 = Asciz	Scala;
const #13 = Asciz	scala/collection/BufferedIterator$class;
const #14 = class	#13;	//  scala/collection/BufferedIterator$class
const #15 = Asciz	java/lang/Object;
const #16 = class	#15;	//  java/lang/Object

{
public static void $init$(scala.collection.BufferedIterator);
  Code:
   Stack=0, Locals=1, Args_size=1
   0:	return
  LineNumberTable: 
   line 20: 0

  LocalVariableTable: 
   Start  Length  Slot  Name   Signature
   0      1      0    $this       Lscala/collection/BufferedIterator;


public static scala.collection.BufferedIterator buffered(scala.collection.BufferedIterator);
  Code:
   Stack=1, Locals=1, Args_size=1
   0:	aload_0
   1:	areturn
  LineNumberTable: 
   line 26: 0

  LocalVariableTable: 
   Start  Length  Slot  Name   Signature
   0      2      0    $this       Lscala/collection/BufferedIterator;


}

