Compiled from "DefaultMap.scala"
public abstract class scala.collection.DefaultMap$class extends java.lang.Object
  SourceFile: "DefaultMap.scala"
  Scala: length = 0x
   
  InnerClass: 
   public final #88= #19 of #87; //$anonfun$$minus$1=class scala/collection/DefaultMap$$anonfun$$minus$1 of class scala/collection/DefaultMap
  minor version: 0
  major version: 49
  Constant pool:
const #1 = Asciz	SourceFile;
const #2 = Asciz	DefaultMap.scala;
const #3 = Asciz	$init$;
const #4 = Asciz	(Lscala/collection/DefaultMap;)V;
const #5 = Asciz	Code;
const #6 = Asciz	LineNumberTable;
const #7 = Asciz	$this;
const #8 = Asciz	Lscala/collection/DefaultMap;;
const #9 = Asciz	LocalVariableTable;
const #10 = Asciz	$minus;
const #11 = Asciz	(Lscala/collection/DefaultMap;Ljava/lang/Object;)Lscala/collection/Map;;
const #12 = Asciz	scala/collection/generic/MapTemplate;
const #13 = class	#12;	//  scala/collection/generic/MapTemplate
const #14 = Asciz	newBuilder;
const #15 = Asciz	()Lscala/collection/generic/Builder;;
const #16 = NameAndType	#14:#15;//  newBuilder:()Lscala/collection/generic/Builder;
const #17 = InterfaceMethod	#13.#16;	//  scala/collection/generic/MapTemplate.newBuilder:()Lscala/collection/generic/Builder;
const #18 = Asciz	scala/collection/DefaultMap$$anonfun$$minus$1;
const #19 = class	#18;	//  scala/collection/DefaultMap$$anonfun$$minus$1
const #20 = Asciz	<init>;
const #21 = Asciz	(Lscala/collection/DefaultMap;Ljava/lang/Object;)V;
const #22 = NameAndType	#20:#21;//  "<init>":(Lscala/collection/DefaultMap;Ljava/lang/Object;)V
const #23 = Method	#19.#22;	//  scala/collection/DefaultMap$$anonfun$$minus$1."<init>":(Lscala/collection/DefaultMap;Ljava/lang/Object;)V
const #24 = Asciz	scala/collection/generic/TraversableTemplate;
const #25 = class	#24;	//  scala/collection/generic/TraversableTemplate
const #26 = Asciz	filter;
const #27 = Asciz	(Lscala/Function1;)Lscala/collection/generic/TraversableTemplate;;
const #28 = NameAndType	#26:#27;//  filter:(Lscala/Function1;)Lscala/collection/generic/TraversableTemplate;
const #29 = InterfaceMethod	#25.#28;	//  scala/collection/generic/TraversableTemplate.filter:(Lscala/Function1;)Lscala/collection/generic/TraversableTemplate;
const #30 = Asciz	scala/collection/Traversable;
const #31 = class	#30;	//  scala/collection/Traversable
const #32 = Asciz	scala/collection/generic/Growable;
const #33 = class	#32;	//  scala/collection/generic/Growable
const #34 = Asciz	$plus$plus$eq;
const #35 = Asciz	(Lscala/collection/Traversable;)Lscala/collection/generic/Growable;;
const #36 = NameAndType	#34:#35;//  $plus$plus$eq:(Lscala/collection/Traversable;)Lscala/collection/generic/Growable;
const #37 = InterfaceMethod	#33.#36;	//  scala/collection/generic/Growable.$plus$plus$eq:(Lscala/collection/Traversable;)Lscala/collection/generic/Growable;
const #38 = Asciz	scala/collection/generic/Builder;
const #39 = class	#38;	//  scala/collection/generic/Builder
const #40 = Asciz	result;
const #41 = Asciz	()Ljava/lang/Object;;
const #42 = NameAndType	#40:#41;//  result:()Ljava/lang/Object;
const #43 = InterfaceMethod	#39.#42;	//  scala/collection/generic/Builder.result:()Ljava/lang/Object;
const #44 = Asciz	scala/collection/Map;
const #45 = class	#44;	//  scala/collection/Map
const #46 = Asciz	key$1;
const #47 = Asciz	Ljava/lang/Object;;
const #48 = Asciz	b;
const #49 = Asciz	Lscala/collection/generic/Builder;;
const #50 = Asciz	$plus;
const #51 = Asciz	(Lscala/collection/DefaultMap;Lscala/Tuple2;)Lscala/collection/Map;;
const #52 = Asciz	scala/collection/Map$;
const #53 = class	#52;	//  scala/collection/Map$
const #54 = Asciz	MODULE$;
const #55 = Asciz	Lscala/collection/Map$;;
const #56 = NameAndType	#54:#55;//  MODULE$:Lscala/collection/Map$;
const #57 = Field	#53.#56;	//  scala/collection/Map$.MODULE$:Lscala/collection/Map$;
const #58 = Asciz	()Lscala/collection/generic/MapBuilder;;
const #59 = NameAndType	#14:#58;//  newBuilder:()Lscala/collection/generic/MapBuilder;
const #60 = Method	#53.#59;	//  scala/collection/Map$.newBuilder:()Lscala/collection/generic/MapBuilder;
const #61 = Asciz	scala/Tuple2;
const #62 = class	#61;	//  scala/Tuple2
const #63 = Asciz	_1;
const #64 = NameAndType	#63:#41;//  _1:()Ljava/lang/Object;
const #65 = Method	#62.#64;	//  scala/Tuple2._1:()Ljava/lang/Object;
const #66 = Asciz	_2;
const #67 = NameAndType	#66:#41;//  _2:()Ljava/lang/Object;
const #68 = Method	#62.#67;	//  scala/Tuple2._2:()Ljava/lang/Object;
const #69 = Asciz	(Ljava/lang/Object;Ljava/lang/Object;)V;
const #70 = NameAndType	#20:#69;//  "<init>":(Ljava/lang/Object;Ljava/lang/Object;)V
const #71 = Method	#62.#70;	//  scala/Tuple2."<init>":(Ljava/lang/Object;Ljava/lang/Object;)V
const #72 = Asciz	scala/collection/generic/MapBuilder;
const #73 = class	#72;	//  scala/collection/generic/MapBuilder
const #74 = Asciz	$plus$eq;
const #75 = Asciz	(Lscala/Tuple2;)Lscala/collection/generic/MapBuilder;;
const #76 = NameAndType	#74:#75;//  $plus$eq:(Lscala/Tuple2;)Lscala/collection/generic/MapBuilder;
const #77 = Method	#73.#76;	//  scala/collection/generic/MapBuilder.$plus$eq:(Lscala/Tuple2;)Lscala/collection/generic/MapBuilder;
const #78 = Asciz	()Lscala/collection/Map;;
const #79 = NameAndType	#40:#78;//  result:()Lscala/collection/Map;
const #80 = Method	#73.#79;	//  scala/collection/generic/MapBuilder.result:()Lscala/collection/Map;
const #81 = Asciz	kv;
const #82 = Asciz	Lscala/Tuple2;;
const #83 = Asciz	Lscala/collection/generic/MapBuilder;;
const #84 = Asciz	Scala;
const #85 = Asciz	InnerClasses;
const #86 = Asciz	scala/collection/DefaultMap;
const #87 = class	#86;	//  scala/collection/DefaultMap
const #88 = Asciz	$anonfun$$minus$1;
const #89 = Asciz	scala/collection/DefaultMap$class;
const #90 = class	#89;	//  scala/collection/DefaultMap$class
const #91 = Asciz	java/lang/Object;
const #92 = class	#91;	//  java/lang/Object

{
public static void $init$(scala.collection.DefaultMap);
  Code:
   Stack=0, Locals=1, Args_size=1
   0:	return
  LineNumberTable: 
   line 32: 0

  LocalVariableTable: 
   Start  Length  Slot  Name   Signature
   0      1      0    $this       Lscala/collection/DefaultMap;


public static scala.collection.Map $minus(scala.collection.DefaultMap, java.lang.Object);
  Code:
   Stack=6, Locals=3, Args_size=2
   0:	aload_0
   1:	invokeinterface	#17,  1; //InterfaceMethod scala/collection/generic/MapTemplate.newBuilder:()Lscala/collection/generic/Builder;
   6:	astore_2
   7:	aload_2
   8:	aload_0
   9:	new	#19; //class scala/collection/DefaultMap$$anonfun$$minus$1
   12:	dup
   13:	aload_0
   14:	aload_1
   15:	invokespecial	#23; //Method scala/collection/DefaultMap$$anonfun$$minus$1."<init>":(Lscala/collection/DefaultMap;Ljava/lang/Object;)V
   18:	invokeinterface	#29,  2; //InterfaceMethod scala/collection/generic/TraversableTemplate.filter:(Lscala/Function1;)Lscala/collection/generic/TraversableTemplate;
   23:	checkcast	#31; //class scala/collection/Traversable
   26:	invokeinterface	#37,  2; //InterfaceMethod scala/collection/generic/Growable.$plus$plus$eq:(Lscala/collection/Traversable;)Lscala/collection/generic/Growable;
   31:	pop
   32:	aload_2
   33:	invokeinterface	#43,  1; //InterfaceMethod scala/collection/generic/Builder.result:()Ljava/lang/Object;
   38:	checkcast	#45; //class scala/collection/Map
   41:	areturn
  LineNumberTable: 
   line 46: 0
   line 47: 7
   line 48: 32

  LocalVariableTable: 
   Start  Length  Slot  Name   Signature
   0      42      0    $this       Lscala/collection/DefaultMap;
   0      42      1    key$1       Ljava/lang/Object;
   7      34      2    b       Lscala/collection/generic/Builder;


public static scala.collection.Map $plus(scala.collection.DefaultMap, scala.Tuple2);
  Code:
   Stack=5, Locals=3, Args_size=2
   0:	getstatic	#57; //Field scala/collection/Map$.MODULE$:Lscala/collection/Map$;
   3:	invokevirtual	#60; //Method scala/collection/Map$.newBuilder:()Lscala/collection/generic/MapBuilder;
   6:	astore_2
   7:	aload_2
   8:	aload_0
   9:	invokeinterface	#37,  2; //InterfaceMethod scala/collection/generic/Growable.$plus$plus$eq:(Lscala/collection/Traversable;)Lscala/collection/generic/Growable;
   14:	pop
   15:	aload_2
   16:	new	#62; //class scala/Tuple2
   19:	dup
   20:	aload_1
   21:	invokevirtual	#65; //Method scala/Tuple2._1:()Ljava/lang/Object;
   24:	aload_1
   25:	invokevirtual	#68; //Method scala/Tuple2._2:()Ljava/lang/Object;
   28:	invokespecial	#71; //Method scala/Tuple2."<init>":(Ljava/lang/Object;Ljava/lang/Object;)V
   31:	invokevirtual	#77; //Method scala/collection/generic/MapBuilder.$plus$eq:(Lscala/Tuple2;)Lscala/collection/generic/MapBuilder;
   34:	pop
   35:	aload_2
   36:	invokevirtual	#80; //Method scala/collection/generic/MapBuilder.result:()Lscala/collection/Map;
   39:	areturn
  LineNumberTable: 
   line 37: 0
   line 38: 7
   line 39: 15
   line 40: 35

  LocalVariableTable: 
   Start  Length  Slot  Name   Signature
   0      40      0    $this       Lscala/collection/DefaultMap;
   0      40      1    kv       Lscala/Tuple2;
   7      32      2    b       Lscala/collection/generic/MapBuilder;


}

