Compiled from "IndexedSeqViewLike.scala"
public abstract class scala.collection.IndexedSeqViewLike$ZippedAll$class extends java.lang.Object
  SourceFile: "IndexedSeqViewLike.scala"
  Scala: length = 0x
   
  InnerClass: 
   public abstract ZippedAll=class scala/collection/IndexedSeqViewLike$ZippedAll of class scala/collection/IndexedSeqViewLike
  minor version: 0
  major version: 49
  Constant pool:
Asciz	SourceFile;
Asciz	IndexedSeqViewLike.scala;
Asciz	iterator;
Asciz	(Lscala/collection/IndexedSeqViewLike$ZippedAll;)Lscala/collection/Iterator;;
Asciz	Code;
Asciz	LineNumberTable;
Asciz	scala/collection/IndexedSeqViewLike$ZippedAll;
class	scala/collection/IndexedSeqViewLike$ZippedAll
Asciz	scala$collection$IndexedSeqViewLike$ZippedAll$$$outer;
Asciz	()Lscala/collection/IndexedSeqViewLike;;
NameAndType	scala$collection$IndexedSeqViewLike$ZippedAll$$$outer:()Lscala/collection/IndexedSeqViewLike;
InterfaceMethod	scala/collection/IndexedSeqViewLike$ZippedAll.scala$collection$IndexedSeqViewLike$ZippedAll$$$outer:()Lscala/collection/IndexedSeqViewLike;
Asciz	scala/collection/IndexedSeqLike;
class	scala/collection/IndexedSeqLike
Asciz	()Lscala/collection/Iterator;;
NameAndType	iterator:()Lscala/collection/Iterator;
InterfaceMethod	scala/collection/IndexedSeqLike.iterator:()Lscala/collection/Iterator;
Asciz	other;
Asciz	()Lscala/collection/Iterable;;
NameAndType	other:()Lscala/collection/Iterable;
InterfaceMethod	scala/collection/IndexedSeqViewLike$ZippedAll.other:()Lscala/collection/Iterable;
Asciz	scala/collection/IterableLike;
class	scala/collection/IterableLike
InterfaceMethod	scala/collection/IterableLike.iterator:()Lscala/collection/Iterator;
Asciz	thisElem;
Asciz	()Ljava/lang/Object;;
NameAndType	thisElem:()Ljava/lang/Object;
InterfaceMethod	scala/collection/IndexedSeqViewLike$ZippedAll.thisElem:()Ljava/lang/Object;
Asciz	thatElem;
NameAndType	thatElem:()Ljava/lang/Object;
InterfaceMethod	scala/collection/IndexedSeqViewLike$ZippedAll.thatElem:()Ljava/lang/Object;
Asciz	scala/collection/Iterator;
class	scala/collection/Iterator
Asciz	zipAll;
Asciz	(Lscala/collection/Iterator;Ljava/lang/Object;Ljava/lang/Object;)Lscala/collection/Iterator;;
NameAndType	zipAll:(Lscala/collection/Iterator;Ljava/lang/Object;Ljava/lang/Object;)Lscala/collection/Iterator;
InterfaceMethod	scala/collection/Iterator.zipAll:(Lscala/collection/Iterator;Ljava/lang/Object;Ljava/lang/Object;)Lscala/collection/Iterator;
Asciz	$this;
Asciz	Lscala/collection/IndexedSeqViewLike$ZippedAll;;
Asciz	LocalVariableTable;
Asciz	length;
Asciz	(Lscala/collection/IndexedSeqViewLike$ZippedAll;)I;
Asciz	scala/Predef$;
class	scala/Predef$
Asciz	MODULE$;
Asciz	Lscala/Predef$;;
NameAndType	MODULE$:Lscala/Predef$;
Field	scala/Predef$.MODULE$:Lscala/Predef$;
Asciz	scala/collection/SeqLike;
class	scala/collection/SeqLike
Asciz	()I;
NameAndType	length:()I
InterfaceMethod	scala/collection/SeqLike.length:()I
Asciz	intWrapper;
Asciz	(I)Lscala/runtime/RichInt;;
NameAndType	intWrapper:(I)Lscala/runtime/RichInt;
Method	scala/Predef$.intWrapper:(I)Lscala/runtime/RichInt;
Asciz	scala/collection/TraversableLike;
class	scala/collection/TraversableLike
Asciz	size;
NameAndType	size:()I
InterfaceMethod	scala/collection/TraversableLike.size:()I
Asciz	scala/runtime/RichInt;
class	scala/runtime/RichInt
Asciz	max;
Asciz	(I)I;
NameAndType	max:(I)I
Method	scala/runtime/RichInt.max:(I)I
Asciz	apply;
Asciz	(Lscala/collection/IndexedSeqViewLike$ZippedAll;I)Lscala/Tuple2;;
Asciz	(I)Ljava/lang/Object;;
NameAndType	apply:(I)Ljava/lang/Object;
InterfaceMethod	scala/collection/SeqLike.apply:(I)Ljava/lang/Object;
Asciz	drop;
NameAndType	drop:(I)Ljava/lang/Object;
InterfaceMethod	scala/collection/TraversableLike.drop:(I)Ljava/lang/Object;
Asciz	head;
NameAndType	head:()Ljava/lang/Object;
InterfaceMethod	scala/collection/IterableLike.head:()Ljava/lang/Object;
Asciz	scala/Tuple2;
class	scala/Tuple2
Asciz	<init>;
Asciz	(Ljava/lang/Object;Ljava/lang/Object;)V;
NameAndType	"<init>":(Ljava/lang/Object;Ljava/lang/Object;)V
Method	scala/Tuple2."<init>":(Ljava/lang/Object;Ljava/lang/Object;)V
Asciz	idx;
Asciz	I;
Asciz	z1;
Asciz	Ljava/lang/Object;;
Asciz	z2;
Asciz	stringPrefix;
Asciz	(Lscala/collection/IndexedSeqViewLike$ZippedAll;)Ljava/lang/String;;
Asciz	scala/collection/mutable/StringBuilder;
class	scala/collection/mutable/StringBuilder
Asciz	()V;
NameAndType	"<init>":()V
Method	scala/collection/mutable/StringBuilder."<init>":()V
Asciz	scala/collection/IndexedSeqViewLike;
class	scala/collection/IndexedSeqViewLike
Asciz	()Ljava/lang/String;;
NameAndType	stringPrefix:()Ljava/lang/String;
InterfaceMethod	scala/collection/IndexedSeqViewLike.stringPrefix:()Ljava/lang/String;
Asciz	append;
Asciz	(Ljava/lang/Object;)Lscala/collection/mutable/StringBuilder;;
NameAndType	append:(Ljava/lang/Object;)Lscala/collection/mutable/StringBuilder;
Method	scala/collection/mutable/StringBuilder.append:(Ljava/lang/Object;)Lscala/collection/mutable/StringBuilder;
Asciz	Z;
String	Z
Asciz	toString;
NameAndType	toString:()Ljava/lang/String;
Method	scala/collection/mutable/StringBuilder.toString:()Ljava/lang/String;
Asciz	$init$;
Asciz	(Lscala/collection/IndexedSeqViewLike$ZippedAll;)V;
Asciz	Scala;
Asciz	InnerClasses;
Asciz	ZippedAll;
Asciz	scala/collection/IndexedSeqViewLike$ZippedAll$class;
class	scala/collection/IndexedSeqViewLike$ZippedAll$class
Asciz	java/lang/Object;
class	java/lang/Object

{
public static scala.collection.Iterator iterator(scala.collection.IndexedSeqViewLike$ZippedAll);
  Signature: (Lscala/collection/IndexedSeqViewLike$ZippedAll;)Lscala/collection/Iterator;
  Code:
   Stack=4, Locals=1, Args_size=1
	aload_0
	invokeinterface	InterfaceMethod scala/collection/IndexedSeqViewLike$ZippedAll.scala$collection$IndexedSeqViewLike$ZippedAll$$$outer:()Lscala/collection/IndexedSeqViewLike;
	invokeinterface	InterfaceMethod scala/collection/IndexedSeqLike.iterator:()Lscala/collection/Iterator;
	aload_0
	invokeinterface	InterfaceMethod scala/collection/IndexedSeqViewLike$ZippedAll.other:()Lscala/collection/Iterable;
	invokeinterface	InterfaceMethod scala/collection/IterableLike.iterator:()Lscala/collection/Iterator;
	aload_0
	invokeinterface	InterfaceMethod scala/collection/IndexedSeqViewLike$ZippedAll.thisElem:()Ljava/lang/Object;
	aload_0
	invokeinterface	InterfaceMethod scala/collection/IndexedSeqViewLike$ZippedAll.thatElem:()Ljava/lang/Object;
	invokeinterface	InterfaceMethod scala/collection/Iterator.zipAll:(Lscala/collection/Iterator;Ljava/lang/Object;Ljava/lang/Object;)Lscala/collection/Iterator;
	areturn
  Labels:
  LocalVariableTable: 
   Start  Length  Slot  Name   Signature
   0      40      0    $this       Lscala/collection/IndexedSeqViewLike$ZippedAll;


public static int length(scala.collection.IndexedSeqViewLike$ZippedAll);
  Signature: (Lscala/collection/IndexedSeqViewLike$ZippedAll;)I
  Code:
   Stack=2, Locals=1, Args_size=1
	getstatic	Field scala/Predef$.MODULE$:Lscala/Predef$;
	aload_0
	invokeinterface	InterfaceMethod scala/collection/IndexedSeqViewLike$ZippedAll.scala$collection$IndexedSeqViewLike$ZippedAll$$$outer:()Lscala/collection/IndexedSeqViewLike;
	invokeinterface	InterfaceMethod scala/collection/SeqLike.length:()I
	invokevirtual	Method scala/Predef$.intWrapper:(I)Lscala/runtime/RichInt;
	aload_0
	invokeinterface	InterfaceMethod scala/collection/IndexedSeqViewLike$ZippedAll.other:()Lscala/collection/Iterable;
	invokeinterface	InterfaceMethod scala/collection/TraversableLike.size:()I
	invokevirtual	Method scala/runtime/RichInt.max:(I)I
	ireturn
  Labels:
  LocalVariableTable: 
   Start  Length  Slot  Name   Signature
   0      32      0    $this       Lscala/collection/IndexedSeqViewLike$ZippedAll;


public static scala.Tuple2 apply(scala.collection.IndexedSeqViewLike$ZippedAll, int);
  Signature: (Lscala/collection/IndexedSeqViewLike$ZippedAll;I)Lscala/Tuple2;
  Code:
   Stack=4, Locals=4, Args_size=2
	iload_1
	aload_0
	invokeinterface	InterfaceMethod scala/collection/IndexedSeqViewLike$ZippedAll.scala$collection$IndexedSeqViewLike$ZippedAll$$$outer:()Lscala/collection/IndexedSeqViewLike;
	invokeinterface	InterfaceMethod scala/collection/SeqLike.length:()I
	if_icmpge	l1 // aload_0
	aload_0
	invokeinterface	InterfaceMethod scala/collection/IndexedSeqViewLike$ZippedAll.scala$collection$IndexedSeqViewLike$ZippedAll$$$outer:()Lscala/collection/IndexedSeqViewLike;
	iload_1
	invokeinterface	InterfaceMethod scala/collection/SeqLike.apply:(I)Ljava/lang/Object;
	goto	l2 // astore_2
l1	aload_0
	invokeinterface	InterfaceMethod scala/collection/IndexedSeqViewLike$ZippedAll.thisElem:()Ljava/lang/Object;
l2	astore_2
	iload_1
	aload_0
	invokeinterface	InterfaceMethod scala/collection/IndexedSeqViewLike$ZippedAll.other:()Lscala/collection/Iterable;
	invokeinterface	InterfaceMethod scala/collection/TraversableLike.size:()I
	if_icmpge	l3 // aload_0
	aload_0
	invokeinterface	InterfaceMethod scala/collection/IndexedSeqViewLike$ZippedAll.other:()Lscala/collection/Iterable;
	iload_1
	invokeinterface	InterfaceMethod scala/collection/TraversableLike.drop:(I)Ljava/lang/Object;
	checkcast	class scala/collection/IterableLike
	invokeinterface	InterfaceMethod scala/collection/IterableLike.head:()Ljava/lang/Object;
	goto	l4 // astore_3
l3	aload_0
	invokeinterface	InterfaceMethod scala/collection/IndexedSeqViewLike$ZippedAll.thatElem:()Ljava/lang/Object;
l4	astore_3
	new	class scala/Tuple2
	dup
	aload_2
	aload_3
	invokespecial	Method scala/Tuple2."<init>":(Ljava/lang/Object;Ljava/lang/Object;)V
	areturn
  Labels:
   	l1 = 30 // aload_0
   	l2 = 36 // astore_2
   	l3 = 75 // aload_0
   	l4 = 81 // astore_3
  LocalVariableTable: 
   Start  Length  Slot  Name   Signature
   0      92      0    $this       Lscala/collection/IndexedSeqViewLike$ZippedAll;
   0      92      1    idx       I
   37      54      2    z1       Ljava/lang/Object;
   82      9      3    z2       Ljava/lang/Object;


public static java.lang.String stringPrefix(scala.collection.IndexedSeqViewLike$ZippedAll);
  Signature: (Lscala/collection/IndexedSeqViewLike$ZippedAll;)Ljava/lang/String;
  Code:
   Stack=2, Locals=1, Args_size=1
	new	class scala/collection/mutable/StringBuilder
	dup
	invokespecial	Method scala/collection/mutable/StringBuilder."<init>":()V
	aload_0
	invokeinterface	InterfaceMethod scala/collection/IndexedSeqViewLike$ZippedAll.scala$collection$IndexedSeqViewLike$ZippedAll$$$outer:()Lscala/collection/IndexedSeqViewLike;
	invokeinterface	InterfaceMethod scala/collection/IndexedSeqViewLike.stringPrefix:()Ljava/lang/String;
	invokevirtual	Method scala/collection/mutable/StringBuilder.append:(Ljava/lang/Object;)Lscala/collection/mutable/StringBuilder;
	ldc	String Z
	invokevirtual	Method scala/collection/mutable/StringBuilder.append:(Ljava/lang/Object;)Lscala/collection/mutable/StringBuilder;
	invokevirtual	Method scala/collection/mutable/StringBuilder.toString:()Ljava/lang/String;
	areturn
  Labels:
  LocalVariableTable: 
   Start  Length  Slot  Name   Signature
   0      30      0    $this       Lscala/collection/IndexedSeqViewLike$ZippedAll;


public static void $init$(scala.collection.IndexedSeqViewLike$ZippedAll);
  Signature: (Lscala/collection/IndexedSeqViewLike$ZippedAll;)V
  Code:
   Stack=0, Locals=1, Args_size=1
	return
  Labels:
  LocalVariableTable: 
   Start  Length  Slot  Name   Signature
   0      1      0    $this       Lscala/collection/IndexedSeqViewLike$ZippedAll;


}

