Compiled from "IndexedSeqViewLike.scala"
public abstract class scala.collection.IndexedSeqViewLike$Zipped$class extends java.lang.Object
  SourceFile: "IndexedSeqViewLike.scala"
  Scala: length = 0x
   
  InnerClass: 
   public abstract Zipped=class scala/collection/IndexedSeqViewLike$Zipped of class scala/collection/IndexedSeqViewLike
  minor version: 0
  major version: 49
  Constant pool:
Asciz	SourceFile;
Asciz	IndexedSeqViewLike.scala;
Asciz	length;
Asciz	(Lscala/collection/IndexedSeqViewLike$Zipped;)I;
Asciz	Code;
Asciz	LineNumberTable;
Asciz	scala/collection/IndexedSeqViewLike$Zipped;
class	scala/collection/IndexedSeqViewLike$Zipped
Asciz	other;
Asciz	()Lscala/collection/Iterable;;
NameAndType	other:()Lscala/collection/Iterable;
InterfaceMethod	scala/collection/IndexedSeqViewLike$Zipped.other:()Lscala/collection/Iterable;
Asciz	scala/collection/TraversableLike;
class	scala/collection/TraversableLike
Asciz	hasDefiniteSize;
Asciz	()Z;
NameAndType	hasDefiniteSize:()Z
InterfaceMethod	scala/collection/TraversableLike.hasDefiniteSize:()Z
Asciz	scala/Predef$;
class	scala/Predef$
Asciz	MODULE$;
Asciz	Lscala/Predef$;;
NameAndType	MODULE$:Lscala/Predef$;
Field	scala/Predef$.MODULE$:Lscala/Predef$;
Asciz	scala$collection$IndexedSeqViewLike$Zipped$$$outer;
Asciz	()Lscala/collection/IndexedSeqViewLike;;
NameAndType	scala$collection$IndexedSeqViewLike$Zipped$$$outer:()Lscala/collection/IndexedSeqViewLike;
InterfaceMethod	scala/collection/IndexedSeqViewLike$Zipped.scala$collection$IndexedSeqViewLike$Zipped$$$outer:()Lscala/collection/IndexedSeqViewLike;
Asciz	scala/collection/SeqLike;
class	scala/collection/SeqLike
Asciz	()I;
NameAndType	length:()I
InterfaceMethod	scala/collection/SeqLike.length:()I
Asciz	intWrapper;
Asciz	(I)Lscala/runtime/RichInt;;
NameAndType	intWrapper:(I)Lscala/runtime/RichInt;
Method	scala/Predef$.intWrapper:(I)Lscala/runtime/RichInt;
Asciz	size;
NameAndType	size:()I
InterfaceMethod	scala/collection/TraversableLike.size:()I
Asciz	scala/runtime/RichInt;
class	scala/runtime/RichInt
Asciz	min;
Asciz	(I)I;
NameAndType	min:(I)I
Method	scala/runtime/RichInt.min:(I)I
Asciz	scala/collection/IterableLike;
class	scala/collection/IterableLike
Asciz	take;
Asciz	(I)Ljava/lang/Object;;
NameAndType	take:(I)Ljava/lang/Object;
InterfaceMethod	scala/collection/IterableLike.take:(I)Ljava/lang/Object;
Asciz	$this;
Asciz	Lscala/collection/IndexedSeqViewLike$Zipped;;
Asciz	LocalVariableTable;
Asciz	apply;
Asciz	(Lscala/collection/IndexedSeqViewLike$Zipped;I)Lscala/Tuple2;;
Asciz	scala/Tuple2;
class	scala/Tuple2
NameAndType	apply:(I)Ljava/lang/Object;
InterfaceMethod	scala/collection/SeqLike.apply:(I)Ljava/lang/Object;
Asciz	iterator;
Asciz	()Lscala/collection/Iterator;;
NameAndType	iterator:()Lscala/collection/Iterator;
InterfaceMethod	scala/collection/IterableLike.iterator:()Lscala/collection/Iterator;
Asciz	scala/collection/Iterator;
class	scala/collection/Iterator
Asciz	drop;
Asciz	(I)Lscala/collection/Iterator;;
NameAndType	drop:(I)Lscala/collection/Iterator;
InterfaceMethod	scala/collection/Iterator.drop:(I)Lscala/collection/Iterator;
Asciz	next;
Asciz	()Ljava/lang/Object;;
NameAndType	next:()Ljava/lang/Object;
InterfaceMethod	scala/collection/Iterator.next:()Ljava/lang/Object;
Asciz	<init>;
Asciz	(Ljava/lang/Object;Ljava/lang/Object;)V;
NameAndType	"<init>":(Ljava/lang/Object;Ljava/lang/Object;)V
Method	scala/Tuple2."<init>":(Ljava/lang/Object;Ljava/lang/Object;)V
Asciz	idx;
Asciz	I;
Asciz	stringPrefix;
Asciz	(Lscala/collection/IndexedSeqViewLike$Zipped;)Ljava/lang/String;;
Asciz	scala/collection/mutable/StringBuilder;
class	scala/collection/mutable/StringBuilder
Asciz	()V;
NameAndType	"<init>":()V
Method	scala/collection/mutable/StringBuilder."<init>":()V
Asciz	scala/collection/IndexedSeqViewLike;
class	scala/collection/IndexedSeqViewLike
Asciz	()Ljava/lang/String;;
NameAndType	stringPrefix:()Ljava/lang/String;
InterfaceMethod	scala/collection/IndexedSeqViewLike.stringPrefix:()Ljava/lang/String;
Asciz	append;
Asciz	(Ljava/lang/Object;)Lscala/collection/mutable/StringBuilder;;
NameAndType	append:(Ljava/lang/Object;)Lscala/collection/mutable/StringBuilder;
Method	scala/collection/mutable/StringBuilder.append:(Ljava/lang/Object;)Lscala/collection/mutable/StringBuilder;
Asciz	Z;
String	Z
Asciz	toString;
NameAndType	toString:()Ljava/lang/String;
Method	scala/collection/mutable/StringBuilder.toString:()Ljava/lang/String;
Asciz	$init$;
Asciz	(Lscala/collection/IndexedSeqViewLike$Zipped;)V;
Asciz	Scala;
Asciz	InnerClasses;
Asciz	Zipped;
Asciz	scala/collection/IndexedSeqViewLike$Zipped$class;
class	scala/collection/IndexedSeqViewLike$Zipped$class
Asciz	java/lang/Object;
class	java/lang/Object

{
public static int length(scala.collection.IndexedSeqViewLike$Zipped);
  Signature: (Lscala/collection/IndexedSeqViewLike$Zipped;)I
  Code:
   Stack=2, Locals=1, Args_size=1
	aload_0
	invokeinterface	InterfaceMethod scala/collection/IndexedSeqViewLike$Zipped.other:()Lscala/collection/Iterable;
	invokeinterface	InterfaceMethod scala/collection/TraversableLike.hasDefiniteSize:()Z
	ifeq	l1 // aload_0
	getstatic	Field scala/Predef$.MODULE$:Lscala/Predef$;
	aload_0
	invokeinterface	InterfaceMethod scala/collection/IndexedSeqViewLike$Zipped.scala$collection$IndexedSeqViewLike$Zipped$$$outer:()Lscala/collection/IndexedSeqViewLike;
	invokeinterface	InterfaceMethod scala/collection/SeqLike.length:()I
	invokevirtual	Method scala/Predef$.intWrapper:(I)Lscala/runtime/RichInt;
	aload_0
	invokeinterface	InterfaceMethod scala/collection/IndexedSeqViewLike$Zipped.other:()Lscala/collection/Iterable;
	invokeinterface	InterfaceMethod scala/collection/TraversableLike.size:()I
	invokevirtual	Method scala/runtime/RichInt.min:(I)I
	goto	l2 // ireturn
l1	aload_0
	invokeinterface	InterfaceMethod scala/collection/IndexedSeqViewLike$Zipped.other:()Lscala/collection/Iterable;
	aload_0
	invokeinterface	InterfaceMethod scala/collection/IndexedSeqViewLike$Zipped.scala$collection$IndexedSeqViewLike$Zipped$$$outer:()Lscala/collection/IndexedSeqViewLike;
	invokeinterface	InterfaceMethod scala/collection/SeqLike.length:()I
	invokeinterface	InterfaceMethod scala/collection/IterableLike.take:(I)Ljava/lang/Object;
	checkcast	class scala/collection/TraversableLike
	invokeinterface	InterfaceMethod scala/collection/TraversableLike.size:()I
l2	ireturn
  Labels:
   	l1 = 48 // aload_0
   	l2 = 78 // ireturn
  LocalVariableTable: 
   Start  Length  Slot  Name   Signature
   0      79      0    $this       Lscala/collection/IndexedSeqViewLike$Zipped;


public static scala.Tuple2 apply(scala.collection.IndexedSeqViewLike$Zipped, int);
  Signature: (Lscala/collection/IndexedSeqViewLike$Zipped;I)Lscala/Tuple2;
  Code:
   Stack=5, Locals=2, Args_size=2
	new	class scala/Tuple2
	dup
	aload_0
	invokeinterface	InterfaceMethod scala/collection/IndexedSeqViewLike$Zipped.scala$collection$IndexedSeqViewLike$Zipped$$$outer:()Lscala/collection/IndexedSeqViewLike;
	iload_1
	invokeinterface	InterfaceMethod scala/collection/SeqLike.apply:(I)Ljava/lang/Object;
	aload_0
	invokeinterface	InterfaceMethod scala/collection/IndexedSeqViewLike$Zipped.other:()Lscala/collection/Iterable;
	invokeinterface	InterfaceMethod scala/collection/IterableLike.iterator:()Lscala/collection/Iterator;
	iload_1
	invokeinterface	InterfaceMethod scala/collection/Iterator.drop:(I)Lscala/collection/Iterator;
	invokeinterface	InterfaceMethod scala/collection/Iterator.next:()Ljava/lang/Object;
	invokespecial	Method scala/Tuple2."<init>":(Ljava/lang/Object;Ljava/lang/Object;)V
	areturn
  Labels:
  LocalVariableTable: 
   Start  Length  Slot  Name   Signature
   0      42      0    $this       Lscala/collection/IndexedSeqViewLike$Zipped;
   0      42      1    idx       I


public static java.lang.String stringPrefix(scala.collection.IndexedSeqViewLike$Zipped);
  Signature: (Lscala/collection/IndexedSeqViewLike$Zipped;)Ljava/lang/String;
  Code:
   Stack=2, Locals=1, Args_size=1
	new	class scala/collection/mutable/StringBuilder
	dup
	invokespecial	Method scala/collection/mutable/StringBuilder."<init>":()V
	aload_0
	invokeinterface	InterfaceMethod scala/collection/IndexedSeqViewLike$Zipped.scala$collection$IndexedSeqViewLike$Zipped$$$outer:()Lscala/collection/IndexedSeqViewLike;
	invokeinterface	InterfaceMethod scala/collection/IndexedSeqViewLike.stringPrefix:()Ljava/lang/String;
	invokevirtual	Method scala/collection/mutable/StringBuilder.append:(Ljava/lang/Object;)Lscala/collection/mutable/StringBuilder;
	ldc	String Z
	invokevirtual	Method scala/collection/mutable/StringBuilder.append:(Ljava/lang/Object;)Lscala/collection/mutable/StringBuilder;
	invokevirtual	Method scala/collection/mutable/StringBuilder.toString:()Ljava/lang/String;
	areturn
  Labels:
  LocalVariableTable: 
   Start  Length  Slot  Name   Signature
   0      30      0    $this       Lscala/collection/IndexedSeqViewLike$Zipped;


public static void $init$(scala.collection.IndexedSeqViewLike$Zipped);
  Signature: (Lscala/collection/IndexedSeqViewLike$Zipped;)V
  Code:
   Stack=0, Locals=1, Args_size=1
	return
  Labels:
  LocalVariableTable: 
   Start  Length  Slot  Name   Signature
   0      1      0    $this       Lscala/collection/IndexedSeqViewLike$Zipped;


}

