Compiled from "IndexedSeqViewLike.scala"
public abstract class scala.collection.IndexedSeqViewLike$class extends java.lang.Object
  SourceFile: "IndexedSeqViewLike.scala"
  Scala: length = 0x
   
  InnerClass: 
   public final $anon$1=class scala/collection/IndexedSeqViewLike$$anon$1 of class scala/collection/IndexedSeqViewLike
   public final $anon$2=class scala/collection/IndexedSeqViewLike$$anon$2 of class scala/collection/IndexedSeqViewLike
   public final $anon$3=class scala/collection/IndexedSeqViewLike$$anon$3 of class scala/collection/IndexedSeqViewLike
   public final $anon$4=class scala/collection/IndexedSeqViewLike$$anon$4 of class scala/collection/IndexedSeqViewLike
   public final $anon$5=class scala/collection/IndexedSeqViewLike$$anon$5 of class scala/collection/IndexedSeqViewLike
   public final $anon$6=class scala/collection/IndexedSeqViewLike$$anon$6 of class scala/collection/IndexedSeqViewLike
   public final $anon$7=class scala/collection/IndexedSeqViewLike$$anon$7 of class scala/collection/IndexedSeqViewLike
   public final $anon$8=class scala/collection/IndexedSeqViewLike$$anon$8 of class scala/collection/IndexedSeqViewLike
   public final $anon$9=class scala/collection/IndexedSeqViewLike$$anon$9 of class scala/collection/IndexedSeqViewLike
   public final $anon$10=class scala/collection/IndexedSeqViewLike$$anon$10 of class scala/collection/IndexedSeqViewLike
   public final $anon$11=class scala/collection/IndexedSeqViewLike$$anon$11 of class scala/collection/IndexedSeqViewLike
   public abstract Transformed=class scala/collection/IndexedSeqViewLike$Transformed of class scala/collection/IndexedSeqViewLike
  minor version: 0
  major version: 49
  Constant pool:
Asciz	SourceFile;
Asciz	IndexedSeqViewLike.scala;
Asciz	$init$;
Asciz	(Lscala/collection/IndexedSeqViewLike;)V;
Asciz	Code;
Asciz	LineNumberTable;
Asciz	$this;
Asciz	Lscala/collection/IndexedSeqViewLike;;
Asciz	LocalVariableTable;
Asciz	stringPrefix;
Asciz	(Lscala/collection/IndexedSeqViewLike;)Ljava/lang/String;;
Asciz	IndexedSeqView;
String	IndexedSeqView
Asciz	newPatched;
Asciz	(Lscala/collection/IndexedSeqViewLike;ILscala/collection/Seq;I)Lscala/collection/IndexedSeqViewLike$Transformed;;
Asciz	scala/collection/IndexedSeqViewLike$$anon$9;
class	scala/collection/IndexedSeqViewLike$$anon$9
Asciz	<init>;
Asciz	(Lscala/collection/IndexedSeqViewLike;ILscala/collection/Seq;I)V;
NameAndType	"<init>":(Lscala/collection/IndexedSeqViewLike;ILscala/collection/Seq;I)V
Method	scala/collection/IndexedSeqViewLike$$anon$9."<init>":(Lscala/collection/IndexedSeqViewLike;ILscala/collection/Seq;I)V
Asciz	_from$1;
Asciz	I;
Asciz	_patch$1;
Asciz	Lscala/collection/Seq;;
Asciz	_replaced$1;
Asciz	newReversed;
Asciz	(Lscala/collection/IndexedSeqViewLike;)Lscala/collection/IndexedSeqViewLike$Transformed;;
Asciz	scala/collection/IndexedSeqViewLike$$anon$8;
class	scala/collection/IndexedSeqViewLike$$anon$8
NameAndType	"<init>":(Lscala/collection/IndexedSeqViewLike;)V
Method	scala/collection/IndexedSeqViewLike$$anon$8."<init>":(Lscala/collection/IndexedSeqViewLike;)V
Asciz	newZippedAll;
Asciz	(Lscala/collection/IndexedSeqViewLike;Lscala/collection/Iterable;Ljava/lang/Object;Ljava/lang/Object;)Lscala/collection/IndexedSeqViewLike$Transformed;;
Asciz	scala/collection/IndexedSeqViewLike$$anon$11;
class	scala/collection/IndexedSeqViewLike$$anon$11
Asciz	(Lscala/collection/IndexedSeqViewLike;Lscala/collection/Iterable;Ljava/lang/Object;Ljava/lang/Object;)V;
NameAndType	"<init>":(Lscala/collection/IndexedSeqViewLike;Lscala/collection/Iterable;Ljava/lang/Object;Ljava/lang/Object;)V
Method	scala/collection/IndexedSeqViewLike$$anon$11."<init>":(Lscala/collection/IndexedSeqViewLike;Lscala/collection/Iterable;Ljava/lang/Object;Ljava/lang/Object;)V
Asciz	that$2;
Asciz	Lscala/collection/Iterable;;
Asciz	_thisElem$1;
Asciz	Ljava/lang/Object;;
Asciz	_thatElem$1;
Asciz	newZipped;
Asciz	(Lscala/collection/IndexedSeqViewLike;Lscala/collection/Iterable;)Lscala/collection/IndexedSeqViewLike$Transformed;;
Asciz	scala/collection/IndexedSeqViewLike$$anon$10;
class	scala/collection/IndexedSeqViewLike$$anon$10
Asciz	(Lscala/collection/IndexedSeqViewLike;Lscala/collection/Iterable;)V;
NameAndType	"<init>":(Lscala/collection/IndexedSeqViewLike;Lscala/collection/Iterable;)V
Method	scala/collection/IndexedSeqViewLike$$anon$10."<init>":(Lscala/collection/IndexedSeqViewLike;Lscala/collection/Iterable;)V
Asciz	that$3;
Asciz	newTakenWhile;
Asciz	(Lscala/collection/IndexedSeqViewLike;Lscala/Function1;)Lscala/collection/IndexedSeqViewLike$Transformed;;
Asciz	scala/collection/IndexedSeqViewLike$$anon$7;
class	scala/collection/IndexedSeqViewLike$$anon$7
Asciz	(Lscala/collection/IndexedSeqViewLike;Lscala/Function1;)V;
NameAndType	"<init>":(Lscala/collection/IndexedSeqViewLike;Lscala/Function1;)V
Method	scala/collection/IndexedSeqViewLike$$anon$7."<init>":(Lscala/collection/IndexedSeqViewLike;Lscala/Function1;)V
Asciz	p$1;
Asciz	Lscala/Function1;;
Asciz	newDroppedWhile;
Asciz	scala/collection/IndexedSeqViewLike$$anon$6;
class	scala/collection/IndexedSeqViewLike$$anon$6
Method	scala/collection/IndexedSeqViewLike$$anon$6."<init>":(Lscala/collection/IndexedSeqViewLike;Lscala/Function1;)V
Asciz	p$2;
Asciz	newSliced;
Asciz	(Lscala/collection/IndexedSeqViewLike;II)Lscala/collection/IndexedSeqViewLike$Transformed;;
Asciz	scala/collection/IndexedSeqViewLike$$anon$5;
class	scala/collection/IndexedSeqViewLike$$anon$5
Asciz	(Lscala/collection/IndexedSeqViewLike;II)V;
NameAndType	"<init>":(Lscala/collection/IndexedSeqViewLike;II)V
Method	scala/collection/IndexedSeqViewLike$$anon$5."<init>":(Lscala/collection/IndexedSeqViewLike;II)V
Asciz	_from$2;
Asciz	_until$1;
Asciz	newFiltered;
Asciz	scala/collection/IndexedSeqViewLike$$anon$4;
class	scala/collection/IndexedSeqViewLike$$anon$4
Method	scala/collection/IndexedSeqViewLike$$anon$4."<init>":(Lscala/collection/IndexedSeqViewLike;Lscala/Function1;)V
Asciz	p$3;
Asciz	newFlatMapped;
Asciz	scala/collection/IndexedSeqViewLike$$anon$3;
class	scala/collection/IndexedSeqViewLike$$anon$3
Method	scala/collection/IndexedSeqViewLike$$anon$3."<init>":(Lscala/collection/IndexedSeqViewLike;Lscala/Function1;)V
Asciz	f$1;
Asciz	newMapped;
Asciz	scala/collection/IndexedSeqViewLike$$anon$2;
class	scala/collection/IndexedSeqViewLike$$anon$2
Method	scala/collection/IndexedSeqViewLike$$anon$2."<init>":(Lscala/collection/IndexedSeqViewLike;Lscala/Function1;)V
Asciz	f$2;
Asciz	newAppended;
Asciz	(Lscala/collection/IndexedSeqViewLike;Lscala/collection/Traversable;)Lscala/collection/IndexedSeqViewLike$Transformed;;
Asciz	scala/collection/IndexedSeqViewLike$$anon$1;
class	scala/collection/IndexedSeqViewLike$$anon$1
Asciz	(Lscala/collection/IndexedSeqViewLike;Lscala/collection/Traversable;)V;
NameAndType	"<init>":(Lscala/collection/IndexedSeqViewLike;Lscala/collection/Traversable;)V
Method	scala/collection/IndexedSeqViewLike$$anon$1."<init>":(Lscala/collection/IndexedSeqViewLike;Lscala/collection/Traversable;)V
Asciz	that$1;
Asciz	Lscala/collection/Traversable;;
Asciz	Scala;
Asciz	InnerClasses;
Asciz	scala/collection/IndexedSeqViewLike;
class	scala/collection/IndexedSeqViewLike
Asciz	$anon$1;
Asciz	$anon$2;
Asciz	$anon$3;
Asciz	$anon$4;
Asciz	$anon$5;
Asciz	$anon$6;
Asciz	$anon$7;
Asciz	$anon$8;
Asciz	$anon$9;
Asciz	$anon$10;
Asciz	$anon$11;
Asciz	scala/collection/IndexedSeqViewLike$Transformed;
class	scala/collection/IndexedSeqViewLike$Transformed
Asciz	Transformed;
Asciz	scala/collection/IndexedSeqViewLike$class;
class	scala/collection/IndexedSeqViewLike$class
Asciz	java/lang/Object;
class	java/lang/Object

{
public static void $init$(scala.collection.IndexedSeqViewLike);
  Signature: (Lscala/collection/IndexedSeqViewLike;)V
  Code:
   Stack=0, Locals=1, Args_size=1
	return
  Labels:
  LocalVariableTable: 
   Start  Length  Slot  Name   Signature
   0      1      0    $this       Lscala/collection/IndexedSeqViewLike;


public static java.lang.String stringPrefix(scala.collection.IndexedSeqViewLike);
  Signature: (Lscala/collection/IndexedSeqViewLike;)Ljava/lang/String;
  Code:
   Stack=1, Locals=1, Args_size=1
	ldc	String IndexedSeqView
	areturn
  Labels:
  LocalVariableTable: 
   Start  Length  Slot  Name   Signature
   0      3      0    $this       Lscala/collection/IndexedSeqViewLike;


public static scala.collection.IndexedSeqViewLike$Transformed newPatched(scala.collection.IndexedSeqViewLike, int, scala.collection.Seq, int);
  Signature: (Lscala/collection/IndexedSeqViewLike;ILscala/collection/Seq;I)Lscala/collection/IndexedSeqViewLike$Transformed;
  Code:
   Stack=6, Locals=4, Args_size=4
	new	class scala/collection/IndexedSeqViewLike$$anon$9
	dup
	aload_0
	iload_1
	aload_2
	iload_3
	invokespecial	Method scala/collection/IndexedSeqViewLike$$anon$9."<init>":(Lscala/collection/IndexedSeqViewLike;ILscala/collection/Seq;I)V
	areturn
  Labels:
  LocalVariableTable: 
   Start  Length  Slot  Name   Signature
   0      12      0    $this       Lscala/collection/IndexedSeqViewLike;
   0      12      1    _from$1       I
   0      12      2    _patch$1       Lscala/collection/Seq;
   0      12      3    _replaced$1       I


public static scala.collection.IndexedSeqViewLike$Transformed newReversed(scala.collection.IndexedSeqViewLike);
  Signature: (Lscala/collection/IndexedSeqViewLike;)Lscala/collection/IndexedSeqViewLike$Transformed;
  Code:
   Stack=3, Locals=1, Args_size=1
	new	class scala/collection/IndexedSeqViewLike$$anon$8
	dup
	aload_0
	invokespecial	Method scala/collection/IndexedSeqViewLike$$anon$8."<init>":(Lscala/collection/IndexedSeqViewLike;)V
	areturn
  Labels:
  LocalVariableTable: 
   Start  Length  Slot  Name   Signature
   0      9      0    $this       Lscala/collection/IndexedSeqViewLike;


public static scala.collection.IndexedSeqViewLike$Transformed newZippedAll(scala.collection.IndexedSeqViewLike, scala.collection.Iterable, java.lang.Object, java.lang.Object);
  Signature: (Lscala/collection/IndexedSeqViewLike;Lscala/collection/Iterable;Ljava/lang/Object;Ljava/lang/Object;)Lscala/collection/IndexedSeqViewLike$Transformed;
  Code:
   Stack=6, Locals=4, Args_size=4
	new	class scala/collection/IndexedSeqViewLike$$anon$11
	dup
	aload_0
	aload_1
	aload_2
	aload_3
	invokespecial	Method scala/collection/IndexedSeqViewLike$$anon$11."<init>":(Lscala/collection/IndexedSeqViewLike;Lscala/collection/Iterable;Ljava/lang/Object;Ljava/lang/Object;)V
	areturn
  Labels:
  LocalVariableTable: 
   Start  Length  Slot  Name   Signature
   0      12      0    $this       Lscala/collection/IndexedSeqViewLike;
   0      12      1    that$2       Lscala/collection/Iterable;
   0      12      2    _thisElem$1       Ljava/lang/Object;
   0      12      3    _thatElem$1       Ljava/lang/Object;


public static scala.collection.IndexedSeqViewLike$Transformed newZipped(scala.collection.IndexedSeqViewLike, scala.collection.Iterable);
  Signature: (Lscala/collection/IndexedSeqViewLike;Lscala/collection/Iterable;)Lscala/collection/IndexedSeqViewLike$Transformed;
  Code:
   Stack=4, Locals=2, Args_size=2
	new	class scala/collection/IndexedSeqViewLike$$anon$10
	dup
	aload_0
	aload_1
	invokespecial	Method scala/collection/IndexedSeqViewLike$$anon$10."<init>":(Lscala/collection/IndexedSeqViewLike;Lscala/collection/Iterable;)V
	areturn
  Labels:
  LocalVariableTable: 
   Start  Length  Slot  Name   Signature
   0      10      0    $this       Lscala/collection/IndexedSeqViewLike;
   0      10      1    that$3       Lscala/collection/Iterable;


public static scala.collection.IndexedSeqViewLike$Transformed newTakenWhile(scala.collection.IndexedSeqViewLike, scala.Function1);
  Signature: (Lscala/collection/IndexedSeqViewLike;Lscala/Function1;)Lscala/collection/IndexedSeqViewLike$Transformed;
  Code:
   Stack=4, Locals=2, Args_size=2
	new	class scala/collection/IndexedSeqViewLike$$anon$7
	dup
	aload_0
	aload_1
	invokespecial	Method scala/collection/IndexedSeqViewLike$$anon$7."<init>":(Lscala/collection/IndexedSeqViewLike;Lscala/Function1;)V
	areturn
  Labels:
  LocalVariableTable: 
   Start  Length  Slot  Name   Signature
   0      10      0    $this       Lscala/collection/IndexedSeqViewLike;
   0      10      1    p$1       Lscala/Function1;


public static scala.collection.IndexedSeqViewLike$Transformed newDroppedWhile(scala.collection.IndexedSeqViewLike, scala.Function1);
  Signature: (Lscala/collection/IndexedSeqViewLike;Lscala/Function1;)Lscala/collection/IndexedSeqViewLike$Transformed;
  Code:
   Stack=4, Locals=2, Args_size=2
	new	class scala/collection/IndexedSeqViewLike$$anon$6
	dup
	aload_0
	aload_1
	invokespecial	Method scala/collection/IndexedSeqViewLike$$anon$6."<init>":(Lscala/collection/IndexedSeqViewLike;Lscala/Function1;)V
	areturn
  Labels:
  LocalVariableTable: 
   Start  Length  Slot  Name   Signature
   0      10      0    $this       Lscala/collection/IndexedSeqViewLike;
   0      10      1    p$2       Lscala/Function1;


public static scala.collection.IndexedSeqViewLike$Transformed newSliced(scala.collection.IndexedSeqViewLike, int, int);
  Signature: (Lscala/collection/IndexedSeqViewLike;II)Lscala/collection/IndexedSeqViewLike$Transformed;
  Code:
   Stack=5, Locals=3, Args_size=3
	new	class scala/collection/IndexedSeqViewLike$$anon$5
	dup
	aload_0
	iload_1
	iload_2
	invokespecial	Method scala/collection/IndexedSeqViewLike$$anon$5."<init>":(Lscala/collection/IndexedSeqViewLike;II)V
	areturn
  Labels:
  LocalVariableTable: 
   Start  Length  Slot  Name   Signature
   0      11      0    $this       Lscala/collection/IndexedSeqViewLike;
   0      11      1    _from$2       I
   0      11      2    _until$1       I


public static scala.collection.IndexedSeqViewLike$Transformed newFiltered(scala.collection.IndexedSeqViewLike, scala.Function1);
  Signature: (Lscala/collection/IndexedSeqViewLike;Lscala/Function1;)Lscala/collection/IndexedSeqViewLike$Transformed;
  Code:
   Stack=4, Locals=2, Args_size=2
	new	class scala/collection/IndexedSeqViewLike$$anon$4
	dup
	aload_0
	aload_1
	invokespecial	Method scala/collection/IndexedSeqViewLike$$anon$4."<init>":(Lscala/collection/IndexedSeqViewLike;Lscala/Function1;)V
	areturn
  Labels:
  LocalVariableTable: 
   Start  Length  Slot  Name   Signature
   0      10      0    $this       Lscala/collection/IndexedSeqViewLike;
   0      10      1    p$3       Lscala/Function1;


public static scala.collection.IndexedSeqViewLike$Transformed newFlatMapped(scala.collection.IndexedSeqViewLike, scala.Function1);
  Signature: (Lscala/collection/IndexedSeqViewLike;Lscala/Function1;)Lscala/collection/IndexedSeqViewLike$Transformed;
  Code:
   Stack=4, Locals=2, Args_size=2
	new	class scala/collection/IndexedSeqViewLike$$anon$3
	dup
	aload_0
	aload_1
	invokespecial	Method scala/collection/IndexedSeqViewLike$$anon$3."<init>":(Lscala/collection/IndexedSeqViewLike;Lscala/Function1;)V
	areturn
  Labels:
  LocalVariableTable: 
   Start  Length  Slot  Name   Signature
   0      10      0    $this       Lscala/collection/IndexedSeqViewLike;
   0      10      1    f$1       Lscala/Function1;


public static scala.collection.IndexedSeqViewLike$Transformed newMapped(scala.collection.IndexedSeqViewLike, scala.Function1);
  Signature: (Lscala/collection/IndexedSeqViewLike;Lscala/Function1;)Lscala/collection/IndexedSeqViewLike$Transformed;
  Code:
   Stack=4, Locals=2, Args_size=2
	new	class scala/collection/IndexedSeqViewLike$$anon$2
	dup
	aload_0
	aload_1
	invokespecial	Method scala/collection/IndexedSeqViewLike$$anon$2."<init>":(Lscala/collection/IndexedSeqViewLike;Lscala/Function1;)V
	areturn
  Labels:
  LocalVariableTable: 
   Start  Length  Slot  Name   Signature
   0      10      0    $this       Lscala/collection/IndexedSeqViewLike;
   0      10      1    f$2       Lscala/Function1;


public static scala.collection.IndexedSeqViewLike$Transformed newAppended(scala.collection.IndexedSeqViewLike, scala.collection.Traversable);
  Signature: (Lscala/collection/IndexedSeqViewLike;Lscala/collection/Traversable;)Lscala/collection/IndexedSeqViewLike$Transformed;
  Code:
   Stack=4, Locals=2, Args_size=2
	new	class scala/collection/IndexedSeqViewLike$$anon$1
	dup
	aload_0
	aload_1
	invokespecial	Method scala/collection/IndexedSeqViewLike$$anon$1."<init>":(Lscala/collection/IndexedSeqViewLike;Lscala/collection/Traversable;)V
	areturn
  Labels:
  LocalVariableTable: 
   Start  Length  Slot  Name   Signature
   0      10      0    $this       Lscala/collection/IndexedSeqViewLike;
   0      10      1    that$1       Lscala/collection/Traversable;


}

