Compiled from "IndexedSeqView.scala"
public final class scala.collection.IndexedSeqView$$anon$2 extends java.lang.Object implements scala.collection.generic.CanBuildFrom
  SourceFile: "IndexedSeqView.scala"
  Signature: length = 0x2
   00 24 
  Scala: length = 0x
   
  InnerClass: 
   public final #41= #16 of #40; //$anon$2=class scala/collection/IndexedSeqView$$anon$2 of class scala/collection/IndexedSeqView
   public #42= #30 of #14; //NoBuilder=class scala/collection/TraversableView$NoBuilder of class scala/collection/TraversableView
  minor version: 0
  major version: 49
  Constant pool:
const #1 = Asciz	SourceFile;
const #2 = Asciz	IndexedSeqView.scala;
const #3 = Asciz	<init>;
const #4 = Asciz	()V;
const #5 = Asciz	Code;
const #6 = Asciz	LineNumberTable;
const #7 = Asciz	java/lang/Object;
const #8 = class	#7;	//  java/lang/Object
const #9 = NameAndType	#3:#4;//  "<init>":()V
const #10 = Method	#8.#9;	//  java/lang/Object."<init>":()V
const #11 = Asciz	apply;
const #12 = Asciz	(Ljava/lang/Object;)Lscala/collection/mutable/Builder;;
const #13 = Asciz	scala/collection/TraversableView;
const #14 = class	#13;	//  scala/collection/TraversableView
const #15 = Asciz	scala/collection/IndexedSeqView$$anon$2;
const #16 = class	#15;	//  scala/collection/IndexedSeqView$$anon$2
const #17 = Asciz	(Lscala/collection/TraversableView;)Lscala/collection/TraversableView$NoBuilder;;
const #18 = NameAndType	#11:#17;//  apply:(Lscala/collection/TraversableView;)Lscala/collection/TraversableView$NoBuilder;
const #19 = Method	#16.#18;	//  scala/collection/IndexedSeqView$$anon$2.apply:(Lscala/collection/TraversableView;)Lscala/collection/TraversableView$NoBuilder;
const #20 = Asciz	this;
const #21 = Asciz	Lscala/collection/IndexedSeqView$$anon$2;;
const #22 = Asciz	from;
const #23 = Asciz	Ljava/lang/Object;;
const #24 = Asciz	LocalVariableTable;
const #25 = Asciz	()Lscala/collection/mutable/Builder;;
const #26 = Asciz	()Lscala/collection/TraversableView$NoBuilder;;
const #27 = NameAndType	#11:#26;//  apply:()Lscala/collection/TraversableView$NoBuilder;
const #28 = Method	#16.#27;	//  scala/collection/IndexedSeqView$$anon$2.apply:()Lscala/collection/TraversableView$NoBuilder;
const #29 = Asciz	scala/collection/TraversableView$NoBuilder;
const #30 = class	#29;	//  scala/collection/TraversableView$NoBuilder
const #31 = Method	#30.#9;	//  scala/collection/TraversableView$NoBuilder."<init>":()V
const #32 = Asciz	()Lscala/collection/TraversableView$NoBuilder<TA;>;;
const #33 = Asciz	Signature;
const #34 = Asciz	Lscala/collection/TraversableView;;
const #35 = Asciz	(Lscala/collection/TraversableView<*[Ljava/lang/Object;>;)Lscala/collection/TraversableView$NoBuilder<TA;>;;
const #36 = Asciz	Ljava/lang/Object;Lscala/collection/generic/CanBuildFrom<Lscala/collection/TraversableView<*[Ljava/lang/Object;>;TA;Lscala/collection/IndexedSeqView<TA;[TA;>;>;;
const #37 = Asciz	Scala;
const #38 = Asciz	InnerClasses;
const #39 = Asciz	scala/collection/IndexedSeqView;
const #40 = class	#39;	//  scala/collection/IndexedSeqView
const #41 = Asciz	$anon$2;
const #42 = Asciz	NoBuilder;
const #43 = Asciz	scala/collection/generic/CanBuildFrom;
const #44 = class	#43;	//  scala/collection/generic/CanBuildFrom

{
public scala.collection.IndexedSeqView$$anon$2();
  Code:
   Stack=1, Locals=1, Args_size=1
   0:	aload_0
   1:	invokespecial	#10; //Method java/lang/Object."<init>":()V
   4:	return
  LineNumberTable: 
   line 34: 0


public scala.collection.mutable.Builder apply(java.lang.Object);
  Code:
   Stack=2, Locals=2, Args_size=2
   0:	aload_0
   1:	aload_1
   2:	checkcast	#14; //class scala/collection/TraversableView
   5:	invokevirtual	#19; //Method apply:(Lscala/collection/TraversableView;)Lscala/collection/TraversableView$NoBuilder;
   8:	areturn
  LineNumberTable: 
   line 34: 0

  LocalVariableTable: 
   Start  Length  Slot  Name   Signature
   0      9      0    this       Lscala/collection/IndexedSeqView$$anon$2;
   0      9      1    from       Ljava/lang/Object;


public scala.collection.mutable.Builder apply();
  Code:
   Stack=1, Locals=1, Args_size=1
   0:	aload_0
   1:	invokevirtual	#28; //Method apply:()Lscala/collection/TraversableView$NoBuilder;
   4:	areturn
  LineNumberTable: 
   line 34: 0


public scala.collection.TraversableView$NoBuilder apply();
  Code:
   Stack=2, Locals=1, Args_size=1
   0:	new	#30; //class scala/collection/TraversableView$NoBuilder
   3:	dup
   4:	invokespecial	#31; //Method scala/collection/TraversableView$NoBuilder."<init>":()V
   7:	areturn
  LineNumberTable: 
   line 36: 0

  Signature: length = 0x2
   00 20 

public scala.collection.TraversableView$NoBuilder apply(scala.collection.TraversableView);
  Code:
   Stack=2, Locals=2, Args_size=2
   0:	new	#30; //class scala/collection/TraversableView$NoBuilder
   3:	dup
   4:	invokespecial	#31; //Method scala/collection/TraversableView$NoBuilder."<init>":()V
   7:	areturn
  LineNumberTable: 
   line 35: 0

  LocalVariableTable: 
   Start  Length  Slot  Name   Signature
   0      8      0    this       Lscala/collection/IndexedSeqView$$anon$2;
   0      8      1    from       Lscala/collection/TraversableView;

  Signature: length = 0x2
   00 23 

}

