Compiled from "IndexedSeqView.scala"
public final class scala.collection.IndexedSeqView$ extends java.lang.Object implements scala.ScalaObject
  SourceFile: "IndexedSeqView.scala"
  Scala: length = 0x
   
  InnerClass: 
   public final #35= #29 of #34; //$anon$1=class scala/collection/IndexedSeqView$$anon$1 of class scala/collection/IndexedSeqView
   public final #36= #23 of #34; //$anon$2=class scala/collection/IndexedSeqView$$anon$2 of class scala/collection/IndexedSeqView
  minor version: 0
  major version: 49
  Constant pool:
const #1 = Asciz	SourceFile;
const #2 = Asciz	IndexedSeqView.scala;
const #3 = Asciz	Scala;
const #4 = Asciz	MODULE$;
const #5 = Asciz	Lscala/collection/IndexedSeqView$;;
const #6 = Asciz	<clinit>;
const #7 = Asciz	()V;
const #8 = Asciz	Code;
const #9 = Asciz	scala/collection/IndexedSeqView$;
const #10 = class	#9;	//  scala/collection/IndexedSeqView$
const #11 = Asciz	<init>;
const #12 = NameAndType	#11:#7;//  "<init>":()V
const #13 = Method	#10.#12;	//  scala/collection/IndexedSeqView$."<init>":()V
const #14 = Asciz	LineNumberTable;
const #15 = Asciz	java/lang/Object;
const #16 = class	#15;	//  java/lang/Object
const #17 = Method	#16.#12;	//  java/lang/Object."<init>":()V
const #18 = NameAndType	#4:#5;//  MODULE$:Lscala/collection/IndexedSeqView$;
const #19 = Field	#10.#18;	//  scala/collection/IndexedSeqView$.MODULE$:Lscala/collection/IndexedSeqView$;
const #20 = Asciz	arrCanBuildFrom;
const #21 = Asciz	()Lscala/collection/generic/CanBuildFrom;;
const #22 = Asciz	scala/collection/IndexedSeqView$$anon$2;
const #23 = class	#22;	//  scala/collection/IndexedSeqView$$anon$2
const #24 = Method	#23.#12;	//  scala/collection/IndexedSeqView$$anon$2."<init>":()V
const #25 = Asciz	<A:Ljava/lang/Object;>()Lscala/collection/generic/CanBuildFrom<Lscala/collection/TraversableView<*[Ljava/lang/Object;>;TA;Lscala/collection/IndexedSeqView<TA;[TA;>;>;;
const #26 = Asciz	Signature;
const #27 = Asciz	canBuildFrom;
const #28 = Asciz	scala/collection/IndexedSeqView$$anon$1;
const #29 = class	#28;	//  scala/collection/IndexedSeqView$$anon$1
const #30 = Method	#29.#12;	//  scala/collection/IndexedSeqView$$anon$1."<init>":()V
const #31 = Asciz	<A:Ljava/lang/Object;>()Lscala/collection/generic/CanBuildFrom<Lscala/collection/TraversableView<*Lscala/collection/Traversable;>;TA;Lscala/collection/IndexedSeqView<TA;Lscala/collection/IndexedSeq<*>;>;>;;
const #32 = Asciz	InnerClasses;
const #33 = Asciz	scala/collection/IndexedSeqView;
const #34 = class	#33;	//  scala/collection/IndexedSeqView
const #35 = Asciz	$anon$1;
const #36 = Asciz	$anon$2;
const #37 = Asciz	scala/ScalaObject;
const #38 = class	#37;	//  scala/ScalaObject

{
public static final scala.collection.IndexedSeqView$ MODULE$;

public static {};
  Code:
   Stack=1, Locals=0, Args_size=0
   0:	new	#10; //class scala/collection/IndexedSeqView$
   3:	invokespecial	#13; //Method "<init>":()V
   6:	return

public scala.collection.generic.CanBuildFrom arrCanBuildFrom();
  Code:
   Stack=2, Locals=1, Args_size=1
   0:	new	#23; //class scala/collection/IndexedSeqView$$anon$2
   3:	dup
   4:	invokespecial	#24; //Method scala/collection/IndexedSeqView$$anon$2."<init>":()V
   7:	areturn
  LineNumberTable: 
   line 34: 0

  Signature: length = 0x2
   00 19 

public scala.collection.generic.CanBuildFrom canBuildFrom();
  Code:
   Stack=2, Locals=1, Args_size=1
   0:	new	#29; //class scala/collection/IndexedSeqView$$anon$1
   3:	dup
   4:	invokespecial	#30; //Method scala/collection/IndexedSeqView$$anon$1."<init>":()V
   7:	areturn
  LineNumberTable: 
   line 29: 0

  Signature: length = 0x2
   00 1F 

}

