Compiled from "IndexedSeqViewLike.scala"
public final class scala.collection.IndexedSeqViewLike$$anon$6 extends java.lang.Object implements scala.collection.IndexedSeqViewLike$Sliced
  SourceFile: "IndexedSeqViewLike.scala"
  Signature: length = 0x2
   03 FFFFFFFE 
  Scala: length = 0x
   
  InnerClass: 
   public abstract Sliced=class scala/collection/SeqViewLike$Sliced of class scala/collection/SeqViewLike
   public abstract Transformed=class scala/collection/SeqViewLike$Transformed of class scala/collection/SeqViewLike
   public abstract $less$colon$less=class scala/Predef$$less$colon$less of class scala/Predef
   public abstract Sliced=class scala/collection/IterableViewLike$Sliced of class scala/collection/IterableViewLike
   public abstract Sliced=class scala/collection/IndexedSeqViewLike$Sliced of class scala/collection/IndexedSeqViewLike
   public WithFilter=class scala/collection/TraversableLike$WithFilter of class scala/collection/TraversableLike
   public abstract Sliced=class scala/collection/TraversableViewLike$Sliced of class scala/collection/TraversableViewLike
   public final $anon$6=class scala/collection/IndexedSeqViewLike$$anon$6 of class scala/collection/IndexedSeqViewLike
   public abstract Transformed=class scala/collection/IterableViewLike$Transformed of class scala/collection/IterableViewLike
   public abstract Transformed=class scala/collection/IndexedSeqViewLike$Transformed of class scala/collection/IndexedSeqViewLike
   public abstract Transformed=class scala/collection/TraversableViewLike$Transformed of class scala/collection/TraversableViewLike
  minor version: 0
  major version: 49
  Constant pool:
Asciz	SourceFile;
Asciz	IndexedSeqViewLike.scala;
Asciz	bitmap$0;
Asciz	I;
Asciz	underlying;
Asciz	Ljava/lang/Object;;
Asciz	$outer;
Asciz	Lscala/collection/IndexedSeqViewLike;;
Asciz	until;
Asciz	from;
Asciz	foreach;
Asciz	(Lscala/Function1;)V;
Asciz	Code;
Asciz	LineNumberTable;
Asciz	scala/collection/IndexedSeqViewLike$Sliced$class;
class	scala/collection/IndexedSeqViewLike$Sliced$class
Asciz	(Lscala/collection/IndexedSeqViewLike$Sliced;Lscala/Function1;)V;
NameAndType	foreach:(Lscala/collection/IndexedSeqViewLike$Sliced;Lscala/Function1;)V
Method	scala/collection/IndexedSeqViewLike$Sliced$class.foreach:(Lscala/collection/IndexedSeqViewLike$Sliced;Lscala/Function1;)V
Asciz	this;
Asciz	Lscala/collection/IndexedSeqViewLike$$anon$6;;
Asciz	f;
Asciz	Lscala/Function1;;
Asciz	LocalVariableTable;
Asciz	length;
Asciz	()I;
Asciz	scala/collection/SeqViewLike$Sliced$class;
class	scala/collection/SeqViewLike$Sliced$class
Asciz	(Lscala/collection/SeqViewLike$Sliced;)I;
NameAndType	length:(Lscala/collection/SeqViewLike$Sliced;)I
Method	scala/collection/SeqViewLike$Sliced$class.length:(Lscala/collection/SeqViewLike$Sliced;)I
Asciz	apply;
Asciz	(I)Ljava/lang/Object;;
Asciz	(Lscala/collection/SeqViewLike$Sliced;I)Ljava/lang/Object;;
NameAndType	apply:(Lscala/collection/SeqViewLike$Sliced;I)Ljava/lang/Object;
Method	scala/collection/SeqViewLike$Sliced$class.apply:(Lscala/collection/SeqViewLike$Sliced;I)Ljava/lang/Object;
Asciz	idx;
Asciz	iterator;
Asciz	()Lscala/collection/Iterator;;
Asciz	scala/collection/IterableViewLike$Sliced$class;
class	scala/collection/IterableViewLike$Sliced$class
Asciz	(Lscala/collection/IterableViewLike$Sliced;)Lscala/collection/Iterator;;
NameAndType	iterator:(Lscala/collection/IterableViewLike$Sliced;)Lscala/collection/Iterator;
Method	scala/collection/IterableViewLike$Sliced$class.iterator:(Lscala/collection/IterableViewLike$Sliced;)Lscala/collection/Iterator;
Asciz	stringPrefix;
Asciz	()Ljava/lang/String;;
Asciz	scala/collection/TraversableViewLike$Sliced$class;
class	scala/collection/TraversableViewLike$Sliced$class
Asciz	(Lscala/collection/TraversableViewLike$Sliced;)Ljava/lang/String;;
NameAndType	stringPrefix:(Lscala/collection/TraversableViewLike$Sliced;)Ljava/lang/String;
Method	scala/collection/TraversableViewLike$Sliced$class.stringPrefix:(Lscala/collection/TraversableViewLike$Sliced;)Ljava/lang/String;
Asciz	slice;
Asciz	(II)Lscala/collection/TraversableView;;
Asciz	(Lscala/collection/TraversableViewLike$Sliced;II)Lscala/collection/TraversableView;;
NameAndType	slice:(Lscala/collection/TraversableViewLike$Sliced;II)Lscala/collection/TraversableView;
Method	scala/collection/TraversableViewLike$Sliced$class.slice:(Lscala/collection/TraversableViewLike$Sliced;II)Lscala/collection/TraversableView;
Asciz	from1;
Asciz	until1;
Asciz	()Ljava/lang/Object;;
Asciz	scala/collection/IndexedSeqViewLike$$anon$6;
class	scala/collection/IndexedSeqViewLike$$anon$6
NameAndType	bitmap$0:I
Field	scala/collection/IndexedSeqViewLike$$anon$6.bitmap$0:I
Asciz	scala/collection/TraversableViewLike$Transformed$class;
class	scala/collection/TraversableViewLike$Transformed$class
Asciz	(Lscala/collection/TraversableViewLike$Transformed;)Ljava/lang/Object;;
NameAndType	underlying:(Lscala/collection/TraversableViewLike$Transformed;)Ljava/lang/Object;
Method	scala/collection/TraversableViewLike$Transformed$class.underlying:(Lscala/collection/TraversableViewLike$Transformed;)Ljava/lang/Object;
NameAndType	underlying:Ljava/lang/Object;
Field	scala/collection/IndexedSeqViewLike$$anon$6.underlying:Ljava/lang/Object;
Asciz	newForced;
Asciz	(Lscala/Function0;)Lscala/collection/IndexedSeqViewLike$Transformed;;
Asciz	scala/collection/IndexedSeqViewLike$class;
class	scala/collection/IndexedSeqViewLike$class
Asciz	(Lscala/collection/IndexedSeqViewLike;Lscala/Function0;)Lscala/collection/IndexedSeqViewLike$Transformed;;
NameAndType	newForced:(Lscala/collection/IndexedSeqViewLike;Lscala/Function0;)Lscala/collection/IndexedSeqViewLike$Transformed;
Method	scala/collection/IndexedSeqViewLike$class.newForced:(Lscala/collection/IndexedSeqViewLike;Lscala/Function0;)Lscala/collection/IndexedSeqViewLike$Transformed;
Asciz	xs;
Asciz	Lscala/Function0;;
Asciz	Signature;
Asciz	newAppended;
Asciz	(Lscala/collection/Traversable;)Lscala/collection/IndexedSeqViewLike$Transformed;;
Asciz	(Lscala/collection/IndexedSeqViewLike;Lscala/collection/Traversable;)Lscala/collection/IndexedSeqViewLike$Transformed;;
NameAndType	newAppended:(Lscala/collection/IndexedSeqViewLike;Lscala/collection/Traversable;)Lscala/collection/IndexedSeqViewLike$Transformed;
Method	scala/collection/IndexedSeqViewLike$class.newAppended:(Lscala/collection/IndexedSeqViewLike;Lscala/collection/Traversable;)Lscala/collection/IndexedSeqViewLike$Transformed;
Asciz	that;
Asciz	Lscala/collection/Traversable;;
Asciz	newMapped;
Asciz	(Lscala/Function1;)Lscala/collection/IndexedSeqViewLike$Transformed;;
Asciz	(Lscala/collection/IndexedSeqViewLike;Lscala/Function1;)Lscala/collection/IndexedSeqViewLike$Transformed;;
NameAndType	newMapped:(Lscala/collection/IndexedSeqViewLike;Lscala/Function1;)Lscala/collection/IndexedSeqViewLike$Transformed;
Method	scala/collection/IndexedSeqViewLike$class.newMapped:(Lscala/collection/IndexedSeqViewLike;Lscala/Function1;)Lscala/collection/IndexedSeqViewLike$Transformed;
Asciz	newFlatMapped;
NameAndType	newFlatMapped:(Lscala/collection/IndexedSeqViewLike;Lscala/Function1;)Lscala/collection/IndexedSeqViewLike$Transformed;
Method	scala/collection/IndexedSeqViewLike$class.newFlatMapped:(Lscala/collection/IndexedSeqViewLike;Lscala/Function1;)Lscala/collection/IndexedSeqViewLike$Transformed;
Asciz	newFiltered;
NameAndType	newFiltered:(Lscala/collection/IndexedSeqViewLike;Lscala/Function1;)Lscala/collection/IndexedSeqViewLike$Transformed;
Method	scala/collection/IndexedSeqViewLike$class.newFiltered:(Lscala/collection/IndexedSeqViewLike;Lscala/Function1;)Lscala/collection/IndexedSeqViewLike$Transformed;
Asciz	p;
Asciz	newSliced;
Asciz	(II)Lscala/collection/IndexedSeqViewLike$Transformed;;
Asciz	(Lscala/collection/IndexedSeqViewLike;II)Lscala/collection/IndexedSeqViewLike$Transformed;;
NameAndType	newSliced:(Lscala/collection/IndexedSeqViewLike;II)Lscala/collection/IndexedSeqViewLike$Transformed;
Method	scala/collection/IndexedSeqViewLike$class.newSliced:(Lscala/collection/IndexedSeqViewLike;II)Lscala/collection/IndexedSeqViewLike$Transformed;
Asciz	_from;
Asciz	_until;
Asciz	newDroppedWhile;
NameAndType	newDroppedWhile:(Lscala/collection/IndexedSeqViewLike;Lscala/Function1;)Lscala/collection/IndexedSeqViewLike$Transformed;
Method	scala/collection/IndexedSeqViewLike$class.newDroppedWhile:(Lscala/collection/IndexedSeqViewLike;Lscala/Function1;)Lscala/collection/IndexedSeqViewLike$Transformed;
Asciz	newTakenWhile;
NameAndType	newTakenWhile:(Lscala/collection/IndexedSeqViewLike;Lscala/Function1;)Lscala/collection/IndexedSeqViewLike$Transformed;
Method	scala/collection/IndexedSeqViewLike$class.newTakenWhile:(Lscala/collection/IndexedSeqViewLike;Lscala/Function1;)Lscala/collection/IndexedSeqViewLike$Transformed;
Asciz	newZipped;
Asciz	(Lscala/collection/Iterable;)Lscala/collection/IndexedSeqViewLike$Transformed;;
Asciz	(Lscala/collection/IndexedSeqViewLike;Lscala/collection/Iterable;)Lscala/collection/IndexedSeqViewLike$Transformed;;
NameAndType	newZipped:(Lscala/collection/IndexedSeqViewLike;Lscala/collection/Iterable;)Lscala/collection/IndexedSeqViewLike$Transformed;
Method	scala/collection/IndexedSeqViewLike$class.newZipped:(Lscala/collection/IndexedSeqViewLike;Lscala/collection/Iterable;)Lscala/collection/IndexedSeqViewLike$Transformed;
Asciz	Lscala/collection/Iterable;;
Asciz	newZippedAll;
Asciz	(Lscala/collection/Iterable;Ljava/lang/Object;Ljava/lang/Object;)Lscala/collection/IndexedSeqViewLike$Transformed;;
Asciz	(Lscala/collection/IndexedSeqViewLike;Lscala/collection/Iterable;Ljava/lang/Object;Ljava/lang/Object;)Lscala/collection/IndexedSeqViewLike$Transformed;;
NameAndType	newZippedAll:(Lscala/collection/IndexedSeqViewLike;Lscala/collection/Iterable;Ljava/lang/Object;Ljava/lang/Object;)Lscala/collection/IndexedSeqViewLike$Transformed;
Method	scala/collection/IndexedSeqViewLike$class.newZippedAll:(Lscala/collection/IndexedSeqViewLike;Lscala/collection/Iterable;Ljava/lang/Object;Ljava/lang/Object;)Lscala/collection/IndexedSeqViewLike$Transformed;
Asciz	_thisElem;
Asciz	_thatElem;
Asciz	newReversed;
Asciz	()Lscala/collection/IndexedSeqViewLike$Transformed;;
Asciz	(Lscala/collection/IndexedSeqViewLike;)Lscala/collection/IndexedSeqViewLike$Transformed;;
NameAndType	newReversed:(Lscala/collection/IndexedSeqViewLike;)Lscala/collection/IndexedSeqViewLike$Transformed;
Method	scala/collection/IndexedSeqViewLike$class.newReversed:(Lscala/collection/IndexedSeqViewLike;)Lscala/collection/IndexedSeqViewLike$Transformed;
Asciz	newPatched;
Asciz	(ILscala/collection/Seq;I)Lscala/collection/IndexedSeqViewLike$Transformed;;
Asciz	(Lscala/collection/IndexedSeqViewLike;ILscala/collection/Seq;I)Lscala/collection/IndexedSeqViewLike$Transformed;;
NameAndType	newPatched:(Lscala/collection/IndexedSeqViewLike;ILscala/collection/Seq;I)Lscala/collection/IndexedSeqViewLike$Transformed;
Method	scala/collection/IndexedSeqViewLike$class.newPatched:(Lscala/collection/IndexedSeqViewLike;ILscala/collection/Seq;I)Lscala/collection/IndexedSeqViewLike$Transformed;
Asciz	_patch;
Asciz	Lscala/collection/Seq;;
Asciz	_replaced;
Asciz	newPrepended;
Asciz	(Ljava/lang/Object;)Lscala/collection/IndexedSeqViewLike$Transformed;;
Asciz	(Lscala/collection/IndexedSeqViewLike;Ljava/lang/Object;)Lscala/collection/IndexedSeqViewLike$Transformed;;
NameAndType	newPrepended:(Lscala/collection/IndexedSeqViewLike;Ljava/lang/Object;)Lscala/collection/IndexedSeqViewLike$Transformed;
Method	scala/collection/IndexedSeqViewLike$class.newPrepended:(Lscala/collection/IndexedSeqViewLike;Ljava/lang/Object;)Lscala/collection/IndexedSeqViewLike$Transformed;
Asciz	elem;
Asciz	reverse;
Asciz	()Lscala/collection/SeqView;;
Asciz	scala/collection/SeqViewLike$class;
class	scala/collection/SeqViewLike$class
Asciz	(Lscala/collection/SeqViewLike;)Lscala/collection/SeqView;;
NameAndType	reverse:(Lscala/collection/SeqViewLike;)Lscala/collection/SeqView;
Method	scala/collection/SeqViewLike$class.reverse:(Lscala/collection/SeqViewLike;)Lscala/collection/SeqView;
Asciz	patch;
Asciz	(ILscala/collection/Seq;ILscala/collection/generic/CanBuildFrom;)Ljava/lang/Object;;
Asciz	(Lscala/collection/SeqViewLike;ILscala/collection/Seq;ILscala/collection/generic/CanBuildFrom;)Ljava/lang/Object;;
NameAndType	patch:(Lscala/collection/SeqViewLike;ILscala/collection/Seq;ILscala/collection/generic/CanBuildFrom;)Ljava/lang/Object;
Method	scala/collection/SeqViewLike$class.patch:(Lscala/collection/SeqViewLike;ILscala/collection/Seq;ILscala/collection/generic/CanBuildFrom;)Ljava/lang/Object;
Asciz	replaced;
Asciz	bf;
Asciz	Lscala/collection/generic/CanBuildFrom;;
Asciz	padTo;
Asciz	(ILjava/lang/Object;Lscala/collection/generic/CanBuildFrom;)Ljava/lang/Object;;
Asciz	(Lscala/collection/SeqViewLike;ILjava/lang/Object;Lscala/collection/generic/CanBuildFrom;)Ljava/lang/Object;;
NameAndType	padTo:(Lscala/collection/SeqViewLike;ILjava/lang/Object;Lscala/collection/generic/CanBuildFrom;)Ljava/lang/Object;
Method	scala/collection/SeqViewLike$class.padTo:(Lscala/collection/SeqViewLike;ILjava/lang/Object;Lscala/collection/generic/CanBuildFrom;)Ljava/lang/Object;
Asciz	len;
Asciz	reverseMap;
Asciz	(Lscala/Function1;Lscala/collection/generic/CanBuildFrom;)Ljava/lang/Object;;
Asciz	(Lscala/collection/SeqViewLike;Lscala/Function1;Lscala/collection/generic/CanBuildFrom;)Ljava/lang/Object;;
NameAndType	reverseMap:(Lscala/collection/SeqViewLike;Lscala/Function1;Lscala/collection/generic/CanBuildFrom;)Ljava/lang/Object;
Method	scala/collection/SeqViewLike$class.reverseMap:(Lscala/collection/SeqViewLike;Lscala/Function1;Lscala/collection/generic/CanBuildFrom;)Ljava/lang/Object;
Asciz	updated;
NameAndType	updated:(Lscala/collection/SeqViewLike;ILjava/lang/Object;Lscala/collection/generic/CanBuildFrom;)Ljava/lang/Object;
Method	scala/collection/SeqViewLike$class.updated:(Lscala/collection/SeqViewLike;ILjava/lang/Object;Lscala/collection/generic/CanBuildFrom;)Ljava/lang/Object;
Asciz	index;
Asciz	$plus$colon;
Asciz	(Ljava/lang/Object;Lscala/collection/generic/CanBuildFrom;)Ljava/lang/Object;;
Asciz	(Lscala/collection/SeqViewLike;Ljava/lang/Object;Lscala/collection/generic/CanBuildFrom;)Ljava/lang/Object;;
NameAndType	$plus$colon:(Lscala/collection/SeqViewLike;Ljava/lang/Object;Lscala/collection/generic/CanBuildFrom;)Ljava/lang/Object;
Method	scala/collection/SeqViewLike$class.$plus$colon:(Lscala/collection/SeqViewLike;Ljava/lang/Object;Lscala/collection/generic/CanBuildFrom;)Ljava/lang/Object;
Asciz	$colon$plus;
NameAndType	$colon$plus:(Lscala/collection/SeqViewLike;Ljava/lang/Object;Lscala/collection/generic/CanBuildFrom;)Ljava/lang/Object;
Method	scala/collection/SeqViewLike$class.$colon$plus:(Lscala/collection/SeqViewLike;Ljava/lang/Object;Lscala/collection/generic/CanBuildFrom;)Ljava/lang/Object;
Asciz	union;
Asciz	(Lscala/collection/Seq;Lscala/collection/generic/CanBuildFrom;)Ljava/lang/Object;;
Asciz	(Lscala/collection/SeqViewLike;Lscala/collection/Seq;Lscala/collection/generic/CanBuildFrom;)Ljava/lang/Object;;
NameAndType	union:(Lscala/collection/SeqViewLike;Lscala/collection/Seq;Lscala/collection/generic/CanBuildFrom;)Ljava/lang/Object;
Method	scala/collection/SeqViewLike$class.union:(Lscala/collection/SeqViewLike;Lscala/collection/Seq;Lscala/collection/generic/CanBuildFrom;)Ljava/lang/Object;
Asciz	diff;
Asciz	(Lscala/collection/Seq;)Lscala/collection/SeqView;;
Asciz	(Lscala/collection/SeqViewLike;Lscala/collection/Seq;)Lscala/collection/SeqView;;
NameAndType	diff:(Lscala/collection/SeqViewLike;Lscala/collection/Seq;)Lscala/collection/SeqView;
Method	scala/collection/SeqViewLike$class.diff:(Lscala/collection/SeqViewLike;Lscala/collection/Seq;)Lscala/collection/SeqView;
Asciz	intersect;
NameAndType	intersect:(Lscala/collection/SeqViewLike;Lscala/collection/Seq;)Lscala/collection/SeqView;
Method	scala/collection/SeqViewLike$class.intersect:(Lscala/collection/SeqViewLike;Lscala/collection/Seq;)Lscala/collection/SeqView;
Asciz	sorted;
Asciz	(Lscala/math/Ordering;)Lscala/collection/SeqView;;
Asciz	(Lscala/collection/SeqViewLike;Lscala/math/Ordering;)Lscala/collection/SeqView;;
NameAndType	sorted:(Lscala/collection/SeqViewLike;Lscala/math/Ordering;)Lscala/collection/SeqView;
Method	scala/collection/SeqViewLike$class.sorted:(Lscala/collection/SeqViewLike;Lscala/math/Ordering;)Lscala/collection/SeqView;
Asciz	ord;
Asciz	Lscala/math/Ordering;;
Asciz	zip;
Asciz	(Lscala/collection/Iterable;Lscala/collection/generic/CanBuildFrom;)Ljava/lang/Object;;
Asciz	scala/collection/IterableViewLike$class;
class	scala/collection/IterableViewLike$class
Asciz	(Lscala/collection/IterableViewLike;Lscala/collection/Iterable;Lscala/collection/generic/CanBuildFrom;)Ljava/lang/Object;;
NameAndType	zip:(Lscala/collection/IterableViewLike;Lscala/collection/Iterable;Lscala/collection/generic/CanBuildFrom;)Ljava/lang/Object;
Method	scala/collection/IterableViewLike$class.zip:(Lscala/collection/IterableViewLike;Lscala/collection/Iterable;Lscala/collection/generic/CanBuildFrom;)Ljava/lang/Object;
Asciz	zipWithIndex;
Asciz	(Lscala/collection/generic/CanBuildFrom;)Ljava/lang/Object;;
Asciz	(Lscala/collection/IterableViewLike;Lscala/collection/generic/CanBuildFrom;)Ljava/lang/Object;;
NameAndType	zipWithIndex:(Lscala/collection/IterableViewLike;Lscala/collection/generic/CanBuildFrom;)Ljava/lang/Object;
Method	scala/collection/IterableViewLike$class.zipWithIndex:(Lscala/collection/IterableViewLike;Lscala/collection/generic/CanBuildFrom;)Ljava/lang/Object;
Asciz	zipAll;
Asciz	(Lscala/collection/Iterable;Ljava/lang/Object;Ljava/lang/Object;Lscala/collection/generic/CanBuildFrom;)Ljava/lang/Object;;
Asciz	(Lscala/collection/IterableViewLike;Lscala/collection/Iterable;Ljava/lang/Object;Ljava/lang/Object;Lscala/collection/generic/CanBuildFrom;)Ljava/lang/Object;;
NameAndType	zipAll:(Lscala/collection/IterableViewLike;Lscala/collection/Iterable;Ljava/lang/Object;Ljava/lang/Object;Lscala/collection/generic/CanBuildFrom;)Ljava/lang/Object;
Method	scala/collection/IterableViewLike$class.zipAll:(Lscala/collection/IterableViewLike;Lscala/collection/Iterable;Ljava/lang/Object;Ljava/lang/Object;Lscala/collection/generic/CanBuildFrom;)Ljava/lang/Object;
Asciz	thisElem;
Asciz	thatElem;
Asciz	grouped;
Asciz	(I)Lscala/collection/Iterator;;
Asciz	(Lscala/collection/IterableViewLike;I)Lscala/collection/Iterator;;
NameAndType	grouped:(Lscala/collection/IterableViewLike;I)Lscala/collection/Iterator;
Method	scala/collection/IterableViewLike$class.grouped:(Lscala/collection/IterableViewLike;I)Lscala/collection/Iterator;
Asciz	size;
Asciz	sliding;
Asciz	(II)Lscala/collection/Iterator;;
Asciz	(Lscala/collection/IterableViewLike;II)Lscala/collection/Iterator;;
NameAndType	sliding:(Lscala/collection/IterableViewLike;II)Lscala/collection/Iterator;
Method	scala/collection/IterableViewLike$class.sliding:(Lscala/collection/IterableViewLike;II)Lscala/collection/Iterator;
Asciz	step;
Asciz	newBuilder;
Asciz	()Lscala/collection/mutable/Builder;;
Asciz	scala/collection/TraversableViewLike$class;
class	scala/collection/TraversableViewLike$class
Asciz	(Lscala/collection/TraversableViewLike;)Lscala/collection/mutable/Builder;;
NameAndType	newBuilder:(Lscala/collection/TraversableViewLike;)Lscala/collection/mutable/Builder;
Method	scala/collection/TraversableViewLike$class.newBuilder:(Lscala/collection/TraversableViewLike;)Lscala/collection/mutable/Builder;
Asciz	force;
Asciz	(Lscala/collection/TraversableViewLike;Lscala/collection/generic/CanBuildFrom;)Ljava/lang/Object;;
NameAndType	force:(Lscala/collection/TraversableViewLike;Lscala/collection/generic/CanBuildFrom;)Ljava/lang/Object;
Method	scala/collection/TraversableViewLike$class.force:(Lscala/collection/TraversableViewLike;Lscala/collection/generic/CanBuildFrom;)Ljava/lang/Object;
Asciz	$plus$plus;
Asciz	(Lscala/collection/Traversable;Lscala/collection/generic/CanBuildFrom;)Ljava/lang/Object;;
Asciz	(Lscala/collection/TraversableViewLike;Lscala/collection/Traversable;Lscala/collection/generic/CanBuildFrom;)Ljava/lang/Object;;
NameAndType	$plus$plus:(Lscala/collection/TraversableViewLike;Lscala/collection/Traversable;Lscala/collection/generic/CanBuildFrom;)Ljava/lang/Object;
Method	scala/collection/TraversableViewLike$class.$plus$plus:(Lscala/collection/TraversableViewLike;Lscala/collection/Traversable;Lscala/collection/generic/CanBuildFrom;)Ljava/lang/Object;
Asciz	(Lscala/collection/Iterator;Lscala/collection/generic/CanBuildFrom;)Ljava/lang/Object;;
Asciz	(Lscala/collection/TraversableViewLike;Lscala/collection/Iterator;Lscala/collection/generic/CanBuildFrom;)Ljava/lang/Object;;
NameAndType	$plus$plus:(Lscala/collection/TraversableViewLike;Lscala/collection/Iterator;Lscala/collection/generic/CanBuildFrom;)Ljava/lang/Object;
Method	scala/collection/TraversableViewLike$class.$plus$plus:(Lscala/collection/TraversableViewLike;Lscala/collection/Iterator;Lscala/collection/generic/CanBuildFrom;)Ljava/lang/Object;
Asciz	Lscala/collection/Iterator;;
Asciz	map;
Asciz	(Lscala/collection/TraversableViewLike;Lscala/Function1;Lscala/collection/generic/CanBuildFrom;)Ljava/lang/Object;;
NameAndType	map:(Lscala/collection/TraversableViewLike;Lscala/Function1;Lscala/collection/generic/CanBuildFrom;)Ljava/lang/Object;
Method	scala/collection/TraversableViewLike$class.map:(Lscala/collection/TraversableViewLike;Lscala/Function1;Lscala/collection/generic/CanBuildFrom;)Ljava/lang/Object;
Asciz	partialMap;
Asciz	(Lscala/PartialFunction;Lscala/collection/generic/CanBuildFrom;)Ljava/lang/Object;;
Asciz	(Lscala/collection/TraversableViewLike;Lscala/PartialFunction;Lscala/collection/generic/CanBuildFrom;)Ljava/lang/Object;;
NameAndType	partialMap:(Lscala/collection/TraversableViewLike;Lscala/PartialFunction;Lscala/collection/generic/CanBuildFrom;)Ljava/lang/Object;
Method	scala/collection/TraversableViewLike$class.partialMap:(Lscala/collection/TraversableViewLike;Lscala/PartialFunction;Lscala/collection/generic/CanBuildFrom;)Ljava/lang/Object;
Asciz	pf;
Asciz	Lscala/PartialFunction;;
Asciz	flatMap;
NameAndType	flatMap:(Lscala/collection/TraversableViewLike;Lscala/Function1;Lscala/collection/generic/CanBuildFrom;)Ljava/lang/Object;
Method	scala/collection/TraversableViewLike$class.flatMap:(Lscala/collection/TraversableViewLike;Lscala/Function1;Lscala/collection/generic/CanBuildFrom;)Ljava/lang/Object;
Asciz	thisSeq;
Asciz	()Lscala/collection/Seq;;
Asciz	(Lscala/collection/TraversableViewLike;)Lscala/collection/Seq;;
NameAndType	thisSeq:(Lscala/collection/TraversableViewLike;)Lscala/collection/Seq;
Method	scala/collection/TraversableViewLike$class.thisSeq:(Lscala/collection/TraversableViewLike;)Lscala/collection/Seq;
Asciz	filter;
Asciz	(Lscala/Function1;)Lscala/collection/TraversableView;;
Asciz	(Lscala/collection/TraversableViewLike;Lscala/Function1;)Lscala/collection/TraversableView;;
NameAndType	filter:(Lscala/collection/TraversableViewLike;Lscala/Function1;)Lscala/collection/TraversableView;
Method	scala/collection/TraversableViewLike$class.filter:(Lscala/collection/TraversableViewLike;Lscala/Function1;)Lscala/collection/TraversableView;
Asciz	partition;
Asciz	(Lscala/Function1;)Lscala/Tuple2;;
Asciz	(Lscala/collection/TraversableViewLike;Lscala/Function1;)Lscala/Tuple2;;
NameAndType	partition:(Lscala/collection/TraversableViewLike;Lscala/Function1;)Lscala/Tuple2;
Method	scala/collection/TraversableViewLike$class.partition:(Lscala/collection/TraversableViewLike;Lscala/Function1;)Lscala/Tuple2;
Asciz	init;
Asciz	()Lscala/collection/TraversableView;;
Asciz	(Lscala/collection/TraversableViewLike;)Lscala/collection/TraversableView;;
NameAndType	init:(Lscala/collection/TraversableViewLike;)Lscala/collection/TraversableView;
Method	scala/collection/TraversableViewLike$class.init:(Lscala/collection/TraversableViewLike;)Lscala/collection/TraversableView;
Asciz	drop;
Asciz	(I)Lscala/collection/TraversableView;;
Asciz	(Lscala/collection/TraversableViewLike;I)Lscala/collection/TraversableView;;
NameAndType	drop:(Lscala/collection/TraversableViewLike;I)Lscala/collection/TraversableView;
Method	scala/collection/TraversableViewLike$class.drop:(Lscala/collection/TraversableViewLike;I)Lscala/collection/TraversableView;
Asciz	n;
Asciz	take;
NameAndType	take:(Lscala/collection/TraversableViewLike;I)Lscala/collection/TraversableView;
Method	scala/collection/TraversableViewLike$class.take:(Lscala/collection/TraversableViewLike;I)Lscala/collection/TraversableView;
Asciz	dropWhile;
NameAndType	dropWhile:(Lscala/collection/TraversableViewLike;Lscala/Function1;)Lscala/collection/TraversableView;
Method	scala/collection/TraversableViewLike$class.dropWhile:(Lscala/collection/TraversableViewLike;Lscala/Function1;)Lscala/collection/TraversableView;
Asciz	takeWhile;
NameAndType	takeWhile:(Lscala/collection/TraversableViewLike;Lscala/Function1;)Lscala/collection/TraversableView;
Method	scala/collection/TraversableViewLike$class.takeWhile:(Lscala/collection/TraversableViewLike;Lscala/Function1;)Lscala/collection/TraversableView;
Asciz	span;
NameAndType	span:(Lscala/collection/TraversableViewLike;Lscala/Function1;)Lscala/Tuple2;
Method	scala/collection/TraversableViewLike$class.span:(Lscala/collection/TraversableViewLike;Lscala/Function1;)Lscala/Tuple2;
Asciz	splitAt;
Asciz	(I)Lscala/Tuple2;;
Asciz	(Lscala/collection/TraversableViewLike;I)Lscala/Tuple2;;
NameAndType	splitAt:(Lscala/collection/TraversableViewLike;I)Lscala/Tuple2;
Method	scala/collection/TraversableViewLike$class.splitAt:(Lscala/collection/TraversableViewLike;I)Lscala/Tuple2;
Asciz	scanLeft;
Asciz	(Ljava/lang/Object;Lscala/Function2;Lscala/collection/generic/CanBuildFrom;)Ljava/lang/Object;;
Asciz	(Lscala/collection/TraversableViewLike;Ljava/lang/Object;Lscala/Function2;Lscala/collection/generic/CanBuildFrom;)Ljava/lang/Object;;
NameAndType	scanLeft:(Lscala/collection/TraversableViewLike;Ljava/lang/Object;Lscala/Function2;Lscala/collection/generic/CanBuildFrom;)Ljava/lang/Object;
Method	scala/collection/TraversableViewLike$class.scanLeft:(Lscala/collection/TraversableViewLike;Ljava/lang/Object;Lscala/Function2;Lscala/collection/generic/CanBuildFrom;)Ljava/lang/Object;
Asciz	z;
Asciz	op;
Asciz	Lscala/Function2;;
Asciz	scanRight;
NameAndType	scanRight:(Lscala/collection/TraversableViewLike;Ljava/lang/Object;Lscala/Function2;Lscala/collection/generic/CanBuildFrom;)Ljava/lang/Object;
Method	scala/collection/TraversableViewLike$class.scanRight:(Lscala/collection/TraversableViewLike;Ljava/lang/Object;Lscala/Function2;Lscala/collection/generic/CanBuildFrom;)Ljava/lang/Object;
Asciz	groupBy;
Asciz	(Lscala/Function1;)Lscala/collection/Map;;
Asciz	(Lscala/collection/TraversableViewLike;Lscala/Function1;)Lscala/collection/Map;;
NameAndType	groupBy:(Lscala/collection/TraversableViewLike;Lscala/Function1;)Lscala/collection/Map;
Method	scala/collection/TraversableViewLike$class.groupBy:(Lscala/collection/TraversableViewLike;Lscala/Function1;)Lscala/collection/Map;
Asciz	companion;
Asciz	()Lscala/collection/generic/GenericCompanion;;
Asciz	scala/collection/IndexedSeq$class;
class	scala/collection/IndexedSeq$class
Asciz	(Lscala/collection/IndexedSeq;)Lscala/collection/generic/GenericCompanion;;
NameAndType	companion:(Lscala/collection/IndexedSeq;)Lscala/collection/generic/GenericCompanion;
Method	scala/collection/IndexedSeq$class.companion:(Lscala/collection/IndexedSeq;)Lscala/collection/generic/GenericCompanion;
Asciz	scala$collection$IndexedSeqLike$$super$reduceLeft;
Asciz	(Lscala/Function2;)Ljava/lang/Object;;
Asciz	scala/collection/TraversableLike$class;
class	scala/collection/TraversableLike$class
Asciz	reduceLeft;
Asciz	(Lscala/collection/TraversableLike;Lscala/Function2;)Ljava/lang/Object;;
NameAndType	reduceLeft:(Lscala/collection/TraversableLike;Lscala/Function2;)Ljava/lang/Object;
Method	scala/collection/TraversableLike$class.reduceLeft:(Lscala/collection/TraversableLike;Lscala/Function2;)Ljava/lang/Object;
Asciz	scala$collection$IndexedSeqLike$$super$reduceRight;
Asciz	scala/collection/IterableLike$class;
class	scala/collection/IterableLike$class
Asciz	reduceRight;
Asciz	(Lscala/collection/IterableLike;Lscala/Function2;)Ljava/lang/Object;;
NameAndType	reduceRight:(Lscala/collection/IterableLike;Lscala/Function2;)Ljava/lang/Object;
Method	scala/collection/IterableLike$class.reduceRight:(Lscala/collection/IterableLike;Lscala/Function2;)Ljava/lang/Object;
Asciz	scala$collection$IndexedSeqLike$$super$zip;
Asciz	(Lscala/collection/IterableLike;Lscala/collection/Iterable;Lscala/collection/generic/CanBuildFrom;)Ljava/lang/Object;;
NameAndType	zip:(Lscala/collection/IterableLike;Lscala/collection/Iterable;Lscala/collection/generic/CanBuildFrom;)Ljava/lang/Object;
Method	scala/collection/IterableLike$class.zip:(Lscala/collection/IterableLike;Lscala/collection/Iterable;Lscala/collection/generic/CanBuildFrom;)Ljava/lang/Object;
Asciz	scala$collection$IndexedSeqLike$$super$head;
Asciz	head;
Asciz	(Lscala/collection/IterableLike;)Ljava/lang/Object;;
NameAndType	head:(Lscala/collection/IterableLike;)Ljava/lang/Object;
Method	scala/collection/IterableLike$class.head:(Lscala/collection/IterableLike;)Ljava/lang/Object;
Asciz	scala$collection$IndexedSeqLike$$super$tail;
Asciz	tail;
Asciz	(Lscala/collection/TraversableLike;)Ljava/lang/Object;;
NameAndType	tail:(Lscala/collection/TraversableLike;)Ljava/lang/Object;
Method	scala/collection/TraversableLike$class.tail:(Lscala/collection/TraversableLike;)Ljava/lang/Object;
Asciz	scala$collection$IndexedSeqLike$$super$last;
Asciz	last;
NameAndType	last:(Lscala/collection/TraversableLike;)Ljava/lang/Object;
Method	scala/collection/TraversableLike$class.last:(Lscala/collection/TraversableLike;)Ljava/lang/Object;
Asciz	scala$collection$IndexedSeqLike$$super$init;
NameAndType	init:(Lscala/collection/TraversableLike;)Ljava/lang/Object;
Method	scala/collection/TraversableLike$class.init:(Lscala/collection/TraversableLike;)Ljava/lang/Object;
Asciz	scala$collection$IndexedSeqLike$$super$sameElements;
Asciz	(Lscala/collection/Iterable;)Z;
Asciz	sameElements;
Asciz	(Lscala/collection/IterableLike;Lscala/collection/Iterable;)Z;
NameAndType	sameElements:(Lscala/collection/IterableLike;Lscala/collection/Iterable;)Z
Method	scala/collection/IterableLike$class.sameElements:(Lscala/collection/IterableLike;Lscala/collection/Iterable;)Z
Asciz	scala$collection$IndexedSeqLike$$super$endsWith;
Asciz	(Lscala/collection/Seq;)Z;
Asciz	scala/collection/SeqLike$class;
class	scala/collection/SeqLike$class
Asciz	endsWith;
Asciz	(Lscala/collection/SeqLike;Lscala/collection/Seq;)Z;
NameAndType	endsWith:(Lscala/collection/SeqLike;Lscala/collection/Seq;)Z
Method	scala/collection/SeqLike$class.endsWith:(Lscala/collection/SeqLike;Lscala/collection/Seq;)Z
Asciz	thisCollection;
Asciz	()Lscala/collection/IndexedSeq;;
Asciz	scala/collection/IndexedSeqLike$class;
class	scala/collection/IndexedSeqLike$class
Asciz	(Lscala/collection/IndexedSeqLike;)Lscala/collection/IndexedSeq;;
NameAndType	thisCollection:(Lscala/collection/IndexedSeqLike;)Lscala/collection/IndexedSeq;
Method	scala/collection/IndexedSeqLike$class.thisCollection:(Lscala/collection/IndexedSeqLike;)Lscala/collection/IndexedSeq;
Asciz	toCollection;
Asciz	(Ljava/lang/Object;)Lscala/collection/IndexedSeq;;
Asciz	(Lscala/collection/IndexedSeqLike;Ljava/lang/Object;)Lscala/collection/IndexedSeq;;
NameAndType	toCollection:(Lscala/collection/IndexedSeqLike;Ljava/lang/Object;)Lscala/collection/IndexedSeq;
Method	scala/collection/IndexedSeqLike$class.toCollection:(Lscala/collection/IndexedSeqLike;Ljava/lang/Object;)Lscala/collection/IndexedSeq;
Asciz	repr;
Asciz	isEmpty;
Asciz	()Z;
Asciz	(Lscala/collection/IndexedSeqLike;)Z;
NameAndType	isEmpty:(Lscala/collection/IndexedSeqLike;)Z
Method	scala/collection/IndexedSeqLike$class.isEmpty:(Lscala/collection/IndexedSeqLike;)Z
Asciz	forall;
Asciz	(Lscala/Function1;)Z;
Asciz	(Lscala/collection/IndexedSeqLike;Lscala/Function1;)Z;
NameAndType	forall:(Lscala/collection/IndexedSeqLike;Lscala/Function1;)Z
Method	scala/collection/IndexedSeqLike$class.forall:(Lscala/collection/IndexedSeqLike;Lscala/Function1;)Z
Asciz	exists;
NameAndType	exists:(Lscala/collection/IndexedSeqLike;Lscala/Function1;)Z
Method	scala/collection/IndexedSeqLike$class.exists:(Lscala/collection/IndexedSeqLike;Lscala/Function1;)Z
Asciz	find;
Asciz	(Lscala/Function1;)Lscala/Option;;
Asciz	(Lscala/collection/IndexedSeqLike;Lscala/Function1;)Lscala/Option;;
NameAndType	find:(Lscala/collection/IndexedSeqLike;Lscala/Function1;)Lscala/Option;
Method	scala/collection/IndexedSeqLike$class.find:(Lscala/collection/IndexedSeqLike;Lscala/Function1;)Lscala/Option;
Asciz	foldLeft;
Asciz	(Ljava/lang/Object;Lscala/Function2;)Ljava/lang/Object;;
Asciz	(Lscala/collection/IndexedSeqLike;Ljava/lang/Object;Lscala/Function2;)Ljava/lang/Object;;
NameAndType	foldLeft:(Lscala/collection/IndexedSeqLike;Ljava/lang/Object;Lscala/Function2;)Ljava/lang/Object;
Method	scala/collection/IndexedSeqLike$class.foldLeft:(Lscala/collection/IndexedSeqLike;Ljava/lang/Object;Lscala/Function2;)Ljava/lang/Object;
Asciz	foldRight;
NameAndType	foldRight:(Lscala/collection/IndexedSeqLike;Ljava/lang/Object;Lscala/Function2;)Ljava/lang/Object;
Method	scala/collection/IndexedSeqLike$class.foldRight:(Lscala/collection/IndexedSeqLike;Ljava/lang/Object;Lscala/Function2;)Ljava/lang/Object;
Asciz	(Lscala/collection/IndexedSeqLike;Lscala/Function2;)Ljava/lang/Object;;
NameAndType	reduceLeft:(Lscala/collection/IndexedSeqLike;Lscala/Function2;)Ljava/lang/Object;
Method	scala/collection/IndexedSeqLike$class.reduceLeft:(Lscala/collection/IndexedSeqLike;Lscala/Function2;)Ljava/lang/Object;
NameAndType	reduceRight:(Lscala/collection/IndexedSeqLike;Lscala/Function2;)Ljava/lang/Object;
Method	scala/collection/IndexedSeqLike$class.reduceRight:(Lscala/collection/IndexedSeqLike;Lscala/Function2;)Ljava/lang/Object;
Asciz	(Lscala/collection/IndexedSeqLike;)Ljava/lang/Object;;
NameAndType	head:(Lscala/collection/IndexedSeqLike;)Ljava/lang/Object;
Method	scala/collection/IndexedSeqLike$class.head:(Lscala/collection/IndexedSeqLike;)Ljava/lang/Object;
NameAndType	tail:(Lscala/collection/IndexedSeqLike;)Ljava/lang/Object;
Method	scala/collection/IndexedSeqLike$class.tail:(Lscala/collection/IndexedSeqLike;)Ljava/lang/Object;
NameAndType	last:(Lscala/collection/IndexedSeqLike;)Ljava/lang/Object;
Method	scala/collection/IndexedSeqLike$class.last:(Lscala/collection/IndexedSeqLike;)Ljava/lang/Object;
Asciz	takeRight;
Asciz	(Lscala/collection/IndexedSeqLike;I)Ljava/lang/Object;;
NameAndType	takeRight:(Lscala/collection/IndexedSeqLike;I)Ljava/lang/Object;
Method	scala/collection/IndexedSeqLike$class.takeRight:(Lscala/collection/IndexedSeqLike;I)Ljava/lang/Object;
Asciz	dropRight;
NameAndType	dropRight:(Lscala/collection/IndexedSeqLike;I)Ljava/lang/Object;
Method	scala/collection/IndexedSeqLike$class.dropRight:(Lscala/collection/IndexedSeqLike;I)Ljava/lang/Object;
Asciz	(Lscala/collection/IndexedSeqLike;Lscala/collection/Iterable;)Z;
NameAndType	sameElements:(Lscala/collection/IndexedSeqLike;Lscala/collection/Iterable;)Z
Method	scala/collection/IndexedSeqLike$class.sameElements:(Lscala/collection/IndexedSeqLike;Lscala/collection/Iterable;)Z
Asciz	copyToArray;
Asciz	(Ljava/lang/Object;II)V;
Asciz	(Lscala/collection/IndexedSeqLike;Ljava/lang/Object;II)V;
NameAndType	copyToArray:(Lscala/collection/IndexedSeqLike;Ljava/lang/Object;II)V
Method	scala/collection/IndexedSeqLike$class.copyToArray:(Lscala/collection/IndexedSeqLike;Ljava/lang/Object;II)V
Asciz	start;
Asciz	lengthCompare;
Asciz	(I)I;
Asciz	(Lscala/collection/IndexedSeqLike;I)I;
NameAndType	lengthCompare:(Lscala/collection/IndexedSeqLike;I)I
Method	scala/collection/IndexedSeqLike$class.lengthCompare:(Lscala/collection/IndexedSeqLike;I)I
Asciz	segmentLength;
Asciz	(Lscala/Function1;I)I;
Asciz	(Lscala/collection/IndexedSeqLike;Lscala/Function1;I)I;
NameAndType	segmentLength:(Lscala/collection/IndexedSeqLike;Lscala/Function1;I)I
Method	scala/collection/IndexedSeqLike$class.segmentLength:(Lscala/collection/IndexedSeqLike;Lscala/Function1;I)I
Asciz	indexWhere;
NameAndType	indexWhere:(Lscala/collection/IndexedSeqLike;Lscala/Function1;I)I
Method	scala/collection/IndexedSeqLike$class.indexWhere:(Lscala/collection/IndexedSeqLike;Lscala/Function1;I)I
Asciz	lastIndexWhere;
NameAndType	lastIndexWhere:(Lscala/collection/IndexedSeqLike;Lscala/Function1;I)I
Method	scala/collection/IndexedSeqLike$class.lastIndexWhere:(Lscala/collection/IndexedSeqLike;Lscala/Function1;I)I
Asciz	end;
Asciz	reverseIterator;
Asciz	(Lscala/collection/IndexedSeqLike;)Lscala/collection/Iterator;;
NameAndType	reverseIterator:(Lscala/collection/IndexedSeqLike;)Lscala/collection/Iterator;
Method	scala/collection/IndexedSeqLike$class.reverseIterator:(Lscala/collection/IndexedSeqLike;)Lscala/collection/Iterator;
Asciz	startsWith;
Asciz	(Lscala/collection/Seq;I)Z;
Asciz	(Lscala/collection/IndexedSeqLike;Lscala/collection/Seq;I)Z;
NameAndType	startsWith:(Lscala/collection/IndexedSeqLike;Lscala/collection/Seq;I)Z
Method	scala/collection/IndexedSeqLike$class.startsWith:(Lscala/collection/IndexedSeqLike;Lscala/collection/Seq;I)Z
Asciz	offset;
Asciz	(Lscala/collection/IndexedSeqLike;Lscala/collection/Seq;)Z;
NameAndType	endsWith:(Lscala/collection/IndexedSeqLike;Lscala/collection/Seq;)Z
Method	scala/collection/IndexedSeqLike$class.endsWith:(Lscala/collection/IndexedSeqLike;Lscala/collection/Seq;)Z
Asciz	view;
Asciz	()Lscala/collection/IndexedSeqView;;
Asciz	(Lscala/collection/IndexedSeqLike;)Lscala/collection/IndexedSeqView;;
NameAndType	view:(Lscala/collection/IndexedSeqLike;)Lscala/collection/IndexedSeqView;
Method	scala/collection/IndexedSeqLike$class.view:(Lscala/collection/IndexedSeqLike;)Lscala/collection/IndexedSeqView;
Asciz	(II)Lscala/collection/IndexedSeqView;;
Asciz	(Lscala/collection/IndexedSeqLike;II)Lscala/collection/IndexedSeqView;;
NameAndType	view:(Lscala/collection/IndexedSeqLike;II)Lscala/collection/IndexedSeqView;
Method	scala/collection/IndexedSeqLike$class.view:(Lscala/collection/IndexedSeqLike;II)Lscala/collection/IndexedSeqView;
Asciz	(Lscala/collection/SeqLike;)I;
NameAndType	size:(Lscala/collection/SeqLike;)I
Method	scala/collection/SeqLike$class.size:(Lscala/collection/SeqLike;)I
Asciz	isDefinedAt;
Asciz	(I)Z;
Asciz	(Lscala/collection/SeqLike;I)Z;
NameAndType	isDefinedAt:(Lscala/collection/SeqLike;I)Z
Method	scala/collection/SeqLike$class.isDefinedAt:(Lscala/collection/SeqLike;I)Z
Asciz	prefixLength;
Asciz	(Lscala/Function1;)I;
Asciz	(Lscala/collection/SeqLike;Lscala/Function1;)I;
NameAndType	prefixLength:(Lscala/collection/SeqLike;Lscala/Function1;)I
Method	scala/collection/SeqLike$class.prefixLength:(Lscala/collection/SeqLike;Lscala/Function1;)I
NameAndType	indexWhere:(Lscala/collection/SeqLike;Lscala/Function1;)I
Method	scala/collection/SeqLike$class.indexWhere:(Lscala/collection/SeqLike;Lscala/Function1;)I
Asciz	findIndexOf;
NameAndType	findIndexOf:(Lscala/collection/SeqLike;Lscala/Function1;)I
Method	scala/collection/SeqLike$class.findIndexOf:(Lscala/collection/SeqLike;Lscala/Function1;)I
Asciz	indexOf;
Asciz	(Ljava/lang/Object;)I;
Asciz	(Lscala/collection/SeqLike;Ljava/lang/Object;)I;
NameAndType	indexOf:(Lscala/collection/SeqLike;Ljava/lang/Object;)I
Method	scala/collection/SeqLike$class.indexOf:(Lscala/collection/SeqLike;Ljava/lang/Object;)I
Asciz	(Ljava/lang/Object;I)I;
Asciz	(Lscala/collection/SeqLike;Ljava/lang/Object;I)I;
NameAndType	indexOf:(Lscala/collection/SeqLike;Ljava/lang/Object;I)I
Method	scala/collection/SeqLike$class.indexOf:(Lscala/collection/SeqLike;Ljava/lang/Object;I)I
Asciz	lastIndexOf;
NameAndType	lastIndexOf:(Lscala/collection/SeqLike;Ljava/lang/Object;)I
Method	scala/collection/SeqLike$class.lastIndexOf:(Lscala/collection/SeqLike;Ljava/lang/Object;)I
NameAndType	lastIndexOf:(Lscala/collection/SeqLike;Ljava/lang/Object;I)I
Method	scala/collection/SeqLike$class.lastIndexOf:(Lscala/collection/SeqLike;Ljava/lang/Object;I)I
NameAndType	lastIndexWhere:(Lscala/collection/SeqLike;Lscala/Function1;)I
Method	scala/collection/SeqLike$class.lastIndexWhere:(Lscala/collection/SeqLike;Lscala/Function1;)I
Asciz	reversedElements;
Asciz	(Lscala/collection/SeqLike;)Lscala/collection/Iterator;;
NameAndType	reversedElements:(Lscala/collection/SeqLike;)Lscala/collection/Iterator;
Method	scala/collection/SeqLike$class.reversedElements:(Lscala/collection/SeqLike;)Lscala/collection/Iterator;
Asciz	Deprecated;
NameAndType	startsWith:(Lscala/collection/SeqLike;Lscala/collection/Seq;)Z
Method	scala/collection/SeqLike$class.startsWith:(Lscala/collection/SeqLike;Lscala/collection/Seq;)Z
Asciz	indexOfSlice;
Asciz	(Lscala/collection/Seq;)I;
Asciz	(Lscala/collection/SeqLike;Lscala/collection/Seq;)I;
NameAndType	indexOfSlice:(Lscala/collection/SeqLike;Lscala/collection/Seq;)I
Method	scala/collection/SeqLike$class.indexOfSlice:(Lscala/collection/SeqLike;Lscala/collection/Seq;)I
Asciz	(Lscala/collection/Seq;I)I;
Asciz	(Lscala/collection/SeqLike;Lscala/collection/Seq;I)I;
NameAndType	indexOfSlice:(Lscala/collection/SeqLike;Lscala/collection/Seq;I)I
Method	scala/collection/SeqLike$class.indexOfSlice:(Lscala/collection/SeqLike;Lscala/collection/Seq;I)I
Asciz	lastIndexOfSlice;
NameAndType	lastIndexOfSlice:(Lscala/collection/SeqLike;Lscala/collection/Seq;)I
Method	scala/collection/SeqLike$class.lastIndexOfSlice:(Lscala/collection/SeqLike;Lscala/collection/Seq;)I
NameAndType	lastIndexOfSlice:(Lscala/collection/SeqLike;Lscala/collection/Seq;I)I
Method	scala/collection/SeqLike$class.lastIndexOfSlice:(Lscala/collection/SeqLike;Lscala/collection/Seq;I)I
Asciz	containsSlice;
NameAndType	containsSlice:(Lscala/collection/SeqLike;Lscala/collection/Seq;)Z
Method	scala/collection/SeqLike$class.containsSlice:(Lscala/collection/SeqLike;Lscala/collection/Seq;)Z
Asciz	contains;
Asciz	(Ljava/lang/Object;)Z;
Asciz	(Lscala/collection/SeqLike;Ljava/lang/Object;)Z;
NameAndType	contains:(Lscala/collection/SeqLike;Ljava/lang/Object;)Z
Method	scala/collection/SeqLike$class.contains:(Lscala/collection/SeqLike;Ljava/lang/Object;)Z
Asciz	distinct;
Asciz	(Lscala/collection/SeqLike;)Ljava/lang/Object;;
NameAndType	distinct:(Lscala/collection/SeqLike;)Ljava/lang/Object;
Method	scala/collection/SeqLike$class.distinct:(Lscala/collection/SeqLike;)Ljava/lang/Object;
Asciz	corresponds;
Asciz	(Lscala/collection/Seq;Lscala/Function2;)Z;
Asciz	(Lscala/collection/SeqLike;Lscala/collection/Seq;Lscala/Function2;)Z;
NameAndType	corresponds:(Lscala/collection/SeqLike;Lscala/collection/Seq;Lscala/Function2;)Z
Method	scala/collection/SeqLike$class.corresponds:(Lscala/collection/SeqLike;Lscala/collection/Seq;Lscala/Function2;)Z
Asciz	sortWith;
Asciz	(Lscala/collection/SeqLike;Lscala/Function2;)Ljava/lang/Object;;
NameAndType	sortWith:(Lscala/collection/SeqLike;Lscala/Function2;)Ljava/lang/Object;
Method	scala/collection/SeqLike$class.sortWith:(Lscala/collection/SeqLike;Lscala/Function2;)Ljava/lang/Object;
Asciz	lt;
Asciz	sortBy;
Asciz	(Lscala/Function1;Lscala/math/Ordering;)Ljava/lang/Object;;
Asciz	(Lscala/collection/SeqLike;Lscala/Function1;Lscala/math/Ordering;)Ljava/lang/Object;;
NameAndType	sortBy:(Lscala/collection/SeqLike;Lscala/Function1;Lscala/math/Ordering;)Ljava/lang/Object;
Method	scala/collection/SeqLike$class.sortBy:(Lscala/collection/SeqLike;Lscala/Function1;Lscala/math/Ordering;)Ljava/lang/Object;
Asciz	toSeq;
Asciz	(Lscala/collection/SeqLike;)Lscala/collection/Seq;;
NameAndType	toSeq:(Lscala/collection/SeqLike;)Lscala/collection/Seq;
Method	scala/collection/SeqLike$class.toSeq:(Lscala/collection/SeqLike;)Lscala/collection/Seq;
Asciz	indices;
Asciz	()Lscala/collection/immutable/Range;;
Asciz	(Lscala/collection/SeqLike;)Lscala/collection/immutable/Range;;
NameAndType	indices:(Lscala/collection/SeqLike;)Lscala/collection/immutable/Range;
Method	scala/collection/SeqLike$class.indices:(Lscala/collection/SeqLike;)Lscala/collection/immutable/Range;
Asciz	hashCode;
NameAndType	hashCode:(Lscala/collection/SeqLike;)I
Method	scala/collection/SeqLike$class.hashCode:(Lscala/collection/SeqLike;)I
Asciz	equals;
NameAndType	equals:(Lscala/collection/SeqLike;Ljava/lang/Object;)Z
Method	scala/collection/SeqLike$class.equals:(Lscala/collection/SeqLike;Ljava/lang/Object;)Z
Asciz	toString;
Asciz	(Lscala/collection/SeqLike;)Ljava/lang/String;;
NameAndType	toString:(Lscala/collection/SeqLike;)Ljava/lang/String;
Method	scala/collection/SeqLike$class.toString:(Lscala/collection/SeqLike;)Ljava/lang/String;
Asciz	findLastIndexOf;
NameAndType	findLastIndexOf:(Lscala/collection/SeqLike;Lscala/Function1;)I
Method	scala/collection/SeqLike$class.findLastIndexOf:(Lscala/collection/SeqLike;Lscala/Function1;)I
Asciz	equalsWith;
NameAndType	equalsWith:(Lscala/collection/SeqLike;Lscala/collection/Seq;Lscala/Function2;)Z
Method	scala/collection/SeqLike$class.equalsWith:(Lscala/collection/SeqLike;Lscala/collection/Seq;Lscala/Function2;)Z
Asciz	projection;
Asciz	(Lscala/collection/SeqLike;)Lscala/collection/SeqView;;
NameAndType	projection:(Lscala/collection/SeqLike;)Lscala/collection/SeqView;
Method	scala/collection/SeqLike$class.projection:(Lscala/collection/SeqLike;)Lscala/collection/SeqView;
Asciz	toIterable;
Asciz	()Lscala/collection/Iterable;;
Asciz	(Lscala/collection/IterableLike;)Lscala/collection/Iterable;;
NameAndType	toIterable:(Lscala/collection/IterableLike;)Lscala/collection/Iterable;
Method	scala/collection/IterableLike$class.toIterable:(Lscala/collection/IterableLike;)Lscala/collection/Iterable;
Asciz	(Lscala/collection/IterableLike;I)Lscala/collection/Iterator;;
NameAndType	sliding:(Lscala/collection/IterableLike;I)Lscala/collection/Iterator;
Method	scala/collection/IterableLike$class.sliding:(Lscala/collection/IterableLike;I)Lscala/collection/Iterator;
Asciz	toStream;
Asciz	()Lscala/collection/immutable/Stream;;
Asciz	(Lscala/collection/IterableLike;)Lscala/collection/immutable/Stream;;
NameAndType	toStream:(Lscala/collection/IterableLike;)Lscala/collection/immutable/Stream;
Method	scala/collection/IterableLike$class.toStream:(Lscala/collection/IterableLike;)Lscala/collection/immutable/Stream;
Asciz	canEqual;
Asciz	(Lscala/collection/IterableLike;Ljava/lang/Object;)Z;
NameAndType	canEqual:(Lscala/collection/IterableLike;Ljava/lang/Object;)Z
Method	scala/collection/IterableLike$class.canEqual:(Lscala/collection/IterableLike;Ljava/lang/Object;)Z
Asciz	elements;
Asciz	(Lscala/collection/IterableLike;)Lscala/collection/Iterator;;
NameAndType	elements:(Lscala/collection/IterableLike;)Lscala/collection/Iterator;
Method	scala/collection/IterableLike$class.elements:(Lscala/collection/IterableLike;)Lscala/collection/Iterator;
Asciz	first;
NameAndType	first:(Lscala/collection/IterableLike;)Ljava/lang/Object;
Method	scala/collection/IterableLike$class.first:(Lscala/collection/IterableLike;)Ljava/lang/Object;
Asciz	firstOption;
Asciz	()Lscala/Option;;
Asciz	(Lscala/collection/IterableLike;)Lscala/Option;;
NameAndType	firstOption:(Lscala/collection/IterableLike;)Lscala/Option;
Method	scala/collection/IterableLike$class.firstOption:(Lscala/collection/IterableLike;)Lscala/Option;
Asciz	genericBuilder;
Asciz	scala/collection/generic/GenericTraversableTemplate$class;
class	scala/collection/generic/GenericTraversableTemplate$class
Asciz	(Lscala/collection/generic/GenericTraversableTemplate;)Lscala/collection/mutable/Builder;;
NameAndType	genericBuilder:(Lscala/collection/generic/GenericTraversableTemplate;)Lscala/collection/mutable/Builder;
Method	scala/collection/generic/GenericTraversableTemplate$class.genericBuilder:(Lscala/collection/generic/GenericTraversableTemplate;)Lscala/collection/mutable/Builder;
Asciz	unzip;
Asciz	(Lscala/collection/generic/GenericTraversableTemplate;Lscala/Function1;)Lscala/Tuple2;;
NameAndType	unzip:(Lscala/collection/generic/GenericTraversableTemplate;Lscala/Function1;)Lscala/Tuple2;
Method	scala/collection/generic/GenericTraversableTemplate$class.unzip:(Lscala/collection/generic/GenericTraversableTemplate;Lscala/Function1;)Lscala/Tuple2;
Asciz	asPair;
Asciz	flatten;
Asciz	(Lscala/Function1;)Lscala/collection/Traversable;;
Asciz	(Lscala/collection/generic/GenericTraversableTemplate;Lscala/Function1;)Lscala/collection/Traversable;;
NameAndType	flatten:(Lscala/collection/generic/GenericTraversableTemplate;Lscala/Function1;)Lscala/collection/Traversable;
Method	scala/collection/generic/GenericTraversableTemplate$class.flatten:(Lscala/collection/generic/GenericTraversableTemplate;Lscala/Function1;)Lscala/collection/Traversable;
Asciz	asTraversable;
Asciz	transpose;
NameAndType	transpose:(Lscala/collection/generic/GenericTraversableTemplate;Lscala/Function1;)Lscala/collection/Traversable;
Method	scala/collection/generic/GenericTraversableTemplate$class.transpose:(Lscala/collection/generic/GenericTraversableTemplate;Lscala/Function1;)Lscala/collection/Traversable;
NameAndType	repr:(Lscala/collection/TraversableLike;)Ljava/lang/Object;
Method	scala/collection/TraversableLike$class.repr:(Lscala/collection/TraversableLike;)Ljava/lang/Object;
Asciz	nonEmpty;
Asciz	(Lscala/collection/TraversableLike;)Z;
NameAndType	nonEmpty:(Lscala/collection/TraversableLike;)Z
Method	scala/collection/TraversableLike$class.nonEmpty:(Lscala/collection/TraversableLike;)Z
Asciz	hasDefiniteSize;
NameAndType	hasDefiniteSize:(Lscala/collection/TraversableLike;)Z
Method	scala/collection/TraversableLike$class.hasDefiniteSize:(Lscala/collection/TraversableLike;)Z
Asciz	filterNot;
Asciz	(Lscala/Function1;)Ljava/lang/Object;;
Asciz	(Lscala/collection/TraversableLike;Lscala/Function1;)Ljava/lang/Object;;
NameAndType	filterNot:(Lscala/collection/TraversableLike;Lscala/Function1;)Ljava/lang/Object;
Method	scala/collection/TraversableLike$class.filterNot:(Lscala/collection/TraversableLike;Lscala/Function1;)Ljava/lang/Object;
Asciz	count;
Asciz	(Lscala/collection/TraversableLike;Lscala/Function1;)I;
NameAndType	count:(Lscala/collection/TraversableLike;Lscala/Function1;)I
Method	scala/collection/TraversableLike$class.count:(Lscala/collection/TraversableLike;Lscala/Function1;)I
Asciz	$div$colon;
Asciz	(Lscala/collection/TraversableLike;Ljava/lang/Object;Lscala/Function2;)Ljava/lang/Object;;
NameAndType	$div$colon:(Lscala/collection/TraversableLike;Ljava/lang/Object;Lscala/Function2;)Ljava/lang/Object;
Method	scala/collection/TraversableLike$class.$div$colon:(Lscala/collection/TraversableLike;Ljava/lang/Object;Lscala/Function2;)Ljava/lang/Object;
Asciz	$colon$bslash;
NameAndType	$colon$bslash:(Lscala/collection/TraversableLike;Ljava/lang/Object;Lscala/Function2;)Ljava/lang/Object;
Method	scala/collection/TraversableLike$class.$colon$bslash:(Lscala/collection/TraversableLike;Ljava/lang/Object;Lscala/Function2;)Ljava/lang/Object;
Asciz	reduceLeftOption;
Asciz	(Lscala/Function2;)Lscala/Option;;
Asciz	(Lscala/collection/TraversableLike;Lscala/Function2;)Lscala/Option;;
NameAndType	reduceLeftOption:(Lscala/collection/TraversableLike;Lscala/Function2;)Lscala/Option;
Method	scala/collection/TraversableLike$class.reduceLeftOption:(Lscala/collection/TraversableLike;Lscala/Function2;)Lscala/Option;
Asciz	reduceRightOption;
NameAndType	reduceRightOption:(Lscala/collection/TraversableLike;Lscala/Function2;)Lscala/Option;
Method	scala/collection/TraversableLike$class.reduceRightOption:(Lscala/collection/TraversableLike;Lscala/Function2;)Lscala/Option;
Asciz	sum;
Asciz	(Lscala/math/Numeric;)Ljava/lang/Object;;
Asciz	(Lscala/collection/TraversableLike;Lscala/math/Numeric;)Ljava/lang/Object;;
NameAndType	sum:(Lscala/collection/TraversableLike;Lscala/math/Numeric;)Ljava/lang/Object;
Method	scala/collection/TraversableLike$class.sum:(Lscala/collection/TraversableLike;Lscala/math/Numeric;)Ljava/lang/Object;
Asciz	num;
Asciz	Lscala/math/Numeric;;
Asciz	product;
NameAndType	product:(Lscala/collection/TraversableLike;Lscala/math/Numeric;)Ljava/lang/Object;
Method	scala/collection/TraversableLike$class.product:(Lscala/collection/TraversableLike;Lscala/math/Numeric;)Ljava/lang/Object;
Asciz	min;
Asciz	(Lscala/math/Ordering;)Ljava/lang/Object;;
Asciz	(Lscala/collection/TraversableLike;Lscala/math/Ordering;)Ljava/lang/Object;;
NameAndType	min:(Lscala/collection/TraversableLike;Lscala/math/Ordering;)Ljava/lang/Object;
Method	scala/collection/TraversableLike$class.min:(Lscala/collection/TraversableLike;Lscala/math/Ordering;)Ljava/lang/Object;
Asciz	cmp;
Asciz	max;
NameAndType	max:(Lscala/collection/TraversableLike;Lscala/math/Ordering;)Ljava/lang/Object;
Method	scala/collection/TraversableLike$class.max:(Lscala/collection/TraversableLike;Lscala/math/Ordering;)Ljava/lang/Object;
Asciz	headOption;
Asciz	(Lscala/collection/TraversableLike;)Lscala/Option;;
NameAndType	headOption:(Lscala/collection/TraversableLike;)Lscala/Option;
Method	scala/collection/TraversableLike$class.headOption:(Lscala/collection/TraversableLike;)Lscala/Option;
Asciz	lastOption;
NameAndType	lastOption:(Lscala/collection/TraversableLike;)Lscala/Option;
Method	scala/collection/TraversableLike$class.lastOption:(Lscala/collection/TraversableLike;)Lscala/Option;
Asciz	copyToBuffer;
Asciz	(Lscala/collection/mutable/Buffer;)V;
Asciz	(Lscala/collection/TraversableLike;Lscala/collection/mutable/Buffer;)V;
NameAndType	copyToBuffer:(Lscala/collection/TraversableLike;Lscala/collection/mutable/Buffer;)V
Method	scala/collection/TraversableLike$class.copyToBuffer:(Lscala/collection/TraversableLike;Lscala/collection/mutable/Buffer;)V
Asciz	dest;
Asciz	Lscala/collection/mutable/Buffer;;
Asciz	(Ljava/lang/Object;I)V;
Asciz	(Lscala/collection/TraversableLike;Ljava/lang/Object;I)V;
NameAndType	copyToArray:(Lscala/collection/TraversableLike;Ljava/lang/Object;I)V
Method	scala/collection/TraversableLike$class.copyToArray:(Lscala/collection/TraversableLike;Ljava/lang/Object;I)V
Asciz	(Ljava/lang/Object;)V;
Asciz	(Lscala/collection/TraversableLike;Ljava/lang/Object;)V;
NameAndType	copyToArray:(Lscala/collection/TraversableLike;Ljava/lang/Object;)V
Method	scala/collection/TraversableLike$class.copyToArray:(Lscala/collection/TraversableLike;Ljava/lang/Object;)V
Asciz	toArray;
Asciz	(Lscala/reflect/ClassManifest;)Ljava/lang/Object;;
Asciz	(Lscala/collection/TraversableLike;Lscala/reflect/ClassManifest;)Ljava/lang/Object;;
NameAndType	toArray:(Lscala/collection/TraversableLike;Lscala/reflect/ClassManifest;)Ljava/lang/Object;
Method	scala/collection/TraversableLike$class.toArray:(Lscala/collection/TraversableLike;Lscala/reflect/ClassManifest;)Ljava/lang/Object;
Asciz	evidence$1;
Asciz	Lscala/reflect/ClassManifest;;
Asciz	toList;
Asciz	()Lscala/collection/immutable/List;;
Asciz	(Lscala/collection/TraversableLike;)Lscala/collection/immutable/List;;
NameAndType	toList:(Lscala/collection/TraversableLike;)Lscala/collection/immutable/List;
Method	scala/collection/TraversableLike$class.toList:(Lscala/collection/TraversableLike;)Lscala/collection/immutable/List;
Asciz	toIndexedSeq;
Asciz	()Lscala/collection/mutable/IndexedSeq;;
Asciz	(Lscala/collection/TraversableLike;)Lscala/collection/mutable/IndexedSeq;;
NameAndType	toIndexedSeq:(Lscala/collection/TraversableLike;)Lscala/collection/mutable/IndexedSeq;
Method	scala/collection/TraversableLike$class.toIndexedSeq:(Lscala/collection/TraversableLike;)Lscala/collection/mutable/IndexedSeq;
Asciz	toSet;
Asciz	()Lscala/collection/immutable/Set;;
Asciz	(Lscala/collection/TraversableLike;)Lscala/collection/immutable/Set;;
NameAndType	toSet:(Lscala/collection/TraversableLike;)Lscala/collection/immutable/Set;
Method	scala/collection/TraversableLike$class.toSet:(Lscala/collection/TraversableLike;)Lscala/collection/immutable/Set;
Asciz	toMap;
Asciz	(Lscala/Predef$$less$colon$less;)Lscala/collection/immutable/Map;;
Asciz	(Lscala/collection/TraversableLike;Lscala/Predef$$less$colon$less;)Lscala/collection/immutable/Map;;
NameAndType	toMap:(Lscala/collection/TraversableLike;Lscala/Predef$$less$colon$less;)Lscala/collection/immutable/Map;
Method	scala/collection/TraversableLike$class.toMap:(Lscala/collection/TraversableLike;Lscala/Predef$$less$colon$less;)Lscala/collection/immutable/Map;
Asciz	ev;
Asciz	Lscala/Predef$$less$colon$less;;
Asciz	mkString;
Asciz	(Ljava/lang/String;Ljava/lang/String;Ljava/lang/String;)Ljava/lang/String;;
Asciz	(Lscala/collection/TraversableLike;Ljava/lang/String;Ljava/lang/String;Ljava/lang/String;)Ljava/lang/String;;
NameAndType	mkString:(Lscala/collection/TraversableLike;Ljava/lang/String;Ljava/lang/String;Ljava/lang/String;)Ljava/lang/String;
Method	scala/collection/TraversableLike$class.mkString:(Lscala/collection/TraversableLike;Ljava/lang/String;Ljava/lang/String;Ljava/lang/String;)Ljava/lang/String;
Asciz	Ljava/lang/String;;
Asciz	sep;
Asciz	(Ljava/lang/String;)Ljava/lang/String;;
Asciz	(Lscala/collection/TraversableLike;Ljava/lang/String;)Ljava/lang/String;;
NameAndType	mkString:(Lscala/collection/TraversableLike;Ljava/lang/String;)Ljava/lang/String;
Method	scala/collection/TraversableLike$class.mkString:(Lscala/collection/TraversableLike;Ljava/lang/String;)Ljava/lang/String;
Asciz	(Lscala/collection/TraversableLike;)Ljava/lang/String;;
NameAndType	mkString:(Lscala/collection/TraversableLike;)Ljava/lang/String;
Method	scala/collection/TraversableLike$class.mkString:(Lscala/collection/TraversableLike;)Ljava/lang/String;
Asciz	addString;
Asciz	(Lscala/collection/mutable/StringBuilder;Ljava/lang/String;Ljava/lang/String;Ljava/lang/String;)Lscala/collection/mutable/StringBuilder;;
Asciz	(Lscala/collection/TraversableLike;Lscala/collection/mutable/StringBuilder;Ljava/lang/String;Ljava/lang/String;Ljava/lang/String;)Lscala/collection/mutable/StringBuilder;;
NameAndType	addString:(Lscala/collection/TraversableLike;Lscala/collection/mutable/StringBuilder;Ljava/lang/String;Ljava/lang/String;Ljava/lang/String;)Lscala/collection/mutable/StringBuilder;
Method	scala/collection/TraversableLike$class.addString:(Lscala/collection/TraversableLike;Lscala/collection/mutable/StringBuilder;Ljava/lang/String;Ljava/lang/String;Ljava/lang/String;)Lscala/collection/mutable/StringBuilder;
Asciz	b;
Asciz	Lscala/collection/mutable/StringBuilder;;
Asciz	(Lscala/collection/mutable/StringBuilder;Ljava/lang/String;)Lscala/collection/mutable/StringBuilder;;
Asciz	(Lscala/collection/TraversableLike;Lscala/collection/mutable/StringBuilder;Ljava/lang/String;)Lscala/collection/mutable/StringBuilder;;
NameAndType	addString:(Lscala/collection/TraversableLike;Lscala/collection/mutable/StringBuilder;Ljava/lang/String;)Lscala/collection/mutable/StringBuilder;
Method	scala/collection/TraversableLike$class.addString:(Lscala/collection/TraversableLike;Lscala/collection/mutable/StringBuilder;Ljava/lang/String;)Lscala/collection/mutable/StringBuilder;
Asciz	(Lscala/collection/mutable/StringBuilder;)Lscala/collection/mutable/StringBuilder;;
Asciz	(Lscala/collection/TraversableLike;Lscala/collection/mutable/StringBuilder;)Lscala/collection/mutable/StringBuilder;;
NameAndType	addString:(Lscala/collection/TraversableLike;Lscala/collection/mutable/StringBuilder;)Lscala/collection/mutable/StringBuilder;
Method	scala/collection/TraversableLike$class.addString:(Lscala/collection/TraversableLike;Lscala/collection/mutable/StringBuilder;)Lscala/collection/mutable/StringBuilder;
Asciz	withFilter;
Asciz	(Lscala/Function1;)Lscala/collection/TraversableLike$WithFilter;;
Asciz	(Lscala/collection/TraversableLike;Lscala/Function1;)Lscala/collection/TraversableLike$WithFilter;;
NameAndType	withFilter:(Lscala/collection/TraversableLike;Lscala/Function1;)Lscala/collection/TraversableLike$WithFilter;
Method	scala/collection/TraversableLike$class.withFilter:(Lscala/collection/TraversableLike;Lscala/Function1;)Lscala/collection/TraversableLike$WithFilter;
Asciz	orElse;
Asciz	(Lscala/PartialFunction;)Lscala/PartialFunction;;
Asciz	scala/PartialFunction$class;
class	scala/PartialFunction$class
Asciz	(Lscala/PartialFunction;Lscala/PartialFunction;)Lscala/PartialFunction;;
NameAndType	orElse:(Lscala/PartialFunction;Lscala/PartialFunction;)Lscala/PartialFunction;
Method	scala/PartialFunction$class.orElse:(Lscala/PartialFunction;Lscala/PartialFunction;)Lscala/PartialFunction;
Asciz	andThen;
Asciz	(Lscala/Function1;)Lscala/PartialFunction;;
Asciz	(Lscala/PartialFunction;Lscala/Function1;)Lscala/PartialFunction;;
NameAndType	andThen:(Lscala/PartialFunction;Lscala/Function1;)Lscala/PartialFunction;
Method	scala/PartialFunction$class.andThen:(Lscala/PartialFunction;Lscala/Function1;)Lscala/PartialFunction;
Asciz	k;
Asciz	lift;
Asciz	()Lscala/Function1;;
Asciz	(Lscala/PartialFunction;)Lscala/Function1;;
NameAndType	lift:(Lscala/PartialFunction;)Lscala/Function1;
Method	scala/PartialFunction$class.lift:(Lscala/PartialFunction;)Lscala/Function1;
Asciz	compose;
Asciz	(Lscala/Function1;)Lscala/Function1;;
Asciz	scala/Function1$class;
class	scala/Function1$class
Asciz	(Lscala/Function1;Lscala/Function1;)Lscala/Function1;;
NameAndType	compose:(Lscala/Function1;Lscala/Function1;)Lscala/Function1;
Method	scala/Function1$class.compose:(Lscala/Function1;Lscala/Function1;)Lscala/Function1;
Asciz	g;
NameAndType	from:I
Field	scala/collection/IndexedSeqViewLike$$anon$6.from:I
NameAndType	until:I
Field	scala/collection/IndexedSeqViewLike$$anon$6.until:I
Asciz	scala$collection$IndexedSeqViewLike$Sliced$$$outer;
Asciz	()Lscala/collection/IndexedSeqViewLike;;
NameAndType	$outer:Lscala/collection/IndexedSeqViewLike;
Field	scala/collection/IndexedSeqViewLike$$anon$6.$outer:Lscala/collection/IndexedSeqViewLike;
Asciz	scala$collection$SeqViewLike$Sliced$$$outer;
Asciz	()Lscala/collection/SeqViewLike;;
Asciz	scala$collection$IterableViewLike$Sliced$$$outer;
Asciz	()Lscala/collection/IterableViewLike;;
Asciz	scala$collection$TraversableViewLike$Sliced$$$outer;
Asciz	()Lscala/collection/TraversableViewLike;;
Asciz	scala$collection$TraversableViewLike$Transformed$$$outer;
Asciz	scala/PartialFunction;
class	scala/PartialFunction
NameAndType	andThen:(Lscala/Function1;)Lscala/PartialFunction;
InterfaceMethod	scala/PartialFunction.andThen:(Lscala/Function1;)Lscala/PartialFunction;
Asciz	()Lscala/collection/IterableView;;
Asciz	scala/collection/SeqLike;
class	scala/collection/SeqLike
NameAndType	projection:()Lscala/collection/SeqView;
InterfaceMethod	scala/collection/SeqLike.projection:()Lscala/collection/SeqView;
Asciz	scala/runtime/BoxesRunTime;
class	scala/runtime/BoxesRunTime
Asciz	unboxToInt;
NameAndType	unboxToInt:(Ljava/lang/Object;)I
Method	scala/runtime/BoxesRunTime.unboxToInt:(Ljava/lang/Object;)I
NameAndType	isDefinedAt:(I)Z
InterfaceMethod	scala/collection/SeqLike.isDefinedAt:(I)Z
Asciz	x;
Asciz	scala/collection/IndexedSeqLike;
class	scala/collection/IndexedSeqLike
NameAndType	view:(II)Lscala/collection/IndexedSeqView;
InterfaceMethod	scala/collection/IndexedSeqLike.view:(II)Lscala/collection/IndexedSeqView;
Asciz	(II)Lscala/collection/IterableView;;
Asciz	(II)Lscala/collection/SeqView;;
NameAndType	view:()Lscala/collection/IndexedSeqView;
InterfaceMethod	scala/collection/IndexedSeqLike.view:()Lscala/collection/IndexedSeqView;
Asciz	(Ljava/lang/Object;)Lscala/collection/Traversable;;
NameAndType	toCollection:(Ljava/lang/Object;)Lscala/collection/IndexedSeq;
InterfaceMethod	scala/collection/IndexedSeqLike.toCollection:(Ljava/lang/Object;)Lscala/collection/IndexedSeq;
Asciz	(Ljava/lang/Object;)Lscala/collection/Iterable;;
Asciz	(Ljava/lang/Object;)Lscala/collection/Seq;;
Asciz	()Lscala/collection/Traversable;;
NameAndType	thisCollection:()Lscala/collection/IndexedSeq;
InterfaceMethod	scala/collection/IndexedSeqLike.thisCollection:()Lscala/collection/IndexedSeq;
Asciz	scala/collection/TraversableViewLike;
class	scala/collection/TraversableViewLike
NameAndType	takeWhile:(Lscala/Function1;)Lscala/collection/TraversableView;
InterfaceMethod	scala/collection/TraversableViewLike.takeWhile:(Lscala/Function1;)Lscala/collection/TraversableView;
NameAndType	dropWhile:(Lscala/Function1;)Lscala/collection/TraversableView;
InterfaceMethod	scala/collection/TraversableViewLike.dropWhile:(Lscala/Function1;)Lscala/collection/TraversableView;
NameAndType	take:(I)Lscala/collection/TraversableView;
InterfaceMethod	scala/collection/TraversableViewLike.take:(I)Lscala/collection/TraversableView;
NameAndType	drop:(I)Lscala/collection/TraversableView;
InterfaceMethod	scala/collection/TraversableViewLike.drop:(I)Lscala/collection/TraversableView;
NameAndType	init:()Lscala/collection/TraversableView;
InterfaceMethod	scala/collection/TraversableViewLike.init:()Lscala/collection/TraversableView;
NameAndType	filter:(Lscala/Function1;)Lscala/collection/TraversableView;
InterfaceMethod	scala/collection/TraversableViewLike.filter:(Lscala/Function1;)Lscala/collection/TraversableView;
Asciz	scala/collection/SeqViewLike;
class	scala/collection/SeqViewLike
NameAndType	sorted:(Lscala/math/Ordering;)Lscala/collection/SeqView;
InterfaceMethod	scala/collection/SeqViewLike.sorted:(Lscala/math/Ordering;)Lscala/collection/SeqView;
Asciz	(Lscala/collection/Seq;)Ljava/lang/Object;;
NameAndType	intersect:(Lscala/collection/Seq;)Lscala/collection/SeqView;
InterfaceMethod	scala/collection/SeqViewLike.intersect:(Lscala/collection/Seq;)Lscala/collection/SeqView;
NameAndType	diff:(Lscala/collection/Seq;)Lscala/collection/SeqView;
InterfaceMethod	scala/collection/SeqViewLike.diff:(Lscala/collection/Seq;)Lscala/collection/SeqView;
NameAndType	reverse:()Lscala/collection/SeqView;
InterfaceMethod	scala/collection/SeqViewLike.reverse:()Lscala/collection/SeqView;
Asciz	(Ljava/lang/Object;)Lscala/collection/SeqViewLike$Transformed;;
Asciz	scala/collection/IndexedSeqViewLike;
class	scala/collection/IndexedSeqViewLike
NameAndType	newPrepended:(Ljava/lang/Object;)Lscala/collection/IndexedSeqViewLike$Transformed;
InterfaceMethod	scala/collection/IndexedSeqViewLike.newPrepended:(Ljava/lang/Object;)Lscala/collection/IndexedSeqViewLike$Transformed;
Asciz	(ILscala/collection/Seq;I)Lscala/collection/SeqViewLike$Transformed;;
NameAndType	newPatched:(ILscala/collection/Seq;I)Lscala/collection/IndexedSeqViewLike$Transformed;
InterfaceMethod	scala/collection/IndexedSeqViewLike.newPatched:(ILscala/collection/Seq;I)Lscala/collection/IndexedSeqViewLike$Transformed;
Asciz	()Lscala/collection/SeqViewLike$Transformed;;
NameAndType	newReversed:()Lscala/collection/IndexedSeqViewLike$Transformed;
InterfaceMethod	scala/collection/IndexedSeqViewLike.newReversed:()Lscala/collection/IndexedSeqViewLike$Transformed;
Asciz	(Lscala/collection/Iterable;Ljava/lang/Object;Ljava/lang/Object;)Lscala/collection/IterableViewLike$Transformed;;
NameAndType	newZippedAll:(Lscala/collection/Iterable;Ljava/lang/Object;Ljava/lang/Object;)Lscala/collection/IndexedSeqViewLike$Transformed;
InterfaceMethod	scala/collection/IndexedSeqViewLike.newZippedAll:(Lscala/collection/Iterable;Ljava/lang/Object;Ljava/lang/Object;)Lscala/collection/IndexedSeqViewLike$Transformed;
Asciz	(Lscala/collection/Iterable;Ljava/lang/Object;Ljava/lang/Object;)Lscala/collection/SeqViewLike$Transformed;;
Asciz	(Lscala/collection/Iterable;)Lscala/collection/IterableViewLike$Transformed;;
NameAndType	newZipped:(Lscala/collection/Iterable;)Lscala/collection/IndexedSeqViewLike$Transformed;
InterfaceMethod	scala/collection/IndexedSeqViewLike.newZipped:(Lscala/collection/Iterable;)Lscala/collection/IndexedSeqViewLike$Transformed;
Asciz	(Lscala/collection/Iterable;)Lscala/collection/SeqViewLike$Transformed;;
Asciz	(Lscala/Function1;)Lscala/collection/TraversableViewLike$Transformed;;
NameAndType	newTakenWhile:(Lscala/Function1;)Lscala/collection/IndexedSeqViewLike$Transformed;
InterfaceMethod	scala/collection/IndexedSeqViewLike.newTakenWhile:(Lscala/Function1;)Lscala/collection/IndexedSeqViewLike$Transformed;
Asciz	(Lscala/Function1;)Lscala/collection/IterableViewLike$Transformed;;
Asciz	(Lscala/Function1;)Lscala/collection/SeqViewLike$Transformed;;
NameAndType	newDroppedWhile:(Lscala/Function1;)Lscala/collection/IndexedSeqViewLike$Transformed;
InterfaceMethod	scala/collection/IndexedSeqViewLike.newDroppedWhile:(Lscala/Function1;)Lscala/collection/IndexedSeqViewLike$Transformed;
Asciz	(II)Lscala/collection/TraversableViewLike$Transformed;;
NameAndType	newSliced:(II)Lscala/collection/IndexedSeqViewLike$Transformed;
InterfaceMethod	scala/collection/IndexedSeqViewLike.newSliced:(II)Lscala/collection/IndexedSeqViewLike$Transformed;
Asciz	(II)Lscala/collection/IterableViewLike$Transformed;;
Asciz	(II)Lscala/collection/SeqViewLike$Transformed;;
NameAndType	newFiltered:(Lscala/Function1;)Lscala/collection/IndexedSeqViewLike$Transformed;
InterfaceMethod	scala/collection/IndexedSeqViewLike.newFiltered:(Lscala/Function1;)Lscala/collection/IndexedSeqViewLike$Transformed;
NameAndType	newFlatMapped:(Lscala/Function1;)Lscala/collection/IndexedSeqViewLike$Transformed;
InterfaceMethod	scala/collection/IndexedSeqViewLike.newFlatMapped:(Lscala/Function1;)Lscala/collection/IndexedSeqViewLike$Transformed;
NameAndType	newMapped:(Lscala/Function1;)Lscala/collection/IndexedSeqViewLike$Transformed;
InterfaceMethod	scala/collection/IndexedSeqViewLike.newMapped:(Lscala/Function1;)Lscala/collection/IndexedSeqViewLike$Transformed;
Asciz	(Lscala/collection/Traversable;)Lscala/collection/TraversableViewLike$Transformed;;
NameAndType	newAppended:(Lscala/collection/Traversable;)Lscala/collection/IndexedSeqViewLike$Transformed;
InterfaceMethod	scala/collection/IndexedSeqViewLike.newAppended:(Lscala/collection/Traversable;)Lscala/collection/IndexedSeqViewLike$Transformed;
Asciz	(Lscala/collection/Traversable;)Lscala/collection/IterableViewLike$Transformed;;
Asciz	(Lscala/collection/Traversable;)Lscala/collection/SeqViewLike$Transformed;;
Asciz	(Lscala/Function0;)Lscala/collection/TraversableViewLike$Transformed;;
NameAndType	newForced:(Lscala/Function0;)Lscala/collection/IndexedSeqViewLike$Transformed;
InterfaceMethod	scala/collection/IndexedSeqViewLike.newForced:(Lscala/Function0;)Lscala/collection/IndexedSeqViewLike$Transformed;
Asciz	(Lscala/Function0;)Lscala/collection/IterableViewLike$Transformed;;
Asciz	(Lscala/Function0;)Lscala/collection/SeqViewLike$Transformed;;
Asciz	(II)Ljava/lang/Object;;
Asciz	scala/collection/TraversableViewLike$Sliced;
class	scala/collection/TraversableViewLike$Sliced
NameAndType	slice:(II)Lscala/collection/TraversableView;
InterfaceMethod	scala/collection/TraversableViewLike$Sliced.slice:(II)Lscala/collection/TraversableView;
Asciz	(Ljava/lang/Object;)Ljava/lang/Object;;
Asciz	scala/collection/SeqViewLike$Sliced;
class	scala/collection/SeqViewLike$Sliced
NameAndType	apply:(I)Ljava/lang/Object;
InterfaceMethod	scala/collection/SeqViewLike$Sliced.apply:(I)Ljava/lang/Object;
Asciz	v1;
Asciz	<init>;
Asciz	(Lscala/collection/IndexedSeqViewLike;II)V;
Asciz	java/lang/NullPointerException;
class	java/lang/NullPointerException
Asciz	()V;
NameAndType	"<init>":()V
Method	java/lang/NullPointerException."<init>":()V
Asciz	java/lang/Object;
class	java/lang/Object
Method	java/lang/Object."<init>":()V
Asciz	$init$;
NameAndType	$init$:(Lscala/Function1;)V
Method	scala/Function1$class.$init$:(Lscala/Function1;)V
Asciz	(Lscala/PartialFunction;)V;
NameAndType	$init$:(Lscala/PartialFunction;)V
Method	scala/PartialFunction$class.$init$:(Lscala/PartialFunction;)V
Asciz	(Lscala/collection/TraversableLike;)V;
NameAndType	$init$:(Lscala/collection/TraversableLike;)V
Method	scala/collection/TraversableLike$class.$init$:(Lscala/collection/TraversableLike;)V
Asciz	(Lscala/collection/generic/GenericTraversableTemplate;)V;
NameAndType	$init$:(Lscala/collection/generic/GenericTraversableTemplate;)V
Method	scala/collection/generic/GenericTraversableTemplate$class.$init$:(Lscala/collection/generic/GenericTraversableTemplate;)V
Asciz	scala/collection/Traversable$class;
class	scala/collection/Traversable$class
Asciz	(Lscala/collection/Traversable;)V;
NameAndType	$init$:(Lscala/collection/Traversable;)V
Method	scala/collection/Traversable$class.$init$:(Lscala/collection/Traversable;)V
Asciz	(Lscala/collection/IterableLike;)V;
NameAndType	$init$:(Lscala/collection/IterableLike;)V
Method	scala/collection/IterableLike$class.$init$:(Lscala/collection/IterableLike;)V
Asciz	scala/collection/Iterable$class;
class	scala/collection/Iterable$class
Asciz	(Lscala/collection/Iterable;)V;
NameAndType	$init$:(Lscala/collection/Iterable;)V
Method	scala/collection/Iterable$class.$init$:(Lscala/collection/Iterable;)V
Asciz	(Lscala/collection/SeqLike;)V;
NameAndType	$init$:(Lscala/collection/SeqLike;)V
Method	scala/collection/SeqLike$class.$init$:(Lscala/collection/SeqLike;)V
Asciz	scala/collection/Seq$class;
class	scala/collection/Seq$class
Asciz	(Lscala/collection/Seq;)V;
NameAndType	$init$:(Lscala/collection/Seq;)V
Method	scala/collection/Seq$class.$init$:(Lscala/collection/Seq;)V
Asciz	(Lscala/collection/IndexedSeqLike;)V;
NameAndType	$init$:(Lscala/collection/IndexedSeqLike;)V
Method	scala/collection/IndexedSeqLike$class.$init$:(Lscala/collection/IndexedSeqLike;)V
Asciz	(Lscala/collection/IndexedSeq;)V;
NameAndType	$init$:(Lscala/collection/IndexedSeq;)V
Method	scala/collection/IndexedSeq$class.$init$:(Lscala/collection/IndexedSeq;)V
Asciz	(Lscala/collection/TraversableViewLike;)V;
NameAndType	$init$:(Lscala/collection/TraversableViewLike;)V
Method	scala/collection/TraversableViewLike$class.$init$:(Lscala/collection/TraversableViewLike;)V
Asciz	(Lscala/collection/IterableViewLike;)V;
NameAndType	$init$:(Lscala/collection/IterableViewLike;)V
Method	scala/collection/IterableViewLike$class.$init$:(Lscala/collection/IterableViewLike;)V
Asciz	(Lscala/collection/SeqViewLike;)V;
NameAndType	$init$:(Lscala/collection/SeqViewLike;)V
Method	scala/collection/SeqViewLike$class.$init$:(Lscala/collection/SeqViewLike;)V
Asciz	(Lscala/collection/IndexedSeqViewLike;)V;
NameAndType	$init$:(Lscala/collection/IndexedSeqViewLike;)V
Method	scala/collection/IndexedSeqViewLike$class.$init$:(Lscala/collection/IndexedSeqViewLike;)V
Asciz	(Lscala/collection/TraversableViewLike$Transformed;)V;
NameAndType	$init$:(Lscala/collection/TraversableViewLike$Transformed;)V
Method	scala/collection/TraversableViewLike$Transformed$class.$init$:(Lscala/collection/TraversableViewLike$Transformed;)V
Asciz	(Lscala/collection/TraversableViewLike$Sliced;)V;
NameAndType	$init$:(Lscala/collection/TraversableViewLike$Sliced;)V
Method	scala/collection/TraversableViewLike$Sliced$class.$init$:(Lscala/collection/TraversableViewLike$Sliced;)V
Asciz	(Lscala/collection/IterableViewLike$Sliced;)V;
NameAndType	$init$:(Lscala/collection/IterableViewLike$Sliced;)V
Method	scala/collection/IterableViewLike$Sliced$class.$init$:(Lscala/collection/IterableViewLike$Sliced;)V
Asciz	(Lscala/collection/SeqViewLike$Sliced;)V;
NameAndType	$init$:(Lscala/collection/SeqViewLike$Sliced;)V
Method	scala/collection/SeqViewLike$Sliced$class.$init$:(Lscala/collection/SeqViewLike$Sliced;)V
Asciz	(Lscala/collection/IndexedSeqViewLike$Sliced;)V;
NameAndType	$init$:(Lscala/collection/IndexedSeqViewLike$Sliced;)V
Method	scala/collection/IndexedSeqViewLike$Sliced$class.$init$:(Lscala/collection/IndexedSeqViewLike$Sliced;)V
Asciz	(Lscala/collection/IndexedSeqViewLike<TA;TColl;TThis;>;)V;
Asciz	Ljava/lang/Object;Lscala/collection/IndexedSeqViewLike<TA;TColl;TThis;>.Sliced;;
Asciz	Scala;
Asciz	InnerClasses;
Asciz	Sliced;
Asciz	scala/collection/SeqViewLike$Transformed;
class	scala/collection/SeqViewLike$Transformed
Asciz	Transformed;
Asciz	scala/Predef$$less$colon$less;
class	scala/Predef$$less$colon$less
Asciz	scala/Predef;
class	scala/Predef
Asciz	$less$colon$less;
Asciz	scala/collection/IterableViewLike$Sliced;
class	scala/collection/IterableViewLike$Sliced
Asciz	scala/collection/IterableViewLike;
class	scala/collection/IterableViewLike
Asciz	scala/collection/IndexedSeqViewLike$Sliced;
class	scala/collection/IndexedSeqViewLike$Sliced
Asciz	scala/collection/TraversableLike$WithFilter;
class	scala/collection/TraversableLike$WithFilter
Asciz	scala/collection/TraversableLike;
class	scala/collection/TraversableLike
Asciz	WithFilter;
Asciz	$anon$6;
Asciz	scala/collection/IterableViewLike$Transformed;
class	scala/collection/IterableViewLike$Transformed
Asciz	scala/collection/IndexedSeqViewLike$Transformed;
class	scala/collection/IndexedSeqViewLike$Transformed
Asciz	scala/collection/TraversableViewLike$Transformed;
class	scala/collection/TraversableViewLike$Transformed

{
public volatile int bitmap$0;
  Signature: I

private final java.lang.Object underlying;
  Signature: Ljava/lang/Object;

private final scala.collection.IndexedSeqViewLike $outer;
  Signature: Lscala/collection/IndexedSeqViewLike;

private final int until;
  Signature: I

private final int from;
  Signature: I

public void foreach(scala.Function1);
  Signature: (Lscala/Function1;)V
  Code:
   Stack=2, Locals=2, Args_size=2
	aload_0
	aload_1
	invokestatic	Method scala/collection/IndexedSeqViewLike$Sliced$class.foreach:(Lscala/collection/IndexedSeqViewLike$Sliced;Lscala/Function1;)V
	return
  Labels:
  LocalVariableTable: 
   Start  Length  Slot  Name   Signature
   0      6      0    this       Lscala/collection/IndexedSeqViewLike$$anon$6;
   0      6      1    f       Lscala/Function1;


public int length();
  Signature: ()I
  Code:
   Stack=1, Locals=1, Args_size=1
	aload_0
	invokestatic	Method scala/collection/SeqViewLike$Sliced$class.length:(Lscala/collection/SeqViewLike$Sliced;)I
	ireturn
  Labels:

public java.lang.Object apply(int);
  Signature: (I)Ljava/lang/Object;
  Code:
   Stack=2, Locals=2, Args_size=2
	aload_0
	iload_1
	invokestatic	Method scala/collection/SeqViewLike$Sliced$class.apply:(Lscala/collection/SeqViewLike$Sliced;I)Ljava/lang/Object;
	areturn
  Labels:
  LocalVariableTable: 
   Start  Length  Slot  Name   Signature
   0      6      0    this       Lscala/collection/IndexedSeqViewLike$$anon$6;
   0      6      1    idx       I


public scala.collection.Iterator iterator();
  Signature: ()Lscala/collection/Iterator;
  Code:
   Stack=1, Locals=1, Args_size=1
	aload_0
	invokestatic	Method scala/collection/IterableViewLike$Sliced$class.iterator:(Lscala/collection/IterableViewLike$Sliced;)Lscala/collection/Iterator;
	areturn
  Labels:

public java.lang.String stringPrefix();
  Signature: ()Ljava/lang/String;
  Code:
   Stack=1, Locals=1, Args_size=1
	aload_0
	invokestatic	Method scala/collection/TraversableViewLike$Sliced$class.stringPrefix:(Lscala/collection/TraversableViewLike$Sliced;)Ljava/lang/String;
	areturn
  Labels:

public scala.collection.TraversableView slice(int, int);
  Signature: (II)Lscala/collection/TraversableView;
  Code:
   Stack=3, Locals=3, Args_size=3
	aload_0
	iload_1
	iload_2
	invokestatic	Method scala/collection/TraversableViewLike$Sliced$class.slice:(Lscala/collection/TraversableViewLike$Sliced;II)Lscala/collection/TraversableView;
	areturn
  Labels:
  LocalVariableTable: 
   Start  Length  Slot  Name   Signature
   0      7      0    this       Lscala/collection/IndexedSeqViewLike$$anon$6;
   0      7      1    from1       I
   0      7      2    until1       I


public java.lang.Object underlying();
  Signature: ()Ljava/lang/Object;
  Code:
   Stack=3, Locals=1, Args_size=1
	aload_0
	getfield	Field bitmap$0:I
	iconst_1
	iand
	iconst_0
	if_icmpne	l1 // aload_0
	aload_0
	dup
	pop
	monitorenter
	aload_0
	getfield	Field bitmap$0:I
	iconst_1
	iand
	iconst_0
	if_icmpne	l2 // aload_0
	aload_0
	aload_0
	invokestatic	Method scala/collection/TraversableViewLike$Transformed$class.underlying:(Lscala/collection/TraversableViewLike$Transformed;)Ljava/lang/Object;
	putfield	Field underlying:Ljava/lang/Object;
	aload_0
	aload_0
	getfield	Field bitmap$0:I
	iconst_1
	ior
	putfield	Field bitmap$0:I
l2	aload_0
	monitorexit
l1	aload_0
	getfield	Field underlying:Ljava/lang/Object;
	areturn
	aload_0
	monitorexit
	athrow
  Labels:
   	l2 = 42 // aload_0
   	l1 = 44 // aload_0
  Exception table:
   from   to  target type
    14    44    49   any

public scala.collection.IndexedSeqViewLike$Transformed newForced(scala.Function0);
  Signature: (Lscala/Function0;)Lscala/collection/IndexedSeqViewLike$Transformed;
  Code:
   Stack=2, Locals=2, Args_size=2
	aload_0
	aload_1
	invokestatic	Method scala/collection/IndexedSeqViewLike$class.newForced:(Lscala/collection/IndexedSeqViewLike;Lscala/Function0;)Lscala/collection/IndexedSeqViewLike$Transformed;
	areturn
  Labels:
  LocalVariableTable: 
   Start  Length  Slot  Name   Signature
   0      6      0    this       Lscala/collection/IndexedSeqViewLike$$anon$6;
   0      6      1    xs       Lscala/Function0;

  Signature: length = 0x2
   00 48 

public scala.collection.IndexedSeqViewLike$Transformed newAppended(scala.collection.Traversable);
  Signature: (Lscala/collection/Traversable;)Lscala/collection/IndexedSeqViewLike$Transformed;
  Code:
   Stack=2, Locals=2, Args_size=2
	aload_0
	aload_1
	invokestatic	Method scala/collection/IndexedSeqViewLike$class.newAppended:(Lscala/collection/IndexedSeqViewLike;Lscala/collection/Traversable;)Lscala/collection/IndexedSeqViewLike$Transformed;
	areturn
  Labels:
  LocalVariableTable: 
   Start  Length  Slot  Name   Signature
   0      6      0    this       Lscala/collection/IndexedSeqViewLike$$anon$6;
   0      6      1    that       Lscala/collection/Traversable;

  Signature: length = 0x2
   00 52 

public scala.collection.IndexedSeqViewLike$Transformed newMapped(scala.Function1);
  Signature: (Lscala/Function1;)Lscala/collection/IndexedSeqViewLike$Transformed;
  Code:
   Stack=2, Locals=2, Args_size=2
	aload_0
	aload_1
	invokestatic	Method scala/collection/IndexedSeqViewLike$class.newMapped:(Lscala/collection/IndexedSeqViewLike;Lscala/Function1;)Lscala/collection/IndexedSeqViewLike$Transformed;
	areturn
  Labels:
  LocalVariableTable: 
   Start  Length  Slot  Name   Signature
   0      6      0    this       Lscala/collection/IndexedSeqViewLike$$anon$6;
   0      6      1    f       Lscala/Function1;

  Signature: length = 0x2
   00 59 

public scala.collection.IndexedSeqViewLike$Transformed newFlatMapped(scala.Function1);
  Signature: (Lscala/Function1;)Lscala/collection/IndexedSeqViewLike$Transformed;
  Code:
   Stack=2, Locals=2, Args_size=2
	aload_0
	aload_1
	invokestatic	Method scala/collection/IndexedSeqViewLike$class.newFlatMapped:(Lscala/collection/IndexedSeqViewLike;Lscala/Function1;)Lscala/collection/IndexedSeqViewLike$Transformed;
	areturn
  Labels:
  LocalVariableTable: 
   Start  Length  Slot  Name   Signature
   0      6      0    this       Lscala/collection/IndexedSeqViewLike$$anon$6;
   0      6      1    f       Lscala/Function1;

  Signature: length = 0x2
   00 59 

public scala.collection.IndexedSeqViewLike$Transformed newFiltered(scala.Function1);
  Signature: (Lscala/Function1;)Lscala/collection/IndexedSeqViewLike$Transformed;
  Code:
   Stack=2, Locals=2, Args_size=2
	aload_0
	aload_1
	invokestatic	Method scala/collection/IndexedSeqViewLike$class.newFiltered:(Lscala/collection/IndexedSeqViewLike;Lscala/Function1;)Lscala/collection/IndexedSeqViewLike$Transformed;
	areturn
  Labels:
  LocalVariableTable: 
   Start  Length  Slot  Name   Signature
   0      6      0    this       Lscala/collection/IndexedSeqViewLike$$anon$6;
   0      6      1    p       Lscala/Function1;

  Signature: length = 0x2
   00 59 

public scala.collection.IndexedSeqViewLike$Transformed newSliced(int, int);
  Signature: (II)Lscala/collection/IndexedSeqViewLike$Transformed;
  Code:
   Stack=3, Locals=3, Args_size=3
	aload_0
	iload_1
	iload_2
	invokestatic	Method scala/collection/IndexedSeqViewLike$class.newSliced:(Lscala/collection/IndexedSeqViewLike;II)Lscala/collection/IndexedSeqViewLike$Transformed;
	areturn
  Labels:
  LocalVariableTable: 
   Start  Length  Slot  Name   Signature
   0      7      0    this       Lscala/collection/IndexedSeqViewLike$$anon$6;
   0      7      1    _from       I
   0      7      2    _until       I

  Signature: length = 0x2
   00 65 

public scala.collection.IndexedSeqViewLike$Transformed newDroppedWhile(scala.Function1);
  Signature: (Lscala/Function1;)Lscala/collection/IndexedSeqViewLike$Transformed;
  Code:
   Stack=2, Locals=2, Args_size=2
	aload_0
	aload_1
	invokestatic	Method scala/collection/IndexedSeqViewLike$class.newDroppedWhile:(Lscala/collection/IndexedSeqViewLike;Lscala/Function1;)Lscala/collection/IndexedSeqViewLike$Transformed;
	areturn
  Labels:
  LocalVariableTable: 
   Start  Length  Slot  Name   Signature
   0      6      0    this       Lscala/collection/IndexedSeqViewLike$$anon$6;
   0      6      1    p       Lscala/Function1;

  Signature: length = 0x2
   00 59 

public scala.collection.IndexedSeqViewLike$Transformed newTakenWhile(scala.Function1);
  Signature: (Lscala/Function1;)Lscala/collection/IndexedSeqViewLike$Transformed;
  Code:
   Stack=2, Locals=2, Args_size=2
	aload_0
	aload_1
	invokestatic	Method scala/collection/IndexedSeqViewLike$class.newTakenWhile:(Lscala/collection/IndexedSeqViewLike;Lscala/Function1;)Lscala/collection/IndexedSeqViewLike$Transformed;
	areturn
  Labels:
  LocalVariableTable: 
   Start  Length  Slot  Name   Signature
   0      6      0    this       Lscala/collection/IndexedSeqViewLike$$anon$6;
   0      6      1    p       Lscala/Function1;

  Signature: length = 0x2
   00 59 

public scala.collection.IndexedSeqViewLike$Transformed newZipped(scala.collection.Iterable);
  Signature: (Lscala/collection/Iterable;)Lscala/collection/IndexedSeqViewLike$Transformed;
  Code:
   Stack=2, Locals=2, Args_size=2
	aload_0
	aload_1
	invokestatic	Method scala/collection/IndexedSeqViewLike$class.newZipped:(Lscala/collection/IndexedSeqViewLike;Lscala/collection/Iterable;)Lscala/collection/IndexedSeqViewLike$Transformed;
	areturn
  Labels:
  LocalVariableTable: 
   Start  Length  Slot  Name   Signature
   0      6      0    this       Lscala/collection/IndexedSeqViewLike$$anon$6;
   0      6      1    that       Lscala/collection/Iterable;

  Signature: length = 0x2
   00 72 

public scala.collection.IndexedSeqViewLike$Transformed newZippedAll(scala.collection.Iterable, java.lang.Object, java.lang.Object);
  Signature: (Lscala/collection/Iterable;Ljava/lang/Object;Ljava/lang/Object;)Lscala/collection/IndexedSeqViewLike$Transformed;
  Code:
   Stack=4, Locals=4, Args_size=4
	aload_0
	aload_1
	aload_2
	aload_3
	invokestatic	Method scala/collection/IndexedSeqViewLike$class.newZippedAll:(Lscala/collection/IndexedSeqViewLike;Lscala/collection/Iterable;Ljava/lang/Object;Ljava/lang/Object;)Lscala/collection/IndexedSeqViewLike$Transformed;
	areturn
  Labels:
  LocalVariableTable: 
   Start  Length  Slot  Name   Signature
   0      8      0    this       Lscala/collection/IndexedSeqViewLike$$anon$6;
   0      8      1    that       Lscala/collection/Iterable;
   0      8      2    _thisElem       Ljava/lang/Object;
   0      8      3    _thatElem       Ljava/lang/Object;

  Signature: length = 0x2
   00 78 

public scala.collection.IndexedSeqViewLike$Transformed newReversed();
  Signature: ()Lscala/collection/IndexedSeqViewLike$Transformed;
  Code:
   Stack=1, Locals=1, Args_size=1
	aload_0
	invokestatic	Method scala/collection/IndexedSeqViewLike$class.newReversed:(Lscala/collection/IndexedSeqViewLike;)Lscala/collection/IndexedSeqViewLike$Transformed;
	areturn
  Labels:
  Signature: length = 0x2
   00 7F 

public scala.collection.IndexedSeqViewLike$Transformed newPatched(int, scala.collection.Seq, int);
  Signature: (ILscala/collection/Seq;I)Lscala/collection/IndexedSeqViewLike$Transformed;
  Code:
   Stack=4, Locals=4, Args_size=4
	aload_0
	iload_1
	aload_2
	iload_3
	invokestatic	Method scala/collection/IndexedSeqViewLike$class.newPatched:(Lscala/collection/IndexedSeqViewLike;ILscala/collection/Seq;I)Lscala/collection/IndexedSeqViewLike$Transformed;
	areturn
  Labels:
  LocalVariableTable: 
   Start  Length  Slot  Name   Signature
   0      8      0    this       Lscala/collection/IndexedSeqViewLike$$anon$6;
   0      8      1    _from       I
   0      8      2    _patch       Lscala/collection/Seq;
   0      8      3    _replaced       I

  Signature: length = 0x2
   00 FFFFFF84 

public scala.collection.IndexedSeqViewLike$Transformed newPrepended(java.lang.Object);
  Signature: (Ljava/lang/Object;)Lscala/collection/IndexedSeqViewLike$Transformed;
  Code:
   Stack=2, Locals=2, Args_size=2
	aload_0
	aload_1
	invokestatic	Method scala/collection/IndexedSeqViewLike$class.newPrepended:(Lscala/collection/IndexedSeqViewLike;Ljava/lang/Object;)Lscala/collection/IndexedSeqViewLike$Transformed;
	areturn
  Labels:
  LocalVariableTable: 
   Start  Length  Slot  Name   Signature
   0      6      0    this       Lscala/collection/IndexedSeqViewLike$$anon$6;
   0      6      1    elem       Ljava/lang/Object;

  Signature: length = 0x2
   00 FFFFFF8C 

public scala.collection.SeqView reverse();
  Signature: ()Lscala/collection/SeqView;
  Code:
   Stack=1, Locals=1, Args_size=1
	aload_0
	invokestatic	Method scala/collection/SeqViewLike$class.reverse:(Lscala/collection/SeqViewLike;)Lscala/collection/SeqView;
	areturn
  Labels:

public java.lang.Object patch(int, scala.collection.Seq, int, scala.collection.generic.CanBuildFrom);
  Signature: (ILscala/collection/Seq;ILscala/collection/generic/CanBuildFrom;)Ljava/lang/Object;
  Code:
   Stack=5, Locals=5, Args_size=5
	aload_0
	iload_1
	aload_2
	iload_3
	aload	4
	invokestatic	Method scala/collection/SeqViewLike$class.patch:(Lscala/collection/SeqViewLike;ILscala/collection/Seq;ILscala/collection/generic/CanBuildFrom;)Ljava/lang/Object;
	areturn
  Labels:
  LocalVariableTable: 
   Start  Length  Slot  Name   Signature
   0      10      0    this       Lscala/collection/IndexedSeqViewLike$$anon$6;
   0      10      1    from       I
   0      10      2    patch       Lscala/collection/Seq;
   0      10      3    replaced       I
   0      10      4    bf       Lscala/collection/generic/CanBuildFrom;


public java.lang.Object padTo(int, java.lang.Object, scala.collection.generic.CanBuildFrom);
  Signature: (ILjava/lang/Object;Lscala/collection/generic/CanBuildFrom;)Ljava/lang/Object;
  Code:
   Stack=4, Locals=4, Args_size=4
	aload_0
	iload_1
	aload_2
	aload_3
	invokestatic	Method scala/collection/SeqViewLike$class.padTo:(Lscala/collection/SeqViewLike;ILjava/lang/Object;Lscala/collection/generic/CanBuildFrom;)Ljava/lang/Object;
	areturn
  Labels:
  LocalVariableTable: 
   Start  Length  Slot  Name   Signature
   0      8      0    this       Lscala/collection/IndexedSeqViewLike$$anon$6;
   0      8      1    len       I
   0      8      2    elem       Ljava/lang/Object;
   0      8      3    bf       Lscala/collection/generic/CanBuildFrom;


public java.lang.Object reverseMap(scala.Function1, scala.collection.generic.CanBuildFrom);
  Signature: (Lscala/Function1;Lscala/collection/generic/CanBuildFrom;)Ljava/lang/Object;
  Code:
   Stack=3, Locals=3, Args_size=3
	aload_0
	aload_1
	aload_2
	invokestatic	Method scala/collection/SeqViewLike$class.reverseMap:(Lscala/collection/SeqViewLike;Lscala/Function1;Lscala/collection/generic/CanBuildFrom;)Ljava/lang/Object;
	areturn
  Labels:
  LocalVariableTable: 
   Start  Length  Slot  Name   Signature
   0      7      0    this       Lscala/collection/IndexedSeqViewLike$$anon$6;
   0      7      1    f       Lscala/Function1;
   0      7      2    bf       Lscala/collection/generic/CanBuildFrom;


public java.lang.Object updated(int, java.lang.Object, scala.collection.generic.CanBuildFrom);
  Signature: (ILjava/lang/Object;Lscala/collection/generic/CanBuildFrom;)Ljava/lang/Object;
  Code:
   Stack=4, Locals=4, Args_size=4
	aload_0
	iload_1
	aload_2
	aload_3
	invokestatic	Method scala/collection/SeqViewLike$class.updated:(Lscala/collection/SeqViewLike;ILjava/lang/Object;Lscala/collection/generic/CanBuildFrom;)Ljava/lang/Object;
	areturn
  Labels:
  LocalVariableTable: 
   Start  Length  Slot  Name   Signature
   0      8      0    this       Lscala/collection/IndexedSeqViewLike$$anon$6;
   0      8      1    index       I
   0      8      2    elem       Ljava/lang/Object;
   0      8      3    bf       Lscala/collection/generic/CanBuildFrom;


public java.lang.Object $plus$colon(java.lang.Object, scala.collection.generic.CanBuildFrom);
  Signature: (Ljava/lang/Object;Lscala/collection/generic/CanBuildFrom;)Ljava/lang/Object;
  Code:
   Stack=3, Locals=3, Args_size=3
	aload_0
	aload_1
	aload_2
	invokestatic	Method scala/collection/SeqViewLike$class.$plus$colon:(Lscala/collection/SeqViewLike;Ljava/lang/Object;Lscala/collection/generic/CanBuildFrom;)Ljava/lang/Object;
	areturn
  Labels:
  LocalVariableTable: 
   Start  Length  Slot  Name   Signature
   0      7      0    this       Lscala/collection/IndexedSeqViewLike$$anon$6;
   0      7      1    elem       Ljava/lang/Object;
   0      7      2    bf       Lscala/collection/generic/CanBuildFrom;


public java.lang.Object $colon$plus(java.lang.Object, scala.collection.generic.CanBuildFrom);
  Signature: (Ljava/lang/Object;Lscala/collection/generic/CanBuildFrom;)Ljava/lang/Object;
  Code:
   Stack=3, Locals=3, Args_size=3
	aload_0
	aload_1
	aload_2
	invokestatic	Method scala/collection/SeqViewLike$class.$colon$plus:(Lscala/collection/SeqViewLike;Ljava/lang/Object;Lscala/collection/generic/CanBuildFrom;)Ljava/lang/Object;
	areturn
  Labels:
  LocalVariableTable: 
   Start  Length  Slot  Name   Signature
   0      7      0    this       Lscala/collection/IndexedSeqViewLike$$anon$6;
   0      7      1    elem       Ljava/lang/Object;
   0      7      2    bf       Lscala/collection/generic/CanBuildFrom;


public java.lang.Object union(scala.collection.Seq, scala.collection.generic.CanBuildFrom);
  Signature: (Lscala/collection/Seq;Lscala/collection/generic/CanBuildFrom;)Ljava/lang/Object;
  Code:
   Stack=3, Locals=3, Args_size=3
	aload_0
	aload_1
	aload_2
	invokestatic	Method scala/collection/SeqViewLike$class.union:(Lscala/collection/SeqViewLike;Lscala/collection/Seq;Lscala/collection/generic/CanBuildFrom;)Ljava/lang/Object;
	areturn
  Labels:
  LocalVariableTable: 
   Start  Length  Slot  Name   Signature
   0      7      0    this       Lscala/collection/IndexedSeqViewLike$$anon$6;
   0      7      1    that       Lscala/collection/Seq;
   0      7      2    bf       Lscala/collection/generic/CanBuildFrom;


public scala.collection.SeqView diff(scala.collection.Seq);
  Signature: (Lscala/collection/Seq;)Lscala/collection/SeqView;
  Code:
   Stack=2, Locals=2, Args_size=2
	aload_0
	aload_1
	invokestatic	Method scala/collection/SeqViewLike$class.diff:(Lscala/collection/SeqViewLike;Lscala/collection/Seq;)Lscala/collection/SeqView;
	areturn
  Labels:
  LocalVariableTable: 
   Start  Length  Slot  Name   Signature
   0      6      0    this       Lscala/collection/IndexedSeqViewLike$$anon$6;
   0      6      1    that       Lscala/collection/Seq;


public scala.collection.SeqView intersect(scala.collection.Seq);
  Signature: (Lscala/collection/Seq;)Lscala/collection/SeqView;
  Code:
   Stack=2, Locals=2, Args_size=2
	aload_0
	aload_1
	invokestatic	Method scala/collection/SeqViewLike$class.intersect:(Lscala/collection/SeqViewLike;Lscala/collection/Seq;)Lscala/collection/SeqView;
	areturn
  Labels:
  LocalVariableTable: 
   Start  Length  Slot  Name   Signature
   0      6      0    this       Lscala/collection/IndexedSeqViewLike$$anon$6;
   0      6      1    that       Lscala/collection/Seq;


public scala.collection.SeqView sorted(scala.math.Ordering);
  Signature: (Lscala/math/Ordering;)Lscala/collection/SeqView;
  Code:
   Stack=2, Locals=2, Args_size=2
	aload_0
	aload_1
	invokestatic	Method scala/collection/SeqViewLike$class.sorted:(Lscala/collection/SeqViewLike;Lscala/math/Ordering;)Lscala/collection/SeqView;
	areturn
  Labels:
  LocalVariableTable: 
   Start  Length  Slot  Name   Signature
   0      6      0    this       Lscala/collection/IndexedSeqViewLike$$anon$6;
   0      6      1    ord       Lscala/math/Ordering;


public java.lang.Object zip(scala.collection.Iterable, scala.collection.generic.CanBuildFrom);
  Signature: (Lscala/collection/Iterable;Lscala/collection/generic/CanBuildFrom;)Ljava/lang/Object;
  Code:
   Stack=3, Locals=3, Args_size=3
	aload_0
	aload_1
	aload_2
	invokestatic	Method scala/collection/IterableViewLike$class.zip:(Lscala/collection/IterableViewLike;Lscala/collection/Iterable;Lscala/collection/generic/CanBuildFrom;)Ljava/lang/Object;
	areturn
  Labels:
  LocalVariableTable: 
   Start  Length  Slot  Name   Signature
   0      7      0    this       Lscala/collection/IndexedSeqViewLike$$anon$6;
   0      7      1    that       Lscala/collection/Iterable;
   0      7      2    bf       Lscala/collection/generic/CanBuildFrom;


public java.lang.Object zipWithIndex(scala.collection.generic.CanBuildFrom);
  Signature: (Lscala/collection/generic/CanBuildFrom;)Ljava/lang/Object;
  Code:
   Stack=2, Locals=2, Args_size=2
	aload_0
	aload_1
	invokestatic	Method scala/collection/IterableViewLike$class.zipWithIndex:(Lscala/collection/IterableViewLike;Lscala/collection/generic/CanBuildFrom;)Ljava/lang/Object;
	areturn
  Labels:
  LocalVariableTable: 
   Start  Length  Slot  Name   Signature
   0      6      0    this       Lscala/collection/IndexedSeqViewLike$$anon$6;
   0      6      1    bf       Lscala/collection/generic/CanBuildFrom;


public java.lang.Object zipAll(scala.collection.Iterable, java.lang.Object, java.lang.Object, scala.collection.generic.CanBuildFrom);
  Signature: (Lscala/collection/Iterable;Ljava/lang/Object;Ljava/lang/Object;Lscala/collection/generic/CanBuildFrom;)Ljava/lang/Object;
  Code:
   Stack=5, Locals=5, Args_size=5
	aload_0
	aload_1
	aload_2
	aload_3
	aload	4
	invokestatic	Method scala/collection/IterableViewLike$class.zipAll:(Lscala/collection/IterableViewLike;Lscala/collection/Iterable;Ljava/lang/Object;Ljava/lang/Object;Lscala/collection/generic/CanBuildFrom;)Ljava/lang/Object;
	areturn
  Labels:
  LocalVariableTable: 
   Start  Length  Slot  Name   Signature
   0      10      0    this       Lscala/collection/IndexedSeqViewLike$$anon$6;
   0      10      1    that       Lscala/collection/Iterable;
   0      10      2    thisElem       Ljava/lang/Object;
   0      10      3    thatElem       Ljava/lang/Object;
   0      10      4    bf       Lscala/collection/generic/CanBuildFrom;


public scala.collection.Iterator grouped(int);
  Signature: (I)Lscala/collection/Iterator;
  Code:
   Stack=2, Locals=2, Args_size=2
	aload_0
	iload_1
	invokestatic	Method scala/collection/IterableViewLike$class.grouped:(Lscala/collection/IterableViewLike;I)Lscala/collection/Iterator;
	areturn
  Labels:
  LocalVariableTable: 
   Start  Length  Slot  Name   Signature
   0      6      0    this       Lscala/collection/IndexedSeqViewLike$$anon$6;
   0      6      1    size       I


public scala.collection.Iterator sliding(int, int);
  Signature: (II)Lscala/collection/Iterator;
  Code:
   Stack=3, Locals=3, Args_size=3
	aload_0
	iload_1
	iload_2
	invokestatic	Method scala/collection/IterableViewLike$class.sliding:(Lscala/collection/IterableViewLike;II)Lscala/collection/Iterator;
	areturn
  Labels:
  LocalVariableTable: 
   Start  Length  Slot  Name   Signature
   0      7      0    this       Lscala/collection/IndexedSeqViewLike$$anon$6;
   0      7      1    size       I
   0      7      2    step       I


public scala.collection.mutable.Builder newBuilder();
  Signature: ()Lscala/collection/mutable/Builder;
  Code:
   Stack=1, Locals=1, Args_size=1
	aload_0
	invokestatic	Method scala/collection/TraversableViewLike$class.newBuilder:(Lscala/collection/TraversableViewLike;)Lscala/collection/mutable/Builder;
	areturn
  Labels:

public java.lang.Object force(scala.collection.generic.CanBuildFrom);
  Signature: (Lscala/collection/generic/CanBuildFrom;)Ljava/lang/Object;
  Code:
   Stack=2, Locals=2, Args_size=2
	aload_0
	aload_1
	invokestatic	Method scala/collection/TraversableViewLike$class.force:(Lscala/collection/TraversableViewLike;Lscala/collection/generic/CanBuildFrom;)Ljava/lang/Object;
	areturn
  Labels:
  LocalVariableTable: 
   Start  Length  Slot  Name   Signature
   0      6      0    this       Lscala/collection/IndexedSeqViewLike$$anon$6;
   0      6      1    bf       Lscala/collection/generic/CanBuildFrom;


public java.lang.Object $plus$plus(scala.collection.Traversable, scala.collection.generic.CanBuildFrom);
  Signature: (Lscala/collection/Traversable;Lscala/collection/generic/CanBuildFrom;)Ljava/lang/Object;
  Code:
   Stack=3, Locals=3, Args_size=3
	aload_0
	aload_1
	aload_2
	invokestatic	Method scala/collection/TraversableViewLike$class.$plus$plus:(Lscala/collection/TraversableViewLike;Lscala/collection/Traversable;Lscala/collection/generic/CanBuildFrom;)Ljava/lang/Object;
	areturn
  Labels:
  LocalVariableTable: 
   Start  Length  Slot  Name   Signature
   0      7      0    this       Lscala/collection/IndexedSeqViewLike$$anon$6;
   0      7      1    that       Lscala/collection/Traversable;
   0      7      2    bf       Lscala/collection/generic/CanBuildFrom;


public java.lang.Object $plus$plus(scala.collection.Iterator, scala.collection.generic.CanBuildFrom);
  Signature: (Lscala/collection/Iterator;Lscala/collection/generic/CanBuildFrom;)Ljava/lang/Object;
  Code:
   Stack=3, Locals=3, Args_size=3
	aload_0
	aload_1
	aload_2
	invokestatic	Method scala/collection/TraversableViewLike$class.$plus$plus:(Lscala/collection/TraversableViewLike;Lscala/collection/Iterator;Lscala/collection/generic/CanBuildFrom;)Ljava/lang/Object;
	areturn
  Labels:
  LocalVariableTable: 
   Start  Length  Slot  Name   Signature
   0      7      0    this       Lscala/collection/IndexedSeqViewLike$$anon$6;
   0      7      1    that       Lscala/collection/Iterator;
   0      7      2    bf       Lscala/collection/generic/CanBuildFrom;


public java.lang.Object map(scala.Function1, scala.collection.generic.CanBuildFrom);
  Signature: (Lscala/Function1;Lscala/collection/generic/CanBuildFrom;)Ljava/lang/Object;
  Code:
   Stack=3, Locals=3, Args_size=3
	aload_0
	aload_1
	aload_2
	invokestatic	Method scala/collection/TraversableViewLike$class.map:(Lscala/collection/TraversableViewLike;Lscala/Function1;Lscala/collection/generic/CanBuildFrom;)Ljava/lang/Object;
	areturn
  Labels:
  LocalVariableTable: 
   Start  Length  Slot  Name   Signature
   0      7      0    this       Lscala/collection/IndexedSeqViewLike$$anon$6;
   0      7      1    f       Lscala/Function1;
   0      7      2    bf       Lscala/collection/generic/CanBuildFrom;


public java.lang.Object partialMap(scala.PartialFunction, scala.collection.generic.CanBuildFrom);
  Signature: (Lscala/PartialFunction;Lscala/collection/generic/CanBuildFrom;)Ljava/lang/Object;
  Code:
   Stack=3, Locals=3, Args_size=3
	aload_0
	aload_1
	aload_2
	invokestatic	Method scala/collection/TraversableViewLike$class.partialMap:(Lscala/collection/TraversableViewLike;Lscala/PartialFunction;Lscala/collection/generic/CanBuildFrom;)Ljava/lang/Object;
	areturn
  Labels:
  LocalVariableTable: 
   Start  Length  Slot  Name   Signature
   0      7      0    this       Lscala/collection/IndexedSeqViewLike$$anon$6;
   0      7      1    pf       Lscala/PartialFunction;
   0      7      2    bf       Lscala/collection/generic/CanBuildFrom;


public java.lang.Object flatMap(scala.Function1, scala.collection.generic.CanBuildFrom);
  Signature: (Lscala/Function1;Lscala/collection/generic/CanBuildFrom;)Ljava/lang/Object;
  Code:
   Stack=3, Locals=3, Args_size=3
	aload_0
	aload_1
	aload_2
	invokestatic	Method scala/collection/TraversableViewLike$class.flatMap:(Lscala/collection/TraversableViewLike;Lscala/Function1;Lscala/collection/generic/CanBuildFrom;)Ljava/lang/Object;
	areturn
  Labels:
  LocalVariableTable: 
   Start  Length  Slot  Name   Signature
   0      7      0    this       Lscala/collection/IndexedSeqViewLike$$anon$6;
   0      7      1    f       Lscala/Function1;
   0      7      2    bf       Lscala/collection/generic/CanBuildFrom;


public scala.collection.Seq thisSeq();
  Signature: ()Lscala/collection/Seq;
  Code:
   Stack=1, Locals=1, Args_size=1
	aload_0
	invokestatic	Method scala/collection/TraversableViewLike$class.thisSeq:(Lscala/collection/TraversableViewLike;)Lscala/collection/Seq;
	areturn
  Labels:

public scala.collection.TraversableView filter(scala.Function1);
  Signature: (Lscala/Function1;)Lscala/collection/TraversableView;
  Code:
   Stack=2, Locals=2, Args_size=2
	aload_0
	aload_1
	invokestatic	Method scala/collection/TraversableViewLike$class.filter:(Lscala/collection/TraversableViewLike;Lscala/Function1;)Lscala/collection/TraversableView;
	areturn
  Labels:
  LocalVariableTable: 
   Start  Length  Slot  Name   Signature
   0      6      0    this       Lscala/collection/IndexedSeqViewLike$$anon$6;
   0      6      1    p       Lscala/Function1;


public scala.Tuple2 partition(scala.Function1);
  Signature: (Lscala/Function1;)Lscala/Tuple2;
  Code:
   Stack=2, Locals=2, Args_size=2
	aload_0
	aload_1
	invokestatic	Method scala/collection/TraversableViewLike$class.partition:(Lscala/collection/TraversableViewLike;Lscala/Function1;)Lscala/Tuple2;
	areturn
  Labels:
  LocalVariableTable: 
   Start  Length  Slot  Name   Signature
   0      6      0    this       Lscala/collection/IndexedSeqViewLike$$anon$6;
   0      6      1    p       Lscala/Function1;


public scala.collection.TraversableView init();
  Signature: ()Lscala/collection/TraversableView;
  Code:
   Stack=1, Locals=1, Args_size=1
	aload_0
	invokestatic	Method scala/collection/TraversableViewLike$class.init:(Lscala/collection/TraversableViewLike;)Lscala/collection/TraversableView;
	areturn
  Labels:

public scala.collection.TraversableView drop(int);
  Signature: (I)Lscala/collection/TraversableView;
  Code:
   Stack=2, Locals=2, Args_size=2
	aload_0
	iload_1
	invokestatic	Method scala/collection/TraversableViewLike$class.drop:(Lscala/collection/TraversableViewLike;I)Lscala/collection/TraversableView;
	areturn
  Labels:
  LocalVariableTable: 
   Start  Length  Slot  Name   Signature
   0      6      0    this       Lscala/collection/IndexedSeqViewLike$$anon$6;
   0      6      1    n       I


public scala.collection.TraversableView take(int);
  Signature: (I)Lscala/collection/TraversableView;
  Code:
   Stack=2, Locals=2, Args_size=2
	aload_0
	iload_1
	invokestatic	Method scala/collection/TraversableViewLike$class.take:(Lscala/collection/TraversableViewLike;I)Lscala/collection/TraversableView;
	areturn
  Labels:
  LocalVariableTable: 
   Start  Length  Slot  Name   Signature
   0      6      0    this       Lscala/collection/IndexedSeqViewLike$$anon$6;
   0      6      1    n       I


public scala.collection.TraversableView dropWhile(scala.Function1);
  Signature: (Lscala/Function1;)Lscala/collection/TraversableView;
  Code:
   Stack=2, Locals=2, Args_size=2
	aload_0
	aload_1
	invokestatic	Method scala/collection/TraversableViewLike$class.dropWhile:(Lscala/collection/TraversableViewLike;Lscala/Function1;)Lscala/collection/TraversableView;
	areturn
  Labels:
  LocalVariableTable: 
   Start  Length  Slot  Name   Signature
   0      6      0    this       Lscala/collection/IndexedSeqViewLike$$anon$6;
   0      6      1    p       Lscala/Function1;


public scala.collection.TraversableView takeWhile(scala.Function1);
  Signature: (Lscala/Function1;)Lscala/collection/TraversableView;
  Code:
   Stack=2, Locals=2, Args_size=2
	aload_0
	aload_1
	invokestatic	Method scala/collection/TraversableViewLike$class.takeWhile:(Lscala/collection/TraversableViewLike;Lscala/Function1;)Lscala/collection/TraversableView;
	areturn
  Labels:
  LocalVariableTable: 
   Start  Length  Slot  Name   Signature
   0      6      0    this       Lscala/collection/IndexedSeqViewLike$$anon$6;
   0      6      1    p       Lscala/Function1;


public scala.Tuple2 span(scala.Function1);
  Signature: (Lscala/Function1;)Lscala/Tuple2;
  Code:
   Stack=2, Locals=2, Args_size=2
	aload_0
	aload_1
	invokestatic	Method scala/collection/TraversableViewLike$class.span:(Lscala/collection/TraversableViewLike;Lscala/Function1;)Lscala/Tuple2;
	areturn
  Labels:
  LocalVariableTable: 
   Start  Length  Slot  Name   Signature
   0      6      0    this       Lscala/collection/IndexedSeqViewLike$$anon$6;
   0      6      1    p       Lscala/Function1;


public scala.Tuple2 splitAt(int);
  Signature: (I)Lscala/Tuple2;
  Code:
   Stack=2, Locals=2, Args_size=2
	aload_0
	iload_1
	invokestatic	Method scala/collection/TraversableViewLike$class.splitAt:(Lscala/collection/TraversableViewLike;I)Lscala/Tuple2;
	areturn
  Labels:
  LocalVariableTable: 
   Start  Length  Slot  Name   Signature
   0      6      0    this       Lscala/collection/IndexedSeqViewLike$$anon$6;
   0      6      1    n       I


public java.lang.Object scanLeft(java.lang.Object, scala.Function2, scala.collection.generic.CanBuildFrom);
  Signature: (Ljava/lang/Object;Lscala/Function2;Lscala/collection/generic/CanBuildFrom;)Ljava/lang/Object;
  Code:
   Stack=4, Locals=4, Args_size=4
	aload_0
	aload_1
	aload_2
	aload_3
	invokestatic	Method scala/collection/TraversableViewLike$class.scanLeft:(Lscala/collection/TraversableViewLike;Ljava/lang/Object;Lscala/Function2;Lscala/collection/generic/CanBuildFrom;)Ljava/lang/Object;
	areturn
  Labels:
  LocalVariableTable: 
   Start  Length  Slot  Name   Signature
   0      8      0    this       Lscala/collection/IndexedSeqViewLike$$anon$6;
   0      8      1    z       Ljava/lang/Object;
   0      8      2    op       Lscala/Function2;
   0      8      3    bf       Lscala/collection/generic/CanBuildFrom;


public java.lang.Object scanRight(java.lang.Object, scala.Function2, scala.collection.generic.CanBuildFrom);
  Signature: (Ljava/lang/Object;Lscala/Function2;Lscala/collection/generic/CanBuildFrom;)Ljava/lang/Object;
  Code:
   Stack=4, Locals=4, Args_size=4
	aload_0
	aload_1
	aload_2
	aload_3
	invokestatic	Method scala/collection/TraversableViewLike$class.scanRight:(Lscala/collection/TraversableViewLike;Ljava/lang/Object;Lscala/Function2;Lscala/collection/generic/CanBuildFrom;)Ljava/lang/Object;
	areturn
  Labels:
  LocalVariableTable: 
   Start  Length  Slot  Name   Signature
   0      8      0    this       Lscala/collection/IndexedSeqViewLike$$anon$6;
   0      8      1    z       Ljava/lang/Object;
   0      8      2    op       Lscala/Function2;
   0      8      3    bf       Lscala/collection/generic/CanBuildFrom;


public scala.collection.Map groupBy(scala.Function1);
  Signature: (Lscala/Function1;)Lscala/collection/Map;
  Code:
   Stack=2, Locals=2, Args_size=2
	aload_0
	aload_1
	invokestatic	Method scala/collection/TraversableViewLike$class.groupBy:(Lscala/collection/TraversableViewLike;Lscala/Function1;)Lscala/collection/Map;
	areturn
  Labels:
  LocalVariableTable: 
   Start  Length  Slot  Name   Signature
   0      6      0    this       Lscala/collection/IndexedSeqViewLike$$anon$6;
   0      6      1    f       Lscala/Function1;


public scala.collection.generic.GenericCompanion companion();
  Signature: ()Lscala/collection/generic/GenericCompanion;
  Code:
   Stack=1, Locals=1, Args_size=1
	aload_0
	invokestatic	Method scala/collection/IndexedSeq$class.companion:(Lscala/collection/IndexedSeq;)Lscala/collection/generic/GenericCompanion;
	areturn
  Labels:

public final java.lang.Object scala$collection$IndexedSeqLike$$super$reduceLeft(scala.Function2);
  Signature: (Lscala/Function2;)Ljava/lang/Object;
  Code:
   Stack=2, Locals=2, Args_size=2
	aload_0
	aload_1
	invokestatic	Method scala/collection/TraversableLike$class.reduceLeft:(Lscala/collection/TraversableLike;Lscala/Function2;)Ljava/lang/Object;
	areturn
  Labels:
  LocalVariableTable: 
   Start  Length  Slot  Name   Signature
   0      6      0    this       Lscala/collection/IndexedSeqViewLike$$anon$6;
   0      6      1    op       Lscala/Function2;


public final java.lang.Object scala$collection$IndexedSeqLike$$super$reduceRight(scala.Function2);
  Signature: (Lscala/Function2;)Ljava/lang/Object;
  Code:
   Stack=2, Locals=2, Args_size=2
	aload_0
	aload_1
	invokestatic	Method scala/collection/IterableLike$class.reduceRight:(Lscala/collection/IterableLike;Lscala/Function2;)Ljava/lang/Object;
	areturn
  Labels:
  LocalVariableTable: 
   Start  Length  Slot  Name   Signature
   0      6      0    this       Lscala/collection/IndexedSeqViewLike$$anon$6;
   0      6      1    op       Lscala/Function2;


public final java.lang.Object scala$collection$IndexedSeqLike$$super$zip(scala.collection.Iterable, scala.collection.generic.CanBuildFrom);
  Signature: (Lscala/collection/Iterable;Lscala/collection/generic/CanBuildFrom;)Ljava/lang/Object;
  Code:
   Stack=3, Locals=3, Args_size=3
	aload_0
	aload_1
	aload_2
	invokestatic	Method scala/collection/IterableLike$class.zip:(Lscala/collection/IterableLike;Lscala/collection/Iterable;Lscala/collection/generic/CanBuildFrom;)Ljava/lang/Object;
	areturn
  Labels:
  LocalVariableTable: 
   Start  Length  Slot  Name   Signature
   0      7      0    this       Lscala/collection/IndexedSeqViewLike$$anon$6;
   0      7      1    that       Lscala/collection/Iterable;
   0      7      2    bf       Lscala/collection/generic/CanBuildFrom;


public final java.lang.Object scala$collection$IndexedSeqLike$$super$head();
  Signature: ()Ljava/lang/Object;
  Code:
   Stack=1, Locals=1, Args_size=1
	aload_0
	invokestatic	Method scala/collection/IterableLike$class.head:(Lscala/collection/IterableLike;)Ljava/lang/Object;
	areturn
  Labels:

public final java.lang.Object scala$collection$IndexedSeqLike$$super$tail();
  Signature: ()Ljava/lang/Object;
  Code:
   Stack=1, Locals=1, Args_size=1
	aload_0
	invokestatic	Method scala/collection/TraversableLike$class.tail:(Lscala/collection/TraversableLike;)Ljava/lang/Object;
	areturn
  Labels:

public final java.lang.Object scala$collection$IndexedSeqLike$$super$last();
  Signature: ()Ljava/lang/Object;
  Code:
   Stack=1, Locals=1, Args_size=1
	aload_0
	invokestatic	Method scala/collection/TraversableLike$class.last:(Lscala/collection/TraversableLike;)Ljava/lang/Object;
	areturn
  Labels:

public final java.lang.Object scala$collection$IndexedSeqLike$$super$init();
  Signature: ()Ljava/lang/Object;
  Code:
   Stack=1, Locals=1, Args_size=1
	aload_0
	invokestatic	Method scala/collection/TraversableLike$class.init:(Lscala/collection/TraversableLike;)Ljava/lang/Object;
	areturn
  Labels:

public final boolean scala$collection$IndexedSeqLike$$super$sameElements(scala.collection.Iterable);
  Signature: (Lscala/collection/Iterable;)Z
  Code:
   Stack=2, Locals=2, Args_size=2
	aload_0
	aload_1
	invokestatic	Method scala/collection/IterableLike$class.sameElements:(Lscala/collection/IterableLike;Lscala/collection/Iterable;)Z
	ireturn
  Labels:
  LocalVariableTable: 
   Start  Length  Slot  Name   Signature
   0      6      0    this       Lscala/collection/IndexedSeqViewLike$$anon$6;
   0      6      1    that       Lscala/collection/Iterable;


public final boolean scala$collection$IndexedSeqLike$$super$endsWith(scala.collection.Seq);
  Signature: (Lscala/collection/Seq;)Z
  Code:
   Stack=2, Locals=2, Args_size=2
	aload_0
	aload_1
	invokestatic	Method scala/collection/SeqLike$class.endsWith:(Lscala/collection/SeqLike;Lscala/collection/Seq;)Z
	ireturn
  Labels:
  LocalVariableTable: 
   Start  Length  Slot  Name   Signature
   0      6      0    this       Lscala/collection/IndexedSeqViewLike$$anon$6;
   0      6      1    that       Lscala/collection/Seq;


public scala.collection.IndexedSeq thisCollection();
  Signature: ()Lscala/collection/IndexedSeq;
  Code:
   Stack=1, Locals=1, Args_size=1
	aload_0
	invokestatic	Method scala/collection/IndexedSeqLike$class.thisCollection:(Lscala/collection/IndexedSeqLike;)Lscala/collection/IndexedSeq;
	areturn
  Labels:

public scala.collection.IndexedSeq toCollection(java.lang.Object);
  Signature: (Ljava/lang/Object;)Lscala/collection/IndexedSeq;
  Code:
   Stack=2, Locals=2, Args_size=2
	aload_0
	aload_1
	invokestatic	Method scala/collection/IndexedSeqLike$class.toCollection:(Lscala/collection/IndexedSeqLike;Ljava/lang/Object;)Lscala/collection/IndexedSeq;
	areturn
  Labels:
  LocalVariableTable: 
   Start  Length  Slot  Name   Signature
   0      6      0    this       Lscala/collection/IndexedSeqViewLike$$anon$6;
   0      6      1    repr       Ljava/lang/Object;


public boolean isEmpty();
  Signature: ()Z
  Code:
   Stack=1, Locals=1, Args_size=1
	aload_0
	invokestatic	Method scala/collection/IndexedSeqLike$class.isEmpty:(Lscala/collection/IndexedSeqLike;)Z
	ireturn
  Labels:

public boolean forall(scala.Function1);
  Signature: (Lscala/Function1;)Z
  Code:
   Stack=2, Locals=2, Args_size=2
	aload_0
	aload_1
	invokestatic	Method scala/collection/IndexedSeqLike$class.forall:(Lscala/collection/IndexedSeqLike;Lscala/Function1;)Z
	ireturn
  Labels:
  LocalVariableTable: 
   Start  Length  Slot  Name   Signature
   0      6      0    this       Lscala/collection/IndexedSeqViewLike$$anon$6;
   0      6      1    p       Lscala/Function1;


public boolean exists(scala.Function1);
  Signature: (Lscala/Function1;)Z
  Code:
   Stack=2, Locals=2, Args_size=2
	aload_0
	aload_1
	invokestatic	Method scala/collection/IndexedSeqLike$class.exists:(Lscala/collection/IndexedSeqLike;Lscala/Function1;)Z
	ireturn
  Labels:
  LocalVariableTable: 
   Start  Length  Slot  Name   Signature
   0      6      0    this       Lscala/collection/IndexedSeqViewLike$$anon$6;
   0      6      1    p       Lscala/Function1;


public scala.Option find(scala.Function1);
  Signature: (Lscala/Function1;)Lscala/Option;
  Code:
   Stack=2, Locals=2, Args_size=2
	aload_0
	aload_1
	invokestatic	Method scala/collection/IndexedSeqLike$class.find:(Lscala/collection/IndexedSeqLike;Lscala/Function1;)Lscala/Option;
	areturn
  Labels:
  LocalVariableTable: 
   Start  Length  Slot  Name   Signature
   0      6      0    this       Lscala/collection/IndexedSeqViewLike$$anon$6;
   0      6      1    p       Lscala/Function1;


public java.lang.Object foldLeft(java.lang.Object, scala.Function2);
  Signature: (Ljava/lang/Object;Lscala/Function2;)Ljava/lang/Object;
  Code:
   Stack=3, Locals=3, Args_size=3
	aload_0
	aload_1
	aload_2
	invokestatic	Method scala/collection/IndexedSeqLike$class.foldLeft:(Lscala/collection/IndexedSeqLike;Ljava/lang/Object;Lscala/Function2;)Ljava/lang/Object;
	areturn
  Labels:
  LocalVariableTable: 
   Start  Length  Slot  Name   Signature
   0      7      0    this       Lscala/collection/IndexedSeqViewLike$$anon$6;
   0      7      1    z       Ljava/lang/Object;
   0      7      2    op       Lscala/Function2;


public java.lang.Object foldRight(java.lang.Object, scala.Function2);
  Signature: (Ljava/lang/Object;Lscala/Function2;)Ljava/lang/Object;
  Code:
   Stack=3, Locals=3, Args_size=3
	aload_0
	aload_1
	aload_2
	invokestatic	Method scala/collection/IndexedSeqLike$class.foldRight:(Lscala/collection/IndexedSeqLike;Ljava/lang/Object;Lscala/Function2;)Ljava/lang/Object;
	areturn
  Labels:
  LocalVariableTable: 
   Start  Length  Slot  Name   Signature
   0      7      0    this       Lscala/collection/IndexedSeqViewLike$$anon$6;
   0      7      1    z       Ljava/lang/Object;
   0      7      2    op       Lscala/Function2;


public java.lang.Object reduceLeft(scala.Function2);
  Signature: (Lscala/Function2;)Ljava/lang/Object;
  Code:
   Stack=2, Locals=2, Args_size=2
	aload_0
	aload_1
	invokestatic	Method scala/collection/IndexedSeqLike$class.reduceLeft:(Lscala/collection/IndexedSeqLike;Lscala/Function2;)Ljava/lang/Object;
	areturn
  Labels:
  LocalVariableTable: 
   Start  Length  Slot  Name   Signature
   0      6      0    this       Lscala/collection/IndexedSeqViewLike$$anon$6;
   0      6      1    op       Lscala/Function2;


public java.lang.Object reduceRight(scala.Function2);
  Signature: (Lscala/Function2;)Ljava/lang/Object;
  Code:
   Stack=2, Locals=2, Args_size=2
	aload_0
	aload_1
	invokestatic	Method scala/collection/IndexedSeqLike$class.reduceRight:(Lscala/collection/IndexedSeqLike;Lscala/Function2;)Ljava/lang/Object;
	areturn
  Labels:
  LocalVariableTable: 
   Start  Length  Slot  Name   Signature
   0      6      0    this       Lscala/collection/IndexedSeqViewLike$$anon$6;
   0      6      1    op       Lscala/Function2;


public java.lang.Object head();
  Signature: ()Ljava/lang/Object;
  Code:
   Stack=1, Locals=1, Args_size=1
	aload_0
	invokestatic	Method scala/collection/IndexedSeqLike$class.head:(Lscala/collection/IndexedSeqLike;)Ljava/lang/Object;
	areturn
  Labels:

public java.lang.Object tail();
  Signature: ()Ljava/lang/Object;
  Code:
   Stack=1, Locals=1, Args_size=1
	aload_0
	invokestatic	Method scala/collection/IndexedSeqLike$class.tail:(Lscala/collection/IndexedSeqLike;)Ljava/lang/Object;
	areturn
  Labels:

public java.lang.Object last();
  Signature: ()Ljava/lang/Object;
  Code:
   Stack=1, Locals=1, Args_size=1
	aload_0
	invokestatic	Method scala/collection/IndexedSeqLike$class.last:(Lscala/collection/IndexedSeqLike;)Ljava/lang/Object;
	areturn
  Labels:

public java.lang.Object takeRight(int);
  Signature: (I)Ljava/lang/Object;
  Code:
   Stack=2, Locals=2, Args_size=2
	aload_0
	iload_1
	invokestatic	Method scala/collection/IndexedSeqLike$class.takeRight:(Lscala/collection/IndexedSeqLike;I)Ljava/lang/Object;
	areturn
  Labels:
  LocalVariableTable: 
   Start  Length  Slot  Name   Signature
   0      6      0    this       Lscala/collection/IndexedSeqViewLike$$anon$6;
   0      6      1    n       I


public java.lang.Object dropRight(int);
  Signature: (I)Ljava/lang/Object;
  Code:
   Stack=2, Locals=2, Args_size=2
	aload_0
	iload_1
	invokestatic	Method scala/collection/IndexedSeqLike$class.dropRight:(Lscala/collection/IndexedSeqLike;I)Ljava/lang/Object;
	areturn
  Labels:
  LocalVariableTable: 
   Start  Length  Slot  Name   Signature
   0      6      0    this       Lscala/collection/IndexedSeqViewLike$$anon$6;
   0      6      1    n       I


public boolean sameElements(scala.collection.Iterable);
  Signature: (Lscala/collection/Iterable;)Z
  Code:
   Stack=2, Locals=2, Args_size=2
	aload_0
	aload_1
	invokestatic	Method scala/collection/IndexedSeqLike$class.sameElements:(Lscala/collection/IndexedSeqLike;Lscala/collection/Iterable;)Z
	ireturn
  Labels:
  LocalVariableTable: 
   Start  Length  Slot  Name   Signature
   0      6      0    this       Lscala/collection/IndexedSeqViewLike$$anon$6;
   0      6      1    that       Lscala/collection/Iterable;


public void copyToArray(java.lang.Object, int, int);
  Signature: (Ljava/lang/Object;II)V
  Code:
   Stack=4, Locals=4, Args_size=4
	aload_0
	aload_1
	iload_2
	iload_3
	invokestatic	Method scala/collection/IndexedSeqLike$class.copyToArray:(Lscala/collection/IndexedSeqLike;Ljava/lang/Object;II)V
	return
  Labels:
  LocalVariableTable: 
   Start  Length  Slot  Name   Signature
   0      8      0    this       Lscala/collection/IndexedSeqViewLike$$anon$6;
   0      8      1    xs       Ljava/lang/Object;
   0      8      2    start       I
   0      8      3    len       I


public int lengthCompare(int);
  Signature: (I)I
  Code:
   Stack=2, Locals=2, Args_size=2
	aload_0
	iload_1
	invokestatic	Method scala/collection/IndexedSeqLike$class.lengthCompare:(Lscala/collection/IndexedSeqLike;I)I
	ireturn
  Labels:
  LocalVariableTable: 
   Start  Length  Slot  Name   Signature
   0      6      0    this       Lscala/collection/IndexedSeqViewLike$$anon$6;
   0      6      1    len       I


public int segmentLength(scala.Function1, int);
  Signature: (Lscala/Function1;I)I
  Code:
   Stack=3, Locals=3, Args_size=3
	aload_0
	aload_1
	iload_2
	invokestatic	Method scala/collection/IndexedSeqLike$class.segmentLength:(Lscala/collection/IndexedSeqLike;Lscala/Function1;I)I
	ireturn
  Labels:
  LocalVariableTable: 
   Start  Length  Slot  Name   Signature
   0      7      0    this       Lscala/collection/IndexedSeqViewLike$$anon$6;
   0      7      1    p       Lscala/Function1;
   0      7      2    from       I


public int indexWhere(scala.Function1, int);
  Signature: (Lscala/Function1;I)I
  Code:
   Stack=3, Locals=3, Args_size=3
	aload_0
	aload_1
	iload_2
	invokestatic	Method scala/collection/IndexedSeqLike$class.indexWhere:(Lscala/collection/IndexedSeqLike;Lscala/Function1;I)I
	ireturn
  Labels:
  LocalVariableTable: 
   Start  Length  Slot  Name   Signature
   0      7      0    this       Lscala/collection/IndexedSeqViewLike$$anon$6;
   0      7      1    p       Lscala/Function1;
   0      7      2    from       I


public int lastIndexWhere(scala.Function1, int);
  Signature: (Lscala/Function1;I)I
  Code:
   Stack=3, Locals=3, Args_size=3
	aload_0
	aload_1
	iload_2
	invokestatic	Method scala/collection/IndexedSeqLike$class.lastIndexWhere:(Lscala/collection/IndexedSeqLike;Lscala/Function1;I)I
	ireturn
  Labels:
  LocalVariableTable: 
   Start  Length  Slot  Name   Signature
   0      7      0    this       Lscala/collection/IndexedSeqViewLike$$anon$6;
   0      7      1    p       Lscala/Function1;
   0      7      2    end       I


public scala.collection.Iterator reverseIterator();
  Signature: ()Lscala/collection/Iterator;
  Code:
   Stack=1, Locals=1, Args_size=1
	aload_0
	invokestatic	Method scala/collection/IndexedSeqLike$class.reverseIterator:(Lscala/collection/IndexedSeqLike;)Lscala/collection/Iterator;
	areturn
  Labels:

public boolean startsWith(scala.collection.Seq, int);
  Signature: (Lscala/collection/Seq;I)Z
  Code:
   Stack=3, Locals=3, Args_size=3
	aload_0
	aload_1
	iload_2
	invokestatic	Method scala/collection/IndexedSeqLike$class.startsWith:(Lscala/collection/IndexedSeqLike;Lscala/collection/Seq;I)Z
	ireturn
  Labels:
  LocalVariableTable: 
   Start  Length  Slot  Name   Signature
   0      7      0    this       Lscala/collection/IndexedSeqViewLike$$anon$6;
   0      7      1    that       Lscala/collection/Seq;
   0      7      2    offset       I


public boolean endsWith(scala.collection.Seq);
  Signature: (Lscala/collection/Seq;)Z
  Code:
   Stack=2, Locals=2, Args_size=2
	aload_0
	aload_1
	invokestatic	Method scala/collection/IndexedSeqLike$class.endsWith:(Lscala/collection/IndexedSeqLike;Lscala/collection/Seq;)Z
	ireturn
  Labels:
  LocalVariableTable: 
   Start  Length  Slot  Name   Signature
   0      6      0    this       Lscala/collection/IndexedSeqViewLike$$anon$6;
   0      6      1    that       Lscala/collection/Seq;


public scala.collection.IndexedSeqView view();
  Signature: ()Lscala/collection/IndexedSeqView;
  Code:
   Stack=1, Locals=1, Args_size=1
	aload_0
	invokestatic	Method scala/collection/IndexedSeqLike$class.view:(Lscala/collection/IndexedSeqLike;)Lscala/collection/IndexedSeqView;
	areturn
  Labels:

public scala.collection.IndexedSeqView view(int, int);
  Signature: (II)Lscala/collection/IndexedSeqView;
  Code:
   Stack=3, Locals=3, Args_size=3
	aload_0
	iload_1
	iload_2
	invokestatic	Method scala/collection/IndexedSeqLike$class.view:(Lscala/collection/IndexedSeqLike;II)Lscala/collection/IndexedSeqView;
	areturn
  Labels:
  LocalVariableTable: 
   Start  Length  Slot  Name   Signature
   0      7      0    this       Lscala/collection/IndexedSeqViewLike$$anon$6;
   0      7      1    from       I
   0      7      2    until       I


public int size();
  Signature: ()I
  Code:
   Stack=1, Locals=1, Args_size=1
	aload_0
	invokestatic	Method scala/collection/SeqLike$class.size:(Lscala/collection/SeqLike;)I
	ireturn
  Labels:

public boolean isDefinedAt(int);
  Signature: (I)Z
  Code:
   Stack=2, Locals=2, Args_size=2
	aload_0
	iload_1
	invokestatic	Method scala/collection/SeqLike$class.isDefinedAt:(Lscala/collection/SeqLike;I)Z
	ireturn
  Labels:
  LocalVariableTable: 
   Start  Length  Slot  Name   Signature
   0      6      0    this       Lscala/collection/IndexedSeqViewLike$$anon$6;
   0      6      1    idx       I


public int prefixLength(scala.Function1);
  Signature: (Lscala/Function1;)I
  Code:
   Stack=2, Locals=2, Args_size=2
	aload_0
	aload_1
	invokestatic	Method scala/collection/SeqLike$class.prefixLength:(Lscala/collection/SeqLike;Lscala/Function1;)I
	ireturn
  Labels:
  LocalVariableTable: 
   Start  Length  Slot  Name   Signature
   0      6      0    this       Lscala/collection/IndexedSeqViewLike$$anon$6;
   0      6      1    p       Lscala/Function1;


public int indexWhere(scala.Function1);
  Signature: (Lscala/Function1;)I
  Code:
   Stack=2, Locals=2, Args_size=2
	aload_0
	aload_1
	invokestatic	Method scala/collection/SeqLike$class.indexWhere:(Lscala/collection/SeqLike;Lscala/Function1;)I
	ireturn
  Labels:
  LocalVariableTable: 
   Start  Length  Slot  Name   Signature
   0      6      0    this       Lscala/collection/IndexedSeqViewLike$$anon$6;
   0      6      1    p       Lscala/Function1;


public int findIndexOf(scala.Function1);
  Signature: (Lscala/Function1;)I
  Code:
   Stack=2, Locals=2, Args_size=2
	aload_0
	aload_1
	invokestatic	Method scala/collection/SeqLike$class.findIndexOf:(Lscala/collection/SeqLike;Lscala/Function1;)I
	ireturn
  Labels:
  LocalVariableTable: 
   Start  Length  Slot  Name   Signature
   0      6      0    this       Lscala/collection/IndexedSeqViewLike$$anon$6;
   0      6      1    p       Lscala/Function1;


public int indexOf(java.lang.Object);
  Signature: (Ljava/lang/Object;)I
  Code:
   Stack=2, Locals=2, Args_size=2
	aload_0
	aload_1
	invokestatic	Method scala/collection/SeqLike$class.indexOf:(Lscala/collection/SeqLike;Ljava/lang/Object;)I
	ireturn
  Labels:
  LocalVariableTable: 
   Start  Length  Slot  Name   Signature
   0      6      0    this       Lscala/collection/IndexedSeqViewLike$$anon$6;
   0      6      1    elem       Ljava/lang/Object;


public int indexOf(java.lang.Object, int);
  Signature: (Ljava/lang/Object;I)I
  Code:
   Stack=3, Locals=3, Args_size=3
	aload_0
	aload_1
	iload_2
	invokestatic	Method scala/collection/SeqLike$class.indexOf:(Lscala/collection/SeqLike;Ljava/lang/Object;I)I
	ireturn
  Labels:
  LocalVariableTable: 
   Start  Length  Slot  Name   Signature
   0      7      0    this       Lscala/collection/IndexedSeqViewLike$$anon$6;
   0      7      1    elem       Ljava/lang/Object;
   0      7      2    from       I


public int lastIndexOf(java.lang.Object);
  Signature: (Ljava/lang/Object;)I
  Code:
   Stack=2, Locals=2, Args_size=2
	aload_0
	aload_1
	invokestatic	Method scala/collection/SeqLike$class.lastIndexOf:(Lscala/collection/SeqLike;Ljava/lang/Object;)I
	ireturn
  Labels:
  LocalVariableTable: 
   Start  Length  Slot  Name   Signature
   0      6      0    this       Lscala/collection/IndexedSeqViewLike$$anon$6;
   0      6      1    elem       Ljava/lang/Object;


public int lastIndexOf(java.lang.Object, int);
  Signature: (Ljava/lang/Object;I)I
  Code:
   Stack=3, Locals=3, Args_size=3
	aload_0
	aload_1
	iload_2
	invokestatic	Method scala/collection/SeqLike$class.lastIndexOf:(Lscala/collection/SeqLike;Ljava/lang/Object;I)I
	ireturn
  Labels:
  LocalVariableTable: 
   Start  Length  Slot  Name   Signature
   0      7      0    this       Lscala/collection/IndexedSeqViewLike$$anon$6;
   0      7      1    elem       Ljava/lang/Object;
   0      7      2    end       I


public int lastIndexWhere(scala.Function1);
  Signature: (Lscala/Function1;)I
  Code:
   Stack=2, Locals=2, Args_size=2
	aload_0
	aload_1
	invokestatic	Method scala/collection/SeqLike$class.lastIndexWhere:(Lscala/collection/SeqLike;Lscala/Function1;)I
	ireturn
  Labels:
  LocalVariableTable: 
   Start  Length  Slot  Name   Signature
   0      6      0    this       Lscala/collection/IndexedSeqViewLike$$anon$6;
   0      6      1    p       Lscala/Function1;


public scala.collection.Iterator reversedElements();
  Signature: ()Lscala/collection/Iterator;
  Code:
   Stack=1, Locals=1, Args_size=1
	aload_0
	invokestatic	Method scala/collection/SeqLike$class.reversedElements:(Lscala/collection/SeqLike;)Lscala/collection/Iterator;
	areturn
  Labels:
  Deprecated: true

public boolean startsWith(scala.collection.Seq);
  Signature: (Lscala/collection/Seq;)Z
  Code:
   Stack=2, Locals=2, Args_size=2
	aload_0
	aload_1
	invokestatic	Method scala/collection/SeqLike$class.startsWith:(Lscala/collection/SeqLike;Lscala/collection/Seq;)Z
	ireturn
  Labels:
  LocalVariableTable: 
   Start  Length  Slot  Name   Signature
   0      6      0    this       Lscala/collection/IndexedSeqViewLike$$anon$6;
   0      6      1    that       Lscala/collection/Seq;


public int indexOfSlice(scala.collection.Seq);
  Signature: (Lscala/collection/Seq;)I
  Code:
   Stack=2, Locals=2, Args_size=2
	aload_0
	aload_1
	invokestatic	Method scala/collection/SeqLike$class.indexOfSlice:(Lscala/collection/SeqLike;Lscala/collection/Seq;)I
	ireturn
  Labels:
  LocalVariableTable: 
   Start  Length  Slot  Name   Signature
   0      6      0    this       Lscala/collection/IndexedSeqViewLike$$anon$6;
   0      6      1    that       Lscala/collection/Seq;


public int indexOfSlice(scala.collection.Seq, int);
  Signature: (Lscala/collection/Seq;I)I
  Code:
   Stack=3, Locals=3, Args_size=3
	aload_0
	aload_1
	iload_2
	invokestatic	Method scala/collection/SeqLike$class.indexOfSlice:(Lscala/collection/SeqLike;Lscala/collection/Seq;I)I
	ireturn
  Labels:
  LocalVariableTable: 
   Start  Length  Slot  Name   Signature
   0      7      0    this       Lscala/collection/IndexedSeqViewLike$$anon$6;
   0      7      1    that       Lscala/collection/Seq;
   0      7      2    from       I


public int lastIndexOfSlice(scala.collection.Seq);
  Signature: (Lscala/collection/Seq;)I
  Code:
   Stack=2, Locals=2, Args_size=2
	aload_0
	aload_1
	invokestatic	Method scala/collection/SeqLike$class.lastIndexOfSlice:(Lscala/collection/SeqLike;Lscala/collection/Seq;)I
	ireturn
  Labels:
  LocalVariableTable: 
   Start  Length  Slot  Name   Signature
   0      6      0    this       Lscala/collection/IndexedSeqViewLike$$anon$6;
   0      6      1    that       Lscala/collection/Seq;


public int lastIndexOfSlice(scala.collection.Seq, int);
  Signature: (Lscala/collection/Seq;I)I
  Code:
   Stack=3, Locals=3, Args_size=3
	aload_0
	aload_1
	iload_2
	invokestatic	Method scala/collection/SeqLike$class.lastIndexOfSlice:(Lscala/collection/SeqLike;Lscala/collection/Seq;I)I
	ireturn
  Labels:
  LocalVariableTable: 
   Start  Length  Slot  Name   Signature
   0      7      0    this       Lscala/collection/IndexedSeqViewLike$$anon$6;
   0      7      1    that       Lscala/collection/Seq;
   0      7      2    end       I


public boolean containsSlice(scala.collection.Seq);
  Signature: (Lscala/collection/Seq;)Z
  Code:
   Stack=2, Locals=2, Args_size=2
	aload_0
	aload_1
	invokestatic	Method scala/collection/SeqLike$class.containsSlice:(Lscala/collection/SeqLike;Lscala/collection/Seq;)Z
	ireturn
  Labels:
  LocalVariableTable: 
   Start  Length  Slot  Name   Signature
   0      6      0    this       Lscala/collection/IndexedSeqViewLike$$anon$6;
   0      6      1    that       Lscala/collection/Seq;


public boolean contains(java.lang.Object);
  Signature: (Ljava/lang/Object;)Z
  Code:
   Stack=2, Locals=2, Args_size=2
	aload_0
	aload_1
	invokestatic	Method scala/collection/SeqLike$class.contains:(Lscala/collection/SeqLike;Ljava/lang/Object;)Z
	ireturn
  Labels:
  LocalVariableTable: 
   Start  Length  Slot  Name   Signature
   0      6      0    this       Lscala/collection/IndexedSeqViewLike$$anon$6;
   0      6      1    elem       Ljava/lang/Object;


public java.lang.Object distinct();
  Signature: ()Ljava/lang/Object;
  Code:
   Stack=1, Locals=1, Args_size=1
	aload_0
	invokestatic	Method scala/collection/SeqLike$class.distinct:(Lscala/collection/SeqLike;)Ljava/lang/Object;
	areturn
  Labels:

public boolean corresponds(scala.collection.Seq, scala.Function2);
  Signature: (Lscala/collection/Seq;Lscala/Function2;)Z
  Code:
   Stack=3, Locals=3, Args_size=3
	aload_0
	aload_1
	aload_2
	invokestatic	Method scala/collection/SeqLike$class.corresponds:(Lscala/collection/SeqLike;Lscala/collection/Seq;Lscala/Function2;)Z
	ireturn
  Labels:
  LocalVariableTable: 
   Start  Length  Slot  Name   Signature
   0      7      0    this       Lscala/collection/IndexedSeqViewLike$$anon$6;
   0      7      1    that       Lscala/collection/Seq;
   0      7      2    p       Lscala/Function2;


public java.lang.Object sortWith(scala.Function2);
  Signature: (Lscala/Function2;)Ljava/lang/Object;
  Code:
   Stack=2, Locals=2, Args_size=2
	aload_0
	aload_1
	invokestatic	Method scala/collection/SeqLike$class.sortWith:(Lscala/collection/SeqLike;Lscala/Function2;)Ljava/lang/Object;
	areturn
  Labels:
  LocalVariableTable: 
   Start  Length  Slot  Name   Signature
   0      6      0    this       Lscala/collection/IndexedSeqViewLike$$anon$6;
   0      6      1    lt       Lscala/Function2;


public java.lang.Object sortBy(scala.Function1, scala.math.Ordering);
  Signature: (Lscala/Function1;Lscala/math/Ordering;)Ljava/lang/Object;
  Code:
   Stack=3, Locals=3, Args_size=3
	aload_0
	aload_1
	aload_2
	invokestatic	Method scala/collection/SeqLike$class.sortBy:(Lscala/collection/SeqLike;Lscala/Function1;Lscala/math/Ordering;)Ljava/lang/Object;
	areturn
  Labels:
  LocalVariableTable: 
   Start  Length  Slot  Name   Signature
   0      7      0    this       Lscala/collection/IndexedSeqViewLike$$anon$6;
   0      7      1    f       Lscala/Function1;
   0      7      2    ord       Lscala/math/Ordering;


public scala.collection.Seq toSeq();
  Signature: ()Lscala/collection/Seq;
  Code:
   Stack=1, Locals=1, Args_size=1
	aload_0
	invokestatic	Method scala/collection/SeqLike$class.toSeq:(Lscala/collection/SeqLike;)Lscala/collection/Seq;
	areturn
  Labels:

public scala.collection.immutable.Range indices();
  Signature: ()Lscala/collection/immutable/Range;
  Code:
   Stack=1, Locals=1, Args_size=1
	aload_0
	invokestatic	Method scala/collection/SeqLike$class.indices:(Lscala/collection/SeqLike;)Lscala/collection/immutable/Range;
	areturn
  Labels:

public int hashCode();
  Signature: ()I
  Code:
   Stack=1, Locals=1, Args_size=1
	aload_0
	invokestatic	Method scala/collection/SeqLike$class.hashCode:(Lscala/collection/SeqLike;)I
	ireturn
  Labels:

public boolean equals(java.lang.Object);
  Signature: (Ljava/lang/Object;)Z
  Code:
   Stack=2, Locals=2, Args_size=2
	aload_0
	aload_1
	invokestatic	Method scala/collection/SeqLike$class.equals:(Lscala/collection/SeqLike;Ljava/lang/Object;)Z
	ireturn
  Labels:
  LocalVariableTable: 
   Start  Length  Slot  Name   Signature
   0      6      0    this       Lscala/collection/IndexedSeqViewLike$$anon$6;
   0      6      1    that       Ljava/lang/Object;


public java.lang.String toString();
  Signature: ()Ljava/lang/String;
  Code:
   Stack=1, Locals=1, Args_size=1
	aload_0
	invokestatic	Method scala/collection/SeqLike$class.toString:(Lscala/collection/SeqLike;)Ljava/lang/String;
	areturn
  Labels:

public int findLastIndexOf(scala.Function1);
  Signature: (Lscala/Function1;)I
  Code:
   Stack=2, Locals=2, Args_size=2
	aload_0
	aload_1
	invokestatic	Method scala/collection/SeqLike$class.findLastIndexOf:(Lscala/collection/SeqLike;Lscala/Function1;)I
	ireturn
  Labels:
  LocalVariableTable: 
   Start  Length  Slot  Name   Signature
   0      6      0    this       Lscala/collection/IndexedSeqViewLike$$anon$6;
   0      6      1    p       Lscala/Function1;

  Deprecated: true

public boolean equalsWith(scala.collection.Seq, scala.Function2);
  Signature: (Lscala/collection/Seq;Lscala/Function2;)Z
  Code:
   Stack=3, Locals=3, Args_size=3
	aload_0
	aload_1
	aload_2
	invokestatic	Method scala/collection/SeqLike$class.equalsWith:(Lscala/collection/SeqLike;Lscala/collection/Seq;Lscala/Function2;)Z
	ireturn
  Labels:
  LocalVariableTable: 
   Start  Length  Slot  Name   Signature
   0      7      0    this       Lscala/collection/IndexedSeqViewLike$$anon$6;
   0      7      1    that       Lscala/collection/Seq;
   0      7      2    f       Lscala/Function2;

  Deprecated: true

public scala.collection.SeqView projection();
  Signature: ()Lscala/collection/SeqView;
  Code:
   Stack=1, Locals=1, Args_size=1
	aload_0
	invokestatic	Method scala/collection/SeqLike$class.projection:(Lscala/collection/SeqLike;)Lscala/collection/SeqView;
	areturn
  Labels:
  Deprecated: true

public scala.collection.Iterable toIterable();
  Signature: ()Lscala/collection/Iterable;
  Code:
   Stack=1, Locals=1, Args_size=1
	aload_0
	invokestatic	Method scala/collection/IterableLike$class.toIterable:(Lscala/collection/IterableLike;)Lscala/collection/Iterable;
	areturn
  Labels:

public scala.collection.Iterator sliding(int);
  Signature: (I)Lscala/collection/Iterator;
  Code:
   Stack=2, Locals=2, Args_size=2
	aload_0
	iload_1
	invokestatic	Method scala/collection/IterableLike$class.sliding:(Lscala/collection/IterableLike;I)Lscala/collection/Iterator;
	areturn
  Labels:
  LocalVariableTable: 
   Start  Length  Slot  Name   Signature
   0      6      0    this       Lscala/collection/IndexedSeqViewLike$$anon$6;
   0      6      1    size       I


public scala.collection.immutable.Stream toStream();
  Signature: ()Lscala/collection/immutable/Stream;
  Code:
   Stack=1, Locals=1, Args_size=1
	aload_0
	invokestatic	Method scala/collection/IterableLike$class.toStream:(Lscala/collection/IterableLike;)Lscala/collection/immutable/Stream;
	areturn
  Labels:

public boolean canEqual(java.lang.Object);
  Signature: (Ljava/lang/Object;)Z
  Code:
   Stack=2, Locals=2, Args_size=2
	aload_0
	aload_1
	invokestatic	Method scala/collection/IterableLike$class.canEqual:(Lscala/collection/IterableLike;Ljava/lang/Object;)Z
	ireturn
  Labels:
  LocalVariableTable: 
   Start  Length  Slot  Name   Signature
   0      6      0    this       Lscala/collection/IndexedSeqViewLike$$anon$6;
   0      6      1    that       Ljava/lang/Object;


public scala.collection.Iterator elements();
  Signature: ()Lscala/collection/Iterator;
  Code:
   Stack=1, Locals=1, Args_size=1
	aload_0
	invokestatic	Method scala/collection/IterableLike$class.elements:(Lscala/collection/IterableLike;)Lscala/collection/Iterator;
	areturn
  Labels:
  Deprecated: true

public java.lang.Object first();
  Signature: ()Ljava/lang/Object;
  Code:
   Stack=1, Locals=1, Args_size=1
	aload_0
	invokestatic	Method scala/collection/IterableLike$class.first:(Lscala/collection/IterableLike;)Ljava/lang/Object;
	areturn
  Labels:
  Deprecated: true

public scala.Option firstOption();
  Signature: ()Lscala/Option;
  Code:
   Stack=1, Locals=1, Args_size=1
	aload_0
	invokestatic	Method scala/collection/IterableLike$class.firstOption:(Lscala/collection/IterableLike;)Lscala/Option;
	areturn
  Labels:
  Deprecated: true

public scala.collection.mutable.Builder genericBuilder();
  Signature: ()Lscala/collection/mutable/Builder;
  Code:
   Stack=1, Locals=1, Args_size=1
	aload_0
	invokestatic	Method scala/collection/generic/GenericTraversableTemplate$class.genericBuilder:(Lscala/collection/generic/GenericTraversableTemplate;)Lscala/collection/mutable/Builder;
	areturn
  Labels:

public scala.Tuple2 unzip(scala.Function1);
  Signature: (Lscala/Function1;)Lscala/Tuple2;
  Code:
   Stack=2, Locals=2, Args_size=2
	aload_0
	aload_1
	invokestatic	Method scala/collection/generic/GenericTraversableTemplate$class.unzip:(Lscala/collection/generic/GenericTraversableTemplate;Lscala/Function1;)Lscala/Tuple2;
	areturn
  Labels:
  LocalVariableTable: 
   Start  Length  Slot  Name   Signature
   0      6      0    this       Lscala/collection/IndexedSeqViewLike$$anon$6;
   0      6      1    asPair       Lscala/Function1;


public scala.collection.Traversable flatten(scala.Function1);
  Signature: (Lscala/Function1;)Lscala/collection/Traversable;
  Code:
   Stack=2, Locals=2, Args_size=2
	aload_0
	aload_1
	invokestatic	Method scala/collection/generic/GenericTraversableTemplate$class.flatten:(Lscala/collection/generic/GenericTraversableTemplate;Lscala/Function1;)Lscala/collection/Traversable;
	areturn
  Labels:
  LocalVariableTable: 
   Start  Length  Slot  Name   Signature
   0      6      0    this       Lscala/collection/IndexedSeqViewLike$$anon$6;
   0      6      1    asTraversable       Lscala/Function1;


public scala.collection.Traversable transpose(scala.Function1);
  Signature: (Lscala/Function1;)Lscala/collection/Traversable;
  Code:
   Stack=2, Locals=2, Args_size=2
	aload_0
	aload_1
	invokestatic	Method scala/collection/generic/GenericTraversableTemplate$class.transpose:(Lscala/collection/generic/GenericTraversableTemplate;Lscala/Function1;)Lscala/collection/Traversable;
	areturn
  Labels:
  LocalVariableTable: 
   Start  Length  Slot  Name   Signature
   0      6      0    this       Lscala/collection/IndexedSeqViewLike$$anon$6;
   0      6      1    asTraversable       Lscala/Function1;


public java.lang.Object repr();
  Signature: ()Ljava/lang/Object;
  Code:
   Stack=1, Locals=1, Args_size=1
	aload_0
	invokestatic	Method scala/collection/TraversableLike$class.repr:(Lscala/collection/TraversableLike;)Ljava/lang/Object;
	areturn
  Labels:

public boolean nonEmpty();
  Signature: ()Z
  Code:
   Stack=1, Locals=1, Args_size=1
	aload_0
	invokestatic	Method scala/collection/TraversableLike$class.nonEmpty:(Lscala/collection/TraversableLike;)Z
	ireturn
  Labels:

public boolean hasDefiniteSize();
  Signature: ()Z
  Code:
   Stack=1, Locals=1, Args_size=1
	aload_0
	invokestatic	Method scala/collection/TraversableLike$class.hasDefiniteSize:(Lscala/collection/TraversableLike;)Z
	ireturn
  Labels:

public java.lang.Object filterNot(scala.Function1);
  Signature: (Lscala/Function1;)Ljava/lang/Object;
  Code:
   Stack=2, Locals=2, Args_size=2
	aload_0
	aload_1
	invokestatic	Method scala/collection/TraversableLike$class.filterNot:(Lscala/collection/TraversableLike;Lscala/Function1;)Ljava/lang/Object;
	areturn
  Labels:
  LocalVariableTable: 
   Start  Length  Slot  Name   Signature
   0      6      0    this       Lscala/collection/IndexedSeqViewLike$$anon$6;
   0      6      1    p       Lscala/Function1;


public int count(scala.Function1);
  Signature: (Lscala/Function1;)I
  Code:
   Stack=2, Locals=2, Args_size=2
	aload_0
	aload_1
	invokestatic	Method scala/collection/TraversableLike$class.count:(Lscala/collection/TraversableLike;Lscala/Function1;)I
	ireturn
  Labels:
  LocalVariableTable: 
   Start  Length  Slot  Name   Signature
   0      6      0    this       Lscala/collection/IndexedSeqViewLike$$anon$6;
   0      6      1    p       Lscala/Function1;


public java.lang.Object $div$colon(java.lang.Object, scala.Function2);
  Signature: (Ljava/lang/Object;Lscala/Function2;)Ljava/lang/Object;
  Code:
   Stack=3, Locals=3, Args_size=3
	aload_0
	aload_1
	aload_2
	invokestatic	Method scala/collection/TraversableLike$class.$div$colon:(Lscala/collection/TraversableLike;Ljava/lang/Object;Lscala/Function2;)Ljava/lang/Object;
	areturn
  Labels:
  LocalVariableTable: 
   Start  Length  Slot  Name   Signature
   0      7      0    this       Lscala/collection/IndexedSeqViewLike$$anon$6;
   0      7      1    z       Ljava/lang/Object;
   0      7      2    op       Lscala/Function2;


public java.lang.Object $colon$bslash(java.lang.Object, scala.Function2);
  Signature: (Ljava/lang/Object;Lscala/Function2;)Ljava/lang/Object;
  Code:
   Stack=3, Locals=3, Args_size=3
	aload_0
	aload_1
	aload_2
	invokestatic	Method scala/collection/TraversableLike$class.$colon$bslash:(Lscala/collection/TraversableLike;Ljava/lang/Object;Lscala/Function2;)Ljava/lang/Object;
	areturn
  Labels:
  LocalVariableTable: 
   Start  Length  Slot  Name   Signature
   0      7      0    this       Lscala/collection/IndexedSeqViewLike$$anon$6;
   0      7      1    z       Ljava/lang/Object;
   0      7      2    op       Lscala/Function2;


public scala.Option reduceLeftOption(scala.Function2);
  Signature: (Lscala/Function2;)Lscala/Option;
  Code:
   Stack=2, Locals=2, Args_size=2
	aload_0
	aload_1
	invokestatic	Method scala/collection/TraversableLike$class.reduceLeftOption:(Lscala/collection/TraversableLike;Lscala/Function2;)Lscala/Option;
	areturn
  Labels:
  LocalVariableTable: 
   Start  Length  Slot  Name   Signature
   0      6      0    this       Lscala/collection/IndexedSeqViewLike$$anon$6;
   0      6      1    op       Lscala/Function2;


public scala.Option reduceRightOption(scala.Function2);
  Signature: (Lscala/Function2;)Lscala/Option;
  Code:
   Stack=2, Locals=2, Args_size=2
	aload_0
	aload_1
	invokestatic	Method scala/collection/TraversableLike$class.reduceRightOption:(Lscala/collection/TraversableLike;Lscala/Function2;)Lscala/Option;
	areturn
  Labels:
  LocalVariableTable: 
   Start  Length  Slot  Name   Signature
   0      6      0    this       Lscala/collection/IndexedSeqViewLike$$anon$6;
   0      6      1    op       Lscala/Function2;


public java.lang.Object sum(scala.math.Numeric);
  Signature: (Lscala/math/Numeric;)Ljava/lang/Object;
  Code:
   Stack=2, Locals=2, Args_size=2
	aload_0
	aload_1
	invokestatic	Method scala/collection/TraversableLike$class.sum:(Lscala/collection/TraversableLike;Lscala/math/Numeric;)Ljava/lang/Object;
	areturn
  Labels:
  LocalVariableTable: 
   Start  Length  Slot  Name   Signature
   0      6      0    this       Lscala/collection/IndexedSeqViewLike$$anon$6;
   0      6      1    num       Lscala/math/Numeric;


public java.lang.Object product(scala.math.Numeric);
  Signature: (Lscala/math/Numeric;)Ljava/lang/Object;
  Code:
   Stack=2, Locals=2, Args_size=2
	aload_0
	aload_1
	invokestatic	Method scala/collection/TraversableLike$class.product:(Lscala/collection/TraversableLike;Lscala/math/Numeric;)Ljava/lang/Object;
	areturn
  Labels:
  LocalVariableTable: 
   Start  Length  Slot  Name   Signature
   0      6      0    this       Lscala/collection/IndexedSeqViewLike$$anon$6;
   0      6      1    num       Lscala/math/Numeric;


public java.lang.Object min(scala.math.Ordering);
  Signature: (Lscala/math/Ordering;)Ljava/lang/Object;
  Code:
   Stack=2, Locals=2, Args_size=2
	aload_0
	aload_1
	invokestatic	Method scala/collection/TraversableLike$class.min:(Lscala/collection/TraversableLike;Lscala/math/Ordering;)Ljava/lang/Object;
	areturn
  Labels:
  LocalVariableTable: 
   Start  Length  Slot  Name   Signature
   0      6      0    this       Lscala/collection/IndexedSeqViewLike$$anon$6;
   0      6      1    cmp       Lscala/math/Ordering;


public java.lang.Object max(scala.math.Ordering);
  Signature: (Lscala/math/Ordering;)Ljava/lang/Object;
  Code:
   Stack=2, Locals=2, Args_size=2
	aload_0
	aload_1
	invokestatic	Method scala/collection/TraversableLike$class.max:(Lscala/collection/TraversableLike;Lscala/math/Ordering;)Ljava/lang/Object;
	areturn
  Labels:
  LocalVariableTable: 
   Start  Length  Slot  Name   Signature
   0      6      0    this       Lscala/collection/IndexedSeqViewLike$$anon$6;
   0      6      1    cmp       Lscala/math/Ordering;


public scala.Option headOption();
  Signature: ()Lscala/Option;
  Code:
   Stack=1, Locals=1, Args_size=1
	aload_0
	invokestatic	Method scala/collection/TraversableLike$class.headOption:(Lscala/collection/TraversableLike;)Lscala/Option;
	areturn
  Labels:

public scala.Option lastOption();
  Signature: ()Lscala/Option;
  Code:
   Stack=1, Locals=1, Args_size=1
	aload_0
	invokestatic	Method scala/collection/TraversableLike$class.lastOption:(Lscala/collection/TraversableLike;)Lscala/Option;
	areturn
  Labels:

public void copyToBuffer(scala.collection.mutable.Buffer);
  Signature: (Lscala/collection/mutable/Buffer;)V
  Code:
   Stack=2, Locals=2, Args_size=2
	aload_0
	aload_1
	invokestatic	Method scala/collection/TraversableLike$class.copyToBuffer:(Lscala/collection/TraversableLike;Lscala/collection/mutable/Buffer;)V
	return
  Labels:
  LocalVariableTable: 
   Start  Length  Slot  Name   Signature
   0      6      0    this       Lscala/collection/IndexedSeqViewLike$$anon$6;
   0      6      1    dest       Lscala/collection/mutable/Buffer;


public void copyToArray(java.lang.Object, int);
  Signature: (Ljava/lang/Object;I)V
  Code:
   Stack=3, Locals=3, Args_size=3
	aload_0
	aload_1
	iload_2
	invokestatic	Method scala/collection/TraversableLike$class.copyToArray:(Lscala/collection/TraversableLike;Ljava/lang/Object;I)V
	return
  Labels:
  LocalVariableTable: 
   Start  Length  Slot  Name   Signature
   0      7      0    this       Lscala/collection/IndexedSeqViewLike$$anon$6;
   0      7      1    xs       Ljava/lang/Object;
   0      7      2    start       I


public void copyToArray(java.lang.Object);
  Signature: (Ljava/lang/Object;)V
  Code:
   Stack=2, Locals=2, Args_size=2
	aload_0
	aload_1
	invokestatic	Method scala/collection/TraversableLike$class.copyToArray:(Lscala/collection/TraversableLike;Ljava/lang/Object;)V
	return
  Labels:
  LocalVariableTable: 
   Start  Length  Slot  Name   Signature
   0      6      0    this       Lscala/collection/IndexedSeqViewLike$$anon$6;
   0      6      1    xs       Ljava/lang/Object;


public java.lang.Object toArray(scala.reflect.ClassManifest);
  Signature: (Lscala/reflect/ClassManifest;)Ljava/lang/Object;
  Code:
   Stack=2, Locals=2, Args_size=2
	aload_0
	aload_1
	invokestatic	Method scala/collection/TraversableLike$class.toArray:(Lscala/collection/TraversableLike;Lscala/reflect/ClassManifest;)Ljava/lang/Object;
	areturn
  Labels:
  LocalVariableTable: 
   Start  Length  Slot  Name   Signature
   0      6      0    this       Lscala/collection/IndexedSeqViewLike$$anon$6;
   0      6      1    evidence$1       Lscala/reflect/ClassManifest;


public scala.collection.immutable.List toList();
  Signature: ()Lscala/collection/immutable/List;
  Code:
   Stack=1, Locals=1, Args_size=1
	aload_0
	invokestatic	Method scala/collection/TraversableLike$class.toList:(Lscala/collection/TraversableLike;)Lscala/collection/immutable/List;
	areturn
  Labels:

public scala.collection.mutable.IndexedSeq toIndexedSeq();
  Signature: ()Lscala/collection/mutable/IndexedSeq;
  Code:
   Stack=1, Locals=1, Args_size=1
	aload_0
	invokestatic	Method scala/collection/TraversableLike$class.toIndexedSeq:(Lscala/collection/TraversableLike;)Lscala/collection/mutable/IndexedSeq;
	areturn
  Labels:

public scala.collection.immutable.Set toSet();
  Signature: ()Lscala/collection/immutable/Set;
  Code:
   Stack=1, Locals=1, Args_size=1
	aload_0
	invokestatic	Method scala/collection/TraversableLike$class.toSet:(Lscala/collection/TraversableLike;)Lscala/collection/immutable/Set;
	areturn
  Labels:

public scala.collection.immutable.Map toMap(scala.Predef$$less$colon$less);
  Signature: (Lscala/Predef$$less$colon$less;)Lscala/collection/immutable/Map;
  Code:
   Stack=2, Locals=2, Args_size=2
	aload_0
	aload_1
	invokestatic	Method scala/collection/TraversableLike$class.toMap:(Lscala/collection/TraversableLike;Lscala/Predef$$less$colon$less;)Lscala/collection/immutable/Map;
	areturn
  Labels:
  LocalVariableTable: 
   Start  Length  Slot  Name   Signature
   0      6      0    this       Lscala/collection/IndexedSeqViewLike$$anon$6;
   0      6      1    ev       Lscala/Predef$$less$colon$less;


public java.lang.String mkString(java.lang.String, java.lang.String, java.lang.String);
  Signature: (Ljava/lang/String;Ljava/lang/String;Ljava/lang/String;)Ljava/lang/String;
  Code:
   Stack=4, Locals=4, Args_size=4
	aload_0
	aload_1
	aload_2
	aload_3
	invokestatic	Method scala/collection/TraversableLike$class.mkString:(Lscala/collection/TraversableLike;Ljava/lang/String;Ljava/lang/String;Ljava/lang/String;)Ljava/lang/String;
	areturn
  Labels:
  LocalVariableTable: 
   Start  Length  Slot  Name   Signature
   0      8      0    this       Lscala/collection/IndexedSeqViewLike$$anon$6;
   0      8      1    start       Ljava/lang/String;
   0      8      2    sep       Ljava/lang/String;
   0      8      3    end       Ljava/lang/String;


public java.lang.String mkString(java.lang.String);
  Signature: (Ljava/lang/String;)Ljava/lang/String;
  Code:
   Stack=2, Locals=2, Args_size=2
	aload_0
	aload_1
	invokestatic	Method scala/collection/TraversableLike$class.mkString:(Lscala/collection/TraversableLike;Ljava/lang/String;)Ljava/lang/String;
	areturn
  Labels:
  LocalVariableTable: 
   Start  Length  Slot  Name   Signature
   0      6      0    this       Lscala/collection/IndexedSeqViewLike$$anon$6;
   0      6      1    sep       Ljava/lang/String;


public java.lang.String mkString();
  Signature: ()Ljava/lang/String;
  Code:
   Stack=1, Locals=1, Args_size=1
	aload_0
	invokestatic	Method scala/collection/TraversableLike$class.mkString:(Lscala/collection/TraversableLike;)Ljava/lang/String;
	areturn
  Labels:

public scala.collection.mutable.StringBuilder addString(scala.collection.mutable.StringBuilder, java.lang.String, java.lang.String, java.lang.String);
  Signature: (Lscala/collection/mutable/StringBuilder;Ljava/lang/String;Ljava/lang/String;Ljava/lang/String;)Lscala/collection/mutable/StringBuilder;
  Code:
   Stack=5, Locals=5, Args_size=5
	aload_0
	aload_1
	aload_2
	aload_3
	aload	4
	invokestatic	Method scala/collection/TraversableLike$class.addString:(Lscala/collection/TraversableLike;Lscala/collection/mutable/StringBuilder;Ljava/lang/String;Ljava/lang/String;Ljava/lang/String;)Lscala/collection/mutable/StringBuilder;
	areturn
  Labels:
  LocalVariableTable: 
   Start  Length  Slot  Name   Signature
   0      10      0    this       Lscala/collection/IndexedSeqViewLike$$anon$6;
   0      10      1    b       Lscala/collection/mutable/StringBuilder;
   0      10      2    start       Ljava/lang/String;
   0      10      3    sep       Ljava/lang/String;
   0      10      4    end       Ljava/lang/String;


public scala.collection.mutable.StringBuilder addString(scala.collection.mutable.StringBuilder, java.lang.String);
  Signature: (Lscala/collection/mutable/StringBuilder;Ljava/lang/String;)Lscala/collection/mutable/StringBuilder;
  Code:
   Stack=3, Locals=3, Args_size=3
	aload_0
	aload_1
	aload_2
	invokestatic	Method scala/collection/TraversableLike$class.addString:(Lscala/collection/TraversableLike;Lscala/collection/mutable/StringBuilder;Ljava/lang/String;)Lscala/collection/mutable/StringBuilder;
	areturn
  Labels:
  LocalVariableTable: 
   Start  Length  Slot  Name   Signature
   0      7      0    this       Lscala/collection/IndexedSeqViewLike$$anon$6;
   0      7      1    b       Lscala/collection/mutable/StringBuilder;
   0      7      2    sep       Ljava/lang/String;


public scala.collection.mutable.StringBuilder addString(scala.collection.mutable.StringBuilder);
  Signature: (Lscala/collection/mutable/StringBuilder;)Lscala/collection/mutable/StringBuilder;
  Code:
   Stack=2, Locals=2, Args_size=2
	aload_0
	aload_1
	invokestatic	Method scala/collection/TraversableLike$class.addString:(Lscala/collection/TraversableLike;Lscala/collection/mutable/StringBuilder;)Lscala/collection/mutable/StringBuilder;
	areturn
  Labels:
  LocalVariableTable: 
   Start  Length  Slot  Name   Signature
   0      6      0    this       Lscala/collection/IndexedSeqViewLike$$anon$6;
   0      6      1    b       Lscala/collection/mutable/StringBuilder;


public scala.collection.TraversableLike$WithFilter withFilter(scala.Function1);
  Signature: (Lscala/Function1;)Lscala/collection/TraversableLike$WithFilter;
  Code:
   Stack=2, Locals=2, Args_size=2
	aload_0
	aload_1
	invokestatic	Method scala/collection/TraversableLike$class.withFilter:(Lscala/collection/TraversableLike;Lscala/Function1;)Lscala/collection/TraversableLike$WithFilter;
	areturn
  Labels:
  LocalVariableTable: 
   Start  Length  Slot  Name   Signature
   0      6      0    this       Lscala/collection/IndexedSeqViewLike$$anon$6;
   0      6      1    p       Lscala/Function1;

  Signature: length = 0x2
   03 10 

public scala.PartialFunction orElse(scala.PartialFunction);
  Signature: (Lscala/PartialFunction;)Lscala/PartialFunction;
  Code:
   Stack=2, Locals=2, Args_size=2
	aload_0
	aload_1
	invokestatic	Method scala/PartialFunction$class.orElse:(Lscala/PartialFunction;Lscala/PartialFunction;)Lscala/PartialFunction;
	areturn
  Labels:
  LocalVariableTable: 
   Start  Length  Slot  Name   Signature
   0      6      0    this       Lscala/collection/IndexedSeqViewLike$$anon$6;
   0      6      1    that       Lscala/PartialFunction;


public scala.PartialFunction andThen(scala.Function1);
  Signature: (Lscala/Function1;)Lscala/PartialFunction;
  Code:
   Stack=2, Locals=2, Args_size=2
	aload_0
	aload_1
	invokestatic	Method scala/PartialFunction$class.andThen:(Lscala/PartialFunction;Lscala/Function1;)Lscala/PartialFunction;
	areturn
  Labels:
  LocalVariableTable: 
   Start  Length  Slot  Name   Signature
   0      6      0    this       Lscala/collection/IndexedSeqViewLike$$anon$6;
   0      6      1    k       Lscala/Function1;


public scala.Function1 lift();
  Signature: ()Lscala/Function1;
  Code:
   Stack=1, Locals=1, Args_size=1
	aload_0
	invokestatic	Method scala/PartialFunction$class.lift:(Lscala/PartialFunction;)Lscala/Function1;
	areturn
  Labels:

public scala.Function1 compose(scala.Function1);
  Signature: (Lscala/Function1;)Lscala/Function1;
  Code:
   Stack=2, Locals=2, Args_size=2
	aload_0
	aload_1
	invokestatic	Method scala/Function1$class.compose:(Lscala/Function1;Lscala/Function1;)Lscala/Function1;
	areturn
  Labels:
  LocalVariableTable: 
   Start  Length  Slot  Name   Signature
   0      6      0    this       Lscala/collection/IndexedSeqViewLike$$anon$6;
   0      6      1    g       Lscala/Function1;


public int from();
  Signature: ()I
  Code:
   Stack=1, Locals=1, Args_size=1
	aload_0
	getfield	Field from:I
	ireturn
  Labels:

public int until();
  Signature: ()I
  Code:
   Stack=1, Locals=1, Args_size=1
	aload_0
	getfield	Field until:I
	ireturn
  Labels:

public scala.collection.IndexedSeqViewLike scala$collection$IndexedSeqViewLike$Sliced$$$outer();
  Signature: ()Lscala/collection/IndexedSeqViewLike;
  Code:
   Stack=1, Locals=1, Args_size=1
	aload_0
	getfield	Field $outer:Lscala/collection/IndexedSeqViewLike;
	areturn
  Labels:

public scala.collection.SeqViewLike scala$collection$SeqViewLike$Sliced$$$outer();
  Signature: ()Lscala/collection/SeqViewLike;
  Code:
   Stack=1, Locals=1, Args_size=1
	aload_0
	getfield	Field $outer:Lscala/collection/IndexedSeqViewLike;
	areturn
  Labels:

public scala.collection.IterableViewLike scala$collection$IterableViewLike$Sliced$$$outer();
  Signature: ()Lscala/collection/IterableViewLike;
  Code:
   Stack=1, Locals=1, Args_size=1
	aload_0
	getfield	Field $outer:Lscala/collection/IndexedSeqViewLike;
	areturn
  Labels:

public scala.collection.TraversableViewLike scala$collection$TraversableViewLike$Sliced$$$outer();
  Signature: ()Lscala/collection/TraversableViewLike;
  Code:
   Stack=1, Locals=1, Args_size=1
	aload_0
	getfield	Field $outer:Lscala/collection/IndexedSeqViewLike;
	areturn
  Labels:

public scala.collection.TraversableViewLike scala$collection$TraversableViewLike$Transformed$$$outer();
  Signature: ()Lscala/collection/TraversableViewLike;
  Code:
   Stack=1, Locals=1, Args_size=1
	aload_0
	getfield	Field $outer:Lscala/collection/IndexedSeqViewLike;
	areturn
  Labels:

public scala.Function1 andThen(scala.Function1);
  Signature: (Lscala/Function1;)Lscala/Function1;
  Code:
   Stack=2, Locals=2, Args_size=2
	aload_0
	aload_1
	invokeinterface	InterfaceMethod scala/PartialFunction.andThen:(Lscala/Function1;)Lscala/PartialFunction;
	areturn
  Labels:
  LocalVariableTable: 
   Start  Length  Slot  Name   Signature
   0      8      0    this       Lscala/collection/IndexedSeqViewLike$$anon$6;
   0      8      1    g       Lscala/Function1;


public scala.collection.IterableView projection();
  Signature: ()Lscala/collection/IterableView;
  Code:
   Stack=1, Locals=1, Args_size=1
	aload_0
	invokeinterface	InterfaceMethod scala/collection/SeqLike.projection:()Lscala/collection/SeqView;
	areturn
  Labels:

public boolean isDefinedAt(java.lang.Object);
  Signature: (Ljava/lang/Object;)Z
  Code:
   Stack=2, Locals=2, Args_size=2
	aload_0
	aload_1
	invokestatic	Method scala/runtime/BoxesRunTime.unboxToInt:(Ljava/lang/Object;)I
	invokeinterface	InterfaceMethod scala/collection/SeqLike.isDefinedAt:(I)Z
	ireturn
  Labels:
  LocalVariableTable: 
   Start  Length  Slot  Name   Signature
   0      11      0    this       Lscala/collection/IndexedSeqViewLike$$anon$6;
   0      11      1    x       Ljava/lang/Object;


public scala.collection.TraversableView view(int, int);
  Signature: (II)Lscala/collection/TraversableView;
  Code:
   Stack=3, Locals=3, Args_size=3
	aload_0
	iload_1
	iload_2
	invokeinterface	InterfaceMethod scala/collection/IndexedSeqLike.view:(II)Lscala/collection/IndexedSeqView;
	areturn
  Labels:
  LocalVariableTable: 
   Start  Length  Slot  Name   Signature
   0      9      0    this       Lscala/collection/IndexedSeqViewLike$$anon$6;
   0      9      1    from       I
   0      9      2    until       I


public scala.collection.IterableView view(int, int);
  Signature: (II)Lscala/collection/IterableView;
  Code:
   Stack=3, Locals=3, Args_size=3
	aload_0
	iload_1
	iload_2
	invokeinterface	InterfaceMethod scala/collection/IndexedSeqLike.view:(II)Lscala/collection/IndexedSeqView;
	areturn
  Labels:
  LocalVariableTable: 
   Start  Length  Slot  Name   Signature
   0      9      0    this       Lscala/collection/IndexedSeqViewLike$$anon$6;
   0      9      1    from       I
   0      9      2    until       I


public scala.collection.SeqView view(int, int);
  Signature: (II)Lscala/collection/SeqView;
  Code:
   Stack=3, Locals=3, Args_size=3
	aload_0
	iload_1
	iload_2
	invokeinterface	InterfaceMethod scala/collection/IndexedSeqLike.view:(II)Lscala/collection/IndexedSeqView;
	areturn
  Labels:
  LocalVariableTable: 
   Start  Length  Slot  Name   Signature
   0      9      0    this       Lscala/collection/IndexedSeqViewLike$$anon$6;
   0      9      1    from       I
   0      9      2    until       I


public scala.collection.TraversableView view();
  Signature: ()Lscala/collection/TraversableView;
  Code:
   Stack=1, Locals=1, Args_size=1
	aload_0
	invokeinterface	InterfaceMethod scala/collection/IndexedSeqLike.view:()Lscala/collection/IndexedSeqView;
	areturn
  Labels:

public scala.collection.IterableView view();
  Signature: ()Lscala/collection/IterableView;
  Code:
   Stack=1, Locals=1, Args_size=1
	aload_0
	invokeinterface	InterfaceMethod scala/collection/IndexedSeqLike.view:()Lscala/collection/IndexedSeqView;
	areturn
  Labels:

public scala.collection.SeqView view();
  Signature: ()Lscala/collection/SeqView;
  Code:
   Stack=1, Locals=1, Args_size=1
	aload_0
	invokeinterface	InterfaceMethod scala/collection/IndexedSeqLike.view:()Lscala/collection/IndexedSeqView;
	areturn
  Labels:

public scala.collection.Traversable toCollection(java.lang.Object);
  Signature: (Ljava/lang/Object;)Lscala/collection/Traversable;
  Code:
   Stack=2, Locals=2, Args_size=2
	aload_0
	aload_1
	invokeinterface	InterfaceMethod scala/collection/IndexedSeqLike.toCollection:(Ljava/lang/Object;)Lscala/collection/IndexedSeq;
	areturn
  Labels:
  LocalVariableTable: 
   Start  Length  Slot  Name   Signature
   0      8      0    this       Lscala/collection/IndexedSeqViewLike$$anon$6;
   0      8      1    repr       Ljava/lang/Object;


public scala.collection.Iterable toCollection(java.lang.Object);
  Signature: (Ljava/lang/Object;)Lscala/collection/Iterable;
  Code:
   Stack=2, Locals=2, Args_size=2
	aload_0
	aload_1
	invokeinterface	InterfaceMethod scala/collection/IndexedSeqLike.toCollection:(Ljava/lang/Object;)Lscala/collection/IndexedSeq;
	areturn
  Labels:
  LocalVariableTable: 
   Start  Length  Slot  Name   Signature
   0      8      0    this       Lscala/collection/IndexedSeqViewLike$$anon$6;
   0      8      1    repr       Ljava/lang/Object;


public scala.collection.Seq toCollection(java.lang.Object);
  Signature: (Ljava/lang/Object;)Lscala/collection/Seq;
  Code:
   Stack=2, Locals=2, Args_size=2
	aload_0
	aload_1
	invokeinterface	InterfaceMethod scala/collection/IndexedSeqLike.toCollection:(Ljava/lang/Object;)Lscala/collection/IndexedSeq;
	areturn
  Labels:
  LocalVariableTable: 
   Start  Length  Slot  Name   Signature
   0      8      0    this       Lscala/collection/IndexedSeqViewLike$$anon$6;
   0      8      1    repr       Ljava/lang/Object;


public scala.collection.Traversable thisCollection();
  Signature: ()Lscala/collection/Traversable;
  Code:
   Stack=1, Locals=1, Args_size=1
	aload_0
	invokeinterface	InterfaceMethod scala/collection/IndexedSeqLike.thisCollection:()Lscala/collection/IndexedSeq;
	areturn
  Labels:

public scala.collection.Iterable thisCollection();
  Signature: ()Lscala/collection/Iterable;
  Code:
   Stack=1, Locals=1, Args_size=1
	aload_0
	invokeinterface	InterfaceMethod scala/collection/IndexedSeqLike.thisCollection:()Lscala/collection/IndexedSeq;
	areturn
  Labels:

public scala.collection.Seq thisCollection();
  Signature: ()Lscala/collection/Seq;
  Code:
   Stack=1, Locals=1, Args_size=1
	aload_0
	invokeinterface	InterfaceMethod scala/collection/IndexedSeqLike.thisCollection:()Lscala/collection/IndexedSeq;
	areturn
  Labels:

public java.lang.Object takeWhile(scala.Function1);
  Signature: (Lscala/Function1;)Ljava/lang/Object;
  Code:
   Stack=2, Locals=2, Args_size=2
	aload_0
	aload_1
	invokeinterface	InterfaceMethod scala/collection/TraversableViewLike.takeWhile:(Lscala/Function1;)Lscala/collection/TraversableView;
	areturn
  Labels:
  LocalVariableTable: 
   Start  Length  Slot  Name   Signature
   0      8      0    this       Lscala/collection/IndexedSeqViewLike$$anon$6;
   0      8      1    p       Lscala/Function1;


public java.lang.Object dropWhile(scala.Function1);
  Signature: (Lscala/Function1;)Ljava/lang/Object;
  Code:
   Stack=2, Locals=2, Args_size=2
	aload_0
	aload_1
	invokeinterface	InterfaceMethod scala/collection/TraversableViewLike.dropWhile:(Lscala/Function1;)Lscala/collection/TraversableView;
	areturn
  Labels:
  LocalVariableTable: 
   Start  Length  Slot  Name   Signature
   0      8      0    this       Lscala/collection/IndexedSeqViewLike$$anon$6;
   0      8      1    p       Lscala/Function1;


public java.lang.Object take(int);
  Signature: (I)Ljava/lang/Object;
  Code:
   Stack=2, Locals=2, Args_size=2
	aload_0
	iload_1
	invokeinterface	InterfaceMethod scala/collection/TraversableViewLike.take:(I)Lscala/collection/TraversableView;
	areturn
  Labels:
  LocalVariableTable: 
   Start  Length  Slot  Name   Signature
   0      8      0    this       Lscala/collection/IndexedSeqViewLike$$anon$6;
   0      8      1    n       I


public java.lang.Object drop(int);
  Signature: (I)Ljava/lang/Object;
  Code:
   Stack=2, Locals=2, Args_size=2
	aload_0
	iload_1
	invokeinterface	InterfaceMethod scala/collection/TraversableViewLike.drop:(I)Lscala/collection/TraversableView;
	areturn
  Labels:
  LocalVariableTable: 
   Start  Length  Slot  Name   Signature
   0      8      0    this       Lscala/collection/IndexedSeqViewLike$$anon$6;
   0      8      1    n       I


public java.lang.Object init();
  Signature: ()Ljava/lang/Object;
  Code:
   Stack=1, Locals=1, Args_size=1
	aload_0
	invokeinterface	InterfaceMethod scala/collection/TraversableViewLike.init:()Lscala/collection/TraversableView;
	areturn
  Labels:

public java.lang.Object filter(scala.Function1);
  Signature: (Lscala/Function1;)Ljava/lang/Object;
  Code:
   Stack=2, Locals=2, Args_size=2
	aload_0
	aload_1
	invokeinterface	InterfaceMethod scala/collection/TraversableViewLike.filter:(Lscala/Function1;)Lscala/collection/TraversableView;
	areturn
  Labels:
  LocalVariableTable: 
   Start  Length  Slot  Name   Signature
   0      8      0    this       Lscala/collection/IndexedSeqViewLike$$anon$6;
   0      8      1    p       Lscala/Function1;


public java.lang.Object sorted(scala.math.Ordering);
  Signature: (Lscala/math/Ordering;)Ljava/lang/Object;
  Code:
   Stack=2, Locals=2, Args_size=2
	aload_0
	aload_1
	invokeinterface	InterfaceMethod scala/collection/SeqViewLike.sorted:(Lscala/math/Ordering;)Lscala/collection/SeqView;
	areturn
  Labels:
  LocalVariableTable: 
   Start  Length  Slot  Name   Signature
   0      8      0    this       Lscala/collection/IndexedSeqViewLike$$anon$6;
   0      8      1    ord       Lscala/math/Ordering;


public java.lang.Object intersect(scala.collection.Seq);
  Signature: (Lscala/collection/Seq;)Ljava/lang/Object;
  Code:
   Stack=2, Locals=2, Args_size=2
	aload_0
	aload_1
	invokeinterface	InterfaceMethod scala/collection/SeqViewLike.intersect:(Lscala/collection/Seq;)Lscala/collection/SeqView;
	areturn
  Labels:
  LocalVariableTable: 
   Start  Length  Slot  Name   Signature
   0      8      0    this       Lscala/collection/IndexedSeqViewLike$$anon$6;
   0      8      1    that       Lscala/collection/Seq;


public java.lang.Object diff(scala.collection.Seq);
  Signature: (Lscala/collection/Seq;)Ljava/lang/Object;
  Code:
   Stack=2, Locals=2, Args_size=2
	aload_0
	aload_1
	invokeinterface	InterfaceMethod scala/collection/SeqViewLike.diff:(Lscala/collection/Seq;)Lscala/collection/SeqView;
	areturn
  Labels:
  LocalVariableTable: 
   Start  Length  Slot  Name   Signature
   0      8      0    this       Lscala/collection/IndexedSeqViewLike$$anon$6;
   0      8      1    that       Lscala/collection/Seq;


public java.lang.Object reverse();
  Signature: ()Ljava/lang/Object;
  Code:
   Stack=1, Locals=1, Args_size=1
	aload_0
	invokeinterface	InterfaceMethod scala/collection/SeqViewLike.reverse:()Lscala/collection/SeqView;
	areturn
  Labels:

public scala.collection.SeqViewLike$Transformed newPrepended(java.lang.Object);
  Signature: (Ljava/lang/Object;)Lscala/collection/SeqViewLike$Transformed;
  Code:
   Stack=2, Locals=2, Args_size=2
	aload_0
	aload_1
	invokeinterface	InterfaceMethod scala/collection/IndexedSeqViewLike.newPrepended:(Ljava/lang/Object;)Lscala/collection/IndexedSeqViewLike$Transformed;
	areturn
  Labels:
  LocalVariableTable: 
   Start  Length  Slot  Name   Signature
   0      8      0    this       Lscala/collection/IndexedSeqViewLike$$anon$6;
   0      8      1    elem       Ljava/lang/Object;

  Signature: length = 0x2
   03 77 

public scala.collection.SeqViewLike$Transformed newPatched(int, scala.collection.Seq, int);
  Signature: (ILscala/collection/Seq;I)Lscala/collection/SeqViewLike$Transformed;
  Code:
   Stack=4, Locals=4, Args_size=4
	aload_0
	iload_1
	aload_2
	iload_3
	invokeinterface	InterfaceMethod scala/collection/IndexedSeqViewLike.newPatched:(ILscala/collection/Seq;I)Lscala/collection/IndexedSeqViewLike$Transformed;
	areturn
  Labels:
  LocalVariableTable: 
   Start  Length  Slot  Name   Signature
   0      10      0    this       Lscala/collection/IndexedSeqViewLike$$anon$6;
   0      10      1    _from       I
   0      10      2    _patch       Lscala/collection/Seq;
   0      10      3    _replaced       I

  Signature: length = 0x2
   03 7C 

public scala.collection.SeqViewLike$Transformed newReversed();
  Signature: ()Lscala/collection/SeqViewLike$Transformed;
  Code:
   Stack=1, Locals=1, Args_size=1
	aload_0
	invokeinterface	InterfaceMethod scala/collection/IndexedSeqViewLike.newReversed:()Lscala/collection/IndexedSeqViewLike$Transformed;
	areturn
  Labels:
  Signature: length = 0x2
   03 7F 

public scala.collection.IterableViewLike$Transformed newZippedAll(scala.collection.Iterable, java.lang.Object, java.lang.Object);
  Signature: (Lscala/collection/Iterable;Ljava/lang/Object;Ljava/lang/Object;)Lscala/collection/IterableViewLike$Transformed;
  Code:
   Stack=4, Locals=4, Args_size=4
	aload_0
	aload_1
	aload_2
	aload_3
	invokeinterface	InterfaceMethod scala/collection/IndexedSeqViewLike.newZippedAll:(Lscala/collection/Iterable;Ljava/lang/Object;Ljava/lang/Object;)Lscala/collection/IndexedSeqViewLike$Transformed;
	areturn
  Labels:
  LocalVariableTable: 
   Start  Length  Slot  Name   Signature
   0      10      0    this       Lscala/collection/IndexedSeqViewLike$$anon$6;
   0      10      1    that       Lscala/collection/Iterable;
   0      10      2    _thisElem       Ljava/lang/Object;
   0      10      3    _thatElem       Ljava/lang/Object;

  Signature: length = 0x2
   03 FFFFFF82 

public scala.collection.SeqViewLike$Transformed newZippedAll(scala.collection.Iterable, java.lang.Object, java.lang.Object);
  Signature: (Lscala/collection/Iterable;Ljava/lang/Object;Ljava/lang/Object;)Lscala/collection/SeqViewLike$Transformed;
  Code:
   Stack=4, Locals=4, Args_size=4
	aload_0
	aload_1
	aload_2
	aload_3
	invokeinterface	InterfaceMethod scala/collection/IndexedSeqViewLike.newZippedAll:(Lscala/collection/Iterable;Ljava/lang/Object;Ljava/lang/Object;)Lscala/collection/IndexedSeqViewLike$Transformed;
	areturn
  Labels:
  LocalVariableTable: 
   Start  Length  Slot  Name   Signature
   0      10      0    this       Lscala/collection/IndexedSeqViewLike$$anon$6;
   0      10      1    that       Lscala/collection/Iterable;
   0      10      2    _thisElem       Ljava/lang/Object;
   0      10      3    _thatElem       Ljava/lang/Object;

  Signature: length = 0x2
   03 FFFFFF85 

public scala.collection.IterableViewLike$Transformed newZipped(scala.collection.Iterable);
  Signature: (Lscala/collection/Iterable;)Lscala/collection/IterableViewLike$Transformed;
  Code:
   Stack=2, Locals=2, Args_size=2
	aload_0
	aload_1
	invokeinterface	InterfaceMethod scala/collection/IndexedSeqViewLike.newZipped:(Lscala/collection/Iterable;)Lscala/collection/IndexedSeqViewLike$Transformed;
	areturn
  Labels:
  LocalVariableTable: 
   Start  Length  Slot  Name   Signature
   0      8      0    this       Lscala/collection/IndexedSeqViewLike$$anon$6;
   0      8      1    that       Lscala/collection/Iterable;

  Signature: length = 0x2
   03 FFFFFF86 

public scala.collection.SeqViewLike$Transformed newZipped(scala.collection.Iterable);
  Signature: (Lscala/collection/Iterable;)Lscala/collection/SeqViewLike$Transformed;
  Code:
   Stack=2, Locals=2, Args_size=2
	aload_0
	aload_1
	invokeinterface	InterfaceMethod scala/collection/IndexedSeqViewLike.newZipped:(Lscala/collection/Iterable;)Lscala/collection/IndexedSeqViewLike$Transformed;
	areturn
  Labels:
  LocalVariableTable: 
   Start  Length  Slot  Name   Signature
   0      8      0    this       Lscala/collection/IndexedSeqViewLike$$anon$6;
   0      8      1    that       Lscala/collection/Iterable;

  Signature: length = 0x2
   03 FFFFFF89 

public scala.collection.TraversableViewLike$Transformed newTakenWhile(scala.Function1);
  Signature: (Lscala/Function1;)Lscala/collection/TraversableViewLike$Transformed;
  Code:
   Stack=2, Locals=2, Args_size=2
	aload_0
	aload_1
	invokeinterface	InterfaceMethod scala/collection/IndexedSeqViewLike.newTakenWhile:(Lscala/Function1;)Lscala/collection/IndexedSeqViewLike$Transformed;
	areturn
  Labels:
  LocalVariableTable: 
   Start  Length  Slot  Name   Signature
   0      8      0    this       Lscala/collection/IndexedSeqViewLike$$anon$6;
   0      8      1    p       Lscala/Function1;

  Signature: length = 0x2
   03 FFFFFF8A 

public scala.collection.IterableViewLike$Transformed newTakenWhile(scala.Function1);
  Signature: (Lscala/Function1;)Lscala/collection/IterableViewLike$Transformed;
  Code:
   Stack=2, Locals=2, Args_size=2
	aload_0
	aload_1
	invokeinterface	InterfaceMethod scala/collection/IndexedSeqViewLike.newTakenWhile:(Lscala/Function1;)Lscala/collection/IndexedSeqViewLike$Transformed;
	areturn
  Labels:
  LocalVariableTable: 
   Start  Length  Slot  Name   Signature
   0      8      0    this       Lscala/collection/IndexedSeqViewLike$$anon$6;
   0      8      1    p       Lscala/Function1;

  Signature: length = 0x2
   03 FFFFFF8D 

public scala.collection.SeqViewLike$Transformed newTakenWhile(scala.Function1);
  Signature: (Lscala/Function1;)Lscala/collection/SeqViewLike$Transformed;
  Code:
   Stack=2, Locals=2, Args_size=2
	aload_0
	aload_1
	invokeinterface	InterfaceMethod scala/collection/IndexedSeqViewLike.newTakenWhile:(Lscala/Function1;)Lscala/collection/IndexedSeqViewLike$Transformed;
	areturn
  Labels:
  LocalVariableTable: 
   Start  Length  Slot  Name   Signature
   0      8      0    this       Lscala/collection/IndexedSeqViewLike$$anon$6;
   0      8      1    p       Lscala/Function1;

  Signature: length = 0x2
   03 FFFFFF8E 

public scala.collection.TraversableViewLike$Transformed newDroppedWhile(scala.Function1);
  Signature: (Lscala/Function1;)Lscala/collection/TraversableViewLike$Transformed;
  Code:
   Stack=2, Locals=2, Args_size=2
	aload_0
	aload_1
	invokeinterface	InterfaceMethod scala/collection/IndexedSeqViewLike.newDroppedWhile:(Lscala/Function1;)Lscala/collection/IndexedSeqViewLike$Transformed;
	areturn
  Labels:
  LocalVariableTable: 
   Start  Length  Slot  Name   Signature
   0      8      0    this       Lscala/collection/IndexedSeqViewLike$$anon$6;
   0      8      1    p       Lscala/Function1;

  Signature: length = 0x2
   03 FFFFFF8A 

public scala.collection.IterableViewLike$Transformed newDroppedWhile(scala.Function1);
  Signature: (Lscala/Function1;)Lscala/collection/IterableViewLike$Transformed;
  Code:
   Stack=2, Locals=2, Args_size=2
	aload_0
	aload_1
	invokeinterface	InterfaceMethod scala/collection/IndexedSeqViewLike.newDroppedWhile:(Lscala/Function1;)Lscala/collection/IndexedSeqViewLike$Transformed;
	areturn
  Labels:
  LocalVariableTable: 
   Start  Length  Slot  Name   Signature
   0      8      0    this       Lscala/collection/IndexedSeqViewLike$$anon$6;
   0      8      1    p       Lscala/Function1;

  Signature: length = 0x2
   03 FFFFFF8D 

public scala.collection.SeqViewLike$Transformed newDroppedWhile(scala.Function1);
  Signature: (Lscala/Function1;)Lscala/collection/SeqViewLike$Transformed;
  Code:
   Stack=2, Locals=2, Args_size=2
	aload_0
	aload_1
	invokeinterface	InterfaceMethod scala/collection/IndexedSeqViewLike.newDroppedWhile:(Lscala/Function1;)Lscala/collection/IndexedSeqViewLike$Transformed;
	areturn
  Labels:
  LocalVariableTable: 
   Start  Length  Slot  Name   Signature
   0      8      0    this       Lscala/collection/IndexedSeqViewLike$$anon$6;
   0      8      1    p       Lscala/Function1;

  Signature: length = 0x2
   03 FFFFFF8E 

public scala.collection.TraversableViewLike$Transformed newSliced(int, int);
  Signature: (II)Lscala/collection/TraversableViewLike$Transformed;
  Code:
   Stack=3, Locals=3, Args_size=3
	aload_0
	iload_1
	iload_2
	invokeinterface	InterfaceMethod scala/collection/IndexedSeqViewLike.newSliced:(II)Lscala/collection/IndexedSeqViewLike$Transformed;
	areturn
  Labels:
  LocalVariableTable: 
   Start  Length  Slot  Name   Signature
   0      9      0    this       Lscala/collection/IndexedSeqViewLike$$anon$6;
   0      9      1    _from       I
   0      9      2    _until       I

  Signature: length = 0x2
   03 FFFFFF91 

public scala.collection.IterableViewLike$Transformed newSliced(int, int);
  Signature: (II)Lscala/collection/IterableViewLike$Transformed;
  Code:
   Stack=3, Locals=3, Args_size=3
	aload_0
	iload_1
	iload_2
	invokeinterface	InterfaceMethod scala/collection/IndexedSeqViewLike.newSliced:(II)Lscala/collection/IndexedSeqViewLike$Transformed;
	areturn
  Labels:
  LocalVariableTable: 
   Start  Length  Slot  Name   Signature
   0      9      0    this       Lscala/collection/IndexedSeqViewLike$$anon$6;
   0      9      1    _from       I
   0      9      2    _until       I

  Signature: length = 0x2
   03 FFFFFF94 

public scala.collection.SeqViewLike$Transformed newSliced(int, int);
  Signature: (II)Lscala/collection/SeqViewLike$Transformed;
  Code:
   Stack=3, Locals=3, Args_size=3
	aload_0
	iload_1
	iload_2
	invokeinterface	InterfaceMethod scala/collection/IndexedSeqViewLike.newSliced:(II)Lscala/collection/IndexedSeqViewLike$Transformed;
	areturn
  Labels:
  LocalVariableTable: 
   Start  Length  Slot  Name   Signature
   0      9      0    this       Lscala/collection/IndexedSeqViewLike$$anon$6;
   0      9      1    _from       I
   0      9      2    _until       I

  Signature: length = 0x2
   03 FFFFFF95 

public scala.collection.TraversableViewLike$Transformed newFiltered(scala.Function1);
  Signature: (Lscala/Function1;)Lscala/collection/TraversableViewLike$Transformed;
  Code:
   Stack=2, Locals=2, Args_size=2
	aload_0
	aload_1
	invokeinterface	InterfaceMethod scala/collection/IndexedSeqViewLike.newFiltered:(Lscala/Function1;)Lscala/collection/IndexedSeqViewLike$Transformed;
	areturn
  Labels:
  LocalVariableTable: 
   Start  Length  Slot  Name   Signature
   0      8      0    this       Lscala/collection/IndexedSeqViewLike$$anon$6;
   0      8      1    p       Lscala/Function1;

  Signature: length = 0x2
   03 FFFFFF8A 

public scala.collection.IterableViewLike$Transformed newFiltered(scala.Function1);
  Signature: (Lscala/Function1;)Lscala/collection/IterableViewLike$Transformed;
  Code:
   Stack=2, Locals=2, Args_size=2
	aload_0
	aload_1
	invokeinterface	InterfaceMethod scala/collection/IndexedSeqViewLike.newFiltered:(Lscala/Function1;)Lscala/collection/IndexedSeqViewLike$Transformed;
	areturn
  Labels:
  LocalVariableTable: 
   Start  Length  Slot  Name   Signature
   0      8      0    this       Lscala/collection/IndexedSeqViewLike$$anon$6;
   0      8      1    p       Lscala/Function1;

  Signature: length = 0x2
   03 FFFFFF8D 

public scala.collection.SeqViewLike$Transformed newFiltered(scala.Function1);
  Signature: (Lscala/Function1;)Lscala/collection/SeqViewLike$Transformed;
  Code:
   Stack=2, Locals=2, Args_size=2
	aload_0
	aload_1
	invokeinterface	InterfaceMethod scala/collection/IndexedSeqViewLike.newFiltered:(Lscala/Function1;)Lscala/collection/IndexedSeqViewLike$Transformed;
	areturn
  Labels:
  LocalVariableTable: 
   Start  Length  Slot  Name   Signature
   0      8      0    this       Lscala/collection/IndexedSeqViewLike$$anon$6;
   0      8      1    p       Lscala/Function1;

  Signature: length = 0x2
   03 FFFFFF8E 

public scala.collection.TraversableViewLike$Transformed newFlatMapped(scala.Function1);
  Signature: (Lscala/Function1;)Lscala/collection/TraversableViewLike$Transformed;
  Code:
   Stack=2, Locals=2, Args_size=2
	aload_0
	aload_1
	invokeinterface	InterfaceMethod scala/collection/IndexedSeqViewLike.newFlatMapped:(Lscala/Function1;)Lscala/collection/IndexedSeqViewLike$Transformed;
	areturn
  Labels:
  LocalVariableTable: 
   Start  Length  Slot  Name   Signature
   0      8      0    this       Lscala/collection/IndexedSeqViewLike$$anon$6;
   0      8      1    f       Lscala/Function1;

  Signature: length = 0x2
   03 FFFFFF8A 

public scala.collection.IterableViewLike$Transformed newFlatMapped(scala.Function1);
  Signature: (Lscala/Function1;)Lscala/collection/IterableViewLike$Transformed;
  Code:
   Stack=2, Locals=2, Args_size=2
	aload_0
	aload_1
	invokeinterface	InterfaceMethod scala/collection/IndexedSeqViewLike.newFlatMapped:(Lscala/Function1;)Lscala/collection/IndexedSeqViewLike$Transformed;
	areturn
  Labels:
  LocalVariableTable: 
   Start  Length  Slot  Name   Signature
   0      8      0    this       Lscala/collection/IndexedSeqViewLike$$anon$6;
   0      8      1    f       Lscala/Function1;

  Signature: length = 0x2
   03 FFFFFF8D 

public scala.collection.SeqViewLike$Transformed newFlatMapped(scala.Function1);
  Signature: (Lscala/Function1;)Lscala/collection/SeqViewLike$Transformed;
  Code:
   Stack=2, Locals=2, Args_size=2
	aload_0
	aload_1
	invokeinterface	InterfaceMethod scala/collection/IndexedSeqViewLike.newFlatMapped:(Lscala/Function1;)Lscala/collection/IndexedSeqViewLike$Transformed;
	areturn
  Labels:
  LocalVariableTable: 
   Start  Length  Slot  Name   Signature
   0      8      0    this       Lscala/collection/IndexedSeqViewLike$$anon$6;
   0      8      1    f       Lscala/Function1;

  Signature: length = 0x2
   03 FFFFFF8E 

public scala.collection.TraversableViewLike$Transformed newMapped(scala.Function1);
  Signature: (Lscala/Function1;)Lscala/collection/TraversableViewLike$Transformed;
  Code:
   Stack=2, Locals=2, Args_size=2
	aload_0
	aload_1
	invokeinterface	InterfaceMethod scala/collection/IndexedSeqViewLike.newMapped:(Lscala/Function1;)Lscala/collection/IndexedSeqViewLike$Transformed;
	areturn
  Labels:
  LocalVariableTable: 
   Start  Length  Slot  Name   Signature
   0      8      0    this       Lscala/collection/IndexedSeqViewLike$$anon$6;
   0      8      1    f       Lscala/Function1;

  Signature: length = 0x2
   03 FFFFFF8A 

public scala.collection.IterableViewLike$Transformed newMapped(scala.Function1);
  Signature: (Lscala/Function1;)Lscala/collection/IterableViewLike$Transformed;
  Code:
   Stack=2, Locals=2, Args_size=2
	aload_0
	aload_1
	invokeinterface	InterfaceMethod scala/collection/IndexedSeqViewLike.newMapped:(Lscala/Function1;)Lscala/collection/IndexedSeqViewLike$Transformed;
	areturn
  Labels:
  LocalVariableTable: 
   Start  Length  Slot  Name   Signature
   0      8      0    this       Lscala/collection/IndexedSeqViewLike$$anon$6;
   0      8      1    f       Lscala/Function1;

  Signature: length = 0x2
   03 FFFFFF8D 

public scala.collection.SeqViewLike$Transformed newMapped(scala.Function1);
  Signature: (Lscala/Function1;)Lscala/collection/SeqViewLike$Transformed;
  Code:
   Stack=2, Locals=2, Args_size=2
	aload_0
	aload_1
	invokeinterface	InterfaceMethod scala/collection/IndexedSeqViewLike.newMapped:(Lscala/Function1;)Lscala/collection/IndexedSeqViewLike$Transformed;
	areturn
  Labels:
  LocalVariableTable: 
   Start  Length  Slot  Name   Signature
   0      8      0    this       Lscala/collection/IndexedSeqViewLike$$anon$6;
   0      8      1    f       Lscala/Function1;

  Signature: length = 0x2
   03 FFFFFF8E 

public scala.collection.TraversableViewLike$Transformed newAppended(scala.collection.Traversable);
  Signature: (Lscala/collection/Traversable;)Lscala/collection/TraversableViewLike$Transformed;
  Code:
   Stack=2, Locals=2, Args_size=2
	aload_0
	aload_1
	invokeinterface	InterfaceMethod scala/collection/IndexedSeqViewLike.newAppended:(Lscala/collection/Traversable;)Lscala/collection/IndexedSeqViewLike$Transformed;
	areturn
  Labels:
  LocalVariableTable: 
   Start  Length  Slot  Name   Signature
   0      8      0    this       Lscala/collection/IndexedSeqViewLike$$anon$6;
   0      8      1    that       Lscala/collection/Traversable;

  Signature: length = 0x2
   03 FFFFFF9C 

public scala.collection.IterableViewLike$Transformed newAppended(scala.collection.Traversable);
  Signature: (Lscala/collection/Traversable;)Lscala/collection/IterableViewLike$Transformed;
  Code:
   Stack=2, Locals=2, Args_size=2
	aload_0
	aload_1
	invokeinterface	InterfaceMethod scala/collection/IndexedSeqViewLike.newAppended:(Lscala/collection/Traversable;)Lscala/collection/IndexedSeqViewLike$Transformed;
	areturn
  Labels:
  LocalVariableTable: 
   Start  Length  Slot  Name   Signature
   0      8      0    this       Lscala/collection/IndexedSeqViewLike$$anon$6;
   0      8      1    that       Lscala/collection/Traversable;

  Signature: length = 0x2
   03 FFFFFF9F 

public scala.collection.SeqViewLike$Transformed newAppended(scala.collection.Traversable);
  Signature: (Lscala/collection/Traversable;)Lscala/collection/SeqViewLike$Transformed;
  Code:
   Stack=2, Locals=2, Args_size=2
	aload_0
	aload_1
	invokeinterface	InterfaceMethod scala/collection/IndexedSeqViewLike.newAppended:(Lscala/collection/Traversable;)Lscala/collection/IndexedSeqViewLike$Transformed;
	areturn
  Labels:
  LocalVariableTable: 
   Start  Length  Slot  Name   Signature
   0      8      0    this       Lscala/collection/IndexedSeqViewLike$$anon$6;
   0      8      1    that       Lscala/collection/Traversable;

  Signature: length = 0x2
   03 FFFFFFA0 

public scala.collection.TraversableViewLike$Transformed newForced(scala.Function0);
  Signature: (Lscala/Function0;)Lscala/collection/TraversableViewLike$Transformed;
  Code:
   Stack=2, Locals=2, Args_size=2
	aload_0
	aload_1
	invokeinterface	InterfaceMethod scala/collection/IndexedSeqViewLike.newForced:(Lscala/Function0;)Lscala/collection/IndexedSeqViewLike$Transformed;
	areturn
  Labels:
  LocalVariableTable: 
   Start  Length  Slot  Name   Signature
   0      8      0    this       Lscala/collection/IndexedSeqViewLike$$anon$6;
   0      8      1    xs       Lscala/Function0;

  Signature: length = 0x2
   03 FFFFFFA1 

public scala.collection.IterableViewLike$Transformed newForced(scala.Function0);
  Signature: (Lscala/Function0;)Lscala/collection/IterableViewLike$Transformed;
  Code:
   Stack=2, Locals=2, Args_size=2
	aload_0
	aload_1
	invokeinterface	InterfaceMethod scala/collection/IndexedSeqViewLike.newForced:(Lscala/Function0;)Lscala/collection/IndexedSeqViewLike$Transformed;
	areturn
  Labels:
  LocalVariableTable: 
   Start  Length  Slot  Name   Signature
   0      8      0    this       Lscala/collection/IndexedSeqViewLike$$anon$6;
   0      8      1    xs       Lscala/Function0;

  Signature: length = 0x2
   03 FFFFFFA4 

public scala.collection.SeqViewLike$Transformed newForced(scala.Function0);
  Signature: (Lscala/Function0;)Lscala/collection/SeqViewLike$Transformed;
  Code:
   Stack=2, Locals=2, Args_size=2
	aload_0
	aload_1
	invokeinterface	InterfaceMethod scala/collection/IndexedSeqViewLike.newForced:(Lscala/Function0;)Lscala/collection/IndexedSeqViewLike$Transformed;
	areturn
  Labels:
  LocalVariableTable: 
   Start  Length  Slot  Name   Signature
   0      8      0    this       Lscala/collection/IndexedSeqViewLike$$anon$6;
   0      8      1    xs       Lscala/Function0;

  Signature: length = 0x2
   03 FFFFFFA5 

public java.lang.Object slice(int, int);
  Signature: (II)Ljava/lang/Object;
  Code:
   Stack=3, Locals=3, Args_size=3
	aload_0
	iload_1
	iload_2
	invokeinterface	InterfaceMethod scala/collection/TraversableViewLike$Sliced.slice:(II)Lscala/collection/TraversableView;
	areturn
  Labels:
  LocalVariableTable: 
   Start  Length  Slot  Name   Signature
   0      9      0    this       Lscala/collection/IndexedSeqViewLike$$anon$6;
   0      9      1    from       I
   0      9      2    until       I


public java.lang.Object apply(java.lang.Object);
  Signature: (Ljava/lang/Object;)Ljava/lang/Object;
  Code:
   Stack=2, Locals=2, Args_size=2
	aload_0
	aload_1
	invokestatic	Method scala/runtime/BoxesRunTime.unboxToInt:(Ljava/lang/Object;)I
	invokeinterface	InterfaceMethod scala/collection/SeqViewLike$Sliced.apply:(I)Ljava/lang/Object;
	areturn
  Labels:
  LocalVariableTable: 
   Start  Length  Slot  Name   Signature
   0      11      0    this       Lscala/collection/IndexedSeqViewLike$$anon$6;
   0      11      1    v1       Ljava/lang/Object;


public scala.collection.IndexedSeqViewLike$$anon$6(scala.collection.IndexedSeqViewLike, int, int);
  Signature: (Lscala/collection/IndexedSeqViewLike;II)V
  Code:
   Stack=2, Locals=4, Args_size=4
	aload_1
	ifnonnull	l1 // aload_0
	new	class java/lang/NullPointerException
	dup
	invokespecial	Method java/lang/NullPointerException."<init>":()V
	athrow
l1	aload_0
	aload_1
	putfield	Field $outer:Lscala/collection/IndexedSeqViewLike;
	aload_0
	invokespecial	Method java/lang/Object."<init>":()V
	aload_0
	invokestatic	Method scala/Function1$class.$init$:(Lscala/Function1;)V
	aload_0
	invokestatic	Method scala/PartialFunction$class.$init$:(Lscala/PartialFunction;)V
	aload_0
	invokestatic	Method scala/collection/TraversableLike$class.$init$:(Lscala/collection/TraversableLike;)V
	aload_0
	invokestatic	Method scala/collection/generic/GenericTraversableTemplate$class.$init$:(Lscala/collection/generic/GenericTraversableTemplate;)V
	aload_0
	invokestatic	Method scala/collection/Traversable$class.$init$:(Lscala/collection/Traversable;)V
	aload_0
	invokestatic	Method scala/collection/IterableLike$class.$init$:(Lscala/collection/IterableLike;)V
	aload_0
	invokestatic	Method scala/collection/Iterable$class.$init$:(Lscala/collection/Iterable;)V
	aload_0
	invokestatic	Method scala/collection/SeqLike$class.$init$:(Lscala/collection/SeqLike;)V
	aload_0
	invokestatic	Method scala/collection/Seq$class.$init$:(Lscala/collection/Seq;)V
	aload_0
	invokestatic	Method scala/collection/IndexedSeqLike$class.$init$:(Lscala/collection/IndexedSeqLike;)V
	aload_0
	invokestatic	Method scala/collection/IndexedSeq$class.$init$:(Lscala/collection/IndexedSeq;)V
	aload_0
	invokestatic	Method scala/collection/TraversableViewLike$class.$init$:(Lscala/collection/TraversableViewLike;)V
	aload_0
	invokestatic	Method scala/collection/IterableViewLike$class.$init$:(Lscala/collection/IterableViewLike;)V
	aload_0
	invokestatic	Method scala/collection/SeqViewLike$class.$init$:(Lscala/collection/SeqViewLike;)V
	aload_0
	invokestatic	Method scala/collection/IndexedSeqViewLike$class.$init$:(Lscala/collection/IndexedSeqViewLike;)V
	aload_0
	invokestatic	Method scala/collection/TraversableViewLike$Transformed$class.$init$:(Lscala/collection/TraversableViewLike$Transformed;)V
	aload_0
	invokestatic	Method scala/collection/TraversableViewLike$Sliced$class.$init$:(Lscala/collection/TraversableViewLike$Sliced;)V
	aload_0
	invokestatic	Method scala/collection/IterableViewLike$Sliced$class.$init$:(Lscala/collection/IterableViewLike$Sliced;)V
	aload_0
	invokestatic	Method scala/collection/SeqViewLike$Sliced$class.$init$:(Lscala/collection/SeqViewLike$Sliced;)V
	aload_0
	invokestatic	Method scala/collection/IndexedSeqViewLike$Sliced$class.$init$:(Lscala/collection/IndexedSeqViewLike$Sliced;)V
	aload_0
	iload_2
	putfield	Field from:I
	aload_0
	iload_3
	putfield	Field until:I
	return
  Labels:
   	l1 = 12 // aload_0
  LocalVariableTable: 
   Start  Length  Slot  Name   Signature
   0      112      0    this       Lscala/collection/IndexedSeqViewLike$$anon$6;
   0      112      1    $outer       Lscala/collection/IndexedSeqViewLike;

  Signature: length = 0x2
   03 FFFFFFFD 

}

