Compiled from "IndexedSeqViewLike.scala"
public abstract class scala.collection.IndexedSeqViewLike$DroppedWhile$class extends java.lang.Object
  SourceFile: "IndexedSeqViewLike.scala"
  Scala: length = 0x
   
  InnerClass: 
   public abstract #25= #22 of #24; //DroppedWhile=class scala/collection/IndexedSeqViewLike$DroppedWhile of class scala/collection/IndexedSeqViewLike
  minor version: 0
  major version: 49
  Constant pool:
const #1 = Asciz	SourceFile;
const #2 = Asciz	IndexedSeqViewLike.scala;
const #3 = Asciz	$init$;
const #4 = Asciz	(Lscala/collection/IndexedSeqViewLike$DroppedWhile;)V;
const #5 = Asciz	Code;
const #6 = Asciz	LineNumberTable;
const #7 = Asciz	$this;
const #8 = Asciz	Lscala/collection/IndexedSeqViewLike$DroppedWhile;;
const #9 = Asciz	LocalVariableTable;
const #10 = Asciz	foreach;
const #11 = Asciz	(Lscala/collection/IndexedSeqViewLike$DroppedWhile;Lscala/Function1;)V;
const #12 = Asciz	scala/collection/IndexedSeqLike$class;
const #13 = class	#12;	//  scala/collection/IndexedSeqLike$class
const #14 = Asciz	(Lscala/collection/IndexedSeqLike;Lscala/Function1;)V;
const #15 = NameAndType	#10:#14;//  foreach:(Lscala/collection/IndexedSeqLike;Lscala/Function1;)V
const #16 = Method	#13.#15;	//  scala/collection/IndexedSeqLike$class.foreach:(Lscala/collection/IndexedSeqLike;Lscala/Function1;)V
const #17 = Asciz	f;
const #18 = Asciz	Lscala/Function1;;
const #19 = Asciz	Scala;
const #20 = Asciz	InnerClasses;
const #21 = Asciz	scala/collection/IndexedSeqViewLike$DroppedWhile;
const #22 = class	#21;	//  scala/collection/IndexedSeqViewLike$DroppedWhile
const #23 = Asciz	scala/collection/IndexedSeqViewLike;
const #24 = class	#23;	//  scala/collection/IndexedSeqViewLike
const #25 = Asciz	DroppedWhile;
const #26 = Asciz	scala/collection/IndexedSeqViewLike$DroppedWhile$class;
const #27 = class	#26;	//  scala/collection/IndexedSeqViewLike$DroppedWhile$class
const #28 = Asciz	java/lang/Object;
const #29 = class	#28;	//  java/lang/Object

{
public static void $init$(scala.collection.IndexedSeqViewLike$DroppedWhile);
  Code:
   Stack=0, Locals=1, Args_size=1
   0:	return
  LineNumberTable: 
   line 57: 0

  LocalVariableTable: 
   Start  Length  Slot  Name   Signature
   0      1      0    $this       Lscala/collection/IndexedSeqViewLike$DroppedWhile;


public static void foreach(scala.collection.IndexedSeqViewLike$DroppedWhile, scala.Function1);
  Code:
   Stack=2, Locals=2, Args_size=2
   0:	aload_0
   1:	aload_1
   2:	invokestatic	#16; //Method scala/collection/IndexedSeqLike$class.foreach:(Lscala/collection/IndexedSeqLike;Lscala/Function1;)V
   5:	return
  LineNumberTable: 
   line 58: 0

  LocalVariableTable: 
   Start  Length  Slot  Name   Signature
   0      6      0    $this       Lscala/collection/IndexedSeqViewLike$DroppedWhile;
   0      6      1    f       Lscala/Function1;


}

