Compiled from "IndexedSeqViewLike.scala"
public abstract class scala.collection.IndexedSeqViewLike$class extends java.lang.Object
  SourceFile: "IndexedSeqViewLike.scala"
  Scala: length = 0x
   
  InnerClass: 
   public final #104= #94 of #103; //$anon$1=class scala/collection/IndexedSeqViewLike$$anon$1 of class scala/collection/IndexedSeqViewLike
   public final #105= #88 of #103; //$anon$2=class scala/collection/IndexedSeqViewLike$$anon$2 of class scala/collection/IndexedSeqViewLike
   public final #106= #83 of #103; //$anon$3=class scala/collection/IndexedSeqViewLike$$anon$3 of class scala/collection/IndexedSeqViewLike
   public final #107= #78 of #103; //$anon$4=class scala/collection/IndexedSeqViewLike$$anon$4 of class scala/collection/IndexedSeqViewLike
   public final #108= #70 of #103; //$anon$5=class scala/collection/IndexedSeqViewLike$$anon$5 of class scala/collection/IndexedSeqViewLike
   public final #109= #64 of #103; //$anon$6=class scala/collection/IndexedSeqViewLike$$anon$6 of class scala/collection/IndexedSeqViewLike
   public final #110= #56 of #103; //$anon$7=class scala/collection/IndexedSeqViewLike$$anon$7 of class scala/collection/IndexedSeqViewLike
   public final #111= #30 of #103; //$anon$8=class scala/collection/IndexedSeqViewLike$$anon$8 of class scala/collection/IndexedSeqViewLike
   public final #112= #17 of #103; //$anon$9=class scala/collection/IndexedSeqViewLike$$anon$9 of class scala/collection/IndexedSeqViewLike
   public final #113= #48 of #103; //$anon$10=class scala/collection/IndexedSeqViewLike$$anon$10 of class scala/collection/IndexedSeqViewLike
   public final #114= #36 of #103; //$anon$11=class scala/collection/IndexedSeqViewLike$$anon$11 of class scala/collection/IndexedSeqViewLike
   public abstract #117= #116 of #103; //Transformed=class scala/collection/IndexedSeqViewLike$Transformed of class scala/collection/IndexedSeqViewLike
  minor version: 0
  major version: 49
  Constant pool:
const #1 = Asciz	SourceFile;
const #2 = Asciz	IndexedSeqViewLike.scala;
const #3 = Asciz	$init$;
const #4 = Asciz	(Lscala/collection/IndexedSeqViewLike;)V;
const #5 = Asciz	Code;
const #6 = Asciz	LineNumberTable;
const #7 = Asciz	$this;
const #8 = Asciz	Lscala/collection/IndexedSeqViewLike;;
const #9 = Asciz	LocalVariableTable;
const #10 = Asciz	stringPrefix;
const #11 = Asciz	(Lscala/collection/IndexedSeqViewLike;)Ljava/lang/String;;
const #12 = Asciz	IndexedSeqView;
const #13 = String	#12;	//  IndexedSeqView
const #14 = Asciz	newPatched;
const #15 = Asciz	(Lscala/collection/IndexedSeqViewLike;ILscala/collection/Seq;I)Lscala/collection/IndexedSeqViewLike$Transformed;;
const #16 = Asciz	scala/collection/IndexedSeqViewLike$$anon$9;
const #17 = class	#16;	//  scala/collection/IndexedSeqViewLike$$anon$9
const #18 = Asciz	<init>;
const #19 = Asciz	(Lscala/collection/IndexedSeqViewLike;ILscala/collection/Seq;I)V;
const #20 = NameAndType	#18:#19;//  "<init>":(Lscala/collection/IndexedSeqViewLike;ILscala/collection/Seq;I)V
const #21 = Method	#17.#20;	//  scala/collection/IndexedSeqViewLike$$anon$9."<init>":(Lscala/collection/IndexedSeqViewLike;ILscala/collection/Seq;I)V
const #22 = Asciz	_from$1;
const #23 = Asciz	I;
const #24 = Asciz	_patch$1;
const #25 = Asciz	Lscala/collection/Seq;;
const #26 = Asciz	_replaced$1;
const #27 = Asciz	newReversed;
const #28 = Asciz	(Lscala/collection/IndexedSeqViewLike;)Lscala/collection/IndexedSeqViewLike$Transformed;;
const #29 = Asciz	scala/collection/IndexedSeqViewLike$$anon$8;
const #30 = class	#29;	//  scala/collection/IndexedSeqViewLike$$anon$8
const #31 = NameAndType	#18:#4;//  "<init>":(Lscala/collection/IndexedSeqViewLike;)V
const #32 = Method	#30.#31;	//  scala/collection/IndexedSeqViewLike$$anon$8."<init>":(Lscala/collection/IndexedSeqViewLike;)V
const #33 = Asciz	newZippedAll;
const #34 = Asciz	(Lscala/collection/IndexedSeqViewLike;Lscala/collection/Iterable;Ljava/lang/Object;Ljava/lang/Object;)Lscala/collection/IndexedSeqViewLike$Transformed;;
const #35 = Asciz	scala/collection/IndexedSeqViewLike$$anon$11;
const #36 = class	#35;	//  scala/collection/IndexedSeqViewLike$$anon$11
const #37 = Asciz	(Lscala/collection/IndexedSeqViewLike;Lscala/collection/Iterable;Ljava/lang/Object;Ljava/lang/Object;)V;
const #38 = NameAndType	#18:#37;//  "<init>":(Lscala/collection/IndexedSeqViewLike;Lscala/collection/Iterable;Ljava/lang/Object;Ljava/lang/Object;)V
const #39 = Method	#36.#38;	//  scala/collection/IndexedSeqViewLike$$anon$11."<init>":(Lscala/collection/IndexedSeqViewLike;Lscala/collection/Iterable;Ljava/lang/Object;Ljava/lang/Object;)V
const #40 = Asciz	that$2;
const #41 = Asciz	Lscala/collection/Iterable;;
const #42 = Asciz	_thisElem$1;
const #43 = Asciz	Ljava/lang/Object;;
const #44 = Asciz	_thatElem$1;
const #45 = Asciz	newZipped;
const #46 = Asciz	(Lscala/collection/IndexedSeqViewLike;Lscala/collection/Iterable;)Lscala/collection/IndexedSeqViewLike$Transformed;;
const #47 = Asciz	scala/collection/IndexedSeqViewLike$$anon$10;
const #48 = class	#47;	//  scala/collection/IndexedSeqViewLike$$anon$10
const #49 = Asciz	(Lscala/collection/IndexedSeqViewLike;Lscala/collection/Iterable;)V;
const #50 = NameAndType	#18:#49;//  "<init>":(Lscala/collection/IndexedSeqViewLike;Lscala/collection/Iterable;)V
const #51 = Method	#48.#50;	//  scala/collection/IndexedSeqViewLike$$anon$10."<init>":(Lscala/collection/IndexedSeqViewLike;Lscala/collection/Iterable;)V
const #52 = Asciz	that$3;
const #53 = Asciz	newTakenWhile;
const #54 = Asciz	(Lscala/collection/IndexedSeqViewLike;Lscala/Function1;)Lscala/collection/IndexedSeqViewLike$Transformed;;
const #55 = Asciz	scala/collection/IndexedSeqViewLike$$anon$7;
const #56 = class	#55;	//  scala/collection/IndexedSeqViewLike$$anon$7
const #57 = Asciz	(Lscala/collection/IndexedSeqViewLike;Lscala/Function1;)V;
const #58 = NameAndType	#18:#57;//  "<init>":(Lscala/collection/IndexedSeqViewLike;Lscala/Function1;)V
const #59 = Method	#56.#58;	//  scala/collection/IndexedSeqViewLike$$anon$7."<init>":(Lscala/collection/IndexedSeqViewLike;Lscala/Function1;)V
const #60 = Asciz	p$1;
const #61 = Asciz	Lscala/Function1;;
const #62 = Asciz	newDroppedWhile;
const #63 = Asciz	scala/collection/IndexedSeqViewLike$$anon$6;
const #64 = class	#63;	//  scala/collection/IndexedSeqViewLike$$anon$6
const #65 = Method	#64.#58;	//  scala/collection/IndexedSeqViewLike$$anon$6."<init>":(Lscala/collection/IndexedSeqViewLike;Lscala/Function1;)V
const #66 = Asciz	p$2;
const #67 = Asciz	newSliced;
const #68 = Asciz	(Lscala/collection/IndexedSeqViewLike;II)Lscala/collection/IndexedSeqViewLike$Transformed;;
const #69 = Asciz	scala/collection/IndexedSeqViewLike$$anon$5;
const #70 = class	#69;	//  scala/collection/IndexedSeqViewLike$$anon$5
const #71 = Asciz	(Lscala/collection/IndexedSeqViewLike;II)V;
const #72 = NameAndType	#18:#71;//  "<init>":(Lscala/collection/IndexedSeqViewLike;II)V
const #73 = Method	#70.#72;	//  scala/collection/IndexedSeqViewLike$$anon$5."<init>":(Lscala/collection/IndexedSeqViewLike;II)V
const #74 = Asciz	_from$2;
const #75 = Asciz	_until$1;
const #76 = Asciz	newFiltered;
const #77 = Asciz	scala/collection/IndexedSeqViewLike$$anon$4;
const #78 = class	#77;	//  scala/collection/IndexedSeqViewLike$$anon$4
const #79 = Method	#78.#58;	//  scala/collection/IndexedSeqViewLike$$anon$4."<init>":(Lscala/collection/IndexedSeqViewLike;Lscala/Function1;)V
const #80 = Asciz	p$3;
const #81 = Asciz	newFlatMapped;
const #82 = Asciz	scala/collection/IndexedSeqViewLike$$anon$3;
const #83 = class	#82;	//  scala/collection/IndexedSeqViewLike$$anon$3
const #84 = Method	#83.#58;	//  scala/collection/IndexedSeqViewLike$$anon$3."<init>":(Lscala/collection/IndexedSeqViewLike;Lscala/Function1;)V
const #85 = Asciz	f$1;
const #86 = Asciz	newMapped;
const #87 = Asciz	scala/collection/IndexedSeqViewLike$$anon$2;
const #88 = class	#87;	//  scala/collection/IndexedSeqViewLike$$anon$2
const #89 = Method	#88.#58;	//  scala/collection/IndexedSeqViewLike$$anon$2."<init>":(Lscala/collection/IndexedSeqViewLike;Lscala/Function1;)V
const #90 = Asciz	f$2;
const #91 = Asciz	newAppended;
const #92 = Asciz	(Lscala/collection/IndexedSeqViewLike;Lscala/collection/Traversable;)Lscala/collection/IndexedSeqViewLike$Transformed;;
const #93 = Asciz	scala/collection/IndexedSeqViewLike$$anon$1;
const #94 = class	#93;	//  scala/collection/IndexedSeqViewLike$$anon$1
const #95 = Asciz	(Lscala/collection/IndexedSeqViewLike;Lscala/collection/Traversable;)V;
const #96 = NameAndType	#18:#95;//  "<init>":(Lscala/collection/IndexedSeqViewLike;Lscala/collection/Traversable;)V
const #97 = Method	#94.#96;	//  scala/collection/IndexedSeqViewLike$$anon$1."<init>":(Lscala/collection/IndexedSeqViewLike;Lscala/collection/Traversable;)V
const #98 = Asciz	that$1;
const #99 = Asciz	Lscala/collection/Traversable;;
const #100 = Asciz	Scala;
const #101 = Asciz	InnerClasses;
const #102 = Asciz	scala/collection/IndexedSeqViewLike;
const #103 = class	#102;	//  scala/collection/IndexedSeqViewLike
const #104 = Asciz	$anon$1;
const #105 = Asciz	$anon$2;
const #106 = Asciz	$anon$3;
const #107 = Asciz	$anon$4;
const #108 = Asciz	$anon$5;
const #109 = Asciz	$anon$6;
const #110 = Asciz	$anon$7;
const #111 = Asciz	$anon$8;
const #112 = Asciz	$anon$9;
const #113 = Asciz	$anon$10;
const #114 = Asciz	$anon$11;
const #115 = Asciz	scala/collection/IndexedSeqViewLike$Transformed;
const #116 = class	#115;	//  scala/collection/IndexedSeqViewLike$Transformed
const #117 = Asciz	Transformed;
const #118 = Asciz	scala/collection/IndexedSeqViewLike$class;
const #119 = class	#118;	//  scala/collection/IndexedSeqViewLike$class
const #120 = Asciz	java/lang/Object;
const #121 = class	#120;	//  java/lang/Object

{
public static void $init$(scala.collection.IndexedSeqViewLike);
  Code:
   Stack=0, Locals=1, Args_size=1
   0:	return
  LineNumberTable: 
   line 27: 0

  LocalVariableTable: 
   Start  Length  Slot  Name   Signature
   0      1      0    $this       Lscala/collection/IndexedSeqViewLike;


public static java.lang.String stringPrefix(scala.collection.IndexedSeqViewLike);
  Code:
   Stack=1, Locals=1, Args_size=1
   0:	ldc	#13; //String IndexedSeqView
   2:	areturn
  LineNumberTable: 
   line 108: 0

  LocalVariableTable: 
   Start  Length  Slot  Name   Signature
   0      3      0    $this       Lscala/collection/IndexedSeqViewLike;


public static scala.collection.IndexedSeqViewLike$Transformed newPatched(scala.collection.IndexedSeqViewLike, int, scala.collection.Seq, int);
  Code:
   Stack=6, Locals=4, Args_size=4
   0:	new	#17; //class scala/collection/IndexedSeqViewLike$$anon$9
   3:	dup
   4:	aload_0
   5:	iload_1
   6:	aload_2
   7:	iload_3
   8:	invokespecial	#21; //Method scala/collection/IndexedSeqViewLike$$anon$9."<init>":(Lscala/collection/IndexedSeqViewLike;ILscala/collection/Seq;I)V
   11:	areturn
  LineNumberTable: 
   line 105: 0

  LocalVariableTable: 
   Start  Length  Slot  Name   Signature
   0      12      0    $this       Lscala/collection/IndexedSeqViewLike;
   0      12      1    _from$1       I
   0      12      2    _patch$1       Lscala/collection/Seq;
   0      12      3    _replaced$1       I


public static scala.collection.IndexedSeqViewLike$Transformed newReversed(scala.collection.IndexedSeqViewLike);
  Code:
   Stack=3, Locals=1, Args_size=1
   0:	new	#30; //class scala/collection/IndexedSeqViewLike$$anon$8
   3:	dup
   4:	aload_0
   5:	invokespecial	#32; //Method scala/collection/IndexedSeqViewLike$$anon$8."<init>":(Lscala/collection/IndexedSeqViewLike;)V
   8:	areturn
  LineNumberTable: 
   line 104: 0

  LocalVariableTable: 
   Start  Length  Slot  Name   Signature
   0      9      0    $this       Lscala/collection/IndexedSeqViewLike;


public static scala.collection.IndexedSeqViewLike$Transformed newZippedAll(scala.collection.IndexedSeqViewLike, scala.collection.Iterable, java.lang.Object, java.lang.Object);
  Code:
   Stack=6, Locals=4, Args_size=4
   0:	new	#36; //class scala/collection/IndexedSeqViewLike$$anon$11
   3:	dup
   4:	aload_0
   5:	aload_1
   6:	aload_2
   7:	aload_3
   8:	invokespecial	#39; //Method scala/collection/IndexedSeqViewLike$$anon$11."<init>":(Lscala/collection/IndexedSeqViewLike;Lscala/collection/Iterable;Ljava/lang/Object;Ljava/lang/Object;)V
   11:	areturn
  LineNumberTable: 
   line 103: 0

  LocalVariableTable: 
   Start  Length  Slot  Name   Signature
   0      12      0    $this       Lscala/collection/IndexedSeqViewLike;
   0      12      1    that$2       Lscala/collection/Iterable;
   0      12      2    _thisElem$1       Ljava/lang/Object;
   0      12      3    _thatElem$1       Ljava/lang/Object;


public static scala.collection.IndexedSeqViewLike$Transformed newZipped(scala.collection.IndexedSeqViewLike, scala.collection.Iterable);
  Code:
   Stack=4, Locals=2, Args_size=2
   0:	new	#48; //class scala/collection/IndexedSeqViewLike$$anon$10
   3:	dup
   4:	aload_0
   5:	aload_1
   6:	invokespecial	#51; //Method scala/collection/IndexedSeqViewLike$$anon$10."<init>":(Lscala/collection/IndexedSeqViewLike;Lscala/collection/Iterable;)V
   9:	areturn
  LineNumberTable: 
   line 102: 0

  LocalVariableTable: 
   Start  Length  Slot  Name   Signature
   0      10      0    $this       Lscala/collection/IndexedSeqViewLike;
   0      10      1    that$3       Lscala/collection/Iterable;


public static scala.collection.IndexedSeqViewLike$Transformed newTakenWhile(scala.collection.IndexedSeqViewLike, scala.Function1);
  Code:
   Stack=4, Locals=2, Args_size=2
   0:	new	#56; //class scala/collection/IndexedSeqViewLike$$anon$7
   3:	dup
   4:	aload_0
   5:	aload_1
   6:	invokespecial	#59; //Method scala/collection/IndexedSeqViewLike$$anon$7."<init>":(Lscala/collection/IndexedSeqViewLike;Lscala/Function1;)V
   9:	areturn
  LineNumberTable: 
   line 101: 0

  LocalVariableTable: 
   Start  Length  Slot  Name   Signature
   0      10      0    $this       Lscala/collection/IndexedSeqViewLike;
   0      10      1    p$1       Lscala/Function1;


public static scala.collection.IndexedSeqViewLike$Transformed newDroppedWhile(scala.collection.IndexedSeqViewLike, scala.Function1);
  Code:
   Stack=4, Locals=2, Args_size=2
   0:	new	#64; //class scala/collection/IndexedSeqViewLike$$anon$6
   3:	dup
   4:	aload_0
   5:	aload_1
   6:	invokespecial	#65; //Method scala/collection/IndexedSeqViewLike$$anon$6."<init>":(Lscala/collection/IndexedSeqViewLike;Lscala/Function1;)V
   9:	areturn
  LineNumberTable: 
   line 100: 0

  LocalVariableTable: 
   Start  Length  Slot  Name   Signature
   0      10      0    $this       Lscala/collection/IndexedSeqViewLike;
   0      10      1    p$2       Lscala/Function1;


public static scala.collection.IndexedSeqViewLike$Transformed newSliced(scala.collection.IndexedSeqViewLike, int, int);
  Code:
   Stack=5, Locals=3, Args_size=3
   0:	new	#70; //class scala/collection/IndexedSeqViewLike$$anon$5
   3:	dup
   4:	aload_0
   5:	iload_1
   6:	iload_2
   7:	invokespecial	#73; //Method scala/collection/IndexedSeqViewLike$$anon$5."<init>":(Lscala/collection/IndexedSeqViewLike;II)V
   10:	areturn
  LineNumberTable: 
   line 99: 0

  LocalVariableTable: 
   Start  Length  Slot  Name   Signature
   0      11      0    $this       Lscala/collection/IndexedSeqViewLike;
   0      11      1    _from$2       I
   0      11      2    _until$1       I


public static scala.collection.IndexedSeqViewLike$Transformed newFiltered(scala.collection.IndexedSeqViewLike, scala.Function1);
  Code:
   Stack=4, Locals=2, Args_size=2
   0:	new	#78; //class scala/collection/IndexedSeqViewLike$$anon$4
   3:	dup
   4:	aload_0
   5:	aload_1
   6:	invokespecial	#79; //Method scala/collection/IndexedSeqViewLike$$anon$4."<init>":(Lscala/collection/IndexedSeqViewLike;Lscala/Function1;)V
   9:	areturn
  LineNumberTable: 
   line 98: 0

  LocalVariableTable: 
   Start  Length  Slot  Name   Signature
   0      10      0    $this       Lscala/collection/IndexedSeqViewLike;
   0      10      1    p$3       Lscala/Function1;


public static scala.collection.IndexedSeqViewLike$Transformed newFlatMapped(scala.collection.IndexedSeqViewLike, scala.Function1);
  Code:
   Stack=4, Locals=2, Args_size=2
   0:	new	#83; //class scala/collection/IndexedSeqViewLike$$anon$3
   3:	dup
   4:	aload_0
   5:	aload_1
   6:	invokespecial	#84; //Method scala/collection/IndexedSeqViewLike$$anon$3."<init>":(Lscala/collection/IndexedSeqViewLike;Lscala/Function1;)V
   9:	areturn
  LineNumberTable: 
   line 97: 0

  LocalVariableTable: 
   Start  Length  Slot  Name   Signature
   0      10      0    $this       Lscala/collection/IndexedSeqViewLike;
   0      10      1    f$1       Lscala/Function1;


public static scala.collection.IndexedSeqViewLike$Transformed newMapped(scala.collection.IndexedSeqViewLike, scala.Function1);
  Code:
   Stack=4, Locals=2, Args_size=2
   0:	new	#88; //class scala/collection/IndexedSeqViewLike$$anon$2
   3:	dup
   4:	aload_0
   5:	aload_1
   6:	invokespecial	#89; //Method scala/collection/IndexedSeqViewLike$$anon$2."<init>":(Lscala/collection/IndexedSeqViewLike;Lscala/Function1;)V
   9:	areturn
  LineNumberTable: 
   line 96: 0

  LocalVariableTable: 
   Start  Length  Slot  Name   Signature
   0      10      0    $this       Lscala/collection/IndexedSeqViewLike;
   0      10      1    f$2       Lscala/Function1;


public static scala.collection.IndexedSeqViewLike$Transformed newAppended(scala.collection.IndexedSeqViewLike, scala.collection.Traversable);
  Code:
   Stack=4, Locals=2, Args_size=2
   0:	new	#94; //class scala/collection/IndexedSeqViewLike$$anon$1
   3:	dup
   4:	aload_0
   5:	aload_1
   6:	invokespecial	#97; //Method scala/collection/IndexedSeqViewLike$$anon$1."<init>":(Lscala/collection/IndexedSeqViewLike;Lscala/collection/Traversable;)V
   9:	areturn
  LineNumberTable: 
   line 95: 0

  LocalVariableTable: 
   Start  Length  Slot  Name   Signature
   0      10      0    $this       Lscala/collection/IndexedSeqViewLike;
   0      10      1    that$1       Lscala/collection/Traversable;


}

