Compiled from "IterableViewLike.scala"
public final class scala.collection.IterableViewLike$FlatMapped$$anonfun$iterator$1 extends java.lang.Object implements scala.Function1,scala.ScalaObject,java.io.Serializable
  SourceFile: "IterableViewLike.scala"
  Scala: length = 0x
   
  InnerClass: 
   public abstract FlatMapped=class scala/collection/IterableViewLike$FlatMapped of class scala/collection/IterableViewLike
   public abstract FlatMapped=class scala/collection/TraversableViewLike$FlatMapped of class scala/collection/TraversableViewLike
   public final $anonfun$iterator$1=class scala/collection/IterableViewLike$FlatMapped$$anonfun$iterator$1 of class scala/collection/IterableViewLike$FlatMapped
  minor version: 0
  major version: 49
  Constant pool:
Asciz	SourceFile;
Asciz	IterableViewLike.scala;
Asciz	<clinit>;
Asciz	()V;
Asciz	Code;
Asciz	serialVersionUID;
Asciz	J;
Asciz	scala/collection/IterableViewLike$FlatMapped$$anonfun$iterator$1;
class	scala/collection/IterableViewLike$FlatMapped$$anonfun$iterator$1
NameAndType	serialVersionUID:J
Field	scala/collection/IterableViewLike$FlatMapped$$anonfun$iterator$1.serialVersionUID:J
Asciz	$outer;
Asciz	Lscala/collection/IterableViewLike$FlatMapped;;
Asciz	<init>;
Asciz	(Lscala/collection/IterableViewLike$FlatMapped;)V;
Asciz	LineNumberTable;
Asciz	java/lang/NullPointerException;
class	java/lang/NullPointerException
NameAndType	"<init>":()V
Method	java/lang/NullPointerException."<init>":()V
NameAndType	$outer:Lscala/collection/IterableViewLike$FlatMapped;
Field	scala/collection/IterableViewLike$FlatMapped$$anonfun$iterator$1.$outer:Lscala/collection/IterableViewLike$FlatMapped;
Asciz	java/lang/Object;
class	java/lang/Object
Method	java/lang/Object."<init>":()V
Asciz	scala/Function1$class;
class	scala/Function1$class
Asciz	$init$;
Asciz	(Lscala/Function1;)V;
NameAndType	$init$:(Lscala/Function1;)V
Method	scala/Function1$class.$init$:(Lscala/Function1;)V
Asciz	this;
Asciz	Lscala/collection/IterableViewLike$FlatMapped$$anonfun$iterator$1;;
Asciz	LocalVariableTable;
Asciz	(Lscala/collection/IterableViewLike<TA;TColl;TThis;>.FlatMapped<TB;>;)V;
Asciz	Signature;
Asciz	apply;
Asciz	(Ljava/lang/Object;)Ljava/lang/Object;;
Asciz	(Ljava/lang/Object;)Lscala/collection/Iterator;;
NameAndType	apply:(Ljava/lang/Object;)Lscala/collection/Iterator;
Method	scala/collection/IterableViewLike$FlatMapped$$anonfun$iterator$1.apply:(Ljava/lang/Object;)Lscala/collection/Iterator;
Asciz	v1;
Asciz	Ljava/lang/Object;;
Asciz	scala/collection/TraversableViewLike$FlatMapped;
class	scala/collection/TraversableViewLike$FlatMapped
Asciz	mapping;
Asciz	()Lscala/Function1;;
NameAndType	mapping:()Lscala/Function1;
InterfaceMethod	scala/collection/TraversableViewLike$FlatMapped.mapping:()Lscala/Function1;
Asciz	scala/Function1;
class	scala/Function1
NameAndType	apply:(Ljava/lang/Object;)Ljava/lang/Object;
InterfaceMethod	scala/Function1.apply:(Ljava/lang/Object;)Ljava/lang/Object;
Asciz	scala/collection/TraversableLike;
class	scala/collection/TraversableLike
Asciz	toIterable;
Asciz	()Lscala/collection/Iterable;;
NameAndType	toIterable:()Lscala/collection/Iterable;
InterfaceMethod	scala/collection/TraversableLike.toIterable:()Lscala/collection/Iterable;
Asciz	scala/collection/IterableLike;
class	scala/collection/IterableLike
Asciz	iterator;
Asciz	()Lscala/collection/Iterator;;
NameAndType	iterator:()Lscala/collection/Iterator;
InterfaceMethod	scala/collection/IterableLike.iterator:()Lscala/collection/Iterator;
Asciz	(TA;)Lscala/collection/Iterator<TB;>;;
Asciz	andThen;
Asciz	(Lscala/Function1;)Lscala/Function1;;
Asciz	(Lscala/Function1;Lscala/Function1;)Lscala/Function1;;
NameAndType	andThen:(Lscala/Function1;Lscala/Function1;)Lscala/Function1;
Method	scala/Function1$class.andThen:(Lscala/Function1;Lscala/Function1;)Lscala/Function1;
Asciz	g;
Asciz	Lscala/Function1;;
Asciz	compose;
NameAndType	compose:(Lscala/Function1;Lscala/Function1;)Lscala/Function1;
Method	scala/Function1$class.compose:(Lscala/Function1;Lscala/Function1;)Lscala/Function1;
Asciz	toString;
Asciz	()Ljava/lang/String;;
Asciz	(Lscala/Function1;)Ljava/lang/String;;
NameAndType	toString:(Lscala/Function1;)Ljava/lang/String;
Method	scala/Function1$class.toString:(Lscala/Function1;)Ljava/lang/String;
Asciz	Scala;
Asciz	InnerClasses;
Asciz	scala/collection/IterableViewLike$FlatMapped;
class	scala/collection/IterableViewLike$FlatMapped
Asciz	scala/collection/IterableViewLike;
class	scala/collection/IterableViewLike
Asciz	FlatMapped;
Asciz	scala/collection/TraversableViewLike;
class	scala/collection/TraversableViewLike
Asciz	$anonfun$iterator$1;
Asciz	scala/ScalaObject;
class	scala/ScalaObject
Asciz	java/io/Serializable;
class	java/io/Serializable

{
public static final long serialVersionUID;
  Signature: J

private final scala.collection.IterableViewLike$FlatMapped $outer;
  Signature: Lscala/collection/IterableViewLike$FlatMapped;

public static {};
  Signature: ()V
  Code:
   Stack=2, Locals=0, Args_size=0
	lconst_0
	putstatic	Field serialVersionUID:J
	return
  Labels:

public scala.collection.IterableViewLike$FlatMapped$$anonfun$iterator$1(scala.collection.IterableViewLike$FlatMapped);
  Signature: (Lscala/collection/IterableViewLike$FlatMapped;)V
  Code:
   Stack=2, Locals=2, Args_size=2
	aload_1
	ifnonnull	l1 // aload_0
	new	class java/lang/NullPointerException
	dup
	invokespecial	Method java/lang/NullPointerException."<init>":()V
	athrow
l1	aload_0
	aload_1
	putfield	Field $outer:Lscala/collection/IterableViewLike$FlatMapped;
	aload_0
	invokespecial	Method java/lang/Object."<init>":()V
	aload_0
	invokestatic	Method scala/Function1$class.$init$:(Lscala/Function1;)V
	return
  Labels:
   	l1 = 12 // aload_0
  LocalVariableTable: 
   Start  Length  Slot  Name   Signature
   0      26      0    this       Lscala/collection/IterableViewLike$FlatMapped$$anonfun$iterator$1;
   0      26      1    $outer       Lscala/collection/IterableViewLike$FlatMapped;

  Signature: length = 0x2
   00 23 

public final java.lang.Object apply(java.lang.Object);
  Signature: (Ljava/lang/Object;)Ljava/lang/Object;
  Code:
   Stack=2, Locals=3, Args_size=2
	aload_0
	getfield	Field $outer:Lscala/collection/IterableViewLike$FlatMapped;
	astore_2
	aload_0
	aload_1
	invokevirtual	Method apply:(Ljava/lang/Object;)Lscala/collection/Iterator;
	areturn
  Labels:
  LocalVariableTable: 
   Start  Length  Slot  Name   Signature
   0      11      0    this       Lscala/collection/IterableViewLike$FlatMapped$$anonfun$iterator$1;
   5      6      1    v1       Ljava/lang/Object;


public final scala.collection.Iterator apply(java.lang.Object);
  Signature: (Ljava/lang/Object;)Lscala/collection/Iterator;
  Code:
   Stack=2, Locals=3, Args_size=2
	aload_0
	getfield	Field $outer:Lscala/collection/IterableViewLike$FlatMapped;
	astore_2
	aload_0
	getfield	Field $outer:Lscala/collection/IterableViewLike$FlatMapped;
	invokeinterface	InterfaceMethod scala/collection/TraversableViewLike$FlatMapped.mapping:()Lscala/Function1;
	aload_1
	invokeinterface	InterfaceMethod scala/Function1.apply:(Ljava/lang/Object;)Ljava/lang/Object;
	checkcast	class scala/collection/TraversableLike
	invokeinterface	InterfaceMethod scala/collection/TraversableLike.toIterable:()Lscala/collection/Iterable;
	invokeinterface	InterfaceMethod scala/collection/IterableLike.iterator:()Lscala/collection/Iterator;
	areturn
  Labels:
  LocalVariableTable: 
   Start  Length  Slot  Name   Signature
   0      34      0    this       Lscala/collection/IterableViewLike$FlatMapped$$anonfun$iterator$1;

  Signature: length = 0x2
   00 42 

public scala.Function1 andThen(scala.Function1);
  Signature: (Lscala/Function1;)Lscala/Function1;
  Code:
   Stack=2, Locals=2, Args_size=2
	aload_0
	aload_1
	invokestatic	Method scala/Function1$class.andThen:(Lscala/Function1;Lscala/Function1;)Lscala/Function1;
	areturn
  Labels:
  LocalVariableTable: 
   Start  Length  Slot  Name   Signature
   0      6      0    this       Lscala/collection/IterableViewLike$FlatMapped$$anonfun$iterator$1;
   0      6      1    g       Lscala/Function1;


public scala.Function1 compose(scala.Function1);
  Signature: (Lscala/Function1;)Lscala/Function1;
  Code:
   Stack=2, Locals=2, Args_size=2
	aload_0
	aload_1
	invokestatic	Method scala/Function1$class.compose:(Lscala/Function1;Lscala/Function1;)Lscala/Function1;
	areturn
  Labels:
  LocalVariableTable: 
   Start  Length  Slot  Name   Signature
   0      6      0    this       Lscala/collection/IterableViewLike$FlatMapped$$anonfun$iterator$1;
   0      6      1    g       Lscala/Function1;


public java.lang.String toString();
  Signature: ()Ljava/lang/String;
  Code:
   Stack=1, Locals=1, Args_size=1
	aload_0
	invokestatic	Method scala/Function1$class.toString:(Lscala/Function1;)Ljava/lang/String;
	areturn
  Labels:

}

