Compiled from "IterableViewLike.scala"
public abstract class scala.collection.IterableViewLike$DroppedWhile$class extends java.lang.Object
  SourceFile: "IterableViewLike.scala"
  Scala: length = 0x
   
  InnerClass: 
   public abstract #39= #13 of #38; //DroppedWhile=class scala/collection/IterableViewLike$DroppedWhile of class scala/collection/IterableViewLike
   public abstract #39= #24 of #41; //DroppedWhile=class scala/collection/TraversableViewLike$DroppedWhile of class scala/collection/TraversableViewLike
  minor version: 0
  major version: 49
  Constant pool:
const #1 = Asciz	SourceFile;
const #2 = Asciz	IterableViewLike.scala;
const #3 = Asciz	$init$;
const #4 = Asciz	(Lscala/collection/IterableViewLike$DroppedWhile;)V;
const #5 = Asciz	Code;
const #6 = Asciz	LineNumberTable;
const #7 = Asciz	$this;
const #8 = Asciz	Lscala/collection/IterableViewLike$DroppedWhile;;
const #9 = Asciz	LocalVariableTable;
const #10 = Asciz	iterator;
const #11 = Asciz	(Lscala/collection/IterableViewLike$DroppedWhile;)Lscala/collection/Iterator;;
const #12 = Asciz	scala/collection/IterableViewLike$DroppedWhile;
const #13 = class	#12;	//  scala/collection/IterableViewLike$DroppedWhile
const #14 = Asciz	scala$collection$IterableViewLike$DroppedWhile$$$outer;
const #15 = Asciz	()Lscala/collection/IterableViewLike;;
const #16 = NameAndType	#14:#15;//  scala$collection$IterableViewLike$DroppedWhile$$$outer:()Lscala/collection/IterableViewLike;
const #17 = InterfaceMethod	#13.#16;	//  scala/collection/IterableViewLike$DroppedWhile.scala$collection$IterableViewLike$DroppedWhile$$$outer:()Lscala/collection/IterableViewLike;
const #18 = Asciz	scala/collection/IterableLike;
const #19 = class	#18;	//  scala/collection/IterableLike
const #20 = Asciz	()Lscala/collection/Iterator;;
const #21 = NameAndType	#10:#20;//  iterator:()Lscala/collection/Iterator;
const #22 = InterfaceMethod	#19.#21;	//  scala/collection/IterableLike.iterator:()Lscala/collection/Iterator;
const #23 = Asciz	scala/collection/TraversableViewLike$DroppedWhile;
const #24 = class	#23;	//  scala/collection/TraversableViewLike$DroppedWhile
const #25 = Asciz	pred;
const #26 = Asciz	()Lscala/Function1;;
const #27 = NameAndType	#25:#26;//  pred:()Lscala/Function1;
const #28 = InterfaceMethod	#24.#27;	//  scala/collection/TraversableViewLike$DroppedWhile.pred:()Lscala/Function1;
const #29 = Asciz	scala/collection/Iterator;
const #30 = class	#29;	//  scala/collection/Iterator
const #31 = Asciz	dropWhile;
const #32 = Asciz	(Lscala/Function1;)Lscala/collection/Iterator;;
const #33 = NameAndType	#31:#32;//  dropWhile:(Lscala/Function1;)Lscala/collection/Iterator;
const #34 = InterfaceMethod	#30.#33;	//  scala/collection/Iterator.dropWhile:(Lscala/Function1;)Lscala/collection/Iterator;
const #35 = Asciz	Scala;
const #36 = Asciz	InnerClasses;
const #37 = Asciz	scala/collection/IterableViewLike;
const #38 = class	#37;	//  scala/collection/IterableViewLike
const #39 = Asciz	DroppedWhile;
const #40 = Asciz	scala/collection/TraversableViewLike;
const #41 = class	#40;	//  scala/collection/TraversableViewLike
const #42 = Asciz	scala/collection/IterableViewLike$DroppedWhile$class;
const #43 = class	#42;	//  scala/collection/IterableViewLike$DroppedWhile$class
const #44 = Asciz	java/lang/Object;
const #45 = class	#44;	//  java/lang/Object

{
public static void $init$(scala.collection.IterableViewLike$DroppedWhile);
  Code:
   Stack=0, Locals=1, Args_size=1
   0:	return
  LineNumberTable: 
   line 56: 0

  LocalVariableTable: 
   Start  Length  Slot  Name   Signature
   0      1      0    $this       Lscala/collection/IterableViewLike$DroppedWhile;


public static scala.collection.Iterator iterator(scala.collection.IterableViewLike$DroppedWhile);
  Code:
   Stack=2, Locals=1, Args_size=1
   0:	aload_0
   1:	invokeinterface	#17,  1; //InterfaceMethod scala/collection/IterableViewLike$DroppedWhile.scala$collection$IterableViewLike$DroppedWhile$$$outer:()Lscala/collection/IterableViewLike;
   6:	invokeinterface	#22,  1; //InterfaceMethod scala/collection/IterableLike.iterator:()Lscala/collection/Iterator;
   11:	aload_0
   12:	invokeinterface	#28,  1; //InterfaceMethod scala/collection/TraversableViewLike$DroppedWhile.pred:()Lscala/Function1;
   17:	invokeinterface	#34,  2; //InterfaceMethod scala/collection/Iterator.dropWhile:(Lscala/Function1;)Lscala/collection/Iterator;
   22:	areturn
  LineNumberTable: 
   line 57: 0

  LocalVariableTable: 
   Start  Length  Slot  Name   Signature
   0      23      0    $this       Lscala/collection/IterableViewLike$DroppedWhile;


}

