Compiled from "Iterator.scala"
public final class scala.collection.Iterator$WithFilter extends java.lang.Object implements scala.ScalaObject
  SourceFile: "Iterator.scala"
  Scala: length = 0x
   
  InnerClass: 
   public final #93= #12 of #47; //WithFilter=class scala/collection/Iterator$WithFilter of class scala/collection/Iterator
   public final #94= #87 of #12; //$anon$23=class scala/collection/Iterator$WithFilter$$anon$23 of class scala/collection/Iterator$WithFilter
   public final #95= #81 of #12; //$anon$24=class scala/collection/Iterator$WithFilter$$anon$24 of class scala/collection/Iterator$WithFilter
   public final #96= #36 of #12; //$anonfun$withFilter$1=class scala/collection/Iterator$WithFilter$$anonfun$withFilter$1 of class scala/collection/Iterator$WithFilter
  minor version: 0
  major version: 49
  Constant pool:
const #1 = Asciz	SourceFile;
const #2 = Asciz	Iterator.scala;
const #3 = Asciz	$outer;
const #4 = Asciz	Lscala/collection/Iterator;;
const #5 = Asciz	scala$collection$Iterator$WithFilter$$p;
const #6 = Asciz	Lscala/Function1;;
const #7 = Asciz	<init>;
const #8 = Asciz	(Lscala/collection/Iterator;Lscala/Function1;)V;
const #9 = Asciz	Code;
const #10 = Asciz	LineNumberTable;
const #11 = Asciz	scala/collection/Iterator$WithFilter;
const #12 = class	#11;	//  scala/collection/Iterator$WithFilter
const #13 = NameAndType	#5:#6;//  scala$collection$Iterator$WithFilter$$p:Lscala/Function1;
const #14 = Field	#12.#13;	//  scala/collection/Iterator$WithFilter.scala$collection$Iterator$WithFilter$$p:Lscala/Function1;
const #15 = Asciz	java/lang/NullPointerException;
const #16 = class	#15;	//  java/lang/NullPointerException
const #17 = Asciz	()V;
const #18 = NameAndType	#7:#17;//  "<init>":()V
const #19 = Method	#16.#18;	//  java/lang/NullPointerException."<init>":()V
const #20 = NameAndType	#3:#4;//  $outer:Lscala/collection/Iterator;
const #21 = Field	#12.#20;	//  scala/collection/Iterator$WithFilter.$outer:Lscala/collection/Iterator;
const #22 = Asciz	java/lang/Object;
const #23 = class	#22;	//  java/lang/Object
const #24 = Method	#23.#18;	//  java/lang/Object."<init>":()V
const #25 = Asciz	this;
const #26 = Asciz	Lscala/collection/Iterator$WithFilter;;
const #27 = Asciz	p;
const #28 = Asciz	LocalVariableTable;
const #29 = Asciz	(Lscala/collection/Iterator<TA;>;Lscala/Function1<TA;Ljava/lang/Boolean;>;)V;
const #30 = Asciz	Signature;
const #31 = Asciz	scala$collection$Iterator$WithFilter$$$outer;
const #32 = Asciz	()Lscala/collection/Iterator;;
const #33 = Asciz	withFilter;
const #34 = Asciz	(Lscala/Function1;)Lscala/collection/Iterator$WithFilter;;
const #35 = Asciz	scala/collection/Iterator$WithFilter$$anonfun$withFilter$1;
const #36 = class	#35;	//  scala/collection/Iterator$WithFilter$$anonfun$withFilter$1
const #37 = Asciz	(Lscala/collection/Iterator$WithFilter;Lscala/Function1;)V;
const #38 = NameAndType	#7:#37;//  "<init>":(Lscala/collection/Iterator$WithFilter;Lscala/Function1;)V
const #39 = Method	#36.#38;	//  scala/collection/Iterator$WithFilter$$anonfun$withFilter$1."<init>":(Lscala/collection/Iterator$WithFilter;Lscala/Function1;)V
const #40 = NameAndType	#7:#8;//  "<init>":(Lscala/collection/Iterator;Lscala/Function1;)V
const #41 = Method	#12.#40;	//  scala/collection/Iterator$WithFilter."<init>":(Lscala/collection/Iterator;Lscala/Function1;)V
const #42 = Asciz	q$1;
const #43 = Asciz	(Lscala/Function1<TA;Ljava/lang/Boolean;>;)Lscala/collection/Iterator<TA;>.WithFilter;;
const #44 = Asciz	foreach;
const #45 = Asciz	(Lscala/Function1;)V;
const #46 = Asciz	scala/collection/Iterator;
const #47 = class	#46;	//  scala/collection/Iterator
const #48 = Asciz	hasNext;
const #49 = Asciz	()Z;
const #50 = NameAndType	#48:#49;//  hasNext:()Z
const #51 = InterfaceMethod	#47.#50;	//  scala/collection/Iterator.hasNext:()Z
const #52 = Asciz	next;
const #53 = Asciz	()Ljava/lang/Object;;
const #54 = NameAndType	#52:#53;//  next:()Ljava/lang/Object;
const #55 = InterfaceMethod	#47.#54;	//  scala/collection/Iterator.next:()Ljava/lang/Object;
const #56 = Asciz	scala/Function1;
const #57 = class	#56;	//  scala/Function1
const #58 = Asciz	apply;
const #59 = Asciz	(Ljava/lang/Object;)Ljava/lang/Object;;
const #60 = NameAndType	#58:#59;//  apply:(Ljava/lang/Object;)Ljava/lang/Object;
const #61 = InterfaceMethod	#57.#60;	//  scala/Function1.apply:(Ljava/lang/Object;)Ljava/lang/Object;
const #62 = Asciz	scala/runtime/BoxesRunTime;
const #63 = class	#62;	//  scala/runtime/BoxesRunTime
const #64 = Asciz	unboxToBoolean;
const #65 = Asciz	(Ljava/lang/Object;)Z;
const #66 = NameAndType	#64:#65;//  unboxToBoolean:(Ljava/lang/Object;)Z
const #67 = Method	#63.#66;	//  scala/runtime/BoxesRunTime.unboxToBoolean:(Ljava/lang/Object;)Z
const #68 = Asciz	scala/runtime/BoxedUnit;
const #69 = class	#68;	//  scala/runtime/BoxedUnit
const #70 = Asciz	UNIT;
const #71 = Asciz	Lscala/runtime/BoxedUnit;;
const #72 = NameAndType	#70:#71;//  UNIT:Lscala/runtime/BoxedUnit;
const #73 = Field	#69.#72;	//  scala/runtime/BoxedUnit.UNIT:Lscala/runtime/BoxedUnit;
const #74 = Asciz	f;
const #75 = Asciz	x;
const #76 = Asciz	Ljava/lang/Object;;
const #77 = Asciz	<U:Ljava/lang/Object;>(Lscala/Function1<TA;TU;>;)V;
const #78 = Asciz	flatMap;
const #79 = Asciz	(Lscala/Function1;)Lscala/collection/Iterator;;
const #80 = Asciz	scala/collection/Iterator$WithFilter$$anon$24;
const #81 = class	#80;	//  scala/collection/Iterator$WithFilter$$anon$24
const #82 = Method	#81.#38;	//  scala/collection/Iterator$WithFilter$$anon$24."<init>":(Lscala/collection/Iterator$WithFilter;Lscala/Function1;)V
const #83 = Asciz	f$6;
const #84 = Asciz	<B:Ljava/lang/Object;>(Lscala/Function1<TA;Lscala/collection/Iterator<TB;>;>;)Lscala/collection/Iterator<TB;>;;
const #85 = Asciz	map;
const #86 = Asciz	scala/collection/Iterator$WithFilter$$anon$23;
const #87 = class	#86;	//  scala/collection/Iterator$WithFilter$$anon$23
const #88 = Method	#87.#38;	//  scala/collection/Iterator$WithFilter$$anon$23."<init>":(Lscala/collection/Iterator$WithFilter;Lscala/Function1;)V
const #89 = Asciz	f$5;
const #90 = Asciz	<B:Ljava/lang/Object;>(Lscala/Function1<TA;TB;>;)Lscala/collection/Iterator<TB;>;;
const #91 = Asciz	Scala;
const #92 = Asciz	InnerClasses;
const #93 = Asciz	WithFilter;
const #94 = Asciz	$anon$23;
const #95 = Asciz	$anon$24;
const #96 = Asciz	$anonfun$withFilter$1;
const #97 = Asciz	scala/ScalaObject;
const #98 = class	#97;	//  scala/ScalaObject

{
public final scala.collection.Iterator $outer;

public final scala.Function1 scala$collection$Iterator$WithFilter$$p;

public scala.collection.Iterator$WithFilter(scala.collection.Iterator, scala.Function1);
  Code:
   Stack=2, Locals=3, Args_size=3
   0:	aload_0
   1:	aload_2
   2:	putfield	#14; //Field scala$collection$Iterator$WithFilter$$p:Lscala/Function1;
   5:	aload_1
   6:	ifnonnull	17
   9:	new	#16; //class java/lang/NullPointerException
   12:	dup
   13:	invokespecial	#19; //Method java/lang/NullPointerException."<init>":()V
   16:	athrow
   17:	aload_0
   18:	aload_1
   19:	putfield	#21; //Field $outer:Lscala/collection/Iterator;
   22:	aload_0
   23:	invokespecial	#24; //Method java/lang/Object."<init>":()V
   26:	return
  LineNumberTable: 
   line 372: 0

  LocalVariableTable: 
   Start  Length  Slot  Name   Signature
   0      27      0    this       Lscala/collection/Iterator$WithFilter;
   0      27      1    $outer       Lscala/collection/Iterator;
   0      27      2    p       Lscala/Function1;

  Signature: length = 0x2
   00 1D 

public scala.collection.Iterator scala$collection$Iterator$WithFilter$$$outer();
  Code:
   Stack=1, Locals=1, Args_size=1
   0:	aload_0
   1:	getfield	#21; //Field $outer:Lscala/collection/Iterator;
   4:	areturn
  LineNumberTable: 
   line 372: 0


public scala.collection.Iterator$WithFilter withFilter(scala.Function1);
  Code:
   Stack=7, Locals=2, Args_size=2
   0:	new	#12; //class scala/collection/Iterator$WithFilter
   3:	dup
   4:	aload_0
   5:	getfield	#21; //Field $outer:Lscala/collection/Iterator;
   8:	new	#36; //class scala/collection/Iterator$WithFilter$$anonfun$withFilter$1
   11:	dup
   12:	aload_0
   13:	aload_1
   14:	invokespecial	#39; //Method scala/collection/Iterator$WithFilter$$anonfun$withFilter$1."<init>":(Lscala/collection/Iterator$WithFilter;Lscala/Function1;)V
   17:	invokespecial	#41; //Method "<init>":(Lscala/collection/Iterator;Lscala/Function1;)V
   20:	areturn
  LineNumberTable: 
   line 414: 0

  LocalVariableTable: 
   Start  Length  Slot  Name   Signature
   0      21      0    this       Lscala/collection/Iterator$WithFilter;
   0      21      1    q$1       Lscala/Function1;

  Signature: length = 0x2
   00 2B 

public void foreach(scala.Function1);
  Code:
   Stack=2, Locals=3, Args_size=2
   0:	aload_0
   1:	getfield	#21; //Field $outer:Lscala/collection/Iterator;
   4:	invokeinterface	#51,  1; //InterfaceMethod scala/collection/Iterator.hasNext:()Z
   9:	ifeq	55
   12:	aload_0
   13:	getfield	#21; //Field $outer:Lscala/collection/Iterator;
   16:	invokeinterface	#55,  1; //InterfaceMethod scala/collection/Iterator.next:()Ljava/lang/Object;
   21:	astore_2
   22:	aload_0
   23:	getfield	#14; //Field scala$collection$Iterator$WithFilter$$p:Lscala/Function1;
   26:	aload_2
   27:	invokeinterface	#61,  2; //InterfaceMethod scala/Function1.apply:(Ljava/lang/Object;)Ljava/lang/Object;
   32:	invokestatic	#67; //Method scala/runtime/BoxesRunTime.unboxToBoolean:(Ljava/lang/Object;)Z
   35:	ifeq	48
   38:	aload_1
   39:	aload_2
   40:	invokeinterface	#61,  2; //InterfaceMethod scala/Function1.apply:(Ljava/lang/Object;)Ljava/lang/Object;
   45:	goto	51
   48:	getstatic	#73; //Field scala/runtime/BoxedUnit.UNIT:Lscala/runtime/BoxedUnit;
   51:	pop
   52:	goto	0
   55:	return
  LineNumberTable: 
   line 408: 0
   line 409: 12
   line 410: 22
   line 408: 55

  LocalVariableTable: 
   Start  Length  Slot  Name   Signature
   0      56      0    this       Lscala/collection/Iterator$WithFilter;
   0      56      1    f       Lscala/Function1;
   22      30      2    x       Ljava/lang/Object;

  Signature: length = 0x2
   00 4D 

public scala.collection.Iterator flatMap(scala.Function1);
  Code:
   Stack=4, Locals=2, Args_size=2
   0:	new	#81; //class scala/collection/Iterator$WithFilter$$anon$24
   3:	dup
   4:	aload_0
   5:	aload_1
   6:	invokespecial	#82; //Method scala/collection/Iterator$WithFilter$$anon$24."<init>":(Lscala/collection/Iterator$WithFilter;Lscala/Function1;)V
   9:	areturn
  LineNumberTable: 
   line 390: 0

  LocalVariableTable: 
   Start  Length  Slot  Name   Signature
   0      10      0    this       Lscala/collection/Iterator$WithFilter;
   0      10      1    f$6       Lscala/Function1;

  Signature: length = 0x2
   00 54 

public scala.collection.Iterator map(scala.Function1);
  Code:
   Stack=4, Locals=2, Args_size=2
   0:	new	#87; //class scala/collection/Iterator$WithFilter$$anon$23
   3:	dup
   4:	aload_0
   5:	aload_1
   6:	invokespecial	#88; //Method scala/collection/Iterator$WithFilter$$anon$23."<init>":(Lscala/collection/Iterator$WithFilter;Lscala/Function1;)V
   9:	areturn
  LineNumberTable: 
   line 374: 0

  LocalVariableTable: 
   Start  Length  Slot  Name   Signature
   0      10      0    this       Lscala/collection/Iterator$WithFilter;
   0      10      1    f$5       Lscala/Function1;

  Signature: length = 0x2
   00 5A 

}

