Compiled from "Iterable.scala"
public final class scala.collection.Iterable$ extends scala.collection.generic.TraversableFactory implements scala.ScalaObject
  SourceFile: "Iterable.scala"
  Scala: length = 0x
   
  Signature: length = 0x2
   00 38 
  InnerClass: 
   public GenericCanBuildFrom=class scala/collection/generic/TraversableFactory$GenericCanBuildFrom of class scala/collection/generic/TraversableFactory
  minor version: 0
  major version: 49
  Constant pool:
Asciz	SourceFile;
Asciz	Iterable.scala;
Asciz	Scala;
Asciz	MODULE$;
Asciz	Lscala/collection/Iterable$;;
Asciz	<clinit>;
Asciz	()V;
Asciz	Code;
Asciz	scala/collection/Iterable$;
class	scala/collection/Iterable$
Asciz	<init>;
NameAndType	"<init>":()V
Method	scala/collection/Iterable$."<init>":()V
Asciz	LineNumberTable;
Asciz	scala/collection/generic/TraversableFactory;
class	scala/collection/generic/TraversableFactory
Method	scala/collection/generic/TraversableFactory."<init>":()V
NameAndType	MODULE$:Lscala/collection/Iterable$;
Field	scala/collection/Iterable$.MODULE$:Lscala/collection/Iterable$;
Asciz	max;
Asciz	(Lscala/collection/Iterable;Lscala/math/Ordering;)Ljava/lang/Object;;
Asciz	scala/collection/TraversableLike;
class	scala/collection/TraversableLike
Asciz	(Lscala/math/Ordering;)Ljava/lang/Object;;
NameAndType	max:(Lscala/math/Ordering;)Ljava/lang/Object;
InterfaceMethod	scala/collection/TraversableLike.max:(Lscala/math/Ordering;)Ljava/lang/Object;
Asciz	this;
Asciz	seq;
Asciz	Lscala/collection/Iterable;;
Asciz	ord;
Asciz	Lscala/math/Ordering;;
Asciz	LocalVariableTable;
Asciz	<A:Ljava/lang/Object;>(Lscala/collection/Iterable<TA;>;Lscala/math/Ordering<TA;>;)TA;;
Asciz	Signature;
Asciz	min;
NameAndType	min:(Lscala/math/Ordering;)Ljava/lang/Object;
InterfaceMethod	scala/collection/TraversableLike.min:(Lscala/math/Ordering;)Ljava/lang/Object;
Asciz	newBuilder;
Asciz	()Lscala/collection/mutable/Builder;;
Asciz	scala/collection/immutable/Iterable$;
class	scala/collection/immutable/Iterable$
Asciz	Lscala/collection/immutable/Iterable$;;
NameAndType	MODULE$:Lscala/collection/immutable/Iterable$;
Field	scala/collection/immutable/Iterable$.MODULE$:Lscala/collection/immutable/Iterable$;
NameAndType	newBuilder:()Lscala/collection/mutable/Builder;
Method	scala/collection/immutable/Iterable$.newBuilder:()Lscala/collection/mutable/Builder;
Asciz	<A:Ljava/lang/Object;>()Lscala/collection/mutable/Builder<TA;Lscala/collection/Iterable<TA;>;>;;
Asciz	canBuildFrom;
Asciz	()Lscala/collection/generic/CanBuildFrom;;
Asciz	scala/collection/generic/TraversableFactory$GenericCanBuildFrom;
class	scala/collection/generic/TraversableFactory$GenericCanBuildFrom
Asciz	(Lscala/collection/generic/TraversableFactory;)V;
NameAndType	"<init>":(Lscala/collection/generic/TraversableFactory;)V
Method	scala/collection/generic/TraversableFactory$GenericCanBuildFrom."<init>":(Lscala/collection/generic/TraversableFactory;)V
Asciz	<A:Ljava/lang/Object;>()Lscala/collection/generic/CanBuildFrom<Lscala/collection/Iterable<*>;TA;Lscala/collection/Iterable<TA;>;>;;
Asciz	Lscala/collection/generic/TraversableFactory<Lscala/collection/Iterable;>;Lscala/ScalaObject;;
Asciz	InnerClasses;
Asciz	GenericCanBuildFrom;
Asciz	scala/ScalaObject;
class	scala/ScalaObject

{
public static final scala.collection.Iterable$ MODULE$;
  Signature: Lscala/collection/Iterable$;

public static {};
  Signature: ()V
  Code:
   Stack=1, Locals=0, Args_size=0
	new	class scala/collection/Iterable$
	invokespecial	Method "<init>":()V
	return
  Labels:

private scala.collection.Iterable$();
  Signature: ()V
  Code:
   Stack=1, Locals=1, Args_size=1
	aload_0
	invokespecial	Method scala/collection/generic/TraversableFactory."<init>":()V
	aload_0
	putstatic	Field MODULE$:Lscala/collection/Iterable$;
	return
  Labels:

public java.lang.Object max(scala.collection.Iterable, scala.math.Ordering);
  Signature: (Lscala/collection/Iterable;Lscala/math/Ordering;)Ljava/lang/Object;
  Code:
   Stack=2, Locals=3, Args_size=3
	aload_1
	aload_2
	invokeinterface	InterfaceMethod scala/collection/TraversableLike.max:(Lscala/math/Ordering;)Ljava/lang/Object;
	areturn
  Labels:
  LocalVariableTable: 
   Start  Length  Slot  Name   Signature
   0      8      0    this       Lscala/collection/Iterable$;
   0      8      1    seq       Lscala/collection/Iterable;
   0      8      2    ord       Lscala/math/Ordering;

  Signature: length = 0x2
   00 21 

public java.lang.Object min(scala.collection.Iterable, scala.math.Ordering);
  Signature: (Lscala/collection/Iterable;Lscala/math/Ordering;)Ljava/lang/Object;
  Code:
   Stack=2, Locals=3, Args_size=3
	aload_1
	aload_2
	invokeinterface	InterfaceMethod scala/collection/TraversableLike.min:(Lscala/math/Ordering;)Ljava/lang/Object;
	areturn
  Labels:
  LocalVariableTable: 
   Start  Length  Slot  Name   Signature
   0      8      0    this       Lscala/collection/Iterable$;
   0      8      1    seq       Lscala/collection/Iterable;
   0      8      2    ord       Lscala/math/Ordering;

  Signature: length = 0x2
   00 21 

public scala.collection.mutable.Builder newBuilder();
  Signature: ()Lscala/collection/mutable/Builder;
  Code:
   Stack=1, Locals=1, Args_size=1
	getstatic	Field scala/collection/immutable/Iterable$.MODULE$:Lscala/collection/immutable/Iterable$;
	invokevirtual	Method scala/collection/immutable/Iterable$.newBuilder:()Lscala/collection/mutable/Builder;
	areturn
  Labels:
  Signature: length = 0x2
   00 2F 

public scala.collection.generic.CanBuildFrom canBuildFrom();
  Signature: ()Lscala/collection/generic/CanBuildFrom;
  Code:
   Stack=3, Locals=1, Args_size=1
	new	class scala/collection/generic/TraversableFactory$GenericCanBuildFrom
	dup
	aload_0
	invokespecial	Method scala/collection/generic/TraversableFactory$GenericCanBuildFrom."<init>":(Lscala/collection/generic/TraversableFactory;)V
	areturn
  Labels:
  Signature: length = 0x2
   00 37 

}

