Compiled from "Iterator.scala"
public abstract class scala.collection.Iterator$class extends java.lang.Object
  SourceFile: "Iterator.scala"
  Scala: length = 0x
   
  InnerClass: 
   public final #505= #180 of #504; //Cons=class scala/collection/immutable/Stream$Cons of class scala/collection/immutable/Stream
   public final #506= #395 of #13; //$anon$6=class scala/collection/Iterator$$anon$6 of class scala/collection/Iterator
   public final #507= #372 of #13; //$anon$5=class scala/collection/Iterator$$anon$5 of class scala/collection/Iterator
   public final #508= #281 of #13; //$anon$2=class scala/collection/Iterator$$anon$2 of class scala/collection/Iterator
   public final #509= #55 of #13; //$anon$1=class scala/collection/Iterator$$anon$1 of class scala/collection/Iterator
   public final #510= #495 of #13; //$anon$18=class scala/collection/Iterator$$anon$18 of class scala/collection/Iterator
   public final #511= #475 of #13; //$anon$19=class scala/collection/Iterator$$anon$19 of class scala/collection/Iterator
   public final #512= #467 of #13; //$anon$20=class scala/collection/Iterator$$anon$20 of class scala/collection/Iterator
   public final #513= #462 of #13; //$anon$21=class scala/collection/Iterator$$anon$21 of class scala/collection/Iterator
   public final #514= #457 of #13; //$anon$22=class scala/collection/Iterator$$anon$22 of class scala/collection/Iterator
   public final #515= #435 of #13; //$anon$25=class scala/collection/Iterator$$anon$25 of class scala/collection/Iterator
   public final #516= #429 of #13; //$anon$26=class scala/collection/Iterator$$anon$26 of class scala/collection/Iterator
   public final #517= #403 of #13; //$anon$27=class scala/collection/Iterator$$anon$27 of class scala/collection/Iterator
   public final #518= #386 of #13; //$anon$28=class scala/collection/Iterator$$anon$28 of class scala/collection/Iterator
   public final #519= #381 of #13; //$anon$29=class scala/collection/Iterator$$anon$29 of class scala/collection/Iterator
   public final #520= #230 of #13; //$anon$30=class scala/collection/Iterator$$anon$30 of class scala/collection/Iterator
   public #521= #250 of #13; //Partner$1=class scala/collection/Iterator$Partner$1 of class scala/collection/Iterator
   public final #522= #454 of #13; //WithFilter=class scala/collection/Iterator$WithFilter of class scala/collection/Iterator
   public final #523= #415 of #13; //$anonfun$1=class scala/collection/Iterator$$anonfun$1 of class scala/collection/Iterator
   public #524= #266 of #13; //GroupedIterator=class scala/collection/Iterator$GroupedIterator of class scala/collection/Iterator
   public final #525= #76 of #13; //$anonfun$append$1=class scala/collection/Iterator$$anonfun$append$1 of class scala/collection/Iterator
   public #526= #412 of #13; //PartitionIterator$1=class scala/collection/Iterator$PartitionIterator$1 of class scala/collection/Iterator
   public final #527= #356 of #13; //$anonfun$contains$1=class scala/collection/Iterator$$anonfun$contains$1 of class scala/collection/Iterator
   public final #528= #177 of #13; //$anonfun$toStream$1=class scala/collection/Iterator$$anonfun$toStream$1 of class scala/collection/Iterator
   public final #529= #444 of #13; //$anonfun$filterNot$1=class scala/collection/Iterator$$anonfun$filterNot$1 of class scala/collection/Iterator
  minor version: 0
  major version: 49
  Constant pool:
const #1 = Asciz	SourceFile;
const #2 = Asciz	Iterator.scala;
const #3 = Asciz	$init$;
const #4 = Asciz	(Lscala/collection/Iterator;)V;
const #5 = Asciz	Code;
const #6 = Asciz	LineNumberTable;
const #7 = Asciz	$this;
const #8 = Asciz	Lscala/collection/Iterator;;
const #9 = Asciz	LocalVariableTable;
const #10 = Asciz	loop$1;
const #11 = Asciz	(Lscala/collection/Iterator;I)Lscala/collection/Iterator;;
const #12 = Asciz	scala/collection/Iterator;
const #13 = class	#12;	//  scala/collection/Iterator
const #14 = Asciz	hasNext;
const #15 = Asciz	()Z;
const #16 = NameAndType	#14:#15;//  hasNext:()Z
const #17 = InterfaceMethod	#13.#16;	//  scala/collection/Iterator.hasNext:()Z
const #18 = Asciz	next;
const #19 = Asciz	()Ljava/lang/Object;;
const #20 = NameAndType	#18:#19;//  next:()Ljava/lang/Object;
const #21 = InterfaceMethod	#13.#20;	//  scala/collection/Iterator.next:()Ljava/lang/Object;
const #22 = Asciz	left;
const #23 = Asciz	I;
const #24 = Asciz	readInto;
const #25 = Asciz	(Lscala/collection/Iterator;Ljava/lang/Object;)V;
const #26 = Asciz	scala/runtime/ScalaRunTime$;
const #27 = class	#26;	//  scala/runtime/ScalaRunTime$
const #28 = Asciz	MODULE$;
const #29 = Asciz	Lscala/runtime/ScalaRunTime$;;
const #30 = NameAndType	#28:#29;//  MODULE$:Lscala/runtime/ScalaRunTime$;
const #31 = Field	#27.#30;	//  scala/runtime/ScalaRunTime$.MODULE$:Lscala/runtime/ScalaRunTime$;
const #32 = Asciz	array_length;
const #33 = Asciz	(Ljava/lang/Object;)I;
const #34 = NameAndType	#32:#33;//  array_length:(Ljava/lang/Object;)I
const #35 = Method	#27.#34;	//  scala/runtime/ScalaRunTime$.array_length:(Ljava/lang/Object;)I
const #36 = Asciz	(Ljava/lang/Object;II)V;
const #37 = NameAndType	#24:#36;//  readInto:(Ljava/lang/Object;II)V
const #38 = InterfaceMethod	#13.#37;	//  scala/collection/Iterator.readInto:(Ljava/lang/Object;II)V
const #39 = Asciz	xs;
const #40 = Asciz	Ljava/lang/Object;;
const #41 = Asciz	(Lscala/collection/Iterator;Ljava/lang/Object;I)V;
const #42 = Asciz	start;
const #43 = Asciz	(Lscala/collection/Iterator;Ljava/lang/Object;II)V;
const #44 = Asciz	java/lang/reflect/Array;
const #45 = class	#44;	//  java/lang/reflect/Array
const #46 = Asciz	set;
const #47 = Asciz	(Ljava/lang/Object;ILjava/lang/Object;)V;
const #48 = NameAndType	#46:#47;//  set:(Ljava/lang/Object;ILjava/lang/Object;)V
const #49 = Method	#45.#48;	//  java/lang/reflect/Array.set:(Ljava/lang/Object;ILjava/lang/Object;)V
const #50 = Asciz	sz;
const #51 = Asciz	i;
const #52 = Asciz	counted;
const #53 = Asciz	(Lscala/collection/Iterator;)Ljava/lang/Object;;
const #54 = Asciz	scala/collection/Iterator$$anon$1;
const #55 = class	#54;	//  scala/collection/Iterator$$anon$1
const #56 = Asciz	<init>;
const #57 = NameAndType	#56:#4;//  "<init>":(Lscala/collection/Iterator;)V
const #58 = Method	#55.#57;	//  scala/collection/Iterator$$anon$1."<init>":(Lscala/collection/Iterator;)V
const #59 = Asciz	collect;
const #60 = Asciz	(Lscala/collection/Iterator;)Lscala/collection/Seq;;
const #61 = Asciz	toSeq;
const #62 = Asciz	()Lscala/collection/Seq;;
const #63 = NameAndType	#61:#62;//  toSeq:()Lscala/collection/Seq;
const #64 = InterfaceMethod	#13.#63;	//  scala/collection/Iterator.toSeq:()Lscala/collection/Seq;
const #65 = Asciz	findIndexOf;
const #66 = Asciz	(Lscala/collection/Iterator;Lscala/Function1;)I;
const #67 = Asciz	indexWhere;
const #68 = Asciz	(Lscala/Function1;)I;
const #69 = NameAndType	#67:#68;//  indexWhere:(Lscala/Function1;)I
const #70 = InterfaceMethod	#13.#69;	//  scala/collection/Iterator.indexWhere:(Lscala/Function1;)I
const #71 = Asciz	p;
const #72 = Asciz	Lscala/Function1;;
const #73 = Asciz	append;
const #74 = Asciz	(Lscala/collection/Iterator;Lscala/collection/Iterator;)Lscala/collection/Iterator;;
const #75 = Asciz	scala/collection/Iterator$$anonfun$append$1;
const #76 = class	#75;	//  scala/collection/Iterator$$anonfun$append$1
const #77 = Asciz	(Lscala/collection/Iterator;Lscala/collection/Iterator;)V;
const #78 = NameAndType	#56:#77;//  "<init>":(Lscala/collection/Iterator;Lscala/collection/Iterator;)V
const #79 = Method	#76.#78;	//  scala/collection/Iterator$$anonfun$append$1."<init>":(Lscala/collection/Iterator;Lscala/collection/Iterator;)V
const #80 = Asciz	$plus$plus;
const #81 = Asciz	(Lscala/Function0;)Lscala/collection/Iterator;;
const #82 = NameAndType	#80:#81;//  $plus$plus:(Lscala/Function0;)Lscala/collection/Iterator;
const #83 = InterfaceMethod	#13.#82;	//  scala/collection/Iterator.$plus$plus:(Lscala/Function0;)Lscala/collection/Iterator;
const #84 = Asciz	that$4;
const #85 = Asciz	toString;
const #86 = Asciz	(Lscala/collection/Iterator;)Ljava/lang/String;;
const #87 = Asciz	scala/collection/mutable/StringBuilder;
const #88 = class	#87;	//  scala/collection/mutable/StringBuilder
const #89 = Asciz	()V;
const #90 = NameAndType	#56:#89;//  "<init>":()V
const #91 = Method	#88.#90;	//  scala/collection/mutable/StringBuilder."<init>":()V
const #92 = Asciz	non-empty;
const #93 = String	#92;	//  non-empty
const #94 = Asciz	empty;
const #95 = String	#94;	//  empty
const #96 = Asciz	(Ljava/lang/Object;)Lscala/collection/mutable/StringBuilder;;
const #97 = NameAndType	#73:#96;//  append:(Ljava/lang/Object;)Lscala/collection/mutable/StringBuilder;
const #98 = Method	#88.#97;	//  scala/collection/mutable/StringBuilder.append:(Ljava/lang/Object;)Lscala/collection/mutable/StringBuilder;
const #99 = Asciz	 iterator;
const #100 = String	#99;	//   iterator
const #101 = Asciz	()Ljava/lang/String;;
const #102 = NameAndType	#85:#101;//  toString:()Ljava/lang/String;
const #103 = Method	#88.#102;	//  scala/collection/mutable/StringBuilder.toString:()Ljava/lang/String;
const #104 = Asciz	addString;
const #105 = Asciz	(Lscala/collection/Iterator;Lscala/collection/mutable/StringBuilder;)Lscala/collection/mutable/StringBuilder;;
const #106 = Asciz	;
const #107 = String	#106;	//  
const #108 = Asciz	(Lscala/collection/mutable/StringBuilder;Ljava/lang/String;Ljava/lang/String;Ljava/lang/String;)Lscala/collection/mutable/StringBuilder;;
const #109 = NameAndType	#104:#108;//  addString:(Lscala/collection/mutable/StringBuilder;Ljava/lang/String;Ljava/lang/String;Ljava/lang/String;)Lscala/collection/mutable/StringBuilder;
const #110 = InterfaceMethod	#13.#109;	//  scala/collection/Iterator.addString:(Lscala/collection/mutable/StringBuilder;Ljava/lang/String;Ljava/lang/String;Ljava/lang/String;)Lscala/collection/mutable/StringBuilder;
const #111 = Asciz	buf;
const #112 = Asciz	Lscala/collection/mutable/StringBuilder;;
const #113 = Asciz	(Lscala/collection/Iterator;Lscala/collection/mutable/StringBuilder;Ljava/lang/String;)Lscala/collection/mutable/StringBuilder;;
const #114 = Asciz	sep;
const #115 = Asciz	Ljava/lang/String;;
const #116 = Asciz	(Lscala/collection/Iterator;Lscala/collection/mutable/StringBuilder;Ljava/lang/String;Ljava/lang/String;Ljava/lang/String;)Lscala/collection/mutable/StringBuilder;;
const #117 = Asciz	(Ljava/lang/String;)Lscala/collection/mutable/StringBuilder;;
const #118 = NameAndType	#73:#117;//  append:(Ljava/lang/String;)Lscala/collection/mutable/StringBuilder;
const #119 = Method	#88.#118;	//  scala/collection/mutable/StringBuilder.append:(Ljava/lang/String;)Lscala/collection/mutable/StringBuilder;
const #120 = Asciz	java/lang/String;
const #121 = class	#120;	//  java/lang/String
const #122 = Asciz	valueOf;
const #123 = Asciz	(Ljava/lang/Object;)Ljava/lang/String;;
const #124 = NameAndType	#122:#123;//  valueOf:(Ljava/lang/Object;)Ljava/lang/String;
const #125 = Method	#121.#124;	//  java/lang/String.valueOf:(Ljava/lang/Object;)Ljava/lang/String;
const #126 = Asciz	scala/runtime/BoxedUnit;
const #127 = class	#126;	//  scala/runtime/BoxedUnit
const #128 = Asciz	UNIT;
const #129 = Asciz	Lscala/runtime/BoxedUnit;;
const #130 = NameAndType	#128:#129;//  UNIT:Lscala/runtime/BoxedUnit;
const #131 = Field	#127.#130;	//  scala/runtime/BoxedUnit.UNIT:Lscala/runtime/BoxedUnit;
const #132 = Asciz	end;
const #133 = Asciz	mkString;
const #134 = Asciz	(Ljava/lang/String;)Ljava/lang/String;;
const #135 = NameAndType	#133:#134;//  mkString:(Ljava/lang/String;)Ljava/lang/String;
const #136 = InterfaceMethod	#13.#135;	//  scala/collection/Iterator.mkString:(Ljava/lang/String;)Ljava/lang/String;
const #137 = Asciz	(Lscala/collection/Iterator;Ljava/lang/String;)Ljava/lang/String;;
const #138 = Asciz	(Ljava/lang/String;Ljava/lang/String;Ljava/lang/String;)Ljava/lang/String;;
const #139 = NameAndType	#133:#138;//  mkString:(Ljava/lang/String;Ljava/lang/String;Ljava/lang/String;)Ljava/lang/String;
const #140 = InterfaceMethod	#13.#139;	//  scala/collection/Iterator.mkString:(Ljava/lang/String;Ljava/lang/String;Ljava/lang/String;)Ljava/lang/String;
const #141 = Asciz	(Lscala/collection/Iterator;Ljava/lang/String;Ljava/lang/String;Ljava/lang/String;)Ljava/lang/String;;
const #142 = Method	#88.#90;	//  scala/collection/mutable/StringBuilder."<init>":()V
const #143 = Method	#88.#102;	//  scala/collection/mutable/StringBuilder.toString:()Ljava/lang/String;
const #144 = Asciz	sameElements;
const #145 = Asciz	(Lscala/collection/Iterator;Lscala/collection/Iterator;)Z;
const #146 = Asciz	java/lang/Number;
const #147 = class	#146;	//  java/lang/Number
const #148 = Asciz	java/lang/Character;
const #149 = class	#148;	//  java/lang/Character
const #150 = Asciz	scala/runtime/BoxesRunTime;
const #151 = class	#150;	//  scala/runtime/BoxesRunTime
const #152 = Asciz	equals2;
const #153 = Asciz	(Ljava/lang/Object;Ljava/lang/Object;)Z;
const #154 = NameAndType	#152:#153;//  equals2:(Ljava/lang/Object;Ljava/lang/Object;)Z
const #155 = Method	#151.#154;	//  scala/runtime/BoxesRunTime.equals2:(Ljava/lang/Object;Ljava/lang/Object;)Z
const #156 = Asciz	java/lang/Object;
const #157 = class	#156;	//  java/lang/Object
const #158 = Asciz	equals;
const #159 = Asciz	(Ljava/lang/Object;)Z;
const #160 = NameAndType	#158:#159;//  equals:(Ljava/lang/Object;)Z
const #161 = Method	#157.#160;	//  java/lang/Object.equals:(Ljava/lang/Object;)Z
const #162 = Asciz	that;
const #163 = Asciz	x0;
const #164 = Asciz	y0;
const #165 = Asciz	scala/collection/mutable/ArrayBuffer;
const #166 = class	#165;	//  scala/collection/mutable/ArrayBuffer
const #167 = Method	#166.#90;	//  scala/collection/mutable/ArrayBuffer."<init>":()V
const #168 = Asciz	copyToBuffer;
const #169 = Asciz	(Lscala/collection/mutable/Buffer;)V;
const #170 = NameAndType	#168:#169;//  copyToBuffer:(Lscala/collection/mutable/Buffer;)V
const #171 = InterfaceMethod	#13.#170;	//  scala/collection/Iterator.copyToBuffer:(Lscala/collection/mutable/Buffer;)V
const #172 = Asciz	buffer;
const #173 = Asciz	Lscala/collection/mutable/ArrayBuffer;;
const #174 = Asciz	toStream;
const #175 = Asciz	(Lscala/collection/Iterator;)Lscala/collection/immutable/Stream;;
const #176 = Asciz	scala/collection/Iterator$$anonfun$toStream$1;
const #177 = class	#176;	//  scala/collection/Iterator$$anonfun$toStream$1
const #178 = Method	#177.#57;	//  scala/collection/Iterator$$anonfun$toStream$1."<init>":(Lscala/collection/Iterator;)V
const #179 = Asciz	scala/collection/immutable/Stream$Cons;
const #180 = class	#179;	//  scala/collection/immutable/Stream$Cons
const #181 = Asciz	(Ljava/lang/Object;Lscala/Function0;)V;
const #182 = NameAndType	#56:#181;//  "<init>":(Ljava/lang/Object;Lscala/Function0;)V
const #183 = Method	#180.#182;	//  scala/collection/immutable/Stream$Cons."<init>":(Ljava/lang/Object;Lscala/Function0;)V
const #184 = Asciz	scala/collection/immutable/Stream$Empty$;
const #185 = class	#184;	//  scala/collection/immutable/Stream$Empty$
const #186 = Asciz	Lscala/collection/immutable/Stream$Empty$;;
const #187 = NameAndType	#28:#186;//  MODULE$:Lscala/collection/immutable/Stream$Empty$;
const #188 = Field	#185.#187;	//  scala/collection/immutable/Stream$Empty$.MODULE$:Lscala/collection/immutable/Stream$Empty$;
const #189 = Asciz	toList;
const #190 = Asciz	(Lscala/collection/Iterator;)Lscala/collection/immutable/List;;
const #191 = Asciz	scala/collection/mutable/ListBuffer;
const #192 = class	#191;	//  scala/collection/mutable/ListBuffer
const #193 = Method	#192.#90;	//  scala/collection/mutable/ListBuffer."<init>":()V
const #194 = Asciz	$plus$eq;
const #195 = Asciz	(Ljava/lang/Object;)Lscala/collection/mutable/ListBuffer;;
const #196 = NameAndType	#194:#195;//  $plus$eq:(Ljava/lang/Object;)Lscala/collection/mutable/ListBuffer;
const #197 = Method	#192.#196;	//  scala/collection/mutable/ListBuffer.$plus$eq:(Ljava/lang/Object;)Lscala/collection/mutable/ListBuffer;
const #198 = Asciz	()Lscala/collection/immutable/List;;
const #199 = NameAndType	#189:#198;//  toList:()Lscala/collection/immutable/List;
const #200 = Method	#192.#199;	//  scala/collection/mutable/ListBuffer.toList:()Lscala/collection/immutable/List;
const #201 = Asciz	res;
const #202 = Asciz	Lscala/collection/mutable/ListBuffer;;
const #203 = Asciz	(Lscala/collection/Iterator;Lscala/collection/mutable/Buffer;)V;
const #204 = Asciz	scala/collection/mutable/BufferLike;
const #205 = class	#204;	//  scala/collection/mutable/BufferLike
const #206 = Asciz	(Ljava/lang/Object;)Lscala/collection/mutable/BufferLike;;
const #207 = NameAndType	#194:#206;//  $plus$eq:(Ljava/lang/Object;)Lscala/collection/mutable/BufferLike;
const #208 = InterfaceMethod	#205.#207;	//  scala/collection/mutable/BufferLike.$plus$eq:(Ljava/lang/Object;)Lscala/collection/mutable/BufferLike;
const #209 = Asciz	dest;
const #210 = Asciz	Lscala/collection/mutable/Buffer;;
const #211 = Asciz	copyToArray;
const #212 = NameAndType	#211:#36;//  copyToArray:(Ljava/lang/Object;II)V
const #213 = InterfaceMethod	#13.#212;	//  scala/collection/Iterator.copyToArray:(Ljava/lang/Object;II)V
const #214 = Asciz	scala/runtime/RichInt;
const #215 = class	#214;	//  scala/runtime/RichInt
const #216 = Asciz	(I)V;
const #217 = NameAndType	#56:#216;//  "<init>":(I)V
const #218 = Method	#215.#217;	//  scala/runtime/RichInt."<init>":(I)V
const #219 = Asciz	getLength;
const #220 = NameAndType	#219:#33;//  getLength:(Ljava/lang/Object;)I
const #221 = Method	#45.#220;	//  java/lang/reflect/Array.getLength:(Ljava/lang/Object;)I
const #222 = Asciz	min;
const #223 = Asciz	(I)I;
const #224 = NameAndType	#222:#223;//  min:(I)I
const #225 = Method	#215.#224;	//  scala/runtime/RichInt.min:(I)I
const #226 = Asciz	len;
const #227 = Asciz	patch;
const #228 = Asciz	(Lscala/collection/Iterator;ILscala/collection/Iterator;I)Ljava/lang/Object;;
const #229 = Asciz	scala/collection/Iterator$$anon$30;
const #230 = class	#229;	//  scala/collection/Iterator$$anon$30
const #231 = Asciz	(Lscala/collection/Iterator;ILscala/collection/Iterator;I)V;
const #232 = NameAndType	#56:#231;//  "<init>":(Lscala/collection/Iterator;ILscala/collection/Iterator;I)V
const #233 = Method	#230.#232;	//  scala/collection/Iterator$$anon$30."<init>":(Lscala/collection/Iterator;ILscala/collection/Iterator;I)V
const #234 = Asciz	from$1;
const #235 = Asciz	patchElems$1;
const #236 = Asciz	replaced$1;
const #237 = Asciz	duplicate;
const #238 = Asciz	(Lscala/collection/Iterator;)Lscala/Tuple2;;
const #239 = Asciz	scala/collection/mutable/Queue;
const #240 = class	#239;	//  scala/collection/mutable/Queue
const #241 = Method	#240.#90;	//  scala/collection/mutable/Queue."<init>":()V
const #242 = Asciz	scala/runtime/ObjectRef;
const #243 = class	#242;	//  scala/runtime/ObjectRef
const #244 = Asciz	(Ljava/lang/Object;)V;
const #245 = NameAndType	#56:#244;//  "<init>":(Ljava/lang/Object;)V
const #246 = Method	#243.#245;	//  scala/runtime/ObjectRef."<init>":(Ljava/lang/Object;)V
const #247 = Asciz	scala/Tuple2;
const #248 = class	#247;	//  scala/Tuple2
const #249 = Asciz	scala/collection/Iterator$Partner$1;
const #250 = class	#249;	//  scala/collection/Iterator$Partner$1
const #251 = Asciz	(Lscala/collection/Iterator;Lscala/collection/mutable/Queue;Lscala/runtime/ObjectRef;)V;
const #252 = NameAndType	#56:#251;//  "<init>":(Lscala/collection/Iterator;Lscala/collection/mutable/Queue;Lscala/runtime/ObjectRef;)V
const #253 = Method	#250.#252;	//  scala/collection/Iterator$Partner$1."<init>":(Lscala/collection/Iterator;Lscala/collection/mutable/Queue;Lscala/runtime/ObjectRef;)V
const #254 = Asciz	(Ljava/lang/Object;Ljava/lang/Object;)V;
const #255 = NameAndType	#56:#254;//  "<init>":(Ljava/lang/Object;Ljava/lang/Object;)V
const #256 = Method	#248.#255;	//  scala/Tuple2."<init>":(Ljava/lang/Object;Ljava/lang/Object;)V
const #257 = Asciz	gap$1;
const #258 = Asciz	Lscala/collection/mutable/Queue;;
const #259 = Asciz	ahead$1;
const #260 = Asciz	Lscala/runtime/ObjectRef;;
const #261 = Asciz	length;
const #262 = Asciz	(Lscala/collection/Iterator;)I;
const #263 = Asciz	sliding;
const #264 = Asciz	(Lscala/collection/Iterator;II)Lscala/collection/Iterator$GroupedIterator;;
const #265 = Asciz	scala/collection/Iterator$GroupedIterator;
const #266 = class	#265;	//  scala/collection/Iterator$GroupedIterator
const #267 = Asciz	(Lscala/collection/Iterator;Lscala/collection/Iterator;II)V;
const #268 = NameAndType	#56:#267;//  "<init>":(Lscala/collection/Iterator;Lscala/collection/Iterator;II)V
const #269 = Method	#266.#268;	//  scala/collection/Iterator$GroupedIterator."<init>":(Lscala/collection/Iterator;Lscala/collection/Iterator;II)V
const #270 = Asciz	size;
const #271 = Asciz	step;
const #272 = Asciz	grouped;
const #273 = Asciz	(Lscala/collection/Iterator;I)Lscala/collection/Iterator$GroupedIterator;;
const #274 = Asciz	scala$collection$Iterator$$takeDestructively;
const #275 = Asciz	(Lscala/collection/Iterator;I)Lscala/collection/Seq;;
const #276 = Asciz	(Ljava/lang/Object;)Lscala/collection/mutable/ArrayBuffer;;
const #277 = NameAndType	#194:#276;//  $plus$eq:(Ljava/lang/Object;)Lscala/collection/mutable/ArrayBuffer;
const #278 = Method	#166.#277;	//  scala/collection/mutable/ArrayBuffer.$plus$eq:(Ljava/lang/Object;)Lscala/collection/mutable/ArrayBuffer;
const #279 = Asciz	buffered;
const #280 = Asciz	scala/collection/Iterator$$anon$2;
const #281 = class	#280;	//  scala/collection/Iterator$$anon$2
const #282 = Method	#281.#57;	//  scala/collection/Iterator$$anon$2."<init>":(Lscala/collection/Iterator;)V
const #283 = Asciz	reduceRightOption;
const #284 = Asciz	(Lscala/collection/Iterator;Lscala/Function2;)Lscala/Option;;
const #285 = Asciz	scala/Some;
const #286 = class	#285;	//  scala/Some
const #287 = Asciz	reduceRight;
const #288 = Asciz	(Lscala/Function2;)Ljava/lang/Object;;
const #289 = NameAndType	#287:#288;//  reduceRight:(Lscala/Function2;)Ljava/lang/Object;
const #290 = InterfaceMethod	#13.#289;	//  scala/collection/Iterator.reduceRight:(Lscala/Function2;)Ljava/lang/Object;
const #291 = Method	#286.#245;	//  scala/Some."<init>":(Ljava/lang/Object;)V
const #292 = Asciz	scala/None$;
const #293 = class	#292;	//  scala/None$
const #294 = Asciz	Lscala/None$;;
const #295 = NameAndType	#28:#294;//  MODULE$:Lscala/None$;
const #296 = Field	#293.#295;	//  scala/None$.MODULE$:Lscala/None$;
const #297 = Asciz	op;
const #298 = Asciz	Lscala/Function2;;
const #299 = Asciz	reduceLeftOption;
const #300 = Asciz	reduceLeft;
const #301 = NameAndType	#300:#288;//  reduceLeft:(Lscala/Function2;)Ljava/lang/Object;
const #302 = InterfaceMethod	#13.#301;	//  scala/collection/Iterator.reduceLeft:(Lscala/Function2;)Ljava/lang/Object;
const #303 = Asciz	(Lscala/collection/Iterator;Lscala/Function2;)Ljava/lang/Object;;
const #304 = Asciz	foldRight;
const #305 = Asciz	(Ljava/lang/Object;Lscala/Function2;)Ljava/lang/Object;;
const #306 = NameAndType	#304:#305;//  foldRight:(Ljava/lang/Object;Lscala/Function2;)Ljava/lang/Object;
const #307 = InterfaceMethod	#13.#306;	//  scala/collection/Iterator.foldRight:(Ljava/lang/Object;Lscala/Function2;)Ljava/lang/Object;
const #308 = Asciz	java/lang/UnsupportedOperationException;
const #309 = class	#308;	//  java/lang/UnsupportedOperationException
const #310 = Asciz	empty.reduceRight;
const #311 = String	#310;	//  empty.reduceRight
const #312 = Asciz	(Ljava/lang/String;)V;
const #313 = NameAndType	#56:#312;//  "<init>":(Ljava/lang/String;)V
const #314 = Method	#309.#313;	//  java/lang/UnsupportedOperationException."<init>":(Ljava/lang/String;)V
const #315 = Asciz	foldLeft;
const #316 = NameAndType	#315:#305;//  foldLeft:(Ljava/lang/Object;Lscala/Function2;)Ljava/lang/Object;
const #317 = InterfaceMethod	#13.#316;	//  scala/collection/Iterator.foldLeft:(Ljava/lang/Object;Lscala/Function2;)Ljava/lang/Object;
const #318 = Asciz	empty.reduceLeft;
const #319 = String	#318;	//  empty.reduceLeft
const #320 = Asciz	$colon$bslash;
const #321 = Asciz	(Lscala/collection/Iterator;Ljava/lang/Object;Lscala/Function2;)Ljava/lang/Object;;
const #322 = Asciz	z;
const #323 = Asciz	$div$colon;
const #324 = Asciz	scala/Function2;
const #325 = class	#324;	//  scala/Function2
const #326 = Asciz	apply;
const #327 = Asciz	(Ljava/lang/Object;Ljava/lang/Object;)Ljava/lang/Object;;
const #328 = NameAndType	#326:#327;//  apply:(Ljava/lang/Object;Ljava/lang/Object;)Ljava/lang/Object;
const #329 = InterfaceMethod	#325.#328;	//  scala/Function2.apply:(Ljava/lang/Object;Ljava/lang/Object;)Ljava/lang/Object;
const #330 = Asciz	acc;
const #331 = Asciz	indexOf;
const #332 = Asciz	(Lscala/collection/Iterator;Ljava/lang/Object;)I;
const #333 = Asciz	elem;
const #334 = Asciz	found;
const #335 = Asciz	Z;
const #336 = Asciz	scala/Function1;
const #337 = class	#336;	//  scala/Function1
const #338 = Asciz	(Ljava/lang/Object;)Ljava/lang/Object;;
const #339 = NameAndType	#326:#338;//  apply:(Ljava/lang/Object;)Ljava/lang/Object;
const #340 = InterfaceMethod	#337.#339;	//  scala/Function1.apply:(Ljava/lang/Object;)Ljava/lang/Object;
const #341 = Asciz	unboxToBoolean;
const #342 = NameAndType	#341:#159;//  unboxToBoolean:(Ljava/lang/Object;)Z
const #343 = Method	#151.#342;	//  scala/runtime/BoxesRunTime.unboxToBoolean:(Ljava/lang/Object;)Z
const #344 = Asciz	find;
const #345 = Asciz	(Lscala/collection/Iterator;Lscala/Function1;)Lscala/Option;;
const #346 = Asciz	scala/Option;
const #347 = class	#346;	//  scala/Option
const #348 = Asciz	isEmpty;
const #349 = NameAndType	#348:#15;//  isEmpty:()Z
const #350 = Method	#347.#349;	//  scala/Option.isEmpty:()Z
const #351 = Asciz	Lscala/Option;;
const #352 = Asciz	e;
const #353 = Asciz	contains;
const #354 = Asciz	(Lscala/collection/Iterator;Ljava/lang/Object;)Z;
const #355 = Asciz	scala/collection/Iterator$$anonfun$contains$1;
const #356 = class	#355;	//  scala/collection/Iterator$$anonfun$contains$1
const #357 = NameAndType	#56:#25;//  "<init>":(Lscala/collection/Iterator;Ljava/lang/Object;)V
const #358 = Method	#356.#357;	//  scala/collection/Iterator$$anonfun$contains$1."<init>":(Lscala/collection/Iterator;Ljava/lang/Object;)V
const #359 = Asciz	exists;
const #360 = Asciz	(Lscala/Function1;)Z;
const #361 = NameAndType	#359:#360;//  exists:(Lscala/Function1;)Z
const #362 = InterfaceMethod	#13.#361;	//  scala/collection/Iterator.exists:(Lscala/Function1;)Z
const #363 = Asciz	elem$5;
const #364 = Asciz	(Lscala/collection/Iterator;Lscala/Function1;)Z;
const #365 = Asciz	forall;
const #366 = Asciz	foreach;
const #367 = Asciz	(Lscala/collection/Iterator;Lscala/Function1;)V;
const #368 = Asciz	f;
const #369 = Asciz	zipAll;
const #370 = Asciz	(Lscala/collection/Iterator;Lscala/collection/Iterator;Ljava/lang/Object;Ljava/lang/Object;)Ljava/lang/Object;;
const #371 = Asciz	scala/collection/Iterator$$anon$5;
const #372 = class	#371;	//  scala/collection/Iterator$$anon$5
const #373 = Asciz	(Lscala/collection/Iterator;Lscala/collection/Iterator;Ljava/lang/Object;Ljava/lang/Object;)V;
const #374 = NameAndType	#56:#373;//  "<init>":(Lscala/collection/Iterator;Lscala/collection/Iterator;Ljava/lang/Object;Ljava/lang/Object;)V
const #375 = Method	#372.#374;	//  scala/collection/Iterator$$anon$5."<init>":(Lscala/collection/Iterator;Lscala/collection/Iterator;Ljava/lang/Object;Ljava/lang/Object;)V
const #376 = Asciz	that$1;
const #377 = Asciz	thisElem$1;
const #378 = Asciz	thatElem$1;
const #379 = Asciz	zipWithIndex;
const #380 = Asciz	scala/collection/Iterator$$anon$29;
const #381 = class	#380;	//  scala/collection/Iterator$$anon$29
const #382 = Method	#381.#57;	//  scala/collection/Iterator$$anon$29."<init>":(Lscala/collection/Iterator;)V
const #383 = Asciz	padTo;
const #384 = Asciz	(Lscala/collection/Iterator;ILjava/lang/Object;)Ljava/lang/Object;;
const #385 = Asciz	scala/collection/Iterator$$anon$28;
const #386 = class	#385;	//  scala/collection/Iterator$$anon$28
const #387 = Asciz	(Lscala/collection/Iterator;ILjava/lang/Object;)V;
const #388 = NameAndType	#56:#387;//  "<init>":(Lscala/collection/Iterator;ILjava/lang/Object;)V
const #389 = Method	#386.#388;	//  scala/collection/Iterator$$anon$28."<init>":(Lscala/collection/Iterator;ILjava/lang/Object;)V
const #390 = Asciz	len$2;
const #391 = Asciz	elem$4;
const #392 = Asciz	zip;
const #393 = Asciz	(Lscala/collection/Iterator;Lscala/collection/Iterator;)Ljava/lang/Object;;
const #394 = Asciz	scala/collection/Iterator$$anon$6;
const #395 = class	#394;	//  scala/collection/Iterator$$anon$6
const #396 = Method	#395.#78;	//  scala/collection/Iterator$$anon$6."<init>":(Lscala/collection/Iterator;Lscala/collection/Iterator;)V
const #397 = Asciz	that$3;
const #398 = Asciz	dropWhile;
const #399 = Asciz	(Lscala/collection/Iterator;Lscala/Function1;)Lscala/collection/Iterator;;
const #400 = NameAndType	#279:#19;//  buffered:()Ljava/lang/Object;
const #401 = InterfaceMethod	#13.#400;	//  scala/collection/Iterator.buffered:()Ljava/lang/Object;
const #402 = Asciz	scala/collection/Iterator$$anon$27;
const #403 = class	#402;	//  scala/collection/Iterator$$anon$27
const #404 = Asciz	(Lscala/collection/Iterator;Lscala/Function1;Ljava/lang/Object;)V;
const #405 = NameAndType	#56:#404;//  "<init>":(Lscala/collection/Iterator;Lscala/Function1;Ljava/lang/Object;)V
const #406 = Method	#403.#405;	//  scala/collection/Iterator$$anon$27."<init>":(Lscala/collection/Iterator;Lscala/Function1;Ljava/lang/Object;)V
const #407 = Asciz	p$3;
const #408 = Asciz	self$3;
const #409 = Asciz	partition;
const #410 = Asciz	(Lscala/collection/Iterator;Lscala/Function1;)Lscala/Tuple2;;
const #411 = Asciz	scala/collection/Iterator$PartitionIterator$1;
const #412 = class	#411;	//  scala/collection/Iterator$PartitionIterator$1
const #413 = Method	#412.#405;	//  scala/collection/Iterator$PartitionIterator$1."<init>":(Lscala/collection/Iterator;Lscala/Function1;Ljava/lang/Object;)V
const #414 = Asciz	scala/collection/Iterator$$anonfun$1;
const #415 = class	#414;	//  scala/collection/Iterator$$anonfun$1
const #416 = NameAndType	#56:#367;//  "<init>":(Lscala/collection/Iterator;Lscala/Function1;)V
const #417 = Method	#415.#416;	//  scala/collection/Iterator$$anonfun$1."<init>":(Lscala/collection/Iterator;Lscala/Function1;)V
const #418 = Asciz	other_$eq;
const #419 = Asciz	(Lscala/collection/Iterator$PartitionIterator$1;)V;
const #420 = NameAndType	#418:#419;//  other_$eq:(Lscala/collection/Iterator$PartitionIterator$1;)V
const #421 = Method	#412.#420;	//  scala/collection/Iterator$PartitionIterator$1.other_$eq:(Lscala/collection/Iterator$PartitionIterator$1;)V
const #422 = Asciz	p$5;
const #423 = Asciz	self$2;
const #424 = Asciz	l;
const #425 = Asciz	Lscala/collection/Iterator$PartitionIterator$1;;
const #426 = Asciz	r;
const #427 = Asciz	takeWhile;
const #428 = Asciz	scala/collection/Iterator$$anon$26;
const #429 = class	#428;	//  scala/collection/Iterator$$anon$26
const #430 = Method	#429.#416;	//  scala/collection/Iterator$$anon$26."<init>":(Lscala/collection/Iterator;Lscala/Function1;)V
const #431 = Asciz	p$2;
const #432 = Asciz	partialMap;
const #433 = Asciz	(Lscala/collection/Iterator;Lscala/PartialFunction;)Lscala/collection/Iterator;;
const #434 = Asciz	scala/collection/Iterator$$anon$25;
const #435 = class	#434;	//  scala/collection/Iterator$$anon$25
const #436 = Asciz	(Lscala/collection/Iterator;Lscala/PartialFunction;Ljava/lang/Object;)V;
const #437 = NameAndType	#56:#436;//  "<init>":(Lscala/collection/Iterator;Lscala/PartialFunction;Ljava/lang/Object;)V
const #438 = Method	#435.#437;	//  scala/collection/Iterator$$anon$25."<init>":(Lscala/collection/Iterator;Lscala/PartialFunction;Ljava/lang/Object;)V
const #439 = Asciz	pf$1;
const #440 = Asciz	Lscala/PartialFunction;;
const #441 = Asciz	self$1;
const #442 = Asciz	filterNot;
const #443 = Asciz	scala/collection/Iterator$$anonfun$filterNot$1;
const #444 = class	#443;	//  scala/collection/Iterator$$anonfun$filterNot$1
const #445 = Method	#444.#416;	//  scala/collection/Iterator$$anonfun$filterNot$1."<init>":(Lscala/collection/Iterator;Lscala/Function1;)V
const #446 = Asciz	filter;
const #447 = Asciz	(Lscala/Function1;)Lscala/collection/Iterator;;
const #448 = NameAndType	#446:#447;//  filter:(Lscala/Function1;)Lscala/collection/Iterator;
const #449 = InterfaceMethod	#13.#448;	//  scala/collection/Iterator.filter:(Lscala/Function1;)Lscala/collection/Iterator;
const #450 = Asciz	p$4;
const #451 = Asciz	withFilter;
const #452 = Asciz	(Lscala/collection/Iterator;Lscala/Function1;)Lscala/collection/Iterator$WithFilter;;
const #453 = Asciz	scala/collection/Iterator$WithFilter;
const #454 = class	#453;	//  scala/collection/Iterator$WithFilter
const #455 = Method	#454.#416;	//  scala/collection/Iterator$WithFilter."<init>":(Lscala/collection/Iterator;Lscala/Function1;)V
const #456 = Asciz	scala/collection/Iterator$$anon$22;
const #457 = class	#456;	//  scala/collection/Iterator$$anon$22
const #458 = Method	#457.#416;	//  scala/collection/Iterator$$anon$22."<init>":(Lscala/collection/Iterator;Lscala/Function1;)V
const #459 = Asciz	p$1;
const #460 = Asciz	flatMap;
const #461 = Asciz	scala/collection/Iterator$$anon$21;
const #462 = class	#461;	//  scala/collection/Iterator$$anon$21
const #463 = Method	#462.#416;	//  scala/collection/Iterator$$anon$21."<init>":(Lscala/collection/Iterator;Lscala/Function1;)V
const #464 = Asciz	f$2;
const #465 = Asciz	(Lscala/collection/Iterator;Lscala/Function0;)Lscala/collection/Iterator;;
const #466 = Asciz	scala/collection/Iterator$$anon$20;
const #467 = class	#466;	//  scala/collection/Iterator$$anon$20
const #468 = Asciz	(Lscala/collection/Iterator;Lscala/Function0;)V;
const #469 = NameAndType	#56:#468;//  "<init>":(Lscala/collection/Iterator;Lscala/Function0;)V
const #470 = Method	#467.#469;	//  scala/collection/Iterator$$anon$20."<init>":(Lscala/collection/Iterator;Lscala/Function0;)V
const #471 = Asciz	that$2;
const #472 = Asciz	Lscala/Function0;;
const #473 = Asciz	map;
const #474 = Asciz	scala/collection/Iterator$$anon$19;
const #475 = class	#474;	//  scala/collection/Iterator$$anon$19
const #476 = Method	#475.#416;	//  scala/collection/Iterator$$anon$19."<init>":(Lscala/collection/Iterator;Lscala/Function1;)V
const #477 = Asciz	f$1;
const #478 = Asciz	slice;
const #479 = Asciz	(Lscala/collection/Iterator;II)Lscala/collection/Iterator;;
const #480 = Asciz	drop;
const #481 = Asciz	(I)Lscala/collection/Iterator;;
const #482 = NameAndType	#480:#481;//  drop:(I)Lscala/collection/Iterator;
const #483 = InterfaceMethod	#13.#482;	//  scala/collection/Iterator.drop:(I)Lscala/collection/Iterator;
const #484 = Asciz	take;
const #485 = NameAndType	#484:#481;//  take:(I)Lscala/collection/Iterator;
const #486 = InterfaceMethod	#13.#485;	//  scala/collection/Iterator.take:(I)Lscala/collection/Iterator;
const #487 = Asciz	from;
const #488 = Asciz	until;
const #489 = Asciz	scala/collection/Iterator$class;
const #490 = class	#489;	//  scala/collection/Iterator$class
const #491 = NameAndType	#10:#11;//  loop$1:(Lscala/collection/Iterator;I)Lscala/collection/Iterator;
const #492 = Method	#490.#491;	//  scala/collection/Iterator$class.loop$1:(Lscala/collection/Iterator;I)Lscala/collection/Iterator;
const #493 = Asciz	n;
const #494 = Asciz	scala/collection/Iterator$$anon$18;
const #495 = class	#494;	//  scala/collection/Iterator$$anon$18
const #496 = Asciz	(Lscala/collection/Iterator;I)V;
const #497 = NameAndType	#56:#496;//  "<init>":(Lscala/collection/Iterator;I)V
const #498 = Method	#495.#497;	//  scala/collection/Iterator$$anon$18."<init>":(Lscala/collection/Iterator;I)V
const #499 = Asciz	n$1;
const #500 = Asciz	sliding$default$2;
const #501 = Asciz	Scala;
const #502 = Asciz	InnerClasses;
const #503 = Asciz	scala/collection/immutable/Stream;
const #504 = class	#503;	//  scala/collection/immutable/Stream
const #505 = Asciz	Cons;
const #506 = Asciz	$anon$6;
const #507 = Asciz	$anon$5;
const #508 = Asciz	$anon$2;
const #509 = Asciz	$anon$1;
const #510 = Asciz	$anon$18;
const #511 = Asciz	$anon$19;
const #512 = Asciz	$anon$20;
const #513 = Asciz	$anon$21;
const #514 = Asciz	$anon$22;
const #515 = Asciz	$anon$25;
const #516 = Asciz	$anon$26;
const #517 = Asciz	$anon$27;
const #518 = Asciz	$anon$28;
const #519 = Asciz	$anon$29;
const #520 = Asciz	$anon$30;
const #521 = Asciz	Partner$1;
const #522 = Asciz	WithFilter;
const #523 = Asciz	$anonfun$1;
const #524 = Asciz	GroupedIterator;
const #525 = Asciz	$anonfun$append$1;
const #526 = Asciz	PartitionIterator$1;
const #527 = Asciz	$anonfun$contains$1;
const #528 = Asciz	$anonfun$toStream$1;
const #529 = Asciz	$anonfun$filterNot$1;

{
public static void $init$(scala.collection.Iterator);
  Code:
   Stack=0, Locals=1, Args_size=1
   0:	return
  LineNumberTable: 
   line 260: 0

  LocalVariableTable: 
   Start  Length  Slot  Name   Signature
   0      1      0    $this       Lscala/collection/Iterator;


public static void readInto(scala.collection.Iterator, java.lang.Object);
  Code:
   Stack=5, Locals=2, Args_size=2
   0:	aload_0
   1:	aload_1
   2:	iconst_0
   3:	getstatic	#31; //Field scala/runtime/ScalaRunTime$.MODULE$:Lscala/runtime/ScalaRunTime$;
   6:	aload_1
   7:	invokevirtual	#35; //Method scala/runtime/ScalaRunTime$.array_length:(Ljava/lang/Object;)I
   10:	invokeinterface	#38,  4; //InterfaceMethod scala/collection/Iterator.readInto:(Ljava/lang/Object;II)V
   15:	return
  LineNumberTable: 
   line 1199: 0

  LocalVariableTable: 
   Start  Length  Slot  Name   Signature
   0      16      0    $this       Lscala/collection/Iterator;
   0      16      1    xs       Ljava/lang/Object;


public static void readInto(scala.collection.Iterator, java.lang.Object, int);
  Code:
   Stack=5, Locals=3, Args_size=3
   0:	aload_0
   1:	aload_1
   2:	iload_2
   3:	getstatic	#31; //Field scala/runtime/ScalaRunTime$.MODULE$:Lscala/runtime/ScalaRunTime$;
   6:	aload_1
   7:	invokevirtual	#35; //Method scala/runtime/ScalaRunTime$.array_length:(Ljava/lang/Object;)I
   10:	iload_2
   11:	isub
   12:	invokeinterface	#38,  4; //InterfaceMethod scala/collection/Iterator.readInto:(Ljava/lang/Object;II)V
   17:	return
  LineNumberTable: 
   line 1194: 0

  LocalVariableTable: 
   Start  Length  Slot  Name   Signature
   0      18      0    $this       Lscala/collection/Iterator;
   0      18      1    xs       Ljava/lang/Object;
   0      18      2    start       I


public static void readInto(scala.collection.Iterator, java.lang.Object, int, int);
  Code:
   Stack=3, Locals=6, Args_size=4
   0:	iload_2
   1:	istore	5
   3:	aload_0
   4:	invokeinterface	#17,  1; //InterfaceMethod scala/collection/Iterator.hasNext:()Z
   9:	ifeq	45
   12:	iload	5
   14:	iload_2
   15:	isub
   16:	iload_3
   17:	if_icmpge	45
   20:	aload_0
   21:	invokeinterface	#21,  1; //InterfaceMethod scala/collection/Iterator.next:()Ljava/lang/Object;
   26:	astore	4
   28:	aload_1
   29:	iload	5
   31:	aload	4
   33:	invokestatic	#49; //Method java/lang/reflect/Array.set:(Ljava/lang/Object;ILjava/lang/Object;)V
   36:	iload	5
   38:	iconst_1
   39:	iadd
   40:	istore	5
   42:	goto	3
   45:	return
  LineNumberTable: 
   line 1185: 0
   line 1186: 3
   line 1187: 20
   line 1188: 36
   line 1184: 45

  LocalVariableTable: 
   Start  Length  Slot  Name   Signature
   0      46      0    $this       Lscala/collection/Iterator;
   0      46      1    xs       Ljava/lang/Object;
   0      46      2    start       I
   0      46      3    sz       I
   3      43      5    i       I


public static java.lang.Object counted(scala.collection.Iterator);
  Code:
   Stack=3, Locals=1, Args_size=1
   0:	new	#55; //class scala/collection/Iterator$$anon$1
   3:	dup
   4:	aload_0
   5:	invokespecial	#58; //Method scala/collection/Iterator$$anon$1."<init>":(Lscala/collection/Iterator;)V
   8:	areturn
  LineNumberTable: 
   line 1167: 0

  LocalVariableTable: 
   Start  Length  Slot  Name   Signature
   0      9      0    $this       Lscala/collection/Iterator;


public static scala.collection.Seq collect(scala.collection.Iterator);
  Code:
   Stack=1, Locals=1, Args_size=1
   0:	aload_0
   1:	invokeinterface	#64,  1; //InterfaceMethod scala/collection/Iterator.toSeq:()Lscala/collection/Seq;
   6:	areturn
  LineNumberTable: 
   line 1162: 0

  LocalVariableTable: 
   Start  Length  Slot  Name   Signature
   0      7      0    $this       Lscala/collection/Iterator;


public static int findIndexOf(scala.collection.Iterator, scala.Function1);
  Code:
   Stack=2, Locals=2, Args_size=2
   0:	aload_0
   1:	aload_1
   2:	invokeinterface	#70,  2; //InterfaceMethod scala/collection/Iterator.indexWhere:(Lscala/Function1;)I
   7:	ireturn
  LineNumberTable: 
   line 1155: 0

  LocalVariableTable: 
   Start  Length  Slot  Name   Signature
   0      8      0    $this       Lscala/collection/Iterator;
   0      8      1    p       Lscala/Function1;


public static scala.collection.Iterator append(scala.collection.Iterator, scala.collection.Iterator);
  Code:
   Stack=5, Locals=2, Args_size=2
   0:	aload_0
   1:	new	#76; //class scala/collection/Iterator$$anonfun$append$1
   4:	dup
   5:	aload_0
   6:	aload_1
   7:	invokespecial	#79; //Method scala/collection/Iterator$$anonfun$append$1."<init>":(Lscala/collection/Iterator;Lscala/collection/Iterator;)V
   10:	invokeinterface	#83,  2; //InterfaceMethod scala/collection/Iterator.$plus$plus:(Lscala/Function0;)Lscala/collection/Iterator;
   15:	areturn
  LineNumberTable: 
   line 1151: 0

  LocalVariableTable: 
   Start  Length  Slot  Name   Signature
   0      16      0    $this       Lscala/collection/Iterator;
   0      16      1    that$4       Lscala/collection/Iterator;


public static java.lang.String toString(scala.collection.Iterator);
  Code:
   Stack=2, Locals=1, Args_size=1
   0:	new	#88; //class scala/collection/mutable/StringBuilder
   3:	dup
   4:	invokespecial	#91; //Method scala/collection/mutable/StringBuilder."<init>":()V
   7:	aload_0
   8:	invokeinterface	#17,  1; //InterfaceMethod scala/collection/Iterator.hasNext:()Z
   13:	ifeq	21
   16:	ldc	#93; //String non-empty
   18:	goto	23
   21:	ldc	#95; //String empty
   23:	invokevirtual	#98; //Method scala/collection/mutable/StringBuilder.append:(Ljava/lang/Object;)Lscala/collection/mutable/StringBuilder;
   26:	ldc	#100; //String  iterator
   28:	invokevirtual	#98; //Method scala/collection/mutable/StringBuilder.append:(Ljava/lang/Object;)Lscala/collection/mutable/StringBuilder;
   31:	invokevirtual	#103; //Method scala/collection/mutable/StringBuilder.toString:()Ljava/lang/String;
   34:	areturn
  LineNumberTable: 
   line 1145: 0

  LocalVariableTable: 
   Start  Length  Slot  Name   Signature
   0      35      0    $this       Lscala/collection/Iterator;


public static scala.collection.mutable.StringBuilder addString(scala.collection.Iterator, scala.collection.mutable.StringBuilder);
  Code:
   Stack=5, Locals=2, Args_size=2
   0:	aload_0
   1:	aload_1
   2:	ldc	#107; //String 
   4:	ldc	#107; //String 
   6:	ldc	#107; //String 
   8:	invokeinterface	#110,  5; //InterfaceMethod scala/collection/Iterator.addString:(Lscala/collection/mutable/StringBuilder;Ljava/lang/String;Ljava/lang/String;Ljava/lang/String;)Lscala/collection/mutable/StringBuilder;
   13:	areturn
  LineNumberTable: 
   line 1143: 0

  LocalVariableTable: 
   Start  Length  Slot  Name   Signature
   0      14      0    $this       Lscala/collection/Iterator;
   0      14      1    buf       Lscala/collection/mutable/StringBuilder;


public static scala.collection.mutable.StringBuilder addString(scala.collection.Iterator, scala.collection.mutable.StringBuilder, java.lang.String);
  Code:
   Stack=5, Locals=3, Args_size=3
   0:	aload_0
   1:	aload_1
   2:	ldc	#107; //String 
   4:	aload_2
   5:	ldc	#107; //String 
   7:	invokeinterface	#110,  5; //InterfaceMethod scala/collection/Iterator.addString:(Lscala/collection/mutable/StringBuilder;Ljava/lang/String;Ljava/lang/String;Ljava/lang/String;)Lscala/collection/mutable/StringBuilder;
   12:	areturn
  LineNumberTable: 
   line 1138: 0

  LocalVariableTable: 
   Start  Length  Slot  Name   Signature
   0      13      0    $this       Lscala/collection/Iterator;
   0      13      1    buf       Lscala/collection/mutable/StringBuilder;
   0      13      2    sep       Ljava/lang/String;


public static scala.collection.mutable.StringBuilder addString(scala.collection.Iterator, scala.collection.mutable.StringBuilder, java.lang.String, java.lang.String, java.lang.String);
  Code:
   Stack=2, Locals=7, Args_size=5
   0:	aload_1
   1:	aload_2
   2:	invokevirtual	#119; //Method scala/collection/mutable/StringBuilder.append:(Ljava/lang/String;)Lscala/collection/mutable/StringBuilder;
   5:	pop
   6:	aload_0
   7:	invokeinterface	#17,  1; //InterfaceMethod scala/collection/Iterator.hasNext:()Z
   12:	ifeq	35
   15:	aload_0
   16:	invokeinterface	#21,  1; //InterfaceMethod scala/collection/Iterator.next:()Ljava/lang/Object;
   21:	astore	5
   23:	aload_1
   24:	aload	5
   26:	invokestatic	#125; //Method java/lang/String.valueOf:(Ljava/lang/Object;)Ljava/lang/String;
   29:	invokevirtual	#119; //Method scala/collection/mutable/StringBuilder.append:(Ljava/lang/String;)Lscala/collection/mutable/StringBuilder;
   32:	goto	38
   35:	getstatic	#131; //Field scala/runtime/BoxedUnit.UNIT:Lscala/runtime/BoxedUnit;
   38:	pop
   39:	aload_0
   40:	invokeinterface	#17,  1; //InterfaceMethod scala/collection/Iterator.hasNext:()Z
   45:	ifeq	75
   48:	aload_1
   49:	aload_3
   50:	invokevirtual	#119; //Method scala/collection/mutable/StringBuilder.append:(Ljava/lang/String;)Lscala/collection/mutable/StringBuilder;
   53:	pop
   54:	aload_0
   55:	invokeinterface	#21,  1; //InterfaceMethod scala/collection/Iterator.next:()Ljava/lang/Object;
   60:	astore	6
   62:	aload_1
   63:	aload	6
   65:	invokestatic	#125; //Method java/lang/String.valueOf:(Ljava/lang/Object;)Ljava/lang/String;
   68:	invokevirtual	#119; //Method scala/collection/mutable/StringBuilder.append:(Ljava/lang/String;)Lscala/collection/mutable/StringBuilder;
   71:	pop
   72:	goto	39
   75:	aload_1
   76:	aload	4
   78:	invokevirtual	#119; //Method scala/collection/mutable/StringBuilder.append:(Ljava/lang/String;)Lscala/collection/mutable/StringBuilder;
   81:	areturn
  LineNumberTable: 
   line 1125: 0
   line 1127: 6
   line 1128: 39
   line 1129: 48
   line 1131: 75

  LocalVariableTable: 
   Start  Length  Slot  Name   Signature
   0      82      0    $this       Lscala/collection/Iterator;
   0      82      1    buf       Lscala/collection/mutable/StringBuilder;
   0      82      2    start       Ljava/lang/String;
   0      82      3    sep       Ljava/lang/String;
   0      82      4    end       Ljava/lang/String;


public static java.lang.String mkString(scala.collection.Iterator);
  Code:
   Stack=2, Locals=1, Args_size=1
   0:	aload_0
   1:	ldc	#107; //String 
   3:	invokeinterface	#136,  2; //InterfaceMethod scala/collection/Iterator.mkString:(Ljava/lang/String;)Ljava/lang/String;
   8:	areturn
  LineNumberTable: 
   line 1116: 0

  LocalVariableTable: 
   Start  Length  Slot  Name   Signature
   0      9      0    $this       Lscala/collection/Iterator;


public static java.lang.String mkString(scala.collection.Iterator, java.lang.String);
  Code:
   Stack=4, Locals=2, Args_size=2
   0:	aload_0
   1:	ldc	#107; //String 
   3:	aload_1
   4:	ldc	#107; //String 
   6:	invokeinterface	#140,  4; //InterfaceMethod scala/collection/Iterator.mkString:(Ljava/lang/String;Ljava/lang/String;Ljava/lang/String;)Ljava/lang/String;
   11:	areturn
  LineNumberTable: 
   line 1108: 0

  LocalVariableTable: 
   Start  Length  Slot  Name   Signature
   0      12      0    $this       Lscala/collection/Iterator;
   0      12      1    sep       Ljava/lang/String;


public static java.lang.String mkString(scala.collection.Iterator, java.lang.String, java.lang.String, java.lang.String);
  Code:
   Stack=5, Locals=5, Args_size=4
   0:	new	#88; //class scala/collection/mutable/StringBuilder
   3:	dup
   4:	invokespecial	#142; //Method scala/collection/mutable/StringBuilder."<init>":()V
   7:	astore	4
   9:	aload_0
   10:	aload	4
   12:	aload_1
   13:	aload_2
   14:	aload_3
   15:	invokeinterface	#110,  5; //InterfaceMethod scala/collection/Iterator.addString:(Lscala/collection/mutable/StringBuilder;Ljava/lang/String;Ljava/lang/String;Ljava/lang/String;)Lscala/collection/mutable/StringBuilder;
   20:	invokevirtual	#143; //Method scala/collection/mutable/StringBuilder.toString:()Ljava/lang/String;
   23:	areturn
  LineNumberTable: 
   line 1097: 0
   line 1098: 9

  LocalVariableTable: 
   Start  Length  Slot  Name   Signature
   0      24      0    $this       Lscala/collection/Iterator;
   0      24      1    start       Ljava/lang/String;
   0      24      2    sep       Ljava/lang/String;
   0      24      3    end       Ljava/lang/String;
   9      14      4    buf       Lscala/collection/mutable/StringBuilder;


public static boolean sameElements(scala.collection.Iterator, scala.collection.Iterator);
  Code:
   Stack=2, Locals=4, Args_size=2
   0:	aload_0
   1:	invokeinterface	#17,  1; //InterfaceMethod scala/collection/Iterator.hasNext:()Z
   6:	ifeq	81
   9:	aload_1
   10:	invokeinterface	#17,  1; //InterfaceMethod scala/collection/Iterator.hasNext:()Z
   15:	ifeq	81
   18:	aload_0
   19:	invokeinterface	#21,  1; //InterfaceMethod scala/collection/Iterator.next:()Ljava/lang/Object;
   24:	aload_1
   25:	invokeinterface	#21,  1; //InterfaceMethod scala/collection/Iterator.next:()Ljava/lang/Object;
   30:	astore_3
   31:	astore_2
   32:	aload_2
   33:	aload_3
   34:	if_acmpne	41
   37:	iconst_1
   38:	goto	76
   41:	aload_2
   42:	ifnonnull	49
   45:	iconst_0
   46:	goto	76
   49:	aload_2
   50:	instanceof	#147; //class java/lang/Number
   53:	ifne	63
   56:	aload_2
   57:	instanceof	#149; //class java/lang/Character
   60:	ifeq	71
   63:	aload_2
   64:	aload_3
   65:	invokestatic	#155; //Method scala/runtime/BoxesRunTime.equals2:(Ljava/lang/Object;Ljava/lang/Object;)Z
   68:	goto	76
   71:	aload_2
   72:	aload_3
   73:	invokevirtual	#161; //Method java/lang/Object.equals:(Ljava/lang/Object;)Z
   76:	ifne	0
   79:	iconst_0
   80:	ireturn
   81:	aload_0
   82:	invokeinterface	#17,  1; //InterfaceMethod scala/collection/Iterator.hasNext:()Z
   87:	ifne	99
   90:	aload_1
   91:	invokeinterface	#17,  1; //InterfaceMethod scala/collection/Iterator.hasNext:()Z
   96:	ifeq	103
   99:	iconst_0
   100:	goto	104
   103:	iconst_1
   104:	ireturn
  LineNumberTable: 
   line 1075: 0
   line 1076: 18
   line 1077: 79
   line 1079: 81
   line 1074: 104

  LocalVariableTable: 
   Start  Length  Slot  Name   Signature
   0      105      0    $this       Lscala/collection/Iterator;
   0      105      1    that       Lscala/collection/Iterator;
   37      42      2    x0       Ljava/lang/Object;
   37      42      3    y0       Ljava/lang/Object;


public static scala.collection.Seq toSeq(scala.collection.Iterator);
  Code:
   Stack=2, Locals=2, Args_size=1
   0:	new	#166; //class scala/collection/mutable/ArrayBuffer
   3:	dup
   4:	invokespecial	#167; //Method scala/collection/mutable/ArrayBuffer."<init>":()V
   7:	astore_1
   8:	aload_0
   9:	aload_1
   10:	invokeinterface	#171,  2; //InterfaceMethod scala/collection/Iterator.copyToBuffer:(Lscala/collection/mutable/Buffer;)V
   15:	aload_1
   16:	areturn
  LineNumberTable: 
   line 1063: 0
   line 1064: 8
   line 1065: 9
   line 1064: 10
   line 1065: 15

  LocalVariableTable: 
   Start  Length  Slot  Name   Signature
   0      17      0    $this       Lscala/collection/Iterator;
   8      8      1    buffer       Lscala/collection/mutable/ArrayBuffer;


public static scala.collection.immutable.Stream toStream(scala.collection.Iterator);
  Code:
   Stack=4, Locals=3, Args_size=1
   0:	aload_0
   1:	invokeinterface	#17,  1; //InterfaceMethod scala/collection/Iterator.hasNext:()Z
   6:	ifeq	37
   9:	aload_0
   10:	invokeinterface	#21,  1; //InterfaceMethod scala/collection/Iterator.next:()Ljava/lang/Object;
   15:	new	#177; //class scala/collection/Iterator$$anonfun$toStream$1
   18:	dup
   19:	aload_0
   20:	invokespecial	#178; //Method scala/collection/Iterator$$anonfun$toStream$1."<init>":(Lscala/collection/Iterator;)V
   23:	astore_2
   24:	astore_1
   25:	new	#180; //class scala/collection/immutable/Stream$Cons
   28:	dup
   29:	aload_1
   30:	aload_2
   31:	invokespecial	#183; //Method scala/collection/immutable/Stream$Cons."<init>":(Ljava/lang/Object;Lscala/Function0;)V
   34:	goto	40
   37:	getstatic	#188; //Field scala/collection/immutable/Stream$Empty$.MODULE$:Lscala/collection/immutable/Stream$Empty$;
   40:	areturn
  LineNumberTable: 
   line 1056: 0

  LocalVariableTable: 
   Start  Length  Slot  Name   Signature
   0      41      0    $this       Lscala/collection/Iterator;


public static scala.collection.immutable.List toList(scala.collection.Iterator);
  Code:
   Stack=2, Locals=2, Args_size=1
   0:	new	#192; //class scala/collection/mutable/ListBuffer
   3:	dup
   4:	invokespecial	#193; //Method scala/collection/mutable/ListBuffer."<init>":()V
   7:	astore_1
   8:	aload_0
   9:	invokeinterface	#17,  1; //InterfaceMethod scala/collection/Iterator.hasNext:()Z
   14:	ifeq	31
   17:	aload_1
   18:	aload_0
   19:	invokeinterface	#21,  1; //InterfaceMethod scala/collection/Iterator.next:()Ljava/lang/Object;
   24:	invokevirtual	#197; //Method scala/collection/mutable/ListBuffer.$plus$eq:(Ljava/lang/Object;)Lscala/collection/mutable/ListBuffer;
   27:	pop
   28:	goto	8
   31:	aload_1
   32:	invokevirtual	#200; //Method scala/collection/mutable/ListBuffer.toList:()Lscala/collection/immutable/List;
   35:	areturn
  LineNumberTable: 
   line 1046: 0
   line 1047: 8
   line 1048: 31

  LocalVariableTable: 
   Start  Length  Slot  Name   Signature
   0      36      0    $this       Lscala/collection/Iterator;
   8      27      1    res       Lscala/collection/mutable/ListBuffer;


public static void copyToBuffer(scala.collection.Iterator, scala.collection.mutable.Buffer);
  Code:
   Stack=2, Locals=2, Args_size=2
   0:	aload_0
   1:	invokeinterface	#17,  1; //InterfaceMethod scala/collection/Iterator.hasNext:()Z
   6:	ifeq	25
   9:	aload_1
   10:	aload_0
   11:	invokeinterface	#21,  1; //InterfaceMethod scala/collection/Iterator.next:()Ljava/lang/Object;
   16:	invokeinterface	#208,  2; //InterfaceMethod scala/collection/mutable/BufferLike.$plus$eq:(Ljava/lang/Object;)Lscala/collection/mutable/BufferLike;
   21:	pop
   22:	goto	0
   25:	return
  LineNumberTable: 
   line 1038: 0

  LocalVariableTable: 
   Start  Length  Slot  Name   Signature
   0      26      0    $this       Lscala/collection/Iterator;
   0      26      1    dest       Lscala/collection/mutable/Buffer;


public static void copyToArray(scala.collection.Iterator, java.lang.Object);
  Code:
   Stack=5, Locals=2, Args_size=2
   0:	aload_0
   1:	aload_1
   2:	iconst_0
   3:	getstatic	#31; //Field scala/runtime/ScalaRunTime$.MODULE$:Lscala/runtime/ScalaRunTime$;
   6:	aload_1
   7:	invokevirtual	#35; //Method scala/runtime/ScalaRunTime$.array_length:(Ljava/lang/Object;)I
   10:	invokeinterface	#213,  4; //InterfaceMethod scala/collection/Iterator.copyToArray:(Ljava/lang/Object;II)V
   15:	return
  LineNumberTable: 
   line 1032: 0

  LocalVariableTable: 
   Start  Length  Slot  Name   Signature
   0      16      0    $this       Lscala/collection/Iterator;
   0      16      1    xs       Ljava/lang/Object;


public static void copyToArray(scala.collection.Iterator, java.lang.Object, int);
  Code:
   Stack=5, Locals=3, Args_size=3
   0:	aload_0
   1:	aload_1
   2:	iload_2
   3:	getstatic	#31; //Field scala/runtime/ScalaRunTime$.MODULE$:Lscala/runtime/ScalaRunTime$;
   6:	aload_1
   7:	invokevirtual	#35; //Method scala/runtime/ScalaRunTime$.array_length:(Ljava/lang/Object;)I
   10:	iload_2
   11:	isub
   12:	invokeinterface	#213,  4; //InterfaceMethod scala/collection/Iterator.copyToArray:(Ljava/lang/Object;II)V
   17:	return
  LineNumberTable: 
   line 1024: 0

  LocalVariableTable: 
   Start  Length  Slot  Name   Signature
   0      18      0    $this       Lscala/collection/Iterator;
   0      18      1    xs       Ljava/lang/Object;
   0      18      2    start       I


public static void copyToArray(scala.collection.Iterator, java.lang.Object, int, int);
  Code:
   Stack=3, Locals=8, Args_size=4
   0:	iload_2
   1:	istore	7
   3:	iload_2
   4:	iload_3
   5:	iadd
   6:	istore	4
   8:	new	#215; //class scala/runtime/RichInt
   11:	dup
   12:	iload	4
   14:	invokespecial	#218; //Method scala/runtime/RichInt."<init>":(I)V
   17:	aload_1
   18:	invokestatic	#221; //Method java/lang/reflect/Array.getLength:(Ljava/lang/Object;)I
   21:	invokevirtual	#225; //Method scala/runtime/RichInt.min:(I)I
   24:	istore	5
   26:	aload_0
   27:	invokeinterface	#17,  1; //InterfaceMethod scala/collection/Iterator.hasNext:()Z
   32:	ifeq	67
   35:	iload	7
   37:	iload	5
   39:	if_icmpge	67
   42:	aload_0
   43:	invokeinterface	#21,  1; //InterfaceMethod scala/collection/Iterator.next:()Ljava/lang/Object;
   48:	astore	6
   50:	aload_1
   51:	iload	7
   53:	aload	6
   55:	invokestatic	#49; //Method java/lang/reflect/Array.set:(Ljava/lang/Object;ILjava/lang/Object;)V
   58:	iload	7
   60:	iconst_1
   61:	iadd
   62:	istore	7
   64:	goto	26
   67:	return
  LineNumberTable: 
   line 1008: 0
   line 1009: 3
   line 1010: 26
   line 1011: 42
   line 1012: 58
   line 1007: 67

  LocalVariableTable: 
   Start  Length  Slot  Name   Signature
   0      68      0    $this       Lscala/collection/Iterator;
   0      68      1    xs       Ljava/lang/Object;
   0      68      2    start       I
   0      68      3    len       I
   26      42      5    end       I
   3      65      7    i       I


public static java.lang.Object patch(scala.collection.Iterator, int, scala.collection.Iterator, int);
  Code:
   Stack=6, Locals=4, Args_size=4
   0:	new	#230; //class scala/collection/Iterator$$anon$30
   3:	dup
   4:	aload_0
   5:	iload_1
   6:	aload_2
   7:	iload_3
   8:	invokespecial	#233; //Method scala/collection/Iterator$$anon$30."<init>":(Lscala/collection/Iterator;ILscala/collection/Iterator;I)V
   11:	areturn
  LineNumberTable: 
   line 983: 0

  LocalVariableTable: 
   Start  Length  Slot  Name   Signature
   0      12      0    $this       Lscala/collection/Iterator;
   0      12      1    from$1       I
   0      12      2    patchElems$1       Lscala/collection/Iterator;
   0      12      3    replaced$1       I


public static scala.Tuple2 duplicate(scala.collection.Iterator);
  Code:
   Stack=8, Locals=3, Args_size=1
   0:	new	#240; //class scala/collection/mutable/Queue
   3:	dup
   4:	invokespecial	#241; //Method scala/collection/mutable/Queue."<init>":()V
   7:	astore_1
   8:	new	#243; //class scala/runtime/ObjectRef
   11:	dup
   12:	aconst_null
   13:	invokespecial	#246; //Method scala/runtime/ObjectRef."<init>":(Ljava/lang/Object;)V
   16:	astore_2
   17:	new	#248; //class scala/Tuple2
   20:	dup
   21:	new	#250; //class scala/collection/Iterator$Partner$1
   24:	dup
   25:	aload_0
   26:	aload_1
   27:	aload_2
   28:	invokespecial	#253; //Method scala/collection/Iterator$Partner$1."<init>":(Lscala/collection/Iterator;Lscala/collection/mutable/Queue;Lscala/runtime/ObjectRef;)V
   31:	new	#250; //class scala/collection/Iterator$Partner$1
   34:	dup
   35:	aload_0
   36:	aload_1
   37:	aload_2
   38:	invokespecial	#253; //Method scala/collection/Iterator$Partner$1."<init>":(Lscala/collection/Iterator;Lscala/collection/mutable/Queue;Lscala/runtime/ObjectRef;)V
   41:	invokespecial	#256; //Method scala/Tuple2."<init>":(Ljava/lang/Object;Ljava/lang/Object;)V
   44:	areturn
  LineNumberTable: 
   line 960: 0
   line 961: 8
   line 975: 17

  LocalVariableTable: 
   Start  Length  Slot  Name   Signature
   0      45      0    $this       Lscala/collection/Iterator;
   8      36      1    gap$1       Lscala/collection/mutable/Queue;
   17      27      2    ahead$1       Lscala/runtime/ObjectRef;


public static int length(scala.collection.Iterator);
  Code:
   Stack=2, Locals=2, Args_size=1
   0:	iconst_0
   1:	istore_1
   2:	aload_0
   3:	invokeinterface	#17,  1; //InterfaceMethod scala/collection/Iterator.hasNext:()Z
   8:	ifeq	25
   11:	aload_0
   12:	invokeinterface	#21,  1; //InterfaceMethod scala/collection/Iterator.next:()Ljava/lang/Object;
   17:	pop
   18:	iload_1
   19:	iconst_1
   20:	iadd
   21:	istore_1
   22:	goto	2
   25:	iload_1
   26:	ireturn
  LineNumberTable: 
   line 947: 0
   line 948: 2
   line 949: 11
   line 951: 25

  LocalVariableTable: 
   Start  Length  Slot  Name   Signature
   0      27      0    $this       Lscala/collection/Iterator;
   2      24      1    i       I


public static scala.collection.Iterator$GroupedIterator sliding(scala.collection.Iterator, int, int);
  Code:
   Stack=6, Locals=3, Args_size=3
   0:	new	#266; //class scala/collection/Iterator$GroupedIterator
   3:	dup
   4:	aload_0
   5:	aload_0
   6:	iload_1
   7:	iload_2
   8:	invokespecial	#269; //Method scala/collection/Iterator$GroupedIterator."<init>":(Lscala/collection/Iterator;Lscala/collection/Iterator;II)V
   11:	areturn
  LineNumberTable: 
   line 941: 0

  LocalVariableTable: 
   Start  Length  Slot  Name   Signature
   0      12      0    $this       Lscala/collection/Iterator;
   0      12      1    size       I
   0      12      2    step       I


public static scala.collection.Iterator$GroupedIterator grouped(scala.collection.Iterator, int);
  Code:
   Stack=6, Locals=2, Args_size=2
   0:	new	#266; //class scala/collection/Iterator$GroupedIterator
   3:	dup
   4:	aload_0
   5:	aload_0
   6:	iload_1
   7:	iload_1
   8:	invokespecial	#269; //Method scala/collection/Iterator$GroupedIterator."<init>":(Lscala/collection/Iterator;Lscala/collection/Iterator;II)V
   11:	areturn
  LineNumberTable: 
   line 920: 0

  LocalVariableTable: 
   Start  Length  Slot  Name   Signature
   0      12      0    $this       Lscala/collection/Iterator;
   0      12      1    size       I


public static final scala.collection.Seq scala$collection$Iterator$$takeDestructively(scala.collection.Iterator, int);
  Code:
   Stack=2, Locals=4, Args_size=2
   0:	new	#166; //class scala/collection/mutable/ArrayBuffer
   3:	dup
   4:	invokespecial	#167; //Method scala/collection/mutable/ArrayBuffer."<init>":()V
   7:	astore_2
   8:	iconst_0
   9:	istore_3
   10:	aload_0
   11:	invokeinterface	#17,  1; //InterfaceMethod scala/collection/Iterator.hasNext:()Z
   16:	ifeq	42
   19:	iload_3
   20:	iload_1
   21:	if_icmpge	42
   24:	aload_2
   25:	aload_0
   26:	invokeinterface	#21,  1; //InterfaceMethod scala/collection/Iterator.next:()Ljava/lang/Object;
   31:	invokevirtual	#278; //Method scala/collection/mutable/ArrayBuffer.$plus$eq:(Ljava/lang/Object;)Lscala/collection/mutable/ArrayBuffer;
   34:	pop
   35:	iload_3
   36:	iconst_1
   37:	iadd
   38:	istore_3
   39:	goto	10
   42:	aload_2
   43:	areturn
  LineNumberTable: 
   line 807: 0
   line 808: 8
   line 809: 10
   line 810: 24
   line 811: 35
   line 813: 42

  LocalVariableTable: 
   Start  Length  Slot  Name   Signature
   0      44      0    $this       Lscala/collection/Iterator;
   0      44      1    size       I
   8      35      2    buf       Lscala/collection/mutable/ArrayBuffer;
   10      33      3    i       I


public static java.lang.Object buffered(scala.collection.Iterator);
  Code:
   Stack=3, Locals=1, Args_size=1
   0:	new	#281; //class scala/collection/Iterator$$anon$2
   3:	dup
   4:	aload_0
   5:	invokespecial	#282; //Method scala/collection/Iterator$$anon$2."<init>":(Lscala/collection/Iterator;)V
   8:	areturn
  LineNumberTable: 
   line 779: 0

  LocalVariableTable: 
   Start  Length  Slot  Name   Signature
   0      9      0    $this       Lscala/collection/Iterator;


public static scala.Option reduceRightOption(scala.collection.Iterator, scala.Function2);
  Code:
   Stack=4, Locals=2, Args_size=2
   0:	aload_0
   1:	invokeinterface	#17,  1; //InterfaceMethod scala/collection/Iterator.hasNext:()Z
   6:	ifeq	26
   9:	new	#286; //class scala/Some
   12:	dup
   13:	aload_0
   14:	aload_1
   15:	invokeinterface	#290,  2; //InterfaceMethod scala/collection/Iterator.reduceRight:(Lscala/Function2;)Ljava/lang/Object;
   20:	invokespecial	#291; //Method scala/Some."<init>":(Ljava/lang/Object;)V
   23:	goto	29
   26:	getstatic	#296; //Field scala/None$.MODULE$:Lscala/None$;
   29:	areturn
  LineNumberTable: 
   line 774: 0

  LocalVariableTable: 
   Start  Length  Slot  Name   Signature
   0      30      0    $this       Lscala/collection/Iterator;
   0      30      1    op       Lscala/Function2;


public static scala.Option reduceLeftOption(scala.collection.Iterator, scala.Function2);
  Code:
   Stack=4, Locals=2, Args_size=2
   0:	aload_0
   1:	invokeinterface	#17,  1; //InterfaceMethod scala/collection/Iterator.hasNext:()Z
   6:	ifeq	26
   9:	new	#286; //class scala/Some
   12:	dup
   13:	aload_0
   14:	aload_1
   15:	invokeinterface	#302,  2; //InterfaceMethod scala/collection/Iterator.reduceLeft:(Lscala/Function2;)Ljava/lang/Object;
   20:	invokespecial	#291; //Method scala/Some."<init>":(Ljava/lang/Object;)V
   23:	goto	29
   26:	getstatic	#296; //Field scala/None$.MODULE$:Lscala/None$;
   29:	areturn
  LineNumberTable: 
   line 764: 0

  LocalVariableTable: 
   Start  Length  Slot  Name   Signature
   0      30      0    $this       Lscala/collection/Iterator;
   0      30      1    op       Lscala/Function2;


public static java.lang.Object reduceRight(scala.collection.Iterator, scala.Function2);
  Code:
   Stack=3, Locals=2, Args_size=2
   0:	aload_0
   1:	invokeinterface	#17,  1; //InterfaceMethod scala/collection/Iterator.hasNext:()Z
   6:	ifeq	23
   9:	aload_0
   10:	aload_0
   11:	invokeinterface	#21,  1; //InterfaceMethod scala/collection/Iterator.next:()Ljava/lang/Object;
   16:	aload_1
   17:	invokeinterface	#307,  3; //InterfaceMethod scala/collection/Iterator.foldRight:(Ljava/lang/Object;Lscala/Function2;)Ljava/lang/Object;
   22:	areturn
   23:	new	#309; //class java/lang/UnsupportedOperationException
   26:	dup
   27:	ldc_w	#311; //String empty.reduceRight
   30:	invokespecial	#314; //Method java/lang/UnsupportedOperationException."<init>":(Ljava/lang/String;)V
   33:	athrow
  LineNumberTable: 
   line 754: 0
   line 755: 23

  LocalVariableTable: 
   Start  Length  Slot  Name   Signature
   0      34      0    $this       Lscala/collection/Iterator;
   0      34      1    op       Lscala/Function2;


public static java.lang.Object reduceLeft(scala.collection.Iterator, scala.Function2);
  Code:
   Stack=3, Locals=2, Args_size=2
   0:	aload_0
   1:	invokeinterface	#17,  1; //InterfaceMethod scala/collection/Iterator.hasNext:()Z
   6:	ifeq	23
   9:	aload_0
   10:	aload_0
   11:	invokeinterface	#21,  1; //InterfaceMethod scala/collection/Iterator.next:()Ljava/lang/Object;
   16:	aload_1
   17:	invokeinterface	#317,  3; //InterfaceMethod scala/collection/Iterator.foldLeft:(Ljava/lang/Object;Lscala/Function2;)Ljava/lang/Object;
   22:	areturn
   23:	new	#309; //class java/lang/UnsupportedOperationException
   26:	dup
   27:	ldc_w	#319; //String empty.reduceLeft
   30:	invokespecial	#314; //Method java/lang/UnsupportedOperationException."<init>":(Ljava/lang/String;)V
   33:	athrow
  LineNumberTable: 
   line 739: 0
   line 740: 23

  LocalVariableTable: 
   Start  Length  Slot  Name   Signature
   0      34      0    $this       Lscala/collection/Iterator;
   0      34      1    op       Lscala/Function2;


public static java.lang.Object $colon$bslash(scala.collection.Iterator, java.lang.Object, scala.Function2);
  Code:
   Stack=3, Locals=3, Args_size=3
   0:	aload_0
   1:	aload_1
   2:	aload_2
   3:	invokeinterface	#307,  3; //InterfaceMethod scala/collection/Iterator.foldRight:(Ljava/lang/Object;Lscala/Function2;)Ljava/lang/Object;
   8:	areturn
  LineNumberTable: 
   line 727: 0

  LocalVariableTable: 
   Start  Length  Slot  Name   Signature
   0      9      0    $this       Lscala/collection/Iterator;
   0      9      1    z       Ljava/lang/Object;
   0      9      2    op       Lscala/Function2;


public static java.lang.Object $div$colon(scala.collection.Iterator, java.lang.Object, scala.Function2);
  Code:
   Stack=3, Locals=3, Args_size=3
   0:	aload_0
   1:	aload_1
   2:	aload_2
   3:	invokeinterface	#317,  3; //InterfaceMethod scala/collection/Iterator.foldLeft:(Ljava/lang/Object;Lscala/Function2;)Ljava/lang/Object;
   8:	areturn
  LineNumberTable: 
   line 716: 0

  LocalVariableTable: 
   Start  Length  Slot  Name   Signature
   0      9      0    $this       Lscala/collection/Iterator;
   0      9      1    z       Ljava/lang/Object;
   0      9      2    op       Lscala/Function2;


public static java.lang.Object foldRight(scala.collection.Iterator, java.lang.Object, scala.Function2);
  Code:
   Stack=5, Locals=3, Args_size=3
   0:	aload_0
   1:	invokeinterface	#17,  1; //InterfaceMethod scala/collection/Iterator.hasNext:()Z
   6:	ifeq	32
   9:	aload_2
   10:	aload_0
   11:	invokeinterface	#21,  1; //InterfaceMethod scala/collection/Iterator.next:()Ljava/lang/Object;
   16:	aload_0
   17:	aload_1
   18:	aload_2
   19:	invokeinterface	#307,  3; //InterfaceMethod scala/collection/Iterator.foldRight:(Ljava/lang/Object;Lscala/Function2;)Ljava/lang/Object;
   24:	invokeinterface	#329,  3; //InterfaceMethod scala/Function2.apply:(Ljava/lang/Object;Ljava/lang/Object;)Ljava/lang/Object;
   29:	goto	33
   32:	aload_1
   33:	areturn
  LineNumberTable: 
   line 704: 0

  LocalVariableTable: 
   Start  Length  Slot  Name   Signature
   0      34      0    $this       Lscala/collection/Iterator;
   0      34      1    z       Ljava/lang/Object;
   0      34      2    op       Lscala/Function2;


public static java.lang.Object foldLeft(scala.collection.Iterator, java.lang.Object, scala.Function2);
  Code:
   Stack=3, Locals=4, Args_size=3
   0:	aload_1
   1:	astore_3
   2:	aload_0
   3:	invokeinterface	#17,  1; //InterfaceMethod scala/collection/Iterator.hasNext:()Z
   8:	ifeq	28
   11:	aload_2
   12:	aload_3
   13:	aload_0
   14:	invokeinterface	#21,  1; //InterfaceMethod scala/collection/Iterator.next:()Ljava/lang/Object;
   19:	invokeinterface	#329,  3; //InterfaceMethod scala/Function2.apply:(Ljava/lang/Object;Ljava/lang/Object;)Ljava/lang/Object;
   24:	astore_3
   25:	goto	2
   28:	aload_3
   29:	areturn
  LineNumberTable: 
   line 690: 0
   line 691: 2
   line 692: 28

  LocalVariableTable: 
   Start  Length  Slot  Name   Signature
   0      30      0    $this       Lscala/collection/Iterator;
   0      30      1    z       Ljava/lang/Object;
   0      30      2    op       Lscala/Function2;
   2      27      3    acc       Ljava/lang/Object;


public static int indexOf(scala.collection.Iterator, java.lang.Object);
  Code:
   Stack=2, Locals=5, Args_size=2
   0:	iconst_0
   1:	istore	4
   3:	iconst_0
   4:	istore_3
   5:	iload_3
   6:	ifne	86
   9:	aload_0
   10:	invokeinterface	#17,  1; //InterfaceMethod scala/collection/Iterator.hasNext:()Z
   15:	ifeq	86
   18:	aload_0
   19:	invokeinterface	#21,  1; //InterfaceMethod scala/collection/Iterator.next:()Ljava/lang/Object;
   24:	astore_2
   25:	aload_2
   26:	aload_1
   27:	if_acmpne	34
   30:	iconst_1
   31:	goto	69
   34:	aload_2
   35:	ifnonnull	42
   38:	iconst_0
   39:	goto	69
   42:	aload_2
   43:	instanceof	#147; //class java/lang/Number
   46:	ifne	56
   49:	aload_2
   50:	instanceof	#149; //class java/lang/Character
   53:	ifeq	64
   56:	aload_2
   57:	aload_1
   58:	invokestatic	#155; //Method scala/runtime/BoxesRunTime.equals2:(Ljava/lang/Object;Ljava/lang/Object;)Z
   61:	goto	69
   64:	aload_2
   65:	aload_1
   66:	invokevirtual	#161; //Method java/lang/Object.equals:(Ljava/lang/Object;)Z
   69:	ifeq	77
   72:	iconst_1
   73:	istore_3
   74:	goto	5
   77:	iload	4
   79:	iconst_1
   80:	iadd
   81:	istore	4
   83:	goto	5
   86:	iload_3
   87:	ifeq	95
   90:	iload	4
   92:	goto	96
   95:	iconst_m1
   96:	ireturn
  LineNumberTable: 
   line 669: 0
   line 670: 3
   line 671: 5
   line 672: 18
   line 673: 72
   line 675: 77
   line 672: 83
   line 678: 86
   line 668: 96

  LocalVariableTable: 
   Start  Length  Slot  Name   Signature
   0      97      0    $this       Lscala/collection/Iterator;
   0      97      1    elem       Ljava/lang/Object;
   30      42      2    x0       Ljava/lang/Object;
   5      92      3    found       Z
   3      94      4    i       I


public static int indexWhere(scala.collection.Iterator, scala.Function1);
  Code:
   Stack=2, Locals=4, Args_size=2
   0:	iconst_0
   1:	istore_2
   2:	iconst_0
   3:	istore_3
   4:	iload_3
   5:	ifne	47
   8:	aload_0
   9:	invokeinterface	#17,  1; //InterfaceMethod scala/collection/Iterator.hasNext:()Z
   14:	ifeq	47
   17:	aload_1
   18:	aload_0
   19:	invokeinterface	#21,  1; //InterfaceMethod scala/collection/Iterator.next:()Ljava/lang/Object;
   24:	invokeinterface	#340,  2; //InterfaceMethod scala/Function1.apply:(Ljava/lang/Object;)Ljava/lang/Object;
   29:	invokestatic	#343; //Method scala/runtime/BoxesRunTime.unboxToBoolean:(Ljava/lang/Object;)Z
   32:	ifeq	40
   35:	iconst_1
   36:	istore_3
   37:	goto	4
   40:	iload_2
   41:	iconst_1
   42:	iadd
   43:	istore_2
   44:	goto	4
   47:	iload_3
   48:	ifeq	55
   51:	iload_2
   52:	goto	56
   55:	iconst_m1
   56:	ireturn
  LineNumberTable: 
   line 647: 0
   line 648: 2
   line 649: 4
   line 650: 17
   line 651: 35
   line 653: 40
   line 650: 44
   line 656: 47
   line 646: 56

  LocalVariableTable: 
   Start  Length  Slot  Name   Signature
   0      57      0    $this       Lscala/collection/Iterator;
   0      57      1    p       Lscala/Function1;
   2      55      2    i       I
   4      53      3    found       Z


public static scala.Option find(scala.collection.Iterator, scala.Function1);
  Code:
   Stack=3, Locals=4, Args_size=2
   0:	getstatic	#296; //Field scala/None$.MODULE$:Lscala/None$;
   3:	astore_2
   4:	aload_2
   5:	invokevirtual	#350; //Method scala/Option.isEmpty:()Z
   8:	ifeq	52
   11:	aload_0
   12:	invokeinterface	#17,  1; //InterfaceMethod scala/collection/Iterator.hasNext:()Z
   17:	ifeq	52
   20:	aload_0
   21:	invokeinterface	#21,  1; //InterfaceMethod scala/collection/Iterator.next:()Ljava/lang/Object;
   26:	astore_3
   27:	aload_1
   28:	aload_3
   29:	invokeinterface	#340,  2; //InterfaceMethod scala/Function1.apply:(Ljava/lang/Object;)Ljava/lang/Object;
   34:	invokestatic	#343; //Method scala/runtime/BoxesRunTime.unboxToBoolean:(Ljava/lang/Object;)Z
   37:	ifeq	4
   40:	new	#286; //class scala/Some
   43:	dup
   44:	aload_3
   45:	invokespecial	#291; //Method scala/Some."<init>":(Ljava/lang/Object;)V
   48:	astore_2
   49:	goto	4
   52:	aload_2
   53:	areturn
  LineNumberTable: 
   line 631: 0
   line 632: 4
   line 633: 20
   line 634: 27
   line 636: 52

  LocalVariableTable: 
   Start  Length  Slot  Name   Signature
   0      54      0    $this       Lscala/collection/Iterator;
   0      54      1    p       Lscala/Function1;
   4      49      2    res       Lscala/Option;
   27      25      3    e       Ljava/lang/Object;


public static boolean contains(scala.collection.Iterator, java.lang.Object);
  Code:
   Stack=5, Locals=2, Args_size=2
   0:	aload_0
   1:	new	#356; //class scala/collection/Iterator$$anonfun$contains$1
   4:	dup
   5:	aload_0
   6:	aload_1
   7:	invokespecial	#358; //Method scala/collection/Iterator$$anonfun$contains$1."<init>":(Lscala/collection/Iterator;Ljava/lang/Object;)V
   10:	invokeinterface	#362,  2; //InterfaceMethod scala/collection/Iterator.exists:(Lscala/Function1;)Z
   15:	ireturn
  LineNumberTable: 
   line 621: 0

  LocalVariableTable: 
   Start  Length  Slot  Name   Signature
   0      16      0    $this       Lscala/collection/Iterator;
   0      16      1    elem$5       Ljava/lang/Object;


public static boolean exists(scala.collection.Iterator, scala.Function1);
  Code:
   Stack=2, Locals=3, Args_size=2
   0:	iconst_0
   1:	istore_2
   2:	iload_2
   3:	ifne	34
   6:	aload_0
   7:	invokeinterface	#17,  1; //InterfaceMethod scala/collection/Iterator.hasNext:()Z
   12:	ifeq	34
   15:	aload_1
   16:	aload_0
   17:	invokeinterface	#21,  1; //InterfaceMethod scala/collection/Iterator.next:()Ljava/lang/Object;
   22:	invokeinterface	#340,  2; //InterfaceMethod scala/Function1.apply:(Ljava/lang/Object;)Ljava/lang/Object;
   27:	invokestatic	#343; //Method scala/runtime/BoxesRunTime.unboxToBoolean:(Ljava/lang/Object;)Z
   30:	istore_2
   31:	goto	2
   34:	iload_2
   35:	ireturn
  LineNumberTable: 
   line 612: 0
   line 613: 2
   line 614: 34

  LocalVariableTable: 
   Start  Length  Slot  Name   Signature
   0      36      0    $this       Lscala/collection/Iterator;
   0      36      1    p       Lscala/Function1;
   2      33      2    res       Z


public static boolean forall(scala.collection.Iterator, scala.Function1);
  Code:
   Stack=2, Locals=3, Args_size=2
   0:	iconst_1
   1:	istore_2
   2:	iload_2
   3:	ifeq	34
   6:	aload_0
   7:	invokeinterface	#17,  1; //InterfaceMethod scala/collection/Iterator.hasNext:()Z
   12:	ifeq	34
   15:	aload_1
   16:	aload_0
   17:	invokeinterface	#21,  1; //InterfaceMethod scala/collection/Iterator.next:()Ljava/lang/Object;
   22:	invokeinterface	#340,  2; //InterfaceMethod scala/Function1.apply:(Ljava/lang/Object;)Ljava/lang/Object;
   27:	invokestatic	#343; //Method scala/runtime/BoxesRunTime.unboxToBoolean:(Ljava/lang/Object;)Z
   30:	istore_2
   31:	goto	2
   34:	iload_2
   35:	ireturn
  LineNumberTable: 
   line 598: 0
   line 599: 2
   line 600: 34

  LocalVariableTable: 
   Start  Length  Slot  Name   Signature
   0      36      0    $this       Lscala/collection/Iterator;
   0      36      1    p       Lscala/Function1;
   2      33      2    res       Z


public static void foreach(scala.collection.Iterator, scala.Function1);
  Code:
   Stack=2, Locals=2, Args_size=2
   0:	aload_0
   1:	invokeinterface	#17,  1; //InterfaceMethod scala/collection/Iterator.hasNext:()Z
   6:	ifeq	25
   9:	aload_1
   10:	aload_0
   11:	invokeinterface	#21,  1; //InterfaceMethod scala/collection/Iterator.next:()Ljava/lang/Object;
   16:	invokeinterface	#340,  2; //InterfaceMethod scala/Function1.apply:(Ljava/lang/Object;)Ljava/lang/Object;
   21:	pop
   22:	goto	0
   25:	return
  LineNumberTable: 
   line 587: 0

  LocalVariableTable: 
   Start  Length  Slot  Name   Signature
   0      26      0    $this       Lscala/collection/Iterator;
   0      26      1    f       Lscala/Function1;


public static java.lang.Object zipAll(scala.collection.Iterator, scala.collection.Iterator, java.lang.Object, java.lang.Object);
  Code:
   Stack=6, Locals=4, Args_size=4
   0:	new	#372; //class scala/collection/Iterator$$anon$5
   3:	dup
   4:	aload_0
   5:	aload_1
   6:	aload_2
   7:	aload_3
   8:	invokespecial	#375; //Method scala/collection/Iterator$$anon$5."<init>":(Lscala/collection/Iterator;Lscala/collection/Iterator;Ljava/lang/Object;Ljava/lang/Object;)V
   11:	areturn
  LineNumberTable: 
   line 570: 0

  LocalVariableTable: 
   Start  Length  Slot  Name   Signature
   0      12      0    $this       Lscala/collection/Iterator;
   0      12      1    that$1       Lscala/collection/Iterator;
   0      12      2    thisElem$1       Ljava/lang/Object;
   0      12      3    thatElem$1       Ljava/lang/Object;


public static java.lang.Object zipWithIndex(scala.collection.Iterator);
  Code:
   Stack=3, Locals=1, Args_size=1
   0:	new	#381; //class scala/collection/Iterator$$anon$29
   3:	dup
   4:	aload_0
   5:	invokespecial	#382; //Method scala/collection/Iterator$$anon$29."<init>":(Lscala/collection/Iterator;)V
   8:	areturn
  LineNumberTable: 
   line 541: 0

  LocalVariableTable: 
   Start  Length  Slot  Name   Signature
   0      9      0    $this       Lscala/collection/Iterator;


public static java.lang.Object padTo(scala.collection.Iterator, int, java.lang.Object);
  Code:
   Stack=5, Locals=3, Args_size=3
   0:	new	#386; //class scala/collection/Iterator$$anon$28
   3:	dup
   4:	aload_0
   5:	iload_1
   6:	aload_2
   7:	invokespecial	#389; //Method scala/collection/Iterator$$anon$28."<init>":(Lscala/collection/Iterator;ILjava/lang/Object;)V
   10:	areturn
  LineNumberTable: 
   line 526: 0

  LocalVariableTable: 
   Start  Length  Slot  Name   Signature
   0      11      0    $this       Lscala/collection/Iterator;
   0      11      1    len$2       I
   0      11      2    elem$4       Ljava/lang/Object;


public static java.lang.Object zip(scala.collection.Iterator, scala.collection.Iterator);
  Code:
   Stack=4, Locals=2, Args_size=2
   0:	new	#395; //class scala/collection/Iterator$$anon$6
   3:	dup
   4:	aload_0
   5:	aload_1
   6:	invokespecial	#396; //Method scala/collection/Iterator$$anon$6."<init>":(Lscala/collection/Iterator;Lscala/collection/Iterator;)V
   9:	areturn
  LineNumberTable: 
   line 517: 0

  LocalVariableTable: 
   Start  Length  Slot  Name   Signature
   0      10      0    $this       Lscala/collection/Iterator;
   0      10      1    that$3       Lscala/collection/Iterator;


public static scala.collection.Iterator dropWhile(scala.collection.Iterator, scala.Function1);
  Code:
   Stack=5, Locals=3, Args_size=2
   0:	aload_0
   1:	invokeinterface	#401,  1; //InterfaceMethod scala/collection/Iterator.buffered:()Ljava/lang/Object;
   6:	astore_2
   7:	new	#403; //class scala/collection/Iterator$$anon$27
   10:	dup
   11:	aload_0
   12:	aload_1
   13:	aload_2
   14:	invokespecial	#406; //Method scala/collection/Iterator$$anon$27."<init>":(Lscala/collection/Iterator;Lscala/Function1;Ljava/lang/Object;)V
   17:	areturn
  LineNumberTable: 
   line 498: 0
   line 499: 7

  LocalVariableTable: 
   Start  Length  Slot  Name   Signature
   0      18      0    $this       Lscala/collection/Iterator;
   0      18      1    p$3       Lscala/Function1;
   7      10      2    self$3       Ljava/lang/Object;


public static scala.Tuple2 partition(scala.collection.Iterator, scala.Function1);
  Code:
   Stack=7, Locals=5, Args_size=2
   0:	aload_0
   1:	invokeinterface	#401,  1; //InterfaceMethod scala/collection/Iterator.buffered:()Ljava/lang/Object;
   6:	astore_2
   7:	new	#412; //class scala/collection/Iterator$PartitionIterator$1
   10:	dup
   11:	aload_0
   12:	aload_1
   13:	aload_2
   14:	invokespecial	#413; //Method scala/collection/Iterator$PartitionIterator$1."<init>":(Lscala/collection/Iterator;Lscala/Function1;Ljava/lang/Object;)V
   17:	astore_3
   18:	new	#412; //class scala/collection/Iterator$PartitionIterator$1
   21:	dup
   22:	aload_0
   23:	new	#415; //class scala/collection/Iterator$$anonfun$1
   26:	dup
   27:	aload_0
   28:	aload_1
   29:	invokespecial	#417; //Method scala/collection/Iterator$$anonfun$1."<init>":(Lscala/collection/Iterator;Lscala/Function1;)V
   32:	aload_2
   33:	invokespecial	#413; //Method scala/collection/Iterator$PartitionIterator$1."<init>":(Lscala/collection/Iterator;Lscala/Function1;Ljava/lang/Object;)V
   36:	astore	4
   38:	aload_3
   39:	aload	4
   41:	invokevirtual	#421; //Method scala/collection/Iterator$PartitionIterator$1.other_$eq:(Lscala/collection/Iterator$PartitionIterator$1;)V
   44:	aload	4
   46:	aload_3
   47:	invokevirtual	#421; //Method scala/collection/Iterator$PartitionIterator$1.other_$eq:(Lscala/collection/Iterator$PartitionIterator$1;)V
   50:	new	#248; //class scala/Tuple2
   53:	dup
   54:	aload_3
   55:	aload	4
   57:	invokespecial	#256; //Method scala/Tuple2."<init>":(Ljava/lang/Object;Ljava/lang/Object;)V
   60:	areturn
  LineNumberTable: 
   line 472: 0
   line 484: 7
   line 485: 18
   line 488: 38
   line 486: 41
   line 487: 44
   line 488: 50

  LocalVariableTable: 
   Start  Length  Slot  Name   Signature
   0      61      0    $this       Lscala/collection/Iterator;
   0      61      1    p$5       Lscala/Function1;
   7      53      2    self$2       Ljava/lang/Object;
   18      42      3    l       Lscala/collection/Iterator$PartitionIterator$1;
   38      22      4    r       Lscala/collection/Iterator$PartitionIterator$1;


public static scala.collection.Iterator takeWhile(scala.collection.Iterator, scala.Function1);
  Code:
   Stack=4, Locals=2, Args_size=2
   0:	new	#429; //class scala/collection/Iterator$$anon$26
   3:	dup
   4:	aload_0
   5:	aload_1
   6:	invokespecial	#430; //Method scala/collection/Iterator$$anon$26."<init>":(Lscala/collection/Iterator;Lscala/Function1;)V
   9:	areturn
  LineNumberTable: 
   line 449: 0

  LocalVariableTable: 
   Start  Length  Slot  Name   Signature
   0      10      0    $this       Lscala/collection/Iterator;
   0      10      1    p$2       Lscala/Function1;


public static scala.collection.Iterator partialMap(scala.collection.Iterator, scala.PartialFunction);
  Code:
   Stack=5, Locals=3, Args_size=2
   0:	aload_0
   1:	invokeinterface	#401,  1; //InterfaceMethod scala/collection/Iterator.buffered:()Ljava/lang/Object;
   6:	astore_2
   7:	new	#435; //class scala/collection/Iterator$$anon$25
   10:	dup
   11:	aload_0
   12:	aload_1
   13:	aload_2
   14:	invokespecial	#438; //Method scala/collection/Iterator$$anon$25."<init>":(Lscala/collection/Iterator;Lscala/PartialFunction;Ljava/lang/Object;)V
   17:	areturn
  LineNumberTable: 
   line 434: 0
   line 435: 7

  LocalVariableTable: 
   Start  Length  Slot  Name   Signature
   0      18      0    $this       Lscala/collection/Iterator;
   0      18      1    pf$1       Lscala/PartialFunction;
   7      10      2    self$1       Ljava/lang/Object;


public static scala.collection.Iterator filterNot(scala.collection.Iterator, scala.Function1);
  Code:
   Stack=5, Locals=2, Args_size=2
   0:	aload_0
   1:	new	#444; //class scala/collection/Iterator$$anonfun$filterNot$1
   4:	dup
   5:	aload_0
   6:	aload_1
   7:	invokespecial	#445; //Method scala/collection/Iterator$$anonfun$filterNot$1."<init>":(Lscala/collection/Iterator;Lscala/Function1;)V
   10:	invokeinterface	#449,  2; //InterfaceMethod scala/collection/Iterator.filter:(Lscala/Function1;)Lscala/collection/Iterator;
   15:	areturn
  LineNumberTable: 
   line 424: 0

  LocalVariableTable: 
   Start  Length  Slot  Name   Signature
   0      16      0    $this       Lscala/collection/Iterator;
   0      16      1    p$4       Lscala/Function1;


public static scala.collection.Iterator$WithFilter withFilter(scala.collection.Iterator, scala.Function1);
  Code:
   Stack=4, Locals=2, Args_size=2
   0:	new	#454; //class scala/collection/Iterator$WithFilter
   3:	dup
   4:	aload_0
   5:	aload_1
   6:	invokespecial	#455; //Method scala/collection/Iterator$WithFilter."<init>":(Lscala/collection/Iterator;Lscala/Function1;)V
   9:	areturn
  LineNumberTable: 
   line 370: 0

  LocalVariableTable: 
   Start  Length  Slot  Name   Signature
   0      10      0    $this       Lscala/collection/Iterator;
   0      10      1    p       Lscala/Function1;


public static scala.collection.Iterator filter(scala.collection.Iterator, scala.Function1);
  Code:
   Stack=4, Locals=2, Args_size=2
   0:	new	#457; //class scala/collection/Iterator$$anon$22
   3:	dup
   4:	aload_0
   5:	aload_1
   6:	invokespecial	#458; //Method scala/collection/Iterator$$anon$22."<init>":(Lscala/collection/Iterator;Lscala/Function1;)V
   9:	areturn
  LineNumberTable: 
   line 354: 0

  LocalVariableTable: 
   Start  Length  Slot  Name   Signature
   0      10      0    $this       Lscala/collection/Iterator;
   0      10      1    p$1       Lscala/Function1;


public static scala.collection.Iterator flatMap(scala.collection.Iterator, scala.Function1);
  Code:
   Stack=4, Locals=2, Args_size=2
   0:	new	#462; //class scala/collection/Iterator$$anon$21
   3:	dup
   4:	aload_0
   5:	aload_1
   6:	invokespecial	#463; //Method scala/collection/Iterator$$anon$21."<init>":(Lscala/collection/Iterator;Lscala/Function1;)V
   9:	areturn
  LineNumberTable: 
   line 340: 0

  LocalVariableTable: 
   Start  Length  Slot  Name   Signature
   0      10      0    $this       Lscala/collection/Iterator;
   0      10      1    f$2       Lscala/Function1;


public static scala.collection.Iterator $plus$plus(scala.collection.Iterator, scala.Function0);
  Code:
   Stack=4, Locals=2, Args_size=2
   0:	new	#467; //class scala/collection/Iterator$$anon$20
   3:	dup
   4:	aload_0
   5:	aload_1
   6:	invokespecial	#470; //Method scala/collection/Iterator$$anon$20."<init>":(Lscala/collection/Iterator;Lscala/Function0;)V
   9:	areturn
  LineNumberTable: 
   line 318: 0

  LocalVariableTable: 
   Start  Length  Slot  Name   Signature
   0      10      0    $this       Lscala/collection/Iterator;
   0      10      1    that$2       Lscala/Function0;


public static scala.collection.Iterator map(scala.collection.Iterator, scala.Function1);
  Code:
   Stack=4, Locals=2, Args_size=2
   0:	new	#475; //class scala/collection/Iterator$$anon$19
   3:	dup
   4:	aload_0
   5:	aload_1
   6:	invokespecial	#476; //Method scala/collection/Iterator$$anon$19."<init>":(Lscala/collection/Iterator;Lscala/Function1;)V
   9:	areturn
  LineNumberTable: 
   line 310: 0

  LocalVariableTable: 
   Start  Length  Slot  Name   Signature
   0      10      0    $this       Lscala/collection/Iterator;
   0      10      1    f$1       Lscala/Function1;


public static scala.collection.Iterator slice(scala.collection.Iterator, int, int);
  Code:
   Stack=3, Locals=3, Args_size=3
   0:	aload_0
   1:	iload_1
   2:	invokeinterface	#483,  2; //InterfaceMethod scala/collection/Iterator.drop:(I)Lscala/collection/Iterator;
   7:	iload_2
   8:	iload_1
   9:	isub
   10:	invokeinterface	#486,  2; //InterfaceMethod scala/collection/Iterator.take:(I)Lscala/collection/Iterator;
   15:	areturn
  LineNumberTable: 
   line 305: 0

  LocalVariableTable: 
   Start  Length  Slot  Name   Signature
   0      16      0    $this       Lscala/collection/Iterator;
   0      16      1    from       I
   0      16      2    until       I


public static scala.collection.Iterator drop(scala.collection.Iterator, int);
  Code:
   Stack=2, Locals=2, Args_size=2
   0:	aload_0
   1:	iload_1
   2:	invokestatic	#492; //Method loop$1:(Lscala/collection/Iterator;I)Lscala/collection/Iterator;
   5:	areturn
  LineNumberTable: 
   line 296: 0

  LocalVariableTable: 
   Start  Length  Slot  Name   Signature
   0      6      0    $this       Lscala/collection/Iterator;
   0      6      1    n       I


public static scala.collection.Iterator take(scala.collection.Iterator, int);
  Code:
   Stack=4, Locals=2, Args_size=2
   0:	new	#495; //class scala/collection/Iterator$$anon$18
   3:	dup
   4:	aload_0
   5:	iload_1
   6:	invokespecial	#498; //Method scala/collection/Iterator$$anon$18."<init>":(Lscala/collection/Iterator;I)V
   9:	areturn
  LineNumberTable: 
   line 276: 0

  LocalVariableTable: 
   Start  Length  Slot  Name   Signature
   0      10      0    $this       Lscala/collection/Iterator;
   0      10      1    n$1       I


public static int sliding$default$2(scala.collection.Iterator);
  Code:
   Stack=1, Locals=1, Args_size=1
   0:	iconst_1
   1:	ireturn
  LineNumberTable: 
   line 940: 0

  LocalVariableTable: 
   Start  Length  Slot  Name   Signature
   0      2      0    $this       Lscala/collection/Iterator;


}

