Compiled from "IterableProxyLike.scala"
public abstract class scala.collection.IterableProxyLike$class extends java.lang.Object
  SourceFile: "IterableProxyLike.scala"
  Scala: length = 0x
   
  minor version: 0
  major version: 49
  Constant pool:
const #1 = Asciz	SourceFile;
const #2 = Asciz	IterableProxyLike.scala;
const #3 = Asciz	$init$;
const #4 = Asciz	(Lscala/collection/IterableProxyLike;)V;
const #5 = Asciz	Code;
const #6 = Asciz	LineNumberTable;
const #7 = Asciz	$this;
const #8 = Asciz	Lscala/collection/IterableProxyLike;;
const #9 = Asciz	LocalVariableTable;
const #10 = Asciz	view;
const #11 = Asciz	(Lscala/collection/IterableProxyLike;II)Lscala/collection/IterableView;;
const #12 = Asciz	scala/collection/TraversableProxyLike;
const #13 = class	#12;	//  scala/collection/TraversableProxyLike
const #14 = Asciz	self;
const #15 = Asciz	()Lscala/collection/TraversableLike;;
const #16 = NameAndType	#14:#15;//  self:()Lscala/collection/TraversableLike;
const #17 = InterfaceMethod	#13.#16;	//  scala/collection/TraversableProxyLike.self:()Lscala/collection/TraversableLike;
const #18 = Asciz	scala/collection/IterableLike;
const #19 = class	#18;	//  scala/collection/IterableLike
const #20 = Asciz	(II)Lscala/collection/IterableView;;
const #21 = NameAndType	#10:#20;//  view:(II)Lscala/collection/IterableView;
const #22 = InterfaceMethod	#19.#21;	//  scala/collection/IterableLike.view:(II)Lscala/collection/IterableView;
const #23 = Asciz	from;
const #24 = Asciz	I;
const #25 = Asciz	until;
const #26 = Asciz	(Lscala/collection/IterableProxyLike;)Ljava/lang/Object;;
const #27 = Asciz	()Ljava/lang/Object;;
const #28 = NameAndType	#10:#27;//  view:()Ljava/lang/Object;
const #29 = InterfaceMethod	#19.#28;	//  scala/collection/IterableLike.view:()Ljava/lang/Object;
const #30 = Asciz	toStream;
const #31 = Asciz	(Lscala/collection/IterableProxyLike;)Lscala/collection/immutable/Stream;;
const #32 = Asciz	()Lscala/collection/immutable/Stream;;
const #33 = NameAndType	#30:#32;//  toStream:()Lscala/collection/immutable/Stream;
const #34 = InterfaceMethod	#19.#33;	//  scala/collection/IterableLike.toStream:()Lscala/collection/immutable/Stream;
const #35 = Asciz	sameElements;
const #36 = Asciz	(Lscala/collection/IterableProxyLike;Lscala/collection/Iterable;)Z;
const #37 = Asciz	(Lscala/collection/Iterable;)Z;
const #38 = NameAndType	#35:#37;//  sameElements:(Lscala/collection/Iterable;)Z
const #39 = InterfaceMethod	#19.#38;	//  scala/collection/IterableLike.sameElements:(Lscala/collection/Iterable;)Z
const #40 = Asciz	that;
const #41 = Asciz	Lscala/collection/Iterable;;
const #42 = Asciz	dropRight;
const #43 = Asciz	(Lscala/collection/IterableProxyLike;I)Lscala/collection/IterableLike;;
const #44 = Asciz	(I)Ljava/lang/Object;;
const #45 = NameAndType	#42:#44;//  dropRight:(I)Ljava/lang/Object;
const #46 = InterfaceMethod	#19.#45;	//  scala/collection/IterableLike.dropRight:(I)Ljava/lang/Object;
const #47 = Asciz	n;
const #48 = Asciz	takeRight;
const #49 = NameAndType	#48:#44;//  takeRight:(I)Ljava/lang/Object;
const #50 = InterfaceMethod	#19.#49;	//  scala/collection/IterableLike.takeRight:(I)Ljava/lang/Object;
const #51 = Asciz	head;
const #52 = NameAndType	#51:#27;//  head:()Ljava/lang/Object;
const #53 = InterfaceMethod	#19.#52;	//  scala/collection/IterableLike.head:()Ljava/lang/Object;
const #54 = Asciz	zipWithIndex;
const #55 = Asciz	(Lscala/collection/IterableProxyLike;Lscala/collection/generic/CanBuildFrom;)Ljava/lang/Object;;
const #56 = Asciz	(Lscala/collection/generic/CanBuildFrom;)Ljava/lang/Object;;
const #57 = NameAndType	#54:#56;//  zipWithIndex:(Lscala/collection/generic/CanBuildFrom;)Ljava/lang/Object;
const #58 = InterfaceMethod	#19.#57;	//  scala/collection/IterableLike.zipWithIndex:(Lscala/collection/generic/CanBuildFrom;)Ljava/lang/Object;
const #59 = Asciz	bf;
const #60 = Asciz	Lscala/collection/generic/CanBuildFrom;;
const #61 = Asciz	zipAll;
const #62 = Asciz	(Lscala/collection/IterableProxyLike;Lscala/collection/Iterable;Ljava/lang/Object;Ljava/lang/Object;Lscala/collection/generic/CanBuildFrom;)Ljava/lang/Object;;
const #63 = Asciz	(Lscala/collection/Iterable;Ljava/lang/Object;Ljava/lang/Object;Lscala/collection/generic/CanBuildFrom;)Ljava/lang/Object;;
const #64 = NameAndType	#61:#63;//  zipAll:(Lscala/collection/Iterable;Ljava/lang/Object;Ljava/lang/Object;Lscala/collection/generic/CanBuildFrom;)Ljava/lang/Object;
const #65 = InterfaceMethod	#19.#64;	//  scala/collection/IterableLike.zipAll:(Lscala/collection/Iterable;Ljava/lang/Object;Ljava/lang/Object;Lscala/collection/generic/CanBuildFrom;)Ljava/lang/Object;
const #66 = Asciz	thisElem;
const #67 = Asciz	Ljava/lang/Object;;
const #68 = Asciz	thatElem;
const #69 = Asciz	zip;
const #70 = Asciz	(Lscala/collection/IterableProxyLike;Lscala/collection/Iterable;Lscala/collection/generic/CanBuildFrom;)Ljava/lang/Object;;
const #71 = Asciz	(Lscala/collection/Iterable;Lscala/collection/generic/CanBuildFrom;)Ljava/lang/Object;;
const #72 = NameAndType	#69:#71;//  zip:(Lscala/collection/Iterable;Lscala/collection/generic/CanBuildFrom;)Ljava/lang/Object;
const #73 = InterfaceMethod	#19.#72;	//  scala/collection/IterableLike.zip:(Lscala/collection/Iterable;Lscala/collection/generic/CanBuildFrom;)Ljava/lang/Object;
const #74 = Asciz	toIterable;
const #75 = Asciz	(Lscala/collection/IterableProxyLike;)Lscala/collection/Iterable;;
const #76 = Asciz	()Lscala/collection/Iterable;;
const #77 = NameAndType	#74:#76;//  toIterable:()Lscala/collection/Iterable;
const #78 = InterfaceMethod	#19.#77;	//  scala/collection/IterableLike.toIterable:()Lscala/collection/Iterable;
const #79 = Asciz	reduceRight;
const #80 = Asciz	(Lscala/collection/IterableProxyLike;Lscala/Function2;)Ljava/lang/Object;;
const #81 = Asciz	(Lscala/Function2;)Ljava/lang/Object;;
const #82 = NameAndType	#79:#81;//  reduceRight:(Lscala/Function2;)Ljava/lang/Object;
const #83 = InterfaceMethod	#19.#82;	//  scala/collection/IterableLike.reduceRight:(Lscala/Function2;)Ljava/lang/Object;
const #84 = Asciz	op;
const #85 = Asciz	Lscala/Function2;;
const #86 = Asciz	foldRight;
const #87 = Asciz	(Lscala/collection/IterableProxyLike;Ljava/lang/Object;Lscala/Function2;)Ljava/lang/Object;;
const #88 = Asciz	(Ljava/lang/Object;Lscala/Function2;)Ljava/lang/Object;;
const #89 = NameAndType	#86:#88;//  foldRight:(Ljava/lang/Object;Lscala/Function2;)Ljava/lang/Object;
const #90 = InterfaceMethod	#19.#89;	//  scala/collection/IterableLike.foldRight:(Ljava/lang/Object;Lscala/Function2;)Ljava/lang/Object;
const #91 = Asciz	z;
const #92 = Asciz	isEmpty;
const #93 = Asciz	(Lscala/collection/IterableProxyLike;)Z;
const #94 = Asciz	()Z;
const #95 = NameAndType	#92:#94;//  isEmpty:()Z
const #96 = InterfaceMethod	#19.#95;	//  scala/collection/IterableLike.isEmpty:()Z
const #97 = Asciz	foreach;
const #98 = Asciz	(Lscala/collection/IterableProxyLike;Lscala/Function1;)V;
const #99 = Asciz	(Lscala/Function1;)V;
const #100 = NameAndType	#97:#99;//  foreach:(Lscala/Function1;)V
const #101 = InterfaceMethod	#19.#100;	//  scala/collection/IterableLike.foreach:(Lscala/Function1;)V
const #102 = Asciz	f;
const #103 = Asciz	Lscala/Function1;;
const #104 = Asciz	iterator;
const #105 = Asciz	(Lscala/collection/IterableProxyLike;)Lscala/collection/Iterator;;
const #106 = Asciz	()Lscala/collection/Iterator;;
const #107 = NameAndType	#104:#106;//  iterator:()Lscala/collection/Iterator;
const #108 = InterfaceMethod	#19.#107;	//  scala/collection/IterableLike.iterator:()Lscala/collection/Iterator;
const #109 = Asciz	Scala;
const #110 = Asciz	scala/collection/IterableProxyLike$class;
const #111 = class	#110;	//  scala/collection/IterableProxyLike$class
const #112 = Asciz	java/lang/Object;
const #113 = class	#112;	//  java/lang/Object

{
public static void $init$(scala.collection.IterableProxyLike);
  Code:
   Stack=0, Locals=1, Args_size=1
   0:	return
  LineNumberTable: 
   line 28: 0

  LocalVariableTable: 
   Start  Length  Slot  Name   Signature
   0      1      0    $this       Lscala/collection/IterableProxyLike;


public static scala.collection.IterableView view(scala.collection.IterableProxyLike, int, int);
  Code:
   Stack=3, Locals=3, Args_size=3
   0:	aload_0
   1:	invokeinterface	#17,  1; //InterfaceMethod scala/collection/TraversableProxyLike.self:()Lscala/collection/TraversableLike;
   6:	checkcast	#19; //class scala/collection/IterableLike
   9:	iload_1
   10:	iload_2
   11:	invokeinterface	#22,  3; //InterfaceMethod scala/collection/IterableLike.view:(II)Lscala/collection/IterableView;
   16:	areturn
  LineNumberTable: 
   line 46: 0

  LocalVariableTable: 
   Start  Length  Slot  Name   Signature
   0      17      0    $this       Lscala/collection/IterableProxyLike;
   0      17      1    from       I
   0      17      2    until       I


public static java.lang.Object view(scala.collection.IterableProxyLike);
  Code:
   Stack=1, Locals=1, Args_size=1
   0:	aload_0
   1:	invokeinterface	#17,  1; //InterfaceMethod scala/collection/TraversableProxyLike.self:()Lscala/collection/TraversableLike;
   6:	checkcast	#19; //class scala/collection/IterableLike
   9:	invokeinterface	#29,  1; //InterfaceMethod scala/collection/IterableLike.view:()Ljava/lang/Object;
   14:	areturn
  LineNumberTable: 
   line 45: 0

  LocalVariableTable: 
   Start  Length  Slot  Name   Signature
   0      15      0    $this       Lscala/collection/IterableProxyLike;


public static scala.collection.immutable.Stream toStream(scala.collection.IterableProxyLike);
  Code:
   Stack=1, Locals=1, Args_size=1
   0:	aload_0
   1:	invokeinterface	#17,  1; //InterfaceMethod scala/collection/TraversableProxyLike.self:()Lscala/collection/TraversableLike;
   6:	checkcast	#19; //class scala/collection/IterableLike
   9:	invokeinterface	#34,  1; //InterfaceMethod scala/collection/IterableLike.toStream:()Lscala/collection/immutable/Stream;
   14:	areturn
  LineNumberTable: 
   line 44: 0

  LocalVariableTable: 
   Start  Length  Slot  Name   Signature
   0      15      0    $this       Lscala/collection/IterableProxyLike;


public static boolean sameElements(scala.collection.IterableProxyLike, scala.collection.Iterable);
  Code:
   Stack=2, Locals=2, Args_size=2
   0:	aload_0
   1:	invokeinterface	#17,  1; //InterfaceMethod scala/collection/TraversableProxyLike.self:()Lscala/collection/TraversableLike;
   6:	checkcast	#19; //class scala/collection/IterableLike
   9:	aload_1
   10:	invokeinterface	#39,  2; //InterfaceMethod scala/collection/IterableLike.sameElements:(Lscala/collection/Iterable;)Z
   15:	ireturn
  LineNumberTable: 
   line 43: 0

  LocalVariableTable: 
   Start  Length  Slot  Name   Signature
   0      16      0    $this       Lscala/collection/IterableProxyLike;
   0      16      1    that       Lscala/collection/Iterable;


public static scala.collection.IterableLike dropRight(scala.collection.IterableProxyLike, int);
  Code:
   Stack=2, Locals=2, Args_size=2
   0:	aload_0
   1:	invokeinterface	#17,  1; //InterfaceMethod scala/collection/TraversableProxyLike.self:()Lscala/collection/TraversableLike;
   6:	checkcast	#19; //class scala/collection/IterableLike
   9:	iload_1
   10:	invokeinterface	#46,  2; //InterfaceMethod scala/collection/IterableLike.dropRight:(I)Ljava/lang/Object;
   15:	checkcast	#19; //class scala/collection/IterableLike
   18:	areturn
  LineNumberTable: 
   line 42: 0

  LocalVariableTable: 
   Start  Length  Slot  Name   Signature
   0      19      0    $this       Lscala/collection/IterableProxyLike;
   0      19      1    n       I


public static scala.collection.IterableLike takeRight(scala.collection.IterableProxyLike, int);
  Code:
   Stack=2, Locals=2, Args_size=2
   0:	aload_0
   1:	invokeinterface	#17,  1; //InterfaceMethod scala/collection/TraversableProxyLike.self:()Lscala/collection/TraversableLike;
   6:	checkcast	#19; //class scala/collection/IterableLike
   9:	iload_1
   10:	invokeinterface	#50,  2; //InterfaceMethod scala/collection/IterableLike.takeRight:(I)Ljava/lang/Object;
   15:	checkcast	#19; //class scala/collection/IterableLike
   18:	areturn
  LineNumberTable: 
   line 41: 0

  LocalVariableTable: 
   Start  Length  Slot  Name   Signature
   0      19      0    $this       Lscala/collection/IterableProxyLike;
   0      19      1    n       I


public static java.lang.Object head(scala.collection.IterableProxyLike);
  Code:
   Stack=1, Locals=1, Args_size=1
   0:	aload_0
   1:	invokeinterface	#17,  1; //InterfaceMethod scala/collection/TraversableProxyLike.self:()Lscala/collection/TraversableLike;
   6:	checkcast	#19; //class scala/collection/IterableLike
   9:	invokeinterface	#53,  1; //InterfaceMethod scala/collection/IterableLike.head:()Ljava/lang/Object;
   14:	areturn
  LineNumberTable: 
   line 40: 0

  LocalVariableTable: 
   Start  Length  Slot  Name   Signature
   0      15      0    $this       Lscala/collection/IterableProxyLike;


public static java.lang.Object zipWithIndex(scala.collection.IterableProxyLike, scala.collection.generic.CanBuildFrom);
  Code:
   Stack=2, Locals=2, Args_size=2
   0:	aload_0
   1:	invokeinterface	#17,  1; //InterfaceMethod scala/collection/TraversableProxyLike.self:()Lscala/collection/TraversableLike;
   6:	checkcast	#19; //class scala/collection/IterableLike
   9:	aload_1
   10:	invokeinterface	#58,  2; //InterfaceMethod scala/collection/IterableLike.zipWithIndex:(Lscala/collection/generic/CanBuildFrom;)Ljava/lang/Object;
   15:	areturn
  LineNumberTable: 
   line 39: 0

  LocalVariableTable: 
   Start  Length  Slot  Name   Signature
   0      16      0    $this       Lscala/collection/IterableProxyLike;
   0      16      1    bf       Lscala/collection/generic/CanBuildFrom;


public static java.lang.Object zipAll(scala.collection.IterableProxyLike, scala.collection.Iterable, java.lang.Object, java.lang.Object, scala.collection.generic.CanBuildFrom);
  Code:
   Stack=5, Locals=5, Args_size=5
   0:	aload_0
   1:	invokeinterface	#17,  1; //InterfaceMethod scala/collection/TraversableProxyLike.self:()Lscala/collection/TraversableLike;
   6:	checkcast	#19; //class scala/collection/IterableLike
   9:	aload_1
   10:	aload_2
   11:	aload_3
   12:	aload	4
   14:	invokeinterface	#65,  5; //InterfaceMethod scala/collection/IterableLike.zipAll:(Lscala/collection/Iterable;Ljava/lang/Object;Ljava/lang/Object;Lscala/collection/generic/CanBuildFrom;)Ljava/lang/Object;
   19:	areturn
  LineNumberTable: 
   line 38: 0

  LocalVariableTable: 
   Start  Length  Slot  Name   Signature
   0      20      0    $this       Lscala/collection/IterableProxyLike;
   0      20      1    that       Lscala/collection/Iterable;
   0      20      2    thisElem       Ljava/lang/Object;
   0      20      3    thatElem       Ljava/lang/Object;
   0      20      4    bf       Lscala/collection/generic/CanBuildFrom;


public static java.lang.Object zip(scala.collection.IterableProxyLike, scala.collection.Iterable, scala.collection.generic.CanBuildFrom);
  Code:
   Stack=3, Locals=3, Args_size=3
   0:	aload_0
   1:	invokeinterface	#17,  1; //InterfaceMethod scala/collection/TraversableProxyLike.self:()Lscala/collection/TraversableLike;
   6:	checkcast	#19; //class scala/collection/IterableLike
   9:	aload_1
   10:	aload_2
   11:	invokeinterface	#73,  3; //InterfaceMethod scala/collection/IterableLike.zip:(Lscala/collection/Iterable;Lscala/collection/generic/CanBuildFrom;)Ljava/lang/Object;
   16:	areturn
  LineNumberTable: 
   line 37: 0

  LocalVariableTable: 
   Start  Length  Slot  Name   Signature
   0      17      0    $this       Lscala/collection/IterableProxyLike;
   0      17      1    that       Lscala/collection/Iterable;
   0      17      2    bf       Lscala/collection/generic/CanBuildFrom;


public static scala.collection.Iterable toIterable(scala.collection.IterableProxyLike);
  Code:
   Stack=1, Locals=1, Args_size=1
   0:	aload_0
   1:	invokeinterface	#17,  1; //InterfaceMethod scala/collection/TraversableProxyLike.self:()Lscala/collection/TraversableLike;
   6:	checkcast	#19; //class scala/collection/IterableLike
   9:	invokeinterface	#78,  1; //InterfaceMethod scala/collection/IterableLike.toIterable:()Lscala/collection/Iterable;
   14:	areturn
  LineNumberTable: 
   line 36: 0

  LocalVariableTable: 
   Start  Length  Slot  Name   Signature
   0      15      0    $this       Lscala/collection/IterableProxyLike;


public static java.lang.Object reduceRight(scala.collection.IterableProxyLike, scala.Function2);
  Code:
   Stack=2, Locals=2, Args_size=2
   0:	aload_0
   1:	invokeinterface	#17,  1; //InterfaceMethod scala/collection/TraversableProxyLike.self:()Lscala/collection/TraversableLike;
   6:	checkcast	#19; //class scala/collection/IterableLike
   9:	aload_1
   10:	invokeinterface	#83,  2; //InterfaceMethod scala/collection/IterableLike.reduceRight:(Lscala/Function2;)Ljava/lang/Object;
   15:	areturn
  LineNumberTable: 
   line 35: 0

  LocalVariableTable: 
   Start  Length  Slot  Name   Signature
   0      16      0    $this       Lscala/collection/IterableProxyLike;
   0      16      1    op       Lscala/Function2;


public static java.lang.Object foldRight(scala.collection.IterableProxyLike, java.lang.Object, scala.Function2);
  Code:
   Stack=3, Locals=3, Args_size=3
   0:	aload_0
   1:	invokeinterface	#17,  1; //InterfaceMethod scala/collection/TraversableProxyLike.self:()Lscala/collection/TraversableLike;
   6:	checkcast	#19; //class scala/collection/IterableLike
   9:	aload_1
   10:	aload_2
   11:	invokeinterface	#90,  3; //InterfaceMethod scala/collection/IterableLike.foldRight:(Ljava/lang/Object;Lscala/Function2;)Ljava/lang/Object;
   16:	areturn
  LineNumberTable: 
   line 34: 0

  LocalVariableTable: 
   Start  Length  Slot  Name   Signature
   0      17      0    $this       Lscala/collection/IterableProxyLike;
   0      17      1    z       Ljava/lang/Object;
   0      17      2    op       Lscala/Function2;


public static boolean isEmpty(scala.collection.IterableProxyLike);
  Code:
   Stack=1, Locals=1, Args_size=1
   0:	aload_0
   1:	invokeinterface	#17,  1; //InterfaceMethod scala/collection/TraversableProxyLike.self:()Lscala/collection/TraversableLike;
   6:	checkcast	#19; //class scala/collection/IterableLike
   9:	invokeinterface	#96,  1; //InterfaceMethod scala/collection/IterableLike.isEmpty:()Z
   14:	ireturn
  LineNumberTable: 
   line 33: 0

  LocalVariableTable: 
   Start  Length  Slot  Name   Signature
   0      15      0    $this       Lscala/collection/IterableProxyLike;


public static void foreach(scala.collection.IterableProxyLike, scala.Function1);
  Code:
   Stack=2, Locals=2, Args_size=2
   0:	aload_0
   1:	invokeinterface	#17,  1; //InterfaceMethod scala/collection/TraversableProxyLike.self:()Lscala/collection/TraversableLike;
   6:	checkcast	#19; //class scala/collection/IterableLike
   9:	aload_1
   10:	invokeinterface	#101,  2; //InterfaceMethod scala/collection/IterableLike.foreach:(Lscala/Function1;)V
   15:	return
  LineNumberTable: 
   line 32: 0

  LocalVariableTable: 
   Start  Length  Slot  Name   Signature
   0      16      0    $this       Lscala/collection/IterableProxyLike;
   0      16      1    f       Lscala/Function1;


public static scala.collection.Iterator iterator(scala.collection.IterableProxyLike);
  Code:
   Stack=1, Locals=1, Args_size=1
   0:	aload_0
   1:	invokeinterface	#17,  1; //InterfaceMethod scala/collection/TraversableProxyLike.self:()Lscala/collection/TraversableLike;
   6:	checkcast	#19; //class scala/collection/IterableLike
   9:	invokeinterface	#108,  1; //InterfaceMethod scala/collection/IterableLike.iterator:()Lscala/collection/Iterator;
   14:	areturn
  LineNumberTable: 
   line 31: 0

  LocalVariableTable: 
   Start  Length  Slot  Name   Signature
   0      15      0    $this       Lscala/collection/IterableProxyLike;


}

