Compiled from "Iterator.scala"
public final class scala.collection.Iterator$WithFilter$$anonfun$withFilter$1 extends java.lang.Object implements scala.Function1,scala.ScalaObject,java.io.Serializable
  SourceFile: "Iterator.scala"
  Scala: length = 0x
   
  InnerClass: 
   public final WithFilter=class scala/collection/Iterator$WithFilter of class scala/collection/Iterator
   public final $anonfun$withFilter$1=class scala/collection/Iterator$WithFilter$$anonfun$withFilter$1 of class scala/collection/Iterator$WithFilter
  minor version: 0
  major version: 49
  Constant pool:
Asciz	SourceFile;
Asciz	Iterator.scala;
Asciz	<clinit>;
Asciz	()V;
Asciz	Code;
Asciz	serialVersionUID;
Asciz	J;
Asciz	scala/collection/Iterator$WithFilter$$anonfun$withFilter$1;
class	scala/collection/Iterator$WithFilter$$anonfun$withFilter$1
NameAndType	serialVersionUID:J
Field	scala/collection/Iterator$WithFilter$$anonfun$withFilter$1.serialVersionUID:J
Asciz	q$1;
Asciz	Lscala/Function1;;
Asciz	$outer;
Asciz	Lscala/collection/Iterator$WithFilter;;
Asciz	<init>;
Asciz	(Lscala/collection/Iterator$WithFilter;Lscala/Function1;)V;
Asciz	LineNumberTable;
Asciz	java/lang/NullPointerException;
class	java/lang/NullPointerException
NameAndType	"<init>":()V
Method	java/lang/NullPointerException."<init>":()V
NameAndType	$outer:Lscala/collection/Iterator$WithFilter;
Field	scala/collection/Iterator$WithFilter$$anonfun$withFilter$1.$outer:Lscala/collection/Iterator$WithFilter;
NameAndType	q$1:Lscala/Function1;
Field	scala/collection/Iterator$WithFilter$$anonfun$withFilter$1.q$1:Lscala/Function1;
Asciz	java/lang/Object;
class	java/lang/Object
Method	java/lang/Object."<init>":()V
Asciz	scala/Function1$class;
class	scala/Function1$class
Asciz	$init$;
Asciz	(Lscala/Function1;)V;
NameAndType	$init$:(Lscala/Function1;)V
Method	scala/Function1$class.$init$:(Lscala/Function1;)V
Asciz	this;
Asciz	Lscala/collection/Iterator$WithFilter$$anonfun$withFilter$1;;
Asciz	LocalVariableTable;
Asciz	(Lscala/collection/Iterator<TA;>.WithFilter;)V;
Asciz	Signature;
Asciz	apply;
Asciz	(Ljava/lang/Object;)Ljava/lang/Object;;
Asciz	(Ljava/lang/Object;)Z;
NameAndType	apply:(Ljava/lang/Object;)Z
Method	scala/collection/Iterator$WithFilter$$anonfun$withFilter$1.apply:(Ljava/lang/Object;)Z
Asciz	scala/runtime/BoxesRunTime;
class	scala/runtime/BoxesRunTime
Asciz	boxToBoolean;
Asciz	(Z)Ljava/lang/Boolean;;
NameAndType	boxToBoolean:(Z)Ljava/lang/Boolean;
Method	scala/runtime/BoxesRunTime.boxToBoolean:(Z)Ljava/lang/Boolean;
Asciz	v1;
Asciz	Ljava/lang/Object;;
Asciz	scala/collection/Iterator$WithFilter;
class	scala/collection/Iterator$WithFilter
Asciz	scala$collection$Iterator$WithFilter$$p;
NameAndType	scala$collection$Iterator$WithFilter$$p:Lscala/Function1;
Field	scala/collection/Iterator$WithFilter.scala$collection$Iterator$WithFilter$$p:Lscala/Function1;
Asciz	scala/Function1;
class	scala/Function1
NameAndType	apply:(Ljava/lang/Object;)Ljava/lang/Object;
InterfaceMethod	scala/Function1.apply:(Ljava/lang/Object;)Ljava/lang/Object;
Asciz	unboxToBoolean;
NameAndType	unboxToBoolean:(Ljava/lang/Object;)Z
Method	scala/runtime/BoxesRunTime.unboxToBoolean:(Ljava/lang/Object;)Z
Asciz	x;
Asciz	(TA;)Z;
Asciz	andThen;
Asciz	(Lscala/Function1;)Lscala/Function1;;
Asciz	(Lscala/Function1;Lscala/Function1;)Lscala/Function1;;
NameAndType	andThen:(Lscala/Function1;Lscala/Function1;)Lscala/Function1;
Method	scala/Function1$class.andThen:(Lscala/Function1;Lscala/Function1;)Lscala/Function1;
Asciz	g;
Asciz	compose;
NameAndType	compose:(Lscala/Function1;Lscala/Function1;)Lscala/Function1;
Method	scala/Function1$class.compose:(Lscala/Function1;Lscala/Function1;)Lscala/Function1;
Asciz	toString;
Asciz	()Ljava/lang/String;;
Asciz	(Lscala/Function1;)Ljava/lang/String;;
NameAndType	toString:(Lscala/Function1;)Ljava/lang/String;
Method	scala/Function1$class.toString:(Lscala/Function1;)Ljava/lang/String;
Asciz	Scala;
Asciz	InnerClasses;
Asciz	scala/collection/Iterator;
class	scala/collection/Iterator
Asciz	WithFilter;
Asciz	$anonfun$withFilter$1;
Asciz	scala/ScalaObject;
class	scala/ScalaObject
Asciz	java/io/Serializable;
class	java/io/Serializable

{
public static final long serialVersionUID;
  Signature: J

private final scala.Function1 q$1;
  Signature: Lscala/Function1;

private final scala.collection.Iterator$WithFilter $outer;
  Signature: Lscala/collection/Iterator$WithFilter;

public static {};
  Signature: ()V
  Code:
   Stack=2, Locals=0, Args_size=0
	lconst_0
	putstatic	Field serialVersionUID:J
	return
  Labels:

public scala.collection.Iterator$WithFilter$$anonfun$withFilter$1(scala.collection.Iterator$WithFilter, scala.Function1);
  Signature: (Lscala/collection/Iterator$WithFilter;Lscala/Function1;)V
  Code:
   Stack=2, Locals=3, Args_size=3
	aload_1
	ifnonnull	l1 // aload_0
	new	class java/lang/NullPointerException
	dup
	invokespecial	Method java/lang/NullPointerException."<init>":()V
	athrow
l1	aload_0
	aload_1
	putfield	Field $outer:Lscala/collection/Iterator$WithFilter;
	aload_0
	aload_2
	putfield	Field q$1:Lscala/Function1;
	aload_0
	invokespecial	Method java/lang/Object."<init>":()V
	aload_0
	invokestatic	Method scala/Function1$class.$init$:(Lscala/Function1;)V
	return
  Labels:
   	l1 = 12 // aload_0
  LocalVariableTable: 
   Start  Length  Slot  Name   Signature
   0      31      0    this       Lscala/collection/Iterator$WithFilter$$anonfun$withFilter$1;
   0      31      1    $outer       Lscala/collection/Iterator$WithFilter;

  Signature: length = 0x2
   00 27 

public final java.lang.Object apply(java.lang.Object);
  Signature: (Ljava/lang/Object;)Ljava/lang/Object;
  Code:
   Stack=2, Locals=4, Args_size=2
	aload_0
	getfield	Field $outer:Lscala/collection/Iterator$WithFilter;
	astore_3
	aload_0
	aload_1
	invokevirtual	Method apply:(Ljava/lang/Object;)Z
	istore_2
	iload_2
	invokestatic	Method scala/runtime/BoxesRunTime.boxToBoolean:(Z)Ljava/lang/Boolean;
	areturn
  Labels:
  LocalVariableTable: 
   Start  Length  Slot  Name   Signature
   0      16      0    this       Lscala/collection/Iterator$WithFilter$$anonfun$withFilter$1;
   5      11      1    v1       Ljava/lang/Object;


public final boolean apply(java.lang.Object);
  Signature: (Ljava/lang/Object;)Z
  Code:
   Stack=2, Locals=3, Args_size=2
	aload_0
	getfield	Field $outer:Lscala/collection/Iterator$WithFilter;
	astore_2
	aload_0
	getfield	Field $outer:Lscala/collection/Iterator$WithFilter;
	getfield	Field scala/collection/Iterator$WithFilter.scala$collection$Iterator$WithFilter$$p:Lscala/Function1;
	aload_1
	invokeinterface	InterfaceMethod scala/Function1.apply:(Ljava/lang/Object;)Ljava/lang/Object;
	invokestatic	Method scala/runtime/BoxesRunTime.unboxToBoolean:(Ljava/lang/Object;)Z
	ifeq	l1 // iconst_0
	aload_0
	getfield	Field q$1:Lscala/Function1;
	aload_1
	invokeinterface	InterfaceMethod scala/Function1.apply:(Ljava/lang/Object;)Ljava/lang/Object;
	invokestatic	Method scala/runtime/BoxesRunTime.unboxToBoolean:(Ljava/lang/Object;)Z
	ifeq	l1 // iconst_0
	iconst_1
	goto	l2 // ireturn
l1	iconst_0
l2	ireturn
  Labels:
   	l1 = 44 // iconst_0
   	l2 = 45 // ireturn
  LocalVariableTable: 
   Start  Length  Slot  Name   Signature
   0      46      0    this       Lscala/collection/Iterator$WithFilter$$anonfun$withFilter$1;
   5      41      1    x       Ljava/lang/Object;

  Signature: length = 0x2
   00 43 

public scala.Function1 andThen(scala.Function1);
  Signature: (Lscala/Function1;)Lscala/Function1;
  Code:
   Stack=2, Locals=2, Args_size=2
	aload_0
	aload_1
	invokestatic	Method scala/Function1$class.andThen:(Lscala/Function1;Lscala/Function1;)Lscala/Function1;
	areturn
  Labels:
  LocalVariableTable: 
   Start  Length  Slot  Name   Signature
   0      6      0    this       Lscala/collection/Iterator$WithFilter$$anonfun$withFilter$1;
   0      6      1    g       Lscala/Function1;


public scala.Function1 compose(scala.Function1);
  Signature: (Lscala/Function1;)Lscala/Function1;
  Code:
   Stack=2, Locals=2, Args_size=2
	aload_0
	aload_1
	invokestatic	Method scala/Function1$class.compose:(Lscala/Function1;Lscala/Function1;)Lscala/Function1;
	areturn
  Labels:
  LocalVariableTable: 
   Start  Length  Slot  Name   Signature
   0      6      0    this       Lscala/collection/Iterator$WithFilter$$anonfun$withFilter$1;
   0      6      1    g       Lscala/Function1;


public java.lang.String toString();
  Signature: ()Ljava/lang/String;
  Code:
   Stack=1, Locals=1, Args_size=1
	aload_0
	invokestatic	Method scala/Function1$class.toString:(Lscala/Function1;)Ljava/lang/String;
	areturn
  Labels:

}

