Compiled from "IterableViewLike.scala"
public abstract class scala.collection.IterableViewLike$Zipped$class extends java.lang.Object
  SourceFile: "IterableViewLike.scala"
  Scala: length = 0x
   
  InnerClass: 
   public abstract Zipped=class scala/collection/IterableViewLike$Zipped of class scala/collection/IterableViewLike
  minor version: 0
  major version: 49
  Constant pool:
Asciz	SourceFile;
Asciz	IterableViewLike.scala;
Asciz	iterator;
Asciz	(Lscala/collection/IterableViewLike$Zipped;)Lscala/collection/Iterator;;
Asciz	Code;
Asciz	LineNumberTable;
Asciz	scala/collection/IterableViewLike$Zipped;
class	scala/collection/IterableViewLike$Zipped
Asciz	scala$collection$IterableViewLike$Zipped$$$outer;
Asciz	()Lscala/collection/IterableViewLike;;
NameAndType	scala$collection$IterableViewLike$Zipped$$$outer:()Lscala/collection/IterableViewLike;
InterfaceMethod	scala/collection/IterableViewLike$Zipped.scala$collection$IterableViewLike$Zipped$$$outer:()Lscala/collection/IterableViewLike;
Asciz	scala/collection/IterableLike;
class	scala/collection/IterableLike
Asciz	()Lscala/collection/Iterator;;
NameAndType	iterator:()Lscala/collection/Iterator;
InterfaceMethod	scala/collection/IterableLike.iterator:()Lscala/collection/Iterator;
Asciz	other;
Asciz	()Lscala/collection/Iterable;;
NameAndType	other:()Lscala/collection/Iterable;
InterfaceMethod	scala/collection/IterableViewLike$Zipped.other:()Lscala/collection/Iterable;
Asciz	scala/collection/Iterator;
class	scala/collection/Iterator
Asciz	zip;
Asciz	(Lscala/collection/Iterator;)Lscala/collection/Iterator;;
NameAndType	zip:(Lscala/collection/Iterator;)Lscala/collection/Iterator;
InterfaceMethod	scala/collection/Iterator.zip:(Lscala/collection/Iterator;)Lscala/collection/Iterator;
Asciz	$this;
Asciz	Lscala/collection/IterableViewLike$Zipped;;
Asciz	LocalVariableTable;
Asciz	stringPrefix;
Asciz	(Lscala/collection/IterableViewLike$Zipped;)Ljava/lang/String;;
Asciz	scala/collection/mutable/StringBuilder;
class	scala/collection/mutable/StringBuilder
Asciz	<init>;
Asciz	()V;
NameAndType	"<init>":()V
Method	scala/collection/mutable/StringBuilder."<init>":()V
Asciz	scala/collection/IterableViewLike;
class	scala/collection/IterableViewLike
Asciz	()Ljava/lang/String;;
NameAndType	stringPrefix:()Ljava/lang/String;
InterfaceMethod	scala/collection/IterableViewLike.stringPrefix:()Ljava/lang/String;
Asciz	append;
Asciz	(Ljava/lang/Object;)Lscala/collection/mutable/StringBuilder;;
NameAndType	append:(Ljava/lang/Object;)Lscala/collection/mutable/StringBuilder;
Method	scala/collection/mutable/StringBuilder.append:(Ljava/lang/Object;)Lscala/collection/mutable/StringBuilder;
Asciz	Z;
String	Z
Asciz	toString;
NameAndType	toString:()Ljava/lang/String;
Method	scala/collection/mutable/StringBuilder.toString:()Ljava/lang/String;
Asciz	$init$;
Asciz	(Lscala/collection/IterableViewLike$Zipped;)V;
Asciz	Scala;
Asciz	InnerClasses;
Asciz	Zipped;
Asciz	scala/collection/IterableViewLike$Zipped$class;
class	scala/collection/IterableViewLike$Zipped$class
Asciz	java/lang/Object;
class	java/lang/Object

{
public static scala.collection.Iterator iterator(scala.collection.IterableViewLike$Zipped);
  Signature: (Lscala/collection/IterableViewLike$Zipped;)Lscala/collection/Iterator;
  Code:
   Stack=2, Locals=1, Args_size=1
	aload_0
	invokeinterface	InterfaceMethod scala/collection/IterableViewLike$Zipped.scala$collection$IterableViewLike$Zipped$$$outer:()Lscala/collection/IterableViewLike;
	invokeinterface	InterfaceMethod scala/collection/IterableLike.iterator:()Lscala/collection/Iterator;
	aload_0
	invokeinterface	InterfaceMethod scala/collection/IterableViewLike$Zipped.other:()Lscala/collection/Iterable;
	invokeinterface	InterfaceMethod scala/collection/IterableLike.iterator:()Lscala/collection/Iterator;
	invokeinterface	InterfaceMethod scala/collection/Iterator.zip:(Lscala/collection/Iterator;)Lscala/collection/Iterator;
	areturn
  Labels:
  LocalVariableTable: 
   Start  Length  Slot  Name   Signature
   0      28      0    $this       Lscala/collection/IterableViewLike$Zipped;


public static java.lang.String stringPrefix(scala.collection.IterableViewLike$Zipped);
  Signature: (Lscala/collection/IterableViewLike$Zipped;)Ljava/lang/String;
  Code:
   Stack=2, Locals=1, Args_size=1
	new	class scala/collection/mutable/StringBuilder
	dup
	invokespecial	Method scala/collection/mutable/StringBuilder."<init>":()V
	aload_0
	invokeinterface	InterfaceMethod scala/collection/IterableViewLike$Zipped.scala$collection$IterableViewLike$Zipped$$$outer:()Lscala/collection/IterableViewLike;
	invokeinterface	InterfaceMethod scala/collection/IterableViewLike.stringPrefix:()Ljava/lang/String;
	invokevirtual	Method scala/collection/mutable/StringBuilder.append:(Ljava/lang/Object;)Lscala/collection/mutable/StringBuilder;
	ldc	String Z
	invokevirtual	Method scala/collection/mutable/StringBuilder.append:(Ljava/lang/Object;)Lscala/collection/mutable/StringBuilder;
	invokevirtual	Method scala/collection/mutable/StringBuilder.toString:()Ljava/lang/String;
	areturn
  Labels:
  LocalVariableTable: 
   Start  Length  Slot  Name   Signature
   0      30      0    $this       Lscala/collection/IterableViewLike$Zipped;


public static void $init$(scala.collection.IterableViewLike$Zipped);
  Signature: (Lscala/collection/IterableViewLike$Zipped;)V
  Code:
   Stack=0, Locals=1, Args_size=1
	return
  Labels:
  LocalVariableTable: 
   Start  Length  Slot  Name   Signature
   0      1      0    $this       Lscala/collection/IterableViewLike$Zipped;


}

