Compiled from "IterableViewLike.scala"
public abstract class scala.collection.IterableViewLike$ZippedAll$class extends java.lang.Object
  SourceFile: "IterableViewLike.scala"
  Scala: length = 0x
   
  InnerClass: 
   public abstract #44= #13 of #43; //ZippedAll=class scala/collection/IterableViewLike$ZippedAll of class scala/collection/IterableViewLike
  minor version: 0
  major version: 49
  Constant pool:
const #1 = Asciz	SourceFile;
const #2 = Asciz	IterableViewLike.scala;
const #3 = Asciz	$init$;
const #4 = Asciz	(Lscala/collection/IterableViewLike$ZippedAll;)V;
const #5 = Asciz	Code;
const #6 = Asciz	LineNumberTable;
const #7 = Asciz	$this;
const #8 = Asciz	Lscala/collection/IterableViewLike$ZippedAll;;
const #9 = Asciz	LocalVariableTable;
const #10 = Asciz	iterator;
const #11 = Asciz	(Lscala/collection/IterableViewLike$ZippedAll;)Lscala/collection/Iterator;;
const #12 = Asciz	scala/collection/IterableViewLike$ZippedAll;
const #13 = class	#12;	//  scala/collection/IterableViewLike$ZippedAll
const #14 = Asciz	scala$collection$IterableViewLike$ZippedAll$$$outer;
const #15 = Asciz	()Lscala/collection/IterableViewLike;;
const #16 = NameAndType	#14:#15;//  scala$collection$IterableViewLike$ZippedAll$$$outer:()Lscala/collection/IterableViewLike;
const #17 = InterfaceMethod	#13.#16;	//  scala/collection/IterableViewLike$ZippedAll.scala$collection$IterableViewLike$ZippedAll$$$outer:()Lscala/collection/IterableViewLike;
const #18 = Asciz	scala/collection/IterableLike;
const #19 = class	#18;	//  scala/collection/IterableLike
const #20 = Asciz	()Lscala/collection/Iterator;;
const #21 = NameAndType	#10:#20;//  iterator:()Lscala/collection/Iterator;
const #22 = InterfaceMethod	#19.#21;	//  scala/collection/IterableLike.iterator:()Lscala/collection/Iterator;
const #23 = Asciz	other;
const #24 = Asciz	()Lscala/collection/Iterable;;
const #25 = NameAndType	#23:#24;//  other:()Lscala/collection/Iterable;
const #26 = InterfaceMethod	#13.#25;	//  scala/collection/IterableViewLike$ZippedAll.other:()Lscala/collection/Iterable;
const #27 = Asciz	thisElem;
const #28 = Asciz	()Ljava/lang/Object;;
const #29 = NameAndType	#27:#28;//  thisElem:()Ljava/lang/Object;
const #30 = InterfaceMethod	#13.#29;	//  scala/collection/IterableViewLike$ZippedAll.thisElem:()Ljava/lang/Object;
const #31 = Asciz	thatElem;
const #32 = NameAndType	#31:#28;//  thatElem:()Ljava/lang/Object;
const #33 = InterfaceMethod	#13.#32;	//  scala/collection/IterableViewLike$ZippedAll.thatElem:()Ljava/lang/Object;
const #34 = Asciz	scala/collection/Iterator;
const #35 = class	#34;	//  scala/collection/Iterator
const #36 = Asciz	zipAll;
const #37 = Asciz	(Lscala/collection/Iterator;Ljava/lang/Object;Ljava/lang/Object;)Ljava/lang/Object;;
const #38 = NameAndType	#36:#37;//  zipAll:(Lscala/collection/Iterator;Ljava/lang/Object;Ljava/lang/Object;)Ljava/lang/Object;
const #39 = InterfaceMethod	#35.#38;	//  scala/collection/Iterator.zipAll:(Lscala/collection/Iterator;Ljava/lang/Object;Ljava/lang/Object;)Ljava/lang/Object;
const #40 = Asciz	Scala;
const #41 = Asciz	InnerClasses;
const #42 = Asciz	scala/collection/IterableViewLike;
const #43 = class	#42;	//  scala/collection/IterableViewLike
const #44 = Asciz	ZippedAll;
const #45 = Asciz	scala/collection/IterableViewLike$ZippedAll$class;
const #46 = class	#45;	//  scala/collection/IterableViewLike$ZippedAll$class
const #47 = Asciz	java/lang/Object;
const #48 = class	#47;	//  java/lang/Object

{
public static void $init$(scala.collection.IterableViewLike$ZippedAll);
  Code:
   Stack=0, Locals=1, Args_size=1
   0:	return
  LineNumberTable: 
   line 66: 0

  LocalVariableTable: 
   Start  Length  Slot  Name   Signature
   0      1      0    $this       Lscala/collection/IterableViewLike$ZippedAll;


public static scala.collection.Iterator iterator(scala.collection.IterableViewLike$ZippedAll);
  Code:
   Stack=4, Locals=1, Args_size=1
   0:	aload_0
   1:	invokeinterface	#17,  1; //InterfaceMethod scala/collection/IterableViewLike$ZippedAll.scala$collection$IterableViewLike$ZippedAll$$$outer:()Lscala/collection/IterableViewLike;
   6:	invokeinterface	#22,  1; //InterfaceMethod scala/collection/IterableLike.iterator:()Lscala/collection/Iterator;
   11:	aload_0
   12:	invokeinterface	#26,  1; //InterfaceMethod scala/collection/IterableViewLike$ZippedAll.other:()Lscala/collection/Iterable;
   17:	invokeinterface	#22,  1; //InterfaceMethod scala/collection/IterableLike.iterator:()Lscala/collection/Iterator;
   22:	aload_0
   23:	invokeinterface	#30,  1; //InterfaceMethod scala/collection/IterableViewLike$ZippedAll.thisElem:()Ljava/lang/Object;
   28:	aload_0
   29:	invokeinterface	#33,  1; //InterfaceMethod scala/collection/IterableViewLike$ZippedAll.thatElem:()Ljava/lang/Object;
   34:	invokeinterface	#39,  4; //InterfaceMethod scala/collection/Iterator.zipAll:(Lscala/collection/Iterator;Ljava/lang/Object;Ljava/lang/Object;)Ljava/lang/Object;
   39:	checkcast	#35; //class scala/collection/Iterator
   42:	areturn
  LineNumberTable: 
   line 71: 0

  LocalVariableTable: 
   Start  Length  Slot  Name   Signature
   0      43      0    $this       Lscala/collection/IterableViewLike$ZippedAll;


}

