Compiled from "IterableViewLike.scala"
public abstract class scala.collection.IterableViewLike$Zipped$class extends java.lang.Object
  SourceFile: "IterableViewLike.scala"
  Scala: length = 0x
   
  InnerClass: 
   public abstract #57= #19 of #25; //Zipped=class scala/collection/IterableViewLike$Zipped of class scala/collection/IterableViewLike
  minor version: 0
  major version: 49
  Constant pool:
const #1 = Asciz	SourceFile;
const #2 = Asciz	IterableViewLike.scala;
const #3 = Asciz	$init$;
const #4 = Asciz	(Lscala/collection/IterableViewLike$Zipped;)V;
const #5 = Asciz	Code;
const #6 = Asciz	LineNumberTable;
const #7 = Asciz	$this;
const #8 = Asciz	Lscala/collection/IterableViewLike$Zipped;;
const #9 = Asciz	LocalVariableTable;
const #10 = Asciz	stringPrefix;
const #11 = Asciz	(Lscala/collection/IterableViewLike$Zipped;)Ljava/lang/String;;
const #12 = Asciz	scala/collection/mutable/StringBuilder;
const #13 = class	#12;	//  scala/collection/mutable/StringBuilder
const #14 = Asciz	<init>;
const #15 = Asciz	()V;
const #16 = NameAndType	#14:#15;//  "<init>":()V
const #17 = Method	#13.#16;	//  scala/collection/mutable/StringBuilder."<init>":()V
const #18 = Asciz	scala/collection/IterableViewLike$Zipped;
const #19 = class	#18;	//  scala/collection/IterableViewLike$Zipped
const #20 = Asciz	scala$collection$IterableViewLike$Zipped$$$outer;
const #21 = Asciz	()Lscala/collection/IterableViewLike;;
const #22 = NameAndType	#20:#21;//  scala$collection$IterableViewLike$Zipped$$$outer:()Lscala/collection/IterableViewLike;
const #23 = InterfaceMethod	#19.#22;	//  scala/collection/IterableViewLike$Zipped.scala$collection$IterableViewLike$Zipped$$$outer:()Lscala/collection/IterableViewLike;
const #24 = Asciz	scala/collection/IterableViewLike;
const #25 = class	#24;	//  scala/collection/IterableViewLike
const #26 = Asciz	()Ljava/lang/String;;
const #27 = NameAndType	#10:#26;//  stringPrefix:()Ljava/lang/String;
const #28 = InterfaceMethod	#25.#27;	//  scala/collection/IterableViewLike.stringPrefix:()Ljava/lang/String;
const #29 = Asciz	append;
const #30 = Asciz	(Ljava/lang/Object;)Lscala/collection/mutable/StringBuilder;;
const #31 = NameAndType	#29:#30;//  append:(Ljava/lang/Object;)Lscala/collection/mutable/StringBuilder;
const #32 = Method	#13.#31;	//  scala/collection/mutable/StringBuilder.append:(Ljava/lang/Object;)Lscala/collection/mutable/StringBuilder;
const #33 = Asciz	Z;
const #34 = String	#33;	//  Z
const #35 = Asciz	toString;
const #36 = NameAndType	#35:#26;//  toString:()Ljava/lang/String;
const #37 = Method	#13.#36;	//  scala/collection/mutable/StringBuilder.toString:()Ljava/lang/String;
const #38 = Asciz	iterator;
const #39 = Asciz	(Lscala/collection/IterableViewLike$Zipped;)Lscala/collection/Iterator;;
const #40 = Asciz	scala/collection/IterableLike;
const #41 = class	#40;	//  scala/collection/IterableLike
const #42 = Asciz	()Lscala/collection/Iterator;;
const #43 = NameAndType	#38:#42;//  iterator:()Lscala/collection/Iterator;
const #44 = InterfaceMethod	#41.#43;	//  scala/collection/IterableLike.iterator:()Lscala/collection/Iterator;
const #45 = Asciz	other;
const #46 = Asciz	()Lscala/collection/Iterable;;
const #47 = NameAndType	#45:#46;//  other:()Lscala/collection/Iterable;
const #48 = InterfaceMethod	#19.#47;	//  scala/collection/IterableViewLike$Zipped.other:()Lscala/collection/Iterable;
const #49 = Asciz	scala/collection/Iterator;
const #50 = class	#49;	//  scala/collection/Iterator
const #51 = Asciz	zip;
const #52 = Asciz	(Lscala/collection/Iterator;)Ljava/lang/Object;;
const #53 = NameAndType	#51:#52;//  zip:(Lscala/collection/Iterator;)Ljava/lang/Object;
const #54 = InterfaceMethod	#50.#53;	//  scala/collection/Iterator.zip:(Lscala/collection/Iterator;)Ljava/lang/Object;
const #55 = Asciz	Scala;
const #56 = Asciz	InnerClasses;
const #57 = Asciz	Zipped;
const #58 = Asciz	scala/collection/IterableViewLike$Zipped$class;
const #59 = class	#58;	//  scala/collection/IterableViewLike$Zipped$class
const #60 = Asciz	java/lang/Object;
const #61 = class	#60;	//  java/lang/Object

{
public static void $init$(scala.collection.IterableViewLike$Zipped);
  Code:
   Stack=0, Locals=1, Args_size=1
   0:	return
  LineNumberTable: 
   line 60: 0

  LocalVariableTable: 
   Start  Length  Slot  Name   Signature
   0      1      0    $this       Lscala/collection/IterableViewLike$Zipped;


public static java.lang.String stringPrefix(scala.collection.IterableViewLike$Zipped);
  Code:
   Stack=2, Locals=1, Args_size=1
   0:	new	#13; //class scala/collection/mutable/StringBuilder
   3:	dup
   4:	invokespecial	#17; //Method scala/collection/mutable/StringBuilder."<init>":()V
   7:	aload_0
   8:	invokeinterface	#23,  1; //InterfaceMethod scala/collection/IterableViewLike$Zipped.scala$collection$IterableViewLike$Zipped$$$outer:()Lscala/collection/IterableViewLike;
   13:	invokeinterface	#28,  1; //InterfaceMethod scala/collection/IterableViewLike.stringPrefix:()Ljava/lang/String;
   18:	invokevirtual	#32; //Method scala/collection/mutable/StringBuilder.append:(Ljava/lang/Object;)Lscala/collection/mutable/StringBuilder;
   21:	ldc	#34; //String Z
   23:	invokevirtual	#32; //Method scala/collection/mutable/StringBuilder.append:(Ljava/lang/Object;)Lscala/collection/mutable/StringBuilder;
   26:	invokevirtual	#37; //Method scala/collection/mutable/StringBuilder.toString:()Ljava/lang/String;
   29:	areturn
  LineNumberTable: 
   line 63: 0

  LocalVariableTable: 
   Start  Length  Slot  Name   Signature
   0      30      0    $this       Lscala/collection/IterableViewLike$Zipped;


public static scala.collection.Iterator iterator(scala.collection.IterableViewLike$Zipped);
  Code:
   Stack=2, Locals=1, Args_size=1
   0:	aload_0
   1:	invokeinterface	#23,  1; //InterfaceMethod scala/collection/IterableViewLike$Zipped.scala$collection$IterableViewLike$Zipped$$$outer:()Lscala/collection/IterableViewLike;
   6:	invokeinterface	#44,  1; //InterfaceMethod scala/collection/IterableLike.iterator:()Lscala/collection/Iterator;
   11:	aload_0
   12:	invokeinterface	#48,  1; //InterfaceMethod scala/collection/IterableViewLike$Zipped.other:()Lscala/collection/Iterable;
   17:	invokeinterface	#44,  1; //InterfaceMethod scala/collection/IterableLike.iterator:()Lscala/collection/Iterator;
   22:	invokeinterface	#54,  2; //InterfaceMethod scala/collection/Iterator.zip:(Lscala/collection/Iterator;)Ljava/lang/Object;
   27:	checkcast	#50; //class scala/collection/Iterator
   30:	areturn
  LineNumberTable: 
   line 62: 0

  LocalVariableTable: 
   Start  Length  Slot  Name   Signature
   0      31      0    $this       Lscala/collection/IterableViewLike$Zipped;


}

