Compiled from "Iterator.scala"
public final class scala.collection.Iterator$WithFilter extends java.lang.Object implements scala.ScalaObject
  SourceFile: "Iterator.scala"
  Scala: length = 0x
   
  InnerClass: 
   public final WithFilter=class scala/collection/Iterator$WithFilter of class scala/collection/Iterator
   public final $anon$23=class scala/collection/Iterator$WithFilter$$anon$23 of class scala/collection/Iterator$WithFilter
   public final $anon$24=class scala/collection/Iterator$WithFilter$$anon$24 of class scala/collection/Iterator$WithFilter
   public final $anonfun$withFilter$1=class scala/collection/Iterator$WithFilter$$anonfun$withFilter$1 of class scala/collection/Iterator$WithFilter
  minor version: 0
  major version: 49
  Constant pool:
Asciz	SourceFile;
Asciz	Iterator.scala;
Asciz	$outer;
Asciz	Lscala/collection/Iterator;;
Asciz	scala$collection$Iterator$WithFilter$$p;
Asciz	Lscala/Function1;;
Asciz	<init>;
Asciz	(Lscala/collection/Iterator;Lscala/Function1;)V;
Asciz	Code;
Asciz	LineNumberTable;
Asciz	scala/collection/Iterator$WithFilter;
class	scala/collection/Iterator$WithFilter
NameAndType	scala$collection$Iterator$WithFilter$$p:Lscala/Function1;
Field	scala/collection/Iterator$WithFilter.scala$collection$Iterator$WithFilter$$p:Lscala/Function1;
Asciz	java/lang/NullPointerException;
class	java/lang/NullPointerException
Asciz	()V;
NameAndType	"<init>":()V
Method	java/lang/NullPointerException."<init>":()V
NameAndType	$outer:Lscala/collection/Iterator;
Field	scala/collection/Iterator$WithFilter.$outer:Lscala/collection/Iterator;
Asciz	java/lang/Object;
class	java/lang/Object
Method	java/lang/Object."<init>":()V
Asciz	this;
Asciz	Lscala/collection/Iterator$WithFilter;;
Asciz	p;
Asciz	LocalVariableTable;
Asciz	(Lscala/collection/Iterator<TA;>;Lscala/Function1<TA;Ljava/lang/Boolean;>;)V;
Asciz	Signature;
Asciz	scala$collection$Iterator$WithFilter$$$outer;
Asciz	()Lscala/collection/Iterator;;
Asciz	withFilter;
Asciz	(Lscala/Function1;)Lscala/collection/Iterator$WithFilter;;
Asciz	scala/collection/Iterator$WithFilter$$anonfun$withFilter$1;
class	scala/collection/Iterator$WithFilter$$anonfun$withFilter$1
Asciz	(Lscala/collection/Iterator$WithFilter;Lscala/Function1;)V;
NameAndType	"<init>":(Lscala/collection/Iterator$WithFilter;Lscala/Function1;)V
Method	scala/collection/Iterator$WithFilter$$anonfun$withFilter$1."<init>":(Lscala/collection/Iterator$WithFilter;Lscala/Function1;)V
NameAndType	"<init>":(Lscala/collection/Iterator;Lscala/Function1;)V
Method	scala/collection/Iterator$WithFilter."<init>":(Lscala/collection/Iterator;Lscala/Function1;)V
Asciz	q$1;
Asciz	(Lscala/Function1<TA;Ljava/lang/Boolean;>;)Lscala/collection/Iterator<TA;>.WithFilter;;
Asciz	foreach;
Asciz	(Lscala/Function1;)V;
Asciz	scala/collection/Iterator;
class	scala/collection/Iterator
Asciz	hasNext;
Asciz	()Z;
NameAndType	hasNext:()Z
InterfaceMethod	scala/collection/Iterator.hasNext:()Z
Asciz	next;
Asciz	()Ljava/lang/Object;;
NameAndType	next:()Ljava/lang/Object;
InterfaceMethod	scala/collection/Iterator.next:()Ljava/lang/Object;
Asciz	scala/Function1;
class	scala/Function1
Asciz	apply;
Asciz	(Ljava/lang/Object;)Ljava/lang/Object;;
NameAndType	apply:(Ljava/lang/Object;)Ljava/lang/Object;
InterfaceMethod	scala/Function1.apply:(Ljava/lang/Object;)Ljava/lang/Object;
Asciz	scala/runtime/BoxesRunTime;
class	scala/runtime/BoxesRunTime
Asciz	unboxToBoolean;
Asciz	(Ljava/lang/Object;)Z;
NameAndType	unboxToBoolean:(Ljava/lang/Object;)Z
Method	scala/runtime/BoxesRunTime.unboxToBoolean:(Ljava/lang/Object;)Z
Asciz	scala/runtime/BoxedUnit;
class	scala/runtime/BoxedUnit
Asciz	UNIT;
Asciz	Lscala/runtime/BoxedUnit;;
NameAndType	UNIT:Lscala/runtime/BoxedUnit;
Field	scala/runtime/BoxedUnit.UNIT:Lscala/runtime/BoxedUnit;
Asciz	f;
Asciz	x;
Asciz	Ljava/lang/Object;;
Asciz	<U:Ljava/lang/Object;>(Lscala/Function1<TA;TU;>;)V;
Asciz	flatMap;
Asciz	(Lscala/Function1;)Lscala/collection/Iterator;;
Asciz	scala/collection/Iterator$WithFilter$$anon$24;
class	scala/collection/Iterator$WithFilter$$anon$24
Method	scala/collection/Iterator$WithFilter$$anon$24."<init>":(Lscala/collection/Iterator$WithFilter;Lscala/Function1;)V
Asciz	f$6;
Asciz	<B:Ljava/lang/Object;>(Lscala/Function1<TA;Lscala/collection/Iterator<TB;>;>;)Lscala/collection/Iterator<TB;>;;
Asciz	map;
Asciz	scala/collection/Iterator$WithFilter$$anon$23;
class	scala/collection/Iterator$WithFilter$$anon$23
Method	scala/collection/Iterator$WithFilter$$anon$23."<init>":(Lscala/collection/Iterator$WithFilter;Lscala/Function1;)V
Asciz	f$5;
Asciz	<B:Ljava/lang/Object;>(Lscala/Function1<TA;TB;>;)Lscala/collection/Iterator<TB;>;;
Asciz	Scala;
Asciz	InnerClasses;
Asciz	WithFilter;
Asciz	$anon$23;
Asciz	$anon$24;
Asciz	$anonfun$withFilter$1;
Asciz	scala/ScalaObject;
class	scala/ScalaObject

{
public final scala.collection.Iterator $outer;
  Signature: Lscala/collection/Iterator;

public final scala.Function1 scala$collection$Iterator$WithFilter$$p;
  Signature: Lscala/Function1;

public scala.collection.Iterator$WithFilter(scala.collection.Iterator, scala.Function1);
  Signature: (Lscala/collection/Iterator;Lscala/Function1;)V
  Code:
   Stack=2, Locals=3, Args_size=3
	aload_0
	aload_2
	putfield	Field scala$collection$Iterator$WithFilter$$p:Lscala/Function1;
	aload_1
	ifnonnull	l1 // aload_0
	new	class java/lang/NullPointerException
	dup
	invokespecial	Method java/lang/NullPointerException."<init>":()V
	athrow
l1	aload_0
	aload_1
	putfield	Field $outer:Lscala/collection/Iterator;
	aload_0
	invokespecial	Method java/lang/Object."<init>":()V
	return
  Labels:
   	l1 = 17 // aload_0
  LocalVariableTable: 
   Start  Length  Slot  Name   Signature
   0      27      0    this       Lscala/collection/Iterator$WithFilter;
   0      27      1    $outer       Lscala/collection/Iterator;
   0      27      2    p       Lscala/Function1;

  Signature: length = 0x2
   00 1D 

public scala.collection.Iterator scala$collection$Iterator$WithFilter$$$outer();
  Signature: ()Lscala/collection/Iterator;
  Code:
   Stack=1, Locals=1, Args_size=1
	aload_0
	getfield	Field $outer:Lscala/collection/Iterator;
	areturn
  Labels:

public scala.collection.Iterator$WithFilter withFilter(scala.Function1);
  Signature: (Lscala/Function1;)Lscala/collection/Iterator$WithFilter;
  Code:
   Stack=7, Locals=2, Args_size=2
	new	class scala/collection/Iterator$WithFilter
	dup
	aload_0
	getfield	Field $outer:Lscala/collection/Iterator;
	new	class scala/collection/Iterator$WithFilter$$anonfun$withFilter$1
	dup
	aload_0
	aload_1
	invokespecial	Method scala/collection/Iterator$WithFilter$$anonfun$withFilter$1."<init>":(Lscala/collection/Iterator$WithFilter;Lscala/Function1;)V
	invokespecial	Method "<init>":(Lscala/collection/Iterator;Lscala/Function1;)V
	areturn
  Labels:
  LocalVariableTable: 
   Start  Length  Slot  Name   Signature
   0      21      0    this       Lscala/collection/Iterator$WithFilter;
   0      21      1    q$1       Lscala/Function1;

  Signature: length = 0x2
   00 2B 

public void foreach(scala.Function1);
  Signature: (Lscala/Function1;)V
  Code:
   Stack=2, Locals=3, Args_size=2
l4	aload_0
	getfield	Field $outer:Lscala/collection/Iterator;
	invokeinterface	InterfaceMethod scala/collection/Iterator.hasNext:()Z
	ifeq	l1 // return
	aload_0
	getfield	Field $outer:Lscala/collection/Iterator;
	invokeinterface	InterfaceMethod scala/collection/Iterator.next:()Ljava/lang/Object;
	astore_2
	aload_0
	getfield	Field scala$collection$Iterator$WithFilter$$p:Lscala/Function1;
	aload_2
	invokeinterface	InterfaceMethod scala/Function1.apply:(Ljava/lang/Object;)Ljava/lang/Object;
	invokestatic	Method scala/runtime/BoxesRunTime.unboxToBoolean:(Ljava/lang/Object;)Z
	ifeq	l2 // getstatic
	aload_1
	aload_2
	invokeinterface	InterfaceMethod scala/Function1.apply:(Ljava/lang/Object;)Ljava/lang/Object;
	goto	l3 // pop
l2	getstatic	Field scala/runtime/BoxedUnit.UNIT:Lscala/runtime/BoxedUnit;
l3	pop
	goto	l4 // aload_0
l1	return
  Labels:
   	l4 = 0 // aload_0
   	l2 = 48 // getstatic
   	l3 = 51 // pop
   	l1 = 55 // return
  LocalVariableTable: 
   Start  Length  Slot  Name   Signature
   0      56      0    this       Lscala/collection/Iterator$WithFilter;
   0      56      1    f       Lscala/Function1;
   22      30      2    x       Ljava/lang/Object;

  Signature: length = 0x2
   00 4D 

public scala.collection.Iterator flatMap(scala.Function1);
  Signature: (Lscala/Function1;)Lscala/collection/Iterator;
  Code:
   Stack=4, Locals=2, Args_size=2
	new	class scala/collection/Iterator$WithFilter$$anon$24
	dup
	aload_0
	aload_1
	invokespecial	Method scala/collection/Iterator$WithFilter$$anon$24."<init>":(Lscala/collection/Iterator$WithFilter;Lscala/Function1;)V
	areturn
  Labels:
  LocalVariableTable: 
   Start  Length  Slot  Name   Signature
   0      10      0    this       Lscala/collection/Iterator$WithFilter;
   0      10      1    f$6       Lscala/Function1;

  Signature: length = 0x2
   00 54 

public scala.collection.Iterator map(scala.Function1);
  Signature: (Lscala/Function1;)Lscala/collection/Iterator;
  Code:
   Stack=4, Locals=2, Args_size=2
	new	class scala/collection/Iterator$WithFilter$$anon$23
	dup
	aload_0
	aload_1
	invokespecial	Method scala/collection/Iterator$WithFilter$$anon$23."<init>":(Lscala/collection/Iterator$WithFilter;Lscala/Function1;)V
	areturn
  Labels:
  LocalVariableTable: 
   Start  Length  Slot  Name   Signature
   0      10      0    this       Lscala/collection/Iterator$WithFilter;
   0      10      1    f$5       Lscala/Function1;

  Signature: length = 0x2
   00 5A 

}

