Compiled from "Iterator.scala"
public class scala.collection.Iterator$IteratorIteratorOps extends java.lang.Object implements scala.ScalaObject
  SourceFile: "Iterator.scala"
  Signature: length = 0x2
   00 20 
  Scala: length = 0x
   
  InnerClass: 
   public #37= #10 of #36; //IteratorIteratorOps=class scala/collection/Iterator$IteratorIteratorOps of class scala/collection/Iterator
   public final #38= #27 of #10; //$anon$14=class scala/collection/Iterator$IteratorIteratorOps$$anon$14 of class scala/collection/Iterator$IteratorIteratorOps
  minor version: 0
  major version: 49
  Constant pool:
const #1 = Asciz	SourceFile;
const #2 = Asciz	Iterator.scala;
const #3 = Asciz	scala$collection$Iterator$IteratorIteratorOps$$its;
const #4 = Asciz	Lscala/collection/Iterator;;
const #5 = Asciz	<init>;
const #6 = Asciz	(Lscala/collection/Iterator;)V;
const #7 = Asciz	Code;
const #8 = Asciz	LineNumberTable;
const #9 = Asciz	scala/collection/Iterator$IteratorIteratorOps;
const #10 = class	#9;	//  scala/collection/Iterator$IteratorIteratorOps
const #11 = NameAndType	#3:#4;//  scala$collection$Iterator$IteratorIteratorOps$$its:Lscala/collection/Iterator;
const #12 = Field	#10.#11;	//  scala/collection/Iterator$IteratorIteratorOps.scala$collection$Iterator$IteratorIteratorOps$$its:Lscala/collection/Iterator;
const #13 = Asciz	java/lang/Object;
const #14 = class	#13;	//  java/lang/Object
const #15 = Asciz	()V;
const #16 = NameAndType	#5:#15;//  "<init>":()V
const #17 = Method	#14.#16;	//  java/lang/Object."<init>":()V
const #18 = Asciz	this;
const #19 = Asciz	Lscala/collection/Iterator$IteratorIteratorOps;;
const #20 = Asciz	its;
const #21 = Asciz	LocalVariableTable;
const #22 = Asciz	(Lscala/collection/Iterator<Lscala/collection/Iterator<TA;>;>;)V;
const #23 = Asciz	Signature;
const #24 = Asciz	flatten;
const #25 = Asciz	()Lscala/collection/Iterator;;
const #26 = Asciz	scala/collection/Iterator$IteratorIteratorOps$$anon$14;
const #27 = class	#26;	//  scala/collection/Iterator$IteratorIteratorOps$$anon$14
const #28 = Asciz	(Lscala/collection/Iterator$IteratorIteratorOps;)V;
const #29 = NameAndType	#5:#28;//  "<init>":(Lscala/collection/Iterator$IteratorIteratorOps;)V
const #30 = Method	#27.#29;	//  scala/collection/Iterator$IteratorIteratorOps$$anon$14."<init>":(Lscala/collection/Iterator$IteratorIteratorOps;)V
const #31 = Asciz	()Lscala/collection/Iterator<TA;>;;
const #32 = Asciz	<A:Ljava/lang/Object;>Ljava/lang/Object;Lscala/ScalaObject;;
const #33 = Asciz	Scala;
const #34 = Asciz	InnerClasses;
const #35 = Asciz	scala/collection/Iterator;
const #36 = class	#35;	//  scala/collection/Iterator
const #37 = Asciz	IteratorIteratorOps;
const #38 = Asciz	$anon$14;
const #39 = Asciz	scala/ScalaObject;
const #40 = class	#39;	//  scala/ScalaObject

{
public final scala.collection.Iterator scala$collection$Iterator$IteratorIteratorOps$$its;

public scala.collection.Iterator$IteratorIteratorOps(scala.collection.Iterator);
  Code:
   Stack=2, Locals=2, Args_size=2
   0:	aload_0
   1:	aload_1
   2:	putfield	#12; //Field scala$collection$Iterator$IteratorIteratorOps$$its:Lscala/collection/Iterator;
   5:	aload_0
   6:	invokespecial	#17; //Method java/lang/Object."<init>":()V
   9:	return
  LineNumberTable: 
   line 147: 0

  LocalVariableTable: 
   Start  Length  Slot  Name   Signature
   0      10      0    this       Lscala/collection/Iterator$IteratorIteratorOps;
   0      10      1    its       Lscala/collection/Iterator;

  Signature: length = 0x2
   00 16 

public scala.collection.Iterator flatten();
  Code:
   Stack=3, Locals=1, Args_size=1
   0:	new	#27; //class scala/collection/Iterator$IteratorIteratorOps$$anon$14
   3:	dup
   4:	aload_0
   5:	invokespecial	#30; //Method scala/collection/Iterator$IteratorIteratorOps$$anon$14."<init>":(Lscala/collection/Iterator$IteratorIteratorOps;)V
   8:	areturn
  LineNumberTable: 
   line 151: 0

  Signature: length = 0x2
   00 1F 

}

