Compiled from "IterableViewLike.scala"
public final class scala.collection.IterableViewLike$Appended$$anonfun$iterator$2 extends scala.runtime.AbstractFunction0 implements java.io.Serializable
  SourceFile: "IterableViewLike.scala"
  Scala: length = 0x
   
  InnerClass: 
   public abstract Appended=class scala/collection/IterableViewLike$Appended of class scala/collection/IterableViewLike
   public abstract Appended=class scala/collection/TraversableViewLike$Appended of class scala/collection/TraversableViewLike
   public final $anonfun$iterator$2=class scala/collection/IterableViewLike$Appended$$anonfun$iterator$2 of class scala/collection/IterableViewLike$Appended
  minor version: 0
  major version: 49
  Constant pool:
Asciz	SourceFile;
Asciz	IterableViewLike.scala;
Asciz	<clinit>;
Asciz	()V;
Asciz	Code;
Asciz	serialVersionUID;
Asciz	J;
Asciz	scala/collection/IterableViewLike$Appended$$anonfun$iterator$2;
class	scala/collection/IterableViewLike$Appended$$anonfun$iterator$2
NameAndType	serialVersionUID:J
Field	scala/collection/IterableViewLike$Appended$$anonfun$iterator$2.serialVersionUID:J
Asciz	$outer;
Asciz	Lscala/collection/IterableViewLike$Appended;;
Asciz	<init>;
Asciz	(Lscala/collection/IterableViewLike$Appended;)V;
Asciz	LineNumberTable;
Asciz	java/lang/NullPointerException;
class	java/lang/NullPointerException
NameAndType	"<init>":()V
Method	java/lang/NullPointerException."<init>":()V
NameAndType	$outer:Lscala/collection/IterableViewLike$Appended;
Field	scala/collection/IterableViewLike$Appended$$anonfun$iterator$2.$outer:Lscala/collection/IterableViewLike$Appended;
Asciz	scala/runtime/AbstractFunction0;
class	scala/runtime/AbstractFunction0
Method	scala/runtime/AbstractFunction0."<init>":()V
Asciz	this;
Asciz	Lscala/collection/IterableViewLike$Appended$$anonfun$iterator$2;;
Asciz	LocalVariableTable;
Asciz	(Lscala/collection/IterableViewLike<TA;TColl;TThis;>.Appended<TB;>;)V;
Asciz	Signature;
Asciz	apply;
Asciz	()Ljava/lang/Object;;
Asciz	()Lscala/collection/Iterator;;
NameAndType	apply:()Lscala/collection/Iterator;
Method	scala/collection/IterableViewLike$Appended$$anonfun$iterator$2.apply:()Lscala/collection/Iterator;
Asciz	scala/collection/TraversableViewLike$Appended;
class	scala/collection/TraversableViewLike$Appended
Asciz	rest;
Asciz	()Lscala/collection/Traversable;;
NameAndType	rest:()Lscala/collection/Traversable;
InterfaceMethod	scala/collection/TraversableViewLike$Appended.rest:()Lscala/collection/Traversable;
Asciz	scala/collection/TraversableLike;
class	scala/collection/TraversableLike
Asciz	toIterable;
Asciz	()Lscala/collection/Iterable;;
NameAndType	toIterable:()Lscala/collection/Iterable;
InterfaceMethod	scala/collection/TraversableLike.toIterable:()Lscala/collection/Iterable;
Asciz	scala/collection/IterableLike;
class	scala/collection/IterableLike
Asciz	iterator;
NameAndType	iterator:()Lscala/collection/Iterator;
InterfaceMethod	scala/collection/IterableLike.iterator:()Lscala/collection/Iterator;
Asciz	()Lscala/collection/Iterator<TB;>;;
Asciz	Scala;
Asciz	InnerClasses;
Asciz	scala/collection/IterableViewLike$Appended;
class	scala/collection/IterableViewLike$Appended
Asciz	scala/collection/IterableViewLike;
class	scala/collection/IterableViewLike
Asciz	Appended;
Asciz	scala/collection/TraversableViewLike;
class	scala/collection/TraversableViewLike
Asciz	$anonfun$iterator$2;
Asciz	java/io/Serializable;
class	java/io/Serializable

{
public static final long serialVersionUID;
  Signature: J

public final scala.collection.IterableViewLike$Appended $outer;
  Signature: Lscala/collection/IterableViewLike$Appended;

public static {};
  Signature: ()V
  Code:
   Stack=2, Locals=0, Args_size=0
	lconst_0
	putstatic	Field serialVersionUID:J
	return
  Labels:

public scala.collection.IterableViewLike$Appended$$anonfun$iterator$2(scala.collection.IterableViewLike$Appended);
  Signature: (Lscala/collection/IterableViewLike$Appended;)V
  Code:
   Stack=2, Locals=2, Args_size=2
	aload_1
	ifnonnull	l1 // aload_0
	new	class java/lang/NullPointerException
	dup
	invokespecial	Method java/lang/NullPointerException."<init>":()V
	athrow
l1	aload_0
	aload_1
	putfield	Field $outer:Lscala/collection/IterableViewLike$Appended;
	aload_0
	invokespecial	Method scala/runtime/AbstractFunction0."<init>":()V
	return
  Labels:
   	l1 = 12 // aload_0
  LocalVariableTable: 
   Start  Length  Slot  Name   Signature
   0      22      0    this       Lscala/collection/IterableViewLike$Appended$$anonfun$iterator$2;
   0      22      1    $outer       Lscala/collection/IterableViewLike$Appended;

  Signature: length = 0x2
   00 1D 

public final java.lang.Object apply();
  Signature: ()Ljava/lang/Object;
  Code:
   Stack=1, Locals=1, Args_size=1
	aload_0
	invokevirtual	Method apply:()Lscala/collection/Iterator;
	areturn
  Labels:

public final scala.collection.Iterator apply();
  Signature: ()Lscala/collection/Iterator;
  Code:
   Stack=1, Locals=1, Args_size=1
	aload_0
	getfield	Field $outer:Lscala/collection/IterableViewLike$Appended;
	invokeinterface	InterfaceMethod scala/collection/TraversableViewLike$Appended.rest:()Lscala/collection/Traversable;
	invokeinterface	InterfaceMethod scala/collection/TraversableLike.toIterable:()Lscala/collection/Iterable;
	invokeinterface	InterfaceMethod scala/collection/IterableLike.iterator:()Lscala/collection/Iterator;
	areturn
  Labels:
  Signature: length = 0x2
   00 35 

}

