Compiled from "IterableViewLike.scala"
public abstract class scala.collection.IterableViewLike$Sliced$class extends java.lang.Object
  SourceFile: "IterableViewLike.scala"
  Scala: length = 0x
   
  InnerClass: 
   public abstract #42= #13 of #41; //Sliced=class scala/collection/IterableViewLike$Sliced of class scala/collection/IterableViewLike
   public abstract #42= #24 of #44; //Sliced=class scala/collection/TraversableViewLike$Sliced of class scala/collection/TraversableViewLike
  minor version: 0
  major version: 49
  Constant pool:
const #1 = Asciz	SourceFile;
const #2 = Asciz	IterableViewLike.scala;
const #3 = Asciz	$init$;
const #4 = Asciz	(Lscala/collection/IterableViewLike$Sliced;)V;
const #5 = Asciz	Code;
const #6 = Asciz	LineNumberTable;
const #7 = Asciz	$this;
const #8 = Asciz	Lscala/collection/IterableViewLike$Sliced;;
const #9 = Asciz	LocalVariableTable;
const #10 = Asciz	iterator;
const #11 = Asciz	(Lscala/collection/IterableViewLike$Sliced;)Lscala/collection/Iterator;;
const #12 = Asciz	scala/collection/IterableViewLike$Sliced;
const #13 = class	#12;	//  scala/collection/IterableViewLike$Sliced
const #14 = Asciz	scala$collection$IterableViewLike$Sliced$$$outer;
const #15 = Asciz	()Lscala/collection/IterableViewLike;;
const #16 = NameAndType	#14:#15;//  scala$collection$IterableViewLike$Sliced$$$outer:()Lscala/collection/IterableViewLike;
const #17 = InterfaceMethod	#13.#16;	//  scala/collection/IterableViewLike$Sliced.scala$collection$IterableViewLike$Sliced$$$outer:()Lscala/collection/IterableViewLike;
const #18 = Asciz	scala/collection/IterableLike;
const #19 = class	#18;	//  scala/collection/IterableLike
const #20 = Asciz	()Lscala/collection/Iterator;;
const #21 = NameAndType	#10:#20;//  iterator:()Lscala/collection/Iterator;
const #22 = InterfaceMethod	#19.#21;	//  scala/collection/IterableLike.iterator:()Lscala/collection/Iterator;
const #23 = Asciz	scala/collection/TraversableViewLike$Sliced;
const #24 = class	#23;	//  scala/collection/TraversableViewLike$Sliced
const #25 = Asciz	from;
const #26 = Asciz	()I;
const #27 = NameAndType	#25:#26;//  from:()I
const #28 = InterfaceMethod	#24.#27;	//  scala/collection/TraversableViewLike$Sliced.from:()I
const #29 = Asciz	until;
const #30 = NameAndType	#29:#26;//  until:()I
const #31 = InterfaceMethod	#24.#30;	//  scala/collection/TraversableViewLike$Sliced.until:()I
const #32 = Asciz	scala/collection/Iterator;
const #33 = class	#32;	//  scala/collection/Iterator
const #34 = Asciz	slice;
const #35 = Asciz	(II)Lscala/collection/Iterator;;
const #36 = NameAndType	#34:#35;//  slice:(II)Lscala/collection/Iterator;
const #37 = InterfaceMethod	#33.#36;	//  scala/collection/Iterator.slice:(II)Lscala/collection/Iterator;
const #38 = Asciz	Scala;
const #39 = Asciz	InnerClasses;
const #40 = Asciz	scala/collection/IterableViewLike;
const #41 = class	#40;	//  scala/collection/IterableViewLike
const #42 = Asciz	Sliced;
const #43 = Asciz	scala/collection/TraversableViewLike;
const #44 = class	#43;	//  scala/collection/TraversableViewLike
const #45 = Asciz	scala/collection/IterableViewLike$Sliced$class;
const #46 = class	#45;	//  scala/collection/IterableViewLike$Sliced$class
const #47 = Asciz	java/lang/Object;
const #48 = class	#47;	//  java/lang/Object

{
public static void $init$(scala.collection.IterableViewLike$Sliced);
  Code:
   Stack=0, Locals=1, Args_size=1
   0:	return
  LineNumberTable: 
   line 32: 0

  LocalVariableTable: 
   Start  Length  Slot  Name   Signature
   0      1      0    $this       Lscala/collection/IterableViewLike$Sliced;


public static scala.collection.Iterator iterator(scala.collection.IterableViewLike$Sliced);
  Code:
   Stack=3, Locals=1, Args_size=1
   0:	aload_0
   1:	invokeinterface	#17,  1; //InterfaceMethod scala/collection/IterableViewLike$Sliced.scala$collection$IterableViewLike$Sliced$$$outer:()Lscala/collection/IterableViewLike;
   6:	invokeinterface	#22,  1; //InterfaceMethod scala/collection/IterableLike.iterator:()Lscala/collection/Iterator;
   11:	aload_0
   12:	invokeinterface	#28,  1; //InterfaceMethod scala/collection/TraversableViewLike$Sliced.from:()I
   17:	aload_0
   18:	invokeinterface	#31,  1; //InterfaceMethod scala/collection/TraversableViewLike$Sliced.until:()I
   23:	invokeinterface	#37,  3; //InterfaceMethod scala/collection/Iterator.slice:(II)Lscala/collection/Iterator;
   28:	areturn
  LineNumberTable: 
   line 33: 0

  LocalVariableTable: 
   Start  Length  Slot  Name   Signature
   0      29      0    $this       Lscala/collection/IterableViewLike$Sliced;


}

