Compiled from "Iterator.scala"
public final class scala.collection.Iterator$WithFilter$$anonfun$withFilter$1 extends scala.runtime.AbstractFunction1 implements java.io.Serializable
  SourceFile: "Iterator.scala"
  Scala: length = 0x
   
  InnerClass: 
   public final #66= #49 of #65; //WithFilter=class scala/collection/Iterator$WithFilter of class scala/collection/Iterator
   public final #67= #9 of #49; //$anonfun$withFilter$1=class scala/collection/Iterator$WithFilter$$anonfun$withFilter$1 of class scala/collection/Iterator$WithFilter
  minor version: 0
  major version: 49
  Constant pool:
const #1 = Asciz	SourceFile;
const #2 = Asciz	Iterator.scala;
const #3 = Asciz	<clinit>;
const #4 = Asciz	()V;
const #5 = Asciz	Code;
const #6 = Asciz	serialVersionUID;
const #7 = Asciz	J;
const #8 = Asciz	scala/collection/Iterator$WithFilter$$anonfun$withFilter$1;
const #9 = class	#8;	//  scala/collection/Iterator$WithFilter$$anonfun$withFilter$1
const #10 = NameAndType	#6:#7;//  serialVersionUID:J
const #11 = Field	#9.#10;	//  scala/collection/Iterator$WithFilter$$anonfun$withFilter$1.serialVersionUID:J
const #12 = Asciz	q$1;
const #13 = Asciz	Lscala/Function1;;
const #14 = Asciz	$outer;
const #15 = Asciz	Lscala/collection/Iterator$WithFilter;;
const #16 = Asciz	<init>;
const #17 = Asciz	(Lscala/collection/Iterator$WithFilter;Lscala/Function1;)V;
const #18 = Asciz	LineNumberTable;
const #19 = Asciz	java/lang/NullPointerException;
const #20 = class	#19;	//  java/lang/NullPointerException
const #21 = NameAndType	#16:#4;//  "<init>":()V
const #22 = Method	#20.#21;	//  java/lang/NullPointerException."<init>":()V
const #23 = NameAndType	#14:#15;//  $outer:Lscala/collection/Iterator$WithFilter;
const #24 = Field	#9.#23;	//  scala/collection/Iterator$WithFilter$$anonfun$withFilter$1.$outer:Lscala/collection/Iterator$WithFilter;
const #25 = NameAndType	#12:#13;//  q$1:Lscala/Function1;
const #26 = Field	#9.#25;	//  scala/collection/Iterator$WithFilter$$anonfun$withFilter$1.q$1:Lscala/Function1;
const #27 = Asciz	scala/runtime/AbstractFunction1;
const #28 = class	#27;	//  scala/runtime/AbstractFunction1
const #29 = Method	#28.#21;	//  scala/runtime/AbstractFunction1."<init>":()V
const #30 = Asciz	this;
const #31 = Asciz	Lscala/collection/Iterator$WithFilter$$anonfun$withFilter$1;;
const #32 = Asciz	LocalVariableTable;
const #33 = Asciz	(Lscala/collection/Iterator<TA;>.WithFilter;)V;
const #34 = Asciz	Signature;
const #35 = Asciz	apply;
const #36 = Asciz	(Ljava/lang/Object;)Ljava/lang/Object;;
const #37 = Asciz	(Ljava/lang/Object;)Z;
const #38 = NameAndType	#35:#37;//  apply:(Ljava/lang/Object;)Z
const #39 = Method	#9.#38;	//  scala/collection/Iterator$WithFilter$$anonfun$withFilter$1.apply:(Ljava/lang/Object;)Z
const #40 = Asciz	scala/runtime/BoxesRunTime;
const #41 = class	#40;	//  scala/runtime/BoxesRunTime
const #42 = Asciz	boxToBoolean;
const #43 = Asciz	(Z)Ljava/lang/Boolean;;
const #44 = NameAndType	#42:#43;//  boxToBoolean:(Z)Ljava/lang/Boolean;
const #45 = Method	#41.#44;	//  scala/runtime/BoxesRunTime.boxToBoolean:(Z)Ljava/lang/Boolean;
const #46 = Asciz	v1;
const #47 = Asciz	Ljava/lang/Object;;
const #48 = Asciz	scala/collection/Iterator$WithFilter;
const #49 = class	#48;	//  scala/collection/Iterator$WithFilter
const #50 = Asciz	scala$collection$Iterator$WithFilter$$p;
const #51 = NameAndType	#50:#13;//  scala$collection$Iterator$WithFilter$$p:Lscala/Function1;
const #52 = Field	#49.#51;	//  scala/collection/Iterator$WithFilter.scala$collection$Iterator$WithFilter$$p:Lscala/Function1;
const #53 = Asciz	scala/Function1;
const #54 = class	#53;	//  scala/Function1
const #55 = NameAndType	#35:#36;//  apply:(Ljava/lang/Object;)Ljava/lang/Object;
const #56 = InterfaceMethod	#54.#55;	//  scala/Function1.apply:(Ljava/lang/Object;)Ljava/lang/Object;
const #57 = Asciz	unboxToBoolean;
const #58 = NameAndType	#57:#37;//  unboxToBoolean:(Ljava/lang/Object;)Z
const #59 = Method	#41.#58;	//  scala/runtime/BoxesRunTime.unboxToBoolean:(Ljava/lang/Object;)Z
const #60 = Asciz	x;
const #61 = Asciz	(TA;)Z;
const #62 = Asciz	Scala;
const #63 = Asciz	InnerClasses;
const #64 = Asciz	scala/collection/Iterator;
const #65 = class	#64;	//  scala/collection/Iterator
const #66 = Asciz	WithFilter;
const #67 = Asciz	$anonfun$withFilter$1;
const #68 = Asciz	java/io/Serializable;
const #69 = class	#68;	//  java/io/Serializable

{
public static final long serialVersionUID;

public static {};
  Code:
   Stack=2, Locals=0, Args_size=0
   0:	lconst_0
   1:	putstatic	#11; //Field serialVersionUID:J
   4:	return

public scala.collection.Iterator$WithFilter$$anonfun$withFilter$1(scala.collection.Iterator$WithFilter, scala.Function1);
  Code:
   Stack=2, Locals=3, Args_size=3
   0:	aload_1
   1:	ifnonnull	12
   4:	new	#20; //class java/lang/NullPointerException
   7:	dup
   8:	invokespecial	#22; //Method java/lang/NullPointerException."<init>":()V
   11:	athrow
   12:	aload_0
   13:	aload_1
   14:	putfield	#24; //Field $outer:Lscala/collection/Iterator$WithFilter;
   17:	aload_0
   18:	aload_2
   19:	putfield	#26; //Field q$1:Lscala/Function1;
   22:	aload_0
   23:	invokespecial	#29; //Method scala/runtime/AbstractFunction1."<init>":()V
   26:	return
  LineNumberTable: 
   line 414: 0

  LocalVariableTable: 
   Start  Length  Slot  Name   Signature
   0      27      0    this       Lscala/collection/Iterator$WithFilter$$anonfun$withFilter$1;
   0      27      1    $outer       Lscala/collection/Iterator$WithFilter;

  Signature: length = 0x2
   00 21 

public final java.lang.Object apply(java.lang.Object);
  Code:
   Stack=2, Locals=3, Args_size=2
   0:	aload_0
   1:	aload_1
   2:	invokevirtual	#39; //Method apply:(Ljava/lang/Object;)Z
   5:	istore_2
   6:	iload_2
   7:	invokestatic	#45; //Method scala/runtime/BoxesRunTime.boxToBoolean:(Z)Ljava/lang/Boolean;
   10:	areturn
  LineNumberTable: 
   line 414: 0

  LocalVariableTable: 
   Start  Length  Slot  Name   Signature
   0      11      0    this       Lscala/collection/Iterator$WithFilter$$anonfun$withFilter$1;
   0      11      1    v1       Ljava/lang/Object;


public final boolean apply(java.lang.Object);
  Code:
   Stack=2, Locals=2, Args_size=2
   0:	aload_0
   1:	getfield	#24; //Field $outer:Lscala/collection/Iterator$WithFilter;
   4:	getfield	#52; //Field scala/collection/Iterator$WithFilter.scala$collection$Iterator$WithFilter$$p:Lscala/Function1;
   7:	aload_1
   8:	invokeinterface	#56,  2; //InterfaceMethod scala/Function1.apply:(Ljava/lang/Object;)Ljava/lang/Object;
   13:	invokestatic	#59; //Method scala/runtime/BoxesRunTime.unboxToBoolean:(Ljava/lang/Object;)Z
   16:	ifeq	39
   19:	aload_0
   20:	getfield	#26; //Field q$1:Lscala/Function1;
   23:	aload_1
   24:	invokeinterface	#56,  2; //InterfaceMethod scala/Function1.apply:(Ljava/lang/Object;)Ljava/lang/Object;
   29:	invokestatic	#59; //Method scala/runtime/BoxesRunTime.unboxToBoolean:(Ljava/lang/Object;)Z
   32:	ifeq	39
   35:	iconst_1
   36:	goto	40
   39:	iconst_0
   40:	ireturn
  LineNumberTable: 
   line 414: 0

  LocalVariableTable: 
   Start  Length  Slot  Name   Signature
   0      41      0    this       Lscala/collection/Iterator$WithFilter$$anonfun$withFilter$1;
   0      41      1    x       Ljava/lang/Object;

  Signature: length = 0x2
   00 3D 

}

