Compiled from "Iterator.scala"
public final class scala.collection.Iterator$$anonfun$toStream$1 extends java.lang.Object implements scala.Function0,scala.ScalaObject,java.io.Serializable
  SourceFile: "Iterator.scala"
  Scala: length = 0x
   
  InnerClass: 
   public final $anonfun$toStream$1=class scala/collection/Iterator$$anonfun$toStream$1 of class scala/collection/Iterator
  minor version: 0
  major version: 49
  Constant pool:
Asciz	SourceFile;
Asciz	Iterator.scala;
Asciz	<clinit>;
Asciz	()V;
Asciz	Code;
Asciz	serialVersionUID;
Asciz	J;
Asciz	scala/collection/Iterator$$anonfun$toStream$1;
class	scala/collection/Iterator$$anonfun$toStream$1
NameAndType	serialVersionUID:J
Field	scala/collection/Iterator$$anonfun$toStream$1.serialVersionUID:J
Asciz	$outer;
Asciz	Lscala/collection/Iterator;;
Asciz	<init>;
Asciz	(Lscala/collection/Iterator;)V;
Asciz	LineNumberTable;
Asciz	java/lang/NullPointerException;
class	java/lang/NullPointerException
NameAndType	"<init>":()V
Method	java/lang/NullPointerException."<init>":()V
NameAndType	$outer:Lscala/collection/Iterator;
Field	scala/collection/Iterator$$anonfun$toStream$1.$outer:Lscala/collection/Iterator;
Asciz	java/lang/Object;
class	java/lang/Object
Method	java/lang/Object."<init>":()V
Asciz	scala/Function0$class;
class	scala/Function0$class
Asciz	$init$;
Asciz	(Lscala/Function0;)V;
NameAndType	$init$:(Lscala/Function0;)V
Method	scala/Function0$class.$init$:(Lscala/Function0;)V
Asciz	this;
Asciz	Lscala/collection/Iterator$$anonfun$toStream$1;;
Asciz	LocalVariableTable;
Asciz	(Lscala/collection/Iterator<TA;>;)V;
Asciz	Signature;
Asciz	apply;
Asciz	()Ljava/lang/Object;;
Asciz	()Lscala/collection/immutable/Stream;;
NameAndType	apply:()Lscala/collection/immutable/Stream;
Method	scala/collection/Iterator$$anonfun$toStream$1.apply:()Lscala/collection/immutable/Stream;
Asciz	scala/collection/Iterator;
class	scala/collection/Iterator
Asciz	toStream;
NameAndType	toStream:()Lscala/collection/immutable/Stream;
InterfaceMethod	scala/collection/Iterator.toStream:()Lscala/collection/immutable/Stream;
Asciz	()Lscala/collection/immutable/Stream<TA;>;;
Asciz	toString;
Asciz	()Ljava/lang/String;;
Asciz	(Lscala/Function0;)Ljava/lang/String;;
NameAndType	toString:(Lscala/Function0;)Ljava/lang/String;
Method	scala/Function0$class.toString:(Lscala/Function0;)Ljava/lang/String;
Asciz	Scala;
Asciz	InnerClasses;
Asciz	$anonfun$toStream$1;
Asciz	scala/Function0;
class	scala/Function0
Asciz	scala/ScalaObject;
class	scala/ScalaObject
Asciz	java/io/Serializable;
class	java/io/Serializable

{
public static final long serialVersionUID;
  Signature: J

private final scala.collection.Iterator $outer;
  Signature: Lscala/collection/Iterator;

public static {};
  Signature: ()V
  Code:
   Stack=2, Locals=0, Args_size=0
	lconst_0
	putstatic	Field serialVersionUID:J
	return
  Labels:

public scala.collection.Iterator$$anonfun$toStream$1(scala.collection.Iterator);
  Signature: (Lscala/collection/Iterator;)V
  Code:
   Stack=2, Locals=2, Args_size=2
	aload_1
	ifnonnull	l1 // aload_0
	new	class java/lang/NullPointerException
	dup
	invokespecial	Method java/lang/NullPointerException."<init>":()V
	athrow
l1	aload_0
	aload_1
	putfield	Field $outer:Lscala/collection/Iterator;
	aload_0
	invokespecial	Method java/lang/Object."<init>":()V
	aload_0
	invokestatic	Method scala/Function0$class.$init$:(Lscala/Function0;)V
	return
  Labels:
   	l1 = 12 // aload_0
  LocalVariableTable: 
   Start  Length  Slot  Name   Signature
   0      26      0    this       Lscala/collection/Iterator$$anonfun$toStream$1;
   0      26      1    $outer       Lscala/collection/Iterator;

  Signature: length = 0x2
   00 23 

public final java.lang.Object apply();
  Signature: ()Ljava/lang/Object;
  Code:
   Stack=1, Locals=2, Args_size=1
	aload_0
	getfield	Field $outer:Lscala/collection/Iterator;
	astore_1
	aload_0
	invokevirtual	Method apply:()Lscala/collection/immutable/Stream;
	areturn
  Labels:
  LocalVariableTable: 
   Start  Length  Slot  Name   Signature
   0      10      0    this       Lscala/collection/Iterator$$anonfun$toStream$1;


public final scala.collection.immutable.Stream apply();
  Signature: ()Lscala/collection/immutable/Stream;
  Code:
   Stack=1, Locals=2, Args_size=1
	aload_0
	getfield	Field $outer:Lscala/collection/Iterator;
	astore_1
	aload_0
	getfield	Field $outer:Lscala/collection/Iterator;
	invokeinterface	InterfaceMethod scala/collection/Iterator.toStream:()Lscala/collection/immutable/Stream;
	areturn
  Labels:
  LocalVariableTable: 
   Start  Length  Slot  Name   Signature
   0      15      0    this       Lscala/collection/Iterator$$anonfun$toStream$1;

  Signature: length = 0x2
   00 2F 

public java.lang.String toString();
  Signature: ()Ljava/lang/String;
  Code:
   Stack=1, Locals=1, Args_size=1
	aload_0
	invokestatic	Method scala/Function0$class.toString:(Lscala/Function0;)Ljava/lang/String;
	areturn
  Labels:

}

