Compiled from "Iterator.scala"
public class scala.collection.Iterator$IteratorCanBuildFrom extends java.lang.Object implements scala.collection.generic.CanBuildFrom,scala.ScalaObject
  SourceFile: "Iterator.scala"
  Scala: length = 0x
   
  Signature: length = 0x2
   00 30 
  InnerClass: 
   public IteratorCanBuildFrom=class scala/collection/Iterator$IteratorCanBuildFrom of class scala/collection/Iterator
   public final $anonfun$newIterator$1=class scala/collection/Iterator$IteratorCanBuildFrom$$anonfun$newIterator$1 of class scala/collection/Iterator$IteratorCanBuildFrom
  minor version: 0
  major version: 49
  Constant pool:
Asciz	SourceFile;
Asciz	Iterator.scala;
Asciz	newIterator;
Asciz	()Lscala/collection/mutable/Builder;;
Asciz	Code;
Asciz	scala/collection/mutable/ArrayBuffer;
class	scala/collection/mutable/ArrayBuffer
Asciz	LineNumberTable;
Asciz	<init>;
Asciz	()V;
NameAndType	"<init>":()V
Method	scala/collection/mutable/ArrayBuffer."<init>":()V
Asciz	scala/collection/Iterator$IteratorCanBuildFrom$$anonfun$newIterator$1;
class	scala/collection/Iterator$IteratorCanBuildFrom$$anonfun$newIterator$1
Asciz	(Lscala/collection/Iterator$IteratorCanBuildFrom;)V;
NameAndType	"<init>":(Lscala/collection/Iterator$IteratorCanBuildFrom;)V
Method	scala/collection/Iterator$IteratorCanBuildFrom$$anonfun$newIterator$1."<init>":(Lscala/collection/Iterator$IteratorCanBuildFrom;)V
Asciz	scala/collection/mutable/Builder;
class	scala/collection/mutable/Builder
Asciz	mapResult;
Asciz	(Lscala/Function1;)Lscala/collection/mutable/Builder;;
NameAndType	mapResult:(Lscala/Function1;)Lscala/collection/mutable/Builder;
InterfaceMethod	scala/collection/mutable/Builder.mapResult:(Lscala/Function1;)Lscala/collection/mutable/Builder;
Asciz	()Lscala/collection/mutable/Builder<TA;Lscala/collection/Iterator<TA;>;>;;
Asciz	Signature;
Asciz	apply;
Asciz	(Lscala/collection/Iterator;)Lscala/collection/mutable/Builder;;
Asciz	scala/collection/Iterator$IteratorCanBuildFrom;
class	scala/collection/Iterator$IteratorCanBuildFrom
NameAndType	newIterator:()Lscala/collection/mutable/Builder;
Method	scala/collection/Iterator$IteratorCanBuildFrom.newIterator:()Lscala/collection/mutable/Builder;
Asciz	this;
Asciz	Lscala/collection/Iterator$IteratorCanBuildFrom;;
Asciz	from;
Asciz	Lscala/collection/Iterator;;
Asciz	LocalVariableTable;
Asciz	(Lscala/collection/Iterator<TA;>;)Lscala/collection/mutable/Builder<TA;Lscala/collection/Iterator<TA;>;>;;
Asciz	(Ljava/lang/Object;)Lscala/collection/mutable/Builder;;
Asciz	scala/collection/Iterator;
class	scala/collection/Iterator
NameAndType	apply:(Lscala/collection/Iterator;)Lscala/collection/mutable/Builder;
Method	scala/collection/Iterator$IteratorCanBuildFrom.apply:(Lscala/collection/Iterator;)Lscala/collection/mutable/Builder;
Asciz	Ljava/lang/Object;;
Asciz	java/lang/Object;
class	java/lang/Object
Method	java/lang/Object."<init>":()V
Asciz	Scala;
Asciz	<A:Ljava/lang/Object;>Ljava/lang/Object;Lscala/collection/generic/CanBuildFrom<Lscala/collection/Iterator<TA;>;TA;Lscala/collection/Iterator<TA;>;>;Lscala/ScalaObject;;
Asciz	InnerClasses;
Asciz	IteratorCanBuildFrom;
Asciz	$anonfun$newIterator$1;
Asciz	scala/collection/generic/CanBuildFrom;
class	scala/collection/generic/CanBuildFrom
Asciz	scala/ScalaObject;
class	scala/ScalaObject

{
public scala.collection.mutable.Builder newIterator();
  Signature: ()Lscala/collection/mutable/Builder;
  Code:
   Stack=4, Locals=1, Args_size=1
	new	class scala/collection/mutable/ArrayBuffer
	dup
	invokespecial	Method scala/collection/mutable/ArrayBuffer."<init>":()V
	new	class scala/collection/Iterator$IteratorCanBuildFrom$$anonfun$newIterator$1
	dup
	aload_0
	invokespecial	Method scala/collection/Iterator$IteratorCanBuildFrom$$anonfun$newIterator$1."<init>":(Lscala/collection/Iterator$IteratorCanBuildFrom;)V
	invokeinterface	InterfaceMethod scala/collection/mutable/Builder.mapResult:(Lscala/Function1;)Lscala/collection/mutable/Builder;
	areturn
  Labels:
  Signature: length = 0x2
   00 18 

public scala.collection.mutable.Builder apply(scala.collection.Iterator);
  Signature: (Lscala/collection/Iterator;)Lscala/collection/mutable/Builder;
  Code:
   Stack=1, Locals=2, Args_size=2
	aload_0
	invokevirtual	Method newIterator:()Lscala/collection/mutable/Builder;
	areturn
  Labels:
  LocalVariableTable: 
   Start  Length  Slot  Name   Signature
   0      5      0    this       Lscala/collection/Iterator$IteratorCanBuildFrom;
   0      5      1    from       Lscala/collection/Iterator;

  Signature: length = 0x2
   00 25 

public scala.collection.mutable.Builder apply();
  Signature: ()Lscala/collection/mutable/Builder;
  Code:
   Stack=1, Locals=1, Args_size=1
	aload_0
	invokevirtual	Method newIterator:()Lscala/collection/mutable/Builder;
	areturn
  Labels:
  Signature: length = 0x2
   00 18 

public scala.collection.mutable.Builder apply(java.lang.Object);
  Signature: (Ljava/lang/Object;)Lscala/collection/mutable/Builder;
  Code:
   Stack=2, Locals=2, Args_size=2
	aload_0
	aload_1
	checkcast	class scala/collection/Iterator
	invokevirtual	Method apply:(Lscala/collection/Iterator;)Lscala/collection/mutable/Builder;
	areturn
  Labels:
  LocalVariableTable: 
   Start  Length  Slot  Name   Signature
   0      9      0    this       Lscala/collection/Iterator$IteratorCanBuildFrom;
   0      9      1    from       Ljava/lang/Object;


public scala.collection.Iterator$IteratorCanBuildFrom();
  Signature: ()V
  Code:
   Stack=1, Locals=1, Args_size=1
	aload_0
	invokespecial	Method java/lang/Object."<init>":()V
	return
  Labels:
  Signature: length = 0x2
   00 0A 

}

