Compiled from "IterableLike.scala"
public abstract class scala.collection.IterableLike$class extends java.lang.Object
  SourceFile: "IterableLike.scala"
  Scala: length = 0x
   
  InnerClass: 
   public final #264= #44 of #13; //$anon$1=class scala/collection/IterableLike$$anon$1 of class scala/collection/IterableLike
   public final #265= #189 of #13; //$anonfun$takeRight$1=class scala/collection/IterableLike$$anonfun$takeRight$1 of class scala/collection/IterableLike
   public final #266= #111 of #13; //$anonfun$zipWithIndex$1=class scala/collection/IterableLike$$anonfun$zipWithIndex$1 of class scala/collection/IterableLike
  minor version: 0
  major version: 49
  Constant pool:
const #1 = Asciz	SourceFile;
const #2 = Asciz	IterableLike.scala;
const #3 = Asciz	$init$;
const #4 = Asciz	(Lscala/collection/IterableLike;)V;
const #5 = Asciz	Code;
const #6 = Asciz	LineNumberTable;
const #7 = Asciz	$this;
const #8 = Asciz	Lscala/collection/IterableLike;;
const #9 = Asciz	LocalVariableTable;
const #10 = Asciz	projection;
const #11 = Asciz	(Lscala/collection/IterableLike;)Ljava/lang/Object;;
const #12 = Asciz	scala/collection/IterableLike;
const #13 = class	#12;	//  scala/collection/IterableLike
const #14 = Asciz	view;
const #15 = Asciz	()Ljava/lang/Object;;
const #16 = NameAndType	#14:#15;//  view:()Ljava/lang/Object;
const #17 = InterfaceMethod	#13.#16;	//  scala/collection/IterableLike.view:()Ljava/lang/Object;
const #18 = Asciz	Deprecated;
const #19 = Asciz	firstOption;
const #20 = Asciz	(Lscala/collection/IterableLike;)Lscala/Option;;
const #21 = Asciz	scala/collection/TraversableLike;
const #22 = class	#21;	//  scala/collection/TraversableLike
const #23 = Asciz	headOption;
const #24 = Asciz	()Lscala/Option;;
const #25 = NameAndType	#23:#24;//  headOption:()Lscala/Option;
const #26 = InterfaceMethod	#22.#25;	//  scala/collection/TraversableLike.headOption:()Lscala/Option;
const #27 = Asciz	first;
const #28 = Asciz	head;
const #29 = NameAndType	#28:#15;//  head:()Ljava/lang/Object;
const #30 = InterfaceMethod	#13.#29;	//  scala/collection/IterableLike.head:()Ljava/lang/Object;
const #31 = Asciz	(Lscala/collection/IterableLike;II)Lscala/collection/IterableView;;
const #32 = Asciz	scala/collection/TraversableViewLike;
const #33 = class	#32;	//  scala/collection/TraversableViewLike
const #34 = Asciz	slice;
const #35 = Asciz	(II)Lscala/collection/TraversableView;;
const #36 = NameAndType	#34:#35;//  slice:(II)Lscala/collection/TraversableView;
const #37 = InterfaceMethod	#33.#36;	//  scala/collection/TraversableViewLike.slice:(II)Lscala/collection/TraversableView;
const #38 = Asciz	scala/collection/IterableView;
const #39 = class	#38;	//  scala/collection/IterableView
const #40 = Asciz	from;
const #41 = Asciz	I;
const #42 = Asciz	until;
const #43 = Asciz	scala/collection/IterableLike$$anon$1;
const #44 = class	#43;	//  scala/collection/IterableLike$$anon$1
const #45 = Asciz	<init>;
const #46 = NameAndType	#45:#4;//  "<init>":(Lscala/collection/IterableLike;)V
const #47 = Method	#44.#46;	//  scala/collection/IterableLike$$anon$1."<init>":(Lscala/collection/IterableLike;)V
const #48 = Asciz	canEqual;
const #49 = Asciz	(Lscala/collection/IterableLike;Ljava/lang/Object;)Z;
const #50 = Asciz	that;
const #51 = Asciz	Ljava/lang/Object;;
const #52 = Asciz	toStream;
const #53 = Asciz	(Lscala/collection/IterableLike;)Lscala/collection/immutable/Stream;;
const #54 = Asciz	iterator;
const #55 = Asciz	()Lscala/collection/Iterator;;
const #56 = NameAndType	#54:#55;//  iterator:()Lscala/collection/Iterator;
const #57 = InterfaceMethod	#13.#56;	//  scala/collection/IterableLike.iterator:()Lscala/collection/Iterator;
const #58 = Asciz	scala/collection/Iterator;
const #59 = class	#58;	//  scala/collection/Iterator
const #60 = Asciz	()Lscala/collection/immutable/Stream;;
const #61 = NameAndType	#52:#60;//  toStream:()Lscala/collection/immutable/Stream;
const #62 = InterfaceMethod	#59.#61;	//  scala/collection/Iterator.toStream:()Lscala/collection/immutable/Stream;
const #63 = Asciz	sameElements;
const #64 = Asciz	(Lscala/collection/IterableLike;Lscala/collection/Iterable;)Z;
const #65 = Asciz	hasNext;
const #66 = Asciz	()Z;
const #67 = NameAndType	#65:#66;//  hasNext:()Z
const #68 = InterfaceMethod	#59.#67;	//  scala/collection/Iterator.hasNext:()Z
const #69 = Asciz	next;
const #70 = NameAndType	#69:#15;//  next:()Ljava/lang/Object;
const #71 = InterfaceMethod	#59.#70;	//  scala/collection/Iterator.next:()Ljava/lang/Object;
const #72 = Asciz	java/lang/Number;
const #73 = class	#72;	//  java/lang/Number
const #74 = Asciz	java/lang/Character;
const #75 = class	#74;	//  java/lang/Character
const #76 = Asciz	scala/runtime/BoxesRunTime;
const #77 = class	#76;	//  scala/runtime/BoxesRunTime
const #78 = Asciz	equals2;
const #79 = Asciz	(Ljava/lang/Object;Ljava/lang/Object;)Z;
const #80 = NameAndType	#78:#79;//  equals2:(Ljava/lang/Object;Ljava/lang/Object;)Z
const #81 = Method	#77.#80;	//  scala/runtime/BoxesRunTime.equals2:(Ljava/lang/Object;Ljava/lang/Object;)Z
const #82 = Asciz	java/lang/Object;
const #83 = class	#82;	//  java/lang/Object
const #84 = Asciz	equals;
const #85 = Asciz	(Ljava/lang/Object;)Z;
const #86 = NameAndType	#84:#85;//  equals:(Ljava/lang/Object;)Z
const #87 = Method	#83.#86;	//  java/lang/Object.equals:(Ljava/lang/Object;)Z
const #88 = Asciz	Lscala/collection/Iterable;;
const #89 = Asciz	x0;
const #90 = Asciz	y0;
const #91 = Asciz	these;
const #92 = Asciz	Lscala/collection/Iterator;;
const #93 = Asciz	those;
const #94 = Asciz	zipWithIndex;
const #95 = Asciz	(Lscala/collection/IterableLike;Lscala/collection/generic/CanBuildFrom;)Ljava/lang/Object;;
const #96 = Asciz	repr;
const #97 = NameAndType	#96:#15;//  repr:()Ljava/lang/Object;
const #98 = InterfaceMethod	#22.#97;	//  scala/collection/TraversableLike.repr:()Ljava/lang/Object;
const #99 = Asciz	scala/collection/generic/CanBuildFrom;
const #100 = class	#99;	//  scala/collection/generic/CanBuildFrom
const #101 = Asciz	apply;
const #102 = Asciz	(Ljava/lang/Object;)Lscala/collection/mutable/Builder;;
const #103 = NameAndType	#101:#102;//  apply:(Ljava/lang/Object;)Lscala/collection/mutable/Builder;
const #104 = InterfaceMethod	#100.#103;	//  scala/collection/generic/CanBuildFrom.apply:(Ljava/lang/Object;)Lscala/collection/mutable/Builder;
const #105 = Asciz	scala/runtime/IntRef;
const #106 = class	#105;	//  scala/runtime/IntRef
const #107 = Asciz	(I)V;
const #108 = NameAndType	#45:#107;//  "<init>":(I)V
const #109 = Method	#106.#108;	//  scala/runtime/IntRef."<init>":(I)V
const #110 = Asciz	scala/collection/IterableLike$$anonfun$zipWithIndex$1;
const #111 = class	#110;	//  scala/collection/IterableLike$$anonfun$zipWithIndex$1
const #112 = Asciz	(Lscala/collection/IterableLike;Lscala/collection/mutable/Builder;Lscala/runtime/IntRef;)V;
const #113 = NameAndType	#45:#112;//  "<init>":(Lscala/collection/IterableLike;Lscala/collection/mutable/Builder;Lscala/runtime/IntRef;)V
const #114 = Method	#111.#113;	//  scala/collection/IterableLike$$anonfun$zipWithIndex$1."<init>":(Lscala/collection/IterableLike;Lscala/collection/mutable/Builder;Lscala/runtime/IntRef;)V
const #115 = Asciz	foreach;
const #116 = Asciz	(Lscala/Function1;)V;
const #117 = NameAndType	#115:#116;//  foreach:(Lscala/Function1;)V
const #118 = InterfaceMethod	#13.#117;	//  scala/collection/IterableLike.foreach:(Lscala/Function1;)V
const #119 = Asciz	scala/collection/mutable/Builder;
const #120 = class	#119;	//  scala/collection/mutable/Builder
const #121 = Asciz	result;
const #122 = NameAndType	#121:#15;//  result:()Ljava/lang/Object;
const #123 = InterfaceMethod	#120.#122;	//  scala/collection/mutable/Builder.result:()Ljava/lang/Object;
const #124 = Asciz	bf;
const #125 = Asciz	Lscala/collection/generic/CanBuildFrom;;
const #126 = Asciz	b$2;
const #127 = Asciz	Lscala/collection/mutable/Builder;;
const #128 = Asciz	i$1;
const #129 = Asciz	Lscala/runtime/IntRef;;
const #130 = Asciz	zipAll;
const #131 = Asciz	(Lscala/collection/IterableLike;Lscala/collection/Iterable;Ljava/lang/Object;Ljava/lang/Object;Lscala/collection/generic/CanBuildFrom;)Ljava/lang/Object;;
const #132 = Asciz	scala/Tuple2;
const #133 = class	#132;	//  scala/Tuple2
const #134 = Asciz	(Ljava/lang/Object;Ljava/lang/Object;)V;
const #135 = NameAndType	#45:#134;//  "<init>":(Ljava/lang/Object;Ljava/lang/Object;)V
const #136 = Method	#133.#135;	//  scala/Tuple2."<init>":(Ljava/lang/Object;Ljava/lang/Object;)V
const #137 = Asciz	$plus$eq;
const #138 = NameAndType	#137:#102;//  $plus$eq:(Ljava/lang/Object;)Lscala/collection/mutable/Builder;
const #139 = InterfaceMethod	#120.#138;	//  scala/collection/mutable/Builder.$plus$eq:(Ljava/lang/Object;)Lscala/collection/mutable/Builder;
const #140 = Asciz	thisElem;
const #141 = Asciz	thatElem;
const #142 = Asciz	b;
const #143 = Asciz	zip;
const #144 = Asciz	(Lscala/collection/IterableLike;Lscala/collection/Iterable;Lscala/collection/generic/CanBuildFrom;)Ljava/lang/Object;;
const #145 = Asciz	copyToArray;
const #146 = Asciz	(Lscala/collection/IterableLike;Ljava/lang/Object;II)V;
const #147 = Asciz	scala/runtime/RichInt;
const #148 = class	#147;	//  scala/runtime/RichInt
const #149 = Method	#148.#108;	//  scala/runtime/RichInt."<init>":(I)V
const #150 = Asciz	java/lang/reflect/Array;
const #151 = class	#150;	//  java/lang/reflect/Array
const #152 = Asciz	getLength;
const #153 = Asciz	(Ljava/lang/Object;)I;
const #154 = NameAndType	#152:#153;//  getLength:(Ljava/lang/Object;)I
const #155 = Method	#151.#154;	//  java/lang/reflect/Array.getLength:(Ljava/lang/Object;)I
const #156 = Asciz	min;
const #157 = Asciz	(I)I;
const #158 = NameAndType	#156:#157;//  min:(I)I
const #159 = Method	#148.#158;	//  scala/runtime/RichInt.min:(I)I
const #160 = Asciz	set;
const #161 = Asciz	(Ljava/lang/Object;ILjava/lang/Object;)V;
const #162 = NameAndType	#160:#161;//  set:(Ljava/lang/Object;ILjava/lang/Object;)V
const #163 = Method	#151.#162;	//  java/lang/reflect/Array.set:(Ljava/lang/Object;ILjava/lang/Object;)V
const #164 = Asciz	xs;
const #165 = Asciz	start;
const #166 = Asciz	len;
const #167 = Asciz	end;
const #168 = Asciz	it;
const #169 = Asciz	i;
const #170 = Asciz	dropRight;
const #171 = Asciz	(Lscala/collection/IterableLike;I)Ljava/lang/Object;;
const #172 = Asciz	newBuilder;
const #173 = Asciz	()Lscala/collection/mutable/Builder;;
const #174 = NameAndType	#172:#173;//  newBuilder:()Lscala/collection/mutable/Builder;
const #175 = InterfaceMethod	#22.#174;	//  scala/collection/TraversableLike.newBuilder:()Lscala/collection/mutable/Builder;
const #176 = Asciz	drop;
const #177 = Asciz	(I)Lscala/collection/Iterator;;
const #178 = NameAndType	#176:#177;//  drop:(I)Lscala/collection/Iterator;
const #179 = InterfaceMethod	#59.#178;	//  scala/collection/Iterator.drop:(I)Lscala/collection/Iterator;
const #180 = Asciz	n;
const #181 = Asciz	lead;
const #182 = Asciz	takeRight;
const #183 = Asciz	scala/runtime/BooleanRef;
const #184 = class	#183;	//  scala/runtime/BooleanRef
const #185 = Asciz	(Z)V;
const #186 = NameAndType	#45:#185;//  "<init>":(Z)V
const #187 = Method	#184.#186;	//  scala/runtime/BooleanRef."<init>":(Z)V
const #188 = Asciz	scala/collection/IterableLike$$anonfun$takeRight$1;
const #189 = class	#188;	//  scala/collection/IterableLike$$anonfun$takeRight$1
const #190 = Asciz	(Lscala/collection/IterableLike;Lscala/collection/mutable/Builder;Lscala/collection/Iterator;Lscala/runtime/BooleanRef;)V;
const #191 = NameAndType	#45:#190;//  "<init>":(Lscala/collection/IterableLike;Lscala/collection/mutable/Builder;Lscala/collection/Iterator;Lscala/runtime/BooleanRef;)V
const #192 = Method	#189.#191;	//  scala/collection/IterableLike$$anonfun$takeRight$1."<init>":(Lscala/collection/IterableLike;Lscala/collection/mutable/Builder;Lscala/collection/Iterator;Lscala/runtime/BooleanRef;)V
const #193 = Asciz	b$1;
const #194 = Asciz	lead$1;
const #195 = Asciz	go$1;
const #196 = Asciz	Lscala/runtime/BooleanRef;;
const #197 = Asciz	takeWhile;
const #198 = Asciz	(Lscala/collection/IterableLike;Lscala/Function1;)Ljava/lang/Object;;
const #199 = Asciz	scala/Function1;
const #200 = class	#199;	//  scala/Function1
const #201 = Asciz	(Ljava/lang/Object;)Ljava/lang/Object;;
const #202 = NameAndType	#101:#201;//  apply:(Ljava/lang/Object;)Ljava/lang/Object;
const #203 = InterfaceMethod	#200.#202;	//  scala/Function1.apply:(Ljava/lang/Object;)Ljava/lang/Object;
const #204 = Asciz	unboxToBoolean;
const #205 = NameAndType	#204:#85;//  unboxToBoolean:(Ljava/lang/Object;)Z
const #206 = Method	#77.#205;	//  scala/runtime/BoxesRunTime.unboxToBoolean:(Ljava/lang/Object;)Z
const #207 = Asciz	p;
const #208 = Asciz	Lscala/Function1;;
const #209 = Asciz	x;
const #210 = Asciz	(Lscala/collection/IterableLike;II)Ljava/lang/Object;;
const #211 = Asciz	take;
const #212 = Asciz	isEmpty;
const #213 = NameAndType	#212:#66;//  isEmpty:()Z
const #214 = InterfaceMethod	#13.#213;	//  scala/collection/IterableLike.isEmpty:()Z
const #215 = Asciz	java/util/NoSuchElementException;
const #216 = class	#215;	//  java/util/NoSuchElementException
const #217 = Asciz	()V;
const #218 = NameAndType	#45:#217;//  "<init>":()V
const #219 = Method	#216.#218;	//  java/util/NoSuchElementException."<init>":()V
const #220 = Asciz	toIterable;
const #221 = Asciz	(Lscala/collection/IterableLike;)Lscala/collection/Iterable;;
const #222 = Asciz	thisCollection;
const #223 = Asciz	()Lscala/collection/Iterable;;
const #224 = NameAndType	#222:#223;//  thisCollection:()Lscala/collection/Iterable;
const #225 = InterfaceMethod	#13.#224;	//  scala/collection/IterableLike.thisCollection:()Lscala/collection/Iterable;
const #226 = Asciz	reduceRight;
const #227 = Asciz	(Lscala/collection/IterableLike;Lscala/Function2;)Ljava/lang/Object;;
const #228 = Asciz	(Lscala/Function2;)Ljava/lang/Object;;
const #229 = NameAndType	#226:#228;//  reduceRight:(Lscala/Function2;)Ljava/lang/Object;
const #230 = InterfaceMethod	#59.#229;	//  scala/collection/Iterator.reduceRight:(Lscala/Function2;)Ljava/lang/Object;
const #231 = Asciz	op;
const #232 = Asciz	Lscala/Function2;;
const #233 = Asciz	foldRight;
const #234 = Asciz	(Lscala/collection/IterableLike;Ljava/lang/Object;Lscala/Function2;)Ljava/lang/Object;;
const #235 = Asciz	(Ljava/lang/Object;Lscala/Function2;)Ljava/lang/Object;;
const #236 = NameAndType	#233:#235;//  foldRight:(Ljava/lang/Object;Lscala/Function2;)Ljava/lang/Object;
const #237 = InterfaceMethod	#59.#236;	//  scala/collection/Iterator.foldRight:(Ljava/lang/Object;Lscala/Function2;)Ljava/lang/Object;
const #238 = Asciz	z;
const #239 = Asciz	(Lscala/collection/IterableLike;)Z;
const #240 = Asciz	find;
const #241 = Asciz	(Lscala/collection/IterableLike;Lscala/Function1;)Lscala/Option;;
const #242 = Asciz	(Lscala/Function1;)Lscala/Option;;
const #243 = NameAndType	#240:#242;//  find:(Lscala/Function1;)Lscala/Option;
const #244 = InterfaceMethod	#59.#243;	//  scala/collection/Iterator.find:(Lscala/Function1;)Lscala/Option;
const #245 = Asciz	exists;
const #246 = Asciz	(Lscala/collection/IterableLike;Lscala/Function1;)Z;
const #247 = Asciz	(Lscala/Function1;)Z;
const #248 = NameAndType	#245:#247;//  exists:(Lscala/Function1;)Z
const #249 = InterfaceMethod	#59.#248;	//  scala/collection/Iterator.exists:(Lscala/Function1;)Z
const #250 = Asciz	forall;
const #251 = NameAndType	#250:#247;//  forall:(Lscala/Function1;)Z
const #252 = InterfaceMethod	#59.#251;	//  scala/collection/Iterator.forall:(Lscala/Function1;)Z
const #253 = Asciz	(Lscala/collection/IterableLike;Lscala/Function1;)V;
const #254 = InterfaceMethod	#59.#117;	//  scala/collection/Iterator.foreach:(Lscala/Function1;)V
const #255 = Asciz	f;
const #256 = Asciz	elements;
const #257 = Asciz	(Lscala/collection/IterableLike;)Lscala/collection/Iterator;;
const #258 = Asciz	toCollection;
const #259 = Asciz	(Lscala/collection/IterableLike;Ljava/lang/Object;)Lscala/collection/Iterable;;
const #260 = Asciz	scala/collection/Iterable;
const #261 = class	#260;	//  scala/collection/Iterable
const #262 = Asciz	Scala;
const #263 = Asciz	InnerClasses;
const #264 = Asciz	$anon$1;
const #265 = Asciz	$anonfun$takeRight$1;
const #266 = Asciz	$anonfun$zipWithIndex$1;
const #267 = Asciz	scala/collection/IterableLike$class;
const #268 = class	#267;	//  scala/collection/IterableLike$class

{
public static void $init$(scala.collection.IterableLike);
  Code:
   Stack=0, Locals=1, Args_size=1
   0:	return
  LineNumberTable: 
   line 59: 0

  LocalVariableTable: 
   Start  Length  Slot  Name   Signature
   0      1      0    $this       Lscala/collection/IterableLike;


public static java.lang.Object projection(scala.collection.IterableLike);
  Code:
   Stack=1, Locals=1, Args_size=1
   0:	aload_0
   1:	invokeinterface	#17,  1; //InterfaceMethod scala/collection/IterableLike.view:()Ljava/lang/Object;
   6:	areturn
  LineNumberTable: 
   line 350: 0

  LocalVariableTable: 
   Start  Length  Slot  Name   Signature
   0      7      0    $this       Lscala/collection/IterableLike;

  Deprecated: true

public static scala.Option firstOption(scala.collection.IterableLike);
  Code:
   Stack=1, Locals=1, Args_size=1
   0:	aload_0
   1:	invokeinterface	#26,  1; //InterfaceMethod scala/collection/TraversableLike.headOption:()Lscala/Option;
   6:	areturn
  LineNumberTable: 
   line 342: 0

  LocalVariableTable: 
   Start  Length  Slot  Name   Signature
   0      7      0    $this       Lscala/collection/IterableLike;

  Deprecated: true

public static java.lang.Object first(scala.collection.IterableLike);
  Code:
   Stack=1, Locals=1, Args_size=1
   0:	aload_0
   1:	invokeinterface	#30,  1; //InterfaceMethod scala/collection/IterableLike.head:()Ljava/lang/Object;
   6:	areturn
  LineNumberTable: 
   line 338: 0

  LocalVariableTable: 
   Start  Length  Slot  Name   Signature
   0      7      0    $this       Lscala/collection/IterableLike;

  Deprecated: true

public static scala.collection.IterableView view(scala.collection.IterableLike, int, int);
  Code:
   Stack=3, Locals=3, Args_size=3
   0:	aload_0
   1:	invokeinterface	#17,  1; //InterfaceMethod scala/collection/IterableLike.view:()Ljava/lang/Object;
   6:	checkcast	#33; //class scala/collection/TraversableViewLike
   9:	iload_1
   10:	iload_2
   11:	invokeinterface	#37,  3; //InterfaceMethod scala/collection/TraversableViewLike.slice:(II)Lscala/collection/TraversableView;
   16:	checkcast	#39; //class scala/collection/IterableView
   19:	areturn
  LineNumberTable: 
   line 336: 0

  LocalVariableTable: 
   Start  Length  Slot  Name   Signature
   0      20      0    $this       Lscala/collection/IterableLike;
   0      20      1    from       I
   0      20      2    until       I


public static java.lang.Object view(scala.collection.IterableLike);
  Code:
   Stack=3, Locals=1, Args_size=1
   0:	new	#44; //class scala/collection/IterableLike$$anon$1
   3:	dup
   4:	aload_0
   5:	invokespecial	#47; //Method scala/collection/IterableLike$$anon$1."<init>":(Lscala/collection/IterableLike;)V
   8:	areturn
  LineNumberTable: 
   line 331: 0

  LocalVariableTable: 
   Start  Length  Slot  Name   Signature
   0      9      0    $this       Lscala/collection/IterableLike;


public static boolean canEqual(scala.collection.IterableLike, java.lang.Object);
  Code:
   Stack=1, Locals=2, Args_size=2
   0:	iconst_1
   1:	ireturn
  LineNumberTable: 
   line 329: 0

  LocalVariableTable: 
   Start  Length  Slot  Name   Signature
   0      2      0    $this       Lscala/collection/IterableLike;
   0      2      1    that       Ljava/lang/Object;


public static scala.collection.immutable.Stream toStream(scala.collection.IterableLike);
  Code:
   Stack=1, Locals=1, Args_size=1
   0:	aload_0
   1:	invokeinterface	#57,  1; //InterfaceMethod scala/collection/IterableLike.iterator:()Lscala/collection/Iterator;
   6:	invokeinterface	#62,  1; //InterfaceMethod scala/collection/Iterator.toStream:()Lscala/collection/immutable/Stream;
   11:	areturn
  LineNumberTable: 
   line 321: 0

  LocalVariableTable: 
   Start  Length  Slot  Name   Signature
   0      12      0    $this       Lscala/collection/IterableLike;


public static boolean sameElements(scala.collection.IterableLike, scala.collection.Iterable);
  Code:
   Stack=2, Locals=6, Args_size=2
   0:	aload_0
   1:	invokeinterface	#57,  1; //InterfaceMethod scala/collection/IterableLike.iterator:()Lscala/collection/Iterator;
   6:	astore	4
   8:	aload_1
   9:	invokeinterface	#57,  1; //InterfaceMethod scala/collection/IterableLike.iterator:()Lscala/collection/Iterator;
   14:	astore	5
   16:	aload	4
   18:	invokeinterface	#68,  1; //InterfaceMethod scala/collection/Iterator.hasNext:()Z
   23:	ifeq	101
   26:	aload	5
   28:	invokeinterface	#68,  1; //InterfaceMethod scala/collection/Iterator.hasNext:()Z
   33:	ifeq	101
   36:	aload	4
   38:	invokeinterface	#71,  1; //InterfaceMethod scala/collection/Iterator.next:()Ljava/lang/Object;
   43:	aload	5
   45:	invokeinterface	#71,  1; //InterfaceMethod scala/collection/Iterator.next:()Ljava/lang/Object;
   50:	astore_3
   51:	astore_2
   52:	aload_2
   53:	aload_3
   54:	if_acmpne	61
   57:	iconst_1
   58:	goto	96
   61:	aload_2
   62:	ifnonnull	69
   65:	iconst_0
   66:	goto	96
   69:	aload_2
   70:	instanceof	#73; //class java/lang/Number
   73:	ifne	83
   76:	aload_2
   77:	instanceof	#75; //class java/lang/Character
   80:	ifeq	91
   83:	aload_2
   84:	aload_3
   85:	invokestatic	#81; //Method scala/runtime/BoxesRunTime.equals2:(Ljava/lang/Object;Ljava/lang/Object;)Z
   88:	goto	96
   91:	aload_2
   92:	aload_3
   93:	invokevirtual	#87; //Method java/lang/Object.equals:(Ljava/lang/Object;)Z
   96:	ifne	16
   99:	iconst_0
   100:	ireturn
   101:	aload	4
   103:	invokeinterface	#68,  1; //InterfaceMethod scala/collection/Iterator.hasNext:()Z
   108:	ifne	121
   111:	aload	5
   113:	invokeinterface	#68,  1; //InterfaceMethod scala/collection/Iterator.hasNext:()Z
   118:	ifeq	125
   121:	iconst_0
   122:	goto	126
   125:	iconst_1
   126:	ireturn
  LineNumberTable: 
   line 312: 0
   line 313: 8
   line 314: 16
   line 315: 36
   line 316: 99
   line 318: 101
   line 311: 126

  LocalVariableTable: 
   Start  Length  Slot  Name   Signature
   0      127      0    $this       Lscala/collection/IterableLike;
   0      127      1    that       Lscala/collection/Iterable;
   57      42      2    x0       Ljava/lang/Object;
   57      42      3    y0       Ljava/lang/Object;
   8      119      4    these       Lscala/collection/Iterator;
   16      111      5    those       Lscala/collection/Iterator;


public static java.lang.Object zipWithIndex(scala.collection.IterableLike, scala.collection.generic.CanBuildFrom);
  Code:
   Stack=6, Locals=4, Args_size=2
   0:	aload_1
   1:	aload_0
   2:	invokeinterface	#98,  1; //InterfaceMethod scala/collection/TraversableLike.repr:()Ljava/lang/Object;
   7:	invokeinterface	#104,  2; //InterfaceMethod scala/collection/generic/CanBuildFrom.apply:(Ljava/lang/Object;)Lscala/collection/mutable/Builder;
   12:	astore_2
   13:	new	#106; //class scala/runtime/IntRef
   16:	dup
   17:	iconst_0
   18:	invokespecial	#109; //Method scala/runtime/IntRef."<init>":(I)V
   21:	astore_3
   22:	aload_0
   23:	new	#111; //class scala/collection/IterableLike$$anonfun$zipWithIndex$1
   26:	dup
   27:	aload_0
   28:	aload_2
   29:	aload_3
   30:	invokespecial	#114; //Method scala/collection/IterableLike$$anonfun$zipWithIndex$1."<init>":(Lscala/collection/IterableLike;Lscala/collection/mutable/Builder;Lscala/runtime/IntRef;)V
   33:	invokeinterface	#118,  2; //InterfaceMethod scala/collection/IterableLike.foreach:(Lscala/Function1;)V
   38:	aload_2
   39:	invokeinterface	#123,  1; //InterfaceMethod scala/collection/mutable/Builder.result:()Ljava/lang/Object;
   44:	areturn
  LineNumberTable: 
   line 288: 0
   line 289: 13
   line 290: 22
   line 294: 38

  LocalVariableTable: 
   Start  Length  Slot  Name   Signature
   0      45      0    $this       Lscala/collection/IterableLike;
   0      45      1    bf       Lscala/collection/generic/CanBuildFrom;
   13      31      2    b$2       Lscala/collection/mutable/Builder;
   22      22      3    i$1       Lscala/runtime/IntRef;


public static java.lang.Object zipAll(scala.collection.IterableLike, scala.collection.Iterable, java.lang.Object, java.lang.Object, scala.collection.generic.CanBuildFrom);
  Code:
   Stack=5, Locals=8, Args_size=5
   0:	aload	4
   2:	aload_0
   3:	invokeinterface	#98,  1; //InterfaceMethod scala/collection/TraversableLike.repr:()Ljava/lang/Object;
   8:	invokeinterface	#104,  2; //InterfaceMethod scala/collection/generic/CanBuildFrom.apply:(Ljava/lang/Object;)Lscala/collection/mutable/Builder;
   13:	astore	5
   15:	aload_0
   16:	invokeinterface	#57,  1; //InterfaceMethod scala/collection/IterableLike.iterator:()Lscala/collection/Iterator;
   21:	astore	6
   23:	aload_1
   24:	invokeinterface	#57,  1; //InterfaceMethod scala/collection/IterableLike.iterator:()Lscala/collection/Iterator;
   29:	astore	7
   31:	aload	6
   33:	invokeinterface	#68,  1; //InterfaceMethod scala/collection/Iterator.hasNext:()Z
   38:	ifeq	83
   41:	aload	7
   43:	invokeinterface	#68,  1; //InterfaceMethod scala/collection/Iterator.hasNext:()Z
   48:	ifeq	83
   51:	aload	5
   53:	new	#133; //class scala/Tuple2
   56:	dup
   57:	aload	6
   59:	invokeinterface	#71,  1; //InterfaceMethod scala/collection/Iterator.next:()Ljava/lang/Object;
   64:	aload	7
   66:	invokeinterface	#71,  1; //InterfaceMethod scala/collection/Iterator.next:()Ljava/lang/Object;
   71:	invokespecial	#136; //Method scala/Tuple2."<init>":(Ljava/lang/Object;Ljava/lang/Object;)V
   74:	invokeinterface	#139,  2; //InterfaceMethod scala/collection/mutable/Builder.$plus$eq:(Ljava/lang/Object;)Lscala/collection/mutable/Builder;
   79:	pop
   80:	goto	31
   83:	aload	6
   85:	invokeinterface	#68,  1; //InterfaceMethod scala/collection/Iterator.hasNext:()Z
   90:	ifeq	119
   93:	aload	5
   95:	new	#133; //class scala/Tuple2
   98:	dup
   99:	aload	6
   101:	invokeinterface	#71,  1; //InterfaceMethod scala/collection/Iterator.next:()Ljava/lang/Object;
   106:	aload_3
   107:	invokespecial	#136; //Method scala/Tuple2."<init>":(Ljava/lang/Object;Ljava/lang/Object;)V
   110:	invokeinterface	#139,  2; //InterfaceMethod scala/collection/mutable/Builder.$plus$eq:(Ljava/lang/Object;)Lscala/collection/mutable/Builder;
   115:	pop
   116:	goto	83
   119:	aload	7
   121:	invokeinterface	#68,  1; //InterfaceMethod scala/collection/Iterator.hasNext:()Z
   126:	ifeq	155
   129:	aload	5
   131:	new	#133; //class scala/Tuple2
   134:	dup
   135:	aload_2
   136:	aload	7
   138:	invokeinterface	#71,  1; //InterfaceMethod scala/collection/Iterator.next:()Ljava/lang/Object;
   143:	invokespecial	#136; //Method scala/Tuple2."<init>":(Ljava/lang/Object;Ljava/lang/Object;)V
   146:	invokeinterface	#139,  2; //InterfaceMethod scala/collection/mutable/Builder.$plus$eq:(Ljava/lang/Object;)Lscala/collection/mutable/Builder;
   151:	pop
   152:	goto	119
   155:	aload	5
   157:	invokeinterface	#123,  1; //InterfaceMethod scala/collection/mutable/Builder.result:()Ljava/lang/Object;
   162:	areturn
  LineNumberTable: 
   line 250: 0
   line 251: 15
   line 252: 23
   line 253: 31
   line 254: 51
   line 255: 83
   line 256: 93
   line 257: 119
   line 258: 129
   line 259: 155

  LocalVariableTable: 
   Start  Length  Slot  Name   Signature
   0      163      0    $this       Lscala/collection/IterableLike;
   0      163      1    that       Lscala/collection/Iterable;
   0      163      2    thisElem       Ljava/lang/Object;
   0      163      3    thatElem       Ljava/lang/Object;
   0      163      4    bf       Lscala/collection/generic/CanBuildFrom;
   15      147      5    b       Lscala/collection/mutable/Builder;
   23      139      6    these       Lscala/collection/Iterator;
   31      131      7    those       Lscala/collection/Iterator;


public static java.lang.Object zip(scala.collection.IterableLike, scala.collection.Iterable, scala.collection.generic.CanBuildFrom);
  Code:
   Stack=5, Locals=6, Args_size=3
   0:	aload_2
   1:	aload_0
   2:	invokeinterface	#98,  1; //InterfaceMethod scala/collection/TraversableLike.repr:()Ljava/lang/Object;
   7:	invokeinterface	#104,  2; //InterfaceMethod scala/collection/generic/CanBuildFrom.apply:(Ljava/lang/Object;)Lscala/collection/mutable/Builder;
   12:	astore_3
   13:	aload_0
   14:	invokeinterface	#57,  1; //InterfaceMethod scala/collection/IterableLike.iterator:()Lscala/collection/Iterator;
   19:	astore	4
   21:	aload_1
   22:	invokeinterface	#57,  1; //InterfaceMethod scala/collection/IterableLike.iterator:()Lscala/collection/Iterator;
   27:	astore	5
   29:	aload	4
   31:	invokeinterface	#68,  1; //InterfaceMethod scala/collection/Iterator.hasNext:()Z
   36:	ifeq	80
   39:	aload	5
   41:	invokeinterface	#68,  1; //InterfaceMethod scala/collection/Iterator.hasNext:()Z
   46:	ifeq	80
   49:	aload_3
   50:	new	#133; //class scala/Tuple2
   53:	dup
   54:	aload	4
   56:	invokeinterface	#71,  1; //InterfaceMethod scala/collection/Iterator.next:()Ljava/lang/Object;
   61:	aload	5
   63:	invokeinterface	#71,  1; //InterfaceMethod scala/collection/Iterator.next:()Ljava/lang/Object;
   68:	invokespecial	#136; //Method scala/Tuple2."<init>":(Ljava/lang/Object;Ljava/lang/Object;)V
   71:	invokeinterface	#139,  2; //InterfaceMethod scala/collection/mutable/Builder.$plus$eq:(Ljava/lang/Object;)Lscala/collection/mutable/Builder;
   76:	pop
   77:	goto	29
   80:	aload_3
   81:	invokeinterface	#123,  1; //InterfaceMethod scala/collection/mutable/Builder.result:()Ljava/lang/Object;
   86:	areturn
  LineNumberTable: 
   line 213: 0
   line 214: 13
   line 215: 21
   line 216: 29
   line 217: 49
   line 218: 80

  LocalVariableTable: 
   Start  Length  Slot  Name   Signature
   0      87      0    $this       Lscala/collection/IterableLike;
   0      87      1    that       Lscala/collection/Iterable;
   0      87      2    bf       Lscala/collection/generic/CanBuildFrom;
   13      73      3    b       Lscala/collection/mutable/Builder;
   21      65      4    these       Lscala/collection/Iterator;
   29      57      5    those       Lscala/collection/Iterator;


public static void copyToArray(scala.collection.IterableLike, java.lang.Object, int, int);
  Code:
   Stack=3, Locals=9, Args_size=4
   0:	iload_2
   1:	istore	8
   3:	iload_2
   4:	iload_3
   5:	iadd
   6:	istore	4
   8:	new	#148; //class scala/runtime/RichInt
   11:	dup
   12:	iload	4
   14:	invokespecial	#149; //Method scala/runtime/RichInt."<init>":(I)V
   17:	aload_1
   18:	invokestatic	#155; //Method java/lang/reflect/Array.getLength:(Ljava/lang/Object;)I
   21:	invokevirtual	#159; //Method scala/runtime/RichInt.min:(I)I
   24:	istore	5
   26:	aload_0
   27:	invokeinterface	#57,  1; //InterfaceMethod scala/collection/IterableLike.iterator:()Lscala/collection/Iterator;
   32:	astore	6
   34:	iload	8
   36:	iload	5
   38:	if_icmpge	77
   41:	aload	6
   43:	invokeinterface	#68,  1; //InterfaceMethod scala/collection/Iterator.hasNext:()Z
   48:	ifeq	77
   51:	aload	6
   53:	invokeinterface	#71,  1; //InterfaceMethod scala/collection/Iterator.next:()Ljava/lang/Object;
   58:	astore	7
   60:	aload_1
   61:	iload	8
   63:	aload	7
   65:	invokestatic	#163; //Method java/lang/reflect/Array.set:(Ljava/lang/Object;ILjava/lang/Object;)V
   68:	iload	8
   70:	iconst_1
   71:	iadd
   72:	istore	8
   74:	goto	34
   77:	return
  LineNumberTable: 
   line 179: 0
   line 180: 3
   line 181: 26
   line 182: 34
   line 183: 51
   line 184: 68
   line 178: 77

  LocalVariableTable: 
   Start  Length  Slot  Name   Signature
   0      78      0    $this       Lscala/collection/IterableLike;
   0      78      1    xs       Ljava/lang/Object;
   0      78      2    start       I
   0      78      3    len       I
   26      52      5    end       I
   34      44      6    it       Lscala/collection/Iterator;
   3      75      8    i       I


public static java.lang.Object dropRight(scala.collection.IterableLike, int);
  Code:
   Stack=2, Locals=5, Args_size=2
   0:	aload_0
   1:	invokeinterface	#175,  1; //InterfaceMethod scala/collection/TraversableLike.newBuilder:()Lscala/collection/mutable/Builder;
   6:	astore_2
   7:	aload_0
   8:	invokeinterface	#57,  1; //InterfaceMethod scala/collection/IterableLike.iterator:()Lscala/collection/Iterator;
   13:	iload_1
   14:	invokeinterface	#179,  2; //InterfaceMethod scala/collection/Iterator.drop:(I)Lscala/collection/Iterator;
   19:	astore_3
   20:	aload_0
   21:	invokeinterface	#57,  1; //InterfaceMethod scala/collection/IterableLike.iterator:()Lscala/collection/Iterator;
   26:	astore	4
   28:	aload_3
   29:	invokeinterface	#68,  1; //InterfaceMethod scala/collection/Iterator.hasNext:()Z
   34:	ifeq	61
   37:	aload_2
   38:	aload	4
   40:	invokeinterface	#71,  1; //InterfaceMethod scala/collection/Iterator.next:()Ljava/lang/Object;
   45:	invokeinterface	#139,  2; //InterfaceMethod scala/collection/mutable/Builder.$plus$eq:(Ljava/lang/Object;)Lscala/collection/mutable/Builder;
   50:	pop
   51:	aload_3
   52:	invokeinterface	#71,  1; //InterfaceMethod scala/collection/Iterator.next:()Ljava/lang/Object;
   57:	pop
   58:	goto	28
   61:	aload_2
   62:	invokeinterface	#123,  1; //InterfaceMethod scala/collection/mutable/Builder.result:()Ljava/lang/Object;
   67:	areturn
  LineNumberTable: 
   line 168: 0
   line 169: 7
   line 170: 20
   line 171: 28
   line 172: 37
   line 173: 51
   line 175: 61

  LocalVariableTable: 
   Start  Length  Slot  Name   Signature
   0      68      0    $this       Lscala/collection/IterableLike;
   0      68      1    n       I
   7      60      2    b       Lscala/collection/mutable/Builder;
   20      47      3    lead       Lscala/collection/Iterator;
   28      39      4    it       Lscala/collection/Iterator;


public static java.lang.Object takeRight(scala.collection.IterableLike, int);
  Code:
   Stack=7, Locals=5, Args_size=2
   0:	aload_0
   1:	invokeinterface	#175,  1; //InterfaceMethod scala/collection/TraversableLike.newBuilder:()Lscala/collection/mutable/Builder;
   6:	astore_2
   7:	aload_0
   8:	invokeinterface	#57,  1; //InterfaceMethod scala/collection/IterableLike.iterator:()Lscala/collection/Iterator;
   13:	iload_1
   14:	invokeinterface	#179,  2; //InterfaceMethod scala/collection/Iterator.drop:(I)Lscala/collection/Iterator;
   19:	astore_3
   20:	new	#184; //class scala/runtime/BooleanRef
   23:	dup
   24:	iconst_0
   25:	invokespecial	#187; //Method scala/runtime/BooleanRef."<init>":(Z)V
   28:	astore	4
   30:	aload_0
   31:	new	#189; //class scala/collection/IterableLike$$anonfun$takeRight$1
   34:	dup
   35:	aload_0
   36:	aload_2
   37:	aload_3
   38:	aload	4
   40:	invokespecial	#192; //Method scala/collection/IterableLike$$anonfun$takeRight$1."<init>":(Lscala/collection/IterableLike;Lscala/collection/mutable/Builder;Lscala/collection/Iterator;Lscala/runtime/BooleanRef;)V
   43:	invokeinterface	#118,  2; //InterfaceMethod scala/collection/IterableLike.foreach:(Lscala/Function1;)V
   48:	aload_2
   49:	invokeinterface	#123,  1; //InterfaceMethod scala/collection/mutable/Builder.result:()Ljava/lang/Object;
   54:	areturn
  LineNumberTable: 
   line 149: 0
   line 150: 7
   line 151: 20
   line 152: 30
   line 157: 48

  LocalVariableTable: 
   Start  Length  Slot  Name   Signature
   0      55      0    $this       Lscala/collection/IterableLike;
   0      55      1    n       I
   7      47      2    b$1       Lscala/collection/mutable/Builder;
   20      34      3    lead$1       Lscala/collection/Iterator;
   30      24      4    go$1       Lscala/runtime/BooleanRef;


public static java.lang.Object takeWhile(scala.collection.IterableLike, scala.Function1);
  Code:
   Stack=2, Locals=5, Args_size=2
   0:	aload_0
   1:	invokeinterface	#175,  1; //InterfaceMethod scala/collection/TraversableLike.newBuilder:()Lscala/collection/mutable/Builder;
   6:	astore_2
   7:	aload_0
   8:	invokeinterface	#57,  1; //InterfaceMethod scala/collection/IterableLike.iterator:()Lscala/collection/Iterator;
   13:	astore_3
   14:	aload_3
   15:	invokeinterface	#68,  1; //InterfaceMethod scala/collection/Iterator.hasNext:()Z
   20:	ifeq	64
   23:	aload_3
   24:	invokeinterface	#71,  1; //InterfaceMethod scala/collection/Iterator.next:()Ljava/lang/Object;
   29:	astore	4
   31:	aload_1
   32:	aload	4
   34:	invokeinterface	#203,  2; //InterfaceMethod scala/Function1.apply:(Ljava/lang/Object;)Ljava/lang/Object;
   39:	invokestatic	#206; //Method scala/runtime/BoxesRunTime.unboxToBoolean:(Ljava/lang/Object;)Z
   42:	ifeq	57
   45:	aload_2
   46:	aload	4
   48:	invokeinterface	#139,  2; //InterfaceMethod scala/collection/mutable/Builder.$plus$eq:(Ljava/lang/Object;)Lscala/collection/mutable/Builder;
   53:	pop
   54:	goto	14
   57:	aload_2
   58:	invokeinterface	#123,  1; //InterfaceMethod scala/collection/mutable/Builder.result:()Ljava/lang/Object;
   63:	areturn
   64:	aload_2
   65:	invokeinterface	#123,  1; //InterfaceMethod scala/collection/mutable/Builder.result:()Ljava/lang/Object;
   70:	areturn
  LineNumberTable: 
   line 131: 0
   line 132: 7
   line 133: 14
   line 134: 23
   line 135: 31
   line 136: 45
   line 135: 57
   line 138: 64

  LocalVariableTable: 
   Start  Length  Slot  Name   Signature
   0      71      0    $this       Lscala/collection/IterableLike;
   0      71      1    p       Lscala/Function1;
   7      63      2    b       Lscala/collection/mutable/Builder;
   14      56      3    it       Lscala/collection/Iterator;
   31      23      4    x       Ljava/lang/Object;
   57      7      4    x       Ljava/lang/Object;


public static java.lang.Object slice(scala.collection.IterableLike, int, int);
  Code:
   Stack=2, Locals=6, Args_size=3
   0:	aload_0
   1:	invokeinterface	#175,  1; //InterfaceMethod scala/collection/TraversableLike.newBuilder:()Lscala/collection/mutable/Builder;
   6:	astore_3
   7:	iload_1
   8:	istore	4
   10:	aload_0
   11:	invokeinterface	#57,  1; //InterfaceMethod scala/collection/IterableLike.iterator:()Lscala/collection/Iterator;
   16:	iload_1
   17:	invokeinterface	#179,  2; //InterfaceMethod scala/collection/Iterator.drop:(I)Lscala/collection/Iterator;
   22:	astore	5
   24:	iload	4
   26:	iload_2
   27:	if_icmpge	63
   30:	aload	5
   32:	invokeinterface	#68,  1; //InterfaceMethod scala/collection/Iterator.hasNext:()Z
   37:	ifeq	63
   40:	aload_3
   41:	aload	5
   43:	invokeinterface	#71,  1; //InterfaceMethod scala/collection/Iterator.next:()Ljava/lang/Object;
   48:	invokeinterface	#139,  2; //InterfaceMethod scala/collection/mutable/Builder.$plus$eq:(Ljava/lang/Object;)Lscala/collection/mutable/Builder;
   53:	pop
   54:	iload	4
   56:	iconst_1
   57:	iadd
   58:	istore	4
   60:	goto	24
   63:	aload_3
   64:	invokeinterface	#123,  1; //InterfaceMethod scala/collection/mutable/Builder.result:()Ljava/lang/Object;
   69:	areturn
  LineNumberTable: 
   line 120: 0
   line 121: 7
   line 122: 10
   line 123: 24
   line 124: 40
   line 125: 54
   line 127: 63

  LocalVariableTable: 
   Start  Length  Slot  Name   Signature
   0      70      0    $this       Lscala/collection/IterableLike;
   0      70      1    from       I
   0      70      2    until       I
   7      62      3    b       Lscala/collection/mutable/Builder;
   10      59      4    i       I
   24      45      5    it       Lscala/collection/Iterator;


public static java.lang.Object take(scala.collection.IterableLike, int);
  Code:
   Stack=2, Locals=5, Args_size=2
   0:	aload_0
   1:	invokeinterface	#175,  1; //InterfaceMethod scala/collection/TraversableLike.newBuilder:()Lscala/collection/mutable/Builder;
   6:	astore_2
   7:	iconst_0
   8:	istore_3
   9:	aload_0
   10:	invokeinterface	#57,  1; //InterfaceMethod scala/collection/IterableLike.iterator:()Lscala/collection/Iterator;
   15:	astore	4
   17:	iload_3
   18:	iload_1
   19:	if_icmpge	53
   22:	aload	4
   24:	invokeinterface	#68,  1; //InterfaceMethod scala/collection/Iterator.hasNext:()Z
   29:	ifeq	53
   32:	aload_2
   33:	aload	4
   35:	invokeinterface	#71,  1; //InterfaceMethod scala/collection/Iterator.next:()Ljava/lang/Object;
   40:	invokeinterface	#139,  2; //InterfaceMethod scala/collection/mutable/Builder.$plus$eq:(Ljava/lang/Object;)Lscala/collection/mutable/Builder;
   45:	pop
   46:	iload_3
   47:	iconst_1
   48:	iadd
   49:	istore_3
   50:	goto	17
   53:	aload_2
   54:	invokeinterface	#123,  1; //InterfaceMethod scala/collection/mutable/Builder.result:()Ljava/lang/Object;
   59:	areturn
  LineNumberTable: 
   line 109: 0
   line 110: 7
   line 111: 9
   line 112: 17
   line 113: 32
   line 114: 46
   line 116: 53

  LocalVariableTable: 
   Start  Length  Slot  Name   Signature
   0      60      0    $this       Lscala/collection/IterableLike;
   0      60      1    n       I
   7      52      2    b       Lscala/collection/mutable/Builder;
   9      50      3    i       I
   17      42      4    it       Lscala/collection/Iterator;


public static java.lang.Object head(scala.collection.IterableLike);
  Code:
   Stack=2, Locals=1, Args_size=1
   0:	aload_0
   1:	invokeinterface	#214,  1; //InterfaceMethod scala/collection/IterableLike.isEmpty:()Z
   6:	ifeq	17
   9:	new	#216; //class java/util/NoSuchElementException
   12:	dup
   13:	invokespecial	#219; //Method java/util/NoSuchElementException."<init>":()V
   16:	athrow
   17:	aload_0
   18:	invokeinterface	#57,  1; //InterfaceMethod scala/collection/IterableLike.iterator:()Lscala/collection/Iterator;
   23:	invokeinterface	#71,  1; //InterfaceMethod scala/collection/Iterator.next:()Ljava/lang/Object;
   28:	areturn
  LineNumberTable: 
   line 105: 0
   line 106: 17
   line 105: 28

  LocalVariableTable: 
   Start  Length  Slot  Name   Signature
   0      29      0    $this       Lscala/collection/IterableLike;


public static scala.collection.Iterable toIterable(scala.collection.IterableLike);
  Code:
   Stack=1, Locals=1, Args_size=1
   0:	aload_0
   1:	invokeinterface	#225,  1; //InterfaceMethod scala/collection/IterableLike.thisCollection:()Lscala/collection/Iterable;
   6:	areturn
  LineNumberTable: 
   line 102: 0

  LocalVariableTable: 
   Start  Length  Slot  Name   Signature
   0      7      0    $this       Lscala/collection/IterableLike;


public static java.lang.Object reduceRight(scala.collection.IterableLike, scala.Function2);
  Code:
   Stack=2, Locals=2, Args_size=2
   0:	aload_0
   1:	invokeinterface	#57,  1; //InterfaceMethod scala/collection/IterableLike.iterator:()Lscala/collection/Iterator;
   6:	aload_1
   7:	invokeinterface	#230,  2; //InterfaceMethod scala/collection/Iterator.reduceRight:(Lscala/Function2;)Ljava/lang/Object;
   12:	areturn
  LineNumberTable: 
   line 100: 0

  LocalVariableTable: 
   Start  Length  Slot  Name   Signature
   0      13      0    $this       Lscala/collection/IterableLike;
   0      13      1    op       Lscala/Function2;


public static java.lang.Object foldRight(scala.collection.IterableLike, java.lang.Object, scala.Function2);
  Code:
   Stack=3, Locals=3, Args_size=3
   0:	aload_0
   1:	invokeinterface	#57,  1; //InterfaceMethod scala/collection/IterableLike.iterator:()Lscala/collection/Iterator;
   6:	aload_1
   7:	aload_2
   8:	invokeinterface	#237,  3; //InterfaceMethod scala/collection/Iterator.foldRight:(Ljava/lang/Object;Lscala/Function2;)Ljava/lang/Object;
   13:	areturn
  LineNumberTable: 
   line 98: 0

  LocalVariableTable: 
   Start  Length  Slot  Name   Signature
   0      14      0    $this       Lscala/collection/IterableLike;
   0      14      1    z       Ljava/lang/Object;
   0      14      2    op       Lscala/Function2;


public static boolean isEmpty(scala.collection.IterableLike);
  Code:
   Stack=1, Locals=1, Args_size=1
   0:	aload_0
   1:	invokeinterface	#57,  1; //InterfaceMethod scala/collection/IterableLike.iterator:()Lscala/collection/Iterator;
   6:	invokeinterface	#68,  1; //InterfaceMethod scala/collection/Iterator.hasNext:()Z
   11:	ifeq	18
   14:	iconst_0
   15:	goto	19
   18:	iconst_1
   19:	ireturn
  LineNumberTable: 
   line 96: 0

  LocalVariableTable: 
   Start  Length  Slot  Name   Signature
   0      20      0    $this       Lscala/collection/IterableLike;


public static scala.Option find(scala.collection.IterableLike, scala.Function1);
  Code:
   Stack=2, Locals=2, Args_size=2
   0:	aload_0
   1:	invokeinterface	#57,  1; //InterfaceMethod scala/collection/IterableLike.iterator:()Lscala/collection/Iterator;
   6:	aload_1
   7:	invokeinterface	#244,  2; //InterfaceMethod scala/collection/Iterator.find:(Lscala/Function1;)Lscala/Option;
   12:	areturn
  LineNumberTable: 
   line 90: 0

  LocalVariableTable: 
   Start  Length  Slot  Name   Signature
   0      13      0    $this       Lscala/collection/IterableLike;
   0      13      1    p       Lscala/Function1;


public static boolean exists(scala.collection.IterableLike, scala.Function1);
  Code:
   Stack=2, Locals=2, Args_size=2
   0:	aload_0
   1:	invokeinterface	#57,  1; //InterfaceMethod scala/collection/IterableLike.iterator:()Lscala/collection/Iterator;
   6:	aload_1
   7:	invokeinterface	#249,  2; //InterfaceMethod scala/collection/Iterator.exists:(Lscala/Function1;)Z
   12:	ireturn
  LineNumberTable: 
   line 88: 0

  LocalVariableTable: 
   Start  Length  Slot  Name   Signature
   0      13      0    $this       Lscala/collection/IterableLike;
   0      13      1    p       Lscala/Function1;


public static boolean forall(scala.collection.IterableLike, scala.Function1);
  Code:
   Stack=2, Locals=2, Args_size=2
   0:	aload_0
   1:	invokeinterface	#57,  1; //InterfaceMethod scala/collection/IterableLike.iterator:()Lscala/collection/Iterator;
   6:	aload_1
   7:	invokeinterface	#252,  2; //InterfaceMethod scala/collection/Iterator.forall:(Lscala/Function1;)Z
   12:	ireturn
  LineNumberTable: 
   line 86: 0

  LocalVariableTable: 
   Start  Length  Slot  Name   Signature
   0      13      0    $this       Lscala/collection/IterableLike;
   0      13      1    p       Lscala/Function1;


public static void foreach(scala.collection.IterableLike, scala.Function1);
  Code:
   Stack=2, Locals=2, Args_size=2
   0:	aload_0
   1:	invokeinterface	#57,  1; //InterfaceMethod scala/collection/IterableLike.iterator:()Lscala/collection/Iterator;
   6:	aload_1
   7:	invokeinterface	#254,  2; //InterfaceMethod scala/collection/Iterator.foreach:(Lscala/Function1;)V
   12:	return
  LineNumberTable: 
   line 83: 0

  LocalVariableTable: 
   Start  Length  Slot  Name   Signature
   0      13      0    $this       Lscala/collection/IterableLike;
   0      13      1    f       Lscala/Function1;


public static scala.collection.Iterator elements(scala.collection.IterableLike);
  Code:
   Stack=1, Locals=1, Args_size=1
   0:	aload_0
   1:	invokeinterface	#57,  1; //InterfaceMethod scala/collection/IterableLike.iterator:()Lscala/collection/Iterator;
   6:	areturn
  LineNumberTable: 
   line 73: 0

  LocalVariableTable: 
   Start  Length  Slot  Name   Signature
   0      7      0    $this       Lscala/collection/IterableLike;

  Deprecated: true

public static scala.collection.Iterable toCollection(scala.collection.IterableLike, java.lang.Object);
  Code:
   Stack=1, Locals=2, Args_size=2
   0:	aload_1
   1:	checkcast	#261; //class scala/collection/Iterable
   4:	areturn
  LineNumberTable: 
   line 63: 0

  LocalVariableTable: 
   Start  Length  Slot  Name   Signature
   0      5      0    $this       Lscala/collection/IterableLike;
   0      5      1    repr       Ljava/lang/Object;


public static scala.collection.Iterable thisCollection(scala.collection.IterableLike);
  Code:
   Stack=1, Locals=1, Args_size=1
   0:	aload_0
   1:	checkcast	#261; //class scala/collection/Iterable
   4:	areturn
  LineNumberTable: 
   line 62: 0

  LocalVariableTable: 
   Start  Length  Slot  Name   Signature
   0      5      0    $this       Lscala/collection/IterableLike;


}

