Compiled from "Iterator.scala"
public final class scala.collection.Iterator$GroupedIterator$$anonfun$padding$1 extends java.lang.Object implements scala.Function0,scala.ScalaObject,java.io.Serializable
  SourceFile: "Iterator.scala"
  Scala: length = 0x
   
  InnerClass: 
   public GroupedIterator=class scala/collection/Iterator$GroupedIterator of class scala/collection/Iterator
   public final $anonfun$padding$1=class scala/collection/Iterator$GroupedIterator$$anonfun$padding$1 of class scala/collection/Iterator$GroupedIterator
  minor version: 0
  major version: 49
  Constant pool:
Asciz	SourceFile;
Asciz	Iterator.scala;
Asciz	<clinit>;
Asciz	()V;
Asciz	Code;
Asciz	serialVersionUID;
Asciz	J;
Asciz	scala/collection/Iterator$GroupedIterator$$anonfun$padding$1;
class	scala/collection/Iterator$GroupedIterator$$anonfun$padding$1
NameAndType	serialVersionUID:J
Field	scala/collection/Iterator$GroupedIterator$$anonfun$padding$1.serialVersionUID:J
Asciz	$outer;
Asciz	Lscala/collection/Iterator$GroupedIterator;;
Asciz	<init>;
Asciz	(Lscala/collection/Iterator$GroupedIterator;)V;
Asciz	LineNumberTable;
Asciz	java/lang/NullPointerException;
class	java/lang/NullPointerException
NameAndType	"<init>":()V
Method	java/lang/NullPointerException."<init>":()V
NameAndType	$outer:Lscala/collection/Iterator$GroupedIterator;
Field	scala/collection/Iterator$GroupedIterator$$anonfun$padding$1.$outer:Lscala/collection/Iterator$GroupedIterator;
Asciz	java/lang/Object;
class	java/lang/Object
Method	java/lang/Object."<init>":()V
Asciz	scala/Function0$class;
class	scala/Function0$class
Asciz	$init$;
Asciz	(Lscala/Function0;)V;
NameAndType	$init$:(Lscala/Function0;)V
Method	scala/Function0$class.$init$:(Lscala/Function0;)V
Asciz	this;
Asciz	Lscala/collection/Iterator$GroupedIterator$$anonfun$padding$1;;
Asciz	LocalVariableTable;
Asciz	(Lscala/collection/Iterator<TA;>.GroupedIterator<TB;>;)V;
Asciz	Signature;
Asciz	apply;
Asciz	()Ljava/lang/Object;;
Asciz	scala/collection/Iterator$GroupedIterator;
class	scala/collection/Iterator$GroupedIterator
Asciz	scala$collection$Iterator$GroupedIterator$$pad;
Asciz	Lscala/Option;;
NameAndType	scala$collection$Iterator$GroupedIterator$$pad:Lscala/Option;
Field	scala/collection/Iterator$GroupedIterator.scala$collection$Iterator$GroupedIterator$$pad:Lscala/Option;
Asciz	scala/Option;
class	scala/Option
Asciz	get;
NameAndType	get:()Ljava/lang/Object;
Method	scala/Option.get:()Ljava/lang/Object;
Asciz	scala/Function0;
class	scala/Function0
NameAndType	apply:()Ljava/lang/Object;
InterfaceMethod	scala/Function0.apply:()Ljava/lang/Object;
Asciz	()TB;;
Asciz	toString;
Asciz	()Ljava/lang/String;;
Asciz	(Lscala/Function0;)Ljava/lang/String;;
NameAndType	toString:(Lscala/Function0;)Ljava/lang/String;
Method	scala/Function0$class.toString:(Lscala/Function0;)Ljava/lang/String;
Asciz	Scala;
Asciz	InnerClasses;
Asciz	scala/collection/Iterator;
class	scala/collection/Iterator
Asciz	GroupedIterator;
Asciz	$anonfun$padding$1;
Asciz	scala/ScalaObject;
class	scala/ScalaObject
Asciz	java/io/Serializable;
class	java/io/Serializable

{
public static final long serialVersionUID;
  Signature: J

private final scala.collection.Iterator$GroupedIterator $outer;
  Signature: Lscala/collection/Iterator$GroupedIterator;

public static {};
  Signature: ()V
  Code:
   Stack=2, Locals=0, Args_size=0
	lconst_0
	putstatic	Field serialVersionUID:J
	return
  Labels:

public scala.collection.Iterator$GroupedIterator$$anonfun$padding$1(scala.collection.Iterator$GroupedIterator);
  Signature: (Lscala/collection/Iterator$GroupedIterator;)V
  Code:
   Stack=2, Locals=2, Args_size=2
	aload_1
	ifnonnull	l1 // aload_0
	new	class java/lang/NullPointerException
	dup
	invokespecial	Method java/lang/NullPointerException."<init>":()V
	athrow
l1	aload_0
	aload_1
	putfield	Field $outer:Lscala/collection/Iterator$GroupedIterator;
	aload_0
	invokespecial	Method java/lang/Object."<init>":()V
	aload_0
	invokestatic	Method scala/Function0$class.$init$:(Lscala/Function0;)V
	return
  Labels:
   	l1 = 12 // aload_0
  LocalVariableTable: 
   Start  Length  Slot  Name   Signature
   0      26      0    this       Lscala/collection/Iterator$GroupedIterator$$anonfun$padding$1;
   0      26      1    $outer       Lscala/collection/Iterator$GroupedIterator;

  Signature: length = 0x2
   00 23 

public final java.lang.Object apply();
  Signature: ()Ljava/lang/Object;
  Code:
   Stack=1, Locals=2, Args_size=1
	aload_0
	getfield	Field $outer:Lscala/collection/Iterator$GroupedIterator;
	astore_1
	aload_0
	getfield	Field $outer:Lscala/collection/Iterator$GroupedIterator;
	getfield	Field scala/collection/Iterator$GroupedIterator.scala$collection$Iterator$GroupedIterator$$pad:Lscala/Option;
	invokevirtual	Method scala/Option.get:()Ljava/lang/Object;
	checkcast	class scala/Function0
	invokeinterface	InterfaceMethod scala/Function0.apply:()Ljava/lang/Object;
	areturn
  Labels:
  LocalVariableTable: 
   Start  Length  Slot  Name   Signature
   0      24      0    this       Lscala/collection/Iterator$GroupedIterator$$anonfun$padding$1;

  Signature: length = 0x2
   00 36 

public java.lang.String toString();
  Signature: ()Ljava/lang/String;
  Code:
   Stack=1, Locals=1, Args_size=1
	aload_0
	invokestatic	Method scala/Function0$class.toString:(Lscala/Function0;)Ljava/lang/String;
	areturn
  Labels:

}

