Compiled from "JavaConversions.scala"
public class scala.collection.JavaConversions$IteratorWrapper extends java.lang.Object implements java.util.Iterator,java.util.Enumeration,scala.ScalaObject,scala.Product,java.io.Serializable
  SourceFile: "JavaConversions.scala"
  Signature: length = 0x2
   00 79 
  Scala: length = 0x
   
  InnerClass: 
   public IteratorWrapper=class scala/collection/JavaConversions$IteratorWrapper of class scala/collection/JavaConversions
  minor version: 0
  major version: 49
  Constant pool:
Asciz	SourceFile;
Asciz	JavaConversions.scala;
Asciz	underlying;
Asciz	Lscala/collection/Iterator;;
Asciz	Lscala/collection/Iterator<TA;>;;
Asciz	Signature;
Asciz	<init>;
Asciz	(Lscala/collection/Iterator;)V;
Asciz	Code;
Asciz	LineNumberTable;
Asciz	scala/collection/JavaConversions$IteratorWrapper;
class	scala/collection/JavaConversions$IteratorWrapper
NameAndType	underlying:Lscala/collection/Iterator;
Field	scala/collection/JavaConversions$IteratorWrapper.underlying:Lscala/collection/Iterator;
Asciz	java/lang/Object;
class	java/lang/Object
Asciz	()V;
NameAndType	"<init>":()V
Method	java/lang/Object."<init>":()V
Asciz	scala/Product$class;
class	scala/Product$class
Asciz	$init$;
Asciz	(Lscala/Product;)V;
NameAndType	$init$:(Lscala/Product;)V
Method	scala/Product$class.$init$:(Lscala/Product;)V
Asciz	this;
Asciz	Lscala/collection/JavaConversions$IteratorWrapper;;
Asciz	LocalVariableTable;
Asciz	(Lscala/collection/Iterator<TA;>;)V;
Asciz	gd1$1;
Asciz	(Lscala/collection/Iterator;)Z;
Asciz	()Lscala/collection/Iterator;;
NameAndType	underlying:()Lscala/collection/Iterator;
Method	scala/collection/JavaConversions$IteratorWrapper.underlying:()Lscala/collection/Iterator;
Asciz	equals;
Asciz	(Ljava/lang/Object;)Z;
NameAndType	equals:(Ljava/lang/Object;)Z
Method	java/lang/Object.equals:(Ljava/lang/Object;)Z
Asciz	remove;
Asciz	()Lscala/runtime/Nothing$;;
NameAndType	remove:()Lscala/runtime/Nothing$;
Method	scala/collection/JavaConversions$IteratorWrapper.remove:()Lscala/runtime/Nothing$;
Asciz	canEqual;
Asciz	productElement;
Asciz	(I)Ljava/lang/Object;;
Asciz	scala/MatchError;
class	scala/MatchError
Asciz	scala/runtime/BoxesRunTime;
class	scala/runtime/BoxesRunTime
Asciz	boxToInteger;
Asciz	(I)Ljava/lang/Integer;;
NameAndType	boxToInteger:(I)Ljava/lang/Integer;
Method	scala/runtime/BoxesRunTime.boxToInteger:(I)Ljava/lang/Integer;
Asciz	toString;
Asciz	()Ljava/lang/String;;
NameAndType	toString:()Ljava/lang/String;
Method	java/lang/Object.toString:()Ljava/lang/String;
Asciz	(Ljava/lang/String;)V;
NameAndType	"<init>":(Ljava/lang/String;)V
Method	scala/MatchError."<init>":(Ljava/lang/String;)V
Asciz	java/lang/IndexOutOfBoundsException;
class	java/lang/IndexOutOfBoundsException
Method	java/lang/IndexOutOfBoundsException."<init>":(Ljava/lang/String;)V
Asciz	productArity;
Asciz	()I;
Asciz	productPrefix;
Asciz	IteratorWrapper;
String	IteratorWrapper
NameAndType	gd1$1:(Lscala/collection/Iterator;)Z
Method	scala/collection/JavaConversions$IteratorWrapper.gd1$1:(Lscala/collection/Iterator;)Z
Asciz	scala/Equals;
class	scala/Equals
NameAndType	canEqual:(Ljava/lang/Object;)Z
InterfaceMethod	scala/Equals.canEqual:(Ljava/lang/Object;)Z
Asciz	temp44;
Asciz	temp45;
Asciz	scala/runtime/ScalaRunTime$;
class	scala/runtime/ScalaRunTime$
Asciz	MODULE$;
Asciz	Lscala/runtime/ScalaRunTime$;;
NameAndType	MODULE$:Lscala/runtime/ScalaRunTime$;
Field	scala/runtime/ScalaRunTime$.MODULE$:Lscala/runtime/ScalaRunTime$;
Asciz	_toString;
Asciz	(Lscala/Product;)Ljava/lang/String;;
NameAndType	_toString:(Lscala/Product;)Ljava/lang/String;
Method	scala/runtime/ScalaRunTime$._toString:(Lscala/Product;)Ljava/lang/String;
Asciz	hashCode;
Asciz	_hashCode;
Asciz	(Lscala/Product;)I;
NameAndType	_hashCode:(Lscala/Product;)I
Method	scala/runtime/ScalaRunTime$._hashCode:(Lscala/Product;)I
Asciz	copy;
Asciz	(Lscala/collection/Iterator;)Lscala/collection/JavaConversions$IteratorWrapper;;
NameAndType	"<init>":(Lscala/collection/Iterator;)V
Method	scala/collection/JavaConversions$IteratorWrapper."<init>":(Lscala/collection/Iterator;)V
Asciz	java/lang/UnsupportedOperationException;
class	java/lang/UnsupportedOperationException
Method	java/lang/UnsupportedOperationException."<init>":()V
Asciz	nextElement;
Asciz	()Ljava/lang/Object;;
Asciz	scala/collection/Iterator;
class	scala/collection/Iterator
Asciz	next;
NameAndType	next:()Ljava/lang/Object;
InterfaceMethod	scala/collection/Iterator.next:()Ljava/lang/Object;
Asciz	()TA;;
Asciz	hasMoreElements;
Asciz	()Z;
Asciz	hasNext;
NameAndType	hasNext:()Z
InterfaceMethod	scala/collection/Iterator.hasNext:()Z
Asciz	()Lscala/collection/Iterator<TA;>;;
Asciz	copy$default$1;
Asciz	productElements;
Asciz	(Lscala/Product;)Lscala/collection/Iterator;;
NameAndType	productElements:(Lscala/Product;)Lscala/collection/Iterator;
Method	scala/Product$class.productElements:(Lscala/Product;)Lscala/collection/Iterator;
Asciz	productIterator;
NameAndType	productIterator:(Lscala/Product;)Lscala/collection/Iterator;
Method	scala/Product$class.productIterator:(Lscala/Product;)Lscala/collection/Iterator;
Asciz	<A:Ljava/lang/Object;>Ljava/lang/Object;Ljava/util/Iterator<TA;>;Ljava/util/Enumeration<TA;>;Lscala/ScalaObject;Lscala/Product;;
Asciz	Scala;
Asciz	InnerClasses;
Asciz	scala/collection/JavaConversions;
class	scala/collection/JavaConversions
Asciz	java/util/Iterator;
class	java/util/Iterator
Asciz	java/util/Enumeration;
class	java/util/Enumeration
Asciz	scala/ScalaObject;
class	scala/ScalaObject
Asciz	scala/Product;
class	scala/Product
Asciz	java/io/Serializable;
class	java/io/Serializable

{
private final scala.collection.Iterator underlying;
  Signature: Lscala/collection/Iterator;
  Signature: length = 0x2
   00 05 

public scala.collection.JavaConversions$IteratorWrapper(scala.collection.Iterator);
  Signature: (Lscala/collection/Iterator;)V
  Code:
   Stack=2, Locals=2, Args_size=2
	aload_0
	aload_1
	putfield	Field underlying:Lscala/collection/Iterator;
	aload_0
	invokespecial	Method java/lang/Object."<init>":()V
	aload_0
	invokestatic	Method scala/Product$class.$init$:(Lscala/Product;)V
	return
  Labels:
  LocalVariableTable: 
   Start  Length  Slot  Name   Signature
   0      14      0    this       Lscala/collection/JavaConversions$IteratorWrapper;
   0      14      1    underlying       Lscala/collection/Iterator;

  Signature: length = 0x2
   00 1D 

private final boolean gd1$1(scala.collection.Iterator);
  Signature: (Lscala/collection/Iterator;)Z
  Code:
   Stack=2, Locals=3, Args_size=2
	aload_1
	aload_0
	invokevirtual	Method underlying:()Lscala/collection/Iterator;
	astore_2
	dup
	ifnonnull	l1 // aload_2
	pop
	aload_2
	ifnull	l2 // iconst_1
	goto	l3 // iconst_0
l1	aload_2
	invokevirtual	Method java/lang/Object.equals:(Ljava/lang/Object;)Z
	ifeq	l3 // iconst_0
l2	iconst_1
	goto	l4 // ireturn
l3	iconst_0
l4	ireturn
  Labels:
   	l1 = 18 // aload_2
   	l2 = 25 // iconst_1
   	l3 = 29 // iconst_0
   	l4 = 30 // ireturn

public void remove();
  Signature: ()V
  Code:
   Stack=1, Locals=1, Args_size=1
	aload_0
	invokevirtual	Method remove:()Lscala/runtime/Nothing$;
	athrow
  Labels:

public boolean canEqual(java.lang.Object);
  Signature: (Ljava/lang/Object;)Z
  Code:
   Stack=1, Locals=2, Args_size=2
	aload_1
	instanceof	class scala/collection/JavaConversions$IteratorWrapper
	ireturn
  Labels:

public java.lang.Object productElement(int);
  Signature: (I)Ljava/lang/Object;
  Code:
   Stack=3, Locals=2, Args_size=2
	iload_1
	iconst_0
	if_icmpne	l1 // iconst_1
	iconst_1
	ifeq	l2 // new
	aload_0
	invokevirtual	Method underlying:()Lscala/collection/Iterator;
	areturn
l2	new	class scala/MatchError
	dup
	iload_1
	invokestatic	Method scala/runtime/BoxesRunTime.boxToInteger:(I)Ljava/lang/Integer;
	invokevirtual	Method java/lang/Object.toString:()Ljava/lang/String;
	invokespecial	Method scala/MatchError."<init>":(Ljava/lang/String;)V
	athrow
l1	iconst_1
	ifeq	l3 // new
	new	class java/lang/IndexOutOfBoundsException
	dup
	iload_1
	invokestatic	Method scala/runtime/BoxesRunTime.boxToInteger:(I)Ljava/lang/Integer;
	invokevirtual	Method java/lang/Object.toString:()Ljava/lang/String;
	invokespecial	Method java/lang/IndexOutOfBoundsException."<init>":(Ljava/lang/String;)V
	athrow
l3	new	class scala/MatchError
	dup
	iload_1
	invokestatic	Method scala/runtime/BoxesRunTime.boxToInteger:(I)Ljava/lang/Integer;
	invokevirtual	Method java/lang/Object.toString:()Ljava/lang/String;
	invokespecial	Method scala/MatchError."<init>":(Ljava/lang/String;)V
	athrow
  Labels:
   	l2 = 14 // new
   	l1 = 29 // iconst_1
   	l3 = 48 // new

public int productArity();
  Signature: ()I
  Code:
   Stack=1, Locals=1, Args_size=1
	iconst_1
	ireturn
  Labels:

public java.lang.String productPrefix();
  Signature: ()Ljava/lang/String;
  Code:
   Stack=1, Locals=1, Args_size=1
	ldc	String IteratorWrapper
	areturn
  Labels:

public boolean equals(java.lang.Object);
  Signature: (Ljava/lang/Object;)Z
  Code:
   Stack=3, Locals=4, Args_size=2
	aload_0
	aload_1
	if_acmpeq	l1 // iconst_1
	aload_1
	instanceof	class scala/collection/JavaConversions$IteratorWrapper
	ifeq	l2 // iconst_1
	aload_1
	checkcast	class scala/collection/JavaConversions$IteratorWrapper
	astore_2
	aload_2
	invokevirtual	Method underlying:()Lscala/collection/Iterator;
	astore_3
	aload_0
	aload_3
	invokespecial	Method gd1$1:(Lscala/collection/Iterator;)Z
	ifeq	l3 // iconst_1
	aload_1
	checkcast	class scala/collection/JavaConversions$IteratorWrapper
	aload_0
	invokeinterface	InterfaceMethod scala/Equals.canEqual:(Ljava/lang/Object;)Z
	goto	l4 // ifeq
l3	iconst_1
	ifeq	l5 // new
	iconst_0
	goto	l4 // ifeq
l5	new	class scala/MatchError
	dup
	aload_1
	invokevirtual	Method java/lang/Object.toString:()Ljava/lang/String;
	invokespecial	Method scala/MatchError."<init>":(Ljava/lang/String;)V
	athrow
l2	iconst_1
	ifeq	l6 // new
	iconst_0
l4	ifeq	l7 // iconst_0
l1	iconst_1
	goto	l8 // ireturn
l7	iconst_0
l8	ireturn
l6	new	class scala/MatchError
	dup
	aload_1
	invokevirtual	Method java/lang/Object.toString:()Ljava/lang/String;
	invokespecial	Method scala/MatchError."<init>":(Ljava/lang/String;)V
	athrow
  Labels:
   	l3 = 43 // iconst_1
   	l5 = 51 // new
   	l2 = 63 // iconst_1
   	l4 = 68 // ifeq
   	l1 = 71 // iconst_1
   	l7 = 75 // iconst_0
   	l8 = 76 // ireturn
   	l6 = 77 // new
  LocalVariableTable: 
   Start  Length  Slot  Name   Signature
   0      89      0    this       Lscala/collection/JavaConversions$IteratorWrapper;
   17      46      2    temp44       Lscala/collection/JavaConversions$IteratorWrapper;
   22      41      3    temp45       Lscala/collection/Iterator;


public java.lang.String toString();
  Signature: ()Ljava/lang/String;
  Code:
   Stack=2, Locals=1, Args_size=1
	getstatic	Field scala/runtime/ScalaRunTime$.MODULE$:Lscala/runtime/ScalaRunTime$;
	aload_0
	invokevirtual	Method scala/runtime/ScalaRunTime$._toString:(Lscala/Product;)Ljava/lang/String;
	areturn
  Labels:

public int hashCode();
  Signature: ()I
  Code:
   Stack=2, Locals=1, Args_size=1
	getstatic	Field scala/runtime/ScalaRunTime$.MODULE$:Lscala/runtime/ScalaRunTime$;
	aload_0
	invokevirtual	Method scala/runtime/ScalaRunTime$._hashCode:(Lscala/Product;)I
	ireturn
  Labels:

public scala.collection.JavaConversions$IteratorWrapper copy(scala.collection.Iterator);
  Signature: (Lscala/collection/Iterator;)Lscala/collection/JavaConversions$IteratorWrapper;
  Code:
   Stack=3, Locals=2, Args_size=2
	new	class scala/collection/JavaConversions$IteratorWrapper
	dup
	aload_1
	invokespecial	Method "<init>":(Lscala/collection/Iterator;)V
	areturn
  Labels:
  LocalVariableTable: 
   Start  Length  Slot  Name   Signature
   0      9      0    this       Lscala/collection/JavaConversions$IteratorWrapper;
   0      9      1    underlying       Lscala/collection/Iterator;


public scala.runtime.Nothing$ remove();
  Signature: ()Lscala/runtime/Nothing$;
  Code:
   Stack=2, Locals=1, Args_size=1
	new	class java/lang/UnsupportedOperationException
	dup
	invokespecial	Method java/lang/UnsupportedOperationException."<init>":()V
	athrow
  Labels:

public java.lang.Object nextElement();
  Signature: ()Ljava/lang/Object;
  Code:
   Stack=1, Locals=1, Args_size=1
	aload_0
	invokevirtual	Method underlying:()Lscala/collection/Iterator;
	invokeinterface	InterfaceMethod scala/collection/Iterator.next:()Ljava/lang/Object;
	areturn
  Labels:
  Signature: length = 0x2
   00 6A 

public boolean hasMoreElements();
  Signature: ()Z
  Code:
   Stack=1, Locals=1, Args_size=1
	aload_0
	invokevirtual	Method underlying:()Lscala/collection/Iterator;
	invokeinterface	InterfaceMethod scala/collection/Iterator.hasNext:()Z
	ireturn
  Labels:

public java.lang.Object next();
  Signature: ()Ljava/lang/Object;
  Code:
   Stack=1, Locals=1, Args_size=1
	aload_0
	invokevirtual	Method underlying:()Lscala/collection/Iterator;
	invokeinterface	InterfaceMethod scala/collection/Iterator.next:()Ljava/lang/Object;
	areturn
  Labels:
  Signature: length = 0x2
   00 6A 

public boolean hasNext();
  Signature: ()Z
  Code:
   Stack=1, Locals=1, Args_size=1
	aload_0
	invokevirtual	Method underlying:()Lscala/collection/Iterator;
	invokeinterface	InterfaceMethod scala/collection/Iterator.hasNext:()Z
	ireturn
  Labels:

public scala.collection.Iterator underlying();
  Signature: ()Lscala/collection/Iterator;
  Code:
   Stack=1, Locals=1, Args_size=1
	aload_0
	getfield	Field underlying:Lscala/collection/Iterator;
	areturn
  Labels:
  Signature: length = 0x2
   00 70 

public scala.collection.Iterator copy$default$1();
  Signature: ()Lscala/collection/Iterator;
  Code:
   Stack=1, Locals=1, Args_size=1
	aload_0
	invokevirtual	Method underlying:()Lscala/collection/Iterator;
	areturn
  Labels:

public scala.collection.Iterator productElements();
  Signature: ()Lscala/collection/Iterator;
  Code:
   Stack=1, Locals=1, Args_size=1
	aload_0
	invokestatic	Method scala/Product$class.productElements:(Lscala/Product;)Lscala/collection/Iterator;
	areturn
  Labels:

public scala.collection.Iterator productIterator();
  Signature: ()Lscala/collection/Iterator;
  Code:
   Stack=1, Locals=1, Args_size=1
	aload_0
	invokestatic	Method scala/Product$class.productIterator:(Lscala/Product;)Lscala/collection/Iterator;
	areturn
  Labels:

}

