Compiled from "JavaConversions.scala"
public class scala.collection.JavaConversions$MutableBufferWrapper extends java.util.AbstractList implements scala.ScalaObject,scala.Product,java.io.Serializable
  SourceFile: "JavaConversions.scala"
  Signature: length = 0x2
   00 76 
  Scala: length = 0x
   
  InnerClass: 
   public #60= #12 of #122; //MutableBufferWrapper=class scala/collection/JavaConversions$MutableBufferWrapper of class scala/collection/JavaConversions
  minor version: 0
  major version: 49
  Constant pool:
const #1 = Asciz	SourceFile;
const #2 = Asciz	JavaConversions.scala;
const #3 = Asciz	underlying;
const #4 = Asciz	Lscala/collection/mutable/Buffer;;
const #5 = Asciz	Lscala/collection/mutable/Buffer<TA;>;;
const #6 = Asciz	Signature;
const #7 = Asciz	<init>;
const #8 = Asciz	(Lscala/collection/mutable/Buffer;)V;
const #9 = Asciz	Code;
const #10 = Asciz	LineNumberTable;
const #11 = Asciz	scala/collection/JavaConversions$MutableBufferWrapper;
const #12 = class	#11;	//  scala/collection/JavaConversions$MutableBufferWrapper
const #13 = NameAndType	#3:#4;//  underlying:Lscala/collection/mutable/Buffer;
const #14 = Field	#12.#13;	//  scala/collection/JavaConversions$MutableBufferWrapper.underlying:Lscala/collection/mutable/Buffer;
const #15 = Asciz	java/util/AbstractList;
const #16 = class	#15;	//  java/util/AbstractList
const #17 = Asciz	()V;
const #18 = NameAndType	#7:#17;//  "<init>":()V
const #19 = Method	#16.#18;	//  java/util/AbstractList."<init>":()V
const #20 = Asciz	scala/Product$class;
const #21 = class	#20;	//  scala/Product$class
const #22 = Asciz	$init$;
const #23 = Asciz	(Lscala/Product;)V;
const #24 = NameAndType	#22:#23;//  $init$:(Lscala/Product;)V
const #25 = Method	#21.#24;	//  scala/Product$class.$init$:(Lscala/Product;)V
const #26 = Asciz	this;
const #27 = Asciz	Lscala/collection/JavaConversions$MutableBufferWrapper;;
const #28 = Asciz	LocalVariableTable;
const #29 = Asciz	(Lscala/collection/mutable/Buffer<TA;>;)V;
const #30 = Asciz	canEqual;
const #31 = Asciz	(Ljava/lang/Object;)Z;
const #32 = Asciz	productElement;
const #33 = Asciz	(I)Ljava/lang/Object;;
const #34 = Asciz	()Lscala/collection/mutable/Buffer;;
const #35 = NameAndType	#3:#34;//  underlying:()Lscala/collection/mutable/Buffer;
const #36 = Method	#12.#35;	//  scala/collection/JavaConversions$MutableBufferWrapper.underlying:()Lscala/collection/mutable/Buffer;
const #37 = Asciz	scala/MatchError;
const #38 = class	#37;	//  scala/MatchError
const #39 = Asciz	scala/runtime/BoxesRunTime;
const #40 = class	#39;	//  scala/runtime/BoxesRunTime
const #41 = Asciz	boxToInteger;
const #42 = Asciz	(I)Ljava/lang/Integer;;
const #43 = NameAndType	#41:#42;//  boxToInteger:(I)Ljava/lang/Integer;
const #44 = Method	#40.#43;	//  scala/runtime/BoxesRunTime.boxToInteger:(I)Ljava/lang/Integer;
const #45 = Asciz	java/lang/Object;
const #46 = class	#45;	//  java/lang/Object
const #47 = Asciz	toString;
const #48 = Asciz	()Ljava/lang/String;;
const #49 = NameAndType	#47:#48;//  toString:()Ljava/lang/String;
const #50 = Method	#46.#49;	//  java/lang/Object.toString:()Ljava/lang/String;
const #51 = Asciz	(Ljava/lang/String;)V;
const #52 = NameAndType	#7:#51;//  "<init>":(Ljava/lang/String;)V
const #53 = Method	#38.#52;	//  scala/MatchError."<init>":(Ljava/lang/String;)V
const #54 = Asciz	java/lang/IndexOutOfBoundsException;
const #55 = class	#54;	//  java/lang/IndexOutOfBoundsException
const #56 = Method	#55.#52;	//  java/lang/IndexOutOfBoundsException."<init>":(Ljava/lang/String;)V
const #57 = Asciz	productArity;
const #58 = Asciz	()I;
const #59 = Asciz	productPrefix;
const #60 = Asciz	MutableBufferWrapper;
const #61 = String	#60;	//  MutableBufferWrapper
const #62 = Asciz	copy;
const #63 = Asciz	(Lscala/collection/mutable/Buffer;)Lscala/collection/JavaConversions$MutableBufferWrapper;;
const #64 = NameAndType	#7:#8;//  "<init>":(Lscala/collection/mutable/Buffer;)V
const #65 = Method	#12.#64;	//  scala/collection/JavaConversions$MutableBufferWrapper."<init>":(Lscala/collection/mutable/Buffer;)V
const #66 = Asciz	remove;
const #67 = Asciz	scala/collection/mutable/BufferLike;
const #68 = class	#67;	//  scala/collection/mutable/BufferLike
const #69 = NameAndType	#66:#33;//  remove:(I)Ljava/lang/Object;
const #70 = InterfaceMethod	#68.#69;	//  scala/collection/mutable/BufferLike.remove:(I)Ljava/lang/Object;
const #71 = Asciz	i;
const #72 = Asciz	I;
const #73 = Asciz	(I)TA;;
const #74 = Asciz	add;
const #75 = Asciz	scala/Predef$;
const #76 = class	#75;	//  scala/Predef$
const #77 = Asciz	MODULE$;
const #78 = Asciz	Lscala/Predef$;;
const #79 = NameAndType	#77:#78;//  MODULE$:Lscala/Predef$;
const #80 = Field	#76.#79;	//  scala/Predef$.MODULE$:Lscala/Predef$;
const #81 = Asciz	genericWrapArray;
const #82 = Asciz	(Ljava/lang/Object;)Lscala/collection/mutable/WrappedArray;;
const #83 = NameAndType	#81:#82;//  genericWrapArray:(Ljava/lang/Object;)Lscala/collection/mutable/WrappedArray;
const #84 = Method	#76.#83;	//  scala/Predef$.genericWrapArray:(Ljava/lang/Object;)Lscala/collection/mutable/WrappedArray;
const #85 = Asciz	append;
const #86 = Asciz	(Lscala/collection/Seq;)V;
const #87 = NameAndType	#85:#86;//  append:(Lscala/collection/Seq;)V
const #88 = InterfaceMethod	#68.#87;	//  scala/collection/mutable/BufferLike.append:(Lscala/collection/Seq;)V
const #89 = Asciz	elem;
const #90 = Asciz	Ljava/lang/Object;;
const #91 = Asciz	(TA;)Z;
const #92 = Asciz	set;
const #93 = Asciz	(ILjava/lang/Object;)Ljava/lang/Object;;
const #94 = Asciz	apply;
const #95 = NameAndType	#94:#33;//  apply:(I)Ljava/lang/Object;
const #96 = InterfaceMethod	#68.#95;	//  scala/collection/mutable/BufferLike.apply:(I)Ljava/lang/Object;
const #97 = Asciz	update;
const #98 = Asciz	(ILjava/lang/Object;)V;
const #99 = NameAndType	#97:#98;//  update:(ILjava/lang/Object;)V
const #100 = InterfaceMethod	#68.#99;	//  scala/collection/mutable/BufferLike.update:(ILjava/lang/Object;)V
const #101 = Asciz	p;
const #102 = Asciz	(ITA;)TA;;
const #103 = Asciz	get;
const #104 = Asciz	size;
const #105 = Asciz	length;
const #106 = NameAndType	#105:#58;//  length:()I
const #107 = InterfaceMethod	#68.#106;	//  scala/collection/mutable/BufferLike.length:()I
const #108 = Asciz	()Lscala/collection/mutable/Buffer<TA;>;;
const #109 = Asciz	copy$default$1;
const #110 = Asciz	productElements;
const #111 = Asciz	()Lscala/collection/Iterator;;
const #112 = Asciz	(Lscala/Product;)Lscala/collection/Iterator;;
const #113 = NameAndType	#110:#112;//  productElements:(Lscala/Product;)Lscala/collection/Iterator;
const #114 = Method	#21.#113;	//  scala/Product$class.productElements:(Lscala/Product;)Lscala/collection/Iterator;
const #115 = Asciz	productIterator;
const #116 = NameAndType	#115:#112;//  productIterator:(Lscala/Product;)Lscala/collection/Iterator;
const #117 = Method	#21.#116;	//  scala/Product$class.productIterator:(Lscala/Product;)Lscala/collection/Iterator;
const #118 = Asciz	<A:Ljava/lang/Object;>Ljava/util/AbstractList<TA;>;Lscala/ScalaObject;Lscala/Product;;
const #119 = Asciz	Scala;
const #120 = Asciz	InnerClasses;
const #121 = Asciz	scala/collection/JavaConversions;
const #122 = class	#121;	//  scala/collection/JavaConversions
const #123 = Asciz	scala/ScalaObject;
const #124 = class	#123;	//  scala/ScalaObject
const #125 = Asciz	scala/Product;
const #126 = class	#125;	//  scala/Product
const #127 = Asciz	java/io/Serializable;
const #128 = class	#127;	//  java/io/Serializable

{
public scala.collection.JavaConversions$MutableBufferWrapper(scala.collection.mutable.Buffer);
  Code:
   Stack=2, Locals=2, Args_size=2
   0:	aload_0
   1:	aload_1
   2:	putfield	#14; //Field underlying:Lscala/collection/mutable/Buffer;
   5:	aload_0
   6:	invokespecial	#19; //Method java/util/AbstractList."<init>":()V
   9:	aload_0
   10:	invokestatic	#25; //Method scala/Product$class.$init$:(Lscala/Product;)V
   13:	return
  LineNumberTable: 
   line 348: 0

  LocalVariableTable: 
   Start  Length  Slot  Name   Signature
   0      14      0    this       Lscala/collection/JavaConversions$MutableBufferWrapper;
   0      14      1    underlying       Lscala/collection/mutable/Buffer;

  Signature: length = 0x2
   00 1D 

public boolean canEqual(java.lang.Object);
  Code:
   Stack=1, Locals=2, Args_size=2
   0:	aload_1
   1:	instanceof	#12; //class scala/collection/JavaConversions$MutableBufferWrapper
   4:	ireturn
  LineNumberTable: 
   line 348: 0


public java.lang.Object productElement(int);
  Code:
   Stack=3, Locals=2, Args_size=2
   0:	iload_1
   1:	iconst_0
   2:	if_icmpne	29
   5:	iconst_1
   6:	ifeq	14
   9:	aload_0
   10:	invokevirtual	#36; //Method underlying:()Lscala/collection/mutable/Buffer;
   13:	areturn
   14:	new	#38; //class scala/MatchError
   17:	dup
   18:	iload_1
   19:	invokestatic	#44; //Method scala/runtime/BoxesRunTime.boxToInteger:(I)Ljava/lang/Integer;
   22:	invokevirtual	#50; //Method java/lang/Object.toString:()Ljava/lang/String;
   25:	invokespecial	#53; //Method scala/MatchError."<init>":(Ljava/lang/String;)V
   28:	athrow
   29:	iconst_1
   30:	ifeq	48
   33:	new	#55; //class java/lang/IndexOutOfBoundsException
   36:	dup
   37:	iload_1
   38:	invokestatic	#44; //Method scala/runtime/BoxesRunTime.boxToInteger:(I)Ljava/lang/Integer;
   41:	invokevirtual	#50; //Method java/lang/Object.toString:()Ljava/lang/String;
   44:	invokespecial	#56; //Method java/lang/IndexOutOfBoundsException."<init>":(Ljava/lang/String;)V
   47:	athrow
   48:	new	#38; //class scala/MatchError
   51:	dup
   52:	iload_1
   53:	invokestatic	#44; //Method scala/runtime/BoxesRunTime.boxToInteger:(I)Ljava/lang/Integer;
   56:	invokevirtual	#50; //Method java/lang/Object.toString:()Ljava/lang/String;
   59:	invokespecial	#53; //Method scala/MatchError."<init>":(Ljava/lang/String;)V
   62:	athrow
  LineNumberTable: 
   line 348: 0
   line 21: 5
   line 348: 9
   line 21: 29
   line 348: 33


public int productArity();
  Code:
   Stack=1, Locals=1, Args_size=1
   0:	iconst_1
   1:	ireturn
  LineNumberTable: 
   line 348: 0


public java.lang.String productPrefix();
  Code:
   Stack=1, Locals=1, Args_size=1
   0:	ldc	#61; //String MutableBufferWrapper
   2:	areturn
  LineNumberTable: 
   line 348: 0


public scala.collection.JavaConversions$MutableBufferWrapper copy(scala.collection.mutable.Buffer);
  Code:
   Stack=3, Locals=2, Args_size=2
   0:	new	#12; //class scala/collection/JavaConversions$MutableBufferWrapper
   3:	dup
   4:	aload_1
   5:	invokespecial	#65; //Method "<init>":(Lscala/collection/mutable/Buffer;)V
   8:	areturn
  LineNumberTable: 
   line 348: 0

  LocalVariableTable: 
   Start  Length  Slot  Name   Signature
   0      9      0    this       Lscala/collection/JavaConversions$MutableBufferWrapper;
   0      9      1    underlying       Lscala/collection/mutable/Buffer;


public java.lang.Object remove(int);
  Code:
   Stack=2, Locals=2, Args_size=2
   0:	aload_0
   1:	invokevirtual	#36; //Method underlying:()Lscala/collection/mutable/Buffer;
   4:	iload_1
   5:	invokeinterface	#70,  2; //InterfaceMethod scala/collection/mutable/BufferLike.remove:(I)Ljava/lang/Object;
   10:	areturn
  LineNumberTable: 
   line 353: 0

  LocalVariableTable: 
   Start  Length  Slot  Name   Signature
   0      11      0    this       Lscala/collection/JavaConversions$MutableBufferWrapper;
   0      11      1    i       I

  Signature: length = 0x2
   00 49 

public boolean add(java.lang.Object);
  Code:
   Stack=6, Locals=2, Args_size=2
   0:	aload_0
   1:	invokevirtual	#36; //Method underlying:()Lscala/collection/mutable/Buffer;
   4:	getstatic	#80; //Field scala/Predef$.MODULE$:Lscala/Predef$;
   7:	iconst_1
   8:	anewarray	#46; //class java/lang/Object
   11:	dup
   12:	iconst_0
   13:	aload_1
   14:	aastore
   15:	invokevirtual	#84; //Method scala/Predef$.genericWrapArray:(Ljava/lang/Object;)Lscala/collection/mutable/WrappedArray;
   18:	invokeinterface	#88,  2; //InterfaceMethod scala/collection/mutable/BufferLike.append:(Lscala/collection/Seq;)V
   23:	iconst_1
   24:	ireturn
  LineNumberTable: 
   line 352: 0

  LocalVariableTable: 
   Start  Length  Slot  Name   Signature
   0      25      0    this       Lscala/collection/JavaConversions$MutableBufferWrapper;
   0      25      1    elem       Ljava/lang/Object;

  Signature: length = 0x2
   00 5B 

public java.lang.Object set(int, java.lang.Object);
  Code:
   Stack=3, Locals=4, Args_size=3
   0:	aload_0
   1:	invokevirtual	#36; //Method underlying:()Lscala/collection/mutable/Buffer;
   4:	iload_1
   5:	invokeinterface	#96,  2; //InterfaceMethod scala/collection/mutable/BufferLike.apply:(I)Ljava/lang/Object;
   10:	astore_3
   11:	aload_0
   12:	invokevirtual	#36; //Method underlying:()Lscala/collection/mutable/Buffer;
   15:	iload_1
   16:	aload_2
   17:	invokeinterface	#100,  3; //InterfaceMethod scala/collection/mutable/BufferLike.update:(ILjava/lang/Object;)V
   22:	aload_3
   23:	areturn
  LineNumberTable: 
   line 351: 0

  LocalVariableTable: 
   Start  Length  Slot  Name   Signature
   0      24      0    this       Lscala/collection/JavaConversions$MutableBufferWrapper;
   0      24      1    i       I
   0      24      2    elem       Ljava/lang/Object;
   11      12      3    p       Ljava/lang/Object;

  Signature: length = 0x2
   00 66 

public java.lang.Object get(int);
  Code:
   Stack=2, Locals=2, Args_size=2
   0:	aload_0
   1:	invokevirtual	#36; //Method underlying:()Lscala/collection/mutable/Buffer;
   4:	iload_1
   5:	invokeinterface	#96,  2; //InterfaceMethod scala/collection/mutable/BufferLike.apply:(I)Ljava/lang/Object;
   10:	areturn
  LineNumberTable: 
   line 350: 0

  LocalVariableTable: 
   Start  Length  Slot  Name   Signature
   0      11      0    this       Lscala/collection/JavaConversions$MutableBufferWrapper;
   0      11      1    i       I

  Signature: length = 0x2
   00 49 

public int size();
  Code:
   Stack=1, Locals=1, Args_size=1
   0:	aload_0
   1:	invokevirtual	#36; //Method underlying:()Lscala/collection/mutable/Buffer;
   4:	invokeinterface	#107,  1; //InterfaceMethod scala/collection/mutable/BufferLike.length:()I
   9:	ireturn
  LineNumberTable: 
   line 349: 0


public scala.collection.mutable.Buffer underlying();
  Code:
   Stack=1, Locals=1, Args_size=1
   0:	aload_0
   1:	getfield	#14; //Field underlying:Lscala/collection/mutable/Buffer;
   4:	areturn
  LineNumberTable: 
   line 348: 0

  Signature: length = 0x2
   00 6C 

public scala.collection.mutable.Buffer copy$default$1();
  Code:
   Stack=1, Locals=1, Args_size=1
   0:	aload_0
   1:	invokevirtual	#36; //Method underlying:()Lscala/collection/mutable/Buffer;
   4:	areturn
  LineNumberTable: 
   line 348: 0


public scala.collection.Iterator productElements();
  Code:
   Stack=1, Locals=1, Args_size=1
   0:	aload_0
   1:	invokestatic	#114; //Method scala/Product$class.productElements:(Lscala/Product;)Lscala/collection/Iterator;
   4:	areturn
  LineNumberTable: 
   line 348: 0


public scala.collection.Iterator productIterator();
  Code:
   Stack=1, Locals=1, Args_size=1
   0:	aload_0
   1:	invokestatic	#117; //Method scala/Product$class.productIterator:(Lscala/Product;)Lscala/collection/Iterator;
   4:	areturn
  LineNumberTable: 
   line 348: 0


}

