Compiled from "JavaConversions.scala"
public final class scala.collection.JavaConversions$MutableMapWrapper$$anon$1$$anon$4$$anon$5 extends java.lang.Object implements java.util.Map$Entry
  SourceFile: "JavaConversions.scala"
  Signature: length = 0x2
   00 60 
  Scala: length = 0x
   
  InnerClass: 
   public abstract #101= #36 of #100; //Entry=class java/util/Map$Entry of class java/util/Map
   public #104= #87 of #103; //MutableMapWrapper=class scala/collection/JavaConversions$MutableMapWrapper of class scala/collection/JavaConversions
   public final #105= #81 of #87; //$anon$1=class scala/collection/JavaConversions$MutableMapWrapper$$anon$1 of class scala/collection/JavaConversions$MutableMapWrapper
   public final #106= #75 of #81; //$anon$4=class scala/collection/JavaConversions$MutableMapWrapper$$anon$1$$anon$4 of class scala/collection/JavaConversions$MutableMapWrapper$$anon$1
   public final #107= #18 of #75; //$anon$5=class scala/collection/JavaConversions$MutableMapWrapper$$anon$1$$anon$4$$anon$5 of class scala/collection/JavaConversions$MutableMapWrapper$$anon$1$$anon$4
  minor version: 0
  major version: 49
  Constant pool:
const #1 = Asciz	SourceFile;
const #2 = Asciz	JavaConversions.scala;
const #3 = Asciz	v$1;
const #4 = Asciz	Ljava/lang/Object;;
const #5 = Asciz	k$1;
const #6 = Asciz	$outer;
const #7 = Asciz	Lscala/collection/JavaConversions$MutableMapWrapper$$anon$1$$anon$4;;
const #8 = Asciz	<init>;
const #9 = Asciz	(Lscala/collection/JavaConversions$MutableMapWrapper$$anon$1$$anon$4;Ljava/lang/Object;Ljava/lang/Object;)V;
const #10 = Asciz	Code;
const #11 = Asciz	LineNumberTable;
const #12 = Asciz	java/lang/NullPointerException;
const #13 = class	#12;	//  java/lang/NullPointerException
const #14 = Asciz	()V;
const #15 = NameAndType	#8:#14;//  "<init>":()V
const #16 = Method	#13.#15;	//  java/lang/NullPointerException."<init>":()V
const #17 = Asciz	scala/collection/JavaConversions$MutableMapWrapper$$anon$1$$anon$4$$anon$5;
const #18 = class	#17;	//  scala/collection/JavaConversions$MutableMapWrapper$$anon$1$$anon$4$$anon$5
const #19 = NameAndType	#6:#7;//  $outer:Lscala/collection/JavaConversions$MutableMapWrapper$$anon$1$$anon$4;
const #20 = Field	#18.#19;	//  scala/collection/JavaConversions$MutableMapWrapper$$anon$1$$anon$4$$anon$5.$outer:Lscala/collection/JavaConversions$MutableMapWrapper$$anon$1$$anon$4;
const #21 = NameAndType	#5:#4;//  k$1:Ljava/lang/Object;
const #22 = Field	#18.#21;	//  scala/collection/JavaConversions$MutableMapWrapper$$anon$1$$anon$4$$anon$5.k$1:Ljava/lang/Object;
const #23 = NameAndType	#3:#4;//  v$1:Ljava/lang/Object;
const #24 = Field	#18.#23;	//  scala/collection/JavaConversions$MutableMapWrapper$$anon$1$$anon$4$$anon$5.v$1:Ljava/lang/Object;
const #25 = Asciz	java/lang/Object;
const #26 = class	#25;	//  java/lang/Object
const #27 = Method	#26.#15;	//  java/lang/Object."<init>":()V
const #28 = Asciz	this;
const #29 = Asciz	Lscala/collection/JavaConversions$MutableMapWrapper$$anon$1$$anon$4$$anon$5;;
const #30 = Asciz	LocalVariableTable;
const #31 = Asciz	(Lscala/collection/JavaConversions$MutableMapWrapper<TA;TB;>.$anon$1.$anon$4;)V;
const #32 = Asciz	Signature;
const #33 = Asciz	equals;
const #34 = Asciz	(Ljava/lang/Object;)Z;
const #35 = Asciz	java/util/Map$Entry;
const #36 = class	#35;	//  java/util/Map$Entry
const #37 = Asciz	getKey;
const #38 = Asciz	()Ljava/lang/Object;;
const #39 = NameAndType	#37:#38;//  getKey:()Ljava/lang/Object;
const #40 = InterfaceMethod	#36.#39;	//  java/util/Map$Entry.getKey:()Ljava/lang/Object;
const #41 = Asciz	java/lang/Number;
const #42 = class	#41;	//  java/lang/Number
const #43 = Asciz	java/lang/Character;
const #44 = class	#43;	//  java/lang/Character
const #45 = Asciz	scala/runtime/BoxesRunTime;
const #46 = class	#45;	//  scala/runtime/BoxesRunTime
const #47 = Asciz	equals2;
const #48 = Asciz	(Ljava/lang/Object;Ljava/lang/Object;)Z;
const #49 = NameAndType	#47:#48;//  equals2:(Ljava/lang/Object;Ljava/lang/Object;)Z
const #50 = Method	#46.#49;	//  scala/runtime/BoxesRunTime.equals2:(Ljava/lang/Object;Ljava/lang/Object;)Z
const #51 = NameAndType	#33:#34;//  equals:(Ljava/lang/Object;)Z
const #52 = Method	#26.#51;	//  java/lang/Object.equals:(Ljava/lang/Object;)Z
const #53 = Asciz	getValue;
const #54 = NameAndType	#53:#38;//  getValue:()Ljava/lang/Object;
const #55 = InterfaceMethod	#36.#54;	//  java/util/Map$Entry.getValue:()Ljava/lang/Object;
const #56 = Asciz	scala/MatchError;
const #57 = class	#56;	//  scala/MatchError
const #58 = Asciz	toString;
const #59 = Asciz	()Ljava/lang/String;;
const #60 = NameAndType	#58:#59;//  toString:()Ljava/lang/String;
const #61 = Method	#26.#60;	//  java/lang/Object.toString:()Ljava/lang/String;
const #62 = Asciz	(Ljava/lang/String;)V;
const #63 = NameAndType	#8:#62;//  "<init>":(Ljava/lang/String;)V
const #64 = Method	#57.#63;	//  scala/MatchError."<init>":(Ljava/lang/String;)V
const #65 = Asciz	other;
const #66 = Asciz	x0;
const #67 = Asciz	y0;
const #68 = Asciz	temp86;
const #69 = Asciz	Ljava/util/Map$Entry;;
const #70 = Asciz	x1;
const #71 = Asciz	y1;
const #72 = Asciz	setValue;
const #73 = Asciz	(Ljava/lang/Object;)Ljava/lang/Object;;
const #74 = Asciz	scala/collection/JavaConversions$MutableMapWrapper$$anon$1$$anon$4;
const #75 = class	#74;	//  scala/collection/JavaConversions$MutableMapWrapper$$anon$1$$anon$4
const #76 = Asciz	scala$collection$JavaConversions$MutableMapWrapper$$anon$$anon$$$outer;
const #77 = Asciz	()Lscala/collection/JavaConversions$MutableMapWrapper$$anon$1;;
const #78 = NameAndType	#76:#77;//  scala$collection$JavaConversions$MutableMapWrapper$$anon$$anon$$$outer:()Lscala/collection/JavaConversions$MutableMapWrapper$$anon$1;
const #79 = Method	#75.#78;	//  scala/collection/JavaConversions$MutableMapWrapper$$anon$1$$anon$4.scala$collection$JavaConversions$MutableMapWrapper$$anon$$anon$$$outer:()Lscala/collection/JavaConversions$MutableMapWrapper$$anon$1;
const #80 = Asciz	scala/collection/JavaConversions$MutableMapWrapper$$anon$1;
const #81 = class	#80;	//  scala/collection/JavaConversions$MutableMapWrapper$$anon$1
const #82 = Asciz	scala$collection$JavaConversions$MutableMapWrapper$$anon$$$outer;
const #83 = Asciz	()Lscala/collection/JavaConversions$MutableMapWrapper;;
const #84 = NameAndType	#82:#83;//  scala$collection$JavaConversions$MutableMapWrapper$$anon$$$outer:()Lscala/collection/JavaConversions$MutableMapWrapper;
const #85 = Method	#81.#84;	//  scala/collection/JavaConversions$MutableMapWrapper$$anon$1.scala$collection$JavaConversions$MutableMapWrapper$$anon$$$outer:()Lscala/collection/JavaConversions$MutableMapWrapper;
const #86 = Asciz	scala/collection/JavaConversions$MutableMapWrapper;
const #87 = class	#86;	//  scala/collection/JavaConversions$MutableMapWrapper
const #88 = Asciz	put;
const #89 = Asciz	(Ljava/lang/Object;Ljava/lang/Object;)Ljava/lang/Object;;
const #90 = NameAndType	#88:#89;//  put:(Ljava/lang/Object;Ljava/lang/Object;)Ljava/lang/Object;
const #91 = Method	#87.#90;	//  scala/collection/JavaConversions$MutableMapWrapper.put:(Ljava/lang/Object;Ljava/lang/Object;)Ljava/lang/Object;
const #92 = Asciz	v1;
const #93 = Asciz	(TB;)TB;;
const #94 = Asciz	()TB;;
const #95 = Asciz	()TA;;
const #96 = Asciz	Ljava/lang/Object;Ljava/util/Map$Entry<TA;TB;>;;
const #97 = Asciz	Scala;
const #98 = Asciz	InnerClasses;
const #99 = Asciz	java/util/Map;
const #100 = class	#99;	//  java/util/Map
const #101 = Asciz	Entry;
const #102 = Asciz	scala/collection/JavaConversions;
const #103 = class	#102;	//  scala/collection/JavaConversions
const #104 = Asciz	MutableMapWrapper;
const #105 = Asciz	$anon$1;
const #106 = Asciz	$anon$4;
const #107 = Asciz	$anon$5;

{
public scala.collection.JavaConversions$MutableMapWrapper$$anon$1$$anon$4$$anon$5(scala.collection.JavaConversions$MutableMapWrapper$$anon$1$$anon$4, java.lang.Object, java.lang.Object);
  Code:
   Stack=2, Locals=4, Args_size=4
   0:	aload_1
   1:	ifnonnull	12
   4:	new	#13; //class java/lang/NullPointerException
   7:	dup
   8:	invokespecial	#16; //Method java/lang/NullPointerException."<init>":()V
   11:	athrow
   12:	aload_0
   13:	aload_1
   14:	putfield	#20; //Field $outer:Lscala/collection/JavaConversions$MutableMapWrapper$$anon$1$$anon$4;
   17:	aload_0
   18:	aload_2
   19:	putfield	#22; //Field k$1:Ljava/lang/Object;
   22:	aload_0
   23:	aload_3
   24:	putfield	#24; //Field v$1:Ljava/lang/Object;
   27:	aload_0
   28:	invokespecial	#27; //Method java/lang/Object."<init>":()V
   31:	return
  LineNumberTable: 
   line 446: 0

  LocalVariableTable: 
   Start  Length  Slot  Name   Signature
   0      32      0    this       Lscala/collection/JavaConversions$MutableMapWrapper$$anon$1$$anon$4$$anon$5;
   0      32      1    $outer       Lscala/collection/JavaConversions$MutableMapWrapper$$anon$1$$anon$4;

  Signature: length = 0x2
   00 1F 

public boolean equals(java.lang.Object);
  Code:
   Stack=3, Locals=7, Args_size=2
   0:	aload_1
   1:	instanceof	#36; //class java/util/Map$Entry
   4:	ifeq	168
   7:	aload_1
   8:	checkcast	#36; //class java/util/Map$Entry
   11:	astore	4
   13:	iconst_1
   14:	ifeq	156
   17:	aload_0
   18:	getfield	#22; //Field k$1:Ljava/lang/Object;
   21:	aload	4
   23:	invokeinterface	#40,  1; //InterfaceMethod java/util/Map$Entry.getKey:()Ljava/lang/Object;
   28:	astore_3
   29:	astore_2
   30:	aload_2
   31:	aload_3
   32:	if_acmpne	39
   35:	iconst_1
   36:	goto	74
   39:	aload_2
   40:	ifnonnull	47
   43:	iconst_0
   44:	goto	74
   47:	aload_2
   48:	instanceof	#42; //class java/lang/Number
   51:	ifne	61
   54:	aload_2
   55:	instanceof	#44; //class java/lang/Character
   58:	ifeq	69
   61:	aload_2
   62:	aload_3
   63:	invokestatic	#50; //Method scala/runtime/BoxesRunTime.equals2:(Ljava/lang/Object;Ljava/lang/Object;)Z
   66:	goto	74
   69:	aload_2
   70:	aload_3
   71:	invokevirtual	#52; //Method java/lang/Object.equals:(Ljava/lang/Object;)Z
   74:	ifeq	152
   77:	aload_0
   78:	getfield	#24; //Field v$1:Ljava/lang/Object;
   81:	aload	4
   83:	invokeinterface	#55,  1; //InterfaceMethod java/util/Map$Entry.getValue:()Ljava/lang/Object;
   88:	astore	6
   90:	astore	5
   92:	aload	5
   94:	aload	6
   96:	if_acmpne	103
   99:	iconst_1
   100:	goto	145
   103:	aload	5
   105:	ifnonnull	112
   108:	iconst_0
   109:	goto	145
   112:	aload	5
   114:	instanceof	#42; //class java/lang/Number
   117:	ifne	128
   120:	aload	5
   122:	instanceof	#44; //class java/lang/Character
   125:	ifeq	138
   128:	aload	5
   130:	aload	6
   132:	invokestatic	#50; //Method scala/runtime/BoxesRunTime.equals2:(Ljava/lang/Object;Ljava/lang/Object;)Z
   135:	goto	145
   138:	aload	5
   140:	aload	6
   142:	invokevirtual	#52; //Method java/lang/Object.equals:(Ljava/lang/Object;)Z
   145:	ifeq	152
   148:	iconst_1
   149:	goto	173
   152:	iconst_0
   153:	goto	173
   156:	new	#57; //class scala/MatchError
   159:	dup
   160:	aload_1
   161:	invokevirtual	#61; //Method java/lang/Object.toString:()Ljava/lang/String;
   164:	invokespecial	#64; //Method scala/MatchError."<init>":(Ljava/lang/String;)V
   167:	athrow
   168:	iconst_1
   169:	ifeq	174
   172:	iconst_0
   173:	ireturn
   174:	new	#57; //class scala/MatchError
   177:	dup
   178:	aload_1
   179:	invokevirtual	#61; //Method java/lang/Object.toString:()Ljava/lang/String;
   182:	invokespecial	#64; //Method scala/MatchError."<init>":(Ljava/lang/String;)V
   185:	athrow
  LineNumberTable: 
   line 450: 0
   line 21: 13
   line 451: 17
   line 450: 156
   line 21: 168
   line 452: 172
   line 450: 173

  LocalVariableTable: 
   Start  Length  Slot  Name   Signature
   0      186      0    this       Lscala/collection/JavaConversions$MutableMapWrapper$$anon$1$$anon$4$$anon$5;
   0      186      1    other       Ljava/lang/Object;
   35      42      2    x0       Ljava/lang/Object;
   35      42      3    y0       Ljava/lang/Object;
   13      155      4    temp86       Ljava/util/Map$Entry;
   99      49      5    x1       Ljava/lang/Object;
   99      49      6    y1       Ljava/lang/Object;


public java.lang.Object setValue(java.lang.Object);
  Code:
   Stack=3, Locals=2, Args_size=2
   0:	aload_0
   1:	getfield	#20; //Field $outer:Lscala/collection/JavaConversions$MutableMapWrapper$$anon$1$$anon$4;
   4:	invokevirtual	#79; //Method scala/collection/JavaConversions$MutableMapWrapper$$anon$1$$anon$4.scala$collection$JavaConversions$MutableMapWrapper$$anon$$anon$$$outer:()Lscala/collection/JavaConversions$MutableMapWrapper$$anon$1;
   7:	invokevirtual	#85; //Method scala/collection/JavaConversions$MutableMapWrapper$$anon$1.scala$collection$JavaConversions$MutableMapWrapper$$anon$$$outer:()Lscala/collection/JavaConversions$MutableMapWrapper;
   10:	aload_0
   11:	getfield	#22; //Field k$1:Ljava/lang/Object;
   14:	aload_1
   15:	invokevirtual	#91; //Method scala/collection/JavaConversions$MutableMapWrapper.put:(Ljava/lang/Object;Ljava/lang/Object;)Ljava/lang/Object;
   18:	areturn
  LineNumberTable: 
   line 449: 0

  LocalVariableTable: 
   Start  Length  Slot  Name   Signature
   0      19      0    this       Lscala/collection/JavaConversions$MutableMapWrapper$$anon$1$$anon$4$$anon$5;
   0      19      1    v1       Ljava/lang/Object;

  Signature: length = 0x2
   00 5D 

public java.lang.Object getValue();
  Code:
   Stack=1, Locals=1, Args_size=1
   0:	aload_0
   1:	getfield	#24; //Field v$1:Ljava/lang/Object;
   4:	areturn
  LineNumberTable: 
   line 448: 0

  Signature: length = 0x2
   00 5E 

public java.lang.Object getKey();
  Code:
   Stack=1, Locals=1, Args_size=1
   0:	aload_0
   1:	getfield	#22; //Field k$1:Ljava/lang/Object;
   4:	areturn
  LineNumberTable: 
   line 447: 0

  Signature: length = 0x2
   00 5F 

}

