Compiled from "JavaConversions.scala"
public final class scala.collection.JavaConversions$IteratorWrapper$ extends java.lang.Object implements scala.ScalaObject
  SourceFile: "JavaConversions.scala"
  Scala: length = 0x
   
  InnerClass: 
   public IteratorWrapper=class scala/collection/JavaConversions$IteratorWrapper of class scala/collection/JavaConversions
  minor version: 0
  major version: 49
  Constant pool:
Asciz	SourceFile;
Asciz	JavaConversions.scala;
Asciz	Scala;
Asciz	MODULE$;
Asciz	Lscala/collection/JavaConversions$IteratorWrapper$;;
Asciz	<clinit>;
Asciz	()V;
Asciz	Code;
Asciz	scala/collection/JavaConversions$IteratorWrapper$;
class	scala/collection/JavaConversions$IteratorWrapper$
Asciz	<init>;
NameAndType	"<init>":()V
Method	scala/collection/JavaConversions$IteratorWrapper$."<init>":()V
Asciz	unapply;
Asciz	(Lscala/collection/JavaConversions$IteratorWrapper;)Lscala/Option;;
Asciz	LineNumberTable;
Asciz	java/lang/Object;
class	java/lang/Object
Asciz	equals;
Asciz	(Ljava/lang/Object;)Z;
NameAndType	equals:(Ljava/lang/Object;)Z
Method	java/lang/Object.equals:(Ljava/lang/Object;)Z
Asciz	scala/None$;
class	scala/None$
Asciz	Lscala/None$;;
NameAndType	MODULE$:Lscala/None$;
Field	scala/None$.MODULE$:Lscala/None$;
Asciz	scala/Some;
class	scala/Some
Asciz	scala/collection/JavaConversions$IteratorWrapper;
class	scala/collection/JavaConversions$IteratorWrapper
Asciz	underlying;
Asciz	()Lscala/collection/Iterator;;
NameAndType	underlying:()Lscala/collection/Iterator;
Method	scala/collection/JavaConversions$IteratorWrapper.underlying:()Lscala/collection/Iterator;
Asciz	(Ljava/lang/Object;)V;
NameAndType	"<init>":(Ljava/lang/Object;)V
Method	scala/Some."<init>":(Ljava/lang/Object;)V
Asciz	this;
Asciz	x$0;
Asciz	Lscala/collection/JavaConversions$IteratorWrapper;;
Asciz	LocalVariableTable;
Asciz	apply;
Asciz	(Lscala/collection/Iterator;)Lscala/collection/JavaConversions$IteratorWrapper;;
Asciz	(Lscala/collection/Iterator;)V;
NameAndType	"<init>":(Lscala/collection/Iterator;)V
Method	scala/collection/JavaConversions$IteratorWrapper."<init>":(Lscala/collection/Iterator;)V
Asciz	Lscala/collection/Iterator;;
Method	java/lang/Object."<init>":()V
NameAndType	MODULE$:Lscala/collection/JavaConversions$IteratorWrapper$;
Field	scala/collection/JavaConversions$IteratorWrapper$.MODULE$:Lscala/collection/JavaConversions$IteratorWrapper$;
Asciz	InnerClasses;
Asciz	scala/collection/JavaConversions;
class	scala/collection/JavaConversions
Asciz	IteratorWrapper;
Asciz	scala/ScalaObject;
class	scala/ScalaObject

{
public static final scala.collection.JavaConversions$IteratorWrapper$ MODULE$;
  Signature: Lscala/collection/JavaConversions$IteratorWrapper$;

public static {};
  Signature: ()V
  Code:
   Stack=1, Locals=0, Args_size=0
	new	class scala/collection/JavaConversions$IteratorWrapper$
	invokespecial	Method "<init>":()V
	return
  Labels:

public scala.Option unapply(scala.collection.JavaConversions$IteratorWrapper);
  Signature: (Lscala/collection/JavaConversions$IteratorWrapper;)Lscala/Option;
  Code:
   Stack=3, Locals=3, Args_size=2
	aload_1
	dup
	astore_2
	ifnull	l1 // getstatic
	aload_2
	aconst_null
	invokevirtual	Method java/lang/Object.equals:(Ljava/lang/Object;)Z
	ifeq	l2 // new
l1	getstatic	Field scala/None$.MODULE$:Lscala/None$;
	goto	l3 // areturn
l2	new	class scala/Some
	dup
	aload_1
	invokevirtual	Method scala/collection/JavaConversions$IteratorWrapper.underlying:()Lscala/collection/Iterator;
	invokespecial	Method scala/Some."<init>":(Ljava/lang/Object;)V
l3	areturn
  Labels:
   	l1 = 14 // getstatic
   	l2 = 20 // new
   	l3 = 31 // areturn
  LocalVariableTable: 
   Start  Length  Slot  Name   Signature
   0      32      0    this       Lscala/collection/JavaConversions$IteratorWrapper$;
   0      32      1    x$0       Lscala/collection/JavaConversions$IteratorWrapper;


public scala.collection.JavaConversions$IteratorWrapper apply(scala.collection.Iterator);
  Signature: (Lscala/collection/Iterator;)Lscala/collection/JavaConversions$IteratorWrapper;
  Code:
   Stack=3, Locals=2, Args_size=2
	new	class scala/collection/JavaConversions$IteratorWrapper
	dup
	aload_1
	invokespecial	Method scala/collection/JavaConversions$IteratorWrapper."<init>":(Lscala/collection/Iterator;)V
	areturn
  Labels:
  LocalVariableTable: 
   Start  Length  Slot  Name   Signature
   0      9      0    this       Lscala/collection/JavaConversions$IteratorWrapper$;
   0      9      1    underlying       Lscala/collection/Iterator;


public scala.collection.JavaConversions$IteratorWrapper$();
  Signature: ()V
  Code:
   Stack=1, Locals=1, Args_size=1
	aload_0
	invokespecial	Method java/lang/Object."<init>":()V
	aload_0
	putstatic	Field MODULE$:Lscala/collection/JavaConversions$IteratorWrapper$;
	return
  Labels:

}

