Compiled from "JavaConversions.scala"
public final class scala.collection.JavaConversions$MutableMapWrapper$ extends java.lang.Object implements scala.ScalaObject
  SourceFile: "JavaConversions.scala"
  Scala: length = 0x
   
  InnerClass: 
   public MutableMapWrapper=class scala/collection/JavaConversions$MutableMapWrapper of class scala/collection/JavaConversions
  minor version: 0
  major version: 49
  Constant pool:
Asciz	SourceFile;
Asciz	JavaConversions.scala;
Asciz	Scala;
Asciz	MODULE$;
Asciz	Lscala/collection/JavaConversions$MutableMapWrapper$;;
Asciz	<clinit>;
Asciz	()V;
Asciz	Code;
Asciz	scala/collection/JavaConversions$MutableMapWrapper$;
class	scala/collection/JavaConversions$MutableMapWrapper$
Asciz	<init>;
NameAndType	"<init>":()V
Method	scala/collection/JavaConversions$MutableMapWrapper$."<init>":()V
Asciz	unapply;
Asciz	(Lscala/collection/JavaConversions$MutableMapWrapper;)Lscala/Option;;
Asciz	LineNumberTable;
Asciz	java/lang/Object;
class	java/lang/Object
Asciz	equals;
Asciz	(Ljava/lang/Object;)Z;
NameAndType	equals:(Ljava/lang/Object;)Z
Method	java/lang/Object.equals:(Ljava/lang/Object;)Z
Asciz	scala/None$;
class	scala/None$
Asciz	Lscala/None$;;
NameAndType	MODULE$:Lscala/None$;
Field	scala/None$.MODULE$:Lscala/None$;
Asciz	scala/Some;
class	scala/Some
Asciz	scala/collection/JavaConversions$MutableMapWrapper;
class	scala/collection/JavaConversions$MutableMapWrapper
Asciz	underlying;
Asciz	()Lscala/collection/mutable/Map;;
NameAndType	underlying:()Lscala/collection/mutable/Map;
Method	scala/collection/JavaConversions$MutableMapWrapper.underlying:()Lscala/collection/mutable/Map;
Asciz	(Ljava/lang/Object;)V;
NameAndType	"<init>":(Ljava/lang/Object;)V
Method	scala/Some."<init>":(Ljava/lang/Object;)V
Asciz	this;
Asciz	x$0;
Asciz	Lscala/collection/JavaConversions$MutableMapWrapper;;
Asciz	LocalVariableTable;
Asciz	apply;
Asciz	(Lscala/collection/mutable/Map;Lscala/reflect/ClassManifest;)Lscala/collection/JavaConversions$MutableMapWrapper;;
Asciz	(Lscala/collection/mutable/Map;Lscala/reflect/ClassManifest;)V;
NameAndType	"<init>":(Lscala/collection/mutable/Map;Lscala/reflect/ClassManifest;)V
Method	scala/collection/JavaConversions$MutableMapWrapper."<init>":(Lscala/collection/mutable/Map;Lscala/reflect/ClassManifest;)V
Asciz	Lscala/collection/mutable/Map;;
Asciz	m;
Asciz	Lscala/reflect/ClassManifest;;
Method	java/lang/Object."<init>":()V
NameAndType	MODULE$:Lscala/collection/JavaConversions$MutableMapWrapper$;
Field	scala/collection/JavaConversions$MutableMapWrapper$.MODULE$:Lscala/collection/JavaConversions$MutableMapWrapper$;
Asciz	InnerClasses;
Asciz	scala/collection/JavaConversions;
class	scala/collection/JavaConversions
Asciz	MutableMapWrapper;
Asciz	scala/ScalaObject;
class	scala/ScalaObject

{
public static final scala.collection.JavaConversions$MutableMapWrapper$ MODULE$;
  Signature: Lscala/collection/JavaConversions$MutableMapWrapper$;

public static {};
  Signature: ()V
  Code:
   Stack=1, Locals=0, Args_size=0
	new	class scala/collection/JavaConversions$MutableMapWrapper$
	invokespecial	Method "<init>":()V
	return
  Labels:

public scala.Option unapply(scala.collection.JavaConversions$MutableMapWrapper);
  Signature: (Lscala/collection/JavaConversions$MutableMapWrapper;)Lscala/Option;
  Code:
   Stack=3, Locals=2, Args_size=2
	aload_1
	dup
	pop
	ifnull	l1 // getstatic
	aload_1
	aconst_null
	invokevirtual	Method java/lang/Object.equals:(Ljava/lang/Object;)Z
	ifeq	l2 // new
l1	getstatic	Field scala/None$.MODULE$:Lscala/None$;
	goto	l3 // areturn
l2	new	class scala/Some
	dup
	aload_1
	invokevirtual	Method scala/collection/JavaConversions$MutableMapWrapper.underlying:()Lscala/collection/mutable/Map;
	invokespecial	Method scala/Some."<init>":(Ljava/lang/Object;)V
l3	areturn
  Labels:
   	l1 = 14 // getstatic
   	l2 = 20 // new
   	l3 = 31 // areturn
  LocalVariableTable: 
   Start  Length  Slot  Name   Signature
   0      32      0    this       Lscala/collection/JavaConversions$MutableMapWrapper$;
   0      32      1    x$0       Lscala/collection/JavaConversions$MutableMapWrapper;


public scala.collection.JavaConversions$MutableMapWrapper apply(scala.collection.mutable.Map, scala.reflect.ClassManifest);
  Signature: (Lscala/collection/mutable/Map;Lscala/reflect/ClassManifest;)Lscala/collection/JavaConversions$MutableMapWrapper;
  Code:
   Stack=4, Locals=3, Args_size=3
	new	class scala/collection/JavaConversions$MutableMapWrapper
	dup
	aload_1
	aload_2
	invokespecial	Method scala/collection/JavaConversions$MutableMapWrapper."<init>":(Lscala/collection/mutable/Map;Lscala/reflect/ClassManifest;)V
	areturn
  Labels:
  LocalVariableTable: 
   Start  Length  Slot  Name   Signature
   0      10      0    this       Lscala/collection/JavaConversions$MutableMapWrapper$;
   0      10      1    underlying       Lscala/collection/mutable/Map;
   0      10      2    m       Lscala/reflect/ClassManifest;


public scala.collection.JavaConversions$MutableMapWrapper$();
  Signature: ()V
  Code:
   Stack=1, Locals=1, Args_size=1
	aload_0
	invokespecial	Method java/lang/Object."<init>":()V
	aload_0
	putstatic	Field MODULE$:Lscala/collection/JavaConversions$MutableMapWrapper$;
	return
  Labels:

}

