Compiled from "JavaConversions.scala"
public class scala.collection.JavaConversions$MutableMapWrapper extends java.util.AbstractMap implements scala.ScalaObject,scala.Product,java.io.Serializable
  SourceFile: "JavaConversions.scala"
  Signature: length = 0x2
   00 FFFFFF9C 
  Scala: length = 0x
   
  InnerClass: 
   public #65= #15 of #160; //MutableMapWrapper=class scala/collection/JavaConversions$MutableMapWrapper of class scala/collection/JavaConversions
   public final #161= #74 of #15; //$anon$1=class scala/collection/JavaConversions$MutableMapWrapper$$anon$1 of class scala/collection/JavaConversions$MutableMapWrapper
  minor version: 0
  major version: 49
  Constant pool:
const #1 = Asciz	SourceFile;
const #2 = Asciz	JavaConversions.scala;
const #3 = Asciz	m;
const #4 = Asciz	Lscala/reflect/ClassManifest;;
const #5 = Asciz	Lscala/reflect/ClassManifest<TA;>;;
const #6 = Asciz	Signature;
const #7 = Asciz	underlying;
const #8 = Asciz	Lscala/collection/mutable/Map;;
const #9 = Asciz	Lscala/collection/mutable/Map<TA;TB;>;;
const #10 = Asciz	<init>;
const #11 = Asciz	(Lscala/collection/mutable/Map;Lscala/reflect/ClassManifest;)V;
const #12 = Asciz	Code;
const #13 = Asciz	LineNumberTable;
const #14 = Asciz	scala/collection/JavaConversions$MutableMapWrapper;
const #15 = class	#14;	//  scala/collection/JavaConversions$MutableMapWrapper
const #16 = NameAndType	#7:#8;//  underlying:Lscala/collection/mutable/Map;
const #17 = Field	#15.#16;	//  scala/collection/JavaConversions$MutableMapWrapper.underlying:Lscala/collection/mutable/Map;
const #18 = NameAndType	#3:#4;//  m:Lscala/reflect/ClassManifest;
const #19 = Field	#15.#18;	//  scala/collection/JavaConversions$MutableMapWrapper.m:Lscala/reflect/ClassManifest;
const #20 = Asciz	java/util/AbstractMap;
const #21 = class	#20;	//  java/util/AbstractMap
const #22 = Asciz	()V;
const #23 = NameAndType	#10:#22;//  "<init>":()V
const #24 = Method	#21.#23;	//  java/util/AbstractMap."<init>":()V
const #25 = Asciz	scala/Product$class;
const #26 = class	#25;	//  scala/Product$class
const #27 = Asciz	$init$;
const #28 = Asciz	(Lscala/Product;)V;
const #29 = NameAndType	#27:#28;//  $init$:(Lscala/Product;)V
const #30 = Method	#26.#29;	//  scala/Product$class.$init$:(Lscala/Product;)V
const #31 = Asciz	this;
const #32 = Asciz	Lscala/collection/JavaConversions$MutableMapWrapper;;
const #33 = Asciz	LocalVariableTable;
const #34 = Asciz	(Lscala/collection/mutable/Map<TA;TB;>;Lscala/reflect/ClassManifest<TA;>;)V;
const #35 = Asciz	canEqual;
const #36 = Asciz	(Ljava/lang/Object;)Z;
const #37 = Asciz	productElement;
const #38 = Asciz	(I)Ljava/lang/Object;;
const #39 = Asciz	()Lscala/collection/mutable/Map;;
const #40 = NameAndType	#7:#39;//  underlying:()Lscala/collection/mutable/Map;
const #41 = Method	#15.#40;	//  scala/collection/JavaConversions$MutableMapWrapper.underlying:()Lscala/collection/mutable/Map;
const #42 = Asciz	scala/MatchError;
const #43 = class	#42;	//  scala/MatchError
const #44 = Asciz	scala/runtime/BoxesRunTime;
const #45 = class	#44;	//  scala/runtime/BoxesRunTime
const #46 = Asciz	boxToInteger;
const #47 = Asciz	(I)Ljava/lang/Integer;;
const #48 = NameAndType	#46:#47;//  boxToInteger:(I)Ljava/lang/Integer;
const #49 = Method	#45.#48;	//  scala/runtime/BoxesRunTime.boxToInteger:(I)Ljava/lang/Integer;
const #50 = Asciz	java/lang/Object;
const #51 = class	#50;	//  java/lang/Object
const #52 = Asciz	toString;
const #53 = Asciz	()Ljava/lang/String;;
const #54 = NameAndType	#52:#53;//  toString:()Ljava/lang/String;
const #55 = Method	#51.#54;	//  java/lang/Object.toString:()Ljava/lang/String;
const #56 = Asciz	(Ljava/lang/String;)V;
const #57 = NameAndType	#10:#56;//  "<init>":(Ljava/lang/String;)V
const #58 = Method	#43.#57;	//  scala/MatchError."<init>":(Ljava/lang/String;)V
const #59 = Asciz	java/lang/IndexOutOfBoundsException;
const #60 = class	#59;	//  java/lang/IndexOutOfBoundsException
const #61 = Method	#60.#57;	//  java/lang/IndexOutOfBoundsException."<init>":(Ljava/lang/String;)V
const #62 = Asciz	productArity;
const #63 = Asciz	()I;
const #64 = Asciz	productPrefix;
const #65 = Asciz	MutableMapWrapper;
const #66 = String	#65;	//  MutableMapWrapper
const #67 = Asciz	copy;
const #68 = Asciz	(Lscala/collection/mutable/Map;Lscala/reflect/ClassManifest;)Lscala/collection/JavaConversions$MutableMapWrapper;;
const #69 = NameAndType	#10:#11;//  "<init>":(Lscala/collection/mutable/Map;Lscala/reflect/ClassManifest;)V
const #70 = Method	#15.#69;	//  scala/collection/JavaConversions$MutableMapWrapper."<init>":(Lscala/collection/mutable/Map;Lscala/reflect/ClassManifest;)V
const #71 = Asciz	entrySet;
const #72 = Asciz	()Ljava/util/Set;;
const #73 = Asciz	scala/collection/JavaConversions$MutableMapWrapper$$anon$1;
const #74 = class	#73;	//  scala/collection/JavaConversions$MutableMapWrapper$$anon$1
const #75 = Asciz	(Lscala/collection/JavaConversions$MutableMapWrapper;)V;
const #76 = NameAndType	#10:#75;//  "<init>":(Lscala/collection/JavaConversions$MutableMapWrapper;)V
const #77 = Method	#74.#76;	//  scala/collection/JavaConversions$MutableMapWrapper$$anon$1."<init>":(Lscala/collection/JavaConversions$MutableMapWrapper;)V
const #78 = Asciz	()Ljava/util/Set<Ljava/util/Map$Entry<TA;TB;>;>;;
const #79 = Asciz	remove;
const #80 = Asciz	(Ljava/lang/Object;)Ljava/lang/Object;;
const #81 = Asciz	scala/reflect/ClassManifest;
const #82 = class	#81;	//  scala/reflect/ClassManifest
const #83 = Asciz	erasure;
const #84 = Asciz	()Ljava/lang/Class;;
const #85 = NameAndType	#83:#84;//  erasure:()Ljava/lang/Class;
const #86 = InterfaceMethod	#82.#85;	//  scala/reflect/ClassManifest.erasure:()Ljava/lang/Class;
const #87 = Asciz	java/lang/Class;
const #88 = class	#87;	//  java/lang/Class
const #89 = Asciz	isInstance;
const #90 = NameAndType	#89:#36;//  isInstance:(Ljava/lang/Object;)Z
const #91 = Method	#88.#90;	//  java/lang/Class.isInstance:(Ljava/lang/Object;)Z
const #92 = Asciz	scala/collection/MapLike;
const #93 = class	#92;	//  scala/collection/MapLike
const #94 = Asciz	get;
const #95 = Asciz	(Ljava/lang/Object;)Lscala/Option;;
const #96 = NameAndType	#94:#95;//  get:(Ljava/lang/Object;)Lscala/Option;
const #97 = InterfaceMethod	#93.#96;	//  scala/collection/MapLike.get:(Ljava/lang/Object;)Lscala/Option;
const #98 = Asciz	scala/Some;
const #99 = class	#98;	//  scala/Some
const #100 = Asciz	x;
const #101 = Asciz	Ljava/lang/Object;;
const #102 = NameAndType	#100:#101;//  x:Ljava/lang/Object;
const #103 = Field	#99.#102;	//  scala/Some.x:Ljava/lang/Object;
const #104 = Asciz	scala/collection/mutable/MapLike;
const #105 = class	#104;	//  scala/collection/mutable/MapLike
const #106 = Asciz	$minus$eq;
const #107 = Asciz	(Ljava/lang/Object;)Lscala/collection/mutable/MapLike;;
const #108 = NameAndType	#106:#107;//  $minus$eq:(Ljava/lang/Object;)Lscala/collection/mutable/MapLike;
const #109 = InterfaceMethod	#105.#108;	//  scala/collection/mutable/MapLike.$minus$eq:(Ljava/lang/Object;)Lscala/collection/mutable/MapLike;
const #110 = Asciz	scala/Option;
const #111 = class	#110;	//  scala/Option
const #112 = Method	#111.#54;	//  scala/Option.toString:()Ljava/lang/String;
const #113 = Asciz	scala/None$;
const #114 = class	#113;	//  scala/None$
const #115 = Asciz	MODULE$;
const #116 = Asciz	Lscala/None$;;
const #117 = NameAndType	#115:#116;//  MODULE$:Lscala/None$;
const #118 = Field	#114.#117;	//  scala/None$.MODULE$:Lscala/None$;
const #119 = Asciz	equals;
const #120 = NameAndType	#119:#36;//  equals:(Ljava/lang/Object;)Z
const #121 = Method	#51.#120;	//  java/lang/Object.equals:(Ljava/lang/Object;)Z
const #122 = Asciz	k;
const #123 = Asciz	temp79;
const #124 = Asciz	Lscala/Some;;
const #125 = Asciz	temp80;
const #126 = Asciz	temp78;
const #127 = Asciz	Lscala/Option;;
const #128 = Asciz	(Ljava/lang/Object;)TB;;
const #129 = Asciz	put;
const #130 = Asciz	(Ljava/lang/Object;Ljava/lang/Object;)Ljava/lang/Object;;
const #131 = Asciz	(Ljava/lang/Object;Ljava/lang/Object;)Lscala/Option;;
const #132 = NameAndType	#129:#131;//  put:(Ljava/lang/Object;Ljava/lang/Object;)Lscala/Option;
const #133 = InterfaceMethod	#105.#132;	//  scala/collection/mutable/MapLike.put:(Ljava/lang/Object;Ljava/lang/Object;)Lscala/Option;
const #134 = Asciz	v;
const #135 = Asciz	temp75;
const #136 = Asciz	temp76;
const #137 = Asciz	temp74;
const #138 = Asciz	(TA;TB;)TB;;
const #139 = Asciz	size;
const #140 = Asciz	scala/collection/TraversableLike;
const #141 = class	#140;	//  scala/collection/TraversableLike
const #142 = NameAndType	#139:#63;//  size:()I
const #143 = InterfaceMethod	#141.#142;	//  scala/collection/TraversableLike.size:()I
const #144 = Asciz	()Lscala/collection/mutable/Map<TA;TB;>;;
const #145 = Asciz	copy$default$1;
const #146 = Asciz	copy$default$2;
const #147 = Asciz	(Lscala/collection/mutable/Map;)Lscala/reflect/ClassManifest;;
const #148 = Asciz	productElements;
const #149 = Asciz	()Lscala/collection/Iterator;;
const #150 = Asciz	(Lscala/Product;)Lscala/collection/Iterator;;
const #151 = NameAndType	#148:#150;//  productElements:(Lscala/Product;)Lscala/collection/Iterator;
const #152 = Method	#26.#151;	//  scala/Product$class.productElements:(Lscala/Product;)Lscala/collection/Iterator;
const #153 = Asciz	productIterator;
const #154 = NameAndType	#153:#150;//  productIterator:(Lscala/Product;)Lscala/collection/Iterator;
const #155 = Method	#26.#154;	//  scala/Product$class.productIterator:(Lscala/Product;)Lscala/collection/Iterator;
const #156 = Asciz	<A:Ljava/lang/Object;B:Ljava/lang/Object;>Ljava/util/AbstractMap<TA;TB;>;Lscala/ScalaObject;Lscala/Product;;
const #157 = Asciz	Scala;
const #158 = Asciz	InnerClasses;
const #159 = Asciz	scala/collection/JavaConversions;
const #160 = class	#159;	//  scala/collection/JavaConversions
const #161 = Asciz	$anon$1;
const #162 = Asciz	scala/ScalaObject;
const #163 = class	#162;	//  scala/ScalaObject
const #164 = Asciz	scala/Product;
const #165 = class	#164;	//  scala/Product
const #166 = Asciz	java/io/Serializable;
const #167 = class	#166;	//  java/io/Serializable

{
public scala.collection.JavaConversions$MutableMapWrapper(scala.collection.mutable.Map, scala.reflect.ClassManifest);
  Code:
   Stack=2, Locals=3, Args_size=3
   0:	aload_0
   1:	aload_1
   2:	putfield	#17; //Field underlying:Lscala/collection/mutable/Map;
   5:	aload_0
   6:	aload_2
   7:	putfield	#19; //Field m:Lscala/reflect/ClassManifest;
   10:	aload_0
   11:	invokespecial	#24; //Method java/util/AbstractMap."<init>":()V
   14:	aload_0
   15:	invokestatic	#30; //Method scala/Product$class.$init$:(Lscala/Product;)V
   18:	return
  LineNumberTable: 
   line 413: 0

  LocalVariableTable: 
   Start  Length  Slot  Name   Signature
   0      19      0    this       Lscala/collection/JavaConversions$MutableMapWrapper;
   0      19      1    underlying       Lscala/collection/mutable/Map;
   0      19      2    m       Lscala/reflect/ClassManifest;

  Signature: length = 0x2
   00 22 

public boolean canEqual(java.lang.Object);
  Code:
   Stack=1, Locals=2, Args_size=2
   0:	aload_1
   1:	instanceof	#15; //class scala/collection/JavaConversions$MutableMapWrapper
   4:	ireturn
  LineNumberTable: 
   line 413: 0


public java.lang.Object productElement(int);
  Code:
   Stack=3, Locals=2, Args_size=2
   0:	iload_1
   1:	iconst_0
   2:	if_icmpne	29
   5:	iconst_1
   6:	ifeq	14
   9:	aload_0
   10:	invokevirtual	#41; //Method underlying:()Lscala/collection/mutable/Map;
   13:	areturn
   14:	new	#43; //class scala/MatchError
   17:	dup
   18:	iload_1
   19:	invokestatic	#49; //Method scala/runtime/BoxesRunTime.boxToInteger:(I)Ljava/lang/Integer;
   22:	invokevirtual	#55; //Method java/lang/Object.toString:()Ljava/lang/String;
   25:	invokespecial	#58; //Method scala/MatchError."<init>":(Ljava/lang/String;)V
   28:	athrow
   29:	iconst_1
   30:	ifeq	48
   33:	new	#60; //class java/lang/IndexOutOfBoundsException
   36:	dup
   37:	iload_1
   38:	invokestatic	#49; //Method scala/runtime/BoxesRunTime.boxToInteger:(I)Ljava/lang/Integer;
   41:	invokevirtual	#55; //Method java/lang/Object.toString:()Ljava/lang/String;
   44:	invokespecial	#61; //Method java/lang/IndexOutOfBoundsException."<init>":(Ljava/lang/String;)V
   47:	athrow
   48:	new	#43; //class scala/MatchError
   51:	dup
   52:	iload_1
   53:	invokestatic	#49; //Method scala/runtime/BoxesRunTime.boxToInteger:(I)Ljava/lang/Integer;
   56:	invokevirtual	#55; //Method java/lang/Object.toString:()Ljava/lang/String;
   59:	invokespecial	#58; //Method scala/MatchError."<init>":(Ljava/lang/String;)V
   62:	athrow
  LineNumberTable: 
   line 413: 0
   line 21: 5
   line 413: 9
   line 21: 29
   line 413: 33


public int productArity();
  Code:
   Stack=1, Locals=1, Args_size=1
   0:	iconst_1
   1:	ireturn
  LineNumberTable: 
   line 413: 0


public java.lang.String productPrefix();
  Code:
   Stack=1, Locals=1, Args_size=1
   0:	ldc	#66; //String MutableMapWrapper
   2:	areturn
  LineNumberTable: 
   line 413: 0


public scala.collection.JavaConversions$MutableMapWrapper copy(scala.collection.mutable.Map, scala.reflect.ClassManifest);
  Code:
   Stack=4, Locals=3, Args_size=3
   0:	new	#15; //class scala/collection/JavaConversions$MutableMapWrapper
   3:	dup
   4:	aload_1
   5:	aload_2
   6:	invokespecial	#70; //Method "<init>":(Lscala/collection/mutable/Map;Lscala/reflect/ClassManifest;)V
   9:	areturn
  LineNumberTable: 
   line 413: 0

  LocalVariableTable: 
   Start  Length  Slot  Name   Signature
   0      10      0    this       Lscala/collection/JavaConversions$MutableMapWrapper;
   0      10      1    underlying       Lscala/collection/mutable/Map;
   0      10      2    m       Lscala/reflect/ClassManifest;


public java.util.Set entrySet();
  Code:
   Stack=3, Locals=1, Args_size=1
   0:	new	#74; //class scala/collection/JavaConversions$MutableMapWrapper$$anon$1
   3:	dup
   4:	aload_0
   5:	invokespecial	#77; //Method scala/collection/JavaConversions$MutableMapWrapper$$anon$1."<init>":(Lscala/collection/JavaConversions$MutableMapWrapper;)V
   8:	areturn
  LineNumberTable: 
   line 434: 0

  Signature: length = 0x2
   00 4E 

public java.lang.Object remove(java.lang.Object);
  Code:
   Stack=3, Locals=5, Args_size=2
   0:	aload_0
   1:	getfield	#19; //Field m:Lscala/reflect/ClassManifest;
   4:	invokeinterface	#86,  1; //InterfaceMethod scala/reflect/ClassManifest.erasure:()Ljava/lang/Class;
   9:	aload_1
   10:	invokevirtual	#91; //Method java/lang/Class.isInstance:(Ljava/lang/Object;)Z
   13:	ifeq	137
   16:	aload_0
   17:	invokevirtual	#41; //Method underlying:()Lscala/collection/mutable/Map;
   20:	aload_1
   21:	invokeinterface	#97,  2; //InterfaceMethod scala/collection/MapLike.get:(Ljava/lang/Object;)Lscala/Option;
   26:	astore	4
   28:	aload	4
   30:	instanceof	#99; //class scala/Some
   33:	ifeq	79
   36:	aload	4
   38:	checkcast	#99; //class scala/Some
   41:	astore_2
   42:	aload_2
   43:	getfield	#103; //Field scala/Some.x:Ljava/lang/Object;
   46:	astore_3
   47:	iconst_1
   48:	ifeq	66
   51:	aload_0
   52:	invokevirtual	#41; //Method underlying:()Lscala/collection/mutable/Map;
   55:	aload_1
   56:	invokeinterface	#109,  2; //InterfaceMethod scala/collection/mutable/MapLike.$minus$eq:(Ljava/lang/Object;)Lscala/collection/mutable/MapLike;
   61:	pop
   62:	aload_3
   63:	goto	138
   66:	new	#43; //class scala/MatchError
   69:	dup
   70:	aload	4
   72:	invokevirtual	#112; //Method scala/Option.toString:()Ljava/lang/String;
   75:	invokespecial	#58; //Method scala/MatchError."<init>":(Ljava/lang/String;)V
   78:	athrow
   79:	getstatic	#118; //Field scala/None$.MODULE$:Lscala/None$;
   82:	dup
   83:	ifnonnull	95
   86:	pop
   87:	aload	4
   89:	ifnull	103
   92:	goto	124
   95:	aload	4
   97:	invokevirtual	#121; //Method java/lang/Object.equals:(Ljava/lang/Object;)Z
   100:	ifeq	124
   103:	iconst_1
   104:	ifeq	111
   107:	aconst_null
   108:	goto	138
   111:	new	#43; //class scala/MatchError
   114:	dup
   115:	aload	4
   117:	invokevirtual	#112; //Method scala/Option.toString:()Ljava/lang/String;
   120:	invokespecial	#58; //Method scala/MatchError."<init>":(Ljava/lang/String;)V
   123:	athrow
   124:	new	#43; //class scala/MatchError
   127:	dup
   128:	aload	4
   130:	invokevirtual	#112; //Method scala/Option.toString:()Ljava/lang/String;
   133:	invokespecial	#58; //Method scala/MatchError."<init>":(Ljava/lang/String;)V
   136:	athrow
   137:	aconst_null
   138:	areturn
  LineNumberTable: 
   line 423: 0
   line 427: 16
   line 422: 36
   line 21: 47
   line 428: 51
   line 427: 66
   line 21: 103
   line 429: 107
   line 427: 111
   line 424: 137
   line 423: 138

  LocalVariableTable: 
   Start  Length  Slot  Name   Signature
   0      139      0    this       Lscala/collection/JavaConversions$MutableMapWrapper;
   0      139      1    k       Ljava/lang/Object;
   42      37      2    temp79       Lscala/Some;
   47      32      3    temp80       Ljava/lang/Object;
   28      109      4    temp78       Lscala/Option;

  Signature: length = 0x2
   00 FFFFFF80 

public java.lang.Object put(java.lang.Object, java.lang.Object);
  Code:
   Stack=3, Locals=6, Args_size=3
   0:	aload_0
   1:	invokevirtual	#41; //Method underlying:()Lscala/collection/mutable/Map;
   4:	aload_1
   5:	aload_2
   6:	invokeinterface	#133,  3; //InterfaceMethod scala/collection/mutable/MapLike.put:(Ljava/lang/Object;Ljava/lang/Object;)Lscala/Option;
   11:	astore	5
   13:	aload	5
   15:	instanceof	#99; //class scala/Some
   18:	ifeq	55
   21:	aload	5
   23:	checkcast	#99; //class scala/Some
   26:	astore_3
   27:	aload_3
   28:	getfield	#103; //Field scala/Some.x:Ljava/lang/Object;
   31:	astore	4
   33:	iconst_1
   34:	ifeq	42
   37:	aload	4
   39:	goto	84
   42:	new	#43; //class scala/MatchError
   45:	dup
   46:	aload	5
   48:	invokevirtual	#112; //Method scala/Option.toString:()Ljava/lang/String;
   51:	invokespecial	#58; //Method scala/MatchError."<init>":(Ljava/lang/String;)V
   54:	athrow
   55:	getstatic	#118; //Field scala/None$.MODULE$:Lscala/None$;
   58:	dup
   59:	ifnonnull	71
   62:	pop
   63:	aload	5
   65:	ifnull	79
   68:	goto	98
   71:	aload	5
   73:	invokevirtual	#121; //Method java/lang/Object.equals:(Ljava/lang/Object;)Z
   76:	ifeq	98
   79:	iconst_1
   80:	ifeq	85
   83:	aconst_null
   84:	areturn
   85:	new	#43; //class scala/MatchError
   88:	dup
   89:	aload	5
   91:	invokevirtual	#112; //Method scala/Option.toString:()Ljava/lang/String;
   94:	invokespecial	#58; //Method scala/MatchError."<init>":(Ljava/lang/String;)V
   97:	athrow
   98:	new	#43; //class scala/MatchError
   101:	dup
   102:	aload	5
   104:	invokevirtual	#112; //Method scala/Option.toString:()Ljava/lang/String;
   107:	invokespecial	#58; //Method scala/MatchError."<init>":(Ljava/lang/String;)V
   110:	athrow
  LineNumberTable: 
   line 417: 0
   line 21: 33
   line 418: 37
   line 417: 42
   line 21: 79
   line 419: 83
   line 417: 84

  LocalVariableTable: 
   Start  Length  Slot  Name   Signature
   0      111      0    this       Lscala/collection/JavaConversions$MutableMapWrapper;
   0      111      1    k       Ljava/lang/Object;
   0      111      2    v       Ljava/lang/Object;
   27      28      3    temp75       Lscala/Some;
   33      22      4    temp76       Ljava/lang/Object;
   13      98      5    temp74       Lscala/Option;

  Signature: length = 0x2
   00 FFFFFF8A 

public int size();
  Code:
   Stack=1, Locals=1, Args_size=1
   0:	aload_0
   1:	invokevirtual	#41; //Method underlying:()Lscala/collection/mutable/Map;
   4:	invokeinterface	#143,  1; //InterfaceMethod scala/collection/TraversableLike.size:()I
   9:	ireturn
  LineNumberTable: 
   line 415: 0


public scala.collection.mutable.Map underlying();
  Code:
   Stack=1, Locals=1, Args_size=1
   0:	aload_0
   1:	getfield	#17; //Field underlying:Lscala/collection/mutable/Map;
   4:	areturn
  LineNumberTable: 
   line 413: 0

  Signature: length = 0x2
   00 FFFFFF90 

public scala.collection.mutable.Map copy$default$1();
  Code:
   Stack=1, Locals=1, Args_size=1
   0:	aload_0
   1:	invokevirtual	#41; //Method underlying:()Lscala/collection/mutable/Map;
   4:	areturn
  LineNumberTable: 
   line 413: 0


public scala.reflect.ClassManifest copy$default$2(scala.collection.mutable.Map);
  Code:
   Stack=1, Locals=2, Args_size=2
   0:	aload_0
   1:	getfield	#19; //Field m:Lscala/reflect/ClassManifest;
   4:	areturn
  LineNumberTable: 
   line 413: 0

  LocalVariableTable: 
   Start  Length  Slot  Name   Signature
   0      5      0    this       Lscala/collection/JavaConversions$MutableMapWrapper;
   0      5      1    underlying       Lscala/collection/mutable/Map;


public scala.collection.Iterator productElements();
  Code:
   Stack=1, Locals=1, Args_size=1
   0:	aload_0
   1:	invokestatic	#152; //Method scala/Product$class.productElements:(Lscala/Product;)Lscala/collection/Iterator;
   4:	areturn
  LineNumberTable: 
   line 413: 0


public scala.collection.Iterator productIterator();
  Code:
   Stack=1, Locals=1, Args_size=1
   0:	aload_0
   1:	invokestatic	#155; //Method scala/Product$class.productIterator:(Lscala/Product;)Lscala/collection/Iterator;
   4:	areturn
  LineNumberTable: 
   line 413: 0


}

