Compiled from "JavaConversions.scala"
public class scala.collection.JavaConversions$MutableSetWrapper extends java.util.AbstractSet implements scala.ScalaObject,scala.Product,java.io.Serializable
  SourceFile: "JavaConversions.scala"
  Signature: length = 0x2
   00 78 
  Scala: length = 0x
   
  InnerClass: 
   public MutableSetWrapper=class scala/collection/JavaConversions$MutableSetWrapper of class scala/collection/JavaConversions
   public final $anon$3=class scala/collection/JavaConversions$MutableSetWrapper$$anon$3 of class scala/collection/JavaConversions$MutableSetWrapper
  minor version: 0
  major version: 49
  Constant pool:
Asciz	SourceFile;
Asciz	JavaConversions.scala;
Asciz	m;
Asciz	Lscala/reflect/ClassManifest;;
Asciz	Lscala/reflect/ClassManifest<TA;>;;
Asciz	Signature;
Asciz	underlying;
Asciz	Lscala/collection/mutable/Set;;
Asciz	Lscala/collection/mutable/Set<TA;>;;
Asciz	<init>;
Asciz	(Lscala/collection/mutable/Set;Lscala/reflect/ClassManifest;)V;
Asciz	Code;
Asciz	LineNumberTable;
Asciz	scala/collection/JavaConversions$MutableSetWrapper;
class	scala/collection/JavaConversions$MutableSetWrapper
NameAndType	underlying:Lscala/collection/mutable/Set;
Field	scala/collection/JavaConversions$MutableSetWrapper.underlying:Lscala/collection/mutable/Set;
NameAndType	m:Lscala/reflect/ClassManifest;
Field	scala/collection/JavaConversions$MutableSetWrapper.m:Lscala/reflect/ClassManifest;
Asciz	java/util/AbstractSet;
class	java/util/AbstractSet
Asciz	()V;
NameAndType	"<init>":()V
Method	java/util/AbstractSet."<init>":()V
Asciz	scala/Product$class;
class	scala/Product$class
Asciz	$init$;
Asciz	(Lscala/Product;)V;
NameAndType	$init$:(Lscala/Product;)V
Method	scala/Product$class.$init$:(Lscala/Product;)V
Asciz	this;
Asciz	Lscala/collection/JavaConversions$MutableSetWrapper;;
Asciz	LocalVariableTable;
Asciz	(Lscala/collection/mutable/Set<TA;>;Lscala/reflect/ClassManifest<TA;>;)V;
Asciz	canEqual;
Asciz	(Ljava/lang/Object;)Z;
Asciz	productElement;
Asciz	(I)Ljava/lang/Object;;
Asciz	()Lscala/collection/mutable/Set;;
NameAndType	underlying:()Lscala/collection/mutable/Set;
Method	scala/collection/JavaConversions$MutableSetWrapper.underlying:()Lscala/collection/mutable/Set;
Asciz	java/lang/IndexOutOfBoundsException;
class	java/lang/IndexOutOfBoundsException
Asciz	scala/runtime/BoxesRunTime;
class	scala/runtime/BoxesRunTime
Asciz	boxToInteger;
Asciz	(I)Ljava/lang/Integer;;
NameAndType	boxToInteger:(I)Ljava/lang/Integer;
Method	scala/runtime/BoxesRunTime.boxToInteger:(I)Ljava/lang/Integer;
Asciz	java/lang/Object;
class	java/lang/Object
Asciz	toString;
Asciz	()Ljava/lang/String;;
NameAndType	toString:()Ljava/lang/String;
Method	java/lang/Object.toString:()Ljava/lang/String;
Asciz	(Ljava/lang/String;)V;
NameAndType	"<init>":(Ljava/lang/String;)V
Method	java/lang/IndexOutOfBoundsException."<init>":(Ljava/lang/String;)V
Asciz	productArity;
Asciz	()I;
Asciz	productPrefix;
Asciz	MutableSetWrapper;
String	MutableSetWrapper
Asciz	copy;
Asciz	(Lscala/collection/mutable/Set;Lscala/reflect/ClassManifest;)Lscala/collection/JavaConversions$MutableSetWrapper;;
NameAndType	"<init>":(Lscala/collection/mutable/Set;Lscala/reflect/ClassManifest;)V
Method	scala/collection/JavaConversions$MutableSetWrapper."<init>":(Lscala/collection/mutable/Set;Lscala/reflect/ClassManifest;)V
Asciz	iterator;
Asciz	()Ljava/util/Iterator;;
Asciz	scala/collection/JavaConversions$MutableSetWrapper$$anon$3;
class	scala/collection/JavaConversions$MutableSetWrapper$$anon$3
Asciz	(Lscala/collection/JavaConversions$MutableSetWrapper;)V;
NameAndType	"<init>":(Lscala/collection/JavaConversions$MutableSetWrapper;)V
Method	scala/collection/JavaConversions$MutableSetWrapper$$anon$3."<init>":(Lscala/collection/JavaConversions$MutableSetWrapper;)V
Asciz	remove;
Asciz	scala/reflect/ClassManifest;
class	scala/reflect/ClassManifest
Asciz	erasure;
Asciz	()Ljava/lang/Class;;
NameAndType	erasure:()Ljava/lang/Class;
InterfaceMethod	scala/reflect/ClassManifest.erasure:()Ljava/lang/Class;
Asciz	java/lang/Class;
class	java/lang/Class
Asciz	isInstance;
NameAndType	isInstance:(Ljava/lang/Object;)Z
Method	java/lang/Class.isInstance:(Ljava/lang/Object;)Z
Asciz	scala/collection/TraversableLike;
class	scala/collection/TraversableLike
Asciz	size;
NameAndType	size:()I
InterfaceMethod	scala/collection/TraversableLike.size:()I
Asciz	scala/collection/mutable/SetLike;
class	scala/collection/mutable/SetLike
Asciz	$minus$eq;
Asciz	(Ljava/lang/Object;)Lscala/collection/mutable/SetLike;;
NameAndType	$minus$eq:(Ljava/lang/Object;)Lscala/collection/mutable/SetLike;
InterfaceMethod	scala/collection/mutable/SetLike.$minus$eq:(Ljava/lang/Object;)Lscala/collection/mutable/SetLike;
Asciz	elem;
Asciz	Ljava/lang/Object;;
Asciz	sz;
Asciz	I;
Asciz	add;
Asciz	$plus$eq;
NameAndType	$plus$eq:(Ljava/lang/Object;)Lscala/collection/mutable/SetLike;
InterfaceMethod	scala/collection/mutable/SetLike.$plus$eq:(Ljava/lang/Object;)Lscala/collection/mutable/SetLike;
Asciz	(TA;)Z;
Asciz	()Lscala/collection/mutable/Set<TA;>;;
Asciz	copy$default$1;
Asciz	copy$default$2;
Asciz	(Lscala/collection/mutable/Set;)Lscala/reflect/ClassManifest;;
Asciz	productElements;
Asciz	()Lscala/collection/Iterator;;
Asciz	(Lscala/Product;)Lscala/collection/Iterator;;
NameAndType	productElements:(Lscala/Product;)Lscala/collection/Iterator;
Method	scala/Product$class.productElements:(Lscala/Product;)Lscala/collection/Iterator;
Asciz	Deprecated;
Asciz	productIterator;
NameAndType	productIterator:(Lscala/Product;)Lscala/collection/Iterator;
Method	scala/Product$class.productIterator:(Lscala/Product;)Lscala/collection/Iterator;
Asciz	<A:Ljava/lang/Object;>Ljava/util/AbstractSet<TA;>;Lscala/ScalaObject;Lscala/Product;;
Asciz	Scala;
Asciz	InnerClasses;
Asciz	scala/collection/JavaConversions;
class	scala/collection/JavaConversions
Asciz	$anon$3;
Asciz	scala/ScalaObject;
class	scala/ScalaObject
Asciz	scala/Product;
class	scala/Product
Asciz	java/io/Serializable;
class	java/io/Serializable

{
private final scala.reflect.ClassManifest m;
  Signature: Lscala/reflect/ClassManifest;
  Signature: length = 0x2
   00 05 

private final scala.collection.mutable.Set underlying;
  Signature: Lscala/collection/mutable/Set;
  Signature: length = 0x2
   00 09 

public scala.collection.JavaConversions$MutableSetWrapper(scala.collection.mutable.Set, scala.reflect.ClassManifest);
  Signature: (Lscala/collection/mutable/Set;Lscala/reflect/ClassManifest;)V
  Code:
   Stack=2, Locals=3, Args_size=3
	aload_0
	aload_1
	putfield	Field underlying:Lscala/collection/mutable/Set;
	aload_0
	aload_2
	putfield	Field m:Lscala/reflect/ClassManifest;
	aload_0
	invokespecial	Method java/util/AbstractSet."<init>":()V
	aload_0
	invokestatic	Method scala/Product$class.$init$:(Lscala/Product;)V
	return
  Labels:
  LocalVariableTable: 
   Start  Length  Slot  Name   Signature
   0      19      0    this       Lscala/collection/JavaConversions$MutableSetWrapper;
   0      19      1    underlying       Lscala/collection/mutable/Set;
   0      19      2    m       Lscala/reflect/ClassManifest;

  Signature: length = 0x2
   00 22 

public boolean canEqual(java.lang.Object);
  Signature: (Ljava/lang/Object;)Z
  Code:
   Stack=1, Locals=2, Args_size=2
	aload_1
	instanceof	class scala/collection/JavaConversions$MutableSetWrapper
	ireturn
  Labels:

public java.lang.Object productElement(int);
  Signature: (I)Ljava/lang/Object;
  Code:
   Stack=3, Locals=2, Args_size=2
	iload_1
	iconst_0
	if_icmpne	l1 // new
	aload_0
	invokevirtual	Method underlying:()Lscala/collection/mutable/Set;
	areturn
l1	new	class java/lang/IndexOutOfBoundsException
	dup
	iload_1
	invokestatic	Method scala/runtime/BoxesRunTime.boxToInteger:(I)Ljava/lang/Integer;
	invokevirtual	Method java/lang/Object.toString:()Ljava/lang/String;
	invokespecial	Method java/lang/IndexOutOfBoundsException."<init>":(Ljava/lang/String;)V
	athrow
  Labels:
   	l1 = 10 // new

public int productArity();
  Signature: ()I
  Code:
   Stack=1, Locals=1, Args_size=1
	iconst_1
	ireturn
  Labels:

public java.lang.String productPrefix();
  Signature: ()Ljava/lang/String;
  Code:
   Stack=1, Locals=1, Args_size=1
	ldc	String MutableSetWrapper
	areturn
  Labels:

public scala.collection.JavaConversions$MutableSetWrapper copy(scala.collection.mutable.Set, scala.reflect.ClassManifest);
  Signature: (Lscala/collection/mutable/Set;Lscala/reflect/ClassManifest;)Lscala/collection/JavaConversions$MutableSetWrapper;
  Code:
   Stack=4, Locals=3, Args_size=3
	new	class scala/collection/JavaConversions$MutableSetWrapper
	dup
	aload_1
	aload_2
	invokespecial	Method "<init>":(Lscala/collection/mutable/Set;Lscala/reflect/ClassManifest;)V
	areturn
  Labels:
  LocalVariableTable: 
   Start  Length  Slot  Name   Signature
   0      10      0    this       Lscala/collection/JavaConversions$MutableSetWrapper;
   0      10      1    underlying       Lscala/collection/mutable/Set;
   0      10      2    m       Lscala/reflect/ClassManifest;


public java.util.Iterator iterator();
  Signature: ()Ljava/util/Iterator;
  Code:
   Stack=3, Locals=1, Args_size=1
	new	class scala/collection/JavaConversions$MutableSetWrapper$$anon$3
	dup
	aload_0
	invokespecial	Method scala/collection/JavaConversions$MutableSetWrapper$$anon$3."<init>":(Lscala/collection/JavaConversions$MutableSetWrapper;)V
	areturn
  Labels:

public boolean remove(java.lang.Object);
  Signature: (Ljava/lang/Object;)Z
  Code:
   Stack=2, Locals=3, Args_size=2
	aload_0
	getfield	Field m:Lscala/reflect/ClassManifest;
	invokeinterface	InterfaceMethod scala/reflect/ClassManifest.erasure:()Ljava/lang/Class;
	aload_1
	invokevirtual	Method java/lang/Class.isInstance:(Ljava/lang/Object;)Z
	ifeq	l1 // iconst_0
	aload_0
	invokevirtual	Method underlying:()Lscala/collection/mutable/Set;
	invokeinterface	InterfaceMethod scala/collection/TraversableLike.size:()I
	istore_2
	aload_0
	invokevirtual	Method underlying:()Lscala/collection/mutable/Set;
	aload_1
	invokeinterface	InterfaceMethod scala/collection/mutable/SetLike.$minus$eq:(Ljava/lang/Object;)Lscala/collection/mutable/SetLike;
	pop
	iload_2
	aload_0
	invokevirtual	Method underlying:()Lscala/collection/mutable/Set;
	invokeinterface	InterfaceMethod scala/collection/TraversableLike.size:()I
	if_icmple	l2 // iconst_0
	iconst_1
	goto	l3 // ifeq
l2	iconst_0
l3	ifeq	l1 // iconst_0
	iconst_1
	goto	l4 // ireturn
l1	iconst_0
l4	ireturn
  Labels:
   	l2 = 54 // iconst_0
   	l3 = 55 // ifeq
   	l1 = 62 // iconst_0
   	l4 = 63 // ireturn
  LocalVariableTable: 
   Start  Length  Slot  Name   Signature
   0      64      0    this       Lscala/collection/JavaConversions$MutableSetWrapper;
   0      64      1    elem       Ljava/lang/Object;
   26      32      2    sz       I


public boolean add(java.lang.Object);
  Signature: (Ljava/lang/Object;)Z
  Code:
   Stack=2, Locals=3, Args_size=2
	aload_0
	invokevirtual	Method underlying:()Lscala/collection/mutable/Set;
	invokeinterface	InterfaceMethod scala/collection/TraversableLike.size:()I
	istore_2
	aload_0
	invokevirtual	Method underlying:()Lscala/collection/mutable/Set;
	aload_1
	invokeinterface	InterfaceMethod scala/collection/mutable/SetLike.$plus$eq:(Ljava/lang/Object;)Lscala/collection/mutable/SetLike;
	pop
	iload_2
	aload_0
	invokevirtual	Method underlying:()Lscala/collection/mutable/Set;
	invokeinterface	InterfaceMethod scala/collection/TraversableLike.size:()I
	if_icmpge	l1 // iconst_0
	iconst_1
	goto	l2 // ireturn
l1	iconst_0
l2	ireturn
  Labels:
   	l1 = 38 // iconst_0
   	l2 = 39 // ireturn
  LocalVariableTable: 
   Start  Length  Slot  Name   Signature
   0      40      0    this       Lscala/collection/JavaConversions$MutableSetWrapper;
   0      40      1    elem       Ljava/lang/Object;
   10      30      2    sz       I

  Signature: length = 0x2
   00 6A 

public int size();
  Signature: ()I
  Code:
   Stack=1, Locals=1, Args_size=1
	aload_0
	invokevirtual	Method underlying:()Lscala/collection/mutable/Set;
	invokeinterface	InterfaceMethod scala/collection/TraversableLike.size:()I
	ireturn
  Labels:

public scala.collection.mutable.Set underlying();
  Signature: ()Lscala/collection/mutable/Set;
  Code:
   Stack=1, Locals=1, Args_size=1
	aload_0
	getfield	Field underlying:Lscala/collection/mutable/Set;
	areturn
  Labels:
  Signature: length = 0x2
   00 6B 

public scala.collection.mutable.Set copy$default$1();
  Signature: ()Lscala/collection/mutable/Set;
  Code:
   Stack=1, Locals=1, Args_size=1
	aload_0
	invokevirtual	Method underlying:()Lscala/collection/mutable/Set;
	areturn
  Labels:

public scala.reflect.ClassManifest copy$default$2(scala.collection.mutable.Set);
  Signature: (Lscala/collection/mutable/Set;)Lscala/reflect/ClassManifest;
  Code:
   Stack=1, Locals=2, Args_size=2
	aload_0
	getfield	Field m:Lscala/reflect/ClassManifest;
	areturn
  Labels:
  LocalVariableTable: 
   Start  Length  Slot  Name   Signature
   0      5      0    this       Lscala/collection/JavaConversions$MutableSetWrapper;
   0      5      1    underlying       Lscala/collection/mutable/Set;


public scala.collection.Iterator productElements();
  Signature: ()Lscala/collection/Iterator;
  Code:
   Stack=1, Locals=1, Args_size=1
	aload_0
	invokestatic	Method scala/Product$class.productElements:(Lscala/Product;)Lscala/collection/Iterator;
	areturn
  Labels:
  Deprecated: true

public scala.collection.Iterator productIterator();
  Signature: ()Lscala/collection/Iterator;
  Code:
   Stack=1, Locals=1, Args_size=1
	aload_0
	invokestatic	Method scala/Product$class.productIterator:(Lscala/Product;)Lscala/collection/Iterator;
	areturn
  Labels:

}

