Compiled from "JavaConversions.scala"
public final class scala.collection.JavaConversions$MutableMapWrapper$$anon$1 extends java.util.AbstractSet
  SourceFile: "JavaConversions.scala"
  Signature: length = 0x2
   00 2E 
  Scala: length = 0x
   
  InnerClass: 
   public MutableMapWrapper=class scala/collection/JavaConversions$MutableMapWrapper of class scala/collection/JavaConversions
   public final $anon$1=class scala/collection/JavaConversions$MutableMapWrapper$$anon$1 of class scala/collection/JavaConversions$MutableMapWrapper
   public final $anon$4=class scala/collection/JavaConversions$MutableMapWrapper$$anon$1$$anon$4 of class scala/collection/JavaConversions$MutableMapWrapper$$anon$1
  minor version: 0
  major version: 49
  Constant pool:
Asciz	SourceFile;
Asciz	JavaConversions.scala;
Asciz	$outer;
Asciz	Lscala/collection/JavaConversions$MutableMapWrapper;;
Asciz	<init>;
Asciz	(Lscala/collection/JavaConversions$MutableMapWrapper;)V;
Asciz	Code;
Asciz	LineNumberTable;
Asciz	java/lang/NullPointerException;
class	java/lang/NullPointerException
Asciz	()V;
NameAndType	"<init>":()V
Method	java/lang/NullPointerException."<init>":()V
Asciz	scala/collection/JavaConversions$MutableMapWrapper$$anon$1;
class	scala/collection/JavaConversions$MutableMapWrapper$$anon$1
NameAndType	$outer:Lscala/collection/JavaConversions$MutableMapWrapper;
Field	scala/collection/JavaConversions$MutableMapWrapper$$anon$1.$outer:Lscala/collection/JavaConversions$MutableMapWrapper;
Asciz	java/util/AbstractSet;
class	java/util/AbstractSet
Method	java/util/AbstractSet."<init>":()V
Asciz	this;
Asciz	Lscala/collection/JavaConversions$MutableMapWrapper$$anon$1;;
Asciz	LocalVariableTable;
Asciz	(Lscala/collection/JavaConversions$MutableMapWrapper<TA;TB;>;)V;
Asciz	Signature;
Asciz	iterator;
Asciz	()Ljava/util/Iterator;;
Asciz	()Ljava/lang/Object;;
NameAndType	iterator:()Ljava/lang/Object;
Method	scala/collection/JavaConversions$MutableMapWrapper$$anon$1.iterator:()Ljava/lang/Object;
Asciz	java/util/Iterator;
class	java/util/Iterator
Asciz	scala$collection$JavaConversions$MutableMapWrapper$$anon$$$outer;
Asciz	()Lscala/collection/JavaConversions$MutableMapWrapper;;
Asciz	scala/collection/JavaConversions$MutableMapWrapper$$anon$1$$anon$4;
class	scala/collection/JavaConversions$MutableMapWrapper$$anon$1$$anon$4
Asciz	(Lscala/collection/JavaConversions$MutableMapWrapper$$anon$1;)V;
NameAndType	"<init>":(Lscala/collection/JavaConversions$MutableMapWrapper$$anon$1;)V
Method	scala/collection/JavaConversions$MutableMapWrapper$$anon$1$$anon$4."<init>":(Lscala/collection/JavaConversions$MutableMapWrapper$$anon$1;)V
Asciz	size;
Asciz	()I;
Asciz	scala/collection/JavaConversions$MutableMapWrapper;
class	scala/collection/JavaConversions$MutableMapWrapper
NameAndType	size:()I
Method	scala/collection/JavaConversions$MutableMapWrapper.size:()I
Asciz	Ljava/util/AbstractSet<Ljava/util/Map$Entry<TA;TB;>;>;;
Asciz	Scala;
Asciz	InnerClasses;
Asciz	scala/collection/JavaConversions;
class	scala/collection/JavaConversions
Asciz	MutableMapWrapper;
Asciz	$anon$1;
Asciz	$anon$4;

{
public final scala.collection.JavaConversions$MutableMapWrapper $outer;
  Signature: Lscala/collection/JavaConversions$MutableMapWrapper;

public scala.collection.JavaConversions$MutableMapWrapper$$anon$1(scala.collection.JavaConversions$MutableMapWrapper);
  Signature: (Lscala/collection/JavaConversions$MutableMapWrapper;)V
  Code:
   Stack=2, Locals=2, Args_size=2
	aload_1
	ifnonnull	l1 // aload_0
	new	class java/lang/NullPointerException
	dup
	invokespecial	Method java/lang/NullPointerException."<init>":()V
	athrow
l1	aload_0
	aload_1
	putfield	Field $outer:Lscala/collection/JavaConversions$MutableMapWrapper;
	aload_0
	invokespecial	Method java/util/AbstractSet."<init>":()V
	return
  Labels:
   	l1 = 12 // aload_0
  LocalVariableTable: 
   Start  Length  Slot  Name   Signature
   0      22      0    this       Lscala/collection/JavaConversions$MutableMapWrapper$$anon$1;
   0      22      1    $outer       Lscala/collection/JavaConversions$MutableMapWrapper;

  Signature: length = 0x2
   00 18 

public java.util.Iterator iterator();
  Signature: ()Ljava/util/Iterator;
  Code:
   Stack=1, Locals=1, Args_size=1
	aload_0
	invokevirtual	Method iterator:()Ljava/lang/Object;
	checkcast	class java/util/Iterator
	areturn
  Labels:

public scala.collection.JavaConversions$MutableMapWrapper scala$collection$JavaConversions$MutableMapWrapper$$anon$$$outer();
  Signature: ()Lscala/collection/JavaConversions$MutableMapWrapper;
  Code:
   Stack=1, Locals=1, Args_size=1
	aload_0
	getfield	Field $outer:Lscala/collection/JavaConversions$MutableMapWrapper;
	areturn
  Labels:

public java.lang.Object iterator();
  Signature: ()Ljava/lang/Object;
  Code:
   Stack=3, Locals=1, Args_size=1
	new	class scala/collection/JavaConversions$MutableMapWrapper$$anon$1$$anon$4
	dup
	aload_0
	invokespecial	Method scala/collection/JavaConversions$MutableMapWrapper$$anon$1$$anon$4."<init>":(Lscala/collection/JavaConversions$MutableMapWrapper$$anon$1;)V
	areturn
  Labels:

public int size();
  Signature: ()I
  Code:
   Stack=1, Locals=1, Args_size=1
	aload_0
	getfield	Field $outer:Lscala/collection/JavaConversions$MutableMapWrapper;
	invokevirtual	Method scala/collection/JavaConversions$MutableMapWrapper.size:()I
	ireturn
  Labels:

}

