Compiled from "JavaConversions.scala"
public final class scala.collection.JavaConversions$MutableMapWrapper$$anon$1$$anon$4 extends java.lang.Object implements java.util.Iterator
  SourceFile: "JavaConversions.scala"
  Signature: length = 0x2
   00 FFFFFF8F 
  Scala: length = 0x
   
  InnerClass: 
   public #148= #35 of #147; //MutableMapWrapper=class scala/collection/JavaConversions$MutableMapWrapper of class scala/collection/JavaConversions
   public final #149= #29 of #35; //$anon$1=class scala/collection/JavaConversions$MutableMapWrapper$$anon$1 of class scala/collection/JavaConversions$MutableMapWrapper
   public final #150= #22 of #29; //$anon$4=class scala/collection/JavaConversions$MutableMapWrapper$$anon$1$$anon$4 of class scala/collection/JavaConversions$MutableMapWrapper$$anon$1
   public final #151= #125 of #22; //$anon$5=class scala/collection/JavaConversions$MutableMapWrapper$$anon$1$$anon$4$$anon$5 of class scala/collection/JavaConversions$MutableMapWrapper$$anon$1$$anon$4
  minor version: 0
  major version: 49
  Constant pool:
const #1 = Asciz	SourceFile;
const #2 = Asciz	JavaConversions.scala;
const #3 = Asciz	$outer;
const #4 = Asciz	Lscala/collection/JavaConversions$MutableMapWrapper$$anon$1;;
const #5 = Asciz	prev;
const #6 = Asciz	Lscala/Option;;
const #7 = Asciz	Lscala/Option<TA;>;;
const #8 = Asciz	Signature;
const #9 = Asciz	ui;
const #10 = Asciz	Lscala/collection/Iterator;;
const #11 = Asciz	Lscala/collection/Iterator<Lscala/Tuple2<TA;TB;>;>;;
const #12 = Asciz	<init>;
const #13 = Asciz	(Lscala/collection/JavaConversions$MutableMapWrapper$$anon$1;)V;
const #14 = Asciz	Code;
const #15 = Asciz	LineNumberTable;
const #16 = Asciz	java/lang/NullPointerException;
const #17 = class	#16;	//  java/lang/NullPointerException
const #18 = Asciz	()V;
const #19 = NameAndType	#12:#18;//  "<init>":()V
const #20 = Method	#17.#19;	//  java/lang/NullPointerException."<init>":()V
const #21 = Asciz	scala/collection/JavaConversions$MutableMapWrapper$$anon$1$$anon$4;
const #22 = class	#21;	//  scala/collection/JavaConversions$MutableMapWrapper$$anon$1$$anon$4
const #23 = NameAndType	#3:#4;//  $outer:Lscala/collection/JavaConversions$MutableMapWrapper$$anon$1;
const #24 = Field	#22.#23;	//  scala/collection/JavaConversions$MutableMapWrapper$$anon$1$$anon$4.$outer:Lscala/collection/JavaConversions$MutableMapWrapper$$anon$1;
const #25 = Asciz	java/lang/Object;
const #26 = class	#25;	//  java/lang/Object
const #27 = Method	#26.#19;	//  java/lang/Object."<init>":()V
const #28 = Asciz	scala/collection/JavaConversions$MutableMapWrapper$$anon$1;
const #29 = class	#28;	//  scala/collection/JavaConversions$MutableMapWrapper$$anon$1
const #30 = Asciz	scala$collection$JavaConversions$MutableMapWrapper$$anon$$$outer;
const #31 = Asciz	()Lscala/collection/JavaConversions$MutableMapWrapper;;
const #32 = NameAndType	#30:#31;//  scala$collection$JavaConversions$MutableMapWrapper$$anon$$$outer:()Lscala/collection/JavaConversions$MutableMapWrapper;
const #33 = Method	#29.#32;	//  scala/collection/JavaConversions$MutableMapWrapper$$anon$1.scala$collection$JavaConversions$MutableMapWrapper$$anon$$$outer:()Lscala/collection/JavaConversions$MutableMapWrapper;
const #34 = Asciz	scala/collection/JavaConversions$MutableMapWrapper;
const #35 = class	#34;	//  scala/collection/JavaConversions$MutableMapWrapper
const #36 = Asciz	underlying;
const #37 = Asciz	()Lscala/collection/mutable/Map;;
const #38 = NameAndType	#36:#37;//  underlying:()Lscala/collection/mutable/Map;
const #39 = Method	#35.#38;	//  scala/collection/JavaConversions$MutableMapWrapper.underlying:()Lscala/collection/mutable/Map;
const #40 = Asciz	scala/collection/MapLike;
const #41 = class	#40;	//  scala/collection/MapLike
const #42 = Asciz	iterator;
const #43 = Asciz	()Lscala/collection/Iterator;;
const #44 = NameAndType	#42:#43;//  iterator:()Lscala/collection/Iterator;
const #45 = InterfaceMethod	#41.#44;	//  scala/collection/MapLike.iterator:()Lscala/collection/Iterator;
const #46 = NameAndType	#9:#10;//  ui:Lscala/collection/Iterator;
const #47 = Field	#22.#46;	//  scala/collection/JavaConversions$MutableMapWrapper$$anon$1$$anon$4.ui:Lscala/collection/Iterator;
const #48 = Asciz	scala/None$;
const #49 = class	#48;	//  scala/None$
const #50 = Asciz	MODULE$;
const #51 = Asciz	Lscala/None$;;
const #52 = NameAndType	#50:#51;//  MODULE$:Lscala/None$;
const #53 = Field	#49.#52;	//  scala/None$.MODULE$:Lscala/None$;
const #54 = NameAndType	#5:#6;//  prev:Lscala/Option;
const #55 = Field	#22.#54;	//  scala/collection/JavaConversions$MutableMapWrapper$$anon$1$$anon$4.prev:Lscala/Option;
const #56 = Asciz	this;
const #57 = Asciz	Lscala/collection/JavaConversions$MutableMapWrapper$$anon$1$$anon$4;;
const #58 = Asciz	LocalVariableTable;
const #59 = Asciz	(Lscala/collection/JavaConversions$MutableMapWrapper<TA;TB;>.$anon$1;)V;
const #60 = Asciz	scala$collection$JavaConversions$MutableMapWrapper$$anon$$anon$$$outer;
const #61 = Asciz	()Lscala/collection/JavaConversions$MutableMapWrapper$$anon$1;;
const #62 = Asciz	remove;
const #63 = Asciz	()Lscala/Option;;
const #64 = NameAndType	#5:#63;//  prev:()Lscala/Option;
const #65 = Method	#22.#64;	//  scala/collection/JavaConversions$MutableMapWrapper$$anon$1$$anon$4.prev:()Lscala/Option;
const #66 = Asciz	scala/Some;
const #67 = class	#66;	//  scala/Some
const #68 = Asciz	x;
const #69 = Asciz	Ljava/lang/Object;;
const #70 = NameAndType	#68:#69;//  x:Ljava/lang/Object;
const #71 = Field	#67.#70;	//  scala/Some.x:Ljava/lang/Object;
const #72 = Asciz	Lscala/collection/JavaConversions$MutableMapWrapper;;
const #73 = NameAndType	#3:#72;//  $outer:Lscala/collection/JavaConversions$MutableMapWrapper;
const #74 = Field	#29.#73;	//  scala/collection/JavaConversions$MutableMapWrapper$$anon$1.$outer:Lscala/collection/JavaConversions$MutableMapWrapper;
const #75 = Asciz	(Ljava/lang/Object;)Ljava/lang/Object;;
const #76 = NameAndType	#62:#75;//  remove:(Ljava/lang/Object;)Ljava/lang/Object;
const #77 = Method	#35.#76;	//  scala/collection/JavaConversions$MutableMapWrapper.remove:(Ljava/lang/Object;)Ljava/lang/Object;
const #78 = Asciz	prev_$eq;
const #79 = Asciz	(Lscala/Option;)V;
const #80 = NameAndType	#78:#79;//  prev_$eq:(Lscala/Option;)V
const #81 = Method	#22.#80;	//  scala/collection/JavaConversions$MutableMapWrapper$$anon$1$$anon$4.prev_$eq:(Lscala/Option;)V
const #82 = Asciz	scala/MatchError;
const #83 = class	#82;	//  scala/MatchError
const #84 = Asciz	scala/Option;
const #85 = class	#84;	//  scala/Option
const #86 = Asciz	toString;
const #87 = Asciz	()Ljava/lang/String;;
const #88 = NameAndType	#86:#87;//  toString:()Ljava/lang/String;
const #89 = Method	#85.#88;	//  scala/Option.toString:()Ljava/lang/String;
const #90 = Asciz	(Ljava/lang/String;)V;
const #91 = NameAndType	#12:#90;//  "<init>":(Ljava/lang/String;)V
const #92 = Method	#83.#91;	//  scala/MatchError."<init>":(Ljava/lang/String;)V
const #93 = Asciz	java/lang/IllegalStateException;
const #94 = class	#93;	//  java/lang/IllegalStateException
const #95 = Asciz	next must be called at least once before remove;
const #96 = String	#95;	//  next must be called at least once before remove
const #97 = Method	#94.#91;	//  java/lang/IllegalStateException."<init>":(Ljava/lang/String;)V
const #98 = Asciz	temp88;
const #99 = Asciz	Lscala/Some;;
const #100 = Asciz	temp89;
const #101 = Asciz	temp87;
const #102 = Asciz	next;
const #103 = Asciz	()Ljava/lang/Object;;
const #104 = NameAndType	#9:#43;//  ui:()Lscala/collection/Iterator;
const #105 = Method	#22.#104;	//  scala/collection/JavaConversions$MutableMapWrapper$$anon$1$$anon$4.ui:()Lscala/collection/Iterator;
const #106 = Asciz	scala/collection/Iterator;
const #107 = class	#106;	//  scala/collection/Iterator
const #108 = NameAndType	#102:#103;//  next:()Ljava/lang/Object;
const #109 = InterfaceMethod	#107.#108;	//  scala/collection/Iterator.next:()Ljava/lang/Object;
const #110 = Asciz	scala/Tuple2;
const #111 = class	#110;	//  scala/Tuple2
const #112 = Asciz	_1;
const #113 = NameAndType	#112:#103;//  _1:()Ljava/lang/Object;
const #114 = Method	#111.#113;	//  scala/Tuple2._1:()Ljava/lang/Object;
const #115 = Asciz	_2;
const #116 = NameAndType	#115:#103;//  _2:()Ljava/lang/Object;
const #117 = Method	#111.#116;	//  scala/Tuple2._2:()Ljava/lang/Object;
const #118 = Asciz	(Ljava/lang/Object;Ljava/lang/Object;)V;
const #119 = NameAndType	#12:#118;//  "<init>":(Ljava/lang/Object;Ljava/lang/Object;)V
const #120 = Method	#111.#119;	//  scala/Tuple2."<init>":(Ljava/lang/Object;Ljava/lang/Object;)V
const #121 = Asciz	(Ljava/lang/Object;)V;
const #122 = NameAndType	#12:#121;//  "<init>":(Ljava/lang/Object;)V
const #123 = Method	#67.#122;	//  scala/Some."<init>":(Ljava/lang/Object;)V
const #124 = Asciz	scala/collection/JavaConversions$MutableMapWrapper$$anon$1$$anon$4$$anon$5;
const #125 = class	#124;	//  scala/collection/JavaConversions$MutableMapWrapper$$anon$1$$anon$4$$anon$5
const #126 = Asciz	(Lscala/collection/JavaConversions$MutableMapWrapper$$anon$1$$anon$4;Ljava/lang/Object;Ljava/lang/Object;)V;
const #127 = NameAndType	#12:#126;//  "<init>":(Lscala/collection/JavaConversions$MutableMapWrapper$$anon$1$$anon$4;Ljava/lang/Object;Ljava/lang/Object;)V
const #128 = Method	#125.#127;	//  scala/collection/JavaConversions$MutableMapWrapper$$anon$1$$anon$4$$anon$5."<init>":(Lscala/collection/JavaConversions$MutableMapWrapper$$anon$1$$anon$4;Ljava/lang/Object;Ljava/lang/Object;)V
const #129 = Method	#111.#88;	//  scala/Tuple2.toString:()Ljava/lang/String;
const #130 = Asciz	temp83;
const #131 = Asciz	temp84;
const #132 = Asciz	k$1;
const #133 = Asciz	v$1;
const #134 = Asciz	temp82;
const #135 = Asciz	Lscala/Tuple2;;
const #136 = Asciz	hasNext;
const #137 = Asciz	()Z;
const #138 = NameAndType	#136:#137;//  hasNext:()Z
const #139 = InterfaceMethod	#107.#138;	//  scala/collection/Iterator.hasNext:()Z
const #140 = Asciz	(Lscala/Option<TA;>;)V;
const #141 = Asciz	()Lscala/Option<TA;>;;
const #142 = Asciz	()Lscala/collection/Iterator<Lscala/Tuple2<TA;TB;>;>;;
const #143 = Asciz	Ljava/lang/Object;Ljava/util/Iterator<Ljava/util/Map$Entry<TA;TB;>;>;;
const #144 = Asciz	Scala;
const #145 = Asciz	InnerClasses;
const #146 = Asciz	scala/collection/JavaConversions;
const #147 = class	#146;	//  scala/collection/JavaConversions
const #148 = Asciz	MutableMapWrapper;
const #149 = Asciz	$anon$1;
const #150 = Asciz	$anon$4;
const #151 = Asciz	$anon$5;
const #152 = Asciz	java/util/Iterator;
const #153 = class	#152;	//  java/util/Iterator

{
public scala.collection.JavaConversions$MutableMapWrapper$$anon$1$$anon$4(scala.collection.JavaConversions$MutableMapWrapper$$anon$1);
  Code:
   Stack=2, Locals=2, Args_size=2
   0:	aload_1
   1:	ifnonnull	12
   4:	new	#17; //class java/lang/NullPointerException
   7:	dup
   8:	invokespecial	#20; //Method java/lang/NullPointerException."<init>":()V
   11:	athrow
   12:	aload_0
   13:	aload_1
   14:	putfield	#24; //Field $outer:Lscala/collection/JavaConversions$MutableMapWrapper$$anon$1;
   17:	aload_0
   18:	invokespecial	#27; //Method java/lang/Object."<init>":()V
   21:	aload_0
   22:	aload_1
   23:	invokevirtual	#33; //Method scala/collection/JavaConversions$MutableMapWrapper$$anon$1.scala$collection$JavaConversions$MutableMapWrapper$$anon$$$outer:()Lscala/collection/JavaConversions$MutableMapWrapper;
   26:	invokevirtual	#39; //Method scala/collection/JavaConversions$MutableMapWrapper.underlying:()Lscala/collection/mutable/Map;
   29:	invokeinterface	#45,  1; //InterfaceMethod scala/collection/MapLike.iterator:()Lscala/collection/Iterator;
   34:	putfield	#47; //Field ui:Lscala/collection/Iterator;
   37:	aload_0
   38:	getstatic	#53; //Field scala/None$.MODULE$:Lscala/None$;
   41:	putfield	#55; //Field prev:Lscala/Option;
   44:	return
  LineNumberTable: 
   line 437: 0
   line 438: 21
   line 439: 37

  LocalVariableTable: 
   Start  Length  Slot  Name   Signature
   0      45      0    this       Lscala/collection/JavaConversions$MutableMapWrapper$$anon$1$$anon$4;
   0      45      1    $outer       Lscala/collection/JavaConversions$MutableMapWrapper$$anon$1;

  Signature: length = 0x2
   00 3B 

public scala.collection.JavaConversions$MutableMapWrapper$$anon$1 scala$collection$JavaConversions$MutableMapWrapper$$anon$$anon$$$outer();
  Code:
   Stack=1, Locals=1, Args_size=1
   0:	aload_0
   1:	getfield	#24; //Field $outer:Lscala/collection/JavaConversions$MutableMapWrapper$$anon$1;
   4:	areturn
  LineNumberTable: 
   line 437: 0


public void remove();
  Code:
   Stack=3, Locals=5, Args_size=1
   0:	aload_0
   1:	invokespecial	#65; //Method prev:()Lscala/Option;
   4:	astore	4
   6:	aload	4
   8:	instanceof	#67; //class scala/Some
   11:	ifeq	64
   14:	aload	4
   16:	checkcast	#67; //class scala/Some
   19:	astore_1
   20:	aload_1
   21:	getfield	#71; //Field scala/Some.x:Ljava/lang/Object;
   24:	astore_3
   25:	iconst_1
   26:	ifeq	51
   29:	aload_0
   30:	getfield	#24; //Field $outer:Lscala/collection/JavaConversions$MutableMapWrapper$$anon$1;
   33:	astore_2
   34:	aload_2
   35:	getfield	#74; //Field scala/collection/JavaConversions$MutableMapWrapper$$anon$1.$outer:Lscala/collection/JavaConversions$MutableMapWrapper;
   38:	aload_3
   39:	invokevirtual	#77; //Method scala/collection/JavaConversions$MutableMapWrapper.remove:(Ljava/lang/Object;)Ljava/lang/Object;
   42:	pop
   43:	aload_0
   44:	getstatic	#53; //Field scala/None$.MODULE$:Lscala/None$;
   47:	invokespecial	#81; //Method prev_$eq:(Lscala/Option;)V
   50:	return
   51:	new	#83; //class scala/MatchError
   54:	dup
   55:	aload	4
   57:	invokevirtual	#89; //Method scala/Option.toString:()Ljava/lang/String;
   60:	invokespecial	#92; //Method scala/MatchError."<init>":(Ljava/lang/String;)V
   63:	athrow
   64:	iconst_1
   65:	ifeq	78
   68:	new	#94; //class java/lang/IllegalStateException
   71:	dup
   72:	ldc	#96; //String next must be called at least once before remove
   74:	invokespecial	#97; //Method java/lang/IllegalStateException."<init>":(Ljava/lang/String;)V
   77:	athrow
   78:	new	#83; //class scala/MatchError
   81:	dup
   82:	aload	4
   84:	invokevirtual	#89; //Method scala/Option.toString:()Ljava/lang/String;
   87:	invokespecial	#92; //Method scala/MatchError."<init>":(Ljava/lang/String;)V
   90:	athrow
  LineNumberTable: 
   line 457: 0
   line 21: 25
   line 458: 29
   line 457: 50
   line 21: 64
   line 459: 68
   line 457: 78

  LocalVariableTable: 
   Start  Length  Slot  Name   Signature
   0      91      0    this       Lscala/collection/JavaConversions$MutableMapWrapper$$anon$1$$anon$4;
   20      44      1    temp88       Lscala/Some;
   25      39      3    temp89       Ljava/lang/Object;
   6      85      4    temp87       Lscala/Option;


public java.lang.Object next();
  Code:
   Stack=5, Locals=7, Args_size=1
   0:	aload_0
   1:	invokespecial	#105; //Method ui:()Lscala/collection/Iterator;
   4:	invokeinterface	#109,  1; //InterfaceMethod scala/collection/Iterator.next:()Ljava/lang/Object;
   9:	checkcast	#111; //class scala/Tuple2
   12:	astore	6
   14:	aload	6
   16:	ifnull	96
   19:	aload	6
   21:	invokevirtual	#114; //Method scala/Tuple2._1:()Ljava/lang/Object;
   24:	astore_1
   25:	aload	6
   27:	invokevirtual	#117; //Method scala/Tuple2._2:()Ljava/lang/Object;
   30:	astore_2
   31:	iconst_1
   32:	ifeq	83
   35:	new	#111; //class scala/Tuple2
   38:	dup
   39:	aload_1
   40:	aload_2
   41:	invokespecial	#120; //Method scala/Tuple2."<init>":(Ljava/lang/Object;Ljava/lang/Object;)V
   44:	astore_3
   45:	aload_3
   46:	invokevirtual	#114; //Method scala/Tuple2._1:()Ljava/lang/Object;
   49:	astore	4
   51:	aload_3
   52:	invokevirtual	#117; //Method scala/Tuple2._2:()Ljava/lang/Object;
   55:	astore	5
   57:	aload_0
   58:	new	#67; //class scala/Some
   61:	dup
   62:	aload	4
   64:	invokespecial	#123; //Method scala/Some."<init>":(Ljava/lang/Object;)V
   67:	invokespecial	#81; //Method prev_$eq:(Lscala/Option;)V
   70:	new	#125; //class scala/collection/JavaConversions$MutableMapWrapper$$anon$1$$anon$4$$anon$5
   73:	dup
   74:	aload_0
   75:	aload	4
   77:	aload	5
   79:	invokespecial	#128; //Method scala/collection/JavaConversions$MutableMapWrapper$$anon$1$$anon$4$$anon$5."<init>":(Lscala/collection/JavaConversions$MutableMapWrapper$$anon$1$$anon$4;Ljava/lang/Object;Ljava/lang/Object;)V
   82:	areturn
   83:	new	#83; //class scala/MatchError
   86:	dup
   87:	aload	6
   89:	invokevirtual	#129; //Method scala/Tuple2.toString:()Ljava/lang/String;
   92:	invokespecial	#92; //Method scala/MatchError."<init>":(Ljava/lang/String;)V
   95:	athrow
   96:	new	#83; //class scala/MatchError
   99:	dup
   100:	aload	6
   102:	invokevirtual	#129; //Method scala/Tuple2.toString:()Ljava/lang/String;
   105:	invokespecial	#92; //Method scala/MatchError."<init>":(Ljava/lang/String;)V
   108:	athrow
  LineNumberTable: 
   line 444: 0
   line 21: 31
   line 444: 35
   line 445: 57
   line 446: 70
   line 444: 83

  LocalVariableTable: 
   Start  Length  Slot  Name   Signature
   0      109      0    this       Lscala/collection/JavaConversions$MutableMapWrapper$$anon$1$$anon$4;
   25      71      1    temp83       Ljava/lang/Object;
   31      65      2    temp84       Ljava/lang/Object;
   51      31      4    k$1       Ljava/lang/Object;
   57      25      5    v$1       Ljava/lang/Object;
   14      95      6    temp82       Lscala/Tuple2;


public boolean hasNext();
  Code:
   Stack=1, Locals=1, Args_size=1
   0:	aload_0
   1:	invokespecial	#105; //Method ui:()Lscala/collection/Iterator;
   4:	invokeinterface	#139,  1; //InterfaceMethod scala/collection/Iterator.hasNext:()Z
   9:	ireturn
  LineNumberTable: 
   line 441: 0


}

