Compiled from "JavaConversions.scala"
public abstract class scala.collection.JavaConversions$JMapWrapperLike$class extends java.lang.Object
  SourceFile: "JavaConversions.scala"
  Scala: length = 0x
   
  InnerClass: 
   public abstract JMapWrapperLike=class scala/collection/JavaConversions$JMapWrapperLike of class scala/collection/JavaConversions
   public final $anon$2=class scala/collection/JavaConversions$JMapWrapperLike$$anon$2 of class scala/collection/JavaConversions$JMapWrapperLike
  minor version: 0
  major version: 49
  Constant pool:
Asciz	SourceFile;
Asciz	JavaConversions.scala;
Asciz	size;
Asciz	(Lscala/collection/JavaConversions$JMapWrapperLike;)I;
Asciz	Code;
Asciz	LineNumberTable;
Asciz	scala/collection/JavaConversions$JMapWrapperLike;
class	scala/collection/JavaConversions$JMapWrapperLike
Asciz	underlying;
Asciz	()Ljava/util/Map;;
NameAndType	underlying:()Ljava/util/Map;
InterfaceMethod	scala/collection/JavaConversions$JMapWrapperLike.underlying:()Ljava/util/Map;
Asciz	java/util/Map;
class	java/util/Map
Asciz	()I;
NameAndType	size:()I
InterfaceMethod	java/util/Map.size:()I
Asciz	$this;
Asciz	Lscala/collection/JavaConversions$JMapWrapperLike;;
Asciz	LocalVariableTable;
Asciz	get;
Asciz	(Lscala/collection/JavaConversions$JMapWrapperLike;Ljava/lang/Object;)Lscala/Option;;
Asciz	(Ljava/lang/Object;)Ljava/lang/Object;;
NameAndType	get:(Ljava/lang/Object;)Ljava/lang/Object;
InterfaceMethod	java/util/Map.get:(Ljava/lang/Object;)Ljava/lang/Object;
Asciz	java/lang/Object;
class	java/lang/Object
Asciz	equals;
Asciz	(Ljava/lang/Object;)Z;
NameAndType	equals:(Ljava/lang/Object;)Z
Method	java/lang/Object.equals:(Ljava/lang/Object;)Z
Asciz	containsKey;
NameAndType	containsKey:(Ljava/lang/Object;)Z
InterfaceMethod	java/util/Map.containsKey:(Ljava/lang/Object;)Z
Asciz	scala/Some;
class	scala/Some
Asciz	<init>;
Asciz	(Ljava/lang/Object;)V;
NameAndType	"<init>":(Ljava/lang/Object;)V
Method	scala/Some."<init>":(Ljava/lang/Object;)V
Asciz	scala/None$;
class	scala/None$
Asciz	MODULE$;
Asciz	Lscala/None$;;
NameAndType	MODULE$:Lscala/None$;
Field	scala/None$.MODULE$:Lscala/None$;
Asciz	k;
Asciz	Ljava/lang/Object;;
Asciz	v;
Asciz	$plus$eq;
Asciz	(Lscala/collection/JavaConversions$JMapWrapperLike;Lscala/Tuple2;)Lscala/collection/JavaConversions$JMapWrapperLike;;
Asciz	scala/Tuple2;
class	scala/Tuple2
Asciz	_1;
Asciz	()Ljava/lang/Object;;
NameAndType	_1:()Ljava/lang/Object;
Method	scala/Tuple2._1:()Ljava/lang/Object;
Asciz	_2;
NameAndType	_2:()Ljava/lang/Object;
Method	scala/Tuple2._2:()Ljava/lang/Object;
Asciz	put;
Asciz	(Ljava/lang/Object;Ljava/lang/Object;)Ljava/lang/Object;;
NameAndType	put:(Ljava/lang/Object;Ljava/lang/Object;)Ljava/lang/Object;
InterfaceMethod	java/util/Map.put:(Ljava/lang/Object;Ljava/lang/Object;)Ljava/lang/Object;
Asciz	kv;
Asciz	Lscala/Tuple2;;
Asciz	$minus$eq;
Asciz	(Lscala/collection/JavaConversions$JMapWrapperLike;Ljava/lang/Object;)Lscala/collection/JavaConversions$JMapWrapperLike;;
Asciz	remove;
NameAndType	remove:(Ljava/lang/Object;)Ljava/lang/Object;
InterfaceMethod	java/util/Map.remove:(Ljava/lang/Object;)Ljava/lang/Object;
Asciz	key;
Asciz	(Lscala/collection/JavaConversions$JMapWrapperLike;Ljava/lang/Object;Ljava/lang/Object;)Lscala/Option;;
Asciz	r;
Asciz	update;
Asciz	(Lscala/collection/JavaConversions$JMapWrapperLike;Ljava/lang/Object;Ljava/lang/Object;)V;
Asciz	iterator;
Asciz	(Lscala/collection/JavaConversions$JMapWrapperLike;)Lscala/collection/Iterator;;
Asciz	scala/collection/JavaConversions$JMapWrapperLike$$anon$2;
class	scala/collection/JavaConversions$JMapWrapperLike$$anon$2
Asciz	(Lscala/collection/JavaConversions$JMapWrapperLike;)V;
NameAndType	"<init>":(Lscala/collection/JavaConversions$JMapWrapperLike;)V
Method	scala/collection/JavaConversions$JMapWrapperLike$$anon$2."<init>":(Lscala/collection/JavaConversions$JMapWrapperLike;)V
Asciz	clear;
Asciz	()V;
NameAndType	clear:()V
InterfaceMethod	java/util/Map.clear:()V
Asciz	empty;
Asciz	(Lscala/collection/JavaConversions$JMapWrapperLike;)Lscala/collection/mutable/Map;;
Asciz	$init$;
Asciz	Scala;
Asciz	InnerClasses;
Asciz	scala/collection/JavaConversions;
class	scala/collection/JavaConversions
Asciz	JMapWrapperLike;
Asciz	$anon$2;
Asciz	scala/collection/JavaConversions$JMapWrapperLike$class;
class	scala/collection/JavaConversions$JMapWrapperLike$class

{
public static int size(scala.collection.JavaConversions$JMapWrapperLike);
  Signature: (Lscala/collection/JavaConversions$JMapWrapperLike;)I
  Code:
   Stack=1, Locals=1, Args_size=1
	aload_0
	invokeinterface	InterfaceMethod scala/collection/JavaConversions$JMapWrapperLike.underlying:()Ljava/util/Map;
	invokeinterface	InterfaceMethod java/util/Map.size:()I
	ireturn
  Labels:
  LocalVariableTable: 
   Start  Length  Slot  Name   Signature
   0      12      0    $this       Lscala/collection/JavaConversions$JMapWrapperLike;


public static scala.Option get(scala.collection.JavaConversions$JMapWrapperLike, java.lang.Object);
  Signature: (Lscala/collection/JavaConversions$JMapWrapperLike;Ljava/lang/Object;)Lscala/Option;
  Code:
   Stack=3, Locals=3, Args_size=2
	aload_0
	invokeinterface	InterfaceMethod scala/collection/JavaConversions$JMapWrapperLike.underlying:()Ljava/util/Map;
	aload_1
	invokeinterface	InterfaceMethod java/util/Map.get:(Ljava/lang/Object;)Ljava/lang/Object;
	astore_2
	aload_2
	dup
	pop
	ifnull	l1 // aload_0
	aload_2
	aconst_null
	invokevirtual	Method java/lang/Object.equals:(Ljava/lang/Object;)Z
	ifeq	l2 // new
l1	aload_0
	invokeinterface	InterfaceMethod scala/collection/JavaConversions$JMapWrapperLike.underlying:()Ljava/util/Map;
	aload_1
	invokeinterface	InterfaceMethod java/util/Map.containsKey:(Ljava/lang/Object;)Z
	ifeq	l3 // getstatic
	new	class scala/Some
	dup
	aconst_null
	invokespecial	Method scala/Some."<init>":(Ljava/lang/Object;)V
	goto	l4 // areturn
l3	getstatic	Field scala/None$.MODULE$:Lscala/None$;
	goto	l4 // areturn
l2	new	class scala/Some
	dup
	aload_2
	invokespecial	Method scala/Some."<init>":(Ljava/lang/Object;)V
l4	areturn
  Labels:
   	l1 = 27 // aload_0
   	l3 = 53 // getstatic
   	l2 = 59 // new
   	l4 = 67 // areturn
  LocalVariableTable: 
   Start  Length  Slot  Name   Signature
   0      68      0    $this       Lscala/collection/JavaConversions$JMapWrapperLike;
   0      68      1    k       Ljava/lang/Object;
   13      55      2    v       Ljava/lang/Object;


public static scala.collection.JavaConversions$JMapWrapperLike $plus$eq(scala.collection.JavaConversions$JMapWrapperLike, scala.Tuple2);
  Signature: (Lscala/collection/JavaConversions$JMapWrapperLike;Lscala/Tuple2;)Lscala/collection/JavaConversions$JMapWrapperLike;
  Code:
   Stack=3, Locals=2, Args_size=2
	aload_0
	invokeinterface	InterfaceMethod scala/collection/JavaConversions$JMapWrapperLike.underlying:()Ljava/util/Map;
	aload_1
	invokevirtual	Method scala/Tuple2._1:()Ljava/lang/Object;
	aload_1
	invokevirtual	Method scala/Tuple2._2:()Ljava/lang/Object;
	invokeinterface	InterfaceMethod java/util/Map.put:(Ljava/lang/Object;Ljava/lang/Object;)Ljava/lang/Object;
	pop
	aload_0
	areturn
  Labels:
  LocalVariableTable: 
   Start  Length  Slot  Name   Signature
   0      22      0    $this       Lscala/collection/JavaConversions$JMapWrapperLike;
   0      22      1    kv       Lscala/Tuple2;


public static scala.collection.JavaConversions$JMapWrapperLike $minus$eq(scala.collection.JavaConversions$JMapWrapperLike, java.lang.Object);
  Signature: (Lscala/collection/JavaConversions$JMapWrapperLike;Ljava/lang/Object;)Lscala/collection/JavaConversions$JMapWrapperLike;
  Code:
   Stack=2, Locals=2, Args_size=2
	aload_0
	invokeinterface	InterfaceMethod scala/collection/JavaConversions$JMapWrapperLike.underlying:()Ljava/util/Map;
	aload_1
	invokeinterface	InterfaceMethod java/util/Map.remove:(Ljava/lang/Object;)Ljava/lang/Object;
	pop
	aload_0
	areturn
  Labels:
  LocalVariableTable: 
   Start  Length  Slot  Name   Signature
   0      15      0    $this       Lscala/collection/JavaConversions$JMapWrapperLike;
   0      15      1    key       Ljava/lang/Object;


public static scala.Option put(scala.collection.JavaConversions$JMapWrapperLike, java.lang.Object, java.lang.Object);
  Signature: (Lscala/collection/JavaConversions$JMapWrapperLike;Ljava/lang/Object;Ljava/lang/Object;)Lscala/Option;
  Code:
   Stack=3, Locals=4, Args_size=3
	aload_0
	invokeinterface	InterfaceMethod scala/collection/JavaConversions$JMapWrapperLike.underlying:()Ljava/util/Map;
	aload_1
	aload_2
	invokeinterface	InterfaceMethod java/util/Map.put:(Ljava/lang/Object;Ljava/lang/Object;)Ljava/lang/Object;
	astore_3
	aload_3
	dup
	pop
	ifnull	l1 // getstatic
	aload_3
	aconst_null
	invokevirtual	Method java/lang/Object.equals:(Ljava/lang/Object;)Z
	ifeq	l2 // new
l1	getstatic	Field scala/None$.MODULE$:Lscala/None$;
	goto	l3 // areturn
l2	new	class scala/Some
	dup
	aload_3
	invokespecial	Method scala/Some."<init>":(Ljava/lang/Object;)V
l3	areturn
  Labels:
   	l1 = 28 // getstatic
   	l2 = 34 // new
   	l3 = 42 // areturn
  LocalVariableTable: 
   Start  Length  Slot  Name   Signature
   0      43      0    $this       Lscala/collection/JavaConversions$JMapWrapperLike;
   0      43      1    k       Ljava/lang/Object;
   0      43      2    v       Ljava/lang/Object;
   14      29      3    r       Ljava/lang/Object;


public static void update(scala.collection.JavaConversions$JMapWrapperLike, java.lang.Object, java.lang.Object);
  Signature: (Lscala/collection/JavaConversions$JMapWrapperLike;Ljava/lang/Object;Ljava/lang/Object;)V
  Code:
   Stack=3, Locals=3, Args_size=3
	aload_0
	invokeinterface	InterfaceMethod scala/collection/JavaConversions$JMapWrapperLike.underlying:()Ljava/util/Map;
	aload_1
	aload_2
	invokeinterface	InterfaceMethod java/util/Map.put:(Ljava/lang/Object;Ljava/lang/Object;)Ljava/lang/Object;
	pop
	return
  Labels:
  LocalVariableTable: 
   Start  Length  Slot  Name   Signature
   0      15      0    $this       Lscala/collection/JavaConversions$JMapWrapperLike;
   0      15      1    k       Ljava/lang/Object;
   0      15      2    v       Ljava/lang/Object;


public static scala.Option remove(scala.collection.JavaConversions$JMapWrapperLike, java.lang.Object);
  Signature: (Lscala/collection/JavaConversions$JMapWrapperLike;Ljava/lang/Object;)Lscala/Option;
  Code:
   Stack=3, Locals=3, Args_size=2
	aload_0
	invokeinterface	InterfaceMethod scala/collection/JavaConversions$JMapWrapperLike.underlying:()Ljava/util/Map;
	aload_1
	invokeinterface	InterfaceMethod java/util/Map.remove:(Ljava/lang/Object;)Ljava/lang/Object;
	astore_2
	aload_2
	dup
	pop
	ifnull	l1 // getstatic
	aload_2
	aconst_null
	invokevirtual	Method java/lang/Object.equals:(Ljava/lang/Object;)Z
	ifeq	l2 // new
l1	getstatic	Field scala/None$.MODULE$:Lscala/None$;
	goto	l3 // areturn
l2	new	class scala/Some
	dup
	aload_2
	invokespecial	Method scala/Some."<init>":(Ljava/lang/Object;)V
l3	areturn
  Labels:
   	l1 = 27 // getstatic
   	l2 = 33 // new
   	l3 = 41 // areturn
  LocalVariableTable: 
   Start  Length  Slot  Name   Signature
   0      42      0    $this       Lscala/collection/JavaConversions$JMapWrapperLike;
   0      42      1    k       Ljava/lang/Object;
   13      29      2    r       Ljava/lang/Object;


public static scala.collection.Iterator iterator(scala.collection.JavaConversions$JMapWrapperLike);
  Signature: (Lscala/collection/JavaConversions$JMapWrapperLike;)Lscala/collection/Iterator;
  Code:
   Stack=3, Locals=1, Args_size=1
	new	class scala/collection/JavaConversions$JMapWrapperLike$$anon$2
	dup
	aload_0
	invokespecial	Method scala/collection/JavaConversions$JMapWrapperLike$$anon$2."<init>":(Lscala/collection/JavaConversions$JMapWrapperLike;)V
	areturn
  Labels:
  LocalVariableTable: 
   Start  Length  Slot  Name   Signature
   0      9      0    $this       Lscala/collection/JavaConversions$JMapWrapperLike;


public static void clear(scala.collection.JavaConversions$JMapWrapperLike);
  Signature: (Lscala/collection/JavaConversions$JMapWrapperLike;)V
  Code:
   Stack=1, Locals=1, Args_size=1
	aload_0
	invokeinterface	InterfaceMethod scala/collection/JavaConversions$JMapWrapperLike.underlying:()Ljava/util/Map;
	invokeinterface	InterfaceMethod java/util/Map.clear:()V
	return
  Labels:
  LocalVariableTable: 
   Start  Length  Slot  Name   Signature
   0      12      0    $this       Lscala/collection/JavaConversions$JMapWrapperLike;


public static scala.collection.mutable.Map empty(scala.collection.JavaConversions$JMapWrapperLike);
  Signature: (Lscala/collection/JavaConversions$JMapWrapperLike;)Lscala/collection/mutable/Map;
  Code:
   Stack=1, Locals=1, Args_size=1
	aconst_null
	areturn
  Labels:
  LocalVariableTable: 
   Start  Length  Slot  Name   Signature
   0      2      0    $this       Lscala/collection/JavaConversions$JMapWrapperLike;


public static void $init$(scala.collection.JavaConversions$JMapWrapperLike);
  Signature: (Lscala/collection/JavaConversions$JMapWrapperLike;)V
  Code:
   Stack=0, Locals=1, Args_size=1
	return
  Labels:
  LocalVariableTable: 
   Start  Length  Slot  Name   Signature
   0      1      0    $this       Lscala/collection/JavaConversions$JMapWrapperLike;


}

