Compiled from "JavaConversions.scala"
public class scala.collection.JavaConversions$JConcurrentMapWrapper extends java.lang.Object implements scala.collection.JavaConversions$JMapWrapperLike,scala.collection.mutable.ConcurrentMap,scala.ScalaObject,scala.Product,java.io.Serializable
  SourceFile: "JavaConversions.scala"
  Signature: length = 0x2
   03 FFFFFFB0 
  Scala: length = 0x
   
  InnerClass: 
   public abstract $less$colon$less=class scala/Predef$$less$colon$less of class scala/Predef
   public WithFilter=class scala/collection/TraversableLike$WithFilter of class scala/collection/TraversableLike
   public abstract JMapWrapperLike=class scala/collection/JavaConversions$JMapWrapperLike of class scala/collection/JavaConversions
   public JConcurrentMapWrapper=class scala/collection/JavaConversions$JConcurrentMapWrapper of class scala/collection/JavaConversions
  minor version: 0
  major version: 49
  Constant pool:
Asciz	SourceFile;
Asciz	JavaConversions.scala;
Asciz	underlying;
Asciz	Ljava/util/concurrent/ConcurrentMap;;
Asciz	Ljava/util/concurrent/ConcurrentMap<TA;TB;>;;
Asciz	Signature;
Asciz	productElementName;
Asciz	(I)Ljava/lang/String;;
Asciz	Code;
Asciz	LineNumberTable;
Asciz	scala/Product$class;
class	scala/Product$class
Asciz	(Lscala/Product;I)Ljava/lang/String;;
NameAndType	productElementName:(Lscala/Product;I)Ljava/lang/String;
Method	scala/Product$class.productElementName:(Lscala/Product;I)Ljava/lang/String;
Asciz	this;
Asciz	Lscala/collection/JavaConversions$JConcurrentMapWrapper;;
Asciz	n;
Asciz	I;
Asciz	LocalVariableTable;
Asciz	productIterator;
Asciz	()Lscala/collection/Iterator;;
Asciz	(Lscala/Product;)Lscala/collection/Iterator;;
NameAndType	productIterator:(Lscala/Product;)Lscala/collection/Iterator;
Method	scala/Product$class.productIterator:(Lscala/Product;)Lscala/collection/Iterator;
Asciz	productElements;
NameAndType	productElements:(Lscala/Product;)Lscala/collection/Iterator;
Method	scala/Product$class.productElements:(Lscala/Product;)Lscala/collection/Iterator;
Asciz	Deprecated;
Asciz	size;
Asciz	()I;
Asciz	scala/collection/JavaConversions$JMapWrapperLike$class;
class	scala/collection/JavaConversions$JMapWrapperLike$class
Asciz	(Lscala/collection/JavaConversions$JMapWrapperLike;)I;
NameAndType	size:(Lscala/collection/JavaConversions$JMapWrapperLike;)I
Method	scala/collection/JavaConversions$JMapWrapperLike$class.size:(Lscala/collection/JavaConversions$JMapWrapperLike;)I
Asciz	$plus$eq;
Asciz	(Lscala/Tuple2;)Lscala/collection/JavaConversions$JMapWrapperLike;;
Asciz	(Lscala/collection/JavaConversions$JMapWrapperLike;Lscala/Tuple2;)Lscala/collection/JavaConversions$JMapWrapperLike;;
NameAndType	$plus$eq:(Lscala/collection/JavaConversions$JMapWrapperLike;Lscala/Tuple2;)Lscala/collection/JavaConversions$JMapWrapperLike;
Method	scala/collection/JavaConversions$JMapWrapperLike$class.$plus$eq:(Lscala/collection/JavaConversions$JMapWrapperLike;Lscala/Tuple2;)Lscala/collection/JavaConversions$JMapWrapperLike;
Asciz	kv;
Asciz	Lscala/Tuple2;;
Asciz	$minus$eq;
Asciz	(Ljava/lang/Object;)Lscala/collection/JavaConversions$JMapWrapperLike;;
Asciz	(Lscala/collection/JavaConversions$JMapWrapperLike;Ljava/lang/Object;)Lscala/collection/JavaConversions$JMapWrapperLike;;
NameAndType	$minus$eq:(Lscala/collection/JavaConversions$JMapWrapperLike;Ljava/lang/Object;)Lscala/collection/JavaConversions$JMapWrapperLike;
Method	scala/collection/JavaConversions$JMapWrapperLike$class.$minus$eq:(Lscala/collection/JavaConversions$JMapWrapperLike;Ljava/lang/Object;)Lscala/collection/JavaConversions$JMapWrapperLike;
Asciz	key;
Asciz	Ljava/lang/Object;;
Asciz	put;
Asciz	(Ljava/lang/Object;Ljava/lang/Object;)Lscala/Option;;
Asciz	(Lscala/collection/JavaConversions$JMapWrapperLike;Ljava/lang/Object;Ljava/lang/Object;)Lscala/Option;;
NameAndType	put:(Lscala/collection/JavaConversions$JMapWrapperLike;Ljava/lang/Object;Ljava/lang/Object;)Lscala/Option;
Method	scala/collection/JavaConversions$JMapWrapperLike$class.put:(Lscala/collection/JavaConversions$JMapWrapperLike;Ljava/lang/Object;Ljava/lang/Object;)Lscala/Option;
Asciz	k;
Asciz	v;
Asciz	update;
Asciz	(Ljava/lang/Object;Ljava/lang/Object;)V;
Asciz	(Lscala/collection/JavaConversions$JMapWrapperLike;Ljava/lang/Object;Ljava/lang/Object;)V;
NameAndType	update:(Lscala/collection/JavaConversions$JMapWrapperLike;Ljava/lang/Object;Ljava/lang/Object;)V
Method	scala/collection/JavaConversions$JMapWrapperLike$class.update:(Lscala/collection/JavaConversions$JMapWrapperLike;Ljava/lang/Object;Ljava/lang/Object;)V
Asciz	remove;
Asciz	(Ljava/lang/Object;)Lscala/Option;;
Asciz	(Lscala/collection/JavaConversions$JMapWrapperLike;Ljava/lang/Object;)Lscala/Option;;
NameAndType	remove:(Lscala/collection/JavaConversions$JMapWrapperLike;Ljava/lang/Object;)Lscala/Option;
Method	scala/collection/JavaConversions$JMapWrapperLike$class.remove:(Lscala/collection/JavaConversions$JMapWrapperLike;Ljava/lang/Object;)Lscala/Option;
Asciz	iterator;
Asciz	(Lscala/collection/JavaConversions$JMapWrapperLike;)Lscala/collection/Iterator;;
NameAndType	iterator:(Lscala/collection/JavaConversions$JMapWrapperLike;)Lscala/collection/Iterator;
Method	scala/collection/JavaConversions$JMapWrapperLike$class.iterator:(Lscala/collection/JavaConversions$JMapWrapperLike;)Lscala/collection/Iterator;
Asciz	clear;
Asciz	()V;
Asciz	(Lscala/collection/JavaConversions$JMapWrapperLike;)V;
NameAndType	clear:(Lscala/collection/JavaConversions$JMapWrapperLike;)V
Method	scala/collection/JavaConversions$JMapWrapperLike$class.clear:(Lscala/collection/JavaConversions$JMapWrapperLike;)V
Asciz	newBuilder;
Asciz	()Lscala/collection/mutable/Builder;;
Asciz	scala/collection/mutable/MapLike$class;
class	scala/collection/mutable/MapLike$class
Asciz	(Lscala/collection/mutable/MapLike;)Lscala/collection/mutable/Builder;;
NameAndType	newBuilder:(Lscala/collection/mutable/MapLike;)Lscala/collection/mutable/Builder;
Method	scala/collection/mutable/MapLike$class.newBuilder:(Lscala/collection/mutable/MapLike;)Lscala/collection/mutable/Builder;
Asciz	updated;
Asciz	(Ljava/lang/Object;Ljava/lang/Object;)Lscala/collection/mutable/Map;;
Asciz	(Lscala/collection/mutable/MapLike;Ljava/lang/Object;Ljava/lang/Object;)Lscala/collection/mutable/Map;;
NameAndType	updated:(Lscala/collection/mutable/MapLike;Ljava/lang/Object;Ljava/lang/Object;)Lscala/collection/mutable/Map;
Method	scala/collection/mutable/MapLike$class.updated:(Lscala/collection/mutable/MapLike;Ljava/lang/Object;Ljava/lang/Object;)Lscala/collection/mutable/Map;
Asciz	value;
Asciz	$plus;
Asciz	(Lscala/Tuple2;)Lscala/collection/mutable/Map;;
Asciz	(Lscala/collection/mutable/MapLike;Lscala/Tuple2;)Lscala/collection/mutable/Map;;
NameAndType	$plus:(Lscala/collection/mutable/MapLike;Lscala/Tuple2;)Lscala/collection/mutable/Map;
Method	scala/collection/mutable/MapLike$class.$plus:(Lscala/collection/mutable/MapLike;Lscala/Tuple2;)Lscala/collection/mutable/Map;
Asciz	(Lscala/Tuple2;Lscala/Tuple2;Lscala/collection/Seq;)Lscala/collection/mutable/Map;;
Asciz	(Lscala/collection/mutable/MapLike;Lscala/Tuple2;Lscala/Tuple2;Lscala/collection/Seq;)Lscala/collection/mutable/Map;;
NameAndType	$plus:(Lscala/collection/mutable/MapLike;Lscala/Tuple2;Lscala/Tuple2;Lscala/collection/Seq;)Lscala/collection/mutable/Map;
Method	scala/collection/mutable/MapLike$class.$plus:(Lscala/collection/mutable/MapLike;Lscala/Tuple2;Lscala/Tuple2;Lscala/collection/Seq;)Lscala/collection/mutable/Map;
Asciz	elem1;
Asciz	elem2;
Asciz	elems;
Asciz	Lscala/collection/Seq;;
Asciz	$plus$plus;
Asciz	(Lscala/collection/Traversable;)Lscala/collection/mutable/Map;;
Asciz	(Lscala/collection/mutable/MapLike;Lscala/collection/Traversable;)Lscala/collection/mutable/Map;;
NameAndType	$plus$plus:(Lscala/collection/mutable/MapLike;Lscala/collection/Traversable;)Lscala/collection/mutable/Map;
Method	scala/collection/mutable/MapLike$class.$plus$plus:(Lscala/collection/mutable/MapLike;Lscala/collection/Traversable;)Lscala/collection/mutable/Map;
Asciz	kvs;
Asciz	Lscala/collection/Traversable;;
Asciz	(Lscala/collection/Iterator;)Lscala/collection/mutable/Map;;
Asciz	(Lscala/collection/mutable/MapLike;Lscala/collection/Iterator;)Lscala/collection/mutable/Map;;
NameAndType	$plus$plus:(Lscala/collection/mutable/MapLike;Lscala/collection/Iterator;)Lscala/collection/mutable/Map;
Method	scala/collection/mutable/MapLike$class.$plus$plus:(Lscala/collection/mutable/MapLike;Lscala/collection/Iterator;)Lscala/collection/mutable/Map;
Asciz	iter;
Asciz	Lscala/collection/Iterator;;
Asciz	$minus;
Asciz	(Ljava/lang/Object;)Lscala/collection/mutable/Map;;
Asciz	(Lscala/collection/mutable/MapLike;Ljava/lang/Object;)Lscala/collection/mutable/Map;;
NameAndType	$minus:(Lscala/collection/mutable/MapLike;Ljava/lang/Object;)Lscala/collection/mutable/Map;
Method	scala/collection/mutable/MapLike$class.$minus:(Lscala/collection/mutable/MapLike;Ljava/lang/Object;)Lscala/collection/mutable/Map;
Asciz	removeKey;
Asciz	(Lscala/collection/mutable/MapLike;Ljava/lang/Object;)Lscala/Option;;
NameAndType	removeKey:(Lscala/collection/mutable/MapLike;Ljava/lang/Object;)Lscala/Option;
Method	scala/collection/mutable/MapLike$class.removeKey:(Lscala/collection/mutable/MapLike;Ljava/lang/Object;)Lscala/Option;
Asciz	getOrElseUpdate;
Asciz	(Ljava/lang/Object;Lscala/Function0;)Ljava/lang/Object;;
Asciz	(Lscala/collection/mutable/MapLike;Ljava/lang/Object;Lscala/Function0;)Ljava/lang/Object;;
NameAndType	getOrElseUpdate:(Lscala/collection/mutable/MapLike;Ljava/lang/Object;Lscala/Function0;)Ljava/lang/Object;
Method	scala/collection/mutable/MapLike$class.getOrElseUpdate:(Lscala/collection/mutable/MapLike;Ljava/lang/Object;Lscala/Function0;)Ljava/lang/Object;
Asciz	op;
Asciz	Lscala/Function0;;
Asciz	transform;
Asciz	(Lscala/Function2;)Lscala/collection/mutable/MapLike;;
Asciz	(Lscala/collection/mutable/MapLike;Lscala/Function2;)Lscala/collection/mutable/MapLike;;
NameAndType	transform:(Lscala/collection/mutable/MapLike;Lscala/Function2;)Lscala/collection/mutable/MapLike;
Method	scala/collection/mutable/MapLike$class.transform:(Lscala/collection/mutable/MapLike;Lscala/Function2;)Lscala/collection/mutable/MapLike;
Asciz	f;
Asciz	Lscala/Function2;;
Asciz	retain;
NameAndType	retain:(Lscala/collection/mutable/MapLike;Lscala/Function2;)Lscala/collection/mutable/MapLike;
Method	scala/collection/mutable/MapLike$class.retain:(Lscala/collection/mutable/MapLike;Lscala/Function2;)Lscala/collection/mutable/MapLike;
Asciz	p;
Asciz	clone;
Asciz	()Lscala/collection/mutable/Map;;
Asciz	(Lscala/collection/mutable/MapLike;)Lscala/collection/mutable/Map;;
NameAndType	clone:(Lscala/collection/mutable/MapLike;)Lscala/collection/mutable/Map;
Method	scala/collection/mutable/MapLike$class.clone:(Lscala/collection/mutable/MapLike;)Lscala/collection/mutable/Map;
Asciz	result;
NameAndType	result:(Lscala/collection/mutable/MapLike;)Lscala/collection/mutable/Map;
Method	scala/collection/mutable/MapLike$class.result:(Lscala/collection/mutable/MapLike;)Lscala/collection/mutable/Map;
Asciz	(Ljava/lang/Object;Ljava/lang/Object;Lscala/collection/Seq;)Lscala/collection/mutable/Map;;
Asciz	(Lscala/collection/mutable/MapLike;Ljava/lang/Object;Ljava/lang/Object;Lscala/collection/Seq;)Lscala/collection/mutable/Map;;
NameAndType	$minus:(Lscala/collection/mutable/MapLike;Ljava/lang/Object;Ljava/lang/Object;Lscala/collection/Seq;)Lscala/collection/mutable/Map;
Method	scala/collection/mutable/MapLike$class.$minus:(Lscala/collection/mutable/MapLike;Ljava/lang/Object;Ljava/lang/Object;Lscala/collection/Seq;)Lscala/collection/mutable/Map;
Asciz	$minus$minus;
NameAndType	$minus$minus:(Lscala/collection/mutable/MapLike;Lscala/collection/Traversable;)Lscala/collection/mutable/Map;
Method	scala/collection/mutable/MapLike$class.$minus$minus:(Lscala/collection/mutable/MapLike;Lscala/collection/Traversable;)Lscala/collection/mutable/Map;
NameAndType	$minus$minus:(Lscala/collection/mutable/MapLike;Lscala/collection/Iterator;)Lscala/collection/mutable/Map;
Method	scala/collection/mutable/MapLike$class.$minus$minus:(Lscala/collection/mutable/MapLike;Lscala/collection/Iterator;)Lscala/collection/mutable/Map;
Asciz	scala$collection$mutable$Cloneable$$super$clone;
Asciz	()Ljava/lang/Object;;
Asciz	java/lang/Object;
class	java/lang/Object
NameAndType	clone:()Ljava/lang/Object;
Method	java/lang/Object.clone:()Ljava/lang/Object;
Asciz	(Ljava/lang/Object;Ljava/lang/Object;Lscala/collection/Seq;)Lscala/collection/generic/Shrinkable;;
Asciz	scala/collection/generic/Shrinkable$class;
class	scala/collection/generic/Shrinkable$class
Asciz	(Lscala/collection/generic/Shrinkable;Ljava/lang/Object;Ljava/lang/Object;Lscala/collection/Seq;)Lscala/collection/generic/Shrinkable;;
NameAndType	$minus$eq:(Lscala/collection/generic/Shrinkable;Ljava/lang/Object;Ljava/lang/Object;Lscala/collection/Seq;)Lscala/collection/generic/Shrinkable;
Method	scala/collection/generic/Shrinkable$class.$minus$eq:(Lscala/collection/generic/Shrinkable;Ljava/lang/Object;Ljava/lang/Object;Lscala/collection/Seq;)Lscala/collection/generic/Shrinkable;
Asciz	$minus$minus$eq;
Asciz	(Lscala/collection/Iterator;)Lscala/collection/generic/Shrinkable;;
Asciz	(Lscala/collection/generic/Shrinkable;Lscala/collection/Iterator;)Lscala/collection/generic/Shrinkable;;
NameAndType	$minus$minus$eq:(Lscala/collection/generic/Shrinkable;Lscala/collection/Iterator;)Lscala/collection/generic/Shrinkable;
Method	scala/collection/generic/Shrinkable$class.$minus$minus$eq:(Lscala/collection/generic/Shrinkable;Lscala/collection/Iterator;)Lscala/collection/generic/Shrinkable;
Asciz	(Lscala/collection/Traversable;)Lscala/collection/generic/Shrinkable;;
Asciz	(Lscala/collection/generic/Shrinkable;Lscala/collection/Traversable;)Lscala/collection/generic/Shrinkable;;
NameAndType	$minus$minus$eq:(Lscala/collection/generic/Shrinkable;Lscala/collection/Traversable;)Lscala/collection/generic/Shrinkable;
Method	scala/collection/generic/Shrinkable$class.$minus$minus$eq:(Lscala/collection/generic/Shrinkable;Lscala/collection/Traversable;)Lscala/collection/generic/Shrinkable;
Asciz	sizeHint;
Asciz	(I)V;
Asciz	scala/collection/mutable/Builder$class;
class	scala/collection/mutable/Builder$class
Asciz	(Lscala/collection/mutable/Builder;I)V;
NameAndType	sizeHint:(Lscala/collection/mutable/Builder;I)V
Method	scala/collection/mutable/Builder$class.sizeHint:(Lscala/collection/mutable/Builder;I)V
Asciz	mapResult;
Asciz	(Lscala/Function1;)Lscala/collection/mutable/Builder;;
Asciz	(Lscala/collection/mutable/Builder;Lscala/Function1;)Lscala/collection/mutable/Builder;;
NameAndType	mapResult:(Lscala/collection/mutable/Builder;Lscala/Function1;)Lscala/collection/mutable/Builder;
Method	scala/collection/mutable/Builder$class.mapResult:(Lscala/collection/mutable/Builder;Lscala/Function1;)Lscala/collection/mutable/Builder;
Asciz	Lscala/Function1;;
Asciz	(Ljava/lang/Object;Ljava/lang/Object;Lscala/collection/Seq;)Lscala/collection/generic/Growable;;
Asciz	scala/collection/generic/Growable$class;
class	scala/collection/generic/Growable$class
Asciz	(Lscala/collection/generic/Growable;Ljava/lang/Object;Ljava/lang/Object;Lscala/collection/Seq;)Lscala/collection/generic/Growable;;
NameAndType	$plus$eq:(Lscala/collection/generic/Growable;Ljava/lang/Object;Ljava/lang/Object;Lscala/collection/Seq;)Lscala/collection/generic/Growable;
Method	scala/collection/generic/Growable$class.$plus$eq:(Lscala/collection/generic/Growable;Ljava/lang/Object;Ljava/lang/Object;Lscala/collection/Seq;)Lscala/collection/generic/Growable;
Asciz	$plus$plus$eq;
Asciz	(Lscala/collection/Iterator;)Lscala/collection/generic/Growable;;
Asciz	(Lscala/collection/generic/Growable;Lscala/collection/Iterator;)Lscala/collection/generic/Growable;;
NameAndType	$plus$plus$eq:(Lscala/collection/generic/Growable;Lscala/collection/Iterator;)Lscala/collection/generic/Growable;
Method	scala/collection/generic/Growable$class.$plus$plus$eq:(Lscala/collection/generic/Growable;Lscala/collection/Iterator;)Lscala/collection/generic/Growable;
Asciz	(Lscala/collection/Traversable;)Lscala/collection/generic/Growable;;
Asciz	(Lscala/collection/generic/Growable;Lscala/collection/Traversable;)Lscala/collection/generic/Growable;;
NameAndType	$plus$plus$eq:(Lscala/collection/generic/Growable;Lscala/collection/Traversable;)Lscala/collection/generic/Growable;
Method	scala/collection/generic/Growable$class.$plus$plus$eq:(Lscala/collection/generic/Growable;Lscala/collection/Traversable;)Lscala/collection/generic/Growable;
Asciz	isEmpty;
Asciz	()Z;
Asciz	scala/collection/MapLike$class;
class	scala/collection/MapLike$class
Asciz	(Lscala/collection/MapLike;)Z;
NameAndType	isEmpty:(Lscala/collection/MapLike;)Z
Method	scala/collection/MapLike$class.isEmpty:(Lscala/collection/MapLike;)Z
Asciz	getOrElse;
Asciz	(Lscala/collection/MapLike;Ljava/lang/Object;Lscala/Function0;)Ljava/lang/Object;;
NameAndType	getOrElse:(Lscala/collection/MapLike;Ljava/lang/Object;Lscala/Function0;)Ljava/lang/Object;
Method	scala/collection/MapLike$class.getOrElse:(Lscala/collection/MapLike;Ljava/lang/Object;Lscala/Function0;)Ljava/lang/Object;
Asciz	default;
Asciz	apply;
Asciz	(Ljava/lang/Object;)Ljava/lang/Object;;
Asciz	(Lscala/collection/MapLike;Ljava/lang/Object;)Ljava/lang/Object;;
NameAndType	apply:(Lscala/collection/MapLike;Ljava/lang/Object;)Ljava/lang/Object;
Method	scala/collection/MapLike$class.apply:(Lscala/collection/MapLike;Ljava/lang/Object;)Ljava/lang/Object;
Asciz	contains;
Asciz	(Ljava/lang/Object;)Z;
Asciz	(Lscala/collection/MapLike;Ljava/lang/Object;)Z;
NameAndType	contains:(Lscala/collection/MapLike;Ljava/lang/Object;)Z
Method	scala/collection/MapLike$class.contains:(Lscala/collection/MapLike;Ljava/lang/Object;)Z
Asciz	isDefinedAt;
NameAndType	isDefinedAt:(Lscala/collection/MapLike;Ljava/lang/Object;)Z
Method	scala/collection/MapLike$class.isDefinedAt:(Lscala/collection/MapLike;Ljava/lang/Object;)Z
Asciz	keySet;
Asciz	()Lscala/collection/Set;;
Asciz	(Lscala/collection/MapLike;)Lscala/collection/Set;;
NameAndType	keySet:(Lscala/collection/MapLike;)Lscala/collection/Set;
Method	scala/collection/MapLike$class.keySet:(Lscala/collection/MapLike;)Lscala/collection/Set;
Asciz	keysIterator;
Asciz	(Lscala/collection/MapLike;)Lscala/collection/Iterator;;
NameAndType	keysIterator:(Lscala/collection/MapLike;)Lscala/collection/Iterator;
Method	scala/collection/MapLike$class.keysIterator:(Lscala/collection/MapLike;)Lscala/collection/Iterator;
Asciz	keys;
Asciz	()Lscala/collection/Iterable;;
Asciz	(Lscala/collection/MapLike;)Lscala/collection/Iterable;;
NameAndType	keys:(Lscala/collection/MapLike;)Lscala/collection/Iterable;
Method	scala/collection/MapLike$class.keys:(Lscala/collection/MapLike;)Lscala/collection/Iterable;
Asciz	values;
NameAndType	values:(Lscala/collection/MapLike;)Lscala/collection/Iterable;
Method	scala/collection/MapLike$class.values:(Lscala/collection/MapLike;)Lscala/collection/Iterable;
Asciz	valuesIterator;
NameAndType	valuesIterator:(Lscala/collection/MapLike;)Lscala/collection/Iterator;
Method	scala/collection/MapLike$class.valuesIterator:(Lscala/collection/MapLike;)Lscala/collection/Iterator;
NameAndType	default:(Lscala/collection/MapLike;Ljava/lang/Object;)Ljava/lang/Object;
Method	scala/collection/MapLike$class.default:(Lscala/collection/MapLike;Ljava/lang/Object;)Ljava/lang/Object;
Asciz	filterKeys;
Asciz	(Lscala/Function1;)Lscala/collection/Map;;
Asciz	(Lscala/collection/MapLike;Lscala/Function1;)Lscala/collection/Map;;
NameAndType	filterKeys:(Lscala/collection/MapLike;Lscala/Function1;)Lscala/collection/Map;
Method	scala/collection/MapLike$class.filterKeys:(Lscala/collection/MapLike;Lscala/Function1;)Lscala/collection/Map;
Asciz	mapValues;
NameAndType	mapValues:(Lscala/collection/MapLike;Lscala/Function1;)Lscala/collection/Map;
Method	scala/collection/MapLike$class.mapValues:(Lscala/collection/MapLike;Lscala/Function1;)Lscala/collection/Map;
Asciz	mapElements;
NameAndType	mapElements:(Lscala/collection/MapLike;Lscala/Function1;)Lscala/collection/Map;
Method	scala/collection/MapLike$class.mapElements:(Lscala/collection/MapLike;Lscala/Function1;)Lscala/collection/Map;
Asciz	filterNot;
NameAndType	filterNot:(Lscala/collection/MapLike;Lscala/Function1;)Lscala/collection/Map;
Method	scala/collection/MapLike$class.filterNot:(Lscala/collection/MapLike;Lscala/Function1;)Lscala/collection/Map;
Asciz	addString;
Asciz	(Lscala/collection/mutable/StringBuilder;Ljava/lang/String;Ljava/lang/String;Ljava/lang/String;)Lscala/collection/mutable/StringBuilder;;
Asciz	(Lscala/collection/MapLike;Lscala/collection/mutable/StringBuilder;Ljava/lang/String;Ljava/lang/String;Ljava/lang/String;)Lscala/collection/mutable/StringBuilder;;
NameAndType	addString:(Lscala/collection/MapLike;Lscala/collection/mutable/StringBuilder;Ljava/lang/String;Ljava/lang/String;Ljava/lang/String;)Lscala/collection/mutable/StringBuilder;
Method	scala/collection/MapLike$class.addString:(Lscala/collection/MapLike;Lscala/collection/mutable/StringBuilder;Ljava/lang/String;Ljava/lang/String;Ljava/lang/String;)Lscala/collection/mutable/StringBuilder;
Asciz	b;
Asciz	Lscala/collection/mutable/StringBuilder;;
Asciz	start;
Asciz	Ljava/lang/String;;
Asciz	sep;
Asciz	end;
Asciz	stringPrefix;
Asciz	()Ljava/lang/String;;
Asciz	(Lscala/collection/MapLike;)Ljava/lang/String;;
NameAndType	stringPrefix:(Lscala/collection/MapLike;)Ljava/lang/String;
Method	scala/collection/MapLike$class.stringPrefix:(Lscala/collection/MapLike;)Ljava/lang/String;
Asciz	toString;
NameAndType	toString:(Lscala/collection/MapLike;)Ljava/lang/String;
Method	scala/collection/MapLike$class.toString:(Lscala/collection/MapLike;)Ljava/lang/String;
Asciz	hashCode;
Asciz	(Lscala/collection/MapLike;)I;
NameAndType	hashCode:(Lscala/collection/MapLike;)I
Method	scala/collection/MapLike$class.hashCode:(Lscala/collection/MapLike;)I
Asciz	equals;
NameAndType	equals:(Lscala/collection/MapLike;Ljava/lang/Object;)Z
Method	scala/collection/MapLike$class.equals:(Lscala/collection/MapLike;Ljava/lang/Object;)Z
Asciz	that;
Asciz	orElse;
Asciz	(Lscala/PartialFunction;)Lscala/PartialFunction;;
Asciz	scala/PartialFunction$class;
class	scala/PartialFunction$class
Asciz	(Lscala/PartialFunction;Lscala/PartialFunction;)Lscala/PartialFunction;;
NameAndType	orElse:(Lscala/PartialFunction;Lscala/PartialFunction;)Lscala/PartialFunction;
Method	scala/PartialFunction$class.orElse:(Lscala/PartialFunction;Lscala/PartialFunction;)Lscala/PartialFunction;
Asciz	Lscala/PartialFunction;;
Asciz	andThen;
Asciz	(Lscala/Function1;)Lscala/PartialFunction;;
Asciz	(Lscala/PartialFunction;Lscala/Function1;)Lscala/PartialFunction;;
NameAndType	andThen:(Lscala/PartialFunction;Lscala/Function1;)Lscala/PartialFunction;
Method	scala/PartialFunction$class.andThen:(Lscala/PartialFunction;Lscala/Function1;)Lscala/PartialFunction;
Asciz	lift;
Asciz	()Lscala/Function1;;
Asciz	(Lscala/PartialFunction;)Lscala/Function1;;
NameAndType	lift:(Lscala/PartialFunction;)Lscala/Function1;
Method	scala/PartialFunction$class.lift:(Lscala/PartialFunction;)Lscala/Function1;
Asciz	compose;
Asciz	(Lscala/Function1;)Lscala/Function1;;
Asciz	scala/Function1$class;
class	scala/Function1$class
Asciz	(Lscala/Function1;Lscala/Function1;)Lscala/Function1;;
NameAndType	compose:(Lscala/Function1;Lscala/Function1;)Lscala/Function1;
Method	scala/Function1$class.compose:(Lscala/Function1;Lscala/Function1;)Lscala/Function1;
Asciz	g;
Asciz	companion;
Asciz	()Lscala/collection/generic/GenericCompanion;;
Asciz	scala/collection/mutable/Iterable$class;
class	scala/collection/mutable/Iterable$class
Asciz	(Lscala/collection/mutable/Iterable;)Lscala/collection/generic/GenericCompanion;;
NameAndType	companion:(Lscala/collection/mutable/Iterable;)Lscala/collection/generic/GenericCompanion;
Method	scala/collection/mutable/Iterable$class.companion:(Lscala/collection/mutable/Iterable;)Lscala/collection/generic/GenericCompanion;
Asciz	thisCollection;
Asciz	scala/collection/IterableLike$class;
class	scala/collection/IterableLike$class
Asciz	(Lscala/collection/IterableLike;)Lscala/collection/Iterable;;
NameAndType	thisCollection:(Lscala/collection/IterableLike;)Lscala/collection/Iterable;
Method	scala/collection/IterableLike$class.thisCollection:(Lscala/collection/IterableLike;)Lscala/collection/Iterable;
Asciz	toCollection;
Asciz	(Ljava/lang/Object;)Lscala/collection/Iterable;;
Asciz	(Lscala/collection/IterableLike;Ljava/lang/Object;)Lscala/collection/Iterable;;
NameAndType	toCollection:(Lscala/collection/IterableLike;Ljava/lang/Object;)Lscala/collection/Iterable;
Method	scala/collection/IterableLike$class.toCollection:(Lscala/collection/IterableLike;Ljava/lang/Object;)Lscala/collection/Iterable;
Asciz	repr;
Asciz	foreach;
Asciz	(Lscala/Function1;)V;
Asciz	(Lscala/collection/IterableLike;Lscala/Function1;)V;
NameAndType	foreach:(Lscala/collection/IterableLike;Lscala/Function1;)V
Method	scala/collection/IterableLike$class.foreach:(Lscala/collection/IterableLike;Lscala/Function1;)V
Asciz	forall;
Asciz	(Lscala/Function1;)Z;
Asciz	(Lscala/collection/IterableLike;Lscala/Function1;)Z;
NameAndType	forall:(Lscala/collection/IterableLike;Lscala/Function1;)Z
Method	scala/collection/IterableLike$class.forall:(Lscala/collection/IterableLike;Lscala/Function1;)Z
Asciz	exists;
NameAndType	exists:(Lscala/collection/IterableLike;Lscala/Function1;)Z
Method	scala/collection/IterableLike$class.exists:(Lscala/collection/IterableLike;Lscala/Function1;)Z
Asciz	find;
Asciz	(Lscala/Function1;)Lscala/Option;;
Asciz	(Lscala/collection/IterableLike;Lscala/Function1;)Lscala/Option;;
NameAndType	find:(Lscala/collection/IterableLike;Lscala/Function1;)Lscala/Option;
Method	scala/collection/IterableLike$class.find:(Lscala/collection/IterableLike;Lscala/Function1;)Lscala/Option;
Asciz	foldRight;
Asciz	(Ljava/lang/Object;Lscala/Function2;)Ljava/lang/Object;;
Asciz	(Lscala/collection/IterableLike;Ljava/lang/Object;Lscala/Function2;)Ljava/lang/Object;;
NameAndType	foldRight:(Lscala/collection/IterableLike;Ljava/lang/Object;Lscala/Function2;)Ljava/lang/Object;
Method	scala/collection/IterableLike$class.foldRight:(Lscala/collection/IterableLike;Ljava/lang/Object;Lscala/Function2;)Ljava/lang/Object;
Asciz	z;
Asciz	reduceRight;
Asciz	(Lscala/Function2;)Ljava/lang/Object;;
Asciz	(Lscala/collection/IterableLike;Lscala/Function2;)Ljava/lang/Object;;
NameAndType	reduceRight:(Lscala/collection/IterableLike;Lscala/Function2;)Ljava/lang/Object;
Method	scala/collection/IterableLike$class.reduceRight:(Lscala/collection/IterableLike;Lscala/Function2;)Ljava/lang/Object;
Asciz	toIterable;
NameAndType	toIterable:(Lscala/collection/IterableLike;)Lscala/collection/Iterable;
Method	scala/collection/IterableLike$class.toIterable:(Lscala/collection/IterableLike;)Lscala/collection/Iterable;
Asciz	head;
Asciz	(Lscala/collection/IterableLike;)Ljava/lang/Object;;
NameAndType	head:(Lscala/collection/IterableLike;)Ljava/lang/Object;
Method	scala/collection/IterableLike$class.head:(Lscala/collection/IterableLike;)Ljava/lang/Object;
Asciz	take;
Asciz	(I)Ljava/lang/Object;;
Asciz	(Lscala/collection/IterableLike;I)Ljava/lang/Object;;
NameAndType	take:(Lscala/collection/IterableLike;I)Ljava/lang/Object;
Method	scala/collection/IterableLike$class.take:(Lscala/collection/IterableLike;I)Ljava/lang/Object;
Asciz	slice;
Asciz	(II)Ljava/lang/Object;;
Asciz	(Lscala/collection/IterableLike;II)Ljava/lang/Object;;
NameAndType	slice:(Lscala/collection/IterableLike;II)Ljava/lang/Object;
Method	scala/collection/IterableLike$class.slice:(Lscala/collection/IterableLike;II)Ljava/lang/Object;
Asciz	from;
Asciz	until;
Asciz	takeWhile;
Asciz	(Lscala/Function1;)Ljava/lang/Object;;
Asciz	(Lscala/collection/IterableLike;Lscala/Function1;)Ljava/lang/Object;;
NameAndType	takeWhile:(Lscala/collection/IterableLike;Lscala/Function1;)Ljava/lang/Object;
Method	scala/collection/IterableLike$class.takeWhile:(Lscala/collection/IterableLike;Lscala/Function1;)Ljava/lang/Object;
Asciz	grouped;
Asciz	(I)Lscala/collection/Iterator;;
Asciz	(Lscala/collection/IterableLike;I)Lscala/collection/Iterator;;
NameAndType	grouped:(Lscala/collection/IterableLike;I)Lscala/collection/Iterator;
Method	scala/collection/IterableLike$class.grouped:(Lscala/collection/IterableLike;I)Lscala/collection/Iterator;
Asciz	sliding;
NameAndType	sliding:(Lscala/collection/IterableLike;I)Lscala/collection/Iterator;
Method	scala/collection/IterableLike$class.sliding:(Lscala/collection/IterableLike;I)Lscala/collection/Iterator;
Asciz	(II)Lscala/collection/Iterator;;
Asciz	(Lscala/collection/IterableLike;II)Lscala/collection/Iterator;;
NameAndType	sliding:(Lscala/collection/IterableLike;II)Lscala/collection/Iterator;
Method	scala/collection/IterableLike$class.sliding:(Lscala/collection/IterableLike;II)Lscala/collection/Iterator;
Asciz	step;
Asciz	takeRight;
NameAndType	takeRight:(Lscala/collection/IterableLike;I)Ljava/lang/Object;
Method	scala/collection/IterableLike$class.takeRight:(Lscala/collection/IterableLike;I)Ljava/lang/Object;
Asciz	dropRight;
NameAndType	dropRight:(Lscala/collection/IterableLike;I)Ljava/lang/Object;
Method	scala/collection/IterableLike$class.dropRight:(Lscala/collection/IterableLike;I)Ljava/lang/Object;
Asciz	copyToArray;
Asciz	(Ljava/lang/Object;II)V;
Asciz	(Lscala/collection/IterableLike;Ljava/lang/Object;II)V;
NameAndType	copyToArray:(Lscala/collection/IterableLike;Ljava/lang/Object;II)V
Method	scala/collection/IterableLike$class.copyToArray:(Lscala/collection/IterableLike;Ljava/lang/Object;II)V
Asciz	xs;
Asciz	len;
Asciz	zip;
Asciz	(Lscala/collection/Iterable;Lscala/collection/generic/CanBuildFrom;)Ljava/lang/Object;;
Asciz	(Lscala/collection/IterableLike;Lscala/collection/Iterable;Lscala/collection/generic/CanBuildFrom;)Ljava/lang/Object;;
NameAndType	zip:(Lscala/collection/IterableLike;Lscala/collection/Iterable;Lscala/collection/generic/CanBuildFrom;)Ljava/lang/Object;
Method	scala/collection/IterableLike$class.zip:(Lscala/collection/IterableLike;Lscala/collection/Iterable;Lscala/collection/generic/CanBuildFrom;)Ljava/lang/Object;
Asciz	Lscala/collection/Iterable;;
Asciz	bf;
Asciz	Lscala/collection/generic/CanBuildFrom;;
Asciz	zipAll;
Asciz	(Lscala/collection/Iterable;Ljava/lang/Object;Ljava/lang/Object;Lscala/collection/generic/CanBuildFrom;)Ljava/lang/Object;;
Asciz	(Lscala/collection/IterableLike;Lscala/collection/Iterable;Ljava/lang/Object;Ljava/lang/Object;Lscala/collection/generic/CanBuildFrom;)Ljava/lang/Object;;
NameAndType	zipAll:(Lscala/collection/IterableLike;Lscala/collection/Iterable;Ljava/lang/Object;Ljava/lang/Object;Lscala/collection/generic/CanBuildFrom;)Ljava/lang/Object;
Method	scala/collection/IterableLike$class.zipAll:(Lscala/collection/IterableLike;Lscala/collection/Iterable;Ljava/lang/Object;Ljava/lang/Object;Lscala/collection/generic/CanBuildFrom;)Ljava/lang/Object;
Asciz	thisElem;
Asciz	thatElem;
Asciz	zipWithIndex;
Asciz	(Lscala/collection/generic/CanBuildFrom;)Ljava/lang/Object;;
Asciz	(Lscala/collection/IterableLike;Lscala/collection/generic/CanBuildFrom;)Ljava/lang/Object;;
NameAndType	zipWithIndex:(Lscala/collection/IterableLike;Lscala/collection/generic/CanBuildFrom;)Ljava/lang/Object;
Method	scala/collection/IterableLike$class.zipWithIndex:(Lscala/collection/IterableLike;Lscala/collection/generic/CanBuildFrom;)Ljava/lang/Object;
Asciz	sameElements;
Asciz	(Lscala/collection/Iterable;)Z;
Asciz	(Lscala/collection/IterableLike;Lscala/collection/Iterable;)Z;
NameAndType	sameElements:(Lscala/collection/IterableLike;Lscala/collection/Iterable;)Z
Method	scala/collection/IterableLike$class.sameElements:(Lscala/collection/IterableLike;Lscala/collection/Iterable;)Z
Asciz	toStream;
Asciz	()Lscala/collection/immutable/Stream;;
Asciz	(Lscala/collection/IterableLike;)Lscala/collection/immutable/Stream;;
NameAndType	toStream:(Lscala/collection/IterableLike;)Lscala/collection/immutable/Stream;
Method	scala/collection/IterableLike$class.toStream:(Lscala/collection/IterableLike;)Lscala/collection/immutable/Stream;
Asciz	canEqual;
Asciz	(Lscala/collection/IterableLike;Ljava/lang/Object;)Z;
NameAndType	canEqual:(Lscala/collection/IterableLike;Ljava/lang/Object;)Z
Method	scala/collection/IterableLike$class.canEqual:(Lscala/collection/IterableLike;Ljava/lang/Object;)Z
Asciz	view;
Asciz	()Lscala/collection/IterableView;;
Asciz	(Lscala/collection/IterableLike;)Lscala/collection/IterableView;;
NameAndType	view:(Lscala/collection/IterableLike;)Lscala/collection/IterableView;
Method	scala/collection/IterableLike$class.view:(Lscala/collection/IterableLike;)Lscala/collection/IterableView;
Asciz	(II)Lscala/collection/IterableView;;
Asciz	(Lscala/collection/IterableLike;II)Lscala/collection/IterableView;;
NameAndType	view:(Lscala/collection/IterableLike;II)Lscala/collection/IterableView;
Method	scala/collection/IterableLike$class.view:(Lscala/collection/IterableLike;II)Lscala/collection/IterableView;
Asciz	elements;
Asciz	(Lscala/collection/IterableLike;)Lscala/collection/Iterator;;
NameAndType	elements:(Lscala/collection/IterableLike;)Lscala/collection/Iterator;
Method	scala/collection/IterableLike$class.elements:(Lscala/collection/IterableLike;)Lscala/collection/Iterator;
Asciz	first;
NameAndType	first:(Lscala/collection/IterableLike;)Ljava/lang/Object;
Method	scala/collection/IterableLike$class.first:(Lscala/collection/IterableLike;)Ljava/lang/Object;
Asciz	firstOption;
Asciz	()Lscala/Option;;
Asciz	(Lscala/collection/IterableLike;)Lscala/Option;;
NameAndType	firstOption:(Lscala/collection/IterableLike;)Lscala/Option;
Method	scala/collection/IterableLike$class.firstOption:(Lscala/collection/IterableLike;)Lscala/Option;
Asciz	projection;
NameAndType	projection:(Lscala/collection/IterableLike;)Lscala/collection/IterableView;
Method	scala/collection/IterableLike$class.projection:(Lscala/collection/IterableLike;)Lscala/collection/IterableView;
Asciz	genericBuilder;
Asciz	scala/collection/generic/GenericTraversableTemplate$class;
class	scala/collection/generic/GenericTraversableTemplate$class
Asciz	(Lscala/collection/generic/GenericTraversableTemplate;)Lscala/collection/mutable/Builder;;
NameAndType	genericBuilder:(Lscala/collection/generic/GenericTraversableTemplate;)Lscala/collection/mutable/Builder;
Method	scala/collection/generic/GenericTraversableTemplate$class.genericBuilder:(Lscala/collection/generic/GenericTraversableTemplate;)Lscala/collection/mutable/Builder;
Asciz	unzip;
Asciz	(Lscala/Function1;)Lscala/Tuple2;;
Asciz	(Lscala/collection/generic/GenericTraversableTemplate;Lscala/Function1;)Lscala/Tuple2;;
NameAndType	unzip:(Lscala/collection/generic/GenericTraversableTemplate;Lscala/Function1;)Lscala/Tuple2;
Method	scala/collection/generic/GenericTraversableTemplate$class.unzip:(Lscala/collection/generic/GenericTraversableTemplate;Lscala/Function1;)Lscala/Tuple2;
Asciz	asPair;
Asciz	flatten;
Asciz	(Lscala/Function1;)Lscala/collection/Traversable;;
Asciz	(Lscala/collection/generic/GenericTraversableTemplate;Lscala/Function1;)Lscala/collection/Traversable;;
NameAndType	flatten:(Lscala/collection/generic/GenericTraversableTemplate;Lscala/Function1;)Lscala/collection/Traversable;
Method	scala/collection/generic/GenericTraversableTemplate$class.flatten:(Lscala/collection/generic/GenericTraversableTemplate;Lscala/Function1;)Lscala/collection/Traversable;
Asciz	asTraversable;
Asciz	transpose;
NameAndType	transpose:(Lscala/collection/generic/GenericTraversableTemplate;Lscala/Function1;)Lscala/collection/Traversable;
Method	scala/collection/generic/GenericTraversableTemplate$class.transpose:(Lscala/collection/generic/GenericTraversableTemplate;Lscala/Function1;)Lscala/collection/Traversable;
Asciz	scala/collection/TraversableLike$class;
class	scala/collection/TraversableLike$class
Asciz	(Lscala/collection/TraversableLike;)Ljava/lang/Object;;
NameAndType	repr:(Lscala/collection/TraversableLike;)Ljava/lang/Object;
Method	scala/collection/TraversableLike$class.repr:(Lscala/collection/TraversableLike;)Ljava/lang/Object;
Asciz	nonEmpty;
Asciz	(Lscala/collection/TraversableLike;)Z;
NameAndType	nonEmpty:(Lscala/collection/TraversableLike;)Z
Method	scala/collection/TraversableLike$class.nonEmpty:(Lscala/collection/TraversableLike;)Z
Asciz	hasDefiniteSize;
NameAndType	hasDefiniteSize:(Lscala/collection/TraversableLike;)Z
Method	scala/collection/TraversableLike$class.hasDefiniteSize:(Lscala/collection/TraversableLike;)Z
Asciz	(Lscala/collection/Traversable;Lscala/collection/generic/CanBuildFrom;)Ljava/lang/Object;;
Asciz	(Lscala/collection/TraversableLike;Lscala/collection/Traversable;Lscala/collection/generic/CanBuildFrom;)Ljava/lang/Object;;
NameAndType	$plus$plus:(Lscala/collection/TraversableLike;Lscala/collection/Traversable;Lscala/collection/generic/CanBuildFrom;)Ljava/lang/Object;
Method	scala/collection/TraversableLike$class.$plus$plus:(Lscala/collection/TraversableLike;Lscala/collection/Traversable;Lscala/collection/generic/CanBuildFrom;)Ljava/lang/Object;
Asciz	(Lscala/collection/Iterator;Lscala/collection/generic/CanBuildFrom;)Ljava/lang/Object;;
Asciz	(Lscala/collection/TraversableLike;Lscala/collection/Iterator;Lscala/collection/generic/CanBuildFrom;)Ljava/lang/Object;;
NameAndType	$plus$plus:(Lscala/collection/TraversableLike;Lscala/collection/Iterator;Lscala/collection/generic/CanBuildFrom;)Ljava/lang/Object;
Method	scala/collection/TraversableLike$class.$plus$plus:(Lscala/collection/TraversableLike;Lscala/collection/Iterator;Lscala/collection/generic/CanBuildFrom;)Ljava/lang/Object;
Asciz	map;
Asciz	(Lscala/Function1;Lscala/collection/generic/CanBuildFrom;)Ljava/lang/Object;;
Asciz	(Lscala/collection/TraversableLike;Lscala/Function1;Lscala/collection/generic/CanBuildFrom;)Ljava/lang/Object;;
NameAndType	map:(Lscala/collection/TraversableLike;Lscala/Function1;Lscala/collection/generic/CanBuildFrom;)Ljava/lang/Object;
Method	scala/collection/TraversableLike$class.map:(Lscala/collection/TraversableLike;Lscala/Function1;Lscala/collection/generic/CanBuildFrom;)Ljava/lang/Object;
Asciz	flatMap;
NameAndType	flatMap:(Lscala/collection/TraversableLike;Lscala/Function1;Lscala/collection/generic/CanBuildFrom;)Ljava/lang/Object;
Method	scala/collection/TraversableLike$class.flatMap:(Lscala/collection/TraversableLike;Lscala/Function1;Lscala/collection/generic/CanBuildFrom;)Ljava/lang/Object;
Asciz	filter;
Asciz	(Lscala/collection/TraversableLike;Lscala/Function1;)Ljava/lang/Object;;
NameAndType	filter:(Lscala/collection/TraversableLike;Lscala/Function1;)Ljava/lang/Object;
Method	scala/collection/TraversableLike$class.filter:(Lscala/collection/TraversableLike;Lscala/Function1;)Ljava/lang/Object;
Asciz	partialMap;
Asciz	(Lscala/PartialFunction;Lscala/collection/generic/CanBuildFrom;)Ljava/lang/Object;;
Asciz	(Lscala/collection/TraversableLike;Lscala/PartialFunction;Lscala/collection/generic/CanBuildFrom;)Ljava/lang/Object;;
NameAndType	partialMap:(Lscala/collection/TraversableLike;Lscala/PartialFunction;Lscala/collection/generic/CanBuildFrom;)Ljava/lang/Object;
Method	scala/collection/TraversableLike$class.partialMap:(Lscala/collection/TraversableLike;Lscala/PartialFunction;Lscala/collection/generic/CanBuildFrom;)Ljava/lang/Object;
Asciz	pf;
Asciz	partition;
Asciz	(Lscala/collection/TraversableLike;Lscala/Function1;)Lscala/Tuple2;;
NameAndType	partition:(Lscala/collection/TraversableLike;Lscala/Function1;)Lscala/Tuple2;
Method	scala/collection/TraversableLike$class.partition:(Lscala/collection/TraversableLike;Lscala/Function1;)Lscala/Tuple2;
Asciz	groupBy;
Asciz	(Lscala/collection/TraversableLike;Lscala/Function1;)Lscala/collection/Map;;
NameAndType	groupBy:(Lscala/collection/TraversableLike;Lscala/Function1;)Lscala/collection/Map;
Method	scala/collection/TraversableLike$class.groupBy:(Lscala/collection/TraversableLike;Lscala/Function1;)Lscala/collection/Map;
Asciz	count;
Asciz	(Lscala/Function1;)I;
Asciz	(Lscala/collection/TraversableLike;Lscala/Function1;)I;
NameAndType	count:(Lscala/collection/TraversableLike;Lscala/Function1;)I
Method	scala/collection/TraversableLike$class.count:(Lscala/collection/TraversableLike;Lscala/Function1;)I
Asciz	foldLeft;
Asciz	(Lscala/collection/TraversableLike;Ljava/lang/Object;Lscala/Function2;)Ljava/lang/Object;;
NameAndType	foldLeft:(Lscala/collection/TraversableLike;Ljava/lang/Object;Lscala/Function2;)Ljava/lang/Object;
Method	scala/collection/TraversableLike$class.foldLeft:(Lscala/collection/TraversableLike;Ljava/lang/Object;Lscala/Function2;)Ljava/lang/Object;
Asciz	$div$colon;
NameAndType	$div$colon:(Lscala/collection/TraversableLike;Ljava/lang/Object;Lscala/Function2;)Ljava/lang/Object;
Method	scala/collection/TraversableLike$class.$div$colon:(Lscala/collection/TraversableLike;Ljava/lang/Object;Lscala/Function2;)Ljava/lang/Object;
Asciz	$colon$bslash;
NameAndType	$colon$bslash:(Lscala/collection/TraversableLike;Ljava/lang/Object;Lscala/Function2;)Ljava/lang/Object;
Method	scala/collection/TraversableLike$class.$colon$bslash:(Lscala/collection/TraversableLike;Ljava/lang/Object;Lscala/Function2;)Ljava/lang/Object;
Asciz	reduceLeft;
Asciz	(Lscala/collection/TraversableLike;Lscala/Function2;)Ljava/lang/Object;;
NameAndType	reduceLeft:(Lscala/collection/TraversableLike;Lscala/Function2;)Ljava/lang/Object;
Method	scala/collection/TraversableLike$class.reduceLeft:(Lscala/collection/TraversableLike;Lscala/Function2;)Ljava/lang/Object;
Asciz	reduceLeftOption;
Asciz	(Lscala/Function2;)Lscala/Option;;
Asciz	(Lscala/collection/TraversableLike;Lscala/Function2;)Lscala/Option;;
NameAndType	reduceLeftOption:(Lscala/collection/TraversableLike;Lscala/Function2;)Lscala/Option;
Method	scala/collection/TraversableLike$class.reduceLeftOption:(Lscala/collection/TraversableLike;Lscala/Function2;)Lscala/Option;
Asciz	reduceRightOption;
NameAndType	reduceRightOption:(Lscala/collection/TraversableLike;Lscala/Function2;)Lscala/Option;
Method	scala/collection/TraversableLike$class.reduceRightOption:(Lscala/collection/TraversableLike;Lscala/Function2;)Lscala/Option;
Asciz	scanLeft;
Asciz	(Ljava/lang/Object;Lscala/Function2;Lscala/collection/generic/CanBuildFrom;)Ljava/lang/Object;;
Asciz	(Lscala/collection/TraversableLike;Ljava/lang/Object;Lscala/Function2;Lscala/collection/generic/CanBuildFrom;)Ljava/lang/Object;;
NameAndType	scanLeft:(Lscala/collection/TraversableLike;Ljava/lang/Object;Lscala/Function2;Lscala/collection/generic/CanBuildFrom;)Ljava/lang/Object;
Method	scala/collection/TraversableLike$class.scanLeft:(Lscala/collection/TraversableLike;Ljava/lang/Object;Lscala/Function2;Lscala/collection/generic/CanBuildFrom;)Ljava/lang/Object;
Asciz	scanRight;
NameAndType	scanRight:(Lscala/collection/TraversableLike;Ljava/lang/Object;Lscala/Function2;Lscala/collection/generic/CanBuildFrom;)Ljava/lang/Object;
Method	scala/collection/TraversableLike$class.scanRight:(Lscala/collection/TraversableLike;Ljava/lang/Object;Lscala/Function2;Lscala/collection/generic/CanBuildFrom;)Ljava/lang/Object;
Asciz	sum;
Asciz	(Lscala/math/Numeric;)Ljava/lang/Object;;
Asciz	(Lscala/collection/TraversableLike;Lscala/math/Numeric;)Ljava/lang/Object;;
NameAndType	sum:(Lscala/collection/TraversableLike;Lscala/math/Numeric;)Ljava/lang/Object;
Method	scala/collection/TraversableLike$class.sum:(Lscala/collection/TraversableLike;Lscala/math/Numeric;)Ljava/lang/Object;
Asciz	num;
Asciz	Lscala/math/Numeric;;
Asciz	product;
NameAndType	product:(Lscala/collection/TraversableLike;Lscala/math/Numeric;)Ljava/lang/Object;
Method	scala/collection/TraversableLike$class.product:(Lscala/collection/TraversableLike;Lscala/math/Numeric;)Ljava/lang/Object;
Asciz	min;
Asciz	(Lscala/math/Ordering;)Ljava/lang/Object;;
Asciz	(Lscala/collection/TraversableLike;Lscala/math/Ordering;)Ljava/lang/Object;;
NameAndType	min:(Lscala/collection/TraversableLike;Lscala/math/Ordering;)Ljava/lang/Object;
Method	scala/collection/TraversableLike$class.min:(Lscala/collection/TraversableLike;Lscala/math/Ordering;)Ljava/lang/Object;
Asciz	cmp;
Asciz	Lscala/math/Ordering;;
Asciz	max;
NameAndType	max:(Lscala/collection/TraversableLike;Lscala/math/Ordering;)Ljava/lang/Object;
Method	scala/collection/TraversableLike$class.max:(Lscala/collection/TraversableLike;Lscala/math/Ordering;)Ljava/lang/Object;
Asciz	headOption;
Asciz	(Lscala/collection/TraversableLike;)Lscala/Option;;
NameAndType	headOption:(Lscala/collection/TraversableLike;)Lscala/Option;
Method	scala/collection/TraversableLike$class.headOption:(Lscala/collection/TraversableLike;)Lscala/Option;
Asciz	tail;
NameAndType	tail:(Lscala/collection/TraversableLike;)Ljava/lang/Object;
Method	scala/collection/TraversableLike$class.tail:(Lscala/collection/TraversableLike;)Ljava/lang/Object;
Asciz	last;
NameAndType	last:(Lscala/collection/TraversableLike;)Ljava/lang/Object;
Method	scala/collection/TraversableLike$class.last:(Lscala/collection/TraversableLike;)Ljava/lang/Object;
Asciz	lastOption;
NameAndType	lastOption:(Lscala/collection/TraversableLike;)Lscala/Option;
Method	scala/collection/TraversableLike$class.lastOption:(Lscala/collection/TraversableLike;)Lscala/Option;
Asciz	init;
NameAndType	init:(Lscala/collection/TraversableLike;)Ljava/lang/Object;
Method	scala/collection/TraversableLike$class.init:(Lscala/collection/TraversableLike;)Ljava/lang/Object;
Asciz	drop;
Asciz	(Lscala/collection/TraversableLike;I)Ljava/lang/Object;;
NameAndType	drop:(Lscala/collection/TraversableLike;I)Ljava/lang/Object;
Method	scala/collection/TraversableLike$class.drop:(Lscala/collection/TraversableLike;I)Ljava/lang/Object;
Asciz	dropWhile;
NameAndType	dropWhile:(Lscala/collection/TraversableLike;Lscala/Function1;)Ljava/lang/Object;
Method	scala/collection/TraversableLike$class.dropWhile:(Lscala/collection/TraversableLike;Lscala/Function1;)Ljava/lang/Object;
Asciz	span;
NameAndType	span:(Lscala/collection/TraversableLike;Lscala/Function1;)Lscala/Tuple2;
Method	scala/collection/TraversableLike$class.span:(Lscala/collection/TraversableLike;Lscala/Function1;)Lscala/Tuple2;
Asciz	splitAt;
Asciz	(I)Lscala/Tuple2;;
Asciz	(Lscala/collection/TraversableLike;I)Lscala/Tuple2;;
NameAndType	splitAt:(Lscala/collection/TraversableLike;I)Lscala/Tuple2;
Method	scala/collection/TraversableLike$class.splitAt:(Lscala/collection/TraversableLike;I)Lscala/Tuple2;
Asciz	copyToBuffer;
Asciz	(Lscala/collection/mutable/Buffer;)V;
Asciz	(Lscala/collection/TraversableLike;Lscala/collection/mutable/Buffer;)V;
NameAndType	copyToBuffer:(Lscala/collection/TraversableLike;Lscala/collection/mutable/Buffer;)V
Method	scala/collection/TraversableLike$class.copyToBuffer:(Lscala/collection/TraversableLike;Lscala/collection/mutable/Buffer;)V
Asciz	dest;
Asciz	Lscala/collection/mutable/Buffer;;
Asciz	(Ljava/lang/Object;I)V;
Asciz	(Lscala/collection/TraversableLike;Ljava/lang/Object;I)V;
NameAndType	copyToArray:(Lscala/collection/TraversableLike;Ljava/lang/Object;I)V
Method	scala/collection/TraversableLike$class.copyToArray:(Lscala/collection/TraversableLike;Ljava/lang/Object;I)V
Asciz	(Ljava/lang/Object;)V;
Asciz	(Lscala/collection/TraversableLike;Ljava/lang/Object;)V;
NameAndType	copyToArray:(Lscala/collection/TraversableLike;Ljava/lang/Object;)V
Method	scala/collection/TraversableLike$class.copyToArray:(Lscala/collection/TraversableLike;Ljava/lang/Object;)V
Asciz	toArray;
Asciz	(Lscala/reflect/ClassManifest;)Ljava/lang/Object;;
Asciz	(Lscala/collection/TraversableLike;Lscala/reflect/ClassManifest;)Ljava/lang/Object;;
NameAndType	toArray:(Lscala/collection/TraversableLike;Lscala/reflect/ClassManifest;)Ljava/lang/Object;
Method	scala/collection/TraversableLike$class.toArray:(Lscala/collection/TraversableLike;Lscala/reflect/ClassManifest;)Ljava/lang/Object;
Asciz	evidence$1;
Asciz	Lscala/reflect/ClassManifest;;
Asciz	toList;
Asciz	()Lscala/collection/immutable/List;;
Asciz	(Lscala/collection/TraversableLike;)Lscala/collection/immutable/List;;
NameAndType	toList:(Lscala/collection/TraversableLike;)Lscala/collection/immutable/List;
Method	scala/collection/TraversableLike$class.toList:(Lscala/collection/TraversableLike;)Lscala/collection/immutable/List;
Asciz	toSeq;
Asciz	()Lscala/collection/Seq;;
Asciz	(Lscala/collection/TraversableLike;)Lscala/collection/Seq;;
NameAndType	toSeq:(Lscala/collection/TraversableLike;)Lscala/collection/Seq;
Method	scala/collection/TraversableLike$class.toSeq:(Lscala/collection/TraversableLike;)Lscala/collection/Seq;
Asciz	toIndexedSeq;
Asciz	()Lscala/collection/mutable/IndexedSeq;;
Asciz	(Lscala/collection/TraversableLike;)Lscala/collection/mutable/IndexedSeq;;
NameAndType	toIndexedSeq:(Lscala/collection/TraversableLike;)Lscala/collection/mutable/IndexedSeq;
Method	scala/collection/TraversableLike$class.toIndexedSeq:(Lscala/collection/TraversableLike;)Lscala/collection/mutable/IndexedSeq;
Asciz	toSet;
Asciz	()Lscala/collection/immutable/Set;;
Asciz	(Lscala/collection/TraversableLike;)Lscala/collection/immutable/Set;;
NameAndType	toSet:(Lscala/collection/TraversableLike;)Lscala/collection/immutable/Set;
Method	scala/collection/TraversableLike$class.toSet:(Lscala/collection/TraversableLike;)Lscala/collection/immutable/Set;
Asciz	toMap;
Asciz	(Lscala/Predef$$less$colon$less;)Lscala/collection/immutable/Map;;
Asciz	(Lscala/collection/TraversableLike;Lscala/Predef$$less$colon$less;)Lscala/collection/immutable/Map;;
NameAndType	toMap:(Lscala/collection/TraversableLike;Lscala/Predef$$less$colon$less;)Lscala/collection/immutable/Map;
Method	scala/collection/TraversableLike$class.toMap:(Lscala/collection/TraversableLike;Lscala/Predef$$less$colon$less;)Lscala/collection/immutable/Map;
Asciz	ev;
Asciz	Lscala/Predef$$less$colon$less;;
Asciz	mkString;
Asciz	(Ljava/lang/String;Ljava/lang/String;Ljava/lang/String;)Ljava/lang/String;;
Asciz	(Lscala/collection/TraversableLike;Ljava/lang/String;Ljava/lang/String;Ljava/lang/String;)Ljava/lang/String;;
NameAndType	mkString:(Lscala/collection/TraversableLike;Ljava/lang/String;Ljava/lang/String;Ljava/lang/String;)Ljava/lang/String;
Method	scala/collection/TraversableLike$class.mkString:(Lscala/collection/TraversableLike;Ljava/lang/String;Ljava/lang/String;Ljava/lang/String;)Ljava/lang/String;
Asciz	(Ljava/lang/String;)Ljava/lang/String;;
Asciz	(Lscala/collection/TraversableLike;Ljava/lang/String;)Ljava/lang/String;;
NameAndType	mkString:(Lscala/collection/TraversableLike;Ljava/lang/String;)Ljava/lang/String;
Method	scala/collection/TraversableLike$class.mkString:(Lscala/collection/TraversableLike;Ljava/lang/String;)Ljava/lang/String;
Asciz	(Lscala/collection/TraversableLike;)Ljava/lang/String;;
NameAndType	mkString:(Lscala/collection/TraversableLike;)Ljava/lang/String;
Method	scala/collection/TraversableLike$class.mkString:(Lscala/collection/TraversableLike;)Ljava/lang/String;
Asciz	(Lscala/collection/mutable/StringBuilder;Ljava/lang/String;)Lscala/collection/mutable/StringBuilder;;
Asciz	(Lscala/collection/TraversableLike;Lscala/collection/mutable/StringBuilder;Ljava/lang/String;)Lscala/collection/mutable/StringBuilder;;
NameAndType	addString:(Lscala/collection/TraversableLike;Lscala/collection/mutable/StringBuilder;Ljava/lang/String;)Lscala/collection/mutable/StringBuilder;
Method	scala/collection/TraversableLike$class.addString:(Lscala/collection/TraversableLike;Lscala/collection/mutable/StringBuilder;Ljava/lang/String;)Lscala/collection/mutable/StringBuilder;
Asciz	(Lscala/collection/mutable/StringBuilder;)Lscala/collection/mutable/StringBuilder;;
Asciz	(Lscala/collection/TraversableLike;Lscala/collection/mutable/StringBuilder;)Lscala/collection/mutable/StringBuilder;;
NameAndType	addString:(Lscala/collection/TraversableLike;Lscala/collection/mutable/StringBuilder;)Lscala/collection/mutable/StringBuilder;
Method	scala/collection/TraversableLike$class.addString:(Lscala/collection/TraversableLike;Lscala/collection/mutable/StringBuilder;)Lscala/collection/mutable/StringBuilder;
Asciz	withFilter;
Asciz	(Lscala/Function1;)Lscala/collection/TraversableLike$WithFilter;;
Asciz	(Lscala/collection/TraversableLike;Lscala/Function1;)Lscala/collection/TraversableLike$WithFilter;;
NameAndType	withFilter:(Lscala/collection/TraversableLike;Lscala/Function1;)Lscala/collection/TraversableLike$WithFilter;
Method	scala/collection/TraversableLike$class.withFilter:(Lscala/collection/TraversableLike;Lscala/Function1;)Lscala/collection/TraversableLike$WithFilter;
Asciz	copy$default$1;
Asciz	()Ljava/util/concurrent/ConcurrentMap;;
Asciz	scala/collection/JavaConversions$JConcurrentMapWrapper;
class	scala/collection/JavaConversions$JConcurrentMapWrapper
NameAndType	underlying:()Ljava/util/concurrent/ConcurrentMap;
Method	scala/collection/JavaConversions$JConcurrentMapWrapper.underlying:()Ljava/util/concurrent/ConcurrentMap;
NameAndType	underlying:Ljava/util/concurrent/ConcurrentMap;
Field	scala/collection/JavaConversions$JConcurrentMapWrapper.underlying:Ljava/util/concurrent/ConcurrentMap;
Asciz	()Ljava/util/concurrent/ConcurrentMap<TA;TB;>;;
Asciz	get;
Asciz	java/util/Map;
class	java/util/Map
NameAndType	get:(Ljava/lang/Object;)Ljava/lang/Object;
InterfaceMethod	java/util/Map.get:(Ljava/lang/Object;)Ljava/lang/Object;
NameAndType	equals:(Ljava/lang/Object;)Z
Method	java/lang/Object.equals:(Ljava/lang/Object;)Z
Asciz	scala/None$;
class	scala/None$
Asciz	MODULE$;
Asciz	Lscala/None$;;
NameAndType	MODULE$:Lscala/None$;
Field	scala/None$.MODULE$:Lscala/None$;
Asciz	scala/Some;
class	scala/Some
Asciz	<init>;
NameAndType	"<init>":(Ljava/lang/Object;)V
Method	scala/Some."<init>":(Ljava/lang/Object;)V
Asciz	(TA;)Lscala/Option<TB;>;;
Asciz	empty;
Asciz	()Lscala/collection/JavaConversions$JConcurrentMapWrapper;;
Asciz	java/util/concurrent/ConcurrentHashMap;
class	java/util/concurrent/ConcurrentHashMap
NameAndType	"<init>":()V
Method	java/util/concurrent/ConcurrentHashMap."<init>":()V
Asciz	(Ljava/util/concurrent/ConcurrentMap;)V;
NameAndType	"<init>":(Ljava/util/concurrent/ConcurrentMap;)V
Method	scala/collection/JavaConversions$JConcurrentMapWrapper."<init>":(Ljava/util/concurrent/ConcurrentMap;)V
Asciz	()Lscala/collection/JavaConversions$JConcurrentMapWrapper<TA;TB;>;;
Asciz	putIfAbsent;
Asciz	java/util/concurrent/ConcurrentMap;
class	java/util/concurrent/ConcurrentMap
Asciz	(Ljava/lang/Object;Ljava/lang/Object;)Ljava/lang/Object;;
NameAndType	putIfAbsent:(Ljava/lang/Object;Ljava/lang/Object;)Ljava/lang/Object;
InterfaceMethod	java/util/concurrent/ConcurrentMap.putIfAbsent:(Ljava/lang/Object;Ljava/lang/Object;)Ljava/lang/Object;
Asciz	r;
Asciz	(TA;TB;)Lscala/Option<TB;>;;
Asciz	(Ljava/lang/Object;Ljava/lang/Object;)Z;
NameAndType	remove:(Ljava/lang/Object;Ljava/lang/Object;)Z
InterfaceMethod	java/util/concurrent/ConcurrentMap.remove:(Ljava/lang/Object;Ljava/lang/Object;)Z
Asciz	(TA;TB;)Z;
Asciz	replace;
NameAndType	replace:(Ljava/lang/Object;Ljava/lang/Object;)Ljava/lang/Object;
InterfaceMethod	java/util/concurrent/ConcurrentMap.replace:(Ljava/lang/Object;Ljava/lang/Object;)Ljava/lang/Object;
Asciz	prev;
Asciz	(Ljava/lang/Object;Ljava/lang/Object;Ljava/lang/Object;)Z;
NameAndType	replace:(Ljava/lang/Object;Ljava/lang/Object;Ljava/lang/Object;)Z
InterfaceMethod	java/util/concurrent/ConcurrentMap.replace:(Ljava/lang/Object;Ljava/lang/Object;Ljava/lang/Object;)Z
Asciz	oldvalue;
Asciz	newvalue;
Asciz	(TA;TB;TB;)Z;
Asciz	copy;
Asciz	(Ljava/util/concurrent/ConcurrentMap;)Lscala/collection/JavaConversions$JConcurrentMapWrapper;;
Asciz	productPrefix;
Asciz	JConcurrentMapWrapper;
String	JConcurrentMapWrapper
Asciz	productArity;
Asciz	productElement;
Asciz	java/lang/IndexOutOfBoundsException;
class	java/lang/IndexOutOfBoundsException
Asciz	scala/runtime/BoxesRunTime;
class	scala/runtime/BoxesRunTime
Asciz	boxToInteger;
Asciz	(I)Ljava/lang/Integer;;
NameAndType	boxToInteger:(I)Ljava/lang/Integer;
Method	scala/runtime/BoxesRunTime.boxToInteger:(I)Ljava/lang/Integer;
NameAndType	toString:()Ljava/lang/String;
Method	java/lang/Object.toString:()Ljava/lang/String;
Asciz	(Ljava/lang/String;)V;
NameAndType	"<init>":(Ljava/lang/String;)V
Method	java/lang/IndexOutOfBoundsException."<init>":(Ljava/lang/String;)V
Asciz	()Lscala/collection/generic/Subtractable;;
Asciz	scala/collection/TraversableLike;
class	scala/collection/TraversableLike
NameAndType	repr:()Ljava/lang/Object;
InterfaceMethod	scala/collection/TraversableLike.repr:()Ljava/lang/Object;
Asciz	scala/collection/generic/Subtractable;
class	scala/collection/generic/Subtractable
Asciz	(II)Lscala/collection/TraversableView;;
Asciz	scala/collection/IterableLike;
class	scala/collection/IterableLike
NameAndType	view:(II)Lscala/collection/IterableView;
InterfaceMethod	scala/collection/IterableLike.view:(II)Lscala/collection/IterableView;
Asciz	()Lscala/collection/TraversableView;;
NameAndType	view:()Lscala/collection/IterableView;
InterfaceMethod	scala/collection/IterableLike.view:()Lscala/collection/IterableView;
Asciz	(Ljava/lang/Object;)Lscala/collection/Traversable;;
NameAndType	toCollection:(Ljava/lang/Object;)Lscala/collection/Iterable;
InterfaceMethod	scala/collection/IterableLike.toCollection:(Ljava/lang/Object;)Lscala/collection/Iterable;
Asciz	()Lscala/collection/Traversable;;
NameAndType	thisCollection:()Lscala/collection/Iterable;
InterfaceMethod	scala/collection/IterableLike.thisCollection:()Lscala/collection/Iterable;
Asciz	scala/PartialFunction;
class	scala/PartialFunction
NameAndType	andThen:(Lscala/Function1;)Lscala/PartialFunction;
InterfaceMethod	scala/PartialFunction.andThen:(Lscala/Function1;)Lscala/PartialFunction;
Asciz	scala/collection/MapLike;
class	scala/collection/MapLike
NameAndType	filterNot:(Lscala/Function1;)Lscala/collection/Map;
InterfaceMethod	scala/collection/MapLike.filterNot:(Lscala/Function1;)Lscala/collection/Map;
Asciz	(Lscala/collection/Iterator;)Lscala/collection/generic/Subtractable;;
Asciz	scala/collection/mutable/MapLike;
class	scala/collection/mutable/MapLike
NameAndType	$minus$minus:(Lscala/collection/Iterator;)Lscala/collection/mutable/Map;
InterfaceMethod	scala/collection/mutable/MapLike.$minus$minus:(Lscala/collection/Iterator;)Lscala/collection/mutable/Map;
Asciz	(Lscala/collection/Traversable;)Lscala/collection/generic/Subtractable;;
NameAndType	$minus$minus:(Lscala/collection/Traversable;)Lscala/collection/mutable/Map;
InterfaceMethod	scala/collection/mutable/MapLike.$minus$minus:(Lscala/collection/Traversable;)Lscala/collection/mutable/Map;
Asciz	(Ljava/lang/Object;Ljava/lang/Object;Lscala/collection/Seq;)Lscala/collection/generic/Subtractable;;
NameAndType	$minus:(Ljava/lang/Object;Ljava/lang/Object;Lscala/collection/Seq;)Lscala/collection/mutable/Map;
InterfaceMethod	scala/collection/mutable/MapLike.$minus:(Ljava/lang/Object;Ljava/lang/Object;Lscala/collection/Seq;)Lscala/collection/mutable/Map;
NameAndType	result:()Lscala/collection/mutable/Map;
InterfaceMethod	scala/collection/mutable/MapLike.result:()Lscala/collection/mutable/Map;
NameAndType	clone:()Lscala/collection/mutable/Map;
InterfaceMethod	scala/collection/mutable/MapLike.clone:()Lscala/collection/mutable/Map;
Asciz	(Ljava/lang/Object;)Lscala/collection/generic/Subtractable;;
NameAndType	$minus:(Ljava/lang/Object;)Lscala/collection/mutable/Map;
InterfaceMethod	scala/collection/mutable/MapLike.$minus:(Ljava/lang/Object;)Lscala/collection/mutable/Map;
Asciz	elem;
Asciz	(Ljava/lang/Object;)Lscala/collection/Map;;
Asciz	(Lscala/collection/Iterator;)Lscala/collection/Map;;
NameAndType	$plus$plus:(Lscala/collection/Iterator;)Lscala/collection/mutable/Map;
InterfaceMethod	scala/collection/mutable/MapLike.$plus$plus:(Lscala/collection/Iterator;)Lscala/collection/mutable/Map;
Asciz	(Lscala/collection/Traversable;)Lscala/collection/Map;;
NameAndType	$plus$plus:(Lscala/collection/Traversable;)Lscala/collection/mutable/Map;
InterfaceMethod	scala/collection/mutable/MapLike.$plus$plus:(Lscala/collection/Traversable;)Lscala/collection/mutable/Map;
Asciz	(Lscala/Tuple2;Lscala/Tuple2;Lscala/collection/Seq;)Lscala/collection/Map;;
NameAndType	$plus:(Lscala/Tuple2;Lscala/Tuple2;Lscala/collection/Seq;)Lscala/collection/mutable/Map;
InterfaceMethod	scala/collection/mutable/MapLike.$plus:(Lscala/Tuple2;Lscala/Tuple2;Lscala/collection/Seq;)Lscala/collection/mutable/Map;
Asciz	kv1;
Asciz	kv2;
Asciz	(Lscala/Tuple2;)Lscala/collection/Map;;
NameAndType	$plus:(Lscala/Tuple2;)Lscala/collection/mutable/Map;
InterfaceMethod	scala/collection/mutable/MapLike.$plus:(Lscala/Tuple2;)Lscala/collection/mutable/Map;
Asciz	(Ljava/lang/Object;Ljava/lang/Object;)Lscala/collection/Map;;
NameAndType	updated:(Ljava/lang/Object;Ljava/lang/Object;)Lscala/collection/mutable/Map;
InterfaceMethod	scala/collection/mutable/MapLike.updated:(Ljava/lang/Object;Ljava/lang/Object;)Lscala/collection/mutable/Map;
Asciz	(Ljava/lang/Object;)Lscala/collection/generic/Shrinkable;;
Asciz	scala/collection/JavaConversions$JMapWrapperLike;
class	scala/collection/JavaConversions$JMapWrapperLike
NameAndType	$minus$eq:(Ljava/lang/Object;)Lscala/collection/JavaConversions$JMapWrapperLike;
InterfaceMethod	scala/collection/JavaConversions$JMapWrapperLike.$minus$eq:(Ljava/lang/Object;)Lscala/collection/JavaConversions$JMapWrapperLike;
Asciz	(Ljava/lang/Object;)Lscala/collection/mutable/MapLike;;
Asciz	(Ljava/lang/Object;)Lscala/collection/generic/Growable;;
Asciz	scala/Tuple2;
class	scala/Tuple2
NameAndType	$plus$eq:(Lscala/Tuple2;)Lscala/collection/JavaConversions$JMapWrapperLike;
InterfaceMethod	scala/collection/JavaConversions$JMapWrapperLike.$plus$eq:(Lscala/Tuple2;)Lscala/collection/JavaConversions$JMapWrapperLike;
Asciz	(Ljava/lang/Object;)Lscala/collection/mutable/Builder;;
Asciz	(Lscala/Tuple2;)Lscala/collection/mutable/MapLike;;
Asciz	()Lscala/collection/Map;;
NameAndType	empty:()Lscala/collection/JavaConversions$JConcurrentMapWrapper;
Method	scala/collection/JavaConversions$JConcurrentMapWrapper.empty:()Lscala/collection/JavaConversions$JConcurrentMapWrapper;
Asciz	()Ljava/util/Map;;
Method	java/lang/Object."<init>":()V
Asciz	$init$;
Asciz	(Lscala/collection/TraversableLike;)V;
NameAndType	$init$:(Lscala/collection/TraversableLike;)V
Method	scala/collection/TraversableLike$class.$init$:(Lscala/collection/TraversableLike;)V
Asciz	(Lscala/collection/generic/GenericTraversableTemplate;)V;
NameAndType	$init$:(Lscala/collection/generic/GenericTraversableTemplate;)V
Method	scala/collection/generic/GenericTraversableTemplate$class.$init$:(Lscala/collection/generic/GenericTraversableTemplate;)V
Asciz	scala/collection/Traversable$class;
class	scala/collection/Traversable$class
Asciz	(Lscala/collection/Traversable;)V;
NameAndType	$init$:(Lscala/collection/Traversable;)V
Method	scala/collection/Traversable$class.$init$:(Lscala/collection/Traversable;)V
Asciz	scala/collection/mutable/Traversable$class;
class	scala/collection/mutable/Traversable$class
Asciz	(Lscala/collection/mutable/Traversable;)V;
NameAndType	$init$:(Lscala/collection/mutable/Traversable;)V
Method	scala/collection/mutable/Traversable$class.$init$:(Lscala/collection/mutable/Traversable;)V
Asciz	(Lscala/collection/IterableLike;)V;
NameAndType	$init$:(Lscala/collection/IterableLike;)V
Method	scala/collection/IterableLike$class.$init$:(Lscala/collection/IterableLike;)V
Asciz	scala/collection/Iterable$class;
class	scala/collection/Iterable$class
Asciz	(Lscala/collection/Iterable;)V;
NameAndType	$init$:(Lscala/collection/Iterable;)V
Method	scala/collection/Iterable$class.$init$:(Lscala/collection/Iterable;)V
Asciz	(Lscala/collection/mutable/Iterable;)V;
NameAndType	$init$:(Lscala/collection/mutable/Iterable;)V
Method	scala/collection/mutable/Iterable$class.$init$:(Lscala/collection/mutable/Iterable;)V
NameAndType	$init$:(Lscala/Function1;)V
Method	scala/Function1$class.$init$:(Lscala/Function1;)V
Asciz	(Lscala/PartialFunction;)V;
NameAndType	$init$:(Lscala/PartialFunction;)V
Method	scala/PartialFunction$class.$init$:(Lscala/PartialFunction;)V
Asciz	scala/collection/generic/Subtractable$class;
class	scala/collection/generic/Subtractable$class
Asciz	(Lscala/collection/generic/Subtractable;)V;
NameAndType	$init$:(Lscala/collection/generic/Subtractable;)V
Method	scala/collection/generic/Subtractable$class.$init$:(Lscala/collection/generic/Subtractable;)V
Asciz	(Lscala/collection/MapLike;)V;
NameAndType	$init$:(Lscala/collection/MapLike;)V
Method	scala/collection/MapLike$class.$init$:(Lscala/collection/MapLike;)V
Asciz	scala/collection/Map$class;
class	scala/collection/Map$class
Asciz	(Lscala/collection/Map;)V;
NameAndType	$init$:(Lscala/collection/Map;)V
Method	scala/collection/Map$class.$init$:(Lscala/collection/Map;)V
Asciz	(Lscala/collection/generic/Growable;)V;
NameAndType	$init$:(Lscala/collection/generic/Growable;)V
Method	scala/collection/generic/Growable$class.$init$:(Lscala/collection/generic/Growable;)V
Asciz	(Lscala/collection/mutable/Builder;)V;
NameAndType	$init$:(Lscala/collection/mutable/Builder;)V
Method	scala/collection/mutable/Builder$class.$init$:(Lscala/collection/mutable/Builder;)V
Asciz	(Lscala/collection/generic/Shrinkable;)V;
NameAndType	$init$:(Lscala/collection/generic/Shrinkable;)V
Method	scala/collection/generic/Shrinkable$class.$init$:(Lscala/collection/generic/Shrinkable;)V
Asciz	scala/collection/mutable/Cloneable$class;
class	scala/collection/mutable/Cloneable$class
Asciz	(Lscala/collection/mutable/Cloneable;)V;
NameAndType	$init$:(Lscala/collection/mutable/Cloneable;)V
Method	scala/collection/mutable/Cloneable$class.$init$:(Lscala/collection/mutable/Cloneable;)V
Asciz	(Lscala/collection/mutable/MapLike;)V;
NameAndType	$init$:(Lscala/collection/mutable/MapLike;)V
Method	scala/collection/mutable/MapLike$class.$init$:(Lscala/collection/mutable/MapLike;)V
Asciz	scala/collection/mutable/Map$class;
class	scala/collection/mutable/Map$class
Asciz	(Lscala/collection/mutable/Map;)V;
NameAndType	$init$:(Lscala/collection/mutable/Map;)V
Method	scala/collection/mutable/Map$class.$init$:(Lscala/collection/mutable/Map;)V
NameAndType	$init$:(Lscala/collection/JavaConversions$JMapWrapperLike;)V
Method	scala/collection/JavaConversions$JMapWrapperLike$class.$init$:(Lscala/collection/JavaConversions$JMapWrapperLike;)V
Asciz	(Lscala/Product;)V;
NameAndType	$init$:(Lscala/Product;)V
Method	scala/Product$class.$init$:(Lscala/Product;)V
Asciz	(Ljava/util/concurrent/ConcurrentMap<TA;TB;>;)V;
Asciz	<A:Ljava/lang/Object;B:Ljava/lang/Object;>Ljava/lang/Object;Lscala/collection/JavaConversions$JMapWrapperLike<TA;TB;Lscala/collection/JavaConversions$JConcurrentMapWrapper<TA;TB;>;>;Lscala/collection/mutable/ConcurrentMap<TA;TB;>;Lscala/ScalaObject;Lscala/Product;;
Asciz	Scala;
Asciz	InnerClasses;
Asciz	scala/Predef$$less$colon$less;
class	scala/Predef$$less$colon$less
Asciz	scala/Predef;
class	scala/Predef
Asciz	$less$colon$less;
Asciz	scala/collection/TraversableLike$WithFilter;
class	scala/collection/TraversableLike$WithFilter
Asciz	WithFilter;
Asciz	scala/collection/JavaConversions;
class	scala/collection/JavaConversions
Asciz	JMapWrapperLike;
Asciz	scala/collection/mutable/ConcurrentMap;
class	scala/collection/mutable/ConcurrentMap
Asciz	scala/ScalaObject;
class	scala/ScalaObject
Asciz	scala/Product;
class	scala/Product
Asciz	java/io/Serializable;
class	java/io/Serializable

{
private final java.util.concurrent.ConcurrentMap underlying;
  Signature: Ljava/util/concurrent/ConcurrentMap;
  Signature: length = 0x2
   00 05 

public java.lang.String productElementName(int);
  Signature: (I)Ljava/lang/String;
  Code:
   Stack=2, Locals=2, Args_size=2
	aload_0
	iload_1
	invokestatic	Method scala/Product$class.productElementName:(Lscala/Product;I)Ljava/lang/String;
	areturn
  Labels:
  LocalVariableTable: 
   Start  Length  Slot  Name   Signature
   0      6      0    this       Lscala/collection/JavaConversions$JConcurrentMapWrapper;
   0      6      1    n       I


public scala.collection.Iterator productIterator();
  Signature: ()Lscala/collection/Iterator;
  Code:
   Stack=1, Locals=1, Args_size=1
	aload_0
	invokestatic	Method scala/Product$class.productIterator:(Lscala/Product;)Lscala/collection/Iterator;
	areturn
  Labels:

public scala.collection.Iterator productElements();
  Signature: ()Lscala/collection/Iterator;
  Code:
   Stack=1, Locals=1, Args_size=1
	aload_0
	invokestatic	Method scala/Product$class.productElements:(Lscala/Product;)Lscala/collection/Iterator;
	areturn
  Labels:
  Deprecated: true

public int size();
  Signature: ()I
  Code:
   Stack=1, Locals=1, Args_size=1
	aload_0
	invokestatic	Method scala/collection/JavaConversions$JMapWrapperLike$class.size:(Lscala/collection/JavaConversions$JMapWrapperLike;)I
	ireturn
  Labels:

public scala.collection.JavaConversions$JMapWrapperLike $plus$eq(scala.Tuple2);
  Signature: (Lscala/Tuple2;)Lscala/collection/JavaConversions$JMapWrapperLike;
  Code:
   Stack=2, Locals=2, Args_size=2
	aload_0
	aload_1
	invokestatic	Method scala/collection/JavaConversions$JMapWrapperLike$class.$plus$eq:(Lscala/collection/JavaConversions$JMapWrapperLike;Lscala/Tuple2;)Lscala/collection/JavaConversions$JMapWrapperLike;
	areturn
  Labels:
  LocalVariableTable: 
   Start  Length  Slot  Name   Signature
   0      6      0    this       Lscala/collection/JavaConversions$JConcurrentMapWrapper;
   0      6      1    kv       Lscala/Tuple2;


public scala.collection.JavaConversions$JMapWrapperLike $minus$eq(java.lang.Object);
  Signature: (Ljava/lang/Object;)Lscala/collection/JavaConversions$JMapWrapperLike;
  Code:
   Stack=2, Locals=2, Args_size=2
	aload_0
	aload_1
	invokestatic	Method scala/collection/JavaConversions$JMapWrapperLike$class.$minus$eq:(Lscala/collection/JavaConversions$JMapWrapperLike;Ljava/lang/Object;)Lscala/collection/JavaConversions$JMapWrapperLike;
	areturn
  Labels:
  LocalVariableTable: 
   Start  Length  Slot  Name   Signature
   0      6      0    this       Lscala/collection/JavaConversions$JConcurrentMapWrapper;
   0      6      1    key       Ljava/lang/Object;


public scala.Option put(java.lang.Object, java.lang.Object);
  Signature: (Ljava/lang/Object;Ljava/lang/Object;)Lscala/Option;
  Code:
   Stack=3, Locals=3, Args_size=3
	aload_0
	aload_1
	aload_2
	invokestatic	Method scala/collection/JavaConversions$JMapWrapperLike$class.put:(Lscala/collection/JavaConversions$JMapWrapperLike;Ljava/lang/Object;Ljava/lang/Object;)Lscala/Option;
	areturn
  Labels:
  LocalVariableTable: 
   Start  Length  Slot  Name   Signature
   0      7      0    this       Lscala/collection/JavaConversions$JConcurrentMapWrapper;
   0      7      1    k       Ljava/lang/Object;
   0      7      2    v       Ljava/lang/Object;


public void update(java.lang.Object, java.lang.Object);
  Signature: (Ljava/lang/Object;Ljava/lang/Object;)V
  Code:
   Stack=3, Locals=3, Args_size=3
	aload_0
	aload_1
	aload_2
	invokestatic	Method scala/collection/JavaConversions$JMapWrapperLike$class.update:(Lscala/collection/JavaConversions$JMapWrapperLike;Ljava/lang/Object;Ljava/lang/Object;)V
	return
  Labels:
  LocalVariableTable: 
   Start  Length  Slot  Name   Signature
   0      7      0    this       Lscala/collection/JavaConversions$JConcurrentMapWrapper;
   0      7      1    k       Ljava/lang/Object;
   0      7      2    v       Ljava/lang/Object;


public scala.Option remove(java.lang.Object);
  Signature: (Ljava/lang/Object;)Lscala/Option;
  Code:
   Stack=2, Locals=2, Args_size=2
	aload_0
	aload_1
	invokestatic	Method scala/collection/JavaConversions$JMapWrapperLike$class.remove:(Lscala/collection/JavaConversions$JMapWrapperLike;Ljava/lang/Object;)Lscala/Option;
	areturn
  Labels:
  LocalVariableTable: 
   Start  Length  Slot  Name   Signature
   0      6      0    this       Lscala/collection/JavaConversions$JConcurrentMapWrapper;
   0      6      1    k       Ljava/lang/Object;


public scala.collection.Iterator iterator();
  Signature: ()Lscala/collection/Iterator;
  Code:
   Stack=1, Locals=1, Args_size=1
	aload_0
	invokestatic	Method scala/collection/JavaConversions$JMapWrapperLike$class.iterator:(Lscala/collection/JavaConversions$JMapWrapperLike;)Lscala/collection/Iterator;
	areturn
  Labels:

public void clear();
  Signature: ()V
  Code:
   Stack=1, Locals=1, Args_size=1
	aload_0
	invokestatic	Method scala/collection/JavaConversions$JMapWrapperLike$class.clear:(Lscala/collection/JavaConversions$JMapWrapperLike;)V
	return
  Labels:

public scala.collection.mutable.Builder newBuilder();
  Signature: ()Lscala/collection/mutable/Builder;
  Code:
   Stack=1, Locals=1, Args_size=1
	aload_0
	invokestatic	Method scala/collection/mutable/MapLike$class.newBuilder:(Lscala/collection/mutable/MapLike;)Lscala/collection/mutable/Builder;
	areturn
  Labels:

public scala.collection.mutable.Map updated(java.lang.Object, java.lang.Object);
  Signature: (Ljava/lang/Object;Ljava/lang/Object;)Lscala/collection/mutable/Map;
  Code:
   Stack=3, Locals=3, Args_size=3
	aload_0
	aload_1
	aload_2
	invokestatic	Method scala/collection/mutable/MapLike$class.updated:(Lscala/collection/mutable/MapLike;Ljava/lang/Object;Ljava/lang/Object;)Lscala/collection/mutable/Map;
	areturn
  Labels:
  LocalVariableTable: 
   Start  Length  Slot  Name   Signature
   0      7      0    this       Lscala/collection/JavaConversions$JConcurrentMapWrapper;
   0      7      1    key       Ljava/lang/Object;
   0      7      2    value       Ljava/lang/Object;


public scala.collection.mutable.Map $plus(scala.Tuple2);
  Signature: (Lscala/Tuple2;)Lscala/collection/mutable/Map;
  Code:
   Stack=2, Locals=2, Args_size=2
	aload_0
	aload_1
	invokestatic	Method scala/collection/mutable/MapLike$class.$plus:(Lscala/collection/mutable/MapLike;Lscala/Tuple2;)Lscala/collection/mutable/Map;
	areturn
  Labels:
  LocalVariableTable: 
   Start  Length  Slot  Name   Signature
   0      6      0    this       Lscala/collection/JavaConversions$JConcurrentMapWrapper;
   0      6      1    kv       Lscala/Tuple2;


public scala.collection.mutable.Map $plus(scala.Tuple2, scala.Tuple2, scala.collection.Seq);
  Signature: (Lscala/Tuple2;Lscala/Tuple2;Lscala/collection/Seq;)Lscala/collection/mutable/Map;
  Code:
   Stack=4, Locals=4, Args_size=4
	aload_0
	aload_1
	aload_2
	aload_3
	invokestatic	Method scala/collection/mutable/MapLike$class.$plus:(Lscala/collection/mutable/MapLike;Lscala/Tuple2;Lscala/Tuple2;Lscala/collection/Seq;)Lscala/collection/mutable/Map;
	areturn
  Labels:
  LocalVariableTable: 
   Start  Length  Slot  Name   Signature
   0      8      0    this       Lscala/collection/JavaConversions$JConcurrentMapWrapper;
   0      8      1    elem1       Lscala/Tuple2;
   0      8      2    elem2       Lscala/Tuple2;
   0      8      3    elems       Lscala/collection/Seq;


public scala.collection.mutable.Map $plus$plus(scala.collection.Traversable);
  Signature: (Lscala/collection/Traversable;)Lscala/collection/mutable/Map;
  Code:
   Stack=2, Locals=2, Args_size=2
	aload_0
	aload_1
	invokestatic	Method scala/collection/mutable/MapLike$class.$plus$plus:(Lscala/collection/mutable/MapLike;Lscala/collection/Traversable;)Lscala/collection/mutable/Map;
	areturn
  Labels:
  LocalVariableTable: 
   Start  Length  Slot  Name   Signature
   0      6      0    this       Lscala/collection/JavaConversions$JConcurrentMapWrapper;
   0      6      1    kvs       Lscala/collection/Traversable;


public scala.collection.mutable.Map $plus$plus(scala.collection.Iterator);
  Signature: (Lscala/collection/Iterator;)Lscala/collection/mutable/Map;
  Code:
   Stack=2, Locals=2, Args_size=2
	aload_0
	aload_1
	invokestatic	Method scala/collection/mutable/MapLike$class.$plus$plus:(Lscala/collection/mutable/MapLike;Lscala/collection/Iterator;)Lscala/collection/mutable/Map;
	areturn
  Labels:
  LocalVariableTable: 
   Start  Length  Slot  Name   Signature
   0      6      0    this       Lscala/collection/JavaConversions$JConcurrentMapWrapper;
   0      6      1    iter       Lscala/collection/Iterator;


public scala.collection.mutable.Map $minus(java.lang.Object);
  Signature: (Ljava/lang/Object;)Lscala/collection/mutable/Map;
  Code:
   Stack=2, Locals=2, Args_size=2
	aload_0
	aload_1
	invokestatic	Method scala/collection/mutable/MapLike$class.$minus:(Lscala/collection/mutable/MapLike;Ljava/lang/Object;)Lscala/collection/mutable/Map;
	areturn
  Labels:
  LocalVariableTable: 
   Start  Length  Slot  Name   Signature
   0      6      0    this       Lscala/collection/JavaConversions$JConcurrentMapWrapper;
   0      6      1    key       Ljava/lang/Object;


public scala.Option removeKey(java.lang.Object);
  Signature: (Ljava/lang/Object;)Lscala/Option;
  Code:
   Stack=2, Locals=2, Args_size=2
	aload_0
	aload_1
	invokestatic	Method scala/collection/mutable/MapLike$class.removeKey:(Lscala/collection/mutable/MapLike;Ljava/lang/Object;)Lscala/Option;
	areturn
  Labels:
  LocalVariableTable: 
   Start  Length  Slot  Name   Signature
   0      6      0    this       Lscala/collection/JavaConversions$JConcurrentMapWrapper;
   0      6      1    key       Ljava/lang/Object;

  Deprecated: true

public java.lang.Object getOrElseUpdate(java.lang.Object, scala.Function0);
  Signature: (Ljava/lang/Object;Lscala/Function0;)Ljava/lang/Object;
  Code:
   Stack=3, Locals=3, Args_size=3
	aload_0
	aload_1
	aload_2
	invokestatic	Method scala/collection/mutable/MapLike$class.getOrElseUpdate:(Lscala/collection/mutable/MapLike;Ljava/lang/Object;Lscala/Function0;)Ljava/lang/Object;
	areturn
  Labels:
  LocalVariableTable: 
   Start  Length  Slot  Name   Signature
   0      7      0    this       Lscala/collection/JavaConversions$JConcurrentMapWrapper;
   0      7      1    key       Ljava/lang/Object;
   0      7      2    op       Lscala/Function0;


public scala.collection.mutable.MapLike transform(scala.Function2);
  Signature: (Lscala/Function2;)Lscala/collection/mutable/MapLike;
  Code:
   Stack=2, Locals=2, Args_size=2
	aload_0
	aload_1
	invokestatic	Method scala/collection/mutable/MapLike$class.transform:(Lscala/collection/mutable/MapLike;Lscala/Function2;)Lscala/collection/mutable/MapLike;
	areturn
  Labels:
  LocalVariableTable: 
   Start  Length  Slot  Name   Signature
   0      6      0    this       Lscala/collection/JavaConversions$JConcurrentMapWrapper;
   0      6      1    f       Lscala/Function2;


public scala.collection.mutable.MapLike retain(scala.Function2);
  Signature: (Lscala/Function2;)Lscala/collection/mutable/MapLike;
  Code:
   Stack=2, Locals=2, Args_size=2
	aload_0
	aload_1
	invokestatic	Method scala/collection/mutable/MapLike$class.retain:(Lscala/collection/mutable/MapLike;Lscala/Function2;)Lscala/collection/mutable/MapLike;
	areturn
  Labels:
  LocalVariableTable: 
   Start  Length  Slot  Name   Signature
   0      6      0    this       Lscala/collection/JavaConversions$JConcurrentMapWrapper;
   0      6      1    p       Lscala/Function2;

  Deprecated: true

public scala.collection.mutable.Map clone();
  Signature: ()Lscala/collection/mutable/Map;
  Code:
   Stack=1, Locals=1, Args_size=1
	aload_0
	invokestatic	Method scala/collection/mutable/MapLike$class.clone:(Lscala/collection/mutable/MapLike;)Lscala/collection/mutable/Map;
	areturn
  Labels:

public scala.collection.mutable.Map result();
  Signature: ()Lscala/collection/mutable/Map;
  Code:
   Stack=1, Locals=1, Args_size=1
	aload_0
	invokestatic	Method scala/collection/mutable/MapLike$class.result:(Lscala/collection/mutable/MapLike;)Lscala/collection/mutable/Map;
	areturn
  Labels:

public scala.collection.mutable.Map $minus(java.lang.Object, java.lang.Object, scala.collection.Seq);
  Signature: (Ljava/lang/Object;Ljava/lang/Object;Lscala/collection/Seq;)Lscala/collection/mutable/Map;
  Code:
   Stack=4, Locals=4, Args_size=4
	aload_0
	aload_1
	aload_2
	aload_3
	invokestatic	Method scala/collection/mutable/MapLike$class.$minus:(Lscala/collection/mutable/MapLike;Ljava/lang/Object;Ljava/lang/Object;Lscala/collection/Seq;)Lscala/collection/mutable/Map;
	areturn
  Labels:
  LocalVariableTable: 
   Start  Length  Slot  Name   Signature
   0      8      0    this       Lscala/collection/JavaConversions$JConcurrentMapWrapper;
   0      8      1    elem1       Ljava/lang/Object;
   0      8      2    elem2       Ljava/lang/Object;
   0      8      3    elems       Lscala/collection/Seq;


public scala.collection.mutable.Map $minus$minus(scala.collection.Traversable);
  Signature: (Lscala/collection/Traversable;)Lscala/collection/mutable/Map;
  Code:
   Stack=2, Locals=2, Args_size=2
	aload_0
	aload_1
	invokestatic	Method scala/collection/mutable/MapLike$class.$minus$minus:(Lscala/collection/mutable/MapLike;Lscala/collection/Traversable;)Lscala/collection/mutable/Map;
	areturn
  Labels:
  LocalVariableTable: 
   Start  Length  Slot  Name   Signature
   0      6      0    this       Lscala/collection/JavaConversions$JConcurrentMapWrapper;
   0      6      1    kvs       Lscala/collection/Traversable;


public scala.collection.mutable.Map $minus$minus(scala.collection.Iterator);
  Signature: (Lscala/collection/Iterator;)Lscala/collection/mutable/Map;
  Code:
   Stack=2, Locals=2, Args_size=2
	aload_0
	aload_1
	invokestatic	Method scala/collection/mutable/MapLike$class.$minus$minus:(Lscala/collection/mutable/MapLike;Lscala/collection/Iterator;)Lscala/collection/mutable/Map;
	areturn
  Labels:
  LocalVariableTable: 
   Start  Length  Slot  Name   Signature
   0      6      0    this       Lscala/collection/JavaConversions$JConcurrentMapWrapper;
   0      6      1    iter       Lscala/collection/Iterator;


public final java.lang.Object scala$collection$mutable$Cloneable$$super$clone();
  Signature: ()Ljava/lang/Object;
  Code:
   Stack=1, Locals=1, Args_size=1
	aload_0
	invokespecial	Method java/lang/Object.clone:()Ljava/lang/Object;
	areturn
  Labels:

public scala.collection.generic.Shrinkable $minus$eq(java.lang.Object, java.lang.Object, scala.collection.Seq);
  Signature: (Ljava/lang/Object;Ljava/lang/Object;Lscala/collection/Seq;)Lscala/collection/generic/Shrinkable;
  Code:
   Stack=4, Locals=4, Args_size=4
	aload_0
	aload_1
	aload_2
	aload_3
	invokestatic	Method scala/collection/generic/Shrinkable$class.$minus$eq:(Lscala/collection/generic/Shrinkable;Ljava/lang/Object;Ljava/lang/Object;Lscala/collection/Seq;)Lscala/collection/generic/Shrinkable;
	areturn
  Labels:
  LocalVariableTable: 
   Start  Length  Slot  Name   Signature
   0      8      0    this       Lscala/collection/JavaConversions$JConcurrentMapWrapper;
   0      8      1    elem1       Ljava/lang/Object;
   0      8      2    elem2       Ljava/lang/Object;
   0      8      3    elems       Lscala/collection/Seq;


public scala.collection.generic.Shrinkable $minus$minus$eq(scala.collection.Iterator);
  Signature: (Lscala/collection/Iterator;)Lscala/collection/generic/Shrinkable;
  Code:
   Stack=2, Locals=2, Args_size=2
	aload_0
	aload_1
	invokestatic	Method scala/collection/generic/Shrinkable$class.$minus$minus$eq:(Lscala/collection/generic/Shrinkable;Lscala/collection/Iterator;)Lscala/collection/generic/Shrinkable;
	areturn
  Labels:
  LocalVariableTable: 
   Start  Length  Slot  Name   Signature
   0      6      0    this       Lscala/collection/JavaConversions$JConcurrentMapWrapper;
   0      6      1    iter       Lscala/collection/Iterator;


public scala.collection.generic.Shrinkable $minus$minus$eq(scala.collection.Traversable);
  Signature: (Lscala/collection/Traversable;)Lscala/collection/generic/Shrinkable;
  Code:
   Stack=2, Locals=2, Args_size=2
	aload_0
	aload_1
	invokestatic	Method scala/collection/generic/Shrinkable$class.$minus$minus$eq:(Lscala/collection/generic/Shrinkable;Lscala/collection/Traversable;)Lscala/collection/generic/Shrinkable;
	areturn
  Labels:
  LocalVariableTable: 
   Start  Length  Slot  Name   Signature
   0      6      0    this       Lscala/collection/JavaConversions$JConcurrentMapWrapper;
   0      6      1    iter       Lscala/collection/Traversable;


public void sizeHint(int);
  Signature: (I)V
  Code:
   Stack=2, Locals=2, Args_size=2
	aload_0
	iload_1
	invokestatic	Method scala/collection/mutable/Builder$class.sizeHint:(Lscala/collection/mutable/Builder;I)V
	return
  Labels:
  LocalVariableTable: 
   Start  Length  Slot  Name   Signature
   0      6      0    this       Lscala/collection/JavaConversions$JConcurrentMapWrapper;
   0      6      1    size       I


public scala.collection.mutable.Builder mapResult(scala.Function1);
  Signature: (Lscala/Function1;)Lscala/collection/mutable/Builder;
  Code:
   Stack=2, Locals=2, Args_size=2
	aload_0
	aload_1
	invokestatic	Method scala/collection/mutable/Builder$class.mapResult:(Lscala/collection/mutable/Builder;Lscala/Function1;)Lscala/collection/mutable/Builder;
	areturn
  Labels:
  LocalVariableTable: 
   Start  Length  Slot  Name   Signature
   0      6      0    this       Lscala/collection/JavaConversions$JConcurrentMapWrapper;
   0      6      1    f       Lscala/Function1;


public scala.collection.generic.Growable $plus$eq(java.lang.Object, java.lang.Object, scala.collection.Seq);
  Signature: (Ljava/lang/Object;Ljava/lang/Object;Lscala/collection/Seq;)Lscala/collection/generic/Growable;
  Code:
   Stack=4, Locals=4, Args_size=4
	aload_0
	aload_1
	aload_2
	aload_3
	invokestatic	Method scala/collection/generic/Growable$class.$plus$eq:(Lscala/collection/generic/Growable;Ljava/lang/Object;Ljava/lang/Object;Lscala/collection/Seq;)Lscala/collection/generic/Growable;
	areturn
  Labels:
  LocalVariableTable: 
   Start  Length  Slot  Name   Signature
   0      8      0    this       Lscala/collection/JavaConversions$JConcurrentMapWrapper;
   0      8      1    elem1       Ljava/lang/Object;
   0      8      2    elem2       Ljava/lang/Object;
   0      8      3    elems       Lscala/collection/Seq;


public scala.collection.generic.Growable $plus$plus$eq(scala.collection.Iterator);
  Signature: (Lscala/collection/Iterator;)Lscala/collection/generic/Growable;
  Code:
   Stack=2, Locals=2, Args_size=2
	aload_0
	aload_1
	invokestatic	Method scala/collection/generic/Growable$class.$plus$plus$eq:(Lscala/collection/generic/Growable;Lscala/collection/Iterator;)Lscala/collection/generic/Growable;
	areturn
  Labels:
  LocalVariableTable: 
   Start  Length  Slot  Name   Signature
   0      6      0    this       Lscala/collection/JavaConversions$JConcurrentMapWrapper;
   0      6      1    iter       Lscala/collection/Iterator;


public scala.collection.generic.Growable $plus$plus$eq(scala.collection.Traversable);
  Signature: (Lscala/collection/Traversable;)Lscala/collection/generic/Growable;
  Code:
   Stack=2, Locals=2, Args_size=2
	aload_0
	aload_1
	invokestatic	Method scala/collection/generic/Growable$class.$plus$plus$eq:(Lscala/collection/generic/Growable;Lscala/collection/Traversable;)Lscala/collection/generic/Growable;
	areturn
  Labels:
  LocalVariableTable: 
   Start  Length  Slot  Name   Signature
   0      6      0    this       Lscala/collection/JavaConversions$JConcurrentMapWrapper;
   0      6      1    elems       Lscala/collection/Traversable;


public boolean isEmpty();
  Signature: ()Z
  Code:
   Stack=1, Locals=1, Args_size=1
	aload_0
	invokestatic	Method scala/collection/MapLike$class.isEmpty:(Lscala/collection/MapLike;)Z
	ireturn
  Labels:

public java.lang.Object getOrElse(java.lang.Object, scala.Function0);
  Signature: (Ljava/lang/Object;Lscala/Function0;)Ljava/lang/Object;
  Code:
   Stack=3, Locals=3, Args_size=3
	aload_0
	aload_1
	aload_2
	invokestatic	Method scala/collection/MapLike$class.getOrElse:(Lscala/collection/MapLike;Ljava/lang/Object;Lscala/Function0;)Ljava/lang/Object;
	areturn
  Labels:
  LocalVariableTable: 
   Start  Length  Slot  Name   Signature
   0      7      0    this       Lscala/collection/JavaConversions$JConcurrentMapWrapper;
   0      7      1    key       Ljava/lang/Object;
   0      7      2    default       Lscala/Function0;


public java.lang.Object apply(java.lang.Object);
  Signature: (Ljava/lang/Object;)Ljava/lang/Object;
  Code:
   Stack=2, Locals=2, Args_size=2
	aload_0
	aload_1
	invokestatic	Method scala/collection/MapLike$class.apply:(Lscala/collection/MapLike;Ljava/lang/Object;)Ljava/lang/Object;
	areturn
  Labels:
  LocalVariableTable: 
   Start  Length  Slot  Name   Signature
   0      6      0    this       Lscala/collection/JavaConversions$JConcurrentMapWrapper;
   0      6      1    key       Ljava/lang/Object;


public boolean contains(java.lang.Object);
  Signature: (Ljava/lang/Object;)Z
  Code:
   Stack=2, Locals=2, Args_size=2
	aload_0
	aload_1
	invokestatic	Method scala/collection/MapLike$class.contains:(Lscala/collection/MapLike;Ljava/lang/Object;)Z
	ireturn
  Labels:
  LocalVariableTable: 
   Start  Length  Slot  Name   Signature
   0      6      0    this       Lscala/collection/JavaConversions$JConcurrentMapWrapper;
   0      6      1    key       Ljava/lang/Object;


public boolean isDefinedAt(java.lang.Object);
  Signature: (Ljava/lang/Object;)Z
  Code:
   Stack=2, Locals=2, Args_size=2
	aload_0
	aload_1
	invokestatic	Method scala/collection/MapLike$class.isDefinedAt:(Lscala/collection/MapLike;Ljava/lang/Object;)Z
	ireturn
  Labels:
  LocalVariableTable: 
   Start  Length  Slot  Name   Signature
   0      6      0    this       Lscala/collection/JavaConversions$JConcurrentMapWrapper;
   0      6      1    key       Ljava/lang/Object;


public scala.collection.Set keySet();
  Signature: ()Lscala/collection/Set;
  Code:
   Stack=1, Locals=1, Args_size=1
	aload_0
	invokestatic	Method scala/collection/MapLike$class.keySet:(Lscala/collection/MapLike;)Lscala/collection/Set;
	areturn
  Labels:

public scala.collection.Iterator keysIterator();
  Signature: ()Lscala/collection/Iterator;
  Code:
   Stack=1, Locals=1, Args_size=1
	aload_0
	invokestatic	Method scala/collection/MapLike$class.keysIterator:(Lscala/collection/MapLike;)Lscala/collection/Iterator;
	areturn
  Labels:

public scala.collection.Iterable keys();
  Signature: ()Lscala/collection/Iterable;
  Code:
   Stack=1, Locals=1, Args_size=1
	aload_0
	invokestatic	Method scala/collection/MapLike$class.keys:(Lscala/collection/MapLike;)Lscala/collection/Iterable;
	areturn
  Labels:

public scala.collection.Iterable values();
  Signature: ()Lscala/collection/Iterable;
  Code:
   Stack=1, Locals=1, Args_size=1
	aload_0
	invokestatic	Method scala/collection/MapLike$class.values:(Lscala/collection/MapLike;)Lscala/collection/Iterable;
	areturn
  Labels:

public scala.collection.Iterator valuesIterator();
  Signature: ()Lscala/collection/Iterator;
  Code:
   Stack=1, Locals=1, Args_size=1
	aload_0
	invokestatic	Method scala/collection/MapLike$class.valuesIterator:(Lscala/collection/MapLike;)Lscala/collection/Iterator;
	areturn
  Labels:

public java.lang.Object default(java.lang.Object);
  Signature: (Ljava/lang/Object;)Ljava/lang/Object;
  Code:
   Stack=2, Locals=2, Args_size=2
	aload_0
	aload_1
	invokestatic	Method scala/collection/MapLike$class.default:(Lscala/collection/MapLike;Ljava/lang/Object;)Ljava/lang/Object;
	areturn
  Labels:
  LocalVariableTable: 
   Start  Length  Slot  Name   Signature
   0      6      0    this       Lscala/collection/JavaConversions$JConcurrentMapWrapper;
   0      6      1    key       Ljava/lang/Object;


public scala.collection.Map filterKeys(scala.Function1);
  Signature: (Lscala/Function1;)Lscala/collection/Map;
  Code:
   Stack=2, Locals=2, Args_size=2
	aload_0
	aload_1
	invokestatic	Method scala/collection/MapLike$class.filterKeys:(Lscala/collection/MapLike;Lscala/Function1;)Lscala/collection/Map;
	areturn
  Labels:
  LocalVariableTable: 
   Start  Length  Slot  Name   Signature
   0      6      0    this       Lscala/collection/JavaConversions$JConcurrentMapWrapper;
   0      6      1    p       Lscala/Function1;


public scala.collection.Map mapValues(scala.Function1);
  Signature: (Lscala/Function1;)Lscala/collection/Map;
  Code:
   Stack=2, Locals=2, Args_size=2
	aload_0
	aload_1
	invokestatic	Method scala/collection/MapLike$class.mapValues:(Lscala/collection/MapLike;Lscala/Function1;)Lscala/collection/Map;
	areturn
  Labels:
  LocalVariableTable: 
   Start  Length  Slot  Name   Signature
   0      6      0    this       Lscala/collection/JavaConversions$JConcurrentMapWrapper;
   0      6      1    f       Lscala/Function1;


public scala.collection.Map mapElements(scala.Function1);
  Signature: (Lscala/Function1;)Lscala/collection/Map;
  Code:
   Stack=2, Locals=2, Args_size=2
	aload_0
	aload_1
	invokestatic	Method scala/collection/MapLike$class.mapElements:(Lscala/collection/MapLike;Lscala/Function1;)Lscala/collection/Map;
	areturn
  Labels:
  LocalVariableTable: 
   Start  Length  Slot  Name   Signature
   0      6      0    this       Lscala/collection/JavaConversions$JConcurrentMapWrapper;
   0      6      1    f       Lscala/Function1;

  Deprecated: true

public scala.collection.Map filterNot(scala.Function1);
  Signature: (Lscala/Function1;)Lscala/collection/Map;
  Code:
   Stack=2, Locals=2, Args_size=2
	aload_0
	aload_1
	invokestatic	Method scala/collection/MapLike$class.filterNot:(Lscala/collection/MapLike;Lscala/Function1;)Lscala/collection/Map;
	areturn
  Labels:
  LocalVariableTable: 
   Start  Length  Slot  Name   Signature
   0      6      0    this       Lscala/collection/JavaConversions$JConcurrentMapWrapper;
   0      6      1    p       Lscala/Function1;


public scala.collection.mutable.StringBuilder addString(scala.collection.mutable.StringBuilder, java.lang.String, java.lang.String, java.lang.String);
  Signature: (Lscala/collection/mutable/StringBuilder;Ljava/lang/String;Ljava/lang/String;Ljava/lang/String;)Lscala/collection/mutable/StringBuilder;
  Code:
   Stack=5, Locals=5, Args_size=5
	aload_0
	aload_1
	aload_2
	aload_3
	aload	4
	invokestatic	Method scala/collection/MapLike$class.addString:(Lscala/collection/MapLike;Lscala/collection/mutable/StringBuilder;Ljava/lang/String;Ljava/lang/String;Ljava/lang/String;)Lscala/collection/mutable/StringBuilder;
	areturn
  Labels:
  LocalVariableTable: 
   Start  Length  Slot  Name   Signature
   0      10      0    this       Lscala/collection/JavaConversions$JConcurrentMapWrapper;
   0      10      1    b       Lscala/collection/mutable/StringBuilder;
   0      10      2    start       Ljava/lang/String;
   0      10      3    sep       Ljava/lang/String;
   0      10      4    end       Ljava/lang/String;


public java.lang.String stringPrefix();
  Signature: ()Ljava/lang/String;
  Code:
   Stack=1, Locals=1, Args_size=1
	aload_0
	invokestatic	Method scala/collection/MapLike$class.stringPrefix:(Lscala/collection/MapLike;)Ljava/lang/String;
	areturn
  Labels:

public java.lang.String toString();
  Signature: ()Ljava/lang/String;
  Code:
   Stack=1, Locals=1, Args_size=1
	aload_0
	invokestatic	Method scala/collection/MapLike$class.toString:(Lscala/collection/MapLike;)Ljava/lang/String;
	areturn
  Labels:

public int hashCode();
  Signature: ()I
  Code:
   Stack=1, Locals=1, Args_size=1
	aload_0
	invokestatic	Method scala/collection/MapLike$class.hashCode:(Lscala/collection/MapLike;)I
	ireturn
  Labels:

public boolean equals(java.lang.Object);
  Signature: (Ljava/lang/Object;)Z
  Code:
   Stack=2, Locals=2, Args_size=2
	aload_0
	aload_1
	invokestatic	Method scala/collection/MapLike$class.equals:(Lscala/collection/MapLike;Ljava/lang/Object;)Z
	ireturn
  Labels:
  LocalVariableTable: 
   Start  Length  Slot  Name   Signature
   0      6      0    this       Lscala/collection/JavaConversions$JConcurrentMapWrapper;
   0      6      1    that       Ljava/lang/Object;


public scala.PartialFunction orElse(scala.PartialFunction);
  Signature: (Lscala/PartialFunction;)Lscala/PartialFunction;
  Code:
   Stack=2, Locals=2, Args_size=2
	aload_0
	aload_1
	invokestatic	Method scala/PartialFunction$class.orElse:(Lscala/PartialFunction;Lscala/PartialFunction;)Lscala/PartialFunction;
	areturn
  Labels:
  LocalVariableTable: 
   Start  Length  Slot  Name   Signature
   0      6      0    this       Lscala/collection/JavaConversions$JConcurrentMapWrapper;
   0      6      1    that       Lscala/PartialFunction;


public scala.PartialFunction andThen(scala.Function1);
  Signature: (Lscala/Function1;)Lscala/PartialFunction;
  Code:
   Stack=2, Locals=2, Args_size=2
	aload_0
	aload_1
	invokestatic	Method scala/PartialFunction$class.andThen:(Lscala/PartialFunction;Lscala/Function1;)Lscala/PartialFunction;
	areturn
  Labels:
  LocalVariableTable: 
   Start  Length  Slot  Name   Signature
   0      6      0    this       Lscala/collection/JavaConversions$JConcurrentMapWrapper;
   0      6      1    k       Lscala/Function1;


public scala.Function1 lift();
  Signature: ()Lscala/Function1;
  Code:
   Stack=1, Locals=1, Args_size=1
	aload_0
	invokestatic	Method scala/PartialFunction$class.lift:(Lscala/PartialFunction;)Lscala/Function1;
	areturn
  Labels:

public scala.Function1 compose(scala.Function1);
  Signature: (Lscala/Function1;)Lscala/Function1;
  Code:
   Stack=2, Locals=2, Args_size=2
	aload_0
	aload_1
	invokestatic	Method scala/Function1$class.compose:(Lscala/Function1;Lscala/Function1;)Lscala/Function1;
	areturn
  Labels:
  LocalVariableTable: 
   Start  Length  Slot  Name   Signature
   0      6      0    this       Lscala/collection/JavaConversions$JConcurrentMapWrapper;
   0      6      1    g       Lscala/Function1;


public scala.collection.generic.GenericCompanion companion();
  Signature: ()Lscala/collection/generic/GenericCompanion;
  Code:
   Stack=1, Locals=1, Args_size=1
	aload_0
	invokestatic	Method scala/collection/mutable/Iterable$class.companion:(Lscala/collection/mutable/Iterable;)Lscala/collection/generic/GenericCompanion;
	areturn
  Labels:

public scala.collection.Iterable thisCollection();
  Signature: ()Lscala/collection/Iterable;
  Code:
   Stack=1, Locals=1, Args_size=1
	aload_0
	invokestatic	Method scala/collection/IterableLike$class.thisCollection:(Lscala/collection/IterableLike;)Lscala/collection/Iterable;
	areturn
  Labels:

public scala.collection.Iterable toCollection(java.lang.Object);
  Signature: (Ljava/lang/Object;)Lscala/collection/Iterable;
  Code:
   Stack=2, Locals=2, Args_size=2
	aload_0
	aload_1
	invokestatic	Method scala/collection/IterableLike$class.toCollection:(Lscala/collection/IterableLike;Ljava/lang/Object;)Lscala/collection/Iterable;
	areturn
  Labels:
  LocalVariableTable: 
   Start  Length  Slot  Name   Signature
   0      6      0    this       Lscala/collection/JavaConversions$JConcurrentMapWrapper;
   0      6      1    repr       Ljava/lang/Object;


public void foreach(scala.Function1);
  Signature: (Lscala/Function1;)V
  Code:
   Stack=2, Locals=2, Args_size=2
	aload_0
	aload_1
	invokestatic	Method scala/collection/IterableLike$class.foreach:(Lscala/collection/IterableLike;Lscala/Function1;)V
	return
  Labels:
  LocalVariableTable: 
   Start  Length  Slot  Name   Signature
   0      6      0    this       Lscala/collection/JavaConversions$JConcurrentMapWrapper;
   0      6      1    f       Lscala/Function1;


public boolean forall(scala.Function1);
  Signature: (Lscala/Function1;)Z
  Code:
   Stack=2, Locals=2, Args_size=2
	aload_0
	aload_1
	invokestatic	Method scala/collection/IterableLike$class.forall:(Lscala/collection/IterableLike;Lscala/Function1;)Z
	ireturn
  Labels:
  LocalVariableTable: 
   Start  Length  Slot  Name   Signature
   0      6      0    this       Lscala/collection/JavaConversions$JConcurrentMapWrapper;
   0      6      1    p       Lscala/Function1;


public boolean exists(scala.Function1);
  Signature: (Lscala/Function1;)Z
  Code:
   Stack=2, Locals=2, Args_size=2
	aload_0
	aload_1
	invokestatic	Method scala/collection/IterableLike$class.exists:(Lscala/collection/IterableLike;Lscala/Function1;)Z
	ireturn
  Labels:
  LocalVariableTable: 
   Start  Length  Slot  Name   Signature
   0      6      0    this       Lscala/collection/JavaConversions$JConcurrentMapWrapper;
   0      6      1    p       Lscala/Function1;


public scala.Option find(scala.Function1);
  Signature: (Lscala/Function1;)Lscala/Option;
  Code:
   Stack=2, Locals=2, Args_size=2
	aload_0
	aload_1
	invokestatic	Method scala/collection/IterableLike$class.find:(Lscala/collection/IterableLike;Lscala/Function1;)Lscala/Option;
	areturn
  Labels:
  LocalVariableTable: 
   Start  Length  Slot  Name   Signature
   0      6      0    this       Lscala/collection/JavaConversions$JConcurrentMapWrapper;
   0      6      1    p       Lscala/Function1;


public java.lang.Object foldRight(java.lang.Object, scala.Function2);
  Signature: (Ljava/lang/Object;Lscala/Function2;)Ljava/lang/Object;
  Code:
   Stack=3, Locals=3, Args_size=3
	aload_0
	aload_1
	aload_2
	invokestatic	Method scala/collection/IterableLike$class.foldRight:(Lscala/collection/IterableLike;Ljava/lang/Object;Lscala/Function2;)Ljava/lang/Object;
	areturn
  Labels:
  LocalVariableTable: 
   Start  Length  Slot  Name   Signature
   0      7      0    this       Lscala/collection/JavaConversions$JConcurrentMapWrapper;
   0      7      1    z       Ljava/lang/Object;
   0      7      2    op       Lscala/Function2;


public java.lang.Object reduceRight(scala.Function2);
  Signature: (Lscala/Function2;)Ljava/lang/Object;
  Code:
   Stack=2, Locals=2, Args_size=2
	aload_0
	aload_1
	invokestatic	Method scala/collection/IterableLike$class.reduceRight:(Lscala/collection/IterableLike;Lscala/Function2;)Ljava/lang/Object;
	areturn
  Labels:
  LocalVariableTable: 
   Start  Length  Slot  Name   Signature
   0      6      0    this       Lscala/collection/JavaConversions$JConcurrentMapWrapper;
   0      6      1    op       Lscala/Function2;


public scala.collection.Iterable toIterable();
  Signature: ()Lscala/collection/Iterable;
  Code:
   Stack=1, Locals=1, Args_size=1
	aload_0
	invokestatic	Method scala/collection/IterableLike$class.toIterable:(Lscala/collection/IterableLike;)Lscala/collection/Iterable;
	areturn
  Labels:

public java.lang.Object head();
  Signature: ()Ljava/lang/Object;
  Code:
   Stack=1, Locals=1, Args_size=1
	aload_0
	invokestatic	Method scala/collection/IterableLike$class.head:(Lscala/collection/IterableLike;)Ljava/lang/Object;
	areturn
  Labels:

public java.lang.Object take(int);
  Signature: (I)Ljava/lang/Object;
  Code:
   Stack=2, Locals=2, Args_size=2
	aload_0
	iload_1
	invokestatic	Method scala/collection/IterableLike$class.take:(Lscala/collection/IterableLike;I)Ljava/lang/Object;
	areturn
  Labels:
  LocalVariableTable: 
   Start  Length  Slot  Name   Signature
   0      6      0    this       Lscala/collection/JavaConversions$JConcurrentMapWrapper;
   0      6      1    n       I


public java.lang.Object slice(int, int);
  Signature: (II)Ljava/lang/Object;
  Code:
   Stack=3, Locals=3, Args_size=3
	aload_0
	iload_1
	iload_2
	invokestatic	Method scala/collection/IterableLike$class.slice:(Lscala/collection/IterableLike;II)Ljava/lang/Object;
	areturn
  Labels:
  LocalVariableTable: 
   Start  Length  Slot  Name   Signature
   0      7      0    this       Lscala/collection/JavaConversions$JConcurrentMapWrapper;
   0      7      1    from       I
   0      7      2    until       I


public java.lang.Object takeWhile(scala.Function1);
  Signature: (Lscala/Function1;)Ljava/lang/Object;
  Code:
   Stack=2, Locals=2, Args_size=2
	aload_0
	aload_1
	invokestatic	Method scala/collection/IterableLike$class.takeWhile:(Lscala/collection/IterableLike;Lscala/Function1;)Ljava/lang/Object;
	areturn
  Labels:
  LocalVariableTable: 
   Start  Length  Slot  Name   Signature
   0      6      0    this       Lscala/collection/JavaConversions$JConcurrentMapWrapper;
   0      6      1    p       Lscala/Function1;


public scala.collection.Iterator grouped(int);
  Signature: (I)Lscala/collection/Iterator;
  Code:
   Stack=2, Locals=2, Args_size=2
	aload_0
	iload_1
	invokestatic	Method scala/collection/IterableLike$class.grouped:(Lscala/collection/IterableLike;I)Lscala/collection/Iterator;
	areturn
  Labels:
  LocalVariableTable: 
   Start  Length  Slot  Name   Signature
   0      6      0    this       Lscala/collection/JavaConversions$JConcurrentMapWrapper;
   0      6      1    size       I


public scala.collection.Iterator sliding(int);
  Signature: (I)Lscala/collection/Iterator;
  Code:
   Stack=2, Locals=2, Args_size=2
	aload_0
	iload_1
	invokestatic	Method scala/collection/IterableLike$class.sliding:(Lscala/collection/IterableLike;I)Lscala/collection/Iterator;
	areturn
  Labels:
  LocalVariableTable: 
   Start  Length  Slot  Name   Signature
   0      6      0    this       Lscala/collection/JavaConversions$JConcurrentMapWrapper;
   0      6      1    size       I


public scala.collection.Iterator sliding(int, int);
  Signature: (II)Lscala/collection/Iterator;
  Code:
   Stack=3, Locals=3, Args_size=3
	aload_0
	iload_1
	iload_2
	invokestatic	Method scala/collection/IterableLike$class.sliding:(Lscala/collection/IterableLike;II)Lscala/collection/Iterator;
	areturn
  Labels:
  LocalVariableTable: 
   Start  Length  Slot  Name   Signature
   0      7      0    this       Lscala/collection/JavaConversions$JConcurrentMapWrapper;
   0      7      1    size       I
   0      7      2    step       I


public java.lang.Object takeRight(int);
  Signature: (I)Ljava/lang/Object;
  Code:
   Stack=2, Locals=2, Args_size=2
	aload_0
	iload_1
	invokestatic	Method scala/collection/IterableLike$class.takeRight:(Lscala/collection/IterableLike;I)Ljava/lang/Object;
	areturn
  Labels:
  LocalVariableTable: 
   Start  Length  Slot  Name   Signature
   0      6      0    this       Lscala/collection/JavaConversions$JConcurrentMapWrapper;
   0      6      1    n       I


public java.lang.Object dropRight(int);
  Signature: (I)Ljava/lang/Object;
  Code:
   Stack=2, Locals=2, Args_size=2
	aload_0
	iload_1
	invokestatic	Method scala/collection/IterableLike$class.dropRight:(Lscala/collection/IterableLike;I)Ljava/lang/Object;
	areturn
  Labels:
  LocalVariableTable: 
   Start  Length  Slot  Name   Signature
   0      6      0    this       Lscala/collection/JavaConversions$JConcurrentMapWrapper;
   0      6      1    n       I


public void copyToArray(java.lang.Object, int, int);
  Signature: (Ljava/lang/Object;II)V
  Code:
   Stack=4, Locals=4, Args_size=4
	aload_0
	aload_1
	iload_2
	iload_3
	invokestatic	Method scala/collection/IterableLike$class.copyToArray:(Lscala/collection/IterableLike;Ljava/lang/Object;II)V
	return
  Labels:
  LocalVariableTable: 
   Start  Length  Slot  Name   Signature
   0      8      0    this       Lscala/collection/JavaConversions$JConcurrentMapWrapper;
   0      8      1    xs       Ljava/lang/Object;
   0      8      2    start       I
   0      8      3    len       I


public java.lang.Object zip(scala.collection.Iterable, scala.collection.generic.CanBuildFrom);
  Signature: (Lscala/collection/Iterable;Lscala/collection/generic/CanBuildFrom;)Ljava/lang/Object;
  Code:
   Stack=3, Locals=3, Args_size=3
	aload_0
	aload_1
	aload_2
	invokestatic	Method scala/collection/IterableLike$class.zip:(Lscala/collection/IterableLike;Lscala/collection/Iterable;Lscala/collection/generic/CanBuildFrom;)Ljava/lang/Object;
	areturn
  Labels:
  LocalVariableTable: 
   Start  Length  Slot  Name   Signature
   0      7      0    this       Lscala/collection/JavaConversions$JConcurrentMapWrapper;
   0      7      1    that       Lscala/collection/Iterable;
   0      7      2    bf       Lscala/collection/generic/CanBuildFrom;


public java.lang.Object zipAll(scala.collection.Iterable, java.lang.Object, java.lang.Object, scala.collection.generic.CanBuildFrom);
  Signature: (Lscala/collection/Iterable;Ljava/lang/Object;Ljava/lang/Object;Lscala/collection/generic/CanBuildFrom;)Ljava/lang/Object;
  Code:
   Stack=5, Locals=5, Args_size=5
	aload_0
	aload_1
	aload_2
	aload_3
	aload	4
	invokestatic	Method scala/collection/IterableLike$class.zipAll:(Lscala/collection/IterableLike;Lscala/collection/Iterable;Ljava/lang/Object;Ljava/lang/Object;Lscala/collection/generic/CanBuildFrom;)Ljava/lang/Object;
	areturn
  Labels:
  LocalVariableTable: 
   Start  Length  Slot  Name   Signature
   0      10      0    this       Lscala/collection/JavaConversions$JConcurrentMapWrapper;
   0      10      1    that       Lscala/collection/Iterable;
   0      10      2    thisElem       Ljava/lang/Object;
   0      10      3    thatElem       Ljava/lang/Object;
   0      10      4    bf       Lscala/collection/generic/CanBuildFrom;


public java.lang.Object zipWithIndex(scala.collection.generic.CanBuildFrom);
  Signature: (Lscala/collection/generic/CanBuildFrom;)Ljava/lang/Object;
  Code:
   Stack=2, Locals=2, Args_size=2
	aload_0
	aload_1
	invokestatic	Method scala/collection/IterableLike$class.zipWithIndex:(Lscala/collection/IterableLike;Lscala/collection/generic/CanBuildFrom;)Ljava/lang/Object;
	areturn
  Labels:
  LocalVariableTable: 
   Start  Length  Slot  Name   Signature
   0      6      0    this       Lscala/collection/JavaConversions$JConcurrentMapWrapper;
   0      6      1    bf       Lscala/collection/generic/CanBuildFrom;


public boolean sameElements(scala.collection.Iterable);
  Signature: (Lscala/collection/Iterable;)Z
  Code:
   Stack=2, Locals=2, Args_size=2
	aload_0
	aload_1
	invokestatic	Method scala/collection/IterableLike$class.sameElements:(Lscala/collection/IterableLike;Lscala/collection/Iterable;)Z
	ireturn
  Labels:
  LocalVariableTable: 
   Start  Length  Slot  Name   Signature
   0      6      0    this       Lscala/collection/JavaConversions$JConcurrentMapWrapper;
   0      6      1    that       Lscala/collection/Iterable;


public scala.collection.immutable.Stream toStream();
  Signature: ()Lscala/collection/immutable/Stream;
  Code:
   Stack=1, Locals=1, Args_size=1
	aload_0
	invokestatic	Method scala/collection/IterableLike$class.toStream:(Lscala/collection/IterableLike;)Lscala/collection/immutable/Stream;
	areturn
  Labels:

public boolean canEqual(java.lang.Object);
  Signature: (Ljava/lang/Object;)Z
  Code:
   Stack=2, Locals=2, Args_size=2
	aload_0
	aload_1
	invokestatic	Method scala/collection/IterableLike$class.canEqual:(Lscala/collection/IterableLike;Ljava/lang/Object;)Z
	ireturn
  Labels:
  LocalVariableTable: 
   Start  Length  Slot  Name   Signature
   0      6      0    this       Lscala/collection/JavaConversions$JConcurrentMapWrapper;
   0      6      1    that       Ljava/lang/Object;


public scala.collection.IterableView view();
  Signature: ()Lscala/collection/IterableView;
  Code:
   Stack=1, Locals=1, Args_size=1
	aload_0
	invokestatic	Method scala/collection/IterableLike$class.view:(Lscala/collection/IterableLike;)Lscala/collection/IterableView;
	areturn
  Labels:

public scala.collection.IterableView view(int, int);
  Signature: (II)Lscala/collection/IterableView;
  Code:
   Stack=3, Locals=3, Args_size=3
	aload_0
	iload_1
	iload_2
	invokestatic	Method scala/collection/IterableLike$class.view:(Lscala/collection/IterableLike;II)Lscala/collection/IterableView;
	areturn
  Labels:
  LocalVariableTable: 
   Start  Length  Slot  Name   Signature
   0      7      0    this       Lscala/collection/JavaConversions$JConcurrentMapWrapper;
   0      7      1    from       I
   0      7      2    until       I


public scala.collection.Iterator elements();
  Signature: ()Lscala/collection/Iterator;
  Code:
   Stack=1, Locals=1, Args_size=1
	aload_0
	invokestatic	Method scala/collection/IterableLike$class.elements:(Lscala/collection/IterableLike;)Lscala/collection/Iterator;
	areturn
  Labels:
  Deprecated: true

public java.lang.Object first();
  Signature: ()Ljava/lang/Object;
  Code:
   Stack=1, Locals=1, Args_size=1
	aload_0
	invokestatic	Method scala/collection/IterableLike$class.first:(Lscala/collection/IterableLike;)Ljava/lang/Object;
	areturn
  Labels:
  Deprecated: true

public scala.Option firstOption();
  Signature: ()Lscala/Option;
  Code:
   Stack=1, Locals=1, Args_size=1
	aload_0
	invokestatic	Method scala/collection/IterableLike$class.firstOption:(Lscala/collection/IterableLike;)Lscala/Option;
	areturn
  Labels:
  Deprecated: true

public scala.collection.IterableView projection();
  Signature: ()Lscala/collection/IterableView;
  Code:
   Stack=1, Locals=1, Args_size=1
	aload_0
	invokestatic	Method scala/collection/IterableLike$class.projection:(Lscala/collection/IterableLike;)Lscala/collection/IterableView;
	areturn
  Labels:
  Deprecated: true

public scala.collection.mutable.Builder genericBuilder();
  Signature: ()Lscala/collection/mutable/Builder;
  Code:
   Stack=1, Locals=1, Args_size=1
	aload_0
	invokestatic	Method scala/collection/generic/GenericTraversableTemplate$class.genericBuilder:(Lscala/collection/generic/GenericTraversableTemplate;)Lscala/collection/mutable/Builder;
	areturn
  Labels:

public scala.Tuple2 unzip(scala.Function1);
  Signature: (Lscala/Function1;)Lscala/Tuple2;
  Code:
   Stack=2, Locals=2, Args_size=2
	aload_0
	aload_1
	invokestatic	Method scala/collection/generic/GenericTraversableTemplate$class.unzip:(Lscala/collection/generic/GenericTraversableTemplate;Lscala/Function1;)Lscala/Tuple2;
	areturn
  Labels:
  LocalVariableTable: 
   Start  Length  Slot  Name   Signature
   0      6      0    this       Lscala/collection/JavaConversions$JConcurrentMapWrapper;
   0      6      1    asPair       Lscala/Function1;


public scala.collection.Traversable flatten(scala.Function1);
  Signature: (Lscala/Function1;)Lscala/collection/Traversable;
  Code:
   Stack=2, Locals=2, Args_size=2
	aload_0
	aload_1
	invokestatic	Method scala/collection/generic/GenericTraversableTemplate$class.flatten:(Lscala/collection/generic/GenericTraversableTemplate;Lscala/Function1;)Lscala/collection/Traversable;
	areturn
  Labels:
  LocalVariableTable: 
   Start  Length  Slot  Name   Signature
   0      6      0    this       Lscala/collection/JavaConversions$JConcurrentMapWrapper;
   0      6      1    asTraversable       Lscala/Function1;


public scala.collection.Traversable transpose(scala.Function1);
  Signature: (Lscala/Function1;)Lscala/collection/Traversable;
  Code:
   Stack=2, Locals=2, Args_size=2
	aload_0
	aload_1
	invokestatic	Method scala/collection/generic/GenericTraversableTemplate$class.transpose:(Lscala/collection/generic/GenericTraversableTemplate;Lscala/Function1;)Lscala/collection/Traversable;
	areturn
  Labels:
  LocalVariableTable: 
   Start  Length  Slot  Name   Signature
   0      6      0    this       Lscala/collection/JavaConversions$JConcurrentMapWrapper;
   0      6      1    asTraversable       Lscala/Function1;


public java.lang.Object repr();
  Signature: ()Ljava/lang/Object;
  Code:
   Stack=1, Locals=1, Args_size=1
	aload_0
	invokestatic	Method scala/collection/TraversableLike$class.repr:(Lscala/collection/TraversableLike;)Ljava/lang/Object;
	areturn
  Labels:

public boolean nonEmpty();
  Signature: ()Z
  Code:
   Stack=1, Locals=1, Args_size=1
	aload_0
	invokestatic	Method scala/collection/TraversableLike$class.nonEmpty:(Lscala/collection/TraversableLike;)Z
	ireturn
  Labels:

public boolean hasDefiniteSize();
  Signature: ()Z
  Code:
   Stack=1, Locals=1, Args_size=1
	aload_0
	invokestatic	Method scala/collection/TraversableLike$class.hasDefiniteSize:(Lscala/collection/TraversableLike;)Z
	ireturn
  Labels:

public java.lang.Object $plus$plus(scala.collection.Traversable, scala.collection.generic.CanBuildFrom);
  Signature: (Lscala/collection/Traversable;Lscala/collection/generic/CanBuildFrom;)Ljava/lang/Object;
  Code:
   Stack=3, Locals=3, Args_size=3
	aload_0
	aload_1
	aload_2
	invokestatic	Method scala/collection/TraversableLike$class.$plus$plus:(Lscala/collection/TraversableLike;Lscala/collection/Traversable;Lscala/collection/generic/CanBuildFrom;)Ljava/lang/Object;
	areturn
  Labels:
  LocalVariableTable: 
   Start  Length  Slot  Name   Signature
   0      7      0    this       Lscala/collection/JavaConversions$JConcurrentMapWrapper;
   0      7      1    that       Lscala/collection/Traversable;
   0      7      2    bf       Lscala/collection/generic/CanBuildFrom;


public java.lang.Object $plus$plus(scala.collection.Iterator, scala.collection.generic.CanBuildFrom);
  Signature: (Lscala/collection/Iterator;Lscala/collection/generic/CanBuildFrom;)Ljava/lang/Object;
  Code:
   Stack=3, Locals=3, Args_size=3
	aload_0
	aload_1
	aload_2
	invokestatic	Method scala/collection/TraversableLike$class.$plus$plus:(Lscala/collection/TraversableLike;Lscala/collection/Iterator;Lscala/collection/generic/CanBuildFrom;)Ljava/lang/Object;
	areturn
  Labels:
  LocalVariableTable: 
   Start  Length  Slot  Name   Signature
   0      7      0    this       Lscala/collection/JavaConversions$JConcurrentMapWrapper;
   0      7      1    that       Lscala/collection/Iterator;
   0      7      2    bf       Lscala/collection/generic/CanBuildFrom;


public java.lang.Object map(scala.Function1, scala.collection.generic.CanBuildFrom);
  Signature: (Lscala/Function1;Lscala/collection/generic/CanBuildFrom;)Ljava/lang/Object;
  Code:
   Stack=3, Locals=3, Args_size=3
	aload_0
	aload_1
	aload_2
	invokestatic	Method scala/collection/TraversableLike$class.map:(Lscala/collection/TraversableLike;Lscala/Function1;Lscala/collection/generic/CanBuildFrom;)Ljava/lang/Object;
	areturn
  Labels:
  LocalVariableTable: 
   Start  Length  Slot  Name   Signature
   0      7      0    this       Lscala/collection/JavaConversions$JConcurrentMapWrapper;
   0      7      1    f       Lscala/Function1;
   0      7      2    bf       Lscala/collection/generic/CanBuildFrom;


public java.lang.Object flatMap(scala.Function1, scala.collection.generic.CanBuildFrom);
  Signature: (Lscala/Function1;Lscala/collection/generic/CanBuildFrom;)Ljava/lang/Object;
  Code:
   Stack=3, Locals=3, Args_size=3
	aload_0
	aload_1
	aload_2
	invokestatic	Method scala/collection/TraversableLike$class.flatMap:(Lscala/collection/TraversableLike;Lscala/Function1;Lscala/collection/generic/CanBuildFrom;)Ljava/lang/Object;
	areturn
  Labels:
  LocalVariableTable: 
   Start  Length  Slot  Name   Signature
   0      7      0    this       Lscala/collection/JavaConversions$JConcurrentMapWrapper;
   0      7      1    f       Lscala/Function1;
   0      7      2    bf       Lscala/collection/generic/CanBuildFrom;


public java.lang.Object filter(scala.Function1);
  Signature: (Lscala/Function1;)Ljava/lang/Object;
  Code:
   Stack=2, Locals=2, Args_size=2
	aload_0
	aload_1
	invokestatic	Method scala/collection/TraversableLike$class.filter:(Lscala/collection/TraversableLike;Lscala/Function1;)Ljava/lang/Object;
	areturn
  Labels:
  LocalVariableTable: 
   Start  Length  Slot  Name   Signature
   0      6      0    this       Lscala/collection/JavaConversions$JConcurrentMapWrapper;
   0      6      1    p       Lscala/Function1;


public java.lang.Object partialMap(scala.PartialFunction, scala.collection.generic.CanBuildFrom);
  Signature: (Lscala/PartialFunction;Lscala/collection/generic/CanBuildFrom;)Ljava/lang/Object;
  Code:
   Stack=3, Locals=3, Args_size=3
	aload_0
	aload_1
	aload_2
	invokestatic	Method scala/collection/TraversableLike$class.partialMap:(Lscala/collection/TraversableLike;Lscala/PartialFunction;Lscala/collection/generic/CanBuildFrom;)Ljava/lang/Object;
	areturn
  Labels:
  LocalVariableTable: 
   Start  Length  Slot  Name   Signature
   0      7      0    this       Lscala/collection/JavaConversions$JConcurrentMapWrapper;
   0      7      1    pf       Lscala/PartialFunction;
   0      7      2    bf       Lscala/collection/generic/CanBuildFrom;


public scala.Tuple2 partition(scala.Function1);
  Signature: (Lscala/Function1;)Lscala/Tuple2;
  Code:
   Stack=2, Locals=2, Args_size=2
	aload_0
	aload_1
	invokestatic	Method scala/collection/TraversableLike$class.partition:(Lscala/collection/TraversableLike;Lscala/Function1;)Lscala/Tuple2;
	areturn
  Labels:
  LocalVariableTable: 
   Start  Length  Slot  Name   Signature
   0      6      0    this       Lscala/collection/JavaConversions$JConcurrentMapWrapper;
   0      6      1    p       Lscala/Function1;


public scala.collection.Map groupBy(scala.Function1);
  Signature: (Lscala/Function1;)Lscala/collection/Map;
  Code:
   Stack=2, Locals=2, Args_size=2
	aload_0
	aload_1
	invokestatic	Method scala/collection/TraversableLike$class.groupBy:(Lscala/collection/TraversableLike;Lscala/Function1;)Lscala/collection/Map;
	areturn
  Labels:
  LocalVariableTable: 
   Start  Length  Slot  Name   Signature
   0      6      0    this       Lscala/collection/JavaConversions$JConcurrentMapWrapper;
   0      6      1    f       Lscala/Function1;


public int count(scala.Function1);
  Signature: (Lscala/Function1;)I
  Code:
   Stack=2, Locals=2, Args_size=2
	aload_0
	aload_1
	invokestatic	Method scala/collection/TraversableLike$class.count:(Lscala/collection/TraversableLike;Lscala/Function1;)I
	ireturn
  Labels:
  LocalVariableTable: 
   Start  Length  Slot  Name   Signature
   0      6      0    this       Lscala/collection/JavaConversions$JConcurrentMapWrapper;
   0      6      1    p       Lscala/Function1;


public java.lang.Object foldLeft(java.lang.Object, scala.Function2);
  Signature: (Ljava/lang/Object;Lscala/Function2;)Ljava/lang/Object;
  Code:
   Stack=3, Locals=3, Args_size=3
	aload_0
	aload_1
	aload_2
	invokestatic	Method scala/collection/TraversableLike$class.foldLeft:(Lscala/collection/TraversableLike;Ljava/lang/Object;Lscala/Function2;)Ljava/lang/Object;
	areturn
  Labels:
  LocalVariableTable: 
   Start  Length  Slot  Name   Signature
   0      7      0    this       Lscala/collection/JavaConversions$JConcurrentMapWrapper;
   0      7      1    z       Ljava/lang/Object;
   0      7      2    op       Lscala/Function2;


public java.lang.Object $div$colon(java.lang.Object, scala.Function2);
  Signature: (Ljava/lang/Object;Lscala/Function2;)Ljava/lang/Object;
  Code:
   Stack=3, Locals=3, Args_size=3
	aload_0
	aload_1
	aload_2
	invokestatic	Method scala/collection/TraversableLike$class.$div$colon:(Lscala/collection/TraversableLike;Ljava/lang/Object;Lscala/Function2;)Ljava/lang/Object;
	areturn
  Labels:
  LocalVariableTable: 
   Start  Length  Slot  Name   Signature
   0      7      0    this       Lscala/collection/JavaConversions$JConcurrentMapWrapper;
   0      7      1    z       Ljava/lang/Object;
   0      7      2    op       Lscala/Function2;


public java.lang.Object $colon$bslash(java.lang.Object, scala.Function2);
  Signature: (Ljava/lang/Object;Lscala/Function2;)Ljava/lang/Object;
  Code:
   Stack=3, Locals=3, Args_size=3
	aload_0
	aload_1
	aload_2
	invokestatic	Method scala/collection/TraversableLike$class.$colon$bslash:(Lscala/collection/TraversableLike;Ljava/lang/Object;Lscala/Function2;)Ljava/lang/Object;
	areturn
  Labels:
  LocalVariableTable: 
   Start  Length  Slot  Name   Signature
   0      7      0    this       Lscala/collection/JavaConversions$JConcurrentMapWrapper;
   0      7      1    z       Ljava/lang/Object;
   0      7      2    op       Lscala/Function2;


public java.lang.Object reduceLeft(scala.Function2);
  Signature: (Lscala/Function2;)Ljava/lang/Object;
  Code:
   Stack=2, Locals=2, Args_size=2
	aload_0
	aload_1
	invokestatic	Method scala/collection/TraversableLike$class.reduceLeft:(Lscala/collection/TraversableLike;Lscala/Function2;)Ljava/lang/Object;
	areturn
  Labels:
  LocalVariableTable: 
   Start  Length  Slot  Name   Signature
   0      6      0    this       Lscala/collection/JavaConversions$JConcurrentMapWrapper;
   0      6      1    op       Lscala/Function2;


public scala.Option reduceLeftOption(scala.Function2);
  Signature: (Lscala/Function2;)Lscala/Option;
  Code:
   Stack=2, Locals=2, Args_size=2
	aload_0
	aload_1
	invokestatic	Method scala/collection/TraversableLike$class.reduceLeftOption:(Lscala/collection/TraversableLike;Lscala/Function2;)Lscala/Option;
	areturn
  Labels:
  LocalVariableTable: 
   Start  Length  Slot  Name   Signature
   0      6      0    this       Lscala/collection/JavaConversions$JConcurrentMapWrapper;
   0      6      1    op       Lscala/Function2;


public scala.Option reduceRightOption(scala.Function2);
  Signature: (Lscala/Function2;)Lscala/Option;
  Code:
   Stack=2, Locals=2, Args_size=2
	aload_0
	aload_1
	invokestatic	Method scala/collection/TraversableLike$class.reduceRightOption:(Lscala/collection/TraversableLike;Lscala/Function2;)Lscala/Option;
	areturn
  Labels:
  LocalVariableTable: 
   Start  Length  Slot  Name   Signature
   0      6      0    this       Lscala/collection/JavaConversions$JConcurrentMapWrapper;
   0      6      1    op       Lscala/Function2;


public java.lang.Object scanLeft(java.lang.Object, scala.Function2, scala.collection.generic.CanBuildFrom);
  Signature: (Ljava/lang/Object;Lscala/Function2;Lscala/collection/generic/CanBuildFrom;)Ljava/lang/Object;
  Code:
   Stack=4, Locals=4, Args_size=4
	aload_0
	aload_1
	aload_2
	aload_3
	invokestatic	Method scala/collection/TraversableLike$class.scanLeft:(Lscala/collection/TraversableLike;Ljava/lang/Object;Lscala/Function2;Lscala/collection/generic/CanBuildFrom;)Ljava/lang/Object;
	areturn
  Labels:
  LocalVariableTable: 
   Start  Length  Slot  Name   Signature
   0      8      0    this       Lscala/collection/JavaConversions$JConcurrentMapWrapper;
   0      8      1    z       Ljava/lang/Object;
   0      8      2    op       Lscala/Function2;
   0      8      3    bf       Lscala/collection/generic/CanBuildFrom;


public java.lang.Object scanRight(java.lang.Object, scala.Function2, scala.collection.generic.CanBuildFrom);
  Signature: (Ljava/lang/Object;Lscala/Function2;Lscala/collection/generic/CanBuildFrom;)Ljava/lang/Object;
  Code:
   Stack=4, Locals=4, Args_size=4
	aload_0
	aload_1
	aload_2
	aload_3
	invokestatic	Method scala/collection/TraversableLike$class.scanRight:(Lscala/collection/TraversableLike;Ljava/lang/Object;Lscala/Function2;Lscala/collection/generic/CanBuildFrom;)Ljava/lang/Object;
	areturn
  Labels:
  LocalVariableTable: 
   Start  Length  Slot  Name   Signature
   0      8      0    this       Lscala/collection/JavaConversions$JConcurrentMapWrapper;
   0      8      1    z       Ljava/lang/Object;
   0      8      2    op       Lscala/Function2;
   0      8      3    bf       Lscala/collection/generic/CanBuildFrom;


public java.lang.Object sum(scala.math.Numeric);
  Signature: (Lscala/math/Numeric;)Ljava/lang/Object;
  Code:
   Stack=2, Locals=2, Args_size=2
	aload_0
	aload_1
	invokestatic	Method scala/collection/TraversableLike$class.sum:(Lscala/collection/TraversableLike;Lscala/math/Numeric;)Ljava/lang/Object;
	areturn
  Labels:
  LocalVariableTable: 
   Start  Length  Slot  Name   Signature
   0      6      0    this       Lscala/collection/JavaConversions$JConcurrentMapWrapper;
   0      6      1    num       Lscala/math/Numeric;


public java.lang.Object product(scala.math.Numeric);
  Signature: (Lscala/math/Numeric;)Ljava/lang/Object;
  Code:
   Stack=2, Locals=2, Args_size=2
	aload_0
	aload_1
	invokestatic	Method scala/collection/TraversableLike$class.product:(Lscala/collection/TraversableLike;Lscala/math/Numeric;)Ljava/lang/Object;
	areturn
  Labels:
  LocalVariableTable: 
   Start  Length  Slot  Name   Signature
   0      6      0    this       Lscala/collection/JavaConversions$JConcurrentMapWrapper;
   0      6      1    num       Lscala/math/Numeric;


public java.lang.Object min(scala.math.Ordering);
  Signature: (Lscala/math/Ordering;)Ljava/lang/Object;
  Code:
   Stack=2, Locals=2, Args_size=2
	aload_0
	aload_1
	invokestatic	Method scala/collection/TraversableLike$class.min:(Lscala/collection/TraversableLike;Lscala/math/Ordering;)Ljava/lang/Object;
	areturn
  Labels:
  LocalVariableTable: 
   Start  Length  Slot  Name   Signature
   0      6      0    this       Lscala/collection/JavaConversions$JConcurrentMapWrapper;
   0      6      1    cmp       Lscala/math/Ordering;


public java.lang.Object max(scala.math.Ordering);
  Signature: (Lscala/math/Ordering;)Ljava/lang/Object;
  Code:
   Stack=2, Locals=2, Args_size=2
	aload_0
	aload_1
	invokestatic	Method scala/collection/TraversableLike$class.max:(Lscala/collection/TraversableLike;Lscala/math/Ordering;)Ljava/lang/Object;
	areturn
  Labels:
  LocalVariableTable: 
   Start  Length  Slot  Name   Signature
   0      6      0    this       Lscala/collection/JavaConversions$JConcurrentMapWrapper;
   0      6      1    cmp       Lscala/math/Ordering;


public scala.Option headOption();
  Signature: ()Lscala/Option;
  Code:
   Stack=1, Locals=1, Args_size=1
	aload_0
	invokestatic	Method scala/collection/TraversableLike$class.headOption:(Lscala/collection/TraversableLike;)Lscala/Option;
	areturn
  Labels:

public java.lang.Object tail();
  Signature: ()Ljava/lang/Object;
  Code:
   Stack=1, Locals=1, Args_size=1
	aload_0
	invokestatic	Method scala/collection/TraversableLike$class.tail:(Lscala/collection/TraversableLike;)Ljava/lang/Object;
	areturn
  Labels:

public java.lang.Object last();
  Signature: ()Ljava/lang/Object;
  Code:
   Stack=1, Locals=1, Args_size=1
	aload_0
	invokestatic	Method scala/collection/TraversableLike$class.last:(Lscala/collection/TraversableLike;)Ljava/lang/Object;
	areturn
  Labels:

public scala.Option lastOption();
  Signature: ()Lscala/Option;
  Code:
   Stack=1, Locals=1, Args_size=1
	aload_0
	invokestatic	Method scala/collection/TraversableLike$class.lastOption:(Lscala/collection/TraversableLike;)Lscala/Option;
	areturn
  Labels:

public java.lang.Object init();
  Signature: ()Ljava/lang/Object;
  Code:
   Stack=1, Locals=1, Args_size=1
	aload_0
	invokestatic	Method scala/collection/TraversableLike$class.init:(Lscala/collection/TraversableLike;)Ljava/lang/Object;
	areturn
  Labels:

public java.lang.Object drop(int);
  Signature: (I)Ljava/lang/Object;
  Code:
   Stack=2, Locals=2, Args_size=2
	aload_0
	iload_1
	invokestatic	Method scala/collection/TraversableLike$class.drop:(Lscala/collection/TraversableLike;I)Ljava/lang/Object;
	areturn
  Labels:
  LocalVariableTable: 
   Start  Length  Slot  Name   Signature
   0      6      0    this       Lscala/collection/JavaConversions$JConcurrentMapWrapper;
   0      6      1    n       I


public java.lang.Object dropWhile(scala.Function1);
  Signature: (Lscala/Function1;)Ljava/lang/Object;
  Code:
   Stack=2, Locals=2, Args_size=2
	aload_0
	aload_1
	invokestatic	Method scala/collection/TraversableLike$class.dropWhile:(Lscala/collection/TraversableLike;Lscala/Function1;)Ljava/lang/Object;
	areturn
  Labels:
  LocalVariableTable: 
   Start  Length  Slot  Name   Signature
   0      6      0    this       Lscala/collection/JavaConversions$JConcurrentMapWrapper;
   0      6      1    p       Lscala/Function1;


public scala.Tuple2 span(scala.Function1);
  Signature: (Lscala/Function1;)Lscala/Tuple2;
  Code:
   Stack=2, Locals=2, Args_size=2
	aload_0
	aload_1
	invokestatic	Method scala/collection/TraversableLike$class.span:(Lscala/collection/TraversableLike;Lscala/Function1;)Lscala/Tuple2;
	areturn
  Labels:
  LocalVariableTable: 
   Start  Length  Slot  Name   Signature
   0      6      0    this       Lscala/collection/JavaConversions$JConcurrentMapWrapper;
   0      6      1    p       Lscala/Function1;


public scala.Tuple2 splitAt(int);
  Signature: (I)Lscala/Tuple2;
  Code:
   Stack=2, Locals=2, Args_size=2
	aload_0
	iload_1
	invokestatic	Method scala/collection/TraversableLike$class.splitAt:(Lscala/collection/TraversableLike;I)Lscala/Tuple2;
	areturn
  Labels:
  LocalVariableTable: 
   Start  Length  Slot  Name   Signature
   0      6      0    this       Lscala/collection/JavaConversions$JConcurrentMapWrapper;
   0      6      1    n       I


public void copyToBuffer(scala.collection.mutable.Buffer);
  Signature: (Lscala/collection/mutable/Buffer;)V
  Code:
   Stack=2, Locals=2, Args_size=2
	aload_0
	aload_1
	invokestatic	Method scala/collection/TraversableLike$class.copyToBuffer:(Lscala/collection/TraversableLike;Lscala/collection/mutable/Buffer;)V
	return
  Labels:
  LocalVariableTable: 
   Start  Length  Slot  Name   Signature
   0      6      0    this       Lscala/collection/JavaConversions$JConcurrentMapWrapper;
   0      6      1    dest       Lscala/collection/mutable/Buffer;


public void copyToArray(java.lang.Object, int);
  Signature: (Ljava/lang/Object;I)V
  Code:
   Stack=3, Locals=3, Args_size=3
	aload_0
	aload_1
	iload_2
	invokestatic	Method scala/collection/TraversableLike$class.copyToArray:(Lscala/collection/TraversableLike;Ljava/lang/Object;I)V
	return
  Labels:
  LocalVariableTable: 
   Start  Length  Slot  Name   Signature
   0      7      0    this       Lscala/collection/JavaConversions$JConcurrentMapWrapper;
   0      7      1    xs       Ljava/lang/Object;
   0      7      2    start       I


public void copyToArray(java.lang.Object);
  Signature: (Ljava/lang/Object;)V
  Code:
   Stack=2, Locals=2, Args_size=2
	aload_0
	aload_1
	invokestatic	Method scala/collection/TraversableLike$class.copyToArray:(Lscala/collection/TraversableLike;Ljava/lang/Object;)V
	return
  Labels:
  LocalVariableTable: 
   Start  Length  Slot  Name   Signature
   0      6      0    this       Lscala/collection/JavaConversions$JConcurrentMapWrapper;
   0      6      1    xs       Ljava/lang/Object;


public java.lang.Object toArray(scala.reflect.ClassManifest);
  Signature: (Lscala/reflect/ClassManifest;)Ljava/lang/Object;
  Code:
   Stack=2, Locals=2, Args_size=2
	aload_0
	aload_1
	invokestatic	Method scala/collection/TraversableLike$class.toArray:(Lscala/collection/TraversableLike;Lscala/reflect/ClassManifest;)Ljava/lang/Object;
	areturn
  Labels:
  LocalVariableTable: 
   Start  Length  Slot  Name   Signature
   0      6      0    this       Lscala/collection/JavaConversions$JConcurrentMapWrapper;
   0      6      1    evidence$1       Lscala/reflect/ClassManifest;


public scala.collection.immutable.List toList();
  Signature: ()Lscala/collection/immutable/List;
  Code:
   Stack=1, Locals=1, Args_size=1
	aload_0
	invokestatic	Method scala/collection/TraversableLike$class.toList:(Lscala/collection/TraversableLike;)Lscala/collection/immutable/List;
	areturn
  Labels:

public scala.collection.Seq toSeq();
  Signature: ()Lscala/collection/Seq;
  Code:
   Stack=1, Locals=1, Args_size=1
	aload_0
	invokestatic	Method scala/collection/TraversableLike$class.toSeq:(Lscala/collection/TraversableLike;)Lscala/collection/Seq;
	areturn
  Labels:

public scala.collection.mutable.IndexedSeq toIndexedSeq();
  Signature: ()Lscala/collection/mutable/IndexedSeq;
  Code:
   Stack=1, Locals=1, Args_size=1
	aload_0
	invokestatic	Method scala/collection/TraversableLike$class.toIndexedSeq:(Lscala/collection/TraversableLike;)Lscala/collection/mutable/IndexedSeq;
	areturn
  Labels:

public scala.collection.immutable.Set toSet();
  Signature: ()Lscala/collection/immutable/Set;
  Code:
   Stack=1, Locals=1, Args_size=1
	aload_0
	invokestatic	Method scala/collection/TraversableLike$class.toSet:(Lscala/collection/TraversableLike;)Lscala/collection/immutable/Set;
	areturn
  Labels:

public scala.collection.immutable.Map toMap(scala.Predef$$less$colon$less);
  Signature: (Lscala/Predef$$less$colon$less;)Lscala/collection/immutable/Map;
  Code:
   Stack=2, Locals=2, Args_size=2
	aload_0
	aload_1
	invokestatic	Method scala/collection/TraversableLike$class.toMap:(Lscala/collection/TraversableLike;Lscala/Predef$$less$colon$less;)Lscala/collection/immutable/Map;
	areturn
  Labels:
  LocalVariableTable: 
   Start  Length  Slot  Name   Signature
   0      6      0    this       Lscala/collection/JavaConversions$JConcurrentMapWrapper;
   0      6      1    ev       Lscala/Predef$$less$colon$less;


public java.lang.String mkString(java.lang.String, java.lang.String, java.lang.String);
  Signature: (Ljava/lang/String;Ljava/lang/String;Ljava/lang/String;)Ljava/lang/String;
  Code:
   Stack=4, Locals=4, Args_size=4
	aload_0
	aload_1
	aload_2
	aload_3
	invokestatic	Method scala/collection/TraversableLike$class.mkString:(Lscala/collection/TraversableLike;Ljava/lang/String;Ljava/lang/String;Ljava/lang/String;)Ljava/lang/String;
	areturn
  Labels:
  LocalVariableTable: 
   Start  Length  Slot  Name   Signature
   0      8      0    this       Lscala/collection/JavaConversions$JConcurrentMapWrapper;
   0      8      1    start       Ljava/lang/String;
   0      8      2    sep       Ljava/lang/String;
   0      8      3    end       Ljava/lang/String;


public java.lang.String mkString(java.lang.String);
  Signature: (Ljava/lang/String;)Ljava/lang/String;
  Code:
   Stack=2, Locals=2, Args_size=2
	aload_0
	aload_1
	invokestatic	Method scala/collection/TraversableLike$class.mkString:(Lscala/collection/TraversableLike;Ljava/lang/String;)Ljava/lang/String;
	areturn
  Labels:
  LocalVariableTable: 
   Start  Length  Slot  Name   Signature
   0      6      0    this       Lscala/collection/JavaConversions$JConcurrentMapWrapper;
   0      6      1    sep       Ljava/lang/String;


public java.lang.String mkString();
  Signature: ()Ljava/lang/String;
  Code:
   Stack=1, Locals=1, Args_size=1
	aload_0
	invokestatic	Method scala/collection/TraversableLike$class.mkString:(Lscala/collection/TraversableLike;)Ljava/lang/String;
	areturn
  Labels:

public scala.collection.mutable.StringBuilder addString(scala.collection.mutable.StringBuilder, java.lang.String);
  Signature: (Lscala/collection/mutable/StringBuilder;Ljava/lang/String;)Lscala/collection/mutable/StringBuilder;
  Code:
   Stack=3, Locals=3, Args_size=3
	aload_0
	aload_1
	aload_2
	invokestatic	Method scala/collection/TraversableLike$class.addString:(Lscala/collection/TraversableLike;Lscala/collection/mutable/StringBuilder;Ljava/lang/String;)Lscala/collection/mutable/StringBuilder;
	areturn
  Labels:
  LocalVariableTable: 
   Start  Length  Slot  Name   Signature
   0      7      0    this       Lscala/collection/JavaConversions$JConcurrentMapWrapper;
   0      7      1    b       Lscala/collection/mutable/StringBuilder;
   0      7      2    sep       Ljava/lang/String;


public scala.collection.mutable.StringBuilder addString(scala.collection.mutable.StringBuilder);
  Signature: (Lscala/collection/mutable/StringBuilder;)Lscala/collection/mutable/StringBuilder;
  Code:
   Stack=2, Locals=2, Args_size=2
	aload_0
	aload_1
	invokestatic	Method scala/collection/TraversableLike$class.addString:(Lscala/collection/TraversableLike;Lscala/collection/mutable/StringBuilder;)Lscala/collection/mutable/StringBuilder;
	areturn
  Labels:
  LocalVariableTable: 
   Start  Length  Slot  Name   Signature
   0      6      0    this       Lscala/collection/JavaConversions$JConcurrentMapWrapper;
   0      6      1    b       Lscala/collection/mutable/StringBuilder;


public scala.collection.TraversableLike$WithFilter withFilter(scala.Function1);
  Signature: (Lscala/Function1;)Lscala/collection/TraversableLike$WithFilter;
  Code:
   Stack=2, Locals=2, Args_size=2
	aload_0
	aload_1
	invokestatic	Method scala/collection/TraversableLike$class.withFilter:(Lscala/collection/TraversableLike;Lscala/Function1;)Lscala/collection/TraversableLike$WithFilter;
	areturn
  Labels:
  LocalVariableTable: 
   Start  Length  Slot  Name   Signature
   0      6      0    this       Lscala/collection/JavaConversions$JConcurrentMapWrapper;
   0      6      1    p       Lscala/Function1;

  Signature: length = 0x2
   02 FFFFFFBE 

public java.util.concurrent.ConcurrentMap copy$default$1();
  Signature: ()Ljava/util/concurrent/ConcurrentMap;
  Code:
   Stack=1, Locals=1, Args_size=1
	aload_0
	invokevirtual	Method underlying:()Ljava/util/concurrent/ConcurrentMap;
	areturn
  Labels:

public java.util.concurrent.ConcurrentMap underlying();
  Signature: ()Ljava/util/concurrent/ConcurrentMap;
  Code:
   Stack=1, Locals=1, Args_size=1
	aload_0
	getfield	Field underlying:Ljava/util/concurrent/ConcurrentMap;
	areturn
  Labels:
  Signature: length = 0x2
   02 FFFFFFCA 

public scala.Option get(java.lang.Object);
  Signature: (Ljava/lang/Object;)Lscala/Option;
  Code:
   Stack=3, Locals=3, Args_size=2
	aload_0
	invokevirtual	Method underlying:()Ljava/util/concurrent/ConcurrentMap;
	aload_1
	invokeinterface	InterfaceMethod java/util/Map.get:(Ljava/lang/Object;)Ljava/lang/Object;
	astore_2
	aload_2
	dup
	pop
	ifnull	l1 // getstatic
	aload_2
	aconst_null
	invokevirtual	Method java/lang/Object.equals:(Ljava/lang/Object;)Z
	ifeq	l2 // new
l1	getstatic	Field scala/None$.MODULE$:Lscala/None$;
	goto	l3 // areturn
l2	new	class scala/Some
	dup
	aload_2
	invokespecial	Method scala/Some."<init>":(Ljava/lang/Object;)V
l3	areturn
  Labels:
   	l1 = 25 // getstatic
   	l2 = 31 // new
   	l3 = 39 // areturn
  LocalVariableTable: 
   Start  Length  Slot  Name   Signature
   0      40      0    this       Lscala/collection/JavaConversions$JConcurrentMapWrapper;
   0      40      1    k       Ljava/lang/Object;
   11      29      2    v       Ljava/lang/Object;

  Signature: length = 0x2
   02 FFFFFFDD 

public scala.collection.JavaConversions$JConcurrentMapWrapper empty();
  Signature: ()Lscala/collection/JavaConversions$JConcurrentMapWrapper;
  Code:
   Stack=4, Locals=1, Args_size=1
	new	class scala/collection/JavaConversions$JConcurrentMapWrapper
	dup
	new	class java/util/concurrent/ConcurrentHashMap
	dup
	invokespecial	Method java/util/concurrent/ConcurrentHashMap."<init>":()V
	invokespecial	Method "<init>":(Ljava/util/concurrent/ConcurrentMap;)V
	areturn
  Labels:
  Signature: length = 0x2
   02 FFFFFFE7 

public scala.Option putIfAbsent(java.lang.Object, java.lang.Object);
  Signature: (Ljava/lang/Object;Ljava/lang/Object;)Lscala/Option;
  Code:
   Stack=3, Locals=4, Args_size=3
	aload_0
	invokevirtual	Method underlying:()Ljava/util/concurrent/ConcurrentMap;
	aload_1
	aload_2
	invokeinterface	InterfaceMethod java/util/concurrent/ConcurrentMap.putIfAbsent:(Ljava/lang/Object;Ljava/lang/Object;)Ljava/lang/Object;
	astore_3
	aload_3
	dup
	pop
	ifnull	l1 // getstatic
	aload_3
	aconst_null
	invokevirtual	Method java/lang/Object.equals:(Ljava/lang/Object;)Z
	ifeq	l2 // new
l1	getstatic	Field scala/None$.MODULE$:Lscala/None$;
	goto	l3 // areturn
l2	new	class scala/Some
	dup
	aload_3
	invokespecial	Method scala/Some."<init>":(Ljava/lang/Object;)V
l3	areturn
  Labels:
   	l1 = 26 // getstatic
   	l2 = 32 // new
   	l3 = 40 // areturn
  LocalVariableTable: 
   Start  Length  Slot  Name   Signature
   0      41      0    this       Lscala/collection/JavaConversions$JConcurrentMapWrapper;
   0      41      1    k       Ljava/lang/Object;
   0      41      2    v       Ljava/lang/Object;
   12      29      3    r       Ljava/lang/Object;

  Signature: length = 0x2
   02 FFFFFFEF 

public boolean remove(java.lang.Object, java.lang.Object);
  Signature: (Ljava/lang/Object;Ljava/lang/Object;)Z
  Code:
   Stack=3, Locals=3, Args_size=3
	aload_0
	invokevirtual	Method underlying:()Ljava/util/concurrent/ConcurrentMap;
	aload_1
	aload_2
	invokeinterface	InterfaceMethod java/util/concurrent/ConcurrentMap.remove:(Ljava/lang/Object;Ljava/lang/Object;)Z
	ireturn
  Labels:
  LocalVariableTable: 
   Start  Length  Slot  Name   Signature
   0      12      0    this       Lscala/collection/JavaConversions$JConcurrentMapWrapper;
   0      12      1    k       Ljava/lang/Object;
   0      12      2    v       Ljava/lang/Object;

  Signature: length = 0x2
   02 FFFFFFF3 

public scala.Option replace(java.lang.Object, java.lang.Object);
  Signature: (Ljava/lang/Object;Ljava/lang/Object;)Lscala/Option;
  Code:
   Stack=3, Locals=4, Args_size=3
	aload_0
	invokevirtual	Method underlying:()Ljava/util/concurrent/ConcurrentMap;
	aload_1
	aload_2
	invokeinterface	InterfaceMethod java/util/concurrent/ConcurrentMap.replace:(Ljava/lang/Object;Ljava/lang/Object;)Ljava/lang/Object;
	astore_3
	aload_3
	dup
	pop
	ifnull	l1 // getstatic
	aload_3
	aconst_null
	invokevirtual	Method java/lang/Object.equals:(Ljava/lang/Object;)Z
	ifeq	l2 // new
l1	getstatic	Field scala/None$.MODULE$:Lscala/None$;
	goto	l3 // areturn
l2	new	class scala/Some
	dup
	aload_3
	invokespecial	Method scala/Some."<init>":(Ljava/lang/Object;)V
l3	areturn
  Labels:
   	l1 = 26 // getstatic
   	l2 = 32 // new
   	l3 = 40 // areturn
  LocalVariableTable: 
   Start  Length  Slot  Name   Signature
   0      41      0    this       Lscala/collection/JavaConversions$JConcurrentMapWrapper;
   0      41      1    k       Ljava/lang/Object;
   0      41      2    v       Ljava/lang/Object;
   12      29      3    prev       Ljava/lang/Object;

  Signature: length = 0x2
   02 FFFFFFEF 

public boolean replace(java.lang.Object, java.lang.Object, java.lang.Object);
  Signature: (Ljava/lang/Object;Ljava/lang/Object;Ljava/lang/Object;)Z
  Code:
   Stack=4, Locals=4, Args_size=4
	aload_0
	invokevirtual	Method underlying:()Ljava/util/concurrent/ConcurrentMap;
	aload_1
	aload_2
	aload_3
	invokeinterface	InterfaceMethod java/util/concurrent/ConcurrentMap.replace:(Ljava/lang/Object;Ljava/lang/Object;Ljava/lang/Object;)Z
	ireturn
  Labels:
  LocalVariableTable: 
   Start  Length  Slot  Name   Signature
   0      13      0    this       Lscala/collection/JavaConversions$JConcurrentMapWrapper;
   0      13      1    k       Ljava/lang/Object;
   0      13      2    oldvalue       Ljava/lang/Object;
   0      13      3    newvalue       Ljava/lang/Object;

  Signature: length = 0x2
   02 FFFFFFFD 

public scala.collection.JavaConversions$JConcurrentMapWrapper copy(java.util.concurrent.ConcurrentMap);
  Signature: (Ljava/util/concurrent/ConcurrentMap;)Lscala/collection/JavaConversions$JConcurrentMapWrapper;
  Code:
   Stack=3, Locals=2, Args_size=2
	new	class scala/collection/JavaConversions$JConcurrentMapWrapper
	dup
	aload_1
	invokespecial	Method "<init>":(Ljava/util/concurrent/ConcurrentMap;)V
	areturn
  Labels:
  LocalVariableTable: 
   Start  Length  Slot  Name   Signature
   0      9      0    this       Lscala/collection/JavaConversions$JConcurrentMapWrapper;
   0      9      1    underlying       Ljava/util/concurrent/ConcurrentMap;


public java.lang.String productPrefix();
  Signature: ()Ljava/lang/String;
  Code:
   Stack=1, Locals=1, Args_size=1
	ldc_w	String JConcurrentMapWrapper
	areturn
  Labels:

public int productArity();
  Signature: ()I
  Code:
   Stack=1, Locals=1, Args_size=1
	iconst_1
	ireturn
  Labels:

public java.lang.Object productElement(int);
  Signature: (I)Ljava/lang/Object;
  Code:
   Stack=3, Locals=2, Args_size=2
	iload_1
	iconst_0
	if_icmpne	l1 // new
	aload_0
	invokevirtual	Method underlying:()Ljava/util/concurrent/ConcurrentMap;
	areturn
l1	new	class java/lang/IndexOutOfBoundsException
	dup
	iload_1
	invokestatic	Method scala/runtime/BoxesRunTime.boxToInteger:(I)Ljava/lang/Integer;
	invokevirtual	Method java/lang/Object.toString:()Ljava/lang/String;
	invokespecial	Method java/lang/IndexOutOfBoundsException."<init>":(Ljava/lang/String;)V
	athrow
  Labels:
   	l1 = 10 // new

public scala.collection.generic.Subtractable repr();
  Signature: ()Lscala/collection/generic/Subtractable;
  Code:
   Stack=1, Locals=1, Args_size=1
	aload_0
	invokeinterface	InterfaceMethod scala/collection/TraversableLike.repr:()Ljava/lang/Object;
	checkcast	class scala/collection/generic/Subtractable
	areturn
  Labels:

public scala.collection.TraversableView view(int, int);
  Signature: (II)Lscala/collection/TraversableView;
  Code:
   Stack=3, Locals=3, Args_size=3
	aload_0
	iload_1
	iload_2
	invokeinterface	InterfaceMethod scala/collection/IterableLike.view:(II)Lscala/collection/IterableView;
	areturn
  Labels:
  LocalVariableTable: 
   Start  Length  Slot  Name   Signature
   0      9      0    this       Lscala/collection/JavaConversions$JConcurrentMapWrapper;
   0      9      1    from       I
   0      9      2    until       I


public scala.collection.TraversableView view();
  Signature: ()Lscala/collection/TraversableView;
  Code:
   Stack=1, Locals=1, Args_size=1
	aload_0
	invokeinterface	InterfaceMethod scala/collection/IterableLike.view:()Lscala/collection/IterableView;
	areturn
  Labels:

public scala.collection.Traversable toCollection(java.lang.Object);
  Signature: (Ljava/lang/Object;)Lscala/collection/Traversable;
  Code:
   Stack=2, Locals=2, Args_size=2
	aload_0
	aload_1
	invokeinterface	InterfaceMethod scala/collection/IterableLike.toCollection:(Ljava/lang/Object;)Lscala/collection/Iterable;
	areturn
  Labels:
  LocalVariableTable: 
   Start  Length  Slot  Name   Signature
   0      8      0    this       Lscala/collection/JavaConversions$JConcurrentMapWrapper;
   0      8      1    repr       Ljava/lang/Object;


public scala.collection.Traversable thisCollection();
  Signature: ()Lscala/collection/Traversable;
  Code:
   Stack=1, Locals=1, Args_size=1
	aload_0
	invokeinterface	InterfaceMethod scala/collection/IterableLike.thisCollection:()Lscala/collection/Iterable;
	areturn
  Labels:

public scala.Function1 andThen(scala.Function1);
  Signature: (Lscala/Function1;)Lscala/Function1;
  Code:
   Stack=2, Locals=2, Args_size=2
	aload_0
	aload_1
	invokeinterface	InterfaceMethod scala/PartialFunction.andThen:(Lscala/Function1;)Lscala/PartialFunction;
	areturn
  Labels:
  LocalVariableTable: 
   Start  Length  Slot  Name   Signature
   0      8      0    this       Lscala/collection/JavaConversions$JConcurrentMapWrapper;
   0      8      1    g       Lscala/Function1;


public java.lang.Object filterNot(scala.Function1);
  Signature: (Lscala/Function1;)Ljava/lang/Object;
  Code:
   Stack=2, Locals=2, Args_size=2
	aload_0
	aload_1
	invokeinterface	InterfaceMethod scala/collection/MapLike.filterNot:(Lscala/Function1;)Lscala/collection/Map;
	areturn
  Labels:
  LocalVariableTable: 
   Start  Length  Slot  Name   Signature
   0      8      0    this       Lscala/collection/JavaConversions$JConcurrentMapWrapper;
   0      8      1    p       Lscala/Function1;


public scala.collection.generic.Subtractable $minus$minus(scala.collection.Iterator);
  Signature: (Lscala/collection/Iterator;)Lscala/collection/generic/Subtractable;
  Code:
   Stack=2, Locals=2, Args_size=2
	aload_0
	aload_1
	invokeinterface	InterfaceMethod scala/collection/mutable/MapLike.$minus$minus:(Lscala/collection/Iterator;)Lscala/collection/mutable/Map;
	areturn
  Labels:
  LocalVariableTable: 
   Start  Length  Slot  Name   Signature
   0      8      0    this       Lscala/collection/JavaConversions$JConcurrentMapWrapper;
   0      8      1    iter       Lscala/collection/Iterator;


public scala.collection.generic.Subtractable $minus$minus(scala.collection.Traversable);
  Signature: (Lscala/collection/Traversable;)Lscala/collection/generic/Subtractable;
  Code:
   Stack=2, Locals=2, Args_size=2
	aload_0
	aload_1
	invokeinterface	InterfaceMethod scala/collection/mutable/MapLike.$minus$minus:(Lscala/collection/Traversable;)Lscala/collection/mutable/Map;
	areturn
  Labels:
  LocalVariableTable: 
   Start  Length  Slot  Name   Signature
   0      8      0    this       Lscala/collection/JavaConversions$JConcurrentMapWrapper;
   0      8      1    elems       Lscala/collection/Traversable;


public scala.collection.generic.Subtractable $minus(java.lang.Object, java.lang.Object, scala.collection.Seq);
  Signature: (Ljava/lang/Object;Ljava/lang/Object;Lscala/collection/Seq;)Lscala/collection/generic/Subtractable;
  Code:
   Stack=4, Locals=4, Args_size=4
	aload_0
	aload_1
	aload_2
	aload_3
	invokeinterface	InterfaceMethod scala/collection/mutable/MapLike.$minus:(Ljava/lang/Object;Ljava/lang/Object;Lscala/collection/Seq;)Lscala/collection/mutable/Map;
	areturn
  Labels:
  LocalVariableTable: 
   Start  Length  Slot  Name   Signature
   0      10      0    this       Lscala/collection/JavaConversions$JConcurrentMapWrapper;
   0      10      1    elem1       Ljava/lang/Object;
   0      10      2    elem2       Ljava/lang/Object;
   0      10      3    elems       Lscala/collection/Seq;


public java.lang.Object result();
  Signature: ()Ljava/lang/Object;
  Code:
   Stack=1, Locals=1, Args_size=1
	aload_0
	invokeinterface	InterfaceMethod scala/collection/mutable/MapLike.result:()Lscala/collection/mutable/Map;
	areturn
  Labels:

public java.lang.Object clone();
  Signature: ()Ljava/lang/Object;
  Code:
   Stack=1, Locals=1, Args_size=1
	aload_0
	invokeinterface	InterfaceMethod scala/collection/mutable/MapLike.clone:()Lscala/collection/mutable/Map;
	areturn
  Labels:

public scala.collection.generic.Subtractable $minus(java.lang.Object);
  Signature: (Ljava/lang/Object;)Lscala/collection/generic/Subtractable;
  Code:
   Stack=2, Locals=2, Args_size=2
	aload_0
	aload_1
	invokeinterface	InterfaceMethod scala/collection/mutable/MapLike.$minus:(Ljava/lang/Object;)Lscala/collection/mutable/Map;
	areturn
  Labels:
  LocalVariableTable: 
   Start  Length  Slot  Name   Signature
   0      8      0    this       Lscala/collection/JavaConversions$JConcurrentMapWrapper;
   0      8      1    elem       Ljava/lang/Object;


public scala.collection.Map $minus(java.lang.Object);
  Signature: (Ljava/lang/Object;)Lscala/collection/Map;
  Code:
   Stack=2, Locals=2, Args_size=2
	aload_0
	aload_1
	invokeinterface	InterfaceMethod scala/collection/mutable/MapLike.$minus:(Ljava/lang/Object;)Lscala/collection/mutable/Map;
	areturn
  Labels:
  LocalVariableTable: 
   Start  Length  Slot  Name   Signature
   0      8      0    this       Lscala/collection/JavaConversions$JConcurrentMapWrapper;
   0      8      1    key       Ljava/lang/Object;


public scala.collection.Map $plus$plus(scala.collection.Iterator);
  Signature: (Lscala/collection/Iterator;)Lscala/collection/Map;
  Code:
   Stack=2, Locals=2, Args_size=2
	aload_0
	aload_1
	invokeinterface	InterfaceMethod scala/collection/mutable/MapLike.$plus$plus:(Lscala/collection/Iterator;)Lscala/collection/mutable/Map;
	areturn
  Labels:
  LocalVariableTable: 
   Start  Length  Slot  Name   Signature
   0      8      0    this       Lscala/collection/JavaConversions$JConcurrentMapWrapper;
   0      8      1    iter       Lscala/collection/Iterator;


public scala.collection.Map $plus$plus(scala.collection.Traversable);
  Signature: (Lscala/collection/Traversable;)Lscala/collection/Map;
  Code:
   Stack=2, Locals=2, Args_size=2
	aload_0
	aload_1
	invokeinterface	InterfaceMethod scala/collection/mutable/MapLike.$plus$plus:(Lscala/collection/Traversable;)Lscala/collection/mutable/Map;
	areturn
  Labels:
  LocalVariableTable: 
   Start  Length  Slot  Name   Signature
   0      8      0    this       Lscala/collection/JavaConversions$JConcurrentMapWrapper;
   0      8      1    kvs       Lscala/collection/Traversable;


public scala.collection.Map $plus(scala.Tuple2, scala.Tuple2, scala.collection.Seq);
  Signature: (Lscala/Tuple2;Lscala/Tuple2;Lscala/collection/Seq;)Lscala/collection/Map;
  Code:
   Stack=4, Locals=4, Args_size=4
	aload_0
	aload_1
	aload_2
	aload_3
	invokeinterface	InterfaceMethod scala/collection/mutable/MapLike.$plus:(Lscala/Tuple2;Lscala/Tuple2;Lscala/collection/Seq;)Lscala/collection/mutable/Map;
	areturn
  Labels:
  LocalVariableTable: 
   Start  Length  Slot  Name   Signature
   0      10      0    this       Lscala/collection/JavaConversions$JConcurrentMapWrapper;
   0      10      1    kv1       Lscala/Tuple2;
   0      10      2    kv2       Lscala/Tuple2;
   0      10      3    kvs       Lscala/collection/Seq;


public scala.collection.Map $plus(scala.Tuple2);
  Signature: (Lscala/Tuple2;)Lscala/collection/Map;
  Code:
   Stack=2, Locals=2, Args_size=2
	aload_0
	aload_1
	invokeinterface	InterfaceMethod scala/collection/mutable/MapLike.$plus:(Lscala/Tuple2;)Lscala/collection/mutable/Map;
	areturn
  Labels:
  LocalVariableTable: 
   Start  Length  Slot  Name   Signature
   0      8      0    this       Lscala/collection/JavaConversions$JConcurrentMapWrapper;
   0      8      1    kv       Lscala/Tuple2;


public scala.collection.Map updated(java.lang.Object, java.lang.Object);
  Signature: (Ljava/lang/Object;Ljava/lang/Object;)Lscala/collection/Map;
  Code:
   Stack=3, Locals=3, Args_size=3
	aload_0
	aload_1
	aload_2
	invokeinterface	InterfaceMethod scala/collection/mutable/MapLike.updated:(Ljava/lang/Object;Ljava/lang/Object;)Lscala/collection/mutable/Map;
	areturn
  Labels:
  LocalVariableTable: 
   Start  Length  Slot  Name   Signature
   0      9      0    this       Lscala/collection/JavaConversions$JConcurrentMapWrapper;
   0      9      1    key       Ljava/lang/Object;
   0      9      2    value       Ljava/lang/Object;


public scala.collection.generic.Shrinkable $minus$eq(java.lang.Object);
  Signature: (Ljava/lang/Object;)Lscala/collection/generic/Shrinkable;
  Code:
   Stack=2, Locals=2, Args_size=2
	aload_0
	aload_1
	invokeinterface	InterfaceMethod scala/collection/JavaConversions$JMapWrapperLike.$minus$eq:(Ljava/lang/Object;)Lscala/collection/JavaConversions$JMapWrapperLike;
	areturn
  Labels:
  LocalVariableTable: 
   Start  Length  Slot  Name   Signature
   0      8      0    this       Lscala/collection/JavaConversions$JConcurrentMapWrapper;
   0      8      1    elem       Ljava/lang/Object;


public scala.collection.mutable.MapLike $minus$eq(java.lang.Object);
  Signature: (Ljava/lang/Object;)Lscala/collection/mutable/MapLike;
  Code:
   Stack=2, Locals=2, Args_size=2
	aload_0
	aload_1
	invokeinterface	InterfaceMethod scala/collection/JavaConversions$JMapWrapperLike.$minus$eq:(Ljava/lang/Object;)Lscala/collection/JavaConversions$JMapWrapperLike;
	areturn
  Labels:
  LocalVariableTable: 
   Start  Length  Slot  Name   Signature
   0      8      0    this       Lscala/collection/JavaConversions$JConcurrentMapWrapper;
   0      8      1    key       Ljava/lang/Object;


public scala.collection.generic.Growable $plus$eq(java.lang.Object);
  Signature: (Ljava/lang/Object;)Lscala/collection/generic/Growable;
  Code:
   Stack=2, Locals=2, Args_size=2
	aload_0
	aload_1
	checkcast	class scala/Tuple2
	invokeinterface	InterfaceMethod scala/collection/JavaConversions$JMapWrapperLike.$plus$eq:(Lscala/Tuple2;)Lscala/collection/JavaConversions$JMapWrapperLike;
	areturn
  Labels:
  LocalVariableTable: 
   Start  Length  Slot  Name   Signature
   0      11      0    this       Lscala/collection/JavaConversions$JConcurrentMapWrapper;
   0      11      1    elem       Ljava/lang/Object;


public scala.collection.mutable.Builder $plus$eq(java.lang.Object);
  Signature: (Ljava/lang/Object;)Lscala/collection/mutable/Builder;
  Code:
   Stack=2, Locals=2, Args_size=2
	aload_0
	aload_1
	checkcast	class scala/Tuple2
	invokeinterface	InterfaceMethod scala/collection/JavaConversions$JMapWrapperLike.$plus$eq:(Lscala/Tuple2;)Lscala/collection/JavaConversions$JMapWrapperLike;
	areturn
  Labels:
  LocalVariableTable: 
   Start  Length  Slot  Name   Signature
   0      11      0    this       Lscala/collection/JavaConversions$JConcurrentMapWrapper;
   0      11      1    elem       Ljava/lang/Object;


public scala.collection.mutable.MapLike $plus$eq(scala.Tuple2);
  Signature: (Lscala/Tuple2;)Lscala/collection/mutable/MapLike;
  Code:
   Stack=2, Locals=2, Args_size=2
	aload_0
	aload_1
	invokeinterface	InterfaceMethod scala/collection/JavaConversions$JMapWrapperLike.$plus$eq:(Lscala/Tuple2;)Lscala/collection/JavaConversions$JMapWrapperLike;
	areturn
  Labels:
  LocalVariableTable: 
   Start  Length  Slot  Name   Signature
   0      8      0    this       Lscala/collection/JavaConversions$JConcurrentMapWrapper;
   0      8      1    kv       Lscala/Tuple2;


public scala.collection.Map empty();
  Signature: ()Lscala/collection/Map;
  Code:
   Stack=1, Locals=1, Args_size=1
	aload_0
	invokevirtual	Method empty:()Lscala/collection/JavaConversions$JConcurrentMapWrapper;
	areturn
  Labels:

public scala.collection.mutable.Map empty();
  Signature: ()Lscala/collection/mutable/Map;
  Code:
   Stack=1, Locals=1, Args_size=1
	aload_0
	invokevirtual	Method empty:()Lscala/collection/JavaConversions$JConcurrentMapWrapper;
	areturn
  Labels:

public java.util.Map underlying();
  Signature: ()Ljava/util/Map;
  Code:
   Stack=1, Locals=1, Args_size=1
	aload_0
	invokevirtual	Method underlying:()Ljava/util/concurrent/ConcurrentMap;
	areturn
  Labels:

public scala.collection.JavaConversions$JConcurrentMapWrapper(java.util.concurrent.ConcurrentMap);
  Signature: (Ljava/util/concurrent/ConcurrentMap;)V
  Code:
   Stack=2, Locals=2, Args_size=2
	aload_0
	aload_1
	putfield	Field underlying:Ljava/util/concurrent/ConcurrentMap;
	aload_0
	invokespecial	Method java/lang/Object."<init>":()V
	aload_0
	invokestatic	Method scala/collection/TraversableLike$class.$init$:(Lscala/collection/TraversableLike;)V
	aload_0
	invokestatic	Method scala/collection/generic/GenericTraversableTemplate$class.$init$:(Lscala/collection/generic/GenericTraversableTemplate;)V
	aload_0
	invokestatic	Method scala/collection/Traversable$class.$init$:(Lscala/collection/Traversable;)V
	aload_0
	invokestatic	Method scala/collection/mutable/Traversable$class.$init$:(Lscala/collection/mutable/Traversable;)V
	aload_0
	invokestatic	Method scala/collection/IterableLike$class.$init$:(Lscala/collection/IterableLike;)V
	aload_0
	invokestatic	Method scala/collection/Iterable$class.$init$:(Lscala/collection/Iterable;)V
	aload_0
	invokestatic	Method scala/collection/mutable/Iterable$class.$init$:(Lscala/collection/mutable/Iterable;)V
	aload_0
	invokestatic	Method scala/Function1$class.$init$:(Lscala/Function1;)V
	aload_0
	invokestatic	Method scala/PartialFunction$class.$init$:(Lscala/PartialFunction;)V
	aload_0
	invokestatic	Method scala/collection/generic/Subtractable$class.$init$:(Lscala/collection/generic/Subtractable;)V
	aload_0
	invokestatic	Method scala/collection/MapLike$class.$init$:(Lscala/collection/MapLike;)V
	aload_0
	invokestatic	Method scala/collection/Map$class.$init$:(Lscala/collection/Map;)V
	aload_0
	invokestatic	Method scala/collection/generic/Growable$class.$init$:(Lscala/collection/generic/Growable;)V
	aload_0
	invokestatic	Method scala/collection/mutable/Builder$class.$init$:(Lscala/collection/mutable/Builder;)V
	aload_0
	invokestatic	Method scala/collection/generic/Shrinkable$class.$init$:(Lscala/collection/generic/Shrinkable;)V
	aload_0
	invokestatic	Method scala/collection/mutable/Cloneable$class.$init$:(Lscala/collection/mutable/Cloneable;)V
	aload_0
	invokestatic	Method scala/collection/mutable/MapLike$class.$init$:(Lscala/collection/mutable/MapLike;)V
	aload_0
	invokestatic	Method scala/collection/mutable/Map$class.$init$:(Lscala/collection/mutable/Map;)V
	aload_0
	invokestatic	Method scala/collection/JavaConversions$JMapWrapperLike$class.$init$:(Lscala/collection/JavaConversions$JMapWrapperLike;)V
	aload_0
	invokestatic	Method scala/Product$class.$init$:(Lscala/Product;)V
	return
  Labels:
  LocalVariableTable: 
   Start  Length  Slot  Name   Signature
   0      90      0    this       Lscala/collection/JavaConversions$JConcurrentMapWrapper;
   0      90      1    underlying       Ljava/util/concurrent/ConcurrentMap;

  Signature: length = 0x2
   03 FFFFFFAF 

}

