Compiled from "JavaConversions.scala"
public class scala.collection.JavaConversions$MutableSetWrapper extends java.util.AbstractSet implements scala.ScalaObject,scala.Product,java.io.Serializable
  SourceFile: "JavaConversions.scala"
  Signature: length = 0x2
   00 7F 
  Scala: length = 0x
   
  InnerClass: 
   public #72= #15 of #131; //MutableSetWrapper=class scala/collection/JavaConversions$MutableSetWrapper of class scala/collection/JavaConversions
   public final #132= #79 of #15; //$anon$3=class scala/collection/JavaConversions$MutableSetWrapper$$anon$3 of class scala/collection/JavaConversions$MutableSetWrapper
  minor version: 0
  major version: 49
  Constant pool:
const #1 = Asciz	SourceFile;
const #2 = Asciz	JavaConversions.scala;
const #3 = Asciz	m;
const #4 = Asciz	Lscala/reflect/ClassManifest;;
const #5 = Asciz	Lscala/reflect/ClassManifest<TA;>;;
const #6 = Asciz	Signature;
const #7 = Asciz	underlying;
const #8 = Asciz	Lscala/collection/mutable/Set;;
const #9 = Asciz	Lscala/collection/mutable/Set<TA;>;;
const #10 = Asciz	<init>;
const #11 = Asciz	(Lscala/collection/mutable/Set;Lscala/reflect/ClassManifest;)V;
const #12 = Asciz	Code;
const #13 = Asciz	LineNumberTable;
const #14 = Asciz	scala/collection/JavaConversions$MutableSetWrapper;
const #15 = class	#14;	//  scala/collection/JavaConversions$MutableSetWrapper
const #16 = NameAndType	#7:#8;//  underlying:Lscala/collection/mutable/Set;
const #17 = Field	#15.#16;	//  scala/collection/JavaConversions$MutableSetWrapper.underlying:Lscala/collection/mutable/Set;
const #18 = NameAndType	#3:#4;//  m:Lscala/reflect/ClassManifest;
const #19 = Field	#15.#18;	//  scala/collection/JavaConversions$MutableSetWrapper.m:Lscala/reflect/ClassManifest;
const #20 = Asciz	java/util/AbstractSet;
const #21 = class	#20;	//  java/util/AbstractSet
const #22 = Asciz	()V;
const #23 = NameAndType	#10:#22;//  "<init>":()V
const #24 = Method	#21.#23;	//  java/util/AbstractSet."<init>":()V
const #25 = Asciz	scala/Product$class;
const #26 = class	#25;	//  scala/Product$class
const #27 = Asciz	$init$;
const #28 = Asciz	(Lscala/Product;)V;
const #29 = NameAndType	#27:#28;//  $init$:(Lscala/Product;)V
const #30 = Method	#26.#29;	//  scala/Product$class.$init$:(Lscala/Product;)V
const #31 = Asciz	this;
const #32 = Asciz	Lscala/collection/JavaConversions$MutableSetWrapper;;
const #33 = Asciz	LocalVariableTable;
const #34 = Asciz	(Lscala/collection/mutable/Set<TA;>;Lscala/reflect/ClassManifest<TA;>;)V;
const #35 = Asciz	iterator;
const #36 = Asciz	()Ljava/util/Iterator;;
const #37 = Asciz	()Ljava/lang/Object;;
const #38 = NameAndType	#35:#37;//  iterator:()Ljava/lang/Object;
const #39 = Method	#15.#38;	//  scala/collection/JavaConversions$MutableSetWrapper.iterator:()Ljava/lang/Object;
const #40 = Asciz	java/util/Iterator;
const #41 = class	#40;	//  java/util/Iterator
const #42 = Asciz	canEqual;
const #43 = Asciz	(Ljava/lang/Object;)Z;
const #44 = Asciz	productElement;
const #45 = Asciz	(I)Ljava/lang/Object;;
const #46 = Asciz	()Lscala/collection/mutable/Set;;
const #47 = NameAndType	#7:#46;//  underlying:()Lscala/collection/mutable/Set;
const #48 = Method	#15.#47;	//  scala/collection/JavaConversions$MutableSetWrapper.underlying:()Lscala/collection/mutable/Set;
const #49 = Asciz	scala/MatchError;
const #50 = class	#49;	//  scala/MatchError
const #51 = Asciz	scala/runtime/BoxesRunTime;
const #52 = class	#51;	//  scala/runtime/BoxesRunTime
const #53 = Asciz	boxToInteger;
const #54 = Asciz	(I)Ljava/lang/Integer;;
const #55 = NameAndType	#53:#54;//  boxToInteger:(I)Ljava/lang/Integer;
const #56 = Method	#52.#55;	//  scala/runtime/BoxesRunTime.boxToInteger:(I)Ljava/lang/Integer;
const #57 = Asciz	java/lang/Object;
const #58 = class	#57;	//  java/lang/Object
const #59 = Asciz	toString;
const #60 = Asciz	()Ljava/lang/String;;
const #61 = NameAndType	#59:#60;//  toString:()Ljava/lang/String;
const #62 = Method	#58.#61;	//  java/lang/Object.toString:()Ljava/lang/String;
const #63 = Asciz	(Ljava/lang/String;)V;
const #64 = NameAndType	#10:#63;//  "<init>":(Ljava/lang/String;)V
const #65 = Method	#50.#64;	//  scala/MatchError."<init>":(Ljava/lang/String;)V
const #66 = Asciz	java/lang/IndexOutOfBoundsException;
const #67 = class	#66;	//  java/lang/IndexOutOfBoundsException
const #68 = Method	#67.#64;	//  java/lang/IndexOutOfBoundsException."<init>":(Ljava/lang/String;)V
const #69 = Asciz	productArity;
const #70 = Asciz	()I;
const #71 = Asciz	productPrefix;
const #72 = Asciz	MutableSetWrapper;
const #73 = String	#72;	//  MutableSetWrapper
const #74 = Asciz	copy;
const #75 = Asciz	(Lscala/collection/mutable/Set;Lscala/reflect/ClassManifest;)Lscala/collection/JavaConversions$MutableSetWrapper;;
const #76 = NameAndType	#10:#11;//  "<init>":(Lscala/collection/mutable/Set;Lscala/reflect/ClassManifest;)V
const #77 = Method	#15.#76;	//  scala/collection/JavaConversions$MutableSetWrapper."<init>":(Lscala/collection/mutable/Set;Lscala/reflect/ClassManifest;)V
const #78 = Asciz	scala/collection/JavaConversions$MutableSetWrapper$$anon$3;
const #79 = class	#78;	//  scala/collection/JavaConversions$MutableSetWrapper$$anon$3
const #80 = Asciz	(Lscala/collection/JavaConversions$MutableSetWrapper;)V;
const #81 = NameAndType	#10:#80;//  "<init>":(Lscala/collection/JavaConversions$MutableSetWrapper;)V
const #82 = Method	#79.#81;	//  scala/collection/JavaConversions$MutableSetWrapper$$anon$3."<init>":(Lscala/collection/JavaConversions$MutableSetWrapper;)V
const #83 = Asciz	remove;
const #84 = Asciz	scala/reflect/ClassManifest;
const #85 = class	#84;	//  scala/reflect/ClassManifest
const #86 = Asciz	erasure;
const #87 = Asciz	()Ljava/lang/Class;;
const #88 = NameAndType	#86:#87;//  erasure:()Ljava/lang/Class;
const #89 = InterfaceMethod	#85.#88;	//  scala/reflect/ClassManifest.erasure:()Ljava/lang/Class;
const #90 = Asciz	java/lang/Class;
const #91 = class	#90;	//  java/lang/Class
const #92 = Asciz	isInstance;
const #93 = NameAndType	#92:#43;//  isInstance:(Ljava/lang/Object;)Z
const #94 = Method	#91.#93;	//  java/lang/Class.isInstance:(Ljava/lang/Object;)Z
const #95 = Asciz	scala/collection/TraversableLike;
const #96 = class	#95;	//  scala/collection/TraversableLike
const #97 = Asciz	size;
const #98 = NameAndType	#97:#70;//  size:()I
const #99 = InterfaceMethod	#96.#98;	//  scala/collection/TraversableLike.size:()I
const #100 = Asciz	scala/collection/mutable/SetLike;
const #101 = class	#100;	//  scala/collection/mutable/SetLike
const #102 = Asciz	$minus$eq;
const #103 = Asciz	(Ljava/lang/Object;)Lscala/collection/mutable/SetLike;;
const #104 = NameAndType	#102:#103;//  $minus$eq:(Ljava/lang/Object;)Lscala/collection/mutable/SetLike;
const #105 = InterfaceMethod	#101.#104;	//  scala/collection/mutable/SetLike.$minus$eq:(Ljava/lang/Object;)Lscala/collection/mutable/SetLike;
const #106 = Asciz	elem;
const #107 = Asciz	Ljava/lang/Object;;
const #108 = Asciz	sz;
const #109 = Asciz	I;
const #110 = Asciz	add;
const #111 = Asciz	$plus$eq;
const #112 = NameAndType	#111:#103;//  $plus$eq:(Ljava/lang/Object;)Lscala/collection/mutable/SetLike;
const #113 = InterfaceMethod	#101.#112;	//  scala/collection/mutable/SetLike.$plus$eq:(Ljava/lang/Object;)Lscala/collection/mutable/SetLike;
const #114 = Asciz	(TA;)Z;
const #115 = Asciz	()Lscala/collection/mutable/Set<TA;>;;
const #116 = Asciz	copy$default$1;
const #117 = Asciz	copy$default$2;
const #118 = Asciz	(Lscala/collection/mutable/Set;)Lscala/reflect/ClassManifest;;
const #119 = Asciz	productElements;
const #120 = Asciz	()Lscala/collection/Iterator;;
const #121 = Asciz	(Lscala/Product;)Lscala/collection/Iterator;;
const #122 = NameAndType	#119:#121;//  productElements:(Lscala/Product;)Lscala/collection/Iterator;
const #123 = Method	#26.#122;	//  scala/Product$class.productElements:(Lscala/Product;)Lscala/collection/Iterator;
const #124 = Asciz	productIterator;
const #125 = NameAndType	#124:#121;//  productIterator:(Lscala/Product;)Lscala/collection/Iterator;
const #126 = Method	#26.#125;	//  scala/Product$class.productIterator:(Lscala/Product;)Lscala/collection/Iterator;
const #127 = Asciz	<A:Ljava/lang/Object;>Ljava/util/AbstractSet<TA;>;Lscala/ScalaObject;Lscala/Product;;
const #128 = Asciz	Scala;
const #129 = Asciz	InnerClasses;
const #130 = Asciz	scala/collection/JavaConversions;
const #131 = class	#130;	//  scala/collection/JavaConversions
const #132 = Asciz	$anon$3;
const #133 = Asciz	scala/ScalaObject;
const #134 = class	#133;	//  scala/ScalaObject
const #135 = Asciz	scala/Product;
const #136 = class	#135;	//  scala/Product
const #137 = Asciz	java/io/Serializable;
const #138 = class	#137;	//  java/io/Serializable

{
public scala.collection.JavaConversions$MutableSetWrapper(scala.collection.mutable.Set, scala.reflect.ClassManifest);
  Code:
   Stack=2, Locals=3, Args_size=3
   0:	aload_0
   1:	aload_1
   2:	putfield	#17; //Field underlying:Lscala/collection/mutable/Set;
   5:	aload_0
   6:	aload_2
   7:	putfield	#19; //Field m:Lscala/reflect/ClassManifest;
   10:	aload_0
   11:	invokespecial	#24; //Method java/util/AbstractSet."<init>":()V
   14:	aload_0
   15:	invokestatic	#30; //Method scala/Product$class.$init$:(Lscala/Product;)V
   18:	return
  LineNumberTable: 
   line 370: 0

  LocalVariableTable: 
   Start  Length  Slot  Name   Signature
   0      19      0    this       Lscala/collection/JavaConversions$MutableSetWrapper;
   0      19      1    underlying       Lscala/collection/mutable/Set;
   0      19      2    m       Lscala/reflect/ClassManifest;

  Signature: length = 0x2
   00 22 

public java.util.Iterator iterator();
  Code:
   Stack=1, Locals=1, Args_size=1
   0:	aload_0
   1:	invokevirtual	#39; //Method iterator:()Ljava/lang/Object;
   4:	checkcast	#41; //class java/util/Iterator
   7:	areturn
  LineNumberTable: 
   line 370: 0


public boolean canEqual(java.lang.Object);
  Code:
   Stack=1, Locals=2, Args_size=2
   0:	aload_1
   1:	instanceof	#15; //class scala/collection/JavaConversions$MutableSetWrapper
   4:	ireturn
  LineNumberTable: 
   line 370: 0


public java.lang.Object productElement(int);
  Code:
   Stack=3, Locals=2, Args_size=2
   0:	iload_1
   1:	iconst_0
   2:	if_icmpne	29
   5:	iconst_1
   6:	ifeq	14
   9:	aload_0
   10:	invokevirtual	#48; //Method underlying:()Lscala/collection/mutable/Set;
   13:	areturn
   14:	new	#50; //class scala/MatchError
   17:	dup
   18:	iload_1
   19:	invokestatic	#56; //Method scala/runtime/BoxesRunTime.boxToInteger:(I)Ljava/lang/Integer;
   22:	invokevirtual	#62; //Method java/lang/Object.toString:()Ljava/lang/String;
   25:	invokespecial	#65; //Method scala/MatchError."<init>":(Ljava/lang/String;)V
   28:	athrow
   29:	iconst_1
   30:	ifeq	48
   33:	new	#67; //class java/lang/IndexOutOfBoundsException
   36:	dup
   37:	iload_1
   38:	invokestatic	#56; //Method scala/runtime/BoxesRunTime.boxToInteger:(I)Ljava/lang/Integer;
   41:	invokevirtual	#62; //Method java/lang/Object.toString:()Ljava/lang/String;
   44:	invokespecial	#68; //Method java/lang/IndexOutOfBoundsException."<init>":(Ljava/lang/String;)V
   47:	athrow
   48:	new	#50; //class scala/MatchError
   51:	dup
   52:	iload_1
   53:	invokestatic	#56; //Method scala/runtime/BoxesRunTime.boxToInteger:(I)Ljava/lang/Integer;
   56:	invokevirtual	#62; //Method java/lang/Object.toString:()Ljava/lang/String;
   59:	invokespecial	#65; //Method scala/MatchError."<init>":(Ljava/lang/String;)V
   62:	athrow
  LineNumberTable: 
   line 370: 0
   line 21: 5
   line 370: 9
   line 21: 29
   line 370: 33


public int productArity();
  Code:
   Stack=1, Locals=1, Args_size=1
   0:	iconst_1
   1:	ireturn
  LineNumberTable: 
   line 370: 0


public java.lang.String productPrefix();
  Code:
   Stack=1, Locals=1, Args_size=1
   0:	ldc	#73; //String MutableSetWrapper
   2:	areturn
  LineNumberTable: 
   line 370: 0


public scala.collection.JavaConversions$MutableSetWrapper copy(scala.collection.mutable.Set, scala.reflect.ClassManifest);
  Code:
   Stack=4, Locals=3, Args_size=3
   0:	new	#15; //class scala/collection/JavaConversions$MutableSetWrapper
   3:	dup
   4:	aload_1
   5:	aload_2
   6:	invokespecial	#77; //Method "<init>":(Lscala/collection/mutable/Set;Lscala/reflect/ClassManifest;)V
   9:	areturn
  LineNumberTable: 
   line 370: 0

  LocalVariableTable: 
   Start  Length  Slot  Name   Signature
   0      10      0    this       Lscala/collection/JavaConversions$MutableSetWrapper;
   0      10      1    underlying       Lscala/collection/mutable/Set;
   0      10      2    m       Lscala/reflect/ClassManifest;


public java.lang.Object iterator();
  Code:
   Stack=3, Locals=1, Args_size=1
   0:	new	#79; //class scala/collection/JavaConversions$MutableSetWrapper$$anon$3
   3:	dup
   4:	aload_0
   5:	invokespecial	#82; //Method scala/collection/JavaConversions$MutableSetWrapper$$anon$3."<init>":(Lscala/collection/JavaConversions$MutableSetWrapper;)V
   8:	areturn
  LineNumberTable: 
   line 381: 0


public boolean remove(java.lang.Object);
  Code:
   Stack=2, Locals=3, Args_size=2
   0:	aload_0
   1:	getfield	#19; //Field m:Lscala/reflect/ClassManifest;
   4:	invokeinterface	#89,  1; //InterfaceMethod scala/reflect/ClassManifest.erasure:()Ljava/lang/Class;
   9:	aload_1
   10:	invokevirtual	#94; //Method java/lang/Class.isInstance:(Ljava/lang/Object;)Z
   13:	ifeq	62
   16:	aload_0
   17:	invokevirtual	#48; //Method underlying:()Lscala/collection/mutable/Set;
   20:	invokeinterface	#99,  1; //InterfaceMethod scala/collection/TraversableLike.size:()I
   25:	istore_2
   26:	aload_0
   27:	invokevirtual	#48; //Method underlying:()Lscala/collection/mutable/Set;
   30:	aload_1
   31:	invokeinterface	#105,  2; //InterfaceMethod scala/collection/mutable/SetLike.$minus$eq:(Ljava/lang/Object;)Lscala/collection/mutable/SetLike;
   36:	pop
   37:	iload_2
   38:	aload_0
   39:	invokevirtual	#48; //Method underlying:()Lscala/collection/mutable/Set;
   42:	invokeinterface	#99,  1; //InterfaceMethod scala/collection/TraversableLike.size:()I
   47:	if_icmple	54
   50:	iconst_1
   51:	goto	55
   54:	iconst_0
   55:	ifeq	62
   58:	iconst_1
   59:	goto	63
   62:	iconst_0
   63:	ireturn
  LineNumberTable: 
   line 375: 0
   line 376: 16
   line 377: 26
   line 378: 37
   line 375: 55

  LocalVariableTable: 
   Start  Length  Slot  Name   Signature
   0      64      0    this       Lscala/collection/JavaConversions$MutableSetWrapper;
   0      64      1    elem       Ljava/lang/Object;
   26      32      2    sz       I


public boolean add(java.lang.Object);
  Code:
   Stack=2, Locals=3, Args_size=2
   0:	aload_0
   1:	invokevirtual	#48; //Method underlying:()Lscala/collection/mutable/Set;
   4:	invokeinterface	#99,  1; //InterfaceMethod scala/collection/TraversableLike.size:()I
   9:	istore_2
   10:	aload_0
   11:	invokevirtual	#48; //Method underlying:()Lscala/collection/mutable/Set;
   14:	aload_1
   15:	invokeinterface	#113,  2; //InterfaceMethod scala/collection/mutable/SetLike.$plus$eq:(Ljava/lang/Object;)Lscala/collection/mutable/SetLike;
   20:	pop
   21:	iload_2
   22:	aload_0
   23:	invokevirtual	#48; //Method underlying:()Lscala/collection/mutable/Set;
   26:	invokeinterface	#99,  1; //InterfaceMethod scala/collection/TraversableLike.size:()I
   31:	if_icmpge	38
   34:	iconst_1
   35:	goto	39
   38:	iconst_0
   39:	ireturn
  LineNumberTable: 
   line 373: 0

  LocalVariableTable: 
   Start  Length  Slot  Name   Signature
   0      40      0    this       Lscala/collection/JavaConversions$MutableSetWrapper;
   0      40      1    elem       Ljava/lang/Object;
   10      30      2    sz       I

  Signature: length = 0x2
   00 72 

public int size();
  Code:
   Stack=1, Locals=1, Args_size=1
   0:	aload_0
   1:	invokevirtual	#48; //Method underlying:()Lscala/collection/mutable/Set;
   4:	invokeinterface	#99,  1; //InterfaceMethod scala/collection/TraversableLike.size:()I
   9:	ireturn
  LineNumberTable: 
   line 372: 0


public scala.collection.mutable.Set underlying();
  Code:
   Stack=1, Locals=1, Args_size=1
   0:	aload_0
   1:	getfield	#17; //Field underlying:Lscala/collection/mutable/Set;
   4:	areturn
  LineNumberTable: 
   line 370: 0

  Signature: length = 0x2
   00 73 

public scala.collection.mutable.Set copy$default$1();
  Code:
   Stack=1, Locals=1, Args_size=1
   0:	aload_0
   1:	invokevirtual	#48; //Method underlying:()Lscala/collection/mutable/Set;
   4:	areturn
  LineNumberTable: 
   line 370: 0


public scala.reflect.ClassManifest copy$default$2(scala.collection.mutable.Set);
  Code:
   Stack=1, Locals=2, Args_size=2
   0:	aload_0
   1:	getfield	#19; //Field m:Lscala/reflect/ClassManifest;
   4:	areturn
  LineNumberTable: 
   line 370: 0

  LocalVariableTable: 
   Start  Length  Slot  Name   Signature
   0      5      0    this       Lscala/collection/JavaConversions$MutableSetWrapper;
   0      5      1    underlying       Lscala/collection/mutable/Set;


public scala.collection.Iterator productElements();
  Code:
   Stack=1, Locals=1, Args_size=1
   0:	aload_0
   1:	invokestatic	#123; //Method scala/Product$class.productElements:(Lscala/Product;)Lscala/collection/Iterator;
   4:	areturn
  LineNumberTable: 
   line 370: 0


public scala.collection.Iterator productIterator();
  Code:
   Stack=1, Locals=1, Args_size=1
   0:	aload_0
   1:	invokestatic	#126; //Method scala/Product$class.productIterator:(Lscala/Product;)Lscala/collection/Iterator;
   4:	areturn
  LineNumberTable: 
   line 370: 0


}

