Compiled from "JavaConversions.scala"
public final class scala.collection.JavaConversions$MutableMapWrapper$$anon$1 extends java.util.AbstractSet
  SourceFile: "JavaConversions.scala"
  Signature: length = 0x2
   00 2E 
  Scala: length = 0x
   
  InnerClass: 
   public #51= #43 of #50; //MutableMapWrapper=class scala/collection/JavaConversions$MutableMapWrapper of class scala/collection/JavaConversions
   public final #52= #15 of #43; //$anon$1=class scala/collection/JavaConversions$MutableMapWrapper$$anon$1 of class scala/collection/JavaConversions$MutableMapWrapper
   public final #53= #36 of #15; //$anon$4=class scala/collection/JavaConversions$MutableMapWrapper$$anon$1$$anon$4 of class scala/collection/JavaConversions$MutableMapWrapper$$anon$1
  minor version: 0
  major version: 49
  Constant pool:
const #1 = Asciz	SourceFile;
const #2 = Asciz	JavaConversions.scala;
const #3 = Asciz	$outer;
const #4 = Asciz	Lscala/collection/JavaConversions$MutableMapWrapper;;
const #5 = Asciz	<init>;
const #6 = Asciz	(Lscala/collection/JavaConversions$MutableMapWrapper;)V;
const #7 = Asciz	Code;
const #8 = Asciz	LineNumberTable;
const #9 = Asciz	java/lang/NullPointerException;
const #10 = class	#9;	//  java/lang/NullPointerException
const #11 = Asciz	()V;
const #12 = NameAndType	#5:#11;//  "<init>":()V
const #13 = Method	#10.#12;	//  java/lang/NullPointerException."<init>":()V
const #14 = Asciz	scala/collection/JavaConversions$MutableMapWrapper$$anon$1;
const #15 = class	#14;	//  scala/collection/JavaConversions$MutableMapWrapper$$anon$1
const #16 = NameAndType	#3:#4;//  $outer:Lscala/collection/JavaConversions$MutableMapWrapper;
const #17 = Field	#15.#16;	//  scala/collection/JavaConversions$MutableMapWrapper$$anon$1.$outer:Lscala/collection/JavaConversions$MutableMapWrapper;
const #18 = Asciz	java/util/AbstractSet;
const #19 = class	#18;	//  java/util/AbstractSet
const #20 = Method	#19.#12;	//  java/util/AbstractSet."<init>":()V
const #21 = Asciz	this;
const #22 = Asciz	Lscala/collection/JavaConversions$MutableMapWrapper$$anon$1;;
const #23 = Asciz	LocalVariableTable;
const #24 = Asciz	(Lscala/collection/JavaConversions$MutableMapWrapper<TA;TB;>;)V;
const #25 = Asciz	Signature;
const #26 = Asciz	iterator;
const #27 = Asciz	()Ljava/util/Iterator;;
const #28 = Asciz	()Ljava/lang/Object;;
const #29 = NameAndType	#26:#28;//  iterator:()Ljava/lang/Object;
const #30 = Method	#15.#29;	//  scala/collection/JavaConversions$MutableMapWrapper$$anon$1.iterator:()Ljava/lang/Object;
const #31 = Asciz	java/util/Iterator;
const #32 = class	#31;	//  java/util/Iterator
const #33 = Asciz	scala$collection$JavaConversions$MutableMapWrapper$$anon$$$outer;
const #34 = Asciz	()Lscala/collection/JavaConversions$MutableMapWrapper;;
const #35 = Asciz	scala/collection/JavaConversions$MutableMapWrapper$$anon$1$$anon$4;
const #36 = class	#35;	//  scala/collection/JavaConversions$MutableMapWrapper$$anon$1$$anon$4
const #37 = Asciz	(Lscala/collection/JavaConversions$MutableMapWrapper$$anon$1;)V;
const #38 = NameAndType	#5:#37;//  "<init>":(Lscala/collection/JavaConversions$MutableMapWrapper$$anon$1;)V
const #39 = Method	#36.#38;	//  scala/collection/JavaConversions$MutableMapWrapper$$anon$1$$anon$4."<init>":(Lscala/collection/JavaConversions$MutableMapWrapper$$anon$1;)V
const #40 = Asciz	size;
const #41 = Asciz	()I;
const #42 = Asciz	scala/collection/JavaConversions$MutableMapWrapper;
const #43 = class	#42;	//  scala/collection/JavaConversions$MutableMapWrapper
const #44 = NameAndType	#40:#41;//  size:()I
const #45 = Method	#43.#44;	//  scala/collection/JavaConversions$MutableMapWrapper.size:()I
const #46 = Asciz	Ljava/util/AbstractSet<Ljava/util/Map$Entry<TA;TB;>;>;;
const #47 = Asciz	Scala;
const #48 = Asciz	InnerClasses;
const #49 = Asciz	scala/collection/JavaConversions;
const #50 = class	#49;	//  scala/collection/JavaConversions
const #51 = Asciz	MutableMapWrapper;
const #52 = Asciz	$anon$1;
const #53 = Asciz	$anon$4;

{
public scala.collection.JavaConversions$MutableMapWrapper$$anon$1(scala.collection.JavaConversions$MutableMapWrapper);
  Code:
   Stack=2, Locals=2, Args_size=2
   0:	aload_1
   1:	ifnonnull	12
   4:	new	#10; //class java/lang/NullPointerException
   7:	dup
   8:	invokespecial	#13; //Method java/lang/NullPointerException."<init>":()V
   11:	athrow
   12:	aload_0
   13:	aload_1
   14:	putfield	#17; //Field $outer:Lscala/collection/JavaConversions$MutableMapWrapper;
   17:	aload_0
   18:	invokespecial	#20; //Method java/util/AbstractSet."<init>":()V
   21:	return
  LineNumberTable: 
   line 432: 0

  LocalVariableTable: 
   Start  Length  Slot  Name   Signature
   0      22      0    this       Lscala/collection/JavaConversions$MutableMapWrapper$$anon$1;
   0      22      1    $outer       Lscala/collection/JavaConversions$MutableMapWrapper;

  Signature: length = 0x2
   00 18 

public java.util.Iterator iterator();
  Code:
   Stack=1, Locals=1, Args_size=1
   0:	aload_0
   1:	invokevirtual	#30; //Method iterator:()Ljava/lang/Object;
   4:	checkcast	#32; //class java/util/Iterator
   7:	areturn
  LineNumberTable: 
   line 432: 0


public scala.collection.JavaConversions$MutableMapWrapper scala$collection$JavaConversions$MutableMapWrapper$$anon$$$outer();
  Code:
   Stack=1, Locals=1, Args_size=1
   0:	aload_0
   1:	getfield	#17; //Field $outer:Lscala/collection/JavaConversions$MutableMapWrapper;
   4:	areturn
  LineNumberTable: 
   line 432: 0


public java.lang.Object iterator();
  Code:
   Stack=3, Locals=1, Args_size=1
   0:	new	#36; //class scala/collection/JavaConversions$MutableMapWrapper$$anon$1$$anon$4
   3:	dup
   4:	aload_0
   5:	invokespecial	#39; //Method scala/collection/JavaConversions$MutableMapWrapper$$anon$1$$anon$4."<init>":(Lscala/collection/JavaConversions$MutableMapWrapper$$anon$1;)V
   8:	areturn
  LineNumberTable: 
   line 435: 0


public int size();
  Code:
   Stack=1, Locals=1, Args_size=1
   0:	aload_0
   1:	getfield	#17; //Field $outer:Lscala/collection/JavaConversions$MutableMapWrapper;
   4:	invokevirtual	#45; //Method scala/collection/JavaConversions$MutableMapWrapper.size:()I
   7:	ireturn
  LineNumberTable: 
   line 433: 0


}

