Compiled from "JavaConversions.scala"
public class scala.collection.JavaConversions$MutableMapWrapper extends java.util.AbstractMap implements scala.ScalaObject,scala.Product,java.io.Serializable
  SourceFile: "JavaConversions.scala"
  Signature: length = 0x2
   00 FFFFFF9D 
  Scala: length = 0x
   
  InnerClass: 
   public MutableMapWrapper=class scala/collection/JavaConversions$MutableMapWrapper of class scala/collection/JavaConversions
   public final $anon$1=class scala/collection/JavaConversions$MutableMapWrapper$$anon$1 of class scala/collection/JavaConversions$MutableMapWrapper
  minor version: 0
  major version: 49
  Constant pool:
Asciz	SourceFile;
Asciz	JavaConversions.scala;
Asciz	m;
Asciz	Lscala/reflect/ClassManifest;;
Asciz	Lscala/reflect/ClassManifest<TA;>;;
Asciz	Signature;
Asciz	underlying;
Asciz	Lscala/collection/mutable/Map;;
Asciz	Lscala/collection/mutable/Map<TA;TB;>;;
Asciz	<init>;
Asciz	(Lscala/collection/mutable/Map;Lscala/reflect/ClassManifest;)V;
Asciz	Code;
Asciz	LineNumberTable;
Asciz	scala/collection/JavaConversions$MutableMapWrapper;
class	scala/collection/JavaConversions$MutableMapWrapper
NameAndType	underlying:Lscala/collection/mutable/Map;
Field	scala/collection/JavaConversions$MutableMapWrapper.underlying:Lscala/collection/mutable/Map;
NameAndType	m:Lscala/reflect/ClassManifest;
Field	scala/collection/JavaConversions$MutableMapWrapper.m:Lscala/reflect/ClassManifest;
Asciz	java/util/AbstractMap;
class	java/util/AbstractMap
Asciz	()V;
NameAndType	"<init>":()V
Method	java/util/AbstractMap."<init>":()V
Asciz	scala/Product$class;
class	scala/Product$class
Asciz	$init$;
Asciz	(Lscala/Product;)V;
NameAndType	$init$:(Lscala/Product;)V
Method	scala/Product$class.$init$:(Lscala/Product;)V
Asciz	this;
Asciz	Lscala/collection/JavaConversions$MutableMapWrapper;;
Asciz	LocalVariableTable;
Asciz	(Lscala/collection/mutable/Map<TA;TB;>;Lscala/reflect/ClassManifest<TA;>;)V;
Asciz	canEqual;
Asciz	(Ljava/lang/Object;)Z;
Asciz	productElement;
Asciz	(I)Ljava/lang/Object;;
Asciz	()Lscala/collection/mutable/Map;;
NameAndType	underlying:()Lscala/collection/mutable/Map;
Method	scala/collection/JavaConversions$MutableMapWrapper.underlying:()Lscala/collection/mutable/Map;
Asciz	java/lang/IndexOutOfBoundsException;
class	java/lang/IndexOutOfBoundsException
Asciz	scala/runtime/BoxesRunTime;
class	scala/runtime/BoxesRunTime
Asciz	boxToInteger;
Asciz	(I)Ljava/lang/Integer;;
NameAndType	boxToInteger:(I)Ljava/lang/Integer;
Method	scala/runtime/BoxesRunTime.boxToInteger:(I)Ljava/lang/Integer;
Asciz	java/lang/Object;
class	java/lang/Object
Asciz	toString;
Asciz	()Ljava/lang/String;;
NameAndType	toString:()Ljava/lang/String;
Method	java/lang/Object.toString:()Ljava/lang/String;
Asciz	(Ljava/lang/String;)V;
NameAndType	"<init>":(Ljava/lang/String;)V
Method	java/lang/IndexOutOfBoundsException."<init>":(Ljava/lang/String;)V
Asciz	productArity;
Asciz	()I;
Asciz	productPrefix;
Asciz	MutableMapWrapper;
String	MutableMapWrapper
Asciz	copy;
Asciz	(Lscala/collection/mutable/Map;Lscala/reflect/ClassManifest;)Lscala/collection/JavaConversions$MutableMapWrapper;;
NameAndType	"<init>":(Lscala/collection/mutable/Map;Lscala/reflect/ClassManifest;)V
Method	scala/collection/JavaConversions$MutableMapWrapper."<init>":(Lscala/collection/mutable/Map;Lscala/reflect/ClassManifest;)V
Asciz	entrySet;
Asciz	()Ljava/util/Set;;
Asciz	scala/collection/JavaConversions$MutableMapWrapper$$anon$1;
class	scala/collection/JavaConversions$MutableMapWrapper$$anon$1
Asciz	(Lscala/collection/JavaConversions$MutableMapWrapper;)V;
NameAndType	"<init>":(Lscala/collection/JavaConversions$MutableMapWrapper;)V
Method	scala/collection/JavaConversions$MutableMapWrapper$$anon$1."<init>":(Lscala/collection/JavaConversions$MutableMapWrapper;)V
Asciz	()Ljava/util/Set<Ljava/util/Map$Entry<TA;TB;>;>;;
Asciz	remove;
Asciz	(Ljava/lang/Object;)Ljava/lang/Object;;
Asciz	scala/reflect/ClassManifest;
class	scala/reflect/ClassManifest
Asciz	erasure;
Asciz	()Ljava/lang/Class;;
NameAndType	erasure:()Ljava/lang/Class;
InterfaceMethod	scala/reflect/ClassManifest.erasure:()Ljava/lang/Class;
Asciz	java/lang/Class;
class	java/lang/Class
Asciz	isInstance;
NameAndType	isInstance:(Ljava/lang/Object;)Z
Method	java/lang/Class.isInstance:(Ljava/lang/Object;)Z
Asciz	scala/collection/MapLike;
class	scala/collection/MapLike
Asciz	get;
Asciz	(Ljava/lang/Object;)Lscala/Option;;
NameAndType	get:(Ljava/lang/Object;)Lscala/Option;
InterfaceMethod	scala/collection/MapLike.get:(Ljava/lang/Object;)Lscala/Option;
Asciz	scala/Some;
class	scala/Some
Asciz	x;
Asciz	Ljava/lang/Object;;
NameAndType	x:Ljava/lang/Object;
Field	scala/Some.x:Ljava/lang/Object;
Asciz	scala/collection/mutable/MapLike;
class	scala/collection/mutable/MapLike
Asciz	$minus$eq;
Asciz	(Ljava/lang/Object;)Lscala/collection/mutable/MapLike;;
NameAndType	$minus$eq:(Ljava/lang/Object;)Lscala/collection/mutable/MapLike;
InterfaceMethod	scala/collection/mutable/MapLike.$minus$eq:(Ljava/lang/Object;)Lscala/collection/mutable/MapLike;
Asciz	scala/None$;
class	scala/None$
Asciz	MODULE$;
Asciz	Lscala/None$;;
NameAndType	MODULE$:Lscala/None$;
Field	scala/None$.MODULE$:Lscala/None$;
Asciz	equals;
NameAndType	equals:(Ljava/lang/Object;)Z
Method	java/lang/Object.equals:(Ljava/lang/Object;)Z
Asciz	scala/MatchError;
class	scala/MatchError
Asciz	scala/Option;
class	scala/Option
Method	scala/Option.toString:()Ljava/lang/String;
Method	scala/MatchError."<init>":(Ljava/lang/String;)V
Asciz	k;
Asciz	temp79;
Asciz	Lscala/Some;;
Asciz	temp80;
Asciz	temp78;
Asciz	Lscala/Option;;
Asciz	(Ljava/lang/Object;)TB;;
Asciz	put;
Asciz	(Ljava/lang/Object;Ljava/lang/Object;)Ljava/lang/Object;;
Asciz	(Ljava/lang/Object;Ljava/lang/Object;)Lscala/Option;;
NameAndType	put:(Ljava/lang/Object;Ljava/lang/Object;)Lscala/Option;
InterfaceMethod	scala/collection/mutable/MapLike.put:(Ljava/lang/Object;Ljava/lang/Object;)Lscala/Option;
Asciz	v;
Asciz	temp75;
Asciz	temp76;
Asciz	temp74;
Asciz	(TA;TB;)TB;;
Asciz	size;
Asciz	scala/collection/TraversableLike;
class	scala/collection/TraversableLike
NameAndType	size:()I
InterfaceMethod	scala/collection/TraversableLike.size:()I
Asciz	()Lscala/collection/mutable/Map<TA;TB;>;;
Asciz	copy$default$1;
Asciz	copy$default$2;
Asciz	(Lscala/collection/mutable/Map;)Lscala/reflect/ClassManifest;;
Asciz	productElements;
Asciz	()Lscala/collection/Iterator;;
Asciz	(Lscala/Product;)Lscala/collection/Iterator;;
NameAndType	productElements:(Lscala/Product;)Lscala/collection/Iterator;
Method	scala/Product$class.productElements:(Lscala/Product;)Lscala/collection/Iterator;
Asciz	Deprecated;
Asciz	productIterator;
NameAndType	productIterator:(Lscala/Product;)Lscala/collection/Iterator;
Method	scala/Product$class.productIterator:(Lscala/Product;)Lscala/collection/Iterator;
Asciz	<A:Ljava/lang/Object;B:Ljava/lang/Object;>Ljava/util/AbstractMap<TA;TB;>;Lscala/ScalaObject;Lscala/Product;;
Asciz	Scala;
Asciz	InnerClasses;
Asciz	scala/collection/JavaConversions;
class	scala/collection/JavaConversions
Asciz	$anon$1;
Asciz	scala/ScalaObject;
class	scala/ScalaObject
Asciz	scala/Product;
class	scala/Product
Asciz	java/io/Serializable;
class	java/io/Serializable

{
private final scala.reflect.ClassManifest m;
  Signature: Lscala/reflect/ClassManifest;
  Signature: length = 0x2
   00 05 

private final scala.collection.mutable.Map underlying;
  Signature: Lscala/collection/mutable/Map;
  Signature: length = 0x2
   00 09 

public scala.collection.JavaConversions$MutableMapWrapper(scala.collection.mutable.Map, scala.reflect.ClassManifest);
  Signature: (Lscala/collection/mutable/Map;Lscala/reflect/ClassManifest;)V
  Code:
   Stack=2, Locals=3, Args_size=3
	aload_0
	aload_1
	putfield	Field underlying:Lscala/collection/mutable/Map;
	aload_0
	aload_2
	putfield	Field m:Lscala/reflect/ClassManifest;
	aload_0
	invokespecial	Method java/util/AbstractMap."<init>":()V
	aload_0
	invokestatic	Method scala/Product$class.$init$:(Lscala/Product;)V
	return
  Labels:
  LocalVariableTable: 
   Start  Length  Slot  Name   Signature
   0      19      0    this       Lscala/collection/JavaConversions$MutableMapWrapper;
   0      19      1    underlying       Lscala/collection/mutable/Map;
   0      19      2    m       Lscala/reflect/ClassManifest;

  Signature: length = 0x2
   00 22 

public boolean canEqual(java.lang.Object);
  Signature: (Ljava/lang/Object;)Z
  Code:
   Stack=1, Locals=2, Args_size=2
	aload_1
	instanceof	class scala/collection/JavaConversions$MutableMapWrapper
	ireturn
  Labels:

public java.lang.Object productElement(int);
  Signature: (I)Ljava/lang/Object;
  Code:
   Stack=3, Locals=2, Args_size=2
	iload_1
	iconst_0
	if_icmpne	l1 // new
	aload_0
	invokevirtual	Method underlying:()Lscala/collection/mutable/Map;
	areturn
l1	new	class java/lang/IndexOutOfBoundsException
	dup
	iload_1
	invokestatic	Method scala/runtime/BoxesRunTime.boxToInteger:(I)Ljava/lang/Integer;
	invokevirtual	Method java/lang/Object.toString:()Ljava/lang/String;
	invokespecial	Method java/lang/IndexOutOfBoundsException."<init>":(Ljava/lang/String;)V
	athrow
  Labels:
   	l1 = 10 // new

public int productArity();
  Signature: ()I
  Code:
   Stack=1, Locals=1, Args_size=1
	iconst_1
	ireturn
  Labels:

public java.lang.String productPrefix();
  Signature: ()Ljava/lang/String;
  Code:
   Stack=1, Locals=1, Args_size=1
	ldc	String MutableMapWrapper
	areturn
  Labels:

public scala.collection.JavaConversions$MutableMapWrapper copy(scala.collection.mutable.Map, scala.reflect.ClassManifest);
  Signature: (Lscala/collection/mutable/Map;Lscala/reflect/ClassManifest;)Lscala/collection/JavaConversions$MutableMapWrapper;
  Code:
   Stack=4, Locals=3, Args_size=3
	new	class scala/collection/JavaConversions$MutableMapWrapper
	dup
	aload_1
	aload_2
	invokespecial	Method "<init>":(Lscala/collection/mutable/Map;Lscala/reflect/ClassManifest;)V
	areturn
  Labels:
  LocalVariableTable: 
   Start  Length  Slot  Name   Signature
   0      10      0    this       Lscala/collection/JavaConversions$MutableMapWrapper;
   0      10      1    underlying       Lscala/collection/mutable/Map;
   0      10      2    m       Lscala/reflect/ClassManifest;


public java.util.Set entrySet();
  Signature: ()Ljava/util/Set;
  Code:
   Stack=3, Locals=1, Args_size=1
	new	class scala/collection/JavaConversions$MutableMapWrapper$$anon$1
	dup
	aload_0
	invokespecial	Method scala/collection/JavaConversions$MutableMapWrapper$$anon$1."<init>":(Lscala/collection/JavaConversions$MutableMapWrapper;)V
	areturn
  Labels:
  Signature: length = 0x2
   00 4B 

public java.lang.Object remove(java.lang.Object);
  Signature: (Ljava/lang/Object;)Ljava/lang/Object;
  Code:
   Stack=3, Locals=5, Args_size=2
	aload_0
	getfield	Field m:Lscala/reflect/ClassManifest;
	invokeinterface	InterfaceMethod scala/reflect/ClassManifest.erasure:()Ljava/lang/Class;
	aload_1
	invokevirtual	Method java/lang/Class.isInstance:(Ljava/lang/Object;)Z
	ifeq	l1 // aconst_null
	aload_0
	invokevirtual	Method underlying:()Lscala/collection/mutable/Map;
	aload_1
	invokeinterface	InterfaceMethod scala/collection/MapLike.get:(Ljava/lang/Object;)Lscala/Option;
	astore	4
	aload	4
	instanceof	class scala/Some
	ifeq	l2 // getstatic
	aload	4
	checkcast	class scala/Some
	astore_2
	aload_2
	getfield	Field scala/Some.x:Ljava/lang/Object;
	astore_3
	aload_0
	invokevirtual	Method underlying:()Lscala/collection/mutable/Map;
	aload_1
	invokeinterface	InterfaceMethod scala/collection/mutable/MapLike.$minus$eq:(Ljava/lang/Object;)Lscala/collection/mutable/MapLike;
	pop
	aload_3
	goto	l3 // areturn
l2	getstatic	Field scala/None$.MODULE$:Lscala/None$;
	dup
	ifnonnull	l4 // aload
	pop
	aload	4
	ifnull	l5 // aconst_null
	goto	l6 // new
l4	aload	4
	invokevirtual	Method java/lang/Object.equals:(Ljava/lang/Object;)Z
	ifeq	l6 // new
l5	aconst_null
	goto	l3 // areturn
l6	new	class scala/MatchError
	dup
	aload	4
	invokevirtual	Method scala/Option.toString:()Ljava/lang/String;
	invokespecial	Method scala/MatchError."<init>":(Ljava/lang/String;)V
	athrow
l1	aconst_null
l3	areturn
  Labels:
   	l2 = 62 // getstatic
   	l4 = 78 // aload
   	l5 = 86 // aconst_null
   	l6 = 90 // new
   	l1 = 103 // aconst_null
   	l3 = 104 // areturn
  LocalVariableTable: 
   Start  Length  Slot  Name   Signature
   0      105      0    this       Lscala/collection/JavaConversions$MutableMapWrapper;
   0      105      1    k       Ljava/lang/Object;
   42      17      2    temp79       Lscala/Some;
   47      12      3    temp80       Ljava/lang/Object;
   28      75      4    temp78       Lscala/Option;

  Signature: length = 0x2
   00 FFFFFF80 

public java.lang.Object put(java.lang.Object, java.lang.Object);
  Signature: (Ljava/lang/Object;Ljava/lang/Object;)Ljava/lang/Object;
  Code:
   Stack=3, Locals=6, Args_size=3
	aload_0
	invokevirtual	Method underlying:()Lscala/collection/mutable/Map;
	aload_1
	aload_2
	invokeinterface	InterfaceMethod scala/collection/mutable/MapLike.put:(Ljava/lang/Object;Ljava/lang/Object;)Lscala/Option;
	astore	5
	aload	5
	instanceof	class scala/Some
	ifeq	l1 // getstatic
	aload	5
	checkcast	class scala/Some
	astore_3
	aload_3
	getfield	Field scala/Some.x:Ljava/lang/Object;
	astore	4
	aload	4
	goto	l2 // areturn
l1	getstatic	Field scala/None$.MODULE$:Lscala/None$;
	dup
	ifnonnull	l3 // aload
	pop
	aload	5
	ifnull	l4 // aconst_null
	goto	l5 // new
l3	aload	5
	invokevirtual	Method java/lang/Object.equals:(Ljava/lang/Object;)Z
	ifeq	l5 // new
l4	aconst_null
l2	areturn
l5	new	class scala/MatchError
	dup
	aload	5
	invokevirtual	Method scala/Option.toString:()Ljava/lang/String;
	invokespecial	Method scala/MatchError."<init>":(Ljava/lang/String;)V
	athrow
  Labels:
   	l1 = 38 // getstatic
   	l3 = 54 // aload
   	l4 = 62 // aconst_null
   	l2 = 63 // areturn
   	l5 = 64 // new
  LocalVariableTable: 
   Start  Length  Slot  Name   Signature
   0      77      0    this       Lscala/collection/JavaConversions$MutableMapWrapper;
   0      77      1    k       Ljava/lang/Object;
   0      77      2    v       Ljava/lang/Object;
   27      8      3    temp75       Lscala/Some;
   33      2      4    temp76       Ljava/lang/Object;
   13      64      5    temp74       Lscala/Option;

  Signature: length = 0x2
   00 FFFFFF8A 

public int size();
  Signature: ()I
  Code:
   Stack=1, Locals=1, Args_size=1
	aload_0
	invokevirtual	Method underlying:()Lscala/collection/mutable/Map;
	invokeinterface	InterfaceMethod scala/collection/TraversableLike.size:()I
	ireturn
  Labels:

public scala.collection.mutable.Map underlying();
  Signature: ()Lscala/collection/mutable/Map;
  Code:
   Stack=1, Locals=1, Args_size=1
	aload_0
	getfield	Field underlying:Lscala/collection/mutable/Map;
	areturn
  Labels:
  Signature: length = 0x2
   00 FFFFFF90 

public scala.collection.mutable.Map copy$default$1();
  Signature: ()Lscala/collection/mutable/Map;
  Code:
   Stack=1, Locals=1, Args_size=1
	aload_0
	invokevirtual	Method underlying:()Lscala/collection/mutable/Map;
	areturn
  Labels:

public scala.reflect.ClassManifest copy$default$2(scala.collection.mutable.Map);
  Signature: (Lscala/collection/mutable/Map;)Lscala/reflect/ClassManifest;
  Code:
   Stack=1, Locals=2, Args_size=2
	aload_0
	getfield	Field m:Lscala/reflect/ClassManifest;
	areturn
  Labels:
  LocalVariableTable: 
   Start  Length  Slot  Name   Signature
   0      5      0    this       Lscala/collection/JavaConversions$MutableMapWrapper;
   0      5      1    underlying       Lscala/collection/mutable/Map;


public scala.collection.Iterator productElements();
  Signature: ()Lscala/collection/Iterator;
  Code:
   Stack=1, Locals=1, Args_size=1
	aload_0
	invokestatic	Method scala/Product$class.productElements:(Lscala/Product;)Lscala/collection/Iterator;
	areturn
  Labels:
  Deprecated: true

public scala.collection.Iterator productIterator();
  Signature: ()Lscala/collection/Iterator;
  Code:
   Stack=1, Locals=1, Args_size=1
	aload_0
	invokestatic	Method scala/Product$class.productIterator:(Lscala/Product;)Lscala/collection/Iterator;
	areturn
  Labels:

}

