Compiled from "JavaConversions.scala"
public class scala.collection.JavaConversions$JMapWrapper extends scala.collection.JavaConversions$JMapWrapperLike implements scala.ScalaObject,scala.Product,java.io.Serializable
  SourceFile: "JavaConversions.scala"
  Signature: length = 0x2
   00 55 
  Scala: length = 0x
   
  InnerClass: 
   public JMapWrapper=class scala/collection/JavaConversions$JMapWrapper of class scala/collection/JavaConversions
   public abstract JMapWrapperLike=class scala/collection/JavaConversions$JMapWrapperLike of class scala/collection/JavaConversions
  minor version: 0
  major version: 49
  Constant pool:
Asciz	SourceFile;
Asciz	JavaConversions.scala;
Asciz	underlying;
Asciz	Ljava/util/Map;;
Asciz	Ljava/util/Map<TA;TB;>;;
Asciz	Signature;
Asciz	productIterator;
Asciz	()Lscala/collection/Iterator;;
Asciz	Code;
Asciz	LineNumberTable;
Asciz	scala/Product$class;
class	scala/Product$class
Asciz	(Lscala/Product;)Lscala/collection/Iterator;;
NameAndType	productIterator:(Lscala/Product;)Lscala/collection/Iterator;
Method	scala/Product$class.productIterator:(Lscala/Product;)Lscala/collection/Iterator;
Asciz	productElements;
NameAndType	productElements:(Lscala/Product;)Lscala/collection/Iterator;
Method	scala/Product$class.productElements:(Lscala/Product;)Lscala/collection/Iterator;
Asciz	Deprecated;
Asciz	copy$default$1;
Asciz	()Ljava/util/Map;;
Asciz	scala/collection/JavaConversions$JMapWrapper;
class	scala/collection/JavaConversions$JMapWrapper
NameAndType	underlying:()Ljava/util/Map;
Method	scala/collection/JavaConversions$JMapWrapper.underlying:()Ljava/util/Map;
NameAndType	underlying:Ljava/util/Map;
Field	scala/collection/JavaConversions$JMapWrapper.underlying:Ljava/util/Map;
Asciz	()Ljava/util/Map<TA;TB;>;;
Asciz	empty;
Asciz	()Lscala/collection/JavaConversions$JMapWrapper;;
Asciz	java/util/HashMap;
class	java/util/HashMap
Asciz	<init>;
Asciz	()V;
NameAndType	"<init>":()V
Method	java/util/HashMap."<init>":()V
Asciz	(Ljava/util/Map;)V;
NameAndType	"<init>":(Ljava/util/Map;)V
Method	scala/collection/JavaConversions$JMapWrapper."<init>":(Ljava/util/Map;)V
Asciz	()Lscala/collection/JavaConversions$JMapWrapper<TA;TB;>;;
Asciz	copy;
Asciz	(Ljava/util/Map;)Lscala/collection/JavaConversions$JMapWrapper;;
Asciz	this;
Asciz	Lscala/collection/JavaConversions$JMapWrapper;;
Asciz	LocalVariableTable;
Asciz	productPrefix;
Asciz	()Ljava/lang/String;;
Asciz	JMapWrapper;
String	JMapWrapper
Asciz	productArity;
Asciz	()I;
Asciz	productElement;
Asciz	(I)Ljava/lang/Object;;
Asciz	java/lang/IndexOutOfBoundsException;
class	java/lang/IndexOutOfBoundsException
Asciz	scala/runtime/BoxesRunTime;
class	scala/runtime/BoxesRunTime
Asciz	boxToInteger;
Asciz	(I)Ljava/lang/Integer;;
NameAndType	boxToInteger:(I)Ljava/lang/Integer;
Method	scala/runtime/BoxesRunTime.boxToInteger:(I)Ljava/lang/Integer;
Asciz	java/lang/Object;
class	java/lang/Object
Asciz	toString;
NameAndType	toString:()Ljava/lang/String;
Method	java/lang/Object.toString:()Ljava/lang/String;
Asciz	(Ljava/lang/String;)V;
NameAndType	"<init>":(Ljava/lang/String;)V
Method	java/lang/IndexOutOfBoundsException."<init>":(Ljava/lang/String;)V
Asciz	productElementName;
Asciz	(I)Ljava/lang/String;;
String	underlying
Asciz	()Lscala/collection/Map;;
NameAndType	empty:()Lscala/collection/JavaConversions$JMapWrapper;
Method	scala/collection/JavaConversions$JMapWrapper.empty:()Lscala/collection/JavaConversions$JMapWrapper;
Asciz	()Lscala/collection/mutable/Map;;
Asciz	scala/collection/JavaConversions$JMapWrapperLike;
class	scala/collection/JavaConversions$JMapWrapperLike
Method	scala/collection/JavaConversions$JMapWrapperLike."<init>":(Ljava/util/Map;)V
Asciz	$init$;
Asciz	(Lscala/Product;)V;
NameAndType	$init$:(Lscala/Product;)V
Method	scala/Product$class.$init$:(Lscala/Product;)V
Asciz	(Ljava/util/Map<TA;TB;>;)V;
Asciz	<A:Ljava/lang/Object;B:Ljava/lang/Object;>Lscala/collection/JavaConversions$JMapWrapperLike<TA;TB;Lscala/collection/JavaConversions$JMapWrapper<TA;TB;>;>;Lscala/ScalaObject;Lscala/Product;;
Asciz	Scala;
Asciz	InnerClasses;
Asciz	scala/collection/JavaConversions;
class	scala/collection/JavaConversions
Asciz	JMapWrapperLike;
Asciz	scala/ScalaObject;
class	scala/ScalaObject
Asciz	scala/Product;
class	scala/Product
Asciz	java/io/Serializable;
class	java/io/Serializable

{
private final java.util.Map underlying;
  Signature: Ljava/util/Map;
  Signature: length = 0x2
   00 05 

public scala.collection.Iterator productIterator();
  Signature: ()Lscala/collection/Iterator;
  Code:
   Stack=1, Locals=1, Args_size=1
	aload_0
	invokestatic	Method scala/Product$class.productIterator:(Lscala/Product;)Lscala/collection/Iterator;
	areturn
  Labels:

public scala.collection.Iterator productElements();
  Signature: ()Lscala/collection/Iterator;
  Code:
   Stack=1, Locals=1, Args_size=1
	aload_0
	invokestatic	Method scala/Product$class.productElements:(Lscala/Product;)Lscala/collection/Iterator;
	areturn
  Labels:
  Deprecated: true

public java.util.Map copy$default$1();
  Signature: ()Ljava/util/Map;
  Code:
   Stack=1, Locals=1, Args_size=1
	aload_0
	invokevirtual	Method underlying:()Ljava/util/Map;
	areturn
  Labels:

public java.util.Map underlying();
  Signature: ()Ljava/util/Map;
  Code:
   Stack=1, Locals=1, Args_size=1
	aload_0
	getfield	Field underlying:Ljava/util/Map;
	areturn
  Labels:
  Signature: length = 0x2
   00 1C 

public scala.collection.JavaConversions$JMapWrapper empty();
  Signature: ()Lscala/collection/JavaConversions$JMapWrapper;
  Code:
   Stack=4, Locals=1, Args_size=1
	new	class scala/collection/JavaConversions$JMapWrapper
	dup
	new	class java/util/HashMap
	dup
	invokespecial	Method java/util/HashMap."<init>":()V
	invokespecial	Method "<init>":(Ljava/util/Map;)V
	areturn
  Labels:
  Signature: length = 0x2
   00 28 

public scala.collection.JavaConversions$JMapWrapper copy(java.util.Map);
  Signature: (Ljava/util/Map;)Lscala/collection/JavaConversions$JMapWrapper;
  Code:
   Stack=3, Locals=2, Args_size=2
	new	class scala/collection/JavaConversions$JMapWrapper
	dup
	aload_1
	invokespecial	Method "<init>":(Ljava/util/Map;)V
	areturn
  Labels:
  LocalVariableTable: 
   Start  Length  Slot  Name   Signature
   0      9      0    this       Lscala/collection/JavaConversions$JMapWrapper;
   0      9      1    underlying       Ljava/util/Map;


public java.lang.String productPrefix();
  Signature: ()Ljava/lang/String;
  Code:
   Stack=1, Locals=1, Args_size=1
	ldc	String JMapWrapper
	areturn
  Labels:

public int productArity();
  Signature: ()I
  Code:
   Stack=1, Locals=1, Args_size=1
	iconst_1
	ireturn
  Labels:

public java.lang.Object productElement(int);
  Signature: (I)Ljava/lang/Object;
  Code:
   Stack=3, Locals=2, Args_size=2
	iload_1
	iconst_0
	if_icmpne	l1 // new
	aload_0
	invokevirtual	Method underlying:()Ljava/util/Map;
	areturn
l1	new	class java/lang/IndexOutOfBoundsException
	dup
	iload_1
	invokestatic	Method scala/runtime/BoxesRunTime.boxToInteger:(I)Ljava/lang/Integer;
	invokevirtual	Method java/lang/Object.toString:()Ljava/lang/String;
	invokespecial	Method java/lang/IndexOutOfBoundsException."<init>":(Ljava/lang/String;)V
	athrow
  Labels:
   	l1 = 10 // new

public java.lang.String productElementName(int);
  Signature: (I)Ljava/lang/String;
  Code:
   Stack=3, Locals=2, Args_size=2
	iload_1
	iconst_0
	if_icmpne	l1 // new
	ldc	String underlying
	areturn
l1	new	class java/lang/IndexOutOfBoundsException
	dup
	iload_1
	invokestatic	Method scala/runtime/BoxesRunTime.boxToInteger:(I)Ljava/lang/Integer;
	invokevirtual	Method java/lang/Object.toString:()Ljava/lang/String;
	invokespecial	Method java/lang/IndexOutOfBoundsException."<init>":(Ljava/lang/String;)V
	athrow
  Labels:
   	l1 = 8 // new

public scala.collection.Map empty();
  Signature: ()Lscala/collection/Map;
  Code:
   Stack=1, Locals=1, Args_size=1
	aload_0
	invokevirtual	Method empty:()Lscala/collection/JavaConversions$JMapWrapper;
	areturn
  Labels:

public scala.collection.mutable.Map empty();
  Signature: ()Lscala/collection/mutable/Map;
  Code:
   Stack=1, Locals=1, Args_size=1
	aload_0
	invokevirtual	Method empty:()Lscala/collection/JavaConversions$JMapWrapper;
	areturn
  Labels:

public scala.collection.JavaConversions$JMapWrapper(java.util.Map);
  Signature: (Ljava/util/Map;)V
  Code:
   Stack=2, Locals=2, Args_size=2
	aload_0
	aload_1
	putfield	Field underlying:Ljava/util/Map;
	aload_0
	aload_1
	invokespecial	Method scala/collection/JavaConversions$JMapWrapperLike."<init>":(Ljava/util/Map;)V
	aload_0
	invokestatic	Method scala/Product$class.$init$:(Lscala/Product;)V
	return
  Labels:
  LocalVariableTable: 
   Start  Length  Slot  Name   Signature
   0      15      0    this       Lscala/collection/JavaConversions$JMapWrapper;
   0      15      1    underlying       Ljava/util/Map;

  Signature: length = 0x2
   00 54 

}

