Compiled from "JavaConversions.scala"
public final class scala.collection.JavaConversions$JIteratorWrapper$ extends java.lang.Object implements scala.ScalaObject
  SourceFile: "JavaConversions.scala"
  Scala: length = 0x
   
  InnerClass: 
   public JIteratorWrapper=class scala/collection/JavaConversions$JIteratorWrapper of class scala/collection/JavaConversions
  minor version: 0
  major version: 49
  Constant pool:
Asciz	SourceFile;
Asciz	JavaConversions.scala;
Asciz	Scala;
Asciz	MODULE$;
Asciz	Lscala/collection/JavaConversions$JIteratorWrapper$;;
Asciz	<clinit>;
Asciz	()V;
Asciz	Code;
Asciz	scala/collection/JavaConversions$JIteratorWrapper$;
class	scala/collection/JavaConversions$JIteratorWrapper$
Asciz	<init>;
NameAndType	"<init>":()V
Method	scala/collection/JavaConversions$JIteratorWrapper$."<init>":()V
Asciz	unapply;
Asciz	(Lscala/collection/JavaConversions$JIteratorWrapper;)Lscala/Option;;
Asciz	LineNumberTable;
Asciz	java/lang/Object;
class	java/lang/Object
Asciz	equals;
Asciz	(Ljava/lang/Object;)Z;
NameAndType	equals:(Ljava/lang/Object;)Z
Method	java/lang/Object.equals:(Ljava/lang/Object;)Z
Asciz	scala/None$;
class	scala/None$
Asciz	Lscala/None$;;
NameAndType	MODULE$:Lscala/None$;
Field	scala/None$.MODULE$:Lscala/None$;
Asciz	scala/Some;
class	scala/Some
Asciz	scala/collection/JavaConversions$JIteratorWrapper;
class	scala/collection/JavaConversions$JIteratorWrapper
Asciz	underlying;
Asciz	()Ljava/util/Iterator;;
NameAndType	underlying:()Ljava/util/Iterator;
Method	scala/collection/JavaConversions$JIteratorWrapper.underlying:()Ljava/util/Iterator;
Asciz	(Ljava/lang/Object;)V;
NameAndType	"<init>":(Ljava/lang/Object;)V
Method	scala/Some."<init>":(Ljava/lang/Object;)V
Asciz	this;
Asciz	x$0;
Asciz	Lscala/collection/JavaConversions$JIteratorWrapper;;
Asciz	LocalVariableTable;
Asciz	apply;
Asciz	(Ljava/util/Iterator;)Lscala/collection/JavaConversions$JIteratorWrapper;;
Asciz	(Ljava/util/Iterator;)V;
NameAndType	"<init>":(Ljava/util/Iterator;)V
Method	scala/collection/JavaConversions$JIteratorWrapper."<init>":(Ljava/util/Iterator;)V
Asciz	Ljava/util/Iterator;;
Method	java/lang/Object."<init>":()V
NameAndType	MODULE$:Lscala/collection/JavaConversions$JIteratorWrapper$;
Field	scala/collection/JavaConversions$JIteratorWrapper$.MODULE$:Lscala/collection/JavaConversions$JIteratorWrapper$;
Asciz	InnerClasses;
Asciz	scala/collection/JavaConversions;
class	scala/collection/JavaConversions
Asciz	JIteratorWrapper;
Asciz	scala/ScalaObject;
class	scala/ScalaObject

{
public static final scala.collection.JavaConversions$JIteratorWrapper$ MODULE$;
  Signature: Lscala/collection/JavaConversions$JIteratorWrapper$;

public static {};
  Signature: ()V
  Code:
   Stack=1, Locals=0, Args_size=0
	new	class scala/collection/JavaConversions$JIteratorWrapper$
	invokespecial	Method "<init>":()V
	return
  Labels:

public scala.Option unapply(scala.collection.JavaConversions$JIteratorWrapper);
  Signature: (Lscala/collection/JavaConversions$JIteratorWrapper;)Lscala/Option;
  Code:
   Stack=3, Locals=3, Args_size=2
	aload_1
	dup
	astore_2
	ifnull	l1 // getstatic
	aload_2
	aconst_null
	invokevirtual	Method java/lang/Object.equals:(Ljava/lang/Object;)Z
	ifeq	l2 // new
l1	getstatic	Field scala/None$.MODULE$:Lscala/None$;
	goto	l3 // areturn
l2	new	class scala/Some
	dup
	aload_1
	invokevirtual	Method scala/collection/JavaConversions$JIteratorWrapper.underlying:()Ljava/util/Iterator;
	invokespecial	Method scala/Some."<init>":(Ljava/lang/Object;)V
l3	areturn
  Labels:
   	l1 = 14 // getstatic
   	l2 = 20 // new
   	l3 = 31 // areturn
  LocalVariableTable: 
   Start  Length  Slot  Name   Signature
   0      32      0    this       Lscala/collection/JavaConversions$JIteratorWrapper$;
   0      32      1    x$0       Lscala/collection/JavaConversions$JIteratorWrapper;


public scala.collection.JavaConversions$JIteratorWrapper apply(java.util.Iterator);
  Signature: (Ljava/util/Iterator;)Lscala/collection/JavaConversions$JIteratorWrapper;
  Code:
   Stack=3, Locals=2, Args_size=2
	new	class scala/collection/JavaConversions$JIteratorWrapper
	dup
	aload_1
	invokespecial	Method scala/collection/JavaConversions$JIteratorWrapper."<init>":(Ljava/util/Iterator;)V
	areturn
  Labels:
  LocalVariableTable: 
   Start  Length  Slot  Name   Signature
   0      9      0    this       Lscala/collection/JavaConversions$JIteratorWrapper$;
   0      9      1    underlying       Ljava/util/Iterator;


public scala.collection.JavaConversions$JIteratorWrapper$();
  Signature: ()V
  Code:
   Stack=1, Locals=1, Args_size=1
	aload_0
	invokespecial	Method java/lang/Object."<init>":()V
	aload_0
	putstatic	Field MODULE$:Lscala/collection/JavaConversions$JIteratorWrapper$;
	return
  Labels:

}

