Compiled from "JavaConversions.scala"
public final class scala.collection.JavaConversions$JPropertiesWrapper$ extends java.lang.Object implements scala.Function1,scala.ScalaObject
  SourceFile: "JavaConversions.scala"
  Scala: length = 0x
   
  InnerClass: 
   public JPropertiesWrapper=class scala/collection/JavaConversions$JPropertiesWrapper of class scala/collection/JavaConversions
   public final $anon$3=class scala/collection/JavaConversions$JPropertiesWrapper$$anon$3 of class scala/collection/JavaConversions$JPropertiesWrapper
  minor version: 0
  major version: 49
  Constant pool:
Asciz	SourceFile;
Asciz	JavaConversions.scala;
Asciz	Scala;
Asciz	MODULE$;
Asciz	Lscala/collection/JavaConversions$JPropertiesWrapper$;;
Asciz	<clinit>;
Asciz	()V;
Asciz	Code;
Asciz	scala/collection/JavaConversions$JPropertiesWrapper$;
class	scala/collection/JavaConversions$JPropertiesWrapper$
Asciz	<init>;
NameAndType	"<init>":()V
Method	scala/collection/JavaConversions$JPropertiesWrapper$."<init>":()V
Asciz	toString;
Asciz	()Ljava/lang/String;;
Asciz	LineNumberTable;
Asciz	scala/Function1$class;
class	scala/Function1$class
Asciz	(Lscala/Function1;)Ljava/lang/String;;
NameAndType	toString:(Lscala/Function1;)Ljava/lang/String;
Method	scala/Function1$class.toString:(Lscala/Function1;)Ljava/lang/String;
Asciz	compose;
Asciz	(Lscala/Function1;)Lscala/Function1;;
Asciz	(Lscala/Function1;Lscala/Function1;)Lscala/Function1;;
NameAndType	compose:(Lscala/Function1;Lscala/Function1;)Lscala/Function1;
Method	scala/Function1$class.compose:(Lscala/Function1;Lscala/Function1;)Lscala/Function1;
Asciz	this;
Asciz	g;
Asciz	Lscala/Function1;;
Asciz	LocalVariableTable;
Asciz	andThen;
NameAndType	andThen:(Lscala/Function1;Lscala/Function1;)Lscala/Function1;
Method	scala/Function1$class.andThen:(Lscala/Function1;Lscala/Function1;)Lscala/Function1;
Asciz	unapply;
Asciz	(Lscala/collection/JavaConversions$JPropertiesWrapper;)Lscala/Some;;
Asciz	scala/Some;
class	scala/Some
Asciz	scala/collection/JavaConversions$JPropertiesWrapper;
class	scala/collection/JavaConversions$JPropertiesWrapper
Asciz	underlying;
Asciz	()Ljava/util/Properties;;
NameAndType	underlying:()Ljava/util/Properties;
Method	scala/collection/JavaConversions$JPropertiesWrapper.underlying:()Ljava/util/Properties;
Asciz	(Ljava/lang/Object;)V;
NameAndType	"<init>":(Ljava/lang/Object;)V
Method	scala/Some."<init>":(Ljava/lang/Object;)V
Asciz	x$0;
Asciz	Lscala/collection/JavaConversions$JPropertiesWrapper;;
Asciz	apply;
Asciz	(Ljava/util/Properties;)Lscala/collection/JavaConversions$JPropertiesWrapper;;
Asciz	(Ljava/util/Properties;)V;
NameAndType	"<init>":(Ljava/util/Properties;)V
Method	scala/collection/JavaConversions$JPropertiesWrapper."<init>":(Ljava/util/Properties;)V
Asciz	Ljava/util/Properties;;
Asciz	(Ljava/lang/Object;)Ljava/lang/Object;;
Asciz	java/util/Properties;
class	java/util/Properties
NameAndType	apply:(Ljava/util/Properties;)Lscala/collection/JavaConversions$JPropertiesWrapper;
Method	scala/collection/JavaConversions$JPropertiesWrapper$.apply:(Ljava/util/Properties;)Lscala/collection/JavaConversions$JPropertiesWrapper;
Asciz	v1;
Asciz	Ljava/lang/Object;;
Asciz	java/lang/Object;
class	java/lang/Object
Method	java/lang/Object."<init>":()V
NameAndType	MODULE$:Lscala/collection/JavaConversions$JPropertiesWrapper$;
Field	scala/collection/JavaConversions$JPropertiesWrapper$.MODULE$:Lscala/collection/JavaConversions$JPropertiesWrapper$;
Asciz	$init$;
Asciz	(Lscala/Function1;)V;
NameAndType	$init$:(Lscala/Function1;)V
Method	scala/Function1$class.$init$:(Lscala/Function1;)V
Asciz	InnerClasses;
Asciz	scala/collection/JavaConversions;
class	scala/collection/JavaConversions
Asciz	JPropertiesWrapper;
Asciz	scala/collection/JavaConversions$JPropertiesWrapper$$anon$3;
class	scala/collection/JavaConversions$JPropertiesWrapper$$anon$3
Asciz	$anon$3;
Asciz	scala/Function1;
class	scala/Function1
Asciz	scala/ScalaObject;
class	scala/ScalaObject

{
public static final scala.collection.JavaConversions$JPropertiesWrapper$ MODULE$;
  Signature: Lscala/collection/JavaConversions$JPropertiesWrapper$;

public static {};
  Signature: ()V
  Code:
   Stack=1, Locals=0, Args_size=0
	new	class scala/collection/JavaConversions$JPropertiesWrapper$
	invokespecial	Method "<init>":()V
	return
  Labels:

public java.lang.String toString();
  Signature: ()Ljava/lang/String;
  Code:
   Stack=1, Locals=1, Args_size=1
	aload_0
	invokestatic	Method scala/Function1$class.toString:(Lscala/Function1;)Ljava/lang/String;
	areturn
  Labels:

public scala.Function1 compose(scala.Function1);
  Signature: (Lscala/Function1;)Lscala/Function1;
  Code:
   Stack=2, Locals=2, Args_size=2
	aload_0
	aload_1
	invokestatic	Method scala/Function1$class.compose:(Lscala/Function1;Lscala/Function1;)Lscala/Function1;
	areturn
  Labels:
  LocalVariableTable: 
   Start  Length  Slot  Name   Signature
   0      6      0    this       Lscala/collection/JavaConversions$JPropertiesWrapper$;
   0      6      1    g       Lscala/Function1;


public scala.Function1 andThen(scala.Function1);
  Signature: (Lscala/Function1;)Lscala/Function1;
  Code:
   Stack=2, Locals=2, Args_size=2
	aload_0
	aload_1
	invokestatic	Method scala/Function1$class.andThen:(Lscala/Function1;Lscala/Function1;)Lscala/Function1;
	areturn
  Labels:
  LocalVariableTable: 
   Start  Length  Slot  Name   Signature
   0      6      0    this       Lscala/collection/JavaConversions$JPropertiesWrapper$;
   0      6      1    g       Lscala/Function1;


public scala.Some unapply(scala.collection.JavaConversions$JPropertiesWrapper);
  Signature: (Lscala/collection/JavaConversions$JPropertiesWrapper;)Lscala/Some;
  Code:
   Stack=3, Locals=2, Args_size=2
	new	class scala/Some
	dup
	aload_1
	invokevirtual	Method scala/collection/JavaConversions$JPropertiesWrapper.underlying:()Ljava/util/Properties;
	invokespecial	Method scala/Some."<init>":(Ljava/lang/Object;)V
	areturn
  Labels:
  LocalVariableTable: 
   Start  Length  Slot  Name   Signature
   0      12      0    this       Lscala/collection/JavaConversions$JPropertiesWrapper$;
   0      12      1    x$0       Lscala/collection/JavaConversions$JPropertiesWrapper;


public scala.collection.JavaConversions$JPropertiesWrapper apply(java.util.Properties);
  Signature: (Ljava/util/Properties;)Lscala/collection/JavaConversions$JPropertiesWrapper;
  Code:
   Stack=3, Locals=2, Args_size=2
	new	class scala/collection/JavaConversions$JPropertiesWrapper
	dup
	aload_1
	invokespecial	Method scala/collection/JavaConversions$JPropertiesWrapper."<init>":(Ljava/util/Properties;)V
	areturn
  Labels:
  LocalVariableTable: 
   Start  Length  Slot  Name   Signature
   0      9      0    this       Lscala/collection/JavaConversions$JPropertiesWrapper$;
   0      9      1    underlying       Ljava/util/Properties;


public java.lang.Object apply(java.lang.Object);
  Signature: (Ljava/lang/Object;)Ljava/lang/Object;
  Code:
   Stack=2, Locals=2, Args_size=2
	aload_0
	aload_1
	checkcast	class java/util/Properties
	invokevirtual	Method apply:(Ljava/util/Properties;)Lscala/collection/JavaConversions$JPropertiesWrapper;
	areturn
  Labels:
  LocalVariableTable: 
   Start  Length  Slot  Name   Signature
   0      9      0    this       Lscala/collection/JavaConversions$JPropertiesWrapper$;
   0      9      1    v1       Ljava/lang/Object;


public scala.collection.JavaConversions$JPropertiesWrapper$();
  Signature: ()V
  Code:
   Stack=1, Locals=1, Args_size=1
	aload_0
	invokespecial	Method java/lang/Object."<init>":()V
	aload_0
	putstatic	Field MODULE$:Lscala/collection/JavaConversions$JPropertiesWrapper$;
	aload_0
	invokestatic	Method scala/Function1$class.$init$:(Lscala/Function1;)V
	return
  Labels:

}

