Compiled from "JavaConversions.scala"
public class scala.collection.JavaConversions$IterableWrapper extends java.util.AbstractCollection implements scala.ScalaObject,scala.Product,java.io.Serializable
  SourceFile: "JavaConversions.scala"
  Signature: length = 0x2
   00 FFFFFF84 
  Scala: length = 0x
   
  InnerClass: 
   public IterableWrapper=class scala/collection/JavaConversions$IterableWrapper of class scala/collection/JavaConversions
  minor version: 0
  major version: 49
  Constant pool:
Asciz	SourceFile;
Asciz	JavaConversions.scala;
Asciz	underlying;
Asciz	Lscala/collection/Iterable;;
Asciz	Lscala/collection/Iterable<TA;>;;
Asciz	Signature;
Asciz	productIterator;
Asciz	()Lscala/collection/Iterator;;
Asciz	Code;
Asciz	LineNumberTable;
Asciz	scala/Product$class;
class	scala/Product$class
Asciz	(Lscala/Product;)Lscala/collection/Iterator;;
NameAndType	productIterator:(Lscala/Product;)Lscala/collection/Iterator;
Method	scala/Product$class.productIterator:(Lscala/Product;)Lscala/collection/Iterator;
Asciz	productElements;
NameAndType	productElements:(Lscala/Product;)Lscala/collection/Iterator;
Method	scala/Product$class.productElements:(Lscala/Product;)Lscala/collection/Iterator;
Asciz	Deprecated;
Asciz	copy$default$1;
Asciz	()Lscala/collection/Iterable;;
Asciz	scala/collection/JavaConversions$IterableWrapper;
class	scala/collection/JavaConversions$IterableWrapper
NameAndType	underlying:()Lscala/collection/Iterable;
Method	scala/collection/JavaConversions$IterableWrapper.underlying:()Lscala/collection/Iterable;
NameAndType	underlying:Lscala/collection/Iterable;
Field	scala/collection/JavaConversions$IterableWrapper.underlying:Lscala/collection/Iterable;
Asciz	()Lscala/collection/Iterable<TA;>;;
Asciz	iterator;
Asciz	()Ljava/util/Iterator;;
Asciz	scala/collection/JavaConversions$;
class	scala/collection/JavaConversions$
Asciz	MODULE$;
Asciz	Lscala/collection/JavaConversions$;;
NameAndType	MODULE$:Lscala/collection/JavaConversions$;
Field	scala/collection/JavaConversions$.MODULE$:Lscala/collection/JavaConversions$;
Asciz	scala/collection/IterableLike;
class	scala/collection/IterableLike
NameAndType	iterator:()Lscala/collection/Iterator;
InterfaceMethod	scala/collection/IterableLike.iterator:()Lscala/collection/Iterator;
Asciz	asIterator;
Asciz	(Lscala/collection/Iterator;)Ljava/util/Iterator;;
NameAndType	asIterator:(Lscala/collection/Iterator;)Ljava/util/Iterator;
Method	scala/collection/JavaConversions$.asIterator:(Lscala/collection/Iterator;)Ljava/util/Iterator;
Asciz	()Ljava/util/Iterator<TA;>;;
Asciz	size;
Asciz	()I;
Asciz	scala/collection/TraversableLike;
class	scala/collection/TraversableLike
NameAndType	size:()I
InterfaceMethod	scala/collection/TraversableLike.size:()I
Asciz	isEmpty;
Asciz	()Z;
NameAndType	isEmpty:()Z
InterfaceMethod	scala/collection/IterableLike.isEmpty:()Z
Asciz	copy;
Asciz	(Lscala/collection/Iterable;)Lscala/collection/JavaConversions$IterableWrapper;;
Asciz	<init>;
Asciz	(Lscala/collection/Iterable;)V;
NameAndType	"<init>":(Lscala/collection/Iterable;)V
Method	scala/collection/JavaConversions$IterableWrapper."<init>":(Lscala/collection/Iterable;)V
Asciz	this;
Asciz	Lscala/collection/JavaConversions$IterableWrapper;;
Asciz	LocalVariableTable;
Asciz	hashCode;
Asciz	scala/runtime/ScalaRunTime$;
class	scala/runtime/ScalaRunTime$
Asciz	Lscala/runtime/ScalaRunTime$;;
NameAndType	MODULE$:Lscala/runtime/ScalaRunTime$;
Field	scala/runtime/ScalaRunTime$.MODULE$:Lscala/runtime/ScalaRunTime$;
Asciz	_hashCode;
Asciz	(Lscala/Product;)I;
NameAndType	_hashCode:(Lscala/Product;)I
Method	scala/runtime/ScalaRunTime$._hashCode:(Lscala/Product;)I
Asciz	equals;
Asciz	(Ljava/lang/Object;)Z;
Asciz	gd4$1;
Asciz	(Lscala/collection/Iterable;)Z;
NameAndType	gd4$1:(Lscala/collection/Iterable;)Z
Method	scala/collection/JavaConversions$IterableWrapper.gd4$1:(Lscala/collection/Iterable;)Z
Asciz	scala/Equals;
class	scala/Equals
Asciz	canEqual;
NameAndType	canEqual:(Ljava/lang/Object;)Z
InterfaceMethod	scala/Equals.canEqual:(Ljava/lang/Object;)Z
Asciz	temp65;
Asciz	Ljava/lang/Object;;
Asciz	temp66;
Asciz	temp67;
Asciz	underlying$4;
Asciz	productPrefix;
Asciz	()Ljava/lang/String;;
Asciz	IterableWrapper;
String	IterableWrapper
Asciz	productArity;
Asciz	productElement;
Asciz	(I)Ljava/lang/Object;;
Asciz	java/lang/IndexOutOfBoundsException;
class	java/lang/IndexOutOfBoundsException
Asciz	scala/runtime/BoxesRunTime;
class	scala/runtime/BoxesRunTime
Asciz	boxToInteger;
Asciz	(I)Ljava/lang/Integer;;
NameAndType	boxToInteger:(I)Ljava/lang/Integer;
Method	scala/runtime/BoxesRunTime.boxToInteger:(I)Ljava/lang/Integer;
Asciz	java/lang/Object;
class	java/lang/Object
Asciz	toString;
NameAndType	toString:()Ljava/lang/String;
Method	java/lang/Object.toString:()Ljava/lang/String;
Asciz	(Ljava/lang/String;)V;
NameAndType	"<init>":(Ljava/lang/String;)V
Method	java/lang/IndexOutOfBoundsException."<init>":(Ljava/lang/String;)V
Asciz	temp68;
Asciz	I;
Asciz	productElementName;
Asciz	(I)Ljava/lang/String;;
String	underlying
Asciz	temp69;
NameAndType	equals:(Ljava/lang/Object;)Z
Method	java/lang/Object.equals:(Ljava/lang/Object;)Z
Asciz	java/util/AbstractCollection;
class	java/util/AbstractCollection
Asciz	()V;
NameAndType	"<init>":()V
Method	java/util/AbstractCollection."<init>":()V
Asciz	$init$;
Asciz	(Lscala/Product;)V;
NameAndType	$init$:(Lscala/Product;)V
Method	scala/Product$class.$init$:(Lscala/Product;)V
Asciz	(Lscala/collection/Iterable<TA;>;)V;
Asciz	<A:Ljava/lang/Object;>Ljava/util/AbstractCollection<TA;>;Lscala/ScalaObject;Lscala/Product;;
Asciz	Scala;
Asciz	InnerClasses;
Asciz	scala/collection/JavaConversions;
class	scala/collection/JavaConversions
Asciz	scala/ScalaObject;
class	scala/ScalaObject
Asciz	scala/Product;
class	scala/Product
Asciz	java/io/Serializable;
class	java/io/Serializable

{
private final scala.collection.Iterable underlying;
  Signature: Lscala/collection/Iterable;
  Signature: length = 0x2
   00 05 

public scala.collection.Iterator productIterator();
  Signature: ()Lscala/collection/Iterator;
  Code:
   Stack=1, Locals=1, Args_size=1
	aload_0
	invokestatic	Method scala/Product$class.productIterator:(Lscala/Product;)Lscala/collection/Iterator;
	areturn
  Labels:

public scala.collection.Iterator productElements();
  Signature: ()Lscala/collection/Iterator;
  Code:
   Stack=1, Locals=1, Args_size=1
	aload_0
	invokestatic	Method scala/Product$class.productElements:(Lscala/Product;)Lscala/collection/Iterator;
	areturn
  Labels:
  Deprecated: true

public scala.collection.Iterable copy$default$1();
  Signature: ()Lscala/collection/Iterable;
  Code:
   Stack=1, Locals=1, Args_size=1
	aload_0
	invokevirtual	Method underlying:()Lscala/collection/Iterable;
	areturn
  Labels:

public scala.collection.Iterable underlying();
  Signature: ()Lscala/collection/Iterable;
  Code:
   Stack=1, Locals=1, Args_size=1
	aload_0
	getfield	Field underlying:Lscala/collection/Iterable;
	areturn
  Labels:
  Signature: length = 0x2
   00 1C 

public java.util.Iterator iterator();
  Signature: ()Ljava/util/Iterator;
  Code:
   Stack=2, Locals=1, Args_size=1
	getstatic	Field scala/collection/JavaConversions$.MODULE$:Lscala/collection/JavaConversions$;
	aload_0
	invokevirtual	Method underlying:()Lscala/collection/Iterable;
	invokeinterface	InterfaceMethod scala/collection/IterableLike.iterator:()Lscala/collection/Iterator;
	invokevirtual	Method scala/collection/JavaConversions$.asIterator:(Lscala/collection/Iterator;)Ljava/util/Iterator;
	areturn
  Labels:
  Signature: length = 0x2
   00 2D 

public int size();
  Signature: ()I
  Code:
   Stack=1, Locals=1, Args_size=1
	aload_0
	invokevirtual	Method underlying:()Lscala/collection/Iterable;
	invokeinterface	InterfaceMethod scala/collection/TraversableLike.size:()I
	ireturn
  Labels:

public boolean isEmpty();
  Signature: ()Z
  Code:
   Stack=1, Locals=1, Args_size=1
	aload_0
	invokevirtual	Method underlying:()Lscala/collection/Iterable;
	invokeinterface	InterfaceMethod scala/collection/IterableLike.isEmpty:()Z
	ireturn
  Labels:

public scala.collection.JavaConversions$IterableWrapper copy(scala.collection.Iterable);
  Signature: (Lscala/collection/Iterable;)Lscala/collection/JavaConversions$IterableWrapper;
  Code:
   Stack=3, Locals=2, Args_size=2
	new	class scala/collection/JavaConversions$IterableWrapper
	dup
	aload_1
	invokespecial	Method "<init>":(Lscala/collection/Iterable;)V
	areturn
  Labels:
  LocalVariableTable: 
   Start  Length  Slot  Name   Signature
   0      9      0    this       Lscala/collection/JavaConversions$IterableWrapper;
   0      9      1    underlying       Lscala/collection/Iterable;


public int hashCode();
  Signature: ()I
  Code:
   Stack=2, Locals=1, Args_size=1
	getstatic	Field scala/runtime/ScalaRunTime$.MODULE$:Lscala/runtime/ScalaRunTime$;
	aload_0
	invokevirtual	Method scala/runtime/ScalaRunTime$._hashCode:(Lscala/Product;)I
	ireturn
  Labels:

public boolean equals(java.lang.Object);
  Signature: (Ljava/lang/Object;)Z
  Code:
   Stack=2, Locals=6, Args_size=2
	aload_0
	aload_1
	if_acmpeq	l1 // iconst_1
	aload_1
	astore_2
	aload_2
	instanceof	class scala/collection/JavaConversions$IterableWrapper
	ifeq	l2 // iconst_0
	aload_2
	checkcast	class scala/collection/JavaConversions$IterableWrapper
	astore_3
	aload_3
	invokevirtual	Method underlying:()Lscala/collection/Iterable;
	astore	4
	aload	4
	astore	5
	aload_0
	aload	5
	invokespecial	Method gd4$1:(Lscala/collection/Iterable;)Z
	ifeq	l3 // iconst_0
	aload_1
	checkcast	class scala/collection/JavaConversions$IterableWrapper
	aload_0
	invokeinterface	InterfaceMethod scala/Equals.canEqual:(Ljava/lang/Object;)Z
	goto	l4 // ifeq
l3	iconst_0
	goto	l4 // ifeq
l2	iconst_0
l4	ifeq	l5 // iconst_0
l1	iconst_1
	goto	l6 // ireturn
l5	iconst_0
l6	ireturn
  Labels:
   	l3 = 51 // iconst_0
   	l2 = 55 // iconst_0
   	l4 = 56 // ifeq
   	l1 = 59 // iconst_1
   	l5 = 63 // iconst_0
   	l6 = 64 // ireturn
  LocalVariableTable: 
   Start  Length  Slot  Name   Signature
   0      65      0    this       Lscala/collection/JavaConversions$IterableWrapper;
   7      52      2    temp65       Ljava/lang/Object;
   19      36      3    temp66       Lscala/collection/JavaConversions$IterableWrapper;
   25      30      4    temp67       Lscala/collection/Iterable;
   29      26      5    underlying$4       Lscala/collection/Iterable;


public java.lang.String productPrefix();
  Signature: ()Ljava/lang/String;
  Code:
   Stack=1, Locals=1, Args_size=1
	ldc	String IterableWrapper
	areturn
  Labels:

public int productArity();
  Signature: ()I
  Code:
   Stack=1, Locals=1, Args_size=1
	iconst_1
	ireturn
  Labels:

public java.lang.Object productElement(int);
  Signature: (I)Ljava/lang/Object;
  Code:
   Stack=3, Locals=3, Args_size=2
	iload_1
	istore_2
	iload_2
	iconst_0
	if_icmpne	l1 // new
	aload_0
	invokevirtual	Method underlying:()Lscala/collection/Iterable;
	areturn
l1	new	class java/lang/IndexOutOfBoundsException
	dup
	iload_1
	invokestatic	Method scala/runtime/BoxesRunTime.boxToInteger:(I)Ljava/lang/Integer;
	invokevirtual	Method java/lang/Object.toString:()Ljava/lang/String;
	invokespecial	Method java/lang/IndexOutOfBoundsException."<init>":(Ljava/lang/String;)V
	athrow
  Labels:
   	l1 = 12 // new
  LocalVariableTable: 
   Start  Length  Slot  Name   Signature
   0      27      0    this       Lscala/collection/JavaConversions$IterableWrapper;
   2      25      2    temp68       I


public java.lang.String productElementName(int);
  Signature: (I)Ljava/lang/String;
  Code:
   Stack=3, Locals=3, Args_size=2
	iload_1
	istore_2
	iload_2
	iconst_0
	if_icmpne	l1 // new
	ldc	String underlying
	areturn
l1	new	class java/lang/IndexOutOfBoundsException
	dup
	iload_1
	invokestatic	Method scala/runtime/BoxesRunTime.boxToInteger:(I)Ljava/lang/Integer;
	invokevirtual	Method java/lang/Object.toString:()Ljava/lang/String;
	invokespecial	Method java/lang/IndexOutOfBoundsException."<init>":(Ljava/lang/String;)V
	athrow
  Labels:
   	l1 = 10 // new
  LocalVariableTable: 
   Start  Length  Slot  Name   Signature
   0      25      0    this       Lscala/collection/JavaConversions$IterableWrapper;
   2      23      2    temp69       I


public boolean canEqual(java.lang.Object);
  Signature: (Ljava/lang/Object;)Z
  Code:
   Stack=1, Locals=2, Args_size=2
	aload_1
	instanceof	class scala/collection/JavaConversions$IterableWrapper
	ireturn
  Labels:

private final boolean gd4$1(scala.collection.Iterable);
  Signature: (Lscala/collection/Iterable;)Z
  Code:
   Stack=2, Locals=3, Args_size=2
	aload_1
	aload_0
	invokevirtual	Method underlying:()Lscala/collection/Iterable;
	astore_2
	dup
	ifnonnull	l1 // aload_2
	pop
	aload_2
	ifnull	l2 // iconst_1
	goto	l3 // iconst_0
l1	aload_2
	invokevirtual	Method java/lang/Object.equals:(Ljava/lang/Object;)Z
	ifeq	l3 // iconst_0
l2	iconst_1
	goto	l4 // ireturn
l3	iconst_0
l4	ireturn
  Labels:
   	l1 = 18 // aload_2
   	l2 = 25 // iconst_1
   	l3 = 29 // iconst_0
   	l4 = 30 // ireturn

public scala.collection.JavaConversions$IterableWrapper(scala.collection.Iterable);
  Signature: (Lscala/collection/Iterable;)V
  Code:
   Stack=2, Locals=2, Args_size=2
	aload_0
	aload_1
	putfield	Field underlying:Lscala/collection/Iterable;
	aload_0
	invokespecial	Method java/util/AbstractCollection."<init>":()V
	aload_0
	invokestatic	Method scala/Product$class.$init$:(Lscala/Product;)V
	return
  Labels:
  LocalVariableTable: 
   Start  Length  Slot  Name   Signature
   0      14      0    this       Lscala/collection/JavaConversions$IterableWrapper;
   0      14      1    underlying       Lscala/collection/Iterable;

  Signature: length = 0x2
   00 FFFFFF83 

}

