Compiled from "JavaConversions.scala"
public final class scala.collection.JavaConversions$MutableMapWrapperLike$$anon$1$$anon$5 extends java.lang.Object implements java.util.Iterator
  SourceFile: "JavaConversions.scala"
  Scala: length = 0x
   
  Signature: length = 0x2
   00 FFFFFF8A 
  InnerClass: 
   public abstract Entry=class java/util/Map$Entry of class java/util/Map
   public abstract MutableMapWrapperLike=class scala/collection/JavaConversions$MutableMapWrapperLike of class scala/collection/JavaConversions
   public final $anon$1=class scala/collection/JavaConversions$MutableMapWrapperLike$$anon$1 of class scala/collection/JavaConversions$MutableMapWrapperLike
   public final $anon$5=class scala/collection/JavaConversions$MutableMapWrapperLike$$anon$1$$anon$5 of class scala/collection/JavaConversions$MutableMapWrapperLike$$anon$1
   public final $anon$6=class scala/collection/JavaConversions$MutableMapWrapperLike$$anon$1$$anon$5$$anon$6 of class scala/collection/JavaConversions$MutableMapWrapperLike$$anon$1$$anon$5
  minor version: 0
  major version: 49
  Constant pool:
Asciz	SourceFile;
Asciz	JavaConversions.scala;
Asciz	ui;
Asciz	Lscala/collection/Iterator;;
Asciz	Lscala/collection/Iterator<Lscala/Tuple2<TA;TB;>;>;;
Asciz	Signature;
Asciz	prev;
Asciz	Lscala/Option;;
Asciz	Lscala/Option<TA;>;;
Asciz	$outer;
Asciz	Lscala/collection/JavaConversions$MutableMapWrapperLike$$anon$1;;
Asciz	()Lscala/collection/Iterator;;
Asciz	Code;
Asciz	LineNumberTable;
Asciz	scala/collection/JavaConversions$MutableMapWrapperLike$$anon$1$$anon$5;
class	scala/collection/JavaConversions$MutableMapWrapperLike$$anon$1$$anon$5
NameAndType	ui:Lscala/collection/Iterator;
Field	scala/collection/JavaConversions$MutableMapWrapperLike$$anon$1$$anon$5.ui:Lscala/collection/Iterator;
Asciz	()Lscala/collection/Iterator<Lscala/Tuple2<TA;TB;>;>;;
Asciz	()Lscala/Option;;
NameAndType	prev:Lscala/Option;
Field	scala/collection/JavaConversions$MutableMapWrapperLike$$anon$1$$anon$5.prev:Lscala/Option;
Asciz	()Lscala/Option<TA;>;;
Asciz	prev_$eq;
Asciz	(Lscala/Option;)V;
Asciz	(Lscala/Option<TA;>;)V;
Asciz	hasNext;
Asciz	()Z;
NameAndType	ui:()Lscala/collection/Iterator;
Method	scala/collection/JavaConversions$MutableMapWrapperLike$$anon$1$$anon$5.ui:()Lscala/collection/Iterator;
Asciz	scala/collection/Iterator;
class	scala/collection/Iterator
NameAndType	hasNext:()Z
InterfaceMethod	scala/collection/Iterator.hasNext:()Z
Asciz	next;
Asciz	()Ljava/util/Map$Entry;;
Asciz	()Ljava/lang/Object;;
NameAndType	next:()Ljava/lang/Object;
InterfaceMethod	scala/collection/Iterator.next:()Ljava/lang/Object;
Asciz	scala/Tuple2;
class	scala/Tuple2
Asciz	_1;
NameAndType	_1:()Ljava/lang/Object;
Method	scala/Tuple2._1:()Ljava/lang/Object;
Asciz	_2;
NameAndType	_2:()Ljava/lang/Object;
Method	scala/Tuple2._2:()Ljava/lang/Object;
Asciz	<init>;
Asciz	(Ljava/lang/Object;Ljava/lang/Object;)V;
NameAndType	"<init>":(Ljava/lang/Object;Ljava/lang/Object;)V
Method	scala/Tuple2."<init>":(Ljava/lang/Object;Ljava/lang/Object;)V
Asciz	scala/Some;
class	scala/Some
Asciz	(Ljava/lang/Object;)V;
NameAndType	"<init>":(Ljava/lang/Object;)V
Method	scala/Some."<init>":(Ljava/lang/Object;)V
NameAndType	prev_$eq:(Lscala/Option;)V
Method	scala/collection/JavaConversions$MutableMapWrapperLike$$anon$1$$anon$5.prev_$eq:(Lscala/Option;)V
Asciz	scala/collection/JavaConversions$MutableMapWrapperLike$$anon$1$$anon$5$$anon$6;
class	scala/collection/JavaConversions$MutableMapWrapperLike$$anon$1$$anon$5$$anon$6
Asciz	(Lscala/collection/JavaConversions$MutableMapWrapperLike$$anon$1$$anon$5;Ljava/lang/Object;Ljava/lang/Object;)V;
NameAndType	"<init>":(Lscala/collection/JavaConversions$MutableMapWrapperLike$$anon$1$$anon$5;Ljava/lang/Object;Ljava/lang/Object;)V
Method	scala/collection/JavaConversions$MutableMapWrapperLike$$anon$1$$anon$5$$anon$6."<init>":(Lscala/collection/JavaConversions$MutableMapWrapperLike$$anon$1$$anon$5;Ljava/lang/Object;Ljava/lang/Object;)V
Asciz	scala/MatchError;
class	scala/MatchError
Method	scala/MatchError."<init>":(Ljava/lang/Object;)V
Asciz	this;
Asciz	Lscala/collection/JavaConversions$MutableMapWrapperLike$$anon$1$$anon$5;;
Asciz	temp89;
Asciz	Lscala/Tuple2;;
Asciz	k$1;
Asciz	Ljava/lang/Object;;
Asciz	v$1;
Asciz	LocalVariableTable;
Asciz	remove;
Asciz	()V;
NameAndType	prev:()Lscala/Option;
Method	scala/collection/JavaConversions$MutableMapWrapperLike$$anon$1$$anon$5.prev:()Lscala/Option;
Asciz	x;
NameAndType	x:Ljava/lang/Object;
Field	scala/Some.x:Ljava/lang/Object;
NameAndType	$outer:Lscala/collection/JavaConversions$MutableMapWrapperLike$$anon$1;
Field	scala/collection/JavaConversions$MutableMapWrapperLike$$anon$1$$anon$5.$outer:Lscala/collection/JavaConversions$MutableMapWrapperLike$$anon$1;
Asciz	scala/collection/JavaConversions$MutableMapWrapperLike$$anon$1;
class	scala/collection/JavaConversions$MutableMapWrapperLike$$anon$1
Asciz	Lscala/collection/JavaConversions$MutableMapWrapperLike;;
NameAndType	$outer:Lscala/collection/JavaConversions$MutableMapWrapperLike;
Field	scala/collection/JavaConversions$MutableMapWrapperLike$$anon$1.$outer:Lscala/collection/JavaConversions$MutableMapWrapperLike;
Asciz	scala/collection/JavaConversions$MutableMapWrapperLike;
class	scala/collection/JavaConversions$MutableMapWrapperLike
Asciz	(Ljava/lang/Object;)Ljava/lang/Object;;
NameAndType	remove:(Ljava/lang/Object;)Ljava/lang/Object;
Method	scala/collection/JavaConversions$MutableMapWrapperLike.remove:(Ljava/lang/Object;)Ljava/lang/Object;
Asciz	scala/None$;
class	scala/None$
Asciz	MODULE$;
Asciz	Lscala/None$;;
NameAndType	MODULE$:Lscala/None$;
Field	scala/None$.MODULE$:Lscala/None$;
Asciz	java/lang/IllegalStateException;
class	java/lang/IllegalStateException
Asciz	next must be called at least once before remove;
String	next must be called at least once before remove
Asciz	(Ljava/lang/String;)V;
NameAndType	"<init>":(Ljava/lang/String;)V
Method	java/lang/IllegalStateException."<init>":(Ljava/lang/String;)V
Asciz	temp94;
Asciz	temp95;
Asciz	Lscala/Some;;
Asciz	temp96;
Asciz	scala$collection$JavaConversions$MutableMapWrapperLike$$anon$$anon$$$outer;
Asciz	()Lscala/collection/JavaConversions$MutableMapWrapperLike$$anon$1;;
NameAndType	next:()Ljava/util/Map$Entry;
Method	scala/collection/JavaConversions$MutableMapWrapperLike$$anon$1$$anon$5.next:()Ljava/util/Map$Entry;
Asciz	(Lscala/collection/JavaConversions$MutableMapWrapperLike$$anon$1;)V;
Asciz	java/lang/NullPointerException;
class	java/lang/NullPointerException
NameAndType	"<init>":()V
Method	java/lang/NullPointerException."<init>":()V
Asciz	java/lang/Object;
class	java/lang/Object
Method	java/lang/Object."<init>":()V
Asciz	scala$collection$JavaConversions$MutableMapWrapperLike$$anon$$$outer;
Asciz	()Lscala/collection/JavaConversions$MutableMapWrapperLike;;
NameAndType	scala$collection$JavaConversions$MutableMapWrapperLike$$anon$$$outer:()Lscala/collection/JavaConversions$MutableMapWrapperLike;
Method	scala/collection/JavaConversions$MutableMapWrapperLike$$anon$1.scala$collection$JavaConversions$MutableMapWrapperLike$$anon$$$outer:()Lscala/collection/JavaConversions$MutableMapWrapperLike;
Asciz	scala$collection$JavaConversions$MutableMapWrapperLike$$underlying;
Asciz	Lscala/collection/mutable/Map;;
NameAndType	scala$collection$JavaConversions$MutableMapWrapperLike$$underlying:Lscala/collection/mutable/Map;
Field	scala/collection/JavaConversions$MutableMapWrapperLike.scala$collection$JavaConversions$MutableMapWrapperLike$$underlying:Lscala/collection/mutable/Map;
Asciz	scala/collection/MapLike;
class	scala/collection/MapLike
Asciz	iterator;
NameAndType	iterator:()Lscala/collection/Iterator;
InterfaceMethod	scala/collection/MapLike.iterator:()Lscala/collection/Iterator;
Asciz	(Lscala/collection/JavaConversions$MutableMapWrapperLike<TA;TB;>.$anon$1;)V;
Asciz	Scala;
Asciz	Ljava/lang/Object;Ljava/util/Iterator<Ljava/util/Map$Entry<TA;TB;>;>;;
Asciz	InnerClasses;
Asciz	java/util/Map$Entry;
class	java/util/Map$Entry
Asciz	java/util/Map;
class	java/util/Map
Asciz	Entry;
Asciz	scala/collection/JavaConversions;
class	scala/collection/JavaConversions
Asciz	MutableMapWrapperLike;
Asciz	$anon$1;
Asciz	$anon$5;
Asciz	$anon$6;
Asciz	java/util/Iterator;
class	java/util/Iterator

{
private final scala.collection.Iterator ui;
  Signature: Lscala/collection/Iterator;
  Signature: length = 0x2
   00 05 

private scala.Option prev;
  Signature: Lscala/Option;
  Signature: length = 0x2
   00 09 

public final scala.collection.JavaConversions$MutableMapWrapperLike$$anon$1 $outer;
  Signature: Lscala/collection/JavaConversions$MutableMapWrapperLike$$anon$1;

private scala.collection.Iterator ui();
  Signature: ()Lscala/collection/Iterator;
  Code:
   Stack=1, Locals=1, Args_size=1
	aload_0
	getfield	Field ui:Lscala/collection/Iterator;
	areturn
  Labels:
  Signature: length = 0x2
   00 13 

private scala.Option prev();
  Signature: ()Lscala/Option;
  Code:
   Stack=1, Locals=1, Args_size=1
	aload_0
	getfield	Field prev:Lscala/Option;
	areturn
  Labels:
  Signature: length = 0x2
   00 17 

private void prev_$eq(scala.Option);
  Signature: (Lscala/Option;)V
  Code:
   Stack=2, Locals=2, Args_size=2
	aload_0
	aload_1
	putfield	Field prev:Lscala/Option;
	return
  Labels:
  Signature: length = 0x2
   00 1A 

public boolean hasNext();
  Signature: ()Z
  Code:
   Stack=1, Locals=1, Args_size=1
	aload_0
	invokespecial	Method ui:()Lscala/collection/Iterator;
	invokeinterface	InterfaceMethod scala/collection/Iterator.hasNext:()Z
	ireturn
  Labels:

public java.util.Map$Entry next();
  Signature: ()Ljava/util/Map$Entry;
  Code:
   Stack=5, Locals=5, Args_size=1
	aload_0
	invokespecial	Method ui:()Lscala/collection/Iterator;
	invokeinterface	InterfaceMethod scala/collection/Iterator.next:()Ljava/lang/Object;
	checkcast	class scala/Tuple2
	astore_2
	aload_2
	ifnull	l1 // new
	new	class scala/Tuple2
	dup
	aload_2
	invokevirtual	Method scala/Tuple2._1:()Ljava/lang/Object;
	aload_2
	invokevirtual	Method scala/Tuple2._2:()Ljava/lang/Object;
	invokespecial	Method scala/Tuple2."<init>":(Ljava/lang/Object;Ljava/lang/Object;)V
	astore_1
	aload_1
	invokevirtual	Method scala/Tuple2._1:()Ljava/lang/Object;
	astore_3
	aload_1
	invokevirtual	Method scala/Tuple2._2:()Ljava/lang/Object;
	astore	4
	aload_0
	new	class scala/Some
	dup
	aload_3
	invokespecial	Method scala/Some."<init>":(Ljava/lang/Object;)V
	invokespecial	Method prev_$eq:(Lscala/Option;)V
	new	class scala/collection/JavaConversions$MutableMapWrapperLike$$anon$1$$anon$5$$anon$6
	dup
	aload_0
	aload_3
	aload	4
	invokespecial	Method scala/collection/JavaConversions$MutableMapWrapperLike$$anon$1$$anon$5$$anon$6."<init>":(Lscala/collection/JavaConversions$MutableMapWrapperLike$$anon$1$$anon$5;Ljava/lang/Object;Ljava/lang/Object;)V
	areturn
l1	new	class scala/MatchError
	dup
	aload_2
	invokespecial	Method scala/MatchError."<init>":(Ljava/lang/Object;)V
	athrow
  Labels:
   	l1 = 68 // new
  LocalVariableTable: 
   Start  Length  Slot  Name   Signature
   0      77      0    this       Lscala/collection/JavaConversions$MutableMapWrapperLike$$anon$1$$anon$5;
   13      64      2    temp89       Lscala/Tuple2;
   38      29      3    k$1       Ljava/lang/Object;
   44      23      4    v$1       Ljava/lang/Object;


public void remove();
  Signature: ()V
  Code:
   Stack=3, Locals=5, Args_size=1
	aload_0
	invokespecial	Method prev:()Lscala/Option;
	astore_1
	aload_1
	instanceof	class scala/Some
	ifeq	l1 // new
	aload_1
	checkcast	class scala/Some
	astore_2
	aload_2
	getfield	Field scala/Some.x:Ljava/lang/Object;
	astore	4
	aload_0
	getfield	Field $outer:Lscala/collection/JavaConversions$MutableMapWrapperLike$$anon$1;
	astore_3
	aload_3
	getfield	Field scala/collection/JavaConversions$MutableMapWrapperLike$$anon$1.$outer:Lscala/collection/JavaConversions$MutableMapWrapperLike;
	aload	4
	invokevirtual	Method scala/collection/JavaConversions$MutableMapWrapperLike.remove:(Ljava/lang/Object;)Ljava/lang/Object;
	pop
	aload_0
	getstatic	Field scala/None$.MODULE$:Lscala/None$;
	invokespecial	Method prev_$eq:(Lscala/Option;)V
	return
l1	new	class java/lang/IllegalStateException
	dup
	ldc	String next must be called at least once before remove
	invokespecial	Method java/lang/IllegalStateException."<init>":(Ljava/lang/String;)V
	athrow
  Labels:
   	l1 = 46 // new
  LocalVariableTable: 
   Start  Length  Slot  Name   Signature
   0      56      0    this       Lscala/collection/JavaConversions$MutableMapWrapperLike$$anon$1$$anon$5;
   5      51      1    temp94       Lscala/Option;
   17      28      2    temp95       Lscala/Some;
   23      22      4    temp96       Ljava/lang/Object;


public scala.collection.JavaConversions$MutableMapWrapperLike$$anon$1 scala$collection$JavaConversions$MutableMapWrapperLike$$anon$$anon$$$outer();
  Signature: ()Lscala/collection/JavaConversions$MutableMapWrapperLike$$anon$1;
  Code:
   Stack=1, Locals=1, Args_size=1
	aload_0
	getfield	Field $outer:Lscala/collection/JavaConversions$MutableMapWrapperLike$$anon$1;
	areturn
  Labels:

public java.lang.Object next();
  Signature: ()Ljava/lang/Object;
  Code:
   Stack=1, Locals=1, Args_size=1
	aload_0
	invokevirtual	Method next:()Ljava/util/Map$Entry;
	areturn
  Labels:

public scala.collection.JavaConversions$MutableMapWrapperLike$$anon$1$$anon$5(scala.collection.JavaConversions$MutableMapWrapperLike$$anon$1);
  Signature: (Lscala/collection/JavaConversions$MutableMapWrapperLike$$anon$1;)V
  Code:
   Stack=2, Locals=2, Args_size=2
	aload_1
	ifnonnull	l1 // aload_0
	new	class java/lang/NullPointerException
	dup
	invokespecial	Method java/lang/NullPointerException."<init>":()V
	athrow
l1	aload_0
	aload_1
	putfield	Field $outer:Lscala/collection/JavaConversions$MutableMapWrapperLike$$anon$1;
	aload_0
	invokespecial	Method java/lang/Object."<init>":()V
	aload_0
	aload_1
	invokevirtual	Method scala/collection/JavaConversions$MutableMapWrapperLike$$anon$1.scala$collection$JavaConversions$MutableMapWrapperLike$$anon$$$outer:()Lscala/collection/JavaConversions$MutableMapWrapperLike;
	getfield	Field scala/collection/JavaConversions$MutableMapWrapperLike.scala$collection$JavaConversions$MutableMapWrapperLike$$underlying:Lscala/collection/mutable/Map;
	invokeinterface	InterfaceMethod scala/collection/MapLike.iterator:()Lscala/collection/Iterator;
	putfield	Field ui:Lscala/collection/Iterator;
	aload_0
	getstatic	Field scala/None$.MODULE$:Lscala/None$;
	putfield	Field prev:Lscala/Option;
	return
  Labels:
   	l1 = 12 // aload_0
  LocalVariableTable: 
   Start  Length  Slot  Name   Signature
   0      45      0    this       Lscala/collection/JavaConversions$MutableMapWrapperLike$$anon$1$$anon$5;
   0      45      1    $outer       Lscala/collection/JavaConversions$MutableMapWrapperLike$$anon$1;

  Signature: length = 0x2
   00 FFFFFF88 

}

