Compiled from "JavaConversions.scala"
public class scala.collection.JavaConversions$JEnumerationWrapper extends java.lang.Object implements scala.collection.Iterator,scala.ScalaObject,scala.Product,java.io.Serializable
  SourceFile: "JavaConversions.scala"
  Signature: length = 0x2
   01 FFFFFF8F 
  Scala: length = 0x
   
  InnerClass: 
   public final WithFilter=class scala/collection/Iterator$WithFilter of class scala/collection/Iterator
   public GroupedIterator=class scala/collection/Iterator$GroupedIterator of class scala/collection/Iterator
   public JEnumerationWrapper=class scala/collection/JavaConversions$JEnumerationWrapper of class scala/collection/JavaConversions
  minor version: 0
  major version: 49
  Constant pool:
Asciz	SourceFile;
Asciz	JavaConversions.scala;
Asciz	underlying;
Asciz	Ljava/util/Enumeration;;
Asciz	Ljava/util/Enumeration<TA;>;;
Asciz	Signature;
Asciz	<init>;
Asciz	(Ljava/util/Enumeration;)V;
Asciz	Code;
Asciz	LineNumberTable;
Asciz	scala/collection/JavaConversions$JEnumerationWrapper;
class	scala/collection/JavaConversions$JEnumerationWrapper
NameAndType	underlying:Ljava/util/Enumeration;
Field	scala/collection/JavaConversions$JEnumerationWrapper.underlying:Ljava/util/Enumeration;
Asciz	java/lang/Object;
class	java/lang/Object
Asciz	()V;
NameAndType	"<init>":()V
Method	java/lang/Object."<init>":()V
Asciz	scala/collection/Iterator$class;
class	scala/collection/Iterator$class
Asciz	$init$;
Asciz	(Lscala/collection/Iterator;)V;
NameAndType	$init$:(Lscala/collection/Iterator;)V
Method	scala/collection/Iterator$class.$init$:(Lscala/collection/Iterator;)V
Asciz	scala/Product$class;
class	scala/Product$class
Asciz	(Lscala/Product;)V;
NameAndType	$init$:(Lscala/Product;)V
Method	scala/Product$class.$init$:(Lscala/Product;)V
Asciz	this;
Asciz	Lscala/collection/JavaConversions$JEnumerationWrapper;;
Asciz	LocalVariableTable;
Asciz	(Ljava/util/Enumeration<TA;>;)V;
Asciz	gd3$1;
Asciz	(Ljava/util/Enumeration;)Z;
Asciz	()Ljava/util/Enumeration;;
NameAndType	underlying:()Ljava/util/Enumeration;
Method	scala/collection/JavaConversions$JEnumerationWrapper.underlying:()Ljava/util/Enumeration;
Asciz	equals;
Asciz	(Ljava/lang/Object;)Z;
NameAndType	equals:(Ljava/lang/Object;)Z
Method	java/lang/Object.equals:(Ljava/lang/Object;)Z
Asciz	canEqual;
Asciz	productElement;
Asciz	(I)Ljava/lang/Object;;
Asciz	scala/MatchError;
class	scala/MatchError
Asciz	scala/runtime/BoxesRunTime;
class	scala/runtime/BoxesRunTime
Asciz	boxToInteger;
Asciz	(I)Ljava/lang/Integer;;
NameAndType	boxToInteger:(I)Ljava/lang/Integer;
Method	scala/runtime/BoxesRunTime.boxToInteger:(I)Ljava/lang/Integer;
Asciz	toString;
Asciz	()Ljava/lang/String;;
NameAndType	toString:()Ljava/lang/String;
Method	java/lang/Object.toString:()Ljava/lang/String;
Asciz	(Ljava/lang/String;)V;
NameAndType	"<init>":(Ljava/lang/String;)V
Method	scala/MatchError."<init>":(Ljava/lang/String;)V
Asciz	java/lang/IndexOutOfBoundsException;
class	java/lang/IndexOutOfBoundsException
Method	java/lang/IndexOutOfBoundsException."<init>":(Ljava/lang/String;)V
Asciz	productArity;
Asciz	()I;
Asciz	productPrefix;
Asciz	JEnumerationWrapper;
String	JEnumerationWrapper
NameAndType	gd3$1:(Ljava/util/Enumeration;)Z
Method	scala/collection/JavaConversions$JEnumerationWrapper.gd3$1:(Ljava/util/Enumeration;)Z
Asciz	scala/Equals;
class	scala/Equals
NameAndType	canEqual:(Ljava/lang/Object;)Z
InterfaceMethod	scala/Equals.canEqual:(Ljava/lang/Object;)Z
Asciz	temp52;
Asciz	temp53;
Asciz	hashCode;
Asciz	scala/runtime/ScalaRunTime$;
class	scala/runtime/ScalaRunTime$
Asciz	MODULE$;
Asciz	Lscala/runtime/ScalaRunTime$;;
NameAndType	MODULE$:Lscala/runtime/ScalaRunTime$;
Field	scala/runtime/ScalaRunTime$.MODULE$:Lscala/runtime/ScalaRunTime$;
Asciz	_hashCode;
Asciz	(Lscala/Product;)I;
NameAndType	_hashCode:(Lscala/Product;)I
Method	scala/runtime/ScalaRunTime$._hashCode:(Lscala/Product;)I
Asciz	copy;
Asciz	(Ljava/util/Enumeration;)Lscala/collection/JavaConversions$JEnumerationWrapper;;
NameAndType	"<init>":(Ljava/util/Enumeration;)V
Method	scala/collection/JavaConversions$JEnumerationWrapper."<init>":(Ljava/util/Enumeration;)V
Asciz	next;
Asciz	()Ljava/lang/Object;;
Asciz	java/util/Enumeration;
class	java/util/Enumeration
Asciz	nextElement;
NameAndType	nextElement:()Ljava/lang/Object;
InterfaceMethod	java/util/Enumeration.nextElement:()Ljava/lang/Object;
Asciz	()TA;;
Asciz	hasNext;
Asciz	()Z;
Asciz	hasMoreElements;
NameAndType	hasMoreElements:()Z
InterfaceMethod	java/util/Enumeration.hasMoreElements:()Z
Asciz	()Ljava/util/Enumeration<TA;>;;
Asciz	copy$default$1;
Asciz	sliding$default$2;
Asciz	(Lscala/collection/Iterator;)I;
NameAndType	sliding$default$2:(Lscala/collection/Iterator;)I
Method	scala/collection/Iterator$class.sliding$default$2:(Lscala/collection/Iterator;)I
Asciz	readInto;
Asciz	(Ljava/lang/Object;)V;
Asciz	(Lscala/collection/Iterator;Ljava/lang/Object;)V;
NameAndType	readInto:(Lscala/collection/Iterator;Ljava/lang/Object;)V
Method	scala/collection/Iterator$class.readInto:(Lscala/collection/Iterator;Ljava/lang/Object;)V
Asciz	xs;
Asciz	Ljava/lang/Object;;
Asciz	(Ljava/lang/Object;I)V;
Asciz	(Lscala/collection/Iterator;Ljava/lang/Object;I)V;
NameAndType	readInto:(Lscala/collection/Iterator;Ljava/lang/Object;I)V
Method	scala/collection/Iterator$class.readInto:(Lscala/collection/Iterator;Ljava/lang/Object;I)V
Asciz	start;
Asciz	I;
Asciz	(Ljava/lang/Object;II)V;
Asciz	(Lscala/collection/Iterator;Ljava/lang/Object;II)V;
NameAndType	readInto:(Lscala/collection/Iterator;Ljava/lang/Object;II)V
Method	scala/collection/Iterator$class.readInto:(Lscala/collection/Iterator;Ljava/lang/Object;II)V
Asciz	sz;
Asciz	counted;
Asciz	(Lscala/collection/Iterator;)Ljava/lang/Object;;
NameAndType	counted:(Lscala/collection/Iterator;)Ljava/lang/Object;
Method	scala/collection/Iterator$class.counted:(Lscala/collection/Iterator;)Ljava/lang/Object;
Asciz	collect;
Asciz	()Lscala/collection/Seq;;
Asciz	(Lscala/collection/Iterator;)Lscala/collection/Seq;;
NameAndType	collect:(Lscala/collection/Iterator;)Lscala/collection/Seq;
Method	scala/collection/Iterator$class.collect:(Lscala/collection/Iterator;)Lscala/collection/Seq;
Asciz	findIndexOf;
Asciz	(Lscala/Function1;)I;
Asciz	(Lscala/collection/Iterator;Lscala/Function1;)I;
NameAndType	findIndexOf:(Lscala/collection/Iterator;Lscala/Function1;)I
Method	scala/collection/Iterator$class.findIndexOf:(Lscala/collection/Iterator;Lscala/Function1;)I
Asciz	p;
Asciz	Lscala/Function1;;
Asciz	append;
Asciz	(Lscala/collection/Iterator;)Lscala/collection/Iterator;;
Asciz	(Lscala/collection/Iterator;Lscala/collection/Iterator;)Lscala/collection/Iterator;;
NameAndType	append:(Lscala/collection/Iterator;Lscala/collection/Iterator;)Lscala/collection/Iterator;
Method	scala/collection/Iterator$class.append:(Lscala/collection/Iterator;Lscala/collection/Iterator;)Lscala/collection/Iterator;
Asciz	that;
Asciz	Lscala/collection/Iterator;;
Asciz	(Lscala/collection/Iterator;)Ljava/lang/String;;
NameAndType	toString:(Lscala/collection/Iterator;)Ljava/lang/String;
Method	scala/collection/Iterator$class.toString:(Lscala/collection/Iterator;)Ljava/lang/String;
Asciz	addString;
Asciz	(Lscala/collection/mutable/StringBuilder;)Lscala/collection/mutable/StringBuilder;;
Asciz	(Lscala/collection/Iterator;Lscala/collection/mutable/StringBuilder;)Lscala/collection/mutable/StringBuilder;;
NameAndType	addString:(Lscala/collection/Iterator;Lscala/collection/mutable/StringBuilder;)Lscala/collection/mutable/StringBuilder;
Method	scala/collection/Iterator$class.addString:(Lscala/collection/Iterator;Lscala/collection/mutable/StringBuilder;)Lscala/collection/mutable/StringBuilder;
Asciz	buf;
Asciz	Lscala/collection/mutable/StringBuilder;;
Asciz	(Lscala/collection/mutable/StringBuilder;Ljava/lang/String;)Lscala/collection/mutable/StringBuilder;;
Asciz	(Lscala/collection/Iterator;Lscala/collection/mutable/StringBuilder;Ljava/lang/String;)Lscala/collection/mutable/StringBuilder;;
NameAndType	addString:(Lscala/collection/Iterator;Lscala/collection/mutable/StringBuilder;Ljava/lang/String;)Lscala/collection/mutable/StringBuilder;
Method	scala/collection/Iterator$class.addString:(Lscala/collection/Iterator;Lscala/collection/mutable/StringBuilder;Ljava/lang/String;)Lscala/collection/mutable/StringBuilder;
Asciz	sep;
Asciz	Ljava/lang/String;;
Asciz	(Lscala/collection/mutable/StringBuilder;Ljava/lang/String;Ljava/lang/String;Ljava/lang/String;)Lscala/collection/mutable/StringBuilder;;
Asciz	(Lscala/collection/Iterator;Lscala/collection/mutable/StringBuilder;Ljava/lang/String;Ljava/lang/String;Ljava/lang/String;)Lscala/collection/mutable/StringBuilder;;
NameAndType	addString:(Lscala/collection/Iterator;Lscala/collection/mutable/StringBuilder;Ljava/lang/String;Ljava/lang/String;Ljava/lang/String;)Lscala/collection/mutable/StringBuilder;
Method	scala/collection/Iterator$class.addString:(Lscala/collection/Iterator;Lscala/collection/mutable/StringBuilder;Ljava/lang/String;Ljava/lang/String;Ljava/lang/String;)Lscala/collection/mutable/StringBuilder;
Asciz	end;
Asciz	mkString;
NameAndType	mkString:(Lscala/collection/Iterator;)Ljava/lang/String;
Method	scala/collection/Iterator$class.mkString:(Lscala/collection/Iterator;)Ljava/lang/String;
Asciz	(Ljava/lang/String;)Ljava/lang/String;;
Asciz	(Lscala/collection/Iterator;Ljava/lang/String;)Ljava/lang/String;;
NameAndType	mkString:(Lscala/collection/Iterator;Ljava/lang/String;)Ljava/lang/String;
Method	scala/collection/Iterator$class.mkString:(Lscala/collection/Iterator;Ljava/lang/String;)Ljava/lang/String;
Asciz	(Ljava/lang/String;Ljava/lang/String;Ljava/lang/String;)Ljava/lang/String;;
Asciz	(Lscala/collection/Iterator;Ljava/lang/String;Ljava/lang/String;Ljava/lang/String;)Ljava/lang/String;;
NameAndType	mkString:(Lscala/collection/Iterator;Ljava/lang/String;Ljava/lang/String;Ljava/lang/String;)Ljava/lang/String;
Method	scala/collection/Iterator$class.mkString:(Lscala/collection/Iterator;Ljava/lang/String;Ljava/lang/String;Ljava/lang/String;)Ljava/lang/String;
Asciz	sameElements;
Asciz	(Lscala/collection/Iterator;)Z;
Asciz	(Lscala/collection/Iterator;Lscala/collection/Iterator;)Z;
NameAndType	sameElements:(Lscala/collection/Iterator;Lscala/collection/Iterator;)Z
Method	scala/collection/Iterator$class.sameElements:(Lscala/collection/Iterator;Lscala/collection/Iterator;)Z
Asciz	toSeq;
NameAndType	toSeq:(Lscala/collection/Iterator;)Lscala/collection/Seq;
Method	scala/collection/Iterator$class.toSeq:(Lscala/collection/Iterator;)Lscala/collection/Seq;
Asciz	toStream;
Asciz	()Lscala/collection/immutable/Stream;;
Asciz	(Lscala/collection/Iterator;)Lscala/collection/immutable/Stream;;
NameAndType	toStream:(Lscala/collection/Iterator;)Lscala/collection/immutable/Stream;
Method	scala/collection/Iterator$class.toStream:(Lscala/collection/Iterator;)Lscala/collection/immutable/Stream;
Asciz	toList;
Asciz	()Lscala/collection/immutable/List;;
Asciz	(Lscala/collection/Iterator;)Lscala/collection/immutable/List;;
NameAndType	toList:(Lscala/collection/Iterator;)Lscala/collection/immutable/List;
Method	scala/collection/Iterator$class.toList:(Lscala/collection/Iterator;)Lscala/collection/immutable/List;
Asciz	copyToBuffer;
Asciz	(Lscala/collection/mutable/Buffer;)V;
Asciz	(Lscala/collection/Iterator;Lscala/collection/mutable/Buffer;)V;
NameAndType	copyToBuffer:(Lscala/collection/Iterator;Lscala/collection/mutable/Buffer;)V
Method	scala/collection/Iterator$class.copyToBuffer:(Lscala/collection/Iterator;Lscala/collection/mutable/Buffer;)V
Asciz	dest;
Asciz	Lscala/collection/mutable/Buffer;;
Asciz	copyToArray;
NameAndType	copyToArray:(Lscala/collection/Iterator;Ljava/lang/Object;)V
Method	scala/collection/Iterator$class.copyToArray:(Lscala/collection/Iterator;Ljava/lang/Object;)V
NameAndType	copyToArray:(Lscala/collection/Iterator;Ljava/lang/Object;I)V
Method	scala/collection/Iterator$class.copyToArray:(Lscala/collection/Iterator;Ljava/lang/Object;I)V
NameAndType	copyToArray:(Lscala/collection/Iterator;Ljava/lang/Object;II)V
Method	scala/collection/Iterator$class.copyToArray:(Lscala/collection/Iterator;Ljava/lang/Object;II)V
Asciz	len;
Asciz	patch;
Asciz	(ILscala/collection/Iterator;I)Ljava/lang/Object;;
Asciz	(Lscala/collection/Iterator;ILscala/collection/Iterator;I)Ljava/lang/Object;;
NameAndType	patch:(Lscala/collection/Iterator;ILscala/collection/Iterator;I)Ljava/lang/Object;
Method	scala/collection/Iterator$class.patch:(Lscala/collection/Iterator;ILscala/collection/Iterator;I)Ljava/lang/Object;
Asciz	from;
Asciz	patchElems;
Asciz	replaced;
Asciz	duplicate;
Asciz	()Lscala/Tuple2;;
Asciz	(Lscala/collection/Iterator;)Lscala/Tuple2;;
NameAndType	duplicate:(Lscala/collection/Iterator;)Lscala/Tuple2;
Method	scala/collection/Iterator$class.duplicate:(Lscala/collection/Iterator;)Lscala/Tuple2;
Asciz	length;
NameAndType	length:(Lscala/collection/Iterator;)I
Method	scala/collection/Iterator$class.length:(Lscala/collection/Iterator;)I
Asciz	sliding;
Asciz	(II)Lscala/collection/Iterator$GroupedIterator;;
Asciz	(Lscala/collection/Iterator;II)Lscala/collection/Iterator$GroupedIterator;;
NameAndType	sliding:(Lscala/collection/Iterator;II)Lscala/collection/Iterator$GroupedIterator;
Method	scala/collection/Iterator$class.sliding:(Lscala/collection/Iterator;II)Lscala/collection/Iterator$GroupedIterator;
Asciz	size;
Asciz	step;
Asciz	grouped;
Asciz	(I)Lscala/collection/Iterator$GroupedIterator;;
Asciz	(Lscala/collection/Iterator;I)Lscala/collection/Iterator$GroupedIterator;;
NameAndType	grouped:(Lscala/collection/Iterator;I)Lscala/collection/Iterator$GroupedIterator;
Method	scala/collection/Iterator$class.grouped:(Lscala/collection/Iterator;I)Lscala/collection/Iterator$GroupedIterator;
Asciz	buffered;
NameAndType	buffered:(Lscala/collection/Iterator;)Ljava/lang/Object;
Method	scala/collection/Iterator$class.buffered:(Lscala/collection/Iterator;)Ljava/lang/Object;
Asciz	reduceRightOption;
Asciz	(Lscala/Function2;)Lscala/Option;;
Asciz	(Lscala/collection/Iterator;Lscala/Function2;)Lscala/Option;;
NameAndType	reduceRightOption:(Lscala/collection/Iterator;Lscala/Function2;)Lscala/Option;
Method	scala/collection/Iterator$class.reduceRightOption:(Lscala/collection/Iterator;Lscala/Function2;)Lscala/Option;
Asciz	op;
Asciz	Lscala/Function2;;
Asciz	reduceLeftOption;
NameAndType	reduceLeftOption:(Lscala/collection/Iterator;Lscala/Function2;)Lscala/Option;
Method	scala/collection/Iterator$class.reduceLeftOption:(Lscala/collection/Iterator;Lscala/Function2;)Lscala/Option;
Asciz	reduceRight;
Asciz	(Lscala/Function2;)Ljava/lang/Object;;
Asciz	(Lscala/collection/Iterator;Lscala/Function2;)Ljava/lang/Object;;
NameAndType	reduceRight:(Lscala/collection/Iterator;Lscala/Function2;)Ljava/lang/Object;
Method	scala/collection/Iterator$class.reduceRight:(Lscala/collection/Iterator;Lscala/Function2;)Ljava/lang/Object;
Asciz	reduceLeft;
NameAndType	reduceLeft:(Lscala/collection/Iterator;Lscala/Function2;)Ljava/lang/Object;
Method	scala/collection/Iterator$class.reduceLeft:(Lscala/collection/Iterator;Lscala/Function2;)Ljava/lang/Object;
Asciz	$colon$bslash;
Asciz	(Ljava/lang/Object;Lscala/Function2;)Ljava/lang/Object;;
Asciz	(Lscala/collection/Iterator;Ljava/lang/Object;Lscala/Function2;)Ljava/lang/Object;;
NameAndType	$colon$bslash:(Lscala/collection/Iterator;Ljava/lang/Object;Lscala/Function2;)Ljava/lang/Object;
Method	scala/collection/Iterator$class.$colon$bslash:(Lscala/collection/Iterator;Ljava/lang/Object;Lscala/Function2;)Ljava/lang/Object;
Asciz	z;
Asciz	$div$colon;
NameAndType	$div$colon:(Lscala/collection/Iterator;Ljava/lang/Object;Lscala/Function2;)Ljava/lang/Object;
Method	scala/collection/Iterator$class.$div$colon:(Lscala/collection/Iterator;Ljava/lang/Object;Lscala/Function2;)Ljava/lang/Object;
Asciz	foldRight;
NameAndType	foldRight:(Lscala/collection/Iterator;Ljava/lang/Object;Lscala/Function2;)Ljava/lang/Object;
Method	scala/collection/Iterator$class.foldRight:(Lscala/collection/Iterator;Ljava/lang/Object;Lscala/Function2;)Ljava/lang/Object;
Asciz	foldLeft;
NameAndType	foldLeft:(Lscala/collection/Iterator;Ljava/lang/Object;Lscala/Function2;)Ljava/lang/Object;
Method	scala/collection/Iterator$class.foldLeft:(Lscala/collection/Iterator;Ljava/lang/Object;Lscala/Function2;)Ljava/lang/Object;
Asciz	indexOf;
Asciz	(Ljava/lang/Object;)I;
Asciz	(Lscala/collection/Iterator;Ljava/lang/Object;)I;
NameAndType	indexOf:(Lscala/collection/Iterator;Ljava/lang/Object;)I
Method	scala/collection/Iterator$class.indexOf:(Lscala/collection/Iterator;Ljava/lang/Object;)I
Asciz	elem;
Asciz	indexWhere;
NameAndType	indexWhere:(Lscala/collection/Iterator;Lscala/Function1;)I
Method	scala/collection/Iterator$class.indexWhere:(Lscala/collection/Iterator;Lscala/Function1;)I
Asciz	find;
Asciz	(Lscala/Function1;)Lscala/Option;;
Asciz	(Lscala/collection/Iterator;Lscala/Function1;)Lscala/Option;;
NameAndType	find:(Lscala/collection/Iterator;Lscala/Function1;)Lscala/Option;
Method	scala/collection/Iterator$class.find:(Lscala/collection/Iterator;Lscala/Function1;)Lscala/Option;
Asciz	contains;
Asciz	(Lscala/collection/Iterator;Ljava/lang/Object;)Z;
NameAndType	contains:(Lscala/collection/Iterator;Ljava/lang/Object;)Z
Method	scala/collection/Iterator$class.contains:(Lscala/collection/Iterator;Ljava/lang/Object;)Z
Asciz	exists;
Asciz	(Lscala/Function1;)Z;
Asciz	(Lscala/collection/Iterator;Lscala/Function1;)Z;
NameAndType	exists:(Lscala/collection/Iterator;Lscala/Function1;)Z
Method	scala/collection/Iterator$class.exists:(Lscala/collection/Iterator;Lscala/Function1;)Z
Asciz	forall;
NameAndType	forall:(Lscala/collection/Iterator;Lscala/Function1;)Z
Method	scala/collection/Iterator$class.forall:(Lscala/collection/Iterator;Lscala/Function1;)Z
Asciz	foreach;
Asciz	(Lscala/Function1;)V;
Asciz	(Lscala/collection/Iterator;Lscala/Function1;)V;
NameAndType	foreach:(Lscala/collection/Iterator;Lscala/Function1;)V
Method	scala/collection/Iterator$class.foreach:(Lscala/collection/Iterator;Lscala/Function1;)V
Asciz	f;
Asciz	zipAll;
Asciz	(Lscala/collection/Iterator;Ljava/lang/Object;Ljava/lang/Object;)Ljava/lang/Object;;
Asciz	(Lscala/collection/Iterator;Lscala/collection/Iterator;Ljava/lang/Object;Ljava/lang/Object;)Ljava/lang/Object;;
NameAndType	zipAll:(Lscala/collection/Iterator;Lscala/collection/Iterator;Ljava/lang/Object;Ljava/lang/Object;)Ljava/lang/Object;
Method	scala/collection/Iterator$class.zipAll:(Lscala/collection/Iterator;Lscala/collection/Iterator;Ljava/lang/Object;Ljava/lang/Object;)Ljava/lang/Object;
Asciz	thisElem;
Asciz	thatElem;
Asciz	zipWithIndex;
NameAndType	zipWithIndex:(Lscala/collection/Iterator;)Ljava/lang/Object;
Method	scala/collection/Iterator$class.zipWithIndex:(Lscala/collection/Iterator;)Ljava/lang/Object;
Asciz	padTo;
Asciz	(ILjava/lang/Object;)Ljava/lang/Object;;
Asciz	(Lscala/collection/Iterator;ILjava/lang/Object;)Ljava/lang/Object;;
NameAndType	padTo:(Lscala/collection/Iterator;ILjava/lang/Object;)Ljava/lang/Object;
Method	scala/collection/Iterator$class.padTo:(Lscala/collection/Iterator;ILjava/lang/Object;)Ljava/lang/Object;
Asciz	zip;
Asciz	(Lscala/collection/Iterator;Lscala/collection/Iterator;)Ljava/lang/Object;;
NameAndType	zip:(Lscala/collection/Iterator;Lscala/collection/Iterator;)Ljava/lang/Object;
Method	scala/collection/Iterator$class.zip:(Lscala/collection/Iterator;Lscala/collection/Iterator;)Ljava/lang/Object;
Asciz	dropWhile;
Asciz	(Lscala/Function1;)Lscala/collection/Iterator;;
Asciz	(Lscala/collection/Iterator;Lscala/Function1;)Lscala/collection/Iterator;;
NameAndType	dropWhile:(Lscala/collection/Iterator;Lscala/Function1;)Lscala/collection/Iterator;
Method	scala/collection/Iterator$class.dropWhile:(Lscala/collection/Iterator;Lscala/Function1;)Lscala/collection/Iterator;
Asciz	partition;
Asciz	(Lscala/Function1;)Lscala/Tuple2;;
Asciz	(Lscala/collection/Iterator;Lscala/Function1;)Lscala/Tuple2;;
NameAndType	partition:(Lscala/collection/Iterator;Lscala/Function1;)Lscala/Tuple2;
Method	scala/collection/Iterator$class.partition:(Lscala/collection/Iterator;Lscala/Function1;)Lscala/Tuple2;
Asciz	takeWhile;
NameAndType	takeWhile:(Lscala/collection/Iterator;Lscala/Function1;)Lscala/collection/Iterator;
Method	scala/collection/Iterator$class.takeWhile:(Lscala/collection/Iterator;Lscala/Function1;)Lscala/collection/Iterator;
Asciz	partialMap;
Asciz	(Lscala/PartialFunction;)Lscala/collection/Iterator;;
Asciz	(Lscala/collection/Iterator;Lscala/PartialFunction;)Lscala/collection/Iterator;;
NameAndType	partialMap:(Lscala/collection/Iterator;Lscala/PartialFunction;)Lscala/collection/Iterator;
Method	scala/collection/Iterator$class.partialMap:(Lscala/collection/Iterator;Lscala/PartialFunction;)Lscala/collection/Iterator;
Asciz	pf;
Asciz	Lscala/PartialFunction;;
Asciz	filterNot;
NameAndType	filterNot:(Lscala/collection/Iterator;Lscala/Function1;)Lscala/collection/Iterator;
Method	scala/collection/Iterator$class.filterNot:(Lscala/collection/Iterator;Lscala/Function1;)Lscala/collection/Iterator;
Asciz	withFilter;
Asciz	(Lscala/Function1;)Lscala/collection/Iterator$WithFilter;;
Asciz	(Lscala/collection/Iterator;Lscala/Function1;)Lscala/collection/Iterator$WithFilter;;
NameAndType	withFilter:(Lscala/collection/Iterator;Lscala/Function1;)Lscala/collection/Iterator$WithFilter;
Method	scala/collection/Iterator$class.withFilter:(Lscala/collection/Iterator;Lscala/Function1;)Lscala/collection/Iterator$WithFilter;
Asciz	filter;
NameAndType	filter:(Lscala/collection/Iterator;Lscala/Function1;)Lscala/collection/Iterator;
Method	scala/collection/Iterator$class.filter:(Lscala/collection/Iterator;Lscala/Function1;)Lscala/collection/Iterator;
Asciz	flatMap;
NameAndType	flatMap:(Lscala/collection/Iterator;Lscala/Function1;)Lscala/collection/Iterator;
Method	scala/collection/Iterator$class.flatMap:(Lscala/collection/Iterator;Lscala/Function1;)Lscala/collection/Iterator;
Asciz	$plus$plus;
Asciz	(Lscala/Function0;)Lscala/collection/Iterator;;
Asciz	(Lscala/collection/Iterator;Lscala/Function0;)Lscala/collection/Iterator;;
NameAndType	$plus$plus:(Lscala/collection/Iterator;Lscala/Function0;)Lscala/collection/Iterator;
Method	scala/collection/Iterator$class.$plus$plus:(Lscala/collection/Iterator;Lscala/Function0;)Lscala/collection/Iterator;
Asciz	Lscala/Function0;;
Asciz	map;
NameAndType	map:(Lscala/collection/Iterator;Lscala/Function1;)Lscala/collection/Iterator;
Method	scala/collection/Iterator$class.map:(Lscala/collection/Iterator;Lscala/Function1;)Lscala/collection/Iterator;
Asciz	slice;
Asciz	(II)Lscala/collection/Iterator;;
Asciz	(Lscala/collection/Iterator;II)Lscala/collection/Iterator;;
NameAndType	slice:(Lscala/collection/Iterator;II)Lscala/collection/Iterator;
Method	scala/collection/Iterator$class.slice:(Lscala/collection/Iterator;II)Lscala/collection/Iterator;
Asciz	until;
Asciz	drop;
Asciz	(I)Lscala/collection/Iterator;;
Asciz	(Lscala/collection/Iterator;I)Lscala/collection/Iterator;;
NameAndType	drop:(Lscala/collection/Iterator;I)Lscala/collection/Iterator;
Method	scala/collection/Iterator$class.drop:(Lscala/collection/Iterator;I)Lscala/collection/Iterator;
Asciz	n;
Asciz	take;
NameAndType	take:(Lscala/collection/Iterator;I)Lscala/collection/Iterator;
Method	scala/collection/Iterator$class.take:(Lscala/collection/Iterator;I)Lscala/collection/Iterator;
Asciz	productElements;
Asciz	()Lscala/collection/Iterator;;
Asciz	(Lscala/Product;)Lscala/collection/Iterator;;
NameAndType	productElements:(Lscala/Product;)Lscala/collection/Iterator;
Method	scala/Product$class.productElements:(Lscala/Product;)Lscala/collection/Iterator;
Asciz	productIterator;
NameAndType	productIterator:(Lscala/Product;)Lscala/collection/Iterator;
Method	scala/Product$class.productIterator:(Lscala/Product;)Lscala/collection/Iterator;
Asciz	<A:Ljava/lang/Object;>Ljava/lang/Object;Lscala/collection/Iterator<TA;>;Lscala/ScalaObject;Lscala/Product;;
Asciz	Scala;
Asciz	InnerClasses;
Asciz	scala/collection/Iterator$WithFilter;
class	scala/collection/Iterator$WithFilter
Asciz	scala/collection/Iterator;
class	scala/collection/Iterator
Asciz	WithFilter;
Asciz	scala/collection/Iterator$GroupedIterator;
class	scala/collection/Iterator$GroupedIterator
Asciz	GroupedIterator;
Asciz	scala/collection/JavaConversions;
class	scala/collection/JavaConversions
Asciz	scala/ScalaObject;
class	scala/ScalaObject
Asciz	scala/Product;
class	scala/Product
Asciz	java/io/Serializable;
class	java/io/Serializable

{
private final java.util.Enumeration underlying;
  Signature: Ljava/util/Enumeration;
  Signature: length = 0x2
   00 05 

public scala.collection.JavaConversions$JEnumerationWrapper(java.util.Enumeration);
  Signature: (Ljava/util/Enumeration;)V
  Code:
   Stack=2, Locals=2, Args_size=2
	aload_0
	aload_1
	putfield	Field underlying:Ljava/util/Enumeration;
	aload_0
	invokespecial	Method java/lang/Object."<init>":()V
	aload_0
	invokestatic	Method scala/collection/Iterator$class.$init$:(Lscala/collection/Iterator;)V
	aload_0
	invokestatic	Method scala/Product$class.$init$:(Lscala/Product;)V
	return
  Labels:
  LocalVariableTable: 
   Start  Length  Slot  Name   Signature
   0      18      0    this       Lscala/collection/JavaConversions$JEnumerationWrapper;
   0      18      1    underlying       Ljava/util/Enumeration;

  Signature: length = 0x2
   00 22 

private final boolean gd3$1(java.util.Enumeration);
  Signature: (Ljava/util/Enumeration;)Z
  Code:
   Stack=2, Locals=3, Args_size=2
	aload_1
	aload_0
	invokevirtual	Method underlying:()Ljava/util/Enumeration;
	astore_2
	dup
	ifnonnull	l1 // aload_2
	pop
	aload_2
	ifnull	l2 // iconst_1
	goto	l3 // iconst_0
l1	aload_2
	invokevirtual	Method java/lang/Object.equals:(Ljava/lang/Object;)Z
	ifeq	l3 // iconst_0
l2	iconst_1
	goto	l4 // ireturn
l3	iconst_0
l4	ireturn
  Labels:
   	l1 = 18 // aload_2
   	l2 = 25 // iconst_1
   	l3 = 29 // iconst_0
   	l4 = 30 // ireturn

public boolean canEqual(java.lang.Object);
  Signature: (Ljava/lang/Object;)Z
  Code:
   Stack=1, Locals=2, Args_size=2
	aload_1
	instanceof	class scala/collection/JavaConversions$JEnumerationWrapper
	ireturn
  Labels:

public java.lang.Object productElement(int);
  Signature: (I)Ljava/lang/Object;
  Code:
   Stack=3, Locals=2, Args_size=2
	iload_1
	iconst_0
	if_icmpne	l1 // iconst_1
	iconst_1
	ifeq	l2 // new
	aload_0
	invokevirtual	Method underlying:()Ljava/util/Enumeration;
	areturn
l2	new	class scala/MatchError
	dup
	iload_1
	invokestatic	Method scala/runtime/BoxesRunTime.boxToInteger:(I)Ljava/lang/Integer;
	invokevirtual	Method java/lang/Object.toString:()Ljava/lang/String;
	invokespecial	Method scala/MatchError."<init>":(Ljava/lang/String;)V
	athrow
l1	iconst_1
	ifeq	l3 // new
	new	class java/lang/IndexOutOfBoundsException
	dup
	iload_1
	invokestatic	Method scala/runtime/BoxesRunTime.boxToInteger:(I)Ljava/lang/Integer;
	invokevirtual	Method java/lang/Object.toString:()Ljava/lang/String;
	invokespecial	Method java/lang/IndexOutOfBoundsException."<init>":(Ljava/lang/String;)V
	athrow
l3	new	class scala/MatchError
	dup
	iload_1
	invokestatic	Method scala/runtime/BoxesRunTime.boxToInteger:(I)Ljava/lang/Integer;
	invokevirtual	Method java/lang/Object.toString:()Ljava/lang/String;
	invokespecial	Method scala/MatchError."<init>":(Ljava/lang/String;)V
	athrow
  Labels:
   	l2 = 14 // new
   	l1 = 29 // iconst_1
   	l3 = 48 // new

public int productArity();
  Signature: ()I
  Code:
   Stack=1, Locals=1, Args_size=1
	iconst_1
	ireturn
  Labels:

public java.lang.String productPrefix();
  Signature: ()Ljava/lang/String;
  Code:
   Stack=1, Locals=1, Args_size=1
	ldc	String JEnumerationWrapper
	areturn
  Labels:

public boolean equals(java.lang.Object);
  Signature: (Ljava/lang/Object;)Z
  Code:
   Stack=3, Locals=4, Args_size=2
	aload_0
	aload_1
	if_acmpeq	l1 // iconst_1
	aload_1
	instanceof	class scala/collection/JavaConversions$JEnumerationWrapper
	ifeq	l2 // iconst_1
	aload_1
	checkcast	class scala/collection/JavaConversions$JEnumerationWrapper
	astore_2
	aload_2
	invokevirtual	Method underlying:()Ljava/util/Enumeration;
	astore_3
	aload_0
	aload_3
	invokespecial	Method gd3$1:(Ljava/util/Enumeration;)Z
	ifeq	l3 // iconst_1
	aload_1
	checkcast	class scala/collection/JavaConversions$JEnumerationWrapper
	aload_0
	invokeinterface	InterfaceMethod scala/Equals.canEqual:(Ljava/lang/Object;)Z
	goto	l4 // ifeq
l3	iconst_1
	ifeq	l5 // new
	iconst_0
	goto	l4 // ifeq
l5	new	class scala/MatchError
	dup
	aload_1
	invokevirtual	Method java/lang/Object.toString:()Ljava/lang/String;
	invokespecial	Method scala/MatchError."<init>":(Ljava/lang/String;)V
	athrow
l2	iconst_1
	ifeq	l6 // new
	iconst_0
l4	ifeq	l7 // iconst_0
l1	iconst_1
	goto	l8 // ireturn
l7	iconst_0
l8	ireturn
l6	new	class scala/MatchError
	dup
	aload_1
	invokevirtual	Method java/lang/Object.toString:()Ljava/lang/String;
	invokespecial	Method scala/MatchError."<init>":(Ljava/lang/String;)V
	athrow
  Labels:
   	l3 = 43 // iconst_1
   	l5 = 51 // new
   	l2 = 63 // iconst_1
   	l4 = 68 // ifeq
   	l1 = 71 // iconst_1
   	l7 = 75 // iconst_0
   	l8 = 76 // ireturn
   	l6 = 77 // new
  LocalVariableTable: 
   Start  Length  Slot  Name   Signature
   0      89      0    this       Lscala/collection/JavaConversions$JEnumerationWrapper;
   17      46      2    temp52       Lscala/collection/JavaConversions$JEnumerationWrapper;
   22      41      3    temp53       Ljava/util/Enumeration;


public int hashCode();
  Signature: ()I
  Code:
   Stack=2, Locals=1, Args_size=1
	getstatic	Field scala/runtime/ScalaRunTime$.MODULE$:Lscala/runtime/ScalaRunTime$;
	aload_0
	invokevirtual	Method scala/runtime/ScalaRunTime$._hashCode:(Lscala/Product;)I
	ireturn
  Labels:

public scala.collection.JavaConversions$JEnumerationWrapper copy(java.util.Enumeration);
  Signature: (Ljava/util/Enumeration;)Lscala/collection/JavaConversions$JEnumerationWrapper;
  Code:
   Stack=3, Locals=2, Args_size=2
	new	class scala/collection/JavaConversions$JEnumerationWrapper
	dup
	aload_1
	invokespecial	Method "<init>":(Ljava/util/Enumeration;)V
	areturn
  Labels:
  LocalVariableTable: 
   Start  Length  Slot  Name   Signature
   0      9      0    this       Lscala/collection/JavaConversions$JEnumerationWrapper;
   0      9      1    underlying       Ljava/util/Enumeration;


public java.lang.Object next();
  Signature: ()Ljava/lang/Object;
  Code:
   Stack=1, Locals=1, Args_size=1
	aload_0
	invokevirtual	Method underlying:()Ljava/util/Enumeration;
	invokeinterface	InterfaceMethod java/util/Enumeration.nextElement:()Ljava/lang/Object;
	areturn
  Labels:
  Signature: length = 0x2
   00 64 

public boolean hasNext();
  Signature: ()Z
  Code:
   Stack=1, Locals=1, Args_size=1
	aload_0
	invokevirtual	Method underlying:()Ljava/util/Enumeration;
	invokeinterface	InterfaceMethod java/util/Enumeration.hasMoreElements:()Z
	ireturn
  Labels:

public java.util.Enumeration underlying();
  Signature: ()Ljava/util/Enumeration;
  Code:
   Stack=1, Locals=1, Args_size=1
	aload_0
	getfield	Field underlying:Ljava/util/Enumeration;
	areturn
  Labels:
  Signature: length = 0x2
   00 6A 

public java.util.Enumeration copy$default$1();
  Signature: ()Ljava/util/Enumeration;
  Code:
   Stack=1, Locals=1, Args_size=1
	aload_0
	invokevirtual	Method underlying:()Ljava/util/Enumeration;
	areturn
  Labels:

public int sliding$default$2();
  Signature: ()I
  Code:
   Stack=1, Locals=1, Args_size=1
	aload_0
	invokestatic	Method scala/collection/Iterator$class.sliding$default$2:(Lscala/collection/Iterator;)I
	ireturn
  Labels:

public void readInto(java.lang.Object);
  Signature: (Ljava/lang/Object;)V
  Code:
   Stack=2, Locals=2, Args_size=2
	aload_0
	aload_1
	invokestatic	Method scala/collection/Iterator$class.readInto:(Lscala/collection/Iterator;Ljava/lang/Object;)V
	return
  Labels:
  LocalVariableTable: 
   Start  Length  Slot  Name   Signature
   0      6      0    this       Lscala/collection/JavaConversions$JEnumerationWrapper;
   0      6      1    xs       Ljava/lang/Object;


public void readInto(java.lang.Object, int);
  Signature: (Ljava/lang/Object;I)V
  Code:
   Stack=3, Locals=3, Args_size=3
	aload_0
	aload_1
	iload_2
	invokestatic	Method scala/collection/Iterator$class.readInto:(Lscala/collection/Iterator;Ljava/lang/Object;I)V
	return
  Labels:
  LocalVariableTable: 
   Start  Length  Slot  Name   Signature
   0      7      0    this       Lscala/collection/JavaConversions$JEnumerationWrapper;
   0      7      1    xs       Ljava/lang/Object;
   0      7      2    start       I


public void readInto(java.lang.Object, int, int);
  Signature: (Ljava/lang/Object;II)V
  Code:
   Stack=4, Locals=4, Args_size=4
	aload_0
	aload_1
	iload_2
	iload_3
	invokestatic	Method scala/collection/Iterator$class.readInto:(Lscala/collection/Iterator;Ljava/lang/Object;II)V
	return
  Labels:
  LocalVariableTable: 
   Start  Length  Slot  Name   Signature
   0      8      0    this       Lscala/collection/JavaConversions$JEnumerationWrapper;
   0      8      1    xs       Ljava/lang/Object;
   0      8      2    start       I
   0      8      3    sz       I


public java.lang.Object counted();
  Signature: ()Ljava/lang/Object;
  Code:
   Stack=1, Locals=1, Args_size=1
	aload_0
	invokestatic	Method scala/collection/Iterator$class.counted:(Lscala/collection/Iterator;)Ljava/lang/Object;
	areturn
  Labels:

public scala.collection.Seq collect();
  Signature: ()Lscala/collection/Seq;
  Code:
   Stack=1, Locals=1, Args_size=1
	aload_0
	invokestatic	Method scala/collection/Iterator$class.collect:(Lscala/collection/Iterator;)Lscala/collection/Seq;
	areturn
  Labels:

public int findIndexOf(scala.Function1);
  Signature: (Lscala/Function1;)I
  Code:
   Stack=2, Locals=2, Args_size=2
	aload_0
	aload_1
	invokestatic	Method scala/collection/Iterator$class.findIndexOf:(Lscala/collection/Iterator;Lscala/Function1;)I
	ireturn
  Labels:
  LocalVariableTable: 
   Start  Length  Slot  Name   Signature
   0      6      0    this       Lscala/collection/JavaConversions$JEnumerationWrapper;
   0      6      1    p       Lscala/Function1;


public scala.collection.Iterator append(scala.collection.Iterator);
  Signature: (Lscala/collection/Iterator;)Lscala/collection/Iterator;
  Code:
   Stack=2, Locals=2, Args_size=2
	aload_0
	aload_1
	invokestatic	Method scala/collection/Iterator$class.append:(Lscala/collection/Iterator;Lscala/collection/Iterator;)Lscala/collection/Iterator;
	areturn
  Labels:
  LocalVariableTable: 
   Start  Length  Slot  Name   Signature
   0      6      0    this       Lscala/collection/JavaConversions$JEnumerationWrapper;
   0      6      1    that       Lscala/collection/Iterator;


public java.lang.String toString();
  Signature: ()Ljava/lang/String;
  Code:
   Stack=1, Locals=1, Args_size=1
	aload_0
	invokestatic	Method scala/collection/Iterator$class.toString:(Lscala/collection/Iterator;)Ljava/lang/String;
	areturn
  Labels:

public scala.collection.mutable.StringBuilder addString(scala.collection.mutable.StringBuilder);
  Signature: (Lscala/collection/mutable/StringBuilder;)Lscala/collection/mutable/StringBuilder;
  Code:
   Stack=2, Locals=2, Args_size=2
	aload_0
	aload_1
	invokestatic	Method scala/collection/Iterator$class.addString:(Lscala/collection/Iterator;Lscala/collection/mutable/StringBuilder;)Lscala/collection/mutable/StringBuilder;
	areturn
  Labels:
  LocalVariableTable: 
   Start  Length  Slot  Name   Signature
   0      6      0    this       Lscala/collection/JavaConversions$JEnumerationWrapper;
   0      6      1    buf       Lscala/collection/mutable/StringBuilder;


public scala.collection.mutable.StringBuilder addString(scala.collection.mutable.StringBuilder, java.lang.String);
  Signature: (Lscala/collection/mutable/StringBuilder;Ljava/lang/String;)Lscala/collection/mutable/StringBuilder;
  Code:
   Stack=3, Locals=3, Args_size=3
	aload_0
	aload_1
	aload_2
	invokestatic	Method scala/collection/Iterator$class.addString:(Lscala/collection/Iterator;Lscala/collection/mutable/StringBuilder;Ljava/lang/String;)Lscala/collection/mutable/StringBuilder;
	areturn
  Labels:
  LocalVariableTable: 
   Start  Length  Slot  Name   Signature
   0      7      0    this       Lscala/collection/JavaConversions$JEnumerationWrapper;
   0      7      1    buf       Lscala/collection/mutable/StringBuilder;
   0      7      2    sep       Ljava/lang/String;


public scala.collection.mutable.StringBuilder addString(scala.collection.mutable.StringBuilder, java.lang.String, java.lang.String, java.lang.String);
  Signature: (Lscala/collection/mutable/StringBuilder;Ljava/lang/String;Ljava/lang/String;Ljava/lang/String;)Lscala/collection/mutable/StringBuilder;
  Code:
   Stack=5, Locals=5, Args_size=5
	aload_0
	aload_1
	aload_2
	aload_3
	aload	4
	invokestatic	Method scala/collection/Iterator$class.addString:(Lscala/collection/Iterator;Lscala/collection/mutable/StringBuilder;Ljava/lang/String;Ljava/lang/String;Ljava/lang/String;)Lscala/collection/mutable/StringBuilder;
	areturn
  Labels:
  LocalVariableTable: 
   Start  Length  Slot  Name   Signature
   0      10      0    this       Lscala/collection/JavaConversions$JEnumerationWrapper;
   0      10      1    buf       Lscala/collection/mutable/StringBuilder;
   0      10      2    start       Ljava/lang/String;
   0      10      3    sep       Ljava/lang/String;
   0      10      4    end       Ljava/lang/String;


public java.lang.String mkString();
  Signature: ()Ljava/lang/String;
  Code:
   Stack=1, Locals=1, Args_size=1
	aload_0
	invokestatic	Method scala/collection/Iterator$class.mkString:(Lscala/collection/Iterator;)Ljava/lang/String;
	areturn
  Labels:

public java.lang.String mkString(java.lang.String);
  Signature: (Ljava/lang/String;)Ljava/lang/String;
  Code:
   Stack=2, Locals=2, Args_size=2
	aload_0
	aload_1
	invokestatic	Method scala/collection/Iterator$class.mkString:(Lscala/collection/Iterator;Ljava/lang/String;)Ljava/lang/String;
	areturn
  Labels:
  LocalVariableTable: 
   Start  Length  Slot  Name   Signature
   0      6      0    this       Lscala/collection/JavaConversions$JEnumerationWrapper;
   0      6      1    sep       Ljava/lang/String;


public java.lang.String mkString(java.lang.String, java.lang.String, java.lang.String);
  Signature: (Ljava/lang/String;Ljava/lang/String;Ljava/lang/String;)Ljava/lang/String;
  Code:
   Stack=4, Locals=4, Args_size=4
	aload_0
	aload_1
	aload_2
	aload_3
	invokestatic	Method scala/collection/Iterator$class.mkString:(Lscala/collection/Iterator;Ljava/lang/String;Ljava/lang/String;Ljava/lang/String;)Ljava/lang/String;
	areturn
  Labels:
  LocalVariableTable: 
   Start  Length  Slot  Name   Signature
   0      8      0    this       Lscala/collection/JavaConversions$JEnumerationWrapper;
   0      8      1    start       Ljava/lang/String;
   0      8      2    sep       Ljava/lang/String;
   0      8      3    end       Ljava/lang/String;


public boolean sameElements(scala.collection.Iterator);
  Signature: (Lscala/collection/Iterator;)Z
  Code:
   Stack=2, Locals=2, Args_size=2
	aload_0
	aload_1
	invokestatic	Method scala/collection/Iterator$class.sameElements:(Lscala/collection/Iterator;Lscala/collection/Iterator;)Z
	ireturn
  Labels:
  LocalVariableTable: 
   Start  Length  Slot  Name   Signature
   0      6      0    this       Lscala/collection/JavaConversions$JEnumerationWrapper;
   0      6      1    that       Lscala/collection/Iterator;


public scala.collection.Seq toSeq();
  Signature: ()Lscala/collection/Seq;
  Code:
   Stack=1, Locals=1, Args_size=1
	aload_0
	invokestatic	Method scala/collection/Iterator$class.toSeq:(Lscala/collection/Iterator;)Lscala/collection/Seq;
	areturn
  Labels:

public scala.collection.immutable.Stream toStream();
  Signature: ()Lscala/collection/immutable/Stream;
  Code:
   Stack=1, Locals=1, Args_size=1
	aload_0
	invokestatic	Method scala/collection/Iterator$class.toStream:(Lscala/collection/Iterator;)Lscala/collection/immutable/Stream;
	areturn
  Labels:

public scala.collection.immutable.List toList();
  Signature: ()Lscala/collection/immutable/List;
  Code:
   Stack=1, Locals=1, Args_size=1
	aload_0
	invokestatic	Method scala/collection/Iterator$class.toList:(Lscala/collection/Iterator;)Lscala/collection/immutable/List;
	areturn
  Labels:

public void copyToBuffer(scala.collection.mutable.Buffer);
  Signature: (Lscala/collection/mutable/Buffer;)V
  Code:
   Stack=2, Locals=2, Args_size=2
	aload_0
	aload_1
	invokestatic	Method scala/collection/Iterator$class.copyToBuffer:(Lscala/collection/Iterator;Lscala/collection/mutable/Buffer;)V
	return
  Labels:
  LocalVariableTable: 
   Start  Length  Slot  Name   Signature
   0      6      0    this       Lscala/collection/JavaConversions$JEnumerationWrapper;
   0      6      1    dest       Lscala/collection/mutable/Buffer;


public void copyToArray(java.lang.Object);
  Signature: (Ljava/lang/Object;)V
  Code:
   Stack=2, Locals=2, Args_size=2
	aload_0
	aload_1
	invokestatic	Method scala/collection/Iterator$class.copyToArray:(Lscala/collection/Iterator;Ljava/lang/Object;)V
	return
  Labels:
  LocalVariableTable: 
   Start  Length  Slot  Name   Signature
   0      6      0    this       Lscala/collection/JavaConversions$JEnumerationWrapper;
   0      6      1    xs       Ljava/lang/Object;


public void copyToArray(java.lang.Object, int);
  Signature: (Ljava/lang/Object;I)V
  Code:
   Stack=3, Locals=3, Args_size=3
	aload_0
	aload_1
	iload_2
	invokestatic	Method scala/collection/Iterator$class.copyToArray:(Lscala/collection/Iterator;Ljava/lang/Object;I)V
	return
  Labels:
  LocalVariableTable: 
   Start  Length  Slot  Name   Signature
   0      7      0    this       Lscala/collection/JavaConversions$JEnumerationWrapper;
   0      7      1    xs       Ljava/lang/Object;
   0      7      2    start       I


public void copyToArray(java.lang.Object, int, int);
  Signature: (Ljava/lang/Object;II)V
  Code:
   Stack=4, Locals=4, Args_size=4
	aload_0
	aload_1
	iload_2
	iload_3
	invokestatic	Method scala/collection/Iterator$class.copyToArray:(Lscala/collection/Iterator;Ljava/lang/Object;II)V
	return
  Labels:
  LocalVariableTable: 
   Start  Length  Slot  Name   Signature
   0      8      0    this       Lscala/collection/JavaConversions$JEnumerationWrapper;
   0      8      1    xs       Ljava/lang/Object;
   0      8      2    start       I
   0      8      3    len       I


public java.lang.Object patch(int, scala.collection.Iterator, int);
  Signature: (ILscala/collection/Iterator;I)Ljava/lang/Object;
  Code:
   Stack=4, Locals=4, Args_size=4
	aload_0
	iload_1
	aload_2
	iload_3
	invokestatic	Method scala/collection/Iterator$class.patch:(Lscala/collection/Iterator;ILscala/collection/Iterator;I)Ljava/lang/Object;
	areturn
  Labels:
  LocalVariableTable: 
   Start  Length  Slot  Name   Signature
   0      8      0    this       Lscala/collection/JavaConversions$JEnumerationWrapper;
   0      8      1    from       I
   0      8      2    patchElems       Lscala/collection/Iterator;
   0      8      3    replaced       I


public scala.Tuple2 duplicate();
  Signature: ()Lscala/Tuple2;
  Code:
   Stack=1, Locals=1, Args_size=1
	aload_0
	invokestatic	Method scala/collection/Iterator$class.duplicate:(Lscala/collection/Iterator;)Lscala/Tuple2;
	areturn
  Labels:

public int length();
  Signature: ()I
  Code:
   Stack=1, Locals=1, Args_size=1
	aload_0
	invokestatic	Method scala/collection/Iterator$class.length:(Lscala/collection/Iterator;)I
	ireturn
  Labels:

public scala.collection.Iterator$GroupedIterator sliding(int, int);
  Signature: (II)Lscala/collection/Iterator$GroupedIterator;
  Code:
   Stack=3, Locals=3, Args_size=3
	aload_0
	iload_1
	iload_2
	invokestatic	Method scala/collection/Iterator$class.sliding:(Lscala/collection/Iterator;II)Lscala/collection/Iterator$GroupedIterator;
	areturn
  Labels:
  LocalVariableTable: 
   Start  Length  Slot  Name   Signature
   0      7      0    this       Lscala/collection/JavaConversions$JEnumerationWrapper;
   0      7      1    size       I
   0      7      2    step       I

  Signature: length = 0x2
   00 FFFFFFEB 

public scala.collection.Iterator$GroupedIterator grouped(int);
  Signature: (I)Lscala/collection/Iterator$GroupedIterator;
  Code:
   Stack=2, Locals=2, Args_size=2
	aload_0
	iload_1
	invokestatic	Method scala/collection/Iterator$class.grouped:(Lscala/collection/Iterator;I)Lscala/collection/Iterator$GroupedIterator;
	areturn
  Labels:
  LocalVariableTable: 
   Start  Length  Slot  Name   Signature
   0      6      0    this       Lscala/collection/JavaConversions$JEnumerationWrapper;
   0      6      1    size       I

  Signature: length = 0x2
   00 FFFFFFF2 

public java.lang.Object buffered();
  Signature: ()Ljava/lang/Object;
  Code:
   Stack=1, Locals=1, Args_size=1
	aload_0
	invokestatic	Method scala/collection/Iterator$class.buffered:(Lscala/collection/Iterator;)Ljava/lang/Object;
	areturn
  Labels:

public scala.Option reduceRightOption(scala.Function2);
  Signature: (Lscala/Function2;)Lscala/Option;
  Code:
   Stack=2, Locals=2, Args_size=2
	aload_0
	aload_1
	invokestatic	Method scala/collection/Iterator$class.reduceRightOption:(Lscala/collection/Iterator;Lscala/Function2;)Lscala/Option;
	areturn
  Labels:
  LocalVariableTable: 
   Start  Length  Slot  Name   Signature
   0      6      0    this       Lscala/collection/JavaConversions$JEnumerationWrapper;
   0      6      1    op       Lscala/Function2;


public scala.Option reduceLeftOption(scala.Function2);
  Signature: (Lscala/Function2;)Lscala/Option;
  Code:
   Stack=2, Locals=2, Args_size=2
	aload_0
	aload_1
	invokestatic	Method scala/collection/Iterator$class.reduceLeftOption:(Lscala/collection/Iterator;Lscala/Function2;)Lscala/Option;
	areturn
  Labels:
  LocalVariableTable: 
   Start  Length  Slot  Name   Signature
   0      6      0    this       Lscala/collection/JavaConversions$JEnumerationWrapper;
   0      6      1    op       Lscala/Function2;


public java.lang.Object reduceRight(scala.Function2);
  Signature: (Lscala/Function2;)Ljava/lang/Object;
  Code:
   Stack=2, Locals=2, Args_size=2
	aload_0
	aload_1
	invokestatic	Method scala/collection/Iterator$class.reduceRight:(Lscala/collection/Iterator;Lscala/Function2;)Ljava/lang/Object;
	areturn
  Labels:
  LocalVariableTable: 
   Start  Length  Slot  Name   Signature
   0      6      0    this       Lscala/collection/JavaConversions$JEnumerationWrapper;
   0      6      1    op       Lscala/Function2;


public java.lang.Object reduceLeft(scala.Function2);
  Signature: (Lscala/Function2;)Ljava/lang/Object;
  Code:
   Stack=2, Locals=2, Args_size=2
	aload_0
	aload_1
	invokestatic	Method scala/collection/Iterator$class.reduceLeft:(Lscala/collection/Iterator;Lscala/Function2;)Ljava/lang/Object;
	areturn
  Labels:
  LocalVariableTable: 
   Start  Length  Slot  Name   Signature
   0      6      0    this       Lscala/collection/JavaConversions$JEnumerationWrapper;
   0      6      1    op       Lscala/Function2;


public java.lang.Object $colon$bslash(java.lang.Object, scala.Function2);
  Signature: (Ljava/lang/Object;Lscala/Function2;)Ljava/lang/Object;
  Code:
   Stack=3, Locals=3, Args_size=3
	aload_0
	aload_1
	aload_2
	invokestatic	Method scala/collection/Iterator$class.$colon$bslash:(Lscala/collection/Iterator;Ljava/lang/Object;Lscala/Function2;)Ljava/lang/Object;
	areturn
  Labels:
  LocalVariableTable: 
   Start  Length  Slot  Name   Signature
   0      7      0    this       Lscala/collection/JavaConversions$JEnumerationWrapper;
   0      7      1    z       Ljava/lang/Object;
   0      7      2    op       Lscala/Function2;


public java.lang.Object $div$colon(java.lang.Object, scala.Function2);
  Signature: (Ljava/lang/Object;Lscala/Function2;)Ljava/lang/Object;
  Code:
   Stack=3, Locals=3, Args_size=3
	aload_0
	aload_1
	aload_2
	invokestatic	Method scala/collection/Iterator$class.$div$colon:(Lscala/collection/Iterator;Ljava/lang/Object;Lscala/Function2;)Ljava/lang/Object;
	areturn
  Labels:
  LocalVariableTable: 
   Start  Length  Slot  Name   Signature
   0      7      0    this       Lscala/collection/JavaConversions$JEnumerationWrapper;
   0      7      1    z       Ljava/lang/Object;
   0      7      2    op       Lscala/Function2;


public java.lang.Object foldRight(java.lang.Object, scala.Function2);
  Signature: (Ljava/lang/Object;Lscala/Function2;)Ljava/lang/Object;
  Code:
   Stack=3, Locals=3, Args_size=3
	aload_0
	aload_1
	aload_2
	invokestatic	Method scala/collection/Iterator$class.foldRight:(Lscala/collection/Iterator;Ljava/lang/Object;Lscala/Function2;)Ljava/lang/Object;
	areturn
  Labels:
  LocalVariableTable: 
   Start  Length  Slot  Name   Signature
   0      7      0    this       Lscala/collection/JavaConversions$JEnumerationWrapper;
   0      7      1    z       Ljava/lang/Object;
   0      7      2    op       Lscala/Function2;


public java.lang.Object foldLeft(java.lang.Object, scala.Function2);
  Signature: (Ljava/lang/Object;Lscala/Function2;)Ljava/lang/Object;
  Code:
   Stack=3, Locals=3, Args_size=3
	aload_0
	aload_1
	aload_2
	invokestatic	Method scala/collection/Iterator$class.foldLeft:(Lscala/collection/Iterator;Ljava/lang/Object;Lscala/Function2;)Ljava/lang/Object;
	areturn
  Labels:
  LocalVariableTable: 
   Start  Length  Slot  Name   Signature
   0      7      0    this       Lscala/collection/JavaConversions$JEnumerationWrapper;
   0      7      1    z       Ljava/lang/Object;
   0      7      2    op       Lscala/Function2;


public int indexOf(java.lang.Object);
  Signature: (Ljava/lang/Object;)I
  Code:
   Stack=2, Locals=2, Args_size=2
	aload_0
	aload_1
	invokestatic	Method scala/collection/Iterator$class.indexOf:(Lscala/collection/Iterator;Ljava/lang/Object;)I
	ireturn
  Labels:
  LocalVariableTable: 
   Start  Length  Slot  Name   Signature
   0      6      0    this       Lscala/collection/JavaConversions$JEnumerationWrapper;
   0      6      1    elem       Ljava/lang/Object;


public int indexWhere(scala.Function1);
  Signature: (Lscala/Function1;)I
  Code:
   Stack=2, Locals=2, Args_size=2
	aload_0
	aload_1
	invokestatic	Method scala/collection/Iterator$class.indexWhere:(Lscala/collection/Iterator;Lscala/Function1;)I
	ireturn
  Labels:
  LocalVariableTable: 
   Start  Length  Slot  Name   Signature
   0      6      0    this       Lscala/collection/JavaConversions$JEnumerationWrapper;
   0      6      1    p       Lscala/Function1;


public scala.Option find(scala.Function1);
  Signature: (Lscala/Function1;)Lscala/Option;
  Code:
   Stack=2, Locals=2, Args_size=2
	aload_0
	aload_1
	invokestatic	Method scala/collection/Iterator$class.find:(Lscala/collection/Iterator;Lscala/Function1;)Lscala/Option;
	areturn
  Labels:
  LocalVariableTable: 
   Start  Length  Slot  Name   Signature
   0      6      0    this       Lscala/collection/JavaConversions$JEnumerationWrapper;
   0      6      1    p       Lscala/Function1;


public boolean contains(java.lang.Object);
  Signature: (Ljava/lang/Object;)Z
  Code:
   Stack=2, Locals=2, Args_size=2
	aload_0
	aload_1
	invokestatic	Method scala/collection/Iterator$class.contains:(Lscala/collection/Iterator;Ljava/lang/Object;)Z
	ireturn
  Labels:
  LocalVariableTable: 
   Start  Length  Slot  Name   Signature
   0      6      0    this       Lscala/collection/JavaConversions$JEnumerationWrapper;
   0      6      1    elem       Ljava/lang/Object;


public boolean exists(scala.Function1);
  Signature: (Lscala/Function1;)Z
  Code:
   Stack=2, Locals=2, Args_size=2
	aload_0
	aload_1
	invokestatic	Method scala/collection/Iterator$class.exists:(Lscala/collection/Iterator;Lscala/Function1;)Z
	ireturn
  Labels:
  LocalVariableTable: 
   Start  Length  Slot  Name   Signature
   0      6      0    this       Lscala/collection/JavaConversions$JEnumerationWrapper;
   0      6      1    p       Lscala/Function1;


public boolean forall(scala.Function1);
  Signature: (Lscala/Function1;)Z
  Code:
   Stack=2, Locals=2, Args_size=2
	aload_0
	aload_1
	invokestatic	Method scala/collection/Iterator$class.forall:(Lscala/collection/Iterator;Lscala/Function1;)Z
	ireturn
  Labels:
  LocalVariableTable: 
   Start  Length  Slot  Name   Signature
   0      6      0    this       Lscala/collection/JavaConversions$JEnumerationWrapper;
   0      6      1    p       Lscala/Function1;


public void foreach(scala.Function1);
  Signature: (Lscala/Function1;)V
  Code:
   Stack=2, Locals=2, Args_size=2
	aload_0
	aload_1
	invokestatic	Method scala/collection/Iterator$class.foreach:(Lscala/collection/Iterator;Lscala/Function1;)V
	return
  Labels:
  LocalVariableTable: 
   Start  Length  Slot  Name   Signature
   0      6      0    this       Lscala/collection/JavaConversions$JEnumerationWrapper;
   0      6      1    f       Lscala/Function1;


public java.lang.Object zipAll(scala.collection.Iterator, java.lang.Object, java.lang.Object);
  Signature: (Lscala/collection/Iterator;Ljava/lang/Object;Ljava/lang/Object;)Ljava/lang/Object;
  Code:
   Stack=4, Locals=4, Args_size=4
	aload_0
	aload_1
	aload_2
	aload_3
	invokestatic	Method scala/collection/Iterator$class.zipAll:(Lscala/collection/Iterator;Lscala/collection/Iterator;Ljava/lang/Object;Ljava/lang/Object;)Ljava/lang/Object;
	areturn
  Labels:
  LocalVariableTable: 
   Start  Length  Slot  Name   Signature
   0      8      0    this       Lscala/collection/JavaConversions$JEnumerationWrapper;
   0      8      1    that       Lscala/collection/Iterator;
   0      8      2    thisElem       Ljava/lang/Object;
   0      8      3    thatElem       Ljava/lang/Object;


public java.lang.Object zipWithIndex();
  Signature: ()Ljava/lang/Object;
  Code:
   Stack=1, Locals=1, Args_size=1
	aload_0
	invokestatic	Method scala/collection/Iterator$class.zipWithIndex:(Lscala/collection/Iterator;)Ljava/lang/Object;
	areturn
  Labels:

public java.lang.Object padTo(int, java.lang.Object);
  Signature: (ILjava/lang/Object;)Ljava/lang/Object;
  Code:
   Stack=3, Locals=3, Args_size=3
	aload_0
	iload_1
	aload_2
	invokestatic	Method scala/collection/Iterator$class.padTo:(Lscala/collection/Iterator;ILjava/lang/Object;)Ljava/lang/Object;
	areturn
  Labels:
  LocalVariableTable: 
   Start  Length  Slot  Name   Signature
   0      7      0    this       Lscala/collection/JavaConversions$JEnumerationWrapper;
   0      7      1    len       I
   0      7      2    elem       Ljava/lang/Object;


public java.lang.Object zip(scala.collection.Iterator);
  Signature: (Lscala/collection/Iterator;)Ljava/lang/Object;
  Code:
   Stack=2, Locals=2, Args_size=2
	aload_0
	aload_1
	invokestatic	Method scala/collection/Iterator$class.zip:(Lscala/collection/Iterator;Lscala/collection/Iterator;)Ljava/lang/Object;
	areturn
  Labels:
  LocalVariableTable: 
   Start  Length  Slot  Name   Signature
   0      6      0    this       Lscala/collection/JavaConversions$JEnumerationWrapper;
   0      6      1    that       Lscala/collection/Iterator;


public scala.collection.Iterator dropWhile(scala.Function1);
  Signature: (Lscala/Function1;)Lscala/collection/Iterator;
  Code:
   Stack=2, Locals=2, Args_size=2
	aload_0
	aload_1
	invokestatic	Method scala/collection/Iterator$class.dropWhile:(Lscala/collection/Iterator;Lscala/Function1;)Lscala/collection/Iterator;
	areturn
  Labels:
  LocalVariableTable: 
   Start  Length  Slot  Name   Signature
   0      6      0    this       Lscala/collection/JavaConversions$JEnumerationWrapper;
   0      6      1    p       Lscala/Function1;


public scala.Tuple2 partition(scala.Function1);
  Signature: (Lscala/Function1;)Lscala/Tuple2;
  Code:
   Stack=2, Locals=2, Args_size=2
	aload_0
	aload_1
	invokestatic	Method scala/collection/Iterator$class.partition:(Lscala/collection/Iterator;Lscala/Function1;)Lscala/Tuple2;
	areturn
  Labels:
  LocalVariableTable: 
   Start  Length  Slot  Name   Signature
   0      6      0    this       Lscala/collection/JavaConversions$JEnumerationWrapper;
   0      6      1    p       Lscala/Function1;


public scala.collection.Iterator takeWhile(scala.Function1);
  Signature: (Lscala/Function1;)Lscala/collection/Iterator;
  Code:
   Stack=2, Locals=2, Args_size=2
	aload_0
	aload_1
	invokestatic	Method scala/collection/Iterator$class.takeWhile:(Lscala/collection/Iterator;Lscala/Function1;)Lscala/collection/Iterator;
	areturn
  Labels:
  LocalVariableTable: 
   Start  Length  Slot  Name   Signature
   0      6      0    this       Lscala/collection/JavaConversions$JEnumerationWrapper;
   0      6      1    p       Lscala/Function1;


public scala.collection.Iterator partialMap(scala.PartialFunction);
  Signature: (Lscala/PartialFunction;)Lscala/collection/Iterator;
  Code:
   Stack=2, Locals=2, Args_size=2
	aload_0
	aload_1
	invokestatic	Method scala/collection/Iterator$class.partialMap:(Lscala/collection/Iterator;Lscala/PartialFunction;)Lscala/collection/Iterator;
	areturn
  Labels:
  LocalVariableTable: 
   Start  Length  Slot  Name   Signature
   0      6      0    this       Lscala/collection/JavaConversions$JEnumerationWrapper;
   0      6      1    pf       Lscala/PartialFunction;


public scala.collection.Iterator filterNot(scala.Function1);
  Signature: (Lscala/Function1;)Lscala/collection/Iterator;
  Code:
   Stack=2, Locals=2, Args_size=2
	aload_0
	aload_1
	invokestatic	Method scala/collection/Iterator$class.filterNot:(Lscala/collection/Iterator;Lscala/Function1;)Lscala/collection/Iterator;
	areturn
  Labels:
  LocalVariableTable: 
   Start  Length  Slot  Name   Signature
   0      6      0    this       Lscala/collection/JavaConversions$JEnumerationWrapper;
   0      6      1    p       Lscala/Function1;


public scala.collection.Iterator$WithFilter withFilter(scala.Function1);
  Signature: (Lscala/Function1;)Lscala/collection/Iterator$WithFilter;
  Code:
   Stack=2, Locals=2, Args_size=2
	aload_0
	aload_1
	invokestatic	Method scala/collection/Iterator$class.withFilter:(Lscala/collection/Iterator;Lscala/Function1;)Lscala/collection/Iterator$WithFilter;
	areturn
  Labels:
  LocalVariableTable: 
   Start  Length  Slot  Name   Signature
   0      6      0    this       Lscala/collection/JavaConversions$JEnumerationWrapper;
   0      6      1    p       Lscala/Function1;

  Signature: length = 0x2
   01 65 

public scala.collection.Iterator filter(scala.Function1);
  Signature: (Lscala/Function1;)Lscala/collection/Iterator;
  Code:
   Stack=2, Locals=2, Args_size=2
	aload_0
	aload_1
	invokestatic	Method scala/collection/Iterator$class.filter:(Lscala/collection/Iterator;Lscala/Function1;)Lscala/collection/Iterator;
	areturn
  Labels:
  LocalVariableTable: 
   Start  Length  Slot  Name   Signature
   0      6      0    this       Lscala/collection/JavaConversions$JEnumerationWrapper;
   0      6      1    p       Lscala/Function1;


public scala.collection.Iterator flatMap(scala.Function1);
  Signature: (Lscala/Function1;)Lscala/collection/Iterator;
  Code:
   Stack=2, Locals=2, Args_size=2
	aload_0
	aload_1
	invokestatic	Method scala/collection/Iterator$class.flatMap:(Lscala/collection/Iterator;Lscala/Function1;)Lscala/collection/Iterator;
	areturn
  Labels:
  LocalVariableTable: 
   Start  Length  Slot  Name   Signature
   0      6      0    this       Lscala/collection/JavaConversions$JEnumerationWrapper;
   0      6      1    f       Lscala/Function1;


public scala.collection.Iterator $plus$plus(scala.Function0);
  Signature: (Lscala/Function0;)Lscala/collection/Iterator;
  Code:
   Stack=2, Locals=2, Args_size=2
	aload_0
	aload_1
	invokestatic	Method scala/collection/Iterator$class.$plus$plus:(Lscala/collection/Iterator;Lscala/Function0;)Lscala/collection/Iterator;
	areturn
  Labels:
  LocalVariableTable: 
   Start  Length  Slot  Name   Signature
   0      6      0    this       Lscala/collection/JavaConversions$JEnumerationWrapper;
   0      6      1    that       Lscala/Function0;


public scala.collection.Iterator map(scala.Function1);
  Signature: (Lscala/Function1;)Lscala/collection/Iterator;
  Code:
   Stack=2, Locals=2, Args_size=2
	aload_0
	aload_1
	invokestatic	Method scala/collection/Iterator$class.map:(Lscala/collection/Iterator;Lscala/Function1;)Lscala/collection/Iterator;
	areturn
  Labels:
  LocalVariableTable: 
   Start  Length  Slot  Name   Signature
   0      6      0    this       Lscala/collection/JavaConversions$JEnumerationWrapper;
   0      6      1    f       Lscala/Function1;


public scala.collection.Iterator slice(int, int);
  Signature: (II)Lscala/collection/Iterator;
  Code:
   Stack=3, Locals=3, Args_size=3
	aload_0
	iload_1
	iload_2
	invokestatic	Method scala/collection/Iterator$class.slice:(Lscala/collection/Iterator;II)Lscala/collection/Iterator;
	areturn
  Labels:
  LocalVariableTable: 
   Start  Length  Slot  Name   Signature
   0      7      0    this       Lscala/collection/JavaConversions$JEnumerationWrapper;
   0      7      1    from       I
   0      7      2    until       I


public scala.collection.Iterator drop(int);
  Signature: (I)Lscala/collection/Iterator;
  Code:
   Stack=2, Locals=2, Args_size=2
	aload_0
	iload_1
	invokestatic	Method scala/collection/Iterator$class.drop:(Lscala/collection/Iterator;I)Lscala/collection/Iterator;
	areturn
  Labels:
  LocalVariableTable: 
   Start  Length  Slot  Name   Signature
   0      6      0    this       Lscala/collection/JavaConversions$JEnumerationWrapper;
   0      6      1    n       I


public scala.collection.Iterator take(int);
  Signature: (I)Lscala/collection/Iterator;
  Code:
   Stack=2, Locals=2, Args_size=2
	aload_0
	iload_1
	invokestatic	Method scala/collection/Iterator$class.take:(Lscala/collection/Iterator;I)Lscala/collection/Iterator;
	areturn
  Labels:
  LocalVariableTable: 
   Start  Length  Slot  Name   Signature
   0      6      0    this       Lscala/collection/JavaConversions$JEnumerationWrapper;
   0      6      1    n       I


public scala.collection.Iterator productElements();
  Signature: ()Lscala/collection/Iterator;
  Code:
   Stack=1, Locals=1, Args_size=1
	aload_0
	invokestatic	Method scala/Product$class.productElements:(Lscala/Product;)Lscala/collection/Iterator;
	areturn
  Labels:

public scala.collection.Iterator productIterator();
  Signature: ()Lscala/collection/Iterator;
  Code:
   Stack=1, Locals=1, Args_size=1
	aload_0
	invokestatic	Method scala/Product$class.productIterator:(Lscala/Product;)Lscala/collection/Iterator;
	areturn
  Labels:

}

