Compiled from "JavaConversions.scala"
public final class scala.collection.JavaConversions$JCollectionWrapper$ extends java.lang.Object implements scala.ScalaObject
  SourceFile: "JavaConversions.scala"
  Scala: length = 0x
   
  InnerClass: 
   public JCollectionWrapper=class scala/collection/JavaConversions$JCollectionWrapper of class scala/collection/JavaConversions
  minor version: 0
  major version: 49
  Constant pool:
Asciz	SourceFile;
Asciz	JavaConversions.scala;
Asciz	Scala;
Asciz	MODULE$;
Asciz	Lscala/collection/JavaConversions$JCollectionWrapper$;;
Asciz	<clinit>;
Asciz	()V;
Asciz	Code;
Asciz	scala/collection/JavaConversions$JCollectionWrapper$;
class	scala/collection/JavaConversions$JCollectionWrapper$
Asciz	<init>;
NameAndType	"<init>":()V
Method	scala/collection/JavaConversions$JCollectionWrapper$."<init>":()V
Asciz	unapply;
Asciz	(Lscala/collection/JavaConversions$JCollectionWrapper;)Lscala/Option;;
Asciz	LineNumberTable;
Asciz	java/lang/Object;
class	java/lang/Object
Asciz	equals;
Asciz	(Ljava/lang/Object;)Z;
NameAndType	equals:(Ljava/lang/Object;)Z
Method	java/lang/Object.equals:(Ljava/lang/Object;)Z
Asciz	scala/None$;
class	scala/None$
Asciz	Lscala/None$;;
NameAndType	MODULE$:Lscala/None$;
Field	scala/None$.MODULE$:Lscala/None$;
Asciz	scala/Some;
class	scala/Some
Asciz	scala/collection/JavaConversions$JCollectionWrapper;
class	scala/collection/JavaConversions$JCollectionWrapper
Asciz	underlying;
Asciz	()Ljava/util/Collection;;
NameAndType	underlying:()Ljava/util/Collection;
Method	scala/collection/JavaConversions$JCollectionWrapper.underlying:()Ljava/util/Collection;
Asciz	(Ljava/lang/Object;)V;
NameAndType	"<init>":(Ljava/lang/Object;)V
Method	scala/Some."<init>":(Ljava/lang/Object;)V
Asciz	this;
Asciz	x$0;
Asciz	Lscala/collection/JavaConversions$JCollectionWrapper;;
Asciz	LocalVariableTable;
Asciz	apply;
Asciz	(Ljava/util/Collection;)Lscala/collection/JavaConversions$JCollectionWrapper;;
Asciz	(Ljava/util/Collection;)V;
NameAndType	"<init>":(Ljava/util/Collection;)V
Method	scala/collection/JavaConversions$JCollectionWrapper."<init>":(Ljava/util/Collection;)V
Asciz	Ljava/util/Collection;;
Method	java/lang/Object."<init>":()V
NameAndType	MODULE$:Lscala/collection/JavaConversions$JCollectionWrapper$;
Field	scala/collection/JavaConversions$JCollectionWrapper$.MODULE$:Lscala/collection/JavaConversions$JCollectionWrapper$;
Asciz	InnerClasses;
Asciz	scala/collection/JavaConversions;
class	scala/collection/JavaConversions
Asciz	JCollectionWrapper;
Asciz	scala/ScalaObject;
class	scala/ScalaObject

{
public static final scala.collection.JavaConversions$JCollectionWrapper$ MODULE$;
  Signature: Lscala/collection/JavaConversions$JCollectionWrapper$;

public static {};
  Signature: ()V
  Code:
   Stack=1, Locals=0, Args_size=0
	new	class scala/collection/JavaConversions$JCollectionWrapper$
	invokespecial	Method "<init>":()V
	return
  Labels:

public scala.Option unapply(scala.collection.JavaConversions$JCollectionWrapper);
  Signature: (Lscala/collection/JavaConversions$JCollectionWrapper;)Lscala/Option;
  Code:
   Stack=3, Locals=2, Args_size=2
	aload_1
	dup
	pop
	ifnull	l1 // getstatic
	aload_1
	aconst_null
	invokevirtual	Method java/lang/Object.equals:(Ljava/lang/Object;)Z
	ifeq	l2 // new
l1	getstatic	Field scala/None$.MODULE$:Lscala/None$;
	goto	l3 // areturn
l2	new	class scala/Some
	dup
	aload_1
	invokevirtual	Method scala/collection/JavaConversions$JCollectionWrapper.underlying:()Ljava/util/Collection;
	invokespecial	Method scala/Some."<init>":(Ljava/lang/Object;)V
l3	areturn
  Labels:
   	l1 = 14 // getstatic
   	l2 = 20 // new
   	l3 = 31 // areturn
  LocalVariableTable: 
   Start  Length  Slot  Name   Signature
   0      32      0    this       Lscala/collection/JavaConversions$JCollectionWrapper$;
   0      32      1    x$0       Lscala/collection/JavaConversions$JCollectionWrapper;


public scala.collection.JavaConversions$JCollectionWrapper apply(java.util.Collection);
  Signature: (Ljava/util/Collection;)Lscala/collection/JavaConversions$JCollectionWrapper;
  Code:
   Stack=3, Locals=2, Args_size=2
	new	class scala/collection/JavaConversions$JCollectionWrapper
	dup
	aload_1
	invokespecial	Method scala/collection/JavaConversions$JCollectionWrapper."<init>":(Ljava/util/Collection;)V
	areturn
  Labels:
  LocalVariableTable: 
   Start  Length  Slot  Name   Signature
   0      9      0    this       Lscala/collection/JavaConversions$JCollectionWrapper$;
   0      9      1    underlying       Ljava/util/Collection;


public scala.collection.JavaConversions$JCollectionWrapper$();
  Signature: ()V
  Code:
   Stack=1, Locals=1, Args_size=1
	aload_0
	invokespecial	Method java/lang/Object."<init>":()V
	aload_0
	putstatic	Field MODULE$:Lscala/collection/JavaConversions$JCollectionWrapper$;
	return
  Labels:

}

