Compiled from "JavaConversions.scala"
public class scala.collection.JavaConversions$IteratorWrapper extends java.lang.Object implements java.util.Iterator,java.util.Enumeration,scala.ScalaObject,scala.Product,java.io.Serializable
  SourceFile: "JavaConversions.scala"
  Signature: length = 0x2
   00 79 
  Scala: length = 0x
   
  InnerClass: 
   public #67= #12 of #125; //IteratorWrapper=class scala/collection/JavaConversions$IteratorWrapper of class scala/collection/JavaConversions
  minor version: 0
  major version: 49
  Constant pool:
const #1 = Asciz	SourceFile;
const #2 = Asciz	JavaConversions.scala;
const #3 = Asciz	underlying;
const #4 = Asciz	Lscala/collection/Iterator;;
const #5 = Asciz	Lscala/collection/Iterator<TA;>;;
const #6 = Asciz	Signature;
const #7 = Asciz	<init>;
const #8 = Asciz	(Lscala/collection/Iterator;)V;
const #9 = Asciz	Code;
const #10 = Asciz	LineNumberTable;
const #11 = Asciz	scala/collection/JavaConversions$IteratorWrapper;
const #12 = class	#11;	//  scala/collection/JavaConversions$IteratorWrapper
const #13 = NameAndType	#3:#4;//  underlying:Lscala/collection/Iterator;
const #14 = Field	#12.#13;	//  scala/collection/JavaConversions$IteratorWrapper.underlying:Lscala/collection/Iterator;
const #15 = Asciz	java/lang/Object;
const #16 = class	#15;	//  java/lang/Object
const #17 = Asciz	()V;
const #18 = NameAndType	#7:#17;//  "<init>":()V
const #19 = Method	#16.#18;	//  java/lang/Object."<init>":()V
const #20 = Asciz	scala/Product$class;
const #21 = class	#20;	//  scala/Product$class
const #22 = Asciz	$init$;
const #23 = Asciz	(Lscala/Product;)V;
const #24 = NameAndType	#22:#23;//  $init$:(Lscala/Product;)V
const #25 = Method	#21.#24;	//  scala/Product$class.$init$:(Lscala/Product;)V
const #26 = Asciz	this;
const #27 = Asciz	Lscala/collection/JavaConversions$IteratorWrapper;;
const #28 = Asciz	LocalVariableTable;
const #29 = Asciz	(Lscala/collection/Iterator<TA;>;)V;
const #30 = Asciz	gd1$1;
const #31 = Asciz	(Lscala/collection/Iterator;)Z;
const #32 = Asciz	()Lscala/collection/Iterator;;
const #33 = NameAndType	#3:#32;//  underlying:()Lscala/collection/Iterator;
const #34 = Method	#12.#33;	//  scala/collection/JavaConversions$IteratorWrapper.underlying:()Lscala/collection/Iterator;
const #35 = Asciz	equals;
const #36 = Asciz	(Ljava/lang/Object;)Z;
const #37 = NameAndType	#35:#36;//  equals:(Ljava/lang/Object;)Z
const #38 = Method	#16.#37;	//  java/lang/Object.equals:(Ljava/lang/Object;)Z
const #39 = Asciz	remove;
const #40 = Asciz	()Lscala/runtime/Nothing$;;
const #41 = NameAndType	#39:#40;//  remove:()Lscala/runtime/Nothing$;
const #42 = Method	#12.#41;	//  scala/collection/JavaConversions$IteratorWrapper.remove:()Lscala/runtime/Nothing$;
const #43 = Asciz	canEqual;
const #44 = Asciz	productElement;
const #45 = Asciz	(I)Ljava/lang/Object;;
const #46 = Asciz	scala/MatchError;
const #47 = class	#46;	//  scala/MatchError
const #48 = Asciz	scala/runtime/BoxesRunTime;
const #49 = class	#48;	//  scala/runtime/BoxesRunTime
const #50 = Asciz	boxToInteger;
const #51 = Asciz	(I)Ljava/lang/Integer;;
const #52 = NameAndType	#50:#51;//  boxToInteger:(I)Ljava/lang/Integer;
const #53 = Method	#49.#52;	//  scala/runtime/BoxesRunTime.boxToInteger:(I)Ljava/lang/Integer;
const #54 = Asciz	toString;
const #55 = Asciz	()Ljava/lang/String;;
const #56 = NameAndType	#54:#55;//  toString:()Ljava/lang/String;
const #57 = Method	#16.#56;	//  java/lang/Object.toString:()Ljava/lang/String;
const #58 = Asciz	(Ljava/lang/String;)V;
const #59 = NameAndType	#7:#58;//  "<init>":(Ljava/lang/String;)V
const #60 = Method	#47.#59;	//  scala/MatchError."<init>":(Ljava/lang/String;)V
const #61 = Asciz	java/lang/IndexOutOfBoundsException;
const #62 = class	#61;	//  java/lang/IndexOutOfBoundsException
const #63 = Method	#62.#59;	//  java/lang/IndexOutOfBoundsException."<init>":(Ljava/lang/String;)V
const #64 = Asciz	productArity;
const #65 = Asciz	()I;
const #66 = Asciz	productPrefix;
const #67 = Asciz	IteratorWrapper;
const #68 = String	#67;	//  IteratorWrapper
const #69 = NameAndType	#30:#31;//  gd1$1:(Lscala/collection/Iterator;)Z
const #70 = Method	#12.#69;	//  scala/collection/JavaConversions$IteratorWrapper.gd1$1:(Lscala/collection/Iterator;)Z
const #71 = Asciz	scala/Equals;
const #72 = class	#71;	//  scala/Equals
const #73 = NameAndType	#43:#36;//  canEqual:(Ljava/lang/Object;)Z
const #74 = InterfaceMethod	#72.#73;	//  scala/Equals.canEqual:(Ljava/lang/Object;)Z
const #75 = Asciz	temp44;
const #76 = Asciz	temp45;
const #77 = Asciz	scala/runtime/ScalaRunTime$;
const #78 = class	#77;	//  scala/runtime/ScalaRunTime$
const #79 = Asciz	MODULE$;
const #80 = Asciz	Lscala/runtime/ScalaRunTime$;;
const #81 = NameAndType	#79:#80;//  MODULE$:Lscala/runtime/ScalaRunTime$;
const #82 = Field	#78.#81;	//  scala/runtime/ScalaRunTime$.MODULE$:Lscala/runtime/ScalaRunTime$;
const #83 = Asciz	_toString;
const #84 = Asciz	(Lscala/Product;)Ljava/lang/String;;
const #85 = NameAndType	#83:#84;//  _toString:(Lscala/Product;)Ljava/lang/String;
const #86 = Method	#78.#85;	//  scala/runtime/ScalaRunTime$._toString:(Lscala/Product;)Ljava/lang/String;
const #87 = Asciz	hashCode;
const #88 = Asciz	_hashCode;
const #89 = Asciz	(Lscala/Product;)I;
const #90 = NameAndType	#88:#89;//  _hashCode:(Lscala/Product;)I
const #91 = Method	#78.#90;	//  scala/runtime/ScalaRunTime$._hashCode:(Lscala/Product;)I
const #92 = Asciz	copy;
const #93 = Asciz	(Lscala/collection/Iterator;)Lscala/collection/JavaConversions$IteratorWrapper;;
const #94 = NameAndType	#7:#8;//  "<init>":(Lscala/collection/Iterator;)V
const #95 = Method	#12.#94;	//  scala/collection/JavaConversions$IteratorWrapper."<init>":(Lscala/collection/Iterator;)V
const #96 = Asciz	java/lang/UnsupportedOperationException;
const #97 = class	#96;	//  java/lang/UnsupportedOperationException
const #98 = Method	#97.#18;	//  java/lang/UnsupportedOperationException."<init>":()V
const #99 = Asciz	nextElement;
const #100 = Asciz	()Ljava/lang/Object;;
const #101 = Asciz	scala/collection/Iterator;
const #102 = class	#101;	//  scala/collection/Iterator
const #103 = Asciz	next;
const #104 = NameAndType	#103:#100;//  next:()Ljava/lang/Object;
const #105 = InterfaceMethod	#102.#104;	//  scala/collection/Iterator.next:()Ljava/lang/Object;
const #106 = Asciz	()TA;;
const #107 = Asciz	hasMoreElements;
const #108 = Asciz	()Z;
const #109 = Asciz	hasNext;
const #110 = NameAndType	#109:#108;//  hasNext:()Z
const #111 = InterfaceMethod	#102.#110;	//  scala/collection/Iterator.hasNext:()Z
const #112 = Asciz	()Lscala/collection/Iterator<TA;>;;
const #113 = Asciz	copy$default$1;
const #114 = Asciz	productElements;
const #115 = Asciz	(Lscala/Product;)Lscala/collection/Iterator;;
const #116 = NameAndType	#114:#115;//  productElements:(Lscala/Product;)Lscala/collection/Iterator;
const #117 = Method	#21.#116;	//  scala/Product$class.productElements:(Lscala/Product;)Lscala/collection/Iterator;
const #118 = Asciz	productIterator;
const #119 = NameAndType	#118:#115;//  productIterator:(Lscala/Product;)Lscala/collection/Iterator;
const #120 = Method	#21.#119;	//  scala/Product$class.productIterator:(Lscala/Product;)Lscala/collection/Iterator;
const #121 = Asciz	<A:Ljava/lang/Object;>Ljava/lang/Object;Ljava/util/Iterator<TA;>;Ljava/util/Enumeration<TA;>;Lscala/ScalaObject;Lscala/Product;;
const #122 = Asciz	Scala;
const #123 = Asciz	InnerClasses;
const #124 = Asciz	scala/collection/JavaConversions;
const #125 = class	#124;	//  scala/collection/JavaConversions
const #126 = Asciz	java/util/Iterator;
const #127 = class	#126;	//  java/util/Iterator
const #128 = Asciz	java/util/Enumeration;
const #129 = class	#128;	//  java/util/Enumeration
const #130 = Asciz	scala/ScalaObject;
const #131 = class	#130;	//  scala/ScalaObject
const #132 = Asciz	scala/Product;
const #133 = class	#132;	//  scala/Product
const #134 = Asciz	java/io/Serializable;
const #135 = class	#134;	//  java/io/Serializable

{
public scala.collection.JavaConversions$IteratorWrapper(scala.collection.Iterator);
  Code:
   Stack=2, Locals=2, Args_size=2
   0:	aload_0
   1:	aload_1
   2:	putfield	#14; //Field underlying:Lscala/collection/Iterator;
   5:	aload_0
   6:	invokespecial	#19; //Method java/lang/Object."<init>":()V
   9:	aload_0
   10:	invokestatic	#25; //Method scala/Product$class.$init$:(Lscala/Product;)V
   13:	return
  LineNumberTable: 
   line 312: 0

  LocalVariableTable: 
   Start  Length  Slot  Name   Signature
   0      14      0    this       Lscala/collection/JavaConversions$IteratorWrapper;
   0      14      1    underlying       Lscala/collection/Iterator;

  Signature: length = 0x2
   00 1D 

public void remove();
  Code:
   Stack=1, Locals=1, Args_size=1
   0:	aload_0
   1:	invokevirtual	#42; //Method remove:()Lscala/runtime/Nothing$;
   4:	athrow
  LineNumberTable: 
   line 312: 0


public boolean canEqual(java.lang.Object);
  Code:
   Stack=1, Locals=2, Args_size=2
   0:	aload_1
   1:	instanceof	#12; //class scala/collection/JavaConversions$IteratorWrapper
   4:	ireturn
  LineNumberTable: 
   line 312: 0


public java.lang.Object productElement(int);
  Code:
   Stack=3, Locals=2, Args_size=2
   0:	iload_1
   1:	iconst_0
   2:	if_icmpne	29
   5:	iconst_1
   6:	ifeq	14
   9:	aload_0
   10:	invokevirtual	#34; //Method underlying:()Lscala/collection/Iterator;
   13:	areturn
   14:	new	#47; //class scala/MatchError
   17:	dup
   18:	iload_1
   19:	invokestatic	#53; //Method scala/runtime/BoxesRunTime.boxToInteger:(I)Ljava/lang/Integer;
   22:	invokevirtual	#57; //Method java/lang/Object.toString:()Ljava/lang/String;
   25:	invokespecial	#60; //Method scala/MatchError."<init>":(Ljava/lang/String;)V
   28:	athrow
   29:	iconst_1
   30:	ifeq	48
   33:	new	#62; //class java/lang/IndexOutOfBoundsException
   36:	dup
   37:	iload_1
   38:	invokestatic	#53; //Method scala/runtime/BoxesRunTime.boxToInteger:(I)Ljava/lang/Integer;
   41:	invokevirtual	#57; //Method java/lang/Object.toString:()Ljava/lang/String;
   44:	invokespecial	#63; //Method java/lang/IndexOutOfBoundsException."<init>":(Ljava/lang/String;)V
   47:	athrow
   48:	new	#47; //class scala/MatchError
   51:	dup
   52:	iload_1
   53:	invokestatic	#53; //Method scala/runtime/BoxesRunTime.boxToInteger:(I)Ljava/lang/Integer;
   56:	invokevirtual	#57; //Method java/lang/Object.toString:()Ljava/lang/String;
   59:	invokespecial	#60; //Method scala/MatchError."<init>":(Ljava/lang/String;)V
   62:	athrow
  LineNumberTable: 
   line 312: 0
   line 21: 5
   line 312: 9
   line 21: 29
   line 312: 33


public int productArity();
  Code:
   Stack=1, Locals=1, Args_size=1
   0:	iconst_1
   1:	ireturn
  LineNumberTable: 
   line 312: 0


public java.lang.String productPrefix();
  Code:
   Stack=1, Locals=1, Args_size=1
   0:	ldc	#68; //String IteratorWrapper
   2:	areturn
  LineNumberTable: 
   line 312: 0


public boolean equals(java.lang.Object);
  Code:
   Stack=3, Locals=4, Args_size=2
   0:	aload_0
   1:	aload_1
   2:	if_acmpeq	71
   5:	aload_1
   6:	instanceof	#12; //class scala/collection/JavaConversions$IteratorWrapper
   9:	ifeq	63
   12:	aload_1
   13:	checkcast	#12; //class scala/collection/JavaConversions$IteratorWrapper
   16:	astore_2
   17:	aload_2
   18:	invokevirtual	#34; //Method underlying:()Lscala/collection/Iterator;
   21:	astore_3
   22:	aload_0
   23:	aload_3
   24:	invokespecial	#70; //Method gd1$1:(Lscala/collection/Iterator;)Z
   27:	ifeq	43
   30:	aload_1
   31:	checkcast	#12; //class scala/collection/JavaConversions$IteratorWrapper
   34:	aload_0
   35:	invokeinterface	#74,  2; //InterfaceMethod scala/Equals.canEqual:(Ljava/lang/Object;)Z
   40:	goto	68
   43:	iconst_1
   44:	ifeq	51
   47:	iconst_0
   48:	goto	68
   51:	new	#47; //class scala/MatchError
   54:	dup
   55:	aload_1
   56:	invokevirtual	#57; //Method java/lang/Object.toString:()Ljava/lang/String;
   59:	invokespecial	#60; //Method scala/MatchError."<init>":(Ljava/lang/String;)V
   62:	athrow
   63:	iconst_1
   64:	ifeq	77
   67:	iconst_0
   68:	ifeq	75
   71:	iconst_1
   72:	goto	76
   75:	iconst_0
   76:	ireturn
   77:	new	#47; //class scala/MatchError
   80:	dup
   81:	aload_1
   82:	invokevirtual	#57; //Method java/lang/Object.toString:()Ljava/lang/String;
   85:	invokespecial	#60; //Method scala/MatchError."<init>":(Ljava/lang/String;)V
   88:	athrow
  LineNumberTable: 
   line 312: 0
   line 21: 43
   line 312: 51
   line 21: 63
   line 312: 68

  LocalVariableTable: 
   Start  Length  Slot  Name   Signature
   0      89      0    this       Lscala/collection/JavaConversions$IteratorWrapper;
   17      46      2    temp44       Lscala/collection/JavaConversions$IteratorWrapper;
   22      41      3    temp45       Lscala/collection/Iterator;


public java.lang.String toString();
  Code:
   Stack=2, Locals=1, Args_size=1
   0:	getstatic	#82; //Field scala/runtime/ScalaRunTime$.MODULE$:Lscala/runtime/ScalaRunTime$;
   3:	aload_0
   4:	invokevirtual	#86; //Method scala/runtime/ScalaRunTime$._toString:(Lscala/Product;)Ljava/lang/String;
   7:	areturn
  LineNumberTable: 
   line 312: 0


public int hashCode();
  Code:
   Stack=2, Locals=1, Args_size=1
   0:	getstatic	#82; //Field scala/runtime/ScalaRunTime$.MODULE$:Lscala/runtime/ScalaRunTime$;
   3:	aload_0
   4:	invokevirtual	#91; //Method scala/runtime/ScalaRunTime$._hashCode:(Lscala/Product;)I
   7:	ireturn
  LineNumberTable: 
   line 312: 0


public scala.collection.JavaConversions$IteratorWrapper copy(scala.collection.Iterator);
  Code:
   Stack=3, Locals=2, Args_size=2
   0:	new	#12; //class scala/collection/JavaConversions$IteratorWrapper
   3:	dup
   4:	aload_1
   5:	invokespecial	#95; //Method "<init>":(Lscala/collection/Iterator;)V
   8:	areturn
  LineNumberTable: 
   line 312: 0

  LocalVariableTable: 
   Start  Length  Slot  Name   Signature
   0      9      0    this       Lscala/collection/JavaConversions$IteratorWrapper;
   0      9      1    underlying       Lscala/collection/Iterator;


public scala.runtime.Nothing$ remove();
  Code:
   Stack=2, Locals=1, Args_size=1
   0:	new	#97; //class java/lang/UnsupportedOperationException
   3:	dup
   4:	invokespecial	#98; //Method java/lang/UnsupportedOperationException."<init>":()V
   7:	athrow
  LineNumberTable: 
   line 317: 0


public java.lang.Object nextElement();
  Code:
   Stack=1, Locals=1, Args_size=1
   0:	aload_0
   1:	invokevirtual	#34; //Method underlying:()Lscala/collection/Iterator;
   4:	invokeinterface	#105,  1; //InterfaceMethod scala/collection/Iterator.next:()Ljava/lang/Object;
   9:	areturn
  LineNumberTable: 
   line 316: 0

  Signature: length = 0x2
   00 6A 

public boolean hasMoreElements();
  Code:
   Stack=1, Locals=1, Args_size=1
   0:	aload_0
   1:	invokevirtual	#34; //Method underlying:()Lscala/collection/Iterator;
   4:	invokeinterface	#111,  1; //InterfaceMethod scala/collection/Iterator.hasNext:()Z
   9:	ireturn
  LineNumberTable: 
   line 315: 0


public java.lang.Object next();
  Code:
   Stack=1, Locals=1, Args_size=1
   0:	aload_0
   1:	invokevirtual	#34; //Method underlying:()Lscala/collection/Iterator;
   4:	invokeinterface	#105,  1; //InterfaceMethod scala/collection/Iterator.next:()Ljava/lang/Object;
   9:	areturn
  LineNumberTable: 
   line 314: 0

  Signature: length = 0x2
   00 6A 

public boolean hasNext();
  Code:
   Stack=1, Locals=1, Args_size=1
   0:	aload_0
   1:	invokevirtual	#34; //Method underlying:()Lscala/collection/Iterator;
   4:	invokeinterface	#111,  1; //InterfaceMethod scala/collection/Iterator.hasNext:()Z
   9:	ireturn
  LineNumberTable: 
   line 313: 0


public scala.collection.Iterator underlying();
  Code:
   Stack=1, Locals=1, Args_size=1
   0:	aload_0
   1:	getfield	#14; //Field underlying:Lscala/collection/Iterator;
   4:	areturn
  LineNumberTable: 
   line 312: 0

  Signature: length = 0x2
   00 70 

public scala.collection.Iterator copy$default$1();
  Code:
   Stack=1, Locals=1, Args_size=1
   0:	aload_0
   1:	invokevirtual	#34; //Method underlying:()Lscala/collection/Iterator;
   4:	areturn
  LineNumberTable: 
   line 312: 0


public scala.collection.Iterator productElements();
  Code:
   Stack=1, Locals=1, Args_size=1
   0:	aload_0
   1:	invokestatic	#117; //Method scala/Product$class.productElements:(Lscala/Product;)Lscala/collection/Iterator;
   4:	areturn
  LineNumberTable: 
   line 312: 0


public scala.collection.Iterator productIterator();
  Code:
   Stack=1, Locals=1, Args_size=1
   0:	aload_0
   1:	invokestatic	#120; //Method scala/Product$class.productIterator:(Lscala/Product;)Lscala/collection/Iterator;
   4:	areturn
  LineNumberTable: 
   line 312: 0


}

