Compiled from "JavaConversions.scala"
public class scala.collection.JavaConversions$MutableBufferWrapper extends java.util.AbstractList implements scala.ScalaObject,scala.Product,java.io.Serializable
  SourceFile: "JavaConversions.scala"
  Signature: length = 0x2
   00 77 
  Scala: length = 0x
   
  InnerClass: 
   public MutableBufferWrapper=class scala/collection/JavaConversions$MutableBufferWrapper of class scala/collection/JavaConversions
  minor version: 0
  major version: 49
  Constant pool:
Asciz	SourceFile;
Asciz	JavaConversions.scala;
Asciz	underlying;
Asciz	Lscala/collection/mutable/Buffer;;
Asciz	Lscala/collection/mutable/Buffer<TA;>;;
Asciz	Signature;
Asciz	productIterator;
Asciz	()Lscala/collection/Iterator;;
Asciz	Code;
Asciz	LineNumberTable;
Asciz	scala/Product$class;
class	scala/Product$class
Asciz	(Lscala/Product;)Lscala/collection/Iterator;;
NameAndType	productIterator:(Lscala/Product;)Lscala/collection/Iterator;
Method	scala/Product$class.productIterator:(Lscala/Product;)Lscala/collection/Iterator;
Asciz	productElements;
NameAndType	productElements:(Lscala/Product;)Lscala/collection/Iterator;
Method	scala/Product$class.productElements:(Lscala/Product;)Lscala/collection/Iterator;
Asciz	Deprecated;
Asciz	copy$default$1;
Asciz	()Lscala/collection/mutable/Buffer;;
Asciz	scala/collection/JavaConversions$MutableBufferWrapper;
class	scala/collection/JavaConversions$MutableBufferWrapper
NameAndType	underlying:()Lscala/collection/mutable/Buffer;
Method	scala/collection/JavaConversions$MutableBufferWrapper.underlying:()Lscala/collection/mutable/Buffer;
NameAndType	underlying:Lscala/collection/mutable/Buffer;
Field	scala/collection/JavaConversions$MutableBufferWrapper.underlying:Lscala/collection/mutable/Buffer;
Asciz	()Lscala/collection/mutable/Buffer<TA;>;;
Asciz	size;
Asciz	()I;
Asciz	scala/collection/mutable/BufferLike;
class	scala/collection/mutable/BufferLike
Asciz	length;
NameAndType	length:()I
InterfaceMethod	scala/collection/mutable/BufferLike.length:()I
Asciz	get;
Asciz	(I)Ljava/lang/Object;;
Asciz	apply;
NameAndType	apply:(I)Ljava/lang/Object;
InterfaceMethod	scala/collection/mutable/BufferLike.apply:(I)Ljava/lang/Object;
Asciz	this;
Asciz	Lscala/collection/JavaConversions$MutableBufferWrapper;;
Asciz	i;
Asciz	I;
Asciz	LocalVariableTable;
Asciz	(I)TA;;
Asciz	set;
Asciz	(ILjava/lang/Object;)Ljava/lang/Object;;
Asciz	update;
Asciz	(ILjava/lang/Object;)V;
NameAndType	update:(ILjava/lang/Object;)V
InterfaceMethod	scala/collection/mutable/BufferLike.update:(ILjava/lang/Object;)V
Asciz	elem;
Asciz	Ljava/lang/Object;;
Asciz	p;
Asciz	(ITA;)TA;;
Asciz	add;
Asciz	(Ljava/lang/Object;)Z;
Asciz	scala/Predef$;
class	scala/Predef$
Asciz	MODULE$;
Asciz	Lscala/Predef$;;
NameAndType	MODULE$:Lscala/Predef$;
Field	scala/Predef$.MODULE$:Lscala/Predef$;
Asciz	java/lang/Object;
class	java/lang/Object
Asciz	genericWrapArray;
Asciz	(Ljava/lang/Object;)Lscala/collection/mutable/WrappedArray;;
NameAndType	genericWrapArray:(Ljava/lang/Object;)Lscala/collection/mutable/WrappedArray;
Method	scala/Predef$.genericWrapArray:(Ljava/lang/Object;)Lscala/collection/mutable/WrappedArray;
Asciz	append;
Asciz	(Lscala/collection/Seq;)V;
NameAndType	append:(Lscala/collection/Seq;)V
InterfaceMethod	scala/collection/mutable/BufferLike.append:(Lscala/collection/Seq;)V
Asciz	(TA;)Z;
Asciz	remove;
NameAndType	remove:(I)Ljava/lang/Object;
InterfaceMethod	scala/collection/mutable/BufferLike.remove:(I)Ljava/lang/Object;
Asciz	copy;
Asciz	(Lscala/collection/mutable/Buffer;)Lscala/collection/JavaConversions$MutableBufferWrapper;;
Asciz	<init>;
Asciz	(Lscala/collection/mutable/Buffer;)V;
NameAndType	"<init>":(Lscala/collection/mutable/Buffer;)V
Method	scala/collection/JavaConversions$MutableBufferWrapper."<init>":(Lscala/collection/mutable/Buffer;)V
Asciz	productPrefix;
Asciz	()Ljava/lang/String;;
Asciz	MutableBufferWrapper;
String	MutableBufferWrapper
Asciz	productArity;
Asciz	productElement;
Asciz	java/lang/IndexOutOfBoundsException;
class	java/lang/IndexOutOfBoundsException
Asciz	scala/runtime/BoxesRunTime;
class	scala/runtime/BoxesRunTime
Asciz	boxToInteger;
Asciz	(I)Ljava/lang/Integer;;
NameAndType	boxToInteger:(I)Ljava/lang/Integer;
Method	scala/runtime/BoxesRunTime.boxToInteger:(I)Ljava/lang/Integer;
Asciz	toString;
NameAndType	toString:()Ljava/lang/String;
Method	java/lang/Object.toString:()Ljava/lang/String;
Asciz	(Ljava/lang/String;)V;
NameAndType	"<init>":(Ljava/lang/String;)V
Method	java/lang/IndexOutOfBoundsException."<init>":(Ljava/lang/String;)V
Asciz	productElementName;
Asciz	(I)Ljava/lang/String;;
String	underlying
Asciz	canEqual;
Asciz	java/util/AbstractList;
class	java/util/AbstractList
Asciz	()V;
NameAndType	"<init>":()V
Method	java/util/AbstractList."<init>":()V
Asciz	$init$;
Asciz	(Lscala/Product;)V;
NameAndType	$init$:(Lscala/Product;)V
Method	scala/Product$class.$init$:(Lscala/Product;)V
Asciz	(Lscala/collection/mutable/Buffer<TA;>;)V;
Asciz	<A:Ljava/lang/Object;>Ljava/util/AbstractList<TA;>;Lscala/ScalaObject;Lscala/Product;;
Asciz	Scala;
Asciz	InnerClasses;
Asciz	scala/collection/JavaConversions;
class	scala/collection/JavaConversions
Asciz	scala/ScalaObject;
class	scala/ScalaObject
Asciz	scala/Product;
class	scala/Product
Asciz	java/io/Serializable;
class	java/io/Serializable

{
private final scala.collection.mutable.Buffer underlying;
  Signature: Lscala/collection/mutable/Buffer;
  Signature: length = 0x2
   00 05 

public scala.collection.Iterator productIterator();
  Signature: ()Lscala/collection/Iterator;
  Code:
   Stack=1, Locals=1, Args_size=1
	aload_0
	invokestatic	Method scala/Product$class.productIterator:(Lscala/Product;)Lscala/collection/Iterator;
	areturn
  Labels:

public scala.collection.Iterator productElements();
  Signature: ()Lscala/collection/Iterator;
  Code:
   Stack=1, Locals=1, Args_size=1
	aload_0
	invokestatic	Method scala/Product$class.productElements:(Lscala/Product;)Lscala/collection/Iterator;
	areturn
  Labels:
  Deprecated: true

public scala.collection.mutable.Buffer copy$default$1();
  Signature: ()Lscala/collection/mutable/Buffer;
  Code:
   Stack=1, Locals=1, Args_size=1
	aload_0
	invokevirtual	Method underlying:()Lscala/collection/mutable/Buffer;
	areturn
  Labels:

public scala.collection.mutable.Buffer underlying();
  Signature: ()Lscala/collection/mutable/Buffer;
  Code:
   Stack=1, Locals=1, Args_size=1
	aload_0
	getfield	Field underlying:Lscala/collection/mutable/Buffer;
	areturn
  Labels:
  Signature: length = 0x2
   00 1C 

public int size();
  Signature: ()I
  Code:
   Stack=1, Locals=1, Args_size=1
	aload_0
	invokevirtual	Method underlying:()Lscala/collection/mutable/Buffer;
	invokeinterface	InterfaceMethod scala/collection/mutable/BufferLike.length:()I
	ireturn
  Labels:

public java.lang.Object get(int);
  Signature: (I)Ljava/lang/Object;
  Code:
   Stack=2, Locals=2, Args_size=2
	aload_0
	invokevirtual	Method underlying:()Lscala/collection/mutable/Buffer;
	iload_1
	invokeinterface	InterfaceMethod scala/collection/mutable/BufferLike.apply:(I)Ljava/lang/Object;
	areturn
  Labels:
  LocalVariableTable: 
   Start  Length  Slot  Name   Signature
   0      11      0    this       Lscala/collection/JavaConversions$MutableBufferWrapper;
   0      11      1    i       I

  Signature: length = 0x2
   00 2E 

public java.lang.Object set(int, java.lang.Object);
  Signature: (ILjava/lang/Object;)Ljava/lang/Object;
  Code:
   Stack=3, Locals=4, Args_size=3
	aload_0
	invokevirtual	Method underlying:()Lscala/collection/mutable/Buffer;
	iload_1
	invokeinterface	InterfaceMethod scala/collection/mutable/BufferLike.apply:(I)Ljava/lang/Object;
	astore_3
	aload_0
	invokevirtual	Method underlying:()Lscala/collection/mutable/Buffer;
	iload_1
	aload_2
	invokeinterface	InterfaceMethod scala/collection/mutable/BufferLike.update:(ILjava/lang/Object;)V
	aload_3
	areturn
  Labels:
  LocalVariableTable: 
   Start  Length  Slot  Name   Signature
   0      24      0    this       Lscala/collection/JavaConversions$MutableBufferWrapper;
   0      24      1    i       I
   0      24      2    elem       Ljava/lang/Object;
   11      12      3    p       Ljava/lang/Object;

  Signature: length = 0x2
   00 38 

public boolean add(java.lang.Object);
  Signature: (Ljava/lang/Object;)Z
  Code:
   Stack=6, Locals=2, Args_size=2
	aload_0
	invokevirtual	Method underlying:()Lscala/collection/mutable/Buffer;
	getstatic	Field scala/Predef$.MODULE$:Lscala/Predef$;
	iconst_1
	anewarray	class java/lang/Object
	dup
	iconst_0
	aload_1
	aastore
	invokevirtual	Method scala/Predef$.genericWrapArray:(Ljava/lang/Object;)Lscala/collection/mutable/WrappedArray;
	invokeinterface	InterfaceMethod scala/collection/mutable/BufferLike.append:(Lscala/collection/Seq;)V
	iconst_1
	ireturn
  Labels:
  LocalVariableTable: 
   Start  Length  Slot  Name   Signature
   0      25      0    this       Lscala/collection/JavaConversions$MutableBufferWrapper;
   0      25      1    elem       Ljava/lang/Object;

  Signature: length = 0x2
   00 4B 

public java.lang.Object remove(int);
  Signature: (I)Ljava/lang/Object;
  Code:
   Stack=2, Locals=2, Args_size=2
	aload_0
	invokevirtual	Method underlying:()Lscala/collection/mutable/Buffer;
	iload_1
	invokeinterface	InterfaceMethod scala/collection/mutable/BufferLike.remove:(I)Ljava/lang/Object;
	areturn
  Labels:
  LocalVariableTable: 
   Start  Length  Slot  Name   Signature
   0      11      0    this       Lscala/collection/JavaConversions$MutableBufferWrapper;
   0      11      1    i       I

  Signature: length = 0x2
   00 2E 

public scala.collection.JavaConversions$MutableBufferWrapper copy(scala.collection.mutable.Buffer);
  Signature: (Lscala/collection/mutable/Buffer;)Lscala/collection/JavaConversions$MutableBufferWrapper;
  Code:
   Stack=3, Locals=2, Args_size=2
	new	class scala/collection/JavaConversions$MutableBufferWrapper
	dup
	aload_1
	invokespecial	Method "<init>":(Lscala/collection/mutable/Buffer;)V
	areturn
  Labels:
  LocalVariableTable: 
   Start  Length  Slot  Name   Signature
   0      9      0    this       Lscala/collection/JavaConversions$MutableBufferWrapper;
   0      9      1    underlying       Lscala/collection/mutable/Buffer;


public java.lang.String productPrefix();
  Signature: ()Ljava/lang/String;
  Code:
   Stack=1, Locals=1, Args_size=1
	ldc	String MutableBufferWrapper
	areturn
  Labels:

public int productArity();
  Signature: ()I
  Code:
   Stack=1, Locals=1, Args_size=1
	iconst_1
	ireturn
  Labels:

public java.lang.Object productElement(int);
  Signature: (I)Ljava/lang/Object;
  Code:
   Stack=3, Locals=2, Args_size=2
	iload_1
	iconst_0
	if_icmpne	l1 // new
	aload_0
	invokevirtual	Method underlying:()Lscala/collection/mutable/Buffer;
	areturn
l1	new	class java/lang/IndexOutOfBoundsException
	dup
	iload_1
	invokestatic	Method scala/runtime/BoxesRunTime.boxToInteger:(I)Ljava/lang/Integer;
	invokevirtual	Method java/lang/Object.toString:()Ljava/lang/String;
	invokespecial	Method java/lang/IndexOutOfBoundsException."<init>":(Ljava/lang/String;)V
	athrow
  Labels:
   	l1 = 10 // new

public java.lang.String productElementName(int);
  Signature: (I)Ljava/lang/String;
  Code:
   Stack=3, Locals=2, Args_size=2
	iload_1
	iconst_0
	if_icmpne	l1 // new
	ldc	String underlying
	areturn
l1	new	class java/lang/IndexOutOfBoundsException
	dup
	iload_1
	invokestatic	Method scala/runtime/BoxesRunTime.boxToInteger:(I)Ljava/lang/Integer;
	invokevirtual	Method java/lang/Object.toString:()Ljava/lang/String;
	invokespecial	Method java/lang/IndexOutOfBoundsException."<init>":(Ljava/lang/String;)V
	athrow
  Labels:
   	l1 = 8 // new

public boolean canEqual(java.lang.Object);
  Signature: (Ljava/lang/Object;)Z
  Code:
   Stack=1, Locals=2, Args_size=2
	aload_1
	instanceof	class scala/collection/JavaConversions$MutableBufferWrapper
	ireturn
  Labels:

public scala.collection.JavaConversions$MutableBufferWrapper(scala.collection.mutable.Buffer);
  Signature: (Lscala/collection/mutable/Buffer;)V
  Code:
   Stack=2, Locals=2, Args_size=2
	aload_0
	aload_1
	putfield	Field underlying:Lscala/collection/mutable/Buffer;
	aload_0
	invokespecial	Method java/util/AbstractList."<init>":()V
	aload_0
	invokestatic	Method scala/Product$class.$init$:(Lscala/Product;)V
	return
  Labels:
  LocalVariableTable: 
   Start  Length  Slot  Name   Signature
   0      14      0    this       Lscala/collection/JavaConversions$MutableBufferWrapper;
   0      14      1    underlying       Lscala/collection/mutable/Buffer;

  Signature: length = 0x2
   00 76 

}

