Compiled from "JavaConversions.scala"
public final class scala.collection.JavaConversions$ extends java.lang.Object implements scala.ScalaObject
  SourceFile: "JavaConversions.scala"
  Scala: length = 0x
   
  InnerClass: 
   public #242= #38 of #241; //JMapWrapper=class scala/collection/JavaConversions$JMapWrapper of class scala/collection/JavaConversions
   public #243= #60 of #241; //JSetWrapper=class scala/collection/JavaConversions$JSetWrapper of class scala/collection/JavaConversions
   public #244= #79 of #241; //JListWrapper=class scala/collection/JavaConversions$JListWrapper of class scala/collection/JavaConversions
   public #245= #93 of #241; //IterableWrapper=class scala/collection/JavaConversions$IterableWrapper of class scala/collection/JavaConversions
   public #246= #122 of #241; //IteratorWrapper=class scala/collection/JavaConversions$IteratorWrapper of class scala/collection/JavaConversions
   public #247= #111 of #241; //JIterableWrapper=class scala/collection/JavaConversions$JIterableWrapper of class scala/collection/JavaConversions
   public #248= #139 of #241; //JIteratorWrapper=class scala/collection/JavaConversions$JIteratorWrapper of class scala/collection/JavaConversions
   public #249= #23 of #241; //MutableMapWrapper=class scala/collection/JavaConversions$MutableMapWrapper of class scala/collection/JavaConversions
   public #250= #55 of #241; //MutableSetWrapper=class scala/collection/JavaConversions$MutableSetWrapper of class scala/collection/JavaConversions
   public #251= #98 of #241; //JCollectionWrapper=class scala/collection/JavaConversions$JCollectionWrapper of class scala/collection/JavaConversions
   public #252= #127 of #241; //JEnumerationWrapper=class scala/collection/JavaConversions$JEnumerationWrapper of class scala/collection/JavaConversions
   public #253= #74 of #241; //MutableBufferWrapper=class scala/collection/JavaConversions$MutableBufferWrapper of class scala/collection/JavaConversions
  minor version: 0
  major version: 49
  Constant pool:
const #1 = Asciz	SourceFile;
const #2 = Asciz	JavaConversions.scala;
const #3 = Asciz	Scala;
const #4 = Asciz	MODULE$;
const #5 = Asciz	Lscala/collection/JavaConversions$;;
const #6 = Asciz	<clinit>;
const #7 = Asciz	()V;
const #8 = Asciz	Code;
const #9 = Asciz	scala/collection/JavaConversions$;
const #10 = class	#9;	//  scala/collection/JavaConversions$
const #11 = Asciz	<init>;
const #12 = NameAndType	#11:#7;//  "<init>":()V
const #13 = Method	#10.#12;	//  scala/collection/JavaConversions$."<init>":()V
const #14 = Asciz	LineNumberTable;
const #15 = Asciz	java/lang/Object;
const #16 = class	#15;	//  java/lang/Object
const #17 = Method	#16.#12;	//  java/lang/Object."<init>":()V
const #18 = NameAndType	#4:#5;//  MODULE$:Lscala/collection/JavaConversions$;
const #19 = Field	#10.#18;	//  scala/collection/JavaConversions$.MODULE$:Lscala/collection/JavaConversions$;
const #20 = Asciz	asMap;
const #21 = Asciz	(Ljava/util/Map;)Lscala/collection/mutable/Map;;
const #22 = Asciz	scala/collection/JavaConversions$MutableMapWrapper;
const #23 = class	#22;	//  scala/collection/JavaConversions$MutableMapWrapper
const #24 = Asciz	underlying;
const #25 = Asciz	()Lscala/collection/mutable/Map;;
const #26 = NameAndType	#24:#25;//  underlying:()Lscala/collection/mutable/Map;
const #27 = Method	#23.#26;	//  scala/collection/JavaConversions$MutableMapWrapper.underlying:()Lscala/collection/mutable/Map;
const #28 = Asciz	scala/MatchError;
const #29 = class	#28;	//  scala/MatchError
const #30 = Asciz	toString;
const #31 = Asciz	()Ljava/lang/String;;
const #32 = NameAndType	#30:#31;//  toString:()Ljava/lang/String;
const #33 = Method	#16.#32;	//  java/lang/Object.toString:()Ljava/lang/String;
const #34 = Asciz	(Ljava/lang/String;)V;
const #35 = NameAndType	#11:#34;//  "<init>":(Ljava/lang/String;)V
const #36 = Method	#29.#35;	//  scala/MatchError."<init>":(Ljava/lang/String;)V
const #37 = Asciz	scala/collection/JavaConversions$JMapWrapper;
const #38 = class	#37;	//  scala/collection/JavaConversions$JMapWrapper
const #39 = Asciz	(Ljava/util/Map;)V;
const #40 = NameAndType	#11:#39;//  "<init>":(Ljava/util/Map;)V
const #41 = Method	#38.#40;	//  scala/collection/JavaConversions$JMapWrapper."<init>":(Ljava/util/Map;)V
const #42 = Asciz	this;
const #43 = Asciz	m;
const #44 = Asciz	Ljava/util/Map;;
const #45 = Asciz	temp41;
const #46 = Asciz	Lscala/collection/JavaConversions$MutableMapWrapper;;
const #47 = Asciz	temp42;
const #48 = Asciz	Lscala/collection/mutable/Map;;
const #49 = Asciz	LocalVariableTable;
const #50 = Asciz	<A:Ljava/lang/Object;B:Ljava/lang/Object;>(Ljava/util/Map<TA;TB;>;)Lscala/collection/mutable/Map<TA;TB;>;;
const #51 = Asciz	Signature;
const #52 = Asciz	asSet;
const #53 = Asciz	(Ljava/util/Set;)Lscala/collection/mutable/Set;;
const #54 = Asciz	scala/collection/JavaConversions$MutableSetWrapper;
const #55 = class	#54;	//  scala/collection/JavaConversions$MutableSetWrapper
const #56 = Asciz	()Lscala/collection/mutable/Set;;
const #57 = NameAndType	#24:#56;//  underlying:()Lscala/collection/mutable/Set;
const #58 = Method	#55.#57;	//  scala/collection/JavaConversions$MutableSetWrapper.underlying:()Lscala/collection/mutable/Set;
const #59 = Asciz	scala/collection/JavaConversions$JSetWrapper;
const #60 = class	#59;	//  scala/collection/JavaConversions$JSetWrapper
const #61 = Asciz	(Ljava/util/Set;)V;
const #62 = NameAndType	#11:#61;//  "<init>":(Ljava/util/Set;)V
const #63 = Method	#60.#62;	//  scala/collection/JavaConversions$JSetWrapper."<init>":(Ljava/util/Set;)V
const #64 = Asciz	s;
const #65 = Asciz	Ljava/util/Set;;
const #66 = Asciz	temp38;
const #67 = Asciz	Lscala/collection/JavaConversions$MutableSetWrapper;;
const #68 = Asciz	temp39;
const #69 = Asciz	Lscala/collection/mutable/Set;;
const #70 = Asciz	<A:Ljava/lang/Object;>(Ljava/util/Set<TA;>;)Lscala/collection/mutable/Set<TA;>;;
const #71 = Asciz	asBuffer;
const #72 = Asciz	(Ljava/util/List;)Lscala/collection/mutable/Buffer;;
const #73 = Asciz	scala/collection/JavaConversions$MutableBufferWrapper;
const #74 = class	#73;	//  scala/collection/JavaConversions$MutableBufferWrapper
const #75 = Asciz	()Lscala/collection/mutable/Buffer;;
const #76 = NameAndType	#24:#75;//  underlying:()Lscala/collection/mutable/Buffer;
const #77 = Method	#74.#76;	//  scala/collection/JavaConversions$MutableBufferWrapper.underlying:()Lscala/collection/mutable/Buffer;
const #78 = Asciz	scala/collection/JavaConversions$JListWrapper;
const #79 = class	#78;	//  scala/collection/JavaConversions$JListWrapper
const #80 = Asciz	(Ljava/util/List;)V;
const #81 = NameAndType	#11:#80;//  "<init>":(Ljava/util/List;)V
const #82 = Method	#79.#81;	//  scala/collection/JavaConversions$JListWrapper."<init>":(Ljava/util/List;)V
const #83 = Asciz	l;
const #84 = Asciz	Ljava/util/List;;
const #85 = Asciz	temp35;
const #86 = Asciz	Lscala/collection/JavaConversions$MutableBufferWrapper;;
const #87 = Asciz	temp36;
const #88 = Asciz	Lscala/collection/mutable/Buffer;;
const #89 = Asciz	<A:Ljava/lang/Object;>(Ljava/util/List<TA;>;)Lscala/collection/mutable/Buffer<TA;>;;
const #90 = Asciz	asIterable;
const #91 = Asciz	(Ljava/util/Collection;)Lscala/collection/Iterable;;
const #92 = Asciz	scala/collection/JavaConversions$IterableWrapper;
const #93 = class	#92;	//  scala/collection/JavaConversions$IterableWrapper
const #94 = Asciz	()Lscala/collection/Iterable;;
const #95 = NameAndType	#24:#94;//  underlying:()Lscala/collection/Iterable;
const #96 = Method	#93.#95;	//  scala/collection/JavaConversions$IterableWrapper.underlying:()Lscala/collection/Iterable;
const #97 = Asciz	scala/collection/JavaConversions$JCollectionWrapper;
const #98 = class	#97;	//  scala/collection/JavaConversions$JCollectionWrapper
const #99 = Asciz	(Ljava/util/Collection;)V;
const #100 = NameAndType	#11:#99;//  "<init>":(Ljava/util/Collection;)V
const #101 = Method	#98.#100;	//  scala/collection/JavaConversions$JCollectionWrapper."<init>":(Ljava/util/Collection;)V
const #102 = Asciz	i;
const #103 = Asciz	Ljava/util/Collection;;
const #104 = Asciz	temp32;
const #105 = Asciz	Lscala/collection/JavaConversions$IterableWrapper;;
const #106 = Asciz	temp33;
const #107 = Asciz	Lscala/collection/Iterable;;
const #108 = Asciz	<A:Ljava/lang/Object;>(Ljava/util/Collection<TA;>;)Lscala/collection/Iterable<TA;>;;
const #109 = Asciz	(Ljava/lang/Iterable;)Lscala/collection/Iterable;;
const #110 = Asciz	scala/collection/JavaConversions$JIterableWrapper;
const #111 = class	#110;	//  scala/collection/JavaConversions$JIterableWrapper
const #112 = Asciz	(Ljava/lang/Iterable;)V;
const #113 = NameAndType	#11:#112;//  "<init>":(Ljava/lang/Iterable;)V
const #114 = Method	#111.#113;	//  scala/collection/JavaConversions$JIterableWrapper."<init>":(Ljava/lang/Iterable;)V
const #115 = Asciz	Ljava/lang/Iterable;;
const #116 = Asciz	temp29;
const #117 = Asciz	temp30;
const #118 = Asciz	<A:Ljava/lang/Object;>(Ljava/lang/Iterable<TA;>;)Lscala/collection/Iterable<TA;>;;
const #119 = Asciz	asIterator;
const #120 = Asciz	(Ljava/util/Enumeration;)Lscala/collection/Iterator;;
const #121 = Asciz	scala/collection/JavaConversions$IteratorWrapper;
const #122 = class	#121;	//  scala/collection/JavaConversions$IteratorWrapper
const #123 = Asciz	()Lscala/collection/Iterator;;
const #124 = NameAndType	#24:#123;//  underlying:()Lscala/collection/Iterator;
const #125 = Method	#122.#124;	//  scala/collection/JavaConversions$IteratorWrapper.underlying:()Lscala/collection/Iterator;
const #126 = Asciz	scala/collection/JavaConversions$JEnumerationWrapper;
const #127 = class	#126;	//  scala/collection/JavaConversions$JEnumerationWrapper
const #128 = Asciz	(Ljava/util/Enumeration;)V;
const #129 = NameAndType	#11:#128;//  "<init>":(Ljava/util/Enumeration;)V
const #130 = Method	#127.#129;	//  scala/collection/JavaConversions$JEnumerationWrapper."<init>":(Ljava/util/Enumeration;)V
const #131 = Asciz	Ljava/util/Enumeration;;
const #132 = Asciz	temp26;
const #133 = Asciz	Lscala/collection/JavaConversions$IteratorWrapper;;
const #134 = Asciz	temp27;
const #135 = Asciz	Lscala/collection/Iterator;;
const #136 = Asciz	<A:Ljava/lang/Object;>(Ljava/util/Enumeration<TA;>;)Lscala/collection/Iterator<TA;>;;
const #137 = Asciz	(Ljava/util/Iterator;)Lscala/collection/Iterator;;
const #138 = Asciz	scala/collection/JavaConversions$JIteratorWrapper;
const #139 = class	#138;	//  scala/collection/JavaConversions$JIteratorWrapper
const #140 = Asciz	(Ljava/util/Iterator;)V;
const #141 = NameAndType	#11:#140;//  "<init>":(Ljava/util/Iterator;)V
const #142 = Method	#139.#141;	//  scala/collection/JavaConversions$JIteratorWrapper."<init>":(Ljava/util/Iterator;)V
const #143 = Asciz	Ljava/util/Iterator;;
const #144 = Asciz	temp23;
const #145 = Asciz	temp24;
const #146 = Asciz	<A:Ljava/lang/Object;>(Ljava/util/Iterator<TA;>;)Lscala/collection/Iterator<TA;>;;
const #147 = Asciz	(Lscala/collection/mutable/Map;Lscala/reflect/ClassManifest;)Ljava/util/Map;;
const #148 = Asciz	()Ljava/util/Map;;
const #149 = NameAndType	#24:#148;//  underlying:()Ljava/util/Map;
const #150 = Method	#38.#149;	//  scala/collection/JavaConversions$JMapWrapper.underlying:()Ljava/util/Map;
const #151 = Asciz	scala/collection/MapLike;
const #152 = class	#151;	//  scala/collection/MapLike
const #153 = InterfaceMethod	#152.#32;	//  scala/collection/MapLike.toString:()Ljava/lang/String;
const #154 = Asciz	(Lscala/collection/mutable/Map;Lscala/reflect/ClassManifest;)V;
const #155 = NameAndType	#11:#154;//  "<init>":(Lscala/collection/mutable/Map;Lscala/reflect/ClassManifest;)V
const #156 = Method	#23.#155;	//  scala/collection/JavaConversions$MutableMapWrapper."<init>":(Lscala/collection/mutable/Map;Lscala/reflect/ClassManifest;)V
const #157 = Asciz	ma;
const #158 = Asciz	Lscala/reflect/ClassManifest;;
const #159 = Asciz	temp20;
const #160 = Asciz	Lscala/collection/JavaConversions$JMapWrapper;;
const #161 = Asciz	temp21;
const #162 = Asciz	<A:Ljava/lang/Object;B:Ljava/lang/Object;>(Lscala/collection/mutable/Map<TA;TB;>;Lscala/reflect/ClassManifest<TA;>;)Ljava/util/Map<TA;TB;>;;
const #163 = Asciz	(Lscala/collection/mutable/Set;Lscala/reflect/ClassManifest;)Ljava/util/Set;;
const #164 = Asciz	()Ljava/util/Set;;
const #165 = NameAndType	#24:#164;//  underlying:()Ljava/util/Set;
const #166 = Method	#60.#165;	//  scala/collection/JavaConversions$JSetWrapper.underlying:()Ljava/util/Set;
const #167 = Asciz	scala/collection/SetLike;
const #168 = class	#167;	//  scala/collection/SetLike
const #169 = InterfaceMethod	#168.#32;	//  scala/collection/SetLike.toString:()Ljava/lang/String;
const #170 = Asciz	(Lscala/collection/mutable/Set;Lscala/reflect/ClassManifest;)V;
const #171 = NameAndType	#11:#170;//  "<init>":(Lscala/collection/mutable/Set;Lscala/reflect/ClassManifest;)V
const #172 = Method	#55.#171;	//  scala/collection/JavaConversions$MutableSetWrapper."<init>":(Lscala/collection/mutable/Set;Lscala/reflect/ClassManifest;)V
const #173 = Asciz	temp17;
const #174 = Asciz	Lscala/collection/JavaConversions$JSetWrapper;;
const #175 = Asciz	temp18;
const #176 = Asciz	<A:Ljava/lang/Object;>(Lscala/collection/mutable/Set<TA;>;Lscala/reflect/ClassManifest<TA;>;)Ljava/util/Set<TA;>;;
const #177 = Asciz	asList;
const #178 = Asciz	(Lscala/collection/mutable/Buffer;)Ljava/util/List;;
const #179 = Asciz	()Ljava/util/List;;
const #180 = NameAndType	#24:#179;//  underlying:()Ljava/util/List;
const #181 = Method	#79.#180;	//  scala/collection/JavaConversions$JListWrapper.underlying:()Ljava/util/List;
const #182 = Asciz	scala/collection/SeqLike;
const #183 = class	#182;	//  scala/collection/SeqLike
const #184 = InterfaceMethod	#183.#32;	//  scala/collection/SeqLike.toString:()Ljava/lang/String;
const #185 = Asciz	(Lscala/collection/mutable/Buffer;)V;
const #186 = NameAndType	#11:#185;//  "<init>":(Lscala/collection/mutable/Buffer;)V
const #187 = Method	#74.#186;	//  scala/collection/JavaConversions$MutableBufferWrapper."<init>":(Lscala/collection/mutable/Buffer;)V
const #188 = Asciz	b;
const #189 = Asciz	temp14;
const #190 = Asciz	Lscala/collection/JavaConversions$JListWrapper;;
const #191 = Asciz	temp15;
const #192 = Asciz	<A:Ljava/lang/Object;>(Lscala/collection/mutable/Buffer<TA;>;)Ljava/util/List<TA;>;;
const #193 = Asciz	asCollection;
const #194 = Asciz	(Lscala/collection/Iterable;)Ljava/util/Collection;;
const #195 = Asciz	()Ljava/util/Collection;;
const #196 = NameAndType	#24:#195;//  underlying:()Ljava/util/Collection;
const #197 = Method	#98.#196;	//  scala/collection/JavaConversions$JCollectionWrapper.underlying:()Ljava/util/Collection;
const #198 = Asciz	scala/collection/TraversableLike;
const #199 = class	#198;	//  scala/collection/TraversableLike
const #200 = InterfaceMethod	#199.#32;	//  scala/collection/TraversableLike.toString:()Ljava/lang/String;
const #201 = Asciz	(Lscala/collection/Iterable;)V;
const #202 = NameAndType	#11:#201;//  "<init>":(Lscala/collection/Iterable;)V
const #203 = Method	#93.#202;	//  scala/collection/JavaConversions$IterableWrapper."<init>":(Lscala/collection/Iterable;)V
const #204 = Asciz	temp11;
const #205 = Asciz	Lscala/collection/JavaConversions$JCollectionWrapper;;
const #206 = Asciz	temp12;
const #207 = Asciz	<A:Ljava/lang/Object;>(Lscala/collection/Iterable<TA;>;)Ljava/util/Collection<TA;>;;
const #208 = Asciz	(Lscala/collection/Iterable;)Ljava/lang/Iterable;;
const #209 = Asciz	()Ljava/lang/Iterable;;
const #210 = NameAndType	#24:#209;//  underlying:()Ljava/lang/Iterable;
const #211 = Method	#111.#210;	//  scala/collection/JavaConversions$JIterableWrapper.underlying:()Ljava/lang/Iterable;
const #212 = Asciz	temp8;
const #213 = Asciz	Lscala/collection/JavaConversions$JIterableWrapper;;
const #214 = Asciz	temp9;
const #215 = Asciz	<A:Ljava/lang/Object;>(Lscala/collection/Iterable<TA;>;)Ljava/lang/Iterable<TA;>;;
const #216 = Asciz	asEnumeration;
const #217 = Asciz	(Lscala/collection/Iterator;)Ljava/util/Enumeration;;
const #218 = Asciz	()Ljava/util/Enumeration;;
const #219 = NameAndType	#24:#218;//  underlying:()Ljava/util/Enumeration;
const #220 = Method	#127.#219;	//  scala/collection/JavaConversions$JEnumerationWrapper.underlying:()Ljava/util/Enumeration;
const #221 = Asciz	scala/collection/Iterator;
const #222 = class	#221;	//  scala/collection/Iterator
const #223 = InterfaceMethod	#222.#32;	//  scala/collection/Iterator.toString:()Ljava/lang/String;
const #224 = Asciz	(Lscala/collection/Iterator;)V;
const #225 = NameAndType	#11:#224;//  "<init>":(Lscala/collection/Iterator;)V
const #226 = Method	#122.#225;	//  scala/collection/JavaConversions$IteratorWrapper."<init>":(Lscala/collection/Iterator;)V
const #227 = Asciz	temp5;
const #228 = Asciz	Lscala/collection/JavaConversions$JEnumerationWrapper;;
const #229 = Asciz	temp6;
const #230 = Asciz	<A:Ljava/lang/Object;>(Lscala/collection/Iterator<TA;>;)Ljava/util/Enumeration<TA;>;;
const #231 = Asciz	(Lscala/collection/Iterator;)Ljava/util/Iterator;;
const #232 = Asciz	()Ljava/util/Iterator;;
const #233 = NameAndType	#24:#232;//  underlying:()Ljava/util/Iterator;
const #234 = Method	#139.#233;	//  scala/collection/JavaConversions$JIteratorWrapper.underlying:()Ljava/util/Iterator;
const #235 = Asciz	temp2;
const #236 = Asciz	Lscala/collection/JavaConversions$JIteratorWrapper;;
const #237 = Asciz	temp3;
const #238 = Asciz	<A:Ljava/lang/Object;>(Lscala/collection/Iterator<TA;>;)Ljava/util/Iterator<TA;>;;
const #239 = Asciz	InnerClasses;
const #240 = Asciz	scala/collection/JavaConversions;
const #241 = class	#240;	//  scala/collection/JavaConversions
const #242 = Asciz	JMapWrapper;
const #243 = Asciz	JSetWrapper;
const #244 = Asciz	JListWrapper;
const #245 = Asciz	IterableWrapper;
const #246 = Asciz	IteratorWrapper;
const #247 = Asciz	JIterableWrapper;
const #248 = Asciz	JIteratorWrapper;
const #249 = Asciz	MutableMapWrapper;
const #250 = Asciz	MutableSetWrapper;
const #251 = Asciz	JCollectionWrapper;
const #252 = Asciz	JEnumerationWrapper;
const #253 = Asciz	MutableBufferWrapper;
const #254 = Asciz	scala/ScalaObject;
const #255 = class	#254;	//  scala/ScalaObject

{
public static final scala.collection.JavaConversions$ MODULE$;

public static {};
  Code:
   Stack=1, Locals=0, Args_size=0
   0:	new	#10; //class scala/collection/JavaConversions$
   3:	invokespecial	#13; //Method "<init>":()V
   6:	return

public scala.collection.mutable.Map asMap(java.util.Map);
  Code:
   Stack=3, Locals=4, Args_size=2
   0:	aload_1
   1:	instanceof	#23; //class scala/collection/JavaConversions$MutableMapWrapper
   4:	ifeq	37
   7:	aload_1
   8:	checkcast	#23; //class scala/collection/JavaConversions$MutableMapWrapper
   11:	astore_2
   12:	aload_2
   13:	invokevirtual	#27; //Method scala/collection/JavaConversions$MutableMapWrapper.underlying:()Lscala/collection/mutable/Map;
   16:	astore_3
   17:	iconst_1
   18:	ifeq	25
   21:	aload_3
   22:	goto	49
   25:	new	#29; //class scala/MatchError
   28:	dup
   29:	aload_1
   30:	invokevirtual	#33; //Method java/lang/Object.toString:()Ljava/lang/String;
   33:	invokespecial	#36; //Method scala/MatchError."<init>":(Ljava/lang/String;)V
   36:	athrow
   37:	iconst_1
   38:	ifeq	50
   41:	new	#38; //class scala/collection/JavaConversions$JMapWrapper
   44:	dup
   45:	aload_1
   46:	invokespecial	#41; //Method scala/collection/JavaConversions$JMapWrapper."<init>":(Ljava/util/Map;)V
   49:	areturn
   50:	new	#29; //class scala/MatchError
   53:	dup
   54:	aload_1
   55:	invokevirtual	#33; //Method java/lang/Object.toString:()Ljava/lang/String;
   58:	invokespecial	#36; //Method scala/MatchError."<init>":(Ljava/lang/String;)V
   61:	athrow
  LineNumberTable: 
   line 305: 0
   line 21: 17
   line 306: 21
   line 305: 25
   line 21: 37
   line 307: 41
   line 305: 49

  LocalVariableTable: 
   Start  Length  Slot  Name   Signature
   0      62      0    this       Lscala/collection/JavaConversions$;
   0      62      1    m       Ljava/util/Map;
   12      25      2    temp41       Lscala/collection/JavaConversions$MutableMapWrapper;
   17      20      3    temp42       Lscala/collection/mutable/Map;

  Signature: length = 0x2
   00 32 

public scala.collection.mutable.Set asSet(java.util.Set);
  Code:
   Stack=3, Locals=4, Args_size=2
   0:	aload_1
   1:	instanceof	#55; //class scala/collection/JavaConversions$MutableSetWrapper
   4:	ifeq	37
   7:	aload_1
   8:	checkcast	#55; //class scala/collection/JavaConversions$MutableSetWrapper
   11:	astore_2
   12:	aload_2
   13:	invokevirtual	#58; //Method scala/collection/JavaConversions$MutableSetWrapper.underlying:()Lscala/collection/mutable/Set;
   16:	astore_3
   17:	iconst_1
   18:	ifeq	25
   21:	aload_3
   22:	goto	49
   25:	new	#29; //class scala/MatchError
   28:	dup
   29:	aload_1
   30:	invokevirtual	#33; //Method java/lang/Object.toString:()Ljava/lang/String;
   33:	invokespecial	#36; //Method scala/MatchError."<init>":(Ljava/lang/String;)V
   36:	athrow
   37:	iconst_1
   38:	ifeq	50
   41:	new	#60; //class scala/collection/JavaConversions$JSetWrapper
   44:	dup
   45:	aload_1
   46:	invokespecial	#63; //Method scala/collection/JavaConversions$JSetWrapper."<init>":(Ljava/util/Set;)V
   49:	areturn
   50:	new	#29; //class scala/MatchError
   53:	dup
   54:	aload_1
   55:	invokevirtual	#33; //Method java/lang/Object.toString:()Ljava/lang/String;
   58:	invokespecial	#36; //Method scala/MatchError."<init>":(Ljava/lang/String;)V
   61:	athrow
  LineNumberTable: 
   line 287: 0
   line 21: 17
   line 288: 21
   line 287: 25
   line 21: 37
   line 289: 41
   line 287: 49

  LocalVariableTable: 
   Start  Length  Slot  Name   Signature
   0      62      0    this       Lscala/collection/JavaConversions$;
   0      62      1    s       Ljava/util/Set;
   12      25      2    temp38       Lscala/collection/JavaConversions$MutableSetWrapper;
   17      20      3    temp39       Lscala/collection/mutable/Set;

  Signature: length = 0x2
   00 46 

public scala.collection.mutable.Buffer asBuffer(java.util.List);
  Code:
   Stack=3, Locals=4, Args_size=2
   0:	aload_1
   1:	instanceof	#74; //class scala/collection/JavaConversions$MutableBufferWrapper
   4:	ifeq	37
   7:	aload_1
   8:	checkcast	#74; //class scala/collection/JavaConversions$MutableBufferWrapper
   11:	astore_2
   12:	aload_2
   13:	invokevirtual	#77; //Method scala/collection/JavaConversions$MutableBufferWrapper.underlying:()Lscala/collection/mutable/Buffer;
   16:	astore_3
   17:	iconst_1
   18:	ifeq	25
   21:	aload_3
   22:	goto	49
   25:	new	#29; //class scala/MatchError
   28:	dup
   29:	aload_1
   30:	invokevirtual	#33; //Method java/lang/Object.toString:()Ljava/lang/String;
   33:	invokespecial	#36; //Method scala/MatchError."<init>":(Ljava/lang/String;)V
   36:	athrow
   37:	iconst_1
   38:	ifeq	50
   41:	new	#79; //class scala/collection/JavaConversions$JListWrapper
   44:	dup
   45:	aload_1
   46:	invokespecial	#82; //Method scala/collection/JavaConversions$JListWrapper."<init>":(Ljava/util/List;)V
   49:	areturn
   50:	new	#29; //class scala/MatchError
   53:	dup
   54:	aload_1
   55:	invokevirtual	#33; //Method java/lang/Object.toString:()Ljava/lang/String;
   58:	invokespecial	#36; //Method scala/MatchError."<init>":(Ljava/lang/String;)V
   61:	athrow
  LineNumberTable: 
   line 269: 0
   line 21: 17
   line 270: 21
   line 269: 25
   line 21: 37
   line 271: 41
   line 269: 49

  LocalVariableTable: 
   Start  Length  Slot  Name   Signature
   0      62      0    this       Lscala/collection/JavaConversions$;
   0      62      1    l       Ljava/util/List;
   12      25      2    temp35       Lscala/collection/JavaConversions$MutableBufferWrapper;
   17      20      3    temp36       Lscala/collection/mutable/Buffer;

  Signature: length = 0x2
   00 59 

public scala.collection.Iterable asIterable(java.util.Collection);
  Code:
   Stack=3, Locals=4, Args_size=2
   0:	aload_1
   1:	instanceof	#93; //class scala/collection/JavaConversions$IterableWrapper
   4:	ifeq	37
   7:	aload_1
   8:	checkcast	#93; //class scala/collection/JavaConversions$IterableWrapper
   11:	astore_2
   12:	aload_2
   13:	invokevirtual	#96; //Method scala/collection/JavaConversions$IterableWrapper.underlying:()Lscala/collection/Iterable;
   16:	astore_3
   17:	iconst_1
   18:	ifeq	25
   21:	aload_3
   22:	goto	49
   25:	new	#29; //class scala/MatchError
   28:	dup
   29:	aload_1
   30:	invokevirtual	#33; //Method java/lang/Object.toString:()Ljava/lang/String;
   33:	invokespecial	#36; //Method scala/MatchError."<init>":(Ljava/lang/String;)V
   36:	athrow
   37:	iconst_1
   38:	ifeq	50
   41:	new	#98; //class scala/collection/JavaConversions$JCollectionWrapper
   44:	dup
   45:	aload_1
   46:	invokespecial	#101; //Method scala/collection/JavaConversions$JCollectionWrapper."<init>":(Ljava/util/Collection;)V
   49:	areturn
   50:	new	#29; //class scala/MatchError
   53:	dup
   54:	aload_1
   55:	invokevirtual	#33; //Method java/lang/Object.toString:()Ljava/lang/String;
   58:	invokespecial	#36; //Method scala/MatchError."<init>":(Ljava/lang/String;)V
   61:	athrow
  LineNumberTable: 
   line 251: 0
   line 21: 17
   line 252: 21
   line 251: 25
   line 21: 37
   line 253: 41
   line 251: 49

  LocalVariableTable: 
   Start  Length  Slot  Name   Signature
   0      62      0    this       Lscala/collection/JavaConversions$;
   0      62      1    i       Ljava/util/Collection;
   12      25      2    temp32       Lscala/collection/JavaConversions$IterableWrapper;
   17      20      3    temp33       Lscala/collection/Iterable;

  Signature: length = 0x2
   00 6C 

public scala.collection.Iterable asIterable(java.lang.Iterable);
  Code:
   Stack=3, Locals=4, Args_size=2
   0:	aload_1
   1:	instanceof	#93; //class scala/collection/JavaConversions$IterableWrapper
   4:	ifeq	37
   7:	aload_1
   8:	checkcast	#93; //class scala/collection/JavaConversions$IterableWrapper
   11:	astore_2
   12:	aload_2
   13:	invokevirtual	#96; //Method scala/collection/JavaConversions$IterableWrapper.underlying:()Lscala/collection/Iterable;
   16:	astore_3
   17:	iconst_1
   18:	ifeq	25
   21:	aload_3
   22:	goto	49
   25:	new	#29; //class scala/MatchError
   28:	dup
   29:	aload_1
   30:	invokevirtual	#33; //Method java/lang/Object.toString:()Ljava/lang/String;
   33:	invokespecial	#36; //Method scala/MatchError."<init>":(Ljava/lang/String;)V
   36:	athrow
   37:	iconst_1
   38:	ifeq	50
   41:	new	#111; //class scala/collection/JavaConversions$JIterableWrapper
   44:	dup
   45:	aload_1
   46:	invokespecial	#114; //Method scala/collection/JavaConversions$JIterableWrapper."<init>":(Ljava/lang/Iterable;)V
   49:	areturn
   50:	new	#29; //class scala/MatchError
   53:	dup
   54:	aload_1
   55:	invokevirtual	#33; //Method java/lang/Object.toString:()Ljava/lang/String;
   58:	invokespecial	#36; //Method scala/MatchError."<init>":(Ljava/lang/String;)V
   61:	athrow
  LineNumberTable: 
   line 236: 0
   line 21: 17
   line 237: 21
   line 236: 25
   line 21: 37
   line 238: 41
   line 236: 49

  LocalVariableTable: 
   Start  Length  Slot  Name   Signature
   0      62      0    this       Lscala/collection/JavaConversions$;
   0      62      1    i       Ljava/lang/Iterable;
   12      25      2    temp29       Lscala/collection/JavaConversions$IterableWrapper;
   17      20      3    temp30       Lscala/collection/Iterable;

  Signature: length = 0x2
   00 76 

public scala.collection.Iterator asIterator(java.util.Enumeration);
  Code:
   Stack=3, Locals=4, Args_size=2
   0:	aload_1
   1:	instanceof	#122; //class scala/collection/JavaConversions$IteratorWrapper
   4:	ifeq	37
   7:	aload_1
   8:	checkcast	#122; //class scala/collection/JavaConversions$IteratorWrapper
   11:	astore_2
   12:	aload_2
   13:	invokevirtual	#125; //Method scala/collection/JavaConversions$IteratorWrapper.underlying:()Lscala/collection/Iterator;
   16:	astore_3
   17:	iconst_1
   18:	ifeq	25
   21:	aload_3
   22:	goto	49
   25:	new	#29; //class scala/MatchError
   28:	dup
   29:	aload_1
   30:	invokevirtual	#33; //Method java/lang/Object.toString:()Ljava/lang/String;
   33:	invokespecial	#36; //Method scala/MatchError."<init>":(Ljava/lang/String;)V
   36:	athrow
   37:	iconst_1
   38:	ifeq	50
   41:	new	#127; //class scala/collection/JavaConversions$JEnumerationWrapper
   44:	dup
   45:	aload_1
   46:	invokespecial	#130; //Method scala/collection/JavaConversions$JEnumerationWrapper."<init>":(Ljava/util/Enumeration;)V
   49:	areturn
   50:	new	#29; //class scala/MatchError
   53:	dup
   54:	aload_1
   55:	invokevirtual	#33; //Method java/lang/Object.toString:()Ljava/lang/String;
   58:	invokespecial	#36; //Method scala/MatchError."<init>":(Ljava/lang/String;)V
   61:	athrow
  LineNumberTable: 
   line 218: 0
   line 21: 17
   line 219: 21
   line 218: 25
   line 21: 37
   line 220: 41
   line 218: 49

  LocalVariableTable: 
   Start  Length  Slot  Name   Signature
   0      62      0    this       Lscala/collection/JavaConversions$;
   0      62      1    i       Ljava/util/Enumeration;
   12      25      2    temp26       Lscala/collection/JavaConversions$IteratorWrapper;
   17      20      3    temp27       Lscala/collection/Iterator;

  Signature: length = 0x2
   00 FFFFFF88 

public scala.collection.Iterator asIterator(java.util.Iterator);
  Code:
   Stack=3, Locals=4, Args_size=2
   0:	aload_1
   1:	instanceof	#122; //class scala/collection/JavaConversions$IteratorWrapper
   4:	ifeq	37
   7:	aload_1
   8:	checkcast	#122; //class scala/collection/JavaConversions$IteratorWrapper
   11:	astore_2
   12:	aload_2
   13:	invokevirtual	#125; //Method scala/collection/JavaConversions$IteratorWrapper.underlying:()Lscala/collection/Iterator;
   16:	astore_3
   17:	iconst_1
   18:	ifeq	25
   21:	aload_3
   22:	goto	49
   25:	new	#29; //class scala/MatchError
   28:	dup
   29:	aload_1
   30:	invokevirtual	#33; //Method java/lang/Object.toString:()Ljava/lang/String;
   33:	invokespecial	#36; //Method scala/MatchError."<init>":(Ljava/lang/String;)V
   36:	athrow
   37:	iconst_1
   38:	ifeq	50
   41:	new	#139; //class scala/collection/JavaConversions$JIteratorWrapper
   44:	dup
   45:	aload_1
   46:	invokespecial	#142; //Method scala/collection/JavaConversions$JIteratorWrapper."<init>":(Ljava/util/Iterator;)V
   49:	areturn
   50:	new	#29; //class scala/MatchError
   53:	dup
   54:	aload_1
   55:	invokevirtual	#33; //Method java/lang/Object.toString:()Ljava/lang/String;
   58:	invokespecial	#36; //Method scala/MatchError."<init>":(Ljava/lang/String;)V
   61:	athrow
  LineNumberTable: 
   line 200: 0
   line 21: 17
   line 201: 21
   line 200: 25
   line 21: 37
   line 202: 41
   line 200: 49

  LocalVariableTable: 
   Start  Length  Slot  Name   Signature
   0      62      0    this       Lscala/collection/JavaConversions$;
   0      62      1    i       Ljava/util/Iterator;
   12      25      2    temp23       Lscala/collection/JavaConversions$IteratorWrapper;
   17      20      3    temp24       Lscala/collection/Iterator;

  Signature: length = 0x2
   00 FFFFFF92 

public java.util.Map asMap(scala.collection.mutable.Map, scala.reflect.ClassManifest);
  Code:
   Stack=4, Locals=5, Args_size=3
   0:	aload_1
   1:	instanceof	#38; //class scala/collection/JavaConversions$JMapWrapper
   4:	ifeq	41
   7:	aload_1
   8:	checkcast	#38; //class scala/collection/JavaConversions$JMapWrapper
   11:	astore_3
   12:	aload_3
   13:	invokevirtual	#150; //Method scala/collection/JavaConversions$JMapWrapper.underlying:()Ljava/util/Map;
   16:	astore	4
   18:	iconst_1
   19:	ifeq	27
   22:	aload	4
   24:	goto	54
   27:	new	#29; //class scala/MatchError
   30:	dup
   31:	aload_1
   32:	invokeinterface	#153,  1; //InterfaceMethod scala/collection/MapLike.toString:()Ljava/lang/String;
   37:	invokespecial	#36; //Method scala/MatchError."<init>":(Ljava/lang/String;)V
   40:	athrow
   41:	iconst_1
   42:	ifeq	55
   45:	new	#23; //class scala/collection/JavaConversions$MutableMapWrapper
   48:	dup
   49:	aload_1
   50:	aload_2
   51:	invokespecial	#156; //Method scala/collection/JavaConversions$MutableMapWrapper."<init>":(Lscala/collection/mutable/Map;Lscala/reflect/ClassManifest;)V
   54:	areturn
   55:	new	#29; //class scala/MatchError
   58:	dup
   59:	aload_1
   60:	invokeinterface	#153,  1; //InterfaceMethod scala/collection/MapLike.toString:()Ljava/lang/String;
   65:	invokespecial	#36; //Method scala/MatchError."<init>":(Ljava/lang/String;)V
   68:	athrow
  LineNumberTable: 
   line 180: 0
   line 21: 18
   line 181: 22
   line 180: 27
   line 21: 41
   line 182: 45
   line 180: 54

  LocalVariableTable: 
   Start  Length  Slot  Name   Signature
   0      69      0    this       Lscala/collection/JavaConversions$;
   0      69      1    m       Lscala/collection/mutable/Map;
   0      69      2    ma       Lscala/reflect/ClassManifest;
   12      29      3    temp20       Lscala/collection/JavaConversions$JMapWrapper;
   18      23      4    temp21       Ljava/util/Map;

  Signature: length = 0x2
   00 FFFFFFA2 

public java.util.Set asSet(scala.collection.mutable.Set, scala.reflect.ClassManifest);
  Code:
   Stack=4, Locals=5, Args_size=3
   0:	aload_1
   1:	instanceof	#60; //class scala/collection/JavaConversions$JSetWrapper
   4:	ifeq	41
   7:	aload_1
   8:	checkcast	#60; //class scala/collection/JavaConversions$JSetWrapper
   11:	astore_3
   12:	aload_3
   13:	invokevirtual	#166; //Method scala/collection/JavaConversions$JSetWrapper.underlying:()Ljava/util/Set;
   16:	astore	4
   18:	iconst_1
   19:	ifeq	27
   22:	aload	4
   24:	goto	54
   27:	new	#29; //class scala/MatchError
   30:	dup
   31:	aload_1
   32:	invokeinterface	#169,  1; //InterfaceMethod scala/collection/SetLike.toString:()Ljava/lang/String;
   37:	invokespecial	#36; //Method scala/MatchError."<init>":(Ljava/lang/String;)V
   40:	athrow
   41:	iconst_1
   42:	ifeq	55
   45:	new	#55; //class scala/collection/JavaConversions$MutableSetWrapper
   48:	dup
   49:	aload_1
   50:	aload_2
   51:	invokespecial	#172; //Method scala/collection/JavaConversions$MutableSetWrapper."<init>":(Lscala/collection/mutable/Set;Lscala/reflect/ClassManifest;)V
   54:	areturn
   55:	new	#29; //class scala/MatchError
   58:	dup
   59:	aload_1
   60:	invokeinterface	#169,  1; //InterfaceMethod scala/collection/SetLike.toString:()Ljava/lang/String;
   65:	invokespecial	#36; //Method scala/MatchError."<init>":(Ljava/lang/String;)V
   68:	athrow
  LineNumberTable: 
   line 162: 0
   line 21: 18
   line 163: 22
   line 162: 27
   line 21: 41
   line 164: 45
   line 162: 54

  LocalVariableTable: 
   Start  Length  Slot  Name   Signature
   0      69      0    this       Lscala/collection/JavaConversions$;
   0      69      1    s       Lscala/collection/mutable/Set;
   0      69      2    m       Lscala/reflect/ClassManifest;
   12      29      3    temp17       Lscala/collection/JavaConversions$JSetWrapper;
   18      23      4    temp18       Ljava/util/Set;

  Signature: length = 0x2
   00 FFFFFFB0 

public java.util.List asList(scala.collection.mutable.Buffer);
  Code:
   Stack=3, Locals=4, Args_size=2
   0:	aload_1
   1:	instanceof	#79; //class scala/collection/JavaConversions$JListWrapper
   4:	ifeq	39
   7:	aload_1
   8:	checkcast	#79; //class scala/collection/JavaConversions$JListWrapper
   11:	astore_2
   12:	aload_2
   13:	invokevirtual	#181; //Method scala/collection/JavaConversions$JListWrapper.underlying:()Ljava/util/List;
   16:	astore_3
   17:	iconst_1
   18:	ifeq	25
   21:	aload_3
   22:	goto	51
   25:	new	#29; //class scala/MatchError
   28:	dup
   29:	aload_1
   30:	invokeinterface	#184,  1; //InterfaceMethod scala/collection/SeqLike.toString:()Ljava/lang/String;
   35:	invokespecial	#36; //Method scala/MatchError."<init>":(Ljava/lang/String;)V
   38:	athrow
   39:	iconst_1
   40:	ifeq	52
   43:	new	#74; //class scala/collection/JavaConversions$MutableBufferWrapper
   46:	dup
   47:	aload_1
   48:	invokespecial	#187; //Method scala/collection/JavaConversions$MutableBufferWrapper."<init>":(Lscala/collection/mutable/Buffer;)V
   51:	areturn
   52:	new	#29; //class scala/MatchError
   55:	dup
   56:	aload_1
   57:	invokeinterface	#184,  1; //InterfaceMethod scala/collection/SeqLike.toString:()Ljava/lang/String;
   62:	invokespecial	#36; //Method scala/MatchError."<init>":(Ljava/lang/String;)V
   65:	athrow
  LineNumberTable: 
   line 144: 0
   line 21: 17
   line 145: 21
   line 144: 25
   line 21: 39
   line 146: 43
   line 144: 51

  LocalVariableTable: 
   Start  Length  Slot  Name   Signature
   0      66      0    this       Lscala/collection/JavaConversions$;
   0      66      1    b       Lscala/collection/mutable/Buffer;
   12      27      2    temp14       Lscala/collection/JavaConversions$JListWrapper;
   17      22      3    temp15       Ljava/util/List;

  Signature: length = 0x2
   00 FFFFFFC0 

public java.util.Collection asCollection(scala.collection.Iterable);
  Code:
   Stack=3, Locals=4, Args_size=2
   0:	aload_1
   1:	instanceof	#98; //class scala/collection/JavaConversions$JCollectionWrapper
   4:	ifeq	39
   7:	aload_1
   8:	checkcast	#98; //class scala/collection/JavaConversions$JCollectionWrapper
   11:	astore_2
   12:	aload_2
   13:	invokevirtual	#197; //Method scala/collection/JavaConversions$JCollectionWrapper.underlying:()Ljava/util/Collection;
   16:	astore_3
   17:	iconst_1
   18:	ifeq	25
   21:	aload_3
   22:	goto	51
   25:	new	#29; //class scala/MatchError
   28:	dup
   29:	aload_1
   30:	invokeinterface	#200,  1; //InterfaceMethod scala/collection/TraversableLike.toString:()Ljava/lang/String;
   35:	invokespecial	#36; //Method scala/MatchError."<init>":(Ljava/lang/String;)V
   38:	athrow
   39:	iconst_1
   40:	ifeq	52
   43:	new	#93; //class scala/collection/JavaConversions$IterableWrapper
   46:	dup
   47:	aload_1
   48:	invokespecial	#203; //Method scala/collection/JavaConversions$IterableWrapper."<init>":(Lscala/collection/Iterable;)V
   51:	areturn
   52:	new	#29; //class scala/MatchError
   55:	dup
   56:	aload_1
   57:	invokeinterface	#200,  1; //InterfaceMethod scala/collection/TraversableLike.toString:()Ljava/lang/String;
   62:	invokespecial	#36; //Method scala/MatchError."<init>":(Ljava/lang/String;)V
   65:	athrow
  LineNumberTable: 
   line 126: 0
   line 21: 17
   line 127: 21
   line 126: 25
   line 21: 39
   line 128: 43
   line 126: 51

  LocalVariableTable: 
   Start  Length  Slot  Name   Signature
   0      66      0    this       Lscala/collection/JavaConversions$;
   0      66      1    i       Lscala/collection/Iterable;
   12      27      2    temp11       Lscala/collection/JavaConversions$JCollectionWrapper;
   17      22      3    temp12       Ljava/util/Collection;

  Signature: length = 0x2
   00 FFFFFFCF 

public java.lang.Iterable asIterable(scala.collection.Iterable);
  Code:
   Stack=3, Locals=4, Args_size=2
   0:	aload_1
   1:	instanceof	#111; //class scala/collection/JavaConversions$JIterableWrapper
   4:	ifeq	39
   7:	aload_1
   8:	checkcast	#111; //class scala/collection/JavaConversions$JIterableWrapper
   11:	astore_2
   12:	aload_2
   13:	invokevirtual	#211; //Method scala/collection/JavaConversions$JIterableWrapper.underlying:()Ljava/lang/Iterable;
   16:	astore_3
   17:	iconst_1
   18:	ifeq	25
   21:	aload_3
   22:	goto	51
   25:	new	#29; //class scala/MatchError
   28:	dup
   29:	aload_1
   30:	invokeinterface	#200,  1; //InterfaceMethod scala/collection/TraversableLike.toString:()Ljava/lang/String;
   35:	invokespecial	#36; //Method scala/MatchError."<init>":(Ljava/lang/String;)V
   38:	athrow
   39:	iconst_1
   40:	ifeq	52
   43:	new	#93; //class scala/collection/JavaConversions$IterableWrapper
   46:	dup
   47:	aload_1
   48:	invokespecial	#203; //Method scala/collection/JavaConversions$IterableWrapper."<init>":(Lscala/collection/Iterable;)V
   51:	areturn
   52:	new	#29; //class scala/MatchError
   55:	dup
   56:	aload_1
   57:	invokeinterface	#200,  1; //InterfaceMethod scala/collection/TraversableLike.toString:()Ljava/lang/String;
   62:	invokespecial	#36; //Method scala/MatchError."<init>":(Ljava/lang/String;)V
   65:	athrow
  LineNumberTable: 
   line 110: 0
   line 21: 17
   line 111: 21
   line 110: 25
   line 21: 39
   line 112: 43
   line 110: 51

  LocalVariableTable: 
   Start  Length  Slot  Name   Signature
   0      66      0    this       Lscala/collection/JavaConversions$;
   0      66      1    i       Lscala/collection/Iterable;
   12      27      2    temp8       Lscala/collection/JavaConversions$JIterableWrapper;
   17      22      3    temp9       Ljava/lang/Iterable;

  Signature: length = 0x2
   00 FFFFFFD7 

public java.util.Enumeration asEnumeration(scala.collection.Iterator);
  Code:
   Stack=3, Locals=4, Args_size=2
   0:	aload_1
   1:	instanceof	#127; //class scala/collection/JavaConversions$JEnumerationWrapper
   4:	ifeq	39
   7:	aload_1
   8:	checkcast	#127; //class scala/collection/JavaConversions$JEnumerationWrapper
   11:	astore_2
   12:	aload_2
   13:	invokevirtual	#220; //Method scala/collection/JavaConversions$JEnumerationWrapper.underlying:()Ljava/util/Enumeration;
   16:	astore_3
   17:	iconst_1
   18:	ifeq	25
   21:	aload_3
   22:	goto	51
   25:	new	#29; //class scala/MatchError
   28:	dup
   29:	aload_1
   30:	invokeinterface	#223,  1; //InterfaceMethod scala/collection/Iterator.toString:()Ljava/lang/String;
   35:	invokespecial	#36; //Method scala/MatchError."<init>":(Ljava/lang/String;)V
   38:	athrow
   39:	iconst_1
   40:	ifeq	52
   43:	new	#122; //class scala/collection/JavaConversions$IteratorWrapper
   46:	dup
   47:	aload_1
   48:	invokespecial	#226; //Method scala/collection/JavaConversions$IteratorWrapper."<init>":(Lscala/collection/Iterator;)V
   51:	areturn
   52:	new	#29; //class scala/MatchError
   55:	dup
   56:	aload_1
   57:	invokeinterface	#223,  1; //InterfaceMethod scala/collection/Iterator.toString:()Ljava/lang/String;
   62:	invokespecial	#36; //Method scala/MatchError."<init>":(Ljava/lang/String;)V
   65:	athrow
  LineNumberTable: 
   line 92: 0
   line 21: 17
   line 93: 21
   line 92: 25
   line 21: 39
   line 94: 43
   line 92: 51

  LocalVariableTable: 
   Start  Length  Slot  Name   Signature
   0      66      0    this       Lscala/collection/JavaConversions$;
   0      66      1    i       Lscala/collection/Iterator;
   12      27      2    temp5       Lscala/collection/JavaConversions$JEnumerationWrapper;
   17      22      3    temp6       Ljava/util/Enumeration;

  Signature: length = 0x2
   00 FFFFFFE6 

public java.util.Iterator asIterator(scala.collection.Iterator);
  Code:
   Stack=3, Locals=4, Args_size=2
   0:	aload_1
   1:	instanceof	#139; //class scala/collection/JavaConversions$JIteratorWrapper
   4:	ifeq	39
   7:	aload_1
   8:	checkcast	#139; //class scala/collection/JavaConversions$JIteratorWrapper
   11:	astore_2
   12:	aload_2
   13:	invokevirtual	#234; //Method scala/collection/JavaConversions$JIteratorWrapper.underlying:()Ljava/util/Iterator;
   16:	astore_3
   17:	iconst_1
   18:	ifeq	25
   21:	aload_3
   22:	goto	51
   25:	new	#29; //class scala/MatchError
   28:	dup
   29:	aload_1
   30:	invokeinterface	#223,  1; //InterfaceMethod scala/collection/Iterator.toString:()Ljava/lang/String;
   35:	invokespecial	#36; //Method scala/MatchError."<init>":(Ljava/lang/String;)V
   38:	athrow
   39:	iconst_1
   40:	ifeq	52
   43:	new	#122; //class scala/collection/JavaConversions$IteratorWrapper
   46:	dup
   47:	aload_1
   48:	invokespecial	#226; //Method scala/collection/JavaConversions$IteratorWrapper."<init>":(Lscala/collection/Iterator;)V
   51:	areturn
   52:	new	#29; //class scala/MatchError
   55:	dup
   56:	aload_1
   57:	invokeinterface	#223,  1; //InterfaceMethod scala/collection/Iterator.toString:()Ljava/lang/String;
   62:	invokespecial	#36; //Method scala/MatchError."<init>":(Ljava/lang/String;)V
   65:	athrow
  LineNumberTable: 
   line 74: 0
   line 21: 17
   line 75: 21
   line 74: 25
   line 21: 39
   line 76: 43
   line 74: 51

  LocalVariableTable: 
   Start  Length  Slot  Name   Signature
   0      66      0    this       Lscala/collection/JavaConversions$;
   0      66      1    i       Lscala/collection/Iterator;
   12      27      2    temp2       Lscala/collection/JavaConversions$JIteratorWrapper;
   17      22      3    temp3       Ljava/util/Iterator;

  Signature: length = 0x2
   00 FFFFFFEE 

}

