Compiled from "JavaConversions.scala"
public final class scala.collection.JavaConversions$MutableSetWrapper$ extends java.lang.Object implements scala.ScalaObject
  SourceFile: "JavaConversions.scala"
  Scala: length = 0x
   
  InnerClass: 
   public MutableSetWrapper=class scala/collection/JavaConversions$MutableSetWrapper of class scala/collection/JavaConversions
   public final $anon$4=class scala/collection/JavaConversions$MutableSetWrapper$$anon$4 of class scala/collection/JavaConversions$MutableSetWrapper
  minor version: 0
  major version: 49
  Constant pool:
Asciz	SourceFile;
Asciz	JavaConversions.scala;
Asciz	MODULE$;
Asciz	Lscala/collection/JavaConversions$MutableSetWrapper$;;
Asciz	<clinit>;
Asciz	()V;
Asciz	Code;
Asciz	scala/collection/JavaConversions$MutableSetWrapper$;
class	scala/collection/JavaConversions$MutableSetWrapper$
Asciz	<init>;
NameAndType	"<init>":()V
Method	scala/collection/JavaConversions$MutableSetWrapper$."<init>":()V
Asciz	unapply;
Asciz	(Lscala/collection/JavaConversions$MutableSetWrapper;)Lscala/Option;;
Asciz	LineNumberTable;
Asciz	scala/None$;
class	scala/None$
Asciz	Lscala/None$;;
NameAndType	MODULE$:Lscala/None$;
Field	scala/None$.MODULE$:Lscala/None$;
Asciz	scala/Some;
class	scala/Some
Asciz	scala/collection/JavaConversions$MutableSetWrapper;
class	scala/collection/JavaConversions$MutableSetWrapper
Asciz	underlying;
Asciz	()Lscala/collection/mutable/Set;;
NameAndType	underlying:()Lscala/collection/mutable/Set;
Method	scala/collection/JavaConversions$MutableSetWrapper.underlying:()Lscala/collection/mutable/Set;
Asciz	(Ljava/lang/Object;)V;
NameAndType	"<init>":(Ljava/lang/Object;)V
Method	scala/Some."<init>":(Ljava/lang/Object;)V
Asciz	this;
Asciz	x$0;
Asciz	Lscala/collection/JavaConversions$MutableSetWrapper;;
Asciz	LocalVariableTable;
Asciz	apply;
Asciz	(Lscala/collection/mutable/Set;Lscala/reflect/ClassManifest;)Lscala/collection/JavaConversions$MutableSetWrapper;;
Asciz	(Lscala/collection/mutable/Set;Lscala/reflect/ClassManifest;)V;
NameAndType	"<init>":(Lscala/collection/mutable/Set;Lscala/reflect/ClassManifest;)V
Method	scala/collection/JavaConversions$MutableSetWrapper."<init>":(Lscala/collection/mutable/Set;Lscala/reflect/ClassManifest;)V
Asciz	Lscala/collection/mutable/Set;;
Asciz	m;
Asciz	Lscala/reflect/ClassManifest;;
Asciz	java/lang/Object;
class	java/lang/Object
Method	java/lang/Object."<init>":()V
NameAndType	MODULE$:Lscala/collection/JavaConversions$MutableSetWrapper$;
Field	scala/collection/JavaConversions$MutableSetWrapper$.MODULE$:Lscala/collection/JavaConversions$MutableSetWrapper$;
Asciz	Scala;
Asciz	InnerClasses;
Asciz	scala/collection/JavaConversions;
class	scala/collection/JavaConversions
Asciz	MutableSetWrapper;
Asciz	scala/collection/JavaConversions$MutableSetWrapper$$anon$4;
class	scala/collection/JavaConversions$MutableSetWrapper$$anon$4
Asciz	$anon$4;
Asciz	scala/ScalaObject;
class	scala/ScalaObject

{
public static final scala.collection.JavaConversions$MutableSetWrapper$ MODULE$;
  Signature: Lscala/collection/JavaConversions$MutableSetWrapper$;

public static {};
  Signature: ()V
  Code:
   Stack=1, Locals=0, Args_size=0
	new	class scala/collection/JavaConversions$MutableSetWrapper$
	invokespecial	Method "<init>":()V
	return
  Labels:

public scala.Option unapply(scala.collection.JavaConversions$MutableSetWrapper);
  Signature: (Lscala/collection/JavaConversions$MutableSetWrapper;)Lscala/Option;
  Code:
   Stack=3, Locals=2, Args_size=2
	aload_1
	ifnonnull	l1 // new
	getstatic	Field scala/None$.MODULE$:Lscala/None$;
	goto	l2 // areturn
l1	new	class scala/Some
	dup
	aload_1
	invokevirtual	Method scala/collection/JavaConversions$MutableSetWrapper.underlying:()Lscala/collection/mutable/Set;
	invokespecial	Method scala/Some."<init>":(Ljava/lang/Object;)V
l2	areturn
  Labels:
   	l1 = 10 // new
   	l2 = 21 // areturn
  LocalVariableTable: 
   Start  Length  Slot  Name   Signature
   0      22      0    this       Lscala/collection/JavaConversions$MutableSetWrapper$;
   0      22      1    x$0       Lscala/collection/JavaConversions$MutableSetWrapper;


public scala.collection.JavaConversions$MutableSetWrapper apply(scala.collection.mutable.Set, scala.reflect.ClassManifest);
  Signature: (Lscala/collection/mutable/Set;Lscala/reflect/ClassManifest;)Lscala/collection/JavaConversions$MutableSetWrapper;
  Code:
   Stack=4, Locals=3, Args_size=3
	new	class scala/collection/JavaConversions$MutableSetWrapper
	dup
	aload_1
	aload_2
	invokespecial	Method scala/collection/JavaConversions$MutableSetWrapper."<init>":(Lscala/collection/mutable/Set;Lscala/reflect/ClassManifest;)V
	areturn
  Labels:
  LocalVariableTable: 
   Start  Length  Slot  Name   Signature
   0      10      0    this       Lscala/collection/JavaConversions$MutableSetWrapper$;
   0      10      1    underlying       Lscala/collection/mutable/Set;
   0      10      2    m       Lscala/reflect/ClassManifest;


public scala.collection.JavaConversions$MutableSetWrapper$();
  Signature: ()V
  Code:
   Stack=1, Locals=1, Args_size=1
	aload_0
	invokespecial	Method java/lang/Object."<init>":()V
	aload_0
	putstatic	Field MODULE$:Lscala/collection/JavaConversions$MutableSetWrapper$;
	return
  Labels:

}

