Compiled from "JavaConversions.scala"
public final class scala.collection.JavaConversions$MutableSetWrapper$$anon$3 extends java.lang.Object implements java.util.Iterator
  SourceFile: "JavaConversions.scala"
  Signature: length = 0x2
   00 6F 
  Scala: length = 0x
   
  InnerClass: 
   public MutableSetWrapper=class scala/collection/JavaConversions$MutableSetWrapper of class scala/collection/JavaConversions
   public final $anon$3=class scala/collection/JavaConversions$MutableSetWrapper$$anon$3 of class scala/collection/JavaConversions$MutableSetWrapper
  minor version: 0
  major version: 49
  Constant pool:
Asciz	SourceFile;
Asciz	JavaConversions.scala;
Asciz	$outer;
Asciz	Lscala/collection/JavaConversions$MutableSetWrapper;;
Asciz	prev;
Asciz	Lscala/Option;;
Asciz	Lscala/Option<TA;>;;
Asciz	Signature;
Asciz	ui;
Asciz	Lscala/collection/Iterator;;
Asciz	Lscala/collection/Iterator<TA;>;;
Asciz	<init>;
Asciz	(Lscala/collection/JavaConversions$MutableSetWrapper;)V;
Asciz	Code;
Asciz	LineNumberTable;
Asciz	java/lang/NullPointerException;
class	java/lang/NullPointerException
Asciz	()V;
NameAndType	"<init>":()V
Method	java/lang/NullPointerException."<init>":()V
Asciz	scala/collection/JavaConversions$MutableSetWrapper$$anon$3;
class	scala/collection/JavaConversions$MutableSetWrapper$$anon$3
NameAndType	$outer:Lscala/collection/JavaConversions$MutableSetWrapper;
Field	scala/collection/JavaConversions$MutableSetWrapper$$anon$3.$outer:Lscala/collection/JavaConversions$MutableSetWrapper;
Asciz	java/lang/Object;
class	java/lang/Object
Method	java/lang/Object."<init>":()V
Asciz	scala/collection/JavaConversions$MutableSetWrapper;
class	scala/collection/JavaConversions$MutableSetWrapper
Asciz	underlying;
Asciz	()Lscala/collection/mutable/Set;;
NameAndType	underlying:()Lscala/collection/mutable/Set;
Method	scala/collection/JavaConversions$MutableSetWrapper.underlying:()Lscala/collection/mutable/Set;
Asciz	scala/collection/IterableLike;
class	scala/collection/IterableLike
Asciz	iterator;
Asciz	()Lscala/collection/Iterator;;
NameAndType	iterator:()Lscala/collection/Iterator;
InterfaceMethod	scala/collection/IterableLike.iterator:()Lscala/collection/Iterator;
NameAndType	ui:Lscala/collection/Iterator;
Field	scala/collection/JavaConversions$MutableSetWrapper$$anon$3.ui:Lscala/collection/Iterator;
Asciz	scala/None$;
class	scala/None$
Asciz	MODULE$;
Asciz	Lscala/None$;;
NameAndType	MODULE$:Lscala/None$;
Field	scala/None$.MODULE$:Lscala/None$;
NameAndType	prev:Lscala/Option;
Field	scala/collection/JavaConversions$MutableSetWrapper$$anon$3.prev:Lscala/Option;
Asciz	this;
Asciz	Lscala/collection/JavaConversions$MutableSetWrapper$$anon$3;;
Asciz	LocalVariableTable;
Asciz	(Lscala/collection/JavaConversions$MutableSetWrapper<TA;>;)V;
Asciz	remove;
Asciz	()Lscala/Option;;
NameAndType	prev:()Lscala/Option;
Method	scala/collection/JavaConversions$MutableSetWrapper$$anon$3.prev:()Lscala/Option;
Asciz	scala/Some;
class	scala/Some
Asciz	x;
Asciz	Ljava/lang/Object;;
NameAndType	x:Ljava/lang/Object;
Field	scala/Some.x:Ljava/lang/Object;
Asciz	(Ljava/lang/Object;)Z;
NameAndType	remove:(Ljava/lang/Object;)Z
Method	scala/collection/JavaConversions$MutableSetWrapper.remove:(Ljava/lang/Object;)Z
Asciz	prev_$eq;
Asciz	(Lscala/Option;)V;
NameAndType	prev_$eq:(Lscala/Option;)V
Method	scala/collection/JavaConversions$MutableSetWrapper$$anon$3.prev_$eq:(Lscala/Option;)V
Asciz	scala/MatchError;
class	scala/MatchError
Asciz	scala/Option;
class	scala/Option
Asciz	toString;
Asciz	()Ljava/lang/String;;
NameAndType	toString:()Ljava/lang/String;
Method	scala/Option.toString:()Ljava/lang/String;
Asciz	(Ljava/lang/String;)V;
NameAndType	"<init>":(Ljava/lang/String;)V
Method	scala/MatchError."<init>":(Ljava/lang/String;)V
Asciz	java/lang/IllegalStateException;
class	java/lang/IllegalStateException
Asciz	next must be called at least once before remove;
String	next must be called at least once before remove
Method	java/lang/IllegalStateException."<init>":(Ljava/lang/String;)V
Asciz	temp70;
Asciz	Lscala/Some;;
Asciz	temp71;
Asciz	temp69;
Asciz	next;
Asciz	()Ljava/lang/Object;;
NameAndType	ui:()Lscala/collection/Iterator;
Method	scala/collection/JavaConversions$MutableSetWrapper$$anon$3.ui:()Lscala/collection/Iterator;
Asciz	scala/collection/Iterator;
class	scala/collection/Iterator
NameAndType	next:()Ljava/lang/Object;
InterfaceMethod	scala/collection/Iterator.next:()Ljava/lang/Object;
Asciz	(Ljava/lang/Object;)V;
NameAndType	"<init>":(Ljava/lang/Object;)V
Method	scala/Some."<init>":(Ljava/lang/Object;)V
Asciz	e;
Asciz	()TA;;
Asciz	hasNext;
Asciz	()Z;
NameAndType	hasNext:()Z
InterfaceMethod	scala/collection/Iterator.hasNext:()Z
Asciz	(Lscala/Option<TA;>;)V;
Asciz	()Lscala/Option<TA;>;;
Asciz	()Lscala/collection/Iterator<TA;>;;
Asciz	Ljava/lang/Object;Ljava/util/Iterator<TA;>;;
Asciz	Scala;
Asciz	InnerClasses;
Asciz	scala/collection/JavaConversions;
class	scala/collection/JavaConversions
Asciz	MutableSetWrapper;
Asciz	$anon$3;
Asciz	java/util/Iterator;
class	java/util/Iterator

{
private final scala.collection.JavaConversions$MutableSetWrapper $outer;
  Signature: Lscala/collection/JavaConversions$MutableSetWrapper;

private scala.Option prev;
  Signature: Lscala/Option;
  Signature: length = 0x2
   00 07 

private final scala.collection.Iterator ui;
  Signature: Lscala/collection/Iterator;
  Signature: length = 0x2
   00 0B 

public scala.collection.JavaConversions$MutableSetWrapper$$anon$3(scala.collection.JavaConversions$MutableSetWrapper);
  Signature: (Lscala/collection/JavaConversions$MutableSetWrapper;)V
  Code:
   Stack=2, Locals=2, Args_size=2
	aload_1
	ifnonnull	l1 // aload_0
	new	class java/lang/NullPointerException
	dup
	invokespecial	Method java/lang/NullPointerException."<init>":()V
	athrow
l1	aload_0
	aload_1
	putfield	Field $outer:Lscala/collection/JavaConversions$MutableSetWrapper;
	aload_0
	invokespecial	Method java/lang/Object."<init>":()V
	aload_0
	aload_1
	invokevirtual	Method scala/collection/JavaConversions$MutableSetWrapper.underlying:()Lscala/collection/mutable/Set;
	invokeinterface	InterfaceMethod scala/collection/IterableLike.iterator:()Lscala/collection/Iterator;
	putfield	Field ui:Lscala/collection/Iterator;
	aload_0
	getstatic	Field scala/None$.MODULE$:Lscala/None$;
	putfield	Field prev:Lscala/Option;
	return
  Labels:
   	l1 = 12 // aload_0
  LocalVariableTable: 
   Start  Length  Slot  Name   Signature
   0      42      0    this       Lscala/collection/JavaConversions$MutableSetWrapper$$anon$3;
   0      42      1    $outer       Lscala/collection/JavaConversions$MutableSetWrapper;

  Signature: length = 0x2
   00 35 

public void remove();
  Signature: ()V
  Code:
   Stack=3, Locals=4, Args_size=1
	aload_0
	invokespecial	Method prev:()Lscala/Option;
	astore_3
	aload_3
	instanceof	class scala/Some
	ifeq	l1 // iconst_1
	aload_3
	checkcast	class scala/Some
	astore_1
	aload_1
	getfield	Field scala/Some.x:Ljava/lang/Object;
	astore_2
	iconst_1
	ifeq	l2 // new
	aload_0
	getfield	Field $outer:Lscala/collection/JavaConversions$MutableSetWrapper;
	aload_2
	invokevirtual	Method scala/collection/JavaConversions$MutableSetWrapper.remove:(Ljava/lang/Object;)Z
	pop
	aload_0
	getstatic	Field scala/None$.MODULE$:Lscala/None$;
	invokespecial	Method prev_$eq:(Lscala/Option;)V
	return
l2	new	class scala/MatchError
	dup
	aload_3
	invokevirtual	Method scala/Option.toString:()Ljava/lang/String;
	invokespecial	Method scala/MatchError."<init>":(Ljava/lang/String;)V
	athrow
l1	iconst_1
	ifeq	l3 // new
	new	class java/lang/IllegalStateException
	dup
	ldc	String next must be called at least once before remove
	invokespecial	Method java/lang/IllegalStateException."<init>":(Ljava/lang/String;)V
	athrow
l3	new	class scala/MatchError
	dup
	aload_3
	invokevirtual	Method scala/Option.toString:()Ljava/lang/String;
	invokespecial	Method scala/MatchError."<init>":(Ljava/lang/String;)V
	athrow
  Labels:
   	l2 = 43 // new
   	l1 = 55 // iconst_1
   	l3 = 69 // new
  LocalVariableTable: 
   Start  Length  Slot  Name   Signature
   0      81      0    this       Lscala/collection/JavaConversions$MutableSetWrapper$$anon$3;
   17      38      1    temp70       Lscala/Some;
   22      33      2    temp71       Ljava/lang/Object;
   5      76      3    temp69       Lscala/Option;


public java.lang.Object next();
  Signature: ()Ljava/lang/Object;
  Code:
   Stack=4, Locals=2, Args_size=1
	aload_0
	invokespecial	Method ui:()Lscala/collection/Iterator;
	invokeinterface	InterfaceMethod scala/collection/Iterator.next:()Ljava/lang/Object;
	astore_1
	aload_0
	new	class scala/Some
	dup
	aload_1
	invokespecial	Method scala/Some."<init>":(Ljava/lang/Object;)V
	invokespecial	Method prev_$eq:(Lscala/Option;)V
	aload_1
	areturn
  Labels:
  LocalVariableTable: 
   Start  Length  Slot  Name   Signature
   0      24      0    this       Lscala/collection/JavaConversions$MutableSetWrapper$$anon$3;
   10      13      1    e       Ljava/lang/Object;

  Signature: length = 0x2
   00 67 

public boolean hasNext();
  Signature: ()Z
  Code:
   Stack=1, Locals=1, Args_size=1
	aload_0
	invokespecial	Method ui:()Lscala/collection/Iterator;
	invokeinterface	InterfaceMethod scala/collection/Iterator.hasNext:()Z
	ireturn
  Labels:

private void prev_$eq(scala.Option);
  Signature: (Lscala/Option;)V
  Code:
   Stack=2, Locals=2, Args_size=2
	aload_0
	aload_1
	putfield	Field prev:Lscala/Option;
	return
  Labels:
  Signature: length = 0x2
   00 6C 

private scala.Option prev();
  Signature: ()Lscala/Option;
  Code:
   Stack=1, Locals=1, Args_size=1
	aload_0
	getfield	Field prev:Lscala/Option;
	areturn
  Labels:
  Signature: length = 0x2
   00 6D 

private scala.collection.Iterator ui();
  Signature: ()Lscala/collection/Iterator;
  Code:
   Stack=1, Locals=1, Args_size=1
	aload_0
	getfield	Field ui:Lscala/collection/Iterator;
	areturn
  Labels:
  Signature: length = 0x2
   00 6E 

}

