Compiled from "JavaConversions.scala"
public final class scala.collection.JavaConversions$JSetWrapper$ extends java.lang.Object implements scala.ScalaObject
  SourceFile: "JavaConversions.scala"
  Scala: length = 0x
   
  InnerClass: 
   public JSetWrapper=class scala/collection/JavaConversions$JSetWrapper of class scala/collection/JavaConversions
  minor version: 0
  major version: 49
  Constant pool:
Asciz	SourceFile;
Asciz	JavaConversions.scala;
Asciz	Scala;
Asciz	MODULE$;
Asciz	Lscala/collection/JavaConversions$JSetWrapper$;;
Asciz	<clinit>;
Asciz	()V;
Asciz	Code;
Asciz	scala/collection/JavaConversions$JSetWrapper$;
class	scala/collection/JavaConversions$JSetWrapper$
Asciz	<init>;
NameAndType	"<init>":()V
Method	scala/collection/JavaConversions$JSetWrapper$."<init>":()V
Asciz	unapply;
Asciz	(Lscala/collection/JavaConversions$JSetWrapper;)Lscala/Option;;
Asciz	LineNumberTable;
Asciz	java/lang/Object;
class	java/lang/Object
Asciz	equals;
Asciz	(Ljava/lang/Object;)Z;
NameAndType	equals:(Ljava/lang/Object;)Z
Method	java/lang/Object.equals:(Ljava/lang/Object;)Z
Asciz	scala/None$;
class	scala/None$
Asciz	Lscala/None$;;
NameAndType	MODULE$:Lscala/None$;
Field	scala/None$.MODULE$:Lscala/None$;
Asciz	scala/Some;
class	scala/Some
Asciz	scala/collection/JavaConversions$JSetWrapper;
class	scala/collection/JavaConversions$JSetWrapper
Asciz	underlying;
Asciz	()Ljava/util/Set;;
NameAndType	underlying:()Ljava/util/Set;
Method	scala/collection/JavaConversions$JSetWrapper.underlying:()Ljava/util/Set;
Asciz	(Ljava/lang/Object;)V;
NameAndType	"<init>":(Ljava/lang/Object;)V
Method	scala/Some."<init>":(Ljava/lang/Object;)V
Asciz	this;
Asciz	x$0;
Asciz	Lscala/collection/JavaConversions$JSetWrapper;;
Asciz	LocalVariableTable;
Asciz	apply;
Asciz	(Ljava/util/Set;)Lscala/collection/JavaConversions$JSetWrapper;;
Asciz	(Ljava/util/Set;)V;
NameAndType	"<init>":(Ljava/util/Set;)V
Method	scala/collection/JavaConversions$JSetWrapper."<init>":(Ljava/util/Set;)V
Asciz	Ljava/util/Set;;
Method	java/lang/Object."<init>":()V
NameAndType	MODULE$:Lscala/collection/JavaConversions$JSetWrapper$;
Field	scala/collection/JavaConversions$JSetWrapper$.MODULE$:Lscala/collection/JavaConversions$JSetWrapper$;
Asciz	InnerClasses;
Asciz	scala/collection/JavaConversions;
class	scala/collection/JavaConversions
Asciz	JSetWrapper;
Asciz	scala/ScalaObject;
class	scala/ScalaObject

{
public static final scala.collection.JavaConversions$JSetWrapper$ MODULE$;
  Signature: Lscala/collection/JavaConversions$JSetWrapper$;

public static {};
  Signature: ()V
  Code:
   Stack=1, Locals=0, Args_size=0
	new	class scala/collection/JavaConversions$JSetWrapper$
	invokespecial	Method "<init>":()V
	return
  Labels:

public scala.Option unapply(scala.collection.JavaConversions$JSetWrapper);
  Signature: (Lscala/collection/JavaConversions$JSetWrapper;)Lscala/Option;
  Code:
   Stack=3, Locals=2, Args_size=2
	aload_1
	dup
	pop
	ifnull	l1 // getstatic
	aload_1
	aconst_null
	invokevirtual	Method java/lang/Object.equals:(Ljava/lang/Object;)Z
	ifeq	l2 // new
l1	getstatic	Field scala/None$.MODULE$:Lscala/None$;
	goto	l3 // areturn
l2	new	class scala/Some
	dup
	aload_1
	invokevirtual	Method scala/collection/JavaConversions$JSetWrapper.underlying:()Ljava/util/Set;
	invokespecial	Method scala/Some."<init>":(Ljava/lang/Object;)V
l3	areturn
  Labels:
   	l1 = 14 // getstatic
   	l2 = 20 // new
   	l3 = 31 // areturn
  LocalVariableTable: 
   Start  Length  Slot  Name   Signature
   0      32      0    this       Lscala/collection/JavaConversions$JSetWrapper$;
   0      32      1    x$0       Lscala/collection/JavaConversions$JSetWrapper;


public scala.collection.JavaConversions$JSetWrapper apply(java.util.Set);
  Signature: (Ljava/util/Set;)Lscala/collection/JavaConversions$JSetWrapper;
  Code:
   Stack=3, Locals=2, Args_size=2
	new	class scala/collection/JavaConversions$JSetWrapper
	dup
	aload_1
	invokespecial	Method scala/collection/JavaConversions$JSetWrapper."<init>":(Ljava/util/Set;)V
	areturn
  Labels:
  LocalVariableTable: 
   Start  Length  Slot  Name   Signature
   0      9      0    this       Lscala/collection/JavaConversions$JSetWrapper$;
   0      9      1    underlying       Ljava/util/Set;


public scala.collection.JavaConversions$JSetWrapper$();
  Signature: ()V
  Code:
   Stack=1, Locals=1, Args_size=1
	aload_0
	invokespecial	Method java/lang/Object."<init>":()V
	aload_0
	putstatic	Field MODULE$:Lscala/collection/JavaConversions$JSetWrapper$;
	return
  Labels:

}

