Compiled from "JavaConversions.scala"
public final class scala.collection.JavaConversions$MutableMapWrapperLike$$anon$1$$anon$5$$anon$6 extends java.lang.Object implements java.util.Map$Entry
  SourceFile: "JavaConversions.scala"
  Signature: length = 0x2
   00 57 
  Scala: length = 0x
   
  InnerClass: 
   public abstract Entry=class java/util/Map$Entry of class java/util/Map
   public abstract MutableMapWrapperLike=class scala/collection/JavaConversions$MutableMapWrapperLike of class scala/collection/JavaConversions
   public final $anon$1=class scala/collection/JavaConversions$MutableMapWrapperLike$$anon$1 of class scala/collection/JavaConversions$MutableMapWrapperLike
   public final $anon$5=class scala/collection/JavaConversions$MutableMapWrapperLike$$anon$1$$anon$5 of class scala/collection/JavaConversions$MutableMapWrapperLike$$anon$1
   public final $anon$6=class scala/collection/JavaConversions$MutableMapWrapperLike$$anon$1$$anon$5$$anon$6 of class scala/collection/JavaConversions$MutableMapWrapperLike$$anon$1$$anon$5
  minor version: 0
  major version: 49
  Constant pool:
Asciz	SourceFile;
Asciz	JavaConversions.scala;
Asciz	v$1;
Asciz	Ljava/lang/Object;;
Asciz	k$1;
Asciz	$outer;
Asciz	Lscala/collection/JavaConversions$MutableMapWrapperLike$$anon$1$$anon$5;;
Asciz	getKey;
Asciz	()Ljava/lang/Object;;
Asciz	Code;
Asciz	LineNumberTable;
Asciz	scala/collection/JavaConversions$MutableMapWrapperLike$$anon$1$$anon$5$$anon$6;
class	scala/collection/JavaConversions$MutableMapWrapperLike$$anon$1$$anon$5$$anon$6
NameAndType	k$1:Ljava/lang/Object;
Field	scala/collection/JavaConversions$MutableMapWrapperLike$$anon$1$$anon$5$$anon$6.k$1:Ljava/lang/Object;
Asciz	()TA;;
Asciz	Signature;
Asciz	getValue;
NameAndType	v$1:Ljava/lang/Object;
Field	scala/collection/JavaConversions$MutableMapWrapperLike$$anon$1$$anon$5$$anon$6.v$1:Ljava/lang/Object;
Asciz	()TB;;
Asciz	setValue;
Asciz	(Ljava/lang/Object;)Ljava/lang/Object;;
NameAndType	$outer:Lscala/collection/JavaConversions$MutableMapWrapperLike$$anon$1$$anon$5;
Field	scala/collection/JavaConversions$MutableMapWrapperLike$$anon$1$$anon$5$$anon$6.$outer:Lscala/collection/JavaConversions$MutableMapWrapperLike$$anon$1$$anon$5;
Asciz	scala/collection/JavaConversions$MutableMapWrapperLike$$anon$1$$anon$5;
class	scala/collection/JavaConversions$MutableMapWrapperLike$$anon$1$$anon$5
Asciz	scala$collection$JavaConversions$MutableMapWrapperLike$$anon$$anon$$$outer;
Asciz	()Lscala/collection/JavaConversions$MutableMapWrapperLike$$anon$1;;
NameAndType	scala$collection$JavaConversions$MutableMapWrapperLike$$anon$$anon$$$outer:()Lscala/collection/JavaConversions$MutableMapWrapperLike$$anon$1;
Method	scala/collection/JavaConversions$MutableMapWrapperLike$$anon$1$$anon$5.scala$collection$JavaConversions$MutableMapWrapperLike$$anon$$anon$$$outer:()Lscala/collection/JavaConversions$MutableMapWrapperLike$$anon$1;
Asciz	scala/collection/JavaConversions$MutableMapWrapperLike$$anon$1;
class	scala/collection/JavaConversions$MutableMapWrapperLike$$anon$1
Asciz	scala$collection$JavaConversions$MutableMapWrapperLike$$anon$$$outer;
Asciz	()Lscala/collection/JavaConversions$MutableMapWrapperLike;;
NameAndType	scala$collection$JavaConversions$MutableMapWrapperLike$$anon$$$outer:()Lscala/collection/JavaConversions$MutableMapWrapperLike;
Method	scala/collection/JavaConversions$MutableMapWrapperLike$$anon$1.scala$collection$JavaConversions$MutableMapWrapperLike$$anon$$$outer:()Lscala/collection/JavaConversions$MutableMapWrapperLike;
Asciz	scala/collection/JavaConversions$MutableMapWrapperLike;
class	scala/collection/JavaConversions$MutableMapWrapperLike
Asciz	put;
Asciz	(Ljava/lang/Object;Ljava/lang/Object;)Ljava/lang/Object;;
NameAndType	put:(Ljava/lang/Object;Ljava/lang/Object;)Ljava/lang/Object;
Method	scala/collection/JavaConversions$MutableMapWrapperLike.put:(Ljava/lang/Object;Ljava/lang/Object;)Ljava/lang/Object;
Asciz	this;
Asciz	Lscala/collection/JavaConversions$MutableMapWrapperLike$$anon$1$$anon$5$$anon$6;;
Asciz	v1;
Asciz	LocalVariableTable;
Asciz	(TB;)TB;;
Asciz	equals;
Asciz	(Ljava/lang/Object;)Z;
Asciz	java/util/Map$Entry;
class	java/util/Map$Entry
NameAndType	getKey:()Ljava/lang/Object;
InterfaceMethod	java/util/Map$Entry.getKey:()Ljava/lang/Object;
Asciz	java/lang/Number;
class	java/lang/Number
Asciz	java/lang/Character;
class	java/lang/Character
Asciz	scala/runtime/BoxesRunTime;
class	scala/runtime/BoxesRunTime
Asciz	equals2;
Asciz	(Ljava/lang/Object;Ljava/lang/Object;)Z;
NameAndType	equals2:(Ljava/lang/Object;Ljava/lang/Object;)Z
Method	scala/runtime/BoxesRunTime.equals2:(Ljava/lang/Object;Ljava/lang/Object;)Z
Asciz	java/lang/Object;
class	java/lang/Object
NameAndType	equals:(Ljava/lang/Object;)Z
Method	java/lang/Object.equals:(Ljava/lang/Object;)Z
NameAndType	getValue:()Ljava/lang/Object;
InterfaceMethod	java/util/Map$Entry.getValue:()Ljava/lang/Object;
Asciz	other;
Asciz	x0;
Asciz	y0;
Asciz	temp93;
Asciz	Ljava/util/Map$Entry;;
Asciz	x1;
Asciz	y1;
Asciz	<init>;
Asciz	(Lscala/collection/JavaConversions$MutableMapWrapperLike$$anon$1$$anon$5;Ljava/lang/Object;Ljava/lang/Object;)V;
Asciz	java/lang/NullPointerException;
class	java/lang/NullPointerException
Asciz	()V;
NameAndType	"<init>":()V
Method	java/lang/NullPointerException."<init>":()V
Method	java/lang/Object."<init>":()V
Asciz	(Lscala/collection/JavaConversions$MutableMapWrapperLike<TA;TB;>.$anon$1.$anon$5;)V;
Asciz	Ljava/lang/Object;Ljava/util/Map$Entry<TA;TB;>;;
Asciz	Scala;
Asciz	InnerClasses;
Asciz	java/util/Map;
class	java/util/Map
Asciz	Entry;
Asciz	scala/collection/JavaConversions;
class	scala/collection/JavaConversions
Asciz	MutableMapWrapperLike;
Asciz	$anon$1;
Asciz	$anon$5;
Asciz	$anon$6;

{
private final java.lang.Object v$1;
  Signature: Ljava/lang/Object;

private final java.lang.Object k$1;
  Signature: Ljava/lang/Object;

private final scala.collection.JavaConversions$MutableMapWrapperLike$$anon$1$$anon$5 $outer;
  Signature: Lscala/collection/JavaConversions$MutableMapWrapperLike$$anon$1$$anon$5;

public java.lang.Object getKey();
  Signature: ()Ljava/lang/Object;
  Code:
   Stack=1, Locals=1, Args_size=1
	aload_0
	getfield	Field k$1:Ljava/lang/Object;
	areturn
  Labels:
  Signature: length = 0x2
   00 10 

public java.lang.Object getValue();
  Signature: ()Ljava/lang/Object;
  Code:
   Stack=1, Locals=1, Args_size=1
	aload_0
	getfield	Field v$1:Ljava/lang/Object;
	areturn
  Labels:
  Signature: length = 0x2
   00 15 

public java.lang.Object setValue(java.lang.Object);
  Signature: (Ljava/lang/Object;)Ljava/lang/Object;
  Code:
   Stack=3, Locals=2, Args_size=2
	aload_0
	getfield	Field $outer:Lscala/collection/JavaConversions$MutableMapWrapperLike$$anon$1$$anon$5;
	invokevirtual	Method scala/collection/JavaConversions$MutableMapWrapperLike$$anon$1$$anon$5.scala$collection$JavaConversions$MutableMapWrapperLike$$anon$$anon$$$outer:()Lscala/collection/JavaConversions$MutableMapWrapperLike$$anon$1;
	invokevirtual	Method scala/collection/JavaConversions$MutableMapWrapperLike$$anon$1.scala$collection$JavaConversions$MutableMapWrapperLike$$anon$$$outer:()Lscala/collection/JavaConversions$MutableMapWrapperLike;
	aload_0
	getfield	Field k$1:Ljava/lang/Object;
	aload_1
	invokevirtual	Method scala/collection/JavaConversions$MutableMapWrapperLike.put:(Ljava/lang/Object;Ljava/lang/Object;)Ljava/lang/Object;
	areturn
  Labels:
  LocalVariableTable: 
   Start  Length  Slot  Name   Signature
   0      19      0    this       Lscala/collection/JavaConversions$MutableMapWrapperLike$$anon$1$$anon$5$$anon$6;
   0      19      1    v1       Ljava/lang/Object;

  Signature: length = 0x2
   00 30 

public boolean equals(java.lang.Object);
  Signature: (Ljava/lang/Object;)Z
  Code:
   Stack=2, Locals=7, Args_size=2
	aload_1
	instanceof	class java/util/Map$Entry
	ifeq	l1 // iconst_0
	aload_1
	checkcast	class java/util/Map$Entry
	astore	4
	aload_0
	getfield	Field k$1:Ljava/lang/Object;
	aload	4
	invokeinterface	InterfaceMethod java/util/Map$Entry.getKey:()Ljava/lang/Object;
	astore_3
	astore_2
	aload_2
	aload_3
	if_acmpne	l2 // aload_2
	iconst_1
	goto	l3 // ifeq
l2	aload_2
	ifnonnull	l4 // aload_2
	iconst_0
	goto	l3 // ifeq
l4	aload_2
	instanceof	class java/lang/Number
	ifne	l5 // aload_2
	aload_2
	instanceof	class java/lang/Character
	ifeq	l6 // aload_2
l5	aload_2
	aload_3
	invokestatic	Method scala/runtime/BoxesRunTime.equals2:(Ljava/lang/Object;Ljava/lang/Object;)Z
	goto	l3 // ifeq
l6	aload_2
	aload_3
	invokevirtual	Method java/lang/Object.equals:(Ljava/lang/Object;)Z
l3	ifeq	l7 // iconst_0
	aload_0
	getfield	Field v$1:Ljava/lang/Object;
	aload	4
	invokeinterface	InterfaceMethod java/util/Map$Entry.getValue:()Ljava/lang/Object;
	astore	6
	astore	5
	aload	5
	aload	6
	if_acmpne	l8 // aload
	iconst_1
	goto	l9 // ifeq
l8	aload	5
	ifnonnull	l10 // aload
	iconst_0
	goto	l9 // ifeq
l10	aload	5
	instanceof	class java/lang/Number
	ifne	l11 // aload
	aload	5
	instanceof	class java/lang/Character
	ifeq	l12 // aload
l11	aload	5
	aload	6
	invokestatic	Method scala/runtime/BoxesRunTime.equals2:(Ljava/lang/Object;Ljava/lang/Object;)Z
	goto	l9 // ifeq
l12	aload	5
	aload	6
	invokevirtual	Method java/lang/Object.equals:(Ljava/lang/Object;)Z
l9	ifeq	l7 // iconst_0
	iconst_1
	goto	l13 // ireturn
l7	iconst_0
	goto	l13 // ireturn
l1	iconst_0
l13	ireturn
  Labels:
   	l2 = 35 // aload_2
   	l4 = 43 // aload_2
   	l5 = 57 // aload_2
   	l6 = 65 // aload_2
   	l3 = 70 // ifeq
   	l8 = 99 // aload
   	l10 = 108 // aload
   	l11 = 124 // aload
   	l12 = 134 // aload
   	l9 = 141 // ifeq
   	l7 = 148 // iconst_0
   	l1 = 152 // iconst_0
   	l13 = 153 // ireturn
  LocalVariableTable: 
   Start  Length  Slot  Name   Signature
   0      154      0    this       Lscala/collection/JavaConversions$MutableMapWrapperLike$$anon$1$$anon$5$$anon$6;
   0      154      1    other       Ljava/lang/Object;
   31      42      2    x0       Ljava/lang/Object;
   31      42      3    y0       Ljava/lang/Object;
   13      139      4    temp93       Ljava/util/Map$Entry;
   95      49      5    x1       Ljava/lang/Object;
   95      49      6    y1       Ljava/lang/Object;


public scala.collection.JavaConversions$MutableMapWrapperLike$$anon$1$$anon$5$$anon$6(scala.collection.JavaConversions$MutableMapWrapperLike$$anon$1$$anon$5, java.lang.Object, java.lang.Object);
  Signature: (Lscala/collection/JavaConversions$MutableMapWrapperLike$$anon$1$$anon$5;Ljava/lang/Object;Ljava/lang/Object;)V
  Code:
   Stack=2, Locals=4, Args_size=4
	aload_1
	ifnonnull	l1 // aload_0
	new	class java/lang/NullPointerException
	dup
	invokespecial	Method java/lang/NullPointerException."<init>":()V
	athrow
l1	aload_0
	aload_1
	putfield	Field $outer:Lscala/collection/JavaConversions$MutableMapWrapperLike$$anon$1$$anon$5;
	aload_0
	aload_2
	putfield	Field k$1:Ljava/lang/Object;
	aload_0
	aload_3
	putfield	Field v$1:Ljava/lang/Object;
	aload_0
	invokespecial	Method java/lang/Object."<init>":()V
	return
  Labels:
   	l1 = 12 // aload_0
  LocalVariableTable: 
   Start  Length  Slot  Name   Signature
   0      32      0    this       Lscala/collection/JavaConversions$MutableMapWrapperLike$$anon$1$$anon$5$$anon$6;
   0      32      1    $outer       Lscala/collection/JavaConversions$MutableMapWrapperLike$$anon$1$$anon$5;

  Signature: length = 0x2
   00 56 

}

