Compiled from "JavaConversions.scala"
public class scala.collection.JavaConversions$JIteratorWrapper extends java.lang.Object implements scala.collection.Iterator,scala.ScalaObject,scala.Product,java.io.Serializable
  SourceFile: "JavaConversions.scala"
  Signature: length = 0x2
   01 FFFFFF9E 
  Scala: length = 0x
   
  InnerClass: 
   public abstract $less$colon$less=class scala/Predef$$less$colon$less of class scala/Predef
   public GroupedIterator=class scala/collection/Iterator$GroupedIterator of class scala/collection/Iterator
   public JIteratorWrapper=class scala/collection/JavaConversions$JIteratorWrapper of class scala/collection/JavaConversions
  minor version: 0
  major version: 49
  Constant pool:
Asciz	SourceFile;
Asciz	JavaConversions.scala;
Asciz	underlying;
Asciz	Ljava/util/Iterator;;
Asciz	Ljava/util/Iterator<TA;>;;
Asciz	Signature;
Asciz	productIterator;
Asciz	()Lscala/collection/Iterator;;
Asciz	Code;
Asciz	LineNumberTable;
Asciz	scala/Product$class;
class	scala/Product$class
Asciz	(Lscala/Product;)Lscala/collection/Iterator;;
NameAndType	productIterator:(Lscala/Product;)Lscala/collection/Iterator;
Method	scala/Product$class.productIterator:(Lscala/Product;)Lscala/collection/Iterator;
Asciz	productElements;
NameAndType	productElements:(Lscala/Product;)Lscala/collection/Iterator;
Method	scala/Product$class.productElements:(Lscala/Product;)Lscala/collection/Iterator;
Asciz	Deprecated;
Asciz	take;
Asciz	(I)Lscala/collection/Iterator;;
Asciz	scala/collection/Iterator$class;
class	scala/collection/Iterator$class
Asciz	(Lscala/collection/Iterator;I)Lscala/collection/Iterator;;
NameAndType	take:(Lscala/collection/Iterator;I)Lscala/collection/Iterator;
Method	scala/collection/Iterator$class.take:(Lscala/collection/Iterator;I)Lscala/collection/Iterator;
Asciz	this;
Asciz	Lscala/collection/JavaConversions$JIteratorWrapper;;
Asciz	n;
Asciz	I;
Asciz	LocalVariableTable;
Asciz	drop;
NameAndType	drop:(Lscala/collection/Iterator;I)Lscala/collection/Iterator;
Method	scala/collection/Iterator$class.drop:(Lscala/collection/Iterator;I)Lscala/collection/Iterator;
Asciz	slice;
Asciz	(II)Lscala/collection/Iterator;;
Asciz	(Lscala/collection/Iterator;II)Lscala/collection/Iterator;;
NameAndType	slice:(Lscala/collection/Iterator;II)Lscala/collection/Iterator;
Method	scala/collection/Iterator$class.slice:(Lscala/collection/Iterator;II)Lscala/collection/Iterator;
Asciz	from;
Asciz	until;
Asciz	map;
Asciz	(Lscala/Function1;)Lscala/collection/Iterator;;
Asciz	(Lscala/collection/Iterator;Lscala/Function1;)Lscala/collection/Iterator;;
NameAndType	map:(Lscala/collection/Iterator;Lscala/Function1;)Lscala/collection/Iterator;
Method	scala/collection/Iterator$class.map:(Lscala/collection/Iterator;Lscala/Function1;)Lscala/collection/Iterator;
Asciz	f;
Asciz	Lscala/Function1;;
Asciz	$plus$plus;
Asciz	(Lscala/Function0;)Lscala/collection/Iterator;;
Asciz	(Lscala/collection/Iterator;Lscala/Function0;)Lscala/collection/Iterator;;
NameAndType	$plus$plus:(Lscala/collection/Iterator;Lscala/Function0;)Lscala/collection/Iterator;
Method	scala/collection/Iterator$class.$plus$plus:(Lscala/collection/Iterator;Lscala/Function0;)Lscala/collection/Iterator;
Asciz	that;
Asciz	Lscala/Function0;;
Asciz	flatMap;
NameAndType	flatMap:(Lscala/collection/Iterator;Lscala/Function1;)Lscala/collection/Iterator;
Method	scala/collection/Iterator$class.flatMap:(Lscala/collection/Iterator;Lscala/Function1;)Lscala/collection/Iterator;
Asciz	filter;
NameAndType	filter:(Lscala/collection/Iterator;Lscala/Function1;)Lscala/collection/Iterator;
Method	scala/collection/Iterator$class.filter:(Lscala/collection/Iterator;Lscala/Function1;)Lscala/collection/Iterator;
Asciz	p;
Asciz	withFilter;
NameAndType	withFilter:(Lscala/collection/Iterator;Lscala/Function1;)Lscala/collection/Iterator;
Method	scala/collection/Iterator$class.withFilter:(Lscala/collection/Iterator;Lscala/Function1;)Lscala/collection/Iterator;
Asciz	filterNot;
NameAndType	filterNot:(Lscala/collection/Iterator;Lscala/Function1;)Lscala/collection/Iterator;
Method	scala/collection/Iterator$class.filterNot:(Lscala/collection/Iterator;Lscala/Function1;)Lscala/collection/Iterator;
Asciz	partialMap;
Asciz	(Lscala/PartialFunction;)Lscala/collection/Iterator;;
Asciz	(Lscala/collection/Iterator;Lscala/PartialFunction;)Lscala/collection/Iterator;;
NameAndType	partialMap:(Lscala/collection/Iterator;Lscala/PartialFunction;)Lscala/collection/Iterator;
Method	scala/collection/Iterator$class.partialMap:(Lscala/collection/Iterator;Lscala/PartialFunction;)Lscala/collection/Iterator;
Asciz	pf;
Asciz	Lscala/PartialFunction;;
Asciz	takeWhile;
NameAndType	takeWhile:(Lscala/collection/Iterator;Lscala/Function1;)Lscala/collection/Iterator;
Method	scala/collection/Iterator$class.takeWhile:(Lscala/collection/Iterator;Lscala/Function1;)Lscala/collection/Iterator;
Asciz	partition;
Asciz	(Lscala/Function1;)Lscala/Tuple2;;
Asciz	(Lscala/collection/Iterator;Lscala/Function1;)Lscala/Tuple2;;
NameAndType	partition:(Lscala/collection/Iterator;Lscala/Function1;)Lscala/Tuple2;
Method	scala/collection/Iterator$class.partition:(Lscala/collection/Iterator;Lscala/Function1;)Lscala/Tuple2;
Asciz	dropWhile;
NameAndType	dropWhile:(Lscala/collection/Iterator;Lscala/Function1;)Lscala/collection/Iterator;
Method	scala/collection/Iterator$class.dropWhile:(Lscala/collection/Iterator;Lscala/Function1;)Lscala/collection/Iterator;
Asciz	zip;
Asciz	(Lscala/collection/Iterator;)Lscala/collection/Iterator;;
Asciz	(Lscala/collection/Iterator;Lscala/collection/Iterator;)Lscala/collection/Iterator;;
NameAndType	zip:(Lscala/collection/Iterator;Lscala/collection/Iterator;)Lscala/collection/Iterator;
Method	scala/collection/Iterator$class.zip:(Lscala/collection/Iterator;Lscala/collection/Iterator;)Lscala/collection/Iterator;
Asciz	Lscala/collection/Iterator;;
Asciz	padTo;
Asciz	(ILjava/lang/Object;)Lscala/collection/Iterator;;
Asciz	(Lscala/collection/Iterator;ILjava/lang/Object;)Lscala/collection/Iterator;;
NameAndType	padTo:(Lscala/collection/Iterator;ILjava/lang/Object;)Lscala/collection/Iterator;
Method	scala/collection/Iterator$class.padTo:(Lscala/collection/Iterator;ILjava/lang/Object;)Lscala/collection/Iterator;
Asciz	len;
Asciz	elem;
Asciz	Ljava/lang/Object;;
Asciz	zipWithIndex;
NameAndType	zipWithIndex:(Lscala/collection/Iterator;)Lscala/collection/Iterator;
Method	scala/collection/Iterator$class.zipWithIndex:(Lscala/collection/Iterator;)Lscala/collection/Iterator;
Asciz	zipAll;
Asciz	(Lscala/collection/Iterator;Ljava/lang/Object;Ljava/lang/Object;)Lscala/collection/Iterator;;
Asciz	(Lscala/collection/Iterator;Lscala/collection/Iterator;Ljava/lang/Object;Ljava/lang/Object;)Lscala/collection/Iterator;;
NameAndType	zipAll:(Lscala/collection/Iterator;Lscala/collection/Iterator;Ljava/lang/Object;Ljava/lang/Object;)Lscala/collection/Iterator;
Method	scala/collection/Iterator$class.zipAll:(Lscala/collection/Iterator;Lscala/collection/Iterator;Ljava/lang/Object;Ljava/lang/Object;)Lscala/collection/Iterator;
Asciz	thisElem;
Asciz	thatElem;
Asciz	foreach;
Asciz	(Lscala/Function1;)V;
Asciz	(Lscala/collection/Iterator;Lscala/Function1;)V;
NameAndType	foreach:(Lscala/collection/Iterator;Lscala/Function1;)V
Method	scala/collection/Iterator$class.foreach:(Lscala/collection/Iterator;Lscala/Function1;)V
Asciz	forall;
Asciz	(Lscala/Function1;)Z;
Asciz	(Lscala/collection/Iterator;Lscala/Function1;)Z;
NameAndType	forall:(Lscala/collection/Iterator;Lscala/Function1;)Z
Method	scala/collection/Iterator$class.forall:(Lscala/collection/Iterator;Lscala/Function1;)Z
Asciz	exists;
NameAndType	exists:(Lscala/collection/Iterator;Lscala/Function1;)Z
Method	scala/collection/Iterator$class.exists:(Lscala/collection/Iterator;Lscala/Function1;)Z
Asciz	contains;
Asciz	(Ljava/lang/Object;)Z;
Asciz	(Lscala/collection/Iterator;Ljava/lang/Object;)Z;
NameAndType	contains:(Lscala/collection/Iterator;Ljava/lang/Object;)Z
Method	scala/collection/Iterator$class.contains:(Lscala/collection/Iterator;Ljava/lang/Object;)Z
Asciz	find;
Asciz	(Lscala/Function1;)Lscala/Option;;
Asciz	(Lscala/collection/Iterator;Lscala/Function1;)Lscala/Option;;
NameAndType	find:(Lscala/collection/Iterator;Lscala/Function1;)Lscala/Option;
Method	scala/collection/Iterator$class.find:(Lscala/collection/Iterator;Lscala/Function1;)Lscala/Option;
Asciz	indexWhere;
Asciz	(Lscala/Function1;)I;
Asciz	(Lscala/collection/Iterator;Lscala/Function1;)I;
NameAndType	indexWhere:(Lscala/collection/Iterator;Lscala/Function1;)I
Method	scala/collection/Iterator$class.indexWhere:(Lscala/collection/Iterator;Lscala/Function1;)I
Asciz	indexOf;
Asciz	(Ljava/lang/Object;)I;
Asciz	(Lscala/collection/Iterator;Ljava/lang/Object;)I;
NameAndType	indexOf:(Lscala/collection/Iterator;Ljava/lang/Object;)I
Method	scala/collection/Iterator$class.indexOf:(Lscala/collection/Iterator;Ljava/lang/Object;)I
Asciz	foldLeft;
Asciz	(Ljava/lang/Object;Lscala/Function2;)Ljava/lang/Object;;
Asciz	(Lscala/collection/Iterator;Ljava/lang/Object;Lscala/Function2;)Ljava/lang/Object;;
NameAndType	foldLeft:(Lscala/collection/Iterator;Ljava/lang/Object;Lscala/Function2;)Ljava/lang/Object;
Method	scala/collection/Iterator$class.foldLeft:(Lscala/collection/Iterator;Ljava/lang/Object;Lscala/Function2;)Ljava/lang/Object;
Asciz	z;
Asciz	op;
Asciz	Lscala/Function2;;
Asciz	foldRight;
NameAndType	foldRight:(Lscala/collection/Iterator;Ljava/lang/Object;Lscala/Function2;)Ljava/lang/Object;
Method	scala/collection/Iterator$class.foldRight:(Lscala/collection/Iterator;Ljava/lang/Object;Lscala/Function2;)Ljava/lang/Object;
Asciz	$div$colon;
NameAndType	$div$colon:(Lscala/collection/Iterator;Ljava/lang/Object;Lscala/Function2;)Ljava/lang/Object;
Method	scala/collection/Iterator$class.$div$colon:(Lscala/collection/Iterator;Ljava/lang/Object;Lscala/Function2;)Ljava/lang/Object;
Asciz	$colon$bslash;
NameAndType	$colon$bslash:(Lscala/collection/Iterator;Ljava/lang/Object;Lscala/Function2;)Ljava/lang/Object;
Method	scala/collection/Iterator$class.$colon$bslash:(Lscala/collection/Iterator;Ljava/lang/Object;Lscala/Function2;)Ljava/lang/Object;
Asciz	reduceLeft;
Asciz	(Lscala/Function2;)Ljava/lang/Object;;
Asciz	(Lscala/collection/Iterator;Lscala/Function2;)Ljava/lang/Object;;
NameAndType	reduceLeft:(Lscala/collection/Iterator;Lscala/Function2;)Ljava/lang/Object;
Method	scala/collection/Iterator$class.reduceLeft:(Lscala/collection/Iterator;Lscala/Function2;)Ljava/lang/Object;
Asciz	reduceRight;
NameAndType	reduceRight:(Lscala/collection/Iterator;Lscala/Function2;)Ljava/lang/Object;
Method	scala/collection/Iterator$class.reduceRight:(Lscala/collection/Iterator;Lscala/Function2;)Ljava/lang/Object;
Asciz	reduceLeftOption;
Asciz	(Lscala/Function2;)Lscala/Option;;
Asciz	(Lscala/collection/Iterator;Lscala/Function2;)Lscala/Option;;
NameAndType	reduceLeftOption:(Lscala/collection/Iterator;Lscala/Function2;)Lscala/Option;
Method	scala/collection/Iterator$class.reduceLeftOption:(Lscala/collection/Iterator;Lscala/Function2;)Lscala/Option;
Asciz	reduceRightOption;
NameAndType	reduceRightOption:(Lscala/collection/Iterator;Lscala/Function2;)Lscala/Option;
Method	scala/collection/Iterator$class.reduceRightOption:(Lscala/collection/Iterator;Lscala/Function2;)Lscala/Option;
Asciz	buffered;
Asciz	()Lscala/collection/BufferedIterator;;
Asciz	(Lscala/collection/Iterator;)Lscala/collection/BufferedIterator;;
NameAndType	buffered:(Lscala/collection/Iterator;)Lscala/collection/BufferedIterator;
Method	scala/collection/Iterator$class.buffered:(Lscala/collection/Iterator;)Lscala/collection/BufferedIterator;
Asciz	grouped;
Asciz	(I)Lscala/collection/Iterator$GroupedIterator;;
Asciz	(Lscala/collection/Iterator;I)Lscala/collection/Iterator$GroupedIterator;;
NameAndType	grouped:(Lscala/collection/Iterator;I)Lscala/collection/Iterator$GroupedIterator;
Method	scala/collection/Iterator$class.grouped:(Lscala/collection/Iterator;I)Lscala/collection/Iterator$GroupedIterator;
Asciz	size;
Asciz	sliding;
Asciz	(II)Lscala/collection/Iterator$GroupedIterator;;
Asciz	(Lscala/collection/Iterator;II)Lscala/collection/Iterator$GroupedIterator;;
NameAndType	sliding:(Lscala/collection/Iterator;II)Lscala/collection/Iterator$GroupedIterator;
Method	scala/collection/Iterator$class.sliding:(Lscala/collection/Iterator;II)Lscala/collection/Iterator$GroupedIterator;
Asciz	step;
Asciz	length;
Asciz	()I;
Asciz	(Lscala/collection/Iterator;)I;
NameAndType	length:(Lscala/collection/Iterator;)I
Method	scala/collection/Iterator$class.length:(Lscala/collection/Iterator;)I
Asciz	duplicate;
Asciz	()Lscala/Tuple2;;
Asciz	(Lscala/collection/Iterator;)Lscala/Tuple2;;
NameAndType	duplicate:(Lscala/collection/Iterator;)Lscala/Tuple2;
Method	scala/collection/Iterator$class.duplicate:(Lscala/collection/Iterator;)Lscala/Tuple2;
Asciz	patch;
Asciz	(ILscala/collection/Iterator;I)Lscala/collection/Iterator;;
Asciz	(Lscala/collection/Iterator;ILscala/collection/Iterator;I)Lscala/collection/Iterator;;
NameAndType	patch:(Lscala/collection/Iterator;ILscala/collection/Iterator;I)Lscala/collection/Iterator;
Method	scala/collection/Iterator$class.patch:(Lscala/collection/Iterator;ILscala/collection/Iterator;I)Lscala/collection/Iterator;
Asciz	patchElems;
Asciz	replaced;
Asciz	copyToArray;
Asciz	(Ljava/lang/Object;II)V;
Asciz	(Lscala/collection/Iterator;Ljava/lang/Object;II)V;
NameAndType	copyToArray:(Lscala/collection/Iterator;Ljava/lang/Object;II)V
Method	scala/collection/Iterator$class.copyToArray:(Lscala/collection/Iterator;Ljava/lang/Object;II)V
Asciz	xs;
Asciz	start;
Asciz	(Ljava/lang/Object;I)V;
Asciz	(Lscala/collection/Iterator;Ljava/lang/Object;I)V;
NameAndType	copyToArray:(Lscala/collection/Iterator;Ljava/lang/Object;I)V
Method	scala/collection/Iterator$class.copyToArray:(Lscala/collection/Iterator;Ljava/lang/Object;I)V
Asciz	(Ljava/lang/Object;)V;
Asciz	(Lscala/collection/Iterator;Ljava/lang/Object;)V;
NameAndType	copyToArray:(Lscala/collection/Iterator;Ljava/lang/Object;)V
Method	scala/collection/Iterator$class.copyToArray:(Lscala/collection/Iterator;Ljava/lang/Object;)V
Asciz	copyToBuffer;
Asciz	(Lscala/collection/mutable/Buffer;)V;
Asciz	(Lscala/collection/Iterator;Lscala/collection/mutable/Buffer;)V;
NameAndType	copyToBuffer:(Lscala/collection/Iterator;Lscala/collection/mutable/Buffer;)V
Method	scala/collection/Iterator$class.copyToBuffer:(Lscala/collection/Iterator;Lscala/collection/mutable/Buffer;)V
Asciz	dest;
Asciz	Lscala/collection/mutable/Buffer;;
Asciz	toList;
Asciz	()Lscala/collection/immutable/List;;
Asciz	(Lscala/collection/Iterator;)Lscala/collection/immutable/List;;
NameAndType	toList:(Lscala/collection/Iterator;)Lscala/collection/immutable/List;
Method	scala/collection/Iterator$class.toList:(Lscala/collection/Iterator;)Lscala/collection/immutable/List;
Asciz	toSet;
Asciz	()Lscala/collection/immutable/Set;;
Asciz	(Lscala/collection/Iterator;)Lscala/collection/immutable/Set;;
NameAndType	toSet:(Lscala/collection/Iterator;)Lscala/collection/immutable/Set;
Method	scala/collection/Iterator$class.toSet:(Lscala/collection/Iterator;)Lscala/collection/immutable/Set;
Asciz	toStream;
Asciz	()Lscala/collection/immutable/Stream;;
Asciz	(Lscala/collection/Iterator;)Lscala/collection/immutable/Stream;;
NameAndType	toStream:(Lscala/collection/Iterator;)Lscala/collection/immutable/Stream;
Method	scala/collection/Iterator$class.toStream:(Lscala/collection/Iterator;)Lscala/collection/immutable/Stream;
Asciz	toSeq;
Asciz	()Lscala/collection/Seq;;
Asciz	(Lscala/collection/Iterator;)Lscala/collection/Seq;;
NameAndType	toSeq:(Lscala/collection/Iterator;)Lscala/collection/Seq;
Method	scala/collection/Iterator$class.toSeq:(Lscala/collection/Iterator;)Lscala/collection/Seq;
Asciz	toMap;
Asciz	(Lscala/Predef$$less$colon$less;)Lscala/collection/immutable/Map;;
Asciz	(Lscala/collection/Iterator;Lscala/Predef$$less$colon$less;)Lscala/collection/immutable/Map;;
NameAndType	toMap:(Lscala/collection/Iterator;Lscala/Predef$$less$colon$less;)Lscala/collection/immutable/Map;
Method	scala/collection/Iterator$class.toMap:(Lscala/collection/Iterator;Lscala/Predef$$less$colon$less;)Lscala/collection/immutable/Map;
Asciz	ev;
Asciz	Lscala/Predef$$less$colon$less;;
Asciz	sameElements;
Asciz	(Lscala/collection/Iterator;)Z;
Asciz	(Lscala/collection/Iterator;Lscala/collection/Iterator;)Z;
NameAndType	sameElements:(Lscala/collection/Iterator;Lscala/collection/Iterator;)Z
Method	scala/collection/Iterator$class.sameElements:(Lscala/collection/Iterator;Lscala/collection/Iterator;)Z
Asciz	mkString;
Asciz	(Ljava/lang/String;Ljava/lang/String;Ljava/lang/String;)Ljava/lang/String;;
Asciz	(Lscala/collection/Iterator;Ljava/lang/String;Ljava/lang/String;Ljava/lang/String;)Ljava/lang/String;;
NameAndType	mkString:(Lscala/collection/Iterator;Ljava/lang/String;Ljava/lang/String;Ljava/lang/String;)Ljava/lang/String;
Method	scala/collection/Iterator$class.mkString:(Lscala/collection/Iterator;Ljava/lang/String;Ljava/lang/String;Ljava/lang/String;)Ljava/lang/String;
Asciz	Ljava/lang/String;;
Asciz	sep;
Asciz	end;
Asciz	(Ljava/lang/String;)Ljava/lang/String;;
Asciz	(Lscala/collection/Iterator;Ljava/lang/String;)Ljava/lang/String;;
NameAndType	mkString:(Lscala/collection/Iterator;Ljava/lang/String;)Ljava/lang/String;
Method	scala/collection/Iterator$class.mkString:(Lscala/collection/Iterator;Ljava/lang/String;)Ljava/lang/String;
Asciz	()Ljava/lang/String;;
Asciz	(Lscala/collection/Iterator;)Ljava/lang/String;;
NameAndType	mkString:(Lscala/collection/Iterator;)Ljava/lang/String;
Method	scala/collection/Iterator$class.mkString:(Lscala/collection/Iterator;)Ljava/lang/String;
Asciz	addString;
Asciz	(Lscala/collection/mutable/StringBuilder;Ljava/lang/String;Ljava/lang/String;Ljava/lang/String;)Lscala/collection/mutable/StringBuilder;;
Asciz	(Lscala/collection/Iterator;Lscala/collection/mutable/StringBuilder;Ljava/lang/String;Ljava/lang/String;Ljava/lang/String;)Lscala/collection/mutable/StringBuilder;;
NameAndType	addString:(Lscala/collection/Iterator;Lscala/collection/mutable/StringBuilder;Ljava/lang/String;Ljava/lang/String;Ljava/lang/String;)Lscala/collection/mutable/StringBuilder;
Method	scala/collection/Iterator$class.addString:(Lscala/collection/Iterator;Lscala/collection/mutable/StringBuilder;Ljava/lang/String;Ljava/lang/String;Ljava/lang/String;)Lscala/collection/mutable/StringBuilder;
Asciz	buf;
Asciz	Lscala/collection/mutable/StringBuilder;;
Asciz	(Lscala/collection/mutable/StringBuilder;Ljava/lang/String;)Lscala/collection/mutable/StringBuilder;;
Asciz	(Lscala/collection/Iterator;Lscala/collection/mutable/StringBuilder;Ljava/lang/String;)Lscala/collection/mutable/StringBuilder;;
NameAndType	addString:(Lscala/collection/Iterator;Lscala/collection/mutable/StringBuilder;Ljava/lang/String;)Lscala/collection/mutable/StringBuilder;
Method	scala/collection/Iterator$class.addString:(Lscala/collection/Iterator;Lscala/collection/mutable/StringBuilder;Ljava/lang/String;)Lscala/collection/mutable/StringBuilder;
Asciz	(Lscala/collection/mutable/StringBuilder;)Lscala/collection/mutable/StringBuilder;;
Asciz	(Lscala/collection/Iterator;Lscala/collection/mutable/StringBuilder;)Lscala/collection/mutable/StringBuilder;;
NameAndType	addString:(Lscala/collection/Iterator;Lscala/collection/mutable/StringBuilder;)Lscala/collection/mutable/StringBuilder;
Method	scala/collection/Iterator$class.addString:(Lscala/collection/Iterator;Lscala/collection/mutable/StringBuilder;)Lscala/collection/mutable/StringBuilder;
Asciz	toString;
NameAndType	toString:(Lscala/collection/Iterator;)Ljava/lang/String;
Method	scala/collection/Iterator$class.toString:(Lscala/collection/Iterator;)Ljava/lang/String;
Asciz	append;
NameAndType	append:(Lscala/collection/Iterator;Lscala/collection/Iterator;)Lscala/collection/Iterator;
Method	scala/collection/Iterator$class.append:(Lscala/collection/Iterator;Lscala/collection/Iterator;)Lscala/collection/Iterator;
Asciz	findIndexOf;
NameAndType	findIndexOf:(Lscala/collection/Iterator;Lscala/Function1;)I
Method	scala/collection/Iterator$class.findIndexOf:(Lscala/collection/Iterator;Lscala/Function1;)I
Asciz	collect;
NameAndType	collect:(Lscala/collection/Iterator;)Lscala/collection/Seq;
Method	scala/collection/Iterator$class.collect:(Lscala/collection/Iterator;)Lscala/collection/Seq;
Asciz	counted;
Asciz	()Lscala/CountedIterator;;
Asciz	(Lscala/collection/Iterator;)Lscala/CountedIterator;;
NameAndType	counted:(Lscala/collection/Iterator;)Lscala/CountedIterator;
Method	scala/collection/Iterator$class.counted:(Lscala/collection/Iterator;)Lscala/CountedIterator;
Asciz	readInto;
NameAndType	readInto:(Lscala/collection/Iterator;Ljava/lang/Object;II)V
Method	scala/collection/Iterator$class.readInto:(Lscala/collection/Iterator;Ljava/lang/Object;II)V
Asciz	sz;
NameAndType	readInto:(Lscala/collection/Iterator;Ljava/lang/Object;I)V
Method	scala/collection/Iterator$class.readInto:(Lscala/collection/Iterator;Ljava/lang/Object;I)V
NameAndType	readInto:(Lscala/collection/Iterator;Ljava/lang/Object;)V
Method	scala/collection/Iterator$class.readInto:(Lscala/collection/Iterator;Ljava/lang/Object;)V
Asciz	sliding$default$2;
NameAndType	sliding$default$2:(Lscala/collection/Iterator;)I
Method	scala/collection/Iterator$class.sliding$default$2:(Lscala/collection/Iterator;)I
Asciz	copy$default$1;
Asciz	()Ljava/util/Iterator;;
Asciz	scala/collection/JavaConversions$JIteratorWrapper;
class	scala/collection/JavaConversions$JIteratorWrapper
NameAndType	underlying:()Ljava/util/Iterator;
Method	scala/collection/JavaConversions$JIteratorWrapper.underlying:()Ljava/util/Iterator;
NameAndType	underlying:Ljava/util/Iterator;
Field	scala/collection/JavaConversions$JIteratorWrapper.underlying:Ljava/util/Iterator;
Asciz	()Ljava/util/Iterator<TA;>;;
Asciz	hasNext;
Asciz	()Z;
Asciz	java/util/Iterator;
class	java/util/Iterator
NameAndType	hasNext:()Z
InterfaceMethod	java/util/Iterator.hasNext:()Z
Asciz	next;
Asciz	()Ljava/lang/Object;;
NameAndType	next:()Ljava/lang/Object;
InterfaceMethod	java/util/Iterator.next:()Ljava/lang/Object;
Asciz	()TA;;
Asciz	copy;
Asciz	(Ljava/util/Iterator;)Lscala/collection/JavaConversions$JIteratorWrapper;;
Asciz	<init>;
Asciz	(Ljava/util/Iterator;)V;
NameAndType	"<init>":(Ljava/util/Iterator;)V
Method	scala/collection/JavaConversions$JIteratorWrapper."<init>":(Ljava/util/Iterator;)V
Asciz	hashCode;
Asciz	scala/runtime/ScalaRunTime$;
class	scala/runtime/ScalaRunTime$
Asciz	MODULE$;
Asciz	Lscala/runtime/ScalaRunTime$;;
NameAndType	MODULE$:Lscala/runtime/ScalaRunTime$;
Field	scala/runtime/ScalaRunTime$.MODULE$:Lscala/runtime/ScalaRunTime$;
Asciz	_hashCode;
Asciz	(Lscala/Product;)I;
NameAndType	_hashCode:(Lscala/Product;)I
Method	scala/runtime/ScalaRunTime$._hashCode:(Lscala/Product;)I
Asciz	equals;
Asciz	gd2$1;
Asciz	(Ljava/util/Iterator;)Z;
NameAndType	gd2$1:(Ljava/util/Iterator;)Z
Method	scala/collection/JavaConversions$JIteratorWrapper.gd2$1:(Ljava/util/Iterator;)Z
Asciz	scala/Equals;
class	scala/Equals
Asciz	canEqual;
NameAndType	canEqual:(Ljava/lang/Object;)Z
InterfaceMethod	scala/Equals.canEqual:(Ljava/lang/Object;)Z
Asciz	temp55;
Asciz	temp56;
Asciz	temp57;
Asciz	underlying$2;
Asciz	productPrefix;
Asciz	JIteratorWrapper;
String	JIteratorWrapper
Asciz	productArity;
Asciz	productElement;
Asciz	(I)Ljava/lang/Object;;
Asciz	java/lang/IndexOutOfBoundsException;
class	java/lang/IndexOutOfBoundsException
Asciz	scala/runtime/BoxesRunTime;
class	scala/runtime/BoxesRunTime
Asciz	boxToInteger;
Asciz	(I)Ljava/lang/Integer;;
NameAndType	boxToInteger:(I)Ljava/lang/Integer;
Method	scala/runtime/BoxesRunTime.boxToInteger:(I)Ljava/lang/Integer;
Asciz	java/lang/Object;
class	java/lang/Object
NameAndType	toString:()Ljava/lang/String;
Method	java/lang/Object.toString:()Ljava/lang/String;
Asciz	(Ljava/lang/String;)V;
NameAndType	"<init>":(Ljava/lang/String;)V
Method	java/lang/IndexOutOfBoundsException."<init>":(Ljava/lang/String;)V
Asciz	temp58;
Asciz	productElementName;
Asciz	(I)Ljava/lang/String;;
String	underlying
Asciz	temp59;
NameAndType	equals:(Ljava/lang/Object;)Z
Method	java/lang/Object.equals:(Ljava/lang/Object;)Z
Asciz	()V;
NameAndType	"<init>":()V
Method	java/lang/Object."<init>":()V
Asciz	$init$;
Asciz	(Lscala/collection/Iterator;)V;
NameAndType	$init$:(Lscala/collection/Iterator;)V
Method	scala/collection/Iterator$class.$init$:(Lscala/collection/Iterator;)V
Asciz	(Lscala/Product;)V;
NameAndType	$init$:(Lscala/Product;)V
Method	scala/Product$class.$init$:(Lscala/Product;)V
Asciz	(Ljava/util/Iterator<TA;>;)V;
Asciz	<A:Ljava/lang/Object;>Ljava/lang/Object;Lscala/collection/Iterator<TA;>;Lscala/ScalaObject;Lscala/Product;;
Asciz	Scala;
Asciz	InnerClasses;
Asciz	scala/Predef$$less$colon$less;
class	scala/Predef$$less$colon$less
Asciz	scala/Predef;
class	scala/Predef
Asciz	$less$colon$less;
Asciz	scala/collection/Iterator$GroupedIterator;
class	scala/collection/Iterator$GroupedIterator
Asciz	scala/collection/Iterator;
class	scala/collection/Iterator
Asciz	GroupedIterator;
Asciz	scala/collection/JavaConversions;
class	scala/collection/JavaConversions
Asciz	scala/ScalaObject;
class	scala/ScalaObject
Asciz	scala/Product;
class	scala/Product
Asciz	java/io/Serializable;
class	java/io/Serializable

{
private final java.util.Iterator underlying;
  Signature: Ljava/util/Iterator;
  Signature: length = 0x2
   00 05 

public scala.collection.Iterator productIterator();
  Signature: ()Lscala/collection/Iterator;
  Code:
   Stack=1, Locals=1, Args_size=1
	aload_0
	invokestatic	Method scala/Product$class.productIterator:(Lscala/Product;)Lscala/collection/Iterator;
	areturn
  Labels:

public scala.collection.Iterator productElements();
  Signature: ()Lscala/collection/Iterator;
  Code:
   Stack=1, Locals=1, Args_size=1
	aload_0
	invokestatic	Method scala/Product$class.productElements:(Lscala/Product;)Lscala/collection/Iterator;
	areturn
  Labels:
  Deprecated: true

public scala.collection.Iterator take(int);
  Signature: (I)Lscala/collection/Iterator;
  Code:
   Stack=2, Locals=2, Args_size=2
	aload_0
	iload_1
	invokestatic	Method scala/collection/Iterator$class.take:(Lscala/collection/Iterator;I)Lscala/collection/Iterator;
	areturn
  Labels:
  LocalVariableTable: 
   Start  Length  Slot  Name   Signature
   0      6      0    this       Lscala/collection/JavaConversions$JIteratorWrapper;
   0      6      1    n       I


public scala.collection.Iterator drop(int);
  Signature: (I)Lscala/collection/Iterator;
  Code:
   Stack=2, Locals=2, Args_size=2
	aload_0
	iload_1
	invokestatic	Method scala/collection/Iterator$class.drop:(Lscala/collection/Iterator;I)Lscala/collection/Iterator;
	areturn
  Labels:
  LocalVariableTable: 
   Start  Length  Slot  Name   Signature
   0      6      0    this       Lscala/collection/JavaConversions$JIteratorWrapper;
   0      6      1    n       I


public scala.collection.Iterator slice(int, int);
  Signature: (II)Lscala/collection/Iterator;
  Code:
   Stack=3, Locals=3, Args_size=3
	aload_0
	iload_1
	iload_2
	invokestatic	Method scala/collection/Iterator$class.slice:(Lscala/collection/Iterator;II)Lscala/collection/Iterator;
	areturn
  Labels:
  LocalVariableTable: 
   Start  Length  Slot  Name   Signature
   0      7      0    this       Lscala/collection/JavaConversions$JIteratorWrapper;
   0      7      1    from       I
   0      7      2    until       I


public scala.collection.Iterator map(scala.Function1);
  Signature: (Lscala/Function1;)Lscala/collection/Iterator;
  Code:
   Stack=2, Locals=2, Args_size=2
	aload_0
	aload_1
	invokestatic	Method scala/collection/Iterator$class.map:(Lscala/collection/Iterator;Lscala/Function1;)Lscala/collection/Iterator;
	areturn
  Labels:
  LocalVariableTable: 
   Start  Length  Slot  Name   Signature
   0      6      0    this       Lscala/collection/JavaConversions$JIteratorWrapper;
   0      6      1    f       Lscala/Function1;


public scala.collection.Iterator $plus$plus(scala.Function0);
  Signature: (Lscala/Function0;)Lscala/collection/Iterator;
  Code:
   Stack=2, Locals=2, Args_size=2
	aload_0
	aload_1
	invokestatic	Method scala/collection/Iterator$class.$plus$plus:(Lscala/collection/Iterator;Lscala/Function0;)Lscala/collection/Iterator;
	areturn
  Labels:
  LocalVariableTable: 
   Start  Length  Slot  Name   Signature
   0      6      0    this       Lscala/collection/JavaConversions$JIteratorWrapper;
   0      6      1    that       Lscala/Function0;


public scala.collection.Iterator flatMap(scala.Function1);
  Signature: (Lscala/Function1;)Lscala/collection/Iterator;
  Code:
   Stack=2, Locals=2, Args_size=2
	aload_0
	aload_1
	invokestatic	Method scala/collection/Iterator$class.flatMap:(Lscala/collection/Iterator;Lscala/Function1;)Lscala/collection/Iterator;
	areturn
  Labels:
  LocalVariableTable: 
   Start  Length  Slot  Name   Signature
   0      6      0    this       Lscala/collection/JavaConversions$JIteratorWrapper;
   0      6      1    f       Lscala/Function1;


public scala.collection.Iterator filter(scala.Function1);
  Signature: (Lscala/Function1;)Lscala/collection/Iterator;
  Code:
   Stack=2, Locals=2, Args_size=2
	aload_0
	aload_1
	invokestatic	Method scala/collection/Iterator$class.filter:(Lscala/collection/Iterator;Lscala/Function1;)Lscala/collection/Iterator;
	areturn
  Labels:
  LocalVariableTable: 
   Start  Length  Slot  Name   Signature
   0      6      0    this       Lscala/collection/JavaConversions$JIteratorWrapper;
   0      6      1    p       Lscala/Function1;


public scala.collection.Iterator withFilter(scala.Function1);
  Signature: (Lscala/Function1;)Lscala/collection/Iterator;
  Code:
   Stack=2, Locals=2, Args_size=2
	aload_0
	aload_1
	invokestatic	Method scala/collection/Iterator$class.withFilter:(Lscala/collection/Iterator;Lscala/Function1;)Lscala/collection/Iterator;
	areturn
  Labels:
  LocalVariableTable: 
   Start  Length  Slot  Name   Signature
   0      6      0    this       Lscala/collection/JavaConversions$JIteratorWrapper;
   0      6      1    p       Lscala/Function1;


public scala.collection.Iterator filterNot(scala.Function1);
  Signature: (Lscala/Function1;)Lscala/collection/Iterator;
  Code:
   Stack=2, Locals=2, Args_size=2
	aload_0
	aload_1
	invokestatic	Method scala/collection/Iterator$class.filterNot:(Lscala/collection/Iterator;Lscala/Function1;)Lscala/collection/Iterator;
	areturn
  Labels:
  LocalVariableTable: 
   Start  Length  Slot  Name   Signature
   0      6      0    this       Lscala/collection/JavaConversions$JIteratorWrapper;
   0      6      1    p       Lscala/Function1;


public scala.collection.Iterator partialMap(scala.PartialFunction);
  Signature: (Lscala/PartialFunction;)Lscala/collection/Iterator;
  Code:
   Stack=2, Locals=2, Args_size=2
	aload_0
	aload_1
	invokestatic	Method scala/collection/Iterator$class.partialMap:(Lscala/collection/Iterator;Lscala/PartialFunction;)Lscala/collection/Iterator;
	areturn
  Labels:
  LocalVariableTable: 
   Start  Length  Slot  Name   Signature
   0      6      0    this       Lscala/collection/JavaConversions$JIteratorWrapper;
   0      6      1    pf       Lscala/PartialFunction;


public scala.collection.Iterator takeWhile(scala.Function1);
  Signature: (Lscala/Function1;)Lscala/collection/Iterator;
  Code:
   Stack=2, Locals=2, Args_size=2
	aload_0
	aload_1
	invokestatic	Method scala/collection/Iterator$class.takeWhile:(Lscala/collection/Iterator;Lscala/Function1;)Lscala/collection/Iterator;
	areturn
  Labels:
  LocalVariableTable: 
   Start  Length  Slot  Name   Signature
   0      6      0    this       Lscala/collection/JavaConversions$JIteratorWrapper;
   0      6      1    p       Lscala/Function1;


public scala.Tuple2 partition(scala.Function1);
  Signature: (Lscala/Function1;)Lscala/Tuple2;
  Code:
   Stack=2, Locals=2, Args_size=2
	aload_0
	aload_1
	invokestatic	Method scala/collection/Iterator$class.partition:(Lscala/collection/Iterator;Lscala/Function1;)Lscala/Tuple2;
	areturn
  Labels:
  LocalVariableTable: 
   Start  Length  Slot  Name   Signature
   0      6      0    this       Lscala/collection/JavaConversions$JIteratorWrapper;
   0      6      1    p       Lscala/Function1;


public scala.collection.Iterator dropWhile(scala.Function1);
  Signature: (Lscala/Function1;)Lscala/collection/Iterator;
  Code:
   Stack=2, Locals=2, Args_size=2
	aload_0
	aload_1
	invokestatic	Method scala/collection/Iterator$class.dropWhile:(Lscala/collection/Iterator;Lscala/Function1;)Lscala/collection/Iterator;
	areturn
  Labels:
  LocalVariableTable: 
   Start  Length  Slot  Name   Signature
   0      6      0    this       Lscala/collection/JavaConversions$JIteratorWrapper;
   0      6      1    p       Lscala/Function1;


public scala.collection.Iterator zip(scala.collection.Iterator);
  Signature: (Lscala/collection/Iterator;)Lscala/collection/Iterator;
  Code:
   Stack=2, Locals=2, Args_size=2
	aload_0
	aload_1
	invokestatic	Method scala/collection/Iterator$class.zip:(Lscala/collection/Iterator;Lscala/collection/Iterator;)Lscala/collection/Iterator;
	areturn
  Labels:
  LocalVariableTable: 
   Start  Length  Slot  Name   Signature
   0      6      0    this       Lscala/collection/JavaConversions$JIteratorWrapper;
   0      6      1    that       Lscala/collection/Iterator;


public scala.collection.Iterator padTo(int, java.lang.Object);
  Signature: (ILjava/lang/Object;)Lscala/collection/Iterator;
  Code:
   Stack=3, Locals=3, Args_size=3
	aload_0
	iload_1
	aload_2
	invokestatic	Method scala/collection/Iterator$class.padTo:(Lscala/collection/Iterator;ILjava/lang/Object;)Lscala/collection/Iterator;
	areturn
  Labels:
  LocalVariableTable: 
   Start  Length  Slot  Name   Signature
   0      7      0    this       Lscala/collection/JavaConversions$JIteratorWrapper;
   0      7      1    len       I
   0      7      2    elem       Ljava/lang/Object;


public scala.collection.Iterator zipWithIndex();
  Signature: ()Lscala/collection/Iterator;
  Code:
   Stack=1, Locals=1, Args_size=1
	aload_0
	invokestatic	Method scala/collection/Iterator$class.zipWithIndex:(Lscala/collection/Iterator;)Lscala/collection/Iterator;
	areturn
  Labels:

public scala.collection.Iterator zipAll(scala.collection.Iterator, java.lang.Object, java.lang.Object);
  Signature: (Lscala/collection/Iterator;Ljava/lang/Object;Ljava/lang/Object;)Lscala/collection/Iterator;
  Code:
   Stack=4, Locals=4, Args_size=4
	aload_0
	aload_1
	aload_2
	aload_3
	invokestatic	Method scala/collection/Iterator$class.zipAll:(Lscala/collection/Iterator;Lscala/collection/Iterator;Ljava/lang/Object;Ljava/lang/Object;)Lscala/collection/Iterator;
	areturn
  Labels:
  LocalVariableTable: 
   Start  Length  Slot  Name   Signature
   0      8      0    this       Lscala/collection/JavaConversions$JIteratorWrapper;
   0      8      1    that       Lscala/collection/Iterator;
   0      8      2    thisElem       Ljava/lang/Object;
   0      8      3    thatElem       Ljava/lang/Object;


public void foreach(scala.Function1);
  Signature: (Lscala/Function1;)V
  Code:
   Stack=2, Locals=2, Args_size=2
	aload_0
	aload_1
	invokestatic	Method scala/collection/Iterator$class.foreach:(Lscala/collection/Iterator;Lscala/Function1;)V
	return
  Labels:
  LocalVariableTable: 
   Start  Length  Slot  Name   Signature
   0      6      0    this       Lscala/collection/JavaConversions$JIteratorWrapper;
   0      6      1    f       Lscala/Function1;


public boolean forall(scala.Function1);
  Signature: (Lscala/Function1;)Z
  Code:
   Stack=2, Locals=2, Args_size=2
	aload_0
	aload_1
	invokestatic	Method scala/collection/Iterator$class.forall:(Lscala/collection/Iterator;Lscala/Function1;)Z
	ireturn
  Labels:
  LocalVariableTable: 
   Start  Length  Slot  Name   Signature
   0      6      0    this       Lscala/collection/JavaConversions$JIteratorWrapper;
   0      6      1    p       Lscala/Function1;


public boolean exists(scala.Function1);
  Signature: (Lscala/Function1;)Z
  Code:
   Stack=2, Locals=2, Args_size=2
	aload_0
	aload_1
	invokestatic	Method scala/collection/Iterator$class.exists:(Lscala/collection/Iterator;Lscala/Function1;)Z
	ireturn
  Labels:
  LocalVariableTable: 
   Start  Length  Slot  Name   Signature
   0      6      0    this       Lscala/collection/JavaConversions$JIteratorWrapper;
   0      6      1    p       Lscala/Function1;


public boolean contains(java.lang.Object);
  Signature: (Ljava/lang/Object;)Z
  Code:
   Stack=2, Locals=2, Args_size=2
	aload_0
	aload_1
	invokestatic	Method scala/collection/Iterator$class.contains:(Lscala/collection/Iterator;Ljava/lang/Object;)Z
	ireturn
  Labels:
  LocalVariableTable: 
   Start  Length  Slot  Name   Signature
   0      6      0    this       Lscala/collection/JavaConversions$JIteratorWrapper;
   0      6      1    elem       Ljava/lang/Object;


public scala.Option find(scala.Function1);
  Signature: (Lscala/Function1;)Lscala/Option;
  Code:
   Stack=2, Locals=2, Args_size=2
	aload_0
	aload_1
	invokestatic	Method scala/collection/Iterator$class.find:(Lscala/collection/Iterator;Lscala/Function1;)Lscala/Option;
	areturn
  Labels:
  LocalVariableTable: 
   Start  Length  Slot  Name   Signature
   0      6      0    this       Lscala/collection/JavaConversions$JIteratorWrapper;
   0      6      1    p       Lscala/Function1;


public int indexWhere(scala.Function1);
  Signature: (Lscala/Function1;)I
  Code:
   Stack=2, Locals=2, Args_size=2
	aload_0
	aload_1
	invokestatic	Method scala/collection/Iterator$class.indexWhere:(Lscala/collection/Iterator;Lscala/Function1;)I
	ireturn
  Labels:
  LocalVariableTable: 
   Start  Length  Slot  Name   Signature
   0      6      0    this       Lscala/collection/JavaConversions$JIteratorWrapper;
   0      6      1    p       Lscala/Function1;


public int indexOf(java.lang.Object);
  Signature: (Ljava/lang/Object;)I
  Code:
   Stack=2, Locals=2, Args_size=2
	aload_0
	aload_1
	invokestatic	Method scala/collection/Iterator$class.indexOf:(Lscala/collection/Iterator;Ljava/lang/Object;)I
	ireturn
  Labels:
  LocalVariableTable: 
   Start  Length  Slot  Name   Signature
   0      6      0    this       Lscala/collection/JavaConversions$JIteratorWrapper;
   0      6      1    elem       Ljava/lang/Object;


public java.lang.Object foldLeft(java.lang.Object, scala.Function2);
  Signature: (Ljava/lang/Object;Lscala/Function2;)Ljava/lang/Object;
  Code:
   Stack=3, Locals=3, Args_size=3
	aload_0
	aload_1
	aload_2
	invokestatic	Method scala/collection/Iterator$class.foldLeft:(Lscala/collection/Iterator;Ljava/lang/Object;Lscala/Function2;)Ljava/lang/Object;
	areturn
  Labels:
  LocalVariableTable: 
   Start  Length  Slot  Name   Signature
   0      7      0    this       Lscala/collection/JavaConversions$JIteratorWrapper;
   0      7      1    z       Ljava/lang/Object;
   0      7      2    op       Lscala/Function2;


public java.lang.Object foldRight(java.lang.Object, scala.Function2);
  Signature: (Ljava/lang/Object;Lscala/Function2;)Ljava/lang/Object;
  Code:
   Stack=3, Locals=3, Args_size=3
	aload_0
	aload_1
	aload_2
	invokestatic	Method scala/collection/Iterator$class.foldRight:(Lscala/collection/Iterator;Ljava/lang/Object;Lscala/Function2;)Ljava/lang/Object;
	areturn
  Labels:
  LocalVariableTable: 
   Start  Length  Slot  Name   Signature
   0      7      0    this       Lscala/collection/JavaConversions$JIteratorWrapper;
   0      7      1    z       Ljava/lang/Object;
   0      7      2    op       Lscala/Function2;


public java.lang.Object $div$colon(java.lang.Object, scala.Function2);
  Signature: (Ljava/lang/Object;Lscala/Function2;)Ljava/lang/Object;
  Code:
   Stack=3, Locals=3, Args_size=3
	aload_0
	aload_1
	aload_2
	invokestatic	Method scala/collection/Iterator$class.$div$colon:(Lscala/collection/Iterator;Ljava/lang/Object;Lscala/Function2;)Ljava/lang/Object;
	areturn
  Labels:
  LocalVariableTable: 
   Start  Length  Slot  Name   Signature
   0      7      0    this       Lscala/collection/JavaConversions$JIteratorWrapper;
   0      7      1    z       Ljava/lang/Object;
   0      7      2    op       Lscala/Function2;


public java.lang.Object $colon$bslash(java.lang.Object, scala.Function2);
  Signature: (Ljava/lang/Object;Lscala/Function2;)Ljava/lang/Object;
  Code:
   Stack=3, Locals=3, Args_size=3
	aload_0
	aload_1
	aload_2
	invokestatic	Method scala/collection/Iterator$class.$colon$bslash:(Lscala/collection/Iterator;Ljava/lang/Object;Lscala/Function2;)Ljava/lang/Object;
	areturn
  Labels:
  LocalVariableTable: 
   Start  Length  Slot  Name   Signature
   0      7      0    this       Lscala/collection/JavaConversions$JIteratorWrapper;
   0      7      1    z       Ljava/lang/Object;
   0      7      2    op       Lscala/Function2;


public java.lang.Object reduceLeft(scala.Function2);
  Signature: (Lscala/Function2;)Ljava/lang/Object;
  Code:
   Stack=2, Locals=2, Args_size=2
	aload_0
	aload_1
	invokestatic	Method scala/collection/Iterator$class.reduceLeft:(Lscala/collection/Iterator;Lscala/Function2;)Ljava/lang/Object;
	areturn
  Labels:
  LocalVariableTable: 
   Start  Length  Slot  Name   Signature
   0      6      0    this       Lscala/collection/JavaConversions$JIteratorWrapper;
   0      6      1    op       Lscala/Function2;


public java.lang.Object reduceRight(scala.Function2);
  Signature: (Lscala/Function2;)Ljava/lang/Object;
  Code:
   Stack=2, Locals=2, Args_size=2
	aload_0
	aload_1
	invokestatic	Method scala/collection/Iterator$class.reduceRight:(Lscala/collection/Iterator;Lscala/Function2;)Ljava/lang/Object;
	areturn
  Labels:
  LocalVariableTable: 
   Start  Length  Slot  Name   Signature
   0      6      0    this       Lscala/collection/JavaConversions$JIteratorWrapper;
   0      6      1    op       Lscala/Function2;


public scala.Option reduceLeftOption(scala.Function2);
  Signature: (Lscala/Function2;)Lscala/Option;
  Code:
   Stack=2, Locals=2, Args_size=2
	aload_0
	aload_1
	invokestatic	Method scala/collection/Iterator$class.reduceLeftOption:(Lscala/collection/Iterator;Lscala/Function2;)Lscala/Option;
	areturn
  Labels:
  LocalVariableTable: 
   Start  Length  Slot  Name   Signature
   0      6      0    this       Lscala/collection/JavaConversions$JIteratorWrapper;
   0      6      1    op       Lscala/Function2;


public scala.Option reduceRightOption(scala.Function2);
  Signature: (Lscala/Function2;)Lscala/Option;
  Code:
   Stack=2, Locals=2, Args_size=2
	aload_0
	aload_1
	invokestatic	Method scala/collection/Iterator$class.reduceRightOption:(Lscala/collection/Iterator;Lscala/Function2;)Lscala/Option;
	areturn
  Labels:
  LocalVariableTable: 
   Start  Length  Slot  Name   Signature
   0      6      0    this       Lscala/collection/JavaConversions$JIteratorWrapper;
   0      6      1    op       Lscala/Function2;


public scala.collection.BufferedIterator buffered();
  Signature: ()Lscala/collection/BufferedIterator;
  Code:
   Stack=1, Locals=1, Args_size=1
	aload_0
	invokestatic	Method scala/collection/Iterator$class.buffered:(Lscala/collection/Iterator;)Lscala/collection/BufferedIterator;
	areturn
  Labels:

public scala.collection.Iterator$GroupedIterator grouped(int);
  Signature: (I)Lscala/collection/Iterator$GroupedIterator;
  Code:
   Stack=2, Locals=2, Args_size=2
	aload_0
	iload_1
	invokestatic	Method scala/collection/Iterator$class.grouped:(Lscala/collection/Iterator;I)Lscala/collection/Iterator$GroupedIterator;
	areturn
  Labels:
  LocalVariableTable: 
   Start  Length  Slot  Name   Signature
   0      6      0    this       Lscala/collection/JavaConversions$JIteratorWrapper;
   0      6      1    size       I

  Signature: length = 0x2
   00 FFFFFFB7 

public scala.collection.Iterator$GroupedIterator sliding(int, int);
  Signature: (II)Lscala/collection/Iterator$GroupedIterator;
  Code:
   Stack=3, Locals=3, Args_size=3
	aload_0
	iload_1
	iload_2
	invokestatic	Method scala/collection/Iterator$class.sliding:(Lscala/collection/Iterator;II)Lscala/collection/Iterator$GroupedIterator;
	areturn
  Labels:
  LocalVariableTable: 
   Start  Length  Slot  Name   Signature
   0      7      0    this       Lscala/collection/JavaConversions$JIteratorWrapper;
   0      7      1    size       I
   0      7      2    step       I

  Signature: length = 0x2
   00 FFFFFFBD 

public int length();
  Signature: ()I
  Code:
   Stack=1, Locals=1, Args_size=1
	aload_0
	invokestatic	Method scala/collection/Iterator$class.length:(Lscala/collection/Iterator;)I
	ireturn
  Labels:

public scala.Tuple2 duplicate();
  Signature: ()Lscala/Tuple2;
  Code:
   Stack=1, Locals=1, Args_size=1
	aload_0
	invokestatic	Method scala/collection/Iterator$class.duplicate:(Lscala/collection/Iterator;)Lscala/Tuple2;
	areturn
  Labels:

public scala.collection.Iterator patch(int, scala.collection.Iterator, int);
  Signature: (ILscala/collection/Iterator;I)Lscala/collection/Iterator;
  Code:
   Stack=4, Locals=4, Args_size=4
	aload_0
	iload_1
	aload_2
	iload_3
	invokestatic	Method scala/collection/Iterator$class.patch:(Lscala/collection/Iterator;ILscala/collection/Iterator;I)Lscala/collection/Iterator;
	areturn
  Labels:
  LocalVariableTable: 
   Start  Length  Slot  Name   Signature
   0      8      0    this       Lscala/collection/JavaConversions$JIteratorWrapper;
   0      8      1    from       I
   0      8      2    patchElems       Lscala/collection/Iterator;
   0      8      3    replaced       I


public void copyToArray(java.lang.Object, int, int);
  Signature: (Ljava/lang/Object;II)V
  Code:
   Stack=4, Locals=4, Args_size=4
	aload_0
	aload_1
	iload_2
	iload_3
	invokestatic	Method scala/collection/Iterator$class.copyToArray:(Lscala/collection/Iterator;Ljava/lang/Object;II)V
	return
  Labels:
  LocalVariableTable: 
   Start  Length  Slot  Name   Signature
   0      8      0    this       Lscala/collection/JavaConversions$JIteratorWrapper;
   0      8      1    xs       Ljava/lang/Object;
   0      8      2    start       I
   0      8      3    len       I


public void copyToArray(java.lang.Object, int);
  Signature: (Ljava/lang/Object;I)V
  Code:
   Stack=3, Locals=3, Args_size=3
	aload_0
	aload_1
	iload_2
	invokestatic	Method scala/collection/Iterator$class.copyToArray:(Lscala/collection/Iterator;Ljava/lang/Object;I)V
	return
  Labels:
  LocalVariableTable: 
   Start  Length  Slot  Name   Signature
   0      7      0    this       Lscala/collection/JavaConversions$JIteratorWrapper;
   0      7      1    xs       Ljava/lang/Object;
   0      7      2    start       I


public void copyToArray(java.lang.Object);
  Signature: (Ljava/lang/Object;)V
  Code:
   Stack=2, Locals=2, Args_size=2
	aload_0
	aload_1
	invokestatic	Method scala/collection/Iterator$class.copyToArray:(Lscala/collection/Iterator;Ljava/lang/Object;)V
	return
  Labels:
  LocalVariableTable: 
   Start  Length  Slot  Name   Signature
   0      6      0    this       Lscala/collection/JavaConversions$JIteratorWrapper;
   0      6      1    xs       Ljava/lang/Object;


public void copyToBuffer(scala.collection.mutable.Buffer);
  Signature: (Lscala/collection/mutable/Buffer;)V
  Code:
   Stack=2, Locals=2, Args_size=2
	aload_0
	aload_1
	invokestatic	Method scala/collection/Iterator$class.copyToBuffer:(Lscala/collection/Iterator;Lscala/collection/mutable/Buffer;)V
	return
  Labels:
  LocalVariableTable: 
   Start  Length  Slot  Name   Signature
   0      6      0    this       Lscala/collection/JavaConversions$JIteratorWrapper;
   0      6      1    dest       Lscala/collection/mutable/Buffer;


public scala.collection.immutable.List toList();
  Signature: ()Lscala/collection/immutable/List;
  Code:
   Stack=1, Locals=1, Args_size=1
	aload_0
	invokestatic	Method scala/collection/Iterator$class.toList:(Lscala/collection/Iterator;)Lscala/collection/immutable/List;
	areturn
  Labels:

public scala.collection.immutable.Set toSet();
  Signature: ()Lscala/collection/immutable/Set;
  Code:
   Stack=1, Locals=1, Args_size=1
	aload_0
	invokestatic	Method scala/collection/Iterator$class.toSet:(Lscala/collection/Iterator;)Lscala/collection/immutable/Set;
	areturn
  Labels:

public scala.collection.immutable.Stream toStream();
  Signature: ()Lscala/collection/immutable/Stream;
  Code:
   Stack=1, Locals=1, Args_size=1
	aload_0
	invokestatic	Method scala/collection/Iterator$class.toStream:(Lscala/collection/Iterator;)Lscala/collection/immutable/Stream;
	areturn
  Labels:

public scala.collection.Seq toSeq();
  Signature: ()Lscala/collection/Seq;
  Code:
   Stack=1, Locals=1, Args_size=1
	aload_0
	invokestatic	Method scala/collection/Iterator$class.toSeq:(Lscala/collection/Iterator;)Lscala/collection/Seq;
	areturn
  Labels:

public scala.collection.immutable.Map toMap(scala.Predef$$less$colon$less);
  Signature: (Lscala/Predef$$less$colon$less;)Lscala/collection/immutable/Map;
  Code:
   Stack=2, Locals=2, Args_size=2
	aload_0
	aload_1
	invokestatic	Method scala/collection/Iterator$class.toMap:(Lscala/collection/Iterator;Lscala/Predef$$less$colon$less;)Lscala/collection/immutable/Map;
	areturn
  Labels:
  LocalVariableTable: 
   Start  Length  Slot  Name   Signature
   0      6      0    this       Lscala/collection/JavaConversions$JIteratorWrapper;
   0      6      1    ev       Lscala/Predef$$less$colon$less;


public boolean sameElements(scala.collection.Iterator);
  Signature: (Lscala/collection/Iterator;)Z
  Code:
   Stack=2, Locals=2, Args_size=2
	aload_0
	aload_1
	invokestatic	Method scala/collection/Iterator$class.sameElements:(Lscala/collection/Iterator;Lscala/collection/Iterator;)Z
	ireturn
  Labels:
  LocalVariableTable: 
   Start  Length  Slot  Name   Signature
   0      6      0    this       Lscala/collection/JavaConversions$JIteratorWrapper;
   0      6      1    that       Lscala/collection/Iterator;


public java.lang.String mkString(java.lang.String, java.lang.String, java.lang.String);
  Signature: (Ljava/lang/String;Ljava/lang/String;Ljava/lang/String;)Ljava/lang/String;
  Code:
   Stack=4, Locals=4, Args_size=4
	aload_0
	aload_1
	aload_2
	aload_3
	invokestatic	Method scala/collection/Iterator$class.mkString:(Lscala/collection/Iterator;Ljava/lang/String;Ljava/lang/String;Ljava/lang/String;)Ljava/lang/String;
	areturn
  Labels:
  LocalVariableTable: 
   Start  Length  Slot  Name   Signature
   0      8      0    this       Lscala/collection/JavaConversions$JIteratorWrapper;
   0      8      1    start       Ljava/lang/String;
   0      8      2    sep       Ljava/lang/String;
   0      8      3    end       Ljava/lang/String;


public java.lang.String mkString(java.lang.String);
  Signature: (Ljava/lang/String;)Ljava/lang/String;
  Code:
   Stack=2, Locals=2, Args_size=2
	aload_0
	aload_1
	invokestatic	Method scala/collection/Iterator$class.mkString:(Lscala/collection/Iterator;Ljava/lang/String;)Ljava/lang/String;
	areturn
  Labels:
  LocalVariableTable: 
   Start  Length  Slot  Name   Signature
   0      6      0    this       Lscala/collection/JavaConversions$JIteratorWrapper;
   0      6      1    sep       Ljava/lang/String;


public java.lang.String mkString();
  Signature: ()Ljava/lang/String;
  Code:
   Stack=1, Locals=1, Args_size=1
	aload_0
	invokestatic	Method scala/collection/Iterator$class.mkString:(Lscala/collection/Iterator;)Ljava/lang/String;
	areturn
  Labels:

public scala.collection.mutable.StringBuilder addString(scala.collection.mutable.StringBuilder, java.lang.String, java.lang.String, java.lang.String);
  Signature: (Lscala/collection/mutable/StringBuilder;Ljava/lang/String;Ljava/lang/String;Ljava/lang/String;)Lscala/collection/mutable/StringBuilder;
  Code:
   Stack=5, Locals=5, Args_size=5
	aload_0
	aload_1
	aload_2
	aload_3
	aload	4
	invokestatic	Method scala/collection/Iterator$class.addString:(Lscala/collection/Iterator;Lscala/collection/mutable/StringBuilder;Ljava/lang/String;Ljava/lang/String;Ljava/lang/String;)Lscala/collection/mutable/StringBuilder;
	areturn
  Labels:
  LocalVariableTable: 
   Start  Length  Slot  Name   Signature
   0      10      0    this       Lscala/collection/JavaConversions$JIteratorWrapper;
   0      10      1    buf       Lscala/collection/mutable/StringBuilder;
   0      10      2    start       Ljava/lang/String;
   0      10      3    sep       Ljava/lang/String;
   0      10      4    end       Ljava/lang/String;


public scala.collection.mutable.StringBuilder addString(scala.collection.mutable.StringBuilder, java.lang.String);
  Signature: (Lscala/collection/mutable/StringBuilder;Ljava/lang/String;)Lscala/collection/mutable/StringBuilder;
  Code:
   Stack=3, Locals=3, Args_size=3
	aload_0
	aload_1
	aload_2
	invokestatic	Method scala/collection/Iterator$class.addString:(Lscala/collection/Iterator;Lscala/collection/mutable/StringBuilder;Ljava/lang/String;)Lscala/collection/mutable/StringBuilder;
	areturn
  Labels:
  LocalVariableTable: 
   Start  Length  Slot  Name   Signature
   0      7      0    this       Lscala/collection/JavaConversions$JIteratorWrapper;
   0      7      1    buf       Lscala/collection/mutable/StringBuilder;
   0      7      2    sep       Ljava/lang/String;


public scala.collection.mutable.StringBuilder addString(scala.collection.mutable.StringBuilder);
  Signature: (Lscala/collection/mutable/StringBuilder;)Lscala/collection/mutable/StringBuilder;
  Code:
   Stack=2, Locals=2, Args_size=2
	aload_0
	aload_1
	invokestatic	Method scala/collection/Iterator$class.addString:(Lscala/collection/Iterator;Lscala/collection/mutable/StringBuilder;)Lscala/collection/mutable/StringBuilder;
	areturn
  Labels:
  LocalVariableTable: 
   Start  Length  Slot  Name   Signature
   0      6      0    this       Lscala/collection/JavaConversions$JIteratorWrapper;
   0      6      1    buf       Lscala/collection/mutable/StringBuilder;


public java.lang.String toString();
  Signature: ()Ljava/lang/String;
  Code:
   Stack=1, Locals=1, Args_size=1
	aload_0
	invokestatic	Method scala/collection/Iterator$class.toString:(Lscala/collection/Iterator;)Ljava/lang/String;
	areturn
  Labels:

public scala.collection.Iterator append(scala.collection.Iterator);
  Signature: (Lscala/collection/Iterator;)Lscala/collection/Iterator;
  Code:
   Stack=2, Locals=2, Args_size=2
	aload_0
	aload_1
	invokestatic	Method scala/collection/Iterator$class.append:(Lscala/collection/Iterator;Lscala/collection/Iterator;)Lscala/collection/Iterator;
	areturn
  Labels:
  LocalVariableTable: 
   Start  Length  Slot  Name   Signature
   0      6      0    this       Lscala/collection/JavaConversions$JIteratorWrapper;
   0      6      1    that       Lscala/collection/Iterator;

  Deprecated: true

public int findIndexOf(scala.Function1);
  Signature: (Lscala/Function1;)I
  Code:
   Stack=2, Locals=2, Args_size=2
	aload_0
	aload_1
	invokestatic	Method scala/collection/Iterator$class.findIndexOf:(Lscala/collection/Iterator;Lscala/Function1;)I
	ireturn
  Labels:
  LocalVariableTable: 
   Start  Length  Slot  Name   Signature
   0      6      0    this       Lscala/collection/JavaConversions$JIteratorWrapper;
   0      6      1    p       Lscala/Function1;

  Deprecated: true

public scala.collection.Seq collect();
  Signature: ()Lscala/collection/Seq;
  Code:
   Stack=1, Locals=1, Args_size=1
	aload_0
	invokestatic	Method scala/collection/Iterator$class.collect:(Lscala/collection/Iterator;)Lscala/collection/Seq;
	areturn
  Labels:
  Deprecated: true

public scala.CountedIterator counted();
  Signature: ()Lscala/CountedIterator;
  Code:
   Stack=1, Locals=1, Args_size=1
	aload_0
	invokestatic	Method scala/collection/Iterator$class.counted:(Lscala/collection/Iterator;)Lscala/CountedIterator;
	areturn
  Labels:
  Deprecated: true

public void readInto(java.lang.Object, int, int);
  Signature: (Ljava/lang/Object;II)V
  Code:
   Stack=4, Locals=4, Args_size=4
	aload_0
	aload_1
	iload_2
	iload_3
	invokestatic	Method scala/collection/Iterator$class.readInto:(Lscala/collection/Iterator;Ljava/lang/Object;II)V
	return
  Labels:
  LocalVariableTable: 
   Start  Length  Slot  Name   Signature
   0      8      0    this       Lscala/collection/JavaConversions$JIteratorWrapper;
   0      8      1    xs       Ljava/lang/Object;
   0      8      2    start       I
   0      8      3    sz       I

  Deprecated: true

public void readInto(java.lang.Object, int);
  Signature: (Ljava/lang/Object;I)V
  Code:
   Stack=3, Locals=3, Args_size=3
	aload_0
	aload_1
	iload_2
	invokestatic	Method scala/collection/Iterator$class.readInto:(Lscala/collection/Iterator;Ljava/lang/Object;I)V
	return
  Labels:
  LocalVariableTable: 
   Start  Length  Slot  Name   Signature
   0      7      0    this       Lscala/collection/JavaConversions$JIteratorWrapper;
   0      7      1    xs       Ljava/lang/Object;
   0      7      2    start       I

  Deprecated: true

public void readInto(java.lang.Object);
  Signature: (Ljava/lang/Object;)V
  Code:
   Stack=2, Locals=2, Args_size=2
	aload_0
	aload_1
	invokestatic	Method scala/collection/Iterator$class.readInto:(Lscala/collection/Iterator;Ljava/lang/Object;)V
	return
  Labels:
  LocalVariableTable: 
   Start  Length  Slot  Name   Signature
   0      6      0    this       Lscala/collection/JavaConversions$JIteratorWrapper;
   0      6      1    xs       Ljava/lang/Object;

  Deprecated: true

public int sliding$default$2();
  Signature: ()I
  Code:
   Stack=1, Locals=1, Args_size=1
	aload_0
	invokestatic	Method scala/collection/Iterator$class.sliding$default$2:(Lscala/collection/Iterator;)I
	ireturn
  Labels:

public java.util.Iterator copy$default$1();
  Signature: ()Ljava/util/Iterator;
  Code:
   Stack=1, Locals=1, Args_size=1
	aload_0
	invokevirtual	Method underlying:()Ljava/util/Iterator;
	areturn
  Labels:

public java.util.Iterator underlying();
  Signature: ()Ljava/util/Iterator;
  Code:
   Stack=1, Locals=1, Args_size=1
	aload_0
	getfield	Field underlying:Ljava/util/Iterator;
	areturn
  Labels:
  Signature: length = 0x2
   01 4C 

public boolean hasNext();
  Signature: ()Z
  Code:
   Stack=1, Locals=1, Args_size=1
	aload_0
	invokevirtual	Method underlying:()Ljava/util/Iterator;
	invokeinterface	InterfaceMethod java/util/Iterator.hasNext:()Z
	ireturn
  Labels:

public java.lang.Object next();
  Signature: ()Ljava/lang/Object;
  Code:
   Stack=1, Locals=1, Args_size=1
	aload_0
	invokevirtual	Method underlying:()Ljava/util/Iterator;
	invokeinterface	InterfaceMethod java/util/Iterator.next:()Ljava/lang/Object;
	areturn
  Labels:
  Signature: length = 0x2
   01 57 

public scala.collection.JavaConversions$JIteratorWrapper copy(java.util.Iterator);
  Signature: (Ljava/util/Iterator;)Lscala/collection/JavaConversions$JIteratorWrapper;
  Code:
   Stack=3, Locals=2, Args_size=2
	new	class scala/collection/JavaConversions$JIteratorWrapper
	dup
	aload_1
	invokespecial	Method "<init>":(Ljava/util/Iterator;)V
	areturn
  Labels:
  LocalVariableTable: 
   Start  Length  Slot  Name   Signature
   0      9      0    this       Lscala/collection/JavaConversions$JIteratorWrapper;
   0      9      1    underlying       Ljava/util/Iterator;


public int hashCode();
  Signature: ()I
  Code:
   Stack=2, Locals=1, Args_size=1
	getstatic	Field scala/runtime/ScalaRunTime$.MODULE$:Lscala/runtime/ScalaRunTime$;
	aload_0
	invokevirtual	Method scala/runtime/ScalaRunTime$._hashCode:(Lscala/Product;)I
	ireturn
  Labels:

public boolean equals(java.lang.Object);
  Signature: (Ljava/lang/Object;)Z
  Code:
   Stack=2, Locals=6, Args_size=2
	aload_0
	aload_1
	if_acmpeq	l1 // iconst_1
	aload_1
	astore_2
	aload_2
	instanceof	class scala/collection/JavaConversions$JIteratorWrapper
	ifeq	l2 // iconst_0
	aload_2
	checkcast	class scala/collection/JavaConversions$JIteratorWrapper
	astore_3
	aload_3
	invokevirtual	Method underlying:()Ljava/util/Iterator;
	astore	4
	aload	4
	astore	5
	aload_0
	aload	5
	invokespecial	Method gd2$1:(Ljava/util/Iterator;)Z
	ifeq	l3 // iconst_0
	aload_1
	checkcast	class scala/collection/JavaConversions$JIteratorWrapper
	aload_0
	invokeinterface	InterfaceMethod scala/Equals.canEqual:(Ljava/lang/Object;)Z
	goto	l4 // ifeq
l3	iconst_0
	goto	l4 // ifeq
l2	iconst_0
l4	ifeq	l5 // iconst_0
l1	iconst_1
	goto	l6 // ireturn
l5	iconst_0
l6	ireturn
  Labels:
   	l3 = 51 // iconst_0
   	l2 = 55 // iconst_0
   	l4 = 56 // ifeq
   	l1 = 59 // iconst_1
   	l5 = 63 // iconst_0
   	l6 = 64 // ireturn
  LocalVariableTable: 
   Start  Length  Slot  Name   Signature
   0      65      0    this       Lscala/collection/JavaConversions$JIteratorWrapper;
   7      52      2    temp55       Ljava/lang/Object;
   19      36      3    temp56       Lscala/collection/JavaConversions$JIteratorWrapper;
   25      30      4    temp57       Ljava/util/Iterator;
   29      26      5    underlying$2       Ljava/util/Iterator;


public java.lang.String productPrefix();
  Signature: ()Ljava/lang/String;
  Code:
   Stack=1, Locals=1, Args_size=1
	ldc_w	String JIteratorWrapper
	areturn
  Labels:

public int productArity();
  Signature: ()I
  Code:
   Stack=1, Locals=1, Args_size=1
	iconst_1
	ireturn
  Labels:

public java.lang.Object productElement(int);
  Signature: (I)Ljava/lang/Object;
  Code:
   Stack=3, Locals=3, Args_size=2
	iload_1
	istore_2
	iload_2
	iconst_0
	if_icmpne	l1 // new
	aload_0
	invokevirtual	Method underlying:()Ljava/util/Iterator;
	areturn
l1	new	class java/lang/IndexOutOfBoundsException
	dup
	iload_1
	invokestatic	Method scala/runtime/BoxesRunTime.boxToInteger:(I)Ljava/lang/Integer;
	invokevirtual	Method java/lang/Object.toString:()Ljava/lang/String;
	invokespecial	Method java/lang/IndexOutOfBoundsException."<init>":(Ljava/lang/String;)V
	athrow
  Labels:
   	l1 = 12 // new
  LocalVariableTable: 
   Start  Length  Slot  Name   Signature
   0      27      0    this       Lscala/collection/JavaConversions$JIteratorWrapper;
   2      25      2    temp58       I


public java.lang.String productElementName(int);
  Signature: (I)Ljava/lang/String;
  Code:
   Stack=3, Locals=3, Args_size=2
	iload_1
	istore_2
	iload_2
	iconst_0
	if_icmpne	l1 // new
	ldc_w	String underlying
	areturn
l1	new	class java/lang/IndexOutOfBoundsException
	dup
	iload_1
	invokestatic	Method scala/runtime/BoxesRunTime.boxToInteger:(I)Ljava/lang/Integer;
	invokevirtual	Method java/lang/Object.toString:()Ljava/lang/String;
	invokespecial	Method java/lang/IndexOutOfBoundsException."<init>":(Ljava/lang/String;)V
	athrow
  Labels:
   	l1 = 11 // new
  LocalVariableTable: 
   Start  Length  Slot  Name   Signature
   0      26      0    this       Lscala/collection/JavaConversions$JIteratorWrapper;
   2      24      2    temp59       I


public boolean canEqual(java.lang.Object);
  Signature: (Ljava/lang/Object;)Z
  Code:
   Stack=1, Locals=2, Args_size=2
	aload_1
	instanceof	class scala/collection/JavaConversions$JIteratorWrapper
	ireturn
  Labels:

private final boolean gd2$1(java.util.Iterator);
  Signature: (Ljava/util/Iterator;)Z
  Code:
   Stack=2, Locals=3, Args_size=2
	aload_1
	aload_0
	invokevirtual	Method underlying:()Ljava/util/Iterator;
	astore_2
	dup
	ifnonnull	l1 // aload_2
	pop
	aload_2
	ifnull	l2 // iconst_1
	goto	l3 // iconst_0
l1	aload_2
	invokevirtual	Method java/lang/Object.equals:(Ljava/lang/Object;)Z
	ifeq	l3 // iconst_0
l2	iconst_1
	goto	l4 // ireturn
l3	iconst_0
l4	ireturn
  Labels:
   	l1 = 18 // aload_2
   	l2 = 25 // iconst_1
   	l3 = 29 // iconst_0
   	l4 = 30 // ireturn

public scala.collection.JavaConversions$JIteratorWrapper(java.util.Iterator);
  Signature: (Ljava/util/Iterator;)V
  Code:
   Stack=2, Locals=2, Args_size=2
	aload_0
	aload_1
	putfield	Field underlying:Ljava/util/Iterator;
	aload_0
	invokespecial	Method java/lang/Object."<init>":()V
	aload_0
	invokestatic	Method scala/collection/Iterator$class.$init$:(Lscala/collection/Iterator;)V
	aload_0
	invokestatic	Method scala/Product$class.$init$:(Lscala/Product;)V
	return
  Labels:
  LocalVariableTable: 
   Start  Length  Slot  Name   Signature
   0      18      0    this       Lscala/collection/JavaConversions$JIteratorWrapper;
   0      18      1    underlying       Ljava/util/Iterator;

  Signature: length = 0x2
   01 FFFFFF9D 

}

