Compiled from "JavaConversions.scala"
public final class scala.collection.JavaConversions$ extends java.lang.Object implements scala.ScalaObject
  SourceFile: "JavaConversions.scala"
  Scala: length = 0x
   
  InnerClass: 
   public JMapWrapper=class scala/collection/JavaConversions$JMapWrapper of class scala/collection/JavaConversions
   public JSetWrapper=class scala/collection/JavaConversions$JSetWrapper of class scala/collection/JavaConversions
   public JListWrapper=class scala/collection/JavaConversions$JListWrapper of class scala/collection/JavaConversions
   public IterableWrapper=class scala/collection/JavaConversions$IterableWrapper of class scala/collection/JavaConversions
   public IteratorWrapper=class scala/collection/JavaConversions$IteratorWrapper of class scala/collection/JavaConversions
   public JIterableWrapper=class scala/collection/JavaConversions$JIterableWrapper of class scala/collection/JavaConversions
   public JIteratorWrapper=class scala/collection/JavaConversions$JIteratorWrapper of class scala/collection/JavaConversions
   public MutableMapWrapper=class scala/collection/JavaConversions$MutableMapWrapper of class scala/collection/JavaConversions
   public MutableSetWrapper=class scala/collection/JavaConversions$MutableSetWrapper of class scala/collection/JavaConversions
   public JCollectionWrapper=class scala/collection/JavaConversions$JCollectionWrapper of class scala/collection/JavaConversions
   public JEnumerationWrapper=class scala/collection/JavaConversions$JEnumerationWrapper of class scala/collection/JavaConversions
   public MutableBufferWrapper=class scala/collection/JavaConversions$MutableBufferWrapper of class scala/collection/JavaConversions
  minor version: 0
  major version: 49
  Constant pool:
Asciz	SourceFile;
Asciz	JavaConversions.scala;
Asciz	Scala;
Asciz	MODULE$;
Asciz	Lscala/collection/JavaConversions$;;
Asciz	<clinit>;
Asciz	()V;
Asciz	Code;
Asciz	scala/collection/JavaConversions$;
class	scala/collection/JavaConversions$
Asciz	<init>;
NameAndType	"<init>":()V
Method	scala/collection/JavaConversions$."<init>":()V
Asciz	LineNumberTable;
Asciz	java/lang/Object;
class	java/lang/Object
Method	java/lang/Object."<init>":()V
NameAndType	MODULE$:Lscala/collection/JavaConversions$;
Field	scala/collection/JavaConversions$.MODULE$:Lscala/collection/JavaConversions$;
Asciz	asMap;
Asciz	(Ljava/util/Map;)Lscala/collection/mutable/Map;;
Asciz	scala/collection/JavaConversions$MutableMapWrapper;
class	scala/collection/JavaConversions$MutableMapWrapper
Asciz	underlying;
Asciz	()Lscala/collection/mutable/Map;;
NameAndType	underlying:()Lscala/collection/mutable/Map;
Method	scala/collection/JavaConversions$MutableMapWrapper.underlying:()Lscala/collection/mutable/Map;
Asciz	scala/MatchError;
class	scala/MatchError
Asciz	toString;
Asciz	()Ljava/lang/String;;
NameAndType	toString:()Ljava/lang/String;
Method	java/lang/Object.toString:()Ljava/lang/String;
Asciz	(Ljava/lang/String;)V;
NameAndType	"<init>":(Ljava/lang/String;)V
Method	scala/MatchError."<init>":(Ljava/lang/String;)V
Asciz	scala/collection/JavaConversions$JMapWrapper;
class	scala/collection/JavaConversions$JMapWrapper
Asciz	(Ljava/util/Map;)V;
NameAndType	"<init>":(Ljava/util/Map;)V
Method	scala/collection/JavaConversions$JMapWrapper."<init>":(Ljava/util/Map;)V
Asciz	this;
Asciz	m;
Asciz	Ljava/util/Map;;
Asciz	temp41;
Asciz	Lscala/collection/JavaConversions$MutableMapWrapper;;
Asciz	temp42;
Asciz	Lscala/collection/mutable/Map;;
Asciz	LocalVariableTable;
Asciz	<A:Ljava/lang/Object;B:Ljava/lang/Object;>(Ljava/util/Map<TA;TB;>;)Lscala/collection/mutable/Map<TA;TB;>;;
Asciz	Signature;
Asciz	asSet;
Asciz	(Ljava/util/Set;)Lscala/collection/mutable/Set;;
Asciz	scala/collection/JavaConversions$MutableSetWrapper;
class	scala/collection/JavaConversions$MutableSetWrapper
Asciz	()Lscala/collection/mutable/Set;;
NameAndType	underlying:()Lscala/collection/mutable/Set;
Method	scala/collection/JavaConversions$MutableSetWrapper.underlying:()Lscala/collection/mutable/Set;
Asciz	scala/collection/JavaConversions$JSetWrapper;
class	scala/collection/JavaConversions$JSetWrapper
Asciz	(Ljava/util/Set;)V;
NameAndType	"<init>":(Ljava/util/Set;)V
Method	scala/collection/JavaConversions$JSetWrapper."<init>":(Ljava/util/Set;)V
Asciz	s;
Asciz	Ljava/util/Set;;
Asciz	temp38;
Asciz	Lscala/collection/JavaConversions$MutableSetWrapper;;
Asciz	temp39;
Asciz	Lscala/collection/mutable/Set;;
Asciz	<A:Ljava/lang/Object;>(Ljava/util/Set<TA;>;)Lscala/collection/mutable/Set<TA;>;;
Asciz	asBuffer;
Asciz	(Ljava/util/List;)Lscala/collection/mutable/Buffer;;
Asciz	scala/collection/JavaConversions$MutableBufferWrapper;
class	scala/collection/JavaConversions$MutableBufferWrapper
Asciz	()Lscala/collection/mutable/Buffer;;
NameAndType	underlying:()Lscala/collection/mutable/Buffer;
Method	scala/collection/JavaConversions$MutableBufferWrapper.underlying:()Lscala/collection/mutable/Buffer;
Asciz	scala/collection/JavaConversions$JListWrapper;
class	scala/collection/JavaConversions$JListWrapper
Asciz	(Ljava/util/List;)V;
NameAndType	"<init>":(Ljava/util/List;)V
Method	scala/collection/JavaConversions$JListWrapper."<init>":(Ljava/util/List;)V
Asciz	l;
Asciz	Ljava/util/List;;
Asciz	temp35;
Asciz	Lscala/collection/JavaConversions$MutableBufferWrapper;;
Asciz	temp36;
Asciz	Lscala/collection/mutable/Buffer;;
Asciz	<A:Ljava/lang/Object;>(Ljava/util/List<TA;>;)Lscala/collection/mutable/Buffer<TA;>;;
Asciz	asIterable;
Asciz	(Ljava/util/Collection;)Lscala/collection/Iterable;;
Asciz	scala/collection/JavaConversions$IterableWrapper;
class	scala/collection/JavaConversions$IterableWrapper
Asciz	()Lscala/collection/Iterable;;
NameAndType	underlying:()Lscala/collection/Iterable;
Method	scala/collection/JavaConversions$IterableWrapper.underlying:()Lscala/collection/Iterable;
Asciz	scala/collection/JavaConversions$JCollectionWrapper;
class	scala/collection/JavaConversions$JCollectionWrapper
Asciz	(Ljava/util/Collection;)V;
NameAndType	"<init>":(Ljava/util/Collection;)V
Method	scala/collection/JavaConversions$JCollectionWrapper."<init>":(Ljava/util/Collection;)V
Asciz	i;
Asciz	Ljava/util/Collection;;
Asciz	temp32;
Asciz	Lscala/collection/JavaConversions$IterableWrapper;;
Asciz	temp33;
Asciz	Lscala/collection/Iterable;;
Asciz	<A:Ljava/lang/Object;>(Ljava/util/Collection<TA;>;)Lscala/collection/Iterable<TA;>;;
Asciz	(Ljava/lang/Iterable;)Lscala/collection/Iterable;;
Asciz	scala/collection/JavaConversions$JIterableWrapper;
class	scala/collection/JavaConversions$JIterableWrapper
Asciz	(Ljava/lang/Iterable;)V;
NameAndType	"<init>":(Ljava/lang/Iterable;)V
Method	scala/collection/JavaConversions$JIterableWrapper."<init>":(Ljava/lang/Iterable;)V
Asciz	Ljava/lang/Iterable;;
Asciz	temp29;
Asciz	temp30;
Asciz	<A:Ljava/lang/Object;>(Ljava/lang/Iterable<TA;>;)Lscala/collection/Iterable<TA;>;;
Asciz	asIterator;
Asciz	(Ljava/util/Enumeration;)Lscala/collection/Iterator;;
Asciz	scala/collection/JavaConversions$IteratorWrapper;
class	scala/collection/JavaConversions$IteratorWrapper
Asciz	()Lscala/collection/Iterator;;
NameAndType	underlying:()Lscala/collection/Iterator;
Method	scala/collection/JavaConversions$IteratorWrapper.underlying:()Lscala/collection/Iterator;
Asciz	scala/collection/JavaConversions$JEnumerationWrapper;
class	scala/collection/JavaConversions$JEnumerationWrapper
Asciz	(Ljava/util/Enumeration;)V;
NameAndType	"<init>":(Ljava/util/Enumeration;)V
Method	scala/collection/JavaConversions$JEnumerationWrapper."<init>":(Ljava/util/Enumeration;)V
Asciz	Ljava/util/Enumeration;;
Asciz	temp26;
Asciz	Lscala/collection/JavaConversions$IteratorWrapper;;
Asciz	temp27;
Asciz	Lscala/collection/Iterator;;
Asciz	<A:Ljava/lang/Object;>(Ljava/util/Enumeration<TA;>;)Lscala/collection/Iterator<TA;>;;
Asciz	(Ljava/util/Iterator;)Lscala/collection/Iterator;;
Asciz	scala/collection/JavaConversions$JIteratorWrapper;
class	scala/collection/JavaConversions$JIteratorWrapper
Asciz	(Ljava/util/Iterator;)V;
NameAndType	"<init>":(Ljava/util/Iterator;)V
Method	scala/collection/JavaConversions$JIteratorWrapper."<init>":(Ljava/util/Iterator;)V
Asciz	Ljava/util/Iterator;;
Asciz	temp23;
Asciz	temp24;
Asciz	<A:Ljava/lang/Object;>(Ljava/util/Iterator<TA;>;)Lscala/collection/Iterator<TA;>;;
Asciz	(Lscala/collection/mutable/Map;Lscala/reflect/ClassManifest;)Ljava/util/Map;;
Asciz	()Ljava/util/Map;;
NameAndType	underlying:()Ljava/util/Map;
Method	scala/collection/JavaConversions$JMapWrapper.underlying:()Ljava/util/Map;
Asciz	scala/collection/MapLike;
class	scala/collection/MapLike
InterfaceMethod	scala/collection/MapLike.toString:()Ljava/lang/String;
Asciz	(Lscala/collection/mutable/Map;Lscala/reflect/ClassManifest;)V;
NameAndType	"<init>":(Lscala/collection/mutable/Map;Lscala/reflect/ClassManifest;)V
Method	scala/collection/JavaConversions$MutableMapWrapper."<init>":(Lscala/collection/mutable/Map;Lscala/reflect/ClassManifest;)V
Asciz	ma;
Asciz	Lscala/reflect/ClassManifest;;
Asciz	temp20;
Asciz	Lscala/collection/JavaConversions$JMapWrapper;;
Asciz	temp21;
Asciz	<A:Ljava/lang/Object;B:Ljava/lang/Object;>(Lscala/collection/mutable/Map<TA;TB;>;Lscala/reflect/ClassManifest<TA;>;)Ljava/util/Map<TA;TB;>;;
Asciz	(Lscala/collection/mutable/Set;Lscala/reflect/ClassManifest;)Ljava/util/Set;;
Asciz	()Ljava/util/Set;;
NameAndType	underlying:()Ljava/util/Set;
Method	scala/collection/JavaConversions$JSetWrapper.underlying:()Ljava/util/Set;
Asciz	scala/collection/SetLike;
class	scala/collection/SetLike
InterfaceMethod	scala/collection/SetLike.toString:()Ljava/lang/String;
Asciz	(Lscala/collection/mutable/Set;Lscala/reflect/ClassManifest;)V;
NameAndType	"<init>":(Lscala/collection/mutable/Set;Lscala/reflect/ClassManifest;)V
Method	scala/collection/JavaConversions$MutableSetWrapper."<init>":(Lscala/collection/mutable/Set;Lscala/reflect/ClassManifest;)V
Asciz	temp17;
Asciz	Lscala/collection/JavaConversions$JSetWrapper;;
Asciz	temp18;
Asciz	<A:Ljava/lang/Object;>(Lscala/collection/mutable/Set<TA;>;Lscala/reflect/ClassManifest<TA;>;)Ljava/util/Set<TA;>;;
Asciz	asList;
Asciz	(Lscala/collection/mutable/Buffer;)Ljava/util/List;;
Asciz	()Ljava/util/List;;
NameAndType	underlying:()Ljava/util/List;
Method	scala/collection/JavaConversions$JListWrapper.underlying:()Ljava/util/List;
Asciz	scala/collection/SeqLike;
class	scala/collection/SeqLike
InterfaceMethod	scala/collection/SeqLike.toString:()Ljava/lang/String;
Asciz	(Lscala/collection/mutable/Buffer;)V;
NameAndType	"<init>":(Lscala/collection/mutable/Buffer;)V
Method	scala/collection/JavaConversions$MutableBufferWrapper."<init>":(Lscala/collection/mutable/Buffer;)V
Asciz	b;
Asciz	temp14;
Asciz	Lscala/collection/JavaConversions$JListWrapper;;
Asciz	temp15;
Asciz	<A:Ljava/lang/Object;>(Lscala/collection/mutable/Buffer<TA;>;)Ljava/util/List<TA;>;;
Asciz	asCollection;
Asciz	(Lscala/collection/Iterable;)Ljava/util/Collection;;
Asciz	()Ljava/util/Collection;;
NameAndType	underlying:()Ljava/util/Collection;
Method	scala/collection/JavaConversions$JCollectionWrapper.underlying:()Ljava/util/Collection;
Asciz	scala/collection/TraversableLike;
class	scala/collection/TraversableLike
InterfaceMethod	scala/collection/TraversableLike.toString:()Ljava/lang/String;
Asciz	(Lscala/collection/Iterable;)V;
NameAndType	"<init>":(Lscala/collection/Iterable;)V
Method	scala/collection/JavaConversions$IterableWrapper."<init>":(Lscala/collection/Iterable;)V
Asciz	temp11;
Asciz	Lscala/collection/JavaConversions$JCollectionWrapper;;
Asciz	temp12;
Asciz	<A:Ljava/lang/Object;>(Lscala/collection/Iterable<TA;>;)Ljava/util/Collection<TA;>;;
Asciz	(Lscala/collection/Iterable;)Ljava/lang/Iterable;;
Asciz	()Ljava/lang/Iterable;;
NameAndType	underlying:()Ljava/lang/Iterable;
Method	scala/collection/JavaConversions$JIterableWrapper.underlying:()Ljava/lang/Iterable;
Asciz	temp8;
Asciz	Lscala/collection/JavaConversions$JIterableWrapper;;
Asciz	temp9;
Asciz	<A:Ljava/lang/Object;>(Lscala/collection/Iterable<TA;>;)Ljava/lang/Iterable<TA;>;;
Asciz	asEnumeration;
Asciz	(Lscala/collection/Iterator;)Ljava/util/Enumeration;;
Asciz	()Ljava/util/Enumeration;;
NameAndType	underlying:()Ljava/util/Enumeration;
Method	scala/collection/JavaConversions$JEnumerationWrapper.underlying:()Ljava/util/Enumeration;
Asciz	scala/collection/Iterator;
class	scala/collection/Iterator
InterfaceMethod	scala/collection/Iterator.toString:()Ljava/lang/String;
Asciz	(Lscala/collection/Iterator;)V;
NameAndType	"<init>":(Lscala/collection/Iterator;)V
Method	scala/collection/JavaConversions$IteratorWrapper."<init>":(Lscala/collection/Iterator;)V
Asciz	temp5;
Asciz	Lscala/collection/JavaConversions$JEnumerationWrapper;;
Asciz	temp6;
Asciz	<A:Ljava/lang/Object;>(Lscala/collection/Iterator<TA;>;)Ljava/util/Enumeration<TA;>;;
Asciz	(Lscala/collection/Iterator;)Ljava/util/Iterator;;
Asciz	()Ljava/util/Iterator;;
NameAndType	underlying:()Ljava/util/Iterator;
Method	scala/collection/JavaConversions$JIteratorWrapper.underlying:()Ljava/util/Iterator;
Asciz	temp2;
Asciz	Lscala/collection/JavaConversions$JIteratorWrapper;;
Asciz	temp3;
Asciz	<A:Ljava/lang/Object;>(Lscala/collection/Iterator<TA;>;)Ljava/util/Iterator<TA;>;;
Asciz	InnerClasses;
Asciz	scala/collection/JavaConversions;
class	scala/collection/JavaConversions
Asciz	JMapWrapper;
Asciz	JSetWrapper;
Asciz	JListWrapper;
Asciz	IterableWrapper;
Asciz	IteratorWrapper;
Asciz	JIterableWrapper;
Asciz	JIteratorWrapper;
Asciz	MutableMapWrapper;
Asciz	MutableSetWrapper;
Asciz	JCollectionWrapper;
Asciz	JEnumerationWrapper;
Asciz	MutableBufferWrapper;
Asciz	scala/ScalaObject;
class	scala/ScalaObject

{
public static final scala.collection.JavaConversions$ MODULE$;
  Signature: Lscala/collection/JavaConversions$;

public static {};
  Signature: ()V
  Code:
   Stack=1, Locals=0, Args_size=0
	new	class scala/collection/JavaConversions$
	invokespecial	Method "<init>":()V
	return
  Labels:

private scala.collection.JavaConversions$();
  Signature: ()V
  Code:
   Stack=1, Locals=1, Args_size=1
	aload_0
	invokespecial	Method java/lang/Object."<init>":()V
	aload_0
	putstatic	Field MODULE$:Lscala/collection/JavaConversions$;
	return
  Labels:

public scala.collection.mutable.Map asMap(java.util.Map);
  Signature: (Ljava/util/Map;)Lscala/collection/mutable/Map;
  Code:
   Stack=3, Locals=4, Args_size=2
	aload_1
	instanceof	class scala/collection/JavaConversions$MutableMapWrapper
	ifeq	l1 // iconst_1
	aload_1
	checkcast	class scala/collection/JavaConversions$MutableMapWrapper
	astore_2
	aload_2
	invokevirtual	Method scala/collection/JavaConversions$MutableMapWrapper.underlying:()Lscala/collection/mutable/Map;
	astore_3
	iconst_1
	ifeq	l2 // new
	aload_3
	goto	l3 // areturn
l2	new	class scala/MatchError
	dup
	aload_1
	invokevirtual	Method java/lang/Object.toString:()Ljava/lang/String;
	invokespecial	Method scala/MatchError."<init>":(Ljava/lang/String;)V
	athrow
l1	iconst_1
	ifeq	l4 // new
	new	class scala/collection/JavaConversions$JMapWrapper
	dup
	aload_1
	invokespecial	Method scala/collection/JavaConversions$JMapWrapper."<init>":(Ljava/util/Map;)V
l3	areturn
l4	new	class scala/MatchError
	dup
	aload_1
	invokevirtual	Method java/lang/Object.toString:()Ljava/lang/String;
	invokespecial	Method scala/MatchError."<init>":(Ljava/lang/String;)V
	athrow
  Labels:
   	l2 = 25 // new
   	l1 = 37 // iconst_1
   	l3 = 49 // areturn
   	l4 = 50 // new
  LocalVariableTable: 
   Start  Length  Slot  Name   Signature
   0      62      0    this       Lscala/collection/JavaConversions$;
   0      62      1    m       Ljava/util/Map;
   12      25      2    temp41       Lscala/collection/JavaConversions$MutableMapWrapper;
   17      20      3    temp42       Lscala/collection/mutable/Map;

  Signature: length = 0x2
   00 32 

public scala.collection.mutable.Set asSet(java.util.Set);
  Signature: (Ljava/util/Set;)Lscala/collection/mutable/Set;
  Code:
   Stack=3, Locals=4, Args_size=2
	aload_1
	instanceof	class scala/collection/JavaConversions$MutableSetWrapper
	ifeq	l1 // iconst_1
	aload_1
	checkcast	class scala/collection/JavaConversions$MutableSetWrapper
	astore_2
	aload_2
	invokevirtual	Method scala/collection/JavaConversions$MutableSetWrapper.underlying:()Lscala/collection/mutable/Set;
	astore_3
	iconst_1
	ifeq	l2 // new
	aload_3
	goto	l3 // areturn
l2	new	class scala/MatchError
	dup
	aload_1
	invokevirtual	Method java/lang/Object.toString:()Ljava/lang/String;
	invokespecial	Method scala/MatchError."<init>":(Ljava/lang/String;)V
	athrow
l1	iconst_1
	ifeq	l4 // new
	new	class scala/collection/JavaConversions$JSetWrapper
	dup
	aload_1
	invokespecial	Method scala/collection/JavaConversions$JSetWrapper."<init>":(Ljava/util/Set;)V
l3	areturn
l4	new	class scala/MatchError
	dup
	aload_1
	invokevirtual	Method java/lang/Object.toString:()Ljava/lang/String;
	invokespecial	Method scala/MatchError."<init>":(Ljava/lang/String;)V
	athrow
  Labels:
   	l2 = 25 // new
   	l1 = 37 // iconst_1
   	l3 = 49 // areturn
   	l4 = 50 // new
  LocalVariableTable: 
   Start  Length  Slot  Name   Signature
   0      62      0    this       Lscala/collection/JavaConversions$;
   0      62      1    s       Ljava/util/Set;
   12      25      2    temp38       Lscala/collection/JavaConversions$MutableSetWrapper;
   17      20      3    temp39       Lscala/collection/mutable/Set;

  Signature: length = 0x2
   00 46 

public scala.collection.mutable.Buffer asBuffer(java.util.List);
  Signature: (Ljava/util/List;)Lscala/collection/mutable/Buffer;
  Code:
   Stack=3, Locals=4, Args_size=2
	aload_1
	instanceof	class scala/collection/JavaConversions$MutableBufferWrapper
	ifeq	l1 // iconst_1
	aload_1
	checkcast	class scala/collection/JavaConversions$MutableBufferWrapper
	astore_2
	aload_2
	invokevirtual	Method scala/collection/JavaConversions$MutableBufferWrapper.underlying:()Lscala/collection/mutable/Buffer;
	astore_3
	iconst_1
	ifeq	l2 // new
	aload_3
	goto	l3 // areturn
l2	new	class scala/MatchError
	dup
	aload_1
	invokevirtual	Method java/lang/Object.toString:()Ljava/lang/String;
	invokespecial	Method scala/MatchError."<init>":(Ljava/lang/String;)V
	athrow
l1	iconst_1
	ifeq	l4 // new
	new	class scala/collection/JavaConversions$JListWrapper
	dup
	aload_1
	invokespecial	Method scala/collection/JavaConversions$JListWrapper."<init>":(Ljava/util/List;)V
l3	areturn
l4	new	class scala/MatchError
	dup
	aload_1
	invokevirtual	Method java/lang/Object.toString:()Ljava/lang/String;
	invokespecial	Method scala/MatchError."<init>":(Ljava/lang/String;)V
	athrow
  Labels:
   	l2 = 25 // new
   	l1 = 37 // iconst_1
   	l3 = 49 // areturn
   	l4 = 50 // new
  LocalVariableTable: 
   Start  Length  Slot  Name   Signature
   0      62      0    this       Lscala/collection/JavaConversions$;
   0      62      1    l       Ljava/util/List;
   12      25      2    temp35       Lscala/collection/JavaConversions$MutableBufferWrapper;
   17      20      3    temp36       Lscala/collection/mutable/Buffer;

  Signature: length = 0x2
   00 59 

public scala.collection.Iterable asIterable(java.util.Collection);
  Signature: (Ljava/util/Collection;)Lscala/collection/Iterable;
  Code:
   Stack=3, Locals=4, Args_size=2
	aload_1
	instanceof	class scala/collection/JavaConversions$IterableWrapper
	ifeq	l1 // iconst_1
	aload_1
	checkcast	class scala/collection/JavaConversions$IterableWrapper
	astore_2
	aload_2
	invokevirtual	Method scala/collection/JavaConversions$IterableWrapper.underlying:()Lscala/collection/Iterable;
	astore_3
	iconst_1
	ifeq	l2 // new
	aload_3
	goto	l3 // areturn
l2	new	class scala/MatchError
	dup
	aload_1
	invokevirtual	Method java/lang/Object.toString:()Ljava/lang/String;
	invokespecial	Method scala/MatchError."<init>":(Ljava/lang/String;)V
	athrow
l1	iconst_1
	ifeq	l4 // new
	new	class scala/collection/JavaConversions$JCollectionWrapper
	dup
	aload_1
	invokespecial	Method scala/collection/JavaConversions$JCollectionWrapper."<init>":(Ljava/util/Collection;)V
l3	areturn
l4	new	class scala/MatchError
	dup
	aload_1
	invokevirtual	Method java/lang/Object.toString:()Ljava/lang/String;
	invokespecial	Method scala/MatchError."<init>":(Ljava/lang/String;)V
	athrow
  Labels:
   	l2 = 25 // new
   	l1 = 37 // iconst_1
   	l3 = 49 // areturn
   	l4 = 50 // new
  LocalVariableTable: 
   Start  Length  Slot  Name   Signature
   0      62      0    this       Lscala/collection/JavaConversions$;
   0      62      1    i       Ljava/util/Collection;
   12      25      2    temp32       Lscala/collection/JavaConversions$IterableWrapper;
   17      20      3    temp33       Lscala/collection/Iterable;

  Signature: length = 0x2
   00 6C 

public scala.collection.Iterable asIterable(java.lang.Iterable);
  Signature: (Ljava/lang/Iterable;)Lscala/collection/Iterable;
  Code:
   Stack=3, Locals=4, Args_size=2
	aload_1
	instanceof	class scala/collection/JavaConversions$IterableWrapper
	ifeq	l1 // iconst_1
	aload_1
	checkcast	class scala/collection/JavaConversions$IterableWrapper
	astore_2
	aload_2
	invokevirtual	Method scala/collection/JavaConversions$IterableWrapper.underlying:()Lscala/collection/Iterable;
	astore_3
	iconst_1
	ifeq	l2 // new
	aload_3
	goto	l3 // areturn
l2	new	class scala/MatchError
	dup
	aload_1
	invokevirtual	Method java/lang/Object.toString:()Ljava/lang/String;
	invokespecial	Method scala/MatchError."<init>":(Ljava/lang/String;)V
	athrow
l1	iconst_1
	ifeq	l4 // new
	new	class scala/collection/JavaConversions$JIterableWrapper
	dup
	aload_1
	invokespecial	Method scala/collection/JavaConversions$JIterableWrapper."<init>":(Ljava/lang/Iterable;)V
l3	areturn
l4	new	class scala/MatchError
	dup
	aload_1
	invokevirtual	Method java/lang/Object.toString:()Ljava/lang/String;
	invokespecial	Method scala/MatchError."<init>":(Ljava/lang/String;)V
	athrow
  Labels:
   	l2 = 25 // new
   	l1 = 37 // iconst_1
   	l3 = 49 // areturn
   	l4 = 50 // new
  LocalVariableTable: 
   Start  Length  Slot  Name   Signature
   0      62      0    this       Lscala/collection/JavaConversions$;
   0      62      1    i       Ljava/lang/Iterable;
   12      25      2    temp29       Lscala/collection/JavaConversions$IterableWrapper;
   17      20      3    temp30       Lscala/collection/Iterable;

  Signature: length = 0x2
   00 76 

public scala.collection.Iterator asIterator(java.util.Enumeration);
  Signature: (Ljava/util/Enumeration;)Lscala/collection/Iterator;
  Code:
   Stack=3, Locals=4, Args_size=2
	aload_1
	instanceof	class scala/collection/JavaConversions$IteratorWrapper
	ifeq	l1 // iconst_1
	aload_1
	checkcast	class scala/collection/JavaConversions$IteratorWrapper
	astore_2
	aload_2
	invokevirtual	Method scala/collection/JavaConversions$IteratorWrapper.underlying:()Lscala/collection/Iterator;
	astore_3
	iconst_1
	ifeq	l2 // new
	aload_3
	goto	l3 // areturn
l2	new	class scala/MatchError
	dup
	aload_1
	invokevirtual	Method java/lang/Object.toString:()Ljava/lang/String;
	invokespecial	Method scala/MatchError."<init>":(Ljava/lang/String;)V
	athrow
l1	iconst_1
	ifeq	l4 // new
	new	class scala/collection/JavaConversions$JEnumerationWrapper
	dup
	aload_1
	invokespecial	Method scala/collection/JavaConversions$JEnumerationWrapper."<init>":(Ljava/util/Enumeration;)V
l3	areturn
l4	new	class scala/MatchError
	dup
	aload_1
	invokevirtual	Method java/lang/Object.toString:()Ljava/lang/String;
	invokespecial	Method scala/MatchError."<init>":(Ljava/lang/String;)V
	athrow
  Labels:
   	l2 = 25 // new
   	l1 = 37 // iconst_1
   	l3 = 49 // areturn
   	l4 = 50 // new
  LocalVariableTable: 
   Start  Length  Slot  Name   Signature
   0      62      0    this       Lscala/collection/JavaConversions$;
   0      62      1    i       Ljava/util/Enumeration;
   12      25      2    temp26       Lscala/collection/JavaConversions$IteratorWrapper;
   17      20      3    temp27       Lscala/collection/Iterator;

  Signature: length = 0x2
   00 FFFFFF88 

public scala.collection.Iterator asIterator(java.util.Iterator);
  Signature: (Ljava/util/Iterator;)Lscala/collection/Iterator;
  Code:
   Stack=3, Locals=4, Args_size=2
	aload_1
	instanceof	class scala/collection/JavaConversions$IteratorWrapper
	ifeq	l1 // iconst_1
	aload_1
	checkcast	class scala/collection/JavaConversions$IteratorWrapper
	astore_2
	aload_2
	invokevirtual	Method scala/collection/JavaConversions$IteratorWrapper.underlying:()Lscala/collection/Iterator;
	astore_3
	iconst_1
	ifeq	l2 // new
	aload_3
	goto	l3 // areturn
l2	new	class scala/MatchError
	dup
	aload_1
	invokevirtual	Method java/lang/Object.toString:()Ljava/lang/String;
	invokespecial	Method scala/MatchError."<init>":(Ljava/lang/String;)V
	athrow
l1	iconst_1
	ifeq	l4 // new
	new	class scala/collection/JavaConversions$JIteratorWrapper
	dup
	aload_1
	invokespecial	Method scala/collection/JavaConversions$JIteratorWrapper."<init>":(Ljava/util/Iterator;)V
l3	areturn
l4	new	class scala/MatchError
	dup
	aload_1
	invokevirtual	Method java/lang/Object.toString:()Ljava/lang/String;
	invokespecial	Method scala/MatchError."<init>":(Ljava/lang/String;)V
	athrow
  Labels:
   	l2 = 25 // new
   	l1 = 37 // iconst_1
   	l3 = 49 // areturn
   	l4 = 50 // new
  LocalVariableTable: 
   Start  Length  Slot  Name   Signature
   0      62      0    this       Lscala/collection/JavaConversions$;
   0      62      1    i       Ljava/util/Iterator;
   12      25      2    temp23       Lscala/collection/JavaConversions$IteratorWrapper;
   17      20      3    temp24       Lscala/collection/Iterator;

  Signature: length = 0x2
   00 FFFFFF92 

public java.util.Map asMap(scala.collection.mutable.Map, scala.reflect.ClassManifest);
  Signature: (Lscala/collection/mutable/Map;Lscala/reflect/ClassManifest;)Ljava/util/Map;
  Code:
   Stack=4, Locals=5, Args_size=3
	aload_1
	instanceof	class scala/collection/JavaConversions$JMapWrapper
	ifeq	l1 // iconst_1
	aload_1
	checkcast	class scala/collection/JavaConversions$JMapWrapper
	astore_3
	aload_3
	invokevirtual	Method scala/collection/JavaConversions$JMapWrapper.underlying:()Ljava/util/Map;
	astore	4
	iconst_1
	ifeq	l2 // new
	aload	4
	goto	l3 // areturn
l2	new	class scala/MatchError
	dup
	aload_1
	invokeinterface	InterfaceMethod scala/collection/MapLike.toString:()Ljava/lang/String;
	invokespecial	Method scala/MatchError."<init>":(Ljava/lang/String;)V
	athrow
l1	iconst_1
	ifeq	l4 // new
	new	class scala/collection/JavaConversions$MutableMapWrapper
	dup
	aload_1
	aload_2
	invokespecial	Method scala/collection/JavaConversions$MutableMapWrapper."<init>":(Lscala/collection/mutable/Map;Lscala/reflect/ClassManifest;)V
l3	areturn
l4	new	class scala/MatchError
	dup
	aload_1
	invokeinterface	InterfaceMethod scala/collection/MapLike.toString:()Ljava/lang/String;
	invokespecial	Method scala/MatchError."<init>":(Ljava/lang/String;)V
	athrow
  Labels:
   	l2 = 27 // new
   	l1 = 41 // iconst_1
   	l3 = 54 // areturn
   	l4 = 55 // new
  LocalVariableTable: 
   Start  Length  Slot  Name   Signature
   0      69      0    this       Lscala/collection/JavaConversions$;
   0      69      1    m       Lscala/collection/mutable/Map;
   0      69      2    ma       Lscala/reflect/ClassManifest;
   12      29      3    temp20       Lscala/collection/JavaConversions$JMapWrapper;
   18      23      4    temp21       Ljava/util/Map;

  Signature: length = 0x2
   00 FFFFFFA2 

public java.util.Set asSet(scala.collection.mutable.Set, scala.reflect.ClassManifest);
  Signature: (Lscala/collection/mutable/Set;Lscala/reflect/ClassManifest;)Ljava/util/Set;
  Code:
   Stack=4, Locals=5, Args_size=3
	aload_1
	instanceof	class scala/collection/JavaConversions$JSetWrapper
	ifeq	l1 // iconst_1
	aload_1
	checkcast	class scala/collection/JavaConversions$JSetWrapper
	astore_3
	aload_3
	invokevirtual	Method scala/collection/JavaConversions$JSetWrapper.underlying:()Ljava/util/Set;
	astore	4
	iconst_1
	ifeq	l2 // new
	aload	4
	goto	l3 // areturn
l2	new	class scala/MatchError
	dup
	aload_1
	invokeinterface	InterfaceMethod scala/collection/SetLike.toString:()Ljava/lang/String;
	invokespecial	Method scala/MatchError."<init>":(Ljava/lang/String;)V
	athrow
l1	iconst_1
	ifeq	l4 // new
	new	class scala/collection/JavaConversions$MutableSetWrapper
	dup
	aload_1
	aload_2
	invokespecial	Method scala/collection/JavaConversions$MutableSetWrapper."<init>":(Lscala/collection/mutable/Set;Lscala/reflect/ClassManifest;)V
l3	areturn
l4	new	class scala/MatchError
	dup
	aload_1
	invokeinterface	InterfaceMethod scala/collection/SetLike.toString:()Ljava/lang/String;
	invokespecial	Method scala/MatchError."<init>":(Ljava/lang/String;)V
	athrow
  Labels:
   	l2 = 27 // new
   	l1 = 41 // iconst_1
   	l3 = 54 // areturn
   	l4 = 55 // new
  LocalVariableTable: 
   Start  Length  Slot  Name   Signature
   0      69      0    this       Lscala/collection/JavaConversions$;
   0      69      1    s       Lscala/collection/mutable/Set;
   0      69      2    m       Lscala/reflect/ClassManifest;
   12      29      3    temp17       Lscala/collection/JavaConversions$JSetWrapper;
   18      23      4    temp18       Ljava/util/Set;

  Signature: length = 0x2
   00 FFFFFFB0 

public java.util.List asList(scala.collection.mutable.Buffer);
  Signature: (Lscala/collection/mutable/Buffer;)Ljava/util/List;
  Code:
   Stack=3, Locals=4, Args_size=2
	aload_1
	instanceof	class scala/collection/JavaConversions$JListWrapper
	ifeq	l1 // iconst_1
	aload_1
	checkcast	class scala/collection/JavaConversions$JListWrapper
	astore_2
	aload_2
	invokevirtual	Method scala/collection/JavaConversions$JListWrapper.underlying:()Ljava/util/List;
	astore_3
	iconst_1
	ifeq	l2 // new
	aload_3
	goto	l3 // areturn
l2	new	class scala/MatchError
	dup
	aload_1
	invokeinterface	InterfaceMethod scala/collection/SeqLike.toString:()Ljava/lang/String;
	invokespecial	Method scala/MatchError."<init>":(Ljava/lang/String;)V
	athrow
l1	iconst_1
	ifeq	l4 // new
	new	class scala/collection/JavaConversions$MutableBufferWrapper
	dup
	aload_1
	invokespecial	Method scala/collection/JavaConversions$MutableBufferWrapper."<init>":(Lscala/collection/mutable/Buffer;)V
l3	areturn
l4	new	class scala/MatchError
	dup
	aload_1
	invokeinterface	InterfaceMethod scala/collection/SeqLike.toString:()Ljava/lang/String;
	invokespecial	Method scala/MatchError."<init>":(Ljava/lang/String;)V
	athrow
  Labels:
   	l2 = 25 // new
   	l1 = 39 // iconst_1
   	l3 = 51 // areturn
   	l4 = 52 // new
  LocalVariableTable: 
   Start  Length  Slot  Name   Signature
   0      66      0    this       Lscala/collection/JavaConversions$;
   0      66      1    b       Lscala/collection/mutable/Buffer;
   12      27      2    temp14       Lscala/collection/JavaConversions$JListWrapper;
   17      22      3    temp15       Ljava/util/List;

  Signature: length = 0x2
   00 FFFFFFC0 

public java.util.Collection asCollection(scala.collection.Iterable);
  Signature: (Lscala/collection/Iterable;)Ljava/util/Collection;
  Code:
   Stack=3, Locals=4, Args_size=2
	aload_1
	instanceof	class scala/collection/JavaConversions$JCollectionWrapper
	ifeq	l1 // iconst_1
	aload_1
	checkcast	class scala/collection/JavaConversions$JCollectionWrapper
	astore_2
	aload_2
	invokevirtual	Method scala/collection/JavaConversions$JCollectionWrapper.underlying:()Ljava/util/Collection;
	astore_3
	iconst_1
	ifeq	l2 // new
	aload_3
	goto	l3 // areturn
l2	new	class scala/MatchError
	dup
	aload_1
	invokeinterface	InterfaceMethod scala/collection/TraversableLike.toString:()Ljava/lang/String;
	invokespecial	Method scala/MatchError."<init>":(Ljava/lang/String;)V
	athrow
l1	iconst_1
	ifeq	l4 // new
	new	class scala/collection/JavaConversions$IterableWrapper
	dup
	aload_1
	invokespecial	Method scala/collection/JavaConversions$IterableWrapper."<init>":(Lscala/collection/Iterable;)V
l3	areturn
l4	new	class scala/MatchError
	dup
	aload_1
	invokeinterface	InterfaceMethod scala/collection/TraversableLike.toString:()Ljava/lang/String;
	invokespecial	Method scala/MatchError."<init>":(Ljava/lang/String;)V
	athrow
  Labels:
   	l2 = 25 // new
   	l1 = 39 // iconst_1
   	l3 = 51 // areturn
   	l4 = 52 // new
  LocalVariableTable: 
   Start  Length  Slot  Name   Signature
   0      66      0    this       Lscala/collection/JavaConversions$;
   0      66      1    i       Lscala/collection/Iterable;
   12      27      2    temp11       Lscala/collection/JavaConversions$JCollectionWrapper;
   17      22      3    temp12       Ljava/util/Collection;

  Signature: length = 0x2
   00 FFFFFFCF 

public java.lang.Iterable asIterable(scala.collection.Iterable);
  Signature: (Lscala/collection/Iterable;)Ljava/lang/Iterable;
  Code:
   Stack=3, Locals=4, Args_size=2
	aload_1
	instanceof	class scala/collection/JavaConversions$JIterableWrapper
	ifeq	l1 // iconst_1
	aload_1
	checkcast	class scala/collection/JavaConversions$JIterableWrapper
	astore_2
	aload_2
	invokevirtual	Method scala/collection/JavaConversions$JIterableWrapper.underlying:()Ljava/lang/Iterable;
	astore_3
	iconst_1
	ifeq	l2 // new
	aload_3
	goto	l3 // areturn
l2	new	class scala/MatchError
	dup
	aload_1
	invokeinterface	InterfaceMethod scala/collection/TraversableLike.toString:()Ljava/lang/String;
	invokespecial	Method scala/MatchError."<init>":(Ljava/lang/String;)V
	athrow
l1	iconst_1
	ifeq	l4 // new
	new	class scala/collection/JavaConversions$IterableWrapper
	dup
	aload_1
	invokespecial	Method scala/collection/JavaConversions$IterableWrapper."<init>":(Lscala/collection/Iterable;)V
l3	areturn
l4	new	class scala/MatchError
	dup
	aload_1
	invokeinterface	InterfaceMethod scala/collection/TraversableLike.toString:()Ljava/lang/String;
	invokespecial	Method scala/MatchError."<init>":(Ljava/lang/String;)V
	athrow
  Labels:
   	l2 = 25 // new
   	l1 = 39 // iconst_1
   	l3 = 51 // areturn
   	l4 = 52 // new
  LocalVariableTable: 
   Start  Length  Slot  Name   Signature
   0      66      0    this       Lscala/collection/JavaConversions$;
   0      66      1    i       Lscala/collection/Iterable;
   12      27      2    temp8       Lscala/collection/JavaConversions$JIterableWrapper;
   17      22      3    temp9       Ljava/lang/Iterable;

  Signature: length = 0x2
   00 FFFFFFD7 

public java.util.Enumeration asEnumeration(scala.collection.Iterator);
  Signature: (Lscala/collection/Iterator;)Ljava/util/Enumeration;
  Code:
   Stack=3, Locals=4, Args_size=2
	aload_1
	instanceof	class scala/collection/JavaConversions$JEnumerationWrapper
	ifeq	l1 // iconst_1
	aload_1
	checkcast	class scala/collection/JavaConversions$JEnumerationWrapper
	astore_2
	aload_2
	invokevirtual	Method scala/collection/JavaConversions$JEnumerationWrapper.underlying:()Ljava/util/Enumeration;
	astore_3
	iconst_1
	ifeq	l2 // new
	aload_3
	goto	l3 // areturn
l2	new	class scala/MatchError
	dup
	aload_1
	invokeinterface	InterfaceMethod scala/collection/Iterator.toString:()Ljava/lang/String;
	invokespecial	Method scala/MatchError."<init>":(Ljava/lang/String;)V
	athrow
l1	iconst_1
	ifeq	l4 // new
	new	class scala/collection/JavaConversions$IteratorWrapper
	dup
	aload_1
	invokespecial	Method scala/collection/JavaConversions$IteratorWrapper."<init>":(Lscala/collection/Iterator;)V
l3	areturn
l4	new	class scala/MatchError
	dup
	aload_1
	invokeinterface	InterfaceMethod scala/collection/Iterator.toString:()Ljava/lang/String;
	invokespecial	Method scala/MatchError."<init>":(Ljava/lang/String;)V
	athrow
  Labels:
   	l2 = 25 // new
   	l1 = 39 // iconst_1
   	l3 = 51 // areturn
   	l4 = 52 // new
  LocalVariableTable: 
   Start  Length  Slot  Name   Signature
   0      66      0    this       Lscala/collection/JavaConversions$;
   0      66      1    i       Lscala/collection/Iterator;
   12      27      2    temp5       Lscala/collection/JavaConversions$JEnumerationWrapper;
   17      22      3    temp6       Ljava/util/Enumeration;

  Signature: length = 0x2
   00 FFFFFFE6 

public java.util.Iterator asIterator(scala.collection.Iterator);
  Signature: (Lscala/collection/Iterator;)Ljava/util/Iterator;
  Code:
   Stack=3, Locals=4, Args_size=2
	aload_1
	instanceof	class scala/collection/JavaConversions$JIteratorWrapper
	ifeq	l1 // iconst_1
	aload_1
	checkcast	class scala/collection/JavaConversions$JIteratorWrapper
	astore_2
	aload_2
	invokevirtual	Method scala/collection/JavaConversions$JIteratorWrapper.underlying:()Ljava/util/Iterator;
	astore_3
	iconst_1
	ifeq	l2 // new
	aload_3
	goto	l3 // areturn
l2	new	class scala/MatchError
	dup
	aload_1
	invokeinterface	InterfaceMethod scala/collection/Iterator.toString:()Ljava/lang/String;
	invokespecial	Method scala/MatchError."<init>":(Ljava/lang/String;)V
	athrow
l1	iconst_1
	ifeq	l4 // new
	new	class scala/collection/JavaConversions$IteratorWrapper
	dup
	aload_1
	invokespecial	Method scala/collection/JavaConversions$IteratorWrapper."<init>":(Lscala/collection/Iterator;)V
l3	areturn
l4	new	class scala/MatchError
	dup
	aload_1
	invokeinterface	InterfaceMethod scala/collection/Iterator.toString:()Ljava/lang/String;
	invokespecial	Method scala/MatchError."<init>":(Ljava/lang/String;)V
	athrow
  Labels:
   	l2 = 25 // new
   	l1 = 39 // iconst_1
   	l3 = 51 // areturn
   	l4 = 52 // new
  LocalVariableTable: 
   Start  Length  Slot  Name   Signature
   0      66      0    this       Lscala/collection/JavaConversions$;
   0      66      1    i       Lscala/collection/Iterator;
   12      27      2    temp2       Lscala/collection/JavaConversions$JIteratorWrapper;
   17      22      3    temp3       Ljava/util/Iterator;

  Signature: length = 0x2
   00 FFFFFFEE 

}

