Compiled from "JavaConversions.scala"
public final class scala.collection.JavaConversions$JListWrapper$ extends java.lang.Object implements scala.ScalaObject
  SourceFile: "JavaConversions.scala"
  Scala: length = 0x
   
  InnerClass: 
   public #46= #23 of #45; //JListWrapper=class scala/collection/JavaConversions$JListWrapper of class scala/collection/JavaConversions
   public final #49= #48 of #23; //$anonfun$insertAll$1=class scala/collection/JavaConversions$JListWrapper$$anonfun$insertAll$1 of class scala/collection/JavaConversions$JListWrapper
  minor version: 0
  major version: 49
  Constant pool:
const #1 = Asciz	SourceFile;
const #2 = Asciz	JavaConversions.scala;
const #3 = Asciz	Scala;
const #4 = Asciz	MODULE$;
const #5 = Asciz	Lscala/collection/JavaConversions$JListWrapper$;;
const #6 = Asciz	<clinit>;
const #7 = Asciz	()V;
const #8 = Asciz	Code;
const #9 = Asciz	scala/collection/JavaConversions$JListWrapper$;
const #10 = class	#9;	//  scala/collection/JavaConversions$JListWrapper$
const #11 = Asciz	<init>;
const #12 = NameAndType	#11:#7;//  "<init>":()V
const #13 = Method	#10.#12;	//  scala/collection/JavaConversions$JListWrapper$."<init>":()V
const #14 = Asciz	LineNumberTable;
const #15 = Asciz	java/lang/Object;
const #16 = class	#15;	//  java/lang/Object
const #17 = Method	#16.#12;	//  java/lang/Object."<init>":()V
const #18 = NameAndType	#4:#5;//  MODULE$:Lscala/collection/JavaConversions$JListWrapper$;
const #19 = Field	#10.#18;	//  scala/collection/JavaConversions$JListWrapper$.MODULE$:Lscala/collection/JavaConversions$JListWrapper$;
const #20 = Asciz	apply;
const #21 = Asciz	(Ljava/util/List;)Lscala/collection/JavaConversions$JListWrapper;;
const #22 = Asciz	scala/collection/JavaConversions$JListWrapper;
const #23 = class	#22;	//  scala/collection/JavaConversions$JListWrapper
const #24 = Asciz	(Ljava/util/List;)V;
const #25 = NameAndType	#11:#24;//  "<init>":(Ljava/util/List;)V
const #26 = Method	#23.#25;	//  scala/collection/JavaConversions$JListWrapper."<init>":(Ljava/util/List;)V
const #27 = Asciz	this;
const #28 = Asciz	underlying;
const #29 = Asciz	Ljava/util/List;;
const #30 = Asciz	LocalVariableTable;
const #31 = Asciz	unapply;
const #32 = Asciz	(Lscala/collection/JavaConversions$JListWrapper;)Lscala/Some;;
const #33 = Asciz	scala/Some;
const #34 = class	#33;	//  scala/Some
const #35 = Asciz	()Ljava/util/List;;
const #36 = NameAndType	#28:#35;//  underlying:()Ljava/util/List;
const #37 = Method	#23.#36;	//  scala/collection/JavaConversions$JListWrapper.underlying:()Ljava/util/List;
const #38 = Asciz	(Ljava/lang/Object;)V;
const #39 = NameAndType	#11:#38;//  "<init>":(Ljava/lang/Object;)V
const #40 = Method	#34.#39;	//  scala/Some."<init>":(Ljava/lang/Object;)V
const #41 = Asciz	x$0;
const #42 = Asciz	Lscala/collection/JavaConversions$JListWrapper;;
const #43 = Asciz	InnerClasses;
const #44 = Asciz	scala/collection/JavaConversions;
const #45 = class	#44;	//  scala/collection/JavaConversions
const #46 = Asciz	JListWrapper;
const #47 = Asciz	scala/collection/JavaConversions$JListWrapper$$anonfun$insertAll$1;
const #48 = class	#47;	//  scala/collection/JavaConversions$JListWrapper$$anonfun$insertAll$1
const #49 = Asciz	$anonfun$insertAll$1;
const #50 = Asciz	scala/ScalaObject;
const #51 = class	#50;	//  scala/ScalaObject

{
public static final scala.collection.JavaConversions$JListWrapper$ MODULE$;

public static {};
  Code:
   Stack=1, Locals=0, Args_size=0
   0:	new	#10; //class scala/collection/JavaConversions$JListWrapper$
   3:	invokespecial	#13; //Method "<init>":()V
   6:	return

public scala.collection.JavaConversions$JListWrapper$();
  Code:
   Stack=1, Locals=1, Args_size=1
   0:	aload_0
   1:	invokespecial	#17; //Method java/lang/Object."<init>":()V
   4:	aload_0
   5:	putstatic	#19; //Field MODULE$:Lscala/collection/JavaConversions$JListWrapper$;
   8:	return
  LineNumberTable: 
   line 356: 0


public scala.collection.JavaConversions$JListWrapper apply(java.util.List);
  Code:
   Stack=3, Locals=2, Args_size=2
   0:	new	#23; //class scala/collection/JavaConversions$JListWrapper
   3:	dup
   4:	aload_1
   5:	invokespecial	#26; //Method scala/collection/JavaConversions$JListWrapper."<init>":(Ljava/util/List;)V
   8:	areturn
  LineNumberTable: 
   line 356: 0

  LocalVariableTable: 
   Start  Length  Slot  Name   Signature
   0      9      0    this       Lscala/collection/JavaConversions$JListWrapper$;
   0      9      1    underlying       Ljava/util/List;


public scala.Some unapply(scala.collection.JavaConversions$JListWrapper);
  Code:
   Stack=3, Locals=2, Args_size=2
   0:	new	#34; //class scala/Some
   3:	dup
   4:	aload_1
   5:	invokevirtual	#37; //Method scala/collection/JavaConversions$JListWrapper.underlying:()Ljava/util/List;
   8:	invokespecial	#40; //Method scala/Some."<init>":(Ljava/lang/Object;)V
   11:	areturn
  LineNumberTable: 
   line 356: 0

  LocalVariableTable: 
   Start  Length  Slot  Name   Signature
   0      12      0    this       Lscala/collection/JavaConversions$JListWrapper$;
   0      12      1    x$0       Lscala/collection/JavaConversions$JListWrapper;


}

