Compiled from "JavaConversions.scala"
public final class scala.collection.JavaConversions$MutableMapWrapper$ extends java.lang.Object implements scala.ScalaObject
  SourceFile: "JavaConversions.scala"
  Scala: length = 0x
   
  InnerClass: 
   public #48= #23 of #47; //MutableMapWrapper=class scala/collection/JavaConversions$MutableMapWrapper of class scala/collection/JavaConversions
   public final #51= #50 of #23; //$anon$1=class scala/collection/JavaConversions$MutableMapWrapper$$anon$1 of class scala/collection/JavaConversions$MutableMapWrapper
  minor version: 0
  major version: 49
  Constant pool:
const #1 = Asciz	SourceFile;
const #2 = Asciz	JavaConversions.scala;
const #3 = Asciz	Scala;
const #4 = Asciz	MODULE$;
const #5 = Asciz	Lscala/collection/JavaConversions$MutableMapWrapper$;;
const #6 = Asciz	<clinit>;
const #7 = Asciz	()V;
const #8 = Asciz	Code;
const #9 = Asciz	scala/collection/JavaConversions$MutableMapWrapper$;
const #10 = class	#9;	//  scala/collection/JavaConversions$MutableMapWrapper$
const #11 = Asciz	<init>;
const #12 = NameAndType	#11:#7;//  "<init>":()V
const #13 = Method	#10.#12;	//  scala/collection/JavaConversions$MutableMapWrapper$."<init>":()V
const #14 = Asciz	LineNumberTable;
const #15 = Asciz	java/lang/Object;
const #16 = class	#15;	//  java/lang/Object
const #17 = Method	#16.#12;	//  java/lang/Object."<init>":()V
const #18 = NameAndType	#4:#5;//  MODULE$:Lscala/collection/JavaConversions$MutableMapWrapper$;
const #19 = Field	#10.#18;	//  scala/collection/JavaConversions$MutableMapWrapper$.MODULE$:Lscala/collection/JavaConversions$MutableMapWrapper$;
const #20 = Asciz	apply;
const #21 = Asciz	(Lscala/collection/mutable/Map;Lscala/reflect/Manifest;)Lscala/collection/JavaConversions$MutableMapWrapper;;
const #22 = Asciz	scala/collection/JavaConversions$MutableMapWrapper;
const #23 = class	#22;	//  scala/collection/JavaConversions$MutableMapWrapper
const #24 = Asciz	(Lscala/collection/mutable/Map;Lscala/reflect/Manifest;)V;
const #25 = NameAndType	#11:#24;//  "<init>":(Lscala/collection/mutable/Map;Lscala/reflect/Manifest;)V
const #26 = Method	#23.#25;	//  scala/collection/JavaConversions$MutableMapWrapper."<init>":(Lscala/collection/mutable/Map;Lscala/reflect/Manifest;)V
const #27 = Asciz	this;
const #28 = Asciz	underlying;
const #29 = Asciz	Lscala/collection/mutable/Map;;
const #30 = Asciz	m;
const #31 = Asciz	Lscala/reflect/Manifest;;
const #32 = Asciz	LocalVariableTable;
const #33 = Asciz	unapply;
const #34 = Asciz	(Lscala/collection/JavaConversions$MutableMapWrapper;)Lscala/Some;;
const #35 = Asciz	scala/Some;
const #36 = class	#35;	//  scala/Some
const #37 = Asciz	()Lscala/collection/mutable/Map;;
const #38 = NameAndType	#28:#37;//  underlying:()Lscala/collection/mutable/Map;
const #39 = Method	#23.#38;	//  scala/collection/JavaConversions$MutableMapWrapper.underlying:()Lscala/collection/mutable/Map;
const #40 = Asciz	(Ljava/lang/Object;)V;
const #41 = NameAndType	#11:#40;//  "<init>":(Ljava/lang/Object;)V
const #42 = Method	#36.#41;	//  scala/Some."<init>":(Ljava/lang/Object;)V
const #43 = Asciz	x$0;
const #44 = Asciz	Lscala/collection/JavaConversions$MutableMapWrapper;;
const #45 = Asciz	InnerClasses;
const #46 = Asciz	scala/collection/JavaConversions;
const #47 = class	#46;	//  scala/collection/JavaConversions
const #48 = Asciz	MutableMapWrapper;
const #49 = Asciz	scala/collection/JavaConversions$MutableMapWrapper$$anon$1;
const #50 = class	#49;	//  scala/collection/JavaConversions$MutableMapWrapper$$anon$1
const #51 = Asciz	$anon$1;
const #52 = Asciz	scala/ScalaObject;
const #53 = class	#52;	//  scala/ScalaObject

{
public static final scala.collection.JavaConversions$MutableMapWrapper$ MODULE$;

public static {};
  Code:
   Stack=1, Locals=0, Args_size=0
   0:	new	#10; //class scala/collection/JavaConversions$MutableMapWrapper$
   3:	invokespecial	#13; //Method "<init>":()V
   6:	return

public scala.collection.JavaConversions$MutableMapWrapper$();
  Code:
   Stack=1, Locals=1, Args_size=1
   0:	aload_0
   1:	invokespecial	#17; //Method java/lang/Object."<init>":()V
   4:	aload_0
   5:	putstatic	#19; //Field MODULE$:Lscala/collection/JavaConversions$MutableMapWrapper$;
   8:	return
  LineNumberTable: 
   line 411: 0


public scala.collection.JavaConversions$MutableMapWrapper apply(scala.collection.mutable.Map, scala.reflect.Manifest);
  Code:
   Stack=4, Locals=3, Args_size=3
   0:	new	#23; //class scala/collection/JavaConversions$MutableMapWrapper
   3:	dup
   4:	aload_1
   5:	aload_2
   6:	invokespecial	#26; //Method scala/collection/JavaConversions$MutableMapWrapper."<init>":(Lscala/collection/mutable/Map;Lscala/reflect/Manifest;)V
   9:	areturn
  LineNumberTable: 
   line 411: 0

  LocalVariableTable: 
   Start  Length  Slot  Name   Signature
   0      10      0    this       Lscala/collection/JavaConversions$MutableMapWrapper$;
   0      10      1    underlying       Lscala/collection/mutable/Map;
   0      10      2    m       Lscala/reflect/Manifest;


public scala.Some unapply(scala.collection.JavaConversions$MutableMapWrapper);
  Code:
   Stack=3, Locals=2, Args_size=2
   0:	new	#36; //class scala/Some
   3:	dup
   4:	aload_1
   5:	invokevirtual	#39; //Method scala/collection/JavaConversions$MutableMapWrapper.underlying:()Lscala/collection/mutable/Map;
   8:	invokespecial	#42; //Method scala/Some."<init>":(Ljava/lang/Object;)V
   11:	areturn
  LineNumberTable: 
   line 411: 0

  LocalVariableTable: 
   Start  Length  Slot  Name   Signature
   0      12      0    this       Lscala/collection/JavaConversions$MutableMapWrapper$;
   0      12      1    x$0       Lscala/collection/JavaConversions$MutableMapWrapper;


}

