Compiled from "JavaConversions.scala"
public final class scala.collection.JavaConversions extends java.lang.Object
  SourceFile: "JavaConversions.scala"
  ScalaSig: length = 0x2A02
   05 00 FFFFFF8A 06 07 05 01 02 FFFFFF88 02 07 01 0F 4A 61 76
   61 43 6F 6E 76 65 72 73 69 6F 6E 73 0A 02 03 04
   01 0A 63 6F 6C 6C 65 63 74 69 6F 6E 0A 01 05 01
   05 73 63 61 6C 61 03 00 10 02 08 09 0D 01 02 06
   08 0A 02 FFFFFF84 FFFFFF80 FFFFFF80 FFFFFF88 02 0B 02 0F 4A 61 76 61 43
   6F 6E 76 65 72 73 69 6F 6E 73 13 03 09 0C 14 10
   02 0D 12 0D 01 0E 0A 02 0F 10 01 04 6C 61 6E 67
   0A 01 11 01 04 6A 61 76 61 09 02 13 0E 02 06 4F
   62 6A 65 63 74 10 02 15 16 0D 01 04 09 02 17 04
   02 0B 53 63 61 6C 61 4F 62 6A 65 63 74 08 05 19
   09 FFFFFF84 00 1A 01 06 3C 69 6E 69 74 3E 14 01 07 08
   05 1C 09 FFFFFF84 01 1D 01 0A 61 73 49 74 65 72 61 74
   6F 72 15 02 1E 27 14 02 1F 30 10 03 20 23 25 0D
   01 21 0A 02 22 10 01 04 75 74 69 6C 09 02 24 21
   02 08 49 74 65 72 61 74 6F 72 10 02 26 27 0C 00
   04 08 28 1B FFFFFF84 FFFFFF80 FFFFFF80 FFFFFFC2 00 29 02 01 41 11 02 2A
   2D 10 02 15 2B 09 02 2C 04 02 07 4E 6F 74 68 69
   6E 67 10 02 15 2E 09 02 2F 04 02 03 41 6E 79 08
   05 31 1B FFFFFFC0 00 32 01 01 69 10 03 08 33 25 09 02
   24 02 08 05 35 09 FFFFFF84 01 36 01 0D 61 73 45 6E 75
   6D 65 72 61 74 69 6F 6E 15 02 37 3C 14 02 38 3D
   10 03 20 39 3B 09 02 3A 21 02 0B 45 6E 75 6D 65
   72 61 74 69 6F 6E 10 02 26 3C 04 08 28 34 FFFFFF84 FFFFFF80
   FFFFFF80 FFFFFFC2 00 29 08 05 31 34 FFFFFFC0 00 3E 10 03 08 33 3B
   08 05 40 09 FFFFFF84 01 41 01 0A 61 73 49 74 65 72 61
   62 6C 65 15 02 42 47 14 02 43 48 10 03 0D 44 46
   09 02 45 0E 02 08 49 74 65 72 61 62 6C 65 10 02
   26 47 04 08 28 3F FFFFFF84 FFFFFF80 FFFFFF80 FFFFFFC2 00 29 08 05 31 3F
   FFFFFFC0 00 49 10 03 08 4A 46 09 02 45 02 08 05 4C 09
   FFFFFF84 01 4D 01 0C 61 73 43 6F 6C 6C 65 63 74 69 6F
   6E 15 02 4E 53 14 02 4F 54 10 03 20 50 52 09 02
   51 21 02 0A 43 6F 6C 6C 65 63 74 69 6F 6E 10 02
   26 53 04 08 28 4B FFFFFF84 FFFFFF80 FFFFFF80 FFFFFFC2 00 29 08 05 31 4B
   FFFFFFC0 00 55 10 03 08 4A 52 08 05 57 09 FFFFFF84 01 58 01
   06 61 73 4C 69 73 74 15 02 59 5E 14 02 5A 5F 10
   03 20 5B 5D 09 02 5C 21 02 04 4C 69 73 74 10 02
   26 5E 04 08 28 56 FFFFFF84 FFFFFF80 FFFFFF80 FFFFFFC2 00 29 08 05 60 56
   FFFFFFC0 00 61 01 01 62 10 03 62 65 5D 0D 01 63 0A 02
   64 02 01 07 6D 75 74 61 62 6C 65 09 02 66 63 02
   06 42 75 66 66 65 72 08 05 68 09 FFFFFF84 01 69 01 05
   61 73 53 65 74 15 02 6A 70 14 02 6B 79 16 02 6C
   71 10 03 20 6D 6F 09 02 6E 21 02 03 53 65 74 10
   02 26 70 04 08 28 67 FFFFFF84 FFFFFF80 FFFFFF80 FFFFFFC2 00 29 08 05 72
   67 FFFFFFC0 01 73 01 01 6D 10 03 74 77 6F 0D 01 75 0A
   02 76 04 01 07 72 65 66 6C 65 63 74 09 02 78 75
   02 08 4D 61 6E 69 66 65 73 74 08 05 7A 67 FFFFFFC0 00
   7B 01 01 73 10 03 62 7C 6F 09 02 6E 63 08 05 7E
   09 FFFFFF84 01 7F 01 05 61 73 4D 61 70 15 06 FFFFFF81 00 FFFFFF81
   06 FFFFFF81 08 14 04 FFFFFF81 01 FFFFFF81 0D 16 04 FFFFFF81 02 FFFFFF81 0A 10
   07 20 FFFFFF81 03 FFFFFF81 05 FFFFFF81 07 09 03 FFFFFF81 04 21 02 03 4D
   61 70 10 03 26 FFFFFF81 06 04 08 28 7D FFFFFF84 FFFFFF80 FFFFFF80 FFFFFFC2 00
   29 10 03 26 FFFFFF81 08 04 09 FFFFFF81 09 7D FFFFFF84 FFFFFF80 FFFFFF80 FFFFFFC2 00
   29 02 01 42 08 07 FFFFFF81 0B 7D FFFFFFC0 01 FFFFFF81 0C 01 02 6D
   61 10 04 74 77 FFFFFF81 05 08 06 72 7D FFFFFFC0 00 FFFFFF81 0E 10
   07 62 FFFFFF81 0F FFFFFF81 05 FFFFFF81 07 09 03 FFFFFF81 04 63 08 06 1C
   09 FFFFFF84 01 FFFFFF81 11 15 04 FFFFFF81 12 FFFFFF81 15 14 04 FFFFFF81 13 FFFFFF81
   16 10 04 08 33 FFFFFF81 14 10 03 26 FFFFFF81 15 04 09 28 FFFFFF81
   10 FFFFFF84 FFFFFF80 FFFFFF80 FFFFFFC2 00 29 08 07 31 FFFFFF81 10 FFFFFFC0 00 FFFFFF81 17
   10 04 20 23 FFFFFF81 14 08 06 1C 09 FFFFFF84 01 FFFFFF81 19 15 04
   FFFFFF81 1A FFFFFF81 1D 14 04 FFFFFF81 1B FFFFFF81 1E 10 04 08 33 FFFFFF81 1C
   10 03 26 FFFFFF81 1D 04 09 28 FFFFFF81 18 FFFFFF84 FFFFFF80 FFFFFF80 FFFFFFC2 00 29
   08 07 31 FFFFFF81 18 FFFFFFC0 00 FFFFFF81 1F 10 04 20 39 FFFFFF81 1C 08
   06 40 09 FFFFFF84 01 FFFFFF81 21 15 04 FFFFFF81 22 FFFFFF81 25 14 04 FFFFFF81
   23 FFFFFF81 26 10 04 08 4A FFFFFF81 24 10 03 26 FFFFFF81 25 04 09
   28 FFFFFF81 20 FFFFFF84 FFFFFF80 FFFFFF80 FFFFFFC2 00 29 08 07 31 FFFFFF81 20 FFFFFFC0 00
   FFFFFF81 27 10 04 0D 44 FFFFFF81 24 08 06 40 09 FFFFFF84 01 FFFFFF81 29
   15 04 FFFFFF81 2A FFFFFF81 2D 14 04 FFFFFF81 2B FFFFFF81 2E 10 04 08 4A
   FFFFFF81 2C 10 03 26 FFFFFF81 2D 04 09 28 FFFFFF81 28 FFFFFF84 FFFFFF80 FFFFFF80 FFFFFFC2
   00 29 08 07 31 FFFFFF81 28 FFFFFFC0 00 FFFFFF81 2F 10 04 20 50 FFFFFF81
   2C 08 07 FFFFFF81 31 09 FFFFFF84 01 FFFFFF81 32 01 08 61 73 42 75
   66 66 65 72 15 04 FFFFFF81 33 FFFFFF81 36 14 04 FFFFFF81 34 FFFFFF81 37
   10 04 62 65 FFFFFF81 35 10 03 26 FFFFFF81 36 04 09 28 FFFFFF81 30
   FFFFFF84 FFFFFF80 FFFFFF80 FFFFFFC2 00 29 08 08 FFFFFF81 38 FFFFFF81 30 FFFFFFC0 00 FFFFFF81 39
   01 01 6C 10 04 20 5B FFFFFF81 35 08 06 68 09 FFFFFF84 01 FFFFFF81
   3B 15 04 FFFFFF81 3C FFFFFF81 3F 14 04 FFFFFF81 3D FFFFFF81 40 10 04 62
   7C FFFFFF81 3E 10 03 26 FFFFFF81 3F 04 09 28 FFFFFF81 3A FFFFFF84 FFFFFF80 FFFFFF80
   FFFFFFC2 00 29 08 07 7A FFFFFF81 3A FFFFFFC0 00 FFFFFF81 41 10 04 20 6D
   FFFFFF81 3E 08 06 7E 09 FFFFFF84 01 FFFFFF81 43 15 06 FFFFFF81 44 FFFFFF81 47
   FFFFFF81 49 14 04 FFFFFF81 45 FFFFFF81 4A 10 07 62 FFFFFF81 0F FFFFFF81 46 FFFFFF81
   48 10 03 26 FFFFFF81 47 04 09 28 FFFFFF81 42 FFFFFF84 FFFFFF80 FFFFFF80 FFFFFFC2 00
   29 10 03 26 FFFFFF81 49 04 0A FFFFFF81 09 FFFFFF81 42 FFFFFF84 FFFFFF80 FFFFFF80 FFFFFFC2
   00 29 08 07 72 FFFFFF81 42 FFFFFFC0 00 FFFFFF81 4B 10 07 20 FFFFFF81 03
   FFFFFF81 46 FFFFFF81 48 06 06 FFFFFF81 4D 09 40 FFFFFF81 4E 02 0F 49 74
   65 72 61 74 6F 72 57 72 61 70 70 65 72 15 04 FFFFFF81
   4F FFFFFF81 52 13 0A FFFFFF81 4C 0C FFFFFF81 50 FFFFFF81 53 14 FFFFFF81 54 10
   04 20 23 FFFFFF81 51 10 03 26 FFFFFF81 52 04 09 28 FFFFFF81 4C FFFFFF84
   FFFFFF80 FFFFFF80 FFFFFFC2 00 29 10 04 20 39 FFFFFF81 51 10 03 15 FFFFFF81 55
   09 03 FFFFFF81 56 04 02 07 50 72 6F 64 75 63 74 08 0B
   FFFFFF81 58 FFFFFF81 4C FFFFFF82 FFFFFFCA FFFFFF80 FFFFFF84 00 FFFFFF81 59 01 0A 75 6E 64
   65 72 6C 79 69 6E 67 15 02 FFFFFF81 5A 10 04 08 33 FFFFFF81
   51 08 0B FFFFFF81 5C FFFFFF81 4C FFFFFF82 FFFFFF88 FFFFFFA0 FFFFFF80 04 FFFFFF81 5A 01 0B
   75 6E 64 65 72 6C 79 69 6E 67 20 08 07 19 FFFFFF81 4C
   FFFFFF84 00 FFFFFF81 5E 14 04 FFFFFF81 5F FFFFFF81 61 10 06 FFFFFF81 60 FFFFFF81 4C
   FFFFFF81 51 0D 01 09 08 08 FFFFFF81 58 FFFFFF81 5D FFFFFFC0 00 FFFFFF81 5A 08
   08 FFFFFF81 63 FFFFFF81 4C FFFFFF84 00 FFFFFF81 64 01 07 68 61 73 4E 65
   78 74 14 02 FFFFFF81 65 10 03 15 FFFFFF81 66 09 03 FFFFFF81 67 04
   02 07 42 6F 6F 6C 65 61 6E 08 08 FFFFFF81 69 FFFFFF81 4C FFFFFF84
   00 FFFFFF81 6A 01 04 6E 65 78 74 14 02 FFFFFF81 51 08 08 FFFFFF81
   6C FFFFFF81 4C FFFFFF84 00 FFFFFF81 64 01 0F 68 61 73 4D 6F 72 65
   45 6C 65 6D 65 6E 74 73 08 08 FFFFFF81 6E FFFFFF81 4C FFFFFF84 00
   FFFFFF81 6A 01 0B 6E 65 78 74 45 6C 65 6D 65 6E 74 08
   08 FFFFFF81 70 FFFFFF81 4C FFFFFF84 00 FFFFFF81 71 01 06 72 65 6D 6F 76
   65 14 01 2A 08 0A FFFFFF81 73 FFFFFF81 4C FFFFFF81 FFFFFF80 FFFFFF84 00 FFFFFF81 74
   01 04 63 6F 70 79 15 04 FFFFFF81 75 FFFFFF81 78 14 04 FFFFFF81 76
   FFFFFF81 79 10 06 FFFFFF81 60 FFFFFF81 4C FFFFFF81 77 10 03 26 FFFFFF81 78 04
   09 28 FFFFFF81 72 FFFFFF84 FFFFFF80 FFFFFF80 FFFFFFC2 00 29 08 0C FFFFFF81 7B FFFFFF81 58
   FFFFFF81 72 FFFFFF90 FFFFFF80 FFFFFFC0 00 FFFFFF81 7A 10 04 08 33 FFFFFF81 77 08 0A
   FFFFFF81 7C FFFFFF81 4C FFFFFF91 FFFFFF80 FFFFFF84 00 FFFFFF81 7D 01 0E 63 6F 70 79
   24 64 65 66 61 75 6C 74 24 31 15 04 FFFFFF81 5A FFFFFF81 7E
   04 09 28 FFFFFF81 7B FFFFFF84 FFFFFF80 FFFFFF80 FFFFFFC2 00 29 08 0B FFFFFF82 00 FFFFFF81
   4C FFFFFF84 FFFFFF80 FFFFFF80 FFFFFF84 20 FFFFFF82 01 01 08 68 61 73 68 43 6F
   64 65 14 02 FFFFFF82 02 10 03 15 FFFFFF82 03 09 03 FFFFFF82 04 04
   02 03 49 6E 74 08 0B FFFFFF82 06 FFFFFF81 4C FFFFFF84 FFFFFF80 FFFFFF80 FFFFFF84 20
   FFFFFF82 07 01 08 74 6F 53 74 72 69 6E 67 14 02 FFFFFF82 08
   10 04 FFFFFF82 09 FFFFFF82 0C 0E 03 15 FFFFFF82 0A 09 03 FFFFFF82 0B 04
   01 06 50 72 65 64 65 66 09 04 FFFFFF82 0D FFFFFF82 0E 02 06
   53 74 72 69 6E 67 0A 03 FFFFFF82 0B 04 08 0B FFFFFF82 10 FFFFFF81
   4C FFFFFF84 FFFFFF80 FFFFFF80 FFFFFF84 20 FFFFFF82 11 01 06 65 71 75 61 6C 73
   14 04 FFFFFF81 65 FFFFFF82 12 08 09 FFFFFF82 13 FFFFFF82 0F FFFFFF81 FFFFFF80 FFFFFFC0 00
   2D 01 03 78 24 31 08 0B FFFFFF82 15 FFFFFF81 4C FFFFFF84 FFFFFF80 FFFFFF80 FFFFFF84
   20 FFFFFF82 16 01 0D 70 72 6F 64 75 63 74 50 72 65 66
   69 78 15 02 FFFFFF82 17 10 03 0D FFFFFF82 18 09 03 FFFFFF82 0D 0E
   08 0B FFFFFF82 1A FFFFFF81 4C FFFFFF84 FFFFFF80 FFFFFF80 FFFFFF84 20 FFFFFF82 1B 01 0C 70
   72 6F 64 75 63 74 41 72 69 74 79 15 02 FFFFFF82 02 08
   0B FFFFFF82 1D FFFFFF81 4C FFFFFF84 FFFFFF80 FFFFFF80 FFFFFF84 20 FFFFFF82 1E 01 0E 70 72
   6F 64 75 63 74 45 6C 65 6D 65 6E 74 14 03 2D FFFFFF82
   1F 08 0A FFFFFF82 13 FFFFFF82 1C FFFFFF81 FFFFFF80 FFFFFFC0 00 FFFFFF82 02 08 0B FFFFFF82
   21 FFFFFF81 4C FFFFFF84 FFFFFF80 FFFFFF80 FFFFFF84 20 FFFFFF82 22 01 08 63 61 6E 45
   71 75 61 6C 14 04 FFFFFF81 65 FFFFFF82 23 08 09 FFFFFF82 13 FFFFFF82 20
   FFFFFF81 FFFFFF80 FFFFFFC0 00 2D 28 04 FFFFFF81 4C FFFFFF82 25 10 03 15 FFFFFF82 26
   09 03 FFFFFF82 27 04 02 0C 73 65 72 69 61 6C 69 7A 61
   62 6C 65 07 09 FFFFFF82 29 09 FFFFFF81 FFFFFF80 FFFFFF88 02 FFFFFF82 2A 01 0F
   49 74 65 72 61 74 6F 72 57 72 61 70 70 65 72 10
   04 FFFFFF81 60 FFFFFF82 2B 06 0A FFFFFF81 4D 09 FFFFFF84 FFFFFF81 FFFFFF80 FFFFFF88 02 FFFFFF82
   2C 13 04 FFFFFF82 2B 0C 14 08 07 19 FFFFFF82 2B FFFFFF84 00 FFFFFF82 2E
   14 02 FFFFFF82 2A 08 0A FFFFFF82 30 FFFFFF82 2B FFFFFF81 FFFFFF80 FFFFFF84 40 FFFFFF82 31
   01 05 61 70 70 6C 79 15 04 FFFFFF82 32 FFFFFF82 35 14 04 FFFFFF82
   33 FFFFFF82 36 10 06 FFFFFF81 60 FFFFFF81 4C FFFFFF82 34 10 03 26 FFFFFF82 35
   04 09 28 FFFFFF82 2F FFFFFF84 FFFFFF80 FFFFFF80 FFFFFFC2 00 29 08 08 FFFFFF81 58 FFFFFF82
   2F FFFFFFC0 00 FFFFFF82 37 10 04 08 33 FFFFFF82 34 08 0A FFFFFF82 39 FFFFFF82
   2B FFFFFF81 FFFFFF80 FFFFFF84 40 FFFFFF82 3A 01 07 75 6E 61 70 70 6C 79
   15 04 FFFFFF82 3B FFFFFF82 41 14 04 FFFFFF82 3C FFFFFF82 42 10 05 15 FFFFFF82
   3D FFFFFF82 3F 09 03 FFFFFF82 3E 04 02 04 53 6F 6D 65 10 04
   08 33 FFFFFF82 40 10 03 26 FFFFFF82 41 04 09 28 FFFFFF82 38 FFFFFF84 FFFFFF80
   FFFFFF80 FFFFFFC2 00 29 08 08 FFFFFF82 43 FFFFFF82 38 FFFFFFC0 00 FFFFFF82 44 01 03
   78 24 30 10 06 FFFFFF81 60 FFFFFF81 4C FFFFFF82 40 06 06 FFFFFF82 46 09
   40 FFFFFF82 47 02 10 4A 49 74 65 72 61 74 6F 72 57 72
   61 70 70 65 72 15 04 FFFFFF82 48 FFFFFF82 4B 13 08 FFFFFF82 45 0C
   FFFFFF82 49 14 FFFFFF81 54 10 04 08 33 FFFFFF82 4A 10 03 26 FFFFFF82 4B
   04 09 28 FFFFFF82 45 FFFFFF84 FFFFFF80 FFFFFF80 FFFFFFC2 00 29 08 0B FFFFFF81 58 FFFFFF82
   45 FFFFFF82 FFFFFFCA FFFFFF80 FFFFFF84 00 FFFFFF82 4D 15 02 FFFFFF82 4E 10 04 20 23
   FFFFFF82 4A 08 0B FFFFFF81 5C FFFFFF82 45 FFFFFF82 FFFFFF88 FFFFFFA0 FFFFFF80 04 FFFFFF82 4E 08
   07 19 FFFFFF82 45 FFFFFF84 00 FFFFFF82 51 14 04 FFFFFF82 52 FFFFFF82 53 10 06
   FFFFFF81 60 FFFFFF82 45 FFFFFF82 4A 08 08 FFFFFF81 58 FFFFFF82 50 FFFFFFC0 00 FFFFFF82 4E
   08 08 FFFFFF81 63 FFFFFF82 45 FFFFFF84 00 FFFFFF82 55 15 02 FFFFFF81 65 08 08
   FFFFFF81 69 FFFFFF82 45 FFFFFF84 00 FFFFFF82 57 14 02 FFFFFF82 4A 08 0A FFFFFF81 73
   FFFFFF82 45 FFFFFF81 FFFFFF80 FFFFFF84 00 FFFFFF82 59 15 04 FFFFFF82 5A FFFFFF82 5D 14 04
   FFFFFF82 5B FFFFFF82 5E 10 06 FFFFFF81 60 FFFFFF82 45 FFFFFF82 5C 10 03 26 FFFFFF82
   5D 04 09 28 FFFFFF82 58 FFFFFF84 FFFFFF80 FFFFFF80 FFFFFFC2 00 29 08 0C FFFFFF82 60
   FFFFFF81 58 FFFFFF82 58 FFFFFF90 FFFFFF80 FFFFFFC0 00 FFFFFF82 5F 10 04 20 23 FFFFFF82 5C
   08 0A FFFFFF81 7C FFFFFF82 45 FFFFFF91 FFFFFF80 FFFFFF84 00 FFFFFF82 61 15 04 FFFFFF82 4E
   FFFFFF82 62 04 09 28 FFFFFF82 60 FFFFFF84 FFFFFF80 FFFFFF80 FFFFFFC2 00 29 08 0B FFFFFF82
   00 FFFFFF82 45 FFFFFF84 FFFFFF80 FFFFFF80 FFFFFF84 20 FFFFFF82 01 08 0B FFFFFF82 10 FFFFFF82 45
   FFFFFF84 FFFFFF80 FFFFFF80 FFFFFF84 20 FFFFFF82 65 14 04 FFFFFF81 65 FFFFFF82 66 08 09 FFFFFF82
   13 FFFFFF82 64 FFFFFF81 FFFFFF80 FFFFFFC0 00 2D 08 0B FFFFFF82 15 FFFFFF82 45 FFFFFF84 FFFFFF80
   FFFFFF80 FFFFFF84 20 FFFFFF82 16 08 0B FFFFFF82 1A FFFFFF82 45 FFFFFF84 FFFFFF80 FFFFFF80 FFFFFF84 20
   FFFFFF82 1B 08 0B FFFFFF82 1D FFFFFF82 45 FFFFFF84 FFFFFF80 FFFFFF80 FFFFFF84 20 FFFFFF82 6A 14
   03 2D FFFFFF82 6B 08 0A FFFFFF82 13 FFFFFF82 69 FFFFFF81 FFFFFF80 FFFFFFC0 00 FFFFFF82 02
   08 0B FFFFFF82 21 FFFFFF82 45 FFFFFF84 FFFFFF80 FFFFFF80 FFFFFF84 20 FFFFFF82 6D 14 04 FFFFFF81
   65 FFFFFF82 6E 08 09 FFFFFF82 13 FFFFFF82 6C FFFFFF81 FFFFFF80 FFFFFFC0 00 2D 28 04
   FFFFFF82 45 FFFFFF82 25 07 09 FFFFFF82 71 09 FFFFFF81 FFFFFF80 FFFFFF88 02 FFFFFF82 72 01
   10 4A 49 74 65 72 61 74 6F 72 57 72 61 70 70 65
   72 10 04 FFFFFF81 60 FFFFFF82 73 06 0A FFFFFF82 46 09 FFFFFF84 FFFFFF81 FFFFFF80 FFFFFF88
   02 FFFFFF82 74 13 04 FFFFFF82 73 0C 14 08 07 19 FFFFFF82 73 FFFFFF84 00
   FFFFFF82 76 14 02 FFFFFF82 72 08 0A FFFFFF82 30 FFFFFF82 73 FFFFFF81 FFFFFF80 FFFFFF84 40
   FFFFFF82 78 15 04 FFFFFF82 79 FFFFFF82 7C 14 04 FFFFFF82 7A FFFFFF82 7D 10 06
   FFFFFF81 60 FFFFFF82 45 FFFFFF82 7B 10 03 26 FFFFFF82 7C 04 09 28 FFFFFF82 77
   FFFFFF84 FFFFFF80 FFFFFF80 FFFFFFC2 00 29 08 08 FFFFFF81 58 FFFFFF82 77 FFFFFFC0 00 FFFFFF82 7E
   10 04 20 23 FFFFFF82 7B 08 0A FFFFFF82 39 FFFFFF82 73 FFFFFF81 FFFFFF80 FFFFFF84 40
   FFFFFF83 00 15 04 FFFFFF83 01 FFFFFF83 05 14 04 FFFFFF83 02 FFFFFF83 06 10 05
   15 FFFFFF82 3D FFFFFF83 03 10 04 20 23 FFFFFF83 04 10 03 26 FFFFFF83 05
   04 09 28 FFFFFF82 7F FFFFFF84 FFFFFF80 FFFFFF80 FFFFFFC2 00 29 08 08 FFFFFF82 43 FFFFFF82
   7F FFFFFFC0 00 FFFFFF83 07 10 06 FFFFFF81 60 FFFFFF82 45 FFFFFF83 04 06 06 FFFFFF83
   09 09 40 FFFFFF83 0A 02 13 4A 45 6E 75 6D 65 72 61 74
   69 6F 6E 57 72 61 70 70 65 72 15 04 FFFFFF83 0B FFFFFF83 0E
   13 08 FFFFFF83 08 0C FFFFFF83 0C 14 FFFFFF81 54 10 04 08 33 FFFFFF83 0D
   10 03 26 FFFFFF83 0E 04 09 28 FFFFFF83 08 FFFFFF84 FFFFFF80 FFFFFF80 FFFFFFC2 00 29
   08 0B FFFFFF81 58 FFFFFF83 08 FFFFFF82 FFFFFFCA FFFFFF80 FFFFFF84 00 FFFFFF83 10 15 02 FFFFFF83
   11 10 04 20 39 FFFFFF83 0D 08 0B FFFFFF81 5C FFFFFF83 08 FFFFFF82 FFFFFF88 FFFFFFA0
   FFFFFF80 04 FFFFFF83 11 08 07 19 FFFFFF83 08 FFFFFF84 00 FFFFFF83 14 14 04 FFFFFF83
   15 FFFFFF83 16 10 06 FFFFFF81 60 FFFFFF83 08 FFFFFF83 0D 08 08 FFFFFF81 58 FFFFFF83
   13 FFFFFFC0 00 FFFFFF83 11 08 08 FFFFFF81 63 FFFFFF83 08 FFFFFF84 00 FFFFFF82 55 08
   08 FFFFFF81 69 FFFFFF83 08 FFFFFF84 00 FFFFFF83 19 14 02 FFFFFF83 0D 08 0A FFFFFF81
   73 FFFFFF83 08 FFFFFF81 FFFFFF80 FFFFFF84 00 FFFFFF83 1B 15 04 FFFFFF83 1C FFFFFF83 1F 14
   04 FFFFFF83 1D FFFFFF83 20 10 06 FFFFFF81 60 FFFFFF83 08 FFFFFF83 1E 10 03 26
   FFFFFF83 1F 04 09 28 FFFFFF83 1A FFFFFF84 FFFFFF80 FFFFFF80 FFFFFFC2 00 29 08 0C FFFFFF83
   22 FFFFFF81 58 FFFFFF83 1A FFFFFF90 FFFFFF80 FFFFFFC0 00 FFFFFF83 21 10 04 20 39 FFFFFF83
   1E 08 0A FFFFFF81 7C FFFFFF83 08 FFFFFF91 FFFFFF80 FFFFFF84 00 FFFFFF83 23 15 04 FFFFFF83
   11 FFFFFF83 24 04 09 28 FFFFFF83 22 FFFFFF84 FFFFFF80 FFFFFF80 FFFFFFC2 00 29 08 0B
   FFFFFF82 00 FFFFFF83 08 FFFFFF84 FFFFFF80 FFFFFF80 FFFFFF84 20 FFFFFF82 01 08 0B FFFFFF82 10 FFFFFF83
   08 FFFFFF84 FFFFFF80 FFFFFF80 FFFFFF84 20 FFFFFF83 27 14 04 FFFFFF81 65 FFFFFF83 28 08 09
   FFFFFF82 13 FFFFFF83 26 FFFFFF81 FFFFFF80 FFFFFFC0 00 2D 08 0B FFFFFF82 15 FFFFFF83 08 FFFFFF84
   FFFFFF80 FFFFFF80 FFFFFF84 20 FFFFFF82 16 08 0B FFFFFF82 1A FFFFFF83 08 FFFFFF84 FFFFFF80 FFFFFF80 FFFFFF84
   20 FFFFFF82 1B 08 0B FFFFFF82 1D FFFFFF83 08 FFFFFF84 FFFFFF80 FFFFFF80 FFFFFF84 20 FFFFFF83 2C
   14 03 2D FFFFFF83 2D 08 0A FFFFFF82 13 FFFFFF83 2B FFFFFF81 FFFFFF80 FFFFFFC0 00 FFFFFF82
   02 08 0B FFFFFF82 21 FFFFFF83 08 FFFFFF84 FFFFFF80 FFFFFF80 FFFFFF84 20 FFFFFF83 2F 14 04
   FFFFFF81 65 FFFFFF83 30 08 09 FFFFFF82 13 FFFFFF83 2E FFFFFF81 FFFFFF80 FFFFFFC0 00 2D 28
   04 FFFFFF83 08 FFFFFF82 25 07 09 FFFFFF83 33 09 FFFFFF81 FFFFFF80 FFFFFF88 02 FFFFFF83 34
   01 13 4A 45 6E 75 6D 65 72 61 74 69 6F 6E 57 72
   61 70 70 65 72 10 04 FFFFFF81 60 FFFFFF83 35 06 0A FFFFFF83 09 09
   FFFFFF84 FFFFFF81 FFFFFF80 FFFFFF88 02 FFFFFF83 36 13 04 FFFFFF83 35 0C 14 08 07 19
   FFFFFF83 35 FFFFFF84 00 FFFFFF83 38 14 02 FFFFFF83 34 08 0A FFFFFF82 30 FFFFFF83 35
   FFFFFF81 FFFFFF80 FFFFFF84 40 FFFFFF83 3A 15 04 FFFFFF83 3B FFFFFF83 3E 14 04 FFFFFF83 3C
   FFFFFF83 3F 10 06 FFFFFF81 60 FFFFFF83 08 FFFFFF83 3D 10 03 26 FFFFFF83 3E 04
   09 28 FFFFFF83 39 FFFFFF84 FFFFFF80 FFFFFF80 FFFFFFC2 00 29 08 08 FFFFFF81 58 FFFFFF83 39
   FFFFFFC0 00 FFFFFF83 40 10 04 20 39 FFFFFF83 3D 08 0A FFFFFF82 39 FFFFFF83 35
   FFFFFF81 FFFFFF80 FFFFFF84 40 FFFFFF83 42 15 04 FFFFFF83 43 FFFFFF83 47 14 04 FFFFFF83 44
   FFFFFF83 48 10 05 15 FFFFFF82 3D FFFFFF83 45 10 04 20 39 FFFFFF83 46 10
   03 26 FFFFFF83 47 04 09 28 FFFFFF83 41 FFFFFF84 FFFFFF80 FFFFFF80 FFFFFFC2 00 29 08
   08 FFFFFF82 43 FFFFFF83 41 FFFFFFC0 00 FFFFFF83 49 10 06 FFFFFF81 60 FFFFFF83 08 FFFFFF83
   46 06 06 FFFFFF83 4B 09 40 FFFFFF83 4C 02 0F 49 74 65 72 61
   62 6C 65 57 72 61 70 70 65 72 15 04 FFFFFF83 4D FFFFFF83 52
   13 07 FFFFFF83 4A FFFFFF83 4E 14 FFFFFF81 54 10 05 20 FFFFFF83 4F FFFFFF83 51
   09 03 FFFFFF83 50 21 02 12 41 62 73 74 72 61 63 74 43
   6F 6C 6C 65 63 74 69 6F 6E 10 03 26 FFFFFF83 52 04 09
   28 FFFFFF83 4A FFFFFF84 FFFFFF80 FFFFFF80 FFFFFFC2 00 29 08 0B FFFFFF81 58 FFFFFF83 4A FFFFFF82
   FFFFFFCA FFFFFF80 FFFFFF84 00 FFFFFF83 54 15 02 FFFFFF83 55 10 04 08 4A FFFFFF83 51
   08 0B FFFFFF81 5C FFFFFF83 4A FFFFFF82 FFFFFF88 FFFFFFA0 FFFFFF80 04 FFFFFF83 55 08 07 19
   FFFFFF83 4A FFFFFF84 00 FFFFFF83 58 14 04 FFFFFF83 59 FFFFFF83 5A 10 06 FFFFFF81 60
   FFFFFF83 4A FFFFFF83 51 08 08 FFFFFF81 58 FFFFFF83 57 FFFFFFC0 00 FFFFFF83 55 08 08
   FFFFFF83 5C FFFFFF83 4A FFFFFF84 00 FFFFFF83 5D 01 08 69 74 65 72 61 74
   6F 72 14 02 FFFFFF83 5E 10 04 20 23 FFFFFF83 51 08 08 FFFFFF83 60
   FFFFFF83 4A FFFFFF84 00 FFFFFF82 01 01 04 73 69 7A 65 08 08 FFFFFF83 62
   FFFFFF83 4A FFFFFF84 20 FFFFFF81 64 01 07 69 73 45 6D 70 74 79 08
   0A FFFFFF81 73 FFFFFF83 4A FFFFFF81 FFFFFF80 FFFFFF84 00 FFFFFF83 64 15 04 FFFFFF83 65 FFFFFF83
   68 14 04 FFFFFF83 66 FFFFFF83 69 10 06 FFFFFF81 60 FFFFFF83 4A FFFFFF83 67 10
   03 26 FFFFFF83 68 04 09 28 FFFFFF83 63 FFFFFF84 FFFFFF80 FFFFFF80 FFFFFFC2 00 29 08
   0C FFFFFF83 6B FFFFFF81 58 FFFFFF83 63 FFFFFF90 FFFFFF80 FFFFFFC0 00 FFFFFF83 6A 10 04 08
   4A FFFFFF83 67 08 0A FFFFFF81 7C FFFFFF83 4A FFFFFF91 FFFFFF80 FFFFFF84 00 FFFFFF83 6C 15
   04 FFFFFF83 55 FFFFFF83 6D 04 09 28 FFFFFF83 6B FFFFFF84 FFFFFF80 FFFFFF80 FFFFFFC2 00 29
   08 0B FFFFFF82 00 FFFFFF83 4A FFFFFF84 FFFFFF80 FFFFFF80 FFFFFF84 20 FFFFFF82 01 08 0B FFFFFF82
   10 FFFFFF83 4A FFFFFF84 FFFFFF80 FFFFFF80 FFFFFF84 20 FFFFFF83 70 14 04 FFFFFF81 65 FFFFFF83 71
   08 09 FFFFFF82 13 FFFFFF83 6F FFFFFF81 FFFFFF80 FFFFFFC0 00 2D 08 0B FFFFFF82 15 FFFFFF83
   4A FFFFFF84 FFFFFF80 FFFFFF80 FFFFFF84 20 FFFFFF82 16 08 0B FFFFFF82 1A FFFFFF83 4A FFFFFF84 FFFFFF80
   FFFFFF80 FFFFFF84 20 FFFFFF82 1B 08 0B FFFFFF82 1D FFFFFF83 4A FFFFFF84 FFFFFF80 FFFFFF80 FFFFFF84 20
   FFFFFF83 75 14 03 2D FFFFFF83 76 08 0A FFFFFF82 13 FFFFFF83 74 FFFFFF81 FFFFFF80 FFFFFFC0
   00 FFFFFF82 02 08 0B FFFFFF82 21 FFFFFF83 4A FFFFFF84 FFFFFF80 FFFFFF80 FFFFFF84 20 FFFFFF83 78
   14 04 FFFFFF81 65 FFFFFF83 79 08 09 FFFFFF82 13 FFFFFF83 77 FFFFFF81 FFFFFF80 FFFFFFC0 00
   2D 28 04 FFFFFF83 4A FFFFFF82 25 07 09 FFFFFF83 7C 09 FFFFFF81 FFFFFF80 FFFFFF88 02
   FFFFFF83 7D 01 0F 49 74 65 72 61 62 6C 65 57 72 61 70
   70 65 72 10 04 FFFFFF81 60 FFFFFF83 7E 06 0A FFFFFF83 4B 09 FFFFFF84 FFFFFF81
   FFFFFF80 FFFFFF88 02 FFFFFF83 7F 13 04 FFFFFF83 7E 0C 14 08 07 19 FFFFFF83 7E
   FFFFFF84 00 FFFFFF84 01 14 02 FFFFFF83 7D 08 0A FFFFFF82 30 FFFFFF83 7E FFFFFF81 FFFFFF80
   FFFFFF84 40 FFFFFF84 03 15 04 FFFFFF84 04 FFFFFF84 07 14 04 FFFFFF84 05 FFFFFF84 08
   10 06 FFFFFF81 60 FFFFFF83 4A FFFFFF84 06 10 03 26 FFFFFF84 07 04 09 28
   FFFFFF84 02 FFFFFF84 FFFFFF80 FFFFFF80 FFFFFFC2 00 29 08 08 FFFFFF81 58 FFFFFF84 02 FFFFFFC0 00
   FFFFFF84 09 10 04 08 4A FFFFFF84 06 08 0A FFFFFF82 39 FFFFFF83 7E FFFFFF81 FFFFFF80
   FFFFFF84 40 FFFFFF84 0B 15 04 FFFFFF84 0C FFFFFF84 10 14 04 FFFFFF84 0D FFFFFF84 11
   10 05 15 FFFFFF82 3D FFFFFF84 0E 10 04 08 4A FFFFFF84 0F 10 03 26
   FFFFFF84 10 04 09 28 FFFFFF84 0A FFFFFF84 FFFFFF80 FFFFFF80 FFFFFFC2 00 29 08 08 FFFFFF82
   43 FFFFFF84 0A FFFFFFC0 00 FFFFFF84 12 10 06 FFFFFF81 60 FFFFFF83 4A FFFFFF84 0F 06
   06 FFFFFF84 14 09 40 FFFFFF84 15 02 10 4A 49 74 65 72 61 62
   6C 65 57 72 61 70 70 65 72 15 04 FFFFFF84 16 FFFFFF84 19 13
   08 FFFFFF84 13 0C FFFFFF84 17 14 FFFFFF81 54 10 04 08 4A FFFFFF84 18 10
   03 26 FFFFFF84 19 04 09 28 FFFFFF84 13 FFFFFF84 FFFFFF80 FFFFFF80 FFFFFFC2 00 29 08
   0B FFFFFF81 58 FFFFFF84 13 FFFFFF82 FFFFFFCA FFFFFF80 FFFFFF84 00 FFFFFF84 1B 15 02 FFFFFF84 1C
   10 04 0D 44 FFFFFF84 18 08 0B FFFFFF81 5C FFFFFF84 13 FFFFFF82 FFFFFF88 FFFFFFA0 FFFFFF80
   04 FFFFFF84 1C 08 07 19 FFFFFF84 13 FFFFFF84 00 FFFFFF84 1F 14 04 FFFFFF84 20
   FFFFFF84 21 10 06 FFFFFF81 60 FFFFFF84 13 FFFFFF84 18 08 08 FFFFFF81 58 FFFFFF84 1E
   FFFFFFC0 00 FFFFFF84 1C 08 08 FFFFFF83 5C FFFFFF84 13 FFFFFF84 00 FFFFFF84 23 15 02
   FFFFFF84 24 10 04 08 33 FFFFFF84 18 08 08 FFFFFF84 26 FFFFFF84 13 FFFFFF84 00
   FFFFFF84 27 01 0A 6E 65 77 42 75 69 6C 64 65 72 15 04
   FFFFFF84 28 FFFFFF84 2C 10 05 62 FFFFFF84 29 FFFFFF84 2B 09 03 FFFFFF84 2A 63
   02 0B 41 72 72 61 79 42 75 66 66 65 72 10 03 26
   FFFFFF84 2C 04 0A FFFFFF81 09 FFFFFF84 25 FFFFFF84 FFFFFF80 FFFFFF80 FFFFFFC2 00 29 08 0A
   FFFFFF81 73 FFFFFF84 13 FFFFFF81 FFFFFF80 FFFFFF84 00 FFFFFF84 2E 15 04 FFFFFF84 2F FFFFFF84 32
   14 04 FFFFFF84 30 FFFFFF84 33 10 06 FFFFFF81 60 FFFFFF84 13 FFFFFF84 31 10 03
   26 FFFFFF84 32 04 09 28 FFFFFF84 2D FFFFFF84 FFFFFF80 FFFFFF80 FFFFFFC2 00 29 08 0C
   FFFFFF84 35 FFFFFF81 58 FFFFFF84 2D FFFFFF90 FFFFFF80 FFFFFFC0 00 FFFFFF84 34 10 04 0D 44
   FFFFFF84 31 08 0A FFFFFF81 7C FFFFFF84 13 FFFFFF91 FFFFFF80 FFFFFF84 00 FFFFFF84 36 15 04
   FFFFFF84 1C FFFFFF84 37 04 09 28 FFFFFF84 35 FFFFFF84 FFFFFF80 FFFFFF80 FFFFFFC2 00 29 08
   0B FFFFFF82 00 FFFFFF84 13 FFFFFF84 FFFFFF80 FFFFFF80 FFFFFF84 20 FFFFFF82 01 08 0B FFFFFF82 10
   FFFFFF84 13 FFFFFF84 FFFFFF80 FFFFFF80 FFFFFF84 20 FFFFFF84 3A 14 04 FFFFFF81 65 FFFFFF84 3B 08
   09 FFFFFF82 13 FFFFFF84 39 FFFFFF81 FFFFFF80 FFFFFFC0 00 2D 08 0B FFFFFF82 15 FFFFFF84 13
   FFFFFF84 FFFFFF80 FFFFFF80 FFFFFF84 20 FFFFFF82 16 08 0B FFFFFF82 1A FFFFFF84 13 FFFFFF84 FFFFFF80 FFFFFF80
   FFFFFF84 20 FFFFFF82 1B 08 0B FFFFFF82 1D FFFFFF84 13 FFFFFF84 FFFFFF80 FFFFFF80 FFFFFF84 20 FFFFFF84
   3F 14 03 2D FFFFFF84 40 08 0A FFFFFF82 13 FFFFFF84 3E FFFFFF81 FFFFFF80 FFFFFFC0 00
   FFFFFF82 02 08 0B FFFFFF82 21 FFFFFF84 13 FFFFFF84 FFFFFF80 FFFFFF80 FFFFFF84 20 FFFFFF84 42 14
   04 FFFFFF81 65 FFFFFF84 43 08 09 FFFFFF82 13 FFFFFF84 41 FFFFFF81 FFFFFF80 FFFFFFC0 00 2D
   28 04 FFFFFF84 13 FFFFFF82 25 07 09 FFFFFF84 46 09 FFFFFF81 FFFFFF80 FFFFFF88 02 FFFFFF84
   47 01 10 4A 49 74 65 72 61 62 6C 65 57 72 61 70
   70 65 72 10 04 FFFFFF81 60 FFFFFF84 48 06 0A FFFFFF84 14 09 FFFFFF84 FFFFFF81
   FFFFFF80 FFFFFF88 02 FFFFFF84 49 13 04 FFFFFF84 48 0C 14 08 07 19 FFFFFF84 48
   FFFFFF84 00 FFFFFF84 4B 14 02 FFFFFF84 47 08 0A FFFFFF82 30 FFFFFF84 48 FFFFFF81 FFFFFF80
   FFFFFF84 40 FFFFFF84 4D 15 04 FFFFFF84 4E FFFFFF84 51 14 04 FFFFFF84 4F FFFFFF84 52
   10 06 FFFFFF81 60 FFFFFF84 13 FFFFFF84 50 10 03 26 FFFFFF84 51 04 09 28
   FFFFFF84 4C FFFFFF84 FFFFFF80 FFFFFF80 FFFFFFC2 00 29 08 08 FFFFFF81 58 FFFFFF84 4C FFFFFFC0 00
   FFFFFF84 53 10 04 0D 44 FFFFFF84 50 08 0A FFFFFF82 39 FFFFFF84 48 FFFFFF81 FFFFFF80
   FFFFFF84 40 FFFFFF84 55 15 04 FFFFFF84 56 FFFFFF84 5A 14 04 FFFFFF84 57 FFFFFF84 5B
   10 05 15 FFFFFF82 3D FFFFFF84 58 10 04 0D 44 FFFFFF84 59 10 03 26
   FFFFFF84 5A 04 09 28 FFFFFF84 54 FFFFFF84 FFFFFF80 FFFFFF80 FFFFFFC2 00 29 08 08 FFFFFF82
   43 FFFFFF84 54 FFFFFFC0 00 FFFFFF84 5C 10 06 FFFFFF81 60 FFFFFF84 13 FFFFFF84 59 06
   06 FFFFFF84 5E 09 40 FFFFFF84 5F 02 12 4A 43 6F 6C 6C 65 63
   74 69 6F 6E 57 72 61 70 70 65 72 15 04 FFFFFF84 60 FFFFFF84
   63 13 08 FFFFFF84 5D 0C FFFFFF84 61 14 FFFFFF81 54 10 04 08 4A FFFFFF84
   62 10 03 26 FFFFFF84 63 04 09 28 FFFFFF84 5D FFFFFF84 FFFFFF80 FFFFFF80 FFFFFFC2 00
   29 08 0B FFFFFF81 58 FFFFFF84 5D FFFFFF82 FFFFFFCA FFFFFF80 FFFFFF84 00 FFFFFF84 65 15 02
   FFFFFF84 66 10 04 20 50 FFFFFF84 62 08 0B FFFFFF81 5C FFFFFF84 5D FFFFFF82 FFFFFF88
   FFFFFFA0 FFFFFF80 04 FFFFFF84 66 08 07 19 FFFFFF84 5D FFFFFF84 00 FFFFFF84 69 14 04
   FFFFFF84 6A FFFFFF84 6B 10 06 FFFFFF81 60 FFFFFF84 5D FFFFFF84 62 08 08 FFFFFF81 58
   FFFFFF84 68 FFFFFFC0 00 FFFFFF84 66 08 08 FFFFFF83 5C FFFFFF84 5D FFFFFF84 00 FFFFFF84 6D
   15 02 FFFFFF84 6E 10 04 08 33 FFFFFF84 62 08 08 FFFFFF83 60 FFFFFF84 5D
   FFFFFF84 20 FFFFFF82 1B 08 08 FFFFFF83 62 FFFFFF84 5D FFFFFF84 20 FFFFFF82 55 08 08
   FFFFFF84 26 FFFFFF84 5D FFFFFF84 00 FFFFFF84 72 15 04 FFFFFF84 73 FFFFFF84 75 10 05
   62 FFFFFF84 29 FFFFFF84 74 10 03 26 FFFFFF84 75 04 0A FFFFFF81 09 FFFFFF84 71
   FFFFFF84 FFFFFF80 FFFFFF80 FFFFFFC2 00 29 08 0A FFFFFF81 73 FFFFFF84 5D FFFFFF81 FFFFFF80 FFFFFF84 00
   FFFFFF84 77 15 04 FFFFFF84 78 FFFFFF84 7B 14 04 FFFFFF84 79 FFFFFF84 7C 10 06
   FFFFFF81 60 FFFFFF84 5D FFFFFF84 7A 10 03 26 FFFFFF84 7B 04 09 28 FFFFFF84 76
   FFFFFF84 FFFFFF80 FFFFFF80 FFFFFFC2 00 29 08 0C FFFFFF84 7E FFFFFF81 58 FFFFFF84 76 FFFFFF90 FFFFFF80
   FFFFFFC0 00 FFFFFF84 7D 10 04 20 50 FFFFFF84 7A 08 0A FFFFFF81 7C FFFFFF84 5D
   FFFFFF91 FFFFFF80 FFFFFF84 00 FFFFFF84 7F 15 04 FFFFFF84 66 FFFFFF85 00 04 09 28 FFFFFF84
   7E FFFFFF84 FFFFFF80 FFFFFF80 FFFFFFC2 00 29 08 0B FFFFFF82 00 FFFFFF84 5D FFFFFF84 FFFFFF80 FFFFFF80
   FFFFFF84 20 FFFFFF82 01 08 0B FFFFFF82 10 FFFFFF84 5D FFFFFF84 FFFFFF80 FFFFFF80 FFFFFF84 20 FFFFFF85
   03 14 04 FFFFFF81 65 FFFFFF85 04 08 09 FFFFFF82 13 FFFFFF85 02 FFFFFF81 FFFFFF80 FFFFFFC0
   00 2D 08 0B FFFFFF82 15 FFFFFF84 5D FFFFFF84 FFFFFF80 FFFFFF80 FFFFFF84 20 FFFFFF82 16 08
   0B FFFFFF82 1A FFFFFF84 5D FFFFFF84 FFFFFF80 FFFFFF80 FFFFFF84 20 FFFFFF82 1B 08 0B FFFFFF82 1D
   FFFFFF84 5D FFFFFF84 FFFFFF80 FFFFFF80 FFFFFF84 20 FFFFFF85 08 14 03 2D FFFFFF85 09 08 0A
   FFFFFF82 13 FFFFFF85 07 FFFFFF81 FFFFFF80 FFFFFFC0 00 FFFFFF82 02 08 0B FFFFFF82 21 FFFFFF84 5D
   FFFFFF84 FFFFFF80 FFFFFF80 FFFFFF84 20 FFFFFF85 0B 14 04 FFFFFF81 65 FFFFFF85 0C 08 09 FFFFFF82
   13 FFFFFF85 0A FFFFFF81 FFFFFF80 FFFFFFC0 00 2D 28 04 FFFFFF84 5D FFFFFF82 25 07 09
   FFFFFF85 0F 09 FFFFFF81 FFFFFF80 FFFFFF88 02 FFFFFF85 10 01 12 4A 43 6F 6C 6C
   65 63 74 69 6F 6E 57 72 61 70 70 65 72 10 04 FFFFFF81
   60 FFFFFF85 11 06 0A FFFFFF84 5E 09 FFFFFF84 FFFFFF81 FFFFFF80 FFFFFF88 02 FFFFFF85 12 13
   04 FFFFFF85 11 0C 14 08 07 19 FFFFFF85 11 FFFFFF84 00 FFFFFF85 14 14 02
   FFFFFF85 10 08 0A FFFFFF82 30 FFFFFF85 11 FFFFFF81 FFFFFF80 FFFFFF84 40 FFFFFF85 16 15 04
   FFFFFF85 17 FFFFFF85 1A 14 04 FFFFFF85 18 FFFFFF85 1B 10 06 FFFFFF81 60 FFFFFF84 5D
   FFFFFF85 19 10 03 26 FFFFFF85 1A 04 09 28 FFFFFF85 15 FFFFFF84 FFFFFF80 FFFFFF80 FFFFFFC2
   00 29 08 08 FFFFFF81 58 FFFFFF85 15 FFFFFFC0 00 FFFFFF85 1C 10 04 20 50
   FFFFFF85 19 08 0A FFFFFF82 39 FFFFFF85 11 FFFFFF81 FFFFFF80 FFFFFF84 40 FFFFFF85 1E 15 04
   FFFFFF85 1F FFFFFF85 23 14 04 FFFFFF85 20 FFFFFF85 24 10 05 15 FFFFFF82 3D FFFFFF85
   21 10 04 20 50 FFFFFF85 22 10 03 26 FFFFFF85 23 04 09 28 FFFFFF85
   1D FFFFFF84 FFFFFF80 FFFFFF80 FFFFFFC2 00 29 08 08 FFFFFF82 43 FFFFFF85 1D FFFFFFC0 00 FFFFFF85
   25 10 06 FFFFFF81 60 FFFFFF84 5D FFFFFF85 22 06 06 FFFFFF85 27 09 40 FFFFFF85
   28 02 14 4D 75 74 61 62 6C 65 42 75 66 66 65 72
   57 72 61 70 70 65 72 15 04 FFFFFF85 29 FFFFFF85 2E 13 07 FFFFFF85
   26 FFFFFF85 2A 14 FFFFFF81 54 10 05 20 FFFFFF85 2B FFFFFF85 2D 09 03 FFFFFF85
   2C 21 02 0C 41 62 73 74 72 61 63 74 4C 69 73 74
   10 03 26 FFFFFF85 2E 04 09 28 FFFFFF85 26 FFFFFF84 FFFFFF80 FFFFFF80 FFFFFFC2 00 29
   08 0B FFFFFF81 58 FFFFFF85 26 FFFFFF82 FFFFFFCA FFFFFF80 FFFFFF84 00 FFFFFF85 30 15 02 FFFFFF85
   31 10 04 62 65 FFFFFF85 2D 08 0B FFFFFF81 5C FFFFFF85 26 FFFFFF82 FFFFFF88 FFFFFFA0
   FFFFFF80 04 FFFFFF85 31 08 07 19 FFFFFF85 26 FFFFFF84 00 FFFFFF85 34 14 04 FFFFFF85
   35 FFFFFF85 36 10 06 FFFFFF81 60 FFFFFF85 26 FFFFFF85 2D 08 08 FFFFFF81 58 FFFFFF85
   33 FFFFFFC0 00 FFFFFF85 31 08 08 FFFFFF83 60 FFFFFF85 26 FFFFFF84 00 FFFFFF82 01 08
   08 FFFFFF85 39 FFFFFF85 26 FFFFFF84 00 FFFFFF85 3A 01 03 67 65 74 14 04
   FFFFFF85 2D FFFFFF85 3B 08 07 31 FFFFFF85 38 FFFFFFC0 00 FFFFFF82 02 08 08 FFFFFF85
   3D FFFFFF85 26 FFFFFF84 20 FFFFFF85 3E 01 03 73 65 74 14 06 FFFFFF85 2D
   FFFFFF85 3F FFFFFF85 40 08 07 31 FFFFFF85 3C FFFFFFC0 00 FFFFFF82 02 08 08 FFFFFF85
   41 FFFFFF85 3C FFFFFFC0 00 FFFFFF85 2D 01 04 65 6C 65 6D 08 08 FFFFFF85
   43 FFFFFF85 26 FFFFFF84 20 FFFFFF85 44 01 03 61 64 64 14 04 FFFFFF81 65
   FFFFFF85 45 08 08 FFFFFF85 41 FFFFFF85 42 FFFFFFC0 00 FFFFFF85 2D 08 08 FFFFFF81 70
   FFFFFF85 26 FFFFFF84 20 FFFFFF85 47 14 04 FFFFFF85 2D FFFFFF85 48 08 07 31 FFFFFF85
   46 FFFFFFC0 00 FFFFFF82 02 08 0A FFFFFF81 73 FFFFFF85 26 FFFFFF81 FFFFFF80 FFFFFF84 00 FFFFFF85
   4A 15 04 FFFFFF85 4B FFFFFF85 4E 14 04 FFFFFF85 4C FFFFFF85 4F 10 06 FFFFFF81
   60 FFFFFF85 26 FFFFFF85 4D 10 03 26 FFFFFF85 4E 04 09 28 FFFFFF85 49 FFFFFF84
   FFFFFF80 FFFFFF80 FFFFFFC2 00 29 08 0C FFFFFF85 51 FFFFFF81 58 FFFFFF85 49 FFFFFF90 FFFFFF80 FFFFFFC0
   00 FFFFFF85 50 10 04 62 65 FFFFFF85 4D 08 0A FFFFFF81 7C FFFFFF85 26 FFFFFF91
   FFFFFF80 FFFFFF84 00 FFFFFF85 52 15 04 FFFFFF85 31 FFFFFF85 53 04 09 28 FFFFFF85 51
   FFFFFF84 FFFFFF80 FFFFFF80 FFFFFFC2 00 29 08 0B FFFFFF82 15 FFFFFF85 26 FFFFFF84 FFFFFF80 FFFFFF80 FFFFFF84
   20 FFFFFF82 16 08 0B FFFFFF82 1A FFFFFF85 26 FFFFFF84 FFFFFF80 FFFFFF80 FFFFFF84 20 FFFFFF82 1B
   08 0B FFFFFF82 1D FFFFFF85 26 FFFFFF84 FFFFFF80 FFFFFF80 FFFFFF84 20 FFFFFF85 57 14 03 2D
   FFFFFF85 58 08 0A FFFFFF82 13 FFFFFF85 56 FFFFFF81 FFFFFF80 FFFFFFC0 00 FFFFFF82 02 08 0B
   FFFFFF82 21 FFFFFF85 26 FFFFFF84 FFFFFF80 FFFFFF80 FFFFFF84 20 FFFFFF85 5A 14 04 FFFFFF81 65 FFFFFF85
   5B 08 09 FFFFFF82 13 FFFFFF85 59 FFFFFF81 FFFFFF80 FFFFFFC0 00 2D 28 04 FFFFFF85 26
   FFFFFF82 25 07 09 FFFFFF85 5E 09 FFFFFF81 FFFFFF80 FFFFFF88 02 FFFFFF85 5F 01 14 4D
   75 74 61 62 6C 65 42 75 66 66 65 72 57 72 61 70
   70 65 72 10 04 FFFFFF81 60 FFFFFF85 60 06 0A FFFFFF85 27 09 FFFFFF84 FFFFFF81
   FFFFFF80 FFFFFF88 02 FFFFFF85 61 13 04 FFFFFF85 60 0C 14 08 07 19 FFFFFF85 60
   FFFFFF84 00 FFFFFF85 63 14 02 FFFFFF85 5F 08 0A FFFFFF82 30 FFFFFF85 60 FFFFFF81 FFFFFF80
   FFFFFF84 40 FFFFFF85 65 15 04 FFFFFF85 66 FFFFFF85 69 14 04 FFFFFF85 67 FFFFFF85 6A
   10 06 FFFFFF81 60 FFFFFF85 26 FFFFFF85 68 10 03 26 FFFFFF85 69 04 09 28
   FFFFFF85 64 FFFFFF84 FFFFFF80 FFFFFF80 FFFFFFC2 00 29 08 08 FFFFFF81 58 FFFFFF85 64 FFFFFFC0 00
   FFFFFF85 6B 10 04 62 65 FFFFFF85 68 08 0A FFFFFF82 39 FFFFFF85 60 FFFFFF81 FFFFFF80
   FFFFFF84 40 FFFFFF85 6D 15 04 FFFFFF85 6E FFFFFF85 72 14 04 FFFFFF85 6F FFFFFF85 73
   10 05 15 FFFFFF82 3D FFFFFF85 70 10 04 62 65 FFFFFF85 71 10 03 26
   FFFFFF85 72 04 09 28 FFFFFF85 6C FFFFFF84 FFFFFF80 FFFFFF80 FFFFFFC2 00 29 08 08 FFFFFF82
   43 FFFFFF85 6C FFFFFFC0 00 FFFFFF85 74 10 06 FFFFFF81 60 FFFFFF85 26 FFFFFF85 71 06
   06 FFFFFF85 76 09 40 FFFFFF85 77 02 0C 4A 4C 69 73 74 57 72
   61 70 70 65 72 15 04 FFFFFF85 78 FFFFFF85 7B 13 08 FFFFFF85 75 0C
   FFFFFF85 79 14 FFFFFF81 54 10 04 62 65 FFFFFF85 7A 10 03 26 FFFFFF85 7B
   04 09 28 FFFFFF85 75 FFFFFF84 FFFFFF80 FFFFFF80 FFFFFFC2 00 29 08 0B FFFFFF81 58 FFFFFF85
   75 FFFFFF82 FFFFFFCA FFFFFF80 FFFFFF84 00 FFFFFF85 7D 15 02 FFFFFF85 7E 10 04 20 5B
   FFFFFF85 7A 08 0B FFFFFF81 5C FFFFFF85 75 FFFFFF82 FFFFFF88 FFFFFFA0 FFFFFF80 04 FFFFFF85 7E 08
   07 19 FFFFFF85 75 FFFFFF84 00 FFFFFF86 01 14 04 FFFFFF86 02 FFFFFF86 03 10 06
   FFFFFF81 60 FFFFFF85 75 FFFFFF85 7A 08 08 FFFFFF81 58 FFFFFF86 00 FFFFFFC0 00 FFFFFF85 7E
   08 08 FFFFFF86 05 FFFFFF85 75 FFFFFF84 00 FFFFFF82 1B 01 06 6C 65 6E 67
   74 68 08 08 FFFFFF83 62 FFFFFF85 75 FFFFFF84 20 FFFFFF82 55 08 08 FFFFFF83 5C
   FFFFFF85 75 FFFFFF84 20 FFFFFF86 08 15 02 FFFFFF86 09 10 04 08 33 FFFFFF85 7A
   08 08 FFFFFF82 30 FFFFFF85 75 FFFFFF84 00 FFFFFF86 0B 14 04 FFFFFF85 7A FFFFFF86 0C
   08 07 31 FFFFFF86 0A FFFFFFC0 00 FFFFFF82 02 08 08 FFFFFF86 0E FFFFFF85 75 FFFFFF84
   00 FFFFFF86 0F 01 06 75 70 64 61 74 65 14 06 FFFFFF86 10 FFFFFF86
   13 FFFFFF86 14 10 03 15 FFFFFF86 11 09 03 FFFFFF86 12 04 02 04 55
   6E 69 74 08 07 31 FFFFFF86 0D FFFFFFC0 00 FFFFFF82 02 08 08 FFFFFF85 41
   FFFFFF86 0D FFFFFFC0 00 FFFFFF85 7A 08 08 FFFFFF86 16 FFFFFF85 75 FFFFFF84 00 FFFFFF86 17
   01 0B 24 70 6C 75 73 24 63 6F 6C 6F 6E 14 04 FFFFFF86
   02 FFFFFF86 18 08 08 FFFFFF85 41 FFFFFF86 15 FFFFFFC0 00 FFFFFF85 7A 08 08 FFFFFF86
   1A FFFFFF85 75 FFFFFF84 00 FFFFFF86 1B 01 08 24 70 6C 75 73 24 65
   71 14 04 FFFFFF86 1C FFFFFF86 1D 0D 02 FFFFFF85 75 08 08 FFFFFF85 41 FFFFFF86
   19 FFFFFFC0 00 FFFFFF85 7A 08 08 FFFFFF86 1F FFFFFF85 75 FFFFFF84 00 FFFFFF86 20 01
   09 69 6E 73 65 72 74 41 6C 6C 14 06 FFFFFF86 10 FFFFFF86 21
   FFFFFF86 22 08 07 31 FFFFFF86 1E FFFFFFC0 00 FFFFFF82 02 08 08 FFFFFF86 23 FFFFFF86
   1E FFFFFFC0 00 FFFFFF86 24 01 05 65 6C 65 6D 73 10 05 08 FFFFFF86
   25 FFFFFF85 7A 09 03 FFFFFF86 26 02 02 0B 54 72 61 76 65 72
   73 61 62 6C 65 08 08 FFFFFF81 70 FFFFFF85 75 FFFFFF84 00 FFFFFF86 28 14
   04 FFFFFF85 7A FFFFFF86 29 08 07 31 FFFFFF86 27 FFFFFFC0 00 FFFFFF82 02 08 08
   FFFFFF86 2B FFFFFF85 75 FFFFFF84 00 FFFFFF86 2C 01 05 63 6C 65 61 72 14
   02 FFFFFF86 10 08 08 FFFFFF86 2E FFFFFF85 75 FFFFFF84 00 FFFFFF86 2F 01 06 72
   65 73 75 6C 74 15 02 FFFFFF86 02 08 0A FFFFFF81 73 FFFFFF85 75 FFFFFF81
   FFFFFF80 FFFFFF84 00 FFFFFF86 31 15 04 FFFFFF86 32 FFFFFF86 35 14 04 FFFFFF86 33 FFFFFF86
   36 10 06 FFFFFF81 60 FFFFFF85 75 FFFFFF86 34 10 03 26 FFFFFF86 35 04 09
   28 FFFFFF86 30 FFFFFF84 FFFFFF80 FFFFFF80 FFFFFFC2 00 29 08 0C FFFFFF86 38 FFFFFF81 58 FFFFFF86
   30 FFFFFF90 FFFFFF80 FFFFFFC0 00 FFFFFF86 37 10 04 20 5B FFFFFF86 34 08 0A FFFFFF81
   7C FFFFFF85 75 FFFFFF91 FFFFFF80 FFFFFF84 00 FFFFFF86 39 15 04 FFFFFF85 7E FFFFFF86 3A 04
   09 28 FFFFFF86 38 FFFFFF84 FFFFFF80 FFFFFF80 FFFFFFC2 00 29 08 0B FFFFFF82 15 FFFFFF85 75
   FFFFFF84 FFFFFF80 FFFFFF80 FFFFFF84 20 FFFFFF82 16 08 0B FFFFFF82 1A FFFFFF85 75 FFFFFF84 FFFFFF80 FFFFFF80
   FFFFFF84 20 FFFFFF82 1B 08 0B FFFFFF82 1D FFFFFF85 75 FFFFFF84 FFFFFF80 FFFFFF80 FFFFFF84 20 FFFFFF86
   3E 14 03 2D FFFFFF86 3F 08 0A FFFFFF82 13 FFFFFF86 3D FFFFFF81 FFFFFF80 FFFFFFC0 00
   FFFFFF82 02 08 0B FFFFFF82 21 FFFFFF85 75 FFFFFF84 FFFFFF80 FFFFFF80 FFFFFF84 20 FFFFFF86 41 14
   04 FFFFFF81 65 FFFFFF86 42 08 09 FFFFFF82 13 FFFFFF86 40 FFFFFF81 FFFFFF80 FFFFFFC0 00 2D
   28 04 FFFFFF85 75 FFFFFF82 25 07 09 FFFFFF86 45 09 FFFFFF81 FFFFFF80 FFFFFF88 02 FFFFFF86
   46 01 0C 4A 4C 69 73 74 57 72 61 70 70 65 72 10
   04 FFFFFF81 60 FFFFFF86 47 06 0A FFFFFF85 76 09 FFFFFF84 FFFFFF81 FFFFFF80 FFFFFF88 02 FFFFFF86
   48 13 04 FFFFFF86 47 0C 14 08 07 19 FFFFFF86 47 FFFFFF84 00 FFFFFF86 4A
   14 02 FFFFFF86 46 08 0A FFFFFF82 30 FFFFFF86 47 FFFFFF81 FFFFFF80 FFFFFF84 40 FFFFFF86 4C
   15 04 FFFFFF86 4D FFFFFF86 50 14 04 FFFFFF86 4E FFFFFF86 51 10 06 FFFFFF81 60
   FFFFFF85 75 FFFFFF86 4F 10 03 26 FFFFFF86 50 04 09 28 FFFFFF86 4B FFFFFF84 FFFFFF80
   FFFFFF80 FFFFFFC2 00 29 08 08 FFFFFF81 58 FFFFFF86 4B FFFFFFC0 00 FFFFFF86 52 10 04
   20 5B FFFFFF86 4F 08 0A FFFFFF82 39 FFFFFF86 47 FFFFFF81 FFFFFF80 FFFFFF84 40 FFFFFF86 54
   15 04 FFFFFF86 55 FFFFFF86 59 14 04 FFFFFF86 56 FFFFFF86 5A 10 05 15 FFFFFF82
   3D FFFFFF86 57 10 04 20 5B FFFFFF86 58 10 03 26 FFFFFF86 59 04 09
   28 FFFFFF86 53 FFFFFF84 FFFFFF80 FFFFFF80 FFFFFFC2 00 29 08 08 FFFFFF82 43 FFFFFF86 53 FFFFFFC0
   00 FFFFFF86 5B 10 06 FFFFFF81 60 FFFFFF85 75 FFFFFF86 58 06 06 FFFFFF86 5D 09
   40 FFFFFF86 5E 02 11 4D 75 74 61 62 6C 65 53 65 74 57
   72 61 70 70 65 72 15 04 FFFFFF86 5F FFFFFF86 64 13 07 FFFFFF86 5C
   FFFFFF86 60 14 FFFFFF81 54 10 05 20 FFFFFF86 61 FFFFFF86 63 09 03 FFFFFF86 62
   21 02 0B 41 62 73 74 72 61 63 74 53 65 74 10 03
   26 FFFFFF86 64 04 09 28 FFFFFF86 5C FFFFFF84 FFFFFF80 FFFFFF80 FFFFFFC2 00 29 08 0B
   FFFFFF81 58 FFFFFF86 5C FFFFFF82 FFFFFFCA FFFFFF80 FFFFFF84 00 FFFFFF86 66 15 02 FFFFFF86 67 10
   04 62 7C FFFFFF86 63 08 0B FFFFFF81 5C FFFFFF86 5C FFFFFF82 FFFFFF88 FFFFFFA0 FFFFFF80 04
   FFFFFF86 67 08 0A 72 FFFFFF86 5C FFFFFF82 FFFFFF80 FFFFFFA0 FFFFFF80 04 FFFFFF86 6A 10 04
   74 77 FFFFFF86 63 08 07 19 FFFFFF86 5C FFFFFF84 00 FFFFFF86 6C 14 04 FFFFFF86
   6D FFFFFF86 70 14 04 FFFFFF86 6E FFFFFF86 6F 10 06 FFFFFF81 60 FFFFFF86 5C FFFFFF86
   63 08 07 72 FFFFFF86 6B FFFFFFC0 00 FFFFFF86 6A 08 08 FFFFFF81 58 FFFFFF86 6B
   FFFFFFC0 00 FFFFFF86 67 08 08 FFFFFF83 60 FFFFFF86 5C FFFFFF84 00 FFFFFF82 01 08 08
   FFFFFF85 43 FFFFFF86 5C FFFFFF84 20 FFFFFF86 73 14 04 FFFFFF81 65 FFFFFF86 74 08 08
   FFFFFF85 41 FFFFFF86 72 FFFFFFC0 00 FFFFFF86 63 08 08 FFFFFF81 70 FFFFFF86 5C FFFFFF84 20
   FFFFFF86 76 14 04 FFFFFF81 65 FFFFFF86 77 08 08 FFFFFF85 41 FFFFFF86 75 FFFFFFC0 00
   FFFFFF86 78 10 03 15 FFFFFF86 79 09 03 FFFFFF86 7A 04 02 06 41 6E
   79 52 65 66 08 08 FFFFFF83 5C FFFFFF86 5C FFFFFF84 00 FFFFFF86 7C 14 02
   FFFFFF86 7D 12 05 FFFFFF86 7E 0C FFFFFF87 00 06 0B FFFFFF86 7F FFFFFF86 7B FFFFFF84
   FFFFFF80 FFFFFF80 FFFFFF80 00 FFFFFF86 7D 02 0C 3C 72 65 66 69 6E 65 6D
   65 6E 74 3E 10 04 20 23 FFFFFF86 63 08 0A FFFFFF87 02 FFFFFF86 7E
   FFFFFFC2 FFFFFF80 FFFFFF84 00 FFFFFF87 03 01 02 75 69 15 02 FFFFFF87 04 10 04
   08 33 FFFFFF86 63 08 0A FFFFFF87 06 FFFFFF86 7E FFFFFFC0 FFFFFF80 FFFFFF84 00 FFFFFF87 07
   01 04 70 72 65 76 15 02 FFFFFF87 08 10 05 15 FFFFFF87 09 FFFFFF86
   63 09 03 FFFFFF87 0A 04 02 06 4F 70 74 69 6F 6E 08 0A
   FFFFFF87 0C FFFFFF86 7E FFFFFFC0 FFFFFF80 FFFFFF84 00 FFFFFF87 0D 01 08 70 72 65 76
   5F 24 65 71 14 04 FFFFFF86 10 FFFFFF87 0E 08 0A FFFFFF82 13 FFFFFF87 0B
   FFFFFF81 FFFFFF80 FFFFFFC0 00 FFFFFF87 08 08 0A FFFFFF81 73 FFFFFF86 5C FFFFFF81 FFFFFF80 FFFFFF84 00
   FFFFFF87 10 15 04 FFFFFF87 11 FFFFFF87 15 14 04 FFFFFF87 12 FFFFFF87 20 14 04
   FFFFFF87 13 FFFFFF87 16 10 06 FFFFFF81 60 FFFFFF86 5C FFFFFF87 14 10 03 26 FFFFFF87
   15 04 09 28 FFFFFF87 0F FFFFFF84 FFFFFF80 FFFFFF80 FFFFFFC2 00 29 08 0B FFFFFF87 18
   72 FFFFFF87 0F FFFFFF90 FFFFFF80 FFFFFFC0 00 FFFFFF87 17 10 04 74 77 FFFFFF87 14 08
   0A FFFFFF87 19 FFFFFF86 5C FFFFFF91 FFFFFF80 FFFFFF84 00 FFFFFF87 1A 01 0E 63 6F 70
   79 24 64 65 66 61 75 6C 74 24 32 15 04 FFFFFF87 1B FFFFFF87
   1F 14 04 FFFFFF86 6A FFFFFF87 1C 08 08 FFFFFF81 58 FFFFFF87 18 FFFFFFC0 00 FFFFFF87
   1D 10 04 62 7C FFFFFF87 1E 10 03 26 FFFFFF87 1F 04 09 28 FFFFFF87
   18 FFFFFF84 FFFFFF80 FFFFFF80 FFFFFFC2 00 29 08 0C FFFFFF87 22 FFFFFF81 58 FFFFFF87 0F FFFFFF90
   FFFFFF80 FFFFFFC0 00 FFFFFF87 21 10 04 62 7C FFFFFF87 14 08 0A FFFFFF81 7C FFFFFF86
   5C FFFFFF91 FFFFFF80 FFFFFF84 00 FFFFFF87 23 15 04 FFFFFF86 67 FFFFFF87 24 04 09 28
   FFFFFF87 22 FFFFFF84 FFFFFF80 FFFFFF80 FFFFFFC2 00 29 08 0B FFFFFF82 15 FFFFFF86 5C FFFFFF84 FFFFFF80
   FFFFFF80 FFFFFF84 20 FFFFFF82 16 08 0B FFFFFF82 1A FFFFFF86 5C FFFFFF84 FFFFFF80 FFFFFF80 FFFFFF84 20
   FFFFFF82 1B 08 0B FFFFFF82 1D FFFFFF86 5C FFFFFF84 FFFFFF80 FFFFFF80 FFFFFF84 20 FFFFFF87 28 14
   03 2D FFFFFF87 29 08 0A FFFFFF82 13 FFFFFF87 27 FFFFFF81 FFFFFF80 FFFFFFC0 00 FFFFFF82 02
   08 0B FFFFFF82 21 FFFFFF86 5C FFFFFF84 FFFFFF80 FFFFFF80 FFFFFF84 20 FFFFFF87 2B 14 04 FFFFFF81
   65 FFFFFF87 2C 08 09 FFFFFF82 13 FFFFFF87 2A FFFFFF81 FFFFFF80 FFFFFFC0 00 2D 28 04
   FFFFFF86 5C FFFFFF82 25 07 09 FFFFFF87 2F 09 FFFFFF81 FFFFFF80 FFFFFF88 02 FFFFFF87 30 01
   11 4D 75 74 61 62 6C 65 53 65 74 57 72 61 70 70
   65 72 10 04 FFFFFF81 60 FFFFFF87 31 06 0A FFFFFF86 5D 09 FFFFFF84 FFFFFF81 FFFFFF80
   FFFFFF88 02 FFFFFF87 32 13 04 FFFFFF87 31 0C 14 08 07 19 FFFFFF87 31 FFFFFF84
   00 FFFFFF87 34 14 02 FFFFFF87 30 08 0A FFFFFF82 30 FFFFFF87 31 FFFFFF81 FFFFFF80 FFFFFF84
   40 FFFFFF87 36 15 04 FFFFFF87 37 FFFFFF87 3B 14 04 FFFFFF87 38 FFFFFF87 3E 14
   04 FFFFFF87 39 FFFFFF87 3C 10 06 FFFFFF81 60 FFFFFF86 5C FFFFFF87 3A 10 03 26
   FFFFFF87 3B 04 09 28 FFFFFF87 35 FFFFFF84 FFFFFF80 FFFFFF80 FFFFFFC2 00 29 08 07 72
   FFFFFF87 35 FFFFFFC0 00 FFFFFF87 3D 10 04 74 77 FFFFFF87 3A 08 08 FFFFFF81 58
   FFFFFF87 35 FFFFFFC0 00 FFFFFF87 3F 10 04 62 7C FFFFFF87 3A 08 0A FFFFFF82 39
   FFFFFF87 31 FFFFFF81 FFFFFF80 FFFFFF84 40 FFFFFF87 41 15 04 FFFFFF87 42 FFFFFF87 46 14 04
   FFFFFF87 43 FFFFFF87 47 10 05 15 FFFFFF82 3D FFFFFF87 44 10 04 62 7C FFFFFF87
   45 10 03 26 FFFFFF87 46 04 09 28 FFFFFF87 40 FFFFFF84 FFFFFF80 FFFFFF80 FFFFFFC2 00
   29 08 08 FFFFFF82 43 FFFFFF87 40 FFFFFFC0 00 FFFFFF87 48 10 06 FFFFFF81 60 FFFFFF86
   5C FFFFFF87 45 06 06 FFFFFF87 4A 09 40 FFFFFF87 4B 02 0B 4A 53 65
   74 57 72 61 70 70 65 72 15 04 FFFFFF87 4C FFFFFF87 4F 13 0A
   FFFFFF87 49 0C FFFFFF87 4D FFFFFF87 50 14 FFFFFF81 54 10 04 62 7C FFFFFF87 4E
   10 03 26 FFFFFF87 4F 04 09 28 FFFFFF87 49 FFFFFF84 FFFFFF80 FFFFFF80 FFFFFFC2 00 29
   10 08 FFFFFF87 51 FFFFFF87 54 FFFFFF87 4E FFFFFF87 56 0D 02 FFFFFF87 52 0A 03
   FFFFFF87 53 02 01 07 67 65 6E 65 72 69 63 09 04 FFFFFF87 55
   FFFFFF87 52 02 12 4D 75 74 61 62 6C 65 53 65 74 54 65
   6D 70 6C 61 74 65 10 06 FFFFFF81 60 FFFFFF87 49 FFFFFF87 4E 08 0B
   FFFFFF81 58 FFFFFF87 49 FFFFFF82 FFFFFFCA FFFFFF80 FFFFFF84 00 FFFFFF87 58 15 02 FFFFFF87 59 10
   04 20 6D FFFFFF87 4E 08 0B FFFFFF81 5C FFFFFF87 49 FFFFFF82 FFFFFF88 FFFFFFA0 FFFFFF80 04
   FFFFFF87 59 08 07 19 FFFFFF87 49 FFFFFF84 00 FFFFFF87 5C 14 04 FFFFFF87 56 FFFFFF87
   5D 08 08 FFFFFF81 58 FFFFFF87 5B FFFFFFC0 00 FFFFFF87 59 08 08 FFFFFF83 60 FFFFFF87
   49 FFFFFF84 20 FFFFFF82 1B 08 08 FFFFFF83 5C FFFFFF87 49 FFFFFF84 00 FFFFFF87 60 15
   02 FFFFFF87 61 10 04 08 33 FFFFFF87 4E 08 08 FFFFFF87 63 FFFFFF87 49 FFFFFF84
   00 FFFFFF87 64 01 08 63 6F 6E 74 61 69 6E 73 14 04 FFFFFF81
   65 FFFFFF87 65 08 08 FFFFFF85 41 FFFFFF87 62 FFFFFFC0 00 FFFFFF87 4E 08 08 FFFFFF86
   1A FFFFFF87 49 FFFFFF84 00 FFFFFF87 67 14 04 FFFFFF87 68 FFFFFF87 69 0D 02 FFFFFF87
   49 08 08 FFFFFF85 41 FFFFFF87 66 FFFFFFC0 00 FFFFFF87 4E 08 08 FFFFFF87 6B FFFFFF87
   49 FFFFFF84 00 FFFFFF87 6C 01 09 24 6D 69 6E 75 73 24 65 71
   14 04 FFFFFF87 68 FFFFFF87 6D 08 08 FFFFFF85 41 FFFFFF87 6A FFFFFFC0 00 FFFFFF87 4E
   08 08 FFFFFF85 43 FFFFFF87 49 FFFFFF84 20 FFFFFF87 6F 14 04 FFFFFF81 65 FFFFFF87 70
   08 08 FFFFFF85 41 FFFFFF87 6E FFFFFFC0 00 FFFFFF87 4E 08 08 FFFFFF81 70 FFFFFF87 49
   FFFFFF84 20 FFFFFF87 72 14 04 FFFFFF81 65 FFFFFF87 73 08 08 FFFFFF85 41 FFFFFF87 71
   FFFFFFC0 00 FFFFFF87 4E 08 08 FFFFFF86 2B FFFFFF87 49 FFFFFF84 20 FFFFFF86 2C 08 08
   FFFFFF87 76 FFFFFF87 49 FFFFFF84 20 FFFFFF87 77 01 05 65 6D 70 74 79 15
   02 FFFFFF87 56 08 0A FFFFFF81 73 FFFFFF87 49 FFFFFF81 FFFFFF80 FFFFFF84 00 FFFFFF87 79 15
   04 FFFFFF87 7A FFFFFF87 7D 14 04 FFFFFF87 7B FFFFFF87 7E 10 06 FFFFFF81 60 FFFFFF87
   49 FFFFFF87 7C 10 03 26 FFFFFF87 7D 04 09 28 FFFFFF87 78 FFFFFF84 FFFFFF80 FFFFFF80
   FFFFFFC2 00 29 08 0C FFFFFF88 00 FFFFFF81 58 FFFFFF87 78 FFFFFF90 FFFFFF80 FFFFFFC0 00 FFFFFF87
   7F 10 04 20 6D FFFFFF87 7C 08 0A FFFFFF81 7C FFFFFF87 49 FFFFFF91 FFFFFF80 FFFFFF84
   00 FFFFFF88 01 15 04 FFFFFF87 59 FFFFFF88 02 04 09 28 FFFFFF88 00 FFFFFF84 FFFFFF80
   FFFFFF80 FFFFFFC2 00 29 08 0B FFFFFF82 15 FFFFFF87 49 FFFFFF84 FFFFFF80 FFFFFF80 FFFFFF84 20 FFFFFF82
   16 08 0B FFFFFF82 1A FFFFFF87 49 FFFFFF84 FFFFFF80 FFFFFF80 FFFFFF84 20 FFFFFF82 1B 08 0B
   FFFFFF82 1D FFFFFF87 49 FFFFFF84 FFFFFF80 FFFFFF80 FFFFFF84 20 FFFFFF88 06 14 03 2D FFFFFF88 07
   08 0A FFFFFF82 13 FFFFFF88 05 FFFFFF81 FFFFFF80 FFFFFFC0 00 FFFFFF82 02 08 0B FFFFFF82 21
   FFFFFF87 49 FFFFFF84 FFFFFF80 FFFFFF80 FFFFFF84 20 FFFFFF88 09 14 04 FFFFFF81 65 FFFFFF88 0A 08
   09 FFFFFF82 13 FFFFFF88 08 FFFFFF81 FFFFFF80 FFFFFFC0 00 2D 28 04 FFFFFF87 49 FFFFFF82 25
   07 09 FFFFFF88 0D 09 FFFFFF81 FFFFFF80 FFFFFF88 02 FFFFFF88 0E 01 0B 4A 53 65
   74 57 72 61 70 70 65 72 10 04 FFFFFF81 60 FFFFFF88 0F 06 0A
   FFFFFF87 4A 09 FFFFFF84 FFFFFF81 FFFFFF80 FFFFFF88 02 FFFFFF88 10 13 04 FFFFFF88 0F 0C 14
   08 07 19 FFFFFF88 0F FFFFFF84 00 FFFFFF88 12 14 02 FFFFFF88 0E 08 0A FFFFFF82
   30 FFFFFF88 0F FFFFFF81 FFFFFF80 FFFFFF84 40 FFFFFF88 14 15 04 FFFFFF88 15 FFFFFF88 18 14
   04 FFFFFF88 16 FFFFFF88 19 10 06 FFFFFF81 60 FFFFFF87 49 FFFFFF88 17 10 03 26
   FFFFFF88 18 04 09 28 FFFFFF88 13 FFFFFF84 FFFFFF80 FFFFFF80 FFFFFFC2 00 29 08 08 FFFFFF81
   58 FFFFFF88 13 FFFFFFC0 00 FFFFFF88 1A 10 04 20 6D FFFFFF88 17 08 0A FFFFFF82
   39 FFFFFF88 0F FFFFFF81 FFFFFF80 FFFFFF84 40 FFFFFF88 1C 15 04 FFFFFF88 1D FFFFFF88 21 14
   04 FFFFFF88 1E FFFFFF88 22 10 05 15 FFFFFF82 3D FFFFFF88 1F 10 04 20 6D
   FFFFFF88 20 10 03 26 FFFFFF88 21 04 09 28 FFFFFF88 1B FFFFFF84 FFFFFF80 FFFFFF80 FFFFFFC2
   00 29 08 08 FFFFFF82 43 FFFFFF88 1B FFFFFFC0 00 FFFFFF88 23 10 06 FFFFFF81 60
   FFFFFF87 49 FFFFFF88 20 06 06 FFFFFF88 25 09 40 FFFFFF88 26 02 11 4D 75
   74 61 62 6C 65 4D 61 70 57 72 61 70 70 65 72 15
   06 FFFFFF88 27 FFFFFF88 2C FFFFFF88 2E 13 07 FFFFFF88 24 FFFFFF88 28 14 FFFFFF81 54
   10 07 20 FFFFFF88 29 FFFFFF88 2B FFFFFF88 2D 09 03 FFFFFF88 2A 21 02 0B
   41 62 73 74 72 61 63 74 4D 61 70 10 03 26 FFFFFF88 2C
   04 09 28 FFFFFF88 24 FFFFFF84 FFFFFF80 FFFFFF80 FFFFFFC2 00 29 10 03 26 FFFFFF88 2E
   04 0A FFFFFF81 09 FFFFFF88 24 FFFFFF84 FFFFFF80 FFFFFF80 FFFFFFC2 00 29 08 0B FFFFFF81 58
   FFFFFF88 24 FFFFFF82 FFFFFFCA FFFFFF80 FFFFFF84 00 FFFFFF88 30 15 02 FFFFFF88 31 10 07 62
   FFFFFF81 0F FFFFFF88 2B FFFFFF88 2D 08 0B FFFFFF81 5C FFFFFF88 24 FFFFFF82 FFFFFF88 FFFFFFA0 FFFFFF80
   04 FFFFFF88 31 08 0A 72 FFFFFF88 24 FFFFFF82 FFFFFF80 FFFFFFA0 FFFFFF80 04 FFFFFF88 34 10
   04 74 77 FFFFFF88 2B 08 07 19 FFFFFF88 24 FFFFFF84 00 FFFFFF88 36 14 04
   FFFFFF88 37 FFFFFF88 3A 14 04 FFFFFF88 38 FFFFFF88 39 10 08 FFFFFF81 60 FFFFFF88 24
   FFFFFF88 2B FFFFFF88 2D 08 07 72 FFFFFF88 35 FFFFFFC0 00 FFFFFF88 34 08 08 FFFFFF81
   58 FFFFFF88 35 FFFFFFC0 00 FFFFFF88 31 08 08 FFFFFF83 60 FFFFFF88 24 FFFFFF84 20 FFFFFF82
   01 08 08 FFFFFF88 3D FFFFFF88 24 FFFFFF84 20 FFFFFF88 3E 01 03 70 75 74
   14 06 FFFFFF88 2D FFFFFF88 3F FFFFFF88 41 08 08 FFFFFF88 40 FFFFFF88 3C FFFFFFC0 00
   FFFFFF88 2B 01 01 6B 08 08 FFFFFF88 42 FFFFFF88 3C FFFFFFC0 00 FFFFFF88 2D 01
   01 76 08 08 FFFFFF81 70 FFFFFF88 24 FFFFFF84 20 FFFFFF88 44 14 04 FFFFFF88 2D
   FFFFFF88 45 08 08 FFFFFF88 40 FFFFFF88 43 FFFFFFC0 00 FFFFFF86 78 08 08 FFFFFF88 47
   FFFFFF88 24 FFFFFF84 20 FFFFFF88 48 01 08 65 6E 74 72 79 53 65 74
   14 02 FFFFFF88 49 10 04 20 6D FFFFFF88 4A 10 08 FFFFFF88 4B FFFFFF88 51
   FFFFFF88 2B FFFFFF88 2D 0E 04 FFFFFF88 4C FFFFFF88 4F 0E 04 FFFFFF88 4D FFFFFF88 4E
   0D 01 10 09 02 22 10 09 03 FFFFFF88 50 21 01 03 4D 61
   70 09 04 FFFFFF88 52 FFFFFF88 53 02 05 45 6E 74 72 79 0A 03
   FFFFFF88 50 21 08 0A FFFFFF81 73 FFFFFF88 24 FFFFFF81 FFFFFF80 FFFFFF84 00 FFFFFF88 55 15
   06 FFFFFF88 56 FFFFFF88 5A FFFFFF88 5C 14 04 FFFFFF88 57 FFFFFF88 68 14 04 FFFFFF88
   58 FFFFFF88 5D 10 08 FFFFFF81 60 FFFFFF88 24 FFFFFF88 59 FFFFFF88 5B 10 03 26
   FFFFFF88 5A 04 09 28 FFFFFF88 54 FFFFFF84 FFFFFF80 FFFFFF80 FFFFFFC2 00 29 10 03 26
   FFFFFF88 5C 04 0A FFFFFF81 09 FFFFFF88 54 FFFFFF84 FFFFFF80 FFFFFF80 FFFFFFC2 00 29 08 0B
   FFFFFF88 5F 72 FFFFFF88 54 FFFFFF90 FFFFFF80 FFFFFFC0 00 FFFFFF88 5E 10 04 74 77 FFFFFF88
   59 08 0A FFFFFF87 19 FFFFFF88 24 FFFFFF91 FFFFFF80 FFFFFF84 00 FFFFFF88 60 15 06 FFFFFF88
   61 FFFFFF88 65 FFFFFF88 67 14 04 FFFFFF88 34 FFFFFF88 62 08 08 FFFFFF81 58 FFFFFF88
   5F FFFFFFC0 00 FFFFFF88 63 10 07 62 FFFFFF81 0F FFFFFF88 64 FFFFFF88 66 10 03
   26 FFFFFF88 65 04 09 28 FFFFFF88 5F FFFFFF84 FFFFFF80 FFFFFF80 FFFFFFC2 00 29 10 03
   26 FFFFFF88 67 04 0A FFFFFF81 09 FFFFFF88 5F FFFFFF84 FFFFFF80 FFFFFF80 FFFFFFC2 00 29 08
   0C FFFFFF88 6A FFFFFF81 58 FFFFFF88 54 FFFFFF90 FFFFFF80 FFFFFFC0 00 FFFFFF88 69 10 07 62
   FFFFFF81 0F FFFFFF88 59 FFFFFF88 5B 08 0A FFFFFF81 7C FFFFFF88 24 FFFFFF91 FFFFFF80 FFFFFF84 00
   FFFFFF88 6B 15 06 FFFFFF88 31 FFFFFF88 6C FFFFFF88 6D 04 09 28 FFFFFF88 6A FFFFFF84
   FFFFFF80 FFFFFF80 FFFFFFC2 00 29 04 0A FFFFFF81 09 FFFFFF88 6A FFFFFF84 FFFFFF80 FFFFFF80 FFFFFFC2 00
   29 08 0B FFFFFF82 15 FFFFFF88 24 FFFFFF84 FFFFFF80 FFFFFF80 FFFFFF84 20 FFFFFF82 16 08 0B
   FFFFFF82 1A FFFFFF88 24 FFFFFF84 FFFFFF80 FFFFFF80 FFFFFF84 20 FFFFFF82 1B 08 0B FFFFFF82 1D FFFFFF88
   24 FFFFFF84 FFFFFF80 FFFFFF80 FFFFFF84 20 FFFFFF88 71 14 03 2D FFFFFF88 72 08 0A FFFFFF82
   13 FFFFFF88 70 FFFFFF81 FFFFFF80 FFFFFFC0 00 FFFFFF82 02 08 0B FFFFFF82 21 FFFFFF88 24 FFFFFF84
   FFFFFF80 FFFFFF80 FFFFFF84 20 FFFFFF88 74 14 04 FFFFFF81 65 FFFFFF88 75 08 09 FFFFFF82 13
   FFFFFF88 73 FFFFFF81 FFFFFF80 FFFFFFC0 00 2D 28 04 FFFFFF88 24 FFFFFF82 25 07 09 FFFFFF88
   78 09 FFFFFF81 FFFFFF80 FFFFFF88 02 FFFFFF88 79 01 11 4D 75 74 61 62 6C
   65 4D 61 70 57 72 61 70 70 65 72 10 04 FFFFFF81 60 FFFFFF88
   7A 06 0A FFFFFF88 25 09 FFFFFF84 FFFFFF81 FFFFFF80 FFFFFF88 02 FFFFFF88 7B 13 04 FFFFFF88
   7A 0C 14 08 07 19 FFFFFF88 7A FFFFFF84 00 FFFFFF88 7D 14 02 FFFFFF88 79
   08 0A FFFFFF82 30 FFFFFF88 7A FFFFFF81 FFFFFF80 FFFFFF84 40 FFFFFF88 7F 15 06 FFFFFF89 00
   FFFFFF89 04 FFFFFF89 06 14 04 FFFFFF89 01 FFFFFF89 09 14 04 FFFFFF89 02 FFFFFF89 07
   10 08 FFFFFF81 60 FFFFFF88 24 FFFFFF89 03 FFFFFF89 05 10 03 26 FFFFFF89 04 04
   09 28 FFFFFF88 7E FFFFFF84 FFFFFF80 FFFFFF80 FFFFFFC2 00 29 10 03 26 FFFFFF89 06 04
   0A FFFFFF81 09 FFFFFF88 7E FFFFFF84 FFFFFF80 FFFFFF80 FFFFFFC2 00 29 08 07 72 FFFFFF88 7E
   FFFFFFC0 00 FFFFFF89 08 10 04 74 77 FFFFFF89 03 08 08 FFFFFF81 58 FFFFFF88 7E
   FFFFFFC0 00 FFFFFF89 0A 10 07 62 FFFFFF81 0F FFFFFF89 03 FFFFFF89 05 08 0A FFFFFF82
   39 FFFFFF88 7A FFFFFF81 FFFFFF80 FFFFFF84 40 FFFFFF89 0C 15 06 FFFFFF89 0D FFFFFF89 11 FFFFFF89
   13 14 04 FFFFFF89 0E FFFFFF89 14 10 05 15 FFFFFF82 3D FFFFFF89 0F 10 07
   62 FFFFFF81 0F FFFFFF89 10 FFFFFF89 12 10 03 26 FFFFFF89 11 04 09 28 FFFFFF89
   0B FFFFFF84 FFFFFF80 FFFFFF80 FFFFFFC2 00 29 10 03 26 FFFFFF89 13 04 0A FFFFFF81 09
   FFFFFF89 0B FFFFFF84 FFFFFF80 FFFFFF80 FFFFFFC2 00 29 08 08 FFFFFF82 43 FFFFFF89 0B FFFFFFC0 00
   FFFFFF89 15 10 08 FFFFFF81 60 FFFFFF88 24 FFFFFF89 10 FFFFFF89 12 06 06 FFFFFF89 17
   09 40 FFFFFF89 18 02 0B 4A 4D 61 70 57 72 61 70 70 65
   72 15 06 FFFFFF89 19 FFFFFF89 1C FFFFFF89 1E 13 0A FFFFFF89 16 0C FFFFFF89 1A
   FFFFFF89 1F 14 FFFFFF81 54 10 07 62 FFFFFF81 0F FFFFFF89 1B FFFFFF89 1D 10 03
   26 FFFFFF89 1C 04 09 28 FFFFFF89 16 FFFFFF84 FFFFFF80 FFFFFF80 FFFFFFC2 00 29 10 03
   26 FFFFFF89 1E 04 0A FFFFFF81 09 FFFFFF89 16 FFFFFF84 FFFFFF80 FFFFFF80 FFFFFFC2 00 29 10
   0A FFFFFF87 51 FFFFFF89 20 FFFFFF89 1B FFFFFF89 1D FFFFFF89 22 09 04 FFFFFF89 21 FFFFFF87
   52 02 12 4D 75 74 61 62 6C 65 4D 61 70 54 65 6D
   70 6C 61 74 65 10 08 FFFFFF81 60 FFFFFF89 16 FFFFFF89 1B FFFFFF89 1D 08
   0B FFFFFF81 58 FFFFFF89 16 FFFFFF82 FFFFFFCA FFFFFF80 FFFFFF84 00 FFFFFF89 24 15 02 FFFFFF89 25
   10 07 20 FFFFFF81 03 FFFFFF89 1B FFFFFF89 1D 08 0B FFFFFF81 5C FFFFFF89 16 FFFFFF82
   FFFFFF88 FFFFFFA0 FFFFFF80 04 FFFFFF89 25 08 07 19 FFFFFF89 16 FFFFFF84 00 FFFFFF89 28 14
   04 FFFFFF89 22 FFFFFF89 29 08 08 FFFFFF81 58 FFFFFF89 27 FFFFFFC0 00 FFFFFF89 25 08
   08 FFFFFF83 60 FFFFFF89 16 FFFFFF84 20 FFFFFF82 1B 08 08 FFFFFF85 39 FFFFFF89 16 FFFFFF84
   00 FFFFFF89 2C 14 04 FFFFFF89 2D FFFFFF89 2E 10 05 15 FFFFFF87 09 FFFFFF89 1D
   08 08 FFFFFF88 40 FFFFFF89 2B FFFFFFC0 00 FFFFFF89 1B 08 08 FFFFFF86 1A FFFFFF89 16
   FFFFFF84 00 FFFFFF89 30 14 04 FFFFFF89 31 FFFFFF89 32 0D 02 FFFFFF89 16 08 08
   FFFFFF89 33 FFFFFF89 2F FFFFFFC0 00 FFFFFF89 34 01 02 6B 76 10 07 15 FFFFFF89
   35 FFFFFF89 1B FFFFFF89 1D 09 03 FFFFFF89 36 04 02 06 54 75 70 6C
   65 32 08 08 FFFFFF87 6B FFFFFF89 16 FFFFFF84 00 FFFFFF89 38 14 04 FFFFFF89 31
   FFFFFF89 39 08 08 FFFFFF89 3A FFFFFF89 37 FFFFFFC0 00 FFFFFF89 1B 01 03 6B 65
   79 08 08 FFFFFF88 3D FFFFFF89 16 FFFFFF84 20 FFFFFF89 3C 14 06 FFFFFF89 2D FFFFFF89
   3D FFFFFF89 3E 08 08 FFFFFF88 40 FFFFFF89 3B FFFFFFC0 00 FFFFFF89 1B 08 08 FFFFFF88
   42 FFFFFF89 3B FFFFFFC0 00 FFFFFF89 1D 08 08 FFFFFF86 0E FFFFFF89 16 FFFFFF84 20 FFFFFF89
   40 14 06 FFFFFF86 10 FFFFFF89 41 FFFFFF89 42 08 08 FFFFFF88 40 FFFFFF89 3F FFFFFFC0
   00 FFFFFF89 1B 08 08 FFFFFF88 42 FFFFFF89 3F FFFFFFC0 00 FFFFFF89 1D 08 08 FFFFFF81
   70 FFFFFF89 16 FFFFFF84 20 FFFFFF89 44 14 04 FFFFFF89 2D FFFFFF89 45 08 08 FFFFFF88
   40 FFFFFF89 43 FFFFFFC0 00 FFFFFF89 1B 08 08 FFFFFF83 5C FFFFFF89 16 FFFFFF84 00 FFFFFF89
   47 15 02 FFFFFF89 48 12 05 FFFFFF89 49 0C FFFFFF89 4A 06 0B FFFFFF86 7F
   FFFFFF89 46 FFFFFF84 FFFFFF80 FFFFFF80 FFFFFF80 00 FFFFFF89 48 10 04 08 33 FFFFFF89 34 08
   0A FFFFFF87 02 FFFFFF89 49 FFFFFFC2 FFFFFF80 FFFFFF84 00 FFFFFF89 4C 15 02 FFFFFF89 4D 10
   04 20 23 FFFFFF89 4E 10 08 FFFFFF89 4F FFFFFF88 51 FFFFFF89 1B FFFFFF89 1D 0D
   02 FFFFFF88 53 08 08 FFFFFF86 2B FFFFFF89 16 FFFFFF84 20 FFFFFF86 2C 08 08 FFFFFF87
   76 FFFFFF89 16 FFFFFF84 20 FFFFFF89 52 15 02 FFFFFF89 22 08 0A FFFFFF81 73 FFFFFF89
   16 FFFFFF81 FFFFFF80 FFFFFF84 00 FFFFFF89 54 15 06 FFFFFF89 55 FFFFFF89 58 FFFFFF89 5A 14
   04 FFFFFF89 56 FFFFFF89 5B 10 08 FFFFFF81 60 FFFFFF89 16 FFFFFF89 57 FFFFFF89 59 10
   03 26 FFFFFF89 58 04 09 28 FFFFFF89 53 FFFFFF84 FFFFFF80 FFFFFF80 FFFFFFC2 00 29 10
   03 26 FFFFFF89 5A 04 0A FFFFFF81 09 FFFFFF89 53 FFFFFF84 FFFFFF80 FFFFFF80 FFFFFFC2 00 29
   08 0C FFFFFF89 5D FFFFFF81 58 FFFFFF89 53 FFFFFF90 FFFFFF80 FFFFFFC0 00 FFFFFF89 5C 10 07
   20 FFFFFF81 03 FFFFFF89 57 FFFFFF89 59 08 0A FFFFFF81 7C FFFFFF89 16 FFFFFF91 FFFFFF80 FFFFFF84
   00 FFFFFF89 5E 15 06 FFFFFF89 25 FFFFFF89 5F FFFFFF89 60 04 09 28 FFFFFF89 5D
   FFFFFF84 FFFFFF80 FFFFFF80 FFFFFFC2 00 29 04 0A FFFFFF81 09 FFFFFF89 5D FFFFFF84 FFFFFF80 FFFFFF80 FFFFFFC2
   00 29 08 0B FFFFFF82 15 FFFFFF89 16 FFFFFF84 FFFFFF80 FFFFFF80 FFFFFF84 20 FFFFFF82 16 08
   0B FFFFFF82 1A FFFFFF89 16 FFFFFF84 FFFFFF80 FFFFFF80 FFFFFF84 20 FFFFFF82 1B 08 0B FFFFFF82 1D
   FFFFFF89 16 FFFFFF84 FFFFFF80 FFFFFF80 FFFFFF84 20 FFFFFF89 64 14 03 2D FFFFFF89 65 08 0A
   FFFFFF82 13 FFFFFF89 63 FFFFFF81 FFFFFF80 FFFFFFC0 00 FFFFFF82 02 08 0B FFFFFF82 21 FFFFFF89 16
   FFFFFF84 FFFFFF80 FFFFFF80 FFFFFF84 20 FFFFFF89 67 14 04 FFFFFF81 65 FFFFFF89 68 08 09 FFFFFF82
   13 FFFFFF89 66 FFFFFF81 FFFFFF80 FFFFFFC0 00 2D 28 04 FFFFFF89 16 FFFFFF82 25 07 09
   FFFFFF89 6B 09 FFFFFF81 FFFFFF80 FFFFFF88 02 FFFFFF89 6C 01 0B 4A 4D 61 70 57
   72 61 70 70 65 72 10 04 FFFFFF81 60 FFFFFF89 6D 06 0A FFFFFF89 17
   09 FFFFFF84 FFFFFF81 FFFFFF80 FFFFFF88 02 FFFFFF89 6E 13 04 FFFFFF89 6D 0C 14 08 07
   19 FFFFFF89 6D FFFFFF84 00 FFFFFF89 70 14 02 FFFFFF89 6C 08 0A FFFFFF82 30 FFFFFF89
   6D FFFFFF81 FFFFFF80 FFFFFF84 40 FFFFFF89 72 15 06 FFFFFF89 73 FFFFFF89 76 FFFFFF89 78 14
   04 FFFFFF89 74 FFFFFF89 79 10 08 FFFFFF81 60 FFFFFF89 16 FFFFFF89 75 FFFFFF89 77 10
   03 26 FFFFFF89 76 04 09 28 FFFFFF89 71 FFFFFF84 FFFFFF80 FFFFFF80 FFFFFFC2 00 29 10
   03 26 FFFFFF89 78 04 0A FFFFFF81 09 FFFFFF89 71 FFFFFF84 FFFFFF80 FFFFFF80 FFFFFFC2 00 29
   08 08 FFFFFF81 58 FFFFFF89 71 FFFFFFC0 00 FFFFFF89 7A 10 07 20 FFFFFF81 03 FFFFFF89
   75 FFFFFF89 77 08 0A FFFFFF82 39 FFFFFF89 6D FFFFFF81 FFFFFF80 FFFFFF84 40 FFFFFF89 7C 15
   06 FFFFFF89 7D FFFFFF8A 01 FFFFFF8A 03 14 04 FFFFFF89 7E FFFFFF8A 04 10 05 15
   FFFFFF82 3D FFFFFF89 7F 10 07 20 FFFFFF81 03 FFFFFF8A 00 FFFFFF8A 02 10 03 26
   FFFFFF8A 01 04 09 28 FFFFFF89 7B FFFFFF84 FFFFFF80 FFFFFF80 FFFFFFC2 00 29 10 03 26
   FFFFFF8A 03 04 0A FFFFFF81 09 FFFFFF89 7B FFFFFF84 FFFFFF80 FFFFFF80 FFFFFFC2 00 29 08 08
   FFFFFF82 43 FFFFFF89 7B FFFFFFC0 00 FFFFFF8A 05 10 08 FFFFFF81 60 FFFFFF89 16 FFFFFF8A 00
   FFFFFF8A 02 
  InnerClass: 
   public #81= #78 of #80; //JSetWrapper=class scala/collection/JavaConversions$JSetWrapper of class scala/collection/JavaConversions
   public #84= #83 of #80; //JMapWrapper=class scala/collection/JavaConversions$JMapWrapper of class scala/collection/JavaConversions
   public #87= #86 of #80; //JListWrapper=class scala/collection/JavaConversions$JListWrapper of class scala/collection/JavaConversions
   public #90= #89 of #80; //IteratorWrapper=class scala/collection/JavaConversions$IteratorWrapper of class scala/collection/JavaConversions
   public #93= #92 of #80; //IterableWrapper=class scala/collection/JavaConversions$IterableWrapper of class scala/collection/JavaConversions
   public #96= #95 of #80; //JIterableWrapper=class scala/collection/JavaConversions$JIterableWrapper of class scala/collection/JavaConversions
   public #99= #98 of #80; //JIteratorWrapper=class scala/collection/JavaConversions$JIteratorWrapper of class scala/collection/JavaConversions
   public #102= #101 of #80; //MutableSetWrapper=class scala/collection/JavaConversions$MutableSetWrapper of class scala/collection/JavaConversions
   public #105= #104 of #80; //MutableMapWrapper=class scala/collection/JavaConversions$MutableMapWrapper of class scala/collection/JavaConversions
   public #108= #107 of #80; //JCollectionWrapper=class scala/collection/JavaConversions$JCollectionWrapper of class scala/collection/JavaConversions
   public #111= #110 of #80; //JEnumerationWrapper=class scala/collection/JavaConversions$JEnumerationWrapper of class scala/collection/JavaConversions
   public #114= #113 of #80; //MutableBufferWrapper=class scala/collection/JavaConversions$MutableBufferWrapper of class scala/collection/JavaConversions
  minor version: 0
  major version: 49
  Constant pool:
const #1 = Asciz	SourceFile;
const #2 = Asciz	JavaConversions.scala;
const #3 = Asciz	asMap;
const #4 = Asciz	(Ljava/util/Map;)Lscala/collection/mutable/Map;;
const #5 = Asciz	Code;
const #6 = Asciz	scala/collection/JavaConversions$;
const #7 = class	#6;	//  scala/collection/JavaConversions$
const #8 = Asciz	MODULE$;
const #9 = Asciz	Lscala/collection/JavaConversions$;;
const #10 = NameAndType	#8:#9;//  MODULE$:Lscala/collection/JavaConversions$;
const #11 = Field	#7.#10;	//  scala/collection/JavaConversions$.MODULE$:Lscala/collection/JavaConversions$;
const #12 = NameAndType	#3:#4;//  asMap:(Ljava/util/Map;)Lscala/collection/mutable/Map;
const #13 = Method	#7.#12;	//  scala/collection/JavaConversions$.asMap:(Ljava/util/Map;)Lscala/collection/mutable/Map;
const #14 = Asciz	<A:Ljava/lang/Object;B:Ljava/lang/Object;>(Ljava/util/Map<TA;TB;>;)Lscala/collection/mutable/Map<TA;TB;>;;
const #15 = Asciz	Signature;
const #16 = Asciz	asSet;
const #17 = Asciz	(Ljava/util/Set;)Lscala/collection/mutable/Set;;
const #18 = NameAndType	#16:#17;//  asSet:(Ljava/util/Set;)Lscala/collection/mutable/Set;
const #19 = Method	#7.#18;	//  scala/collection/JavaConversions$.asSet:(Ljava/util/Set;)Lscala/collection/mutable/Set;
const #20 = Asciz	<A:Ljava/lang/Object;>(Ljava/util/Set<TA;>;)Lscala/collection/mutable/Set<TA;>;;
const #21 = Asciz	asBuffer;
const #22 = Asciz	(Ljava/util/List;)Lscala/collection/mutable/Buffer;;
const #23 = NameAndType	#21:#22;//  asBuffer:(Ljava/util/List;)Lscala/collection/mutable/Buffer;
const #24 = Method	#7.#23;	//  scala/collection/JavaConversions$.asBuffer:(Ljava/util/List;)Lscala/collection/mutable/Buffer;
const #25 = Asciz	<A:Ljava/lang/Object;>(Ljava/util/List<TA;>;)Lscala/collection/mutable/Buffer<TA;>;;
const #26 = Asciz	asIterable;
const #27 = Asciz	(Ljava/util/Collection;)Lscala/collection/Iterable;;
const #28 = NameAndType	#26:#27;//  asIterable:(Ljava/util/Collection;)Lscala/collection/Iterable;
const #29 = Method	#7.#28;	//  scala/collection/JavaConversions$.asIterable:(Ljava/util/Collection;)Lscala/collection/Iterable;
const #30 = Asciz	<A:Ljava/lang/Object;>(Ljava/util/Collection<TA;>;)Lscala/collection/Iterable<TA;>;;
const #31 = Asciz	(Ljava/lang/Iterable;)Lscala/collection/Iterable;;
const #32 = NameAndType	#26:#31;//  asIterable:(Ljava/lang/Iterable;)Lscala/collection/Iterable;
const #33 = Method	#7.#32;	//  scala/collection/JavaConversions$.asIterable:(Ljava/lang/Iterable;)Lscala/collection/Iterable;
const #34 = Asciz	<A:Ljava/lang/Object;>(Ljava/lang/Iterable<TA;>;)Lscala/collection/Iterable<TA;>;;
const #35 = Asciz	asIterator;
const #36 = Asciz	(Ljava/util/Enumeration;)Lscala/collection/Iterator;;
const #37 = NameAndType	#35:#36;//  asIterator:(Ljava/util/Enumeration;)Lscala/collection/Iterator;
const #38 = Method	#7.#37;	//  scala/collection/JavaConversions$.asIterator:(Ljava/util/Enumeration;)Lscala/collection/Iterator;
const #39 = Asciz	<A:Ljava/lang/Object;>(Ljava/util/Enumeration<TA;>;)Lscala/collection/Iterator<TA;>;;
const #40 = Asciz	(Ljava/util/Iterator;)Lscala/collection/Iterator;;
const #41 = NameAndType	#35:#40;//  asIterator:(Ljava/util/Iterator;)Lscala/collection/Iterator;
const #42 = Method	#7.#41;	//  scala/collection/JavaConversions$.asIterator:(Ljava/util/Iterator;)Lscala/collection/Iterator;
const #43 = Asciz	<A:Ljava/lang/Object;>(Ljava/util/Iterator<TA;>;)Lscala/collection/Iterator<TA;>;;
const #44 = Asciz	(Lscala/collection/mutable/Map;Lscala/reflect/Manifest;)Ljava/util/Map;;
const #45 = NameAndType	#3:#44;//  asMap:(Lscala/collection/mutable/Map;Lscala/reflect/Manifest;)Ljava/util/Map;
const #46 = Method	#7.#45;	//  scala/collection/JavaConversions$.asMap:(Lscala/collection/mutable/Map;Lscala/reflect/Manifest;)Ljava/util/Map;
const #47 = Asciz	<A:Ljava/lang/Object;B:Ljava/lang/Object;>(Lscala/collection/mutable/Map<TA;TB;>;Lscala/reflect/Manifest<TA;>;)Ljava/util/Map<TA;TB;>;;
const #48 = Asciz	(Lscala/collection/mutable/Set;Lscala/reflect/Manifest;)Ljava/util/Set;;
const #49 = NameAndType	#16:#48;//  asSet:(Lscala/collection/mutable/Set;Lscala/reflect/Manifest;)Ljava/util/Set;
const #50 = Method	#7.#49;	//  scala/collection/JavaConversions$.asSet:(Lscala/collection/mutable/Set;Lscala/reflect/Manifest;)Ljava/util/Set;
const #51 = Asciz	<A:Ljava/lang/Object;>(Lscala/collection/mutable/Set<TA;>;Lscala/reflect/Manifest<TA;>;)Ljava/util/Set<TA;>;;
const #52 = Asciz	asList;
const #53 = Asciz	(Lscala/collection/mutable/Buffer;)Ljava/util/List;;
const #54 = NameAndType	#52:#53;//  asList:(Lscala/collection/mutable/Buffer;)Ljava/util/List;
const #55 = Method	#7.#54;	//  scala/collection/JavaConversions$.asList:(Lscala/collection/mutable/Buffer;)Ljava/util/List;
const #56 = Asciz	<A:Ljava/lang/Object;>(Lscala/collection/mutable/Buffer<TA;>;)Ljava/util/List<TA;>;;
const #57 = Asciz	asCollection;
const #58 = Asciz	(Lscala/collection/Iterable;)Ljava/util/Collection;;
const #59 = NameAndType	#57:#58;//  asCollection:(Lscala/collection/Iterable;)Ljava/util/Collection;
const #60 = Method	#7.#59;	//  scala/collection/JavaConversions$.asCollection:(Lscala/collection/Iterable;)Ljava/util/Collection;
const #61 = Asciz	<A:Ljava/lang/Object;>(Lscala/collection/Iterable<TA;>;)Ljava/util/Collection<TA;>;;
const #62 = Asciz	(Lscala/collection/Iterable;)Ljava/lang/Iterable;;
const #63 = NameAndType	#26:#62;//  asIterable:(Lscala/collection/Iterable;)Ljava/lang/Iterable;
const #64 = Method	#7.#63;	//  scala/collection/JavaConversions$.asIterable:(Lscala/collection/Iterable;)Ljava/lang/Iterable;
const #65 = Asciz	<A:Ljava/lang/Object;>(Lscala/collection/Iterable<TA;>;)Ljava/lang/Iterable<TA;>;;
const #66 = Asciz	asEnumeration;
const #67 = Asciz	(Lscala/collection/Iterator;)Ljava/util/Enumeration;;
const #68 = NameAndType	#66:#67;//  asEnumeration:(Lscala/collection/Iterator;)Ljava/util/Enumeration;
const #69 = Method	#7.#68;	//  scala/collection/JavaConversions$.asEnumeration:(Lscala/collection/Iterator;)Ljava/util/Enumeration;
const #70 = Asciz	<A:Ljava/lang/Object;>(Lscala/collection/Iterator<TA;>;)Ljava/util/Enumeration<TA;>;;
const #71 = Asciz	(Lscala/collection/Iterator;)Ljava/util/Iterator;;
const #72 = NameAndType	#35:#71;//  asIterator:(Lscala/collection/Iterator;)Ljava/util/Iterator;
const #73 = Method	#7.#72;	//  scala/collection/JavaConversions$.asIterator:(Lscala/collection/Iterator;)Ljava/util/Iterator;
const #74 = Asciz	<A:Ljava/lang/Object;>(Lscala/collection/Iterator<TA;>;)Ljava/util/Iterator<TA;>;;
const #75 = Asciz	ScalaSig;
const #76 = Asciz	InnerClasses;
const #77 = Asciz	scala/collection/JavaConversions$JSetWrapper;
const #78 = class	#77;	//  scala/collection/JavaConversions$JSetWrapper
const #79 = Asciz	scala/collection/JavaConversions;
const #80 = class	#79;	//  scala/collection/JavaConversions
const #81 = Asciz	JSetWrapper;
const #82 = Asciz	scala/collection/JavaConversions$JMapWrapper;
const #83 = class	#82;	//  scala/collection/JavaConversions$JMapWrapper
const #84 = Asciz	JMapWrapper;
const #85 = Asciz	scala/collection/JavaConversions$JListWrapper;
const #86 = class	#85;	//  scala/collection/JavaConversions$JListWrapper
const #87 = Asciz	JListWrapper;
const #88 = Asciz	scala/collection/JavaConversions$IteratorWrapper;
const #89 = class	#88;	//  scala/collection/JavaConversions$IteratorWrapper
const #90 = Asciz	IteratorWrapper;
const #91 = Asciz	scala/collection/JavaConversions$IterableWrapper;
const #92 = class	#91;	//  scala/collection/JavaConversions$IterableWrapper
const #93 = Asciz	IterableWrapper;
const #94 = Asciz	scala/collection/JavaConversions$JIterableWrapper;
const #95 = class	#94;	//  scala/collection/JavaConversions$JIterableWrapper
const #96 = Asciz	JIterableWrapper;
const #97 = Asciz	scala/collection/JavaConversions$JIteratorWrapper;
const #98 = class	#97;	//  scala/collection/JavaConversions$JIteratorWrapper
const #99 = Asciz	JIteratorWrapper;
const #100 = Asciz	scala/collection/JavaConversions$MutableSetWrapper;
const #101 = class	#100;	//  scala/collection/JavaConversions$MutableSetWrapper
const #102 = Asciz	MutableSetWrapper;
const #103 = Asciz	scala/collection/JavaConversions$MutableMapWrapper;
const #104 = class	#103;	//  scala/collection/JavaConversions$MutableMapWrapper
const #105 = Asciz	MutableMapWrapper;
const #106 = Asciz	scala/collection/JavaConversions$JCollectionWrapper;
const #107 = class	#106;	//  scala/collection/JavaConversions$JCollectionWrapper
const #108 = Asciz	JCollectionWrapper;
const #109 = Asciz	scala/collection/JavaConversions$JEnumerationWrapper;
const #110 = class	#109;	//  scala/collection/JavaConversions$JEnumerationWrapper
const #111 = Asciz	JEnumerationWrapper;
const #112 = Asciz	scala/collection/JavaConversions$MutableBufferWrapper;
const #113 = class	#112;	//  scala/collection/JavaConversions$MutableBufferWrapper
const #114 = Asciz	MutableBufferWrapper;
const #115 = Asciz	java/lang/Object;
const #116 = class	#115;	//  java/lang/Object

{
public static final scala.collection.mutable.Map asMap(java.util.Map);
  Code:
   Stack=2, Locals=1, Args_size=1
   0:	getstatic	#11; //Field scala/collection/JavaConversions$.MODULE$:Lscala/collection/JavaConversions$;
   3:	aload_0
   4:	invokevirtual	#13; //Method scala/collection/JavaConversions$.asMap:(Ljava/util/Map;)Lscala/collection/mutable/Map;
   7:	areturn
  Signature: length = 0x2
   00 0E 

public static final scala.collection.mutable.Set asSet(java.util.Set);
  Code:
   Stack=2, Locals=1, Args_size=1
   0:	getstatic	#11; //Field scala/collection/JavaConversions$.MODULE$:Lscala/collection/JavaConversions$;
   3:	aload_0
   4:	invokevirtual	#19; //Method scala/collection/JavaConversions$.asSet:(Ljava/util/Set;)Lscala/collection/mutable/Set;
   7:	areturn
  Signature: length = 0x2
   00 14 

public static final scala.collection.mutable.Buffer asBuffer(java.util.List);
  Code:
   Stack=2, Locals=1, Args_size=1
   0:	getstatic	#11; //Field scala/collection/JavaConversions$.MODULE$:Lscala/collection/JavaConversions$;
   3:	aload_0
   4:	invokevirtual	#24; //Method scala/collection/JavaConversions$.asBuffer:(Ljava/util/List;)Lscala/collection/mutable/Buffer;
   7:	areturn
  Signature: length = 0x2
   00 19 

public static final scala.collection.Iterable asIterable(java.util.Collection);
  Code:
   Stack=2, Locals=1, Args_size=1
   0:	getstatic	#11; //Field scala/collection/JavaConversions$.MODULE$:Lscala/collection/JavaConversions$;
   3:	aload_0
   4:	invokevirtual	#29; //Method scala/collection/JavaConversions$.asIterable:(Ljava/util/Collection;)Lscala/collection/Iterable;
   7:	areturn
  Signature: length = 0x2
   00 1E 

public static final scala.collection.Iterable asIterable(java.lang.Iterable);
  Code:
   Stack=2, Locals=1, Args_size=1
   0:	getstatic	#11; //Field scala/collection/JavaConversions$.MODULE$:Lscala/collection/JavaConversions$;
   3:	aload_0
   4:	invokevirtual	#33; //Method scala/collection/JavaConversions$.asIterable:(Ljava/lang/Iterable;)Lscala/collection/Iterable;
   7:	areturn
  Signature: length = 0x2
   00 22 

public static final scala.collection.Iterator asIterator(java.util.Enumeration);
  Code:
   Stack=2, Locals=1, Args_size=1
   0:	getstatic	#11; //Field scala/collection/JavaConversions$.MODULE$:Lscala/collection/JavaConversions$;
   3:	aload_0
   4:	invokevirtual	#38; //Method scala/collection/JavaConversions$.asIterator:(Ljava/util/Enumeration;)Lscala/collection/Iterator;
   7:	areturn
  Signature: length = 0x2
   00 27 

public static final scala.collection.Iterator asIterator(java.util.Iterator);
  Code:
   Stack=2, Locals=1, Args_size=1
   0:	getstatic	#11; //Field scala/collection/JavaConversions$.MODULE$:Lscala/collection/JavaConversions$;
   3:	aload_0
   4:	invokevirtual	#42; //Method scala/collection/JavaConversions$.asIterator:(Ljava/util/Iterator;)Lscala/collection/Iterator;
   7:	areturn
  Signature: length = 0x2
   00 2B 

public static final java.util.Map asMap(scala.collection.mutable.Map, scala.reflect.Manifest);
  Code:
   Stack=3, Locals=2, Args_size=2
   0:	getstatic	#11; //Field scala/collection/JavaConversions$.MODULE$:Lscala/collection/JavaConversions$;
   3:	aload_0
   4:	aload_1
   5:	invokevirtual	#46; //Method scala/collection/JavaConversions$.asMap:(Lscala/collection/mutable/Map;Lscala/reflect/Manifest;)Ljava/util/Map;
   8:	areturn
  Signature: length = 0x2
   00 2F 

public static final java.util.Set asSet(scala.collection.mutable.Set, scala.reflect.Manifest);
  Code:
   Stack=3, Locals=2, Args_size=2
   0:	getstatic	#11; //Field scala/collection/JavaConversions$.MODULE$:Lscala/collection/JavaConversions$;
   3:	aload_0
   4:	aload_1
   5:	invokevirtual	#50; //Method scala/collection/JavaConversions$.asSet:(Lscala/collection/mutable/Set;Lscala/reflect/Manifest;)Ljava/util/Set;
   8:	areturn
  Signature: length = 0x2
   00 33 

public static final java.util.List asList(scala.collection.mutable.Buffer);
  Code:
   Stack=2, Locals=1, Args_size=1
   0:	getstatic	#11; //Field scala/collection/JavaConversions$.MODULE$:Lscala/collection/JavaConversions$;
   3:	aload_0
   4:	invokevirtual	#55; //Method scala/collection/JavaConversions$.asList:(Lscala/collection/mutable/Buffer;)Ljava/util/List;
   7:	areturn
  Signature: length = 0x2
   00 38 

public static final java.util.Collection asCollection(scala.collection.Iterable);
  Code:
   Stack=2, Locals=1, Args_size=1
   0:	getstatic	#11; //Field scala/collection/JavaConversions$.MODULE$:Lscala/collection/JavaConversions$;
   3:	aload_0
   4:	invokevirtual	#60; //Method scala/collection/JavaConversions$.asCollection:(Lscala/collection/Iterable;)Ljava/util/Collection;
   7:	areturn
  Signature: length = 0x2
   00 3D 

public static final java.lang.Iterable asIterable(scala.collection.Iterable);
  Code:
   Stack=2, Locals=1, Args_size=1
   0:	getstatic	#11; //Field scala/collection/JavaConversions$.MODULE$:Lscala/collection/JavaConversions$;
   3:	aload_0
   4:	invokevirtual	#64; //Method scala/collection/JavaConversions$.asIterable:(Lscala/collection/Iterable;)Ljava/lang/Iterable;
   7:	areturn
  Signature: length = 0x2
   00 41 

public static final java.util.Enumeration asEnumeration(scala.collection.Iterator);
  Code:
   Stack=2, Locals=1, Args_size=1
   0:	getstatic	#11; //Field scala/collection/JavaConversions$.MODULE$:Lscala/collection/JavaConversions$;
   3:	aload_0
   4:	invokevirtual	#69; //Method scala/collection/JavaConversions$.asEnumeration:(Lscala/collection/Iterator;)Ljava/util/Enumeration;
   7:	areturn
  Signature: length = 0x2
   00 46 

public static final java.util.Iterator asIterator(scala.collection.Iterator);
  Code:
   Stack=2, Locals=1, Args_size=1
   0:	getstatic	#11; //Field scala/collection/JavaConversions$.MODULE$:Lscala/collection/JavaConversions$;
   3:	aload_0
   4:	invokevirtual	#73; //Method scala/collection/JavaConversions$.asIterator:(Lscala/collection/Iterator;)Ljava/util/Iterator;
   7:	areturn
  Signature: length = 0x2
   00 4A 

}

