Compiled from "LinearSeqLike.scala"
public abstract class scala.collection.LinearSeqLike$class extends java.lang.Object
  SourceFile: "LinearSeqLike.scala"
  Scala: length = 0x
   
  InnerClass: 
   public final #216= #200 of #40; //$anon$1=class scala/collection/LinearSeqLike$$anon$1 of class scala/collection/LinearSeqLike
  minor version: 0
  major version: 49
  Constant pool:
const #1 = Asciz	SourceFile;
const #2 = Asciz	LinearSeqLike.scala;
const #3 = Asciz	$init$;
const #4 = Asciz	(Lscala/collection/LinearSeqLike;)V;
const #5 = Asciz	Code;
const #6 = Asciz	LineNumberTable;
const #7 = Asciz	$this;
const #8 = Asciz	Lscala/collection/LinearSeqLike;;
const #9 = Asciz	LocalVariableTable;
const #10 = Asciz	lastIndexWhere;
const #11 = Asciz	(Lscala/collection/LinearSeqLike;Lscala/Function1;I)I;
const #12 = Asciz	scala/collection/IterableLike;
const #13 = class	#12;	//  scala/collection/IterableLike
const #14 = Asciz	isEmpty;
const #15 = Asciz	()Z;
const #16 = NameAndType	#14:#15;//  isEmpty:()Z
const #17 = InterfaceMethod	#13.#16;	//  scala/collection/IterableLike.isEmpty:()Z
const #18 = Asciz	head;
const #19 = Asciz	()Ljava/lang/Object;;
const #20 = NameAndType	#18:#19;//  head:()Ljava/lang/Object;
const #21 = InterfaceMethod	#13.#20;	//  scala/collection/IterableLike.head:()Ljava/lang/Object;
const #22 = Asciz	scala/Function1;
const #23 = class	#22;	//  scala/Function1
const #24 = Asciz	apply;
const #25 = Asciz	(Ljava/lang/Object;)Ljava/lang/Object;;
const #26 = NameAndType	#24:#25;//  apply:(Ljava/lang/Object;)Ljava/lang/Object;
const #27 = InterfaceMethod	#23.#26;	//  scala/Function1.apply:(Ljava/lang/Object;)Ljava/lang/Object;
const #28 = Asciz	scala/runtime/BoxesRunTime;
const #29 = class	#28;	//  scala/runtime/BoxesRunTime
const #30 = Asciz	unboxToBoolean;
const #31 = Asciz	(Ljava/lang/Object;)Z;
const #32 = NameAndType	#30:#31;//  unboxToBoolean:(Ljava/lang/Object;)Z
const #33 = Method	#29.#32;	//  scala/runtime/BoxesRunTime.unboxToBoolean:(Ljava/lang/Object;)Z
const #34 = Asciz	scala/collection/TraversableLike;
const #35 = class	#34;	//  scala/collection/TraversableLike
const #36 = Asciz	tail;
const #37 = NameAndType	#36:#19;//  tail:()Ljava/lang/Object;
const #38 = InterfaceMethod	#35.#37;	//  scala/collection/TraversableLike.tail:()Ljava/lang/Object;
const #39 = Asciz	scala/collection/LinearSeqLike;
const #40 = class	#39;	//  scala/collection/LinearSeqLike
const #41 = Asciz	p;
const #42 = Asciz	Lscala/Function1;;
const #43 = Asciz	end;
const #44 = Asciz	I;
const #45 = Asciz	i;
const #46 = Asciz	these;
const #47 = Asciz	last;
const #48 = Asciz	indexWhere;
const #49 = Asciz	drop;
const #50 = Asciz	(I)Lscala/collection/LinearSeqLike;;
const #51 = NameAndType	#49:#50;//  drop:(I)Lscala/collection/LinearSeqLike;
const #52 = InterfaceMethod	#40.#51;	//  scala/collection/LinearSeqLike.drop:(I)Lscala/collection/LinearSeqLike;
const #53 = Asciz	from;
const #54 = Asciz	segmentLength;
const #55 = Asciz	isDefinedAt;
const #56 = Asciz	(Lscala/collection/LinearSeqLike;I)Z;
const #57 = Asciz	lengthCompare;
const #58 = Asciz	(I)I;
const #59 = NameAndType	#57:#58;//  lengthCompare:(I)I
const #60 = InterfaceMethod	#40.#59;	//  scala/collection/LinearSeqLike.lengthCompare:(I)I
const #61 = Asciz	x;
const #62 = Asciz	(Lscala/collection/LinearSeqLike;I)I;
const #63 = Asciz	len;
const #64 = Asciz	sameElements;
const #65 = Asciz	(Lscala/collection/LinearSeqLike;Lscala/collection/Iterable;)Z;
const #66 = Asciz	scala/collection/LinearSeq;
const #67 = class	#66;	//  scala/collection/LinearSeq
const #68 = Asciz	java/lang/Number;
const #69 = class	#68;	//  java/lang/Number
const #70 = Asciz	java/lang/Character;
const #71 = class	#70;	//  java/lang/Character
const #72 = Asciz	equals2;
const #73 = Asciz	(Ljava/lang/Object;Ljava/lang/Object;)Z;
const #74 = NameAndType	#72:#73;//  equals2:(Ljava/lang/Object;Ljava/lang/Object;)Z
const #75 = Method	#29.#74;	//  scala/runtime/BoxesRunTime.equals2:(Ljava/lang/Object;Ljava/lang/Object;)Z
const #76 = Asciz	java/lang/Object;
const #77 = class	#76;	//  java/lang/Object
const #78 = Asciz	equals;
const #79 = NameAndType	#78:#31;//  equals:(Ljava/lang/Object;)Z
const #80 = Method	#77.#79;	//  java/lang/Object.equals:(Ljava/lang/Object;)Z
const #81 = Asciz	scala/MatchError;
const #82 = class	#81;	//  scala/MatchError
const #83 = Asciz	toString;
const #84 = Asciz	()Ljava/lang/String;;
const #85 = NameAndType	#83:#84;//  toString:()Ljava/lang/String;
const #86 = InterfaceMethod	#35.#85;	//  scala/collection/TraversableLike.toString:()Ljava/lang/String;
const #87 = Asciz	<init>;
const #88 = Asciz	(Ljava/lang/String;)V;
const #89 = NameAndType	#87:#88;//  "<init>":(Ljava/lang/String;)V
const #90 = Method	#82.#89;	//  scala/MatchError."<init>":(Ljava/lang/String;)V
const #91 = Asciz	scala$collection$LinearSeqLike$$super$sameElements;
const #92 = Asciz	(Lscala/collection/Iterable;)Z;
const #93 = NameAndType	#91:#92;//  scala$collection$LinearSeqLike$$super$sameElements:(Lscala/collection/Iterable;)Z
const #94 = InterfaceMethod	#40.#93;	//  scala/collection/LinearSeqLike.scala$collection$LinearSeqLike$$super$sameElements:(Lscala/collection/Iterable;)Z
const #95 = Asciz	that;
const #96 = Asciz	Lscala/collection/Iterable;;
const #97 = Asciz	temp2;
const #98 = Asciz	Lscala/collection/LinearSeq;;
const #99 = Asciz	x0;
const #100 = Asciz	Ljava/lang/Object;;
const #101 = Asciz	y0;
const #102 = Asciz	those;
const #103 = Asciz	span;
const #104 = Asciz	(Lscala/collection/LinearSeqLike;Lscala/Function1;)Lscala/Tuple2;;
const #105 = Asciz	repr;
const #106 = NameAndType	#105:#19;//  repr:()Ljava/lang/Object;
const #107 = InterfaceMethod	#35.#106;	//  scala/collection/TraversableLike.repr:()Ljava/lang/Object;
const #108 = Asciz	newBuilder;
const #109 = Asciz	()Lscala/collection/mutable/Builder;;
const #110 = NameAndType	#108:#109;//  newBuilder:()Lscala/collection/mutable/Builder;
const #111 = InterfaceMethod	#35.#110;	//  scala/collection/TraversableLike.newBuilder:()Lscala/collection/mutable/Builder;
const #112 = Asciz	scala/collection/mutable/Builder;
const #113 = class	#112;	//  scala/collection/mutable/Builder
const #114 = Asciz	$plus$eq;
const #115 = Asciz	(Ljava/lang/Object;)Lscala/collection/mutable/Builder;;
const #116 = NameAndType	#114:#115;//  $plus$eq:(Ljava/lang/Object;)Lscala/collection/mutable/Builder;
const #117 = InterfaceMethod	#113.#116;	//  scala/collection/mutable/Builder.$plus$eq:(Ljava/lang/Object;)Lscala/collection/mutable/Builder;
const #118 = Asciz	scala/Tuple2;
const #119 = class	#118;	//  scala/Tuple2
const #120 = Asciz	result;
const #121 = NameAndType	#120:#19;//  result:()Ljava/lang/Object;
const #122 = InterfaceMethod	#113.#121;	//  scala/collection/mutable/Builder.result:()Ljava/lang/Object;
const #123 = Asciz	(Ljava/lang/Object;Ljava/lang/Object;)V;
const #124 = NameAndType	#87:#123;//  "<init>":(Ljava/lang/Object;Ljava/lang/Object;)V
const #125 = Method	#119.#124;	//  scala/Tuple2."<init>":(Ljava/lang/Object;Ljava/lang/Object;)V
const #126 = Asciz	b;
const #127 = Asciz	Lscala/collection/mutable/Builder;;
const #128 = Asciz	takeWhile;
const #129 = Asciz	(Lscala/collection/LinearSeqLike;Lscala/Function1;)Lscala/collection/LinearSeqLike;;
const #130 = Asciz	slice;
const #131 = Asciz	(Lscala/collection/LinearSeqLike;II)Lscala/collection/LinearSeqLike;;
const #132 = Asciz	until;
const #133 = Asciz	dropRight;
const #134 = Asciz	(Lscala/collection/LinearSeqLike;I)Lscala/collection/LinearSeqLike;;
const #135 = Asciz	n;
const #136 = Asciz	lead;
const #137 = Asciz	count;
const #138 = Asciz	take;
const #139 = Asciz	(Lscala/collection/LinearSeqLike;)Ljava/lang/Object;;
const #140 = Asciz	java/util/NoSuchElementException;
const #141 = class	#140;	//  java/util/NoSuchElementException
const #142 = Asciz	()V;
const #143 = NameAndType	#87:#142;//  "<init>":()V
const #144 = Method	#141.#143;	//  java/util/NoSuchElementException."<init>":()V
const #145 = Asciz	nx;
const #146 = Asciz	reduceRight;
const #147 = Asciz	(Lscala/collection/LinearSeqLike;Lscala/Function2;)Ljava/lang/Object;;
const #148 = Asciz	java/lang/UnsupportedOperationException;
const #149 = class	#148;	//  java/lang/UnsupportedOperationException
const #150 = Asciz	Nil.reduceRight;
const #151 = String	#150;	//  Nil.reduceRight
const #152 = Method	#149.#89;	//  java/lang/UnsupportedOperationException."<init>":(Ljava/lang/String;)V
const #153 = Asciz	(Lscala/Function2;)Ljava/lang/Object;;
const #154 = NameAndType	#146:#153;//  reduceRight:(Lscala/Function2;)Ljava/lang/Object;
const #155 = InterfaceMethod	#40.#154;	//  scala/collection/LinearSeqLike.reduceRight:(Lscala/Function2;)Ljava/lang/Object;
const #156 = Asciz	scala/Function2;
const #157 = class	#156;	//  scala/Function2
const #158 = Asciz	(Ljava/lang/Object;Ljava/lang/Object;)Ljava/lang/Object;;
const #159 = NameAndType	#24:#158;//  apply:(Ljava/lang/Object;Ljava/lang/Object;)Ljava/lang/Object;
const #160 = InterfaceMethod	#157.#159;	//  scala/Function2.apply:(Ljava/lang/Object;Ljava/lang/Object;)Ljava/lang/Object;
const #161 = Asciz	op;
const #162 = Asciz	Lscala/Function2;;
const #163 = Asciz	reduceLeft;
const #164 = Asciz	empty.reduceLeft;
const #165 = String	#164;	//  empty.reduceLeft
const #166 = Asciz	foldLeft;
const #167 = Asciz	(Ljava/lang/Object;Lscala/Function2;)Ljava/lang/Object;;
const #168 = NameAndType	#166:#167;//  foldLeft:(Ljava/lang/Object;Lscala/Function2;)Ljava/lang/Object;
const #169 = InterfaceMethod	#40.#168;	//  scala/collection/LinearSeqLike.foldLeft:(Ljava/lang/Object;Lscala/Function2;)Ljava/lang/Object;
const #170 = Asciz	f;
const #171 = Asciz	foldRight;
const #172 = Asciz	(Lscala/collection/LinearSeqLike;Ljava/lang/Object;Lscala/Function2;)Ljava/lang/Object;;
const #173 = NameAndType	#171:#167;//  foldRight:(Ljava/lang/Object;Lscala/Function2;)Ljava/lang/Object;
const #174 = InterfaceMethod	#40.#173;	//  scala/collection/LinearSeqLike.foldRight:(Ljava/lang/Object;Lscala/Function2;)Ljava/lang/Object;
const #175 = Asciz	z;
const #176 = Asciz	acc;
const #177 = Asciz	find;
const #178 = Asciz	(Lscala/collection/LinearSeqLike;Lscala/Function1;)Lscala/Option;;
const #179 = Asciz	scala/None$;
const #180 = class	#179;	//  scala/None$
const #181 = Asciz	MODULE$;
const #182 = Asciz	Lscala/None$;;
const #183 = NameAndType	#181:#182;//  MODULE$:Lscala/None$;
const #184 = Field	#180.#183;	//  scala/None$.MODULE$:Lscala/None$;
const #185 = Asciz	scala/Some;
const #186 = class	#185;	//  scala/Some
const #187 = Asciz	(Ljava/lang/Object;)V;
const #188 = NameAndType	#87:#187;//  "<init>":(Ljava/lang/Object;)V
const #189 = Method	#186.#188;	//  scala/Some."<init>":(Ljava/lang/Object;)V
const #190 = Asciz	(Lscala/collection/LinearSeqLike;Lscala/Function1;)I;
const #191 = Asciz	cnt;
const #192 = Asciz	exists;
const #193 = Asciz	(Lscala/collection/LinearSeqLike;Lscala/Function1;)Z;
const #194 = Asciz	forall;
const #195 = Asciz	foreach;
const #196 = Asciz	(Lscala/collection/LinearSeqLike;Lscala/Function1;)V;
const #197 = Asciz	iterator;
const #198 = Asciz	(Lscala/collection/LinearSeqLike;)Lscala/collection/Iterator;;
const #199 = Asciz	scala/collection/LinearSeqLike$$anon$1;
const #200 = class	#199;	//  scala/collection/LinearSeqLike$$anon$1
const #201 = NameAndType	#87:#4;//  "<init>":(Lscala/collection/LinearSeqLike;)V
const #202 = Method	#200.#201;	//  scala/collection/LinearSeqLike$$anon$1."<init>":(Lscala/collection/LinearSeqLike;)V
const #203 = Asciz	(Lscala/collection/LinearSeqLike;I)Ljava/lang/Object;;
const #204 = Asciz	java/lang/IndexOutOfBoundsException;
const #205 = class	#204;	//  java/lang/IndexOutOfBoundsException
const #206 = Method	#205.#143;	//  java/lang/IndexOutOfBoundsException."<init>":()V
const #207 = Asciz	rest;
const #208 = Asciz	length;
const #209 = Asciz	(Lscala/collection/LinearSeqLike;)I;
const #210 = Asciz	toCollection;
const #211 = Asciz	(Lscala/collection/LinearSeqLike;Lscala/collection/LinearSeqLike;)Lscala/collection/LinearSeq;;
const #212 = Asciz	thisCollection;
const #213 = Asciz	(Lscala/collection/LinearSeqLike;)Lscala/collection/LinearSeq;;
const #214 = Asciz	Scala;
const #215 = Asciz	InnerClasses;
const #216 = Asciz	$anon$1;
const #217 = Asciz	scala/collection/LinearSeqLike$class;
const #218 = class	#217;	//  scala/collection/LinearSeqLike$class

{
public static void $init$(scala.collection.LinearSeqLike);
  Code:
   Stack=0, Locals=1, Args_size=1
   0:	return
  LineNumberTable: 
   line 45: 0

  LocalVariableTable: 
   Start  Length  Slot  Name   Signature
   0      1      0    $this       Lscala/collection/LinearSeqLike;


public static int lastIndexWhere(scala.collection.LinearSeqLike, scala.Function1, int);
  Code:
   Stack=2, Locals=6, Args_size=3
   0:	iconst_0
   1:	istore_3
   2:	aload_0
   3:	astore	4
   5:	iconst_m1
   6:	istore	5
   8:	aload	4
   10:	invokeinterface	#17,  1; //InterfaceMethod scala/collection/IterableLike.isEmpty:()Z
   15:	ifne	64
   18:	iload_3
   19:	iload_2
   20:	if_icmpgt	64
   23:	aload_1
   24:	aload	4
   26:	invokeinterface	#21,  1; //InterfaceMethod scala/collection/IterableLike.head:()Ljava/lang/Object;
   31:	invokeinterface	#27,  2; //InterfaceMethod scala/Function1.apply:(Ljava/lang/Object;)Ljava/lang/Object;
   36:	invokestatic	#33; //Method scala/runtime/BoxesRunTime.unboxToBoolean:(Ljava/lang/Object;)Z
   39:	ifeq	45
   42:	iload_3
   43:	istore	5
   45:	aload	4
   47:	invokeinterface	#38,  1; //InterfaceMethod scala/collection/TraversableLike.tail:()Ljava/lang/Object;
   52:	checkcast	#40; //class scala/collection/LinearSeqLike
   55:	astore	4
   57:	iload_3
   58:	iconst_1
   59:	iadd
   60:	istore_3
   61:	goto	8
   64:	iload	5
   66:	ireturn
  LineNumberTable: 
   line 317: 0
   line 318: 2
   line 319: 5
   line 320: 8
   line 321: 23
   line 322: 45
   line 323: 57
   line 325: 64

  LocalVariableTable: 
   Start  Length  Slot  Name   Signature
   0      67      0    $this       Lscala/collection/LinearSeqLike;
   0      67      1    p       Lscala/Function1;
   0      67      2    end       I
   2      64      3    i       I
   5      61      4    these       Lscala/collection/LinearSeqLike;
   8      58      5    last       I


public static int indexWhere(scala.collection.LinearSeqLike, scala.Function1, int);
  Code:
   Stack=2, Locals=5, Args_size=3
   0:	iload_2
   1:	istore_3
   2:	aload_0
   3:	iload_2
   4:	invokeinterface	#52,  2; //InterfaceMethod scala/collection/LinearSeqLike.drop:(I)Lscala/collection/LinearSeqLike;
   9:	astore	4
   11:	aload	4
   13:	invokeinterface	#17,  1; //InterfaceMethod scala/collection/IterableLike.isEmpty:()Z
   18:	ifne	40
   21:	aload_1
   22:	aload	4
   24:	invokeinterface	#21,  1; //InterfaceMethod scala/collection/IterableLike.head:()Ljava/lang/Object;
   29:	invokeinterface	#27,  2; //InterfaceMethod scala/Function1.apply:(Ljava/lang/Object;)Ljava/lang/Object;
   34:	invokestatic	#33; //Method scala/runtime/BoxesRunTime.unboxToBoolean:(Ljava/lang/Object;)Z
   37:	ifeq	56
   40:	aload	4
   42:	invokeinterface	#17,  1; //InterfaceMethod scala/collection/IterableLike.isEmpty:()Z
   47:	ifeq	54
   50:	iconst_m1
   51:	goto	55
   54:	iload_3
   55:	ireturn
   56:	iload_3
   57:	iconst_1
   58:	iadd
   59:	istore_3
   60:	aload	4
   62:	invokeinterface	#38,  1; //InterfaceMethod scala/collection/TraversableLike.tail:()Ljava/lang/Object;
   67:	checkcast	#40; //class scala/collection/LinearSeqLike
   70:	astore	4
   72:	goto	11
  LineNumberTable: 
   line 306: 0
   line 307: 2
   line 308: 11
   line 312: 40
   line 305: 55
   line 309: 56
   line 310: 60

  LocalVariableTable: 
   Start  Length  Slot  Name   Signature
   0      75      0    $this       Lscala/collection/LinearSeqLike;
   0      75      1    p       Lscala/Function1;
   0      75      2    from       I
   2      73      3    i       I
   11      64      4    these       Lscala/collection/LinearSeqLike;


public static int segmentLength(scala.collection.LinearSeqLike, scala.Function1, int);
  Code:
   Stack=2, Locals=5, Args_size=3
   0:	iconst_0
   1:	istore_3
   2:	aload_0
   3:	iload_2
   4:	invokeinterface	#52,  2; //InterfaceMethod scala/collection/LinearSeqLike.drop:(I)Lscala/collection/LinearSeqLike;
   9:	astore	4
   11:	aload	4
   13:	invokeinterface	#17,  1; //InterfaceMethod scala/collection/IterableLike.isEmpty:()Z
   18:	ifne	59
   21:	aload_1
   22:	aload	4
   24:	invokeinterface	#21,  1; //InterfaceMethod scala/collection/IterableLike.head:()Ljava/lang/Object;
   29:	invokeinterface	#27,  2; //InterfaceMethod scala/Function1.apply:(Ljava/lang/Object;)Ljava/lang/Object;
   34:	invokestatic	#33; //Method scala/runtime/BoxesRunTime.unboxToBoolean:(Ljava/lang/Object;)Z
   37:	ifeq	59
   40:	iload_3
   41:	iconst_1
   42:	iadd
   43:	istore_3
   44:	aload	4
   46:	invokeinterface	#38,  1; //InterfaceMethod scala/collection/TraversableLike.tail:()Ljava/lang/Object;
   51:	checkcast	#40; //class scala/collection/LinearSeqLike
   54:	astore	4
   56:	goto	11
   59:	iload_3
   60:	ireturn
  LineNumberTable: 
   line 295: 0
   line 296: 2
   line 297: 11
   line 298: 40
   line 299: 44
   line 301: 59

  LocalVariableTable: 
   Start  Length  Slot  Name   Signature
   0      61      0    $this       Lscala/collection/LinearSeqLike;
   0      61      1    p       Lscala/Function1;
   0      61      2    from       I
   2      58      3    i       I
   11      49      4    these       Lscala/collection/LinearSeqLike;


public static boolean isDefinedAt(scala.collection.LinearSeqLike, int);
  Code:
   Stack=2, Locals=2, Args_size=2
   0:	iload_1
   1:	iconst_0
   2:	if_icmplt	20
   5:	aload_0
   6:	iload_1
   7:	invokeinterface	#60,  2; //InterfaceMethod scala/collection/LinearSeqLike.lengthCompare:(I)I
   12:	iconst_0
   13:	if_icmple	20
   16:	iconst_1
   17:	goto	21
   20:	iconst_0
   21:	ireturn
  LineNumberTable: 
   line 291: 0

  LocalVariableTable: 
   Start  Length  Slot  Name   Signature
   0      22      0    $this       Lscala/collection/LinearSeqLike;
   0      22      1    x       I


public static int lengthCompare(scala.collection.LinearSeqLike, int);
  Code:
   Stack=2, Locals=4, Args_size=2
   0:	iconst_0
   1:	istore_2
   2:	aload_0
   3:	astore_3
   4:	aload_3
   5:	invokeinterface	#17,  1; //InterfaceMethod scala/collection/IterableLike.isEmpty:()Z
   10:	ifne	35
   13:	iload_2
   14:	iload_1
   15:	if_icmpgt	35
   18:	iload_2
   19:	iconst_1
   20:	iadd
   21:	istore_2
   22:	aload_3
   23:	invokeinterface	#38,  1; //InterfaceMethod scala/collection/TraversableLike.tail:()Ljava/lang/Object;
   28:	checkcast	#40; //class scala/collection/LinearSeqLike
   31:	astore_3
   32:	goto	4
   35:	iload_2
   36:	iload_1
   37:	isub
   38:	ireturn
  LineNumberTable: 
   line 281: 0
   line 282: 2
   line 283: 4
   line 284: 18
   line 285: 22
   line 287: 35

  LocalVariableTable: 
   Start  Length  Slot  Name   Signature
   0      39      0    $this       Lscala/collection/LinearSeqLike;
   0      39      1    len       I
   2      36      2    i       I
   4      34      3    these       Lscala/collection/LinearSeqLike;


public static boolean sameElements(scala.collection.LinearSeqLike, scala.collection.Iterable);
  Code:
   Stack=3, Locals=7, Args_size=2
   0:	aload_1
   1:	instanceof	#67; //class scala/collection/LinearSeq
   4:	ifeq	178
   7:	aload_1
   8:	checkcast	#67; //class scala/collection/LinearSeq
   11:	astore_2
   12:	iconst_1
   13:	ifeq	164
   16:	aload_0
   17:	astore	5
   19:	aload_2
   20:	astore	6
   22:	aload	5
   24:	invokeinterface	#17,  1; //InterfaceMethod scala/collection/IterableLike.isEmpty:()Z
   29:	ifne	136
   32:	aload	6
   34:	invokeinterface	#17,  1; //InterfaceMethod scala/collection/IterableLike.isEmpty:()Z
   39:	ifne	136
   42:	aload	5
   44:	invokeinterface	#21,  1; //InterfaceMethod scala/collection/IterableLike.head:()Ljava/lang/Object;
   49:	aload	6
   51:	invokeinterface	#21,  1; //InterfaceMethod scala/collection/IterableLike.head:()Ljava/lang/Object;
   56:	astore	4
   58:	astore_3
   59:	aload_3
   60:	aload	4
   62:	if_acmpne	69
   65:	iconst_1
   66:	goto	106
   69:	aload_3
   70:	ifnonnull	77
   73:	iconst_0
   74:	goto	106
   77:	aload_3
   78:	instanceof	#69; //class java/lang/Number
   81:	ifne	91
   84:	aload_3
   85:	instanceof	#71; //class java/lang/Character
   88:	ifeq	100
   91:	aload_3
   92:	aload	4
   94:	invokestatic	#75; //Method scala/runtime/BoxesRunTime.equals2:(Ljava/lang/Object;Ljava/lang/Object;)Z
   97:	goto	106
   100:	aload_3
   101:	aload	4
   103:	invokevirtual	#80; //Method java/lang/Object.equals:(Ljava/lang/Object;)Z
   106:	ifeq	136
   109:	aload	5
   111:	invokeinterface	#38,  1; //InterfaceMethod scala/collection/TraversableLike.tail:()Ljava/lang/Object;
   116:	checkcast	#40; //class scala/collection/LinearSeqLike
   119:	astore	5
   121:	aload	6
   123:	invokeinterface	#38,  1; //InterfaceMethod scala/collection/TraversableLike.tail:()Ljava/lang/Object;
   128:	checkcast	#67; //class scala/collection/LinearSeq
   131:	astore	6
   133:	goto	22
   136:	aload	5
   138:	invokeinterface	#17,  1; //InterfaceMethod scala/collection/IterableLike.isEmpty:()Z
   143:	ifeq	160
   146:	aload	6
   148:	invokeinterface	#17,  1; //InterfaceMethod scala/collection/IterableLike.isEmpty:()Z
   153:	ifeq	160
   156:	iconst_1
   157:	goto	189
   160:	iconst_0
   161:	goto	189
   164:	new	#82; //class scala/MatchError
   167:	dup
   168:	aload_1
   169:	invokeinterface	#86,  1; //InterfaceMethod scala/collection/TraversableLike.toString:()Ljava/lang/String;
   174:	invokespecial	#90; //Method scala/MatchError."<init>":(Ljava/lang/String;)V
   177:	athrow
   178:	iconst_1
   179:	ifeq	190
   182:	aload_0
   183:	aload_1
   184:	invokeinterface	#94,  2; //InterfaceMethod scala/collection/LinearSeqLike.scala$collection$LinearSeqLike$$super$sameElements:(Lscala/collection/Iterable;)Z
   189:	ireturn
   190:	new	#82; //class scala/MatchError
   193:	dup
   194:	aload_1
   195:	invokeinterface	#86,  1; //InterfaceMethod scala/collection/TraversableLike.toString:()Ljava/lang/String;
   200:	invokespecial	#90; //Method scala/MatchError."<init>":(Ljava/lang/String;)V
   203:	athrow
  LineNumberTable: 
   line 266: 0
   line 21: 12
   line 268: 16
   line 269: 19
   line 270: 22
   line 271: 109
   line 272: 121
   line 274: 136
   line 266: 164
   line 21: 178
   line 276: 182
   line 266: 189

  LocalVariableTable: 
   Start  Length  Slot  Name   Signature
   0      204      0    $this       Lscala/collection/LinearSeqLike;
   0      204      1    that       Lscala/collection/Iterable;
   12      166      2    temp2       Lscala/collection/LinearSeq;
   65      44      3    x0       Ljava/lang/Object;
   65      44      4    y0       Ljava/lang/Object;
   19      145      5    these       Lscala/collection/LinearSeqLike;
   22      142      6    those       Lscala/collection/LinearSeq;


public static scala.Tuple2 span(scala.collection.LinearSeqLike, scala.Function1);
  Code:
   Stack=4, Locals=4, Args_size=2
   0:	aload_0
   1:	invokeinterface	#107,  1; //InterfaceMethod scala/collection/TraversableLike.repr:()Ljava/lang/Object;
   6:	checkcast	#40; //class scala/collection/LinearSeqLike
   9:	astore_2
   10:	aload_0
   11:	invokeinterface	#111,  1; //InterfaceMethod scala/collection/TraversableLike.newBuilder:()Lscala/collection/mutable/Builder;
   16:	astore_3
   17:	aload_2
   18:	invokeinterface	#17,  1; //InterfaceMethod scala/collection/IterableLike.isEmpty:()Z
   23:	ifne	70
   26:	aload_1
   27:	aload_2
   28:	invokeinterface	#21,  1; //InterfaceMethod scala/collection/IterableLike.head:()Ljava/lang/Object;
   33:	invokeinterface	#27,  2; //InterfaceMethod scala/Function1.apply:(Ljava/lang/Object;)Ljava/lang/Object;
   38:	invokestatic	#33; //Method scala/runtime/BoxesRunTime.unboxToBoolean:(Ljava/lang/Object;)Z
   41:	ifeq	70
   44:	aload_3
   45:	aload_2
   46:	invokeinterface	#21,  1; //InterfaceMethod scala/collection/IterableLike.head:()Ljava/lang/Object;
   51:	invokeinterface	#117,  2; //InterfaceMethod scala/collection/mutable/Builder.$plus$eq:(Ljava/lang/Object;)Lscala/collection/mutable/Builder;
   56:	pop
   57:	aload_2
   58:	invokeinterface	#38,  1; //InterfaceMethod scala/collection/TraversableLike.tail:()Ljava/lang/Object;
   63:	checkcast	#40; //class scala/collection/LinearSeqLike
   66:	astore_2
   67:	goto	17
   70:	new	#119; //class scala/Tuple2
   73:	dup
   74:	aload_3
   75:	invokeinterface	#122,  1; //InterfaceMethod scala/collection/mutable/Builder.result:()Ljava/lang/Object;
   80:	aload_2
   81:	invokespecial	#125; //Method scala/Tuple2."<init>":(Ljava/lang/Object;Ljava/lang/Object;)V
   84:	areturn
  LineNumberTable: 
   line 256: 0
   line 257: 10
   line 258: 17
   line 259: 44
   line 260: 57
   line 262: 70

  LocalVariableTable: 
   Start  Length  Slot  Name   Signature
   0      85      0    $this       Lscala/collection/LinearSeqLike;
   0      85      1    p       Lscala/Function1;
   10      74      2    these       Lscala/collection/LinearSeqLike;
   17      67      3    b       Lscala/collection/mutable/Builder;


public static scala.collection.LinearSeqLike takeWhile(scala.collection.LinearSeqLike, scala.Function1);
  Code:
   Stack=2, Locals=4, Args_size=2
   0:	aload_0
   1:	invokeinterface	#111,  1; //InterfaceMethod scala/collection/TraversableLike.newBuilder:()Lscala/collection/mutable/Builder;
   6:	astore_2
   7:	aload_0
   8:	astore_3
   9:	aload_3
   10:	invokeinterface	#17,  1; //InterfaceMethod scala/collection/IterableLike.isEmpty:()Z
   15:	ifne	62
   18:	aload_1
   19:	aload_3
   20:	invokeinterface	#21,  1; //InterfaceMethod scala/collection/IterableLike.head:()Ljava/lang/Object;
   25:	invokeinterface	#27,  2; //InterfaceMethod scala/Function1.apply:(Ljava/lang/Object;)Ljava/lang/Object;
   30:	invokestatic	#33; //Method scala/runtime/BoxesRunTime.unboxToBoolean:(Ljava/lang/Object;)Z
   33:	ifeq	62
   36:	aload_2
   37:	aload_3
   38:	invokeinterface	#21,  1; //InterfaceMethod scala/collection/IterableLike.head:()Ljava/lang/Object;
   43:	invokeinterface	#117,  2; //InterfaceMethod scala/collection/mutable/Builder.$plus$eq:(Ljava/lang/Object;)Lscala/collection/mutable/Builder;
   48:	pop
   49:	aload_3
   50:	invokeinterface	#38,  1; //InterfaceMethod scala/collection/TraversableLike.tail:()Ljava/lang/Object;
   55:	checkcast	#40; //class scala/collection/LinearSeqLike
   58:	astore_3
   59:	goto	9
   62:	aload_2
   63:	invokeinterface	#122,  1; //InterfaceMethod scala/collection/mutable/Builder.result:()Ljava/lang/Object;
   68:	checkcast	#40; //class scala/collection/LinearSeqLike
   71:	areturn
  LineNumberTable: 
   line 245: 0
   line 246: 7
   line 247: 9
   line 248: 36
   line 249: 49
   line 251: 62

  LocalVariableTable: 
   Start  Length  Slot  Name   Signature
   0      72      0    $this       Lscala/collection/LinearSeqLike;
   0      72      1    p       Lscala/Function1;
   7      64      2    b       Lscala/collection/mutable/Builder;
   9      62      3    these       Lscala/collection/LinearSeqLike;


public static scala.collection.LinearSeqLike slice(scala.collection.LinearSeqLike, int, int);
  Code:
   Stack=2, Locals=6, Args_size=3
   0:	aload_0
   1:	invokeinterface	#111,  1; //InterfaceMethod scala/collection/TraversableLike.newBuilder:()Lscala/collection/mutable/Builder;
   6:	astore_3
   7:	iload_1
   8:	istore	4
   10:	aload_0
   11:	iload_1
   12:	invokeinterface	#52,  2; //InterfaceMethod scala/collection/LinearSeqLike.drop:(I)Lscala/collection/LinearSeqLike;
   17:	astore	5
   19:	iload	4
   21:	iload_2
   22:	if_icmpge	70
   25:	aload	5
   27:	invokeinterface	#17,  1; //InterfaceMethod scala/collection/IterableLike.isEmpty:()Z
   32:	ifne	70
   35:	aload_3
   36:	aload	5
   38:	invokeinterface	#21,  1; //InterfaceMethod scala/collection/IterableLike.head:()Ljava/lang/Object;
   43:	invokeinterface	#117,  2; //InterfaceMethod scala/collection/mutable/Builder.$plus$eq:(Ljava/lang/Object;)Lscala/collection/mutable/Builder;
   48:	pop
   49:	aload	5
   51:	invokeinterface	#38,  1; //InterfaceMethod scala/collection/TraversableLike.tail:()Ljava/lang/Object;
   56:	checkcast	#40; //class scala/collection/LinearSeqLike
   59:	astore	5
   61:	iload	4
   63:	iconst_1
   64:	iadd
   65:	istore	4
   67:	goto	19
   70:	aload_3
   71:	invokeinterface	#122,  1; //InterfaceMethod scala/collection/mutable/Builder.result:()Ljava/lang/Object;
   76:	checkcast	#40; //class scala/collection/LinearSeqLike
   79:	areturn
  LineNumberTable: 
   line 232: 0
   line 233: 7
   line 234: 10
   line 235: 19
   line 236: 35
   line 237: 49
   line 238: 61
   line 240: 70

  LocalVariableTable: 
   Start  Length  Slot  Name   Signature
   0      80      0    $this       Lscala/collection/LinearSeqLike;
   0      80      1    from       I
   0      80      2    until       I
   7      72      3    b       Lscala/collection/mutable/Builder;
   10      69      4    i       I
   19      60      5    these       Lscala/collection/LinearSeqLike;


public static scala.collection.LinearSeqLike dropRight(scala.collection.LinearSeqLike, int);
  Code:
   Stack=2, Locals=5, Args_size=2
   0:	aload_0
   1:	invokeinterface	#111,  1; //InterfaceMethod scala/collection/TraversableLike.newBuilder:()Lscala/collection/mutable/Builder;
   6:	astore_2
   7:	aload_0
   8:	astore_3
   9:	aload_0
   10:	iload_1
   11:	invokeinterface	#52,  2; //InterfaceMethod scala/collection/LinearSeqLike.drop:(I)Lscala/collection/LinearSeqLike;
   16:	astore	4
   18:	aload	4
   20:	invokeinterface	#17,  1; //InterfaceMethod scala/collection/IterableLike.isEmpty:()Z
   25:	ifeq	38
   28:	aload_2
   29:	invokeinterface	#122,  1; //InterfaceMethod scala/collection/mutable/Builder.result:()Ljava/lang/Object;
   34:	checkcast	#40; //class scala/collection/LinearSeqLike
   37:	areturn
   38:	aload_2
   39:	aload_3
   40:	invokeinterface	#21,  1; //InterfaceMethod scala/collection/IterableLike.head:()Ljava/lang/Object;
   45:	invokeinterface	#117,  2; //InterfaceMethod scala/collection/mutable/Builder.$plus$eq:(Ljava/lang/Object;)Lscala/collection/mutable/Builder;
   50:	pop
   51:	aload_3
   52:	invokeinterface	#38,  1; //InterfaceMethod scala/collection/TraversableLike.tail:()Ljava/lang/Object;
   57:	checkcast	#40; //class scala/collection/LinearSeqLike
   60:	astore_3
   61:	aload	4
   63:	invokeinterface	#38,  1; //InterfaceMethod scala/collection/TraversableLike.tail:()Ljava/lang/Object;
   68:	checkcast	#40; //class scala/collection/LinearSeqLike
   71:	astore	4
   73:	goto	18
  LineNumberTable: 
   line 219: 0
   line 220: 7
   line 221: 9
   line 222: 18
   line 227: 28
   line 223: 38
   line 224: 51
   line 225: 61

  LocalVariableTable: 
   Start  Length  Slot  Name   Signature
   0      76      0    $this       Lscala/collection/LinearSeqLike;
   0      76      1    n       I
   7      30      2    b       Lscala/collection/mutable/Builder;
   38      38      2    b       Lscala/collection/mutable/Builder;
   9      28      3    these       Lscala/collection/LinearSeqLike;
   38      38      3    these       Lscala/collection/LinearSeqLike;
   18      19      4    lead       Lscala/collection/LinearSeqLike;
   38      38      4    lead       Lscala/collection/LinearSeqLike;


public static scala.collection.LinearSeqLike drop(scala.collection.LinearSeqLike, int);
  Code:
   Stack=2, Locals=4, Args_size=2
   0:	aload_0
   1:	invokeinterface	#107,  1; //InterfaceMethod scala/collection/TraversableLike.repr:()Ljava/lang/Object;
   6:	checkcast	#40; //class scala/collection/LinearSeqLike
   9:	astore_2
   10:	iload_1
   11:	istore_3
   12:	aload_2
   13:	invokeinterface	#17,  1; //InterfaceMethod scala/collection/IterableLike.isEmpty:()Z
   18:	ifne	43
   21:	iload_3
   22:	iconst_0
   23:	if_icmple	43
   26:	aload_2
   27:	invokeinterface	#38,  1; //InterfaceMethod scala/collection/TraversableLike.tail:()Ljava/lang/Object;
   32:	checkcast	#40; //class scala/collection/LinearSeqLike
   35:	astore_2
   36:	iload_3
   37:	iconst_1
   38:	isub
   39:	istore_3
   40:	goto	12
   43:	aload_2
   44:	areturn
  LineNumberTable: 
   line 208: 0
   line 209: 10
   line 210: 12
   line 211: 26
   line 212: 36
   line 214: 43

  LocalVariableTable: 
   Start  Length  Slot  Name   Signature
   0      45      0    $this       Lscala/collection/LinearSeqLike;
   0      45      1    n       I
   10      34      2    these       Lscala/collection/LinearSeqLike;
   12      32      3    count       I


public static scala.collection.LinearSeqLike take(scala.collection.LinearSeqLike, int);
  Code:
   Stack=2, Locals=5, Args_size=2
   0:	aload_0
   1:	invokeinterface	#111,  1; //InterfaceMethod scala/collection/TraversableLike.newBuilder:()Lscala/collection/mutable/Builder;
   6:	astore_2
   7:	iconst_0
   8:	istore_3
   9:	aload_0
   10:	invokeinterface	#107,  1; //InterfaceMethod scala/collection/TraversableLike.repr:()Ljava/lang/Object;
   15:	checkcast	#40; //class scala/collection/LinearSeqLike
   18:	astore	4
   20:	aload	4
   22:	invokeinterface	#17,  1; //InterfaceMethod scala/collection/IterableLike.isEmpty:()Z
   27:	ifne	68
   30:	iload_3
   31:	iload_1
   32:	if_icmpge	68
   35:	iload_3
   36:	iconst_1
   37:	iadd
   38:	istore_3
   39:	aload_2
   40:	aload	4
   42:	invokeinterface	#21,  1; //InterfaceMethod scala/collection/IterableLike.head:()Ljava/lang/Object;
   47:	invokeinterface	#117,  2; //InterfaceMethod scala/collection/mutable/Builder.$plus$eq:(Ljava/lang/Object;)Lscala/collection/mutable/Builder;
   52:	pop
   53:	aload	4
   55:	invokeinterface	#38,  1; //InterfaceMethod scala/collection/TraversableLike.tail:()Ljava/lang/Object;
   60:	checkcast	#40; //class scala/collection/LinearSeqLike
   63:	astore	4
   65:	goto	20
   68:	aload_2
   69:	invokeinterface	#122,  1; //InterfaceMethod scala/collection/mutable/Builder.result:()Ljava/lang/Object;
   74:	checkcast	#40; //class scala/collection/LinearSeqLike
   77:	areturn
  LineNumberTable: 
   line 195: 0
   line 196: 7
   line 197: 9
   line 198: 20
   line 199: 35
   line 200: 39
   line 201: 53
   line 203: 68

  LocalVariableTable: 
   Start  Length  Slot  Name   Signature
   0      78      0    $this       Lscala/collection/LinearSeqLike;
   0      78      1    n       I
   7      70      2    b       Lscala/collection/mutable/Builder;
   9      68      3    i       I
   20      57      4    these       Lscala/collection/LinearSeqLike;


public static java.lang.Object last(scala.collection.LinearSeqLike);
  Code:
   Stack=2, Locals=3, Args_size=1
   0:	aload_0
   1:	invokeinterface	#17,  1; //InterfaceMethod scala/collection/IterableLike.isEmpty:()Z
   6:	ifeq	17
   9:	new	#141; //class java/util/NoSuchElementException
   12:	dup
   13:	invokespecial	#144; //Method java/util/NoSuchElementException."<init>":()V
   16:	athrow
   17:	aload_0
   18:	astore_1
   19:	aload_0
   20:	invokeinterface	#38,  1; //InterfaceMethod scala/collection/TraversableLike.tail:()Ljava/lang/Object;
   25:	checkcast	#40; //class scala/collection/LinearSeqLike
   28:	astore_2
   29:	aload_2
   30:	invokeinterface	#17,  1; //InterfaceMethod scala/collection/IterableLike.isEmpty:()Z
   35:	ifeq	45
   38:	aload_1
   39:	invokeinterface	#21,  1; //InterfaceMethod scala/collection/IterableLike.head:()Ljava/lang/Object;
   44:	areturn
   45:	aload_2
   46:	astore_1
   47:	aload_2
   48:	invokeinterface	#38,  1; //InterfaceMethod scala/collection/TraversableLike.tail:()Ljava/lang/Object;
   53:	checkcast	#40; //class scala/collection/LinearSeqLike
   56:	astore_2
   57:	goto	29
  LineNumberTable: 
   line 183: 0
   line 184: 17
   line 185: 19
   line 186: 29
   line 190: 38
   line 187: 45
   line 188: 47

  LocalVariableTable: 
   Start  Length  Slot  Name   Signature
   0      60      0    $this       Lscala/collection/LinearSeqLike;
   19      25      1    these       Lscala/collection/LinearSeqLike;
   45      15      1    these       Lscala/collection/LinearSeqLike;
   29      15      2    nx       Lscala/collection/LinearSeqLike;
   45      15      2    nx       Lscala/collection/LinearSeqLike;


public static java.lang.Object reduceRight(scala.collection.LinearSeqLike, scala.Function2);
  Code:
   Stack=4, Locals=2, Args_size=2
   0:	aload_0
   1:	invokeinterface	#17,  1; //InterfaceMethod scala/collection/IterableLike.isEmpty:()Z
   6:	ifeq	19
   9:	new	#149; //class java/lang/UnsupportedOperationException
   12:	dup
   13:	ldc	#151; //String Nil.reduceRight
   15:	invokespecial	#152; //Method java/lang/UnsupportedOperationException."<init>":(Ljava/lang/String;)V
   18:	athrow
   19:	aload_0
   20:	invokeinterface	#38,  1; //InterfaceMethod scala/collection/TraversableLike.tail:()Ljava/lang/Object;
   25:	checkcast	#13; //class scala/collection/IterableLike
   28:	invokeinterface	#17,  1; //InterfaceMethod scala/collection/IterableLike.isEmpty:()Z
   33:	ifeq	45
   36:	aload_0
   37:	invokeinterface	#21,  1; //InterfaceMethod scala/collection/IterableLike.head:()Ljava/lang/Object;
   42:	goto	72
   45:	aload_1
   46:	aload_0
   47:	invokeinterface	#21,  1; //InterfaceMethod scala/collection/IterableLike.head:()Ljava/lang/Object;
   52:	aload_0
   53:	invokeinterface	#38,  1; //InterfaceMethod scala/collection/TraversableLike.tail:()Ljava/lang/Object;
   58:	checkcast	#40; //class scala/collection/LinearSeqLike
   61:	aload_1
   62:	invokeinterface	#155,  2; //InterfaceMethod scala/collection/LinearSeqLike.reduceRight:(Lscala/Function2;)Ljava/lang/Object;
   67:	invokeinterface	#160,  3; //InterfaceMethod scala/Function2.apply:(Ljava/lang/Object;Ljava/lang/Object;)Ljava/lang/Object;
   72:	areturn
  LineNumberTable: 
   line 177: 0
   line 178: 19
   line 179: 45
   line 177: 72

  LocalVariableTable: 
   Start  Length  Slot  Name   Signature
   0      73      0    $this       Lscala/collection/LinearSeqLike;
   0      73      1    op       Lscala/Function2;


public static java.lang.Object reduceLeft(scala.collection.LinearSeqLike, scala.Function2);
  Code:
   Stack=3, Locals=2, Args_size=2
   0:	aload_0
   1:	invokeinterface	#17,  1; //InterfaceMethod scala/collection/IterableLike.isEmpty:()Z
   6:	ifeq	19
   9:	new	#149; //class java/lang/UnsupportedOperationException
   12:	dup
   13:	ldc	#165; //String empty.reduceLeft
   15:	invokespecial	#152; //Method java/lang/UnsupportedOperationException."<init>":(Ljava/lang/String;)V
   18:	athrow
   19:	aload_0
   20:	invokeinterface	#38,  1; //InterfaceMethod scala/collection/TraversableLike.tail:()Ljava/lang/Object;
   25:	checkcast	#40; //class scala/collection/LinearSeqLike
   28:	aload_0
   29:	invokeinterface	#21,  1; //InterfaceMethod scala/collection/IterableLike.head:()Ljava/lang/Object;
   34:	aload_1
   35:	invokeinterface	#169,  3; //InterfaceMethod scala/collection/LinearSeqLike.foldLeft:(Ljava/lang/Object;Lscala/Function2;)Ljava/lang/Object;
   40:	areturn
  LineNumberTable: 
   line 172: 0
   line 173: 19
   line 172: 40

  LocalVariableTable: 
   Start  Length  Slot  Name   Signature
   0      41      0    $this       Lscala/collection/LinearSeqLike;
   0      41      1    f       Lscala/Function2;


public static java.lang.Object foldRight(scala.collection.LinearSeqLike, java.lang.Object, scala.Function2);
  Code:
   Stack=5, Locals=3, Args_size=3
   0:	aload_0
   1:	invokeinterface	#17,  1; //InterfaceMethod scala/collection/IterableLike.isEmpty:()Z
   6:	ifeq	13
   9:	aload_1
   10:	goto	41
   13:	aload_2
   14:	aload_0
   15:	invokeinterface	#21,  1; //InterfaceMethod scala/collection/IterableLike.head:()Ljava/lang/Object;
   20:	aload_0
   21:	invokeinterface	#38,  1; //InterfaceMethod scala/collection/TraversableLike.tail:()Ljava/lang/Object;
   26:	checkcast	#40; //class scala/collection/LinearSeqLike
   29:	aload_1
   30:	aload_2
   31:	invokeinterface	#174,  3; //InterfaceMethod scala/collection/LinearSeqLike.foldRight:(Ljava/lang/Object;Lscala/Function2;)Ljava/lang/Object;
   36:	invokeinterface	#160,  3; //InterfaceMethod scala/Function2.apply:(Ljava/lang/Object;Ljava/lang/Object;)Ljava/lang/Object;
   41:	areturn
  LineNumberTable: 
   line 167: 0
   line 168: 13
   line 167: 41

  LocalVariableTable: 
   Start  Length  Slot  Name   Signature
   0      42      0    $this       Lscala/collection/LinearSeqLike;
   0      42      1    z       Ljava/lang/Object;
   0      42      2    f       Lscala/Function2;


public static java.lang.Object foldLeft(scala.collection.LinearSeqLike, java.lang.Object, scala.Function2);
  Code:
   Stack=3, Locals=5, Args_size=3
   0:	aload_1
   1:	astore_3
   2:	aload_0
   3:	astore	4
   5:	aload	4
   7:	invokeinterface	#17,  1; //InterfaceMethod scala/collection/IterableLike.isEmpty:()Z
   12:	ifeq	17
   15:	aload_3
   16:	areturn
   17:	aload_2
   18:	aload_3
   19:	aload	4
   21:	invokeinterface	#21,  1; //InterfaceMethod scala/collection/IterableLike.head:()Ljava/lang/Object;
   26:	invokeinterface	#160,  3; //InterfaceMethod scala/Function2.apply:(Ljava/lang/Object;Ljava/lang/Object;)Ljava/lang/Object;
   31:	astore_3
   32:	aload	4
   34:	invokeinterface	#38,  1; //InterfaceMethod scala/collection/TraversableLike.tail:()Ljava/lang/Object;
   39:	checkcast	#40; //class scala/collection/LinearSeqLike
   42:	astore	4
   44:	goto	5
  LineNumberTable: 
   line 156: 0
   line 157: 2
   line 158: 5
   line 162: 15
   line 159: 17
   line 160: 32

  LocalVariableTable: 
   Start  Length  Slot  Name   Signature
   0      47      0    $this       Lscala/collection/LinearSeqLike;
   0      47      1    z       Ljava/lang/Object;
   0      47      2    f       Lscala/Function2;
   2      14      3    acc       Ljava/lang/Object;
   17      30      3    acc       Ljava/lang/Object;
   5      11      4    these       Lscala/collection/LinearSeqLike;
   17      30      4    these       Lscala/collection/LinearSeqLike;


public static scala.Option find(scala.collection.LinearSeqLike, scala.Function1);
  Code:
   Stack=3, Locals=3, Args_size=2
   0:	aload_0
   1:	astore_2
   2:	aload_2
   3:	invokeinterface	#17,  1; //InterfaceMethod scala/collection/IterableLike.isEmpty:()Z
   8:	ifeq	15
   11:	getstatic	#184; //Field scala/None$.MODULE$:Lscala/None$;
   14:	areturn
   15:	aload_1
   16:	aload_2
   17:	invokeinterface	#21,  1; //InterfaceMethod scala/collection/IterableLike.head:()Ljava/lang/Object;
   22:	invokeinterface	#27,  2; //InterfaceMethod scala/Function1.apply:(Ljava/lang/Object;)Ljava/lang/Object;
   27:	invokestatic	#33; //Method scala/runtime/BoxesRunTime.unboxToBoolean:(Ljava/lang/Object;)Z
   30:	ifeq	47
   33:	new	#186; //class scala/Some
   36:	dup
   37:	aload_2
   38:	invokeinterface	#21,  1; //InterfaceMethod scala/collection/IterableLike.head:()Ljava/lang/Object;
   43:	invokespecial	#189; //Method scala/Some."<init>":(Ljava/lang/Object;)V
   46:	areturn
   47:	aload_2
   48:	invokeinterface	#38,  1; //InterfaceMethod scala/collection/TraversableLike.tail:()Ljava/lang/Object;
   53:	checkcast	#40; //class scala/collection/LinearSeqLike
   56:	astore_2
   57:	goto	2
  LineNumberTable: 
   line 136: 0
   line 137: 2
   line 141: 11
   line 138: 15
   line 139: 47

  LocalVariableTable: 
   Start  Length  Slot  Name   Signature
   0      60      0    $this       Lscala/collection/LinearSeqLike;
   0      60      1    p       Lscala/Function1;
   2      12      2    these       Lscala/collection/LinearSeqLike;
   15      45      2    these       Lscala/collection/LinearSeqLike;


public static int count(scala.collection.LinearSeqLike, scala.Function1);
  Code:
   Stack=2, Locals=4, Args_size=2
   0:	aload_0
   1:	astore_2
   2:	iconst_0
   3:	istore_3
   4:	aload_2
   5:	invokeinterface	#17,  1; //InterfaceMethod scala/collection/IterableLike.isEmpty:()Z
   10:	ifeq	15
   13:	iload_3
   14:	ireturn
   15:	aload_1
   16:	aload_2
   17:	invokeinterface	#21,  1; //InterfaceMethod scala/collection/IterableLike.head:()Ljava/lang/Object;
   22:	invokeinterface	#27,  2; //InterfaceMethod scala/Function1.apply:(Ljava/lang/Object;)Ljava/lang/Object;
   27:	invokestatic	#33; //Method scala/runtime/BoxesRunTime.unboxToBoolean:(Ljava/lang/Object;)Z
   30:	ifeq	37
   33:	iload_3
   34:	iconst_1
   35:	iadd
   36:	istore_3
   37:	aload_2
   38:	invokeinterface	#38,  1; //InterfaceMethod scala/collection/TraversableLike.tail:()Ljava/lang/Object;
   43:	checkcast	#40; //class scala/collection/LinearSeqLike
   46:	astore_2
   47:	goto	4
  LineNumberTable: 
   line 125: 0
   line 126: 2
   line 127: 4
   line 131: 13
   line 128: 15
   line 129: 37

  LocalVariableTable: 
   Start  Length  Slot  Name   Signature
   0      50      0    $this       Lscala/collection/LinearSeqLike;
   0      50      1    p       Lscala/Function1;
   2      12      2    these       Lscala/collection/LinearSeqLike;
   15      35      2    these       Lscala/collection/LinearSeqLike;
   4      10      3    cnt       I
   15      35      3    cnt       I


public static boolean exists(scala.collection.LinearSeqLike, scala.Function1);
  Code:
   Stack=2, Locals=3, Args_size=2
   0:	aload_0
   1:	astore_2
   2:	aload_2
   3:	invokeinterface	#17,  1; //InterfaceMethod scala/collection/IterableLike.isEmpty:()Z
   8:	ifeq	13
   11:	iconst_0
   12:	ireturn
   13:	aload_1
   14:	aload_2
   15:	invokeinterface	#21,  1; //InterfaceMethod scala/collection/IterableLike.head:()Ljava/lang/Object;
   20:	invokeinterface	#27,  2; //InterfaceMethod scala/Function1.apply:(Ljava/lang/Object;)Ljava/lang/Object;
   25:	invokestatic	#33; //Method scala/runtime/BoxesRunTime.unboxToBoolean:(Ljava/lang/Object;)Z
   28:	ifeq	33
   31:	iconst_1
   32:	ireturn
   33:	aload_2
   34:	invokeinterface	#38,  1; //InterfaceMethod scala/collection/TraversableLike.tail:()Ljava/lang/Object;
   39:	checkcast	#40; //class scala/collection/LinearSeqLike
   42:	astore_2
   43:	goto	2
  LineNumberTable: 
   line 115: 0
   line 116: 2
   line 120: 11
   line 117: 13
   line 118: 33

  LocalVariableTable: 
   Start  Length  Slot  Name   Signature
   0      46      0    $this       Lscala/collection/LinearSeqLike;
   0      46      1    p       Lscala/Function1;
   2      10      2    these       Lscala/collection/LinearSeqLike;
   13      33      2    these       Lscala/collection/LinearSeqLike;


public static boolean forall(scala.collection.LinearSeqLike, scala.Function1);
  Code:
   Stack=2, Locals=3, Args_size=2
   0:	aload_0
   1:	astore_2
   2:	aload_2
   3:	invokeinterface	#17,  1; //InterfaceMethod scala/collection/IterableLike.isEmpty:()Z
   8:	ifeq	13
   11:	iconst_1
   12:	ireturn
   13:	aload_1
   14:	aload_2
   15:	invokeinterface	#21,  1; //InterfaceMethod scala/collection/IterableLike.head:()Ljava/lang/Object;
   20:	invokeinterface	#27,  2; //InterfaceMethod scala/Function1.apply:(Ljava/lang/Object;)Ljava/lang/Object;
   25:	invokestatic	#33; //Method scala/runtime/BoxesRunTime.unboxToBoolean:(Ljava/lang/Object;)Z
   28:	ifeq	44
   31:	aload_2
   32:	invokeinterface	#38,  1; //InterfaceMethod scala/collection/TraversableLike.tail:()Ljava/lang/Object;
   37:	checkcast	#40; //class scala/collection/LinearSeqLike
   40:	astore_2
   41:	goto	2
   44:	iconst_0
   45:	ireturn
  LineNumberTable: 
   line 105: 0
   line 106: 2
   line 110: 11
   line 107: 13
   line 108: 31
   line 107: 44

  LocalVariableTable: 
   Start  Length  Slot  Name   Signature
   0      46      0    $this       Lscala/collection/LinearSeqLike;
   0      46      1    p       Lscala/Function1;
   2      10      2    these       Lscala/collection/LinearSeqLike;
   13      33      2    these       Lscala/collection/LinearSeqLike;


public static void foreach(scala.collection.LinearSeqLike, scala.Function1);
  Code:
   Stack=2, Locals=3, Args_size=2
   0:	aload_0
   1:	astore_2
   2:	aload_2
   3:	invokeinterface	#17,  1; //InterfaceMethod scala/collection/IterableLike.isEmpty:()Z
   8:	ifeq	12
   11:	return
   12:	aload_1
   13:	aload_2
   14:	invokeinterface	#21,  1; //InterfaceMethod scala/collection/IterableLike.head:()Ljava/lang/Object;
   19:	invokeinterface	#27,  2; //InterfaceMethod scala/Function1.apply:(Ljava/lang/Object;)Ljava/lang/Object;
   24:	pop
   25:	aload_2
   26:	invokeinterface	#38,  1; //InterfaceMethod scala/collection/TraversableLike.tail:()Ljava/lang/Object;
   31:	checkcast	#40; //class scala/collection/LinearSeqLike
   34:	astore_2
   35:	goto	2
  LineNumberTable: 
   line 95: 0
   line 96: 2
   line 94: 11
   line 97: 12
   line 98: 25

  LocalVariableTable: 
   Start  Length  Slot  Name   Signature
   0      38      0    $this       Lscala/collection/LinearSeqLike;
   0      38      1    f       Lscala/Function1;
   2      36      2    these       Lscala/collection/LinearSeqLike;


public static scala.collection.Iterator iterator(scala.collection.LinearSeqLike);
  Code:
   Stack=3, Locals=1, Args_size=1
   0:	new	#200; //class scala/collection/LinearSeqLike$$anon$1
   3:	dup
   4:	aload_0
   5:	invokespecial	#202; //Method scala/collection/LinearSeqLike$$anon$1."<init>":(Lscala/collection/LinearSeqLike;)V
   8:	areturn
  LineNumberTable: 
   line 83: 0

  LocalVariableTable: 
   Start  Length  Slot  Name   Signature
   0      9      0    $this       Lscala/collection/LinearSeqLike;


public static java.lang.Object apply(scala.collection.LinearSeqLike, int);
  Code:
   Stack=2, Locals=3, Args_size=2
   0:	aload_0
   1:	iload_1
   2:	invokeinterface	#52,  2; //InterfaceMethod scala/collection/LinearSeqLike.drop:(I)Lscala/collection/LinearSeqLike;
   7:	astore_2
   8:	iload_1
   9:	iconst_0
   10:	if_icmplt	22
   13:	aload_2
   14:	invokeinterface	#17,  1; //InterfaceMethod scala/collection/IterableLike.isEmpty:()Z
   19:	ifeq	30
   22:	new	#205; //class java/lang/IndexOutOfBoundsException
   25:	dup
   26:	invokespecial	#206; //Method java/lang/IndexOutOfBoundsException."<init>":()V
   29:	athrow
   30:	aload_2
   31:	invokeinterface	#21,  1; //InterfaceMethod scala/collection/IterableLike.head:()Ljava/lang/Object;
   36:	areturn
  LineNumberTable: 
   line 77: 0
   line 78: 8
   line 79: 30

  LocalVariableTable: 
   Start  Length  Slot  Name   Signature
   0      37      0    $this       Lscala/collection/LinearSeqLike;
   0      37      1    n       I
   8      28      2    rest       Lscala/collection/LinearSeqLike;


public static int length(scala.collection.LinearSeqLike);
  Code:
   Stack=2, Locals=3, Args_size=1
   0:	aload_0
   1:	astore_1
   2:	iconst_0
   3:	istore_2
   4:	aload_1
   5:	invokeinterface	#17,  1; //InterfaceMethod scala/collection/IterableLike.isEmpty:()Z
   10:	ifeq	15
   13:	iload_2
   14:	ireturn
   15:	iload_2
   16:	iconst_1
   17:	iadd
   18:	istore_2
   19:	aload_1
   20:	invokeinterface	#38,  1; //InterfaceMethod scala/collection/TraversableLike.tail:()Ljava/lang/Object;
   25:	checkcast	#40; //class scala/collection/LinearSeqLike
   28:	astore_1
   29:	goto	4
  LineNumberTable: 
   line 63: 0
   line 64: 2
   line 65: 4
   line 69: 13
   line 66: 15
   line 67: 19

  LocalVariableTable: 
   Start  Length  Slot  Name   Signature
   0      32      0    $this       Lscala/collection/LinearSeqLike;
   2      12      1    these       Lscala/collection/LinearSeqLike;
   15      17      1    these       Lscala/collection/LinearSeqLike;
   4      10      2    len       I
   15      17      2    len       I


public static scala.collection.LinearSeq toCollection(scala.collection.LinearSeqLike, scala.collection.LinearSeqLike);
  Code:
   Stack=1, Locals=2, Args_size=2
   0:	aload_1
   1:	checkcast	#67; //class scala/collection/LinearSeq
   4:	areturn
  LineNumberTable: 
   line 48: 0

  LocalVariableTable: 
   Start  Length  Slot  Name   Signature
   0      5      0    $this       Lscala/collection/LinearSeqLike;
   0      5      1    repr       Lscala/collection/LinearSeqLike;


public static scala.collection.LinearSeq thisCollection(scala.collection.LinearSeqLike);
  Code:
   Stack=1, Locals=1, Args_size=1
   0:	aload_0
   1:	checkcast	#67; //class scala/collection/LinearSeq
   4:	areturn
  LineNumberTable: 
   line 47: 0

  LocalVariableTable: 
   Start  Length  Slot  Name   Signature
   0      5      0    $this       Lscala/collection/LinearSeqLike;


}

