Compiled from "Map.scala"
public abstract class scala.collection.Map$class extends java.lang.Object
  SourceFile: "Map.scala"
  Scala: length = 0x
   
  minor version: 0
  major version: 49
  Constant pool:
const #1 = Asciz	SourceFile;
const #2 = Asciz	Map.scala;
const #3 = Asciz	$init$;
const #4 = Asciz	(Lscala/collection/Map;)V;
const #5 = Asciz	Code;
const #6 = Asciz	LineNumberTable;
const #7 = Asciz	$this;
const #8 = Asciz	Lscala/collection/Map;;
const #9 = Asciz	LocalVariableTable;
const #10 = Asciz	empty;
const #11 = Asciz	(Lscala/collection/Map;)Lscala/collection/Map;;
const #12 = Asciz	scala/collection/Map$;
const #13 = class	#12;	//  scala/collection/Map$
const #14 = Asciz	MODULE$;
const #15 = Asciz	Lscala/collection/Map$;;
const #16 = NameAndType	#14:#15;//  MODULE$:Lscala/collection/Map$;
const #17 = Field	#13.#16;	//  scala/collection/Map$.MODULE$:Lscala/collection/Map$;
const #18 = Asciz	()Lscala/collection/immutable/Map;;
const #19 = NameAndType	#10:#18;//  empty:()Lscala/collection/immutable/Map;
const #20 = Method	#13.#19;	//  scala/collection/Map$.empty:()Lscala/collection/immutable/Map;
const #21 = Asciz	Scala;
const #22 = Asciz	scala/collection/Map$class;
const #23 = class	#22;	//  scala/collection/Map$class
const #24 = Asciz	java/lang/Object;
const #25 = class	#24;	//  java/lang/Object

{
public static void $init$(scala.collection.Map);
  Code:
   Stack=0, Locals=1, Args_size=1
   0:	return
  LineNumberTable: 
   line 41: 0

  LocalVariableTable: 
   Start  Length  Slot  Name   Signature
   0      1      0    $this       Lscala/collection/Map;


public static scala.collection.Map empty(scala.collection.Map);
  Code:
   Stack=1, Locals=1, Args_size=1
   0:	getstatic	#17; //Field scala/collection/Map$.MODULE$:Lscala/collection/Map$;
   3:	invokevirtual	#20; //Method scala/collection/Map$.empty:()Lscala/collection/immutable/Map;
   6:	areturn
  LineNumberTable: 
   line 42: 0

  LocalVariableTable: 
   Start  Length  Slot  Name   Signature
   0      7      0    $this       Lscala/collection/Map;


}

