Compiled from "MapLike.scala"
public final class scala.collection.MapLike$$anonfun$transform$2 extends scala.runtime.AbstractFunction1 implements java.io.Serializable
  SourceFile: "MapLike.scala"
  Scala: length = 0x
   
  InnerClass: 
   public final $anonfun$transform$2=class scala/collection/MapLike$$anonfun$transform$2 of class scala/collection/MapLike
  minor version: 0
  major version: 49
  Constant pool:
Asciz	SourceFile;
Asciz	MapLike.scala;
Asciz	<clinit>;
Asciz	()V;
Asciz	Code;
Asciz	serialVersionUID;
Asciz	J;
Asciz	scala/collection/MapLike$$anonfun$transform$2;
class	scala/collection/MapLike$$anonfun$transform$2
NameAndType	serialVersionUID:J
Field	scala/collection/MapLike$$anonfun$transform$2.serialVersionUID:J
Asciz	b$1;
Asciz	Lscala/collection/mutable/Builder;;
Asciz	f$5;
Asciz	Lscala/Function2;;
Asciz	apply;
Asciz	(Lscala/Tuple2;)Lscala/collection/mutable/Builder;;
Asciz	LineNumberTable;
Asciz	scala/Tuple2;
class	scala/Tuple2
Asciz	_1;
Asciz	()Ljava/lang/Object;;
NameAndType	_1:()Ljava/lang/Object;
Method	scala/Tuple2._1:()Ljava/lang/Object;
NameAndType	b$1:Lscala/collection/mutable/Builder;
Field	scala/collection/MapLike$$anonfun$transform$2.b$1:Lscala/collection/mutable/Builder;
NameAndType	f$5:Lscala/Function2;
Field	scala/collection/MapLike$$anonfun$transform$2.f$5:Lscala/Function2;
Asciz	_2;
NameAndType	_2:()Ljava/lang/Object;
Method	scala/Tuple2._2:()Ljava/lang/Object;
Asciz	scala/Function2;
class	scala/Function2
Asciz	(Ljava/lang/Object;Ljava/lang/Object;)Ljava/lang/Object;;
NameAndType	apply:(Ljava/lang/Object;Ljava/lang/Object;)Ljava/lang/Object;
InterfaceMethod	scala/Function2.apply:(Ljava/lang/Object;Ljava/lang/Object;)Ljava/lang/Object;
Asciz	<init>;
Asciz	(Ljava/lang/Object;Ljava/lang/Object;)V;
NameAndType	"<init>":(Ljava/lang/Object;Ljava/lang/Object;)V
Method	scala/Tuple2."<init>":(Ljava/lang/Object;Ljava/lang/Object;)V
Asciz	scala/collection/mutable/Builder;
class	scala/collection/mutable/Builder
Asciz	$plus$eq;
Asciz	(Ljava/lang/Object;)Lscala/collection/mutable/Builder;;
NameAndType	$plus$eq:(Ljava/lang/Object;)Lscala/collection/mutable/Builder;
InterfaceMethod	scala/collection/mutable/Builder.$plus$eq:(Ljava/lang/Object;)Lscala/collection/mutable/Builder;
Asciz	scala/MatchError;
class	scala/MatchError
Asciz	(Ljava/lang/Object;)V;
NameAndType	"<init>":(Ljava/lang/Object;)V
Method	scala/MatchError."<init>":(Ljava/lang/Object;)V
Asciz	this;
Asciz	Lscala/collection/MapLike$$anonfun$transform$2;;
Asciz	temp38;
Asciz	Ljava/lang/Object;;
Asciz	LocalVariableTable;
Asciz	(Lscala/Tuple2<TA;TB;>;)Lscala/collection/mutable/Builder<Lscala/Tuple2<TA;TC;>;TThat;>;;
Asciz	Signature;
Asciz	(Ljava/lang/Object;)Ljava/lang/Object;;
NameAndType	apply:(Lscala/Tuple2;)Lscala/collection/mutable/Builder;
Method	scala/collection/MapLike$$anonfun$transform$2.apply:(Lscala/Tuple2;)Lscala/collection/mutable/Builder;
Asciz	v1;
Asciz	(Lscala/collection/MapLike;Lscala/Function2;Lscala/collection/mutable/Builder;)V;
Asciz	scala/runtime/AbstractFunction1;
class	scala/runtime/AbstractFunction1
NameAndType	"<init>":()V
Method	scala/runtime/AbstractFunction1."<init>":()V
Asciz	$outer;
Asciz	Lscala/collection/MapLike;;
Asciz	(Lscala/collection/MapLike<TA;TB;TThis;>;)V;
Asciz	Scala;
Asciz	InnerClasses;
Asciz	scala/collection/MapLike;
class	scala/collection/MapLike
Asciz	$anonfun$transform$2;
Asciz	java/io/Serializable;
class	java/io/Serializable

{
public static final long serialVersionUID;
  Signature: J

public final scala.collection.mutable.Builder b$1;
  Signature: Lscala/collection/mutable/Builder;

public final scala.Function2 f$5;
  Signature: Lscala/Function2;

public static {};
  Signature: ()V
  Code:
   Stack=2, Locals=0, Args_size=0
	lconst_0
	putstatic	Field serialVersionUID:J
	return
  Labels:

public final scala.collection.mutable.Builder apply(scala.Tuple2);
  Signature: (Lscala/Tuple2;)Lscala/collection/mutable/Builder;
  Code:
   Stack=7, Locals=3, Args_size=2
	aload_1
	ifnull	l1 // new
	aload_1
	invokevirtual	Method scala/Tuple2._1:()Ljava/lang/Object;
	astore_2
	aload_0
	getfield	Field b$1:Lscala/collection/mutable/Builder;
	new	class scala/Tuple2
	dup
	aload_2
	aload_0
	getfield	Field f$5:Lscala/Function2;
	aload_2
	aload_1
	invokevirtual	Method scala/Tuple2._2:()Ljava/lang/Object;
	invokeinterface	InterfaceMethod scala/Function2.apply:(Ljava/lang/Object;Ljava/lang/Object;)Ljava/lang/Object;
	invokespecial	Method scala/Tuple2."<init>":(Ljava/lang/Object;Ljava/lang/Object;)V
	invokeinterface	InterfaceMethod scala/collection/mutable/Builder.$plus$eq:(Ljava/lang/Object;)Lscala/collection/mutable/Builder;
	areturn
l1	new	class scala/MatchError
	dup
	aload_1
	invokespecial	Method scala/MatchError."<init>":(Ljava/lang/Object;)V
	athrow
  Labels:
   	l1 = 41 // new
  LocalVariableTable: 
   Start  Length  Slot  Name   Signature
   0      50      0    this       Lscala/collection/MapLike$$anonfun$transform$2;
   9      31      2    temp38       Ljava/lang/Object;

  Signature: length = 0x2
   00 39 

public final java.lang.Object apply(java.lang.Object);
  Signature: (Ljava/lang/Object;)Ljava/lang/Object;
  Code:
   Stack=2, Locals=2, Args_size=2
	aload_0
	aload_1
	checkcast	class scala/Tuple2
	invokevirtual	Method apply:(Lscala/Tuple2;)Lscala/collection/mutable/Builder;
	areturn
  Labels:
  LocalVariableTable: 
   Start  Length  Slot  Name   Signature
   0      9      0    this       Lscala/collection/MapLike$$anonfun$transform$2;
   0      9      1    v1       Ljava/lang/Object;


public scala.collection.MapLike$$anonfun$transform$2(scala.collection.MapLike, scala.Function2, scala.collection.mutable.Builder);
  Signature: (Lscala/collection/MapLike;Lscala/Function2;Lscala/collection/mutable/Builder;)V
  Code:
   Stack=2, Locals=4, Args_size=4
	aload_0
	aload_2
	putfield	Field f$5:Lscala/Function2;
	aload_0
	aload_3
	putfield	Field b$1:Lscala/collection/mutable/Builder;
	aload_0
	invokespecial	Method scala/runtime/AbstractFunction1."<init>":()V
	return
  Labels:
  LocalVariableTable: 
   Start  Length  Slot  Name   Signature
   0      15      0    this       Lscala/collection/MapLike$$anonfun$transform$2;
   0      15      1    $outer       Lscala/collection/MapLike;

  Signature: length = 0x2
   00 46 

}

