Compiled from "MapLike.scala"
public final class scala.collection.MapLike$$anonfun$liftedTree1$1$1 extends java.lang.Object implements scala.Function1,scala.ScalaObject,java.io.Serializable
  SourceFile: "MapLike.scala"
  Scala: length = 0x
   
  InnerClass: 
   public final #115= #9 of #59; //$anonfun$liftedTree1$1$1=class scala/collection/MapLike$$anonfun$liftedTree1$1$1 of class scala/collection/MapLike
  minor version: 0
  major version: 49
  Constant pool:
const #1 = Asciz	SourceFile;
const #2 = Asciz	MapLike.scala;
const #3 = Asciz	<clinit>;
const #4 = Asciz	()V;
const #5 = Asciz	Code;
const #6 = Asciz	serialVersionUID;
const #7 = Asciz	J;
const #8 = Asciz	scala/collection/MapLike$$anonfun$liftedTree1$1$1;
const #9 = class	#8;	//  scala/collection/MapLike$$anonfun$liftedTree1$1$1
const #10 = NameAndType	#6:#7;//  serialVersionUID:J
const #11 = Field	#9.#10;	//  scala/collection/MapLike$$anonfun$liftedTree1$1$1.serialVersionUID:J
const #12 = Asciz	that$1;
const #13 = Asciz	Lscala/collection/Map;;
const #14 = Asciz	<init>;
const #15 = Asciz	(Lscala/collection/MapLike;Lscala/collection/Map;)V;
const #16 = Asciz	LineNumberTable;
const #17 = NameAndType	#12:#13;//  that$1:Lscala/collection/Map;
const #18 = Field	#9.#17;	//  scala/collection/MapLike$$anonfun$liftedTree1$1$1.that$1:Lscala/collection/Map;
const #19 = Asciz	java/lang/Object;
const #20 = class	#19;	//  java/lang/Object
const #21 = NameAndType	#14:#4;//  "<init>":()V
const #22 = Method	#20.#21;	//  java/lang/Object."<init>":()V
const #23 = Asciz	scala/Function1$class;
const #24 = class	#23;	//  scala/Function1$class
const #25 = Asciz	$init$;
const #26 = Asciz	(Lscala/Function1;)V;
const #27 = NameAndType	#25:#26;//  $init$:(Lscala/Function1;)V
const #28 = Method	#24.#27;	//  scala/Function1$class.$init$:(Lscala/Function1;)V
const #29 = Asciz	this;
const #30 = Asciz	Lscala/collection/MapLike$$anonfun$liftedTree1$1$1;;
const #31 = Asciz	$outer;
const #32 = Asciz	Lscala/collection/MapLike;;
const #33 = Asciz	LocalVariableTable;
const #34 = Asciz	(Lscala/collection/MapLike<TA;TB;TThis;>;)V;
const #35 = Asciz	Signature;
const #36 = Asciz	apply;
const #37 = Asciz	(Ljava/lang/Object;)Ljava/lang/Object;;
const #38 = Asciz	scala/Tuple2;
const #39 = class	#38;	//  scala/Tuple2
const #40 = Asciz	(Lscala/Tuple2;)Z;
const #41 = NameAndType	#36:#40;//  apply:(Lscala/Tuple2;)Z
const #42 = Method	#9.#41;	//  scala/collection/MapLike$$anonfun$liftedTree1$1$1.apply:(Lscala/Tuple2;)Z
const #43 = Asciz	scala/runtime/BoxesRunTime;
const #44 = class	#43;	//  scala/runtime/BoxesRunTime
const #45 = Asciz	boxToBoolean;
const #46 = Asciz	(Z)Ljava/lang/Boolean;;
const #47 = NameAndType	#45:#46;//  boxToBoolean:(Z)Ljava/lang/Boolean;
const #48 = Method	#44.#47;	//  scala/runtime/BoxesRunTime.boxToBoolean:(Z)Ljava/lang/Boolean;
const #49 = Asciz	v1;
const #50 = Asciz	Ljava/lang/Object;;
const #51 = Asciz	_1;
const #52 = Asciz	()Ljava/lang/Object;;
const #53 = NameAndType	#51:#52;//  _1:()Ljava/lang/Object;
const #54 = Method	#39.#53;	//  scala/Tuple2._1:()Ljava/lang/Object;
const #55 = Asciz	_2;
const #56 = NameAndType	#55:#52;//  _2:()Ljava/lang/Object;
const #57 = Method	#39.#56;	//  scala/Tuple2._2:()Ljava/lang/Object;
const #58 = Asciz	scala/collection/MapLike;
const #59 = class	#58;	//  scala/collection/MapLike
const #60 = Asciz	get;
const #61 = Asciz	(Ljava/lang/Object;)Lscala/Option;;
const #62 = NameAndType	#60:#61;//  get:(Ljava/lang/Object;)Lscala/Option;
const #63 = InterfaceMethod	#59.#62;	//  scala/collection/MapLike.get:(Ljava/lang/Object;)Lscala/Option;
const #64 = Asciz	scala/Some;
const #65 = class	#64;	//  scala/Some
const #66 = Asciz	x;
const #67 = NameAndType	#66:#50;//  x:Ljava/lang/Object;
const #68 = Field	#65.#67;	//  scala/Some.x:Ljava/lang/Object;
const #69 = Asciz	java/lang/Number;
const #70 = class	#69;	//  java/lang/Number
const #71 = Asciz	java/lang/Character;
const #72 = class	#71;	//  java/lang/Character
const #73 = Asciz	equals2;
const #74 = Asciz	(Ljava/lang/Object;Ljava/lang/Object;)Z;
const #75 = NameAndType	#73:#74;//  equals2:(Ljava/lang/Object;Ljava/lang/Object;)Z
const #76 = Method	#44.#75;	//  scala/runtime/BoxesRunTime.equals2:(Ljava/lang/Object;Ljava/lang/Object;)Z
const #77 = Asciz	equals;
const #78 = Asciz	(Ljava/lang/Object;)Z;
const #79 = NameAndType	#77:#78;//  equals:(Ljava/lang/Object;)Z
const #80 = Method	#20.#79;	//  java/lang/Object.equals:(Ljava/lang/Object;)Z
const #81 = Asciz	scala/MatchError;
const #82 = class	#81;	//  scala/MatchError
const #83 = Asciz	scala/Option;
const #84 = class	#83;	//  scala/Option
const #85 = Asciz	toString;
const #86 = Asciz	()Ljava/lang/String;;
const #87 = NameAndType	#85:#86;//  toString:()Ljava/lang/String;
const #88 = Method	#84.#87;	//  scala/Option.toString:()Ljava/lang/String;
const #89 = Asciz	(Ljava/lang/String;)V;
const #90 = NameAndType	#14:#89;//  "<init>":(Ljava/lang/String;)V
const #91 = Method	#82.#90;	//  scala/MatchError."<init>":(Ljava/lang/String;)V
const #92 = Method	#39.#87;	//  scala/Tuple2.toString:()Ljava/lang/String;
const #93 = Asciz	temp42;
const #94 = Asciz	$inlThis0;
const #95 = Asciz	temp43;
const #96 = Asciz	y0;
const #97 = Asciz	temp37;
const #98 = Asciz	Lscala/Option;;
const #99 = Asciz	(Lscala/Tuple2<TA;TB;>;)Z;
const #100 = Asciz	andThen;
const #101 = Asciz	(Lscala/Function1;)Lscala/Function1;;
const #102 = Asciz	(Lscala/Function1;Lscala/Function1;)Lscala/Function1;;
const #103 = NameAndType	#100:#102;//  andThen:(Lscala/Function1;Lscala/Function1;)Lscala/Function1;
const #104 = Method	#24.#103;	//  scala/Function1$class.andThen:(Lscala/Function1;Lscala/Function1;)Lscala/Function1;
const #105 = Asciz	g;
const #106 = Asciz	Lscala/Function1;;
const #107 = Asciz	compose;
const #108 = NameAndType	#107:#102;//  compose:(Lscala/Function1;Lscala/Function1;)Lscala/Function1;
const #109 = Method	#24.#108;	//  scala/Function1$class.compose:(Lscala/Function1;Lscala/Function1;)Lscala/Function1;
const #110 = Asciz	(Lscala/Function1;)Ljava/lang/String;;
const #111 = NameAndType	#85:#110;//  toString:(Lscala/Function1;)Ljava/lang/String;
const #112 = Method	#24.#111;	//  scala/Function1$class.toString:(Lscala/Function1;)Ljava/lang/String;
const #113 = Asciz	Scala;
const #114 = Asciz	InnerClasses;
const #115 = Asciz	$anonfun$liftedTree1$1$1;
const #116 = Asciz	scala/Function1;
const #117 = class	#116;	//  scala/Function1
const #118 = Asciz	scala/ScalaObject;
const #119 = class	#118;	//  scala/ScalaObject
const #120 = Asciz	java/io/Serializable;
const #121 = class	#120;	//  java/io/Serializable

{
public static final long serialVersionUID;

public static {};
  Code:
   Stack=2, Locals=0, Args_size=0
   0:	lconst_0
   1:	putstatic	#11; //Field serialVersionUID:J
   4:	return

public scala.collection.MapLike$$anonfun$liftedTree1$1$1(scala.collection.MapLike, scala.collection.Map);
  Code:
   Stack=2, Locals=3, Args_size=3
   0:	aload_0
   1:	aload_2
   2:	putfield	#18; //Field that$1:Lscala/collection/Map;
   5:	aload_0
   6:	invokespecial	#22; //Method java/lang/Object."<init>":()V
   9:	aload_0
   10:	invokestatic	#28; //Method scala/Function1$class.$init$:(Lscala/Function1;)V
   13:	return
  LineNumberTable: 
   line 285: 0

  LocalVariableTable: 
   Start  Length  Slot  Name   Signature
   0      14      0    this       Lscala/collection/MapLike$$anonfun$liftedTree1$1$1;
   0      14      1    $outer       Lscala/collection/MapLike;

  Signature: length = 0x2
   00 22 

public final java.lang.Object apply(java.lang.Object);
  Code:
   Stack=2, Locals=3, Args_size=2
   0:	aload_0
   1:	aload_1
   2:	checkcast	#39; //class scala/Tuple2
   5:	invokevirtual	#42; //Method apply:(Lscala/Tuple2;)Z
   8:	istore_2
   9:	iload_2
   10:	invokestatic	#48; //Method scala/runtime/BoxesRunTime.boxToBoolean:(Z)Ljava/lang/Boolean;
   13:	areturn
  LineNumberTable: 
   line 285: 0

  LocalVariableTable: 
   Start  Length  Slot  Name   Signature
   0      14      0    this       Lscala/collection/MapLike$$anonfun$liftedTree1$1$1;
   0      14      1    v1       Ljava/lang/Object;


public final boolean apply(scala.Tuple2);
  Code:
   Stack=3, Locals=7, Args_size=2
   0:	aload_1
   1:	ifnull	180
   4:	aload_1
   5:	invokevirtual	#54; //Method scala/Tuple2._1:()Ljava/lang/Object;
   8:	astore_2
   9:	aload_1
   10:	invokevirtual	#57; //Method scala/Tuple2._2:()Ljava/lang/Object;
   13:	astore	4
   15:	iconst_1
   16:	ifeq	168
   19:	aload_0
   20:	getfield	#18; //Field that$1:Lscala/collection/Map;
   23:	aload_2
   24:	invokeinterface	#63,  2; //InterfaceMethod scala/collection/MapLike.get:(Ljava/lang/Object;)Lscala/Option;
   29:	astore	6
   31:	aload	6
   33:	instanceof	#65; //class scala/Some
   36:	ifeq	149
   39:	aload	6
   41:	checkcast	#65; //class scala/Some
   44:	astore_3
   45:	aload_3
   46:	getfield	#68; //Field scala/Some.x:Ljava/lang/Object;
   49:	astore	5
   51:	aload	4
   53:	aload	5
   55:	if_acmpne	62
   58:	iconst_1
   59:	goto	104
   62:	aload	4
   64:	ifnonnull	71
   67:	iconst_0
   68:	goto	104
   71:	aload	4
   73:	instanceof	#70; //class java/lang/Number
   76:	ifne	87
   79:	aload	4
   81:	instanceof	#72; //class java/lang/Character
   84:	ifeq	97
   87:	aload	4
   89:	aload	5
   91:	invokestatic	#76; //Method scala/runtime/BoxesRunTime.equals2:(Ljava/lang/Object;Ljava/lang/Object;)Z
   94:	goto	104
   97:	aload	4
   99:	aload	5
   101:	invokevirtual	#80; //Method java/lang/Object.equals:(Ljava/lang/Object;)Z
   104:	ifeq	128
   107:	iconst_1
   108:	ifeq	115
   111:	iconst_1
   112:	goto	154
   115:	new	#82; //class scala/MatchError
   118:	dup
   119:	aload	6
   121:	invokevirtual	#88; //Method scala/Option.toString:()Ljava/lang/String;
   124:	invokespecial	#91; //Method scala/MatchError."<init>":(Ljava/lang/String;)V
   127:	athrow
   128:	iconst_1
   129:	ifeq	136
   132:	iconst_0
   133:	goto	154
   136:	new	#82; //class scala/MatchError
   139:	dup
   140:	aload	6
   142:	invokevirtual	#88; //Method scala/Option.toString:()Ljava/lang/String;
   145:	invokespecial	#91; //Method scala/MatchError."<init>":(Ljava/lang/String;)V
   148:	athrow
   149:	iconst_1
   150:	ifeq	155
   153:	iconst_0
   154:	ireturn
   155:	new	#82; //class scala/MatchError
   158:	dup
   159:	aload	6
   161:	invokevirtual	#88; //Method scala/Option.toString:()Ljava/lang/String;
   164:	invokespecial	#91; //Method scala/MatchError."<init>":(Ljava/lang/String;)V
   167:	athrow
   168:	new	#82; //class scala/MatchError
   171:	dup
   172:	aload_1
   173:	invokevirtual	#92; //Method scala/Tuple2.toString:()Ljava/lang/String;
   176:	invokespecial	#91; //Method scala/MatchError."<init>":(Ljava/lang/String;)V
   179:	athrow
   180:	new	#82; //class scala/MatchError
   183:	dup
   184:	aload_1
   185:	invokevirtual	#92; //Method scala/Tuple2.toString:()Ljava/lang/String;
   188:	invokespecial	#91; //Method scala/MatchError."<init>":(Ljava/lang/String;)V
   191:	athrow
  LineNumberTable: 
   line 285: 0
   line 21: 15
   line 286: 19
   line 285: 39
   line 21: 107
   line 287: 111
   line 286: 115
   line 21: 128
   line 288: 132
   line 286: 136
   line 21: 149
   line 288: 153
   line 285: 154
   line 286: 155
   line 285: 168

  LocalVariableTable: 
   Start  Length  Slot  Name   Signature
   0      192      0    this       Lscala/collection/MapLike$$anonfun$liftedTree1$1$1;
   9      145      2    temp42       Ljava/lang/Object;
   155      25      2    temp42       Ljava/lang/Object;
   58      49      3    $inlThis0       Ljava/lang/Object;
   15      139      4    temp43       Ljava/lang/Object;
   155      25      4    temp43       Ljava/lang/Object;
   58      49      5    y0       Ljava/lang/Object;
   31      123      6    temp37       Lscala/Option;
   155      13      6    temp37       Lscala/Option;

  Signature: length = 0x2
   00 63 

public scala.Function1 andThen(scala.Function1);
  Code:
   Stack=2, Locals=2, Args_size=2
   0:	aload_0
   1:	aload_1
   2:	invokestatic	#104; //Method scala/Function1$class.andThen:(Lscala/Function1;Lscala/Function1;)Lscala/Function1;
   5:	areturn
  LineNumberTable: 
   line 285: 0

  LocalVariableTable: 
   Start  Length  Slot  Name   Signature
   0      6      0    this       Lscala/collection/MapLike$$anonfun$liftedTree1$1$1;
   0      6      1    g       Lscala/Function1;


public scala.Function1 compose(scala.Function1);
  Code:
   Stack=2, Locals=2, Args_size=2
   0:	aload_0
   1:	aload_1
   2:	invokestatic	#109; //Method scala/Function1$class.compose:(Lscala/Function1;Lscala/Function1;)Lscala/Function1;
   5:	areturn
  LineNumberTable: 
   line 285: 0

  LocalVariableTable: 
   Start  Length  Slot  Name   Signature
   0      6      0    this       Lscala/collection/MapLike$$anonfun$liftedTree1$1$1;
   0      6      1    g       Lscala/Function1;


public java.lang.String toString();
  Code:
   Stack=1, Locals=1, Args_size=1
   0:	aload_0
   1:	invokestatic	#112; //Method scala/Function1$class.toString:(Lscala/Function1;)Ljava/lang/String;
   4:	areturn
  LineNumberTable: 
   line 285: 0


}

