Compiled from "MapLike.scala"
public final class scala.collection.MapLike$$anon$1 extends java.lang.Object implements scala.collection.DefaultMap
  SourceFile: "MapLike.scala"
  Signature: length = 0x2
   02 FFFFFFD2 
  Scala: length = 0x
   
  InnerClass: 
   public final $anon$1=class scala/collection/MapLike$$anon$1 of class scala/collection/MapLike
   public abstract $less$colon$less=class scala/Predef$$less$colon$less of class scala/Predef
   public WithFilter=class scala/collection/TraversableLike$WithFilter of class scala/collection/TraversableLike
   public final $anonfun$foreach$5=class scala/collection/MapLike$$anon$1$$anonfun$foreach$5 of class scala/collection/MapLike$$anon$1
   public final $anonfun$iterator$1=class scala/collection/MapLike$$anon$1$$anonfun$iterator$1 of class scala/collection/MapLike$$anon$1
  minor version: 0
  major version: 49
  Constant pool:
Asciz	SourceFile;
Asciz	MapLike.scala;
Asciz	p$1;
Asciz	Lscala/Function1;;
Asciz	$outer;
Asciz	Lscala/collection/MapLike;;
Asciz	$plus;
Asciz	(Lscala/Tuple2;)Lscala/collection/Map;;
Asciz	Code;
Asciz	LineNumberTable;
Asciz	scala/collection/DefaultMap$class;
class	scala/collection/DefaultMap$class
Asciz	(Lscala/collection/DefaultMap;Lscala/Tuple2;)Lscala/collection/Map;;
NameAndType	$plus:(Lscala/collection/DefaultMap;Lscala/Tuple2;)Lscala/collection/Map;
Method	scala/collection/DefaultMap$class.$plus:(Lscala/collection/DefaultMap;Lscala/Tuple2;)Lscala/collection/Map;
Asciz	this;
Asciz	Lscala/collection/MapLike$$anon$1;;
Asciz	kv;
Asciz	Lscala/Tuple2;;
Asciz	LocalVariableTable;
Asciz	$minus;
Asciz	(Ljava/lang/Object;)Lscala/collection/Map;;
Asciz	(Lscala/collection/DefaultMap;Ljava/lang/Object;)Lscala/collection/Map;;
NameAndType	$minus:(Lscala/collection/DefaultMap;Ljava/lang/Object;)Lscala/collection/Map;
Method	scala/collection/DefaultMap$class.$minus:(Lscala/collection/DefaultMap;Ljava/lang/Object;)Lscala/collection/Map;
Asciz	key;
Asciz	Ljava/lang/Object;;
Asciz	empty;
Asciz	()Lscala/collection/Map;;
Asciz	scala/collection/Map$class;
class	scala/collection/Map$class
Asciz	(Lscala/collection/Map;)Lscala/collection/Map;;
NameAndType	empty:(Lscala/collection/Map;)Lscala/collection/Map;
Method	scala/collection/Map$class.empty:(Lscala/collection/Map;)Lscala/collection/Map;
Asciz	newBuilder;
Asciz	()Lscala/collection/mutable/Builder;;
Asciz	scala/collection/MapLike$class;
class	scala/collection/MapLike$class
Asciz	(Lscala/collection/MapLike;)Lscala/collection/mutable/Builder;;
NameAndType	newBuilder:(Lscala/collection/MapLike;)Lscala/collection/mutable/Builder;
Method	scala/collection/MapLike$class.newBuilder:(Lscala/collection/MapLike;)Lscala/collection/mutable/Builder;
Asciz	isEmpty;
Asciz	()Z;
Asciz	(Lscala/collection/MapLike;)Z;
NameAndType	isEmpty:(Lscala/collection/MapLike;)Z
Method	scala/collection/MapLike$class.isEmpty:(Lscala/collection/MapLike;)Z
Asciz	getOrElse;
Asciz	(Ljava/lang/Object;Lscala/Function0;)Ljava/lang/Object;;
Asciz	(Lscala/collection/MapLike;Ljava/lang/Object;Lscala/Function0;)Ljava/lang/Object;;
NameAndType	getOrElse:(Lscala/collection/MapLike;Ljava/lang/Object;Lscala/Function0;)Ljava/lang/Object;
Method	scala/collection/MapLike$class.getOrElse:(Lscala/collection/MapLike;Ljava/lang/Object;Lscala/Function0;)Ljava/lang/Object;
Asciz	default;
Asciz	Lscala/Function0;;
Asciz	apply;
Asciz	(Ljava/lang/Object;)Ljava/lang/Object;;
Asciz	(Lscala/collection/MapLike;Ljava/lang/Object;)Ljava/lang/Object;;
NameAndType	apply:(Lscala/collection/MapLike;Ljava/lang/Object;)Ljava/lang/Object;
Method	scala/collection/MapLike$class.apply:(Lscala/collection/MapLike;Ljava/lang/Object;)Ljava/lang/Object;
Asciz	isDefinedAt;
Asciz	(Ljava/lang/Object;)Z;
Asciz	(Lscala/collection/MapLike;Ljava/lang/Object;)Z;
NameAndType	isDefinedAt:(Lscala/collection/MapLike;Ljava/lang/Object;)Z
Method	scala/collection/MapLike$class.isDefinedAt:(Lscala/collection/MapLike;Ljava/lang/Object;)Z
Asciz	keySet;
Asciz	()Lscala/collection/Set;;
Asciz	(Lscala/collection/MapLike;)Lscala/collection/Set;;
NameAndType	keySet:(Lscala/collection/MapLike;)Lscala/collection/Set;
Method	scala/collection/MapLike$class.keySet:(Lscala/collection/MapLike;)Lscala/collection/Set;
Asciz	keysIterator;
Asciz	()Lscala/collection/Iterator;;
Asciz	(Lscala/collection/MapLike;)Lscala/collection/Iterator;;
NameAndType	keysIterator:(Lscala/collection/MapLike;)Lscala/collection/Iterator;
Method	scala/collection/MapLike$class.keysIterator:(Lscala/collection/MapLike;)Lscala/collection/Iterator;
Asciz	keys;
NameAndType	keys:(Lscala/collection/MapLike;)Lscala/collection/Iterator;
Method	scala/collection/MapLike$class.keys:(Lscala/collection/MapLike;)Lscala/collection/Iterator;
Asciz	Deprecated;
Asciz	valuesIterable;
Asciz	()Lscala/collection/Iterable;;
Asciz	(Lscala/collection/MapLike;)Lscala/collection/Iterable;;
NameAndType	valuesIterable:(Lscala/collection/MapLike;)Lscala/collection/Iterable;
Method	scala/collection/MapLike$class.valuesIterable:(Lscala/collection/MapLike;)Lscala/collection/Iterable;
Asciz	valuesIterator;
NameAndType	valuesIterator:(Lscala/collection/MapLike;)Lscala/collection/Iterator;
Method	scala/collection/MapLike$class.valuesIterator:(Lscala/collection/MapLike;)Lscala/collection/Iterator;
Asciz	values;
NameAndType	values:(Lscala/collection/MapLike;)Lscala/collection/Iterator;
Method	scala/collection/MapLike$class.values:(Lscala/collection/MapLike;)Lscala/collection/Iterator;
NameAndType	default:(Lscala/collection/MapLike;Ljava/lang/Object;)Ljava/lang/Object;
Method	scala/collection/MapLike$class.default:(Lscala/collection/MapLike;Ljava/lang/Object;)Ljava/lang/Object;
Asciz	filterKeys;
Asciz	(Lscala/Function1;)Lscala/collection/Map;;
Asciz	(Lscala/collection/MapLike;Lscala/Function1;)Lscala/collection/Map;;
NameAndType	filterKeys:(Lscala/collection/MapLike;Lscala/Function1;)Lscala/collection/Map;
Method	scala/collection/MapLike$class.filterKeys:(Lscala/collection/MapLike;Lscala/Function1;)Lscala/collection/Map;
Asciz	p;
Asciz	mapValues;
NameAndType	mapValues:(Lscala/collection/MapLike;Lscala/Function1;)Lscala/collection/Map;
Method	scala/collection/MapLike$class.mapValues:(Lscala/collection/MapLike;Lscala/Function1;)Lscala/collection/Map;
Asciz	f;
Asciz	mapElements;
NameAndType	mapElements:(Lscala/collection/MapLike;Lscala/Function1;)Lscala/collection/Map;
Method	scala/collection/MapLike$class.mapElements:(Lscala/collection/MapLike;Lscala/Function1;)Lscala/collection/Map;
Asciz	updated;
Asciz	(Ljava/lang/Object;Ljava/lang/Object;)Lscala/collection/Map;;
Asciz	(Lscala/collection/MapLike;Ljava/lang/Object;Ljava/lang/Object;)Lscala/collection/Map;;
NameAndType	updated:(Lscala/collection/MapLike;Ljava/lang/Object;Ljava/lang/Object;)Lscala/collection/Map;
Method	scala/collection/MapLike$class.updated:(Lscala/collection/MapLike;Ljava/lang/Object;Ljava/lang/Object;)Lscala/collection/Map;
Asciz	value;
Asciz	(Lscala/Tuple2;Lscala/Tuple2;Lscala/collection/Seq;)Lscala/collection/Map;;
Asciz	(Lscala/collection/MapLike;Lscala/Tuple2;Lscala/Tuple2;Lscala/collection/Seq;)Lscala/collection/Map;;
NameAndType	$plus:(Lscala/collection/MapLike;Lscala/Tuple2;Lscala/Tuple2;Lscala/collection/Seq;)Lscala/collection/Map;
Method	scala/collection/MapLike$class.$plus:(Lscala/collection/MapLike;Lscala/Tuple2;Lscala/Tuple2;Lscala/collection/Seq;)Lscala/collection/Map;
Asciz	kv1;
Asciz	kv2;
Asciz	kvs;
Asciz	Lscala/collection/Seq;;
Asciz	$plus$plus;
Asciz	(Lscala/collection/Traversable;)Lscala/collection/Map;;
Asciz	(Lscala/collection/MapLike;Lscala/collection/Traversable;)Lscala/collection/Map;;
NameAndType	$plus$plus:(Lscala/collection/MapLike;Lscala/collection/Traversable;)Lscala/collection/Map;
Method	scala/collection/MapLike$class.$plus$plus:(Lscala/collection/MapLike;Lscala/collection/Traversable;)Lscala/collection/Map;
Asciz	Lscala/collection/Traversable;;
Asciz	(Lscala/collection/Iterator;)Lscala/collection/Map;;
Asciz	(Lscala/collection/MapLike;Lscala/collection/Iterator;)Lscala/collection/Map;;
NameAndType	$plus$plus:(Lscala/collection/MapLike;Lscala/collection/Iterator;)Lscala/collection/Map;
Method	scala/collection/MapLike$class.$plus$plus:(Lscala/collection/MapLike;Lscala/collection/Iterator;)Lscala/collection/Map;
Asciz	iter;
Asciz	Lscala/collection/Iterator;;
Asciz	filterNot;
NameAndType	filterNot:(Lscala/collection/MapLike;Lscala/Function1;)Lscala/collection/Map;
Method	scala/collection/MapLike$class.filterNot:(Lscala/collection/MapLike;Lscala/Function1;)Lscala/collection/Map;
Asciz	addString;
Asciz	(Lscala/collection/mutable/StringBuilder;Ljava/lang/String;Ljava/lang/String;Ljava/lang/String;)Lscala/collection/mutable/StringBuilder;;
Asciz	(Lscala/collection/MapLike;Lscala/collection/mutable/StringBuilder;Ljava/lang/String;Ljava/lang/String;Ljava/lang/String;)Lscala/collection/mutable/StringBuilder;;
NameAndType	addString:(Lscala/collection/MapLike;Lscala/collection/mutable/StringBuilder;Ljava/lang/String;Ljava/lang/String;Ljava/lang/String;)Lscala/collection/mutable/StringBuilder;
Method	scala/collection/MapLike$class.addString:(Lscala/collection/MapLike;Lscala/collection/mutable/StringBuilder;Ljava/lang/String;Ljava/lang/String;Ljava/lang/String;)Lscala/collection/mutable/StringBuilder;
Asciz	b;
Asciz	Lscala/collection/mutable/StringBuilder;;
Asciz	start;
Asciz	Ljava/lang/String;;
Asciz	sep;
Asciz	end;
Asciz	stringPrefix;
Asciz	()Ljava/lang/String;;
Asciz	(Lscala/collection/MapLike;)Ljava/lang/String;;
NameAndType	stringPrefix:(Lscala/collection/MapLike;)Ljava/lang/String;
Method	scala/collection/MapLike$class.stringPrefix:(Lscala/collection/MapLike;)Ljava/lang/String;
Asciz	toString;
NameAndType	toString:(Lscala/collection/MapLike;)Ljava/lang/String;
Method	scala/collection/MapLike$class.toString:(Lscala/collection/MapLike;)Ljava/lang/String;
Asciz	hashCode;
Asciz	()I;
Asciz	(Lscala/collection/MapLike;)I;
NameAndType	hashCode:(Lscala/collection/MapLike;)I
Method	scala/collection/MapLike$class.hashCode:(Lscala/collection/MapLike;)I
Asciz	equals;
NameAndType	equals:(Lscala/collection/MapLike;Ljava/lang/Object;)Z
Method	scala/collection/MapLike$class.equals:(Lscala/collection/MapLike;Ljava/lang/Object;)Z
Asciz	that;
Asciz	(Ljava/lang/Object;Ljava/lang/Object;Lscala/collection/Seq;)Lscala/collection/generic/Subtractable;;
Asciz	scala/collection/generic/Subtractable$class;
class	scala/collection/generic/Subtractable$class
Asciz	(Lscala/collection/generic/Subtractable;Ljava/lang/Object;Ljava/lang/Object;Lscala/collection/Seq;)Lscala/collection/generic/Subtractable;;
NameAndType	$minus:(Lscala/collection/generic/Subtractable;Ljava/lang/Object;Ljava/lang/Object;Lscala/collection/Seq;)Lscala/collection/generic/Subtractable;
Method	scala/collection/generic/Subtractable$class.$minus:(Lscala/collection/generic/Subtractable;Ljava/lang/Object;Ljava/lang/Object;Lscala/collection/Seq;)Lscala/collection/generic/Subtractable;
Asciz	elem1;
Asciz	elem2;
Asciz	elems;
Asciz	$minus$minus;
Asciz	(Lscala/collection/Traversable;)Lscala/collection/generic/Subtractable;;
Asciz	(Lscala/collection/generic/Subtractable;Lscala/collection/Traversable;)Lscala/collection/generic/Subtractable;;
NameAndType	$minus$minus:(Lscala/collection/generic/Subtractable;Lscala/collection/Traversable;)Lscala/collection/generic/Subtractable;
Method	scala/collection/generic/Subtractable$class.$minus$minus:(Lscala/collection/generic/Subtractable;Lscala/collection/Traversable;)Lscala/collection/generic/Subtractable;
Asciz	(Lscala/collection/Iterator;)Lscala/collection/generic/Subtractable;;
Asciz	(Lscala/collection/generic/Subtractable;Lscala/collection/Iterator;)Lscala/collection/generic/Subtractable;;
NameAndType	$minus$minus:(Lscala/collection/generic/Subtractable;Lscala/collection/Iterator;)Lscala/collection/generic/Subtractable;
Method	scala/collection/generic/Subtractable$class.$minus$minus:(Lscala/collection/generic/Subtractable;Lscala/collection/Iterator;)Lscala/collection/generic/Subtractable;
Asciz	orElse;
Asciz	(Lscala/PartialFunction;)Lscala/PartialFunction;;
Asciz	scala/PartialFunction$class;
class	scala/PartialFunction$class
Asciz	(Lscala/PartialFunction;Lscala/PartialFunction;)Lscala/PartialFunction;;
NameAndType	orElse:(Lscala/PartialFunction;Lscala/PartialFunction;)Lscala/PartialFunction;
Method	scala/PartialFunction$class.orElse:(Lscala/PartialFunction;Lscala/PartialFunction;)Lscala/PartialFunction;
Asciz	Lscala/PartialFunction;;
Asciz	andThen;
Asciz	(Lscala/Function1;)Lscala/PartialFunction;;
Asciz	(Lscala/PartialFunction;Lscala/Function1;)Lscala/PartialFunction;;
NameAndType	andThen:(Lscala/PartialFunction;Lscala/Function1;)Lscala/PartialFunction;
Method	scala/PartialFunction$class.andThen:(Lscala/PartialFunction;Lscala/Function1;)Lscala/PartialFunction;
Asciz	k;
Asciz	lift;
Asciz	()Lscala/Function1;;
Asciz	(Lscala/PartialFunction;)Lscala/Function1;;
NameAndType	lift:(Lscala/PartialFunction;)Lscala/Function1;
Method	scala/PartialFunction$class.lift:(Lscala/PartialFunction;)Lscala/Function1;
Asciz	compose;
Asciz	(Lscala/Function1;)Lscala/Function1;;
Asciz	scala/Function1$class;
class	scala/Function1$class
Asciz	(Lscala/Function1;Lscala/Function1;)Lscala/Function1;;
NameAndType	compose:(Lscala/Function1;Lscala/Function1;)Lscala/Function1;
Method	scala/Function1$class.compose:(Lscala/Function1;Lscala/Function1;)Lscala/Function1;
Asciz	g;
Asciz	companion;
Asciz	()Lscala/collection/generic/GenericCompanion;;
Asciz	scala/collection/Iterable$class;
class	scala/collection/Iterable$class
Asciz	(Lscala/collection/Iterable;)Lscala/collection/generic/GenericCompanion;;
NameAndType	companion:(Lscala/collection/Iterable;)Lscala/collection/generic/GenericCompanion;
Method	scala/collection/Iterable$class.companion:(Lscala/collection/Iterable;)Lscala/collection/generic/GenericCompanion;
Asciz	thisCollection;
Asciz	scala/collection/IterableLike$class;
class	scala/collection/IterableLike$class
Asciz	(Lscala/collection/IterableLike;)Lscala/collection/Iterable;;
NameAndType	thisCollection:(Lscala/collection/IterableLike;)Lscala/collection/Iterable;
Method	scala/collection/IterableLike$class.thisCollection:(Lscala/collection/IterableLike;)Lscala/collection/Iterable;
Asciz	toCollection;
Asciz	(Ljava/lang/Object;)Lscala/collection/Iterable;;
Asciz	(Lscala/collection/IterableLike;Ljava/lang/Object;)Lscala/collection/Iterable;;
NameAndType	toCollection:(Lscala/collection/IterableLike;Ljava/lang/Object;)Lscala/collection/Iterable;
Method	scala/collection/IterableLike$class.toCollection:(Lscala/collection/IterableLike;Ljava/lang/Object;)Lscala/collection/Iterable;
Asciz	repr;
Asciz	elements;
Asciz	(Lscala/collection/IterableLike;)Lscala/collection/Iterator;;
NameAndType	elements:(Lscala/collection/IterableLike;)Lscala/collection/Iterator;
Method	scala/collection/IterableLike$class.elements:(Lscala/collection/IterableLike;)Lscala/collection/Iterator;
Asciz	forall;
Asciz	(Lscala/Function1;)Z;
Asciz	(Lscala/collection/IterableLike;Lscala/Function1;)Z;
NameAndType	forall:(Lscala/collection/IterableLike;Lscala/Function1;)Z
Method	scala/collection/IterableLike$class.forall:(Lscala/collection/IterableLike;Lscala/Function1;)Z
Asciz	exists;
NameAndType	exists:(Lscala/collection/IterableLike;Lscala/Function1;)Z
Method	scala/collection/IterableLike$class.exists:(Lscala/collection/IterableLike;Lscala/Function1;)Z
Asciz	find;
Asciz	(Lscala/Function1;)Lscala/Option;;
Asciz	(Lscala/collection/IterableLike;Lscala/Function1;)Lscala/Option;;
NameAndType	find:(Lscala/collection/IterableLike;Lscala/Function1;)Lscala/Option;
Method	scala/collection/IterableLike$class.find:(Lscala/collection/IterableLike;Lscala/Function1;)Lscala/Option;
Asciz	foldRight;
Asciz	(Ljava/lang/Object;Lscala/Function2;)Ljava/lang/Object;;
Asciz	(Lscala/collection/IterableLike;Ljava/lang/Object;Lscala/Function2;)Ljava/lang/Object;;
NameAndType	foldRight:(Lscala/collection/IterableLike;Ljava/lang/Object;Lscala/Function2;)Ljava/lang/Object;
Method	scala/collection/IterableLike$class.foldRight:(Lscala/collection/IterableLike;Ljava/lang/Object;Lscala/Function2;)Ljava/lang/Object;
Asciz	z;
Asciz	op;
Asciz	Lscala/Function2;;
Asciz	reduceRight;
Asciz	(Lscala/Function2;)Ljava/lang/Object;;
Asciz	(Lscala/collection/IterableLike;Lscala/Function2;)Ljava/lang/Object;;
NameAndType	reduceRight:(Lscala/collection/IterableLike;Lscala/Function2;)Ljava/lang/Object;
Method	scala/collection/IterableLike$class.reduceRight:(Lscala/collection/IterableLike;Lscala/Function2;)Ljava/lang/Object;
Asciz	toIterable;
NameAndType	toIterable:(Lscala/collection/IterableLike;)Lscala/collection/Iterable;
Method	scala/collection/IterableLike$class.toIterable:(Lscala/collection/IterableLike;)Lscala/collection/Iterable;
Asciz	head;
Asciz	()Ljava/lang/Object;;
Asciz	(Lscala/collection/IterableLike;)Ljava/lang/Object;;
NameAndType	head:(Lscala/collection/IterableLike;)Ljava/lang/Object;
Method	scala/collection/IterableLike$class.head:(Lscala/collection/IterableLike;)Ljava/lang/Object;
Asciz	take;
Asciz	(I)Ljava/lang/Object;;
Asciz	(Lscala/collection/IterableLike;I)Ljava/lang/Object;;
NameAndType	take:(Lscala/collection/IterableLike;I)Ljava/lang/Object;
Method	scala/collection/IterableLike$class.take:(Lscala/collection/IterableLike;I)Ljava/lang/Object;
Asciz	n;
Asciz	I;
Asciz	slice;
Asciz	(II)Ljava/lang/Object;;
Asciz	(Lscala/collection/IterableLike;II)Ljava/lang/Object;;
NameAndType	slice:(Lscala/collection/IterableLike;II)Ljava/lang/Object;
Method	scala/collection/IterableLike$class.slice:(Lscala/collection/IterableLike;II)Ljava/lang/Object;
Asciz	from;
Asciz	until;
Asciz	takeWhile;
Asciz	(Lscala/Function1;)Ljava/lang/Object;;
Asciz	(Lscala/collection/IterableLike;Lscala/Function1;)Ljava/lang/Object;;
NameAndType	takeWhile:(Lscala/collection/IterableLike;Lscala/Function1;)Ljava/lang/Object;
Method	scala/collection/IterableLike$class.takeWhile:(Lscala/collection/IterableLike;Lscala/Function1;)Ljava/lang/Object;
Asciz	grouped;
Asciz	(I)Lscala/collection/Iterator;;
Asciz	(Lscala/collection/IterableLike;I)Lscala/collection/Iterator;;
NameAndType	grouped:(Lscala/collection/IterableLike;I)Lscala/collection/Iterator;
Method	scala/collection/IterableLike$class.grouped:(Lscala/collection/IterableLike;I)Lscala/collection/Iterator;
Asciz	size;
Asciz	sliding;
NameAndType	sliding:(Lscala/collection/IterableLike;I)Lscala/collection/Iterator;
Method	scala/collection/IterableLike$class.sliding:(Lscala/collection/IterableLike;I)Lscala/collection/Iterator;
Asciz	(II)Lscala/collection/Iterator;;
Asciz	(Lscala/collection/IterableLike;II)Lscala/collection/Iterator;;
NameAndType	sliding:(Lscala/collection/IterableLike;II)Lscala/collection/Iterator;
Method	scala/collection/IterableLike$class.sliding:(Lscala/collection/IterableLike;II)Lscala/collection/Iterator;
Asciz	step;
Asciz	takeRight;
NameAndType	takeRight:(Lscala/collection/IterableLike;I)Ljava/lang/Object;
Method	scala/collection/IterableLike$class.takeRight:(Lscala/collection/IterableLike;I)Ljava/lang/Object;
Asciz	dropRight;
NameAndType	dropRight:(Lscala/collection/IterableLike;I)Ljava/lang/Object;
Method	scala/collection/IterableLike$class.dropRight:(Lscala/collection/IterableLike;I)Ljava/lang/Object;
Asciz	copyToArray;
Asciz	(Ljava/lang/Object;II)V;
Asciz	(Lscala/collection/IterableLike;Ljava/lang/Object;II)V;
NameAndType	copyToArray:(Lscala/collection/IterableLike;Ljava/lang/Object;II)V
Method	scala/collection/IterableLike$class.copyToArray:(Lscala/collection/IterableLike;Ljava/lang/Object;II)V
Asciz	xs;
Asciz	len;
Asciz	zip;
Asciz	(Lscala/collection/Iterable;Lscala/collection/generic/CanBuildFrom;)Ljava/lang/Object;;
Asciz	(Lscala/collection/IterableLike;Lscala/collection/Iterable;Lscala/collection/generic/CanBuildFrom;)Ljava/lang/Object;;
NameAndType	zip:(Lscala/collection/IterableLike;Lscala/collection/Iterable;Lscala/collection/generic/CanBuildFrom;)Ljava/lang/Object;
Method	scala/collection/IterableLike$class.zip:(Lscala/collection/IterableLike;Lscala/collection/Iterable;Lscala/collection/generic/CanBuildFrom;)Ljava/lang/Object;
Asciz	Lscala/collection/Iterable;;
Asciz	bf;
Asciz	Lscala/collection/generic/CanBuildFrom;;
Asciz	zipAll;
Asciz	(Lscala/collection/Iterable;Ljava/lang/Object;Ljava/lang/Object;Lscala/collection/generic/CanBuildFrom;)Ljava/lang/Object;;
Asciz	(Lscala/collection/IterableLike;Lscala/collection/Iterable;Ljava/lang/Object;Ljava/lang/Object;Lscala/collection/generic/CanBuildFrom;)Ljava/lang/Object;;
NameAndType	zipAll:(Lscala/collection/IterableLike;Lscala/collection/Iterable;Ljava/lang/Object;Ljava/lang/Object;Lscala/collection/generic/CanBuildFrom;)Ljava/lang/Object;
Method	scala/collection/IterableLike$class.zipAll:(Lscala/collection/IterableLike;Lscala/collection/Iterable;Ljava/lang/Object;Ljava/lang/Object;Lscala/collection/generic/CanBuildFrom;)Ljava/lang/Object;
Asciz	thisElem;
Asciz	thatElem;
Asciz	zipWithIndex;
Asciz	(Lscala/collection/generic/CanBuildFrom;)Ljava/lang/Object;;
Asciz	(Lscala/collection/IterableLike;Lscala/collection/generic/CanBuildFrom;)Ljava/lang/Object;;
NameAndType	zipWithIndex:(Lscala/collection/IterableLike;Lscala/collection/generic/CanBuildFrom;)Ljava/lang/Object;
Method	scala/collection/IterableLike$class.zipWithIndex:(Lscala/collection/IterableLike;Lscala/collection/generic/CanBuildFrom;)Ljava/lang/Object;
Asciz	sameElements;
Asciz	(Lscala/collection/Iterable;)Z;
Asciz	(Lscala/collection/IterableLike;Lscala/collection/Iterable;)Z;
NameAndType	sameElements:(Lscala/collection/IterableLike;Lscala/collection/Iterable;)Z
Method	scala/collection/IterableLike$class.sameElements:(Lscala/collection/IterableLike;Lscala/collection/Iterable;)Z
Asciz	toStream;
Asciz	()Lscala/collection/immutable/Stream;;
Asciz	(Lscala/collection/IterableLike;)Lscala/collection/immutable/Stream;;
NameAndType	toStream:(Lscala/collection/IterableLike;)Lscala/collection/immutable/Stream;
Method	scala/collection/IterableLike$class.toStream:(Lscala/collection/IterableLike;)Lscala/collection/immutable/Stream;
Asciz	canEqual;
Asciz	(Lscala/collection/IterableLike;Ljava/lang/Object;)Z;
NameAndType	canEqual:(Lscala/collection/IterableLike;Ljava/lang/Object;)Z
Method	scala/collection/IterableLike$class.canEqual:(Lscala/collection/IterableLike;Ljava/lang/Object;)Z
Asciz	view;
Asciz	()Lscala/collection/IterableView;;
Asciz	(Lscala/collection/IterableLike;)Lscala/collection/IterableView;;
NameAndType	view:(Lscala/collection/IterableLike;)Lscala/collection/IterableView;
Method	scala/collection/IterableLike$class.view:(Lscala/collection/IterableLike;)Lscala/collection/IterableView;
Asciz	(II)Lscala/collection/IterableView;;
Asciz	(Lscala/collection/IterableLike;II)Lscala/collection/IterableView;;
NameAndType	view:(Lscala/collection/IterableLike;II)Lscala/collection/IterableView;
Method	scala/collection/IterableLike$class.view:(Lscala/collection/IterableLike;II)Lscala/collection/IterableView;
Asciz	first;
NameAndType	first:(Lscala/collection/IterableLike;)Ljava/lang/Object;
Method	scala/collection/IterableLike$class.first:(Lscala/collection/IterableLike;)Ljava/lang/Object;
Asciz	firstOption;
Asciz	()Lscala/Option;;
Asciz	(Lscala/collection/IterableLike;)Lscala/Option;;
NameAndType	firstOption:(Lscala/collection/IterableLike;)Lscala/Option;
Method	scala/collection/IterableLike$class.firstOption:(Lscala/collection/IterableLike;)Lscala/Option;
Asciz	projection;
NameAndType	projection:(Lscala/collection/IterableLike;)Lscala/collection/IterableView;
Method	scala/collection/IterableLike$class.projection:(Lscala/collection/IterableLike;)Lscala/collection/IterableView;
Asciz	genericBuilder;
Asciz	scala/collection/generic/GenericTraversableTemplate$class;
class	scala/collection/generic/GenericTraversableTemplate$class
Asciz	(Lscala/collection/generic/GenericTraversableTemplate;)Lscala/collection/mutable/Builder;;
NameAndType	genericBuilder:(Lscala/collection/generic/GenericTraversableTemplate;)Lscala/collection/mutable/Builder;
Method	scala/collection/generic/GenericTraversableTemplate$class.genericBuilder:(Lscala/collection/generic/GenericTraversableTemplate;)Lscala/collection/mutable/Builder;
Asciz	unzip;
Asciz	(Lscala/Function1;)Lscala/Tuple2;;
Asciz	(Lscala/collection/generic/GenericTraversableTemplate;Lscala/Function1;)Lscala/Tuple2;;
NameAndType	unzip:(Lscala/collection/generic/GenericTraversableTemplate;Lscala/Function1;)Lscala/Tuple2;
Method	scala/collection/generic/GenericTraversableTemplate$class.unzip:(Lscala/collection/generic/GenericTraversableTemplate;Lscala/Function1;)Lscala/Tuple2;
Asciz	asPair;
Asciz	flatten;
Asciz	(Lscala/Function1;)Lscala/collection/Traversable;;
Asciz	(Lscala/collection/generic/GenericTraversableTemplate;Lscala/Function1;)Lscala/collection/Traversable;;
NameAndType	flatten:(Lscala/collection/generic/GenericTraversableTemplate;Lscala/Function1;)Lscala/collection/Traversable;
Method	scala/collection/generic/GenericTraversableTemplate$class.flatten:(Lscala/collection/generic/GenericTraversableTemplate;Lscala/Function1;)Lscala/collection/Traversable;
Asciz	asTraversable;
Asciz	transpose;
NameAndType	transpose:(Lscala/collection/generic/GenericTraversableTemplate;Lscala/Function1;)Lscala/collection/Traversable;
Method	scala/collection/generic/GenericTraversableTemplate$class.transpose:(Lscala/collection/generic/GenericTraversableTemplate;Lscala/Function1;)Lscala/collection/Traversable;
Asciz	scala/collection/TraversableLike$class;
class	scala/collection/TraversableLike$class
Asciz	(Lscala/collection/TraversableLike;)Ljava/lang/Object;;
NameAndType	repr:(Lscala/collection/TraversableLike;)Ljava/lang/Object;
Method	scala/collection/TraversableLike$class.repr:(Lscala/collection/TraversableLike;)Ljava/lang/Object;
Asciz	nonEmpty;
Asciz	(Lscala/collection/TraversableLike;)Z;
NameAndType	nonEmpty:(Lscala/collection/TraversableLike;)Z
Method	scala/collection/TraversableLike$class.nonEmpty:(Lscala/collection/TraversableLike;)Z
Asciz	(Lscala/collection/TraversableLike;)I;
NameAndType	size:(Lscala/collection/TraversableLike;)I
Method	scala/collection/TraversableLike$class.size:(Lscala/collection/TraversableLike;)I
Asciz	hasDefiniteSize;
NameAndType	hasDefiniteSize:(Lscala/collection/TraversableLike;)Z
Method	scala/collection/TraversableLike$class.hasDefiniteSize:(Lscala/collection/TraversableLike;)Z
Asciz	(Lscala/collection/Traversable;Lscala/collection/generic/CanBuildFrom;)Ljava/lang/Object;;
Asciz	(Lscala/collection/TraversableLike;Lscala/collection/Traversable;Lscala/collection/generic/CanBuildFrom;)Ljava/lang/Object;;
NameAndType	$plus$plus:(Lscala/collection/TraversableLike;Lscala/collection/Traversable;Lscala/collection/generic/CanBuildFrom;)Ljava/lang/Object;
Method	scala/collection/TraversableLike$class.$plus$plus:(Lscala/collection/TraversableLike;Lscala/collection/Traversable;Lscala/collection/generic/CanBuildFrom;)Ljava/lang/Object;
Asciz	(Lscala/collection/Iterator;Lscala/collection/generic/CanBuildFrom;)Ljava/lang/Object;;
Asciz	(Lscala/collection/TraversableLike;Lscala/collection/Iterator;Lscala/collection/generic/CanBuildFrom;)Ljava/lang/Object;;
NameAndType	$plus$plus:(Lscala/collection/TraversableLike;Lscala/collection/Iterator;Lscala/collection/generic/CanBuildFrom;)Ljava/lang/Object;
Method	scala/collection/TraversableLike$class.$plus$plus:(Lscala/collection/TraversableLike;Lscala/collection/Iterator;Lscala/collection/generic/CanBuildFrom;)Ljava/lang/Object;
Asciz	map;
Asciz	(Lscala/Function1;Lscala/collection/generic/CanBuildFrom;)Ljava/lang/Object;;
Asciz	(Lscala/collection/TraversableLike;Lscala/Function1;Lscala/collection/generic/CanBuildFrom;)Ljava/lang/Object;;
NameAndType	map:(Lscala/collection/TraversableLike;Lscala/Function1;Lscala/collection/generic/CanBuildFrom;)Ljava/lang/Object;
Method	scala/collection/TraversableLike$class.map:(Lscala/collection/TraversableLike;Lscala/Function1;Lscala/collection/generic/CanBuildFrom;)Ljava/lang/Object;
Asciz	flatMap;
NameAndType	flatMap:(Lscala/collection/TraversableLike;Lscala/Function1;Lscala/collection/generic/CanBuildFrom;)Ljava/lang/Object;
Method	scala/collection/TraversableLike$class.flatMap:(Lscala/collection/TraversableLike;Lscala/Function1;Lscala/collection/generic/CanBuildFrom;)Ljava/lang/Object;
Asciz	filter;
Asciz	(Lscala/collection/TraversableLike;Lscala/Function1;)Ljava/lang/Object;;
NameAndType	filter:(Lscala/collection/TraversableLike;Lscala/Function1;)Ljava/lang/Object;
Method	scala/collection/TraversableLike$class.filter:(Lscala/collection/TraversableLike;Lscala/Function1;)Ljava/lang/Object;
Asciz	partialMap;
Asciz	(Lscala/PartialFunction;Lscala/collection/generic/CanBuildFrom;)Ljava/lang/Object;;
Asciz	(Lscala/collection/TraversableLike;Lscala/PartialFunction;Lscala/collection/generic/CanBuildFrom;)Ljava/lang/Object;;
NameAndType	partialMap:(Lscala/collection/TraversableLike;Lscala/PartialFunction;Lscala/collection/generic/CanBuildFrom;)Ljava/lang/Object;
Method	scala/collection/TraversableLike$class.partialMap:(Lscala/collection/TraversableLike;Lscala/PartialFunction;Lscala/collection/generic/CanBuildFrom;)Ljava/lang/Object;
Asciz	pf;
Asciz	partition;
Asciz	(Lscala/collection/TraversableLike;Lscala/Function1;)Lscala/Tuple2;;
NameAndType	partition:(Lscala/collection/TraversableLike;Lscala/Function1;)Lscala/Tuple2;
Method	scala/collection/TraversableLike$class.partition:(Lscala/collection/TraversableLike;Lscala/Function1;)Lscala/Tuple2;
Asciz	groupBy;
Asciz	(Lscala/collection/TraversableLike;Lscala/Function1;)Lscala/collection/Map;;
NameAndType	groupBy:(Lscala/collection/TraversableLike;Lscala/Function1;)Lscala/collection/Map;
Method	scala/collection/TraversableLike$class.groupBy:(Lscala/collection/TraversableLike;Lscala/Function1;)Lscala/collection/Map;
Asciz	count;
Asciz	(Lscala/Function1;)I;
Asciz	(Lscala/collection/TraversableLike;Lscala/Function1;)I;
NameAndType	count:(Lscala/collection/TraversableLike;Lscala/Function1;)I
Method	scala/collection/TraversableLike$class.count:(Lscala/collection/TraversableLike;Lscala/Function1;)I
Asciz	foldLeft;
Asciz	(Lscala/collection/TraversableLike;Ljava/lang/Object;Lscala/Function2;)Ljava/lang/Object;;
NameAndType	foldLeft:(Lscala/collection/TraversableLike;Ljava/lang/Object;Lscala/Function2;)Ljava/lang/Object;
Method	scala/collection/TraversableLike$class.foldLeft:(Lscala/collection/TraversableLike;Ljava/lang/Object;Lscala/Function2;)Ljava/lang/Object;
Asciz	$div$colon;
NameAndType	$div$colon:(Lscala/collection/TraversableLike;Ljava/lang/Object;Lscala/Function2;)Ljava/lang/Object;
Method	scala/collection/TraversableLike$class.$div$colon:(Lscala/collection/TraversableLike;Ljava/lang/Object;Lscala/Function2;)Ljava/lang/Object;
Asciz	$colon$bslash;
NameAndType	$colon$bslash:(Lscala/collection/TraversableLike;Ljava/lang/Object;Lscala/Function2;)Ljava/lang/Object;
Method	scala/collection/TraversableLike$class.$colon$bslash:(Lscala/collection/TraversableLike;Ljava/lang/Object;Lscala/Function2;)Ljava/lang/Object;
Asciz	reduceLeft;
Asciz	(Lscala/collection/TraversableLike;Lscala/Function2;)Ljava/lang/Object;;
NameAndType	reduceLeft:(Lscala/collection/TraversableLike;Lscala/Function2;)Ljava/lang/Object;
Method	scala/collection/TraversableLike$class.reduceLeft:(Lscala/collection/TraversableLike;Lscala/Function2;)Ljava/lang/Object;
Asciz	reduceLeftOption;
Asciz	(Lscala/Function2;)Lscala/Option;;
Asciz	(Lscala/collection/TraversableLike;Lscala/Function2;)Lscala/Option;;
NameAndType	reduceLeftOption:(Lscala/collection/TraversableLike;Lscala/Function2;)Lscala/Option;
Method	scala/collection/TraversableLike$class.reduceLeftOption:(Lscala/collection/TraversableLike;Lscala/Function2;)Lscala/Option;
Asciz	reduceRightOption;
NameAndType	reduceRightOption:(Lscala/collection/TraversableLike;Lscala/Function2;)Lscala/Option;
Method	scala/collection/TraversableLike$class.reduceRightOption:(Lscala/collection/TraversableLike;Lscala/Function2;)Lscala/Option;
Asciz	sum;
Asciz	(Lscala/math/Numeric;)Ljava/lang/Object;;
Asciz	(Lscala/collection/TraversableLike;Lscala/math/Numeric;)Ljava/lang/Object;;
NameAndType	sum:(Lscala/collection/TraversableLike;Lscala/math/Numeric;)Ljava/lang/Object;
Method	scala/collection/TraversableLike$class.sum:(Lscala/collection/TraversableLike;Lscala/math/Numeric;)Ljava/lang/Object;
Asciz	num;
Asciz	Lscala/math/Numeric;;
Asciz	product;
NameAndType	product:(Lscala/collection/TraversableLike;Lscala/math/Numeric;)Ljava/lang/Object;
Method	scala/collection/TraversableLike$class.product:(Lscala/collection/TraversableLike;Lscala/math/Numeric;)Ljava/lang/Object;
Asciz	min;
Asciz	(Lscala/math/Ordering;)Ljava/lang/Object;;
Asciz	(Lscala/collection/TraversableLike;Lscala/math/Ordering;)Ljava/lang/Object;;
NameAndType	min:(Lscala/collection/TraversableLike;Lscala/math/Ordering;)Ljava/lang/Object;
Method	scala/collection/TraversableLike$class.min:(Lscala/collection/TraversableLike;Lscala/math/Ordering;)Ljava/lang/Object;
Asciz	cmp;
Asciz	Lscala/math/Ordering;;
Asciz	max;
NameAndType	max:(Lscala/collection/TraversableLike;Lscala/math/Ordering;)Ljava/lang/Object;
Method	scala/collection/TraversableLike$class.max:(Lscala/collection/TraversableLike;Lscala/math/Ordering;)Ljava/lang/Object;
Asciz	headOption;
Asciz	(Lscala/collection/TraversableLike;)Lscala/Option;;
NameAndType	headOption:(Lscala/collection/TraversableLike;)Lscala/Option;
Method	scala/collection/TraversableLike$class.headOption:(Lscala/collection/TraversableLike;)Lscala/Option;
Asciz	tail;
NameAndType	tail:(Lscala/collection/TraversableLike;)Ljava/lang/Object;
Method	scala/collection/TraversableLike$class.tail:(Lscala/collection/TraversableLike;)Ljava/lang/Object;
Asciz	last;
NameAndType	last:(Lscala/collection/TraversableLike;)Ljava/lang/Object;
Method	scala/collection/TraversableLike$class.last:(Lscala/collection/TraversableLike;)Ljava/lang/Object;
Asciz	lastOption;
NameAndType	lastOption:(Lscala/collection/TraversableLike;)Lscala/Option;
Method	scala/collection/TraversableLike$class.lastOption:(Lscala/collection/TraversableLike;)Lscala/Option;
Asciz	init;
NameAndType	init:(Lscala/collection/TraversableLike;)Ljava/lang/Object;
Method	scala/collection/TraversableLike$class.init:(Lscala/collection/TraversableLike;)Ljava/lang/Object;
Asciz	drop;
Asciz	(Lscala/collection/TraversableLike;I)Ljava/lang/Object;;
NameAndType	drop:(Lscala/collection/TraversableLike;I)Ljava/lang/Object;
Method	scala/collection/TraversableLike$class.drop:(Lscala/collection/TraversableLike;I)Ljava/lang/Object;
Asciz	dropWhile;
NameAndType	dropWhile:(Lscala/collection/TraversableLike;Lscala/Function1;)Ljava/lang/Object;
Method	scala/collection/TraversableLike$class.dropWhile:(Lscala/collection/TraversableLike;Lscala/Function1;)Ljava/lang/Object;
Asciz	span;
NameAndType	span:(Lscala/collection/TraversableLike;Lscala/Function1;)Lscala/Tuple2;
Method	scala/collection/TraversableLike$class.span:(Lscala/collection/TraversableLike;Lscala/Function1;)Lscala/Tuple2;
Asciz	splitAt;
Asciz	(I)Lscala/Tuple2;;
Asciz	(Lscala/collection/TraversableLike;I)Lscala/Tuple2;;
NameAndType	splitAt:(Lscala/collection/TraversableLike;I)Lscala/Tuple2;
Method	scala/collection/TraversableLike$class.splitAt:(Lscala/collection/TraversableLike;I)Lscala/Tuple2;
Asciz	copyToBuffer;
Asciz	(Lscala/collection/mutable/Buffer;)V;
Asciz	(Lscala/collection/TraversableLike;Lscala/collection/mutable/Buffer;)V;
NameAndType	copyToBuffer:(Lscala/collection/TraversableLike;Lscala/collection/mutable/Buffer;)V
Method	scala/collection/TraversableLike$class.copyToBuffer:(Lscala/collection/TraversableLike;Lscala/collection/mutable/Buffer;)V
Asciz	dest;
Asciz	Lscala/collection/mutable/Buffer;;
Asciz	(Ljava/lang/Object;I)V;
Asciz	(Lscala/collection/TraversableLike;Ljava/lang/Object;I)V;
NameAndType	copyToArray:(Lscala/collection/TraversableLike;Ljava/lang/Object;I)V
Method	scala/collection/TraversableLike$class.copyToArray:(Lscala/collection/TraversableLike;Ljava/lang/Object;I)V
Asciz	(Ljava/lang/Object;)V;
Asciz	(Lscala/collection/TraversableLike;Ljava/lang/Object;)V;
NameAndType	copyToArray:(Lscala/collection/TraversableLike;Ljava/lang/Object;)V
Method	scala/collection/TraversableLike$class.copyToArray:(Lscala/collection/TraversableLike;Ljava/lang/Object;)V
Asciz	toArray;
Asciz	(Lscala/reflect/ClassManifest;)Ljava/lang/Object;;
Asciz	(Lscala/collection/TraversableLike;Lscala/reflect/ClassManifest;)Ljava/lang/Object;;
NameAndType	toArray:(Lscala/collection/TraversableLike;Lscala/reflect/ClassManifest;)Ljava/lang/Object;
Method	scala/collection/TraversableLike$class.toArray:(Lscala/collection/TraversableLike;Lscala/reflect/ClassManifest;)Ljava/lang/Object;
Asciz	evidence$1;
Asciz	Lscala/reflect/ClassManifest;;
Asciz	toList;
Asciz	()Lscala/collection/immutable/List;;
Asciz	(Lscala/collection/TraversableLike;)Lscala/collection/immutable/List;;
NameAndType	toList:(Lscala/collection/TraversableLike;)Lscala/collection/immutable/List;
Method	scala/collection/TraversableLike$class.toList:(Lscala/collection/TraversableLike;)Lscala/collection/immutable/List;
Asciz	toSeq;
Asciz	()Lscala/collection/Seq;;
Asciz	(Lscala/collection/TraversableLike;)Lscala/collection/Seq;;
NameAndType	toSeq:(Lscala/collection/TraversableLike;)Lscala/collection/Seq;
Method	scala/collection/TraversableLike$class.toSeq:(Lscala/collection/TraversableLike;)Lscala/collection/Seq;
Asciz	toIndexedSeq;
Asciz	()Lscala/collection/mutable/IndexedSeq;;
Asciz	(Lscala/collection/TraversableLike;)Lscala/collection/mutable/IndexedSeq;;
NameAndType	toIndexedSeq:(Lscala/collection/TraversableLike;)Lscala/collection/mutable/IndexedSeq;
Method	scala/collection/TraversableLike$class.toIndexedSeq:(Lscala/collection/TraversableLike;)Lscala/collection/mutable/IndexedSeq;
Asciz	toSet;
Asciz	()Lscala/collection/immutable/Set;;
Asciz	(Lscala/collection/TraversableLike;)Lscala/collection/immutable/Set;;
NameAndType	toSet:(Lscala/collection/TraversableLike;)Lscala/collection/immutable/Set;
Method	scala/collection/TraversableLike$class.toSet:(Lscala/collection/TraversableLike;)Lscala/collection/immutable/Set;
Asciz	toMap;
Asciz	(Lscala/Predef$$less$colon$less;)Lscala/collection/immutable/Map;;
Asciz	(Lscala/collection/TraversableLike;Lscala/Predef$$less$colon$less;)Lscala/collection/immutable/Map;;
NameAndType	toMap:(Lscala/collection/TraversableLike;Lscala/Predef$$less$colon$less;)Lscala/collection/immutable/Map;
Method	scala/collection/TraversableLike$class.toMap:(Lscala/collection/TraversableLike;Lscala/Predef$$less$colon$less;)Lscala/collection/immutable/Map;
Asciz	ev;
Asciz	Lscala/Predef$$less$colon$less;;
Asciz	mkString;
Asciz	(Ljava/lang/String;Ljava/lang/String;Ljava/lang/String;)Ljava/lang/String;;
Asciz	(Lscala/collection/TraversableLike;Ljava/lang/String;Ljava/lang/String;Ljava/lang/String;)Ljava/lang/String;;
NameAndType	mkString:(Lscala/collection/TraversableLike;Ljava/lang/String;Ljava/lang/String;Ljava/lang/String;)Ljava/lang/String;
Method	scala/collection/TraversableLike$class.mkString:(Lscala/collection/TraversableLike;Ljava/lang/String;Ljava/lang/String;Ljava/lang/String;)Ljava/lang/String;
Asciz	(Ljava/lang/String;)Ljava/lang/String;;
Asciz	(Lscala/collection/TraversableLike;Ljava/lang/String;)Ljava/lang/String;;
NameAndType	mkString:(Lscala/collection/TraversableLike;Ljava/lang/String;)Ljava/lang/String;
Method	scala/collection/TraversableLike$class.mkString:(Lscala/collection/TraversableLike;Ljava/lang/String;)Ljava/lang/String;
Asciz	(Lscala/collection/TraversableLike;)Ljava/lang/String;;
NameAndType	mkString:(Lscala/collection/TraversableLike;)Ljava/lang/String;
Method	scala/collection/TraversableLike$class.mkString:(Lscala/collection/TraversableLike;)Ljava/lang/String;
Asciz	(Lscala/collection/mutable/StringBuilder;Ljava/lang/String;)Lscala/collection/mutable/StringBuilder;;
Asciz	(Lscala/collection/TraversableLike;Lscala/collection/mutable/StringBuilder;Ljava/lang/String;)Lscala/collection/mutable/StringBuilder;;
NameAndType	addString:(Lscala/collection/TraversableLike;Lscala/collection/mutable/StringBuilder;Ljava/lang/String;)Lscala/collection/mutable/StringBuilder;
Method	scala/collection/TraversableLike$class.addString:(Lscala/collection/TraversableLike;Lscala/collection/mutable/StringBuilder;Ljava/lang/String;)Lscala/collection/mutable/StringBuilder;
Asciz	(Lscala/collection/mutable/StringBuilder;)Lscala/collection/mutable/StringBuilder;;
Asciz	(Lscala/collection/TraversableLike;Lscala/collection/mutable/StringBuilder;)Lscala/collection/mutable/StringBuilder;;
NameAndType	addString:(Lscala/collection/TraversableLike;Lscala/collection/mutable/StringBuilder;)Lscala/collection/mutable/StringBuilder;
Method	scala/collection/TraversableLike$class.addString:(Lscala/collection/TraversableLike;Lscala/collection/mutable/StringBuilder;)Lscala/collection/mutable/StringBuilder;
Asciz	withFilter;
Asciz	(Lscala/Function1;)Lscala/collection/TraversableLike$WithFilter;;
Asciz	(Lscala/collection/TraversableLike;Lscala/Function1;)Lscala/collection/TraversableLike$WithFilter;;
NameAndType	withFilter:(Lscala/collection/TraversableLike;Lscala/Function1;)Lscala/collection/TraversableLike$WithFilter;
Method	scala/collection/TraversableLike$class.withFilter:(Lscala/collection/TraversableLike;Lscala/Function1;)Lscala/collection/TraversableLike$WithFilter;
Asciz	Signature;
Asciz	foreach;
Asciz	(Lscala/Function1;)V;
Asciz	scala/collection/MapLike$$anon$1;
class	scala/collection/MapLike$$anon$1
NameAndType	$outer:Lscala/collection/MapLike;
Field	scala/collection/MapLike$$anon$1.$outer:Lscala/collection/MapLike;
Asciz	scala/collection/MapLike$$anon$1$$anonfun$foreach$5;
class	scala/collection/MapLike$$anon$1$$anonfun$foreach$5
Asciz	<init>;
Asciz	(Lscala/collection/MapLike$$anon$1;Lscala/Function1;)V;
NameAndType	"<init>":(Lscala/collection/MapLike$$anon$1;Lscala/Function1;)V
Method	scala/collection/MapLike$$anon$1$$anonfun$foreach$5."<init>":(Lscala/collection/MapLike$$anon$1;Lscala/Function1;)V
Asciz	scala/collection/IterableLike;
class	scala/collection/IterableLike
NameAndType	foreach:(Lscala/Function1;)V
InterfaceMethod	scala/collection/IterableLike.foreach:(Lscala/Function1;)V
Asciz	f$3;
Asciz	<C:Ljava/lang/Object;>(Lscala/Function1<Lscala/Tuple2<TA;TB;>;TC;>;)V;
Asciz	iterator;
Asciz	scala/collection/MapLike;
class	scala/collection/MapLike
NameAndType	iterator:()Lscala/collection/Iterator;
InterfaceMethod	scala/collection/MapLike.iterator:()Lscala/collection/Iterator;
Asciz	scala/collection/MapLike$$anon$1$$anonfun$iterator$1;
class	scala/collection/MapLike$$anon$1$$anonfun$iterator$1
Asciz	(Lscala/collection/MapLike$$anon$1;)V;
NameAndType	"<init>":(Lscala/collection/MapLike$$anon$1;)V
Method	scala/collection/MapLike$$anon$1$$anonfun$iterator$1."<init>":(Lscala/collection/MapLike$$anon$1;)V
Asciz	scala/collection/Iterator;
class	scala/collection/Iterator
Asciz	(Lscala/Function1;)Lscala/collection/Iterator;;
NameAndType	filter:(Lscala/Function1;)Lscala/collection/Iterator;
InterfaceMethod	scala/collection/Iterator.filter:(Lscala/Function1;)Lscala/collection/Iterator;
Asciz	()Lscala/collection/Iterator<Lscala/Tuple2<TA;TB;>;>;;
Asciz	contains;
NameAndType	contains:(Ljava/lang/Object;)Z
InterfaceMethod	scala/collection/MapLike.contains:(Ljava/lang/Object;)Z
NameAndType	p$1:Lscala/Function1;
Field	scala/collection/MapLike$$anon$1.p$1:Lscala/Function1;
Asciz	scala/Function1;
class	scala/Function1
NameAndType	apply:(Ljava/lang/Object;)Ljava/lang/Object;
InterfaceMethod	scala/Function1.apply:(Ljava/lang/Object;)Ljava/lang/Object;
Asciz	scala/runtime/BoxesRunTime;
class	scala/runtime/BoxesRunTime
Asciz	unboxToBoolean;
NameAndType	unboxToBoolean:(Ljava/lang/Object;)Z
Method	scala/runtime/BoxesRunTime.unboxToBoolean:(Ljava/lang/Object;)Z
Asciz	(TA;)Z;
Asciz	get;
Asciz	(Ljava/lang/Object;)Lscala/Option;;
NameAndType	get:(Ljava/lang/Object;)Lscala/Option;
InterfaceMethod	scala/collection/MapLike.get:(Ljava/lang/Object;)Lscala/Option;
Asciz	scala/None$;
class	scala/None$
Asciz	MODULE$;
Asciz	Lscala/None$;;
NameAndType	MODULE$:Lscala/None$;
Field	scala/None$.MODULE$:Lscala/None$;
Asciz	(TA;)Lscala/Option<TB;>;;
Asciz	()Lscala/collection/generic/Subtractable;;
Asciz	scala/collection/TraversableLike;
class	scala/collection/TraversableLike
NameAndType	repr:()Ljava/lang/Object;
InterfaceMethod	scala/collection/TraversableLike.repr:()Ljava/lang/Object;
Asciz	scala/collection/generic/Subtractable;
class	scala/collection/generic/Subtractable
Asciz	(II)Lscala/collection/TraversableView;;
NameAndType	view:(II)Lscala/collection/IterableView;
InterfaceMethod	scala/collection/IterableLike.view:(II)Lscala/collection/IterableView;
Asciz	()Lscala/collection/TraversableView;;
NameAndType	view:()Lscala/collection/IterableView;
InterfaceMethod	scala/collection/IterableLike.view:()Lscala/collection/IterableView;
Asciz	(Ljava/lang/Object;)Lscala/collection/Traversable;;
NameAndType	toCollection:(Ljava/lang/Object;)Lscala/collection/Iterable;
InterfaceMethod	scala/collection/IterableLike.toCollection:(Ljava/lang/Object;)Lscala/collection/Iterable;
Asciz	()Lscala/collection/Traversable;;
NameAndType	thisCollection:()Lscala/collection/Iterable;
InterfaceMethod	scala/collection/IterableLike.thisCollection:()Lscala/collection/Iterable;
Asciz	scala/PartialFunction;
class	scala/PartialFunction
NameAndType	andThen:(Lscala/Function1;)Lscala/PartialFunction;
InterfaceMethod	scala/PartialFunction.andThen:(Lscala/Function1;)Lscala/PartialFunction;
NameAndType	filterNot:(Lscala/Function1;)Lscala/collection/Map;
InterfaceMethod	scala/collection/MapLike.filterNot:(Lscala/Function1;)Lscala/collection/Map;
Asciz	(Ljava/lang/Object;)Lscala/collection/generic/Subtractable;;
Asciz	scala/collection/DefaultMap;
class	scala/collection/DefaultMap
NameAndType	$minus:(Ljava/lang/Object;)Lscala/collection/Map;
InterfaceMethod	scala/collection/DefaultMap.$minus:(Ljava/lang/Object;)Lscala/collection/Map;
Asciz	elem;
Asciz	(Lscala/collection/MapLike;Lscala/Function1;)V;
Asciz	java/lang/NullPointerException;
class	java/lang/NullPointerException
Asciz	()V;
NameAndType	"<init>":()V
Method	java/lang/NullPointerException."<init>":()V
Asciz	java/lang/Object;
class	java/lang/Object
Method	java/lang/Object."<init>":()V
Asciz	$init$;
Asciz	(Lscala/collection/TraversableLike;)V;
NameAndType	$init$:(Lscala/collection/TraversableLike;)V
Method	scala/collection/TraversableLike$class.$init$:(Lscala/collection/TraversableLike;)V
Asciz	(Lscala/collection/generic/GenericTraversableTemplate;)V;
NameAndType	$init$:(Lscala/collection/generic/GenericTraversableTemplate;)V
Method	scala/collection/generic/GenericTraversableTemplate$class.$init$:(Lscala/collection/generic/GenericTraversableTemplate;)V
Asciz	scala/collection/Traversable$class;
class	scala/collection/Traversable$class
Asciz	(Lscala/collection/Traversable;)V;
NameAndType	$init$:(Lscala/collection/Traversable;)V
Method	scala/collection/Traversable$class.$init$:(Lscala/collection/Traversable;)V
Asciz	(Lscala/collection/IterableLike;)V;
NameAndType	$init$:(Lscala/collection/IterableLike;)V
Method	scala/collection/IterableLike$class.$init$:(Lscala/collection/IterableLike;)V
Asciz	(Lscala/collection/Iterable;)V;
NameAndType	$init$:(Lscala/collection/Iterable;)V
Method	scala/collection/Iterable$class.$init$:(Lscala/collection/Iterable;)V
NameAndType	$init$:(Lscala/Function1;)V
Method	scala/Function1$class.$init$:(Lscala/Function1;)V
Asciz	(Lscala/PartialFunction;)V;
NameAndType	$init$:(Lscala/PartialFunction;)V
Method	scala/PartialFunction$class.$init$:(Lscala/PartialFunction;)V
Asciz	(Lscala/collection/generic/Subtractable;)V;
NameAndType	$init$:(Lscala/collection/generic/Subtractable;)V
Method	scala/collection/generic/Subtractable$class.$init$:(Lscala/collection/generic/Subtractable;)V
Asciz	(Lscala/collection/MapLike;)V;
NameAndType	$init$:(Lscala/collection/MapLike;)V
Method	scala/collection/MapLike$class.$init$:(Lscala/collection/MapLike;)V
Asciz	(Lscala/collection/Map;)V;
NameAndType	$init$:(Lscala/collection/Map;)V
Method	scala/collection/Map$class.$init$:(Lscala/collection/Map;)V
Asciz	(Lscala/collection/DefaultMap;)V;
NameAndType	$init$:(Lscala/collection/DefaultMap;)V
Method	scala/collection/DefaultMap$class.$init$:(Lscala/collection/DefaultMap;)V
Asciz	(Lscala/collection/MapLike<TA;TB;TThis;>;)V;
Asciz	Ljava/lang/Object;Lscala/collection/DefaultMap<TA;TB;>;;
Asciz	Scala;
Asciz	InnerClasses;
Asciz	$anon$1;
Asciz	scala/Predef$$less$colon$less;
class	scala/Predef$$less$colon$less
Asciz	scala/Predef;
class	scala/Predef
Asciz	$less$colon$less;
Asciz	scala/collection/TraversableLike$WithFilter;
class	scala/collection/TraversableLike$WithFilter
Asciz	WithFilter;
Asciz	$anonfun$foreach$5;
Asciz	$anonfun$iterator$1;

{
public final scala.Function1 p$1;
  Signature: Lscala/Function1;

private final scala.collection.MapLike $outer;
  Signature: Lscala/collection/MapLike;

public scala.collection.Map $plus(scala.Tuple2);
  Signature: (Lscala/Tuple2;)Lscala/collection/Map;
  Code:
   Stack=2, Locals=2, Args_size=2
	aload_0
	aload_1
	invokestatic	Method scala/collection/DefaultMap$class.$plus:(Lscala/collection/DefaultMap;Lscala/Tuple2;)Lscala/collection/Map;
	areturn
  Labels:
  LocalVariableTable: 
   Start  Length  Slot  Name   Signature
   0      6      0    this       Lscala/collection/MapLike$$anon$1;
   0      6      1    kv       Lscala/Tuple2;


public scala.collection.Map $minus(java.lang.Object);
  Signature: (Ljava/lang/Object;)Lscala/collection/Map;
  Code:
   Stack=2, Locals=2, Args_size=2
	aload_0
	aload_1
	invokestatic	Method scala/collection/DefaultMap$class.$minus:(Lscala/collection/DefaultMap;Ljava/lang/Object;)Lscala/collection/Map;
	areturn
  Labels:
  LocalVariableTable: 
   Start  Length  Slot  Name   Signature
   0      6      0    this       Lscala/collection/MapLike$$anon$1;
   0      6      1    key       Ljava/lang/Object;


public scala.collection.Map empty();
  Signature: ()Lscala/collection/Map;
  Code:
   Stack=1, Locals=1, Args_size=1
	aload_0
	invokestatic	Method scala/collection/Map$class.empty:(Lscala/collection/Map;)Lscala/collection/Map;
	areturn
  Labels:

public scala.collection.mutable.Builder newBuilder();
  Signature: ()Lscala/collection/mutable/Builder;
  Code:
   Stack=1, Locals=1, Args_size=1
	aload_0
	invokestatic	Method scala/collection/MapLike$class.newBuilder:(Lscala/collection/MapLike;)Lscala/collection/mutable/Builder;
	areturn
  Labels:

public boolean isEmpty();
  Signature: ()Z
  Code:
   Stack=1, Locals=1, Args_size=1
	aload_0
	invokestatic	Method scala/collection/MapLike$class.isEmpty:(Lscala/collection/MapLike;)Z
	ireturn
  Labels:

public java.lang.Object getOrElse(java.lang.Object, scala.Function0);
  Signature: (Ljava/lang/Object;Lscala/Function0;)Ljava/lang/Object;
  Code:
   Stack=3, Locals=3, Args_size=3
	aload_0
	aload_1
	aload_2
	invokestatic	Method scala/collection/MapLike$class.getOrElse:(Lscala/collection/MapLike;Ljava/lang/Object;Lscala/Function0;)Ljava/lang/Object;
	areturn
  Labels:
  LocalVariableTable: 
   Start  Length  Slot  Name   Signature
   0      7      0    this       Lscala/collection/MapLike$$anon$1;
   0      7      1    key       Ljava/lang/Object;
   0      7      2    default       Lscala/Function0;


public java.lang.Object apply(java.lang.Object);
  Signature: (Ljava/lang/Object;)Ljava/lang/Object;
  Code:
   Stack=2, Locals=2, Args_size=2
	aload_0
	aload_1
	invokestatic	Method scala/collection/MapLike$class.apply:(Lscala/collection/MapLike;Ljava/lang/Object;)Ljava/lang/Object;
	areturn
  Labels:
  LocalVariableTable: 
   Start  Length  Slot  Name   Signature
   0      6      0    this       Lscala/collection/MapLike$$anon$1;
   0      6      1    key       Ljava/lang/Object;


public boolean isDefinedAt(java.lang.Object);
  Signature: (Ljava/lang/Object;)Z
  Code:
   Stack=2, Locals=2, Args_size=2
	aload_0
	aload_1
	invokestatic	Method scala/collection/MapLike$class.isDefinedAt:(Lscala/collection/MapLike;Ljava/lang/Object;)Z
	ireturn
  Labels:
  LocalVariableTable: 
   Start  Length  Slot  Name   Signature
   0      6      0    this       Lscala/collection/MapLike$$anon$1;
   0      6      1    key       Ljava/lang/Object;


public scala.collection.Set keySet();
  Signature: ()Lscala/collection/Set;
  Code:
   Stack=1, Locals=1, Args_size=1
	aload_0
	invokestatic	Method scala/collection/MapLike$class.keySet:(Lscala/collection/MapLike;)Lscala/collection/Set;
	areturn
  Labels:

public scala.collection.Iterator keysIterator();
  Signature: ()Lscala/collection/Iterator;
  Code:
   Stack=1, Locals=1, Args_size=1
	aload_0
	invokestatic	Method scala/collection/MapLike$class.keysIterator:(Lscala/collection/MapLike;)Lscala/collection/Iterator;
	areturn
  Labels:

public scala.collection.Iterator keys();
  Signature: ()Lscala/collection/Iterator;
  Code:
   Stack=1, Locals=1, Args_size=1
	aload_0
	invokestatic	Method scala/collection/MapLike$class.keys:(Lscala/collection/MapLike;)Lscala/collection/Iterator;
	areturn
  Labels:
  Deprecated: true

public scala.collection.Iterable valuesIterable();
  Signature: ()Lscala/collection/Iterable;
  Code:
   Stack=1, Locals=1, Args_size=1
	aload_0
	invokestatic	Method scala/collection/MapLike$class.valuesIterable:(Lscala/collection/MapLike;)Lscala/collection/Iterable;
	areturn
  Labels:

public scala.collection.Iterator valuesIterator();
  Signature: ()Lscala/collection/Iterator;
  Code:
   Stack=1, Locals=1, Args_size=1
	aload_0
	invokestatic	Method scala/collection/MapLike$class.valuesIterator:(Lscala/collection/MapLike;)Lscala/collection/Iterator;
	areturn
  Labels:

public scala.collection.Iterator values();
  Signature: ()Lscala/collection/Iterator;
  Code:
   Stack=1, Locals=1, Args_size=1
	aload_0
	invokestatic	Method scala/collection/MapLike$class.values:(Lscala/collection/MapLike;)Lscala/collection/Iterator;
	areturn
  Labels:
  Deprecated: true

public java.lang.Object default(java.lang.Object);
  Signature: (Ljava/lang/Object;)Ljava/lang/Object;
  Code:
   Stack=2, Locals=2, Args_size=2
	aload_0
	aload_1
	invokestatic	Method scala/collection/MapLike$class.default:(Lscala/collection/MapLike;Ljava/lang/Object;)Ljava/lang/Object;
	areturn
  Labels:
  LocalVariableTable: 
   Start  Length  Slot  Name   Signature
   0      6      0    this       Lscala/collection/MapLike$$anon$1;
   0      6      1    key       Ljava/lang/Object;


public scala.collection.Map filterKeys(scala.Function1);
  Signature: (Lscala/Function1;)Lscala/collection/Map;
  Code:
   Stack=2, Locals=2, Args_size=2
	aload_0
	aload_1
	invokestatic	Method scala/collection/MapLike$class.filterKeys:(Lscala/collection/MapLike;Lscala/Function1;)Lscala/collection/Map;
	areturn
  Labels:
  LocalVariableTable: 
   Start  Length  Slot  Name   Signature
   0      6      0    this       Lscala/collection/MapLike$$anon$1;
   0      6      1    p       Lscala/Function1;


public scala.collection.Map mapValues(scala.Function1);
  Signature: (Lscala/Function1;)Lscala/collection/Map;
  Code:
   Stack=2, Locals=2, Args_size=2
	aload_0
	aload_1
	invokestatic	Method scala/collection/MapLike$class.mapValues:(Lscala/collection/MapLike;Lscala/Function1;)Lscala/collection/Map;
	areturn
  Labels:
  LocalVariableTable: 
   Start  Length  Slot  Name   Signature
   0      6      0    this       Lscala/collection/MapLike$$anon$1;
   0      6      1    f       Lscala/Function1;


public scala.collection.Map mapElements(scala.Function1);
  Signature: (Lscala/Function1;)Lscala/collection/Map;
  Code:
   Stack=2, Locals=2, Args_size=2
	aload_0
	aload_1
	invokestatic	Method scala/collection/MapLike$class.mapElements:(Lscala/collection/MapLike;Lscala/Function1;)Lscala/collection/Map;
	areturn
  Labels:
  LocalVariableTable: 
   Start  Length  Slot  Name   Signature
   0      6      0    this       Lscala/collection/MapLike$$anon$1;
   0      6      1    f       Lscala/Function1;

  Deprecated: true

public scala.collection.Map updated(java.lang.Object, java.lang.Object);
  Signature: (Ljava/lang/Object;Ljava/lang/Object;)Lscala/collection/Map;
  Code:
   Stack=3, Locals=3, Args_size=3
	aload_0
	aload_1
	aload_2
	invokestatic	Method scala/collection/MapLike$class.updated:(Lscala/collection/MapLike;Ljava/lang/Object;Ljava/lang/Object;)Lscala/collection/Map;
	areturn
  Labels:
  LocalVariableTable: 
   Start  Length  Slot  Name   Signature
   0      7      0    this       Lscala/collection/MapLike$$anon$1;
   0      7      1    key       Ljava/lang/Object;
   0      7      2    value       Ljava/lang/Object;


public scala.collection.Map $plus(scala.Tuple2, scala.Tuple2, scala.collection.Seq);
  Signature: (Lscala/Tuple2;Lscala/Tuple2;Lscala/collection/Seq;)Lscala/collection/Map;
  Code:
   Stack=4, Locals=4, Args_size=4
	aload_0
	aload_1
	aload_2
	aload_3
	invokestatic	Method scala/collection/MapLike$class.$plus:(Lscala/collection/MapLike;Lscala/Tuple2;Lscala/Tuple2;Lscala/collection/Seq;)Lscala/collection/Map;
	areturn
  Labels:
  LocalVariableTable: 
   Start  Length  Slot  Name   Signature
   0      8      0    this       Lscala/collection/MapLike$$anon$1;
   0      8      1    kv1       Lscala/Tuple2;
   0      8      2    kv2       Lscala/Tuple2;
   0      8      3    kvs       Lscala/collection/Seq;


public scala.collection.Map $plus$plus(scala.collection.Traversable);
  Signature: (Lscala/collection/Traversable;)Lscala/collection/Map;
  Code:
   Stack=2, Locals=2, Args_size=2
	aload_0
	aload_1
	invokestatic	Method scala/collection/MapLike$class.$plus$plus:(Lscala/collection/MapLike;Lscala/collection/Traversable;)Lscala/collection/Map;
	areturn
  Labels:
  LocalVariableTable: 
   Start  Length  Slot  Name   Signature
   0      6      0    this       Lscala/collection/MapLike$$anon$1;
   0      6      1    kvs       Lscala/collection/Traversable;


public scala.collection.Map $plus$plus(scala.collection.Iterator);
  Signature: (Lscala/collection/Iterator;)Lscala/collection/Map;
  Code:
   Stack=2, Locals=2, Args_size=2
	aload_0
	aload_1
	invokestatic	Method scala/collection/MapLike$class.$plus$plus:(Lscala/collection/MapLike;Lscala/collection/Iterator;)Lscala/collection/Map;
	areturn
  Labels:
  LocalVariableTable: 
   Start  Length  Slot  Name   Signature
   0      6      0    this       Lscala/collection/MapLike$$anon$1;
   0      6      1    iter       Lscala/collection/Iterator;


public scala.collection.Map filterNot(scala.Function1);
  Signature: (Lscala/Function1;)Lscala/collection/Map;
  Code:
   Stack=2, Locals=2, Args_size=2
	aload_0
	aload_1
	invokestatic	Method scala/collection/MapLike$class.filterNot:(Lscala/collection/MapLike;Lscala/Function1;)Lscala/collection/Map;
	areturn
  Labels:
  LocalVariableTable: 
   Start  Length  Slot  Name   Signature
   0      6      0    this       Lscala/collection/MapLike$$anon$1;
   0      6      1    p       Lscala/Function1;


public scala.collection.mutable.StringBuilder addString(scala.collection.mutable.StringBuilder, java.lang.String, java.lang.String, java.lang.String);
  Signature: (Lscala/collection/mutable/StringBuilder;Ljava/lang/String;Ljava/lang/String;Ljava/lang/String;)Lscala/collection/mutable/StringBuilder;
  Code:
   Stack=5, Locals=5, Args_size=5
	aload_0
	aload_1
	aload_2
	aload_3
	aload	4
	invokestatic	Method scala/collection/MapLike$class.addString:(Lscala/collection/MapLike;Lscala/collection/mutable/StringBuilder;Ljava/lang/String;Ljava/lang/String;Ljava/lang/String;)Lscala/collection/mutable/StringBuilder;
	areturn
  Labels:
  LocalVariableTable: 
   Start  Length  Slot  Name   Signature
   0      10      0    this       Lscala/collection/MapLike$$anon$1;
   0      10      1    b       Lscala/collection/mutable/StringBuilder;
   0      10      2    start       Ljava/lang/String;
   0      10      3    sep       Ljava/lang/String;
   0      10      4    end       Ljava/lang/String;


public java.lang.String stringPrefix();
  Signature: ()Ljava/lang/String;
  Code:
   Stack=1, Locals=1, Args_size=1
	aload_0
	invokestatic	Method scala/collection/MapLike$class.stringPrefix:(Lscala/collection/MapLike;)Ljava/lang/String;
	areturn
  Labels:

public java.lang.String toString();
  Signature: ()Ljava/lang/String;
  Code:
   Stack=1, Locals=1, Args_size=1
	aload_0
	invokestatic	Method scala/collection/MapLike$class.toString:(Lscala/collection/MapLike;)Ljava/lang/String;
	areturn
  Labels:

public int hashCode();
  Signature: ()I
  Code:
   Stack=1, Locals=1, Args_size=1
	aload_0
	invokestatic	Method scala/collection/MapLike$class.hashCode:(Lscala/collection/MapLike;)I
	ireturn
  Labels:

public boolean equals(java.lang.Object);
  Signature: (Ljava/lang/Object;)Z
  Code:
   Stack=2, Locals=2, Args_size=2
	aload_0
	aload_1
	invokestatic	Method scala/collection/MapLike$class.equals:(Lscala/collection/MapLike;Ljava/lang/Object;)Z
	ireturn
  Labels:
  LocalVariableTable: 
   Start  Length  Slot  Name   Signature
   0      6      0    this       Lscala/collection/MapLike$$anon$1;
   0      6      1    that       Ljava/lang/Object;


public scala.collection.generic.Subtractable $minus(java.lang.Object, java.lang.Object, scala.collection.Seq);
  Signature: (Ljava/lang/Object;Ljava/lang/Object;Lscala/collection/Seq;)Lscala/collection/generic/Subtractable;
  Code:
   Stack=4, Locals=4, Args_size=4
	aload_0
	aload_1
	aload_2
	aload_3
	invokestatic	Method scala/collection/generic/Subtractable$class.$minus:(Lscala/collection/generic/Subtractable;Ljava/lang/Object;Ljava/lang/Object;Lscala/collection/Seq;)Lscala/collection/generic/Subtractable;
	areturn
  Labels:
  LocalVariableTable: 
   Start  Length  Slot  Name   Signature
   0      8      0    this       Lscala/collection/MapLike$$anon$1;
   0      8      1    elem1       Ljava/lang/Object;
   0      8      2    elem2       Ljava/lang/Object;
   0      8      3    elems       Lscala/collection/Seq;


public scala.collection.generic.Subtractable $minus$minus(scala.collection.Traversable);
  Signature: (Lscala/collection/Traversable;)Lscala/collection/generic/Subtractable;
  Code:
   Stack=2, Locals=2, Args_size=2
	aload_0
	aload_1
	invokestatic	Method scala/collection/generic/Subtractable$class.$minus$minus:(Lscala/collection/generic/Subtractable;Lscala/collection/Traversable;)Lscala/collection/generic/Subtractable;
	areturn
  Labels:
  LocalVariableTable: 
   Start  Length  Slot  Name   Signature
   0      6      0    this       Lscala/collection/MapLike$$anon$1;
   0      6      1    elems       Lscala/collection/Traversable;


public scala.collection.generic.Subtractable $minus$minus(scala.collection.Iterator);
  Signature: (Lscala/collection/Iterator;)Lscala/collection/generic/Subtractable;
  Code:
   Stack=2, Locals=2, Args_size=2
	aload_0
	aload_1
	invokestatic	Method scala/collection/generic/Subtractable$class.$minus$minus:(Lscala/collection/generic/Subtractable;Lscala/collection/Iterator;)Lscala/collection/generic/Subtractable;
	areturn
  Labels:
  LocalVariableTable: 
   Start  Length  Slot  Name   Signature
   0      6      0    this       Lscala/collection/MapLike$$anon$1;
   0      6      1    iter       Lscala/collection/Iterator;


public scala.PartialFunction orElse(scala.PartialFunction);
  Signature: (Lscala/PartialFunction;)Lscala/PartialFunction;
  Code:
   Stack=2, Locals=2, Args_size=2
	aload_0
	aload_1
	invokestatic	Method scala/PartialFunction$class.orElse:(Lscala/PartialFunction;Lscala/PartialFunction;)Lscala/PartialFunction;
	areturn
  Labels:
  LocalVariableTable: 
   Start  Length  Slot  Name   Signature
   0      6      0    this       Lscala/collection/MapLike$$anon$1;
   0      6      1    that       Lscala/PartialFunction;


public scala.PartialFunction andThen(scala.Function1);
  Signature: (Lscala/Function1;)Lscala/PartialFunction;
  Code:
   Stack=2, Locals=2, Args_size=2
	aload_0
	aload_1
	invokestatic	Method scala/PartialFunction$class.andThen:(Lscala/PartialFunction;Lscala/Function1;)Lscala/PartialFunction;
	areturn
  Labels:
  LocalVariableTable: 
   Start  Length  Slot  Name   Signature
   0      6      0    this       Lscala/collection/MapLike$$anon$1;
   0      6      1    k       Lscala/Function1;


public scala.Function1 lift();
  Signature: ()Lscala/Function1;
  Code:
   Stack=1, Locals=1, Args_size=1
	aload_0
	invokestatic	Method scala/PartialFunction$class.lift:(Lscala/PartialFunction;)Lscala/Function1;
	areturn
  Labels:

public scala.Function1 compose(scala.Function1);
  Signature: (Lscala/Function1;)Lscala/Function1;
  Code:
   Stack=2, Locals=2, Args_size=2
	aload_0
	aload_1
	invokestatic	Method scala/Function1$class.compose:(Lscala/Function1;Lscala/Function1;)Lscala/Function1;
	areturn
  Labels:
  LocalVariableTable: 
   Start  Length  Slot  Name   Signature
   0      6      0    this       Lscala/collection/MapLike$$anon$1;
   0      6      1    g       Lscala/Function1;


public scala.collection.generic.GenericCompanion companion();
  Signature: ()Lscala/collection/generic/GenericCompanion;
  Code:
   Stack=1, Locals=1, Args_size=1
	aload_0
	invokestatic	Method scala/collection/Iterable$class.companion:(Lscala/collection/Iterable;)Lscala/collection/generic/GenericCompanion;
	areturn
  Labels:

public scala.collection.Iterable thisCollection();
  Signature: ()Lscala/collection/Iterable;
  Code:
   Stack=1, Locals=1, Args_size=1
	aload_0
	invokestatic	Method scala/collection/IterableLike$class.thisCollection:(Lscala/collection/IterableLike;)Lscala/collection/Iterable;
	areturn
  Labels:

public scala.collection.Iterable toCollection(java.lang.Object);
  Signature: (Ljava/lang/Object;)Lscala/collection/Iterable;
  Code:
   Stack=2, Locals=2, Args_size=2
	aload_0
	aload_1
	invokestatic	Method scala/collection/IterableLike$class.toCollection:(Lscala/collection/IterableLike;Ljava/lang/Object;)Lscala/collection/Iterable;
	areturn
  Labels:
  LocalVariableTable: 
   Start  Length  Slot  Name   Signature
   0      6      0    this       Lscala/collection/MapLike$$anon$1;
   0      6      1    repr       Ljava/lang/Object;


public scala.collection.Iterator elements();
  Signature: ()Lscala/collection/Iterator;
  Code:
   Stack=1, Locals=1, Args_size=1
	aload_0
	invokestatic	Method scala/collection/IterableLike$class.elements:(Lscala/collection/IterableLike;)Lscala/collection/Iterator;
	areturn
  Labels:
  Deprecated: true

public boolean forall(scala.Function1);
  Signature: (Lscala/Function1;)Z
  Code:
   Stack=2, Locals=2, Args_size=2
	aload_0
	aload_1
	invokestatic	Method scala/collection/IterableLike$class.forall:(Lscala/collection/IterableLike;Lscala/Function1;)Z
	ireturn
  Labels:
  LocalVariableTable: 
   Start  Length  Slot  Name   Signature
   0      6      0    this       Lscala/collection/MapLike$$anon$1;
   0      6      1    p       Lscala/Function1;


public boolean exists(scala.Function1);
  Signature: (Lscala/Function1;)Z
  Code:
   Stack=2, Locals=2, Args_size=2
	aload_0
	aload_1
	invokestatic	Method scala/collection/IterableLike$class.exists:(Lscala/collection/IterableLike;Lscala/Function1;)Z
	ireturn
  Labels:
  LocalVariableTable: 
   Start  Length  Slot  Name   Signature
   0      6      0    this       Lscala/collection/MapLike$$anon$1;
   0      6      1    p       Lscala/Function1;


public scala.Option find(scala.Function1);
  Signature: (Lscala/Function1;)Lscala/Option;
  Code:
   Stack=2, Locals=2, Args_size=2
	aload_0
	aload_1
	invokestatic	Method scala/collection/IterableLike$class.find:(Lscala/collection/IterableLike;Lscala/Function1;)Lscala/Option;
	areturn
  Labels:
  LocalVariableTable: 
   Start  Length  Slot  Name   Signature
   0      6      0    this       Lscala/collection/MapLike$$anon$1;
   0      6      1    p       Lscala/Function1;


public java.lang.Object foldRight(java.lang.Object, scala.Function2);
  Signature: (Ljava/lang/Object;Lscala/Function2;)Ljava/lang/Object;
  Code:
   Stack=3, Locals=3, Args_size=3
	aload_0
	aload_1
	aload_2
	invokestatic	Method scala/collection/IterableLike$class.foldRight:(Lscala/collection/IterableLike;Ljava/lang/Object;Lscala/Function2;)Ljava/lang/Object;
	areturn
  Labels:
  LocalVariableTable: 
   Start  Length  Slot  Name   Signature
   0      7      0    this       Lscala/collection/MapLike$$anon$1;
   0      7      1    z       Ljava/lang/Object;
   0      7      2    op       Lscala/Function2;


public java.lang.Object reduceRight(scala.Function2);
  Signature: (Lscala/Function2;)Ljava/lang/Object;
  Code:
   Stack=2, Locals=2, Args_size=2
	aload_0
	aload_1
	invokestatic	Method scala/collection/IterableLike$class.reduceRight:(Lscala/collection/IterableLike;Lscala/Function2;)Ljava/lang/Object;
	areturn
  Labels:
  LocalVariableTable: 
   Start  Length  Slot  Name   Signature
   0      6      0    this       Lscala/collection/MapLike$$anon$1;
   0      6      1    op       Lscala/Function2;


public scala.collection.Iterable toIterable();
  Signature: ()Lscala/collection/Iterable;
  Code:
   Stack=1, Locals=1, Args_size=1
	aload_0
	invokestatic	Method scala/collection/IterableLike$class.toIterable:(Lscala/collection/IterableLike;)Lscala/collection/Iterable;
	areturn
  Labels:

public java.lang.Object head();
  Signature: ()Ljava/lang/Object;
  Code:
   Stack=1, Locals=1, Args_size=1
	aload_0
	invokestatic	Method scala/collection/IterableLike$class.head:(Lscala/collection/IterableLike;)Ljava/lang/Object;
	areturn
  Labels:

public java.lang.Object take(int);
  Signature: (I)Ljava/lang/Object;
  Code:
   Stack=2, Locals=2, Args_size=2
	aload_0
	iload_1
	invokestatic	Method scala/collection/IterableLike$class.take:(Lscala/collection/IterableLike;I)Ljava/lang/Object;
	areturn
  Labels:
  LocalVariableTable: 
   Start  Length  Slot  Name   Signature
   0      6      0    this       Lscala/collection/MapLike$$anon$1;
   0      6      1    n       I


public java.lang.Object slice(int, int);
  Signature: (II)Ljava/lang/Object;
  Code:
   Stack=3, Locals=3, Args_size=3
	aload_0
	iload_1
	iload_2
	invokestatic	Method scala/collection/IterableLike$class.slice:(Lscala/collection/IterableLike;II)Ljava/lang/Object;
	areturn
  Labels:
  LocalVariableTable: 
   Start  Length  Slot  Name   Signature
   0      7      0    this       Lscala/collection/MapLike$$anon$1;
   0      7      1    from       I
   0      7      2    until       I


public java.lang.Object takeWhile(scala.Function1);
  Signature: (Lscala/Function1;)Ljava/lang/Object;
  Code:
   Stack=2, Locals=2, Args_size=2
	aload_0
	aload_1
	invokestatic	Method scala/collection/IterableLike$class.takeWhile:(Lscala/collection/IterableLike;Lscala/Function1;)Ljava/lang/Object;
	areturn
  Labels:
  LocalVariableTable: 
   Start  Length  Slot  Name   Signature
   0      6      0    this       Lscala/collection/MapLike$$anon$1;
   0      6      1    p       Lscala/Function1;


public scala.collection.Iterator grouped(int);
  Signature: (I)Lscala/collection/Iterator;
  Code:
   Stack=2, Locals=2, Args_size=2
	aload_0
	iload_1
	invokestatic	Method scala/collection/IterableLike$class.grouped:(Lscala/collection/IterableLike;I)Lscala/collection/Iterator;
	areturn
  Labels:
  LocalVariableTable: 
   Start  Length  Slot  Name   Signature
   0      6      0    this       Lscala/collection/MapLike$$anon$1;
   0      6      1    size       I


public scala.collection.Iterator sliding(int);
  Signature: (I)Lscala/collection/Iterator;
  Code:
   Stack=2, Locals=2, Args_size=2
	aload_0
	iload_1
	invokestatic	Method scala/collection/IterableLike$class.sliding:(Lscala/collection/IterableLike;I)Lscala/collection/Iterator;
	areturn
  Labels:
  LocalVariableTable: 
   Start  Length  Slot  Name   Signature
   0      6      0    this       Lscala/collection/MapLike$$anon$1;
   0      6      1    size       I


public scala.collection.Iterator sliding(int, int);
  Signature: (II)Lscala/collection/Iterator;
  Code:
   Stack=3, Locals=3, Args_size=3
	aload_0
	iload_1
	iload_2
	invokestatic	Method scala/collection/IterableLike$class.sliding:(Lscala/collection/IterableLike;II)Lscala/collection/Iterator;
	areturn
  Labels:
  LocalVariableTable: 
   Start  Length  Slot  Name   Signature
   0      7      0    this       Lscala/collection/MapLike$$anon$1;
   0      7      1    size       I
   0      7      2    step       I


public java.lang.Object takeRight(int);
  Signature: (I)Ljava/lang/Object;
  Code:
   Stack=2, Locals=2, Args_size=2
	aload_0
	iload_1
	invokestatic	Method scala/collection/IterableLike$class.takeRight:(Lscala/collection/IterableLike;I)Ljava/lang/Object;
	areturn
  Labels:
  LocalVariableTable: 
   Start  Length  Slot  Name   Signature
   0      6      0    this       Lscala/collection/MapLike$$anon$1;
   0      6      1    n       I


public java.lang.Object dropRight(int);
  Signature: (I)Ljava/lang/Object;
  Code:
   Stack=2, Locals=2, Args_size=2
	aload_0
	iload_1
	invokestatic	Method scala/collection/IterableLike$class.dropRight:(Lscala/collection/IterableLike;I)Ljava/lang/Object;
	areturn
  Labels:
  LocalVariableTable: 
   Start  Length  Slot  Name   Signature
   0      6      0    this       Lscala/collection/MapLike$$anon$1;
   0      6      1    n       I


public void copyToArray(java.lang.Object, int, int);
  Signature: (Ljava/lang/Object;II)V
  Code:
   Stack=4, Locals=4, Args_size=4
	aload_0
	aload_1
	iload_2
	iload_3
	invokestatic	Method scala/collection/IterableLike$class.copyToArray:(Lscala/collection/IterableLike;Ljava/lang/Object;II)V
	return
  Labels:
  LocalVariableTable: 
   Start  Length  Slot  Name   Signature
   0      8      0    this       Lscala/collection/MapLike$$anon$1;
   0      8      1    xs       Ljava/lang/Object;
   0      8      2    start       I
   0      8      3    len       I


public java.lang.Object zip(scala.collection.Iterable, scala.collection.generic.CanBuildFrom);
  Signature: (Lscala/collection/Iterable;Lscala/collection/generic/CanBuildFrom;)Ljava/lang/Object;
  Code:
   Stack=3, Locals=3, Args_size=3
	aload_0
	aload_1
	aload_2
	invokestatic	Method scala/collection/IterableLike$class.zip:(Lscala/collection/IterableLike;Lscala/collection/Iterable;Lscala/collection/generic/CanBuildFrom;)Ljava/lang/Object;
	areturn
  Labels:
  LocalVariableTable: 
   Start  Length  Slot  Name   Signature
   0      7      0    this       Lscala/collection/MapLike$$anon$1;
   0      7      1    that       Lscala/collection/Iterable;
   0      7      2    bf       Lscala/collection/generic/CanBuildFrom;


public java.lang.Object zipAll(scala.collection.Iterable, java.lang.Object, java.lang.Object, scala.collection.generic.CanBuildFrom);
  Signature: (Lscala/collection/Iterable;Ljava/lang/Object;Ljava/lang/Object;Lscala/collection/generic/CanBuildFrom;)Ljava/lang/Object;
  Code:
   Stack=5, Locals=5, Args_size=5
	aload_0
	aload_1
	aload_2
	aload_3
	aload	4
	invokestatic	Method scala/collection/IterableLike$class.zipAll:(Lscala/collection/IterableLike;Lscala/collection/Iterable;Ljava/lang/Object;Ljava/lang/Object;Lscala/collection/generic/CanBuildFrom;)Ljava/lang/Object;
	areturn
  Labels:
  LocalVariableTable: 
   Start  Length  Slot  Name   Signature
   0      10      0    this       Lscala/collection/MapLike$$anon$1;
   0      10      1    that       Lscala/collection/Iterable;
   0      10      2    thisElem       Ljava/lang/Object;
   0      10      3    thatElem       Ljava/lang/Object;
   0      10      4    bf       Lscala/collection/generic/CanBuildFrom;


public java.lang.Object zipWithIndex(scala.collection.generic.CanBuildFrom);
  Signature: (Lscala/collection/generic/CanBuildFrom;)Ljava/lang/Object;
  Code:
   Stack=2, Locals=2, Args_size=2
	aload_0
	aload_1
	invokestatic	Method scala/collection/IterableLike$class.zipWithIndex:(Lscala/collection/IterableLike;Lscala/collection/generic/CanBuildFrom;)Ljava/lang/Object;
	areturn
  Labels:
  LocalVariableTable: 
   Start  Length  Slot  Name   Signature
   0      6      0    this       Lscala/collection/MapLike$$anon$1;
   0      6      1    bf       Lscala/collection/generic/CanBuildFrom;


public boolean sameElements(scala.collection.Iterable);
  Signature: (Lscala/collection/Iterable;)Z
  Code:
   Stack=2, Locals=2, Args_size=2
	aload_0
	aload_1
	invokestatic	Method scala/collection/IterableLike$class.sameElements:(Lscala/collection/IterableLike;Lscala/collection/Iterable;)Z
	ireturn
  Labels:
  LocalVariableTable: 
   Start  Length  Slot  Name   Signature
   0      6      0    this       Lscala/collection/MapLike$$anon$1;
   0      6      1    that       Lscala/collection/Iterable;


public scala.collection.immutable.Stream toStream();
  Signature: ()Lscala/collection/immutable/Stream;
  Code:
   Stack=1, Locals=1, Args_size=1
	aload_0
	invokestatic	Method scala/collection/IterableLike$class.toStream:(Lscala/collection/IterableLike;)Lscala/collection/immutable/Stream;
	areturn
  Labels:

public boolean canEqual(java.lang.Object);
  Signature: (Ljava/lang/Object;)Z
  Code:
   Stack=2, Locals=2, Args_size=2
	aload_0
	aload_1
	invokestatic	Method scala/collection/IterableLike$class.canEqual:(Lscala/collection/IterableLike;Ljava/lang/Object;)Z
	ireturn
  Labels:
  LocalVariableTable: 
   Start  Length  Slot  Name   Signature
   0      6      0    this       Lscala/collection/MapLike$$anon$1;
   0      6      1    that       Ljava/lang/Object;


public scala.collection.IterableView view();
  Signature: ()Lscala/collection/IterableView;
  Code:
   Stack=1, Locals=1, Args_size=1
	aload_0
	invokestatic	Method scala/collection/IterableLike$class.view:(Lscala/collection/IterableLike;)Lscala/collection/IterableView;
	areturn
  Labels:

public scala.collection.IterableView view(int, int);
  Signature: (II)Lscala/collection/IterableView;
  Code:
   Stack=3, Locals=3, Args_size=3
	aload_0
	iload_1
	iload_2
	invokestatic	Method scala/collection/IterableLike$class.view:(Lscala/collection/IterableLike;II)Lscala/collection/IterableView;
	areturn
  Labels:
  LocalVariableTable: 
   Start  Length  Slot  Name   Signature
   0      7      0    this       Lscala/collection/MapLike$$anon$1;
   0      7      1    from       I
   0      7      2    until       I


public java.lang.Object first();
  Signature: ()Ljava/lang/Object;
  Code:
   Stack=1, Locals=1, Args_size=1
	aload_0
	invokestatic	Method scala/collection/IterableLike$class.first:(Lscala/collection/IterableLike;)Ljava/lang/Object;
	areturn
  Labels:
  Deprecated: true

public scala.Option firstOption();
  Signature: ()Lscala/Option;
  Code:
   Stack=1, Locals=1, Args_size=1
	aload_0
	invokestatic	Method scala/collection/IterableLike$class.firstOption:(Lscala/collection/IterableLike;)Lscala/Option;
	areturn
  Labels:
  Deprecated: true

public scala.collection.IterableView projection();
  Signature: ()Lscala/collection/IterableView;
  Code:
   Stack=1, Locals=1, Args_size=1
	aload_0
	invokestatic	Method scala/collection/IterableLike$class.projection:(Lscala/collection/IterableLike;)Lscala/collection/IterableView;
	areturn
  Labels:
  Deprecated: true

public scala.collection.mutable.Builder genericBuilder();
  Signature: ()Lscala/collection/mutable/Builder;
  Code:
   Stack=1, Locals=1, Args_size=1
	aload_0
	invokestatic	Method scala/collection/generic/GenericTraversableTemplate$class.genericBuilder:(Lscala/collection/generic/GenericTraversableTemplate;)Lscala/collection/mutable/Builder;
	areturn
  Labels:

public scala.Tuple2 unzip(scala.Function1);
  Signature: (Lscala/Function1;)Lscala/Tuple2;
  Code:
   Stack=2, Locals=2, Args_size=2
	aload_0
	aload_1
	invokestatic	Method scala/collection/generic/GenericTraversableTemplate$class.unzip:(Lscala/collection/generic/GenericTraversableTemplate;Lscala/Function1;)Lscala/Tuple2;
	areturn
  Labels:
  LocalVariableTable: 
   Start  Length  Slot  Name   Signature
   0      6      0    this       Lscala/collection/MapLike$$anon$1;
   0      6      1    asPair       Lscala/Function1;


public scala.collection.Traversable flatten(scala.Function1);
  Signature: (Lscala/Function1;)Lscala/collection/Traversable;
  Code:
   Stack=2, Locals=2, Args_size=2
	aload_0
	aload_1
	invokestatic	Method scala/collection/generic/GenericTraversableTemplate$class.flatten:(Lscala/collection/generic/GenericTraversableTemplate;Lscala/Function1;)Lscala/collection/Traversable;
	areturn
  Labels:
  LocalVariableTable: 
   Start  Length  Slot  Name   Signature
   0      6      0    this       Lscala/collection/MapLike$$anon$1;
   0      6      1    asTraversable       Lscala/Function1;


public scala.collection.Traversable transpose(scala.Function1);
  Signature: (Lscala/Function1;)Lscala/collection/Traversable;
  Code:
   Stack=2, Locals=2, Args_size=2
	aload_0
	aload_1
	invokestatic	Method scala/collection/generic/GenericTraversableTemplate$class.transpose:(Lscala/collection/generic/GenericTraversableTemplate;Lscala/Function1;)Lscala/collection/Traversable;
	areturn
  Labels:
  LocalVariableTable: 
   Start  Length  Slot  Name   Signature
   0      6      0    this       Lscala/collection/MapLike$$anon$1;
   0      6      1    asTraversable       Lscala/Function1;


public java.lang.Object repr();
  Signature: ()Ljava/lang/Object;
  Code:
   Stack=1, Locals=1, Args_size=1
	aload_0
	invokestatic	Method scala/collection/TraversableLike$class.repr:(Lscala/collection/TraversableLike;)Ljava/lang/Object;
	areturn
  Labels:

public boolean nonEmpty();
  Signature: ()Z
  Code:
   Stack=1, Locals=1, Args_size=1
	aload_0
	invokestatic	Method scala/collection/TraversableLike$class.nonEmpty:(Lscala/collection/TraversableLike;)Z
	ireturn
  Labels:

public int size();
  Signature: ()I
  Code:
   Stack=1, Locals=1, Args_size=1
	aload_0
	invokestatic	Method scala/collection/TraversableLike$class.size:(Lscala/collection/TraversableLike;)I
	ireturn
  Labels:

public boolean hasDefiniteSize();
  Signature: ()Z
  Code:
   Stack=1, Locals=1, Args_size=1
	aload_0
	invokestatic	Method scala/collection/TraversableLike$class.hasDefiniteSize:(Lscala/collection/TraversableLike;)Z
	ireturn
  Labels:

public java.lang.Object $plus$plus(scala.collection.Traversable, scala.collection.generic.CanBuildFrom);
  Signature: (Lscala/collection/Traversable;Lscala/collection/generic/CanBuildFrom;)Ljava/lang/Object;
  Code:
   Stack=3, Locals=3, Args_size=3
	aload_0
	aload_1
	aload_2
	invokestatic	Method scala/collection/TraversableLike$class.$plus$plus:(Lscala/collection/TraversableLike;Lscala/collection/Traversable;Lscala/collection/generic/CanBuildFrom;)Ljava/lang/Object;
	areturn
  Labels:
  LocalVariableTable: 
   Start  Length  Slot  Name   Signature
   0      7      0    this       Lscala/collection/MapLike$$anon$1;
   0      7      1    that       Lscala/collection/Traversable;
   0      7      2    bf       Lscala/collection/generic/CanBuildFrom;


public java.lang.Object $plus$plus(scala.collection.Iterator, scala.collection.generic.CanBuildFrom);
  Signature: (Lscala/collection/Iterator;Lscala/collection/generic/CanBuildFrom;)Ljava/lang/Object;
  Code:
   Stack=3, Locals=3, Args_size=3
	aload_0
	aload_1
	aload_2
	invokestatic	Method scala/collection/TraversableLike$class.$plus$plus:(Lscala/collection/TraversableLike;Lscala/collection/Iterator;Lscala/collection/generic/CanBuildFrom;)Ljava/lang/Object;
	areturn
  Labels:
  LocalVariableTable: 
   Start  Length  Slot  Name   Signature
   0      7      0    this       Lscala/collection/MapLike$$anon$1;
   0      7      1    that       Lscala/collection/Iterator;
   0      7      2    bf       Lscala/collection/generic/CanBuildFrom;


public java.lang.Object map(scala.Function1, scala.collection.generic.CanBuildFrom);
  Signature: (Lscala/Function1;Lscala/collection/generic/CanBuildFrom;)Ljava/lang/Object;
  Code:
   Stack=3, Locals=3, Args_size=3
	aload_0
	aload_1
	aload_2
	invokestatic	Method scala/collection/TraversableLike$class.map:(Lscala/collection/TraversableLike;Lscala/Function1;Lscala/collection/generic/CanBuildFrom;)Ljava/lang/Object;
	areturn
  Labels:
  LocalVariableTable: 
   Start  Length  Slot  Name   Signature
   0      7      0    this       Lscala/collection/MapLike$$anon$1;
   0      7      1    f       Lscala/Function1;
   0      7      2    bf       Lscala/collection/generic/CanBuildFrom;


public java.lang.Object flatMap(scala.Function1, scala.collection.generic.CanBuildFrom);
  Signature: (Lscala/Function1;Lscala/collection/generic/CanBuildFrom;)Ljava/lang/Object;
  Code:
   Stack=3, Locals=3, Args_size=3
	aload_0
	aload_1
	aload_2
	invokestatic	Method scala/collection/TraversableLike$class.flatMap:(Lscala/collection/TraversableLike;Lscala/Function1;Lscala/collection/generic/CanBuildFrom;)Ljava/lang/Object;
	areturn
  Labels:
  LocalVariableTable: 
   Start  Length  Slot  Name   Signature
   0      7      0    this       Lscala/collection/MapLike$$anon$1;
   0      7      1    f       Lscala/Function1;
   0      7      2    bf       Lscala/collection/generic/CanBuildFrom;


public java.lang.Object filter(scala.Function1);
  Signature: (Lscala/Function1;)Ljava/lang/Object;
  Code:
   Stack=2, Locals=2, Args_size=2
	aload_0
	aload_1
	invokestatic	Method scala/collection/TraversableLike$class.filter:(Lscala/collection/TraversableLike;Lscala/Function1;)Ljava/lang/Object;
	areturn
  Labels:
  LocalVariableTable: 
   Start  Length  Slot  Name   Signature
   0      6      0    this       Lscala/collection/MapLike$$anon$1;
   0      6      1    p       Lscala/Function1;


public java.lang.Object partialMap(scala.PartialFunction, scala.collection.generic.CanBuildFrom);
  Signature: (Lscala/PartialFunction;Lscala/collection/generic/CanBuildFrom;)Ljava/lang/Object;
  Code:
   Stack=3, Locals=3, Args_size=3
	aload_0
	aload_1
	aload_2
	invokestatic	Method scala/collection/TraversableLike$class.partialMap:(Lscala/collection/TraversableLike;Lscala/PartialFunction;Lscala/collection/generic/CanBuildFrom;)Ljava/lang/Object;
	areturn
  Labels:
  LocalVariableTable: 
   Start  Length  Slot  Name   Signature
   0      7      0    this       Lscala/collection/MapLike$$anon$1;
   0      7      1    pf       Lscala/PartialFunction;
   0      7      2    bf       Lscala/collection/generic/CanBuildFrom;


public scala.Tuple2 partition(scala.Function1);
  Signature: (Lscala/Function1;)Lscala/Tuple2;
  Code:
   Stack=2, Locals=2, Args_size=2
	aload_0
	aload_1
	invokestatic	Method scala/collection/TraversableLike$class.partition:(Lscala/collection/TraversableLike;Lscala/Function1;)Lscala/Tuple2;
	areturn
  Labels:
  LocalVariableTable: 
   Start  Length  Slot  Name   Signature
   0      6      0    this       Lscala/collection/MapLike$$anon$1;
   0      6      1    p       Lscala/Function1;


public scala.collection.Map groupBy(scala.Function1);
  Signature: (Lscala/Function1;)Lscala/collection/Map;
  Code:
   Stack=2, Locals=2, Args_size=2
	aload_0
	aload_1
	invokestatic	Method scala/collection/TraversableLike$class.groupBy:(Lscala/collection/TraversableLike;Lscala/Function1;)Lscala/collection/Map;
	areturn
  Labels:
  LocalVariableTable: 
   Start  Length  Slot  Name   Signature
   0      6      0    this       Lscala/collection/MapLike$$anon$1;
   0      6      1    f       Lscala/Function1;


public int count(scala.Function1);
  Signature: (Lscala/Function1;)I
  Code:
   Stack=2, Locals=2, Args_size=2
	aload_0
	aload_1
	invokestatic	Method scala/collection/TraversableLike$class.count:(Lscala/collection/TraversableLike;Lscala/Function1;)I
	ireturn
  Labels:
  LocalVariableTable: 
   Start  Length  Slot  Name   Signature
   0      6      0    this       Lscala/collection/MapLike$$anon$1;
   0      6      1    p       Lscala/Function1;


public java.lang.Object foldLeft(java.lang.Object, scala.Function2);
  Signature: (Ljava/lang/Object;Lscala/Function2;)Ljava/lang/Object;
  Code:
   Stack=3, Locals=3, Args_size=3
	aload_0
	aload_1
	aload_2
	invokestatic	Method scala/collection/TraversableLike$class.foldLeft:(Lscala/collection/TraversableLike;Ljava/lang/Object;Lscala/Function2;)Ljava/lang/Object;
	areturn
  Labels:
  LocalVariableTable: 
   Start  Length  Slot  Name   Signature
   0      7      0    this       Lscala/collection/MapLike$$anon$1;
   0      7      1    z       Ljava/lang/Object;
   0      7      2    op       Lscala/Function2;


public java.lang.Object $div$colon(java.lang.Object, scala.Function2);
  Signature: (Ljava/lang/Object;Lscala/Function2;)Ljava/lang/Object;
  Code:
   Stack=3, Locals=3, Args_size=3
	aload_0
	aload_1
	aload_2
	invokestatic	Method scala/collection/TraversableLike$class.$div$colon:(Lscala/collection/TraversableLike;Ljava/lang/Object;Lscala/Function2;)Ljava/lang/Object;
	areturn
  Labels:
  LocalVariableTable: 
   Start  Length  Slot  Name   Signature
   0      7      0    this       Lscala/collection/MapLike$$anon$1;
   0      7      1    z       Ljava/lang/Object;
   0      7      2    op       Lscala/Function2;


public java.lang.Object $colon$bslash(java.lang.Object, scala.Function2);
  Signature: (Ljava/lang/Object;Lscala/Function2;)Ljava/lang/Object;
  Code:
   Stack=3, Locals=3, Args_size=3
	aload_0
	aload_1
	aload_2
	invokestatic	Method scala/collection/TraversableLike$class.$colon$bslash:(Lscala/collection/TraversableLike;Ljava/lang/Object;Lscala/Function2;)Ljava/lang/Object;
	areturn
  Labels:
  LocalVariableTable: 
   Start  Length  Slot  Name   Signature
   0      7      0    this       Lscala/collection/MapLike$$anon$1;
   0      7      1    z       Ljava/lang/Object;
   0      7      2    op       Lscala/Function2;


public java.lang.Object reduceLeft(scala.Function2);
  Signature: (Lscala/Function2;)Ljava/lang/Object;
  Code:
   Stack=2, Locals=2, Args_size=2
	aload_0
	aload_1
	invokestatic	Method scala/collection/TraversableLike$class.reduceLeft:(Lscala/collection/TraversableLike;Lscala/Function2;)Ljava/lang/Object;
	areturn
  Labels:
  LocalVariableTable: 
   Start  Length  Slot  Name   Signature
   0      6      0    this       Lscala/collection/MapLike$$anon$1;
   0      6      1    op       Lscala/Function2;


public scala.Option reduceLeftOption(scala.Function2);
  Signature: (Lscala/Function2;)Lscala/Option;
  Code:
   Stack=2, Locals=2, Args_size=2
	aload_0
	aload_1
	invokestatic	Method scala/collection/TraversableLike$class.reduceLeftOption:(Lscala/collection/TraversableLike;Lscala/Function2;)Lscala/Option;
	areturn
  Labels:
  LocalVariableTable: 
   Start  Length  Slot  Name   Signature
   0      6      0    this       Lscala/collection/MapLike$$anon$1;
   0      6      1    op       Lscala/Function2;


public scala.Option reduceRightOption(scala.Function2);
  Signature: (Lscala/Function2;)Lscala/Option;
  Code:
   Stack=2, Locals=2, Args_size=2
	aload_0
	aload_1
	invokestatic	Method scala/collection/TraversableLike$class.reduceRightOption:(Lscala/collection/TraversableLike;Lscala/Function2;)Lscala/Option;
	areturn
  Labels:
  LocalVariableTable: 
   Start  Length  Slot  Name   Signature
   0      6      0    this       Lscala/collection/MapLike$$anon$1;
   0      6      1    op       Lscala/Function2;


public java.lang.Object sum(scala.math.Numeric);
  Signature: (Lscala/math/Numeric;)Ljava/lang/Object;
  Code:
   Stack=2, Locals=2, Args_size=2
	aload_0
	aload_1
	invokestatic	Method scala/collection/TraversableLike$class.sum:(Lscala/collection/TraversableLike;Lscala/math/Numeric;)Ljava/lang/Object;
	areturn
  Labels:
  LocalVariableTable: 
   Start  Length  Slot  Name   Signature
   0      6      0    this       Lscala/collection/MapLike$$anon$1;
   0      6      1    num       Lscala/math/Numeric;


public java.lang.Object product(scala.math.Numeric);
  Signature: (Lscala/math/Numeric;)Ljava/lang/Object;
  Code:
   Stack=2, Locals=2, Args_size=2
	aload_0
	aload_1
	invokestatic	Method scala/collection/TraversableLike$class.product:(Lscala/collection/TraversableLike;Lscala/math/Numeric;)Ljava/lang/Object;
	areturn
  Labels:
  LocalVariableTable: 
   Start  Length  Slot  Name   Signature
   0      6      0    this       Lscala/collection/MapLike$$anon$1;
   0      6      1    num       Lscala/math/Numeric;


public java.lang.Object min(scala.math.Ordering);
  Signature: (Lscala/math/Ordering;)Ljava/lang/Object;
  Code:
   Stack=2, Locals=2, Args_size=2
	aload_0
	aload_1
	invokestatic	Method scala/collection/TraversableLike$class.min:(Lscala/collection/TraversableLike;Lscala/math/Ordering;)Ljava/lang/Object;
	areturn
  Labels:
  LocalVariableTable: 
   Start  Length  Slot  Name   Signature
   0      6      0    this       Lscala/collection/MapLike$$anon$1;
   0      6      1    cmp       Lscala/math/Ordering;


public java.lang.Object max(scala.math.Ordering);
  Signature: (Lscala/math/Ordering;)Ljava/lang/Object;
  Code:
   Stack=2, Locals=2, Args_size=2
	aload_0
	aload_1
	invokestatic	Method scala/collection/TraversableLike$class.max:(Lscala/collection/TraversableLike;Lscala/math/Ordering;)Ljava/lang/Object;
	areturn
  Labels:
  LocalVariableTable: 
   Start  Length  Slot  Name   Signature
   0      6      0    this       Lscala/collection/MapLike$$anon$1;
   0      6      1    cmp       Lscala/math/Ordering;


public scala.Option headOption();
  Signature: ()Lscala/Option;
  Code:
   Stack=1, Locals=1, Args_size=1
	aload_0
	invokestatic	Method scala/collection/TraversableLike$class.headOption:(Lscala/collection/TraversableLike;)Lscala/Option;
	areturn
  Labels:

public java.lang.Object tail();
  Signature: ()Ljava/lang/Object;
  Code:
   Stack=1, Locals=1, Args_size=1
	aload_0
	invokestatic	Method scala/collection/TraversableLike$class.tail:(Lscala/collection/TraversableLike;)Ljava/lang/Object;
	areturn
  Labels:

public java.lang.Object last();
  Signature: ()Ljava/lang/Object;
  Code:
   Stack=1, Locals=1, Args_size=1
	aload_0
	invokestatic	Method scala/collection/TraversableLike$class.last:(Lscala/collection/TraversableLike;)Ljava/lang/Object;
	areturn
  Labels:

public scala.Option lastOption();
  Signature: ()Lscala/Option;
  Code:
   Stack=1, Locals=1, Args_size=1
	aload_0
	invokestatic	Method scala/collection/TraversableLike$class.lastOption:(Lscala/collection/TraversableLike;)Lscala/Option;
	areturn
  Labels:

public java.lang.Object init();
  Signature: ()Ljava/lang/Object;
  Code:
   Stack=1, Locals=1, Args_size=1
	aload_0
	invokestatic	Method scala/collection/TraversableLike$class.init:(Lscala/collection/TraversableLike;)Ljava/lang/Object;
	areturn
  Labels:

public java.lang.Object drop(int);
  Signature: (I)Ljava/lang/Object;
  Code:
   Stack=2, Locals=2, Args_size=2
	aload_0
	iload_1
	invokestatic	Method scala/collection/TraversableLike$class.drop:(Lscala/collection/TraversableLike;I)Ljava/lang/Object;
	areturn
  Labels:
  LocalVariableTable: 
   Start  Length  Slot  Name   Signature
   0      6      0    this       Lscala/collection/MapLike$$anon$1;
   0      6      1    n       I


public java.lang.Object dropWhile(scala.Function1);
  Signature: (Lscala/Function1;)Ljava/lang/Object;
  Code:
   Stack=2, Locals=2, Args_size=2
	aload_0
	aload_1
	invokestatic	Method scala/collection/TraversableLike$class.dropWhile:(Lscala/collection/TraversableLike;Lscala/Function1;)Ljava/lang/Object;
	areturn
  Labels:
  LocalVariableTable: 
   Start  Length  Slot  Name   Signature
   0      6      0    this       Lscala/collection/MapLike$$anon$1;
   0      6      1    p       Lscala/Function1;


public scala.Tuple2 span(scala.Function1);
  Signature: (Lscala/Function1;)Lscala/Tuple2;
  Code:
   Stack=2, Locals=2, Args_size=2
	aload_0
	aload_1
	invokestatic	Method scala/collection/TraversableLike$class.span:(Lscala/collection/TraversableLike;Lscala/Function1;)Lscala/Tuple2;
	areturn
  Labels:
  LocalVariableTable: 
   Start  Length  Slot  Name   Signature
   0      6      0    this       Lscala/collection/MapLike$$anon$1;
   0      6      1    p       Lscala/Function1;


public scala.Tuple2 splitAt(int);
  Signature: (I)Lscala/Tuple2;
  Code:
   Stack=2, Locals=2, Args_size=2
	aload_0
	iload_1
	invokestatic	Method scala/collection/TraversableLike$class.splitAt:(Lscala/collection/TraversableLike;I)Lscala/Tuple2;
	areturn
  Labels:
  LocalVariableTable: 
   Start  Length  Slot  Name   Signature
   0      6      0    this       Lscala/collection/MapLike$$anon$1;
   0      6      1    n       I


public void copyToBuffer(scala.collection.mutable.Buffer);
  Signature: (Lscala/collection/mutable/Buffer;)V
  Code:
   Stack=2, Locals=2, Args_size=2
	aload_0
	aload_1
	invokestatic	Method scala/collection/TraversableLike$class.copyToBuffer:(Lscala/collection/TraversableLike;Lscala/collection/mutable/Buffer;)V
	return
  Labels:
  LocalVariableTable: 
   Start  Length  Slot  Name   Signature
   0      6      0    this       Lscala/collection/MapLike$$anon$1;
   0      6      1    dest       Lscala/collection/mutable/Buffer;


public void copyToArray(java.lang.Object, int);
  Signature: (Ljava/lang/Object;I)V
  Code:
   Stack=3, Locals=3, Args_size=3
	aload_0
	aload_1
	iload_2
	invokestatic	Method scala/collection/TraversableLike$class.copyToArray:(Lscala/collection/TraversableLike;Ljava/lang/Object;I)V
	return
  Labels:
  LocalVariableTable: 
   Start  Length  Slot  Name   Signature
   0      7      0    this       Lscala/collection/MapLike$$anon$1;
   0      7      1    xs       Ljava/lang/Object;
   0      7      2    start       I


public void copyToArray(java.lang.Object);
  Signature: (Ljava/lang/Object;)V
  Code:
   Stack=2, Locals=2, Args_size=2
	aload_0
	aload_1
	invokestatic	Method scala/collection/TraversableLike$class.copyToArray:(Lscala/collection/TraversableLike;Ljava/lang/Object;)V
	return
  Labels:
  LocalVariableTable: 
   Start  Length  Slot  Name   Signature
   0      6      0    this       Lscala/collection/MapLike$$anon$1;
   0      6      1    xs       Ljava/lang/Object;


public java.lang.Object toArray(scala.reflect.ClassManifest);
  Signature: (Lscala/reflect/ClassManifest;)Ljava/lang/Object;
  Code:
   Stack=2, Locals=2, Args_size=2
	aload_0
	aload_1
	invokestatic	Method scala/collection/TraversableLike$class.toArray:(Lscala/collection/TraversableLike;Lscala/reflect/ClassManifest;)Ljava/lang/Object;
	areturn
  Labels:
  LocalVariableTable: 
   Start  Length  Slot  Name   Signature
   0      6      0    this       Lscala/collection/MapLike$$anon$1;
   0      6      1    evidence$1       Lscala/reflect/ClassManifest;


public scala.collection.immutable.List toList();
  Signature: ()Lscala/collection/immutable/List;
  Code:
   Stack=1, Locals=1, Args_size=1
	aload_0
	invokestatic	Method scala/collection/TraversableLike$class.toList:(Lscala/collection/TraversableLike;)Lscala/collection/immutable/List;
	areturn
  Labels:

public scala.collection.Seq toSeq();
  Signature: ()Lscala/collection/Seq;
  Code:
   Stack=1, Locals=1, Args_size=1
	aload_0
	invokestatic	Method scala/collection/TraversableLike$class.toSeq:(Lscala/collection/TraversableLike;)Lscala/collection/Seq;
	areturn
  Labels:

public scala.collection.mutable.IndexedSeq toIndexedSeq();
  Signature: ()Lscala/collection/mutable/IndexedSeq;
  Code:
   Stack=1, Locals=1, Args_size=1
	aload_0
	invokestatic	Method scala/collection/TraversableLike$class.toIndexedSeq:(Lscala/collection/TraversableLike;)Lscala/collection/mutable/IndexedSeq;
	areturn
  Labels:

public scala.collection.immutable.Set toSet();
  Signature: ()Lscala/collection/immutable/Set;
  Code:
   Stack=1, Locals=1, Args_size=1
	aload_0
	invokestatic	Method scala/collection/TraversableLike$class.toSet:(Lscala/collection/TraversableLike;)Lscala/collection/immutable/Set;
	areturn
  Labels:

public scala.collection.immutable.Map toMap(scala.Predef$$less$colon$less);
  Signature: (Lscala/Predef$$less$colon$less;)Lscala/collection/immutable/Map;
  Code:
   Stack=2, Locals=2, Args_size=2
	aload_0
	aload_1
	invokestatic	Method scala/collection/TraversableLike$class.toMap:(Lscala/collection/TraversableLike;Lscala/Predef$$less$colon$less;)Lscala/collection/immutable/Map;
	areturn
  Labels:
  LocalVariableTable: 
   Start  Length  Slot  Name   Signature
   0      6      0    this       Lscala/collection/MapLike$$anon$1;
   0      6      1    ev       Lscala/Predef$$less$colon$less;


public java.lang.String mkString(java.lang.String, java.lang.String, java.lang.String);
  Signature: (Ljava/lang/String;Ljava/lang/String;Ljava/lang/String;)Ljava/lang/String;
  Code:
   Stack=4, Locals=4, Args_size=4
	aload_0
	aload_1
	aload_2
	aload_3
	invokestatic	Method scala/collection/TraversableLike$class.mkString:(Lscala/collection/TraversableLike;Ljava/lang/String;Ljava/lang/String;Ljava/lang/String;)Ljava/lang/String;
	areturn
  Labels:
  LocalVariableTable: 
   Start  Length  Slot  Name   Signature
   0      8      0    this       Lscala/collection/MapLike$$anon$1;
   0      8      1    start       Ljava/lang/String;
   0      8      2    sep       Ljava/lang/String;
   0      8      3    end       Ljava/lang/String;


public java.lang.String mkString(java.lang.String);
  Signature: (Ljava/lang/String;)Ljava/lang/String;
  Code:
   Stack=2, Locals=2, Args_size=2
	aload_0
	aload_1
	invokestatic	Method scala/collection/TraversableLike$class.mkString:(Lscala/collection/TraversableLike;Ljava/lang/String;)Ljava/lang/String;
	areturn
  Labels:
  LocalVariableTable: 
   Start  Length  Slot  Name   Signature
   0      6      0    this       Lscala/collection/MapLike$$anon$1;
   0      6      1    sep       Ljava/lang/String;


public java.lang.String mkString();
  Signature: ()Ljava/lang/String;
  Code:
   Stack=1, Locals=1, Args_size=1
	aload_0
	invokestatic	Method scala/collection/TraversableLike$class.mkString:(Lscala/collection/TraversableLike;)Ljava/lang/String;
	areturn
  Labels:

public scala.collection.mutable.StringBuilder addString(scala.collection.mutable.StringBuilder, java.lang.String);
  Signature: (Lscala/collection/mutable/StringBuilder;Ljava/lang/String;)Lscala/collection/mutable/StringBuilder;
  Code:
   Stack=3, Locals=3, Args_size=3
	aload_0
	aload_1
	aload_2
	invokestatic	Method scala/collection/TraversableLike$class.addString:(Lscala/collection/TraversableLike;Lscala/collection/mutable/StringBuilder;Ljava/lang/String;)Lscala/collection/mutable/StringBuilder;
	areturn
  Labels:
  LocalVariableTable: 
   Start  Length  Slot  Name   Signature
   0      7      0    this       Lscala/collection/MapLike$$anon$1;
   0      7      1    b       Lscala/collection/mutable/StringBuilder;
   0      7      2    sep       Ljava/lang/String;


public scala.collection.mutable.StringBuilder addString(scala.collection.mutable.StringBuilder);
  Signature: (Lscala/collection/mutable/StringBuilder;)Lscala/collection/mutable/StringBuilder;
  Code:
   Stack=2, Locals=2, Args_size=2
	aload_0
	aload_1
	invokestatic	Method scala/collection/TraversableLike$class.addString:(Lscala/collection/TraversableLike;Lscala/collection/mutable/StringBuilder;)Lscala/collection/mutable/StringBuilder;
	areturn
  Labels:
  LocalVariableTable: 
   Start  Length  Slot  Name   Signature
   0      6      0    this       Lscala/collection/MapLike$$anon$1;
   0      6      1    b       Lscala/collection/mutable/StringBuilder;


public scala.collection.TraversableLike$WithFilter withFilter(scala.Function1);
  Signature: (Lscala/Function1;)Lscala/collection/TraversableLike$WithFilter;
  Code:
   Stack=2, Locals=2, Args_size=2
	aload_0
	aload_1
	invokestatic	Method scala/collection/TraversableLike$class.withFilter:(Lscala/collection/TraversableLike;Lscala/Function1;)Lscala/collection/TraversableLike$WithFilter;
	areturn
  Labels:
  LocalVariableTable: 
   Start  Length  Slot  Name   Signature
   0      6      0    this       Lscala/collection/MapLike$$anon$1;
   0      6      1    p       Lscala/Function1;

  Signature: length = 0x2
   02 45 

public void foreach(scala.Function1);
  Signature: (Lscala/Function1;)V
  Code:
   Stack=5, Locals=2, Args_size=2
	aload_0
	getfield	Field $outer:Lscala/collection/MapLike;
	new	class scala/collection/MapLike$$anon$1$$anonfun$foreach$5
	dup
	aload_0
	aload_1
	invokespecial	Method scala/collection/MapLike$$anon$1$$anonfun$foreach$5."<init>":(Lscala/collection/MapLike$$anon$1;Lscala/Function1;)V
	invokeinterface	InterfaceMethod scala/collection/IterableLike.foreach:(Lscala/Function1;)V
	return
  Labels:
  LocalVariableTable: 
   Start  Length  Slot  Name   Signature
   0      19      0    this       Lscala/collection/MapLike$$anon$1;
   0      19      1    f$3       Lscala/Function1;

  Signature: length = 0x2
   02 5B 

public scala.collection.Iterator iterator();
  Signature: ()Lscala/collection/Iterator;
  Code:
   Stack=4, Locals=1, Args_size=1
	aload_0
	getfield	Field $outer:Lscala/collection/MapLike;
	invokeinterface	InterfaceMethod scala/collection/MapLike.iterator:()Lscala/collection/Iterator;
	new	class scala/collection/MapLike$$anon$1$$anonfun$iterator$1
	dup
	aload_0
	invokespecial	Method scala/collection/MapLike$$anon$1$$anonfun$iterator$1."<init>":(Lscala/collection/MapLike$$anon$1;)V
	invokeinterface	InterfaceMethod scala/collection/Iterator.filter:(Lscala/Function1;)Lscala/collection/Iterator;
	areturn
  Labels:
  Signature: length = 0x2
   02 6B 

public boolean contains(java.lang.Object);
  Signature: (Ljava/lang/Object;)Z
  Code:
   Stack=2, Locals=2, Args_size=2
	aload_0
	getfield	Field $outer:Lscala/collection/MapLike;
	aload_1
	invokeinterface	InterfaceMethod scala/collection/MapLike.contains:(Ljava/lang/Object;)Z
	ifeq	l1 // iconst_0
	aload_0
	getfield	Field p$1:Lscala/Function1;
	aload_1
	invokeinterface	InterfaceMethod scala/Function1.apply:(Ljava/lang/Object;)Ljava/lang/Object;
	invokestatic	Method scala/runtime/BoxesRunTime.unboxToBoolean:(Ljava/lang/Object;)Z
	ifeq	l1 // iconst_0
	iconst_1
	goto	l2 // ireturn
l1	iconst_0
l2	ireturn
  Labels:
   	l1 = 33 // iconst_0
   	l2 = 34 // ireturn
  LocalVariableTable: 
   Start  Length  Slot  Name   Signature
   0      35      0    this       Lscala/collection/MapLike$$anon$1;
   0      35      1    key       Ljava/lang/Object;

  Signature: length = 0x2
   02 7A 

public scala.Option get(java.lang.Object);
  Signature: (Ljava/lang/Object;)Lscala/Option;
  Code:
   Stack=2, Locals=2, Args_size=2
	aload_0
	getfield	Field p$1:Lscala/Function1;
	aload_1
	invokeinterface	InterfaceMethod scala/Function1.apply:(Ljava/lang/Object;)Ljava/lang/Object;
	invokestatic	Method scala/runtime/BoxesRunTime.unboxToBoolean:(Ljava/lang/Object;)Z
	ifeq	l1 // getstatic
	aload_0
	getfield	Field $outer:Lscala/collection/MapLike;
	aload_1
	invokeinterface	InterfaceMethod scala/collection/MapLike.get:(Ljava/lang/Object;)Lscala/Option;
	goto	l2 // areturn
l1	getstatic	Field scala/None$.MODULE$:Lscala/None$;
l2	areturn
  Labels:
   	l1 = 29 // getstatic
   	l2 = 32 // areturn
  LocalVariableTable: 
   Start  Length  Slot  Name   Signature
   0      33      0    this       Lscala/collection/MapLike$$anon$1;
   0      33      1    key       Ljava/lang/Object;

  Signature: length = 0x2
   02 FFFFFF85 

public scala.collection.generic.Subtractable repr();
  Signature: ()Lscala/collection/generic/Subtractable;
  Code:
   Stack=1, Locals=1, Args_size=1
	aload_0
	invokeinterface	InterfaceMethod scala/collection/TraversableLike.repr:()Ljava/lang/Object;
	checkcast	class scala/collection/generic/Subtractable
	areturn
  Labels:

public scala.collection.TraversableView view(int, int);
  Signature: (II)Lscala/collection/TraversableView;
  Code:
   Stack=3, Locals=3, Args_size=3
	aload_0
	iload_1
	iload_2
	invokeinterface	InterfaceMethod scala/collection/IterableLike.view:(II)Lscala/collection/IterableView;
	areturn
  Labels:
  LocalVariableTable: 
   Start  Length  Slot  Name   Signature
   0      9      0    this       Lscala/collection/MapLike$$anon$1;
   0      9      1    from       I
   0      9      2    until       I


public scala.collection.TraversableView view();
  Signature: ()Lscala/collection/TraversableView;
  Code:
   Stack=1, Locals=1, Args_size=1
	aload_0
	invokeinterface	InterfaceMethod scala/collection/IterableLike.view:()Lscala/collection/IterableView;
	areturn
  Labels:

public scala.collection.Traversable toCollection(java.lang.Object);
  Signature: (Ljava/lang/Object;)Lscala/collection/Traversable;
  Code:
   Stack=2, Locals=2, Args_size=2
	aload_0
	aload_1
	invokeinterface	InterfaceMethod scala/collection/IterableLike.toCollection:(Ljava/lang/Object;)Lscala/collection/Iterable;
	areturn
  Labels:
  LocalVariableTable: 
   Start  Length  Slot  Name   Signature
   0      8      0    this       Lscala/collection/MapLike$$anon$1;
   0      8      1    repr       Ljava/lang/Object;


public scala.collection.Traversable thisCollection();
  Signature: ()Lscala/collection/Traversable;
  Code:
   Stack=1, Locals=1, Args_size=1
	aload_0
	invokeinterface	InterfaceMethod scala/collection/IterableLike.thisCollection:()Lscala/collection/Iterable;
	areturn
  Labels:

public scala.Function1 andThen(scala.Function1);
  Signature: (Lscala/Function1;)Lscala/Function1;
  Code:
   Stack=2, Locals=2, Args_size=2
	aload_0
	aload_1
	invokeinterface	InterfaceMethod scala/PartialFunction.andThen:(Lscala/Function1;)Lscala/PartialFunction;
	areturn
  Labels:
  LocalVariableTable: 
   Start  Length  Slot  Name   Signature
   0      8      0    this       Lscala/collection/MapLike$$anon$1;
   0      8      1    g       Lscala/Function1;


public java.lang.Object filterNot(scala.Function1);
  Signature: (Lscala/Function1;)Ljava/lang/Object;
  Code:
   Stack=2, Locals=2, Args_size=2
	aload_0
	aload_1
	invokeinterface	InterfaceMethod scala/collection/MapLike.filterNot:(Lscala/Function1;)Lscala/collection/Map;
	areturn
  Labels:
  LocalVariableTable: 
   Start  Length  Slot  Name   Signature
   0      8      0    this       Lscala/collection/MapLike$$anon$1;
   0      8      1    p       Lscala/Function1;


public scala.collection.generic.Subtractable $minus(java.lang.Object);
  Signature: (Ljava/lang/Object;)Lscala/collection/generic/Subtractable;
  Code:
   Stack=2, Locals=2, Args_size=2
	aload_0
	aload_1
	invokeinterface	InterfaceMethod scala/collection/DefaultMap.$minus:(Ljava/lang/Object;)Lscala/collection/Map;
	areturn
  Labels:
  LocalVariableTable: 
   Start  Length  Slot  Name   Signature
   0      8      0    this       Lscala/collection/MapLike$$anon$1;
   0      8      1    elem       Ljava/lang/Object;


public scala.collection.MapLike$$anon$1(scala.collection.MapLike, scala.Function1);
  Signature: (Lscala/collection/MapLike;Lscala/Function1;)V
  Code:
   Stack=2, Locals=3, Args_size=3
	aload_1
	ifnonnull	l1 // aload_0
	new	class java/lang/NullPointerException
	dup
	invokespecial	Method java/lang/NullPointerException."<init>":()V
	athrow
l1	aload_0
	aload_1
	putfield	Field $outer:Lscala/collection/MapLike;
	aload_0
	aload_2
	putfield	Field p$1:Lscala/Function1;
	aload_0
	invokespecial	Method java/lang/Object."<init>":()V
	aload_0
	invokestatic	Method scala/collection/TraversableLike$class.$init$:(Lscala/collection/TraversableLike;)V
	aload_0
	invokestatic	Method scala/collection/generic/GenericTraversableTemplate$class.$init$:(Lscala/collection/generic/GenericTraversableTemplate;)V
	aload_0
	invokestatic	Method scala/collection/Traversable$class.$init$:(Lscala/collection/Traversable;)V
	aload_0
	invokestatic	Method scala/collection/IterableLike$class.$init$:(Lscala/collection/IterableLike;)V
	aload_0
	invokestatic	Method scala/collection/Iterable$class.$init$:(Lscala/collection/Iterable;)V
	aload_0
	invokestatic	Method scala/Function1$class.$init$:(Lscala/Function1;)V
	aload_0
	invokestatic	Method scala/PartialFunction$class.$init$:(Lscala/PartialFunction;)V
	aload_0
	invokestatic	Method scala/collection/generic/Subtractable$class.$init$:(Lscala/collection/generic/Subtractable;)V
	aload_0
	invokestatic	Method scala/collection/MapLike$class.$init$:(Lscala/collection/MapLike;)V
	aload_0
	invokestatic	Method scala/collection/Map$class.$init$:(Lscala/collection/Map;)V
	aload_0
	invokestatic	Method scala/collection/DefaultMap$class.$init$:(Lscala/collection/DefaultMap;)V
	return
  Labels:
   	l1 = 12 // aload_0
  LocalVariableTable: 
   Start  Length  Slot  Name   Signature
   0      71      0    this       Lscala/collection/MapLike$$anon$1;
   0      71      1    $outer       Lscala/collection/MapLike;

  Signature: length = 0x2
   02 FFFFFFD1 

}

