Compiled from "MapLike.scala"
public abstract class scala.collection.MapLike$class extends java.lang.Object
  SourceFile: "MapLike.scala"
  Scala: length = 0x
   
  InnerClass: 
   public final #310= #245 of #125; //$anon$3=class scala/collection/MapLike$$anon$3 of class scala/collection/MapLike
   public final #311= #233 of #125; //$anon$4=class scala/collection/MapLike$$anon$4 of class scala/collection/MapLike
   public final #312= #207 of #125; //$anon$1=class scala/collection/MapLike$$anon$1 of class scala/collection/MapLike
   public final #313= #200 of #125; //$anon$2=class scala/collection/MapLike$$anon$2 of class scala/collection/MapLike
   public #314= #250 of #125; //DefaultKeySet=class scala/collection/MapLike$DefaultKeySet of class scala/collection/MapLike
   public final #315= #82 of #125; //$anonfun$hashCode$1=class scala/collection/MapLike$$anonfun$hashCode$1 of class scala/collection/MapLike
   public final #316= #131 of #125; //$anonfun$addString$1=class scala/collection/MapLike$$anonfun$addString$1 of class scala/collection/MapLike
   public #317= #238 of #125; //DefaultValuesIterable=class scala/collection/MapLike$DefaultValuesIterable of class scala/collection/MapLike
   public final #318= #164 of #125; //$anonfun$$plus$plus$1=class scala/collection/MapLike$$anonfun$$plus$plus$1 of class scala/collection/MapLike
   public final #319= #154 of #125; //$anonfun$$plus$plus$2=class scala/collection/MapLike$$anonfun$$plus$plus$2 of class scala/collection/MapLike
   public final #320= #13 of #125; //$anonfun$liftedTree1$1$1=class scala/collection/MapLike$$anonfun$liftedTree1$1$1 of class scala/collection/MapLike
  minor version: 0
  major version: 49
  Constant pool:
const #1 = Asciz	SourceFile;
const #2 = Asciz	MapLike.scala;
const #3 = Asciz	$init$;
const #4 = Asciz	(Lscala/collection/MapLike;)V;
const #5 = Asciz	Code;
const #6 = Asciz	LineNumberTable;
const #7 = Asciz	$this;
const #8 = Asciz	Lscala/collection/MapLike;;
const #9 = Asciz	LocalVariableTable;
const #10 = Asciz	liftedTree1$1;
const #11 = Asciz	(Lscala/collection/MapLike;Lscala/collection/Map;)Z;
const #12 = Asciz	scala/collection/MapLike$$anonfun$liftedTree1$1$1;
const #13 = class	#12;	//  scala/collection/MapLike$$anonfun$liftedTree1$1$1
const #14 = Asciz	<init>;
const #15 = Asciz	(Lscala/collection/MapLike;Lscala/collection/Map;)V;
const #16 = NameAndType	#14:#15;//  "<init>":(Lscala/collection/MapLike;Lscala/collection/Map;)V
const #17 = Method	#13.#16;	//  scala/collection/MapLike$$anonfun$liftedTree1$1$1."<init>":(Lscala/collection/MapLike;Lscala/collection/Map;)V
const #18 = Asciz	scala/collection/IterableLike;
const #19 = class	#18;	//  scala/collection/IterableLike
const #20 = Asciz	forall;
const #21 = Asciz	(Lscala/Function1;)Z;
const #22 = NameAndType	#20:#21;//  forall:(Lscala/Function1;)Z
const #23 = InterfaceMethod	#19.#22;	//  scala/collection/IterableLike.forall:(Lscala/Function1;)Z
const #24 = Asciz	calss cast ;
const #25 = String	#24;	//  calss cast 
const #26 = Asciz	scala/Console$;
const #27 = class	#26;	//  scala/Console$
const #28 = Asciz	MODULE$;
const #29 = Asciz	Lscala/Console$;;
const #30 = NameAndType	#28:#29;//  MODULE$:Lscala/Console$;
const #31 = Field	#27.#30;	//  scala/Console$.MODULE$:Lscala/Console$;
const #32 = Asciz	out;
const #33 = Asciz	()Ljava/io/PrintStream;;
const #34 = NameAndType	#32:#33;//  out:()Ljava/io/PrintStream;
const #35 = Method	#27.#34;	//  scala/Console$.out:()Ljava/io/PrintStream;
const #36 = Asciz	java/io/PrintStream;
const #37 = class	#36;	//  java/io/PrintStream
const #38 = Asciz	println;
const #39 = Asciz	(Ljava/lang/Object;)V;
const #40 = NameAndType	#38:#39;//  println:(Ljava/lang/Object;)V
const #41 = Method	#37.#40;	//  java/io/PrintStream.println:(Ljava/lang/Object;)V
const #42 = Asciz	java/lang/ClassCastException;
const #43 = class	#42;	//  java/lang/ClassCastException
const #44 = Asciz	exceptionResult1;
const #45 = Asciz	Z;
const #46 = Asciz	equals;
const #47 = Asciz	(Lscala/collection/MapLike;Ljava/lang/Object;)Z;
const #48 = Asciz	scala/collection/Map;
const #49 = class	#48;	//  scala/collection/Map
const #50 = Asciz	canEqual;
const #51 = Asciz	(Ljava/lang/Object;)Z;
const #52 = NameAndType	#50:#51;//  canEqual:(Ljava/lang/Object;)Z
const #53 = InterfaceMethod	#19.#52;	//  scala/collection/IterableLike.canEqual:(Ljava/lang/Object;)Z
const #54 = Asciz	scala/collection/TraversableLike;
const #55 = class	#54;	//  scala/collection/TraversableLike
const #56 = Asciz	size;
const #57 = Asciz	()I;
const #58 = NameAndType	#56:#57;//  size:()I
const #59 = InterfaceMethod	#55.#58;	//  scala/collection/TraversableLike.size:()I
const #60 = Asciz	scala/collection/MapLike$class;
const #61 = class	#60;	//  scala/collection/MapLike$class
const #62 = NameAndType	#10:#11;//  liftedTree1$1:(Lscala/collection/MapLike;Lscala/collection/Map;)Z
const #63 = Method	#61.#62;	//  scala/collection/MapLike$class.liftedTree1$1:(Lscala/collection/MapLike;Lscala/collection/Map;)Z
const #64 = Asciz	scala/MatchError;
const #65 = class	#64;	//  scala/MatchError
const #66 = Asciz	java/lang/Object;
const #67 = class	#66;	//  java/lang/Object
const #68 = Asciz	toString;
const #69 = Asciz	()Ljava/lang/String;;
const #70 = NameAndType	#68:#69;//  toString:()Ljava/lang/String;
const #71 = Method	#67.#70;	//  java/lang/Object.toString:()Ljava/lang/String;
const #72 = Asciz	(Ljava/lang/String;)V;
const #73 = NameAndType	#14:#72;//  "<init>":(Ljava/lang/String;)V
const #74 = Method	#65.#73;	//  scala/MatchError."<init>":(Ljava/lang/String;)V
const #75 = Asciz	that;
const #76 = Asciz	Ljava/lang/Object;;
const #77 = Asciz	temp45;
const #78 = Asciz	Lscala/collection/Map;;
const #79 = Asciz	hashCode;
const #80 = Asciz	(Lscala/collection/MapLike;)I;
const #81 = Asciz	scala/collection/MapLike$$anonfun$hashCode$1;
const #82 = class	#81;	//  scala/collection/MapLike$$anonfun$hashCode$1
const #83 = NameAndType	#14:#4;//  "<init>":(Lscala/collection/MapLike;)V
const #84 = Method	#82.#83;	//  scala/collection/MapLike$$anonfun$hashCode$1."<init>":(Lscala/collection/MapLike;)V
const #85 = Asciz	scala/collection/Iterable$;
const #86 = class	#85;	//  scala/collection/Iterable$
const #87 = Asciz	Lscala/collection/Iterable$;;
const #88 = NameAndType	#28:#87;//  MODULE$:Lscala/collection/Iterable$;
const #89 = Field	#86.#88;	//  scala/collection/Iterable$.MODULE$:Lscala/collection/Iterable$;
const #90 = Asciz	canBuildFrom;
const #91 = Asciz	()Lscala/collection/generic/CanBuildFrom;;
const #92 = NameAndType	#90:#91;//  canBuildFrom:()Lscala/collection/generic/CanBuildFrom;
const #93 = Method	#86.#92;	//  scala/collection/Iterable$.canBuildFrom:()Lscala/collection/generic/CanBuildFrom;
const #94 = Asciz	map;
const #95 = Asciz	(Lscala/Function1;Lscala/collection/generic/CanBuildFrom;)Ljava/lang/Object;;
const #96 = NameAndType	#94:#95;//  map:(Lscala/Function1;Lscala/collection/generic/CanBuildFrom;)Ljava/lang/Object;
const #97 = InterfaceMethod	#55.#96;	//  scala/collection/TraversableLike.map:(Lscala/Function1;Lscala/collection/generic/CanBuildFrom;)Ljava/lang/Object;
const #98 = Asciz	scala/math/Numeric$IntIsIntegral$;
const #99 = class	#98;	//  scala/math/Numeric$IntIsIntegral$
const #100 = Asciz	Lscala/math/Numeric$IntIsIntegral$;;
const #101 = NameAndType	#28:#100;//  MODULE$:Lscala/math/Numeric$IntIsIntegral$;
const #102 = Field	#99.#101;	//  scala/math/Numeric$IntIsIntegral$.MODULE$:Lscala/math/Numeric$IntIsIntegral$;
const #103 = Asciz	sum;
const #104 = Asciz	(Lscala/math/Numeric;)Ljava/lang/Object;;
const #105 = NameAndType	#103:#104;//  sum:(Lscala/math/Numeric;)Ljava/lang/Object;
const #106 = InterfaceMethod	#55.#105;	//  scala/collection/TraversableLike.sum:(Lscala/math/Numeric;)Ljava/lang/Object;
const #107 = Asciz	scala/runtime/BoxesRunTime;
const #108 = class	#107;	//  scala/runtime/BoxesRunTime
const #109 = Asciz	unboxToInt;
const #110 = Asciz	(Ljava/lang/Object;)I;
const #111 = NameAndType	#109:#110;//  unboxToInt:(Ljava/lang/Object;)I
const #112 = Method	#108.#111;	//  scala/runtime/BoxesRunTime.unboxToInt:(Ljava/lang/Object;)I
const #113 = Asciz	(Lscala/collection/MapLike;)Ljava/lang/String;;
const #114 = Asciz	scala/collection/TraversableLike$class;
const #115 = class	#114;	//  scala/collection/TraversableLike$class
const #116 = Asciz	(Lscala/collection/TraversableLike;)Ljava/lang/String;;
const #117 = NameAndType	#68:#116;//  toString:(Lscala/collection/TraversableLike;)Ljava/lang/String;
const #118 = Method	#115.#117;	//  scala/collection/TraversableLike$class.toString:(Lscala/collection/TraversableLike;)Ljava/lang/String;
const #119 = Asciz	stringPrefix;
const #120 = Asciz	Map;
const #121 = String	#120;	//  Map
const #122 = Asciz	addString;
const #123 = Asciz	(Lscala/collection/MapLike;Lscala/collection/mutable/StringBuilder;Ljava/lang/String;Ljava/lang/String;Ljava/lang/String;)Lscala/collection/mutable/StringBuilder;;
const #124 = Asciz	scala/collection/MapLike;
const #125 = class	#124;	//  scala/collection/MapLike
const #126 = Asciz	iterator;
const #127 = Asciz	()Lscala/collection/Iterator;;
const #128 = NameAndType	#126:#127;//  iterator:()Lscala/collection/Iterator;
const #129 = InterfaceMethod	#125.#128;	//  scala/collection/MapLike.iterator:()Lscala/collection/Iterator;
const #130 = Asciz	scala/collection/MapLike$$anonfun$addString$1;
const #131 = class	#130;	//  scala/collection/MapLike$$anonfun$addString$1
const #132 = Method	#131.#83;	//  scala/collection/MapLike$$anonfun$addString$1."<init>":(Lscala/collection/MapLike;)V
const #133 = Asciz	scala/collection/Iterator;
const #134 = class	#133;	//  scala/collection/Iterator
const #135 = Asciz	(Lscala/Function1;)Lscala/collection/Iterator;;
const #136 = NameAndType	#94:#135;//  map:(Lscala/Function1;)Lscala/collection/Iterator;
const #137 = InterfaceMethod	#134.#136;	//  scala/collection/Iterator.map:(Lscala/Function1;)Lscala/collection/Iterator;
const #138 = Asciz	(Lscala/collection/mutable/StringBuilder;Ljava/lang/String;Ljava/lang/String;Ljava/lang/String;)Lscala/collection/mutable/StringBuilder;;
const #139 = NameAndType	#122:#138;//  addString:(Lscala/collection/mutable/StringBuilder;Ljava/lang/String;Ljava/lang/String;Ljava/lang/String;)Lscala/collection/mutable/StringBuilder;
const #140 = InterfaceMethod	#134.#139;	//  scala/collection/Iterator.addString:(Lscala/collection/mutable/StringBuilder;Ljava/lang/String;Ljava/lang/String;Ljava/lang/String;)Lscala/collection/mutable/StringBuilder;
const #141 = Asciz	b;
const #142 = Asciz	Lscala/collection/mutable/StringBuilder;;
const #143 = Asciz	start;
const #144 = Asciz	Ljava/lang/String;;
const #145 = Asciz	sep;
const #146 = Asciz	end;
const #147 = Asciz	$plus$plus;
const #148 = Asciz	(Lscala/collection/MapLike;Lscala/collection/Iterator;)Lscala/collection/Map;;
const #149 = Asciz	repr;
const #150 = Asciz	()Ljava/lang/Object;;
const #151 = NameAndType	#149:#150;//  repr:()Ljava/lang/Object;
const #152 = InterfaceMethod	#55.#151;	//  scala/collection/TraversableLike.repr:()Ljava/lang/Object;
const #153 = Asciz	scala/collection/MapLike$$anonfun$$plus$plus$2;
const #154 = class	#153;	//  scala/collection/MapLike$$anonfun$$plus$plus$2
const #155 = Method	#154.#83;	//  scala/collection/MapLike$$anonfun$$plus$plus$2."<init>":(Lscala/collection/MapLike;)V
const #156 = Asciz	$div$colon;
const #157 = Asciz	(Ljava/lang/Object;Lscala/Function2;)Ljava/lang/Object;;
const #158 = NameAndType	#156:#157;//  $div$colon:(Ljava/lang/Object;Lscala/Function2;)Ljava/lang/Object;
const #159 = InterfaceMethod	#134.#158;	//  scala/collection/Iterator.$div$colon:(Ljava/lang/Object;Lscala/Function2;)Ljava/lang/Object;
const #160 = Asciz	iter;
const #161 = Asciz	Lscala/collection/Iterator;;
const #162 = Asciz	(Lscala/collection/MapLike;Lscala/collection/Traversable;)Lscala/collection/Map;;
const #163 = Asciz	scala/collection/MapLike$$anonfun$$plus$plus$1;
const #164 = class	#163;	//  scala/collection/MapLike$$anonfun$$plus$plus$1
const #165 = Method	#164.#83;	//  scala/collection/MapLike$$anonfun$$plus$plus$1."<init>":(Lscala/collection/MapLike;)V
const #166 = InterfaceMethod	#55.#158;	//  scala/collection/TraversableLike.$div$colon:(Ljava/lang/Object;Lscala/Function2;)Ljava/lang/Object;
const #167 = Asciz	kvs;
const #168 = Asciz	Lscala/collection/Traversable;;
const #169 = Asciz	$plus;
const #170 = Asciz	(Lscala/collection/MapLike;Lscala/Tuple2;Lscala/Tuple2;Lscala/collection/Seq;)Lscala/collection/Map;;
const #171 = Asciz	(Lscala/Tuple2;)Lscala/collection/Map;;
const #172 = NameAndType	#169:#171;//  $plus:(Lscala/Tuple2;)Lscala/collection/Map;
const #173 = InterfaceMethod	#125.#172;	//  scala/collection/MapLike.$plus:(Lscala/Tuple2;)Lscala/collection/Map;
const #174 = Asciz	(Lscala/collection/Traversable;)Lscala/collection/Map;;
const #175 = NameAndType	#147:#174;//  $plus$plus:(Lscala/collection/Traversable;)Lscala/collection/Map;
const #176 = InterfaceMethod	#125.#175;	//  scala/collection/MapLike.$plus$plus:(Lscala/collection/Traversable;)Lscala/collection/Map;
const #177 = Asciz	kv1;
const #178 = Asciz	Lscala/Tuple2;;
const #179 = Asciz	kv2;
const #180 = Asciz	Lscala/collection/Seq;;
const #181 = Asciz	updated;
const #182 = Asciz	(Lscala/collection/MapLike;Ljava/lang/Object;Ljava/lang/Object;)Lscala/collection/Map;;
const #183 = Asciz	scala/Tuple2;
const #184 = class	#183;	//  scala/Tuple2
const #185 = Asciz	(Ljava/lang/Object;Ljava/lang/Object;)V;
const #186 = NameAndType	#14:#185;//  "<init>":(Ljava/lang/Object;Ljava/lang/Object;)V
const #187 = Method	#184.#186;	//  scala/Tuple2."<init>":(Ljava/lang/Object;Ljava/lang/Object;)V
const #188 = Asciz	key;
const #189 = Asciz	value;
const #190 = Asciz	mapElements;
const #191 = Asciz	(Lscala/collection/MapLike;Lscala/Function1;)Ljava/lang/Object;;
const #192 = Asciz	mapValues;
const #193 = Asciz	(Lscala/Function1;)Ljava/lang/Object;;
const #194 = NameAndType	#192:#193;//  mapValues:(Lscala/Function1;)Ljava/lang/Object;
const #195 = InterfaceMethod	#125.#194;	//  scala/collection/MapLike.mapValues:(Lscala/Function1;)Ljava/lang/Object;
const #196 = Asciz	f;
const #197 = Asciz	Lscala/Function1;;
const #198 = Asciz	Deprecated;
const #199 = Asciz	scala/collection/MapLike$$anon$2;
const #200 = class	#199;	//  scala/collection/MapLike$$anon$2
const #201 = Asciz	(Lscala/collection/MapLike;Lscala/Function1;)V;
const #202 = NameAndType	#14:#201;//  "<init>":(Lscala/collection/MapLike;Lscala/Function1;)V
const #203 = Method	#200.#202;	//  scala/collection/MapLike$$anon$2."<init>":(Lscala/collection/MapLike;Lscala/Function1;)V
const #204 = Asciz	f$4;
const #205 = Asciz	filterKeys;
const #206 = Asciz	scala/collection/MapLike$$anon$1;
const #207 = class	#206;	//  scala/collection/MapLike$$anon$1
const #208 = Method	#207.#202;	//  scala/collection/MapLike$$anon$1."<init>":(Lscala/collection/MapLike;Lscala/Function1;)V
const #209 = Asciz	p$1;
const #210 = Asciz	default;
const #211 = Asciz	(Lscala/collection/MapLike;Ljava/lang/Object;)Ljava/lang/Object;;
const #212 = Asciz	java/util/NoSuchElementException;
const #213 = class	#212;	//  java/util/NoSuchElementException
const #214 = Asciz	scala/collection/mutable/StringBuilder;
const #215 = class	#214;	//  scala/collection/mutable/StringBuilder
const #216 = Asciz	()V;
const #217 = NameAndType	#14:#216;//  "<init>":()V
const #218 = Method	#215.#217;	//  scala/collection/mutable/StringBuilder."<init>":()V
const #219 = Asciz	key not found: ;
const #220 = String	#219;	//  key not found: 
const #221 = Asciz	append;
const #222 = Asciz	(Ljava/lang/Object;)Lscala/collection/mutable/StringBuilder;;
const #223 = NameAndType	#221:#222;//  append:(Ljava/lang/Object;)Lscala/collection/mutable/StringBuilder;
const #224 = Method	#215.#223;	//  scala/collection/mutable/StringBuilder.append:(Ljava/lang/Object;)Lscala/collection/mutable/StringBuilder;
const #225 = Method	#215.#70;	//  scala/collection/mutable/StringBuilder.toString:()Ljava/lang/String;
const #226 = Method	#213.#73;	//  java/util/NoSuchElementException."<init>":(Ljava/lang/String;)V
const #227 = Asciz	values;
const #228 = Asciz	(Lscala/collection/MapLike;)Lscala/collection/Iterator;;
const #229 = Asciz	valuesIterator;
const #230 = NameAndType	#229:#127;//  valuesIterator:()Lscala/collection/Iterator;
const #231 = InterfaceMethod	#125.#230;	//  scala/collection/MapLike.valuesIterator:()Lscala/collection/Iterator;
const #232 = Asciz	scala/collection/MapLike$$anon$4;
const #233 = class	#232;	//  scala/collection/MapLike$$anon$4
const #234 = Method	#233.#83;	//  scala/collection/MapLike$$anon$4."<init>":(Lscala/collection/MapLike;)V
const #235 = Asciz	valuesIterable;
const #236 = Asciz	(Lscala/collection/MapLike;)Lscala/collection/Iterable;;
const #237 = Asciz	scala/collection/MapLike$DefaultValuesIterable;
const #238 = class	#237;	//  scala/collection/MapLike$DefaultValuesIterable
const #239 = Method	#238.#83;	//  scala/collection/MapLike$DefaultValuesIterable."<init>":(Lscala/collection/MapLike;)V
const #240 = Asciz	keys;
const #241 = Asciz	keysIterator;
const #242 = NameAndType	#241:#127;//  keysIterator:()Lscala/collection/Iterator;
const #243 = InterfaceMethod	#125.#242;	//  scala/collection/MapLike.keysIterator:()Lscala/collection/Iterator;
const #244 = Asciz	scala/collection/MapLike$$anon$3;
const #245 = class	#244;	//  scala/collection/MapLike$$anon$3
const #246 = Method	#245.#83;	//  scala/collection/MapLike$$anon$3."<init>":(Lscala/collection/MapLike;)V
const #247 = Asciz	keySet;
const #248 = Asciz	(Lscala/collection/MapLike;)Lscala/collection/Set;;
const #249 = Asciz	scala/collection/MapLike$DefaultKeySet;
const #250 = class	#249;	//  scala/collection/MapLike$DefaultKeySet
const #251 = Method	#250.#83;	//  scala/collection/MapLike$DefaultKeySet."<init>":(Lscala/collection/MapLike;)V
const #252 = Asciz	isDefinedAt;
const #253 = Asciz	contains;
const #254 = NameAndType	#253:#51;//  contains:(Ljava/lang/Object;)Z
const #255 = InterfaceMethod	#125.#254;	//  scala/collection/MapLike.contains:(Ljava/lang/Object;)Z
const #256 = Asciz	get;
const #257 = Asciz	(Ljava/lang/Object;)Lscala/Option;;
const #258 = NameAndType	#256:#257;//  get:(Ljava/lang/Object;)Lscala/Option;
const #259 = InterfaceMethod	#125.#258;	//  scala/collection/MapLike.get:(Ljava/lang/Object;)Lscala/Option;
const #260 = Asciz	scala/None$;
const #261 = class	#260;	//  scala/None$
const #262 = Asciz	Lscala/None$;;
const #263 = NameAndType	#28:#262;//  MODULE$:Lscala/None$;
const #264 = Field	#261.#263;	//  scala/None$.MODULE$:Lscala/None$;
const #265 = NameAndType	#46:#51;//  equals:(Ljava/lang/Object;)Z
const #266 = Method	#67.#265;	//  java/lang/Object.equals:(Ljava/lang/Object;)Z
const #267 = Asciz	scala/Option;
const #268 = class	#267;	//  scala/Option
const #269 = Method	#268.#70;	//  scala/Option.toString:()Ljava/lang/String;
const #270 = Asciz	scala/Some;
const #271 = class	#270;	//  scala/Some
const #272 = Asciz	temp9;
const #273 = Asciz	Lscala/Option;;
const #274 = Asciz	apply;
const #275 = Asciz	(Ljava/lang/Object;)Ljava/lang/Object;;
const #276 = NameAndType	#210:#275;//  default:(Ljava/lang/Object;)Ljava/lang/Object;
const #277 = InterfaceMethod	#125.#276;	//  scala/collection/MapLike.default:(Ljava/lang/Object;)Ljava/lang/Object;
const #278 = Asciz	x;
const #279 = NameAndType	#278:#76;//  x:Ljava/lang/Object;
const #280 = Field	#271.#279;	//  scala/Some.x:Ljava/lang/Object;
const #281 = Asciz	temp7;
const #282 = Asciz	Lscala/Some;;
const #283 = Asciz	temp8;
const #284 = Asciz	temp5;
const #285 = Asciz	getOrElse;
const #286 = Asciz	(Lscala/collection/MapLike;Ljava/lang/Object;Lscala/Function0;)Ljava/lang/Object;;
const #287 = Asciz	scala/Function0;
const #288 = class	#287;	//  scala/Function0
const #289 = NameAndType	#274:#150;//  apply:()Ljava/lang/Object;
const #290 = InterfaceMethod	#288.#289;	//  scala/Function0.apply:()Ljava/lang/Object;
const #291 = Asciz	Lscala/Function0;;
const #292 = Asciz	temp2;
const #293 = Asciz	temp3;
const #294 = Asciz	temp1;
const #295 = Asciz	isEmpty;
const #296 = Asciz	(Lscala/collection/MapLike;)Z;
const #297 = Asciz	newBuilder;
const #298 = Asciz	(Lscala/collection/MapLike;)Lscala/collection/mutable/Builder;;
const #299 = Asciz	scala/collection/mutable/MapBuilder;
const #300 = class	#299;	//  scala/collection/mutable/MapBuilder
const #301 = Asciz	empty;
const #302 = Asciz	()Lscala/collection/MapLike;;
const #303 = NameAndType	#301:#302;//  empty:()Lscala/collection/MapLike;
const #304 = InterfaceMethod	#125.#303;	//  scala/collection/MapLike.empty:()Lscala/collection/MapLike;
const #305 = Asciz	(Lscala/collection/Map;)V;
const #306 = NameAndType	#14:#305;//  "<init>":(Lscala/collection/Map;)V
const #307 = Method	#300.#306;	//  scala/collection/mutable/MapBuilder."<init>":(Lscala/collection/Map;)V
const #308 = Asciz	Scala;
const #309 = Asciz	InnerClasses;
const #310 = Asciz	$anon$3;
const #311 = Asciz	$anon$4;
const #312 = Asciz	$anon$1;
const #313 = Asciz	$anon$2;
const #314 = Asciz	DefaultKeySet;
const #315 = Asciz	$anonfun$hashCode$1;
const #316 = Asciz	$anonfun$addString$1;
const #317 = Asciz	DefaultValuesIterable;
const #318 = Asciz	$anonfun$$plus$plus$1;
const #319 = Asciz	$anonfun$$plus$plus$2;
const #320 = Asciz	$anonfun$liftedTree1$1$1;

{
public static void $init$(scala.collection.MapLike);
  Code:
   Stack=0, Locals=1, Args_size=1
   0:	return
  LineNumberTable: 
   line 55: 0

  LocalVariableTable: 
   Start  Length  Slot  Name   Signature
   0      1      0    $this       Lscala/collection/MapLike;


public static boolean equals(scala.collection.MapLike, java.lang.Object);
  Code:
   Stack=3, Locals=3, Args_size=2
   0:	aload_1
   1:	instanceof	#49; //class scala/collection/Map
   4:	ifeq	74
   7:	aload_1
   8:	checkcast	#49; //class scala/collection/Map
   11:	astore_2
   12:	iconst_1
   13:	ifeq	62
   16:	aload_0
   17:	aload_2
   18:	if_acmpeq	54
   21:	aload_2
   22:	aload_0
   23:	invokeinterface	#53,  2; //InterfaceMethod scala/collection/IterableLike.canEqual:(Ljava/lang/Object;)Z
   28:	ifeq	58
   31:	aload_0
   32:	invokeinterface	#59,  1; //InterfaceMethod scala/collection/TraversableLike.size:()I
   37:	aload_2
   38:	invokeinterface	#59,  1; //InterfaceMethod scala/collection/TraversableLike.size:()I
   43:	if_icmpne	58
   46:	aload_0
   47:	aload_2
   48:	invokestatic	#63; //Method liftedTree1$1:(Lscala/collection/MapLike;Lscala/collection/Map;)Z
   51:	ifeq	58
   54:	iconst_1
   55:	goto	79
   58:	iconst_0
   59:	goto	79
   62:	new	#65; //class scala/MatchError
   65:	dup
   66:	aload_1
   67:	invokevirtual	#71; //Method java/lang/Object.toString:()Ljava/lang/String;
   70:	invokespecial	#74; //Method scala/MatchError."<init>":(Ljava/lang/String;)V
   73:	athrow
   74:	iconst_1
   75:	ifeq	80
   78:	iconst_0
   79:	ireturn
   80:	new	#65; //class scala/MatchError
   83:	dup
   84:	aload_1
   85:	invokevirtual	#71; //Method java/lang/Object.toString:()Ljava/lang/String;
   88:	invokespecial	#74; //Method scala/MatchError."<init>":(Ljava/lang/String;)V
   91:	athrow
  LineNumberTable: 
   line 340: 0
   line 21: 12
   line 342: 16
   line 343: 21
   line 344: 31
   line 345: 46
   line 342: 54
   line 340: 62
   line 21: 74
   line 357: 78
   line 340: 79

  LocalVariableTable: 
   Start  Length  Slot  Name   Signature
   0      92      0    $this       Lscala/collection/MapLike;
   0      92      1    that       Ljava/lang/Object;
   12      62      2    temp45       Lscala/collection/Map;


public static int hashCode(scala.collection.MapLike);
  Code:
   Stack=4, Locals=1, Args_size=1
   0:	aload_0
   1:	new	#82; //class scala/collection/MapLike$$anonfun$hashCode$1
   4:	dup
   5:	aload_0
   6:	invokespecial	#84; //Method scala/collection/MapLike$$anonfun$hashCode$1."<init>":(Lscala/collection/MapLike;)V
   9:	getstatic	#89; //Field scala/collection/Iterable$.MODULE$:Lscala/collection/Iterable$;
   12:	invokevirtual	#93; //Method scala/collection/Iterable$.canBuildFrom:()Lscala/collection/generic/CanBuildFrom;
   15:	invokeinterface	#97,  3; //InterfaceMethod scala/collection/TraversableLike.map:(Lscala/Function1;Lscala/collection/generic/CanBuildFrom;)Ljava/lang/Object;
   20:	checkcast	#55; //class scala/collection/TraversableLike
   23:	getstatic	#102; //Field scala/math/Numeric$IntIsIntegral$.MODULE$:Lscala/math/Numeric$IntIsIntegral$;
   26:	invokeinterface	#106,  2; //InterfaceMethod scala/collection/TraversableLike.sum:(Lscala/math/Numeric;)Ljava/lang/Object;
   31:	invokestatic	#112; //Method scala/runtime/BoxesRunTime.unboxToInt:(Ljava/lang/Object;)I
   34:	ireturn
  LineNumberTable: 
   line 330: 0

  LocalVariableTable: 
   Start  Length  Slot  Name   Signature
   0      35      0    $this       Lscala/collection/MapLike;


public static java.lang.String toString(scala.collection.MapLike);
  Code:
   Stack=1, Locals=1, Args_size=1
   0:	aload_0
   1:	invokestatic	#118; //Method scala/collection/TraversableLike$class.toString:(Lscala/collection/TraversableLike;)Ljava/lang/String;
   4:	areturn
  LineNumberTable: 
   line 328: 0

  LocalVariableTable: 
   Start  Length  Slot  Name   Signature
   0      5      0    $this       Lscala/collection/MapLike;


public static java.lang.String stringPrefix(scala.collection.MapLike);
  Code:
   Stack=1, Locals=1, Args_size=1
   0:	ldc	#121; //String Map
   2:	areturn
  LineNumberTable: 
   line 325: 0

  LocalVariableTable: 
   Start  Length  Slot  Name   Signature
   0      3      0    $this       Lscala/collection/MapLike;


public static scala.collection.mutable.StringBuilder addString(scala.collection.MapLike, scala.collection.mutable.StringBuilder, java.lang.String, java.lang.String, java.lang.String);
  Code:
   Stack=5, Locals=5, Args_size=5
   0:	aload_0
   1:	invokeinterface	#129,  1; //InterfaceMethod scala/collection/MapLike.iterator:()Lscala/collection/Iterator;
   6:	new	#131; //class scala/collection/MapLike$$anonfun$addString$1
   9:	dup
   10:	aload_0
   11:	invokespecial	#132; //Method scala/collection/MapLike$$anonfun$addString$1."<init>":(Lscala/collection/MapLike;)V
   14:	invokeinterface	#137,  2; //InterfaceMethod scala/collection/Iterator.map:(Lscala/Function1;)Lscala/collection/Iterator;
   19:	aload_1
   20:	aload_2
   21:	aload_3
   22:	aload	4
   24:	invokeinterface	#140,  5; //InterfaceMethod scala/collection/Iterator.addString:(Lscala/collection/mutable/StringBuilder;Ljava/lang/String;Ljava/lang/String;Ljava/lang/String;)Lscala/collection/mutable/StringBuilder;
   29:	areturn
  LineNumberTable: 
   line 319: 0

  LocalVariableTable: 
   Start  Length  Slot  Name   Signature
   0      30      0    $this       Lscala/collection/MapLike;
   0      30      1    b       Lscala/collection/mutable/StringBuilder;
   0      30      2    start       Ljava/lang/String;
   0      30      3    sep       Ljava/lang/String;
   0      30      4    end       Ljava/lang/String;


public static scala.collection.Map $plus$plus(scala.collection.MapLike, scala.collection.Iterator);
  Code:
   Stack=5, Locals=3, Args_size=2
   0:	aload_0
   1:	invokeinterface	#152,  1; //InterfaceMethod scala/collection/TraversableLike.repr:()Ljava/lang/Object;
   6:	checkcast	#49; //class scala/collection/Map
   9:	astore_2
   10:	aload_1
   11:	aload_2
   12:	new	#154; //class scala/collection/MapLike$$anonfun$$plus$plus$2
   15:	dup
   16:	aload_0
   17:	invokespecial	#155; //Method scala/collection/MapLike$$anonfun$$plus$plus$2."<init>":(Lscala/collection/MapLike;)V
   20:	invokeinterface	#159,  3; //InterfaceMethod scala/collection/Iterator.$div$colon:(Ljava/lang/Object;Lscala/Function2;)Ljava/lang/Object;
   25:	checkcast	#49; //class scala/collection/Map
   28:	areturn
  LineNumberTable: 
   line 305: 0

  LocalVariableTable: 
   Start  Length  Slot  Name   Signature
   0      29      0    $this       Lscala/collection/MapLike;
   0      29      1    iter       Lscala/collection/Iterator;


public static scala.collection.Map $plus$plus(scala.collection.MapLike, scala.collection.Traversable);
  Code:
   Stack=5, Locals=3, Args_size=2
   0:	aload_0
   1:	invokeinterface	#152,  1; //InterfaceMethod scala/collection/TraversableLike.repr:()Ljava/lang/Object;
   6:	checkcast	#49; //class scala/collection/Map
   9:	astore_2
   10:	aload_1
   11:	aload_2
   12:	new	#164; //class scala/collection/MapLike$$anonfun$$plus$plus$1
   15:	dup
   16:	aload_0
   17:	invokespecial	#165; //Method scala/collection/MapLike$$anonfun$$plus$plus$1."<init>":(Lscala/collection/MapLike;)V
   20:	invokeinterface	#166,  3; //InterfaceMethod scala/collection/TraversableLike.$div$colon:(Ljava/lang/Object;Lscala/Function2;)Ljava/lang/Object;
   25:	checkcast	#49; //class scala/collection/Map
   28:	areturn
  LineNumberTable: 
   line 295: 0

  LocalVariableTable: 
   Start  Length  Slot  Name   Signature
   0      29      0    $this       Lscala/collection/MapLike;
   0      29      1    kvs       Lscala/collection/Traversable;


public static scala.collection.Map $plus(scala.collection.MapLike, scala.Tuple2, scala.Tuple2, scala.collection.Seq);
  Code:
   Stack=2, Locals=4, Args_size=4
   0:	aload_0
   1:	aload_1
   2:	invokeinterface	#173,  2; //InterfaceMethod scala/collection/MapLike.$plus:(Lscala/Tuple2;)Lscala/collection/Map;
   7:	aload_2
   8:	invokeinterface	#173,  2; //InterfaceMethod scala/collection/MapLike.$plus:(Lscala/Tuple2;)Lscala/collection/Map;
   13:	aload_3
   14:	invokeinterface	#176,  2; //InterfaceMethod scala/collection/MapLike.$plus$plus:(Lscala/collection/Traversable;)Lscala/collection/Map;
   19:	areturn
  LineNumberTable: 
   line 285: 0

  LocalVariableTable: 
   Start  Length  Slot  Name   Signature
   0      20      0    $this       Lscala/collection/MapLike;
   0      20      1    kv1       Lscala/Tuple2;
   0      20      2    kv2       Lscala/Tuple2;
   0      20      3    kvs       Lscala/collection/Seq;


public static scala.collection.Map updated(scala.collection.MapLike, java.lang.Object, java.lang.Object);
  Code:
   Stack=5, Locals=3, Args_size=3
   0:	aload_0
   1:	new	#184; //class scala/Tuple2
   4:	dup
   5:	aload_1
   6:	aload_2
   7:	invokespecial	#187; //Method scala/Tuple2."<init>":(Ljava/lang/Object;Ljava/lang/Object;)V
   10:	invokeinterface	#173,  2; //InterfaceMethod scala/collection/MapLike.$plus:(Lscala/Tuple2;)Lscala/collection/Map;
   15:	areturn
  LineNumberTable: 
   line 269: 0

  LocalVariableTable: 
   Start  Length  Slot  Name   Signature
   0      16      0    $this       Lscala/collection/MapLike;
   0      16      1    key       Ljava/lang/Object;
   0      16      2    value       Ljava/lang/Object;


public static java.lang.Object mapElements(scala.collection.MapLike, scala.Function1);
  Code:
   Stack=2, Locals=2, Args_size=2
   0:	aload_0
   1:	aload_1
   2:	invokeinterface	#195,  2; //InterfaceMethod scala/collection/MapLike.mapValues:(Lscala/Function1;)Ljava/lang/Object;
   7:	areturn
  LineNumberTable: 
   line 256: 0

  LocalVariableTable: 
   Start  Length  Slot  Name   Signature
   0      8      0    $this       Lscala/collection/MapLike;
   0      8      1    f       Lscala/Function1;

  Deprecated: true

public static java.lang.Object mapValues(scala.collection.MapLike, scala.Function1);
  Code:
   Stack=4, Locals=2, Args_size=2
   0:	new	#200; //class scala/collection/MapLike$$anon$2
   3:	dup
   4:	aload_0
   5:	aload_1
   6:	invokespecial	#203; //Method scala/collection/MapLike$$anon$2."<init>":(Lscala/collection/MapLike;Lscala/Function1;)V
   9:	areturn
  LineNumberTable: 
   line 248: 0

  LocalVariableTable: 
   Start  Length  Slot  Name   Signature
   0      10      0    $this       Lscala/collection/MapLike;
   0      10      1    f$4       Lscala/Function1;


public static java.lang.Object filterKeys(scala.collection.MapLike, scala.Function1);
  Code:
   Stack=4, Locals=2, Args_size=2
   0:	new	#207; //class scala/collection/MapLike$$anon$1
   3:	dup
   4:	aload_0
   5:	aload_1
   6:	invokespecial	#208; //Method scala/collection/MapLike$$anon$1."<init>":(Lscala/collection/MapLike;Lscala/Function1;)V
   9:	areturn
  LineNumberTable: 
   line 233: 0

  LocalVariableTable: 
   Start  Length  Slot  Name   Signature
   0      10      0    $this       Lscala/collection/MapLike;
   0      10      1    p$1       Lscala/Function1;


public static java.lang.Object default(scala.collection.MapLike, java.lang.Object);
  Code:
   Stack=4, Locals=2, Args_size=2
   0:	new	#213; //class java/util/NoSuchElementException
   3:	dup
   4:	new	#215; //class scala/collection/mutable/StringBuilder
   7:	dup
   8:	invokespecial	#218; //Method scala/collection/mutable/StringBuilder."<init>":()V
   11:	ldc	#220; //String key not found: 
   13:	invokevirtual	#224; //Method scala/collection/mutable/StringBuilder.append:(Ljava/lang/Object;)Lscala/collection/mutable/StringBuilder;
   16:	aload_1
   17:	invokevirtual	#224; //Method scala/collection/mutable/StringBuilder.append:(Ljava/lang/Object;)Lscala/collection/mutable/StringBuilder;
   20:	invokevirtual	#225; //Method scala/collection/mutable/StringBuilder.toString:()Ljava/lang/String;
   23:	invokespecial	#226; //Method java/util/NoSuchElementException."<init>":(Ljava/lang/String;)V
   26:	athrow
  LineNumberTable: 
   line 226: 0

  LocalVariableTable: 
   Start  Length  Slot  Name   Signature
   0      27      0    $this       Lscala/collection/MapLike;
   0      27      1    key       Ljava/lang/Object;


public static scala.collection.Iterator values(scala.collection.MapLike);
  Code:
   Stack=1, Locals=1, Args_size=1
   0:	aload_0
   1:	invokeinterface	#231,  1; //InterfaceMethod scala/collection/MapLike.valuesIterator:()Lscala/collection/Iterator;
   6:	areturn
  LineNumberTable: 
   line 215: 0

  LocalVariableTable: 
   Start  Length  Slot  Name   Signature
   0      7      0    $this       Lscala/collection/MapLike;

  Deprecated: true

public static scala.collection.Iterator valuesIterator(scala.collection.MapLike);
  Code:
   Stack=3, Locals=1, Args_size=1
   0:	new	#233; //class scala/collection/MapLike$$anon$4
   3:	dup
   4:	aload_0
   5:	invokespecial	#234; //Method scala/collection/MapLike$$anon$4."<init>":(Lscala/collection/MapLike;)V
   8:	areturn
  LineNumberTable: 
   line 204: 0

  LocalVariableTable: 
   Start  Length  Slot  Name   Signature
   0      9      0    $this       Lscala/collection/MapLike;


public static scala.collection.Iterable valuesIterable(scala.collection.MapLike);
  Code:
   Stack=3, Locals=1, Args_size=1
   0:	new	#238; //class scala/collection/MapLike$DefaultValuesIterable
   3:	dup
   4:	aload_0
   5:	invokespecial	#239; //Method scala/collection/MapLike$DefaultValuesIterable."<init>":(Lscala/collection/MapLike;)V
   8:	areturn
  LineNumberTable: 
   line 190: 0

  LocalVariableTable: 
   Start  Length  Slot  Name   Signature
   0      9      0    $this       Lscala/collection/MapLike;


public static scala.collection.Iterator keys(scala.collection.MapLike);
  Code:
   Stack=1, Locals=1, Args_size=1
   0:	aload_0
   1:	invokeinterface	#243,  1; //InterfaceMethod scala/collection/MapLike.keysIterator:()Lscala/collection/Iterator;
   6:	areturn
  LineNumberTable: 
   line 185: 0

  LocalVariableTable: 
   Start  Length  Slot  Name   Signature
   0      7      0    $this       Lscala/collection/MapLike;

  Deprecated: true

public static scala.collection.Iterator keysIterator(scala.collection.MapLike);
  Code:
   Stack=3, Locals=1, Args_size=1
   0:	new	#245; //class scala/collection/MapLike$$anon$3
   3:	dup
   4:	aload_0
   5:	invokespecial	#246; //Method scala/collection/MapLike$$anon$3."<init>":(Lscala/collection/MapLike;)V
   8:	areturn
  LineNumberTable: 
   line 174: 0

  LocalVariableTable: 
   Start  Length  Slot  Name   Signature
   0      9      0    $this       Lscala/collection/MapLike;


public static scala.collection.Set keySet(scala.collection.MapLike);
  Code:
   Stack=3, Locals=1, Args_size=1
   0:	new	#250; //class scala/collection/MapLike$DefaultKeySet
   3:	dup
   4:	aload_0
   5:	invokespecial	#251; //Method scala/collection/MapLike$DefaultKeySet."<init>":(Lscala/collection/MapLike;)V
   8:	areturn
  LineNumberTable: 
   line 157: 0

  LocalVariableTable: 
   Start  Length  Slot  Name   Signature
   0      9      0    $this       Lscala/collection/MapLike;


public static boolean isDefinedAt(scala.collection.MapLike, java.lang.Object);
  Code:
   Stack=2, Locals=2, Args_size=2
   0:	aload_0
   1:	aload_1
   2:	invokeinterface	#255,  2; //InterfaceMethod scala/collection/MapLike.contains:(Ljava/lang/Object;)Z
   7:	ireturn
  LineNumberTable: 
   line 152: 0

  LocalVariableTable: 
   Start  Length  Slot  Name   Signature
   0      8      0    $this       Lscala/collection/MapLike;
   0      8      1    key       Ljava/lang/Object;


public static boolean contains(scala.collection.MapLike, java.lang.Object);
  Code:
   Stack=3, Locals=3, Args_size=2
   0:	aload_0
   1:	aload_1
   2:	invokeinterface	#259,  2; //InterfaceMethod scala/collection/MapLike.get:(Ljava/lang/Object;)Lscala/Option;
   7:	astore_2
   8:	getstatic	#264; //Field scala/None$.MODULE$:Lscala/None$;
   11:	dup
   12:	ifnonnull	23
   15:	pop
   16:	aload_2
   17:	ifnull	30
   20:	goto	50
   23:	aload_2
   24:	invokevirtual	#266; //Method java/lang/Object.equals:(Ljava/lang/Object;)Z
   27:	ifeq	50
   30:	iconst_1
   31:	ifeq	38
   34:	iconst_0
   35:	goto	62
   38:	new	#65; //class scala/MatchError
   41:	dup
   42:	aload_2
   43:	invokevirtual	#269; //Method scala/Option.toString:()Ljava/lang/String;
   46:	invokespecial	#74; //Method scala/MatchError."<init>":(Ljava/lang/String;)V
   49:	athrow
   50:	aload_2
   51:	instanceof	#271; //class scala/Some
   54:	ifeq	75
   57:	iconst_1
   58:	ifeq	63
   61:	iconst_1
   62:	ireturn
   63:	new	#65; //class scala/MatchError
   66:	dup
   67:	aload_2
   68:	invokevirtual	#269; //Method scala/Option.toString:()Ljava/lang/String;
   71:	invokespecial	#74; //Method scala/MatchError."<init>":(Ljava/lang/String;)V
   74:	athrow
   75:	new	#65; //class scala/MatchError
   78:	dup
   79:	aload_2
   80:	invokevirtual	#269; //Method scala/Option.toString:()Ljava/lang/String;
   83:	invokespecial	#74; //Method scala/MatchError."<init>":(Ljava/lang/String;)V
   86:	athrow
  LineNumberTable: 
   line 140: 0
   line 21: 30
   line 141: 34
   line 140: 38
   line 21: 57
   line 142: 61
   line 140: 62

  LocalVariableTable: 
   Start  Length  Slot  Name   Signature
   0      87      0    $this       Lscala/collection/MapLike;
   0      87      1    key       Ljava/lang/Object;
   8      79      2    temp9       Lscala/Option;


public static java.lang.Object apply(scala.collection.MapLike, java.lang.Object);
  Code:
   Stack=3, Locals=5, Args_size=2
   0:	aload_0
   1:	aload_1
   2:	invokeinterface	#259,  2; //InterfaceMethod scala/collection/MapLike.get:(Ljava/lang/Object;)Lscala/Option;
   7:	astore	4
   9:	getstatic	#264; //Field scala/None$.MODULE$:Lscala/None$;
   12:	dup
   13:	ifnonnull	25
   16:	pop
   17:	aload	4
   19:	ifnull	33
   22:	goto	60
   25:	aload	4
   27:	invokevirtual	#266; //Method java/lang/Object.equals:(Ljava/lang/Object;)Z
   30:	ifeq	60
   33:	iconst_1
   34:	ifeq	47
   37:	aload_0
   38:	aload_1
   39:	invokeinterface	#277,  2; //InterfaceMethod scala/collection/MapLike.default:(Ljava/lang/Object;)Ljava/lang/Object;
   44:	goto	84
   47:	new	#65; //class scala/MatchError
   50:	dup
   51:	aload	4
   53:	invokevirtual	#269; //Method scala/Option.toString:()Ljava/lang/String;
   56:	invokespecial	#74; //Method scala/MatchError."<init>":(Ljava/lang/String;)V
   59:	athrow
   60:	aload	4
   62:	instanceof	#271; //class scala/Some
   65:	ifeq	98
   68:	aload	4
   70:	checkcast	#271; //class scala/Some
   73:	astore_2
   74:	aload_2
   75:	getfield	#280; //Field scala/Some.x:Ljava/lang/Object;
   78:	astore_3
   79:	iconst_1
   80:	ifeq	85
   83:	aload_3
   84:	areturn
   85:	new	#65; //class scala/MatchError
   88:	dup
   89:	aload	4
   91:	invokevirtual	#269; //Method scala/Option.toString:()Ljava/lang/String;
   94:	invokespecial	#74; //Method scala/MatchError."<init>":(Ljava/lang/String;)V
   97:	athrow
   98:	new	#65; //class scala/MatchError
   101:	dup
   102:	aload	4
   104:	invokevirtual	#269; //Method scala/Option.toString:()Ljava/lang/String;
   107:	invokespecial	#74; //Method scala/MatchError."<init>":(Ljava/lang/String;)V
   110:	athrow
  LineNumberTable: 
   line 130: 0
   line 21: 33
   line 131: 37
   line 130: 47
   line 21: 79
   line 132: 83
   line 130: 84

  LocalVariableTable: 
   Start  Length  Slot  Name   Signature
   0      111      0    $this       Lscala/collection/MapLike;
   0      111      1    key       Ljava/lang/Object;
   74      10      2    temp7       Lscala/Some;
   85      13      2    temp7       Lscala/Some;
   79      5      3    temp8       Ljava/lang/Object;
   85      13      3    temp8       Ljava/lang/Object;
   9      102      4    temp5       Lscala/Option;


public static java.lang.Object getOrElse(scala.collection.MapLike, java.lang.Object, scala.Function0);
  Code:
   Stack=3, Locals=6, Args_size=3
   0:	aload_0
   1:	aload_1
   2:	invokeinterface	#259,  2; //InterfaceMethod scala/collection/MapLike.get:(Ljava/lang/Object;)Lscala/Option;
   7:	astore	5
   9:	aload	5
   11:	instanceof	#271; //class scala/Some
   14:	ifeq	51
   17:	aload	5
   19:	checkcast	#271; //class scala/Some
   22:	astore_3
   23:	aload_3
   24:	getfield	#280; //Field scala/Some.x:Ljava/lang/Object;
   27:	astore	4
   29:	iconst_1
   30:	ifeq	38
   33:	aload	4
   35:	goto	85
   38:	new	#65; //class scala/MatchError
   41:	dup
   42:	aload	5
   44:	invokevirtual	#269; //Method scala/Option.toString:()Ljava/lang/String;
   47:	invokespecial	#74; //Method scala/MatchError."<init>":(Ljava/lang/String;)V
   50:	athrow
   51:	getstatic	#264; //Field scala/None$.MODULE$:Lscala/None$;
   54:	dup
   55:	ifnonnull	67
   58:	pop
   59:	aload	5
   61:	ifnull	75
   64:	goto	99
   67:	aload	5
   69:	invokevirtual	#266; //Method java/lang/Object.equals:(Ljava/lang/Object;)Z
   72:	ifeq	99
   75:	iconst_1
   76:	ifeq	86
   79:	aload_2
   80:	invokeinterface	#290,  1; //InterfaceMethod scala/Function0.apply:()Ljava/lang/Object;
   85:	areturn
   86:	new	#65; //class scala/MatchError
   89:	dup
   90:	aload	5
   92:	invokevirtual	#269; //Method scala/Option.toString:()Ljava/lang/String;
   95:	invokespecial	#74; //Method scala/MatchError."<init>":(Ljava/lang/String;)V
   98:	athrow
   99:	new	#65; //class scala/MatchError
   102:	dup
   103:	aload	5
   105:	invokevirtual	#269; //Method scala/Option.toString:()Ljava/lang/String;
   108:	invokespecial	#74; //Method scala/MatchError."<init>":(Ljava/lang/String;)V
   111:	athrow
  LineNumberTable: 
   line 116: 0
   line 21: 29
   line 117: 33
   line 116: 38
   line 21: 75
   line 118: 79
   line 116: 85

  LocalVariableTable: 
   Start  Length  Slot  Name   Signature
   0      112      0    $this       Lscala/collection/MapLike;
   0      112      1    key       Ljava/lang/Object;
   0      112      2    default       Lscala/Function0;
   23      28      3    temp2       Lscala/Some;
   29      22      4    temp3       Ljava/lang/Object;
   9      103      5    temp1       Lscala/Option;


public static boolean isEmpty(scala.collection.MapLike);
  Code:
   Stack=2, Locals=1, Args_size=1
   0:	aload_0
   1:	invokeinterface	#59,  1; //InterfaceMethod scala/collection/TraversableLike.size:()I
   6:	iconst_0
   7:	if_icmpne	14
   10:	iconst_1
   11:	goto	15
   14:	iconst_0
   15:	ireturn
  LineNumberTable: 
   line 105: 0

  LocalVariableTable: 
   Start  Length  Slot  Name   Signature
   0      16      0    $this       Lscala/collection/MapLike;


public static scala.collection.mutable.Builder newBuilder(scala.collection.MapLike);
  Code:
   Stack=3, Locals=1, Args_size=1
   0:	new	#300; //class scala/collection/mutable/MapBuilder
   3:	dup
   4:	aload_0
   5:	invokeinterface	#304,  1; //InterfaceMethod scala/collection/MapLike.empty:()Lscala/collection/MapLike;
   10:	checkcast	#49; //class scala/collection/Map
   13:	invokespecial	#307; //Method scala/collection/mutable/MapBuilder."<init>":(Lscala/collection/Map;)V
   16:	areturn
  LineNumberTable: 
   line 70: 0

  LocalVariableTable: 
   Start  Length  Slot  Name   Signature
   0      17      0    $this       Lscala/collection/MapLike;


}

