Compiled from "MapLike.scala"
public final class scala.collection.MapLike$$anonfun$liftedTree1$1$1 extends scala.runtime.AbstractFunction1 implements java.io.Serializable
  SourceFile: "MapLike.scala"
  Scala: length = 0x
   
  InnerClass: 
   public final $anonfun$liftedTree1$1$1=class scala/collection/MapLike$$anonfun$liftedTree1$1$1 of class scala/collection/MapLike
  minor version: 0
  major version: 49
  Constant pool:
Asciz	SourceFile;
Asciz	MapLike.scala;
Asciz	<clinit>;
Asciz	()V;
Asciz	Code;
Asciz	serialVersionUID;
Asciz	J;
Asciz	scala/collection/MapLike$$anonfun$liftedTree1$1$1;
class	scala/collection/MapLike$$anonfun$liftedTree1$1$1
NameAndType	serialVersionUID:J
Field	scala/collection/MapLike$$anonfun$liftedTree1$1$1.serialVersionUID:J
Asciz	that$1;
Asciz	Lscala/collection/Map;;
Asciz	apply;
Asciz	(Lscala/Tuple2;)Z;
Asciz	LineNumberTable;
Asciz	scala/Tuple2;
class	scala/Tuple2
Asciz	_1;
Asciz	()Ljava/lang/Object;;
NameAndType	_1:()Ljava/lang/Object;
Method	scala/Tuple2._1:()Ljava/lang/Object;
NameAndType	that$1:Lscala/collection/Map;
Field	scala/collection/MapLike$$anonfun$liftedTree1$1$1.that$1:Lscala/collection/Map;
Asciz	scala/collection/MapLike;
class	scala/collection/MapLike
Asciz	get;
Asciz	(Ljava/lang/Object;)Lscala/Option;;
NameAndType	get:(Ljava/lang/Object;)Lscala/Option;
InterfaceMethod	scala/collection/MapLike.get:(Ljava/lang/Object;)Lscala/Option;
Asciz	scala/Some;
class	scala/Some
Asciz	_2;
NameAndType	_2:()Ljava/lang/Object;
Method	scala/Tuple2._2:()Ljava/lang/Object;
Asciz	x;
Asciz	Ljava/lang/Object;;
NameAndType	x:Ljava/lang/Object;
Field	scala/Some.x:Ljava/lang/Object;
Asciz	java/lang/Number;
class	java/lang/Number
Asciz	java/lang/Character;
class	java/lang/Character
Asciz	scala/runtime/BoxesRunTime;
class	scala/runtime/BoxesRunTime
Asciz	equals2;
Asciz	(Ljava/lang/Object;Ljava/lang/Object;)Z;
NameAndType	equals2:(Ljava/lang/Object;Ljava/lang/Object;)Z
Method	scala/runtime/BoxesRunTime.equals2:(Ljava/lang/Object;Ljava/lang/Object;)Z
Asciz	java/lang/Object;
class	java/lang/Object
Asciz	equals;
Asciz	(Ljava/lang/Object;)Z;
NameAndType	equals:(Ljava/lang/Object;)Z
Method	java/lang/Object.equals:(Ljava/lang/Object;)Z
Asciz	scala/MatchError;
class	scala/MatchError
Asciz	toString;
Asciz	()Ljava/lang/String;;
NameAndType	toString:()Ljava/lang/String;
Method	scala/Tuple2.toString:()Ljava/lang/String;
Asciz	<init>;
Asciz	(Ljava/lang/String;)V;
NameAndType	"<init>":(Ljava/lang/String;)V
Method	scala/MatchError."<init>":(Ljava/lang/String;)V
Asciz	this;
Asciz	Lscala/collection/MapLike$$anonfun$liftedTree1$1$1;;
Asciz	temp42;
Asciz	temp37;
Asciz	Lscala/Option;;
Asciz	$inlThis0;
Asciz	x0;
Asciz	y0;
Asciz	LocalVariableTable;
Asciz	(Lscala/Tuple2<TA;TB;>;)Z;
Asciz	Signature;
Asciz	(Ljava/lang/Object;)Ljava/lang/Object;;
NameAndType	apply:(Lscala/Tuple2;)Z
Method	scala/collection/MapLike$$anonfun$liftedTree1$1$1.apply:(Lscala/Tuple2;)Z
Asciz	boxToBoolean;
Asciz	(Z)Ljava/lang/Boolean;;
NameAndType	boxToBoolean:(Z)Ljava/lang/Boolean;
Method	scala/runtime/BoxesRunTime.boxToBoolean:(Z)Ljava/lang/Boolean;
Asciz	v1;
Asciz	(Lscala/collection/MapLike;Lscala/collection/Map;)V;
Asciz	scala/runtime/AbstractFunction1;
class	scala/runtime/AbstractFunction1
NameAndType	"<init>":()V
Method	scala/runtime/AbstractFunction1."<init>":()V
Asciz	$outer;
Asciz	Lscala/collection/MapLike;;
Asciz	(Lscala/collection/MapLike<TA;TB;TThis;>;)V;
Asciz	Scala;
Asciz	InnerClasses;
Asciz	$anonfun$liftedTree1$1$1;
Asciz	java/io/Serializable;
class	java/io/Serializable

{
public static final long serialVersionUID;
  Signature: J

public final scala.collection.Map that$1;
  Signature: Lscala/collection/Map;

public static {};
  Signature: ()V
  Code:
   Stack=2, Locals=0, Args_size=0
	lconst_0
	putstatic	Field serialVersionUID:J
	return
  Labels:

public final boolean apply(scala.Tuple2);
  Signature: (Lscala/Tuple2;)Z
  Code:
   Stack=3, Locals=7, Args_size=2
	aload_1
	ifnull	l1 // new
	aload_1
	invokevirtual	Method scala/Tuple2._1:()Ljava/lang/Object;
	astore_2
	aload_0
	getfield	Field that$1:Lscala/collection/Map;
	aload_2
	invokeinterface	InterfaceMethod scala/collection/MapLike.get:(Ljava/lang/Object;)Lscala/Option;
	astore_3
	aload_3
	instanceof	class scala/Some
	ifeq	l2 // iconst_0
	aload_1
	invokevirtual	Method scala/Tuple2._2:()Ljava/lang/Object;
	aload_3
	checkcast	class scala/Some
	astore	4
	aload	4
	getfield	Field scala/Some.x:Ljava/lang/Object;
	astore	6
	astore	5
	aload	5
	aload	6
	if_acmpne	l3 // aload
	iconst_1
	goto	l4 // ifeq
l3	aload	5
	ifnonnull	l5 // aload
	iconst_0
	goto	l4 // ifeq
l5	aload	5
	instanceof	class java/lang/Number
	ifne	l6 // aload
	aload	5
	instanceof	class java/lang/Character
	ifeq	l7 // aload
l6	aload	5
	aload	6
	invokestatic	Method scala/runtime/BoxesRunTime.equals2:(Ljava/lang/Object;Ljava/lang/Object;)Z
	goto	l4 // ifeq
l7	aload	5
	aload	6
	invokevirtual	Method java/lang/Object.equals:(Ljava/lang/Object;)Z
l4	ifeq	l8 // iconst_0
	iconst_1
	goto	l9 // ireturn
l8	iconst_0
	goto	l9 // ireturn
l2	iconst_0
l9	ireturn
l1	new	class scala/MatchError
	dup
	aload_1
	invokevirtual	Method scala/Tuple2.toString:()Ljava/lang/String;
	invokespecial	Method scala/MatchError."<init>":(Ljava/lang/String;)V
	athrow
  Labels:
   	l3 = 57 // aload
   	l5 = 66 // aload
   	l6 = 82 // aload
   	l7 = 92 // aload
   	l4 = 99 // ifeq
   	l8 = 106 // iconst_0
   	l2 = 110 // iconst_0
   	l9 = 111 // ireturn
   	l1 = 112 // new
  LocalVariableTable: 
   Start  Length  Slot  Name   Signature
   0      124      0    this       Lscala/collection/MapLike$$anonfun$liftedTree1$1$1;
   9      102      2    temp42       Ljava/lang/Object;
   20      91      3    temp37       Lscala/Option;
   53      49      4    $inlThis0       Ljava/lang/Object;
   53      49      5    x0       Ljava/lang/Object;
   53      49      6    y0       Ljava/lang/Object;

  Signature: length = 0x2
   00 4B 

public final java.lang.Object apply(java.lang.Object);
  Signature: (Ljava/lang/Object;)Ljava/lang/Object;
  Code:
   Stack=2, Locals=3, Args_size=2
	aload_0
	aload_1
	checkcast	class scala/Tuple2
	invokevirtual	Method apply:(Lscala/Tuple2;)Z
	istore_2
	iload_2
	invokestatic	Method scala/runtime/BoxesRunTime.boxToBoolean:(Z)Ljava/lang/Boolean;
	areturn
  Labels:
  LocalVariableTable: 
   Start  Length  Slot  Name   Signature
   0      14      0    this       Lscala/collection/MapLike$$anonfun$liftedTree1$1$1;
   0      14      1    v1       Ljava/lang/Object;


public scala.collection.MapLike$$anonfun$liftedTree1$1$1(scala.collection.MapLike, scala.collection.Map);
  Signature: (Lscala/collection/MapLike;Lscala/collection/Map;)V
  Code:
   Stack=2, Locals=3, Args_size=3
	aload_0
	aload_2
	putfield	Field that$1:Lscala/collection/Map;
	aload_0
	invokespecial	Method scala/runtime/AbstractFunction1."<init>":()V
	return
  Labels:
  LocalVariableTable: 
   Start  Length  Slot  Name   Signature
   0      10      0    this       Lscala/collection/MapLike$$anonfun$liftedTree1$1$1;
   0      10      1    $outer       Lscala/collection/MapLike;

  Signature: length = 0x2
   00 5C 

}

