Compiled from "MapLike.scala"
public final class scala.collection.MapLike$$anon$2$$anonfun$foreach$7 extends java.lang.Object implements scala.Function1,scala.ScalaObject,java.io.Serializable
  SourceFile: "MapLike.scala"
  Scala: length = 0x
   
  InnerClass: 
   public final $anon$2=class scala/collection/MapLike$$anon$2 of class scala/collection/MapLike
   public final $anonfun$foreach$7=class scala/collection/MapLike$$anon$2$$anonfun$foreach$7 of class scala/collection/MapLike$$anon$2
  minor version: 0
  major version: 49
  Constant pool:
Asciz	SourceFile;
Asciz	MapLike.scala;
Asciz	<clinit>;
Asciz	()V;
Asciz	Code;
Asciz	serialVersionUID;
Asciz	J;
Asciz	scala/collection/MapLike$$anon$2$$anonfun$foreach$7;
class	scala/collection/MapLike$$anon$2$$anonfun$foreach$7
NameAndType	serialVersionUID:J
Field	scala/collection/MapLike$$anon$2$$anonfun$foreach$7.serialVersionUID:J
Asciz	g$1;
Asciz	Lscala/Function1;;
Asciz	$outer;
Asciz	Lscala/collection/MapLike$$anon$2;;
Asciz	<init>;
Asciz	(Lscala/collection/MapLike$$anon$2;Lscala/Function1;)V;
Asciz	LineNumberTable;
Asciz	java/lang/NullPointerException;
class	java/lang/NullPointerException
NameAndType	"<init>":()V
Method	java/lang/NullPointerException."<init>":()V
NameAndType	$outer:Lscala/collection/MapLike$$anon$2;
Field	scala/collection/MapLike$$anon$2$$anonfun$foreach$7.$outer:Lscala/collection/MapLike$$anon$2;
NameAndType	g$1:Lscala/Function1;
Field	scala/collection/MapLike$$anon$2$$anonfun$foreach$7.g$1:Lscala/Function1;
Asciz	java/lang/Object;
class	java/lang/Object
Method	java/lang/Object."<init>":()V
Asciz	scala/Function1$class;
class	scala/Function1$class
Asciz	$init$;
Asciz	(Lscala/Function1;)V;
NameAndType	$init$:(Lscala/Function1;)V
Method	scala/Function1$class.$init$:(Lscala/Function1;)V
Asciz	this;
Asciz	Lscala/collection/MapLike$$anon$2$$anonfun$foreach$7;;
Asciz	LocalVariableTable;
Asciz	(Lscala/collection/MapLike<TA;TB;TThis;>.$anon$2;)V;
Asciz	Signature;
Asciz	apply;
Asciz	(Ljava/lang/Object;)Ljava/lang/Object;;
Asciz	scala/Tuple2;
class	scala/Tuple2
Asciz	(Lscala/Tuple2;)Ljava/lang/Object;;
NameAndType	apply:(Lscala/Tuple2;)Ljava/lang/Object;
Method	scala/collection/MapLike$$anon$2$$anonfun$foreach$7.apply:(Lscala/Tuple2;)Ljava/lang/Object;
Asciz	v1;
Asciz	Ljava/lang/Object;;
Asciz	_1;
Asciz	()Ljava/lang/Object;;
NameAndType	_1:()Ljava/lang/Object;
Method	scala/Tuple2._1:()Ljava/lang/Object;
Asciz	_2;
NameAndType	_2:()Ljava/lang/Object;
Method	scala/Tuple2._2:()Ljava/lang/Object;
Asciz	scala/collection/MapLike$$anon$2;
class	scala/collection/MapLike$$anon$2
Asciz	f$4;
NameAndType	f$4:Lscala/Function1;
Field	scala/collection/MapLike$$anon$2.f$4:Lscala/Function1;
Asciz	scala/Function1;
class	scala/Function1
NameAndType	apply:(Ljava/lang/Object;)Ljava/lang/Object;
InterfaceMethod	scala/Function1.apply:(Ljava/lang/Object;)Ljava/lang/Object;
Asciz	(Ljava/lang/Object;Ljava/lang/Object;)V;
NameAndType	"<init>":(Ljava/lang/Object;Ljava/lang/Object;)V
Method	scala/Tuple2."<init>":(Ljava/lang/Object;Ljava/lang/Object;)V
Asciz	scala/MatchError;
class	scala/MatchError
Asciz	toString;
Asciz	()Ljava/lang/String;;
NameAndType	toString:()Ljava/lang/String;
Method	scala/Tuple2.toString:()Ljava/lang/String;
Asciz	(Ljava/lang/String;)V;
NameAndType	"<init>":(Ljava/lang/String;)V
Method	scala/MatchError."<init>":(Ljava/lang/String;)V
Asciz	temp29;
Asciz	temp30;
Asciz	(Lscala/Tuple2<TA;TB;>;)TD;;
Asciz	andThen;
Asciz	(Lscala/Function1;)Lscala/Function1;;
Asciz	(Lscala/Function1;Lscala/Function1;)Lscala/Function1;;
NameAndType	andThen:(Lscala/Function1;Lscala/Function1;)Lscala/Function1;
Method	scala/Function1$class.andThen:(Lscala/Function1;Lscala/Function1;)Lscala/Function1;
Asciz	g;
Asciz	compose;
NameAndType	compose:(Lscala/Function1;Lscala/Function1;)Lscala/Function1;
Method	scala/Function1$class.compose:(Lscala/Function1;Lscala/Function1;)Lscala/Function1;
Asciz	(Lscala/Function1;)Ljava/lang/String;;
NameAndType	toString:(Lscala/Function1;)Ljava/lang/String;
Method	scala/Function1$class.toString:(Lscala/Function1;)Ljava/lang/String;
Asciz	Scala;
Asciz	InnerClasses;
Asciz	scala/collection/MapLike;
class	scala/collection/MapLike
Asciz	$anon$2;
Asciz	$anonfun$foreach$7;
Asciz	scala/ScalaObject;
class	scala/ScalaObject
Asciz	java/io/Serializable;
class	java/io/Serializable

{
public static final long serialVersionUID;
  Signature: J

private final scala.Function1 g$1;
  Signature: Lscala/Function1;

private final scala.collection.MapLike$$anon$2 $outer;
  Signature: Lscala/collection/MapLike$$anon$2;

public static {};
  Signature: ()V
  Code:
   Stack=2, Locals=0, Args_size=0
	lconst_0
	putstatic	Field serialVersionUID:J
	return
  Labels:

public scala.collection.MapLike$$anon$2$$anonfun$foreach$7(scala.collection.MapLike$$anon$2, scala.Function1);
  Signature: (Lscala/collection/MapLike$$anon$2;Lscala/Function1;)V
  Code:
   Stack=2, Locals=3, Args_size=3
	aload_1
	ifnonnull	l1 // aload_0
	new	class java/lang/NullPointerException
	dup
	invokespecial	Method java/lang/NullPointerException."<init>":()V
	athrow
l1	aload_0
	aload_1
	putfield	Field $outer:Lscala/collection/MapLike$$anon$2;
	aload_0
	aload_2
	putfield	Field g$1:Lscala/Function1;
	aload_0
	invokespecial	Method java/lang/Object."<init>":()V
	aload_0
	invokestatic	Method scala/Function1$class.$init$:(Lscala/Function1;)V
	return
  Labels:
   	l1 = 12 // aload_0
  LocalVariableTable: 
   Start  Length  Slot  Name   Signature
   0      31      0    this       Lscala/collection/MapLike$$anon$2$$anonfun$foreach$7;
   0      31      1    $outer       Lscala/collection/MapLike$$anon$2;

  Signature: length = 0x2
   00 27 

public final java.lang.Object apply(java.lang.Object);
  Signature: (Ljava/lang/Object;)Ljava/lang/Object;
  Code:
   Stack=2, Locals=3, Args_size=2
	aload_0
	getfield	Field $outer:Lscala/collection/MapLike$$anon$2;
	astore_2
	aload_0
	aload_1
	checkcast	class scala/Tuple2
	invokevirtual	Method apply:(Lscala/Tuple2;)Ljava/lang/Object;
	areturn
  Labels:
  LocalVariableTable: 
   Start  Length  Slot  Name   Signature
   0      14      0    this       Lscala/collection/MapLike$$anon$2$$anonfun$foreach$7;
   5      9      1    v1       Ljava/lang/Object;


public final java.lang.Object apply(scala.Tuple2);
  Signature: (Lscala/Tuple2;)Ljava/lang/Object;
  Code:
   Stack=6, Locals=5, Args_size=2
	aload_0
	getfield	Field $outer:Lscala/collection/MapLike$$anon$2;
	astore	4
	aload_1
	ifnull	l1 // new
	aload_1
	invokevirtual	Method scala/Tuple2._1:()Ljava/lang/Object;
	astore_2
	aload_1
	invokevirtual	Method scala/Tuple2._2:()Ljava/lang/Object;
	astore_3
	iconst_1
	ifeq	l2 // new
	aload_0
	getfield	Field g$1:Lscala/Function1;
	new	class scala/Tuple2
	dup
	aload_2
	aload_0
	getfield	Field $outer:Lscala/collection/MapLike$$anon$2;
	getfield	Field scala/collection/MapLike$$anon$2.f$4:Lscala/Function1;
	aload_3
	invokeinterface	InterfaceMethod scala/Function1.apply:(Ljava/lang/Object;)Ljava/lang/Object;
	invokespecial	Method scala/Tuple2."<init>":(Ljava/lang/Object;Ljava/lang/Object;)V
	invokeinterface	InterfaceMethod scala/Function1.apply:(Ljava/lang/Object;)Ljava/lang/Object;
	areturn
l2	new	class scala/MatchError
	dup
	aload_1
	invokevirtual	Method scala/Tuple2.toString:()Ljava/lang/String;
	invokespecial	Method scala/MatchError."<init>":(Ljava/lang/String;)V
	athrow
l1	new	class scala/MatchError
	dup
	aload_1
	invokevirtual	Method scala/Tuple2.toString:()Ljava/lang/String;
	invokespecial	Method scala/MatchError."<init>":(Ljava/lang/String;)V
	athrow
  Labels:
   	l2 = 55 // new
   	l1 = 67 // new
  LocalVariableTable: 
   Start  Length  Slot  Name   Signature
   0      79      0    this       Lscala/collection/MapLike$$anon$2$$anonfun$foreach$7;
   15      52      2    temp29       Ljava/lang/Object;
   20      47      3    temp30       Ljava/lang/Object;

  Signature: length = 0x2
   00 50 

public scala.Function1 andThen(scala.Function1);
  Signature: (Lscala/Function1;)Lscala/Function1;
  Code:
   Stack=2, Locals=2, Args_size=2
	aload_0
	aload_1
	invokestatic	Method scala/Function1$class.andThen:(Lscala/Function1;Lscala/Function1;)Lscala/Function1;
	areturn
  Labels:
  LocalVariableTable: 
   Start  Length  Slot  Name   Signature
   0      6      0    this       Lscala/collection/MapLike$$anon$2$$anonfun$foreach$7;
   0      6      1    g       Lscala/Function1;


public scala.Function1 compose(scala.Function1);
  Signature: (Lscala/Function1;)Lscala/Function1;
  Code:
   Stack=2, Locals=2, Args_size=2
	aload_0
	aload_1
	invokestatic	Method scala/Function1$class.compose:(Lscala/Function1;Lscala/Function1;)Lscala/Function1;
	areturn
  Labels:
  LocalVariableTable: 
   Start  Length  Slot  Name   Signature
   0      6      0    this       Lscala/collection/MapLike$$anon$2$$anonfun$foreach$7;
   0      6      1    g       Lscala/Function1;


public java.lang.String toString();
  Signature: ()Ljava/lang/String;
  Code:
   Stack=1, Locals=1, Args_size=1
	aload_0
	invokestatic	Method scala/Function1$class.toString:(Lscala/Function1;)Ljava/lang/String;
	areturn
  Labels:

}

