Compiled from "MapLike.scala"
public final class scala.collection.MapLike$$anon$2$$anonfun$iterator$2 extends scala.runtime.AbstractFunction1 implements java.io.Serializable
  SourceFile: "MapLike.scala"
  Scala: length = 0x
   
  InnerClass: 
   public final $anon$2=class scala/collection/MapLike$$anon$2 of class scala/collection/MapLike
   public final $anonfun$iterator$2=class scala/collection/MapLike$$anon$2$$anonfun$iterator$2 of class scala/collection/MapLike$$anon$2
  minor version: 0
  major version: 49
  Constant pool:
Asciz	SourceFile;
Asciz	MapLike.scala;
Asciz	<clinit>;
Asciz	()V;
Asciz	Code;
Asciz	serialVersionUID;
Asciz	J;
Asciz	scala/collection/MapLike$$anon$2$$anonfun$iterator$2;
class	scala/collection/MapLike$$anon$2$$anonfun$iterator$2
NameAndType	serialVersionUID:J
Field	scala/collection/MapLike$$anon$2$$anonfun$iterator$2.serialVersionUID:J
Asciz	$outer;
Asciz	Lscala/collection/MapLike$$anon$2;;
Asciz	<init>;
Asciz	(Lscala/collection/MapLike$$anon$2;)V;
Asciz	LineNumberTable;
Asciz	java/lang/NullPointerException;
class	java/lang/NullPointerException
NameAndType	"<init>":()V
Method	java/lang/NullPointerException."<init>":()V
NameAndType	$outer:Lscala/collection/MapLike$$anon$2;
Field	scala/collection/MapLike$$anon$2$$anonfun$iterator$2.$outer:Lscala/collection/MapLike$$anon$2;
Asciz	scala/runtime/AbstractFunction1;
class	scala/runtime/AbstractFunction1
Method	scala/runtime/AbstractFunction1."<init>":()V
Asciz	this;
Asciz	Lscala/collection/MapLike$$anon$2$$anonfun$iterator$2;;
Asciz	LocalVariableTable;
Asciz	(Lscala/collection/MapLike<TA;TB;TThis;>.$anon$2;)V;
Asciz	Signature;
Asciz	apply;
Asciz	(Ljava/lang/Object;)Ljava/lang/Object;;
Asciz	scala/Tuple2;
class	scala/Tuple2
Asciz	(Lscala/Tuple2;)Lscala/Tuple2;;
NameAndType	apply:(Lscala/Tuple2;)Lscala/Tuple2;
Method	scala/collection/MapLike$$anon$2$$anonfun$iterator$2.apply:(Lscala/Tuple2;)Lscala/Tuple2;
Asciz	v1;
Asciz	Ljava/lang/Object;;
Asciz	_1;
Asciz	()Ljava/lang/Object;;
NameAndType	_1:()Ljava/lang/Object;
Method	scala/Tuple2._1:()Ljava/lang/Object;
Asciz	_2;
NameAndType	_2:()Ljava/lang/Object;
Method	scala/Tuple2._2:()Ljava/lang/Object;
Asciz	scala/collection/MapLike$$anon$2;
class	scala/collection/MapLike$$anon$2
Asciz	f$4;
Asciz	Lscala/Function1;;
NameAndType	f$4:Lscala/Function1;
Field	scala/collection/MapLike$$anon$2.f$4:Lscala/Function1;
Asciz	scala/Function1;
class	scala/Function1
NameAndType	apply:(Ljava/lang/Object;)Ljava/lang/Object;
InterfaceMethod	scala/Function1.apply:(Ljava/lang/Object;)Ljava/lang/Object;
Asciz	(Ljava/lang/Object;Ljava/lang/Object;)V;
NameAndType	"<init>":(Ljava/lang/Object;Ljava/lang/Object;)V
Method	scala/Tuple2."<init>":(Ljava/lang/Object;Ljava/lang/Object;)V
Asciz	scala/MatchError;
class	scala/MatchError
Asciz	toString;
Asciz	()Ljava/lang/String;;
NameAndType	toString:()Ljava/lang/String;
Method	scala/Tuple2.toString:()Ljava/lang/String;
Asciz	(Ljava/lang/String;)V;
NameAndType	"<init>":(Ljava/lang/String;)V
Method	scala/MatchError."<init>":(Ljava/lang/String;)V
Asciz	temp32;
Asciz	temp33;
Asciz	(Lscala/Tuple2<TA;TB;>;)Lscala/Tuple2<TA;TC;>;;
Asciz	Scala;
Asciz	InnerClasses;
Asciz	scala/collection/MapLike;
class	scala/collection/MapLike
Asciz	$anon$2;
Asciz	$anonfun$iterator$2;
Asciz	java/io/Serializable;
class	java/io/Serializable

{
public static final long serialVersionUID;
  Signature: J

private final scala.collection.MapLike$$anon$2 $outer;
  Signature: Lscala/collection/MapLike$$anon$2;

public static {};
  Signature: ()V
  Code:
   Stack=2, Locals=0, Args_size=0
	lconst_0
	putstatic	Field serialVersionUID:J
	return
  Labels:

public scala.collection.MapLike$$anon$2$$anonfun$iterator$2(scala.collection.MapLike$$anon$2);
  Signature: (Lscala/collection/MapLike$$anon$2;)V
  Code:
   Stack=2, Locals=2, Args_size=2
	aload_1
	ifnonnull	l1 // aload_0
	new	class java/lang/NullPointerException
	dup
	invokespecial	Method java/lang/NullPointerException."<init>":()V
	athrow
l1	aload_0
	aload_1
	putfield	Field $outer:Lscala/collection/MapLike$$anon$2;
	aload_0
	invokespecial	Method scala/runtime/AbstractFunction1."<init>":()V
	return
  Labels:
   	l1 = 12 // aload_0
  LocalVariableTable: 
   Start  Length  Slot  Name   Signature
   0      22      0    this       Lscala/collection/MapLike$$anon$2$$anonfun$iterator$2;
   0      22      1    $outer       Lscala/collection/MapLike$$anon$2;

  Signature: length = 0x2
   00 1D 

public final java.lang.Object apply(java.lang.Object);
  Signature: (Ljava/lang/Object;)Ljava/lang/Object;
  Code:
   Stack=2, Locals=2, Args_size=2
	aload_0
	aload_1
	checkcast	class scala/Tuple2
	invokevirtual	Method apply:(Lscala/Tuple2;)Lscala/Tuple2;
	areturn
  Labels:
  LocalVariableTable: 
   Start  Length  Slot  Name   Signature
   0      9      0    this       Lscala/collection/MapLike$$anon$2$$anonfun$iterator$2;
   0      9      1    v1       Ljava/lang/Object;


public final scala.Tuple2 apply(scala.Tuple2);
  Signature: (Lscala/Tuple2;)Lscala/Tuple2;
  Code:
   Stack=5, Locals=4, Args_size=2
	aload_1
	ifnull	l1 // new
	aload_1
	invokevirtual	Method scala/Tuple2._1:()Ljava/lang/Object;
	astore_2
	aload_1
	invokevirtual	Method scala/Tuple2._2:()Ljava/lang/Object;
	astore_3
	iconst_1
	ifeq	l2 // new
	new	class scala/Tuple2
	dup
	aload_2
	aload_0
	getfield	Field $outer:Lscala/collection/MapLike$$anon$2;
	getfield	Field scala/collection/MapLike$$anon$2.f$4:Lscala/Function1;
	aload_3
	invokeinterface	InterfaceMethod scala/Function1.apply:(Ljava/lang/Object;)Ljava/lang/Object;
	invokespecial	Method scala/Tuple2."<init>":(Ljava/lang/Object;Ljava/lang/Object;)V
	areturn
l2	new	class scala/MatchError
	dup
	aload_1
	invokevirtual	Method scala/Tuple2.toString:()Ljava/lang/String;
	invokespecial	Method scala/MatchError."<init>":(Ljava/lang/String;)V
	athrow
l1	new	class scala/MatchError
	dup
	aload_1
	invokevirtual	Method scala/Tuple2.toString:()Ljava/lang/String;
	invokespecial	Method scala/MatchError."<init>":(Ljava/lang/String;)V
	athrow
  Labels:
   	l2 = 40 // new
   	l1 = 52 // new
  LocalVariableTable: 
   Start  Length  Slot  Name   Signature
   0      64      0    this       Lscala/collection/MapLike$$anon$2$$anonfun$iterator$2;
   9      43      2    temp32       Ljava/lang/Object;
   14      38      3    temp33       Ljava/lang/Object;

  Signature: length = 0x2
   00 47 

}

