Compiled from "MapLike.scala"
public final class scala.collection.MapLike$DefaultValuesIterable$$anonfun$foreach$4 extends scala.runtime.AbstractFunction1 implements java.io.Serializable
  SourceFile: "MapLike.scala"
  Scala: length = 0x
   
  InnerClass: 
   public DefaultValuesIterable=class scala/collection/MapLike$DefaultValuesIterable of class scala/collection/MapLike
   public final $anonfun$foreach$4=class scala/collection/MapLike$DefaultValuesIterable$$anonfun$foreach$4 of class scala/collection/MapLike$DefaultValuesIterable
  minor version: 0
  major version: 49
  Constant pool:
Asciz	SourceFile;
Asciz	MapLike.scala;
Asciz	<clinit>;
Asciz	()V;
Asciz	Code;
Asciz	serialVersionUID;
Asciz	J;
Asciz	scala/collection/MapLike$DefaultValuesIterable$$anonfun$foreach$4;
class	scala/collection/MapLike$DefaultValuesIterable$$anonfun$foreach$4
NameAndType	serialVersionUID:J
Field	scala/collection/MapLike$DefaultValuesIterable$$anonfun$foreach$4.serialVersionUID:J
Asciz	f$2;
Asciz	Lscala/Function1;;
Asciz	<init>;
Asciz	(Lscala/collection/MapLike$DefaultValuesIterable;Lscala/Function1;)V;
Asciz	LineNumberTable;
NameAndType	f$2:Lscala/Function1;
Field	scala/collection/MapLike$DefaultValuesIterable$$anonfun$foreach$4.f$2:Lscala/Function1;
Asciz	scala/runtime/AbstractFunction1;
class	scala/runtime/AbstractFunction1
NameAndType	"<init>":()V
Method	scala/runtime/AbstractFunction1."<init>":()V
Asciz	this;
Asciz	Lscala/collection/MapLike$DefaultValuesIterable$$anonfun$foreach$4;;
Asciz	$outer;
Asciz	Lscala/collection/MapLike$DefaultValuesIterable;;
Asciz	LocalVariableTable;
Asciz	(Lscala/collection/MapLike<TA;TB;TThis;>.DefaultValuesIterable;)V;
Asciz	Signature;
Asciz	apply;
Asciz	(Ljava/lang/Object;)Ljava/lang/Object;;
Asciz	scala/Tuple2;
class	scala/Tuple2
Asciz	(Lscala/Tuple2;)Ljava/lang/Object;;
NameAndType	apply:(Lscala/Tuple2;)Ljava/lang/Object;
Method	scala/collection/MapLike$DefaultValuesIterable$$anonfun$foreach$4.apply:(Lscala/Tuple2;)Ljava/lang/Object;
Asciz	v1;
Asciz	Ljava/lang/Object;;
Asciz	_2;
Asciz	()Ljava/lang/Object;;
NameAndType	_2:()Ljava/lang/Object;
Method	scala/Tuple2._2:()Ljava/lang/Object;
Asciz	scala/Function1;
class	scala/Function1
NameAndType	apply:(Ljava/lang/Object;)Ljava/lang/Object;
InterfaceMethod	scala/Function1.apply:(Ljava/lang/Object;)Ljava/lang/Object;
Asciz	scala/MatchError;
class	scala/MatchError
Asciz	toString;
Asciz	()Ljava/lang/String;;
NameAndType	toString:()Ljava/lang/String;
Method	scala/Tuple2.toString:()Ljava/lang/String;
Asciz	(Ljava/lang/String;)V;
NameAndType	"<init>":(Ljava/lang/String;)V
Method	scala/MatchError."<init>":(Ljava/lang/String;)V
Asciz	temp24;
Asciz	(Lscala/Tuple2<TA;TB;>;)TC;;
Asciz	Scala;
Asciz	InnerClasses;
Asciz	scala/collection/MapLike$DefaultValuesIterable;
class	scala/collection/MapLike$DefaultValuesIterable
Asciz	scala/collection/MapLike;
class	scala/collection/MapLike
Asciz	DefaultValuesIterable;
Asciz	$anonfun$foreach$4;
Asciz	java/io/Serializable;
class	java/io/Serializable

{
public static final long serialVersionUID;
  Signature: J

public final scala.Function1 f$2;
  Signature: Lscala/Function1;

public static {};
  Signature: ()V
  Code:
   Stack=2, Locals=0, Args_size=0
	lconst_0
	putstatic	Field serialVersionUID:J
	return
  Labels:

public scala.collection.MapLike$DefaultValuesIterable$$anonfun$foreach$4(scala.collection.MapLike$DefaultValuesIterable, scala.Function1);
  Signature: (Lscala/collection/MapLike$DefaultValuesIterable;Lscala/Function1;)V
  Code:
   Stack=2, Locals=3, Args_size=3
	aload_0
	aload_2
	putfield	Field f$2:Lscala/Function1;
	aload_0
	invokespecial	Method scala/runtime/AbstractFunction1."<init>":()V
	return
  Labels:
  LocalVariableTable: 
   Start  Length  Slot  Name   Signature
   0      10      0    this       Lscala/collection/MapLike$DefaultValuesIterable$$anonfun$foreach$4;
   0      10      1    $outer       Lscala/collection/MapLike$DefaultValuesIterable;

  Signature: length = 0x2
   00 1C 

public final java.lang.Object apply(java.lang.Object);
  Signature: (Ljava/lang/Object;)Ljava/lang/Object;
  Code:
   Stack=2, Locals=2, Args_size=2
	aload_0
	aload_1
	checkcast	class scala/Tuple2
	invokevirtual	Method apply:(Lscala/Tuple2;)Ljava/lang/Object;
	areturn
  Labels:
  LocalVariableTable: 
   Start  Length  Slot  Name   Signature
   0      9      0    this       Lscala/collection/MapLike$DefaultValuesIterable$$anonfun$foreach$4;
   0      9      1    v1       Ljava/lang/Object;


public final java.lang.Object apply(scala.Tuple2);
  Signature: (Lscala/Tuple2;)Ljava/lang/Object;
  Code:
   Stack=3, Locals=3, Args_size=2
	aload_1
	ifnull	l1 // new
	aload_1
	invokevirtual	Method scala/Tuple2._2:()Ljava/lang/Object;
	astore_2
	iconst_1
	ifeq	l2 // new
	aload_0
	getfield	Field f$2:Lscala/Function1;
	aload_2
	invokeinterface	InterfaceMethod scala/Function1.apply:(Ljava/lang/Object;)Ljava/lang/Object;
	areturn
l2	new	class scala/MatchError
	dup
	aload_1
	invokevirtual	Method scala/Tuple2.toString:()Ljava/lang/String;
	invokespecial	Method scala/MatchError."<init>":(Ljava/lang/String;)V
	athrow
l1	new	class scala/MatchError
	dup
	aload_1
	invokevirtual	Method scala/Tuple2.toString:()Ljava/lang/String;
	invokespecial	Method scala/MatchError."<init>":(Ljava/lang/String;)V
	athrow
  Labels:
   	l2 = 24 // new
   	l1 = 36 // new
  LocalVariableTable: 
   Start  Length  Slot  Name   Signature
   0      48      0    this       Lscala/collection/MapLike$DefaultValuesIterable$$anonfun$foreach$4;
   9      27      2    temp24       Ljava/lang/Object;

  Signature: length = 0x2
   00 39 

}

