Compiled from "package.scala"
public final class scala.collection.package$$anon$1 extends java.lang.Object implements scala.collection.generic.CanBuildFrom
  SourceFile: "package.scala"
  Signature: length = 0x2
   00 21 
  Scala: length = 0x
   
  InnerClass: 
   public final #38= #10 of #37; //$anon$1=class scala/collection/package$$anon$1 of class scala/collection/package
  minor version: 0
  major version: 49
  Constant pool:
const #1 = Asciz	SourceFile;
const #2 = Asciz	package.scala;
const #3 = Asciz	b$1;
const #4 = Asciz	Lscala/collection/generic/CanBuildFrom;;
const #5 = Asciz	<init>;
const #6 = Asciz	(Lscala/collection/generic/CanBuildFrom;)V;
const #7 = Asciz	Code;
const #8 = Asciz	LineNumberTable;
const #9 = Asciz	scala/collection/package$$anon$1;
const #10 = class	#9;	//  scala/collection/package$$anon$1
const #11 = NameAndType	#3:#4;//  b$1:Lscala/collection/generic/CanBuildFrom;
const #12 = Field	#10.#11;	//  scala/collection/package$$anon$1.b$1:Lscala/collection/generic/CanBuildFrom;
const #13 = Asciz	java/lang/Object;
const #14 = class	#13;	//  java/lang/Object
const #15 = Asciz	()V;
const #16 = NameAndType	#5:#15;//  "<init>":()V
const #17 = Method	#14.#16;	//  java/lang/Object."<init>":()V
const #18 = Asciz	apply;
const #19 = Asciz	()Lscala/collection/mutable/Builder;;
const #20 = Asciz	scala/collection/generic/CanBuildFrom;
const #21 = class	#20;	//  scala/collection/generic/CanBuildFrom
const #22 = NameAndType	#18:#19;//  apply:()Lscala/collection/mutable/Builder;
const #23 = InterfaceMethod	#21.#22;	//  scala/collection/generic/CanBuildFrom.apply:()Lscala/collection/mutable/Builder;
const #24 = Asciz	()Lscala/collection/mutable/Builder<TT;TTo;>;;
const #25 = Asciz	Signature;
const #26 = Asciz	(Ljava/lang/Object;)Lscala/collection/mutable/Builder;;
const #27 = Asciz	this;
const #28 = Asciz	Lscala/collection/package$$anon$1;;
const #29 = Asciz	from;
const #30 = Asciz	Ljava/lang/Object;;
const #31 = Asciz	LocalVariableTable;
const #32 = Asciz	(TFrom;)Lscala/collection/mutable/Builder<TT;TTo;>;;
const #33 = Asciz	Ljava/lang/Object;Lscala/collection/generic/CanBuildFrom<TFrom;TT;TTo;>;;
const #34 = Asciz	Scala;
const #35 = Asciz	InnerClasses;
const #36 = Asciz	scala/collection/package;
const #37 = class	#36;	//  scala/collection/package
const #38 = Asciz	$anon$1;

{
public scala.collection.package$$anon$1(scala.collection.generic.CanBuildFrom);
  Code:
   Stack=2, Locals=2, Args_size=2
   0:	aload_0
   1:	aload_1
   2:	putfield	#12; //Field b$1:Lscala/collection/generic/CanBuildFrom;
   5:	aload_0
   6:	invokespecial	#17; //Method java/lang/Object."<init>":()V
   9:	return
  LineNumberTable: 
   line 7: 0


public scala.collection.mutable.Builder apply();
  Code:
   Stack=1, Locals=1, Args_size=1
   0:	aload_0
   1:	getfield	#12; //Field b$1:Lscala/collection/generic/CanBuildFrom;
   4:	invokeinterface	#23,  1; //InterfaceMethod scala/collection/generic/CanBuildFrom.apply:()Lscala/collection/mutable/Builder;
   9:	areturn
  LineNumberTable: 
   line 8: 0

  Signature: length = 0x2
   00 18 

public scala.collection.mutable.Builder apply(java.lang.Object);
  Code:
   Stack=1, Locals=2, Args_size=2
   0:	aload_0
   1:	getfield	#12; //Field b$1:Lscala/collection/generic/CanBuildFrom;
   4:	invokeinterface	#23,  1; //InterfaceMethod scala/collection/generic/CanBuildFrom.apply:()Lscala/collection/mutable/Builder;
   9:	areturn
  LineNumberTable: 
   line 8: 0

  LocalVariableTable: 
   Start  Length  Slot  Name   Signature
   0      10      0    this       Lscala/collection/package$$anon$1;
   0      10      1    from       Ljava/lang/Object;

  Signature: length = 0x2
   00 20 

}

