Compiled from "Seq.scala"
public final class scala.collection.Seq$ extends scala.collection.generic.SeqFactory implements scala.ScalaObject
  SourceFile: "Seq.scala"
  Scala: length = 0x
   
  Signature: length = 0x2
   00 4B 
  InnerClass: 
   public #79= #70 of #78; //GenericCanBuildFrom=class scala/collection/generic/TraversableFactory$GenericCanBuildFrom of class scala/collection/generic/TraversableFactory
  minor version: 0
  major version: 49
  Constant pool:
const #1 = Asciz	SourceFile;
const #2 = Asciz	Seq.scala;
const #3 = Asciz	Scala;
const #4 = Asciz	MODULE$;
const #5 = Asciz	Lscala/collection/Seq$;;
const #6 = Asciz	<clinit>;
const #7 = Asciz	()V;
const #8 = Asciz	Code;
const #9 = Asciz	scala/collection/Seq$;
const #10 = class	#9;	//  scala/collection/Seq$
const #11 = Asciz	<init>;
const #12 = NameAndType	#11:#7;//  "<init>":()V
const #13 = Method	#10.#12;	//  scala/collection/Seq$."<init>":()V
const #14 = Asciz	hashSeed;
const #15 = Asciz	I;
const #16 = Asciz	LineNumberTable;
const #17 = Asciz	scala/collection/generic/SeqFactory;
const #18 = class	#17;	//  scala/collection/generic/SeqFactory
const #19 = Method	#18.#12;	//  scala/collection/generic/SeqFactory."<init>":()V
const #20 = NameAndType	#4:#5;//  MODULE$:Lscala/collection/Seq$;
const #21 = Field	#10.#20;	//  scala/collection/Seq$.MODULE$:Lscala/collection/Seq$;
const #22 = Asciz	Seq;
const #23 = String	#22;	//  Seq
const #24 = Asciz	java/lang/String;
const #25 = class	#24;	//  java/lang/String
const #26 = Asciz	hashCode;
const #27 = Asciz	()I;
const #28 = NameAndType	#26:#27;//  hashCode:()I
const #29 = Method	#25.#28;	//  java/lang/String.hashCode:()I
const #30 = NameAndType	#14:#15;//  hashSeed:I
const #31 = Field	#10.#30;	//  scala/collection/Seq$.hashSeed:I
const #32 = Asciz	singleton;
const #33 = Asciz	(Ljava/lang/Object;)Lscala/collection/Seq;;
const #34 = Asciz	scala/Predef$;
const #35 = class	#34;	//  scala/Predef$
const #36 = Asciz	Lscala/Predef$;;
const #37 = NameAndType	#4:#36;//  MODULE$:Lscala/Predef$;
const #38 = Field	#35.#37;	//  scala/Predef$.MODULE$:Lscala/Predef$;
const #39 = Asciz	java/lang/Object;
const #40 = class	#39;	//  java/lang/Object
const #41 = Asciz	genericWrapArray;
const #42 = Asciz	(Ljava/lang/Object;)Lscala/collection/mutable/WrappedArray;;
const #43 = NameAndType	#41:#42;//  genericWrapArray:(Ljava/lang/Object;)Lscala/collection/mutable/WrappedArray;
const #44 = Method	#35.#43;	//  scala/Predef$.genericWrapArray:(Ljava/lang/Object;)Lscala/collection/mutable/WrappedArray;
const #45 = Asciz	apply;
const #46 = Asciz	(Lscala/collection/Seq;)Lscala/collection/Traversable;;
const #47 = NameAndType	#45:#46;//  apply:(Lscala/collection/Seq;)Lscala/collection/Traversable;
const #48 = Method	#10.#47;	//  scala/collection/Seq$.apply:(Lscala/collection/Seq;)Lscala/collection/Traversable;
const #49 = Asciz	scala/collection/Seq;
const #50 = class	#49;	//  scala/collection/Seq
const #51 = Asciz	this;
const #52 = Asciz	value;
const #53 = Asciz	Ljava/lang/Object;;
const #54 = Asciz	LocalVariableTable;
const #55 = Asciz	<A:Ljava/lang/Object;>(TA;)Lscala/collection/Seq<TA;>;;
const #56 = Asciz	Signature;
const #57 = Asciz	newBuilder;
const #58 = Asciz	()Lscala/collection/mutable/Builder;;
const #59 = Asciz	scala/collection/immutable/Seq$;
const #60 = class	#59;	//  scala/collection/immutable/Seq$
const #61 = Asciz	Lscala/collection/immutable/Seq$;;
const #62 = NameAndType	#4:#61;//  MODULE$:Lscala/collection/immutable/Seq$;
const #63 = Field	#60.#62;	//  scala/collection/immutable/Seq$.MODULE$:Lscala/collection/immutable/Seq$;
const #64 = NameAndType	#57:#58;//  newBuilder:()Lscala/collection/mutable/Builder;
const #65 = Method	#60.#64;	//  scala/collection/immutable/Seq$.newBuilder:()Lscala/collection/mutable/Builder;
const #66 = Asciz	<A:Ljava/lang/Object;>()Lscala/collection/mutable/Builder<TA;Lscala/collection/Seq<TA;>;>;;
const #67 = Asciz	canBuildFrom;
const #68 = Asciz	()Lscala/collection/generic/CanBuildFrom;;
const #69 = Asciz	scala/collection/generic/TraversableFactory$GenericCanBuildFrom;
const #70 = class	#69;	//  scala/collection/generic/TraversableFactory$GenericCanBuildFrom
const #71 = Asciz	(Lscala/collection/generic/TraversableFactory;)V;
const #72 = NameAndType	#11:#71;//  "<init>":(Lscala/collection/generic/TraversableFactory;)V
const #73 = Method	#70.#72;	//  scala/collection/generic/TraversableFactory$GenericCanBuildFrom."<init>":(Lscala/collection/generic/TraversableFactory;)V
const #74 = Asciz	<A:Ljava/lang/Object;>()Lscala/collection/generic/CanBuildFrom<Lscala/collection/Seq<*>;TA;Lscala/collection/Seq<TA;>;>;;
const #75 = Asciz	Lscala/collection/generic/SeqFactory<Lscala/collection/Seq;>;Lscala/ScalaObject;;
const #76 = Asciz	InnerClasses;
const #77 = Asciz	scala/collection/generic/TraversableFactory;
const #78 = class	#77;	//  scala/collection/generic/TraversableFactory
const #79 = Asciz	GenericCanBuildFrom;
const #80 = Asciz	scala/ScalaObject;
const #81 = class	#80;	//  scala/ScalaObject

{
public static final scala.collection.Seq$ MODULE$;

public static {};
  Code:
   Stack=1, Locals=0, Args_size=0
   0:	new	#10; //class scala/collection/Seq$
   3:	invokespecial	#13; //Method "<init>":()V
   6:	return

public scala.collection.Seq singleton(java.lang.Object);
  Code:
   Stack=6, Locals=2, Args_size=2
   0:	aload_0
   1:	getstatic	#38; //Field scala/Predef$.MODULE$:Lscala/Predef$;
   4:	iconst_1
   5:	anewarray	#40; //class java/lang/Object
   8:	dup
   9:	iconst_0
   10:	aload_1
   11:	aastore
   12:	invokevirtual	#44; //Method scala/Predef$.genericWrapArray:(Ljava/lang/Object;)Lscala/collection/mutable/WrappedArray;
   15:	invokevirtual	#48; //Method apply:(Lscala/collection/Seq;)Lscala/collection/Traversable;
   18:	checkcast	#50; //class scala/collection/Seq
   21:	areturn
  LineNumberTable: 
   line 56: 0

  LocalVariableTable: 
   Start  Length  Slot  Name   Signature
   0      22      0    this       Lscala/collection/Seq$;
   0      22      1    value       Ljava/lang/Object;

  Signature: length = 0x2
   00 37 

public scala.collection.mutable.Builder newBuilder();
  Code:
   Stack=1, Locals=1, Args_size=1
   0:	getstatic	#63; //Field scala/collection/immutable/Seq$.MODULE$:Lscala/collection/immutable/Seq$;
   3:	invokevirtual	#65; //Method scala/collection/immutable/Seq$.newBuilder:()Lscala/collection/mutable/Builder;
   6:	areturn
  LineNumberTable: 
   line 50: 0

  Signature: length = 0x2
   00 42 

public scala.collection.generic.CanBuildFrom canBuildFrom();
  Code:
   Stack=3, Locals=1, Args_size=1
   0:	new	#70; //class scala/collection/generic/TraversableFactory$GenericCanBuildFrom
   3:	dup
   4:	aload_0
   5:	invokespecial	#73; //Method scala/collection/generic/TraversableFactory$GenericCanBuildFrom."<init>":(Lscala/collection/generic/TraversableFactory;)V
   8:	areturn
  LineNumberTable: 
   line 49: 0

  Signature: length = 0x2
   00 4A 

public int hashSeed();
  Code:
   Stack=1, Locals=1, Args_size=1
   0:	aload_0
   1:	getfield	#31; //Field hashSeed:I
   4:	ireturn
  LineNumberTable: 
   line 47: 0


}

