Compiled from "SeqLike.scala"
public final class scala.collection.SeqLike$$anonfun$reverse$2 extends scala.runtime.AbstractFunction1 implements java.io.Serializable
  SourceFile: "SeqLike.scala"
  Scala: length = 0x
   
  InnerClass: 
   public final #48= #9 of #47; //$anonfun$reverse$2=class scala/collection/SeqLike$$anonfun$reverse$2 of class scala/collection/SeqLike
  minor version: 0
  major version: 49
  Constant pool:
const #1 = Asciz	SourceFile;
const #2 = Asciz	SeqLike.scala;
const #3 = Asciz	<clinit>;
const #4 = Asciz	()V;
const #5 = Asciz	Code;
const #6 = Asciz	serialVersionUID;
const #7 = Asciz	J;
const #8 = Asciz	scala/collection/SeqLike$$anonfun$reverse$2;
const #9 = class	#8;	//  scala/collection/SeqLike$$anonfun$reverse$2
const #10 = NameAndType	#6:#7;//  serialVersionUID:J
const #11 = Field	#9.#10;	//  scala/collection/SeqLike$$anonfun$reverse$2.serialVersionUID:J
const #12 = Asciz	b$1;
const #13 = Asciz	Lscala/collection/mutable/Builder;;
const #14 = Asciz	<init>;
const #15 = Asciz	(Lscala/collection/SeqLike;Lscala/collection/mutable/Builder;)V;
const #16 = Asciz	LineNumberTable;
const #17 = NameAndType	#12:#13;//  b$1:Lscala/collection/mutable/Builder;
const #18 = Field	#9.#17;	//  scala/collection/SeqLike$$anonfun$reverse$2.b$1:Lscala/collection/mutable/Builder;
const #19 = Asciz	scala/runtime/AbstractFunction1;
const #20 = class	#19;	//  scala/runtime/AbstractFunction1
const #21 = NameAndType	#14:#4;//  "<init>":()V
const #22 = Method	#20.#21;	//  scala/runtime/AbstractFunction1."<init>":()V
const #23 = Asciz	this;
const #24 = Asciz	Lscala/collection/SeqLike$$anonfun$reverse$2;;
const #25 = Asciz	$outer;
const #26 = Asciz	Lscala/collection/SeqLike;;
const #27 = Asciz	LocalVariableTable;
const #28 = Asciz	(Lscala/collection/SeqLike<TA;TRepr;>;)V;
const #29 = Asciz	Signature;
const #30 = Asciz	apply;
const #31 = Asciz	(Ljava/lang/Object;)Ljava/lang/Object;;
const #32 = Asciz	(Ljava/lang/Object;)Lscala/collection/mutable/Builder;;
const #33 = NameAndType	#30:#32;//  apply:(Ljava/lang/Object;)Lscala/collection/mutable/Builder;
const #34 = Method	#9.#33;	//  scala/collection/SeqLike$$anonfun$reverse$2.apply:(Ljava/lang/Object;)Lscala/collection/mutable/Builder;
const #35 = Asciz	v1;
const #36 = Asciz	Ljava/lang/Object;;
const #37 = Asciz	scala/collection/mutable/Builder;
const #38 = class	#37;	//  scala/collection/mutable/Builder
const #39 = Asciz	$plus$eq;
const #40 = NameAndType	#39:#32;//  $plus$eq:(Ljava/lang/Object;)Lscala/collection/mutable/Builder;
const #41 = InterfaceMethod	#38.#40;	//  scala/collection/mutable/Builder.$plus$eq:(Ljava/lang/Object;)Lscala/collection/mutable/Builder;
const #42 = Asciz	x;
const #43 = Asciz	(TA;)Lscala/collection/mutable/Builder<TA;TRepr;>;;
const #44 = Asciz	Scala;
const #45 = Asciz	InnerClasses;
const #46 = Asciz	scala/collection/SeqLike;
const #47 = class	#46;	//  scala/collection/SeqLike
const #48 = Asciz	$anonfun$reverse$2;
const #49 = Asciz	java/io/Serializable;
const #50 = class	#49;	//  java/io/Serializable

{
public static final long serialVersionUID;

public static {};
  Code:
   Stack=2, Locals=0, Args_size=0
   0:	lconst_0
   1:	putstatic	#11; //Field serialVersionUID:J
   4:	return

public scala.collection.SeqLike$$anonfun$reverse$2(scala.collection.SeqLike, scala.collection.mutable.Builder);
  Code:
   Stack=2, Locals=3, Args_size=3
   0:	aload_0
   1:	aload_2
   2:	putfield	#18; //Field b$1:Lscala/collection/mutable/Builder;
   5:	aload_0
   6:	invokespecial	#22; //Method scala/runtime/AbstractFunction1."<init>":()V
   9:	return
  LineNumberTable: 
   line 357: 0

  LocalVariableTable: 
   Start  Length  Slot  Name   Signature
   0      10      0    this       Lscala/collection/SeqLike$$anonfun$reverse$2;
   0      10      1    $outer       Lscala/collection/SeqLike;

  Signature: length = 0x2
   00 1C 

public final java.lang.Object apply(java.lang.Object);
  Code:
   Stack=2, Locals=2, Args_size=2
   0:	aload_0
   1:	aload_1
   2:	invokevirtual	#34; //Method apply:(Ljava/lang/Object;)Lscala/collection/mutable/Builder;
   5:	areturn
  LineNumberTable: 
   line 357: 0

  LocalVariableTable: 
   Start  Length  Slot  Name   Signature
   0      6      0    this       Lscala/collection/SeqLike$$anonfun$reverse$2;
   0      6      1    v1       Ljava/lang/Object;


public final scala.collection.mutable.Builder apply(java.lang.Object);
  Code:
   Stack=2, Locals=2, Args_size=2
   0:	aload_0
   1:	getfield	#18; //Field b$1:Lscala/collection/mutable/Builder;
   4:	aload_1
   5:	invokeinterface	#41,  2; //InterfaceMethod scala/collection/mutable/Builder.$plus$eq:(Ljava/lang/Object;)Lscala/collection/mutable/Builder;
   10:	areturn
  LineNumberTable: 
   line 358: 0

  LocalVariableTable: 
   Start  Length  Slot  Name   Signature
   0      11      0    this       Lscala/collection/SeqLike$$anonfun$reverse$2;
   0      11      1    x       Ljava/lang/Object;

  Signature: length = 0x2
   00 2B 

}

