Compiled from "SeqLike.scala"
public final class scala.collection.SeqLike$$anonfun$lastIndexOf$2 extends java.lang.Object implements scala.Function1,scala.ScalaObject,java.io.Serializable
  SourceFile: "SeqLike.scala"
  Scala: length = 0x
   
  InnerClass: 
   public final $anonfun$lastIndexOf$2=class scala/collection/SeqLike$$anonfun$lastIndexOf$2 of class scala/collection/SeqLike
  minor version: 0
  major version: 49
  Constant pool:
Asciz	SourceFile;
Asciz	SeqLike.scala;
Asciz	<clinit>;
Asciz	()V;
Asciz	Code;
Asciz	serialVersionUID;
Asciz	J;
Asciz	scala/collection/SeqLike$$anonfun$lastIndexOf$2;
class	scala/collection/SeqLike$$anonfun$lastIndexOf$2
NameAndType	serialVersionUID:J
Field	scala/collection/SeqLike$$anonfun$lastIndexOf$2.serialVersionUID:J
Asciz	elem$3;
Asciz	Ljava/lang/Object;;
Asciz	<init>;
Asciz	(Lscala/collection/SeqLike;Ljava/lang/Object;)V;
Asciz	LineNumberTable;
NameAndType	elem$3:Ljava/lang/Object;
Field	scala/collection/SeqLike$$anonfun$lastIndexOf$2.elem$3:Ljava/lang/Object;
Asciz	java/lang/Object;
class	java/lang/Object
NameAndType	"<init>":()V
Method	java/lang/Object."<init>":()V
Asciz	scala/Function1$class;
class	scala/Function1$class
Asciz	$init$;
Asciz	(Lscala/Function1;)V;
NameAndType	$init$:(Lscala/Function1;)V
Method	scala/Function1$class.$init$:(Lscala/Function1;)V
Asciz	this;
Asciz	Lscala/collection/SeqLike$$anonfun$lastIndexOf$2;;
Asciz	$outer;
Asciz	Lscala/collection/SeqLike;;
Asciz	LocalVariableTable;
Asciz	(Lscala/collection/SeqLike<TA;TRepr;>;)V;
Asciz	Signature;
Asciz	apply;
Asciz	(Ljava/lang/Object;)Ljava/lang/Object;;
Asciz	(Ljava/lang/Object;)Z;
NameAndType	apply:(Ljava/lang/Object;)Z
Method	scala/collection/SeqLike$$anonfun$lastIndexOf$2.apply:(Ljava/lang/Object;)Z
Asciz	scala/runtime/BoxesRunTime;
class	scala/runtime/BoxesRunTime
Asciz	boxToBoolean;
Asciz	(Z)Ljava/lang/Boolean;;
NameAndType	boxToBoolean:(Z)Ljava/lang/Boolean;
Method	scala/runtime/BoxesRunTime.boxToBoolean:(Z)Ljava/lang/Boolean;
Asciz	v1;
Asciz	java/lang/Number;
class	java/lang/Number
Asciz	java/lang/Character;
class	java/lang/Character
Asciz	equals2;
Asciz	(Ljava/lang/Object;Ljava/lang/Object;)Z;
NameAndType	equals2:(Ljava/lang/Object;Ljava/lang/Object;)Z
Method	scala/runtime/BoxesRunTime.equals2:(Ljava/lang/Object;Ljava/lang/Object;)Z
Asciz	equals;
NameAndType	equals:(Ljava/lang/Object;)Z
Method	java/lang/Object.equals:(Ljava/lang/Object;)Z
Asciz	x0;
Asciz	andThen;
Asciz	(Lscala/Function1;)Lscala/Function1;;
Asciz	(Lscala/Function1;Lscala/Function1;)Lscala/Function1;;
NameAndType	andThen:(Lscala/Function1;Lscala/Function1;)Lscala/Function1;
Method	scala/Function1$class.andThen:(Lscala/Function1;Lscala/Function1;)Lscala/Function1;
Asciz	g;
Asciz	Lscala/Function1;;
Asciz	compose;
NameAndType	compose:(Lscala/Function1;Lscala/Function1;)Lscala/Function1;
Method	scala/Function1$class.compose:(Lscala/Function1;Lscala/Function1;)Lscala/Function1;
Asciz	toString;
Asciz	()Ljava/lang/String;;
Asciz	(Lscala/Function1;)Ljava/lang/String;;
NameAndType	toString:(Lscala/Function1;)Ljava/lang/String;
Method	scala/Function1$class.toString:(Lscala/Function1;)Ljava/lang/String;
Asciz	Scala;
Asciz	InnerClasses;
Asciz	scala/collection/SeqLike;
class	scala/collection/SeqLike
Asciz	$anonfun$lastIndexOf$2;
Asciz	scala/Function1;
class	scala/Function1
Asciz	scala/ScalaObject;
class	scala/ScalaObject
Asciz	java/io/Serializable;
class	java/io/Serializable

{
public static final long serialVersionUID;
  Signature: J

private final java.lang.Object elem$3;
  Signature: Ljava/lang/Object;

public static {};
  Signature: ()V
  Code:
   Stack=2, Locals=0, Args_size=0
	lconst_0
	putstatic	Field serialVersionUID:J
	return
  Labels:

public scala.collection.SeqLike$$anonfun$lastIndexOf$2(scala.collection.SeqLike, java.lang.Object);
  Signature: (Lscala/collection/SeqLike;Ljava/lang/Object;)V
  Code:
   Stack=2, Locals=3, Args_size=3
	aload_0
	aload_2
	putfield	Field elem$3:Ljava/lang/Object;
	aload_0
	invokespecial	Method java/lang/Object."<init>":()V
	aload_0
	invokestatic	Method scala/Function1$class.$init$:(Lscala/Function1;)V
	return
  Labels:
  LocalVariableTable: 
   Start  Length  Slot  Name   Signature
   0      14      0    this       Lscala/collection/SeqLike$$anonfun$lastIndexOf$2;
   0      14      1    $outer       Lscala/collection/SeqLike;

  Signature: length = 0x2
   00 22 

public final java.lang.Object apply(java.lang.Object);
  Signature: (Ljava/lang/Object;)Ljava/lang/Object;
  Code:
   Stack=2, Locals=3, Args_size=2
	aload_0
	aload_1
	invokevirtual	Method apply:(Ljava/lang/Object;)Z
	istore_2
	iload_2
	invokestatic	Method scala/runtime/BoxesRunTime.boxToBoolean:(Z)Ljava/lang/Boolean;
	areturn
  Labels:
  LocalVariableTable: 
   Start  Length  Slot  Name   Signature
   0      11      0    this       Lscala/collection/SeqLike$$anonfun$lastIndexOf$2;
   0      11      1    v1       Ljava/lang/Object;


public final boolean apply(java.lang.Object);
  Signature: (Ljava/lang/Object;)Z
  Code:
   Stack=2, Locals=3, Args_size=2
	aload_0
	getfield	Field elem$3:Ljava/lang/Object;
	astore_2
	aload_2
	aload_1
	if_acmpne	l1 // aload_2
	iconst_1
	goto	l2 // ifeq
l1	aload_2
	ifnonnull	l3 // aload_2
	iconst_0
	goto	l2 // ifeq
l3	aload_2
	instanceof	class java/lang/Number
	ifne	l4 // aload_2
	aload_2
	instanceof	class java/lang/Character
	ifeq	l5 // aload_2
l4	aload_2
	aload_1
	invokestatic	Method scala/runtime/BoxesRunTime.equals2:(Ljava/lang/Object;Ljava/lang/Object;)Z
	goto	l2 // ifeq
l5	aload_2
	aload_1
	invokevirtual	Method java/lang/Object.equals:(Ljava/lang/Object;)Z
l2	ifeq	l6 // iconst_0
	iconst_1
	goto	l7 // ireturn
l6	iconst_0
l7	ireturn
  Labels:
   	l1 = 14 // aload_2
   	l3 = 22 // aload_2
   	l4 = 36 // aload_2
   	l5 = 44 // aload_2
   	l2 = 49 // ifeq
   	l6 = 56 // iconst_0
   	l7 = 57 // ireturn
  LocalVariableTable: 
   Start  Length  Slot  Name   Signature
   0      58      0    this       Lscala/collection/SeqLike$$anonfun$lastIndexOf$2;
   10      42      2    x0       Ljava/lang/Object;


public scala.Function1 andThen(scala.Function1);
  Signature: (Lscala/Function1;)Lscala/Function1;
  Code:
   Stack=2, Locals=2, Args_size=2
	aload_0
	aload_1
	invokestatic	Method scala/Function1$class.andThen:(Lscala/Function1;Lscala/Function1;)Lscala/Function1;
	areturn
  Labels:
  LocalVariableTable: 
   Start  Length  Slot  Name   Signature
   0      6      0    this       Lscala/collection/SeqLike$$anonfun$lastIndexOf$2;
   0      6      1    g       Lscala/Function1;


public scala.Function1 compose(scala.Function1);
  Signature: (Lscala/Function1;)Lscala/Function1;
  Code:
   Stack=2, Locals=2, Args_size=2
	aload_0
	aload_1
	invokestatic	Method scala/Function1$class.compose:(Lscala/Function1;Lscala/Function1;)Lscala/Function1;
	areturn
  Labels:
  LocalVariableTable: 
   Start  Length  Slot  Name   Signature
   0      6      0    this       Lscala/collection/SeqLike$$anonfun$lastIndexOf$2;
   0      6      1    g       Lscala/Function1;


public java.lang.String toString();
  Signature: ()Ljava/lang/String;
  Code:
   Stack=1, Locals=1, Args_size=1
	aload_0
	invokestatic	Method scala/Function1$class.toString:(Lscala/Function1;)Ljava/lang/String;
	areturn
  Labels:

}

