Compiled from "SeqLike.scala"
public final class scala.collection.SeqLike$$anonfun$reverseMap$1 extends scala.runtime.AbstractFunction1 implements java.io.Serializable
  SourceFile: "SeqLike.scala"
  Scala: length = 0x
   
  InnerClass: 
   public final $anonfun$reverseMap$1=class scala/collection/SeqLike$$anonfun$reverseMap$1 of class scala/collection/SeqLike
  minor version: 0
  major version: 49
  Constant pool:
Asciz	SourceFile;
Asciz	SeqLike.scala;
Asciz	<clinit>;
Asciz	()V;
Asciz	Code;
Asciz	serialVersionUID;
Asciz	J;
Asciz	scala/collection/SeqLike$$anonfun$reverseMap$1;
class	scala/collection/SeqLike$$anonfun$reverseMap$1
NameAndType	serialVersionUID:J
Field	scala/collection/SeqLike$$anonfun$reverseMap$1.serialVersionUID:J
Asciz	xs$2;
Asciz	Lscala/runtime/ObjectRef;;
Asciz	apply;
Asciz	(Ljava/lang/Object;)V;
Asciz	LineNumberTable;
NameAndType	xs$2:Lscala/runtime/ObjectRef;
Field	scala/collection/SeqLike$$anonfun$reverseMap$1.xs$2:Lscala/runtime/ObjectRef;
Asciz	scala/runtime/ObjectRef;
class	scala/runtime/ObjectRef
Asciz	elem;
Asciz	Ljava/lang/Object;;
NameAndType	elem:Ljava/lang/Object;
Field	scala/runtime/ObjectRef.elem:Ljava/lang/Object;
Asciz	scala/collection/immutable/List;
class	scala/collection/immutable/List
Asciz	$colon$colon;
Asciz	(Ljava/lang/Object;)Lscala/collection/immutable/List;;
NameAndType	$colon$colon:(Ljava/lang/Object;)Lscala/collection/immutable/List;
Method	scala/collection/immutable/List.$colon$colon:(Ljava/lang/Object;)Lscala/collection/immutable/List;
Asciz	this;
Asciz	Lscala/collection/SeqLike$$anonfun$reverseMap$1;;
Asciz	x;
Asciz	LocalVariableTable;
Asciz	(TA;)V;
Asciz	Signature;
Asciz	(Ljava/lang/Object;)Ljava/lang/Object;;
NameAndType	apply:(Ljava/lang/Object;)V
Method	scala/collection/SeqLike$$anonfun$reverseMap$1.apply:(Ljava/lang/Object;)V
Asciz	scala/runtime/BoxedUnit;
class	scala/runtime/BoxedUnit
Asciz	UNIT;
Asciz	Lscala/runtime/BoxedUnit;;
NameAndType	UNIT:Lscala/runtime/BoxedUnit;
Field	scala/runtime/BoxedUnit.UNIT:Lscala/runtime/BoxedUnit;
Asciz	v1;
Asciz	<init>;
Asciz	(Lscala/collection/SeqLike;Lscala/runtime/ObjectRef;)V;
Asciz	scala/runtime/AbstractFunction1;
class	scala/runtime/AbstractFunction1
NameAndType	"<init>":()V
Method	scala/runtime/AbstractFunction1."<init>":()V
Asciz	$outer;
Asciz	Lscala/collection/SeqLike;;
Asciz	(Lscala/collection/SeqLike<TA;TRepr;>;)V;
Asciz	Scala;
Asciz	InnerClasses;
Asciz	scala/collection/SeqLike;
class	scala/collection/SeqLike
Asciz	$anonfun$reverseMap$1;
Asciz	java/io/Serializable;
class	java/io/Serializable

{
public static final long serialVersionUID;
  Signature: J

private final scala.runtime.ObjectRef xs$2;
  Signature: Lscala/runtime/ObjectRef;

public static {};
  Signature: ()V
  Code:
   Stack=2, Locals=0, Args_size=0
	lconst_0
	putstatic	Field serialVersionUID:J
	return
  Labels:

public final void apply(java.lang.Object);
  Signature: (Ljava/lang/Object;)V
  Code:
   Stack=3, Locals=3, Args_size=2
	aload_0
	getfield	Field xs$2:Lscala/runtime/ObjectRef;
	aload_1
	astore_2
	aload_0
	getfield	Field xs$2:Lscala/runtime/ObjectRef;
	getfield	Field scala/runtime/ObjectRef.elem:Ljava/lang/Object;
	checkcast	class scala/collection/immutable/List
	aload_2
	invokevirtual	Method scala/collection/immutable/List.$colon$colon:(Ljava/lang/Object;)Lscala/collection/immutable/List;
	putfield	Field scala/runtime/ObjectRef.elem:Ljava/lang/Object;
	return
  Labels:
  LocalVariableTable: 
   Start  Length  Slot  Name   Signature
   0      24      0    this       Lscala/collection/SeqLike$$anonfun$reverseMap$1;
   0      24      1    x       Ljava/lang/Object;

  Signature: length = 0x2
   00 23 

public final java.lang.Object apply(java.lang.Object);
  Signature: (Ljava/lang/Object;)Ljava/lang/Object;
  Code:
   Stack=2, Locals=2, Args_size=2
	aload_0
	aload_1
	invokevirtual	Method apply:(Ljava/lang/Object;)V
	getstatic	Field scala/runtime/BoxedUnit.UNIT:Lscala/runtime/BoxedUnit;
	areturn
  Labels:
  LocalVariableTable: 
   Start  Length  Slot  Name   Signature
   0      9      0    this       Lscala/collection/SeqLike$$anonfun$reverseMap$1;
   0      9      1    v1       Ljava/lang/Object;


public scala.collection.SeqLike$$anonfun$reverseMap$1(scala.collection.SeqLike, scala.runtime.ObjectRef);
  Signature: (Lscala/collection/SeqLike;Lscala/runtime/ObjectRef;)V
  Code:
   Stack=2, Locals=3, Args_size=3
	aload_0
	aload_2
	putfield	Field xs$2:Lscala/runtime/ObjectRef;
	aload_0
	invokespecial	Method scala/runtime/AbstractFunction1."<init>":()V
	return
  Labels:
  LocalVariableTable: 
   Start  Length  Slot  Name   Signature
   0      10      0    this       Lscala/collection/SeqLike$$anonfun$reverseMap$1;
   0      10      1    $outer       Lscala/collection/SeqLike;

  Signature: length = 0x2
   00 37 

}

