Compiled from "SeqLike.scala"
public final class scala.collection.SeqLike$$anonfun$sortWith$1 extends java.lang.Object implements scala.Function1,scala.ScalaObject,java.io.Serializable
  SourceFile: "SeqLike.scala"
  Scala: length = 0x
   
  InnerClass: 
   public final $anonfun$sortWith$1=class scala/collection/SeqLike$$anonfun$sortWith$1 of class scala/collection/SeqLike
  minor version: 0
  major version: 49
  Constant pool:
Asciz	SourceFile;
Asciz	SeqLike.scala;
Asciz	<clinit>;
Asciz	()V;
Asciz	Code;
Asciz	serialVersionUID;
Asciz	J;
Asciz	scala/collection/SeqLike$$anonfun$sortWith$1;
class	scala/collection/SeqLike$$anonfun$sortWith$1
NameAndType	serialVersionUID:J
Field	scala/collection/SeqLike$$anonfun$sortWith$1.serialVersionUID:J
Asciz	i$2;
Asciz	Lscala/runtime/IntRef;;
Asciz	arr$1;
Asciz	Lscala/collection/mutable/GenericArray;;
Asciz	<init>;
Asciz	(Lscala/collection/SeqLike;Lscala/collection/mutable/GenericArray;Lscala/runtime/IntRef;)V;
Asciz	LineNumberTable;
NameAndType	arr$1:Lscala/collection/mutable/GenericArray;
Field	scala/collection/SeqLike$$anonfun$sortWith$1.arr$1:Lscala/collection/mutable/GenericArray;
NameAndType	i$2:Lscala/runtime/IntRef;
Field	scala/collection/SeqLike$$anonfun$sortWith$1.i$2:Lscala/runtime/IntRef;
Asciz	java/lang/Object;
class	java/lang/Object
NameAndType	"<init>":()V
Method	java/lang/Object."<init>":()V
Asciz	scala/Function1$class;
class	scala/Function1$class
Asciz	$init$;
Asciz	(Lscala/Function1;)V;
NameAndType	$init$:(Lscala/Function1;)V
Method	scala/Function1$class.$init$:(Lscala/Function1;)V
Asciz	this;
Asciz	Lscala/collection/SeqLike$$anonfun$sortWith$1;;
Asciz	$outer;
Asciz	Lscala/collection/SeqLike;;
Asciz	LocalVariableTable;
Asciz	(Lscala/collection/SeqLike<TA;TRepr;>;)V;
Asciz	Signature;
Asciz	apply;
Asciz	(Ljava/lang/Object;)Ljava/lang/Object;;
Asciz	(Ljava/lang/Object;)V;
NameAndType	apply:(Ljava/lang/Object;)V
Method	scala/collection/SeqLike$$anonfun$sortWith$1.apply:(Ljava/lang/Object;)V
Asciz	scala/runtime/BoxedUnit;
class	scala/runtime/BoxedUnit
Asciz	UNIT;
Asciz	Lscala/runtime/BoxedUnit;;
NameAndType	UNIT:Lscala/runtime/BoxedUnit;
Field	scala/runtime/BoxedUnit.UNIT:Lscala/runtime/BoxedUnit;
Asciz	v1;
Asciz	Ljava/lang/Object;;
Asciz	scala/runtime/IntRef;
class	scala/runtime/IntRef
Asciz	elem;
Asciz	I;
NameAndType	elem:I
Field	scala/runtime/IntRef.elem:I
Asciz	scala/collection/mutable/GenericArray;
class	scala/collection/mutable/GenericArray
Asciz	update;
Asciz	(ILjava/lang/Object;)V;
NameAndType	update:(ILjava/lang/Object;)V
Method	scala/collection/mutable/GenericArray.update:(ILjava/lang/Object;)V
Asciz	x;
Asciz	(TA;)V;
Asciz	andThen;
Asciz	(Lscala/Function1;)Lscala/Function1;;
Asciz	(Lscala/Function1;Lscala/Function1;)Lscala/Function1;;
NameAndType	andThen:(Lscala/Function1;Lscala/Function1;)Lscala/Function1;
Method	scala/Function1$class.andThen:(Lscala/Function1;Lscala/Function1;)Lscala/Function1;
Asciz	g;
Asciz	Lscala/Function1;;
Asciz	compose;
NameAndType	compose:(Lscala/Function1;Lscala/Function1;)Lscala/Function1;
Method	scala/Function1$class.compose:(Lscala/Function1;Lscala/Function1;)Lscala/Function1;
Asciz	toString;
Asciz	()Ljava/lang/String;;
Asciz	(Lscala/Function1;)Ljava/lang/String;;
NameAndType	toString:(Lscala/Function1;)Ljava/lang/String;
Method	scala/Function1$class.toString:(Lscala/Function1;)Ljava/lang/String;
Asciz	Scala;
Asciz	InnerClasses;
Asciz	scala/collection/SeqLike;
class	scala/collection/SeqLike
Asciz	$anonfun$sortWith$1;
Asciz	scala/Function1;
class	scala/Function1
Asciz	scala/ScalaObject;
class	scala/ScalaObject
Asciz	java/io/Serializable;
class	java/io/Serializable

{
public static final long serialVersionUID;
  Signature: J

private final scala.runtime.IntRef i$2;
  Signature: Lscala/runtime/IntRef;

private final scala.collection.mutable.GenericArray arr$1;
  Signature: Lscala/collection/mutable/GenericArray;

public static {};
  Signature: ()V
  Code:
   Stack=2, Locals=0, Args_size=0
	lconst_0
	putstatic	Field serialVersionUID:J
	return
  Labels:

public scala.collection.SeqLike$$anonfun$sortWith$1(scala.collection.SeqLike, scala.collection.mutable.GenericArray, scala.runtime.IntRef);
  Signature: (Lscala/collection/SeqLike;Lscala/collection/mutable/GenericArray;Lscala/runtime/IntRef;)V
  Code:
   Stack=2, Locals=4, Args_size=4
	aload_0
	aload_2
	putfield	Field arr$1:Lscala/collection/mutable/GenericArray;
	aload_0
	aload_3
	putfield	Field i$2:Lscala/runtime/IntRef;
	aload_0
	invokespecial	Method java/lang/Object."<init>":()V
	aload_0
	invokestatic	Method scala/Function1$class.$init$:(Lscala/Function1;)V
	return
  Labels:
  LocalVariableTable: 
   Start  Length  Slot  Name   Signature
   0      19      0    this       Lscala/collection/SeqLike$$anonfun$sortWith$1;
   0      19      1    $outer       Lscala/collection/SeqLike;

  Signature: length = 0x2
   00 26 

public final java.lang.Object apply(java.lang.Object);
  Signature: (Ljava/lang/Object;)Ljava/lang/Object;
  Code:
   Stack=2, Locals=2, Args_size=2
	aload_0
	aload_1
	invokevirtual	Method apply:(Ljava/lang/Object;)V
	getstatic	Field scala/runtime/BoxedUnit.UNIT:Lscala/runtime/BoxedUnit;
	areturn
  Labels:
  LocalVariableTable: 
   Start  Length  Slot  Name   Signature
   0      9      0    this       Lscala/collection/SeqLike$$anonfun$sortWith$1;
   0      9      1    v1       Ljava/lang/Object;


public final void apply(java.lang.Object);
  Signature: (Ljava/lang/Object;)V
  Code:
   Stack=3, Locals=2, Args_size=2
	aload_0
	getfield	Field arr$1:Lscala/collection/mutable/GenericArray;
	aload_0
	getfield	Field i$2:Lscala/runtime/IntRef;
	getfield	Field scala/runtime/IntRef.elem:I
	aload_1
	invokevirtual	Method scala/collection/mutable/GenericArray.update:(ILjava/lang/Object;)V
	aload_0
	getfield	Field i$2:Lscala/runtime/IntRef;
	aload_0
	getfield	Field i$2:Lscala/runtime/IntRef;
	getfield	Field scala/runtime/IntRef.elem:I
	iconst_1
	iadd
	putfield	Field scala/runtime/IntRef.elem:I
	return
  Labels:
  LocalVariableTable: 
   Start  Length  Slot  Name   Signature
   0      32      0    this       Lscala/collection/SeqLike$$anonfun$sortWith$1;
   0      32      1    x       Ljava/lang/Object;

  Signature: length = 0x2
   00 42 

public scala.Function1 andThen(scala.Function1);
  Signature: (Lscala/Function1;)Lscala/Function1;
  Code:
   Stack=2, Locals=2, Args_size=2
	aload_0
	aload_1
	invokestatic	Method scala/Function1$class.andThen:(Lscala/Function1;Lscala/Function1;)Lscala/Function1;
	areturn
  Labels:
  LocalVariableTable: 
   Start  Length  Slot  Name   Signature
   0      6      0    this       Lscala/collection/SeqLike$$anonfun$sortWith$1;
   0      6      1    g       Lscala/Function1;


public scala.Function1 compose(scala.Function1);
  Signature: (Lscala/Function1;)Lscala/Function1;
  Code:
   Stack=2, Locals=2, Args_size=2
	aload_0
	aload_1
	invokestatic	Method scala/Function1$class.compose:(Lscala/Function1;Lscala/Function1;)Lscala/Function1;
	areturn
  Labels:
  LocalVariableTable: 
   Start  Length  Slot  Name   Signature
   0      6      0    this       Lscala/collection/SeqLike$$anonfun$sortWith$1;
   0      6      1    g       Lscala/Function1;


public java.lang.String toString();
  Signature: ()Ljava/lang/String;
  Code:
   Stack=1, Locals=1, Args_size=1
	aload_0
	invokestatic	Method scala/Function1$class.toString:(Lscala/Function1;)Ljava/lang/String;
	areturn
  Labels:

}

