Compiled from "SeqLike.scala"
public abstract class scala.collection.SeqLike$class extends java.lang.Object
  SourceFile: "SeqLike.scala"
  Scala: length = 0x
   
  InnerClass: 
   public final #542= #345 of #13; //$anon$1=class scala/collection/SeqLike$$anon$1 of class scala/collection/SeqLike
   public final #543= #137 of #13; //$anon$2=class scala/collection/SeqLike$$anon$2 of class scala/collection/SeqLike
   public final #544= #229 of #167; //$anon$4=class scala/math/Ordering$$anon$4 of class scala/math/Ordering
   public final #545= #370 of #13; //$anonfun$diff$1=class scala/collection/SeqLike$$anonfun$diff$1 of class scala/collection/SeqLike
   public final #546= #517 of #13; //$anonfun$indexOf$1=class scala/collection/SeqLike$$anonfun$indexOf$1 of class scala/collection/SeqLike
   public final #547= #492 of #13; //$anonfun$reverse$2=class scala/collection/SeqLike$$anonfun$reverse$2 of class scala/collection/SeqLike
   public final #548= #489 of #13; //$anonfun$reverse$1=class scala/collection/SeqLike$$anonfun$reverse$1 of class scala/collection/SeqLike
   public final #549= #382 of #13; //$anonfun$contains$1=class scala/collection/SeqLike$$anonfun$contains$1 of class scala/collection/SeqLike
   public final #550= #211 of #13; //$anonfun$sortWith$2=class scala/collection/SeqLike$$anonfun$sortWith$2 of class scala/collection/SeqLike
   public final #551= #188 of #13; //$anonfun$sortWith$1=class scala/collection/SeqLike$$anonfun$sortWith$1 of class scala/collection/SeqLike
   public final #552= #111 of #13; //$anonfun$hashCode$1=class scala/collection/SeqLike$$anonfun$hashCode$1 of class scala/collection/SeqLike
   public final #553= #362 of #13; //$anonfun$intersect$1=class scala/collection/SeqLike$$anonfun$intersect$1 of class scala/collection/SeqLike
   public final #554= #348 of #13; //$anonfun$occCounts$1=class scala/collection/SeqLike$$anonfun$occCounts$1 of class scala/collection/SeqLike
   public final #555= #478 of #13; //$anonfun$reverseMap$2=class scala/collection/SeqLike$$anonfun$reverseMap$2 of class scala/collection/SeqLike
   public final #556= #469 of #13; //$anonfun$reverseMap$1=class scala/collection/SeqLike$$anonfun$reverseMap$1 of class scala/collection/SeqLike
   public final #557= #513 of #13; //$anonfun$lastIndexOf$1=class scala/collection/SeqLike$$anonfun$lastIndexOf$1 of class scala/collection/SeqLike
   public final #558= #508 of #13; //$anonfun$lastIndexOf$2=class scala/collection/SeqLike$$anonfun$lastIndexOf$2 of class scala/collection/SeqLike
   public final #559= #335 of #13; //$anonfun$removeDuplicates$1=class scala/collection/SeqLike$$anonfun$removeDuplicates$1 of class scala/collection/SeqLike
  minor version: 0
  major version: 49
  Constant pool:
const #1 = Asciz	SourceFile;
const #2 = Asciz	SeqLike.scala;
const #3 = Asciz	$init$;
const #4 = Asciz	(Lscala/collection/SeqLike;)V;
const #5 = Asciz	Code;
const #6 = Asciz	LineNumberTable;
const #7 = Asciz	$this;
const #8 = Asciz	Lscala/collection/SeqLike;;
const #9 = Asciz	LocalVariableTable;
const #10 = Asciz	projection;
const #11 = Asciz	(Lscala/collection/SeqLike;)Ljava/lang/Object;;
const #12 = Asciz	scala/collection/SeqLike;
const #13 = class	#12;	//  scala/collection/SeqLike
const #14 = Asciz	view;
const #15 = Asciz	()Ljava/lang/Object;;
const #16 = NameAndType	#14:#15;//  view:()Ljava/lang/Object;
const #17 = InterfaceMethod	#13.#16;	//  scala/collection/SeqLike.view:()Ljava/lang/Object;
const #18 = Asciz	Deprecated;
const #19 = Asciz	equalsWith;
const #20 = Asciz	(Lscala/collection/SeqLike;Lscala/collection/Seq;Lscala/Function2;)Z;
const #21 = Asciz	scala/collection/IterableLike;
const #22 = class	#21;	//  scala/collection/IterableLike
const #23 = Asciz	iterator;
const #24 = Asciz	()Lscala/collection/Iterator;;
const #25 = NameAndType	#23:#24;//  iterator:()Lscala/collection/Iterator;
const #26 = InterfaceMethod	#22.#25;	//  scala/collection/IterableLike.iterator:()Lscala/collection/Iterator;
const #27 = Asciz	scala/collection/Iterator;
const #28 = class	#27;	//  scala/collection/Iterator
const #29 = Asciz	hasNext;
const #30 = Asciz	()Z;
const #31 = NameAndType	#29:#30;//  hasNext:()Z
const #32 = InterfaceMethod	#28.#31;	//  scala/collection/Iterator.hasNext:()Z
const #33 = Asciz	next;
const #34 = NameAndType	#33:#15;//  next:()Ljava/lang/Object;
const #35 = InterfaceMethod	#28.#34;	//  scala/collection/Iterator.next:()Ljava/lang/Object;
const #36 = Asciz	scala/Function2;
const #37 = class	#36;	//  scala/Function2
const #38 = Asciz	apply;
const #39 = Asciz	(Ljava/lang/Object;Ljava/lang/Object;)Ljava/lang/Object;;
const #40 = NameAndType	#38:#39;//  apply:(Ljava/lang/Object;Ljava/lang/Object;)Ljava/lang/Object;
const #41 = InterfaceMethod	#37.#40;	//  scala/Function2.apply:(Ljava/lang/Object;Ljava/lang/Object;)Ljava/lang/Object;
const #42 = Asciz	scala/runtime/BoxesRunTime;
const #43 = class	#42;	//  scala/runtime/BoxesRunTime
const #44 = Asciz	unboxToBoolean;
const #45 = Asciz	(Ljava/lang/Object;)Z;
const #46 = NameAndType	#44:#45;//  unboxToBoolean:(Ljava/lang/Object;)Z
const #47 = Method	#43.#46;	//  scala/runtime/BoxesRunTime.unboxToBoolean:(Ljava/lang/Object;)Z
const #48 = Asciz	that;
const #49 = Asciz	Lscala/collection/Seq;;
const #50 = Asciz	f;
const #51 = Asciz	Lscala/Function2;;
const #52 = Asciz	i;
const #53 = Asciz	Lscala/collection/Iterator;;
const #54 = Asciz	j;
const #55 = Asciz	findLastIndexOf;
const #56 = Asciz	(Lscala/collection/SeqLike;Lscala/Function1;)I;
const #57 = Asciz	lastIndexWhere;
const #58 = Asciz	(Lscala/Function1;)I;
const #59 = NameAndType	#57:#58;//  lastIndexWhere:(Lscala/Function1;)I
const #60 = InterfaceMethod	#13.#59;	//  scala/collection/SeqLike.lastIndexWhere:(Lscala/Function1;)I
const #61 = Asciz	p;
const #62 = Asciz	Lscala/Function1;;
const #63 = Asciz	toString;
const #64 = Asciz	(Lscala/collection/SeqLike;)Ljava/lang/String;;
const #65 = Asciz	scala/collection/TraversableLike$class;
const #66 = class	#65;	//  scala/collection/TraversableLike$class
const #67 = Asciz	(Lscala/collection/TraversableLike;)Ljava/lang/String;;
const #68 = NameAndType	#63:#67;//  toString:(Lscala/collection/TraversableLike;)Ljava/lang/String;
const #69 = Method	#66.#68;	//  scala/collection/TraversableLike$class.toString:(Lscala/collection/TraversableLike;)Ljava/lang/String;
const #70 = Asciz	equals;
const #71 = Asciz	(Lscala/collection/SeqLike;Ljava/lang/Object;)Z;
const #72 = Asciz	scala/collection/Seq;
const #73 = class	#72;	//  scala/collection/Seq
const #74 = Asciz	canEqual;
const #75 = NameAndType	#74:#45;//  canEqual:(Ljava/lang/Object;)Z
const #76 = InterfaceMethod	#22.#75;	//  scala/collection/IterableLike.canEqual:(Ljava/lang/Object;)Z
const #77 = Asciz	sameElements;
const #78 = Asciz	(Lscala/collection/Iterable;)Z;
const #79 = NameAndType	#77:#78;//  sameElements:(Lscala/collection/Iterable;)Z
const #80 = InterfaceMethod	#22.#79;	//  scala/collection/IterableLike.sameElements:(Lscala/collection/Iterable;)Z
const #81 = Asciz	scala/MatchError;
const #82 = class	#81;	//  scala/MatchError
const #83 = Asciz	java/lang/Object;
const #84 = class	#83;	//  java/lang/Object
const #85 = Asciz	()Ljava/lang/String;;
const #86 = NameAndType	#63:#85;//  toString:()Ljava/lang/String;
const #87 = Method	#84.#86;	//  java/lang/Object.toString:()Ljava/lang/String;
const #88 = Asciz	<init>;
const #89 = Asciz	(Ljava/lang/String;)V;
const #90 = NameAndType	#88:#89;//  "<init>":(Ljava/lang/String;)V
const #91 = Method	#82.#90;	//  scala/MatchError."<init>":(Ljava/lang/String;)V
const #92 = Asciz	Ljava/lang/Object;;
const #93 = Asciz	temp17;
const #94 = Asciz	hashCode;
const #95 = Asciz	(Lscala/collection/SeqLike;)I;
const #96 = Asciz	scala/collection/Seq$;
const #97 = class	#96;	//  scala/collection/Seq$
const #98 = Asciz	MODULE$;
const #99 = Asciz	Lscala/collection/Seq$;;
const #100 = NameAndType	#98:#99;//  MODULE$:Lscala/collection/Seq$;
const #101 = Field	#97.#100;	//  scala/collection/Seq$.MODULE$:Lscala/collection/Seq$;
const #102 = Asciz	hashSeed;
const #103 = Asciz	()I;
const #104 = NameAndType	#102:#103;//  hashSeed:()I
const #105 = Method	#97.#104;	//  scala/collection/Seq$.hashSeed:()I
const #106 = Asciz	boxToInteger;
const #107 = Asciz	(I)Ljava/lang/Integer;;
const #108 = NameAndType	#106:#107;//  boxToInteger:(I)Ljava/lang/Integer;
const #109 = Method	#43.#108;	//  scala/runtime/BoxesRunTime.boxToInteger:(I)Ljava/lang/Integer;
const #110 = Asciz	scala/collection/SeqLike$$anonfun$hashCode$1;
const #111 = class	#110;	//  scala/collection/SeqLike$$anonfun$hashCode$1
const #112 = NameAndType	#88:#4;//  "<init>":(Lscala/collection/SeqLike;)V
const #113 = Method	#111.#112;	//  scala/collection/SeqLike$$anonfun$hashCode$1."<init>":(Lscala/collection/SeqLike;)V
const #114 = Asciz	scala/collection/TraversableLike;
const #115 = class	#114;	//  scala/collection/TraversableLike
const #116 = Asciz	$div$colon;
const #117 = Asciz	(Ljava/lang/Object;Lscala/Function2;)Ljava/lang/Object;;
const #118 = NameAndType	#116:#117;//  $div$colon:(Ljava/lang/Object;Lscala/Function2;)Ljava/lang/Object;
const #119 = InterfaceMethod	#115.#118;	//  scala/collection/TraversableLike.$div$colon:(Ljava/lang/Object;Lscala/Function2;)Ljava/lang/Object;
const #120 = Asciz	unboxToInt;
const #121 = Asciz	(Ljava/lang/Object;)I;
const #122 = NameAndType	#120:#121;//  unboxToInt:(Ljava/lang/Object;)I
const #123 = Method	#43.#122;	//  scala/runtime/BoxesRunTime.unboxToInt:(Ljava/lang/Object;)I
const #124 = Asciz	(Lscala/collection/SeqLike;II)Lscala/collection/SeqView;;
const #125 = Asciz	scala/collection/TraversableViewLike;
const #126 = class	#125;	//  scala/collection/TraversableViewLike
const #127 = Asciz	slice;
const #128 = Asciz	(II)Lscala/collection/TraversableView;;
const #129 = NameAndType	#127:#128;//  slice:(II)Lscala/collection/TraversableView;
const #130 = InterfaceMethod	#126.#129;	//  scala/collection/TraversableViewLike.slice:(II)Lscala/collection/TraversableView;
const #131 = Asciz	scala/collection/SeqView;
const #132 = class	#131;	//  scala/collection/SeqView
const #133 = Asciz	from;
const #134 = Asciz	I;
const #135 = Asciz	until;
const #136 = Asciz	scala/collection/SeqLike$$anon$2;
const #137 = class	#136;	//  scala/collection/SeqLike$$anon$2
const #138 = Method	#137.#112;	//  scala/collection/SeqLike$$anon$2."<init>":(Lscala/collection/SeqLike;)V
const #139 = Asciz	indices;
const #140 = Asciz	(Lscala/collection/SeqLike;)Lscala/collection/immutable/Range;;
const #141 = Asciz	scala/Predef$;
const #142 = class	#141;	//  scala/Predef$
const #143 = Asciz	Lscala/Predef$;;
const #144 = NameAndType	#98:#143;//  MODULE$:Lscala/Predef$;
const #145 = Field	#142.#144;	//  scala/Predef$.MODULE$:Lscala/Predef$;
const #146 = Asciz	intWrapper;
const #147 = Asciz	(I)Lscala/runtime/RichInt;;
const #148 = NameAndType	#146:#147;//  intWrapper:(I)Lscala/runtime/RichInt;
const #149 = Method	#142.#148;	//  scala/Predef$.intWrapper:(I)Lscala/runtime/RichInt;
const #150 = Asciz	length;
const #151 = NameAndType	#150:#103;//  length:()I
const #152 = InterfaceMethod	#13.#151;	//  scala/collection/SeqLike.length:()I
const #153 = Asciz	scala/runtime/RichInt;
const #154 = class	#153;	//  scala/runtime/RichInt
const #155 = Asciz	(I)Lscala/collection/immutable/Range;;
const #156 = NameAndType	#135:#155;//  until:(I)Lscala/collection/immutable/Range;
const #157 = Method	#154.#156;	//  scala/runtime/RichInt.until:(I)Lscala/collection/immutable/Range;
const #158 = Asciz	toSeq;
const #159 = Asciz	(Lscala/collection/SeqLike;)Lscala/collection/Seq;;
const #160 = Asciz	thisCollection;
const #161 = Asciz	()Lscala/collection/Seq;;
const #162 = NameAndType	#160:#161;//  thisCollection:()Lscala/collection/Seq;
const #163 = InterfaceMethod	#13.#162;	//  scala/collection/SeqLike.thisCollection:()Lscala/collection/Seq;
const #164 = Asciz	sortBy;
const #165 = Asciz	(Lscala/collection/SeqLike;Lscala/Function1;Lscala/math/Ordering;)Ljava/lang/Object;;
const #166 = Asciz	scala/math/Ordering;
const #167 = class	#166;	//  scala/math/Ordering
const #168 = Asciz	on;
const #169 = Asciz	(Lscala/Function1;)Lscala/math/Ordering;;
const #170 = NameAndType	#168:#169;//  on:(Lscala/Function1;)Lscala/math/Ordering;
const #171 = InterfaceMethod	#167.#170;	//  scala/math/Ordering.on:(Lscala/Function1;)Lscala/math/Ordering;
const #172 = Asciz	sortWith;
const #173 = Asciz	(Lscala/math/Ordering;)Ljava/lang/Object;;
const #174 = NameAndType	#172:#173;//  sortWith:(Lscala/math/Ordering;)Ljava/lang/Object;
const #175 = InterfaceMethod	#13.#174;	//  scala/collection/SeqLike.sortWith:(Lscala/math/Ordering;)Ljava/lang/Object;
const #176 = Asciz	ord;
const #177 = Asciz	Lscala/math/Ordering;;
const #178 = Asciz	(Lscala/collection/SeqLike;Lscala/math/Ordering;)Ljava/lang/Object;;
const #179 = Asciz	scala/collection/mutable/GenericArray;
const #180 = class	#179;	//  scala/collection/mutable/GenericArray
const #181 = Asciz	(I)V;
const #182 = NameAndType	#88:#181;//  "<init>":(I)V
const #183 = Method	#180.#182;	//  scala/collection/mutable/GenericArray."<init>":(I)V
const #184 = Asciz	scala/runtime/IntRef;
const #185 = class	#184;	//  scala/runtime/IntRef
const #186 = Method	#185.#182;	//  scala/runtime/IntRef."<init>":(I)V
const #187 = Asciz	scala/collection/SeqLike$$anonfun$sortWith$1;
const #188 = class	#187;	//  scala/collection/SeqLike$$anonfun$sortWith$1
const #189 = Asciz	(Lscala/collection/SeqLike;Lscala/collection/mutable/GenericArray;Lscala/runtime/IntRef;)V;
const #190 = NameAndType	#88:#189;//  "<init>":(Lscala/collection/SeqLike;Lscala/collection/mutable/GenericArray;Lscala/runtime/IntRef;)V
const #191 = Method	#188.#190;	//  scala/collection/SeqLike$$anonfun$sortWith$1."<init>":(Lscala/collection/SeqLike;Lscala/collection/mutable/GenericArray;Lscala/runtime/IntRef;)V
const #192 = Asciz	foreach;
const #193 = Asciz	(Lscala/Function1;)V;
const #194 = NameAndType	#192:#193;//  foreach:(Lscala/Function1;)V
const #195 = InterfaceMethod	#22.#194;	//  scala/collection/IterableLike.foreach:(Lscala/Function1;)V
const #196 = Asciz	array;
const #197 = Asciz	()[Ljava/lang/Object;;
const #198 = NameAndType	#196:#197;//  array:()[Ljava/lang/Object;
const #199 = Method	#180.#198;	//  scala/collection/mutable/GenericArray.array:()[Ljava/lang/Object;
const #200 = Asciz	java/util/Arrays;
const #201 = class	#200;	//  java/util/Arrays
const #202 = Asciz	sort;
const #203 = Asciz	([Ljava/lang/Object;Ljava/util/Comparator;)V;
const #204 = NameAndType	#202:#203;//  sort:([Ljava/lang/Object;Ljava/util/Comparator;)V
const #205 = Method	#201.#204;	//  java/util/Arrays.sort:([Ljava/lang/Object;Ljava/util/Comparator;)V
const #206 = Asciz	newBuilder;
const #207 = Asciz	()Lscala/collection/mutable/Builder;;
const #208 = NameAndType	#206:#207;//  newBuilder:()Lscala/collection/mutable/Builder;
const #209 = InterfaceMethod	#115.#208;	//  scala/collection/TraversableLike.newBuilder:()Lscala/collection/mutable/Builder;
const #210 = Asciz	scala/collection/SeqLike$$anonfun$sortWith$2;
const #211 = class	#210;	//  scala/collection/SeqLike$$anonfun$sortWith$2
const #212 = Asciz	(Lscala/collection/SeqLike;Lscala/collection/mutable/Builder;)V;
const #213 = NameAndType	#88:#212;//  "<init>":(Lscala/collection/SeqLike;Lscala/collection/mutable/Builder;)V
const #214 = Method	#211.#213;	//  scala/collection/SeqLike$$anonfun$sortWith$2."<init>":(Lscala/collection/SeqLike;Lscala/collection/mutable/Builder;)V
const #215 = Method	#180.#194;	//  scala/collection/mutable/GenericArray.foreach:(Lscala/Function1;)V
const #216 = Asciz	scala/collection/mutable/Builder;
const #217 = class	#216;	//  scala/collection/mutable/Builder
const #218 = Asciz	result;
const #219 = NameAndType	#218:#15;//  result:()Ljava/lang/Object;
const #220 = InterfaceMethod	#217.#219;	//  scala/collection/mutable/Builder.result:()Ljava/lang/Object;
const #221 = Asciz	arr$1;
const #222 = Asciz	Lscala/collection/mutable/GenericArray;;
const #223 = Asciz	i$2;
const #224 = Asciz	Lscala/runtime/IntRef;;
const #225 = Asciz	b$6;
const #226 = Asciz	Lscala/collection/mutable/Builder;;
const #227 = Asciz	(Lscala/collection/SeqLike;Lscala/Function2;)Ljava/lang/Object;;
const #228 = Asciz	scala/math/Ordering$$anon$4;
const #229 = class	#228;	//  scala/math/Ordering$$anon$4
const #230 = Asciz	(Lscala/Function2;)V;
const #231 = NameAndType	#88:#230;//  "<init>":(Lscala/Function2;)V
const #232 = Method	#229.#231;	//  scala/math/Ordering$$anon$4."<init>":(Lscala/Function2;)V
const #233 = Asciz	lt;
const #234 = Asciz	corresponds;
const #235 = Asciz	padTo;
const #236 = Asciz	(Lscala/collection/SeqLike;ILjava/lang/Object;Lscala/collection/generic/CanBuildFrom;)Ljava/lang/Object;;
const #237 = Asciz	repr;
const #238 = NameAndType	#237:#15;//  repr:()Ljava/lang/Object;
const #239 = InterfaceMethod	#115.#238;	//  scala/collection/TraversableLike.repr:()Ljava/lang/Object;
const #240 = Asciz	scala/collection/generic/CanBuildFrom;
const #241 = class	#240;	//  scala/collection/generic/CanBuildFrom
const #242 = Asciz	(Ljava/lang/Object;)Lscala/collection/mutable/Builder;;
const #243 = NameAndType	#38:#242;//  apply:(Ljava/lang/Object;)Lscala/collection/mutable/Builder;
const #244 = InterfaceMethod	#241.#243;	//  scala/collection/generic/CanBuildFrom.apply:(Ljava/lang/Object;)Lscala/collection/mutable/Builder;
const #245 = Method	#154.#182;	//  scala/runtime/RichInt."<init>":(I)V
const #246 = Asciz	max;
const #247 = Asciz	(I)I;
const #248 = NameAndType	#246:#247;//  max:(I)I
const #249 = Method	#154.#248;	//  scala/runtime/RichInt.max:(I)I
const #250 = Asciz	sizeHint;
const #251 = NameAndType	#250:#181;//  sizeHint:(I)V
const #252 = InterfaceMethod	#217.#251;	//  scala/collection/mutable/Builder.sizeHint:(I)V
const #253 = Asciz	scala/collection/generic/Growable;
const #254 = class	#253;	//  scala/collection/generic/Growable
const #255 = Asciz	$plus$plus$eq;
const #256 = Asciz	(Lscala/collection/Traversable;)Lscala/collection/generic/Growable;;
const #257 = NameAndType	#255:#256;//  $plus$plus$eq:(Lscala/collection/Traversable;)Lscala/collection/generic/Growable;
const #258 = InterfaceMethod	#254.#257;	//  scala/collection/generic/Growable.$plus$plus$eq:(Lscala/collection/Traversable;)Lscala/collection/generic/Growable;
const #259 = Asciz	$plus$eq;
const #260 = NameAndType	#259:#242;//  $plus$eq:(Ljava/lang/Object;)Lscala/collection/mutable/Builder;
const #261 = InterfaceMethod	#217.#260;	//  scala/collection/mutable/Builder.$plus$eq:(Ljava/lang/Object;)Lscala/collection/mutable/Builder;
const #262 = Asciz	len;
const #263 = Asciz	elem;
const #264 = Asciz	bf;
const #265 = Asciz	Lscala/collection/generic/CanBuildFrom;;
const #266 = Asciz	diff;
const #267 = Asciz	b;
const #268 = Asciz	$colon$plus;
const #269 = Asciz	(Lscala/collection/SeqLike;Ljava/lang/Object;Lscala/collection/generic/CanBuildFrom;)Ljava/lang/Object;;
const #270 = Asciz	$plus$colon;
const #271 = Asciz	updated;
const #272 = Asciz	splitAt;
const #273 = Asciz	(I)Lscala/Tuple2;;
const #274 = NameAndType	#272:#273;//  splitAt:(I)Lscala/Tuple2;
const #275 = InterfaceMethod	#115.#274;	//  scala/collection/TraversableLike.splitAt:(I)Lscala/Tuple2;
const #276 = Asciz	scala/Tuple2;
const #277 = class	#276;	//  scala/Tuple2
const #278 = Asciz	_1;
const #279 = NameAndType	#278:#15;//  _1:()Ljava/lang/Object;
const #280 = Method	#277.#279;	//  scala/Tuple2._1:()Ljava/lang/Object;
const #281 = Asciz	_2;
const #282 = NameAndType	#281:#15;//  _2:()Ljava/lang/Object;
const #283 = Method	#277.#282;	//  scala/Tuple2._2:()Ljava/lang/Object;
const #284 = Asciz	(Ljava/lang/Object;Ljava/lang/Object;)V;
const #285 = NameAndType	#88:#284;//  "<init>":(Ljava/lang/Object;Ljava/lang/Object;)V
const #286 = Method	#277.#285;	//  scala/Tuple2."<init>":(Ljava/lang/Object;Ljava/lang/Object;)V
const #287 = Asciz	toCollection;
const #288 = Asciz	(Ljava/lang/Object;)Lscala/collection/Seq;;
const #289 = NameAndType	#287:#288;//  toCollection:(Ljava/lang/Object;)Lscala/collection/Seq;
const #290 = InterfaceMethod	#13.#289;	//  scala/collection/SeqLike.toCollection:(Ljava/lang/Object;)Lscala/collection/Seq;
const #291 = Asciz	tail;
const #292 = NameAndType	#291:#15;//  tail:()Ljava/lang/Object;
const #293 = InterfaceMethod	#115.#292;	//  scala/collection/TraversableLike.tail:()Ljava/lang/Object;
const #294 = Asciz	scala/collection/Traversable;
const #295 = class	#294;	//  scala/collection/Traversable
const #296 = Method	#277.#86;	//  scala/Tuple2.toString:()Ljava/lang/String;
const #297 = Asciz	index;
const #298 = Asciz	temp14;
const #299 = Asciz	temp15;
const #300 = Asciz	prefix;
const #301 = Asciz	rest;
const #302 = Asciz	temp13;
const #303 = Asciz	Lscala/Tuple2;;
const #304 = Asciz	patch;
const #305 = Asciz	(Lscala/collection/SeqLike;ILscala/collection/Seq;ILscala/collection/generic/CanBuildFrom;)Ljava/lang/Object;;
const #306 = Asciz	drop;
const #307 = Asciz	(I)Lscala/collection/TraversableView;;
const #308 = NameAndType	#306:#307;//  drop:(I)Lscala/collection/TraversableView;
const #309 = InterfaceMethod	#126.#308;	//  scala/collection/TraversableViewLike.drop:(I)Lscala/collection/TraversableView;
const #310 = Asciz	replaced;
const #311 = Asciz	temp11;
const #312 = Asciz	temp12;
const #313 = Asciz	temp10;
const #314 = Asciz	removeDuplicates;
const #315 = Asciz	scala/runtime/ObjectRef;
const #316 = class	#315;	//  scala/runtime/ObjectRef
const #317 = Asciz	scala/collection/Set$;
const #318 = class	#317;	//  scala/collection/Set$
const #319 = Asciz	Lscala/collection/Set$;;
const #320 = NameAndType	#98:#319;//  MODULE$:Lscala/collection/Set$;
const #321 = Field	#318.#320;	//  scala/collection/Set$.MODULE$:Lscala/collection/Set$;
const #322 = Asciz	genericWrapArray;
const #323 = Asciz	(Ljava/lang/Object;)Lscala/collection/mutable/WrappedArray;;
const #324 = NameAndType	#322:#323;//  genericWrapArray:(Ljava/lang/Object;)Lscala/collection/mutable/WrappedArray;
const #325 = Method	#142.#324;	//  scala/Predef$.genericWrapArray:(Ljava/lang/Object;)Lscala/collection/mutable/WrappedArray;
const #326 = Asciz	(Lscala/collection/Seq;)Lscala/collection/Traversable;;
const #327 = NameAndType	#38:#326;//  apply:(Lscala/collection/Seq;)Lscala/collection/Traversable;
const #328 = Method	#318.#327;	//  scala/collection/Set$.apply:(Lscala/collection/Seq;)Lscala/collection/Traversable;
const #329 = Asciz	scala/collection/Set;
const #330 = class	#329;	//  scala/collection/Set
const #331 = Asciz	(Ljava/lang/Object;)V;
const #332 = NameAndType	#88:#331;//  "<init>":(Ljava/lang/Object;)V
const #333 = Method	#316.#332;	//  scala/runtime/ObjectRef."<init>":(Ljava/lang/Object;)V
const #334 = Asciz	scala/collection/SeqLike$$anonfun$removeDuplicates$1;
const #335 = class	#334;	//  scala/collection/SeqLike$$anonfun$removeDuplicates$1
const #336 = Asciz	(Lscala/collection/SeqLike;Lscala/collection/mutable/Builder;Lscala/runtime/ObjectRef;)V;
const #337 = NameAndType	#88:#336;//  "<init>":(Lscala/collection/SeqLike;Lscala/collection/mutable/Builder;Lscala/runtime/ObjectRef;)V
const #338 = Method	#335.#337;	//  scala/collection/SeqLike$$anonfun$removeDuplicates$1."<init>":(Lscala/collection/SeqLike;Lscala/collection/mutable/Builder;Lscala/runtime/ObjectRef;)V
const #339 = Asciz	b$5;
const #340 = Asciz	seen$1;
const #341 = Asciz	Lscala/runtime/ObjectRef;;
const #342 = Asciz	occCounts;
const #343 = Asciz	(Lscala/collection/SeqLike;Lscala/collection/Seq;)Lscala/collection/mutable/Map;;
const #344 = Asciz	scala/collection/SeqLike$$anon$1;
const #345 = class	#344;	//  scala/collection/SeqLike$$anon$1
const #346 = Method	#345.#112;	//  scala/collection/SeqLike$$anon$1."<init>":(Lscala/collection/SeqLike;)V
const #347 = Asciz	scala/collection/SeqLike$$anonfun$occCounts$1;
const #348 = class	#347;	//  scala/collection/SeqLike$$anonfun$occCounts$1
const #349 = Asciz	(Lscala/collection/SeqLike;Lscala/collection/mutable/HashMap;)V;
const #350 = NameAndType	#88:#349;//  "<init>":(Lscala/collection/SeqLike;Lscala/collection/mutable/HashMap;)V
const #351 = Method	#348.#350;	//  scala/collection/SeqLike$$anonfun$occCounts$1."<init>":(Lscala/collection/SeqLike;Lscala/collection/mutable/HashMap;)V
const #352 = Asciz	seq;
const #353 = Asciz	occ$3;
const #354 = Asciz	Lscala/collection/mutable/HashMap;;
const #355 = Asciz	intersect;
const #356 = Asciz	(Lscala/collection/SeqLike;Lscala/collection/Seq;)Ljava/lang/Object;;
const #357 = Asciz	scala/collection/SeqLike$class;
const #358 = class	#357;	//  scala/collection/SeqLike$class
const #359 = NameAndType	#342:#343;//  occCounts:(Lscala/collection/SeqLike;Lscala/collection/Seq;)Lscala/collection/mutable/Map;
const #360 = Method	#358.#359;	//  scala/collection/SeqLike$class.occCounts:(Lscala/collection/SeqLike;Lscala/collection/Seq;)Lscala/collection/mutable/Map;
const #361 = Asciz	scala/collection/SeqLike$$anonfun$intersect$1;
const #362 = class	#361;	//  scala/collection/SeqLike$$anonfun$intersect$1
const #363 = Asciz	(Lscala/collection/SeqLike;Lscala/collection/mutable/Map;Lscala/collection/mutable/Builder;)V;
const #364 = NameAndType	#88:#363;//  "<init>":(Lscala/collection/SeqLike;Lscala/collection/mutable/Map;Lscala/collection/mutable/Builder;)V
const #365 = Method	#362.#364;	//  scala/collection/SeqLike$$anonfun$intersect$1."<init>":(Lscala/collection/SeqLike;Lscala/collection/mutable/Map;Lscala/collection/mutable/Builder;)V
const #366 = Asciz	occ$2;
const #367 = Asciz	Lscala/collection/mutable/Map;;
const #368 = Asciz	b$4;
const #369 = Asciz	scala/collection/SeqLike$$anonfun$diff$1;
const #370 = class	#369;	//  scala/collection/SeqLike$$anonfun$diff$1
const #371 = Method	#370.#364;	//  scala/collection/SeqLike$$anonfun$diff$1."<init>":(Lscala/collection/SeqLike;Lscala/collection/mutable/Map;Lscala/collection/mutable/Builder;)V
const #372 = Asciz	occ$1;
const #373 = Asciz	b$3;
const #374 = Asciz	union;
const #375 = Asciz	(Lscala/collection/SeqLike;Lscala/collection/Seq;Lscala/collection/generic/CanBuildFrom;)Ljava/lang/Object;;
const #376 = Asciz	$plus$plus;
const #377 = Asciz	(Lscala/collection/Traversable;Lscala/collection/generic/CanBuildFrom;)Ljava/lang/Object;;
const #378 = NameAndType	#376:#377;//  $plus$plus:(Lscala/collection/Traversable;Lscala/collection/generic/CanBuildFrom;)Ljava/lang/Object;
const #379 = InterfaceMethod	#115.#378;	//  scala/collection/TraversableLike.$plus$plus:(Lscala/collection/Traversable;Lscala/collection/generic/CanBuildFrom;)Ljava/lang/Object;
const #380 = Asciz	contains;
const #381 = Asciz	scala/collection/SeqLike$$anonfun$contains$1;
const #382 = class	#381;	//  scala/collection/SeqLike$$anonfun$contains$1
const #383 = Asciz	(Lscala/collection/SeqLike;Ljava/lang/Object;)V;
const #384 = NameAndType	#88:#383;//  "<init>":(Lscala/collection/SeqLike;Ljava/lang/Object;)V
const #385 = Method	#382.#384;	//  scala/collection/SeqLike$$anonfun$contains$1."<init>":(Lscala/collection/SeqLike;Ljava/lang/Object;)V
const #386 = Asciz	exists;
const #387 = Asciz	(Lscala/Function1;)Z;
const #388 = NameAndType	#386:#387;//  exists:(Lscala/Function1;)Z
const #389 = InterfaceMethod	#22.#388;	//  scala/collection/IterableLike.exists:(Lscala/Function1;)Z
const #390 = Asciz	elem$4;
const #391 = Asciz	containsSlice;
const #392 = Asciz	(Lscala/collection/SeqLike;Lscala/collection/Seq;)Z;
const #393 = Asciz	indexOfSlice;
const #394 = Asciz	(Lscala/collection/Seq;)I;
const #395 = NameAndType	#393:#394;//  indexOfSlice:(Lscala/collection/Seq;)I
const #396 = InterfaceMethod	#13.#395;	//  scala/collection/SeqLike.indexOfSlice:(Lscala/collection/Seq;)I
const #397 = Asciz	lastIndexOfSlice;
const #398 = Asciz	(Lscala/collection/SeqLike;Lscala/collection/Seq;I)I;
const #399 = Asciz	scala/collection/SeqLike$;
const #400 = class	#399;	//  scala/collection/SeqLike$
const #401 = Asciz	Lscala/collection/SeqLike$;;
const #402 = NameAndType	#98:#401;//  MODULE$:Lscala/collection/SeqLike$;
const #403 = Field	#400.#402;	//  scala/collection/SeqLike$.MODULE$:Lscala/collection/SeqLike$;
const #404 = Asciz	lastIndexOf;
const #405 = Asciz	(Lscala/collection/Seq;IILscala/collection/Seq;III)I;
const #406 = NameAndType	#404:#405;//  lastIndexOf:(Lscala/collection/Seq;IILscala/collection/Seq;III)I
const #407 = Method	#400.#406;	//  scala/collection/SeqLike$.lastIndexOf:(Lscala/collection/Seq;IILscala/collection/Seq;III)I
const #408 = Asciz	end;
const #409 = Asciz	(Lscala/collection/SeqLike;Lscala/collection/Seq;)I;
const #410 = Asciz	(Lscala/collection/Seq;I)I;
const #411 = NameAndType	#397:#410;//  lastIndexOfSlice:(Lscala/collection/Seq;I)I
const #412 = InterfaceMethod	#13.#411;	//  scala/collection/SeqLike.lastIndexOfSlice:(Lscala/collection/Seq;I)I
const #413 = Asciz	hasDefiniteSize;
const #414 = NameAndType	#413:#30;//  hasDefiniteSize:()Z
const #415 = InterfaceMethod	#115.#414;	//  scala/collection/TraversableLike.hasDefiniteSize:()Z
const #416 = Asciz	indexOf;
const #417 = NameAndType	#416:#405;//  indexOf:(Lscala/collection/Seq;IILscala/collection/Seq;III)I
const #418 = Method	#400.#417;	//  scala/collection/SeqLike$.indexOf:(Lscala/collection/Seq;IILscala/collection/Seq;III)I
const #419 = Asciz	(I)Ljava/lang/Object;;
const #420 = NameAndType	#306:#419;//  drop:(I)Ljava/lang/Object;
const #421 = InterfaceMethod	#115.#420;	//  scala/collection/TraversableLike.drop:(I)Ljava/lang/Object;
const #422 = Asciz	isEmpty;
const #423 = NameAndType	#422:#30;//  isEmpty:()Z
const #424 = InterfaceMethod	#22.#423;	//  scala/collection/IterableLike.isEmpty:()Z
const #425 = Asciz	startsWith;
const #426 = Asciz	(Lscala/collection/Seq;)Z;
const #427 = NameAndType	#425:#426;//  startsWith:(Lscala/collection/Seq;)Z
const #428 = InterfaceMethod	#13.#427;	//  scala/collection/SeqLike.startsWith:(Lscala/collection/Seq;)Z
const #429 = Asciz	s;
const #430 = NameAndType	#393:#410;//  indexOfSlice:(Lscala/collection/Seq;I)I
const #431 = InterfaceMethod	#13.#430;	//  scala/collection/SeqLike.indexOfSlice:(Lscala/collection/Seq;I)I
const #432 = Asciz	endsWith;
const #433 = Asciz	(I)Lscala/collection/Iterator;;
const #434 = NameAndType	#306:#433;//  drop:(I)Lscala/collection/Iterator;
const #435 = InterfaceMethod	#28.#434;	//  scala/collection/Iterator.drop:(I)Lscala/collection/Iterator;
const #436 = Asciz	java/lang/Number;
const #437 = class	#436;	//  java/lang/Number
const #438 = Asciz	java/lang/Character;
const #439 = class	#438;	//  java/lang/Character
const #440 = Asciz	equals2;
const #441 = Asciz	(Ljava/lang/Object;Ljava/lang/Object;)Z;
const #442 = NameAndType	#440:#441;//  equals2:(Ljava/lang/Object;Ljava/lang/Object;)Z
const #443 = Method	#43.#442;	//  scala/runtime/BoxesRunTime.equals2:(Ljava/lang/Object;Ljava/lang/Object;)Z
const #444 = NameAndType	#70:#45;//  equals:(Ljava/lang/Object;)Z
const #445 = Method	#84.#444;	//  java/lang/Object.equals:(Ljava/lang/Object;)Z
const #446 = Asciz	x0;
const #447 = Asciz	y0;
const #448 = Asciz	(Lscala/collection/Seq;I)Z;
const #449 = NameAndType	#425:#448;//  startsWith:(Lscala/collection/Seq;I)Z
const #450 = InterfaceMethod	#13.#449;	//  scala/collection/SeqLike.startsWith:(Lscala/collection/Seq;I)Z
const #451 = Asciz	(Lscala/collection/SeqLike;Lscala/collection/Seq;I)Z;
const #452 = Asciz	offset;
const #453 = Asciz	reversedElements;
const #454 = Asciz	(Lscala/collection/SeqLike;)Lscala/collection/Iterator;;
const #455 = Asciz	reverseIterator;
const #456 = NameAndType	#455:#24;//  reverseIterator:()Lscala/collection/Iterator;
const #457 = InterfaceMethod	#13.#456;	//  scala/collection/SeqLike.reverseIterator:()Lscala/collection/Iterator;
const #458 = Asciz	reverse;
const #459 = NameAndType	#458:#15;//  reverse:()Ljava/lang/Object;
const #460 = InterfaceMethod	#13.#459;	//  scala/collection/SeqLike.reverse:()Ljava/lang/Object;
const #461 = Asciz	reverseMap;
const #462 = Asciz	(Lscala/collection/SeqLike;Lscala/Function1;Lscala/collection/generic/CanBuildFrom;)Ljava/lang/Object;;
const #463 = Asciz	scala/collection/immutable/Nil$;
const #464 = class	#463;	//  scala/collection/immutable/Nil$
const #465 = Asciz	Lscala/collection/immutable/Nil$;;
const #466 = NameAndType	#98:#465;//  MODULE$:Lscala/collection/immutable/Nil$;
const #467 = Field	#464.#466;	//  scala/collection/immutable/Nil$.MODULE$:Lscala/collection/immutable/Nil$;
const #468 = Asciz	scala/collection/SeqLike$$anonfun$reverseMap$1;
const #469 = class	#468;	//  scala/collection/SeqLike$$anonfun$reverseMap$1
const #470 = Asciz	(Lscala/collection/SeqLike;Lscala/runtime/ObjectRef;)V;
const #471 = NameAndType	#88:#470;//  "<init>":(Lscala/collection/SeqLike;Lscala/runtime/ObjectRef;)V
const #472 = Method	#469.#471;	//  scala/collection/SeqLike$$anonfun$reverseMap$1."<init>":(Lscala/collection/SeqLike;Lscala/runtime/ObjectRef;)V
const #473 = NameAndType	#263:#92;//  elem:Ljava/lang/Object;
const #474 = Field	#316.#473;	//  scala/runtime/ObjectRef.elem:Ljava/lang/Object;
const #475 = Asciz	scala/collection/immutable/List;
const #476 = class	#475;	//  scala/collection/immutable/List
const #477 = Asciz	scala/collection/SeqLike$$anonfun$reverseMap$2;
const #478 = class	#477;	//  scala/collection/SeqLike$$anonfun$reverseMap$2
const #479 = Asciz	(Lscala/collection/SeqLike;Lscala/Function1;Lscala/collection/mutable/Builder;)V;
const #480 = NameAndType	#88:#479;//  "<init>":(Lscala/collection/SeqLike;Lscala/Function1;Lscala/collection/mutable/Builder;)V
const #481 = Method	#478.#480;	//  scala/collection/SeqLike$$anonfun$reverseMap$2."<init>":(Lscala/collection/SeqLike;Lscala/Function1;Lscala/collection/mutable/Builder;)V
const #482 = Asciz	scala/collection/LinearSeqLike;
const #483 = class	#482;	//  scala/collection/LinearSeqLike
const #484 = InterfaceMethod	#483.#194;	//  scala/collection/LinearSeqLike.foreach:(Lscala/Function1;)V
const #485 = Asciz	f$1;
const #486 = Asciz	xs$2;
const #487 = Asciz	b$2;
const #488 = Asciz	scala/collection/SeqLike$$anonfun$reverse$1;
const #489 = class	#488;	//  scala/collection/SeqLike$$anonfun$reverse$1
const #490 = Method	#489.#471;	//  scala/collection/SeqLike$$anonfun$reverse$1."<init>":(Lscala/collection/SeqLike;Lscala/runtime/ObjectRef;)V
const #491 = Asciz	scala/collection/SeqLike$$anonfun$reverse$2;
const #492 = class	#491;	//  scala/collection/SeqLike$$anonfun$reverse$2
const #493 = Method	#492.#213;	//  scala/collection/SeqLike$$anonfun$reverse$2."<init>":(Lscala/collection/SeqLike;Lscala/collection/mutable/Builder;)V
const #494 = Asciz	xs$1;
const #495 = Asciz	b$1;
const #496 = Asciz	(Lscala/collection/SeqLike;Lscala/Function1;I)I;
const #497 = Asciz	scala/Function1;
const #498 = class	#497;	//  scala/Function1
const #499 = Asciz	(Ljava/lang/Object;)Ljava/lang/Object;;
const #500 = NameAndType	#38:#499;//  apply:(Ljava/lang/Object;)Ljava/lang/Object;
const #501 = InterfaceMethod	#498.#500;	//  scala/Function1.apply:(Ljava/lang/Object;)Ljava/lang/Object;
const #502 = Asciz	it;
const #503 = Asciz	(Lscala/Function1;I)I;
const #504 = NameAndType	#57:#503;//  lastIndexWhere:(Lscala/Function1;I)I
const #505 = InterfaceMethod	#13.#504;	//  scala/collection/SeqLike.lastIndexWhere:(Lscala/Function1;I)I
const #506 = Asciz	(Lscala/collection/SeqLike;Ljava/lang/Object;I)I;
const #507 = Asciz	scala/collection/SeqLike$$anonfun$lastIndexOf$2;
const #508 = class	#507;	//  scala/collection/SeqLike$$anonfun$lastIndexOf$2
const #509 = Method	#508.#384;	//  scala/collection/SeqLike$$anonfun$lastIndexOf$2."<init>":(Lscala/collection/SeqLike;Ljava/lang/Object;)V
const #510 = Asciz	elem$3;
const #511 = Asciz	(Lscala/collection/SeqLike;Ljava/lang/Object;)I;
const #512 = Asciz	scala/collection/SeqLike$$anonfun$lastIndexOf$1;
const #513 = class	#512;	//  scala/collection/SeqLike$$anonfun$lastIndexOf$1
const #514 = Method	#513.#384;	//  scala/collection/SeqLike$$anonfun$lastIndexOf$1."<init>":(Lscala/collection/SeqLike;Ljava/lang/Object;)V
const #515 = Asciz	elem$2;
const #516 = Asciz	scala/collection/SeqLike$$anonfun$indexOf$1;
const #517 = class	#516;	//  scala/collection/SeqLike$$anonfun$indexOf$1
const #518 = Method	#517.#384;	//  scala/collection/SeqLike$$anonfun$indexOf$1."<init>":(Lscala/collection/SeqLike;Ljava/lang/Object;)V
const #519 = Asciz	indexWhere;
const #520 = NameAndType	#519:#503;//  indexWhere:(Lscala/Function1;I)I
const #521 = InterfaceMethod	#13.#520;	//  scala/collection/SeqLike.indexWhere:(Lscala/Function1;I)I
const #522 = Asciz	elem$1;
const #523 = Asciz	(Ljava/lang/Object;I)I;
const #524 = NameAndType	#416:#523;//  indexOf:(Ljava/lang/Object;I)I
const #525 = InterfaceMethod	#13.#524;	//  scala/collection/SeqLike.indexOf:(Ljava/lang/Object;I)I
const #526 = Asciz	findIndexOf;
const #527 = NameAndType	#519:#58;//  indexWhere:(Lscala/Function1;)I
const #528 = InterfaceMethod	#13.#527;	//  scala/collection/SeqLike.indexWhere:(Lscala/Function1;)I
const #529 = Asciz	prefixLength;
const #530 = Asciz	segmentLength;
const #531 = NameAndType	#530:#503;//  segmentLength:(Lscala/Function1;I)I
const #532 = InterfaceMethod	#13.#531;	//  scala/collection/SeqLike.segmentLength:(Lscala/Function1;I)I
const #533 = Asciz	isDefinedAt;
const #534 = Asciz	(Lscala/collection/SeqLike;I)Z;
const #535 = Asciz	idx;
const #536 = Asciz	size;
const #537 = Asciz	lengthCompare;
const #538 = Asciz	(Lscala/collection/SeqLike;I)I;
const #539 = Asciz	(Lscala/collection/SeqLike;Ljava/lang/Object;)Lscala/collection/Seq;;
const #540 = Asciz	Scala;
const #541 = Asciz	InnerClasses;
const #542 = Asciz	$anon$1;
const #543 = Asciz	$anon$2;
const #544 = Asciz	$anon$4;
const #545 = Asciz	$anonfun$diff$1;
const #546 = Asciz	$anonfun$indexOf$1;
const #547 = Asciz	$anonfun$reverse$2;
const #548 = Asciz	$anonfun$reverse$1;
const #549 = Asciz	$anonfun$contains$1;
const #550 = Asciz	$anonfun$sortWith$2;
const #551 = Asciz	$anonfun$sortWith$1;
const #552 = Asciz	$anonfun$hashCode$1;
const #553 = Asciz	$anonfun$intersect$1;
const #554 = Asciz	$anonfun$occCounts$1;
const #555 = Asciz	$anonfun$reverseMap$2;
const #556 = Asciz	$anonfun$reverseMap$1;
const #557 = Asciz	$anonfun$lastIndexOf$1;
const #558 = Asciz	$anonfun$lastIndexOf$2;
const #559 = Asciz	$anonfun$removeDuplicates$1;

{
public static void $init$(scala.collection.SeqLike);
  Code:
   Stack=0, Locals=1, Args_size=1
   0:	return
  LineNumberTable: 
   line 153: 0

  LocalVariableTable: 
   Start  Length  Slot  Name   Signature
   0      1      0    $this       Lscala/collection/SeqLike;


public static java.lang.Object projection(scala.collection.SeqLike);
  Code:
   Stack=1, Locals=1, Args_size=1
   0:	aload_0
   1:	invokeinterface	#17,  1; //InterfaceMethod scala/collection/SeqLike.view:()Ljava/lang/Object;
   6:	areturn
  LineNumberTable: 
   line 881: 0

  LocalVariableTable: 
   Start  Length  Slot  Name   Signature
   0      7      0    $this       Lscala/collection/SeqLike;

  Deprecated: true

public static boolean equalsWith(scala.collection.SeqLike, scala.collection.Seq, scala.Function2);
  Code:
   Stack=3, Locals=5, Args_size=3
   0:	aload_0
   1:	invokeinterface	#26,  1; //InterfaceMethod scala/collection/IterableLike.iterator:()Lscala/collection/Iterator;
   6:	astore_3
   7:	aload_1
   8:	invokeinterface	#26,  1; //InterfaceMethod scala/collection/IterableLike.iterator:()Lscala/collection/Iterator;
   13:	astore	4
   15:	aload_3
   16:	invokeinterface	#32,  1; //InterfaceMethod scala/collection/Iterator.hasNext:()Z
   21:	ifeq	61
   24:	aload	4
   26:	invokeinterface	#32,  1; //InterfaceMethod scala/collection/Iterator.hasNext:()Z
   31:	ifeq	61
   34:	aload_2
   35:	aload_3
   36:	invokeinterface	#35,  1; //InterfaceMethod scala/collection/Iterator.next:()Ljava/lang/Object;
   41:	aload	4
   43:	invokeinterface	#35,  1; //InterfaceMethod scala/collection/Iterator.next:()Ljava/lang/Object;
   48:	invokeinterface	#41,  3; //InterfaceMethod scala/Function2.apply:(Ljava/lang/Object;Ljava/lang/Object;)Ljava/lang/Object;
   53:	invokestatic	#47; //Method scala/runtime/BoxesRunTime.unboxToBoolean:(Ljava/lang/Object;)Z
   56:	ifne	15
   59:	iconst_0
   60:	ireturn
   61:	aload_3
   62:	invokeinterface	#32,  1; //InterfaceMethod scala/collection/Iterator.hasNext:()Z
   67:	ifne	80
   70:	aload	4
   72:	invokeinterface	#32,  1; //InterfaceMethod scala/collection/Iterator.hasNext:()Z
   77:	ifeq	84
   80:	iconst_0
   81:	goto	85
   84:	iconst_1
   85:	ireturn
  LineNumberTable: 
   line 866: 0
   line 867: 7
   line 868: 15
   line 869: 34
   line 870: 59
   line 872: 61
   line 865: 85

  LocalVariableTable: 
   Start  Length  Slot  Name   Signature
   0      86      0    $this       Lscala/collection/SeqLike;
   0      86      1    that       Lscala/collection/Seq;
   0      86      2    f       Lscala/Function2;
   7      79      3    i       Lscala/collection/Iterator;
   15      71      4    j       Lscala/collection/Iterator;

  Deprecated: true

public static int findLastIndexOf(scala.collection.SeqLike, scala.Function1);
  Code:
   Stack=2, Locals=2, Args_size=2
   0:	aload_0
   1:	aload_1
   2:	invokeinterface	#60,  2; //InterfaceMethod scala/collection/SeqLike.lastIndexWhere:(Lscala/Function1;)I
   7:	ireturn
  LineNumberTable: 
   line 852: 0

  LocalVariableTable: 
   Start  Length  Slot  Name   Signature
   0      8      0    $this       Lscala/collection/SeqLike;
   0      8      1    p       Lscala/Function1;


public static java.lang.String toString(scala.collection.SeqLike);
  Code:
   Stack=1, Locals=1, Args_size=1
   0:	aload_0
   1:	invokestatic	#69; //Method scala/collection/TraversableLike$class.toString:(Lscala/collection/TraversableLike;)Ljava/lang/String;
   4:	areturn
  LineNumberTable: 
   line 848: 0

  LocalVariableTable: 
   Start  Length  Slot  Name   Signature
   0      5      0    $this       Lscala/collection/SeqLike;


public static boolean equals(scala.collection.SeqLike, java.lang.Object);
  Code:
   Stack=3, Locals=3, Args_size=2
   0:	aload_1
   1:	instanceof	#73; //class scala/collection/Seq
   4:	ifeq	56
   7:	aload_1
   8:	checkcast	#73; //class scala/collection/Seq
   11:	astore_2
   12:	iconst_1
   13:	ifeq	44
   16:	aload_2
   17:	aload_0
   18:	invokeinterface	#76,  2; //InterfaceMethod scala/collection/IterableLike.canEqual:(Ljava/lang/Object;)Z
   23:	ifeq	40
   26:	aload_0
   27:	aload_2
   28:	invokeinterface	#80,  2; //InterfaceMethod scala/collection/IterableLike.sameElements:(Lscala/collection/Iterable;)Z
   33:	ifeq	40
   36:	iconst_1
   37:	goto	61
   40:	iconst_0
   41:	goto	61
   44:	new	#82; //class scala/MatchError
   47:	dup
   48:	aload_1
   49:	invokevirtual	#87; //Method java/lang/Object.toString:()Ljava/lang/String;
   52:	invokespecial	#91; //Method scala/MatchError."<init>":(Ljava/lang/String;)V
   55:	athrow
   56:	iconst_1
   57:	ifeq	62
   60:	iconst_0
   61:	ireturn
   62:	new	#82; //class scala/MatchError
   65:	dup
   66:	aload_1
   67:	invokevirtual	#87; //Method java/lang/Object.toString:()Ljava/lang/String;
   70:	invokespecial	#91; //Method scala/MatchError."<init>":(Ljava/lang/String;)V
   73:	athrow
  LineNumberTable: 
   line 841: 0
   line 21: 12
   line 842: 16
   line 841: 44
   line 21: 56
   line 843: 60
   line 841: 61

  LocalVariableTable: 
   Start  Length  Slot  Name   Signature
   0      74      0    $this       Lscala/collection/SeqLike;
   0      74      1    that       Ljava/lang/Object;
   12      44      2    temp17       Lscala/collection/Seq;


public static int hashCode(scala.collection.SeqLike);
  Code:
   Stack=5, Locals=2, Args_size=1
   0:	getstatic	#101; //Field scala/collection/Seq$.MODULE$:Lscala/collection/Seq$;
   3:	invokevirtual	#105; //Method scala/collection/Seq$.hashSeed:()I
   6:	istore_1
   7:	aload_0
   8:	iload_1
   9:	invokestatic	#109; //Method scala/runtime/BoxesRunTime.boxToInteger:(I)Ljava/lang/Integer;
   12:	new	#111; //class scala/collection/SeqLike$$anonfun$hashCode$1
   15:	dup
   16:	aload_0
   17:	invokespecial	#113; //Method scala/collection/SeqLike$$anonfun$hashCode$1."<init>":(Lscala/collection/SeqLike;)V
   20:	invokeinterface	#119,  3; //InterfaceMethod scala/collection/TraversableLike.$div$colon:(Ljava/lang/Object;Lscala/Function2;)Ljava/lang/Object;
   25:	invokestatic	#123; //Method scala/runtime/BoxesRunTime.unboxToInt:(Ljava/lang/Object;)I
   28:	ireturn
  LineNumberTable: 
   line 839: 0

  LocalVariableTable: 
   Start  Length  Slot  Name   Signature
   0      29      0    $this       Lscala/collection/SeqLike;


public static scala.collection.SeqView view(scala.collection.SeqLike, int, int);
  Code:
   Stack=3, Locals=3, Args_size=3
   0:	aload_0
   1:	invokeinterface	#17,  1; //InterfaceMethod scala/collection/SeqLike.view:()Ljava/lang/Object;
   6:	checkcast	#126; //class scala/collection/TraversableViewLike
   9:	iload_1
   10:	iload_2
   11:	invokeinterface	#130,  3; //InterfaceMethod scala/collection/TraversableViewLike.slice:(II)Lscala/collection/TraversableView;
   16:	checkcast	#132; //class scala/collection/SeqView
   19:	areturn
  LineNumberTable: 
   line 834: 0

  LocalVariableTable: 
   Start  Length  Slot  Name   Signature
   0      20      0    $this       Lscala/collection/SeqLike;
   0      20      1    from       I
   0      20      2    until       I


public static java.lang.Object view(scala.collection.SeqLike);
  Code:
   Stack=3, Locals=1, Args_size=1
   0:	new	#137; //class scala/collection/SeqLike$$anon$2
   3:	dup
   4:	aload_0
   5:	invokespecial	#138; //Method scala/collection/SeqLike$$anon$2."<init>":(Lscala/collection/SeqLike;)V
   8:	areturn
  LineNumberTable: 
   line 827: 0

  LocalVariableTable: 
   Start  Length  Slot  Name   Signature
   0      9      0    $this       Lscala/collection/SeqLike;


public static scala.collection.immutable.Range indices(scala.collection.SeqLike);
  Code:
   Stack=2, Locals=1, Args_size=1
   0:	getstatic	#145; //Field scala/Predef$.MODULE$:Lscala/Predef$;
   3:	iconst_0
   4:	invokevirtual	#149; //Method scala/Predef$.intWrapper:(I)Lscala/runtime/RichInt;
   7:	aload_0
   8:	invokeinterface	#152,  1; //InterfaceMethod scala/collection/SeqLike.length:()I
   13:	invokevirtual	#157; //Method scala/runtime/RichInt.until:(I)Lscala/collection/immutable/Range;
   16:	areturn
  LineNumberTable: 
   line 825: 0

  LocalVariableTable: 
   Start  Length  Slot  Name   Signature
   0      17      0    $this       Lscala/collection/SeqLike;


public static scala.collection.Seq toSeq(scala.collection.SeqLike);
  Code:
   Stack=1, Locals=1, Args_size=1
   0:	aload_0
   1:	invokeinterface	#163,  1; //InterfaceMethod scala/collection/SeqLike.thisCollection:()Lscala/collection/Seq;
   6:	areturn
  LineNumberTable: 
   line 819: 0

  LocalVariableTable: 
   Start  Length  Slot  Name   Signature
   0      7      0    $this       Lscala/collection/SeqLike;


public static java.lang.Object sortBy(scala.collection.SeqLike, scala.Function1, scala.math.Ordering);
  Code:
   Stack=3, Locals=3, Args_size=3
   0:	aload_0
   1:	aload_2
   2:	aload_1
   3:	invokeinterface	#171,  2; //InterfaceMethod scala/math/Ordering.on:(Lscala/Function1;)Lscala/math/Ordering;
   8:	invokeinterface	#175,  2; //InterfaceMethod scala/collection/SeqLike.sortWith:(Lscala/math/Ordering;)Ljava/lang/Object;
   13:	areturn
  LineNumberTable: 
   line 812: 0

  LocalVariableTable: 
   Start  Length  Slot  Name   Signature
   0      14      0    $this       Lscala/collection/SeqLike;
   0      14      1    f       Lscala/Function1;
   0      14      2    ord       Lscala/math/Ordering;


public static java.lang.Object sortWith(scala.collection.SeqLike, scala.math.Ordering);
  Code:
   Stack=6, Locals=5, Args_size=2
   0:	new	#180; //class scala/collection/mutable/GenericArray
   3:	dup
   4:	aload_0
   5:	invokeinterface	#152,  1; //InterfaceMethod scala/collection/SeqLike.length:()I
   10:	invokespecial	#183; //Method scala/collection/mutable/GenericArray."<init>":(I)V
   13:	astore_2
   14:	new	#185; //class scala/runtime/IntRef
   17:	dup
   18:	iconst_0
   19:	invokespecial	#186; //Method scala/runtime/IntRef."<init>":(I)V
   22:	astore_3
   23:	aload_0
   24:	new	#188; //class scala/collection/SeqLike$$anonfun$sortWith$1
   27:	dup
   28:	aload_0
   29:	aload_2
   30:	aload_3
   31:	invokespecial	#191; //Method scala/collection/SeqLike$$anonfun$sortWith$1."<init>":(Lscala/collection/SeqLike;Lscala/collection/mutable/GenericArray;Lscala/runtime/IntRef;)V
   34:	invokeinterface	#195,  2; //InterfaceMethod scala/collection/IterableLike.foreach:(Lscala/Function1;)V
   39:	aload_2
   40:	invokevirtual	#199; //Method scala/collection/mutable/GenericArray.array:()[Ljava/lang/Object;
   43:	aload_1
   44:	invokestatic	#205; //Method java/util/Arrays.sort:([Ljava/lang/Object;Ljava/util/Comparator;)V
   47:	aload_0
   48:	invokeinterface	#209,  1; //InterfaceMethod scala/collection/TraversableLike.newBuilder:()Lscala/collection/mutable/Builder;
   53:	astore	4
   55:	aload_2
   56:	new	#211; //class scala/collection/SeqLike$$anonfun$sortWith$2
   59:	dup
   60:	aload_0
   61:	aload	4
   63:	invokespecial	#214; //Method scala/collection/SeqLike$$anonfun$sortWith$2."<init>":(Lscala/collection/SeqLike;Lscala/collection/mutable/Builder;)V
   66:	invokevirtual	#215; //Method scala/collection/mutable/GenericArray.foreach:(Lscala/Function1;)V
   69:	aload	4
   71:	invokeinterface	#220,  1; //InterfaceMethod scala/collection/mutable/Builder.result:()Ljava/lang/Object;
   76:	areturn
  LineNumberTable: 
   line 779: 0
   line 780: 14
   line 781: 23
   line 788: 29
   line 781: 30
   line 786: 39
   line 785: 44
   line 787: 47
   line 788: 55
   line 789: 69

  LocalVariableTable: 
   Start  Length  Slot  Name   Signature
   0      77      0    $this       Lscala/collection/SeqLike;
   0      77      1    ord       Lscala/math/Ordering;
   14      62      2    arr$1       Lscala/collection/mutable/GenericArray;
   23      53      3    i$2       Lscala/runtime/IntRef;
   55      21      4    b$6       Lscala/collection/mutable/Builder;


public static java.lang.Object sortWith(scala.collection.SeqLike, scala.Function2);
  Code:
   Stack=4, Locals=2, Args_size=2
   0:	aload_0
   1:	new	#229; //class scala/math/Ordering$$anon$4
   4:	dup
   5:	aload_1
   6:	invokespecial	#232; //Method scala/math/Ordering$$anon$4."<init>":(Lscala/Function2;)V
   9:	invokeinterface	#175,  2; //InterfaceMethod scala/collection/SeqLike.sortWith:(Lscala/math/Ordering;)Ljava/lang/Object;
   14:	areturn
  LineNumberTable: 
   line 765: 0

  LocalVariableTable: 
   Start  Length  Slot  Name   Signature
   0      15      0    $this       Lscala/collection/SeqLike;
   0      15      1    lt       Lscala/Function2;


public static boolean corresponds(scala.collection.SeqLike, scala.collection.Seq, scala.Function2);
  Code:
   Stack=3, Locals=5, Args_size=3
   0:	aload_0
   1:	invokeinterface	#26,  1; //InterfaceMethod scala/collection/IterableLike.iterator:()Lscala/collection/Iterator;
   6:	astore_3
   7:	aload_1
   8:	invokeinterface	#26,  1; //InterfaceMethod scala/collection/IterableLike.iterator:()Lscala/collection/Iterator;
   13:	astore	4
   15:	aload_3
   16:	invokeinterface	#32,  1; //InterfaceMethod scala/collection/Iterator.hasNext:()Z
   21:	ifeq	61
   24:	aload	4
   26:	invokeinterface	#32,  1; //InterfaceMethod scala/collection/Iterator.hasNext:()Z
   31:	ifeq	61
   34:	aload_2
   35:	aload_3
   36:	invokeinterface	#35,  1; //InterfaceMethod scala/collection/Iterator.next:()Ljava/lang/Object;
   41:	aload	4
   43:	invokeinterface	#35,  1; //InterfaceMethod scala/collection/Iterator.next:()Ljava/lang/Object;
   48:	invokeinterface	#41,  3; //InterfaceMethod scala/Function2.apply:(Ljava/lang/Object;Ljava/lang/Object;)Ljava/lang/Object;
   53:	invokestatic	#47; //Method scala/runtime/BoxesRunTime.unboxToBoolean:(Ljava/lang/Object;)Z
   56:	ifne	15
   59:	iconst_0
   60:	ireturn
   61:	aload_3
   62:	invokeinterface	#32,  1; //InterfaceMethod scala/collection/Iterator.hasNext:()Z
   67:	ifne	80
   70:	aload	4
   72:	invokeinterface	#32,  1; //InterfaceMethod scala/collection/Iterator.hasNext:()Z
   77:	ifeq	84
   80:	iconst_0
   81:	goto	85
   84:	iconst_1
   85:	ireturn
  LineNumberTable: 
   line 740: 0
   line 741: 7
   line 742: 15
   line 743: 34
   line 744: 59
   line 746: 61
   line 739: 85

  LocalVariableTable: 
   Start  Length  Slot  Name   Signature
   0      86      0    $this       Lscala/collection/SeqLike;
   0      86      1    that       Lscala/collection/Seq;
   0      86      2    p       Lscala/Function2;
   7      79      3    i       Lscala/collection/Iterator;
   15      71      4    j       Lscala/collection/Iterator;


public static java.lang.Object padTo(scala.collection.SeqLike, int, java.lang.Object, scala.collection.generic.CanBuildFrom);
  Code:
   Stack=4, Locals=7, Args_size=4
   0:	aload_3
   1:	aload_0
   2:	invokeinterface	#239,  1; //InterfaceMethod scala/collection/TraversableLike.repr:()Ljava/lang/Object;
   7:	invokeinterface	#244,  2; //InterfaceMethod scala/collection/generic/CanBuildFrom.apply:(Ljava/lang/Object;)Lscala/collection/mutable/Builder;
   12:	astore	6
   14:	aload	6
   16:	aload_0
   17:	invokeinterface	#152,  1; //InterfaceMethod scala/collection/SeqLike.length:()I
   22:	istore	4
   24:	new	#154; //class scala/runtime/RichInt
   27:	dup
   28:	iload	4
   30:	invokespecial	#245; //Method scala/runtime/RichInt."<init>":(I)V
   33:	iload_1
   34:	invokevirtual	#249; //Method scala/runtime/RichInt.max:(I)I
   37:	invokeinterface	#252,  2; //InterfaceMethod scala/collection/mutable/Builder.sizeHint:(I)V
   42:	iload_1
   43:	aload_0
   44:	invokeinterface	#152,  1; //InterfaceMethod scala/collection/SeqLike.length:()I
   49:	isub
   50:	istore	5
   52:	aload	6
   54:	aload_0
   55:	invokeinterface	#163,  1; //InterfaceMethod scala/collection/SeqLike.thisCollection:()Lscala/collection/Seq;
   60:	invokeinterface	#258,  2; //InterfaceMethod scala/collection/generic/Growable.$plus$plus$eq:(Lscala/collection/Traversable;)Lscala/collection/generic/Growable;
   65:	pop
   66:	iload	5
   68:	iconst_0
   69:	if_icmple	90
   72:	aload	6
   74:	aload_2
   75:	invokeinterface	#261,  2; //InterfaceMethod scala/collection/mutable/Builder.$plus$eq:(Ljava/lang/Object;)Lscala/collection/mutable/Builder;
   80:	pop
   81:	iload	5
   83:	iconst_1
   84:	isub
   85:	istore	5
   87:	goto	66
   90:	aload	6
   92:	invokeinterface	#220,  1; //InterfaceMethod scala/collection/mutable/Builder.result:()Ljava/lang/Object;
   97:	areturn
  LineNumberTable: 
   line 718: 0
   line 719: 14
   line 720: 42
   line 721: 52
   line 722: 66
   line 723: 72
   line 724: 81
   line 726: 90

  LocalVariableTable: 
   Start  Length  Slot  Name   Signature
   0      98      0    $this       Lscala/collection/SeqLike;
   0      98      1    len       I
   0      98      2    elem       Ljava/lang/Object;
   0      98      3    bf       Lscala/collection/generic/CanBuildFrom;
   52      45      5    diff       I
   14      83      6    b       Lscala/collection/mutable/Builder;


public static java.lang.Object $colon$plus(scala.collection.SeqLike, java.lang.Object, scala.collection.generic.CanBuildFrom);
  Code:
   Stack=2, Locals=4, Args_size=3
   0:	aload_2
   1:	aload_0
   2:	invokeinterface	#239,  1; //InterfaceMethod scala/collection/TraversableLike.repr:()Ljava/lang/Object;
   7:	invokeinterface	#244,  2; //InterfaceMethod scala/collection/generic/CanBuildFrom.apply:(Ljava/lang/Object;)Lscala/collection/mutable/Builder;
   12:	astore_3
   13:	aload_3
   14:	aload_0
   15:	invokeinterface	#163,  1; //InterfaceMethod scala/collection/SeqLike.thisCollection:()Lscala/collection/Seq;
   20:	invokeinterface	#258,  2; //InterfaceMethod scala/collection/generic/Growable.$plus$plus$eq:(Lscala/collection/Traversable;)Lscala/collection/generic/Growable;
   25:	pop
   26:	aload_3
   27:	aload_1
   28:	invokeinterface	#261,  2; //InterfaceMethod scala/collection/mutable/Builder.$plus$eq:(Ljava/lang/Object;)Lscala/collection/mutable/Builder;
   33:	pop
   34:	aload_3
   35:	invokeinterface	#220,  1; //InterfaceMethod scala/collection/mutable/Builder.result:()Ljava/lang/Object;
   40:	areturn
  LineNumberTable: 
   line 697: 0
   line 698: 13
   line 699: 26
   line 700: 34

  LocalVariableTable: 
   Start  Length  Slot  Name   Signature
   0      41      0    $this       Lscala/collection/SeqLike;
   0      41      1    elem       Ljava/lang/Object;
   0      41      2    bf       Lscala/collection/generic/CanBuildFrom;
   13      27      3    b       Lscala/collection/mutable/Builder;


public static java.lang.Object $plus$colon(scala.collection.SeqLike, java.lang.Object, scala.collection.generic.CanBuildFrom);
  Code:
   Stack=2, Locals=4, Args_size=3
   0:	aload_2
   1:	aload_0
   2:	invokeinterface	#239,  1; //InterfaceMethod scala/collection/TraversableLike.repr:()Ljava/lang/Object;
   7:	invokeinterface	#244,  2; //InterfaceMethod scala/collection/generic/CanBuildFrom.apply:(Ljava/lang/Object;)Lscala/collection/mutable/Builder;
   12:	astore_3
   13:	aload_3
   14:	aload_1
   15:	invokeinterface	#261,  2; //InterfaceMethod scala/collection/mutable/Builder.$plus$eq:(Ljava/lang/Object;)Lscala/collection/mutable/Builder;
   20:	pop
   21:	aload_3
   22:	aload_0
   23:	invokeinterface	#163,  1; //InterfaceMethod scala/collection/SeqLike.thisCollection:()Lscala/collection/Seq;
   28:	invokeinterface	#258,  2; //InterfaceMethod scala/collection/generic/Growable.$plus$plus$eq:(Lscala/collection/Traversable;)Lscala/collection/generic/Growable;
   33:	pop
   34:	aload_3
   35:	invokeinterface	#220,  1; //InterfaceMethod scala/collection/mutable/Builder.result:()Ljava/lang/Object;
   40:	areturn
  LineNumberTable: 
   line 678: 0
   line 679: 13
   line 680: 21
   line 681: 34

  LocalVariableTable: 
   Start  Length  Slot  Name   Signature
   0      41      0    $this       Lscala/collection/SeqLike;
   0      41      1    elem       Ljava/lang/Object;
   0      41      2    bf       Lscala/collection/generic/CanBuildFrom;
   13      27      3    b       Lscala/collection/mutable/Builder;


public static java.lang.Object updated(scala.collection.SeqLike, int, java.lang.Object, scala.collection.generic.CanBuildFrom);
  Code:
   Stack=4, Locals=11, Args_size=4
   0:	aload_3
   1:	aload_0
   2:	invokeinterface	#239,  1; //InterfaceMethod scala/collection/TraversableLike.repr:()Ljava/lang/Object;
   7:	invokeinterface	#244,  2; //InterfaceMethod scala/collection/generic/CanBuildFrom.apply:(Ljava/lang/Object;)Lscala/collection/mutable/Builder;
   12:	astore	9
   14:	aload_0
   15:	iload_1
   16:	invokeinterface	#275,  2; //InterfaceMethod scala/collection/TraversableLike.splitAt:(I)Lscala/Tuple2;
   21:	astore	10
   23:	aload	10
   25:	ifnull	151
   28:	aload	10
   30:	invokevirtual	#280; //Method scala/Tuple2._1:()Ljava/lang/Object;
   33:	astore	4
   35:	aload	10
   37:	invokevirtual	#283; //Method scala/Tuple2._2:()Ljava/lang/Object;
   40:	astore	5
   42:	iconst_1
   43:	ifeq	138
   46:	new	#277; //class scala/Tuple2
   49:	dup
   50:	aload	4
   52:	aload	5
   54:	invokespecial	#286; //Method scala/Tuple2."<init>":(Ljava/lang/Object;Ljava/lang/Object;)V
   57:	astore	6
   59:	aload	6
   61:	invokevirtual	#280; //Method scala/Tuple2._1:()Ljava/lang/Object;
   64:	astore	7
   66:	aload	6
   68:	invokevirtual	#283; //Method scala/Tuple2._2:()Ljava/lang/Object;
   71:	astore	8
   73:	aload	9
   75:	aload_0
   76:	aload	7
   78:	invokeinterface	#290,  2; //InterfaceMethod scala/collection/SeqLike.toCollection:(Ljava/lang/Object;)Lscala/collection/Seq;
   83:	invokeinterface	#258,  2; //InterfaceMethod scala/collection/generic/Growable.$plus$plus$eq:(Lscala/collection/Traversable;)Lscala/collection/generic/Growable;
   88:	pop
   89:	aload	9
   91:	aload_2
   92:	invokeinterface	#261,  2; //InterfaceMethod scala/collection/mutable/Builder.$plus$eq:(Ljava/lang/Object;)Lscala/collection/mutable/Builder;
   97:	pop
   98:	aload	9
   100:	aload_0
   101:	aload	8
   103:	invokeinterface	#290,  2; //InterfaceMethod scala/collection/SeqLike.toCollection:(Ljava/lang/Object;)Lscala/collection/Seq;
   108:	invokeinterface	#17,  1; //InterfaceMethod scala/collection/SeqLike.view:()Ljava/lang/Object;
   113:	checkcast	#115; //class scala/collection/TraversableLike
   116:	invokeinterface	#293,  1; //InterfaceMethod scala/collection/TraversableLike.tail:()Ljava/lang/Object;
   121:	checkcast	#295; //class scala/collection/Traversable
   124:	invokeinterface	#258,  2; //InterfaceMethod scala/collection/generic/Growable.$plus$plus$eq:(Lscala/collection/Traversable;)Lscala/collection/generic/Growable;
   129:	pop
   130:	aload	9
   132:	invokeinterface	#220,  1; //InterfaceMethod scala/collection/mutable/Builder.result:()Ljava/lang/Object;
   137:	areturn
   138:	new	#82; //class scala/MatchError
   141:	dup
   142:	aload	10
   144:	invokevirtual	#296; //Method scala/Tuple2.toString:()Ljava/lang/String;
   147:	invokespecial	#91; //Method scala/MatchError."<init>":(Ljava/lang/String;)V
   150:	athrow
   151:	new	#82; //class scala/MatchError
   154:	dup
   155:	aload	10
   157:	invokevirtual	#296; //Method scala/Tuple2.toString:()Ljava/lang/String;
   160:	invokespecial	#91; //Method scala/MatchError."<init>":(Ljava/lang/String;)V
   163:	athrow
  LineNumberTable: 
   line 658: 0
   line 659: 14
   line 21: 42
   line 659: 46
   line 660: 73
   line 661: 89
   line 662: 98
   line 663: 130
   line 659: 138

  LocalVariableTable: 
   Start  Length  Slot  Name   Signature
   0      164      0    $this       Lscala/collection/SeqLike;
   0      164      1    index       I
   0      164      2    elem       Ljava/lang/Object;
   0      164      3    bf       Lscala/collection/generic/CanBuildFrom;
   35      116      4    temp14       Ljava/lang/Object;
   42      109      5    temp15       Ljava/lang/Object;
   66      71      7    prefix       Ljava/lang/Object;
   73      64      8    rest       Ljava/lang/Object;
   14      123      9    b       Lscala/collection/mutable/Builder;
   138      26      9    b       Lscala/collection/mutable/Builder;
   23      141      10    temp13       Lscala/Tuple2;


public static java.lang.Object patch(scala.collection.SeqLike, int, scala.collection.Seq, int, scala.collection.generic.CanBuildFrom);
  Code:
   Stack=4, Locals=12, Args_size=5
   0:	aload	4
   2:	aload_0
   3:	invokeinterface	#239,  1; //InterfaceMethod scala/collection/TraversableLike.repr:()Ljava/lang/Object;
   8:	invokeinterface	#244,  2; //InterfaceMethod scala/collection/generic/CanBuildFrom.apply:(Ljava/lang/Object;)Lscala/collection/mutable/Builder;
   13:	astore	10
   15:	aload_0
   16:	iload_1
   17:	invokeinterface	#275,  2; //InterfaceMethod scala/collection/TraversableLike.splitAt:(I)Lscala/Tuple2;
   22:	astore	11
   24:	aload	11
   26:	ifnull	150
   29:	aload	11
   31:	invokevirtual	#280; //Method scala/Tuple2._1:()Ljava/lang/Object;
   34:	astore	5
   36:	aload	11
   38:	invokevirtual	#283; //Method scala/Tuple2._2:()Ljava/lang/Object;
   41:	astore	6
   43:	iconst_1
   44:	ifeq	137
   47:	new	#277; //class scala/Tuple2
   50:	dup
   51:	aload	5
   53:	aload	6
   55:	invokespecial	#286; //Method scala/Tuple2."<init>":(Ljava/lang/Object;Ljava/lang/Object;)V
   58:	astore	7
   60:	aload	7
   62:	invokevirtual	#280; //Method scala/Tuple2._1:()Ljava/lang/Object;
   65:	astore	8
   67:	aload	7
   69:	invokevirtual	#283; //Method scala/Tuple2._2:()Ljava/lang/Object;
   72:	astore	9
   74:	aload	10
   76:	aload_0
   77:	aload	8
   79:	invokeinterface	#290,  2; //InterfaceMethod scala/collection/SeqLike.toCollection:(Ljava/lang/Object;)Lscala/collection/Seq;
   84:	invokeinterface	#258,  2; //InterfaceMethod scala/collection/generic/Growable.$plus$plus$eq:(Lscala/collection/Traversable;)Lscala/collection/generic/Growable;
   89:	pop
   90:	aload	10
   92:	aload_2
   93:	invokeinterface	#258,  2; //InterfaceMethod scala/collection/generic/Growable.$plus$plus$eq:(Lscala/collection/Traversable;)Lscala/collection/generic/Growable;
   98:	pop
   99:	aload	10
   101:	aload_0
   102:	aload	9
   104:	invokeinterface	#290,  2; //InterfaceMethod scala/collection/SeqLike.toCollection:(Ljava/lang/Object;)Lscala/collection/Seq;
   109:	invokeinterface	#17,  1; //InterfaceMethod scala/collection/SeqLike.view:()Ljava/lang/Object;
   114:	checkcast	#126; //class scala/collection/TraversableViewLike
   117:	iload_3
   118:	invokeinterface	#309,  2; //InterfaceMethod scala/collection/TraversableViewLike.drop:(I)Lscala/collection/TraversableView;
   123:	invokeinterface	#258,  2; //InterfaceMethod scala/collection/generic/Growable.$plus$plus$eq:(Lscala/collection/Traversable;)Lscala/collection/generic/Growable;
   128:	pop
   129:	aload	10
   131:	invokeinterface	#220,  1; //InterfaceMethod scala/collection/mutable/Builder.result:()Ljava/lang/Object;
   136:	areturn
   137:	new	#82; //class scala/MatchError
   140:	dup
   141:	aload	11
   143:	invokevirtual	#296; //Method scala/Tuple2.toString:()Ljava/lang/String;
   146:	invokespecial	#91; //Method scala/MatchError."<init>":(Ljava/lang/String;)V
   149:	athrow
   150:	new	#82; //class scala/MatchError
   153:	dup
   154:	aload	11
   156:	invokevirtual	#296; //Method scala/Tuple2.toString:()Ljava/lang/String;
   159:	invokespecial	#91; //Method scala/MatchError."<init>":(Ljava/lang/String;)V
   162:	athrow
  LineNumberTable: 
   line 639: 0
   line 640: 15
   line 21: 43
   line 640: 47
   line 641: 74
   line 642: 90
   line 643: 99
   line 644: 129
   line 640: 137

  LocalVariableTable: 
   Start  Length  Slot  Name   Signature
   0      163      0    $this       Lscala/collection/SeqLike;
   0      163      1    from       I
   0      163      2    patch       Lscala/collection/Seq;
   0      163      3    replaced       I
   0      163      4    bf       Lscala/collection/generic/CanBuildFrom;
   36      114      5    temp11       Ljava/lang/Object;
   43      107      6    temp12       Ljava/lang/Object;
   67      69      8    prefix       Ljava/lang/Object;
   74      62      9    rest       Ljava/lang/Object;
   15      121      10    b       Lscala/collection/mutable/Builder;
   137      26      10    b       Lscala/collection/mutable/Builder;
   24      139      11    temp10       Lscala/Tuple2;


public static java.lang.Object removeDuplicates(scala.collection.SeqLike);
  Code:
   Stack=6, Locals=3, Args_size=1
   0:	aload_0
   1:	invokeinterface	#209,  1; //InterfaceMethod scala/collection/TraversableLike.newBuilder:()Lscala/collection/mutable/Builder;
   6:	astore_1
   7:	new	#316; //class scala/runtime/ObjectRef
   10:	dup
   11:	getstatic	#321; //Field scala/collection/Set$.MODULE$:Lscala/collection/Set$;
   14:	getstatic	#145; //Field scala/Predef$.MODULE$:Lscala/Predef$;
   17:	iconst_0
   18:	anewarray	#84; //class java/lang/Object
   21:	invokevirtual	#325; //Method scala/Predef$.genericWrapArray:(Ljava/lang/Object;)Lscala/collection/mutable/WrappedArray;
   24:	invokevirtual	#328; //Method scala/collection/Set$.apply:(Lscala/collection/Seq;)Lscala/collection/Traversable;
   27:	checkcast	#330; //class scala/collection/Set
   30:	invokespecial	#333; //Method scala/runtime/ObjectRef."<init>":(Ljava/lang/Object;)V
   33:	astore_2
   34:	aload_0
   35:	new	#335; //class scala/collection/SeqLike$$anonfun$removeDuplicates$1
   38:	dup
   39:	aload_0
   40:	aload_1
   41:	aload_2
   42:	invokespecial	#338; //Method scala/collection/SeqLike$$anonfun$removeDuplicates$1."<init>":(Lscala/collection/SeqLike;Lscala/collection/mutable/Builder;Lscala/runtime/ObjectRef;)V
   45:	invokeinterface	#195,  2; //InterfaceMethod scala/collection/IterableLike.foreach:(Lscala/Function1;)V
   50:	aload_1
   51:	invokeinterface	#220,  1; //InterfaceMethod scala/collection/mutable/Builder.result:()Ljava/lang/Object;
   56:	areturn
  LineNumberTable: 
   line 611: 0
   line 612: 7
   line 613: 34
   line 619: 50

  LocalVariableTable: 
   Start  Length  Slot  Name   Signature
   0      57      0    $this       Lscala/collection/SeqLike;
   7      49      1    b$5       Lscala/collection/mutable/Builder;
   34      22      2    seen$1       Lscala/runtime/ObjectRef;


public static java.lang.Object intersect(scala.collection.SeqLike, scala.collection.Seq);
  Code:
   Stack=6, Locals=4, Args_size=2
   0:	aload_0
   1:	aload_1
   2:	invokestatic	#360; //Method occCounts:(Lscala/collection/SeqLike;Lscala/collection/Seq;)Lscala/collection/mutable/Map;
   5:	astore_2
   6:	aload_0
   7:	invokeinterface	#209,  1; //InterfaceMethod scala/collection/TraversableLike.newBuilder:()Lscala/collection/mutable/Builder;
   12:	astore_3
   13:	aload_0
   14:	new	#362; //class scala/collection/SeqLike$$anonfun$intersect$1
   17:	dup
   18:	aload_0
   19:	aload_2
   20:	aload_3
   21:	invokespecial	#365; //Method scala/collection/SeqLike$$anonfun$intersect$1."<init>":(Lscala/collection/SeqLike;Lscala/collection/mutable/Map;Lscala/collection/mutable/Builder;)V
   24:	invokeinterface	#195,  2; //InterfaceMethod scala/collection/IterableLike.foreach:(Lscala/Function1;)V
   29:	aload_3
   30:	invokeinterface	#220,  1; //InterfaceMethod scala/collection/mutable/Builder.result:()Ljava/lang/Object;
   35:	areturn
  LineNumberTable: 
   line 589: 0
   line 590: 6
   line 591: 13
   line 596: 29

  LocalVariableTable: 
   Start  Length  Slot  Name   Signature
   0      36      0    $this       Lscala/collection/SeqLike;
   0      36      1    that       Lscala/collection/Seq;
   6      29      2    occ$2       Lscala/collection/mutable/Map;
   13      22      3    b$4       Lscala/collection/mutable/Builder;


public static java.lang.Object diff(scala.collection.SeqLike, scala.collection.Seq);
  Code:
   Stack=6, Locals=4, Args_size=2
   0:	aload_0
   1:	aload_1
   2:	invokestatic	#360; //Method occCounts:(Lscala/collection/SeqLike;Lscala/collection/Seq;)Lscala/collection/mutable/Map;
   5:	astore_2
   6:	aload_0
   7:	invokeinterface	#209,  1; //InterfaceMethod scala/collection/TraversableLike.newBuilder:()Lscala/collection/mutable/Builder;
   12:	astore_3
   13:	aload_0
   14:	new	#370; //class scala/collection/SeqLike$$anonfun$diff$1
   17:	dup
   18:	aload_0
   19:	aload_2
   20:	aload_3
   21:	invokespecial	#371; //Method scala/collection/SeqLike$$anonfun$diff$1."<init>":(Lscala/collection/SeqLike;Lscala/collection/mutable/Map;Lscala/collection/mutable/Builder;)V
   24:	invokeinterface	#195,  2; //InterfaceMethod scala/collection/IterableLike.foreach:(Lscala/Function1;)V
   29:	aload_3
   30:	invokeinterface	#220,  1; //InterfaceMethod scala/collection/mutable/Builder.result:()Ljava/lang/Object;
   35:	areturn
  LineNumberTable: 
   line 561: 0
   line 562: 6
   line 563: 13
   line 566: 29

  LocalVariableTable: 
   Start  Length  Slot  Name   Signature
   0      36      0    $this       Lscala/collection/SeqLike;
   0      36      1    that       Lscala/collection/Seq;
   6      29      2    occ$1       Lscala/collection/mutable/Map;
   13      22      3    b$3       Lscala/collection/mutable/Builder;


public static java.lang.Object union(scala.collection.SeqLike, scala.collection.Seq, scala.collection.generic.CanBuildFrom);
  Code:
   Stack=3, Locals=3, Args_size=3
   0:	aload_0
   1:	aload_1
   2:	aload_2
   3:	invokeinterface	#379,  3; //InterfaceMethod scala/collection/TraversableLike.$plus$plus:(Lscala/collection/Traversable;Lscala/collection/generic/CanBuildFrom;)Ljava/lang/Object;
   8:	areturn
  LineNumberTable: 
   line 539: 0

  LocalVariableTable: 
   Start  Length  Slot  Name   Signature
   0      9      0    $this       Lscala/collection/SeqLike;
   0      9      1    that       Lscala/collection/Seq;
   0      9      2    bf       Lscala/collection/generic/CanBuildFrom;


public static boolean contains(scala.collection.SeqLike, java.lang.Object);
  Code:
   Stack=5, Locals=2, Args_size=2
   0:	aload_0
   1:	new	#382; //class scala/collection/SeqLike$$anonfun$contains$1
   4:	dup
   5:	aload_0
   6:	aload_1
   7:	invokespecial	#385; //Method scala/collection/SeqLike$$anonfun$contains$1."<init>":(Lscala/collection/SeqLike;Ljava/lang/Object;)V
   10:	invokeinterface	#389,  2; //InterfaceMethod scala/collection/IterableLike.exists:(Lscala/Function1;)Z
   15:	ireturn
  LineNumberTable: 
   line 516: 0

  LocalVariableTable: 
   Start  Length  Slot  Name   Signature
   0      16      0    $this       Lscala/collection/SeqLike;
   0      16      1    elem$4       Ljava/lang/Object;


public static boolean containsSlice(scala.collection.SeqLike, scala.collection.Seq);
  Code:
   Stack=2, Locals=2, Args_size=2
   0:	aload_0
   1:	aload_1
   2:	invokeinterface	#396,  2; //InterfaceMethod scala/collection/SeqLike.indexOfSlice:(Lscala/collection/Seq;)I
   7:	iconst_m1
   8:	if_icmpeq	15
   11:	iconst_1
   12:	goto	16
   15:	iconst_0
   16:	ireturn
  LineNumberTable: 
   line 507: 0

  LocalVariableTable: 
   Start  Length  Slot  Name   Signature
   0      17      0    $this       Lscala/collection/SeqLike;
   0      17      1    that       Lscala/collection/Seq;


public static int lastIndexOfSlice(scala.collection.SeqLike, scala.collection.Seq, int);
  Code:
   Stack=8, Locals=3, Args_size=3
   0:	getstatic	#403; //Field scala/collection/SeqLike$.MODULE$:Lscala/collection/SeqLike$;
   3:	aload_0
   4:	invokeinterface	#163,  1; //InterfaceMethod scala/collection/SeqLike.thisCollection:()Lscala/collection/Seq;
   9:	iconst_0
   10:	aload_0
   11:	invokeinterface	#152,  1; //InterfaceMethod scala/collection/SeqLike.length:()I
   16:	aload_1
   17:	iconst_0
   18:	aload_1
   19:	invokeinterface	#152,  1; //InterfaceMethod scala/collection/SeqLike.length:()I
   24:	iload_2
   25:	invokevirtual	#407; //Method scala/collection/SeqLike$.lastIndexOf:(Lscala/collection/Seq;IILscala/collection/Seq;III)I
   28:	ireturn
  LineNumberTable: 
   line 499: 0

  LocalVariableTable: 
   Start  Length  Slot  Name   Signature
   0      29      0    $this       Lscala/collection/SeqLike;
   0      29      1    that       Lscala/collection/Seq;
   0      29      2    end       I


public static int lastIndexOfSlice(scala.collection.SeqLike, scala.collection.Seq);
  Code:
   Stack=3, Locals=2, Args_size=2
   0:	aload_0
   1:	aload_1
   2:	aload_1
   3:	invokeinterface	#152,  1; //InterfaceMethod scala/collection/SeqLike.length:()I
   8:	invokeinterface	#412,  3; //InterfaceMethod scala/collection/SeqLike.lastIndexOfSlice:(Lscala/collection/Seq;I)I
   13:	ireturn
  LineNumberTable: 
   line 490: 0

  LocalVariableTable: 
   Start  Length  Slot  Name   Signature
   0      14      0    $this       Lscala/collection/SeqLike;
   0      14      1    that       Lscala/collection/Seq;


public static int indexOfSlice(scala.collection.SeqLike, scala.collection.Seq, int);
  Code:
   Stack=8, Locals=5, Args_size=3
   0:	aload_0
   1:	invokeinterface	#415,  1; //InterfaceMethod scala/collection/TraversableLike.hasDefiniteSize:()Z
   6:	ifeq	49
   9:	aload_1
   10:	invokeinterface	#415,  1; //InterfaceMethod scala/collection/TraversableLike.hasDefiniteSize:()Z
   15:	ifeq	49
   18:	getstatic	#403; //Field scala/collection/SeqLike$.MODULE$:Lscala/collection/SeqLike$;
   21:	aload_0
   22:	invokeinterface	#163,  1; //InterfaceMethod scala/collection/SeqLike.thisCollection:()Lscala/collection/Seq;
   27:	iconst_0
   28:	aload_0
   29:	invokeinterface	#152,  1; //InterfaceMethod scala/collection/SeqLike.length:()I
   34:	aload_1
   35:	iconst_0
   36:	aload_1
   37:	invokeinterface	#152,  1; //InterfaceMethod scala/collection/SeqLike.length:()I
   42:	iload_2
   43:	invokevirtual	#418; //Method scala/collection/SeqLike$.indexOf:(Lscala/collection/Seq;IILscala/collection/Seq;III)I
   46:	goto	79
   49:	iload_2
   50:	istore_3
   51:	aload_0
   52:	invokeinterface	#163,  1; //InterfaceMethod scala/collection/SeqLike.thisCollection:()Lscala/collection/Seq;
   57:	iload_2
   58:	invokeinterface	#421,  2; //InterfaceMethod scala/collection/TraversableLike.drop:(I)Ljava/lang/Object;
   63:	checkcast	#73; //class scala/collection/Seq
   66:	astore	4
   68:	aload	4
   70:	invokeinterface	#424,  1; //InterfaceMethod scala/collection/IterableLike.isEmpty:()Z
   75:	ifeq	80
   78:	iconst_m1
   79:	ireturn
   80:	aload	4
   82:	aload_1
   83:	invokeinterface	#428,  2; //InterfaceMethod scala/collection/SeqLike.startsWith:(Lscala/collection/Seq;)Z
   88:	ifeq	93
   91:	iload_3
   92:	ireturn
   93:	iload_3
   94:	iconst_1
   95:	iadd
   96:	istore_3
   97:	aload	4
   99:	invokeinterface	#293,  1; //InterfaceMethod scala/collection/TraversableLike.tail:()Ljava/lang/Object;
   104:	checkcast	#73; //class scala/collection/Seq
   107:	astore	4
   109:	goto	68
  LineNumberTable: 
   line 469: 0
   line 470: 18
   line 472: 49
   line 473: 51
   line 474: 68
   line 481: 78
   line 469: 79
   line 475: 80
   line 476: 91
   line 478: 93
   line 479: 97

  LocalVariableTable: 
   Start  Length  Slot  Name   Signature
   0      112      0    $this       Lscala/collection/SeqLike;
   0      112      1    that       Lscala/collection/Seq;
   0      112      2    from       I
   51      28      3    i       I
   80      32      3    i       I
   68      11      4    s       Lscala/collection/Seq;
   80      32      4    s       Lscala/collection/Seq;


public static int indexOfSlice(scala.collection.SeqLike, scala.collection.Seq);
  Code:
   Stack=3, Locals=2, Args_size=2
   0:	aload_0
   1:	aload_1
   2:	iconst_0
   3:	invokeinterface	#431,  3; //InterfaceMethod scala/collection/SeqLike.indexOfSlice:(Lscala/collection/Seq;I)I
   8:	ireturn
  LineNumberTable: 
   line 459: 0

  LocalVariableTable: 
   Start  Length  Slot  Name   Signature
   0      9      0    $this       Lscala/collection/SeqLike;
   0      9      1    that       Lscala/collection/Seq;


public static boolean endsWith(scala.collection.SeqLike, scala.collection.Seq);
  Code:
   Stack=3, Locals=6, Args_size=2
   0:	aload_0
   1:	invokeinterface	#26,  1; //InterfaceMethod scala/collection/IterableLike.iterator:()Lscala/collection/Iterator;
   6:	aload_0
   7:	invokeinterface	#152,  1; //InterfaceMethod scala/collection/SeqLike.length:()I
   12:	aload_1
   13:	invokeinterface	#152,  1; //InterfaceMethod scala/collection/SeqLike.length:()I
   18:	isub
   19:	invokeinterface	#435,  2; //InterfaceMethod scala/collection/Iterator.drop:(I)Lscala/collection/Iterator;
   24:	astore_2
   25:	aload_1
   26:	invokeinterface	#26,  1; //InterfaceMethod scala/collection/IterableLike.iterator:()Lscala/collection/Iterator;
   31:	astore	5
   33:	aload_2
   34:	invokeinterface	#32,  1; //InterfaceMethod scala/collection/Iterator.hasNext:()Z
   39:	ifeq	120
   42:	aload	5
   44:	invokeinterface	#32,  1; //InterfaceMethod scala/collection/Iterator.hasNext:()Z
   49:	ifeq	120
   52:	aload_2
   53:	invokeinterface	#35,  1; //InterfaceMethod scala/collection/Iterator.next:()Ljava/lang/Object;
   58:	aload	5
   60:	invokeinterface	#35,  1; //InterfaceMethod scala/collection/Iterator.next:()Ljava/lang/Object;
   65:	astore	4
   67:	astore_3
   68:	aload_3
   69:	aload	4
   71:	if_acmpne	78
   74:	iconst_1
   75:	goto	115
   78:	aload_3
   79:	ifnonnull	86
   82:	iconst_0
   83:	goto	115
   86:	aload_3
   87:	instanceof	#437; //class java/lang/Number
   90:	ifne	100
   93:	aload_3
   94:	instanceof	#439; //class java/lang/Character
   97:	ifeq	109
   100:	aload_3
   101:	aload	4
   103:	invokestatic	#443; //Method scala/runtime/BoxesRunTime.equals2:(Ljava/lang/Object;Ljava/lang/Object;)Z
   106:	goto	115
   109:	aload_3
   110:	aload	4
   112:	invokevirtual	#445; //Method java/lang/Object.equals:(Ljava/lang/Object;)Z
   115:	ifne	33
   118:	iconst_0
   119:	ireturn
   120:	aload	5
   122:	invokeinterface	#32,  1; //InterfaceMethod scala/collection/Iterator.hasNext:()Z
   127:	ifeq	134
   130:	iconst_0
   131:	goto	135
   134:	iconst_1
   135:	ireturn
  LineNumberTable: 
   line 444: 0
   line 445: 25
   line 446: 33
   line 447: 52
   line 448: 118
   line 450: 120
   line 443: 135

  LocalVariableTable: 
   Start  Length  Slot  Name   Signature
   0      136      0    $this       Lscala/collection/SeqLike;
   0      136      1    that       Lscala/collection/Seq;
   25      111      2    i       Lscala/collection/Iterator;
   74      44      3    x0       Ljava/lang/Object;
   74      44      4    y0       Ljava/lang/Object;
   33      103      5    j       Lscala/collection/Iterator;


public static boolean startsWith(scala.collection.SeqLike, scala.collection.Seq);
  Code:
   Stack=3, Locals=2, Args_size=2
   0:	aload_0
   1:	aload_1
   2:	iconst_0
   3:	invokeinterface	#450,  3; //InterfaceMethod scala/collection/SeqLike.startsWith:(Lscala/collection/Seq;I)Z
   8:	ireturn
  LineNumberTable: 
   line 436: 0

  LocalVariableTable: 
   Start  Length  Slot  Name   Signature
   0      9      0    $this       Lscala/collection/SeqLike;
   0      9      1    that       Lscala/collection/Seq;


public static boolean startsWith(scala.collection.SeqLike, scala.collection.Seq, int);
  Code:
   Stack=2, Locals=7, Args_size=3
   0:	aload_0
   1:	invokeinterface	#26,  1; //InterfaceMethod scala/collection/IterableLike.iterator:()Lscala/collection/Iterator;
   6:	iload_2
   7:	invokeinterface	#435,  2; //InterfaceMethod scala/collection/Iterator.drop:(I)Lscala/collection/Iterator;
   12:	astore_3
   13:	aload_1
   14:	invokeinterface	#26,  1; //InterfaceMethod scala/collection/IterableLike.iterator:()Lscala/collection/Iterator;
   19:	astore	6
   21:	aload	6
   23:	invokeinterface	#32,  1; //InterfaceMethod scala/collection/Iterator.hasNext:()Z
   28:	ifeq	115
   31:	aload_3
   32:	invokeinterface	#32,  1; //InterfaceMethod scala/collection/Iterator.hasNext:()Z
   37:	ifeq	115
   40:	aload_3
   41:	invokeinterface	#35,  1; //InterfaceMethod scala/collection/Iterator.next:()Ljava/lang/Object;
   46:	aload	6
   48:	invokeinterface	#35,  1; //InterfaceMethod scala/collection/Iterator.next:()Ljava/lang/Object;
   53:	astore	5
   55:	astore	4
   57:	aload	4
   59:	aload	5
   61:	if_acmpne	68
   64:	iconst_1
   65:	goto	110
   68:	aload	4
   70:	ifnonnull	77
   73:	iconst_0
   74:	goto	110
   77:	aload	4
   79:	instanceof	#437; //class java/lang/Number
   82:	ifne	93
   85:	aload	4
   87:	instanceof	#439; //class java/lang/Character
   90:	ifeq	103
   93:	aload	4
   95:	aload	5
   97:	invokestatic	#443; //Method scala/runtime/BoxesRunTime.equals2:(Ljava/lang/Object;Ljava/lang/Object;)Z
   100:	goto	110
   103:	aload	4
   105:	aload	5
   107:	invokevirtual	#445; //Method java/lang/Object.equals:(Ljava/lang/Object;)Z
   110:	ifne	21
   113:	iconst_0
   114:	ireturn
   115:	aload	6
   117:	invokeinterface	#32,  1; //InterfaceMethod scala/collection/Iterator.hasNext:()Z
   122:	ifeq	129
   125:	iconst_0
   126:	goto	130
   129:	iconst_1
   130:	ireturn
  LineNumberTable: 
   line 421: 0
   line 422: 13
   line 423: 21
   line 424: 40
   line 425: 113
   line 427: 115
   line 420: 130

  LocalVariableTable: 
   Start  Length  Slot  Name   Signature
   0      131      0    $this       Lscala/collection/SeqLike;
   0      131      1    that       Lscala/collection/Seq;
   0      131      2    offset       I
   13      118      3    i       Lscala/collection/Iterator;
   64      49      4    x0       Ljava/lang/Object;
   64      49      5    y0       Ljava/lang/Object;
   21      110      6    j       Lscala/collection/Iterator;


public static scala.collection.Iterator reversedElements(scala.collection.SeqLike);
  Code:
   Stack=1, Locals=1, Args_size=1
   0:	aload_0
   1:	invokeinterface	#457,  1; //InterfaceMethod scala/collection/SeqLike.reverseIterator:()Lscala/collection/Iterator;
   6:	areturn
  LineNumberTable: 
   line 407: 0

  LocalVariableTable: 
   Start  Length  Slot  Name   Signature
   0      7      0    $this       Lscala/collection/SeqLike;

  Deprecated: true

public static scala.collection.Iterator reverseIterator(scala.collection.SeqLike);
  Code:
   Stack=2, Locals=1, Args_size=1
   0:	aload_0
   1:	aload_0
   2:	invokeinterface	#460,  1; //InterfaceMethod scala/collection/SeqLike.reverse:()Ljava/lang/Object;
   7:	invokeinterface	#290,  2; //InterfaceMethod scala/collection/SeqLike.toCollection:(Ljava/lang/Object;)Lscala/collection/Seq;
   12:	invokeinterface	#26,  1; //InterfaceMethod scala/collection/IterableLike.iterator:()Lscala/collection/Iterator;
   17:	areturn
  LineNumberTable: 
   line 404: 0

  LocalVariableTable: 
   Start  Length  Slot  Name   Signature
   0      18      0    $this       Lscala/collection/SeqLike;


public static java.lang.Object reverseMap(scala.collection.SeqLike, scala.Function1, scala.collection.generic.CanBuildFrom);
  Code:
   Stack=6, Locals=5, Args_size=3
   0:	new	#316; //class scala/runtime/ObjectRef
   3:	dup
   4:	getstatic	#467; //Field scala/collection/immutable/Nil$.MODULE$:Lscala/collection/immutable/Nil$;
   7:	invokespecial	#333; //Method scala/runtime/ObjectRef."<init>":(Ljava/lang/Object;)V
   10:	astore_3
   11:	aload_0
   12:	new	#469; //class scala/collection/SeqLike$$anonfun$reverseMap$1
   15:	dup
   16:	aload_0
   17:	aload_3
   18:	invokespecial	#472; //Method scala/collection/SeqLike$$anonfun$reverseMap$1."<init>":(Lscala/collection/SeqLike;Lscala/runtime/ObjectRef;)V
   21:	invokeinterface	#195,  2; //InterfaceMethod scala/collection/IterableLike.foreach:(Lscala/Function1;)V
   26:	aload_2
   27:	aload_0
   28:	invokeinterface	#239,  1; //InterfaceMethod scala/collection/TraversableLike.repr:()Ljava/lang/Object;
   33:	invokeinterface	#244,  2; //InterfaceMethod scala/collection/generic/CanBuildFrom.apply:(Ljava/lang/Object;)Lscala/collection/mutable/Builder;
   38:	astore	4
   40:	aload_3
   41:	getfield	#474; //Field scala/runtime/ObjectRef.elem:Ljava/lang/Object;
   44:	checkcast	#476; //class scala/collection/immutable/List
   47:	new	#478; //class scala/collection/SeqLike$$anonfun$reverseMap$2
   50:	dup
   51:	aload_0
   52:	aload_1
   53:	aload	4
   55:	invokespecial	#481; //Method scala/collection/SeqLike$$anonfun$reverseMap$2."<init>":(Lscala/collection/SeqLike;Lscala/Function1;Lscala/collection/mutable/Builder;)V
   58:	invokeinterface	#484,  2; //InterfaceMethod scala/collection/LinearSeqLike.foreach:(Lscala/Function1;)V
   63:	aload	4
   65:	invokeinterface	#220,  1; //InterfaceMethod scala/collection/mutable/Builder.result:()Ljava/lang/Object;
   70:	areturn
  LineNumberTable: 
   line 386: 0
   line 387: 11
   line 390: 17
   line 387: 18
   line 389: 26
   line 390: 40
   line 393: 63

  LocalVariableTable: 
   Start  Length  Slot  Name   Signature
   0      71      0    $this       Lscala/collection/SeqLike;
   0      71      1    f$1       Lscala/Function1;
   0      71      2    bf       Lscala/collection/generic/CanBuildFrom;
   11      59      3    xs$2       Lscala/runtime/ObjectRef;
   40      30      4    b$2       Lscala/collection/mutable/Builder;


public static java.lang.Object reverse(scala.collection.SeqLike);
  Code:
   Stack=5, Locals=3, Args_size=1
   0:	new	#316; //class scala/runtime/ObjectRef
   3:	dup
   4:	getstatic	#467; //Field scala/collection/immutable/Nil$.MODULE$:Lscala/collection/immutable/Nil$;
   7:	invokespecial	#333; //Method scala/runtime/ObjectRef."<init>":(Ljava/lang/Object;)V
   10:	astore_1
   11:	aload_0
   12:	new	#489; //class scala/collection/SeqLike$$anonfun$reverse$1
   15:	dup
   16:	aload_0
   17:	aload_1
   18:	invokespecial	#490; //Method scala/collection/SeqLike$$anonfun$reverse$1."<init>":(Lscala/collection/SeqLike;Lscala/runtime/ObjectRef;)V
   21:	invokeinterface	#195,  2; //InterfaceMethod scala/collection/IterableLike.foreach:(Lscala/Function1;)V
   26:	aload_0
   27:	invokeinterface	#209,  1; //InterfaceMethod scala/collection/TraversableLike.newBuilder:()Lscala/collection/mutable/Builder;
   32:	astore_2
   33:	aload_1
   34:	getfield	#474; //Field scala/runtime/ObjectRef.elem:Ljava/lang/Object;
   37:	checkcast	#476; //class scala/collection/immutable/List
   40:	new	#492; //class scala/collection/SeqLike$$anonfun$reverse$2
   43:	dup
   44:	aload_0
   45:	aload_2
   46:	invokespecial	#493; //Method scala/collection/SeqLike$$anonfun$reverse$2."<init>":(Lscala/collection/SeqLike;Lscala/collection/mutable/Builder;)V
   49:	invokeinterface	#484,  2; //InterfaceMethod scala/collection/LinearSeqLike.foreach:(Lscala/Function1;)V
   54:	aload_2
   55:	invokeinterface	#220,  1; //InterfaceMethod scala/collection/mutable/Builder.result:()Ljava/lang/Object;
   60:	areturn
  LineNumberTable: 
   line 355: 0
   line 356: 11
   line 359: 17
   line 356: 18
   line 358: 26
   line 359: 33
   line 361: 54

  LocalVariableTable: 
   Start  Length  Slot  Name   Signature
   0      61      0    $this       Lscala/collection/SeqLike;
   11      49      1    xs$1       Lscala/runtime/ObjectRef;
   33      27      2    b$1       Lscala/collection/mutable/Builder;


public static int lastIndexWhere(scala.collection.SeqLike, scala.Function1, int);
  Code:
   Stack=2, Locals=6, Args_size=3
   0:	aload_0
   1:	invokeinterface	#152,  1; //InterfaceMethod scala/collection/SeqLike.length:()I
   6:	iconst_1
   7:	isub
   8:	istore_3
   9:	aload_0
   10:	invokeinterface	#457,  1; //InterfaceMethod scala/collection/SeqLike.reverseIterator:()Lscala/collection/Iterator;
   15:	astore	4
   17:	aload	4
   19:	invokeinterface	#32,  1; //InterfaceMethod scala/collection/Iterator.hasNext:()Z
   24:	ifeq	70
   27:	aload	4
   29:	invokeinterface	#35,  1; //InterfaceMethod scala/collection/Iterator.next:()Ljava/lang/Object;
   34:	astore	5
   36:	iload_3
   37:	iload_2
   38:	if_icmpgt	59
   41:	aload_1
   42:	aload	5
   44:	invokeinterface	#501,  2; //InterfaceMethod scala/Function1.apply:(Ljava/lang/Object;)Ljava/lang/Object;
   49:	invokestatic	#47; //Method scala/runtime/BoxesRunTime.unboxToBoolean:(Ljava/lang/Object;)Z
   52:	ifeq	59
   55:	iconst_0
   56:	goto	60
   59:	iconst_1
   60:	ifeq	70
   63:	iload_3
   64:	iconst_1
   65:	isub
   66:	istore_3
   67:	goto	17
   70:	iload_3
   71:	ireturn
  LineNumberTable: 
   line 342: 0
   line 343: 9
   line 344: 17
   line 345: 70

  LocalVariableTable: 
   Start  Length  Slot  Name   Signature
   0      72      0    $this       Lscala/collection/SeqLike;
   0      72      1    p       Lscala/Function1;
   0      72      2    end       I
   9      62      3    i       I
   17      54      4    it       Lscala/collection/Iterator;
   36      27      5    elem       Ljava/lang/Object;


public static int lastIndexWhere(scala.collection.SeqLike, scala.Function1);
  Code:
   Stack=4, Locals=2, Args_size=2
   0:	aload_0
   1:	aload_1
   2:	aload_0
   3:	invokeinterface	#152,  1; //InterfaceMethod scala/collection/SeqLike.length:()I
   8:	iconst_1
   9:	isub
   10:	invokeinterface	#505,  3; //InterfaceMethod scala/collection/SeqLike.lastIndexWhere:(Lscala/Function1;I)I
   15:	ireturn
  LineNumberTable: 
   line 333: 0

  LocalVariableTable: 
   Start  Length  Slot  Name   Signature
   0      16      0    $this       Lscala/collection/SeqLike;
   0      16      1    p       Lscala/Function1;


public static int lastIndexOf(scala.collection.SeqLike, java.lang.Object, int);
  Code:
   Stack=5, Locals=3, Args_size=3
   0:	aload_0
   1:	new	#508; //class scala/collection/SeqLike$$anonfun$lastIndexOf$2
   4:	dup
   5:	aload_0
   6:	aload_1
   7:	invokespecial	#509; //Method scala/collection/SeqLike$$anonfun$lastIndexOf$2."<init>":(Lscala/collection/SeqLike;Ljava/lang/Object;)V
   10:	iload_2
   11:	invokeinterface	#505,  3; //InterfaceMethod scala/collection/SeqLike.lastIndexWhere:(Lscala/Function1;I)I
   16:	ireturn
  LineNumberTable: 
   line 323: 0

  LocalVariableTable: 
   Start  Length  Slot  Name   Signature
   0      17      0    $this       Lscala/collection/SeqLike;
   0      17      1    elem$3       Ljava/lang/Object;
   0      17      2    end       I


public static int lastIndexOf(scala.collection.SeqLike, java.lang.Object);
  Code:
   Stack=5, Locals=2, Args_size=2
   0:	aload_0
   1:	new	#513; //class scala/collection/SeqLike$$anonfun$lastIndexOf$1
   4:	dup
   5:	aload_0
   6:	aload_1
   7:	invokespecial	#514; //Method scala/collection/SeqLike$$anonfun$lastIndexOf$1."<init>":(Lscala/collection/SeqLike;Ljava/lang/Object;)V
   10:	invokeinterface	#60,  2; //InterfaceMethod scala/collection/SeqLike.lastIndexWhere:(Lscala/Function1;)I
   15:	ireturn
  LineNumberTable: 
   line 311: 0

  LocalVariableTable: 
   Start  Length  Slot  Name   Signature
   0      16      0    $this       Lscala/collection/SeqLike;
   0      16      1    elem$2       Ljava/lang/Object;


public static int indexOf(scala.collection.SeqLike, java.lang.Object, int);
  Code:
   Stack=5, Locals=3, Args_size=3
   0:	aload_0
   1:	new	#517; //class scala/collection/SeqLike$$anonfun$indexOf$1
   4:	dup
   5:	aload_0
   6:	aload_1
   7:	invokespecial	#518; //Method scala/collection/SeqLike$$anonfun$indexOf$1."<init>":(Lscala/collection/SeqLike;Ljava/lang/Object;)V
   10:	iload_2
   11:	invokeinterface	#521,  3; //InterfaceMethod scala/collection/SeqLike.indexWhere:(Lscala/Function1;I)I
   16:	ireturn
  LineNumberTable: 
   line 298: 0

  LocalVariableTable: 
   Start  Length  Slot  Name   Signature
   0      17      0    $this       Lscala/collection/SeqLike;
   0      17      1    elem$1       Ljava/lang/Object;
   0      17      2    from       I


public static int indexOf(scala.collection.SeqLike, java.lang.Object);
  Code:
   Stack=3, Locals=2, Args_size=2
   0:	aload_0
   1:	aload_1
   2:	iconst_0
   3:	invokeinterface	#525,  3; //InterfaceMethod scala/collection/SeqLike.indexOf:(Ljava/lang/Object;I)I
   8:	ireturn
  LineNumberTable: 
   line 284: 0

  LocalVariableTable: 
   Start  Length  Slot  Name   Signature
   0      9      0    $this       Lscala/collection/SeqLike;
   0      9      1    elem       Ljava/lang/Object;


public static int findIndexOf(scala.collection.SeqLike, scala.Function1);
  Code:
   Stack=2, Locals=2, Args_size=2
   0:	aload_0
   1:	aload_1
   2:	invokeinterface	#528,  2; //InterfaceMethod scala/collection/SeqLike.indexWhere:(Lscala/Function1;)I
   7:	ireturn
  LineNumberTable: 
   line 271: 0

  LocalVariableTable: 
   Start  Length  Slot  Name   Signature
   0      8      0    $this       Lscala/collection/SeqLike;
   0      8      1    p       Lscala/Function1;


public static int indexWhere(scala.collection.SeqLike, scala.Function1, int);
  Code:
   Stack=2, Locals=5, Args_size=3
   0:	iload_2
   1:	istore_3
   2:	aload_0
   3:	invokeinterface	#26,  1; //InterfaceMethod scala/collection/IterableLike.iterator:()Lscala/collection/Iterator;
   8:	iload_2
   9:	invokeinterface	#435,  2; //InterfaceMethod scala/collection/Iterator.drop:(I)Lscala/collection/Iterator;
   14:	astore	4
   16:	aload	4
   18:	invokeinterface	#32,  1; //InterfaceMethod scala/collection/Iterator.hasNext:()Z
   23:	ifeq	52
   26:	aload_1
   27:	aload	4
   29:	invokeinterface	#35,  1; //InterfaceMethod scala/collection/Iterator.next:()Ljava/lang/Object;
   34:	invokeinterface	#501,  2; //InterfaceMethod scala/Function1.apply:(Ljava/lang/Object;)Ljava/lang/Object;
   39:	invokestatic	#47; //Method scala/runtime/BoxesRunTime.unboxToBoolean:(Ljava/lang/Object;)Z
   42:	ifne	52
   45:	iload_3
   46:	iconst_1
   47:	iadd
   48:	istore_3
   49:	goto	16
   52:	aload	4
   54:	invokeinterface	#32,  1; //InterfaceMethod scala/collection/Iterator.hasNext:()Z
   59:	ifeq	66
   62:	iload_3
   63:	goto	67
   66:	iconst_m1
   67:	ireturn
  LineNumberTable: 
   line 262: 0
   line 263: 2
   line 264: 16
   line 265: 45
   line 266: 52
   line 261: 67

  LocalVariableTable: 
   Start  Length  Slot  Name   Signature
   0      68      0    $this       Lscala/collection/SeqLike;
   0      68      1    p       Lscala/Function1;
   0      68      2    from       I
   2      66      3    i       I
   16      52      4    it       Lscala/collection/Iterator;


public static int indexWhere(scala.collection.SeqLike, scala.Function1);
  Code:
   Stack=3, Locals=2, Args_size=2
   0:	aload_0
   1:	aload_1
   2:	iconst_0
   3:	invokeinterface	#521,  3; //InterfaceMethod scala/collection/SeqLike.indexWhere:(Lscala/Function1;I)I
   8:	ireturn
  LineNumberTable: 
   line 250: 0

  LocalVariableTable: 
   Start  Length  Slot  Name   Signature
   0      9      0    $this       Lscala/collection/SeqLike;
   0      9      1    p       Lscala/Function1;


public static int prefixLength(scala.collection.SeqLike, scala.Function1);
  Code:
   Stack=3, Locals=2, Args_size=2
   0:	aload_0
   1:	aload_1
   2:	iconst_0
   3:	invokeinterface	#532,  3; //InterfaceMethod scala/collection/SeqLike.segmentLength:(Lscala/Function1;I)I
   8:	ireturn
  LineNumberTable: 
   line 240: 0

  LocalVariableTable: 
   Start  Length  Slot  Name   Signature
   0      9      0    $this       Lscala/collection/SeqLike;
   0      9      1    p       Lscala/Function1;


public static int segmentLength(scala.collection.SeqLike, scala.Function1, int);
  Code:
   Stack=2, Locals=5, Args_size=3
   0:	iconst_0
   1:	istore_3
   2:	aload_0
   3:	invokeinterface	#26,  1; //InterfaceMethod scala/collection/IterableLike.iterator:()Lscala/collection/Iterator;
   8:	iload_2
   9:	invokeinterface	#435,  2; //InterfaceMethod scala/collection/Iterator.drop:(I)Lscala/collection/Iterator;
   14:	astore	4
   16:	aload	4
   18:	invokeinterface	#32,  1; //InterfaceMethod scala/collection/Iterator.hasNext:()Z
   23:	ifeq	52
   26:	aload_1
   27:	aload	4
   29:	invokeinterface	#35,  1; //InterfaceMethod scala/collection/Iterator.next:()Ljava/lang/Object;
   34:	invokeinterface	#501,  2; //InterfaceMethod scala/Function1.apply:(Ljava/lang/Object;)Ljava/lang/Object;
   39:	invokestatic	#47; //Method scala/runtime/BoxesRunTime.unboxToBoolean:(Ljava/lang/Object;)Z
   42:	ifeq	52
   45:	iload_3
   46:	iconst_1
   47:	iadd
   48:	istore_3
   49:	goto	16
   52:	iload_3
   53:	ireturn
  LineNumberTable: 
   line 225: 0
   line 226: 2
   line 227: 16
   line 228: 45
   line 229: 52

  LocalVariableTable: 
   Start  Length  Slot  Name   Signature
   0      54      0    $this       Lscala/collection/SeqLike;
   0      54      1    p       Lscala/Function1;
   0      54      2    from       I
   2      51      3    i       I
   16      37      4    it       Lscala/collection/Iterator;


public static boolean isDefinedAt(scala.collection.SeqLike, int);
  Code:
   Stack=2, Locals=2, Args_size=2
   0:	iload_1
   1:	iconst_0
   2:	if_icmplt	19
   5:	iload_1
   6:	aload_0
   7:	invokeinterface	#152,  1; //InterfaceMethod scala/collection/SeqLike.length:()I
   12:	if_icmpge	19
   15:	iconst_1
   16:	goto	20
   19:	iconst_0
   20:	ireturn
  LineNumberTable: 
   line 213: 0

  LocalVariableTable: 
   Start  Length  Slot  Name   Signature
   0      21      0    $this       Lscala/collection/SeqLike;
   0      21      1    idx       I


public static int size(scala.collection.SeqLike);
  Code:
   Stack=1, Locals=1, Args_size=1
   0:	aload_0
   1:	invokeinterface	#152,  1; //InterfaceMethod scala/collection/SeqLike.length:()I
   6:	ireturn
  LineNumberTable: 
   line 203: 0

  LocalVariableTable: 
   Start  Length  Slot  Name   Signature
   0      7      0    $this       Lscala/collection/SeqLike;


public static int lengthCompare(scala.collection.SeqLike, int);
  Code:
   Stack=2, Locals=4, Args_size=2
   0:	iconst_0
   1:	istore_2
   2:	aload_0
   3:	invokeinterface	#26,  1; //InterfaceMethod scala/collection/IterableLike.iterator:()Lscala/collection/Iterator;
   8:	astore_3
   9:	aload_3
   10:	invokeinterface	#32,  1; //InterfaceMethod scala/collection/Iterator.hasNext:()Z
   15:	ifeq	37
   18:	iload_2
   19:	iload_1
   20:	if_icmpgt	37
   23:	aload_3
   24:	invokeinterface	#35,  1; //InterfaceMethod scala/collection/Iterator.next:()Ljava/lang/Object;
   29:	pop
   30:	iload_2
   31:	iconst_1
   32:	iadd
   33:	istore_2
   34:	goto	9
   37:	iload_2
   38:	iload_1
   39:	isub
   40:	ireturn
  LineNumberTable: 
   line 190: 0
   line 191: 2
   line 192: 9
   line 193: 23
   line 194: 30
   line 196: 37

  LocalVariableTable: 
   Start  Length  Slot  Name   Signature
   0      41      0    $this       Lscala/collection/SeqLike;
   0      41      1    len       I
   2      38      2    i       I
   9      31      3    it       Lscala/collection/Iterator;


public static scala.collection.Seq toCollection(scala.collection.SeqLike, java.lang.Object);
  Code:
   Stack=1, Locals=2, Args_size=2
   0:	aload_1
   1:	checkcast	#73; //class scala/collection/Seq
   4:	areturn
  LineNumberTable: 
   line 156: 0

  LocalVariableTable: 
   Start  Length  Slot  Name   Signature
   0      5      0    $this       Lscala/collection/SeqLike;
   0      5      1    repr       Ljava/lang/Object;


public static scala.collection.Seq thisCollection(scala.collection.SeqLike);
  Code:
   Stack=1, Locals=1, Args_size=1
   0:	aload_0
   1:	checkcast	#73; //class scala/collection/Seq
   4:	areturn
  LineNumberTable: 
   line 155: 0

  LocalVariableTable: 
   Start  Length  Slot  Name   Signature
   0      5      0    $this       Lscala/collection/SeqLike;


}

