Compiled from "SeqLike.scala"
public final class scala.collection.SeqLike$$anonfun$hashCode$1 extends scala.runtime.AbstractFunction2 implements java.io.Serializable
  InnerClass: 
   public final $anonfun$hashCode$1=class scala/collection/SeqLike$$anonfun$hashCode$1 of class scala/collection/SeqLike
  Scala: length = 0x
   
  SourceFile: "SeqLike.scala"
  minor version: 0
  major version: 49
  Constant pool:
int	41;
class	java/io/Serializable
class	java/lang/Object
class	scala/collection/SeqLike
class	scala/collection/SeqLike$$anonfun$hashCode$1
class	scala/runtime/AbstractFunction2
class	scala/runtime/BoxesRunTime
Field	scala/collection/SeqLike$$anonfun$hashCode$1.serialVersionUID:J
Method	java/lang/Object.hashCode:()I
Method	scala/collection/SeqLike$$anonfun$hashCode$1.apply:(ILjava/lang/Object;)I
Method	scala/runtime/AbstractFunction2."<init>":()V
Method	scala/runtime/BoxesRunTime.boxToInteger:(I)Ljava/lang/Integer;
Method	scala/runtime/BoxesRunTime.unboxToInt:(Ljava/lang/Object;)I
NameAndType	"<init>":()V
NameAndType	apply:(ILjava/lang/Object;)I
NameAndType	boxToInteger:(I)Ljava/lang/Integer;
NameAndType	hashCode:()I
NameAndType	serialVersionUID:J
NameAndType	unboxToInt:(Ljava/lang/Object;)I
Asciz	$anonfun$hashCode$1;
Asciz	$outer;
Asciz	()I;
Asciz	()V;
Asciz	(I)Ljava/lang/Integer;;
Asciz	(ILjava/lang/Object;)I;
Asciz	(ITA;)I;
Asciz	(Ljava/lang/Object;)I;
Asciz	(Ljava/lang/Object;Ljava/lang/Object;)Ljava/lang/Object;;
Asciz	(Lscala/collection/SeqLike;)V;
Asciz	(Lscala/collection/SeqLike<TA;TRepr;>;)V;
Asciz	<clinit>;
Asciz	<init>;
Asciz	Code;
Asciz	InnerClasses;
Asciz	J;
Asciz	LineNumberTable;
Asciz	Ljava/lang/Object;;
Asciz	LocalVariableTable;
Asciz	Lscala/collection/SeqLike$$anonfun$hashCode$1;;
Asciz	Lscala/collection/SeqLike;;
Asciz	Scala;
Asciz	SeqLike.scala;
Asciz	Signature;
Asciz	SourceFile;
Asciz	apply;
Asciz	boxToInteger;
Asciz	hashCode;
Asciz	java/io/Serializable;
Asciz	java/lang/Object;
Asciz	scala/collection/SeqLike;
Asciz	scala/collection/SeqLike$$anonfun$hashCode$1;
Asciz	scala/runtime/AbstractFunction2;
Asciz	scala/runtime/BoxesRunTime;
Asciz	serialVersionUID;
Asciz	this;
Asciz	unboxToInt;
Asciz	v1;
Asciz	v2;

{
public static final long serialVersionUID;
  Signature: J

public static {};
  Signature: ()V
  Code:
   Stack=2, Locals=0, Args_size=0
	lconst_0
	putstatic	Field serialVersionUID:J
	return
  Labels:

public scala.collection.SeqLike$$anonfun$hashCode$1(scala.collection.SeqLike);
  Signature: (Lscala/collection/SeqLike;)V
  Code:
   Stack=1, Locals=2, Args_size=2
	aload_0
	invokespecial	Method scala/runtime/AbstractFunction2."<init>":()V
	return
  Labels:
  LocalVariableTable: 
   Start  Length  Slot  Name   Signature
   0      5      0    this       Lscala/collection/SeqLike$$anonfun$hashCode$1;
   0      5      1    $outer       Lscala/collection/SeqLike;

  Signature: length = 0x2
   00 1E 

public final java.lang.Object apply(java.lang.Object, java.lang.Object);
  Signature: (Ljava/lang/Object;Ljava/lang/Object;)Ljava/lang/Object;
  Code:
   Stack=3, Locals=4, Args_size=3
	aload_0
	aload_1
	invokestatic	Method scala/runtime/BoxesRunTime.unboxToInt:(Ljava/lang/Object;)I
	aload_2
	invokevirtual	Method apply:(ILjava/lang/Object;)I
	istore_3
	iload_3
	invokestatic	Method scala/runtime/BoxesRunTime.boxToInteger:(I)Ljava/lang/Integer;
	areturn
  Labels:
  LocalVariableTable: 
   Start  Length  Slot  Name   Signature
   0      15      0    this       Lscala/collection/SeqLike$$anonfun$hashCode$1;
   0      15      1    v1       Ljava/lang/Object;
   0      15      2    v2       Ljava/lang/Object;


public final int apply(int, java.lang.Object);
  Signature: (ILjava/lang/Object;)I
  Code:
   Stack=2, Locals=3, Args_size=3
	iload_1
	ldc	int 41
	imul
	aload_2
	invokevirtual	Method java/lang/Object.hashCode:()I
	iadd
	ireturn
  Labels:
  Signature: length = 0x2
   00 1A 

}

