Compiled from "Sequence.scala"
public final class scala.collection.Sequence$ extends scala.collection.generic.SequenceFactory implements scala.ScalaObject
  SourceFile: "Sequence.scala"
  Scala: length = 0x
   
  Signature: length = 0x2
   00 43 
  InnerClass: 
   public #71= #62 of #70; //VirtualBuilderFactory=class scala/collection/generic/TraversableFactory$VirtualBuilderFactory of class scala/collection/generic/TraversableFactory
  minor version: 0
  major version: 49
  Constant pool:
const #1 = Asciz	SourceFile;
const #2 = Asciz	Sequence.scala;
const #3 = Asciz	Scala;
const #4 = Asciz	MODULE$;
const #5 = Asciz	Lscala/collection/Sequence$;;
const #6 = Asciz	<clinit>;
const #7 = Asciz	()V;
const #8 = Asciz	Code;
const #9 = Asciz	scala/collection/Sequence$;
const #10 = class	#9;	//  scala/collection/Sequence$
const #11 = Asciz	<init>;
const #12 = NameAndType	#11:#7;//  "<init>":()V
const #13 = Method	#10.#12;	//  scala/collection/Sequence$."<init>":()V
const #14 = Asciz	LineNumberTable;
const #15 = Asciz	scala/collection/generic/SequenceFactory;
const #16 = class	#15;	//  scala/collection/generic/SequenceFactory
const #17 = Method	#16.#12;	//  scala/collection/generic/SequenceFactory."<init>":()V
const #18 = NameAndType	#4:#5;//  MODULE$:Lscala/collection/Sequence$;
const #19 = Field	#10.#18;	//  scala/collection/Sequence$.MODULE$:Lscala/collection/Sequence$;
const #20 = Asciz	single;
const #21 = Asciz	(Ljava/lang/Object;)Lscala/collection/Sequence;;
const #22 = Asciz	singleton;
const #23 = NameAndType	#22:#21;//  singleton:(Ljava/lang/Object;)Lscala/collection/Sequence;
const #24 = Method	#10.#23;	//  scala/collection/Sequence$.singleton:(Ljava/lang/Object;)Lscala/collection/Sequence;
const #25 = Asciz	this;
const #26 = Asciz	x;
const #27 = Asciz	Ljava/lang/Object;;
const #28 = Asciz	LocalVariableTable;
const #29 = Asciz	<A:Ljava/lang/Object;>(TA;)Lscala/collection/Sequence<TA;>;;
const #30 = Asciz	Signature;
const #31 = Asciz	scala/runtime/ScalaRunTime$;
const #32 = class	#31;	//  scala/runtime/ScalaRunTime$
const #33 = Asciz	Lscala/runtime/ScalaRunTime$;;
const #34 = NameAndType	#4:#33;//  MODULE$:Lscala/runtime/ScalaRunTime$;
const #35 = Field	#32.#34;	//  scala/runtime/ScalaRunTime$.MODULE$:Lscala/runtime/ScalaRunTime$;
const #36 = Asciz	java/lang/Object;
const #37 = class	#36;	//  java/lang/Object
const #38 = Asciz	boxArray;
const #39 = Asciz	(Ljava/lang/Object;)Lscala/runtime/BoxedArray;;
const #40 = NameAndType	#38:#39;//  boxArray:(Ljava/lang/Object;)Lscala/runtime/BoxedArray;
const #41 = Method	#32.#40;	//  scala/runtime/ScalaRunTime$.boxArray:(Ljava/lang/Object;)Lscala/runtime/BoxedArray;
const #42 = Asciz	apply;
const #43 = Asciz	(Lscala/collection/Sequence;)Lscala/collection/Traversable;;
const #44 = NameAndType	#42:#43;//  apply:(Lscala/collection/Sequence;)Lscala/collection/Traversable;
const #45 = Method	#10.#44;	//  scala/collection/Sequence$.apply:(Lscala/collection/Sequence;)Lscala/collection/Traversable;
const #46 = Asciz	scala/collection/Sequence;
const #47 = class	#46;	//  scala/collection/Sequence
const #48 = Asciz	value;
const #49 = Asciz	newBuilder;
const #50 = Asciz	()Lscala/collection/generic/Builder;;
const #51 = Asciz	scala/collection/immutable/Sequence$;
const #52 = class	#51;	//  scala/collection/immutable/Sequence$
const #53 = Asciz	Lscala/collection/immutable/Sequence$;;
const #54 = NameAndType	#4:#53;//  MODULE$:Lscala/collection/immutable/Sequence$;
const #55 = Field	#52.#54;	//  scala/collection/immutable/Sequence$.MODULE$:Lscala/collection/immutable/Sequence$;
const #56 = NameAndType	#49:#50;//  newBuilder:()Lscala/collection/generic/Builder;
const #57 = Method	#52.#56;	//  scala/collection/immutable/Sequence$.newBuilder:()Lscala/collection/generic/Builder;
const #58 = Asciz	<A:Ljava/lang/Object;>()Lscala/collection/generic/Builder<TA;Lscala/collection/Sequence<TA;>;>;;
const #59 = Asciz	builderFactory;
const #60 = Asciz	()Lscala/collection/generic/BuilderFactory;;
const #61 = Asciz	scala/collection/generic/TraversableFactory$VirtualBuilderFactory;
const #62 = class	#61;	//  scala/collection/generic/TraversableFactory$VirtualBuilderFactory
const #63 = Asciz	(Lscala/collection/generic/TraversableFactory;)V;
const #64 = NameAndType	#11:#63;//  "<init>":(Lscala/collection/generic/TraversableFactory;)V
const #65 = Method	#62.#64;	//  scala/collection/generic/TraversableFactory$VirtualBuilderFactory."<init>":(Lscala/collection/generic/TraversableFactory;)V
const #66 = Asciz	<A:Ljava/lang/Object;>()Lscala/collection/generic/BuilderFactory<TA;Lscala/collection/Sequence<TA;>;Lscala/collection/Sequence<*>;>;;
const #67 = Asciz	Lscala/collection/generic/SequenceFactory<Lscala/collection/Sequence<TA;>;>;Lscala/ScalaObject;;
const #68 = Asciz	InnerClasses;
const #69 = Asciz	scala/collection/generic/TraversableFactory;
const #70 = class	#69;	//  scala/collection/generic/TraversableFactory
const #71 = Asciz	VirtualBuilderFactory;
const #72 = Asciz	scala/ScalaObject;
const #73 = class	#72;	//  scala/ScalaObject

{
public static final scala.collection.Sequence$ MODULE$;

public static {};
  Code:
   Stack=1, Locals=0, Args_size=0
   0:	new	#10; //class scala/collection/Sequence$
   3:	invokespecial	#13; //Method "<init>":()V
   6:	return

public scala.collection.Sequence single(java.lang.Object);
  Code:
   Stack=2, Locals=2, Args_size=2
   0:	aload_0
   1:	aload_1
   2:	invokevirtual	#24; //Method singleton:(Ljava/lang/Object;)Lscala/collection/Sequence;
   5:	areturn
  LineNumberTable: 
   line 50: 0

  LocalVariableTable: 
   Start  Length  Slot  Name   Signature
   0      6      0    this       Lscala/collection/Sequence$;
   0      6      1    x       Ljava/lang/Object;

  Signature: length = 0x2
   00 1D 

public scala.collection.Sequence singleton(java.lang.Object);
  Code:
   Stack=6, Locals=2, Args_size=2
   0:	aload_0
   1:	getstatic	#35; //Field scala/runtime/ScalaRunTime$.MODULE$:Lscala/runtime/ScalaRunTime$;
   4:	iconst_1
   5:	anewarray	#37; //class java/lang/Object
   8:	dup
   9:	iconst_0
   10:	aload_1
   11:	aastore
   12:	invokevirtual	#41; //Method scala/runtime/ScalaRunTime$.boxArray:(Ljava/lang/Object;)Lscala/runtime/BoxedArray;
   15:	invokevirtual	#45; //Method apply:(Lscala/collection/Sequence;)Lscala/collection/Traversable;
   18:	checkcast	#47; //class scala/collection/Sequence
   21:	areturn
  LineNumberTable: 
   line 46: 0

  LocalVariableTable: 
   Start  Length  Slot  Name   Signature
   0      22      0    this       Lscala/collection/Sequence$;
   0      22      1    value       Ljava/lang/Object;

  Signature: length = 0x2
   00 1D 

public scala.collection.generic.Builder newBuilder();
  Code:
   Stack=1, Locals=1, Args_size=1
   0:	getstatic	#55; //Field scala/collection/immutable/Sequence$.MODULE$:Lscala/collection/immutable/Sequence$;
   3:	invokevirtual	#57; //Method scala/collection/immutable/Sequence$.newBuilder:()Lscala/collection/generic/Builder;
   6:	areturn
  LineNumberTable: 
   line 41: 0

  Signature: length = 0x2
   00 3A 

public scala.collection.generic.BuilderFactory builderFactory();
  Code:
   Stack=3, Locals=1, Args_size=1
   0:	new	#62; //class scala/collection/generic/TraversableFactory$VirtualBuilderFactory
   3:	dup
   4:	aload_0
   5:	invokespecial	#65; //Method scala/collection/generic/TraversableFactory$VirtualBuilderFactory."<init>":(Lscala/collection/generic/TraversableFactory;)V
   8:	areturn
  LineNumberTable: 
   line 40: 0

  Signature: length = 0x2
   00 42 

}

