Compiled from "SeqViewLike.scala"
public abstract class scala.collection.SeqViewLike$ZippedAll$class extends java.lang.Object
  SourceFile: "SeqViewLike.scala"
  Scala: length = 0x
   
  InnerClass: 
   public abstract ZippedAll=class scala/collection/SeqViewLike$ZippedAll of class scala/collection/SeqViewLike
   public abstract ZippedAll=class scala/collection/IterableViewLike$ZippedAll of class scala/collection/IterableViewLike
  minor version: 0
  major version: 49
  Constant pool:
Asciz	SourceFile;
Asciz	SeqViewLike.scala;
Asciz	thatSeq;
Asciz	(Lscala/collection/SeqViewLike$ZippedAll;)Lscala/collection/Seq;;
Asciz	Code;
Asciz	LineNumberTable;
Asciz	scala/collection/IterableViewLike$ZippedAll;
class	scala/collection/IterableViewLike$ZippedAll
Asciz	other;
Asciz	()Lscala/collection/Iterable;;
NameAndType	other:()Lscala/collection/Iterable;
InterfaceMethod	scala/collection/IterableViewLike$ZippedAll.other:()Lscala/collection/Iterable;
Asciz	scala/collection/TraversableOnce;
class	scala/collection/TraversableOnce
Asciz	toSeq;
Asciz	()Lscala/collection/Seq;;
NameAndType	toSeq:()Lscala/collection/Seq;
InterfaceMethod	scala/collection/TraversableOnce.toSeq:()Lscala/collection/Seq;
Asciz	$this;
Asciz	Lscala/collection/SeqViewLike$ZippedAll;;
Asciz	LocalVariableTable;
Asciz	length;
Asciz	(Lscala/collection/SeqViewLike$ZippedAll;)I;
Asciz	scala/Predef$;
class	scala/Predef$
Asciz	MODULE$;
Asciz	Lscala/Predef$;;
NameAndType	MODULE$:Lscala/Predef$;
Field	scala/Predef$.MODULE$:Lscala/Predef$;
Asciz	scala/collection/SeqViewLike$ZippedAll;
class	scala/collection/SeqViewLike$ZippedAll
Asciz	scala$collection$SeqViewLike$ZippedAll$$$outer;
Asciz	()Lscala/collection/SeqViewLike;;
NameAndType	scala$collection$SeqViewLike$ZippedAll$$$outer:()Lscala/collection/SeqViewLike;
InterfaceMethod	scala/collection/SeqViewLike$ZippedAll.scala$collection$SeqViewLike$ZippedAll$$$outer:()Lscala/collection/SeqViewLike;
Asciz	scala/collection/SeqLike;
class	scala/collection/SeqLike
Asciz	()I;
NameAndType	length:()I
InterfaceMethod	scala/collection/SeqLike.length:()I
Asciz	intWrapper;
Asciz	(I)Lscala/runtime/RichInt;;
NameAndType	intWrapper:(I)Lscala/runtime/RichInt;
Method	scala/Predef$.intWrapper:(I)Lscala/runtime/RichInt;
NameAndType	thatSeq:()Lscala/collection/Seq;
InterfaceMethod	scala/collection/SeqViewLike$ZippedAll.thatSeq:()Lscala/collection/Seq;
Asciz	scala/runtime/RichInt;
class	scala/runtime/RichInt
Asciz	max;
Asciz	(I)I;
NameAndType	max:(I)I
Method	scala/runtime/RichInt.max:(I)I
Asciz	apply;
Asciz	(Lscala/collection/SeqViewLike$ZippedAll;I)Lscala/Tuple2;;
Asciz	scala/Tuple2;
class	scala/Tuple2
Asciz	(I)Ljava/lang/Object;;
NameAndType	apply:(I)Ljava/lang/Object;
InterfaceMethod	scala/collection/SeqLike.apply:(I)Ljava/lang/Object;
Asciz	thisElem;
Asciz	()Ljava/lang/Object;;
NameAndType	thisElem:()Ljava/lang/Object;
InterfaceMethod	scala/collection/IterableViewLike$ZippedAll.thisElem:()Ljava/lang/Object;
Asciz	thatElem;
NameAndType	thatElem:()Ljava/lang/Object;
InterfaceMethod	scala/collection/IterableViewLike$ZippedAll.thatElem:()Ljava/lang/Object;
Asciz	<init>;
Asciz	(Ljava/lang/Object;Ljava/lang/Object;)V;
NameAndType	"<init>":(Ljava/lang/Object;Ljava/lang/Object;)V
Method	scala/Tuple2."<init>":(Ljava/lang/Object;Ljava/lang/Object;)V
Asciz	idx;
Asciz	I;
Asciz	$init$;
Asciz	(Lscala/collection/SeqViewLike$ZippedAll;)V;
Asciz	Scala;
Asciz	InnerClasses;
Asciz	scala/collection/SeqViewLike;
class	scala/collection/SeqViewLike
Asciz	ZippedAll;
Asciz	scala/collection/IterableViewLike;
class	scala/collection/IterableViewLike
Asciz	scala/collection/SeqViewLike$ZippedAll$class;
class	scala/collection/SeqViewLike$ZippedAll$class
Asciz	java/lang/Object;
class	java/lang/Object

{
public static scala.collection.Seq thatSeq(scala.collection.SeqViewLike$ZippedAll);
  Signature: (Lscala/collection/SeqViewLike$ZippedAll;)Lscala/collection/Seq;
  Code:
   Stack=1, Locals=1, Args_size=1
	aload_0
	invokeinterface	InterfaceMethod scala/collection/IterableViewLike$ZippedAll.other:()Lscala/collection/Iterable;
	invokeinterface	InterfaceMethod scala/collection/TraversableOnce.toSeq:()Lscala/collection/Seq;
	areturn
  Labels:
  LocalVariableTable: 
   Start  Length  Slot  Name   Signature
   0      12      0    $this       Lscala/collection/SeqViewLike$ZippedAll;


public static int length(scala.collection.SeqViewLike$ZippedAll);
  Signature: (Lscala/collection/SeqViewLike$ZippedAll;)I
  Code:
   Stack=2, Locals=1, Args_size=1
	getstatic	Field scala/Predef$.MODULE$:Lscala/Predef$;
	aload_0
	invokeinterface	InterfaceMethod scala/collection/SeqViewLike$ZippedAll.scala$collection$SeqViewLike$ZippedAll$$$outer:()Lscala/collection/SeqViewLike;
	invokeinterface	InterfaceMethod scala/collection/SeqLike.length:()I
	invokevirtual	Method scala/Predef$.intWrapper:(I)Lscala/runtime/RichInt;
	aload_0
	invokeinterface	InterfaceMethod scala/collection/SeqViewLike$ZippedAll.thatSeq:()Lscala/collection/Seq;
	invokeinterface	InterfaceMethod scala/collection/SeqLike.length:()I
	invokevirtual	Method scala/runtime/RichInt.max:(I)I
	ireturn
  Labels:
  LocalVariableTable: 
   Start  Length  Slot  Name   Signature
   0      32      0    $this       Lscala/collection/SeqViewLike$ZippedAll;


public static scala.Tuple2 apply(scala.collection.SeqViewLike$ZippedAll, int);
  Signature: (Lscala/collection/SeqViewLike$ZippedAll;I)Lscala/Tuple2;
  Code:
   Stack=5, Locals=2, Args_size=2
	new	class scala/Tuple2
	dup
	iload_1
	aload_0
	invokeinterface	InterfaceMethod scala/collection/SeqViewLike$ZippedAll.scala$collection$SeqViewLike$ZippedAll$$$outer:()Lscala/collection/SeqViewLike;
	invokeinterface	InterfaceMethod scala/collection/SeqLike.length:()I
	if_icmpge	l1 // aload_0
	aload_0
	invokeinterface	InterfaceMethod scala/collection/SeqViewLike$ZippedAll.scala$collection$SeqViewLike$ZippedAll$$$outer:()Lscala/collection/SeqViewLike;
	iload_1
	invokeinterface	InterfaceMethod scala/collection/SeqLike.apply:(I)Ljava/lang/Object;
	goto	l2 // iload_1
l1	aload_0
	invokeinterface	InterfaceMethod scala/collection/IterableViewLike$ZippedAll.thisElem:()Ljava/lang/Object;
l2	iload_1
	aload_0
	invokeinterface	InterfaceMethod scala/collection/SeqViewLike$ZippedAll.thatSeq:()Lscala/collection/Seq;
	invokeinterface	InterfaceMethod scala/collection/SeqLike.length:()I
	if_icmpge	l3 // aload_0
	aload_0
	invokeinterface	InterfaceMethod scala/collection/SeqViewLike$ZippedAll.thatSeq:()Lscala/collection/Seq;
	iload_1
	invokeinterface	InterfaceMethod scala/collection/SeqLike.apply:(I)Ljava/lang/Object;
	goto	l4 // invokespecial
l3	aload_0
	invokeinterface	InterfaceMethod scala/collection/IterableViewLike$ZippedAll.thatElem:()Ljava/lang/Object;
l4	invokespecial	Method scala/Tuple2."<init>":(Ljava/lang/Object;Ljava/lang/Object;)V
	areturn
  Labels:
   	l1 = 34 // aload_0
   	l2 = 40 // iload_1
   	l3 = 70 // aload_0
   	l4 = 76 // invokespecial
  LocalVariableTable: 
   Start  Length  Slot  Name   Signature
   0      80      0    $this       Lscala/collection/SeqViewLike$ZippedAll;
   0      80      1    idx       I


public static void $init$(scala.collection.SeqViewLike$ZippedAll);
  Signature: (Lscala/collection/SeqViewLike$ZippedAll;)V
  Code:
   Stack=0, Locals=1, Args_size=1
	return
  Labels:
  LocalVariableTable: 
   Start  Length  Slot  Name   Signature
   0      1      0    $this       Lscala/collection/SeqViewLike$ZippedAll;


}

