Compiled from "SeqViewLike.scala"
public abstract class scala.collection.SeqViewLike$Mapped$class extends java.lang.Object
  SourceFile: "SeqViewLike.scala"
  Scala: length = 0x
   
  InnerClass: 
   public abstract Mapped=class scala/collection/SeqViewLike$Mapped of class scala/collection/SeqViewLike
   public abstract Mapped=class scala/collection/TraversableViewLike$Mapped of class scala/collection/TraversableViewLike
  minor version: 0
  major version: 49
  Constant pool:
Asciz	SourceFile;
Asciz	SeqViewLike.scala;
Asciz	length;
Asciz	(Lscala/collection/SeqViewLike$Mapped;)I;
Asciz	Code;
Asciz	LineNumberTable;
Asciz	scala/collection/SeqViewLike$Mapped;
class	scala/collection/SeqViewLike$Mapped
Asciz	scala$collection$SeqViewLike$Mapped$$$outer;
Asciz	()Lscala/collection/SeqViewLike;;
NameAndType	scala$collection$SeqViewLike$Mapped$$$outer:()Lscala/collection/SeqViewLike;
InterfaceMethod	scala/collection/SeqViewLike$Mapped.scala$collection$SeqViewLike$Mapped$$$outer:()Lscala/collection/SeqViewLike;
Asciz	scala/collection/SeqLike;
class	scala/collection/SeqLike
Asciz	()I;
NameAndType	length:()I
InterfaceMethod	scala/collection/SeqLike.length:()I
Asciz	$this;
Asciz	Lscala/collection/SeqViewLike$Mapped;;
Asciz	LocalVariableTable;
Asciz	apply;
Asciz	(Lscala/collection/SeqViewLike$Mapped;I)Ljava/lang/Object;;
Asciz	scala/collection/TraversableViewLike$Mapped;
class	scala/collection/TraversableViewLike$Mapped
Asciz	mapping;
Asciz	()Lscala/Function1;;
NameAndType	mapping:()Lscala/Function1;
InterfaceMethod	scala/collection/TraversableViewLike$Mapped.mapping:()Lscala/Function1;
Asciz	(I)Ljava/lang/Object;;
NameAndType	apply:(I)Ljava/lang/Object;
InterfaceMethod	scala/collection/SeqLike.apply:(I)Ljava/lang/Object;
Asciz	scala/Function1;
class	scala/Function1
Asciz	(Ljava/lang/Object;)Ljava/lang/Object;;
NameAndType	apply:(Ljava/lang/Object;)Ljava/lang/Object;
InterfaceMethod	scala/Function1.apply:(Ljava/lang/Object;)Ljava/lang/Object;
Asciz	idx;
Asciz	I;
Asciz	$init$;
Asciz	(Lscala/collection/SeqViewLike$Mapped;)V;
Asciz	Scala;
Asciz	InnerClasses;
Asciz	scala/collection/SeqViewLike;
class	scala/collection/SeqViewLike
Asciz	Mapped;
Asciz	scala/collection/TraversableViewLike;
class	scala/collection/TraversableViewLike
Asciz	scala/collection/SeqViewLike$Mapped$class;
class	scala/collection/SeqViewLike$Mapped$class
Asciz	java/lang/Object;
class	java/lang/Object

{
public static int length(scala.collection.SeqViewLike$Mapped);
  Signature: (Lscala/collection/SeqViewLike$Mapped;)I
  Code:
   Stack=1, Locals=1, Args_size=1
	aload_0
	invokeinterface	InterfaceMethod scala/collection/SeqViewLike$Mapped.scala$collection$SeqViewLike$Mapped$$$outer:()Lscala/collection/SeqViewLike;
	invokeinterface	InterfaceMethod scala/collection/SeqLike.length:()I
	ireturn
  Labels:
  LocalVariableTable: 
   Start  Length  Slot  Name   Signature
   0      12      0    $this       Lscala/collection/SeqViewLike$Mapped;


public static java.lang.Object apply(scala.collection.SeqViewLike$Mapped, int);
  Signature: (Lscala/collection/SeqViewLike$Mapped;I)Ljava/lang/Object;
  Code:
   Stack=3, Locals=2, Args_size=2
	aload_0
	invokeinterface	InterfaceMethod scala/collection/TraversableViewLike$Mapped.mapping:()Lscala/Function1;
	aload_0
	invokeinterface	InterfaceMethod scala/collection/SeqViewLike$Mapped.scala$collection$SeqViewLike$Mapped$$$outer:()Lscala/collection/SeqViewLike;
	iload_1
	invokeinterface	InterfaceMethod scala/collection/SeqLike.apply:(I)Ljava/lang/Object;
	invokeinterface	InterfaceMethod scala/Function1.apply:(Ljava/lang/Object;)Ljava/lang/Object;
	areturn
  Labels:
  LocalVariableTable: 
   Start  Length  Slot  Name   Signature
   0      24      0    $this       Lscala/collection/SeqViewLike$Mapped;
   0      24      1    idx       I


public static void $init$(scala.collection.SeqViewLike$Mapped);
  Signature: (Lscala/collection/SeqViewLike$Mapped;)V
  Code:
   Stack=0, Locals=1, Args_size=1
	return
  Labels:
  LocalVariableTable: 
   Start  Length  Slot  Name   Signature
   0      1      0    $this       Lscala/collection/SeqViewLike$Mapped;


}

