Compiled from "SeqViewLike.scala"
public abstract class scala.collection.SeqViewLike$FlatMapped$class extends java.lang.Object
  SourceFile: "SeqViewLike.scala"
  Scala: length = 0x
   
  InnerClass: 
   public abstract ByOne=class scala/collection/immutable/Range$ByOne of class scala/collection/immutable/Range
   public abstract FlatMapped=class scala/collection/SeqViewLike$FlatMapped of class scala/collection/SeqViewLike
   public abstract FlatMapped=class scala/collection/TraversableViewLike$FlatMapped of class scala/collection/TraversableViewLike
   public final $anonfun$index$1=class scala/collection/SeqViewLike$FlatMapped$$anonfun$index$1 of class scala/collection/SeqViewLike$FlatMapped
  minor version: 0
  major version: 49
  Constant pool:
Asciz	SourceFile;
Asciz	SeqViewLike.scala;
Asciz	index;
Asciz	(Lscala/collection/SeqViewLike$FlatMapped;)[I;
Asciz	Code;
Asciz	LineNumberTable;
Asciz	scala/collection/SeqViewLike$FlatMapped;
class	scala/collection/SeqViewLike$FlatMapped
Asciz	scala$collection$SeqViewLike$FlatMapped$$$outer;
Asciz	()Lscala/collection/SeqViewLike;;
NameAndType	scala$collection$SeqViewLike$FlatMapped$$$outer:()Lscala/collection/SeqViewLike;
InterfaceMethod	scala/collection/SeqViewLike$FlatMapped.scala$collection$SeqViewLike$FlatMapped$$$outer:()Lscala/collection/SeqViewLike;
Asciz	scala/collection/SeqLike;
class	scala/collection/SeqLike
Asciz	length;
Asciz	()I;
NameAndType	length:()I
InterfaceMethod	scala/collection/SeqLike.length:()I
Asciz	scala/Predef$;
class	scala/Predef$
Asciz	MODULE$;
Asciz	Lscala/Predef$;;
NameAndType	MODULE$:Lscala/Predef$;
Field	scala/Predef$.MODULE$:Lscala/Predef$;
Asciz	intWrapper;
Asciz	(I)Lscala/runtime/RichInt;;
NameAndType	intWrapper:(I)Lscala/runtime/RichInt;
Method	scala/Predef$.intWrapper:(I)Lscala/runtime/RichInt;
Asciz	scala/runtime/RichInt;
class	scala/runtime/RichInt
Asciz	until;
Asciz	(I)Lscala/collection/immutable/Range$ByOne;;
NameAndType	until:(I)Lscala/collection/immutable/Range$ByOne;
Method	scala/runtime/RichInt.until:(I)Lscala/collection/immutable/Range$ByOne;
Asciz	scala/collection/SeqViewLike$FlatMapped$$anonfun$index$1;
class	scala/collection/SeqViewLike$FlatMapped$$anonfun$index$1
Asciz	<init>;
Asciz	(Lscala/collection/SeqViewLike$FlatMapped;[I)V;
NameAndType	"<init>":(Lscala/collection/SeqViewLike$FlatMapped;[I)V
Method	scala/collection/SeqViewLike$FlatMapped$$anonfun$index$1."<init>":(Lscala/collection/SeqViewLike$FlatMapped;[I)V
Asciz	scala/collection/immutable/Range$ByOne;
class	scala/collection/immutable/Range$ByOne
Asciz	foreach;
Asciz	(Lscala/Function1;)V;
NameAndType	foreach:(Lscala/Function1;)V
InterfaceMethod	scala/collection/immutable/Range$ByOne.foreach:(Lscala/Function1;)V
Asciz	$this;
Asciz	Lscala/collection/SeqViewLike$FlatMapped;;
Asciz	index$1;
Asciz	[I;
Asciz	LocalVariableTable;
Asciz	findRow;
Asciz	(Lscala/collection/SeqViewLike$FlatMapped;III)I;
Asciz	()[I;
NameAndType	index:()[I
InterfaceMethod	scala/collection/SeqViewLike$FlatMapped.index:()[I
Asciz	(III)I;
NameAndType	findRow:(III)I
InterfaceMethod	scala/collection/SeqViewLike$FlatMapped.findRow:(III)I
Asciz	idx;
Asciz	I;
Asciz	lo;
Asciz	hi;
Asciz	mid;
Asciz	(Lscala/collection/SeqViewLike$FlatMapped;)I;
Asciz	apply;
Asciz	(Lscala/collection/SeqViewLike$FlatMapped;I)Ljava/lang/Object;;
Asciz	scala/collection/TraversableViewLike$FlatMapped;
class	scala/collection/TraversableViewLike$FlatMapped
Asciz	mapping;
Asciz	()Lscala/Function1;;
NameAndType	mapping:()Lscala/Function1;
InterfaceMethod	scala/collection/TraversableViewLike$FlatMapped.mapping:()Lscala/Function1;
Asciz	(I)Ljava/lang/Object;;
NameAndType	apply:(I)Ljava/lang/Object;
InterfaceMethod	scala/collection/SeqLike.apply:(I)Ljava/lang/Object;
Asciz	scala/Function1;
class	scala/Function1
Asciz	(Ljava/lang/Object;)Ljava/lang/Object;;
NameAndType	apply:(Ljava/lang/Object;)Ljava/lang/Object;
InterfaceMethod	scala/Function1.apply:(Ljava/lang/Object;)Ljava/lang/Object;
Asciz	scala/collection/TraversableOnce;
class	scala/collection/TraversableOnce
Asciz	toSeq;
Asciz	()Lscala/collection/Seq;;
NameAndType	toSeq:()Lscala/collection/Seq;
InterfaceMethod	scala/collection/TraversableOnce.toSeq:()Lscala/collection/Seq;
Asciz	row;
Asciz	$init$;
Asciz	(Lscala/collection/SeqViewLike$FlatMapped;)V;
Asciz	Scala;
Asciz	InnerClasses;
Asciz	scala/collection/immutable/Range;
class	scala/collection/immutable/Range
Asciz	ByOne;
Asciz	scala/collection/SeqViewLike;
class	scala/collection/SeqViewLike
Asciz	FlatMapped;
Asciz	scala/collection/TraversableViewLike;
class	scala/collection/TraversableViewLike
Asciz	$anonfun$index$1;
Asciz	scala/collection/SeqViewLike$FlatMapped$class;
class	scala/collection/SeqViewLike$FlatMapped$class
Asciz	java/lang/Object;
class	java/lang/Object

{
public static int[] index(scala.collection.SeqViewLike$FlatMapped);
  Signature: (Lscala/collection/SeqViewLike$FlatMapped;)[I
  Code:
   Stack=5, Locals=2, Args_size=1
	aload_0
	invokeinterface	InterfaceMethod scala/collection/SeqViewLike$FlatMapped.scala$collection$SeqViewLike$FlatMapped$$$outer:()Lscala/collection/SeqViewLike;
	invokeinterface	InterfaceMethod scala/collection/SeqLike.length:()I
	iconst_1
	iadd
	newarray int
	astore_1
	aload_1
	iconst_0
	iconst_0
	iastore
	getstatic	Field scala/Predef$.MODULE$:Lscala/Predef$;
	iconst_0
	invokevirtual	Method scala/Predef$.intWrapper:(I)Lscala/runtime/RichInt;
	aload_0
	invokeinterface	InterfaceMethod scala/collection/SeqViewLike$FlatMapped.scala$collection$SeqViewLike$FlatMapped$$$outer:()Lscala/collection/SeqViewLike;
	invokeinterface	InterfaceMethod scala/collection/SeqLike.length:()I
	invokevirtual	Method scala/runtime/RichInt.until:(I)Lscala/collection/immutable/Range$ByOne;
	new	class scala/collection/SeqViewLike$FlatMapped$$anonfun$index$1
	dup
	aload_0
	aload_1
	invokespecial	Method scala/collection/SeqViewLike$FlatMapped$$anonfun$index$1."<init>":(Lscala/collection/SeqViewLike$FlatMapped;[I)V
	invokeinterface	InterfaceMethod scala/collection/immutable/Range$ByOne.foreach:(Lscala/Function1;)V
	aload_1
	areturn
  Labels:
  LocalVariableTable: 
   Start  Length  Slot  Name   Signature
   0      57      0    $this       Lscala/collection/SeqViewLike$FlatMapped;
   16      40      1    index$1       [I


public static int findRow(scala.collection.SeqViewLike$FlatMapped, int, int, int);
  Signature: (Lscala/collection/SeqViewLike$FlatMapped;III)I
  Code:
   Stack=5, Locals=5, Args_size=4
	iload_2
	iload_3
	iadd
	iconst_2
	idiv
	istore	4
	iload_1
	aload_0
	invokeinterface	InterfaceMethod scala/collection/SeqViewLike$FlatMapped.index:()[I
	iload	4
	iaload
	if_icmpge	l1 // iload_1
	aload_0
	iload_1
	iload_2
	iload	4
	iconst_1
	isub
	invokeinterface	InterfaceMethod scala/collection/SeqViewLike$FlatMapped.findRow:(III)I
	goto	l2 // ireturn
l1	iload_1
	aload_0
	invokeinterface	InterfaceMethod scala/collection/SeqViewLike$FlatMapped.index:()[I
	iload	4
	iconst_1
	iadd
	iaload
	if_icmplt	l3 // iload
	aload_0
	iload_1
	iload	4
	iconst_1
	iadd
	iload_3
	invokeinterface	InterfaceMethod scala/collection/SeqViewLike$FlatMapped.findRow:(III)I
	goto	l2 // ireturn
l3	iload	4
l2	ireturn
  Labels:
   	l1 = 35 // iload_1
   	l3 = 65 // iload
   	l2 = 67 // ireturn
  LocalVariableTable: 
   Start  Length  Slot  Name   Signature
   0      68      0    $this       Lscala/collection/SeqViewLike$FlatMapped;
   0      68      1    idx       I
   0      68      2    lo       I
   0      68      3    hi       I
   7      61      4    mid       I


public static int length(scala.collection.SeqViewLike$FlatMapped);
  Signature: (Lscala/collection/SeqViewLike$FlatMapped;)I
  Code:
   Stack=2, Locals=1, Args_size=1
	aload_0
	invokeinterface	InterfaceMethod scala/collection/SeqViewLike$FlatMapped.index:()[I
	aload_0
	invokeinterface	InterfaceMethod scala/collection/SeqViewLike$FlatMapped.scala$collection$SeqViewLike$FlatMapped$$$outer:()Lscala/collection/SeqViewLike;
	invokeinterface	InterfaceMethod scala/collection/SeqLike.length:()I
	iaload
	ireturn
  Labels:
  LocalVariableTable: 
   Start  Length  Slot  Name   Signature
   0      19      0    $this       Lscala/collection/SeqViewLike$FlatMapped;


public static java.lang.Object apply(scala.collection.SeqViewLike$FlatMapped, int);
  Signature: (Lscala/collection/SeqViewLike$FlatMapped;I)Ljava/lang/Object;
  Code:
   Stack=5, Locals=3, Args_size=2
	aload_0
	iload_1
	iconst_0
	aload_0
	invokeinterface	InterfaceMethod scala/collection/SeqViewLike$FlatMapped.scala$collection$SeqViewLike$FlatMapped$$$outer:()Lscala/collection/SeqViewLike;
	invokeinterface	InterfaceMethod scala/collection/SeqLike.length:()I
	iconst_1
	isub
	invokeinterface	InterfaceMethod scala/collection/SeqViewLike$FlatMapped.findRow:(III)I
	istore_2
	aload_0
	invokeinterface	InterfaceMethod scala/collection/TraversableViewLike$FlatMapped.mapping:()Lscala/Function1;
	aload_0
	invokeinterface	InterfaceMethod scala/collection/SeqViewLike$FlatMapped.scala$collection$SeqViewLike$FlatMapped$$$outer:()Lscala/collection/SeqViewLike;
	iload_2
	invokeinterface	InterfaceMethod scala/collection/SeqLike.apply:(I)Ljava/lang/Object;
	invokeinterface	InterfaceMethod scala/Function1.apply:(Ljava/lang/Object;)Ljava/lang/Object;
	checkcast	class scala/collection/TraversableOnce
	invokeinterface	InterfaceMethod scala/collection/TraversableOnce.toSeq:()Lscala/collection/Seq;
	iload_1
	aload_0
	invokeinterface	InterfaceMethod scala/collection/SeqViewLike$FlatMapped.index:()[I
	iload_2
	iaload
	isub
	invokeinterface	InterfaceMethod scala/collection/SeqLike.apply:(I)Ljava/lang/Object;
	areturn
  Labels:
  LocalVariableTable: 
   Start  Length  Slot  Name   Signature
   0      69      0    $this       Lscala/collection/SeqViewLike$FlatMapped;
   0      69      1    idx       I
   22      46      2    row       I


public static void $init$(scala.collection.SeqViewLike$FlatMapped);
  Signature: (Lscala/collection/SeqViewLike$FlatMapped;)V
  Code:
   Stack=0, Locals=1, Args_size=1
	return
  Labels:
  LocalVariableTable: 
   Start  Length  Slot  Name   Signature
   0      1      0    $this       Lscala/collection/SeqViewLike$FlatMapped;


}

