Compiled from "SeqViewLike.scala"
public final class scala.collection.SeqViewLike$$anonfun$sorted$1 extends scala.runtime.AbstractFunction0 implements java.io.Serializable
  SourceFile: "SeqViewLike.scala"
  Scala: length = 0x
   
  InnerClass: 
   public final $anonfun$sorted$1=class scala/collection/SeqViewLike$$anonfun$sorted$1 of class scala/collection/SeqViewLike
  minor version: 0
  major version: 49
  Constant pool:
Asciz	SourceFile;
Asciz	SeqViewLike.scala;
Asciz	<clinit>;
Asciz	()V;
Asciz	Code;
Asciz	serialVersionUID;
Asciz	J;
Asciz	scala/collection/SeqViewLike$$anonfun$sorted$1;
class	scala/collection/SeqViewLike$$anonfun$sorted$1
NameAndType	serialVersionUID:J
Field	scala/collection/SeqViewLike$$anonfun$sorted$1.serialVersionUID:J
Asciz	ord$1;
Asciz	Lscala/math/Ordering;;
Asciz	$outer;
Asciz	Lscala/collection/SeqViewLike;;
Asciz	apply;
Asciz	()Lscala/collection/Seq;;
Asciz	LineNumberTable;
NameAndType	$outer:Lscala/collection/SeqViewLike;
Field	scala/collection/SeqViewLike$$anonfun$sorted$1.$outer:Lscala/collection/SeqViewLike;
Asciz	scala/collection/TraversableViewLike;
class	scala/collection/TraversableViewLike
Asciz	thisSeq;
NameAndType	thisSeq:()Lscala/collection/Seq;
InterfaceMethod	scala/collection/TraversableViewLike.thisSeq:()Lscala/collection/Seq;
NameAndType	ord$1:Lscala/math/Ordering;
Field	scala/collection/SeqViewLike$$anonfun$sorted$1.ord$1:Lscala/math/Ordering;
Asciz	scala/collection/SeqLike;
class	scala/collection/SeqLike
Asciz	sorted;
Asciz	(Lscala/math/Ordering;)Ljava/lang/Object;;
NameAndType	sorted:(Lscala/math/Ordering;)Ljava/lang/Object;
InterfaceMethod	scala/collection/SeqLike.sorted:(Lscala/math/Ordering;)Ljava/lang/Object;
Asciz	scala/collection/Seq;
class	scala/collection/Seq
Asciz	()Lscala/collection/Seq<TA;>;;
Asciz	Signature;
Asciz	()Ljava/lang/Object;;
NameAndType	apply:()Lscala/collection/Seq;
Method	scala/collection/SeqViewLike$$anonfun$sorted$1.apply:()Lscala/collection/Seq;
Asciz	<init>;
Asciz	(Lscala/collection/SeqViewLike;Lscala/math/Ordering;)V;
Asciz	java/lang/NullPointerException;
class	java/lang/NullPointerException
NameAndType	"<init>":()V
Method	java/lang/NullPointerException."<init>":()V
Asciz	scala/runtime/AbstractFunction0;
class	scala/runtime/AbstractFunction0
Method	scala/runtime/AbstractFunction0."<init>":()V
Asciz	this;
Asciz	Lscala/collection/SeqViewLike$$anonfun$sorted$1;;
Asciz	LocalVariableTable;
Asciz	(Lscala/collection/SeqViewLike<TA;TColl;TThis;>;)V;
Asciz	Scala;
Asciz	InnerClasses;
Asciz	scala/collection/SeqViewLike;
class	scala/collection/SeqViewLike
Asciz	$anonfun$sorted$1;
Asciz	java/io/Serializable;
class	java/io/Serializable

{
public static final long serialVersionUID;
  Signature: J

public final scala.math.Ordering ord$1;
  Signature: Lscala/math/Ordering;

public final scala.collection.SeqViewLike $outer;
  Signature: Lscala/collection/SeqViewLike;

public static {};
  Signature: ()V
  Code:
   Stack=2, Locals=0, Args_size=0
	lconst_0
	putstatic	Field serialVersionUID:J
	return
  Labels:

public final scala.collection.Seq apply();
  Signature: ()Lscala/collection/Seq;
  Code:
   Stack=2, Locals=1, Args_size=1
	aload_0
	getfield	Field $outer:Lscala/collection/SeqViewLike;
	invokeinterface	InterfaceMethod scala/collection/TraversableViewLike.thisSeq:()Lscala/collection/Seq;
	aload_0
	getfield	Field ord$1:Lscala/math/Ordering;
	invokeinterface	InterfaceMethod scala/collection/SeqLike.sorted:(Lscala/math/Ordering;)Ljava/lang/Object;
	checkcast	class scala/collection/Seq
	areturn
  Labels:
  Signature: length = 0x2
   00 24 

public final java.lang.Object apply();
  Signature: ()Ljava/lang/Object;
  Code:
   Stack=1, Locals=1, Args_size=1
	aload_0
	invokevirtual	Method apply:()Lscala/collection/Seq;
	areturn
  Labels:

public scala.collection.SeqViewLike$$anonfun$sorted$1(scala.collection.SeqViewLike, scala.math.Ordering);
  Signature: (Lscala/collection/SeqViewLike;Lscala/math/Ordering;)V
  Code:
   Stack=2, Locals=3, Args_size=3
	aload_1
	ifnonnull	l1 // aload_0
	new	class java/lang/NullPointerException
	dup
	invokespecial	Method java/lang/NullPointerException."<init>":()V
	athrow
l1	aload_0
	aload_1
	putfield	Field $outer:Lscala/collection/SeqViewLike;
	aload_0
	aload_2
	putfield	Field ord$1:Lscala/math/Ordering;
	aload_0
	invokespecial	Method scala/runtime/AbstractFunction0."<init>":()V
	return
  Labels:
   	l1 = 12 // aload_0
  LocalVariableTable: 
   Start  Length  Slot  Name   Signature
   0      27      0    this       Lscala/collection/SeqViewLike$$anonfun$sorted$1;
   0      27      1    $outer       Lscala/collection/SeqViewLike;

  Signature: length = 0x2
   00 35 

}

