Compiled from "SeqViewLike.scala"
public abstract class scala.collection.SeqViewLike$Zipped$class extends java.lang.Object
  SourceFile: "SeqViewLike.scala"
  Scala: length = 0x
   
  InnerClass: 
   public abstract Zipped=class scala/collection/SeqViewLike$Zipped of class scala/collection/SeqViewLike
   public abstract Zipped=class scala/collection/IterableViewLike$Zipped of class scala/collection/IterableViewLike
  minor version: 0
  major version: 49
  Constant pool:
Asciz	SourceFile;
Asciz	SeqViewLike.scala;
Asciz	thatSeq;
Asciz	(Lscala/collection/SeqViewLike$Zipped;)Lscala/collection/Seq;;
Asciz	Code;
Asciz	LineNumberTable;
Asciz	scala/collection/IterableViewLike$Zipped;
class	scala/collection/IterableViewLike$Zipped
Asciz	other;
Asciz	()Lscala/collection/Iterable;;
NameAndType	other:()Lscala/collection/Iterable;
InterfaceMethod	scala/collection/IterableViewLike$Zipped.other:()Lscala/collection/Iterable;
Asciz	scala/collection/TraversableLike;
class	scala/collection/TraversableLike
Asciz	toSeq;
Asciz	()Lscala/collection/Seq;;
NameAndType	toSeq:()Lscala/collection/Seq;
InterfaceMethod	scala/collection/TraversableLike.toSeq:()Lscala/collection/Seq;
Asciz	$this;
Asciz	Lscala/collection/SeqViewLike$Zipped;;
Asciz	LocalVariableTable;
Asciz	length;
Asciz	(Lscala/collection/SeqViewLike$Zipped;)I;
Asciz	scala/collection/SeqViewLike$Zipped;
class	scala/collection/SeqViewLike$Zipped
NameAndType	thatSeq:()Lscala/collection/Seq;
InterfaceMethod	scala/collection/SeqViewLike$Zipped.thatSeq:()Lscala/collection/Seq;
Asciz	scala$collection$SeqViewLike$Zipped$$$outer;
Asciz	()Lscala/collection/SeqViewLike;;
NameAndType	scala$collection$SeqViewLike$Zipped$$$outer:()Lscala/collection/SeqViewLike;
InterfaceMethod	scala/collection/SeqViewLike$Zipped.scala$collection$SeqViewLike$Zipped$$$outer:()Lscala/collection/SeqViewLike;
Asciz	scala/collection/SeqLike;
class	scala/collection/SeqLike
Asciz	()I;
NameAndType	length:()I
InterfaceMethod	scala/collection/SeqLike.length:()I
Asciz	lengthCompare;
Asciz	(I)I;
NameAndType	lengthCompare:(I)I
InterfaceMethod	scala/collection/SeqLike.lengthCompare:(I)I
Asciz	apply;
Asciz	(Lscala/collection/SeqViewLike$Zipped;I)Lscala/Tuple2;;
Asciz	scala/Tuple2;
class	scala/Tuple2
Asciz	(I)Ljava/lang/Object;;
NameAndType	apply:(I)Ljava/lang/Object;
InterfaceMethod	scala/collection/SeqLike.apply:(I)Ljava/lang/Object;
Asciz	<init>;
Asciz	(Ljava/lang/Object;Ljava/lang/Object;)V;
NameAndType	"<init>":(Ljava/lang/Object;Ljava/lang/Object;)V
Method	scala/Tuple2."<init>":(Ljava/lang/Object;Ljava/lang/Object;)V
Asciz	idx;
Asciz	I;
Asciz	$init$;
Asciz	(Lscala/collection/SeqViewLike$Zipped;)V;
Asciz	Scala;
Asciz	InnerClasses;
Asciz	scala/collection/SeqViewLike;
class	scala/collection/SeqViewLike
Asciz	Zipped;
Asciz	scala/collection/IterableViewLike;
class	scala/collection/IterableViewLike
Asciz	scala/collection/SeqViewLike$Zipped$class;
class	scala/collection/SeqViewLike$Zipped$class
Asciz	java/lang/Object;
class	java/lang/Object

{
public static scala.collection.Seq thatSeq(scala.collection.SeqViewLike$Zipped);
  Signature: (Lscala/collection/SeqViewLike$Zipped;)Lscala/collection/Seq;
  Code:
   Stack=1, Locals=1, Args_size=1
	aload_0
	invokeinterface	InterfaceMethod scala/collection/IterableViewLike$Zipped.other:()Lscala/collection/Iterable;
	invokeinterface	InterfaceMethod scala/collection/TraversableLike.toSeq:()Lscala/collection/Seq;
	areturn
  Labels:
  LocalVariableTable: 
   Start  Length  Slot  Name   Signature
   0      12      0    $this       Lscala/collection/SeqViewLike$Zipped;


public static int length(scala.collection.SeqViewLike$Zipped);
  Signature: (Lscala/collection/SeqViewLike$Zipped;)I
  Code:
   Stack=2, Locals=1, Args_size=1
	aload_0
	invokeinterface	InterfaceMethod scala/collection/SeqViewLike$Zipped.thatSeq:()Lscala/collection/Seq;
	aload_0
	invokeinterface	InterfaceMethod scala/collection/SeqViewLike$Zipped.scala$collection$SeqViewLike$Zipped$$$outer:()Lscala/collection/SeqViewLike;
	invokeinterface	InterfaceMethod scala/collection/SeqLike.length:()I
	invokeinterface	InterfaceMethod scala/collection/SeqLike.lengthCompare:(I)I
	iconst_0
	if_icmpgt	l1 // aload_0
	aload_0
	invokeinterface	InterfaceMethod scala/collection/SeqViewLike$Zipped.thatSeq:()Lscala/collection/Seq;
	invokeinterface	InterfaceMethod scala/collection/SeqLike.length:()I
	goto	l2 // ireturn
l1	aload_0
	invokeinterface	InterfaceMethod scala/collection/SeqViewLike$Zipped.scala$collection$SeqViewLike$Zipped$$$outer:()Lscala/collection/SeqViewLike;
	invokeinterface	InterfaceMethod scala/collection/SeqLike.length:()I
l2	ireturn
  Labels:
   	l1 = 40 // aload_0
   	l2 = 51 // ireturn
  LocalVariableTable: 
   Start  Length  Slot  Name   Signature
   0      52      0    $this       Lscala/collection/SeqViewLike$Zipped;


public static scala.Tuple2 apply(scala.collection.SeqViewLike$Zipped, int);
  Signature: (Lscala/collection/SeqViewLike$Zipped;I)Lscala/Tuple2;
  Code:
   Stack=5, Locals=2, Args_size=2
	new	class scala/Tuple2
	dup
	aload_0
	invokeinterface	InterfaceMethod scala/collection/SeqViewLike$Zipped.scala$collection$SeqViewLike$Zipped$$$outer:()Lscala/collection/SeqViewLike;
	iload_1
	invokeinterface	InterfaceMethod scala/collection/SeqLike.apply:(I)Ljava/lang/Object;
	aload_0
	invokeinterface	InterfaceMethod scala/collection/SeqViewLike$Zipped.thatSeq:()Lscala/collection/Seq;
	iload_1
	invokeinterface	InterfaceMethod scala/collection/SeqLike.apply:(I)Ljava/lang/Object;
	invokespecial	Method scala/Tuple2."<init>":(Ljava/lang/Object;Ljava/lang/Object;)V
	areturn
  Labels:
  LocalVariableTable: 
   Start  Length  Slot  Name   Signature
   0      32      0    $this       Lscala/collection/SeqViewLike$Zipped;
   0      32      1    idx       I


public static void $init$(scala.collection.SeqViewLike$Zipped);
  Signature: (Lscala/collection/SeqViewLike$Zipped;)V
  Code:
   Stack=0, Locals=1, Args_size=1
	return
  Labels:
  LocalVariableTable: 
   Start  Length  Slot  Name   Signature
   0      1      0    $this       Lscala/collection/SeqViewLike$Zipped;


}

