Compiled from "SeqViewLike.scala"
public final class scala.collection.SeqViewLike$Filtered$$anonfun$index$2 extends scala.runtime.AbstractFunction1 implements java.io.Serializable
  SourceFile: "SeqViewLike.scala"
  Scala: length = 0x
   
  InnerClass: 
   public abstract Filtered=class scala/collection/SeqViewLike$Filtered of class scala/collection/SeqViewLike
   public abstract Filtered=class scala/collection/TraversableViewLike$Filtered of class scala/collection/TraversableViewLike
   public final $anonfun$index$2=class scala/collection/SeqViewLike$Filtered$$anonfun$index$2 of class scala/collection/SeqViewLike$Filtered
  minor version: 0
  major version: 49
  Constant pool:
Asciz	SourceFile;
Asciz	SeqViewLike.scala;
Asciz	<clinit>;
Asciz	()V;
Asciz	Code;
Asciz	serialVersionUID;
Asciz	J;
Asciz	scala/collection/SeqViewLike$Filtered$$anonfun$index$2;
class	scala/collection/SeqViewLike$Filtered$$anonfun$index$2
NameAndType	serialVersionUID:J
Field	scala/collection/SeqViewLike$Filtered$$anonfun$index$2.serialVersionUID:J
Asciz	$outer;
Asciz	Lscala/collection/SeqViewLike$Filtered;;
Asciz	len$1;
Asciz	Lscala/runtime/IntRef;;
Asciz	arr$1;
Asciz	[I;
Asciz	apply;
Asciz	(I)V;
Asciz	LineNumberTable;
NameAndType	$outer:Lscala/collection/SeqViewLike$Filtered;
Field	scala/collection/SeqViewLike$Filtered$$anonfun$index$2.$outer:Lscala/collection/SeqViewLike$Filtered;
Asciz	scala/collection/TraversableViewLike$Filtered;
class	scala/collection/TraversableViewLike$Filtered
Asciz	pred;
Asciz	()Lscala/Function1;;
NameAndType	pred:()Lscala/Function1;
InterfaceMethod	scala/collection/TraversableViewLike$Filtered.pred:()Lscala/Function1;
Asciz	scala/collection/SeqViewLike$Filtered;
class	scala/collection/SeqViewLike$Filtered
Asciz	scala$collection$SeqViewLike$Filtered$$$outer;
Asciz	()Lscala/collection/SeqViewLike;;
NameAndType	scala$collection$SeqViewLike$Filtered$$$outer:()Lscala/collection/SeqViewLike;
InterfaceMethod	scala/collection/SeqViewLike$Filtered.scala$collection$SeqViewLike$Filtered$$$outer:()Lscala/collection/SeqViewLike;
Asciz	scala/collection/SeqLike;
class	scala/collection/SeqLike
Asciz	(I)Ljava/lang/Object;;
NameAndType	apply:(I)Ljava/lang/Object;
InterfaceMethod	scala/collection/SeqLike.apply:(I)Ljava/lang/Object;
Asciz	scala/Function1;
class	scala/Function1
Asciz	(Ljava/lang/Object;)Ljava/lang/Object;;
NameAndType	apply:(Ljava/lang/Object;)Ljava/lang/Object;
InterfaceMethod	scala/Function1.apply:(Ljava/lang/Object;)Ljava/lang/Object;
Asciz	scala/runtime/BoxesRunTime;
class	scala/runtime/BoxesRunTime
Asciz	unboxToBoolean;
Asciz	(Ljava/lang/Object;)Z;
NameAndType	unboxToBoolean:(Ljava/lang/Object;)Z
Method	scala/runtime/BoxesRunTime.unboxToBoolean:(Ljava/lang/Object;)Z
NameAndType	arr$1:[I
Field	scala/collection/SeqViewLike$Filtered$$anonfun$index$2.arr$1:[I
NameAndType	len$1:Lscala/runtime/IntRef;
Field	scala/collection/SeqViewLike$Filtered$$anonfun$index$2.len$1:Lscala/runtime/IntRef;
Asciz	scala/runtime/IntRef;
class	scala/runtime/IntRef
Asciz	elem;
Asciz	I;
NameAndType	elem:I
Field	scala/runtime/IntRef.elem:I
Asciz	this;
Asciz	Lscala/collection/SeqViewLike$Filtered$$anonfun$index$2;;
Asciz	i;
Asciz	LocalVariableTable;
Asciz	apply$mcVI$sp;
Asciz	v1;
Asciz	unboxToInt;
Asciz	(Ljava/lang/Object;)I;
NameAndType	unboxToInt:(Ljava/lang/Object;)I
Method	scala/runtime/BoxesRunTime.unboxToInt:(Ljava/lang/Object;)I
NameAndType	apply:(I)V
Method	scala/collection/SeqViewLike$Filtered$$anonfun$index$2.apply:(I)V
Asciz	scala/runtime/BoxedUnit;
class	scala/runtime/BoxedUnit
Asciz	UNIT;
Asciz	Lscala/runtime/BoxedUnit;;
NameAndType	UNIT:Lscala/runtime/BoxedUnit;
Field	scala/runtime/BoxedUnit.UNIT:Lscala/runtime/BoxedUnit;
Asciz	Ljava/lang/Object;;
Asciz	<init>;
Asciz	(Lscala/collection/SeqViewLike$Filtered;Lscala/runtime/IntRef;[I)V;
Asciz	java/lang/NullPointerException;
class	java/lang/NullPointerException
NameAndType	"<init>":()V
Method	java/lang/NullPointerException."<init>":()V
Asciz	scala/runtime/AbstractFunction1;
class	scala/runtime/AbstractFunction1
Method	scala/runtime/AbstractFunction1."<init>":()V
Asciz	(Lscala/collection/SeqViewLike<TA;TColl;TThis;>.Filtered;)V;
Asciz	Signature;
Asciz	Scala;
Asciz	InnerClasses;
Asciz	scala/collection/SeqViewLike;
class	scala/collection/SeqViewLike
Asciz	Filtered;
Asciz	scala/collection/TraversableViewLike;
class	scala/collection/TraversableViewLike
Asciz	$anonfun$index$2;
Asciz	java/io/Serializable;
class	java/io/Serializable

{
public static final long serialVersionUID;
  Signature: J

public final scala.collection.SeqViewLike$Filtered $outer;
  Signature: Lscala/collection/SeqViewLike$Filtered;

public final scala.runtime.IntRef len$1;
  Signature: Lscala/runtime/IntRef;

public final int[] arr$1;
  Signature: [I

public static {};
  Signature: ()V
  Code:
   Stack=2, Locals=0, Args_size=0
	lconst_0
	putstatic	Field serialVersionUID:J
	return
  Labels:

public final void apply(int);
  Signature: (I)V
  Code:
   Stack=3, Locals=2, Args_size=2
	aload_0
	getfield	Field $outer:Lscala/collection/SeqViewLike$Filtered;
	invokeinterface	InterfaceMethod scala/collection/TraversableViewLike$Filtered.pred:()Lscala/Function1;
	aload_0
	getfield	Field $outer:Lscala/collection/SeqViewLike$Filtered;
	invokeinterface	InterfaceMethod scala/collection/SeqViewLike$Filtered.scala$collection$SeqViewLike$Filtered$$$outer:()Lscala/collection/SeqViewLike;
	iload_1
	invokeinterface	InterfaceMethod scala/collection/SeqLike.apply:(I)Ljava/lang/Object;
	invokeinterface	InterfaceMethod scala/Function1.apply:(Ljava/lang/Object;)Ljava/lang/Object;
	invokestatic	Method scala/runtime/BoxesRunTime.unboxToBoolean:(Ljava/lang/Object;)Z
	ifeq	l1 // return
	aload_0
	getfield	Field arr$1:[I
	aload_0
	getfield	Field len$1:Lscala/runtime/IntRef;
	getfield	Field scala/runtime/IntRef.elem:I
	iload_1
	iastore
	aload_0
	getfield	Field len$1:Lscala/runtime/IntRef;
	aload_0
	getfield	Field len$1:Lscala/runtime/IntRef;
	getfield	Field scala/runtime/IntRef.elem:I
	iconst_1
	iadd
	putfield	Field scala/runtime/IntRef.elem:I
l1	return
  Labels:
   	l1 = 64 // return
  LocalVariableTable: 
   Start  Length  Slot  Name   Signature
   0      65      0    this       Lscala/collection/SeqViewLike$Filtered$$anonfun$index$2;
   0      65      1    i       I


public void apply$mcVI$sp(int);
  Signature: (I)V
  Code:
   Stack=3, Locals=2, Args_size=2
	aload_0
	getfield	Field $outer:Lscala/collection/SeqViewLike$Filtered;
	invokeinterface	InterfaceMethod scala/collection/TraversableViewLike$Filtered.pred:()Lscala/Function1;
	aload_0
	getfield	Field $outer:Lscala/collection/SeqViewLike$Filtered;
	invokeinterface	InterfaceMethod scala/collection/SeqViewLike$Filtered.scala$collection$SeqViewLike$Filtered$$$outer:()Lscala/collection/SeqViewLike;
	iload_1
	invokeinterface	InterfaceMethod scala/collection/SeqLike.apply:(I)Ljava/lang/Object;
	invokeinterface	InterfaceMethod scala/Function1.apply:(Ljava/lang/Object;)Ljava/lang/Object;
	invokestatic	Method scala/runtime/BoxesRunTime.unboxToBoolean:(Ljava/lang/Object;)Z
	ifeq	l1 // return
	aload_0
	getfield	Field arr$1:[I
	aload_0
	getfield	Field len$1:Lscala/runtime/IntRef;
	getfield	Field scala/runtime/IntRef.elem:I
	iload_1
	iastore
	aload_0
	getfield	Field len$1:Lscala/runtime/IntRef;
	aload_0
	getfield	Field len$1:Lscala/runtime/IntRef;
	getfield	Field scala/runtime/IntRef.elem:I
	iconst_1
	iadd
	putfield	Field scala/runtime/IntRef.elem:I
l1	return
  Labels:
   	l1 = 64 // return
  LocalVariableTable: 
   Start  Length  Slot  Name   Signature
   0      65      0    this       Lscala/collection/SeqViewLike$Filtered$$anonfun$index$2;
   0      65      1    v1       I


public final java.lang.Object apply(java.lang.Object);
  Signature: (Ljava/lang/Object;)Ljava/lang/Object;
  Code:
   Stack=2, Locals=2, Args_size=2
	aload_0
	aload_1
	invokestatic	Method scala/runtime/BoxesRunTime.unboxToInt:(Ljava/lang/Object;)I
	invokevirtual	Method apply:(I)V
	getstatic	Field scala/runtime/BoxedUnit.UNIT:Lscala/runtime/BoxedUnit;
	areturn
  Labels:
  LocalVariableTable: 
   Start  Length  Slot  Name   Signature
   0      12      0    this       Lscala/collection/SeqViewLike$Filtered$$anonfun$index$2;
   0      12      1    v1       Ljava/lang/Object;


public scala.collection.SeqViewLike$Filtered$$anonfun$index$2(scala.collection.SeqViewLike$Filtered, scala.runtime.IntRef, int[]);
  Signature: (Lscala/collection/SeqViewLike$Filtered;Lscala/runtime/IntRef;[I)V
  Code:
   Stack=2, Locals=4, Args_size=4
	aload_1
	ifnonnull	l1 // aload_0
	new	class java/lang/NullPointerException
	dup
	invokespecial	Method java/lang/NullPointerException."<init>":()V
	athrow
l1	aload_0
	aload_1
	putfield	Field $outer:Lscala/collection/SeqViewLike$Filtered;
	aload_0
	aload_2
	putfield	Field len$1:Lscala/runtime/IntRef;
	aload_0
	aload_3
	putfield	Field arr$1:[I
	aload_0
	invokespecial	Method scala/runtime/AbstractFunction1."<init>":()V
	return
  Labels:
   	l1 = 12 // aload_0
  LocalVariableTable: 
   Start  Length  Slot  Name   Signature
   0      32      0    this       Lscala/collection/SeqViewLike$Filtered$$anonfun$index$2;
   0      32      1    $outer       Lscala/collection/SeqViewLike$Filtered;

  Signature: length = 0x2
   00 59 

}

