Compiled from "SeqViewLike.scala"
public final class scala.collection.SeqViewLike$FlatMapped$$anonfun$index$1 extends java.lang.Object implements scala.Function1,scala.ScalaObject,java.io.Serializable
  SourceFile: "SeqViewLike.scala"
  Scala: length = 0x
   
  InnerClass: 
   public abstract FlatMapped=class scala/collection/SeqViewLike$FlatMapped of class scala/collection/SeqViewLike
   public abstract FlatMapped=class scala/collection/TraversableViewLike$FlatMapped of class scala/collection/TraversableViewLike
   public final $anonfun$index$1=class scala/collection/SeqViewLike$FlatMapped$$anonfun$index$1 of class scala/collection/SeqViewLike$FlatMapped
  minor version: 0
  major version: 49
  Constant pool:
Asciz	SourceFile;
Asciz	SeqViewLike.scala;
Asciz	<clinit>;
Asciz	()V;
Asciz	Code;
Asciz	serialVersionUID;
Asciz	J;
Asciz	scala/collection/SeqViewLike$FlatMapped$$anonfun$index$1;
class	scala/collection/SeqViewLike$FlatMapped$$anonfun$index$1
NameAndType	serialVersionUID:J
Field	scala/collection/SeqViewLike$FlatMapped$$anonfun$index$1.serialVersionUID:J
Asciz	index$1;
Asciz	[I;
Asciz	$outer;
Asciz	Lscala/collection/SeqViewLike$FlatMapped;;
Asciz	<init>;
Asciz	(Lscala/collection/SeqViewLike$FlatMapped;[I)V;
Asciz	LineNumberTable;
Asciz	java/lang/NullPointerException;
class	java/lang/NullPointerException
NameAndType	"<init>":()V
Method	java/lang/NullPointerException."<init>":()V
NameAndType	$outer:Lscala/collection/SeqViewLike$FlatMapped;
Field	scala/collection/SeqViewLike$FlatMapped$$anonfun$index$1.$outer:Lscala/collection/SeqViewLike$FlatMapped;
NameAndType	index$1:[I
Field	scala/collection/SeqViewLike$FlatMapped$$anonfun$index$1.index$1:[I
Asciz	java/lang/Object;
class	java/lang/Object
Method	java/lang/Object."<init>":()V
Asciz	scala/Function1$class;
class	scala/Function1$class
Asciz	$init$;
Asciz	(Lscala/Function1;)V;
NameAndType	$init$:(Lscala/Function1;)V
Method	scala/Function1$class.$init$:(Lscala/Function1;)V
Asciz	this;
Asciz	Lscala/collection/SeqViewLike$FlatMapped$$anonfun$index$1;;
Asciz	LocalVariableTable;
Asciz	(Lscala/collection/SeqViewLike<TA;TColl;TThis;>.FlatMapped<TB;>;)V;
Asciz	Signature;
Asciz	apply;
Asciz	(Ljava/lang/Object;)Ljava/lang/Object;;
Asciz	scala/runtime/BoxesRunTime;
class	scala/runtime/BoxesRunTime
Asciz	unboxToInt;
Asciz	(Ljava/lang/Object;)I;
NameAndType	unboxToInt:(Ljava/lang/Object;)I
Method	scala/runtime/BoxesRunTime.unboxToInt:(Ljava/lang/Object;)I
Asciz	(I)V;
NameAndType	apply:(I)V
Method	scala/collection/SeqViewLike$FlatMapped$$anonfun$index$1.apply:(I)V
Asciz	scala/runtime/BoxedUnit;
class	scala/runtime/BoxedUnit
Asciz	UNIT;
Asciz	Lscala/runtime/BoxedUnit;;
NameAndType	UNIT:Lscala/runtime/BoxedUnit;
Field	scala/runtime/BoxedUnit.UNIT:Lscala/runtime/BoxedUnit;
Asciz	v1;
Asciz	Ljava/lang/Object;;
Asciz	scala/collection/TraversableViewLike$FlatMapped;
class	scala/collection/TraversableViewLike$FlatMapped
Asciz	mapping;
Asciz	()Lscala/Function1;;
NameAndType	mapping:()Lscala/Function1;
InterfaceMethod	scala/collection/TraversableViewLike$FlatMapped.mapping:()Lscala/Function1;
Asciz	scala/collection/SeqViewLike$FlatMapped;
class	scala/collection/SeqViewLike$FlatMapped
Asciz	scala$collection$SeqViewLike$FlatMapped$$$outer;
Asciz	()Lscala/collection/SeqViewLike;;
NameAndType	scala$collection$SeqViewLike$FlatMapped$$$outer:()Lscala/collection/SeqViewLike;
InterfaceMethod	scala/collection/SeqViewLike$FlatMapped.scala$collection$SeqViewLike$FlatMapped$$$outer:()Lscala/collection/SeqViewLike;
Asciz	scala/collection/SeqLike;
class	scala/collection/SeqLike
Asciz	(I)Ljava/lang/Object;;
NameAndType	apply:(I)Ljava/lang/Object;
InterfaceMethod	scala/collection/SeqLike.apply:(I)Ljava/lang/Object;
Asciz	scala/Function1;
class	scala/Function1
NameAndType	apply:(Ljava/lang/Object;)Ljava/lang/Object;
InterfaceMethod	scala/Function1.apply:(Ljava/lang/Object;)Ljava/lang/Object;
Asciz	scala/collection/TraversableLike;
class	scala/collection/TraversableLike
Asciz	size;
Asciz	()I;
NameAndType	size:()I
InterfaceMethod	scala/collection/TraversableLike.size:()I
Asciz	i;
Asciz	I;
Asciz	andThen;
Asciz	(Lscala/Function1;)Lscala/Function1;;
Asciz	(Lscala/Function1;Lscala/Function1;)Lscala/Function1;;
NameAndType	andThen:(Lscala/Function1;Lscala/Function1;)Lscala/Function1;
Method	scala/Function1$class.andThen:(Lscala/Function1;Lscala/Function1;)Lscala/Function1;
Asciz	g;
Asciz	Lscala/Function1;;
Asciz	compose;
NameAndType	compose:(Lscala/Function1;Lscala/Function1;)Lscala/Function1;
Method	scala/Function1$class.compose:(Lscala/Function1;Lscala/Function1;)Lscala/Function1;
Asciz	toString;
Asciz	()Ljava/lang/String;;
Asciz	(Lscala/Function1;)Ljava/lang/String;;
NameAndType	toString:(Lscala/Function1;)Ljava/lang/String;
Method	scala/Function1$class.toString:(Lscala/Function1;)Ljava/lang/String;
Asciz	Scala;
Asciz	InnerClasses;
Asciz	scala/collection/SeqViewLike;
class	scala/collection/SeqViewLike
Asciz	FlatMapped;
Asciz	scala/collection/TraversableViewLike;
class	scala/collection/TraversableViewLike
Asciz	$anonfun$index$1;
Asciz	scala/ScalaObject;
class	scala/ScalaObject
Asciz	java/io/Serializable;
class	java/io/Serializable

{
public static final long serialVersionUID;
  Signature: J

private final int[] index$1;
  Signature: [I

private final scala.collection.SeqViewLike$FlatMapped $outer;
  Signature: Lscala/collection/SeqViewLike$FlatMapped;

public static {};
  Signature: ()V
  Code:
   Stack=2, Locals=0, Args_size=0
	lconst_0
	putstatic	Field serialVersionUID:J
	return
  Labels:

public scala.collection.SeqViewLike$FlatMapped$$anonfun$index$1(scala.collection.SeqViewLike$FlatMapped, int[]);
  Signature: (Lscala/collection/SeqViewLike$FlatMapped;[I)V
  Code:
   Stack=2, Locals=3, Args_size=3
	aload_1
	ifnonnull	l1 // aload_0
	new	class java/lang/NullPointerException
	dup
	invokespecial	Method java/lang/NullPointerException."<init>":()V
	athrow
l1	aload_0
	aload_1
	putfield	Field $outer:Lscala/collection/SeqViewLike$FlatMapped;
	aload_0
	aload_2
	putfield	Field index$1:[I
	aload_0
	invokespecial	Method java/lang/Object."<init>":()V
	aload_0
	invokestatic	Method scala/Function1$class.$init$:(Lscala/Function1;)V
	return
  Labels:
   	l1 = 12 // aload_0
  LocalVariableTable: 
   Start  Length  Slot  Name   Signature
   0      31      0    this       Lscala/collection/SeqViewLike$FlatMapped$$anonfun$index$1;
   0      31      1    $outer       Lscala/collection/SeqViewLike$FlatMapped;

  Signature: length = 0x2
   00 27 

public final java.lang.Object apply(java.lang.Object);
  Signature: (Ljava/lang/Object;)Ljava/lang/Object;
  Code:
   Stack=2, Locals=3, Args_size=2
	aload_0
	getfield	Field $outer:Lscala/collection/SeqViewLike$FlatMapped;
	astore_2
	aload_0
	aload_1
	invokestatic	Method scala/runtime/BoxesRunTime.unboxToInt:(Ljava/lang/Object;)I
	invokevirtual	Method apply:(I)V
	getstatic	Field scala/runtime/BoxedUnit.UNIT:Lscala/runtime/BoxedUnit;
	areturn
  Labels:
  LocalVariableTable: 
   Start  Length  Slot  Name   Signature
   0      17      0    this       Lscala/collection/SeqViewLike$FlatMapped$$anonfun$index$1;
   5      12      1    v1       Ljava/lang/Object;


public final void apply(int);
  Signature: (I)V
  Code:
   Stack=6, Locals=3, Args_size=2
	aload_0
	getfield	Field $outer:Lscala/collection/SeqViewLike$FlatMapped;
	astore_2
	aload_0
	getfield	Field index$1:[I
	iload_1
	iconst_1
	iadd
	aload_0
	getfield	Field index$1:[I
	iload_1
	iaload
	aload_0
	getfield	Field $outer:Lscala/collection/SeqViewLike$FlatMapped;
	invokeinterface	InterfaceMethod scala/collection/TraversableViewLike$FlatMapped.mapping:()Lscala/Function1;
	aload_0
	getfield	Field $outer:Lscala/collection/SeqViewLike$FlatMapped;
	invokeinterface	InterfaceMethod scala/collection/SeqViewLike$FlatMapped.scala$collection$SeqViewLike$FlatMapped$$$outer:()Lscala/collection/SeqViewLike;
	iload_1
	invokeinterface	InterfaceMethod scala/collection/SeqLike.apply:(I)Ljava/lang/Object;
	invokeinterface	InterfaceMethod scala/Function1.apply:(Ljava/lang/Object;)Ljava/lang/Object;
	checkcast	class scala/collection/TraversableLike
	invokeinterface	InterfaceMethod scala/collection/TraversableLike.size:()I
	iadd
	iastore
	return
  Labels:
  LocalVariableTable: 
   Start  Length  Slot  Name   Signature
   0      58      0    this       Lscala/collection/SeqViewLike$FlatMapped$$anonfun$index$1;
   5      53      1    i       I


public scala.Function1 andThen(scala.Function1);
  Signature: (Lscala/Function1;)Lscala/Function1;
  Code:
   Stack=2, Locals=2, Args_size=2
	aload_0
	aload_1
	invokestatic	Method scala/Function1$class.andThen:(Lscala/Function1;Lscala/Function1;)Lscala/Function1;
	areturn
  Labels:
  LocalVariableTable: 
   Start  Length  Slot  Name   Signature
   0      6      0    this       Lscala/collection/SeqViewLike$FlatMapped$$anonfun$index$1;
   0      6      1    g       Lscala/Function1;


public scala.Function1 compose(scala.Function1);
  Signature: (Lscala/Function1;)Lscala/Function1;
  Code:
   Stack=2, Locals=2, Args_size=2
	aload_0
	aload_1
	invokestatic	Method scala/Function1$class.compose:(Lscala/Function1;Lscala/Function1;)Lscala/Function1;
	areturn
  Labels:
  LocalVariableTable: 
   Start  Length  Slot  Name   Signature
   0      6      0    this       Lscala/collection/SeqViewLike$FlatMapped$$anonfun$index$1;
   0      6      1    g       Lscala/Function1;


public java.lang.String toString();
  Signature: ()Ljava/lang/String;
  Code:
   Stack=1, Locals=1, Args_size=1
	aload_0
	invokestatic	Method scala/Function1$class.toString:(Lscala/Function1;)Ljava/lang/String;
	areturn
  Labels:

}

