Compiled from "SeqViewLike.scala"
public final class scala.collection.SeqViewLike$$anonfun$union$1 extends scala.runtime.AbstractFunction0 implements java.io.Serializable
  SourceFile: "SeqViewLike.scala"
  Scala: length = 0x
   
  InnerClass: 
   public final $anonfun$union$1=class scala/collection/SeqViewLike$$anonfun$union$1 of class scala/collection/SeqViewLike
  minor version: 0
  major version: 49
  Constant pool:
Asciz	SourceFile;
Asciz	SeqViewLike.scala;
Asciz	<clinit>;
Asciz	()V;
Asciz	Code;
Asciz	serialVersionUID;
Asciz	J;
Asciz	scala/collection/SeqViewLike$$anonfun$union$1;
class	scala/collection/SeqViewLike$$anonfun$union$1
NameAndType	serialVersionUID:J
Field	scala/collection/SeqViewLike$$anonfun$union$1.serialVersionUID:J
Asciz	that$6;
Asciz	Lscala/collection/Seq;;
Asciz	$outer;
Asciz	Lscala/collection/SeqViewLike;;
Asciz	apply;
Asciz	()Lscala/collection/Seq;;
Asciz	LineNumberTable;
NameAndType	$outer:Lscala/collection/SeqViewLike;
Field	scala/collection/SeqViewLike$$anonfun$union$1.$outer:Lscala/collection/SeqViewLike;
Asciz	scala/collection/TraversableViewLike;
class	scala/collection/TraversableViewLike
Asciz	thisSeq;
NameAndType	thisSeq:()Lscala/collection/Seq;
InterfaceMethod	scala/collection/TraversableViewLike.thisSeq:()Lscala/collection/Seq;
NameAndType	that$6:Lscala/collection/Seq;
Field	scala/collection/SeqViewLike$$anonfun$union$1.that$6:Lscala/collection/Seq;
Asciz	scala/collection/Seq$;
class	scala/collection/Seq$
Asciz	MODULE$;
Asciz	Lscala/collection/Seq$;;
NameAndType	MODULE$:Lscala/collection/Seq$;
Field	scala/collection/Seq$.MODULE$:Lscala/collection/Seq$;
Asciz	canBuildFrom;
Asciz	()Lscala/collection/generic/CanBuildFrom;;
NameAndType	canBuildFrom:()Lscala/collection/generic/CanBuildFrom;
Method	scala/collection/Seq$.canBuildFrom:()Lscala/collection/generic/CanBuildFrom;
Asciz	scala/collection/SeqLike;
class	scala/collection/SeqLike
Asciz	union;
Asciz	(Lscala/collection/Seq;Lscala/collection/generic/CanBuildFrom;)Ljava/lang/Object;;
NameAndType	union:(Lscala/collection/Seq;Lscala/collection/generic/CanBuildFrom;)Ljava/lang/Object;
InterfaceMethod	scala/collection/SeqLike.union:(Lscala/collection/Seq;Lscala/collection/generic/CanBuildFrom;)Ljava/lang/Object;
Asciz	scala/collection/Seq;
class	scala/collection/Seq
Asciz	()Lscala/collection/Seq<TB;>;;
Asciz	Signature;
Asciz	()Ljava/lang/Object;;
NameAndType	apply:()Lscala/collection/Seq;
Method	scala/collection/SeqViewLike$$anonfun$union$1.apply:()Lscala/collection/Seq;
Asciz	<init>;
Asciz	(Lscala/collection/SeqViewLike;Lscala/collection/Seq;)V;
Asciz	java/lang/NullPointerException;
class	java/lang/NullPointerException
NameAndType	"<init>":()V
Method	java/lang/NullPointerException."<init>":()V
Asciz	scala/runtime/AbstractFunction0;
class	scala/runtime/AbstractFunction0
Method	scala/runtime/AbstractFunction0."<init>":()V
Asciz	this;
Asciz	Lscala/collection/SeqViewLike$$anonfun$union$1;;
Asciz	LocalVariableTable;
Asciz	(Lscala/collection/SeqViewLike<TA;TColl;TThis;>;)V;
Asciz	Scala;
Asciz	InnerClasses;
Asciz	scala/collection/SeqViewLike;
class	scala/collection/SeqViewLike
Asciz	$anonfun$union$1;
Asciz	java/io/Serializable;
class	java/io/Serializable

{
public static final long serialVersionUID;
  Signature: J

public final scala.collection.Seq that$6;
  Signature: Lscala/collection/Seq;

public final scala.collection.SeqViewLike $outer;
  Signature: Lscala/collection/SeqViewLike;

public static {};
  Signature: ()V
  Code:
   Stack=2, Locals=0, Args_size=0
	lconst_0
	putstatic	Field serialVersionUID:J
	return
  Labels:

public final scala.collection.Seq apply();
  Signature: ()Lscala/collection/Seq;
  Code:
   Stack=3, Locals=1, Args_size=1
	aload_0
	getfield	Field $outer:Lscala/collection/SeqViewLike;
	invokeinterface	InterfaceMethod scala/collection/TraversableViewLike.thisSeq:()Lscala/collection/Seq;
	aload_0
	getfield	Field that$6:Lscala/collection/Seq;
	getstatic	Field scala/collection/Seq$.MODULE$:Lscala/collection/Seq$;
	invokevirtual	Method scala/collection/Seq$.canBuildFrom:()Lscala/collection/generic/CanBuildFrom;
	invokeinterface	InterfaceMethod scala/collection/SeqLike.union:(Lscala/collection/Seq;Lscala/collection/generic/CanBuildFrom;)Ljava/lang/Object;
	checkcast	class scala/collection/Seq
	areturn
  Labels:
  Signature: length = 0x2
   00 2E 

public final java.lang.Object apply();
  Signature: ()Ljava/lang/Object;
  Code:
   Stack=1, Locals=1, Args_size=1
	aload_0
	invokevirtual	Method apply:()Lscala/collection/Seq;
	areturn
  Labels:

public scala.collection.SeqViewLike$$anonfun$union$1(scala.collection.SeqViewLike, scala.collection.Seq);
  Signature: (Lscala/collection/SeqViewLike;Lscala/collection/Seq;)V
  Code:
   Stack=2, Locals=3, Args_size=3
	aload_1
	ifnonnull	l1 // aload_0
	new	class java/lang/NullPointerException
	dup
	invokespecial	Method java/lang/NullPointerException."<init>":()V
	athrow
l1	aload_0
	aload_1
	putfield	Field $outer:Lscala/collection/SeqViewLike;
	aload_0
	aload_2
	putfield	Field that$6:Lscala/collection/Seq;
	aload_0
	invokespecial	Method scala/runtime/AbstractFunction0."<init>":()V
	return
  Labels:
   	l1 = 12 // aload_0
  LocalVariableTable: 
   Start  Length  Slot  Name   Signature
   0      27      0    this       Lscala/collection/SeqViewLike$$anonfun$union$1;
   0      27      1    $outer       Lscala/collection/SeqViewLike;

  Signature: length = 0x2
   00 3F 

}

