Compiled from "Set.scala"
public final class scala.collection.Set$ extends scala.collection.generic.SetFactory implements scala.ScalaObject
  SourceFile: "Set.scala"
  Scala: length = 0x
   
  Signature: length = 0x2
   00 2C 
  minor version: 0
  major version: 49
  Constant pool:
const #1 = Asciz	SourceFile;
const #2 = Asciz	Set.scala;
const #3 = Asciz	Scala;
const #4 = Asciz	MODULE$;
const #5 = Asciz	Lscala/collection/Set$;;
const #6 = Asciz	<clinit>;
const #7 = Asciz	()V;
const #8 = Asciz	Code;
const #9 = Asciz	scala/collection/Set$;
const #10 = class	#9;	//  scala/collection/Set$
const #11 = Asciz	<init>;
const #12 = NameAndType	#11:#7;//  "<init>":()V
const #13 = Method	#10.#12;	//  scala/collection/Set$."<init>":()V
const #14 = Asciz	LineNumberTable;
const #15 = Asciz	scala/collection/generic/SetFactory;
const #16 = class	#15;	//  scala/collection/generic/SetFactory
const #17 = Method	#16.#12;	//  scala/collection/generic/SetFactory."<init>":()V
const #18 = NameAndType	#4:#5;//  MODULE$:Lscala/collection/Set$;
const #19 = Field	#10.#18;	//  scala/collection/Set$.MODULE$:Lscala/collection/Set$;
const #20 = Asciz	empty;
const #21 = Asciz	()Lscala/collection/Traversable;;
const #22 = Asciz	()Lscala/collection/Set;;
const #23 = NameAndType	#20:#22;//  empty:()Lscala/collection/Set;
const #24 = Method	#10.#23;	//  scala/collection/Set$.empty:()Lscala/collection/Set;
const #25 = Asciz	canBuildFrom;
const #26 = Asciz	()Lscala/collection/generic/CanBuildFrom;;
const #27 = Asciz	setCanBuildFrom;
const #28 = Asciz	()Ljava/lang/Object;;
const #29 = NameAndType	#27:#28;//  setCanBuildFrom:()Ljava/lang/Object;
const #30 = Method	#10.#29;	//  scala/collection/Set$.setCanBuildFrom:()Ljava/lang/Object;
const #31 = Asciz	scala/collection/generic/CanBuildFrom;
const #32 = class	#31;	//  scala/collection/generic/CanBuildFrom
const #33 = Asciz	<A:Ljava/lang/Object;>()Lscala/collection/generic/CanBuildFrom<Lscala/collection/Set<*>;TA;Lscala/collection/Set<TA;>;>;;
const #34 = Asciz	Signature;
const #35 = Asciz	scala/collection/immutable/Set$;
const #36 = class	#35;	//  scala/collection/immutable/Set$
const #37 = Asciz	Lscala/collection/immutable/Set$;;
const #38 = NameAndType	#4:#37;//  MODULE$:Lscala/collection/immutable/Set$;
const #39 = Field	#36.#38;	//  scala/collection/immutable/Set$.MODULE$:Lscala/collection/immutable/Set$;
const #40 = Asciz	()Lscala/collection/immutable/Set;;
const #41 = NameAndType	#20:#40;//  empty:()Lscala/collection/immutable/Set;
const #42 = Method	#36.#41;	//  scala/collection/immutable/Set$.empty:()Lscala/collection/immutable/Set;
const #43 = Asciz	<A:Ljava/lang/Object;>()Lscala/collection/Set<TA;>;;
const #44 = Asciz	Lscala/collection/generic/SetFactory<Lscala/collection/Set;>;Lscala/ScalaObject;;
const #45 = Asciz	scala/ScalaObject;
const #46 = class	#45;	//  scala/ScalaObject

{
public static final scala.collection.Set$ MODULE$;

public static {};
  Code:
   Stack=1, Locals=0, Args_size=0
   0:	new	#10; //class scala/collection/Set$
   3:	invokespecial	#13; //Method "<init>":()V
   6:	return

public scala.collection.Traversable empty();
  Code:
   Stack=1, Locals=1, Args_size=1
   0:	aload_0
   1:	invokevirtual	#24; //Method empty:()Lscala/collection/Set;
   4:	areturn
  LineNumberTable: 
   line 37: 0


public scala.collection.generic.CanBuildFrom canBuildFrom();
  Code:
   Stack=1, Locals=1, Args_size=1
   0:	aload_0
   1:	invokevirtual	#30; //Method setCanBuildFrom:()Ljava/lang/Object;
   4:	checkcast	#32; //class scala/collection/generic/CanBuildFrom
   7:	areturn
  LineNumberTable: 
   line 39: 0

  Signature: length = 0x2
   00 21 

public scala.collection.Set empty();
  Code:
   Stack=1, Locals=1, Args_size=1
   0:	getstatic	#39; //Field scala/collection/immutable/Set$.MODULE$:Lscala/collection/immutable/Set$;
   3:	invokevirtual	#42; //Method scala/collection/immutable/Set$.empty:()Lscala/collection/immutable/Set;
   6:	areturn
  LineNumberTable: 
   line 38: 0

  Signature: length = 0x2
   00 2B 

}

