Compiled from "SetLike.scala"
public final class scala.collection.SetLike$$anonfun$subsetOf$1 extends java.lang.Object implements scala.Function1,scala.ScalaObject,java.io.Serializable
  SourceFile: "SetLike.scala"
  Scala: length = 0x
   
  InnerClass: 
   public final $anonfun$subsetOf$1=class scala/collection/SetLike$$anonfun$subsetOf$1 of class scala/collection/SetLike
  minor version: 0
  major version: 49
  Constant pool:
Asciz	SourceFile;
Asciz	SetLike.scala;
Asciz	<clinit>;
Asciz	()V;
Asciz	Code;
Asciz	serialVersionUID;
Asciz	J;
Asciz	scala/collection/SetLike$$anonfun$subsetOf$1;
class	scala/collection/SetLike$$anonfun$subsetOf$1
NameAndType	serialVersionUID:J
Field	scala/collection/SetLike$$anonfun$subsetOf$1.serialVersionUID:J
Asciz	that$2;
Asciz	Lscala/collection/Set;;
Asciz	<init>;
Asciz	(Lscala/collection/SetLike;Lscala/collection/Set;)V;
Asciz	LineNumberTable;
NameAndType	that$2:Lscala/collection/Set;
Field	scala/collection/SetLike$$anonfun$subsetOf$1.that$2:Lscala/collection/Set;
Asciz	java/lang/Object;
class	java/lang/Object
NameAndType	"<init>":()V
Method	java/lang/Object."<init>":()V
Asciz	scala/Function1$class;
class	scala/Function1$class
Asciz	$init$;
Asciz	(Lscala/Function1;)V;
NameAndType	$init$:(Lscala/Function1;)V
Method	scala/Function1$class.$init$:(Lscala/Function1;)V
Asciz	this;
Asciz	Lscala/collection/SetLike$$anonfun$subsetOf$1;;
Asciz	$outer;
Asciz	Lscala/collection/SetLike;;
Asciz	LocalVariableTable;
Asciz	(Lscala/collection/SetLike<TA;TThis;>;)V;
Asciz	Signature;
Asciz	apply;
Asciz	(Ljava/lang/Object;)Ljava/lang/Object;;
Asciz	(Ljava/lang/Object;)Z;
NameAndType	apply:(Ljava/lang/Object;)Z
Method	scala/collection/SetLike$$anonfun$subsetOf$1.apply:(Ljava/lang/Object;)Z
Asciz	scala/runtime/BoxesRunTime;
class	scala/runtime/BoxesRunTime
Asciz	boxToBoolean;
Asciz	(Z)Ljava/lang/Boolean;;
NameAndType	boxToBoolean:(Z)Ljava/lang/Boolean;
Method	scala/runtime/BoxesRunTime.boxToBoolean:(Z)Ljava/lang/Boolean;
Asciz	v1;
Asciz	Ljava/lang/Object;;
Asciz	scala/collection/SetLike;
class	scala/collection/SetLike
Asciz	contains;
NameAndType	contains:(Ljava/lang/Object;)Z
InterfaceMethod	scala/collection/SetLike.contains:(Ljava/lang/Object;)Z
Asciz	(TA;)Z;
Asciz	andThen;
Asciz	(Lscala/Function1;)Lscala/Function1;;
Asciz	(Lscala/Function1;Lscala/Function1;)Lscala/Function1;;
NameAndType	andThen:(Lscala/Function1;Lscala/Function1;)Lscala/Function1;
Method	scala/Function1$class.andThen:(Lscala/Function1;Lscala/Function1;)Lscala/Function1;
Asciz	g;
Asciz	Lscala/Function1;;
Asciz	compose;
NameAndType	compose:(Lscala/Function1;Lscala/Function1;)Lscala/Function1;
Method	scala/Function1$class.compose:(Lscala/Function1;Lscala/Function1;)Lscala/Function1;
Asciz	toString;
Asciz	()Ljava/lang/String;;
Asciz	(Lscala/Function1;)Ljava/lang/String;;
NameAndType	toString:(Lscala/Function1;)Ljava/lang/String;
Method	scala/Function1$class.toString:(Lscala/Function1;)Ljava/lang/String;
Asciz	Scala;
Asciz	InnerClasses;
Asciz	$anonfun$subsetOf$1;
Asciz	scala/Function1;
class	scala/Function1
Asciz	scala/ScalaObject;
class	scala/ScalaObject
Asciz	java/io/Serializable;
class	java/io/Serializable

{
public static final long serialVersionUID;
  Signature: J

private final scala.collection.Set that$2;
  Signature: Lscala/collection/Set;

public static {};
  Signature: ()V
  Code:
   Stack=2, Locals=0, Args_size=0
	lconst_0
	putstatic	Field serialVersionUID:J
	return
  Labels:

public scala.collection.SetLike$$anonfun$subsetOf$1(scala.collection.SetLike, scala.collection.Set);
  Signature: (Lscala/collection/SetLike;Lscala/collection/Set;)V
  Code:
   Stack=2, Locals=3, Args_size=3
	aload_0
	aload_2
	putfield	Field that$2:Lscala/collection/Set;
	aload_0
	invokespecial	Method java/lang/Object."<init>":()V
	aload_0
	invokestatic	Method scala/Function1$class.$init$:(Lscala/Function1;)V
	return
  Labels:
  LocalVariableTable: 
   Start  Length  Slot  Name   Signature
   0      14      0    this       Lscala/collection/SetLike$$anonfun$subsetOf$1;
   0      14      1    $outer       Lscala/collection/SetLike;

  Signature: length = 0x2
   00 22 

public final java.lang.Object apply(java.lang.Object);
  Signature: (Ljava/lang/Object;)Ljava/lang/Object;
  Code:
   Stack=2, Locals=3, Args_size=2
	aload_0
	aload_1
	invokevirtual	Method apply:(Ljava/lang/Object;)Z
	istore_2
	iload_2
	invokestatic	Method scala/runtime/BoxesRunTime.boxToBoolean:(Z)Ljava/lang/Boolean;
	areturn
  Labels:
  LocalVariableTable: 
   Start  Length  Slot  Name   Signature
   0      11      0    this       Lscala/collection/SetLike$$anonfun$subsetOf$1;
   0      11      1    v1       Ljava/lang/Object;


public final boolean apply(java.lang.Object);
  Signature: (Ljava/lang/Object;)Z
  Code:
   Stack=2, Locals=2, Args_size=2
	aload_0
	getfield	Field that$2:Lscala/collection/Set;
	aload_1
	invokeinterface	InterfaceMethod scala/collection/SetLike.contains:(Ljava/lang/Object;)Z
	ireturn
  Labels:
  Signature: length = 0x2
   00 36 

public scala.Function1 andThen(scala.Function1);
  Signature: (Lscala/Function1;)Lscala/Function1;
  Code:
   Stack=2, Locals=2, Args_size=2
	aload_0
	aload_1
	invokestatic	Method scala/Function1$class.andThen:(Lscala/Function1;Lscala/Function1;)Lscala/Function1;
	areturn
  Labels:
  LocalVariableTable: 
   Start  Length  Slot  Name   Signature
   0      6      0    this       Lscala/collection/SetLike$$anonfun$subsetOf$1;
   0      6      1    g       Lscala/Function1;


public scala.Function1 compose(scala.Function1);
  Signature: (Lscala/Function1;)Lscala/Function1;
  Code:
   Stack=2, Locals=2, Args_size=2
	aload_0
	aload_1
	invokestatic	Method scala/Function1$class.compose:(Lscala/Function1;Lscala/Function1;)Lscala/Function1;
	areturn
  Labels:
  LocalVariableTable: 
   Start  Length  Slot  Name   Signature
   0      6      0    this       Lscala/collection/SetLike$$anonfun$subsetOf$1;
   0      6      1    g       Lscala/Function1;


public java.lang.String toString();
  Signature: ()Ljava/lang/String;
  Code:
   Stack=1, Locals=1, Args_size=1
	aload_0
	invokestatic	Method scala/Function1$class.toString:(Lscala/Function1;)Ljava/lang/String;
	areturn
  Labels:

}

