Compiled from "SetLike.scala"
public abstract class scala.collection.SetLike$class extends java.lang.Object
  SourceFile: "SetLike.scala"
  Scala: length = 0x
   
  InnerClass: 
   public final #168= #103 of #13; //$anonfun$subsetOf$1=class scala/collection/SetLike$$anonfun$subsetOf$1 of class scala/collection/SetLike
   public final #169= #61 of #13; //$anonfun$hashCode$1=class scala/collection/SetLike$$anonfun$hashCode$1 of class scala/collection/SetLike
   public final #170= #141 of #13; //$anonfun$intersect$1=class scala/collection/SetLike$$anonfun$intersect$1 of class scala/collection/SetLike
  minor version: 0
  major version: 49
  Constant pool:
const #1 = Asciz	SourceFile;
const #2 = Asciz	SetLike.scala;
const #3 = Asciz	$init$;
const #4 = Asciz	(Lscala/collection/SetLike;)V;
const #5 = Asciz	Code;
const #6 = Asciz	LineNumberTable;
const #7 = Asciz	$this;
const #8 = Asciz	Lscala/collection/SetLike;;
const #9 = Asciz	LocalVariableTable;
const #10 = Asciz	liftedTree1$1;
const #11 = Asciz	(Lscala/collection/SetLike;Lscala/collection/Set;)Z;
const #12 = Asciz	scala/collection/SetLike;
const #13 = class	#12;	//  scala/collection/SetLike
const #14 = Asciz	subsetOf;
const #15 = Asciz	(Lscala/collection/Set;)Z;
const #16 = NameAndType	#14:#15;//  subsetOf:(Lscala/collection/Set;)Z
const #17 = InterfaceMethod	#13.#16;	//  scala/collection/SetLike.subsetOf:(Lscala/collection/Set;)Z
const #18 = Asciz	java/lang/ClassCastException;
const #19 = class	#18;	//  java/lang/ClassCastException
const #20 = Asciz	exceptionResult1;
const #21 = Asciz	Z;
const #22 = Asciz	equals;
const #23 = Asciz	(Lscala/collection/SetLike;Ljava/lang/Object;)Z;
const #24 = Asciz	scala/collection/Set;
const #25 = class	#24;	//  scala/collection/Set
const #26 = Asciz	scala/collection/IterableLike;
const #27 = class	#26;	//  scala/collection/IterableLike
const #28 = Asciz	canEqual;
const #29 = Asciz	(Ljava/lang/Object;)Z;
const #30 = NameAndType	#28:#29;//  canEqual:(Ljava/lang/Object;)Z
const #31 = InterfaceMethod	#27.#30;	//  scala/collection/IterableLike.canEqual:(Ljava/lang/Object;)Z
const #32 = Asciz	scala/collection/TraversableLike;
const #33 = class	#32;	//  scala/collection/TraversableLike
const #34 = Asciz	size;
const #35 = Asciz	()I;
const #36 = NameAndType	#34:#35;//  size:()I
const #37 = InterfaceMethod	#33.#36;	//  scala/collection/TraversableLike.size:()I
const #38 = Asciz	scala/collection/SetLike$class;
const #39 = class	#38;	//  scala/collection/SetLike$class
const #40 = NameAndType	#10:#11;//  liftedTree1$1:(Lscala/collection/SetLike;Lscala/collection/Set;)Z
const #41 = Method	#39.#40;	//  scala/collection/SetLike$class.liftedTree1$1:(Lscala/collection/SetLike;Lscala/collection/Set;)Z
const #42 = Asciz	scala/MatchError;
const #43 = class	#42;	//  scala/MatchError
const #44 = Asciz	java/lang/Object;
const #45 = class	#44;	//  java/lang/Object
const #46 = Asciz	toString;
const #47 = Asciz	()Ljava/lang/String;;
const #48 = NameAndType	#46:#47;//  toString:()Ljava/lang/String;
const #49 = Method	#45.#48;	//  java/lang/Object.toString:()Ljava/lang/String;
const #50 = Asciz	<init>;
const #51 = Asciz	(Ljava/lang/String;)V;
const #52 = NameAndType	#50:#51;//  "<init>":(Ljava/lang/String;)V
const #53 = Method	#43.#52;	//  scala/MatchError."<init>":(Ljava/lang/String;)V
const #54 = Asciz	that;
const #55 = Asciz	Ljava/lang/Object;;
const #56 = Asciz	temp2;
const #57 = Asciz	Lscala/collection/Set;;
const #58 = Asciz	hashCode;
const #59 = Asciz	(Lscala/collection/SetLike;)I;
const #60 = Asciz	scala/collection/SetLike$$anonfun$hashCode$1;
const #61 = class	#60;	//  scala/collection/SetLike$$anonfun$hashCode$1
const #62 = NameAndType	#50:#4;//  "<init>":(Lscala/collection/SetLike;)V
const #63 = Method	#61.#62;	//  scala/collection/SetLike$$anonfun$hashCode$1."<init>":(Lscala/collection/SetLike;)V
const #64 = Asciz	scala/collection/Set$;
const #65 = class	#64;	//  scala/collection/Set$
const #66 = Asciz	MODULE$;
const #67 = Asciz	Lscala/collection/Set$;;
const #68 = NameAndType	#66:#67;//  MODULE$:Lscala/collection/Set$;
const #69 = Field	#65.#68;	//  scala/collection/Set$.MODULE$:Lscala/collection/Set$;
const #70 = Asciz	canBuildFrom;
const #71 = Asciz	()Lscala/collection/generic/CanBuildFrom;;
const #72 = NameAndType	#70:#71;//  canBuildFrom:()Lscala/collection/generic/CanBuildFrom;
const #73 = Method	#65.#72;	//  scala/collection/Set$.canBuildFrom:()Lscala/collection/generic/CanBuildFrom;
const #74 = Asciz	map;
const #75 = Asciz	(Lscala/Function1;Lscala/collection/generic/CanBuildFrom;)Ljava/lang/Object;;
const #76 = NameAndType	#74:#75;//  map:(Lscala/Function1;Lscala/collection/generic/CanBuildFrom;)Ljava/lang/Object;
const #77 = InterfaceMethod	#33.#76;	//  scala/collection/TraversableLike.map:(Lscala/Function1;Lscala/collection/generic/CanBuildFrom;)Ljava/lang/Object;
const #78 = Asciz	scala/math/Numeric$IntIsIntegral$;
const #79 = class	#78;	//  scala/math/Numeric$IntIsIntegral$
const #80 = Asciz	Lscala/math/Numeric$IntIsIntegral$;;
const #81 = NameAndType	#66:#80;//  MODULE$:Lscala/math/Numeric$IntIsIntegral$;
const #82 = Field	#79.#81;	//  scala/math/Numeric$IntIsIntegral$.MODULE$:Lscala/math/Numeric$IntIsIntegral$;
const #83 = Asciz	sum;
const #84 = Asciz	(Lscala/math/Numeric;)Ljava/lang/Object;;
const #85 = NameAndType	#83:#84;//  sum:(Lscala/math/Numeric;)Ljava/lang/Object;
const #86 = InterfaceMethod	#33.#85;	//  scala/collection/TraversableLike.sum:(Lscala/math/Numeric;)Ljava/lang/Object;
const #87 = Asciz	scala/runtime/BoxesRunTime;
const #88 = class	#87;	//  scala/runtime/BoxesRunTime
const #89 = Asciz	unboxToInt;
const #90 = Asciz	(Ljava/lang/Object;)I;
const #91 = NameAndType	#89:#90;//  unboxToInt:(Ljava/lang/Object;)I
const #92 = Method	#88.#91;	//  scala/runtime/BoxesRunTime.unboxToInt:(Ljava/lang/Object;)I
const #93 = Asciz	(Lscala/collection/SetLike;)Ljava/lang/String;;
const #94 = Asciz	scala/collection/TraversableLike$class;
const #95 = class	#94;	//  scala/collection/TraversableLike$class
const #96 = Asciz	(Lscala/collection/TraversableLike;)Ljava/lang/String;;
const #97 = NameAndType	#46:#96;//  toString:(Lscala/collection/TraversableLike;)Ljava/lang/String;
const #98 = Method	#95.#97;	//  scala/collection/TraversableLike$class.toString:(Lscala/collection/TraversableLike;)Ljava/lang/String;
const #99 = Asciz	stringPrefix;
const #100 = Asciz	Set;
const #101 = String	#100;	//  Set
const #102 = Asciz	scala/collection/SetLike$$anonfun$subsetOf$1;
const #103 = class	#102;	//  scala/collection/SetLike$$anonfun$subsetOf$1
const #104 = Asciz	(Lscala/collection/SetLike;Lscala/collection/Set;)V;
const #105 = NameAndType	#50:#104;//  "<init>":(Lscala/collection/SetLike;Lscala/collection/Set;)V
const #106 = Method	#103.#105;	//  scala/collection/SetLike$$anonfun$subsetOf$1."<init>":(Lscala/collection/SetLike;Lscala/collection/Set;)V
const #107 = Asciz	forall;
const #108 = Asciz	(Lscala/Function1;)Z;
const #109 = NameAndType	#107:#108;//  forall:(Lscala/Function1;)Z
const #110 = InterfaceMethod	#27.#109;	//  scala/collection/IterableLike.forall:(Lscala/Function1;)Z
const #111 = Asciz	that$1;
const #112 = Asciz	$amp$tilde;
const #113 = Asciz	(Lscala/collection/SetLike;Lscala/collection/Set;)Lscala/collection/SetLike;;
const #114 = Asciz	diff;
const #115 = Asciz	(Lscala/collection/Set;)Lscala/collection/SetLike;;
const #116 = NameAndType	#114:#115;//  diff:(Lscala/collection/Set;)Lscala/collection/SetLike;
const #117 = InterfaceMethod	#13.#116;	//  scala/collection/SetLike.diff:(Lscala/collection/Set;)Lscala/collection/SetLike;
const #118 = Asciz	scala/collection/generic/Subtractable;
const #119 = class	#118;	//  scala/collection/generic/Subtractable
const #120 = Asciz	$minus$minus;
const #121 = Asciz	(Lscala/collection/Traversable;)Lscala/collection/generic/Subtractable;;
const #122 = NameAndType	#120:#121;//  $minus$minus:(Lscala/collection/Traversable;)Lscala/collection/generic/Subtractable;
const #123 = InterfaceMethod	#119.#122;	//  scala/collection/generic/Subtractable.$minus$minus:(Lscala/collection/Traversable;)Lscala/collection/generic/Subtractable;
const #124 = Asciz	$bar;
const #125 = Asciz	union;
const #126 = NameAndType	#125:#115;//  union:(Lscala/collection/Set;)Lscala/collection/SetLike;
const #127 = InterfaceMethod	#13.#126;	//  scala/collection/SetLike.union:(Lscala/collection/Set;)Lscala/collection/SetLike;
const #128 = Asciz	scala/collection/generic/Addable;
const #129 = class	#128;	//  scala/collection/generic/Addable
const #130 = Asciz	$plus$plus;
const #131 = Asciz	(Lscala/collection/Traversable;)Lscala/collection/generic/Addable;;
const #132 = NameAndType	#130:#131;//  $plus$plus:(Lscala/collection/Traversable;)Lscala/collection/generic/Addable;
const #133 = InterfaceMethod	#129.#132;	//  scala/collection/generic/Addable.$plus$plus:(Lscala/collection/Traversable;)Lscala/collection/generic/Addable;
const #134 = Asciz	$times$times;
const #135 = Asciz	intersect;
const #136 = NameAndType	#135:#115;//  intersect:(Lscala/collection/Set;)Lscala/collection/SetLike;
const #137 = InterfaceMethod	#13.#136;	//  scala/collection/SetLike.intersect:(Lscala/collection/Set;)Lscala/collection/SetLike;
const #138 = Asciz	Deprecated;
const #139 = Asciz	$amp;
const #140 = Asciz	scala/collection/SetLike$$anonfun$intersect$1;
const #141 = class	#140;	//  scala/collection/SetLike$$anonfun$intersect$1
const #142 = Method	#141.#105;	//  scala/collection/SetLike$$anonfun$intersect$1."<init>":(Lscala/collection/SetLike;Lscala/collection/Set;)V
const #143 = Asciz	filter;
const #144 = Asciz	(Lscala/Function1;)Ljava/lang/Object;;
const #145 = NameAndType	#143:#144;//  filter:(Lscala/Function1;)Ljava/lang/Object;
const #146 = InterfaceMethod	#33.#145;	//  scala/collection/TraversableLike.filter:(Lscala/Function1;)Ljava/lang/Object;
const #147 = Asciz	that$2;
const #148 = Asciz	apply;
const #149 = Asciz	contains;
const #150 = NameAndType	#149:#29;//  contains:(Ljava/lang/Object;)Z
const #151 = InterfaceMethod	#13.#150;	//  scala/collection/SetLike.contains:(Ljava/lang/Object;)Z
const #152 = Asciz	elem;
const #153 = Asciz	isEmpty;
const #154 = Asciz	(Lscala/collection/SetLike;)Z;
const #155 = Asciz	newBuilder;
const #156 = Asciz	(Lscala/collection/SetLike;)Lscala/collection/mutable/Builder;;
const #157 = Asciz	scala/collection/mutable/AddingBuilder;
const #158 = class	#157;	//  scala/collection/mutable/AddingBuilder
const #159 = Asciz	empty;
const #160 = Asciz	()Lscala/collection/SetLike;;
const #161 = NameAndType	#159:#160;//  empty:()Lscala/collection/SetLike;
const #162 = InterfaceMethod	#13.#161;	//  scala/collection/SetLike.empty:()Lscala/collection/SetLike;
const #163 = Asciz	(Lscala/collection/generic/Addable;)V;
const #164 = NameAndType	#50:#163;//  "<init>":(Lscala/collection/generic/Addable;)V
const #165 = Method	#158.#164;	//  scala/collection/mutable/AddingBuilder."<init>":(Lscala/collection/generic/Addable;)V
const #166 = Asciz	Scala;
const #167 = Asciz	InnerClasses;
const #168 = Asciz	$anonfun$subsetOf$1;
const #169 = Asciz	$anonfun$hashCode$1;
const #170 = Asciz	$anonfun$intersect$1;

{
public static void $init$(scala.collection.SetLike);
  Code:
   Stack=0, Locals=1, Args_size=1
   0:	return
  LineNumberTable: 
   line 51: 0

  LocalVariableTable: 
   Start  Length  Slot  Name   Signature
   0      1      0    $this       Lscala/collection/SetLike;


public static boolean equals(scala.collection.SetLike, java.lang.Object);
  Code:
   Stack=3, Locals=3, Args_size=2
   0:	aload_1
   1:	instanceof	#25; //class scala/collection/Set
   4:	ifeq	74
   7:	aload_1
   8:	checkcast	#25; //class scala/collection/Set
   11:	astore_2
   12:	iconst_1
   13:	ifeq	62
   16:	aload_0
   17:	aload_2
   18:	if_acmpeq	54
   21:	aload_2
   22:	aload_0
   23:	invokeinterface	#31,  2; //InterfaceMethod scala/collection/IterableLike.canEqual:(Ljava/lang/Object;)Z
   28:	ifeq	58
   31:	aload_0
   32:	invokeinterface	#37,  1; //InterfaceMethod scala/collection/TraversableLike.size:()I
   37:	aload_2
   38:	invokeinterface	#37,  1; //InterfaceMethod scala/collection/TraversableLike.size:()I
   43:	if_icmpne	58
   46:	aload_0
   47:	aload_2
   48:	invokestatic	#41; //Method liftedTree1$1:(Lscala/collection/SetLike;Lscala/collection/Set;)Z
   51:	ifeq	58
   54:	iconst_1
   55:	goto	79
   58:	iconst_0
   59:	goto	79
   62:	new	#43; //class scala/MatchError
   65:	dup
   66:	aload_1
   67:	invokevirtual	#49; //Method java/lang/Object.toString:()Ljava/lang/String;
   70:	invokespecial	#53; //Method scala/MatchError."<init>":(Ljava/lang/String;)V
   73:	athrow
   74:	iconst_1
   75:	ifeq	80
   78:	iconst_0
   79:	ireturn
   80:	new	#43; //class scala/MatchError
   83:	dup
   84:	aload_1
   85:	invokevirtual	#49; //Method java/lang/Object.toString:()Ljava/lang/String;
   88:	invokespecial	#53; //Method scala/MatchError."<init>":(Ljava/lang/String;)V
   91:	athrow
  LineNumberTable: 
   line 192: 0
   line 21: 12
   line 194: 16
   line 195: 21
   line 196: 31
   line 197: 46
   line 194: 54
   line 192: 62
   line 21: 74
   line 200: 78
   line 192: 79

  LocalVariableTable: 
   Start  Length  Slot  Name   Signature
   0      92      0    $this       Lscala/collection/SetLike;
   0      92      1    that       Ljava/lang/Object;
   12      62      2    temp2       Lscala/collection/Set;


public static int hashCode(scala.collection.SetLike);
  Code:
   Stack=4, Locals=1, Args_size=1
   0:	aload_0
   1:	new	#61; //class scala/collection/SetLike$$anonfun$hashCode$1
   4:	dup
   5:	aload_0
   6:	invokespecial	#63; //Method scala/collection/SetLike$$anonfun$hashCode$1."<init>":(Lscala/collection/SetLike;)V
   9:	getstatic	#69; //Field scala/collection/Set$.MODULE$:Lscala/collection/Set$;
   12:	invokevirtual	#73; //Method scala/collection/Set$.canBuildFrom:()Lscala/collection/generic/CanBuildFrom;
   15:	invokeinterface	#77,  3; //InterfaceMethod scala/collection/TraversableLike.map:(Lscala/Function1;Lscala/collection/generic/CanBuildFrom;)Ljava/lang/Object;
   20:	checkcast	#33; //class scala/collection/TraversableLike
   23:	getstatic	#82; //Field scala/math/Numeric$IntIsIntegral$.MODULE$:Lscala/math/Numeric$IntIsIntegral$;
   26:	invokeinterface	#86,  2; //InterfaceMethod scala/collection/TraversableLike.sum:(Lscala/math/Numeric;)Ljava/lang/Object;
   31:	invokestatic	#92; //Method scala/runtime/BoxesRunTime.unboxToInt:(Ljava/lang/Object;)I
   34:	ireturn
  LineNumberTable: 
   line 180: 0

  LocalVariableTable: 
   Start  Length  Slot  Name   Signature
   0      35      0    $this       Lscala/collection/SetLike;


public static java.lang.String toString(scala.collection.SetLike);
  Code:
   Stack=1, Locals=1, Args_size=1
   0:	aload_0
   1:	invokestatic	#98; //Method scala/collection/TraversableLike$class.toString:(Lscala/collection/TraversableLike;)Ljava/lang/String;
   4:	areturn
  LineNumberTable: 
   line 179: 0

  LocalVariableTable: 
   Start  Length  Slot  Name   Signature
   0      5      0    $this       Lscala/collection/SetLike;


public static java.lang.String stringPrefix(scala.collection.SetLike);
  Code:
   Stack=1, Locals=1, Args_size=1
   0:	ldc	#101; //String Set
   2:	areturn
  LineNumberTable: 
   line 177: 0

  LocalVariableTable: 
   Start  Length  Slot  Name   Signature
   0      3      0    $this       Lscala/collection/SetLike;


public static boolean subsetOf(scala.collection.SetLike, scala.collection.Set);
  Code:
   Stack=5, Locals=2, Args_size=2
   0:	aload_0
   1:	new	#103; //class scala/collection/SetLike$$anonfun$subsetOf$1
   4:	dup
   5:	aload_0
   6:	aload_1
   7:	invokespecial	#106; //Method scala/collection/SetLike$$anonfun$subsetOf$1."<init>":(Lscala/collection/SetLike;Lscala/collection/Set;)V
   10:	invokeinterface	#110,  2; //InterfaceMethod scala/collection/IterableLike.forall:(Lscala/Function1;)Z
   15:	ireturn
  LineNumberTable: 
   line 171: 0

  LocalVariableTable: 
   Start  Length  Slot  Name   Signature
   0      16      0    $this       Lscala/collection/SetLike;
   0      16      1    that$1       Lscala/collection/Set;


public static scala.collection.SetLike $amp$tilde(scala.collection.SetLike, scala.collection.Set);
  Code:
   Stack=2, Locals=2, Args_size=2
   0:	aload_0
   1:	aload_1
   2:	invokeinterface	#117,  2; //InterfaceMethod scala/collection/SetLike.diff:(Lscala/collection/Set;)Lscala/collection/SetLike;
   7:	areturn
  LineNumberTable: 
   line 163: 0

  LocalVariableTable: 
   Start  Length  Slot  Name   Signature
   0      8      0    $this       Lscala/collection/SetLike;
   0      8      1    that       Lscala/collection/Set;


public static scala.collection.SetLike diff(scala.collection.SetLike, scala.collection.Set);
  Code:
   Stack=2, Locals=2, Args_size=2
   0:	aload_0
   1:	aload_1
   2:	invokeinterface	#123,  2; //InterfaceMethod scala/collection/generic/Subtractable.$minus$minus:(Lscala/collection/Traversable;)Lscala/collection/generic/Subtractable;
   7:	checkcast	#13; //class scala/collection/SetLike
   10:	areturn
  LineNumberTable: 
   line 154: 0

  LocalVariableTable: 
   Start  Length  Slot  Name   Signature
   0      11      0    $this       Lscala/collection/SetLike;
   0      11      1    that       Lscala/collection/Set;


public static scala.collection.SetLike $bar(scala.collection.SetLike, scala.collection.Set);
  Code:
   Stack=2, Locals=2, Args_size=2
   0:	aload_0
   1:	aload_1
   2:	invokeinterface	#127,  2; //InterfaceMethod scala/collection/SetLike.union:(Lscala/collection/Set;)Lscala/collection/SetLike;
   7:	areturn
  LineNumberTable: 
   line 146: 0

  LocalVariableTable: 
   Start  Length  Slot  Name   Signature
   0      8      0    $this       Lscala/collection/SetLike;
   0      8      1    that       Lscala/collection/Set;


public static scala.collection.SetLike union(scala.collection.SetLike, scala.collection.Set);
  Code:
   Stack=2, Locals=2, Args_size=2
   0:	aload_0
   1:	aload_1
   2:	invokeinterface	#133,  2; //InterfaceMethod scala/collection/generic/Addable.$plus$plus:(Lscala/collection/Traversable;)Lscala/collection/generic/Addable;
   7:	checkcast	#13; //class scala/collection/SetLike
   10:	areturn
  LineNumberTable: 
   line 137: 0

  LocalVariableTable: 
   Start  Length  Slot  Name   Signature
   0      11      0    $this       Lscala/collection/SetLike;
   0      11      1    that       Lscala/collection/Set;


public static scala.collection.SetLike $times$times(scala.collection.SetLike, scala.collection.Set);
  Code:
   Stack=2, Locals=2, Args_size=2
   0:	aload_0
   1:	aload_1
   2:	invokeinterface	#137,  2; //InterfaceMethod scala/collection/SetLike.intersect:(Lscala/collection/Set;)Lscala/collection/SetLike;
   7:	areturn
  LineNumberTable: 
   line 129: 0

  LocalVariableTable: 
   Start  Length  Slot  Name   Signature
   0      8      0    $this       Lscala/collection/SetLike;
   0      8      1    that       Lscala/collection/Set;

  Deprecated: true

public static scala.collection.SetLike $amp(scala.collection.SetLike, scala.collection.Set);
  Code:
   Stack=2, Locals=2, Args_size=2
   0:	aload_0
   1:	aload_1
   2:	invokeinterface	#137,  2; //InterfaceMethod scala/collection/SetLike.intersect:(Lscala/collection/Set;)Lscala/collection/SetLike;
   7:	areturn
  LineNumberTable: 
   line 121: 0

  LocalVariableTable: 
   Start  Length  Slot  Name   Signature
   0      8      0    $this       Lscala/collection/SetLike;
   0      8      1    that       Lscala/collection/Set;


public static scala.collection.SetLike intersect(scala.collection.SetLike, scala.collection.Set);
  Code:
   Stack=5, Locals=2, Args_size=2
   0:	aload_0
   1:	new	#141; //class scala/collection/SetLike$$anonfun$intersect$1
   4:	dup
   5:	aload_0
   6:	aload_1
   7:	invokespecial	#142; //Method scala/collection/SetLike$$anonfun$intersect$1."<init>":(Lscala/collection/SetLike;Lscala/collection/Set;)V
   10:	invokeinterface	#146,  2; //InterfaceMethod scala/collection/TraversableLike.filter:(Lscala/Function1;)Ljava/lang/Object;
   15:	checkcast	#13; //class scala/collection/SetLike
   18:	areturn
  LineNumberTable: 
   line 112: 0

  LocalVariableTable: 
   Start  Length  Slot  Name   Signature
   0      19      0    $this       Lscala/collection/SetLike;
   0      19      1    that$2       Lscala/collection/Set;


public static boolean apply(scala.collection.SetLike, java.lang.Object);
  Code:
   Stack=2, Locals=2, Args_size=2
   0:	aload_0
   1:	aload_1
   2:	invokeinterface	#151,  2; //InterfaceMethod scala/collection/SetLike.contains:(Ljava/lang/Object;)Z
   7:	ireturn
  LineNumberTable: 
   line 104: 0

  LocalVariableTable: 
   Start  Length  Slot  Name   Signature
   0      8      0    $this       Lscala/collection/SetLike;
   0      8      1    elem       Ljava/lang/Object;


public static boolean isEmpty(scala.collection.SetLike);
  Code:
   Stack=2, Locals=1, Args_size=1
   0:	aload_0
   1:	invokeinterface	#37,  1; //InterfaceMethod scala/collection/TraversableLike.size:()I
   6:	iconst_0
   7:	if_icmpne	14
   10:	iconst_1
   11:	goto	15
   14:	iconst_0
   15:	ireturn
  LineNumberTable: 
   line 96: 0

  LocalVariableTable: 
   Start  Length  Slot  Name   Signature
   0      16      0    $this       Lscala/collection/SetLike;


public static scala.collection.mutable.Builder newBuilder(scala.collection.SetLike);
  Code:
   Stack=3, Locals=1, Args_size=1
   0:	new	#158; //class scala/collection/mutable/AddingBuilder
   3:	dup
   4:	aload_0
   5:	invokeinterface	#162,  1; //InterfaceMethod scala/collection/SetLike.empty:()Lscala/collection/SetLike;
   10:	invokespecial	#165; //Method scala/collection/mutable/AddingBuilder."<init>":(Lscala/collection/generic/Addable;)V
   13:	areturn
  LineNumberTable: 
   line 66: 0

  LocalVariableTable: 
   Start  Length  Slot  Name   Signature
   0      14      0    $this       Lscala/collection/SetLike;


}

