Compiled from "SetProxyLike.scala"
public abstract class scala.collection.SetProxyLike$class extends java.lang.Object
  SourceFile: "SetProxyLike.scala"
  Scala: length = 0x
   
  minor version: 0
  major version: 49
  Constant pool:
const #1 = Asciz	SourceFile;
const #2 = Asciz	SetProxyLike.scala;
const #3 = Asciz	$init$;
const #4 = Asciz	(Lscala/collection/SetProxyLike;)V;
const #5 = Asciz	Code;
const #6 = Asciz	LineNumberTable;
const #7 = Asciz	$this;
const #8 = Asciz	Lscala/collection/SetProxyLike;;
const #9 = Asciz	LocalVariableTable;
const #10 = Asciz	subsetOf;
const #11 = Asciz	(Lscala/collection/SetProxyLike;Lscala/collection/Set;)Z;
const #12 = Asciz	scala/collection/TraversableProxyLike;
const #13 = class	#12;	//  scala/collection/TraversableProxyLike
const #14 = Asciz	self;
const #15 = Asciz	()Lscala/collection/TraversableLike;;
const #16 = NameAndType	#14:#15;//  self:()Lscala/collection/TraversableLike;
const #17 = InterfaceMethod	#13.#16;	//  scala/collection/TraversableProxyLike.self:()Lscala/collection/TraversableLike;
const #18 = Asciz	scala/collection/SetLike;
const #19 = class	#18;	//  scala/collection/SetLike
const #20 = Asciz	(Lscala/collection/Set;)Z;
const #21 = NameAndType	#10:#20;//  subsetOf:(Lscala/collection/Set;)Z
const #22 = InterfaceMethod	#19.#21;	//  scala/collection/SetLike.subsetOf:(Lscala/collection/Set;)Z
const #23 = Asciz	that;
const #24 = Asciz	Lscala/collection/Set;;
const #25 = Asciz	$amp$tilde;
const #26 = Asciz	(Lscala/collection/SetProxyLike;Lscala/collection/Set;)Lscala/collection/SetLike;;
const #27 = Asciz	(Lscala/collection/Set;)Lscala/collection/SetLike;;
const #28 = NameAndType	#25:#27;//  $amp$tilde:(Lscala/collection/Set;)Lscala/collection/SetLike;
const #29 = InterfaceMethod	#19.#28;	//  scala/collection/SetLike.$amp$tilde:(Lscala/collection/Set;)Lscala/collection/SetLike;
const #30 = Asciz	diff;
const #31 = NameAndType	#30:#27;//  diff:(Lscala/collection/Set;)Lscala/collection/SetLike;
const #32 = InterfaceMethod	#19.#31;	//  scala/collection/SetLike.diff:(Lscala/collection/Set;)Lscala/collection/SetLike;
const #33 = Asciz	$bar;
const #34 = NameAndType	#33:#27;//  $bar:(Lscala/collection/Set;)Lscala/collection/SetLike;
const #35 = InterfaceMethod	#19.#34;	//  scala/collection/SetLike.$bar:(Lscala/collection/Set;)Lscala/collection/SetLike;
const #36 = Asciz	union;
const #37 = NameAndType	#36:#27;//  union:(Lscala/collection/Set;)Lscala/collection/SetLike;
const #38 = InterfaceMethod	#19.#37;	//  scala/collection/SetLike.union:(Lscala/collection/Set;)Lscala/collection/SetLike;
const #39 = Asciz	$amp;
const #40 = NameAndType	#39:#27;//  $amp:(Lscala/collection/Set;)Lscala/collection/SetLike;
const #41 = InterfaceMethod	#19.#40;	//  scala/collection/SetLike.$amp:(Lscala/collection/Set;)Lscala/collection/SetLike;
const #42 = Asciz	intersect;
const #43 = NameAndType	#42:#27;//  intersect:(Lscala/collection/Set;)Lscala/collection/SetLike;
const #44 = InterfaceMethod	#19.#43;	//  scala/collection/SetLike.intersect:(Lscala/collection/Set;)Lscala/collection/SetLike;
const #45 = Asciz	apply;
const #46 = Asciz	(Lscala/collection/SetProxyLike;Ljava/lang/Object;)Z;
const #47 = Asciz	(Ljava/lang/Object;)Z;
const #48 = NameAndType	#45:#47;//  apply:(Ljava/lang/Object;)Z
const #49 = InterfaceMethod	#19.#48;	//  scala/collection/SetLike.apply:(Ljava/lang/Object;)Z
const #50 = Asciz	elem;
const #51 = Asciz	Ljava/lang/Object;;
const #52 = Asciz	isEmpty;
const #53 = Asciz	(Lscala/collection/SetProxyLike;)Z;
const #54 = Asciz	()Z;
const #55 = NameAndType	#52:#54;//  isEmpty:()Z
const #56 = InterfaceMethod	#19.#55;	//  scala/collection/SetLike.isEmpty:()Z
const #57 = Asciz	contains;
const #58 = NameAndType	#57:#47;//  contains:(Ljava/lang/Object;)Z
const #59 = InterfaceMethod	#19.#58;	//  scala/collection/SetLike.contains:(Ljava/lang/Object;)Z
const #60 = Asciz	Scala;
const #61 = Asciz	scala/collection/SetProxyLike$class;
const #62 = class	#61;	//  scala/collection/SetProxyLike$class
const #63 = Asciz	java/lang/Object;
const #64 = class	#63;	//  java/lang/Object

{
public static void $init$(scala.collection.SetProxyLike);
  Code:
   Stack=0, Locals=1, Args_size=1
   0:	return
  LineNumberTable: 
   line 22: 0

  LocalVariableTable: 
   Start  Length  Slot  Name   Signature
   0      1      0    $this       Lscala/collection/SetProxyLike;


public static boolean subsetOf(scala.collection.SetProxyLike, scala.collection.Set);
  Code:
   Stack=2, Locals=2, Args_size=2
   0:	aload_0
   1:	invokeinterface	#17,  1; //InterfaceMethod scala/collection/TraversableProxyLike.self:()Lscala/collection/TraversableLike;
   6:	checkcast	#19; //class scala/collection/SetLike
   9:	aload_1
   10:	invokeinterface	#22,  2; //InterfaceMethod scala/collection/SetLike.subsetOf:(Lscala/collection/Set;)Z
   15:	ireturn
  LineNumberTable: 
   line 36: 0

  LocalVariableTable: 
   Start  Length  Slot  Name   Signature
   0      16      0    $this       Lscala/collection/SetProxyLike;
   0      16      1    that       Lscala/collection/Set;


public static scala.collection.SetLike $amp$tilde(scala.collection.SetProxyLike, scala.collection.Set);
  Code:
   Stack=2, Locals=2, Args_size=2
   0:	aload_0
   1:	invokeinterface	#17,  1; //InterfaceMethod scala/collection/TraversableProxyLike.self:()Lscala/collection/TraversableLike;
   6:	checkcast	#19; //class scala/collection/SetLike
   9:	aload_1
   10:	invokeinterface	#29,  2; //InterfaceMethod scala/collection/SetLike.$amp$tilde:(Lscala/collection/Set;)Lscala/collection/SetLike;
   15:	areturn
  LineNumberTable: 
   line 35: 0

  LocalVariableTable: 
   Start  Length  Slot  Name   Signature
   0      16      0    $this       Lscala/collection/SetProxyLike;
   0      16      1    that       Lscala/collection/Set;


public static scala.collection.SetLike diff(scala.collection.SetProxyLike, scala.collection.Set);
  Code:
   Stack=2, Locals=2, Args_size=2
   0:	aload_0
   1:	invokeinterface	#17,  1; //InterfaceMethod scala/collection/TraversableProxyLike.self:()Lscala/collection/TraversableLike;
   6:	checkcast	#19; //class scala/collection/SetLike
   9:	aload_1
   10:	invokeinterface	#32,  2; //InterfaceMethod scala/collection/SetLike.diff:(Lscala/collection/Set;)Lscala/collection/SetLike;
   15:	areturn
  LineNumberTable: 
   line 34: 0

  LocalVariableTable: 
   Start  Length  Slot  Name   Signature
   0      16      0    $this       Lscala/collection/SetProxyLike;
   0      16      1    that       Lscala/collection/Set;


public static scala.collection.SetLike $bar(scala.collection.SetProxyLike, scala.collection.Set);
  Code:
   Stack=2, Locals=2, Args_size=2
   0:	aload_0
   1:	invokeinterface	#17,  1; //InterfaceMethod scala/collection/TraversableProxyLike.self:()Lscala/collection/TraversableLike;
   6:	checkcast	#19; //class scala/collection/SetLike
   9:	aload_1
   10:	invokeinterface	#35,  2; //InterfaceMethod scala/collection/SetLike.$bar:(Lscala/collection/Set;)Lscala/collection/SetLike;
   15:	areturn
  LineNumberTable: 
   line 33: 0

  LocalVariableTable: 
   Start  Length  Slot  Name   Signature
   0      16      0    $this       Lscala/collection/SetProxyLike;
   0      16      1    that       Lscala/collection/Set;


public static scala.collection.SetLike union(scala.collection.SetProxyLike, scala.collection.Set);
  Code:
   Stack=2, Locals=2, Args_size=2
   0:	aload_0
   1:	invokeinterface	#17,  1; //InterfaceMethod scala/collection/TraversableProxyLike.self:()Lscala/collection/TraversableLike;
   6:	checkcast	#19; //class scala/collection/SetLike
   9:	aload_1
   10:	invokeinterface	#38,  2; //InterfaceMethod scala/collection/SetLike.union:(Lscala/collection/Set;)Lscala/collection/SetLike;
   15:	areturn
  LineNumberTable: 
   line 32: 0

  LocalVariableTable: 
   Start  Length  Slot  Name   Signature
   0      16      0    $this       Lscala/collection/SetProxyLike;
   0      16      1    that       Lscala/collection/Set;


public static scala.collection.SetLike $amp(scala.collection.SetProxyLike, scala.collection.Set);
  Code:
   Stack=2, Locals=2, Args_size=2
   0:	aload_0
   1:	invokeinterface	#17,  1; //InterfaceMethod scala/collection/TraversableProxyLike.self:()Lscala/collection/TraversableLike;
   6:	checkcast	#19; //class scala/collection/SetLike
   9:	aload_1
   10:	invokeinterface	#41,  2; //InterfaceMethod scala/collection/SetLike.$amp:(Lscala/collection/Set;)Lscala/collection/SetLike;
   15:	areturn
  LineNumberTable: 
   line 31: 0

  LocalVariableTable: 
   Start  Length  Slot  Name   Signature
   0      16      0    $this       Lscala/collection/SetProxyLike;
   0      16      1    that       Lscala/collection/Set;


public static scala.collection.SetLike intersect(scala.collection.SetProxyLike, scala.collection.Set);
  Code:
   Stack=2, Locals=2, Args_size=2
   0:	aload_0
   1:	invokeinterface	#17,  1; //InterfaceMethod scala/collection/TraversableProxyLike.self:()Lscala/collection/TraversableLike;
   6:	checkcast	#19; //class scala/collection/SetLike
   9:	aload_1
   10:	invokeinterface	#44,  2; //InterfaceMethod scala/collection/SetLike.intersect:(Lscala/collection/Set;)Lscala/collection/SetLike;
   15:	areturn
  LineNumberTable: 
   line 30: 0

  LocalVariableTable: 
   Start  Length  Slot  Name   Signature
   0      16      0    $this       Lscala/collection/SetProxyLike;
   0      16      1    that       Lscala/collection/Set;


public static boolean apply(scala.collection.SetProxyLike, java.lang.Object);
  Code:
   Stack=2, Locals=2, Args_size=2
   0:	aload_0
   1:	invokeinterface	#17,  1; //InterfaceMethod scala/collection/TraversableProxyLike.self:()Lscala/collection/TraversableLike;
   6:	checkcast	#19; //class scala/collection/SetLike
   9:	aload_1
   10:	invokeinterface	#49,  2; //InterfaceMethod scala/collection/SetLike.apply:(Ljava/lang/Object;)Z
   15:	ireturn
  LineNumberTable: 
   line 29: 0

  LocalVariableTable: 
   Start  Length  Slot  Name   Signature
   0      16      0    $this       Lscala/collection/SetProxyLike;
   0      16      1    elem       Ljava/lang/Object;


public static boolean isEmpty(scala.collection.SetProxyLike);
  Code:
   Stack=1, Locals=1, Args_size=1
   0:	aload_0
   1:	invokeinterface	#17,  1; //InterfaceMethod scala/collection/TraversableProxyLike.self:()Lscala/collection/TraversableLike;
   6:	checkcast	#19; //class scala/collection/SetLike
   9:	invokeinterface	#56,  1; //InterfaceMethod scala/collection/SetLike.isEmpty:()Z
   14:	ireturn
  LineNumberTable: 
   line 28: 0

  LocalVariableTable: 
   Start  Length  Slot  Name   Signature
   0      15      0    $this       Lscala/collection/SetProxyLike;


public static boolean contains(scala.collection.SetProxyLike, java.lang.Object);
  Code:
   Stack=2, Locals=2, Args_size=2
   0:	aload_0
   1:	invokeinterface	#17,  1; //InterfaceMethod scala/collection/TraversableProxyLike.self:()Lscala/collection/TraversableLike;
   6:	checkcast	#19; //class scala/collection/SetLike
   9:	aload_1
   10:	invokeinterface	#59,  2; //InterfaceMethod scala/collection/SetLike.contains:(Ljava/lang/Object;)Z
   15:	ireturn
  LineNumberTable: 
   line 27: 0

  LocalVariableTable: 
   Start  Length  Slot  Name   Signature
   0      16      0    $this       Lscala/collection/SetProxyLike;
   0      16      1    elem       Ljava/lang/Object;


}

