Compiled from "SortedMap.scala"
public final class scala.collection.SortedMap$ extends scala.collection.generic.SortedMapFactory implements scala.ScalaObject
  SourceFile: "SortedMap.scala"
  Scala: length = 0x
   
  Signature: length = 0x2
   00 2D 
  InnerClass: 
   public SortedMapCanBuildFrom=class scala/collection/generic/SortedMapFactory$SortedMapCanBuildFrom of class scala/collection/generic/SortedMapFactory
  minor version: 0
  major version: 49
  Constant pool:
Asciz	SourceFile;
Asciz	SortedMap.scala;
Asciz	Scala;
Asciz	MODULE$;
Asciz	Lscala/collection/SortedMap$;;
Asciz	<clinit>;
Asciz	()V;
Asciz	Code;
Asciz	scala/collection/SortedMap$;
class	scala/collection/SortedMap$
Asciz	<init>;
NameAndType	"<init>":()V
Method	scala/collection/SortedMap$."<init>":()V
Asciz	empty;
Asciz	(Lscala/math/Ordering;)Lscala/collection/immutable/SortedMap;;
Asciz	scala/collection/immutable/SortedMap$;
class	scala/collection/immutable/SortedMap$
Asciz	Lscala/collection/immutable/SortedMap$;;
NameAndType	MODULE$:Lscala/collection/immutable/SortedMap$;
Field	scala/collection/immutable/SortedMap$.MODULE$:Lscala/collection/immutable/SortedMap$;
Asciz	LineNumberTable;
NameAndType	empty:(Lscala/math/Ordering;)Lscala/collection/immutable/SortedMap;
Method	scala/collection/immutable/SortedMap$.empty:(Lscala/math/Ordering;)Lscala/collection/immutable/SortedMap;
Asciz	this;
Asciz	ord;
Asciz	Lscala/math/Ordering;;
Asciz	LocalVariableTable;
Asciz	<A:Ljava/lang/Object;B:Ljava/lang/Object;>(Lscala/math/Ordering<TA;>;)Lscala/collection/immutable/SortedMap<TA;TB;>;;
Asciz	Signature;
Asciz	canBuildFrom;
Asciz	(Lscala/math/Ordering;)Lscala/collection/generic/CanBuildFrom;;
Asciz	scala/collection/generic/SortedMapFactory$SortedMapCanBuildFrom;
class	scala/collection/generic/SortedMapFactory$SortedMapCanBuildFrom
Asciz	(Lscala/collection/generic/SortedMapFactory;Lscala/math/Ordering;)V;
NameAndType	"<init>":(Lscala/collection/generic/SortedMapFactory;Lscala/math/Ordering;)V
Method	scala/collection/generic/SortedMapFactory$SortedMapCanBuildFrom."<init>":(Lscala/collection/generic/SortedMapFactory;Lscala/math/Ordering;)V
Asciz	<A:Ljava/lang/Object;B:Ljava/lang/Object;>(Lscala/math/Ordering<TA;>;)Lscala/collection/generic/CanBuildFrom<Lscala/collection/SortedMap<**>;Lscala/Tuple2<TA;TB;>;Lscala/collection/SortedMap<TA;TB;>;>;;
Asciz	(Lscala/math/Ordering;)Lscala/collection/SortedMap;;
Method	scala/collection/SortedMap$.empty:(Lscala/math/Ordering;)Lscala/collection/immutable/SortedMap;
Asciz	scala/collection/generic/SortedMapFactory;
class	scala/collection/generic/SortedMapFactory
Method	scala/collection/generic/SortedMapFactory."<init>":()V
NameAndType	MODULE$:Lscala/collection/SortedMap$;
Field	scala/collection/SortedMap$.MODULE$:Lscala/collection/SortedMap$;
Asciz	Lscala/collection/generic/SortedMapFactory<Lscala/collection/SortedMap;>;Lscala/ScalaObject;;
Asciz	InnerClasses;
Asciz	SortedMapCanBuildFrom;
Asciz	scala/ScalaObject;
class	scala/ScalaObject

{
public static final scala.collection.SortedMap$ MODULE$;
  Signature: Lscala/collection/SortedMap$;

public static {};
  Signature: ()V
  Code:
   Stack=1, Locals=0, Args_size=0
	new	class scala/collection/SortedMap$
	invokespecial	Method "<init>":()V
	return
  Labels:

public scala.collection.immutable.SortedMap empty(scala.math.Ordering);
  Signature: (Lscala/math/Ordering;)Lscala/collection/immutable/SortedMap;
  Code:
   Stack=2, Locals=2, Args_size=2
	getstatic	Field scala/collection/immutable/SortedMap$.MODULE$:Lscala/collection/immutable/SortedMap$;
	aload_1
	invokevirtual	Method scala/collection/immutable/SortedMap$.empty:(Lscala/math/Ordering;)Lscala/collection/immutable/SortedMap;
	areturn
  Labels:
  LocalVariableTable: 
   Start  Length  Slot  Name   Signature
   0      8      0    this       Lscala/collection/SortedMap$;
   0      8      1    ord       Lscala/math/Ordering;

  Signature: length = 0x2
   00 1C 

public scala.collection.generic.CanBuildFrom canBuildFrom(scala.math.Ordering);
  Signature: (Lscala/math/Ordering;)Lscala/collection/generic/CanBuildFrom;
  Code:
   Stack=4, Locals=2, Args_size=2
	new	class scala/collection/generic/SortedMapFactory$SortedMapCanBuildFrom
	dup
	aload_0
	aload_1
	invokespecial	Method scala/collection/generic/SortedMapFactory$SortedMapCanBuildFrom."<init>":(Lscala/collection/generic/SortedMapFactory;Lscala/math/Ordering;)V
	areturn
  Labels:
  LocalVariableTable: 
   Start  Length  Slot  Name   Signature
   0      10      0    this       Lscala/collection/SortedMap$;
   0      10      1    ord       Lscala/math/Ordering;

  Signature: length = 0x2
   00 25 

public scala.collection.SortedMap empty(scala.math.Ordering);
  Signature: (Lscala/math/Ordering;)Lscala/collection/SortedMap;
  Code:
   Stack=2, Locals=2, Args_size=2
	aload_0
	aload_1
	invokevirtual	Method empty:(Lscala/math/Ordering;)Lscala/collection/immutable/SortedMap;
	areturn
  Labels:
  LocalVariableTable: 
   Start  Length  Slot  Name   Signature
   0      6      0    this       Lscala/collection/SortedMap$;
   0      6      1    ord       Lscala/math/Ordering;


private scala.collection.SortedMap$();
  Signature: ()V
  Code:
   Stack=1, Locals=1, Args_size=1
	aload_0
	invokespecial	Method scala/collection/generic/SortedMapFactory."<init>":()V
	aload_0
	putstatic	Field MODULE$:Lscala/collection/SortedMap$;
	return
  Labels:

}

