Compiled from "SortedSetLike.scala"
public abstract class scala.collection.SortedSetLike$class extends java.lang.Object
  SourceFile: "SortedSetLike.scala"
  Scala: length = 0x
   
  minor version: 0
  major version: 49
  Constant pool:
const #1 = Asciz	SourceFile;
const #2 = Asciz	SortedSetLike.scala;
const #3 = Asciz	$init$;
const #4 = Asciz	(Lscala/collection/SortedSetLike;)V;
const #5 = Asciz	Code;
const #6 = Asciz	LineNumberTable;
const #7 = Asciz	$this;
const #8 = Asciz	Lscala/collection/SortedSetLike;;
const #9 = Asciz	LocalVariableTable;
const #10 = Asciz	gd1$1;
const #11 = Asciz	(Lscala/collection/SortedSetLike;Lscala/collection/SortedSet;)Z;
const #12 = Asciz	scala/collection/SortedSetLike;
const #13 = class	#12;	//  scala/collection/SortedSetLike
const #14 = Asciz	ordering;
const #15 = Asciz	()Lscala/math/Ordering;;
const #16 = NameAndType	#14:#15;//  ordering:()Lscala/math/Ordering;
const #17 = InterfaceMethod	#13.#16;	//  scala/collection/SortedSetLike.ordering:()Lscala/math/Ordering;
const #18 = Asciz	java/lang/Object;
const #19 = class	#18;	//  java/lang/Object
const #20 = Asciz	equals;
const #21 = Asciz	(Ljava/lang/Object;)Z;
const #22 = NameAndType	#20:#21;//  equals:(Ljava/lang/Object;)Z
const #23 = Method	#19.#22;	//  java/lang/Object.equals:(Ljava/lang/Object;)Z
const #24 = Asciz	subsetOf;
const #25 = Asciz	(Lscala/collection/SortedSetLike;Lscala/collection/Set;)Z;
const #26 = Asciz	scala/collection/SortedSet;
const #27 = class	#26;	//  scala/collection/SortedSet
const #28 = Asciz	scala/collection/SortedSetLike$class;
const #29 = class	#28;	//  scala/collection/SortedSetLike$class
const #30 = NameAndType	#10:#11;//  gd1$1:(Lscala/collection/SortedSetLike;Lscala/collection/SortedSet;)Z
const #31 = Method	#29.#30;	//  scala/collection/SortedSetLike$class.gd1$1:(Lscala/collection/SortedSetLike;Lscala/collection/SortedSet;)Z
const #32 = Asciz	scala/collection/IterableLike;
const #33 = class	#32;	//  scala/collection/IterableLike
const #34 = Asciz	iterator;
const #35 = Asciz	()Lscala/collection/Iterator;;
const #36 = NameAndType	#34:#35;//  iterator:()Lscala/collection/Iterator;
const #37 = InterfaceMethod	#33.#36;	//  scala/collection/IterableLike.iterator:()Lscala/collection/Iterator;
const #38 = Asciz	scala/collection/generic/Sorted;
const #39 = class	#38;	//  scala/collection/generic/Sorted
const #40 = Asciz	hasAll;
const #41 = Asciz	(Lscala/collection/Iterator;)Z;
const #42 = NameAndType	#40:#41;//  hasAll:(Lscala/collection/Iterator;)Z
const #43 = InterfaceMethod	#39.#42;	//  scala/collection/generic/Sorted.hasAll:(Lscala/collection/Iterator;)Z
const #44 = Asciz	scala/MatchError;
const #45 = class	#44;	//  scala/MatchError
const #46 = Asciz	scala/collection/SetLike;
const #47 = class	#46;	//  scala/collection/SetLike
const #48 = Asciz	toString;
const #49 = Asciz	()Ljava/lang/String;;
const #50 = NameAndType	#48:#49;//  toString:()Ljava/lang/String;
const #51 = InterfaceMethod	#47.#50;	//  scala/collection/SetLike.toString:()Ljava/lang/String;
const #52 = Asciz	<init>;
const #53 = Asciz	(Ljava/lang/String;)V;
const #54 = NameAndType	#52:#53;//  "<init>":(Ljava/lang/String;)V
const #55 = Method	#45.#54;	//  scala/MatchError."<init>":(Ljava/lang/String;)V
const #56 = Asciz	scala$collection$SortedSetLike$$super$subsetOf;
const #57 = Asciz	(Lscala/collection/Set;)Z;
const #58 = NameAndType	#56:#57;//  scala$collection$SortedSetLike$$super$subsetOf:(Lscala/collection/Set;)Z
const #59 = InterfaceMethod	#13.#58;	//  scala/collection/SortedSetLike.scala$collection$SortedSetLike$$super$subsetOf:(Lscala/collection/Set;)Z
const #60 = Asciz	that;
const #61 = Asciz	Lscala/collection/Set;;
const #62 = Asciz	temp2;
const #63 = Asciz	Lscala/collection/SortedSet;;
const #64 = Asciz	range;
const #65 = Asciz	(Lscala/collection/SortedSetLike;Ljava/lang/Object;Ljava/lang/Object;)Lscala/collection/SortedSet;;
const #66 = Asciz	scala/Some;
const #67 = class	#66;	//  scala/Some
const #68 = Asciz	(Ljava/lang/Object;)V;
const #69 = NameAndType	#52:#68;//  "<init>":(Ljava/lang/Object;)V
const #70 = Method	#67.#69;	//  scala/Some."<init>":(Ljava/lang/Object;)V
const #71 = Asciz	rangeImpl;
const #72 = Asciz	(Lscala/Option;Lscala/Option;)Lscala/collection/SortedSet;;
const #73 = NameAndType	#71:#72;//  rangeImpl:(Lscala/Option;Lscala/Option;)Lscala/collection/SortedSet;
const #74 = InterfaceMethod	#13.#73;	//  scala/collection/SortedSetLike.rangeImpl:(Lscala/Option;Lscala/Option;)Lscala/collection/SortedSet;
const #75 = Asciz	from;
const #76 = Asciz	Ljava/lang/Object;;
const #77 = Asciz	until;
const #78 = Asciz	(Lscala/collection/SortedSetLike;Ljava/lang/Object;)Lscala/collection/SortedSet;;
const #79 = Asciz	scala/None$;
const #80 = class	#79;	//  scala/None$
const #81 = Asciz	MODULE$;
const #82 = Asciz	Lscala/None$;;
const #83 = NameAndType	#81:#82;//  MODULE$:Lscala/None$;
const #84 = Field	#80.#83;	//  scala/None$.MODULE$:Lscala/None$;
const #85 = Asciz	lastKey;
const #86 = Asciz	(Lscala/collection/SortedSetLike;)Ljava/lang/Object;;
const #87 = Asciz	scala/collection/TraversableLike;
const #88 = class	#87;	//  scala/collection/TraversableLike
const #89 = Asciz	last;
const #90 = Asciz	()Ljava/lang/Object;;
const #91 = NameAndType	#89:#90;//  last:()Ljava/lang/Object;
const #92 = InterfaceMethod	#88.#91;	//  scala/collection/TraversableLike.last:()Ljava/lang/Object;
const #93 = Asciz	firstKey;
const #94 = Asciz	head;
const #95 = NameAndType	#94:#90;//  head:()Ljava/lang/Object;
const #96 = InterfaceMethod	#33.#95;	//  scala/collection/IterableLike.head:()Ljava/lang/Object;
const #97 = Asciz	keySet;
const #98 = Asciz	(Lscala/collection/SortedSetLike;)Lscala/collection/SortedSet;;
const #99 = Asciz	repr;
const #100 = NameAndType	#99:#90;//  repr:()Ljava/lang/Object;
const #101 = InterfaceMethod	#88.#100;	//  scala/collection/TraversableLike.repr:()Ljava/lang/Object;
const #102 = Asciz	Scala;

{
public static void $init$(scala.collection.SortedSetLike);
  Code:
   Stack=0, Locals=1, Args_size=1
   0:	return
  LineNumberTable: 
   line 21: 0

  LocalVariableTable: 
   Start  Length  Slot  Name   Signature
   0      1      0    $this       Lscala/collection/SortedSetLike;


public static boolean subsetOf(scala.collection.SortedSetLike, scala.collection.Set);
  Code:
   Stack=3, Locals=4, Args_size=2
   0:	aload_1
   1:	instanceof	#27; //class scala/collection/SortedSet
   4:	ifeq	58
   7:	aload_1
   8:	checkcast	#27; //class scala/collection/SortedSet
   11:	astore_2
   12:	aload_0
   13:	aload_2
   14:	invokestatic	#31; //Method gd1$1:(Lscala/collection/SortedSetLike;Lscala/collection/SortedSet;)Z
   17:	ifeq	35
   20:	aload_2
   21:	aload_0
   22:	invokeinterface	#37,  1; //InterfaceMethod scala/collection/IterableLike.iterator:()Lscala/collection/Iterator;
   27:	invokeinterface	#43,  2; //InterfaceMethod scala/collection/generic/Sorted.hasAll:(Lscala/collection/Iterator;)Z
   32:	goto	71
   35:	iconst_1
   36:	ifeq	44
   39:	aload_2
   40:	astore_3
   41:	goto	64
   44:	new	#45; //class scala/MatchError
   47:	dup
   48:	aload_1
   49:	invokeinterface	#51,  1; //InterfaceMethod scala/collection/SetLike.toString:()Ljava/lang/String;
   54:	invokespecial	#55; //Method scala/MatchError."<init>":(Ljava/lang/String;)V
   57:	athrow
   58:	iconst_1
   59:	ifeq	72
   62:	aload_1
   63:	astore_3
   64:	aload_0
   65:	aload_3
   66:	invokeinterface	#59,  2; //InterfaceMethod scala/collection/SortedSetLike.scala$collection$SortedSetLike$$super$subsetOf:(Lscala/collection/Set;)Z
   71:	ireturn
   72:	new	#45; //class scala/MatchError
   75:	dup
   76:	aload_1
   77:	invokeinterface	#51,  1; //InterfaceMethod scala/collection/SetLike.toString:()Ljava/lang/String;
   82:	invokespecial	#55; //Method scala/MatchError."<init>":(Ljava/lang/String;)V
   85:	athrow
  LineNumberTable: 
   line 37: 0
   line 41: 20
   line 21: 35
   line 42: 39
   line 37: 44
   line 21: 58
   line 42: 62
   line 37: 71

  LocalVariableTable: 
   Start  Length  Slot  Name   Signature
   0      86      0    $this       Lscala/collection/SortedSetLike;
   0      86      1    that       Lscala/collection/Set;
   12      46      2    temp2       Lscala/collection/SortedSet;
   64      7      2    temp2       Lscala/collection/SortedSet;
   35      4      3    that       Lscala/collection/Set;
   41      3      3    that       Lscala/collection/Set;
   39      19      3    that       Lscala/collection/Set;
   64      7      3    that       Lscala/collection/Set;


public static scala.collection.SortedSet range(scala.collection.SortedSetLike, java.lang.Object, java.lang.Object);
  Code:
   Stack=5, Locals=3, Args_size=3
   0:	aload_0
   1:	new	#67; //class scala/Some
   4:	dup
   5:	aload_1
   6:	invokespecial	#70; //Method scala/Some."<init>":(Ljava/lang/Object;)V
   9:	new	#67; //class scala/Some
   12:	dup
   13:	aload_2
   14:	invokespecial	#70; //Method scala/Some."<init>":(Ljava/lang/Object;)V
   17:	invokeinterface	#74,  3; //InterfaceMethod scala/collection/SortedSetLike.rangeImpl:(Lscala/Option;Lscala/Option;)Lscala/collection/SortedSet;
   22:	areturn
  LineNumberTable: 
   line 35: 0

  LocalVariableTable: 
   Start  Length  Slot  Name   Signature
   0      23      0    $this       Lscala/collection/SortedSetLike;
   0      23      1    from       Ljava/lang/Object;
   0      23      2    until       Ljava/lang/Object;


public static scala.collection.SortedSet until(scala.collection.SortedSetLike, java.lang.Object);
  Code:
   Stack=5, Locals=2, Args_size=2
   0:	aload_0
   1:	getstatic	#84; //Field scala/None$.MODULE$:Lscala/None$;
   4:	new	#67; //class scala/Some
   7:	dup
   8:	aload_1
   9:	invokespecial	#70; //Method scala/Some."<init>":(Ljava/lang/Object;)V
   12:	invokeinterface	#74,  3; //InterfaceMethod scala/collection/SortedSetLike.rangeImpl:(Lscala/Option;Lscala/Option;)Lscala/collection/SortedSet;
   17:	areturn
  LineNumberTable: 
   line 34: 0

  LocalVariableTable: 
   Start  Length  Slot  Name   Signature
   0      18      0    $this       Lscala/collection/SortedSetLike;
   0      18      1    until       Ljava/lang/Object;


public static scala.collection.SortedSet from(scala.collection.SortedSetLike, java.lang.Object);
  Code:
   Stack=4, Locals=2, Args_size=2
   0:	aload_0
   1:	new	#67; //class scala/Some
   4:	dup
   5:	aload_1
   6:	invokespecial	#70; //Method scala/Some."<init>":(Ljava/lang/Object;)V
   9:	getstatic	#84; //Field scala/None$.MODULE$:Lscala/None$;
   12:	invokeinterface	#74,  3; //InterfaceMethod scala/collection/SortedSetLike.rangeImpl:(Lscala/Option;Lscala/Option;)Lscala/collection/SortedSet;
   17:	areturn
  LineNumberTable: 
   line 33: 0

  LocalVariableTable: 
   Start  Length  Slot  Name   Signature
   0      18      0    $this       Lscala/collection/SortedSetLike;
   0      18      1    from       Ljava/lang/Object;


public static java.lang.Object lastKey(scala.collection.SortedSetLike);
  Code:
   Stack=1, Locals=1, Args_size=1
   0:	aload_0
   1:	invokeinterface	#92,  1; //InterfaceMethod scala/collection/TraversableLike.last:()Ljava/lang/Object;
   6:	areturn
  LineNumberTable: 
   line 29: 0

  LocalVariableTable: 
   Start  Length  Slot  Name   Signature
   0      7      0    $this       Lscala/collection/SortedSetLike;


public static java.lang.Object firstKey(scala.collection.SortedSetLike);
  Code:
   Stack=1, Locals=1, Args_size=1
   0:	aload_0
   1:	invokeinterface	#96,  1; //InterfaceMethod scala/collection/IterableLike.head:()Ljava/lang/Object;
   6:	areturn
  LineNumberTable: 
   line 28: 0

  LocalVariableTable: 
   Start  Length  Slot  Name   Signature
   0      7      0    $this       Lscala/collection/SortedSetLike;


public static scala.collection.SortedSet keySet(scala.collection.SortedSetLike);
  Code:
   Stack=1, Locals=1, Args_size=1
   0:	aload_0
   1:	invokeinterface	#101,  1; //InterfaceMethod scala/collection/TraversableLike.repr:()Ljava/lang/Object;
   6:	checkcast	#27; //class scala/collection/SortedSet
   9:	areturn
  LineNumberTable: 
   line 26: 0

  LocalVariableTable: 
   Start  Length  Slot  Name   Signature
   0      10      0    $this       Lscala/collection/SortedSetLike;


}

