Compiled from "SortedMap.scala"
public abstract class scala.collection.SortedMap$class extends java.lang.Object
  SourceFile: "SortedMap.scala"
  Scala: length = 0x
   
  minor version: 0
  major version: 49
  Constant pool:
const #1 = Asciz	SourceFile;
const #2 = Asciz	SortedMap.scala;
const #3 = Asciz	$init$;
const #4 = Asciz	(Lscala/collection/SortedMap;)V;
const #5 = Asciz	Code;
const #6 = Asciz	LineNumberTable;
const #7 = Asciz	$this;
const #8 = Asciz	Lscala/collection/SortedMap;;
const #9 = Asciz	LocalVariableTable;
const #10 = Asciz	newBuilder;
const #11 = Asciz	(Lscala/collection/SortedMap;)Lscala/collection/mutable/Builder;;
const #12 = Asciz	scala/collection/immutable/SortedMap$;
const #13 = class	#12;	//  scala/collection/immutable/SortedMap$
const #14 = Asciz	MODULE$;
const #15 = Asciz	Lscala/collection/immutable/SortedMap$;;
const #16 = NameAndType	#14:#15;//  MODULE$:Lscala/collection/immutable/SortedMap$;
const #17 = Field	#13.#16;	//  scala/collection/immutable/SortedMap$.MODULE$:Lscala/collection/immutable/SortedMap$;
const #18 = Asciz	scala/collection/SortedMapLike;
const #19 = class	#18;	//  scala/collection/SortedMapLike
const #20 = Asciz	ordering;
const #21 = Asciz	()Lscala/math/Ordering;;
const #22 = NameAndType	#20:#21;//  ordering:()Lscala/math/Ordering;
const #23 = InterfaceMethod	#19.#22;	//  scala/collection/SortedMapLike.ordering:()Lscala/math/Ordering;
const #24 = Asciz	(Lscala/math/Ordering;)Lscala/collection/mutable/Builder;;
const #25 = NameAndType	#10:#24;//  newBuilder:(Lscala/math/Ordering;)Lscala/collection/mutable/Builder;
const #26 = Method	#13.#25;	//  scala/collection/immutable/SortedMap$.newBuilder:(Lscala/math/Ordering;)Lscala/collection/mutable/Builder;
const #27 = Asciz	empty;
const #28 = Asciz	(Lscala/collection/SortedMap;)Lscala/collection/immutable/SortedMap;;
const #29 = Asciz	scala/collection/SortedMap$;
const #30 = class	#29;	//  scala/collection/SortedMap$
const #31 = Asciz	Lscala/collection/SortedMap$;;
const #32 = NameAndType	#14:#31;//  MODULE$:Lscala/collection/SortedMap$;
const #33 = Field	#30.#32;	//  scala/collection/SortedMap$.MODULE$:Lscala/collection/SortedMap$;
const #34 = Asciz	(Lscala/math/Ordering;)Lscala/collection/immutable/SortedMap;;
const #35 = NameAndType	#27:#34;//  empty:(Lscala/math/Ordering;)Lscala/collection/immutable/SortedMap;
const #36 = Method	#30.#35;	//  scala/collection/SortedMap$.empty:(Lscala/math/Ordering;)Lscala/collection/immutable/SortedMap;
const #37 = Asciz	Scala;
const #38 = Asciz	scala/collection/SortedMap$class;
const #39 = class	#38;	//  scala/collection/SortedMap$class
const #40 = Asciz	java/lang/Object;
const #41 = class	#40;	//  java/lang/Object

{
public static void $init$(scala.collection.SortedMap);
  Code:
   Stack=0, Locals=1, Args_size=1
   0:	return
  LineNumberTable: 
   line 22: 0

  LocalVariableTable: 
   Start  Length  Slot  Name   Signature
   0      1      0    $this       Lscala/collection/SortedMap;


public static scala.collection.mutable.Builder newBuilder(scala.collection.SortedMap);
  Code:
   Stack=2, Locals=1, Args_size=1
   0:	getstatic	#17; //Field scala/collection/immutable/SortedMap$.MODULE$:Lscala/collection/immutable/SortedMap$;
   3:	aload_0
   4:	invokeinterface	#23,  1; //InterfaceMethod scala/collection/SortedMapLike.ordering:()Lscala/math/Ordering;
   9:	invokevirtual	#26; //Method scala/collection/immutable/SortedMap$.newBuilder:(Lscala/math/Ordering;)Lscala/collection/mutable/Builder;
   12:	areturn
  LineNumberTable: 
   line 27: 0

  LocalVariableTable: 
   Start  Length  Slot  Name   Signature
   0      13      0    $this       Lscala/collection/SortedMap;


public static scala.collection.immutable.SortedMap empty(scala.collection.SortedMap);
  Code:
   Stack=2, Locals=1, Args_size=1
   0:	getstatic	#33; //Field scala/collection/SortedMap$.MODULE$:Lscala/collection/SortedMap$;
   3:	aload_0
   4:	invokeinterface	#23,  1; //InterfaceMethod scala/collection/SortedMapLike.ordering:()Lscala/math/Ordering;
   9:	invokevirtual	#36; //Method scala/collection/SortedMap$.empty:(Lscala/math/Ordering;)Lscala/collection/immutable/SortedMap;
   12:	areturn
  LineNumberTable: 
   line 24: 0

  LocalVariableTable: 
   Start  Length  Slot  Name   Signature
   0      13      0    $this       Lscala/collection/SortedMap;


}

