Compiled from "TraversableViewLike.scala"
public abstract class scala.collection.TraversableViewLike$DroppedWhile$class extends java.lang.Object
  SourceFile: "TraversableViewLike.scala"
  Scala: length = 0x
   
  InnerClass: 
   public abstract DroppedWhile=class scala/collection/TraversableViewLike$DroppedWhile of class scala/collection/TraversableViewLike
   public final $anonfun$foreach$8=class scala/collection/TraversableViewLike$DroppedWhile$$anonfun$foreach$8 of class scala/collection/TraversableViewLike$DroppedWhile
  minor version: 0
  major version: 49
  Constant pool:
Asciz	SourceFile;
Asciz	TraversableViewLike.scala;
Asciz	$init$;
Asciz	(Lscala/collection/TraversableViewLike$DroppedWhile;)V;
Asciz	Code;
Asciz	LineNumberTable;
Asciz	$this;
Asciz	Lscala/collection/TraversableViewLike$DroppedWhile;;
Asciz	LocalVariableTable;
Asciz	stringPrefix;
Asciz	(Lscala/collection/TraversableViewLike$DroppedWhile;)Ljava/lang/String;;
Asciz	scala/collection/mutable/StringBuilder;
class	scala/collection/mutable/StringBuilder
Asciz	<init>;
Asciz	()V;
NameAndType	"<init>":()V
Method	scala/collection/mutable/StringBuilder."<init>":()V
Asciz	scala/collection/TraversableViewLike$DroppedWhile;
class	scala/collection/TraversableViewLike$DroppedWhile
Asciz	scala$collection$TraversableViewLike$DroppedWhile$$$outer;
Asciz	()Lscala/collection/TraversableViewLike;;
NameAndType	scala$collection$TraversableViewLike$DroppedWhile$$$outer:()Lscala/collection/TraversableViewLike;
InterfaceMethod	scala/collection/TraversableViewLike$DroppedWhile.scala$collection$TraversableViewLike$DroppedWhile$$$outer:()Lscala/collection/TraversableViewLike;
Asciz	scala/collection/TraversableViewLike;
class	scala/collection/TraversableViewLike
Asciz	()Ljava/lang/String;;
NameAndType	stringPrefix:()Ljava/lang/String;
InterfaceMethod	scala/collection/TraversableViewLike.stringPrefix:()Ljava/lang/String;
Asciz	append;
Asciz	(Ljava/lang/Object;)Lscala/collection/mutable/StringBuilder;;
NameAndType	append:(Ljava/lang/Object;)Lscala/collection/mutable/StringBuilder;
Method	scala/collection/mutable/StringBuilder.append:(Ljava/lang/Object;)Lscala/collection/mutable/StringBuilder;
Asciz	D;
String	D
Asciz	toString;
NameAndType	toString:()Ljava/lang/String;
Method	scala/collection/mutable/StringBuilder.toString:()Ljava/lang/String;
Asciz	foreach;
Asciz	(Lscala/collection/TraversableViewLike$DroppedWhile;Lscala/Function1;)V;
Asciz	scala/runtime/BooleanRef;
class	scala/runtime/BooleanRef
Asciz	(Z)V;
NameAndType	"<init>":(Z)V
Method	scala/runtime/BooleanRef."<init>":(Z)V
Asciz	scala/collection/TraversableViewLike$DroppedWhile$$anonfun$foreach$8;
class	scala/collection/TraversableViewLike$DroppedWhile$$anonfun$foreach$8
Asciz	(Lscala/collection/TraversableViewLike$DroppedWhile;Lscala/Function1;Lscala/runtime/BooleanRef;)V;
NameAndType	"<init>":(Lscala/collection/TraversableViewLike$DroppedWhile;Lscala/Function1;Lscala/runtime/BooleanRef;)V
Method	scala/collection/TraversableViewLike$DroppedWhile$$anonfun$foreach$8."<init>":(Lscala/collection/TraversableViewLike$DroppedWhile;Lscala/Function1;Lscala/runtime/BooleanRef;)V
Asciz	scala/collection/generic/GenericTraversableTemplate;
class	scala/collection/generic/GenericTraversableTemplate
Asciz	(Lscala/Function1;)V;
NameAndType	foreach:(Lscala/Function1;)V
InterfaceMethod	scala/collection/generic/GenericTraversableTemplate.foreach:(Lscala/Function1;)V
Asciz	f$9;
Asciz	Lscala/Function1;;
Asciz	go$1;
Asciz	Lscala/runtime/BooleanRef;;
Asciz	Scala;
Asciz	InnerClasses;
Asciz	DroppedWhile;
Asciz	$anonfun$foreach$8;
Asciz	scala/collection/TraversableViewLike$DroppedWhile$class;
class	scala/collection/TraversableViewLike$DroppedWhile$class
Asciz	java/lang/Object;
class	java/lang/Object

{
public static void $init$(scala.collection.TraversableViewLike$DroppedWhile);
  Signature: (Lscala/collection/TraversableViewLike$DroppedWhile;)V
  Code:
   Stack=0, Locals=1, Args_size=1
	return
  Labels:
  LocalVariableTable: 
   Start  Length  Slot  Name   Signature
   0      1      0    $this       Lscala/collection/TraversableViewLike$DroppedWhile;


public static java.lang.String stringPrefix(scala.collection.TraversableViewLike$DroppedWhile);
  Signature: (Lscala/collection/TraversableViewLike$DroppedWhile;)Ljava/lang/String;
  Code:
   Stack=2, Locals=1, Args_size=1
	new	class scala/collection/mutable/StringBuilder
	dup
	invokespecial	Method scala/collection/mutable/StringBuilder."<init>":()V
	aload_0
	invokeinterface	InterfaceMethod scala/collection/TraversableViewLike$DroppedWhile.scala$collection$TraversableViewLike$DroppedWhile$$$outer:()Lscala/collection/TraversableViewLike;
	invokeinterface	InterfaceMethod scala/collection/TraversableViewLike.stringPrefix:()Ljava/lang/String;
	invokevirtual	Method scala/collection/mutable/StringBuilder.append:(Ljava/lang/Object;)Lscala/collection/mutable/StringBuilder;
	ldc	String D
	invokevirtual	Method scala/collection/mutable/StringBuilder.append:(Ljava/lang/Object;)Lscala/collection/mutable/StringBuilder;
	invokevirtual	Method scala/collection/mutable/StringBuilder.toString:()Ljava/lang/String;
	areturn
  Labels:
  LocalVariableTable: 
   Start  Length  Slot  Name   Signature
   0      30      0    $this       Lscala/collection/TraversableViewLike$DroppedWhile;


public static void foreach(scala.collection.TraversableViewLike$DroppedWhile, scala.Function1);
  Signature: (Lscala/collection/TraversableViewLike$DroppedWhile;Lscala/Function1;)V
  Code:
   Stack=6, Locals=3, Args_size=2
	new	class scala/runtime/BooleanRef
	dup
	iconst_0
	invokespecial	Method scala/runtime/BooleanRef."<init>":(Z)V
	astore_2
	aload_0
	invokeinterface	InterfaceMethod scala/collection/TraversableViewLike$DroppedWhile.scala$collection$TraversableViewLike$DroppedWhile$$$outer:()Lscala/collection/TraversableViewLike;
	new	class scala/collection/TraversableViewLike$DroppedWhile$$anonfun$foreach$8
	dup
	aload_0
	aload_1
	aload_2
	invokespecial	Method scala/collection/TraversableViewLike$DroppedWhile$$anonfun$foreach$8."<init>":(Lscala/collection/TraversableViewLike$DroppedWhile;Lscala/Function1;Lscala/runtime/BooleanRef;)V
	invokeinterface	InterfaceMethod scala/collection/generic/GenericTraversableTemplate.foreach:(Lscala/Function1;)V
	return
  Labels:
  LocalVariableTable: 
   Start  Length  Slot  Name   Signature
   0      31      0    $this       Lscala/collection/TraversableViewLike$DroppedWhile;
   0      31      1    f$9       Lscala/Function1;
   9      21      2    go$1       Lscala/runtime/BooleanRef;


}

