Compiled from "Traversable.scala"
public class scala.collection.Traversable$ComparableTraversableOps extends java.lang.Object implements scala.ScalaObject
  SourceFile: "Traversable.scala"
  Signature: length = 0x2
   00 56 
  Scala: length = 0x
   
  InnerClass: 
   public #91= #14 of #90; //ComparableTraversableOps=class scala/collection/Traversable$ComparableTraversableOps of class scala/collection/Traversable
   public final #92= #44 of #14; //$anonfun$max$1=class scala/collection/Traversable$ComparableTraversableOps$$anonfun$max$1 of class scala/collection/Traversable$ComparableTraversableOps
   public final #93= #80 of #14; //$anonfun$min$1=class scala/collection/Traversable$ComparableTraversableOps$$anonfun$min$1 of class scala/collection/Traversable$ComparableTraversableOps
   public final #94= #61 of #14; //$anonfun$max$2=class scala/collection/Traversable$ComparableTraversableOps$$anonfun$max$2 of class scala/collection/Traversable$ComparableTraversableOps
   public final #95= #83 of #14; //$anonfun$min$2=class scala/collection/Traversable$ComparableTraversableOps$$anonfun$min$2 of class scala/collection/Traversable$ComparableTraversableOps
  minor version: 0
  major version: 49
  Constant pool:
const #1 = Asciz	SourceFile;
const #2 = Asciz	Traversable.scala;
const #3 = Asciz	scala$collection$Traversable$ComparableTraversableOps$$cmp;
const #4 = Asciz	Lscala/Ordering;;
const #5 = Asciz	self;
const #6 = Asciz	Lscala/collection/Traversable;;
const #7 = Asciz	Lscala/collection/Traversable<TA;>;;
const #8 = Asciz	Signature;
const #9 = Asciz	<init>;
const #10 = Asciz	(Lscala/collection/Traversable;Lscala/Ordering;)V;
const #11 = Asciz	Code;
const #12 = Asciz	LineNumberTable;
const #13 = Asciz	scala/collection/Traversable$ComparableTraversableOps;
const #14 = class	#13;	//  scala/collection/Traversable$ComparableTraversableOps
const #15 = NameAndType	#5:#6;//  self:Lscala/collection/Traversable;
const #16 = Field	#14.#15;	//  scala/collection/Traversable$ComparableTraversableOps.self:Lscala/collection/Traversable;
const #17 = NameAndType	#3:#4;//  scala$collection$Traversable$ComparableTraversableOps$$cmp:Lscala/Ordering;
const #18 = Field	#14.#17;	//  scala/collection/Traversable$ComparableTraversableOps.scala$collection$Traversable$ComparableTraversableOps$$cmp:Lscala/Ordering;
const #19 = Asciz	java/lang/Object;
const #20 = class	#19;	//  java/lang/Object
const #21 = Asciz	()V;
const #22 = NameAndType	#9:#21;//  "<init>":()V
const #23 = Method	#20.#22;	//  java/lang/Object."<init>":()V
const #24 = Asciz	this;
const #25 = Asciz	Lscala/collection/Traversable$ComparableTraversableOps;;
const #26 = Asciz	cmp;
const #27 = Asciz	LocalVariableTable;
const #28 = Asciz	(Lscala/collection/Traversable<TA;>;Lscala/Ordering<TA;>;)V;
const #29 = Asciz	max;
const #30 = Asciz	()Ljava/lang/Object;;
const #31 = Asciz	scala/Predef$;
const #32 = class	#31;	//  scala/Predef$
const #33 = Asciz	MODULE$;
const #34 = Asciz	Lscala/Predef$;;
const #35 = NameAndType	#33:#34;//  MODULE$:Lscala/Predef$;
const #36 = Field	#32.#35;	//  scala/Predef$.MODULE$:Lscala/Predef$;
const #37 = Asciz	scala/collection/generic/TraversableTemplate;
const #38 = class	#37;	//  scala/collection/generic/TraversableTemplate
const #39 = Asciz	isEmpty;
const #40 = Asciz	()Z;
const #41 = NameAndType	#39:#40;//  isEmpty:()Z
const #42 = InterfaceMethod	#38.#41;	//  scala/collection/generic/TraversableTemplate.isEmpty:()Z
const #43 = Asciz	scala/collection/Traversable$ComparableTraversableOps$$anonfun$max$1;
const #44 = class	#43;	//  scala/collection/Traversable$ComparableTraversableOps$$anonfun$max$1
const #45 = Asciz	(Lscala/collection/Traversable$ComparableTraversableOps;)V;
const #46 = NameAndType	#9:#45;//  "<init>":(Lscala/collection/Traversable$ComparableTraversableOps;)V
const #47 = Method	#44.#46;	//  scala/collection/Traversable$ComparableTraversableOps$$anonfun$max$1."<init>":(Lscala/collection/Traversable$ComparableTraversableOps;)V
const #48 = Asciz	require;
const #49 = Asciz	(ZLscala/Function0;)V;
const #50 = NameAndType	#48:#49;//  require:(ZLscala/Function0;)V
const #51 = Method	#32.#50;	//  scala/Predef$.require:(ZLscala/Function0;)V
const #52 = Asciz	scala/runtime/ObjectRef;
const #53 = class	#52;	//  scala/runtime/ObjectRef
const #54 = Asciz	head;
const #55 = NameAndType	#54:#30;//  head:()Ljava/lang/Object;
const #56 = InterfaceMethod	#38.#55;	//  scala/collection/generic/TraversableTemplate.head:()Ljava/lang/Object;
const #57 = Asciz	(Ljava/lang/Object;)V;
const #58 = NameAndType	#9:#57;//  "<init>":(Ljava/lang/Object;)V
const #59 = Method	#53.#58;	//  scala/runtime/ObjectRef."<init>":(Ljava/lang/Object;)V
const #60 = Asciz	scala/collection/Traversable$ComparableTraversableOps$$anonfun$max$2;
const #61 = class	#60;	//  scala/collection/Traversable$ComparableTraversableOps$$anonfun$max$2
const #62 = Asciz	(Lscala/collection/Traversable$ComparableTraversableOps;Lscala/runtime/ObjectRef;)V;
const #63 = NameAndType	#9:#62;//  "<init>":(Lscala/collection/Traversable$ComparableTraversableOps;Lscala/runtime/ObjectRef;)V
const #64 = Method	#61.#63;	//  scala/collection/Traversable$ComparableTraversableOps$$anonfun$max$2."<init>":(Lscala/collection/Traversable$ComparableTraversableOps;Lscala/runtime/ObjectRef;)V
const #65 = Asciz	scala/collection/generic/TraversableClass;
const #66 = class	#65;	//  scala/collection/generic/TraversableClass
const #67 = Asciz	foreach;
const #68 = Asciz	(Lscala/Function1;)V;
const #69 = NameAndType	#67:#68;//  foreach:(Lscala/Function1;)V
const #70 = InterfaceMethod	#66.#69;	//  scala/collection/generic/TraversableClass.foreach:(Lscala/Function1;)V
const #71 = Asciz	elem;
const #72 = Asciz	Ljava/lang/Object;;
const #73 = NameAndType	#71:#72;//  elem:Ljava/lang/Object;
const #74 = Field	#53.#73;	//  scala/runtime/ObjectRef.elem:Ljava/lang/Object;
const #75 = Asciz	acc$2;
const #76 = Asciz	Lscala/runtime/ObjectRef;;
const #77 = Asciz	()TA;;
const #78 = Asciz	min;
const #79 = Asciz	scala/collection/Traversable$ComparableTraversableOps$$anonfun$min$1;
const #80 = class	#79;	//  scala/collection/Traversable$ComparableTraversableOps$$anonfun$min$1
const #81 = Method	#80.#46;	//  scala/collection/Traversable$ComparableTraversableOps$$anonfun$min$1."<init>":(Lscala/collection/Traversable$ComparableTraversableOps;)V
const #82 = Asciz	scala/collection/Traversable$ComparableTraversableOps$$anonfun$min$2;
const #83 = class	#82;	//  scala/collection/Traversable$ComparableTraversableOps$$anonfun$min$2
const #84 = Method	#83.#63;	//  scala/collection/Traversable$ComparableTraversableOps$$anonfun$min$2."<init>":(Lscala/collection/Traversable$ComparableTraversableOps;Lscala/runtime/ObjectRef;)V
const #85 = Asciz	acc$1;
const #86 = Asciz	<A:Ljava/lang/Object;>Ljava/lang/Object;Lscala/ScalaObject;;
const #87 = Asciz	Scala;
const #88 = Asciz	InnerClasses;
const #89 = Asciz	scala/collection/Traversable;
const #90 = class	#89;	//  scala/collection/Traversable
const #91 = Asciz	ComparableTraversableOps;
const #92 = Asciz	$anonfun$max$1;
const #93 = Asciz	$anonfun$min$1;
const #94 = Asciz	$anonfun$max$2;
const #95 = Asciz	$anonfun$min$2;
const #96 = Asciz	scala/ScalaObject;
const #97 = class	#96;	//  scala/ScalaObject

{
public final scala.Ordering scala$collection$Traversable$ComparableTraversableOps$$cmp;

public scala.collection.Traversable$ComparableTraversableOps(scala.collection.Traversable, scala.Ordering);
  Code:
   Stack=2, Locals=3, Args_size=3
   0:	aload_0
   1:	aload_1
   2:	putfield	#16; //Field self:Lscala/collection/Traversable;
   5:	aload_0
   6:	aload_2
   7:	putfield	#18; //Field scala$collection$Traversable$ComparableTraversableOps$$cmp:Lscala/Ordering;
   10:	aload_0
   11:	invokespecial	#23; //Method java/lang/Object."<init>":()V
   14:	return
  LineNumberTable: 
   line 108: 0

  LocalVariableTable: 
   Start  Length  Slot  Name   Signature
   0      15      0    this       Lscala/collection/Traversable$ComparableTraversableOps;
   0      15      1    self       Lscala/collection/Traversable;
   0      15      2    cmp       Lscala/Ordering;

  Signature: length = 0x2
   00 1C 

public java.lang.Object max();
  Code:
   Stack=5, Locals=2, Args_size=1
   0:	getstatic	#36; //Field scala/Predef$.MODULE$:Lscala/Predef$;
   3:	aload_0
   4:	getfield	#16; //Field self:Lscala/collection/Traversable;
   7:	invokeinterface	#42,  1; //InterfaceMethod scala/collection/generic/TraversableTemplate.isEmpty:()Z
   12:	ifeq	19
   15:	iconst_0
   16:	goto	20
   19:	iconst_1
   20:	new	#44; //class scala/collection/Traversable$ComparableTraversableOps$$anonfun$max$1
   23:	dup
   24:	aload_0
   25:	invokespecial	#47; //Method scala/collection/Traversable$ComparableTraversableOps$$anonfun$max$1."<init>":(Lscala/collection/Traversable$ComparableTraversableOps;)V
   28:	invokevirtual	#51; //Method scala/Predef$.require:(ZLscala/Function0;)V
   31:	new	#53; //class scala/runtime/ObjectRef
   34:	dup
   35:	aload_0
   36:	getfield	#16; //Field self:Lscala/collection/Traversable;
   39:	invokeinterface	#56,  1; //InterfaceMethod scala/collection/generic/TraversableTemplate.head:()Ljava/lang/Object;
   44:	invokespecial	#59; //Method scala/runtime/ObjectRef."<init>":(Ljava/lang/Object;)V
   47:	astore_1
   48:	aload_0
   49:	getfield	#16; //Field self:Lscala/collection/Traversable;
   52:	new	#61; //class scala/collection/Traversable$ComparableTraversableOps$$anonfun$max$2
   55:	dup
   56:	aload_0
   57:	aload_1
   58:	invokespecial	#64; //Method scala/collection/Traversable$ComparableTraversableOps$$anonfun$max$2."<init>":(Lscala/collection/Traversable$ComparableTraversableOps;Lscala/runtime/ObjectRef;)V
   61:	invokeinterface	#70,  2; //InterfaceMethod scala/collection/generic/TraversableClass.foreach:(Lscala/Function1;)V
   66:	aload_1
   67:	getfield	#74; //Field scala/runtime/ObjectRef.elem:Ljava/lang/Object;
   70:	areturn
  LineNumberTable: 
   line 121: 0
   line 122: 31
   line 123: 48
   line 125: 66

  LocalVariableTable: 
   Start  Length  Slot  Name   Signature
   0      71      0    this       Lscala/collection/Traversable$ComparableTraversableOps;
   48      22      1    acc$2       Lscala/runtime/ObjectRef;

  Signature: length = 0x2
   00 4D 

public java.lang.Object min();
  Code:
   Stack=5, Locals=2, Args_size=1
   0:	getstatic	#36; //Field scala/Predef$.MODULE$:Lscala/Predef$;
   3:	aload_0
   4:	getfield	#16; //Field self:Lscala/collection/Traversable;
   7:	invokeinterface	#42,  1; //InterfaceMethod scala/collection/generic/TraversableTemplate.isEmpty:()Z
   12:	ifeq	19
   15:	iconst_0
   16:	goto	20
   19:	iconst_1
   20:	new	#80; //class scala/collection/Traversable$ComparableTraversableOps$$anonfun$min$1
   23:	dup
   24:	aload_0
   25:	invokespecial	#81; //Method scala/collection/Traversable$ComparableTraversableOps$$anonfun$min$1."<init>":(Lscala/collection/Traversable$ComparableTraversableOps;)V
   28:	invokevirtual	#51; //Method scala/Predef$.require:(ZLscala/Function0;)V
   31:	new	#53; //class scala/runtime/ObjectRef
   34:	dup
   35:	aload_0
   36:	getfield	#16; //Field self:Lscala/collection/Traversable;
   39:	invokeinterface	#56,  1; //InterfaceMethod scala/collection/generic/TraversableTemplate.head:()Ljava/lang/Object;
   44:	invokespecial	#59; //Method scala/runtime/ObjectRef."<init>":(Ljava/lang/Object;)V
   47:	astore_1
   48:	aload_0
   49:	getfield	#16; //Field self:Lscala/collection/Traversable;
   52:	new	#83; //class scala/collection/Traversable$ComparableTraversableOps$$anonfun$min$2
   55:	dup
   56:	aload_0
   57:	aload_1
   58:	invokespecial	#84; //Method scala/collection/Traversable$ComparableTraversableOps$$anonfun$min$2."<init>":(Lscala/collection/Traversable$ComparableTraversableOps;Lscala/runtime/ObjectRef;)V
   61:	invokeinterface	#70,  2; //InterfaceMethod scala/collection/generic/TraversableClass.foreach:(Lscala/Function1;)V
   66:	aload_1
   67:	getfield	#74; //Field scala/runtime/ObjectRef.elem:Ljava/lang/Object;
   70:	areturn
  LineNumberTable: 
   line 112: 0
   line 113: 31
   line 114: 48
   line 116: 66

  LocalVariableTable: 
   Start  Length  Slot  Name   Signature
   0      71      0    this       Lscala/collection/Traversable$ComparableTraversableOps;
   48      22      1    acc$1       Lscala/runtime/ObjectRef;

  Signature: length = 0x2
   00 4D 

}

