Compiled from "TraversableLike.scala"
public final class scala.collection.TraversableLike$WithFilter$$anonfun$map$2 extends java.lang.Object implements scala.Function1,scala.ScalaObject,java.io.Serializable
  SourceFile: "TraversableLike.scala"
  Scala: length = 0x
   
  InnerClass: 
   public WithFilter=class scala/collection/TraversableLike$WithFilter of class scala/collection/TraversableLike
   public final $anonfun$map$2=class scala/collection/TraversableLike$WithFilter$$anonfun$map$2 of class scala/collection/TraversableLike$WithFilter
  minor version: 0
  major version: 49
  Constant pool:
Asciz	SourceFile;
Asciz	TraversableLike.scala;
Asciz	<clinit>;
Asciz	()V;
Asciz	Code;
Asciz	serialVersionUID;
Asciz	J;
Asciz	scala/collection/TraversableLike$WithFilter$$anonfun$map$2;
class	scala/collection/TraversableLike$WithFilter$$anonfun$map$2
NameAndType	serialVersionUID:J
Field	scala/collection/TraversableLike$WithFilter$$anonfun$map$2.serialVersionUID:J
Asciz	b$12;
Asciz	Lscala/collection/mutable/Builder;;
Asciz	f$5;
Asciz	Lscala/Function1;;
Asciz	$outer;
Asciz	Lscala/collection/TraversableLike$WithFilter;;
Asciz	<init>;
Asciz	(Lscala/collection/TraversableLike$WithFilter;Lscala/Function1;Lscala/collection/mutable/Builder;)V;
Asciz	LineNumberTable;
Asciz	java/lang/NullPointerException;
class	java/lang/NullPointerException
NameAndType	"<init>":()V
Method	java/lang/NullPointerException."<init>":()V
NameAndType	$outer:Lscala/collection/TraversableLike$WithFilter;
Field	scala/collection/TraversableLike$WithFilter$$anonfun$map$2.$outer:Lscala/collection/TraversableLike$WithFilter;
NameAndType	f$5:Lscala/Function1;
Field	scala/collection/TraversableLike$WithFilter$$anonfun$map$2.f$5:Lscala/Function1;
NameAndType	b$12:Lscala/collection/mutable/Builder;
Field	scala/collection/TraversableLike$WithFilter$$anonfun$map$2.b$12:Lscala/collection/mutable/Builder;
Asciz	java/lang/Object;
class	java/lang/Object
Method	java/lang/Object."<init>":()V
Asciz	scala/Function1$class;
class	scala/Function1$class
Asciz	$init$;
Asciz	(Lscala/Function1;)V;
NameAndType	$init$:(Lscala/Function1;)V
Method	scala/Function1$class.$init$:(Lscala/Function1;)V
Asciz	this;
Asciz	Lscala/collection/TraversableLike$WithFilter$$anonfun$map$2;;
Asciz	LocalVariableTable;
Asciz	(Lscala/collection/TraversableLike<TA;TRepr;>.WithFilter;)V;
Asciz	Signature;
Asciz	apply;
Asciz	(Ljava/lang/Object;)Ljava/lang/Object;;
Asciz	scala/collection/TraversableLike$WithFilter;
class	scala/collection/TraversableLike$WithFilter
Asciz	scala$collection$TraversableLike$WithFilter$$p;
NameAndType	scala$collection$TraversableLike$WithFilter$$p:Lscala/Function1;
Field	scala/collection/TraversableLike$WithFilter.scala$collection$TraversableLike$WithFilter$$p:Lscala/Function1;
Asciz	scala/Function1;
class	scala/Function1
NameAndType	apply:(Ljava/lang/Object;)Ljava/lang/Object;
InterfaceMethod	scala/Function1.apply:(Ljava/lang/Object;)Ljava/lang/Object;
Asciz	scala/runtime/BoxesRunTime;
class	scala/runtime/BoxesRunTime
Asciz	unboxToBoolean;
Asciz	(Ljava/lang/Object;)Z;
NameAndType	unboxToBoolean:(Ljava/lang/Object;)Z
Method	scala/runtime/BoxesRunTime.unboxToBoolean:(Ljava/lang/Object;)Z
Asciz	scala/collection/mutable/Builder;
class	scala/collection/mutable/Builder
Asciz	$plus$eq;
Asciz	(Ljava/lang/Object;)Lscala/collection/mutable/Builder;;
NameAndType	$plus$eq:(Ljava/lang/Object;)Lscala/collection/mutable/Builder;
InterfaceMethod	scala/collection/mutable/Builder.$plus$eq:(Ljava/lang/Object;)Lscala/collection/mutable/Builder;
Asciz	scala/runtime/BoxedUnit;
class	scala/runtime/BoxedUnit
Asciz	UNIT;
Asciz	Lscala/runtime/BoxedUnit;;
NameAndType	UNIT:Lscala/runtime/BoxedUnit;
Field	scala/runtime/BoxedUnit.UNIT:Lscala/runtime/BoxedUnit;
Asciz	x;
Asciz	Ljava/lang/Object;;
Asciz	(TA;)Ljava/lang/Object;;
Asciz	andThen;
Asciz	(Lscala/Function1;)Lscala/Function1;;
Asciz	(Lscala/Function1;Lscala/Function1;)Lscala/Function1;;
NameAndType	andThen:(Lscala/Function1;Lscala/Function1;)Lscala/Function1;
Method	scala/Function1$class.andThen:(Lscala/Function1;Lscala/Function1;)Lscala/Function1;
Asciz	g;
Asciz	compose;
NameAndType	compose:(Lscala/Function1;Lscala/Function1;)Lscala/Function1;
Method	scala/Function1$class.compose:(Lscala/Function1;Lscala/Function1;)Lscala/Function1;
Asciz	toString;
Asciz	()Ljava/lang/String;;
Asciz	(Lscala/Function1;)Ljava/lang/String;;
NameAndType	toString:(Lscala/Function1;)Ljava/lang/String;
Method	scala/Function1$class.toString:(Lscala/Function1;)Ljava/lang/String;
Asciz	Scala;
Asciz	InnerClasses;
Asciz	scala/collection/TraversableLike;
class	scala/collection/TraversableLike
Asciz	WithFilter;
Asciz	$anonfun$map$2;
Asciz	scala/ScalaObject;
class	scala/ScalaObject
Asciz	java/io/Serializable;
class	java/io/Serializable

{
public static final long serialVersionUID;
  Signature: J

private final scala.collection.mutable.Builder b$12;
  Signature: Lscala/collection/mutable/Builder;

private final scala.Function1 f$5;
  Signature: Lscala/Function1;

private final scala.collection.TraversableLike$WithFilter $outer;
  Signature: Lscala/collection/TraversableLike$WithFilter;

public static {};
  Signature: ()V
  Code:
   Stack=2, Locals=0, Args_size=0
	lconst_0
	putstatic	Field serialVersionUID:J
	return
  Labels:

public scala.collection.TraversableLike$WithFilter$$anonfun$map$2(scala.collection.TraversableLike$WithFilter, scala.Function1, scala.collection.mutable.Builder);
  Signature: (Lscala/collection/TraversableLike$WithFilter;Lscala/Function1;Lscala/collection/mutable/Builder;)V
  Code:
   Stack=2, Locals=4, Args_size=4
	aload_1
	ifnonnull	l1 // aload_0
	new	class java/lang/NullPointerException
	dup
	invokespecial	Method java/lang/NullPointerException."<init>":()V
	athrow
l1	aload_0
	aload_1
	putfield	Field $outer:Lscala/collection/TraversableLike$WithFilter;
	aload_0
	aload_2
	putfield	Field f$5:Lscala/Function1;
	aload_0
	aload_3
	putfield	Field b$12:Lscala/collection/mutable/Builder;
	aload_0
	invokespecial	Method java/lang/Object."<init>":()V
	aload_0
	invokestatic	Method scala/Function1$class.$init$:(Lscala/Function1;)V
	return
  Labels:
   	l1 = 12 // aload_0
  LocalVariableTable: 
   Start  Length  Slot  Name   Signature
   0      36      0    this       Lscala/collection/TraversableLike$WithFilter$$anonfun$map$2;
   0      36      1    $outer       Lscala/collection/TraversableLike$WithFilter;

  Signature: length = 0x2
   00 2B 

public final java.lang.Object apply(java.lang.Object);
  Signature: (Ljava/lang/Object;)Ljava/lang/Object;
  Code:
   Stack=3, Locals=3, Args_size=2
	aload_0
	getfield	Field $outer:Lscala/collection/TraversableLike$WithFilter;
	astore_2
	aload_0
	getfield	Field $outer:Lscala/collection/TraversableLike$WithFilter;
	getfield	Field scala/collection/TraversableLike$WithFilter.scala$collection$TraversableLike$WithFilter$$p:Lscala/Function1;
	aload_1
	invokeinterface	InterfaceMethod scala/Function1.apply:(Ljava/lang/Object;)Ljava/lang/Object;
	invokestatic	Method scala/runtime/BoxesRunTime.unboxToBoolean:(Ljava/lang/Object;)Z
	ifeq	l1 // getstatic
	aload_0
	getfield	Field b$12:Lscala/collection/mutable/Builder;
	aload_0
	getfield	Field f$5:Lscala/Function1;
	aload_1
	invokeinterface	InterfaceMethod scala/Function1.apply:(Ljava/lang/Object;)Ljava/lang/Object;
	invokeinterface	InterfaceMethod scala/collection/mutable/Builder.$plus$eq:(Ljava/lang/Object;)Lscala/collection/mutable/Builder;
	goto	l2 // areturn
l1	getstatic	Field scala/runtime/BoxedUnit.UNIT:Lscala/runtime/BoxedUnit;
l2	areturn
  Labels:
   	l1 = 46 // getstatic
   	l2 = 49 // areturn
  LocalVariableTable: 
   Start  Length  Slot  Name   Signature
   0      50      0    this       Lscala/collection/TraversableLike$WithFilter$$anonfun$map$2;
   5      45      1    x       Ljava/lang/Object;

  Signature: length = 0x2
   00 4C 

public scala.Function1 andThen(scala.Function1);
  Signature: (Lscala/Function1;)Lscala/Function1;
  Code:
   Stack=2, Locals=2, Args_size=2
	aload_0
	aload_1
	invokestatic	Method scala/Function1$class.andThen:(Lscala/Function1;Lscala/Function1;)Lscala/Function1;
	areturn
  Labels:
  LocalVariableTable: 
   Start  Length  Slot  Name   Signature
   0      6      0    this       Lscala/collection/TraversableLike$WithFilter$$anonfun$map$2;
   0      6      1    g       Lscala/Function1;


public scala.Function1 compose(scala.Function1);
  Signature: (Lscala/Function1;)Lscala/Function1;
  Code:
   Stack=2, Locals=2, Args_size=2
	aload_0
	aload_1
	invokestatic	Method scala/Function1$class.compose:(Lscala/Function1;Lscala/Function1;)Lscala/Function1;
	areturn
  Labels:
  LocalVariableTable: 
   Start  Length  Slot  Name   Signature
   0      6      0    this       Lscala/collection/TraversableLike$WithFilter$$anonfun$map$2;
   0      6      1    g       Lscala/Function1;


public java.lang.String toString();
  Signature: ()Ljava/lang/String;
  Code:
   Stack=1, Locals=1, Args_size=1
	aload_0
	invokestatic	Method scala/Function1$class.toString:(Lscala/Function1;)Ljava/lang/String;
	areturn
  Labels:

}

