Compiled from "TraversableLike.scala"
public abstract class scala.collection.TraversableLike$class extends java.lang.Object
  SourceFile: "TraversableLike.scala"
  Scala: length = 0x
   
  InnerClass: 
   public final #722= #38 of #23; //$anon$1=class scala/collection/TraversableLike$$anon$1 of class scala/collection/TraversableLike
   public final #723= #445 of #23; //$anonfun$1=class scala/collection/TraversableLike$$anonfun$1 of class scala/collection/TraversableLike
   public #724= #13 of #23; //WithFilter=class scala/collection/TraversableLike$WithFilter of class scala/collection/TraversableLike
   public final #725= #687 of #23; //$anonfun$map$1=class scala/collection/TraversableLike$$anonfun$map$1 of class scala/collection/TraversableLike
   public final #726= #494 of #23; //$anonfun$sum$1=class scala/collection/TraversableLike$$anonfun$sum$1 of class scala/collection/TraversableLike
   public final #727= #468 of #23; //$anonfun$min$2=class scala/collection/TraversableLike$$anonfun$min$2 of class scala/collection/TraversableLike
   public final #728= #458 of #23; //$anonfun$max$2=class scala/collection/TraversableLike$$anonfun$max$2 of class scala/collection/TraversableLike
   public final #729= #703 of #23; //$anonfun$size$1=class scala/collection/TraversableLike$$anonfun$size$1 of class scala/collection/TraversableLike
   public final #730= #571 of #23; //$anonfun$find$1=class scala/collection/TraversableLike$$anonfun$find$1 of class scala/collection/TraversableLike
   public final #731= #448 of #23; //$anonfun$head$1=class scala/collection/TraversableLike$$anonfun$head$1 of class scala/collection/TraversableLike
   public final #732= #423 of #23; //$anonfun$last$1=class scala/collection/TraversableLike$$anonfun$last$1 of class scala/collection/TraversableLike
   public final #733= #401 of #23; //$anonfun$init$1=class scala/collection/TraversableLike$$anonfun$init$1 of class scala/collection/TraversableLike
   public final #734= #375 of #23; //$anonfun$take$1=class scala/collection/TraversableLike$$anonfun$take$1 of class scala/collection/TraversableLike
   public final #735= #366 of #23; //$anonfun$drop$1=class scala/collection/TraversableLike$$anonfun$drop$1 of class scala/collection/TraversableLike
   public final #736= #327 of #23; //$anonfun$span$1=class scala/collection/TraversableLike$$anonfun$span$1 of class scala/collection/TraversableLike
   public final #737= #582 of #23; //$anonfun$count$1=class scala/collection/TraversableLike$$anonfun$count$1 of class scala/collection/TraversableLike
   public final #738= #355 of #23; //$anonfun$slice$1=class scala/collection/TraversableLike$$anonfun$slice$1 of class scala/collection/TraversableLike
   public final #739= #674 of #23; //$anonfun$filter$1=class scala/collection/TraversableLike$$anonfun$filter$1 of class scala/collection/TraversableLike
   public final #740= #603 of #23; //$anonfun$forall$1=class scala/collection/TraversableLike$$anonfun$forall$1 of class scala/collection/TraversableLike
   public final #741= #593 of #23; //$anonfun$exists$1=class scala/collection/TraversableLike$$anonfun$exists$1 of class scala/collection/TraversableLike
   public final #742= #710 of #23; //$anonfun$isEmpty$1=class scala/collection/TraversableLike$$anonfun$isEmpty$1 of class scala/collection/TraversableLike
   public final #743= #681 of #23; //$anonfun$flatMap$1=class scala/collection/TraversableLike$$anonfun$flatMap$1 of class scala/collection/TraversableLike
   public final #744= #629 of #23; //$anonfun$groupBy$2=class scala/collection/TraversableLike$$anonfun$groupBy$2 of class scala/collection/TraversableLike
   public final #745= #624 of #23; //$anonfun$groupBy$1=class scala/collection/TraversableLike$$anonfun$groupBy$1 of class scala/collection/TraversableLike
   public final #746= #482 of #23; //$anonfun$product$1=class scala/collection/TraversableLike$$anonfun$product$1 of class scala/collection/TraversableLike
   public final #747= #306 of #23; //$anonfun$splitAt$1=class scala/collection/TraversableLike$$anonfun$splitAt$1 of class scala/collection/TraversableLike
   public final #748= #562 of #23; //$anonfun$foldLeft$1=class scala/collection/TraversableLike$$anonfun$foldLeft$1 of class scala/collection/TraversableLike
   public final #749= #667 of #23; //$anonfun$filterNot$1=class scala/collection/TraversableLike$$anonfun$filterNot$1 of class scala/collection/TraversableLike
   public final #750= #641 of #23; //$anonfun$partition$1=class scala/collection/TraversableLike$$anonfun$partition$1 of class scala/collection/TraversableLike
   public final #751= #552 of #23; //$anonfun$foldRight$2=class scala/collection/TraversableLike$$anonfun$foldRight$2 of class scala/collection/TraversableLike
   public final #752= #549 of #23; //$anonfun$foldRight$1=class scala/collection/TraversableLike$$anonfun$foldRight$1 of class scala/collection/TraversableLike
   public final #753= #347 of #23; //$anonfun$takeWhile$1=class scala/collection/TraversableLike$$anonfun$takeWhile$1 of class scala/collection/TraversableLike
   public final #754= #338 of #23; //$anonfun$dropWhile$1=class scala/collection/TraversableLike$$anonfun$dropWhile$1 of class scala/collection/TraversableLike
   public final #755= #128 of #23; //$anonfun$addString$1=class scala/collection/TraversableLike$$anonfun$addString$1 of class scala/collection/TraversableLike
   public final #756= #656 of #23; //$anonfun$partialMap$1=class scala/collection/TraversableLike$$anonfun$partialMap$1 of class scala/collection/TraversableLike
   public final #757= #534 of #23; //$anonfun$reduceLeft$1=class scala/collection/TraversableLike$$anonfun$reduceLeft$1 of class scala/collection/TraversableLike
   public final #758= #518 of #23; //$anonfun$reduceRight$2=class scala/collection/TraversableLike$$anonfun$reduceRight$2 of class scala/collection/TraversableLike
   public final #759= #515 of #23; //$anonfun$reduceRight$1=class scala/collection/TraversableLike$$anonfun$reduceRight$1 of class scala/collection/TraversableLike
   public final #760= #276 of #23; //$anonfun$copyToArray$1=class scala/collection/TraversableLike$$anonfun$copyToArray$1 of class scala/collection/TraversableLike
   public final #761= #294 of #23; //$anonfun$copyToBuffer$1=class scala/collection/TraversableLike$$anonfun$copyToBuffer$1 of class scala/collection/TraversableLike
  minor version: 0
  major version: 49
  Constant pool:
const #1 = Asciz	SourceFile;
const #2 = Asciz	TraversableLike.scala;
const #3 = Asciz	$init$;
const #4 = Asciz	(Lscala/collection/TraversableLike;)V;
const #5 = Asciz	Code;
const #6 = Asciz	LineNumberTable;
const #7 = Asciz	$this;
const #8 = Asciz	Lscala/collection/TraversableLike;;
const #9 = Asciz	LocalVariableTable;
const #10 = Asciz	withFilter;
const #11 = Asciz	(Lscala/collection/TraversableLike;Lscala/Function1;)Lscala/collection/TraversableLike$WithFilter;;
const #12 = Asciz	scala/collection/TraversableLike$WithFilter;
const #13 = class	#12;	//  scala/collection/TraversableLike$WithFilter
const #14 = Asciz	<init>;
const #15 = Asciz	(Lscala/collection/TraversableLike;Lscala/Function1;)V;
const #16 = NameAndType	#14:#15;//  "<init>":(Lscala/collection/TraversableLike;Lscala/Function1;)V
const #17 = Method	#13.#16;	//  scala/collection/TraversableLike$WithFilter."<init>":(Lscala/collection/TraversableLike;Lscala/Function1;)V
const #18 = Asciz	p;
const #19 = Asciz	Lscala/Function1;;
const #20 = Asciz	view;
const #21 = Asciz	(Lscala/collection/TraversableLike;II)Lscala/collection/TraversableView;;
const #22 = Asciz	scala/collection/TraversableLike;
const #23 = class	#22;	//  scala/collection/TraversableLike
const #24 = Asciz	()Ljava/lang/Object;;
const #25 = NameAndType	#20:#24;//  view:()Ljava/lang/Object;
const #26 = InterfaceMethod	#23.#25;	//  scala/collection/TraversableLike.view:()Ljava/lang/Object;
const #27 = Asciz	scala/collection/TraversableViewLike;
const #28 = class	#27;	//  scala/collection/TraversableViewLike
const #29 = Asciz	slice;
const #30 = Asciz	(II)Lscala/collection/TraversableView;;
const #31 = NameAndType	#29:#30;//  slice:(II)Lscala/collection/TraversableView;
const #32 = InterfaceMethod	#28.#31;	//  scala/collection/TraversableViewLike.slice:(II)Lscala/collection/TraversableView;
const #33 = Asciz	from;
const #34 = Asciz	I;
const #35 = Asciz	until;
const #36 = Asciz	(Lscala/collection/TraversableLike;)Ljava/lang/Object;;
const #37 = Asciz	scala/collection/TraversableLike$$anon$1;
const #38 = class	#37;	//  scala/collection/TraversableLike$$anon$1
const #39 = NameAndType	#14:#4;//  "<init>":(Lscala/collection/TraversableLike;)V
const #40 = Method	#38.#39;	//  scala/collection/TraversableLike$$anon$1."<init>":(Lscala/collection/TraversableLike;)V
const #41 = Asciz	stringPrefix;
const #42 = Asciz	(Lscala/collection/TraversableLike;)Ljava/lang/String;;
const #43 = Asciz	repr;
const #44 = NameAndType	#43:#24;//  repr:()Ljava/lang/Object;
const #45 = InterfaceMethod	#23.#44;	//  scala/collection/TraversableLike.repr:()Ljava/lang/Object;
const #46 = Asciz	java/lang/Object;
const #47 = class	#46;	//  java/lang/Object
const #48 = Asciz	getClass;
const #49 = Asciz	()Ljava/lang/Class;;
const #50 = NameAndType	#48:#49;//  getClass:()Ljava/lang/Class;
const #51 = Method	#47.#50;	//  java/lang/Object.getClass:()Ljava/lang/Class;
const #52 = Asciz	java/lang/Class;
const #53 = class	#52;	//  java/lang/Class
const #54 = Asciz	getName;
const #55 = Asciz	()Ljava/lang/String;;
const #56 = NameAndType	#54:#55;//  getName:()Ljava/lang/String;
const #57 = Method	#53.#56;	//  java/lang/Class.getName:()Ljava/lang/String;
const #58 = int	46;
const #59 = Asciz	java/lang/String;
const #60 = class	#59;	//  java/lang/String
const #61 = Asciz	lastIndexOf;
const #62 = Asciz	(I)I;
const #63 = NameAndType	#61:#62;//  lastIndexOf:(I)I
const #64 = Method	#60.#63;	//  java/lang/String.lastIndexOf:(I)I
const #65 = Asciz	substring;
const #66 = Asciz	(I)Ljava/lang/String;;
const #67 = NameAndType	#65:#66;//  substring:(I)Ljava/lang/String;
const #68 = Method	#60.#67;	//  java/lang/String.substring:(I)Ljava/lang/String;
const #69 = int	36;
const #70 = Asciz	indexOf;
const #71 = NameAndType	#70:#62;//  indexOf:(I)I
const #72 = Method	#60.#71;	//  java/lang/String.indexOf:(I)I
const #73 = Asciz	(II)Ljava/lang/String;;
const #74 = NameAndType	#65:#73;//  substring:(II)Ljava/lang/String;
const #75 = Method	#60.#74;	//  java/lang/String.substring:(II)Ljava/lang/String;
const #76 = Asciz	string;
const #77 = Asciz	Ljava/lang/String;;
const #78 = Asciz	idx1;
const #79 = Asciz	idx2;
const #80 = Asciz	toString;
const #81 = Asciz	scala/collection/mutable/StringBuilder;
const #82 = class	#81;	//  scala/collection/mutable/StringBuilder
const #83 = Asciz	()V;
const #84 = NameAndType	#14:#83;//  "<init>":()V
const #85 = Method	#82.#84;	//  scala/collection/mutable/StringBuilder."<init>":()V
const #86 = NameAndType	#41:#55;//  stringPrefix:()Ljava/lang/String;
const #87 = InterfaceMethod	#23.#86;	//  scala/collection/TraversableLike.stringPrefix:()Ljava/lang/String;
const #88 = Asciz	append;
const #89 = Asciz	(Ljava/lang/Object;)Lscala/collection/mutable/StringBuilder;;
const #90 = NameAndType	#88:#89;//  append:(Ljava/lang/Object;)Lscala/collection/mutable/StringBuilder;
const #91 = Method	#82.#90;	//  scala/collection/mutable/StringBuilder.append:(Ljava/lang/Object;)Lscala/collection/mutable/StringBuilder;
const #92 = Asciz	(;
const #93 = String	#92;	//  (
const #94 = NameAndType	#80:#55;//  toString:()Ljava/lang/String;
const #95 = Method	#82.#94;	//  scala/collection/mutable/StringBuilder.toString:()Ljava/lang/String;
const #96 = Asciz	, ;
const #97 = String	#96;	//  , 
const #98 = Asciz	);
const #99 = String	#98;	//  )
const #100 = Asciz	mkString;
const #101 = Asciz	(Ljava/lang/String;Ljava/lang/String;Ljava/lang/String;)Ljava/lang/String;;
const #102 = NameAndType	#100:#101;//  mkString:(Ljava/lang/String;Ljava/lang/String;Ljava/lang/String;)Ljava/lang/String;
const #103 = InterfaceMethod	#23.#102;	//  scala/collection/TraversableLike.mkString:(Ljava/lang/String;Ljava/lang/String;Ljava/lang/String;)Ljava/lang/String;
const #104 = Asciz	addString;
const #105 = Asciz	(Lscala/collection/TraversableLike;Lscala/collection/mutable/StringBuilder;)Lscala/collection/mutable/StringBuilder;;
const #106 = Asciz	;
const #107 = String	#106;	//  
const #108 = Asciz	(Lscala/collection/mutable/StringBuilder;Ljava/lang/String;)Lscala/collection/mutable/StringBuilder;;
const #109 = NameAndType	#104:#108;//  addString:(Lscala/collection/mutable/StringBuilder;Ljava/lang/String;)Lscala/collection/mutable/StringBuilder;
const #110 = InterfaceMethod	#23.#109;	//  scala/collection/TraversableLike.addString:(Lscala/collection/mutable/StringBuilder;Ljava/lang/String;)Lscala/collection/mutable/StringBuilder;
const #111 = Asciz	b;
const #112 = Asciz	Lscala/collection/mutable/StringBuilder;;
const #113 = Asciz	(Lscala/collection/TraversableLike;Lscala/collection/mutable/StringBuilder;Ljava/lang/String;)Lscala/collection/mutable/StringBuilder;;
const #114 = Asciz	(Lscala/collection/mutable/StringBuilder;Ljava/lang/String;Ljava/lang/String;Ljava/lang/String;)Lscala/collection/mutable/StringBuilder;;
const #115 = NameAndType	#104:#114;//  addString:(Lscala/collection/mutable/StringBuilder;Ljava/lang/String;Ljava/lang/String;Ljava/lang/String;)Lscala/collection/mutable/StringBuilder;
const #116 = InterfaceMethod	#23.#115;	//  scala/collection/TraversableLike.addString:(Lscala/collection/mutable/StringBuilder;Ljava/lang/String;Ljava/lang/String;Ljava/lang/String;)Lscala/collection/mutable/StringBuilder;
const #117 = Asciz	sep;
const #118 = Asciz	(Lscala/collection/TraversableLike;Lscala/collection/mutable/StringBuilder;Ljava/lang/String;Ljava/lang/String;Ljava/lang/String;)Lscala/collection/mutable/StringBuilder;;
const #119 = Asciz	(Ljava/lang/String;)Lscala/collection/mutable/StringBuilder;;
const #120 = NameAndType	#88:#119;//  append:(Ljava/lang/String;)Lscala/collection/mutable/StringBuilder;
const #121 = Method	#82.#120;	//  scala/collection/mutable/StringBuilder.append:(Ljava/lang/String;)Lscala/collection/mutable/StringBuilder;
const #122 = Asciz	scala/runtime/BooleanRef;
const #123 = class	#122;	//  scala/runtime/BooleanRef
const #124 = Asciz	(Z)V;
const #125 = NameAndType	#14:#124;//  "<init>":(Z)V
const #126 = Method	#123.#125;	//  scala/runtime/BooleanRef."<init>":(Z)V
const #127 = Asciz	scala/collection/TraversableLike$$anonfun$addString$1;
const #128 = class	#127;	//  scala/collection/TraversableLike$$anonfun$addString$1
const #129 = Asciz	(Lscala/collection/TraversableLike;Lscala/collection/mutable/StringBuilder;Ljava/lang/String;Lscala/runtime/BooleanRef;)V;
const #130 = NameAndType	#14:#129;//  "<init>":(Lscala/collection/TraversableLike;Lscala/collection/mutable/StringBuilder;Ljava/lang/String;Lscala/runtime/BooleanRef;)V
const #131 = Method	#128.#130;	//  scala/collection/TraversableLike$$anonfun$addString$1."<init>":(Lscala/collection/TraversableLike;Lscala/collection/mutable/StringBuilder;Ljava/lang/String;Lscala/runtime/BooleanRef;)V
const #132 = Asciz	foreach;
const #133 = Asciz	(Lscala/Function1;)V;
const #134 = NameAndType	#132:#133;//  foreach:(Lscala/Function1;)V
const #135 = InterfaceMethod	#23.#134;	//  scala/collection/TraversableLike.foreach:(Lscala/Function1;)V
const #136 = Asciz	b$1;
const #137 = Asciz	start;
const #138 = Asciz	sep$1;
const #139 = Asciz	end;
const #140 = Asciz	first$2;
const #141 = Asciz	Lscala/runtime/BooleanRef;;
const #142 = Method	#82.#84;	//  scala/collection/mutable/StringBuilder."<init>":()V
const #143 = Asciz	(Lscala/collection/mutable/StringBuilder;)Lscala/collection/mutable/StringBuilder;;
const #144 = NameAndType	#104:#143;//  addString:(Lscala/collection/mutable/StringBuilder;)Lscala/collection/mutable/StringBuilder;
const #145 = InterfaceMethod	#23.#144;	//  scala/collection/TraversableLike.addString:(Lscala/collection/mutable/StringBuilder;)Lscala/collection/mutable/StringBuilder;
const #146 = Method	#82.#94;	//  scala/collection/mutable/StringBuilder.toString:()Ljava/lang/String;
const #147 = Asciz	(Lscala/collection/TraversableLike;Ljava/lang/String;)Ljava/lang/String;;
const #148 = Asciz	(Lscala/collection/TraversableLike;Ljava/lang/String;Ljava/lang/String;Ljava/lang/String;)Ljava/lang/String;;
const #149 = Asciz	toSet;
const #150 = Asciz	(Lscala/collection/TraversableLike;)Lscala/collection/immutable/Set;;
const #151 = Asciz	scala/collection/immutable/Set$;
const #152 = class	#151;	//  scala/collection/immutable/Set$
const #153 = Asciz	MODULE$;
const #154 = Asciz	Lscala/collection/immutable/Set$;;
const #155 = NameAndType	#153:#154;//  MODULE$:Lscala/collection/immutable/Set$;
const #156 = Field	#152.#155;	//  scala/collection/immutable/Set$.MODULE$:Lscala/collection/immutable/Set$;
const #157 = Asciz	scala/Predef$;
const #158 = class	#157;	//  scala/Predef$
const #159 = Asciz	Lscala/Predef$;;
const #160 = NameAndType	#153:#159;//  MODULE$:Lscala/Predef$;
const #161 = Field	#158.#160;	//  scala/Predef$.MODULE$:Lscala/Predef$;
const #162 = Asciz	genericWrapArray;
const #163 = Asciz	(Ljava/lang/Object;)Lscala/collection/mutable/WrappedArray;;
const #164 = NameAndType	#162:#163;//  genericWrapArray:(Ljava/lang/Object;)Lscala/collection/mutable/WrappedArray;
const #165 = Method	#158.#164;	//  scala/Predef$.genericWrapArray:(Ljava/lang/Object;)Lscala/collection/mutable/WrappedArray;
const #166 = Asciz	apply;
const #167 = Asciz	(Lscala/collection/Seq;)Lscala/collection/Traversable;;
const #168 = NameAndType	#166:#167;//  apply:(Lscala/collection/Seq;)Lscala/collection/Traversable;
const #169 = Method	#152.#168;	//  scala/collection/immutable/Set$.apply:(Lscala/collection/Seq;)Lscala/collection/Traversable;
const #170 = Asciz	scala/collection/generic/Addable;
const #171 = class	#170;	//  scala/collection/generic/Addable
const #172 = Asciz	thisCollection;
const #173 = Asciz	()Lscala/collection/Traversable;;
const #174 = NameAndType	#172:#173;//  thisCollection:()Lscala/collection/Traversable;
const #175 = InterfaceMethod	#23.#174;	//  scala/collection/TraversableLike.thisCollection:()Lscala/collection/Traversable;
const #176 = Asciz	$plus$plus;
const #177 = Asciz	(Lscala/collection/Traversable;)Lscala/collection/generic/Addable;;
const #178 = NameAndType	#176:#177;//  $plus$plus:(Lscala/collection/Traversable;)Lscala/collection/generic/Addable;
const #179 = InterfaceMethod	#171.#178;	//  scala/collection/generic/Addable.$plus$plus:(Lscala/collection/Traversable;)Lscala/collection/generic/Addable;
const #180 = Asciz	scala/collection/immutable/Set;
const #181 = class	#180;	//  scala/collection/immutable/Set
const #182 = Asciz	toStream;
const #183 = Asciz	(Lscala/collection/TraversableLike;)Lscala/collection/immutable/Stream;;
const #184 = Asciz	toList;
const #185 = Asciz	()Lscala/collection/immutable/List;;
const #186 = NameAndType	#184:#185;//  toList:()Lscala/collection/immutable/List;
const #187 = InterfaceMethod	#23.#186;	//  scala/collection/TraversableLike.toList:()Lscala/collection/immutable/List;
const #188 = Asciz	scala/collection/immutable/List;
const #189 = class	#188;	//  scala/collection/immutable/List
const #190 = Asciz	()Lscala/collection/immutable/Stream;;
const #191 = NameAndType	#182:#190;//  toStream:()Lscala/collection/immutable/Stream;
const #192 = Method	#189.#191;	//  scala/collection/immutable/List.toStream:()Lscala/collection/immutable/Stream;
const #193 = Asciz	toIndexedSeq;
const #194 = Asciz	(Lscala/collection/TraversableLike;)Lscala/collection/mutable/IndexedSeq;;
const #195 = Asciz	scala/collection/mutable/ArrayBuffer;
const #196 = class	#195;	//  scala/collection/mutable/ArrayBuffer
const #197 = Method	#196.#84;	//  scala/collection/mutable/ArrayBuffer."<init>":()V
const #198 = Asciz	$plus$plus$eq;
const #199 = Asciz	(Lscala/collection/Traversable;)Lscala/collection/mutable/ArrayBuffer;;
const #200 = NameAndType	#198:#199;//  $plus$plus$eq:(Lscala/collection/Traversable;)Lscala/collection/mutable/ArrayBuffer;
const #201 = Method	#196.#200;	//  scala/collection/mutable/ArrayBuffer.$plus$plus$eq:(Lscala/collection/Traversable;)Lscala/collection/mutable/ArrayBuffer;
const #202 = Asciz	toSeq;
const #203 = Asciz	(Lscala/collection/TraversableLike;)Lscala/collection/Seq;;
const #204 = Asciz	toIterable;
const #205 = Asciz	(Lscala/collection/TraversableLike;)Lscala/collection/Iterable;;
const #206 = InterfaceMethod	#23.#191;	//  scala/collection/TraversableLike.toStream:()Lscala/collection/immutable/Stream;
const #207 = Asciz	(Lscala/collection/TraversableLike;)Lscala/collection/immutable/List;;
const #208 = Asciz	scala/collection/mutable/ListBuffer;
const #209 = class	#208;	//  scala/collection/mutable/ListBuffer
const #210 = Method	#209.#84;	//  scala/collection/mutable/ListBuffer."<init>":()V
const #211 = Asciz	scala/collection/generic/Growable;
const #212 = class	#211;	//  scala/collection/generic/Growable
const #213 = Asciz	(Lscala/collection/Traversable;)Lscala/collection/generic/Growable;;
const #214 = NameAndType	#198:#213;//  $plus$plus$eq:(Lscala/collection/Traversable;)Lscala/collection/generic/Growable;
const #215 = InterfaceMethod	#212.#214;	//  scala/collection/generic/Growable.$plus$plus$eq:(Lscala/collection/Traversable;)Lscala/collection/generic/Growable;
const #216 = Method	#209.#186;	//  scala/collection/mutable/ListBuffer.toList:()Lscala/collection/immutable/List;
const #217 = Asciz	toArray;
const #218 = Asciz	(Lscala/collection/TraversableLike;Lscala/reflect/ClassManifest;)Ljava/lang/Object;;
const #219 = Asciz	size;
const #220 = Asciz	()I;
const #221 = NameAndType	#219:#220;//  size:()I
const #222 = InterfaceMethod	#23.#221;	//  scala/collection/TraversableLike.size:()I
const #223 = Asciz	scala/reflect/ClassManifest;
const #224 = class	#223;	//  scala/reflect/ClassManifest
const #225 = Asciz	newArray;
const #226 = Asciz	(I)Ljava/lang/Object;;
const #227 = NameAndType	#225:#226;//  newArray:(I)Ljava/lang/Object;
const #228 = InterfaceMethod	#224.#227;	//  scala/reflect/ClassManifest.newArray:(I)Ljava/lang/Object;
const #229 = Asciz	copyToArray;
const #230 = Asciz	(Ljava/lang/Object;I)V;
const #231 = NameAndType	#229:#230;//  copyToArray:(Ljava/lang/Object;I)V
const #232 = InterfaceMethod	#23.#231;	//  scala/collection/TraversableLike.copyToArray:(Ljava/lang/Object;I)V
const #233 = Asciz	evidence$1;
const #234 = Asciz	Lscala/reflect/ClassManifest;;
const #235 = Asciz	result;
const #236 = Asciz	Ljava/lang/Object;;
const #237 = Asciz	(Lscala/collection/TraversableLike;Ljava/lang/Object;I)V;
const #238 = Asciz	scala/runtime/ScalaRunTime$;
const #239 = class	#238;	//  scala/runtime/ScalaRunTime$
const #240 = Asciz	Lscala/runtime/ScalaRunTime$;;
const #241 = NameAndType	#153:#240;//  MODULE$:Lscala/runtime/ScalaRunTime$;
const #242 = Field	#239.#241;	//  scala/runtime/ScalaRunTime$.MODULE$:Lscala/runtime/ScalaRunTime$;
const #243 = Asciz	array_length;
const #244 = Asciz	(Ljava/lang/Object;)I;
const #245 = NameAndType	#243:#244;//  array_length:(Ljava/lang/Object;)I
const #246 = Method	#239.#245;	//  scala/runtime/ScalaRunTime$.array_length:(Ljava/lang/Object;)I
const #247 = Asciz	(Ljava/lang/Object;II)V;
const #248 = NameAndType	#229:#247;//  copyToArray:(Ljava/lang/Object;II)V
const #249 = InterfaceMethod	#23.#248;	//  scala/collection/TraversableLike.copyToArray:(Ljava/lang/Object;II)V
const #250 = Asciz	xs;
const #251 = Asciz	(Lscala/collection/TraversableLike;Ljava/lang/Object;II)V;
const #252 = Asciz	scala/runtime/IntRef;
const #253 = class	#252;	//  scala/runtime/IntRef
const #254 = Asciz	(I)V;
const #255 = NameAndType	#14:#254;//  "<init>":(I)V
const #256 = Method	#253.#255;	//  scala/runtime/IntRef."<init>":(I)V
const #257 = Asciz	intWrapper;
const #258 = Asciz	(I)Lscala/runtime/RichInt;;
const #259 = NameAndType	#257:#258;//  intWrapper:(I)Lscala/runtime/RichInt;
const #260 = Method	#158.#259;	//  scala/Predef$.intWrapper:(I)Lscala/runtime/RichInt;
const #261 = Asciz	scala/runtime/RichInt;
const #262 = class	#261;	//  scala/runtime/RichInt
const #263 = Asciz	min;
const #264 = NameAndType	#263:#62;//  min:(I)I
const #265 = Method	#262.#264;	//  scala/runtime/RichInt.min:(I)I
const #266 = Asciz	scala/collection/Traversable$;
const #267 = class	#266;	//  scala/collection/Traversable$
const #268 = Asciz	Lscala/collection/Traversable$;;
const #269 = NameAndType	#153:#268;//  MODULE$:Lscala/collection/Traversable$;
const #270 = Field	#267.#269;	//  scala/collection/Traversable$.MODULE$:Lscala/collection/Traversable$;
const #271 = Asciz	breaks;
const #272 = Asciz	()Lscala/util/control/Breaks;;
const #273 = NameAndType	#271:#272;//  breaks:()Lscala/util/control/Breaks;
const #274 = Method	#267.#273;	//  scala/collection/Traversable$.breaks:()Lscala/util/control/Breaks;
const #275 = Asciz	scala/collection/TraversableLike$$anonfun$copyToArray$1;
const #276 = class	#275;	//  scala/collection/TraversableLike$$anonfun$copyToArray$1
const #277 = Asciz	(Lscala/collection/TraversableLike;Ljava/lang/Object;Lscala/runtime/IntRef;I)V;
const #278 = NameAndType	#14:#277;//  "<init>":(Lscala/collection/TraversableLike;Ljava/lang/Object;Lscala/runtime/IntRef;I)V
const #279 = Method	#276.#278;	//  scala/collection/TraversableLike$$anonfun$copyToArray$1."<init>":(Lscala/collection/TraversableLike;Ljava/lang/Object;Lscala/runtime/IntRef;I)V
const #280 = Asciz	scala/util/control/Breaks;
const #281 = class	#280;	//  scala/util/control/Breaks
const #282 = Asciz	breakable;
const #283 = Asciz	(Lscala/Function0;)V;
const #284 = NameAndType	#282:#283;//  breakable:(Lscala/Function0;)V
const #285 = Method	#281.#284;	//  scala/util/control/Breaks.breakable:(Lscala/Function0;)V
const #286 = Asciz	xs$1;
const #287 = Asciz	len;
const #288 = Asciz	i$5;
const #289 = Asciz	Lscala/runtime/IntRef;;
const #290 = Asciz	end$1;
const #291 = Asciz	copyToBuffer;
const #292 = Asciz	(Lscala/collection/TraversableLike;Lscala/collection/mutable/Buffer;)V;
const #293 = Asciz	scala/collection/TraversableLike$$anonfun$copyToBuffer$1;
const #294 = class	#293;	//  scala/collection/TraversableLike$$anonfun$copyToBuffer$1
const #295 = NameAndType	#14:#292;//  "<init>":(Lscala/collection/TraversableLike;Lscala/collection/mutable/Buffer;)V
const #296 = Method	#294.#295;	//  scala/collection/TraversableLike$$anonfun$copyToBuffer$1."<init>":(Lscala/collection/TraversableLike;Lscala/collection/mutable/Buffer;)V
const #297 = Asciz	dest$1;
const #298 = Asciz	Lscala/collection/mutable/Buffer;;
const #299 = Asciz	splitAt;
const #300 = Asciz	(Lscala/collection/TraversableLike;I)Lscala/Tuple2;;
const #301 = Asciz	newBuilder;
const #302 = Asciz	()Lscala/collection/mutable/Builder;;
const #303 = NameAndType	#301:#302;//  newBuilder:()Lscala/collection/mutable/Builder;
const #304 = InterfaceMethod	#23.#303;	//  scala/collection/TraversableLike.newBuilder:()Lscala/collection/mutable/Builder;
const #305 = Asciz	scala/collection/TraversableLike$$anonfun$splitAt$1;
const #306 = class	#305;	//  scala/collection/TraversableLike$$anonfun$splitAt$1
const #307 = Asciz	(Lscala/collection/TraversableLike;ILscala/collection/mutable/Builder;Lscala/collection/mutable/Builder;Lscala/runtime/IntRef;)V;
const #308 = NameAndType	#14:#307;//  "<init>":(Lscala/collection/TraversableLike;ILscala/collection/mutable/Builder;Lscala/collection/mutable/Builder;Lscala/runtime/IntRef;)V
const #309 = Method	#306.#308;	//  scala/collection/TraversableLike$$anonfun$splitAt$1."<init>":(Lscala/collection/TraversableLike;ILscala/collection/mutable/Builder;Lscala/collection/mutable/Builder;Lscala/runtime/IntRef;)V
const #310 = Asciz	scala/Tuple2;
const #311 = class	#310;	//  scala/Tuple2
const #312 = Asciz	scala/collection/mutable/Builder;
const #313 = class	#312;	//  scala/collection/mutable/Builder
const #314 = NameAndType	#235:#24;//  result:()Ljava/lang/Object;
const #315 = InterfaceMethod	#313.#314;	//  scala/collection/mutable/Builder.result:()Ljava/lang/Object;
const #316 = Asciz	(Ljava/lang/Object;Ljava/lang/Object;)V;
const #317 = NameAndType	#14:#316;//  "<init>":(Ljava/lang/Object;Ljava/lang/Object;)V
const #318 = Method	#311.#317;	//  scala/Tuple2."<init>":(Ljava/lang/Object;Ljava/lang/Object;)V
const #319 = Asciz	n$3;
const #320 = Asciz	l$3;
const #321 = Asciz	Lscala/collection/mutable/Builder;;
const #322 = Asciz	r$3;
const #323 = Asciz	i$4;
const #324 = Asciz	span;
const #325 = Asciz	(Lscala/collection/TraversableLike;Lscala/Function1;)Lscala/Tuple2;;
const #326 = Asciz	scala/collection/TraversableLike$$anonfun$span$1;
const #327 = class	#326;	//  scala/collection/TraversableLike$$anonfun$span$1
const #328 = Asciz	(Lscala/collection/TraversableLike;Lscala/Function1;Lscala/collection/mutable/Builder;Lscala/collection/mutable/Builder;Lscala/runtime/BooleanRef;)V;
const #329 = NameAndType	#14:#328;//  "<init>":(Lscala/collection/TraversableLike;Lscala/Function1;Lscala/collection/mutable/Builder;Lscala/collection/mutable/Builder;Lscala/runtime/BooleanRef;)V
const #330 = Method	#327.#329;	//  scala/collection/TraversableLike$$anonfun$span$1."<init>":(Lscala/collection/TraversableLike;Lscala/Function1;Lscala/collection/mutable/Builder;Lscala/collection/mutable/Builder;Lscala/runtime/BooleanRef;)V
const #331 = Asciz	p$7;
const #332 = Asciz	l$2;
const #333 = Asciz	r$2;
const #334 = Asciz	toLeft$1;
const #335 = Asciz	dropWhile;
const #336 = Asciz	(Lscala/collection/TraversableLike;Lscala/Function1;)Ljava/lang/Object;;
const #337 = Asciz	scala/collection/TraversableLike$$anonfun$dropWhile$1;
const #338 = class	#337;	//  scala/collection/TraversableLike$$anonfun$dropWhile$1
const #339 = Asciz	(Lscala/collection/TraversableLike;Lscala/Function1;Lscala/collection/mutable/Builder;Lscala/runtime/BooleanRef;)V;
const #340 = NameAndType	#14:#339;//  "<init>":(Lscala/collection/TraversableLike;Lscala/Function1;Lscala/collection/mutable/Builder;Lscala/runtime/BooleanRef;)V
const #341 = Method	#338.#340;	//  scala/collection/TraversableLike$$anonfun$dropWhile$1."<init>":(Lscala/collection/TraversableLike;Lscala/Function1;Lscala/collection/mutable/Builder;Lscala/runtime/BooleanRef;)V
const #342 = Asciz	p$6;
const #343 = Asciz	b$11;
const #344 = Asciz	go$1;
const #345 = Asciz	takeWhile;
const #346 = Asciz	scala/collection/TraversableLike$$anonfun$takeWhile$1;
const #347 = class	#346;	//  scala/collection/TraversableLike$$anonfun$takeWhile$1
const #348 = Asciz	(Lscala/collection/TraversableLike;Lscala/Function1;Lscala/collection/mutable/Builder;)V;
const #349 = NameAndType	#14:#348;//  "<init>":(Lscala/collection/TraversableLike;Lscala/Function1;Lscala/collection/mutable/Builder;)V
const #350 = Method	#347.#349;	//  scala/collection/TraversableLike$$anonfun$takeWhile$1."<init>":(Lscala/collection/TraversableLike;Lscala/Function1;Lscala/collection/mutable/Builder;)V
const #351 = Asciz	p$5;
const #352 = Asciz	b$10;
const #353 = Asciz	(Lscala/collection/TraversableLike;II)Ljava/lang/Object;;
const #354 = Asciz	scala/collection/TraversableLike$$anonfun$slice$1;
const #355 = class	#354;	//  scala/collection/TraversableLike$$anonfun$slice$1
const #356 = Asciz	(Lscala/collection/TraversableLike;IILscala/collection/mutable/Builder;Lscala/runtime/IntRef;)V;
const #357 = NameAndType	#14:#356;//  "<init>":(Lscala/collection/TraversableLike;IILscala/collection/mutable/Builder;Lscala/runtime/IntRef;)V
const #358 = Method	#355.#357;	//  scala/collection/TraversableLike$$anonfun$slice$1."<init>":(Lscala/collection/TraversableLike;IILscala/collection/mutable/Builder;Lscala/runtime/IntRef;)V
const #359 = Asciz	from$1;
const #360 = Asciz	until$1;
const #361 = Asciz	b$9;
const #362 = Asciz	i$3;
const #363 = Asciz	drop;
const #364 = Asciz	(Lscala/collection/TraversableLike;I)Ljava/lang/Object;;
const #365 = Asciz	scala/collection/TraversableLike$$anonfun$drop$1;
const #366 = class	#365;	//  scala/collection/TraversableLike$$anonfun$drop$1
const #367 = Asciz	(Lscala/collection/TraversableLike;ILscala/collection/mutable/Builder;Lscala/runtime/IntRef;)V;
const #368 = NameAndType	#14:#367;//  "<init>":(Lscala/collection/TraversableLike;ILscala/collection/mutable/Builder;Lscala/runtime/IntRef;)V
const #369 = Method	#366.#368;	//  scala/collection/TraversableLike$$anonfun$drop$1."<init>":(Lscala/collection/TraversableLike;ILscala/collection/mutable/Builder;Lscala/runtime/IntRef;)V
const #370 = Asciz	n$2;
const #371 = Asciz	b$8;
const #372 = Asciz	i$2;
const #373 = Asciz	take;
const #374 = Asciz	scala/collection/TraversableLike$$anonfun$take$1;
const #375 = class	#374;	//  scala/collection/TraversableLike$$anonfun$take$1
const #376 = Method	#375.#368;	//  scala/collection/TraversableLike$$anonfun$take$1."<init>":(Lscala/collection/TraversableLike;ILscala/collection/mutable/Builder;Lscala/runtime/IntRef;)V
const #377 = Asciz	n$1;
const #378 = Asciz	b$7;
const #379 = Asciz	i$1;
const #380 = Asciz	init;
const #381 = Asciz	isEmpty;
const #382 = Asciz	()Z;
const #383 = NameAndType	#381:#382;//  isEmpty:()Z
const #384 = InterfaceMethod	#23.#383;	//  scala/collection/TraversableLike.isEmpty:()Z
const #385 = Asciz	java/lang/UnsupportedOperationException;
const #386 = class	#385;	//  java/lang/UnsupportedOperationException
const #387 = Asciz	empty.init;
const #388 = String	#387;	//  empty.init
const #389 = Asciz	(Ljava/lang/String;)V;
const #390 = NameAndType	#14:#389;//  "<init>":(Ljava/lang/String;)V
const #391 = Method	#386.#390;	//  java/lang/UnsupportedOperationException."<init>":(Ljava/lang/String;)V
const #392 = Asciz	scala/runtime/ObjectRef;
const #393 = class	#392;	//  scala/runtime/ObjectRef
const #394 = Asciz	head;
const #395 = NameAndType	#394:#24;//  head:()Ljava/lang/Object;
const #396 = InterfaceMethod	#23.#395;	//  scala/collection/TraversableLike.head:()Ljava/lang/Object;
const #397 = Asciz	(Ljava/lang/Object;)V;
const #398 = NameAndType	#14:#397;//  "<init>":(Ljava/lang/Object;)V
const #399 = Method	#393.#398;	//  scala/runtime/ObjectRef."<init>":(Ljava/lang/Object;)V
const #400 = Asciz	scala/collection/TraversableLike$$anonfun$init$1;
const #401 = class	#400;	//  scala/collection/TraversableLike$$anonfun$init$1
const #402 = Asciz	(Lscala/collection/TraversableLike;Lscala/runtime/ObjectRef;Lscala/runtime/BooleanRef;Lscala/collection/mutable/Builder;)V;
const #403 = NameAndType	#14:#402;//  "<init>":(Lscala/collection/TraversableLike;Lscala/runtime/ObjectRef;Lscala/runtime/BooleanRef;Lscala/collection/mutable/Builder;)V
const #404 = Method	#401.#403;	//  scala/collection/TraversableLike$$anonfun$init$1."<init>":(Lscala/collection/TraversableLike;Lscala/runtime/ObjectRef;Lscala/runtime/BooleanRef;Lscala/collection/mutable/Builder;)V
const #405 = Asciz	lst$2;
const #406 = Asciz	Lscala/runtime/ObjectRef;;
const #407 = Asciz	follow$1;
const #408 = Asciz	b$6;
const #409 = Asciz	lastOption;
const #410 = Asciz	(Lscala/collection/TraversableLike;)Lscala/Option;;
const #411 = Asciz	scala/None$;
const #412 = class	#411;	//  scala/None$
const #413 = Asciz	Lscala/None$;;
const #414 = NameAndType	#153:#413;//  MODULE$:Lscala/None$;
const #415 = Field	#412.#414;	//  scala/None$.MODULE$:Lscala/None$;
const #416 = Asciz	scala/Some;
const #417 = class	#416;	//  scala/Some
const #418 = Asciz	last;
const #419 = NameAndType	#418:#24;//  last:()Ljava/lang/Object;
const #420 = InterfaceMethod	#23.#419;	//  scala/collection/TraversableLike.last:()Ljava/lang/Object;
const #421 = Method	#417.#398;	//  scala/Some."<init>":(Ljava/lang/Object;)V
const #422 = Asciz	scala/collection/TraversableLike$$anonfun$last$1;
const #423 = class	#422;	//  scala/collection/TraversableLike$$anonfun$last$1
const #424 = Asciz	(Lscala/collection/TraversableLike;Lscala/runtime/ObjectRef;)V;
const #425 = NameAndType	#14:#424;//  "<init>":(Lscala/collection/TraversableLike;Lscala/runtime/ObjectRef;)V
const #426 = Method	#423.#425;	//  scala/collection/TraversableLike$$anonfun$last$1."<init>":(Lscala/collection/TraversableLike;Lscala/runtime/ObjectRef;)V
const #427 = Asciz	elem;
const #428 = NameAndType	#427:#236;//  elem:Ljava/lang/Object;
const #429 = Field	#393.#428;	//  scala/runtime/ObjectRef.elem:Ljava/lang/Object;
const #430 = Asciz	lst$1;
const #431 = Asciz	tail;
const #432 = NameAndType	#363:#226;//  drop:(I)Ljava/lang/Object;
const #433 = InterfaceMethod	#23.#432;	//  scala/collection/TraversableLike.drop:(I)Ljava/lang/Object;
const #434 = Asciz	java/lang/IllegalArgumentException;
const #435 = class	#434;	//  java/lang/IllegalArgumentException
const #436 = Asciz	requirement failed: ;
const #437 = String	#436;	//  requirement failed: 
const #438 = Asciz	<empty>.tail;
const #439 = String	#438;	//  <empty>.tail
const #440 = Method	#435.#390;	//  java/lang/IllegalArgumentException."<init>":(Ljava/lang/String;)V
const #441 = Asciz	requirement0;
const #442 = Asciz	Z;
const #443 = Asciz	headOption;
const #444 = Asciz	scala/collection/TraversableLike$$anonfun$1;
const #445 = class	#444;	//  scala/collection/TraversableLike$$anonfun$1
const #446 = Method	#445.#39;	//  scala/collection/TraversableLike$$anonfun$1."<init>":(Lscala/collection/TraversableLike;)V
const #447 = Asciz	scala/collection/TraversableLike$$anonfun$head$1;
const #448 = class	#447;	//  scala/collection/TraversableLike$$anonfun$head$1
const #449 = Method	#448.#425;	//  scala/collection/TraversableLike$$anonfun$head$1."<init>":(Lscala/collection/TraversableLike;Lscala/runtime/ObjectRef;)V
const #450 = Asciz	scala/Function0;
const #451 = class	#450;	//  scala/Function0
const #452 = NameAndType	#166:#24;//  apply:()Ljava/lang/Object;
const #453 = InterfaceMethod	#451.#452;	//  scala/Function0.apply:()Ljava/lang/Object;
const #454 = Asciz	result$8;
const #455 = Asciz	max;
const #456 = Asciz	(Lscala/collection/TraversableLike;Lscala/math/Ordering;)Ljava/lang/Object;;
const #457 = Asciz	scala/collection/TraversableLike$$anonfun$max$2;
const #458 = class	#457;	//  scala/collection/TraversableLike$$anonfun$max$2
const #459 = Asciz	(Lscala/collection/TraversableLike;Lscala/math/Ordering;Lscala/runtime/ObjectRef;)V;
const #460 = NameAndType	#14:#459;//  "<init>":(Lscala/collection/TraversableLike;Lscala/math/Ordering;Lscala/runtime/ObjectRef;)V
const #461 = Method	#458.#460;	//  scala/collection/TraversableLike$$anonfun$max$2."<init>":(Lscala/collection/TraversableLike;Lscala/math/Ordering;Lscala/runtime/ObjectRef;)V
const #462 = Asciz	<empty>.max;
const #463 = String	#462;	//  <empty>.max
const #464 = Asciz	cmp$2;
const #465 = Asciz	Lscala/math/Ordering;;
const #466 = Asciz	acc$4;
const #467 = Asciz	scala/collection/TraversableLike$$anonfun$min$2;
const #468 = class	#467;	//  scala/collection/TraversableLike$$anonfun$min$2
const #469 = Method	#468.#460;	//  scala/collection/TraversableLike$$anonfun$min$2."<init>":(Lscala/collection/TraversableLike;Lscala/math/Ordering;Lscala/runtime/ObjectRef;)V
const #470 = Asciz	<empty>.min;
const #471 = String	#470;	//  <empty>.min
const #472 = Asciz	cmp$1;
const #473 = Asciz	acc$3;
const #474 = Asciz	product;
const #475 = Asciz	(Lscala/collection/TraversableLike;Lscala/math/Numeric;)Ljava/lang/Object;;
const #476 = Asciz	scala/math/Numeric;
const #477 = class	#476;	//  scala/math/Numeric
const #478 = Asciz	one;
const #479 = NameAndType	#478:#24;//  one:()Ljava/lang/Object;
const #480 = InterfaceMethod	#477.#479;	//  scala/math/Numeric.one:()Ljava/lang/Object;
const #481 = Asciz	scala/collection/TraversableLike$$anonfun$product$1;
const #482 = class	#481;	//  scala/collection/TraversableLike$$anonfun$product$1
const #483 = Asciz	(Lscala/collection/TraversableLike;Lscala/math/Numeric;Lscala/runtime/ObjectRef;)V;
const #484 = NameAndType	#14:#483;//  "<init>":(Lscala/collection/TraversableLike;Lscala/math/Numeric;Lscala/runtime/ObjectRef;)V
const #485 = Method	#482.#484;	//  scala/collection/TraversableLike$$anonfun$product$1."<init>":(Lscala/collection/TraversableLike;Lscala/math/Numeric;Lscala/runtime/ObjectRef;)V
const #486 = Asciz	num$2;
const #487 = Asciz	Lscala/math/Numeric;;
const #488 = Asciz	acc$2;
const #489 = Asciz	sum;
const #490 = Asciz	zero;
const #491 = NameAndType	#490:#24;//  zero:()Ljava/lang/Object;
const #492 = InterfaceMethod	#477.#491;	//  scala/math/Numeric.zero:()Ljava/lang/Object;
const #493 = Asciz	scala/collection/TraversableLike$$anonfun$sum$1;
const #494 = class	#493;	//  scala/collection/TraversableLike$$anonfun$sum$1
const #495 = Method	#494.#484;	//  scala/collection/TraversableLike$$anonfun$sum$1."<init>":(Lscala/collection/TraversableLike;Lscala/math/Numeric;Lscala/runtime/ObjectRef;)V
const #496 = Asciz	num$1;
const #497 = Asciz	acc$1;
const #498 = Asciz	reduceRightOption;
const #499 = Asciz	(Lscala/collection/TraversableLike;Lscala/Function2;)Lscala/Option;;
const #500 = Asciz	reduceRight;
const #501 = Asciz	(Lscala/Function2;)Ljava/lang/Object;;
const #502 = NameAndType	#500:#501;//  reduceRight:(Lscala/Function2;)Ljava/lang/Object;
const #503 = InterfaceMethod	#23.#502;	//  scala/collection/TraversableLike.reduceRight:(Lscala/Function2;)Ljava/lang/Object;
const #504 = Asciz	op;
const #505 = Asciz	Lscala/Function2;;
const #506 = Asciz	(Lscala/collection/TraversableLike;Lscala/Function2;)Ljava/lang/Object;;
const #507 = Asciz	empty.reduceRight;
const #508 = String	#507;	//  empty.reduceRight
const #509 = Asciz	scala/collection/immutable/Nil$;
const #510 = class	#509;	//  scala/collection/immutable/Nil$
const #511 = Asciz	Lscala/collection/immutable/Nil$;;
const #512 = NameAndType	#153:#511;//  MODULE$:Lscala/collection/immutable/Nil$;
const #513 = Field	#510.#512;	//  scala/collection/immutable/Nil$.MODULE$:Lscala/collection/immutable/Nil$;
const #514 = Asciz	scala/collection/TraversableLike$$anonfun$reduceRight$1;
const #515 = class	#514;	//  scala/collection/TraversableLike$$anonfun$reduceRight$1
const #516 = Method	#515.#425;	//  scala/collection/TraversableLike$$anonfun$reduceRight$1."<init>":(Lscala/collection/TraversableLike;Lscala/runtime/ObjectRef;)V
const #517 = Asciz	scala/collection/TraversableLike$$anonfun$reduceRight$2;
const #518 = class	#517;	//  scala/collection/TraversableLike$$anonfun$reduceRight$2
const #519 = Asciz	(Lscala/collection/TraversableLike;Lscala/Function2;)V;
const #520 = NameAndType	#14:#519;//  "<init>":(Lscala/collection/TraversableLike;Lscala/Function2;)V
const #521 = Method	#518.#520;	//  scala/collection/TraversableLike$$anonfun$reduceRight$2."<init>":(Lscala/collection/TraversableLike;Lscala/Function2;)V
const #522 = Asciz	scala/collection/LinearSeqLike;
const #523 = class	#522;	//  scala/collection/LinearSeqLike
const #524 = Asciz	reduceLeft;
const #525 = NameAndType	#524:#501;//  reduceLeft:(Lscala/Function2;)Ljava/lang/Object;
const #526 = InterfaceMethod	#523.#525;	//  scala/collection/LinearSeqLike.reduceLeft:(Lscala/Function2;)Ljava/lang/Object;
const #527 = Asciz	op$4;
const #528 = Asciz	elems$2;
const #529 = Asciz	reduceLeftOption;
const #530 = InterfaceMethod	#23.#525;	//  scala/collection/TraversableLike.reduceLeft:(Lscala/Function2;)Ljava/lang/Object;
const #531 = Asciz	empty.reduceLeft;
const #532 = String	#531;	//  empty.reduceLeft
const #533 = Asciz	scala/collection/TraversableLike$$anonfun$reduceLeft$1;
const #534 = class	#533;	//  scala/collection/TraversableLike$$anonfun$reduceLeft$1
const #535 = Asciz	(Lscala/collection/TraversableLike;Lscala/Function2;Lscala/runtime/ObjectRef;Lscala/runtime/BooleanRef;)V;
const #536 = NameAndType	#14:#535;//  "<init>":(Lscala/collection/TraversableLike;Lscala/Function2;Lscala/runtime/ObjectRef;Lscala/runtime/BooleanRef;)V
const #537 = Method	#534.#536;	//  scala/collection/TraversableLike$$anonfun$reduceLeft$1."<init>":(Lscala/collection/TraversableLike;Lscala/Function2;Lscala/runtime/ObjectRef;Lscala/runtime/BooleanRef;)V
const #538 = Asciz	op$3;
const #539 = Asciz	result$7;
const #540 = Asciz	first$1;
const #541 = Asciz	$colon$bslash;
const #542 = Asciz	(Lscala/collection/TraversableLike;Ljava/lang/Object;Lscala/Function2;)Ljava/lang/Object;;
const #543 = Asciz	foldRight;
const #544 = Asciz	(Ljava/lang/Object;Lscala/Function2;)Ljava/lang/Object;;
const #545 = NameAndType	#543:#544;//  foldRight:(Ljava/lang/Object;Lscala/Function2;)Ljava/lang/Object;
const #546 = InterfaceMethod	#23.#545;	//  scala/collection/TraversableLike.foldRight:(Ljava/lang/Object;Lscala/Function2;)Ljava/lang/Object;
const #547 = Asciz	z;
const #548 = Asciz	scala/collection/TraversableLike$$anonfun$foldRight$1;
const #549 = class	#548;	//  scala/collection/TraversableLike$$anonfun$foldRight$1
const #550 = Method	#549.#425;	//  scala/collection/TraversableLike$$anonfun$foldRight$1."<init>":(Lscala/collection/TraversableLike;Lscala/runtime/ObjectRef;)V
const #551 = Asciz	scala/collection/TraversableLike$$anonfun$foldRight$2;
const #552 = class	#551;	//  scala/collection/TraversableLike$$anonfun$foldRight$2
const #553 = Method	#552.#520;	//  scala/collection/TraversableLike$$anonfun$foldRight$2."<init>":(Lscala/collection/TraversableLike;Lscala/Function2;)V
const #554 = Asciz	foldLeft;
const #555 = NameAndType	#554:#544;//  foldLeft:(Ljava/lang/Object;Lscala/Function2;)Ljava/lang/Object;
const #556 = InterfaceMethod	#523.#555;	//  scala/collection/LinearSeqLike.foldLeft:(Ljava/lang/Object;Lscala/Function2;)Ljava/lang/Object;
const #557 = Asciz	op$2;
const #558 = Asciz	elems$1;
const #559 = Asciz	$div$colon;
const #560 = InterfaceMethod	#23.#555;	//  scala/collection/TraversableLike.foldLeft:(Ljava/lang/Object;Lscala/Function2;)Ljava/lang/Object;
const #561 = Asciz	scala/collection/TraversableLike$$anonfun$foldLeft$1;
const #562 = class	#561;	//  scala/collection/TraversableLike$$anonfun$foldLeft$1
const #563 = Asciz	(Lscala/collection/TraversableLike;Lscala/Function2;Lscala/runtime/ObjectRef;)V;
const #564 = NameAndType	#14:#563;//  "<init>":(Lscala/collection/TraversableLike;Lscala/Function2;Lscala/runtime/ObjectRef;)V
const #565 = Method	#562.#564;	//  scala/collection/TraversableLike$$anonfun$foldLeft$1."<init>":(Lscala/collection/TraversableLike;Lscala/Function2;Lscala/runtime/ObjectRef;)V
const #566 = Asciz	op$1;
const #567 = Asciz	result$6;
const #568 = Asciz	find;
const #569 = Asciz	(Lscala/collection/TraversableLike;Lscala/Function1;)Lscala/Option;;
const #570 = Asciz	scala/collection/TraversableLike$$anonfun$find$1;
const #571 = class	#570;	//  scala/collection/TraversableLike$$anonfun$find$1
const #572 = Asciz	(Lscala/collection/TraversableLike;Lscala/Function1;Lscala/runtime/ObjectRef;)V;
const #573 = NameAndType	#14:#572;//  "<init>":(Lscala/collection/TraversableLike;Lscala/Function1;Lscala/runtime/ObjectRef;)V
const #574 = Method	#571.#573;	//  scala/collection/TraversableLike$$anonfun$find$1."<init>":(Lscala/collection/TraversableLike;Lscala/Function1;Lscala/runtime/ObjectRef;)V
const #575 = Asciz	scala/Option;
const #576 = class	#575;	//  scala/Option
const #577 = Asciz	p$1;
const #578 = Asciz	result$5;
const #579 = Asciz	count;
const #580 = Asciz	(Lscala/collection/TraversableLike;Lscala/Function1;)I;
const #581 = Asciz	scala/collection/TraversableLike$$anonfun$count$1;
const #582 = class	#581;	//  scala/collection/TraversableLike$$anonfun$count$1
const #583 = Asciz	(Lscala/collection/TraversableLike;Lscala/Function1;Lscala/runtime/IntRef;)V;
const #584 = NameAndType	#14:#583;//  "<init>":(Lscala/collection/TraversableLike;Lscala/Function1;Lscala/runtime/IntRef;)V
const #585 = Method	#582.#584;	//  scala/collection/TraversableLike$$anonfun$count$1."<init>":(Lscala/collection/TraversableLike;Lscala/Function1;Lscala/runtime/IntRef;)V
const #586 = NameAndType	#427:#34;//  elem:I
const #587 = Field	#253.#586;	//  scala/runtime/IntRef.elem:I
const #588 = Asciz	p$8;
const #589 = Asciz	cnt$1;
const #590 = Asciz	exists;
const #591 = Asciz	(Lscala/collection/TraversableLike;Lscala/Function1;)Z;
const #592 = Asciz	scala/collection/TraversableLike$$anonfun$exists$1;
const #593 = class	#592;	//  scala/collection/TraversableLike$$anonfun$exists$1
const #594 = Asciz	(Lscala/collection/TraversableLike;Lscala/Function1;Lscala/runtime/BooleanRef;)V;
const #595 = NameAndType	#14:#594;//  "<init>":(Lscala/collection/TraversableLike;Lscala/Function1;Lscala/runtime/BooleanRef;)V
const #596 = Method	#593.#595;	//  scala/collection/TraversableLike$$anonfun$exists$1."<init>":(Lscala/collection/TraversableLike;Lscala/Function1;Lscala/runtime/BooleanRef;)V
const #597 = NameAndType	#427:#442;//  elem:Z
const #598 = Field	#123.#597;	//  scala/runtime/BooleanRef.elem:Z
const #599 = Asciz	p$4;
const #600 = Asciz	result$4;
const #601 = Asciz	forall;
const #602 = Asciz	scala/collection/TraversableLike$$anonfun$forall$1;
const #603 = class	#602;	//  scala/collection/TraversableLike$$anonfun$forall$1
const #604 = Method	#603.#595;	//  scala/collection/TraversableLike$$anonfun$forall$1."<init>":(Lscala/collection/TraversableLike;Lscala/Function1;Lscala/runtime/BooleanRef;)V
const #605 = Asciz	p$2;
const #606 = Asciz	result$3;
const #607 = Asciz	groupBy;
const #608 = Asciz	(Lscala/collection/TraversableLike;Lscala/Function1;)Lscala/collection/Map;;
const #609 = Asciz	scala/collection/Map$;
const #610 = class	#609;	//  scala/collection/Map$
const #611 = Asciz	Lscala/collection/Map$;;
const #612 = NameAndType	#153:#611;//  MODULE$:Lscala/collection/Map$;
const #613 = Field	#610.#612;	//  scala/collection/Map$.MODULE$:Lscala/collection/Map$;
const #614 = Asciz	[Ljava/lang/Object;;
const #615 = class	#614;	//  "[Ljava/lang/Object;"
const #616 = Asciz	wrapRefArray;
const #617 = Asciz	([Ljava/lang/Object;)Lscala/collection/mutable/WrappedArray;;
const #618 = NameAndType	#616:#617;//  wrapRefArray:([Ljava/lang/Object;)Lscala/collection/mutable/WrappedArray;
const #619 = Method	#158.#618;	//  scala/Predef$.wrapRefArray:([Ljava/lang/Object;)Lscala/collection/mutable/WrappedArray;
const #620 = Asciz	(Lscala/collection/Seq;)Lscala/collection/Map;;
const #621 = NameAndType	#166:#620;//  apply:(Lscala/collection/Seq;)Lscala/collection/Map;
const #622 = Method	#610.#621;	//  scala/collection/Map$.apply:(Lscala/collection/Seq;)Lscala/collection/Map;
const #623 = Asciz	scala/collection/TraversableLike$$anonfun$groupBy$1;
const #624 = class	#623;	//  scala/collection/TraversableLike$$anonfun$groupBy$1
const #625 = Method	#624.#573;	//  scala/collection/TraversableLike$$anonfun$groupBy$1."<init>":(Lscala/collection/TraversableLike;Lscala/Function1;Lscala/runtime/ObjectRef;)V
const #626 = Asciz	scala/collection/Map;
const #627 = class	#626;	//  scala/collection/Map
const #628 = Asciz	scala/collection/TraversableLike$$anonfun$groupBy$2;
const #629 = class	#628;	//  scala/collection/TraversableLike$$anonfun$groupBy$2
const #630 = Method	#629.#39;	//  scala/collection/TraversableLike$$anonfun$groupBy$2."<init>":(Lscala/collection/TraversableLike;)V
const #631 = Asciz	scala/collection/MapLike;
const #632 = class	#631;	//  scala/collection/MapLike
const #633 = Asciz	mapValues;
const #634 = Asciz	(Lscala/Function1;)Ljava/lang/Object;;
const #635 = NameAndType	#633:#634;//  mapValues:(Lscala/Function1;)Ljava/lang/Object;
const #636 = InterfaceMethod	#632.#635;	//  scala/collection/MapLike.mapValues:(Lscala/Function1;)Ljava/lang/Object;
const #637 = Asciz	f$4;
const #638 = Asciz	m$1;
const #639 = Asciz	partition;
const #640 = Asciz	scala/collection/TraversableLike$$anonfun$partition$1;
const #641 = class	#640;	//  scala/collection/TraversableLike$$anonfun$partition$1
const #642 = Asciz	(Lscala/collection/TraversableLike;Lscala/Function1;Lscala/collection/mutable/Builder;Lscala/collection/mutable/Builder;)V;
const #643 = NameAndType	#14:#642;//  "<init>":(Lscala/collection/TraversableLike;Lscala/Function1;Lscala/collection/mutable/Builder;Lscala/collection/mutable/Builder;)V
const #644 = Method	#641.#643;	//  scala/collection/TraversableLike$$anonfun$partition$1."<init>":(Lscala/collection/TraversableLike;Lscala/Function1;Lscala/collection/mutable/Builder;Lscala/collection/mutable/Builder;)V
const #645 = Asciz	p$10;
const #646 = Asciz	l$1;
const #647 = Asciz	r$1;
const #648 = Asciz	partialMap;
const #649 = Asciz	(Lscala/collection/TraversableLike;Lscala/PartialFunction;Lscala/collection/generic/CanBuildFrom;)Ljava/lang/Object;;
const #650 = Asciz	scala/collection/generic/CanBuildFrom;
const #651 = class	#650;	//  scala/collection/generic/CanBuildFrom
const #652 = Asciz	(Ljava/lang/Object;)Lscala/collection/mutable/Builder;;
const #653 = NameAndType	#166:#652;//  apply:(Ljava/lang/Object;)Lscala/collection/mutable/Builder;
const #654 = InterfaceMethod	#651.#653;	//  scala/collection/generic/CanBuildFrom.apply:(Ljava/lang/Object;)Lscala/collection/mutable/Builder;
const #655 = Asciz	scala/collection/TraversableLike$$anonfun$partialMap$1;
const #656 = class	#655;	//  scala/collection/TraversableLike$$anonfun$partialMap$1
const #657 = Asciz	(Lscala/collection/TraversableLike;Lscala/PartialFunction;Lscala/collection/mutable/Builder;)V;
const #658 = NameAndType	#14:#657;//  "<init>":(Lscala/collection/TraversableLike;Lscala/PartialFunction;Lscala/collection/mutable/Builder;)V
const #659 = Method	#656.#658;	//  scala/collection/TraversableLike$$anonfun$partialMap$1."<init>":(Lscala/collection/TraversableLike;Lscala/PartialFunction;Lscala/collection/mutable/Builder;)V
const #660 = Asciz	pf$1;
const #661 = Asciz	Lscala/PartialFunction;;
const #662 = Asciz	bf;
const #663 = Asciz	Lscala/collection/generic/CanBuildFrom;;
const #664 = Asciz	b$5;
const #665 = Asciz	filterNot;
const #666 = Asciz	scala/collection/TraversableLike$$anonfun$filterNot$1;
const #667 = class	#666;	//  scala/collection/TraversableLike$$anonfun$filterNot$1
const #668 = Method	#667.#16;	//  scala/collection/TraversableLike$$anonfun$filterNot$1."<init>":(Lscala/collection/TraversableLike;Lscala/Function1;)V
const #669 = Asciz	filter;
const #670 = NameAndType	#669:#634;//  filter:(Lscala/Function1;)Ljava/lang/Object;
const #671 = InterfaceMethod	#23.#670;	//  scala/collection/TraversableLike.filter:(Lscala/Function1;)Ljava/lang/Object;
const #672 = Asciz	p$9;
const #673 = Asciz	scala/collection/TraversableLike$$anonfun$filter$1;
const #674 = class	#673;	//  scala/collection/TraversableLike$$anonfun$filter$1
const #675 = Method	#674.#349;	//  scala/collection/TraversableLike$$anonfun$filter$1."<init>":(Lscala/collection/TraversableLike;Lscala/Function1;Lscala/collection/mutable/Builder;)V
const #676 = Asciz	p$3;
const #677 = Asciz	b$4;
const #678 = Asciz	flatMap;
const #679 = Asciz	(Lscala/collection/TraversableLike;Lscala/Function1;Lscala/collection/generic/CanBuildFrom;)Ljava/lang/Object;;
const #680 = Asciz	scala/collection/TraversableLike$$anonfun$flatMap$1;
const #681 = class	#680;	//  scala/collection/TraversableLike$$anonfun$flatMap$1
const #682 = Method	#681.#349;	//  scala/collection/TraversableLike$$anonfun$flatMap$1."<init>":(Lscala/collection/TraversableLike;Lscala/Function1;Lscala/collection/mutable/Builder;)V
const #683 = Asciz	f$3;
const #684 = Asciz	b$3;
const #685 = Asciz	map;
const #686 = Asciz	scala/collection/TraversableLike$$anonfun$map$1;
const #687 = class	#686;	//  scala/collection/TraversableLike$$anonfun$map$1
const #688 = Method	#687.#349;	//  scala/collection/TraversableLike$$anonfun$map$1."<init>":(Lscala/collection/TraversableLike;Lscala/Function1;Lscala/collection/mutable/Builder;)V
const #689 = Asciz	f$1;
const #690 = Asciz	b$2;
const #691 = Asciz	(Lscala/collection/TraversableLike;Lscala/collection/Iterator;Lscala/collection/generic/CanBuildFrom;)Ljava/lang/Object;;
const #692 = Asciz	(Lscala/collection/Iterator;)Lscala/collection/generic/Growable;;
const #693 = NameAndType	#198:#692;//  $plus$plus$eq:(Lscala/collection/Iterator;)Lscala/collection/generic/Growable;
const #694 = InterfaceMethod	#212.#693;	//  scala/collection/generic/Growable.$plus$plus$eq:(Lscala/collection/Iterator;)Lscala/collection/generic/Growable;
const #695 = Asciz	that;
const #696 = Asciz	Lscala/collection/Iterator;;
const #697 = Asciz	(Lscala/collection/TraversableLike;Lscala/collection/Traversable;Lscala/collection/generic/CanBuildFrom;)Ljava/lang/Object;;
const #698 = Asciz	Lscala/collection/Traversable;;
const #699 = Asciz	hasDefiniteSize;
const #700 = Asciz	(Lscala/collection/TraversableLike;)Z;
const #701 = Asciz	(Lscala/collection/TraversableLike;)I;
const #702 = Asciz	scala/collection/TraversableLike$$anonfun$size$1;
const #703 = class	#702;	//  scala/collection/TraversableLike$$anonfun$size$1
const #704 = Asciz	(Lscala/collection/TraversableLike;Lscala/runtime/IntRef;)V;
const #705 = NameAndType	#14:#704;//  "<init>":(Lscala/collection/TraversableLike;Lscala/runtime/IntRef;)V
const #706 = Method	#703.#705;	//  scala/collection/TraversableLike$$anonfun$size$1."<init>":(Lscala/collection/TraversableLike;Lscala/runtime/IntRef;)V
const #707 = Asciz	result$2;
const #708 = Asciz	nonEmpty;
const #709 = Asciz	scala/collection/TraversableLike$$anonfun$isEmpty$1;
const #710 = class	#709;	//  scala/collection/TraversableLike$$anonfun$isEmpty$1
const #711 = Asciz	(Lscala/collection/TraversableLike;Lscala/runtime/BooleanRef;)V;
const #712 = NameAndType	#14:#711;//  "<init>":(Lscala/collection/TraversableLike;Lscala/runtime/BooleanRef;)V
const #713 = Method	#710.#712;	//  scala/collection/TraversableLike$$anonfun$isEmpty$1."<init>":(Lscala/collection/TraversableLike;Lscala/runtime/BooleanRef;)V
const #714 = Asciz	result$1;
const #715 = Asciz	toCollection;
const #716 = Asciz	(Lscala/collection/TraversableLike;Ljava/lang/Object;)Lscala/collection/Traversable;;
const #717 = Asciz	scala/collection/Traversable;
const #718 = class	#717;	//  scala/collection/Traversable
const #719 = Asciz	(Lscala/collection/TraversableLike;)Lscala/collection/Traversable;;
const #720 = Asciz	Scala;
const #721 = Asciz	InnerClasses;
const #722 = Asciz	$anon$1;
const #723 = Asciz	$anonfun$1;
const #724 = Asciz	WithFilter;
const #725 = Asciz	$anonfun$map$1;
const #726 = Asciz	$anonfun$sum$1;
const #727 = Asciz	$anonfun$min$2;
const #728 = Asciz	$anonfun$max$2;
const #729 = Asciz	$anonfun$size$1;
const #730 = Asciz	$anonfun$find$1;
const #731 = Asciz	$anonfun$head$1;
const #732 = Asciz	$anonfun$last$1;
const #733 = Asciz	$anonfun$init$1;
const #734 = Asciz	$anonfun$take$1;
const #735 = Asciz	$anonfun$drop$1;
const #736 = Asciz	$anonfun$span$1;
const #737 = Asciz	$anonfun$count$1;
const #738 = Asciz	$anonfun$slice$1;
const #739 = Asciz	$anonfun$filter$1;
const #740 = Asciz	$anonfun$forall$1;
const #741 = Asciz	$anonfun$exists$1;
const #742 = Asciz	$anonfun$isEmpty$1;
const #743 = Asciz	$anonfun$flatMap$1;
const #744 = Asciz	$anonfun$groupBy$2;
const #745 = Asciz	$anonfun$groupBy$1;
const #746 = Asciz	$anonfun$product$1;
const #747 = Asciz	$anonfun$splitAt$1;
const #748 = Asciz	$anonfun$foldLeft$1;
const #749 = Asciz	$anonfun$filterNot$1;
const #750 = Asciz	$anonfun$partition$1;
const #751 = Asciz	$anonfun$foldRight$2;
const #752 = Asciz	$anonfun$foldRight$1;
const #753 = Asciz	$anonfun$takeWhile$1;
const #754 = Asciz	$anonfun$dropWhile$1;
const #755 = Asciz	$anonfun$addString$1;
const #756 = Asciz	$anonfun$partialMap$1;
const #757 = Asciz	$anonfun$reduceLeft$1;
const #758 = Asciz	$anonfun$reduceRight$2;
const #759 = Asciz	$anonfun$reduceRight$1;
const #760 = Asciz	$anonfun$copyToArray$1;
const #761 = Asciz	$anonfun$copyToBuffer$1;
const #762 = Asciz	scala/collection/TraversableLike$class;
const #763 = class	#762;	//  scala/collection/TraversableLike$class

{
public static void $init$(scala.collection.TraversableLike);
  Code:
   Stack=0, Locals=1, Args_size=1
   0:	return
  LineNumberTable: 
   line 65: 0

  LocalVariableTable: 
   Start  Length  Slot  Name   Signature
   0      1      0    $this       Lscala/collection/TraversableLike;


public static scala.collection.TraversableLike$WithFilter withFilter(scala.collection.TraversableLike, scala.Function1);
  Code:
   Stack=4, Locals=2, Args_size=2
   0:	new	#13; //class scala/collection/TraversableLike$WithFilter
   3:	dup
   4:	aload_0
   5:	aload_1
   6:	invokespecial	#17; //Method scala/collection/TraversableLike$WithFilter."<init>":(Lscala/collection/TraversableLike;Lscala/Function1;)V
   9:	areturn
  LineNumberTable: 
   line 846: 0

  LocalVariableTable: 
   Start  Length  Slot  Name   Signature
   0      10      0    $this       Lscala/collection/TraversableLike;
   0      10      1    p       Lscala/Function1;


public static scala.collection.TraversableView view(scala.collection.TraversableLike, int, int);
  Code:
   Stack=3, Locals=3, Args_size=3
   0:	aload_0
   1:	invokeinterface	#26,  1; //InterfaceMethod scala/collection/TraversableLike.view:()Ljava/lang/Object;
   6:	checkcast	#28; //class scala/collection/TraversableViewLike
   9:	iload_1
   10:	iload_2
   11:	invokeinterface	#32,  3; //InterfaceMethod scala/collection/TraversableViewLike.slice:(II)Lscala/collection/TraversableView;
   16:	areturn
  LineNumberTable: 
   line 820: 0

  LocalVariableTable: 
   Start  Length  Slot  Name   Signature
   0      17      0    $this       Lscala/collection/TraversableLike;
   0      17      1    from       I
   0      17      2    until       I


public static java.lang.Object view(scala.collection.TraversableLike);
  Code:
   Stack=3, Locals=1, Args_size=1
   0:	new	#38; //class scala/collection/TraversableLike$$anon$1
   3:	dup
   4:	aload_0
   5:	invokespecial	#40; //Method scala/collection/TraversableLike$$anon$1."<init>":(Lscala/collection/TraversableLike;)V
   8:	areturn
  LineNumberTable: 
   line 804: 0

  LocalVariableTable: 
   Start  Length  Slot  Name   Signature
   0      9      0    $this       Lscala/collection/TraversableLike;


public static java.lang.String stringPrefix(scala.collection.TraversableLike);
  Code:
   Stack=3, Locals=4, Args_size=1
   0:	aload_0
   1:	invokeinterface	#45,  1; //InterfaceMethod scala/collection/TraversableLike.repr:()Ljava/lang/Object;
   6:	invokevirtual	#51; //Method java/lang/Object.getClass:()Ljava/lang/Class;
   9:	invokevirtual	#57; //Method java/lang/Class.getName:()Ljava/lang/String;
   12:	astore_1
   13:	aload_1
   14:	ldc	#58; //int 46
   16:	invokevirtual	#64; //Method java/lang/String.lastIndexOf:(I)I
   19:	istore_2
   20:	iload_2
   21:	iconst_m1
   22:	if_icmpeq	33
   25:	aload_1
   26:	iload_2
   27:	iconst_1
   28:	iadd
   29:	invokevirtual	#68; //Method java/lang/String.substring:(I)Ljava/lang/String;
   32:	astore_1
   33:	aload_1
   34:	ldc	#69; //int 36
   36:	invokevirtual	#72; //Method java/lang/String.indexOf:(I)I
   39:	istore_3
   40:	iload_3
   41:	iconst_m1
   42:	if_icmpeq	52
   45:	aload_1
   46:	iconst_0
   47:	iload_3
   48:	invokevirtual	#75; //Method java/lang/String.substring:(II)Ljava/lang/String;
   51:	astore_1
   52:	aload_1
   53:	areturn
  LineNumberTable: 
   line 794: 0
   line 795: 13
   line 796: 20
   line 797: 33
   line 798: 40
   line 799: 52

  LocalVariableTable: 
   Start  Length  Slot  Name   Signature
   0      54      0    $this       Lscala/collection/TraversableLike;
   13      40      1    string       Ljava/lang/String;
   20      33      2    idx1       I
   40      13      3    idx2       I


public static java.lang.String toString(scala.collection.TraversableLike);
  Code:
   Stack=4, Locals=1, Args_size=1
   0:	aload_0
   1:	new	#82; //class scala/collection/mutable/StringBuilder
   4:	dup
   5:	invokespecial	#85; //Method scala/collection/mutable/StringBuilder."<init>":()V
   8:	aload_0
   9:	invokeinterface	#87,  1; //InterfaceMethod scala/collection/TraversableLike.stringPrefix:()Ljava/lang/String;
   14:	invokevirtual	#91; //Method scala/collection/mutable/StringBuilder.append:(Ljava/lang/Object;)Lscala/collection/mutable/StringBuilder;
   17:	ldc	#93; //String (
   19:	invokevirtual	#91; //Method scala/collection/mutable/StringBuilder.append:(Ljava/lang/Object;)Lscala/collection/mutable/StringBuilder;
   22:	invokevirtual	#95; //Method scala/collection/mutable/StringBuilder.toString:()Ljava/lang/String;
   25:	ldc	#97; //String , 
   27:	ldc	#99; //String )
   29:	invokeinterface	#103,  4; //InterfaceMethod scala/collection/TraversableLike.mkString:(Ljava/lang/String;Ljava/lang/String;Ljava/lang/String;)Ljava/lang/String;
   34:	areturn
  LineNumberTable: 
   line 789: 0

  LocalVariableTable: 
   Start  Length  Slot  Name   Signature
   0      35      0    $this       Lscala/collection/TraversableLike;


public static scala.collection.mutable.StringBuilder addString(scala.collection.TraversableLike, scala.collection.mutable.StringBuilder);
  Code:
   Stack=3, Locals=2, Args_size=2
   0:	aload_0
   1:	aload_1
   2:	ldc	#107; //String 
   4:	invokeinterface	#110,  3; //InterfaceMethod scala/collection/TraversableLike.addString:(Lscala/collection/mutable/StringBuilder;Ljava/lang/String;)Lscala/collection/mutable/StringBuilder;
   9:	areturn
  LineNumberTable: 
   line 787: 0

  LocalVariableTable: 
   Start  Length  Slot  Name   Signature
   0      10      0    $this       Lscala/collection/TraversableLike;
   0      10      1    b       Lscala/collection/mutable/StringBuilder;


public static scala.collection.mutable.StringBuilder addString(scala.collection.TraversableLike, scala.collection.mutable.StringBuilder, java.lang.String);
  Code:
   Stack=5, Locals=3, Args_size=3
   0:	aload_0
   1:	aload_1
   2:	ldc	#107; //String 
   4:	aload_2
   5:	ldc	#107; //String 
   7:	invokeinterface	#116,  5; //InterfaceMethod scala/collection/TraversableLike.addString:(Lscala/collection/mutable/StringBuilder;Ljava/lang/String;Ljava/lang/String;Ljava/lang/String;)Lscala/collection/mutable/StringBuilder;
   12:	areturn
  LineNumberTable: 
   line 782: 0

  LocalVariableTable: 
   Start  Length  Slot  Name   Signature
   0      13      0    $this       Lscala/collection/TraversableLike;
   0      13      1    b       Lscala/collection/mutable/StringBuilder;
   0      13      2    sep       Ljava/lang/String;


public static scala.collection.mutable.StringBuilder addString(scala.collection.TraversableLike, scala.collection.mutable.StringBuilder, java.lang.String, java.lang.String, java.lang.String);
  Code:
   Stack=7, Locals=6, Args_size=5
   0:	aload_1
   1:	aload_2
   2:	invokevirtual	#121; //Method scala/collection/mutable/StringBuilder.append:(Ljava/lang/String;)Lscala/collection/mutable/StringBuilder;
   5:	pop
   6:	new	#123; //class scala/runtime/BooleanRef
   9:	dup
   10:	iconst_1
   11:	invokespecial	#126; //Method scala/runtime/BooleanRef."<init>":(Z)V
   14:	astore	5
   16:	aload_0
   17:	new	#128; //class scala/collection/TraversableLike$$anonfun$addString$1
   20:	dup
   21:	aload_0
   22:	aload_1
   23:	aload_3
   24:	aload	5
   26:	invokespecial	#131; //Method scala/collection/TraversableLike$$anonfun$addString$1."<init>":(Lscala/collection/TraversableLike;Lscala/collection/mutable/StringBuilder;Ljava/lang/String;Lscala/runtime/BooleanRef;)V
   29:	invokeinterface	#135,  2; //InterfaceMethod scala/collection/TraversableLike.foreach:(Lscala/Function1;)V
   34:	aload_1
   35:	aload	4
   37:	invokevirtual	#121; //Method scala/collection/mutable/StringBuilder.append:(Ljava/lang/String;)Lscala/collection/mutable/StringBuilder;
   40:	areturn
  LineNumberTable: 
   line 768: 0
   line 769: 6
   line 770: 16
   line 775: 34

  LocalVariableTable: 
   Start  Length  Slot  Name   Signature
   0      41      0    $this       Lscala/collection/TraversableLike;
   0      41      1    b$1       Lscala/collection/mutable/StringBuilder;
   0      41      2    start       Ljava/lang/String;
   0      41      3    sep$1       Ljava/lang/String;
   0      41      4    end       Ljava/lang/String;
   16      24      5    first$2       Lscala/runtime/BooleanRef;


public static java.lang.String mkString(scala.collection.TraversableLike);
  Code:
   Stack=3, Locals=1, Args_size=1
   0:	aload_0
   1:	new	#82; //class scala/collection/mutable/StringBuilder
   4:	dup
   5:	invokespecial	#142; //Method scala/collection/mutable/StringBuilder."<init>":()V
   8:	invokeinterface	#145,  2; //InterfaceMethod scala/collection/TraversableLike.addString:(Lscala/collection/mutable/StringBuilder;)Lscala/collection/mutable/StringBuilder;
   13:	invokevirtual	#146; //Method scala/collection/mutable/StringBuilder.toString:()Ljava/lang/String;
   16:	areturn
  LineNumberTable: 
   line 759: 0

  LocalVariableTable: 
   Start  Length  Slot  Name   Signature
   0      17      0    $this       Lscala/collection/TraversableLike;


public static java.lang.String mkString(scala.collection.TraversableLike, java.lang.String);
  Code:
   Stack=3, Locals=2, Args_size=2
   0:	aload_0
   1:	new	#82; //class scala/collection/mutable/StringBuilder
   4:	dup
   5:	invokespecial	#142; //Method scala/collection/mutable/StringBuilder."<init>":()V
   8:	aload_1
   9:	invokeinterface	#110,  3; //InterfaceMethod scala/collection/TraversableLike.addString:(Lscala/collection/mutable/StringBuilder;Ljava/lang/String;)Lscala/collection/mutable/StringBuilder;
   14:	invokevirtual	#146; //Method scala/collection/mutable/StringBuilder.toString:()Ljava/lang/String;
   17:	areturn
  LineNumberTable: 
   line 752: 0

  LocalVariableTable: 
   Start  Length  Slot  Name   Signature
   0      18      0    $this       Lscala/collection/TraversableLike;
   0      18      1    sep       Ljava/lang/String;


public static java.lang.String mkString(scala.collection.TraversableLike, java.lang.String, java.lang.String, java.lang.String);
  Code:
   Stack=5, Locals=4, Args_size=4
   0:	aload_0
   1:	new	#82; //class scala/collection/mutable/StringBuilder
   4:	dup
   5:	invokespecial	#142; //Method scala/collection/mutable/StringBuilder."<init>":()V
   8:	aload_1
   9:	aload_2
   10:	aload_3
   11:	invokeinterface	#116,  5; //InterfaceMethod scala/collection/TraversableLike.addString:(Lscala/collection/mutable/StringBuilder;Ljava/lang/String;Ljava/lang/String;Ljava/lang/String;)Lscala/collection/mutable/StringBuilder;
   16:	invokevirtual	#146; //Method scala/collection/mutable/StringBuilder.toString:()Ljava/lang/String;
   19:	areturn
  LineNumberTable: 
   line 742: 0

  LocalVariableTable: 
   Start  Length  Slot  Name   Signature
   0      20      0    $this       Lscala/collection/TraversableLike;
   0      20      1    start       Ljava/lang/String;
   0      20      2    sep       Ljava/lang/String;
   0      20      3    end       Ljava/lang/String;


public static scala.collection.immutable.Set toSet(scala.collection.TraversableLike);
  Code:
   Stack=3, Locals=1, Args_size=1
   0:	getstatic	#156; //Field scala/collection/immutable/Set$.MODULE$:Lscala/collection/immutable/Set$;
   3:	getstatic	#161; //Field scala/Predef$.MODULE$:Lscala/Predef$;
   6:	iconst_0
   7:	anewarray	#47; //class java/lang/Object
   10:	invokevirtual	#165; //Method scala/Predef$.genericWrapArray:(Ljava/lang/Object;)Lscala/collection/mutable/WrappedArray;
   13:	invokevirtual	#169; //Method scala/collection/immutable/Set$.apply:(Lscala/collection/Seq;)Lscala/collection/Traversable;
   16:	checkcast	#171; //class scala/collection/generic/Addable
   19:	aload_0
   20:	invokeinterface	#175,  1; //InterfaceMethod scala/collection/TraversableLike.thisCollection:()Lscala/collection/Traversable;
   25:	invokeinterface	#179,  2; //InterfaceMethod scala/collection/generic/Addable.$plus$plus:(Lscala/collection/Traversable;)Lscala/collection/generic/Addable;
   30:	checkcast	#181; //class scala/collection/immutable/Set
   33:	areturn
  LineNumberTable: 
   line 727: 0

  LocalVariableTable: 
   Start  Length  Slot  Name   Signature
   0      34      0    $this       Lscala/collection/TraversableLike;


public static scala.collection.immutable.Stream toStream(scala.collection.TraversableLike);
  Code:
   Stack=1, Locals=1, Args_size=1
   0:	aload_0
   1:	invokeinterface	#187,  1; //InterfaceMethod scala/collection/TraversableLike.toList:()Lscala/collection/immutable/List;
   6:	invokevirtual	#192; //Method scala/collection/immutable/List.toStream:()Lscala/collection/immutable/Stream;
   9:	areturn
  LineNumberTable: 
   line 723: 0

  LocalVariableTable: 
   Start  Length  Slot  Name   Signature
   0      10      0    $this       Lscala/collection/TraversableLike;


public static scala.collection.mutable.IndexedSeq toIndexedSeq(scala.collection.TraversableLike);
  Code:
   Stack=2, Locals=1, Args_size=1
   0:	new	#196; //class scala/collection/mutable/ArrayBuffer
   3:	dup
   4:	invokespecial	#197; //Method scala/collection/mutable/ArrayBuffer."<init>":()V
   7:	aload_0
   8:	invokeinterface	#175,  1; //InterfaceMethod scala/collection/TraversableLike.thisCollection:()Lscala/collection/Traversable;
   13:	invokevirtual	#201; //Method scala/collection/mutable/ArrayBuffer.$plus$plus$eq:(Lscala/collection/Traversable;)Lscala/collection/mutable/ArrayBuffer;
   16:	areturn
  LineNumberTable: 
   line 719: 0

  LocalVariableTable: 
   Start  Length  Slot  Name   Signature
   0      17      0    $this       Lscala/collection/TraversableLike;


public static scala.collection.Seq toSeq(scala.collection.TraversableLike);
  Code:
   Stack=1, Locals=1, Args_size=1
   0:	aload_0
   1:	invokeinterface	#187,  1; //InterfaceMethod scala/collection/TraversableLike.toList:()Lscala/collection/immutable/List;
   6:	areturn
  LineNumberTable: 
   line 714: 0

  LocalVariableTable: 
   Start  Length  Slot  Name   Signature
   0      7      0    $this       Lscala/collection/TraversableLike;


public static scala.collection.Iterable toIterable(scala.collection.TraversableLike);
  Code:
   Stack=1, Locals=1, Args_size=1
   0:	aload_0
   1:	invokeinterface	#206,  1; //InterfaceMethod scala/collection/TraversableLike.toStream:()Lscala/collection/immutable/Stream;
   6:	areturn
  LineNumberTable: 
   line 709: 0

  LocalVariableTable: 
   Start  Length  Slot  Name   Signature
   0      7      0    $this       Lscala/collection/TraversableLike;


public static scala.collection.immutable.List toList(scala.collection.TraversableLike);
  Code:
   Stack=2, Locals=1, Args_size=1
   0:	new	#209; //class scala/collection/mutable/ListBuffer
   3:	dup
   4:	invokespecial	#210; //Method scala/collection/mutable/ListBuffer."<init>":()V
   7:	aload_0
   8:	invokeinterface	#175,  1; //InterfaceMethod scala/collection/TraversableLike.thisCollection:()Lscala/collection/Traversable;
   13:	invokeinterface	#215,  2; //InterfaceMethod scala/collection/generic/Growable.$plus$plus$eq:(Lscala/collection/Traversable;)Lscala/collection/generic/Growable;
   18:	checkcast	#209; //class scala/collection/mutable/ListBuffer
   21:	invokevirtual	#216; //Method scala/collection/mutable/ListBuffer.toList:()Lscala/collection/immutable/List;
   24:	areturn
  LineNumberTable: 
   line 704: 0

  LocalVariableTable: 
   Start  Length  Slot  Name   Signature
   0      25      0    $this       Lscala/collection/TraversableLike;


public static java.lang.Object toArray(scala.collection.TraversableLike, scala.reflect.ClassManifest);
  Code:
   Stack=3, Locals=3, Args_size=2
   0:	aload_1
   1:	aload_0
   2:	invokeinterface	#222,  1; //InterfaceMethod scala/collection/TraversableLike.size:()I
   7:	invokeinterface	#228,  2; //InterfaceMethod scala/reflect/ClassManifest.newArray:(I)Ljava/lang/Object;
   12:	astore_2
   13:	aload_0
   14:	aload_2
   15:	iconst_0
   16:	invokeinterface	#232,  3; //InterfaceMethod scala/collection/TraversableLike.copyToArray:(Ljava/lang/Object;I)V
   21:	aload_2
   22:	areturn
  LineNumberTable: 
   line 696: 0
   line 697: 13
   line 698: 21

  LocalVariableTable: 
   Start  Length  Slot  Name   Signature
   0      23      0    $this       Lscala/collection/TraversableLike;
   0      23      1    evidence$1       Lscala/reflect/ClassManifest;
   13      9      2    result       Ljava/lang/Object;


public static void copyToArray(scala.collection.TraversableLike, java.lang.Object, int);
  Code:
   Stack=5, Locals=3, Args_size=3
   0:	aload_0
   1:	aload_1
   2:	iload_2
   3:	getstatic	#242; //Field scala/runtime/ScalaRunTime$.MODULE$:Lscala/runtime/ScalaRunTime$;
   6:	aload_1
   7:	invokevirtual	#246; //Method scala/runtime/ScalaRunTime$.array_length:(Ljava/lang/Object;)I
   10:	iload_2
   11:	isub
   12:	invokeinterface	#249,  4; //InterfaceMethod scala/collection/TraversableLike.copyToArray:(Ljava/lang/Object;II)V
   17:	return
  LineNumberTable: 
   line 689: 0

  LocalVariableTable: 
   Start  Length  Slot  Name   Signature
   0      18      0    $this       Lscala/collection/TraversableLike;
   0      18      1    xs       Ljava/lang/Object;
   0      18      2    start       I


public static void copyToArray(scala.collection.TraversableLike, java.lang.Object, int, int);
  Code:
   Stack=7, Locals=6, Args_size=4
   0:	new	#253; //class scala/runtime/IntRef
   3:	dup
   4:	iload_2
   5:	invokespecial	#256; //Method scala/runtime/IntRef."<init>":(I)V
   8:	astore	4
   10:	getstatic	#161; //Field scala/Predef$.MODULE$:Lscala/Predef$;
   13:	iload_2
   14:	iload_3
   15:	iadd
   16:	invokevirtual	#260; //Method scala/Predef$.intWrapper:(I)Lscala/runtime/RichInt;
   19:	getstatic	#242; //Field scala/runtime/ScalaRunTime$.MODULE$:Lscala/runtime/ScalaRunTime$;
   22:	aload_1
   23:	invokevirtual	#246; //Method scala/runtime/ScalaRunTime$.array_length:(Ljava/lang/Object;)I
   26:	invokevirtual	#265; //Method scala/runtime/RichInt.min:(I)I
   29:	istore	5
   31:	getstatic	#270; //Field scala/collection/Traversable$.MODULE$:Lscala/collection/Traversable$;
   34:	invokevirtual	#274; //Method scala/collection/Traversable$.breaks:()Lscala/util/control/Breaks;
   37:	new	#276; //class scala/collection/TraversableLike$$anonfun$copyToArray$1
   40:	dup
   41:	aload_0
   42:	aload_1
   43:	aload	4
   45:	iload	5
   47:	invokespecial	#279; //Method scala/collection/TraversableLike$$anonfun$copyToArray$1."<init>":(Lscala/collection/TraversableLike;Ljava/lang/Object;Lscala/runtime/IntRef;I)V
   50:	invokevirtual	#285; //Method scala/util/control/Breaks.breakable:(Lscala/Function0;)V
   53:	return
  LineNumberTable: 
   line 668: 0
   line 669: 10
   line 670: 31
   line 671: 37
   line 670: 50

  LocalVariableTable: 
   Start  Length  Slot  Name   Signature
   0      54      0    $this       Lscala/collection/TraversableLike;
   0      54      1    xs$1       Ljava/lang/Object;
   0      54      2    start       I
   0      54      3    len       I
   10      43      4    i$5       Lscala/runtime/IntRef;
   31      22      5    end$1       I


public static void copyToBuffer(scala.collection.TraversableLike, scala.collection.mutable.Buffer);
  Code:
   Stack=5, Locals=2, Args_size=2
   0:	aload_0
   1:	new	#294; //class scala/collection/TraversableLike$$anonfun$copyToBuffer$1
   4:	dup
   5:	aload_0
   6:	aload_1
   7:	invokespecial	#296; //Method scala/collection/TraversableLike$$anonfun$copyToBuffer$1."<init>":(Lscala/collection/TraversableLike;Lscala/collection/mutable/Buffer;)V
   10:	invokeinterface	#135,  2; //InterfaceMethod scala/collection/TraversableLike.foreach:(Lscala/Function1;)V
   15:	return
  LineNumberTable: 
   line 654: 0

  LocalVariableTable: 
   Start  Length  Slot  Name   Signature
   0      16      0    $this       Lscala/collection/TraversableLike;
   0      16      1    dest$1       Lscala/collection/mutable/Buffer;


public static scala.Tuple2 splitAt(scala.collection.TraversableLike, int);
  Code:
   Stack=8, Locals=5, Args_size=2
   0:	aload_0
   1:	invokeinterface	#304,  1; //InterfaceMethod scala/collection/TraversableLike.newBuilder:()Lscala/collection/mutable/Builder;
   6:	astore_2
   7:	aload_0
   8:	invokeinterface	#304,  1; //InterfaceMethod scala/collection/TraversableLike.newBuilder:()Lscala/collection/mutable/Builder;
   13:	astore_3
   14:	new	#253; //class scala/runtime/IntRef
   17:	dup
   18:	iconst_0
   19:	invokespecial	#256; //Method scala/runtime/IntRef."<init>":(I)V
   22:	astore	4
   24:	aload_0
   25:	new	#306; //class scala/collection/TraversableLike$$anonfun$splitAt$1
   28:	dup
   29:	aload_0
   30:	iload_1
   31:	aload_2
   32:	aload_3
   33:	aload	4
   35:	invokespecial	#309; //Method scala/collection/TraversableLike$$anonfun$splitAt$1."<init>":(Lscala/collection/TraversableLike;ILscala/collection/mutable/Builder;Lscala/collection/mutable/Builder;Lscala/runtime/IntRef;)V
   38:	invokeinterface	#135,  2; //InterfaceMethod scala/collection/TraversableLike.foreach:(Lscala/Function1;)V
   43:	new	#311; //class scala/Tuple2
   46:	dup
   47:	aload_2
   48:	invokeinterface	#315,  1; //InterfaceMethod scala/collection/mutable/Builder.result:()Ljava/lang/Object;
   53:	aload_3
   54:	invokeinterface	#315,  1; //InterfaceMethod scala/collection/mutable/Builder.result:()Ljava/lang/Object;
   59:	invokespecial	#318; //Method scala/Tuple2."<init>":(Ljava/lang/Object;Ljava/lang/Object;)V
   62:	areturn
  LineNumberTable: 
   line 640: 0
   line 641: 14
   line 642: 24
   line 646: 43

  LocalVariableTable: 
   Start  Length  Slot  Name   Signature
   0      63      0    $this       Lscala/collection/TraversableLike;
   0      63      1    n$3       I
   7      55      2    l$3       Lscala/collection/mutable/Builder;
   14      48      3    r$3       Lscala/collection/mutable/Builder;
   24      38      4    i$4       Lscala/runtime/IntRef;


public static scala.Tuple2 span(scala.collection.TraversableLike, scala.Function1);
  Code:
   Stack=8, Locals=5, Args_size=2
   0:	aload_0
   1:	invokeinterface	#304,  1; //InterfaceMethod scala/collection/TraversableLike.newBuilder:()Lscala/collection/mutable/Builder;
   6:	astore_2
   7:	aload_0
   8:	invokeinterface	#304,  1; //InterfaceMethod scala/collection/TraversableLike.newBuilder:()Lscala/collection/mutable/Builder;
   13:	astore_3
   14:	new	#123; //class scala/runtime/BooleanRef
   17:	dup
   18:	iconst_1
   19:	invokespecial	#126; //Method scala/runtime/BooleanRef."<init>":(Z)V
   22:	astore	4
   24:	aload_0
   25:	new	#327; //class scala/collection/TraversableLike$$anonfun$span$1
   28:	dup
   29:	aload_0
   30:	aload_1
   31:	aload_2
   32:	aload_3
   33:	aload	4
   35:	invokespecial	#330; //Method scala/collection/TraversableLike$$anonfun$span$1."<init>":(Lscala/collection/TraversableLike;Lscala/Function1;Lscala/collection/mutable/Builder;Lscala/collection/mutable/Builder;Lscala/runtime/BooleanRef;)V
   38:	invokeinterface	#135,  2; //InterfaceMethod scala/collection/TraversableLike.foreach:(Lscala/Function1;)V
   43:	new	#311; //class scala/Tuple2
   46:	dup
   47:	aload_2
   48:	invokeinterface	#315,  1; //InterfaceMethod scala/collection/mutable/Builder.result:()Ljava/lang/Object;
   53:	aload_3
   54:	invokeinterface	#315,  1; //InterfaceMethod scala/collection/mutable/Builder.result:()Ljava/lang/Object;
   59:	invokespecial	#318; //Method scala/Tuple2."<init>":(Ljava/lang/Object;Ljava/lang/Object;)V
   62:	areturn
  LineNumberTable: 
   line 622: 0
   line 623: 14
   line 624: 24
   line 628: 43

  LocalVariableTable: 
   Start  Length  Slot  Name   Signature
   0      63      0    $this       Lscala/collection/TraversableLike;
   0      63      1    p$7       Lscala/Function1;
   7      55      2    l$2       Lscala/collection/mutable/Builder;
   14      48      3    r$2       Lscala/collection/mutable/Builder;
   24      38      4    toLeft$1       Lscala/runtime/BooleanRef;


public static java.lang.Object dropWhile(scala.collection.TraversableLike, scala.Function1);
  Code:
   Stack=7, Locals=4, Args_size=2
   0:	aload_0
   1:	invokeinterface	#304,  1; //InterfaceMethod scala/collection/TraversableLike.newBuilder:()Lscala/collection/mutable/Builder;
   6:	astore_2
   7:	new	#123; //class scala/runtime/BooleanRef
   10:	dup
   11:	iconst_0
   12:	invokespecial	#126; //Method scala/runtime/BooleanRef."<init>":(Z)V
   15:	astore_3
   16:	aload_0
   17:	new	#338; //class scala/collection/TraversableLike$$anonfun$dropWhile$1
   20:	dup
   21:	aload_0
   22:	aload_1
   23:	aload_2
   24:	aload_3
   25:	invokespecial	#341; //Method scala/collection/TraversableLike$$anonfun$dropWhile$1."<init>":(Lscala/collection/TraversableLike;Lscala/Function1;Lscala/collection/mutable/Builder;Lscala/runtime/BooleanRef;)V
   28:	invokeinterface	#135,  2; //InterfaceMethod scala/collection/TraversableLike.foreach:(Lscala/Function1;)V
   33:	aload_2
   34:	invokeinterface	#315,  1; //InterfaceMethod scala/collection/mutable/Builder.result:()Ljava/lang/Object;
   39:	areturn
  LineNumberTable: 
   line 604: 0
   line 605: 7
   line 606: 16
   line 610: 33

  LocalVariableTable: 
   Start  Length  Slot  Name   Signature
   0      40      0    $this       Lscala/collection/TraversableLike;
   0      40      1    p$6       Lscala/Function1;
   7      32      2    b$11       Lscala/collection/mutable/Builder;
   16      23      3    go$1       Lscala/runtime/BooleanRef;


public static java.lang.Object takeWhile(scala.collection.TraversableLike, scala.Function1);
  Code:
   Stack=6, Locals=3, Args_size=2
   0:	aload_0
   1:	invokeinterface	#304,  1; //InterfaceMethod scala/collection/TraversableLike.newBuilder:()Lscala/collection/mutable/Builder;
   6:	astore_2
   7:	getstatic	#270; //Field scala/collection/Traversable$.MODULE$:Lscala/collection/Traversable$;
   10:	invokevirtual	#274; //Method scala/collection/Traversable$.breaks:()Lscala/util/control/Breaks;
   13:	new	#347; //class scala/collection/TraversableLike$$anonfun$takeWhile$1
   16:	dup
   17:	aload_0
   18:	aload_1
   19:	aload_2
   20:	invokespecial	#350; //Method scala/collection/TraversableLike$$anonfun$takeWhile$1."<init>":(Lscala/collection/TraversableLike;Lscala/Function1;Lscala/collection/mutable/Builder;)V
   23:	invokevirtual	#285; //Method scala/util/control/Breaks.breakable:(Lscala/Function0;)V
   26:	aload_2
   27:	invokeinterface	#315,  1; //InterfaceMethod scala/collection/mutable/Builder.result:()Ljava/lang/Object;
   32:	areturn
  LineNumberTable: 
   line 587: 0
   line 588: 7
   line 589: 13
   line 588: 23
   line 594: 26

  LocalVariableTable: 
   Start  Length  Slot  Name   Signature
   0      33      0    $this       Lscala/collection/TraversableLike;
   0      33      1    p$5       Lscala/Function1;
   7      25      2    b$10       Lscala/collection/mutable/Builder;


public static java.lang.Object slice(scala.collection.TraversableLike, int, int);
  Code:
   Stack=8, Locals=5, Args_size=3
   0:	aload_0
   1:	invokeinterface	#304,  1; //InterfaceMethod scala/collection/TraversableLike.newBuilder:()Lscala/collection/mutable/Builder;
   6:	astore_3
   7:	new	#253; //class scala/runtime/IntRef
   10:	dup
   11:	iconst_0
   12:	invokespecial	#256; //Method scala/runtime/IntRef."<init>":(I)V
   15:	astore	4
   17:	getstatic	#270; //Field scala/collection/Traversable$.MODULE$:Lscala/collection/Traversable$;
   20:	invokevirtual	#274; //Method scala/collection/Traversable$.breaks:()Lscala/util/control/Breaks;
   23:	new	#355; //class scala/collection/TraversableLike$$anonfun$slice$1
   26:	dup
   27:	aload_0
   28:	iload_1
   29:	iload_2
   30:	aload_3
   31:	aload	4
   33:	invokespecial	#358; //Method scala/collection/TraversableLike$$anonfun$slice$1."<init>":(Lscala/collection/TraversableLike;IILscala/collection/mutable/Builder;Lscala/runtime/IntRef;)V
   36:	invokevirtual	#285; //Method scala/util/control/Breaks.breakable:(Lscala/Function0;)V
   39:	aload_3
   40:	invokeinterface	#315,  1; //InterfaceMethod scala/collection/mutable/Builder.result:()Ljava/lang/Object;
   45:	areturn
  LineNumberTable: 
   line 568: 0
   line 569: 7
   line 570: 17
   line 571: 23
   line 570: 36
   line 577: 39

  LocalVariableTable: 
   Start  Length  Slot  Name   Signature
   0      46      0    $this       Lscala/collection/TraversableLike;
   0      46      1    from$1       I
   0      46      2    until$1       I
   7      38      3    b$9       Lscala/collection/mutable/Builder;
   17      28      4    i$3       Lscala/runtime/IntRef;


public static java.lang.Object drop(scala.collection.TraversableLike, int);
  Code:
   Stack=7, Locals=4, Args_size=2
   0:	aload_0
   1:	invokeinterface	#304,  1; //InterfaceMethod scala/collection/TraversableLike.newBuilder:()Lscala/collection/mutable/Builder;
   6:	astore_2
   7:	new	#253; //class scala/runtime/IntRef
   10:	dup
   11:	iconst_0
   12:	invokespecial	#256; //Method scala/runtime/IntRef."<init>":(I)V
   15:	astore_3
   16:	aload_0
   17:	new	#366; //class scala/collection/TraversableLike$$anonfun$drop$1
   20:	dup
   21:	aload_0
   22:	iload_1
   23:	aload_2
   24:	aload_3
   25:	invokespecial	#369; //Method scala/collection/TraversableLike$$anonfun$drop$1."<init>":(Lscala/collection/TraversableLike;ILscala/collection/mutable/Builder;Lscala/runtime/IntRef;)V
   28:	invokeinterface	#135,  2; //InterfaceMethod scala/collection/TraversableLike.foreach:(Lscala/Function1;)V
   33:	aload_2
   34:	invokeinterface	#315,  1; //InterfaceMethod scala/collection/mutable/Builder.result:()Ljava/lang/Object;
   39:	areturn
  LineNumberTable: 
   line 548: 0
   line 549: 7
   line 550: 16
   line 554: 33

  LocalVariableTable: 
   Start  Length  Slot  Name   Signature
   0      40      0    $this       Lscala/collection/TraversableLike;
   0      40      1    n$2       I
   7      32      2    b$8       Lscala/collection/mutable/Builder;
   16      23      3    i$2       Lscala/runtime/IntRef;


public static java.lang.Object take(scala.collection.TraversableLike, int);
  Code:
   Stack=7, Locals=4, Args_size=2
   0:	aload_0
   1:	invokeinterface	#304,  1; //InterfaceMethod scala/collection/TraversableLike.newBuilder:()Lscala/collection/mutable/Builder;
   6:	astore_2
   7:	new	#253; //class scala/runtime/IntRef
   10:	dup
   11:	iconst_0
   12:	invokespecial	#256; //Method scala/runtime/IntRef."<init>":(I)V
   15:	astore_3
   16:	getstatic	#270; //Field scala/collection/Traversable$.MODULE$:Lscala/collection/Traversable$;
   19:	invokevirtual	#274; //Method scala/collection/Traversable$.breaks:()Lscala/util/control/Breaks;
   22:	new	#375; //class scala/collection/TraversableLike$$anonfun$take$1
   25:	dup
   26:	aload_0
   27:	iload_1
   28:	aload_2
   29:	aload_3
   30:	invokespecial	#376; //Method scala/collection/TraversableLike$$anonfun$take$1."<init>":(Lscala/collection/TraversableLike;ILscala/collection/mutable/Builder;Lscala/runtime/IntRef;)V
   33:	invokevirtual	#285; //Method scala/util/control/Breaks.breakable:(Lscala/Function0;)V
   36:	aload_2
   37:	invokeinterface	#315,  1; //InterfaceMethod scala/collection/mutable/Builder.result:()Ljava/lang/Object;
   42:	areturn
  LineNumberTable: 
   line 527: 0
   line 528: 7
   line 529: 16
   line 530: 22
   line 529: 33
   line 536: 36

  LocalVariableTable: 
   Start  Length  Slot  Name   Signature
   0      43      0    $this       Lscala/collection/TraversableLike;
   0      43      1    n$1       I
   7      35      2    b$7       Lscala/collection/mutable/Builder;
   16      26      3    i$1       Lscala/runtime/IntRef;


public static java.lang.Object init(scala.collection.TraversableLike);
  Code:
   Stack=7, Locals=4, Args_size=1
   0:	aload_0
   1:	invokeinterface	#384,  1; //InterfaceMethod scala/collection/TraversableLike.isEmpty:()Z
   6:	ifeq	20
   9:	new	#386; //class java/lang/UnsupportedOperationException
   12:	dup
   13:	ldc_w	#388; //String empty.init
   16:	invokespecial	#391; //Method java/lang/UnsupportedOperationException."<init>":(Ljava/lang/String;)V
   19:	athrow
   20:	new	#393; //class scala/runtime/ObjectRef
   23:	dup
   24:	aload_0
   25:	invokeinterface	#396,  1; //InterfaceMethod scala/collection/TraversableLike.head:()Ljava/lang/Object;
   30:	invokespecial	#399; //Method scala/runtime/ObjectRef."<init>":(Ljava/lang/Object;)V
   33:	astore_1
   34:	new	#123; //class scala/runtime/BooleanRef
   37:	dup
   38:	iconst_0
   39:	invokespecial	#126; //Method scala/runtime/BooleanRef."<init>":(Z)V
   42:	astore_2
   43:	aload_0
   44:	invokeinterface	#304,  1; //InterfaceMethod scala/collection/TraversableLike.newBuilder:()Lscala/collection/mutable/Builder;
   49:	astore_3
   50:	aload_0
   51:	new	#401; //class scala/collection/TraversableLike$$anonfun$init$1
   54:	dup
   55:	aload_0
   56:	aload_1
   57:	aload_2
   58:	aload_3
   59:	invokespecial	#404; //Method scala/collection/TraversableLike$$anonfun$init$1."<init>":(Lscala/collection/TraversableLike;Lscala/runtime/ObjectRef;Lscala/runtime/BooleanRef;Lscala/collection/mutable/Builder;)V
   62:	invokeinterface	#135,  2; //InterfaceMethod scala/collection/TraversableLike.foreach:(Lscala/Function1;)V
   67:	aload_3
   68:	invokeinterface	#315,  1; //InterfaceMethod scala/collection/mutable/Builder.result:()Ljava/lang/Object;
   73:	areturn
  LineNumberTable: 
   line 507: 0
   line 508: 20
   line 509: 34
   line 510: 43
   line 511: 50
   line 516: 67

  LocalVariableTable: 
   Start  Length  Slot  Name   Signature
   0      74      0    $this       Lscala/collection/TraversableLike;
   34      39      1    lst$2       Lscala/runtime/ObjectRef;
   43      30      2    follow$1       Lscala/runtime/BooleanRef;
   50      23      3    b$6       Lscala/collection/mutable/Builder;


public static scala.Option lastOption(scala.collection.TraversableLike);
  Code:
   Stack=3, Locals=1, Args_size=1
   0:	aload_0
   1:	invokeinterface	#384,  1; //InterfaceMethod scala/collection/TraversableLike.isEmpty:()Z
   6:	ifeq	15
   9:	getstatic	#415; //Field scala/None$.MODULE$:Lscala/None$;
   12:	goto	28
   15:	new	#417; //class scala/Some
   18:	dup
   19:	aload_0
   20:	invokeinterface	#420,  1; //InterfaceMethod scala/collection/TraversableLike.last:()Ljava/lang/Object;
   25:	invokespecial	#421; //Method scala/Some."<init>":(Ljava/lang/Object;)V
   28:	areturn
  LineNumberTable: 
   line 500: 0

  LocalVariableTable: 
   Start  Length  Slot  Name   Signature
   0      29      0    $this       Lscala/collection/TraversableLike;


public static java.lang.Object last(scala.collection.TraversableLike);
  Code:
   Stack=5, Locals=2, Args_size=1
   0:	new	#393; //class scala/runtime/ObjectRef
   3:	dup
   4:	aload_0
   5:	invokeinterface	#396,  1; //InterfaceMethod scala/collection/TraversableLike.head:()Ljava/lang/Object;
   10:	invokespecial	#399; //Method scala/runtime/ObjectRef."<init>":(Ljava/lang/Object;)V
   13:	astore_1
   14:	aload_0
   15:	new	#423; //class scala/collection/TraversableLike$$anonfun$last$1
   18:	dup
   19:	aload_0
   20:	aload_1
   21:	invokespecial	#426; //Method scala/collection/TraversableLike$$anonfun$last$1."<init>":(Lscala/collection/TraversableLike;Lscala/runtime/ObjectRef;)V
   24:	invokeinterface	#135,  2; //InterfaceMethod scala/collection/TraversableLike.foreach:(Lscala/Function1;)V
   29:	aload_1
   30:	getfield	#429; //Field scala/runtime/ObjectRef.elem:Ljava/lang/Object;
   33:	areturn
  LineNumberTable: 
   line 488: 0
   line 489: 14
   line 491: 20
   line 489: 21
   line 491: 29

  LocalVariableTable: 
   Start  Length  Slot  Name   Signature
   0      34      0    $this       Lscala/collection/TraversableLike;
   14      19      1    lst$1       Lscala/runtime/ObjectRef;


public static java.lang.Object tail(scala.collection.TraversableLike);
  Code:
   Stack=4, Locals=2, Args_size=1
   0:	aload_0
   1:	invokeinterface	#384,  1; //InterfaceMethod scala/collection/TraversableLike.isEmpty:()Z
   6:	ifeq	13
   9:	iconst_0
   10:	goto	14
   13:	iconst_1
   14:	istore_1
   15:	iload_1
   16:	ifeq	27
   19:	aload_0
   20:	iconst_1
   21:	invokeinterface	#433,  2; //InterfaceMethod scala/collection/TraversableLike.drop:(I)Ljava/lang/Object;
   26:	areturn
   27:	new	#435; //class java/lang/IllegalArgumentException
   30:	dup
   31:	new	#82; //class scala/collection/mutable/StringBuilder
   34:	dup
   35:	invokespecial	#85; //Method scala/collection/mutable/StringBuilder."<init>":()V
   38:	ldc_w	#437; //String requirement failed: 
   41:	invokevirtual	#91; //Method scala/collection/mutable/StringBuilder.append:(Ljava/lang/Object;)Lscala/collection/mutable/StringBuilder;
   44:	ldc_w	#439; //String <empty>.tail
   47:	invokevirtual	#91; //Method scala/collection/mutable/StringBuilder.append:(Ljava/lang/Object;)Lscala/collection/mutable/StringBuilder;
   50:	invokevirtual	#95; //Method scala/collection/mutable/StringBuilder.toString:()Ljava/lang/String;
   53:	invokespecial	#440; //Method java/lang/IllegalArgumentException."<init>":(Ljava/lang/String;)V
   56:	athrow
  LineNumberTable: 
   line 478: 0
   line 479: 19
   line 478: 27

  LocalVariableTable: 
   Start  Length  Slot  Name   Signature
   0      57      0    $this       Lscala/collection/TraversableLike;
   19      38      1    requirement0       Z


public static scala.Option headOption(scala.collection.TraversableLike);
  Code:
   Stack=3, Locals=1, Args_size=1
   0:	aload_0
   1:	invokeinterface	#384,  1; //InterfaceMethod scala/collection/TraversableLike.isEmpty:()Z
   6:	ifeq	15
   9:	getstatic	#415; //Field scala/None$.MODULE$:Lscala/None$;
   12:	goto	28
   15:	new	#417; //class scala/Some
   18:	dup
   19:	aload_0
   20:	invokeinterface	#396,  1; //InterfaceMethod scala/collection/TraversableLike.head:()Ljava/lang/Object;
   25:	invokespecial	#421; //Method scala/Some."<init>":(Ljava/lang/Object;)V
   28:	areturn
  LineNumberTable: 
   line 471: 0

  LocalVariableTable: 
   Start  Length  Slot  Name   Signature
   0      29      0    $this       Lscala/collection/TraversableLike;


public static java.lang.Object head(scala.collection.TraversableLike);
  Code:
   Stack=5, Locals=2, Args_size=1
   0:	new	#393; //class scala/runtime/ObjectRef
   3:	dup
   4:	new	#445; //class scala/collection/TraversableLike$$anonfun$1
   7:	dup
   8:	aload_0
   9:	invokespecial	#446; //Method scala/collection/TraversableLike$$anonfun$1."<init>":(Lscala/collection/TraversableLike;)V
   12:	invokespecial	#399; //Method scala/runtime/ObjectRef."<init>":(Ljava/lang/Object;)V
   15:	astore_1
   16:	getstatic	#270; //Field scala/collection/Traversable$.MODULE$:Lscala/collection/Traversable$;
   19:	invokevirtual	#274; //Method scala/collection/Traversable$.breaks:()Lscala/util/control/Breaks;
   22:	new	#448; //class scala/collection/TraversableLike$$anonfun$head$1
   25:	dup
   26:	aload_0
   27:	aload_1
   28:	invokespecial	#449; //Method scala/collection/TraversableLike$$anonfun$head$1."<init>":(Lscala/collection/TraversableLike;Lscala/runtime/ObjectRef;)V
   31:	invokevirtual	#285; //Method scala/util/control/Breaks.breakable:(Lscala/Function0;)V
   34:	aload_1
   35:	getfield	#429; //Field scala/runtime/ObjectRef.elem:Ljava/lang/Object;
   38:	checkcast	#451; //class scala/Function0
   41:	invokeinterface	#453,  1; //InterfaceMethod scala/Function0.apply:()Ljava/lang/Object;
   46:	areturn
  LineNumberTable: 
   line 457: 0
   line 458: 16
   line 459: 22
   line 464: 27
   line 459: 28
   line 458: 31
   line 464: 34

  LocalVariableTable: 
   Start  Length  Slot  Name   Signature
   0      47      0    $this       Lscala/collection/TraversableLike;
   16      30      1    result$8       Lscala/runtime/ObjectRef;


public static java.lang.Object max(scala.collection.TraversableLike, scala.math.Ordering);
  Code:
   Stack=6, Locals=4, Args_size=2
   0:	aload_0
   1:	invokeinterface	#384,  1; //InterfaceMethod scala/collection/TraversableLike.isEmpty:()Z
   6:	ifeq	13
   9:	iconst_0
   10:	goto	14
   13:	iconst_1
   14:	istore_2
   15:	iload_2
   16:	ifeq	54
   19:	new	#393; //class scala/runtime/ObjectRef
   22:	dup
   23:	aload_0
   24:	invokeinterface	#396,  1; //InterfaceMethod scala/collection/TraversableLike.head:()Ljava/lang/Object;
   29:	invokespecial	#399; //Method scala/runtime/ObjectRef."<init>":(Ljava/lang/Object;)V
   32:	astore_3
   33:	aload_0
   34:	new	#458; //class scala/collection/TraversableLike$$anonfun$max$2
   37:	dup
   38:	aload_0
   39:	aload_1
   40:	aload_3
   41:	invokespecial	#461; //Method scala/collection/TraversableLike$$anonfun$max$2."<init>":(Lscala/collection/TraversableLike;Lscala/math/Ordering;Lscala/runtime/ObjectRef;)V
   44:	invokeinterface	#135,  2; //InterfaceMethod scala/collection/TraversableLike.foreach:(Lscala/Function1;)V
   49:	aload_3
   50:	getfield	#429; //Field scala/runtime/ObjectRef.elem:Ljava/lang/Object;
   53:	areturn
   54:	new	#435; //class java/lang/IllegalArgumentException
   57:	dup
   58:	new	#82; //class scala/collection/mutable/StringBuilder
   61:	dup
   62:	invokespecial	#85; //Method scala/collection/mutable/StringBuilder."<init>":()V
   65:	ldc_w	#437; //String requirement failed: 
   68:	invokevirtual	#91; //Method scala/collection/mutable/StringBuilder.append:(Ljava/lang/Object;)Lscala/collection/mutable/StringBuilder;
   71:	ldc_w	#463; //String <empty>.max
   74:	invokevirtual	#91; //Method scala/collection/mutable/StringBuilder.append:(Ljava/lang/Object;)Lscala/collection/mutable/StringBuilder;
   77:	invokevirtual	#95; //Method scala/collection/mutable/StringBuilder.toString:()Ljava/lang/String;
   80:	invokespecial	#440; //Method java/lang/IllegalArgumentException."<init>":(Ljava/lang/String;)V
   83:	athrow
  LineNumberTable: 
   line 444: 0
   line 445: 19
   line 446: 33
   line 448: 40
   line 446: 41
   line 448: 49
   line 444: 54

  LocalVariableTable: 
   Start  Length  Slot  Name   Signature
   0      84      0    $this       Lscala/collection/TraversableLike;
   0      84      1    cmp$2       Lscala/math/Ordering;
   19      65      2    requirement0       Z
   33      20      3    acc$4       Lscala/runtime/ObjectRef;


public static java.lang.Object min(scala.collection.TraversableLike, scala.math.Ordering);
  Code:
   Stack=6, Locals=4, Args_size=2
   0:	aload_0
   1:	invokeinterface	#384,  1; //InterfaceMethod scala/collection/TraversableLike.isEmpty:()Z
   6:	ifeq	13
   9:	iconst_0
   10:	goto	14
   13:	iconst_1
   14:	istore_2
   15:	iload_2
   16:	ifeq	54
   19:	new	#393; //class scala/runtime/ObjectRef
   22:	dup
   23:	aload_0
   24:	invokeinterface	#396,  1; //InterfaceMethod scala/collection/TraversableLike.head:()Ljava/lang/Object;
   29:	invokespecial	#399; //Method scala/runtime/ObjectRef."<init>":(Ljava/lang/Object;)V
   32:	astore_3
   33:	aload_0
   34:	new	#468; //class scala/collection/TraversableLike$$anonfun$min$2
   37:	dup
   38:	aload_0
   39:	aload_1
   40:	aload_3
   41:	invokespecial	#469; //Method scala/collection/TraversableLike$$anonfun$min$2."<init>":(Lscala/collection/TraversableLike;Lscala/math/Ordering;Lscala/runtime/ObjectRef;)V
   44:	invokeinterface	#135,  2; //InterfaceMethod scala/collection/TraversableLike.foreach:(Lscala/Function1;)V
   49:	aload_3
   50:	getfield	#429; //Field scala/runtime/ObjectRef.elem:Ljava/lang/Object;
   53:	areturn
   54:	new	#435; //class java/lang/IllegalArgumentException
   57:	dup
   58:	new	#82; //class scala/collection/mutable/StringBuilder
   61:	dup
   62:	invokespecial	#85; //Method scala/collection/mutable/StringBuilder."<init>":()V
   65:	ldc_w	#437; //String requirement failed: 
   68:	invokevirtual	#91; //Method scala/collection/mutable/StringBuilder.append:(Ljava/lang/Object;)Lscala/collection/mutable/StringBuilder;
   71:	ldc_w	#471; //String <empty>.min
   74:	invokevirtual	#91; //Method scala/collection/mutable/StringBuilder.append:(Ljava/lang/Object;)Lscala/collection/mutable/StringBuilder;
   77:	invokevirtual	#95; //Method scala/collection/mutable/StringBuilder.toString:()Ljava/lang/String;
   80:	invokespecial	#440; //Method java/lang/IllegalArgumentException."<init>":(Ljava/lang/String;)V
   83:	athrow
  LineNumberTable: 
   line 435: 0
   line 436: 19
   line 437: 33
   line 439: 40
   line 437: 41
   line 439: 49
   line 435: 54

  LocalVariableTable: 
   Start  Length  Slot  Name   Signature
   0      84      0    $this       Lscala/collection/TraversableLike;
   0      84      1    cmp$1       Lscala/math/Ordering;
   19      65      2    requirement0       Z
   33      20      3    acc$3       Lscala/runtime/ObjectRef;


public static java.lang.Object product(scala.collection.TraversableLike, scala.math.Numeric);
  Code:
   Stack=6, Locals=3, Args_size=2
   0:	new	#393; //class scala/runtime/ObjectRef
   3:	dup
   4:	aload_1
   5:	invokeinterface	#480,  1; //InterfaceMethod scala/math/Numeric.one:()Ljava/lang/Object;
   10:	invokespecial	#399; //Method scala/runtime/ObjectRef."<init>":(Ljava/lang/Object;)V
   13:	astore_2
   14:	aload_0
   15:	new	#482; //class scala/collection/TraversableLike$$anonfun$product$1
   18:	dup
   19:	aload_0
   20:	aload_1
   21:	aload_2
   22:	invokespecial	#485; //Method scala/collection/TraversableLike$$anonfun$product$1."<init>":(Lscala/collection/TraversableLike;Lscala/math/Numeric;Lscala/runtime/ObjectRef;)V
   25:	invokeinterface	#135,  2; //InterfaceMethod scala/collection/TraversableLike.foreach:(Lscala/Function1;)V
   30:	aload_2
   31:	getfield	#429; //Field scala/runtime/ObjectRef.elem:Ljava/lang/Object;
   34:	areturn
  LineNumberTable: 
   line 428: 0
   line 429: 14
   line 430: 21
   line 429: 22
   line 430: 30

  LocalVariableTable: 
   Start  Length  Slot  Name   Signature
   0      35      0    $this       Lscala/collection/TraversableLike;
   0      35      1    num$2       Lscala/math/Numeric;
   14      20      2    acc$2       Lscala/runtime/ObjectRef;


public static java.lang.Object sum(scala.collection.TraversableLike, scala.math.Numeric);
  Code:
   Stack=6, Locals=3, Args_size=2
   0:	new	#393; //class scala/runtime/ObjectRef
   3:	dup
   4:	aload_1
   5:	invokeinterface	#492,  1; //InterfaceMethod scala/math/Numeric.zero:()Ljava/lang/Object;
   10:	invokespecial	#399; //Method scala/runtime/ObjectRef."<init>":(Ljava/lang/Object;)V
   13:	astore_2
   14:	aload_0
   15:	new	#494; //class scala/collection/TraversableLike$$anonfun$sum$1
   18:	dup
   19:	aload_0
   20:	aload_1
   21:	aload_2
   22:	invokespecial	#495; //Method scala/collection/TraversableLike$$anonfun$sum$1."<init>":(Lscala/collection/TraversableLike;Lscala/math/Numeric;Lscala/runtime/ObjectRef;)V
   25:	invokeinterface	#135,  2; //InterfaceMethod scala/collection/TraversableLike.foreach:(Lscala/Function1;)V
   30:	aload_2
   31:	getfield	#429; //Field scala/runtime/ObjectRef.elem:Ljava/lang/Object;
   34:	areturn
  LineNumberTable: 
   line 421: 0
   line 422: 14
   line 423: 21
   line 422: 22
   line 423: 30

  LocalVariableTable: 
   Start  Length  Slot  Name   Signature
   0      35      0    $this       Lscala/collection/TraversableLike;
   0      35      1    num$1       Lscala/math/Numeric;
   14      20      2    acc$1       Lscala/runtime/ObjectRef;


public static scala.Option reduceRightOption(scala.collection.TraversableLike, scala.Function2);
  Code:
   Stack=4, Locals=2, Args_size=2
   0:	aload_0
   1:	invokeinterface	#384,  1; //InterfaceMethod scala/collection/TraversableLike.isEmpty:()Z
   6:	ifeq	15
   9:	getstatic	#415; //Field scala/None$.MODULE$:Lscala/None$;
   12:	goto	29
   15:	new	#417; //class scala/Some
   18:	dup
   19:	aload_0
   20:	aload_1
   21:	invokeinterface	#503,  2; //InterfaceMethod scala/collection/TraversableLike.reduceRight:(Lscala/Function2;)Ljava/lang/Object;
   26:	invokespecial	#421; //Method scala/Some."<init>":(Ljava/lang/Object;)V
   29:	areturn
  LineNumberTable: 
   line 416: 0

  LocalVariableTable: 
   Start  Length  Slot  Name   Signature
   0      30      0    $this       Lscala/collection/TraversableLike;
   0      30      1    op       Lscala/Function2;


public static java.lang.Object reduceRight(scala.collection.TraversableLike, scala.Function2);
  Code:
   Stack=5, Locals=3, Args_size=2
   0:	aload_0
   1:	invokeinterface	#384,  1; //InterfaceMethod scala/collection/TraversableLike.isEmpty:()Z
   6:	ifeq	20
   9:	new	#386; //class java/lang/UnsupportedOperationException
   12:	dup
   13:	ldc_w	#508; //String empty.reduceRight
   16:	invokespecial	#391; //Method java/lang/UnsupportedOperationException."<init>":(Ljava/lang/String;)V
   19:	athrow
   20:	new	#393; //class scala/runtime/ObjectRef
   23:	dup
   24:	getstatic	#513; //Field scala/collection/immutable/Nil$.MODULE$:Lscala/collection/immutable/Nil$;
   27:	invokespecial	#399; //Method scala/runtime/ObjectRef."<init>":(Ljava/lang/Object;)V
   30:	astore_2
   31:	aload_0
   32:	new	#515; //class scala/collection/TraversableLike$$anonfun$reduceRight$1
   35:	dup
   36:	aload_0
   37:	aload_2
   38:	invokespecial	#516; //Method scala/collection/TraversableLike$$anonfun$reduceRight$1."<init>":(Lscala/collection/TraversableLike;Lscala/runtime/ObjectRef;)V
   41:	invokeinterface	#135,  2; //InterfaceMethod scala/collection/TraversableLike.foreach:(Lscala/Function1;)V
   46:	aload_2
   47:	getfield	#429; //Field scala/runtime/ObjectRef.elem:Ljava/lang/Object;
   50:	checkcast	#189; //class scala/collection/immutable/List
   53:	new	#518; //class scala/collection/TraversableLike$$anonfun$reduceRight$2
   56:	dup
   57:	aload_0
   58:	aload_1
   59:	invokespecial	#521; //Method scala/collection/TraversableLike$$anonfun$reduceRight$2."<init>":(Lscala/collection/TraversableLike;Lscala/Function2;)V
   62:	invokeinterface	#526,  2; //InterfaceMethod scala/collection/LinearSeqLike.reduceLeft:(Lscala/Function2;)Ljava/lang/Object;
   67:	areturn
  LineNumberTable: 
   line 401: 0
   line 402: 20
   line 403: 31
   line 404: 37
   line 403: 38
   line 404: 46

  LocalVariableTable: 
   Start  Length  Slot  Name   Signature
   0      68      0    $this       Lscala/collection/TraversableLike;
   0      68      1    op$4       Lscala/Function2;
   31      36      2    elems$2       Lscala/runtime/ObjectRef;


public static scala.Option reduceLeftOption(scala.collection.TraversableLike, scala.Function2);
  Code:
   Stack=4, Locals=2, Args_size=2
   0:	aload_0
   1:	invokeinterface	#384,  1; //InterfaceMethod scala/collection/TraversableLike.isEmpty:()Z
   6:	ifeq	15
   9:	getstatic	#415; //Field scala/None$.MODULE$:Lscala/None$;
   12:	goto	29
   15:	new	#417; //class scala/Some
   18:	dup
   19:	aload_0
   20:	aload_1
   21:	invokeinterface	#530,  2; //InterfaceMethod scala/collection/TraversableLike.reduceLeft:(Lscala/Function2;)Ljava/lang/Object;
   26:	invokespecial	#421; //Method scala/Some."<init>":(Ljava/lang/Object;)V
   29:	areturn
  LineNumberTable: 
   line 384: 0

  LocalVariableTable: 
   Start  Length  Slot  Name   Signature
   0      30      0    $this       Lscala/collection/TraversableLike;
   0      30      1    op       Lscala/Function2;


public static java.lang.Object reduceLeft(scala.collection.TraversableLike, scala.Function2);
  Code:
   Stack=7, Locals=4, Args_size=2
   0:	aload_0
   1:	invokeinterface	#384,  1; //InterfaceMethod scala/collection/TraversableLike.isEmpty:()Z
   6:	ifeq	20
   9:	new	#386; //class java/lang/UnsupportedOperationException
   12:	dup
   13:	ldc_w	#532; //String empty.reduceLeft
   16:	invokespecial	#391; //Method java/lang/UnsupportedOperationException."<init>":(Ljava/lang/String;)V
   19:	athrow
   20:	new	#393; //class scala/runtime/ObjectRef
   23:	dup
   24:	aload_0
   25:	invokeinterface	#396,  1; //InterfaceMethod scala/collection/TraversableLike.head:()Ljava/lang/Object;
   30:	invokespecial	#399; //Method scala/runtime/ObjectRef."<init>":(Ljava/lang/Object;)V
   33:	astore_2
   34:	new	#123; //class scala/runtime/BooleanRef
   37:	dup
   38:	iconst_1
   39:	invokespecial	#126; //Method scala/runtime/BooleanRef."<init>":(Z)V
   42:	astore_3
   43:	aload_0
   44:	new	#534; //class scala/collection/TraversableLike$$anonfun$reduceLeft$1
   47:	dup
   48:	aload_0
   49:	aload_1
   50:	aload_2
   51:	aload_3
   52:	invokespecial	#537; //Method scala/collection/TraversableLike$$anonfun$reduceLeft$1."<init>":(Lscala/collection/TraversableLike;Lscala/Function2;Lscala/runtime/ObjectRef;Lscala/runtime/BooleanRef;)V
   55:	invokeinterface	#135,  2; //InterfaceMethod scala/collection/TraversableLike.foreach:(Lscala/Function1;)V
   60:	aload_2
   61:	getfield	#429; //Field scala/runtime/ObjectRef.elem:Ljava/lang/Object;
   64:	areturn
  LineNumberTable: 
   line 366: 0
   line 367: 20
   line 368: 34
   line 369: 43
   line 372: 50
   line 369: 51
   line 372: 60

  LocalVariableTable: 
   Start  Length  Slot  Name   Signature
   0      65      0    $this       Lscala/collection/TraversableLike;
   0      65      1    op$3       Lscala/Function2;
   34      30      2    result$7       Lscala/runtime/ObjectRef;
   43      21      3    first$1       Lscala/runtime/BooleanRef;


public static java.lang.Object $colon$bslash(scala.collection.TraversableLike, java.lang.Object, scala.Function2);
  Code:
   Stack=3, Locals=3, Args_size=3
   0:	aload_0
   1:	aload_1
   2:	aload_2
   3:	invokeinterface	#546,  3; //InterfaceMethod scala/collection/TraversableLike.foldRight:(Ljava/lang/Object;Lscala/Function2;)Ljava/lang/Object;
   8:	areturn
  LineNumberTable: 
   line 352: 0

  LocalVariableTable: 
   Start  Length  Slot  Name   Signature
   0      9      0    $this       Lscala/collection/TraversableLike;
   0      9      1    z       Ljava/lang/Object;
   0      9      2    op       Lscala/Function2;


public static java.lang.Object foldRight(scala.collection.TraversableLike, java.lang.Object, scala.Function2);
  Code:
   Stack=6, Locals=4, Args_size=3
   0:	new	#393; //class scala/runtime/ObjectRef
   3:	dup
   4:	getstatic	#513; //Field scala/collection/immutable/Nil$.MODULE$:Lscala/collection/immutable/Nil$;
   7:	invokespecial	#399; //Method scala/runtime/ObjectRef."<init>":(Ljava/lang/Object;)V
   10:	astore_3
   11:	aload_0
   12:	new	#549; //class scala/collection/TraversableLike$$anonfun$foldRight$1
   15:	dup
   16:	aload_0
   17:	aload_3
   18:	invokespecial	#550; //Method scala/collection/TraversableLike$$anonfun$foldRight$1."<init>":(Lscala/collection/TraversableLike;Lscala/runtime/ObjectRef;)V
   21:	invokeinterface	#135,  2; //InterfaceMethod scala/collection/TraversableLike.foreach:(Lscala/Function1;)V
   26:	aload_3
   27:	getfield	#429; //Field scala/runtime/ObjectRef.elem:Ljava/lang/Object;
   30:	checkcast	#189; //class scala/collection/immutable/List
   33:	aload_1
   34:	new	#552; //class scala/collection/TraversableLike$$anonfun$foldRight$2
   37:	dup
   38:	aload_0
   39:	aload_2
   40:	invokespecial	#553; //Method scala/collection/TraversableLike$$anonfun$foldRight$2."<init>":(Lscala/collection/TraversableLike;Lscala/Function2;)V
   43:	invokeinterface	#556,  3; //InterfaceMethod scala/collection/LinearSeqLike.foldLeft:(Ljava/lang/Object;Lscala/Function2;)Ljava/lang/Object;
   48:	areturn
  LineNumberTable: 
   line 341: 0
   line 342: 11
   line 343: 17
   line 342: 18
   line 343: 26

  LocalVariableTable: 
   Start  Length  Slot  Name   Signature
   0      49      0    $this       Lscala/collection/TraversableLike;
   0      49      1    z       Ljava/lang/Object;
   0      49      2    op$2       Lscala/Function2;
   11      37      3    elems$1       Lscala/runtime/ObjectRef;


public static java.lang.Object $div$colon(scala.collection.TraversableLike, java.lang.Object, scala.Function2);
  Code:
   Stack=3, Locals=3, Args_size=3
   0:	aload_0
   1:	aload_1
   2:	aload_2
   3:	invokeinterface	#560,  3; //InterfaceMethod scala/collection/TraversableLike.foldLeft:(Ljava/lang/Object;Lscala/Function2;)Ljava/lang/Object;
   8:	areturn
  LineNumberTable: 
   line 328: 0

  LocalVariableTable: 
   Start  Length  Slot  Name   Signature
   0      9      0    $this       Lscala/collection/TraversableLike;
   0      9      1    z       Ljava/lang/Object;
   0      9      2    op       Lscala/Function2;


public static java.lang.Object foldLeft(scala.collection.TraversableLike, java.lang.Object, scala.Function2);
  Code:
   Stack=6, Locals=4, Args_size=3
   0:	new	#393; //class scala/runtime/ObjectRef
   3:	dup
   4:	aload_1
   5:	invokespecial	#399; //Method scala/runtime/ObjectRef."<init>":(Ljava/lang/Object;)V
   8:	astore_3
   9:	aload_0
   10:	new	#562; //class scala/collection/TraversableLike$$anonfun$foldLeft$1
   13:	dup
   14:	aload_0
   15:	aload_2
   16:	aload_3
   17:	invokespecial	#565; //Method scala/collection/TraversableLike$$anonfun$foldLeft$1."<init>":(Lscala/collection/TraversableLike;Lscala/Function2;Lscala/runtime/ObjectRef;)V
   20:	invokeinterface	#135,  2; //InterfaceMethod scala/collection/TraversableLike.foreach:(Lscala/Function1;)V
   25:	aload_3
   26:	getfield	#429; //Field scala/runtime/ObjectRef.elem:Ljava/lang/Object;
   29:	areturn
  LineNumberTable: 
   line 315: 0
   line 316: 9
   line 318: 16
   line 316: 17
   line 318: 25

  LocalVariableTable: 
   Start  Length  Slot  Name   Signature
   0      30      0    $this       Lscala/collection/TraversableLike;
   0      30      1    z       Ljava/lang/Object;
   0      30      2    op$1       Lscala/Function2;
   9      20      3    result$6       Lscala/runtime/ObjectRef;


public static scala.Option find(scala.collection.TraversableLike, scala.Function1);
  Code:
   Stack=6, Locals=3, Args_size=2
   0:	new	#393; //class scala/runtime/ObjectRef
   3:	dup
   4:	getstatic	#415; //Field scala/None$.MODULE$:Lscala/None$;
   7:	invokespecial	#399; //Method scala/runtime/ObjectRef."<init>":(Ljava/lang/Object;)V
   10:	astore_2
   11:	getstatic	#270; //Field scala/collection/Traversable$.MODULE$:Lscala/collection/Traversable$;
   14:	invokevirtual	#274; //Method scala/collection/Traversable$.breaks:()Lscala/util/control/Breaks;
   17:	new	#571; //class scala/collection/TraversableLike$$anonfun$find$1
   20:	dup
   21:	aload_0
   22:	aload_1
   23:	aload_2
   24:	invokespecial	#574; //Method scala/collection/TraversableLike$$anonfun$find$1."<init>":(Lscala/collection/TraversableLike;Lscala/Function1;Lscala/runtime/ObjectRef;)V
   27:	invokevirtual	#285; //Method scala/util/control/Breaks.breakable:(Lscala/Function0;)V
   30:	aload_2
   31:	getfield	#429; //Field scala/runtime/ObjectRef.elem:Ljava/lang/Object;
   34:	checkcast	#576; //class scala/Option
   37:	areturn
  LineNumberTable: 
   line 295: 0
   line 296: 11
   line 297: 17
   line 300: 23
   line 297: 24
   line 296: 27
   line 300: 30

  LocalVariableTable: 
   Start  Length  Slot  Name   Signature
   0      38      0    $this       Lscala/collection/TraversableLike;
   0      38      1    p$1       Lscala/Function1;
   11      26      2    result$5       Lscala/runtime/ObjectRef;


public static int count(scala.collection.TraversableLike, scala.Function1);
  Code:
   Stack=6, Locals=3, Args_size=2
   0:	new	#253; //class scala/runtime/IntRef
   3:	dup
   4:	iconst_0
   5:	invokespecial	#256; //Method scala/runtime/IntRef."<init>":(I)V
   8:	astore_2
   9:	aload_0
   10:	new	#582; //class scala/collection/TraversableLike$$anonfun$count$1
   13:	dup
   14:	aload_0
   15:	aload_1
   16:	aload_2
   17:	invokespecial	#585; //Method scala/collection/TraversableLike$$anonfun$count$1."<init>":(Lscala/collection/TraversableLike;Lscala/Function1;Lscala/runtime/IntRef;)V
   20:	invokeinterface	#135,  2; //InterfaceMethod scala/collection/TraversableLike.foreach:(Lscala/Function1;)V
   25:	aload_2
   26:	getfield	#587; //Field scala/runtime/IntRef.elem:I
   29:	ireturn
  LineNumberTable: 
   line 278: 0
   line 279: 9
   line 282: 16
   line 279: 17
   line 282: 25

  LocalVariableTable: 
   Start  Length  Slot  Name   Signature
   0      30      0    $this       Lscala/collection/TraversableLike;
   0      30      1    p$8       Lscala/Function1;
   9      20      2    cnt$1       Lscala/runtime/IntRef;


public static boolean exists(scala.collection.TraversableLike, scala.Function1);
  Code:
   Stack=6, Locals=3, Args_size=2
   0:	new	#123; //class scala/runtime/BooleanRef
   3:	dup
   4:	iconst_0
   5:	invokespecial	#126; //Method scala/runtime/BooleanRef."<init>":(Z)V
   8:	astore_2
   9:	getstatic	#270; //Field scala/collection/Traversable$.MODULE$:Lscala/collection/Traversable$;
   12:	invokevirtual	#274; //Method scala/collection/Traversable$.breaks:()Lscala/util/control/Breaks;
   15:	new	#593; //class scala/collection/TraversableLike$$anonfun$exists$1
   18:	dup
   19:	aload_0
   20:	aload_1
   21:	aload_2
   22:	invokespecial	#596; //Method scala/collection/TraversableLike$$anonfun$exists$1."<init>":(Lscala/collection/TraversableLike;Lscala/Function1;Lscala/runtime/BooleanRef;)V
   25:	invokevirtual	#285; //Method scala/util/control/Breaks.breakable:(Lscala/Function0;)V
   28:	aload_2
   29:	getfield	#598; //Field scala/runtime/BooleanRef.elem:Z
   32:	ireturn
  LineNumberTable: 
   line 263: 0
   line 264: 9
   line 265: 15
   line 268: 21
   line 265: 22
   line 264: 25
   line 268: 28

  LocalVariableTable: 
   Start  Length  Slot  Name   Signature
   0      33      0    $this       Lscala/collection/TraversableLike;
   0      33      1    p$4       Lscala/Function1;
   9      23      2    result$4       Lscala/runtime/BooleanRef;


public static boolean forall(scala.collection.TraversableLike, scala.Function1);
  Code:
   Stack=6, Locals=3, Args_size=2
   0:	new	#123; //class scala/runtime/BooleanRef
   3:	dup
   4:	iconst_1
   5:	invokespecial	#126; //Method scala/runtime/BooleanRef."<init>":(Z)V
   8:	astore_2
   9:	getstatic	#270; //Field scala/collection/Traversable$.MODULE$:Lscala/collection/Traversable$;
   12:	invokevirtual	#274; //Method scala/collection/Traversable$.breaks:()Lscala/util/control/Breaks;
   15:	new	#603; //class scala/collection/TraversableLike$$anonfun$forall$1
   18:	dup
   19:	aload_0
   20:	aload_1
   21:	aload_2
   22:	invokespecial	#604; //Method scala/collection/TraversableLike$$anonfun$forall$1."<init>":(Lscala/collection/TraversableLike;Lscala/Function1;Lscala/runtime/BooleanRef;)V
   25:	invokevirtual	#285; //Method scala/util/control/Breaks.breakable:(Lscala/Function0;)V
   28:	aload_2
   29:	getfield	#598; //Field scala/runtime/BooleanRef.elem:Z
   32:	ireturn
  LineNumberTable: 
   line 248: 0
   line 249: 9
   line 250: 15
   line 253: 21
   line 250: 22
   line 249: 25
   line 253: 28

  LocalVariableTable: 
   Start  Length  Slot  Name   Signature
   0      33      0    $this       Lscala/collection/TraversableLike;
   0      33      1    p$2       Lscala/Function1;
   9      23      2    result$3       Lscala/runtime/BooleanRef;


public static scala.collection.Map groupBy(scala.collection.TraversableLike, scala.Function1);
  Code:
   Stack=6, Locals=3, Args_size=2
   0:	new	#393; //class scala/runtime/ObjectRef
   3:	dup
   4:	getstatic	#613; //Field scala/collection/Map$.MODULE$:Lscala/collection/Map$;
   7:	getstatic	#161; //Field scala/Predef$.MODULE$:Lscala/Predef$;
   10:	iconst_0
   11:	anewarray	#311; //class scala/Tuple2
   14:	checkcast	#615; //class "[Ljava/lang/Object;"
   17:	invokevirtual	#619; //Method scala/Predef$.wrapRefArray:([Ljava/lang/Object;)Lscala/collection/mutable/WrappedArray;
   20:	invokevirtual	#622; //Method scala/collection/Map$.apply:(Lscala/collection/Seq;)Lscala/collection/Map;
   23:	invokespecial	#399; //Method scala/runtime/ObjectRef."<init>":(Ljava/lang/Object;)V
   26:	astore_2
   27:	aload_0
   28:	new	#624; //class scala/collection/TraversableLike$$anonfun$groupBy$1
   31:	dup
   32:	aload_0
   33:	aload_1
   34:	aload_2
   35:	invokespecial	#625; //Method scala/collection/TraversableLike$$anonfun$groupBy$1."<init>":(Lscala/collection/TraversableLike;Lscala/Function1;Lscala/runtime/ObjectRef;)V
   38:	invokeinterface	#135,  2; //InterfaceMethod scala/collection/TraversableLike.foreach:(Lscala/Function1;)V
   43:	aload_2
   44:	getfield	#429; //Field scala/runtime/ObjectRef.elem:Ljava/lang/Object;
   47:	checkcast	#627; //class scala/collection/Map
   50:	new	#629; //class scala/collection/TraversableLike$$anonfun$groupBy$2
   53:	dup
   54:	aload_0
   55:	invokespecial	#630; //Method scala/collection/TraversableLike$$anonfun$groupBy$2."<init>":(Lscala/collection/TraversableLike;)V
   58:	invokeinterface	#636,  2; //InterfaceMethod scala/collection/MapLike.mapValues:(Lscala/Function1;)Ljava/lang/Object;
   63:	checkcast	#627; //class scala/collection/Map
   66:	areturn
  LineNumberTable: 
   line 229: 0
   line 230: 27
   line 238: 34
   line 230: 35
   line 238: 43

  LocalVariableTable: 
   Start  Length  Slot  Name   Signature
   0      67      0    $this       Lscala/collection/TraversableLike;
   0      67      1    f$4       Lscala/Function1;
   27      39      2    m$1       Lscala/runtime/ObjectRef;


public static scala.Tuple2 partition(scala.collection.TraversableLike, scala.Function1);
  Code:
   Stack=7, Locals=4, Args_size=2
   0:	aload_0
   1:	invokeinterface	#304,  1; //InterfaceMethod scala/collection/TraversableLike.newBuilder:()Lscala/collection/mutable/Builder;
   6:	astore_2
   7:	aload_0
   8:	invokeinterface	#304,  1; //InterfaceMethod scala/collection/TraversableLike.newBuilder:()Lscala/collection/mutable/Builder;
   13:	astore_3
   14:	aload_0
   15:	new	#641; //class scala/collection/TraversableLike$$anonfun$partition$1
   18:	dup
   19:	aload_0
   20:	aload_1
   21:	aload_2
   22:	aload_3
   23:	invokespecial	#644; //Method scala/collection/TraversableLike$$anonfun$partition$1."<init>":(Lscala/collection/TraversableLike;Lscala/Function1;Lscala/collection/mutable/Builder;Lscala/collection/mutable/Builder;)V
   26:	invokeinterface	#135,  2; //InterfaceMethod scala/collection/TraversableLike.foreach:(Lscala/Function1;)V
   31:	new	#311; //class scala/Tuple2
   34:	dup
   35:	aload_2
   36:	invokeinterface	#315,  1; //InterfaceMethod scala/collection/mutable/Builder.result:()Ljava/lang/Object;
   41:	aload_3
   42:	invokeinterface	#315,  1; //InterfaceMethod scala/collection/mutable/Builder.result:()Ljava/lang/Object;
   47:	invokespecial	#318; //Method scala/Tuple2."<init>":(Ljava/lang/Object;Ljava/lang/Object;)V
   50:	areturn
  LineNumberTable: 
   line 215: 0
   line 216: 14
   line 217: 31

  LocalVariableTable: 
   Start  Length  Slot  Name   Signature
   0      51      0    $this       Lscala/collection/TraversableLike;
   0      51      1    p$10       Lscala/Function1;
   7      43      2    l$1       Lscala/collection/mutable/Builder;
   14      36      3    r$1       Lscala/collection/mutable/Builder;


public static java.lang.Object partialMap(scala.collection.TraversableLike, scala.PartialFunction, scala.collection.generic.CanBuildFrom);
  Code:
   Stack=6, Locals=4, Args_size=3
   0:	aload_2
   1:	aload_0
   2:	invokeinterface	#45,  1; //InterfaceMethod scala/collection/TraversableLike.repr:()Ljava/lang/Object;
   7:	invokeinterface	#654,  2; //InterfaceMethod scala/collection/generic/CanBuildFrom.apply:(Ljava/lang/Object;)Lscala/collection/mutable/Builder;
   12:	astore_3
   13:	aload_0
   14:	new	#656; //class scala/collection/TraversableLike$$anonfun$partialMap$1
   17:	dup
   18:	aload_0
   19:	aload_1
   20:	aload_3
   21:	invokespecial	#659; //Method scala/collection/TraversableLike$$anonfun$partialMap$1."<init>":(Lscala/collection/TraversableLike;Lscala/PartialFunction;Lscala/collection/mutable/Builder;)V
   24:	invokeinterface	#135,  2; //InterfaceMethod scala/collection/TraversableLike.foreach:(Lscala/Function1;)V
   29:	aload_3
   30:	invokeinterface	#315,  1; //InterfaceMethod scala/collection/mutable/Builder.result:()Ljava/lang/Object;
   35:	areturn
  LineNumberTable: 
   line 201: 0
   line 202: 13
   line 203: 29

  LocalVariableTable: 
   Start  Length  Slot  Name   Signature
   0      36      0    $this       Lscala/collection/TraversableLike;
   0      36      1    pf$1       Lscala/PartialFunction;
   0      36      2    bf       Lscala/collection/generic/CanBuildFrom;
   13      22      3    b$5       Lscala/collection/mutable/Builder;


public static java.lang.Object filterNot(scala.collection.TraversableLike, scala.Function1);
  Code:
   Stack=5, Locals=2, Args_size=2
   0:	aload_0
   1:	new	#667; //class scala/collection/TraversableLike$$anonfun$filterNot$1
   4:	dup
   5:	aload_0
   6:	aload_1
   7:	invokespecial	#668; //Method scala/collection/TraversableLike$$anonfun$filterNot$1."<init>":(Lscala/collection/TraversableLike;Lscala/Function1;)V
   10:	invokeinterface	#671,  2; //InterfaceMethod scala/collection/TraversableLike.filter:(Lscala/Function1;)Ljava/lang/Object;
   15:	areturn
  LineNumberTable: 
   line 192: 0

  LocalVariableTable: 
   Start  Length  Slot  Name   Signature
   0      16      0    $this       Lscala/collection/TraversableLike;
   0      16      1    p$9       Lscala/Function1;


public static java.lang.Object filter(scala.collection.TraversableLike, scala.Function1);
  Code:
   Stack=6, Locals=3, Args_size=2
   0:	aload_0
   1:	invokeinterface	#304,  1; //InterfaceMethod scala/collection/TraversableLike.newBuilder:()Lscala/collection/mutable/Builder;
   6:	astore_2
   7:	aload_0
   8:	new	#674; //class scala/collection/TraversableLike$$anonfun$filter$1
   11:	dup
   12:	aload_0
   13:	aload_1
   14:	aload_2
   15:	invokespecial	#675; //Method scala/collection/TraversableLike$$anonfun$filter$1."<init>":(Lscala/collection/TraversableLike;Lscala/Function1;Lscala/collection/mutable/Builder;)V
   18:	invokeinterface	#135,  2; //InterfaceMethod scala/collection/TraversableLike.foreach:(Lscala/Function1;)V
   23:	aload_2
   24:	invokeinterface	#315,  1; //InterfaceMethod scala/collection/mutable/Builder.result:()Ljava/lang/Object;
   29:	areturn
  LineNumberTable: 
   line 180: 0
   line 181: 7
   line 183: 23

  LocalVariableTable: 
   Start  Length  Slot  Name   Signature
   0      30      0    $this       Lscala/collection/TraversableLike;
   0      30      1    p$3       Lscala/Function1;
   7      22      2    b$4       Lscala/collection/mutable/Builder;


public static java.lang.Object flatMap(scala.collection.TraversableLike, scala.Function1, scala.collection.generic.CanBuildFrom);
  Code:
   Stack=6, Locals=4, Args_size=3
   0:	aload_2
   1:	aload_0
   2:	invokeinterface	#45,  1; //InterfaceMethod scala/collection/TraversableLike.repr:()Ljava/lang/Object;
   7:	invokeinterface	#654,  2; //InterfaceMethod scala/collection/generic/CanBuildFrom.apply:(Ljava/lang/Object;)Lscala/collection/mutable/Builder;
   12:	astore_3
   13:	aload_0
   14:	new	#681; //class scala/collection/TraversableLike$$anonfun$flatMap$1
   17:	dup
   18:	aload_0
   19:	aload_1
   20:	aload_3
   21:	invokespecial	#682; //Method scala/collection/TraversableLike$$anonfun$flatMap$1."<init>":(Lscala/collection/TraversableLike;Lscala/Function1;Lscala/collection/mutable/Builder;)V
   24:	invokeinterface	#135,  2; //InterfaceMethod scala/collection/TraversableLike.foreach:(Lscala/Function1;)V
   29:	aload_3
   30:	invokeinterface	#315,  1; //InterfaceMethod scala/collection/mutable/Builder.result:()Ljava/lang/Object;
   35:	areturn
  LineNumberTable: 
   line 169: 0
   line 170: 13
   line 171: 29

  LocalVariableTable: 
   Start  Length  Slot  Name   Signature
   0      36      0    $this       Lscala/collection/TraversableLike;
   0      36      1    f$3       Lscala/Function1;
   0      36      2    bf       Lscala/collection/generic/CanBuildFrom;
   13      22      3    b$3       Lscala/collection/mutable/Builder;


public static java.lang.Object map(scala.collection.TraversableLike, scala.Function1, scala.collection.generic.CanBuildFrom);
  Code:
   Stack=6, Locals=4, Args_size=3
   0:	aload_2
   1:	aload_0
   2:	invokeinterface	#45,  1; //InterfaceMethod scala/collection/TraversableLike.repr:()Ljava/lang/Object;
   7:	invokeinterface	#654,  2; //InterfaceMethod scala/collection/generic/CanBuildFrom.apply:(Ljava/lang/Object;)Lscala/collection/mutable/Builder;
   12:	astore_3
   13:	aload_0
   14:	new	#687; //class scala/collection/TraversableLike$$anonfun$map$1
   17:	dup
   18:	aload_0
   19:	aload_1
   20:	aload_3
   21:	invokespecial	#688; //Method scala/collection/TraversableLike$$anonfun$map$1."<init>":(Lscala/collection/TraversableLike;Lscala/Function1;Lscala/collection/mutable/Builder;)V
   24:	invokeinterface	#135,  2; //InterfaceMethod scala/collection/TraversableLike.foreach:(Lscala/Function1;)V
   29:	aload_3
   30:	invokeinterface	#315,  1; //InterfaceMethod scala/collection/mutable/Builder.result:()Ljava/lang/Object;
   35:	areturn
  LineNumberTable: 
   line 158: 0
   line 159: 13
   line 160: 29

  LocalVariableTable: 
   Start  Length  Slot  Name   Signature
   0      36      0    $this       Lscala/collection/TraversableLike;
   0      36      1    f$1       Lscala/Function1;
   0      36      2    bf       Lscala/collection/generic/CanBuildFrom;
   13      22      3    b$2       Lscala/collection/mutable/Builder;


public static java.lang.Object $plus$plus(scala.collection.TraversableLike, scala.collection.Iterator, scala.collection.generic.CanBuildFrom);
  Code:
   Stack=2, Locals=4, Args_size=3
   0:	aload_2
   1:	aload_0
   2:	invokeinterface	#45,  1; //InterfaceMethod scala/collection/TraversableLike.repr:()Ljava/lang/Object;
   7:	invokeinterface	#654,  2; //InterfaceMethod scala/collection/generic/CanBuildFrom.apply:(Ljava/lang/Object;)Lscala/collection/mutable/Builder;
   12:	astore_3
   13:	aload_3
   14:	aload_0
   15:	invokeinterface	#175,  1; //InterfaceMethod scala/collection/TraversableLike.thisCollection:()Lscala/collection/Traversable;
   20:	invokeinterface	#215,  2; //InterfaceMethod scala/collection/generic/Growable.$plus$plus$eq:(Lscala/collection/Traversable;)Lscala/collection/generic/Growable;
   25:	pop
   26:	aload_3
   27:	aload_1
   28:	invokeinterface	#694,  2; //InterfaceMethod scala/collection/generic/Growable.$plus$plus$eq:(Lscala/collection/Iterator;)Lscala/collection/generic/Growable;
   33:	pop
   34:	aload_3
   35:	invokeinterface	#315,  1; //InterfaceMethod scala/collection/mutable/Builder.result:()Ljava/lang/Object;
   40:	areturn
  LineNumberTable: 
   line 145: 0
   line 146: 13
   line 147: 26
   line 148: 34

  LocalVariableTable: 
   Start  Length  Slot  Name   Signature
   0      41      0    $this       Lscala/collection/TraversableLike;
   0      41      1    that       Lscala/collection/Iterator;
   0      41      2    bf       Lscala/collection/generic/CanBuildFrom;
   13      27      3    b       Lscala/collection/mutable/Builder;


public static java.lang.Object $plus$plus(scala.collection.TraversableLike, scala.collection.Traversable, scala.collection.generic.CanBuildFrom);
  Code:
   Stack=2, Locals=4, Args_size=3
   0:	aload_2
   1:	aload_0
   2:	invokeinterface	#45,  1; //InterfaceMethod scala/collection/TraversableLike.repr:()Ljava/lang/Object;
   7:	invokeinterface	#654,  2; //InterfaceMethod scala/collection/generic/CanBuildFrom.apply:(Ljava/lang/Object;)Lscala/collection/mutable/Builder;
   12:	astore_3
   13:	aload_3
   14:	aload_0
   15:	invokeinterface	#175,  1; //InterfaceMethod scala/collection/TraversableLike.thisCollection:()Lscala/collection/Traversable;
   20:	invokeinterface	#215,  2; //InterfaceMethod scala/collection/generic/Growable.$plus$plus$eq:(Lscala/collection/Traversable;)Lscala/collection/generic/Growable;
   25:	pop
   26:	aload_3
   27:	aload_1
   28:	invokeinterface	#215,  2; //InterfaceMethod scala/collection/generic/Growable.$plus$plus$eq:(Lscala/collection/Traversable;)Lscala/collection/generic/Growable;
   33:	pop
   34:	aload_3
   35:	invokeinterface	#315,  1; //InterfaceMethod scala/collection/mutable/Builder.result:()Ljava/lang/Object;
   40:	areturn
  LineNumberTable: 
   line 133: 0
   line 134: 13
   line 135: 26
   line 136: 34

  LocalVariableTable: 
   Start  Length  Slot  Name   Signature
   0      41      0    $this       Lscala/collection/TraversableLike;
   0      41      1    that       Lscala/collection/Traversable;
   0      41      2    bf       Lscala/collection/generic/CanBuildFrom;
   13      27      3    b       Lscala/collection/mutable/Builder;


public static boolean hasDefiniteSize(scala.collection.TraversableLike);
  Code:
   Stack=1, Locals=1, Args_size=1
   0:	iconst_1
   1:	ireturn
  LineNumberTable: 
   line 125: 0

  LocalVariableTable: 
   Start  Length  Slot  Name   Signature
   0      2      0    $this       Lscala/collection/TraversableLike;


public static int size(scala.collection.TraversableLike);
  Code:
   Stack=5, Locals=2, Args_size=1
   0:	new	#253; //class scala/runtime/IntRef
   3:	dup
   4:	iconst_0
   5:	invokespecial	#256; //Method scala/runtime/IntRef."<init>":(I)V
   8:	astore_1
   9:	aload_0
   10:	new	#703; //class scala/collection/TraversableLike$$anonfun$size$1
   13:	dup
   14:	aload_0
   15:	aload_1
   16:	invokespecial	#706; //Method scala/collection/TraversableLike$$anonfun$size$1."<init>":(Lscala/collection/TraversableLike;Lscala/runtime/IntRef;)V
   19:	invokeinterface	#135,  2; //InterfaceMethod scala/collection/TraversableLike.foreach:(Lscala/Function1;)V
   24:	aload_1
   25:	getfield	#587; //Field scala/runtime/IntRef.elem:I
   28:	ireturn
  LineNumberTable: 
   line 113: 0
   line 114: 9
   line 115: 15
   line 114: 16
   line 115: 24

  LocalVariableTable: 
   Start  Length  Slot  Name   Signature
   0      29      0    $this       Lscala/collection/TraversableLike;
   9      19      1    result$2       Lscala/runtime/IntRef;


public static boolean nonEmpty(scala.collection.TraversableLike);
  Code:
   Stack=1, Locals=1, Args_size=1
   0:	aload_0
   1:	invokeinterface	#384,  1; //InterfaceMethod scala/collection/TraversableLike.isEmpty:()Z
   6:	ifeq	13
   9:	iconst_0
   10:	goto	14
   13:	iconst_1
   14:	ireturn
  LineNumberTable: 
   line 108: 0

  LocalVariableTable: 
   Start  Length  Slot  Name   Signature
   0      15      0    $this       Lscala/collection/TraversableLike;


public static boolean isEmpty(scala.collection.TraversableLike);
  Code:
   Stack=5, Locals=2, Args_size=1
   0:	new	#123; //class scala/runtime/BooleanRef
   3:	dup
   4:	iconst_1
   5:	invokespecial	#126; //Method scala/runtime/BooleanRef."<init>":(Z)V
   8:	astore_1
   9:	getstatic	#270; //Field scala/collection/Traversable$.MODULE$:Lscala/collection/Traversable$;
   12:	invokevirtual	#274; //Method scala/collection/Traversable$.breaks:()Lscala/util/control/Breaks;
   15:	new	#710; //class scala/collection/TraversableLike$$anonfun$isEmpty$1
   18:	dup
   19:	aload_0
   20:	aload_1
   21:	invokespecial	#713; //Method scala/collection/TraversableLike$$anonfun$isEmpty$1."<init>":(Lscala/collection/TraversableLike;Lscala/runtime/BooleanRef;)V
   24:	invokevirtual	#285; //Method scala/util/control/Breaks.breakable:(Lscala/Function0;)V
   27:	aload_1
   28:	getfield	#598; //Field scala/runtime/BooleanRef.elem:Z
   31:	ireturn
  LineNumberTable: 
   line 96: 0
   line 97: 9
   line 98: 15
   line 103: 20
   line 98: 21
   line 97: 24
   line 103: 27

  LocalVariableTable: 
   Start  Length  Slot  Name   Signature
   0      32      0    $this       Lscala/collection/TraversableLike;
   9      22      1    result$1       Lscala/runtime/BooleanRef;


public static scala.collection.Traversable toCollection(scala.collection.TraversableLike, java.lang.Object);
  Code:
   Stack=1, Locals=2, Args_size=2
   0:	aload_1
   1:	checkcast	#718; //class scala/collection/Traversable
   4:	areturn
  LineNumberTable: 
   line 73: 0

  LocalVariableTable: 
   Start  Length  Slot  Name   Signature
   0      5      0    $this       Lscala/collection/TraversableLike;
   0      5      1    repr       Ljava/lang/Object;


public static scala.collection.Traversable thisCollection(scala.collection.TraversableLike);
  Code:
   Stack=1, Locals=1, Args_size=1
   0:	aload_0
   1:	checkcast	#718; //class scala/collection/Traversable
   4:	areturn
  LineNumberTable: 
   line 72: 0

  LocalVariableTable: 
   Start  Length  Slot  Name   Signature
   0      5      0    $this       Lscala/collection/TraversableLike;


public static java.lang.Object repr(scala.collection.TraversableLike);
  Code:
   Stack=1, Locals=1, Args_size=1
   0:	aload_0
   1:	areturn
  LineNumberTable: 
   line 70: 0

  LocalVariableTable: 
   Start  Length  Slot  Name   Signature
   0      2      0    $this       Lscala/collection/TraversableLike;


}

