Compiled from "TraversableViewLike.scala"
public final class scala.collection.TraversableViewLike$$anonfun$thisSeq$1 extends scala.runtime.AbstractFunction1 implements java.io.Serializable
  SourceFile: "TraversableViewLike.scala"
  Scala: length = 0x
   
  InnerClass: 
   public final $anonfun$thisSeq$1=class scala/collection/TraversableViewLike$$anonfun$thisSeq$1 of class scala/collection/TraversableViewLike
  minor version: 0
  major version: 49
  Constant pool:
Asciz	SourceFile;
Asciz	TraversableViewLike.scala;
Asciz	<clinit>;
Asciz	()V;
Asciz	Code;
Asciz	serialVersionUID;
Asciz	J;
Asciz	scala/collection/TraversableViewLike$$anonfun$thisSeq$1;
class	scala/collection/TraversableViewLike$$anonfun$thisSeq$1
NameAndType	serialVersionUID:J
Field	scala/collection/TraversableViewLike$$anonfun$thisSeq$1.serialVersionUID:J
Asciz	buf$1;
Asciz	Lscala/collection/mutable/ArrayBuffer;;
Asciz	apply;
Asciz	(Ljava/lang/Object;)Lscala/collection/mutable/ArrayBuffer;;
Asciz	LineNumberTable;
NameAndType	buf$1:Lscala/collection/mutable/ArrayBuffer;
Field	scala/collection/TraversableViewLike$$anonfun$thisSeq$1.buf$1:Lscala/collection/mutable/ArrayBuffer;
Asciz	scala/collection/mutable/ArrayBuffer;
class	scala/collection/mutable/ArrayBuffer
Asciz	$plus$eq;
NameAndType	$plus$eq:(Ljava/lang/Object;)Lscala/collection/mutable/ArrayBuffer;
Method	scala/collection/mutable/ArrayBuffer.$plus$eq:(Ljava/lang/Object;)Lscala/collection/mutable/ArrayBuffer;
Asciz	(TA;)Lscala/collection/mutable/ArrayBuffer<TA;>;;
Asciz	Signature;
Asciz	(Ljava/lang/Object;)Ljava/lang/Object;;
NameAndType	apply:(Ljava/lang/Object;)Lscala/collection/mutable/ArrayBuffer;
Method	scala/collection/TraversableViewLike$$anonfun$thisSeq$1.apply:(Ljava/lang/Object;)Lscala/collection/mutable/ArrayBuffer;
Asciz	this;
Asciz	Lscala/collection/TraversableViewLike$$anonfun$thisSeq$1;;
Asciz	v1;
Asciz	Ljava/lang/Object;;
Asciz	LocalVariableTable;
Asciz	<init>;
Asciz	(Lscala/collection/TraversableViewLike;Lscala/collection/mutable/ArrayBuffer;)V;
Asciz	scala/runtime/AbstractFunction1;
class	scala/runtime/AbstractFunction1
NameAndType	"<init>":()V
Method	scala/runtime/AbstractFunction1."<init>":()V
Asciz	$outer;
Asciz	Lscala/collection/TraversableViewLike;;
Asciz	(Lscala/collection/TraversableViewLike<TA;TColl;TThis;>;)V;
Asciz	Scala;
Asciz	InnerClasses;
Asciz	scala/collection/TraversableViewLike;
class	scala/collection/TraversableViewLike
Asciz	$anonfun$thisSeq$1;
Asciz	java/io/Serializable;
class	java/io/Serializable

{
public static final long serialVersionUID;
  Signature: J

public final scala.collection.mutable.ArrayBuffer buf$1;
  Signature: Lscala/collection/mutable/ArrayBuffer;

public static {};
  Signature: ()V
  Code:
   Stack=2, Locals=0, Args_size=0
	lconst_0
	putstatic	Field serialVersionUID:J
	return
  Labels:

public final scala.collection.mutable.ArrayBuffer apply(java.lang.Object);
  Signature: (Ljava/lang/Object;)Lscala/collection/mutable/ArrayBuffer;
  Code:
   Stack=2, Locals=2, Args_size=2
	aload_0
	getfield	Field buf$1:Lscala/collection/mutable/ArrayBuffer;
	aload_1
	invokevirtual	Method scala/collection/mutable/ArrayBuffer.$plus$eq:(Ljava/lang/Object;)Lscala/collection/mutable/ArrayBuffer;
	areturn
  Labels:
  Signature: length = 0x2
   00 18 

public final java.lang.Object apply(java.lang.Object);
  Signature: (Ljava/lang/Object;)Ljava/lang/Object;
  Code:
   Stack=2, Locals=2, Args_size=2
	aload_0
	aload_1
	invokevirtual	Method apply:(Ljava/lang/Object;)Lscala/collection/mutable/ArrayBuffer;
	areturn
  Labels:
  LocalVariableTable: 
   Start  Length  Slot  Name   Signature
   0      6      0    this       Lscala/collection/TraversableViewLike$$anonfun$thisSeq$1;
   0      6      1    v1       Ljava/lang/Object;


public scala.collection.TraversableViewLike$$anonfun$thisSeq$1(scala.collection.TraversableViewLike, scala.collection.mutable.ArrayBuffer);
  Signature: (Lscala/collection/TraversableViewLike;Lscala/collection/mutable/ArrayBuffer;)V
  Code:
   Stack=2, Locals=3, Args_size=3
	aload_0
	aload_2
	putfield	Field buf$1:Lscala/collection/mutable/ArrayBuffer;
	aload_0
	invokespecial	Method scala/runtime/AbstractFunction1."<init>":()V
	return
  Labels:
  LocalVariableTable: 
   Start  Length  Slot  Name   Signature
   0      10      0    this       Lscala/collection/TraversableViewLike$$anonfun$thisSeq$1;
   0      10      1    $outer       Lscala/collection/TraversableViewLike;

  Signature: length = 0x2
   00 2A 

}

