Compiled from "TraversableViewLike.scala"
public final class scala.collection.TraversableViewLike$$anonfun$partialMap$1 extends scala.runtime.AbstractFunction1 implements java.io.Serializable
  SourceFile: "TraversableViewLike.scala"
  Scala: length = 0x
   
  InnerClass: 
   public final $anonfun$partialMap$1=class scala/collection/TraversableViewLike$$anonfun$partialMap$1 of class scala/collection/TraversableViewLike
  minor version: 0
  major version: 49
  Constant pool:
Asciz	SourceFile;
Asciz	TraversableViewLike.scala;
Asciz	<clinit>;
Asciz	()V;
Asciz	Code;
Asciz	serialVersionUID;
Asciz	J;
Asciz	scala/collection/TraversableViewLike$$anonfun$partialMap$1;
class	scala/collection/TraversableViewLike$$anonfun$partialMap$1
NameAndType	serialVersionUID:J
Field	scala/collection/TraversableViewLike$$anonfun$partialMap$1.serialVersionUID:J
Asciz	pf$1;
Asciz	Lscala/PartialFunction;;
Asciz	apply;
Asciz	(Ljava/lang/Object;)Z;
Asciz	LineNumberTable;
NameAndType	pf$1:Lscala/PartialFunction;
Field	scala/collection/TraversableViewLike$$anonfun$partialMap$1.pf$1:Lscala/PartialFunction;
Asciz	scala/PartialFunction;
class	scala/PartialFunction
Asciz	isDefinedAt;
NameAndType	isDefinedAt:(Ljava/lang/Object;)Z
InterfaceMethod	scala/PartialFunction.isDefinedAt:(Ljava/lang/Object;)Z
Asciz	(TA;)Z;
Asciz	Signature;
Asciz	(Ljava/lang/Object;)Ljava/lang/Object;;
NameAndType	apply:(Ljava/lang/Object;)Z
Method	scala/collection/TraversableViewLike$$anonfun$partialMap$1.apply:(Ljava/lang/Object;)Z
Asciz	scala/runtime/BoxesRunTime;
class	scala/runtime/BoxesRunTime
Asciz	boxToBoolean;
Asciz	(Z)Ljava/lang/Boolean;;
NameAndType	boxToBoolean:(Z)Ljava/lang/Boolean;
Method	scala/runtime/BoxesRunTime.boxToBoolean:(Z)Ljava/lang/Boolean;
Asciz	this;
Asciz	Lscala/collection/TraversableViewLike$$anonfun$partialMap$1;;
Asciz	v1;
Asciz	Ljava/lang/Object;;
Asciz	LocalVariableTable;
Asciz	<init>;
Asciz	(Lscala/collection/TraversableViewLike;Lscala/PartialFunction;)V;
Asciz	scala/runtime/AbstractFunction1;
class	scala/runtime/AbstractFunction1
NameAndType	"<init>":()V
Method	scala/runtime/AbstractFunction1."<init>":()V
Asciz	$outer;
Asciz	Lscala/collection/TraversableViewLike;;
Asciz	(Lscala/collection/TraversableViewLike<TA;TColl;TThis;>;)V;
Asciz	Scala;
Asciz	InnerClasses;
Asciz	scala/collection/TraversableViewLike;
class	scala/collection/TraversableViewLike
Asciz	$anonfun$partialMap$1;
Asciz	java/io/Serializable;
class	java/io/Serializable

{
public static final long serialVersionUID;
  Signature: J

public final scala.PartialFunction pf$1;
  Signature: Lscala/PartialFunction;

public static {};
  Signature: ()V
  Code:
   Stack=2, Locals=0, Args_size=0
	lconst_0
	putstatic	Field serialVersionUID:J
	return
  Labels:

public final boolean apply(java.lang.Object);
  Signature: (Ljava/lang/Object;)Z
  Code:
   Stack=2, Locals=2, Args_size=2
	aload_0
	getfield	Field pf$1:Lscala/PartialFunction;
	aload_1
	invokeinterface	InterfaceMethod scala/PartialFunction.isDefinedAt:(Ljava/lang/Object;)Z
	ireturn
  Labels:
  Signature: length = 0x2
   00 18 

public final java.lang.Object apply(java.lang.Object);
  Signature: (Ljava/lang/Object;)Ljava/lang/Object;
  Code:
   Stack=2, Locals=3, Args_size=2
	aload_0
	aload_1
	invokevirtual	Method apply:(Ljava/lang/Object;)Z
	istore_2
	iload_2
	invokestatic	Method scala/runtime/BoxesRunTime.boxToBoolean:(Z)Ljava/lang/Boolean;
	areturn
  Labels:
  LocalVariableTable: 
   Start  Length  Slot  Name   Signature
   0      11      0    this       Lscala/collection/TraversableViewLike$$anonfun$partialMap$1;
   0      11      1    v1       Ljava/lang/Object;


public scala.collection.TraversableViewLike$$anonfun$partialMap$1(scala.collection.TraversableViewLike, scala.PartialFunction);
  Signature: (Lscala/collection/TraversableViewLike;Lscala/PartialFunction;)V
  Code:
   Stack=2, Locals=3, Args_size=3
	aload_0
	aload_2
	putfield	Field pf$1:Lscala/PartialFunction;
	aload_0
	invokespecial	Method scala/runtime/AbstractFunction1."<init>":()V
	return
  Labels:
  LocalVariableTable: 
   Start  Length  Slot  Name   Signature
   0      10      0    this       Lscala/collection/TraversableViewLike$$anonfun$partialMap$1;
   0      10      1    $outer       Lscala/collection/TraversableViewLike;

  Signature: length = 0x2
   00 30 

}

