Compiled from "Traversable.scala"
public class scala.collection.Traversable$TraversableTraversableOps extends java.lang.Object implements scala.ScalaObject
  SourceFile: "Traversable.scala"
  Signature: length = 0x2
   00 75 
  Scala: length = 0x
   
  InnerClass: 
   public #122= #10 of #121; //TraversableTraversableOps=class scala/collection/Traversable$TraversableTraversableOps of class scala/collection/Traversable
   public final #123= #43 of #10; //$anonfun$1=class scala/collection/Traversable$TraversableTraversableOps$$anonfun$1 of class scala/collection/Traversable$TraversableTraversableOps
   public final #124= #112 of #10; //$anonfun$flatten$1=class scala/collection/Traversable$TraversableTraversableOps$$anonfun$flatten$1 of class scala/collection/Traversable$TraversableTraversableOps
   public final #125= #92 of #10; //$anonfun$transpose$2=class scala/collection/Traversable$TraversableTraversableOps$$anonfun$transpose$2 of class scala/collection/Traversable$TraversableTraversableOps
   public final #126= #75 of #10; //$anonfun$transpose$1=class scala/collection/Traversable$TraversableTraversableOps$$anonfun$transpose$1 of class scala/collection/Traversable$TraversableTraversableOps
  minor version: 0
  major version: 49
  Constant pool:
const #1 = Asciz	SourceFile;
const #2 = Asciz	Traversable.scala;
const #3 = Asciz	scala$collection$Traversable$TraversableTraversableOps$$self;
const #4 = Asciz	Lscala/collection/Traversable;;
const #5 = Asciz	<init>;
const #6 = Asciz	(Lscala/collection/Traversable;)V;
const #7 = Asciz	Code;
const #8 = Asciz	LineNumberTable;
const #9 = Asciz	scala/collection/Traversable$TraversableTraversableOps;
const #10 = class	#9;	//  scala/collection/Traversable$TraversableTraversableOps
const #11 = NameAndType	#3:#4;//  scala$collection$Traversable$TraversableTraversableOps$$self:Lscala/collection/Traversable;
const #12 = Field	#10.#11;	//  scala/collection/Traversable$TraversableTraversableOps.scala$collection$Traversable$TraversableTraversableOps$$self:Lscala/collection/Traversable;
const #13 = Asciz	java/lang/Object;
const #14 = class	#13;	//  java/lang/Object
const #15 = Asciz	()V;
const #16 = NameAndType	#5:#15;//  "<init>":()V
const #17 = Method	#14.#16;	//  java/lang/Object."<init>":()V
const #18 = Asciz	this;
const #19 = Asciz	Lscala/collection/Traversable$TraversableTraversableOps;;
const #20 = Asciz	self;
const #21 = Asciz	LocalVariableTable;
const #22 = Asciz	(TThis;)V;
const #23 = Asciz	Signature;
const #24 = Asciz	transpose;
const #25 = Asciz	(Lscala/collection/generic/BuilderFactory;Lscala/collection/generic/BuilderFactory;)Ljava/lang/Object;;
const #26 = Asciz	scala/runtime/ScalaRunTime$;
const #27 = class	#26;	//  scala/runtime/ScalaRunTime$
const #28 = Asciz	MODULE$;
const #29 = Asciz	Lscala/runtime/ScalaRunTime$;;
const #30 = NameAndType	#28:#29;//  MODULE$:Lscala/runtime/ScalaRunTime$;
const #31 = Field	#27.#30;	//  scala/runtime/ScalaRunTime$.MODULE$:Lscala/runtime/ScalaRunTime$;
const #32 = Asciz	scala/collection/generic/TraversableTemplate;
const #33 = class	#32;	//  scala/collection/generic/TraversableTemplate
const #34 = Asciz	head;
const #35 = Asciz	()Ljava/lang/Object;;
const #36 = NameAndType	#34:#35;//  head:()Ljava/lang/Object;
const #37 = InterfaceMethod	#33.#36;	//  scala/collection/generic/TraversableTemplate.head:()Ljava/lang/Object;
const #38 = Asciz	boxArray;
const #39 = Asciz	(Ljava/lang/Object;)Lscala/runtime/BoxedArray;;
const #40 = NameAndType	#38:#39;//  boxArray:(Ljava/lang/Object;)Lscala/runtime/BoxedArray;
const #41 = Method	#27.#40;	//  scala/runtime/ScalaRunTime$.boxArray:(Ljava/lang/Object;)Lscala/runtime/BoxedArray;
const #42 = Asciz	scala/collection/Traversable$TraversableTraversableOps$$anonfun$1;
const #43 = class	#42;	//  scala/collection/Traversable$TraversableTraversableOps$$anonfun$1
const #44 = Asciz	(Lscala/collection/Traversable$TraversableTraversableOps;Lscala/collection/generic/BuilderFactory;)V;
const #45 = NameAndType	#5:#44;//  "<init>":(Lscala/collection/Traversable$TraversableTraversableOps;Lscala/collection/generic/BuilderFactory;)V
const #46 = Method	#43.#45;	//  scala/collection/Traversable$TraversableTraversableOps$$anonfun$1."<init>":(Lscala/collection/Traversable$TraversableTraversableOps;Lscala/collection/generic/BuilderFactory;)V
const #47 = Asciz	scala/collection/Traversable$;
const #48 = class	#47;	//  scala/collection/Traversable$
const #49 = Asciz	Lscala/collection/Traversable$;;
const #50 = NameAndType	#28:#49;//  MODULE$:Lscala/collection/Traversable$;
const #51 = Field	#48.#50;	//  scala/collection/Traversable$.MODULE$:Lscala/collection/Traversable$;
const #52 = Asciz	builderFactory;
const #53 = Asciz	()Lscala/collection/generic/BuilderFactory;;
const #54 = NameAndType	#52:#53;//  builderFactory:()Lscala/collection/generic/BuilderFactory;
const #55 = Method	#48.#54;	//  scala/collection/Traversable$.builderFactory:()Lscala/collection/generic/BuilderFactory;
const #56 = Asciz	map;
const #57 = Asciz	(Lscala/Function1;Lscala/collection/generic/BuilderFactory;)Ljava/lang/Object;;
const #58 = NameAndType	#56:#57;//  map:(Lscala/Function1;Lscala/collection/generic/BuilderFactory;)Ljava/lang/Object;
const #59 = InterfaceMethod	#33.#58;	//  scala/collection/generic/TraversableTemplate.map:(Lscala/Function1;Lscala/collection/generic/BuilderFactory;)Ljava/lang/Object;
const #60 = Asciz	toArray;
const #61 = Asciz	()Lscala/runtime/BoxedArray;;
const #62 = NameAndType	#60:#61;//  toArray:()Lscala/runtime/BoxedArray;
const #63 = InterfaceMethod	#33.#62;	//  scala/collection/generic/TraversableTemplate.toArray:()Lscala/runtime/BoxedArray;
const #64 = Asciz	scala/collection/generic/Builder;
const #65 = class	#64;	//  scala/collection/generic/Builder
const #66 = Asciz	arrayValue;
const #67 = Asciz	(Lscala/runtime/BoxedArray;Ljava/lang/Class;)Ljava/lang/Object;;
const #68 = NameAndType	#66:#67;//  arrayValue:(Lscala/runtime/BoxedArray;Ljava/lang/Class;)Ljava/lang/Object;
const #69 = Method	#27.#68;	//  scala/runtime/ScalaRunTime$.arrayValue:(Lscala/runtime/BoxedArray;Ljava/lang/Class;)Ljava/lang/Object;
const #70 = Asciz	scala/runtime/BoxedArray;
const #71 = class	#70;	//  scala/runtime/BoxedArray
const #72 = Asciz	[Lscala/collection/generic/Builder;;
const #73 = class	#72;	//  "[Lscala/collection/generic/Builder;"
const #74 = Asciz	scala/collection/Traversable$TraversableTraversableOps$$anonfun$transpose$1;
const #75 = class	#74;	//  scala/collection/Traversable$TraversableTraversableOps$$anonfun$transpose$1
const #76 = Asciz	(Lscala/collection/Traversable$TraversableTraversableOps;[Lscala/collection/generic/Builder;)V;
const #77 = NameAndType	#5:#76;//  "<init>":(Lscala/collection/Traversable$TraversableTraversableOps;[Lscala/collection/generic/Builder;)V
const #78 = Method	#75.#77;	//  scala/collection/Traversable$TraversableTraversableOps$$anonfun$transpose$1."<init>":(Lscala/collection/Traversable$TraversableTraversableOps;[Lscala/collection/generic/Builder;)V
const #79 = Asciz	scala/collection/generic/TraversableClass;
const #80 = class	#79;	//  scala/collection/generic/TraversableClass
const #81 = Asciz	foreach;
const #82 = Asciz	(Lscala/Function1;)V;
const #83 = NameAndType	#81:#82;//  foreach:(Lscala/Function1;)V
const #84 = InterfaceMethod	#80.#83;	//  scala/collection/generic/TraversableClass.foreach:(Lscala/Function1;)V
const #85 = Asciz	scala/collection/generic/BuilderFactory;
const #86 = class	#85;	//  scala/collection/generic/BuilderFactory
const #87 = Asciz	apply;
const #88 = Asciz	(Ljava/lang/Object;)Lscala/collection/generic/Builder;;
const #89 = NameAndType	#87:#88;//  apply:(Ljava/lang/Object;)Lscala/collection/generic/Builder;
const #90 = InterfaceMethod	#86.#89;	//  scala/collection/generic/BuilderFactory.apply:(Ljava/lang/Object;)Lscala/collection/generic/Builder;
const #91 = Asciz	scala/collection/Traversable$TraversableTraversableOps$$anonfun$transpose$2;
const #92 = class	#91;	//  scala/collection/Traversable$TraversableTraversableOps$$anonfun$transpose$2
const #93 = Asciz	(Lscala/collection/Traversable$TraversableTraversableOps;Lscala/collection/generic/Builder;)V;
const #94 = NameAndType	#5:#93;//  "<init>":(Lscala/collection/Traversable$TraversableTraversableOps;Lscala/collection/generic/Builder;)V
const #95 = Method	#92.#94;	//  scala/collection/Traversable$TraversableTraversableOps$$anonfun$transpose$2."<init>":(Lscala/collection/Traversable$TraversableTraversableOps;Lscala/collection/generic/Builder;)V
const #96 = Asciz	scala/collection/generic/VectorTemplate;
const #97 = class	#96;	//  scala/collection/generic/VectorTemplate
const #98 = InterfaceMethod	#97.#83;	//  scala/collection/generic/VectorTemplate.foreach:(Lscala/Function1;)V
const #99 = Asciz	result;
const #100 = NameAndType	#99:#35;//  result:()Ljava/lang/Object;
const #101 = InterfaceMethod	#65.#100;	//  scala/collection/generic/Builder.result:()Ljava/lang/Object;
const #102 = Asciz	bf$1;
const #103 = Asciz	Lscala/collection/generic/BuilderFactory;;
const #104 = Asciz	bbf;
const #105 = Asciz	bs$1;
const #106 = Asciz	bb$1;
const #107 = Asciz	Lscala/collection/generic/Builder;;
const #108 = Asciz	<Row:Ljava/lang/Object;That:Ljava/lang/Object;>(Lscala/collection/generic/BuilderFactory<TA;TRow;TThis;>;Lscala/collection/generic/BuilderFactory<TRow;TThat;TThis;>;)TThat;;
const #109 = Asciz	flatten;
const #110 = Asciz	(Lscala/collection/generic/BuilderFactory;)Ljava/lang/Object;;
const #111 = Asciz	scala/collection/Traversable$TraversableTraversableOps$$anonfun$flatten$1;
const #112 = class	#111;	//  scala/collection/Traversable$TraversableTraversableOps$$anonfun$flatten$1
const #113 = Method	#112.#94;	//  scala/collection/Traversable$TraversableTraversableOps$$anonfun$flatten$1."<init>":(Lscala/collection/Traversable$TraversableTraversableOps;Lscala/collection/generic/Builder;)V
const #114 = Asciz	bf;
const #115 = Asciz	b$1;
const #116 = Asciz	<That:Ljava/lang/Object;>(Lscala/collection/generic/BuilderFactory<TA;TThat;TThis;>;)TThat;;
const #117 = Asciz	<This::Lscala/collection/Traversable<Lscala/collection/Traversable<TA;>;>;A:Ljava/lang/Object;>Ljava/lang/Object;Lscala/ScalaObject;;
const #118 = Asciz	Scala;
const #119 = Asciz	InnerClasses;
const #120 = Asciz	scala/collection/Traversable;
const #121 = class	#120;	//  scala/collection/Traversable
const #122 = Asciz	TraversableTraversableOps;
const #123 = Asciz	$anonfun$1;
const #124 = Asciz	$anonfun$flatten$1;
const #125 = Asciz	$anonfun$transpose$2;
const #126 = Asciz	$anonfun$transpose$1;
const #127 = Asciz	scala/ScalaObject;
const #128 = class	#127;	//  scala/ScalaObject

{
public final scala.collection.Traversable scala$collection$Traversable$TraversableTraversableOps$$self;

public scala.collection.Traversable$TraversableTraversableOps(scala.collection.Traversable);
  Code:
   Stack=2, Locals=2, Args_size=2
   0:	aload_0
   1:	aload_1
   2:	putfield	#12; //Field scala$collection$Traversable$TraversableTraversableOps$$self:Lscala/collection/Traversable;
   5:	aload_0
   6:	invokespecial	#17; //Method java/lang/Object."<init>":()V
   9:	return
  LineNumberTable: 
   line 150: 0

  LocalVariableTable: 
   Start  Length  Slot  Name   Signature
   0      10      0    this       Lscala/collection/Traversable$TraversableTraversableOps;
   0      10      1    self       Lscala/collection/Traversable;

  Signature: length = 0x2
   00 16 

public java.lang.Object transpose(scala.collection.generic.BuilderFactory, scala.collection.generic.BuilderFactory);
  Code:
   Stack=6, Locals=8, Args_size=3
   0:	getstatic	#31; //Field scala/runtime/ScalaRunTime$.MODULE$:Lscala/runtime/ScalaRunTime$;
   3:	aload_0
   4:	getfield	#12; //Field scala$collection$Traversable$TraversableTraversableOps$$self:Lscala/collection/Traversable;
   7:	invokeinterface	#37,  1; //InterfaceMethod scala/collection/generic/TraversableTemplate.head:()Ljava/lang/Object;
   12:	astore	6
   14:	aload	6
   16:	instanceof	#33; //class scala/collection/generic/TraversableTemplate
   19:	ifeq	27
   22:	aload	6
   24:	goto	35
   27:	getstatic	#31; //Field scala/runtime/ScalaRunTime$.MODULE$:Lscala/runtime/ScalaRunTime$;
   30:	aload	6
   32:	invokevirtual	#41; //Method scala/runtime/ScalaRunTime$.boxArray:(Ljava/lang/Object;)Lscala/runtime/BoxedArray;
   35:	checkcast	#33; //class scala/collection/generic/TraversableTemplate
   38:	new	#43; //class scala/collection/Traversable$TraversableTraversableOps$$anonfun$1
   41:	dup
   42:	aload_0
   43:	aload_1
   44:	invokespecial	#46; //Method scala/collection/Traversable$TraversableTraversableOps$$anonfun$1."<init>":(Lscala/collection/Traversable$TraversableTraversableOps;Lscala/collection/generic/BuilderFactory;)V
   47:	getstatic	#51; //Field scala/collection/Traversable$.MODULE$:Lscala/collection/Traversable$;
   50:	invokevirtual	#55; //Method scala/collection/Traversable$.builderFactory:()Lscala/collection/generic/BuilderFactory;
   53:	invokeinterface	#59,  3; //InterfaceMethod scala/collection/generic/TraversableTemplate.map:(Lscala/Function1;Lscala/collection/generic/BuilderFactory;)Ljava/lang/Object;
   58:	astore	5
   60:	aload	5
   62:	instanceof	#33; //class scala/collection/generic/TraversableTemplate
   65:	ifeq	73
   68:	aload	5
   70:	goto	81
   73:	getstatic	#31; //Field scala/runtime/ScalaRunTime$.MODULE$:Lscala/runtime/ScalaRunTime$;
   76:	aload	5
   78:	invokevirtual	#41; //Method scala/runtime/ScalaRunTime$.boxArray:(Ljava/lang/Object;)Lscala/runtime/BoxedArray;
   81:	checkcast	#33; //class scala/collection/generic/TraversableTemplate
   84:	invokeinterface	#63,  1; //InterfaceMethod scala/collection/generic/TraversableTemplate.toArray:()Lscala/runtime/BoxedArray;
   89:	ldc	#65; //class scala/collection/generic/Builder
   91:	invokevirtual	#69; //Method scala/runtime/ScalaRunTime$.arrayValue:(Lscala/runtime/BoxedArray;Ljava/lang/Class;)Ljava/lang/Object;
   94:	astore	4
   96:	aload	4
   98:	instanceof	#71; //class scala/runtime/BoxedArray
   101:	ifeq	120
   104:	getstatic	#31; //Field scala/runtime/ScalaRunTime$.MODULE$:Lscala/runtime/ScalaRunTime$;
   107:	aload	4
   109:	checkcast	#71; //class scala/runtime/BoxedArray
   112:	ldc	#65; //class scala/collection/generic/Builder
   114:	invokevirtual	#69; //Method scala/runtime/ScalaRunTime$.arrayValue:(Lscala/runtime/BoxedArray;Ljava/lang/Class;)Ljava/lang/Object;
   117:	goto	122
   120:	aload	4
   122:	checkcast	#73; //class "[Lscala/collection/generic/Builder;"
   125:	astore_3
   126:	aload_0
   127:	getfield	#12; //Field scala$collection$Traversable$TraversableTraversableOps$$self:Lscala/collection/Traversable;
   130:	new	#75; //class scala/collection/Traversable$TraversableTraversableOps$$anonfun$transpose$1
   133:	dup
   134:	aload_0
   135:	aload_3
   136:	invokespecial	#78; //Method scala/collection/Traversable$TraversableTraversableOps$$anonfun$transpose$1."<init>":(Lscala/collection/Traversable$TraversableTraversableOps;[Lscala/collection/generic/Builder;)V
   139:	invokeinterface	#84,  2; //InterfaceMethod scala/collection/generic/TraversableClass.foreach:(Lscala/Function1;)V
   144:	aload_2
   145:	aload_0
   146:	getfield	#12; //Field scala$collection$Traversable$TraversableTraversableOps$$self:Lscala/collection/Traversable;
   149:	invokeinterface	#90,  2; //InterfaceMethod scala/collection/generic/BuilderFactory.apply:(Ljava/lang/Object;)Lscala/collection/generic/Builder;
   154:	astore	7
   156:	getstatic	#31; //Field scala/runtime/ScalaRunTime$.MODULE$:Lscala/runtime/ScalaRunTime$;
   159:	aload_3
   160:	invokevirtual	#41; //Method scala/runtime/ScalaRunTime$.boxArray:(Ljava/lang/Object;)Lscala/runtime/BoxedArray;
   163:	new	#92; //class scala/collection/Traversable$TraversableTraversableOps$$anonfun$transpose$2
   166:	dup
   167:	aload_0
   168:	aload	7
   170:	invokespecial	#95; //Method scala/collection/Traversable$TraversableTraversableOps$$anonfun$transpose$2."<init>":(Lscala/collection/Traversable$TraversableTraversableOps;Lscala/collection/generic/Builder;)V
   173:	invokeinterface	#98,  2; //InterfaceMethod scala/collection/generic/VectorTemplate.foreach:(Lscala/Function1;)V
   178:	aload	7
   180:	invokeinterface	#101,  1; //InterfaceMethod scala/collection/generic/Builder.result:()Ljava/lang/Object;
   185:	areturn
  LineNumberTable: 
   line 163: 0
   line 164: 126
   line 171: 144
   line 172: 156
   line 173: 178

  LocalVariableTable: 
   Start  Length  Slot  Name   Signature
   0      186      0    this       Lscala/collection/Traversable$TraversableTraversableOps;
   0      186      1    bf$1       Lscala/collection/generic/BuilderFactory;
   0      186      2    bbf       Lscala/collection/generic/BuilderFactory;
   126      59      3    bs$1       [Lscala/collection/generic/Builder;
   156      29      7    bb$1       Lscala/collection/generic/Builder;

  Signature: length = 0x2
   00 6C 

public java.lang.Object flatten(scala.collection.generic.BuilderFactory);
  Code:
   Stack=5, Locals=3, Args_size=2
   0:	aload_1
   1:	aload_0
   2:	getfield	#12; //Field scala$collection$Traversable$TraversableTraversableOps$$self:Lscala/collection/Traversable;
   5:	invokeinterface	#90,  2; //InterfaceMethod scala/collection/generic/BuilderFactory.apply:(Ljava/lang/Object;)Lscala/collection/generic/Builder;
   10:	astore_2
   11:	aload_0
   12:	getfield	#12; //Field scala$collection$Traversable$TraversableTraversableOps$$self:Lscala/collection/Traversable;
   15:	new	#112; //class scala/collection/Traversable$TraversableTraversableOps$$anonfun$flatten$1
   18:	dup
   19:	aload_0
   20:	aload_2
   21:	invokespecial	#113; //Method scala/collection/Traversable$TraversableTraversableOps$$anonfun$flatten$1."<init>":(Lscala/collection/Traversable$TraversableTraversableOps;Lscala/collection/generic/Builder;)V
   24:	invokeinterface	#84,  2; //InterfaceMethod scala/collection/generic/TraversableClass.foreach:(Lscala/Function1;)V
   29:	aload_2
   30:	invokeinterface	#101,  1; //InterfaceMethod scala/collection/generic/Builder.result:()Ljava/lang/Object;
   35:	areturn
  LineNumberTable: 
   line 154: 0
   line 155: 11
   line 157: 29

  LocalVariableTable: 
   Start  Length  Slot  Name   Signature
   0      36      0    this       Lscala/collection/Traversable$TraversableTraversableOps;
   0      36      1    bf       Lscala/collection/generic/BuilderFactory;
   11      24      2    b$1       Lscala/collection/generic/Builder;

  Signature: length = 0x2
   00 74 

}

