Compiled from "TraversableLike.scala"
public final class scala.collection.TraversableLike$$anonfun$foldLeft$1 extends scala.runtime.AbstractFunction1 implements java.io.Serializable
  SourceFile: "TraversableLike.scala"
  Scala: length = 0x
   
  InnerClass: 
   public final $anonfun$foldLeft$1=class scala/collection/TraversableLike$$anonfun$foldLeft$1 of class scala/collection/TraversableLike
  minor version: 0
  major version: 49
  Constant pool:
Asciz	SourceFile;
Asciz	TraversableLike.scala;
Asciz	<clinit>;
Asciz	()V;
Asciz	Code;
Asciz	serialVersionUID;
Asciz	J;
Asciz	scala/collection/TraversableLike$$anonfun$foldLeft$1;
class	scala/collection/TraversableLike$$anonfun$foldLeft$1
NameAndType	serialVersionUID:J
Field	scala/collection/TraversableLike$$anonfun$foldLeft$1.serialVersionUID:J
Asciz	result$6;
Asciz	Lscala/runtime/ObjectRef;;
Asciz	op$1;
Asciz	Lscala/Function2;;
Asciz	<init>;
Asciz	(Lscala/collection/TraversableLike;Lscala/Function2;Lscala/runtime/ObjectRef;)V;
Asciz	LineNumberTable;
NameAndType	op$1:Lscala/Function2;
Field	scala/collection/TraversableLike$$anonfun$foldLeft$1.op$1:Lscala/Function2;
NameAndType	result$6:Lscala/runtime/ObjectRef;
Field	scala/collection/TraversableLike$$anonfun$foldLeft$1.result$6:Lscala/runtime/ObjectRef;
Asciz	scala/runtime/AbstractFunction1;
class	scala/runtime/AbstractFunction1
NameAndType	"<init>":()V
Method	scala/runtime/AbstractFunction1."<init>":()V
Asciz	this;
Asciz	Lscala/collection/TraversableLike$$anonfun$foldLeft$1;;
Asciz	$outer;
Asciz	Lscala/collection/TraversableLike;;
Asciz	LocalVariableTable;
Asciz	(Lscala/collection/TraversableLike<TA;TRepr;>;)V;
Asciz	Signature;
Asciz	apply;
Asciz	(Ljava/lang/Object;)Ljava/lang/Object;;
Asciz	(Ljava/lang/Object;)V;
NameAndType	apply:(Ljava/lang/Object;)V
Method	scala/collection/TraversableLike$$anonfun$foldLeft$1.apply:(Ljava/lang/Object;)V
Asciz	scala/runtime/BoxedUnit;
class	scala/runtime/BoxedUnit
Asciz	UNIT;
Asciz	Lscala/runtime/BoxedUnit;;
NameAndType	UNIT:Lscala/runtime/BoxedUnit;
Field	scala/runtime/BoxedUnit.UNIT:Lscala/runtime/BoxedUnit;
Asciz	v1;
Asciz	Ljava/lang/Object;;
Asciz	scala/runtime/ObjectRef;
class	scala/runtime/ObjectRef
Asciz	elem;
NameAndType	elem:Ljava/lang/Object;
Field	scala/runtime/ObjectRef.elem:Ljava/lang/Object;
Asciz	scala/Function2;
class	scala/Function2
Asciz	(Ljava/lang/Object;Ljava/lang/Object;)Ljava/lang/Object;;
NameAndType	apply:(Ljava/lang/Object;Ljava/lang/Object;)Ljava/lang/Object;
InterfaceMethod	scala/Function2.apply:(Ljava/lang/Object;Ljava/lang/Object;)Ljava/lang/Object;
Asciz	x;
Asciz	(TA;)V;
Asciz	Scala;
Asciz	InnerClasses;
Asciz	scala/collection/TraversableLike;
class	scala/collection/TraversableLike
Asciz	$anonfun$foldLeft$1;
Asciz	java/io/Serializable;
class	java/io/Serializable

{
public static final long serialVersionUID;
  Signature: J

private final scala.runtime.ObjectRef result$6;
  Signature: Lscala/runtime/ObjectRef;

private final scala.Function2 op$1;
  Signature: Lscala/Function2;

public static {};
  Signature: ()V
  Code:
   Stack=2, Locals=0, Args_size=0
	lconst_0
	putstatic	Field serialVersionUID:J
	return
  Labels:

public scala.collection.TraversableLike$$anonfun$foldLeft$1(scala.collection.TraversableLike, scala.Function2, scala.runtime.ObjectRef);
  Signature: (Lscala/collection/TraversableLike;Lscala/Function2;Lscala/runtime/ObjectRef;)V
  Code:
   Stack=2, Locals=4, Args_size=4
	aload_0
	aload_2
	putfield	Field op$1:Lscala/Function2;
	aload_0
	aload_3
	putfield	Field result$6:Lscala/runtime/ObjectRef;
	aload_0
	invokespecial	Method scala/runtime/AbstractFunction1."<init>":()V
	return
  Labels:
  LocalVariableTable: 
   Start  Length  Slot  Name   Signature
   0      15      0    this       Lscala/collection/TraversableLike$$anonfun$foldLeft$1;
   0      15      1    $outer       Lscala/collection/TraversableLike;

  Signature: length = 0x2
   00 20 

public final java.lang.Object apply(java.lang.Object);
  Signature: (Ljava/lang/Object;)Ljava/lang/Object;
  Code:
   Stack=2, Locals=2, Args_size=2
	aload_0
	aload_1
	invokevirtual	Method apply:(Ljava/lang/Object;)V
	getstatic	Field scala/runtime/BoxedUnit.UNIT:Lscala/runtime/BoxedUnit;
	areturn
  Labels:
  LocalVariableTable: 
   Start  Length  Slot  Name   Signature
   0      9      0    this       Lscala/collection/TraversableLike$$anonfun$foldLeft$1;
   0      9      1    v1       Ljava/lang/Object;


public final void apply(java.lang.Object);
  Signature: (Ljava/lang/Object;)V
  Code:
   Stack=4, Locals=2, Args_size=2
	aload_0
	getfield	Field result$6:Lscala/runtime/ObjectRef;
	aload_0
	getfield	Field op$1:Lscala/Function2;
	aload_0
	getfield	Field result$6:Lscala/runtime/ObjectRef;
	getfield	Field scala/runtime/ObjectRef.elem:Ljava/lang/Object;
	aload_1
	invokeinterface	InterfaceMethod scala/Function2.apply:(Ljava/lang/Object;Ljava/lang/Object;)Ljava/lang/Object;
	putfield	Field scala/runtime/ObjectRef.elem:Ljava/lang/Object;
	return
  Labels:
  LocalVariableTable: 
   Start  Length  Slot  Name   Signature
   0      25      0    this       Lscala/collection/TraversableLike$$anonfun$foldLeft$1;
   0      25      1    x       Ljava/lang/Object;

  Signature: length = 0x2
   00 3A 

}

