Compiled from "TraversableLike.scala"
public final class scala.collection.TraversableLike$$anonfun$flatMap$1 extends scala.runtime.AbstractFunction1 implements java.io.Serializable
  SourceFile: "TraversableLike.scala"
  Scala: length = 0x
   
  InnerClass: 
   public final $anonfun$flatMap$1=class scala/collection/TraversableLike$$anonfun$flatMap$1 of class scala/collection/TraversableLike
  minor version: 0
  major version: 49
  Constant pool:
Asciz	SourceFile;
Asciz	TraversableLike.scala;
Asciz	<clinit>;
Asciz	()V;
Asciz	Code;
Asciz	serialVersionUID;
Asciz	J;
Asciz	scala/collection/TraversableLike$$anonfun$flatMap$1;
class	scala/collection/TraversableLike$$anonfun$flatMap$1
NameAndType	serialVersionUID:J
Field	scala/collection/TraversableLike$$anonfun$flatMap$1.serialVersionUID:J
Asciz	f$4;
Asciz	Lscala/Function1;;
Asciz	b$2;
Asciz	Lscala/collection/mutable/Builder;;
Asciz	apply;
Asciz	(Ljava/lang/Object;)Lscala/collection/mutable/Builder;;
Asciz	LineNumberTable;
NameAndType	b$2:Lscala/collection/mutable/Builder;
Field	scala/collection/TraversableLike$$anonfun$flatMap$1.b$2:Lscala/collection/mutable/Builder;
NameAndType	f$4:Lscala/Function1;
Field	scala/collection/TraversableLike$$anonfun$flatMap$1.f$4:Lscala/Function1;
Asciz	scala/Function1;
class	scala/Function1
Asciz	(Ljava/lang/Object;)Ljava/lang/Object;;
NameAndType	apply:(Ljava/lang/Object;)Ljava/lang/Object;
InterfaceMethod	scala/Function1.apply:(Ljava/lang/Object;)Ljava/lang/Object;
Asciz	scala/collection/TraversableOnce;
class	scala/collection/TraversableOnce
Asciz	scala/collection/generic/Growable;
class	scala/collection/generic/Growable
Asciz	$plus$plus$eq;
Asciz	(Lscala/collection/TraversableOnce;)Lscala/collection/generic/Growable;;
NameAndType	$plus$plus$eq:(Lscala/collection/TraversableOnce;)Lscala/collection/generic/Growable;
InterfaceMethod	scala/collection/generic/Growable.$plus$plus$eq:(Lscala/collection/TraversableOnce;)Lscala/collection/generic/Growable;
Asciz	scala/collection/mutable/Builder;
class	scala/collection/mutable/Builder
Asciz	this;
Asciz	Lscala/collection/TraversableLike$$anonfun$flatMap$1;;
Asciz	x;
Asciz	Ljava/lang/Object;;
Asciz	LocalVariableTable;
Asciz	(TA;)Lscala/collection/mutable/Builder<TB;TThat;>;;
Asciz	Signature;
NameAndType	apply:(Ljava/lang/Object;)Lscala/collection/mutable/Builder;
Method	scala/collection/TraversableLike$$anonfun$flatMap$1.apply:(Ljava/lang/Object;)Lscala/collection/mutable/Builder;
Asciz	v1;
Asciz	<init>;
Asciz	(Lscala/collection/TraversableLike;Lscala/Function1;Lscala/collection/mutable/Builder;)V;
Asciz	scala/runtime/AbstractFunction1;
class	scala/runtime/AbstractFunction1
NameAndType	"<init>":()V
Method	scala/runtime/AbstractFunction1."<init>":()V
Asciz	$outer;
Asciz	Lscala/collection/TraversableLike;;
Asciz	(Lscala/collection/TraversableLike<TA;TRepr;>;)V;
Asciz	Scala;
Asciz	InnerClasses;
Asciz	scala/collection/TraversableLike;
class	scala/collection/TraversableLike
Asciz	$anonfun$flatMap$1;
Asciz	java/io/Serializable;
class	java/io/Serializable

{
public static final long serialVersionUID;
  Signature: J

public final scala.Function1 f$4;
  Signature: Lscala/Function1;

public final scala.collection.mutable.Builder b$2;
  Signature: Lscala/collection/mutable/Builder;

public static {};
  Signature: ()V
  Code:
   Stack=2, Locals=0, Args_size=0
	lconst_0
	putstatic	Field serialVersionUID:J
	return
  Labels:

public final scala.collection.mutable.Builder apply(java.lang.Object);
  Signature: (Ljava/lang/Object;)Lscala/collection/mutable/Builder;
  Code:
   Stack=3, Locals=2, Args_size=2
	aload_0
	getfield	Field b$2:Lscala/collection/mutable/Builder;
	aload_0
	getfield	Field f$4:Lscala/Function1;
	aload_1
	invokeinterface	InterfaceMethod scala/Function1.apply:(Ljava/lang/Object;)Ljava/lang/Object;
	checkcast	class scala/collection/TraversableOnce
	invokeinterface	InterfaceMethod scala/collection/generic/Growable.$plus$plus$eq:(Lscala/collection/TraversableOnce;)Lscala/collection/generic/Growable;
	checkcast	class scala/collection/mutable/Builder
	areturn
  Labels:
  LocalVariableTable: 
   Start  Length  Slot  Name   Signature
   0      26      0    this       Lscala/collection/TraversableLike$$anonfun$flatMap$1;
   0      26      1    x       Ljava/lang/Object;

  Signature: length = 0x2
   00 2B 

public final java.lang.Object apply(java.lang.Object);
  Signature: (Ljava/lang/Object;)Ljava/lang/Object;
  Code:
   Stack=2, Locals=2, Args_size=2
	aload_0
	aload_1
	invokevirtual	Method apply:(Ljava/lang/Object;)Lscala/collection/mutable/Builder;
	areturn
  Labels:
  LocalVariableTable: 
   Start  Length  Slot  Name   Signature
   0      6      0    this       Lscala/collection/TraversableLike$$anonfun$flatMap$1;
   0      6      1    v1       Ljava/lang/Object;


public scala.collection.TraversableLike$$anonfun$flatMap$1(scala.collection.TraversableLike, scala.Function1, scala.collection.mutable.Builder);
  Signature: (Lscala/collection/TraversableLike;Lscala/Function1;Lscala/collection/mutable/Builder;)V
  Code:
   Stack=2, Locals=4, Args_size=4
	aload_0
	aload_2
	putfield	Field f$4:Lscala/Function1;
	aload_0
	aload_3
	putfield	Field b$2:Lscala/collection/mutable/Builder;
	aload_0
	invokespecial	Method scala/runtime/AbstractFunction1."<init>":()V
	return
  Labels:
  LocalVariableTable: 
   Start  Length  Slot  Name   Signature
   0      15      0    this       Lscala/collection/TraversableLike$$anonfun$flatMap$1;
   0      15      1    $outer       Lscala/collection/TraversableLike;

  Signature: length = 0x2
   00 38 

}

