Compiled from "TraversableViewLike.scala"
public abstract class scala.collection.TraversableViewLike$Appended$class extends java.lang.Object
  SourceFile: "TraversableViewLike.scala"
  Scala: length = 0x
   
  InnerClass: 
   public abstract Appended=class scala/collection/TraversableViewLike$Appended of class scala/collection/TraversableViewLike
   public final $anonfun$foreach$5=class scala/collection/TraversableViewLike$Appended$$anonfun$foreach$5 of class scala/collection/TraversableViewLike$Appended
   public final $anonfun$foreach$4=class scala/collection/TraversableViewLike$Appended$$anonfun$foreach$4 of class scala/collection/TraversableViewLike$Appended
  minor version: 0
  major version: 49
  Constant pool:
Asciz	SourceFile;
Asciz	TraversableViewLike.scala;
Asciz	$init$;
Asciz	(Lscala/collection/TraversableViewLike$Appended;)V;
Asciz	Code;
Asciz	LineNumberTable;
Asciz	$this;
Asciz	Lscala/collection/TraversableViewLike$Appended;;
Asciz	LocalVariableTable;
Asciz	stringPrefix;
Asciz	(Lscala/collection/TraversableViewLike$Appended;)Ljava/lang/String;;
Asciz	scala/collection/mutable/StringBuilder;
class	scala/collection/mutable/StringBuilder
Asciz	<init>;
Asciz	()V;
NameAndType	"<init>":()V
Method	scala/collection/mutable/StringBuilder."<init>":()V
Asciz	scala/collection/TraversableViewLike$Appended;
class	scala/collection/TraversableViewLike$Appended
Asciz	scala$collection$TraversableViewLike$Appended$$$outer;
Asciz	()Lscala/collection/TraversableViewLike;;
NameAndType	scala$collection$TraversableViewLike$Appended$$$outer:()Lscala/collection/TraversableViewLike;
InterfaceMethod	scala/collection/TraversableViewLike$Appended.scala$collection$TraversableViewLike$Appended$$$outer:()Lscala/collection/TraversableViewLike;
Asciz	scala/collection/TraversableViewLike;
class	scala/collection/TraversableViewLike
Asciz	()Ljava/lang/String;;
NameAndType	stringPrefix:()Ljava/lang/String;
InterfaceMethod	scala/collection/TraversableViewLike.stringPrefix:()Ljava/lang/String;
Asciz	append;
Asciz	(Ljava/lang/Object;)Lscala/collection/mutable/StringBuilder;;
NameAndType	append:(Ljava/lang/Object;)Lscala/collection/mutable/StringBuilder;
Method	scala/collection/mutable/StringBuilder.append:(Ljava/lang/Object;)Lscala/collection/mutable/StringBuilder;
Asciz	A;
String	A
Asciz	toString;
NameAndType	toString:()Ljava/lang/String;
Method	scala/collection/mutable/StringBuilder.toString:()Ljava/lang/String;
Asciz	foreach;
Asciz	(Lscala/collection/TraversableViewLike$Appended;Lscala/Function1;)V;
Asciz	scala/collection/TraversableViewLike$Appended$$anonfun$foreach$4;
class	scala/collection/TraversableViewLike$Appended$$anonfun$foreach$4
NameAndType	"<init>":(Lscala/collection/TraversableViewLike$Appended;Lscala/Function1;)V
Method	scala/collection/TraversableViewLike$Appended$$anonfun$foreach$4."<init>":(Lscala/collection/TraversableViewLike$Appended;Lscala/Function1;)V
Asciz	scala/collection/generic/GenericTraversableTemplate;
class	scala/collection/generic/GenericTraversableTemplate
Asciz	(Lscala/Function1;)V;
NameAndType	foreach:(Lscala/Function1;)V
InterfaceMethod	scala/collection/generic/GenericTraversableTemplate.foreach:(Lscala/Function1;)V
Asciz	rest;
Asciz	()Lscala/collection/Traversable;;
NameAndType	rest:()Lscala/collection/Traversable;
InterfaceMethod	scala/collection/TraversableViewLike$Appended.rest:()Lscala/collection/Traversable;
Asciz	scala/collection/TraversableViewLike$Appended$$anonfun$foreach$5;
class	scala/collection/TraversableViewLike$Appended$$anonfun$foreach$5
Method	scala/collection/TraversableViewLike$Appended$$anonfun$foreach$5."<init>":(Lscala/collection/TraversableViewLike$Appended;Lscala/Function1;)V
Asciz	f$6;
Asciz	Lscala/Function1;;
Asciz	Scala;
Asciz	InnerClasses;
Asciz	Appended;
Asciz	$anonfun$foreach$5;
Asciz	$anonfun$foreach$4;
Asciz	scala/collection/TraversableViewLike$Appended$class;
class	scala/collection/TraversableViewLike$Appended$class
Asciz	java/lang/Object;
class	java/lang/Object

{
public static void $init$(scala.collection.TraversableViewLike$Appended);
  Signature: (Lscala/collection/TraversableViewLike$Appended;)V
  Code:
   Stack=0, Locals=1, Args_size=1
	return
  Labels:
  LocalVariableTable: 
   Start  Length  Slot  Name   Signature
   0      1      0    $this       Lscala/collection/TraversableViewLike$Appended;


public static java.lang.String stringPrefix(scala.collection.TraversableViewLike$Appended);
  Signature: (Lscala/collection/TraversableViewLike$Appended;)Ljava/lang/String;
  Code:
   Stack=2, Locals=1, Args_size=1
	new	class scala/collection/mutable/StringBuilder
	dup
	invokespecial	Method scala/collection/mutable/StringBuilder."<init>":()V
	aload_0
	invokeinterface	InterfaceMethod scala/collection/TraversableViewLike$Appended.scala$collection$TraversableViewLike$Appended$$$outer:()Lscala/collection/TraversableViewLike;
	invokeinterface	InterfaceMethod scala/collection/TraversableViewLike.stringPrefix:()Ljava/lang/String;
	invokevirtual	Method scala/collection/mutable/StringBuilder.append:(Ljava/lang/Object;)Lscala/collection/mutable/StringBuilder;
	ldc	String A
	invokevirtual	Method scala/collection/mutable/StringBuilder.append:(Ljava/lang/Object;)Lscala/collection/mutable/StringBuilder;
	invokevirtual	Method scala/collection/mutable/StringBuilder.toString:()Ljava/lang/String;
	areturn
  Labels:
  LocalVariableTable: 
   Start  Length  Slot  Name   Signature
   0      30      0    $this       Lscala/collection/TraversableViewLike$Appended;


public static void foreach(scala.collection.TraversableViewLike$Appended, scala.Function1);
  Signature: (Lscala/collection/TraversableViewLike$Appended;Lscala/Function1;)V
  Code:
   Stack=5, Locals=2, Args_size=2
	aload_0
	invokeinterface	InterfaceMethod scala/collection/TraversableViewLike$Appended.scala$collection$TraversableViewLike$Appended$$$outer:()Lscala/collection/TraversableViewLike;
	new	class scala/collection/TraversableViewLike$Appended$$anonfun$foreach$4
	dup
	aload_0
	aload_1
	invokespecial	Method scala/collection/TraversableViewLike$Appended$$anonfun$foreach$4."<init>":(Lscala/collection/TraversableViewLike$Appended;Lscala/Function1;)V
	invokeinterface	InterfaceMethod scala/collection/generic/GenericTraversableTemplate.foreach:(Lscala/Function1;)V
	aload_0
	invokeinterface	InterfaceMethod scala/collection/TraversableViewLike$Appended.rest:()Lscala/collection/Traversable;
	new	class scala/collection/TraversableViewLike$Appended$$anonfun$foreach$5
	dup
	aload_0
	aload_1
	invokespecial	Method scala/collection/TraversableViewLike$Appended$$anonfun$foreach$5."<init>":(Lscala/collection/TraversableViewLike$Appended;Lscala/Function1;)V
	invokeinterface	InterfaceMethod scala/collection/generic/GenericTraversableTemplate.foreach:(Lscala/Function1;)V
	return
  Labels:
  LocalVariableTable: 
   Start  Length  Slot  Name   Signature
   0      41      0    $this       Lscala/collection/TraversableViewLike$Appended;
   0      41      1    f$6       Lscala/Function1;


}

