Compiled from "Traversable.scala"
public class scala.collection.Traversable$NumericTraversableOps extends java.lang.Object implements scala.ScalaObject
  SourceFile: "Traversable.scala"
  Signature: length = 0x2
   00 43 
  Scala: length = 0x
   
  InnerClass: 
   public #72= #14 of #71; //NumericTraversableOps=class scala/collection/Traversable$NumericTraversableOps of class scala/collection/Traversable
   public final #73= #64 of #14; //$anonfun$sum$1=class scala/collection/Traversable$NumericTraversableOps$$anonfun$sum$1 of class scala/collection/Traversable$NumericTraversableOps
   public final #74= #42 of #14; //$anonfun$product$1=class scala/collection/Traversable$NumericTraversableOps$$anonfun$product$1 of class scala/collection/Traversable$NumericTraversableOps
  minor version: 0
  major version: 49
  Constant pool:
const #1 = Asciz	SourceFile;
const #2 = Asciz	Traversable.scala;
const #3 = Asciz	scala$collection$Traversable$NumericTraversableOps$$num;
const #4 = Asciz	Lscala/Numeric;;
const #5 = Asciz	self;
const #6 = Asciz	Lscala/collection/Traversable;;
const #7 = Asciz	Lscala/collection/Traversable<TA;>;;
const #8 = Asciz	Signature;
const #9 = Asciz	<init>;
const #10 = Asciz	(Lscala/collection/Traversable;Lscala/Numeric;)V;
const #11 = Asciz	Code;
const #12 = Asciz	LineNumberTable;
const #13 = Asciz	scala/collection/Traversable$NumericTraversableOps;
const #14 = class	#13;	//  scala/collection/Traversable$NumericTraversableOps
const #15 = NameAndType	#5:#6;//  self:Lscala/collection/Traversable;
const #16 = Field	#14.#15;	//  scala/collection/Traversable$NumericTraversableOps.self:Lscala/collection/Traversable;
const #17 = NameAndType	#3:#4;//  scala$collection$Traversable$NumericTraversableOps$$num:Lscala/Numeric;
const #18 = Field	#14.#17;	//  scala/collection/Traversable$NumericTraversableOps.scala$collection$Traversable$NumericTraversableOps$$num:Lscala/Numeric;
const #19 = Asciz	java/lang/Object;
const #20 = class	#19;	//  java/lang/Object
const #21 = Asciz	()V;
const #22 = NameAndType	#9:#21;//  "<init>":()V
const #23 = Method	#20.#22;	//  java/lang/Object."<init>":()V
const #24 = Asciz	this;
const #25 = Asciz	Lscala/collection/Traversable$NumericTraversableOps;;
const #26 = Asciz	num;
const #27 = Asciz	LocalVariableTable;
const #28 = Asciz	(Lscala/collection/Traversable<TA;>;Lscala/Numeric<TA;>;)V;
const #29 = Asciz	product;
const #30 = Asciz	()Ljava/lang/Object;;
const #31 = Asciz	scala/runtime/ObjectRef;
const #32 = class	#31;	//  scala/runtime/ObjectRef
const #33 = Asciz	scala/Numeric;
const #34 = class	#33;	//  scala/Numeric
const #35 = Asciz	one;
const #36 = NameAndType	#35:#30;//  one:()Ljava/lang/Object;
const #37 = InterfaceMethod	#34.#36;	//  scala/Numeric.one:()Ljava/lang/Object;
const #38 = Asciz	(Ljava/lang/Object;)V;
const #39 = NameAndType	#9:#38;//  "<init>":(Ljava/lang/Object;)V
const #40 = Method	#32.#39;	//  scala/runtime/ObjectRef."<init>":(Ljava/lang/Object;)V
const #41 = Asciz	scala/collection/Traversable$NumericTraversableOps$$anonfun$product$1;
const #42 = class	#41;	//  scala/collection/Traversable$NumericTraversableOps$$anonfun$product$1
const #43 = Asciz	(Lscala/collection/Traversable$NumericTraversableOps;Lscala/runtime/ObjectRef;)V;
const #44 = NameAndType	#9:#43;//  "<init>":(Lscala/collection/Traversable$NumericTraversableOps;Lscala/runtime/ObjectRef;)V
const #45 = Method	#42.#44;	//  scala/collection/Traversable$NumericTraversableOps$$anonfun$product$1."<init>":(Lscala/collection/Traversable$NumericTraversableOps;Lscala/runtime/ObjectRef;)V
const #46 = Asciz	scala/collection/generic/TraversableClass;
const #47 = class	#46;	//  scala/collection/generic/TraversableClass
const #48 = Asciz	foreach;
const #49 = Asciz	(Lscala/Function1;)V;
const #50 = NameAndType	#48:#49;//  foreach:(Lscala/Function1;)V
const #51 = InterfaceMethod	#47.#50;	//  scala/collection/generic/TraversableClass.foreach:(Lscala/Function1;)V
const #52 = Asciz	elem;
const #53 = Asciz	Ljava/lang/Object;;
const #54 = NameAndType	#52:#53;//  elem:Ljava/lang/Object;
const #55 = Field	#32.#54;	//  scala/runtime/ObjectRef.elem:Ljava/lang/Object;
const #56 = Asciz	acc$4;
const #57 = Asciz	Lscala/runtime/ObjectRef;;
const #58 = Asciz	()TA;;
const #59 = Asciz	sum;
const #60 = Asciz	zero;
const #61 = NameAndType	#60:#30;//  zero:()Ljava/lang/Object;
const #62 = InterfaceMethod	#34.#61;	//  scala/Numeric.zero:()Ljava/lang/Object;
const #63 = Asciz	scala/collection/Traversable$NumericTraversableOps$$anonfun$sum$1;
const #64 = class	#63;	//  scala/collection/Traversable$NumericTraversableOps$$anonfun$sum$1
const #65 = Method	#64.#44;	//  scala/collection/Traversable$NumericTraversableOps$$anonfun$sum$1."<init>":(Lscala/collection/Traversable$NumericTraversableOps;Lscala/runtime/ObjectRef;)V
const #66 = Asciz	acc$3;
const #67 = Asciz	<A:Ljava/lang/Object;>Ljava/lang/Object;Lscala/ScalaObject;;
const #68 = Asciz	Scala;
const #69 = Asciz	InnerClasses;
const #70 = Asciz	scala/collection/Traversable;
const #71 = class	#70;	//  scala/collection/Traversable
const #72 = Asciz	NumericTraversableOps;
const #73 = Asciz	$anonfun$sum$1;
const #74 = Asciz	$anonfun$product$1;
const #75 = Asciz	scala/ScalaObject;
const #76 = class	#75;	//  scala/ScalaObject

{
public final scala.Numeric scala$collection$Traversable$NumericTraversableOps$$num;

public scala.collection.Traversable$NumericTraversableOps(scala.collection.Traversable, scala.Numeric);
  Code:
   Stack=2, Locals=3, Args_size=3
   0:	aload_0
   1:	aload_1
   2:	putfield	#16; //Field self:Lscala/collection/Traversable;
   5:	aload_0
   6:	aload_2
   7:	putfield	#18; //Field scala$collection$Traversable$NumericTraversableOps$$num:Lscala/Numeric;
   10:	aload_0
   11:	invokespecial	#23; //Method java/lang/Object."<init>":()V
   14:	return
  LineNumberTable: 
   line 131: 0

  LocalVariableTable: 
   Start  Length  Slot  Name   Signature
   0      15      0    this       Lscala/collection/Traversable$NumericTraversableOps;
   0      15      1    self       Lscala/collection/Traversable;
   0      15      2    num       Lscala/Numeric;

  Signature: length = 0x2
   00 1C 

public java.lang.Object product();
  Code:
   Stack=5, Locals=2, Args_size=1
   0:	new	#32; //class scala/runtime/ObjectRef
   3:	dup
   4:	aload_0
   5:	getfield	#18; //Field scala$collection$Traversable$NumericTraversableOps$$num:Lscala/Numeric;
   8:	invokeinterface	#37,  1; //InterfaceMethod scala/Numeric.one:()Ljava/lang/Object;
   13:	invokespecial	#40; //Method scala/runtime/ObjectRef."<init>":(Ljava/lang/Object;)V
   16:	astore_1
   17:	aload_0
   18:	getfield	#16; //Field self:Lscala/collection/Traversable;
   21:	new	#42; //class scala/collection/Traversable$NumericTraversableOps$$anonfun$product$1
   24:	dup
   25:	aload_0
   26:	aload_1
   27:	invokespecial	#45; //Method scala/collection/Traversable$NumericTraversableOps$$anonfun$product$1."<init>":(Lscala/collection/Traversable$NumericTraversableOps;Lscala/runtime/ObjectRef;)V
   30:	invokeinterface	#51,  2; //InterfaceMethod scala/collection/generic/TraversableClass.foreach:(Lscala/Function1;)V
   35:	aload_1
   36:	getfield	#55; //Field scala/runtime/ObjectRef.elem:Ljava/lang/Object;
   39:	areturn
  LineNumberTable: 
   line 142: 0
   line 143: 17
   line 144: 35

  LocalVariableTable: 
   Start  Length  Slot  Name   Signature
   0      40      0    this       Lscala/collection/Traversable$NumericTraversableOps;
   17      22      1    acc$4       Lscala/runtime/ObjectRef;

  Signature: length = 0x2
   00 3A 

public java.lang.Object sum();
  Code:
   Stack=5, Locals=2, Args_size=1
   0:	new	#32; //class scala/runtime/ObjectRef
   3:	dup
   4:	aload_0
   5:	getfield	#18; //Field scala$collection$Traversable$NumericTraversableOps$$num:Lscala/Numeric;
   8:	invokeinterface	#62,  1; //InterfaceMethod scala/Numeric.zero:()Ljava/lang/Object;
   13:	invokespecial	#40; //Method scala/runtime/ObjectRef."<init>":(Ljava/lang/Object;)V
   16:	astore_1
   17:	aload_0
   18:	getfield	#16; //Field self:Lscala/collection/Traversable;
   21:	new	#64; //class scala/collection/Traversable$NumericTraversableOps$$anonfun$sum$1
   24:	dup
   25:	aload_0
   26:	aload_1
   27:	invokespecial	#65; //Method scala/collection/Traversable$NumericTraversableOps$$anonfun$sum$1."<init>":(Lscala/collection/Traversable$NumericTraversableOps;Lscala/runtime/ObjectRef;)V
   30:	invokeinterface	#51,  2; //InterfaceMethod scala/collection/generic/TraversableClass.foreach:(Lscala/Function1;)V
   35:	aload_1
   36:	getfield	#55; //Field scala/runtime/ObjectRef.elem:Ljava/lang/Object;
   39:	areturn
  LineNumberTable: 
   line 135: 0
   line 136: 17
   line 137: 35

  LocalVariableTable: 
   Start  Length  Slot  Name   Signature
   0      40      0    this       Lscala/collection/Traversable$NumericTraversableOps;
   17      22      1    acc$3       Lscala/runtime/ObjectRef;

  Signature: length = 0x2
   00 3A 

}

