Compiled from "TraversableLike.scala"
public class scala.collection.TraversableLike$WithFilter extends java.lang.Object implements scala.ScalaObject
  SourceFile: "TraversableLike.scala"
  Scala: length = 0x
   
  InnerClass: 
   public #94= #12 of #52; //WithFilter=class scala/collection/TraversableLike$WithFilter of class scala/collection/TraversableLike
   public final #95= #87 of #12; //$anonfun$map$2=class scala/collection/TraversableLike$WithFilter$$anonfun$map$2 of class scala/collection/TraversableLike$WithFilter
   public final #96= #70 of #12; //$anonfun$flatMap$2=class scala/collection/TraversableLike$WithFilter$$anonfun$flatMap$2 of class scala/collection/TraversableLike$WithFilter
   public final #97= #49 of #12; //$anonfun$foreach$1=class scala/collection/TraversableLike$WithFilter$$anonfun$foreach$1 of class scala/collection/TraversableLike$WithFilter
   public final #98= #38 of #12; //$anonfun$withFilter$1=class scala/collection/TraversableLike$WithFilter$$anonfun$withFilter$1 of class scala/collection/TraversableLike$WithFilter
  minor version: 0
  major version: 49
  Constant pool:
const #1 = Asciz	SourceFile;
const #2 = Asciz	TraversableLike.scala;
const #3 = Asciz	$outer;
const #4 = Asciz	Lscala/collection/TraversableLike;;
const #5 = Asciz	scala$collection$TraversableLike$WithFilter$$p;
const #6 = Asciz	Lscala/Function1;;
const #7 = Asciz	<init>;
const #8 = Asciz	(Lscala/collection/TraversableLike;Lscala/Function1;)V;
const #9 = Asciz	Code;
const #10 = Asciz	LineNumberTable;
const #11 = Asciz	scala/collection/TraversableLike$WithFilter;
const #12 = class	#11;	//  scala/collection/TraversableLike$WithFilter
const #13 = NameAndType	#5:#6;//  scala$collection$TraversableLike$WithFilter$$p:Lscala/Function1;
const #14 = Field	#12.#13;	//  scala/collection/TraversableLike$WithFilter.scala$collection$TraversableLike$WithFilter$$p:Lscala/Function1;
const #15 = Asciz	java/lang/NullPointerException;
const #16 = class	#15;	//  java/lang/NullPointerException
const #17 = Asciz	()V;
const #18 = NameAndType	#7:#17;//  "<init>":()V
const #19 = Method	#16.#18;	//  java/lang/NullPointerException."<init>":()V
const #20 = NameAndType	#3:#4;//  $outer:Lscala/collection/TraversableLike;
const #21 = Field	#12.#20;	//  scala/collection/TraversableLike$WithFilter.$outer:Lscala/collection/TraversableLike;
const #22 = Asciz	java/lang/Object;
const #23 = class	#22;	//  java/lang/Object
const #24 = Method	#23.#18;	//  java/lang/Object."<init>":()V
const #25 = Asciz	this;
const #26 = Asciz	Lscala/collection/TraversableLike$WithFilter;;
const #27 = Asciz	p;
const #28 = Asciz	LocalVariableTable;
const #29 = Asciz	(Lscala/collection/TraversableLike<TA;TRepr;>;Lscala/Function1<TA;Ljava/lang/Boolean;>;)V;
const #30 = Asciz	Signature;
const #31 = Asciz	scala$collection$TraversableLike$WithFilter$$$outer;
const #32 = Asciz	()Lscala/collection/TraversableLike;;
const #33 = Asciz	withFilter;
const #34 = Asciz	(Lscala/Function1;)Lscala/collection/TraversableLike$WithFilter;;
const #35 = NameAndType	#31:#32;//  scala$collection$TraversableLike$WithFilter$$$outer:()Lscala/collection/TraversableLike;
const #36 = Method	#12.#35;	//  scala/collection/TraversableLike$WithFilter.scala$collection$TraversableLike$WithFilter$$$outer:()Lscala/collection/TraversableLike;
const #37 = Asciz	scala/collection/TraversableLike$WithFilter$$anonfun$withFilter$1;
const #38 = class	#37;	//  scala/collection/TraversableLike$WithFilter$$anonfun$withFilter$1
const #39 = Asciz	(Lscala/collection/TraversableLike$WithFilter;Lscala/Function1;)V;
const #40 = NameAndType	#7:#39;//  "<init>":(Lscala/collection/TraversableLike$WithFilter;Lscala/Function1;)V
const #41 = Method	#38.#40;	//  scala/collection/TraversableLike$WithFilter$$anonfun$withFilter$1."<init>":(Lscala/collection/TraversableLike$WithFilter;Lscala/Function1;)V
const #42 = NameAndType	#7:#8;//  "<init>":(Lscala/collection/TraversableLike;Lscala/Function1;)V
const #43 = Method	#12.#42;	//  scala/collection/TraversableLike$WithFilter."<init>":(Lscala/collection/TraversableLike;Lscala/Function1;)V
const #44 = Asciz	q$1;
const #45 = Asciz	(Lscala/Function1<TA;Ljava/lang/Boolean;>;)Lscala/collection/TraversableLike<TA;TRepr;>.WithFilter;;
const #46 = Asciz	foreach;
const #47 = Asciz	(Lscala/Function1;)V;
const #48 = Asciz	scala/collection/TraversableLike$WithFilter$$anonfun$foreach$1;
const #49 = class	#48;	//  scala/collection/TraversableLike$WithFilter$$anonfun$foreach$1
const #50 = Method	#49.#40;	//  scala/collection/TraversableLike$WithFilter$$anonfun$foreach$1."<init>":(Lscala/collection/TraversableLike$WithFilter;Lscala/Function1;)V
const #51 = Asciz	scala/collection/TraversableLike;
const #52 = class	#51;	//  scala/collection/TraversableLike
const #53 = NameAndType	#46:#47;//  foreach:(Lscala/Function1;)V
const #54 = InterfaceMethod	#52.#53;	//  scala/collection/TraversableLike.foreach:(Lscala/Function1;)V
const #55 = Asciz	f$2;
const #56 = Asciz	<U:Ljava/lang/Object;>(Lscala/Function1<TA;TU;>;)V;
const #57 = Asciz	flatMap;
const #58 = Asciz	(Lscala/Function1;Lscala/collection/generic/CanBuildFrom;)Ljava/lang/Object;;
const #59 = Asciz	repr;
const #60 = Asciz	()Ljava/lang/Object;;
const #61 = NameAndType	#59:#60;//  repr:()Ljava/lang/Object;
const #62 = InterfaceMethod	#52.#61;	//  scala/collection/TraversableLike.repr:()Ljava/lang/Object;
const #63 = Asciz	scala/collection/generic/CanBuildFrom;
const #64 = class	#63;	//  scala/collection/generic/CanBuildFrom
const #65 = Asciz	apply;
const #66 = Asciz	(Ljava/lang/Object;)Lscala/collection/mutable/Builder;;
const #67 = NameAndType	#65:#66;//  apply:(Ljava/lang/Object;)Lscala/collection/mutable/Builder;
const #68 = InterfaceMethod	#64.#67;	//  scala/collection/generic/CanBuildFrom.apply:(Ljava/lang/Object;)Lscala/collection/mutable/Builder;
const #69 = Asciz	scala/collection/TraversableLike$WithFilter$$anonfun$flatMap$2;
const #70 = class	#69;	//  scala/collection/TraversableLike$WithFilter$$anonfun$flatMap$2
const #71 = Asciz	(Lscala/collection/TraversableLike$WithFilter;Lscala/Function1;Lscala/collection/mutable/Builder;)V;
const #72 = NameAndType	#7:#71;//  "<init>":(Lscala/collection/TraversableLike$WithFilter;Lscala/Function1;Lscala/collection/mutable/Builder;)V
const #73 = Method	#70.#72;	//  scala/collection/TraversableLike$WithFilter$$anonfun$flatMap$2."<init>":(Lscala/collection/TraversableLike$WithFilter;Lscala/Function1;Lscala/collection/mutable/Builder;)V
const #74 = Asciz	scala/collection/mutable/Builder;
const #75 = class	#74;	//  scala/collection/mutable/Builder
const #76 = Asciz	result;
const #77 = NameAndType	#76:#60;//  result:()Ljava/lang/Object;
const #78 = InterfaceMethod	#75.#77;	//  scala/collection/mutable/Builder.result:()Ljava/lang/Object;
const #79 = Asciz	f$6;
const #80 = Asciz	bf;
const #81 = Asciz	Lscala/collection/generic/CanBuildFrom;;
const #82 = Asciz	b$13;
const #83 = Asciz	Lscala/collection/mutable/Builder;;
const #84 = Asciz	<B:Ljava/lang/Object;That:Ljava/lang/Object;>(Lscala/Function1<TA;Lscala/collection/Traversable<TB;>;>;Lscala/collection/generic/CanBuildFrom<TRepr;TB;TThat;>;)TThat;;
const #85 = Asciz	map;
const #86 = Asciz	scala/collection/TraversableLike$WithFilter$$anonfun$map$2;
const #87 = class	#86;	//  scala/collection/TraversableLike$WithFilter$$anonfun$map$2
const #88 = Method	#87.#72;	//  scala/collection/TraversableLike$WithFilter$$anonfun$map$2."<init>":(Lscala/collection/TraversableLike$WithFilter;Lscala/Function1;Lscala/collection/mutable/Builder;)V
const #89 = Asciz	f$5;
const #90 = Asciz	b$12;
const #91 = Asciz	<B:Ljava/lang/Object;That:Ljava/lang/Object;>(Lscala/Function1<TA;TB;>;Lscala/collection/generic/CanBuildFrom<TRepr;TB;TThat;>;)TThat;;
const #92 = Asciz	Scala;
const #93 = Asciz	InnerClasses;
const #94 = Asciz	WithFilter;
const #95 = Asciz	$anonfun$map$2;
const #96 = Asciz	$anonfun$flatMap$2;
const #97 = Asciz	$anonfun$foreach$1;
const #98 = Asciz	$anonfun$withFilter$1;
const #99 = Asciz	scala/ScalaObject;
const #100 = class	#99;	//  scala/ScalaObject

{
public final scala.collection.TraversableLike $outer;

public final scala.Function1 scala$collection$TraversableLike$WithFilter$$p;

public scala.collection.TraversableLike$WithFilter(scala.collection.TraversableLike, scala.Function1);
  Code:
   Stack=2, Locals=3, Args_size=3
   0:	aload_0
   1:	aload_2
   2:	putfield	#14; //Field scala$collection$TraversableLike$WithFilter$$p:Lscala/Function1;
   5:	aload_1
   6:	ifnonnull	17
   9:	new	#16; //class java/lang/NullPointerException
   12:	dup
   13:	invokespecial	#19; //Method java/lang/NullPointerException."<init>":()V
   16:	athrow
   17:	aload_0
   18:	aload_1
   19:	putfield	#21; //Field $outer:Lscala/collection/TraversableLike;
   22:	aload_0
   23:	invokespecial	#24; //Method java/lang/Object."<init>":()V
   26:	return
  LineNumberTable: 
   line 1153: 0

  LocalVariableTable: 
   Start  Length  Slot  Name   Signature
   0      27      0    this       Lscala/collection/TraversableLike$WithFilter;
   0      27      1    $outer       Lscala/collection/TraversableLike;
   0      27      2    p       Lscala/Function1;

  Signature: length = 0x2
   00 1D 

public scala.collection.TraversableLike scala$collection$TraversableLike$WithFilter$$$outer();
  Code:
   Stack=1, Locals=1, Args_size=1
   0:	aload_0
   1:	getfield	#21; //Field $outer:Lscala/collection/TraversableLike;
   4:	areturn
  LineNumberTable: 
   line 1153: 0


public scala.collection.TraversableLike$WithFilter withFilter(scala.Function1);
  Code:
   Stack=7, Locals=2, Args_size=2
   0:	new	#12; //class scala/collection/TraversableLike$WithFilter
   3:	dup
   4:	aload_0
   5:	invokevirtual	#36; //Method scala$collection$TraversableLike$WithFilter$$$outer:()Lscala/collection/TraversableLike;
   8:	new	#38; //class scala/collection/TraversableLike$WithFilter$$anonfun$withFilter$1
   11:	dup
   12:	aload_0
   13:	aload_1
   14:	invokespecial	#41; //Method scala/collection/TraversableLike$WithFilter$$anonfun$withFilter$1."<init>":(Lscala/collection/TraversableLike$WithFilter;Lscala/Function1;)V
   17:	invokespecial	#43; //Method "<init>":(Lscala/collection/TraversableLike;Lscala/Function1;)V
   20:	areturn
  LineNumberTable: 
   line 1233: 0

  LocalVariableTable: 
   Start  Length  Slot  Name   Signature
   0      21      0    this       Lscala/collection/TraversableLike$WithFilter;
   0      21      1    q$1       Lscala/Function1;

  Signature: length = 0x2
   00 2D 

public void foreach(scala.Function1);
  Code:
   Stack=5, Locals=2, Args_size=2
   0:	aload_0
   1:	invokevirtual	#36; //Method scala$collection$TraversableLike$WithFilter$$$outer:()Lscala/collection/TraversableLike;
   4:	new	#49; //class scala/collection/TraversableLike$WithFilter$$anonfun$foreach$1
   7:	dup
   8:	aload_0
   9:	aload_1
   10:	invokespecial	#50; //Method scala/collection/TraversableLike$WithFilter$$anonfun$foreach$1."<init>":(Lscala/collection/TraversableLike$WithFilter;Lscala/Function1;)V
   13:	invokeinterface	#54,  2; //InterfaceMethod scala/collection/TraversableLike.foreach:(Lscala/Function1;)V
   18:	return
  LineNumberTable: 
   line 1221: 0

  LocalVariableTable: 
   Start  Length  Slot  Name   Signature
   0      19      0    this       Lscala/collection/TraversableLike$WithFilter;
   0      19      1    f$2       Lscala/Function1;

  Signature: length = 0x2
   00 38 

public java.lang.Object flatMap(scala.Function1, scala.collection.generic.CanBuildFrom);
  Code:
   Stack=6, Locals=4, Args_size=3
   0:	aload_2
   1:	aload_0
   2:	invokevirtual	#36; //Method scala$collection$TraversableLike$WithFilter$$$outer:()Lscala/collection/TraversableLike;
   5:	invokeinterface	#62,  1; //InterfaceMethod scala/collection/TraversableLike.repr:()Ljava/lang/Object;
   10:	invokeinterface	#68,  2; //InterfaceMethod scala/collection/generic/CanBuildFrom.apply:(Ljava/lang/Object;)Lscala/collection/mutable/Builder;
   15:	astore_3
   16:	aload_0
   17:	invokevirtual	#36; //Method scala$collection$TraversableLike$WithFilter$$$outer:()Lscala/collection/TraversableLike;
   20:	new	#70; //class scala/collection/TraversableLike$WithFilter$$anonfun$flatMap$2
   23:	dup
   24:	aload_0
   25:	aload_1
   26:	aload_3
   27:	invokespecial	#73; //Method scala/collection/TraversableLike$WithFilter$$anonfun$flatMap$2."<init>":(Lscala/collection/TraversableLike$WithFilter;Lscala/Function1;Lscala/collection/mutable/Builder;)V
   30:	invokeinterface	#54,  2; //InterfaceMethod scala/collection/TraversableLike.foreach:(Lscala/Function1;)V
   35:	aload_3
   36:	invokeinterface	#78,  1; //InterfaceMethod scala/collection/mutable/Builder.result:()Ljava/lang/Object;
   41:	areturn
  LineNumberTable: 
   line 1199: 0
   line 1200: 16
   line 1202: 35

  LocalVariableTable: 
   Start  Length  Slot  Name   Signature
   0      42      0    this       Lscala/collection/TraversableLike$WithFilter;
   0      42      1    f$6       Lscala/Function1;
   0      42      2    bf       Lscala/collection/generic/CanBuildFrom;
   16      25      3    b$13       Lscala/collection/mutable/Builder;

  Signature: length = 0x2
   00 54 

public java.lang.Object map(scala.Function1, scala.collection.generic.CanBuildFrom);
  Code:
   Stack=6, Locals=4, Args_size=3
   0:	aload_2
   1:	aload_0
   2:	invokevirtual	#36; //Method scala$collection$TraversableLike$WithFilter$$$outer:()Lscala/collection/TraversableLike;
   5:	invokeinterface	#62,  1; //InterfaceMethod scala/collection/TraversableLike.repr:()Ljava/lang/Object;
   10:	invokeinterface	#68,  2; //InterfaceMethod scala/collection/generic/CanBuildFrom.apply:(Ljava/lang/Object;)Lscala/collection/mutable/Builder;
   15:	astore_3
   16:	aload_0
   17:	invokevirtual	#36; //Method scala$collection$TraversableLike$WithFilter$$$outer:()Lscala/collection/TraversableLike;
   20:	new	#87; //class scala/collection/TraversableLike$WithFilter$$anonfun$map$2
   23:	dup
   24:	aload_0
   25:	aload_1
   26:	aload_3
   27:	invokespecial	#88; //Method scala/collection/TraversableLike$WithFilter$$anonfun$map$2."<init>":(Lscala/collection/TraversableLike$WithFilter;Lscala/Function1;Lscala/collection/mutable/Builder;)V
   30:	invokeinterface	#54,  2; //InterfaceMethod scala/collection/TraversableLike.foreach:(Lscala/Function1;)V
   35:	aload_3
   36:	invokeinterface	#78,  1; //InterfaceMethod scala/collection/mutable/Builder.result:()Ljava/lang/Object;
   41:	areturn
  LineNumberTable: 
   line 1175: 0
   line 1176: 16
   line 1178: 35

  LocalVariableTable: 
   Start  Length  Slot  Name   Signature
   0      42      0    this       Lscala/collection/TraversableLike$WithFilter;
   0      42      1    f$5       Lscala/Function1;
   0      42      2    bf       Lscala/collection/generic/CanBuildFrom;
   16      25      3    b$12       Lscala/collection/mutable/Builder;

  Signature: length = 0x2
   00 5B 

}

