Compiled from "TraversableLike.scala"
public final class scala.collection.TraversableLike$$anonfun$filterNot$1 extends scala.runtime.AbstractFunction1 implements java.io.Serializable
  InnerClass: 
   public final $anonfun$filterNot$1=class scala/collection/TraversableLike$$anonfun$filterNot$1 of class scala/collection/TraversableLike
  Scala: length = 0x
   
  SourceFile: "TraversableLike.scala"
  minor version: 0
  major version: 49
  Constant pool:
class	java/io/Serializable
class	scala/Function1
class	scala/collection/TraversableLike
class	scala/collection/TraversableLike$$anonfun$filterNot$1
class	scala/runtime/AbstractFunction1
class	scala/runtime/BoxesRunTime
Field	scala/collection/TraversableLike$$anonfun$filterNot$1.p$9:Lscala/Function1;
Field	scala/collection/TraversableLike$$anonfun$filterNot$1.serialVersionUID:J
Method	scala/collection/TraversableLike$$anonfun$filterNot$1.apply:(Ljava/lang/Object;)Z
Method	scala/runtime/AbstractFunction1."<init>":()V
Method	scala/runtime/BoxesRunTime.boxToBoolean:(Z)Ljava/lang/Boolean;
Method	scala/runtime/BoxesRunTime.unboxToBoolean:(Ljava/lang/Object;)Z
InterfaceMethod	scala/Function1.apply:(Ljava/lang/Object;)Ljava/lang/Object;
NameAndType	"<init>":()V
NameAndType	apply:(Ljava/lang/Object;)Ljava/lang/Object;
NameAndType	apply:(Ljava/lang/Object;)Z
NameAndType	boxToBoolean:(Z)Ljava/lang/Boolean;
NameAndType	p$9:Lscala/Function1;
NameAndType	serialVersionUID:J
NameAndType	unboxToBoolean:(Ljava/lang/Object;)Z
Asciz	$anonfun$filterNot$1;
Asciz	$outer;
Asciz	()V;
Asciz	(Ljava/lang/Object;)Ljava/lang/Object;;
Asciz	(Ljava/lang/Object;)Z;
Asciz	(Lscala/collection/TraversableLike;Lscala/Function1;)V;
Asciz	(Lscala/collection/TraversableLike<TA;TRepr;>;)V;
Asciz	(TA;)Z;
Asciz	(Z)Ljava/lang/Boolean;;
Asciz	<clinit>;
Asciz	<init>;
Asciz	Code;
Asciz	InnerClasses;
Asciz	J;
Asciz	LineNumberTable;
Asciz	Ljava/lang/Object;;
Asciz	LocalVariableTable;
Asciz	Lscala/Function1;;
Asciz	Lscala/collection/TraversableLike$$anonfun$filterNot$1;;
Asciz	Lscala/collection/TraversableLike;;
Asciz	Scala;
Asciz	Signature;
Asciz	SourceFile;
Asciz	TraversableLike.scala;
Asciz	apply;
Asciz	boxToBoolean;
Asciz	java/io/Serializable;
Asciz	p$9;
Asciz	scala/Function1;
Asciz	scala/collection/TraversableLike;
Asciz	scala/collection/TraversableLike$$anonfun$filterNot$1;
Asciz	scala/runtime/AbstractFunction1;
Asciz	scala/runtime/BoxesRunTime;
Asciz	serialVersionUID;
Asciz	this;
Asciz	unboxToBoolean;
Asciz	v1;

{
public static final long serialVersionUID;
  Signature: J

public final scala.Function1 p$9;
  Signature: Lscala/Function1;

public static {};
  Signature: ()V
  Code:
   Stack=2, Locals=0, Args_size=0
	lconst_0
	putstatic	Field serialVersionUID:J
	return
  Labels:

public final boolean apply(java.lang.Object);
  Signature: (Ljava/lang/Object;)Z
  Code:
   Stack=2, Locals=2, Args_size=2
	aload_0
	getfield	Field p$9:Lscala/Function1;
	aload_1
	invokeinterface	InterfaceMethod scala/Function1.apply:(Ljava/lang/Object;)Ljava/lang/Object;
	invokestatic	Method scala/runtime/BoxesRunTime.unboxToBoolean:(Ljava/lang/Object;)Z
	ifeq	l1 // iconst_1
	iconst_0
	goto	l2 // ireturn
l1	iconst_1
l2	ireturn
  Labels:
   	l1 = 20 // iconst_1
   	l2 = 21 // ireturn
  Signature: length = 0x2
   00 1C 

public final java.lang.Object apply(java.lang.Object);
  Signature: (Ljava/lang/Object;)Ljava/lang/Object;
  Code:
   Stack=2, Locals=3, Args_size=2
	aload_0
	aload_1
	invokevirtual	Method apply:(Ljava/lang/Object;)Z
	istore_2
	iload_2
	invokestatic	Method scala/runtime/BoxesRunTime.boxToBoolean:(Z)Ljava/lang/Boolean;
	areturn
  Labels:
  LocalVariableTable: 
   Start  Length  Slot  Name   Signature
   0      11      0    this       Lscala/collection/TraversableLike$$anonfun$filterNot$1;
   0      11      1    v1       Ljava/lang/Object;


public scala.collection.TraversableLike$$anonfun$filterNot$1(scala.collection.TraversableLike, scala.Function1);
  Signature: (Lscala/collection/TraversableLike;Lscala/Function1;)V
  Code:
   Stack=2, Locals=3, Args_size=3
	aload_0
	aload_2
	putfield	Field p$9:Lscala/Function1;
	aload_0
	invokespecial	Method scala/runtime/AbstractFunction1."<init>":()V
	return
  Labels:
  LocalVariableTable: 
   Start  Length  Slot  Name   Signature
   0      10      0    this       Lscala/collection/TraversableLike$$anonfun$filterNot$1;
   0      10      1    $outer       Lscala/collection/TraversableLike;

  Signature: length = 0x2
   00 1B 

}

