Compiled from "Traversable.scala"
public final class scala.collection.Traversable$ComparableTraversableOps$$anonfun$max$1 extends java.lang.Object implements scala.Function0,scala.ScalaObject,java.io.Serializable
  SourceFile: "Traversable.scala"
  Scala: length = 0x
   
  InnerClass: 
   public #44= #41 of #43; //ComparableTraversableOps=class scala/collection/Traversable$ComparableTraversableOps of class scala/collection/Traversable
   public final #45= #28 of #41; //$anonfun$max$1=class scala/collection/Traversable$ComparableTraversableOps$$anonfun$max$1 of class scala/collection/Traversable$ComparableTraversableOps
  minor version: 0
  major version: 49
  Constant pool:
const #1 = Asciz	SourceFile;
const #2 = Asciz	Traversable.scala;
const #3 = Asciz	<init>;
const #4 = Asciz	(Lscala/collection/Traversable$ComparableTraversableOps;)V;
const #5 = Asciz	Code;
const #6 = Asciz	LineNumberTable;
const #7 = Asciz	java/lang/Object;
const #8 = class	#7;	//  java/lang/Object
const #9 = Asciz	()V;
const #10 = NameAndType	#3:#9;//  "<init>":()V
const #11 = Method	#8.#10;	//  java/lang/Object."<init>":()V
const #12 = Asciz	scala/Function0$class;
const #13 = class	#12;	//  scala/Function0$class
const #14 = Asciz	$init$;
const #15 = Asciz	(Lscala/Function0;)V;
const #16 = NameAndType	#14:#15;//  $init$:(Lscala/Function0;)V
const #17 = Method	#13.#16;	//  scala/Function0$class.$init$:(Lscala/Function0;)V
const #18 = Asciz	this;
const #19 = Asciz	Lscala/collection/Traversable$ComparableTraversableOps$$anonfun$max$1;;
const #20 = Asciz	$outer;
const #21 = Asciz	Lscala/collection/Traversable$ComparableTraversableOps;;
const #22 = Asciz	LocalVariableTable;
const #23 = Asciz	(Lscala/collection/Traversable$ComparableTraversableOps<TA;>;)V;
const #24 = Asciz	Signature;
const #25 = Asciz	apply;
const #26 = Asciz	()Ljava/lang/Object;;
const #27 = Asciz	scala/collection/Traversable$ComparableTraversableOps$$anonfun$max$1;
const #28 = class	#27;	//  scala/collection/Traversable$ComparableTraversableOps$$anonfun$max$1
const #29 = Asciz	()Ljava/lang/String;;
const #30 = NameAndType	#25:#29;//  apply:()Ljava/lang/String;
const #31 = Method	#28.#30;	//  scala/collection/Traversable$ComparableTraversableOps$$anonfun$max$1.apply:()Ljava/lang/String;
const #32 = Asciz	max(<empty>);
const #33 = String	#32;	//  max(<empty>)
const #34 = Asciz	toString;
const #35 = Asciz	(Lscala/Function0;)Ljava/lang/String;;
const #36 = NameAndType	#34:#35;//  toString:(Lscala/Function0;)Ljava/lang/String;
const #37 = Method	#13.#36;	//  scala/Function0$class.toString:(Lscala/Function0;)Ljava/lang/String;
const #38 = Asciz	Scala;
const #39 = Asciz	InnerClasses;
const #40 = Asciz	scala/collection/Traversable$ComparableTraversableOps;
const #41 = class	#40;	//  scala/collection/Traversable$ComparableTraversableOps
const #42 = Asciz	scala/collection/Traversable;
const #43 = class	#42;	//  scala/collection/Traversable
const #44 = Asciz	ComparableTraversableOps;
const #45 = Asciz	$anonfun$max$1;
const #46 = Asciz	scala/Function0;
const #47 = class	#46;	//  scala/Function0
const #48 = Asciz	scala/ScalaObject;
const #49 = class	#48;	//  scala/ScalaObject
const #50 = Asciz	java/io/Serializable;
const #51 = class	#50;	//  java/io/Serializable

{
public scala.collection.Traversable$ComparableTraversableOps$$anonfun$max$1(scala.collection.Traversable$ComparableTraversableOps);
  Code:
   Stack=1, Locals=2, Args_size=2
   0:	aload_0
   1:	invokespecial	#11; //Method java/lang/Object."<init>":()V
   4:	aload_0
   5:	invokestatic	#17; //Method scala/Function0$class.$init$:(Lscala/Function0;)V
   8:	return
  LineNumberTable: 
   line 121: 0

  LocalVariableTable: 
   Start  Length  Slot  Name   Signature
   0      9      0    this       Lscala/collection/Traversable$ComparableTraversableOps$$anonfun$max$1;
   0      9      1    $outer       Lscala/collection/Traversable$ComparableTraversableOps;

  Signature: length = 0x2
   00 17 

public final java.lang.Object apply();
  Code:
   Stack=1, Locals=1, Args_size=1
   0:	aload_0
   1:	invokevirtual	#31; //Method apply:()Ljava/lang/String;
   4:	areturn
  LineNumberTable: 
   line 121: 0


public final java.lang.String apply();
  Code:
   Stack=1, Locals=1, Args_size=1
   0:	ldc	#33; //String max(<empty>)
   2:	areturn
  LineNumberTable: 
   line 121: 0


public java.lang.String toString();
  Code:
   Stack=1, Locals=1, Args_size=1
   0:	aload_0
   1:	invokestatic	#37; //Method scala/Function0$class.toString:(Lscala/Function0;)Ljava/lang/String;
   4:	areturn
  LineNumberTable: 
   line 121: 0


}

