Compiled from "TraversableLike.scala"
public final class scala.collection.TraversableLike$$anonfun$addString$1 extends scala.runtime.AbstractFunction1 implements java.io.Serializable
  SourceFile: "TraversableLike.scala"
  Scala: length = 0x
   
  InnerClass: 
   public final $anonfun$addString$1=class scala/collection/TraversableLike$$anonfun$addString$1 of class scala/collection/TraversableLike
  minor version: 0
  major version: 49
  Constant pool:
Asciz	SourceFile;
Asciz	TraversableLike.scala;
Asciz	<clinit>;
Asciz	()V;
Asciz	Code;
Asciz	serialVersionUID;
Asciz	J;
Asciz	scala/collection/TraversableLike$$anonfun$addString$1;
class	scala/collection/TraversableLike$$anonfun$addString$1
NameAndType	serialVersionUID:J
Field	scala/collection/TraversableLike$$anonfun$addString$1.serialVersionUID:J
Asciz	first$2;
Asciz	Lscala/runtime/BooleanRef;;
Asciz	sep$1;
Asciz	Ljava/lang/String;;
Asciz	b$1;
Asciz	Lscala/collection/mutable/StringBuilder;;
Asciz	<init>;
Asciz	(Lscala/collection/TraversableLike;Lscala/collection/mutable/StringBuilder;Ljava/lang/String;Lscala/runtime/BooleanRef;)V;
Asciz	LineNumberTable;
NameAndType	b$1:Lscala/collection/mutable/StringBuilder;
Field	scala/collection/TraversableLike$$anonfun$addString$1.b$1:Lscala/collection/mutable/StringBuilder;
NameAndType	sep$1:Ljava/lang/String;
Field	scala/collection/TraversableLike$$anonfun$addString$1.sep$1:Ljava/lang/String;
NameAndType	first$2:Lscala/runtime/BooleanRef;
Field	scala/collection/TraversableLike$$anonfun$addString$1.first$2:Lscala/runtime/BooleanRef;
Asciz	scala/runtime/AbstractFunction1;
class	scala/runtime/AbstractFunction1
NameAndType	"<init>":()V
Method	scala/runtime/AbstractFunction1."<init>":()V
Asciz	this;
Asciz	Lscala/collection/TraversableLike$$anonfun$addString$1;;
Asciz	$outer;
Asciz	Lscala/collection/TraversableLike;;
Asciz	LocalVariableTable;
Asciz	(Lscala/collection/TraversableLike<TA;TRepr;>;)V;
Asciz	Signature;
Asciz	apply;
Asciz	(Ljava/lang/Object;)Ljava/lang/Object;;
Asciz	(Ljava/lang/Object;)Lscala/collection/mutable/StringBuilder;;
NameAndType	apply:(Ljava/lang/Object;)Lscala/collection/mutable/StringBuilder;
Method	scala/collection/TraversableLike$$anonfun$addString$1.apply:(Ljava/lang/Object;)Lscala/collection/mutable/StringBuilder;
Asciz	v1;
Asciz	Ljava/lang/Object;;
Asciz	scala/runtime/BooleanRef;
class	scala/runtime/BooleanRef
Asciz	elem;
Asciz	Z;
NameAndType	elem:Z
Field	scala/runtime/BooleanRef.elem:Z
Asciz	scala/runtime/BoxedUnit;
class	scala/runtime/BoxedUnit
Asciz	UNIT;
Asciz	Lscala/runtime/BoxedUnit;;
NameAndType	UNIT:Lscala/runtime/BoxedUnit;
Field	scala/runtime/BoxedUnit.UNIT:Lscala/runtime/BoxedUnit;
Asciz	scala/collection/mutable/StringBuilder;
class	scala/collection/mutable/StringBuilder
Asciz	append;
Asciz	(Ljava/lang/String;)Lscala/collection/mutable/StringBuilder;;
NameAndType	append:(Ljava/lang/String;)Lscala/collection/mutable/StringBuilder;
Method	scala/collection/mutable/StringBuilder.append:(Ljava/lang/String;)Lscala/collection/mutable/StringBuilder;
Asciz	java/lang/String;
class	java/lang/String
Asciz	valueOf;
Asciz	(Ljava/lang/Object;)Ljava/lang/String;;
NameAndType	valueOf:(Ljava/lang/Object;)Ljava/lang/String;
Method	java/lang/String.valueOf:(Ljava/lang/Object;)Ljava/lang/String;
Asciz	x;
Asciz	(TA;)Lscala/collection/mutable/StringBuilder;;
Asciz	Scala;
Asciz	InnerClasses;
Asciz	scala/collection/TraversableLike;
class	scala/collection/TraversableLike
Asciz	$anonfun$addString$1;
Asciz	java/io/Serializable;
class	java/io/Serializable

{
public static final long serialVersionUID;
  Signature: J

private final scala.runtime.BooleanRef first$2;
  Signature: Lscala/runtime/BooleanRef;

private final java.lang.String sep$1;
  Signature: Ljava/lang/String;

private final scala.collection.mutable.StringBuilder b$1;
  Signature: Lscala/collection/mutable/StringBuilder;

public static {};
  Signature: ()V
  Code:
   Stack=2, Locals=0, Args_size=0
	lconst_0
	putstatic	Field serialVersionUID:J
	return
  Labels:

public scala.collection.TraversableLike$$anonfun$addString$1(scala.collection.TraversableLike, scala.collection.mutable.StringBuilder, java.lang.String, scala.runtime.BooleanRef);
  Signature: (Lscala/collection/TraversableLike;Lscala/collection/mutable/StringBuilder;Ljava/lang/String;Lscala/runtime/BooleanRef;)V
  Code:
   Stack=2, Locals=5, Args_size=5
	aload_0
	aload_2
	putfield	Field b$1:Lscala/collection/mutable/StringBuilder;
	aload_0
	aload_3
	putfield	Field sep$1:Ljava/lang/String;
	aload_0
	aload	4
	putfield	Field first$2:Lscala/runtime/BooleanRef;
	aload_0
	invokespecial	Method scala/runtime/AbstractFunction1."<init>":()V
	return
  Labels:
  LocalVariableTable: 
   Start  Length  Slot  Name   Signature
   0      21      0    this       Lscala/collection/TraversableLike$$anonfun$addString$1;
   0      21      1    $outer       Lscala/collection/TraversableLike;

  Signature: length = 0x2
   00 24 

public final java.lang.Object apply(java.lang.Object);
  Signature: (Ljava/lang/Object;)Ljava/lang/Object;
  Code:
   Stack=2, Locals=2, Args_size=2
	aload_0
	aload_1
	invokevirtual	Method apply:(Ljava/lang/Object;)Lscala/collection/mutable/StringBuilder;
	areturn
  Labels:
  LocalVariableTable: 
   Start  Length  Slot  Name   Signature
   0      6      0    this       Lscala/collection/TraversableLike$$anonfun$addString$1;
   0      6      1    v1       Ljava/lang/Object;


public final scala.collection.mutable.StringBuilder apply(java.lang.Object);
  Signature: (Ljava/lang/Object;)Lscala/collection/mutable/StringBuilder;
  Code:
   Stack=2, Locals=3, Args_size=2
	aload_0
	getfield	Field first$2:Lscala/runtime/BooleanRef;
	getfield	Field scala/runtime/BooleanRef.elem:Z
	ifeq	l1 // aload_0
	aload_0
	getfield	Field first$2:Lscala/runtime/BooleanRef;
	iconst_0
	putfield	Field scala/runtime/BooleanRef.elem:Z
	getstatic	Field scala/runtime/BoxedUnit.UNIT:Lscala/runtime/BoxedUnit;
	goto	l2 // pop
l1	aload_0
	getfield	Field b$1:Lscala/collection/mutable/StringBuilder;
	aload_0
	getfield	Field sep$1:Ljava/lang/String;
	invokevirtual	Method scala/collection/mutable/StringBuilder.append:(Ljava/lang/String;)Lscala/collection/mutable/StringBuilder;
l2	pop
	aload_0
	getfield	Field b$1:Lscala/collection/mutable/StringBuilder;
	astore_2
	aload_2
	aload_1
	invokestatic	Method java/lang/String.valueOf:(Ljava/lang/Object;)Ljava/lang/String;
	invokevirtual	Method scala/collection/mutable/StringBuilder.append:(Ljava/lang/String;)Lscala/collection/mutable/StringBuilder;
	areturn
  Labels:
   	l1 = 24 // aload_0
   	l2 = 35 // pop
  LocalVariableTable: 
   Start  Length  Slot  Name   Signature
   0      50      0    this       Lscala/collection/TraversableLike$$anonfun$addString$1;
   0      50      1    x       Ljava/lang/Object;

  Signature: length = 0x2
   00 46 

}

