Compiled from "TraversableView.scala"
public class scala.collection.TraversableView$NoBuilder extends java.lang.Object implements scala.collection.mutable.Builder,scala.ScalaObject
  SourceFile: "TraversableView.scala"
  Signature: length = 0x2
   00 66 
  Scala: length = 0x
   
  InnerClass: 
   public NoBuilder=class scala/collection/TraversableView$NoBuilder of class scala/collection/TraversableView
  minor version: 0
  major version: 49
  Constant pool:
Asciz	SourceFile;
Asciz	TraversableView.scala;
Asciz	<init>;
Asciz	()V;
Asciz	Code;
Asciz	LineNumberTable;
Asciz	java/lang/Object;
class	java/lang/Object
NameAndType	"<init>":()V
Method	java/lang/Object."<init>":()V
Asciz	scala/collection/generic/Growable$class;
class	scala/collection/generic/Growable$class
Asciz	$init$;
Asciz	(Lscala/collection/generic/Growable;)V;
NameAndType	$init$:(Lscala/collection/generic/Growable;)V
Method	scala/collection/generic/Growable$class.$init$:(Lscala/collection/generic/Growable;)V
Asciz	scala/collection/mutable/Builder$class;
class	scala/collection/mutable/Builder$class
Asciz	(Lscala/collection/mutable/Builder;)V;
NameAndType	$init$:(Lscala/collection/mutable/Builder;)V
Method	scala/collection/mutable/Builder$class.$init$:(Lscala/collection/mutable/Builder;)V
Asciz	Signature;
Asciz	$plus$eq;
Asciz	(Ljava/lang/Object;)Lscala/collection/mutable/Builder;;
Asciz	scala/collection/TraversableView$NoBuilder;
class	scala/collection/TraversableView$NoBuilder
Asciz	(Ljava/lang/Object;)Lscala/collection/TraversableView$NoBuilder;;
NameAndType	$plus$eq:(Ljava/lang/Object;)Lscala/collection/TraversableView$NoBuilder;
Method	scala/collection/TraversableView$NoBuilder.$plus$eq:(Ljava/lang/Object;)Lscala/collection/TraversableView$NoBuilder;
Asciz	this;
Asciz	Lscala/collection/TraversableView$NoBuilder;;
Asciz	elem;
Asciz	Ljava/lang/Object;;
Asciz	LocalVariableTable;
Asciz	(Ljava/lang/Object;)Lscala/collection/generic/Growable;;
Asciz	result;
Asciz	()Ljava/lang/Object;;
Asciz	()Lscala/runtime/Nothing$;;
NameAndType	result:()Lscala/runtime/Nothing$;
Method	scala/collection/TraversableView$NoBuilder.result:()Lscala/runtime/Nothing$;
Asciz	clear;
Asciz	java/lang/UnsupportedOperationException;
class	java/lang/UnsupportedOperationException
Asciz	TraversableView.Builder.result;
String	TraversableView.Builder.result
Asciz	(Ljava/lang/String;)V;
NameAndType	"<init>":(Ljava/lang/String;)V
Method	java/lang/UnsupportedOperationException."<init>":(Ljava/lang/String;)V
Asciz	elements;
Asciz	()Lscala/collection/Iterator;;
Asciz	iterator;
NameAndType	iterator:()Lscala/collection/Iterator;
Method	scala/collection/TraversableView$NoBuilder.iterator:()Lscala/collection/Iterator;
Asciz	()Lscala/collection/Iterator<TA;>;;
Asciz	Deprecated;
Asciz	scala/collection/Iterator$;
class	scala/collection/Iterator$
Asciz	MODULE$;
Asciz	Lscala/collection/Iterator$;;
NameAndType	MODULE$:Lscala/collection/Iterator$;
Field	scala/collection/Iterator$.MODULE$:Lscala/collection/Iterator$;
Asciz	empty;
NameAndType	empty:()Ljava/lang/Object;
Method	scala/collection/Iterator$.empty:()Ljava/lang/Object;
Asciz	scala/collection/Iterator;
class	scala/collection/Iterator
Asciz	(TA;)Lscala/collection/TraversableView$NoBuilder<TA;>;;
Asciz	$plus$plus$eq;
Asciz	(Lscala/collection/Traversable;)Lscala/collection/generic/Growable;;
Asciz	(Lscala/collection/generic/Growable;Lscala/collection/Traversable;)Lscala/collection/generic/Growable;;
NameAndType	$plus$plus$eq:(Lscala/collection/generic/Growable;Lscala/collection/Traversable;)Lscala/collection/generic/Growable;
Method	scala/collection/generic/Growable$class.$plus$plus$eq:(Lscala/collection/generic/Growable;Lscala/collection/Traversable;)Lscala/collection/generic/Growable;
Asciz	elems;
Asciz	Lscala/collection/Traversable;;
Asciz	(Lscala/collection/Iterator;)Lscala/collection/generic/Growable;;
Asciz	(Lscala/collection/generic/Growable;Lscala/collection/Iterator;)Lscala/collection/generic/Growable;;
NameAndType	$plus$plus$eq:(Lscala/collection/generic/Growable;Lscala/collection/Iterator;)Lscala/collection/generic/Growable;
Method	scala/collection/generic/Growable$class.$plus$plus$eq:(Lscala/collection/generic/Growable;Lscala/collection/Iterator;)Lscala/collection/generic/Growable;
Asciz	iter;
Asciz	Lscala/collection/Iterator;;
Asciz	(Ljava/lang/Object;Ljava/lang/Object;Lscala/collection/Seq;)Lscala/collection/generic/Growable;;
Asciz	(Lscala/collection/generic/Growable;Ljava/lang/Object;Ljava/lang/Object;Lscala/collection/Seq;)Lscala/collection/generic/Growable;;
NameAndType	$plus$eq:(Lscala/collection/generic/Growable;Ljava/lang/Object;Ljava/lang/Object;Lscala/collection/Seq;)Lscala/collection/generic/Growable;
Method	scala/collection/generic/Growable$class.$plus$eq:(Lscala/collection/generic/Growable;Ljava/lang/Object;Ljava/lang/Object;Lscala/collection/Seq;)Lscala/collection/generic/Growable;
Asciz	elem1;
Asciz	elem2;
Asciz	Lscala/collection/Seq;;
Asciz	mapResult;
Asciz	(Lscala/Function1;)Lscala/collection/mutable/Builder;;
Asciz	(Lscala/collection/mutable/Builder;Lscala/Function1;)Lscala/collection/mutable/Builder;;
NameAndType	mapResult:(Lscala/collection/mutable/Builder;Lscala/Function1;)Lscala/collection/mutable/Builder;
Method	scala/collection/mutable/Builder$class.mapResult:(Lscala/collection/mutable/Builder;Lscala/Function1;)Lscala/collection/mutable/Builder;
Asciz	f;
Asciz	Lscala/Function1;;
Asciz	sizeHint;
Asciz	(I)V;
Asciz	(Lscala/collection/mutable/Builder;I)V;
NameAndType	sizeHint:(Lscala/collection/mutable/Builder;I)V
Method	scala/collection/mutable/Builder$class.sizeHint:(Lscala/collection/mutable/Builder;I)V
Asciz	size;
Asciz	I;
Asciz	<A:Ljava/lang/Object;>Ljava/lang/Object;Lscala/collection/mutable/Builder<TA;Lscala/runtime/Nothing$;>;Lscala/ScalaObject;;
Asciz	Scala;
Asciz	InnerClasses;
Asciz	scala/collection/TraversableView;
class	scala/collection/TraversableView
Asciz	NoBuilder;
Asciz	scala/collection/mutable/Builder;
class	scala/collection/mutable/Builder
Asciz	scala/ScalaObject;
class	scala/ScalaObject

{
public scala.collection.TraversableView$NoBuilder();
  Signature: ()V
  Code:
   Stack=1, Locals=1, Args_size=1
	aload_0
	invokespecial	Method java/lang/Object."<init>":()V
	aload_0
	invokestatic	Method scala/collection/generic/Growable$class.$init$:(Lscala/collection/generic/Growable;)V
	aload_0
	invokestatic	Method scala/collection/mutable/Builder$class.$init$:(Lscala/collection/mutable/Builder;)V
	return
  Labels:
  Signature: length = 0x2
   00 04 

public scala.collection.mutable.Builder $plus$eq(java.lang.Object);
  Signature: (Ljava/lang/Object;)Lscala/collection/mutable/Builder;
  Code:
   Stack=2, Locals=2, Args_size=2
	aload_0
	aload_1
	invokevirtual	Method $plus$eq:(Ljava/lang/Object;)Lscala/collection/TraversableView$NoBuilder;
	areturn
  Labels:
  LocalVariableTable: 
   Start  Length  Slot  Name   Signature
   0      6      0    this       Lscala/collection/TraversableView$NoBuilder;
   0      6      1    elem       Ljava/lang/Object;


public scala.collection.generic.Growable $plus$eq(java.lang.Object);
  Signature: (Ljava/lang/Object;)Lscala/collection/generic/Growable;
  Code:
   Stack=2, Locals=2, Args_size=2
	aload_0
	aload_1
	invokevirtual	Method $plus$eq:(Ljava/lang/Object;)Lscala/collection/TraversableView$NoBuilder;
	areturn
  Labels:
  LocalVariableTable: 
   Start  Length  Slot  Name   Signature
   0      6      0    this       Lscala/collection/TraversableView$NoBuilder;
   0      6      1    elem       Ljava/lang/Object;


public java.lang.Object result();
  Signature: ()Ljava/lang/Object;
  Code:
   Stack=1, Locals=1, Args_size=1
	aload_0
	invokevirtual	Method result:()Lscala/runtime/Nothing$;
	athrow
  Labels:

public void clear();
  Signature: ()V
  Code:
   Stack=0, Locals=1, Args_size=1
	return
  Labels:

public scala.runtime.Nothing$ result();
  Signature: ()Lscala/runtime/Nothing$;
  Code:
   Stack=3, Locals=1, Args_size=1
	new	class java/lang/UnsupportedOperationException
	dup
	ldc	String TraversableView.Builder.result
	invokespecial	Method java/lang/UnsupportedOperationException."<init>":(Ljava/lang/String;)V
	athrow
  Labels:

public scala.collection.Iterator elements();
  Signature: ()Lscala/collection/Iterator;
  Code:
   Stack=1, Locals=1, Args_size=1
	aload_0
	invokevirtual	Method iterator:()Lscala/collection/Iterator;
	areturn
  Labels:
  Signature: length = 0x2
   00 36 
  Deprecated: true

public scala.collection.Iterator iterator();
  Signature: ()Lscala/collection/Iterator;
  Code:
   Stack=1, Locals=1, Args_size=1
	getstatic	Field scala/collection/Iterator$.MODULE$:Lscala/collection/Iterator$;
	invokevirtual	Method scala/collection/Iterator$.empty:()Ljava/lang/Object;
	checkcast	class scala/collection/Iterator
	areturn
  Labels:
  Signature: length = 0x2
   00 36 

public scala.collection.TraversableView$NoBuilder $plus$eq(java.lang.Object);
  Signature: (Ljava/lang/Object;)Lscala/collection/TraversableView$NoBuilder;
  Code:
   Stack=1, Locals=2, Args_size=2
	aload_0
	areturn
  Labels:
  LocalVariableTable: 
   Start  Length  Slot  Name   Signature
   0      2      0    this       Lscala/collection/TraversableView$NoBuilder;
   0      2      1    elem       Ljava/lang/Object;

  Signature: length = 0x2
   00 43 

public scala.collection.generic.Growable $plus$plus$eq(scala.collection.Traversable);
  Signature: (Lscala/collection/Traversable;)Lscala/collection/generic/Growable;
  Code:
   Stack=2, Locals=2, Args_size=2
	aload_0
	aload_1
	invokestatic	Method scala/collection/generic/Growable$class.$plus$plus$eq:(Lscala/collection/generic/Growable;Lscala/collection/Traversable;)Lscala/collection/generic/Growable;
	areturn
  Labels:
  LocalVariableTable: 
   Start  Length  Slot  Name   Signature
   0      6      0    this       Lscala/collection/TraversableView$NoBuilder;
   0      6      1    elems       Lscala/collection/Traversable;


public scala.collection.generic.Growable $plus$plus$eq(scala.collection.Iterator);
  Signature: (Lscala/collection/Iterator;)Lscala/collection/generic/Growable;
  Code:
   Stack=2, Locals=2, Args_size=2
	aload_0
	aload_1
	invokestatic	Method scala/collection/generic/Growable$class.$plus$plus$eq:(Lscala/collection/generic/Growable;Lscala/collection/Iterator;)Lscala/collection/generic/Growable;
	areturn
  Labels:
  LocalVariableTable: 
   Start  Length  Slot  Name   Signature
   0      6      0    this       Lscala/collection/TraversableView$NoBuilder;
   0      6      1    iter       Lscala/collection/Iterator;


public scala.collection.generic.Growable $plus$eq(java.lang.Object, java.lang.Object, scala.collection.Seq);
  Signature: (Ljava/lang/Object;Ljava/lang/Object;Lscala/collection/Seq;)Lscala/collection/generic/Growable;
  Code:
   Stack=4, Locals=4, Args_size=4
	aload_0
	aload_1
	aload_2
	aload_3
	invokestatic	Method scala/collection/generic/Growable$class.$plus$eq:(Lscala/collection/generic/Growable;Ljava/lang/Object;Ljava/lang/Object;Lscala/collection/Seq;)Lscala/collection/generic/Growable;
	areturn
  Labels:
  LocalVariableTable: 
   Start  Length  Slot  Name   Signature
   0      8      0    this       Lscala/collection/TraversableView$NoBuilder;
   0      8      1    elem1       Ljava/lang/Object;
   0      8      2    elem2       Ljava/lang/Object;
   0      8      3    elems       Lscala/collection/Seq;


public scala.collection.mutable.Builder mapResult(scala.Function1);
  Signature: (Lscala/Function1;)Lscala/collection/mutable/Builder;
  Code:
   Stack=2, Locals=2, Args_size=2
	aload_0
	aload_1
	invokestatic	Method scala/collection/mutable/Builder$class.mapResult:(Lscala/collection/mutable/Builder;Lscala/Function1;)Lscala/collection/mutable/Builder;
	areturn
  Labels:
  LocalVariableTable: 
   Start  Length  Slot  Name   Signature
   0      6      0    this       Lscala/collection/TraversableView$NoBuilder;
   0      6      1    f       Lscala/Function1;


public void sizeHint(int);
  Signature: (I)V
  Code:
   Stack=2, Locals=2, Args_size=2
	aload_0
	iload_1
	invokestatic	Method scala/collection/mutable/Builder$class.sizeHint:(Lscala/collection/mutable/Builder;I)V
	return
  Labels:
  LocalVariableTable: 
   Start  Length  Slot  Name   Signature
   0      6      0    this       Lscala/collection/TraversableView$NoBuilder;
   0      6      1    size       I


}

