Compiled from "TraversableLike.scala"
public final class scala.collection.TraversableLike$$anonfun$reduceLeft$1 extends java.lang.Object implements scala.Function1,scala.ScalaObject,java.io.Serializable
  SourceFile: "TraversableLike.scala"
  Scala: length = 0x
   
  InnerClass: 
   public final $anonfun$reduceLeft$1=class scala/collection/TraversableLike$$anonfun$reduceLeft$1 of class scala/collection/TraversableLike
  minor version: 0
  major version: 49
  Constant pool:
Asciz	SourceFile;
Asciz	TraversableLike.scala;
Asciz	<clinit>;
Asciz	()V;
Asciz	Code;
Asciz	serialVersionUID;
Asciz	J;
Asciz	scala/collection/TraversableLike$$anonfun$reduceLeft$1;
class	scala/collection/TraversableLike$$anonfun$reduceLeft$1
NameAndType	serialVersionUID:J
Field	scala/collection/TraversableLike$$anonfun$reduceLeft$1.serialVersionUID:J
Asciz	first$1;
Asciz	Lscala/runtime/BooleanRef;;
Asciz	result$7;
Asciz	Lscala/runtime/ObjectRef;;
Asciz	op$3;
Asciz	Lscala/Function2;;
Asciz	<init>;
Asciz	(Lscala/collection/TraversableLike;Lscala/Function2;Lscala/runtime/ObjectRef;Lscala/runtime/BooleanRef;)V;
Asciz	LineNumberTable;
NameAndType	op$3:Lscala/Function2;
Field	scala/collection/TraversableLike$$anonfun$reduceLeft$1.op$3:Lscala/Function2;
NameAndType	result$7:Lscala/runtime/ObjectRef;
Field	scala/collection/TraversableLike$$anonfun$reduceLeft$1.result$7:Lscala/runtime/ObjectRef;
NameAndType	first$1:Lscala/runtime/BooleanRef;
Field	scala/collection/TraversableLike$$anonfun$reduceLeft$1.first$1:Lscala/runtime/BooleanRef;
Asciz	java/lang/Object;
class	java/lang/Object
NameAndType	"<init>":()V
Method	java/lang/Object."<init>":()V
Asciz	scala/Function1$class;
class	scala/Function1$class
Asciz	$init$;
Asciz	(Lscala/Function1;)V;
NameAndType	$init$:(Lscala/Function1;)V
Method	scala/Function1$class.$init$:(Lscala/Function1;)V
Asciz	this;
Asciz	Lscala/collection/TraversableLike$$anonfun$reduceLeft$1;;
Asciz	$outer;
Asciz	Lscala/collection/TraversableLike;;
Asciz	LocalVariableTable;
Asciz	(Lscala/collection/TraversableLike<TA;TRepr;>;)V;
Asciz	Signature;
Asciz	apply;
Asciz	(Ljava/lang/Object;)Ljava/lang/Object;;
Asciz	(Ljava/lang/Object;)V;
NameAndType	apply:(Ljava/lang/Object;)V
Method	scala/collection/TraversableLike$$anonfun$reduceLeft$1.apply:(Ljava/lang/Object;)V
Asciz	scala/runtime/BoxedUnit;
class	scala/runtime/BoxedUnit
Asciz	UNIT;
Asciz	Lscala/runtime/BoxedUnit;;
NameAndType	UNIT:Lscala/runtime/BoxedUnit;
Field	scala/runtime/BoxedUnit.UNIT:Lscala/runtime/BoxedUnit;
Asciz	v1;
Asciz	Ljava/lang/Object;;
Asciz	scala/runtime/BooleanRef;
class	scala/runtime/BooleanRef
Asciz	elem;
Asciz	Z;
NameAndType	elem:Z
Field	scala/runtime/BooleanRef.elem:Z
Asciz	scala/runtime/ObjectRef;
class	scala/runtime/ObjectRef
NameAndType	elem:Ljava/lang/Object;
Field	scala/runtime/ObjectRef.elem:Ljava/lang/Object;
Asciz	scala/Function2;
class	scala/Function2
Asciz	(Ljava/lang/Object;Ljava/lang/Object;)Ljava/lang/Object;;
NameAndType	apply:(Ljava/lang/Object;Ljava/lang/Object;)Ljava/lang/Object;
InterfaceMethod	scala/Function2.apply:(Ljava/lang/Object;Ljava/lang/Object;)Ljava/lang/Object;
Asciz	x;
Asciz	(TA;)V;
Asciz	andThen;
Asciz	(Lscala/Function1;)Lscala/Function1;;
Asciz	(Lscala/Function1;Lscala/Function1;)Lscala/Function1;;
NameAndType	andThen:(Lscala/Function1;Lscala/Function1;)Lscala/Function1;
Method	scala/Function1$class.andThen:(Lscala/Function1;Lscala/Function1;)Lscala/Function1;
Asciz	g;
Asciz	Lscala/Function1;;
Asciz	compose;
NameAndType	compose:(Lscala/Function1;Lscala/Function1;)Lscala/Function1;
Method	scala/Function1$class.compose:(Lscala/Function1;Lscala/Function1;)Lscala/Function1;
Asciz	toString;
Asciz	()Ljava/lang/String;;
Asciz	(Lscala/Function1;)Ljava/lang/String;;
NameAndType	toString:(Lscala/Function1;)Ljava/lang/String;
Method	scala/Function1$class.toString:(Lscala/Function1;)Ljava/lang/String;
Asciz	Scala;
Asciz	InnerClasses;
Asciz	scala/collection/TraversableLike;
class	scala/collection/TraversableLike
Asciz	$anonfun$reduceLeft$1;
Asciz	scala/Function1;
class	scala/Function1
Asciz	scala/ScalaObject;
class	scala/ScalaObject
Asciz	java/io/Serializable;
class	java/io/Serializable

{
public static final long serialVersionUID;
  Signature: J

private final scala.runtime.BooleanRef first$1;
  Signature: Lscala/runtime/BooleanRef;

private final scala.runtime.ObjectRef result$7;
  Signature: Lscala/runtime/ObjectRef;

private final scala.Function2 op$3;
  Signature: Lscala/Function2;

public static {};
  Signature: ()V
  Code:
   Stack=2, Locals=0, Args_size=0
	lconst_0
	putstatic	Field serialVersionUID:J
	return
  Labels:

public scala.collection.TraversableLike$$anonfun$reduceLeft$1(scala.collection.TraversableLike, scala.Function2, scala.runtime.ObjectRef, scala.runtime.BooleanRef);
  Signature: (Lscala/collection/TraversableLike;Lscala/Function2;Lscala/runtime/ObjectRef;Lscala/runtime/BooleanRef;)V
  Code:
   Stack=2, Locals=5, Args_size=5
	aload_0
	aload_2
	putfield	Field op$3:Lscala/Function2;
	aload_0
	aload_3
	putfield	Field result$7:Lscala/runtime/ObjectRef;
	aload_0
	aload	4
	putfield	Field first$1:Lscala/runtime/BooleanRef;
	aload_0
	invokespecial	Method java/lang/Object."<init>":()V
	aload_0
	invokestatic	Method scala/Function1$class.$init$:(Lscala/Function1;)V
	return
  Labels:
  LocalVariableTable: 
   Start  Length  Slot  Name   Signature
   0      25      0    this       Lscala/collection/TraversableLike$$anonfun$reduceLeft$1;
   0      25      1    $outer       Lscala/collection/TraversableLike;

  Signature: length = 0x2
   00 2A 

public final java.lang.Object apply(java.lang.Object);
  Signature: (Ljava/lang/Object;)Ljava/lang/Object;
  Code:
   Stack=2, Locals=2, Args_size=2
	aload_0
	aload_1
	invokevirtual	Method apply:(Ljava/lang/Object;)V
	getstatic	Field scala/runtime/BoxedUnit.UNIT:Lscala/runtime/BoxedUnit;
	areturn
  Labels:
  LocalVariableTable: 
   Start  Length  Slot  Name   Signature
   0      9      0    this       Lscala/collection/TraversableLike$$anonfun$reduceLeft$1;
   0      9      1    v1       Ljava/lang/Object;


public final void apply(java.lang.Object);
  Signature: (Ljava/lang/Object;)V
  Code:
   Stack=4, Locals=2, Args_size=2
	aload_0
	getfield	Field first$1:Lscala/runtime/BooleanRef;
	getfield	Field scala/runtime/BooleanRef.elem:Z
	ifeq	l1 // aload_0
	aload_0
	getfield	Field first$1:Lscala/runtime/BooleanRef;
	iconst_0
	putfield	Field scala/runtime/BooleanRef.elem:Z
	goto	l2 // return
l1	aload_0
	getfield	Field result$7:Lscala/runtime/ObjectRef;
	aload_0
	getfield	Field op$3:Lscala/Function2;
	aload_0
	getfield	Field result$7:Lscala/runtime/ObjectRef;
	getfield	Field scala/runtime/ObjectRef.elem:Ljava/lang/Object;
	aload_1
	invokeinterface	InterfaceMethod scala/Function2.apply:(Ljava/lang/Object;Ljava/lang/Object;)Ljava/lang/Object;
	putfield	Field scala/runtime/ObjectRef.elem:Ljava/lang/Object;
l2	return
  Labels:
   	l1 = 21 // aload_0
   	l2 = 45 // return
  LocalVariableTable: 
   Start  Length  Slot  Name   Signature
   0      46      0    this       Lscala/collection/TraversableLike$$anonfun$reduceLeft$1;
   0      46      1    x       Ljava/lang/Object;

  Signature: length = 0x2
   00 49 

public scala.Function1 andThen(scala.Function1);
  Signature: (Lscala/Function1;)Lscala/Function1;
  Code:
   Stack=2, Locals=2, Args_size=2
	aload_0
	aload_1
	invokestatic	Method scala/Function1$class.andThen:(Lscala/Function1;Lscala/Function1;)Lscala/Function1;
	areturn
  Labels:
  LocalVariableTable: 
   Start  Length  Slot  Name   Signature
   0      6      0    this       Lscala/collection/TraversableLike$$anonfun$reduceLeft$1;
   0      6      1    g       Lscala/Function1;


public scala.Function1 compose(scala.Function1);
  Signature: (Lscala/Function1;)Lscala/Function1;
  Code:
   Stack=2, Locals=2, Args_size=2
	aload_0
	aload_1
	invokestatic	Method scala/Function1$class.compose:(Lscala/Function1;Lscala/Function1;)Lscala/Function1;
	areturn
  Labels:
  LocalVariableTable: 
   Start  Length  Slot  Name   Signature
   0      6      0    this       Lscala/collection/TraversableLike$$anonfun$reduceLeft$1;
   0      6      1    g       Lscala/Function1;


public java.lang.String toString();
  Signature: ()Ljava/lang/String;
  Code:
   Stack=1, Locals=1, Args_size=1
	aload_0
	invokestatic	Method scala/Function1$class.toString:(Lscala/Function1;)Ljava/lang/String;
	areturn
  Labels:

}

