Compiled from "TraversableProxyLike.scala"
public class scala.collection.TraversableProxyLikeConfirmation extends java.lang.Object implements scala.collection.TraversableProxyLike,scala.collection.interfaces.TraversableMethods,scala.ScalaObject
  SourceFile: "TraversableProxyLike.scala"
  Signature: length = 0x2
   01 FFFFFF9C 
  ScalaSig: length = 0x1E2
   05 00 47 06 04 01 02 04 07 02 20 54 72 61 76 65
   72 73 61 62 6C 65 50 72 6F 78 79 4C 69 6B 65 43
   6F 6E 66 69 72 6D 61 74 69 6F 6E 0A 02 03 04 01
   0A 63 6F 6C 6C 65 63 74 69 6F 6E 0A 01 05 01 05
   73 63 61 6C 61 03 00 15 03 08 17 32 13 05 00 09
   11 24 2A 10 02 0A 0F 0D 01 0B 0A 02 0C 0D 01 04
   6C 61 6E 67 0A 01 0E 01 04 6A 61 76 61 09 02 10
   0B 02 06 4F 62 6A 65 63 74 10 04 12 13 15 21 0D
   01 02 09 02 14 02 02 14 54 72 61 76 65 72 73 61
   62 6C 65 50 72 6F 78 79 4C 69 6B 65 10 02 16 17
   0C 00 04 08 18 00 FFFFFF84 FFFFFF80 FFFFFF84 FFFFFFC2 00 19 02 01 41 11
   02 1A 1E 10 02 1B 1C 0D 01 04 09 02 1D 04 02 07
   4E 6F 74 68 69 6E 67 10 02 1B 1F 09 02 20 04 02
   03 41 6E 79 10 03 12 22 15 09 02 23 02 02 0B 54
   72 61 76 65 72 73 61 62 6C 65 10 04 25 28 15 21
   0D 01 26 0A 02 27 02 01 0A 69 6E 74 65 72 66 61
   63 65 73 09 02 29 26 02 12 54 72 61 76 65 72 73
   61 62 6C 65 4D 65 74 68 6F 64 73 10 02 1B 2B 09
   02 2C 04 02 0B 53 63 61 6C 61 4F 62 6A 65 63 74
   08 05 2E 00 FFFFFF84 00 2F 01 06 3C 69 6E 69 74 3E 14
   01 30 10 04 12 00 15 31 10 02 16 32 04 08 33 00
   FFFFFF84 FFFFFF80 FFFFFF84 FFFFFFC2 00 34 02 04 54 68 69 73 11 02 1A 35
   12 03 36 38 21 06 08 37 00 FFFFFF84 FFFFFF80 FFFFFF80 FFFFFF80 00 35 02
   0C 3C 72 65 66 69 6E 65 6D 65 6E 74 3E 10 04 12
   39 15 31 09 02 3A 02 02 0F 54 72 61 76 65 72 73
   61 62 6C 65 4C 69 6B 65 08 05 3C 00 FFFFFF84 00 3D 01
   04 73 65 6C 66 15 01 31 08 06 3F 00 FFFFFFA0 FFFFFF84 08 40
   01 0A 6E 65 77 42 75 69 6C 64 65 72 15 01 41 10
   04 42 45 15 21 0D 01 43 0A 02 44 02 01 07 6D 75
   74 61 62 6C 65 09 02 46 43 02 07 42 75 69 6C 64
   65 72 
  InnerClass: 
   public WithFilter=class scala/collection/TraversableLike$WithFilter of class scala/collection/TraversableLike
  minor version: 0
  major version: 49
  Constant pool:
Asciz	SourceFile;
Asciz	TraversableProxyLike.scala;
Asciz	<init>;
Asciz	()V;
Asciz	Code;
Asciz	LineNumberTable;
Asciz	java/lang/Object;
class	java/lang/Object
NameAndType	"<init>":()V
Method	java/lang/Object."<init>":()V
Asciz	scala/collection/TraversableLike$class;
class	scala/collection/TraversableLike$class
Asciz	$init$;
Asciz	(Lscala/collection/TraversableLike;)V;
NameAndType	$init$:(Lscala/collection/TraversableLike;)V
Method	scala/collection/TraversableLike$class.$init$:(Lscala/collection/TraversableLike;)V
Asciz	scala/Proxy$class;
class	scala/Proxy$class
Asciz	(Lscala/Proxy;)V;
NameAndType	$init$:(Lscala/Proxy;)V
Method	scala/Proxy$class.$init$:(Lscala/Proxy;)V
Asciz	scala/collection/TraversableProxyLike$class;
class	scala/collection/TraversableProxyLike$class
Asciz	(Lscala/collection/TraversableProxyLike;)V;
NameAndType	$init$:(Lscala/collection/TraversableProxyLike;)V
Method	scala/collection/TraversableProxyLike$class.$init$:(Lscala/collection/TraversableProxyLike;)V
Asciz	Signature;
Asciz	self;
Asciz	()Ljava/lang/Object;;
Asciz	scala/collection/TraversableProxyLikeConfirmation;
class	scala/collection/TraversableProxyLikeConfirmation
Asciz	()Lscala/collection/TraversableLike;;
NameAndType	self:()Lscala/collection/TraversableLike;
Method	scala/collection/TraversableProxyLikeConfirmation.self:()Lscala/collection/TraversableLike;
Asciz	filter;
Asciz	(Lscala/Function1;)Ljava/lang/Object;;
Asciz	scala/collection/TraversableProxyLike;
class	scala/collection/TraversableProxyLike
Asciz	(Lscala/Function1;)Lscala/collection/TraversableLike;;
NameAndType	filter:(Lscala/Function1;)Lscala/collection/TraversableLike;
InterfaceMethod	scala/collection/TraversableProxyLike.filter:(Lscala/Function1;)Lscala/collection/TraversableLike;
Asciz	this;
Asciz	Lscala/collection/TraversableProxyLikeConfirmation;;
Asciz	p;
Asciz	Lscala/Function1;;
Asciz	LocalVariableTable;
Asciz	(Lscala/Function1;)Lscala/collection/Traversable;;
Asciz	scala/collection/Traversable;
class	scala/collection/Traversable
Asciz	filterNot;
NameAndType	filterNot:(Lscala/Function1;)Lscala/collection/TraversableLike;
InterfaceMethod	scala/collection/TraversableProxyLike.filterNot:(Lscala/Function1;)Lscala/collection/TraversableLike;
Asciz	tail;
NameAndType	tail:()Lscala/collection/TraversableLike;
InterfaceMethod	scala/collection/TraversableProxyLike.tail:()Lscala/collection/TraversableLike;
Asciz	()Lscala/collection/Traversable;;
Asciz	init;
NameAndType	init:()Lscala/collection/TraversableLike;
InterfaceMethod	scala/collection/TraversableProxyLike.init:()Lscala/collection/TraversableLike;
Asciz	take;
Asciz	(I)Ljava/lang/Object;;
Asciz	(I)Lscala/collection/TraversableLike;;
NameAndType	take:(I)Lscala/collection/TraversableLike;
InterfaceMethod	scala/collection/TraversableProxyLike.take:(I)Lscala/collection/TraversableLike;
Asciz	n;
Asciz	I;
Asciz	(I)Lscala/collection/Traversable;;
Asciz	drop;
NameAndType	drop:(I)Lscala/collection/TraversableLike;
InterfaceMethod	scala/collection/TraversableProxyLike.drop:(I)Lscala/collection/TraversableLike;
Asciz	slice;
Asciz	(II)Ljava/lang/Object;;
Asciz	(II)Lscala/collection/TraversableLike;;
NameAndType	slice:(II)Lscala/collection/TraversableLike;
InterfaceMethod	scala/collection/TraversableProxyLike.slice:(II)Lscala/collection/TraversableLike;
Asciz	from;
Asciz	until;
Asciz	(II)Lscala/collection/Traversable;;
Asciz	takeWhile;
NameAndType	takeWhile:(Lscala/Function1;)Lscala/collection/TraversableLike;
InterfaceMethod	scala/collection/TraversableProxyLike.takeWhile:(Lscala/Function1;)Lscala/collection/TraversableLike;
Asciz	dropWhile;
NameAndType	dropWhile:(Lscala/Function1;)Lscala/collection/TraversableLike;
InterfaceMethod	scala/collection/TraversableProxyLike.dropWhile:(Lscala/Function1;)Lscala/collection/TraversableLike;
Asciz	view;
Asciz	()Lscala/collection/TraversableView;;
NameAndType	view:()Ljava/lang/Object;
InterfaceMethod	scala/collection/TraversableProxyLike.view:()Ljava/lang/Object;
Asciz	scala/collection/TraversableView;
class	scala/collection/TraversableView
Asciz	newBuilder;
Asciz	()Lscala/collection/mutable/Builder;;
Asciz	scala/collection/Traversable$;
class	scala/collection/Traversable$
Asciz	MODULE$;
Asciz	Lscala/collection/Traversable$;;
NameAndType	MODULE$:Lscala/collection/Traversable$;
Field	scala/collection/Traversable$.MODULE$:Lscala/collection/Traversable$;
NameAndType	newBuilder:()Lscala/collection/mutable/Builder;
Method	scala/collection/Traversable$.newBuilder:()Lscala/collection/mutable/Builder;
Asciz	()Lscala/collection/mutable/Builder<TA;Lscala/collection/Traversable<TA;>;>;;
Asciz	scala/collection/TraversableLike;
class	scala/collection/TraversableLike
Asciz	repr;
NameAndType	repr:()Ljava/lang/Object;
InterfaceMethod	scala/collection/TraversableLike.repr:()Ljava/lang/Object;
Asciz	()TThis;;
Asciz	withFilter;
Asciz	(Lscala/Function1;)Lscala/collection/TraversableLike$WithFilter;;
Asciz	(Lscala/collection/TraversableLike;Lscala/Function1;)Lscala/collection/TraversableLike$WithFilter;;
NameAndType	withFilter:(Lscala/collection/TraversableLike;Lscala/Function1;)Lscala/collection/TraversableLike$WithFilter;
Method	scala/collection/TraversableLike$class.withFilter:(Lscala/collection/TraversableLike;Lscala/Function1;)Lscala/collection/TraversableLike$WithFilter;
Asciz	toIndexedSeq;
Asciz	()Lscala/collection/mutable/IndexedSeq;;
Asciz	(Lscala/collection/TraversableLike;)Lscala/collection/mutable/IndexedSeq;;
NameAndType	toIndexedSeq:(Lscala/collection/TraversableLike;)Lscala/collection/mutable/IndexedSeq;
Method	scala/collection/TraversableLike$class.toIndexedSeq:(Lscala/collection/TraversableLike;)Lscala/collection/mutable/IndexedSeq;
Asciz	max;
Asciz	(Lscala/math/Ordering;)Ljava/lang/Object;;
Asciz	(Lscala/collection/TraversableLike;Lscala/math/Ordering;)Ljava/lang/Object;;
NameAndType	max:(Lscala/collection/TraversableLike;Lscala/math/Ordering;)Ljava/lang/Object;
Method	scala/collection/TraversableLike$class.max:(Lscala/collection/TraversableLike;Lscala/math/Ordering;)Ljava/lang/Object;
Asciz	cmp;
Asciz	Lscala/math/Ordering;;
Asciz	min;
NameAndType	min:(Lscala/collection/TraversableLike;Lscala/math/Ordering;)Ljava/lang/Object;
Method	scala/collection/TraversableLike$class.min:(Lscala/collection/TraversableLike;Lscala/math/Ordering;)Ljava/lang/Object;
Asciz	product;
Asciz	(Lscala/math/Numeric;)Ljava/lang/Object;;
Asciz	(Lscala/collection/TraversableLike;Lscala/math/Numeric;)Ljava/lang/Object;;
NameAndType	product:(Lscala/collection/TraversableLike;Lscala/math/Numeric;)Ljava/lang/Object;
Method	scala/collection/TraversableLike$class.product:(Lscala/collection/TraversableLike;Lscala/math/Numeric;)Ljava/lang/Object;
Asciz	num;
Asciz	Lscala/math/Numeric;;
Asciz	sum;
NameAndType	sum:(Lscala/collection/TraversableLike;Lscala/math/Numeric;)Ljava/lang/Object;
Method	scala/collection/TraversableLike$class.sum:(Lscala/collection/TraversableLike;Lscala/math/Numeric;)Ljava/lang/Object;
Asciz	partialMap;
Asciz	(Lscala/PartialFunction;Lscala/collection/generic/CanBuildFrom;)Ljava/lang/Object;;
Asciz	(Lscala/collection/TraversableLike;Lscala/PartialFunction;Lscala/collection/generic/CanBuildFrom;)Ljava/lang/Object;;
NameAndType	partialMap:(Lscala/collection/TraversableLike;Lscala/PartialFunction;Lscala/collection/generic/CanBuildFrom;)Ljava/lang/Object;
Method	scala/collection/TraversableLike$class.partialMap:(Lscala/collection/TraversableLike;Lscala/PartialFunction;Lscala/collection/generic/CanBuildFrom;)Ljava/lang/Object;
Asciz	pf;
Asciz	Lscala/PartialFunction;;
Asciz	bf;
Asciz	Lscala/collection/generic/CanBuildFrom;;
Asciz	toCollection;
Asciz	(Ljava/lang/Object;)Lscala/collection/Traversable;;
Asciz	(Lscala/collection/TraversableLike;Ljava/lang/Object;)Lscala/collection/Traversable;;
NameAndType	toCollection:(Lscala/collection/TraversableLike;Ljava/lang/Object;)Lscala/collection/Traversable;
Method	scala/collection/TraversableLike$class.toCollection:(Lscala/collection/TraversableLike;Ljava/lang/Object;)Lscala/collection/Traversable;
Asciz	Ljava/lang/Object;;
Asciz	thisCollection;
Asciz	(Lscala/collection/TraversableLike;)Lscala/collection/Traversable;;
NameAndType	thisCollection:(Lscala/collection/TraversableLike;)Lscala/collection/Traversable;
Method	scala/collection/TraversableLike$class.thisCollection:(Lscala/collection/TraversableLike;)Lscala/collection/Traversable;
Asciz	(Lscala/collection/TraversableLike;)Ljava/lang/Object;;
NameAndType	repr:(Lscala/collection/TraversableLike;)Ljava/lang/Object;
Method	scala/collection/TraversableLike$class.repr:(Lscala/collection/TraversableLike;)Ljava/lang/Object;
Asciz	toString;
Asciz	()Ljava/lang/String;;
Asciz	(Lscala/Proxy;)Ljava/lang/String;;
NameAndType	toString:(Lscala/Proxy;)Ljava/lang/String;
Method	scala/Proxy$class.toString:(Lscala/Proxy;)Ljava/lang/String;
Asciz	equals;
Asciz	(Ljava/lang/Object;)Z;
Asciz	(Lscala/Proxy;Ljava/lang/Object;)Z;
NameAndType	equals:(Lscala/Proxy;Ljava/lang/Object;)Z
Method	scala/Proxy$class.equals:(Lscala/Proxy;Ljava/lang/Object;)Z
Asciz	that;
Asciz	hashCode;
Asciz	()I;
Asciz	(Lscala/Proxy;)I;
NameAndType	hashCode:(Lscala/Proxy;)I
Method	scala/Proxy$class.hashCode:(Lscala/Proxy;)I
Asciz	(II)Lscala/collection/TraversableView;;
Asciz	(Lscala/collection/TraversableProxyLike;II)Lscala/collection/TraversableView;;
NameAndType	view:(Lscala/collection/TraversableProxyLike;II)Lscala/collection/TraversableView;
Method	scala/collection/TraversableProxyLike$class.view:(Lscala/collection/TraversableProxyLike;II)Lscala/collection/TraversableView;
Asciz	(Lscala/collection/TraversableProxyLike;)Ljava/lang/Object;;
NameAndType	view:(Lscala/collection/TraversableProxyLike;)Ljava/lang/Object;
Method	scala/collection/TraversableProxyLike$class.view:(Lscala/collection/TraversableProxyLike;)Ljava/lang/Object;
Asciz	stringPrefix;
Asciz	(Lscala/collection/TraversableProxyLike;)Ljava/lang/String;;
NameAndType	stringPrefix:(Lscala/collection/TraversableProxyLike;)Ljava/lang/String;
Method	scala/collection/TraversableProxyLike$class.stringPrefix:(Lscala/collection/TraversableProxyLike;)Ljava/lang/String;
Asciz	addString;
Asciz	(Lscala/collection/mutable/StringBuilder;)Lscala/collection/mutable/StringBuilder;;
Asciz	(Lscala/collection/TraversableProxyLike;Lscala/collection/mutable/StringBuilder;)Lscala/collection/mutable/StringBuilder;;
NameAndType	addString:(Lscala/collection/TraversableProxyLike;Lscala/collection/mutable/StringBuilder;)Lscala/collection/mutable/StringBuilder;
Method	scala/collection/TraversableProxyLike$class.addString:(Lscala/collection/TraversableProxyLike;Lscala/collection/mutable/StringBuilder;)Lscala/collection/mutable/StringBuilder;
Asciz	b;
Asciz	Lscala/collection/mutable/StringBuilder;;
Asciz	(Lscala/collection/mutable/StringBuilder;Ljava/lang/String;)Lscala/collection/mutable/StringBuilder;;
Asciz	(Lscala/collection/TraversableProxyLike;Lscala/collection/mutable/StringBuilder;Ljava/lang/String;)Lscala/collection/mutable/StringBuilder;;
NameAndType	addString:(Lscala/collection/TraversableProxyLike;Lscala/collection/mutable/StringBuilder;Ljava/lang/String;)Lscala/collection/mutable/StringBuilder;
Method	scala/collection/TraversableProxyLike$class.addString:(Lscala/collection/TraversableProxyLike;Lscala/collection/mutable/StringBuilder;Ljava/lang/String;)Lscala/collection/mutable/StringBuilder;
Asciz	sep;
Asciz	Ljava/lang/String;;
Asciz	(Lscala/collection/mutable/StringBuilder;Ljava/lang/String;Ljava/lang/String;Ljava/lang/String;)Lscala/collection/mutable/StringBuilder;;
Asciz	(Lscala/collection/TraversableProxyLike;Lscala/collection/mutable/StringBuilder;Ljava/lang/String;Ljava/lang/String;Ljava/lang/String;)Lscala/collection/mutable/StringBuilder;;
NameAndType	addString:(Lscala/collection/TraversableProxyLike;Lscala/collection/mutable/StringBuilder;Ljava/lang/String;Ljava/lang/String;Ljava/lang/String;)Lscala/collection/mutable/StringBuilder;
Method	scala/collection/TraversableProxyLike$class.addString:(Lscala/collection/TraversableProxyLike;Lscala/collection/mutable/StringBuilder;Ljava/lang/String;Ljava/lang/String;Ljava/lang/String;)Lscala/collection/mutable/StringBuilder;
Asciz	start;
Asciz	end;
Asciz	mkString;
NameAndType	mkString:(Lscala/collection/TraversableProxyLike;)Ljava/lang/String;
Method	scala/collection/TraversableProxyLike$class.mkString:(Lscala/collection/TraversableProxyLike;)Ljava/lang/String;
Asciz	(Ljava/lang/String;)Ljava/lang/String;;
Asciz	(Lscala/collection/TraversableProxyLike;Ljava/lang/String;)Ljava/lang/String;;
NameAndType	mkString:(Lscala/collection/TraversableProxyLike;Ljava/lang/String;)Ljava/lang/String;
Method	scala/collection/TraversableProxyLike$class.mkString:(Lscala/collection/TraversableProxyLike;Ljava/lang/String;)Ljava/lang/String;
Asciz	(Ljava/lang/String;Ljava/lang/String;Ljava/lang/String;)Ljava/lang/String;;
Asciz	(Lscala/collection/TraversableProxyLike;Ljava/lang/String;Ljava/lang/String;Ljava/lang/String;)Ljava/lang/String;;
NameAndType	mkString:(Lscala/collection/TraversableProxyLike;Ljava/lang/String;Ljava/lang/String;Ljava/lang/String;)Ljava/lang/String;
Method	scala/collection/TraversableProxyLike$class.mkString:(Lscala/collection/TraversableProxyLike;Ljava/lang/String;Ljava/lang/String;Ljava/lang/String;)Ljava/lang/String;
Asciz	toSet;
Asciz	()Lscala/collection/immutable/Set;;
Asciz	(Lscala/collection/TraversableProxyLike;)Lscala/collection/immutable/Set;;
NameAndType	toSet:(Lscala/collection/TraversableProxyLike;)Lscala/collection/immutable/Set;
Method	scala/collection/TraversableProxyLike$class.toSet:(Lscala/collection/TraversableProxyLike;)Lscala/collection/immutable/Set;
Asciz	toStream;
Asciz	()Lscala/collection/immutable/Stream;;
Asciz	(Lscala/collection/TraversableProxyLike;)Lscala/collection/immutable/Stream;;
NameAndType	toStream:(Lscala/collection/TraversableProxyLike;)Lscala/collection/immutable/Stream;
Method	scala/collection/TraversableProxyLike$class.toStream:(Lscala/collection/TraversableProxyLike;)Lscala/collection/immutable/Stream;
Asciz	toSeq;
Asciz	()Lscala/collection/Seq;;
Asciz	(Lscala/collection/TraversableProxyLike;)Lscala/collection/Seq;;
NameAndType	toSeq:(Lscala/collection/TraversableProxyLike;)Lscala/collection/Seq;
Method	scala/collection/TraversableProxyLike$class.toSeq:(Lscala/collection/TraversableProxyLike;)Lscala/collection/Seq;
Asciz	toIterable;
Asciz	()Lscala/collection/Iterable;;
Asciz	(Lscala/collection/TraversableProxyLike;)Lscala/collection/Iterable;;
NameAndType	toIterable:(Lscala/collection/TraversableProxyLike;)Lscala/collection/Iterable;
Method	scala/collection/TraversableProxyLike$class.toIterable:(Lscala/collection/TraversableProxyLike;)Lscala/collection/Iterable;
Asciz	toList;
Asciz	()Lscala/collection/immutable/List;;
Asciz	(Lscala/collection/TraversableProxyLike;)Lscala/collection/immutable/List;;
NameAndType	toList:(Lscala/collection/TraversableProxyLike;)Lscala/collection/immutable/List;
Method	scala/collection/TraversableProxyLike$class.toList:(Lscala/collection/TraversableProxyLike;)Lscala/collection/immutable/List;
Asciz	toArray;
Asciz	(Lscala/reflect/ClassManifest;)Ljava/lang/Object;;
Asciz	(Lscala/collection/TraversableProxyLike;Lscala/reflect/ClassManifest;)Ljava/lang/Object;;
NameAndType	toArray:(Lscala/collection/TraversableProxyLike;Lscala/reflect/ClassManifest;)Ljava/lang/Object;
Method	scala/collection/TraversableProxyLike$class.toArray:(Lscala/collection/TraversableProxyLike;Lscala/reflect/ClassManifest;)Ljava/lang/Object;
Asciz	evidence$1;
Asciz	Lscala/reflect/ClassManifest;;
Asciz	copyToArray;
Asciz	(Ljava/lang/Object;I)V;
Asciz	(Lscala/collection/TraversableProxyLike;Ljava/lang/Object;I)V;
NameAndType	copyToArray:(Lscala/collection/TraversableProxyLike;Ljava/lang/Object;I)V
Method	scala/collection/TraversableProxyLike$class.copyToArray:(Lscala/collection/TraversableProxyLike;Ljava/lang/Object;I)V
Asciz	xs;
Asciz	(Ljava/lang/Object;II)V;
Asciz	(Lscala/collection/TraversableProxyLike;Ljava/lang/Object;II)V;
NameAndType	copyToArray:(Lscala/collection/TraversableProxyLike;Ljava/lang/Object;II)V
Method	scala/collection/TraversableProxyLike$class.copyToArray:(Lscala/collection/TraversableProxyLike;Ljava/lang/Object;II)V
Asciz	len;
Asciz	copyToBuffer;
Asciz	(Lscala/collection/mutable/Buffer;)V;
Asciz	(Lscala/collection/TraversableProxyLike;Lscala/collection/mutable/Buffer;)V;
NameAndType	copyToBuffer:(Lscala/collection/TraversableProxyLike;Lscala/collection/mutable/Buffer;)V
Method	scala/collection/TraversableProxyLike$class.copyToBuffer:(Lscala/collection/TraversableProxyLike;Lscala/collection/mutable/Buffer;)V
Asciz	dest;
Asciz	Lscala/collection/mutable/Buffer;;
Asciz	splitAt;
Asciz	(I)Lscala/Tuple2;;
Asciz	(Lscala/collection/TraversableProxyLike;I)Lscala/Tuple2;;
NameAndType	splitAt:(Lscala/collection/TraversableProxyLike;I)Lscala/Tuple2;
Method	scala/collection/TraversableProxyLike$class.splitAt:(Lscala/collection/TraversableProxyLike;I)Lscala/Tuple2;
Asciz	span;
Asciz	(Lscala/Function1;)Lscala/Tuple2;;
Asciz	(Lscala/collection/TraversableProxyLike;Lscala/Function1;)Lscala/Tuple2;;
NameAndType	span:(Lscala/collection/TraversableProxyLike;Lscala/Function1;)Lscala/Tuple2;
Method	scala/collection/TraversableProxyLike$class.span:(Lscala/collection/TraversableProxyLike;Lscala/Function1;)Lscala/Tuple2;
Asciz	(Lscala/collection/TraversableProxyLike;Lscala/Function1;)Lscala/collection/TraversableLike;;
NameAndType	dropWhile:(Lscala/collection/TraversableProxyLike;Lscala/Function1;)Lscala/collection/TraversableLike;
Method	scala/collection/TraversableProxyLike$class.dropWhile:(Lscala/collection/TraversableProxyLike;Lscala/Function1;)Lscala/collection/TraversableLike;
NameAndType	takeWhile:(Lscala/collection/TraversableProxyLike;Lscala/Function1;)Lscala/collection/TraversableLike;
Method	scala/collection/TraversableProxyLike$class.takeWhile:(Lscala/collection/TraversableProxyLike;Lscala/Function1;)Lscala/collection/TraversableLike;
Asciz	(Lscala/collection/TraversableProxyLike;II)Lscala/collection/TraversableLike;;
NameAndType	slice:(Lscala/collection/TraversableProxyLike;II)Lscala/collection/TraversableLike;
Method	scala/collection/TraversableProxyLike$class.slice:(Lscala/collection/TraversableProxyLike;II)Lscala/collection/TraversableLike;
Asciz	(Lscala/collection/TraversableProxyLike;I)Lscala/collection/TraversableLike;;
NameAndType	drop:(Lscala/collection/TraversableProxyLike;I)Lscala/collection/TraversableLike;
Method	scala/collection/TraversableProxyLike$class.drop:(Lscala/collection/TraversableProxyLike;I)Lscala/collection/TraversableLike;
NameAndType	take:(Lscala/collection/TraversableProxyLike;I)Lscala/collection/TraversableLike;
Method	scala/collection/TraversableProxyLike$class.take:(Lscala/collection/TraversableProxyLike;I)Lscala/collection/TraversableLike;
Asciz	(Lscala/collection/TraversableProxyLike;)Lscala/collection/TraversableLike;;
NameAndType	init:(Lscala/collection/TraversableProxyLike;)Lscala/collection/TraversableLike;
Method	scala/collection/TraversableProxyLike$class.init:(Lscala/collection/TraversableProxyLike;)Lscala/collection/TraversableLike;
Asciz	lastOption;
Asciz	()Lscala/Option;;
Asciz	(Lscala/collection/TraversableProxyLike;)Lscala/Option;;
NameAndType	lastOption:(Lscala/collection/TraversableProxyLike;)Lscala/Option;
Method	scala/collection/TraversableProxyLike$class.lastOption:(Lscala/collection/TraversableProxyLike;)Lscala/Option;
Asciz	last;
NameAndType	last:(Lscala/collection/TraversableProxyLike;)Ljava/lang/Object;
Method	scala/collection/TraversableProxyLike$class.last:(Lscala/collection/TraversableProxyLike;)Ljava/lang/Object;
NameAndType	tail:(Lscala/collection/TraversableProxyLike;)Lscala/collection/TraversableLike;
Method	scala/collection/TraversableProxyLike$class.tail:(Lscala/collection/TraversableProxyLike;)Lscala/collection/TraversableLike;
Asciz	headOption;
NameAndType	headOption:(Lscala/collection/TraversableProxyLike;)Lscala/Option;
Method	scala/collection/TraversableProxyLike$class.headOption:(Lscala/collection/TraversableProxyLike;)Lscala/Option;
Asciz	head;
NameAndType	head:(Lscala/collection/TraversableProxyLike;)Ljava/lang/Object;
Method	scala/collection/TraversableProxyLike$class.head:(Lscala/collection/TraversableProxyLike;)Ljava/lang/Object;
Asciz	reduceRightOption;
Asciz	(Lscala/Function2;)Lscala/Option;;
Asciz	(Lscala/collection/TraversableProxyLike;Lscala/Function2;)Lscala/Option;;
NameAndType	reduceRightOption:(Lscala/collection/TraversableProxyLike;Lscala/Function2;)Lscala/Option;
Method	scala/collection/TraversableProxyLike$class.reduceRightOption:(Lscala/collection/TraversableProxyLike;Lscala/Function2;)Lscala/Option;
Asciz	op;
Asciz	Lscala/Function2;;
Asciz	reduceRight;
Asciz	(Lscala/Function2;)Ljava/lang/Object;;
Asciz	(Lscala/collection/TraversableProxyLike;Lscala/Function2;)Ljava/lang/Object;;
NameAndType	reduceRight:(Lscala/collection/TraversableProxyLike;Lscala/Function2;)Ljava/lang/Object;
Method	scala/collection/TraversableProxyLike$class.reduceRight:(Lscala/collection/TraversableProxyLike;Lscala/Function2;)Ljava/lang/Object;
Asciz	reduceLeftOption;
NameAndType	reduceLeftOption:(Lscala/collection/TraversableProxyLike;Lscala/Function2;)Lscala/Option;
Method	scala/collection/TraversableProxyLike$class.reduceLeftOption:(Lscala/collection/TraversableProxyLike;Lscala/Function2;)Lscala/Option;
Asciz	reduceLeft;
NameAndType	reduceLeft:(Lscala/collection/TraversableProxyLike;Lscala/Function2;)Ljava/lang/Object;
Method	scala/collection/TraversableProxyLike$class.reduceLeft:(Lscala/collection/TraversableProxyLike;Lscala/Function2;)Ljava/lang/Object;
Asciz	$colon$bslash;
Asciz	(Ljava/lang/Object;Lscala/Function2;)Ljava/lang/Object;;
Asciz	(Lscala/collection/TraversableProxyLike;Ljava/lang/Object;Lscala/Function2;)Ljava/lang/Object;;
NameAndType	$colon$bslash:(Lscala/collection/TraversableProxyLike;Ljava/lang/Object;Lscala/Function2;)Ljava/lang/Object;
Method	scala/collection/TraversableProxyLike$class.$colon$bslash:(Lscala/collection/TraversableProxyLike;Ljava/lang/Object;Lscala/Function2;)Ljava/lang/Object;
Asciz	z;
Asciz	foldRight;
NameAndType	foldRight:(Lscala/collection/TraversableProxyLike;Ljava/lang/Object;Lscala/Function2;)Ljava/lang/Object;
Method	scala/collection/TraversableProxyLike$class.foldRight:(Lscala/collection/TraversableProxyLike;Ljava/lang/Object;Lscala/Function2;)Ljava/lang/Object;
Asciz	$div$colon;
NameAndType	$div$colon:(Lscala/collection/TraversableProxyLike;Ljava/lang/Object;Lscala/Function2;)Ljava/lang/Object;
Method	scala/collection/TraversableProxyLike$class.$div$colon:(Lscala/collection/TraversableProxyLike;Ljava/lang/Object;Lscala/Function2;)Ljava/lang/Object;
Asciz	foldLeft;
NameAndType	foldLeft:(Lscala/collection/TraversableProxyLike;Ljava/lang/Object;Lscala/Function2;)Ljava/lang/Object;
Method	scala/collection/TraversableProxyLike$class.foldLeft:(Lscala/collection/TraversableProxyLike;Ljava/lang/Object;Lscala/Function2;)Ljava/lang/Object;
Asciz	find;
Asciz	(Lscala/Function1;)Lscala/Option;;
Asciz	(Lscala/collection/TraversableProxyLike;Lscala/Function1;)Lscala/Option;;
NameAndType	find:(Lscala/collection/TraversableProxyLike;Lscala/Function1;)Lscala/Option;
Method	scala/collection/TraversableProxyLike$class.find:(Lscala/collection/TraversableProxyLike;Lscala/Function1;)Lscala/Option;
Asciz	count;
Asciz	(Lscala/Function1;)I;
Asciz	(Lscala/collection/TraversableProxyLike;Lscala/Function1;)I;
NameAndType	count:(Lscala/collection/TraversableProxyLike;Lscala/Function1;)I
Method	scala/collection/TraversableProxyLike$class.count:(Lscala/collection/TraversableProxyLike;Lscala/Function1;)I
Asciz	exists;
Asciz	(Lscala/Function1;)Z;
Asciz	(Lscala/collection/TraversableProxyLike;Lscala/Function1;)Z;
NameAndType	exists:(Lscala/collection/TraversableProxyLike;Lscala/Function1;)Z
Method	scala/collection/TraversableProxyLike$class.exists:(Lscala/collection/TraversableProxyLike;Lscala/Function1;)Z
Asciz	forall;
NameAndType	forall:(Lscala/collection/TraversableProxyLike;Lscala/Function1;)Z
Method	scala/collection/TraversableProxyLike$class.forall:(Lscala/collection/TraversableProxyLike;Lscala/Function1;)Z
Asciz	groupBy;
Asciz	(Lscala/Function1;)Lscala/collection/Map;;
Asciz	(Lscala/collection/TraversableProxyLike;Lscala/Function1;)Lscala/collection/Map;;
NameAndType	groupBy:(Lscala/collection/TraversableProxyLike;Lscala/Function1;)Lscala/collection/Map;
Method	scala/collection/TraversableProxyLike$class.groupBy:(Lscala/collection/TraversableProxyLike;Lscala/Function1;)Lscala/collection/Map;
Asciz	f;
Asciz	partition;
NameAndType	partition:(Lscala/collection/TraversableProxyLike;Lscala/Function1;)Lscala/Tuple2;
Method	scala/collection/TraversableProxyLike$class.partition:(Lscala/collection/TraversableProxyLike;Lscala/Function1;)Lscala/Tuple2;
NameAndType	filterNot:(Lscala/collection/TraversableProxyLike;Lscala/Function1;)Lscala/collection/TraversableLike;
Method	scala/collection/TraversableProxyLike$class.filterNot:(Lscala/collection/TraversableProxyLike;Lscala/Function1;)Lscala/collection/TraversableLike;
NameAndType	filter:(Lscala/collection/TraversableProxyLike;Lscala/Function1;)Lscala/collection/TraversableLike;
Method	scala/collection/TraversableProxyLike$class.filter:(Lscala/collection/TraversableProxyLike;Lscala/Function1;)Lscala/collection/TraversableLike;
Asciz	flatMap;
Asciz	(Lscala/Function1;Lscala/collection/generic/CanBuildFrom;)Ljava/lang/Object;;
Asciz	(Lscala/collection/TraversableProxyLike;Lscala/Function1;Lscala/collection/generic/CanBuildFrom;)Ljava/lang/Object;;
NameAndType	flatMap:(Lscala/collection/TraversableProxyLike;Lscala/Function1;Lscala/collection/generic/CanBuildFrom;)Ljava/lang/Object;
Method	scala/collection/TraversableProxyLike$class.flatMap:(Lscala/collection/TraversableProxyLike;Lscala/Function1;Lscala/collection/generic/CanBuildFrom;)Ljava/lang/Object;
Asciz	map;
NameAndType	map:(Lscala/collection/TraversableProxyLike;Lscala/Function1;Lscala/collection/generic/CanBuildFrom;)Ljava/lang/Object;
Method	scala/collection/TraversableProxyLike$class.map:(Lscala/collection/TraversableProxyLike;Lscala/Function1;Lscala/collection/generic/CanBuildFrom;)Ljava/lang/Object;
Asciz	$plus$plus;
Asciz	(Lscala/collection/Iterator;Lscala/collection/generic/CanBuildFrom;)Ljava/lang/Object;;
Asciz	(Lscala/collection/TraversableProxyLike;Lscala/collection/Iterator;Lscala/collection/generic/CanBuildFrom;)Ljava/lang/Object;;
NameAndType	$plus$plus:(Lscala/collection/TraversableProxyLike;Lscala/collection/Iterator;Lscala/collection/generic/CanBuildFrom;)Ljava/lang/Object;
Method	scala/collection/TraversableProxyLike$class.$plus$plus:(Lscala/collection/TraversableProxyLike;Lscala/collection/Iterator;Lscala/collection/generic/CanBuildFrom;)Ljava/lang/Object;
Asciz	Lscala/collection/Iterator;;
Asciz	(Lscala/collection/Traversable;Lscala/collection/generic/CanBuildFrom;)Ljava/lang/Object;;
Asciz	(Lscala/collection/TraversableProxyLike;Lscala/collection/Traversable;Lscala/collection/generic/CanBuildFrom;)Ljava/lang/Object;;
NameAndType	$plus$plus:(Lscala/collection/TraversableProxyLike;Lscala/collection/Traversable;Lscala/collection/generic/CanBuildFrom;)Ljava/lang/Object;
Method	scala/collection/TraversableProxyLike$class.$plus$plus:(Lscala/collection/TraversableProxyLike;Lscala/collection/Traversable;Lscala/collection/generic/CanBuildFrom;)Ljava/lang/Object;
Asciz	Lscala/collection/Traversable;;
Asciz	hasDefiniteSize;
Asciz	()Z;
Asciz	(Lscala/collection/TraversableProxyLike;)Z;
NameAndType	hasDefiniteSize:(Lscala/collection/TraversableProxyLike;)Z
Method	scala/collection/TraversableProxyLike$class.hasDefiniteSize:(Lscala/collection/TraversableProxyLike;)Z
Asciz	size;
Asciz	(Lscala/collection/TraversableProxyLike;)I;
NameAndType	size:(Lscala/collection/TraversableProxyLike;)I
Method	scala/collection/TraversableProxyLike$class.size:(Lscala/collection/TraversableProxyLike;)I
Asciz	nonEmpty;
NameAndType	nonEmpty:(Lscala/collection/TraversableProxyLike;)Z
Method	scala/collection/TraversableProxyLike$class.nonEmpty:(Lscala/collection/TraversableProxyLike;)Z
Asciz	isEmpty;
NameAndType	isEmpty:(Lscala/collection/TraversableProxyLike;)Z
Method	scala/collection/TraversableProxyLike$class.isEmpty:(Lscala/collection/TraversableProxyLike;)Z
Asciz	foreach;
Asciz	(Lscala/Function1;)V;
Asciz	(Lscala/collection/TraversableProxyLike;Lscala/Function1;)V;
NameAndType	foreach:(Lscala/collection/TraversableProxyLike;Lscala/Function1;)V
Method	scala/collection/TraversableProxyLike$class.foreach:(Lscala/collection/TraversableProxyLike;Lscala/Function1;)V
Asciz	<A:Ljava/lang/Object;This::Lscala/collection/TraversableLike<TA;TThis;>;:Lscala/collection/Traversable<TA;>;>Ljava/lang/Object;Lscala/collection/TraversableProxyLike<TA;Lscala/collection/Traversable<TA;>;>;Lscala/collection/interfaces/TraversableMethods<TA;Lscala/collection/Traversable<TA;>;>;Lscala/ScalaObject;;
Asciz	ScalaSig;
Asciz	InnerClasses;
Asciz	scala/collection/TraversableLike$WithFilter;
class	scala/collection/TraversableLike$WithFilter
Asciz	WithFilter;
Asciz	scala/collection/interfaces/TraversableMethods;
class	scala/collection/interfaces/TraversableMethods
Asciz	scala/ScalaObject;
class	scala/ScalaObject

{
public scala.collection.TraversableProxyLikeConfirmation();
  Signature: ()V
  Code:
   Stack=1, Locals=1, Args_size=1
	aload_0
	invokespecial	Method java/lang/Object."<init>":()V
	aload_0
	invokestatic	Method scala/collection/TraversableLike$class.$init$:(Lscala/collection/TraversableLike;)V
	aload_0
	invokestatic	Method scala/Proxy$class.$init$:(Lscala/Proxy;)V
	aload_0
	invokestatic	Method scala/collection/TraversableProxyLike$class.$init$:(Lscala/collection/TraversableProxyLike;)V
	return
  Labels:
  Signature: length = 0x2
   00 04 

public java.lang.Object self();
  Signature: ()Ljava/lang/Object;
  Code:
   Stack=1, Locals=1, Args_size=1
	aload_0
	invokevirtual	Method self:()Lscala/collection/TraversableLike;
	areturn
  Labels:

public java.lang.Object filter(scala.Function1);
  Signature: (Lscala/Function1;)Ljava/lang/Object;
  Code:
   Stack=2, Locals=2, Args_size=2
	aload_0
	aload_1
	invokeinterface	InterfaceMethod scala/collection/TraversableProxyLike.filter:(Lscala/Function1;)Lscala/collection/TraversableLike;
	areturn
  Labels:
  LocalVariableTable: 
   Start  Length  Slot  Name   Signature
   0      8      0    this       Lscala/collection/TraversableProxyLikeConfirmation;
   0      8      1    p       Lscala/Function1;


public scala.collection.Traversable filter(scala.Function1);
  Signature: (Lscala/Function1;)Lscala/collection/Traversable;
  Code:
   Stack=2, Locals=2, Args_size=2
	aload_0
	aload_1
	invokeinterface	InterfaceMethod scala/collection/TraversableProxyLike.filter:(Lscala/Function1;)Lscala/collection/TraversableLike;
	checkcast	class scala/collection/Traversable
	areturn
  Labels:
  LocalVariableTable: 
   Start  Length  Slot  Name   Signature
   0      11      0    this       Lscala/collection/TraversableProxyLikeConfirmation;
   0      11      1    p       Lscala/Function1;


public java.lang.Object filterNot(scala.Function1);
  Signature: (Lscala/Function1;)Ljava/lang/Object;
  Code:
   Stack=2, Locals=2, Args_size=2
	aload_0
	aload_1
	invokeinterface	InterfaceMethod scala/collection/TraversableProxyLike.filterNot:(Lscala/Function1;)Lscala/collection/TraversableLike;
	areturn
  Labels:
  LocalVariableTable: 
   Start  Length  Slot  Name   Signature
   0      8      0    this       Lscala/collection/TraversableProxyLikeConfirmation;
   0      8      1    p       Lscala/Function1;


public scala.collection.Traversable filterNot(scala.Function1);
  Signature: (Lscala/Function1;)Lscala/collection/Traversable;
  Code:
   Stack=2, Locals=2, Args_size=2
	aload_0
	aload_1
	invokeinterface	InterfaceMethod scala/collection/TraversableProxyLike.filterNot:(Lscala/Function1;)Lscala/collection/TraversableLike;
	checkcast	class scala/collection/Traversable
	areturn
  Labels:
  LocalVariableTable: 
   Start  Length  Slot  Name   Signature
   0      11      0    this       Lscala/collection/TraversableProxyLikeConfirmation;
   0      11      1    p       Lscala/Function1;


public java.lang.Object tail();
  Signature: ()Ljava/lang/Object;
  Code:
   Stack=1, Locals=1, Args_size=1
	aload_0
	invokeinterface	InterfaceMethod scala/collection/TraversableProxyLike.tail:()Lscala/collection/TraversableLike;
	areturn
  Labels:

public scala.collection.Traversable tail();
  Signature: ()Lscala/collection/Traversable;
  Code:
   Stack=1, Locals=1, Args_size=1
	aload_0
	invokeinterface	InterfaceMethod scala/collection/TraversableProxyLike.tail:()Lscala/collection/TraversableLike;
	checkcast	class scala/collection/Traversable
	areturn
  Labels:

public java.lang.Object init();
  Signature: ()Ljava/lang/Object;
  Code:
   Stack=1, Locals=1, Args_size=1
	aload_0
	invokeinterface	InterfaceMethod scala/collection/TraversableProxyLike.init:()Lscala/collection/TraversableLike;
	areturn
  Labels:

public scala.collection.Traversable init();
  Signature: ()Lscala/collection/Traversable;
  Code:
   Stack=1, Locals=1, Args_size=1
	aload_0
	invokeinterface	InterfaceMethod scala/collection/TraversableProxyLike.init:()Lscala/collection/TraversableLike;
	checkcast	class scala/collection/Traversable
	areturn
  Labels:

public java.lang.Object take(int);
  Signature: (I)Ljava/lang/Object;
  Code:
   Stack=2, Locals=2, Args_size=2
	aload_0
	iload_1
	invokeinterface	InterfaceMethod scala/collection/TraversableProxyLike.take:(I)Lscala/collection/TraversableLike;
	areturn
  Labels:
  LocalVariableTable: 
   Start  Length  Slot  Name   Signature
   0      8      0    this       Lscala/collection/TraversableProxyLikeConfirmation;
   0      8      1    n       I


public scala.collection.Traversable take(int);
  Signature: (I)Lscala/collection/Traversable;
  Code:
   Stack=2, Locals=2, Args_size=2
	aload_0
	iload_1
	invokeinterface	InterfaceMethod scala/collection/TraversableProxyLike.take:(I)Lscala/collection/TraversableLike;
	checkcast	class scala/collection/Traversable
	areturn
  Labels:
  LocalVariableTable: 
   Start  Length  Slot  Name   Signature
   0      11      0    this       Lscala/collection/TraversableProxyLikeConfirmation;
   0      11      1    n       I


public java.lang.Object drop(int);
  Signature: (I)Ljava/lang/Object;
  Code:
   Stack=2, Locals=2, Args_size=2
	aload_0
	iload_1
	invokeinterface	InterfaceMethod scala/collection/TraversableProxyLike.drop:(I)Lscala/collection/TraversableLike;
	areturn
  Labels:
  LocalVariableTable: 
   Start  Length  Slot  Name   Signature
   0      8      0    this       Lscala/collection/TraversableProxyLikeConfirmation;
   0      8      1    n       I


public scala.collection.Traversable drop(int);
  Signature: (I)Lscala/collection/Traversable;
  Code:
   Stack=2, Locals=2, Args_size=2
	aload_0
	iload_1
	invokeinterface	InterfaceMethod scala/collection/TraversableProxyLike.drop:(I)Lscala/collection/TraversableLike;
	checkcast	class scala/collection/Traversable
	areturn
  Labels:
  LocalVariableTable: 
   Start  Length  Slot  Name   Signature
   0      11      0    this       Lscala/collection/TraversableProxyLikeConfirmation;
   0      11      1    n       I


public java.lang.Object slice(int, int);
  Signature: (II)Ljava/lang/Object;
  Code:
   Stack=3, Locals=3, Args_size=3
	aload_0
	iload_1
	iload_2
	invokeinterface	InterfaceMethod scala/collection/TraversableProxyLike.slice:(II)Lscala/collection/TraversableLike;
	areturn
  Labels:
  LocalVariableTable: 
   Start  Length  Slot  Name   Signature
   0      9      0    this       Lscala/collection/TraversableProxyLikeConfirmation;
   0      9      1    from       I
   0      9      2    until       I


public scala.collection.Traversable slice(int, int);
  Signature: (II)Lscala/collection/Traversable;
  Code:
   Stack=3, Locals=3, Args_size=3
	aload_0
	iload_1
	iload_2
	invokeinterface	InterfaceMethod scala/collection/TraversableProxyLike.slice:(II)Lscala/collection/TraversableLike;
	checkcast	class scala/collection/Traversable
	areturn
  Labels:
  LocalVariableTable: 
   Start  Length  Slot  Name   Signature
   0      12      0    this       Lscala/collection/TraversableProxyLikeConfirmation;
   0      12      1    from       I
   0      12      2    until       I


public java.lang.Object takeWhile(scala.Function1);
  Signature: (Lscala/Function1;)Ljava/lang/Object;
  Code:
   Stack=2, Locals=2, Args_size=2
	aload_0
	aload_1
	invokeinterface	InterfaceMethod scala/collection/TraversableProxyLike.takeWhile:(Lscala/Function1;)Lscala/collection/TraversableLike;
	areturn
  Labels:
  LocalVariableTable: 
   Start  Length  Slot  Name   Signature
   0      8      0    this       Lscala/collection/TraversableProxyLikeConfirmation;
   0      8      1    p       Lscala/Function1;


public scala.collection.Traversable takeWhile(scala.Function1);
  Signature: (Lscala/Function1;)Lscala/collection/Traversable;
  Code:
   Stack=2, Locals=2, Args_size=2
	aload_0
	aload_1
	invokeinterface	InterfaceMethod scala/collection/TraversableProxyLike.takeWhile:(Lscala/Function1;)Lscala/collection/TraversableLike;
	checkcast	class scala/collection/Traversable
	areturn
  Labels:
  LocalVariableTable: 
   Start  Length  Slot  Name   Signature
   0      11      0    this       Lscala/collection/TraversableProxyLikeConfirmation;
   0      11      1    p       Lscala/Function1;


public java.lang.Object dropWhile(scala.Function1);
  Signature: (Lscala/Function1;)Ljava/lang/Object;
  Code:
   Stack=2, Locals=2, Args_size=2
	aload_0
	aload_1
	invokeinterface	InterfaceMethod scala/collection/TraversableProxyLike.dropWhile:(Lscala/Function1;)Lscala/collection/TraversableLike;
	areturn
  Labels:
  LocalVariableTable: 
   Start  Length  Slot  Name   Signature
   0      8      0    this       Lscala/collection/TraversableProxyLikeConfirmation;
   0      8      1    p       Lscala/Function1;


public scala.collection.Traversable dropWhile(scala.Function1);
  Signature: (Lscala/Function1;)Lscala/collection/Traversable;
  Code:
   Stack=2, Locals=2, Args_size=2
	aload_0
	aload_1
	invokeinterface	InterfaceMethod scala/collection/TraversableProxyLike.dropWhile:(Lscala/Function1;)Lscala/collection/TraversableLike;
	checkcast	class scala/collection/Traversable
	areturn
  Labels:
  LocalVariableTable: 
   Start  Length  Slot  Name   Signature
   0      11      0    this       Lscala/collection/TraversableProxyLikeConfirmation;
   0      11      1    p       Lscala/Function1;


public scala.collection.TraversableView view();
  Signature: ()Lscala/collection/TraversableView;
  Code:
   Stack=1, Locals=1, Args_size=1
	aload_0
	invokeinterface	InterfaceMethod scala/collection/TraversableProxyLike.view:()Ljava/lang/Object;
	checkcast	class scala/collection/TraversableView
	areturn
  Labels:

public scala.collection.mutable.Builder newBuilder();
  Signature: ()Lscala/collection/mutable/Builder;
  Code:
   Stack=1, Locals=1, Args_size=1
	getstatic	Field scala/collection/Traversable$.MODULE$:Lscala/collection/Traversable$;
	invokevirtual	Method scala/collection/Traversable$.newBuilder:()Lscala/collection/mutable/Builder;
	areturn
  Labels:
  Signature: length = 0x2
   00 65 

public scala.collection.TraversableLike self();
  Signature: ()Lscala/collection/TraversableLike;
  Code:
   Stack=1, Locals=1, Args_size=1
	aload_0
	invokeinterface	InterfaceMethod scala/collection/TraversableLike.repr:()Ljava/lang/Object;
	checkcast	class scala/collection/TraversableLike
	areturn
  Labels:
  Signature: length = 0x2
   00 6B 

public scala.collection.TraversableLike$WithFilter withFilter(scala.Function1);
  Signature: (Lscala/Function1;)Lscala/collection/TraversableLike$WithFilter;
  Code:
   Stack=2, Locals=2, Args_size=2
	aload_0
	aload_1
	invokestatic	Method scala/collection/TraversableLike$class.withFilter:(Lscala/collection/TraversableLike;Lscala/Function1;)Lscala/collection/TraversableLike$WithFilter;
	areturn
  Labels:
  LocalVariableTable: 
   Start  Length  Slot  Name   Signature
   0      6      0    this       Lscala/collection/TraversableProxyLikeConfirmation;
   0      6      1    p       Lscala/Function1;

  Signature: length = 0x2
   00 6D 

public scala.collection.mutable.IndexedSeq toIndexedSeq();
  Signature: ()Lscala/collection/mutable/IndexedSeq;
  Code:
   Stack=1, Locals=1, Args_size=1
	aload_0
	invokestatic	Method scala/collection/TraversableLike$class.toIndexedSeq:(Lscala/collection/TraversableLike;)Lscala/collection/mutable/IndexedSeq;
	areturn
  Labels:

public java.lang.Object max(scala.math.Ordering);
  Signature: (Lscala/math/Ordering;)Ljava/lang/Object;
  Code:
   Stack=2, Locals=2, Args_size=2
	aload_0
	aload_1
	invokestatic	Method scala/collection/TraversableLike$class.max:(Lscala/collection/TraversableLike;Lscala/math/Ordering;)Ljava/lang/Object;
	areturn
  Labels:
  LocalVariableTable: 
   Start  Length  Slot  Name   Signature
   0      6      0    this       Lscala/collection/TraversableProxyLikeConfirmation;
   0      6      1    cmp       Lscala/math/Ordering;


public java.lang.Object min(scala.math.Ordering);
  Signature: (Lscala/math/Ordering;)Ljava/lang/Object;
  Code:
   Stack=2, Locals=2, Args_size=2
	aload_0
	aload_1
	invokestatic	Method scala/collection/TraversableLike$class.min:(Lscala/collection/TraversableLike;Lscala/math/Ordering;)Ljava/lang/Object;
	areturn
  Labels:
  LocalVariableTable: 
   Start  Length  Slot  Name   Signature
   0      6      0    this       Lscala/collection/TraversableProxyLikeConfirmation;
   0      6      1    cmp       Lscala/math/Ordering;


public java.lang.Object product(scala.math.Numeric);
  Signature: (Lscala/math/Numeric;)Ljava/lang/Object;
  Code:
   Stack=2, Locals=2, Args_size=2
	aload_0
	aload_1
	invokestatic	Method scala/collection/TraversableLike$class.product:(Lscala/collection/TraversableLike;Lscala/math/Numeric;)Ljava/lang/Object;
	areturn
  Labels:
  LocalVariableTable: 
   Start  Length  Slot  Name   Signature
   0      6      0    this       Lscala/collection/TraversableProxyLikeConfirmation;
   0      6      1    num       Lscala/math/Numeric;


public java.lang.Object sum(scala.math.Numeric);
  Signature: (Lscala/math/Numeric;)Ljava/lang/Object;
  Code:
   Stack=2, Locals=2, Args_size=2
	aload_0
	aload_1
	invokestatic	Method scala/collection/TraversableLike$class.sum:(Lscala/collection/TraversableLike;Lscala/math/Numeric;)Ljava/lang/Object;
	areturn
  Labels:
  LocalVariableTable: 
   Start  Length  Slot  Name   Signature
   0      6      0    this       Lscala/collection/TraversableProxyLikeConfirmation;
   0      6      1    num       Lscala/math/Numeric;


public java.lang.Object partialMap(scala.PartialFunction, scala.collection.generic.CanBuildFrom);
  Signature: (Lscala/PartialFunction;Lscala/collection/generic/CanBuildFrom;)Ljava/lang/Object;
  Code:
   Stack=3, Locals=3, Args_size=3
	aload_0
	aload_1
	aload_2
	invokestatic	Method scala/collection/TraversableLike$class.partialMap:(Lscala/collection/TraversableLike;Lscala/PartialFunction;Lscala/collection/generic/CanBuildFrom;)Ljava/lang/Object;
	areturn
  Labels:
  LocalVariableTable: 
   Start  Length  Slot  Name   Signature
   0      7      0    this       Lscala/collection/TraversableProxyLikeConfirmation;
   0      7      1    pf       Lscala/PartialFunction;
   0      7      2    bf       Lscala/collection/generic/CanBuildFrom;


public scala.collection.Traversable toCollection(java.lang.Object);
  Signature: (Ljava/lang/Object;)Lscala/collection/Traversable;
  Code:
   Stack=2, Locals=2, Args_size=2
	aload_0
	aload_1
	invokestatic	Method scala/collection/TraversableLike$class.toCollection:(Lscala/collection/TraversableLike;Ljava/lang/Object;)Lscala/collection/Traversable;
	areturn
  Labels:
  LocalVariableTable: 
   Start  Length  Slot  Name   Signature
   0      6      0    this       Lscala/collection/TraversableProxyLikeConfirmation;
   0      6      1    repr       Ljava/lang/Object;


public scala.collection.Traversable thisCollection();
  Signature: ()Lscala/collection/Traversable;
  Code:
   Stack=1, Locals=1, Args_size=1
	aload_0
	invokestatic	Method scala/collection/TraversableLike$class.thisCollection:(Lscala/collection/TraversableLike;)Lscala/collection/Traversable;
	areturn
  Labels:

public java.lang.Object repr();
  Signature: ()Ljava/lang/Object;
  Code:
   Stack=1, Locals=1, Args_size=1
	aload_0
	invokestatic	Method scala/collection/TraversableLike$class.repr:(Lscala/collection/TraversableLike;)Ljava/lang/Object;
	areturn
  Labels:

public java.lang.String toString();
  Signature: ()Ljava/lang/String;
  Code:
   Stack=1, Locals=1, Args_size=1
	aload_0
	invokestatic	Method scala/Proxy$class.toString:(Lscala/Proxy;)Ljava/lang/String;
	areturn
  Labels:

public boolean equals(java.lang.Object);
  Signature: (Ljava/lang/Object;)Z
  Code:
   Stack=2, Locals=2, Args_size=2
	aload_0
	aload_1
	invokestatic	Method scala/Proxy$class.equals:(Lscala/Proxy;Ljava/lang/Object;)Z
	ireturn
  Labels:
  LocalVariableTable: 
   Start  Length  Slot  Name   Signature
   0      6      0    this       Lscala/collection/TraversableProxyLikeConfirmation;
   0      6      1    that       Ljava/lang/Object;


public int hashCode();
  Signature: ()I
  Code:
   Stack=1, Locals=1, Args_size=1
	aload_0
	invokestatic	Method scala/Proxy$class.hashCode:(Lscala/Proxy;)I
	ireturn
  Labels:

public scala.collection.TraversableView view(int, int);
  Signature: (II)Lscala/collection/TraversableView;
  Code:
   Stack=3, Locals=3, Args_size=3
	aload_0
	iload_1
	iload_2
	invokestatic	Method scala/collection/TraversableProxyLike$class.view:(Lscala/collection/TraversableProxyLike;II)Lscala/collection/TraversableView;
	areturn
  Labels:
  LocalVariableTable: 
   Start  Length  Slot  Name   Signature
   0      7      0    this       Lscala/collection/TraversableProxyLikeConfirmation;
   0      7      1    from       I
   0      7      2    until       I


public java.lang.Object view();
  Signature: ()Ljava/lang/Object;
  Code:
   Stack=1, Locals=1, Args_size=1
	aload_0
	invokestatic	Method scala/collection/TraversableProxyLike$class.view:(Lscala/collection/TraversableProxyLike;)Ljava/lang/Object;
	areturn
  Labels:

public java.lang.String stringPrefix();
  Signature: ()Ljava/lang/String;
  Code:
   Stack=1, Locals=1, Args_size=1
	aload_0
	invokestatic	Method scala/collection/TraversableProxyLike$class.stringPrefix:(Lscala/collection/TraversableProxyLike;)Ljava/lang/String;
	areturn
  Labels:

public scala.collection.mutable.StringBuilder addString(scala.collection.mutable.StringBuilder);
  Signature: (Lscala/collection/mutable/StringBuilder;)Lscala/collection/mutable/StringBuilder;
  Code:
   Stack=2, Locals=2, Args_size=2
	aload_0
	aload_1
	invokestatic	Method scala/collection/TraversableProxyLike$class.addString:(Lscala/collection/TraversableProxyLike;Lscala/collection/mutable/StringBuilder;)Lscala/collection/mutable/StringBuilder;
	areturn
  Labels:
  LocalVariableTable: 
   Start  Length  Slot  Name   Signature
   0      6      0    this       Lscala/collection/TraversableProxyLikeConfirmation;
   0      6      1    b       Lscala/collection/mutable/StringBuilder;


public scala.collection.mutable.StringBuilder addString(scala.collection.mutable.StringBuilder, java.lang.String);
  Signature: (Lscala/collection/mutable/StringBuilder;Ljava/lang/String;)Lscala/collection/mutable/StringBuilder;
  Code:
   Stack=3, Locals=3, Args_size=3
	aload_0
	aload_1
	aload_2
	invokestatic	Method scala/collection/TraversableProxyLike$class.addString:(Lscala/collection/TraversableProxyLike;Lscala/collection/mutable/StringBuilder;Ljava/lang/String;)Lscala/collection/mutable/StringBuilder;
	areturn
  Labels:
  LocalVariableTable: 
   Start  Length  Slot  Name   Signature
   0      7      0    this       Lscala/collection/TraversableProxyLikeConfirmation;
   0      7      1    b       Lscala/collection/mutable/StringBuilder;
   0      7      2    sep       Ljava/lang/String;


public scala.collection.mutable.StringBuilder addString(scala.collection.mutable.StringBuilder, java.lang.String, java.lang.String, java.lang.String);
  Signature: (Lscala/collection/mutable/StringBuilder;Ljava/lang/String;Ljava/lang/String;Ljava/lang/String;)Lscala/collection/mutable/StringBuilder;
  Code:
   Stack=5, Locals=5, Args_size=5
	aload_0
	aload_1
	aload_2
	aload_3
	aload	4
	invokestatic	Method scala/collection/TraversableProxyLike$class.addString:(Lscala/collection/TraversableProxyLike;Lscala/collection/mutable/StringBuilder;Ljava/lang/String;Ljava/lang/String;Ljava/lang/String;)Lscala/collection/mutable/StringBuilder;
	areturn
  Labels:
  LocalVariableTable: 
   Start  Length  Slot  Name   Signature
   0      10      0    this       Lscala/collection/TraversableProxyLikeConfirmation;
   0      10      1    b       Lscala/collection/mutable/StringBuilder;
   0      10      2    start       Ljava/lang/String;
   0      10      3    sep       Ljava/lang/String;
   0      10      4    end       Ljava/lang/String;


public java.lang.String mkString();
  Signature: ()Ljava/lang/String;
  Code:
   Stack=1, Locals=1, Args_size=1
	aload_0
	invokestatic	Method scala/collection/TraversableProxyLike$class.mkString:(Lscala/collection/TraversableProxyLike;)Ljava/lang/String;
	areturn
  Labels:

public java.lang.String mkString(java.lang.String);
  Signature: (Ljava/lang/String;)Ljava/lang/String;
  Code:
   Stack=2, Locals=2, Args_size=2
	aload_0
	aload_1
	invokestatic	Method scala/collection/TraversableProxyLike$class.mkString:(Lscala/collection/TraversableProxyLike;Ljava/lang/String;)Ljava/lang/String;
	areturn
  Labels:
  LocalVariableTable: 
   Start  Length  Slot  Name   Signature
   0      6      0    this       Lscala/collection/TraversableProxyLikeConfirmation;
   0      6      1    sep       Ljava/lang/String;


public java.lang.String mkString(java.lang.String, java.lang.String, java.lang.String);
  Signature: (Ljava/lang/String;Ljava/lang/String;Ljava/lang/String;)Ljava/lang/String;
  Code:
   Stack=4, Locals=4, Args_size=4
	aload_0
	aload_1
	aload_2
	aload_3
	invokestatic	Method scala/collection/TraversableProxyLike$class.mkString:(Lscala/collection/TraversableProxyLike;Ljava/lang/String;Ljava/lang/String;Ljava/lang/String;)Ljava/lang/String;
	areturn
  Labels:
  LocalVariableTable: 
   Start  Length  Slot  Name   Signature
   0      8      0    this       Lscala/collection/TraversableProxyLikeConfirmation;
   0      8      1    start       Ljava/lang/String;
   0      8      2    sep       Ljava/lang/String;
   0      8      3    end       Ljava/lang/String;


public scala.collection.immutable.Set toSet();
  Signature: ()Lscala/collection/immutable/Set;
  Code:
   Stack=1, Locals=1, Args_size=1
	aload_0
	invokestatic	Method scala/collection/TraversableProxyLike$class.toSet:(Lscala/collection/TraversableProxyLike;)Lscala/collection/immutable/Set;
	areturn
  Labels:

public scala.collection.immutable.Stream toStream();
  Signature: ()Lscala/collection/immutable/Stream;
  Code:
   Stack=1, Locals=1, Args_size=1
	aload_0
	invokestatic	Method scala/collection/TraversableProxyLike$class.toStream:(Lscala/collection/TraversableProxyLike;)Lscala/collection/immutable/Stream;
	areturn
  Labels:

public scala.collection.Seq toSeq();
  Signature: ()Lscala/collection/Seq;
  Code:
   Stack=1, Locals=1, Args_size=1
	aload_0
	invokestatic	Method scala/collection/TraversableProxyLike$class.toSeq:(Lscala/collection/TraversableProxyLike;)Lscala/collection/Seq;
	areturn
  Labels:

public scala.collection.Iterable toIterable();
  Signature: ()Lscala/collection/Iterable;
  Code:
   Stack=1, Locals=1, Args_size=1
	aload_0
	invokestatic	Method scala/collection/TraversableProxyLike$class.toIterable:(Lscala/collection/TraversableProxyLike;)Lscala/collection/Iterable;
	areturn
  Labels:

public scala.collection.immutable.List toList();
  Signature: ()Lscala/collection/immutable/List;
  Code:
   Stack=1, Locals=1, Args_size=1
	aload_0
	invokestatic	Method scala/collection/TraversableProxyLike$class.toList:(Lscala/collection/TraversableProxyLike;)Lscala/collection/immutable/List;
	areturn
  Labels:

public java.lang.Object toArray(scala.reflect.ClassManifest);
  Signature: (Lscala/reflect/ClassManifest;)Ljava/lang/Object;
  Code:
   Stack=2, Locals=2, Args_size=2
	aload_0
	aload_1
	invokestatic	Method scala/collection/TraversableProxyLike$class.toArray:(Lscala/collection/TraversableProxyLike;Lscala/reflect/ClassManifest;)Ljava/lang/Object;
	areturn
  Labels:
  LocalVariableTable: 
   Start  Length  Slot  Name   Signature
   0      6      0    this       Lscala/collection/TraversableProxyLikeConfirmation;
   0      6      1    evidence$1       Lscala/reflect/ClassManifest;


public void copyToArray(java.lang.Object, int);
  Signature: (Ljava/lang/Object;I)V
  Code:
   Stack=3, Locals=3, Args_size=3
	aload_0
	aload_1
	iload_2
	invokestatic	Method scala/collection/TraversableProxyLike$class.copyToArray:(Lscala/collection/TraversableProxyLike;Ljava/lang/Object;I)V
	return
  Labels:
  LocalVariableTable: 
   Start  Length  Slot  Name   Signature
   0      7      0    this       Lscala/collection/TraversableProxyLikeConfirmation;
   0      7      1    xs       Ljava/lang/Object;
   0      7      2    start       I


public void copyToArray(java.lang.Object, int, int);
  Signature: (Ljava/lang/Object;II)V
  Code:
   Stack=4, Locals=4, Args_size=4
	aload_0
	aload_1
	iload_2
	iload_3
	invokestatic	Method scala/collection/TraversableProxyLike$class.copyToArray:(Lscala/collection/TraversableProxyLike;Ljava/lang/Object;II)V
	return
  Labels:
  LocalVariableTable: 
   Start  Length  Slot  Name   Signature
   0      8      0    this       Lscala/collection/TraversableProxyLikeConfirmation;
   0      8      1    xs       Ljava/lang/Object;
   0      8      2    start       I
   0      8      3    len       I


public void copyToBuffer(scala.collection.mutable.Buffer);
  Signature: (Lscala/collection/mutable/Buffer;)V
  Code:
   Stack=2, Locals=2, Args_size=2
	aload_0
	aload_1
	invokestatic	Method scala/collection/TraversableProxyLike$class.copyToBuffer:(Lscala/collection/TraversableProxyLike;Lscala/collection/mutable/Buffer;)V
	return
  Labels:
  LocalVariableTable: 
   Start  Length  Slot  Name   Signature
   0      6      0    this       Lscala/collection/TraversableProxyLikeConfirmation;
   0      6      1    dest       Lscala/collection/mutable/Buffer;


public scala.Tuple2 splitAt(int);
  Signature: (I)Lscala/Tuple2;
  Code:
   Stack=2, Locals=2, Args_size=2
	aload_0
	iload_1
	invokestatic	Method scala/collection/TraversableProxyLike$class.splitAt:(Lscala/collection/TraversableProxyLike;I)Lscala/Tuple2;
	areturn
  Labels:
  LocalVariableTable: 
   Start  Length  Slot  Name   Signature
   0      6      0    this       Lscala/collection/TraversableProxyLikeConfirmation;
   0      6      1    n       I


public scala.Tuple2 span(scala.Function1);
  Signature: (Lscala/Function1;)Lscala/Tuple2;
  Code:
   Stack=2, Locals=2, Args_size=2
	aload_0
	aload_1
	invokestatic	Method scala/collection/TraversableProxyLike$class.span:(Lscala/collection/TraversableProxyLike;Lscala/Function1;)Lscala/Tuple2;
	areturn
  Labels:
  LocalVariableTable: 
   Start  Length  Slot  Name   Signature
   0      6      0    this       Lscala/collection/TraversableProxyLikeConfirmation;
   0      6      1    p       Lscala/Function1;


public scala.collection.TraversableLike dropWhile(scala.Function1);
  Signature: (Lscala/Function1;)Lscala/collection/TraversableLike;
  Code:
   Stack=2, Locals=2, Args_size=2
	aload_0
	aload_1
	invokestatic	Method scala/collection/TraversableProxyLike$class.dropWhile:(Lscala/collection/TraversableProxyLike;Lscala/Function1;)Lscala/collection/TraversableLike;
	areturn
  Labels:
  LocalVariableTable: 
   Start  Length  Slot  Name   Signature
   0      6      0    this       Lscala/collection/TraversableProxyLikeConfirmation;
   0      6      1    p       Lscala/Function1;


public scala.collection.TraversableLike takeWhile(scala.Function1);
  Signature: (Lscala/Function1;)Lscala/collection/TraversableLike;
  Code:
   Stack=2, Locals=2, Args_size=2
	aload_0
	aload_1
	invokestatic	Method scala/collection/TraversableProxyLike$class.takeWhile:(Lscala/collection/TraversableProxyLike;Lscala/Function1;)Lscala/collection/TraversableLike;
	areturn
  Labels:
  LocalVariableTable: 
   Start  Length  Slot  Name   Signature
   0      6      0    this       Lscala/collection/TraversableProxyLikeConfirmation;
   0      6      1    p       Lscala/Function1;


public scala.collection.TraversableLike slice(int, int);
  Signature: (II)Lscala/collection/TraversableLike;
  Code:
   Stack=3, Locals=3, Args_size=3
	aload_0
	iload_1
	iload_2
	invokestatic	Method scala/collection/TraversableProxyLike$class.slice:(Lscala/collection/TraversableProxyLike;II)Lscala/collection/TraversableLike;
	areturn
  Labels:
  LocalVariableTable: 
   Start  Length  Slot  Name   Signature
   0      7      0    this       Lscala/collection/TraversableProxyLikeConfirmation;
   0      7      1    from       I
   0      7      2    until       I


public scala.collection.TraversableLike drop(int);
  Signature: (I)Lscala/collection/TraversableLike;
  Code:
   Stack=2, Locals=2, Args_size=2
	aload_0
	iload_1
	invokestatic	Method scala/collection/TraversableProxyLike$class.drop:(Lscala/collection/TraversableProxyLike;I)Lscala/collection/TraversableLike;
	areturn
  Labels:
  LocalVariableTable: 
   Start  Length  Slot  Name   Signature
   0      6      0    this       Lscala/collection/TraversableProxyLikeConfirmation;
   0      6      1    n       I


public scala.collection.TraversableLike take(int);
  Signature: (I)Lscala/collection/TraversableLike;
  Code:
   Stack=2, Locals=2, Args_size=2
	aload_0
	iload_1
	invokestatic	Method scala/collection/TraversableProxyLike$class.take:(Lscala/collection/TraversableProxyLike;I)Lscala/collection/TraversableLike;
	areturn
  Labels:
  LocalVariableTable: 
   Start  Length  Slot  Name   Signature
   0      6      0    this       Lscala/collection/TraversableProxyLikeConfirmation;
   0      6      1    n       I


public scala.collection.TraversableLike init();
  Signature: ()Lscala/collection/TraversableLike;
  Code:
   Stack=1, Locals=1, Args_size=1
	aload_0
	invokestatic	Method scala/collection/TraversableProxyLike$class.init:(Lscala/collection/TraversableProxyLike;)Lscala/collection/TraversableLike;
	areturn
  Labels:

public scala.Option lastOption();
  Signature: ()Lscala/Option;
  Code:
   Stack=1, Locals=1, Args_size=1
	aload_0
	invokestatic	Method scala/collection/TraversableProxyLike$class.lastOption:(Lscala/collection/TraversableProxyLike;)Lscala/Option;
	areturn
  Labels:

public java.lang.Object last();
  Signature: ()Ljava/lang/Object;
  Code:
   Stack=1, Locals=1, Args_size=1
	aload_0
	invokestatic	Method scala/collection/TraversableProxyLike$class.last:(Lscala/collection/TraversableProxyLike;)Ljava/lang/Object;
	areturn
  Labels:

public scala.collection.TraversableLike tail();
  Signature: ()Lscala/collection/TraversableLike;
  Code:
   Stack=1, Locals=1, Args_size=1
	aload_0
	invokestatic	Method scala/collection/TraversableProxyLike$class.tail:(Lscala/collection/TraversableProxyLike;)Lscala/collection/TraversableLike;
	areturn
  Labels:

public scala.Option headOption();
  Signature: ()Lscala/Option;
  Code:
   Stack=1, Locals=1, Args_size=1
	aload_0
	invokestatic	Method scala/collection/TraversableProxyLike$class.headOption:(Lscala/collection/TraversableProxyLike;)Lscala/Option;
	areturn
  Labels:

public java.lang.Object head();
  Signature: ()Ljava/lang/Object;
  Code:
   Stack=1, Locals=1, Args_size=1
	aload_0
	invokestatic	Method scala/collection/TraversableProxyLike$class.head:(Lscala/collection/TraversableProxyLike;)Ljava/lang/Object;
	areturn
  Labels:

public scala.Option reduceRightOption(scala.Function2);
  Signature: (Lscala/Function2;)Lscala/Option;
  Code:
   Stack=2, Locals=2, Args_size=2
	aload_0
	aload_1
	invokestatic	Method scala/collection/TraversableProxyLike$class.reduceRightOption:(Lscala/collection/TraversableProxyLike;Lscala/Function2;)Lscala/Option;
	areturn
  Labels:
  LocalVariableTable: 
   Start  Length  Slot  Name   Signature
   0      6      0    this       Lscala/collection/TraversableProxyLikeConfirmation;
   0      6      1    op       Lscala/Function2;


public java.lang.Object reduceRight(scala.Function2);
  Signature: (Lscala/Function2;)Ljava/lang/Object;
  Code:
   Stack=2, Locals=2, Args_size=2
	aload_0
	aload_1
	invokestatic	Method scala/collection/TraversableProxyLike$class.reduceRight:(Lscala/collection/TraversableProxyLike;Lscala/Function2;)Ljava/lang/Object;
	areturn
  Labels:
  LocalVariableTable: 
   Start  Length  Slot  Name   Signature
   0      6      0    this       Lscala/collection/TraversableProxyLikeConfirmation;
   0      6      1    op       Lscala/Function2;


public scala.Option reduceLeftOption(scala.Function2);
  Signature: (Lscala/Function2;)Lscala/Option;
  Code:
   Stack=2, Locals=2, Args_size=2
	aload_0
	aload_1
	invokestatic	Method scala/collection/TraversableProxyLike$class.reduceLeftOption:(Lscala/collection/TraversableProxyLike;Lscala/Function2;)Lscala/Option;
	areturn
  Labels:
  LocalVariableTable: 
   Start  Length  Slot  Name   Signature
   0      6      0    this       Lscala/collection/TraversableProxyLikeConfirmation;
   0      6      1    op       Lscala/Function2;


public java.lang.Object reduceLeft(scala.Function2);
  Signature: (Lscala/Function2;)Ljava/lang/Object;
  Code:
   Stack=2, Locals=2, Args_size=2
	aload_0
	aload_1
	invokestatic	Method scala/collection/TraversableProxyLike$class.reduceLeft:(Lscala/collection/TraversableProxyLike;Lscala/Function2;)Ljava/lang/Object;
	areturn
  Labels:
  LocalVariableTable: 
   Start  Length  Slot  Name   Signature
   0      6      0    this       Lscala/collection/TraversableProxyLikeConfirmation;
   0      6      1    op       Lscala/Function2;


public java.lang.Object $colon$bslash(java.lang.Object, scala.Function2);
  Signature: (Ljava/lang/Object;Lscala/Function2;)Ljava/lang/Object;
  Code:
   Stack=3, Locals=3, Args_size=3
	aload_0
	aload_1
	aload_2
	invokestatic	Method scala/collection/TraversableProxyLike$class.$colon$bslash:(Lscala/collection/TraversableProxyLike;Ljava/lang/Object;Lscala/Function2;)Ljava/lang/Object;
	areturn
  Labels:
  LocalVariableTable: 
   Start  Length  Slot  Name   Signature
   0      7      0    this       Lscala/collection/TraversableProxyLikeConfirmation;
   0      7      1    z       Ljava/lang/Object;
   0      7      2    op       Lscala/Function2;


public java.lang.Object foldRight(java.lang.Object, scala.Function2);
  Signature: (Ljava/lang/Object;Lscala/Function2;)Ljava/lang/Object;
  Code:
   Stack=3, Locals=3, Args_size=3
	aload_0
	aload_1
	aload_2
	invokestatic	Method scala/collection/TraversableProxyLike$class.foldRight:(Lscala/collection/TraversableProxyLike;Ljava/lang/Object;Lscala/Function2;)Ljava/lang/Object;
	areturn
  Labels:
  LocalVariableTable: 
   Start  Length  Slot  Name   Signature
   0      7      0    this       Lscala/collection/TraversableProxyLikeConfirmation;
   0      7      1    z       Ljava/lang/Object;
   0      7      2    op       Lscala/Function2;


public java.lang.Object $div$colon(java.lang.Object, scala.Function2);
  Signature: (Ljava/lang/Object;Lscala/Function2;)Ljava/lang/Object;
  Code:
   Stack=3, Locals=3, Args_size=3
	aload_0
	aload_1
	aload_2
	invokestatic	Method scala/collection/TraversableProxyLike$class.$div$colon:(Lscala/collection/TraversableProxyLike;Ljava/lang/Object;Lscala/Function2;)Ljava/lang/Object;
	areturn
  Labels:
  LocalVariableTable: 
   Start  Length  Slot  Name   Signature
   0      7      0    this       Lscala/collection/TraversableProxyLikeConfirmation;
   0      7      1    z       Ljava/lang/Object;
   0      7      2    op       Lscala/Function2;


public java.lang.Object foldLeft(java.lang.Object, scala.Function2);
  Signature: (Ljava/lang/Object;Lscala/Function2;)Ljava/lang/Object;
  Code:
   Stack=3, Locals=3, Args_size=3
	aload_0
	aload_1
	aload_2
	invokestatic	Method scala/collection/TraversableProxyLike$class.foldLeft:(Lscala/collection/TraversableProxyLike;Ljava/lang/Object;Lscala/Function2;)Ljava/lang/Object;
	areturn
  Labels:
  LocalVariableTable: 
   Start  Length  Slot  Name   Signature
   0      7      0    this       Lscala/collection/TraversableProxyLikeConfirmation;
   0      7      1    z       Ljava/lang/Object;
   0      7      2    op       Lscala/Function2;


public scala.Option find(scala.Function1);
  Signature: (Lscala/Function1;)Lscala/Option;
  Code:
   Stack=2, Locals=2, Args_size=2
	aload_0
	aload_1
	invokestatic	Method scala/collection/TraversableProxyLike$class.find:(Lscala/collection/TraversableProxyLike;Lscala/Function1;)Lscala/Option;
	areturn
  Labels:
  LocalVariableTable: 
   Start  Length  Slot  Name   Signature
   0      6      0    this       Lscala/collection/TraversableProxyLikeConfirmation;
   0      6      1    p       Lscala/Function1;


public int count(scala.Function1);
  Signature: (Lscala/Function1;)I
  Code:
   Stack=2, Locals=2, Args_size=2
	aload_0
	aload_1
	invokestatic	Method scala/collection/TraversableProxyLike$class.count:(Lscala/collection/TraversableProxyLike;Lscala/Function1;)I
	ireturn
  Labels:
  LocalVariableTable: 
   Start  Length  Slot  Name   Signature
   0      6      0    this       Lscala/collection/TraversableProxyLikeConfirmation;
   0      6      1    p       Lscala/Function1;


public boolean exists(scala.Function1);
  Signature: (Lscala/Function1;)Z
  Code:
   Stack=2, Locals=2, Args_size=2
	aload_0
	aload_1
	invokestatic	Method scala/collection/TraversableProxyLike$class.exists:(Lscala/collection/TraversableProxyLike;Lscala/Function1;)Z
	ireturn
  Labels:
  LocalVariableTable: 
   Start  Length  Slot  Name   Signature
   0      6      0    this       Lscala/collection/TraversableProxyLikeConfirmation;
   0      6      1    p       Lscala/Function1;


public boolean forall(scala.Function1);
  Signature: (Lscala/Function1;)Z
  Code:
   Stack=2, Locals=2, Args_size=2
	aload_0
	aload_1
	invokestatic	Method scala/collection/TraversableProxyLike$class.forall:(Lscala/collection/TraversableProxyLike;Lscala/Function1;)Z
	ireturn
  Labels:
  LocalVariableTable: 
   Start  Length  Slot  Name   Signature
   0      6      0    this       Lscala/collection/TraversableProxyLikeConfirmation;
   0      6      1    p       Lscala/Function1;


public scala.collection.Map groupBy(scala.Function1);
  Signature: (Lscala/Function1;)Lscala/collection/Map;
  Code:
   Stack=2, Locals=2, Args_size=2
	aload_0
	aload_1
	invokestatic	Method scala/collection/TraversableProxyLike$class.groupBy:(Lscala/collection/TraversableProxyLike;Lscala/Function1;)Lscala/collection/Map;
	areturn
  Labels:
  LocalVariableTable: 
   Start  Length  Slot  Name   Signature
   0      6      0    this       Lscala/collection/TraversableProxyLikeConfirmation;
   0      6      1    f       Lscala/Function1;


public scala.Tuple2 partition(scala.Function1);
  Signature: (Lscala/Function1;)Lscala/Tuple2;
  Code:
   Stack=2, Locals=2, Args_size=2
	aload_0
	aload_1
	invokestatic	Method scala/collection/TraversableProxyLike$class.partition:(Lscala/collection/TraversableProxyLike;Lscala/Function1;)Lscala/Tuple2;
	areturn
  Labels:
  LocalVariableTable: 
   Start  Length  Slot  Name   Signature
   0      6      0    this       Lscala/collection/TraversableProxyLikeConfirmation;
   0      6      1    p       Lscala/Function1;


public scala.collection.TraversableLike filterNot(scala.Function1);
  Signature: (Lscala/Function1;)Lscala/collection/TraversableLike;
  Code:
   Stack=2, Locals=2, Args_size=2
	aload_0
	aload_1
	invokestatic	Method scala/collection/TraversableProxyLike$class.filterNot:(Lscala/collection/TraversableProxyLike;Lscala/Function1;)Lscala/collection/TraversableLike;
	areturn
  Labels:
  LocalVariableTable: 
   Start  Length  Slot  Name   Signature
   0      6      0    this       Lscala/collection/TraversableProxyLikeConfirmation;
   0      6      1    p       Lscala/Function1;


public scala.collection.TraversableLike filter(scala.Function1);
  Signature: (Lscala/Function1;)Lscala/collection/TraversableLike;
  Code:
   Stack=2, Locals=2, Args_size=2
	aload_0
	aload_1
	invokestatic	Method scala/collection/TraversableProxyLike$class.filter:(Lscala/collection/TraversableProxyLike;Lscala/Function1;)Lscala/collection/TraversableLike;
	areturn
  Labels:
  LocalVariableTable: 
   Start  Length  Slot  Name   Signature
   0      6      0    this       Lscala/collection/TraversableProxyLikeConfirmation;
   0      6      1    p       Lscala/Function1;


public java.lang.Object flatMap(scala.Function1, scala.collection.generic.CanBuildFrom);
  Signature: (Lscala/Function1;Lscala/collection/generic/CanBuildFrom;)Ljava/lang/Object;
  Code:
   Stack=3, Locals=3, Args_size=3
	aload_0
	aload_1
	aload_2
	invokestatic	Method scala/collection/TraversableProxyLike$class.flatMap:(Lscala/collection/TraversableProxyLike;Lscala/Function1;Lscala/collection/generic/CanBuildFrom;)Ljava/lang/Object;
	areturn
  Labels:
  LocalVariableTable: 
   Start  Length  Slot  Name   Signature
   0      7      0    this       Lscala/collection/TraversableProxyLikeConfirmation;
   0      7      1    f       Lscala/Function1;
   0      7      2    bf       Lscala/collection/generic/CanBuildFrom;


public java.lang.Object map(scala.Function1, scala.collection.generic.CanBuildFrom);
  Signature: (Lscala/Function1;Lscala/collection/generic/CanBuildFrom;)Ljava/lang/Object;
  Code:
   Stack=3, Locals=3, Args_size=3
	aload_0
	aload_1
	aload_2
	invokestatic	Method scala/collection/TraversableProxyLike$class.map:(Lscala/collection/TraversableProxyLike;Lscala/Function1;Lscala/collection/generic/CanBuildFrom;)Ljava/lang/Object;
	areturn
  Labels:
  LocalVariableTable: 
   Start  Length  Slot  Name   Signature
   0      7      0    this       Lscala/collection/TraversableProxyLikeConfirmation;
   0      7      1    f       Lscala/Function1;
   0      7      2    bf       Lscala/collection/generic/CanBuildFrom;


public java.lang.Object $plus$plus(scala.collection.Iterator, scala.collection.generic.CanBuildFrom);
  Signature: (Lscala/collection/Iterator;Lscala/collection/generic/CanBuildFrom;)Ljava/lang/Object;
  Code:
   Stack=3, Locals=3, Args_size=3
	aload_0
	aload_1
	aload_2
	invokestatic	Method scala/collection/TraversableProxyLike$class.$plus$plus:(Lscala/collection/TraversableProxyLike;Lscala/collection/Iterator;Lscala/collection/generic/CanBuildFrom;)Ljava/lang/Object;
	areturn
  Labels:
  LocalVariableTable: 
   Start  Length  Slot  Name   Signature
   0      7      0    this       Lscala/collection/TraversableProxyLikeConfirmation;
   0      7      1    that       Lscala/collection/Iterator;
   0      7      2    bf       Lscala/collection/generic/CanBuildFrom;


public java.lang.Object $plus$plus(scala.collection.Traversable, scala.collection.generic.CanBuildFrom);
  Signature: (Lscala/collection/Traversable;Lscala/collection/generic/CanBuildFrom;)Ljava/lang/Object;
  Code:
   Stack=3, Locals=3, Args_size=3
	aload_0
	aload_1
	aload_2
	invokestatic	Method scala/collection/TraversableProxyLike$class.$plus$plus:(Lscala/collection/TraversableProxyLike;Lscala/collection/Traversable;Lscala/collection/generic/CanBuildFrom;)Ljava/lang/Object;
	areturn
  Labels:
  LocalVariableTable: 
   Start  Length  Slot  Name   Signature
   0      7      0    this       Lscala/collection/TraversableProxyLikeConfirmation;
   0      7      1    that       Lscala/collection/Traversable;
   0      7      2    bf       Lscala/collection/generic/CanBuildFrom;


public boolean hasDefiniteSize();
  Signature: ()Z
  Code:
   Stack=1, Locals=1, Args_size=1
	aload_0
	invokestatic	Method scala/collection/TraversableProxyLike$class.hasDefiniteSize:(Lscala/collection/TraversableProxyLike;)Z
	ireturn
  Labels:

public int size();
  Signature: ()I
  Code:
   Stack=1, Locals=1, Args_size=1
	aload_0
	invokestatic	Method scala/collection/TraversableProxyLike$class.size:(Lscala/collection/TraversableProxyLike;)I
	ireturn
  Labels:

public boolean nonEmpty();
  Signature: ()Z
  Code:
   Stack=1, Locals=1, Args_size=1
	aload_0
	invokestatic	Method scala/collection/TraversableProxyLike$class.nonEmpty:(Lscala/collection/TraversableProxyLike;)Z
	ireturn
  Labels:

public boolean isEmpty();
  Signature: ()Z
  Code:
   Stack=1, Locals=1, Args_size=1
	aload_0
	invokestatic	Method scala/collection/TraversableProxyLike$class.isEmpty:(Lscala/collection/TraversableProxyLike;)Z
	ireturn
  Labels:

public void foreach(scala.Function1);
  Signature: (Lscala/Function1;)V
  Code:
   Stack=2, Locals=2, Args_size=2
	aload_0
	aload_1
	invokestatic	Method scala/collection/TraversableProxyLike$class.foreach:(Lscala/collection/TraversableProxyLike;Lscala/Function1;)V
	return
  Labels:
  LocalVariableTable: 
   Start  Length  Slot  Name   Signature
   0      6      0    this       Lscala/collection/TraversableProxyLikeConfirmation;
   0      6      1    f       Lscala/Function1;


}

