Compiled from "TraversableLike.scala"
public final class scala.collection.TraversableLike$$anonfun$drop$1 extends scala.runtime.AbstractFunction1 implements java.io.Serializable
  SourceFile: "TraversableLike.scala"
  Scala: length = 0x
   
  InnerClass: 
   public final $anonfun$drop$1=class scala/collection/TraversableLike$$anonfun$drop$1 of class scala/collection/TraversableLike
  minor version: 0
  major version: 49
  Constant pool:
Asciz	SourceFile;
Asciz	TraversableLike.scala;
Asciz	<clinit>;
Asciz	()V;
Asciz	Code;
Asciz	serialVersionUID;
Asciz	J;
Asciz	scala/collection/TraversableLike$$anonfun$drop$1;
class	scala/collection/TraversableLike$$anonfun$drop$1
NameAndType	serialVersionUID:J
Field	scala/collection/TraversableLike$$anonfun$drop$1.serialVersionUID:J
Asciz	i$2;
Asciz	Lscala/runtime/IntRef;;
Asciz	b$8;
Asciz	Lscala/collection/mutable/Builder;;
Asciz	n$2;
Asciz	I;
Asciz	apply;
Asciz	(Ljava/lang/Object;)V;
Asciz	LineNumberTable;
NameAndType	i$2:Lscala/runtime/IntRef;
Field	scala/collection/TraversableLike$$anonfun$drop$1.i$2:Lscala/runtime/IntRef;
Asciz	scala/runtime/IntRef;
class	scala/runtime/IntRef
Asciz	elem;
NameAndType	elem:I
Field	scala/runtime/IntRef.elem:I
NameAndType	n$2:I
Field	scala/collection/TraversableLike$$anonfun$drop$1.n$2:I
NameAndType	b$8:Lscala/collection/mutable/Builder;
Field	scala/collection/TraversableLike$$anonfun$drop$1.b$8:Lscala/collection/mutable/Builder;
Asciz	scala/collection/mutable/Builder;
class	scala/collection/mutable/Builder
Asciz	$plus$eq;
Asciz	(Ljava/lang/Object;)Lscala/collection/mutable/Builder;;
NameAndType	$plus$eq:(Ljava/lang/Object;)Lscala/collection/mutable/Builder;
InterfaceMethod	scala/collection/mutable/Builder.$plus$eq:(Ljava/lang/Object;)Lscala/collection/mutable/Builder;
Asciz	scala/runtime/BoxedUnit;
class	scala/runtime/BoxedUnit
Asciz	UNIT;
Asciz	Lscala/runtime/BoxedUnit;;
NameAndType	UNIT:Lscala/runtime/BoxedUnit;
Field	scala/runtime/BoxedUnit.UNIT:Lscala/runtime/BoxedUnit;
Asciz	this;
Asciz	Lscala/collection/TraversableLike$$anonfun$drop$1;;
Asciz	x;
Asciz	Ljava/lang/Object;;
Asciz	LocalVariableTable;
Asciz	(TA;)V;
Asciz	Signature;
Asciz	(Ljava/lang/Object;)Ljava/lang/Object;;
NameAndType	apply:(Ljava/lang/Object;)V
Method	scala/collection/TraversableLike$$anonfun$drop$1.apply:(Ljava/lang/Object;)V
Asciz	v1;
Asciz	<init>;
Asciz	(Lscala/collection/TraversableLike;ILscala/collection/mutable/Builder;Lscala/runtime/IntRef;)V;
Asciz	scala/runtime/AbstractFunction1;
class	scala/runtime/AbstractFunction1
NameAndType	"<init>":()V
Method	scala/runtime/AbstractFunction1."<init>":()V
Asciz	$outer;
Asciz	Lscala/collection/TraversableLike;;
Asciz	(Lscala/collection/TraversableLike<TA;TRepr;>;)V;
Asciz	Scala;
Asciz	InnerClasses;
Asciz	scala/collection/TraversableLike;
class	scala/collection/TraversableLike
Asciz	$anonfun$drop$1;
Asciz	java/io/Serializable;
class	java/io/Serializable

{
public static final long serialVersionUID;
  Signature: J

private final scala.runtime.IntRef i$2;
  Signature: Lscala/runtime/IntRef;

private final scala.collection.mutable.Builder b$8;
  Signature: Lscala/collection/mutable/Builder;

private final int n$2;
  Signature: I

public static {};
  Signature: ()V
  Code:
   Stack=2, Locals=0, Args_size=0
	lconst_0
	putstatic	Field serialVersionUID:J
	return
  Labels:

public final void apply(java.lang.Object);
  Signature: (Ljava/lang/Object;)V
  Code:
   Stack=3, Locals=2, Args_size=2
	aload_0
	getfield	Field i$2:Lscala/runtime/IntRef;
	getfield	Field scala/runtime/IntRef.elem:I
	aload_0
	getfield	Field n$2:I
	if_icmplt	l1 // getstatic
	aload_0
	getfield	Field b$8:Lscala/collection/mutable/Builder;
	aload_1
	invokeinterface	InterfaceMethod scala/collection/mutable/Builder.$plus$eq:(Ljava/lang/Object;)Lscala/collection/mutable/Builder;
	goto	l2 // pop
l1	getstatic	Field scala/runtime/BoxedUnit.UNIT:Lscala/runtime/BoxedUnit;
l2	pop
	aload_0
	getfield	Field i$2:Lscala/runtime/IntRef;
	aload_0
	getfield	Field i$2:Lscala/runtime/IntRef;
	getfield	Field scala/runtime/IntRef.elem:I
	iconst_1
	iadd
	putfield	Field scala/runtime/IntRef.elem:I
	return
  Labels:
   	l1 = 27 // getstatic
   	l2 = 30 // pop
  LocalVariableTable: 
   Start  Length  Slot  Name   Signature
   0      48      0    this       Lscala/collection/TraversableLike$$anonfun$drop$1;
   0      48      1    x       Ljava/lang/Object;

  Signature: length = 0x2
   00 31 

public final java.lang.Object apply(java.lang.Object);
  Signature: (Ljava/lang/Object;)Ljava/lang/Object;
  Code:
   Stack=2, Locals=2, Args_size=2
	aload_0
	aload_1
	invokevirtual	Method apply:(Ljava/lang/Object;)V
	getstatic	Field scala/runtime/BoxedUnit.UNIT:Lscala/runtime/BoxedUnit;
	areturn
  Labels:
  LocalVariableTable: 
   Start  Length  Slot  Name   Signature
   0      9      0    this       Lscala/collection/TraversableLike$$anonfun$drop$1;
   0      9      1    v1       Ljava/lang/Object;


public scala.collection.TraversableLike$$anonfun$drop$1(scala.collection.TraversableLike, int, scala.collection.mutable.Builder, scala.runtime.IntRef);
  Signature: (Lscala/collection/TraversableLike;ILscala/collection/mutable/Builder;Lscala/runtime/IntRef;)V
  Code:
   Stack=2, Locals=5, Args_size=5
	aload_0
	iload_2
	putfield	Field n$2:I
	aload_0
	aload_3
	putfield	Field b$8:Lscala/collection/mutable/Builder;
	aload_0
	aload	4
	putfield	Field i$2:Lscala/runtime/IntRef;
	aload_0
	invokespecial	Method scala/runtime/AbstractFunction1."<init>":()V
	return
  Labels:
  LocalVariableTable: 
   Start  Length  Slot  Name   Signature
   0      21      0    this       Lscala/collection/TraversableLike$$anonfun$drop$1;
   0      21      1    $outer       Lscala/collection/TraversableLike;

  Signature: length = 0x2
   00 3F 

}

