Compiled from "Traversable.scala"
public class scala.collection.Traversable$PairTraversableOps extends java.lang.Object implements scala.ScalaObject
  SourceFile: "Traversable.scala"
  Signature: length = 0x2
   00 3D 
  Scala: length = 0x
   
  InnerClass: 
   public #66= #12 of #65; //PairTraversableOps=class scala/collection/Traversable$PairTraversableOps of class scala/collection/Traversable
   public final #67= #33 of #12; //$anonfun$unzip$1=class scala/collection/Traversable$PairTraversableOps$$anonfun$unzip$1 of class scala/collection/Traversable$PairTraversableOps
  minor version: 0
  major version: 49
  Constant pool:
const #1 = Asciz	SourceFile;
const #2 = Asciz	Traversable.scala;
const #3 = Asciz	self;
const #4 = Asciz	Lscala/collection/Traversable;;
const #5 = Asciz	TThis;;
const #6 = Asciz	Signature;
const #7 = Asciz	<init>;
const #8 = Asciz	(Lscala/collection/Traversable;)V;
const #9 = Asciz	Code;
const #10 = Asciz	LineNumberTable;
const #11 = Asciz	scala/collection/Traversable$PairTraversableOps;
const #12 = class	#11;	//  scala/collection/Traversable$PairTraversableOps
const #13 = NameAndType	#3:#4;//  self:Lscala/collection/Traversable;
const #14 = Field	#12.#13;	//  scala/collection/Traversable$PairTraversableOps.self:Lscala/collection/Traversable;
const #15 = Asciz	java/lang/Object;
const #16 = class	#15;	//  java/lang/Object
const #17 = Asciz	()V;
const #18 = NameAndType	#7:#17;//  "<init>":()V
const #19 = Method	#16.#18;	//  java/lang/Object."<init>":()V
const #20 = Asciz	this;
const #21 = Asciz	Lscala/collection/Traversable$PairTraversableOps;;
const #22 = Asciz	LocalVariableTable;
const #23 = Asciz	(TThis;)V;
const #24 = Asciz	unzip;
const #25 = Asciz	(Lscala/collection/generic/BuilderFactory;Lscala/collection/generic/BuilderFactory;)Lscala/Tuple2;;
const #26 = Asciz	scala/collection/generic/BuilderFactory;
const #27 = class	#26;	//  scala/collection/generic/BuilderFactory
const #28 = Asciz	apply;
const #29 = Asciz	(Ljava/lang/Object;)Lscala/collection/generic/Builder;;
const #30 = NameAndType	#28:#29;//  apply:(Ljava/lang/Object;)Lscala/collection/generic/Builder;
const #31 = InterfaceMethod	#27.#30;	//  scala/collection/generic/BuilderFactory.apply:(Ljava/lang/Object;)Lscala/collection/generic/Builder;
const #32 = Asciz	scala/collection/Traversable$PairTraversableOps$$anonfun$unzip$1;
const #33 = class	#32;	//  scala/collection/Traversable$PairTraversableOps$$anonfun$unzip$1
const #34 = Asciz	(Lscala/collection/Traversable$PairTraversableOps;Lscala/collection/generic/Builder;Lscala/collection/generic/Builder;)V;
const #35 = NameAndType	#7:#34;//  "<init>":(Lscala/collection/Traversable$PairTraversableOps;Lscala/collection/generic/Builder;Lscala/collection/generic/Builder;)V
const #36 = Method	#33.#35;	//  scala/collection/Traversable$PairTraversableOps$$anonfun$unzip$1."<init>":(Lscala/collection/Traversable$PairTraversableOps;Lscala/collection/generic/Builder;Lscala/collection/generic/Builder;)V
const #37 = Asciz	scala/collection/generic/TraversableClass;
const #38 = class	#37;	//  scala/collection/generic/TraversableClass
const #39 = Asciz	foreach;
const #40 = Asciz	(Lscala/Function1;)V;
const #41 = NameAndType	#39:#40;//  foreach:(Lscala/Function1;)V
const #42 = InterfaceMethod	#38.#41;	//  scala/collection/generic/TraversableClass.foreach:(Lscala/Function1;)V
const #43 = Asciz	scala/Tuple2;
const #44 = class	#43;	//  scala/Tuple2
const #45 = Asciz	scala/collection/generic/Builder;
const #46 = class	#45;	//  scala/collection/generic/Builder
const #47 = Asciz	result;
const #48 = Asciz	()Ljava/lang/Object;;
const #49 = NameAndType	#47:#48;//  result:()Ljava/lang/Object;
const #50 = InterfaceMethod	#46.#49;	//  scala/collection/generic/Builder.result:()Ljava/lang/Object;
const #51 = Asciz	(Ljava/lang/Object;Ljava/lang/Object;)V;
const #52 = NameAndType	#7:#51;//  "<init>":(Ljava/lang/Object;Ljava/lang/Object;)V
const #53 = Method	#44.#52;	//  scala/Tuple2."<init>":(Ljava/lang/Object;Ljava/lang/Object;)V
const #54 = Asciz	bf1;
const #55 = Asciz	Lscala/collection/generic/BuilderFactory;;
const #56 = Asciz	bf2;
const #57 = Asciz	b1$1;
const #58 = Asciz	Lscala/collection/generic/Builder;;
const #59 = Asciz	b2$1;
const #60 = Asciz	<That1:Ljava/lang/Object;That2:Ljava/lang/Object;>(Lscala/collection/generic/BuilderFactory<TA1;TThat1;TThis;>;Lscala/collection/generic/BuilderFactory<TA2;TThat2;TThis;>;)Lscala/Tuple2<TThat1;TThat2;>;;
const #61 = Asciz	<This::Lscala/collection/Traversable<Lscala/Tuple2<TA1;TA2;>;>;A1:Ljava/lang/Object;A2:Ljava/lang/Object;>Ljava/lang/Object;Lscala/ScalaObject;;
const #62 = Asciz	Scala;
const #63 = Asciz	InnerClasses;
const #64 = Asciz	scala/collection/Traversable;
const #65 = class	#64;	//  scala/collection/Traversable
const #66 = Asciz	PairTraversableOps;
const #67 = Asciz	$anonfun$unzip$1;
const #68 = Asciz	scala/ScalaObject;
const #69 = class	#68;	//  scala/ScalaObject

{
public scala.collection.Traversable$PairTraversableOps(scala.collection.Traversable);
  Code:
   Stack=2, Locals=2, Args_size=2
   0:	aload_0
   1:	aload_1
   2:	putfield	#14; //Field self:Lscala/collection/Traversable;
   5:	aload_0
   6:	invokespecial	#19; //Method java/lang/Object."<init>":()V
   9:	return
  LineNumberTable: 
   line 179: 0

  LocalVariableTable: 
   Start  Length  Slot  Name   Signature
   0      10      0    this       Lscala/collection/Traversable$PairTraversableOps;
   0      10      1    self       Lscala/collection/Traversable;

  Signature: length = 0x2
   00 17 

public scala.Tuple2 unzip(scala.collection.generic.BuilderFactory, scala.collection.generic.BuilderFactory);
  Code:
   Stack=6, Locals=5, Args_size=3
   0:	aload_1
   1:	aload_0
   2:	getfield	#14; //Field self:Lscala/collection/Traversable;
   5:	invokeinterface	#31,  2; //InterfaceMethod scala/collection/generic/BuilderFactory.apply:(Ljava/lang/Object;)Lscala/collection/generic/Builder;
   10:	astore_3
   11:	aload_2
   12:	aload_0
   13:	getfield	#14; //Field self:Lscala/collection/Traversable;
   16:	invokeinterface	#31,  2; //InterfaceMethod scala/collection/generic/BuilderFactory.apply:(Ljava/lang/Object;)Lscala/collection/generic/Builder;
   21:	astore	4
   23:	aload_0
   24:	getfield	#14; //Field self:Lscala/collection/Traversable;
   27:	new	#33; //class scala/collection/Traversable$PairTraversableOps$$anonfun$unzip$1
   30:	dup
   31:	aload_0
   32:	aload_3
   33:	aload	4
   35:	invokespecial	#36; //Method scala/collection/Traversable$PairTraversableOps$$anonfun$unzip$1."<init>":(Lscala/collection/Traversable$PairTraversableOps;Lscala/collection/generic/Builder;Lscala/collection/generic/Builder;)V
   38:	invokeinterface	#42,  2; //InterfaceMethod scala/collection/generic/TraversableClass.foreach:(Lscala/Function1;)V
   43:	new	#44; //class scala/Tuple2
   46:	dup
   47:	aload_3
   48:	invokeinterface	#50,  1; //InterfaceMethod scala/collection/generic/Builder.result:()Ljava/lang/Object;
   53:	aload	4
   55:	invokeinterface	#50,  1; //InterfaceMethod scala/collection/generic/Builder.result:()Ljava/lang/Object;
   60:	invokespecial	#53; //Method scala/Tuple2."<init>":(Ljava/lang/Object;Ljava/lang/Object;)V
   63:	areturn
  LineNumberTable: 
   line 185: 0
   line 186: 11
   line 187: 23
   line 191: 43

  LocalVariableTable: 
   Start  Length  Slot  Name   Signature
   0      64      0    this       Lscala/collection/Traversable$PairTraversableOps;
   0      64      1    bf1       Lscala/collection/generic/BuilderFactory;
   0      64      2    bf2       Lscala/collection/generic/BuilderFactory;
   11      52      3    b1$1       Lscala/collection/generic/Builder;
   23      40      4    b2$1       Lscala/collection/generic/Builder;

  Signature: length = 0x2
   00 3C 

}

