Compiled from "TraversableLike.scala"
public final class scala.collection.TraversableLike$$anonfun$head$1$$anonfun$apply$5$$anonfun$apply$6 extends scala.runtime.AbstractFunction0 implements java.io.Serializable
  SourceFile: "TraversableLike.scala"
  Scala: length = 0x
   
  InnerClass: 
   public final #39= #36 of #38; //$anonfun$apply$5=class scala/collection/TraversableLike$$anonfun$head$1$$anonfun$apply$5 of class scala/collection/TraversableLike$$anonfun$head$1
   public final #40= #9 of #36; //$anonfun$apply$6=class scala/collection/TraversableLike$$anonfun$head$1$$anonfun$apply$5$$anonfun$apply$6 of class scala/collection/TraversableLike$$anonfun$head$1$$anonfun$apply$5
  minor version: 0
  major version: 49
  Constant pool:
const #1 = Asciz	SourceFile;
const #2 = Asciz	TraversableLike.scala;
const #3 = Asciz	<clinit>;
const #4 = Asciz	()V;
const #5 = Asciz	Code;
const #6 = Asciz	serialVersionUID;
const #7 = Asciz	J;
const #8 = Asciz	scala/collection/TraversableLike$$anonfun$head$1$$anonfun$apply$5$$anonfun$apply$6;
const #9 = class	#8;	//  scala/collection/TraversableLike$$anonfun$head$1$$anonfun$apply$5$$anonfun$apply$6
const #10 = NameAndType	#6:#7;//  serialVersionUID:J
const #11 = Field	#9.#10;	//  scala/collection/TraversableLike$$anonfun$head$1$$anonfun$apply$5$$anonfun$apply$6.serialVersionUID:J
const #12 = Asciz	x$5;
const #13 = Asciz	Ljava/lang/Object;;
const #14 = Asciz	<init>;
const #15 = Asciz	(Lscala/collection/TraversableLike$$anonfun$head$1$$anonfun$apply$5;Ljava/lang/Object;)V;
const #16 = Asciz	LineNumberTable;
const #17 = NameAndType	#12:#13;//  x$5:Ljava/lang/Object;
const #18 = Field	#9.#17;	//  scala/collection/TraversableLike$$anonfun$head$1$$anonfun$apply$5$$anonfun$apply$6.x$5:Ljava/lang/Object;
const #19 = Asciz	scala/runtime/AbstractFunction0;
const #20 = class	#19;	//  scala/runtime/AbstractFunction0
const #21 = NameAndType	#14:#4;//  "<init>":()V
const #22 = Method	#20.#21;	//  scala/runtime/AbstractFunction0."<init>":()V
const #23 = Asciz	this;
const #24 = Asciz	Lscala/collection/TraversableLike$$anonfun$head$1$$anonfun$apply$5$$anonfun$apply$6;;
const #25 = Asciz	$outer;
const #26 = Asciz	Lscala/collection/TraversableLike$$anonfun$head$1$$anonfun$apply$5;;
const #27 = Asciz	LocalVariableTable;
const #28 = Asciz	(Lscala/collection/TraversableLike<TA;TRepr;>.$anonfun$head$1.$anonfun$apply$5;)V;
const #29 = Asciz	Signature;
const #30 = Asciz	apply;
const #31 = Asciz	()Ljava/lang/Object;;
const #32 = Asciz	()TA;;
const #33 = Asciz	Scala;
const #34 = Asciz	InnerClasses;
const #35 = Asciz	scala/collection/TraversableLike$$anonfun$head$1$$anonfun$apply$5;
const #36 = class	#35;	//  scala/collection/TraversableLike$$anonfun$head$1$$anonfun$apply$5
const #37 = Asciz	scala/collection/TraversableLike$$anonfun$head$1;
const #38 = class	#37;	//  scala/collection/TraversableLike$$anonfun$head$1
const #39 = Asciz	$anonfun$apply$5;
const #40 = Asciz	$anonfun$apply$6;
const #41 = Asciz	java/io/Serializable;
const #42 = class	#41;	//  java/io/Serializable

{
public static final long serialVersionUID;

public static {};
  Code:
   Stack=2, Locals=0, Args_size=0
   0:	lconst_0
   1:	putstatic	#11; //Field serialVersionUID:J
   4:	return

public scala.collection.TraversableLike$$anonfun$head$1$$anonfun$apply$5$$anonfun$apply$6(scala.collection.TraversableLike$$anonfun$head$1$$anonfun$apply$5, java.lang.Object);
  Code:
   Stack=2, Locals=3, Args_size=3
   0:	aload_0
   1:	aload_2
   2:	putfield	#18; //Field x$5:Ljava/lang/Object;
   5:	aload_0
   6:	invokespecial	#22; //Method scala/runtime/AbstractFunction0."<init>":()V
   9:	return
  LineNumberTable: 
   line 706: 0

  LocalVariableTable: 
   Start  Length  Slot  Name   Signature
   0      10      0    this       Lscala/collection/TraversableLike$$anonfun$head$1$$anonfun$apply$5$$anonfun$apply$6;
   0      10      1    $outer       Lscala/collection/TraversableLike$$anonfun$head$1$$anonfun$apply$5;

  Signature: length = 0x2
   00 1C 

public final java.lang.Object apply();
  Code:
   Stack=1, Locals=1, Args_size=1
   0:	aload_0
   1:	getfield	#18; //Field x$5:Ljava/lang/Object;
   4:	areturn
  LineNumberTable: 
   line 706: 0

  Signature: length = 0x2
   00 20 

}

