Compiled from "TraversableProxyLike.scala"
public abstract class scala.collection.TraversableProxyLike$class extends java.lang.Object
  SourceFile: "TraversableProxyLike.scala"
  Scala: length = 0x
   
  minor version: 0
  major version: 49
  Constant pool:
const #1 = Asciz	SourceFile;
const #2 = Asciz	TraversableProxyLike.scala;
const #3 = Asciz	$init$;
const #4 = Asciz	(Lscala/collection/TraversableProxyLike;)V;
const #5 = Asciz	Code;
const #6 = Asciz	LineNumberTable;
const #7 = Asciz	$this;
const #8 = Asciz	Lscala/collection/TraversableProxyLike;;
const #9 = Asciz	LocalVariableTable;
const #10 = Asciz	view;
const #11 = Asciz	(Lscala/collection/TraversableProxyLike;II)Lscala/collection/TraversableView;;
const #12 = Asciz	scala/collection/TraversableProxyLike;
const #13 = class	#12;	//  scala/collection/TraversableProxyLike
const #14 = Asciz	self;
const #15 = Asciz	()Lscala/collection/TraversableLike;;
const #16 = NameAndType	#14:#15;//  self:()Lscala/collection/TraversableLike;
const #17 = InterfaceMethod	#13.#16;	//  scala/collection/TraversableProxyLike.self:()Lscala/collection/TraversableLike;
const #18 = Asciz	scala/collection/TraversableLike;
const #19 = class	#18;	//  scala/collection/TraversableLike
const #20 = Asciz	(II)Lscala/collection/TraversableView;;
const #21 = NameAndType	#10:#20;//  view:(II)Lscala/collection/TraversableView;
const #22 = InterfaceMethod	#19.#21;	//  scala/collection/TraversableLike.view:(II)Lscala/collection/TraversableView;
const #23 = Asciz	from;
const #24 = Asciz	I;
const #25 = Asciz	until;
const #26 = Asciz	(Lscala/collection/TraversableProxyLike;)Ljava/lang/Object;;
const #27 = Asciz	()Ljava/lang/Object;;
const #28 = NameAndType	#10:#27;//  view:()Ljava/lang/Object;
const #29 = InterfaceMethod	#19.#28;	//  scala/collection/TraversableLike.view:()Ljava/lang/Object;
const #30 = Asciz	stringPrefix;
const #31 = Asciz	(Lscala/collection/TraversableProxyLike;)Ljava/lang/String;;
const #32 = Asciz	()Ljava/lang/String;;
const #33 = NameAndType	#30:#32;//  stringPrefix:()Ljava/lang/String;
const #34 = InterfaceMethod	#19.#33;	//  scala/collection/TraversableLike.stringPrefix:()Ljava/lang/String;
const #35 = Asciz	addString;
const #36 = Asciz	(Lscala/collection/TraversableProxyLike;Lscala/collection/mutable/StringBuilder;)Lscala/collection/mutable/StringBuilder;;
const #37 = Asciz	(Lscala/collection/mutable/StringBuilder;)Lscala/collection/mutable/StringBuilder;;
const #38 = NameAndType	#35:#37;//  addString:(Lscala/collection/mutable/StringBuilder;)Lscala/collection/mutable/StringBuilder;
const #39 = InterfaceMethod	#19.#38;	//  scala/collection/TraversableLike.addString:(Lscala/collection/mutable/StringBuilder;)Lscala/collection/mutable/StringBuilder;
const #40 = Asciz	b;
const #41 = Asciz	Lscala/collection/mutable/StringBuilder;;
const #42 = Asciz	(Lscala/collection/TraversableProxyLike;Lscala/collection/mutable/StringBuilder;Ljava/lang/String;)Lscala/collection/mutable/StringBuilder;;
const #43 = Asciz	(Lscala/collection/mutable/StringBuilder;Ljava/lang/String;)Lscala/collection/mutable/StringBuilder;;
const #44 = NameAndType	#35:#43;//  addString:(Lscala/collection/mutable/StringBuilder;Ljava/lang/String;)Lscala/collection/mutable/StringBuilder;
const #45 = InterfaceMethod	#19.#44;	//  scala/collection/TraversableLike.addString:(Lscala/collection/mutable/StringBuilder;Ljava/lang/String;)Lscala/collection/mutable/StringBuilder;
const #46 = Asciz	sep;
const #47 = Asciz	Ljava/lang/String;;
const #48 = Asciz	(Lscala/collection/TraversableProxyLike;Lscala/collection/mutable/StringBuilder;Ljava/lang/String;Ljava/lang/String;Ljava/lang/String;)Lscala/collection/mutable/StringBuilder;;
const #49 = Asciz	(Lscala/collection/mutable/StringBuilder;Ljava/lang/String;Ljava/lang/String;Ljava/lang/String;)Lscala/collection/mutable/StringBuilder;;
const #50 = NameAndType	#35:#49;//  addString:(Lscala/collection/mutable/StringBuilder;Ljava/lang/String;Ljava/lang/String;Ljava/lang/String;)Lscala/collection/mutable/StringBuilder;
const #51 = InterfaceMethod	#19.#50;	//  scala/collection/TraversableLike.addString:(Lscala/collection/mutable/StringBuilder;Ljava/lang/String;Ljava/lang/String;Ljava/lang/String;)Lscala/collection/mutable/StringBuilder;
const #52 = Asciz	start;
const #53 = Asciz	end;
const #54 = Asciz	mkString;
const #55 = NameAndType	#54:#32;//  mkString:()Ljava/lang/String;
const #56 = InterfaceMethod	#19.#55;	//  scala/collection/TraversableLike.mkString:()Ljava/lang/String;
const #57 = Asciz	(Lscala/collection/TraversableProxyLike;Ljava/lang/String;)Ljava/lang/String;;
const #58 = Asciz	(Ljava/lang/String;)Ljava/lang/String;;
const #59 = NameAndType	#54:#58;//  mkString:(Ljava/lang/String;)Ljava/lang/String;
const #60 = InterfaceMethod	#19.#59;	//  scala/collection/TraversableLike.mkString:(Ljava/lang/String;)Ljava/lang/String;
const #61 = Asciz	(Lscala/collection/TraversableProxyLike;Ljava/lang/String;Ljava/lang/String;Ljava/lang/String;)Ljava/lang/String;;
const #62 = Asciz	(Ljava/lang/String;Ljava/lang/String;Ljava/lang/String;)Ljava/lang/String;;
const #63 = NameAndType	#54:#62;//  mkString:(Ljava/lang/String;Ljava/lang/String;Ljava/lang/String;)Ljava/lang/String;
const #64 = InterfaceMethod	#19.#63;	//  scala/collection/TraversableLike.mkString:(Ljava/lang/String;Ljava/lang/String;Ljava/lang/String;)Ljava/lang/String;
const #65 = Asciz	toSet;
const #66 = Asciz	(Lscala/collection/TraversableProxyLike;)Lscala/collection/immutable/Set;;
const #67 = Asciz	()Lscala/collection/immutable/Set;;
const #68 = NameAndType	#65:#67;//  toSet:()Lscala/collection/immutable/Set;
const #69 = InterfaceMethod	#19.#68;	//  scala/collection/TraversableLike.toSet:()Lscala/collection/immutable/Set;
const #70 = Asciz	toStream;
const #71 = Asciz	(Lscala/collection/TraversableProxyLike;)Lscala/collection/immutable/Stream;;
const #72 = Asciz	()Lscala/collection/immutable/Stream;;
const #73 = NameAndType	#70:#72;//  toStream:()Lscala/collection/immutable/Stream;
const #74 = InterfaceMethod	#19.#73;	//  scala/collection/TraversableLike.toStream:()Lscala/collection/immutable/Stream;
const #75 = Asciz	toSeq;
const #76 = Asciz	(Lscala/collection/TraversableProxyLike;)Lscala/collection/Seq;;
const #77 = Asciz	()Lscala/collection/Seq;;
const #78 = NameAndType	#75:#77;//  toSeq:()Lscala/collection/Seq;
const #79 = InterfaceMethod	#19.#78;	//  scala/collection/TraversableLike.toSeq:()Lscala/collection/Seq;
const #80 = Asciz	toIterable;
const #81 = Asciz	(Lscala/collection/TraversableProxyLike;)Lscala/collection/Iterable;;
const #82 = Asciz	()Lscala/collection/Iterable;;
const #83 = NameAndType	#80:#82;//  toIterable:()Lscala/collection/Iterable;
const #84 = InterfaceMethod	#19.#83;	//  scala/collection/TraversableLike.toIterable:()Lscala/collection/Iterable;
const #85 = Asciz	toList;
const #86 = Asciz	(Lscala/collection/TraversableProxyLike;)Lscala/collection/immutable/List;;
const #87 = Asciz	()Lscala/collection/immutable/List;;
const #88 = NameAndType	#85:#87;//  toList:()Lscala/collection/immutable/List;
const #89 = InterfaceMethod	#19.#88;	//  scala/collection/TraversableLike.toList:()Lscala/collection/immutable/List;
const #90 = Asciz	toArray;
const #91 = Asciz	(Lscala/collection/TraversableProxyLike;Lscala/reflect/ClassManifest;)Ljava/lang/Object;;
const #92 = Asciz	(Lscala/reflect/ClassManifest;)Ljava/lang/Object;;
const #93 = NameAndType	#90:#92;//  toArray:(Lscala/reflect/ClassManifest;)Ljava/lang/Object;
const #94 = InterfaceMethod	#19.#93;	//  scala/collection/TraversableLike.toArray:(Lscala/reflect/ClassManifest;)Ljava/lang/Object;
const #95 = Asciz	evidence$1;
const #96 = Asciz	Lscala/reflect/ClassManifest;;
const #97 = Asciz	copyToArray;
const #98 = Asciz	(Lscala/collection/TraversableProxyLike;Ljava/lang/Object;I)V;
const #99 = Asciz	(Ljava/lang/Object;I)V;
const #100 = NameAndType	#97:#99;//  copyToArray:(Ljava/lang/Object;I)V
const #101 = InterfaceMethod	#19.#100;	//  scala/collection/TraversableLike.copyToArray:(Ljava/lang/Object;I)V
const #102 = Asciz	xs;
const #103 = Asciz	Ljava/lang/Object;;
const #104 = Asciz	(Lscala/collection/TraversableProxyLike;Ljava/lang/Object;II)V;
const #105 = Asciz	(Ljava/lang/Object;II)V;
const #106 = NameAndType	#97:#105;//  copyToArray:(Ljava/lang/Object;II)V
const #107 = InterfaceMethod	#19.#106;	//  scala/collection/TraversableLike.copyToArray:(Ljava/lang/Object;II)V
const #108 = Asciz	len;
const #109 = Asciz	copyToBuffer;
const #110 = Asciz	(Lscala/collection/TraversableProxyLike;Lscala/collection/mutable/Buffer;)V;
const #111 = Asciz	(Lscala/collection/mutable/Buffer;)V;
const #112 = NameAndType	#109:#111;//  copyToBuffer:(Lscala/collection/mutable/Buffer;)V
const #113 = InterfaceMethod	#19.#112;	//  scala/collection/TraversableLike.copyToBuffer:(Lscala/collection/mutable/Buffer;)V
const #114 = Asciz	dest;
const #115 = Asciz	Lscala/collection/mutable/Buffer;;
const #116 = Asciz	splitAt;
const #117 = Asciz	(Lscala/collection/TraversableProxyLike;I)Lscala/Tuple2;;
const #118 = Asciz	(I)Lscala/Tuple2;;
const #119 = NameAndType	#116:#118;//  splitAt:(I)Lscala/Tuple2;
const #120 = InterfaceMethod	#19.#119;	//  scala/collection/TraversableLike.splitAt:(I)Lscala/Tuple2;
const #121 = Asciz	n;
const #122 = Asciz	span;
const #123 = Asciz	(Lscala/collection/TraversableProxyLike;Lscala/Function1;)Lscala/Tuple2;;
const #124 = Asciz	(Lscala/Function1;)Lscala/Tuple2;;
const #125 = NameAndType	#122:#124;//  span:(Lscala/Function1;)Lscala/Tuple2;
const #126 = InterfaceMethod	#19.#125;	//  scala/collection/TraversableLike.span:(Lscala/Function1;)Lscala/Tuple2;
const #127 = Asciz	p;
const #128 = Asciz	Lscala/Function1;;
const #129 = Asciz	dropWhile;
const #130 = Asciz	(Lscala/collection/TraversableProxyLike;Lscala/Function1;)Lscala/collection/TraversableLike;;
const #131 = Asciz	(Lscala/Function1;)Ljava/lang/Object;;
const #132 = NameAndType	#129:#131;//  dropWhile:(Lscala/Function1;)Ljava/lang/Object;
const #133 = InterfaceMethod	#19.#132;	//  scala/collection/TraversableLike.dropWhile:(Lscala/Function1;)Ljava/lang/Object;
const #134 = Asciz	takeWhile;
const #135 = NameAndType	#134:#131;//  takeWhile:(Lscala/Function1;)Ljava/lang/Object;
const #136 = InterfaceMethod	#19.#135;	//  scala/collection/TraversableLike.takeWhile:(Lscala/Function1;)Ljava/lang/Object;
const #137 = Asciz	slice;
const #138 = Asciz	(Lscala/collection/TraversableProxyLike;II)Lscala/collection/TraversableLike;;
const #139 = Asciz	(II)Ljava/lang/Object;;
const #140 = NameAndType	#137:#139;//  slice:(II)Ljava/lang/Object;
const #141 = InterfaceMethod	#19.#140;	//  scala/collection/TraversableLike.slice:(II)Ljava/lang/Object;
const #142 = Asciz	drop;
const #143 = Asciz	(Lscala/collection/TraversableProxyLike;I)Lscala/collection/TraversableLike;;
const #144 = Asciz	(I)Ljava/lang/Object;;
const #145 = NameAndType	#142:#144;//  drop:(I)Ljava/lang/Object;
const #146 = InterfaceMethod	#19.#145;	//  scala/collection/TraversableLike.drop:(I)Ljava/lang/Object;
const #147 = Asciz	take;
const #148 = NameAndType	#147:#144;//  take:(I)Ljava/lang/Object;
const #149 = InterfaceMethod	#19.#148;	//  scala/collection/TraversableLike.take:(I)Ljava/lang/Object;
const #150 = Asciz	init;
const #151 = Asciz	(Lscala/collection/TraversableProxyLike;)Lscala/collection/TraversableLike;;
const #152 = NameAndType	#150:#27;//  init:()Ljava/lang/Object;
const #153 = InterfaceMethod	#19.#152;	//  scala/collection/TraversableLike.init:()Ljava/lang/Object;
const #154 = Asciz	lastOption;
const #155 = Asciz	(Lscala/collection/TraversableProxyLike;)Lscala/Option;;
const #156 = Asciz	()Lscala/Option;;
const #157 = NameAndType	#154:#156;//  lastOption:()Lscala/Option;
const #158 = InterfaceMethod	#19.#157;	//  scala/collection/TraversableLike.lastOption:()Lscala/Option;
const #159 = Asciz	last;
const #160 = NameAndType	#159:#27;//  last:()Ljava/lang/Object;
const #161 = InterfaceMethod	#19.#160;	//  scala/collection/TraversableLike.last:()Ljava/lang/Object;
const #162 = Asciz	tail;
const #163 = NameAndType	#162:#27;//  tail:()Ljava/lang/Object;
const #164 = InterfaceMethod	#19.#163;	//  scala/collection/TraversableLike.tail:()Ljava/lang/Object;
const #165 = Asciz	headOption;
const #166 = NameAndType	#165:#156;//  headOption:()Lscala/Option;
const #167 = InterfaceMethod	#19.#166;	//  scala/collection/TraversableLike.headOption:()Lscala/Option;
const #168 = Asciz	head;
const #169 = NameAndType	#168:#27;//  head:()Ljava/lang/Object;
const #170 = InterfaceMethod	#19.#169;	//  scala/collection/TraversableLike.head:()Ljava/lang/Object;
const #171 = Asciz	reduceRightOption;
const #172 = Asciz	(Lscala/collection/TraversableProxyLike;Lscala/Function2;)Lscala/Option;;
const #173 = Asciz	(Lscala/Function2;)Lscala/Option;;
const #174 = NameAndType	#171:#173;//  reduceRightOption:(Lscala/Function2;)Lscala/Option;
const #175 = InterfaceMethod	#19.#174;	//  scala/collection/TraversableLike.reduceRightOption:(Lscala/Function2;)Lscala/Option;
const #176 = Asciz	op;
const #177 = Asciz	Lscala/Function2;;
const #178 = Asciz	reduceRight;
const #179 = Asciz	(Lscala/collection/TraversableProxyLike;Lscala/Function2;)Ljava/lang/Object;;
const #180 = Asciz	(Lscala/Function2;)Ljava/lang/Object;;
const #181 = NameAndType	#178:#180;//  reduceRight:(Lscala/Function2;)Ljava/lang/Object;
const #182 = InterfaceMethod	#19.#181;	//  scala/collection/TraversableLike.reduceRight:(Lscala/Function2;)Ljava/lang/Object;
const #183 = Asciz	reduceLeftOption;
const #184 = NameAndType	#183:#173;//  reduceLeftOption:(Lscala/Function2;)Lscala/Option;
const #185 = InterfaceMethod	#19.#184;	//  scala/collection/TraversableLike.reduceLeftOption:(Lscala/Function2;)Lscala/Option;
const #186 = Asciz	reduceLeft;
const #187 = NameAndType	#186:#180;//  reduceLeft:(Lscala/Function2;)Ljava/lang/Object;
const #188 = InterfaceMethod	#19.#187;	//  scala/collection/TraversableLike.reduceLeft:(Lscala/Function2;)Ljava/lang/Object;
const #189 = Asciz	$colon$bslash;
const #190 = Asciz	(Lscala/collection/TraversableProxyLike;Ljava/lang/Object;Lscala/Function2;)Ljava/lang/Object;;
const #191 = Asciz	(Ljava/lang/Object;Lscala/Function2;)Ljava/lang/Object;;
const #192 = NameAndType	#189:#191;//  $colon$bslash:(Ljava/lang/Object;Lscala/Function2;)Ljava/lang/Object;
const #193 = InterfaceMethod	#19.#192;	//  scala/collection/TraversableLike.$colon$bslash:(Ljava/lang/Object;Lscala/Function2;)Ljava/lang/Object;
const #194 = Asciz	z;
const #195 = Asciz	foldRight;
const #196 = NameAndType	#195:#191;//  foldRight:(Ljava/lang/Object;Lscala/Function2;)Ljava/lang/Object;
const #197 = InterfaceMethod	#19.#196;	//  scala/collection/TraversableLike.foldRight:(Ljava/lang/Object;Lscala/Function2;)Ljava/lang/Object;
const #198 = Asciz	$div$colon;
const #199 = NameAndType	#198:#191;//  $div$colon:(Ljava/lang/Object;Lscala/Function2;)Ljava/lang/Object;
const #200 = InterfaceMethod	#19.#199;	//  scala/collection/TraversableLike.$div$colon:(Ljava/lang/Object;Lscala/Function2;)Ljava/lang/Object;
const #201 = Asciz	foldLeft;
const #202 = NameAndType	#201:#191;//  foldLeft:(Ljava/lang/Object;Lscala/Function2;)Ljava/lang/Object;
const #203 = InterfaceMethod	#19.#202;	//  scala/collection/TraversableLike.foldLeft:(Ljava/lang/Object;Lscala/Function2;)Ljava/lang/Object;
const #204 = Asciz	find;
const #205 = Asciz	(Lscala/collection/TraversableProxyLike;Lscala/Function1;)Lscala/Option;;
const #206 = Asciz	(Lscala/Function1;)Lscala/Option;;
const #207 = NameAndType	#204:#206;//  find:(Lscala/Function1;)Lscala/Option;
const #208 = InterfaceMethod	#19.#207;	//  scala/collection/TraversableLike.find:(Lscala/Function1;)Lscala/Option;
const #209 = Asciz	count;
const #210 = Asciz	(Lscala/collection/TraversableProxyLike;Lscala/Function1;)I;
const #211 = Asciz	(Lscala/Function1;)I;
const #212 = NameAndType	#209:#211;//  count:(Lscala/Function1;)I
const #213 = InterfaceMethod	#19.#212;	//  scala/collection/TraversableLike.count:(Lscala/Function1;)I
const #214 = Asciz	exists;
const #215 = Asciz	(Lscala/collection/TraversableProxyLike;Lscala/Function1;)Z;
const #216 = Asciz	(Lscala/Function1;)Z;
const #217 = NameAndType	#214:#216;//  exists:(Lscala/Function1;)Z
const #218 = InterfaceMethod	#19.#217;	//  scala/collection/TraversableLike.exists:(Lscala/Function1;)Z
const #219 = Asciz	forall;
const #220 = NameAndType	#219:#216;//  forall:(Lscala/Function1;)Z
const #221 = InterfaceMethod	#19.#220;	//  scala/collection/TraversableLike.forall:(Lscala/Function1;)Z
const #222 = Asciz	groupBy;
const #223 = Asciz	(Lscala/collection/TraversableProxyLike;Lscala/Function1;)Lscala/collection/Map;;
const #224 = Asciz	(Lscala/Function1;)Lscala/collection/Map;;
const #225 = NameAndType	#222:#224;//  groupBy:(Lscala/Function1;)Lscala/collection/Map;
const #226 = InterfaceMethod	#19.#225;	//  scala/collection/TraversableLike.groupBy:(Lscala/Function1;)Lscala/collection/Map;
const #227 = Asciz	f;
const #228 = Asciz	partition;
const #229 = NameAndType	#228:#124;//  partition:(Lscala/Function1;)Lscala/Tuple2;
const #230 = InterfaceMethod	#19.#229;	//  scala/collection/TraversableLike.partition:(Lscala/Function1;)Lscala/Tuple2;
const #231 = Asciz	filterNot;
const #232 = NameAndType	#231:#131;//  filterNot:(Lscala/Function1;)Ljava/lang/Object;
const #233 = InterfaceMethod	#19.#232;	//  scala/collection/TraversableLike.filterNot:(Lscala/Function1;)Ljava/lang/Object;
const #234 = Asciz	filter;
const #235 = NameAndType	#234:#131;//  filter:(Lscala/Function1;)Ljava/lang/Object;
const #236 = InterfaceMethod	#19.#235;	//  scala/collection/TraversableLike.filter:(Lscala/Function1;)Ljava/lang/Object;
const #237 = Asciz	flatMap;
const #238 = Asciz	(Lscala/collection/TraversableProxyLike;Lscala/Function1;Lscala/collection/generic/CanBuildFrom;)Ljava/lang/Object;;
const #239 = Asciz	(Lscala/Function1;Lscala/collection/generic/CanBuildFrom;)Ljava/lang/Object;;
const #240 = NameAndType	#237:#239;//  flatMap:(Lscala/Function1;Lscala/collection/generic/CanBuildFrom;)Ljava/lang/Object;
const #241 = InterfaceMethod	#19.#240;	//  scala/collection/TraversableLike.flatMap:(Lscala/Function1;Lscala/collection/generic/CanBuildFrom;)Ljava/lang/Object;
const #242 = Asciz	bf;
const #243 = Asciz	Lscala/collection/generic/CanBuildFrom;;
const #244 = Asciz	map;
const #245 = NameAndType	#244:#239;//  map:(Lscala/Function1;Lscala/collection/generic/CanBuildFrom;)Ljava/lang/Object;
const #246 = InterfaceMethod	#19.#245;	//  scala/collection/TraversableLike.map:(Lscala/Function1;Lscala/collection/generic/CanBuildFrom;)Ljava/lang/Object;
const #247 = Asciz	$plus$plus;
const #248 = Asciz	(Lscala/collection/TraversableProxyLike;Lscala/collection/Iterator;Lscala/collection/generic/CanBuildFrom;)Ljava/lang/Object;;
const #249 = Asciz	(Lscala/collection/Iterator;Lscala/collection/generic/CanBuildFrom;)Ljava/lang/Object;;
const #250 = NameAndType	#247:#249;//  $plus$plus:(Lscala/collection/Iterator;Lscala/collection/generic/CanBuildFrom;)Ljava/lang/Object;
const #251 = InterfaceMethod	#19.#250;	//  scala/collection/TraversableLike.$plus$plus:(Lscala/collection/Iterator;Lscala/collection/generic/CanBuildFrom;)Ljava/lang/Object;
const #252 = Asciz	that;
const #253 = Asciz	Lscala/collection/Iterator;;
const #254 = Asciz	(Lscala/collection/TraversableProxyLike;Lscala/collection/Traversable;Lscala/collection/generic/CanBuildFrom;)Ljava/lang/Object;;
const #255 = Asciz	(Lscala/collection/Traversable;Lscala/collection/generic/CanBuildFrom;)Ljava/lang/Object;;
const #256 = NameAndType	#247:#255;//  $plus$plus:(Lscala/collection/Traversable;Lscala/collection/generic/CanBuildFrom;)Ljava/lang/Object;
const #257 = InterfaceMethod	#19.#256;	//  scala/collection/TraversableLike.$plus$plus:(Lscala/collection/Traversable;Lscala/collection/generic/CanBuildFrom;)Ljava/lang/Object;
const #258 = Asciz	Lscala/collection/Traversable;;
const #259 = Asciz	hasDefiniteSize;
const #260 = Asciz	(Lscala/collection/TraversableProxyLike;)Z;
const #261 = Asciz	()Z;
const #262 = NameAndType	#259:#261;//  hasDefiniteSize:()Z
const #263 = InterfaceMethod	#19.#262;	//  scala/collection/TraversableLike.hasDefiniteSize:()Z
const #264 = Asciz	size;
const #265 = Asciz	(Lscala/collection/TraversableProxyLike;)I;
const #266 = Asciz	()I;
const #267 = NameAndType	#264:#266;//  size:()I
const #268 = InterfaceMethod	#19.#267;	//  scala/collection/TraversableLike.size:()I
const #269 = Asciz	nonEmpty;
const #270 = NameAndType	#269:#261;//  nonEmpty:()Z
const #271 = InterfaceMethod	#19.#270;	//  scala/collection/TraversableLike.nonEmpty:()Z
const #272 = Asciz	isEmpty;
const #273 = NameAndType	#272:#261;//  isEmpty:()Z
const #274 = InterfaceMethod	#19.#273;	//  scala/collection/TraversableLike.isEmpty:()Z
const #275 = Asciz	foreach;
const #276 = Asciz	(Lscala/collection/TraversableProxyLike;Lscala/Function1;)V;
const #277 = Asciz	scala/collection/generic/GenericTraversableTemplate;
const #278 = class	#277;	//  scala/collection/generic/GenericTraversableTemplate
const #279 = Asciz	(Lscala/Function1;)V;
const #280 = NameAndType	#275:#279;//  foreach:(Lscala/Function1;)V
const #281 = InterfaceMethod	#278.#280;	//  scala/collection/generic/GenericTraversableTemplate.foreach:(Lscala/Function1;)V
const #282 = Asciz	Scala;
const #283 = Asciz	scala/collection/TraversableProxyLike$class;
const #284 = class	#283;	//  scala/collection/TraversableProxyLike$class
const #285 = Asciz	java/lang/Object;
const #286 = class	#285;	//  java/lang/Object

{
public static void $init$(scala.collection.TraversableProxyLike);
  Code:
   Stack=0, Locals=1, Args_size=1
   0:	return
  LineNumberTable: 
   line 27: 0

  LocalVariableTable: 
   Start  Length  Slot  Name   Signature
   0      1      0    $this       Lscala/collection/TraversableProxyLike;


public static scala.collection.TraversableView view(scala.collection.TraversableProxyLike, int, int);
  Code:
   Stack=3, Locals=3, Args_size=3
   0:	aload_0
   1:	invokeinterface	#17,  1; //InterfaceMethod scala/collection/TraversableProxyLike.self:()Lscala/collection/TraversableLike;
   6:	iload_1
   7:	iload_2
   8:	invokeinterface	#22,  3; //InterfaceMethod scala/collection/TraversableLike.view:(II)Lscala/collection/TraversableView;
   13:	areturn
  LineNumberTable: 
   line 85: 0

  LocalVariableTable: 
   Start  Length  Slot  Name   Signature
   0      14      0    $this       Lscala/collection/TraversableProxyLike;
   0      14      1    from       I
   0      14      2    until       I


public static java.lang.Object view(scala.collection.TraversableProxyLike);
  Code:
   Stack=1, Locals=1, Args_size=1
   0:	aload_0
   1:	invokeinterface	#17,  1; //InterfaceMethod scala/collection/TraversableProxyLike.self:()Lscala/collection/TraversableLike;
   6:	invokeinterface	#29,  1; //InterfaceMethod scala/collection/TraversableLike.view:()Ljava/lang/Object;
   11:	areturn
  LineNumberTable: 
   line 84: 0

  LocalVariableTable: 
   Start  Length  Slot  Name   Signature
   0      12      0    $this       Lscala/collection/TraversableProxyLike;


public static java.lang.String stringPrefix(scala.collection.TraversableProxyLike);
  Code:
   Stack=1, Locals=1, Args_size=1
   0:	aload_0
   1:	invokeinterface	#17,  1; //InterfaceMethod scala/collection/TraversableProxyLike.self:()Lscala/collection/TraversableLike;
   6:	invokeinterface	#34,  1; //InterfaceMethod scala/collection/TraversableLike.stringPrefix:()Ljava/lang/String;
   11:	areturn
  LineNumberTable: 
   line 83: 0

  LocalVariableTable: 
   Start  Length  Slot  Name   Signature
   0      12      0    $this       Lscala/collection/TraversableProxyLike;


public static scala.collection.mutable.StringBuilder addString(scala.collection.TraversableProxyLike, scala.collection.mutable.StringBuilder);
  Code:
   Stack=2, Locals=2, Args_size=2
   0:	aload_0
   1:	invokeinterface	#17,  1; //InterfaceMethod scala/collection/TraversableProxyLike.self:()Lscala/collection/TraversableLike;
   6:	aload_1
   7:	invokeinterface	#39,  2; //InterfaceMethod scala/collection/TraversableLike.addString:(Lscala/collection/mutable/StringBuilder;)Lscala/collection/mutable/StringBuilder;
   12:	areturn
  LineNumberTable: 
   line 82: 0

  LocalVariableTable: 
   Start  Length  Slot  Name   Signature
   0      13      0    $this       Lscala/collection/TraversableProxyLike;
   0      13      1    b       Lscala/collection/mutable/StringBuilder;


public static scala.collection.mutable.StringBuilder addString(scala.collection.TraversableProxyLike, scala.collection.mutable.StringBuilder, java.lang.String);
  Code:
   Stack=3, Locals=3, Args_size=3
   0:	aload_0
   1:	invokeinterface	#17,  1; //InterfaceMethod scala/collection/TraversableProxyLike.self:()Lscala/collection/TraversableLike;
   6:	aload_1
   7:	aload_2
   8:	invokeinterface	#45,  3; //InterfaceMethod scala/collection/TraversableLike.addString:(Lscala/collection/mutable/StringBuilder;Ljava/lang/String;)Lscala/collection/mutable/StringBuilder;
   13:	areturn
  LineNumberTable: 
   line 81: 0

  LocalVariableTable: 
   Start  Length  Slot  Name   Signature
   0      14      0    $this       Lscala/collection/TraversableProxyLike;
   0      14      1    b       Lscala/collection/mutable/StringBuilder;
   0      14      2    sep       Ljava/lang/String;


public static scala.collection.mutable.StringBuilder addString(scala.collection.TraversableProxyLike, scala.collection.mutable.StringBuilder, java.lang.String, java.lang.String, java.lang.String);
  Code:
   Stack=5, Locals=5, Args_size=5
   0:	aload_0
   1:	invokeinterface	#17,  1; //InterfaceMethod scala/collection/TraversableProxyLike.self:()Lscala/collection/TraversableLike;
   6:	aload_1
   7:	aload_2
   8:	aload_3
   9:	aload	4
   11:	invokeinterface	#51,  5; //InterfaceMethod scala/collection/TraversableLike.addString:(Lscala/collection/mutable/StringBuilder;Ljava/lang/String;Ljava/lang/String;Ljava/lang/String;)Lscala/collection/mutable/StringBuilder;
   16:	areturn
  LineNumberTable: 
   line 80: 0

  LocalVariableTable: 
   Start  Length  Slot  Name   Signature
   0      17      0    $this       Lscala/collection/TraversableProxyLike;
   0      17      1    b       Lscala/collection/mutable/StringBuilder;
   0      17      2    start       Ljava/lang/String;
   0      17      3    sep       Ljava/lang/String;
   0      17      4    end       Ljava/lang/String;


public static java.lang.String mkString(scala.collection.TraversableProxyLike);
  Code:
   Stack=1, Locals=1, Args_size=1
   0:	aload_0
   1:	invokeinterface	#17,  1; //InterfaceMethod scala/collection/TraversableProxyLike.self:()Lscala/collection/TraversableLike;
   6:	invokeinterface	#56,  1; //InterfaceMethod scala/collection/TraversableLike.mkString:()Ljava/lang/String;
   11:	areturn
  LineNumberTable: 
   line 79: 0

  LocalVariableTable: 
   Start  Length  Slot  Name   Signature
   0      12      0    $this       Lscala/collection/TraversableProxyLike;


public static java.lang.String mkString(scala.collection.TraversableProxyLike, java.lang.String);
  Code:
   Stack=2, Locals=2, Args_size=2
   0:	aload_0
   1:	invokeinterface	#17,  1; //InterfaceMethod scala/collection/TraversableProxyLike.self:()Lscala/collection/TraversableLike;
   6:	aload_1
   7:	invokeinterface	#60,  2; //InterfaceMethod scala/collection/TraversableLike.mkString:(Ljava/lang/String;)Ljava/lang/String;
   12:	areturn
  LineNumberTable: 
   line 78: 0

  LocalVariableTable: 
   Start  Length  Slot  Name   Signature
   0      13      0    $this       Lscala/collection/TraversableProxyLike;
   0      13      1    sep       Ljava/lang/String;


public static java.lang.String mkString(scala.collection.TraversableProxyLike, java.lang.String, java.lang.String, java.lang.String);
  Code:
   Stack=4, Locals=4, Args_size=4
   0:	aload_0
   1:	invokeinterface	#17,  1; //InterfaceMethod scala/collection/TraversableProxyLike.self:()Lscala/collection/TraversableLike;
   6:	aload_1
   7:	aload_2
   8:	aload_3
   9:	invokeinterface	#64,  4; //InterfaceMethod scala/collection/TraversableLike.mkString:(Ljava/lang/String;Ljava/lang/String;Ljava/lang/String;)Ljava/lang/String;
   14:	areturn
  LineNumberTable: 
   line 77: 0

  LocalVariableTable: 
   Start  Length  Slot  Name   Signature
   0      15      0    $this       Lscala/collection/TraversableProxyLike;
   0      15      1    start       Ljava/lang/String;
   0      15      2    sep       Ljava/lang/String;
   0      15      3    end       Ljava/lang/String;


public static scala.collection.immutable.Set toSet(scala.collection.TraversableProxyLike);
  Code:
   Stack=1, Locals=1, Args_size=1
   0:	aload_0
   1:	invokeinterface	#17,  1; //InterfaceMethod scala/collection/TraversableProxyLike.self:()Lscala/collection/TraversableLike;
   6:	invokeinterface	#69,  1; //InterfaceMethod scala/collection/TraversableLike.toSet:()Lscala/collection/immutable/Set;
   11:	areturn
  LineNumberTable: 
   line 76: 0

  LocalVariableTable: 
   Start  Length  Slot  Name   Signature
   0      12      0    $this       Lscala/collection/TraversableProxyLike;


public static scala.collection.immutable.Stream toStream(scala.collection.TraversableProxyLike);
  Code:
   Stack=1, Locals=1, Args_size=1
   0:	aload_0
   1:	invokeinterface	#17,  1; //InterfaceMethod scala/collection/TraversableProxyLike.self:()Lscala/collection/TraversableLike;
   6:	invokeinterface	#74,  1; //InterfaceMethod scala/collection/TraversableLike.toStream:()Lscala/collection/immutable/Stream;
   11:	areturn
  LineNumberTable: 
   line 75: 0

  LocalVariableTable: 
   Start  Length  Slot  Name   Signature
   0      12      0    $this       Lscala/collection/TraversableProxyLike;


public static scala.collection.Seq toSeq(scala.collection.TraversableProxyLike);
  Code:
   Stack=1, Locals=1, Args_size=1
   0:	aload_0
   1:	invokeinterface	#17,  1; //InterfaceMethod scala/collection/TraversableProxyLike.self:()Lscala/collection/TraversableLike;
   6:	invokeinterface	#79,  1; //InterfaceMethod scala/collection/TraversableLike.toSeq:()Lscala/collection/Seq;
   11:	areturn
  LineNumberTable: 
   line 74: 0

  LocalVariableTable: 
   Start  Length  Slot  Name   Signature
   0      12      0    $this       Lscala/collection/TraversableProxyLike;


public static scala.collection.Iterable toIterable(scala.collection.TraversableProxyLike);
  Code:
   Stack=1, Locals=1, Args_size=1
   0:	aload_0
   1:	invokeinterface	#17,  1; //InterfaceMethod scala/collection/TraversableProxyLike.self:()Lscala/collection/TraversableLike;
   6:	invokeinterface	#84,  1; //InterfaceMethod scala/collection/TraversableLike.toIterable:()Lscala/collection/Iterable;
   11:	areturn
  LineNumberTable: 
   line 73: 0

  LocalVariableTable: 
   Start  Length  Slot  Name   Signature
   0      12      0    $this       Lscala/collection/TraversableProxyLike;


public static scala.collection.immutable.List toList(scala.collection.TraversableProxyLike);
  Code:
   Stack=1, Locals=1, Args_size=1
   0:	aload_0
   1:	invokeinterface	#17,  1; //InterfaceMethod scala/collection/TraversableProxyLike.self:()Lscala/collection/TraversableLike;
   6:	invokeinterface	#89,  1; //InterfaceMethod scala/collection/TraversableLike.toList:()Lscala/collection/immutable/List;
   11:	areturn
  LineNumberTable: 
   line 72: 0

  LocalVariableTable: 
   Start  Length  Slot  Name   Signature
   0      12      0    $this       Lscala/collection/TraversableProxyLike;


public static java.lang.Object toArray(scala.collection.TraversableProxyLike, scala.reflect.ClassManifest);
  Code:
   Stack=2, Locals=2, Args_size=2
   0:	aload_0
   1:	invokeinterface	#17,  1; //InterfaceMethod scala/collection/TraversableProxyLike.self:()Lscala/collection/TraversableLike;
   6:	aload_1
   7:	invokeinterface	#94,  2; //InterfaceMethod scala/collection/TraversableLike.toArray:(Lscala/reflect/ClassManifest;)Ljava/lang/Object;
   12:	areturn
  LineNumberTable: 
   line 71: 0

  LocalVariableTable: 
   Start  Length  Slot  Name   Signature
   0      13      0    $this       Lscala/collection/TraversableProxyLike;
   0      13      1    evidence$1       Lscala/reflect/ClassManifest;


public static void copyToArray(scala.collection.TraversableProxyLike, java.lang.Object, int);
  Code:
   Stack=3, Locals=3, Args_size=3
   0:	aload_0
   1:	invokeinterface	#17,  1; //InterfaceMethod scala/collection/TraversableProxyLike.self:()Lscala/collection/TraversableLike;
   6:	aload_1
   7:	iload_2
   8:	invokeinterface	#101,  3; //InterfaceMethod scala/collection/TraversableLike.copyToArray:(Ljava/lang/Object;I)V
   13:	return
  LineNumberTable: 
   line 70: 0

  LocalVariableTable: 
   Start  Length  Slot  Name   Signature
   0      14      0    $this       Lscala/collection/TraversableProxyLike;
   0      14      1    xs       Ljava/lang/Object;
   0      14      2    start       I


public static void copyToArray(scala.collection.TraversableProxyLike, java.lang.Object, int, int);
  Code:
   Stack=4, Locals=4, Args_size=4
   0:	aload_0
   1:	invokeinterface	#17,  1; //InterfaceMethod scala/collection/TraversableProxyLike.self:()Lscala/collection/TraversableLike;
   6:	aload_1
   7:	iload_2
   8:	iload_3
   9:	invokeinterface	#107,  4; //InterfaceMethod scala/collection/TraversableLike.copyToArray:(Ljava/lang/Object;II)V
   14:	return
  LineNumberTable: 
   line 69: 0

  LocalVariableTable: 
   Start  Length  Slot  Name   Signature
   0      15      0    $this       Lscala/collection/TraversableProxyLike;
   0      15      1    xs       Ljava/lang/Object;
   0      15      2    start       I
   0      15      3    len       I


public static void copyToBuffer(scala.collection.TraversableProxyLike, scala.collection.mutable.Buffer);
  Code:
   Stack=2, Locals=2, Args_size=2
   0:	aload_0
   1:	invokeinterface	#17,  1; //InterfaceMethod scala/collection/TraversableProxyLike.self:()Lscala/collection/TraversableLike;
   6:	aload_1
   7:	invokeinterface	#113,  2; //InterfaceMethod scala/collection/TraversableLike.copyToBuffer:(Lscala/collection/mutable/Buffer;)V
   12:	return
  LineNumberTable: 
   line 68: 0

  LocalVariableTable: 
   Start  Length  Slot  Name   Signature
   0      13      0    $this       Lscala/collection/TraversableProxyLike;
   0      13      1    dest       Lscala/collection/mutable/Buffer;


public static scala.Tuple2 splitAt(scala.collection.TraversableProxyLike, int);
  Code:
   Stack=2, Locals=2, Args_size=2
   0:	aload_0
   1:	invokeinterface	#17,  1; //InterfaceMethod scala/collection/TraversableProxyLike.self:()Lscala/collection/TraversableLike;
   6:	iload_1
   7:	invokeinterface	#120,  2; //InterfaceMethod scala/collection/TraversableLike.splitAt:(I)Lscala/Tuple2;
   12:	areturn
  LineNumberTable: 
   line 67: 0

  LocalVariableTable: 
   Start  Length  Slot  Name   Signature
   0      13      0    $this       Lscala/collection/TraversableProxyLike;
   0      13      1    n       I


public static scala.Tuple2 span(scala.collection.TraversableProxyLike, scala.Function1);
  Code:
   Stack=2, Locals=2, Args_size=2
   0:	aload_0
   1:	invokeinterface	#17,  1; //InterfaceMethod scala/collection/TraversableProxyLike.self:()Lscala/collection/TraversableLike;
   6:	aload_1
   7:	invokeinterface	#126,  2; //InterfaceMethod scala/collection/TraversableLike.span:(Lscala/Function1;)Lscala/Tuple2;
   12:	areturn
  LineNumberTable: 
   line 66: 0

  LocalVariableTable: 
   Start  Length  Slot  Name   Signature
   0      13      0    $this       Lscala/collection/TraversableProxyLike;
   0      13      1    p       Lscala/Function1;


public static scala.collection.TraversableLike dropWhile(scala.collection.TraversableProxyLike, scala.Function1);
  Code:
   Stack=2, Locals=2, Args_size=2
   0:	aload_0
   1:	invokeinterface	#17,  1; //InterfaceMethod scala/collection/TraversableProxyLike.self:()Lscala/collection/TraversableLike;
   6:	aload_1
   7:	invokeinterface	#133,  2; //InterfaceMethod scala/collection/TraversableLike.dropWhile:(Lscala/Function1;)Ljava/lang/Object;
   12:	checkcast	#19; //class scala/collection/TraversableLike
   15:	areturn
  LineNumberTable: 
   line 65: 0

  LocalVariableTable: 
   Start  Length  Slot  Name   Signature
   0      16      0    $this       Lscala/collection/TraversableProxyLike;
   0      16      1    p       Lscala/Function1;


public static scala.collection.TraversableLike takeWhile(scala.collection.TraversableProxyLike, scala.Function1);
  Code:
   Stack=2, Locals=2, Args_size=2
   0:	aload_0
   1:	invokeinterface	#17,  1; //InterfaceMethod scala/collection/TraversableProxyLike.self:()Lscala/collection/TraversableLike;
   6:	aload_1
   7:	invokeinterface	#136,  2; //InterfaceMethod scala/collection/TraversableLike.takeWhile:(Lscala/Function1;)Ljava/lang/Object;
   12:	checkcast	#19; //class scala/collection/TraversableLike
   15:	areturn
  LineNumberTable: 
   line 64: 0

  LocalVariableTable: 
   Start  Length  Slot  Name   Signature
   0      16      0    $this       Lscala/collection/TraversableProxyLike;
   0      16      1    p       Lscala/Function1;


public static scala.collection.TraversableLike slice(scala.collection.TraversableProxyLike, int, int);
  Code:
   Stack=3, Locals=3, Args_size=3
   0:	aload_0
   1:	invokeinterface	#17,  1; //InterfaceMethod scala/collection/TraversableProxyLike.self:()Lscala/collection/TraversableLike;
   6:	iload_1
   7:	iload_2
   8:	invokeinterface	#141,  3; //InterfaceMethod scala/collection/TraversableLike.slice:(II)Ljava/lang/Object;
   13:	checkcast	#19; //class scala/collection/TraversableLike
   16:	areturn
  LineNumberTable: 
   line 63: 0

  LocalVariableTable: 
   Start  Length  Slot  Name   Signature
   0      17      0    $this       Lscala/collection/TraversableProxyLike;
   0      17      1    from       I
   0      17      2    until       I


public static scala.collection.TraversableLike drop(scala.collection.TraversableProxyLike, int);
  Code:
   Stack=2, Locals=2, Args_size=2
   0:	aload_0
   1:	invokeinterface	#17,  1; //InterfaceMethod scala/collection/TraversableProxyLike.self:()Lscala/collection/TraversableLike;
   6:	iload_1
   7:	invokeinterface	#146,  2; //InterfaceMethod scala/collection/TraversableLike.drop:(I)Ljava/lang/Object;
   12:	checkcast	#19; //class scala/collection/TraversableLike
   15:	areturn
  LineNumberTable: 
   line 62: 0

  LocalVariableTable: 
   Start  Length  Slot  Name   Signature
   0      16      0    $this       Lscala/collection/TraversableProxyLike;
   0      16      1    n       I


public static scala.collection.TraversableLike take(scala.collection.TraversableProxyLike, int);
  Code:
   Stack=2, Locals=2, Args_size=2
   0:	aload_0
   1:	invokeinterface	#17,  1; //InterfaceMethod scala/collection/TraversableProxyLike.self:()Lscala/collection/TraversableLike;
   6:	iload_1
   7:	invokeinterface	#149,  2; //InterfaceMethod scala/collection/TraversableLike.take:(I)Ljava/lang/Object;
   12:	checkcast	#19; //class scala/collection/TraversableLike
   15:	areturn
  LineNumberTable: 
   line 61: 0

  LocalVariableTable: 
   Start  Length  Slot  Name   Signature
   0      16      0    $this       Lscala/collection/TraversableProxyLike;
   0      16      1    n       I


public static scala.collection.TraversableLike init(scala.collection.TraversableProxyLike);
  Code:
   Stack=1, Locals=1, Args_size=1
   0:	aload_0
   1:	invokeinterface	#17,  1; //InterfaceMethod scala/collection/TraversableProxyLike.self:()Lscala/collection/TraversableLike;
   6:	invokeinterface	#153,  1; //InterfaceMethod scala/collection/TraversableLike.init:()Ljava/lang/Object;
   11:	checkcast	#19; //class scala/collection/TraversableLike
   14:	areturn
  LineNumberTable: 
   line 60: 0

  LocalVariableTable: 
   Start  Length  Slot  Name   Signature
   0      15      0    $this       Lscala/collection/TraversableProxyLike;


public static scala.Option lastOption(scala.collection.TraversableProxyLike);
  Code:
   Stack=1, Locals=1, Args_size=1
   0:	aload_0
   1:	invokeinterface	#17,  1; //InterfaceMethod scala/collection/TraversableProxyLike.self:()Lscala/collection/TraversableLike;
   6:	invokeinterface	#158,  1; //InterfaceMethod scala/collection/TraversableLike.lastOption:()Lscala/Option;
   11:	areturn
  LineNumberTable: 
   line 59: 0

  LocalVariableTable: 
   Start  Length  Slot  Name   Signature
   0      12      0    $this       Lscala/collection/TraversableProxyLike;


public static java.lang.Object last(scala.collection.TraversableProxyLike);
  Code:
   Stack=1, Locals=1, Args_size=1
   0:	aload_0
   1:	invokeinterface	#17,  1; //InterfaceMethod scala/collection/TraversableProxyLike.self:()Lscala/collection/TraversableLike;
   6:	invokeinterface	#161,  1; //InterfaceMethod scala/collection/TraversableLike.last:()Ljava/lang/Object;
   11:	areturn
  LineNumberTable: 
   line 58: 0

  LocalVariableTable: 
   Start  Length  Slot  Name   Signature
   0      12      0    $this       Lscala/collection/TraversableProxyLike;


public static scala.collection.TraversableLike tail(scala.collection.TraversableProxyLike);
  Code:
   Stack=1, Locals=1, Args_size=1
   0:	aload_0
   1:	invokeinterface	#17,  1; //InterfaceMethod scala/collection/TraversableProxyLike.self:()Lscala/collection/TraversableLike;
   6:	invokeinterface	#164,  1; //InterfaceMethod scala/collection/TraversableLike.tail:()Ljava/lang/Object;
   11:	checkcast	#19; //class scala/collection/TraversableLike
   14:	areturn
  LineNumberTable: 
   line 57: 0

  LocalVariableTable: 
   Start  Length  Slot  Name   Signature
   0      15      0    $this       Lscala/collection/TraversableProxyLike;


public static scala.Option headOption(scala.collection.TraversableProxyLike);
  Code:
   Stack=1, Locals=1, Args_size=1
   0:	aload_0
   1:	invokeinterface	#17,  1; //InterfaceMethod scala/collection/TraversableProxyLike.self:()Lscala/collection/TraversableLike;
   6:	invokeinterface	#167,  1; //InterfaceMethod scala/collection/TraversableLike.headOption:()Lscala/Option;
   11:	areturn
  LineNumberTable: 
   line 56: 0

  LocalVariableTable: 
   Start  Length  Slot  Name   Signature
   0      12      0    $this       Lscala/collection/TraversableProxyLike;


public static java.lang.Object head(scala.collection.TraversableProxyLike);
  Code:
   Stack=1, Locals=1, Args_size=1
   0:	aload_0
   1:	invokeinterface	#17,  1; //InterfaceMethod scala/collection/TraversableProxyLike.self:()Lscala/collection/TraversableLike;
   6:	invokeinterface	#170,  1; //InterfaceMethod scala/collection/TraversableLike.head:()Ljava/lang/Object;
   11:	areturn
  LineNumberTable: 
   line 55: 0

  LocalVariableTable: 
   Start  Length  Slot  Name   Signature
   0      12      0    $this       Lscala/collection/TraversableProxyLike;


public static scala.Option reduceRightOption(scala.collection.TraversableProxyLike, scala.Function2);
  Code:
   Stack=2, Locals=2, Args_size=2
   0:	aload_0
   1:	invokeinterface	#17,  1; //InterfaceMethod scala/collection/TraversableProxyLike.self:()Lscala/collection/TraversableLike;
   6:	aload_1
   7:	invokeinterface	#175,  2; //InterfaceMethod scala/collection/TraversableLike.reduceRightOption:(Lscala/Function2;)Lscala/Option;
   12:	areturn
  LineNumberTable: 
   line 54: 0

  LocalVariableTable: 
   Start  Length  Slot  Name   Signature
   0      13      0    $this       Lscala/collection/TraversableProxyLike;
   0      13      1    op       Lscala/Function2;


public static java.lang.Object reduceRight(scala.collection.TraversableProxyLike, scala.Function2);
  Code:
   Stack=2, Locals=2, Args_size=2
   0:	aload_0
   1:	invokeinterface	#17,  1; //InterfaceMethod scala/collection/TraversableProxyLike.self:()Lscala/collection/TraversableLike;
   6:	aload_1
   7:	invokeinterface	#182,  2; //InterfaceMethod scala/collection/TraversableLike.reduceRight:(Lscala/Function2;)Ljava/lang/Object;
   12:	areturn
  LineNumberTable: 
   line 53: 0

  LocalVariableTable: 
   Start  Length  Slot  Name   Signature
   0      13      0    $this       Lscala/collection/TraversableProxyLike;
   0      13      1    op       Lscala/Function2;


public static scala.Option reduceLeftOption(scala.collection.TraversableProxyLike, scala.Function2);
  Code:
   Stack=2, Locals=2, Args_size=2
   0:	aload_0
   1:	invokeinterface	#17,  1; //InterfaceMethod scala/collection/TraversableProxyLike.self:()Lscala/collection/TraversableLike;
   6:	aload_1
   7:	invokeinterface	#185,  2; //InterfaceMethod scala/collection/TraversableLike.reduceLeftOption:(Lscala/Function2;)Lscala/Option;
   12:	areturn
  LineNumberTable: 
   line 52: 0

  LocalVariableTable: 
   Start  Length  Slot  Name   Signature
   0      13      0    $this       Lscala/collection/TraversableProxyLike;
   0      13      1    op       Lscala/Function2;


public static java.lang.Object reduceLeft(scala.collection.TraversableProxyLike, scala.Function2);
  Code:
   Stack=2, Locals=2, Args_size=2
   0:	aload_0
   1:	invokeinterface	#17,  1; //InterfaceMethod scala/collection/TraversableProxyLike.self:()Lscala/collection/TraversableLike;
   6:	aload_1
   7:	invokeinterface	#188,  2; //InterfaceMethod scala/collection/TraversableLike.reduceLeft:(Lscala/Function2;)Ljava/lang/Object;
   12:	areturn
  LineNumberTable: 
   line 51: 0

  LocalVariableTable: 
   Start  Length  Slot  Name   Signature
   0      13      0    $this       Lscala/collection/TraversableProxyLike;
   0      13      1    op       Lscala/Function2;


public static java.lang.Object $colon$bslash(scala.collection.TraversableProxyLike, java.lang.Object, scala.Function2);
  Code:
   Stack=3, Locals=3, Args_size=3
   0:	aload_0
   1:	invokeinterface	#17,  1; //InterfaceMethod scala/collection/TraversableProxyLike.self:()Lscala/collection/TraversableLike;
   6:	aload_1
   7:	aload_2
   8:	invokeinterface	#193,  3; //InterfaceMethod scala/collection/TraversableLike.$colon$bslash:(Ljava/lang/Object;Lscala/Function2;)Ljava/lang/Object;
   13:	areturn
  LineNumberTable: 
   line 50: 0

  LocalVariableTable: 
   Start  Length  Slot  Name   Signature
   0      14      0    $this       Lscala/collection/TraversableProxyLike;
   0      14      1    z       Ljava/lang/Object;
   0      14      2    op       Lscala/Function2;


public static java.lang.Object foldRight(scala.collection.TraversableProxyLike, java.lang.Object, scala.Function2);
  Code:
   Stack=3, Locals=3, Args_size=3
   0:	aload_0
   1:	invokeinterface	#17,  1; //InterfaceMethod scala/collection/TraversableProxyLike.self:()Lscala/collection/TraversableLike;
   6:	aload_1
   7:	aload_2
   8:	invokeinterface	#197,  3; //InterfaceMethod scala/collection/TraversableLike.foldRight:(Ljava/lang/Object;Lscala/Function2;)Ljava/lang/Object;
   13:	areturn
  LineNumberTable: 
   line 49: 0

  LocalVariableTable: 
   Start  Length  Slot  Name   Signature
   0      14      0    $this       Lscala/collection/TraversableProxyLike;
   0      14      1    z       Ljava/lang/Object;
   0      14      2    op       Lscala/Function2;


public static java.lang.Object $div$colon(scala.collection.TraversableProxyLike, java.lang.Object, scala.Function2);
  Code:
   Stack=3, Locals=3, Args_size=3
   0:	aload_0
   1:	invokeinterface	#17,  1; //InterfaceMethod scala/collection/TraversableProxyLike.self:()Lscala/collection/TraversableLike;
   6:	aload_1
   7:	aload_2
   8:	invokeinterface	#200,  3; //InterfaceMethod scala/collection/TraversableLike.$div$colon:(Ljava/lang/Object;Lscala/Function2;)Ljava/lang/Object;
   13:	areturn
  LineNumberTable: 
   line 48: 0

  LocalVariableTable: 
   Start  Length  Slot  Name   Signature
   0      14      0    $this       Lscala/collection/TraversableProxyLike;
   0      14      1    z       Ljava/lang/Object;
   0      14      2    op       Lscala/Function2;


public static java.lang.Object foldLeft(scala.collection.TraversableProxyLike, java.lang.Object, scala.Function2);
  Code:
   Stack=3, Locals=3, Args_size=3
   0:	aload_0
   1:	invokeinterface	#17,  1; //InterfaceMethod scala/collection/TraversableProxyLike.self:()Lscala/collection/TraversableLike;
   6:	aload_1
   7:	aload_2
   8:	invokeinterface	#203,  3; //InterfaceMethod scala/collection/TraversableLike.foldLeft:(Ljava/lang/Object;Lscala/Function2;)Ljava/lang/Object;
   13:	areturn
  LineNumberTable: 
   line 47: 0

  LocalVariableTable: 
   Start  Length  Slot  Name   Signature
   0      14      0    $this       Lscala/collection/TraversableProxyLike;
   0      14      1    z       Ljava/lang/Object;
   0      14      2    op       Lscala/Function2;


public static scala.Option find(scala.collection.TraversableProxyLike, scala.Function1);
  Code:
   Stack=2, Locals=2, Args_size=2
   0:	aload_0
   1:	invokeinterface	#17,  1; //InterfaceMethod scala/collection/TraversableProxyLike.self:()Lscala/collection/TraversableLike;
   6:	aload_1
   7:	invokeinterface	#208,  2; //InterfaceMethod scala/collection/TraversableLike.find:(Lscala/Function1;)Lscala/Option;
   12:	areturn
  LineNumberTable: 
   line 46: 0

  LocalVariableTable: 
   Start  Length  Slot  Name   Signature
   0      13      0    $this       Lscala/collection/TraversableProxyLike;
   0      13      1    p       Lscala/Function1;


public static int count(scala.collection.TraversableProxyLike, scala.Function1);
  Code:
   Stack=2, Locals=2, Args_size=2
   0:	aload_0
   1:	invokeinterface	#17,  1; //InterfaceMethod scala/collection/TraversableProxyLike.self:()Lscala/collection/TraversableLike;
   6:	aload_1
   7:	invokeinterface	#213,  2; //InterfaceMethod scala/collection/TraversableLike.count:(Lscala/Function1;)I
   12:	ireturn
  LineNumberTable: 
   line 45: 0

  LocalVariableTable: 
   Start  Length  Slot  Name   Signature
   0      13      0    $this       Lscala/collection/TraversableProxyLike;
   0      13      1    p       Lscala/Function1;


public static boolean exists(scala.collection.TraversableProxyLike, scala.Function1);
  Code:
   Stack=2, Locals=2, Args_size=2
   0:	aload_0
   1:	invokeinterface	#17,  1; //InterfaceMethod scala/collection/TraversableProxyLike.self:()Lscala/collection/TraversableLike;
   6:	aload_1
   7:	invokeinterface	#218,  2; //InterfaceMethod scala/collection/TraversableLike.exists:(Lscala/Function1;)Z
   12:	ireturn
  LineNumberTable: 
   line 44: 0

  LocalVariableTable: 
   Start  Length  Slot  Name   Signature
   0      13      0    $this       Lscala/collection/TraversableProxyLike;
   0      13      1    p       Lscala/Function1;


public static boolean forall(scala.collection.TraversableProxyLike, scala.Function1);
  Code:
   Stack=2, Locals=2, Args_size=2
   0:	aload_0
   1:	invokeinterface	#17,  1; //InterfaceMethod scala/collection/TraversableProxyLike.self:()Lscala/collection/TraversableLike;
   6:	aload_1
   7:	invokeinterface	#221,  2; //InterfaceMethod scala/collection/TraversableLike.forall:(Lscala/Function1;)Z
   12:	ireturn
  LineNumberTable: 
   line 43: 0

  LocalVariableTable: 
   Start  Length  Slot  Name   Signature
   0      13      0    $this       Lscala/collection/TraversableProxyLike;
   0      13      1    p       Lscala/Function1;


public static scala.collection.Map groupBy(scala.collection.TraversableProxyLike, scala.Function1);
  Code:
   Stack=2, Locals=2, Args_size=2
   0:	aload_0
   1:	invokeinterface	#17,  1; //InterfaceMethod scala/collection/TraversableProxyLike.self:()Lscala/collection/TraversableLike;
   6:	aload_1
   7:	invokeinterface	#226,  2; //InterfaceMethod scala/collection/TraversableLike.groupBy:(Lscala/Function1;)Lscala/collection/Map;
   12:	areturn
  LineNumberTable: 
   line 42: 0

  LocalVariableTable: 
   Start  Length  Slot  Name   Signature
   0      13      0    $this       Lscala/collection/TraversableProxyLike;
   0      13      1    f       Lscala/Function1;


public static scala.Tuple2 partition(scala.collection.TraversableProxyLike, scala.Function1);
  Code:
   Stack=2, Locals=2, Args_size=2
   0:	aload_0
   1:	invokeinterface	#17,  1; //InterfaceMethod scala/collection/TraversableProxyLike.self:()Lscala/collection/TraversableLike;
   6:	aload_1
   7:	invokeinterface	#230,  2; //InterfaceMethod scala/collection/TraversableLike.partition:(Lscala/Function1;)Lscala/Tuple2;
   12:	areturn
  LineNumberTable: 
   line 41: 0

  LocalVariableTable: 
   Start  Length  Slot  Name   Signature
   0      13      0    $this       Lscala/collection/TraversableProxyLike;
   0      13      1    p       Lscala/Function1;


public static scala.collection.TraversableLike filterNot(scala.collection.TraversableProxyLike, scala.Function1);
  Code:
   Stack=2, Locals=2, Args_size=2
   0:	aload_0
   1:	invokeinterface	#17,  1; //InterfaceMethod scala/collection/TraversableProxyLike.self:()Lscala/collection/TraversableLike;
   6:	aload_1
   7:	invokeinterface	#233,  2; //InterfaceMethod scala/collection/TraversableLike.filterNot:(Lscala/Function1;)Ljava/lang/Object;
   12:	checkcast	#19; //class scala/collection/TraversableLike
   15:	areturn
  LineNumberTable: 
   line 40: 0

  LocalVariableTable: 
   Start  Length  Slot  Name   Signature
   0      16      0    $this       Lscala/collection/TraversableProxyLike;
   0      16      1    p       Lscala/Function1;


public static scala.collection.TraversableLike filter(scala.collection.TraversableProxyLike, scala.Function1);
  Code:
   Stack=2, Locals=2, Args_size=2
   0:	aload_0
   1:	invokeinterface	#17,  1; //InterfaceMethod scala/collection/TraversableProxyLike.self:()Lscala/collection/TraversableLike;
   6:	aload_1
   7:	invokeinterface	#236,  2; //InterfaceMethod scala/collection/TraversableLike.filter:(Lscala/Function1;)Ljava/lang/Object;
   12:	checkcast	#19; //class scala/collection/TraversableLike
   15:	areturn
  LineNumberTable: 
   line 39: 0

  LocalVariableTable: 
   Start  Length  Slot  Name   Signature
   0      16      0    $this       Lscala/collection/TraversableProxyLike;
   0      16      1    p       Lscala/Function1;


public static java.lang.Object flatMap(scala.collection.TraversableProxyLike, scala.Function1, scala.collection.generic.CanBuildFrom);
  Code:
   Stack=3, Locals=3, Args_size=3
   0:	aload_0
   1:	invokeinterface	#17,  1; //InterfaceMethod scala/collection/TraversableProxyLike.self:()Lscala/collection/TraversableLike;
   6:	aload_1
   7:	aload_2
   8:	invokeinterface	#241,  3; //InterfaceMethod scala/collection/TraversableLike.flatMap:(Lscala/Function1;Lscala/collection/generic/CanBuildFrom;)Ljava/lang/Object;
   13:	areturn
  LineNumberTable: 
   line 38: 0

  LocalVariableTable: 
   Start  Length  Slot  Name   Signature
   0      14      0    $this       Lscala/collection/TraversableProxyLike;
   0      14      1    f       Lscala/Function1;
   0      14      2    bf       Lscala/collection/generic/CanBuildFrom;


public static java.lang.Object map(scala.collection.TraversableProxyLike, scala.Function1, scala.collection.generic.CanBuildFrom);
  Code:
   Stack=3, Locals=3, Args_size=3
   0:	aload_0
   1:	invokeinterface	#17,  1; //InterfaceMethod scala/collection/TraversableProxyLike.self:()Lscala/collection/TraversableLike;
   6:	aload_1
   7:	aload_2
   8:	invokeinterface	#246,  3; //InterfaceMethod scala/collection/TraversableLike.map:(Lscala/Function1;Lscala/collection/generic/CanBuildFrom;)Ljava/lang/Object;
   13:	areturn
  LineNumberTable: 
   line 37: 0

  LocalVariableTable: 
   Start  Length  Slot  Name   Signature
   0      14      0    $this       Lscala/collection/TraversableProxyLike;
   0      14      1    f       Lscala/Function1;
   0      14      2    bf       Lscala/collection/generic/CanBuildFrom;


public static java.lang.Object $plus$plus(scala.collection.TraversableProxyLike, scala.collection.Iterator, scala.collection.generic.CanBuildFrom);
  Code:
   Stack=3, Locals=3, Args_size=3
   0:	aload_0
   1:	invokeinterface	#17,  1; //InterfaceMethod scala/collection/TraversableProxyLike.self:()Lscala/collection/TraversableLike;
   6:	aload_1
   7:	aload_2
   8:	invokeinterface	#251,  3; //InterfaceMethod scala/collection/TraversableLike.$plus$plus:(Lscala/collection/Iterator;Lscala/collection/generic/CanBuildFrom;)Ljava/lang/Object;
   13:	areturn
  LineNumberTable: 
   line 36: 0

  LocalVariableTable: 
   Start  Length  Slot  Name   Signature
   0      14      0    $this       Lscala/collection/TraversableProxyLike;
   0      14      1    that       Lscala/collection/Iterator;
   0      14      2    bf       Lscala/collection/generic/CanBuildFrom;


public static java.lang.Object $plus$plus(scala.collection.TraversableProxyLike, scala.collection.Traversable, scala.collection.generic.CanBuildFrom);
  Code:
   Stack=3, Locals=3, Args_size=3
   0:	aload_0
   1:	invokeinterface	#17,  1; //InterfaceMethod scala/collection/TraversableProxyLike.self:()Lscala/collection/TraversableLike;
   6:	aload_1
   7:	aload_2
   8:	invokeinterface	#257,  3; //InterfaceMethod scala/collection/TraversableLike.$plus$plus:(Lscala/collection/Traversable;Lscala/collection/generic/CanBuildFrom;)Ljava/lang/Object;
   13:	areturn
  LineNumberTable: 
   line 35: 0

  LocalVariableTable: 
   Start  Length  Slot  Name   Signature
   0      14      0    $this       Lscala/collection/TraversableProxyLike;
   0      14      1    that       Lscala/collection/Traversable;
   0      14      2    bf       Lscala/collection/generic/CanBuildFrom;


public static boolean hasDefiniteSize(scala.collection.TraversableProxyLike);
  Code:
   Stack=1, Locals=1, Args_size=1
   0:	aload_0
   1:	invokeinterface	#17,  1; //InterfaceMethod scala/collection/TraversableProxyLike.self:()Lscala/collection/TraversableLike;
   6:	invokeinterface	#263,  1; //InterfaceMethod scala/collection/TraversableLike.hasDefiniteSize:()Z
   11:	ireturn
  LineNumberTable: 
   line 34: 0

  LocalVariableTable: 
   Start  Length  Slot  Name   Signature
   0      12      0    $this       Lscala/collection/TraversableProxyLike;


public static int size(scala.collection.TraversableProxyLike);
  Code:
   Stack=1, Locals=1, Args_size=1
   0:	aload_0
   1:	invokeinterface	#17,  1; //InterfaceMethod scala/collection/TraversableProxyLike.self:()Lscala/collection/TraversableLike;
   6:	invokeinterface	#268,  1; //InterfaceMethod scala/collection/TraversableLike.size:()I
   11:	ireturn
  LineNumberTable: 
   line 33: 0

  LocalVariableTable: 
   Start  Length  Slot  Name   Signature
   0      12      0    $this       Lscala/collection/TraversableProxyLike;


public static boolean nonEmpty(scala.collection.TraversableProxyLike);
  Code:
   Stack=1, Locals=1, Args_size=1
   0:	aload_0
   1:	invokeinterface	#17,  1; //InterfaceMethod scala/collection/TraversableProxyLike.self:()Lscala/collection/TraversableLike;
   6:	invokeinterface	#271,  1; //InterfaceMethod scala/collection/TraversableLike.nonEmpty:()Z
   11:	ireturn
  LineNumberTable: 
   line 32: 0

  LocalVariableTable: 
   Start  Length  Slot  Name   Signature
   0      12      0    $this       Lscala/collection/TraversableProxyLike;


public static boolean isEmpty(scala.collection.TraversableProxyLike);
  Code:
   Stack=1, Locals=1, Args_size=1
   0:	aload_0
   1:	invokeinterface	#17,  1; //InterfaceMethod scala/collection/TraversableProxyLike.self:()Lscala/collection/TraversableLike;
   6:	invokeinterface	#274,  1; //InterfaceMethod scala/collection/TraversableLike.isEmpty:()Z
   11:	ireturn
  LineNumberTable: 
   line 31: 0

  LocalVariableTable: 
   Start  Length  Slot  Name   Signature
   0      12      0    $this       Lscala/collection/TraversableProxyLike;


public static void foreach(scala.collection.TraversableProxyLike, scala.Function1);
  Code:
   Stack=2, Locals=2, Args_size=2
   0:	aload_0
   1:	invokeinterface	#17,  1; //InterfaceMethod scala/collection/TraversableProxyLike.self:()Lscala/collection/TraversableLike;
   6:	checkcast	#278; //class scala/collection/generic/GenericTraversableTemplate
   9:	aload_1
   10:	invokeinterface	#281,  2; //InterfaceMethod scala/collection/generic/GenericTraversableTemplate.foreach:(Lscala/Function1;)V
   15:	return
  LineNumberTable: 
   line 30: 0

  LocalVariableTable: 
   Start  Length  Slot  Name   Signature
   0      16      0    $this       Lscala/collection/TraversableProxyLike;
   0      16      1    f       Lscala/Function1;


}

