Compiled from "TraversableLike.scala"
public final class scala.collection.TraversableLike$$anonfun$slice$1 extends java.lang.Object implements scala.Function0,scala.ScalaObject,java.io.Serializable
  SourceFile: "TraversableLike.scala"
  Scala: length = 0x
   
  InnerClass: 
   public final $anonfun$slice$1=class scala/collection/TraversableLike$$anonfun$slice$1 of class scala/collection/TraversableLike
   public final $anonfun$apply$8=class scala/collection/TraversableLike$$anonfun$slice$1$$anonfun$apply$8 of class scala/collection/TraversableLike$$anonfun$slice$1
  minor version: 0
  major version: 49
  Constant pool:
Asciz	SourceFile;
Asciz	TraversableLike.scala;
Asciz	<clinit>;
Asciz	()V;
Asciz	Code;
Asciz	serialVersionUID;
Asciz	J;
Asciz	scala/collection/TraversableLike$$anonfun$slice$1;
class	scala/collection/TraversableLike$$anonfun$slice$1
NameAndType	serialVersionUID:J
Field	scala/collection/TraversableLike$$anonfun$slice$1.serialVersionUID:J
Asciz	i$3;
Asciz	Lscala/runtime/IntRef;;
Asciz	b$9;
Asciz	Lscala/collection/mutable/Builder;;
Asciz	until$1;
Asciz	I;
Asciz	from$1;
Asciz	$outer;
Asciz	Lscala/collection/TraversableLike;;
Asciz	<init>;
Asciz	(Lscala/collection/TraversableLike;IILscala/collection/mutable/Builder;Lscala/runtime/IntRef;)V;
Asciz	LineNumberTable;
Asciz	java/lang/NullPointerException;
class	java/lang/NullPointerException
NameAndType	"<init>":()V
Method	java/lang/NullPointerException."<init>":()V
NameAndType	$outer:Lscala/collection/TraversableLike;
Field	scala/collection/TraversableLike$$anonfun$slice$1.$outer:Lscala/collection/TraversableLike;
NameAndType	from$1:I
Field	scala/collection/TraversableLike$$anonfun$slice$1.from$1:I
NameAndType	until$1:I
Field	scala/collection/TraversableLike$$anonfun$slice$1.until$1:I
NameAndType	b$9:Lscala/collection/mutable/Builder;
Field	scala/collection/TraversableLike$$anonfun$slice$1.b$9:Lscala/collection/mutable/Builder;
NameAndType	i$3:Lscala/runtime/IntRef;
Field	scala/collection/TraversableLike$$anonfun$slice$1.i$3:Lscala/runtime/IntRef;
Asciz	java/lang/Object;
class	java/lang/Object
Method	java/lang/Object."<init>":()V
Asciz	scala/Function0$class;
class	scala/Function0$class
Asciz	$init$;
Asciz	(Lscala/Function0;)V;
NameAndType	$init$:(Lscala/Function0;)V
Method	scala/Function0$class.$init$:(Lscala/Function0;)V
Asciz	this;
Asciz	Lscala/collection/TraversableLike$$anonfun$slice$1;;
Asciz	LocalVariableTable;
Asciz	(Lscala/collection/TraversableLike<TA;TRepr;>;)V;
Asciz	Signature;
Asciz	apply;
Asciz	()Ljava/lang/Object;;
NameAndType	apply:()V
Method	scala/collection/TraversableLike$$anonfun$slice$1.apply:()V
Asciz	scala/runtime/BoxedUnit;
class	scala/runtime/BoxedUnit
Asciz	UNIT;
Asciz	Lscala/runtime/BoxedUnit;;
NameAndType	UNIT:Lscala/runtime/BoxedUnit;
Field	scala/runtime/BoxedUnit.UNIT:Lscala/runtime/BoxedUnit;
Asciz	scala/collection/TraversableLike$$anonfun$slice$1$$anonfun$apply$8;
class	scala/collection/TraversableLike$$anonfun$slice$1$$anonfun$apply$8
Asciz	(Lscala/collection/TraversableLike$$anonfun$slice$1;)V;
NameAndType	"<init>":(Lscala/collection/TraversableLike$$anonfun$slice$1;)V
Method	scala/collection/TraversableLike$$anonfun$slice$1$$anonfun$apply$8."<init>":(Lscala/collection/TraversableLike$$anonfun$slice$1;)V
Asciz	scala/collection/TraversableLike;
class	scala/collection/TraversableLike
Asciz	foreach;
Asciz	(Lscala/Function1;)V;
NameAndType	foreach:(Lscala/Function1;)V
InterfaceMethod	scala/collection/TraversableLike.foreach:(Lscala/Function1;)V
Asciz	toString;
Asciz	()Ljava/lang/String;;
Asciz	(Lscala/Function0;)Ljava/lang/String;;
NameAndType	toString:(Lscala/Function0;)Ljava/lang/String;
Method	scala/Function0$class.toString:(Lscala/Function0;)Ljava/lang/String;
Asciz	Scala;
Asciz	InnerClasses;
Asciz	$anonfun$slice$1;
Asciz	$anonfun$apply$8;
Asciz	scala/Function0;
class	scala/Function0
Asciz	scala/ScalaObject;
class	scala/ScalaObject
Asciz	java/io/Serializable;
class	java/io/Serializable

{
public static final long serialVersionUID;
  Signature: J

public final scala.runtime.IntRef i$3;
  Signature: Lscala/runtime/IntRef;

public final scala.collection.mutable.Builder b$9;
  Signature: Lscala/collection/mutable/Builder;

public final int until$1;
  Signature: I

public final int from$1;
  Signature: I

private final scala.collection.TraversableLike $outer;
  Signature: Lscala/collection/TraversableLike;

public static {};
  Signature: ()V
  Code:
   Stack=2, Locals=0, Args_size=0
	lconst_0
	putstatic	Field serialVersionUID:J
	return
  Labels:

public scala.collection.TraversableLike$$anonfun$slice$1(scala.collection.TraversableLike, int, int, scala.collection.mutable.Builder, scala.runtime.IntRef);
  Signature: (Lscala/collection/TraversableLike;IILscala/collection/mutable/Builder;Lscala/runtime/IntRef;)V
  Code:
   Stack=2, Locals=6, Args_size=6
	aload_1
	ifnonnull	l1 // aload_0
	new	class java/lang/NullPointerException
	dup
	invokespecial	Method java/lang/NullPointerException."<init>":()V
	athrow
l1	aload_0
	aload_1
	putfield	Field $outer:Lscala/collection/TraversableLike;
	aload_0
	iload_2
	putfield	Field from$1:I
	aload_0
	iload_3
	putfield	Field until$1:I
	aload_0
	aload	4
	putfield	Field b$9:Lscala/collection/mutable/Builder;
	aload_0
	aload	5
	putfield	Field i$3:Lscala/runtime/IntRef;
	aload_0
	invokespecial	Method java/lang/Object."<init>":()V
	aload_0
	invokestatic	Method scala/Function0$class.$init$:(Lscala/Function0;)V
	return
  Labels:
   	l1 = 12 // aload_0
  LocalVariableTable: 
   Start  Length  Slot  Name   Signature
   0      48      0    this       Lscala/collection/TraversableLike$$anonfun$slice$1;
   0      48      1    $outer       Lscala/collection/TraversableLike;

  Signature: length = 0x2
   00 32 

public final java.lang.Object apply();
  Signature: ()Ljava/lang/Object;
  Code:
   Stack=1, Locals=2, Args_size=1
	aload_0
	getfield	Field $outer:Lscala/collection/TraversableLike;
	astore_1
	aload_0
	invokevirtual	Method apply:()V
	getstatic	Field scala/runtime/BoxedUnit.UNIT:Lscala/runtime/BoxedUnit;
	areturn
  Labels:
  LocalVariableTable: 
   Start  Length  Slot  Name   Signature
   0      13      0    this       Lscala/collection/TraversableLike$$anonfun$slice$1;


public final void apply();
  Signature: ()V
  Code:
   Stack=4, Locals=2, Args_size=1
	aload_0
	getfield	Field $outer:Lscala/collection/TraversableLike;
	astore_1
	aload_0
	getfield	Field $outer:Lscala/collection/TraversableLike;
	new	class scala/collection/TraversableLike$$anonfun$slice$1$$anonfun$apply$8
	dup
	aload_0
	invokespecial	Method scala/collection/TraversableLike$$anonfun$slice$1$$anonfun$apply$8."<init>":(Lscala/collection/TraversableLike$$anonfun$slice$1;)V
	invokeinterface	InterfaceMethod scala/collection/TraversableLike.foreach:(Lscala/Function1;)V
	return
  Labels:
  LocalVariableTable: 
   Start  Length  Slot  Name   Signature
   0      23      0    this       Lscala/collection/TraversableLike$$anonfun$slice$1;


public java.lang.String toString();
  Signature: ()Ljava/lang/String;
  Code:
   Stack=1, Locals=1, Args_size=1
	aload_0
	invokestatic	Method scala/Function0$class.toString:(Lscala/Function0;)Ljava/lang/String;
	areturn
  Labels:

}

