Compiled from "TraversableLike.scala"
public final class scala.collection.TraversableLike$$anonfun$partialMap$1 extends java.lang.Object implements scala.Function1,scala.ScalaObject,java.io.Serializable
  SourceFile: "TraversableLike.scala"
  Scala: length = 0x
   
  InnerClass: 
   public final $anonfun$partialMap$1=class scala/collection/TraversableLike$$anonfun$partialMap$1 of class scala/collection/TraversableLike
  minor version: 0
  major version: 49
  Constant pool:
Asciz	SourceFile;
Asciz	TraversableLike.scala;
Asciz	<clinit>;
Asciz	()V;
Asciz	Code;
Asciz	serialVersionUID;
Asciz	J;
Asciz	scala/collection/TraversableLike$$anonfun$partialMap$1;
class	scala/collection/TraversableLike$$anonfun$partialMap$1
NameAndType	serialVersionUID:J
Field	scala/collection/TraversableLike$$anonfun$partialMap$1.serialVersionUID:J
Asciz	b$5;
Asciz	Lscala/collection/mutable/Builder;;
Asciz	pf$1;
Asciz	Lscala/PartialFunction;;
Asciz	<init>;
Asciz	(Lscala/collection/TraversableLike;Lscala/PartialFunction;Lscala/collection/mutable/Builder;)V;
Asciz	LineNumberTable;
NameAndType	pf$1:Lscala/PartialFunction;
Field	scala/collection/TraversableLike$$anonfun$partialMap$1.pf$1:Lscala/PartialFunction;
NameAndType	b$5:Lscala/collection/mutable/Builder;
Field	scala/collection/TraversableLike$$anonfun$partialMap$1.b$5:Lscala/collection/mutable/Builder;
Asciz	java/lang/Object;
class	java/lang/Object
NameAndType	"<init>":()V
Method	java/lang/Object."<init>":()V
Asciz	scala/Function1$class;
class	scala/Function1$class
Asciz	$init$;
Asciz	(Lscala/Function1;)V;
NameAndType	$init$:(Lscala/Function1;)V
Method	scala/Function1$class.$init$:(Lscala/Function1;)V
Asciz	this;
Asciz	Lscala/collection/TraversableLike$$anonfun$partialMap$1;;
Asciz	$outer;
Asciz	Lscala/collection/TraversableLike;;
Asciz	LocalVariableTable;
Asciz	(Lscala/collection/TraversableLike<TA;TRepr;>;)V;
Asciz	Signature;
Asciz	apply;
Asciz	(Ljava/lang/Object;)Ljava/lang/Object;;
Asciz	scala/PartialFunction;
class	scala/PartialFunction
Asciz	isDefinedAt;
Asciz	(Ljava/lang/Object;)Z;
NameAndType	isDefinedAt:(Ljava/lang/Object;)Z
InterfaceMethod	scala/PartialFunction.isDefinedAt:(Ljava/lang/Object;)Z
Asciz	scala/Function1;
class	scala/Function1
NameAndType	apply:(Ljava/lang/Object;)Ljava/lang/Object;
InterfaceMethod	scala/Function1.apply:(Ljava/lang/Object;)Ljava/lang/Object;
Asciz	scala/collection/mutable/Builder;
class	scala/collection/mutable/Builder
Asciz	$plus$eq;
Asciz	(Ljava/lang/Object;)Lscala/collection/mutable/Builder;;
NameAndType	$plus$eq:(Ljava/lang/Object;)Lscala/collection/mutable/Builder;
InterfaceMethod	scala/collection/mutable/Builder.$plus$eq:(Ljava/lang/Object;)Lscala/collection/mutable/Builder;
Asciz	scala/runtime/BoxedUnit;
class	scala/runtime/BoxedUnit
Asciz	UNIT;
Asciz	Lscala/runtime/BoxedUnit;;
NameAndType	UNIT:Lscala/runtime/BoxedUnit;
Field	scala/runtime/BoxedUnit.UNIT:Lscala/runtime/BoxedUnit;
Asciz	x;
Asciz	Ljava/lang/Object;;
Asciz	(TA;)Ljava/lang/Object;;
Asciz	andThen;
Asciz	(Lscala/Function1;)Lscala/Function1;;
Asciz	(Lscala/Function1;Lscala/Function1;)Lscala/Function1;;
NameAndType	andThen:(Lscala/Function1;Lscala/Function1;)Lscala/Function1;
Method	scala/Function1$class.andThen:(Lscala/Function1;Lscala/Function1;)Lscala/Function1;
Asciz	g;
Asciz	Lscala/Function1;;
Asciz	compose;
NameAndType	compose:(Lscala/Function1;Lscala/Function1;)Lscala/Function1;
Method	scala/Function1$class.compose:(Lscala/Function1;Lscala/Function1;)Lscala/Function1;
Asciz	toString;
Asciz	()Ljava/lang/String;;
Asciz	(Lscala/Function1;)Ljava/lang/String;;
NameAndType	toString:(Lscala/Function1;)Ljava/lang/String;
Method	scala/Function1$class.toString:(Lscala/Function1;)Ljava/lang/String;
Asciz	Scala;
Asciz	InnerClasses;
Asciz	scala/collection/TraversableLike;
class	scala/collection/TraversableLike
Asciz	$anonfun$partialMap$1;
Asciz	scala/ScalaObject;
class	scala/ScalaObject
Asciz	java/io/Serializable;
class	java/io/Serializable

{
public static final long serialVersionUID;
  Signature: J

private final scala.collection.mutable.Builder b$5;
  Signature: Lscala/collection/mutable/Builder;

private final scala.PartialFunction pf$1;
  Signature: Lscala/PartialFunction;

public static {};
  Signature: ()V
  Code:
   Stack=2, Locals=0, Args_size=0
	lconst_0
	putstatic	Field serialVersionUID:J
	return
  Labels:

public scala.collection.TraversableLike$$anonfun$partialMap$1(scala.collection.TraversableLike, scala.PartialFunction, scala.collection.mutable.Builder);
  Signature: (Lscala/collection/TraversableLike;Lscala/PartialFunction;Lscala/collection/mutable/Builder;)V
  Code:
   Stack=2, Locals=4, Args_size=4
	aload_0
	aload_2
	putfield	Field pf$1:Lscala/PartialFunction;
	aload_0
	aload_3
	putfield	Field b$5:Lscala/collection/mutable/Builder;
	aload_0
	invokespecial	Method java/lang/Object."<init>":()V
	aload_0
	invokestatic	Method scala/Function1$class.$init$:(Lscala/Function1;)V
	return
  Labels:
  LocalVariableTable: 
   Start  Length  Slot  Name   Signature
   0      19      0    this       Lscala/collection/TraversableLike$$anonfun$partialMap$1;
   0      19      1    $outer       Lscala/collection/TraversableLike;

  Signature: length = 0x2
   00 26 

public final java.lang.Object apply(java.lang.Object);
  Signature: (Ljava/lang/Object;)Ljava/lang/Object;
  Code:
   Stack=3, Locals=2, Args_size=2
	aload_0
	getfield	Field pf$1:Lscala/PartialFunction;
	aload_1
	invokeinterface	InterfaceMethod scala/PartialFunction.isDefinedAt:(Ljava/lang/Object;)Z
	ifeq	l1 // getstatic
	aload_0
	getfield	Field b$5:Lscala/collection/mutable/Builder;
	aload_0
	getfield	Field pf$1:Lscala/PartialFunction;
	aload_1
	invokeinterface	InterfaceMethod scala/Function1.apply:(Ljava/lang/Object;)Ljava/lang/Object;
	invokeinterface	InterfaceMethod scala/collection/mutable/Builder.$plus$eq:(Ljava/lang/Object;)Lscala/collection/mutable/Builder;
	goto	l2 // areturn
l1	getstatic	Field scala/runtime/BoxedUnit.UNIT:Lscala/runtime/BoxedUnit;
l2	areturn
  Labels:
   	l1 = 35 // getstatic
   	l2 = 38 // areturn
  LocalVariableTable: 
   Start  Length  Slot  Name   Signature
   0      39      0    this       Lscala/collection/TraversableLike$$anonfun$partialMap$1;
   0      39      1    x       Ljava/lang/Object;

  Signature: length = 0x2
   00 42 

public scala.Function1 andThen(scala.Function1);
  Signature: (Lscala/Function1;)Lscala/Function1;
  Code:
   Stack=2, Locals=2, Args_size=2
	aload_0
	aload_1
	invokestatic	Method scala/Function1$class.andThen:(Lscala/Function1;Lscala/Function1;)Lscala/Function1;
	areturn
  Labels:
  LocalVariableTable: 
   Start  Length  Slot  Name   Signature
   0      6      0    this       Lscala/collection/TraversableLike$$anonfun$partialMap$1;
   0      6      1    g       Lscala/Function1;


public scala.Function1 compose(scala.Function1);
  Signature: (Lscala/Function1;)Lscala/Function1;
  Code:
   Stack=2, Locals=2, Args_size=2
	aload_0
	aload_1
	invokestatic	Method scala/Function1$class.compose:(Lscala/Function1;Lscala/Function1;)Lscala/Function1;
	areturn
  Labels:
  LocalVariableTable: 
   Start  Length  Slot  Name   Signature
   0      6      0    this       Lscala/collection/TraversableLike$$anonfun$partialMap$1;
   0      6      1    g       Lscala/Function1;


public java.lang.String toString();
  Signature: ()Ljava/lang/String;
  Code:
   Stack=1, Locals=1, Args_size=1
	aload_0
	invokestatic	Method scala/Function1$class.toString:(Lscala/Function1;)Ljava/lang/String;
	areturn
  Labels:

}

