Compiled from "TraversableLike.scala"
public final class scala.collection.TraversableLike$$anonfun$slice$1$$anonfun$apply$8 extends java.lang.Object implements scala.Function1,scala.ScalaObject,java.io.Serializable
  SourceFile: "TraversableLike.scala"
  Scala: length = 0x
   
  InnerClass: 
   public final $anonfun$slice$1=class scala/collection/TraversableLike$$anonfun$slice$1 of class scala/collection/TraversableLike
   public final $anonfun$apply$8=class scala/collection/TraversableLike$$anonfun$slice$1$$anonfun$apply$8 of class scala/collection/TraversableLike$$anonfun$slice$1
  minor version: 0
  major version: 49
  Constant pool:
Asciz	SourceFile;
Asciz	TraversableLike.scala;
Asciz	<clinit>;
Asciz	()V;
Asciz	Code;
Asciz	serialVersionUID;
Asciz	J;
Asciz	scala/collection/TraversableLike$$anonfun$slice$1$$anonfun$apply$8;
class	scala/collection/TraversableLike$$anonfun$slice$1$$anonfun$apply$8
NameAndType	serialVersionUID:J
Field	scala/collection/TraversableLike$$anonfun$slice$1$$anonfun$apply$8.serialVersionUID:J
Asciz	$outer;
Asciz	Lscala/collection/TraversableLike$$anonfun$slice$1;;
Asciz	<init>;
Asciz	(Lscala/collection/TraversableLike$$anonfun$slice$1;)V;
Asciz	LineNumberTable;
Asciz	java/lang/NullPointerException;
class	java/lang/NullPointerException
NameAndType	"<init>":()V
Method	java/lang/NullPointerException."<init>":()V
NameAndType	$outer:Lscala/collection/TraversableLike$$anonfun$slice$1;
Field	scala/collection/TraversableLike$$anonfun$slice$1$$anonfun$apply$8.$outer:Lscala/collection/TraversableLike$$anonfun$slice$1;
Asciz	java/lang/Object;
class	java/lang/Object
Method	java/lang/Object."<init>":()V
Asciz	scala/Function1$class;
class	scala/Function1$class
Asciz	$init$;
Asciz	(Lscala/Function1;)V;
NameAndType	$init$:(Lscala/Function1;)V
Method	scala/Function1$class.$init$:(Lscala/Function1;)V
Asciz	this;
Asciz	Lscala/collection/TraversableLike$$anonfun$slice$1$$anonfun$apply$8;;
Asciz	LocalVariableTable;
Asciz	(Lscala/collection/TraversableLike<TA;TRepr;>.$anonfun$slice$1;)V;
Asciz	Signature;
Asciz	apply;
Asciz	(Ljava/lang/Object;)Ljava/lang/Object;;
Asciz	(Ljava/lang/Object;)V;
NameAndType	apply:(Ljava/lang/Object;)V
Method	scala/collection/TraversableLike$$anonfun$slice$1$$anonfun$apply$8.apply:(Ljava/lang/Object;)V
Asciz	scala/runtime/BoxedUnit;
class	scala/runtime/BoxedUnit
Asciz	UNIT;
Asciz	Lscala/runtime/BoxedUnit;;
NameAndType	UNIT:Lscala/runtime/BoxedUnit;
Field	scala/runtime/BoxedUnit.UNIT:Lscala/runtime/BoxedUnit;
Asciz	v1;
Asciz	Ljava/lang/Object;;
Asciz	scala/collection/TraversableLike$$anonfun$slice$1;
class	scala/collection/TraversableLike$$anonfun$slice$1
Asciz	i$3;
Asciz	Lscala/runtime/IntRef;;
NameAndType	i$3:Lscala/runtime/IntRef;
Field	scala/collection/TraversableLike$$anonfun$slice$1.i$3:Lscala/runtime/IntRef;
Asciz	scala/runtime/IntRef;
class	scala/runtime/IntRef
Asciz	elem;
Asciz	I;
NameAndType	elem:I
Field	scala/runtime/IntRef.elem:I
Asciz	from$1;
NameAndType	from$1:I
Field	scala/collection/TraversableLike$$anonfun$slice$1.from$1:I
Asciz	b$9;
Asciz	Lscala/collection/mutable/Builder;;
NameAndType	b$9:Lscala/collection/mutable/Builder;
Field	scala/collection/TraversableLike$$anonfun$slice$1.b$9:Lscala/collection/mutable/Builder;
Asciz	scala/collection/mutable/Builder;
class	scala/collection/mutable/Builder
Asciz	$plus$eq;
Asciz	(Ljava/lang/Object;)Lscala/collection/mutable/Builder;;
NameAndType	$plus$eq:(Ljava/lang/Object;)Lscala/collection/mutable/Builder;
InterfaceMethod	scala/collection/mutable/Builder.$plus$eq:(Ljava/lang/Object;)Lscala/collection/mutable/Builder;
Asciz	until$1;
NameAndType	until$1:I
Field	scala/collection/TraversableLike$$anonfun$slice$1.until$1:I
Asciz	scala/collection/Traversable$;
class	scala/collection/Traversable$
Asciz	MODULE$;
Asciz	Lscala/collection/Traversable$;;
NameAndType	MODULE$:Lscala/collection/Traversable$;
Field	scala/collection/Traversable$.MODULE$:Lscala/collection/Traversable$;
Asciz	breaks;
Asciz	()Lscala/util/control/Breaks;;
NameAndType	breaks:()Lscala/util/control/Breaks;
Method	scala/collection/Traversable$.breaks:()Lscala/util/control/Breaks;
Asciz	scala/util/control/Breaks;
class	scala/util/control/Breaks
Asciz	break;
NameAndType	break:()V
Method	scala/util/control/Breaks.break:()V
Asciz	x;
Asciz	(TA;)V;
Asciz	andThen;
Asciz	(Lscala/Function1;)Lscala/Function1;;
Asciz	(Lscala/Function1;Lscala/Function1;)Lscala/Function1;;
NameAndType	andThen:(Lscala/Function1;Lscala/Function1;)Lscala/Function1;
Method	scala/Function1$class.andThen:(Lscala/Function1;Lscala/Function1;)Lscala/Function1;
Asciz	g;
Asciz	Lscala/Function1;;
Asciz	compose;
NameAndType	compose:(Lscala/Function1;Lscala/Function1;)Lscala/Function1;
Method	scala/Function1$class.compose:(Lscala/Function1;Lscala/Function1;)Lscala/Function1;
Asciz	toString;
Asciz	()Ljava/lang/String;;
Asciz	(Lscala/Function1;)Ljava/lang/String;;
NameAndType	toString:(Lscala/Function1;)Ljava/lang/String;
Method	scala/Function1$class.toString:(Lscala/Function1;)Ljava/lang/String;
Asciz	Scala;
Asciz	InnerClasses;
Asciz	scala/collection/TraversableLike;
class	scala/collection/TraversableLike
Asciz	$anonfun$slice$1;
Asciz	$anonfun$apply$8;
Asciz	scala/Function1;
class	scala/Function1
Asciz	scala/ScalaObject;
class	scala/ScalaObject
Asciz	java/io/Serializable;
class	java/io/Serializable

{
public static final long serialVersionUID;
  Signature: J

private final scala.collection.TraversableLike$$anonfun$slice$1 $outer;
  Signature: Lscala/collection/TraversableLike$$anonfun$slice$1;

public static {};
  Signature: ()V
  Code:
   Stack=2, Locals=0, Args_size=0
	lconst_0
	putstatic	Field serialVersionUID:J
	return
  Labels:

public scala.collection.TraversableLike$$anonfun$slice$1$$anonfun$apply$8(scala.collection.TraversableLike$$anonfun$slice$1);
  Signature: (Lscala/collection/TraversableLike$$anonfun$slice$1;)V
  Code:
   Stack=2, Locals=2, Args_size=2
	aload_1
	ifnonnull	l1 // aload_0
	new	class java/lang/NullPointerException
	dup
	invokespecial	Method java/lang/NullPointerException."<init>":()V
	athrow
l1	aload_0
	aload_1
	putfield	Field $outer:Lscala/collection/TraversableLike$$anonfun$slice$1;
	aload_0
	invokespecial	Method java/lang/Object."<init>":()V
	aload_0
	invokestatic	Method scala/Function1$class.$init$:(Lscala/Function1;)V
	return
  Labels:
   	l1 = 12 // aload_0
  LocalVariableTable: 
   Start  Length  Slot  Name   Signature
   0      26      0    this       Lscala/collection/TraversableLike$$anonfun$slice$1$$anonfun$apply$8;
   0      26      1    $outer       Lscala/collection/TraversableLike$$anonfun$slice$1;

  Signature: length = 0x2
   00 23 

public final java.lang.Object apply(java.lang.Object);
  Signature: (Ljava/lang/Object;)Ljava/lang/Object;
  Code:
   Stack=2, Locals=3, Args_size=2
	aload_0
	getfield	Field $outer:Lscala/collection/TraversableLike$$anonfun$slice$1;
	astore_2
	aload_0
	aload_1
	invokevirtual	Method apply:(Ljava/lang/Object;)V
	getstatic	Field scala/runtime/BoxedUnit.UNIT:Lscala/runtime/BoxedUnit;
	areturn
  Labels:
  LocalVariableTable: 
   Start  Length  Slot  Name   Signature
   0      14      0    this       Lscala/collection/TraversableLike$$anonfun$slice$1$$anonfun$apply$8;
   5      9      1    v1       Ljava/lang/Object;


public final void apply(java.lang.Object);
  Signature: (Ljava/lang/Object;)V
  Code:
   Stack=3, Locals=3, Args_size=2
	aload_0
	getfield	Field $outer:Lscala/collection/TraversableLike$$anonfun$slice$1;
	astore_2
	aload_0
	getfield	Field $outer:Lscala/collection/TraversableLike$$anonfun$slice$1;
	getfield	Field scala/collection/TraversableLike$$anonfun$slice$1.i$3:Lscala/runtime/IntRef;
	getfield	Field scala/runtime/IntRef.elem:I
	aload_0
	getfield	Field $outer:Lscala/collection/TraversableLike$$anonfun$slice$1;
	getfield	Field scala/collection/TraversableLike$$anonfun$slice$1.from$1:I
	if_icmplt	l1 // getstatic
	aload_0
	getfield	Field $outer:Lscala/collection/TraversableLike$$anonfun$slice$1;
	getfield	Field scala/collection/TraversableLike$$anonfun$slice$1.b$9:Lscala/collection/mutable/Builder;
	aload_1
	invokeinterface	InterfaceMethod scala/collection/mutable/Builder.$plus$eq:(Ljava/lang/Object;)Lscala/collection/mutable/Builder;
	goto	l2 // pop
l1	getstatic	Field scala/runtime/BoxedUnit.UNIT:Lscala/runtime/BoxedUnit;
l2	pop
	aload_0
	getfield	Field $outer:Lscala/collection/TraversableLike$$anonfun$slice$1;
	getfield	Field scala/collection/TraversableLike$$anonfun$slice$1.i$3:Lscala/runtime/IntRef;
	aload_0
	getfield	Field $outer:Lscala/collection/TraversableLike$$anonfun$slice$1;
	getfield	Field scala/collection/TraversableLike$$anonfun$slice$1.i$3:Lscala/runtime/IntRef;
	getfield	Field scala/runtime/IntRef.elem:I
	iconst_1
	iadd
	putfield	Field scala/runtime/IntRef.elem:I
	aload_0
	getfield	Field $outer:Lscala/collection/TraversableLike$$anonfun$slice$1;
	getfield	Field scala/collection/TraversableLike$$anonfun$slice$1.i$3:Lscala/runtime/IntRef;
	getfield	Field scala/runtime/IntRef.elem:I
	aload_0
	getfield	Field $outer:Lscala/collection/TraversableLike$$anonfun$slice$1;
	getfield	Field scala/collection/TraversableLike$$anonfun$slice$1.until$1:I
	if_icmpne	l3 // return
	getstatic	Field scala/collection/Traversable$.MODULE$:Lscala/collection/Traversable$;
	invokevirtual	Method scala/collection/Traversable$.breaks:()Lscala/util/control/Breaks;
	invokevirtual	Method scala/util/control/Breaks.break:()V
l3	return
  Labels:
   	l1 = 41 // getstatic
   	l2 = 44 // pop
   	l3 = 96 // return
  LocalVariableTable: 
   Start  Length  Slot  Name   Signature
   0      97      0    this       Lscala/collection/TraversableLike$$anonfun$slice$1$$anonfun$apply$8;
   5      92      1    x       Ljava/lang/Object;

  Signature: length = 0x2
   00 5E 

public scala.Function1 andThen(scala.Function1);
  Signature: (Lscala/Function1;)Lscala/Function1;
  Code:
   Stack=2, Locals=2, Args_size=2
	aload_0
	aload_1
	invokestatic	Method scala/Function1$class.andThen:(Lscala/Function1;Lscala/Function1;)Lscala/Function1;
	areturn
  Labels:
  LocalVariableTable: 
   Start  Length  Slot  Name   Signature
   0      6      0    this       Lscala/collection/TraversableLike$$anonfun$slice$1$$anonfun$apply$8;
   0      6      1    g       Lscala/Function1;


public scala.Function1 compose(scala.Function1);
  Signature: (Lscala/Function1;)Lscala/Function1;
  Code:
   Stack=2, Locals=2, Args_size=2
	aload_0
	aload_1
	invokestatic	Method scala/Function1$class.compose:(Lscala/Function1;Lscala/Function1;)Lscala/Function1;
	areturn
  Labels:
  LocalVariableTable: 
   Start  Length  Slot  Name   Signature
   0      6      0    this       Lscala/collection/TraversableLike$$anonfun$slice$1$$anonfun$apply$8;
   0      6      1    g       Lscala/Function1;


public java.lang.String toString();
  Signature: ()Ljava/lang/String;
  Code:
   Stack=1, Locals=1, Args_size=1
	aload_0
	invokestatic	Method scala/Function1$class.toString:(Lscala/Function1;)Ljava/lang/String;
	areturn
  Labels:

}

