Compiled from "Traversable.scala"
public final class scala.collection.Traversable$TraversableTraversableOps$$anonfun$transpose$1 extends java.lang.Object implements scala.Function1,scala.ScalaObject,java.io.Serializable
  SourceFile: "Traversable.scala"
  Scala: length = 0x
   
  InnerClass: 
   public #95= #94 of #34; //TraversableTraversableOps=class scala/collection/Traversable$TraversableTraversableOps of class scala/collection/Traversable
   public final #96= #10 of #94; //$anonfun$transpose$1=class scala/collection/Traversable$TraversableTraversableOps$$anonfun$transpose$1 of class scala/collection/Traversable$TraversableTraversableOps
   public final #97= #62 of #10; //$anonfun$apply$1=class scala/collection/Traversable$TraversableTraversableOps$$anonfun$transpose$1$$anonfun$apply$1 of class scala/collection/Traversable$TraversableTraversableOps$$anonfun$transpose$1
  minor version: 0
  major version: 49
  Constant pool:
const #1 = Asciz	SourceFile;
const #2 = Asciz	Traversable.scala;
const #3 = Asciz	bs$1;
const #4 = Asciz	[Lscala/collection/generic/Builder;;
const #5 = Asciz	<init>;
const #6 = Asciz	(Lscala/collection/Traversable$TraversableTraversableOps;[Lscala/collection/generic/Builder;)V;
const #7 = Asciz	Code;
const #8 = Asciz	LineNumberTable;
const #9 = Asciz	scala/collection/Traversable$TraversableTraversableOps$$anonfun$transpose$1;
const #10 = class	#9;	//  scala/collection/Traversable$TraversableTraversableOps$$anonfun$transpose$1
const #11 = NameAndType	#3:#4;//  bs$1:[Lscala/collection/generic/Builder;
const #12 = Field	#10.#11;	//  scala/collection/Traversable$TraversableTraversableOps$$anonfun$transpose$1.bs$1:[Lscala/collection/generic/Builder;
const #13 = Asciz	java/lang/Object;
const #14 = class	#13;	//  java/lang/Object
const #15 = Asciz	()V;
const #16 = NameAndType	#5:#15;//  "<init>":()V
const #17 = Method	#14.#16;	//  java/lang/Object."<init>":()V
const #18 = Asciz	scala/Function1$class;
const #19 = class	#18;	//  scala/Function1$class
const #20 = Asciz	$init$;
const #21 = Asciz	(Lscala/Function1;)V;
const #22 = NameAndType	#20:#21;//  $init$:(Lscala/Function1;)V
const #23 = Method	#19.#22;	//  scala/Function1$class.$init$:(Lscala/Function1;)V
const #24 = Asciz	this;
const #25 = Asciz	Lscala/collection/Traversable$TraversableTraversableOps$$anonfun$transpose$1;;
const #26 = Asciz	$outer;
const #27 = Asciz	Lscala/collection/Traversable$TraversableTraversableOps;;
const #28 = Asciz	LocalVariableTable;
const #29 = Asciz	(Lscala/collection/Traversable$TraversableTraversableOps<TThis;TA;>;)V;
const #30 = Asciz	Signature;
const #31 = Asciz	apply;
const #32 = Asciz	(Ljava/lang/Object;)Ljava/lang/Object;;
const #33 = Asciz	scala/collection/Traversable;
const #34 = class	#33;	//  scala/collection/Traversable
const #35 = Asciz	scala/runtime/ScalaRunTime$;
const #36 = class	#35;	//  scala/runtime/ScalaRunTime$
const #37 = Asciz	MODULE$;
const #38 = Asciz	Lscala/runtime/ScalaRunTime$;;
const #39 = NameAndType	#37:#38;//  MODULE$:Lscala/runtime/ScalaRunTime$;
const #40 = Field	#36.#39;	//  scala/runtime/ScalaRunTime$.MODULE$:Lscala/runtime/ScalaRunTime$;
const #41 = Asciz	boxArray;
const #42 = Asciz	(Ljava/lang/Object;)Lscala/runtime/BoxedArray;;
const #43 = NameAndType	#41:#42;//  boxArray:(Ljava/lang/Object;)Lscala/runtime/BoxedArray;
const #44 = Method	#36.#43;	//  scala/runtime/ScalaRunTime$.boxArray:(Ljava/lang/Object;)Lscala/runtime/BoxedArray;
const #45 = Asciz	(Lscala/collection/Traversable;)V;
const #46 = NameAndType	#31:#45;//  apply:(Lscala/collection/Traversable;)V
const #47 = Method	#10.#46;	//  scala/collection/Traversable$TraversableTraversableOps$$anonfun$transpose$1.apply:(Lscala/collection/Traversable;)V
const #48 = Asciz	scala/runtime/BoxedUnit;
const #49 = class	#48;	//  scala/runtime/BoxedUnit
const #50 = Asciz	UNIT;
const #51 = Asciz	Lscala/runtime/BoxedUnit;;
const #52 = NameAndType	#50:#51;//  UNIT:Lscala/runtime/BoxedUnit;
const #53 = Field	#49.#52;	//  scala/runtime/BoxedUnit.UNIT:Lscala/runtime/BoxedUnit;
const #54 = Asciz	v1;
const #55 = Asciz	Ljava/lang/Object;;
const #56 = Asciz	scala/runtime/IntRef;
const #57 = class	#56;	//  scala/runtime/IntRef
const #58 = Asciz	(I)V;
const #59 = NameAndType	#5:#58;//  "<init>":(I)V
const #60 = Method	#57.#59;	//  scala/runtime/IntRef."<init>":(I)V
const #61 = Asciz	scala/collection/Traversable$TraversableTraversableOps$$anonfun$transpose$1$$anonfun$apply$1;
const #62 = class	#61;	//  scala/collection/Traversable$TraversableTraversableOps$$anonfun$transpose$1$$anonfun$apply$1
const #63 = Asciz	(Lscala/collection/Traversable$TraversableTraversableOps$$anonfun$transpose$1;Lscala/runtime/IntRef;)V;
const #64 = NameAndType	#5:#63;//  "<init>":(Lscala/collection/Traversable$TraversableTraversableOps$$anonfun$transpose$1;Lscala/runtime/IntRef;)V
const #65 = Method	#62.#64;	//  scala/collection/Traversable$TraversableTraversableOps$$anonfun$transpose$1$$anonfun$apply$1."<init>":(Lscala/collection/Traversable$TraversableTraversableOps$$anonfun$transpose$1;Lscala/runtime/IntRef;)V
const #66 = Asciz	scala/collection/generic/TraversableClass;
const #67 = class	#66;	//  scala/collection/generic/TraversableClass
const #68 = Asciz	foreach;
const #69 = NameAndType	#68:#21;//  foreach:(Lscala/Function1;)V
const #70 = InterfaceMethod	#67.#69;	//  scala/collection/generic/TraversableClass.foreach:(Lscala/Function1;)V
const #71 = Asciz	xs;
const #72 = Asciz	Lscala/collection/Traversable;;
const #73 = Asciz	i$1;
const #74 = Asciz	Lscala/runtime/IntRef;;
const #75 = Asciz	(Lscala/collection/Traversable<TA;>;)V;
const #76 = Asciz	andThen;
const #77 = Asciz	(Lscala/Function1;)Lscala/Function1;;
const #78 = Asciz	(Lscala/Function1;Lscala/Function1;)Lscala/Function1;;
const #79 = NameAndType	#76:#78;//  andThen:(Lscala/Function1;Lscala/Function1;)Lscala/Function1;
const #80 = Method	#19.#79;	//  scala/Function1$class.andThen:(Lscala/Function1;Lscala/Function1;)Lscala/Function1;
const #81 = Asciz	g;
const #82 = Asciz	Lscala/Function1;;
const #83 = Asciz	compose;
const #84 = NameAndType	#83:#78;//  compose:(Lscala/Function1;Lscala/Function1;)Lscala/Function1;
const #85 = Method	#19.#84;	//  scala/Function1$class.compose:(Lscala/Function1;Lscala/Function1;)Lscala/Function1;
const #86 = Asciz	toString;
const #87 = Asciz	()Ljava/lang/String;;
const #88 = Asciz	(Lscala/Function1;)Ljava/lang/String;;
const #89 = NameAndType	#86:#88;//  toString:(Lscala/Function1;)Ljava/lang/String;
const #90 = Method	#19.#89;	//  scala/Function1$class.toString:(Lscala/Function1;)Ljava/lang/String;
const #91 = Asciz	Scala;
const #92 = Asciz	InnerClasses;
const #93 = Asciz	scala/collection/Traversable$TraversableTraversableOps;
const #94 = class	#93;	//  scala/collection/Traversable$TraversableTraversableOps
const #95 = Asciz	TraversableTraversableOps;
const #96 = Asciz	$anonfun$transpose$1;
const #97 = Asciz	$anonfun$apply$1;
const #98 = Asciz	scala/Function1;
const #99 = class	#98;	//  scala/Function1
const #100 = Asciz	scala/ScalaObject;
const #101 = class	#100;	//  scala/ScalaObject
const #102 = Asciz	java/io/Serializable;
const #103 = class	#102;	//  java/io/Serializable

{
public final scala.collection.generic.Builder[] bs$1;

public scala.collection.Traversable$TraversableTraversableOps$$anonfun$transpose$1(scala.collection.Traversable$TraversableTraversableOps, scala.collection.generic.Builder[]);
  Code:
   Stack=2, Locals=3, Args_size=3
   0:	aload_0
   1:	aload_2
   2:	putfield	#12; //Field bs$1:[Lscala/collection/generic/Builder;
   5:	aload_0
   6:	invokespecial	#17; //Method java/lang/Object."<init>":()V
   9:	aload_0
   10:	invokestatic	#23; //Method scala/Function1$class.$init$:(Lscala/Function1;)V
   13:	return
  LineNumberTable: 
   line 164: 0

  LocalVariableTable: 
   Start  Length  Slot  Name   Signature
   0      14      0    this       Lscala/collection/Traversable$TraversableTraversableOps$$anonfun$transpose$1;
   0      14      1    $outer       Lscala/collection/Traversable$TraversableTraversableOps;

  Signature: length = 0x2
   00 1D 

public final java.lang.Object apply(java.lang.Object);
  Code:
   Stack=3, Locals=2, Args_size=2
   0:	aload_0
   1:	aload_1
   2:	instanceof	#34; //class scala/collection/Traversable
   5:	ifeq	12
   8:	aload_1
   9:	goto	19
   12:	getstatic	#40; //Field scala/runtime/ScalaRunTime$.MODULE$:Lscala/runtime/ScalaRunTime$;
   15:	aload_1
   16:	invokevirtual	#44; //Method scala/runtime/ScalaRunTime$.boxArray:(Ljava/lang/Object;)Lscala/runtime/BoxedArray;
   19:	checkcast	#34; //class scala/collection/Traversable
   22:	invokevirtual	#47; //Method apply:(Lscala/collection/Traversable;)V
   25:	getstatic	#53; //Field scala/runtime/BoxedUnit.UNIT:Lscala/runtime/BoxedUnit;
   28:	areturn
  LineNumberTable: 
   line 164: 0

  LocalVariableTable: 
   Start  Length  Slot  Name   Signature
   0      29      0    this       Lscala/collection/Traversable$TraversableTraversableOps$$anonfun$transpose$1;
   0      29      1    v1       Ljava/lang/Object;


public final void apply(scala.collection.Traversable);
  Code:
   Stack=5, Locals=3, Args_size=2
   0:	new	#57; //class scala/runtime/IntRef
   3:	dup
   4:	iconst_0
   5:	invokespecial	#60; //Method scala/runtime/IntRef."<init>":(I)V
   8:	astore_2
   9:	aload_1
   10:	new	#62; //class scala/collection/Traversable$TraversableTraversableOps$$anonfun$transpose$1$$anonfun$apply$1
   13:	dup
   14:	aload_0
   15:	aload_2
   16:	invokespecial	#65; //Method scala/collection/Traversable$TraversableTraversableOps$$anonfun$transpose$1$$anonfun$apply$1."<init>":(Lscala/collection/Traversable$TraversableTraversableOps$$anonfun$transpose$1;Lscala/runtime/IntRef;)V
   19:	invokeinterface	#70,  2; //InterfaceMethod scala/collection/generic/TraversableClass.foreach:(Lscala/Function1;)V
   24:	return
  LineNumberTable: 
   line 165: 0
   line 166: 9

  LocalVariableTable: 
   Start  Length  Slot  Name   Signature
   0      25      0    this       Lscala/collection/Traversable$TraversableTraversableOps$$anonfun$transpose$1;
   0      25      1    xs       Lscala/collection/Traversable;
   9      15      2    i$1       Lscala/runtime/IntRef;

  Signature: length = 0x2
   00 4B 

public scala.Function1 andThen(scala.Function1);
  Code:
   Stack=2, Locals=2, Args_size=2
   0:	aload_0
   1:	aload_1
   2:	invokestatic	#80; //Method scala/Function1$class.andThen:(Lscala/Function1;Lscala/Function1;)Lscala/Function1;
   5:	areturn
  LineNumberTable: 
   line 164: 0

  LocalVariableTable: 
   Start  Length  Slot  Name   Signature
   0      6      0    this       Lscala/collection/Traversable$TraversableTraversableOps$$anonfun$transpose$1;
   0      6      1    g       Lscala/Function1;


public scala.Function1 compose(scala.Function1);
  Code:
   Stack=2, Locals=2, Args_size=2
   0:	aload_0
   1:	aload_1
   2:	invokestatic	#85; //Method scala/Function1$class.compose:(Lscala/Function1;Lscala/Function1;)Lscala/Function1;
   5:	areturn
  LineNumberTable: 
   line 164: 0

  LocalVariableTable: 
   Start  Length  Slot  Name   Signature
   0      6      0    this       Lscala/collection/Traversable$TraversableTraversableOps$$anonfun$transpose$1;
   0      6      1    g       Lscala/Function1;


public java.lang.String toString();
  Code:
   Stack=1, Locals=1, Args_size=1
   0:	aload_0
   1:	invokestatic	#90; //Method scala/Function1$class.toString:(Lscala/Function1;)Ljava/lang/String;
   4:	areturn
  LineNumberTable: 
   line 164: 0


}

