Compiled from "TraversableLike.scala"
public final class scala.collection.TraversableLike$$anonfun$copyToBuffer$1 extends scala.runtime.AbstractFunction1 implements java.io.Serializable
  SourceFile: "TraversableLike.scala"
  Scala: length = 0x
   
  InnerClass: 
   public final $anonfun$copyToBuffer$1=class scala/collection/TraversableLike$$anonfun$copyToBuffer$1 of class scala/collection/TraversableLike
  minor version: 0
  major version: 49
  Constant pool:
Asciz	SourceFile;
Asciz	TraversableLike.scala;
Asciz	<clinit>;
Asciz	()V;
Asciz	Code;
Asciz	serialVersionUID;
Asciz	J;
Asciz	scala/collection/TraversableLike$$anonfun$copyToBuffer$1;
class	scala/collection/TraversableLike$$anonfun$copyToBuffer$1
NameAndType	serialVersionUID:J
Field	scala/collection/TraversableLike$$anonfun$copyToBuffer$1.serialVersionUID:J
Asciz	dest$1;
Asciz	Lscala/collection/mutable/Buffer;;
Asciz	<init>;
Asciz	(Lscala/collection/TraversableLike;Lscala/collection/mutable/Buffer;)V;
Asciz	LineNumberTable;
NameAndType	dest$1:Lscala/collection/mutable/Buffer;
Field	scala/collection/TraversableLike$$anonfun$copyToBuffer$1.dest$1:Lscala/collection/mutable/Buffer;
Asciz	scala/runtime/AbstractFunction1;
class	scala/runtime/AbstractFunction1
NameAndType	"<init>":()V
Method	scala/runtime/AbstractFunction1."<init>":()V
Asciz	this;
Asciz	Lscala/collection/TraversableLike$$anonfun$copyToBuffer$1;;
Asciz	$outer;
Asciz	Lscala/collection/TraversableLike;;
Asciz	LocalVariableTable;
Asciz	(Lscala/collection/TraversableLike<TA;TRepr;>;)V;
Asciz	Signature;
Asciz	apply;
Asciz	(Ljava/lang/Object;)Ljava/lang/Object;;
Asciz	(Ljava/lang/Object;)Lscala/collection/mutable/Buffer;;
NameAndType	apply:(Ljava/lang/Object;)Lscala/collection/mutable/Buffer;
Method	scala/collection/TraversableLike$$anonfun$copyToBuffer$1.apply:(Ljava/lang/Object;)Lscala/collection/mutable/Buffer;
Asciz	v1;
Asciz	Ljava/lang/Object;;
Asciz	scala/collection/mutable/BufferLike;
class	scala/collection/mutable/BufferLike
Asciz	$plus$eq;
NameAndType	$plus$eq:(Ljava/lang/Object;)Lscala/collection/mutable/Buffer;
InterfaceMethod	scala/collection/mutable/BufferLike.$plus$eq:(Ljava/lang/Object;)Lscala/collection/mutable/Buffer;
Asciz	x;
Asciz	(TA;)Lscala/collection/mutable/Buffer<TB;>;;
Asciz	Scala;
Asciz	InnerClasses;
Asciz	scala/collection/TraversableLike;
class	scala/collection/TraversableLike
Asciz	$anonfun$copyToBuffer$1;
Asciz	java/io/Serializable;
class	java/io/Serializable

{
public static final long serialVersionUID;
  Signature: J

private final scala.collection.mutable.Buffer dest$1;
  Signature: Lscala/collection/mutable/Buffer;

public static {};
  Signature: ()V
  Code:
   Stack=2, Locals=0, Args_size=0
	lconst_0
	putstatic	Field serialVersionUID:J
	return
  Labels:

public scala.collection.TraversableLike$$anonfun$copyToBuffer$1(scala.collection.TraversableLike, scala.collection.mutable.Buffer);
  Signature: (Lscala/collection/TraversableLike;Lscala/collection/mutable/Buffer;)V
  Code:
   Stack=2, Locals=3, Args_size=3
	aload_0
	aload_2
	putfield	Field dest$1:Lscala/collection/mutable/Buffer;
	aload_0
	invokespecial	Method scala/runtime/AbstractFunction1."<init>":()V
	return
  Labels:
  LocalVariableTable: 
   Start  Length  Slot  Name   Signature
   0      10      0    this       Lscala/collection/TraversableLike$$anonfun$copyToBuffer$1;
   0      10      1    $outer       Lscala/collection/TraversableLike;

  Signature: length = 0x2
   00 1C 

public final java.lang.Object apply(java.lang.Object);
  Signature: (Ljava/lang/Object;)Ljava/lang/Object;
  Code:
   Stack=2, Locals=2, Args_size=2
	aload_0
	aload_1
	invokevirtual	Method apply:(Ljava/lang/Object;)Lscala/collection/mutable/Buffer;
	areturn
  Labels:
  LocalVariableTable: 
   Start  Length  Slot  Name   Signature
   0      6      0    this       Lscala/collection/TraversableLike$$anonfun$copyToBuffer$1;
   0      6      1    v1       Ljava/lang/Object;


public final scala.collection.mutable.Buffer apply(java.lang.Object);
  Signature: (Ljava/lang/Object;)Lscala/collection/mutable/Buffer;
  Code:
   Stack=2, Locals=2, Args_size=2
	aload_0
	getfield	Field dest$1:Lscala/collection/mutable/Buffer;
	aload_1
	invokeinterface	InterfaceMethod scala/collection/mutable/BufferLike.$plus$eq:(Ljava/lang/Object;)Lscala/collection/mutable/Buffer;
	areturn
  Labels:
  LocalVariableTable: 
   Start  Length  Slot  Name   Signature
   0      11      0    this       Lscala/collection/TraversableLike$$anonfun$copyToBuffer$1;
   0      11      1    x       Ljava/lang/Object;

  Signature: length = 0x2
   00 2B 

}

