Compiled from "TraversableViewLike.scala"
public final class scala.collection.TraversableViewLike$TakenWhile$$anonfun$foreach$7 extends scala.runtime.AbstractFunction1 implements java.io.Serializable
  SourceFile: "TraversableViewLike.scala"
  Scala: length = 0x
   
  InnerClass: 
   public abstract TakenWhile=class scala/collection/TraversableViewLike$TakenWhile of class scala/collection/TraversableViewLike
   public final $anonfun$foreach$7=class scala/collection/TraversableViewLike$TakenWhile$$anonfun$foreach$7 of class scala/collection/TraversableViewLike$TakenWhile
  minor version: 0
  major version: 49
  Constant pool:
Asciz	SourceFile;
Asciz	TraversableViewLike.scala;
Asciz	<clinit>;
Asciz	()V;
Asciz	Code;
Asciz	serialVersionUID;
Asciz	J;
Asciz	scala/collection/TraversableViewLike$TakenWhile$$anonfun$foreach$7;
class	scala/collection/TraversableViewLike$TakenWhile$$anonfun$foreach$7
NameAndType	serialVersionUID:J
Field	scala/collection/TraversableViewLike$TakenWhile$$anonfun$foreach$7.serialVersionUID:J
Asciz	nonLocalReturnKey2$1;
Asciz	Ljava/lang/Object;;
Asciz	f$8;
Asciz	Lscala/Function1;;
Asciz	$outer;
Asciz	Lscala/collection/TraversableViewLike$TakenWhile;;
Asciz	apply;
Asciz	(Ljava/lang/Object;)Ljava/lang/Object;;
Asciz	LineNumberTable;
NameAndType	$outer:Lscala/collection/TraversableViewLike$TakenWhile;
Field	scala/collection/TraversableViewLike$TakenWhile$$anonfun$foreach$7.$outer:Lscala/collection/TraversableViewLike$TakenWhile;
Asciz	scala/collection/TraversableViewLike$TakenWhile;
class	scala/collection/TraversableViewLike$TakenWhile
Asciz	pred;
Asciz	()Lscala/Function1;;
NameAndType	pred:()Lscala/Function1;
InterfaceMethod	scala/collection/TraversableViewLike$TakenWhile.pred:()Lscala/Function1;
Asciz	scala/Function1;
class	scala/Function1
NameAndType	apply:(Ljava/lang/Object;)Ljava/lang/Object;
InterfaceMethod	scala/Function1.apply:(Ljava/lang/Object;)Ljava/lang/Object;
Asciz	scala/runtime/BoxesRunTime;
class	scala/runtime/BoxesRunTime
Asciz	unboxToBoolean;
Asciz	(Ljava/lang/Object;)Z;
NameAndType	unboxToBoolean:(Ljava/lang/Object;)Z
Method	scala/runtime/BoxesRunTime.unboxToBoolean:(Ljava/lang/Object;)Z
NameAndType	f$8:Lscala/Function1;
Field	scala/collection/TraversableViewLike$TakenWhile$$anonfun$foreach$7.f$8:Lscala/Function1;
Asciz	scala/runtime/NonLocalReturnException;
class	scala/runtime/NonLocalReturnException
NameAndType	nonLocalReturnKey2$1:Ljava/lang/Object;
Field	scala/collection/TraversableViewLike$TakenWhile$$anonfun$foreach$7.nonLocalReturnKey2$1:Ljava/lang/Object;
Asciz	scala/runtime/BoxedUnit;
class	scala/runtime/BoxedUnit
Asciz	UNIT;
Asciz	Lscala/runtime/BoxedUnit;;
NameAndType	UNIT:Lscala/runtime/BoxedUnit;
Field	scala/runtime/BoxedUnit.UNIT:Lscala/runtime/BoxedUnit;
Asciz	<init>;
Asciz	(Ljava/lang/Object;Ljava/lang/Object;)V;
NameAndType	"<init>":(Ljava/lang/Object;Ljava/lang/Object;)V
Method	scala/runtime/NonLocalReturnException."<init>":(Ljava/lang/Object;Ljava/lang/Object;)V
Asciz	this;
Asciz	Lscala/collection/TraversableViewLike$TakenWhile$$anonfun$foreach$7;;
Asciz	x;
Asciz	LocalVariableTable;
Asciz	(TA;)TC;;
Asciz	Signature;
Asciz	(Lscala/collection/TraversableViewLike$TakenWhile;Lscala/Function1;Ljava/lang/Object;)V;
Asciz	java/lang/NullPointerException;
class	java/lang/NullPointerException
NameAndType	"<init>":()V
Method	java/lang/NullPointerException."<init>":()V
Asciz	scala/runtime/AbstractFunction1;
class	scala/runtime/AbstractFunction1
Method	scala/runtime/AbstractFunction1."<init>":()V
Asciz	(Lscala/collection/TraversableViewLike<TA;TColl;TThis;>.TakenWhile;)V;
Asciz	Scala;
Asciz	InnerClasses;
Asciz	scala/collection/TraversableViewLike;
class	scala/collection/TraversableViewLike
Asciz	TakenWhile;
Asciz	$anonfun$foreach$7;
Asciz	java/io/Serializable;
class	java/io/Serializable

{
public static final long serialVersionUID;
  Signature: J

private final java.lang.Object nonLocalReturnKey2$1;
  Signature: Ljava/lang/Object;

private final scala.Function1 f$8;
  Signature: Lscala/Function1;

private final scala.collection.TraversableViewLike$TakenWhile $outer;
  Signature: Lscala/collection/TraversableViewLike$TakenWhile;

public static {};
  Signature: ()V
  Code:
   Stack=2, Locals=0, Args_size=0
	lconst_0
	putstatic	Field serialVersionUID:J
	return
  Labels:

public final java.lang.Object apply(java.lang.Object);
  Signature: (Ljava/lang/Object;)Ljava/lang/Object;
  Code:
   Stack=4, Locals=2, Args_size=2
	aload_0
	getfield	Field $outer:Lscala/collection/TraversableViewLike$TakenWhile;
	invokeinterface	InterfaceMethod scala/collection/TraversableViewLike$TakenWhile.pred:()Lscala/Function1;
	aload_1
	invokeinterface	InterfaceMethod scala/Function1.apply:(Ljava/lang/Object;)Ljava/lang/Object;
	invokestatic	Method scala/runtime/BoxesRunTime.unboxToBoolean:(Ljava/lang/Object;)Z
	ifeq	l1 // new
	aload_0
	getfield	Field f$8:Lscala/Function1;
	aload_1
	invokeinterface	InterfaceMethod scala/Function1.apply:(Ljava/lang/Object;)Ljava/lang/Object;
	areturn
l1	new	class scala/runtime/NonLocalReturnException
	dup
	aload_0
	getfield	Field nonLocalReturnKey2$1:Ljava/lang/Object;
	getstatic	Field scala/runtime/BoxedUnit.UNIT:Lscala/runtime/BoxedUnit;
	invokespecial	Method scala/runtime/NonLocalReturnException."<init>":(Ljava/lang/Object;Ljava/lang/Object;)V
	athrow
  Labels:
   	l1 = 32 // new
  LocalVariableTable: 
   Start  Length  Slot  Name   Signature
   0      47      0    this       Lscala/collection/TraversableViewLike$TakenWhile$$anonfun$foreach$7;
   0      47      1    x       Ljava/lang/Object;

  Signature: length = 0x2
   00 3B 

public scala.collection.TraversableViewLike$TakenWhile$$anonfun$foreach$7(scala.collection.TraversableViewLike$TakenWhile, scala.Function1, java.lang.Object);
  Signature: (Lscala/collection/TraversableViewLike$TakenWhile;Lscala/Function1;Ljava/lang/Object;)V
  Code:
   Stack=2, Locals=4, Args_size=4
	aload_1
	ifnonnull	l1 // aload_0
	new	class java/lang/NullPointerException
	dup
	invokespecial	Method java/lang/NullPointerException."<init>":()V
	athrow
l1	aload_0
	aload_1
	putfield	Field $outer:Lscala/collection/TraversableViewLike$TakenWhile;
	aload_0
	aload_2
	putfield	Field f$8:Lscala/Function1;
	aload_0
	aload_3
	putfield	Field nonLocalReturnKey2$1:Ljava/lang/Object;
	aload_0
	invokespecial	Method scala/runtime/AbstractFunction1."<init>":()V
	return
  Labels:
   	l1 = 12 // aload_0
  LocalVariableTable: 
   Start  Length  Slot  Name   Signature
   0      32      0    this       Lscala/collection/TraversableViewLike$TakenWhile$$anonfun$foreach$7;
   0      32      1    $outer       Lscala/collection/TraversableViewLike$TakenWhile;

  Signature: length = 0x2
   00 45 

}

