Compiled from "TraversableLike.scala"
public final class scala.collection.TraversableLike$$anonfun$2 extends scala.runtime.AbstractFunction2 implements java.io.Serializable
  SourceFile: "TraversableLike.scala"
  Scala: length = 0x
   
  InnerClass: 
   public final $anonfun$2=class scala/collection/TraversableLike$$anonfun$2 of class scala/collection/TraversableLike
  minor version: 0
  major version: 49
  Constant pool:
Asciz	SourceFile;
Asciz	TraversableLike.scala;
Asciz	<clinit>;
Asciz	()V;
Asciz	Code;
Asciz	serialVersionUID;
Asciz	J;
Asciz	scala/collection/TraversableLike$$anonfun$2;
class	scala/collection/TraversableLike$$anonfun$2
NameAndType	serialVersionUID:J
Field	scala/collection/TraversableLike$$anonfun$2.serialVersionUID:J
Asciz	op$6;
Asciz	Lscala/Function2;;
Asciz	apply;
Asciz	(Ljava/lang/Object;Lscala/Tuple2;)Lscala/Tuple2;;
Asciz	LineNumberTable;
NameAndType	op$6:Lscala/Function2;
Field	scala/collection/TraversableLike$$anonfun$2.op$6:Lscala/Function2;
Asciz	scala/Tuple2;
class	scala/Tuple2
Asciz	_1;
Asciz	()Ljava/lang/Object;;
NameAndType	_1:()Ljava/lang/Object;
Method	scala/Tuple2._1:()Ljava/lang/Object;
Asciz	scala/Function2;
class	scala/Function2
Asciz	(Ljava/lang/Object;Ljava/lang/Object;)Ljava/lang/Object;;
NameAndType	apply:(Ljava/lang/Object;Ljava/lang/Object;)Ljava/lang/Object;
InterfaceMethod	scala/Function2.apply:(Ljava/lang/Object;Ljava/lang/Object;)Ljava/lang/Object;
Asciz	_2;
NameAndType	_2:()Ljava/lang/Object;
Method	scala/Tuple2._2:()Ljava/lang/Object;
Asciz	scala/collection/mutable/Builder;
class	scala/collection/mutable/Builder
Asciz	$plus$eq;
Asciz	(Ljava/lang/Object;)Lscala/collection/mutable/Builder;;
NameAndType	$plus$eq:(Ljava/lang/Object;)Lscala/collection/mutable/Builder;
InterfaceMethod	scala/collection/mutable/Builder.$plus$eq:(Ljava/lang/Object;)Lscala/collection/mutable/Builder;
Asciz	<init>;
Asciz	(Ljava/lang/Object;Ljava/lang/Object;)V;
NameAndType	"<init>":(Ljava/lang/Object;Ljava/lang/Object;)V
Method	scala/Tuple2."<init>":(Ljava/lang/Object;Ljava/lang/Object;)V
Asciz	this;
Asciz	Lscala/collection/TraversableLike$$anonfun$2;;
Asciz	x;
Asciz	Ljava/lang/Object;;
Asciz	acc;
Asciz	Lscala/Tuple2;;
Asciz	next;
Asciz	LocalVariableTable;
Asciz	(TA;Lscala/Tuple2<TB;Lscala/collection/mutable/Builder<TB;TThat;>;>;)Lscala/Tuple2<TB;Lscala/collection/mutable/Builder<TB;TThat;>;>;;
Asciz	Signature;
NameAndType	apply:(Ljava/lang/Object;Lscala/Tuple2;)Lscala/Tuple2;
Method	scala/collection/TraversableLike$$anonfun$2.apply:(Ljava/lang/Object;Lscala/Tuple2;)Lscala/Tuple2;
Asciz	v1;
Asciz	v2;
Asciz	(Lscala/collection/TraversableLike;Lscala/Function2;)V;
Asciz	scala/runtime/AbstractFunction2;
class	scala/runtime/AbstractFunction2
NameAndType	"<init>":()V
Method	scala/runtime/AbstractFunction2."<init>":()V
Asciz	$outer;
Asciz	Lscala/collection/TraversableLike;;
Asciz	(Lscala/collection/TraversableLike<TA;TRepr;>;)V;
Asciz	Scala;
Asciz	InnerClasses;
Asciz	scala/collection/TraversableLike;
class	scala/collection/TraversableLike
Asciz	$anonfun$2;
Asciz	java/io/Serializable;
class	java/io/Serializable

{
public static final long serialVersionUID;
  Signature: J

public final scala.Function2 op$6;
  Signature: Lscala/Function2;

public static {};
  Signature: ()V
  Code:
   Stack=2, Locals=0, Args_size=0
	lconst_0
	putstatic	Field serialVersionUID:J
	return
  Labels:

public final scala.Tuple2 apply(java.lang.Object, scala.Tuple2);
  Signature: (Ljava/lang/Object;Lscala/Tuple2;)Lscala/Tuple2;
  Code:
   Stack=5, Locals=4, Args_size=3
	aload_0
	getfield	Field op$6:Lscala/Function2;
	aload_1
	aload_2
	invokevirtual	Method scala/Tuple2._1:()Ljava/lang/Object;
	invokeinterface	InterfaceMethod scala/Function2.apply:(Ljava/lang/Object;Ljava/lang/Object;)Ljava/lang/Object;
	astore_3
	new	class scala/Tuple2
	dup
	aload_3
	aload_2
	invokevirtual	Method scala/Tuple2._2:()Ljava/lang/Object;
	checkcast	class scala/collection/mutable/Builder
	aload_3
	invokeinterface	InterfaceMethod scala/collection/mutable/Builder.$plus$eq:(Ljava/lang/Object;)Lscala/collection/mutable/Builder;
	invokespecial	Method scala/Tuple2."<init>":(Ljava/lang/Object;Ljava/lang/Object;)V
	areturn
  Labels:
  LocalVariableTable: 
   Start  Length  Slot  Name   Signature
   0      37      0    this       Lscala/collection/TraversableLike$$anonfun$2;
   0      37      1    x       Ljava/lang/Object;
   0      37      2    acc       Lscala/Tuple2;
   15      21      3    next       Ljava/lang/Object;

  Signature: length = 0x2
   00 33 

public final java.lang.Object apply(java.lang.Object, java.lang.Object);
  Signature: (Ljava/lang/Object;Ljava/lang/Object;)Ljava/lang/Object;
  Code:
   Stack=3, Locals=3, Args_size=3
	aload_0
	aload_1
	aload_2
	checkcast	class scala/Tuple2
	invokevirtual	Method apply:(Ljava/lang/Object;Lscala/Tuple2;)Lscala/Tuple2;
	areturn
  Labels:
  LocalVariableTable: 
   Start  Length  Slot  Name   Signature
   0      10      0    this       Lscala/collection/TraversableLike$$anonfun$2;
   0      10      1    v1       Ljava/lang/Object;
   0      10      2    v2       Ljava/lang/Object;


public scala.collection.TraversableLike$$anonfun$2(scala.collection.TraversableLike, scala.Function2);
  Signature: (Lscala/collection/TraversableLike;Lscala/Function2;)V
  Code:
   Stack=2, Locals=3, Args_size=3
	aload_0
	aload_2
	putfield	Field op$6:Lscala/Function2;
	aload_0
	invokespecial	Method scala/runtime/AbstractFunction2."<init>":()V
	return
  Labels:
  LocalVariableTable: 
   Start  Length  Slot  Name   Signature
   0      10      0    this       Lscala/collection/TraversableLike$$anonfun$2;
   0      10      1    $outer       Lscala/collection/TraversableLike;

  Signature: length = 0x2
   00 40 

}

