Compiled from "TraversableViewLike.scala"
public final class scala.collection.TraversableViewLike$DroppedWhile$$anonfun$foreach$8 extends java.lang.Object implements scala.Function1,scala.ScalaObject,java.io.Serializable
  SourceFile: "TraversableViewLike.scala"
  Scala: length = 0x
   
  InnerClass: 
   public abstract DroppedWhile=class scala/collection/TraversableViewLike$DroppedWhile of class scala/collection/TraversableViewLike
   public final $anonfun$foreach$8=class scala/collection/TraversableViewLike$DroppedWhile$$anonfun$foreach$8 of class scala/collection/TraversableViewLike$DroppedWhile
  minor version: 0
  major version: 49
  Constant pool:
Asciz	SourceFile;
Asciz	TraversableViewLike.scala;
Asciz	<clinit>;
Asciz	()V;
Asciz	Code;
Asciz	serialVersionUID;
Asciz	J;
Asciz	scala/collection/TraversableViewLike$DroppedWhile$$anonfun$foreach$8;
class	scala/collection/TraversableViewLike$DroppedWhile$$anonfun$foreach$8
NameAndType	serialVersionUID:J
Field	scala/collection/TraversableViewLike$DroppedWhile$$anonfun$foreach$8.serialVersionUID:J
Asciz	go$1;
Asciz	Lscala/runtime/BooleanRef;;
Asciz	f$9;
Asciz	Lscala/Function1;;
Asciz	$outer;
Asciz	Lscala/collection/TraversableViewLike$DroppedWhile;;
Asciz	<init>;
Asciz	(Lscala/collection/TraversableViewLike$DroppedWhile;Lscala/Function1;Lscala/runtime/BooleanRef;)V;
Asciz	LineNumberTable;
Asciz	java/lang/NullPointerException;
class	java/lang/NullPointerException
NameAndType	"<init>":()V
Method	java/lang/NullPointerException."<init>":()V
NameAndType	$outer:Lscala/collection/TraversableViewLike$DroppedWhile;
Field	scala/collection/TraversableViewLike$DroppedWhile$$anonfun$foreach$8.$outer:Lscala/collection/TraversableViewLike$DroppedWhile;
NameAndType	f$9:Lscala/Function1;
Field	scala/collection/TraversableViewLike$DroppedWhile$$anonfun$foreach$8.f$9:Lscala/Function1;
NameAndType	go$1:Lscala/runtime/BooleanRef;
Field	scala/collection/TraversableViewLike$DroppedWhile$$anonfun$foreach$8.go$1:Lscala/runtime/BooleanRef;
Asciz	java/lang/Object;
class	java/lang/Object
Method	java/lang/Object."<init>":()V
Asciz	scala/Function1$class;
class	scala/Function1$class
Asciz	$init$;
Asciz	(Lscala/Function1;)V;
NameAndType	$init$:(Lscala/Function1;)V
Method	scala/Function1$class.$init$:(Lscala/Function1;)V
Asciz	this;
Asciz	Lscala/collection/TraversableViewLike$DroppedWhile$$anonfun$foreach$8;;
Asciz	LocalVariableTable;
Asciz	(Lscala/collection/TraversableViewLike<TA;TColl;TThis;>.DroppedWhile;)V;
Asciz	Signature;
Asciz	apply;
Asciz	(Ljava/lang/Object;)Ljava/lang/Object;;
Asciz	scala/runtime/BooleanRef;
class	scala/runtime/BooleanRef
Asciz	elem;
Asciz	Z;
NameAndType	elem:Z
Field	scala/runtime/BooleanRef.elem:Z
Asciz	scala/collection/TraversableViewLike$DroppedWhile;
class	scala/collection/TraversableViewLike$DroppedWhile
Asciz	pred;
Asciz	()Lscala/Function1;;
NameAndType	pred:()Lscala/Function1;
InterfaceMethod	scala/collection/TraversableViewLike$DroppedWhile.pred:()Lscala/Function1;
Asciz	scala/Function1;
class	scala/Function1
NameAndType	apply:(Ljava/lang/Object;)Ljava/lang/Object;
InterfaceMethod	scala/Function1.apply:(Ljava/lang/Object;)Ljava/lang/Object;
Asciz	scala/runtime/BoxesRunTime;
class	scala/runtime/BoxesRunTime
Asciz	unboxToBoolean;
Asciz	(Ljava/lang/Object;)Z;
NameAndType	unboxToBoolean:(Ljava/lang/Object;)Z
Method	scala/runtime/BoxesRunTime.unboxToBoolean:(Ljava/lang/Object;)Z
Asciz	scala/runtime/BoxedUnit;
class	scala/runtime/BoxedUnit
Asciz	UNIT;
Asciz	Lscala/runtime/BoxedUnit;;
NameAndType	UNIT:Lscala/runtime/BoxedUnit;
Field	scala/runtime/BoxedUnit.UNIT:Lscala/runtime/BoxedUnit;
Asciz	x;
Asciz	Ljava/lang/Object;;
Asciz	(TA;)Ljava/lang/Object;;
Asciz	andThen;
Asciz	(Lscala/Function1;)Lscala/Function1;;
Asciz	(Lscala/Function1;Lscala/Function1;)Lscala/Function1;;
NameAndType	andThen:(Lscala/Function1;Lscala/Function1;)Lscala/Function1;
Method	scala/Function1$class.andThen:(Lscala/Function1;Lscala/Function1;)Lscala/Function1;
Asciz	g;
Asciz	compose;
NameAndType	compose:(Lscala/Function1;Lscala/Function1;)Lscala/Function1;
Method	scala/Function1$class.compose:(Lscala/Function1;Lscala/Function1;)Lscala/Function1;
Asciz	toString;
Asciz	()Ljava/lang/String;;
Asciz	(Lscala/Function1;)Ljava/lang/String;;
NameAndType	toString:(Lscala/Function1;)Ljava/lang/String;
Method	scala/Function1$class.toString:(Lscala/Function1;)Ljava/lang/String;
Asciz	Scala;
Asciz	InnerClasses;
Asciz	scala/collection/TraversableViewLike;
class	scala/collection/TraversableViewLike
Asciz	DroppedWhile;
Asciz	$anonfun$foreach$8;
Asciz	scala/ScalaObject;
class	scala/ScalaObject
Asciz	java/io/Serializable;
class	java/io/Serializable

{
public static final long serialVersionUID;
  Signature: J

private final scala.runtime.BooleanRef go$1;
  Signature: Lscala/runtime/BooleanRef;

private final scala.Function1 f$9;
  Signature: Lscala/Function1;

private final scala.collection.TraversableViewLike$DroppedWhile $outer;
  Signature: Lscala/collection/TraversableViewLike$DroppedWhile;

public static {};
  Signature: ()V
  Code:
   Stack=2, Locals=0, Args_size=0
	lconst_0
	putstatic	Field serialVersionUID:J
	return
  Labels:

public scala.collection.TraversableViewLike$DroppedWhile$$anonfun$foreach$8(scala.collection.TraversableViewLike$DroppedWhile, scala.Function1, scala.runtime.BooleanRef);
  Signature: (Lscala/collection/TraversableViewLike$DroppedWhile;Lscala/Function1;Lscala/runtime/BooleanRef;)V
  Code:
   Stack=2, Locals=4, Args_size=4
	aload_1
	ifnonnull	l1 // aload_0
	new	class java/lang/NullPointerException
	dup
	invokespecial	Method java/lang/NullPointerException."<init>":()V
	athrow
l1	aload_0
	aload_1
	putfield	Field $outer:Lscala/collection/TraversableViewLike$DroppedWhile;
	aload_0
	aload_2
	putfield	Field f$9:Lscala/Function1;
	aload_0
	aload_3
	putfield	Field go$1:Lscala/runtime/BooleanRef;
	aload_0
	invokespecial	Method java/lang/Object."<init>":()V
	aload_0
	invokestatic	Method scala/Function1$class.$init$:(Lscala/Function1;)V
	return
  Labels:
   	l1 = 12 // aload_0
  LocalVariableTable: 
   Start  Length  Slot  Name   Signature
   0      36      0    this       Lscala/collection/TraversableViewLike$DroppedWhile$$anonfun$foreach$8;
   0      36      1    $outer       Lscala/collection/TraversableViewLike$DroppedWhile;

  Signature: length = 0x2
   00 2B 

public final java.lang.Object apply(java.lang.Object);
  Signature: (Ljava/lang/Object;)Ljava/lang/Object;
  Code:
   Stack=2, Locals=3, Args_size=2
	aload_0
	getfield	Field $outer:Lscala/collection/TraversableViewLike$DroppedWhile;
	astore_2
	aload_0
	getfield	Field go$1:Lscala/runtime/BooleanRef;
	getfield	Field scala/runtime/BooleanRef.elem:Z
	ifne	l1 // aload_0
	aload_0
	getfield	Field $outer:Lscala/collection/TraversableViewLike$DroppedWhile;
	invokeinterface	InterfaceMethod scala/collection/TraversableViewLike$DroppedWhile.pred:()Lscala/Function1;
	aload_1
	invokeinterface	InterfaceMethod scala/Function1.apply:(Ljava/lang/Object;)Ljava/lang/Object;
	invokestatic	Method scala/runtime/BoxesRunTime.unboxToBoolean:(Ljava/lang/Object;)Z
	ifne	l1 // aload_0
	aload_0
	getfield	Field go$1:Lscala/runtime/BooleanRef;
	iconst_1
	putfield	Field scala/runtime/BooleanRef.elem:Z
l1	aload_0
	getfield	Field go$1:Lscala/runtime/BooleanRef;
	getfield	Field scala/runtime/BooleanRef.elem:Z
	ifeq	l2 // getstatic
	aload_0
	getfield	Field f$9:Lscala/Function1;
	aload_1
	invokeinterface	InterfaceMethod scala/Function1.apply:(Ljava/lang/Object;)Ljava/lang/Object;
	goto	l3 // areturn
l2	getstatic	Field scala/runtime/BoxedUnit.UNIT:Lscala/runtime/BoxedUnit;
l3	areturn
  Labels:
   	l1 = 44 // aload_0
   	l2 = 67 // getstatic
   	l3 = 70 // areturn
  LocalVariableTable: 
   Start  Length  Slot  Name   Signature
   0      71      0    this       Lscala/collection/TraversableViewLike$DroppedWhile$$anonfun$foreach$8;
   5      66      1    x       Ljava/lang/Object;

  Signature: length = 0x2
   00 4D 

public scala.Function1 andThen(scala.Function1);
  Signature: (Lscala/Function1;)Lscala/Function1;
  Code:
   Stack=2, Locals=2, Args_size=2
	aload_0
	aload_1
	invokestatic	Method scala/Function1$class.andThen:(Lscala/Function1;Lscala/Function1;)Lscala/Function1;
	areturn
  Labels:
  LocalVariableTable: 
   Start  Length  Slot  Name   Signature
   0      6      0    this       Lscala/collection/TraversableViewLike$DroppedWhile$$anonfun$foreach$8;
   0      6      1    g       Lscala/Function1;


public scala.Function1 compose(scala.Function1);
  Signature: (Lscala/Function1;)Lscala/Function1;
  Code:
   Stack=2, Locals=2, Args_size=2
	aload_0
	aload_1
	invokestatic	Method scala/Function1$class.compose:(Lscala/Function1;Lscala/Function1;)Lscala/Function1;
	areturn
  Labels:
  LocalVariableTable: 
   Start  Length  Slot  Name   Signature
   0      6      0    this       Lscala/collection/TraversableViewLike$DroppedWhile$$anonfun$foreach$8;
   0      6      1    g       Lscala/Function1;


public java.lang.String toString();
  Signature: ()Ljava/lang/String;
  Code:
   Stack=1, Locals=1, Args_size=1
	aload_0
	invokestatic	Method scala/Function1$class.toString:(Lscala/Function1;)Ljava/lang/String;
	areturn
  Labels:

}

