Compiled from "TraversableLike.scala"
public final class scala.collection.TraversableLike$$anonfun$toMap$1 extends scala.runtime.AbstractFunction1 implements java.io.Serializable
  SourceFile: "TraversableLike.scala"
  Scala: length = 0x
   
  InnerClass: 
   public abstract $less$colon$less=class scala/Predef$$less$colon$less of class scala/Predef
   public final $anonfun$toMap$1=class scala/collection/TraversableLike$$anonfun$toMap$1 of class scala/collection/TraversableLike
  minor version: 0
  major version: 49
  Constant pool:
Asciz	SourceFile;
Asciz	TraversableLike.scala;
Asciz	<clinit>;
Asciz	()V;
Asciz	Code;
Asciz	serialVersionUID;
Asciz	J;
Asciz	scala/collection/TraversableLike$$anonfun$toMap$1;
class	scala/collection/TraversableLike$$anonfun$toMap$1
NameAndType	serialVersionUID:J
Field	scala/collection/TraversableLike$$anonfun$toMap$1.serialVersionUID:J
Asciz	b$12;
Asciz	Lscala/collection/mutable/Builder;;
Asciz	ev$1;
Asciz	Lscala/Predef$$less$colon$less;;
Asciz	<init>;
Asciz	(Lscala/collection/TraversableLike;Lscala/Predef$$less$colon$less;Lscala/collection/mutable/Builder;)V;
Asciz	LineNumberTable;
NameAndType	ev$1:Lscala/Predef$$less$colon$less;
Field	scala/collection/TraversableLike$$anonfun$toMap$1.ev$1:Lscala/Predef$$less$colon$less;
NameAndType	b$12:Lscala/collection/mutable/Builder;
Field	scala/collection/TraversableLike$$anonfun$toMap$1.b$12:Lscala/collection/mutable/Builder;
Asciz	scala/runtime/AbstractFunction1;
class	scala/runtime/AbstractFunction1
NameAndType	"<init>":()V
Method	scala/runtime/AbstractFunction1."<init>":()V
Asciz	this;
Asciz	Lscala/collection/TraversableLike$$anonfun$toMap$1;;
Asciz	$outer;
Asciz	Lscala/collection/TraversableLike;;
Asciz	LocalVariableTable;
Asciz	(Lscala/collection/TraversableLike<TA;TRepr;>;)V;
Asciz	Signature;
Asciz	apply;
Asciz	(Ljava/lang/Object;)Ljava/lang/Object;;
Asciz	(Ljava/lang/Object;)Lscala/collection/mutable/Builder;;
NameAndType	apply:(Ljava/lang/Object;)Lscala/collection/mutable/Builder;
Method	scala/collection/TraversableLike$$anonfun$toMap$1.apply:(Ljava/lang/Object;)Lscala/collection/mutable/Builder;
Asciz	v1;
Asciz	Ljava/lang/Object;;
Asciz	scala/Function1;
class	scala/Function1
NameAndType	apply:(Ljava/lang/Object;)Ljava/lang/Object;
InterfaceMethod	scala/Function1.apply:(Ljava/lang/Object;)Ljava/lang/Object;
Asciz	scala/collection/mutable/Builder;
class	scala/collection/mutable/Builder
Asciz	$plus$eq;
NameAndType	$plus$eq:(Ljava/lang/Object;)Lscala/collection/mutable/Builder;
InterfaceMethod	scala/collection/mutable/Builder.$plus$eq:(Ljava/lang/Object;)Lscala/collection/mutable/Builder;
Asciz	x;
Asciz	(TA;)Lscala/collection/mutable/Builder<Lscala/Tuple2<TT;TU;>;Lscala/collection/immutable/Map<TT;TU;>;>;;
Asciz	Scala;
Asciz	InnerClasses;
Asciz	scala/Predef$$less$colon$less;
class	scala/Predef$$less$colon$less
Asciz	scala/Predef;
class	scala/Predef
Asciz	$less$colon$less;
Asciz	scala/collection/TraversableLike;
class	scala/collection/TraversableLike
Asciz	$anonfun$toMap$1;
Asciz	java/io/Serializable;
class	java/io/Serializable

{
public static final long serialVersionUID;
  Signature: J

public final scala.collection.mutable.Builder b$12;
  Signature: Lscala/collection/mutable/Builder;

public final scala.Predef$$less$colon$less ev$1;
  Signature: Lscala/Predef$$less$colon$less;

public static {};
  Signature: ()V
  Code:
   Stack=2, Locals=0, Args_size=0
	lconst_0
	putstatic	Field serialVersionUID:J
	return
  Labels:

public scala.collection.TraversableLike$$anonfun$toMap$1(scala.collection.TraversableLike, scala.Predef$$less$colon$less, scala.collection.mutable.Builder);
  Signature: (Lscala/collection/TraversableLike;Lscala/Predef$$less$colon$less;Lscala/collection/mutable/Builder;)V
  Code:
   Stack=2, Locals=4, Args_size=4
	aload_0
	aload_2
	putfield	Field ev$1:Lscala/Predef$$less$colon$less;
	aload_0
	aload_3
	putfield	Field b$12:Lscala/collection/mutable/Builder;
	aload_0
	invokespecial	Method scala/runtime/AbstractFunction1."<init>":()V
	return
  Labels:
  LocalVariableTable: 
   Start  Length  Slot  Name   Signature
   0      15      0    this       Lscala/collection/TraversableLike$$anonfun$toMap$1;
   0      15      1    $outer       Lscala/collection/TraversableLike;

  Signature: length = 0x2
   00 20 

public final java.lang.Object apply(java.lang.Object);
  Signature: (Ljava/lang/Object;)Ljava/lang/Object;
  Code:
   Stack=2, Locals=2, Args_size=2
	aload_0
	aload_1
	invokevirtual	Method apply:(Ljava/lang/Object;)Lscala/collection/mutable/Builder;
	areturn
  Labels:
  LocalVariableTable: 
   Start  Length  Slot  Name   Signature
   0      6      0    this       Lscala/collection/TraversableLike$$anonfun$toMap$1;
   0      6      1    v1       Ljava/lang/Object;


public final scala.collection.mutable.Builder apply(java.lang.Object);
  Signature: (Ljava/lang/Object;)Lscala/collection/mutable/Builder;
  Code:
   Stack=3, Locals=2, Args_size=2
	aload_0
	getfield	Field b$12:Lscala/collection/mutable/Builder;
	aload_0
	getfield	Field ev$1:Lscala/Predef$$less$colon$less;
	aload_1
	invokeinterface	InterfaceMethod scala/Function1.apply:(Ljava/lang/Object;)Ljava/lang/Object;
	invokeinterface	InterfaceMethod scala/collection/mutable/Builder.$plus$eq:(Ljava/lang/Object;)Lscala/collection/mutable/Builder;
	areturn
  Labels:
  LocalVariableTable: 
   Start  Length  Slot  Name   Signature
   0      20      0    this       Lscala/collection/TraversableLike$$anonfun$toMap$1;
   0      20      1    x       Ljava/lang/Object;

  Signature: length = 0x2
   00 33 

}

