Compiled from "TraversableProxyLike.scala"
public class scala.collection.TraversableProxyLikeConfirmation extends java.lang.Object implements scala.collection.TraversableProxyLike,scala.collection.interfaces.TraversableMethods,scala.ScalaObject
  SourceFile: "TraversableProxyLike.scala"
  Signature: length = 0x2
   01 FFFFFFA0 
  ScalaSig: length = 0x1E2
   05 00 47 06 04 01 02 04 07 02 20 54 72 61 76 65
   72 73 61 62 6C 65 50 72 6F 78 79 4C 69 6B 65 43
   6F 6E 66 69 72 6D 61 74 69 6F 6E 0A 02 03 04 01
   0A 63 6F 6C 6C 65 63 74 69 6F 6E 0A 01 05 01 05
   73 63 61 6C 61 03 00 15 03 08 17 32 13 05 00 09
   11 24 2A 10 02 0A 0F 0D 01 0B 0A 02 0C 0D 01 04
   6C 61 6E 67 0A 01 0E 01 04 6A 61 76 61 09 02 10
   0B 02 06 4F 62 6A 65 63 74 10 04 12 13 15 21 0D
   01 02 09 02 14 02 02 14 54 72 61 76 65 72 73 61
   62 6C 65 50 72 6F 78 79 4C 69 6B 65 10 02 16 17
   0C 00 04 08 18 00 FFFFFF84 FFFFFF80 FFFFFF84 FFFFFFC2 00 19 02 01 41 11
   02 1A 1E 10 02 1B 1C 0D 01 04 09 02 1D 04 02 07
   4E 6F 74 68 69 6E 67 10 02 1B 1F 09 02 20 04 02
   03 41 6E 79 10 03 12 22 15 09 02 23 02 02 0B 54
   72 61 76 65 72 73 61 62 6C 65 10 04 25 28 15 21
   0D 01 26 0A 02 27 02 01 0A 69 6E 74 65 72 66 61
   63 65 73 09 02 29 26 02 12 54 72 61 76 65 72 73
   61 62 6C 65 4D 65 74 68 6F 64 73 10 02 1B 2B 09
   02 2C 04 02 0B 53 63 61 6C 61 4F 62 6A 65 63 74
   08 05 2E 00 FFFFFF84 00 2F 01 06 3C 69 6E 69 74 3E 14
   01 30 10 04 12 00 15 31 10 02 16 32 04 08 33 00
   FFFFFF84 FFFFFF80 FFFFFF84 FFFFFFC2 00 34 02 04 54 68 69 73 11 02 1A 35
   12 03 36 38 21 06 08 37 00 FFFFFF84 FFFFFF80 FFFFFF80 FFFFFF80 00 35 02
   0C 3C 72 65 66 69 6E 65 6D 65 6E 74 3E 10 04 12
   39 15 31 09 02 3A 02 02 0F 54 72 61 76 65 72 73
   61 62 6C 65 4C 69 6B 65 08 05 3C 00 FFFFFF84 00 3D 01
   04 73 65 6C 66 15 01 31 08 06 3F 00 FFFFFFA0 FFFFFF84 08 40
   01 0A 6E 65 77 42 75 69 6C 64 65 72 15 01 41 10
   04 42 45 15 21 0D 01 43 0A 02 44 02 01 07 6D 75
   74 61 62 6C 65 09 02 46 43 02 07 42 75 69 6C 64
   65 72 
  InnerClass: 
   public #421= #420 of #103; //WithFilter=class scala/collection/TraversableLike$WithFilter of class scala/collection/TraversableLike
  minor version: 0
  major version: 49
  Constant pool:
const #1 = Asciz	SourceFile;
const #2 = Asciz	TraversableProxyLike.scala;
const #3 = Asciz	<init>;
const #4 = Asciz	()V;
const #5 = Asciz	Code;
const #6 = Asciz	LineNumberTable;
const #7 = Asciz	java/lang/Object;
const #8 = class	#7;	//  java/lang/Object
const #9 = NameAndType	#3:#4;//  "<init>":()V
const #10 = Method	#8.#9;	//  java/lang/Object."<init>":()V
const #11 = Asciz	scala/collection/TraversableLike$class;
const #12 = class	#11;	//  scala/collection/TraversableLike$class
const #13 = Asciz	$init$;
const #14 = Asciz	(Lscala/collection/TraversableLike;)V;
const #15 = NameAndType	#13:#14;//  $init$:(Lscala/collection/TraversableLike;)V
const #16 = Method	#12.#15;	//  scala/collection/TraversableLike$class.$init$:(Lscala/collection/TraversableLike;)V
const #17 = Asciz	scala/Proxy$class;
const #18 = class	#17;	//  scala/Proxy$class
const #19 = Asciz	(Lscala/Proxy;)V;
const #20 = NameAndType	#13:#19;//  $init$:(Lscala/Proxy;)V
const #21 = Method	#18.#20;	//  scala/Proxy$class.$init$:(Lscala/Proxy;)V
const #22 = Asciz	scala/collection/TraversableProxyLike$class;
const #23 = class	#22;	//  scala/collection/TraversableProxyLike$class
const #24 = Asciz	(Lscala/collection/TraversableProxyLike;)V;
const #25 = NameAndType	#13:#24;//  $init$:(Lscala/collection/TraversableProxyLike;)V
const #26 = Method	#23.#25;	//  scala/collection/TraversableProxyLike$class.$init$:(Lscala/collection/TraversableProxyLike;)V
const #27 = Asciz	Signature;
const #28 = Asciz	self;
const #29 = Asciz	()Ljava/lang/Object;;
const #30 = Asciz	scala/collection/TraversableProxyLikeConfirmation;
const #31 = class	#30;	//  scala/collection/TraversableProxyLikeConfirmation
const #32 = Asciz	()Lscala/collection/TraversableLike;;
const #33 = NameAndType	#28:#32;//  self:()Lscala/collection/TraversableLike;
const #34 = Method	#31.#33;	//  scala/collection/TraversableProxyLikeConfirmation.self:()Lscala/collection/TraversableLike;
const #35 = Asciz	filter;
const #36 = Asciz	(Lscala/Function1;)Ljava/lang/Object;;
const #37 = Asciz	scala/collection/TraversableProxyLike;
const #38 = class	#37;	//  scala/collection/TraversableProxyLike
const #39 = Asciz	(Lscala/Function1;)Lscala/collection/TraversableLike;;
const #40 = NameAndType	#35:#39;//  filter:(Lscala/Function1;)Lscala/collection/TraversableLike;
const #41 = InterfaceMethod	#38.#40;	//  scala/collection/TraversableProxyLike.filter:(Lscala/Function1;)Lscala/collection/TraversableLike;
const #42 = Asciz	this;
const #43 = Asciz	Lscala/collection/TraversableProxyLikeConfirmation;;
const #44 = Asciz	p;
const #45 = Asciz	Lscala/Function1;;
const #46 = Asciz	LocalVariableTable;
const #47 = Asciz	(Lscala/Function1;)Lscala/collection/Traversable;;
const #48 = Asciz	scala/collection/Traversable;
const #49 = class	#48;	//  scala/collection/Traversable
const #50 = Asciz	filterNot;
const #51 = NameAndType	#50:#39;//  filterNot:(Lscala/Function1;)Lscala/collection/TraversableLike;
const #52 = InterfaceMethod	#38.#51;	//  scala/collection/TraversableProxyLike.filterNot:(Lscala/Function1;)Lscala/collection/TraversableLike;
const #53 = Asciz	tail;
const #54 = NameAndType	#53:#32;//  tail:()Lscala/collection/TraversableLike;
const #55 = InterfaceMethod	#38.#54;	//  scala/collection/TraversableProxyLike.tail:()Lscala/collection/TraversableLike;
const #56 = Asciz	()Lscala/collection/Traversable;;
const #57 = Asciz	init;
const #58 = NameAndType	#57:#32;//  init:()Lscala/collection/TraversableLike;
const #59 = InterfaceMethod	#38.#58;	//  scala/collection/TraversableProxyLike.init:()Lscala/collection/TraversableLike;
const #60 = Asciz	take;
const #61 = Asciz	(I)Ljava/lang/Object;;
const #62 = Asciz	(I)Lscala/collection/TraversableLike;;
const #63 = NameAndType	#60:#62;//  take:(I)Lscala/collection/TraversableLike;
const #64 = InterfaceMethod	#38.#63;	//  scala/collection/TraversableProxyLike.take:(I)Lscala/collection/TraversableLike;
const #65 = Asciz	n;
const #66 = Asciz	I;
const #67 = Asciz	(I)Lscala/collection/Traversable;;
const #68 = Asciz	drop;
const #69 = NameAndType	#68:#62;//  drop:(I)Lscala/collection/TraversableLike;
const #70 = InterfaceMethod	#38.#69;	//  scala/collection/TraversableProxyLike.drop:(I)Lscala/collection/TraversableLike;
const #71 = Asciz	slice;
const #72 = Asciz	(II)Ljava/lang/Object;;
const #73 = Asciz	(II)Lscala/collection/TraversableLike;;
const #74 = NameAndType	#71:#73;//  slice:(II)Lscala/collection/TraversableLike;
const #75 = InterfaceMethod	#38.#74;	//  scala/collection/TraversableProxyLike.slice:(II)Lscala/collection/TraversableLike;
const #76 = Asciz	from;
const #77 = Asciz	until;
const #78 = Asciz	(II)Lscala/collection/Traversable;;
const #79 = Asciz	takeWhile;
const #80 = NameAndType	#79:#39;//  takeWhile:(Lscala/Function1;)Lscala/collection/TraversableLike;
const #81 = InterfaceMethod	#38.#80;	//  scala/collection/TraversableProxyLike.takeWhile:(Lscala/Function1;)Lscala/collection/TraversableLike;
const #82 = Asciz	dropWhile;
const #83 = NameAndType	#82:#39;//  dropWhile:(Lscala/Function1;)Lscala/collection/TraversableLike;
const #84 = InterfaceMethod	#38.#83;	//  scala/collection/TraversableProxyLike.dropWhile:(Lscala/Function1;)Lscala/collection/TraversableLike;
const #85 = Asciz	view;
const #86 = Asciz	()Lscala/collection/TraversableView;;
const #87 = NameAndType	#85:#29;//  view:()Ljava/lang/Object;
const #88 = InterfaceMethod	#38.#87;	//  scala/collection/TraversableProxyLike.view:()Ljava/lang/Object;
const #89 = Asciz	scala/collection/TraversableView;
const #90 = class	#89;	//  scala/collection/TraversableView
const #91 = Asciz	newBuilder;
const #92 = Asciz	()Lscala/collection/mutable/Builder;;
const #93 = Asciz	scala/collection/Traversable$;
const #94 = class	#93;	//  scala/collection/Traversable$
const #95 = Asciz	MODULE$;
const #96 = Asciz	Lscala/collection/Traversable$;;
const #97 = NameAndType	#95:#96;//  MODULE$:Lscala/collection/Traversable$;
const #98 = Field	#94.#97;	//  scala/collection/Traversable$.MODULE$:Lscala/collection/Traversable$;
const #99 = NameAndType	#91:#92;//  newBuilder:()Lscala/collection/mutable/Builder;
const #100 = Method	#94.#99;	//  scala/collection/Traversable$.newBuilder:()Lscala/collection/mutable/Builder;
const #101 = Asciz	()Lscala/collection/mutable/Builder<TA;Lscala/collection/Traversable<TA;>;>;;
const #102 = Asciz	scala/collection/TraversableLike;
const #103 = class	#102;	//  scala/collection/TraversableLike
const #104 = Asciz	repr;
const #105 = NameAndType	#104:#29;//  repr:()Ljava/lang/Object;
const #106 = InterfaceMethod	#103.#105;	//  scala/collection/TraversableLike.repr:()Ljava/lang/Object;
const #107 = Asciz	()TThis;;
const #108 = Asciz	withFilter;
const #109 = Asciz	(Lscala/Function1;)Lscala/collection/TraversableLike$WithFilter;;
const #110 = Asciz	(Lscala/collection/TraversableLike;Lscala/Function1;)Lscala/collection/TraversableLike$WithFilter;;
const #111 = NameAndType	#108:#110;//  withFilter:(Lscala/collection/TraversableLike;Lscala/Function1;)Lscala/collection/TraversableLike$WithFilter;
const #112 = Method	#12.#111;	//  scala/collection/TraversableLike$class.withFilter:(Lscala/collection/TraversableLike;Lscala/Function1;)Lscala/collection/TraversableLike$WithFilter;
const #113 = Asciz	toIndexedSeq;
const #114 = Asciz	()Lscala/collection/mutable/IndexedSeq;;
const #115 = Asciz	(Lscala/collection/TraversableLike;)Lscala/collection/mutable/IndexedSeq;;
const #116 = NameAndType	#113:#115;//  toIndexedSeq:(Lscala/collection/TraversableLike;)Lscala/collection/mutable/IndexedSeq;
const #117 = Method	#12.#116;	//  scala/collection/TraversableLike$class.toIndexedSeq:(Lscala/collection/TraversableLike;)Lscala/collection/mutable/IndexedSeq;
const #118 = Asciz	copyToArray;
const #119 = Asciz	(Ljava/lang/Object;)V;
const #120 = Asciz	(Lscala/collection/TraversableLike;Ljava/lang/Object;)V;
const #121 = NameAndType	#118:#120;//  copyToArray:(Lscala/collection/TraversableLike;Ljava/lang/Object;)V
const #122 = Method	#12.#121;	//  scala/collection/TraversableLike$class.copyToArray:(Lscala/collection/TraversableLike;Ljava/lang/Object;)V
const #123 = Asciz	xs;
const #124 = Asciz	Ljava/lang/Object;;
const #125 = Asciz	max;
const #126 = Asciz	(Lscala/math/Ordering;)Ljava/lang/Object;;
const #127 = Asciz	(Lscala/collection/TraversableLike;Lscala/math/Ordering;)Ljava/lang/Object;;
const #128 = NameAndType	#125:#127;//  max:(Lscala/collection/TraversableLike;Lscala/math/Ordering;)Ljava/lang/Object;
const #129 = Method	#12.#128;	//  scala/collection/TraversableLike$class.max:(Lscala/collection/TraversableLike;Lscala/math/Ordering;)Ljava/lang/Object;
const #130 = Asciz	cmp;
const #131 = Asciz	Lscala/math/Ordering;;
const #132 = Asciz	min;
const #133 = NameAndType	#132:#127;//  min:(Lscala/collection/TraversableLike;Lscala/math/Ordering;)Ljava/lang/Object;
const #134 = Method	#12.#133;	//  scala/collection/TraversableLike$class.min:(Lscala/collection/TraversableLike;Lscala/math/Ordering;)Ljava/lang/Object;
const #135 = Asciz	product;
const #136 = Asciz	(Lscala/math/Numeric;)Ljava/lang/Object;;
const #137 = Asciz	(Lscala/collection/TraversableLike;Lscala/math/Numeric;)Ljava/lang/Object;;
const #138 = NameAndType	#135:#137;//  product:(Lscala/collection/TraversableLike;Lscala/math/Numeric;)Ljava/lang/Object;
const #139 = Method	#12.#138;	//  scala/collection/TraversableLike$class.product:(Lscala/collection/TraversableLike;Lscala/math/Numeric;)Ljava/lang/Object;
const #140 = Asciz	num;
const #141 = Asciz	Lscala/math/Numeric;;
const #142 = Asciz	sum;
const #143 = NameAndType	#142:#137;//  sum:(Lscala/collection/TraversableLike;Lscala/math/Numeric;)Ljava/lang/Object;
const #144 = Method	#12.#143;	//  scala/collection/TraversableLike$class.sum:(Lscala/collection/TraversableLike;Lscala/math/Numeric;)Ljava/lang/Object;
const #145 = Asciz	toCollection;
const #146 = Asciz	(Ljava/lang/Object;)Lscala/collection/Traversable;;
const #147 = Asciz	(Lscala/collection/TraversableLike;Ljava/lang/Object;)Lscala/collection/Traversable;;
const #148 = NameAndType	#145:#147;//  toCollection:(Lscala/collection/TraversableLike;Ljava/lang/Object;)Lscala/collection/Traversable;
const #149 = Method	#12.#148;	//  scala/collection/TraversableLike$class.toCollection:(Lscala/collection/TraversableLike;Ljava/lang/Object;)Lscala/collection/Traversable;
const #150 = Asciz	thisCollection;
const #151 = Asciz	(Lscala/collection/TraversableLike;)Lscala/collection/Traversable;;
const #152 = NameAndType	#150:#151;//  thisCollection:(Lscala/collection/TraversableLike;)Lscala/collection/Traversable;
const #153 = Method	#12.#152;	//  scala/collection/TraversableLike$class.thisCollection:(Lscala/collection/TraversableLike;)Lscala/collection/Traversable;
const #154 = Asciz	(Lscala/collection/TraversableLike;)Ljava/lang/Object;;
const #155 = NameAndType	#104:#154;//  repr:(Lscala/collection/TraversableLike;)Ljava/lang/Object;
const #156 = Method	#12.#155;	//  scala/collection/TraversableLike$class.repr:(Lscala/collection/TraversableLike;)Ljava/lang/Object;
const #157 = Asciz	toString;
const #158 = Asciz	()Ljava/lang/String;;
const #159 = Asciz	(Lscala/Proxy;)Ljava/lang/String;;
const #160 = NameAndType	#157:#159;//  toString:(Lscala/Proxy;)Ljava/lang/String;
const #161 = Method	#18.#160;	//  scala/Proxy$class.toString:(Lscala/Proxy;)Ljava/lang/String;
const #162 = Asciz	equals;
const #163 = Asciz	(Ljava/lang/Object;)Z;
const #164 = Asciz	(Lscala/Proxy;Ljava/lang/Object;)Z;
const #165 = NameAndType	#162:#164;//  equals:(Lscala/Proxy;Ljava/lang/Object;)Z
const #166 = Method	#18.#165;	//  scala/Proxy$class.equals:(Lscala/Proxy;Ljava/lang/Object;)Z
const #167 = Asciz	that;
const #168 = Asciz	hashCode;
const #169 = Asciz	()I;
const #170 = Asciz	(Lscala/Proxy;)I;
const #171 = NameAndType	#168:#170;//  hashCode:(Lscala/Proxy;)I
const #172 = Method	#18.#171;	//  scala/Proxy$class.hashCode:(Lscala/Proxy;)I
const #173 = Asciz	(II)Lscala/collection/TraversableView;;
const #174 = Asciz	(Lscala/collection/TraversableProxyLike;II)Lscala/collection/TraversableView;;
const #175 = NameAndType	#85:#174;//  view:(Lscala/collection/TraversableProxyLike;II)Lscala/collection/TraversableView;
const #176 = Method	#23.#175;	//  scala/collection/TraversableProxyLike$class.view:(Lscala/collection/TraversableProxyLike;II)Lscala/collection/TraversableView;
const #177 = Asciz	(Lscala/collection/TraversableProxyLike;)Ljava/lang/Object;;
const #178 = NameAndType	#85:#177;//  view:(Lscala/collection/TraversableProxyLike;)Ljava/lang/Object;
const #179 = Method	#23.#178;	//  scala/collection/TraversableProxyLike$class.view:(Lscala/collection/TraversableProxyLike;)Ljava/lang/Object;
const #180 = Asciz	stringPrefix;
const #181 = Asciz	(Lscala/collection/TraversableProxyLike;)Ljava/lang/String;;
const #182 = NameAndType	#180:#181;//  stringPrefix:(Lscala/collection/TraversableProxyLike;)Ljava/lang/String;
const #183 = Method	#23.#182;	//  scala/collection/TraversableProxyLike$class.stringPrefix:(Lscala/collection/TraversableProxyLike;)Ljava/lang/String;
const #184 = Asciz	addString;
const #185 = Asciz	(Lscala/collection/mutable/StringBuilder;)Lscala/collection/mutable/StringBuilder;;
const #186 = Asciz	(Lscala/collection/TraversableProxyLike;Lscala/collection/mutable/StringBuilder;)Lscala/collection/mutable/StringBuilder;;
const #187 = NameAndType	#184:#186;//  addString:(Lscala/collection/TraversableProxyLike;Lscala/collection/mutable/StringBuilder;)Lscala/collection/mutable/StringBuilder;
const #188 = Method	#23.#187;	//  scala/collection/TraversableProxyLike$class.addString:(Lscala/collection/TraversableProxyLike;Lscala/collection/mutable/StringBuilder;)Lscala/collection/mutable/StringBuilder;
const #189 = Asciz	b;
const #190 = Asciz	Lscala/collection/mutable/StringBuilder;;
const #191 = Asciz	(Lscala/collection/mutable/StringBuilder;Ljava/lang/String;)Lscala/collection/mutable/StringBuilder;;
const #192 = Asciz	(Lscala/collection/TraversableProxyLike;Lscala/collection/mutable/StringBuilder;Ljava/lang/String;)Lscala/collection/mutable/StringBuilder;;
const #193 = NameAndType	#184:#192;//  addString:(Lscala/collection/TraversableProxyLike;Lscala/collection/mutable/StringBuilder;Ljava/lang/String;)Lscala/collection/mutable/StringBuilder;
const #194 = Method	#23.#193;	//  scala/collection/TraversableProxyLike$class.addString:(Lscala/collection/TraversableProxyLike;Lscala/collection/mutable/StringBuilder;Ljava/lang/String;)Lscala/collection/mutable/StringBuilder;
const #195 = Asciz	sep;
const #196 = Asciz	Ljava/lang/String;;
const #197 = Asciz	(Lscala/collection/mutable/StringBuilder;Ljava/lang/String;Ljava/lang/String;Ljava/lang/String;)Lscala/collection/mutable/StringBuilder;;
const #198 = Asciz	(Lscala/collection/TraversableProxyLike;Lscala/collection/mutable/StringBuilder;Ljava/lang/String;Ljava/lang/String;Ljava/lang/String;)Lscala/collection/mutable/StringBuilder;;
const #199 = NameAndType	#184:#198;//  addString:(Lscala/collection/TraversableProxyLike;Lscala/collection/mutable/StringBuilder;Ljava/lang/String;Ljava/lang/String;Ljava/lang/String;)Lscala/collection/mutable/StringBuilder;
const #200 = Method	#23.#199;	//  scala/collection/TraversableProxyLike$class.addString:(Lscala/collection/TraversableProxyLike;Lscala/collection/mutable/StringBuilder;Ljava/lang/String;Ljava/lang/String;Ljava/lang/String;)Lscala/collection/mutable/StringBuilder;
const #201 = Asciz	start;
const #202 = Asciz	end;
const #203 = Asciz	mkString;
const #204 = NameAndType	#203:#181;//  mkString:(Lscala/collection/TraversableProxyLike;)Ljava/lang/String;
const #205 = Method	#23.#204;	//  scala/collection/TraversableProxyLike$class.mkString:(Lscala/collection/TraversableProxyLike;)Ljava/lang/String;
const #206 = Asciz	(Ljava/lang/String;)Ljava/lang/String;;
const #207 = Asciz	(Lscala/collection/TraversableProxyLike;Ljava/lang/String;)Ljava/lang/String;;
const #208 = NameAndType	#203:#207;//  mkString:(Lscala/collection/TraversableProxyLike;Ljava/lang/String;)Ljava/lang/String;
const #209 = Method	#23.#208;	//  scala/collection/TraversableProxyLike$class.mkString:(Lscala/collection/TraversableProxyLike;Ljava/lang/String;)Ljava/lang/String;
const #210 = Asciz	(Ljava/lang/String;Ljava/lang/String;Ljava/lang/String;)Ljava/lang/String;;
const #211 = Asciz	(Lscala/collection/TraversableProxyLike;Ljava/lang/String;Ljava/lang/String;Ljava/lang/String;)Ljava/lang/String;;
const #212 = NameAndType	#203:#211;//  mkString:(Lscala/collection/TraversableProxyLike;Ljava/lang/String;Ljava/lang/String;Ljava/lang/String;)Ljava/lang/String;
const #213 = Method	#23.#212;	//  scala/collection/TraversableProxyLike$class.mkString:(Lscala/collection/TraversableProxyLike;Ljava/lang/String;Ljava/lang/String;Ljava/lang/String;)Ljava/lang/String;
const #214 = Asciz	toSet;
const #215 = Asciz	()Lscala/collection/immutable/Set;;
const #216 = Asciz	(Lscala/collection/TraversableProxyLike;)Lscala/collection/immutable/Set;;
const #217 = NameAndType	#214:#216;//  toSet:(Lscala/collection/TraversableProxyLike;)Lscala/collection/immutable/Set;
const #218 = Method	#23.#217;	//  scala/collection/TraversableProxyLike$class.toSet:(Lscala/collection/TraversableProxyLike;)Lscala/collection/immutable/Set;
const #219 = Asciz	toStream;
const #220 = Asciz	()Lscala/collection/immutable/Stream;;
const #221 = Asciz	(Lscala/collection/TraversableProxyLike;)Lscala/collection/immutable/Stream;;
const #222 = NameAndType	#219:#221;//  toStream:(Lscala/collection/TraversableProxyLike;)Lscala/collection/immutable/Stream;
const #223 = Method	#23.#222;	//  scala/collection/TraversableProxyLike$class.toStream:(Lscala/collection/TraversableProxyLike;)Lscala/collection/immutable/Stream;
const #224 = Asciz	toSeq;
const #225 = Asciz	()Lscala/collection/Seq;;
const #226 = Asciz	(Lscala/collection/TraversableProxyLike;)Lscala/collection/Seq;;
const #227 = NameAndType	#224:#226;//  toSeq:(Lscala/collection/TraversableProxyLike;)Lscala/collection/Seq;
const #228 = Method	#23.#227;	//  scala/collection/TraversableProxyLike$class.toSeq:(Lscala/collection/TraversableProxyLike;)Lscala/collection/Seq;
const #229 = Asciz	toIterable;
const #230 = Asciz	()Lscala/collection/Iterable;;
const #231 = Asciz	(Lscala/collection/TraversableProxyLike;)Lscala/collection/Iterable;;
const #232 = NameAndType	#229:#231;//  toIterable:(Lscala/collection/TraversableProxyLike;)Lscala/collection/Iterable;
const #233 = Method	#23.#232;	//  scala/collection/TraversableProxyLike$class.toIterable:(Lscala/collection/TraversableProxyLike;)Lscala/collection/Iterable;
const #234 = Asciz	toList;
const #235 = Asciz	()Lscala/collection/immutable/List;;
const #236 = Asciz	(Lscala/collection/TraversableProxyLike;)Lscala/collection/immutable/List;;
const #237 = NameAndType	#234:#236;//  toList:(Lscala/collection/TraversableProxyLike;)Lscala/collection/immutable/List;
const #238 = Method	#23.#237;	//  scala/collection/TraversableProxyLike$class.toList:(Lscala/collection/TraversableProxyLike;)Lscala/collection/immutable/List;
const #239 = Asciz	toArray;
const #240 = Asciz	(Lscala/reflect/ClassManifest;)Ljava/lang/Object;;
const #241 = Asciz	(Lscala/collection/TraversableProxyLike;Lscala/reflect/ClassManifest;)Ljava/lang/Object;;
const #242 = NameAndType	#239:#241;//  toArray:(Lscala/collection/TraversableProxyLike;Lscala/reflect/ClassManifest;)Ljava/lang/Object;
const #243 = Method	#23.#242;	//  scala/collection/TraversableProxyLike$class.toArray:(Lscala/collection/TraversableProxyLike;Lscala/reflect/ClassManifest;)Ljava/lang/Object;
const #244 = Asciz	evidence$1;
const #245 = Asciz	Lscala/reflect/ClassManifest;;
const #246 = Asciz	(Ljava/lang/Object;I)V;
const #247 = Asciz	(Lscala/collection/TraversableProxyLike;Ljava/lang/Object;I)V;
const #248 = NameAndType	#118:#247;//  copyToArray:(Lscala/collection/TraversableProxyLike;Ljava/lang/Object;I)V
const #249 = Method	#23.#248;	//  scala/collection/TraversableProxyLike$class.copyToArray:(Lscala/collection/TraversableProxyLike;Ljava/lang/Object;I)V
const #250 = Asciz	(Ljava/lang/Object;II)V;
const #251 = Asciz	(Lscala/collection/TraversableProxyLike;Ljava/lang/Object;II)V;
const #252 = NameAndType	#118:#251;//  copyToArray:(Lscala/collection/TraversableProxyLike;Ljava/lang/Object;II)V
const #253 = Method	#23.#252;	//  scala/collection/TraversableProxyLike$class.copyToArray:(Lscala/collection/TraversableProxyLike;Ljava/lang/Object;II)V
const #254 = Asciz	len;
const #255 = Asciz	copyToBuffer;
const #256 = Asciz	(Lscala/collection/mutable/Buffer;)V;
const #257 = Asciz	(Lscala/collection/TraversableProxyLike;Lscala/collection/mutable/Buffer;)V;
const #258 = NameAndType	#255:#257;//  copyToBuffer:(Lscala/collection/TraversableProxyLike;Lscala/collection/mutable/Buffer;)V
const #259 = Method	#23.#258;	//  scala/collection/TraversableProxyLike$class.copyToBuffer:(Lscala/collection/TraversableProxyLike;Lscala/collection/mutable/Buffer;)V
const #260 = Asciz	dest;
const #261 = Asciz	Lscala/collection/mutable/Buffer;;
const #262 = Asciz	splitAt;
const #263 = Asciz	(I)Lscala/Tuple2;;
const #264 = Asciz	(Lscala/collection/TraversableProxyLike;I)Lscala/Tuple2;;
const #265 = NameAndType	#262:#264;//  splitAt:(Lscala/collection/TraversableProxyLike;I)Lscala/Tuple2;
const #266 = Method	#23.#265;	//  scala/collection/TraversableProxyLike$class.splitAt:(Lscala/collection/TraversableProxyLike;I)Lscala/Tuple2;
const #267 = Asciz	span;
const #268 = Asciz	(Lscala/Function1;)Lscala/Tuple2;;
const #269 = Asciz	(Lscala/collection/TraversableProxyLike;Lscala/Function1;)Lscala/Tuple2;;
const #270 = NameAndType	#267:#269;//  span:(Lscala/collection/TraversableProxyLike;Lscala/Function1;)Lscala/Tuple2;
const #271 = Method	#23.#270;	//  scala/collection/TraversableProxyLike$class.span:(Lscala/collection/TraversableProxyLike;Lscala/Function1;)Lscala/Tuple2;
const #272 = Asciz	(Lscala/collection/TraversableProxyLike;Lscala/Function1;)Lscala/collection/TraversableLike;;
const #273 = NameAndType	#82:#272;//  dropWhile:(Lscala/collection/TraversableProxyLike;Lscala/Function1;)Lscala/collection/TraversableLike;
const #274 = Method	#23.#273;	//  scala/collection/TraversableProxyLike$class.dropWhile:(Lscala/collection/TraversableProxyLike;Lscala/Function1;)Lscala/collection/TraversableLike;
const #275 = NameAndType	#79:#272;//  takeWhile:(Lscala/collection/TraversableProxyLike;Lscala/Function1;)Lscala/collection/TraversableLike;
const #276 = Method	#23.#275;	//  scala/collection/TraversableProxyLike$class.takeWhile:(Lscala/collection/TraversableProxyLike;Lscala/Function1;)Lscala/collection/TraversableLike;
const #277 = Asciz	(Lscala/collection/TraversableProxyLike;II)Lscala/collection/TraversableLike;;
const #278 = NameAndType	#71:#277;//  slice:(Lscala/collection/TraversableProxyLike;II)Lscala/collection/TraversableLike;
const #279 = Method	#23.#278;	//  scala/collection/TraversableProxyLike$class.slice:(Lscala/collection/TraversableProxyLike;II)Lscala/collection/TraversableLike;
const #280 = Asciz	(Lscala/collection/TraversableProxyLike;I)Lscala/collection/TraversableLike;;
const #281 = NameAndType	#68:#280;//  drop:(Lscala/collection/TraversableProxyLike;I)Lscala/collection/TraversableLike;
const #282 = Method	#23.#281;	//  scala/collection/TraversableProxyLike$class.drop:(Lscala/collection/TraversableProxyLike;I)Lscala/collection/TraversableLike;
const #283 = NameAndType	#60:#280;//  take:(Lscala/collection/TraversableProxyLike;I)Lscala/collection/TraversableLike;
const #284 = Method	#23.#283;	//  scala/collection/TraversableProxyLike$class.take:(Lscala/collection/TraversableProxyLike;I)Lscala/collection/TraversableLike;
const #285 = Asciz	(Lscala/collection/TraversableProxyLike;)Lscala/collection/TraversableLike;;
const #286 = NameAndType	#57:#285;//  init:(Lscala/collection/TraversableProxyLike;)Lscala/collection/TraversableLike;
const #287 = Method	#23.#286;	//  scala/collection/TraversableProxyLike$class.init:(Lscala/collection/TraversableProxyLike;)Lscala/collection/TraversableLike;
const #288 = Asciz	lastOption;
const #289 = Asciz	()Lscala/Option;;
const #290 = Asciz	(Lscala/collection/TraversableProxyLike;)Lscala/Option;;
const #291 = NameAndType	#288:#290;//  lastOption:(Lscala/collection/TraversableProxyLike;)Lscala/Option;
const #292 = Method	#23.#291;	//  scala/collection/TraversableProxyLike$class.lastOption:(Lscala/collection/TraversableProxyLike;)Lscala/Option;
const #293 = Asciz	last;
const #294 = NameAndType	#293:#177;//  last:(Lscala/collection/TraversableProxyLike;)Ljava/lang/Object;
const #295 = Method	#23.#294;	//  scala/collection/TraversableProxyLike$class.last:(Lscala/collection/TraversableProxyLike;)Ljava/lang/Object;
const #296 = NameAndType	#53:#285;//  tail:(Lscala/collection/TraversableProxyLike;)Lscala/collection/TraversableLike;
const #297 = Method	#23.#296;	//  scala/collection/TraversableProxyLike$class.tail:(Lscala/collection/TraversableProxyLike;)Lscala/collection/TraversableLike;
const #298 = Asciz	headOption;
const #299 = NameAndType	#298:#290;//  headOption:(Lscala/collection/TraversableProxyLike;)Lscala/Option;
const #300 = Method	#23.#299;	//  scala/collection/TraversableProxyLike$class.headOption:(Lscala/collection/TraversableProxyLike;)Lscala/Option;
const #301 = Asciz	head;
const #302 = NameAndType	#301:#177;//  head:(Lscala/collection/TraversableProxyLike;)Ljava/lang/Object;
const #303 = Method	#23.#302;	//  scala/collection/TraversableProxyLike$class.head:(Lscala/collection/TraversableProxyLike;)Ljava/lang/Object;
const #304 = Asciz	reduceRightOption;
const #305 = Asciz	(Lscala/Function2;)Lscala/Option;;
const #306 = Asciz	(Lscala/collection/TraversableProxyLike;Lscala/Function2;)Lscala/Option;;
const #307 = NameAndType	#304:#306;//  reduceRightOption:(Lscala/collection/TraversableProxyLike;Lscala/Function2;)Lscala/Option;
const #308 = Method	#23.#307;	//  scala/collection/TraversableProxyLike$class.reduceRightOption:(Lscala/collection/TraversableProxyLike;Lscala/Function2;)Lscala/Option;
const #309 = Asciz	op;
const #310 = Asciz	Lscala/Function2;;
const #311 = Asciz	reduceRight;
const #312 = Asciz	(Lscala/Function2;)Ljava/lang/Object;;
const #313 = Asciz	(Lscala/collection/TraversableProxyLike;Lscala/Function2;)Ljava/lang/Object;;
const #314 = NameAndType	#311:#313;//  reduceRight:(Lscala/collection/TraversableProxyLike;Lscala/Function2;)Ljava/lang/Object;
const #315 = Method	#23.#314;	//  scala/collection/TraversableProxyLike$class.reduceRight:(Lscala/collection/TraversableProxyLike;Lscala/Function2;)Ljava/lang/Object;
const #316 = Asciz	reduceLeftOption;
const #317 = NameAndType	#316:#306;//  reduceLeftOption:(Lscala/collection/TraversableProxyLike;Lscala/Function2;)Lscala/Option;
const #318 = Method	#23.#317;	//  scala/collection/TraversableProxyLike$class.reduceLeftOption:(Lscala/collection/TraversableProxyLike;Lscala/Function2;)Lscala/Option;
const #319 = Asciz	reduceLeft;
const #320 = NameAndType	#319:#313;//  reduceLeft:(Lscala/collection/TraversableProxyLike;Lscala/Function2;)Ljava/lang/Object;
const #321 = Method	#23.#320;	//  scala/collection/TraversableProxyLike$class.reduceLeft:(Lscala/collection/TraversableProxyLike;Lscala/Function2;)Ljava/lang/Object;
const #322 = Asciz	$colon$bslash;
const #323 = Asciz	(Ljava/lang/Object;Lscala/Function2;)Ljava/lang/Object;;
const #324 = Asciz	(Lscala/collection/TraversableProxyLike;Ljava/lang/Object;Lscala/Function2;)Ljava/lang/Object;;
const #325 = NameAndType	#322:#324;//  $colon$bslash:(Lscala/collection/TraversableProxyLike;Ljava/lang/Object;Lscala/Function2;)Ljava/lang/Object;
const #326 = Method	#23.#325;	//  scala/collection/TraversableProxyLike$class.$colon$bslash:(Lscala/collection/TraversableProxyLike;Ljava/lang/Object;Lscala/Function2;)Ljava/lang/Object;
const #327 = Asciz	z;
const #328 = Asciz	foldRight;
const #329 = NameAndType	#328:#324;//  foldRight:(Lscala/collection/TraversableProxyLike;Ljava/lang/Object;Lscala/Function2;)Ljava/lang/Object;
const #330 = Method	#23.#329;	//  scala/collection/TraversableProxyLike$class.foldRight:(Lscala/collection/TraversableProxyLike;Ljava/lang/Object;Lscala/Function2;)Ljava/lang/Object;
const #331 = Asciz	$div$colon;
const #332 = NameAndType	#331:#324;//  $div$colon:(Lscala/collection/TraversableProxyLike;Ljava/lang/Object;Lscala/Function2;)Ljava/lang/Object;
const #333 = Method	#23.#332;	//  scala/collection/TraversableProxyLike$class.$div$colon:(Lscala/collection/TraversableProxyLike;Ljava/lang/Object;Lscala/Function2;)Ljava/lang/Object;
const #334 = Asciz	foldLeft;
const #335 = NameAndType	#334:#324;//  foldLeft:(Lscala/collection/TraversableProxyLike;Ljava/lang/Object;Lscala/Function2;)Ljava/lang/Object;
const #336 = Method	#23.#335;	//  scala/collection/TraversableProxyLike$class.foldLeft:(Lscala/collection/TraversableProxyLike;Ljava/lang/Object;Lscala/Function2;)Ljava/lang/Object;
const #337 = Asciz	find;
const #338 = Asciz	(Lscala/Function1;)Lscala/Option;;
const #339 = Asciz	(Lscala/collection/TraversableProxyLike;Lscala/Function1;)Lscala/Option;;
const #340 = NameAndType	#337:#339;//  find:(Lscala/collection/TraversableProxyLike;Lscala/Function1;)Lscala/Option;
const #341 = Method	#23.#340;	//  scala/collection/TraversableProxyLike$class.find:(Lscala/collection/TraversableProxyLike;Lscala/Function1;)Lscala/Option;
const #342 = Asciz	count;
const #343 = Asciz	(Lscala/Function1;)I;
const #344 = Asciz	(Lscala/collection/TraversableProxyLike;Lscala/Function1;)I;
const #345 = NameAndType	#342:#344;//  count:(Lscala/collection/TraversableProxyLike;Lscala/Function1;)I
const #346 = Method	#23.#345;	//  scala/collection/TraversableProxyLike$class.count:(Lscala/collection/TraversableProxyLike;Lscala/Function1;)I
const #347 = Asciz	exists;
const #348 = Asciz	(Lscala/Function1;)Z;
const #349 = Asciz	(Lscala/collection/TraversableProxyLike;Lscala/Function1;)Z;
const #350 = NameAndType	#347:#349;//  exists:(Lscala/collection/TraversableProxyLike;Lscala/Function1;)Z
const #351 = Method	#23.#350;	//  scala/collection/TraversableProxyLike$class.exists:(Lscala/collection/TraversableProxyLike;Lscala/Function1;)Z
const #352 = Asciz	forall;
const #353 = NameAndType	#352:#349;//  forall:(Lscala/collection/TraversableProxyLike;Lscala/Function1;)Z
const #354 = Method	#23.#353;	//  scala/collection/TraversableProxyLike$class.forall:(Lscala/collection/TraversableProxyLike;Lscala/Function1;)Z
const #355 = Asciz	groupBy;
const #356 = Asciz	(Lscala/Function1;)Lscala/collection/Map;;
const #357 = Asciz	(Lscala/collection/TraversableProxyLike;Lscala/Function1;)Lscala/collection/Map;;
const #358 = NameAndType	#355:#357;//  groupBy:(Lscala/collection/TraversableProxyLike;Lscala/Function1;)Lscala/collection/Map;
const #359 = Method	#23.#358;	//  scala/collection/TraversableProxyLike$class.groupBy:(Lscala/collection/TraversableProxyLike;Lscala/Function1;)Lscala/collection/Map;
const #360 = Asciz	f;
const #361 = Asciz	partition;
const #362 = NameAndType	#361:#269;//  partition:(Lscala/collection/TraversableProxyLike;Lscala/Function1;)Lscala/Tuple2;
const #363 = Method	#23.#362;	//  scala/collection/TraversableProxyLike$class.partition:(Lscala/collection/TraversableProxyLike;Lscala/Function1;)Lscala/Tuple2;
const #364 = NameAndType	#50:#272;//  filterNot:(Lscala/collection/TraversableProxyLike;Lscala/Function1;)Lscala/collection/TraversableLike;
const #365 = Method	#23.#364;	//  scala/collection/TraversableProxyLike$class.filterNot:(Lscala/collection/TraversableProxyLike;Lscala/Function1;)Lscala/collection/TraversableLike;
const #366 = NameAndType	#35:#272;//  filter:(Lscala/collection/TraversableProxyLike;Lscala/Function1;)Lscala/collection/TraversableLike;
const #367 = Method	#23.#366;	//  scala/collection/TraversableProxyLike$class.filter:(Lscala/collection/TraversableProxyLike;Lscala/Function1;)Lscala/collection/TraversableLike;
const #368 = Asciz	partialMap;
const #369 = Asciz	(Lscala/PartialFunction;Lscala/collection/generic/CanBuildFrom;)Ljava/lang/Object;;
const #370 = Asciz	(Lscala/collection/TraversableProxyLike;Lscala/PartialFunction;Lscala/collection/generic/CanBuildFrom;)Ljava/lang/Object;;
const #371 = NameAndType	#368:#370;//  partialMap:(Lscala/collection/TraversableProxyLike;Lscala/PartialFunction;Lscala/collection/generic/CanBuildFrom;)Ljava/lang/Object;
const #372 = Method	#23.#371;	//  scala/collection/TraversableProxyLike$class.partialMap:(Lscala/collection/TraversableProxyLike;Lscala/PartialFunction;Lscala/collection/generic/CanBuildFrom;)Ljava/lang/Object;
const #373 = Asciz	pf;
const #374 = Asciz	Lscala/PartialFunction;;
const #375 = Asciz	bf;
const #376 = Asciz	Lscala/collection/generic/CanBuildFrom;;
const #377 = Asciz	flatMap;
const #378 = Asciz	(Lscala/Function1;Lscala/collection/generic/CanBuildFrom;)Ljava/lang/Object;;
const #379 = Asciz	(Lscala/collection/TraversableProxyLike;Lscala/Function1;Lscala/collection/generic/CanBuildFrom;)Ljava/lang/Object;;
const #380 = NameAndType	#377:#379;//  flatMap:(Lscala/collection/TraversableProxyLike;Lscala/Function1;Lscala/collection/generic/CanBuildFrom;)Ljava/lang/Object;
const #381 = Method	#23.#380;	//  scala/collection/TraversableProxyLike$class.flatMap:(Lscala/collection/TraversableProxyLike;Lscala/Function1;Lscala/collection/generic/CanBuildFrom;)Ljava/lang/Object;
const #382 = Asciz	map;
const #383 = NameAndType	#382:#379;//  map:(Lscala/collection/TraversableProxyLike;Lscala/Function1;Lscala/collection/generic/CanBuildFrom;)Ljava/lang/Object;
const #384 = Method	#23.#383;	//  scala/collection/TraversableProxyLike$class.map:(Lscala/collection/TraversableProxyLike;Lscala/Function1;Lscala/collection/generic/CanBuildFrom;)Ljava/lang/Object;
const #385 = Asciz	$plus$plus;
const #386 = Asciz	(Lscala/collection/Iterator;Lscala/collection/generic/CanBuildFrom;)Ljava/lang/Object;;
const #387 = Asciz	(Lscala/collection/TraversableProxyLike;Lscala/collection/Iterator;Lscala/collection/generic/CanBuildFrom;)Ljava/lang/Object;;
const #388 = NameAndType	#385:#387;//  $plus$plus:(Lscala/collection/TraversableProxyLike;Lscala/collection/Iterator;Lscala/collection/generic/CanBuildFrom;)Ljava/lang/Object;
const #389 = Method	#23.#388;	//  scala/collection/TraversableProxyLike$class.$plus$plus:(Lscala/collection/TraversableProxyLike;Lscala/collection/Iterator;Lscala/collection/generic/CanBuildFrom;)Ljava/lang/Object;
const #390 = Asciz	Lscala/collection/Iterator;;
const #391 = Asciz	(Lscala/collection/Traversable;Lscala/collection/generic/CanBuildFrom;)Ljava/lang/Object;;
const #392 = Asciz	(Lscala/collection/TraversableProxyLike;Lscala/collection/Traversable;Lscala/collection/generic/CanBuildFrom;)Ljava/lang/Object;;
const #393 = NameAndType	#385:#392;//  $plus$plus:(Lscala/collection/TraversableProxyLike;Lscala/collection/Traversable;Lscala/collection/generic/CanBuildFrom;)Ljava/lang/Object;
const #394 = Method	#23.#393;	//  scala/collection/TraversableProxyLike$class.$plus$plus:(Lscala/collection/TraversableProxyLike;Lscala/collection/Traversable;Lscala/collection/generic/CanBuildFrom;)Ljava/lang/Object;
const #395 = Asciz	Lscala/collection/Traversable;;
const #396 = Asciz	hasDefiniteSize;
const #397 = Asciz	()Z;
const #398 = Asciz	(Lscala/collection/TraversableProxyLike;)Z;
const #399 = NameAndType	#396:#398;//  hasDefiniteSize:(Lscala/collection/TraversableProxyLike;)Z
const #400 = Method	#23.#399;	//  scala/collection/TraversableProxyLike$class.hasDefiniteSize:(Lscala/collection/TraversableProxyLike;)Z
const #401 = Asciz	size;
const #402 = Asciz	(Lscala/collection/TraversableProxyLike;)I;
const #403 = NameAndType	#401:#402;//  size:(Lscala/collection/TraversableProxyLike;)I
const #404 = Method	#23.#403;	//  scala/collection/TraversableProxyLike$class.size:(Lscala/collection/TraversableProxyLike;)I
const #405 = Asciz	nonEmpty;
const #406 = NameAndType	#405:#398;//  nonEmpty:(Lscala/collection/TraversableProxyLike;)Z
const #407 = Method	#23.#406;	//  scala/collection/TraversableProxyLike$class.nonEmpty:(Lscala/collection/TraversableProxyLike;)Z
const #408 = Asciz	isEmpty;
const #409 = NameAndType	#408:#398;//  isEmpty:(Lscala/collection/TraversableProxyLike;)Z
const #410 = Method	#23.#409;	//  scala/collection/TraversableProxyLike$class.isEmpty:(Lscala/collection/TraversableProxyLike;)Z
const #411 = Asciz	foreach;
const #412 = Asciz	(Lscala/Function1;)V;
const #413 = Asciz	(Lscala/collection/TraversableProxyLike;Lscala/Function1;)V;
const #414 = NameAndType	#411:#413;//  foreach:(Lscala/collection/TraversableProxyLike;Lscala/Function1;)V
const #415 = Method	#23.#414;	//  scala/collection/TraversableProxyLike$class.foreach:(Lscala/collection/TraversableProxyLike;Lscala/Function1;)V
const #416 = Asciz	<A:Ljava/lang/Object;This::Lscala/collection/TraversableLike<TA;TThis;>;:Lscala/collection/Traversable<TA;>;>Ljava/lang/Object;Lscala/collection/TraversableProxyLike<TA;Lscala/collection/Traversable<TA;>;>;Lscala/collection/interfaces/TraversableMethods<TA;Lscala/collection/Traversable<TA;>;>;Lscala/ScalaObject;;
const #417 = Asciz	ScalaSig;
const #418 = Asciz	InnerClasses;
const #419 = Asciz	scala/collection/TraversableLike$WithFilter;
const #420 = class	#419;	//  scala/collection/TraversableLike$WithFilter
const #421 = Asciz	WithFilter;
const #422 = Asciz	scala/collection/interfaces/TraversableMethods;
const #423 = class	#422;	//  scala/collection/interfaces/TraversableMethods
const #424 = Asciz	scala/ScalaObject;
const #425 = class	#424;	//  scala/ScalaObject

{
public scala.collection.TraversableProxyLikeConfirmation();
  Code:
   Stack=1, Locals=1, Args_size=1
   0:	aload_0
   1:	invokespecial	#10; //Method java/lang/Object."<init>":()V
   4:	aload_0
   5:	invokestatic	#16; //Method scala/collection/TraversableLike$class.$init$:(Lscala/collection/TraversableLike;)V
   8:	aload_0
   9:	invokestatic	#21; //Method scala/Proxy$class.$init$:(Lscala/Proxy;)V
   12:	aload_0
   13:	invokestatic	#26; //Method scala/collection/TraversableProxyLike$class.$init$:(Lscala/collection/TraversableProxyLike;)V
   16:	return
  LineNumberTable: 
   line 90: 0

  Signature: length = 0x2
   00 04 

public java.lang.Object self();
  Code:
   Stack=1, Locals=1, Args_size=1
   0:	aload_0
   1:	invokevirtual	#34; //Method self:()Lscala/collection/TraversableLike;
   4:	areturn
  LineNumberTable: 
   line 89: 0


public java.lang.Object filter(scala.Function1);
  Code:
   Stack=2, Locals=2, Args_size=2
   0:	aload_0
   1:	aload_1
   2:	invokeinterface	#41,  2; //InterfaceMethod scala/collection/TraversableProxyLike.filter:(Lscala/Function1;)Lscala/collection/TraversableLike;
   7:	areturn
  LineNumberTable: 
   line 89: 0

  LocalVariableTable: 
   Start  Length  Slot  Name   Signature
   0      8      0    this       Lscala/collection/TraversableProxyLikeConfirmation;
   0      8      1    p       Lscala/Function1;


public scala.collection.Traversable filter(scala.Function1);
  Code:
   Stack=2, Locals=2, Args_size=2
   0:	aload_0
   1:	aload_1
   2:	invokeinterface	#41,  2; //InterfaceMethod scala/collection/TraversableProxyLike.filter:(Lscala/Function1;)Lscala/collection/TraversableLike;
   7:	checkcast	#49; //class scala/collection/Traversable
   10:	areturn
  LineNumberTable: 
   line 89: 0

  LocalVariableTable: 
   Start  Length  Slot  Name   Signature
   0      11      0    this       Lscala/collection/TraversableProxyLikeConfirmation;
   0      11      1    p       Lscala/Function1;


public java.lang.Object filterNot(scala.Function1);
  Code:
   Stack=2, Locals=2, Args_size=2
   0:	aload_0
   1:	aload_1
   2:	invokeinterface	#52,  2; //InterfaceMethod scala/collection/TraversableProxyLike.filterNot:(Lscala/Function1;)Lscala/collection/TraversableLike;
   7:	areturn
  LineNumberTable: 
   line 89: 0

  LocalVariableTable: 
   Start  Length  Slot  Name   Signature
   0      8      0    this       Lscala/collection/TraversableProxyLikeConfirmation;
   0      8      1    p       Lscala/Function1;


public scala.collection.Traversable filterNot(scala.Function1);
  Code:
   Stack=2, Locals=2, Args_size=2
   0:	aload_0
   1:	aload_1
   2:	invokeinterface	#52,  2; //InterfaceMethod scala/collection/TraversableProxyLike.filterNot:(Lscala/Function1;)Lscala/collection/TraversableLike;
   7:	checkcast	#49; //class scala/collection/Traversable
   10:	areturn
  LineNumberTable: 
   line 89: 0

  LocalVariableTable: 
   Start  Length  Slot  Name   Signature
   0      11      0    this       Lscala/collection/TraversableProxyLikeConfirmation;
   0      11      1    p       Lscala/Function1;


public java.lang.Object tail();
  Code:
   Stack=1, Locals=1, Args_size=1
   0:	aload_0
   1:	invokeinterface	#55,  1; //InterfaceMethod scala/collection/TraversableProxyLike.tail:()Lscala/collection/TraversableLike;
   6:	areturn
  LineNumberTable: 
   line 89: 0


public scala.collection.Traversable tail();
  Code:
   Stack=1, Locals=1, Args_size=1
   0:	aload_0
   1:	invokeinterface	#55,  1; //InterfaceMethod scala/collection/TraversableProxyLike.tail:()Lscala/collection/TraversableLike;
   6:	checkcast	#49; //class scala/collection/Traversable
   9:	areturn
  LineNumberTable: 
   line 89: 0


public java.lang.Object init();
  Code:
   Stack=1, Locals=1, Args_size=1
   0:	aload_0
   1:	invokeinterface	#59,  1; //InterfaceMethod scala/collection/TraversableProxyLike.init:()Lscala/collection/TraversableLike;
   6:	areturn
  LineNumberTable: 
   line 89: 0


public scala.collection.Traversable init();
  Code:
   Stack=1, Locals=1, Args_size=1
   0:	aload_0
   1:	invokeinterface	#59,  1; //InterfaceMethod scala/collection/TraversableProxyLike.init:()Lscala/collection/TraversableLike;
   6:	checkcast	#49; //class scala/collection/Traversable
   9:	areturn
  LineNumberTable: 
   line 89: 0


public java.lang.Object take(int);
  Code:
   Stack=2, Locals=2, Args_size=2
   0:	aload_0
   1:	iload_1
   2:	invokeinterface	#64,  2; //InterfaceMethod scala/collection/TraversableProxyLike.take:(I)Lscala/collection/TraversableLike;
   7:	areturn
  LineNumberTable: 
   line 89: 0

  LocalVariableTable: 
   Start  Length  Slot  Name   Signature
   0      8      0    this       Lscala/collection/TraversableProxyLikeConfirmation;
   0      8      1    n       I


public scala.collection.Traversable take(int);
  Code:
   Stack=2, Locals=2, Args_size=2
   0:	aload_0
   1:	iload_1
   2:	invokeinterface	#64,  2; //InterfaceMethod scala/collection/TraversableProxyLike.take:(I)Lscala/collection/TraversableLike;
   7:	checkcast	#49; //class scala/collection/Traversable
   10:	areturn
  LineNumberTable: 
   line 89: 0

  LocalVariableTable: 
   Start  Length  Slot  Name   Signature
   0      11      0    this       Lscala/collection/TraversableProxyLikeConfirmation;
   0      11      1    n       I


public java.lang.Object drop(int);
  Code:
   Stack=2, Locals=2, Args_size=2
   0:	aload_0
   1:	iload_1
   2:	invokeinterface	#70,  2; //InterfaceMethod scala/collection/TraversableProxyLike.drop:(I)Lscala/collection/TraversableLike;
   7:	areturn
  LineNumberTable: 
   line 89: 0

  LocalVariableTable: 
   Start  Length  Slot  Name   Signature
   0      8      0    this       Lscala/collection/TraversableProxyLikeConfirmation;
   0      8      1    n       I


public scala.collection.Traversable drop(int);
  Code:
   Stack=2, Locals=2, Args_size=2
   0:	aload_0
   1:	iload_1
   2:	invokeinterface	#70,  2; //InterfaceMethod scala/collection/TraversableProxyLike.drop:(I)Lscala/collection/TraversableLike;
   7:	checkcast	#49; //class scala/collection/Traversable
   10:	areturn
  LineNumberTable: 
   line 89: 0

  LocalVariableTable: 
   Start  Length  Slot  Name   Signature
   0      11      0    this       Lscala/collection/TraversableProxyLikeConfirmation;
   0      11      1    n       I


public java.lang.Object slice(int, int);
  Code:
   Stack=3, Locals=3, Args_size=3
   0:	aload_0
   1:	iload_1
   2:	iload_2
   3:	invokeinterface	#75,  3; //InterfaceMethod scala/collection/TraversableProxyLike.slice:(II)Lscala/collection/TraversableLike;
   8:	areturn
  LineNumberTable: 
   line 89: 0

  LocalVariableTable: 
   Start  Length  Slot  Name   Signature
   0      9      0    this       Lscala/collection/TraversableProxyLikeConfirmation;
   0      9      1    from       I
   0      9      2    until       I


public scala.collection.Traversable slice(int, int);
  Code:
   Stack=3, Locals=3, Args_size=3
   0:	aload_0
   1:	iload_1
   2:	iload_2
   3:	invokeinterface	#75,  3; //InterfaceMethod scala/collection/TraversableProxyLike.slice:(II)Lscala/collection/TraversableLike;
   8:	checkcast	#49; //class scala/collection/Traversable
   11:	areturn
  LineNumberTable: 
   line 89: 0

  LocalVariableTable: 
   Start  Length  Slot  Name   Signature
   0      12      0    this       Lscala/collection/TraversableProxyLikeConfirmation;
   0      12      1    from       I
   0      12      2    until       I


public java.lang.Object takeWhile(scala.Function1);
  Code:
   Stack=2, Locals=2, Args_size=2
   0:	aload_0
   1:	aload_1
   2:	invokeinterface	#81,  2; //InterfaceMethod scala/collection/TraversableProxyLike.takeWhile:(Lscala/Function1;)Lscala/collection/TraversableLike;
   7:	areturn
  LineNumberTable: 
   line 89: 0

  LocalVariableTable: 
   Start  Length  Slot  Name   Signature
   0      8      0    this       Lscala/collection/TraversableProxyLikeConfirmation;
   0      8      1    p       Lscala/Function1;


public scala.collection.Traversable takeWhile(scala.Function1);
  Code:
   Stack=2, Locals=2, Args_size=2
   0:	aload_0
   1:	aload_1
   2:	invokeinterface	#81,  2; //InterfaceMethod scala/collection/TraversableProxyLike.takeWhile:(Lscala/Function1;)Lscala/collection/TraversableLike;
   7:	checkcast	#49; //class scala/collection/Traversable
   10:	areturn
  LineNumberTable: 
   line 89: 0

  LocalVariableTable: 
   Start  Length  Slot  Name   Signature
   0      11      0    this       Lscala/collection/TraversableProxyLikeConfirmation;
   0      11      1    p       Lscala/Function1;


public java.lang.Object dropWhile(scala.Function1);
  Code:
   Stack=2, Locals=2, Args_size=2
   0:	aload_0
   1:	aload_1
   2:	invokeinterface	#84,  2; //InterfaceMethod scala/collection/TraversableProxyLike.dropWhile:(Lscala/Function1;)Lscala/collection/TraversableLike;
   7:	areturn
  LineNumberTable: 
   line 89: 0

  LocalVariableTable: 
   Start  Length  Slot  Name   Signature
   0      8      0    this       Lscala/collection/TraversableProxyLikeConfirmation;
   0      8      1    p       Lscala/Function1;


public scala.collection.Traversable dropWhile(scala.Function1);
  Code:
   Stack=2, Locals=2, Args_size=2
   0:	aload_0
   1:	aload_1
   2:	invokeinterface	#84,  2; //InterfaceMethod scala/collection/TraversableProxyLike.dropWhile:(Lscala/Function1;)Lscala/collection/TraversableLike;
   7:	checkcast	#49; //class scala/collection/Traversable
   10:	areturn
  LineNumberTable: 
   line 89: 0

  LocalVariableTable: 
   Start  Length  Slot  Name   Signature
   0      11      0    this       Lscala/collection/TraversableProxyLikeConfirmation;
   0      11      1    p       Lscala/Function1;


public scala.collection.TraversableView view();
  Code:
   Stack=1, Locals=1, Args_size=1
   0:	aload_0
   1:	invokeinterface	#88,  1; //InterfaceMethod scala/collection/TraversableProxyLike.view:()Ljava/lang/Object;
   6:	checkcast	#90; //class scala/collection/TraversableView
   9:	areturn
  LineNumberTable: 
   line 89: 0


public scala.collection.mutable.Builder newBuilder();
  Code:
   Stack=1, Locals=1, Args_size=1
   0:	getstatic	#98; //Field scala/collection/Traversable$.MODULE$:Lscala/collection/Traversable$;
   3:	invokevirtual	#100; //Method scala/collection/Traversable$.newBuilder:()Lscala/collection/mutable/Builder;
   6:	areturn
  LineNumberTable: 
   line 94: 0

  Signature: length = 0x2
   00 65 

public scala.collection.TraversableLike self();
  Code:
   Stack=1, Locals=1, Args_size=1
   0:	aload_0
   1:	invokeinterface	#106,  1; //InterfaceMethod scala/collection/TraversableLike.repr:()Ljava/lang/Object;
   6:	checkcast	#103; //class scala/collection/TraversableLike
   9:	areturn
  LineNumberTable: 
   line 93: 0

  Signature: length = 0x2
   00 6B 

public scala.collection.TraversableLike$WithFilter withFilter(scala.Function1);
  Code:
   Stack=2, Locals=2, Args_size=2
   0:	aload_0
   1:	aload_1
   2:	invokestatic	#112; //Method scala/collection/TraversableLike$class.withFilter:(Lscala/collection/TraversableLike;Lscala/Function1;)Lscala/collection/TraversableLike$WithFilter;
   5:	areturn
  LineNumberTable: 
   line 89: 0

  LocalVariableTable: 
   Start  Length  Slot  Name   Signature
   0      6      0    this       Lscala/collection/TraversableProxyLikeConfirmation;
   0      6      1    p       Lscala/Function1;

  Signature: length = 0x2
   00 6D 

public scala.collection.mutable.IndexedSeq toIndexedSeq();
  Code:
   Stack=1, Locals=1, Args_size=1
   0:	aload_0
   1:	invokestatic	#117; //Method scala/collection/TraversableLike$class.toIndexedSeq:(Lscala/collection/TraversableLike;)Lscala/collection/mutable/IndexedSeq;
   4:	areturn
  LineNumberTable: 
   line 89: 0


public void copyToArray(java.lang.Object);
  Code:
   Stack=2, Locals=2, Args_size=2
   0:	aload_0
   1:	aload_1
   2:	invokestatic	#122; //Method scala/collection/TraversableLike$class.copyToArray:(Lscala/collection/TraversableLike;Ljava/lang/Object;)V
   5:	return
  LineNumberTable: 
   line 89: 0

  LocalVariableTable: 
   Start  Length  Slot  Name   Signature
   0      6      0    this       Lscala/collection/TraversableProxyLikeConfirmation;
   0      6      1    xs       Ljava/lang/Object;


public java.lang.Object max(scala.math.Ordering);
  Code:
   Stack=2, Locals=2, Args_size=2
   0:	aload_0
   1:	aload_1
   2:	invokestatic	#129; //Method scala/collection/TraversableLike$class.max:(Lscala/collection/TraversableLike;Lscala/math/Ordering;)Ljava/lang/Object;
   5:	areturn
  LineNumberTable: 
   line 89: 0

  LocalVariableTable: 
   Start  Length  Slot  Name   Signature
   0      6      0    this       Lscala/collection/TraversableProxyLikeConfirmation;
   0      6      1    cmp       Lscala/math/Ordering;


public java.lang.Object min(scala.math.Ordering);
  Code:
   Stack=2, Locals=2, Args_size=2
   0:	aload_0
   1:	aload_1
   2:	invokestatic	#134; //Method scala/collection/TraversableLike$class.min:(Lscala/collection/TraversableLike;Lscala/math/Ordering;)Ljava/lang/Object;
   5:	areturn
  LineNumberTable: 
   line 89: 0

  LocalVariableTable: 
   Start  Length  Slot  Name   Signature
   0      6      0    this       Lscala/collection/TraversableProxyLikeConfirmation;
   0      6      1    cmp       Lscala/math/Ordering;


public java.lang.Object product(scala.math.Numeric);
  Code:
   Stack=2, Locals=2, Args_size=2
   0:	aload_0
   1:	aload_1
   2:	invokestatic	#139; //Method scala/collection/TraversableLike$class.product:(Lscala/collection/TraversableLike;Lscala/math/Numeric;)Ljava/lang/Object;
   5:	areturn
  LineNumberTable: 
   line 89: 0

  LocalVariableTable: 
   Start  Length  Slot  Name   Signature
   0      6      0    this       Lscala/collection/TraversableProxyLikeConfirmation;
   0      6      1    num       Lscala/math/Numeric;


public java.lang.Object sum(scala.math.Numeric);
  Code:
   Stack=2, Locals=2, Args_size=2
   0:	aload_0
   1:	aload_1
   2:	invokestatic	#144; //Method scala/collection/TraversableLike$class.sum:(Lscala/collection/TraversableLike;Lscala/math/Numeric;)Ljava/lang/Object;
   5:	areturn
  LineNumberTable: 
   line 89: 0

  LocalVariableTable: 
   Start  Length  Slot  Name   Signature
   0      6      0    this       Lscala/collection/TraversableProxyLikeConfirmation;
   0      6      1    num       Lscala/math/Numeric;


public scala.collection.Traversable toCollection(java.lang.Object);
  Code:
   Stack=2, Locals=2, Args_size=2
   0:	aload_0
   1:	aload_1
   2:	invokestatic	#149; //Method scala/collection/TraversableLike$class.toCollection:(Lscala/collection/TraversableLike;Ljava/lang/Object;)Lscala/collection/Traversable;
   5:	areturn
  LineNumberTable: 
   line 89: 0

  LocalVariableTable: 
   Start  Length  Slot  Name   Signature
   0      6      0    this       Lscala/collection/TraversableProxyLikeConfirmation;
   0      6      1    repr       Ljava/lang/Object;


public scala.collection.Traversable thisCollection();
  Code:
   Stack=1, Locals=1, Args_size=1
   0:	aload_0
   1:	invokestatic	#153; //Method scala/collection/TraversableLike$class.thisCollection:(Lscala/collection/TraversableLike;)Lscala/collection/Traversable;
   4:	areturn
  LineNumberTable: 
   line 89: 0


public java.lang.Object repr();
  Code:
   Stack=1, Locals=1, Args_size=1
   0:	aload_0
   1:	invokestatic	#156; //Method scala/collection/TraversableLike$class.repr:(Lscala/collection/TraversableLike;)Ljava/lang/Object;
   4:	areturn
  LineNumberTable: 
   line 89: 0


public java.lang.String toString();
  Code:
   Stack=1, Locals=1, Args_size=1
   0:	aload_0
   1:	invokestatic	#161; //Method scala/Proxy$class.toString:(Lscala/Proxy;)Ljava/lang/String;
   4:	areturn
  LineNumberTable: 
   line 89: 0


public boolean equals(java.lang.Object);
  Code:
   Stack=2, Locals=2, Args_size=2
   0:	aload_0
   1:	aload_1
   2:	invokestatic	#166; //Method scala/Proxy$class.equals:(Lscala/Proxy;Ljava/lang/Object;)Z
   5:	ireturn
  LineNumberTable: 
   line 89: 0

  LocalVariableTable: 
   Start  Length  Slot  Name   Signature
   0      6      0    this       Lscala/collection/TraversableProxyLikeConfirmation;
   0      6      1    that       Ljava/lang/Object;


public int hashCode();
  Code:
   Stack=1, Locals=1, Args_size=1
   0:	aload_0
   1:	invokestatic	#172; //Method scala/Proxy$class.hashCode:(Lscala/Proxy;)I
   4:	ireturn
  LineNumberTable: 
   line 89: 0


public scala.collection.TraversableView view(int, int);
  Code:
   Stack=3, Locals=3, Args_size=3
   0:	aload_0
   1:	iload_1
   2:	iload_2
   3:	invokestatic	#176; //Method scala/collection/TraversableProxyLike$class.view:(Lscala/collection/TraversableProxyLike;II)Lscala/collection/TraversableView;
   6:	areturn
  LineNumberTable: 
   line 89: 0

  LocalVariableTable: 
   Start  Length  Slot  Name   Signature
   0      7      0    this       Lscala/collection/TraversableProxyLikeConfirmation;
   0      7      1    from       I
   0      7      2    until       I


public java.lang.Object view();
  Code:
   Stack=1, Locals=1, Args_size=1
   0:	aload_0
   1:	invokestatic	#179; //Method scala/collection/TraversableProxyLike$class.view:(Lscala/collection/TraversableProxyLike;)Ljava/lang/Object;
   4:	areturn
  LineNumberTable: 
   line 89: 0


public java.lang.String stringPrefix();
  Code:
   Stack=1, Locals=1, Args_size=1
   0:	aload_0
   1:	invokestatic	#183; //Method scala/collection/TraversableProxyLike$class.stringPrefix:(Lscala/collection/TraversableProxyLike;)Ljava/lang/String;
   4:	areturn
  LineNumberTable: 
   line 89: 0


public scala.collection.mutable.StringBuilder addString(scala.collection.mutable.StringBuilder);
  Code:
   Stack=2, Locals=2, Args_size=2
   0:	aload_0
   1:	aload_1
   2:	invokestatic	#188; //Method scala/collection/TraversableProxyLike$class.addString:(Lscala/collection/TraversableProxyLike;Lscala/collection/mutable/StringBuilder;)Lscala/collection/mutable/StringBuilder;
   5:	areturn
  LineNumberTable: 
   line 89: 0

  LocalVariableTable: 
   Start  Length  Slot  Name   Signature
   0      6      0    this       Lscala/collection/TraversableProxyLikeConfirmation;
   0      6      1    b       Lscala/collection/mutable/StringBuilder;


public scala.collection.mutable.StringBuilder addString(scala.collection.mutable.StringBuilder, java.lang.String);
  Code:
   Stack=3, Locals=3, Args_size=3
   0:	aload_0
   1:	aload_1
   2:	aload_2
   3:	invokestatic	#194; //Method scala/collection/TraversableProxyLike$class.addString:(Lscala/collection/TraversableProxyLike;Lscala/collection/mutable/StringBuilder;Ljava/lang/String;)Lscala/collection/mutable/StringBuilder;
   6:	areturn
  LineNumberTable: 
   line 89: 0

  LocalVariableTable: 
   Start  Length  Slot  Name   Signature
   0      7      0    this       Lscala/collection/TraversableProxyLikeConfirmation;
   0      7      1    b       Lscala/collection/mutable/StringBuilder;
   0      7      2    sep       Ljava/lang/String;


public scala.collection.mutable.StringBuilder addString(scala.collection.mutable.StringBuilder, java.lang.String, java.lang.String, java.lang.String);
  Code:
   Stack=5, Locals=5, Args_size=5
   0:	aload_0
   1:	aload_1
   2:	aload_2
   3:	aload_3
   4:	aload	4
   6:	invokestatic	#200; //Method scala/collection/TraversableProxyLike$class.addString:(Lscala/collection/TraversableProxyLike;Lscala/collection/mutable/StringBuilder;Ljava/lang/String;Ljava/lang/String;Ljava/lang/String;)Lscala/collection/mutable/StringBuilder;
   9:	areturn
  LineNumberTable: 
   line 89: 0

  LocalVariableTable: 
   Start  Length  Slot  Name   Signature
   0      10      0    this       Lscala/collection/TraversableProxyLikeConfirmation;
   0      10      1    b       Lscala/collection/mutable/StringBuilder;
   0      10      2    start       Ljava/lang/String;
   0      10      3    sep       Ljava/lang/String;
   0      10      4    end       Ljava/lang/String;


public java.lang.String mkString();
  Code:
   Stack=1, Locals=1, Args_size=1
   0:	aload_0
   1:	invokestatic	#205; //Method scala/collection/TraversableProxyLike$class.mkString:(Lscala/collection/TraversableProxyLike;)Ljava/lang/String;
   4:	areturn
  LineNumberTable: 
   line 89: 0


public java.lang.String mkString(java.lang.String);
  Code:
   Stack=2, Locals=2, Args_size=2
   0:	aload_0
   1:	aload_1
   2:	invokestatic	#209; //Method scala/collection/TraversableProxyLike$class.mkString:(Lscala/collection/TraversableProxyLike;Ljava/lang/String;)Ljava/lang/String;
   5:	areturn
  LineNumberTable: 
   line 89: 0

  LocalVariableTable: 
   Start  Length  Slot  Name   Signature
   0      6      0    this       Lscala/collection/TraversableProxyLikeConfirmation;
   0      6      1    sep       Ljava/lang/String;


public java.lang.String mkString(java.lang.String, java.lang.String, java.lang.String);
  Code:
   Stack=4, Locals=4, Args_size=4
   0:	aload_0
   1:	aload_1
   2:	aload_2
   3:	aload_3
   4:	invokestatic	#213; //Method scala/collection/TraversableProxyLike$class.mkString:(Lscala/collection/TraversableProxyLike;Ljava/lang/String;Ljava/lang/String;Ljava/lang/String;)Ljava/lang/String;
   7:	areturn
  LineNumberTable: 
   line 89: 0

  LocalVariableTable: 
   Start  Length  Slot  Name   Signature
   0      8      0    this       Lscala/collection/TraversableProxyLikeConfirmation;
   0      8      1    start       Ljava/lang/String;
   0      8      2    sep       Ljava/lang/String;
   0      8      3    end       Ljava/lang/String;


public scala.collection.immutable.Set toSet();
  Code:
   Stack=1, Locals=1, Args_size=1
   0:	aload_0
   1:	invokestatic	#218; //Method scala/collection/TraversableProxyLike$class.toSet:(Lscala/collection/TraversableProxyLike;)Lscala/collection/immutable/Set;
   4:	areturn
  LineNumberTable: 
   line 89: 0


public scala.collection.immutable.Stream toStream();
  Code:
   Stack=1, Locals=1, Args_size=1
   0:	aload_0
   1:	invokestatic	#223; //Method scala/collection/TraversableProxyLike$class.toStream:(Lscala/collection/TraversableProxyLike;)Lscala/collection/immutable/Stream;
   4:	areturn
  LineNumberTable: 
   line 89: 0


public scala.collection.Seq toSeq();
  Code:
   Stack=1, Locals=1, Args_size=1
   0:	aload_0
   1:	invokestatic	#228; //Method scala/collection/TraversableProxyLike$class.toSeq:(Lscala/collection/TraversableProxyLike;)Lscala/collection/Seq;
   4:	areturn
  LineNumberTable: 
   line 89: 0


public scala.collection.Iterable toIterable();
  Code:
   Stack=1, Locals=1, Args_size=1
   0:	aload_0
   1:	invokestatic	#233; //Method scala/collection/TraversableProxyLike$class.toIterable:(Lscala/collection/TraversableProxyLike;)Lscala/collection/Iterable;
   4:	areturn
  LineNumberTable: 
   line 89: 0


public scala.collection.immutable.List toList();
  Code:
   Stack=1, Locals=1, Args_size=1
   0:	aload_0
   1:	invokestatic	#238; //Method scala/collection/TraversableProxyLike$class.toList:(Lscala/collection/TraversableProxyLike;)Lscala/collection/immutable/List;
   4:	areturn
  LineNumberTable: 
   line 89: 0


public java.lang.Object toArray(scala.reflect.ClassManifest);
  Code:
   Stack=2, Locals=2, Args_size=2
   0:	aload_0
   1:	aload_1
   2:	invokestatic	#243; //Method scala/collection/TraversableProxyLike$class.toArray:(Lscala/collection/TraversableProxyLike;Lscala/reflect/ClassManifest;)Ljava/lang/Object;
   5:	areturn
  LineNumberTable: 
   line 89: 0

  LocalVariableTable: 
   Start  Length  Slot  Name   Signature
   0      6      0    this       Lscala/collection/TraversableProxyLikeConfirmation;
   0      6      1    evidence$1       Lscala/reflect/ClassManifest;


public void copyToArray(java.lang.Object, int);
  Code:
   Stack=3, Locals=3, Args_size=3
   0:	aload_0
   1:	aload_1
   2:	iload_2
   3:	invokestatic	#249; //Method scala/collection/TraversableProxyLike$class.copyToArray:(Lscala/collection/TraversableProxyLike;Ljava/lang/Object;I)V
   6:	return
  LineNumberTable: 
   line 89: 0

  LocalVariableTable: 
   Start  Length  Slot  Name   Signature
   0      7      0    this       Lscala/collection/TraversableProxyLikeConfirmation;
   0      7      1    xs       Ljava/lang/Object;
   0      7      2    start       I


public void copyToArray(java.lang.Object, int, int);
  Code:
   Stack=4, Locals=4, Args_size=4
   0:	aload_0
   1:	aload_1
   2:	iload_2
   3:	iload_3
   4:	invokestatic	#253; //Method scala/collection/TraversableProxyLike$class.copyToArray:(Lscala/collection/TraversableProxyLike;Ljava/lang/Object;II)V
   7:	return
  LineNumberTable: 
   line 89: 0

  LocalVariableTable: 
   Start  Length  Slot  Name   Signature
   0      8      0    this       Lscala/collection/TraversableProxyLikeConfirmation;
   0      8      1    xs       Ljava/lang/Object;
   0      8      2    start       I
   0      8      3    len       I


public void copyToBuffer(scala.collection.mutable.Buffer);
  Code:
   Stack=2, Locals=2, Args_size=2
   0:	aload_0
   1:	aload_1
   2:	invokestatic	#259; //Method scala/collection/TraversableProxyLike$class.copyToBuffer:(Lscala/collection/TraversableProxyLike;Lscala/collection/mutable/Buffer;)V
   5:	return
  LineNumberTable: 
   line 89: 0

  LocalVariableTable: 
   Start  Length  Slot  Name   Signature
   0      6      0    this       Lscala/collection/TraversableProxyLikeConfirmation;
   0      6      1    dest       Lscala/collection/mutable/Buffer;


public scala.Tuple2 splitAt(int);
  Code:
   Stack=2, Locals=2, Args_size=2
   0:	aload_0
   1:	iload_1
   2:	invokestatic	#266; //Method scala/collection/TraversableProxyLike$class.splitAt:(Lscala/collection/TraversableProxyLike;I)Lscala/Tuple2;
   5:	areturn
  LineNumberTable: 
   line 89: 0

  LocalVariableTable: 
   Start  Length  Slot  Name   Signature
   0      6      0    this       Lscala/collection/TraversableProxyLikeConfirmation;
   0      6      1    n       I


public scala.Tuple2 span(scala.Function1);
  Code:
   Stack=2, Locals=2, Args_size=2
   0:	aload_0
   1:	aload_1
   2:	invokestatic	#271; //Method scala/collection/TraversableProxyLike$class.span:(Lscala/collection/TraversableProxyLike;Lscala/Function1;)Lscala/Tuple2;
   5:	areturn
  LineNumberTable: 
   line 89: 0

  LocalVariableTable: 
   Start  Length  Slot  Name   Signature
   0      6      0    this       Lscala/collection/TraversableProxyLikeConfirmation;
   0      6      1    p       Lscala/Function1;


public scala.collection.TraversableLike dropWhile(scala.Function1);
  Code:
   Stack=2, Locals=2, Args_size=2
   0:	aload_0
   1:	aload_1
   2:	invokestatic	#274; //Method scala/collection/TraversableProxyLike$class.dropWhile:(Lscala/collection/TraversableProxyLike;Lscala/Function1;)Lscala/collection/TraversableLike;
   5:	areturn
  LineNumberTable: 
   line 89: 0

  LocalVariableTable: 
   Start  Length  Slot  Name   Signature
   0      6      0    this       Lscala/collection/TraversableProxyLikeConfirmation;
   0      6      1    p       Lscala/Function1;


public scala.collection.TraversableLike takeWhile(scala.Function1);
  Code:
   Stack=2, Locals=2, Args_size=2
   0:	aload_0
   1:	aload_1
   2:	invokestatic	#276; //Method scala/collection/TraversableProxyLike$class.takeWhile:(Lscala/collection/TraversableProxyLike;Lscala/Function1;)Lscala/collection/TraversableLike;
   5:	areturn
  LineNumberTable: 
   line 89: 0

  LocalVariableTable: 
   Start  Length  Slot  Name   Signature
   0      6      0    this       Lscala/collection/TraversableProxyLikeConfirmation;
   0      6      1    p       Lscala/Function1;


public scala.collection.TraversableLike slice(int, int);
  Code:
   Stack=3, Locals=3, Args_size=3
   0:	aload_0
   1:	iload_1
   2:	iload_2
   3:	invokestatic	#279; //Method scala/collection/TraversableProxyLike$class.slice:(Lscala/collection/TraversableProxyLike;II)Lscala/collection/TraversableLike;
   6:	areturn
  LineNumberTable: 
   line 89: 0

  LocalVariableTable: 
   Start  Length  Slot  Name   Signature
   0      7      0    this       Lscala/collection/TraversableProxyLikeConfirmation;
   0      7      1    from       I
   0      7      2    until       I


public scala.collection.TraversableLike drop(int);
  Code:
   Stack=2, Locals=2, Args_size=2
   0:	aload_0
   1:	iload_1
   2:	invokestatic	#282; //Method scala/collection/TraversableProxyLike$class.drop:(Lscala/collection/TraversableProxyLike;I)Lscala/collection/TraversableLike;
   5:	areturn
  LineNumberTable: 
   line 89: 0

  LocalVariableTable: 
   Start  Length  Slot  Name   Signature
   0      6      0    this       Lscala/collection/TraversableProxyLikeConfirmation;
   0      6      1    n       I


public scala.collection.TraversableLike take(int);
  Code:
   Stack=2, Locals=2, Args_size=2
   0:	aload_0
   1:	iload_1
   2:	invokestatic	#284; //Method scala/collection/TraversableProxyLike$class.take:(Lscala/collection/TraversableProxyLike;I)Lscala/collection/TraversableLike;
   5:	areturn
  LineNumberTable: 
   line 89: 0

  LocalVariableTable: 
   Start  Length  Slot  Name   Signature
   0      6      0    this       Lscala/collection/TraversableProxyLikeConfirmation;
   0      6      1    n       I


public scala.collection.TraversableLike init();
  Code:
   Stack=1, Locals=1, Args_size=1
   0:	aload_0
   1:	invokestatic	#287; //Method scala/collection/TraversableProxyLike$class.init:(Lscala/collection/TraversableProxyLike;)Lscala/collection/TraversableLike;
   4:	areturn
  LineNumberTable: 
   line 89: 0


public scala.Option lastOption();
  Code:
   Stack=1, Locals=1, Args_size=1
   0:	aload_0
   1:	invokestatic	#292; //Method scala/collection/TraversableProxyLike$class.lastOption:(Lscala/collection/TraversableProxyLike;)Lscala/Option;
   4:	areturn
  LineNumberTable: 
   line 89: 0


public java.lang.Object last();
  Code:
   Stack=1, Locals=1, Args_size=1
   0:	aload_0
   1:	invokestatic	#295; //Method scala/collection/TraversableProxyLike$class.last:(Lscala/collection/TraversableProxyLike;)Ljava/lang/Object;
   4:	areturn
  LineNumberTable: 
   line 89: 0


public scala.collection.TraversableLike tail();
  Code:
   Stack=1, Locals=1, Args_size=1
   0:	aload_0
   1:	invokestatic	#297; //Method scala/collection/TraversableProxyLike$class.tail:(Lscala/collection/TraversableProxyLike;)Lscala/collection/TraversableLike;
   4:	areturn
  LineNumberTable: 
   line 89: 0


public scala.Option headOption();
  Code:
   Stack=1, Locals=1, Args_size=1
   0:	aload_0
   1:	invokestatic	#300; //Method scala/collection/TraversableProxyLike$class.headOption:(Lscala/collection/TraversableProxyLike;)Lscala/Option;
   4:	areturn
  LineNumberTable: 
   line 89: 0


public java.lang.Object head();
  Code:
   Stack=1, Locals=1, Args_size=1
   0:	aload_0
   1:	invokestatic	#303; //Method scala/collection/TraversableProxyLike$class.head:(Lscala/collection/TraversableProxyLike;)Ljava/lang/Object;
   4:	areturn
  LineNumberTable: 
   line 89: 0


public scala.Option reduceRightOption(scala.Function2);
  Code:
   Stack=2, Locals=2, Args_size=2
   0:	aload_0
   1:	aload_1
   2:	invokestatic	#308; //Method scala/collection/TraversableProxyLike$class.reduceRightOption:(Lscala/collection/TraversableProxyLike;Lscala/Function2;)Lscala/Option;
   5:	areturn
  LineNumberTable: 
   line 89: 0

  LocalVariableTable: 
   Start  Length  Slot  Name   Signature
   0      6      0    this       Lscala/collection/TraversableProxyLikeConfirmation;
   0      6      1    op       Lscala/Function2;


public java.lang.Object reduceRight(scala.Function2);
  Code:
   Stack=2, Locals=2, Args_size=2
   0:	aload_0
   1:	aload_1
   2:	invokestatic	#315; //Method scala/collection/TraversableProxyLike$class.reduceRight:(Lscala/collection/TraversableProxyLike;Lscala/Function2;)Ljava/lang/Object;
   5:	areturn
  LineNumberTable: 
   line 89: 0

  LocalVariableTable: 
   Start  Length  Slot  Name   Signature
   0      6      0    this       Lscala/collection/TraversableProxyLikeConfirmation;
   0      6      1    op       Lscala/Function2;


public scala.Option reduceLeftOption(scala.Function2);
  Code:
   Stack=2, Locals=2, Args_size=2
   0:	aload_0
   1:	aload_1
   2:	invokestatic	#318; //Method scala/collection/TraversableProxyLike$class.reduceLeftOption:(Lscala/collection/TraversableProxyLike;Lscala/Function2;)Lscala/Option;
   5:	areturn
  LineNumberTable: 
   line 89: 0

  LocalVariableTable: 
   Start  Length  Slot  Name   Signature
   0      6      0    this       Lscala/collection/TraversableProxyLikeConfirmation;
   0      6      1    op       Lscala/Function2;


public java.lang.Object reduceLeft(scala.Function2);
  Code:
   Stack=2, Locals=2, Args_size=2
   0:	aload_0
   1:	aload_1
   2:	invokestatic	#321; //Method scala/collection/TraversableProxyLike$class.reduceLeft:(Lscala/collection/TraversableProxyLike;Lscala/Function2;)Ljava/lang/Object;
   5:	areturn
  LineNumberTable: 
   line 89: 0

  LocalVariableTable: 
   Start  Length  Slot  Name   Signature
   0      6      0    this       Lscala/collection/TraversableProxyLikeConfirmation;
   0      6      1    op       Lscala/Function2;


public java.lang.Object $colon$bslash(java.lang.Object, scala.Function2);
  Code:
   Stack=3, Locals=3, Args_size=3
   0:	aload_0
   1:	aload_1
   2:	aload_2
   3:	invokestatic	#326; //Method scala/collection/TraversableProxyLike$class.$colon$bslash:(Lscala/collection/TraversableProxyLike;Ljava/lang/Object;Lscala/Function2;)Ljava/lang/Object;
   6:	areturn
  LineNumberTable: 
   line 89: 0

  LocalVariableTable: 
   Start  Length  Slot  Name   Signature
   0      7      0    this       Lscala/collection/TraversableProxyLikeConfirmation;
   0      7      1    z       Ljava/lang/Object;
   0      7      2    op       Lscala/Function2;


public java.lang.Object foldRight(java.lang.Object, scala.Function2);
  Code:
   Stack=3, Locals=3, Args_size=3
   0:	aload_0
   1:	aload_1
   2:	aload_2
   3:	invokestatic	#330; //Method scala/collection/TraversableProxyLike$class.foldRight:(Lscala/collection/TraversableProxyLike;Ljava/lang/Object;Lscala/Function2;)Ljava/lang/Object;
   6:	areturn
  LineNumberTable: 
   line 89: 0

  LocalVariableTable: 
   Start  Length  Slot  Name   Signature
   0      7      0    this       Lscala/collection/TraversableProxyLikeConfirmation;
   0      7      1    z       Ljava/lang/Object;
   0      7      2    op       Lscala/Function2;


public java.lang.Object $div$colon(java.lang.Object, scala.Function2);
  Code:
   Stack=3, Locals=3, Args_size=3
   0:	aload_0
   1:	aload_1
   2:	aload_2
   3:	invokestatic	#333; //Method scala/collection/TraversableProxyLike$class.$div$colon:(Lscala/collection/TraversableProxyLike;Ljava/lang/Object;Lscala/Function2;)Ljava/lang/Object;
   6:	areturn
  LineNumberTable: 
   line 89: 0

  LocalVariableTable: 
   Start  Length  Slot  Name   Signature
   0      7      0    this       Lscala/collection/TraversableProxyLikeConfirmation;
   0      7      1    z       Ljava/lang/Object;
   0      7      2    op       Lscala/Function2;


public java.lang.Object foldLeft(java.lang.Object, scala.Function2);
  Code:
   Stack=3, Locals=3, Args_size=3
   0:	aload_0
   1:	aload_1
   2:	aload_2
   3:	invokestatic	#336; //Method scala/collection/TraversableProxyLike$class.foldLeft:(Lscala/collection/TraversableProxyLike;Ljava/lang/Object;Lscala/Function2;)Ljava/lang/Object;
   6:	areturn
  LineNumberTable: 
   line 89: 0

  LocalVariableTable: 
   Start  Length  Slot  Name   Signature
   0      7      0    this       Lscala/collection/TraversableProxyLikeConfirmation;
   0      7      1    z       Ljava/lang/Object;
   0      7      2    op       Lscala/Function2;


public scala.Option find(scala.Function1);
  Code:
   Stack=2, Locals=2, Args_size=2
   0:	aload_0
   1:	aload_1
   2:	invokestatic	#341; //Method scala/collection/TraversableProxyLike$class.find:(Lscala/collection/TraversableProxyLike;Lscala/Function1;)Lscala/Option;
   5:	areturn
  LineNumberTable: 
   line 89: 0

  LocalVariableTable: 
   Start  Length  Slot  Name   Signature
   0      6      0    this       Lscala/collection/TraversableProxyLikeConfirmation;
   0      6      1    p       Lscala/Function1;


public int count(scala.Function1);
  Code:
   Stack=2, Locals=2, Args_size=2
   0:	aload_0
   1:	aload_1
   2:	invokestatic	#346; //Method scala/collection/TraversableProxyLike$class.count:(Lscala/collection/TraversableProxyLike;Lscala/Function1;)I
   5:	ireturn
  LineNumberTable: 
   line 89: 0

  LocalVariableTable: 
   Start  Length  Slot  Name   Signature
   0      6      0    this       Lscala/collection/TraversableProxyLikeConfirmation;
   0      6      1    p       Lscala/Function1;


public boolean exists(scala.Function1);
  Code:
   Stack=2, Locals=2, Args_size=2
   0:	aload_0
   1:	aload_1
   2:	invokestatic	#351; //Method scala/collection/TraversableProxyLike$class.exists:(Lscala/collection/TraversableProxyLike;Lscala/Function1;)Z
   5:	ireturn
  LineNumberTable: 
   line 89: 0

  LocalVariableTable: 
   Start  Length  Slot  Name   Signature
   0      6      0    this       Lscala/collection/TraversableProxyLikeConfirmation;
   0      6      1    p       Lscala/Function1;


public boolean forall(scala.Function1);
  Code:
   Stack=2, Locals=2, Args_size=2
   0:	aload_0
   1:	aload_1
   2:	invokestatic	#354; //Method scala/collection/TraversableProxyLike$class.forall:(Lscala/collection/TraversableProxyLike;Lscala/Function1;)Z
   5:	ireturn
  LineNumberTable: 
   line 89: 0

  LocalVariableTable: 
   Start  Length  Slot  Name   Signature
   0      6      0    this       Lscala/collection/TraversableProxyLikeConfirmation;
   0      6      1    p       Lscala/Function1;


public scala.collection.Map groupBy(scala.Function1);
  Code:
   Stack=2, Locals=2, Args_size=2
   0:	aload_0
   1:	aload_1
   2:	invokestatic	#359; //Method scala/collection/TraversableProxyLike$class.groupBy:(Lscala/collection/TraversableProxyLike;Lscala/Function1;)Lscala/collection/Map;
   5:	areturn
  LineNumberTable: 
   line 89: 0

  LocalVariableTable: 
   Start  Length  Slot  Name   Signature
   0      6      0    this       Lscala/collection/TraversableProxyLikeConfirmation;
   0      6      1    f       Lscala/Function1;


public scala.Tuple2 partition(scala.Function1);
  Code:
   Stack=2, Locals=2, Args_size=2
   0:	aload_0
   1:	aload_1
   2:	invokestatic	#363; //Method scala/collection/TraversableProxyLike$class.partition:(Lscala/collection/TraversableProxyLike;Lscala/Function1;)Lscala/Tuple2;
   5:	areturn
  LineNumberTable: 
   line 89: 0

  LocalVariableTable: 
   Start  Length  Slot  Name   Signature
   0      6      0    this       Lscala/collection/TraversableProxyLikeConfirmation;
   0      6      1    p       Lscala/Function1;


public scala.collection.TraversableLike filterNot(scala.Function1);
  Code:
   Stack=2, Locals=2, Args_size=2
   0:	aload_0
   1:	aload_1
   2:	invokestatic	#365; //Method scala/collection/TraversableProxyLike$class.filterNot:(Lscala/collection/TraversableProxyLike;Lscala/Function1;)Lscala/collection/TraversableLike;
   5:	areturn
  LineNumberTable: 
   line 89: 0

  LocalVariableTable: 
   Start  Length  Slot  Name   Signature
   0      6      0    this       Lscala/collection/TraversableProxyLikeConfirmation;
   0      6      1    p       Lscala/Function1;


public scala.collection.TraversableLike filter(scala.Function1);
  Code:
   Stack=2, Locals=2, Args_size=2
   0:	aload_0
   1:	aload_1
   2:	invokestatic	#367; //Method scala/collection/TraversableProxyLike$class.filter:(Lscala/collection/TraversableProxyLike;Lscala/Function1;)Lscala/collection/TraversableLike;
   5:	areturn
  LineNumberTable: 
   line 89: 0

  LocalVariableTable: 
   Start  Length  Slot  Name   Signature
   0      6      0    this       Lscala/collection/TraversableProxyLikeConfirmation;
   0      6      1    p       Lscala/Function1;


public java.lang.Object partialMap(scala.PartialFunction, scala.collection.generic.CanBuildFrom);
  Code:
   Stack=3, Locals=3, Args_size=3
   0:	aload_0
   1:	aload_1
   2:	aload_2
   3:	invokestatic	#372; //Method scala/collection/TraversableProxyLike$class.partialMap:(Lscala/collection/TraversableProxyLike;Lscala/PartialFunction;Lscala/collection/generic/CanBuildFrom;)Ljava/lang/Object;
   6:	areturn
  LineNumberTable: 
   line 89: 0

  LocalVariableTable: 
   Start  Length  Slot  Name   Signature
   0      7      0    this       Lscala/collection/TraversableProxyLikeConfirmation;
   0      7      1    pf       Lscala/PartialFunction;
   0      7      2    bf       Lscala/collection/generic/CanBuildFrom;


public java.lang.Object flatMap(scala.Function1, scala.collection.generic.CanBuildFrom);
  Code:
   Stack=3, Locals=3, Args_size=3
   0:	aload_0
   1:	aload_1
   2:	aload_2
   3:	invokestatic	#381; //Method scala/collection/TraversableProxyLike$class.flatMap:(Lscala/collection/TraversableProxyLike;Lscala/Function1;Lscala/collection/generic/CanBuildFrom;)Ljava/lang/Object;
   6:	areturn
  LineNumberTable: 
   line 89: 0

  LocalVariableTable: 
   Start  Length  Slot  Name   Signature
   0      7      0    this       Lscala/collection/TraversableProxyLikeConfirmation;
   0      7      1    f       Lscala/Function1;
   0      7      2    bf       Lscala/collection/generic/CanBuildFrom;


public java.lang.Object map(scala.Function1, scala.collection.generic.CanBuildFrom);
  Code:
   Stack=3, Locals=3, Args_size=3
   0:	aload_0
   1:	aload_1
   2:	aload_2
   3:	invokestatic	#384; //Method scala/collection/TraversableProxyLike$class.map:(Lscala/collection/TraversableProxyLike;Lscala/Function1;Lscala/collection/generic/CanBuildFrom;)Ljava/lang/Object;
   6:	areturn
  LineNumberTable: 
   line 89: 0

  LocalVariableTable: 
   Start  Length  Slot  Name   Signature
   0      7      0    this       Lscala/collection/TraversableProxyLikeConfirmation;
   0      7      1    f       Lscala/Function1;
   0      7      2    bf       Lscala/collection/generic/CanBuildFrom;


public java.lang.Object $plus$plus(scala.collection.Iterator, scala.collection.generic.CanBuildFrom);
  Code:
   Stack=3, Locals=3, Args_size=3
   0:	aload_0
   1:	aload_1
   2:	aload_2
   3:	invokestatic	#389; //Method scala/collection/TraversableProxyLike$class.$plus$plus:(Lscala/collection/TraversableProxyLike;Lscala/collection/Iterator;Lscala/collection/generic/CanBuildFrom;)Ljava/lang/Object;
   6:	areturn
  LineNumberTable: 
   line 89: 0

  LocalVariableTable: 
   Start  Length  Slot  Name   Signature
   0      7      0    this       Lscala/collection/TraversableProxyLikeConfirmation;
   0      7      1    that       Lscala/collection/Iterator;
   0      7      2    bf       Lscala/collection/generic/CanBuildFrom;


public java.lang.Object $plus$plus(scala.collection.Traversable, scala.collection.generic.CanBuildFrom);
  Code:
   Stack=3, Locals=3, Args_size=3
   0:	aload_0
   1:	aload_1
   2:	aload_2
   3:	invokestatic	#394; //Method scala/collection/TraversableProxyLike$class.$plus$plus:(Lscala/collection/TraversableProxyLike;Lscala/collection/Traversable;Lscala/collection/generic/CanBuildFrom;)Ljava/lang/Object;
   6:	areturn
  LineNumberTable: 
   line 89: 0

  LocalVariableTable: 
   Start  Length  Slot  Name   Signature
   0      7      0    this       Lscala/collection/TraversableProxyLikeConfirmation;
   0      7      1    that       Lscala/collection/Traversable;
   0      7      2    bf       Lscala/collection/generic/CanBuildFrom;


public boolean hasDefiniteSize();
  Code:
   Stack=1, Locals=1, Args_size=1
   0:	aload_0
   1:	invokestatic	#400; //Method scala/collection/TraversableProxyLike$class.hasDefiniteSize:(Lscala/collection/TraversableProxyLike;)Z
   4:	ireturn
  LineNumberTable: 
   line 89: 0


public int size();
  Code:
   Stack=1, Locals=1, Args_size=1
   0:	aload_0
   1:	invokestatic	#404; //Method scala/collection/TraversableProxyLike$class.size:(Lscala/collection/TraversableProxyLike;)I
   4:	ireturn
  LineNumberTable: 
   line 89: 0


public boolean nonEmpty();
  Code:
   Stack=1, Locals=1, Args_size=1
   0:	aload_0
   1:	invokestatic	#407; //Method scala/collection/TraversableProxyLike$class.nonEmpty:(Lscala/collection/TraversableProxyLike;)Z
   4:	ireturn
  LineNumberTable: 
   line 89: 0


public boolean isEmpty();
  Code:
   Stack=1, Locals=1, Args_size=1
   0:	aload_0
   1:	invokestatic	#410; //Method scala/collection/TraversableProxyLike$class.isEmpty:(Lscala/collection/TraversableProxyLike;)Z
   4:	ireturn
  LineNumberTable: 
   line 89: 0


public void foreach(scala.Function1);
  Code:
   Stack=2, Locals=2, Args_size=2
   0:	aload_0
   1:	aload_1
   2:	invokestatic	#415; //Method scala/collection/TraversableProxyLike$class.foreach:(Lscala/collection/TraversableProxyLike;Lscala/Function1;)V
   5:	return
  LineNumberTable: 
   line 89: 0

  LocalVariableTable: 
   Start  Length  Slot  Name   Signature
   0      6      0    this       Lscala/collection/TraversableProxyLikeConfirmation;
   0      6      1    f       Lscala/Function1;


}

