Compiled from "TraversableViewLike.scala"
public abstract class scala.collection.TraversableViewLike$Forced$class extends java.lang.Object
  SourceFile: "TraversableViewLike.scala"
  Scala: length = 0x
   
  InnerClass: 
   public abstract Forced=class scala/collection/TraversableViewLike$Forced of class scala/collection/TraversableViewLike
  minor version: 0
  major version: 49
  Constant pool:
Asciz	SourceFile;
Asciz	TraversableViewLike.scala;
Asciz	scala$collection$TraversableViewLike$Forced$$forcedCache;
Asciz	(Lscala/collection/TraversableViewLike$Forced;)Lscala/collection/Seq;;
Asciz	Code;
Asciz	LineNumberTable;
Asciz	scala/collection/TraversableViewLike$Forced;
class	scala/collection/TraversableViewLike$Forced
Asciz	forced;
Asciz	()Lscala/collection/Seq;;
NameAndType	forced:()Lscala/collection/Seq;
InterfaceMethod	scala/collection/TraversableViewLike$Forced.forced:()Lscala/collection/Seq;
Asciz	$this;
Asciz	Lscala/collection/TraversableViewLike$Forced;;
Asciz	LocalVariableTable;
Asciz	foreach;
Asciz	(Lscala/collection/TraversableViewLike$Forced;Lscala/Function1;)V;
NameAndType	scala$collection$TraversableViewLike$Forced$$forcedCache:()Lscala/collection/Seq;
InterfaceMethod	scala/collection/TraversableViewLike$Forced.scala$collection$TraversableViewLike$Forced$$forcedCache:()Lscala/collection/Seq;
Asciz	scala/collection/IterableLike;
class	scala/collection/IterableLike
Asciz	(Lscala/Function1;)V;
NameAndType	foreach:(Lscala/Function1;)V
InterfaceMethod	scala/collection/IterableLike.foreach:(Lscala/Function1;)V
Asciz	f;
Asciz	Lscala/Function1;;
Asciz	stringPrefix;
Asciz	(Lscala/collection/TraversableViewLike$Forced;)Ljava/lang/String;;
Asciz	scala/collection/mutable/StringBuilder;
class	scala/collection/mutable/StringBuilder
Asciz	<init>;
Asciz	()V;
NameAndType	"<init>":()V
Method	scala/collection/mutable/StringBuilder."<init>":()V
Asciz	scala$collection$TraversableViewLike$Forced$$$outer;
Asciz	()Lscala/collection/TraversableViewLike;;
NameAndType	scala$collection$TraversableViewLike$Forced$$$outer:()Lscala/collection/TraversableViewLike;
InterfaceMethod	scala/collection/TraversableViewLike$Forced.scala$collection$TraversableViewLike$Forced$$$outer:()Lscala/collection/TraversableViewLike;
Asciz	scala/collection/TraversableViewLike;
class	scala/collection/TraversableViewLike
Asciz	()Ljava/lang/String;;
NameAndType	stringPrefix:()Ljava/lang/String;
InterfaceMethod	scala/collection/TraversableViewLike.stringPrefix:()Ljava/lang/String;
Asciz	append;
Asciz	(Ljava/lang/Object;)Lscala/collection/mutable/StringBuilder;;
NameAndType	append:(Ljava/lang/Object;)Lscala/collection/mutable/StringBuilder;
Method	scala/collection/mutable/StringBuilder.append:(Ljava/lang/Object;)Lscala/collection/mutable/StringBuilder;
Asciz	C;
String	C
Asciz	toString;
NameAndType	toString:()Ljava/lang/String;
Method	scala/collection/mutable/StringBuilder.toString:()Ljava/lang/String;
Asciz	$init$;
Asciz	(Lscala/collection/TraversableViewLike$Forced;)V;
Asciz	Scala;
Asciz	InnerClasses;
Asciz	Forced;
Asciz	scala/collection/TraversableViewLike$Forced$class;
class	scala/collection/TraversableViewLike$Forced$class
Asciz	java/lang/Object;
class	java/lang/Object

{
public static final scala.collection.Seq scala$collection$TraversableViewLike$Forced$$forcedCache(scala.collection.TraversableViewLike$Forced);
  Signature: (Lscala/collection/TraversableViewLike$Forced;)Lscala/collection/Seq;
  Code:
   Stack=1, Locals=1, Args_size=1
	aload_0
	invokeinterface	InterfaceMethod scala/collection/TraversableViewLike$Forced.forced:()Lscala/collection/Seq;
	areturn
  Labels:
  LocalVariableTable: 
   Start  Length  Slot  Name   Signature
   0      7      0    $this       Lscala/collection/TraversableViewLike$Forced;


public static void foreach(scala.collection.TraversableViewLike$Forced, scala.Function1);
  Signature: (Lscala/collection/TraversableViewLike$Forced;Lscala/Function1;)V
  Code:
   Stack=2, Locals=2, Args_size=2
	aload_0
	invokeinterface	InterfaceMethod scala/collection/TraversableViewLike$Forced.scala$collection$TraversableViewLike$Forced$$forcedCache:()Lscala/collection/Seq;
	aload_1
	invokeinterface	InterfaceMethod scala/collection/IterableLike.foreach:(Lscala/Function1;)V
	return
  Labels:
  LocalVariableTable: 
   Start  Length  Slot  Name   Signature
   0      13      0    $this       Lscala/collection/TraversableViewLike$Forced;
   0      13      1    f       Lscala/Function1;


public static java.lang.String stringPrefix(scala.collection.TraversableViewLike$Forced);
  Signature: (Lscala/collection/TraversableViewLike$Forced;)Ljava/lang/String;
  Code:
   Stack=2, Locals=1, Args_size=1
	new	class scala/collection/mutable/StringBuilder
	dup
	invokespecial	Method scala/collection/mutable/StringBuilder."<init>":()V
	aload_0
	invokeinterface	InterfaceMethod scala/collection/TraversableViewLike$Forced.scala$collection$TraversableViewLike$Forced$$$outer:()Lscala/collection/TraversableViewLike;
	invokeinterface	InterfaceMethod scala/collection/TraversableViewLike.stringPrefix:()Ljava/lang/String;
	invokevirtual	Method scala/collection/mutable/StringBuilder.append:(Ljava/lang/Object;)Lscala/collection/mutable/StringBuilder;
	ldc	String C
	invokevirtual	Method scala/collection/mutable/StringBuilder.append:(Ljava/lang/Object;)Lscala/collection/mutable/StringBuilder;
	invokevirtual	Method scala/collection/mutable/StringBuilder.toString:()Ljava/lang/String;
	areturn
  Labels:
  LocalVariableTable: 
   Start  Length  Slot  Name   Signature
   0      30      0    $this       Lscala/collection/TraversableViewLike$Forced;


public static void $init$(scala.collection.TraversableViewLike$Forced);
  Signature: (Lscala/collection/TraversableViewLike$Forced;)V
  Code:
   Stack=0, Locals=1, Args_size=1
	return
  Labels:
  LocalVariableTable: 
   Start  Length  Slot  Name   Signature
   0      1      0    $this       Lscala/collection/TraversableViewLike$Forced;


}

