Compiled from "Vector.scala"
public final class scala.collection.Vector$ extends scala.collection.generic.SequenceFactory implements scala.ScalaObject
  SourceFile: "Vector.scala"
  Scala: length = 0x
   
  Signature: length = 0x2
   00 27 
  InnerClass: 
   public #43= #34 of #42; //VirtualBuilderFactory=class scala/collection/generic/TraversableFactory$VirtualBuilderFactory of class scala/collection/generic/TraversableFactory
  minor version: 0
  major version: 49
  Constant pool:
const #1 = Asciz	SourceFile;
const #2 = Asciz	Vector.scala;
const #3 = Asciz	Scala;
const #4 = Asciz	MODULE$;
const #5 = Asciz	Lscala/collection/Vector$;;
const #6 = Asciz	<clinit>;
const #7 = Asciz	()V;
const #8 = Asciz	Code;
const #9 = Asciz	scala/collection/Vector$;
const #10 = class	#9;	//  scala/collection/Vector$
const #11 = Asciz	<init>;
const #12 = NameAndType	#11:#7;//  "<init>":()V
const #13 = Method	#10.#12;	//  scala/collection/Vector$."<init>":()V
const #14 = Asciz	LineNumberTable;
const #15 = Asciz	scala/collection/generic/SequenceFactory;
const #16 = class	#15;	//  scala/collection/generic/SequenceFactory
const #17 = Method	#16.#12;	//  scala/collection/generic/SequenceFactory."<init>":()V
const #18 = NameAndType	#4:#5;//  MODULE$:Lscala/collection/Vector$;
const #19 = Field	#10.#18;	//  scala/collection/Vector$.MODULE$:Lscala/collection/Vector$;
const #20 = Asciz	newBuilder;
const #21 = Asciz	()Lscala/collection/generic/Builder;;
const #22 = Asciz	scala/collection/mutable/Vector$;
const #23 = class	#22;	//  scala/collection/mutable/Vector$
const #24 = Asciz	Lscala/collection/mutable/Vector$;;
const #25 = NameAndType	#4:#24;//  MODULE$:Lscala/collection/mutable/Vector$;
const #26 = Field	#23.#25;	//  scala/collection/mutable/Vector$.MODULE$:Lscala/collection/mutable/Vector$;
const #27 = NameAndType	#20:#21;//  newBuilder:()Lscala/collection/generic/Builder;
const #28 = Method	#23.#27;	//  scala/collection/mutable/Vector$.newBuilder:()Lscala/collection/generic/Builder;
const #29 = Asciz	<A:Ljava/lang/Object;>()Lscala/collection/generic/Builder<TA;Lscala/collection/Vector<TA;>;>;;
const #30 = Asciz	Signature;
const #31 = Asciz	builderFactory;
const #32 = Asciz	()Lscala/collection/generic/BuilderFactory;;
const #33 = Asciz	scala/collection/generic/TraversableFactory$VirtualBuilderFactory;
const #34 = class	#33;	//  scala/collection/generic/TraversableFactory$VirtualBuilderFactory
const #35 = Asciz	(Lscala/collection/generic/TraversableFactory;)V;
const #36 = NameAndType	#11:#35;//  "<init>":(Lscala/collection/generic/TraversableFactory;)V
const #37 = Method	#34.#36;	//  scala/collection/generic/TraversableFactory$VirtualBuilderFactory."<init>":(Lscala/collection/generic/TraversableFactory;)V
const #38 = Asciz	<A:Ljava/lang/Object;>()Lscala/collection/generic/BuilderFactory<TA;Lscala/collection/Vector<TA;>;Lscala/collection/Vector<*>;>;;
const #39 = Asciz	Lscala/collection/generic/SequenceFactory<Lscala/collection/Vector<TA;>;>;Lscala/ScalaObject;;
const #40 = Asciz	InnerClasses;
const #41 = Asciz	scala/collection/generic/TraversableFactory;
const #42 = class	#41;	//  scala/collection/generic/TraversableFactory
const #43 = Asciz	VirtualBuilderFactory;
const #44 = Asciz	scala/ScalaObject;
const #45 = class	#44;	//  scala/ScalaObject

{
public static final scala.collection.Vector$ MODULE$;

public static {};
  Code:
   Stack=1, Locals=0, Args_size=0
   0:	new	#10; //class scala/collection/Vector$
   3:	invokespecial	#13; //Method "<init>":()V
   6:	return

public scala.collection.generic.Builder newBuilder();
  Code:
   Stack=1, Locals=1, Args_size=1
   0:	getstatic	#26; //Field scala/collection/mutable/Vector$.MODULE$:Lscala/collection/mutable/Vector$;
   3:	invokevirtual	#28; //Method scala/collection/mutable/Vector$.newBuilder:()Lscala/collection/generic/Builder;
   6:	areturn
  LineNumberTable: 
   line 32: 0

  Signature: length = 0x2
   00 1D 

public scala.collection.generic.BuilderFactory builderFactory();
  Code:
   Stack=3, Locals=1, Args_size=1
   0:	new	#34; //class scala/collection/generic/TraversableFactory$VirtualBuilderFactory
   3:	dup
   4:	aload_0
   5:	invokespecial	#37; //Method scala/collection/generic/TraversableFactory$VirtualBuilderFactory."<init>":(Lscala/collection/generic/TraversableFactory;)V
   8:	areturn
  LineNumberTable: 
   line 31: 0

  Signature: length = 0x2
   00 26 

}

