Compiled from "ActorGC.scala"
public abstract class scala.actors.scheduler.ActorGC$class extends java.lang.Object
  SourceFile: "ActorGC.scala"
  Scala: length = 0x
   
  InnerClass: 
   public final ArrowAssoc=class scala/Predef$ArrowAssoc of class scala/Predef
   public final $anonfun$terminated$1=class scala/actors/scheduler/ActorGC$$anonfun$terminated$1 of class scala/actors/scheduler/ActorGC
  minor version: 0
  major version: 49
  Constant pool:
Asciz	SourceFile;
Asciz	ActorGC.scala;
Asciz	newActor;
Asciz	(Lscala/actors/scheduler/ActorGC;Lscala/actors/Reactor;)V;
Asciz	Code;
Asciz	LineNumberTable;
Asciz	java/lang/ref/WeakReference;
class	java/lang/ref/WeakReference
Asciz	scala/actors/scheduler/ActorGC;
class	scala/actors/scheduler/ActorGC
Asciz	scala$actors$scheduler$ActorGC$$refQ;
Asciz	()Ljava/lang/ref/ReferenceQueue;;
NameAndType	scala$actors$scheduler$ActorGC$$refQ:()Ljava/lang/ref/ReferenceQueue;
InterfaceMethod	scala/actors/scheduler/ActorGC.scala$actors$scheduler$ActorGC$$refQ:()Ljava/lang/ref/ReferenceQueue;
Asciz	<init>;
Asciz	(Ljava/lang/Object;Ljava/lang/ref/ReferenceQueue;)V;
NameAndType	"<init>":(Ljava/lang/Object;Ljava/lang/ref/ReferenceQueue;)V
Method	java/lang/ref/WeakReference."<init>":(Ljava/lang/Object;Ljava/lang/ref/ReferenceQueue;)V
Asciz	scala$actors$scheduler$ActorGC$$refSet;
Asciz	()Lscala/collection/mutable/HashSet;;
NameAndType	scala$actors$scheduler$ActorGC$$refSet:()Lscala/collection/mutable/HashSet;
InterfaceMethod	scala/actors/scheduler/ActorGC.scala$actors$scheduler$ActorGC$$refSet:()Lscala/collection/mutable/HashSet;
Asciz	scala/collection/mutable/HashSet;
class	scala/collection/mutable/HashSet
Asciz	$plus$eq;
Asciz	(Ljava/lang/Object;)Lscala/collection/mutable/HashSet;;
NameAndType	$plus$eq:(Ljava/lang/Object;)Lscala/collection/mutable/HashSet;
Method	scala/collection/mutable/HashSet.$plus$eq:(Ljava/lang/Object;)Lscala/collection/mutable/HashSet;
Asciz	scala/actors/scheduler/TerminationMonitor;
class	scala/actors/scheduler/TerminationMonitor
Asciz	activeActors;
Asciz	()I;
NameAndType	activeActors:()I
InterfaceMethod	scala/actors/scheduler/TerminationMonitor.activeActors:()I
Asciz	activeActors_$eq;
Asciz	(I)V;
NameAndType	activeActors_$eq:(I)V
InterfaceMethod	scala/actors/scheduler/TerminationMonitor.activeActors_$eq:(I)V
Asciz	scala/runtime/BoxedUnit;
class	scala/runtime/BoxedUnit
Asciz	UNIT;
Asciz	Lscala/runtime/BoxedUnit;;
NameAndType	UNIT:Lscala/runtime/BoxedUnit;
Field	scala/runtime/BoxedUnit.UNIT:Lscala/runtime/BoxedUnit;
Asciz	$this;
Asciz	Lscala/actors/scheduler/ActorGC;;
Asciz	a;
Asciz	Lscala/actors/Reactor;;
Asciz	wr;
Asciz	Ljava/lang/ref/WeakReference;;
Asciz	LocalVariableTable;
Asciz	gc;
Asciz	(Lscala/actors/scheduler/ActorGC;)V;
Asciz	scala/actors/scheduler/ActorGC$class;
class	scala/actors/scheduler/ActorGC$class
Asciz	drainRefQ$1;
NameAndType	drainRefQ$1:(Lscala/actors/scheduler/ActorGC;)V
Method	scala/actors/scheduler/ActorGC$class.drainRefQ$1:(Lscala/actors/scheduler/ActorGC;)V
Asciz	status;
Asciz	scala/Predef$;
class	scala/Predef$
Asciz	MODULE$;
Asciz	Lscala/Predef$;;
NameAndType	MODULE$:Lscala/Predef$;
Field	scala/Predef$.MODULE$:Lscala/Predef$;
Asciz	scala/collection/mutable/StringBuilder;
class	scala/collection/mutable/StringBuilder
Asciz	()V;
NameAndType	"<init>":()V
Method	scala/collection/mutable/StringBuilder."<init>":()V
Asciz	any2stringadd;
Asciz	(Ljava/lang/Object;)Lscala/runtime/StringAdd;;
NameAndType	any2stringadd:(Ljava/lang/Object;)Lscala/runtime/StringAdd;
Method	scala/Predef$.any2stringadd:(Ljava/lang/Object;)Lscala/runtime/StringAdd;
Asciz	: size of refSet: ;
String	: size of refSet: 
Asciz	scala/runtime/StringAdd;
class	scala/runtime/StringAdd
Asciz	$plus;
Asciz	(Ljava/lang/String;)Ljava/lang/String;;
NameAndType	$plus:(Ljava/lang/String;)Ljava/lang/String;
Method	scala/runtime/StringAdd.$plus:(Ljava/lang/String;)Ljava/lang/String;
Asciz	append;
Asciz	(Ljava/lang/Object;)Lscala/collection/mutable/StringBuilder;;
NameAndType	append:(Ljava/lang/Object;)Lscala/collection/mutable/StringBuilder;
Method	scala/collection/mutable/StringBuilder.append:(Ljava/lang/Object;)Lscala/collection/mutable/StringBuilder;
Asciz	size;
NameAndType	size:()I
Method	scala/collection/mutable/HashSet.size:()I
Asciz	scala/runtime/BoxesRunTime;
class	scala/runtime/BoxesRunTime
Asciz	boxToInteger;
Asciz	(I)Ljava/lang/Integer;;
NameAndType	boxToInteger:(I)Ljava/lang/Integer;
Method	scala/runtime/BoxesRunTime.boxToInteger:(I)Ljava/lang/Integer;
Asciz	toString;
Asciz	()Ljava/lang/String;;
NameAndType	toString:()Ljava/lang/String;
Method	scala/collection/mutable/StringBuilder.toString:()Ljava/lang/String;
Asciz	println;
Asciz	(Ljava/lang/Object;)V;
NameAndType	println:(Ljava/lang/Object;)V
Method	scala/Predef$.println:(Ljava/lang/Object;)V
Asciz	allActorsTerminated;
Asciz	(Lscala/actors/scheduler/ActorGC;)Z;
Asciz	boxToBoolean;
Asciz	(Z)Ljava/lang/Boolean;;
NameAndType	boxToBoolean:(Z)Ljava/lang/Boolean;
Method	scala/runtime/BoxesRunTime.boxToBoolean:(Z)Ljava/lang/Boolean;
Asciz	unboxToBoolean;
Asciz	(Ljava/lang/Object;)Z;
NameAndType	unboxToBoolean:(Ljava/lang/Object;)Z
Method	scala/runtime/BoxesRunTime.unboxToBoolean:(Ljava/lang/Object;)Z
Asciz	onTerminate;
Asciz	(Lscala/actors/scheduler/ActorGC;Lscala/actors/Reactor;Lscala/Function0;)V;
Asciz	terminationHandlers;
Asciz	()Lscala/collection/mutable/HashMap;;
NameAndType	terminationHandlers:()Lscala/collection/mutable/HashMap;
InterfaceMethod	scala/actors/scheduler/TerminationMonitor.terminationHandlers:()Lscala/collection/mutable/HashMap;
Asciz	any2ArrowAssoc;
Asciz	(Ljava/lang/Object;)Lscala/Predef$ArrowAssoc;;
NameAndType	any2ArrowAssoc:(Ljava/lang/Object;)Lscala/Predef$ArrowAssoc;
Method	scala/Predef$.any2ArrowAssoc:(Ljava/lang/Object;)Lscala/Predef$ArrowAssoc;
Asciz	scala/Predef$ArrowAssoc;
class	scala/Predef$ArrowAssoc
Asciz	$minus$greater;
Asciz	(Ljava/lang/Object;)Lscala/Tuple2;;
NameAndType	$minus$greater:(Ljava/lang/Object;)Lscala/Tuple2;
Method	scala/Predef$ArrowAssoc.$minus$greater:(Ljava/lang/Object;)Lscala/Tuple2;
Asciz	scala/collection/mutable/HashMap;
class	scala/collection/mutable/HashMap
Asciz	(Lscala/Tuple2;)Lscala/collection/mutable/HashMap;;
NameAndType	$plus$eq:(Lscala/Tuple2;)Lscala/collection/mutable/HashMap;
Method	scala/collection/mutable/HashMap.$plus$eq:(Lscala/Tuple2;)Lscala/collection/mutable/HashMap;
Asciz	f;
Asciz	Lscala/Function0;;
Asciz	terminated;
Asciz	scala$actors$scheduler$ActorGC$$super$terminated;
Asciz	(Lscala/actors/Reactor;)V;
NameAndType	scala$actors$scheduler$ActorGC$$super$terminated:(Lscala/actors/Reactor;)V
InterfaceMethod	scala/actors/scheduler/ActorGC.scala$actors$scheduler$ActorGC$$super$terminated:(Lscala/actors/Reactor;)V
Asciz	scala/actors/scheduler/ActorGC$$anonfun$terminated$1;
class	scala/actors/scheduler/ActorGC$$anonfun$terminated$1
NameAndType	"<init>":(Lscala/actors/scheduler/ActorGC;Lscala/actors/Reactor;)V
Method	scala/actors/scheduler/ActorGC$$anonfun$terminated$1."<init>":(Lscala/actors/scheduler/ActorGC;Lscala/actors/Reactor;)V
Asciz	scala/collection/IterableLike;
class	scala/collection/IterableLike
Asciz	find;
Asciz	(Lscala/Function1;)Lscala/Option;;
NameAndType	find:(Lscala/Function1;)Lscala/Option;
InterfaceMethod	scala/collection/IterableLike.find:(Lscala/Function1;)Lscala/Option;
Asciz	scala/Some;
class	scala/Some
Asciz	x;
Asciz	()Ljava/lang/Object;;
NameAndType	x:()Ljava/lang/Object;
Method	scala/Some.x:()Ljava/lang/Object;
Asciz	java/lang/ref/Reference;
class	java/lang/ref/Reference
Asciz	clear;
NameAndType	clear:()V
Method	java/lang/ref/Reference.clear:()V
Asciz	$minus$eq;
NameAndType	$minus$eq:(Ljava/lang/Object;)Lscala/collection/mutable/HashSet;
Method	scala/collection/mutable/HashSet.$minus$eq:(Ljava/lang/Object;)Lscala/collection/mutable/HashSet;
Asciz	scala/None$;
class	scala/None$
Asciz	Lscala/None$;;
NameAndType	MODULE$:Lscala/None$;
Field	scala/None$.MODULE$:Lscala/None$;
Asciz	java/lang/Object;
class	java/lang/Object
Asciz	equals;
NameAndType	equals:(Ljava/lang/Object;)Z
Method	java/lang/Object.equals:(Ljava/lang/Object;)Z
Asciz	scala/MatchError;
class	scala/MatchError
NameAndType	"<init>":(Ljava/lang/Object;)V
Method	scala/MatchError."<init>":(Ljava/lang/Object;)V
Asciz	a$1;
Asciz	temp1;
Asciz	Lscala/Option;;
Asciz	temp2;
Asciz	Lscala/Some;;
Asciz	temp3;
Asciz	Ljava/lang/ref/Reference;;
Asciz	r;
Asciz	getPendingCount;
Asciz	(Lscala/actors/scheduler/ActorGC;)I;
Asciz	unboxToInt;
Asciz	(Ljava/lang/Object;)I;
NameAndType	unboxToInt:(Ljava/lang/Object;)I
Method	scala/runtime/BoxesRunTime.unboxToInt:(Ljava/lang/Object;)I
Asciz	setPendingCount;
Asciz	(Lscala/actors/scheduler/ActorGC;I)V;
Asciz	cnt;
Asciz	I;
Asciz	java/lang/ref/ReferenceQueue;
class	java/lang/ref/ReferenceQueue
Asciz	poll;
Asciz	()Ljava/lang/ref/Reference;;
NameAndType	poll:()Ljava/lang/ref/Reference;
Method	java/lang/ref/ReferenceQueue.poll:()Ljava/lang/ref/Reference;
Asciz	$init$;
Method	java/lang/ref/ReferenceQueue."<init>":()V
Asciz	scala$actors$scheduler$ActorGC$_setter_$scala$actors$scheduler$ActorGC$$refQ_$eq;
Asciz	(Ljava/lang/ref/ReferenceQueue;)V;
NameAndType	scala$actors$scheduler$ActorGC$_setter_$scala$actors$scheduler$ActorGC$$refQ_$eq:(Ljava/lang/ref/ReferenceQueue;)V
InterfaceMethod	scala/actors/scheduler/ActorGC.scala$actors$scheduler$ActorGC$_setter_$scala$actors$scheduler$ActorGC$$refQ_$eq:(Ljava/lang/ref/ReferenceQueue;)V
Method	scala/collection/mutable/HashSet."<init>":()V
Asciz	scala$actors$scheduler$ActorGC$_setter_$scala$actors$scheduler$ActorGC$$refSet_$eq;
Asciz	(Lscala/collection/mutable/HashSet;)V;
NameAndType	scala$actors$scheduler$ActorGC$_setter_$scala$actors$scheduler$ActorGC$$refSet_$eq:(Lscala/collection/mutable/HashSet;)V
InterfaceMethod	scala/actors/scheduler/ActorGC.scala$actors$scheduler$ActorGC$_setter_$scala$actors$scheduler$ActorGC$$refSet_$eq:(Lscala/collection/mutable/HashSet;)V
Asciz	Scala;
Asciz	InnerClasses;
Asciz	scala/Predef;
class	scala/Predef
Asciz	ArrowAssoc;
Asciz	$anonfun$terminated$1;

{
public static void newActor(scala.actors.scheduler.ActorGC, scala.actors.Reactor);
  Signature: (Lscala/actors/scheduler/ActorGC;Lscala/actors/Reactor;)V
  Code:
   Stack=4, Locals=4, Args_size=2
	aload_0
	dup
	astore_2
	monitorenter
	new	class java/lang/ref/WeakReference
	dup
	aload_1
	aload_0
	invokeinterface	InterfaceMethod scala/actors/scheduler/ActorGC.scala$actors$scheduler$ActorGC$$refQ:()Ljava/lang/ref/ReferenceQueue;
	invokespecial	Method java/lang/ref/WeakReference."<init>":(Ljava/lang/Object;Ljava/lang/ref/ReferenceQueue;)V
	astore_3
	aload_0
	invokeinterface	InterfaceMethod scala/actors/scheduler/ActorGC.scala$actors$scheduler$ActorGC$$refSet:()Lscala/collection/mutable/HashSet;
	aload_3
	invokevirtual	Method scala/collection/mutable/HashSet.$plus$eq:(Ljava/lang/Object;)Lscala/collection/mutable/HashSet;
	pop
	aload_0
	aload_0
	invokeinterface	InterfaceMethod scala/actors/scheduler/TerminationMonitor.activeActors:()I
	iconst_1
	iadd
	invokeinterface	InterfaceMethod scala/actors/scheduler/TerminationMonitor.activeActors_$eq:(I)V
	getstatic	Field scala/runtime/BoxedUnit.UNIT:Lscala/runtime/BoxedUnit;
	pop
	aload_2
	monitorexit
	return
	aload_2
	monitorexit
	athrow
  Labels:
  Exception table:
   from   to  target type
     4    50    51   any
  LocalVariableTable: 
   Start  Length  Slot  Name   Signature
   0      54      0    $this       Lscala/actors/scheduler/ActorGC;
   0      54      1    a       Lscala/actors/Reactor;
   19      29      3    wr       Ljava/lang/ref/WeakReference;


public static void gc(scala.actors.scheduler.ActorGC);
  Signature: (Lscala/actors/scheduler/ActorGC;)V
  Code:
   Stack=2, Locals=2, Args_size=1
	aload_0
	dup
	astore_1
	monitorenter
	aload_0
	invokestatic	Method drainRefQ$1:(Lscala/actors/scheduler/ActorGC;)V
	getstatic	Field scala/runtime/BoxedUnit.UNIT:Lscala/runtime/BoxedUnit;
	pop
	aload_1
	monitorexit
	return
	aload_1
	monitorexit
	athrow
  Labels:
  Exception table:
   from   to  target type
     4    14    15   any
  LocalVariableTable: 
   Start  Length  Slot  Name   Signature
   0      18      0    $this       Lscala/actors/scheduler/ActorGC;


public static void status(scala.actors.scheduler.ActorGC);
  Signature: (Lscala/actors/scheduler/ActorGC;)V
  Code:
   Stack=4, Locals=1, Args_size=1
	getstatic	Field scala/Predef$.MODULE$:Lscala/Predef$;
	new	class scala/collection/mutable/StringBuilder
	dup
	invokespecial	Method scala/collection/mutable/StringBuilder."<init>":()V
	getstatic	Field scala/Predef$.MODULE$:Lscala/Predef$;
	aload_0
	invokevirtual	Method scala/Predef$.any2stringadd:(Ljava/lang/Object;)Lscala/runtime/StringAdd;
	ldc	String : size of refSet: 
	invokevirtual	Method scala/runtime/StringAdd.$plus:(Ljava/lang/String;)Ljava/lang/String;
	invokevirtual	Method scala/collection/mutable/StringBuilder.append:(Ljava/lang/Object;)Lscala/collection/mutable/StringBuilder;
	aload_0
	invokeinterface	InterfaceMethod scala/actors/scheduler/ActorGC.scala$actors$scheduler$ActorGC$$refSet:()Lscala/collection/mutable/HashSet;
	invokevirtual	Method scala/collection/mutable/HashSet.size:()I
	invokestatic	Method scala/runtime/BoxesRunTime.boxToInteger:(I)Ljava/lang/Integer;
	invokevirtual	Method scala/collection/mutable/StringBuilder.append:(Ljava/lang/Object;)Lscala/collection/mutable/StringBuilder;
	invokevirtual	Method scala/collection/mutable/StringBuilder.toString:()Ljava/lang/String;
	invokevirtual	Method scala/Predef$.println:(Ljava/lang/Object;)V
	return
  Labels:
  LocalVariableTable: 
   Start  Length  Slot  Name   Signature
   0      47      0    $this       Lscala/actors/scheduler/ActorGC;


public static boolean allActorsTerminated(scala.actors.scheduler.ActorGC);
  Signature: (Lscala/actors/scheduler/ActorGC;)Z
  Code:
   Stack=2, Locals=3, Args_size=1
	aload_0
	dup
	astore_1
	monitorenter
	aload_0
	invokeinterface	InterfaceMethod scala/actors/scheduler/TerminationMonitor.activeActors:()I
	iconst_0
	if_icmpgt	l1 // iconst_0
	iconst_1
	goto	l2 // invokestatic
l1	iconst_0
l2	invokestatic	Method scala/runtime/BoxesRunTime.boxToBoolean:(Z)Ljava/lang/Boolean;
	astore_2
	aload_1
	monitorexit
	aload_2
	invokestatic	Method scala/runtime/BoxesRunTime.unboxToBoolean:(Ljava/lang/Object;)Z
	ireturn
	aload_1
	monitorexit
	athrow
  Labels:
   	l1 = 18 // iconst_0
   	l2 = 19 // invokestatic
  Exception table:
   from   to  target type
     4    25    30   any
  LocalVariableTable: 
   Start  Length  Slot  Name   Signature
   0      33      0    $this       Lscala/actors/scheduler/ActorGC;


public static void onTerminate(scala.actors.scheduler.ActorGC, scala.actors.Reactor, scala.Function0);
  Signature: (Lscala/actors/scheduler/ActorGC;Lscala/actors/Reactor;Lscala/Function0;)V
  Code:
   Stack=3, Locals=4, Args_size=3
	aload_0
	dup
	astore_3
	monitorenter
	aload_0
	invokeinterface	InterfaceMethod scala/actors/scheduler/TerminationMonitor.terminationHandlers:()Lscala/collection/mutable/HashMap;
	getstatic	Field scala/Predef$.MODULE$:Lscala/Predef$;
	aload_1
	invokevirtual	Method scala/Predef$.any2ArrowAssoc:(Ljava/lang/Object;)Lscala/Predef$ArrowAssoc;
	aload_2
	invokevirtual	Method scala/Predef$ArrowAssoc.$minus$greater:(Ljava/lang/Object;)Lscala/Tuple2;
	invokevirtual	Method scala/collection/mutable/HashMap.$plus$eq:(Lscala/Tuple2;)Lscala/collection/mutable/HashMap;
	pop
	aload_3
	monitorexit
	return
	aload_3
	monitorexit
	athrow
  Labels:
  Exception table:
   from   to  target type
     4    27    28   any
  LocalVariableTable: 
   Start  Length  Slot  Name   Signature
   0      31      0    $this       Lscala/actors/scheduler/ActorGC;
   0      31      1    a       Lscala/actors/Reactor;
   0      31      2    f       Lscala/Function0;


public static void terminated(scala.actors.scheduler.ActorGC, scala.actors.Reactor);
  Signature: (Lscala/actors/scheduler/ActorGC;Lscala/actors/Reactor;)V
  Code:
   Stack=5, Locals=8, Args_size=2
	aload_0
	aload_1
	invokeinterface	InterfaceMethod scala/actors/scheduler/ActorGC.scala$actors$scheduler$ActorGC$$super$terminated:(Lscala/actors/Reactor;)V
	aload_0
	dup
	astore_2
	monitorenter
	aload_0
	invokeinterface	InterfaceMethod scala/actors/scheduler/ActorGC.scala$actors$scheduler$ActorGC$$refSet:()Lscala/collection/mutable/HashSet;
	new	class scala/actors/scheduler/ActorGC$$anonfun$terminated$1
	dup
	aload_0
	aload_1
	invokespecial	Method scala/actors/scheduler/ActorGC$$anonfun$terminated$1."<init>":(Lscala/actors/scheduler/ActorGC;Lscala/actors/Reactor;)V
	invokeinterface	InterfaceMethod scala/collection/IterableLike.find:(Lscala/Function1;)Lscala/Option;
	astore_3
	aload_3
	instanceof	class scala/Some
	ifeq	l1 // getstatic
	aload_3
	checkcast	class scala/Some
	astore	4
	aload	4
	invokevirtual	Method scala/Some.x:()Ljava/lang/Object;
	checkcast	class java/lang/ref/Reference
	astore	5
	aload	5
	astore	6
	aload	6
	invokevirtual	Method java/lang/ref/Reference.clear:()V
	aload_0
	invokeinterface	InterfaceMethod scala/actors/scheduler/ActorGC.scala$actors$scheduler$ActorGC$$refSet:()Lscala/collection/mutable/HashSet;
	aload	6
	invokevirtual	Method scala/collection/mutable/HashSet.$minus$eq:(Ljava/lang/Object;)Lscala/collection/mutable/HashSet;
	goto	l2 // pop
l1	getstatic	Field scala/None$.MODULE$:Lscala/None$;
	aload_3
	astore	7
	dup
	ifnonnull	l3 // aload
	pop
	aload	7
	ifnull	l4 // getstatic
	goto	l5 // new
l3	aload	7
	invokevirtual	Method java/lang/Object.equals:(Ljava/lang/Object;)Z
	ifeq	l5 // new
l4	getstatic	Field scala/runtime/BoxedUnit.UNIT:Lscala/runtime/BoxedUnit;
l2	pop
	aload_2
	monitorexit
	return
l5	new	class scala/MatchError
	dup
	aload_3
	invokespecial	Method scala/MatchError."<init>":(Ljava/lang/Object;)V
	athrow
	aload_2
	monitorexit
	athrow
  Labels:
   	l1 = 78 // getstatic
   	l3 = 97 // aload
   	l4 = 105 // getstatic
   	l2 = 108 // pop
   	l5 = 112 // new
  Exception table:
   from   to  target type
    11   111   121   any
   112   121   121   any
  LocalVariableTable: 
   Start  Length  Slot  Name   Signature
   0      124      0    $this       Lscala/actors/scheduler/ActorGC;
   0      124      1    a$1       Lscala/actors/Reactor;
   32      77      3    temp1       Lscala/Option;
   112      9      3    temp1       Lscala/Option;
   45      30      4    temp2       Lscala/Some;
   55      20      5    temp3       Ljava/lang/ref/Reference;
   59      16      6    r       Ljava/lang/ref/Reference;


public static int getPendingCount(scala.actors.scheduler.ActorGC);
  Signature: (Lscala/actors/scheduler/ActorGC;)I
  Code:
   Stack=2, Locals=3, Args_size=1
	aload_0
	dup
	astore_1
	monitorenter
	aload_0
	invokeinterface	InterfaceMethod scala/actors/scheduler/TerminationMonitor.activeActors:()I
	invokestatic	Method scala/runtime/BoxesRunTime.boxToInteger:(I)Ljava/lang/Integer;
	astore_2
	aload_1
	monitorexit
	aload_2
	invokestatic	Method scala/runtime/BoxesRunTime.unboxToInt:(Ljava/lang/Object;)I
	ireturn
	aload_1
	monitorexit
	athrow
  Labels:
  Exception table:
   from   to  target type
     4    16    21   any
  LocalVariableTable: 
   Start  Length  Slot  Name   Signature
   0      24      0    $this       Lscala/actors/scheduler/ActorGC;


public static void setPendingCount(scala.actors.scheduler.ActorGC, int);
  Signature: (Lscala/actors/scheduler/ActorGC;I)V
  Code:
   Stack=2, Locals=3, Args_size=2
	aload_0
	dup
	astore_2
	monitorenter
	aload_0
	iload_1
	invokeinterface	InterfaceMethod scala/actors/scheduler/TerminationMonitor.activeActors_$eq:(I)V
	getstatic	Field scala/runtime/BoxedUnit.UNIT:Lscala/runtime/BoxedUnit;
	pop
	aload_2
	monitorexit
	return
	aload_2
	monitorexit
	athrow
  Labels:
  Exception table:
   from   to  target type
     4    17    18   any
  LocalVariableTable: 
   Start  Length  Slot  Name   Signature
   0      21      0    $this       Lscala/actors/scheduler/ActorGC;
   0      21      1    cnt       I


private static final void drainRefQ$1(scala.actors.scheduler.ActorGC);
  Signature: (Lscala/actors/scheduler/ActorGC;)V
  Code:
   Stack=3, Locals=4, Args_size=1
l3	aload_0
	invokeinterface	InterfaceMethod scala/actors/scheduler/ActorGC.scala$actors$scheduler$ActorGC$$refQ:()Ljava/lang/ref/ReferenceQueue;
	invokevirtual	Method java/lang/ref/ReferenceQueue.poll:()Ljava/lang/ref/Reference;
	astore_2
	aload_2
	dup
	astore_3
	ifnull	l1 // return
	aload_3
	aconst_null
	invokevirtual	Method java/lang/Object.equals:(Ljava/lang/Object;)Z
	ifeq	l2 // aload_0
l1	return
l2	aload_0
	aload_0
	invokeinterface	InterfaceMethod scala/actors/scheduler/TerminationMonitor.activeActors:()I
	iconst_1
	isub
	invokeinterface	InterfaceMethod scala/actors/scheduler/TerminationMonitor.activeActors_$eq:(I)V
	aload_0
	invokeinterface	InterfaceMethod scala/actors/scheduler/ActorGC.scala$actors$scheduler$ActorGC$$refSet:()Lscala/collection/mutable/HashSet;
	aload_2
	invokevirtual	Method scala/collection/mutable/HashSet.$minus$eq:(Ljava/lang/Object;)Lscala/collection/mutable/HashSet;
	pop
	aload_0
	astore_0
	goto	l3 // aload_0
  Labels:
   	l3 = 0 // aload_0
   	l1 = 24 // return
   	l2 = 25 // aload_0
  LocalVariableTable: 
   Start  Length  Slot  Name   Signature
   0      55      0    $this       Lscala/actors/scheduler/ActorGC;
   10      45      2    wr       Ljava/lang/ref/Reference;


public static void $init$(scala.actors.scheduler.ActorGC);
  Signature: (Lscala/actors/scheduler/ActorGC;)V
  Code:
   Stack=3, Locals=1, Args_size=1
	aload_0
	new	class java/lang/ref/ReferenceQueue
	dup
	invokespecial	Method java/lang/ref/ReferenceQueue."<init>":()V
	invokeinterface	InterfaceMethod scala/actors/scheduler/ActorGC.scala$actors$scheduler$ActorGC$_setter_$scala$actors$scheduler$ActorGC$$refQ_$eq:(Ljava/lang/ref/ReferenceQueue;)V
	aload_0
	new	class scala/collection/mutable/HashSet
	dup
	invokespecial	Method scala/collection/mutable/HashSet."<init>":()V
	invokeinterface	InterfaceMethod scala/actors/scheduler/ActorGC.scala$actors$scheduler$ActorGC$_setter_$scala$actors$scheduler$ActorGC$$refSet_$eq:(Lscala/collection/mutable/HashSet;)V
	return
  Labels:
  LocalVariableTable: 
   Start  Length  Slot  Name   Signature
   0      27      0    $this       Lscala/actors/scheduler/ActorGC;


}

