Compiled from "DaemonScheduler.scala"
public final class scala.actors.scheduler.DaemonScheduler extends java.lang.Object
  SourceFile: "DaemonScheduler.scala"
  ScalaSig: length = 0x10A
   05 00 27 07 05 01 02 FFFFFF88 02 09 01 0F 44 61 65 6D
   6F 6E 53 63 68 65 64 75 6C 65 72 0A 02 03 04 01
   09 73 63 68 65 64 75 6C 65 72 0A 02 05 06 01 06
   61 63 74 6F 72 73 0A 01 07 01 05 73 63 61 6C 61
   03 00 10 02 0A 0B 0D 01 02 06 08 0C 02 FFFFFF84 FFFFFF80 FFFFFF80
   FFFFFF88 02 0D 02 0F 44 61 65 6D 6F 6E 53 63 68 65 64
   75 6C 65 72 13 04 0B 0E 16 19 10 02 0F 14 0D 01
   10 0A 02 11 12 01 04 6C 61 6E 67 0A 01 13 01 04
   6A 61 76 61 09 02 15 10 02 06 4F 62 6A 65 63 74
   10 02 0A 17 09 02 18 02 02 13 44 65 6C 65 67 61
   74 69 6E 67 53 63 68 65 64 75 6C 65 72 10 02 1A
   1B 0D 01 06 09 02 1C 06 02 0B 53 63 61 6C 61 4F
   62 6A 65 63 74 08 05 1E 0B FFFFFF84 00 1F 01 06 3C 69
   6E 69 74 3E 14 01 09 08 05 21 0B FFFFFF84 00 22 01 10
   6D 61 6B 65 4E 65 77 53 63 68 65 64 75 6C 65 72
   14 01 23 10 02 24 25 0D 01 04 09 02 26 04 02 0A
   49 53 63 68 65 64 75 6C 65 72 
  minor version: 0
  major version: 49
  Constant pool:
Asciz	SourceFile;
Asciz	DaemonScheduler.scala;
Asciz	printActorDump;
Asciz	()V;
Asciz	Code;
Asciz	scala/actors/scheduler/DaemonScheduler$;
class	scala/actors/scheduler/DaemonScheduler$
Asciz	MODULE$;
Asciz	Lscala/actors/scheduler/DaemonScheduler$;;
NameAndType	MODULE$:Lscala/actors/scheduler/DaemonScheduler$;
Field	scala/actors/scheduler/DaemonScheduler$.MODULE$:Lscala/actors/scheduler/DaemonScheduler$;
NameAndType	printActorDump:()V
Method	scala/actors/scheduler/DaemonScheduler$.printActorDump:()V
Asciz	Deprecated;
Asciz	onLockup;
Asciz	(ILscala/Function0;)V;
NameAndType	onLockup:(ILscala/Function0;)V
Method	scala/actors/scheduler/DaemonScheduler$.onLockup:(ILscala/Function0;)V
Asciz	(Lscala/Function0;)V;
NameAndType	onLockup:(Lscala/Function0;)V
Method	scala/actors/scheduler/DaemonScheduler$.onLockup:(Lscala/Function0;)V
Asciz	tick;
Asciz	(Lscala/actors/Actor;)V;
NameAndType	tick:(Lscala/actors/Actor;)V
Method	scala/actors/scheduler/DaemonScheduler$.tick:(Lscala/actors/Actor;)V
Asciz	managedBlock;
Asciz	(Lscala/concurrent/ManagedBlocker;)V;
NameAndType	managedBlock:(Lscala/concurrent/ManagedBlocker;)V
Method	scala/actors/scheduler/DaemonScheduler$.managedBlock:(Lscala/concurrent/ManagedBlocker;)V
Asciz	onTerminate;
Asciz	(Lscala/actors/Reactor;Lscala/Function0;)V;
NameAndType	onTerminate:(Lscala/actors/Reactor;Lscala/Function0;)V
Method	scala/actors/scheduler/DaemonScheduler$.onTerminate:(Lscala/actors/Reactor;Lscala/Function0;)V
Asciz	terminated;
Asciz	(Lscala/actors/Reactor;)V;
NameAndType	terminated:(Lscala/actors/Reactor;)V
Method	scala/actors/scheduler/DaemonScheduler$.terminated:(Lscala/actors/Reactor;)V
Asciz	newActor;
NameAndType	newActor:(Lscala/actors/Reactor;)V
Method	scala/actors/scheduler/DaemonScheduler$.newActor:(Lscala/actors/Reactor;)V
Asciz	shutdown;
NameAndType	shutdown:()V
Method	scala/actors/scheduler/DaemonScheduler$.shutdown:()V
Asciz	executeFromActor;
Asciz	(Ljava/lang/Runnable;)V;
NameAndType	executeFromActor:(Ljava/lang/Runnable;)V
Method	scala/actors/scheduler/DaemonScheduler$.executeFromActor:(Ljava/lang/Runnable;)V
Asciz	execute;
NameAndType	execute:(Ljava/lang/Runnable;)V
Method	scala/actors/scheduler/DaemonScheduler$.execute:(Ljava/lang/Runnable;)V
NameAndType	execute:(Lscala/Function0;)V
Method	scala/actors/scheduler/DaemonScheduler$.execute:(Lscala/Function0;)V
Asciz	isActive;
Asciz	()Z;
NameAndType	isActive:()Z
Method	scala/actors/scheduler/DaemonScheduler$.isActive:()Z
Asciz	impl_$eq;
Asciz	(Lscala/actors/IScheduler;)V;
NameAndType	impl_$eq:(Lscala/actors/IScheduler;)V
Method	scala/actors/scheduler/DaemonScheduler$.impl_$eq:(Lscala/actors/IScheduler;)V
Asciz	impl;
Asciz	()Lscala/actors/IScheduler;;
NameAndType	impl:()Lscala/actors/IScheduler;
Method	scala/actors/scheduler/DaemonScheduler$.impl:()Lscala/actors/IScheduler;
Asciz	makeNewScheduler;
NameAndType	makeNewScheduler:()Lscala/actors/IScheduler;
Method	scala/actors/scheduler/DaemonScheduler$.makeNewScheduler:()Lscala/actors/IScheduler;
Asciz	ScalaSig;
Asciz	scala/actors/scheduler/DaemonScheduler;
class	scala/actors/scheduler/DaemonScheduler
Asciz	java/lang/Object;
class	java/lang/Object

{
public static final void printActorDump();
  Signature: ()V
  Code:
   Stack=1, Locals=0, Args_size=0
	getstatic	Field scala/actors/scheduler/DaemonScheduler$.MODULE$:Lscala/actors/scheduler/DaemonScheduler$;
	invokevirtual	Method scala/actors/scheduler/DaemonScheduler$.printActorDump:()V
	return
  Labels:
  Deprecated: true

public static final void onLockup(int, scala.Function0);
  Signature: (ILscala/Function0;)V
  Code:
   Stack=3, Locals=2, Args_size=2
	getstatic	Field scala/actors/scheduler/DaemonScheduler$.MODULE$:Lscala/actors/scheduler/DaemonScheduler$;
	iload_0
	aload_1
	invokevirtual	Method scala/actors/scheduler/DaemonScheduler$.onLockup:(ILscala/Function0;)V
	return
  Labels:
  Deprecated: true

public static final void onLockup(scala.Function0);
  Signature: (Lscala/Function0;)V
  Code:
   Stack=2, Locals=1, Args_size=1
	getstatic	Field scala/actors/scheduler/DaemonScheduler$.MODULE$:Lscala/actors/scheduler/DaemonScheduler$;
	aload_0
	invokevirtual	Method scala/actors/scheduler/DaemonScheduler$.onLockup:(Lscala/Function0;)V
	return
  Labels:
  Deprecated: true

public static final void tick(scala.actors.Actor);
  Signature: (Lscala/actors/Actor;)V
  Code:
   Stack=2, Locals=1, Args_size=1
	getstatic	Field scala/actors/scheduler/DaemonScheduler$.MODULE$:Lscala/actors/scheduler/DaemonScheduler$;
	aload_0
	invokevirtual	Method scala/actors/scheduler/DaemonScheduler$.tick:(Lscala/actors/Actor;)V
	return
  Labels:
  Deprecated: true

public static final void managedBlock(scala.concurrent.ManagedBlocker);
  Signature: (Lscala/concurrent/ManagedBlocker;)V
  Code:
   Stack=2, Locals=1, Args_size=1
	getstatic	Field scala/actors/scheduler/DaemonScheduler$.MODULE$:Lscala/actors/scheduler/DaemonScheduler$;
	aload_0
	invokevirtual	Method scala/actors/scheduler/DaemonScheduler$.managedBlock:(Lscala/concurrent/ManagedBlocker;)V
	return
  Labels:

public static final void onTerminate(scala.actors.Reactor, scala.Function0);
  Signature: (Lscala/actors/Reactor;Lscala/Function0;)V
  Code:
   Stack=3, Locals=2, Args_size=2
	getstatic	Field scala/actors/scheduler/DaemonScheduler$.MODULE$:Lscala/actors/scheduler/DaemonScheduler$;
	aload_0
	aload_1
	invokevirtual	Method scala/actors/scheduler/DaemonScheduler$.onTerminate:(Lscala/actors/Reactor;Lscala/Function0;)V
	return
  Labels:

public static final void terminated(scala.actors.Reactor);
  Signature: (Lscala/actors/Reactor;)V
  Code:
   Stack=2, Locals=1, Args_size=1
	getstatic	Field scala/actors/scheduler/DaemonScheduler$.MODULE$:Lscala/actors/scheduler/DaemonScheduler$;
	aload_0
	invokevirtual	Method scala/actors/scheduler/DaemonScheduler$.terminated:(Lscala/actors/Reactor;)V
	return
  Labels:

public static final void newActor(scala.actors.Reactor);
  Signature: (Lscala/actors/Reactor;)V
  Code:
   Stack=2, Locals=1, Args_size=1
	getstatic	Field scala/actors/scheduler/DaemonScheduler$.MODULE$:Lscala/actors/scheduler/DaemonScheduler$;
	aload_0
	invokevirtual	Method scala/actors/scheduler/DaemonScheduler$.newActor:(Lscala/actors/Reactor;)V
	return
  Labels:

public static final void shutdown();
  Signature: ()V
  Code:
   Stack=1, Locals=0, Args_size=0
	getstatic	Field scala/actors/scheduler/DaemonScheduler$.MODULE$:Lscala/actors/scheduler/DaemonScheduler$;
	invokevirtual	Method scala/actors/scheduler/DaemonScheduler$.shutdown:()V
	return
  Labels:

public static final void executeFromActor(java.lang.Runnable);
  Signature: (Ljava/lang/Runnable;)V
  Code:
   Stack=2, Locals=1, Args_size=1
	getstatic	Field scala/actors/scheduler/DaemonScheduler$.MODULE$:Lscala/actors/scheduler/DaemonScheduler$;
	aload_0
	invokevirtual	Method scala/actors/scheduler/DaemonScheduler$.executeFromActor:(Ljava/lang/Runnable;)V
	return
  Labels:

public static final void execute(java.lang.Runnable);
  Signature: (Ljava/lang/Runnable;)V
  Code:
   Stack=2, Locals=1, Args_size=1
	getstatic	Field scala/actors/scheduler/DaemonScheduler$.MODULE$:Lscala/actors/scheduler/DaemonScheduler$;
	aload_0
	invokevirtual	Method scala/actors/scheduler/DaemonScheduler$.execute:(Ljava/lang/Runnable;)V
	return
  Labels:

public static final void execute(scala.Function0);
  Signature: (Lscala/Function0;)V
  Code:
   Stack=2, Locals=1, Args_size=1
	getstatic	Field scala/actors/scheduler/DaemonScheduler$.MODULE$:Lscala/actors/scheduler/DaemonScheduler$;
	aload_0
	invokevirtual	Method scala/actors/scheduler/DaemonScheduler$.execute:(Lscala/Function0;)V
	return
  Labels:

public static final boolean isActive();
  Signature: ()Z
  Code:
   Stack=1, Locals=0, Args_size=0
	getstatic	Field scala/actors/scheduler/DaemonScheduler$.MODULE$:Lscala/actors/scheduler/DaemonScheduler$;
	invokevirtual	Method scala/actors/scheduler/DaemonScheduler$.isActive:()Z
	ireturn
  Labels:

public static final void impl_$eq(scala.actors.IScheduler);
  Signature: (Lscala/actors/IScheduler;)V
  Code:
   Stack=2, Locals=1, Args_size=1
	getstatic	Field scala/actors/scheduler/DaemonScheduler$.MODULE$:Lscala/actors/scheduler/DaemonScheduler$;
	aload_0
	invokevirtual	Method scala/actors/scheduler/DaemonScheduler$.impl_$eq:(Lscala/actors/IScheduler;)V
	return
  Labels:

public static final scala.actors.IScheduler impl();
  Signature: ()Lscala/actors/IScheduler;
  Code:
   Stack=1, Locals=0, Args_size=0
	getstatic	Field scala/actors/scheduler/DaemonScheduler$.MODULE$:Lscala/actors/scheduler/DaemonScheduler$;
	invokevirtual	Method scala/actors/scheduler/DaemonScheduler$.impl:()Lscala/actors/IScheduler;
	areturn
  Labels:

public static final scala.actors.IScheduler makeNewScheduler();
  Signature: ()Lscala/actors/IScheduler;
  Code:
   Stack=1, Locals=0, Args_size=0
	getstatic	Field scala/actors/scheduler/DaemonScheduler$.MODULE$:Lscala/actors/scheduler/DaemonScheduler$;
	invokevirtual	Method scala/actors/scheduler/DaemonScheduler$.makeNewScheduler:()Lscala/actors/IScheduler;
	areturn
  Labels:

}

