Compiled from "DefaultThreadPoolScheduler.scala"
public final class scala.actors.scheduler.DefaultThreadPoolScheduler$$anon$1 extends java.lang.Object implements java.util.concurrent.ThreadFactory
  SourceFile: "DefaultThreadPoolScheduler.scala"
  Scala: length = 0x
   
  InnerClass: 
   public final #47= #15 of #32; //$anon$1=class scala/actors/scheduler/DefaultThreadPoolScheduler$$anon$1 of class scala/actors/scheduler/DefaultThreadPoolScheduler
  minor version: 0
  major version: 49
  Constant pool:
const #1 = Asciz	SourceFile;
const #2 = Asciz	DefaultThreadPoolScheduler.scala;
const #3 = Asciz	$outer;
const #4 = Asciz	Lscala/actors/scheduler/DefaultThreadPoolScheduler;;
const #5 = Asciz	<init>;
const #6 = Asciz	(Lscala/actors/scheduler/DefaultThreadPoolScheduler;)V;
const #7 = Asciz	Code;
const #8 = Asciz	LineNumberTable;
const #9 = Asciz	java/lang/NullPointerException;
const #10 = class	#9;	//  java/lang/NullPointerException
const #11 = Asciz	()V;
const #12 = NameAndType	#5:#11;//  "<init>":()V
const #13 = Method	#10.#12;	//  java/lang/NullPointerException."<init>":()V
const #14 = Asciz	scala/actors/scheduler/DefaultThreadPoolScheduler$$anon$1;
const #15 = class	#14;	//  scala/actors/scheduler/DefaultThreadPoolScheduler$$anon$1
const #16 = NameAndType	#3:#4;//  $outer:Lscala/actors/scheduler/DefaultThreadPoolScheduler;
const #17 = Field	#15.#16;	//  scala/actors/scheduler/DefaultThreadPoolScheduler$$anon$1.$outer:Lscala/actors/scheduler/DefaultThreadPoolScheduler;
const #18 = Asciz	java/lang/Object;
const #19 = class	#18;	//  java/lang/Object
const #20 = Method	#19.#12;	//  java/lang/Object."<init>":()V
const #21 = Asciz	this;
const #22 = Asciz	Lscala/actors/scheduler/DefaultThreadPoolScheduler$$anon$1;;
const #23 = Asciz	LocalVariableTable;
const #24 = Asciz	newThread;
const #25 = Asciz	(Ljava/lang/Runnable;)Ljava/lang/Thread;;
const #26 = Asciz	java/lang/Thread;
const #27 = class	#26;	//  java/lang/Thread
const #28 = Asciz	(Ljava/lang/Runnable;)V;
const #29 = NameAndType	#5:#28;//  "<init>":(Ljava/lang/Runnable;)V
const #30 = Method	#27.#29;	//  java/lang/Thread."<init>":(Ljava/lang/Runnable;)V
const #31 = Asciz	scala/actors/scheduler/DefaultThreadPoolScheduler;
const #32 = class	#31;	//  scala/actors/scheduler/DefaultThreadPoolScheduler
const #33 = Asciz	scala$actors$scheduler$DefaultThreadPoolScheduler$$daemon;
const #34 = Asciz	Z;
const #35 = NameAndType	#33:#34;//  scala$actors$scheduler$DefaultThreadPoolScheduler$$daemon:Z
const #36 = Field	#32.#35;	//  scala/actors/scheduler/DefaultThreadPoolScheduler.scala$actors$scheduler$DefaultThreadPoolScheduler$$daemon:Z
const #37 = Asciz	setDaemon;
const #38 = Asciz	(Z)V;
const #39 = NameAndType	#37:#38;//  setDaemon:(Z)V
const #40 = Method	#27.#39;	//  java/lang/Thread.setDaemon:(Z)V
const #41 = Asciz	r;
const #42 = Asciz	Ljava/lang/Runnable;;
const #43 = Asciz	t;
const #44 = Asciz	Ljava/lang/Thread;;
const #45 = Asciz	Scala;
const #46 = Asciz	InnerClasses;
const #47 = Asciz	$anon$1;
const #48 = Asciz	java/util/concurrent/ThreadFactory;
const #49 = class	#48;	//  java/util/concurrent/ThreadFactory

{
public scala.actors.scheduler.DefaultThreadPoolScheduler$$anon$1(scala.actors.scheduler.DefaultThreadPoolScheduler);
  Code:
   Stack=2, Locals=2, Args_size=2
   0:	aload_1
   1:	ifnonnull	12
   4:	new	#10; //class java/lang/NullPointerException
   7:	dup
   8:	invokespecial	#13; //Method java/lang/NullPointerException."<init>":()V
   11:	athrow
   12:	aload_0
   13:	aload_1
   14:	putfield	#17; //Field $outer:Lscala/actors/scheduler/DefaultThreadPoolScheduler;
   17:	aload_0
   18:	invokespecial	#20; //Method java/lang/Object."<init>":()V
   21:	return
  LineNumberTable: 
   line 32: 0

  LocalVariableTable: 
   Start  Length  Slot  Name   Signature
   0      22      0    this       Lscala/actors/scheduler/DefaultThreadPoolScheduler$$anon$1;
   0      22      1    $outer       Lscala/actors/scheduler/DefaultThreadPoolScheduler;


public java.lang.Thread newThread(java.lang.Runnable);
  Code:
   Stack=3, Locals=3, Args_size=2
   0:	new	#27; //class java/lang/Thread
   3:	dup
   4:	aload_1
   5:	invokespecial	#30; //Method java/lang/Thread."<init>":(Ljava/lang/Runnable;)V
   8:	astore_2
   9:	aload_2
   10:	aload_0
   11:	getfield	#17; //Field $outer:Lscala/actors/scheduler/DefaultThreadPoolScheduler;
   14:	getfield	#36; //Field scala/actors/scheduler/DefaultThreadPoolScheduler.scala$actors$scheduler$DefaultThreadPoolScheduler$$daemon:Z
   17:	invokevirtual	#40; //Method java/lang/Thread.setDaemon:(Z)V
   20:	aload_2
   21:	areturn
  LineNumberTable: 
   line 34: 0
   line 36: 9
   line 35: 10
   line 36: 20

  LocalVariableTable: 
   Start  Length  Slot  Name   Signature
   0      22      0    this       Lscala/actors/scheduler/DefaultThreadPoolScheduler$$anon$1;
   0      22      1    r       Ljava/lang/Runnable;
   9      12      2    t       Ljava/lang/Thread;


}

