Compiled from "DefaultExecutorScheduler.scala"
public class scala.actors.scheduler.DefaultExecutorScheduler extends scala.actors.scheduler.SchedulerService implements scala.actors.scheduler.ExecutorScheduler,scala.ScalaObject
  SourceFile: "DefaultExecutorScheduler.scala"
  ScalaSig: length = 0x2B1
   05 00 5C 06 08 01 02 FFFFFF84 FFFFFF80 FFFFFF80 FFFFFF80 00 09 02 18 44
   65 66 61 75 6C 74 45 78 65 63 75 74 6F 72 53 63
   68 65 64 75 6C 65 72 0A 02 03 04 01 09 73 63 68
   65 64 75 6C 65 72 0A 02 05 06 01 06 61 63 74 6F
   72 73 0A 01 07 01 05 73 63 61 6C 61 03 00 13 04
   00 0A 0E 11 10 02 0B 0C 0D 01 02 09 02 0D 02 02
   10 53 63 68 65 64 75 6C 65 72 53 65 72 76 69 63
   65 10 02 0B 0F 09 02 10 02 02 11 45 78 65 63 75
   74 6F 72 53 63 68 65 64 75 6C 65 72 10 02 12 13
   0D 01 06 09 02 14 06 02 0B 53 63 61 6C 61 4F 62
   6A 65 63 74 08 08 16 00 FFFFFF82 FFFFFF80 FFFFFFA0 FFFFFF80 04 17 01 06
   64 61 65 6D 6F 6E 10 02 12 18 09 02 19 06 02 07
   42 6F 6F 6C 65 61 6E 08 05 1B 00 FFFFFF84 00 1C 01 06
   3C 69 6E 69 74 3E 14 02 1D 1E 10 02 0B 00 08 05
   16 1A FFFFFFC0 00 17 08 05 1B 00 FFFFFF84 00 20 14 01 1D 08
   07 22 00 FFFFFFC2 FFFFFF80 FFFFFF84 04 23 01 09 77 6F 72 6B 51 75
   65 75 65 15 01 24 10 03 25 2C 2E 0D 01 26 0A 02
   27 28 01 0A 63 6F 6E 63 75 72 72 65 6E 74 0A 02
   29 2A 01 04 75 74 69 6C 0A 01 2B 01 04 6A 61 76
   61 09 02 2D 26 02 13 4C 69 6E 6B 65 64 42 6C 6F
   63 6B 69 6E 67 51 75 65 75 65 10 02 2F 32 0E 02
   12 30 09 02 31 06 01 06 50 72 65 64 65 66 09 02
   33 34 02 08 52 75 6E 6E 61 62 6C 65 0A 02 31 06
   08 06 36 00 FFFFFFA0 FFFFFF80 04 24 01 0A 77 6F 72 6B 51 75
   65 75 65 20 08 07 38 00 FFFFFFC2 FFFFFF80 FFFFFF84 04 39 01 0D 74
   68 72 65 61 64 46 61 63 74 6F 72 79 15 01 3A 12
   03 3B 3F 45 06 08 3C 3D FFFFFF84 FFFFFF80 FFFFFF80 FFFFFF80 00 3A 02 0C
   3C 72 65 66 69 6E 65 6D 65 6E 74 3E 08 06 3E 00
   FFFFFFA0 FFFFFF80 04 3A 01 0E 74 68 72 65 61 64 46 61 63 74
   6F 72 79 20 10 02 40 43 0D 01 41 0A 02 42 2A 01
   04 6C 61 6E 67 09 02 44 41 02 06 4F 62 6A 65 63
   74 10 02 25 46 09 02 47 26 02 0D 54 68 72 65 61
   64 46 61 63 74 6F 72 79 08 07 49 00 FFFFFFC2 FFFFFF80 FFFFFF84 04
   4A 01 0A 74 68 72 65 61 64 50 6F 6F 6C 15 01 4B
   10 02 25 4C 09 02 4D 26 02 12 54 68 72 65 61 64
   50 6F 6F 6C 45 78 65 63 75 74 6F 72 08 06 4F 00
   FFFFFFA0 FFFFFF80 04 4B 01 0B 74 68 72 65 61 64 50 6F 6F 6C
   20 08 07 51 00 FFFFFFC2 FFFFFF80 FFFFFF84 00 4A 01 08 65 78 65 63
   75 74 6F 72 08 06 53 00 FFFFFFA0 FFFFFF80 04 4B 01 09 65 78
   65 63 75 74 6F 72 20 08 07 55 00 FFFFFFC2 FFFFFF80 FFFFFF84 20 56
   01 0A 43 48 45 43 4B 5F 46 52 45 51 15 01 57 10
   02 12 58 09 02 59 06 02 03 49 6E 74 08 06 5B 00
   FFFFFFA0 FFFFFF80 04 57 01 0B 43 48 45 43 4B 5F 46 52 45 51
   20 
  InnerClass: 
   public final #121= #42 of #21; //$anon$1=class scala/actors/scheduler/DefaultExecutorScheduler$$anon$1 of class scala/actors/scheduler/DefaultExecutorScheduler
  minor version: 0
  major version: 49
  Constant pool:
const #1 = Asciz	SourceFile;
const #2 = Asciz	DefaultExecutorScheduler.scala;
const #3 = Asciz	CHECK_FREQ;
const #4 = Asciz	I;
const #5 = Asciz	executor;
const #6 = Asciz	Ljava/util/concurrent/ThreadPoolExecutor;;
const #7 = Asciz	threadPool;
const #8 = Asciz	threadFactory;
const #9 = Asciz	Ljava/lang/Object;;
const #10 = Asciz	workQueue;
const #11 = Asciz	Ljava/util/concurrent/LinkedBlockingQueue;;
const #12 = Asciz	Ljava/util/concurrent/LinkedBlockingQueue<Ljava/lang/Runnable;>;;
const #13 = Asciz	Signature;
const #14 = Asciz	scala$actors$scheduler$DefaultExecutorScheduler$$daemon;
const #15 = Asciz	Z;
const #16 = Asciz	<init>;
const #17 = Asciz	(Z)V;
const #18 = Asciz	Code;
const #19 = Asciz	LineNumberTable;
const #20 = Asciz	scala/actors/scheduler/DefaultExecutorScheduler;
const #21 = class	#20;	//  scala/actors/scheduler/DefaultExecutorScheduler
const #22 = NameAndType	#14:#15;//  scala$actors$scheduler$DefaultExecutorScheduler$$daemon:Z
const #23 = Field	#21.#22;	//  scala/actors/scheduler/DefaultExecutorScheduler.scala$actors$scheduler$DefaultExecutorScheduler$$daemon:Z
const #24 = Asciz	scala/actors/scheduler/SchedulerService;
const #25 = class	#24;	//  scala/actors/scheduler/SchedulerService
const #26 = NameAndType	#16:#17;//  "<init>":(Z)V
const #27 = Method	#25.#26;	//  scala/actors/scheduler/SchedulerService."<init>":(Z)V
const #28 = Asciz	scala/actors/scheduler/ExecutorScheduler$class;
const #29 = class	#28;	//  scala/actors/scheduler/ExecutorScheduler$class
const #30 = Asciz	$init$;
const #31 = Asciz	(Lscala/actors/scheduler/ExecutorScheduler;)V;
const #32 = NameAndType	#30:#31;//  $init$:(Lscala/actors/scheduler/ExecutorScheduler;)V
const #33 = Method	#29.#32;	//  scala/actors/scheduler/ExecutorScheduler$class.$init$:(Lscala/actors/scheduler/ExecutorScheduler;)V
const #34 = Asciz	java/util/concurrent/LinkedBlockingQueue;
const #35 = class	#34;	//  java/util/concurrent/LinkedBlockingQueue
const #36 = Asciz	()V;
const #37 = NameAndType	#16:#36;//  "<init>":()V
const #38 = Method	#35.#37;	//  java/util/concurrent/LinkedBlockingQueue."<init>":()V
const #39 = NameAndType	#10:#11;//  workQueue:Ljava/util/concurrent/LinkedBlockingQueue;
const #40 = Field	#21.#39;	//  scala/actors/scheduler/DefaultExecutorScheduler.workQueue:Ljava/util/concurrent/LinkedBlockingQueue;
const #41 = Asciz	scala/actors/scheduler/DefaultExecutorScheduler$$anon$1;
const #42 = class	#41;	//  scala/actors/scheduler/DefaultExecutorScheduler$$anon$1
const #43 = Asciz	(Lscala/actors/scheduler/DefaultExecutorScheduler;)V;
const #44 = NameAndType	#16:#43;//  "<init>":(Lscala/actors/scheduler/DefaultExecutorScheduler;)V
const #45 = Method	#42.#44;	//  scala/actors/scheduler/DefaultExecutorScheduler$$anon$1."<init>":(Lscala/actors/scheduler/DefaultExecutorScheduler;)V
const #46 = NameAndType	#8:#9;//  threadFactory:Ljava/lang/Object;
const #47 = Field	#21.#46;	//  scala/actors/scheduler/DefaultExecutorScheduler.threadFactory:Ljava/lang/Object;
const #48 = Asciz	java/util/concurrent/ThreadPoolExecutor;
const #49 = class	#48;	//  java/util/concurrent/ThreadPoolExecutor
const #50 = Asciz	scala/actors/scheduler/ThreadPoolConfig$;
const #51 = class	#50;	//  scala/actors/scheduler/ThreadPoolConfig$
const #52 = Asciz	MODULE$;
const #53 = Asciz	Lscala/actors/scheduler/ThreadPoolConfig$;;
const #54 = NameAndType	#52:#53;//  MODULE$:Lscala/actors/scheduler/ThreadPoolConfig$;
const #55 = Field	#51.#54;	//  scala/actors/scheduler/ThreadPoolConfig$.MODULE$:Lscala/actors/scheduler/ThreadPoolConfig$;
const #56 = Asciz	corePoolSize;
const #57 = Asciz	()I;
const #58 = NameAndType	#56:#57;//  corePoolSize:()I
const #59 = Method	#51.#58;	//  scala/actors/scheduler/ThreadPoolConfig$.corePoolSize:()I
const #60 = Asciz	maxPoolSize;
const #61 = NameAndType	#60:#57;//  maxPoolSize:()I
const #62 = Method	#51.#61;	//  scala/actors/scheduler/ThreadPoolConfig$.maxPoolSize:()I
const #63 = long	50l;
const #65 = Asciz	java/util/concurrent/TimeUnit;
const #66 = class	#65;	//  java/util/concurrent/TimeUnit
const #67 = Asciz	MILLISECONDS;
const #68 = Asciz	Ljava/util/concurrent/TimeUnit;;
const #69 = NameAndType	#67:#68;//  MILLISECONDS:Ljava/util/concurrent/TimeUnit;
const #70 = Field	#66.#69;	//  java/util/concurrent/TimeUnit.MILLISECONDS:Ljava/util/concurrent/TimeUnit;
const #71 = Asciz	()Ljava/util/concurrent/LinkedBlockingQueue;;
const #72 = NameAndType	#10:#71;//  workQueue:()Ljava/util/concurrent/LinkedBlockingQueue;
const #73 = Method	#21.#72;	//  scala/actors/scheduler/DefaultExecutorScheduler.workQueue:()Ljava/util/concurrent/LinkedBlockingQueue;
const #74 = Asciz	()Ljava/lang/Object;;
const #75 = NameAndType	#8:#74;//  threadFactory:()Ljava/lang/Object;
const #76 = Method	#21.#75;	//  scala/actors/scheduler/DefaultExecutorScheduler.threadFactory:()Ljava/lang/Object;
const #77 = Asciz	java/util/concurrent/ThreadFactory;
const #78 = class	#77;	//  java/util/concurrent/ThreadFactory
const #79 = Asciz	(IIJLjava/util/concurrent/TimeUnit;Ljava/util/concurrent/BlockingQueue;Ljava/util/concurrent/ThreadFactory;)V;
const #80 = NameAndType	#16:#79;//  "<init>":(IIJLjava/util/concurrent/TimeUnit;Ljava/util/concurrent/BlockingQueue;Ljava/util/concurrent/ThreadFactory;)V
const #81 = Method	#49.#80;	//  java/util/concurrent/ThreadPoolExecutor."<init>":(IIJLjava/util/concurrent/TimeUnit;Ljava/util/concurrent/BlockingQueue;Ljava/util/concurrent/ThreadFactory;)V
const #82 = NameAndType	#7:#6;//  threadPool:Ljava/util/concurrent/ThreadPoolExecutor;
const #83 = Field	#21.#82;	//  scala/actors/scheduler/DefaultExecutorScheduler.threadPool:Ljava/util/concurrent/ThreadPoolExecutor;
const #84 = Asciz	()Ljava/util/concurrent/ThreadPoolExecutor;;
const #85 = NameAndType	#7:#84;//  threadPool:()Ljava/util/concurrent/ThreadPoolExecutor;
const #86 = Method	#21.#85;	//  scala/actors/scheduler/DefaultExecutorScheduler.threadPool:()Ljava/util/concurrent/ThreadPoolExecutor;
const #87 = NameAndType	#5:#6;//  executor:Ljava/util/concurrent/ThreadPoolExecutor;
const #88 = Field	#21.#87;	//  scala/actors/scheduler/DefaultExecutorScheduler.executor:Ljava/util/concurrent/ThreadPoolExecutor;
const #89 = int	50;
const #90 = NameAndType	#3:#4;//  CHECK_FREQ:I
const #91 = Field	#21.#90;	//  scala/actors/scheduler/DefaultExecutorScheduler.CHECK_FREQ:I
const #92 = Asciz	this;
const #93 = Asciz	Lscala/actors/scheduler/DefaultExecutorScheduler;;
const #94 = Asciz	daemon;
const #95 = Asciz	LocalVariableTable;
const #96 = Asciz	()Ljava/util/concurrent/ExecutorService;;
const #97 = NameAndType	#5:#84;//  executor:()Ljava/util/concurrent/ThreadPoolExecutor;
const #98 = Method	#21.#97;	//  scala/actors/scheduler/DefaultExecutorScheduler.executor:()Ljava/util/concurrent/ThreadPoolExecutor;
const #99 = Asciz	()Ljava/util/concurrent/LinkedBlockingQueue<Ljava/lang/Runnable;>;;
const #100 = Method	#21.#26;	//  scala/actors/scheduler/DefaultExecutorScheduler."<init>":(Z)V
const #101 = Asciz	isActive;
const #102 = Asciz	()Z;
const #103 = Asciz	(Lscala/actors/scheduler/ExecutorScheduler;)Z;
const #104 = NameAndType	#101:#103;//  isActive:(Lscala/actors/scheduler/ExecutorScheduler;)Z
const #105 = Method	#29.#104;	//  scala/actors/scheduler/ExecutorScheduler$class.isActive:(Lscala/actors/scheduler/ExecutorScheduler;)Z
const #106 = Asciz	onShutdown;
const #107 = NameAndType	#106:#31;//  onShutdown:(Lscala/actors/scheduler/ExecutorScheduler;)V
const #108 = Method	#29.#107;	//  scala/actors/scheduler/ExecutorScheduler$class.onShutdown:(Lscala/actors/scheduler/ExecutorScheduler;)V
const #109 = Asciz	executeFromActor;
const #110 = Asciz	(Ljava/lang/Runnable;)V;
const #111 = Asciz	(Lscala/actors/scheduler/ExecutorScheduler;Ljava/lang/Runnable;)V;
const #112 = NameAndType	#109:#111;//  executeFromActor:(Lscala/actors/scheduler/ExecutorScheduler;Ljava/lang/Runnable;)V
const #113 = Method	#29.#112;	//  scala/actors/scheduler/ExecutorScheduler$class.executeFromActor:(Lscala/actors/scheduler/ExecutorScheduler;Ljava/lang/Runnable;)V
const #114 = Asciz	task;
const #115 = Asciz	Ljava/lang/Runnable;;
const #116 = Asciz	execute;
const #117 = NameAndType	#116:#111;//  execute:(Lscala/actors/scheduler/ExecutorScheduler;Ljava/lang/Runnable;)V
const #118 = Method	#29.#117;	//  scala/actors/scheduler/ExecutorScheduler$class.execute:(Lscala/actors/scheduler/ExecutorScheduler;Ljava/lang/Runnable;)V
const #119 = Asciz	ScalaSig;
const #120 = Asciz	InnerClasses;
const #121 = Asciz	$anon$1;
const #122 = Asciz	scala/actors/scheduler/ExecutorScheduler;
const #123 = class	#122;	//  scala/actors/scheduler/ExecutorScheduler
const #124 = Asciz	scala/ScalaObject;
const #125 = class	#124;	//  scala/ScalaObject

{
public final boolean scala$actors$scheduler$DefaultExecutorScheduler$$daemon;

public scala.actors.scheduler.DefaultExecutorScheduler(boolean);
  Code:
   Stack=10, Locals=2, Args_size=2
   0:	aload_0
   1:	iload_1
   2:	putfield	#23; //Field scala$actors$scheduler$DefaultExecutorScheduler$$daemon:Z
   5:	aload_0
   6:	iload_1
   7:	invokespecial	#27; //Method scala/actors/scheduler/SchedulerService."<init>":(Z)V
   10:	aload_0
   11:	invokestatic	#33; //Method scala/actors/scheduler/ExecutorScheduler$class.$init$:(Lscala/actors/scheduler/ExecutorScheduler;)V
   14:	aload_0
   15:	new	#35; //class java/util/concurrent/LinkedBlockingQueue
   18:	dup
   19:	invokespecial	#38; //Method java/util/concurrent/LinkedBlockingQueue."<init>":()V
   22:	putfield	#40; //Field workQueue:Ljava/util/concurrent/LinkedBlockingQueue;
   25:	aload_0
   26:	new	#42; //class scala/actors/scheduler/DefaultExecutorScheduler$$anon$1
   29:	dup
   30:	aload_0
   31:	invokespecial	#45; //Method scala/actors/scheduler/DefaultExecutorScheduler$$anon$1."<init>":(Lscala/actors/scheduler/DefaultExecutorScheduler;)V
   34:	putfield	#47; //Field threadFactory:Ljava/lang/Object;
   37:	aload_0
   38:	new	#49; //class java/util/concurrent/ThreadPoolExecutor
   41:	dup
   42:	getstatic	#55; //Field scala/actors/scheduler/ThreadPoolConfig$.MODULE$:Lscala/actors/scheduler/ThreadPoolConfig$;
   45:	invokevirtual	#59; //Method scala/actors/scheduler/ThreadPoolConfig$.corePoolSize:()I
   48:	getstatic	#55; //Field scala/actors/scheduler/ThreadPoolConfig$.MODULE$:Lscala/actors/scheduler/ThreadPoolConfig$;
   51:	invokevirtual	#62; //Method scala/actors/scheduler/ThreadPoolConfig$.maxPoolSize:()I
   54:	ldc2_w	#63; //long 50l
   57:	getstatic	#70; //Field java/util/concurrent/TimeUnit.MILLISECONDS:Ljava/util/concurrent/TimeUnit;
   60:	aload_0
   61:	invokespecial	#73; //Method workQueue:()Ljava/util/concurrent/LinkedBlockingQueue;
   64:	aload_0
   65:	invokespecial	#76; //Method threadFactory:()Ljava/lang/Object;
   68:	checkcast	#78; //class java/util/concurrent/ThreadFactory
   71:	invokespecial	#81; //Method java/util/concurrent/ThreadPoolExecutor."<init>":(IIJLjava/util/concurrent/TimeUnit;Ljava/util/concurrent/BlockingQueue;Ljava/util/concurrent/ThreadFactory;)V
   74:	putfield	#83; //Field threadPool:Ljava/util/concurrent/ThreadPoolExecutor;
   77:	aload_0
   78:	aload_0
   79:	invokespecial	#86; //Method threadPool:()Ljava/util/concurrent/ThreadPoolExecutor;
   82:	putfield	#88; //Field executor:Ljava/util/concurrent/ThreadPoolExecutor;
   85:	aload_0
   86:	ldc	#89; //int 50
   88:	putfield	#91; //Field CHECK_FREQ:I
   91:	return
  LineNumberTable: 
   line 27: 0
   line 28: 6
   line 27: 7
   line 33: 14
   line 35: 25
   line 43: 37
   line 44: 48
   line 45: 54
   line 46: 57
   line 47: 60
   line 48: 64
   line 43: 71
   line 50: 77
   line 52: 85

  LocalVariableTable: 
   Start  Length  Slot  Name   Signature
   0      92      0    this       Lscala/actors/scheduler/DefaultExecutorScheduler;
   0      92      1    daemon       Z


public java.util.concurrent.ExecutorService executor();
  Code:
   Stack=1, Locals=1, Args_size=1
   0:	aload_0
   1:	invokevirtual	#98; //Method executor:()Ljava/util/concurrent/ThreadPoolExecutor;
   4:	areturn
  LineNumberTable: 
   line 27: 0


public int CHECK_FREQ();
  Code:
   Stack=1, Locals=1, Args_size=1
   0:	aload_0
   1:	getfield	#91; //Field CHECK_FREQ:I
   4:	ireturn
  LineNumberTable: 
   line 52: 0


public java.util.concurrent.ThreadPoolExecutor executor();
  Code:
   Stack=1, Locals=1, Args_size=1
   0:	aload_0
   1:	getfield	#88; //Field executor:Ljava/util/concurrent/ThreadPoolExecutor;
   4:	areturn
  LineNumberTable: 
   line 50: 0


public scala.actors.scheduler.DefaultExecutorScheduler();
  Code:
   Stack=2, Locals=1, Args_size=1
   0:	aload_0
   1:	iconst_0
   2:	invokespecial	#100; //Method "<init>":(Z)V
   5:	return
  LineNumberTable: 
   line 31: 0


public boolean isActive();
  Code:
   Stack=1, Locals=1, Args_size=1
   0:	aload_0
   1:	invokestatic	#105; //Method scala/actors/scheduler/ExecutorScheduler$class.isActive:(Lscala/actors/scheduler/ExecutorScheduler;)Z
   4:	ireturn
  LineNumberTable: 
   line 27: 0


public void onShutdown();
  Code:
   Stack=1, Locals=1, Args_size=1
   0:	aload_0
   1:	invokestatic	#108; //Method scala/actors/scheduler/ExecutorScheduler$class.onShutdown:(Lscala/actors/scheduler/ExecutorScheduler;)V
   4:	return
  LineNumberTable: 
   line 27: 0


public void executeFromActor(java.lang.Runnable);
  Code:
   Stack=2, Locals=2, Args_size=2
   0:	aload_0
   1:	aload_1
   2:	invokestatic	#113; //Method scala/actors/scheduler/ExecutorScheduler$class.executeFromActor:(Lscala/actors/scheduler/ExecutorScheduler;Ljava/lang/Runnable;)V
   5:	return
  LineNumberTable: 
   line 27: 0

  LocalVariableTable: 
   Start  Length  Slot  Name   Signature
   0      6      0    this       Lscala/actors/scheduler/DefaultExecutorScheduler;
   0      6      1    task       Ljava/lang/Runnable;


public void execute(java.lang.Runnable);
  Code:
   Stack=2, Locals=2, Args_size=2
   0:	aload_0
   1:	aload_1
   2:	invokestatic	#118; //Method scala/actors/scheduler/ExecutorScheduler$class.execute:(Lscala/actors/scheduler/ExecutorScheduler;Ljava/lang/Runnable;)V
   5:	return
  LineNumberTable: 
   line 27: 0

  LocalVariableTable: 
   Start  Length  Slot  Name   Signature
   0      6      0    this       Lscala/actors/scheduler/DefaultExecutorScheduler;
   0      6      1    task       Ljava/lang/Runnable;


}

