Compiled from "DefaultThreadPoolScheduler.scala"
public class scala.actors.scheduler.DefaultThreadPoolScheduler extends scala.actors.scheduler.ThreadPoolScheduler implements scala.ScalaObject
  SourceFile: "DefaultThreadPoolScheduler.scala"
  ScalaSig: length = 0xCF
   05 00 1C 06 09 01 02 FFFFFF84 FFFFFF80 FFFFFF80 FFFFFF80 00 04 08 02 1A
   44 65 66 61 75 6C 74 54 68 72 65 61 64 50 6F 6F
   6C 53 63 68 65 64 75 6C 65 72 0A 02 03 04 01 09
   73 63 68 65 64 75 6C 65 72 0A 02 05 06 01 06 61
   63 74 6F 72 73 0A 01 07 01 05 73 63 61 6C 61 13
   03 00 09 0D 10 02 0A 0B 0D 01 02 09 02 0C 02 02
   13 54 68 72 65 61 64 50 6F 6F 6C 53 63 68 65 64
   75 6C 65 72 10 02 0E 0F 0D 01 06 09 02 10 06 02
   0B 53 63 61 6C 61 4F 62 6A 65 63 74 08 08 12 00
   FFFFFF82 FFFFFF80 FFFFFFA0 FFFFFF80 04 14 01 06 64 61 65 6D 6F 6E 03 00
   10 02 0E 15 09 02 16 06 02 07 42 6F 6F 6C 65 61
   6E 08 05 18 00 FFFFFF84 00 19 01 06 3C 69 6E 69 74 3E
   14 02 1A 1B 10 02 0A 00 08 05 12 17 FFFFFFC0 00 14 
  InnerClass: 
   public final $anon$1=class scala/actors/scheduler/DefaultThreadPoolScheduler$$anon$1 of class scala/actors/scheduler/DefaultThreadPoolScheduler
   public CallerRunsPolicy=class java/util/concurrent/ThreadPoolExecutor$CallerRunsPolicy of class java/util/concurrent/ThreadPoolExecutor
  minor version: 0
  major version: 49
  Constant pool:
Asciz	SourceFile;
Asciz	DefaultThreadPoolScheduler.scala;
Asciz	scala$actors$scheduler$DefaultThreadPoolScheduler$$daemon;
Asciz	Z;
Asciz	<init>;
Asciz	(Z)V;
Asciz	Code;
Asciz	LineNumberTable;
Asciz	scala/actors/scheduler/DefaultThreadPoolScheduler;
class	scala/actors/scheduler/DefaultThreadPoolScheduler
NameAndType	scala$actors$scheduler$DefaultThreadPoolScheduler$$daemon:Z
Field	scala/actors/scheduler/DefaultThreadPoolScheduler.scala$actors$scheduler$DefaultThreadPoolScheduler$$daemon:Z
Asciz	scala/actors/scheduler/ThreadPoolScheduler;
class	scala/actors/scheduler/ThreadPoolScheduler
NameAndType	"<init>":(Z)V
Method	scala/actors/scheduler/ThreadPoolScheduler."<init>":(Z)V
Asciz	java/util/concurrent/LinkedBlockingQueue;
class	java/util/concurrent/LinkedBlockingQueue
Asciz	()V;
NameAndType	"<init>":()V
Method	java/util/concurrent/LinkedBlockingQueue."<init>":()V
Asciz	scala/actors/scheduler/DefaultThreadPoolScheduler$$anon$1;
class	scala/actors/scheduler/DefaultThreadPoolScheduler$$anon$1
Asciz	(Lscala/actors/scheduler/DefaultThreadPoolScheduler;)V;
NameAndType	"<init>":(Lscala/actors/scheduler/DefaultThreadPoolScheduler;)V
Method	scala/actors/scheduler/DefaultThreadPoolScheduler$$anon$1."<init>":(Lscala/actors/scheduler/DefaultThreadPoolScheduler;)V
Asciz	java/util/concurrent/ThreadPoolExecutor;
class	java/util/concurrent/ThreadPoolExecutor
Asciz	scala/actors/scheduler/ThreadPoolConfig$;
class	scala/actors/scheduler/ThreadPoolConfig$
Asciz	MODULE$;
Asciz	Lscala/actors/scheduler/ThreadPoolConfig$;;
NameAndType	MODULE$:Lscala/actors/scheduler/ThreadPoolConfig$;
Field	scala/actors/scheduler/ThreadPoolConfig$.MODULE$:Lscala/actors/scheduler/ThreadPoolConfig$;
Asciz	corePoolSize;
Asciz	()I;
NameAndType	corePoolSize:()I
Method	scala/actors/scheduler/ThreadPoolConfig$.corePoolSize:()I
Asciz	maxPoolSize;
NameAndType	maxPoolSize:()I
Method	scala/actors/scheduler/ThreadPoolConfig$.maxPoolSize:()I
long	60000l;
Asciz	java/util/concurrent/TimeUnit;
class	java/util/concurrent/TimeUnit
Asciz	MILLISECONDS;
Asciz	Ljava/util/concurrent/TimeUnit;;
NameAndType	MILLISECONDS:Ljava/util/concurrent/TimeUnit;
Field	java/util/concurrent/TimeUnit.MILLISECONDS:Ljava/util/concurrent/TimeUnit;
Asciz	java/util/concurrent/ThreadFactory;
class	java/util/concurrent/ThreadFactory
Asciz	java/util/concurrent/ThreadPoolExecutor$CallerRunsPolicy;
class	java/util/concurrent/ThreadPoolExecutor$CallerRunsPolicy
Method	java/util/concurrent/ThreadPoolExecutor$CallerRunsPolicy."<init>":()V
Asciz	(IIJLjava/util/concurrent/TimeUnit;Ljava/util/concurrent/BlockingQueue;Ljava/util/concurrent/ThreadFactory;Ljava/util/concurrent/RejectedExecutionHandler;)V;
NameAndType	"<init>":(IIJLjava/util/concurrent/TimeUnit;Ljava/util/concurrent/BlockingQueue;Ljava/util/concurrent/ThreadFactory;Ljava/util/concurrent/RejectedExecutionHandler;)V
Method	java/util/concurrent/ThreadPoolExecutor."<init>":(IIJLjava/util/concurrent/TimeUnit;Ljava/util/concurrent/BlockingQueue;Ljava/util/concurrent/ThreadFactory;Ljava/util/concurrent/RejectedExecutionHandler;)V
Asciz	executor_$eq;
Asciz	(Ljava/util/concurrent/ThreadPoolExecutor;)V;
NameAndType	executor_$eq:(Ljava/util/concurrent/ThreadPoolExecutor;)V
Method	scala/actors/scheduler/DefaultThreadPoolScheduler.executor_$eq:(Ljava/util/concurrent/ThreadPoolExecutor;)V
Asciz	this;
Asciz	Lscala/actors/scheduler/DefaultThreadPoolScheduler;;
Asciz	daemon;
Asciz	workQueue;
Asciz	Ljava/util/concurrent/LinkedBlockingQueue;;
Asciz	threadFactory;
Asciz	Ljava/lang/Object;;
Asciz	LocalVariableTable;
Asciz	ScalaSig;
Asciz	InnerClasses;
Asciz	$anon$1;
Asciz	CallerRunsPolicy;
Asciz	scala/ScalaObject;
class	scala/ScalaObject

{
public final boolean scala$actors$scheduler$DefaultThreadPoolScheduler$$daemon;
  Signature: Z

public scala.actors.scheduler.DefaultThreadPoolScheduler(boolean);
  Signature: (Z)V
  Code:
   Stack=12, Locals=4, Args_size=2
	aload_0
	iload_1
	putfield	Field scala$actors$scheduler$DefaultThreadPoolScheduler$$daemon:Z
	aload_0
	iload_1
	invokespecial	Method scala/actors/scheduler/ThreadPoolScheduler."<init>":(Z)V
	aload_0
	new	class java/util/concurrent/LinkedBlockingQueue
	dup
	invokespecial	Method java/util/concurrent/LinkedBlockingQueue."<init>":()V
	astore_2
	new	class scala/actors/scheduler/DefaultThreadPoolScheduler$$anon$1
	dup
	aload_0
	invokespecial	Method scala/actors/scheduler/DefaultThreadPoolScheduler$$anon$1."<init>":(Lscala/actors/scheduler/DefaultThreadPoolScheduler;)V
	astore_3
	new	class java/util/concurrent/ThreadPoolExecutor
	dup
	getstatic	Field scala/actors/scheduler/ThreadPoolConfig$.MODULE$:Lscala/actors/scheduler/ThreadPoolConfig$;
	invokevirtual	Method scala/actors/scheduler/ThreadPoolConfig$.corePoolSize:()I
	getstatic	Field scala/actors/scheduler/ThreadPoolConfig$.MODULE$:Lscala/actors/scheduler/ThreadPoolConfig$;
	invokevirtual	Method scala/actors/scheduler/ThreadPoolConfig$.maxPoolSize:()I
	ldc2_w	long 60000l
	getstatic	Field java/util/concurrent/TimeUnit.MILLISECONDS:Ljava/util/concurrent/TimeUnit;
	aload_2
	aload_3
	checkcast	class java/util/concurrent/ThreadFactory
	new	class java/util/concurrent/ThreadPoolExecutor$CallerRunsPolicy
	dup
	invokespecial	Method java/util/concurrent/ThreadPoolExecutor$CallerRunsPolicy."<init>":()V
	invokespecial	Method java/util/concurrent/ThreadPoolExecutor."<init>":(IIJLjava/util/concurrent/TimeUnit;Ljava/util/concurrent/BlockingQueue;Ljava/util/concurrent/ThreadFactory;Ljava/util/concurrent/RejectedExecutionHandler;)V
	invokevirtual	Method executor_$eq:(Ljava/util/concurrent/ThreadPoolExecutor;)V
	return
  Labels:
  LocalVariableTable: 
   Start  Length  Slot  Name   Signature
   0      69      0    this       Lscala/actors/scheduler/DefaultThreadPoolScheduler;
   0      69      1    daemon       Z
   19      46      2    workQueue       Ljava/util/concurrent/LinkedBlockingQueue;
   28      37      3    threadFactory       Ljava/lang/Object;


}

