Compiled from "DelegatingScheduler.scala"
public abstract class scala.actors.scheduler.DelegatingScheduler$class extends java.lang.Object
  SourceFile: "DelegatingScheduler.scala"
  Scala: length = 0x
   
  minor version: 0
  major version: 49
  Constant pool:
const #1 = Asciz	SourceFile;
const #2 = Asciz	DelegatingScheduler.scala;
const #3 = Asciz	$init$;
const #4 = Asciz	(Lscala/actors/scheduler/DelegatingScheduler;)V;
const #5 = Asciz	Code;
const #6 = Asciz	LineNumberTable;
const #7 = Asciz	scala/actors/scheduler/DelegatingScheduler;
const #8 = class	#7;	//  scala/actors/scheduler/DelegatingScheduler
const #9 = Asciz	sched_$eq;
const #10 = Asciz	(Lscala/actors/IScheduler;)V;
const #11 = NameAndType	#9:#10;//  sched_$eq:(Lscala/actors/IScheduler;)V
const #12 = InterfaceMethod	#8.#11;	//  scala/actors/scheduler/DelegatingScheduler.sched_$eq:(Lscala/actors/IScheduler;)V
const #13 = Asciz	$this;
const #14 = Asciz	Lscala/actors/scheduler/DelegatingScheduler;;
const #15 = Asciz	LocalVariableTable;
const #16 = Asciz	managedBlock;
const #17 = Asciz	(Lscala/actors/scheduler/DelegatingScheduler;Lscala/concurrent/ManagedBlocker;)V;
const #18 = Asciz	impl;
const #19 = Asciz	()Lscala/actors/IScheduler;;
const #20 = NameAndType	#18:#19;//  impl:()Lscala/actors/IScheduler;
const #21 = InterfaceMethod	#8.#20;	//  scala/actors/scheduler/DelegatingScheduler.impl:()Lscala/actors/IScheduler;
const #22 = Asciz	scala/actors/IScheduler;
const #23 = class	#22;	//  scala/actors/IScheduler
const #24 = Asciz	(Lscala/concurrent/ManagedBlocker;)V;
const #25 = NameAndType	#16:#24;//  managedBlock:(Lscala/concurrent/ManagedBlocker;)V
const #26 = InterfaceMethod	#23.#25;	//  scala/actors/IScheduler.managedBlock:(Lscala/concurrent/ManagedBlocker;)V
const #27 = Asciz	blocker;
const #28 = Asciz	Lscala/concurrent/ManagedBlocker;;
const #29 = Asciz	onTerminate;
const #30 = Asciz	(Lscala/actors/scheduler/DelegatingScheduler;Lscala/actors/Reactor;Lscala/Function0;)V;
const #31 = Asciz	(Lscala/actors/Reactor;Lscala/Function0;)V;
const #32 = NameAndType	#29:#31;//  onTerminate:(Lscala/actors/Reactor;Lscala/Function0;)V
const #33 = InterfaceMethod	#23.#32;	//  scala/actors/IScheduler.onTerminate:(Lscala/actors/Reactor;Lscala/Function0;)V
const #34 = Asciz	actor;
const #35 = Asciz	Lscala/actors/Reactor;;
const #36 = Asciz	f;
const #37 = Asciz	Lscala/Function0;;
const #38 = Asciz	terminated;
const #39 = Asciz	(Lscala/actors/scheduler/DelegatingScheduler;Lscala/actors/Reactor;)V;
const #40 = Asciz	(Lscala/actors/Reactor;)V;
const #41 = NameAndType	#38:#40;//  terminated:(Lscala/actors/Reactor;)V
const #42 = InterfaceMethod	#23.#41;	//  scala/actors/IScheduler.terminated:(Lscala/actors/Reactor;)V
const #43 = Asciz	newActor;
const #44 = Asciz	sched;
const #45 = NameAndType	#44:#19;//  sched:()Lscala/actors/IScheduler;
const #46 = InterfaceMethod	#8.#45;	//  scala/actors/scheduler/DelegatingScheduler.sched:()Lscala/actors/IScheduler;
const #47 = Asciz	isActive;
const #48 = Asciz	()Z;
const #49 = NameAndType	#47:#48;//  isActive:()Z
const #50 = InterfaceMethod	#23.#49;	//  scala/actors/IScheduler.isActive:()Z
const #51 = NameAndType	#43:#40;//  newActor:(Lscala/actors/Reactor;)V
const #52 = InterfaceMethod	#23.#51;	//  scala/actors/IScheduler.newActor:(Lscala/actors/Reactor;)V
const #53 = Asciz	scala/runtime/BoxesRunTime;
const #54 = class	#53;	//  scala/runtime/BoxesRunTime
const #55 = Asciz	boxToBoolean;
const #56 = Asciz	(Z)Ljava/lang/Boolean;;
const #57 = NameAndType	#55:#56;//  boxToBoolean:(Z)Ljava/lang/Boolean;
const #58 = Method	#54.#57;	//  scala/runtime/BoxesRunTime.boxToBoolean:(Z)Ljava/lang/Boolean;
const #59 = Asciz	unboxToBoolean;
const #60 = Asciz	(Ljava/lang/Object;)Z;
const #61 = NameAndType	#59:#60;//  unboxToBoolean:(Ljava/lang/Object;)Z
const #62 = Method	#54.#61;	//  scala/runtime/BoxesRunTime.unboxToBoolean:(Ljava/lang/Object;)Z
const #63 = Asciz	makeNewScheduler;
const #64 = NameAndType	#63:#19;//  makeNewScheduler:()Lscala/actors/IScheduler;
const #65 = InterfaceMethod	#8.#64;	//  scala/actors/scheduler/DelegatingScheduler.makeNewScheduler:()Lscala/actors/IScheduler;
const #66 = Asciz	java/lang/Throwable;
const #67 = class	#66;	//  java/lang/Throwable
const #68 = Asciz	createNew;
const #69 = Asciz	Z;
const #70 = Asciz	shutdown;
const #71 = Asciz	()V;
const #72 = NameAndType	#70:#71;//  shutdown:()V
const #73 = InterfaceMethod	#23.#72;	//  scala/actors/IScheduler.shutdown:()V
const #74 = Asciz	executeFromActor;
const #75 = Asciz	(Lscala/actors/scheduler/DelegatingScheduler;Ljava/lang/Runnable;)V;
const #76 = Asciz	(Ljava/lang/Runnable;)V;
const #77 = NameAndType	#74:#76;//  executeFromActor:(Ljava/lang/Runnable;)V
const #78 = InterfaceMethod	#23.#77;	//  scala/actors/IScheduler.executeFromActor:(Ljava/lang/Runnable;)V
const #79 = Asciz	task;
const #80 = Asciz	Ljava/lang/Runnable;;
const #81 = Asciz	execute;
const #82 = NameAndType	#81:#76;//  execute:(Ljava/lang/Runnable;)V
const #83 = InterfaceMethod	#23.#82;	//  scala/actors/IScheduler.execute:(Ljava/lang/Runnable;)V
const #84 = Asciz	(Lscala/actors/scheduler/DelegatingScheduler;Lscala/Function0;)V;
const #85 = Asciz	(Lscala/Function0;)V;
const #86 = NameAndType	#81:#85;//  execute:(Lscala/Function0;)V
const #87 = InterfaceMethod	#23.#86;	//  scala/actors/IScheduler.execute:(Lscala/Function0;)V
const #88 = Asciz	fun;
const #89 = Asciz	(Lscala/actors/scheduler/DelegatingScheduler;)Z;
const #90 = Asciz	impl_$eq;
const #91 = Asciz	(Lscala/actors/scheduler/DelegatingScheduler;Lscala/actors/IScheduler;)V;
const #92 = Asciz	scheduler;
const #93 = Asciz	Lscala/actors/IScheduler;;
const #94 = Asciz	(Lscala/actors/scheduler/DelegatingScheduler;)Lscala/actors/IScheduler;;
const #95 = Asciz	Scala;
const #96 = Asciz	scala/actors/scheduler/DelegatingScheduler$class;
const #97 = class	#96;	//  scala/actors/scheduler/DelegatingScheduler$class
const #98 = Asciz	java/lang/Object;
const #99 = class	#98;	//  java/lang/Object

{
public static void $init$(scala.actors.scheduler.DelegatingScheduler);
  Code:
   Stack=2, Locals=1, Args_size=1
   0:	aload_0
   1:	aconst_null
   2:	invokeinterface	#12,  2; //InterfaceMethod scala/actors/scheduler/DelegatingScheduler.sched_$eq:(Lscala/actors/IScheduler;)V
   7:	return
  LineNumberTable: 
   line 20: 0

  LocalVariableTable: 
   Start  Length  Slot  Name   Signature
   0      8      0    $this       Lscala/actors/scheduler/DelegatingScheduler;


public static void managedBlock(scala.actors.scheduler.DelegatingScheduler, scala.concurrent.ManagedBlocker);
  Code:
   Stack=2, Locals=2, Args_size=2
   0:	aload_0
   1:	invokeinterface	#21,  1; //InterfaceMethod scala/actors/scheduler/DelegatingScheduler.impl:()Lscala/actors/IScheduler;
   6:	aload_1
   7:	invokeinterface	#26,  2; //InterfaceMethod scala/actors/IScheduler.managedBlock:(Lscala/concurrent/ManagedBlocker;)V
   12:	return
  LineNumberTable: 
   line 73: 0

  LocalVariableTable: 
   Start  Length  Slot  Name   Signature
   0      13      0    $this       Lscala/actors/scheduler/DelegatingScheduler;
   0      13      1    blocker       Lscala/concurrent/ManagedBlocker;


public static void onTerminate(scala.actors.scheduler.DelegatingScheduler, scala.actors.Reactor, scala.Function0);
  Code:
   Stack=3, Locals=3, Args_size=3
   0:	aload_0
   1:	invokeinterface	#21,  1; //InterfaceMethod scala/actors/scheduler/DelegatingScheduler.impl:()Lscala/actors/IScheduler;
   6:	aload_1
   7:	aload_2
   8:	invokeinterface	#33,  3; //InterfaceMethod scala/actors/IScheduler.onTerminate:(Lscala/actors/Reactor;Lscala/Function0;)V
   13:	return
  LineNumberTable: 
   line 70: 0

  LocalVariableTable: 
   Start  Length  Slot  Name   Signature
   0      14      0    $this       Lscala/actors/scheduler/DelegatingScheduler;
   0      14      1    actor       Lscala/actors/Reactor;
   0      14      2    f       Lscala/Function0;


public static void terminated(scala.actors.scheduler.DelegatingScheduler, scala.actors.Reactor);
  Code:
   Stack=2, Locals=2, Args_size=2
   0:	aload_0
   1:	invokeinterface	#21,  1; //InterfaceMethod scala/actors/scheduler/DelegatingScheduler.impl:()Lscala/actors/IScheduler;
   6:	aload_1
   7:	invokeinterface	#42,  2; //InterfaceMethod scala/actors/IScheduler.terminated:(Lscala/actors/Reactor;)V
   12:	return
  LineNumberTable: 
   line 68: 0

  LocalVariableTable: 
   Start  Length  Slot  Name   Signature
   0      13      0    $this       Lscala/actors/scheduler/DelegatingScheduler;
   0      13      1    actor       Lscala/actors/Reactor;


public static void newActor(scala.actors.scheduler.DelegatingScheduler, scala.actors.Reactor);
  Code:
   Stack=2, Locals=6, Args_size=2
   0:	aload_0
   1:	dup
   2:	pop
   3:	monitorenter
   4:	aload_0
   5:	invokeinterface	#46,  1; //InterfaceMethod scala/actors/scheduler/DelegatingScheduler.sched:()Lscala/actors/IScheduler;
   10:	ifnonnull	17
   13:	iconst_1
   14:	goto	74
   17:	aload_0
   18:	invokeinterface	#46,  1; //InterfaceMethod scala/actors/scheduler/DelegatingScheduler.sched:()Lscala/actors/IScheduler;
   23:	dup
   24:	astore	5
   26:	monitorenter
   27:	aload_0
   28:	invokeinterface	#46,  1; //InterfaceMethod scala/actors/scheduler/DelegatingScheduler.sched:()Lscala/actors/IScheduler;
   33:	invokeinterface	#50,  1; //InterfaceMethod scala/actors/IScheduler.isActive:()Z
   38:	ifeq	62
   41:	aload_0
   42:	invokeinterface	#46,  1; //InterfaceMethod scala/actors/scheduler/DelegatingScheduler.sched:()Lscala/actors/IScheduler;
   47:	aload_1
   48:	invokeinterface	#52,  2; //InterfaceMethod scala/actors/IScheduler.newActor:(Lscala/actors/Reactor;)V
   53:	iconst_0
   54:	istore_2
   55:	iload_2
   56:	invokestatic	#58; //Method scala/runtime/BoxesRunTime.boxToBoolean:(Z)Ljava/lang/Boolean;
   59:	goto	68
   62:	iconst_1
   63:	istore_3
   64:	iload_3
   65:	invokestatic	#58; //Method scala/runtime/BoxesRunTime.boxToBoolean:(Z)Ljava/lang/Boolean;
   68:	aload	5
   70:	monitorexit
   71:	invokestatic	#62; //Method scala/runtime/BoxesRunTime.unboxToBoolean:(Ljava/lang/Object;)Z
   74:	istore	4
   76:	iload	4
   78:	ifeq	108
   81:	aload_0
   82:	aload_0
   83:	invokeinterface	#65,  1; //InterfaceMethod scala/actors/scheduler/DelegatingScheduler.makeNewScheduler:()Lscala/actors/IScheduler;
   88:	invokeinterface	#12,  2; //InterfaceMethod scala/actors/scheduler/DelegatingScheduler.sched_$eq:(Lscala/actors/IScheduler;)V
   93:	aload_0
   94:	invokeinterface	#46,  1; //InterfaceMethod scala/actors/scheduler/DelegatingScheduler.sched:()Lscala/actors/IScheduler;
   99:	aload_1
   100:	invokeinterface	#52,  2; //InterfaceMethod scala/actors/IScheduler.newActor:(Lscala/actors/Reactor;)V
   105:	goto	108
   108:	aload_0
   109:	monitorexit
   110:	return
   111:	aload	5
   113:	monitorexit
   114:	athrow
   115:	aload_0
   116:	monitorexit
   117:	athrow
  Exception table:
   from   to  target type
    27    71   111   Class java/lang/Throwable

     4   110   115   Class java/lang/Throwable

   111   115   115   Class java/lang/Throwable

  LineNumberTable: 
   line 51: 0
   line 52: 4
   line 53: 13
   line 54: 17
   line 55: 27
   line 58: 41
   line 59: 53
   line 55: 59
   line 56: 62
   line 54: 68
   line 52: 74
   line 62: 76
   line 63: 81
   line 64: 93
   line 62: 108
   line 51: 109
   line 54: 113
   line 51: 116

  LocalVariableTable: 
   Start  Length  Slot  Name   Signature
   0      118      0    $this       Lscala/actors/scheduler/DelegatingScheduler;
   0      118      1    actor       Lscala/actors/Reactor;
   76      32      4    createNew       Z


public static void shutdown(scala.actors.scheduler.DelegatingScheduler);
  Code:
   Stack=2, Locals=1, Args_size=1
   0:	aload_0
   1:	dup
   2:	pop
   3:	monitorenter
   4:	aload_0
   5:	invokeinterface	#46,  1; //InterfaceMethod scala/actors/scheduler/DelegatingScheduler.sched:()Lscala/actors/IScheduler;
   10:	ifnull	34
   13:	aload_0
   14:	invokeinterface	#46,  1; //InterfaceMethod scala/actors/scheduler/DelegatingScheduler.sched:()Lscala/actors/IScheduler;
   19:	invokeinterface	#73,  1; //InterfaceMethod scala/actors/IScheduler.shutdown:()V
   24:	aload_0
   25:	aconst_null
   26:	invokeinterface	#12,  2; //InterfaceMethod scala/actors/scheduler/DelegatingScheduler.sched_$eq:(Lscala/actors/IScheduler;)V
   31:	goto	34
   34:	aload_0
   35:	monitorexit
   36:	return
   37:	aload_0
   38:	monitorexit
   39:	athrow
  Exception table:
   from   to  target type
     4    36    37   Class java/lang/Throwable

  LineNumberTable: 
   line 44: 0
   line 45: 4
   line 46: 13
   line 47: 24
   line 44: 34

  LocalVariableTable: 
   Start  Length  Slot  Name   Signature
   0      40      0    $this       Lscala/actors/scheduler/DelegatingScheduler;


public static void executeFromActor(scala.actors.scheduler.DelegatingScheduler, java.lang.Runnable);
  Code:
   Stack=2, Locals=2, Args_size=2
   0:	aload_0
   1:	invokeinterface	#21,  1; //InterfaceMethod scala/actors/scheduler/DelegatingScheduler.impl:()Lscala/actors/IScheduler;
   6:	aload_1
   7:	invokeinterface	#78,  2; //InterfaceMethod scala/actors/IScheduler.executeFromActor:(Ljava/lang/Runnable;)V
   12:	return
  LineNumberTable: 
   line 42: 0

  LocalVariableTable: 
   Start  Length  Slot  Name   Signature
   0      13      0    $this       Lscala/actors/scheduler/DelegatingScheduler;
   0      13      1    task       Ljava/lang/Runnable;


public static void execute(scala.actors.scheduler.DelegatingScheduler, java.lang.Runnable);
  Code:
   Stack=2, Locals=2, Args_size=2
   0:	aload_0
   1:	invokeinterface	#21,  1; //InterfaceMethod scala/actors/scheduler/DelegatingScheduler.impl:()Lscala/actors/IScheduler;
   6:	aload_1
   7:	invokeinterface	#83,  2; //InterfaceMethod scala/actors/IScheduler.execute:(Ljava/lang/Runnable;)V
   12:	return
  LineNumberTable: 
   line 40: 0

  LocalVariableTable: 
   Start  Length  Slot  Name   Signature
   0      13      0    $this       Lscala/actors/scheduler/DelegatingScheduler;
   0      13      1    task       Ljava/lang/Runnable;


public static void execute(scala.actors.scheduler.DelegatingScheduler, scala.Function0);
  Code:
   Stack=2, Locals=2, Args_size=2
   0:	aload_0
   1:	invokeinterface	#21,  1; //InterfaceMethod scala/actors/scheduler/DelegatingScheduler.impl:()Lscala/actors/IScheduler;
   6:	aload_1
   7:	invokeinterface	#87,  2; //InterfaceMethod scala/actors/IScheduler.execute:(Lscala/Function0;)V
   12:	return
  LineNumberTable: 
   line 38: 0

  LocalVariableTable: 
   Start  Length  Slot  Name   Signature
   0      13      0    $this       Lscala/actors/scheduler/DelegatingScheduler;
   0      13      1    fun       Lscala/Function0;


public static boolean isActive(scala.actors.scheduler.DelegatingScheduler);
  Code:
   Stack=1, Locals=1, Args_size=1
   0:	iconst_1
   1:	ireturn
  LineNumberTable: 
   line 36: 0

  LocalVariableTable: 
   Start  Length  Slot  Name   Signature
   0      2      0    $this       Lscala/actors/scheduler/DelegatingScheduler;


public static final void impl_$eq(scala.actors.scheduler.DelegatingScheduler, scala.actors.IScheduler);
  Code:
   Stack=2, Locals=2, Args_size=2
   0:	aload_0
   1:	dup
   2:	pop
   3:	monitorenter
   4:	aload_0
   5:	aload_1
   6:	invokeinterface	#12,  2; //InterfaceMethod scala/actors/scheduler/DelegatingScheduler.sched_$eq:(Lscala/actors/IScheduler;)V
   11:	aload_0
   12:	monitorexit
   13:	return
   14:	aload_0
   15:	monitorexit
   16:	athrow
  Exception table:
   from   to  target type
     4    13    14   Class java/lang/Throwable

  LineNumberTable: 
   line 28: 0
   line 30: 4
   line 28: 12

  LocalVariableTable: 
   Start  Length  Slot  Name   Signature
   0      17      0    $this       Lscala/actors/scheduler/DelegatingScheduler;
   0      17      1    scheduler       Lscala/actors/IScheduler;


public static final scala.actors.IScheduler impl(scala.actors.scheduler.DelegatingScheduler);
  Code:
   Stack=2, Locals=1, Args_size=1
   0:	aload_0
   1:	dup
   2:	pop
   3:	monitorenter
   4:	aload_0
   5:	invokeinterface	#46,  1; //InterfaceMethod scala/actors/scheduler/DelegatingScheduler.sched:()Lscala/actors/IScheduler;
   10:	ifnull	27
   13:	aload_0
   14:	invokeinterface	#46,  1; //InterfaceMethod scala/actors/scheduler/DelegatingScheduler.sched:()Lscala/actors/IScheduler;
   19:	invokeinterface	#50,  1; //InterfaceMethod scala/actors/IScheduler.isActive:()Z
   24:	ifne	39
   27:	aload_0
   28:	aload_0
   29:	invokeinterface	#65,  1; //InterfaceMethod scala/actors/scheduler/DelegatingScheduler.makeNewScheduler:()Lscala/actors/IScheduler;
   34:	invokeinterface	#12,  2; //InterfaceMethod scala/actors/scheduler/DelegatingScheduler.sched_$eq:(Lscala/actors/IScheduler;)V
   39:	aload_0
   40:	invokeinterface	#46,  1; //InterfaceMethod scala/actors/scheduler/DelegatingScheduler.sched:()Lscala/actors/IScheduler;
   45:	aload_0
   46:	monitorexit
   47:	checkcast	#23; //class scala/actors/IScheduler
   50:	areturn
   51:	aload_0
   52:	monitorexit
   53:	athrow
  Exception table:
   from   to  target type
     4    47    51   Class java/lang/Throwable

  LineNumberTable: 
   line 22: 0
   line 23: 4
   line 24: 27
   line 25: 39
   line 22: 46

  LocalVariableTable: 
   Start  Length  Slot  Name   Signature
   0      54      0    $this       Lscala/actors/scheduler/DelegatingScheduler;


}

