Compiled from "DrainableForkJoinPool.scala"
public class scala.actors.scheduler.DrainableForkJoinPool extends scala.actors.forkjoin.ForkJoinPool implements scala.ScalaObject
  SourceFile: "DrainableForkJoinPool.scala"
  ScalaSig: length = 0x155
   05 00 38 06 08 01 02 FFFFFF84 FFFFFF80 FFFFFF80 FFFFFF80 04 09 02 15 44
   72 61 69 6E 61 62 6C 65 46 6F 72 6B 4A 6F 69 6E
   50 6F 6F 6C 0A 02 03 04 01 09 73 63 68 65 64 75
   6C 65 72 0A 02 05 06 01 06 61 63 74 6F 72 73 0A
   01 07 01 05 73 63 61 6C 61 03 00 13 03 00 0A 10
   10 02 0B 0E 0D 01 0C 0A 02 0D 04 01 08 66 6F 72
   6B 6A 6F 69 6E 09 02 0F 0C 02 0C 46 6F 72 6B 4A
   6F 69 6E 50 6F 6F 6C 10 02 11 12 0D 01 06 09 02
   13 06 02 0B 53 63 61 6C 61 4F 62 6A 65 63 74 08
   05 15 00 FFFFFF84 00 16 01 06 3C 69 6E 69 74 3E 14 01
   17 10 02 18 00 0D 01 02 08 05 1A 00 FFFFFF84 20 1B 01
   0C 64 72 61 69 6E 54 61 73 6B 73 54 6F 14 02 1C
   1F 10 02 11 1D 09 02 1E 06 02 03 49 6E 74 08 05
   20 19 FFFFFFC0 00 21 01 01 63 10 03 22 27 29 0D 01 23
   0A 02 24 25 01 04 75 74 69 6C 0A 01 26 01 04 6A
   61 76 61 09 02 28 23 02 0A 43 6F 6C 6C 65 63 74
   69 6F 6E 30 02 2A 2F 10 03 0B 2B 2D 09 02 2C 0C
   02 0C 46 6F 72 6B 4A 6F 69 6E 54 61 73 6B 10 02
   2E 2F 0C 00 04 08 30 00 FFFFFF84 FFFFFF80 FFFFFF80 FFFFFF82 00 31 02 03
   5F 24 31 11 02 32 35 10 02 11 33 09 02 34 06 02
   07 4E 6F 74 68 69 6E 67 10 02 11 36 09 02 37 06
   02 03 41 6E 79 
  minor version: 0
  major version: 49
  Constant pool:
const #1 = Asciz	SourceFile;
const #2 = Asciz	DrainableForkJoinPool.scala;
const #3 = Asciz	<init>;
const #4 = Asciz	()V;
const #5 = Asciz	Code;
const #6 = Asciz	LineNumberTable;
const #7 = Asciz	scala/actors/forkjoin/ForkJoinPool;
const #8 = class	#7;	//  scala/actors/forkjoin/ForkJoinPool
const #9 = NameAndType	#3:#4;//  "<init>":()V
const #10 = Method	#8.#9;	//  scala/actors/forkjoin/ForkJoinPool."<init>":()V
const #11 = Asciz	drainTasksTo;
const #12 = Asciz	(Ljava/util/Collection;)I;
const #13 = NameAndType	#11:#12;//  drainTasksTo:(Ljava/util/Collection;)I
const #14 = Method	#8.#13;	//  scala/actors/forkjoin/ForkJoinPool.drainTasksTo:(Ljava/util/Collection;)I
const #15 = Asciz	this;
const #16 = Asciz	Lscala/actors/scheduler/DrainableForkJoinPool;;
const #17 = Asciz	c;
const #18 = Asciz	Ljava/util/Collection;;
const #19 = Asciz	LocalVariableTable;
const #20 = Asciz	(Ljava/util/Collection<Lscala/actors/forkjoin/ForkJoinTask<*>;>;)I;
const #21 = Asciz	Signature;
const #22 = Asciz	ScalaSig;
const #23 = Asciz	scala/actors/scheduler/DrainableForkJoinPool;
const #24 = class	#23;	//  scala/actors/scheduler/DrainableForkJoinPool
const #25 = Asciz	scala/ScalaObject;
const #26 = class	#25;	//  scala/ScalaObject

{
public scala.actors.scheduler.DrainableForkJoinPool();
  Code:
   Stack=1, Locals=1, Args_size=1
   0:	aload_0
   1:	invokespecial	#10; //Method scala/actors/forkjoin/ForkJoinPool."<init>":()V
   4:	return
  LineNumberTable: 
   line 7: 0


public int drainTasksTo(java.util.Collection);
  Code:
   Stack=2, Locals=2, Args_size=2
   0:	aload_0
   1:	aload_1
   2:	invokespecial	#14; //Method scala/actors/forkjoin/ForkJoinPool.drainTasksTo:(Ljava/util/Collection;)I
   5:	ireturn
  LineNumberTable: 
   line 10: 0

  LocalVariableTable: 
   Start  Length  Slot  Name   Signature
   0      6      0    this       Lscala/actors/scheduler/DrainableForkJoinPool;
   0      6      1    c       Ljava/util/Collection;

  Signature: length = 0x2
   00 14 

}

