Compiled from "ExecutorScheduler.scala"
public final class scala.actors.scheduler.ExecutorScheduler$ extends java.lang.Object implements scala.ScalaObject
  SourceFile: "ExecutorScheduler.scala"
  Scala: length = 0x
   
  InnerClass: 
   public final $anon$2=class scala/actors/scheduler/ExecutorScheduler$$anon$2 of class scala/actors/scheduler/ExecutorScheduler
   public final $anon$1=class scala/actors/scheduler/ExecutorScheduler$$anon$1 of class scala/actors/scheduler/ExecutorScheduler
   public RunCallable=class scala/actors/scheduler/ExecutorScheduler$RunCallable of class scala/actors/scheduler/ExecutorScheduler
  minor version: 0
  major version: 49
  Constant pool:
Asciz	SourceFile;
Asciz	ExecutorScheduler.scala;
Asciz	MODULE$;
Asciz	Lscala/actors/scheduler/ExecutorScheduler$;;
Asciz	<clinit>;
Asciz	()V;
Asciz	Code;
Asciz	scala/actors/scheduler/ExecutorScheduler$;
class	scala/actors/scheduler/ExecutorScheduler$
Asciz	<init>;
NameAndType	"<init>":()V
Method	scala/actors/scheduler/ExecutorScheduler$."<init>":()V
Asciz	start;
Asciz	(Lscala/actors/scheduler/ExecutorScheduler;)Lscala/actors/scheduler/ExecutorScheduler;;
Asciz	LineNumberTable;
Asciz	java/lang/Thread;
class	java/lang/Thread
NameAndType	start:()V
Method	java/lang/Thread.start:()V
Asciz	this;
Asciz	sched;
Asciz	Lscala/actors/scheduler/ExecutorScheduler;;
Asciz	LocalVariableTable;
Asciz	apply;
Asciz	(Ljava/util/concurrent/ExecutorService;)Lscala/actors/scheduler/ExecutorScheduler;;
Asciz	scala/actors/scheduler/ExecutorScheduler$$anon$1;
class	scala/actors/scheduler/ExecutorScheduler$$anon$1
Asciz	(Ljava/util/concurrent/ExecutorService;)V;
NameAndType	"<init>":(Ljava/util/concurrent/ExecutorService;)V
Method	scala/actors/scheduler/ExecutorScheduler$$anon$1."<init>":(Ljava/util/concurrent/ExecutorService;)V
NameAndType	start:(Lscala/actors/scheduler/ExecutorScheduler;)Lscala/actors/scheduler/ExecutorScheduler;
Method	scala/actors/scheduler/ExecutorScheduler$.start:(Lscala/actors/scheduler/ExecutorScheduler;)Lscala/actors/scheduler/ExecutorScheduler;
Asciz	exec$2;
Asciz	Ljava/util/concurrent/ExecutorService;;
Asciz	(Ljava/util/concurrent/ExecutorService;Z)Lscala/actors/scheduler/ExecutorScheduler;;
Asciz	scala/actors/scheduler/ExecutorScheduler$$anon$2;
class	scala/actors/scheduler/ExecutorScheduler$$anon$2
Asciz	(Ljava/util/concurrent/ExecutorService;Z)V;
NameAndType	"<init>":(Ljava/util/concurrent/ExecutorService;Z)V
Method	scala/actors/scheduler/ExecutorScheduler$$anon$2."<init>":(Ljava/util/concurrent/ExecutorService;Z)V
Asciz	exec$1;
Asciz	term$1;
Asciz	Z;
Asciz	java/lang/Object;
class	java/lang/Object
Method	java/lang/Object."<init>":()V
NameAndType	MODULE$:Lscala/actors/scheduler/ExecutorScheduler$;
Field	scala/actors/scheduler/ExecutorScheduler$.MODULE$:Lscala/actors/scheduler/ExecutorScheduler$;
Asciz	Scala;
Asciz	InnerClasses;
Asciz	scala/actors/scheduler/ExecutorScheduler;
class	scala/actors/scheduler/ExecutorScheduler
Asciz	$anon$2;
Asciz	$anon$1;
Asciz	scala/actors/scheduler/ExecutorScheduler$RunCallable;
class	scala/actors/scheduler/ExecutorScheduler$RunCallable
Asciz	RunCallable;
Asciz	scala/ScalaObject;
class	scala/ScalaObject

{
public static final scala.actors.scheduler.ExecutorScheduler$ MODULE$;
  Signature: Lscala/actors/scheduler/ExecutorScheduler$;

public static {};
  Signature: ()V
  Code:
   Stack=1, Locals=0, Args_size=0
	new	class scala/actors/scheduler/ExecutorScheduler$
	invokespecial	Method "<init>":()V
	return
  Labels:

private scala.actors.scheduler.ExecutorScheduler start(scala.actors.scheduler.ExecutorScheduler);
  Signature: (Lscala/actors/scheduler/ExecutorScheduler;)Lscala/actors/scheduler/ExecutorScheduler;
  Code:
   Stack=1, Locals=2, Args_size=2
	aload_1
	checkcast	class java/lang/Thread
	invokevirtual	Method java/lang/Thread.start:()V
	aload_1
	areturn
  Labels:
  LocalVariableTable: 
   Start  Length  Slot  Name   Signature
   0      9      0    this       Lscala/actors/scheduler/ExecutorScheduler$;
   0      9      1    sched       Lscala/actors/scheduler/ExecutorScheduler;


public scala.actors.scheduler.ExecutorScheduler apply(java.util.concurrent.ExecutorService);
  Signature: (Ljava/util/concurrent/ExecutorService;)Lscala/actors/scheduler/ExecutorScheduler;
  Code:
   Stack=4, Locals=2, Args_size=2
	aload_0
	new	class scala/actors/scheduler/ExecutorScheduler$$anon$1
	dup
	aload_1
	invokespecial	Method scala/actors/scheduler/ExecutorScheduler$$anon$1."<init>":(Ljava/util/concurrent/ExecutorService;)V
	invokespecial	Method start:(Lscala/actors/scheduler/ExecutorScheduler;)Lscala/actors/scheduler/ExecutorScheduler;
	areturn
  Labels:
  LocalVariableTable: 
   Start  Length  Slot  Name   Signature
   0      13      0    this       Lscala/actors/scheduler/ExecutorScheduler$;
   0      13      1    exec$2       Ljava/util/concurrent/ExecutorService;


public scala.actors.scheduler.ExecutorScheduler apply(java.util.concurrent.ExecutorService, boolean);
  Signature: (Ljava/util/concurrent/ExecutorService;Z)Lscala/actors/scheduler/ExecutorScheduler;
  Code:
   Stack=5, Locals=3, Args_size=3
	aload_0
	new	class scala/actors/scheduler/ExecutorScheduler$$anon$2
	dup
	aload_1
	iload_2
	invokespecial	Method scala/actors/scheduler/ExecutorScheduler$$anon$2."<init>":(Ljava/util/concurrent/ExecutorService;Z)V
	invokespecial	Method start:(Lscala/actors/scheduler/ExecutorScheduler;)Lscala/actors/scheduler/ExecutorScheduler;
	areturn
  Labels:
  LocalVariableTable: 
   Start  Length  Slot  Name   Signature
   0      14      0    this       Lscala/actors/scheduler/ExecutorScheduler$;
   0      14      1    exec$1       Ljava/util/concurrent/ExecutorService;
   0      14      2    term$1       Z


private scala.actors.scheduler.ExecutorScheduler$();
  Signature: ()V
  Code:
   Stack=1, Locals=1, Args_size=1
	aload_0
	invokespecial	Method java/lang/Object."<init>":()V
	aload_0
	putstatic	Field MODULE$:Lscala/actors/scheduler/ExecutorScheduler$;
	return
  Labels:

}

