Compiled from "ExecutorScheduler.scala"
public class scala.actors.scheduler.ExecutorScheduler$RunCallable extends java.lang.Object implements java.util.concurrent.Callable,java.lang.Runnable,scala.ScalaObject
  SourceFile: "ExecutorScheduler.scala"
  Signature: length = 0x2
   00 31 
  Scala: length = 0x
   
  InnerClass: 
   public #54= #14 of #53; //RunCallable=class scala/actors/scheduler/ExecutorScheduler$RunCallable of class scala/actors/scheduler/ExecutorScheduler
  minor version: 0
  major version: 49
  Constant pool:
const #1 = Asciz	SourceFile;
const #2 = Asciz	ExecutorScheduler.scala;
const #3 = Asciz	$outer;
const #4 = Asciz	Lscala/actors/scheduler/ExecutorScheduler;;
const #5 = Asciz	fun;
const #6 = Asciz	Lscala/Function0;;
const #7 = Asciz	Lscala/Function0<Ljava/lang/Object;>;;
const #8 = Asciz	Signature;
const #9 = Asciz	<init>;
const #10 = Asciz	(Lscala/actors/scheduler/ExecutorScheduler;Lscala/Function0;)V;
const #11 = Asciz	Code;
const #12 = Asciz	LineNumberTable;
const #13 = Asciz	scala/actors/scheduler/ExecutorScheduler$RunCallable;
const #14 = class	#13;	//  scala/actors/scheduler/ExecutorScheduler$RunCallable
const #15 = NameAndType	#5:#6;//  fun:Lscala/Function0;
const #16 = Field	#14.#15;	//  scala/actors/scheduler/ExecutorScheduler$RunCallable.fun:Lscala/Function0;
const #17 = Asciz	java/lang/NullPointerException;
const #18 = class	#17;	//  java/lang/NullPointerException
const #19 = Asciz	()V;
const #20 = NameAndType	#9:#19;//  "<init>":()V
const #21 = Method	#18.#20;	//  java/lang/NullPointerException."<init>":()V
const #22 = NameAndType	#3:#4;//  $outer:Lscala/actors/scheduler/ExecutorScheduler;
const #23 = Field	#14.#22;	//  scala/actors/scheduler/ExecutorScheduler$RunCallable.$outer:Lscala/actors/scheduler/ExecutorScheduler;
const #24 = Asciz	java/lang/Object;
const #25 = class	#24;	//  java/lang/Object
const #26 = Method	#25.#20;	//  java/lang/Object."<init>":()V
const #27 = Asciz	this;
const #28 = Asciz	Lscala/actors/scheduler/ExecutorScheduler$RunCallable;;
const #29 = Asciz	LocalVariableTable;
const #30 = Asciz	(Lscala/actors/scheduler/ExecutorScheduler;Lscala/Function0<Ljava/lang/Object;>;)V;
const #31 = Asciz	call;
const #32 = Asciz	()Ljava/lang/Object;;
const #33 = NameAndType	#31:#19;//  call:()V
const #34 = Method	#14.#33;	//  scala/actors/scheduler/ExecutorScheduler$RunCallable.call:()V
const #35 = Asciz	scala/runtime/BoxedUnit;
const #36 = class	#35;	//  scala/runtime/BoxedUnit
const #37 = Asciz	UNIT;
const #38 = Asciz	Lscala/runtime/BoxedUnit;;
const #39 = NameAndType	#37:#38;//  UNIT:Lscala/runtime/BoxedUnit;
const #40 = Field	#36.#39;	//  scala/runtime/BoxedUnit.UNIT:Lscala/runtime/BoxedUnit;
const #41 = Asciz	scala$actors$scheduler$ExecutorScheduler$RunCallable$$$outer;
const #42 = Asciz	()Lscala/actors/scheduler/ExecutorScheduler;;
const #43 = Asciz	run;
const #44 = Asciz	scala/Function0;
const #45 = class	#44;	//  scala/Function0
const #46 = Asciz	apply;
const #47 = NameAndType	#46:#32;//  apply:()Ljava/lang/Object;
const #48 = InterfaceMethod	#45.#47;	//  scala/Function0.apply:()Ljava/lang/Object;
const #49 = Asciz	Ljava/lang/Object;Ljava/util/concurrent/Callable<Ljava/lang/Object;>;Ljava/lang/Runnable;Lscala/ScalaObject;;
const #50 = Asciz	Scala;
const #51 = Asciz	InnerClasses;
const #52 = Asciz	scala/actors/scheduler/ExecutorScheduler;
const #53 = class	#52;	//  scala/actors/scheduler/ExecutorScheduler
const #54 = Asciz	RunCallable;
const #55 = Asciz	java/util/concurrent/Callable;
const #56 = class	#55;	//  java/util/concurrent/Callable
const #57 = Asciz	java/lang/Runnable;
const #58 = class	#57;	//  java/lang/Runnable
const #59 = Asciz	scala/ScalaObject;
const #60 = class	#59;	//  scala/ScalaObject

{
public final scala.actors.scheduler.ExecutorScheduler $outer;

public scala.actors.scheduler.ExecutorScheduler$RunCallable(scala.actors.scheduler.ExecutorScheduler, scala.Function0);
  Code:
   Stack=2, Locals=3, Args_size=3
   0:	aload_0
   1:	aload_2
   2:	putfield	#16; //Field fun:Lscala/Function0;
   5:	aload_1
   6:	ifnonnull	17
   9:	new	#18; //class java/lang/NullPointerException
   12:	dup
   13:	invokespecial	#21; //Method java/lang/NullPointerException."<init>":()V
   16:	athrow
   17:	aload_0
   18:	aload_1
   19:	putfield	#23; //Field $outer:Lscala/actors/scheduler/ExecutorScheduler;
   22:	aload_0
   23:	invokespecial	#26; //Method java/lang/Object."<init>":()V
   26:	return
  LineNumberTable: 
   line 29: 0

  LocalVariableTable: 
   Start  Length  Slot  Name   Signature
   0      27      0    this       Lscala/actors/scheduler/ExecutorScheduler$RunCallable;
   0      27      1    $outer       Lscala/actors/scheduler/ExecutorScheduler;
   0      27      2    fun       Lscala/Function0;

  Signature: length = 0x2
   00 1E 

public java.lang.Object call();
  Code:
   Stack=1, Locals=1, Args_size=1
   0:	aload_0
   1:	invokevirtual	#34; //Method call:()V
   4:	getstatic	#40; //Field scala/runtime/BoxedUnit.UNIT:Lscala/runtime/BoxedUnit;
   7:	areturn
  LineNumberTable: 
   line 29: 0


public scala.actors.scheduler.ExecutorScheduler scala$actors$scheduler$ExecutorScheduler$RunCallable$$$outer();
  Code:
   Stack=1, Locals=1, Args_size=1
   0:	aload_0
   1:	getfield	#23; //Field $outer:Lscala/actors/scheduler/ExecutorScheduler;
   4:	areturn
  LineNumberTable: 
   line 29: 0


public void run();
  Code:
   Stack=1, Locals=1, Args_size=1
   0:	aload_0
   1:	getfield	#16; //Field fun:Lscala/Function0;
   4:	invokeinterface	#48,  1; //InterfaceMethod scala/Function0.apply:()Ljava/lang/Object;
   9:	pop
   10:	return
  LineNumberTable: 
   line 31: 0


public void call();
  Code:
   Stack=1, Locals=1, Args_size=1
   0:	aload_0
   1:	getfield	#16; //Field fun:Lscala/Function0;
   4:	invokeinterface	#48,  1; //InterfaceMethod scala/Function0.apply:()Ljava/lang/Object;
   9:	pop
   10:	return
  LineNumberTable: 
   line 30: 0


}

