Compiled from "ExecutorScheduler.scala"
public abstract class scala.actors.scheduler.ExecutorScheduler$class extends java.lang.Object
  SourceFile: "ExecutorScheduler.scala"
  Scala: length = 0x
   
  InnerClass: 
   public RunCallable=class scala/actors/scheduler/ExecutorScheduler$RunCallable of class scala/actors/scheduler/ExecutorScheduler
  minor version: 0
  major version: 49
  Constant pool:
Asciz	SourceFile;
Asciz	ExecutorScheduler.scala;
Asciz	$init$;
Asciz	(Lscala/actors/scheduler/ExecutorScheduler;)V;
Asciz	Code;
Asciz	LineNumberTable;
Asciz	$this;
Asciz	Lscala/actors/scheduler/ExecutorScheduler;;
Asciz	LocalVariableTable;
Asciz	isActive;
Asciz	(Lscala/actors/scheduler/ExecutorScheduler;)Z;
Asciz	scala/concurrent/ThreadPoolRunner;
class	scala/concurrent/ThreadPoolRunner
Asciz	executor;
Asciz	()Ljava/util/concurrent/ExecutorService;;
NameAndType	executor:()Ljava/util/concurrent/ExecutorService;
InterfaceMethod	scala/concurrent/ThreadPoolRunner.executor:()Ljava/util/concurrent/ExecutorService;
Asciz	java/util/concurrent/ExecutorService;
class	java/util/concurrent/ExecutorService
Asciz	isShutdown;
Asciz	()Z;
NameAndType	isShutdown:()Z
InterfaceMethod	java/util/concurrent/ExecutorService.isShutdown:()Z
Asciz	onShutdown;
Asciz	shutdown;
Asciz	()V;
NameAndType	shutdown:()V
InterfaceMethod	java/util/concurrent/ExecutorService.shutdown:()V
Asciz	execute;
Asciz	(Lscala/actors/scheduler/ExecutorScheduler;Lscala/Function0;)V;
Asciz	scala/actors/scheduler/ExecutorScheduler$RunCallable;
class	scala/actors/scheduler/ExecutorScheduler$RunCallable
Asciz	<init>;
NameAndType	"<init>":(Lscala/actors/scheduler/ExecutorScheduler;Lscala/Function0;)V
Method	scala/actors/scheduler/ExecutorScheduler$RunCallable."<init>":(Lscala/actors/scheduler/ExecutorScheduler;Lscala/Function0;)V
Asciz	scala/concurrent/ThreadPoolRunner$class;
class	scala/concurrent/ThreadPoolRunner$class
Asciz	(Lscala/concurrent/ThreadPoolRunner;Ljava/util/concurrent/Callable;)V;
NameAndType	execute:(Lscala/concurrent/ThreadPoolRunner;Ljava/util/concurrent/Callable;)V
Method	scala/concurrent/ThreadPoolRunner$class.execute:(Lscala/concurrent/ThreadPoolRunner;Ljava/util/concurrent/Callable;)V
Asciz	fun;
Asciz	Lscala/Function0;;
Asciz	(Lscala/actors/scheduler/ExecutorScheduler;Ljava/lang/Runnable;)V;
Asciz	java/util/concurrent/Callable;
class	java/util/concurrent/Callable
Asciz	task;
Asciz	Ljava/lang/Runnable;;
Asciz	Scala;
Asciz	InnerClasses;
Asciz	scala/actors/scheduler/ExecutorScheduler;
class	scala/actors/scheduler/ExecutorScheduler
Asciz	RunCallable;
Asciz	scala/actors/scheduler/ExecutorScheduler$class;
class	scala/actors/scheduler/ExecutorScheduler$class
Asciz	java/lang/Object;
class	java/lang/Object

{
public static void $init$(scala.actors.scheduler.ExecutorScheduler);
  Signature: (Lscala/actors/scheduler/ExecutorScheduler;)V
  Code:
   Stack=0, Locals=1, Args_size=1
	return
  Labels:
  LocalVariableTable: 
   Start  Length  Slot  Name   Signature
   0      1      0    $this       Lscala/actors/scheduler/ExecutorScheduler;


public static boolean isActive(scala.actors.scheduler.ExecutorScheduler);
  Signature: (Lscala/actors/scheduler/ExecutorScheduler;)Z
  Code:
   Stack=1, Locals=1, Args_size=1
	aload_0
	invokeinterface	InterfaceMethod scala/concurrent/ThreadPoolRunner.executor:()Ljava/util/concurrent/ExecutorService;
	ifnull	l1 // iconst_0
	aload_0
	invokeinterface	InterfaceMethod scala/concurrent/ThreadPoolRunner.executor:()Ljava/util/concurrent/ExecutorService;
	invokeinterface	InterfaceMethod java/util/concurrent/ExecutorService.isShutdown:()Z
	ifne	l1 // iconst_0
	iconst_1
	goto	l2 // ireturn
l1	iconst_0
l2	ireturn
  Labels:
   	l1 = 27 // iconst_0
   	l2 = 28 // ireturn
  LocalVariableTable: 
   Start  Length  Slot  Name   Signature
   0      29      0    $this       Lscala/actors/scheduler/ExecutorScheduler;


public static void onShutdown(scala.actors.scheduler.ExecutorScheduler);
  Signature: (Lscala/actors/scheduler/ExecutorScheduler;)V
  Code:
   Stack=1, Locals=1, Args_size=1
	aload_0
	invokeinterface	InterfaceMethod scala/concurrent/ThreadPoolRunner.executor:()Ljava/util/concurrent/ExecutorService;
	invokeinterface	InterfaceMethod java/util/concurrent/ExecutorService.shutdown:()V
	return
  Labels:
  LocalVariableTable: 
   Start  Length  Slot  Name   Signature
   0      12      0    $this       Lscala/actors/scheduler/ExecutorScheduler;


public static void execute(scala.actors.scheduler.ExecutorScheduler, scala.Function0);
  Signature: (Lscala/actors/scheduler/ExecutorScheduler;Lscala/Function0;)V
  Code:
   Stack=5, Locals=2, Args_size=2
	aload_0
	new	class scala/actors/scheduler/ExecutorScheduler$RunCallable
	dup
	aload_0
	aload_1
	invokespecial	Method scala/actors/scheduler/ExecutorScheduler$RunCallable."<init>":(Lscala/actors/scheduler/ExecutorScheduler;Lscala/Function0;)V
	invokestatic	Method scala/concurrent/ThreadPoolRunner$class.execute:(Lscala/concurrent/ThreadPoolRunner;Ljava/util/concurrent/Callable;)V
	return
  Labels:
  LocalVariableTable: 
   Start  Length  Slot  Name   Signature
   0      14      0    $this       Lscala/actors/scheduler/ExecutorScheduler;
   0      14      1    fun       Lscala/Function0;


public static void execute(scala.actors.scheduler.ExecutorScheduler, java.lang.Runnable);
  Signature: (Lscala/actors/scheduler/ExecutorScheduler;Ljava/lang/Runnable;)V
  Code:
   Stack=2, Locals=2, Args_size=2
	aload_0
	aload_1
	checkcast	class java/util/concurrent/Callable
	invokestatic	Method scala/concurrent/ThreadPoolRunner$class.execute:(Lscala/concurrent/ThreadPoolRunner;Ljava/util/concurrent/Callable;)V
	return
  Labels:
  LocalVariableTable: 
   Start  Length  Slot  Name   Signature
   0      9      0    $this       Lscala/actors/scheduler/ExecutorScheduler;
   0      9      1    task       Ljava/lang/Runnable;


}

