Compiled from "ExecutorScheduler.scala"
public class scala.actors.scheduler.ExecutorScheduler$RunCallable extends java.lang.Object implements java.util.concurrent.Callable,java.lang.Runnable,scala.ScalaObject
  SourceFile: "ExecutorScheduler.scala"
  Scala: length = 0x
   
  Signature: length = 0x2
   00 32 
  InnerClass: 
   public RunCallable=class scala/actors/scheduler/ExecutorScheduler$RunCallable of class scala/actors/scheduler/ExecutorScheduler
  minor version: 0
  major version: 49
  Constant pool:
Asciz	SourceFile;
Asciz	ExecutorScheduler.scala;
Asciz	fun;
Asciz	Lscala/Function0;;
Asciz	Lscala/Function0<Ljava/lang/Object;>;;
Asciz	Signature;
Asciz	$outer;
Asciz	Lscala/actors/scheduler/ExecutorScheduler;;
Asciz	call;
Asciz	()V;
Asciz	Code;
Asciz	LineNumberTable;
Asciz	scala/actors/scheduler/ExecutorScheduler$RunCallable;
class	scala/actors/scheduler/ExecutorScheduler$RunCallable
NameAndType	fun:Lscala/Function0;
Field	scala/actors/scheduler/ExecutorScheduler$RunCallable.fun:Lscala/Function0;
Asciz	scala/Function0;
class	scala/Function0
Asciz	apply;
Asciz	()Ljava/lang/Object;;
NameAndType	apply:()Ljava/lang/Object;
InterfaceMethod	scala/Function0.apply:()Ljava/lang/Object;
Asciz	run;
Asciz	scala$actors$scheduler$ExecutorScheduler$RunCallable$$$outer;
Asciz	()Lscala/actors/scheduler/ExecutorScheduler;;
NameAndType	$outer:Lscala/actors/scheduler/ExecutorScheduler;
Field	scala/actors/scheduler/ExecutorScheduler$RunCallable.$outer:Lscala/actors/scheduler/ExecutorScheduler;
NameAndType	call:()V
Method	scala/actors/scheduler/ExecutorScheduler$RunCallable.call:()V
Asciz	scala/runtime/BoxedUnit;
class	scala/runtime/BoxedUnit
Asciz	UNIT;
Asciz	Lscala/runtime/BoxedUnit;;
NameAndType	UNIT:Lscala/runtime/BoxedUnit;
Field	scala/runtime/BoxedUnit.UNIT:Lscala/runtime/BoxedUnit;
Asciz	<init>;
Asciz	(Lscala/actors/scheduler/ExecutorScheduler;Lscala/Function0;)V;
Asciz	java/lang/NullPointerException;
class	java/lang/NullPointerException
NameAndType	"<init>":()V
Method	java/lang/NullPointerException."<init>":()V
Asciz	java/lang/Object;
class	java/lang/Object
Method	java/lang/Object."<init>":()V
Asciz	this;
Asciz	Lscala/actors/scheduler/ExecutorScheduler$RunCallable;;
Asciz	LocalVariableTable;
Asciz	(Lscala/actors/scheduler/ExecutorScheduler;Lscala/Function0<Ljava/lang/Object;>;)V;
Asciz	Scala;
Asciz	Ljava/lang/Object;Ljava/util/concurrent/Callable<Ljava/lang/Object;>;Ljava/lang/Runnable;Lscala/ScalaObject;;
Asciz	InnerClasses;
Asciz	scala/actors/scheduler/ExecutorScheduler;
class	scala/actors/scheduler/ExecutorScheduler
Asciz	RunCallable;
Asciz	java/util/concurrent/Callable;
class	java/util/concurrent/Callable
Asciz	java/lang/Runnable;
class	java/lang/Runnable
Asciz	scala/ScalaObject;
class	scala/ScalaObject

{
private final scala.Function0 fun;
  Signature: Lscala/Function0;
  Signature: length = 0x2
   00 05 

public final scala.actors.scheduler.ExecutorScheduler $outer;
  Signature: Lscala/actors/scheduler/ExecutorScheduler;

public void call();
  Signature: ()V
  Code:
   Stack=1, Locals=1, Args_size=1
	aload_0
	getfield	Field fun:Lscala/Function0;
	invokeinterface	InterfaceMethod scala/Function0.apply:()Ljava/lang/Object;
	pop
	return
  Labels:

public void run();
  Signature: ()V
  Code:
   Stack=1, Locals=1, Args_size=1
	aload_0
	getfield	Field fun:Lscala/Function0;
	invokeinterface	InterfaceMethod scala/Function0.apply:()Ljava/lang/Object;
	pop
	return
  Labels:

public scala.actors.scheduler.ExecutorScheduler scala$actors$scheduler$ExecutorScheduler$RunCallable$$$outer();
  Signature: ()Lscala/actors/scheduler/ExecutorScheduler;
  Code:
   Stack=1, Locals=1, Args_size=1
	aload_0
	getfield	Field $outer:Lscala/actors/scheduler/ExecutorScheduler;
	areturn
  Labels:

public java.lang.Object call();
  Signature: ()Ljava/lang/Object;
  Code:
   Stack=1, Locals=1, Args_size=1
	aload_0
	invokevirtual	Method call:()V
	getstatic	Field scala/runtime/BoxedUnit.UNIT:Lscala/runtime/BoxedUnit;
	areturn
  Labels:

public scala.actors.scheduler.ExecutorScheduler$RunCallable(scala.actors.scheduler.ExecutorScheduler, scala.Function0);
  Signature: (Lscala/actors/scheduler/ExecutorScheduler;Lscala/Function0;)V
  Code:
   Stack=2, Locals=3, Args_size=3
	aload_0
	aload_2
	putfield	Field fun:Lscala/Function0;
	aload_1
	ifnonnull	l1 // aload_0
	new	class java/lang/NullPointerException
	dup
	invokespecial	Method java/lang/NullPointerException."<init>":()V
	athrow
l1	aload_0
	aload_1
	putfield	Field $outer:Lscala/actors/scheduler/ExecutorScheduler;
	aload_0
	invokespecial	Method java/lang/Object."<init>":()V
	return
  Labels:
   	l1 = 17 // aload_0
  LocalVariableTable: 
   Start  Length  Slot  Name   Signature
   0      27      0    this       Lscala/actors/scheduler/ExecutorScheduler$RunCallable;
   0      27      1    $outer       Lscala/actors/scheduler/ExecutorScheduler;
   0      27      2    fun       Lscala/Function0;

  Signature: length = 0x2
   00 30 

}

