Compiled from "ForkJoinScheduler.scala"
public final class scala.actors.scheduler.ForkJoinScheduler$$anonfun$allWorkersBlocked$1 extends java.lang.Object implements scala.Function1,scala.ScalaObject,java.io.Serializable
  SourceFile: "ForkJoinScheduler.scala"
  Scala: length = 0x
   
  InnerClass: 
   public final #82= #49 of #81; //State=class java/lang/Thread$State of class java/lang/Thread
   public final #85= #28 of #84; //$anonfun$allWorkersBlocked$1=class scala/actors/scheduler/ForkJoinScheduler$$anonfun$allWorkersBlocked$1 of class scala/actors/scheduler/ForkJoinScheduler
  minor version: 0
  major version: 49
  Constant pool:
const #1 = Asciz	SourceFile;
const #2 = Asciz	ForkJoinScheduler.scala;
const #3 = Asciz	<init>;
const #4 = Asciz	(Lscala/actors/scheduler/ForkJoinScheduler;)V;
const #5 = Asciz	Code;
const #6 = Asciz	LineNumberTable;
const #7 = Asciz	java/lang/Object;
const #8 = class	#7;	//  java/lang/Object
const #9 = Asciz	()V;
const #10 = NameAndType	#3:#9;//  "<init>":()V
const #11 = Method	#8.#10;	//  java/lang/Object."<init>":()V
const #12 = Asciz	scala/Function1$class;
const #13 = class	#12;	//  scala/Function1$class
const #14 = Asciz	$init$;
const #15 = Asciz	(Lscala/Function1;)V;
const #16 = NameAndType	#14:#15;//  $init$:(Lscala/Function1;)V
const #17 = Method	#13.#16;	//  scala/Function1$class.$init$:(Lscala/Function1;)V
const #18 = Asciz	this;
const #19 = Asciz	Lscala/actors/scheduler/ForkJoinScheduler$$anonfun$allWorkersBlocked$1;;
const #20 = Asciz	$outer;
const #21 = Asciz	Lscala/actors/scheduler/ForkJoinScheduler;;
const #22 = Asciz	LocalVariableTable;
const #23 = Asciz	apply;
const #24 = Asciz	(Ljava/lang/Object;)Ljava/lang/Object;;
const #25 = Asciz	scala/actors/forkjoin/ForkJoinWorkerThread;
const #26 = class	#25;	//  scala/actors/forkjoin/ForkJoinWorkerThread
const #27 = Asciz	scala/actors/scheduler/ForkJoinScheduler$$anonfun$allWorkersBlocked$1;
const #28 = class	#27;	//  scala/actors/scheduler/ForkJoinScheduler$$anonfun$allWorkersBlocked$1
const #29 = Asciz	(Lscala/actors/forkjoin/ForkJoinWorkerThread;)Z;
const #30 = NameAndType	#23:#29;//  apply:(Lscala/actors/forkjoin/ForkJoinWorkerThread;)Z
const #31 = Method	#28.#30;	//  scala/actors/scheduler/ForkJoinScheduler$$anonfun$allWorkersBlocked$1.apply:(Lscala/actors/forkjoin/ForkJoinWorkerThread;)Z
const #32 = Asciz	scala/runtime/BoxesRunTime;
const #33 = class	#32;	//  scala/runtime/BoxesRunTime
const #34 = Asciz	boxToBoolean;
const #35 = Asciz	(Z)Ljava/lang/Boolean;;
const #36 = NameAndType	#34:#35;//  boxToBoolean:(Z)Ljava/lang/Boolean;
const #37 = Method	#33.#36;	//  scala/runtime/BoxesRunTime.boxToBoolean:(Z)Ljava/lang/Boolean;
const #38 = Asciz	v1;
const #39 = Asciz	Ljava/lang/Object;;
const #40 = Asciz	equals;
const #41 = Asciz	(Ljava/lang/Object;)Z;
const #42 = NameAndType	#40:#41;//  equals:(Ljava/lang/Object;)Z
const #43 = Method	#8.#42;	//  java/lang/Object.equals:(Ljava/lang/Object;)Z
const #44 = Asciz	getState;
const #45 = Asciz	()Ljava/lang/Thread$State;;
const #46 = NameAndType	#44:#45;//  getState:()Ljava/lang/Thread$State;
const #47 = Method	#26.#46;	//  scala/actors/forkjoin/ForkJoinWorkerThread.getState:()Ljava/lang/Thread$State;
const #48 = Asciz	java/lang/Thread$State;
const #49 = class	#48;	//  java/lang/Thread$State
const #50 = Asciz	BLOCKED;
const #51 = Asciz	Ljava/lang/Thread$State;;
const #52 = NameAndType	#50:#51;//  BLOCKED:Ljava/lang/Thread$State;
const #53 = Field	#49.#52;	//  java/lang/Thread$State.BLOCKED:Ljava/lang/Thread$State;
const #54 = Asciz	WAITING;
const #55 = NameAndType	#54:#51;//  WAITING:Ljava/lang/Thread$State;
const #56 = Field	#49.#55;	//  java/lang/Thread$State.WAITING:Ljava/lang/Thread$State;
const #57 = Asciz	TIMED_WAITING;
const #58 = NameAndType	#57:#51;//  TIMED_WAITING:Ljava/lang/Thread$State;
const #59 = Field	#49.#58;	//  java/lang/Thread$State.TIMED_WAITING:Ljava/lang/Thread$State;
const #60 = Asciz	t;
const #61 = Asciz	Lscala/actors/forkjoin/ForkJoinWorkerThread;;
const #62 = Asciz	s;
const #63 = Asciz	andThen;
const #64 = Asciz	(Lscala/Function1;)Lscala/Function1;;
const #65 = Asciz	(Lscala/Function1;Lscala/Function1;)Lscala/Function1;;
const #66 = NameAndType	#63:#65;//  andThen:(Lscala/Function1;Lscala/Function1;)Lscala/Function1;
const #67 = Method	#13.#66;	//  scala/Function1$class.andThen:(Lscala/Function1;Lscala/Function1;)Lscala/Function1;
const #68 = Asciz	g;
const #69 = Asciz	Lscala/Function1;;
const #70 = Asciz	compose;
const #71 = NameAndType	#70:#65;//  compose:(Lscala/Function1;Lscala/Function1;)Lscala/Function1;
const #72 = Method	#13.#71;	//  scala/Function1$class.compose:(Lscala/Function1;Lscala/Function1;)Lscala/Function1;
const #73 = Asciz	toString;
const #74 = Asciz	()Ljava/lang/String;;
const #75 = Asciz	(Lscala/Function1;)Ljava/lang/String;;
const #76 = NameAndType	#73:#75;//  toString:(Lscala/Function1;)Ljava/lang/String;
const #77 = Method	#13.#76;	//  scala/Function1$class.toString:(Lscala/Function1;)Ljava/lang/String;
const #78 = Asciz	Scala;
const #79 = Asciz	InnerClasses;
const #80 = Asciz	java/lang/Thread;
const #81 = class	#80;	//  java/lang/Thread
const #82 = Asciz	State;
const #83 = Asciz	scala/actors/scheduler/ForkJoinScheduler;
const #84 = class	#83;	//  scala/actors/scheduler/ForkJoinScheduler
const #85 = Asciz	$anonfun$allWorkersBlocked$1;
const #86 = Asciz	scala/Function1;
const #87 = class	#86;	//  scala/Function1
const #88 = Asciz	scala/ScalaObject;
const #89 = class	#88;	//  scala/ScalaObject
const #90 = Asciz	java/io/Serializable;
const #91 = class	#90;	//  java/io/Serializable

{
public scala.actors.scheduler.ForkJoinScheduler$$anonfun$allWorkersBlocked$1(scala.actors.scheduler.ForkJoinScheduler);
  Code:
   Stack=1, Locals=2, Args_size=2
   0:	aload_0
   1:	invokespecial	#11; //Method java/lang/Object."<init>":()V
   4:	aload_0
   5:	invokestatic	#17; //Method scala/Function1$class.$init$:(Lscala/Function1;)V
   8:	return
  LineNumberTable: 
   line 39: 0

  LocalVariableTable: 
   Start  Length  Slot  Name   Signature
   0      9      0    this       Lscala/actors/scheduler/ForkJoinScheduler$$anonfun$allWorkersBlocked$1;
   0      9      1    $outer       Lscala/actors/scheduler/ForkJoinScheduler;


public final java.lang.Object apply(java.lang.Object);
  Code:
   Stack=2, Locals=2, Args_size=2
   0:	aload_0
   1:	aload_1
   2:	checkcast	#26; //class scala/actors/forkjoin/ForkJoinWorkerThread
   5:	invokevirtual	#31; //Method apply:(Lscala/actors/forkjoin/ForkJoinWorkerThread;)Z
   8:	invokestatic	#37; //Method scala/runtime/BoxesRunTime.boxToBoolean:(Z)Ljava/lang/Boolean;
   11:	areturn
  LineNumberTable: 
   line 39: 0

  LocalVariableTable: 
   Start  Length  Slot  Name   Signature
   0      12      0    this       Lscala/actors/scheduler/ForkJoinScheduler$$anonfun$allWorkersBlocked$1;
   0      12      1    v1       Ljava/lang/Object;


public final boolean apply(scala.actors.forkjoin.ForkJoinWorkerThread);
  Code:
   Stack=2, Locals=7, Args_size=2
   0:	aload_1
   1:	dup
   2:	astore_2
   3:	ifnull	108
   6:	aload_2
   7:	aconst_null
   8:	invokevirtual	#43; //Method java/lang/Object.equals:(Ljava/lang/Object;)Z
   11:	ifne	108
   14:	aload_1
   15:	invokevirtual	#47; //Method scala/actors/forkjoin/ForkJoinWorkerThread.getState:()Ljava/lang/Thread$State;
   18:	astore_3
   19:	aload_3
   20:	getstatic	#53; //Field java/lang/Thread$State.BLOCKED:Ljava/lang/Thread$State;
   23:	astore	4
   25:	dup
   26:	ifnonnull	38
   29:	pop
   30:	aload	4
   32:	ifnull	100
   35:	goto	46
   38:	aload	4
   40:	invokevirtual	#43; //Method java/lang/Object.equals:(Ljava/lang/Object;)Z
   43:	ifne	100
   46:	aload_3
   47:	getstatic	#56; //Field java/lang/Thread$State.WAITING:Ljava/lang/Thread$State;
   50:	astore	5
   52:	dup
   53:	ifnonnull	65
   56:	pop
   57:	aload	5
   59:	ifnull	100
   62:	goto	73
   65:	aload	5
   67:	invokevirtual	#43; //Method java/lang/Object.equals:(Ljava/lang/Object;)Z
   70:	ifne	100
   73:	aload_3
   74:	getstatic	#59; //Field java/lang/Thread$State.TIMED_WAITING:Ljava/lang/Thread$State;
   77:	astore	6
   79:	dup
   80:	ifnonnull	92
   83:	pop
   84:	aload	6
   86:	ifnull	100
   89:	goto	104
   92:	aload	6
   94:	invokevirtual	#43; //Method java/lang/Object.equals:(Ljava/lang/Object;)Z
   97:	ifeq	104
   100:	iconst_1
   101:	goto	105
   104:	iconst_0
   105:	ifeq	112
   108:	iconst_1
   109:	goto	113
   112:	iconst_0
   113:	ireturn
  LineNumberTable: 
   line 40: 0
   line 41: 14
   line 42: 19
   line 40: 105

  LocalVariableTable: 
   Start  Length  Slot  Name   Signature
   0      114      0    this       Lscala/actors/scheduler/ForkJoinScheduler$$anonfun$allWorkersBlocked$1;
   0      114      1    t       Lscala/actors/forkjoin/ForkJoinWorkerThread;
   19      89      3    s       Ljava/lang/Thread$State;


public scala.Function1 andThen(scala.Function1);
  Code:
   Stack=2, Locals=2, Args_size=2
   0:	aload_0
   1:	aload_1
   2:	invokestatic	#67; //Method scala/Function1$class.andThen:(Lscala/Function1;Lscala/Function1;)Lscala/Function1;
   5:	areturn
  LineNumberTable: 
   line 39: 0

  LocalVariableTable: 
   Start  Length  Slot  Name   Signature
   0      6      0    this       Lscala/actors/scheduler/ForkJoinScheduler$$anonfun$allWorkersBlocked$1;
   0      6      1    g       Lscala/Function1;


public scala.Function1 compose(scala.Function1);
  Code:
   Stack=2, Locals=2, Args_size=2
   0:	aload_0
   1:	aload_1
   2:	invokestatic	#72; //Method scala/Function1$class.compose:(Lscala/Function1;Lscala/Function1;)Lscala/Function1;
   5:	areturn
  LineNumberTable: 
   line 39: 0

  LocalVariableTable: 
   Start  Length  Slot  Name   Signature
   0      6      0    this       Lscala/actors/scheduler/ForkJoinScheduler$$anonfun$allWorkersBlocked$1;
   0      6      1    g       Lscala/Function1;


public java.lang.String toString();
  Code:
   Stack=1, Locals=1, Args_size=1
   0:	aload_0
   1:	invokestatic	#77; //Method scala/Function1$class.toString:(Lscala/Function1;)Ljava/lang/String;
   4:	areturn
  LineNumberTable: 
   line 39: 0


}

