Compiled from "SchedulerService.scala"
public class scala.actors.scheduler.QuitException extends java.lang.Throwable implements scala.util.control.ControlException,scala.ScalaObject
  SourceFile: "SchedulerService.scala"
  ScalaSig: length = 0xD8
   05 00 23 06 09 01 02 FFFFFF84 FFFFFF80 FFFFFF80 FFFFFF80 00 04 08 02 0D
   51 75 69 74 45 78 63 65 70 74 69 6F 6E 0A 02 03
   04 01 09 73 63 68 65 64 75 6C 65 72 0A 02 05 06
   01 06 61 63 74 6F 72 73 0A 01 07 01 05 73 63 61
   6C 61 13 04 00 09 11 19 10 02 0A 0F 0D 01 0B 0A
   02 0C 0D 01 04 6C 61 6E 67 0A 01 0E 01 04 6A 61
   76 61 09 02 10 0B 02 09 54 68 72 6F 77 61 62 6C
   65 10 02 12 17 0D 01 13 0A 02 14 15 01 07 63 6F
   6E 74 72 6F 6C 0A 02 16 06 01 04 75 74 69 6C 09
   02 18 13 02 10 43 6F 6E 74 72 6F 6C 45 78 63 65
   70 74 69 6F 6E 10 02 1A 1B 0D 01 06 09 02 1C 06
   02 0B 53 63 61 6C 61 4F 62 6A 65 63 74 08 05 1E
   00 FFFFFF84 00 20 01 06 3C 69 6E 69 74 3E 03 00 14 01
   21 10 02 22 00 0D 01 02 
  minor version: 0
  major version: 49
  Constant pool:
const #1 = Asciz	SourceFile;
const #2 = Asciz	SchedulerService.scala;
const #3 = Asciz	<init>;
const #4 = Asciz	()V;
const #5 = Asciz	Code;
const #6 = Asciz	LineNumberTable;
const #7 = Asciz	java/lang/Throwable;
const #8 = class	#7;	//  java/lang/Throwable
const #9 = NameAndType	#3:#4;//  "<init>":()V
const #10 = Method	#8.#9;	//  java/lang/Throwable."<init>":()V
const #11 = Asciz	scala/util/control/NoStackTrace$class;
const #12 = class	#11;	//  scala/util/control/NoStackTrace$class
const #13 = Asciz	$init$;
const #14 = Asciz	(Lscala/util/control/NoStackTrace;)V;
const #15 = NameAndType	#13:#14;//  $init$:(Lscala/util/control/NoStackTrace;)V
const #16 = Method	#12.#15;	//  scala/util/control/NoStackTrace$class.$init$:(Lscala/util/control/NoStackTrace;)V
const #17 = Asciz	fillInStackTrace;
const #18 = Asciz	()Ljava/lang/Throwable;;
const #19 = Asciz	(Lscala/util/control/NoStackTrace;)Ljava/lang/Throwable;;
const #20 = NameAndType	#17:#19;//  fillInStackTrace:(Lscala/util/control/NoStackTrace;)Ljava/lang/Throwable;
const #21 = Method	#12.#20;	//  scala/util/control/NoStackTrace$class.fillInStackTrace:(Lscala/util/control/NoStackTrace;)Ljava/lang/Throwable;
const #22 = Asciz	ScalaSig;
const #23 = Asciz	scala/actors/scheduler/QuitException;
const #24 = class	#23;	//  scala/actors/scheduler/QuitException
const #25 = Asciz	scala/util/control/ControlException;
const #26 = class	#25;	//  scala/util/control/ControlException
const #27 = Asciz	scala/ScalaObject;
const #28 = class	#27;	//  scala/ScalaObject

{
public scala.actors.scheduler.QuitException();
  Code:
   Stack=1, Locals=1, Args_size=1
   0:	aload_0
   1:	invokespecial	#10; //Method java/lang/Throwable."<init>":()V
   4:	aload_0
   5:	invokestatic	#16; //Method scala/util/control/NoStackTrace$class.$init$:(Lscala/util/control/NoStackTrace;)V
   8:	return
  LineNumberTable: 
   line 80: 0


public java.lang.Throwable fillInStackTrace();
  Code:
   Stack=1, Locals=1, Args_size=1
   0:	aload_0
   1:	invokestatic	#21; //Method scala/util/control/NoStackTrace$class.fillInStackTrace:(Lscala/util/control/NoStackTrace;)Ljava/lang/Throwable;
   4:	areturn
  LineNumberTable: 
   line 80: 0


}

