Compiled from "ResizableThreadPoolScheduler.scala"
public class scala.actors.scheduler.ResizableThreadPoolScheduler$DaemonThreadFactory extends java.lang.Object implements scala.actors.threadpool.ThreadFactory,scala.ScalaObject
  SourceFile: "ResizableThreadPoolScheduler.scala"
  Scala: length = 0x
   
  InnerClass: 
   public #51= #15 of #36; //DaemonThreadFactory=class scala/actors/scheduler/ResizableThreadPoolScheduler$DaemonThreadFactory of class scala/actors/scheduler/ResizableThreadPoolScheduler
  minor version: 0
  major version: 49
  Constant pool:
const #1 = Asciz	SourceFile;
const #2 = Asciz	ResizableThreadPoolScheduler.scala;
const #3 = Asciz	$outer;
const #4 = Asciz	Lscala/actors/scheduler/ResizableThreadPoolScheduler;;
const #5 = Asciz	<init>;
const #6 = Asciz	(Lscala/actors/scheduler/ResizableThreadPoolScheduler;)V;
const #7 = Asciz	Code;
const #8 = Asciz	LineNumberTable;
const #9 = Asciz	java/lang/NullPointerException;
const #10 = class	#9;	//  java/lang/NullPointerException
const #11 = Asciz	()V;
const #12 = NameAndType	#5:#11;//  "<init>":()V
const #13 = Method	#10.#12;	//  java/lang/NullPointerException."<init>":()V
const #14 = Asciz	scala/actors/scheduler/ResizableThreadPoolScheduler$DaemonThreadFactory;
const #15 = class	#14;	//  scala/actors/scheduler/ResizableThreadPoolScheduler$DaemonThreadFactory
const #16 = NameAndType	#3:#4;//  $outer:Lscala/actors/scheduler/ResizableThreadPoolScheduler;
const #17 = Field	#15.#16;	//  scala/actors/scheduler/ResizableThreadPoolScheduler$DaemonThreadFactory.$outer:Lscala/actors/scheduler/ResizableThreadPoolScheduler;
const #18 = Asciz	java/lang/Object;
const #19 = class	#18;	//  java/lang/Object
const #20 = Method	#19.#12;	//  java/lang/Object."<init>":()V
const #21 = Asciz	this;
const #22 = Asciz	Lscala/actors/scheduler/ResizableThreadPoolScheduler$DaemonThreadFactory;;
const #23 = Asciz	LocalVariableTable;
const #24 = Asciz	scala$actors$scheduler$ResizableThreadPoolScheduler$DaemonThreadFactory$$$outer;
const #25 = Asciz	()Lscala/actors/scheduler/ResizableThreadPoolScheduler;;
const #26 = Asciz	newThread;
const #27 = Asciz	(Ljava/lang/Runnable;)Ljava/lang/Thread;;
const #28 = Asciz	java/lang/Thread;
const #29 = class	#28;	//  java/lang/Thread
const #30 = Asciz	(Ljava/lang/Runnable;)V;
const #31 = NameAndType	#5:#30;//  "<init>":(Ljava/lang/Runnable;)V
const #32 = Method	#29.#31;	//  java/lang/Thread."<init>":(Ljava/lang/Runnable;)V
const #33 = NameAndType	#24:#25;//  scala$actors$scheduler$ResizableThreadPoolScheduler$DaemonThreadFactory$$$outer:()Lscala/actors/scheduler/ResizableThreadPoolScheduler;
const #34 = Method	#15.#33;	//  scala/actors/scheduler/ResizableThreadPoolScheduler$DaemonThreadFactory.scala$actors$scheduler$ResizableThreadPoolScheduler$DaemonThreadFactory$$$outer:()Lscala/actors/scheduler/ResizableThreadPoolScheduler;
const #35 = Asciz	scala/actors/scheduler/ResizableThreadPoolScheduler;
const #36 = class	#35;	//  scala/actors/scheduler/ResizableThreadPoolScheduler
const #37 = Asciz	daemon;
const #38 = Asciz	()Z;
const #39 = NameAndType	#37:#38;//  daemon:()Z
const #40 = Method	#36.#39;	//  scala/actors/scheduler/ResizableThreadPoolScheduler.daemon:()Z
const #41 = Asciz	setDaemon;
const #42 = Asciz	(Z)V;
const #43 = NameAndType	#41:#42;//  setDaemon:(Z)V
const #44 = Method	#29.#43;	//  java/lang/Thread.setDaemon:(Z)V
const #45 = Asciz	r;
const #46 = Asciz	Ljava/lang/Runnable;;
const #47 = Asciz	t;
const #48 = Asciz	Ljava/lang/Thread;;
const #49 = Asciz	Scala;
const #50 = Asciz	InnerClasses;
const #51 = Asciz	DaemonThreadFactory;
const #52 = Asciz	scala/actors/threadpool/ThreadFactory;
const #53 = class	#52;	//  scala/actors/threadpool/ThreadFactory
const #54 = Asciz	scala/ScalaObject;
const #55 = class	#54;	//  scala/ScalaObject

{
public final scala.actors.scheduler.ResizableThreadPoolScheduler $outer;

public scala.actors.scheduler.ResizableThreadPoolScheduler$DaemonThreadFactory(scala.actors.scheduler.ResizableThreadPoolScheduler);
  Code:
   Stack=2, Locals=2, Args_size=2
   0:	aload_1
   1:	ifnonnull	12
   4:	new	#10; //class java/lang/NullPointerException
   7:	dup
   8:	invokespecial	#13; //Method java/lang/NullPointerException."<init>":()V
   11:	athrow
   12:	aload_0
   13:	aload_1
   14:	putfield	#17; //Field $outer:Lscala/actors/scheduler/ResizableThreadPoolScheduler;
   17:	aload_0
   18:	invokespecial	#20; //Method java/lang/Object."<init>":()V
   21:	return
  LineNumberTable: 
   line 52: 0

  LocalVariableTable: 
   Start  Length  Slot  Name   Signature
   0      22      0    this       Lscala/actors/scheduler/ResizableThreadPoolScheduler$DaemonThreadFactory;
   0      22      1    $outer       Lscala/actors/scheduler/ResizableThreadPoolScheduler;


public scala.actors.scheduler.ResizableThreadPoolScheduler scala$actors$scheduler$ResizableThreadPoolScheduler$DaemonThreadFactory$$$outer();
  Code:
   Stack=1, Locals=1, Args_size=1
   0:	aload_0
   1:	getfield	#17; //Field $outer:Lscala/actors/scheduler/ResizableThreadPoolScheduler;
   4:	areturn
  LineNumberTable: 
   line 52: 0


public java.lang.Thread newThread(java.lang.Runnable);
  Code:
   Stack=3, Locals=3, Args_size=2
   0:	new	#29; //class java/lang/Thread
   3:	dup
   4:	aload_1
   5:	invokespecial	#32; //Method java/lang/Thread."<init>":(Ljava/lang/Runnable;)V
   8:	astore_2
   9:	aload_2
   10:	aload_0
   11:	invokevirtual	#34; //Method scala$actors$scheduler$ResizableThreadPoolScheduler$DaemonThreadFactory$$$outer:()Lscala/actors/scheduler/ResizableThreadPoolScheduler;
   14:	invokevirtual	#40; //Method scala/actors/scheduler/ResizableThreadPoolScheduler.daemon:()Z
   17:	invokevirtual	#44; //Method java/lang/Thread.setDaemon:(Z)V
   20:	aload_2
   21:	areturn
  LineNumberTable: 
   line 54: 0
   line 56: 9
   line 55: 10
   line 56: 20

  LocalVariableTable: 
   Start  Length  Slot  Name   Signature
   0      22      0    this       Lscala/actors/scheduler/ResizableThreadPoolScheduler$DaemonThreadFactory;
   0      22      1    r       Ljava/lang/Runnable;
   9      12      2    t       Ljava/lang/Thread;


}

