Compiled from "ResizableThreadPoolScheduler.scala"
public class scala.actors.scheduler.ResizableThreadPoolScheduler$DaemonThreadFactory extends java.lang.Object implements scala.actors.threadpool.ThreadFactory,scala.ScalaObject
  SourceFile: "ResizableThreadPoolScheduler.scala"
  Scala: length = 0x
   
  InnerClass: 
   public DaemonThreadFactory=class scala/actors/scheduler/ResizableThreadPoolScheduler$DaemonThreadFactory of class scala/actors/scheduler/ResizableThreadPoolScheduler
  minor version: 0
  major version: 49
  Constant pool:
Asciz	SourceFile;
Asciz	ResizableThreadPoolScheduler.scala;
Asciz	$outer;
Asciz	Lscala/actors/scheduler/ResizableThreadPoolScheduler;;
Asciz	newThread;
Asciz	(Ljava/lang/Runnable;)Ljava/lang/Thread;;
Asciz	Code;
Asciz	java/lang/Thread;
class	java/lang/Thread
Asciz	LineNumberTable;
Asciz	<init>;
Asciz	(Ljava/lang/Runnable;)V;
NameAndType	"<init>":(Ljava/lang/Runnable;)V
Method	java/lang/Thread."<init>":(Ljava/lang/Runnable;)V
Asciz	scala/actors/scheduler/ResizableThreadPoolScheduler$DaemonThreadFactory;
class	scala/actors/scheduler/ResizableThreadPoolScheduler$DaemonThreadFactory
Asciz	scala$actors$scheduler$ResizableThreadPoolScheduler$DaemonThreadFactory$$$outer;
Asciz	()Lscala/actors/scheduler/ResizableThreadPoolScheduler;;
NameAndType	scala$actors$scheduler$ResizableThreadPoolScheduler$DaemonThreadFactory$$$outer:()Lscala/actors/scheduler/ResizableThreadPoolScheduler;
Method	scala/actors/scheduler/ResizableThreadPoolScheduler$DaemonThreadFactory.scala$actors$scheduler$ResizableThreadPoolScheduler$DaemonThreadFactory$$$outer:()Lscala/actors/scheduler/ResizableThreadPoolScheduler;
Asciz	scala/actors/scheduler/ResizableThreadPoolScheduler;
class	scala/actors/scheduler/ResizableThreadPoolScheduler
Asciz	daemon;
Asciz	()Z;
NameAndType	daemon:()Z
Method	scala/actors/scheduler/ResizableThreadPoolScheduler.daemon:()Z
Asciz	setDaemon;
Asciz	(Z)V;
NameAndType	setDaemon:(Z)V
Method	java/lang/Thread.setDaemon:(Z)V
Asciz	this;
Asciz	Lscala/actors/scheduler/ResizableThreadPoolScheduler$DaemonThreadFactory;;
Asciz	r;
Asciz	Ljava/lang/Runnable;;
Asciz	t;
Asciz	Ljava/lang/Thread;;
Asciz	LocalVariableTable;
NameAndType	$outer:Lscala/actors/scheduler/ResizableThreadPoolScheduler;
Field	scala/actors/scheduler/ResizableThreadPoolScheduler$DaemonThreadFactory.$outer:Lscala/actors/scheduler/ResizableThreadPoolScheduler;
Asciz	(Lscala/actors/scheduler/ResizableThreadPoolScheduler;)V;
Asciz	java/lang/NullPointerException;
class	java/lang/NullPointerException
Asciz	()V;
NameAndType	"<init>":()V
Method	java/lang/NullPointerException."<init>":()V
Asciz	java/lang/Object;
class	java/lang/Object
Method	java/lang/Object."<init>":()V
Asciz	Scala;
Asciz	InnerClasses;
Asciz	DaemonThreadFactory;
Asciz	scala/actors/threadpool/ThreadFactory;
class	scala/actors/threadpool/ThreadFactory
Asciz	scala/ScalaObject;
class	scala/ScalaObject

{
public final scala.actors.scheduler.ResizableThreadPoolScheduler $outer;
  Signature: Lscala/actors/scheduler/ResizableThreadPoolScheduler;

public java.lang.Thread newThread(java.lang.Runnable);
  Signature: (Ljava/lang/Runnable;)Ljava/lang/Thread;
  Code:
   Stack=3, Locals=3, Args_size=2
	new	class java/lang/Thread
	dup
	aload_1
	invokespecial	Method java/lang/Thread."<init>":(Ljava/lang/Runnable;)V
	astore_2
	aload_2
	aload_0
	invokevirtual	Method scala$actors$scheduler$ResizableThreadPoolScheduler$DaemonThreadFactory$$$outer:()Lscala/actors/scheduler/ResizableThreadPoolScheduler;
	invokevirtual	Method scala/actors/scheduler/ResizableThreadPoolScheduler.daemon:()Z
	invokevirtual	Method java/lang/Thread.setDaemon:(Z)V
	aload_2
	areturn
  Labels:
  LocalVariableTable: 
   Start  Length  Slot  Name   Signature
   0      22      0    this       Lscala/actors/scheduler/ResizableThreadPoolScheduler$DaemonThreadFactory;
   0      22      1    r       Ljava/lang/Runnable;
   9      12      2    t       Ljava/lang/Thread;


public scala.actors.scheduler.ResizableThreadPoolScheduler scala$actors$scheduler$ResizableThreadPoolScheduler$DaemonThreadFactory$$$outer();
  Signature: ()Lscala/actors/scheduler/ResizableThreadPoolScheduler;
  Code:
   Stack=1, Locals=1, Args_size=1
	aload_0
	getfield	Field $outer:Lscala/actors/scheduler/ResizableThreadPoolScheduler;
	areturn
  Labels:

public scala.actors.scheduler.ResizableThreadPoolScheduler$DaemonThreadFactory(scala.actors.scheduler.ResizableThreadPoolScheduler);
  Signature: (Lscala/actors/scheduler/ResizableThreadPoolScheduler;)V
  Code:
   Stack=2, Locals=2, Args_size=2
	aload_1
	ifnonnull	l1 // aload_0
	new	class java/lang/NullPointerException
	dup
	invokespecial	Method java/lang/NullPointerException."<init>":()V
	athrow
l1	aload_0
	aload_1
	putfield	Field $outer:Lscala/actors/scheduler/ResizableThreadPoolScheduler;
	aload_0
	invokespecial	Method java/lang/Object."<init>":()V
	return
  Labels:
   	l1 = 12 // aload_0
  LocalVariableTable: 
   Start  Length  Slot  Name   Signature
   0      22      0    this       Lscala/actors/scheduler/ResizableThreadPoolScheduler$DaemonThreadFactory;
   0      22      1    $outer       Lscala/actors/scheduler/ResizableThreadPoolScheduler;


}

