Compiled from "SchedulerService.scala"
public abstract class scala.actors.scheduler.SchedulerService extends java.lang.Thread implements scala.actors.IScheduler,scala.actors.ActorGC,scala.ScalaObject
  SourceFile: "SchedulerService.scala"
  ScalaSig: length = 0x1D7
   05 00 46 06 08 01 02 FFFFFF84 FFFFFF80 FFFFFF80 FFFFFF81 00 09 02 10 53
   63 68 65 64 75 6C 65 72 53 65 72 76 69 63 65 0A
   02 03 04 01 09 73 63 68 65 64 75 6C 65 72 0A 02
   05 06 01 06 61 63 74 6F 72 73 0A 01 07 01 05 73
   63 61 6C 61 03 00 13 05 00 0A 12 16 19 10 02 0B
   10 0D 01 0C 0A 02 0D 0E 01 04 6C 61 6E 67 0A 01
   0F 01 04 6A 61 76 61 09 02 11 0C 02 06 54 68 72
   65 61 64 10 02 13 14 0D 01 04 09 02 15 04 02 0A
   49 53 63 68 65 64 75 6C 65 72 10 02 13 17 09 02
   18 04 02 07 41 63 74 6F 72 47 43 10 02 1A 1B 0D
   01 06 09 02 1C 06 02 0B 53 63 61 6C 61 4F 62 6A
   65 63 74 08 08 1E 00 FFFFFF82 FFFFFF80 FFFFFFA0 FFFFFF80 04 1F 01 06 64
   61 65 6D 6F 6E 10 02 1A 20 09 02 21 06 02 07 42
   6F 6F 6C 65 61 6E 08 05 23 00 FFFFFF84 00 24 01 06 3C
   69 6E 69 74 3E 14 02 25 27 10 02 26 00 0D 01 02
   08 05 1E 22 FFFFFFC0 00 1F 08 05 23 00 FFFFFF84 00 29 14 01
   25 08 07 2B 00 FFFFFFC0 FFFFFF80 FFFFFF84 04 2C 01 0B 74 65 72 6D
   69 6E 61 74 69 6E 67 15 01 1F 08 07 2E 00 FFFFFFC0 FFFFFF80
   FFFFFF84 04 2F 01 0F 74 65 72 6D 69 6E 61 74 69 6E 67
   5F 24 65 71 14 02 30 33 10 02 1A 31 09 02 32 06
   02 04 55 6E 69 74 08 07 34 2D FFFFFF81 FFFFFF80 FFFFFFC0 00 1F 01
   03 78 24 31 08 06 36 00 FFFFFFA0 FFFFFFA0 04 1F 01 0C 74 65
   72 6D 69 6E 61 74 69 6E 67 20 08 07 38 00 FFFFFFC2 FFFFFF80
   FFFFFF84 08 39 01 0A 43 48 45 43 4B 5F 46 52 45 51 15
   01 3A 10 02 1A 3B 09 02 3C 06 02 03 49 6E 74 08
   06 3E 00 FFFFFFA0 FFFFFF80 04 3A 01 0B 43 48 45 43 4B 5F 46
   52 45 51 20 08 05 40 00 FFFFFF86 00 41 01 0A 6F 6E 53
   68 75 74 64 6F 77 6E 14 01 30 08 05 43 00 FFFFFF84 20
   41 01 03 72 75 6E 08 05 45 00 FFFFFF84 00 41 01 08 73
   68 75 74 64 6F 77 6E 
  minor version: 0
  major version: 49
  Constant pool:
const #1 = Asciz	SourceFile;
const #2 = Asciz	SchedulerService.scala;
const #3 = Asciz	scala$actors$scheduler$TerminationMonitor$$started;
const #4 = Asciz	Z;
const #5 = Asciz	terminationHandlers;
const #6 = Asciz	Lscala/collection/mutable/HashMap;;
const #7 = Asciz	activeActors;
const #8 = Asciz	I;
const #9 = Asciz	scala$actors$ActorGC$$refSet;
const #10 = Asciz	Lscala/collection/mutable/HashSet;;
const #11 = Asciz	scala$actors$ActorGC$$refQ;
const #12 = Asciz	Ljava/lang/ref/ReferenceQueue;;
const #13 = Asciz	CHECK_FREQ;
const #14 = Asciz	terminating;
const #15 = Asciz	<init>;
const #16 = Asciz	(Z)V;
const #17 = Asciz	Code;
const #18 = Asciz	LineNumberTable;
const #19 = Asciz	java/lang/Thread;
const #20 = class	#19;	//  java/lang/Thread
const #21 = Asciz	()V;
const #22 = NameAndType	#15:#21;//  "<init>":()V
const #23 = Method	#20.#22;	//  java/lang/Thread."<init>":()V
const #24 = Asciz	scala/actors/IScheduler$class;
const #25 = class	#24;	//  scala/actors/IScheduler$class
const #26 = Asciz	$init$;
const #27 = Asciz	(Lscala/actors/IScheduler;)V;
const #28 = NameAndType	#26:#27;//  $init$:(Lscala/actors/IScheduler;)V
const #29 = Method	#25.#28;	//  scala/actors/IScheduler$class.$init$:(Lscala/actors/IScheduler;)V
const #30 = Asciz	scala/actors/scheduler/TerminationMonitor$class;
const #31 = class	#30;	//  scala/actors/scheduler/TerminationMonitor$class
const #32 = Asciz	(Lscala/actors/scheduler/TerminationMonitor;)V;
const #33 = NameAndType	#26:#32;//  $init$:(Lscala/actors/scheduler/TerminationMonitor;)V
const #34 = Method	#31.#33;	//  scala/actors/scheduler/TerminationMonitor$class.$init$:(Lscala/actors/scheduler/TerminationMonitor;)V
const #35 = Asciz	scala/actors/ActorGC$class;
const #36 = class	#35;	//  scala/actors/ActorGC$class
const #37 = Asciz	(Lscala/actors/ActorGC;)V;
const #38 = NameAndType	#26:#37;//  $init$:(Lscala/actors/ActorGC;)V
const #39 = Method	#36.#38;	//  scala/actors/ActorGC$class.$init$:(Lscala/actors/ActorGC;)V
const #40 = Asciz	scala/actors/scheduler/SchedulerService;
const #41 = class	#40;	//  scala/actors/scheduler/SchedulerService
const #42 = Asciz	setDaemon;
const #43 = NameAndType	#42:#16;//  setDaemon:(Z)V
const #44 = Method	#41.#43;	//  scala/actors/scheduler/SchedulerService.setDaemon:(Z)V
const #45 = NameAndType	#14:#4;//  terminating:Z
const #46 = Field	#41.#45;	//  scala/actors/scheduler/SchedulerService.terminating:Z
const #47 = int	100;
const #48 = NameAndType	#13:#8;//  CHECK_FREQ:I
const #49 = Field	#41.#48;	//  scala/actors/scheduler/SchedulerService.CHECK_FREQ:I
const #50 = Asciz	this;
const #51 = Asciz	Lscala/actors/scheduler/SchedulerService;;
const #52 = Asciz	daemon;
const #53 = Asciz	LocalVariableTable;
const #54 = Asciz	liftedTree1$1;
const #55 = Asciz	()I;
const #56 = NameAndType	#13:#55;//  CHECK_FREQ:()I
const #57 = Method	#41.#56;	//  scala/actors/scheduler/SchedulerService.CHECK_FREQ:()I
const #58 = Asciz	wait;
const #59 = Asciz	(J)V;
const #60 = NameAndType	#58:#59;//  wait:(J)V
const #61 = Method	#41.#60;	//  scala/actors/scheduler/SchedulerService.wait:(J)V
const #62 = Asciz	java/lang/InterruptedException;
const #63 = class	#62;	//  java/lang/InterruptedException
const #64 = Asciz	shutdown;
const #65 = Asciz	terminating_$eq;
const #66 = NameAndType	#65:#16;//  terminating_$eq:(Z)V
const #67 = Method	#41.#66;	//  scala/actors/scheduler/SchedulerService.terminating_$eq:(Z)V
const #68 = Asciz	run;
const #69 = NameAndType	#54:#21;//  liftedTree1$1:()V
const #70 = Method	#41.#69;	//  scala/actors/scheduler/SchedulerService.liftedTree1$1:()V
const #71 = Asciz	()Z;
const #72 = NameAndType	#14:#71;//  terminating:()Z
const #73 = Method	#41.#72;	//  scala/actors/scheduler/SchedulerService.terminating:()Z
const #74 = Asciz	scala/actors/scheduler/QuitException;
const #75 = class	#74;	//  scala/actors/scheduler/QuitException
const #76 = Method	#75.#22;	//  scala/actors/scheduler/QuitException."<init>":()V
const #77 = Asciz	scala/actors/ActorGC;
const #78 = class	#77;	//  scala/actors/ActorGC
const #79 = Asciz	gc;
const #80 = NameAndType	#79:#21;//  gc:()V
const #81 = InterfaceMethod	#78.#80;	//  scala/actors/ActorGC.gc:()V
const #82 = Asciz	allActorsTerminated;
const #83 = NameAndType	#82:#71;//  allActorsTerminated:()Z
const #84 = InterfaceMethod	#78.#83;	//  scala/actors/ActorGC.allActorsTerminated:()Z
const #85 = Asciz	scala/actors/Debug$;
const #86 = class	#85;	//  scala/actors/Debug$
const #87 = Asciz	MODULE$;
const #88 = Asciz	Lscala/actors/Debug$;;
const #89 = NameAndType	#87:#88;//  MODULE$:Lscala/actors/Debug$;
const #90 = Field	#86.#89;	//  scala/actors/Debug$.MODULE$:Lscala/actors/Debug$;
const #91 = Asciz	scala/runtime/StringAdd;
const #92 = class	#91;	//  scala/runtime/StringAdd
const #93 = Asciz	(Ljava/lang/Object;)V;
const #94 = NameAndType	#15:#93;//  "<init>":(Ljava/lang/Object;)V
const #95 = Method	#92.#94;	//  scala/runtime/StringAdd."<init>":(Ljava/lang/Object;)V
const #96 = Asciz	: initiating shutdown...;
const #97 = String	#96;	//  : initiating shutdown...
const #98 = Asciz	$plus;
const #99 = Asciz	(Ljava/lang/String;)Ljava/lang/String;;
const #100 = NameAndType	#98:#99;//  $plus:(Ljava/lang/String;)Ljava/lang/String;
const #101 = Method	#92.#100;	//  scala/runtime/StringAdd.$plus:(Ljava/lang/String;)Ljava/lang/String;
const #102 = Asciz	info;
const #103 = Asciz	(Ljava/lang/String;)V;
const #104 = NameAndType	#102:#103;//  info:(Ljava/lang/String;)V
const #105 = Method	#86.#104;	//  scala/actors/Debug$.info:(Ljava/lang/String;)V
const #106 = Asciz	onShutdown;
const #107 = NameAndType	#106:#21;//  onShutdown:()V
const #108 = Method	#41.#107;	//  scala/actors/scheduler/SchedulerService.onShutdown:()V
const #109 = NameAndType	#15:#16;//  "<init>":(Z)V
const #110 = Method	#41.#109;	//  scala/actors/scheduler/SchedulerService."<init>":(Z)V
const #111 = Asciz	printActorDump;
const #112 = NameAndType	#111:#27;//  printActorDump:(Lscala/actors/IScheduler;)V
const #113 = Method	#25.#112;	//  scala/actors/IScheduler$class.printActorDump:(Lscala/actors/IScheduler;)V
const #114 = Asciz	Deprecated;
const #115 = Asciz	onLockup;
const #116 = Asciz	(ILscala/Function0;)V;
const #117 = Asciz	(Lscala/actors/IScheduler;ILscala/Function0;)V;
const #118 = NameAndType	#115:#117;//  onLockup:(Lscala/actors/IScheduler;ILscala/Function0;)V
const #119 = Method	#25.#118;	//  scala/actors/IScheduler$class.onLockup:(Lscala/actors/IScheduler;ILscala/Function0;)V
const #120 = Asciz	millis;
const #121 = Asciz	handler;
const #122 = Asciz	Lscala/Function0;;
const #123 = Asciz	(Lscala/Function0;)V;
const #124 = Asciz	(Lscala/actors/IScheduler;Lscala/Function0;)V;
const #125 = NameAndType	#115:#124;//  onLockup:(Lscala/actors/IScheduler;Lscala/Function0;)V
const #126 = Method	#25.#125;	//  scala/actors/IScheduler$class.onLockup:(Lscala/actors/IScheduler;Lscala/Function0;)V
const #127 = Asciz	tick;
const #128 = Asciz	(Lscala/actors/Actor;)V;
const #129 = Asciz	(Lscala/actors/IScheduler;Lscala/actors/Actor;)V;
const #130 = NameAndType	#127:#129;//  tick:(Lscala/actors/IScheduler;Lscala/actors/Actor;)V
const #131 = Method	#25.#130;	//  scala/actors/IScheduler$class.tick:(Lscala/actors/IScheduler;Lscala/actors/Actor;)V
const #132 = Asciz	a;
const #133 = Asciz	Lscala/actors/Actor;;
const #134 = Asciz	executeFromActor;
const #135 = Asciz	(Ljava/lang/Runnable;)V;
const #136 = Asciz	(Lscala/actors/IScheduler;Ljava/lang/Runnable;)V;
const #137 = NameAndType	#134:#136;//  executeFromActor:(Lscala/actors/IScheduler;Ljava/lang/Runnable;)V
const #138 = Method	#25.#137;	//  scala/actors/IScheduler$class.executeFromActor:(Lscala/actors/IScheduler;Ljava/lang/Runnable;)V
const #139 = Asciz	task;
const #140 = Asciz	Ljava/lang/Runnable;;
const #141 = Asciz	allTerminated;
const #142 = Asciz	(Lscala/actors/scheduler/TerminationMonitor;)Z;
const #143 = NameAndType	#141:#142;//  allTerminated:(Lscala/actors/scheduler/TerminationMonitor;)Z
const #144 = Method	#31.#143;	//  scala/actors/scheduler/TerminationMonitor$class.allTerminated:(Lscala/actors/scheduler/TerminationMonitor;)Z
const #145 = Asciz	scala$actors$scheduler$TerminationMonitor$_setter_$terminationHandlers_$eq;
const #146 = Asciz	(Lscala/collection/mutable/HashMap;)V;
const #147 = NameAndType	#5:#6;//  terminationHandlers:Lscala/collection/mutable/HashMap;
const #148 = Field	#41.#147;	//  scala/actors/scheduler/SchedulerService.terminationHandlers:Lscala/collection/mutable/HashMap;
const #149 = Asciz	scala$actors$scheduler$TerminationMonitor$$started_$eq;
const #150 = NameAndType	#3:#4;//  scala$actors$scheduler$TerminationMonitor$$started:Z
const #151 = Field	#41.#150;	//  scala/actors/scheduler/SchedulerService.scala$actors$scheduler$TerminationMonitor$$started:Z
const #152 = Asciz	()Lscala/collection/mutable/HashMap;;
const #153 = Asciz	activeActors_$eq;
const #154 = Asciz	(I)V;
const #155 = NameAndType	#7:#8;//  activeActors:I
const #156 = Field	#41.#155;	//  scala/actors/scheduler/SchedulerService.activeActors:I
const #157 = Asciz	setPendingCount;
const #158 = Asciz	(Lscala/actors/ActorGC;I)V;
const #159 = NameAndType	#157:#158;//  setPendingCount:(Lscala/actors/ActorGC;I)V
const #160 = Method	#36.#159;	//  scala/actors/ActorGC$class.setPendingCount:(Lscala/actors/ActorGC;I)V
const #161 = Asciz	cnt;
const #162 = Asciz	getPendingCount;
const #163 = Asciz	(Lscala/actors/ActorGC;)I;
const #164 = NameAndType	#162:#163;//  getPendingCount:(Lscala/actors/ActorGC;)I
const #165 = Method	#36.#164;	//  scala/actors/ActorGC$class.getPendingCount:(Lscala/actors/ActorGC;)I
const #166 = Asciz	terminated;
const #167 = Asciz	(Lscala/actors/Reactor;)V;
const #168 = Asciz	(Lscala/actors/ActorGC;Lscala/actors/Reactor;)V;
const #169 = NameAndType	#166:#168;//  terminated:(Lscala/actors/ActorGC;Lscala/actors/Reactor;)V
const #170 = Method	#36.#169;	//  scala/actors/ActorGC$class.terminated:(Lscala/actors/ActorGC;Lscala/actors/Reactor;)V
const #171 = Asciz	Lscala/actors/Reactor;;
const #172 = Asciz	onTerminate;
const #173 = Asciz	(Lscala/actors/Reactor;Lscala/Function0;)V;
const #174 = Asciz	(Lscala/actors/ActorGC;Lscala/actors/Reactor;Lscala/Function0;)V;
const #175 = NameAndType	#172:#174;//  onTerminate:(Lscala/actors/ActorGC;Lscala/actors/Reactor;Lscala/Function0;)V
const #176 = Method	#36.#175;	//  scala/actors/ActorGC$class.onTerminate:(Lscala/actors/ActorGC;Lscala/actors/Reactor;Lscala/Function0;)V
const #177 = Asciz	f;
const #178 = Asciz	(Lscala/actors/ActorGC;)Z;
const #179 = NameAndType	#82:#178;//  allActorsTerminated:(Lscala/actors/ActorGC;)Z
const #180 = Method	#36.#179;	//  scala/actors/ActorGC$class.allActorsTerminated:(Lscala/actors/ActorGC;)Z
const #181 = Asciz	status;
const #182 = NameAndType	#181:#37;//  status:(Lscala/actors/ActorGC;)V
const #183 = Method	#36.#182;	//  scala/actors/ActorGC$class.status:(Lscala/actors/ActorGC;)V
const #184 = NameAndType	#79:#37;//  gc:(Lscala/actors/ActorGC;)V
const #185 = Method	#36.#184;	//  scala/actors/ActorGC$class.gc:(Lscala/actors/ActorGC;)V
const #186 = Asciz	newActor;
const #187 = NameAndType	#186:#168;//  newActor:(Lscala/actors/ActorGC;Lscala/actors/Reactor;)V
const #188 = Method	#36.#187;	//  scala/actors/ActorGC$class.newActor:(Lscala/actors/ActorGC;Lscala/actors/Reactor;)V
const #189 = Asciz	scala$actors$ActorGC$_setter_$scala$actors$ActorGC$$refSet_$eq;
const #190 = Asciz	(Lscala/collection/mutable/HashSet;)V;
const #191 = NameAndType	#9:#10;//  scala$actors$ActorGC$$refSet:Lscala/collection/mutable/HashSet;
const #192 = Field	#41.#191;	//  scala/actors/scheduler/SchedulerService.scala$actors$ActorGC$$refSet:Lscala/collection/mutable/HashSet;
const #193 = Asciz	scala$actors$ActorGC$_setter_$scala$actors$ActorGC$$refQ_$eq;
const #194 = Asciz	(Ljava/lang/ref/ReferenceQueue;)V;
const #195 = NameAndType	#11:#12;//  scala$actors$ActorGC$$refQ:Ljava/lang/ref/ReferenceQueue;
const #196 = Field	#41.#195;	//  scala/actors/scheduler/SchedulerService.scala$actors$ActorGC$$refQ:Ljava/lang/ref/ReferenceQueue;
const #197 = Asciz	scala$actors$ActorGC$$super$terminated;
const #198 = Asciz	(Lscala/actors/scheduler/TerminationMonitor;Lscala/actors/Reactor;)V;
const #199 = NameAndType	#166:#198;//  terminated:(Lscala/actors/scheduler/TerminationMonitor;Lscala/actors/Reactor;)V
const #200 = Method	#31.#199;	//  scala/actors/scheduler/TerminationMonitor$class.terminated:(Lscala/actors/scheduler/TerminationMonitor;Lscala/actors/Reactor;)V
const #201 = Asciz	()Lscala/collection/mutable/HashSet;;
const #202 = Asciz	()Ljava/lang/ref/ReferenceQueue;;
const #203 = Asciz	ScalaSig;
const #204 = Asciz	scala/actors/IScheduler;
const #205 = class	#204;	//  scala/actors/IScheduler
const #206 = Asciz	scala/ScalaObject;
const #207 = class	#206;	//  scala/ScalaObject

{
public scala.actors.scheduler.SchedulerService(boolean);
  Code:
   Stack=2, Locals=2, Args_size=2
   0:	aload_0
   1:	invokespecial	#23; //Method java/lang/Thread."<init>":()V
   4:	aload_0
   5:	invokestatic	#29; //Method scala/actors/IScheduler$class.$init$:(Lscala/actors/IScheduler;)V
   8:	aload_0
   9:	invokestatic	#34; //Method scala/actors/scheduler/TerminationMonitor$class.$init$:(Lscala/actors/scheduler/TerminationMonitor;)V
   12:	aload_0
   13:	invokestatic	#39; //Method scala/actors/ActorGC$class.$init$:(Lscala/actors/ActorGC;)V
   16:	aload_0
   17:	iload_1
   18:	invokevirtual	#44; //Method setDaemon:(Z)V
   21:	aload_0
   22:	iconst_0
   23:	putfield	#46; //Field terminating:Z
   26:	aload_0
   27:	ldc	#47; //int 100
   29:	putfield	#49; //Field CHECK_FREQ:I
   32:	return
  LineNumberTable: 
   line 26: 0
   line 28: 16
   line 33: 21
   line 35: 26

  LocalVariableTable: 
   Start  Length  Slot  Name   Signature
   0      33      0    this       Lscala/actors/scheduler/SchedulerService;
   0      33      1    daemon       Z


public void shutdown();
  Code:
   Stack=2, Locals=1, Args_size=1
   0:	aload_0
   1:	dup
   2:	pop
   3:	monitorenter
   4:	aload_0
   5:	iconst_1
   6:	invokespecial	#67; //Method terminating_$eq:(Z)V
   9:	aload_0
   10:	monitorexit
   11:	return
   12:	aload_0
   13:	monitorexit
   14:	athrow
  Exception table:
   from   to  target type
     4    11    12   any
  LineNumberTable: 
   line 68: 0
   line 69: 4
   line 68: 10


public void run();
  Code:
   Stack=4, Locals=1, Args_size=1
   0:	aload_0
   1:	dup
   2:	pop
   3:	monitorenter
   4:	aload_0
   5:	invokespecial	#70; //Method liftedTree1$1:()V
   8:	aload_0
   9:	invokespecial	#73; //Method terminating:()Z
   12:	ifeq	23
   15:	new	#75; //class scala/actors/scheduler/QuitException
   18:	dup
   19:	invokespecial	#76; //Method scala/actors/scheduler/QuitException."<init>":()V
   22:	athrow
   23:	aload_0
   24:	invokeinterface	#81,  1; //InterfaceMethod scala/actors/ActorGC.gc:()V
   29:	aload_0
   30:	invokeinterface	#84,  1; //InterfaceMethod scala/actors/ActorGC.allActorsTerminated:()Z
   35:	ifeq	46
   38:	new	#75; //class scala/actors/scheduler/QuitException
   41:	dup
   42:	invokespecial	#76; //Method scala/actors/scheduler/QuitException."<init>":()V
   45:	athrow
   46:	aload_0
   47:	monitorexit
   48:	goto	0
   51:	aload_0
   52:	monitorexit
   53:	athrow
   54:	pop
   55:	getstatic	#90; //Field scala/actors/Debug$.MODULE$:Lscala/actors/Debug$;
   58:	new	#92; //class scala/runtime/StringAdd
   61:	dup
   62:	aload_0
   63:	invokespecial	#95; //Method scala/runtime/StringAdd."<init>":(Ljava/lang/Object;)V
   66:	ldc	#97; //String : initiating shutdown...
   68:	invokevirtual	#101; //Method scala/runtime/StringAdd.$plus:(Ljava/lang/String;)Ljava/lang/String;
   71:	invokevirtual	#105; //Method scala/actors/Debug$.info:(Ljava/lang/String;)V
   74:	aload_0
   75:	invokevirtual	#108; //Method onShutdown:()V
   78:	return
  Exception table:
   from   to  target type
     4    51    51   any
     0    54    54   Class scala/actors/scheduler/QuitException

  LineNumberTable: 
   line 42: 0
   line 43: 4
   line 48: 8
   line 49: 15
   line 51: 23
   line 53: 29
   line 54: 38
   line 42: 47
   line 59: 55
   line 61: 74
   line 40: 78


public abstract void onShutdown();

public int CHECK_FREQ();
  Code:
   Stack=1, Locals=1, Args_size=1
   0:	aload_0
   1:	getfield	#49; //Field CHECK_FREQ:I
   4:	ireturn
  LineNumberTable: 
   line 35: 0


public scala.actors.scheduler.SchedulerService();
  Code:
   Stack=2, Locals=1, Args_size=1
   0:	aload_0
   1:	iconst_0
   2:	invokespecial	#110; //Method "<init>":(Z)V
   5:	return
  LineNumberTable: 
   line 31: 0


public void printActorDump();
  Code:
   Stack=1, Locals=1, Args_size=1
   0:	aload_0
   1:	invokestatic	#113; //Method scala/actors/IScheduler$class.printActorDump:(Lscala/actors/IScheduler;)V
   4:	return
  LineNumberTable: 
   line 26: 0

  Deprecated: true

public void onLockup(int, scala.Function0);
  Code:
   Stack=3, Locals=3, Args_size=3
   0:	aload_0
   1:	iload_1
   2:	aload_2
   3:	invokestatic	#119; //Method scala/actors/IScheduler$class.onLockup:(Lscala/actors/IScheduler;ILscala/Function0;)V
   6:	return
  LineNumberTable: 
   line 26: 0

  LocalVariableTable: 
   Start  Length  Slot  Name   Signature
   0      7      0    this       Lscala/actors/scheduler/SchedulerService;
   0      7      1    millis       I
   0      7      2    handler       Lscala/Function0;

  Deprecated: true

public void onLockup(scala.Function0);
  Code:
   Stack=2, Locals=2, Args_size=2
   0:	aload_0
   1:	aload_1
   2:	invokestatic	#126; //Method scala/actors/IScheduler$class.onLockup:(Lscala/actors/IScheduler;Lscala/Function0;)V
   5:	return
  LineNumberTable: 
   line 26: 0

  LocalVariableTable: 
   Start  Length  Slot  Name   Signature
   0      6      0    this       Lscala/actors/scheduler/SchedulerService;
   0      6      1    handler       Lscala/Function0;

  Deprecated: true

public void tick(scala.actors.Actor);
  Code:
   Stack=2, Locals=2, Args_size=2
   0:	aload_0
   1:	aload_1
   2:	invokestatic	#131; //Method scala/actors/IScheduler$class.tick:(Lscala/actors/IScheduler;Lscala/actors/Actor;)V
   5:	return
  LineNumberTable: 
   line 26: 0

  LocalVariableTable: 
   Start  Length  Slot  Name   Signature
   0      6      0    this       Lscala/actors/scheduler/SchedulerService;
   0      6      1    a       Lscala/actors/Actor;

  Deprecated: true

public void executeFromActor(java.lang.Runnable);
  Code:
   Stack=2, Locals=2, Args_size=2
   0:	aload_0
   1:	aload_1
   2:	invokestatic	#138; //Method scala/actors/IScheduler$class.executeFromActor:(Lscala/actors/IScheduler;Ljava/lang/Runnable;)V
   5:	return
  LineNumberTable: 
   line 26: 0

  LocalVariableTable: 
   Start  Length  Slot  Name   Signature
   0      6      0    this       Lscala/actors/scheduler/SchedulerService;
   0      6      1    task       Ljava/lang/Runnable;


public boolean allTerminated();
  Code:
   Stack=1, Locals=1, Args_size=1
   0:	aload_0
   1:	invokestatic	#144; //Method scala/actors/scheduler/TerminationMonitor$class.allTerminated:(Lscala/actors/scheduler/TerminationMonitor;)Z
   4:	ireturn
  LineNumberTable: 
   line 26: 0

  Deprecated: true

public void scala$actors$scheduler$TerminationMonitor$_setter_$terminationHandlers_$eq(scala.collection.mutable.HashMap);
  Code:
   Stack=2, Locals=2, Args_size=2
   0:	aload_0
   1:	aload_1
   2:	putfield	#148; //Field terminationHandlers:Lscala/collection/mutable/HashMap;
   5:	return
  LineNumberTable: 
   line 26: 0


public final void scala$actors$scheduler$TerminationMonitor$$started_$eq(boolean);
  Code:
   Stack=2, Locals=2, Args_size=2
   0:	aload_0
   1:	iload_1
   2:	putfield	#151; //Field scala$actors$scheduler$TerminationMonitor$$started:Z
   5:	return
  LineNumberTable: 
   line 26: 0


public final boolean scala$actors$scheduler$TerminationMonitor$$started();
  Code:
   Stack=1, Locals=1, Args_size=1
   0:	aload_0
   1:	getfield	#151; //Field scala$actors$scheduler$TerminationMonitor$$started:Z
   4:	ireturn
  LineNumberTable: 
   line 26: 0


public scala.collection.mutable.HashMap terminationHandlers();
  Code:
   Stack=1, Locals=1, Args_size=1
   0:	aload_0
   1:	getfield	#148; //Field terminationHandlers:Lscala/collection/mutable/HashMap;
   4:	areturn
  LineNumberTable: 
   line 26: 0


public void activeActors_$eq(int);
  Code:
   Stack=2, Locals=2, Args_size=2
   0:	aload_0
   1:	iload_1
   2:	putfield	#156; //Field activeActors:I
   5:	return
  LineNumberTable: 
   line 26: 0


public int activeActors();
  Code:
   Stack=1, Locals=1, Args_size=1
   0:	aload_0
   1:	getfield	#156; //Field activeActors:I
   4:	ireturn
  LineNumberTable: 
   line 26: 0


public void setPendingCount(int);
  Code:
   Stack=2, Locals=2, Args_size=2
   0:	aload_0
   1:	iload_1
   2:	invokestatic	#160; //Method scala/actors/ActorGC$class.setPendingCount:(Lscala/actors/ActorGC;I)V
   5:	return
  LineNumberTable: 
   line 26: 0

  LocalVariableTable: 
   Start  Length  Slot  Name   Signature
   0      6      0    this       Lscala/actors/scheduler/SchedulerService;
   0      6      1    cnt       I


public int getPendingCount();
  Code:
   Stack=1, Locals=1, Args_size=1
   0:	aload_0
   1:	invokestatic	#165; //Method scala/actors/ActorGC$class.getPendingCount:(Lscala/actors/ActorGC;)I
   4:	ireturn
  LineNumberTable: 
   line 26: 0


public void terminated(scala.actors.Reactor);
  Code:
   Stack=2, Locals=2, Args_size=2
   0:	aload_0
   1:	aload_1
   2:	invokestatic	#170; //Method scala/actors/ActorGC$class.terminated:(Lscala/actors/ActorGC;Lscala/actors/Reactor;)V
   5:	return
  LineNumberTable: 
   line 26: 0

  LocalVariableTable: 
   Start  Length  Slot  Name   Signature
   0      6      0    this       Lscala/actors/scheduler/SchedulerService;
   0      6      1    a       Lscala/actors/Reactor;


public void onTerminate(scala.actors.Reactor, scala.Function0);
  Code:
   Stack=3, Locals=3, Args_size=3
   0:	aload_0
   1:	aload_1
   2:	aload_2
   3:	invokestatic	#176; //Method scala/actors/ActorGC$class.onTerminate:(Lscala/actors/ActorGC;Lscala/actors/Reactor;Lscala/Function0;)V
   6:	return
  LineNumberTable: 
   line 26: 0

  LocalVariableTable: 
   Start  Length  Slot  Name   Signature
   0      7      0    this       Lscala/actors/scheduler/SchedulerService;
   0      7      1    a       Lscala/actors/Reactor;
   0      7      2    f       Lscala/Function0;


public boolean allActorsTerminated();
  Code:
   Stack=1, Locals=1, Args_size=1
   0:	aload_0
   1:	invokestatic	#180; //Method scala/actors/ActorGC$class.allActorsTerminated:(Lscala/actors/ActorGC;)Z
   4:	ireturn
  LineNumberTable: 
   line 26: 0


public void status();
  Code:
   Stack=1, Locals=1, Args_size=1
   0:	aload_0
   1:	invokestatic	#183; //Method scala/actors/ActorGC$class.status:(Lscala/actors/ActorGC;)V
   4:	return
  LineNumberTable: 
   line 26: 0


public void gc();
  Code:
   Stack=1, Locals=1, Args_size=1
   0:	aload_0
   1:	invokestatic	#185; //Method scala/actors/ActorGC$class.gc:(Lscala/actors/ActorGC;)V
   4:	return
  LineNumberTable: 
   line 26: 0


public void newActor(scala.actors.Reactor);
  Code:
   Stack=2, Locals=2, Args_size=2
   0:	aload_0
   1:	aload_1
   2:	invokestatic	#188; //Method scala/actors/ActorGC$class.newActor:(Lscala/actors/ActorGC;Lscala/actors/Reactor;)V
   5:	return
  LineNumberTable: 
   line 26: 0

  LocalVariableTable: 
   Start  Length  Slot  Name   Signature
   0      6      0    this       Lscala/actors/scheduler/SchedulerService;
   0      6      1    a       Lscala/actors/Reactor;


public void scala$actors$ActorGC$_setter_$scala$actors$ActorGC$$refSet_$eq(scala.collection.mutable.HashSet);
  Code:
   Stack=2, Locals=2, Args_size=2
   0:	aload_0
   1:	aload_1
   2:	putfield	#192; //Field scala$actors$ActorGC$$refSet:Lscala/collection/mutable/HashSet;
   5:	return
  LineNumberTable: 
   line 26: 0


public void scala$actors$ActorGC$_setter_$scala$actors$ActorGC$$refQ_$eq(java.lang.ref.ReferenceQueue);
  Code:
   Stack=2, Locals=2, Args_size=2
   0:	aload_0
   1:	aload_1
   2:	putfield	#196; //Field scala$actors$ActorGC$$refQ:Ljava/lang/ref/ReferenceQueue;
   5:	return
  LineNumberTable: 
   line 26: 0


public final void scala$actors$ActorGC$$super$terminated(scala.actors.Reactor);
  Code:
   Stack=2, Locals=2, Args_size=2
   0:	aload_0
   1:	aload_1
   2:	invokestatic	#200; //Method scala/actors/scheduler/TerminationMonitor$class.terminated:(Lscala/actors/scheduler/TerminationMonitor;Lscala/actors/Reactor;)V
   5:	return
  LineNumberTable: 
   line 26: 0

  LocalVariableTable: 
   Start  Length  Slot  Name   Signature
   0      6      0    this       Lscala/actors/scheduler/SchedulerService;
   0      6      1    a       Lscala/actors/Reactor;


public final scala.collection.mutable.HashSet scala$actors$ActorGC$$refSet();
  Code:
   Stack=1, Locals=1, Args_size=1
   0:	aload_0
   1:	getfield	#192; //Field scala$actors$ActorGC$$refSet:Lscala/collection/mutable/HashSet;
   4:	areturn
  LineNumberTable: 
   line 26: 0


public final java.lang.ref.ReferenceQueue scala$actors$ActorGC$$refQ();
  Code:
   Stack=1, Locals=1, Args_size=1
   0:	aload_0
   1:	getfield	#196; //Field scala$actors$ActorGC$$refQ:Ljava/lang/ref/ReferenceQueue;
   4:	areturn
  LineNumberTable: 
   line 26: 0


}

