Compiled from "SimpleExecutorScheduler.scala"
public class scala.actors.scheduler.SimpleExecutorScheduler extends scala.actors.scheduler.TerminationService implements scala.actors.scheduler.ExecutorScheduler,scala.ScalaObject
  SourceFile: "SimpleExecutorScheduler.scala"
  ScalaSig: length = 0x1DD
   05 00 40 06 08 01 02 FFFFFF84 FFFFFF80 FFFFFF80 FFFFFF80 00 09 02 17 53
   69 6D 70 6C 65 45 78 65 63 75 74 6F 72 53 63 68
   65 64 75 6C 65 72 0A 02 03 04 01 09 73 63 68 65
   64 75 6C 65 72 0A 02 05 06 01 06 61 63 74 6F 72
   73 0A 01 07 01 05 73 63 61 6C 61 03 00 13 04 00
   0A 0E 11 10 02 0B 0C 0D 01 02 09 02 0D 02 02 12
   54 65 72 6D 69 6E 61 74 69 6F 6E 53 65 72 76 69
   63 65 10 02 0B 0F 09 02 10 02 02 11 45 78 65 63
   75 74 6F 72 53 63 68 65 64 75 6C 65 72 10 02 12
   13 0D 01 06 09 02 14 06 02 0B 53 63 61 6C 61 4F
   62 6A 65 63 74 08 08 16 00 FFFFFF82 FFFFFFC0 FFFFFF80 FFFFFF84 08 17 01
   08 65 78 65 63 75 74 6F 72 15 01 18 10 02 19 20
   0D 01 1A 0A 02 1B 1C 01 0A 63 6F 6E 63 75 72 72
   65 6E 74 0A 02 1D 1E 01 04 75 74 69 6C 0A 01 1F
   01 04 6A 61 76 61 09 02 21 1A 02 0F 45 78 65 63
   75 74 6F 72 53 65 72 76 69 63 65 08 08 23 00 FFFFFF82
   FFFFFFC0 FFFFFF80 FFFFFF84 08 24 01 0C 65 78 65 63 75 74 6F 72 5F
   24 65 71 14 02 25 28 10 02 12 26 09 02 27 06 02
   04 55 6E 69 74 08 07 29 22 FFFFFF81 FFFFFF80 FFFFFFC0 00 18 01 03
   78 24 31 08 08 2B 00 FFFFFF82 FFFFFF80 FFFFFFA0 FFFFFFA0 04 18 01 09 65
   78 65 63 75 74 6F 72 20 08 08 2D 00 FFFFFF82 FFFFFFC0 FFFFFF80 FFFFFF84
   08 2E 01 09 74 65 72 6D 69 6E 61 74 65 15 01 2F
   10 02 12 30 09 02 31 06 02 07 42 6F 6F 6C 65 61
   6E 08 08 33 00 FFFFFF82 FFFFFFC0 FFFFFF80 FFFFFF84 08 34 01 0D 74 65 72
   6D 69 6E 61 74 65 5F 24 65 71 14 02 25 35 08 07
   29 32 FFFFFF81 FFFFFF80 FFFFFFC0 00 2F 08 08 37 00 FFFFFF82 FFFFFF80 FFFFFFA0 FFFFFFA0 04
   2F 01 0A 74 65 72 6D 69 6E 61 74 65 20 08 05 39
   00 FFFFFF84 00 3A 01 06 3C 69 6E 69 74 3E 14 03 3B 3C
   3D 10 02 0B 00 08 05 16 38 FFFFFFC0 00 18 08 05 2D 38
   FFFFFFC0 00 2F 08 05 39 00 FFFFFF84 00 3F 14 01 3B 
  minor version: 0
  major version: 49
  Constant pool:
Asciz	SourceFile;
Asciz	SimpleExecutorScheduler.scala;
Asciz	terminate;
Asciz	Z;
Asciz	executor;
Asciz	Ljava/util/concurrent/ExecutorService;;
Asciz	<init>;
Asciz	(Ljava/util/concurrent/ExecutorService;Z)V;
Asciz	Code;
Asciz	LineNumberTable;
Asciz	scala/actors/scheduler/SimpleExecutorScheduler;
class	scala/actors/scheduler/SimpleExecutorScheduler
NameAndType	executor:Ljava/util/concurrent/ExecutorService;
Field	scala/actors/scheduler/SimpleExecutorScheduler.executor:Ljava/util/concurrent/ExecutorService;
NameAndType	terminate:Z
Field	scala/actors/scheduler/SimpleExecutorScheduler.terminate:Z
Asciz	scala/actors/scheduler/TerminationService;
class	scala/actors/scheduler/TerminationService
Asciz	(Z)V;
NameAndType	"<init>":(Z)V
Method	scala/actors/scheduler/TerminationService."<init>":(Z)V
Asciz	scala/concurrent/TaskRunner$class;
class	scala/concurrent/TaskRunner$class
Asciz	$init$;
Asciz	(Lscala/concurrent/TaskRunner;)V;
NameAndType	$init$:(Lscala/concurrent/TaskRunner;)V
Method	scala/concurrent/TaskRunner$class.$init$:(Lscala/concurrent/TaskRunner;)V
Asciz	scala/concurrent/ThreadPoolRunner$class;
class	scala/concurrent/ThreadPoolRunner$class
Asciz	(Lscala/concurrent/ThreadPoolRunner;)V;
NameAndType	$init$:(Lscala/concurrent/ThreadPoolRunner;)V
Method	scala/concurrent/ThreadPoolRunner$class.$init$:(Lscala/concurrent/ThreadPoolRunner;)V
Asciz	scala/actors/scheduler/ExecutorScheduler$class;
class	scala/actors/scheduler/ExecutorScheduler$class
Asciz	(Lscala/actors/scheduler/ExecutorScheduler;)V;
NameAndType	$init$:(Lscala/actors/scheduler/ExecutorScheduler;)V
Method	scala/actors/scheduler/ExecutorScheduler$class.$init$:(Lscala/actors/scheduler/ExecutorScheduler;)V
Asciz	this;
Asciz	Lscala/actors/scheduler/SimpleExecutorScheduler;;
Asciz	LocalVariableTable;
Asciz	functionAsTask;
Asciz	(Lscala/Function0;)Ljava/lang/Object;;
Asciz	scala/concurrent/ThreadPoolRunner;
class	scala/concurrent/ThreadPoolRunner
Asciz	(Lscala/Function0;)Ljava/util/concurrent/Callable;;
NameAndType	functionAsTask:(Lscala/Function0;)Ljava/util/concurrent/Callable;
InterfaceMethod	scala/concurrent/ThreadPoolRunner.functionAsTask:(Lscala/Function0;)Ljava/util/concurrent/Callable;
Asciz	fun;
Asciz	Lscala/Function0;;
Asciz	futureAsFunction;
Asciz	(Ljava/lang/Object;)Lscala/Function0;;
Asciz	java/util/concurrent/Future;
class	java/util/concurrent/Future
Asciz	(Ljava/util/concurrent/Future;)Lscala/Function0;;
NameAndType	futureAsFunction:(Ljava/util/concurrent/Future;)Lscala/Function0;
InterfaceMethod	scala/concurrent/ThreadPoolRunner.futureAsFunction:(Ljava/util/concurrent/Future;)Lscala/Function0;
Asciz	x;
Asciz	Ljava/lang/Object;;
Asciz	submit;
Asciz	(Ljava/lang/Object;)Ljava/lang/Object;;
Asciz	java/util/concurrent/Callable;
class	java/util/concurrent/Callable
Asciz	(Ljava/util/concurrent/Callable;)Ljava/util/concurrent/Future;;
NameAndType	submit:(Ljava/util/concurrent/Callable;)Ljava/util/concurrent/Future;
InterfaceMethod	scala/concurrent/ThreadPoolRunner.submit:(Ljava/util/concurrent/Callable;)Ljava/util/concurrent/Future;
Asciz	task;
Asciz	execute;
Asciz	(Ljava/lang/Object;)V;
Asciz	(Ljava/util/concurrent/Callable;)V;
NameAndType	execute:(Ljava/util/concurrent/Callable;)V
InterfaceMethod	scala/concurrent/ThreadPoolRunner.execute:(Ljava/util/concurrent/Callable;)V
Asciz	()V;
NameAndType	"<init>":(Ljava/util/concurrent/ExecutorService;Z)V
Method	scala/actors/scheduler/SimpleExecutorScheduler."<init>":(Ljava/util/concurrent/ExecutorService;Z)V
Asciz	terminate_$eq;
Asciz	()Z;
Asciz	executor_$eq;
Asciz	(Ljava/util/concurrent/ExecutorService;)V;
Asciz	()Ljava/util/concurrent/ExecutorService;;
Asciz	tryCatch;
Asciz	(Lscala/Function0;)Lscala/Either;;
Asciz	(Lscala/concurrent/TaskRunner;Lscala/Function0;)Lscala/Either;;
NameAndType	tryCatch:(Lscala/concurrent/TaskRunner;Lscala/Function0;)Lscala/Either;
Method	scala/concurrent/TaskRunner$class.tryCatch:(Lscala/concurrent/TaskRunner;Lscala/Function0;)Lscala/Either;
Asciz	body;
Asciz	managedBlock;
Asciz	(Lscala/concurrent/ManagedBlocker;)V;
Asciz	(Lscala/concurrent/ThreadPoolRunner;Lscala/concurrent/ManagedBlocker;)V;
NameAndType	managedBlock:(Lscala/concurrent/ThreadPoolRunner;Lscala/concurrent/ManagedBlocker;)V
Method	scala/concurrent/ThreadPoolRunner$class.managedBlock:(Lscala/concurrent/ThreadPoolRunner;Lscala/concurrent/ManagedBlocker;)V
Asciz	blocker;
Asciz	Lscala/concurrent/ManagedBlocker;;
Asciz	(Lscala/concurrent/ThreadPoolRunner;Ljava/util/concurrent/Callable;)V;
NameAndType	execute:(Lscala/concurrent/ThreadPoolRunner;Ljava/util/concurrent/Callable;)V
Method	scala/concurrent/ThreadPoolRunner$class.execute:(Lscala/concurrent/ThreadPoolRunner;Ljava/util/concurrent/Callable;)V
Asciz	Ljava/util/concurrent/Callable;;
Asciz	(Lscala/concurrent/ThreadPoolRunner;Ljava/util/concurrent/Callable;)Ljava/util/concurrent/Future;;
NameAndType	submit:(Lscala/concurrent/ThreadPoolRunner;Ljava/util/concurrent/Callable;)Ljava/util/concurrent/Future;
Method	scala/concurrent/ThreadPoolRunner$class.submit:(Lscala/concurrent/ThreadPoolRunner;Ljava/util/concurrent/Callable;)Ljava/util/concurrent/Future;
Asciz	(Lscala/concurrent/ThreadPoolRunner;Ljava/util/concurrent/Future;)Lscala/Function0;;
NameAndType	futureAsFunction:(Lscala/concurrent/ThreadPoolRunner;Ljava/util/concurrent/Future;)Lscala/Function0;
Method	scala/concurrent/ThreadPoolRunner$class.futureAsFunction:(Lscala/concurrent/ThreadPoolRunner;Ljava/util/concurrent/Future;)Lscala/Function0;
Asciz	Ljava/util/concurrent/Future;;
Asciz	(Lscala/concurrent/ThreadPoolRunner;Lscala/Function0;)Ljava/util/concurrent/Callable;;
NameAndType	functionAsTask:(Lscala/concurrent/ThreadPoolRunner;Lscala/Function0;)Ljava/util/concurrent/Callable;
Method	scala/concurrent/ThreadPoolRunner$class.functionAsTask:(Lscala/concurrent/ThreadPoolRunner;Lscala/Function0;)Ljava/util/concurrent/Callable;
Asciz	isActive;
Asciz	(Lscala/actors/scheduler/ExecutorScheduler;)Z;
NameAndType	isActive:(Lscala/actors/scheduler/ExecutorScheduler;)Z
Method	scala/actors/scheduler/ExecutorScheduler$class.isActive:(Lscala/actors/scheduler/ExecutorScheduler;)Z
Asciz	onShutdown;
NameAndType	onShutdown:(Lscala/actors/scheduler/ExecutorScheduler;)V
Method	scala/actors/scheduler/ExecutorScheduler$class.onShutdown:(Lscala/actors/scheduler/ExecutorScheduler;)V
Asciz	(Lscala/Function0;)V;
Asciz	(Lscala/actors/scheduler/ExecutorScheduler;Lscala/Function0;)V;
NameAndType	execute:(Lscala/actors/scheduler/ExecutorScheduler;Lscala/Function0;)V
Method	scala/actors/scheduler/ExecutorScheduler$class.execute:(Lscala/actors/scheduler/ExecutorScheduler;Lscala/Function0;)V
Asciz	(Ljava/lang/Runnable;)V;
Asciz	(Lscala/actors/scheduler/ExecutorScheduler;Ljava/lang/Runnable;)V;
NameAndType	execute:(Lscala/actors/scheduler/ExecutorScheduler;Ljava/lang/Runnable;)V
Method	scala/actors/scheduler/ExecutorScheduler$class.execute:(Lscala/actors/scheduler/ExecutorScheduler;Ljava/lang/Runnable;)V
Asciz	Ljava/lang/Runnable;;
Asciz	ScalaSig;
Asciz	scala/actors/scheduler/ExecutorScheduler;
class	scala/actors/scheduler/ExecutorScheduler
Asciz	scala/ScalaObject;
class	scala/ScalaObject

{
private boolean terminate;
  Signature: Z

private java.util.concurrent.ExecutorService executor;
  Signature: Ljava/util/concurrent/ExecutorService;

public scala.actors.scheduler.SimpleExecutorScheduler(java.util.concurrent.ExecutorService, boolean);
  Signature: (Ljava/util/concurrent/ExecutorService;Z)V
  Code:
   Stack=2, Locals=3, Args_size=3
	aload_0
	aload_1
	putfield	Field executor:Ljava/util/concurrent/ExecutorService;
	aload_0
	iload_2
	putfield	Field terminate:Z
	aload_0
	iload_2
	invokespecial	Method scala/actors/scheduler/TerminationService."<init>":(Z)V
	aload_0
	invokestatic	Method scala/concurrent/TaskRunner$class.$init$:(Lscala/concurrent/TaskRunner;)V
	aload_0
	invokestatic	Method scala/concurrent/ThreadPoolRunner$class.$init$:(Lscala/concurrent/ThreadPoolRunner;)V
	aload_0
	invokestatic	Method scala/actors/scheduler/ExecutorScheduler$class.$init$:(Lscala/actors/scheduler/ExecutorScheduler;)V
	return
  Labels:
  LocalVariableTable: 
   Start  Length  Slot  Name   Signature
   0      28      0    this       Lscala/actors/scheduler/SimpleExecutorScheduler;
   0      28      1    executor       Ljava/util/concurrent/ExecutorService;
   0      28      2    terminate       Z


public java.lang.Object functionAsTask(scala.Function0);
  Signature: (Lscala/Function0;)Ljava/lang/Object;
  Code:
   Stack=2, Locals=2, Args_size=2
	aload_0
	aload_1
	invokeinterface	InterfaceMethod scala/concurrent/ThreadPoolRunner.functionAsTask:(Lscala/Function0;)Ljava/util/concurrent/Callable;
	areturn
  Labels:
  LocalVariableTable: 
   Start  Length  Slot  Name   Signature
   0      8      0    this       Lscala/actors/scheduler/SimpleExecutorScheduler;
   0      8      1    fun       Lscala/Function0;


public scala.Function0 futureAsFunction(java.lang.Object);
  Signature: (Ljava/lang/Object;)Lscala/Function0;
  Code:
   Stack=2, Locals=2, Args_size=2
	aload_0
	aload_1
	checkcast	class java/util/concurrent/Future
	invokeinterface	InterfaceMethod scala/concurrent/ThreadPoolRunner.futureAsFunction:(Ljava/util/concurrent/Future;)Lscala/Function0;
	areturn
  Labels:
  LocalVariableTable: 
   Start  Length  Slot  Name   Signature
   0      11      0    this       Lscala/actors/scheduler/SimpleExecutorScheduler;
   0      11      1    x       Ljava/lang/Object;


public java.lang.Object submit(java.lang.Object);
  Signature: (Ljava/lang/Object;)Ljava/lang/Object;
  Code:
   Stack=2, Locals=2, Args_size=2
	aload_0
	aload_1
	checkcast	class java/util/concurrent/Callable
	invokeinterface	InterfaceMethod scala/concurrent/ThreadPoolRunner.submit:(Ljava/util/concurrent/Callable;)Ljava/util/concurrent/Future;
	areturn
  Labels:
  LocalVariableTable: 
   Start  Length  Slot  Name   Signature
   0      11      0    this       Lscala/actors/scheduler/SimpleExecutorScheduler;
   0      11      1    task       Ljava/lang/Object;


public void execute(java.lang.Object);
  Signature: (Ljava/lang/Object;)V
  Code:
   Stack=2, Locals=2, Args_size=2
	aload_0
	aload_1
	checkcast	class java/util/concurrent/Callable
	invokeinterface	InterfaceMethod scala/concurrent/ThreadPoolRunner.execute:(Ljava/util/concurrent/Callable;)V
	return
  Labels:
  LocalVariableTable: 
   Start  Length  Slot  Name   Signature
   0      11      0    this       Lscala/actors/scheduler/SimpleExecutorScheduler;
   0      11      1    task       Ljava/lang/Object;


public scala.actors.scheduler.SimpleExecutorScheduler();
  Signature: ()V
  Code:
   Stack=3, Locals=1, Args_size=1
	aload_0
	aconst_null
	iconst_1
	invokespecial	Method "<init>":(Ljava/util/concurrent/ExecutorService;Z)V
	return
  Labels:

public void terminate_$eq(boolean);
  Signature: (Z)V
  Code:
   Stack=2, Locals=2, Args_size=2
	aload_0
	iload_1
	putfield	Field terminate:Z
	return
  Labels:

public boolean terminate();
  Signature: ()Z
  Code:
   Stack=1, Locals=1, Args_size=1
	aload_0
	getfield	Field terminate:Z
	ireturn
  Labels:

public void executor_$eq(java.util.concurrent.ExecutorService);
  Signature: (Ljava/util/concurrent/ExecutorService;)V
  Code:
   Stack=2, Locals=2, Args_size=2
	aload_0
	aload_1
	putfield	Field executor:Ljava/util/concurrent/ExecutorService;
	return
  Labels:

public java.util.concurrent.ExecutorService executor();
  Signature: ()Ljava/util/concurrent/ExecutorService;
  Code:
   Stack=1, Locals=1, Args_size=1
	aload_0
	getfield	Field executor:Ljava/util/concurrent/ExecutorService;
	areturn
  Labels:

public scala.Either tryCatch(scala.Function0);
  Signature: (Lscala/Function0;)Lscala/Either;
  Code:
   Stack=2, Locals=2, Args_size=2
	aload_0
	aload_1
	invokestatic	Method scala/concurrent/TaskRunner$class.tryCatch:(Lscala/concurrent/TaskRunner;Lscala/Function0;)Lscala/Either;
	areturn
  Labels:
  LocalVariableTable: 
   Start  Length  Slot  Name   Signature
   0      6      0    this       Lscala/actors/scheduler/SimpleExecutorScheduler;
   0      6      1    body       Lscala/Function0;


public void managedBlock(scala.concurrent.ManagedBlocker);
  Signature: (Lscala/concurrent/ManagedBlocker;)V
  Code:
   Stack=2, Locals=2, Args_size=2
	aload_0
	aload_1
	invokestatic	Method scala/concurrent/ThreadPoolRunner$class.managedBlock:(Lscala/concurrent/ThreadPoolRunner;Lscala/concurrent/ManagedBlocker;)V
	return
  Labels:
  LocalVariableTable: 
   Start  Length  Slot  Name   Signature
   0      6      0    this       Lscala/actors/scheduler/SimpleExecutorScheduler;
   0      6      1    blocker       Lscala/concurrent/ManagedBlocker;


public void execute(java.util.concurrent.Callable);
  Signature: (Ljava/util/concurrent/Callable;)V
  Code:
   Stack=2, Locals=2, Args_size=2
	aload_0
	aload_1
	invokestatic	Method scala/concurrent/ThreadPoolRunner$class.execute:(Lscala/concurrent/ThreadPoolRunner;Ljava/util/concurrent/Callable;)V
	return
  Labels:
  LocalVariableTable: 
   Start  Length  Slot  Name   Signature
   0      6      0    this       Lscala/actors/scheduler/SimpleExecutorScheduler;
   0      6      1    task       Ljava/util/concurrent/Callable;


public java.util.concurrent.Future submit(java.util.concurrent.Callable);
  Signature: (Ljava/util/concurrent/Callable;)Ljava/util/concurrent/Future;
  Code:
   Stack=2, Locals=2, Args_size=2
	aload_0
	aload_1
	invokestatic	Method scala/concurrent/ThreadPoolRunner$class.submit:(Lscala/concurrent/ThreadPoolRunner;Ljava/util/concurrent/Callable;)Ljava/util/concurrent/Future;
	areturn
  Labels:
  LocalVariableTable: 
   Start  Length  Slot  Name   Signature
   0      6      0    this       Lscala/actors/scheduler/SimpleExecutorScheduler;
   0      6      1    task       Ljava/util/concurrent/Callable;


public scala.Function0 futureAsFunction(java.util.concurrent.Future);
  Signature: (Ljava/util/concurrent/Future;)Lscala/Function0;
  Code:
   Stack=2, Locals=2, Args_size=2
	aload_0
	aload_1
	invokestatic	Method scala/concurrent/ThreadPoolRunner$class.futureAsFunction:(Lscala/concurrent/ThreadPoolRunner;Ljava/util/concurrent/Future;)Lscala/Function0;
	areturn
  Labels:
  LocalVariableTable: 
   Start  Length  Slot  Name   Signature
   0      6      0    this       Lscala/actors/scheduler/SimpleExecutorScheduler;
   0      6      1    x       Ljava/util/concurrent/Future;


public java.util.concurrent.Callable functionAsTask(scala.Function0);
  Signature: (Lscala/Function0;)Ljava/util/concurrent/Callable;
  Code:
   Stack=2, Locals=2, Args_size=2
	aload_0
	aload_1
	invokestatic	Method scala/concurrent/ThreadPoolRunner$class.functionAsTask:(Lscala/concurrent/ThreadPoolRunner;Lscala/Function0;)Ljava/util/concurrent/Callable;
	areturn
  Labels:
  LocalVariableTable: 
   Start  Length  Slot  Name   Signature
   0      6      0    this       Lscala/actors/scheduler/SimpleExecutorScheduler;
   0      6      1    fun       Lscala/Function0;


public boolean isActive();
  Signature: ()Z
  Code:
   Stack=1, Locals=1, Args_size=1
	aload_0
	invokestatic	Method scala/actors/scheduler/ExecutorScheduler$class.isActive:(Lscala/actors/scheduler/ExecutorScheduler;)Z
	ireturn
  Labels:

public void onShutdown();
  Signature: ()V
  Code:
   Stack=1, Locals=1, Args_size=1
	aload_0
	invokestatic	Method scala/actors/scheduler/ExecutorScheduler$class.onShutdown:(Lscala/actors/scheduler/ExecutorScheduler;)V
	return
  Labels:

public void execute(scala.Function0);
  Signature: (Lscala/Function0;)V
  Code:
   Stack=2, Locals=2, Args_size=2
	aload_0
	aload_1
	invokestatic	Method scala/actors/scheduler/ExecutorScheduler$class.execute:(Lscala/actors/scheduler/ExecutorScheduler;Lscala/Function0;)V
	return
  Labels:
  LocalVariableTable: 
   Start  Length  Slot  Name   Signature
   0      6      0    this       Lscala/actors/scheduler/SimpleExecutorScheduler;
   0      6      1    fun       Lscala/Function0;


public void execute(java.lang.Runnable);
  Signature: (Ljava/lang/Runnable;)V
  Code:
   Stack=2, Locals=2, Args_size=2
	aload_0
	aload_1
	invokestatic	Method scala/actors/scheduler/ExecutorScheduler$class.execute:(Lscala/actors/scheduler/ExecutorScheduler;Ljava/lang/Runnable;)V
	return
  Labels:
  LocalVariableTable: 
   Start  Length  Slot  Name   Signature
   0      6      0    this       Lscala/actors/scheduler/SimpleExecutorScheduler;
   0      6      1    task       Ljava/lang/Runnable;


}

