Compiled from "SingleThreadedScheduler.scala"
public class scala.actors.scheduler.SingleThreadedScheduler extends java.lang.Object implements scala.actors.IScheduler,scala.ScalaObject
  SourceFile: "SingleThreadedScheduler.scala"
  ScalaSig: length = 0x363
   05 00 7E 06 08 01 02 FFFFFF84 FFFFFF80 FFFFFF80 FFFFFF80 00 09 02 17 53
   69 6E 67 6C 65 54 68 72 65 61 64 65 64 53 63 68
   65 64 75 6C 65 72 0A 02 03 04 01 09 73 63 68 65
   64 75 6C 65 72 0A 02 05 06 01 06 61 63 74 6F 72
   73 0A 01 07 01 05 73 63 61 6C 61 03 00 13 04 00
   0A 12 16 10 02 0B 10 0D 01 0C 0A 02 0D 0E 01 04
   6C 61 6E 67 0A 01 0F 01 04 6A 61 76 61 09 02 11
   0C 02 06 4F 62 6A 65 63 74 10 02 13 14 0D 01 04
   09 02 15 04 02 0A 49 53 63 68 65 64 75 6C 65 72
   10 02 17 18 0D 01 06 09 02 19 06 02 0B 53 63 61
   6C 61 4F 62 6A 65 63 74 08 05 1B 00 FFFFFF84 00 1C 01
   06 3C 69 6E 69 74 3E 14 01 1D 10 02 1E 00 0D 01
   02 08 07 20 00 FFFFFFC2 FFFFFF80 FFFFFF84 04 21 01 05 74 61 73 6B
   73 15 01 22 10 03 23 28 2A 0D 01 24 0A 02 25 26
   01 07 6D 75 74 61 62 6C 65 0A 02 27 06 01 0A 63
   6F 6C 6C 65 63 74 69 6F 6E 09 02 29 24 02 05 51
   75 65 75 65 10 02 0B 2B 09 02 2C 0C 02 08 52 75
   6E 6E 61 62 6C 65 08 06 2E 00 FFFFFFA0 FFFFFF80 04 22 01 06
   74 61 73 6B 73 20 08 07 30 00 FFFFFFC2 FFFFFF80 FFFFFF84 08 31 01
   0A 6D 61 78 4E 65 73 74 69 6E 67 15 01 32 10 02
   17 33 09 02 34 06 02 03 49 6E 74 08 06 36 00 FFFFFFA0
   FFFFFF80 04 32 01 0B 6D 61 78 4E 65 73 74 69 6E 67 20
   08 07 38 00 FFFFFFC0 FFFFFF80 FFFFFF84 04 31 01 07 63 75 72 4E 65
   73 74 08 07 3A 00 FFFFFFC0 FFFFFF80 FFFFFF84 04 3B 01 0B 63 75 72
   4E 65 73 74 5F 24 65 71 14 02 3C 3F 10 02 17 3D
   09 02 3E 06 02 04 55 6E 69 74 08 07 40 39 FFFFFF81 FFFFFF80
   FFFFFFC0 00 32 01 03 78 24 31 08 06 42 00 FFFFFFA0 FFFFFFA0 04 32
   01 08 63 75 72 4E 65 73 74 20 08 07 44 00 FFFFFFC0 FFFFFF80
   FFFFFF84 04 45 01 0A 69 73 53 68 75 74 64 6F 77 6E 15
   01 46 10 02 17 47 09 02 48 06 02 07 42 6F 6F 6C
   65 61 6E 08 07 4A 00 FFFFFFC0 FFFFFF80 FFFFFF84 04 4B 01 0E 69 73
   53 68 75 74 64 6F 77 6E 5F 24 65 71 14 02 3C 4C
   08 07 40 49 FFFFFF81 FFFFFF80 FFFFFFC0 00 46 08 06 4E 00 FFFFFFA0 FFFFFFA0 04
   46 01 0B 69 73 53 68 75 74 64 6F 77 6E 20 08 05
   50 00 FFFFFF84 00 51 01 07 65 78 65 63 75 74 65 14 02
   3C 52 08 05 53 4F FFFFFFC0 00 2A 01 04 74 61 73 6B 08
   05 50 00 FFFFFF84 00 55 14 02 3C 56 08 06 57 54 FFFFFF84 FFFFFFC0
   00 58 01 03 66 75 6E 10 03 17 59 3C 09 02 5A 06
   02 08 3C 62 79 6E 61 6D 65 3E 08 05 5C 00 FFFFFF84 00
   5D 01 08 73 68 75 74 64 6F 77 6E 14 01 3C 08 05
   5F 00 FFFFFF84 00 60 01 08 6E 65 77 41 63 74 6F 72 14
   02 3C 61 08 05 62 5E FFFFFFC0 00 63 01 05 61 63 74 6F
   72 10 02 13 64 09 02 65 04 02 07 52 65 61 63 74
   6F 72 08 05 67 00 FFFFFF84 00 68 01 0A 74 65 72 6D 69
   6E 61 74 65 64 14 02 3C 69 08 05 62 66 FFFFFFC0 00 63
   08 05 6B 00 FFFFFF84 00 6C 01 0B 6F 6E 54 65 72 6D 69
   6E 61 74 65 14 02 6D 70 14 02 3C 6E 08 06 6F 6A
   FFFFFF84 FFFFFFC0 00 58 01 01 66 08 05 62 6A FFFFFFC0 00 63 08 05
   72 00 FFFFFF84 00 45 01 08 69 73 41 63 74 69 76 65 08
   05 74 00 FFFFFF84 00 75 01 0C 6D 61 6E 61 67 65 64 42
   6C 6F 63 6B 14 02 3C 76 08 05 77 73 FFFFFFC0 00 78 01
   07 62 6C 6F 63 6B 65 72 10 02 79 7C 0D 01 7A 0A
   02 7B 06 01 0A 63 6F 6E 63 75 72 72 65 6E 74 09
   02 7D 7A 02 0E 4D 61 6E 61 67 65 64 42 6C 6F 63
   6B 65 72 
  InnerClass: 
   public final #140= #91 of #30; //$anon$1=class scala/actors/scheduler/SingleThreadedScheduler$$anon$1 of class scala/actors/scheduler/SingleThreadedScheduler
  minor version: 0
  major version: 49
  Constant pool:
const #1 = Asciz	SourceFile;
const #2 = Asciz	SingleThreadedScheduler.scala;
const #3 = Asciz	isShutdown;
const #4 = Asciz	Z;
const #5 = Asciz	curNest;
const #6 = Asciz	I;
const #7 = Asciz	maxNesting;
const #8 = Asciz	tasks;
const #9 = Asciz	Lscala/collection/mutable/Queue;;
const #10 = Asciz	Lscala/collection/mutable/Queue<Ljava/lang/Runnable;>;;
const #11 = Asciz	Signature;
const #12 = Asciz	<init>;
const #13 = Asciz	()V;
const #14 = Asciz	Code;
const #15 = Asciz	LineNumberTable;
const #16 = Asciz	java/lang/Object;
const #17 = class	#16;	//  java/lang/Object
const #18 = NameAndType	#12:#13;//  "<init>":()V
const #19 = Method	#17.#18;	//  java/lang/Object."<init>":()V
const #20 = Asciz	scala/actors/IScheduler$class;
const #21 = class	#20;	//  scala/actors/IScheduler$class
const #22 = Asciz	$init$;
const #23 = Asciz	(Lscala/actors/IScheduler;)V;
const #24 = NameAndType	#22:#23;//  $init$:(Lscala/actors/IScheduler;)V
const #25 = Method	#21.#24;	//  scala/actors/IScheduler$class.$init$:(Lscala/actors/IScheduler;)V
const #26 = Asciz	scala/collection/mutable/Queue;
const #27 = class	#26;	//  scala/collection/mutable/Queue
const #28 = Method	#27.#18;	//  scala/collection/mutable/Queue."<init>":()V
const #29 = Asciz	scala/actors/scheduler/SingleThreadedScheduler;
const #30 = class	#29;	//  scala/actors/scheduler/SingleThreadedScheduler
const #31 = NameAndType	#8:#9;//  tasks:Lscala/collection/mutable/Queue;
const #32 = Field	#30.#31;	//  scala/actors/scheduler/SingleThreadedScheduler.tasks:Lscala/collection/mutable/Queue;
const #33 = int	10;
const #34 = NameAndType	#7:#6;//  maxNesting:I
const #35 = Field	#30.#34;	//  scala/actors/scheduler/SingleThreadedScheduler.maxNesting:I
const #36 = NameAndType	#5:#6;//  curNest:I
const #37 = Field	#30.#36;	//  scala/actors/scheduler/SingleThreadedScheduler.curNest:I
const #38 = NameAndType	#3:#4;//  isShutdown:Z
const #39 = Field	#30.#38;	//  scala/actors/scheduler/SingleThreadedScheduler.isShutdown:Z
const #40 = Asciz	managedBlock;
const #41 = Asciz	(Lscala/concurrent/ManagedBlocker;)V;
const #42 = Asciz	scala/concurrent/ManagedBlocker;
const #43 = class	#42;	//  scala/concurrent/ManagedBlocker
const #44 = Asciz	block;
const #45 = Asciz	()Z;
const #46 = NameAndType	#44:#45;//  block:()Z
const #47 = InterfaceMethod	#43.#46;	//  scala/concurrent/ManagedBlocker.block:()Z
const #48 = Asciz	this;
const #49 = Asciz	Lscala/actors/scheduler/SingleThreadedScheduler;;
const #50 = Asciz	blocker;
const #51 = Asciz	Lscala/concurrent/ManagedBlocker;;
const #52 = Asciz	LocalVariableTable;
const #53 = Asciz	isActive;
const #54 = NameAndType	#3:#45;//  isShutdown:()Z
const #55 = Method	#30.#54;	//  scala/actors/scheduler/SingleThreadedScheduler.isShutdown:()Z
const #56 = Asciz	onTerminate;
const #57 = Asciz	(Lscala/actors/Reactor;Lscala/Function0;)V;
const #58 = Asciz	actor;
const #59 = Asciz	Lscala/actors/Reactor;;
const #60 = Asciz	f;
const #61 = Asciz	Lscala/Function0;;
const #62 = Asciz	(Lscala/actors/Reactor;Lscala/Function0<Ljava/lang/Object;>;)V;
const #63 = Asciz	terminated;
const #64 = Asciz	(Lscala/actors/Reactor;)V;
const #65 = Asciz	newActor;
const #66 = Asciz	shutdown;
const #67 = Asciz	isShutdown_$eq;
const #68 = Asciz	(Z)V;
const #69 = NameAndType	#67:#68;//  isShutdown_$eq:(Z)V
const #70 = Method	#30.#69;	//  scala/actors/scheduler/SingleThreadedScheduler.isShutdown_$eq:(Z)V
const #71 = Asciz	()Lscala/collection/mutable/Queue;;
const #72 = NameAndType	#8:#71;//  tasks:()Lscala/collection/mutable/Queue;
const #73 = Method	#30.#72;	//  scala/actors/scheduler/SingleThreadedScheduler.tasks:()Lscala/collection/mutable/Queue;
const #74 = Asciz	isEmpty;
const #75 = NameAndType	#74:#45;//  isEmpty:()Z
const #76 = Method	#27.#75;	//  scala/collection/mutable/Queue.isEmpty:()Z
const #77 = Asciz	dequeue;
const #78 = Asciz	()Ljava/lang/Object;;
const #79 = NameAndType	#77:#78;//  dequeue:()Ljava/lang/Object;
const #80 = Method	#27.#79;	//  scala/collection/mutable/Queue.dequeue:()Ljava/lang/Object;
const #81 = Asciz	java/lang/Runnable;
const #82 = class	#81;	//  java/lang/Runnable
const #83 = Asciz	run;
const #84 = NameAndType	#83:#13;//  run:()V
const #85 = InterfaceMethod	#82.#84;	//  java/lang/Runnable.run:()V
const #86 = Asciz	task;
const #87 = Asciz	Ljava/lang/Runnable;;
const #88 = Asciz	execute;
const #89 = Asciz	(Lscala/Function0;)V;
const #90 = Asciz	scala/actors/scheduler/SingleThreadedScheduler$$anon$1;
const #91 = class	#90;	//  scala/actors/scheduler/SingleThreadedScheduler$$anon$1
const #92 = Asciz	(Lscala/actors/scheduler/SingleThreadedScheduler;Lscala/Function0;)V;
const #93 = NameAndType	#12:#92;//  "<init>":(Lscala/actors/scheduler/SingleThreadedScheduler;Lscala/Function0;)V
const #94 = Method	#91.#93;	//  scala/actors/scheduler/SingleThreadedScheduler$$anon$1."<init>":(Lscala/actors/scheduler/SingleThreadedScheduler;Lscala/Function0;)V
const #95 = Asciz	(Ljava/lang/Runnable;)V;
const #96 = NameAndType	#88:#95;//  execute:(Ljava/lang/Runnable;)V
const #97 = Method	#30.#96;	//  scala/actors/scheduler/SingleThreadedScheduler.execute:(Ljava/lang/Runnable;)V
const #98 = Asciz	fun$1;
const #99 = Asciz	(Lscala/Function0<Ljava/lang/Object;>;)V;
const #100 = Asciz	()I;
const #101 = NameAndType	#5:#100;//  curNest:()I
const #102 = Method	#30.#101;	//  scala/actors/scheduler/SingleThreadedScheduler.curNest:()I
const #103 = NameAndType	#7:#100;//  maxNesting:()I
const #104 = Method	#30.#103;	//  scala/actors/scheduler/SingleThreadedScheduler.maxNesting:()I
const #105 = Asciz	curNest_$eq;
const #106 = Asciz	(I)V;
const #107 = NameAndType	#105:#106;//  curNest_$eq:(I)V
const #108 = Method	#30.#107;	//  scala/actors/scheduler/SingleThreadedScheduler.curNest_$eq:(I)V
const #109 = Asciz	$plus$eq;
const #110 = Asciz	(Ljava/lang/Object;)Lscala/collection/mutable/MutableList;;
const #111 = NameAndType	#109:#110;//  $plus$eq:(Ljava/lang/Object;)Lscala/collection/mutable/MutableList;
const #112 = Method	#27.#111;	//  scala/collection/mutable/Queue.$plus$eq:(Ljava/lang/Object;)Lscala/collection/mutable/MutableList;
const #113 = Asciz	()Lscala/collection/mutable/Queue<Ljava/lang/Runnable;>;;
const #114 = Asciz	printActorDump;
const #115 = NameAndType	#114:#23;//  printActorDump:(Lscala/actors/IScheduler;)V
const #116 = Method	#21.#115;	//  scala/actors/IScheduler$class.printActorDump:(Lscala/actors/IScheduler;)V
const #117 = Asciz	onLockup;
const #118 = Asciz	(ILscala/Function0;)V;
const #119 = Asciz	(Lscala/actors/IScheduler;ILscala/Function0;)V;
const #120 = NameAndType	#117:#119;//  onLockup:(Lscala/actors/IScheduler;ILscala/Function0;)V
const #121 = Method	#21.#120;	//  scala/actors/IScheduler$class.onLockup:(Lscala/actors/IScheduler;ILscala/Function0;)V
const #122 = Asciz	millis;
const #123 = Asciz	handler;
const #124 = Asciz	(Lscala/actors/IScheduler;Lscala/Function0;)V;
const #125 = NameAndType	#117:#124;//  onLockup:(Lscala/actors/IScheduler;Lscala/Function0;)V
const #126 = Method	#21.#125;	//  scala/actors/IScheduler$class.onLockup:(Lscala/actors/IScheduler;Lscala/Function0;)V
const #127 = Asciz	tick;
const #128 = Asciz	(Lscala/actors/Actor;)V;
const #129 = Asciz	(Lscala/actors/IScheduler;Lscala/actors/Actor;)V;
const #130 = NameAndType	#127:#129;//  tick:(Lscala/actors/IScheduler;Lscala/actors/Actor;)V
const #131 = Method	#21.#130;	//  scala/actors/IScheduler$class.tick:(Lscala/actors/IScheduler;Lscala/actors/Actor;)V
const #132 = Asciz	a;
const #133 = Asciz	Lscala/actors/Actor;;
const #134 = Asciz	executeFromActor;
const #135 = Asciz	(Lscala/actors/IScheduler;Ljava/lang/Runnable;)V;
const #136 = NameAndType	#134:#135;//  executeFromActor:(Lscala/actors/IScheduler;Ljava/lang/Runnable;)V
const #137 = Method	#21.#136;	//  scala/actors/IScheduler$class.executeFromActor:(Lscala/actors/IScheduler;Ljava/lang/Runnable;)V
const #138 = Asciz	ScalaSig;
const #139 = Asciz	InnerClasses;
const #140 = Asciz	$anon$1;
const #141 = Asciz	scala/actors/IScheduler;
const #142 = class	#141;	//  scala/actors/IScheduler
const #143 = Asciz	scala/ScalaObject;
const #144 = class	#143;	//  scala/ScalaObject

{
public scala.actors.scheduler.SingleThreadedScheduler();
  Code:
   Stack=3, Locals=1, Args_size=1
   0:	aload_0
   1:	invokespecial	#19; //Method java/lang/Object."<init>":()V
   4:	aload_0
   5:	invokestatic	#25; //Method scala/actors/IScheduler$class.$init$:(Lscala/actors/IScheduler;)V
   8:	aload_0
   9:	new	#27; //class scala/collection/mutable/Queue
   12:	dup
   13:	invokespecial	#28; //Method scala/collection/mutable/Queue."<init>":()V
   16:	putfield	#32; //Field tasks:Lscala/collection/mutable/Queue;
   19:	aload_0
   20:	ldc	#33; //int 10
   22:	putfield	#35; //Field maxNesting:I
   25:	aload_0
   26:	iconst_0
   27:	putfield	#37; //Field curNest:I
   30:	aload_0
   31:	iconst_0
   32:	putfield	#39; //Field isShutdown:Z
   35:	return
  LineNumberTable: 
   line 21: 0
   line 23: 8
   line 28: 19
   line 30: 25
   line 31: 30


public void managedBlock(scala.concurrent.ManagedBlocker);
  Code:
   Stack=1, Locals=2, Args_size=2
   0:	aload_1
   1:	invokeinterface	#47,  1; //InterfaceMethod scala/concurrent/ManagedBlocker.block:()Z
   6:	pop
   7:	return
  LineNumberTable: 
   line 67: 0

  LocalVariableTable: 
   Start  Length  Slot  Name   Signature
   0      8      0    this       Lscala/actors/scheduler/SingleThreadedScheduler;
   0      8      1    blocker       Lscala/concurrent/ManagedBlocker;


public boolean isActive();
  Code:
   Stack=1, Locals=1, Args_size=1
   0:	aload_0
   1:	invokespecial	#55; //Method isShutdown:()Z
   4:	ifeq	11
   7:	iconst_0
   8:	goto	12
   11:	iconst_1
   12:	ireturn
  LineNumberTable: 
   line 64: 0


public void onTerminate(scala.actors.Reactor, scala.Function0);
  Code:
   Stack=0, Locals=3, Args_size=3
   0:	return
  LineNumberTable: 
   line 61: 0

  LocalVariableTable: 
   Start  Length  Slot  Name   Signature
   0      1      0    this       Lscala/actors/scheduler/SingleThreadedScheduler;
   0      1      1    actor       Lscala/actors/Reactor;
   0      1      2    f       Lscala/Function0;

  Signature: length = 0x2
   00 3E 

public void terminated(scala.actors.Reactor);
  Code:
   Stack=0, Locals=2, Args_size=2
   0:	return
  LineNumberTable: 
   line 58: 0

  LocalVariableTable: 
   Start  Length  Slot  Name   Signature
   0      1      0    this       Lscala/actors/scheduler/SingleThreadedScheduler;
   0      1      1    actor       Lscala/actors/Reactor;


public void newActor(scala.actors.Reactor);
  Code:
   Stack=0, Locals=2, Args_size=2
   0:	return
  LineNumberTable: 
   line 57: 0

  LocalVariableTable: 
   Start  Length  Slot  Name   Signature
   0      1      0    this       Lscala/actors/scheduler/SingleThreadedScheduler;
   0      1      1    actor       Lscala/actors/Reactor;


public void shutdown();
  Code:
   Stack=2, Locals=2, Args_size=1
   0:	aload_0
   1:	iconst_0
   2:	invokespecial	#70; //Method isShutdown_$eq:(Z)V
   5:	aload_0
   6:	invokespecial	#73; //Method tasks:()Lscala/collection/mutable/Queue;
   9:	invokevirtual	#76; //Method scala/collection/mutable/Queue.isEmpty:()Z
   12:	ifeq	21
   15:	aload_0
   16:	iconst_1
   17:	invokespecial	#70; //Method isShutdown_$eq:(Z)V
   20:	return
   21:	aload_0
   22:	invokespecial	#73; //Method tasks:()Lscala/collection/mutable/Queue;
   25:	invokevirtual	#80; //Method scala/collection/mutable/Queue.dequeue:()Ljava/lang/Object;
   28:	checkcast	#82; //class java/lang/Runnable
   31:	astore_1
   32:	aload_1
   33:	invokeinterface	#85,  1; //InterfaceMethod java/lang/Runnable.run:()V
   38:	goto	5
  LineNumberTable: 
   line 49: 0
   line 50: 5
   line 54: 15
   line 51: 21
   line 52: 32

  LocalVariableTable: 
   Start  Length  Slot  Name   Signature
   0      41      0    this       Lscala/actors/scheduler/SingleThreadedScheduler;
   32      6      1    task       Ljava/lang/Runnable;


public void execute(scala.Function0);
  Code:
   Stack=5, Locals=2, Args_size=2
   0:	aload_0
   1:	new	#91; //class scala/actors/scheduler/SingleThreadedScheduler$$anon$1
   4:	dup
   5:	aload_0
   6:	aload_1
   7:	invokespecial	#94; //Method scala/actors/scheduler/SingleThreadedScheduler$$anon$1."<init>":(Lscala/actors/scheduler/SingleThreadedScheduler;Lscala/Function0;)V
   10:	invokevirtual	#97; //Method execute:(Ljava/lang/Runnable;)V
   13:	return
  LineNumberTable: 
   line 44: 0

  LocalVariableTable: 
   Start  Length  Slot  Name   Signature
   0      14      0    this       Lscala/actors/scheduler/SingleThreadedScheduler;
   0      14      1    fun$1       Lscala/Function0;

  Signature: length = 0x2
   00 63 

public void execute(java.lang.Runnable);
  Code:
   Stack=3, Locals=2, Args_size=2
   0:	aload_0
   1:	invokespecial	#102; //Method curNest:()I
   4:	aload_0
   5:	invokevirtual	#104; //Method maxNesting:()I
   8:	if_icmpge	30
   11:	aload_0
   12:	aload_0
   13:	invokespecial	#102; //Method curNest:()I
   16:	iconst_1
   17:	iadd
   18:	invokespecial	#108; //Method curNest_$eq:(I)V
   21:	aload_1
   22:	invokeinterface	#85,  1; //InterfaceMethod java/lang/Runnable.run:()V
   27:	goto	44
   30:	aload_0
   31:	iconst_0
   32:	invokespecial	#108; //Method curNest_$eq:(I)V
   35:	aload_0
   36:	invokespecial	#73; //Method tasks:()Lscala/collection/mutable/Queue;
   39:	aload_1
   40:	invokevirtual	#112; //Method scala/collection/mutable/Queue.$plus$eq:(Ljava/lang/Object;)Lscala/collection/mutable/MutableList;
   43:	pop
   44:	return
  LineNumberTable: 
   line 34: 0
   line 35: 11
   line 36: 21
   line 38: 30
   line 39: 35
   line 34: 44

  LocalVariableTable: 
   Start  Length  Slot  Name   Signature
   0      45      0    this       Lscala/actors/scheduler/SingleThreadedScheduler;
   0      45      1    task       Ljava/lang/Runnable;


public int maxNesting();
  Code:
   Stack=1, Locals=1, Args_size=1
   0:	aload_0
   1:	getfield	#35; //Field maxNesting:I
   4:	ireturn
  LineNumberTable: 
   line 28: 0


public void printActorDump();
  Code:
   Stack=1, Locals=1, Args_size=1
   0:	aload_0
   1:	invokestatic	#116; //Method scala/actors/IScheduler$class.printActorDump:(Lscala/actors/IScheduler;)V
   4:	return
  LineNumberTable: 
   line 21: 0


public void onLockup(int, scala.Function0);
  Code:
   Stack=3, Locals=3, Args_size=3
   0:	aload_0
   1:	iload_1
   2:	aload_2
   3:	invokestatic	#121; //Method scala/actors/IScheduler$class.onLockup:(Lscala/actors/IScheduler;ILscala/Function0;)V
   6:	return
  LineNumberTable: 
   line 21: 0

  LocalVariableTable: 
   Start  Length  Slot  Name   Signature
   0      7      0    this       Lscala/actors/scheduler/SingleThreadedScheduler;
   0      7      1    millis       I
   0      7      2    handler       Lscala/Function0;


public void onLockup(scala.Function0);
  Code:
   Stack=2, Locals=2, Args_size=2
   0:	aload_0
   1:	aload_1
   2:	invokestatic	#126; //Method scala/actors/IScheduler$class.onLockup:(Lscala/actors/IScheduler;Lscala/Function0;)V
   5:	return
  LineNumberTable: 
   line 21: 0

  LocalVariableTable: 
   Start  Length  Slot  Name   Signature
   0      6      0    this       Lscala/actors/scheduler/SingleThreadedScheduler;
   0      6      1    handler       Lscala/Function0;


public void tick(scala.actors.Actor);
  Code:
   Stack=2, Locals=2, Args_size=2
   0:	aload_0
   1:	aload_1
   2:	invokestatic	#131; //Method scala/actors/IScheduler$class.tick:(Lscala/actors/IScheduler;Lscala/actors/Actor;)V
   5:	return
  LineNumberTable: 
   line 21: 0

  LocalVariableTable: 
   Start  Length  Slot  Name   Signature
   0      6      0    this       Lscala/actors/scheduler/SingleThreadedScheduler;
   0      6      1    a       Lscala/actors/Actor;


public void executeFromActor(java.lang.Runnable);
  Code:
   Stack=2, Locals=2, Args_size=2
   0:	aload_0
   1:	aload_1
   2:	invokestatic	#137; //Method scala/actors/IScheduler$class.executeFromActor:(Lscala/actors/IScheduler;Ljava/lang/Runnable;)V
   5:	return
  LineNumberTable: 
   line 21: 0

  LocalVariableTable: 
   Start  Length  Slot  Name   Signature
   0      6      0    this       Lscala/actors/scheduler/SingleThreadedScheduler;
   0      6      1    task       Ljava/lang/Runnable;


}

