Compiled from "TerminationMonitor.scala"
public abstract class scala.actors.scheduler.TerminationMonitor$class extends java.lang.Object
  SourceFile: "TerminationMonitor.scala"
  Scala: length = 0x
   
  InnerClass: 
   public final ArrowAssoc=class scala/Predef$ArrowAssoc of class scala/Predef
   public final $anonfun$1=class scala/actors/scheduler/TerminationMonitor$$anonfun$1 of class scala/actors/scheduler/TerminationMonitor
  minor version: 0
  major version: 49
  Constant pool:
Asciz	SourceFile;
Asciz	TerminationMonitor.scala;
Asciz	newActor;
Asciz	(Lscala/actors/scheduler/TerminationMonitor;Lscala/actors/Reactor;)V;
Asciz	Code;
Asciz	LineNumberTable;
Asciz	scala/actors/scheduler/TerminationMonitor;
class	scala/actors/scheduler/TerminationMonitor
Asciz	activeActors;
Asciz	()I;
NameAndType	activeActors:()I
InterfaceMethod	scala/actors/scheduler/TerminationMonitor.activeActors:()I
Asciz	activeActors_$eq;
Asciz	(I)V;
NameAndType	activeActors_$eq:(I)V
InterfaceMethod	scala/actors/scheduler/TerminationMonitor.activeActors_$eq:(I)V
Asciz	scala$actors$scheduler$TerminationMonitor$$started;
Asciz	()Z;
NameAndType	scala$actors$scheduler$TerminationMonitor$$started:()Z
InterfaceMethod	scala/actors/scheduler/TerminationMonitor.scala$actors$scheduler$TerminationMonitor$$started:()Z
Asciz	scala/runtime/BoxedUnit;
class	scala/runtime/BoxedUnit
Asciz	UNIT;
Asciz	Lscala/runtime/BoxedUnit;;
NameAndType	UNIT:Lscala/runtime/BoxedUnit;
Field	scala/runtime/BoxedUnit.UNIT:Lscala/runtime/BoxedUnit;
Asciz	scala$actors$scheduler$TerminationMonitor$$started_$eq;
Asciz	(Z)V;
NameAndType	scala$actors$scheduler$TerminationMonitor$$started_$eq:(Z)V
InterfaceMethod	scala/actors/scheduler/TerminationMonitor.scala$actors$scheduler$TerminationMonitor$$started_$eq:(Z)V
Asciz	$this;
Asciz	Lscala/actors/scheduler/TerminationMonitor;;
Asciz	a;
Asciz	Lscala/actors/Reactor;;
Asciz	LocalVariableTable;
Asciz	onTerminate;
Asciz	(Lscala/actors/scheduler/TerminationMonitor;Lscala/actors/Reactor;Lscala/Function0;)V;
Asciz	terminationHandlers;
Asciz	()Lscala/collection/mutable/HashMap;;
NameAndType	terminationHandlers:()Lscala/collection/mutable/HashMap;
InterfaceMethod	scala/actors/scheduler/TerminationMonitor.terminationHandlers:()Lscala/collection/mutable/HashMap;
Asciz	scala/Predef$;
class	scala/Predef$
Asciz	MODULE$;
Asciz	Lscala/Predef$;;
NameAndType	MODULE$:Lscala/Predef$;
Field	scala/Predef$.MODULE$:Lscala/Predef$;
Asciz	any2ArrowAssoc;
Asciz	(Ljava/lang/Object;)Lscala/Predef$ArrowAssoc;;
NameAndType	any2ArrowAssoc:(Ljava/lang/Object;)Lscala/Predef$ArrowAssoc;
Method	scala/Predef$.any2ArrowAssoc:(Ljava/lang/Object;)Lscala/Predef$ArrowAssoc;
Asciz	scala/Predef$ArrowAssoc;
class	scala/Predef$ArrowAssoc
Asciz	$minus$greater;
Asciz	(Ljava/lang/Object;)Lscala/Tuple2;;
NameAndType	$minus$greater:(Ljava/lang/Object;)Lscala/Tuple2;
Method	scala/Predef$ArrowAssoc.$minus$greater:(Ljava/lang/Object;)Lscala/Tuple2;
Asciz	scala/collection/mutable/HashMap;
class	scala/collection/mutable/HashMap
Asciz	$plus$eq;
Asciz	(Lscala/Tuple2;)Lscala/collection/mutable/HashMap;;
NameAndType	$plus$eq:(Lscala/Tuple2;)Lscala/collection/mutable/HashMap;
Method	scala/collection/mutable/HashMap.$plus$eq:(Lscala/Tuple2;)Lscala/collection/mutable/HashMap;
Asciz	f;
Asciz	Lscala/Function0;;
Asciz	terminated;
Asciz	get;
Asciz	(Ljava/lang/Object;)Lscala/Option;;
NameAndType	get:(Ljava/lang/Object;)Lscala/Option;
Method	scala/collection/mutable/HashMap.get:(Ljava/lang/Object;)Lscala/Option;
Asciz	scala/Some;
class	scala/Some
Asciz	$minus$eq;
Asciz	(Ljava/lang/Object;)Lscala/collection/mutable/HashMap;;
NameAndType	$minus$eq:(Ljava/lang/Object;)Lscala/collection/mutable/HashMap;
Method	scala/collection/mutable/HashMap.$minus$eq:(Ljava/lang/Object;)Lscala/collection/mutable/HashMap;
Asciz	x;
Asciz	()Ljava/lang/Object;;
NameAndType	x:()Ljava/lang/Object;
Method	scala/Some.x:()Ljava/lang/Object;
Asciz	scala/None$;
class	scala/None$
Asciz	Lscala/None$;;
NameAndType	MODULE$:Lscala/None$;
Field	scala/None$.MODULE$:Lscala/None$;
Asciz	java/lang/Object;
class	java/lang/Object
Asciz	equals;
Asciz	(Ljava/lang/Object;)Z;
NameAndType	equals:(Ljava/lang/Object;)Z
Method	java/lang/Object.equals:(Ljava/lang/Object;)Z
Asciz	scala/actors/scheduler/TerminationMonitor$$anonfun$1;
class	scala/actors/scheduler/TerminationMonitor$$anonfun$1
Asciz	<init>;
Asciz	(Lscala/actors/scheduler/TerminationMonitor;)V;
NameAndType	"<init>":(Lscala/actors/scheduler/TerminationMonitor;)V
Method	scala/actors/scheduler/TerminationMonitor$$anonfun$1."<init>":(Lscala/actors/scheduler/TerminationMonitor;)V
Asciz	scala/Function0;
class	scala/Function0
Asciz	apply;
NameAndType	apply:()Ljava/lang/Object;
InterfaceMethod	scala/Function0.apply:()Ljava/lang/Object;
Asciz	scala/MatchError;
class	scala/MatchError
Asciz	(Ljava/lang/Object;)V;
NameAndType	"<init>":(Ljava/lang/Object;)V
Method	scala/MatchError."<init>":(Ljava/lang/Object;)V
Asciz	todo;
Asciz	temp1;
Asciz	Lscala/Option;;
Asciz	allActorsTerminated;
Asciz	(Lscala/actors/scheduler/TerminationMonitor;)Z;
Asciz	scala/runtime/BoxesRunTime;
class	scala/runtime/BoxesRunTime
Asciz	boxToBoolean;
Asciz	(Z)Ljava/lang/Boolean;;
NameAndType	boxToBoolean:(Z)Ljava/lang/Boolean;
Method	scala/runtime/BoxesRunTime.boxToBoolean:(Z)Ljava/lang/Boolean;
Asciz	unboxToBoolean;
NameAndType	unboxToBoolean:(Ljava/lang/Object;)Z
Method	scala/runtime/BoxesRunTime.unboxToBoolean:(Ljava/lang/Object;)Z
Asciz	allTerminated;
NameAndType	allActorsTerminated:()Z
InterfaceMethod	scala/actors/scheduler/TerminationMonitor.allActorsTerminated:()Z
Asciz	Deprecated;
Asciz	gc;
Asciz	$init$;
Asciz	()V;
NameAndType	"<init>":()V
Method	scala/collection/mutable/HashMap."<init>":()V
Asciz	scala$actors$scheduler$TerminationMonitor$_setter_$terminationHandlers_$eq;
Asciz	(Lscala/collection/mutable/HashMap;)V;
NameAndType	scala$actors$scheduler$TerminationMonitor$_setter_$terminationHandlers_$eq:(Lscala/collection/mutable/HashMap;)V
InterfaceMethod	scala/actors/scheduler/TerminationMonitor.scala$actors$scheduler$TerminationMonitor$_setter_$terminationHandlers_$eq:(Lscala/collection/mutable/HashMap;)V
Asciz	Scala;
Asciz	InnerClasses;
Asciz	scala/Predef;
class	scala/Predef
Asciz	ArrowAssoc;
Asciz	$anonfun$1;
Asciz	scala/actors/scheduler/TerminationMonitor$class;
class	scala/actors/scheduler/TerminationMonitor$class

{
public static void newActor(scala.actors.scheduler.TerminationMonitor, scala.actors.Reactor);
  Signature: (Lscala/actors/scheduler/TerminationMonitor;Lscala/actors/Reactor;)V
  Code:
   Stack=3, Locals=3, Args_size=2
	aload_0
	dup
	astore_2
	monitorenter
	aload_0
	aload_0
	invokeinterface	InterfaceMethod scala/actors/scheduler/TerminationMonitor.activeActors:()I
	iconst_1
	iadd
	invokeinterface	InterfaceMethod scala/actors/scheduler/TerminationMonitor.activeActors_$eq:(I)V
	aload_0
	invokeinterface	InterfaceMethod scala/actors/scheduler/TerminationMonitor.scala$actors$scheduler$TerminationMonitor$$started:()Z
	ifeq	l1 // aload_0
	getstatic	Field scala/runtime/BoxedUnit.UNIT:Lscala/runtime/BoxedUnit;
	goto	l2 // pop
l1	aload_0
	iconst_1
	invokeinterface	InterfaceMethod scala/actors/scheduler/TerminationMonitor.scala$actors$scheduler$TerminationMonitor$$started_$eq:(Z)V
	getstatic	Field scala/runtime/BoxedUnit.UNIT:Lscala/runtime/BoxedUnit;
l2	pop
	aload_2
	monitorexit
	return
	aload_2
	monitorexit
	athrow
  Labels:
   	l1 = 33 // aload_0
   	l2 = 43 // pop
  Exception table:
   from   to  target type
     4    46    47   any
  LocalVariableTable: 
   Start  Length  Slot  Name   Signature
   0      50      0    $this       Lscala/actors/scheduler/TerminationMonitor;
   0      50      1    a       Lscala/actors/Reactor;


public static void onTerminate(scala.actors.scheduler.TerminationMonitor, scala.actors.Reactor, scala.Function0);
  Signature: (Lscala/actors/scheduler/TerminationMonitor;Lscala/actors/Reactor;Lscala/Function0;)V
  Code:
   Stack=3, Locals=4, Args_size=3
	aload_0
	dup
	astore_3
	monitorenter
	aload_0
	invokeinterface	InterfaceMethod scala/actors/scheduler/TerminationMonitor.terminationHandlers:()Lscala/collection/mutable/HashMap;
	getstatic	Field scala/Predef$.MODULE$:Lscala/Predef$;
	aload_1
	invokevirtual	Method scala/Predef$.any2ArrowAssoc:(Ljava/lang/Object;)Lscala/Predef$ArrowAssoc;
	aload_2
	invokevirtual	Method scala/Predef$ArrowAssoc.$minus$greater:(Ljava/lang/Object;)Lscala/Tuple2;
	invokevirtual	Method scala/collection/mutable/HashMap.$plus$eq:(Lscala/Tuple2;)Lscala/collection/mutable/HashMap;
	pop
	aload_3
	monitorexit
	return
	aload_3
	monitorexit
	athrow
  Labels:
  Exception table:
   from   to  target type
     4    27    28   any
  LocalVariableTable: 
   Start  Length  Slot  Name   Signature
   0      31      0    $this       Lscala/actors/scheduler/TerminationMonitor;
   0      31      1    a       Lscala/actors/Reactor;
   0      31      2    f       Lscala/Function0;


public static void terminated(scala.actors.scheduler.TerminationMonitor, scala.actors.Reactor);
  Signature: (Lscala/actors/scheduler/TerminationMonitor;Lscala/actors/Reactor;)V
  Code:
   Stack=3, Locals=8, Args_size=2
	aload_0
	dup
	astore_3
	monitorenter
	aload_0
	invokeinterface	InterfaceMethod scala/actors/scheduler/TerminationMonitor.terminationHandlers:()Lscala/collection/mutable/HashMap;
	aload_1
	invokevirtual	Method scala/collection/mutable/HashMap.get:(Ljava/lang/Object;)Lscala/Option;
	astore	5
	aload	5
	instanceof	class scala/Some
	ifeq	l1 // getstatic
	aload_0
	invokeinterface	InterfaceMethod scala/actors/scheduler/TerminationMonitor.terminationHandlers:()Lscala/collection/mutable/HashMap;
	aload_1
	invokevirtual	Method scala/collection/mutable/HashMap.$minus$eq:(Ljava/lang/Object;)Lscala/collection/mutable/HashMap;
	pop
	aload	5
	checkcast	class scala/Some
	invokevirtual	Method scala/Some.x:()Ljava/lang/Object;
	goto	l2 // astore
l1	getstatic	Field scala/None$.MODULE$:Lscala/None$;
	aload	5
	astore	6
	dup
	ifnonnull	l3 // aload
	pop
	aload	6
	ifnull	l4 // new
	goto	l5 // new
l3	aload	6
	invokevirtual	Method java/lang/Object.equals:(Ljava/lang/Object;)Z
	ifeq	l5 // new
l4	new	class scala/actors/scheduler/TerminationMonitor$$anonfun$1
	dup
	aload_0
	invokespecial	Method scala/actors/scheduler/TerminationMonitor$$anonfun$1."<init>":(Lscala/actors/scheduler/TerminationMonitor;)V
l2	astore	4
	aload_3
	monitorexit
	aload	4
	checkcast	class scala/Function0
	astore_2
	aload_2
	invokeinterface	InterfaceMethod scala/Function0.apply:()Ljava/lang/Object;
	pop
	aload_0
	dup
	astore	7
	monitorenter
	aload_0
	aload_0
	invokeinterface	InterfaceMethod scala/actors/scheduler/TerminationMonitor.activeActors:()I
	iconst_1
	isub
	invokeinterface	InterfaceMethod scala/actors/scheduler/TerminationMonitor.activeActors_$eq:(I)V
	getstatic	Field scala/runtime/BoxedUnit.UNIT:Lscala/runtime/BoxedUnit;
	pop
	aload	7
	monitorexit
	return
l5	new	class scala/MatchError
	dup
	aload	5
	invokespecial	Method scala/MatchError."<init>":(Ljava/lang/Object;)V
	athrow
	aload_3
	monitorexit
	athrow
	aload	7
	monitorexit
	athrow
  Labels:
   	l1 = 46 // getstatic
   	l3 = 66 // aload
   	l4 = 74 // new
   	l2 = 82 // astore
   	l5 = 126 // new
  Exception table:
   from   to  target type
   104   125   139   any
     4    86   136   any
   126   136   136   any
  LocalVariableTable: 
   Start  Length  Slot  Name   Signature
   0      143      0    $this       Lscala/actors/scheduler/TerminationMonitor;
   0      143      1    a       Lscala/actors/Reactor;
   92      34      2    todo       Lscala/Function0;
   139      4      2    todo       Lscala/Function0;
   16      70      5    temp1       Lscala/Option;
   126      10      5    temp1       Lscala/Option;


public static boolean allActorsTerminated(scala.actors.scheduler.TerminationMonitor);
  Signature: (Lscala/actors/scheduler/TerminationMonitor;)Z
  Code:
   Stack=2, Locals=3, Args_size=1
	aload_0
	dup
	astore_1
	monitorenter
	aload_0
	invokeinterface	InterfaceMethod scala/actors/scheduler/TerminationMonitor.scala$actors$scheduler$TerminationMonitor$$started:()Z
	ifeq	l1 // iconst_0
	aload_0
	invokeinterface	InterfaceMethod scala/actors/scheduler/TerminationMonitor.activeActors:()I
	iconst_0
	if_icmpgt	l1 // iconst_0
	iconst_1
	goto	l2 // invokestatic
l1	iconst_0
l2	invokestatic	Method scala/runtime/BoxesRunTime.boxToBoolean:(Z)Ljava/lang/Boolean;
	astore_2
	aload_1
	monitorexit
	aload_2
	invokestatic	Method scala/runtime/BoxesRunTime.unboxToBoolean:(Ljava/lang/Object;)Z
	ireturn
	aload_1
	monitorexit
	athrow
  Labels:
   	l1 = 27 // iconst_0
   	l2 = 28 // invokestatic
  Exception table:
   from   to  target type
     4    34    39   any
  LocalVariableTable: 
   Start  Length  Slot  Name   Signature
   0      42      0    $this       Lscala/actors/scheduler/TerminationMonitor;


public static boolean allTerminated(scala.actors.scheduler.TerminationMonitor);
  Signature: (Lscala/actors/scheduler/TerminationMonitor;)Z
  Code:
   Stack=1, Locals=1, Args_size=1
	aload_0
	invokeinterface	InterfaceMethod scala/actors/scheduler/TerminationMonitor.allActorsTerminated:()Z
	ireturn
  Labels:
  LocalVariableTable: 
   Start  Length  Slot  Name   Signature
   0      7      0    $this       Lscala/actors/scheduler/TerminationMonitor;

  Deprecated: true

public static void gc(scala.actors.scheduler.TerminationMonitor);
  Signature: (Lscala/actors/scheduler/TerminationMonitor;)V
  Code:
   Stack=0, Locals=1, Args_size=1
	return
  Labels:
  LocalVariableTable: 
   Start  Length  Slot  Name   Signature
   0      1      0    $this       Lscala/actors/scheduler/TerminationMonitor;


public static void $init$(scala.actors.scheduler.TerminationMonitor);
  Signature: (Lscala/actors/scheduler/TerminationMonitor;)V
  Code:
   Stack=3, Locals=1, Args_size=1
	aload_0
	iconst_0
	invokeinterface	InterfaceMethod scala/actors/scheduler/TerminationMonitor.activeActors_$eq:(I)V
	aload_0
	new	class scala/collection/mutable/HashMap
	dup
	invokespecial	Method scala/collection/mutable/HashMap."<init>":()V
	invokeinterface	InterfaceMethod scala/actors/scheduler/TerminationMonitor.scala$actors$scheduler$TerminationMonitor$_setter_$terminationHandlers_$eq:(Lscala/collection/mutable/HashMap;)V
	aload_0
	iconst_0
	invokeinterface	InterfaceMethod scala/actors/scheduler/TerminationMonitor.scala$actors$scheduler$TerminationMonitor$$started_$eq:(Z)V
	return
  Labels:
  LocalVariableTable: 
   Start  Length  Slot  Name   Signature
   0      28      0    $this       Lscala/actors/scheduler/TerminationMonitor;


}

