Compiled from "TerminationMonitor.scala"
public abstract class scala.actors.scheduler.TerminationMonitor$class extends java.lang.Object
  SourceFile: "TerminationMonitor.scala"
  Scala: length = 0x
   
  InnerClass: 
   public #149= #134 of #148; //ArrowAssoc=class scala/Predef$ArrowAssoc of class scala/Predef
   public final #150= #89 of #8; //$anonfun$2=class scala/actors/scheduler/TerminationMonitor$$anonfun$2 of class scala/actors/scheduler/TerminationMonitor
   public final #151= #73 of #8; //$anonfun$1=class scala/actors/scheduler/TerminationMonitor$$anonfun$1 of class scala/actors/scheduler/TerminationMonitor
  minor version: 0
  major version: 49
  Constant pool:
const #1 = Asciz	SourceFile;
const #2 = Asciz	TerminationMonitor.scala;
const #3 = Asciz	$init$;
const #4 = Asciz	(Lscala/actors/scheduler/TerminationMonitor;)V;
const #5 = Asciz	Code;
const #6 = Asciz	LineNumberTable;
const #7 = Asciz	scala/actors/scheduler/TerminationMonitor;
const #8 = class	#7;	//  scala/actors/scheduler/TerminationMonitor
const #9 = Asciz	scala$actors$scheduler$TerminationMonitor$$pendingReactions_$eq;
const #10 = Asciz	(I)V;
const #11 = NameAndType	#9:#10;//  scala$actors$scheduler$TerminationMonitor$$pendingReactions_$eq:(I)V
const #12 = InterfaceMethod	#8.#11;	//  scala/actors/scheduler/TerminationMonitor.scala$actors$scheduler$TerminationMonitor$$pendingReactions_$eq:(I)V
const #13 = Asciz	scala/collection/mutable/HashMap;
const #14 = class	#13;	//  scala/collection/mutable/HashMap
const #15 = Asciz	<init>;
const #16 = Asciz	()V;
const #17 = NameAndType	#15:#16;//  "<init>":()V
const #18 = Method	#14.#17;	//  scala/collection/mutable/HashMap."<init>":()V
const #19 = Asciz	scala$actors$scheduler$TerminationMonitor$_setter_$scala$actors$scheduler$TerminationMonitor$$termHandlers_$eq;
const #20 = Asciz	(Lscala/collection/mutable/HashMap;)V;
const #21 = NameAndType	#19:#20;//  scala$actors$scheduler$TerminationMonitor$_setter_$scala$actors$scheduler$TerminationMonitor$$termHandlers_$eq:(Lscala/collection/mutable/HashMap;)V
const #22 = InterfaceMethod	#8.#21;	//  scala/actors/scheduler/TerminationMonitor.scala$actors$scheduler$TerminationMonitor$_setter_$scala$actors$scheduler$TerminationMonitor$$termHandlers_$eq:(Lscala/collection/mutable/HashMap;)V
const #23 = Asciz	scala$actors$scheduler$TerminationMonitor$$started_$eq;
const #24 = Asciz	(Z)V;
const #25 = NameAndType	#23:#24;//  scala$actors$scheduler$TerminationMonitor$$started_$eq:(Z)V
const #26 = InterfaceMethod	#8.#25;	//  scala/actors/scheduler/TerminationMonitor.scala$actors$scheduler$TerminationMonitor$$started_$eq:(Z)V
const #27 = Asciz	$this;
const #28 = Asciz	Lscala/actors/scheduler/TerminationMonitor;;
const #29 = Asciz	LocalVariableTable;
const #30 = Asciz	allTerminated;
const #31 = Asciz	(Lscala/actors/scheduler/TerminationMonitor;)Z;
const #32 = Asciz	scala$actors$scheduler$TerminationMonitor$$started;
const #33 = Asciz	()Z;
const #34 = NameAndType	#32:#33;//  scala$actors$scheduler$TerminationMonitor$$started:()Z
const #35 = InterfaceMethod	#8.#34;	//  scala/actors/scheduler/TerminationMonitor.scala$actors$scheduler$TerminationMonitor$$started:()Z
const #36 = Asciz	scala$actors$scheduler$TerminationMonitor$$pendingReactions;
const #37 = Asciz	()I;
const #38 = NameAndType	#36:#37;//  scala$actors$scheduler$TerminationMonitor$$pendingReactions:()I
const #39 = InterfaceMethod	#8.#38;	//  scala/actors/scheduler/TerminationMonitor.scala$actors$scheduler$TerminationMonitor$$pendingReactions:()I
const #40 = Asciz	scala/runtime/BoxesRunTime;
const #41 = class	#40;	//  scala/runtime/BoxesRunTime
const #42 = Asciz	boxToBoolean;
const #43 = Asciz	(Z)Ljava/lang/Boolean;;
const #44 = NameAndType	#42:#43;//  boxToBoolean:(Z)Ljava/lang/Boolean;
const #45 = Method	#41.#44;	//  scala/runtime/BoxesRunTime.boxToBoolean:(Z)Ljava/lang/Boolean;
const #46 = Asciz	unboxToBoolean;
const #47 = Asciz	(Ljava/lang/Object;)Z;
const #48 = NameAndType	#46:#47;//  unboxToBoolean:(Ljava/lang/Object;)Z
const #49 = Method	#41.#48;	//  scala/runtime/BoxesRunTime.unboxToBoolean:(Ljava/lang/Object;)Z
const #50 = Asciz	terminated;
const #51 = Asciz	(Lscala/actors/scheduler/TerminationMonitor;Lscala/actors/Reactor;)V;
const #52 = Asciz	scala$actors$scheduler$TerminationMonitor$$termHandlers;
const #53 = Asciz	()Lscala/collection/mutable/HashMap;;
const #54 = NameAndType	#52:#53;//  scala$actors$scheduler$TerminationMonitor$$termHandlers:()Lscala/collection/mutable/HashMap;
const #55 = InterfaceMethod	#8.#54;	//  scala/actors/scheduler/TerminationMonitor.scala$actors$scheduler$TerminationMonitor$$termHandlers:()Lscala/collection/mutable/HashMap;
const #56 = Asciz	get;
const #57 = Asciz	(Ljava/lang/Object;)Lscala/Option;;
const #58 = NameAndType	#56:#57;//  get:(Ljava/lang/Object;)Lscala/Option;
const #59 = Method	#14.#58;	//  scala/collection/mutable/HashMap.get:(Ljava/lang/Object;)Lscala/Option;
const #60 = Asciz	scala/Some;
const #61 = class	#60;	//  scala/Some
const #62 = Asciz	x;
const #63 = Asciz	()Ljava/lang/Object;;
const #64 = NameAndType	#62:#63;//  x:()Ljava/lang/Object;
const #65 = Method	#61.#64;	//  scala/Some.x:()Ljava/lang/Object;
const #66 = Asciz	scala/Function0;
const #67 = class	#66;	//  scala/Function0
const #68 = Asciz	$minus$eq;
const #69 = Asciz	(Ljava/lang/Object;)Lscala/collection/mutable/HashMap;;
const #70 = NameAndType	#68:#69;//  $minus$eq:(Ljava/lang/Object;)Lscala/collection/mutable/HashMap;
const #71 = Method	#14.#70;	//  scala/collection/mutable/HashMap.$minus$eq:(Ljava/lang/Object;)Lscala/collection/mutable/HashMap;
const #72 = Asciz	scala/actors/scheduler/TerminationMonitor$$anonfun$1;
const #73 = class	#72;	//  scala/actors/scheduler/TerminationMonitor$$anonfun$1
const #74 = Asciz	(Lscala/actors/scheduler/TerminationMonitor;Lscala/Function0;)V;
const #75 = NameAndType	#15:#74;//  "<init>":(Lscala/actors/scheduler/TerminationMonitor;Lscala/Function0;)V
const #76 = Method	#73.#75;	//  scala/actors/scheduler/TerminationMonitor$$anonfun$1."<init>":(Lscala/actors/scheduler/TerminationMonitor;Lscala/Function0;)V
const #77 = Asciz	scala/None$;
const #78 = class	#77;	//  scala/None$
const #79 = Asciz	MODULE$;
const #80 = Asciz	Lscala/None$;;
const #81 = NameAndType	#79:#80;//  MODULE$:Lscala/None$;
const #82 = Field	#78.#81;	//  scala/None$.MODULE$:Lscala/None$;
const #83 = Asciz	java/lang/Object;
const #84 = class	#83;	//  java/lang/Object
const #85 = Asciz	equals;
const #86 = NameAndType	#85:#47;//  equals:(Ljava/lang/Object;)Z
const #87 = Method	#84.#86;	//  java/lang/Object.equals:(Ljava/lang/Object;)Z
const #88 = Asciz	scala/actors/scheduler/TerminationMonitor$$anonfun$2;
const #89 = class	#88;	//  scala/actors/scheduler/TerminationMonitor$$anonfun$2
const #90 = NameAndType	#15:#4;//  "<init>":(Lscala/actors/scheduler/TerminationMonitor;)V
const #91 = Method	#89.#90;	//  scala/actors/scheduler/TerminationMonitor$$anonfun$2."<init>":(Lscala/actors/scheduler/TerminationMonitor;)V
const #92 = Asciz	apply;
const #93 = NameAndType	#92:#63;//  apply:()Ljava/lang/Object;
const #94 = InterfaceMethod	#67.#93;	//  scala/Function0.apply:()Ljava/lang/Object;
const #95 = Asciz	scala/runtime/BoxedUnit;
const #96 = class	#95;	//  scala/runtime/BoxedUnit
const #97 = Asciz	UNIT;
const #98 = Asciz	Lscala/runtime/BoxedUnit;;
const #99 = NameAndType	#97:#98;//  UNIT:Lscala/runtime/BoxedUnit;
const #100 = Field	#96.#99;	//  scala/runtime/BoxedUnit.UNIT:Lscala/runtime/BoxedUnit;
const #101 = Asciz	scala/MatchError;
const #102 = class	#101;	//  scala/MatchError
const #103 = Asciz	scala/Option;
const #104 = class	#103;	//  scala/Option
const #105 = Asciz	toString;
const #106 = Asciz	()Ljava/lang/String;;
const #107 = NameAndType	#105:#106;//  toString:()Ljava/lang/String;
const #108 = Method	#104.#107;	//  scala/Option.toString:()Ljava/lang/String;
const #109 = Asciz	(Ljava/lang/String;)V;
const #110 = NameAndType	#15:#109;//  "<init>":(Ljava/lang/String;)V
const #111 = Method	#102.#110;	//  scala/MatchError."<init>":(Ljava/lang/String;)V
const #112 = Asciz	a;
const #113 = Asciz	Lscala/actors/Reactor;;
const #114 = Asciz	todo;
const #115 = Asciz	Lscala/Function0;;
const #116 = Asciz	temp1;
const #117 = Asciz	Lscala/Option;;
const #118 = Asciz	temp2;
const #119 = Asciz	Lscala/Some;;
const #120 = Asciz	temp3;
const #121 = Asciz	handler$1;
const #122 = Asciz	onTerminate;
const #123 = Asciz	(Lscala/actors/scheduler/TerminationMonitor;Lscala/actors/Reactor;Lscala/Function0;)V;
const #124 = Asciz	scala/Predef$;
const #125 = class	#124;	//  scala/Predef$
const #126 = Asciz	Lscala/Predef$;;
const #127 = NameAndType	#79:#126;//  MODULE$:Lscala/Predef$;
const #128 = Field	#125.#127;	//  scala/Predef$.MODULE$:Lscala/Predef$;
const #129 = Asciz	any2ArrowAssoc;
const #130 = Asciz	(Ljava/lang/Object;)Lscala/Predef$ArrowAssoc;;
const #131 = NameAndType	#129:#130;//  any2ArrowAssoc:(Ljava/lang/Object;)Lscala/Predef$ArrowAssoc;
const #132 = Method	#125.#131;	//  scala/Predef$.any2ArrowAssoc:(Ljava/lang/Object;)Lscala/Predef$ArrowAssoc;
const #133 = Asciz	scala/Predef$ArrowAssoc;
const #134 = class	#133;	//  scala/Predef$ArrowAssoc
const #135 = Asciz	$minus$greater;
const #136 = Asciz	(Ljava/lang/Object;)Lscala/Tuple2;;
const #137 = NameAndType	#135:#136;//  $minus$greater:(Ljava/lang/Object;)Lscala/Tuple2;
const #138 = Method	#134.#137;	//  scala/Predef$ArrowAssoc.$minus$greater:(Ljava/lang/Object;)Lscala/Tuple2;
const #139 = Asciz	$plus$eq;
const #140 = Asciz	(Lscala/Tuple2;)Lscala/collection/mutable/HashMap;;
const #141 = NameAndType	#139:#140;//  $plus$eq:(Lscala/Tuple2;)Lscala/collection/mutable/HashMap;
const #142 = Method	#14.#141;	//  scala/collection/mutable/HashMap.$plus$eq:(Lscala/Tuple2;)Lscala/collection/mutable/HashMap;
const #143 = Asciz	f;
const #144 = Asciz	newActor;
const #145 = Asciz	Scala;
const #146 = Asciz	InnerClasses;
const #147 = Asciz	scala/Predef;
const #148 = class	#147;	//  scala/Predef
const #149 = Asciz	ArrowAssoc;
const #150 = Asciz	$anonfun$2;
const #151 = Asciz	$anonfun$1;
const #152 = Asciz	scala/actors/scheduler/TerminationMonitor$class;
const #153 = class	#152;	//  scala/actors/scheduler/TerminationMonitor$class

{
public static void $init$(scala.actors.scheduler.TerminationMonitor);
  Code:
   Stack=3, Locals=1, Args_size=1
   0:	aload_0
   1:	iconst_0
   2:	invokeinterface	#12,  2; //InterfaceMethod scala/actors/scheduler/TerminationMonitor.scala$actors$scheduler$TerminationMonitor$$pendingReactions_$eq:(I)V
   7:	aload_0
   8:	new	#14; //class scala/collection/mutable/HashMap
   11:	dup
   12:	invokespecial	#18; //Method scala/collection/mutable/HashMap."<init>":()V
   15:	invokeinterface	#22,  2; //InterfaceMethod scala/actors/scheduler/TerminationMonitor.scala$actors$scheduler$TerminationMonitor$_setter_$scala$actors$scheduler$TerminationMonitor$$termHandlers_$eq:(Lscala/collection/mutable/HashMap;)V
   20:	aload_0
   21:	iconst_0
   22:	invokeinterface	#26,  2; //InterfaceMethod scala/actors/scheduler/TerminationMonitor.scala$actors$scheduler$TerminationMonitor$$started_$eq:(Z)V
   27:	return
  LineNumberTable: 
   line 18: 0
   line 19: 7
   line 20: 20

  LocalVariableTable: 
   Start  Length  Slot  Name   Signature
   0      28      0    $this       Lscala/actors/scheduler/TerminationMonitor;


public static boolean allTerminated(scala.actors.scheduler.TerminationMonitor);
  Code:
   Stack=2, Locals=2, Args_size=1
   0:	aload_0
   1:	dup
   2:	astore_1
   3:	monitorenter
   4:	aload_0
   5:	invokeinterface	#35,  1; //InterfaceMethod scala/actors/scheduler/TerminationMonitor.scala$actors$scheduler$TerminationMonitor$$started:()Z
   10:	ifeq	27
   13:	aload_0
   14:	invokeinterface	#39,  1; //InterfaceMethod scala/actors/scheduler/TerminationMonitor.scala$actors$scheduler$TerminationMonitor$$pendingReactions:()I
   19:	iconst_0
   20:	if_icmpgt	27
   23:	iconst_1
   24:	goto	28
   27:	iconst_0
   28:	invokestatic	#45; //Method scala/runtime/BoxesRunTime.boxToBoolean:(Z)Ljava/lang/Boolean;
   31:	aload_1
   32:	monitorexit
   33:	invokestatic	#49; //Method scala/runtime/BoxesRunTime.unboxToBoolean:(Ljava/lang/Object;)Z
   36:	ireturn
   37:	aload_1
   38:	monitorexit
   39:	athrow
  Exception table:
   from   to  target type
     4    33    37   any
  LineNumberTable: 
   line 59: 0
   line 60: 4
   line 59: 32

  LocalVariableTable: 
   Start  Length  Slot  Name   Signature
   0      40      0    $this       Lscala/actors/scheduler/TerminationMonitor;


public static void terminated(scala.actors.scheduler.TerminationMonitor, scala.actors.Reactor);
  Code:
   Stack=4, Locals=11, Args_size=2
   0:	aload_0
   1:	dup
   2:	astore_2
   3:	monitorenter
   4:	aload_0
   5:	dup
   6:	astore	4
   8:	monitorenter
   9:	aload_0
   10:	invokeinterface	#55,  1; //InterfaceMethod scala/actors/scheduler/TerminationMonitor.scala$actors$scheduler$TerminationMonitor$$termHandlers:()Lscala/collection/mutable/HashMap;
   15:	aload_1
   16:	invokevirtual	#59; //Method scala/collection/mutable/HashMap.get:(Ljava/lang/Object;)Lscala/Option;
   19:	astore	5
   21:	aload	5
   23:	instanceof	#61; //class scala/Some
   26:	ifeq	74
   29:	aload	5
   31:	checkcast	#61; //class scala/Some
   34:	astore	6
   36:	aload	6
   38:	invokevirtual	#65; //Method scala/Some.x:()Ljava/lang/Object;
   41:	checkcast	#67; //class scala/Function0
   44:	astore	7
   46:	aload	7
   48:	astore	8
   50:	aload_0
   51:	invokeinterface	#55,  1; //InterfaceMethod scala/actors/scheduler/TerminationMonitor.scala$actors$scheduler$TerminationMonitor$$termHandlers:()Lscala/collection/mutable/HashMap;
   56:	aload_1
   57:	invokevirtual	#71; //Method scala/collection/mutable/HashMap.$minus$eq:(Ljava/lang/Object;)Lscala/collection/mutable/HashMap;
   60:	pop
   61:	new	#73; //class scala/actors/scheduler/TerminationMonitor$$anonfun$1
   64:	dup
   65:	aload_0
   66:	aload	8
   68:	invokespecial	#76; //Method scala/actors/scheduler/TerminationMonitor$$anonfun$1."<init>":(Lscala/actors/scheduler/TerminationMonitor;Lscala/Function0;)V
   71:	goto	118
   74:	getstatic	#82; //Field scala/None$.MODULE$:Lscala/None$;
   77:	aload	5
   79:	astore	9
   81:	dup
   82:	ifnonnull	94
   85:	pop
   86:	aload	9
   88:	ifnull	102
   91:	goto	161
   94:	aload	9
   96:	invokevirtual	#87; //Method java/lang/Object.equals:(Ljava/lang/Object;)Z
   99:	ifeq	161
   102:	aload	5
   104:	instanceof	#78; //class scala/None$
   107:	ifeq	161
   110:	new	#89; //class scala/actors/scheduler/TerminationMonitor$$anonfun$2
   113:	dup
   114:	aload_0
   115:	invokespecial	#91; //Method scala/actors/scheduler/TerminationMonitor$$anonfun$2."<init>":(Lscala/actors/scheduler/TerminationMonitor;)V
   118:	aload	4
   120:	monitorexit
   121:	checkcast	#67; //class scala/Function0
   124:	astore_3
   125:	aload_3
   126:	invokeinterface	#94,  1; //InterfaceMethod scala/Function0.apply:()Ljava/lang/Object;
   131:	pop
   132:	aload_0
   133:	dup
   134:	astore	10
   136:	monitorenter
   137:	aload_0
   138:	aload_0
   139:	invokeinterface	#39,  1; //InterfaceMethod scala/actors/scheduler/TerminationMonitor.scala$actors$scheduler$TerminationMonitor$$pendingReactions:()I
   144:	iconst_1
   145:	isub
   146:	invokeinterface	#12,  2; //InterfaceMethod scala/actors/scheduler/TerminationMonitor.scala$actors$scheduler$TerminationMonitor$$pendingReactions_$eq:(I)V
   151:	getstatic	#100; //Field scala/runtime/BoxedUnit.UNIT:Lscala/runtime/BoxedUnit;
   154:	pop
   155:	aload	10
   157:	monitorexit
   158:	aload_2
   159:	monitorexit
   160:	return
   161:	new	#102; //class scala/MatchError
   164:	dup
   165:	aload	5
   167:	invokevirtual	#108; //Method scala/Option.toString:()Ljava/lang/String;
   170:	invokespecial	#111; //Method scala/MatchError."<init>":(Ljava/lang/String;)V
   173:	athrow
   174:	aload	4
   176:	monitorexit
   177:	athrow
   178:	aload	10
   180:	monitorexit
   181:	athrow
   182:	aload_2
   183:	monitorexit
   184:	athrow
  Exception table:
   from   to  target type
   137   158   178   any
     9   121   174   any
   161   174   174   any
     4   160   182   any
   161   182   182   any
  LineNumberTable: 
   line 39: 0
   line 41: 4
   line 42: 9
   line 43: 46
   line 44: 50
   line 45: 61
   line 42: 74
   line 47: 110
   line 55: 118
   line 41: 120
   line 55: 121
   line 41: 124
   line 52: 125
   line 54: 132
   line 55: 137
   line 54: 157
   line 39: 158
   line 42: 161
   line 41: 176
   line 54: 180
   line 39: 183

  LocalVariableTable: 
   Start  Length  Slot  Name   Signature
   0      185      0    $this       Lscala/actors/scheduler/TerminationMonitor;
   0      185      1    a       Lscala/actors/Reactor;
   125      35      3    todo       Lscala/Function0;
   178      4      3    todo       Lscala/Function0;
   21      100      5    temp1       Lscala/Option;
   161      13      5    temp1       Lscala/Option;
   36      35      6    temp2       Lscala/Some;
   46      25      7    temp3       Lscala/Function0;
   50      21      8    handler$1       Lscala/Function0;


public static void onTerminate(scala.actors.scheduler.TerminationMonitor, scala.actors.Reactor, scala.Function0);
  Code:
   Stack=3, Locals=4, Args_size=3
   0:	aload_0
   1:	dup
   2:	astore_3
   3:	monitorenter
   4:	aload_0
   5:	invokeinterface	#55,  1; //InterfaceMethod scala/actors/scheduler/TerminationMonitor.scala$actors$scheduler$TerminationMonitor$$termHandlers:()Lscala/collection/mutable/HashMap;
   10:	getstatic	#128; //Field scala/Predef$.MODULE$:Lscala/Predef$;
   13:	aload_1
   14:	invokevirtual	#132; //Method scala/Predef$.any2ArrowAssoc:(Ljava/lang/Object;)Lscala/Predef$ArrowAssoc;
   17:	aload_2
   18:	invokevirtual	#138; //Method scala/Predef$ArrowAssoc.$minus$greater:(Ljava/lang/Object;)Lscala/Tuple2;
   21:	invokevirtual	#142; //Method scala/collection/mutable/HashMap.$plus$eq:(Lscala/Tuple2;)Lscala/collection/mutable/HashMap;
   24:	pop
   25:	aload_3
   26:	monitorexit
   27:	return
   28:	aload_3
   29:	monitorexit
   30:	athrow
  Exception table:
   from   to  target type
     4    27    28   any
  LineNumberTable: 
   line 35: 0
   line 36: 4
   line 35: 26

  LocalVariableTable: 
   Start  Length  Slot  Name   Signature
   0      31      0    $this       Lscala/actors/scheduler/TerminationMonitor;
   0      31      1    a       Lscala/actors/Reactor;
   0      31      2    f       Lscala/Function0;


public static void newActor(scala.actors.scheduler.TerminationMonitor, scala.actors.Reactor);
  Code:
   Stack=3, Locals=3, Args_size=2
   0:	aload_0
   1:	dup
   2:	astore_2
   3:	monitorenter
   4:	aload_0
   5:	aload_0
   6:	invokeinterface	#39,  1; //InterfaceMethod scala/actors/scheduler/TerminationMonitor.scala$actors$scheduler$TerminationMonitor$$pendingReactions:()I
   11:	iconst_1
   12:	iadd
   13:	invokeinterface	#12,  2; //InterfaceMethod scala/actors/scheduler/TerminationMonitor.scala$actors$scheduler$TerminationMonitor$$pendingReactions_$eq:(I)V
   18:	aload_0
   19:	invokeinterface	#35,  1; //InterfaceMethod scala/actors/scheduler/TerminationMonitor.scala$actors$scheduler$TerminationMonitor$$started:()Z
   24:	ifeq	33
   27:	getstatic	#100; //Field scala/runtime/BoxedUnit.UNIT:Lscala/runtime/BoxedUnit;
   30:	goto	43
   33:	aload_0
   34:	iconst_1
   35:	invokeinterface	#26,  2; //InterfaceMethod scala/actors/scheduler/TerminationMonitor.scala$actors$scheduler$TerminationMonitor$$started_$eq:(Z)V
   40:	getstatic	#100; //Field scala/runtime/BoxedUnit.UNIT:Lscala/runtime/BoxedUnit;
   43:	pop
   44:	aload_2
   45:	monitorexit
   46:	return
   47:	aload_2
   48:	monitorexit
   49:	athrow
  Exception table:
   from   to  target type
     4    46    47   any
  LineNumberTable: 
   line 23: 0
   line 24: 4
   line 25: 18
   line 26: 33
   line 25: 43
   line 23: 45

  LocalVariableTable: 
   Start  Length  Slot  Name   Signature
   0      50      0    $this       Lscala/actors/scheduler/TerminationMonitor;
   0      50      1    a       Lscala/actors/Reactor;


}

