Compiled from "TerminationService.scala"
public abstract class scala.actors.scheduler.TerminationService$class extends java.lang.Object
  SourceFile: "TerminationService.scala"
  Scala: length = 0x
   
  minor version: 0
  major version: 49
  Constant pool:
Asciz	SourceFile;
Asciz	TerminationService.scala;
Asciz	run;
Asciz	(Ljava/lang/Thread;)V;
Asciz	Code;
Asciz	LineNumberTable;
Asciz	scala/actors/scheduler/TerminationService$class;
class	scala/actors/scheduler/TerminationService$class
Asciz	liftedTree1$1;
NameAndType	liftedTree1$1:(Ljava/lang/Thread;)V
Method	scala/actors/scheduler/TerminationService$class.liftedTree1$1:(Ljava/lang/Thread;)V
Asciz	scala/actors/scheduler/TerminationService;
class	scala/actors/scheduler/TerminationService
Asciz	scala$actors$scheduler$TerminationService$$terminating;
Asciz	()Z;
NameAndType	scala$actors$scheduler$TerminationService$$terminating:()Z
InterfaceMethod	scala/actors/scheduler/TerminationService.scala$actors$scheduler$TerminationService$$terminating:()Z
Asciz	terminate;
NameAndType	terminate:()Z
InterfaceMethod	scala/actors/scheduler/TerminationService.terminate:()Z
Asciz	scala/actors/scheduler/TerminationMonitor;
class	scala/actors/scheduler/TerminationMonitor
Asciz	allActorsTerminated;
NameAndType	allActorsTerminated:()Z
InterfaceMethod	scala/actors/scheduler/TerminationMonitor.allActorsTerminated:()Z
Asciz	scala/actors/scheduler/QuitControl;
class	scala/actors/scheduler/QuitControl
Asciz	<init>;
Asciz	()V;
NameAndType	"<init>":()V
Method	scala/actors/scheduler/QuitControl."<init>":()V
Asciz	gc;
NameAndType	gc:()V
InterfaceMethod	scala/actors/scheduler/TerminationMonitor.gc:()V
Asciz	scala/actors/Debug$;
class	scala/actors/Debug$
Asciz	MODULE$;
Asciz	Lscala/actors/Debug$;;
NameAndType	MODULE$:Lscala/actors/Debug$;
Field	scala/actors/Debug$.MODULE$:Lscala/actors/Debug$;
Asciz	scala/runtime/StringAdd;
class	scala/runtime/StringAdd
Asciz	(Ljava/lang/Object;)V;
NameAndType	"<init>":(Ljava/lang/Object;)V
Method	scala/runtime/StringAdd."<init>":(Ljava/lang/Object;)V
Asciz	: initiating shutdown...;
String	: initiating shutdown...
Asciz	$plus;
Asciz	(Ljava/lang/String;)Ljava/lang/String;;
NameAndType	$plus:(Ljava/lang/String;)Ljava/lang/String;
Method	scala/runtime/StringAdd.$plus:(Ljava/lang/String;)Ljava/lang/String;
Asciz	info;
Asciz	(Ljava/lang/String;)V;
NameAndType	info:(Ljava/lang/String;)V
Method	scala/actors/Debug$.info:(Ljava/lang/String;)V
Asciz	onShutdown;
NameAndType	onShutdown:()V
InterfaceMethod	scala/actors/scheduler/TerminationService.onShutdown:()V
Asciz	$this;
Asciz	Ljava/lang/Thread;;
Asciz	LocalVariableTable;
Asciz	shutdown;
Asciz	scala$actors$scheduler$TerminationService$$terminating_$eq;
Asciz	(Z)V;
NameAndType	scala$actors$scheduler$TerminationService$$terminating_$eq:(Z)V
InterfaceMethod	scala/actors/scheduler/TerminationService.scala$actors$scheduler$TerminationService$$terminating_$eq:(Z)V
Asciz	CHECK_FREQ;
Asciz	()I;
NameAndType	CHECK_FREQ:()I
InterfaceMethod	scala/actors/scheduler/TerminationService.CHECK_FREQ:()I
Asciz	java/lang/Thread;
class	java/lang/Thread
Asciz	wait;
Asciz	(J)V;
NameAndType	wait:(J)V
Method	java/lang/Thread.wait:(J)V
Asciz	java/lang/InterruptedException;
class	java/lang/InterruptedException
Asciz	$init$;
Asciz	scala$actors$scheduler$TerminationService$_setter_$terminate_$eq;
NameAndType	scala$actors$scheduler$TerminationService$_setter_$terminate_$eq:(Z)V
InterfaceMethod	scala/actors/scheduler/TerminationService.scala$actors$scheduler$TerminationService$_setter_$terminate_$eq:(Z)V
int	50;
Asciz	scala$actors$scheduler$TerminationService$_setter_$CHECK_FREQ_$eq;
Asciz	(I)V;
NameAndType	scala$actors$scheduler$TerminationService$_setter_$CHECK_FREQ_$eq:(I)V
InterfaceMethod	scala/actors/scheduler/TerminationService.scala$actors$scheduler$TerminationService$_setter_$CHECK_FREQ_$eq:(I)V
Asciz	Scala;
Asciz	java/lang/Object;
class	java/lang/Object

{
public static void run(java.lang.Thread);
  Signature: (Ljava/lang/Thread;)V
  Code:
   Stack=4, Locals=1, Args_size=1
l3	aload_0
	dup
	pop
	monitorenter
	aload_0
	invokestatic	Method liftedTree1$1:(Ljava/lang/Thread;)V
	aload_0
	checkcast	class scala/actors/scheduler/TerminationService
	invokeinterface	InterfaceMethod scala/actors/scheduler/TerminationService.scala$actors$scheduler$TerminationService$$terminating:()Z
	ifne	l1 // new
	aload_0
	checkcast	class scala/actors/scheduler/TerminationService
	invokeinterface	InterfaceMethod scala/actors/scheduler/TerminationService.terminate:()Z
	ifeq	l2 // aload_0
	aload_0
	checkcast	class scala/actors/scheduler/TerminationMonitor
	invokeinterface	InterfaceMethod scala/actors/scheduler/TerminationMonitor.allActorsTerminated:()Z
	ifeq	l2 // aload_0
l1	new	class scala/actors/scheduler/QuitControl
	dup
	invokespecial	Method scala/actors/scheduler/QuitControl."<init>":()V
	athrow
l2	aload_0
	checkcast	class scala/actors/scheduler/TerminationMonitor
	invokeinterface	InterfaceMethod scala/actors/scheduler/TerminationMonitor.gc:()V
	aload_0
	monitorexit
	goto	l3 // aload_0
	aload_0
	monitorexit
	athrow
	pop
	getstatic	Field scala/actors/Debug$.MODULE$:Lscala/actors/Debug$;
	new	class scala/runtime/StringAdd
	dup
	aload_0
	invokespecial	Method scala/runtime/StringAdd."<init>":(Ljava/lang/Object;)V
	ldc	String : initiating shutdown...
	invokevirtual	Method scala/runtime/StringAdd.$plus:(Ljava/lang/String;)Ljava/lang/String;
	invokevirtual	Method scala/actors/Debug$.info:(Ljava/lang/String;)V
	aload_0
	checkcast	class scala/actors/scheduler/TerminationService
	invokeinterface	InterfaceMethod scala/actors/scheduler/TerminationService.onShutdown:()V
	return
  Labels:
   	l3 = 0 // aload_0
   	l1 = 44 // new
   	l2 = 52 // aload_0
  Exception table:
   from   to  target type
     4    66    66   any
     0    69    69   Class scala/actors/scheduler/QuitControl

  LocalVariableTable: 
   Start  Length  Slot  Name   Signature
   0      99      0    $this       Ljava/lang/Thread;


public static void shutdown(java.lang.Thread);
  Signature: (Ljava/lang/Thread;)V
  Code:
   Stack=2, Locals=1, Args_size=1
	aload_0
	dup
	pop
	monitorenter
	aload_0
	checkcast	class scala/actors/scheduler/TerminationService
	iconst_1
	invokeinterface	InterfaceMethod scala/actors/scheduler/TerminationService.scala$actors$scheduler$TerminationService$$terminating_$eq:(Z)V
	aload_0
	monitorexit
	return
	aload_0
	monitorexit
	athrow
  Labels:
  Exception table:
   from   to  target type
     4    16    17   any
  LocalVariableTable: 
   Start  Length  Slot  Name   Signature
   0      20      0    $this       Ljava/lang/Thread;


private static final void liftedTree1$1(java.lang.Thread);
  Signature: (Ljava/lang/Thread;)V
  Code:
   Stack=3, Locals=1, Args_size=1
	aload_0
	aload_0
	checkcast	class scala/actors/scheduler/TerminationService
	invokeinterface	InterfaceMethod scala/actors/scheduler/TerminationService.CHECK_FREQ:()I
	i2l
	invokevirtual	Method java/lang/Thread.wait:(J)V
	goto	l1 // return
	pop
l1	return
  Labels:
   	l1 = 18 // return
  Exception table:
   from   to  target type
     0    17    17   Class java/lang/InterruptedException

  LocalVariableTable: 
   Start  Length  Slot  Name   Signature
   0      19      0    $this       Ljava/lang/Thread;


public static void $init$(java.lang.Thread);
  Signature: (Ljava/lang/Thread;)V
  Code:
   Stack=2, Locals=1, Args_size=1
	aload_0
	checkcast	class scala/actors/scheduler/TerminationService
	iconst_0
	invokeinterface	InterfaceMethod scala/actors/scheduler/TerminationService.scala$actors$scheduler$TerminationService$$terminating_$eq:(Z)V
	aload_0
	checkcast	class scala/actors/scheduler/TerminationService
	iconst_1
	invokeinterface	InterfaceMethod scala/actors/scheduler/TerminationService.scala$actors$scheduler$TerminationService$_setter_$terminate_$eq:(Z)V
	aload_0
	checkcast	class scala/actors/scheduler/TerminationService
	ldc	int 50
	invokeinterface	InterfaceMethod scala/actors/scheduler/TerminationService.scala$actors$scheduler$TerminationService$_setter_$CHECK_FREQ_$eq:(I)V
	return
  Labels:
  LocalVariableTable: 
   Start  Length  Slot  Name   Signature
   0      32      0    $this       Ljava/lang/Thread;


}

