Compiled from "ThreadPoolScheduler.scala"
public class scala.actors.scheduler.ThreadPoolScheduler extends java.lang.Thread implements scala.actors.scheduler.ExecutorScheduler,scala.actors.scheduler.TerminationMonitor,scala.ScalaObject
  SourceFile: "ThreadPoolScheduler.scala"
  ScalaSig: length = 0x2B9
   05 00 5E 06 08 01 02 FFFFFF84 FFFFFF80 FFFFFF80 FFFFFF80 00 09 02 13 54
   68 72 65 61 64 50 6F 6F 6C 53 63 68 65 64 75 6C
   65 72 0A 02 03 04 01 09 73 63 68 65 64 75 6C 65
   72 0A 02 05 06 01 06 61 63 74 6F 72 73 0A 01 07
   01 05 73 63 61 6C 61 03 00 13 05 00 0A 12 16 19
   10 02 0B 10 0D 01 0C 0A 02 0D 0E 01 04 6C 61 6E
   67 0A 01 0F 01 04 6A 61 76 61 09 02 11 0C 02 06
   54 68 72 65 61 64 10 02 13 14 0D 01 02 09 02 15
   02 02 11 45 78 65 63 75 74 6F 72 53 63 68 65 64
   75 6C 65 72 10 02 13 17 09 02 18 02 02 12 54 65
   72 6D 69 6E 61 74 69 6F 6E 4D 6F 6E 69 74 6F 72
   10 02 1A 1B 0D 01 06 09 02 1C 06 02 0B 53 63 61
   6C 61 4F 62 6A 65 63 74 08 08 1E 00 FFFFFF82 FFFFFFC0 FFFFFF80 FFFFFF84
   08 1F 01 08 65 78 65 63 75 74 6F 72 15 01 20 10
   02 21 26 0D 01 22 0A 02 23 24 01 0A 63 6F 6E 63
   75 72 72 65 6E 74 0A 02 25 0E 01 04 75 74 69 6C
   09 02 27 22 02 12 54 68 72 65 61 64 50 6F 6F 6C
   45 78 65 63 75 74 6F 72 08 08 29 00 FFFFFF82 FFFFFFC0 FFFFFF80 FFFFFF84
   08 2A 01 0C 65 78 65 63 75 74 6F 72 5F 24 65 71
   14 02 2B 2E 10 02 1A 2C 09 02 2D 06 02 04 55 6E
   69 74 08 07 2F 28 FFFFFF81 FFFFFF80 FFFFFFC0 00 20 01 03 78 24 31
   08 08 31 00 FFFFFF82 FFFFFF80 FFFFFFA0 FFFFFFA0 04 20 01 09 65 78 65 63
   75 74 6F 72 20 08 08 33 00 FFFFFF82 FFFFFFC2 FFFFFF80 FFFFFF84 08 34 01
   09 74 65 72 6D 69 6E 61 74 65 15 01 35 10 02 1A
   36 09 02 37 06 02 07 42 6F 6F 6C 65 61 6E 08 08
   39 00 FFFFFF82 FFFFFF80 FFFFFFA0 FFFFFF80 04 35 01 0A 74 65 72 6D 69 6E
   61 74 65 20 08 08 3B 00 FFFFFF82 FFFFFFC2 FFFFFF80 FFFFFF84 08 34 01 06
   64 61 65 6D 6F 6E 08 08 3D 00 FFFFFF82 FFFFFF80 FFFFFFA0 FFFFFF80 04 35
   01 07 64 61 65 6D 6F 6E 20 08 05 3F 00 FFFFFF84 00 40
   01 06 3C 69 6E 69 74 3E 14 04 41 42 43 44 10 02
   13 00 08 05 1E 3E FFFFFFC0 00 20 08 05 33 3E FFFFFFC0 00 35
   08 05 3B 3E FFFFFFC0 00 35 08 07 46 00 FFFFFFC0 FFFFFF80 FFFFFF84 04 34
   01 0B 74 65 72 6D 69 6E 61 74 69 6E 67 08 07 48
   00 FFFFFFC0 FFFFFF80 FFFFFF84 04 49 01 0F 74 65 72 6D 69 6E 61 74
   69 6E 67 5F 24 65 71 14 02 2B 4A 08 07 2F 47 FFFFFF81
   FFFFFF80 FFFFFFC0 00 35 08 06 4C 00 FFFFFFA0 FFFFFFA0 04 35 01 0C 74 65
   72 6D 69 6E 61 74 69 6E 67 20 08 07 4E 00 FFFFFFC2 FFFFFF80
   FFFFFF84 08 4F 01 0A 43 48 45 43 4B 5F 46 52 45 51 15
   01 50 10 02 1A 51 09 02 52 06 02 03 49 6E 74 08
   06 54 00 FFFFFFA0 FFFFFF80 04 50 01 0B 43 48 45 43 4B 5F 46
   52 45 51 20 08 05 3F 00 FFFFFF84 00 56 14 02 41 57 08
   05 58 55 FFFFFFC0 00 35 01 01 64 08 05 5A 00 FFFFFF84 20 5B
   01 03 72 75 6E 14 01 2B 08 05 5D 00 FFFFFF84 00 5B 01
   08 73 68 75 74 64 6F 77 6E 
  minor version: 0
  major version: 49
  Constant pool:
Asciz	SourceFile;
Asciz	ThreadPoolScheduler.scala;
Asciz	scala$actors$scheduler$TerminationMonitor$$started;
Asciz	Z;
Asciz	terminationHandlers;
Asciz	Lscala/collection/mutable/HashMap;;
Asciz	activeActors;
Asciz	I;
Asciz	CHECK_FREQ;
Asciz	terminating;
Asciz	daemon;
Asciz	terminate;
Asciz	executor;
Asciz	Ljava/util/concurrent/ThreadPoolExecutor;;
Asciz	<init>;
Asciz	(Ljava/util/concurrent/ThreadPoolExecutor;ZZ)V;
Asciz	Code;
Asciz	LineNumberTable;
Asciz	scala/actors/scheduler/ThreadPoolScheduler;
class	scala/actors/scheduler/ThreadPoolScheduler
NameAndType	executor:Ljava/util/concurrent/ThreadPoolExecutor;
Field	scala/actors/scheduler/ThreadPoolScheduler.executor:Ljava/util/concurrent/ThreadPoolExecutor;
NameAndType	terminate:Z
Field	scala/actors/scheduler/ThreadPoolScheduler.terminate:Z
NameAndType	daemon:Z
Field	scala/actors/scheduler/ThreadPoolScheduler.daemon:Z
Asciz	java/lang/Thread;
class	java/lang/Thread
Asciz	()V;
NameAndType	"<init>":()V
Method	java/lang/Thread."<init>":()V
Asciz	scala/actors/IScheduler$class;
class	scala/actors/IScheduler$class
Asciz	$init$;
Asciz	(Lscala/actors/IScheduler;)V;
NameAndType	$init$:(Lscala/actors/IScheduler;)V
Method	scala/actors/IScheduler$class.$init$:(Lscala/actors/IScheduler;)V
Asciz	scala/concurrent/TaskRunner$class;
class	scala/concurrent/TaskRunner$class
Asciz	(Lscala/concurrent/TaskRunner;)V;
NameAndType	$init$:(Lscala/concurrent/TaskRunner;)V
Method	scala/concurrent/TaskRunner$class.$init$:(Lscala/concurrent/TaskRunner;)V
Asciz	scala/concurrent/ThreadPoolRunner$class;
class	scala/concurrent/ThreadPoolRunner$class
Asciz	(Lscala/concurrent/ThreadPoolRunner;)V;
NameAndType	$init$:(Lscala/concurrent/ThreadPoolRunner;)V
Method	scala/concurrent/ThreadPoolRunner$class.$init$:(Lscala/concurrent/ThreadPoolRunner;)V
Asciz	scala/actors/scheduler/ExecutorScheduler$class;
class	scala/actors/scheduler/ExecutorScheduler$class
Asciz	(Lscala/actors/scheduler/ExecutorScheduler;)V;
NameAndType	$init$:(Lscala/actors/scheduler/ExecutorScheduler;)V
Method	scala/actors/scheduler/ExecutorScheduler$class.$init$:(Lscala/actors/scheduler/ExecutorScheduler;)V
Asciz	scala/actors/scheduler/TerminationMonitor$class;
class	scala/actors/scheduler/TerminationMonitor$class
Asciz	(Lscala/actors/scheduler/TerminationMonitor;)V;
NameAndType	$init$:(Lscala/actors/scheduler/TerminationMonitor;)V
Method	scala/actors/scheduler/TerminationMonitor$class.$init$:(Lscala/actors/scheduler/TerminationMonitor;)V
Asciz	setDaemon;
Asciz	(Z)V;
NameAndType	setDaemon:(Z)V
Method	scala/actors/scheduler/ThreadPoolScheduler.setDaemon:(Z)V
NameAndType	terminating:Z
Field	scala/actors/scheduler/ThreadPoolScheduler.terminating:Z
int	10;
NameAndType	CHECK_FREQ:I
Field	scala/actors/scheduler/ThreadPoolScheduler.CHECK_FREQ:I
Asciz	this;
Asciz	Lscala/actors/scheduler/ThreadPoolScheduler;;
Asciz	LocalVariableTable;
Asciz	liftedTree1$1;
Asciz	()I;
NameAndType	CHECK_FREQ:()I
Method	scala/actors/scheduler/ThreadPoolScheduler.CHECK_FREQ:()I
Asciz	wait;
Asciz	(J)V;
NameAndType	wait:(J)V
Method	scala/actors/scheduler/ThreadPoolScheduler.wait:(J)V
Asciz	java/lang/InterruptedException;
class	java/lang/InterruptedException
Asciz	()Ljava/util/concurrent/ExecutorService;;
Asciz	()Ljava/util/concurrent/ThreadPoolExecutor;;
NameAndType	executor:()Ljava/util/concurrent/ThreadPoolExecutor;
Method	scala/actors/scheduler/ThreadPoolScheduler.executor:()Ljava/util/concurrent/ThreadPoolExecutor;
Asciz	functionAsTask;
Asciz	(Lscala/Function0;)Ljava/lang/Object;;
Asciz	scala/concurrent/ThreadPoolRunner;
class	scala/concurrent/ThreadPoolRunner
Asciz	(Lscala/Function0;)Ljava/util/concurrent/Callable;;
NameAndType	functionAsTask:(Lscala/Function0;)Ljava/util/concurrent/Callable;
InterfaceMethod	scala/concurrent/ThreadPoolRunner.functionAsTask:(Lscala/Function0;)Ljava/util/concurrent/Callable;
Asciz	fun;
Asciz	Lscala/Function0;;
Asciz	futureAsFunction;
Asciz	(Ljava/lang/Object;)Lscala/Function0;;
Asciz	java/util/concurrent/Future;
class	java/util/concurrent/Future
Asciz	(Ljava/util/concurrent/Future;)Lscala/Function0;;
NameAndType	futureAsFunction:(Ljava/util/concurrent/Future;)Lscala/Function0;
InterfaceMethod	scala/concurrent/ThreadPoolRunner.futureAsFunction:(Ljava/util/concurrent/Future;)Lscala/Function0;
Asciz	x;
Asciz	Ljava/lang/Object;;
Asciz	submit;
Asciz	(Ljava/lang/Object;)Ljava/lang/Object;;
Asciz	java/util/concurrent/Callable;
class	java/util/concurrent/Callable
Asciz	(Ljava/util/concurrent/Callable;)Ljava/util/concurrent/Future;;
NameAndType	submit:(Ljava/util/concurrent/Callable;)Ljava/util/concurrent/Future;
InterfaceMethod	scala/concurrent/ThreadPoolRunner.submit:(Ljava/util/concurrent/Callable;)Ljava/util/concurrent/Future;
Asciz	task;
Asciz	execute;
Asciz	(Ljava/lang/Object;)V;
Asciz	(Ljava/util/concurrent/Callable;)V;
NameAndType	execute:(Ljava/util/concurrent/Callable;)V
InterfaceMethod	scala/concurrent/ThreadPoolRunner.execute:(Ljava/util/concurrent/Callable;)V
Asciz	shutdown;
Asciz	terminating_$eq;
NameAndType	terminating_$eq:(Z)V
Method	scala/actors/scheduler/ThreadPoolScheduler.terminating_$eq:(Z)V
Asciz	java/lang/Throwable;
class	java/lang/Throwable
Asciz	run;
NameAndType	liftedTree1$1:()V
Method	scala/actors/scheduler/ThreadPoolScheduler.liftedTree1$1:()V
Asciz	()Z;
NameAndType	terminating:()Z
Method	scala/actors/scheduler/ThreadPoolScheduler.terminating:()Z
NameAndType	terminate:()Z
Method	scala/actors/scheduler/ThreadPoolScheduler.terminate:()Z
Asciz	scala/actors/scheduler/TerminationMonitor;
class	scala/actors/scheduler/TerminationMonitor
Asciz	allTerminated;
NameAndType	allTerminated:()Z
InterfaceMethod	scala/actors/scheduler/TerminationMonitor.allTerminated:()Z
Asciz	scala/actors/scheduler/QuitException;
class	scala/actors/scheduler/QuitException
Method	scala/actors/scheduler/QuitException."<init>":()V
Asciz	gc;
NameAndType	gc:()V
InterfaceMethod	scala/actors/scheduler/TerminationMonitor.gc:()V
Asciz	scala/actors/Debug$;
class	scala/actors/Debug$
Asciz	MODULE$;
Asciz	Lscala/actors/Debug$;;
NameAndType	MODULE$:Lscala/actors/Debug$;
Field	scala/actors/Debug$.MODULE$:Lscala/actors/Debug$;
Asciz	scala/runtime/StringAdd;
class	scala/runtime/StringAdd
NameAndType	"<init>":(Ljava/lang/Object;)V
Method	scala/runtime/StringAdd."<init>":(Ljava/lang/Object;)V
Asciz	: initiating shutdown...;
String	: initiating shutdown...
Asciz	$plus;
Asciz	(Ljava/lang/String;)Ljava/lang/String;;
NameAndType	$plus:(Ljava/lang/String;)Ljava/lang/String;
Method	scala/runtime/StringAdd.$plus:(Ljava/lang/String;)Ljava/lang/String;
Asciz	info;
Asciz	(Ljava/lang/String;)V;
NameAndType	info:(Ljava/lang/String;)V
Method	scala/actors/Debug$.info:(Ljava/lang/String;)V
Asciz	scala/actors/scheduler/ExecutorScheduler;
class	scala/actors/scheduler/ExecutorScheduler
Asciz	onShutdown;
NameAndType	onShutdown:()V
InterfaceMethod	scala/actors/scheduler/ExecutorScheduler.onShutdown:()V
NameAndType	"<init>":(Ljava/util/concurrent/ThreadPoolExecutor;ZZ)V
Method	scala/actors/scheduler/ThreadPoolScheduler."<init>":(Ljava/util/concurrent/ThreadPoolExecutor;ZZ)V
Asciz	d;
Asciz	executor_$eq;
Asciz	(Ljava/util/concurrent/ThreadPoolExecutor;)V;
Asciz	printActorDump;
NameAndType	printActorDump:(Lscala/actors/IScheduler;)V
Method	scala/actors/IScheduler$class.printActorDump:(Lscala/actors/IScheduler;)V
Asciz	onLockup;
Asciz	(ILscala/Function0;)V;
Asciz	(Lscala/actors/IScheduler;ILscala/Function0;)V;
NameAndType	onLockup:(Lscala/actors/IScheduler;ILscala/Function0;)V
Method	scala/actors/IScheduler$class.onLockup:(Lscala/actors/IScheduler;ILscala/Function0;)V
Asciz	millis;
Asciz	handler;
Asciz	(Lscala/Function0;)V;
Asciz	(Lscala/actors/IScheduler;Lscala/Function0;)V;
NameAndType	onLockup:(Lscala/actors/IScheduler;Lscala/Function0;)V
Method	scala/actors/IScheduler$class.onLockup:(Lscala/actors/IScheduler;Lscala/Function0;)V
Asciz	tick;
Asciz	(Lscala/actors/Actor;)V;
Asciz	(Lscala/actors/IScheduler;Lscala/actors/Actor;)V;
NameAndType	tick:(Lscala/actors/IScheduler;Lscala/actors/Actor;)V
Method	scala/actors/IScheduler$class.tick:(Lscala/actors/IScheduler;Lscala/actors/Actor;)V
Asciz	a;
Asciz	Lscala/actors/Actor;;
Asciz	executeFromActor;
Asciz	(Ljava/lang/Runnable;)V;
Asciz	(Lscala/actors/IScheduler;Ljava/lang/Runnable;)V;
NameAndType	executeFromActor:(Lscala/actors/IScheduler;Ljava/lang/Runnable;)V
Method	scala/actors/IScheduler$class.executeFromActor:(Lscala/actors/IScheduler;Ljava/lang/Runnable;)V
Asciz	Ljava/lang/Runnable;;
Asciz	tryCatch;
Asciz	(Lscala/Function0;)Lscala/Either;;
Asciz	(Lscala/concurrent/TaskRunner;Lscala/Function0;)Lscala/Either;;
NameAndType	tryCatch:(Lscala/concurrent/TaskRunner;Lscala/Function0;)Lscala/Either;
Method	scala/concurrent/TaskRunner$class.tryCatch:(Lscala/concurrent/TaskRunner;Lscala/Function0;)Lscala/Either;
Asciz	body;
Asciz	managedBlock;
Asciz	(Lscala/concurrent/ManagedBlocker;)V;
Asciz	(Lscala/concurrent/ThreadPoolRunner;Lscala/concurrent/ManagedBlocker;)V;
NameAndType	managedBlock:(Lscala/concurrent/ThreadPoolRunner;Lscala/concurrent/ManagedBlocker;)V
Method	scala/concurrent/ThreadPoolRunner$class.managedBlock:(Lscala/concurrent/ThreadPoolRunner;Lscala/concurrent/ManagedBlocker;)V
Asciz	blocker;
Asciz	Lscala/concurrent/ManagedBlocker;;
Asciz	(Lscala/concurrent/ThreadPoolRunner;Ljava/util/concurrent/Callable;)V;
NameAndType	execute:(Lscala/concurrent/ThreadPoolRunner;Ljava/util/concurrent/Callable;)V
Method	scala/concurrent/ThreadPoolRunner$class.execute:(Lscala/concurrent/ThreadPoolRunner;Ljava/util/concurrent/Callable;)V
Asciz	Ljava/util/concurrent/Callable;;
Asciz	(Lscala/concurrent/ThreadPoolRunner;Ljava/util/concurrent/Callable;)Ljava/util/concurrent/Future;;
NameAndType	submit:(Lscala/concurrent/ThreadPoolRunner;Ljava/util/concurrent/Callable;)Ljava/util/concurrent/Future;
Method	scala/concurrent/ThreadPoolRunner$class.submit:(Lscala/concurrent/ThreadPoolRunner;Ljava/util/concurrent/Callable;)Ljava/util/concurrent/Future;
Asciz	(Lscala/concurrent/ThreadPoolRunner;Ljava/util/concurrent/Future;)Lscala/Function0;;
NameAndType	futureAsFunction:(Lscala/concurrent/ThreadPoolRunner;Ljava/util/concurrent/Future;)Lscala/Function0;
Method	scala/concurrent/ThreadPoolRunner$class.futureAsFunction:(Lscala/concurrent/ThreadPoolRunner;Ljava/util/concurrent/Future;)Lscala/Function0;
Asciz	Ljava/util/concurrent/Future;;
Asciz	(Lscala/concurrent/ThreadPoolRunner;Lscala/Function0;)Ljava/util/concurrent/Callable;;
NameAndType	functionAsTask:(Lscala/concurrent/ThreadPoolRunner;Lscala/Function0;)Ljava/util/concurrent/Callable;
Method	scala/concurrent/ThreadPoolRunner$class.functionAsTask:(Lscala/concurrent/ThreadPoolRunner;Lscala/Function0;)Ljava/util/concurrent/Callable;
Asciz	isActive;
Asciz	(Lscala/actors/scheduler/ExecutorScheduler;)Z;
NameAndType	isActive:(Lscala/actors/scheduler/ExecutorScheduler;)Z
Method	scala/actors/scheduler/ExecutorScheduler$class.isActive:(Lscala/actors/scheduler/ExecutorScheduler;)Z
NameAndType	onShutdown:(Lscala/actors/scheduler/ExecutorScheduler;)V
Method	scala/actors/scheduler/ExecutorScheduler$class.onShutdown:(Lscala/actors/scheduler/ExecutorScheduler;)V
Asciz	(Lscala/actors/scheduler/ExecutorScheduler;Lscala/Function0;)V;
NameAndType	execute:(Lscala/actors/scheduler/ExecutorScheduler;Lscala/Function0;)V
Method	scala/actors/scheduler/ExecutorScheduler$class.execute:(Lscala/actors/scheduler/ExecutorScheduler;Lscala/Function0;)V
Asciz	(Lscala/actors/scheduler/ExecutorScheduler;Ljava/lang/Runnable;)V;
NameAndType	execute:(Lscala/actors/scheduler/ExecutorScheduler;Ljava/lang/Runnable;)V
Method	scala/actors/scheduler/ExecutorScheduler$class.execute:(Lscala/actors/scheduler/ExecutorScheduler;Ljava/lang/Runnable;)V
NameAndType	gc:(Lscala/actors/scheduler/TerminationMonitor;)V
Method	scala/actors/scheduler/TerminationMonitor$class.gc:(Lscala/actors/scheduler/TerminationMonitor;)V
Asciz	(Lscala/actors/scheduler/TerminationMonitor;)Z;
NameAndType	allTerminated:(Lscala/actors/scheduler/TerminationMonitor;)Z
Method	scala/actors/scheduler/TerminationMonitor$class.allTerminated:(Lscala/actors/scheduler/TerminationMonitor;)Z
Asciz	terminated;
Asciz	(Lscala/actors/Reactor;)V;
Asciz	(Lscala/actors/scheduler/TerminationMonitor;Lscala/actors/Reactor;)V;
NameAndType	terminated:(Lscala/actors/scheduler/TerminationMonitor;Lscala/actors/Reactor;)V
Method	scala/actors/scheduler/TerminationMonitor$class.terminated:(Lscala/actors/scheduler/TerminationMonitor;Lscala/actors/Reactor;)V
Asciz	Lscala/actors/Reactor;;
Asciz	onTerminate;
Asciz	(Lscala/actors/Reactor;Lscala/Function0;)V;
Asciz	(Lscala/actors/scheduler/TerminationMonitor;Lscala/actors/Reactor;Lscala/Function0;)V;
NameAndType	onTerminate:(Lscala/actors/scheduler/TerminationMonitor;Lscala/actors/Reactor;Lscala/Function0;)V
Method	scala/actors/scheduler/TerminationMonitor$class.onTerminate:(Lscala/actors/scheduler/TerminationMonitor;Lscala/actors/Reactor;Lscala/Function0;)V
Asciz	f;
Asciz	newActor;
NameAndType	newActor:(Lscala/actors/scheduler/TerminationMonitor;Lscala/actors/Reactor;)V
Method	scala/actors/scheduler/TerminationMonitor$class.newActor:(Lscala/actors/scheduler/TerminationMonitor;Lscala/actors/Reactor;)V
Asciz	scala$actors$scheduler$TerminationMonitor$_setter_$terminationHandlers_$eq;
Asciz	(Lscala/collection/mutable/HashMap;)V;
NameAndType	terminationHandlers:Lscala/collection/mutable/HashMap;
Field	scala/actors/scheduler/ThreadPoolScheduler.terminationHandlers:Lscala/collection/mutable/HashMap;
Asciz	scala$actors$scheduler$TerminationMonitor$$started_$eq;
NameAndType	scala$actors$scheduler$TerminationMonitor$$started:Z
Field	scala/actors/scheduler/ThreadPoolScheduler.scala$actors$scheduler$TerminationMonitor$$started:Z
Asciz	()Lscala/collection/mutable/HashMap;;
Asciz	activeActors_$eq;
Asciz	(I)V;
NameAndType	activeActors:I
Field	scala/actors/scheduler/ThreadPoolScheduler.activeActors:I
Asciz	ScalaSig;
Asciz	scala/ScalaObject;
class	scala/ScalaObject

{
private boolean scala$actors$scheduler$TerminationMonitor$$started;
  Signature: Z

private final scala.collection.mutable.HashMap terminationHandlers;
  Signature: Lscala/collection/mutable/HashMap;

private int activeActors;
  Signature: I

private final int CHECK_FREQ;
  Signature: I

private boolean terminating;
  Signature: Z

private final boolean daemon;
  Signature: Z

private final boolean terminate;
  Signature: Z

private java.util.concurrent.ThreadPoolExecutor executor;
  Signature: Ljava/util/concurrent/ThreadPoolExecutor;

public scala.actors.scheduler.ThreadPoolScheduler(java.util.concurrent.ThreadPoolExecutor, boolean, boolean);
  Signature: (Ljava/util/concurrent/ThreadPoolExecutor;ZZ)V
  Code:
   Stack=2, Locals=4, Args_size=4
	aload_0
	aload_1
	putfield	Field executor:Ljava/util/concurrent/ThreadPoolExecutor;
	aload_0
	iload_2
	putfield	Field terminate:Z
	aload_0
	iload_3
	putfield	Field daemon:Z
	aload_0
	invokespecial	Method java/lang/Thread."<init>":()V
	aload_0
	invokestatic	Method scala/actors/IScheduler$class.$init$:(Lscala/actors/IScheduler;)V
	aload_0
	invokestatic	Method scala/concurrent/TaskRunner$class.$init$:(Lscala/concurrent/TaskRunner;)V
	aload_0
	invokestatic	Method scala/concurrent/ThreadPoolRunner$class.$init$:(Lscala/concurrent/ThreadPoolRunner;)V
	aload_0
	invokestatic	Method scala/actors/scheduler/ExecutorScheduler$class.$init$:(Lscala/actors/scheduler/ExecutorScheduler;)V
	aload_0
	invokestatic	Method scala/actors/scheduler/TerminationMonitor$class.$init$:(Lscala/actors/scheduler/TerminationMonitor;)V
	aload_0
	iload_3
	invokevirtual	Method setDaemon:(Z)V
	aload_0
	iconst_0
	putfield	Field terminating:Z
	aload_0
	ldc	int 10
	putfield	Field CHECK_FREQ:I
	return
  Labels:
  LocalVariableTable: 
   Start  Length  Slot  Name   Signature
   0      56      0    this       Lscala/actors/scheduler/ThreadPoolScheduler;
   0      56      1    executor       Ljava/util/concurrent/ThreadPoolExecutor;
   0      56      2    terminate       Z
   0      56      3    daemon       Z


private final void liftedTree1$1();
  Signature: ()V
  Code:
   Stack=3, Locals=1, Args_size=1
	aload_0
	aload_0
	invokevirtual	Method CHECK_FREQ:()I
	i2l
	invokevirtual	Method wait:(J)V
	goto	l1 // return
	pop
l1	return
  Labels:
   	l1 = 13 // return
  Exception table:
   from   to  target type
     0    12    12   Class java/lang/InterruptedException


public java.util.concurrent.ExecutorService executor();
  Signature: ()Ljava/util/concurrent/ExecutorService;
  Code:
   Stack=1, Locals=1, Args_size=1
	aload_0
	invokevirtual	Method executor:()Ljava/util/concurrent/ThreadPoolExecutor;
	areturn
  Labels:

public java.lang.Object functionAsTask(scala.Function0);
  Signature: (Lscala/Function0;)Ljava/lang/Object;
  Code:
   Stack=2, Locals=2, Args_size=2
	aload_0
	aload_1
	invokeinterface	InterfaceMethod scala/concurrent/ThreadPoolRunner.functionAsTask:(Lscala/Function0;)Ljava/util/concurrent/Callable;
	areturn
  Labels:
  LocalVariableTable: 
   Start  Length  Slot  Name   Signature
   0      8      0    this       Lscala/actors/scheduler/ThreadPoolScheduler;
   0      8      1    fun       Lscala/Function0;


public scala.Function0 futureAsFunction(java.lang.Object);
  Signature: (Ljava/lang/Object;)Lscala/Function0;
  Code:
   Stack=2, Locals=2, Args_size=2
	aload_0
	aload_1
	checkcast	class java/util/concurrent/Future
	invokeinterface	InterfaceMethod scala/concurrent/ThreadPoolRunner.futureAsFunction:(Ljava/util/concurrent/Future;)Lscala/Function0;
	areturn
  Labels:
  LocalVariableTable: 
   Start  Length  Slot  Name   Signature
   0      11      0    this       Lscala/actors/scheduler/ThreadPoolScheduler;
   0      11      1    x       Ljava/lang/Object;


public java.lang.Object submit(java.lang.Object);
  Signature: (Ljava/lang/Object;)Ljava/lang/Object;
  Code:
   Stack=2, Locals=2, Args_size=2
	aload_0
	aload_1
	checkcast	class java/util/concurrent/Callable
	invokeinterface	InterfaceMethod scala/concurrent/ThreadPoolRunner.submit:(Ljava/util/concurrent/Callable;)Ljava/util/concurrent/Future;
	areturn
  Labels:
  LocalVariableTable: 
   Start  Length  Slot  Name   Signature
   0      11      0    this       Lscala/actors/scheduler/ThreadPoolScheduler;
   0      11      1    task       Ljava/lang/Object;


public void execute(java.lang.Object);
  Signature: (Ljava/lang/Object;)V
  Code:
   Stack=2, Locals=2, Args_size=2
	aload_0
	aload_1
	checkcast	class java/util/concurrent/Callable
	invokeinterface	InterfaceMethod scala/concurrent/ThreadPoolRunner.execute:(Ljava/util/concurrent/Callable;)V
	return
  Labels:
  LocalVariableTable: 
   Start  Length  Slot  Name   Signature
   0      11      0    this       Lscala/actors/scheduler/ThreadPoolScheduler;
   0      11      1    task       Ljava/lang/Object;


public void shutdown();
  Signature: ()V
  Code:
   Stack=2, Locals=1, Args_size=1
	aload_0
	dup
	pop
	monitorenter
	aload_0
	iconst_1
	invokespecial	Method terminating_$eq:(Z)V
	aload_0
	monitorexit
	return
	aload_0
	monitorexit
	athrow
  Labels:
  Exception table:
   from   to  target type
     4    11    12   Class java/lang/Throwable


public void run();
  Signature: ()V
  Code:
   Stack=4, Locals=1, Args_size=1
l3	aload_0
	dup
	pop
	monitorenter
	aload_0
	invokespecial	Method liftedTree1$1:()V
	aload_0
	invokespecial	Method terminating:()Z
	ifne	l1 // new
	aload_0
	invokevirtual	Method terminate:()Z
	ifeq	l2 // aload_0
	aload_0
	invokeinterface	InterfaceMethod scala/actors/scheduler/TerminationMonitor.allTerminated:()Z
	ifeq	l2 // aload_0
l1	new	class scala/actors/scheduler/QuitException
	dup
	invokespecial	Method scala/actors/scheduler/QuitException."<init>":()V
	athrow
l2	aload_0
	invokeinterface	InterfaceMethod scala/actors/scheduler/TerminationMonitor.gc:()V
	aload_0
	monitorexit
	goto	l3 // aload_0
	aload_0
	monitorexit
	athrow
	pop
	getstatic	Field scala/actors/Debug$.MODULE$:Lscala/actors/Debug$;
	new	class scala/runtime/StringAdd
	dup
	aload_0
	invokespecial	Method scala/runtime/StringAdd."<init>":(Ljava/lang/Object;)V
	ldc	String : initiating shutdown...
	invokevirtual	Method scala/runtime/StringAdd.$plus:(Ljava/lang/String;)Ljava/lang/String;
	invokevirtual	Method scala/actors/Debug$.info:(Ljava/lang/String;)V
	aload_0
	invokeinterface	InterfaceMethod scala/actors/scheduler/ExecutorScheduler.onShutdown:()V
	return
  Labels:
   	l3 = 0 // aload_0
   	l1 = 31 // new
   	l2 = 39 // aload_0
  Exception table:
   from   to  target type
     4    50    50   Class java/lang/Throwable

     0    53    53   Class scala/actors/scheduler/QuitException


public scala.actors.scheduler.ThreadPoolScheduler(boolean);
  Signature: (Z)V
  Code:
   Stack=4, Locals=2, Args_size=2
	aload_0
	aconst_null
	iconst_1
	iload_1
	invokespecial	Method "<init>":(Ljava/util/concurrent/ThreadPoolExecutor;ZZ)V
	return
  Labels:
  LocalVariableTable: 
   Start  Length  Slot  Name   Signature
   0      8      0    this       Lscala/actors/scheduler/ThreadPoolScheduler;
   0      8      1    d       Z


public int CHECK_FREQ();
  Signature: ()I
  Code:
   Stack=1, Locals=1, Args_size=1
	aload_0
	getfield	Field CHECK_FREQ:I
	ireturn
  Labels:

private void terminating_$eq(boolean);
  Signature: (Z)V
  Code:
   Stack=2, Locals=2, Args_size=2
	aload_0
	iload_1
	putfield	Field terminating:Z
	return
  Labels:

private boolean terminating();
  Signature: ()Z
  Code:
   Stack=1, Locals=1, Args_size=1
	aload_0
	getfield	Field terminating:Z
	ireturn
  Labels:

public boolean daemon();
  Signature: ()Z
  Code:
   Stack=1, Locals=1, Args_size=1
	aload_0
	getfield	Field daemon:Z
	ireturn
  Labels:

public boolean terminate();
  Signature: ()Z
  Code:
   Stack=1, Locals=1, Args_size=1
	aload_0
	getfield	Field terminate:Z
	ireturn
  Labels:

public void executor_$eq(java.util.concurrent.ThreadPoolExecutor);
  Signature: (Ljava/util/concurrent/ThreadPoolExecutor;)V
  Code:
   Stack=2, Locals=2, Args_size=2
	aload_0
	aload_1
	putfield	Field executor:Ljava/util/concurrent/ThreadPoolExecutor;
	return
  Labels:

public java.util.concurrent.ThreadPoolExecutor executor();
  Signature: ()Ljava/util/concurrent/ThreadPoolExecutor;
  Code:
   Stack=1, Locals=1, Args_size=1
	aload_0
	getfield	Field executor:Ljava/util/concurrent/ThreadPoolExecutor;
	areturn
  Labels:

public void printActorDump();
  Signature: ()V
  Code:
   Stack=1, Locals=1, Args_size=1
	aload_0
	invokestatic	Method scala/actors/IScheduler$class.printActorDump:(Lscala/actors/IScheduler;)V
	return
  Labels:

public void onLockup(int, scala.Function0);
  Signature: (ILscala/Function0;)V
  Code:
   Stack=3, Locals=3, Args_size=3
	aload_0
	iload_1
	aload_2
	invokestatic	Method scala/actors/IScheduler$class.onLockup:(Lscala/actors/IScheduler;ILscala/Function0;)V
	return
  Labels:
  LocalVariableTable: 
   Start  Length  Slot  Name   Signature
   0      7      0    this       Lscala/actors/scheduler/ThreadPoolScheduler;
   0      7      1    millis       I
   0      7      2    handler       Lscala/Function0;


public void onLockup(scala.Function0);
  Signature: (Lscala/Function0;)V
  Code:
   Stack=2, Locals=2, Args_size=2
	aload_0
	aload_1
	invokestatic	Method scala/actors/IScheduler$class.onLockup:(Lscala/actors/IScheduler;Lscala/Function0;)V
	return
  Labels:
  LocalVariableTable: 
   Start  Length  Slot  Name   Signature
   0      6      0    this       Lscala/actors/scheduler/ThreadPoolScheduler;
   0      6      1    handler       Lscala/Function0;


public void tick(scala.actors.Actor);
  Signature: (Lscala/actors/Actor;)V
  Code:
   Stack=2, Locals=2, Args_size=2
	aload_0
	aload_1
	invokestatic	Method scala/actors/IScheduler$class.tick:(Lscala/actors/IScheduler;Lscala/actors/Actor;)V
	return
  Labels:
  LocalVariableTable: 
   Start  Length  Slot  Name   Signature
   0      6      0    this       Lscala/actors/scheduler/ThreadPoolScheduler;
   0      6      1    a       Lscala/actors/Actor;


public void executeFromActor(java.lang.Runnable);
  Signature: (Ljava/lang/Runnable;)V
  Code:
   Stack=2, Locals=2, Args_size=2
	aload_0
	aload_1
	invokestatic	Method scala/actors/IScheduler$class.executeFromActor:(Lscala/actors/IScheduler;Ljava/lang/Runnable;)V
	return
  Labels:
  LocalVariableTable: 
   Start  Length  Slot  Name   Signature
   0      6      0    this       Lscala/actors/scheduler/ThreadPoolScheduler;
   0      6      1    task       Ljava/lang/Runnable;


public scala.Either tryCatch(scala.Function0);
  Signature: (Lscala/Function0;)Lscala/Either;
  Code:
   Stack=2, Locals=2, Args_size=2
	aload_0
	aload_1
	invokestatic	Method scala/concurrent/TaskRunner$class.tryCatch:(Lscala/concurrent/TaskRunner;Lscala/Function0;)Lscala/Either;
	areturn
  Labels:
  LocalVariableTable: 
   Start  Length  Slot  Name   Signature
   0      6      0    this       Lscala/actors/scheduler/ThreadPoolScheduler;
   0      6      1    body       Lscala/Function0;


public void managedBlock(scala.concurrent.ManagedBlocker);
  Signature: (Lscala/concurrent/ManagedBlocker;)V
  Code:
   Stack=2, Locals=2, Args_size=2
	aload_0
	aload_1
	invokestatic	Method scala/concurrent/ThreadPoolRunner$class.managedBlock:(Lscala/concurrent/ThreadPoolRunner;Lscala/concurrent/ManagedBlocker;)V
	return
  Labels:
  LocalVariableTable: 
   Start  Length  Slot  Name   Signature
   0      6      0    this       Lscala/actors/scheduler/ThreadPoolScheduler;
   0      6      1    blocker       Lscala/concurrent/ManagedBlocker;


public void execute(java.util.concurrent.Callable);
  Signature: (Ljava/util/concurrent/Callable;)V
  Code:
   Stack=2, Locals=2, Args_size=2
	aload_0
	aload_1
	invokestatic	Method scala/concurrent/ThreadPoolRunner$class.execute:(Lscala/concurrent/ThreadPoolRunner;Ljava/util/concurrent/Callable;)V
	return
  Labels:
  LocalVariableTable: 
   Start  Length  Slot  Name   Signature
   0      6      0    this       Lscala/actors/scheduler/ThreadPoolScheduler;
   0      6      1    task       Ljava/util/concurrent/Callable;


public java.util.concurrent.Future submit(java.util.concurrent.Callable);
  Signature: (Ljava/util/concurrent/Callable;)Ljava/util/concurrent/Future;
  Code:
   Stack=2, Locals=2, Args_size=2
	aload_0
	aload_1
	invokestatic	Method scala/concurrent/ThreadPoolRunner$class.submit:(Lscala/concurrent/ThreadPoolRunner;Ljava/util/concurrent/Callable;)Ljava/util/concurrent/Future;
	areturn
  Labels:
  LocalVariableTable: 
   Start  Length  Slot  Name   Signature
   0      6      0    this       Lscala/actors/scheduler/ThreadPoolScheduler;
   0      6      1    task       Ljava/util/concurrent/Callable;


public scala.Function0 futureAsFunction(java.util.concurrent.Future);
  Signature: (Ljava/util/concurrent/Future;)Lscala/Function0;
  Code:
   Stack=2, Locals=2, Args_size=2
	aload_0
	aload_1
	invokestatic	Method scala/concurrent/ThreadPoolRunner$class.futureAsFunction:(Lscala/concurrent/ThreadPoolRunner;Ljava/util/concurrent/Future;)Lscala/Function0;
	areturn
  Labels:
  LocalVariableTable: 
   Start  Length  Slot  Name   Signature
   0      6      0    this       Lscala/actors/scheduler/ThreadPoolScheduler;
   0      6      1    x       Ljava/util/concurrent/Future;


public java.util.concurrent.Callable functionAsTask(scala.Function0);
  Signature: (Lscala/Function0;)Ljava/util/concurrent/Callable;
  Code:
   Stack=2, Locals=2, Args_size=2
	aload_0
	aload_1
	invokestatic	Method scala/concurrent/ThreadPoolRunner$class.functionAsTask:(Lscala/concurrent/ThreadPoolRunner;Lscala/Function0;)Ljava/util/concurrent/Callable;
	areturn
  Labels:
  LocalVariableTable: 
   Start  Length  Slot  Name   Signature
   0      6      0    this       Lscala/actors/scheduler/ThreadPoolScheduler;
   0      6      1    fun       Lscala/Function0;


public boolean isActive();
  Signature: ()Z
  Code:
   Stack=1, Locals=1, Args_size=1
	aload_0
	invokestatic	Method scala/actors/scheduler/ExecutorScheduler$class.isActive:(Lscala/actors/scheduler/ExecutorScheduler;)Z
	ireturn
  Labels:

public void onShutdown();
  Signature: ()V
  Code:
   Stack=1, Locals=1, Args_size=1
	aload_0
	invokestatic	Method scala/actors/scheduler/ExecutorScheduler$class.onShutdown:(Lscala/actors/scheduler/ExecutorScheduler;)V
	return
  Labels:

public void execute(scala.Function0);
  Signature: (Lscala/Function0;)V
  Code:
   Stack=2, Locals=2, Args_size=2
	aload_0
	aload_1
	invokestatic	Method scala/actors/scheduler/ExecutorScheduler$class.execute:(Lscala/actors/scheduler/ExecutorScheduler;Lscala/Function0;)V
	return
  Labels:
  LocalVariableTable: 
   Start  Length  Slot  Name   Signature
   0      6      0    this       Lscala/actors/scheduler/ThreadPoolScheduler;
   0      6      1    fun       Lscala/Function0;


public void execute(java.lang.Runnable);
  Signature: (Ljava/lang/Runnable;)V
  Code:
   Stack=2, Locals=2, Args_size=2
	aload_0
	aload_1
	invokestatic	Method scala/actors/scheduler/ExecutorScheduler$class.execute:(Lscala/actors/scheduler/ExecutorScheduler;Ljava/lang/Runnable;)V
	return
  Labels:
  LocalVariableTable: 
   Start  Length  Slot  Name   Signature
   0      6      0    this       Lscala/actors/scheduler/ThreadPoolScheduler;
   0      6      1    task       Ljava/lang/Runnable;


public void gc();
  Signature: ()V
  Code:
   Stack=1, Locals=1, Args_size=1
	aload_0
	invokestatic	Method scala/actors/scheduler/TerminationMonitor$class.gc:(Lscala/actors/scheduler/TerminationMonitor;)V
	return
  Labels:

public boolean allTerminated();
  Signature: ()Z
  Code:
   Stack=1, Locals=1, Args_size=1
	aload_0
	invokestatic	Method scala/actors/scheduler/TerminationMonitor$class.allTerminated:(Lscala/actors/scheduler/TerminationMonitor;)Z
	ireturn
  Labels:

public void terminated(scala.actors.Reactor);
  Signature: (Lscala/actors/Reactor;)V
  Code:
   Stack=2, Locals=2, Args_size=2
	aload_0
	aload_1
	invokestatic	Method scala/actors/scheduler/TerminationMonitor$class.terminated:(Lscala/actors/scheduler/TerminationMonitor;Lscala/actors/Reactor;)V
	return
  Labels:
  LocalVariableTable: 
   Start  Length  Slot  Name   Signature
   0      6      0    this       Lscala/actors/scheduler/ThreadPoolScheduler;
   0      6      1    a       Lscala/actors/Reactor;


public void onTerminate(scala.actors.Reactor, scala.Function0);
  Signature: (Lscala/actors/Reactor;Lscala/Function0;)V
  Code:
   Stack=3, Locals=3, Args_size=3
	aload_0
	aload_1
	aload_2
	invokestatic	Method scala/actors/scheduler/TerminationMonitor$class.onTerminate:(Lscala/actors/scheduler/TerminationMonitor;Lscala/actors/Reactor;Lscala/Function0;)V
	return
  Labels:
  LocalVariableTable: 
   Start  Length  Slot  Name   Signature
   0      7      0    this       Lscala/actors/scheduler/ThreadPoolScheduler;
   0      7      1    a       Lscala/actors/Reactor;
   0      7      2    f       Lscala/Function0;


public void newActor(scala.actors.Reactor);
  Signature: (Lscala/actors/Reactor;)V
  Code:
   Stack=2, Locals=2, Args_size=2
	aload_0
	aload_1
	invokestatic	Method scala/actors/scheduler/TerminationMonitor$class.newActor:(Lscala/actors/scheduler/TerminationMonitor;Lscala/actors/Reactor;)V
	return
  Labels:
  LocalVariableTable: 
   Start  Length  Slot  Name   Signature
   0      6      0    this       Lscala/actors/scheduler/ThreadPoolScheduler;
   0      6      1    a       Lscala/actors/Reactor;


public void scala$actors$scheduler$TerminationMonitor$_setter_$terminationHandlers_$eq(scala.collection.mutable.HashMap);
  Signature: (Lscala/collection/mutable/HashMap;)V
  Code:
   Stack=2, Locals=2, Args_size=2
	aload_0
	aload_1
	putfield	Field terminationHandlers:Lscala/collection/mutable/HashMap;
	return
  Labels:

public final void scala$actors$scheduler$TerminationMonitor$$started_$eq(boolean);
  Signature: (Z)V
  Code:
   Stack=2, Locals=2, Args_size=2
	aload_0
	iload_1
	putfield	Field scala$actors$scheduler$TerminationMonitor$$started:Z
	return
  Labels:

public final boolean scala$actors$scheduler$TerminationMonitor$$started();
  Signature: ()Z
  Code:
   Stack=1, Locals=1, Args_size=1
	aload_0
	getfield	Field scala$actors$scheduler$TerminationMonitor$$started:Z
	ireturn
  Labels:

public scala.collection.mutable.HashMap terminationHandlers();
  Signature: ()Lscala/collection/mutable/HashMap;
  Code:
   Stack=1, Locals=1, Args_size=1
	aload_0
	getfield	Field terminationHandlers:Lscala/collection/mutable/HashMap;
	areturn
  Labels:

public void activeActors_$eq(int);
  Signature: (I)V
  Code:
   Stack=2, Locals=2, Args_size=2
	aload_0
	iload_1
	putfield	Field activeActors:I
	return
  Labels:

public int activeActors();
  Signature: ()I
  Code:
   Stack=1, Locals=1, Args_size=1
	aload_0
	getfield	Field activeActors:I
	ireturn
  Labels:

}

