Compiled from "ThreadPoolConfig.scala"
public final class scala.actors.scheduler.ThreadPoolConfig$ extends java.lang.Object implements scala.ScalaObject
  SourceFile: "ThreadPoolConfig.scala"
  Scala: length = 0x
   
  minor version: 0
  major version: 49
  Constant pool:
Asciz	SourceFile;
Asciz	ThreadPoolConfig.scala;
Asciz	Scala;
Asciz	MODULE$;
Asciz	Lscala/actors/scheduler/ThreadPoolConfig$;;
Asciz	<clinit>;
Asciz	()V;
Asciz	Code;
Asciz	scala/actors/scheduler/ThreadPoolConfig$;
class	scala/actors/scheduler/ThreadPoolConfig$
Asciz	<init>;
NameAndType	"<init>":()V
Method	scala/actors/scheduler/ThreadPoolConfig$."<init>":()V
Asciz	maxPoolSize;
Asciz	I;
Asciz	corePoolSize;
Asciz	minNumThreads;
Asciz	rt;
Asciz	Ljava/lang/Runtime;;
Asciz	LineNumberTable;
Asciz	java/lang/Object;
class	java/lang/Object
Method	java/lang/Object."<init>":()V
NameAndType	MODULE$:Lscala/actors/scheduler/ThreadPoolConfig$;
Field	scala/actors/scheduler/ThreadPoolConfig$.MODULE$:Lscala/actors/scheduler/ThreadPoolConfig$;
Asciz	java/lang/Runtime;
class	java/lang/Runtime
Asciz	getRuntime;
Asciz	()Ljava/lang/Runtime;;
NameAndType	getRuntime:()Ljava/lang/Runtime;
Method	java/lang/Runtime.getRuntime:()Ljava/lang/Runtime;
NameAndType	rt:Ljava/lang/Runtime;
Field	scala/actors/scheduler/ThreadPoolConfig$.rt:Ljava/lang/Runtime;
NameAndType	minNumThreads:I
Field	scala/actors/scheduler/ThreadPoolConfig$.minNumThreads:I
Asciz	actors.corePoolSize;
String	actors.corePoolSize
Asciz	getIntegerProp;
Asciz	(Ljava/lang/String;)Lscala/Option;;
NameAndType	getIntegerProp:(Ljava/lang/String;)Lscala/Option;
Method	scala/actors/scheduler/ThreadPoolConfig$.getIntegerProp:(Ljava/lang/String;)Lscala/Option;
Asciz	scala/Some;
class	scala/Some
Asciz	x;
Asciz	()Ljava/lang/Object;;
NameAndType	x:()Ljava/lang/Object;
Method	scala/Some.x:()Ljava/lang/Object;
Asciz	scala/runtime/BoxesRunTime;
class	scala/runtime/BoxesRunTime
Asciz	unboxToInt;
Asciz	(Ljava/lang/Object;)I;
NameAndType	unboxToInt:(Ljava/lang/Object;)I
Method	scala/runtime/BoxesRunTime.unboxToInt:(Ljava/lang/Object;)I
Asciz	gd1$1;
Asciz	(I)Z;
NameAndType	gd1$1:(I)Z
Method	scala/actors/scheduler/ThreadPoolConfig$.gd1$1:(I)Z
Asciz	scala/MatchError;
class	scala/MatchError
Asciz	scala/Option;
class	scala/Option
Asciz	toString;
Asciz	()Ljava/lang/String;;
NameAndType	toString:()Ljava/lang/String;
Method	scala/Option.toString:()Ljava/lang/String;
Asciz	(Ljava/lang/String;)V;
NameAndType	"<init>":(Ljava/lang/String;)V
Method	scala/MatchError."<init>":(Ljava/lang/String;)V
NameAndType	rt:()Ljava/lang/Runtime;
Method	scala/actors/scheduler/ThreadPoolConfig$.rt:()Ljava/lang/Runtime;
Asciz	availableProcessors;
Asciz	()I;
NameAndType	availableProcessors:()I
Method	java/lang/Runtime.availableProcessors:()I
NameAndType	minNumThreads:()I
Method	scala/actors/scheduler/ThreadPoolConfig$.minNumThreads:()I
NameAndType	corePoolSize:I
Field	scala/actors/scheduler/ThreadPoolConfig$.corePoolSize:I
Asciz	actors.maxPoolSize;
String	actors.maxPoolSize
Asciz	gd2$1;
NameAndType	gd2$1:(I)Z
Method	scala/actors/scheduler/ThreadPoolConfig$.gd2$1:(I)Z
Asciz	gd3$1;
NameAndType	gd3$1:(I)Z
Method	scala/actors/scheduler/ThreadPoolConfig$.gd3$1:(I)Z
NameAndType	corePoolSize:()I
Method	scala/actors/scheduler/ThreadPoolConfig$.corePoolSize:()I
int	256;
NameAndType	maxPoolSize:I
Field	scala/actors/scheduler/ThreadPoolConfig$.maxPoolSize:I
Asciz	this;
Asciz	temp2;
Asciz	Lscala/Some;;
Asciz	temp3;
Asciz	byCores;
Asciz	temp5;
Asciz	temp6;
Asciz	temp4;
Asciz	Lscala/Option;;
Asciz	temp1;
Asciz	LocalVariableTable;
Asciz	useForkJoin;
Asciz	()Z;
Asciz	actors.enableForkJoin;
String	actors.enableForkJoin
Asciz	java/lang/System;
class	java/lang/System
Asciz	getProperty;
Asciz	(Ljava/lang/String;)Ljava/lang/String;;
NameAndType	getProperty:(Ljava/lang/String;)Ljava/lang/String;
Method	java/lang/System.getProperty:(Ljava/lang/String;)Ljava/lang/String;
Asciz	equals;
Asciz	(Ljava/lang/Object;)Z;
NameAndType	equals:(Ljava/lang/Object;)Z
Method	java/lang/Object.equals:(Ljava/lang/Object;)Z
Asciz	java.version;
String	java.version
Asciz	java.vm.vendor;
String	java.vm.vendor
Asciz	scala/actors/Debug$;
class	scala/actors/Debug$
Asciz	Lscala/actors/Debug$;;
NameAndType	MODULE$:Lscala/actors/Debug$;
Field	scala/actors/Debug$.MODULE$:Lscala/actors/Debug$;
Asciz	scala/collection/mutable/StringBuilder;
class	scala/collection/mutable/StringBuilder
Method	scala/collection/mutable/StringBuilder."<init>":()V
Asciz	scala/runtime/StringAdd;
class	scala/runtime/StringAdd
Asciz	(Ljava/lang/Object;)V;
NameAndType	"<init>":(Ljava/lang/Object;)V
Method	scala/runtime/StringAdd."<init>":(Ljava/lang/Object;)V
Asciz	: java.version = ;
String	: java.version = 
Asciz	$plus;
NameAndType	$plus:(Ljava/lang/String;)Ljava/lang/String;
Method	scala/runtime/StringAdd.$plus:(Ljava/lang/String;)Ljava/lang/String;
Asciz	append;
Asciz	(Ljava/lang/Object;)Lscala/collection/mutable/StringBuilder;;
NameAndType	append:(Ljava/lang/Object;)Lscala/collection/mutable/StringBuilder;
Method	scala/collection/mutable/StringBuilder.append:(Ljava/lang/Object;)Lscala/collection/mutable/StringBuilder;
Method	scala/collection/mutable/StringBuilder.toString:()Ljava/lang/String;
Asciz	info;
NameAndType	info:(Ljava/lang/String;)V
Method	scala/actors/Debug$.info:(Ljava/lang/String;)V
Asciz	: java.vm.vendor = ;
String	: java.vm.vendor = 
Asciz	1.6;
String	1.6
Asciz	java/lang/String;
class	java/lang/String
Asciz	indexOf;
Asciz	(Ljava/lang/String;)I;
NameAndType	indexOf:(Ljava/lang/String;)I
Method	java/lang/String.indexOf:(Ljava/lang/String;)I
Asciz	1.7;
String	1.7
Asciz	Sun;
String	Sun
Asciz	true;
String	true
Method	java/lang/String.equals:(Ljava/lang/Object;)Z
Asciz	java/lang/SecurityException;
class	java/lang/SecurityException
Asciz	javaVersion;
Asciz	Ljava/lang/String;;
Asciz	jvmVendor;
Asciz	fjProp;
Asciz	exceptionResult2;
Asciz	Z;
Asciz	java/lang/Integer;
class	java/lang/Integer
Asciz	parseInt;
NameAndType	parseInt:(Ljava/lang/String;)I
Method	java/lang/Integer.parseInt:(Ljava/lang/String;)I
Asciz	boxToInteger;
Asciz	(I)Ljava/lang/Integer;;
NameAndType	boxToInteger:(I)Ljava/lang/Integer;
Method	scala/runtime/BoxesRunTime.boxToInteger:(I)Ljava/lang/Integer;
Method	scala/Some."<init>":(Ljava/lang/Object;)V
Asciz	scala/None$;
class	scala/None$
Asciz	Lscala/None$;;
NameAndType	MODULE$:Lscala/None$;
Field	scala/None$.MODULE$:Lscala/None$;
Asciz	java/security/AccessControlException;
class	java/security/AccessControlException
Asciz	java/lang/NumberFormatException;
class	java/lang/NumberFormatException
Asciz	propName;
Asciz	prop;
Asciz	exceptionResult1;
Asciz	(Ljava/lang/String;)Lscala/Option<Ljava/lang/Integer;>;;
Asciz	Signature;
Asciz	scala/ScalaObject;
class	scala/ScalaObject

{
public static final scala.actors.scheduler.ThreadPoolConfig$ MODULE$;
  Signature: Lscala/actors/scheduler/ThreadPoolConfig$;

private final int maxPoolSize;
  Signature: I

private final int corePoolSize;
  Signature: I

private final int minNumThreads;
  Signature: I

private final java.lang.Runtime rt;
  Signature: Ljava/lang/Runtime;

public static {};
  Signature: ()V
  Code:
   Stack=1, Locals=0, Args_size=0
	new	class scala/actors/scheduler/ThreadPoolConfig$
	invokespecial	Method "<init>":()V
	return
  Labels:

private scala.actors.scheduler.ThreadPoolConfig$();
  Signature: ()V
  Code:
   Stack=4, Locals=8, Args_size=1
	aload_0
	invokespecial	Method java/lang/Object."<init>":()V
	aload_0
	putstatic	Field MODULE$:Lscala/actors/scheduler/ThreadPoolConfig$;
	aload_0
	invokestatic	Method java/lang/Runtime.getRuntime:()Ljava/lang/Runtime;
	putfield	Field rt:Ljava/lang/Runtime;
	aload_0
	iconst_4
	putfield	Field minNumThreads:I
	aload_0
	aload_0
	ldc	String actors.corePoolSize
	invokespecial	Method getIntegerProp:(Ljava/lang/String;)Lscala/Option;
	astore	7
	aload	7
	instanceof	class scala/Some
	ifeq	l1 // iconst_1
	aload	7
	checkcast	class scala/Some
	astore_1
	aload_1
	invokevirtual	Method scala/Some.x:()Ljava/lang/Object;
	invokestatic	Method scala/runtime/BoxesRunTime.unboxToInt:(Ljava/lang/Object;)I
	istore_2
	aload_0
	iload_2
	invokespecial	Method gd1$1:(I)Z
	ifeq	l2 // iconst_1
	iload_2
	goto	l3 // putfield
l2	iconst_1
	ifne	l4 // aload_0
	new	class scala/MatchError
	dup
	aload	7
	invokevirtual	Method scala/Option.toString:()Ljava/lang/String;
	invokespecial	Method scala/MatchError."<init>":(Ljava/lang/String;)V
	athrow
l1	iconst_1
	ifeq	l5 // new
l4	aload_0
	invokespecial	Method rt:()Ljava/lang/Runtime;
	invokevirtual	Method java/lang/Runtime.availableProcessors:()I
	iconst_2
	imul
	istore_3
	iload_3
	aload_0
	invokespecial	Method minNumThreads:()I
	if_icmple	l6 // aload_0
	iload_3
	goto	l3 // putfield
l6	aload_0
	invokespecial	Method minNumThreads:()I
l3	putfield	Field corePoolSize:I
	aload_0
	aload_0
	ldc	String actors.maxPoolSize
	invokespecial	Method getIntegerProp:(Ljava/lang/String;)Lscala/Option;
	astore	6
	aload	6
	instanceof	class scala/Some
	ifeq	l7 // iconst_1
	aload	6
	checkcast	class scala/Some
	astore	4
	aload	4
	invokevirtual	Method scala/Some.x:()Ljava/lang/Object;
	invokestatic	Method scala/runtime/BoxesRunTime.unboxToInt:(Ljava/lang/Object;)I
	istore	5
	aload_0
	iload	5
	invokespecial	Method gd2$1:(I)Z
	ifeq	l8 // aload_0
	iload	5
	goto	l9 // putfield
l8	aload_0
	iload	5
	invokespecial	Method gd3$1:(I)Z
	ifeq	l10 // iconst_1
	aload_0
	invokevirtual	Method corePoolSize:()I
	goto	l9 // putfield
l10	iconst_1
	ifeq	l11 // new
	ldc	int 256
	goto	l9 // putfield
l11	new	class scala/MatchError
	dup
	aload	6
	invokevirtual	Method scala/Option.toString:()Ljava/lang/String;
	invokespecial	Method scala/MatchError."<init>":(Ljava/lang/String;)V
	athrow
l7	iconst_1
	ifeq	l12 // new
	ldc	int 256
l9	putfield	Field maxPoolSize:I
	return
l12	new	class scala/MatchError
	dup
	aload	6
	invokevirtual	Method scala/Option.toString:()Ljava/lang/String;
	invokespecial	Method scala/MatchError."<init>":(Ljava/lang/String;)V
	athrow
l5	new	class scala/MatchError
	dup
	aload	7
	invokevirtual	Method scala/Option.toString:()Ljava/lang/String;
	invokespecial	Method scala/MatchError."<init>":(Ljava/lang/String;)V
	athrow
  Labels:
   	l2 = 63 // iconst_1
   	l1 = 80 // iconst_1
   	l4 = 84 // aload_0
   	l6 = 106 // aload_0
   	l3 = 110 // putfield
   	l8 = 161 // aload_0
   	l10 = 177 // iconst_1
   	l11 = 186 // new
   	l7 = 199 // iconst_1
   	l9 = 205 // putfield
   	l12 = 209 // new
   	l5 = 222 // new
  LocalVariableTable: 
   Start  Length  Slot  Name   Signature
   0      235      0    this       Lscala/actors/scheduler/ThreadPoolConfig$;
   43      37      1    temp2       Lscala/Some;
   84      26      1    temp2       Lscala/Some;
   51      29      2    temp3       I
   84      26      2    temp3       I
   94      16      3    byCores       I
   137      62      4    temp5       Lscala/Some;
   147      52      5    temp6       I
   122      100      6    temp4       Lscala/Option;
   29      101      7    temp1       Lscala/Option;
   222      13      7    temp1       Lscala/Option;


private final boolean gd3$1(int);
  Signature: (I)Z
  Code:
   Stack=2, Locals=2, Args_size=2
	iload_1
	aload_0
	getfield	Field corePoolSize:I
	if_icmpge	l1 // iconst_0
	iconst_1
	goto	l2 // ireturn
l1	iconst_0
l2	ireturn
  Labels:
   	l1 = 12 // iconst_0
   	l2 = 13 // ireturn

private final boolean gd2$1(int);
  Signature: (I)Z
  Code:
   Stack=2, Locals=2, Args_size=2
	iload_1
	aload_0
	getfield	Field corePoolSize:I
	if_icmplt	l1 // iconst_0
	iconst_1
	goto	l2 // ireturn
l1	iconst_0
l2	ireturn
  Labels:
   	l1 = 12 // iconst_0
   	l2 = 13 // ireturn

private final boolean gd1$1(int);
  Signature: (I)Z
  Code:
   Stack=2, Locals=2, Args_size=2
	iload_1
	iconst_0
	if_icmple	l1 // iconst_0
	iconst_1
	goto	l2 // ireturn
l1	iconst_0
l2	ireturn
  Labels:
   	l1 = 9 // iconst_0
   	l2 = 10 // ireturn

public boolean useForkJoin();
  Signature: ()Z
  Code:
   Stack=5, Locals=5, Args_size=1
	ldc	String actors.enableForkJoin
	invokestatic	Method java/lang/System.getProperty:(Ljava/lang/String;)Ljava/lang/String;
	astore_3
	aload_3
	dup
	pop
	ifnull	l1 // ldc
	aload_3
	aconst_null
	invokevirtual	Method java/lang/Object.equals:(Ljava/lang/Object;)Z
	ifeq	l2 // aload_3
l1	ldc	String java.version
	invokestatic	Method java/lang/System.getProperty:(Ljava/lang/String;)Ljava/lang/String;
	astore_1
	ldc	String java.vm.vendor
	invokestatic	Method java/lang/System.getProperty:(Ljava/lang/String;)Ljava/lang/String;
	astore_2
	getstatic	Field scala/actors/Debug$.MODULE$:Lscala/actors/Debug$;
	new	class scala/collection/mutable/StringBuilder
	dup
	invokespecial	Method scala/collection/mutable/StringBuilder."<init>":()V
	new	class scala/runtime/StringAdd
	dup
	aload_0
	invokespecial	Method scala/runtime/StringAdd."<init>":(Ljava/lang/Object;)V
	ldc	String : java.version = 
	invokevirtual	Method scala/runtime/StringAdd.$plus:(Ljava/lang/String;)Ljava/lang/String;
	invokevirtual	Method scala/collection/mutable/StringBuilder.append:(Ljava/lang/Object;)Lscala/collection/mutable/StringBuilder;
	aload_1
	invokevirtual	Method scala/collection/mutable/StringBuilder.append:(Ljava/lang/Object;)Lscala/collection/mutable/StringBuilder;
	invokevirtual	Method scala/collection/mutable/StringBuilder.toString:()Ljava/lang/String;
	invokevirtual	Method scala/actors/Debug$.info:(Ljava/lang/String;)V
	getstatic	Field scala/actors/Debug$.MODULE$:Lscala/actors/Debug$;
	new	class scala/collection/mutable/StringBuilder
	dup
	invokespecial	Method scala/collection/mutable/StringBuilder."<init>":()V
	new	class scala/runtime/StringAdd
	dup
	aload_0
	invokespecial	Method scala/runtime/StringAdd."<init>":(Ljava/lang/Object;)V
	ldc	String : java.vm.vendor = 
	invokevirtual	Method scala/runtime/StringAdd.$plus:(Ljava/lang/String;)Ljava/lang/String;
	invokevirtual	Method scala/collection/mutable/StringBuilder.append:(Ljava/lang/Object;)Lscala/collection/mutable/StringBuilder;
	aload_2
	invokevirtual	Method scala/collection/mutable/StringBuilder.append:(Ljava/lang/Object;)Lscala/collection/mutable/StringBuilder;
	invokevirtual	Method scala/collection/mutable/StringBuilder.toString:()Ljava/lang/String;
	invokevirtual	Method scala/actors/Debug$.info:(Ljava/lang/String;)V
	aload_1
	ldc	String 1.6
	invokevirtual	Method java/lang/String.indexOf:(Ljava/lang/String;)I
	iconst_m1
	if_icmpne	l3 // aload_2
	aload_1
	ldc	String 1.7
	invokevirtual	Method java/lang/String.indexOf:(Ljava/lang/String;)I
	iconst_m1
	if_icmpeq	l4 // iconst_0
l3	aload_2
	ldc	String Sun
	invokevirtual	Method java/lang/String.indexOf:(Ljava/lang/String;)I
	iconst_m1
	if_icmpeq	l4 // iconst_0
	iconst_1
	goto	l5 // istore
l4	iconst_0
	goto	l5 // istore
l2	aload_3
	ldc	String true
	invokevirtual	Method java/lang/String.equals:(Ljava/lang/Object;)Z
l5	istore	4
	goto	l6 // iload
	pop
	iconst_0
	istore	4
l6	iload	4
	ireturn
  Labels:
   	l1 = 20 // ldc
   	l3 = 124 // aload_2
   	l4 = 138 // iconst_0
   	l2 = 142 // aload_3
   	l5 = 148 // istore
   	l6 = 157 // iload
  Exception table:
   from   to  target type
     0   153   153   Class java/lang/SecurityException

  LocalVariableTable: 
   Start  Length  Slot  Name   Signature
   0      160      0    this       Lscala/actors/scheduler/ThreadPoolConfig$;
   26      116      1    javaVersion       Ljava/lang/String;
   32      110      2    jvmVendor       Ljava/lang/String;
   6      147      3    fjProp       Ljava/lang/String;
   0      159      4    exceptionResult2       Z


public int maxPoolSize();
  Signature: ()I
  Code:
   Stack=1, Locals=1, Args_size=1
	aload_0
	getfield	Field maxPoolSize:I
	ireturn
  Labels:

public int corePoolSize();
  Signature: ()I
  Code:
   Stack=1, Locals=1, Args_size=1
	aload_0
	getfield	Field corePoolSize:I
	ireturn
  Labels:

private scala.Option getIntegerProp(java.lang.String);
  Signature: (Ljava/lang/String;)Lscala/Option;
  Code:
   Stack=3, Locals=5, Args_size=2
	aload_1
	invokestatic	Method java/lang/System.getProperty:(Ljava/lang/String;)Ljava/lang/String;
	astore_2
	new	class scala/Some
	dup
	aload_2
	invokestatic	Method java/lang/Integer.parseInt:(Ljava/lang/String;)I
	istore_3
	iload_3
	invokestatic	Method scala/runtime/BoxesRunTime.boxToInteger:(I)Ljava/lang/Integer;
	invokespecial	Method scala/Some."<init>":(Ljava/lang/Object;)V
	astore	4
	goto	l1 // aload
	pop
	getstatic	Field scala/None$.MODULE$:Lscala/None$;
	astore	4
	goto	l1 // aload
	pop
	getstatic	Field scala/None$.MODULE$:Lscala/None$;
	astore	4
l1	aload	4
	areturn
  Labels:
   	l1 = 41 // aload
  Exception table:
   from   to  target type
     0    26    35   Class java/security/AccessControlException

     0    26    26   Class java/lang/NumberFormatException

  LocalVariableTable: 
   Start  Length  Slot  Name   Signature
   0      44      0    this       Lscala/actors/scheduler/ThreadPoolConfig$;
   0      44      1    propName       Ljava/lang/String;
   5      16      2    prop       Ljava/lang/String;
   0      43      4    exceptionResult1       Lscala/Option;

  Signature: length = 0x2
   00 FFFFFFC2 

private int minNumThreads();
  Signature: ()I
  Code:
   Stack=1, Locals=1, Args_size=1
	aload_0
	getfield	Field minNumThreads:I
	ireturn
  Labels:

private java.lang.Runtime rt();
  Signature: ()Ljava/lang/Runtime;
  Code:
   Stack=1, Locals=1, Args_size=1
	aload_0
	getfield	Field rt:Ljava/lang/Runtime;
	areturn
  Labels:

}

