Compiled from "ThreadPoolConfig.scala"
public final class scala.actors.scheduler.ThreadPoolConfig extends java.lang.Object
  SourceFile: "ThreadPoolConfig.scala"
  ScalaSig: length = 0x20D
   05 00 4A 07 05 01 02 FFFFFF88 02 09 01 10 54 68 72 65
   61 64 50 6F 6F 6C 43 6F 6E 66 69 67 0A 02 03 04
   01 09 73 63 68 65 64 75 6C 65 72 0A 02 05 06 01
   06 61 63 74 6F 72 73 0A 01 07 01 05 73 63 61 6C
   61 03 00 10 02 0A 0B 0D 01 02 06 08 0C 02 FFFFFF84 FFFFFF80
   FFFFFF80 FFFFFF88 02 0D 02 10 54 68 72 65 61 64 50 6F 6F 6C
   43 6F 6E 66 69 67 13 03 0B 0E 16 10 02 0F 14 0D
   01 10 0A 02 11 12 01 04 6C 61 6E 67 0A 01 13 01
   04 6A 61 76 61 09 02 15 10 02 06 4F 62 6A 65 63
   74 10 02 17 18 0D 01 06 09 02 19 06 02 0B 53 63
   61 6C 61 4F 62 6A 65 63 74 08 05 1B 0B FFFFFF84 00 1C
   01 06 3C 69 6E 69 74 3E 14 01 09 08 07 1E 0B FFFFFFC2
   FFFFFF80 FFFFFF84 04 1F 01 02 72 74 15 01 20 10 02 0F 21 09
   02 22 10 02 07 52 75 6E 74 69 6D 65 08 06 24 0B
   FFFFFFA0 FFFFFF80 04 20 01 03 72 74 20 08 07 26 0B FFFFFFC2 FFFFFF80 FFFFFF84
   04 27 01 0D 6D 69 6E 4E 75 6D 54 68 72 65 61 64
   73 15 01 28 10 02 17 29 09 02 2A 06 02 03 49 6E
   74 08 06 2C 0B FFFFFFA0 FFFFFF80 04 28 01 0E 6D 69 6E 4E 75
   6D 54 68 72 65 61 64 73 20 08 05 2E 0B FFFFFF84 04 2F
   01 0E 67 65 74 49 6E 74 65 67 65 72 50 72 6F 70
   14 02 30 33 10 03 17 31 28 09 02 32 06 02 06 4F
   70 74 69 6F 6E 08 05 34 2D FFFFFFC0 00 35 01 08 70 72
   6F 70 4E 61 6D 65 10 02 36 39 0E 02 17 37 09 02
   38 06 01 06 50 72 65 64 65 66 09 02 3A 3B 02 06
   53 74 72 69 6E 67 0A 02 38 06 08 07 3D 0B FFFFFFC2 FFFFFF80
   FFFFFF84 00 27 01 0C 63 6F 72 65 50 6F 6F 6C 53 69 7A
   65 08 06 3F 0B FFFFFFA0 FFFFFF80 04 28 01 0D 63 6F 72 65 50
   6F 6F 6C 53 69 7A 65 20 08 07 41 0B FFFFFFC2 FFFFFF80 FFFFFF84 00
   27 01 0B 6D 61 78 50 6F 6F 6C 53 69 7A 65 08 06
   43 0B FFFFFFA0 FFFFFF80 04 28 01 0C 6D 61 78 50 6F 6F 6C 53
   69 7A 65 20 08 06 45 0B FFFFFF84 00 04 46 01 0B 75 73
   65 46 6F 72 6B 4A 6F 69 6E 15 01 47 10 02 17 48
   09 02 49 06 02 07 42 6F 6F 6C 65 61 6E 
  minor version: 0
  major version: 49
  Constant pool:
const #1 = Asciz	SourceFile;
const #2 = Asciz	ThreadPoolConfig.scala;
const #3 = Asciz	useForkJoin;
const #4 = Asciz	()Z;
const #5 = Asciz	Code;
const #6 = Asciz	scala/actors/scheduler/ThreadPoolConfig$;
const #7 = class	#6;	//  scala/actors/scheduler/ThreadPoolConfig$
const #8 = Asciz	MODULE$;
const #9 = Asciz	Lscala/actors/scheduler/ThreadPoolConfig$;;
const #10 = NameAndType	#8:#9;//  MODULE$:Lscala/actors/scheduler/ThreadPoolConfig$;
const #11 = Field	#7.#10;	//  scala/actors/scheduler/ThreadPoolConfig$.MODULE$:Lscala/actors/scheduler/ThreadPoolConfig$;
const #12 = NameAndType	#3:#4;//  useForkJoin:()Z
const #13 = Method	#7.#12;	//  scala/actors/scheduler/ThreadPoolConfig$.useForkJoin:()Z
const #14 = Asciz	maxPoolSize;
const #15 = Asciz	()I;
const #16 = NameAndType	#14:#15;//  maxPoolSize:()I
const #17 = Method	#7.#16;	//  scala/actors/scheduler/ThreadPoolConfig$.maxPoolSize:()I
const #18 = Asciz	corePoolSize;
const #19 = NameAndType	#18:#15;//  corePoolSize:()I
const #20 = Method	#7.#19;	//  scala/actors/scheduler/ThreadPoolConfig$.corePoolSize:()I
const #21 = Asciz	ScalaSig;
const #22 = Asciz	scala/actors/scheduler/ThreadPoolConfig;
const #23 = class	#22;	//  scala/actors/scheduler/ThreadPoolConfig
const #24 = Asciz	java/lang/Object;
const #25 = class	#24;	//  java/lang/Object

{
public static final boolean useForkJoin();
  Code:
   Stack=1, Locals=0, Args_size=0
   0:	getstatic	#11; //Field scala/actors/scheduler/ThreadPoolConfig$.MODULE$:Lscala/actors/scheduler/ThreadPoolConfig$;
   3:	invokevirtual	#13; //Method scala/actors/scheduler/ThreadPoolConfig$.useForkJoin:()Z
   6:	ireturn

public static final int maxPoolSize();
  Code:
   Stack=1, Locals=0, Args_size=0
   0:	getstatic	#11; //Field scala/actors/scheduler/ThreadPoolConfig$.MODULE$:Lscala/actors/scheduler/ThreadPoolConfig$;
   3:	invokevirtual	#17; //Method scala/actors/scheduler/ThreadPoolConfig$.maxPoolSize:()I
   6:	ireturn

public static final int corePoolSize();
  Code:
   Stack=1, Locals=0, Args_size=0
   0:	getstatic	#11; //Field scala/actors/scheduler/ThreadPoolConfig$.MODULE$:Lscala/actors/scheduler/ThreadPoolConfig$;
   3:	invokevirtual	#20; //Method scala/actors/scheduler/ThreadPoolConfig$.corePoolSize:()I
   6:	ireturn

}

