Compiled from "EncodingHeuristics.scala"
public final class scala.xml.include.sax.EncodingHeuristics$EncodingNames$ extends java.lang.Object implements scala.ScalaObject
  SourceFile: "EncodingHeuristics.scala"
  Scala: length = 0x
   
  minor version: 0
  major version: 49
  Constant pool:
Asciz	SourceFile;
Asciz	EncodingHeuristics.scala;
Asciz	MODULE$;
Asciz	Lscala/xml/include/sax/EncodingHeuristics$EncodingNames$;;
Asciz	<clinit>;
Asciz	()V;
Asciz	Code;
Asciz	scala/xml/include/sax/EncodingHeuristics$EncodingNames$;
class	scala/xml/include/sax/EncodingHeuristics$EncodingNames$
Asciz	<init>;
NameAndType	"<init>":()V
Method	scala/xml/include/sax/EncodingHeuristics$EncodingNames$."<init>":()V
Asciz	bigUCS4;
Asciz	Ljava/lang/String;;
Asciz	littleUCS4;
Asciz	unusualUCS4;
Asciz	bigUTF16;
Asciz	littleUTF16;
Asciz	utf8;
Asciz	default;
Asciz	()Ljava/lang/String;;
Asciz	LineNumberTable;
NameAndType	bigUCS4:Ljava/lang/String;
Field	scala/xml/include/sax/EncodingHeuristics$EncodingNames$.bigUCS4:Ljava/lang/String;
NameAndType	littleUCS4:Ljava/lang/String;
Field	scala/xml/include/sax/EncodingHeuristics$EncodingNames$.littleUCS4:Ljava/lang/String;
NameAndType	unusualUCS4:Ljava/lang/String;
Field	scala/xml/include/sax/EncodingHeuristics$EncodingNames$.unusualUCS4:Ljava/lang/String;
NameAndType	bigUTF16:Ljava/lang/String;
Field	scala/xml/include/sax/EncodingHeuristics$EncodingNames$.bigUTF16:Ljava/lang/String;
NameAndType	littleUTF16:Ljava/lang/String;
Field	scala/xml/include/sax/EncodingHeuristics$EncodingNames$.littleUTF16:Ljava/lang/String;
NameAndType	utf8:Ljava/lang/String;
Field	scala/xml/include/sax/EncodingHeuristics$EncodingNames$.utf8:Ljava/lang/String;
NameAndType	default:Ljava/lang/String;
Field	scala/xml/include/sax/EncodingHeuristics$EncodingNames$.default:Ljava/lang/String;
Asciz	java/lang/Object;
class	java/lang/Object
Method	java/lang/Object."<init>":()V
NameAndType	MODULE$:Lscala/xml/include/sax/EncodingHeuristics$EncodingNames$;
Field	scala/xml/include/sax/EncodingHeuristics$EncodingNames$.MODULE$:Lscala/xml/include/sax/EncodingHeuristics$EncodingNames$;
Asciz	UCS-4;
String	UCS-4
Asciz	UTF-16BE;
String	UTF-16BE
Asciz	UTF-16LE;
String	UTF-16LE
Asciz	UTF-8;
String	UTF-8
NameAndType	utf8:()Ljava/lang/String;
Method	scala/xml/include/sax/EncodingHeuristics$EncodingNames$.utf8:()Ljava/lang/String;
Asciz	Scala;
Asciz	scala/ScalaObject;
class	scala/ScalaObject

{
public static final scala.xml.include.sax.EncodingHeuristics$EncodingNames$ MODULE$;
  Signature: Lscala/xml/include/sax/EncodingHeuristics$EncodingNames$;

private final java.lang.String bigUCS4;
  Signature: Ljava/lang/String;

private final java.lang.String littleUCS4;
  Signature: Ljava/lang/String;

private final java.lang.String unusualUCS4;
  Signature: Ljava/lang/String;

private final java.lang.String bigUTF16;
  Signature: Ljava/lang/String;

private final java.lang.String littleUTF16;
  Signature: Ljava/lang/String;

private final java.lang.String utf8;
  Signature: Ljava/lang/String;

private final java.lang.String default;
  Signature: Ljava/lang/String;

public static {};
  Signature: ()V
  Code:
   Stack=1, Locals=0, Args_size=0
	new	class scala/xml/include/sax/EncodingHeuristics$EncodingNames$
	invokespecial	Method "<init>":()V
	return
  Labels:

public java.lang.String bigUCS4();
  Signature: ()Ljava/lang/String;
  Code:
   Stack=1, Locals=1, Args_size=1
	aload_0
	getfield	Field bigUCS4:Ljava/lang/String;
	areturn
  Labels:

public java.lang.String littleUCS4();
  Signature: ()Ljava/lang/String;
  Code:
   Stack=1, Locals=1, Args_size=1
	aload_0
	getfield	Field littleUCS4:Ljava/lang/String;
	areturn
  Labels:

public java.lang.String unusualUCS4();
  Signature: ()Ljava/lang/String;
  Code:
   Stack=1, Locals=1, Args_size=1
	aload_0
	getfield	Field unusualUCS4:Ljava/lang/String;
	areturn
  Labels:

public java.lang.String bigUTF16();
  Signature: ()Ljava/lang/String;
  Code:
   Stack=1, Locals=1, Args_size=1
	aload_0
	getfield	Field bigUTF16:Ljava/lang/String;
	areturn
  Labels:

public java.lang.String littleUTF16();
  Signature: ()Ljava/lang/String;
  Code:
   Stack=1, Locals=1, Args_size=1
	aload_0
	getfield	Field littleUTF16:Ljava/lang/String;
	areturn
  Labels:

public java.lang.String utf8();
  Signature: ()Ljava/lang/String;
  Code:
   Stack=1, Locals=1, Args_size=1
	aload_0
	getfield	Field utf8:Ljava/lang/String;
	areturn
  Labels:

public java.lang.String default();
  Signature: ()Ljava/lang/String;
  Code:
   Stack=1, Locals=1, Args_size=1
	aload_0
	getfield	Field default:Ljava/lang/String;
	areturn
  Labels:

public scala.xml.include.sax.EncodingHeuristics$EncodingNames$();
  Signature: ()V
  Code:
   Stack=2, Locals=1, Args_size=1
	aload_0
	invokespecial	Method java/lang/Object."<init>":()V
	aload_0
	putstatic	Field MODULE$:Lscala/xml/include/sax/EncodingHeuristics$EncodingNames$;
	aload_0
	ldc	String UCS-4
	putfield	Field bigUCS4:Ljava/lang/String;
	aload_0
	ldc	String UCS-4
	putfield	Field littleUCS4:Ljava/lang/String;
	aload_0
	ldc	String UCS-4
	putfield	Field unusualUCS4:Ljava/lang/String;
	aload_0
	ldc	String UTF-16BE
	putfield	Field bigUTF16:Ljava/lang/String;
	aload_0
	ldc	String UTF-16LE
	putfield	Field littleUTF16:Ljava/lang/String;
	aload_0
	ldc	String UTF-8
	putfield	Field utf8:Ljava/lang/String;
	aload_0
	aload_0
	invokevirtual	Method utf8:()Ljava/lang/String;
	putfield	Field default:Ljava/lang/String;
	return
  Labels:

}

