Compiled from "Main.scala"
public final class scala.xml.include.sax.Main$$anonfun$main$1$$anonfun$apply$4 extends java.lang.Object implements scala.Function0,scala.ScalaObject,java.io.Serializable
  SourceFile: "Main.scala"
  Scala: length = 0x
   
  InnerClass: 
   public final #80= #77 of #79; //$anonfun$main$1=class scala/xml/include/sax/Main$$anonfun$main$1 of class scala/xml/include/sax/Main
   public final #81= #9 of #77; //$anonfun$apply$4=class scala/xml/include/sax/Main$$anonfun$main$1$$anonfun$apply$4 of class scala/xml/include/sax/Main$$anonfun$main$1
  minor version: 0
  major version: 49
  Constant pool:
const #1 = Asciz	SourceFile;
const #2 = Asciz	Main.scala;
const #3 = Asciz	<clinit>;
const #4 = Asciz	()V;
const #5 = Asciz	Code;
const #6 = Asciz	serialVersionUID;
const #7 = Asciz	J;
const #8 = Asciz	scala/xml/include/sax/Main$$anonfun$main$1$$anonfun$apply$4;
const #9 = class	#8;	//  scala/xml/include/sax/Main$$anonfun$main$1$$anonfun$apply$4
const #10 = NameAndType	#6:#7;//  serialVersionUID:J
const #11 = Field	#9.#10;	//  scala/xml/include/sax/Main$$anonfun$main$1$$anonfun$apply$4.serialVersionUID:J
const #12 = Asciz	s$1;
const #13 = Asciz	Lscala/xml/include/sax/XIncluder;;
const #14 = Asciz	includer$1;
const #15 = Asciz	Lscala/xml/include/sax/XIncludeFilter;;
const #16 = Asciz	<init>;
const #17 = Asciz	(Lscala/xml/include/sax/Main$$anonfun$main$1;Lscala/xml/include/sax/XIncludeFilter;Lscala/xml/include/sax/XIncluder;)V;
const #18 = Asciz	LineNumberTable;
const #19 = NameAndType	#14:#15;//  includer$1:Lscala/xml/include/sax/XIncludeFilter;
const #20 = Field	#9.#19;	//  scala/xml/include/sax/Main$$anonfun$main$1$$anonfun$apply$4.includer$1:Lscala/xml/include/sax/XIncludeFilter;
const #21 = NameAndType	#12:#13;//  s$1:Lscala/xml/include/sax/XIncluder;
const #22 = Field	#9.#21;	//  scala/xml/include/sax/Main$$anonfun$main$1$$anonfun$apply$4.s$1:Lscala/xml/include/sax/XIncluder;
const #23 = Asciz	java/lang/Object;
const #24 = class	#23;	//  java/lang/Object
const #25 = NameAndType	#16:#4;//  "<init>":()V
const #26 = Method	#24.#25;	//  java/lang/Object."<init>":()V
const #27 = Asciz	scala/Function0$class;
const #28 = class	#27;	//  scala/Function0$class
const #29 = Asciz	$init$;
const #30 = Asciz	(Lscala/Function0;)V;
const #31 = NameAndType	#29:#30;//  $init$:(Lscala/Function0;)V
const #32 = Method	#28.#31;	//  scala/Function0$class.$init$:(Lscala/Function0;)V
const #33 = Asciz	this;
const #34 = Asciz	Lscala/xml/include/sax/Main$$anonfun$main$1$$anonfun$apply$4;;
const #35 = Asciz	$outer;
const #36 = Asciz	Lscala/xml/include/sax/Main$$anonfun$main$1;;
const #37 = Asciz	LocalVariableTable;
const #38 = Asciz	apply;
const #39 = Asciz	()Ljava/lang/Object;;
const #40 = NameAndType	#38:#4;//  apply:()V
const #41 = Method	#9.#40;	//  scala/xml/include/sax/Main$$anonfun$main$1$$anonfun$apply$4.apply:()V
const #42 = Asciz	scala/runtime/BoxedUnit;
const #43 = class	#42;	//  scala/runtime/BoxedUnit
const #44 = Asciz	UNIT;
const #45 = Asciz	Lscala/runtime/BoxedUnit;;
const #46 = NameAndType	#44:#45;//  UNIT:Lscala/runtime/BoxedUnit;
const #47 = Field	#43.#46;	//  scala/runtime/BoxedUnit.UNIT:Lscala/runtime/BoxedUnit;
const #48 = Asciz	scala/xml/include/sax/Main$;
const #49 = class	#48;	//  scala/xml/include/sax/Main$
const #50 = Asciz	MODULE$;
const #51 = Asciz	Lscala/xml/include/sax/Main$;;
const #52 = NameAndType	#50:#51;//  MODULE$:Lscala/xml/include/sax/Main$;
const #53 = Field	#49.#52;	//  scala/xml/include/sax/Main$.MODULE$:Lscala/xml/include/sax/Main$;
const #54 = Asciz	scala$xml$include$sax$Main$$lexicalHandler;
const #55 = Asciz	()Ljava/lang/String;;
const #56 = NameAndType	#54:#55;//  scala$xml$include$sax$Main$$lexicalHandler:()Ljava/lang/String;
const #57 = Method	#49.#56;	//  scala/xml/include/sax/Main$.scala$xml$include$sax$Main$$lexicalHandler:()Ljava/lang/String;
const #58 = Asciz	scala/xml/include/sax/XIncludeFilter;
const #59 = class	#58;	//  scala/xml/include/sax/XIncludeFilter
const #60 = Asciz	setProperty;
const #61 = Asciz	(Ljava/lang/String;Ljava/lang/Object;)V;
const #62 = NameAndType	#60:#61;//  setProperty:(Ljava/lang/String;Ljava/lang/Object;)V
const #63 = Method	#59.#62;	//  scala/xml/include/sax/XIncludeFilter.setProperty:(Ljava/lang/String;Ljava/lang/Object;)V
const #64 = Asciz	scala/xml/include/sax/XIncluder;
const #65 = class	#64;	//  scala/xml/include/sax/XIncluder
const #66 = Asciz	setFilter;
const #67 = Asciz	(Lscala/xml/include/sax/XIncludeFilter;)V;
const #68 = NameAndType	#66:#67;//  setFilter:(Lscala/xml/include/sax/XIncludeFilter;)V
const #69 = Method	#65.#68;	//  scala/xml/include/sax/XIncluder.setFilter:(Lscala/xml/include/sax/XIncludeFilter;)V
const #70 = Asciz	toString;
const #71 = Asciz	(Lscala/Function0;)Ljava/lang/String;;
const #72 = NameAndType	#70:#71;//  toString:(Lscala/Function0;)Ljava/lang/String;
const #73 = Method	#28.#72;	//  scala/Function0$class.toString:(Lscala/Function0;)Ljava/lang/String;
const #74 = Asciz	Scala;
const #75 = Asciz	InnerClasses;
const #76 = Asciz	scala/xml/include/sax/Main$$anonfun$main$1;
const #77 = class	#76;	//  scala/xml/include/sax/Main$$anonfun$main$1
const #78 = Asciz	scala/xml/include/sax/Main;
const #79 = class	#78;	//  scala/xml/include/sax/Main
const #80 = Asciz	$anonfun$main$1;
const #81 = Asciz	$anonfun$apply$4;
const #82 = Asciz	scala/Function0;
const #83 = class	#82;	//  scala/Function0
const #84 = Asciz	scala/ScalaObject;
const #85 = class	#84;	//  scala/ScalaObject
const #86 = Asciz	java/io/Serializable;
const #87 = class	#86;	//  java/io/Serializable

{
public static final long serialVersionUID;

public static {};
  Code:
   Stack=2, Locals=0, Args_size=0
   0:	lconst_0
   1:	putstatic	#11; //Field serialVersionUID:J
   4:	return

public scala.xml.include.sax.Main$$anonfun$main$1$$anonfun$apply$4(scala.xml.include.sax.Main$$anonfun$main$1, scala.xml.include.sax.XIncludeFilter, scala.xml.include.sax.XIncluder);
  Code:
   Stack=2, Locals=4, Args_size=4
   0:	aload_0
   1:	aload_2
   2:	putfield	#20; //Field includer$1:Lscala/xml/include/sax/XIncludeFilter;
   5:	aload_0
   6:	aload_3
   7:	putfield	#22; //Field s$1:Lscala/xml/include/sax/XIncluder;
   10:	aload_0
   11:	invokespecial	#26; //Method java/lang/Object."<init>":()V
   14:	aload_0
   15:	invokestatic	#32; //Method scala/Function0$class.$init$:(Lscala/Function0;)V
   18:	return
  LineNumberTable: 
   line 69: 0

  LocalVariableTable: 
   Start  Length  Slot  Name   Signature
   0      19      0    this       Lscala/xml/include/sax/Main$$anonfun$main$1$$anonfun$apply$4;
   0      19      1    $outer       Lscala/xml/include/sax/Main$$anonfun$main$1;


public final java.lang.Object apply();
  Code:
   Stack=1, Locals=1, Args_size=1
   0:	aload_0
   1:	invokevirtual	#41; //Method apply:()V
   4:	getstatic	#47; //Field scala/runtime/BoxedUnit.UNIT:Lscala/runtime/BoxedUnit;
   7:	areturn
  LineNumberTable: 
   line 69: 0


public final void apply();
  Code:
   Stack=3, Locals=1, Args_size=1
   0:	aload_0
   1:	getfield	#20; //Field includer$1:Lscala/xml/include/sax/XIncludeFilter;
   4:	getstatic	#53; //Field scala/xml/include/sax/Main$.MODULE$:Lscala/xml/include/sax/Main$;
   7:	invokevirtual	#57; //Method scala/xml/include/sax/Main$.scala$xml$include$sax$Main$$lexicalHandler:()Ljava/lang/String;
   10:	aload_0
   11:	getfield	#22; //Field s$1:Lscala/xml/include/sax/XIncluder;
   14:	invokevirtual	#63; //Method scala/xml/include/sax/XIncludeFilter.setProperty:(Ljava/lang/String;Ljava/lang/Object;)V
   17:	aload_0
   18:	getfield	#22; //Field s$1:Lscala/xml/include/sax/XIncluder;
   21:	aload_0
   22:	getfield	#20; //Field includer$1:Lscala/xml/include/sax/XIncludeFilter;
   25:	invokevirtual	#69; //Method scala/xml/include/sax/XIncluder.setFilter:(Lscala/xml/include/sax/XIncludeFilter;)V
   28:	return
  LineNumberTable: 
   line 70: 0
   line 71: 17


public java.lang.String toString();
  Code:
   Stack=1, Locals=1, Args_size=1
   0:	aload_0
   1:	invokestatic	#73; //Method scala/Function0$class.toString:(Lscala/Function0;)Ljava/lang/String;
   4:	areturn
  LineNumberTable: 
   line 69: 0


}

