Compiled from "Main.scala"
public final class scala.xml.include.sax.Main$$anonfun$main$1$$anonfun$apply$3 extends java.lang.Object implements scala.Function1,scala.ScalaObject,java.io.Serializable
  SourceFile: "Main.scala"
  Scala: length = 0x
   
  InnerClass: 
   public final $anonfun$main$1=class scala/xml/include/sax/Main$$anonfun$main$1 of class scala/xml/include/sax/Main
   public final $anonfun$apply$3=class scala/xml/include/sax/Main$$anonfun$main$1$$anonfun$apply$3 of class scala/xml/include/sax/Main$$anonfun$main$1
  minor version: 0
  major version: 49
  Constant pool:
Asciz	SourceFile;
Asciz	Main.scala;
Asciz	<clinit>;
Asciz	()V;
Asciz	Code;
Asciz	serialVersionUID;
Asciz	J;
Asciz	scala/xml/include/sax/Main$$anonfun$main$1$$anonfun$apply$3;
class	scala/xml/include/sax/Main$$anonfun$main$1$$anonfun$apply$3
NameAndType	serialVersionUID:J
Field	scala/xml/include/sax/Main$$anonfun$main$1$$anonfun$apply$3.serialVersionUID:J
Asciz	includer$1;
Asciz	Lscala/xml/include/sax/XIncludeFilter;;
Asciz	<init>;
Asciz	(Lscala/xml/include/sax/Main$$anonfun$main$1;Lscala/xml/include/sax/XIncludeFilter;)V;
Asciz	LineNumberTable;
NameAndType	includer$1:Lscala/xml/include/sax/XIncludeFilter;
Field	scala/xml/include/sax/Main$$anonfun$main$1$$anonfun$apply$3.includer$1:Lscala/xml/include/sax/XIncludeFilter;
Asciz	java/lang/Object;
class	java/lang/Object
NameAndType	"<init>":()V
Method	java/lang/Object."<init>":()V
Asciz	scala/Function1$class;
class	scala/Function1$class
Asciz	$init$;
Asciz	(Lscala/Function1;)V;
NameAndType	$init$:(Lscala/Function1;)V
Method	scala/Function1$class.$init$:(Lscala/Function1;)V
Asciz	this;
Asciz	Lscala/xml/include/sax/Main$$anonfun$main$1$$anonfun$apply$3;;
Asciz	$outer;
Asciz	Lscala/xml/include/sax/Main$$anonfun$main$1;;
Asciz	LocalVariableTable;
Asciz	apply;
Asciz	(Ljava/lang/Object;)Ljava/lang/Object;;
Asciz	org/xml/sax/EntityResolver;
class	org/xml/sax/EntityResolver
Asciz	(Lorg/xml/sax/EntityResolver;)V;
NameAndType	apply:(Lorg/xml/sax/EntityResolver;)V
Method	scala/xml/include/sax/Main$$anonfun$main$1$$anonfun$apply$3.apply:(Lorg/xml/sax/EntityResolver;)V
Asciz	scala/runtime/BoxedUnit;
class	scala/runtime/BoxedUnit
Asciz	UNIT;
Asciz	Lscala/runtime/BoxedUnit;;
NameAndType	UNIT:Lscala/runtime/BoxedUnit;
Field	scala/runtime/BoxedUnit.UNIT:Lscala/runtime/BoxedUnit;
Asciz	v1;
Asciz	Ljava/lang/Object;;
Asciz	scala/xml/include/sax/XIncludeFilter;
class	scala/xml/include/sax/XIncludeFilter
Asciz	setEntityResolver;
NameAndType	setEntityResolver:(Lorg/xml/sax/EntityResolver;)V
Method	scala/xml/include/sax/XIncludeFilter.setEntityResolver:(Lorg/xml/sax/EntityResolver;)V
Asciz	andThen;
Asciz	(Lscala/Function1;)Lscala/Function1;;
Asciz	(Lscala/Function1;Lscala/Function1;)Lscala/Function1;;
NameAndType	andThen:(Lscala/Function1;Lscala/Function1;)Lscala/Function1;
Method	scala/Function1$class.andThen:(Lscala/Function1;Lscala/Function1;)Lscala/Function1;
Asciz	g;
Asciz	Lscala/Function1;;
Asciz	compose;
NameAndType	compose:(Lscala/Function1;Lscala/Function1;)Lscala/Function1;
Method	scala/Function1$class.compose:(Lscala/Function1;Lscala/Function1;)Lscala/Function1;
Asciz	toString;
Asciz	()Ljava/lang/String;;
Asciz	(Lscala/Function1;)Ljava/lang/String;;
NameAndType	toString:(Lscala/Function1;)Ljava/lang/String;
Method	scala/Function1$class.toString:(Lscala/Function1;)Ljava/lang/String;
Asciz	Scala;
Asciz	InnerClasses;
Asciz	scala/xml/include/sax/Main$$anonfun$main$1;
class	scala/xml/include/sax/Main$$anonfun$main$1
Asciz	scala/xml/include/sax/Main;
class	scala/xml/include/sax/Main
Asciz	$anonfun$main$1;
Asciz	$anonfun$apply$3;
Asciz	scala/Function1;
class	scala/Function1
Asciz	scala/ScalaObject;
class	scala/ScalaObject
Asciz	java/io/Serializable;
class	java/io/Serializable

{
public static final long serialVersionUID;
  Signature: J

private final scala.xml.include.sax.XIncludeFilter includer$1;
  Signature: Lscala/xml/include/sax/XIncludeFilter;

public static {};
  Signature: ()V
  Code:
   Stack=2, Locals=0, Args_size=0
	lconst_0
	putstatic	Field serialVersionUID:J
	return
  Labels:

public scala.xml.include.sax.Main$$anonfun$main$1$$anonfun$apply$3(scala.xml.include.sax.Main$$anonfun$main$1, scala.xml.include.sax.XIncludeFilter);
  Signature: (Lscala/xml/include/sax/Main$$anonfun$main$1;Lscala/xml/include/sax/XIncludeFilter;)V
  Code:
   Stack=2, Locals=3, Args_size=3
	aload_0
	aload_2
	putfield	Field includer$1:Lscala/xml/include/sax/XIncludeFilter;
	aload_0
	invokespecial	Method java/lang/Object."<init>":()V
	aload_0
	invokestatic	Method scala/Function1$class.$init$:(Lscala/Function1;)V
	return
  Labels:
  LocalVariableTable: 
   Start  Length  Slot  Name   Signature
   0      14      0    this       Lscala/xml/include/sax/Main$$anonfun$main$1$$anonfun$apply$3;
   0      14      1    $outer       Lscala/xml/include/sax/Main$$anonfun$main$1;


public final java.lang.Object apply(java.lang.Object);
  Signature: (Ljava/lang/Object;)Ljava/lang/Object;
  Code:
   Stack=2, Locals=2, Args_size=2
	aload_0
	aload_1
	checkcast	class org/xml/sax/EntityResolver
	invokevirtual	Method apply:(Lorg/xml/sax/EntityResolver;)V
	getstatic	Field scala/runtime/BoxedUnit.UNIT:Lscala/runtime/BoxedUnit;
	areturn
  Labels:
  LocalVariableTable: 
   Start  Length  Slot  Name   Signature
   0      12      0    this       Lscala/xml/include/sax/Main$$anonfun$main$1$$anonfun$apply$3;
   0      12      1    v1       Ljava/lang/Object;


public final void apply(org.xml.sax.EntityResolver);
  Signature: (Lorg/xml/sax/EntityResolver;)V
  Code:
   Stack=2, Locals=2, Args_size=2
	aload_0
	getfield	Field includer$1:Lscala/xml/include/sax/XIncludeFilter;
	aload_1
	invokevirtual	Method scala/xml/include/sax/XIncludeFilter.setEntityResolver:(Lorg/xml/sax/EntityResolver;)V
	return
  Labels:

public scala.Function1 andThen(scala.Function1);
  Signature: (Lscala/Function1;)Lscala/Function1;
  Code:
   Stack=2, Locals=2, Args_size=2
	aload_0
	aload_1
	invokestatic	Method scala/Function1$class.andThen:(Lscala/Function1;Lscala/Function1;)Lscala/Function1;
	areturn
  Labels:
  LocalVariableTable: 
   Start  Length  Slot  Name   Signature
   0      6      0    this       Lscala/xml/include/sax/Main$$anonfun$main$1$$anonfun$apply$3;
   0      6      1    g       Lscala/Function1;


public scala.Function1 compose(scala.Function1);
  Signature: (Lscala/Function1;)Lscala/Function1;
  Code:
   Stack=2, Locals=2, Args_size=2
	aload_0
	aload_1
	invokestatic	Method scala/Function1$class.compose:(Lscala/Function1;Lscala/Function1;)Lscala/Function1;
	areturn
  Labels:
  LocalVariableTable: 
   Start  Length  Slot  Name   Signature
   0      6      0    this       Lscala/xml/include/sax/Main$$anonfun$main$1$$anonfun$apply$3;
   0      6      1    g       Lscala/Function1;


public java.lang.String toString();
  Signature: ()Ljava/lang/String;
  Code:
   Stack=1, Locals=1, Args_size=1
	aload_0
	invokestatic	Method scala/Function1$class.toString:(Lscala/Function1;)Ljava/lang/String;
	areturn
  Labels:

}

