Compiled from "Main.scala"
public final class scala.xml.include.sax.Main extends java.lang.Object
  SourceFile: "Main.scala"
  ScalaSig: length = 0x1A8
   05 00 40 07 05 01 02 FFFFFF88 02 0B 01 04 4D 61 69 6E
   0A 02 03 04 01 03 73 61 78 0A 02 05 06 01 07 69
   6E 63 6C 75 64 65 0A 02 07 08 01 03 78 6D 6C 0A
   01 09 01 05 73 63 61 6C 61 03 00 10 02 0C 0D 0D
   01 02 06 08 0E 02 FFFFFF84 FFFFFF80 FFFFFF80 FFFFFF88 02 0F 02 04 4D 61
   69 6E 13 03 0D 10 18 10 02 11 16 0D 01 12 0A 02
   13 14 01 04 6C 61 6E 67 0A 01 15 01 04 6A 61 76
   61 09 02 17 12 02 06 4F 62 6A 65 63 74 10 02 19
   1A 0D 01 08 09 02 1B 08 02 0B 53 63 61 6C 61 4F
   62 6A 65 63 74 08 05 1D 0D FFFFFF84 00 1E 01 06 3C 69
   6E 69 74 3E 14 01 0B 08 07 20 0D FFFFFFC2 FFFFFF80 FFFFFF84 04 21
   01 0B 78 65 72 63 65 73 43 6C 61 73 73 15 01 22
   10 02 11 23 09 02 24 12 02 06 53 74 72 69 6E 67
   08 06 26 0D FFFFFFA0 FFFFFF80 04 22 01 0C 78 65 72 63 65 73
   43 6C 61 73 73 20 08 07 28 0D FFFFFFC2 FFFFFF80 FFFFFF84 04 21 01
   11 6E 61 6D 65 73 70 61 63 65 50 72 65 66 69 78
   65 73 08 06 2A 0D FFFFFFA0 FFFFFF80 04 22 01 12 6E 61 6D 65
   73 70 61 63 65 50 72 65 66 69 78 65 73 20 08 07
   2C 0D FFFFFFC2 FFFFFF80 FFFFFF84 04 21 01 0E 6C 65 78 69 63 61 6C
   48 61 6E 64 6C 65 72 08 06 2E 0D FFFFFFA0 FFFFFF80 04 22 01
   0F 6C 65 78 69 63 61 6C 48 61 6E 64 6C 65 72 20
   08 05 30 0D FFFFFF84 00 31 01 04 6D 61 69 6E 14 02 32
   35 10 02 19 33 09 02 34 08 02 04 55 6E 69 74 08
   05 36 2F FFFFFFC0 00 37 01 04 61 72 67 73 10 03 19 38
   3A 09 02 39 08 02 05 41 72 72 61 79 10 02 3B 3E
   0E 02 19 3C 09 02 3D 08 01 06 50 72 65 64 65 66
   09 02 24 3F 0A 02 3D 08 
  InnerClass: 
   public final #35= #32 of #34; //$anonfun$4=class scala/xml/include/sax/Main$$anonfun$4 of class scala/xml/include/sax/Main
   public final #38= #37 of #34; //$anonfun$3=class scala/xml/include/sax/Main$$anonfun$3 of class scala/xml/include/sax/Main
   public final #41= #40 of #34; //$anonfun$2=class scala/xml/include/sax/Main$$anonfun$2 of class scala/xml/include/sax/Main
   public final #44= #43 of #34; //$anonfun$1=class scala/xml/include/sax/Main$$anonfun$1 of class scala/xml/include/sax/Main
   public final #47= #46 of #34; //$anonfun$main$1=class scala/xml/include/sax/Main$$anonfun$main$1 of class scala/xml/include/sax/Main
  minor version: 0
  major version: 49
  Constant pool:
const #1 = Asciz	SourceFile;
const #2 = Asciz	Main.scala;
const #3 = Asciz	error$1;
const #4 = Asciz	(Ljava/lang/String;)V;
const #5 = Asciz	Code;
const #6 = Asciz	scala/xml/include/sax/Main$;
const #7 = class	#6;	//  scala/xml/include/sax/Main$
const #8 = Asciz	MODULE$;
const #9 = Asciz	Lscala/xml/include/sax/Main$;;
const #10 = NameAndType	#8:#9;//  MODULE$:Lscala/xml/include/sax/Main$;
const #11 = Field	#7.#10;	//  scala/xml/include/sax/Main$.MODULE$:Lscala/xml/include/sax/Main$;
const #12 = NameAndType	#3:#4;//  error$1:(Ljava/lang/String;)V
const #13 = Method	#7.#12;	//  scala/xml/include/sax/Main$.error$1:(Ljava/lang/String;)V
const #14 = Asciz	saxe$1;
const #15 = Asciz	(Lscala/Function0;)Lscala/Option;;
const #16 = NameAndType	#14:#15;//  saxe$1:(Lscala/Function0;)Lscala/Option;
const #17 = Method	#7.#16;	//  scala/xml/include/sax/Main$.saxe$1:(Lscala/Function0;)Lscala/Option;
const #18 = Asciz	main;
const #19 = Asciz	([Ljava/lang/String;)V;
const #20 = NameAndType	#18:#19;//  main:([Ljava/lang/String;)V
const #21 = Method	#7.#20;	//  scala/xml/include/sax/Main$.main:([Ljava/lang/String;)V
const #22 = Asciz	scala$xml$include$sax$Main$$lexicalHandler;
const #23 = Asciz	()Ljava/lang/String;;
const #24 = NameAndType	#22:#23;//  scala$xml$include$sax$Main$$lexicalHandler:()Ljava/lang/String;
const #25 = Method	#7.#24;	//  scala/xml/include/sax/Main$.scala$xml$include$sax$Main$$lexicalHandler:()Ljava/lang/String;
const #26 = Asciz	scala$xml$include$sax$Main$$xercesClass;
const #27 = NameAndType	#26:#23;//  scala$xml$include$sax$Main$$xercesClass:()Ljava/lang/String;
const #28 = Method	#7.#27;	//  scala/xml/include/sax/Main$.scala$xml$include$sax$Main$$xercesClass:()Ljava/lang/String;
const #29 = Asciz	ScalaSig;
const #30 = Asciz	InnerClasses;
const #31 = Asciz	scala/xml/include/sax/Main$$anonfun$4;
const #32 = class	#31;	//  scala/xml/include/sax/Main$$anonfun$4
const #33 = Asciz	scala/xml/include/sax/Main;
const #34 = class	#33;	//  scala/xml/include/sax/Main
const #35 = Asciz	$anonfun$4;
const #36 = Asciz	scala/xml/include/sax/Main$$anonfun$3;
const #37 = class	#36;	//  scala/xml/include/sax/Main$$anonfun$3
const #38 = Asciz	$anonfun$3;
const #39 = Asciz	scala/xml/include/sax/Main$$anonfun$2;
const #40 = class	#39;	//  scala/xml/include/sax/Main$$anonfun$2
const #41 = Asciz	$anonfun$2;
const #42 = Asciz	scala/xml/include/sax/Main$$anonfun$1;
const #43 = class	#42;	//  scala/xml/include/sax/Main$$anonfun$1
const #44 = Asciz	$anonfun$1;
const #45 = Asciz	scala/xml/include/sax/Main$$anonfun$main$1;
const #46 = class	#45;	//  scala/xml/include/sax/Main$$anonfun$main$1
const #47 = Asciz	$anonfun$main$1;
const #48 = Asciz	java/lang/Object;
const #49 = class	#48;	//  java/lang/Object

{
public static final void error$1(java.lang.String);
  Code:
   Stack=2, Locals=1, Args_size=1
   0:	getstatic	#11; //Field scala/xml/include/sax/Main$.MODULE$:Lscala/xml/include/sax/Main$;
   3:	aload_0
   4:	invokevirtual	#13; //Method scala/xml/include/sax/Main$.error$1:(Ljava/lang/String;)V
   7:	return

public static final scala.Option saxe$1(scala.Function0);
  Code:
   Stack=2, Locals=1, Args_size=1
   0:	getstatic	#11; //Field scala/xml/include/sax/Main$.MODULE$:Lscala/xml/include/sax/Main$;
   3:	aload_0
   4:	invokevirtual	#17; //Method scala/xml/include/sax/Main$.saxe$1:(Lscala/Function0;)Lscala/Option;
   7:	areturn

public static final void main(java.lang.String[]);
  Code:
   Stack=2, Locals=1, Args_size=1
   0:	getstatic	#11; //Field scala/xml/include/sax/Main$.MODULE$:Lscala/xml/include/sax/Main$;
   3:	aload_0
   4:	invokevirtual	#21; //Method scala/xml/include/sax/Main$.main:([Ljava/lang/String;)V
   7:	return

public static final java.lang.String scala$xml$include$sax$Main$$lexicalHandler();
  Code:
   Stack=1, Locals=0, Args_size=0
   0:	getstatic	#11; //Field scala/xml/include/sax/Main$.MODULE$:Lscala/xml/include/sax/Main$;
   3:	invokevirtual	#25; //Method scala/xml/include/sax/Main$.scala$xml$include$sax$Main$$lexicalHandler:()Ljava/lang/String;
   6:	areturn

public static final java.lang.String scala$xml$include$sax$Main$$xercesClass();
  Code:
   Stack=1, Locals=0, Args_size=0
   0:	getstatic	#11; //Field scala/xml/include/sax/Main$.MODULE$:Lscala/xml/include/sax/Main$;
   3:	invokevirtual	#28; //Method scala/xml/include/sax/Main$.scala$xml$include$sax$Main$$xercesClass:()Ljava/lang/String;
   6:	areturn

}

