Compiled from "Main.scala"
public final class scala.xml.include.sax.Main$$anonfun$3 extends scala.runtime.AbstractFunction0 implements java.io.Serializable
  SourceFile: "Main.scala"
  Scala: length = 0x
   
  InnerClass: 
   public final $anonfun$3=class scala/xml/include/sax/Main$$anonfun$3 of class scala/xml/include/sax/Main
  minor version: 0
  major version: 49
  Constant pool:
Asciz	SourceFile;
Asciz	Main.scala;
Asciz	<clinit>;
Asciz	()V;
Asciz	Code;
Asciz	serialVersionUID;
Asciz	J;
Asciz	scala/xml/include/sax/Main$$anonfun$3;
class	scala/xml/include/sax/Main$$anonfun$3
NameAndType	serialVersionUID:J
Field	scala/xml/include/sax/Main$$anonfun$3.serialVersionUID:J
Asciz	parser$1;
Asciz	Lorg/xml/sax/XMLReader;;
Asciz	args$1;
Asciz	[Ljava/lang/String;;
Asciz	<init>;
Asciz	([Ljava/lang/String;Lorg/xml/sax/XMLReader;)V;
Asciz	LineNumberTable;
NameAndType	args$1:[Ljava/lang/String;
Field	scala/xml/include/sax/Main$$anonfun$3.args$1:[Ljava/lang/String;
NameAndType	parser$1:Lorg/xml/sax/XMLReader;
Field	scala/xml/include/sax/Main$$anonfun$3.parser$1:Lorg/xml/sax/XMLReader;
Asciz	scala/runtime/AbstractFunction0;
class	scala/runtime/AbstractFunction0
NameAndType	"<init>":()V
Method	scala/runtime/AbstractFunction0."<init>":()V
Asciz	apply;
Asciz	()Ljava/lang/Object;;
Asciz	()Lorg/xml/sax/EntityResolver;;
NameAndType	apply:()Lorg/xml/sax/EntityResolver;
Method	scala/xml/include/sax/Main$$anonfun$3.apply:()Lorg/xml/sax/EntityResolver;
Asciz	java/lang/Class;
class	java/lang/Class
Asciz	forName;
Asciz	(Ljava/lang/String;)Ljava/lang/Class;;
NameAndType	forName:(Ljava/lang/String;)Ljava/lang/Class;
Method	java/lang/Class.forName:(Ljava/lang/String;)Ljava/lang/Class;
Asciz	newInstance;
NameAndType	newInstance:()Ljava/lang/Object;
Method	java/lang/Class.newInstance:()Ljava/lang/Object;
Asciz	org/xml/sax/EntityResolver;
class	org/xml/sax/EntityResolver
Asciz	org/xml/sax/XMLReader;
class	org/xml/sax/XMLReader
Asciz	setEntityResolver;
Asciz	(Lorg/xml/sax/EntityResolver;)V;
NameAndType	setEntityResolver:(Lorg/xml/sax/EntityResolver;)V
InterfaceMethod	org/xml/sax/XMLReader.setEntityResolver:(Lorg/xml/sax/EntityResolver;)V
Asciz	this;
Asciz	Lscala/xml/include/sax/Main$$anonfun$3;;
Asciz	r;
Asciz	Lorg/xml/sax/EntityResolver;;
Asciz	LocalVariableTable;
Asciz	Scala;
Asciz	InnerClasses;
Asciz	scala/xml/include/sax/Main;
class	scala/xml/include/sax/Main
Asciz	$anonfun$3;
Asciz	java/io/Serializable;
class	java/io/Serializable

{
public static final long serialVersionUID;
  Signature: J

private final org.xml.sax.XMLReader parser$1;
  Signature: Lorg/xml/sax/XMLReader;

private final java.lang.String[] args$1;
  Signature: [Ljava/lang/String;

public static {};
  Signature: ()V
  Code:
   Stack=2, Locals=0, Args_size=0
	lconst_0
	putstatic	Field serialVersionUID:J
	return
  Labels:

public scala.xml.include.sax.Main$$anonfun$3(java.lang.String[], org.xml.sax.XMLReader);
  Signature: ([Ljava/lang/String;Lorg/xml/sax/XMLReader;)V
  Code:
   Stack=2, Locals=3, Args_size=3
	aload_0
	aload_1
	putfield	Field args$1:[Ljava/lang/String;
	aload_0
	aload_2
	putfield	Field parser$1:Lorg/xml/sax/XMLReader;
	aload_0
	invokespecial	Method scala/runtime/AbstractFunction0."<init>":()V
	return
  Labels:

public final java.lang.Object apply();
  Signature: ()Ljava/lang/Object;
  Code:
   Stack=1, Locals=1, Args_size=1
	aload_0
	invokevirtual	Method apply:()Lorg/xml/sax/EntityResolver;
	areturn
  Labels:

public final org.xml.sax.EntityResolver apply();
  Signature: ()Lorg/xml/sax/EntityResolver;
  Code:
   Stack=2, Locals=2, Args_size=1
	aload_0
	getfield	Field args$1:[Ljava/lang/String;
	iconst_1
	aaload
	invokestatic	Method java/lang/Class.forName:(Ljava/lang/String;)Ljava/lang/Class;
	invokevirtual	Method java/lang/Class.newInstance:()Ljava/lang/Object;
	checkcast	class org/xml/sax/EntityResolver
	astore_1
	aload_0
	getfield	Field parser$1:Lorg/xml/sax/XMLReader;
	aload_1
	invokeinterface	InterfaceMethod org/xml/sax/XMLReader.setEntityResolver:(Lorg/xml/sax/EntityResolver;)V
	aload_1
	areturn
  Labels:
  LocalVariableTable: 
   Start  Length  Slot  Name   Signature
   0      28      0    this       Lscala/xml/include/sax/Main$$anonfun$3;
   16      11      1    r       Lorg/xml/sax/EntityResolver;


}

