Compiled from "Main.scala"
public final class scala.xml.include.sax.Main$$anonfun$4 extends java.lang.Object implements scala.Function0,scala.ScalaObject,java.io.Serializable
  SourceFile: "Main.scala"
  Scala: length = 0x
   
  InnerClass: 
   public final $anonfun$4=class scala/xml/include/sax/Main$$anonfun$4 of class scala/xml/include/sax/Main
  minor version: 0
  major version: 49
  Constant pool:
Asciz	SourceFile;
Asciz	Main.scala;
Asciz	<clinit>;
Asciz	()V;
Asciz	Code;
Asciz	serialVersionUID;
Asciz	J;
Asciz	scala/xml/include/sax/Main$$anonfun$4;
class	scala/xml/include/sax/Main$$anonfun$4
NameAndType	serialVersionUID:J
Field	scala/xml/include/sax/Main$$anonfun$4.serialVersionUID:J
Asciz	nonLocalReturnKey1$1;
Asciz	Ljava/lang/Object;;
Asciz	<init>;
Asciz	(Ljava/lang/Object;)V;
Asciz	LineNumberTable;
NameAndType	nonLocalReturnKey1$1:Ljava/lang/Object;
Field	scala/xml/include/sax/Main$$anonfun$4.nonLocalReturnKey1$1:Ljava/lang/Object;
Asciz	java/lang/Object;
class	java/lang/Object
NameAndType	"<init>":()V
Method	java/lang/Object."<init>":()V
Asciz	scala/Function0$class;
class	scala/Function0$class
Asciz	$init$;
Asciz	(Lscala/Function0;)V;
NameAndType	$init$:(Lscala/Function0;)V
Method	scala/Function0$class.$init$:(Lscala/Function0;)V
Asciz	apply;
Asciz	()Ljava/lang/Object;;
Asciz	()Lscala/runtime/Nothing$;;
NameAndType	apply:()Lscala/runtime/Nothing$;
Method	scala/xml/include/sax/Main$$anonfun$4.apply:()Lscala/runtime/Nothing$;
Asciz	scala/runtime/NonLocalReturnException;
class	scala/runtime/NonLocalReturnException
Asciz	scala/xml/include/sax/Main$;
class	scala/xml/include/sax/Main$
Asciz	MODULE$;
Asciz	Lscala/xml/include/sax/Main$;;
NameAndType	MODULE$:Lscala/xml/include/sax/Main$;
Field	scala/xml/include/sax/Main$.MODULE$:Lscala/xml/include/sax/Main$;
Asciz	Could not load requested EntityResolver;
String	Could not load requested EntityResolver
Asciz	error$1;
Asciz	(Ljava/lang/String;)V;
NameAndType	error$1:(Ljava/lang/String;)V
Method	scala/xml/include/sax/Main$.error$1:(Ljava/lang/String;)V
Asciz	scala/runtime/BoxedUnit;
class	scala/runtime/BoxedUnit
Asciz	UNIT;
Asciz	Lscala/runtime/BoxedUnit;;
NameAndType	UNIT:Lscala/runtime/BoxedUnit;
Field	scala/runtime/BoxedUnit.UNIT:Lscala/runtime/BoxedUnit;
Asciz	(Ljava/lang/Object;Ljava/lang/Object;)V;
NameAndType	"<init>":(Ljava/lang/Object;Ljava/lang/Object;)V
Method	scala/runtime/NonLocalReturnException."<init>":(Ljava/lang/Object;Ljava/lang/Object;)V
Asciz	toString;
Asciz	()Ljava/lang/String;;
Asciz	(Lscala/Function0;)Ljava/lang/String;;
NameAndType	toString:(Lscala/Function0;)Ljava/lang/String;
Method	scala/Function0$class.toString:(Lscala/Function0;)Ljava/lang/String;
Asciz	Scala;
Asciz	InnerClasses;
Asciz	scala/xml/include/sax/Main;
class	scala/xml/include/sax/Main
Asciz	$anonfun$4;
Asciz	scala/Function0;
class	scala/Function0
Asciz	scala/ScalaObject;
class	scala/ScalaObject
Asciz	java/io/Serializable;
class	java/io/Serializable

{
public static final long serialVersionUID;
  Signature: J

private final java.lang.Object nonLocalReturnKey1$1;
  Signature: Ljava/lang/Object;

public static {};
  Signature: ()V
  Code:
   Stack=2, Locals=0, Args_size=0
	lconst_0
	putstatic	Field serialVersionUID:J
	return
  Labels:

public scala.xml.include.sax.Main$$anonfun$4(java.lang.Object);
  Signature: (Ljava/lang/Object;)V
  Code:
   Stack=2, Locals=2, Args_size=2
	aload_0
	aload_1
	putfield	Field nonLocalReturnKey1$1:Ljava/lang/Object;
	aload_0
	invokespecial	Method java/lang/Object."<init>":()V
	aload_0
	invokestatic	Method scala/Function0$class.$init$:(Lscala/Function0;)V
	return
  Labels:

public final java.lang.Object apply();
  Signature: ()Ljava/lang/Object;
  Code:
   Stack=1, Locals=1, Args_size=1
	aload_0
	invokevirtual	Method apply:()Lscala/runtime/Nothing$;
	athrow
  Labels:

public final scala.runtime.Nothing$ apply();
  Signature: ()Lscala/runtime/Nothing$;
  Code:
   Stack=5, Locals=1, Args_size=1
	new	class scala/runtime/NonLocalReturnException
	dup
	aload_0
	getfield	Field nonLocalReturnKey1$1:Ljava/lang/Object;
	getstatic	Field scala/xml/include/sax/Main$.MODULE$:Lscala/xml/include/sax/Main$;
	ldc	String Could not load requested EntityResolver
	invokevirtual	Method scala/xml/include/sax/Main$.error$1:(Ljava/lang/String;)V
	getstatic	Field scala/runtime/BoxedUnit.UNIT:Lscala/runtime/BoxedUnit;
	invokespecial	Method scala/runtime/NonLocalReturnException."<init>":(Ljava/lang/Object;Ljava/lang/Object;)V
	athrow
  Labels:

public java.lang.String toString();
  Signature: ()Ljava/lang/String;
  Code:
   Stack=1, Locals=1, Args_size=1
	aload_0
	invokestatic	Method scala/Function0$class.toString:(Lscala/Function0;)Ljava/lang/String;
	areturn
  Labels:

}

