Compiled from "Main.scala"
public final class scala.xml.include.sax.Main$ extends java.lang.Object implements scala.ScalaObject
  SourceFile: "Main.scala"
  Scala: length = 0x
   
  InnerClass: 
   public ofRef=class scala/collection/mutable/ArrayOps$ofRef of class scala/collection/mutable/ArrayOps
   public Catch=class scala/util/control/Exception$Catch of class scala/util/control/Exception
   public final $anonfun$4=class scala/xml/include/sax/Main$$anonfun$4 of class scala/xml/include/sax/Main
   public final $anonfun$3=class scala/xml/include/sax/Main$$anonfun$3 of class scala/xml/include/sax/Main
   public final $anonfun$2=class scala/xml/include/sax/Main$$anonfun$2 of class scala/xml/include/sax/Main
   public final $anonfun$1=class scala/xml/include/sax/Main$$anonfun$1 of class scala/xml/include/sax/Main
   public final $anonfun$main$1=class scala/xml/include/sax/Main$$anonfun$main$1 of class scala/xml/include/sax/Main
  minor version: 0
  major version: 49
  Constant pool:
Asciz	SourceFile;
Asciz	Main.scala;
Asciz	MODULE$;
Asciz	Lscala/xml/include/sax/Main$;;
Asciz	<clinit>;
Asciz	()V;
Asciz	Code;
Asciz	scala/xml/include/sax/Main$;
class	scala/xml/include/sax/Main$
Asciz	<init>;
NameAndType	"<init>":()V
Method	scala/xml/include/sax/Main$."<init>":()V
Asciz	namespacePrefixes;
Asciz	Ljava/lang/String;;
Asciz	scala$xml$include$sax$Main$$lexicalHandler;
Asciz	()Ljava/lang/String;;
Asciz	LineNumberTable;
NameAndType	namespacePrefixes:Ljava/lang/String;
Field	scala/xml/include/sax/Main$.namespacePrefixes:Ljava/lang/String;
NameAndType	scala$xml$include$sax$Main$$lexicalHandler:Ljava/lang/String;
Field	scala/xml/include/sax/Main$.scala$xml$include$sax$Main$$lexicalHandler:Ljava/lang/String;
Asciz	main;
Asciz	([Ljava/lang/String;)V;
Asciz	java/lang/Object;
class	java/lang/Object
Method	java/lang/Object."<init>":()V
Asciz	scala/xml/include/sax/Main$$anonfun$1;
class	scala/xml/include/sax/Main$$anonfun$1
Method	scala/xml/include/sax/Main$$anonfun$1."<init>":()V
Asciz	scala/util/control/Exception$;
class	scala/util/control/Exception$
Asciz	Lscala/util/control/Exception$;;
NameAndType	MODULE$:Lscala/util/control/Exception$;
Field	scala/util/control/Exception$.MODULE$:Lscala/util/control/Exception$;
Asciz	scala/Predef$;
class	scala/Predef$
Asciz	Lscala/Predef$;;
NameAndType	MODULE$:Lscala/Predef$;
Field	scala/Predef$.MODULE$:Lscala/Predef$;
Asciz	java/lang/Class;
class	java/lang/Class
Asciz	org/xml/sax/SAXException;
class	org/xml/sax/SAXException
Asciz	[Ljava/lang/Object;;
class	"[Ljava/lang/Object;"
Asciz	wrapRefArray;
Asciz	([Ljava/lang/Object;)Lscala/collection/mutable/WrappedArray;;
NameAndType	wrapRefArray:([Ljava/lang/Object;)Lscala/collection/mutable/WrappedArray;
Method	scala/Predef$.wrapRefArray:([Ljava/lang/Object;)Lscala/collection/mutable/WrappedArray;
Asciz	catching;
Asciz	(Lscala/collection/Seq;)Lscala/util/control/Exception$Catch;;
NameAndType	catching:(Lscala/collection/Seq;)Lscala/util/control/Exception$Catch;
Method	scala/util/control/Exception$.catching:(Lscala/collection/Seq;)Lscala/util/control/Exception$Catch;
Asciz	scala/util/control/Exception$Catch;
class	scala/util/control/Exception$Catch
Asciz	opt;
Asciz	(Lscala/Function0;)Lscala/Option;;
NameAndType	opt:(Lscala/Function0;)Lscala/Option;
Method	scala/util/control/Exception$Catch.opt:(Lscala/Function0;)Lscala/Option;
Asciz	scala/xml/include/sax/Main$$anonfun$2;
class	scala/xml/include/sax/Main$$anonfun$2
Asciz	(Ljava/lang/Object;)V;
NameAndType	"<init>":(Ljava/lang/Object;)V
Method	scala/xml/include/sax/Main$$anonfun$2."<init>":(Ljava/lang/Object;)V
Asciz	scala/Option;
class	scala/Option
Asciz	getOrElse;
Asciz	(Lscala/Function0;)Ljava/lang/Object;;
NameAndType	getOrElse:(Lscala/Function0;)Ljava/lang/Object;
Method	scala/Option.getOrElse:(Lscala/Function0;)Ljava/lang/Object;
Asciz	org/xml/sax/XMLReader;
class	org/xml/sax/XMLReader
NameAndType	namespacePrefixes:()Ljava/lang/String;
Method	scala/xml/include/sax/Main$.namespacePrefixes:()Ljava/lang/String;
Asciz	setFeature;
Asciz	(Ljava/lang/String;Z)V;
NameAndType	setFeature:(Ljava/lang/String;Z)V
InterfaceMethod	org/xml/sax/XMLReader.setFeature:(Ljava/lang/String;Z)V
Asciz	scala/collection/mutable/ArrayOps$ofRef;
class	scala/collection/mutable/ArrayOps$ofRef
Asciz	([Ljava/lang/Object;)V;
NameAndType	"<init>":([Ljava/lang/Object;)V
Method	scala/collection/mutable/ArrayOps$ofRef."<init>":([Ljava/lang/Object;)V
Asciz	scala/collection/IndexedSeqOptimized;
class	scala/collection/IndexedSeqOptimized
Asciz	isEmpty;
Asciz	()Z;
NameAndType	isEmpty:()Z
InterfaceMethod	scala/collection/IndexedSeqOptimized.isEmpty:()Z
Asciz	dashR$1;
Asciz	([Ljava/lang/String;)Z;
NameAndType	dashR$1:([Ljava/lang/String;)Z
Method	scala/xml/include/sax/Main$.dashR$1:([Ljava/lang/String;)Z
Asciz	drop;
Asciz	(I)Ljava/lang/Object;;
NameAndType	drop:(I)Ljava/lang/Object;
InterfaceMethod	scala/collection/IndexedSeqOptimized.drop:(I)Ljava/lang/Object;
Asciz	[Ljava/lang/String;;
class	"[Ljava/lang/String;"
Asciz	scala/None$;
class	scala/None$
Asciz	Lscala/None$;;
NameAndType	MODULE$:Lscala/None$;
Field	scala/None$.MODULE$:Lscala/None$;
Asciz	java/lang/Exception;
class	java/lang/Exception
Asciz	scala/xml/include/sax/Main$$anonfun$3;
class	scala/xml/include/sax/Main$$anonfun$3
Asciz	([Ljava/lang/String;Lorg/xml/sax/XMLReader;)V;
NameAndType	"<init>":([Ljava/lang/String;Lorg/xml/sax/XMLReader;)V
Method	scala/xml/include/sax/Main$$anonfun$3."<init>":([Ljava/lang/String;Lorg/xml/sax/XMLReader;)V
Asciz	scala/xml/include/sax/Main$$anonfun$4;
class	scala/xml/include/sax/Main$$anonfun$4
Method	scala/xml/include/sax/Main$$anonfun$4."<init>":(Ljava/lang/Object;)V
Asciz	orElse;
NameAndType	orElse:(Lscala/Function0;)Lscala/Option;
Method	scala/Option.orElse:(Lscala/Function0;)Lscala/Option;
Asciz	scala/xml/include/sax/Main$$anonfun$main$1;
class	scala/xml/include/sax/Main$$anonfun$main$1
Asciz	(Lorg/xml/sax/XMLReader;Lscala/Option;)V;
NameAndType	"<init>":(Lorg/xml/sax/XMLReader;Lscala/Option;)V
Method	scala/xml/include/sax/Main$$anonfun$main$1."<init>":(Lorg/xml/sax/XMLReader;Lscala/Option;)V
Asciz	foreach;
Asciz	(Lscala/Function1;)V;
NameAndType	foreach:(Lscala/Function1;)V
InterfaceMethod	scala/collection/IndexedSeqOptimized.foreach:(Lscala/Function1;)V
Asciz	java/lang/System;
class	java/lang/System
Asciz	err;
Asciz	Ljava/io/PrintStream;;
NameAndType	err:Ljava/io/PrintStream;
Field	java/lang/System.err:Ljava/io/PrintStream;
Asciz	java/io/PrintStream;
class	java/io/PrintStream
Asciz	println;
NameAndType	println:(Ljava/lang/Object;)V
Method	java/io/PrintStream.println:(Ljava/lang/Object;)V
Asciz	scala/runtime/NonLocalReturnControl;
class	scala/runtime/NonLocalReturnControl
Asciz	key;
Asciz	()Ljava/lang/Object;;
NameAndType	key:()Ljava/lang/Object;
Method	scala/runtime/NonLocalReturnControl.key:()Ljava/lang/Object;
Asciz	this;
Asciz	args$1;
Asciz	body0;
Asciz	Lscala/Function0;;
Asciz	xs0;
Asciz	xs1;
Asciz	args2;
Asciz	xs2;
Asciz	parser$1;
Asciz	Lorg/xml/sax/XMLReader;;
Asciz	resolver$1;
Asciz	Lscala/Option;;
Asciz	LocalVariableTable;
Asciz	saxe$1;
Asciz	body;
Asciz	error$1;
Asciz	(Ljava/lang/String;)V;
NameAndType	println:(Ljava/lang/String;)V
Method	java/io/PrintStream.println:(Ljava/lang/String;)V
Asciz	msg;
Asciz	scala/collection/SeqLike;
class	scala/collection/SeqLike
Asciz	size;
Asciz	()I;
NameAndType	size:()I
InterfaceMethod	scala/collection/SeqLike.size:()I
Asciz	-r;
String	-r
Asciz	equals;
Asciz	(Ljava/lang/Object;)Z;
NameAndType	equals:(Ljava/lang/Object;)Z
Method	java/lang/Object.equals:(Ljava/lang/Object;)Z
NameAndType	MODULE$:Lscala/xml/include/sax/Main$;
Field	scala/xml/include/sax/Main$.MODULE$:Lscala/xml/include/sax/Main$;
Asciz	http://xml.org/sax/features/namespace-prefixes;
String	http://xml.org/sax/features/namespace-prefixes
Asciz	http://xml.org/sax/properties/lexical-handler;
String	http://xml.org/sax/properties/lexical-handler
Asciz	Scala;
Asciz	InnerClasses;
Asciz	scala/collection/mutable/ArrayOps;
class	scala/collection/mutable/ArrayOps
Asciz	ofRef;
Asciz	scala/util/control/Exception;
class	scala/util/control/Exception
Asciz	Catch;
Asciz	scala/xml/include/sax/Main;
class	scala/xml/include/sax/Main
Asciz	$anonfun$4;
Asciz	$anonfun$3;
Asciz	$anonfun$2;
Asciz	$anonfun$1;
Asciz	$anonfun$main$1;
Asciz	scala/ScalaObject;
class	scala/ScalaObject

{
public static final scala.xml.include.sax.Main$ MODULE$;
  Signature: Lscala/xml/include/sax/Main$;

private final java.lang.String namespacePrefixes;
  Signature: Ljava/lang/String;

private final java.lang.String scala$xml$include$sax$Main$$lexicalHandler;
  Signature: Ljava/lang/String;

public static {};
  Signature: ()V
  Code:
   Stack=1, Locals=0, Args_size=0
	new	class scala/xml/include/sax/Main$
	invokespecial	Method "<init>":()V
	return
  Labels:

private java.lang.String namespacePrefixes();
  Signature: ()Ljava/lang/String;
  Code:
   Stack=1, Locals=1, Args_size=1
	aload_0
	getfield	Field namespacePrefixes:Ljava/lang/String;
	areturn
  Labels:

public final java.lang.String scala$xml$include$sax$Main$$lexicalHandler();
  Signature: ()Ljava/lang/String;
  Code:
   Stack=1, Locals=1, Args_size=1
	aload_0
	getfield	Field scala$xml$include$sax$Main$$lexicalHandler:Ljava/lang/String;
	areturn
  Labels:

public void main(java.lang.String[]);
  Signature: ([Ljava/lang/String;)V
  Code:
   Stack=6, Locals=12, Args_size=2
	new	class java/lang/Object
	dup
	invokespecial	Method java/lang/Object."<init>":()V
	astore	10
	new	class scala/xml/include/sax/Main$$anonfun$1
	dup
	invokespecial	Method scala/xml/include/sax/Main$$anonfun$1."<init>":()V
	astore_2
	getstatic	Field scala/util/control/Exception$.MODULE$:Lscala/util/control/Exception$;
	getstatic	Field scala/Predef$.MODULE$:Lscala/Predef$;
	iconst_1
	anewarray	class java/lang/Class
	dup
	iconst_0
	ldc	class org/xml/sax/SAXException
	aastore
	checkcast	class "[Ljava/lang/Object;"
	invokevirtual	Method scala/Predef$.wrapRefArray:([Ljava/lang/Object;)Lscala/collection/mutable/WrappedArray;
	invokevirtual	Method scala/util/control/Exception$.catching:(Lscala/collection/Seq;)Lscala/util/control/Exception$Catch;
	aload_2
	invokevirtual	Method scala/util/control/Exception$Catch.opt:(Lscala/Function0;)Lscala/Option;
	new	class scala/xml/include/sax/Main$$anonfun$2
	dup
	aload	10
	invokespecial	Method scala/xml/include/sax/Main$$anonfun$2."<init>":(Ljava/lang/Object;)V
	invokevirtual	Method scala/Option.getOrElse:(Lscala/Function0;)Ljava/lang/Object;
	checkcast	class org/xml/sax/XMLReader
	astore	7
	aload	7
	aload_0
	invokespecial	Method namespacePrefixes:()Ljava/lang/String;
	iconst_1
	invokeinterface	InterfaceMethod org/xml/sax/XMLReader.setFeature:(Ljava/lang/String;Z)V
	aload_1
	checkcast	class "[Ljava/lang/Object;"
	astore_3
	new	class scala/collection/mutable/ArrayOps$ofRef
	dup
	aload_3
	invokespecial	Method scala/collection/mutable/ArrayOps$ofRef."<init>":([Ljava/lang/Object;)V
	invokeinterface	InterfaceMethod scala/collection/IndexedSeqOptimized.isEmpty:()Z
	ifeq	l1 // aload_0
	return
l1	aload_0
	aload_1
	invokespecial	Method dashR$1:([Ljava/lang/String;)Z
	ifeq	l2 // aload_1
	aload_1
	checkcast	class "[Ljava/lang/Object;"
	astore	4
	new	class scala/collection/mutable/ArrayOps$ofRef
	dup
	aload	4
	invokespecial	Method scala/collection/mutable/ArrayOps$ofRef."<init>":([Ljava/lang/Object;)V
	iconst_2
	invokeinterface	InterfaceMethod scala/collection/IndexedSeqOptimized.drop:(I)Ljava/lang/Object;
	checkcast	class "[Ljava/lang/String;"
	goto	l3 // astore
l2	aload_1
l3	astore	5
	aload_0
	aload_1
	invokespecial	Method dashR$1:([Ljava/lang/String;)Z
	ifeq	l4 // getstatic
	getstatic	Field scala/None$.MODULE$:Lscala/None$;
	goto	l5 // astore
l4	getstatic	Field scala/util/control/Exception$.MODULE$:Lscala/util/control/Exception$;
	getstatic	Field scala/Predef$.MODULE$:Lscala/Predef$;
	iconst_1
	anewarray	class java/lang/Class
	dup
	iconst_0
	ldc	class java/lang/Exception
	aastore
	checkcast	class "[Ljava/lang/Object;"
	invokevirtual	Method scala/Predef$.wrapRefArray:([Ljava/lang/Object;)Lscala/collection/mutable/WrappedArray;
	invokevirtual	Method scala/util/control/Exception$.catching:(Lscala/collection/Seq;)Lscala/util/control/Exception$Catch;
	new	class scala/xml/include/sax/Main$$anonfun$3
	dup
	aload_1
	aload	7
	invokespecial	Method scala/xml/include/sax/Main$$anonfun$3."<init>":([Ljava/lang/String;Lorg/xml/sax/XMLReader;)V
	invokevirtual	Method scala/util/control/Exception$Catch.opt:(Lscala/Function0;)Lscala/Option;
	new	class scala/xml/include/sax/Main$$anonfun$4
	dup
	aload	10
	invokespecial	Method scala/xml/include/sax/Main$$anonfun$4."<init>":(Ljava/lang/Object;)V
	invokevirtual	Method scala/Option.orElse:(Lscala/Function0;)Lscala/Option;
l5	astore	8
	aload	5
	checkcast	class "[Ljava/lang/Object;"
	astore	6
	new	class scala/collection/mutable/ArrayOps$ofRef
	dup
	aload	6
	invokespecial	Method scala/collection/mutable/ArrayOps$ofRef."<init>":([Ljava/lang/Object;)V
	new	class scala/xml/include/sax/Main$$anonfun$main$1
	dup
	aload	7
	aload	8
	invokespecial	Method scala/xml/include/sax/Main$$anonfun$main$1."<init>":(Lorg/xml/sax/XMLReader;Lscala/Option;)V
	invokeinterface	InterfaceMethod scala/collection/IndexedSeqOptimized.foreach:(Lscala/Function1;)V
	goto	l6 // return
	astore	9
	getstatic	Field java/lang/System.err:Ljava/io/PrintStream;
	aload	9
	invokevirtual	Method java/io/PrintStream.println:(Ljava/lang/Object;)V
	return
	astore	11
	aload	11
	invokevirtual	Method scala/runtime/NonLocalReturnControl.key:()Ljava/lang/Object;
	aload	10
	if_acmpne	l7 // aload
l6	return
l7	aload	11
	athrow
  Labels:
   	l1 = 96 // aload_0
   	l2 = 131 // aload_1
   	l3 = 132 // astore
   	l4 = 148 // getstatic
   	l5 = 197 // astore
   	l6 = 257 // return
   	l7 = 258 // aload
  Exception table:
   from   to  target type
    62    74   234   Class org/xml/sax/SAXException

     9   245   245   Class scala/runtime/NonLocalReturnControl

  LocalVariableTable: 
   Start  Length  Slot  Name   Signature
   0      261      0    this       Lscala/xml/include/sax/Main$;
   0      261      1    args$1       [Ljava/lang/String;
   17      28      2    body0       Lscala/Function0;
   79      8      3    xs0       [Ljava/lang/Object;
   110      9      4    xs1       [Ljava/lang/Object;
   134      97      5    args2       [Ljava/lang/String;
   206      9      6    xs2       [Ljava/lang/Object;
   62      169      7    parser$1       Lorg/xml/sax/XMLReader;
   234      11      7    parser$1       Lorg/xml/sax/XMLReader;
   199      32      8    resolver$1       Lscala/Option;


public final scala.Option saxe$1(scala.Function0);
  Signature: (Lscala/Function0;)Lscala/Option;
  Code:
   Stack=6, Locals=2, Args_size=2
	getstatic	Field scala/util/control/Exception$.MODULE$:Lscala/util/control/Exception$;
	getstatic	Field scala/Predef$.MODULE$:Lscala/Predef$;
	iconst_1
	anewarray	class java/lang/Class
	dup
	iconst_0
	ldc	class org/xml/sax/SAXException
	aastore
	checkcast	class "[Ljava/lang/Object;"
	invokevirtual	Method scala/Predef$.wrapRefArray:([Ljava/lang/Object;)Lscala/collection/mutable/WrappedArray;
	invokevirtual	Method scala/util/control/Exception$.catching:(Lscala/collection/Seq;)Lscala/util/control/Exception$Catch;
	aload_1
	invokevirtual	Method scala/util/control/Exception$Catch.opt:(Lscala/Function0;)Lscala/Option;
	areturn
  Labels:
  LocalVariableTable: 
   Start  Length  Slot  Name   Signature
   0      29      0    this       Lscala/xml/include/sax/Main$;
   0      29      1    body       Lscala/Function0;


public final void error$1(java.lang.String);
  Signature: (Ljava/lang/String;)V
  Code:
   Stack=2, Locals=2, Args_size=2
	getstatic	Field java/lang/System.err:Ljava/io/PrintStream;
	aload_1
	invokevirtual	Method java/io/PrintStream.println:(Ljava/lang/String;)V
	return
  Labels:
  LocalVariableTable: 
   Start  Length  Slot  Name   Signature
   0      8      0    this       Lscala/xml/include/sax/Main$;
   0      8      1    msg       Ljava/lang/String;


private final boolean dashR$1(java.lang.String[]);
  Signature: ([Ljava/lang/String;)Z
  Code:
   Stack=3, Locals=4, Args_size=2
	aload_1
	checkcast	class "[Ljava/lang/Object;"
	astore_2
	new	class scala/collection/mutable/ArrayOps$ofRef
	dup
	aload_2
	invokespecial	Method scala/collection/mutable/ArrayOps$ofRef."<init>":([Ljava/lang/Object;)V
	invokeinterface	InterfaceMethod scala/collection/SeqLike.size:()I
	iconst_2
	if_icmplt	l1 // iconst_0
	aload_1
	iconst_0
	aaload
	ldc	String -r
	astore_3
	dup
	ifnonnull	l2 // aload_3
	pop
	aload_3
	ifnull	l3 // iconst_1
	goto	l1 // iconst_0
l2	aload_3
	invokevirtual	Method java/lang/Object.equals:(Ljava/lang/Object;)Z
	ifeq	l1 // iconst_0
l3	iconst_1
	goto	l4 // ireturn
l1	iconst_0
l4	ireturn
  Labels:
   	l2 = 40 // aload_3
   	l3 = 47 // iconst_1
   	l1 = 51 // iconst_0
   	l4 = 52 // ireturn
  LocalVariableTable: 
   Start  Length  Slot  Name   Signature
   0      53      0    this       Lscala/xml/include/sax/Main$;


private scala.xml.include.sax.Main$();
  Signature: ()V
  Code:
   Stack=2, Locals=1, Args_size=1
	aload_0
	invokespecial	Method java/lang/Object."<init>":()V
	aload_0
	putstatic	Field MODULE$:Lscala/xml/include/sax/Main$;
	aload_0
	ldc	String http://xml.org/sax/features/namespace-prefixes
	putfield	Field namespacePrefixes:Ljava/lang/String;
	aload_0
	ldc	String http://xml.org/sax/properties/lexical-handler
	putfield	Field scala$xml$include$sax$Main$$lexicalHandler:Ljava/lang/String;
	return
  Labels:

}

