Compiled from "Main.scala"
public final class scala.xml.include.sax.Main$$anonfun$main$1 extends java.lang.Object implements scala.Function1,scala.ScalaObject,java.io.Serializable
  SourceFile: "Main.scala"
  Scala: length = 0x
   
  InnerClass: 
   public #201= #115 of #200; //Catch=class scala/util/control/Exception$Catch of class scala/util/control/Exception
   public final #204= #9 of #203; //$anonfun$main$1=class scala/xml/include/sax/Main$$anonfun$main$1 of class scala/xml/include/sax/Main
   public final #205= #112 of #200; //$anonfun$ignoring$1=class scala/util/control/Exception$$anonfun$ignoring$1 of class scala/util/control/Exception
   public final #206= #121 of #9; //$anonfun$apply$4=class scala/xml/include/sax/Main$$anonfun$main$1$$anonfun$apply$4 of class scala/xml/include/sax/Main$$anonfun$main$1
   public final #207= #76 of #9; //$anonfun$apply$3=class scala/xml/include/sax/Main$$anonfun$main$1$$anonfun$apply$3 of class scala/xml/include/sax/Main$$anonfun$main$1
  minor version: 0
  major version: 49
  Constant pool:
const #1 = Asciz	SourceFile;
const #2 = Asciz	Main.scala;
const #3 = Asciz	<clinit>;
const #4 = Asciz	()V;
const #5 = Asciz	Code;
const #6 = Asciz	serialVersionUID;
const #7 = Asciz	J;
const #8 = Asciz	scala/xml/include/sax/Main$$anonfun$main$1;
const #9 = class	#8;	//  scala/xml/include/sax/Main$$anonfun$main$1
const #10 = NameAndType	#6:#7;//  serialVersionUID:J
const #11 = Field	#9.#10;	//  scala/xml/include/sax/Main$$anonfun$main$1.serialVersionUID:J
const #12 = Asciz	resolver$1;
const #13 = Asciz	Lscala/Option;;
const #14 = Asciz	parser$1;
const #15 = Asciz	Lorg/xml/sax/XMLReader;;
const #16 = Asciz	<init>;
const #17 = Asciz	(Lorg/xml/sax/XMLReader;Lscala/Option;)V;
const #18 = Asciz	LineNumberTable;
const #19 = NameAndType	#14:#15;//  parser$1:Lorg/xml/sax/XMLReader;
const #20 = Field	#9.#19;	//  scala/xml/include/sax/Main$$anonfun$main$1.parser$1:Lorg/xml/sax/XMLReader;
const #21 = NameAndType	#12:#13;//  resolver$1:Lscala/Option;
const #22 = Field	#9.#21;	//  scala/xml/include/sax/Main$$anonfun$main$1.resolver$1:Lscala/Option;
const #23 = Asciz	java/lang/Object;
const #24 = class	#23;	//  java/lang/Object
const #25 = NameAndType	#16:#4;//  "<init>":()V
const #26 = Method	#24.#25;	//  java/lang/Object."<init>":()V
const #27 = Asciz	scala/Function1$class;
const #28 = class	#27;	//  scala/Function1$class
const #29 = Asciz	$init$;
const #30 = Asciz	(Lscala/Function1;)V;
const #31 = NameAndType	#29:#30;//  $init$:(Lscala/Function1;)V
const #32 = Method	#28.#31;	//  scala/Function1$class.$init$:(Lscala/Function1;)V
const #33 = Asciz	apply;
const #34 = Asciz	(Ljava/lang/Object;)Ljava/lang/Object;;
const #35 = Asciz	java/lang/String;
const #36 = class	#35;	//  java/lang/String
const #37 = Asciz	(Ljava/lang/String;)V;
const #38 = NameAndType	#33:#37;//  apply:(Ljava/lang/String;)V
const #39 = Method	#9.#38;	//  scala/xml/include/sax/Main$$anonfun$main$1.apply:(Ljava/lang/String;)V
const #40 = Asciz	scala/runtime/BoxedUnit;
const #41 = class	#40;	//  scala/runtime/BoxedUnit
const #42 = Asciz	UNIT;
const #43 = Asciz	Lscala/runtime/BoxedUnit;;
const #44 = NameAndType	#42:#43;//  UNIT:Lscala/runtime/BoxedUnit;
const #45 = Field	#41.#44;	//  scala/runtime/BoxedUnit.UNIT:Lscala/runtime/BoxedUnit;
const #46 = Asciz	this;
const #47 = Asciz	Lscala/xml/include/sax/Main$$anonfun$main$1;;
const #48 = Asciz	v1;
const #49 = Asciz	Ljava/lang/Object;;
const #50 = Asciz	LocalVariableTable;
const #51 = Asciz	scala/xml/include/sax/XIncludeFilter;
const #52 = class	#51;	//  scala/xml/include/sax/XIncludeFilter
const #53 = Method	#52.#25;	//  scala/xml/include/sax/XIncludeFilter."<init>":()V
const #54 = Asciz	setParent;
const #55 = Asciz	(Lorg/xml/sax/XMLReader;)V;
const #56 = NameAndType	#54:#55;//  setParent:(Lorg/xml/sax/XMLReader;)V
const #57 = Method	#52.#56;	//  scala/xml/include/sax/XIncludeFilter.setParent:(Lorg/xml/sax/XMLReader;)V
const #58 = Asciz	scala/xml/include/sax/XIncluder;
const #59 = class	#58;	//  scala/xml/include/sax/XIncluder
const #60 = Asciz	java/lang/System;
const #61 = class	#60;	//  java/lang/System
const #62 = Asciz	out;
const #63 = Asciz	Ljava/io/PrintStream;;
const #64 = NameAndType	#62:#63;//  out:Ljava/io/PrintStream;
const #65 = Field	#61.#64;	//  java/lang/System.out:Ljava/io/PrintStream;
const #66 = Asciz	UTF-8;
const #67 = String	#66;	//  UTF-8
const #68 = Asciz	(Ljava/io/OutputStream;Ljava/lang/String;)V;
const #69 = NameAndType	#16:#68;//  "<init>":(Ljava/io/OutputStream;Ljava/lang/String;)V
const #70 = Method	#59.#69;	//  scala/xml/include/sax/XIncluder."<init>":(Ljava/io/OutputStream;Ljava/lang/String;)V
const #71 = Asciz	setContentHandler;
const #72 = Asciz	(Lorg/xml/sax/ContentHandler;)V;
const #73 = NameAndType	#71:#72;//  setContentHandler:(Lorg/xml/sax/ContentHandler;)V
const #74 = Method	#52.#73;	//  scala/xml/include/sax/XIncludeFilter.setContentHandler:(Lorg/xml/sax/ContentHandler;)V
const #75 = Asciz	scala/xml/include/sax/Main$$anonfun$main$1$$anonfun$apply$3;
const #76 = class	#75;	//  scala/xml/include/sax/Main$$anonfun$main$1$$anonfun$apply$3
const #77 = Asciz	(Lscala/xml/include/sax/Main$$anonfun$main$1;Lscala/xml/include/sax/XIncludeFilter;)V;
const #78 = NameAndType	#16:#77;//  "<init>":(Lscala/xml/include/sax/Main$$anonfun$main$1;Lscala/xml/include/sax/XIncludeFilter;)V
const #79 = Method	#76.#78;	//  scala/xml/include/sax/Main$$anonfun$main$1$$anonfun$apply$3."<init>":(Lscala/xml/include/sax/Main$$anonfun$main$1;Lscala/xml/include/sax/XIncludeFilter;)V
const #80 = Asciz	scala/Option;
const #81 = class	#80;	//  scala/Option
const #82 = Asciz	map;
const #83 = Asciz	(Lscala/Function1;)Lscala/Option;;
const #84 = NameAndType	#82:#83;//  map:(Lscala/Function1;)Lscala/Option;
const #85 = Method	#81.#84;	//  scala/Option.map:(Lscala/Function1;)Lscala/Option;
const #86 = Asciz	scala/util/control/Exception$;
const #87 = class	#86;	//  scala/util/control/Exception$
const #88 = Asciz	MODULE$;
const #89 = Asciz	Lscala/util/control/Exception$;;
const #90 = NameAndType	#88:#89;//  MODULE$:Lscala/util/control/Exception$;
const #91 = Field	#87.#90;	//  scala/util/control/Exception$.MODULE$:Lscala/util/control/Exception$;
const #92 = Asciz	scala/Predef$;
const #93 = class	#92;	//  scala/Predef$
const #94 = Asciz	Lscala/Predef$;;
const #95 = NameAndType	#88:#94;//  MODULE$:Lscala/Predef$;
const #96 = Field	#93.#95;	//  scala/Predef$.MODULE$:Lscala/Predef$;
const #97 = Asciz	java/lang/Class;
const #98 = class	#97;	//  java/lang/Class
const #99 = Asciz	org/xml/sax/SAXException;
const #100 = class	#99;	//  org/xml/sax/SAXException
const #101 = Asciz	[Ljava/lang/Object;;
const #102 = class	#101;	//  "[Ljava/lang/Object;"
const #103 = Asciz	wrapRefArray;
const #104 = Asciz	([Ljava/lang/Object;)Lscala/collection/mutable/WrappedArray;;
const #105 = NameAndType	#103:#104;//  wrapRefArray:([Ljava/lang/Object;)Lscala/collection/mutable/WrappedArray;
const #106 = Method	#93.#105;	//  scala/Predef$.wrapRefArray:([Ljava/lang/Object;)Lscala/collection/mutable/WrappedArray;
const #107 = Asciz	catching;
const #108 = Asciz	(Lscala/collection/Seq;)Lscala/util/control/Exception$Catch;;
const #109 = NameAndType	#107:#108;//  catching:(Lscala/collection/Seq;)Lscala/util/control/Exception$Catch;
const #110 = Method	#87.#109;	//  scala/util/control/Exception$.catching:(Lscala/collection/Seq;)Lscala/util/control/Exception$Catch;
const #111 = Asciz	scala/util/control/Exception$$anonfun$ignoring$1;
const #112 = class	#111;	//  scala/util/control/Exception$$anonfun$ignoring$1
const #113 = Method	#112.#25;	//  scala/util/control/Exception$$anonfun$ignoring$1."<init>":()V
const #114 = Asciz	scala/util/control/Exception$Catch;
const #115 = class	#114;	//  scala/util/control/Exception$Catch
const #116 = Asciz	withApply;
const #117 = Asciz	(Lscala/Function1;)Lscala/util/control/Exception$Catch;;
const #118 = NameAndType	#116:#117;//  withApply:(Lscala/Function1;)Lscala/util/control/Exception$Catch;
const #119 = Method	#115.#118;	//  scala/util/control/Exception$Catch.withApply:(Lscala/Function1;)Lscala/util/control/Exception$Catch;
const #120 = Asciz	scala/xml/include/sax/Main$$anonfun$main$1$$anonfun$apply$4;
const #121 = class	#120;	//  scala/xml/include/sax/Main$$anonfun$main$1$$anonfun$apply$4
const #122 = Asciz	(Lscala/xml/include/sax/Main$$anonfun$main$1;Lscala/xml/include/sax/XIncludeFilter;Lscala/xml/include/sax/XIncluder;)V;
const #123 = NameAndType	#16:#122;//  "<init>":(Lscala/xml/include/sax/Main$$anonfun$main$1;Lscala/xml/include/sax/XIncludeFilter;Lscala/xml/include/sax/XIncluder;)V
const #124 = Method	#121.#123;	//  scala/xml/include/sax/Main$$anonfun$main$1$$anonfun$apply$4."<init>":(Lscala/xml/include/sax/Main$$anonfun$main$1;Lscala/xml/include/sax/XIncludeFilter;Lscala/xml/include/sax/XIncluder;)V
const #125 = Asciz	(Lscala/Function0;)Ljava/lang/Object;;
const #126 = NameAndType	#33:#125;//  apply:(Lscala/Function0;)Ljava/lang/Object;
const #127 = Method	#115.#126;	//  scala/util/control/Exception$Catch.apply:(Lscala/Function0;)Ljava/lang/Object;
const #128 = Asciz	parse;
const #129 = NameAndType	#128:#37;//  parse:(Ljava/lang/String;)V
const #130 = Method	#52.#129;	//  scala/xml/include/sax/XIncludeFilter.parse:(Ljava/lang/String;)V
const #131 = Asciz	toString;
const #132 = Asciz	()Ljava/lang/String;;
const #133 = NameAndType	#131:#132;//  toString:()Ljava/lang/String;
const #134 = Method	#100.#133;	//  org/xml/sax/SAXException.toString:()Ljava/lang/String;
const #135 = Asciz	err;
const #136 = NameAndType	#135:#63;//  err:Ljava/io/PrintStream;
const #137 = Field	#61.#136;	//  java/lang/System.err:Ljava/io/PrintStream;
const #138 = Asciz	java/io/PrintStream;
const #139 = class	#138;	//  java/io/PrintStream
const #140 = Asciz	println;
const #141 = NameAndType	#140:#37;//  println:(Ljava/lang/String;)V
const #142 = Method	#139.#141;	//  java/io/PrintStream.println:(Ljava/lang/String;)V
const #143 = Asciz	org/xml/sax/SAXParseException;
const #144 = class	#143;	//  org/xml/sax/SAXParseException
const #145 = Method	#144.#133;	//  org/xml/sax/SAXParseException.toString:()Ljava/lang/String;
const #146 = Asciz	Problem in %s at line %d;
const #147 = String	#146;	//  Problem in %s at line %d
const #148 = Asciz	scala/collection/immutable/StringOps;
const #149 = class	#148;	//  scala/collection/immutable/StringOps
const #150 = NameAndType	#16:#37;//  "<init>":(Ljava/lang/String;)V
const #151 = Method	#149.#150;	//  scala/collection/immutable/StringOps."<init>":(Ljava/lang/String;)V
const #152 = Asciz	getSystemId;
const #153 = NameAndType	#152:#132;//  getSystemId:()Ljava/lang/String;
const #154 = Method	#144.#153;	//  org/xml/sax/SAXParseException.getSystemId:()Ljava/lang/String;
const #155 = Asciz	getLineNumber;
const #156 = Asciz	()I;
const #157 = NameAndType	#155:#156;//  getLineNumber:()I
const #158 = Method	#144.#157;	//  org/xml/sax/SAXParseException.getLineNumber:()I
const #159 = Asciz	scala/runtime/BoxesRunTime;
const #160 = class	#159;	//  scala/runtime/BoxesRunTime
const #161 = Asciz	boxToInteger;
const #162 = Asciz	(I)Ljava/lang/Integer;;
const #163 = NameAndType	#161:#162;//  boxToInteger:(I)Ljava/lang/Integer;
const #164 = Method	#160.#163;	//  scala/runtime/BoxesRunTime.boxToInteger:(I)Ljava/lang/Integer;
const #165 = Asciz	genericWrapArray;
const #166 = Asciz	(Ljava/lang/Object;)Lscala/collection/mutable/WrappedArray;;
const #167 = NameAndType	#165:#166;//  genericWrapArray:(Ljava/lang/Object;)Lscala/collection/mutable/WrappedArray;
const #168 = Method	#93.#167;	//  scala/Predef$.genericWrapArray:(Ljava/lang/Object;)Lscala/collection/mutable/WrappedArray;
const #169 = Asciz	scala/collection/immutable/StringLike;
const #170 = class	#169;	//  scala/collection/immutable/StringLike
const #171 = Asciz	format;
const #172 = Asciz	(Lscala/collection/Seq;)Ljava/lang/String;;
const #173 = NameAndType	#171:#172;//  format:(Lscala/collection/Seq;)Ljava/lang/String;
const #174 = InterfaceMethod	#170.#173;	//  scala/collection/immutable/StringLike.format:(Lscala/collection/Seq;)Ljava/lang/String;
const #175 = Asciz	arg;
const #176 = Asciz	Ljava/lang/String;;
const #177 = Asciz	$inlThis0;
const #178 = Asciz	exceptions0;
const #179 = Asciz	Lscala/collection/Seq;;
const #180 = Asciz	s$1;
const #181 = Asciz	Lscala/xml/include/sax/XIncluder;;
const #182 = Asciz	includer$1;
const #183 = Asciz	Lscala/xml/include/sax/XIncludeFilter;;
const #184 = Asciz	andThen;
const #185 = Asciz	(Lscala/Function1;)Lscala/Function1;;
const #186 = Asciz	(Lscala/Function1;Lscala/Function1;)Lscala/Function1;;
const #187 = NameAndType	#184:#186;//  andThen:(Lscala/Function1;Lscala/Function1;)Lscala/Function1;
const #188 = Method	#28.#187;	//  scala/Function1$class.andThen:(Lscala/Function1;Lscala/Function1;)Lscala/Function1;
const #189 = Asciz	g;
const #190 = Asciz	Lscala/Function1;;
const #191 = Asciz	compose;
const #192 = NameAndType	#191:#186;//  compose:(Lscala/Function1;Lscala/Function1;)Lscala/Function1;
const #193 = Method	#28.#192;	//  scala/Function1$class.compose:(Lscala/Function1;Lscala/Function1;)Lscala/Function1;
const #194 = Asciz	(Lscala/Function1;)Ljava/lang/String;;
const #195 = NameAndType	#131:#194;//  toString:(Lscala/Function1;)Ljava/lang/String;
const #196 = Method	#28.#195;	//  scala/Function1$class.toString:(Lscala/Function1;)Ljava/lang/String;
const #197 = Asciz	Scala;
const #198 = Asciz	InnerClasses;
const #199 = Asciz	scala/util/control/Exception;
const #200 = class	#199;	//  scala/util/control/Exception
const #201 = Asciz	Catch;
const #202 = Asciz	scala/xml/include/sax/Main;
const #203 = class	#202;	//  scala/xml/include/sax/Main
const #204 = Asciz	$anonfun$main$1;
const #205 = Asciz	$anonfun$ignoring$1;
const #206 = Asciz	$anonfun$apply$4;
const #207 = Asciz	$anonfun$apply$3;
const #208 = Asciz	scala/Function1;
const #209 = class	#208;	//  scala/Function1
const #210 = Asciz	scala/ScalaObject;
const #211 = class	#210;	//  scala/ScalaObject
const #212 = Asciz	java/io/Serializable;
const #213 = class	#212;	//  java/io/Serializable

{
public static final long serialVersionUID;

public static {};
  Code:
   Stack=2, Locals=0, Args_size=0
   0:	lconst_0
   1:	putstatic	#11; //Field serialVersionUID:J
   4:	return

public scala.xml.include.sax.Main$$anonfun$main$1(org.xml.sax.XMLReader, scala.Option);
  Code:
   Stack=2, Locals=3, Args_size=3
   0:	aload_0
   1:	aload_1
   2:	putfield	#20; //Field parser$1:Lorg/xml/sax/XMLReader;
   5:	aload_0
   6:	aload_2
   7:	putfield	#22; //Field resolver$1:Lscala/Option;
   10:	aload_0
   11:	invokespecial	#26; //Method java/lang/Object."<init>":()V
   14:	aload_0
   15:	invokestatic	#32; //Method scala/Function1$class.$init$:(Lscala/Function1;)V
   18:	return
  LineNumberTable: 
   line 60: 0


public final java.lang.Object apply(java.lang.Object);
  Code:
   Stack=2, Locals=2, Args_size=2
   0:	aload_0
   1:	aload_1
   2:	checkcast	#36; //class java/lang/String
   5:	invokevirtual	#39; //Method apply:(Ljava/lang/String;)V
   8:	getstatic	#45; //Field scala/runtime/BoxedUnit.UNIT:Lscala/runtime/BoxedUnit;
   11:	areturn
  LineNumberTable: 
   line 60: 0

  LocalVariableTable: 
   Start  Length  Slot  Name   Signature
   0      12      0    this       Lscala/xml/include/sax/Main$$anonfun$main$1;
   0      12      1    v1       Ljava/lang/Object;


public final void apply(java.lang.String);
  Code:
   Stack=6, Locals=13, Args_size=2
   0:	new	#52; //class scala/xml/include/sax/XIncludeFilter
   3:	dup
   4:	invokespecial	#53; //Method scala/xml/include/sax/XIncludeFilter."<init>":()V
   7:	astore	5
   9:	aload	5
   11:	aload_0
   12:	getfield	#20; //Field parser$1:Lorg/xml/sax/XMLReader;
   15:	invokevirtual	#57; //Method scala/xml/include/sax/XIncludeFilter.setParent:(Lorg/xml/sax/XMLReader;)V
   18:	new	#59; //class scala/xml/include/sax/XIncluder
   21:	dup
   22:	getstatic	#65; //Field java/lang/System.out:Ljava/io/PrintStream;
   25:	ldc	#67; //String UTF-8
   27:	invokespecial	#70; //Method scala/xml/include/sax/XIncluder."<init>":(Ljava/io/OutputStream;Ljava/lang/String;)V
   30:	astore	4
   32:	aload	5
   34:	aload	4
   36:	invokevirtual	#74; //Method scala/xml/include/sax/XIncludeFilter.setContentHandler:(Lorg/xml/sax/ContentHandler;)V
   39:	aload_0
   40:	getfield	#22; //Field resolver$1:Lscala/Option;
   43:	new	#76; //class scala/xml/include/sax/Main$$anonfun$main$1$$anonfun$apply$3
   46:	dup
   47:	aload_0
   48:	aload	5
   50:	invokespecial	#79; //Method scala/xml/include/sax/Main$$anonfun$main$1$$anonfun$apply$3."<init>":(Lscala/xml/include/sax/Main$$anonfun$main$1;Lscala/xml/include/sax/XIncludeFilter;)V
   53:	invokevirtual	#85; //Method scala/Option.map:(Lscala/Function1;)Lscala/Option;
   56:	pop
   57:	getstatic	#91; //Field scala/util/control/Exception$.MODULE$:Lscala/util/control/Exception$;
   60:	getstatic	#96; //Field scala/Predef$.MODULE$:Lscala/Predef$;
   63:	iconst_1
   64:	anewarray	#98; //class java/lang/Class
   67:	dup
   68:	iconst_0
   69:	ldc	#100; //class org/xml/sax/SAXException
   71:	aastore
   72:	checkcast	#102; //class "[Ljava/lang/Object;"
   75:	invokevirtual	#106; //Method scala/Predef$.wrapRefArray:([Ljava/lang/Object;)Lscala/collection/mutable/WrappedArray;
   78:	astore_3
   79:	astore_2
   80:	aload_2
   81:	aload_3
   82:	invokevirtual	#110; //Method scala/util/control/Exception$.catching:(Lscala/collection/Seq;)Lscala/util/control/Exception$Catch;
   85:	new	#112; //class scala/util/control/Exception$$anonfun$ignoring$1
   88:	dup
   89:	invokespecial	#113; //Method scala/util/control/Exception$$anonfun$ignoring$1."<init>":()V
   92:	invokevirtual	#119; //Method scala/util/control/Exception$Catch.withApply:(Lscala/Function1;)Lscala/util/control/Exception$Catch;
   95:	new	#121; //class scala/xml/include/sax/Main$$anonfun$main$1$$anonfun$apply$4
   98:	dup
   99:	aload_0
   100:	aload	5
   102:	aload	4
   104:	invokespecial	#124; //Method scala/xml/include/sax/Main$$anonfun$main$1$$anonfun$apply$4."<init>":(Lscala/xml/include/sax/Main$$anonfun$main$1;Lscala/xml/include/sax/XIncludeFilter;Lscala/xml/include/sax/XIncluder;)V
   107:	invokevirtual	#127; //Method scala/util/control/Exception$Catch.apply:(Lscala/Function0;)Ljava/lang/Object;
   110:	pop
   111:	aload	5
   113:	aload_1
   114:	invokevirtual	#130; //Method scala/xml/include/sax/XIncludeFilter.parse:(Ljava/lang/String;)V
   117:	goto	218
   120:	astore	6
   122:	aload	6
   124:	invokevirtual	#134; //Method org/xml/sax/SAXException.toString:()Ljava/lang/String;
   127:	astore	7
   129:	getstatic	#137; //Field java/lang/System.err:Ljava/io/PrintStream;
   132:	aload	7
   134:	invokevirtual	#142; //Method java/io/PrintStream.println:(Ljava/lang/String;)V
   137:	goto	218
   140:	astore	10
   142:	aload	10
   144:	invokevirtual	#145; //Method org/xml/sax/SAXParseException.toString:()Ljava/lang/String;
   147:	astore	8
   149:	getstatic	#137; //Field java/lang/System.err:Ljava/io/PrintStream;
   152:	aload	8
   154:	invokevirtual	#142; //Method java/io/PrintStream.println:(Ljava/lang/String;)V
   157:	ldc	#147; //String Problem in %s at line %d
   159:	astore	9
   161:	new	#149; //class scala/collection/immutable/StringOps
   164:	dup
   165:	aload	9
   167:	invokespecial	#151; //Method scala/collection/immutable/StringOps."<init>":(Ljava/lang/String;)V
   170:	getstatic	#96; //Field scala/Predef$.MODULE$:Lscala/Predef$;
   173:	iconst_2
   174:	anewarray	#24; //class java/lang/Object
   177:	dup
   178:	iconst_0
   179:	aload	10
   181:	invokevirtual	#154; //Method org/xml/sax/SAXParseException.getSystemId:()Ljava/lang/String;
   184:	aastore
   185:	dup
   186:	iconst_1
   187:	aload	10
   189:	invokevirtual	#158; //Method org/xml/sax/SAXParseException.getLineNumber:()I
   192:	istore	11
   194:	iload	11
   196:	invokestatic	#164; //Method scala/runtime/BoxesRunTime.boxToInteger:(I)Ljava/lang/Integer;
   199:	aastore
   200:	invokevirtual	#168; //Method scala/Predef$.genericWrapArray:(Ljava/lang/Object;)Lscala/collection/mutable/WrappedArray;
   203:	invokeinterface	#174,  2; //InterfaceMethod scala/collection/immutable/StringLike.format:(Lscala/collection/Seq;)Ljava/lang/String;
   208:	astore	12
   210:	getstatic	#137; //Field java/lang/System.err:Ljava/io/PrintStream;
   213:	aload	12
   215:	invokevirtual	#142; //Method java/io/PrintStream.println:(Ljava/lang/String;)V
   218:	return
  Exception table:
   from   to  target type
     0   120   140   Class org/xml/sax/SAXParseException

     0   120   120   Class org/xml/sax/SAXException

  LineNumberTable: 
   line 62: 0
   line 67: 9
   line 63: 11
   line 64: 18
   line 65: 32
   line 67: 39
   line 69: 57
   line 73: 100
   line 69: 102
   line 73: 111
   line 79: 120
   line 80: 122
   line 76: 140
   line 77: 142
   line 78: 157
   line 61: 218

  LocalVariableTable: 
   Start  Length  Slot  Name   Signature
   0      219      0    this       Lscala/xml/include/sax/Main$$anonfun$main$1;
   0      219      1    arg       Ljava/lang/String;
   80      40      2    $inlThis0       Ljava/lang/Object;
   80      15      3    exceptions0       Lscala/collection/Seq;
   32      85      4    s$1       Lscala/xml/include/sax/XIncluder;
   9      108      5    includer$1       Lscala/xml/include/sax/XIncludeFilter;


public scala.Function1 andThen(scala.Function1);
  Code:
   Stack=2, Locals=2, Args_size=2
   0:	aload_0
   1:	aload_1
   2:	invokestatic	#188; //Method scala/Function1$class.andThen:(Lscala/Function1;Lscala/Function1;)Lscala/Function1;
   5:	areturn
  LineNumberTable: 
   line 60: 0

  LocalVariableTable: 
   Start  Length  Slot  Name   Signature
   0      6      0    this       Lscala/xml/include/sax/Main$$anonfun$main$1;
   0      6      1    g       Lscala/Function1;


public scala.Function1 compose(scala.Function1);
  Code:
   Stack=2, Locals=2, Args_size=2
   0:	aload_0
   1:	aload_1
   2:	invokestatic	#193; //Method scala/Function1$class.compose:(Lscala/Function1;Lscala/Function1;)Lscala/Function1;
   5:	areturn
  LineNumberTable: 
   line 60: 0

  LocalVariableTable: 
   Start  Length  Slot  Name   Signature
   0      6      0    this       Lscala/xml/include/sax/Main$$anonfun$main$1;
   0      6      1    g       Lscala/Function1;


public java.lang.String toString();
  Code:
   Stack=1, Locals=1, Args_size=1
   0:	aload_0
   1:	invokestatic	#196; //Method scala/Function1$class.toString:(Lscala/Function1;)Ljava/lang/String;
   4:	areturn
  LineNumberTable: 
   line 60: 0


}

