Compiled from "Main.scala"
public final class scala.xml.include.sax.Main$$anonfun$3 extends java.lang.Object implements scala.Function0,scala.ScalaObject,java.io.Serializable
  SourceFile: "Main.scala"
  Scala: length = 0x
   
  InnerClass: 
   public final #69= #9 of #68; //$anonfun$3=class scala/xml/include/sax/Main$$anonfun$3 of class scala/xml/include/sax/Main
  minor version: 0
  major version: 49
  Constant pool:
const #1 = Asciz	SourceFile;
const #2 = Asciz	Main.scala;
const #3 = Asciz	<clinit>;
const #4 = Asciz	()V;
const #5 = Asciz	Code;
const #6 = Asciz	serialVersionUID;
const #7 = Asciz	J;
const #8 = Asciz	scala/xml/include/sax/Main$$anonfun$3;
const #9 = class	#8;	//  scala/xml/include/sax/Main$$anonfun$3
const #10 = NameAndType	#6:#7;//  serialVersionUID:J
const #11 = Field	#9.#10;	//  scala/xml/include/sax/Main$$anonfun$3.serialVersionUID:J
const #12 = Asciz	parser$1;
const #13 = Asciz	Lorg/xml/sax/XMLReader;;
const #14 = Asciz	args$1;
const #15 = Asciz	[Ljava/lang/String;;
const #16 = Asciz	<init>;
const #17 = Asciz	([Ljava/lang/String;Lorg/xml/sax/XMLReader;)V;
const #18 = Asciz	LineNumberTable;
const #19 = NameAndType	#14:#15;//  args$1:[Ljava/lang/String;
const #20 = Field	#9.#19;	//  scala/xml/include/sax/Main$$anonfun$3.args$1:[Ljava/lang/String;
const #21 = NameAndType	#12:#13;//  parser$1:Lorg/xml/sax/XMLReader;
const #22 = Field	#9.#21;	//  scala/xml/include/sax/Main$$anonfun$3.parser$1:Lorg/xml/sax/XMLReader;
const #23 = Asciz	java/lang/Object;
const #24 = class	#23;	//  java/lang/Object
const #25 = NameAndType	#16:#4;//  "<init>":()V
const #26 = Method	#24.#25;	//  java/lang/Object."<init>":()V
const #27 = Asciz	scala/Function0$class;
const #28 = class	#27;	//  scala/Function0$class
const #29 = Asciz	$init$;
const #30 = Asciz	(Lscala/Function0;)V;
const #31 = NameAndType	#29:#30;//  $init$:(Lscala/Function0;)V
const #32 = Method	#28.#31;	//  scala/Function0$class.$init$:(Lscala/Function0;)V
const #33 = Asciz	apply;
const #34 = Asciz	()Ljava/lang/Object;;
const #35 = Asciz	()Lorg/xml/sax/EntityResolver;;
const #36 = NameAndType	#33:#35;//  apply:()Lorg/xml/sax/EntityResolver;
const #37 = Method	#9.#36;	//  scala/xml/include/sax/Main$$anonfun$3.apply:()Lorg/xml/sax/EntityResolver;
const #38 = Asciz	java/lang/Class;
const #39 = class	#38;	//  java/lang/Class
const #40 = Asciz	forName;
const #41 = Asciz	(Ljava/lang/String;)Ljava/lang/Class;;
const #42 = NameAndType	#40:#41;//  forName:(Ljava/lang/String;)Ljava/lang/Class;
const #43 = Method	#39.#42;	//  java/lang/Class.forName:(Ljava/lang/String;)Ljava/lang/Class;
const #44 = Asciz	newInstance;
const #45 = NameAndType	#44:#34;//  newInstance:()Ljava/lang/Object;
const #46 = Method	#39.#45;	//  java/lang/Class.newInstance:()Ljava/lang/Object;
const #47 = Asciz	org/xml/sax/EntityResolver;
const #48 = class	#47;	//  org/xml/sax/EntityResolver
const #49 = Asciz	org/xml/sax/XMLReader;
const #50 = class	#49;	//  org/xml/sax/XMLReader
const #51 = Asciz	setEntityResolver;
const #52 = Asciz	(Lorg/xml/sax/EntityResolver;)V;
const #53 = NameAndType	#51:#52;//  setEntityResolver:(Lorg/xml/sax/EntityResolver;)V
const #54 = InterfaceMethod	#50.#53;	//  org/xml/sax/XMLReader.setEntityResolver:(Lorg/xml/sax/EntityResolver;)V
const #55 = Asciz	this;
const #56 = Asciz	Lscala/xml/include/sax/Main$$anonfun$3;;
const #57 = Asciz	r;
const #58 = Asciz	Lorg/xml/sax/EntityResolver;;
const #59 = Asciz	LocalVariableTable;
const #60 = Asciz	toString;
const #61 = Asciz	()Ljava/lang/String;;
const #62 = Asciz	(Lscala/Function0;)Ljava/lang/String;;
const #63 = NameAndType	#60:#62;//  toString:(Lscala/Function0;)Ljava/lang/String;
const #64 = Method	#28.#63;	//  scala/Function0$class.toString:(Lscala/Function0;)Ljava/lang/String;
const #65 = Asciz	Scala;
const #66 = Asciz	InnerClasses;
const #67 = Asciz	scala/xml/include/sax/Main;
const #68 = class	#67;	//  scala/xml/include/sax/Main
const #69 = Asciz	$anonfun$3;
const #70 = Asciz	scala/Function0;
const #71 = class	#70;	//  scala/Function0
const #72 = Asciz	scala/ScalaObject;
const #73 = class	#72;	//  scala/ScalaObject
const #74 = Asciz	java/io/Serializable;
const #75 = class	#74;	//  java/io/Serializable

{
public static final long serialVersionUID;

public static {};
  Code:
   Stack=2, Locals=0, Args_size=0
   0:	lconst_0
   1:	putstatic	#11; //Field serialVersionUID:J
   4:	return

public scala.xml.include.sax.Main$$anonfun$3(java.lang.String[], org.xml.sax.XMLReader);
  Code:
   Stack=2, Locals=3, Args_size=3
   0:	aload_0
   1:	aload_1
   2:	putfield	#20; //Field args$1:[Ljava/lang/String;
   5:	aload_0
   6:	aload_2
   7:	putfield	#22; //Field parser$1:Lorg/xml/sax/XMLReader;
   10:	aload_0
   11:	invokespecial	#26; //Method java/lang/Object."<init>":()V
   14:	aload_0
   15:	invokestatic	#32; //Method scala/Function0$class.$init$:(Lscala/Function0;)V
   18:	return
  LineNumberTable: 
   line 54: 0


public final java.lang.Object apply();
  Code:
   Stack=1, Locals=1, Args_size=1
   0:	aload_0
   1:	invokevirtual	#37; //Method apply:()Lorg/xml/sax/EntityResolver;
   4:	areturn
  LineNumberTable: 
   line 54: 0


public final org.xml.sax.EntityResolver apply();
  Code:
   Stack=2, Locals=2, Args_size=1
   0:	aload_0
   1:	getfield	#20; //Field args$1:[Ljava/lang/String;
   4:	iconst_1
   5:	aaload
   6:	invokestatic	#43; //Method java/lang/Class.forName:(Ljava/lang/String;)Ljava/lang/Class;
   9:	invokevirtual	#46; //Method java/lang/Class.newInstance:()Ljava/lang/Object;
   12:	checkcast	#48; //class org/xml/sax/EntityResolver
   15:	astore_1
   16:	aload_0
   17:	getfield	#22; //Field parser$1:Lorg/xml/sax/XMLReader;
   20:	aload_1
   21:	invokeinterface	#54,  2; //InterfaceMethod org/xml/sax/XMLReader.setEntityResolver:(Lorg/xml/sax/EntityResolver;)V
   26:	aload_1
   27:	areturn
  LineNumberTable: 
   line 55: 0
   line 56: 16
   line 57: 26

  LocalVariableTable: 
   Start  Length  Slot  Name   Signature
   0      28      0    this       Lscala/xml/include/sax/Main$$anonfun$3;
   16      11      1    r       Lorg/xml/sax/EntityResolver;


public java.lang.String toString();
  Code:
   Stack=1, Locals=1, Args_size=1
   0:	aload_0
   1:	invokestatic	#64; //Method scala/Function0$class.toString:(Lscala/Function0;)Ljava/lang/String;
   4:	areturn
  LineNumberTable: 
   line 54: 0


}

