Compiled from "Main.scala"
public final class scala.xml.include.sax.Main$$anonfun$2$$anonfun$apply$1 extends java.lang.Object implements scala.Function0,scala.ScalaObject,java.io.Serializable
  SourceFile: "Main.scala"
  Scala: length = 0x
   
  InnerClass: 
   public final $anonfun$2=class scala/xml/include/sax/Main$$anonfun$2 of class scala/xml/include/sax/Main
   public final $anonfun$apply$1=class scala/xml/include/sax/Main$$anonfun$2$$anonfun$apply$1 of class scala/xml/include/sax/Main$$anonfun$2
  minor version: 0
  major version: 49
  Constant pool:
Asciz	SourceFile;
Asciz	Main.scala;
Asciz	<clinit>;
Asciz	()V;
Asciz	Code;
Asciz	serialVersionUID;
Asciz	J;
Asciz	scala/xml/include/sax/Main$$anonfun$2$$anonfun$apply$1;
class	scala/xml/include/sax/Main$$anonfun$2$$anonfun$apply$1
NameAndType	serialVersionUID:J
Field	scala/xml/include/sax/Main$$anonfun$2$$anonfun$apply$1.serialVersionUID:J
Asciz	<init>;
Asciz	(Lscala/xml/include/sax/Main$$anonfun$2;)V;
Asciz	LineNumberTable;
Asciz	java/lang/Object;
class	java/lang/Object
NameAndType	"<init>":()V
Method	java/lang/Object."<init>":()V
Asciz	scala/Function0$class;
class	scala/Function0$class
Asciz	$init$;
Asciz	(Lscala/Function0;)V;
NameAndType	$init$:(Lscala/Function0;)V
Method	scala/Function0$class.$init$:(Lscala/Function0;)V
Asciz	this;
Asciz	Lscala/xml/include/sax/Main$$anonfun$2$$anonfun$apply$1;;
Asciz	$outer;
Asciz	Lscala/xml/include/sax/Main$$anonfun$2;;
Asciz	LocalVariableTable;
Asciz	apply;
Asciz	()Ljava/lang/Object;;
Asciz	()Lorg/xml/sax/XMLReader;;
NameAndType	apply:()Lorg/xml/sax/XMLReader;
Method	scala/xml/include/sax/Main$$anonfun$2$$anonfun$apply$1.apply:()Lorg/xml/sax/XMLReader;
Asciz	scala/xml/include/sax/Main$;
class	scala/xml/include/sax/Main$
Asciz	MODULE$;
Asciz	Lscala/xml/include/sax/Main$;;
NameAndType	MODULE$:Lscala/xml/include/sax/Main$;
Field	scala/xml/include/sax/Main$.MODULE$:Lscala/xml/include/sax/Main$;
Asciz	scala$xml$include$sax$Main$$xercesClass;
Asciz	()Ljava/lang/String;;
NameAndType	scala$xml$include$sax$Main$$xercesClass:()Ljava/lang/String;
Method	scala/xml/include/sax/Main$.scala$xml$include$sax$Main$$xercesClass:()Ljava/lang/String;
Asciz	org/xml/sax/helpers/XMLReaderFactory;
class	org/xml/sax/helpers/XMLReaderFactory
Asciz	createXMLReader;
Asciz	(Ljava/lang/String;)Lorg/xml/sax/XMLReader;;
NameAndType	createXMLReader:(Ljava/lang/String;)Lorg/xml/sax/XMLReader;
Method	org/xml/sax/helpers/XMLReaderFactory.createXMLReader:(Ljava/lang/String;)Lorg/xml/sax/XMLReader;
Asciz	toString;
Asciz	(Lscala/Function0;)Ljava/lang/String;;
NameAndType	toString:(Lscala/Function0;)Ljava/lang/String;
Method	scala/Function0$class.toString:(Lscala/Function0;)Ljava/lang/String;
Asciz	Scala;
Asciz	InnerClasses;
Asciz	scala/xml/include/sax/Main$$anonfun$2;
class	scala/xml/include/sax/Main$$anonfun$2
Asciz	scala/xml/include/sax/Main;
class	scala/xml/include/sax/Main
Asciz	$anonfun$2;
Asciz	$anonfun$apply$1;
Asciz	scala/Function0;
class	scala/Function0
Asciz	scala/ScalaObject;
class	scala/ScalaObject
Asciz	java/io/Serializable;
class	java/io/Serializable

{
public static final long serialVersionUID;
  Signature: J

public static {};
  Signature: ()V
  Code:
   Stack=2, Locals=0, Args_size=0
	lconst_0
	putstatic	Field serialVersionUID:J
	return
  Labels:

public scala.xml.include.sax.Main$$anonfun$2$$anonfun$apply$1(scala.xml.include.sax.Main$$anonfun$2);
  Signature: (Lscala/xml/include/sax/Main$$anonfun$2;)V
  Code:
   Stack=1, Locals=2, Args_size=2
	aload_0
	invokespecial	Method java/lang/Object."<init>":()V
	aload_0
	invokestatic	Method scala/Function0$class.$init$:(Lscala/Function0;)V
	return
  Labels:
  LocalVariableTable: 
   Start  Length  Slot  Name   Signature
   0      9      0    this       Lscala/xml/include/sax/Main$$anonfun$2$$anonfun$apply$1;
   0      9      1    $outer       Lscala/xml/include/sax/Main$$anonfun$2;


public final java.lang.Object apply();
  Signature: ()Ljava/lang/Object;
  Code:
   Stack=1, Locals=1, Args_size=1
	aload_0
	invokevirtual	Method apply:()Lorg/xml/sax/XMLReader;
	areturn
  Labels:

public final org.xml.sax.XMLReader apply();
  Signature: ()Lorg/xml/sax/XMLReader;
  Code:
   Stack=1, Locals=1, Args_size=1
	getstatic	Field scala/xml/include/sax/Main$.MODULE$:Lscala/xml/include/sax/Main$;
	invokevirtual	Method scala/xml/include/sax/Main$.scala$xml$include$sax$Main$$xercesClass:()Ljava/lang/String;
	invokestatic	Method org/xml/sax/helpers/XMLReaderFactory.createXMLReader:(Ljava/lang/String;)Lorg/xml/sax/XMLReader;
	areturn
  Labels:

public java.lang.String toString();
  Signature: ()Ljava/lang/String;
  Code:
   Stack=1, Locals=1, Args_size=1
	aload_0
	invokestatic	Method scala/Function0$class.toString:(Lscala/Function0;)Ljava/lang/String;
	areturn
  Labels:

}

