Compiled from "Main.scala"
public final class scala.xml.include.sax.Main$$anonfun$main$1$$anonfun$apply$4 extends java.lang.Object implements scala.Function0,scala.ScalaObject,java.io.Serializable
  SourceFile: "Main.scala"
  Scala: length = 0x
   
  InnerClass: 
   public final $anonfun$main$1=class scala/xml/include/sax/Main$$anonfun$main$1 of class scala/xml/include/sax/Main
   public final $anonfun$apply$4=class scala/xml/include/sax/Main$$anonfun$main$1$$anonfun$apply$4 of class scala/xml/include/sax/Main$$anonfun$main$1
  minor version: 0
  major version: 49
  Constant pool:
Asciz	SourceFile;
Asciz	Main.scala;
Asciz	<clinit>;
Asciz	()V;
Asciz	Code;
Asciz	serialVersionUID;
Asciz	J;
Asciz	scala/xml/include/sax/Main$$anonfun$main$1$$anonfun$apply$4;
class	scala/xml/include/sax/Main$$anonfun$main$1$$anonfun$apply$4
NameAndType	serialVersionUID:J
Field	scala/xml/include/sax/Main$$anonfun$main$1$$anonfun$apply$4.serialVersionUID:J
Asciz	s$1;
Asciz	Lscala/xml/include/sax/XIncluder;;
Asciz	includer$1;
Asciz	Lscala/xml/include/sax/XIncludeFilter;;
Asciz	<init>;
Asciz	(Lscala/xml/include/sax/Main$$anonfun$main$1;Lscala/xml/include/sax/XIncludeFilter;Lscala/xml/include/sax/XIncluder;)V;
Asciz	LineNumberTable;
NameAndType	includer$1:Lscala/xml/include/sax/XIncludeFilter;
Field	scala/xml/include/sax/Main$$anonfun$main$1$$anonfun$apply$4.includer$1:Lscala/xml/include/sax/XIncludeFilter;
NameAndType	s$1:Lscala/xml/include/sax/XIncluder;
Field	scala/xml/include/sax/Main$$anonfun$main$1$$anonfun$apply$4.s$1:Lscala/xml/include/sax/XIncluder;
Asciz	java/lang/Object;
class	java/lang/Object
NameAndType	"<init>":()V
Method	java/lang/Object."<init>":()V
Asciz	scala/Function0$class;
class	scala/Function0$class
Asciz	$init$;
Asciz	(Lscala/Function0;)V;
NameAndType	$init$:(Lscala/Function0;)V
Method	scala/Function0$class.$init$:(Lscala/Function0;)V
Asciz	this;
Asciz	Lscala/xml/include/sax/Main$$anonfun$main$1$$anonfun$apply$4;;
Asciz	$outer;
Asciz	Lscala/xml/include/sax/Main$$anonfun$main$1;;
Asciz	LocalVariableTable;
Asciz	apply;
Asciz	()Ljava/lang/Object;;
NameAndType	apply:()V
Method	scala/xml/include/sax/Main$$anonfun$main$1$$anonfun$apply$4.apply:()V
Asciz	scala/runtime/BoxedUnit;
class	scala/runtime/BoxedUnit
Asciz	UNIT;
Asciz	Lscala/runtime/BoxedUnit;;
NameAndType	UNIT:Lscala/runtime/BoxedUnit;
Field	scala/runtime/BoxedUnit.UNIT:Lscala/runtime/BoxedUnit;
Asciz	scala/xml/include/sax/Main$;
class	scala/xml/include/sax/Main$
Asciz	MODULE$;
Asciz	Lscala/xml/include/sax/Main$;;
NameAndType	MODULE$:Lscala/xml/include/sax/Main$;
Field	scala/xml/include/sax/Main$.MODULE$:Lscala/xml/include/sax/Main$;
Asciz	scala$xml$include$sax$Main$$lexicalHandler;
Asciz	()Ljava/lang/String;;
NameAndType	scala$xml$include$sax$Main$$lexicalHandler:()Ljava/lang/String;
Method	scala/xml/include/sax/Main$.scala$xml$include$sax$Main$$lexicalHandler:()Ljava/lang/String;
Asciz	scala/xml/include/sax/XIncludeFilter;
class	scala/xml/include/sax/XIncludeFilter
Asciz	setProperty;
Asciz	(Ljava/lang/String;Ljava/lang/Object;)V;
NameAndType	setProperty:(Ljava/lang/String;Ljava/lang/Object;)V
Method	scala/xml/include/sax/XIncludeFilter.setProperty:(Ljava/lang/String;Ljava/lang/Object;)V
Asciz	scala/xml/include/sax/XIncluder;
class	scala/xml/include/sax/XIncluder
Asciz	setFilter;
Asciz	(Lscala/xml/include/sax/XIncludeFilter;)V;
NameAndType	setFilter:(Lscala/xml/include/sax/XIncludeFilter;)V
Method	scala/xml/include/sax/XIncluder.setFilter:(Lscala/xml/include/sax/XIncludeFilter;)V
Asciz	toString;
Asciz	(Lscala/Function0;)Ljava/lang/String;;
NameAndType	toString:(Lscala/Function0;)Ljava/lang/String;
Method	scala/Function0$class.toString:(Lscala/Function0;)Ljava/lang/String;
Asciz	Scala;
Asciz	InnerClasses;
Asciz	scala/xml/include/sax/Main$$anonfun$main$1;
class	scala/xml/include/sax/Main$$anonfun$main$1
Asciz	scala/xml/include/sax/Main;
class	scala/xml/include/sax/Main
Asciz	$anonfun$main$1;
Asciz	$anonfun$apply$4;
Asciz	scala/Function0;
class	scala/Function0
Asciz	scala/ScalaObject;
class	scala/ScalaObject
Asciz	java/io/Serializable;
class	java/io/Serializable

{
public static final long serialVersionUID;
  Signature: J

private final scala.xml.include.sax.XIncluder s$1;
  Signature: Lscala/xml/include/sax/XIncluder;

private final scala.xml.include.sax.XIncludeFilter includer$1;
  Signature: Lscala/xml/include/sax/XIncludeFilter;

public static {};
  Signature: ()V
  Code:
   Stack=2, Locals=0, Args_size=0
	lconst_0
	putstatic	Field serialVersionUID:J
	return
  Labels:

public scala.xml.include.sax.Main$$anonfun$main$1$$anonfun$apply$4(scala.xml.include.sax.Main$$anonfun$main$1, scala.xml.include.sax.XIncludeFilter, scala.xml.include.sax.XIncluder);
  Signature: (Lscala/xml/include/sax/Main$$anonfun$main$1;Lscala/xml/include/sax/XIncludeFilter;Lscala/xml/include/sax/XIncluder;)V
  Code:
   Stack=2, Locals=4, Args_size=4
	aload_0
	aload_2
	putfield	Field includer$1:Lscala/xml/include/sax/XIncludeFilter;
	aload_0
	aload_3
	putfield	Field s$1:Lscala/xml/include/sax/XIncluder;
	aload_0
	invokespecial	Method java/lang/Object."<init>":()V
	aload_0
	invokestatic	Method scala/Function0$class.$init$:(Lscala/Function0;)V
	return
  Labels:
  LocalVariableTable: 
   Start  Length  Slot  Name   Signature
   0      19      0    this       Lscala/xml/include/sax/Main$$anonfun$main$1$$anonfun$apply$4;
   0      19      1    $outer       Lscala/xml/include/sax/Main$$anonfun$main$1;


public final java.lang.Object apply();
  Signature: ()Ljava/lang/Object;
  Code:
   Stack=1, Locals=1, Args_size=1
	aload_0
	invokevirtual	Method apply:()V
	getstatic	Field scala/runtime/BoxedUnit.UNIT:Lscala/runtime/BoxedUnit;
	areturn
  Labels:

public final void apply();
  Signature: ()V
  Code:
   Stack=3, Locals=1, Args_size=1
	aload_0
	getfield	Field includer$1:Lscala/xml/include/sax/XIncludeFilter;
	getstatic	Field scala/xml/include/sax/Main$.MODULE$:Lscala/xml/include/sax/Main$;
	invokevirtual	Method scala/xml/include/sax/Main$.scala$xml$include$sax$Main$$lexicalHandler:()Ljava/lang/String;
	aload_0
	getfield	Field s$1:Lscala/xml/include/sax/XIncluder;
	invokevirtual	Method scala/xml/include/sax/XIncludeFilter.setProperty:(Ljava/lang/String;Ljava/lang/Object;)V
	aload_0
	getfield	Field s$1:Lscala/xml/include/sax/XIncluder;
	aload_0
	getfield	Field includer$1:Lscala/xml/include/sax/XIncludeFilter;
	invokevirtual	Method scala/xml/include/sax/XIncluder.setFilter:(Lscala/xml/include/sax/XIncludeFilter;)V
	return
  Labels:

public java.lang.String toString();
  Signature: ()Ljava/lang/String;
  Code:
   Stack=1, Locals=1, Args_size=1
	aload_0
	invokestatic	Method scala/Function0$class.toString:(Lscala/Function0;)Ljava/lang/String;
	areturn
  Labels:

}

