Compiled from "XIncludeFilter.scala"
public class scala.xml.include.sax.XIncludeFilter extends org.xml.sax.helpers.XMLFilterImpl implements scala.ScalaObject
  SourceFile: "XIncludeFilter.scala"
  ScalaSig: length = 0x624
   05 00 FFFFFF81 4B 06 08 01 02 FFFFFF84 FFFFFF80 FFFFFF80 FFFFFF80 00 0B 02 0E
   58 49 6E 63 6C 75 64 65 46 69 6C 74 65 72 0A 02
   03 04 01 03 73 61 78 0A 02 05 06 01 07 69 6E 63
   6C 75 64 65 0A 02 07 08 01 03 78 6D 6C 0A 01 09
   01 05 73 63 61 6C 61 03 00 13 03 00 0C 16 10 02
   0D 14 0D 01 0E 0A 02 0F 10 01 07 68 65 6C 70 65
   72 73 0A 02 03 11 0A 02 07 12 0A 01 13 01 03 6F
   72 67 09 02 15 0E 02 0D 58 4D 4C 46 69 6C 74 65
   72 49 6D 70 6C 10 02 17 18 0D 01 08 09 02 19 08
   02 0B 53 63 61 6C 61 4F 62 6A 65 63 74 08 05 1B
   00 FFFFFF84 00 1C 01 06 3C 69 6E 69 74 3E 14 01 1D 10
   02 1E 00 0D 01 02 08 07 20 00 FFFFFFC2 FFFFFF80 FFFFFF84 02 21 01
   12 58 49 4E 43 4C 55 44 45 5F 4E 41 4D 45 53 50
   41 43 45 15 01 22 0F 01 23 21 01 24 01 1F 68 74
   74 70 3A 2F 2F 77 77 77 2E 77 33 2E 6F 72 67 2F
   32 30 30 31 2F 58 49 6E 63 6C 75 64 65 08 06 26
   00 FFFFFFA0 FFFFFF80 06 22 01 13 58 49 4E 43 4C 55 44 45 5F
   4E 41 4D 45 53 50 41 43 45 20 08 07 28 00 FFFFFFC2 FFFFFF80
   FFFFFF84 04 29 01 05 62 61 73 65 73 15 01 2A 10 03 2B
   30 32 0D 01 2C 0A 02 2D 2E 01 04 75 74 69 6C 0A
   01 2F 01 04 6A 61 76 61 09 02 31 2C 02 05 53 74
   61 63 6B 10 02 33 37 0E 02 34 35 0D 01 06 09 02
   36 06 01 07 70 61 63 6B 61 67 65 09 02 38 39 02
   03 55 52 4C 0A 02 36 06 08 06 3B 00 FFFFFFA0 FFFFFF80 04 2A
   01 06 62 61 73 65 73 20 08 07 3D 00 FFFFFFC2 FFFFFF80 FFFFFF84 04
   3E 01 08 6C 6F 63 61 74 6F 72 73 15 01 3F 10 03
   2B 30 40 10 02 41 42 0D 01 10 09 02 43 10 02 07
   4C 6F 63 61 74 6F 72 08 06 45 00 FFFFFFA0 FFFFFF80 04 3F 01
   09 6C 6F 63 61 74 6F 72 73 20 08 05 47 00 FFFFFF84 20
   48 01 12 73 65 74 44 6F 63 75 6D 65 6E 74 4C 6F
   63 61 74 6F 72 14 02 49 4C 10 02 17 4A 09 02 4B
   08 02 04 55 6E 69 74 08 05 4D 46 FFFFFFC0 00 40 01 07
   6C 6F 63 61 74 6F 72 08 07 4F 00 FFFFFFC0 FFFFFF80 FFFFFF84 04 50
   01 05 6C 65 76 65 6C 15 01 51 10 02 17 52 09 02
   53 08 02 03 49 6E 74 08 07 55 00 FFFFFFC0 FFFFFF80 FFFFFF84 04 56
   01 09 6C 65 76 65 6C 5F 24 65 71 14 02 49 57 08
   07 58 54 FFFFFF81 FFFFFF80 FFFFFFC0 00 51 01 03 78 24 31 08 06 5A
   00 FFFFFFA0 FFFFFFA0 04 51 01 06 6C 65 76 65 6C 20 08 05 5C
   00 FFFFFF84 00 5D 01 14 69 6E 73 69 64 65 49 6E 63 6C
   75 64 65 45 6C 65 6D 65 6E 74 14 01 5E 10 02 17
   5F 09 02 60 08 02 07 42 6F 6F 6C 65 61 6E 08 05
   62 00 FFFFFF84 20 63 01 0C 73 74 61 72 74 45 6C 65 6D
   65 6E 74 14 05 49 64 6D 6F 71 08 05 65 61 FFFFFFC0 00
   66 01 03 75 72 69 10 02 67 6A 0E 02 17 68 09 02
   69 08 01 06 50 72 65 64 65 66 09 02 6B 6C 02 06
   53 74 72 69 6E 67 0A 02 69 08 08 05 6E 61 FFFFFFC0 00
   66 01 09 6C 6F 63 61 6C 4E 61 6D 65 08 05 70 61
   FFFFFFC0 00 66 01 05 71 4E 61 6D 65 08 05 72 61 FFFFFFC0 00
   73 01 05 61 74 74 73 31 10 02 41 74 09 02 75 10
   02 0A 41 74 74 72 69 62 75 74 65 73 08 05 77 00
   FFFFFF84 20 78 01 0A 65 6E 64 45 6C 65 6D 65 6E 74 14
   04 49 79 7A 7B 08 05 65 76 FFFFFFC0 00 66 08 05 6E 76
   FFFFFFC0 00 66 08 05 70 76 FFFFFFC0 00 66 08 07 7D 00 FFFFFFC0 FFFFFF80
   FFFFFF84 04 50 01 05 64 65 70 74 68 08 08 7F 00 FFFFFFC0 FFFFFF80
   FFFFFF84 04 FFFFFF81 00 01 09 64 65 70 74 68 5F 24 65 71 14
   03 49 FFFFFF81 01 08 07 58 7E FFFFFF81 FFFFFF80 FFFFFFC0 00 51 08 07 FFFFFF81
   03 00 FFFFFFA0 FFFFFFA0 04 51 01 06 64 65 70 74 68 20 08 07
   FFFFFF81 05 00 FFFFFF84 20 FFFFFF81 06 01 0D 73 74 61 72 74 44 6F
   63 75 6D 65 6E 74 14 01 49 08 07 FFFFFF81 08 00 FFFFFF84 20
   FFFFFF81 06 01 0B 65 6E 64 44 6F 63 75 6D 65 6E 74 08
   07 FFFFFF81 0A 00 FFFFFF84 20 FFFFFF81 0B 01 12 73 74 61 72 74 50
   72 65 66 69 78 4D 61 70 70 69 6E 67 14 05 49 FFFFFF81
   0C FFFFFF81 0E 08 07 FFFFFF81 0D FFFFFF81 09 FFFFFFC0 00 66 01 06 70 72
   65 66 69 78 08 06 65 FFFFFF81 09 FFFFFFC0 00 66 08 07 FFFFFF81 10
   00 FFFFFF84 20 FFFFFF81 11 01 10 65 6E 64 50 72 65 66 69 78
   4D 61 70 70 69 6E 67 14 03 49 FFFFFF81 12 08 07 FFFFFF81 0D
   FFFFFF81 0F FFFFFFC0 00 66 08 07 FFFFFF81 14 00 FFFFFF84 20 FFFFFF81 15 01 0A
   63 68 61 72 61 63 74 65 72 73 14 07 49 FFFFFF81 16 FFFFFF81
   1E FFFFFF81 20 08 08 FFFFFF81 17 FFFFFF81 13 FFFFFFC0 00 FFFFFF81 18 01 02 63
   68 10 05 17 FFFFFF81 19 FFFFFF81 1B 09 03 FFFFFF81 1A 08 02 05 41
   72 72 61 79 10 03 17 FFFFFF81 1C 09 03 FFFFFF81 1D 08 02 04
   43 68 61 72 08 07 FFFFFF81 1F FFFFFF81 13 FFFFFFC0 00 51 01 05 73
   74 61 72 74 08 07 FFFFFF81 21 FFFFFF81 13 FFFFFFC0 00 51 01 06 6C
   65 6E 67 74 68 08 07 FFFFFF81 23 00 FFFFFF84 20 FFFFFF81 24 01 13
   69 67 6E 6F 72 61 62 6C 65 57 68 69 74 65 73 70
   61 63 65 14 07 49 FFFFFF81 25 FFFFFF81 26 FFFFFF81 27 08 08 FFFFFF81 17
   FFFFFF81 22 FFFFFFC0 00 FFFFFF81 18 08 07 FFFFFF81 1F FFFFFF81 22 FFFFFFC0 00 51 08
   07 FFFFFF81 21 FFFFFF81 22 FFFFFFC0 00 51 08 07 FFFFFF81 29 00 FFFFFF84 20 FFFFFF81
   2A 01 15 70 72 6F 63 65 73 73 69 6E 67 49 6E 73
   74 72 75 63 74 69 6F 6E 14 05 49 FFFFFF81 2B FFFFFF81 2D 08
   07 FFFFFF81 2C FFFFFF81 28 FFFFFFC0 00 66 01 06 74 61 72 67 65 74
   08 07 FFFFFF81 2E FFFFFF81 28 FFFFFFC0 00 66 01 04 64 61 74 61 08
   07 FFFFFF81 30 00 FFFFFF84 20 FFFFFF81 31 01 0D 73 6B 69 70 70 65
   64 45 6E 74 69 74 79 14 03 49 FFFFFF81 32 08 07 FFFFFF81 33
   FFFFFF81 2F FFFFFFC0 00 66 01 04 6E 61 6D 65 08 07 FFFFFF81 35 00
   FFFFFF84 04 FFFFFF81 36 01 0B 67 65 74 4C 6F 63 61 74 69 6F
   6E 14 01 66 08 07 FFFFFF81 38 00 FFFFFF84 04 FFFFFF81 39 01 13 69
   6E 63 6C 75 64 65 54 65 78 74 44 6F 63 75 6D 65
   6E 74 14 05 49 FFFFFF81 3A FFFFFF81 3C 08 07 FFFFFF81 3B FFFFFF81 37 FFFFFFC0
   00 66 01 03 75 72 6C 08 07 FFFFFF81 3D FFFFFF81 37 FFFFFFC0 00 66
   01 09 65 6E 63 6F 64 69 6E 67 31 08 09 FFFFFF81 3F 00
   FFFFFFC0 FFFFFF80 FFFFFF84 04 FFFFFF81 40 01 06 61 74 52 6F 6F 74 15 01
   5E 08 09 FFFFFF81 42 00 FFFFFFC0 FFFFFF80 FFFFFF84 04 FFFFFF81 43 01 0A 61 74
   52 6F 6F 74 5F 24 65 71 14 03 49 FFFFFF81 44 08 08 58
   FFFFFF81 41 FFFFFF81 FFFFFF80 FFFFFFC0 00 5E 08 07 FFFFFF81 46 00 FFFFFFA0 FFFFFFA0 04 5E
   01 07 61 74 52 6F 6F 74 20 08 07 FFFFFF81 48 00 FFFFFF84 04
   FFFFFF81 49 01 12 69 6E 63 6C 75 64 65 58 4D 4C 44 6F
   63 75 6D 65 6E 74 14 03 49 FFFFFF81 4A 08 07 FFFFFF81 3B FFFFFF81
   47 FFFFFFC0 00 66 
  minor version: 0
  major version: 49
  Constant pool:
Asciz	SourceFile;
Asciz	XIncludeFilter.scala;
Asciz	atRoot;
Asciz	Z;
Asciz	depth;
Asciz	I;
Asciz	level;
Asciz	locators;
Asciz	Ljava/util/Stack;;
Asciz	Ljava/util/Stack<Lorg/xml/sax/Locator;>;;
Asciz	Signature;
Asciz	bases;
Asciz	Ljava/util/Stack<Ljava/net/URL;>;;
Asciz	XINCLUDE_NAMESPACE;
Asciz	Ljava/lang/String;;
Asciz	()Ljava/lang/String;;
Asciz	Code;
Asciz	http://www.w3.org/2001/XInclude;
String	http://www.w3.org/2001/XInclude
Asciz	LineNumberTable;
Asciz	()Ljava/util/Stack;;
Asciz	scala/xml/include/sax/XIncludeFilter;
class	scala/xml/include/sax/XIncludeFilter
NameAndType	bases:Ljava/util/Stack;
Field	scala/xml/include/sax/XIncludeFilter.bases:Ljava/util/Stack;
Asciz	()Ljava/util/Stack<Ljava/net/URL;>;;
NameAndType	locators:Ljava/util/Stack;
Field	scala/xml/include/sax/XIncludeFilter.locators:Ljava/util/Stack;
Asciz	()Ljava/util/Stack<Lorg/xml/sax/Locator;>;;
Asciz	setDocumentLocator;
Asciz	(Lorg/xml/sax/Locator;)V;
NameAndType	locators:()Ljava/util/Stack;
Method	scala/xml/include/sax/XIncludeFilter.locators:()Ljava/util/Stack;
Asciz	java/util/Stack;
class	java/util/Stack
Asciz	push;
Asciz	(Ljava/lang/Object;)Ljava/lang/Object;;
NameAndType	push:(Ljava/lang/Object;)Ljava/lang/Object;
Method	java/util/Stack.push:(Ljava/lang/Object;)Ljava/lang/Object;
Asciz	org/xml/sax/Locator;
class	org/xml/sax/Locator
Asciz	getSystemId;
NameAndType	getSystemId:()Ljava/lang/String;
InterfaceMethod	org/xml/sax/Locator.getSystemId:()Ljava/lang/String;
NameAndType	bases:()Ljava/util/Stack;
Method	scala/xml/include/sax/XIncludeFilter.bases:()Ljava/util/Stack;
Asciz	java/net/URL;
class	java/net/URL
Asciz	<init>;
Asciz	(Ljava/lang/String;)V;
NameAndType	"<init>":(Ljava/lang/String;)V
Method	java/net/URL."<init>":(Ljava/lang/String;)V
Asciz	org/xml/sax/helpers/XMLFilterImpl;
class	org/xml/sax/helpers/XMLFilterImpl
NameAndType	setDocumentLocator:(Lorg/xml/sax/Locator;)V
Method	org/xml/sax/helpers/XMLFilterImpl.setDocumentLocator:(Lorg/xml/sax/Locator;)V
Asciz	java/lang/UnsupportedOperationException;
class	java/lang/UnsupportedOperationException
Asciz	scala/collection/mutable/StringBuilder;
class	scala/collection/mutable/StringBuilder
Asciz	()V;
NameAndType	"<init>":()V
Method	scala/collection/mutable/StringBuilder."<init>":()V
Asciz	Unrecognized SYSTEM ID: ;
String	Unrecognized SYSTEM ID: 
Asciz	append;
Asciz	(Ljava/lang/Object;)Lscala/collection/mutable/StringBuilder;;
NameAndType	append:(Ljava/lang/Object;)Lscala/collection/mutable/StringBuilder;
Method	scala/collection/mutable/StringBuilder.append:(Ljava/lang/Object;)Lscala/collection/mutable/StringBuilder;
Asciz	toString;
NameAndType	toString:()Ljava/lang/String;
Method	scala/collection/mutable/StringBuilder.toString:()Ljava/lang/String;
Method	java/lang/UnsupportedOperationException."<init>":(Ljava/lang/String;)V
Asciz	java/net/MalformedURLException;
class	java/net/MalformedURLException
Asciz	this;
Asciz	Lscala/xml/include/sax/XIncludeFilter;;
Asciz	locator;
Asciz	Lorg/xml/sax/Locator;;
Asciz	base;
Asciz	exceptionResult1;
Asciz	Ljava/lang/Object;;
Asciz	LocalVariableTable;
Asciz	()I;
NameAndType	level:I
Field	scala/xml/include/sax/XIncludeFilter.level:I
Asciz	level_$eq;
Asciz	(I)V;
Asciz	insideIncludeElement;
Asciz	()Z;
NameAndType	level:()I
Method	scala/xml/include/sax/XIncludeFilter.level:()I
Asciz	startElement;
Asciz	(Ljava/lang/String;Ljava/lang/String;Ljava/lang/String;Lorg/xml/sax/Attributes;)V;
Asciz	http://www.w3.org/XML/1998/namespace;
String	http://www.w3.org/XML/1998/namespace
String	base
Asciz	org/xml/sax/Attributes;
class	org/xml/sax/Attributes
Asciz	getValue;
Asciz	(Ljava/lang/String;Ljava/lang/String;)Ljava/lang/String;;
NameAndType	getValue:(Ljava/lang/String;Ljava/lang/String;)Ljava/lang/String;
InterfaceMethod	org/xml/sax/Attributes.getValue:(Ljava/lang/String;Ljava/lang/String;)Ljava/lang/String;
Asciz	peek;
Asciz	()Ljava/lang/Object;;
NameAndType	peek:()Ljava/lang/Object;
Method	java/util/Stack.peek:()Ljava/lang/Object;
Asciz	java/lang/Object;
class	java/lang/Object
Asciz	equals;
Asciz	(Ljava/lang/Object;)Z;
NameAndType	equals:(Ljava/lang/Object;)Z
Method	java/lang/Object.equals:(Ljava/lang/Object;)Z
Asciz	(Ljava/net/URL;Ljava/lang/String;)V;
NameAndType	"<init>":(Ljava/net/URL;Ljava/lang/String;)V
Method	java/net/URL."<init>":(Ljava/net/URL;Ljava/lang/String;)V
Asciz	java/lang/String;
class	java/lang/String
Method	java/lang/String.equals:(Ljava/lang/Object;)Z
Asciz	include;
String	include
Asciz	href;
String	href
Asciz	(Ljava/lang/String;)Ljava/lang/String;;
NameAndType	getValue:(Ljava/lang/String;)Ljava/lang/String;
InterfaceMethod	org/xml/sax/Attributes.getValue:(Ljava/lang/String;)Ljava/lang/String;
Asciz	org/xml/sax/SAXException;
class	org/xml/sax/SAXException
Asciz	Missing href attribute;
String	Missing href attribute
Method	org/xml/sax/SAXException."<init>":(Ljava/lang/String;)V
Asciz	parse;
String	parse
Asciz	xml;
String	xml
Asciz	text;
String	text
Asciz	encoding;
String	encoding
Asciz	includeTextDocument;
Asciz	(Ljava/lang/String;Ljava/lang/String;)V;
NameAndType	includeTextDocument:(Ljava/lang/String;Ljava/lang/String;)V
Method	scala/xml/include/sax/XIncludeFilter.includeTextDocument:(Ljava/lang/String;Ljava/lang/String;)V
Asciz	includeXMLDocument;
NameAndType	includeXMLDocument:(Ljava/lang/String;)V
Method	scala/xml/include/sax/XIncludeFilter.includeXMLDocument:(Ljava/lang/String;)V
NameAndType	level_$eq:(I)V
Method	scala/xml/include/sax/XIncludeFilter.level_$eq:(I)V
Asciz	Illegal value for parse attribute: ;
String	Illegal value for parse attribute: 
NameAndType	atRoot:()Z
Method	scala/xml/include/sax/XIncludeFilter.atRoot:()Z
Asciz	org/xml/sax/helpers/AttributesImpl;
class	org/xml/sax/helpers/AttributesImpl
Asciz	(Lorg/xml/sax/Attributes;)V;
NameAndType	"<init>":(Lorg/xml/sax/Attributes;)V
Method	org/xml/sax/helpers/AttributesImpl."<init>":(Lorg/xml/sax/Attributes;)V
Asciz	xml:base;
String	xml:base
Asciz	CDATA;
String	CDATA
Asciz	toExternalForm;
NameAndType	toExternalForm:()Ljava/lang/String;
Method	java/net/URL.toExternalForm:()Ljava/lang/String;
Asciz	addAttribute;
Asciz	(Ljava/lang/String;Ljava/lang/String;Ljava/lang/String;Ljava/lang/String;Ljava/lang/String;)V;
NameAndType	addAttribute:(Ljava/lang/String;Ljava/lang/String;Ljava/lang/String;Ljava/lang/String;Ljava/lang/String;)V
Method	org/xml/sax/helpers/AttributesImpl.addAttribute:(Ljava/lang/String;Ljava/lang/String;Ljava/lang/String;Ljava/lang/String;Ljava/lang/String;)V
Asciz	atRoot_$eq;
Asciz	(Z)V;
NameAndType	atRoot_$eq:(Z)V
Method	scala/xml/include/sax/XIncludeFilter.atRoot_$eq:(Z)V
NameAndType	startElement:(Ljava/lang/String;Ljava/lang/String;Ljava/lang/String;Lorg/xml/sax/Attributes;)V
Method	org/xml/sax/helpers/XMLFilterImpl.startElement:(Ljava/lang/String;Ljava/lang/String;Ljava/lang/String;Lorg/xml/sax/Attributes;)V
Asciz	Malformed base URL: ;
String	Malformed base URL: 
Asciz	(Ljava/lang/String;Ljava/lang/Exception;)V;
NameAndType	"<init>":(Ljava/lang/String;Ljava/lang/Exception;)V
Method	org/xml/sax/SAXException."<init>":(Ljava/lang/String;Ljava/lang/Exception;)V
Asciz	uri;
Asciz	localName;
Asciz	qName;
Asciz	atts1;
Asciz	Lorg/xml/sax/Attributes;;
Asciz	atts;
Asciz	parentBase;
Asciz	Ljava/net/URL;;
Asciz	currentBase;
Asciz	attsImpl;
Asciz	Lorg/xml/sax/helpers/AttributesImpl;;
Asciz	endElement;
Asciz	(Ljava/lang/String;Ljava/lang/String;Ljava/lang/String;)V;
Asciz	pop;
NameAndType	pop:()Ljava/lang/Object;
Method	java/util/Stack.pop:()Ljava/lang/Object;
NameAndType	endElement:(Ljava/lang/String;Ljava/lang/String;Ljava/lang/String;)V
Method	org/xml/sax/helpers/XMLFilterImpl.endElement:(Ljava/lang/String;Ljava/lang/String;Ljava/lang/String;)V
NameAndType	depth:I
Field	scala/xml/include/sax/XIncludeFilter.depth:I
Asciz	depth_$eq;
Asciz	startDocument;
NameAndType	depth:()I
Method	scala/xml/include/sax/XIncludeFilter.depth:()I
NameAndType	startDocument:()V
Method	org/xml/sax/helpers/XMLFilterImpl.startDocument:()V
NameAndType	depth_$eq:(I)V
Method	scala/xml/include/sax/XIncludeFilter.depth_$eq:(I)V
Asciz	endDocument;
NameAndType	endDocument:()V
Method	org/xml/sax/helpers/XMLFilterImpl.endDocument:()V
Asciz	startPrefixMapping;
NameAndType	startPrefixMapping:(Ljava/lang/String;Ljava/lang/String;)V
Method	org/xml/sax/helpers/XMLFilterImpl.startPrefixMapping:(Ljava/lang/String;Ljava/lang/String;)V
Asciz	prefix;
Asciz	endPrefixMapping;
NameAndType	endPrefixMapping:(Ljava/lang/String;)V
Method	org/xml/sax/helpers/XMLFilterImpl.endPrefixMapping:(Ljava/lang/String;)V
Asciz	characters;
Asciz	([CII)V;
NameAndType	characters:([CII)V
Method	org/xml/sax/helpers/XMLFilterImpl.characters:([CII)V
Asciz	ch;
Asciz	[C;
Asciz	start;
Asciz	length;
Asciz	ignorableWhitespace;
NameAndType	ignorableWhitespace:([CII)V
Method	org/xml/sax/helpers/XMLFilterImpl.ignorableWhitespace:([CII)V
Asciz	processingInstruction;
NameAndType	processingInstruction:(Ljava/lang/String;Ljava/lang/String;)V
Method	org/xml/sax/helpers/XMLFilterImpl.processingInstruction:(Ljava/lang/String;Ljava/lang/String;)V
Asciz	target;
Asciz	data;
Asciz	skippedEntity;
NameAndType	skippedEntity:(Ljava/lang/String;)V
Method	org/xml/sax/helpers/XMLFilterImpl.skippedEntity:(Ljava/lang/String;)V
Asciz	name;
Asciz	getLocation;
Asciz	;
String	
Asciz	getPublicId;
NameAndType	getPublicId:()Ljava/lang/String;
InterfaceMethod	org/xml/sax/Locator.getPublicId:()Ljava/lang/String;
Asciz	getLineNumber;
NameAndType	getLineNumber:()I
InterfaceMethod	org/xml/sax/Locator.getLineNumber:()I
Asciz	getColumnNumber;
NameAndType	getColumnNumber:()I
InterfaceMethod	org/xml/sax/Locator.getColumnNumber:()I
Asciz	 in document included from ;
String	 in document included from 
Asciz	 at ;
String	 at 
Asciz	 at line ;
String	 at line 
Asciz	scala/runtime/BoxesRunTime;
class	scala/runtime/BoxesRunTime
Asciz	boxToInteger;
Asciz	(I)Ljava/lang/Integer;;
NameAndType	boxToInteger:(I)Ljava/lang/Integer;
Method	scala/runtime/BoxesRunTime.boxToInteger:(I)Ljava/lang/Integer;
Asciz	, column ;
String	, column 
Asciz	locationString;
Asciz	publicID;
Asciz	systemID;
Asciz	column;
Asciz	line;
Asciz	trim;
NameAndType	trim:()Ljava/lang/String;
Method	java/lang/String.trim:()Ljava/lang/String;
Asciz	UTF-8;
String	UTF-8
Asciz	openConnection;
Asciz	()Ljava/net/URLConnection;;
NameAndType	openConnection:()Ljava/net/URLConnection;
Method	java/net/URL.openConnection:()Ljava/net/URLConnection;
Asciz	java/io/BufferedInputStream;
class	java/io/BufferedInputStream
Asciz	java/net/URLConnection;
class	java/net/URLConnection
Asciz	getInputStream;
Asciz	()Ljava/io/InputStream;;
NameAndType	getInputStream:()Ljava/io/InputStream;
Method	java/net/URLConnection.getInputStream:()Ljava/io/InputStream;
Asciz	(Ljava/io/InputStream;)V;
NameAndType	"<init>":(Ljava/io/InputStream;)V
Method	java/io/BufferedInputStream."<init>":(Ljava/io/InputStream;)V
Asciz	getContentEncoding;
NameAndType	getContentEncoding:()Ljava/lang/String;
Method	java/net/URLConnection.getContentEncoding:()Ljava/lang/String;
Asciz	getContentType;
NameAndType	getContentType:()Ljava/lang/String;
Method	java/net/URLConnection.getContentType:()Ljava/lang/String;
Asciz	toLowerCase;
NameAndType	toLowerCase:()Ljava/lang/String;
Method	java/lang/String.toLowerCase:()Ljava/lang/String;
Asciz	text/xml;
String	text/xml
Asciz	application/xml;
String	application/xml
Asciz	text/;
String	text/
Asciz	startsWith;
Asciz	(Ljava/lang/String;)Z;
NameAndType	startsWith:(Ljava/lang/String;)Z
Method	java/lang/String.startsWith:(Ljava/lang/String;)Z
Asciz	+xml;
String	+xml
Asciz	endsWith;
NameAndType	endsWith:(Ljava/lang/String;)Z
Method	java/lang/String.endsWith:(Ljava/lang/String;)Z
Asciz	application/;
String	application/
Asciz	scala/xml/include/sax/EncodingHeuristics$;
class	scala/xml/include/sax/EncodingHeuristics$
Asciz	MODULE$;
Asciz	Lscala/xml/include/sax/EncodingHeuristics$;;
NameAndType	MODULE$:Lscala/xml/include/sax/EncodingHeuristics$;
Field	scala/xml/include/sax/EncodingHeuristics$.MODULE$:Lscala/xml/include/sax/EncodingHeuristics$;
Asciz	readEncodingFromStream;
Asciz	(Ljava/io/InputStream;)Ljava/lang/String;;
NameAndType	readEncodingFromStream:(Ljava/io/InputStream;)Ljava/lang/String;
Method	scala/xml/include/sax/EncodingHeuristics$.readEncodingFromStream:(Ljava/io/InputStream;)Ljava/lang/String;
Asciz	java/io/InputStreamReader;
class	java/io/InputStreamReader
Asciz	(Ljava/io/InputStream;Ljava/lang/String;)V;
NameAndType	"<init>":(Ljava/io/InputStream;Ljava/lang/String;)V
Method	java/io/InputStreamReader."<init>":(Ljava/io/InputStream;Ljava/lang/String;)V
int	1024;
Asciz	read;
Asciz	([CII)I;
NameAndType	read:([CII)I
Method	java/io/InputStreamReader.read:([CII)I
Method	scala/xml/include/sax/XIncludeFilter.characters:([CII)V
Asciz	scala/xml/include/UnavailableResourceException;
class	scala/xml/include/UnavailableResourceException
Asciz	Unresolvable URL ;
String	Unresolvable URL 
NameAndType	getLocation:()Ljava/lang/String;
Method	scala/xml/include/sax/XIncludeFilter.getLocation:()Ljava/lang/String;
Method	scala/xml/include/UnavailableResourceException."<init>":(Ljava/lang/String;)V
Asciz	setRootCause;
Asciz	(Ljava/lang/Throwable;)V;
NameAndType	setRootCause:(Ljava/lang/Throwable;)V
Method	scala/xml/include/UnavailableResourceException.setRootCause:(Ljava/lang/Throwable;)V
Asciz	Document not found: ;
String	Document not found: 
Asciz	Unsupported encoding: ;
String	Unsupported encoding: 
Asciz	java/io/UnsupportedEncodingException;
class	java/io/UnsupportedEncodingException
Asciz	java/io/IOException;
class	java/io/IOException
Asciz	url;
Asciz	encoding1;
Asciz	source;
Asciz	ex;
Asciz	Lscala/xml/include/UnavailableResourceException;;
Asciz	uc;
Asciz	Ljava/net/URLConnection;;
Asciz	in;
Asciz	Ljava/io/BufferedInputStream;;
Asciz	encodingFromHeader;
Asciz	contentType;
Asciz	reader;
Asciz	Ljava/io/InputStreamReader;;
Asciz	c;
Asciz	charsRead;
NameAndType	atRoot:Z
Field	scala/xml/include/sax/XIncludeFilter.atRoot:Z
Asciz	org/xml/sax/helpers/XMLReaderFactory;
class	org/xml/sax/helpers/XMLReaderFactory
Asciz	createXMLReader;
Asciz	()Lorg/xml/sax/XMLReader;;
NameAndType	createXMLReader:()Lorg/xml/sax/XMLReader;
Method	org/xml/sax/helpers/XMLReaderFactory.createXMLReader:()Lorg/xml/sax/XMLReader;
Asciz	scala/xml/package$;
class	scala/xml/package$
Asciz	Lscala/xml/package$;;
NameAndType	MODULE$:Lscala/xml/package$;
Field	scala/xml/package$.MODULE$:Lscala/xml/package$;
Asciz	XercesClassName;
NameAndType	XercesClassName:()Ljava/lang/String;
Method	scala/xml/package$.XercesClassName:()Ljava/lang/String;
Asciz	(Ljava/lang/String;)Lorg/xml/sax/XMLReader;;
NameAndType	createXMLReader:(Ljava/lang/String;)Lorg/xml/sax/XMLReader;
Method	org/xml/sax/helpers/XMLReaderFactory.createXMLReader:(Ljava/lang/String;)Lorg/xml/sax/XMLReader;
Asciz	org/xml/sax/XMLReader;
class	org/xml/sax/XMLReader
Asciz	setContentHandler;
Asciz	(Lorg/xml/sax/ContentHandler;)V;
NameAndType	setContentHandler:(Lorg/xml/sax/ContentHandler;)V
InterfaceMethod	org/xml/sax/XMLReader.setContentHandler:(Lorg/xml/sax/ContentHandler;)V
Asciz	getEntityResolver;
Asciz	()Lorg/xml/sax/EntityResolver;;
NameAndType	getEntityResolver:()Lorg/xml/sax/EntityResolver;
Method	scala/xml/include/sax/XIncludeFilter.getEntityResolver:()Lorg/xml/sax/EntityResolver;
Asciz	setEntityResolver;
Asciz	(Lorg/xml/sax/EntityResolver;)V;
NameAndType	setEntityResolver:(Lorg/xml/sax/EntityResolver;)V
InterfaceMethod	org/xml/sax/XMLReader.setEntityResolver:(Lorg/xml/sax/EntityResolver;)V
Asciz	contains;
NameAndType	contains:(Ljava/lang/Object;)Z
Method	java/util/Stack.contains:(Ljava/lang/Object;)Z
Asciz	Circular XInclude Reference;
String	Circular XInclude Reference
Asciz	scala/xml/include/CircularIncludeException;
class	scala/xml/include/CircularIncludeException
Asciz	Circular XInclude Reference to ;
String	Circular XInclude Reference to 
Method	scala/xml/include/CircularIncludeException."<init>":(Ljava/lang/String;)V
NameAndType	parse:(Ljava/lang/String;)V
InterfaceMethod	org/xml/sax/XMLReader.parse:(Ljava/lang/String;)V
Asciz	java/lang/System;
class	java/lang/System
Asciz	err;
Asciz	Ljava/io/PrintStream;;
NameAndType	err:Ljava/io/PrintStream;
Field	java/lang/System.err:Ljava/io/PrintStream;
Asciz	Could not find an XML parser;
String	Could not find an XML parser
Asciz	java/io/PrintStream;
class	java/io/PrintStream
Asciz	println;
NameAndType	println:(Ljava/lang/String;)V
Method	java/io/PrintStream.println:(Ljava/lang/String;)V
Asciz	exceptionResult2;
Asciz	parser;
Asciz	Lorg/xml/sax/XMLReader;;
Asciz	exceptionResult3;
Asciz	exceptionResult4;
Asciz	resolver;
Asciz	Lorg/xml/sax/EntityResolver;;
Asciz	previousLevel;
Method	org/xml/sax/helpers/XMLFilterImpl."<init>":()V
Method	java/util/Stack."<init>":()V
Asciz	ScalaSig;
Asciz	scala/ScalaObject;
class	scala/ScalaObject

{
private boolean atRoot;
  Signature: Z

private int depth;
  Signature: I

private int level;
  Signature: I

private final java.util.Stack locators;
  Signature: Ljava/util/Stack;
  Signature: length = 0x2
   00 0A 

private final java.util.Stack bases;
  Signature: Ljava/util/Stack;
  Signature: length = 0x2
   00 0D 

private final java.lang.String XINCLUDE_NAMESPACE;
  Signature: Ljava/lang/String;

public final java.lang.String XINCLUDE_NAMESPACE();
  Signature: ()Ljava/lang/String;
  Code:
   Stack=1, Locals=1, Args_size=1
	ldc	String http://www.w3.org/2001/XInclude
	areturn
  Labels:

private java.util.Stack bases();
  Signature: ()Ljava/util/Stack;
  Code:
   Stack=1, Locals=1, Args_size=1
	aload_0
	getfield	Field bases:Ljava/util/Stack;
	areturn
  Labels:
  Signature: length = 0x2
   00 1A 

private java.util.Stack locators();
  Signature: ()Ljava/util/Stack;
  Code:
   Stack=1, Locals=1, Args_size=1
	aload_0
	getfield	Field locators:Ljava/util/Stack;
	areturn
  Labels:
  Signature: length = 0x2
   00 1D 

public void setDocumentLocator(org.xml.sax.Locator);
  Signature: (Lorg/xml/sax/Locator;)V
  Code:
   Stack=4, Locals=5, Args_size=2
	aload_0
	invokespecial	Method locators:()Ljava/util/Stack;
	aload_1
	invokevirtual	Method java/util/Stack.push:(Ljava/lang/Object;)Ljava/lang/Object;
	pop
	aload_1
	invokeinterface	InterfaceMethod org/xml/sax/Locator.getSystemId:()Ljava/lang/String;
	astore_2
	aconst_null
	astore_3
	aload_0
	invokespecial	Method bases:()Ljava/util/Stack;
	new	class java/net/URL
	dup
	aload_2
	invokespecial	Method java/net/URL."<init>":(Ljava/lang/String;)V
	invokevirtual	Method java/util/Stack.push:(Ljava/lang/Object;)Ljava/lang/Object;
	astore_3
	aload_3
	pop
	aload_0
	aload_1
	invokespecial	Method org/xml/sax/helpers/XMLFilterImpl.setDocumentLocator:(Lorg/xml/sax/Locator;)V
	return
	astore	4
	new	class java/lang/UnsupportedOperationException
	dup
	new	class scala/collection/mutable/StringBuilder
	dup
	invokespecial	Method scala/collection/mutable/StringBuilder."<init>":()V
	ldc	String Unrecognized SYSTEM ID: 
	invokevirtual	Method scala/collection/mutable/StringBuilder.append:(Ljava/lang/Object;)Lscala/collection/mutable/StringBuilder;
	aload_2
	invokevirtual	Method scala/collection/mutable/StringBuilder.append:(Ljava/lang/Object;)Lscala/collection/mutable/StringBuilder;
	invokevirtual	Method scala/collection/mutable/StringBuilder.toString:()Ljava/lang/String;
	invokespecial	Method java/lang/UnsupportedOperationException."<init>":(Ljava/lang/String;)V
	athrow
  Labels:
  Exception table:
   from   to  target type
    18    34    42   Class java/net/MalformedURLException

  LocalVariableTable: 
   Start  Length  Slot  Name   Signature
   0      71      0    this       Lscala/xml/include/sax/XIncludeFilter;
   0      71      1    locator       Lorg/xml/sax/Locator;
   16      25      2    base       Ljava/lang/String;
   42      29      2    base       Ljava/lang/String;
   18      18      3    exceptionResult1       Ljava/lang/Object;
   42      29      3    exceptionResult1       Ljava/lang/Object;


private int level();
  Signature: ()I
  Code:
   Stack=1, Locals=1, Args_size=1
	aload_0
	getfield	Field level:I
	ireturn
  Labels:

private void level_$eq(int);
  Signature: (I)V
  Code:
   Stack=2, Locals=2, Args_size=2
	aload_0
	iload_1
	putfield	Field level:I
	return
  Labels:

public boolean insideIncludeElement();
  Signature: ()Z
  Code:
   Stack=2, Locals=1, Args_size=1
	aload_0
	invokespecial	Method level:()I
	iconst_0
	if_icmpeq	l1 // iconst_0
	iconst_1
	goto	l2 // ireturn
l1	iconst_0
l2	ireturn
  Labels:
   	l1 = 12 // iconst_0
   	l2 = 13 // ireturn

public void startElement(java.lang.String, java.lang.String, java.lang.String, org.xml.sax.Attributes);
  Signature: (Ljava/lang/String;Ljava/lang/String;Ljava/lang/String;Lorg/xml/sax/Attributes;)V
  Code:
   Stack=6, Locals=17, Args_size=5
	aload	4
	astore	5
	aload_0
	invokespecial	Method level:()I
	iconst_0
	if_icmpne	l1 // return
	aload	5
	ldc	String http://www.w3.org/XML/1998/namespace
	ldc	String base
	invokeinterface	InterfaceMethod org/xml/sax/Attributes.getValue:(Ljava/lang/String;Ljava/lang/String;)Ljava/lang/String;
	astore	6
	aload_0
	invokespecial	Method bases:()Ljava/util/Stack;
	invokevirtual	Method java/util/Stack.peek:()Ljava/lang/Object;
	checkcast	class java/net/URL
	astore	7
	aload	7
	astore	8
	aload	6
	dup
	astore	9
	ifnull	l2 // aload_0
	aload	9
	aconst_null
	invokevirtual	Method java/lang/Object.equals:(Ljava/lang/Object;)Z
	ifne	l2 // aload_0
	new	class java/net/URL
	dup
	aload	7
	aload	6
	invokespecial	Method java/net/URL."<init>":(Ljava/net/URL;Ljava/lang/String;)V
	astore	8
l2	aload_0
	invokespecial	Method bases:()Ljava/util/Stack;
	aload	8
	invokevirtual	Method java/util/Stack.push:(Ljava/lang/Object;)Ljava/lang/Object;
	pop
	aload_1
	ldc	String http://www.w3.org/2001/XInclude
	invokevirtual	Method java/lang/String.equals:(Ljava/lang/Object;)Z
	ifeq	l3 // aload_0
	aload_2
	ldc	String include
	invokevirtual	Method java/lang/String.equals:(Ljava/lang/Object;)Z
	ifeq	l3 // aload_0
	aload	5
	ldc	String href
	invokeinterface	InterfaceMethod org/xml/sax/Attributes.getValue:(Ljava/lang/String;)Ljava/lang/String;
	astore	11
	aload	11
	dup
	astore	12
	ifnull	l4 // new
	aload	12
	aconst_null
	invokevirtual	Method java/lang/Object.equals:(Ljava/lang/Object;)Z
	ifeq	l5 // aload
l4	new	class org/xml/sax/SAXException
	dup
	ldc	String Missing href attribute
	invokespecial	Method org/xml/sax/SAXException."<init>":(Ljava/lang/String;)V
	athrow
l5	aload	5
	ldc	String parse
	invokeinterface	InterfaceMethod org/xml/sax/Attributes.getValue:(Ljava/lang/String;)Ljava/lang/String;
	astore	13
	aload	13
	dup
	astore	14
	ifnull	l6 // ldc
	aload	14
	aconst_null
	invokevirtual	Method java/lang/Object.equals:(Ljava/lang/Object;)Z
	ifeq	l7 // aload
l6	ldc	String xml
	astore	13
l7	aload	13
	ldc	String text
	invokevirtual	Method java/lang/String.equals:(Ljava/lang/Object;)Z
	ifeq	l8 // aload
	aload	5
	ldc	String encoding
	invokeinterface	InterfaceMethod org/xml/sax/Attributes.getValue:(Ljava/lang/String;)Ljava/lang/String;
	astore	15
	aload_0
	aload	11
	aload	15
	invokespecial	Method includeTextDocument:(Ljava/lang/String;Ljava/lang/String;)V
	goto	l9 // aload_0
l8	aload	13
	ldc	String xml
	invokevirtual	Method java/lang/String.equals:(Ljava/lang/Object;)Z
	ifeq	l10 // new
	aload_0
	aload	11
	invokespecial	Method includeXMLDocument:(Ljava/lang/String;)V
l9	aload_0
	aload_0
	invokespecial	Method level:()I
	iconst_1
	iadd
	invokespecial	Method level_$eq:(I)V
	goto	l1 // return
l10	new	class org/xml/sax/SAXException
	dup
	new	class scala/collection/mutable/StringBuilder
	dup
	invokespecial	Method scala/collection/mutable/StringBuilder."<init>":()V
	ldc	String Illegal value for parse attribute: 
	invokevirtual	Method scala/collection/mutable/StringBuilder.append:(Ljava/lang/Object;)Lscala/collection/mutable/StringBuilder;
	aload	13
	invokevirtual	Method scala/collection/mutable/StringBuilder.append:(Ljava/lang/Object;)Lscala/collection/mutable/StringBuilder;
	invokevirtual	Method scala/collection/mutable/StringBuilder.toString:()Ljava/lang/String;
	invokespecial	Method org/xml/sax/SAXException."<init>":(Ljava/lang/String;)V
	athrow
l3	aload_0
	invokespecial	Method atRoot:()Z
	ifeq	l11 // aload_0
	new	class org/xml/sax/helpers/AttributesImpl
	dup
	aload	5
	invokespecial	Method org/xml/sax/helpers/AttributesImpl."<init>":(Lorg/xml/sax/Attributes;)V
	astore	16
	aload	16
	ldc	String http://www.w3.org/XML/1998/namespace
	ldc	String base
	ldc	String xml:base
	ldc	String CDATA
	aload	8
	invokevirtual	Method java/net/URL.toExternalForm:()Ljava/lang/String;
	invokevirtual	Method org/xml/sax/helpers/AttributesImpl.addAttribute:(Ljava/lang/String;Ljava/lang/String;Ljava/lang/String;Ljava/lang/String;Ljava/lang/String;)V
	aload	16
	astore	5
	aload_0
	iconst_0
	invokespecial	Method atRoot_$eq:(Z)V
l11	aload_0
	aload_1
	aload_2
	aload_3
	aload	5
	invokespecial	Method org/xml/sax/helpers/XMLFilterImpl.startElement:(Ljava/lang/String;Ljava/lang/String;Ljava/lang/String;Lorg/xml/sax/Attributes;)V
l1	return
	astore	10
	new	class org/xml/sax/SAXException
	dup
	new	class scala/collection/mutable/StringBuilder
	dup
	invokespecial	Method scala/collection/mutable/StringBuilder."<init>":()V
	ldc	String Malformed base URL: 
	invokevirtual	Method scala/collection/mutable/StringBuilder.append:(Ljava/lang/Object;)Lscala/collection/mutable/StringBuilder;
	aload	8
	invokevirtual	Method scala/collection/mutable/StringBuilder.append:(Ljava/lang/Object;)Lscala/collection/mutable/StringBuilder;
	invokevirtual	Method scala/collection/mutable/StringBuilder.toString:()Ljava/lang/String;
	aload	10
	invokespecial	Method org/xml/sax/SAXException."<init>":(Ljava/lang/String;Ljava/lang/Exception;)V
	athrow
  Labels:
   	l2 = 71 // aload_0
   	l4 = 127 // new
   	l5 = 137 // aload
   	l6 = 165 // ldc
   	l7 = 169 // aload
   	l8 = 201 // aload
   	l9 = 217 // aload_0
   	l10 = 230 // new
   	l3 = 258 // aload_0
   	l11 = 303 // aload_0
   	l1 = 312 // return
  Exception table:
   from   to  target type
    58    71   313   Class java/net/MalformedURLException

  LocalVariableTable: 
   Start  Length  Slot  Name   Signature
   0      345      0    this       Lscala/xml/include/sax/XIncludeFilter;
   0      345      1    uri       Ljava/lang/String;
   0      345      2    localName       Ljava/lang/String;
   0      345      3    qName       Ljava/lang/String;
   0      345      4    atts1       Lorg/xml/sax/Attributes;
   4      341      5    atts       Lorg/xml/sax/Attributes;
   25      287      6    base       Ljava/lang/String;
   313      32      6    base       Ljava/lang/String;
   37      275      7    parentBase       Ljava/net/URL;
   313      32      7    parentBase       Ljava/net/URL;
   41      271      8    currentBase       Ljava/net/URL;
   313      32      8    currentBase       Ljava/net/URL;
   110      117      11    href       Ljava/lang/String;
   230      28      11    href       Ljava/lang/String;
   148      79      13    parse       Ljava/lang/String;
   230      28      13    parse       Ljava/lang/String;
   190      8      15    encoding       Ljava/lang/String;
   276      27      16    attsImpl       Lorg/xml/sax/helpers/AttributesImpl;


public void endElement(java.lang.String, java.lang.String, java.lang.String);
  Signature: (Ljava/lang/String;Ljava/lang/String;Ljava/lang/String;)V
  Code:
   Stack=4, Locals=4, Args_size=4
	aload_1
	ldc	String http://www.w3.org/2001/XInclude
	invokevirtual	Method java/lang/String.equals:(Ljava/lang/Object;)Z
	ifeq	l1 // aload_0
	aload_2
	ldc	String include
	invokevirtual	Method java/lang/String.equals:(Ljava/lang/Object;)Z
	ifeq	l1 // aload_0
	aload_0
	aload_0
	invokespecial	Method level:()I
	iconst_1
	isub
	invokespecial	Method level_$eq:(I)V
	goto	l2 // return
l1	aload_0
	invokespecial	Method level:()I
	iconst_0
	if_icmpne	l2 // return
	aload_0
	invokespecial	Method bases:()Ljava/util/Stack;
	invokevirtual	Method java/util/Stack.pop:()Ljava/lang/Object;
	pop
	aload_0
	aload_1
	aload_2
	aload_3
	invokespecial	Method org/xml/sax/helpers/XMLFilterImpl.endElement:(Ljava/lang/String;Ljava/lang/String;Ljava/lang/String;)V
l2	return
  Labels:
   	l1 = 31 // aload_0
   	l2 = 54 // return
  LocalVariableTable: 
   Start  Length  Slot  Name   Signature
   0      55      0    this       Lscala/xml/include/sax/XIncludeFilter;
   0      55      1    uri       Ljava/lang/String;
   0      55      2    localName       Ljava/lang/String;
   0      55      3    qName       Ljava/lang/String;


private int depth();
  Signature: ()I
  Code:
   Stack=1, Locals=1, Args_size=1
	aload_0
	getfield	Field depth:I
	ireturn
  Labels:

private void depth_$eq(int);
  Signature: (I)V
  Code:
   Stack=2, Locals=2, Args_size=2
	aload_0
	iload_1
	putfield	Field depth:I
	return
  Labels:

public void startDocument();
  Signature: ()V
  Code:
   Stack=3, Locals=1, Args_size=1
	aload_0
	iconst_0
	invokespecial	Method level_$eq:(I)V
	aload_0
	invokespecial	Method depth:()I
	iconst_0
	if_icmpne	l1 // aload_0
	aload_0
	invokespecial	Method org/xml/sax/helpers/XMLFilterImpl.startDocument:()V
l1	aload_0
	aload_0
	invokespecial	Method depth:()I
	iconst_1
	iadd
	invokespecial	Method depth_$eq:(I)V
	return
  Labels:
   	l1 = 17 // aload_0

public void endDocument();
  Signature: ()V
  Code:
   Stack=3, Locals=1, Args_size=1
	aload_0
	invokespecial	Method locators:()Ljava/util/Stack;
	invokevirtual	Method java/util/Stack.pop:()Ljava/lang/Object;
	pop
	aload_0
	invokespecial	Method bases:()Ljava/util/Stack;
	invokevirtual	Method java/util/Stack.pop:()Ljava/lang/Object;
	pop
	aload_0
	aload_0
	invokespecial	Method depth:()I
	iconst_1
	isub
	invokespecial	Method depth_$eq:(I)V
	aload_0
	invokespecial	Method depth:()I
	iconst_0
	if_icmpne	l1 // return
	aload_0
	invokespecial	Method org/xml/sax/helpers/XMLFilterImpl.endDocument:()V
l1	return
  Labels:
   	l1 = 38 // return

public void startPrefixMapping(java.lang.String, java.lang.String);
  Signature: (Ljava/lang/String;Ljava/lang/String;)V
  Code:
   Stack=3, Locals=3, Args_size=3
	aload_0
	invokespecial	Method level:()I
	iconst_0
	if_icmpne	l1 // return
	aload_0
	aload_1
	aload_2
	invokespecial	Method org/xml/sax/helpers/XMLFilterImpl.startPrefixMapping:(Ljava/lang/String;Ljava/lang/String;)V
l1	return
  Labels:
   	l1 = 14 // return
  LocalVariableTable: 
   Start  Length  Slot  Name   Signature
   0      15      0    this       Lscala/xml/include/sax/XIncludeFilter;
   0      15      1    prefix       Ljava/lang/String;
   0      15      2    uri       Ljava/lang/String;


public void endPrefixMapping(java.lang.String);
  Signature: (Ljava/lang/String;)V
  Code:
   Stack=2, Locals=2, Args_size=2
	aload_0
	invokespecial	Method level:()I
	iconst_0
	if_icmpne	l1 // return
	aload_0
	aload_1
	invokespecial	Method org/xml/sax/helpers/XMLFilterImpl.endPrefixMapping:(Ljava/lang/String;)V
l1	return
  Labels:
   	l1 = 13 // return
  LocalVariableTable: 
   Start  Length  Slot  Name   Signature
   0      14      0    this       Lscala/xml/include/sax/XIncludeFilter;
   0      14      1    prefix       Ljava/lang/String;


public void characters(char[], int, int);
  Signature: ([CII)V
  Code:
   Stack=4, Locals=4, Args_size=4
	aload_0
	invokespecial	Method level:()I
	iconst_0
	if_icmpne	l1 // return
	aload_0
	aload_1
	iload_2
	iload_3
	invokespecial	Method org/xml/sax/helpers/XMLFilterImpl.characters:([CII)V
l1	return
  Labels:
   	l1 = 15 // return
  LocalVariableTable: 
   Start  Length  Slot  Name   Signature
   0      16      0    this       Lscala/xml/include/sax/XIncludeFilter;
   0      16      1    ch       [C
   0      16      2    start       I
   0      16      3    length       I


public void ignorableWhitespace(char[], int, int);
  Signature: ([CII)V
  Code:
   Stack=4, Locals=4, Args_size=4
	aload_0
	invokespecial	Method level:()I
	iconst_0
	if_icmpne	l1 // return
	aload_0
	aload_1
	iload_2
	iload_3
	invokespecial	Method org/xml/sax/helpers/XMLFilterImpl.ignorableWhitespace:([CII)V
l1	return
  Labels:
   	l1 = 15 // return
  LocalVariableTable: 
   Start  Length  Slot  Name   Signature
   0      16      0    this       Lscala/xml/include/sax/XIncludeFilter;
   0      16      1    ch       [C
   0      16      2    start       I
   0      16      3    length       I


public void processingInstruction(java.lang.String, java.lang.String);
  Signature: (Ljava/lang/String;Ljava/lang/String;)V
  Code:
   Stack=3, Locals=3, Args_size=3
	aload_0
	invokespecial	Method level:()I
	iconst_0
	if_icmpne	l1 // return
	aload_0
	aload_1
	aload_2
	invokespecial	Method org/xml/sax/helpers/XMLFilterImpl.processingInstruction:(Ljava/lang/String;Ljava/lang/String;)V
l1	return
  Labels:
   	l1 = 14 // return
  LocalVariableTable: 
   Start  Length  Slot  Name   Signature
   0      15      0    this       Lscala/xml/include/sax/XIncludeFilter;
   0      15      1    target       Ljava/lang/String;
   0      15      2    data       Ljava/lang/String;


public void skippedEntity(java.lang.String);
  Signature: (Ljava/lang/String;)V
  Code:
   Stack=2, Locals=2, Args_size=2
	aload_0
	invokespecial	Method level:()I
	iconst_0
	if_icmpne	l1 // return
	aload_0
	aload_1
	invokespecial	Method org/xml/sax/helpers/XMLFilterImpl.skippedEntity:(Ljava/lang/String;)V
l1	return
  Labels:
   	l1 = 13 // return
  LocalVariableTable: 
   Start  Length  Slot  Name   Signature
   0      14      0    this       Lscala/xml/include/sax/XIncludeFilter;
   0      14      1    name       Ljava/lang/String;


private java.lang.String getLocation();
  Signature: ()Ljava/lang/String;
  Code:
   Stack=2, Locals=8, Args_size=1
	ldc	String 
	astore_1
	aload_0
	invokespecial	Method locators:()Ljava/util/Stack;
	invokevirtual	Method java/util/Stack.peek:()Ljava/lang/Object;
	checkcast	class org/xml/sax/Locator
	astore_2
	ldc	String 
	astore_3
	ldc	String 
	astore	4
	iconst_m1
	istore	5
	iconst_m1
	istore	6
	aload_2
	dup
	astore	7
	ifnull	l1 // new
	aload	7
	aconst_null
	invokevirtual	Method java/lang/Object.equals:(Ljava/lang/Object;)Z
	ifne	l1 // new
	aload_2
	invokeinterface	InterfaceMethod org/xml/sax/Locator.getPublicId:()Ljava/lang/String;
	astore_3
	aload_2
	invokeinterface	InterfaceMethod org/xml/sax/Locator.getSystemId:()Ljava/lang/String;
	astore	4
	aload_2
	invokeinterface	InterfaceMethod org/xml/sax/Locator.getLineNumber:()I
	istore	6
	aload_2
	invokeinterface	InterfaceMethod org/xml/sax/Locator.getColumnNumber:()I
	istore	5
l1	new	class scala/collection/mutable/StringBuilder
	dup
	invokespecial	Method scala/collection/mutable/StringBuilder."<init>":()V
	ldc	String  in document included from 
	invokevirtual	Method scala/collection/mutable/StringBuilder.append:(Ljava/lang/Object;)Lscala/collection/mutable/StringBuilder;
	aload_3
	invokevirtual	Method scala/collection/mutable/StringBuilder.append:(Ljava/lang/Object;)Lscala/collection/mutable/StringBuilder;
	ldc	String  at 
	invokevirtual	Method scala/collection/mutable/StringBuilder.append:(Ljava/lang/Object;)Lscala/collection/mutable/StringBuilder;
	aload	4
	invokevirtual	Method scala/collection/mutable/StringBuilder.append:(Ljava/lang/Object;)Lscala/collection/mutable/StringBuilder;
	ldc	String  at line 
	invokevirtual	Method scala/collection/mutable/StringBuilder.append:(Ljava/lang/Object;)Lscala/collection/mutable/StringBuilder;
	iload	6
	invokestatic	Method scala/runtime/BoxesRunTime.boxToInteger:(I)Ljava/lang/Integer;
	invokevirtual	Method scala/collection/mutable/StringBuilder.append:(Ljava/lang/Object;)Lscala/collection/mutable/StringBuilder;
	ldc_w	String , column 
	invokevirtual	Method scala/collection/mutable/StringBuilder.append:(Ljava/lang/Object;)Lscala/collection/mutable/StringBuilder;
	iload	5
	invokestatic	Method scala/runtime/BoxesRunTime.boxToInteger:(I)Ljava/lang/Integer;
	invokevirtual	Method scala/collection/mutable/StringBuilder.append:(Ljava/lang/Object;)Lscala/collection/mutable/StringBuilder;
	invokevirtual	Method scala/collection/mutable/StringBuilder.toString:()Ljava/lang/String;
	astore_1
	aload_1
	areturn
  Labels:
   	l1 = 74 // new
  LocalVariableTable: 
   Start  Length  Slot  Name   Signature
   0      133      0    this       Lscala/xml/include/sax/XIncludeFilter;
   3      129      1    locationString       Ljava/lang/String;
   14      118      2    locator       Lorg/xml/sax/Locator;
   17      115      3    publicID       Ljava/lang/String;
   21      111      4    systemID       Ljava/lang/String;
   24      108      5    column       I
   27      105      6    line       I


private void includeTextDocument(java.lang.String, java.lang.String);
  Signature: (Ljava/lang/String;Ljava/lang/String;)V
  Code:
   Stack=4, Locals=20, Args_size=3
	aload_2
	astore_3
	aload_3
	dup
	astore	4
	ifnull	l1 // ldc_w
	aload	4
	aconst_null
	invokevirtual	Method java/lang/Object.equals:(Ljava/lang/Object;)Z
	ifne	l1 // ldc_w
	aload_3
	invokevirtual	Method java/lang/String.trim:()Ljava/lang/String;
	ldc	String 
	invokevirtual	Method java/lang/String.equals:(Ljava/lang/Object;)Z
	ifeq	l2 // aconst_null
l1	ldc_w	String UTF-8
	astore_3
l2	aconst_null
	pop
	aconst_null
	astore	5
	aload_0
	invokespecial	Method bases:()Ljava/util/Stack;
	invokevirtual	Method java/util/Stack.peek:()Ljava/lang/Object;
	checkcast	class java/net/URL
	astore	8
	new	class java/net/URL
	dup
	aload	8
	aload_1
	invokespecial	Method java/net/URL."<init>":(Ljava/net/URL;Ljava/lang/String;)V
	astore	5
	aload	5
	invokevirtual	Method java/net/URL.openConnection:()Ljava/net/URLConnection;
	astore	11
	new	class java/io/BufferedInputStream
	dup
	aload	11
	invokevirtual	Method java/net/URLConnection.getInputStream:()Ljava/io/InputStream;
	invokespecial	Method java/io/BufferedInputStream."<init>":(Ljava/io/InputStream;)V
	astore	12
	aload	11
	invokevirtual	Method java/net/URLConnection.getContentEncoding:()Ljava/lang/String;
	astore	13
	aload	11
	invokevirtual	Method java/net/URLConnection.getContentType:()Ljava/lang/String;
	astore	14
	aload	13
	dup
	astore	15
	ifnull	l3 // aload
	aload	15
	aconst_null
	invokevirtual	Method java/lang/Object.equals:(Ljava/lang/Object;)Z
	ifeq	l4 // aload
l3	aload	14
	dup
	astore	16
	ifnull	l5 // new
	aload	16
	aconst_null
	invokevirtual	Method java/lang/Object.equals:(Ljava/lang/Object;)Z
	ifne	l5 // new
	aload	14
	invokevirtual	Method java/lang/String.toLowerCase:()Ljava/lang/String;
	astore	14
	aload	14
	ldc_w	String text/xml
	invokevirtual	Method java/lang/String.equals:(Ljava/lang/Object;)Z
	ifne	l6 // getstatic
	aload	14
	ldc_w	String application/xml
	invokevirtual	Method java/lang/String.equals:(Ljava/lang/Object;)Z
	ifne	l6 // getstatic
	aload	14
	ldc_w	String text/
	invokevirtual	Method java/lang/String.startsWith:(Ljava/lang/String;)Z
	ifeq	l7 // aload
	aload	14
	ldc_w	String +xml
	invokevirtual	Method java/lang/String.endsWith:(Ljava/lang/String;)Z
	ifne	l6 // getstatic
l7	aload	14
	ldc_w	String application/
	invokevirtual	Method java/lang/String.startsWith:(Ljava/lang/String;)Z
	ifeq	l5 // new
	aload	14
	ldc_w	String +xml
	invokevirtual	Method java/lang/String.endsWith:(Ljava/lang/String;)Z
	ifeq	l5 // new
l6	getstatic	Field scala/xml/include/sax/EncodingHeuristics$.MODULE$:Lscala/xml/include/sax/EncodingHeuristics$;
	aload	12
	invokevirtual	Method scala/xml/include/sax/EncodingHeuristics$.readEncodingFromStream:(Ljava/io/InputStream;)Ljava/lang/String;
	astore_3
	goto	l5 // new
l4	aload	13
	astore_3
l5	new	class java/io/InputStreamReader
	dup
	aload	12
	aload_3
	invokespecial	Method java/io/InputStreamReader."<init>":(Ljava/io/InputStream;Ljava/lang/String;)V
	astore	17
	ldc_w	int 1024
	newarray char
	astore	18
	iconst_0
	istore	19
l9	aload	17
	aload	18
	iconst_0
	ldc_w	int 1024
	invokevirtual	Method java/io/InputStreamReader.read:([CII)I
	istore	19
	iload	19
	iconst_0
	if_icmple	l8 // iload
	aload_0
	aload	18
	iconst_0
	iload	19
	invokevirtual	Method characters:([CII)V
l8	iload	19
	iconst_m1
	if_icmpne	l9 // aload
	return
	astore	6
	new	class scala/xml/include/UnavailableResourceException
	dup
	new	class scala/collection/mutable/StringBuilder
	dup
	invokespecial	Method scala/collection/mutable/StringBuilder."<init>":()V
	ldc_w	String Unresolvable URL 
	invokevirtual	Method scala/collection/mutable/StringBuilder.append:(Ljava/lang/Object;)Lscala/collection/mutable/StringBuilder;
	aload_1
	invokevirtual	Method scala/collection/mutable/StringBuilder.append:(Ljava/lang/Object;)Lscala/collection/mutable/StringBuilder;
	aload_0
	invokespecial	Method getLocation:()Ljava/lang/String;
	invokevirtual	Method scala/collection/mutable/StringBuilder.append:(Ljava/lang/Object;)Lscala/collection/mutable/StringBuilder;
	invokevirtual	Method scala/collection/mutable/StringBuilder.toString:()Ljava/lang/String;
	invokespecial	Method scala/xml/include/UnavailableResourceException."<init>":(Ljava/lang/String;)V
	astore	7
	aload	7
	aload	6
	invokevirtual	Method scala/xml/include/UnavailableResourceException.setRootCause:(Ljava/lang/Throwable;)V
	new	class org/xml/sax/SAXException
	dup
	new	class scala/collection/mutable/StringBuilder
	dup
	invokespecial	Method scala/collection/mutable/StringBuilder."<init>":()V
	ldc_w	String Unresolvable URL 
	invokevirtual	Method scala/collection/mutable/StringBuilder.append:(Ljava/lang/Object;)Lscala/collection/mutable/StringBuilder;
	aload_1
	invokevirtual	Method scala/collection/mutable/StringBuilder.append:(Ljava/lang/Object;)Lscala/collection/mutable/StringBuilder;
	aload_0
	invokespecial	Method getLocation:()Ljava/lang/String;
	invokevirtual	Method scala/collection/mutable/StringBuilder.append:(Ljava/lang/Object;)Lscala/collection/mutable/StringBuilder;
	invokevirtual	Method scala/collection/mutable/StringBuilder.toString:()Ljava/lang/String;
	aload	7
	invokespecial	Method org/xml/sax/SAXException."<init>":(Ljava/lang/String;Ljava/lang/Exception;)V
	athrow
	astore	9
	new	class org/xml/sax/SAXException
	dup
	new	class scala/collection/mutable/StringBuilder
	dup
	invokespecial	Method scala/collection/mutable/StringBuilder."<init>":()V
	ldc_w	String Document not found: 
	invokevirtual	Method scala/collection/mutable/StringBuilder.append:(Ljava/lang/Object;)Lscala/collection/mutable/StringBuilder;
	aload	5
	invokevirtual	Method java/net/URL.toExternalForm:()Ljava/lang/String;
	invokevirtual	Method scala/collection/mutable/StringBuilder.append:(Ljava/lang/Object;)Lscala/collection/mutable/StringBuilder;
	aload_0
	invokespecial	Method getLocation:()Ljava/lang/String;
	invokevirtual	Method scala/collection/mutable/StringBuilder.append:(Ljava/lang/Object;)Lscala/collection/mutable/StringBuilder;
	invokevirtual	Method scala/collection/mutable/StringBuilder.toString:()Ljava/lang/String;
	aload	9
	invokespecial	Method org/xml/sax/SAXException."<init>":(Ljava/lang/String;Ljava/lang/Exception;)V
	athrow
	astore	10
	new	class org/xml/sax/SAXException
	dup
	new	class scala/collection/mutable/StringBuilder
	dup
	invokespecial	Method scala/collection/mutable/StringBuilder."<init>":()V
	ldc_w	String Unsupported encoding: 
	invokevirtual	Method scala/collection/mutable/StringBuilder.append:(Ljava/lang/Object;)Lscala/collection/mutable/StringBuilder;
	aload_3
	invokevirtual	Method scala/collection/mutable/StringBuilder.append:(Ljava/lang/Object;)Lscala/collection/mutable/StringBuilder;
	aload_0
	invokespecial	Method getLocation:()Ljava/lang/String;
	invokevirtual	Method scala/collection/mutable/StringBuilder.append:(Ljava/lang/Object;)Lscala/collection/mutable/StringBuilder;
	invokevirtual	Method scala/collection/mutable/StringBuilder.toString:()Ljava/lang/String;
	aload	10
	invokespecial	Method org/xml/sax/SAXException."<init>":(Ljava/lang/String;Ljava/lang/Exception;)V
	athrow
  Labels:
   	l1 = 30 // ldc_w
   	l2 = 34 // aconst_null
   	l3 = 115 // aload
   	l7 = 183 // aload
   	l6 = 205 // getstatic
   	l4 = 217 // aload
   	l5 = 220 // new
   	l9 = 242 // aload
   	l8 = 270 // iload
  Exception table:
   from   to  target type
    63   276   402   Class java/io/UnsupportedEncodingException

    63   276   359   Class java/io/IOException

    39    63   277   Class java/net/MalformedURLException

  LocalVariableTable: 
   Start  Length  Slot  Name   Signature
   0      441      0    this       Lscala/xml/include/sax/XIncludeFilter;
   0      441      1    url       Ljava/lang/String;
   0      441      2    encoding1       Ljava/lang/String;
   2      439      3    encoding       Ljava/lang/String;
   39      402      5    source       Ljava/net/URL;
   315      44      7    ex       Lscala/xml/include/UnavailableResourceException;
   51      12      8    base       Ljava/net/URL;
   70      206      11    uc       Ljava/net/URLConnection;
   84      192      12    in       Ljava/io/BufferedInputStream;
   91      185      13    encodingFromHeader       Ljava/lang/String;
   98      178      14    contentType       Ljava/lang/String;
   232      44      17    reader       Ljava/io/InputStreamReader;
   239      37      18    c       [C
   242      34      19    charsRead       I


private boolean atRoot();
  Signature: ()Z
  Code:
   Stack=1, Locals=1, Args_size=1
	aload_0
	getfield	Field atRoot:Z
	ireturn
  Labels:

private void atRoot_$eq(boolean);
  Signature: (Z)V
  Code:
   Stack=2, Locals=2, Args_size=2
	aload_0
	iload_1
	putfield	Field atRoot:Z
	return
  Labels:

private void includeXMLDocument(java.lang.String);
  Signature: (Ljava/lang/String;)V
  Code:
   Stack=7, Locals=14, Args_size=2
	aconst_null
	astore_3
	new	class java/net/URL
	dup
	aload_0
	invokespecial	Method bases:()Ljava/util/Stack;
	invokevirtual	Method java/util/Stack.peek:()Ljava/lang/Object;
	checkcast	class java/net/URL
	aload_1
	invokespecial	Method java/net/URL."<init>":(Ljava/net/URL;Ljava/lang/String;)V
	astore_3
	aload_3
	astore_2
	aconst_null
	astore	8
	invokestatic	Method org/xml/sax/helpers/XMLReaderFactory.createXMLReader:()Lorg/xml/sax/XMLReader;
	astore	8
	goto	l1 // aload
	astore	4
	new	class scala/xml/include/UnavailableResourceException
	dup
	new	class scala/collection/mutable/StringBuilder
	dup
	invokespecial	Method scala/collection/mutable/StringBuilder."<init>":()V
	ldc_w	String Unresolvable URL 
	invokevirtual	Method scala/collection/mutable/StringBuilder.append:(Ljava/lang/Object;)Lscala/collection/mutable/StringBuilder;
	aload_1
	invokevirtual	Method scala/collection/mutable/StringBuilder.append:(Ljava/lang/Object;)Lscala/collection/mutable/StringBuilder;
	aload_0
	invokespecial	Method getLocation:()Ljava/lang/String;
	invokevirtual	Method scala/collection/mutable/StringBuilder.append:(Ljava/lang/Object;)Lscala/collection/mutable/StringBuilder;
	invokevirtual	Method scala/collection/mutable/StringBuilder.toString:()Ljava/lang/String;
	invokespecial	Method scala/xml/include/UnavailableResourceException."<init>":(Ljava/lang/String;)V
	astore	5
	aload	5
	aload	4
	invokevirtual	Method scala/xml/include/UnavailableResourceException.setRootCause:(Ljava/lang/Throwable;)V
	new	class org/xml/sax/SAXException
	dup
	new	class scala/collection/mutable/StringBuilder
	dup
	invokespecial	Method scala/collection/mutable/StringBuilder."<init>":()V
	ldc_w	String Unresolvable URL 
	invokevirtual	Method scala/collection/mutable/StringBuilder.append:(Ljava/lang/Object;)Lscala/collection/mutable/StringBuilder;
	aload_1
	invokevirtual	Method scala/collection/mutable/StringBuilder.append:(Ljava/lang/Object;)Lscala/collection/mutable/StringBuilder;
	aload_0
	invokespecial	Method getLocation:()Ljava/lang/String;
	invokevirtual	Method scala/collection/mutable/StringBuilder.append:(Ljava/lang/Object;)Lscala/collection/mutable/StringBuilder;
	invokevirtual	Method scala/collection/mutable/StringBuilder.toString:()Ljava/lang/String;
	aload	5
	invokespecial	Method org/xml/sax/SAXException."<init>":(Ljava/lang/String;Ljava/lang/Exception;)V
	athrow
	astore	9
	aconst_null
	astore	10
	getstatic	Field scala/xml/package$.MODULE$:Lscala/xml/package$;
	invokevirtual	Method scala/xml/package$.XercesClassName:()Ljava/lang/String;
	invokestatic	Method org/xml/sax/helpers/XMLReaderFactory.createXMLReader:(Ljava/lang/String;)Lorg/xml/sax/XMLReader;
	astore	10
	aload	10
	astore	8
l1	aload	8
	astore	7
	aload	7
	aload_0
	invokeinterface	InterfaceMethod org/xml/sax/XMLReader.setContentHandler:(Lorg/xml/sax/ContentHandler;)V
	aload_0
	invokevirtual	Method getEntityResolver:()Lorg/xml/sax/EntityResolver;
	astore	11
	aload	11
	dup
	astore	12
	ifnull	l2 // aload_0
	aload	12
	aconst_null
	invokevirtual	Method java/lang/Object.equals:(Ljava/lang/Object;)Z
	ifne	l2 // aload_0
	aload	7
	aload	11
	invokeinterface	InterfaceMethod org/xml/sax/XMLReader.setEntityResolver:(Lorg/xml/sax/EntityResolver;)V
l2	aload_0
	invokespecial	Method level:()I
	istore	13
	aload_0
	iconst_0
	invokespecial	Method level_$eq:(I)V
	aload_0
	invokespecial	Method bases:()Ljava/util/Stack;
	aload_2
	invokevirtual	Method java/util/Stack.contains:(Ljava/lang/Object;)Z
	ifeq	l3 // aload_0
	new	class org/xml/sax/SAXException
	dup
	ldc_w	String Circular XInclude Reference
	new	class scala/xml/include/CircularIncludeException
	dup
	new	class scala/collection/mutable/StringBuilder
	dup
	invokespecial	Method scala/collection/mutable/StringBuilder."<init>":()V
	ldc_w	String Circular XInclude Reference to 
	invokevirtual	Method scala/collection/mutable/StringBuilder.append:(Ljava/lang/Object;)Lscala/collection/mutable/StringBuilder;
	aload_2
	invokevirtual	Method scala/collection/mutable/StringBuilder.append:(Ljava/lang/Object;)Lscala/collection/mutable/StringBuilder;
	aload_0
	invokespecial	Method getLocation:()Ljava/lang/String;
	invokevirtual	Method scala/collection/mutable/StringBuilder.append:(Ljava/lang/Object;)Lscala/collection/mutable/StringBuilder;
	invokevirtual	Method scala/collection/mutable/StringBuilder.toString:()Ljava/lang/String;
	invokespecial	Method scala/xml/include/CircularIncludeException."<init>":(Ljava/lang/String;)V
	invokespecial	Method org/xml/sax/SAXException."<init>":(Ljava/lang/String;Ljava/lang/Exception;)V
	athrow
l3	aload_0
	invokespecial	Method bases:()Ljava/util/Stack;
	aload_2
	invokevirtual	Method java/util/Stack.push:(Ljava/lang/Object;)Ljava/lang/Object;
	pop
	aload_0
	iconst_1
	invokespecial	Method atRoot_$eq:(Z)V
	aload	7
	aload_2
	invokevirtual	Method java/net/URL.toExternalForm:()Ljava/lang/String;
	invokeinterface	InterfaceMethod org/xml/sax/XMLReader.parse:(Ljava/lang/String;)V
	aload_0
	iload	13
	invokespecial	Method level_$eq:(I)V
	aload_0
	invokespecial	Method bases:()Ljava/util/Stack;
	invokevirtual	Method java/util/Stack.pop:()Ljava/lang/Object;
	pop
	return
	pop
	getstatic	Field java/lang/System.err:Ljava/io/PrintStream;
	ldc_w	String Could not find an XML parser
	invokevirtual	Method java/io/PrintStream.println:(Ljava/lang/String;)V
	return
	astore	6
	new	class org/xml/sax/SAXException
	dup
	new	class scala/collection/mutable/StringBuilder
	dup
	invokespecial	Method scala/collection/mutable/StringBuilder."<init>":()V
	ldc_w	String Document not found: 
	invokevirtual	Method scala/collection/mutable/StringBuilder.append:(Ljava/lang/Object;)Lscala/collection/mutable/StringBuilder;
	aload_2
	invokevirtual	Method java/net/URL.toExternalForm:()Ljava/lang/String;
	invokevirtual	Method scala/collection/mutable/StringBuilder.append:(Ljava/lang/Object;)Lscala/collection/mutable/StringBuilder;
	aload_0
	invokespecial	Method getLocation:()Ljava/lang/String;
	invokevirtual	Method scala/collection/mutable/StringBuilder.append:(Ljava/lang/Object;)Lscala/collection/mutable/StringBuilder;
	invokevirtual	Method scala/collection/mutable/StringBuilder.toString:()Ljava/lang/String;
	aload	6
	invokespecial	Method org/xml/sax/SAXException."<init>":(Ljava/lang/String;Ljava/lang/Exception;)V
	athrow
  Labels:
   	l1 = 136 // aload
   	l2 = 180 // aload_0
   	l3 = 247 // aload_0
  Exception table:
   from   to  target type
   121   132   287   Class org/xml/sax/SAXException

    26    34   116   Class org/xml/sax/SAXException

    23    34   298   Class java/io/IOException

   116   286   298   Class java/io/IOException

   287   298   298   Class java/io/IOException

     2    21    34   Class java/net/MalformedURLException

  LocalVariableTable: 
   Start  Length  Slot  Name   Signature
   0      340      0    this       Lscala/xml/include/sax/XIncludeFilter;
   0      340      1    url       Ljava/lang/String;
   23      11      2    source       Ljava/net/URL;
   116      224      2    source       Ljava/net/URL;
   2      20      3    exceptionResult2       Ljava/net/URL;
   34      82      3    exceptionResult2       Ljava/net/URL;
   72      44      5    ex       Lscala/xml/include/UnavailableResourceException;
   140      146      7    parser       Lorg/xml/sax/XMLReader;
   26      8      8    exceptionResult3       Lorg/xml/sax/XMLReader;
   116      22      8    exceptionResult3       Lorg/xml/sax/XMLReader;
   287      11      8    exceptionResult3       Lorg/xml/sax/XMLReader;
   121      13      10    exceptionResult4       Lorg/xml/sax/XMLReader;
   287      11      10    exceptionResult4       Lorg/xml/sax/XMLReader;
   154      132      11    resolver       Lorg/xml/sax/EntityResolver;
   186      100      13    previousLevel       I


public scala.xml.include.sax.XIncludeFilter();
  Signature: ()V
  Code:
   Stack=3, Locals=1, Args_size=1
	aload_0
	invokespecial	Method org/xml/sax/helpers/XMLFilterImpl."<init>":()V
	aload_0
	new	class java/util/Stack
	dup
	invokespecial	Method java/util/Stack."<init>":()V
	putfield	Field bases:Ljava/util/Stack;
	aload_0
	new	class java/util/Stack
	dup
	invokespecial	Method java/util/Stack."<init>":()V
	putfield	Field locators:Ljava/util/Stack;
	aload_0
	iconst_0
	putfield	Field level:I
	aload_0
	iconst_0
	putfield	Field depth:I
	aload_0
	iconst_0
	putfield	Field atRoot:Z
	return
  Labels:

}

