Compiled from "XIncluder.scala"
public class scala.xml.include.sax.XIncluder extends java.lang.Object implements org.xml.sax.ContentHandler,org.xml.sax.ext.LexicalHandler,scala.ScalaObject
  SourceFile: "XIncluder.scala"
  ScalaSig: length = 0x6B8
   05 00 FFFFFF81 61 06 08 01 02 FFFFFF84 FFFFFF80 FFFFFF80 FFFFFF80 00 0B 02 09
   58 49 6E 63 6C 75 64 65 72 0A 02 03 04 01 03 73
   61 78 0A 02 05 06 01 07 69 6E 63 6C 75 64 65 0A
   02 07 08 01 03 78 6D 6C 0A 01 09 01 05 73 63 61
   6C 61 03 00 13 05 00 0C 14 1C 22 10 02 0D 12 0D
   01 0E 0A 02 0F 10 01 04 6C 61 6E 67 0A 01 11 01
   04 6A 61 76 61 09 02 13 0E 02 06 4F 62 6A 65 63
   74 10 02 15 1A 0D 01 16 0A 02 03 17 0A 02 07 18
   0A 01 19 01 03 6F 72 67 09 02 1B 16 02 0E 43 6F
   6E 74 65 6E 74 48 61 6E 64 6C 65 72 10 02 1D 20
   0D 01 1E 0A 02 1F 16 01 03 65 78 74 09 02 21 1E
   02 0E 4C 65 78 69 63 61 6C 48 61 6E 64 6C 65 72
   10 02 23 24 0D 01 08 09 02 25 08 02 0B 53 63 61
   6C 61 4F 62 6A 65 63 74 08 08 27 00 FFFFFF82 FFFFFF80 FFFFFFA0 FFFFFF80
   04 28 01 04 6F 75 74 73 10 02 29 2C 0D 01 2A 0A
   02 2B 10 01 02 69 6F 09 02 2D 2A 02 0C 4F 75 74
   70 75 74 53 74 72 65 61 6D 08 08 2F 00 FFFFFF82 FFFFFF80 FFFFFFA0
   FFFFFF80 04 30 01 08 65 6E 63 6F 64 69 6E 67 10 02 31
   34 0E 02 23 32 09 02 33 08 01 06 50 72 65 64 65
   66 09 02 35 36 02 06 53 74 72 69 6E 67 0A 02 33
   08 08 05 38 00 FFFFFF84 00 39 01 06 3C 69 6E 69 74 3E
   14 03 3A 3C 3D 10 02 3B 00 0D 01 02 08 05 27 37
   FFFFFFC0 00 28 08 05 2F 37 FFFFFFC0 00 30 08 07 3F 00 FFFFFFC0 FFFFFF80
   FFFFFF84 00 40 01 03 6F 75 74 15 01 41 10 02 29 42 09
   02 43 2A 02 12 4F 75 74 70 75 74 53 74 72 65 61
   6D 57 72 69 74 65 72 08 07 45 00 FFFFFFC0 FFFFFF80 FFFFFF84 00 46
   01 07 6F 75 74 5F 24 65 71 14 02 47 4A 10 02 23
   48 09 02 49 08 02 04 55 6E 69 74 08 07 4B 44 FFFFFF81
   FFFFFF80 FFFFFFC0 00 41 01 03 78 24 31 08 06 4D 00 FFFFFFA0 FFFFFFA0 04
   41 01 04 6F 75 74 20 08 05 4F 00 FFFFFF84 00 50 01 12
   73 65 74 44 6F 63 75 6D 65 6E 74 4C 6F 63 61 74
   6F 72 14 02 47 51 08 05 52 4E FFFFFFC0 00 53 01 07 6C
   6F 63 61 74 6F 72 10 02 15 54 09 02 55 16 02 07
   4C 6F 63 61 74 6F 72 08 05 57 00 FFFFFF84 00 58 01 0D
   73 74 61 72 74 44 6F 63 75 6D 65 6E 74 14 01 47
   08 05 5A 00 FFFFFF84 00 58 01 0B 65 6E 64 44 6F 63 75
   6D 65 6E 74 08 05 5C 00 FFFFFF84 00 5D 01 12 73 74 61
   72 74 50 72 65 66 69 78 4D 61 70 70 69 6E 67 14
   03 47 5E 60 08 05 5F 5B FFFFFFC0 00 30 01 06 70 72 65
   66 69 78 08 05 61 5B FFFFFFC0 00 30 01 03 75 72 69 08
   05 63 00 FFFFFF84 00 64 01 10 65 6E 64 50 72 65 66 69
   78 4D 61 70 70 69 6E 67 14 02 47 65 08 05 5F 62
   FFFFFFC0 00 30 08 05 67 00 FFFFFF84 00 68 01 0C 73 74 61 72
   74 45 6C 65 6D 65 6E 74 14 05 47 69 6B 6D 6F 08
   05 6A 66 FFFFFFC0 00 30 01 0C 6E 61 6D 65 73 70 61 63
   65 55 52 49 08 05 6C 66 FFFFFFC0 00 30 01 09 6C 6F 63
   61 6C 4E 61 6D 65 08 05 6E 66 FFFFFFC0 00 30 01 0D 71
   75 61 6C 69 66 69 65 64 4E 61 6D 65 08 05 70 66
   FFFFFFC0 00 71 01 04 61 74 74 73 10 02 15 72 09 02 73
   16 02 0A 41 74 74 72 69 62 75 74 65 73 08 05 75
   00 FFFFFF84 00 76 01 0A 65 6E 64 45 6C 65 6D 65 6E 74
   14 04 47 77 78 79 08 05 6A 74 FFFFFFC0 00 30 08 05 6C
   74 FFFFFFC0 00 30 08 05 6E 74 FFFFFFC0 00 30 08 05 7B 00 FFFFFF84
   00 7C 01 0A 63 68 61 72 61 63 74 65 72 73 14 06
   47 7D FFFFFF81 05 FFFFFF81 0A 08 05 7E 7A FFFFFFC0 00 7F 01 02 63
   68 10 05 23 FFFFFF81 00 FFFFFF81 02 09 03 FFFFFF81 01 08 02 05 41
   72 72 61 79 10 03 23 FFFFFF81 03 09 03 FFFFFF81 04 08 02 04
   43 68 61 72 08 07 FFFFFF81 06 7A FFFFFFC0 00 FFFFFF81 07 01 05 73
   74 61 72 74 10 03 23 FFFFFF81 08 09 03 FFFFFF81 09 08 02 03
   49 6E 74 08 07 FFFFFF81 0B 7A FFFFFFC0 00 FFFFFF81 07 01 06 6C 65
   6E 67 74 68 08 07 FFFFFF81 0D 00 FFFFFF84 00 FFFFFF81 0E 01 13 69
   67 6E 6F 72 61 62 6C 65 57 68 69 74 65 73 70 61
   63 65 14 07 47 FFFFFF81 0F FFFFFF81 10 FFFFFF81 11 08 06 7E FFFFFF81 0C
   FFFFFFC0 00 7F 08 08 FFFFFF81 06 FFFFFF81 0C FFFFFFC0 00 FFFFFF81 07 08 08 FFFFFF81
   0B FFFFFF81 0C FFFFFFC0 00 FFFFFF81 07 08 07 FFFFFF81 13 00 FFFFFF84 00 FFFFFF81 14
   01 15 70 72 6F 63 65 73 73 69 6E 67 49 6E 73 74
   72 75 63 74 69 6F 6E 14 05 47 FFFFFF81 15 FFFFFF81 17 08 07
   FFFFFF81 16 FFFFFF81 12 FFFFFFC0 00 30 01 06 74 61 72 67 65 74 08
   07 FFFFFF81 18 FFFFFF81 12 FFFFFFC0 00 30 01 04 64 61 74 61 08 07
   FFFFFF81 1A 00 FFFFFF84 00 FFFFFF81 1B 01 0D 73 6B 69 70 70 65 64
   45 6E 74 69 74 79 14 03 47 FFFFFF81 1C 08 07 FFFFFF81 1D FFFFFF81
   19 FFFFFFC0 00 30 01 04 6E 61 6D 65 08 09 FFFFFF81 1F 00 FFFFFFC0
   FFFFFF80 FFFFFF84 04 FFFFFF81 20 01 05 69 6E 44 54 44 15 02 FFFFFF81 21
   10 03 23 FFFFFF81 22 09 03 FFFFFF81 23 08 02 07 42 6F 6F 6C
   65 61 6E 08 09 FFFFFF81 25 00 FFFFFFC0 FFFFFF80 FFFFFF84 04 FFFFFF81 26 01 09
   69 6E 44 54 44 5F 24 65 71 14 03 47 FFFFFF81 27 08 09
   4B FFFFFF81 24 FFFFFF81 FFFFFF80 FFFFFFC0 00 FFFFFF81 21 08 08 FFFFFF81 29 00 FFFFFFA0 FFFFFFA0
   04 FFFFFF81 21 01 06 69 6E 44 54 44 20 08 09 FFFFFF81 2B 00
   FFFFFFC2 FFFFFF80 FFFFFF84 04 FFFFFF81 2C 01 08 65 6E 74 69 74 69 65 73
   15 02 FFFFFF81 2D 10 05 FFFFFF81 2E FFFFFF81 31 30 0D 02 FFFFFF81 2F 0A
   03 FFFFFF81 30 10 01 04 75 74 69 6C 09 04 FFFFFF81 32 FFFFFF81 2F
   02 05 53 74 61 63 6B 08 08 FFFFFF81 34 00 FFFFFFA0 FFFFFF80 04 FFFFFF81
   2D 01 09 65 6E 74 69 74 69 65 73 20 08 07 FFFFFF81 36
   00 FFFFFF84 00 FFFFFF81 37 01 08 73 74 61 72 74 44 54 44 14
   07 47 FFFFFF81 38 FFFFFF81 39 FFFFFF81 3B 08 07 FFFFFF81 1D FFFFFF81 35 FFFFFFC0 00
   30 08 07 FFFFFF81 3A FFFFFF81 35 FFFFFFC0 00 30 01 08 70 75 62 6C
   69 63 49 44 08 07 FFFFFF81 3C FFFFFF81 35 FFFFFFC0 00 30 01 08 73
   79 73 74 65 6D 49 44 08 06 FFFFFF81 3E 00 FFFFFF84 00 58 01
   06 65 6E 64 44 54 44 08 07 FFFFFF81 40 00 FFFFFF84 00 FFFFFF81 41
   01 0B 73 74 61 72 74 45 6E 74 69 74 79 14 03 47
   FFFFFF81 42 08 07 FFFFFF81 1D FFFFFF81 3F FFFFFFC0 00 30 08 07 FFFFFF81 44 00
   FFFFFF84 00 FFFFFF81 45 01 09 65 6E 64 45 6E 74 69 74 79 14
   03 47 FFFFFF81 46 08 07 FFFFFF81 1D FFFFFF81 43 FFFFFFC0 00 30 08 06 FFFFFF81
   48 00 FFFFFF84 00 58 01 0A 73 74 61 72 74 43 44 41 54
   41 08 06 FFFFFF81 4A 00 FFFFFF84 00 58 01 08 65 6E 64 43 44
   41 54 41 08 09 FFFFFF81 4C 00 FFFFFFC0 FFFFFF80 FFFFFF84 04 FFFFFF81 4D 01 06
   66 69 6C 74 65 72 15 02 FFFFFF81 4E 10 03 3B FFFFFF81 4F 09
   03 FFFFFF81 50 02 02 0E 58 49 6E 63 6C 75 64 65 46 69
   6C 74 65 72 08 09 FFFFFF81 52 00 FFFFFFC0 FFFFFF80 FFFFFF84 04 FFFFFF81 53 01
   0A 66 69 6C 74 65 72 5F 24 65 71 14 03 47 FFFFFF81 54
   08 09 4B FFFFFF81 51 FFFFFF81 FFFFFF80 FFFFFFC0 00 FFFFFF81 4E 08 08 FFFFFF81 56 00
   FFFFFFA0 FFFFFFA0 04 FFFFFF81 4E 01 07 66 69 6C 74 65 72 20 08 07
   FFFFFF81 58 00 FFFFFF84 00 FFFFFF81 59 01 09 73 65 74 46 69 6C 74
   65 72 14 03 47 FFFFFF81 5A 08 08 FFFFFF81 4C FFFFFF81 57 FFFFFFC0 00 FFFFFF81
   4E 08 07 FFFFFF81 5C 00 FFFFFF84 00 FFFFFF81 5D 01 07 63 6F 6D 6D
   65 6E 74 14 07 47 FFFFFF81 5E FFFFFF81 5F FFFFFF81 60 08 06 7E FFFFFF81
   5B FFFFFFC0 00 7F 08 08 FFFFFF81 06 FFFFFF81 5B FFFFFFC0 00 FFFFFF81 07 08 08
   FFFFFF81 0B FFFFFF81 5B FFFFFFC0 00 FFFFFF81 07 
  InnerClass: 
   public final $anonfun$escape$2=class scala/xml/Utility$$anonfun$escape$2 of class scala/xml/Utility
   public final $anonfun$escape$1=class scala/xml/Utility$$anonfun$escape$1 of class scala/xml/Utility
  minor version: 0
  major version: 49
  Constant pool:
Asciz	SourceFile;
Asciz	XIncluder.scala;
Asciz	filter;
Asciz	Lscala/xml/include/sax/XIncludeFilter;;
Asciz	entities;
Asciz	Ljava/util/Stack;;
Asciz	Ljava/util/Stack<Ljava/lang/String;>;;
Asciz	Signature;
Asciz	inDTD;
Asciz	Z;
Asciz	out;
Asciz	Ljava/io/OutputStreamWriter;;
Asciz	encoding;
Asciz	Ljava/lang/String;;
Asciz	<init>;
Asciz	(Ljava/io/OutputStream;Ljava/lang/String;)V;
Asciz	Code;
Asciz	LineNumberTable;
Asciz	scala/xml/include/sax/XIncluder;
class	scala/xml/include/sax/XIncluder
NameAndType	encoding:Ljava/lang/String;
Field	scala/xml/include/sax/XIncluder.encoding:Ljava/lang/String;
Asciz	java/lang/Object;
class	java/lang/Object
Asciz	()V;
NameAndType	"<init>":()V
Method	java/lang/Object."<init>":()V
Asciz	java/io/OutputStreamWriter;
class	java/io/OutputStreamWriter
NameAndType	"<init>":(Ljava/io/OutputStream;Ljava/lang/String;)V
Method	java/io/OutputStreamWriter."<init>":(Ljava/io/OutputStream;Ljava/lang/String;)V
NameAndType	out:Ljava/io/OutputStreamWriter;
Field	scala/xml/include/sax/XIncluder.out:Ljava/io/OutputStreamWriter;
NameAndType	inDTD:Z
Field	scala/xml/include/sax/XIncluder.inDTD:Z
Asciz	java/util/Stack;
class	java/util/Stack
Method	java/util/Stack."<init>":()V
NameAndType	entities:Ljava/util/Stack;
Field	scala/xml/include/sax/XIncluder.entities:Ljava/util/Stack;
NameAndType	filter:Lscala/xml/include/sax/XIncludeFilter;
Field	scala/xml/include/sax/XIncluder.filter:Lscala/xml/include/sax/XIncludeFilter;
Asciz	this;
Asciz	Lscala/xml/include/sax/XIncluder;;
Asciz	outs;
Asciz	Ljava/io/OutputStream;;
Asciz	LocalVariableTable;
Asciz	comment;
Asciz	([CII)V;
Asciz	()Z;
NameAndType	inDTD:()Z
Method	scala/xml/include/sax/XIncluder.inDTD:()Z
Asciz	()Lscala/xml/include/sax/XIncludeFilter;;
NameAndType	filter:()Lscala/xml/include/sax/XIncludeFilter;
Method	scala/xml/include/sax/XIncluder.filter:()Lscala/xml/include/sax/XIncludeFilter;
Asciz	scala/xml/include/sax/XIncludeFilter;
class	scala/xml/include/sax/XIncludeFilter
Asciz	insideIncludeElement;
NameAndType	insideIncludeElement:()Z
Method	scala/xml/include/sax/XIncludeFilter.insideIncludeElement:()Z
Asciz	()Ljava/io/OutputStreamWriter;;
NameAndType	out:()Ljava/io/OutputStreamWriter;
Method	scala/xml/include/sax/XIncluder.out:()Ljava/io/OutputStreamWriter;
Asciz	<!--;
String	<!--
Asciz	write;
Asciz	(Ljava/lang/String;)V;
NameAndType	write:(Ljava/lang/String;)V
Method	java/io/OutputStreamWriter.write:(Ljava/lang/String;)V
NameAndType	write:([CII)V
Method	java/io/OutputStreamWriter.write:([CII)V
Asciz	-->;
String	-->
Asciz	org/xml/sax/SAXException;
class	org/xml/sax/SAXException
Asciz	Write failed;
String	Write failed
Asciz	(Ljava/lang/String;Ljava/lang/Exception;)V;
NameAndType	"<init>":(Ljava/lang/String;Ljava/lang/Exception;)V
Method	org/xml/sax/SAXException."<init>":(Ljava/lang/String;Ljava/lang/Exception;)V
Asciz	java/io/IOException;
class	java/io/IOException
Asciz	ch;
Asciz	[C;
Asciz	start;
Asciz	I;
Asciz	length;
Asciz	setFilter;
Asciz	(Lscala/xml/include/sax/XIncludeFilter;)V;
Asciz	filter_$eq;
NameAndType	filter_$eq:(Lscala/xml/include/sax/XIncludeFilter;)V
Method	scala/xml/include/sax/XIncluder.filter_$eq:(Lscala/xml/include/sax/XIncludeFilter;)V
Asciz	endCDATA;
Asciz	startCDATA;
Asciz	endEntity;
Asciz	()Ljava/util/Stack;;
NameAndType	entities:()Ljava/util/Stack;
Method	scala/xml/include/sax/XIncluder.entities:()Ljava/util/Stack;
Asciz	pop;
Asciz	()Ljava/lang/Object;;
NameAndType	pop:()Ljava/lang/Object;
Method	java/util/Stack.pop:()Ljava/lang/Object;
Asciz	name;
Asciz	startEntity;
Asciz	push;
Asciz	(Ljava/lang/Object;)Ljava/lang/Object;;
NameAndType	push:(Ljava/lang/Object;)Ljava/lang/Object;
Method	java/util/Stack.push:(Ljava/lang/Object;)Ljava/lang/Object;
Asciz	endDTD;
Asciz	startDTD;
Asciz	(Ljava/lang/String;Ljava/lang/String;Ljava/lang/String;)V;
Asciz	inDTD_$eq;
Asciz	(Z)V;
NameAndType	inDTD_$eq:(Z)V
Method	scala/xml/include/sax/XIncluder.inDTD_$eq:(Z)V
Asciz	size;
Asciz	()I;
NameAndType	size:()I
Method	java/util/Stack.size:()I
Asciz	;
String	
Asciz	equals;
Asciz	(Ljava/lang/Object;)Z;
NameAndType	equals:(Ljava/lang/Object;)Z
Method	java/lang/Object.equals:(Ljava/lang/Object;)Z
Asciz	scala/collection/mutable/StringBuilder;
class	scala/collection/mutable/StringBuilder
Method	scala/collection/mutable/StringBuilder."<init>":()V
Asciz	 SYSTEM \";
String	 SYSTEM \"
Asciz	append;
Asciz	(Ljava/lang/Object;)Lscala/collection/mutable/StringBuilder;;
NameAndType	append:(Ljava/lang/Object;)Lscala/collection/mutable/StringBuilder;
Method	scala/collection/mutable/StringBuilder.append:(Ljava/lang/Object;)Lscala/collection/mutable/StringBuilder;
int	34;
Asciz	scala/runtime/BoxesRunTime;
class	scala/runtime/BoxesRunTime
Asciz	boxToCharacter;
Asciz	(C)Ljava/lang/Character;;
NameAndType	boxToCharacter:(C)Ljava/lang/Character;
Method	scala/runtime/BoxesRunTime.boxToCharacter:(C)Ljava/lang/Character;
Asciz	toString;
Asciz	()Ljava/lang/String;;
NameAndType	toString:()Ljava/lang/String;
Method	scala/collection/mutable/StringBuilder.toString:()Ljava/lang/String;
Asciz	 PUBLIC \";
String	 PUBLIC \"
Asciz	\" \";
String	\" \"
Asciz	<!DOCTYPE ;
String	<!DOCTYPE 
Asciz	>\r\n;
String	>\r\n
Asciz	Error while writing DOCTYPE;
String	Error while writing DOCTYPE
Asciz	publicID;
Asciz	systemID;
Asciz	id;
Asciz	()Ljava/util/Stack<Ljava/lang/String;>;;
Asciz	skippedEntity;
Asciz	&;
String	&
Asciz	;;
String	;
Asciz	processingInstruction;
Asciz	(Ljava/lang/String;Ljava/lang/String;)V;
Asciz	<?;
String	<?
Asciz	 ;
String	 
Asciz	?>;
String	?>
Asciz	target;
Asciz	data;
Asciz	ignorableWhitespace;
Asciz	characters;
NameAndType	characters:([CII)V
Method	scala/xml/include/sax/XIncluder.characters:([CII)V
int	38;
Asciz	&amp;;
String	&amp;
int	60;
Asciz	&lt;;
String	&lt;
int	62;
Asciz	&gt;;
String	&gt;
Asciz	(I)V;
NameAndType	write:(I)V
Method	java/io/OutputStreamWriter.write:(I)V
Asciz	i;
Asciz	c;
Asciz	C;
Asciz	endElement;
Asciz	</;
String	</
Asciz	>;
String	>
Asciz	namespaceURI;
Asciz	localName;
Asciz	qualifiedName;
Asciz	startElement;
Asciz	(Ljava/lang/String;Ljava/lang/String;Ljava/lang/String;Lorg/xml/sax/Attributes;)V;
Asciz	<;
String	<
Asciz	org/xml/sax/Attributes;
class	org/xml/sax/Attributes
Asciz	getLength;
NameAndType	getLength:()I
InterfaceMethod	org/xml/sax/Attributes.getLength:()I
Asciz	getQName;
Asciz	(I)Ljava/lang/String;;
NameAndType	getQName:(I)Ljava/lang/String;
InterfaceMethod	org/xml/sax/Attributes.getQName:(I)Ljava/lang/String;
Asciz	=';
String	='
Asciz	getValue;
NameAndType	getValue:(I)Ljava/lang/String;
InterfaceMethod	org/xml/sax/Attributes.getValue:(I)Ljava/lang/String;
Asciz	scala/xml/Utility$$anonfun$escape$1;
class	scala/xml/Utility$$anonfun$escape$1
NameAndType	"<init>":(Ljava/lang/String;)V
Method	scala/xml/Utility$$anonfun$escape$1."<init>":(Ljava/lang/String;)V
Method	scala/collection/mutable/StringBuilder."<init>":()V
Asciz	scala/collection/immutable/StringOps;
class	scala/collection/immutable/StringOps
Method	scala/collection/immutable/StringOps."<init>":(Ljava/lang/String;)V
Asciz	scala/xml/Utility$$anonfun$escape$2;
class	scala/xml/Utility$$anonfun$escape$2
Method	scala/xml/Utility$$anonfun$escape$2."<init>":()V
Asciz	scala/collection/IndexedSeqLike$class;
class	scala/collection/IndexedSeqLike$class
Asciz	foldLeft;
Asciz	(Lscala/collection/IndexedSeqLike;Ljava/lang/Object;Lscala/Function2;)Ljava/lang/Object;;
NameAndType	foldLeft:(Lscala/collection/IndexedSeqLike;Ljava/lang/Object;Lscala/Function2;)Ljava/lang/Object;
Method	scala/collection/IndexedSeqLike$class.foldLeft:(Lscala/collection/IndexedSeqLike;Ljava/lang/Object;Lscala/Function2;)Ljava/lang/Object;
Method	scala/collection/mutable/StringBuilder.toString:()Ljava/lang/String;
Asciz	';
String	'
Asciz	atts;
Asciz	Lorg/xml/sax/Attributes;;
Asciz	value;
Asciz	sb00;
Asciz	Lscala/collection/mutable/StringBuilder;;
Asciz	endPrefixMapping;
Asciz	prefix;
Asciz	startPrefixMapping;
Asciz	uri;
Asciz	endDocument;
Asciz	flush;
NameAndType	flush:()V
Method	java/io/OutputStreamWriter.flush:()V
Asciz	Flush failed;
String	Flush failed
Asciz	startDocument;
Asciz	<?xml version='1.0' encoding=';
String	<?xml version='1.0' encoding='
Asciz	'?>\r\n;
String	'?>\r\n
Asciz	setDocumentLocator;
Asciz	(Lorg/xml/sax/Locator;)V;
Asciz	locator;
Asciz	Lorg/xml/sax/Locator;;
Asciz	out_$eq;
Asciz	(Ljava/io/OutputStreamWriter;)V;
Asciz	ScalaSig;
Asciz	InnerClasses;
Asciz	scala/xml/Utility;
class	scala/xml/Utility
Asciz	$anonfun$escape$2;
Asciz	$anonfun$escape$1;
Asciz	org/xml/sax/ContentHandler;
class	org/xml/sax/ContentHandler
Asciz	org/xml/sax/ext/LexicalHandler;
class	org/xml/sax/ext/LexicalHandler
Asciz	scala/ScalaObject;
class	scala/ScalaObject

{
private scala.xml.include.sax.XIncludeFilter filter;
  Signature: Lscala/xml/include/sax/XIncludeFilter;

private final java.util.Stack entities;
  Signature: Ljava/util/Stack;
  Signature: length = 0x2
   00 07 

private boolean inDTD;
  Signature: Z

private java.io.OutputStreamWriter out;
  Signature: Ljava/io/OutputStreamWriter;

private final java.lang.String encoding;
  Signature: Ljava/lang/String;

public scala.xml.include.sax.XIncluder(java.io.OutputStream, java.lang.String);
  Signature: (Ljava/io/OutputStream;Ljava/lang/String;)V
  Code:
   Stack=5, Locals=3, Args_size=3
	aload_0
	aload_2
	putfield	Field encoding:Ljava/lang/String;
	aload_0
	invokespecial	Method java/lang/Object."<init>":()V
	aload_0
	new	class java/io/OutputStreamWriter
	dup
	aload_1
	aload_2
	invokespecial	Method java/io/OutputStreamWriter."<init>":(Ljava/io/OutputStream;Ljava/lang/String;)V
	putfield	Field out:Ljava/io/OutputStreamWriter;
	aload_0
	iconst_0
	putfield	Field inDTD:Z
	aload_0
	new	class java/util/Stack
	dup
	invokespecial	Method java/util/Stack."<init>":()V
	putfield	Field entities:Ljava/util/Stack;
	aload_0
	aconst_null
	putfield	Field filter:Lscala/xml/include/sax/XIncludeFilter;
	return
  Labels:
  LocalVariableTable: 
   Start  Length  Slot  Name   Signature
   0      44      0    this       Lscala/xml/include/sax/XIncluder;
   0      44      1    outs       Ljava/io/OutputStream;
   0      44      2    encoding       Ljava/lang/String;


public void comment(char[], int, int);
  Signature: ([CII)V
  Code:
   Stack=4, Locals=5, Args_size=4
	aload_0
	invokespecial	Method inDTD:()Z
	ifne	l1 // return
	aload_0
	invokespecial	Method filter:()Lscala/xml/include/sax/XIncludeFilter;
	invokevirtual	Method scala/xml/include/sax/XIncludeFilter.insideIncludeElement:()Z
	ifne	l1 // return
	aload_0
	invokevirtual	Method out:()Ljava/io/OutputStreamWriter;
	ldc	String <!--
	invokevirtual	Method java/io/OutputStreamWriter.write:(Ljava/lang/String;)V
	aload_0
	invokevirtual	Method out:()Ljava/io/OutputStreamWriter;
	aload_1
	iload_2
	iload_3
	invokevirtual	Method java/io/OutputStreamWriter.write:([CII)V
	aload_0
	invokevirtual	Method out:()Ljava/io/OutputStreamWriter;
	ldc	String -->
	invokevirtual	Method java/io/OutputStreamWriter.write:(Ljava/lang/String;)V
l1	return
	astore	4
	new	class org/xml/sax/SAXException
	dup
	ldc	String Write failed
	aload	4
	invokespecial	Method org/xml/sax/SAXException."<init>":(Ljava/lang/String;Ljava/lang/Exception;)V
	athrow
  Labels:
   	l1 = 45 // return
  Exception table:
   from   to  target type
    17    45    46   Class java/io/IOException

  LocalVariableTable: 
   Start  Length  Slot  Name   Signature
   0      60      0    this       Lscala/xml/include/sax/XIncluder;
   0      60      1    ch       [C
   0      60      2    start       I
   0      60      3    length       I


public void setFilter(scala.xml.include.sax.XIncludeFilter);
  Signature: (Lscala/xml/include/sax/XIncludeFilter;)V
  Code:
   Stack=2, Locals=2, Args_size=2
	aload_0
	aload_1
	invokespecial	Method filter_$eq:(Lscala/xml/include/sax/XIncludeFilter;)V
	return
  Labels:
  LocalVariableTable: 
   Start  Length  Slot  Name   Signature
   0      6      0    this       Lscala/xml/include/sax/XIncluder;
   0      6      1    filter       Lscala/xml/include/sax/XIncludeFilter;


private void filter_$eq(scala.xml.include.sax.XIncludeFilter);
  Signature: (Lscala/xml/include/sax/XIncludeFilter;)V
  Code:
   Stack=2, Locals=2, Args_size=2
	aload_0
	aload_1
	putfield	Field filter:Lscala/xml/include/sax/XIncludeFilter;
	return
  Labels:

private scala.xml.include.sax.XIncludeFilter filter();
  Signature: ()Lscala/xml/include/sax/XIncludeFilter;
  Code:
   Stack=1, Locals=1, Args_size=1
	aload_0
	getfield	Field filter:Lscala/xml/include/sax/XIncludeFilter;
	areturn
  Labels:

public void endCDATA();
  Signature: ()V
  Code:
   Stack=0, Locals=1, Args_size=1
	return
  Labels:

public void startCDATA();
  Signature: ()V
  Code:
   Stack=0, Locals=1, Args_size=1
	return
  Labels:

public void endEntity(java.lang.String);
  Signature: (Ljava/lang/String;)V
  Code:
   Stack=1, Locals=2, Args_size=2
	aload_0
	invokespecial	Method entities:()Ljava/util/Stack;
	invokevirtual	Method java/util/Stack.pop:()Ljava/lang/Object;
	pop
	return
  Labels:
  LocalVariableTable: 
   Start  Length  Slot  Name   Signature
   0      9      0    this       Lscala/xml/include/sax/XIncluder;
   0      9      1    name       Ljava/lang/String;


public void startEntity(java.lang.String);
  Signature: (Ljava/lang/String;)V
  Code:
   Stack=2, Locals=2, Args_size=2
	aload_0
	invokespecial	Method entities:()Ljava/util/Stack;
	aload_1
	invokevirtual	Method java/util/Stack.push:(Ljava/lang/Object;)Ljava/lang/Object;
	pop
	return
  Labels:
  LocalVariableTable: 
   Start  Length  Slot  Name   Signature
   0      10      0    this       Lscala/xml/include/sax/XIncluder;
   0      10      1    name       Ljava/lang/String;


public void endDTD();
  Signature: ()V
  Code:
   Stack=0, Locals=1, Args_size=1
	return
  Labels:

public void startDTD(java.lang.String, java.lang.String, java.lang.String);
  Signature: (Ljava/lang/String;Ljava/lang/String;Ljava/lang/String;)V
  Code:
   Stack=4, Locals=8, Args_size=4
	aload_0
	iconst_1
	invokespecial	Method inDTD_$eq:(Z)V
	aload_0
	invokespecial	Method entities:()Ljava/util/Stack;
	invokevirtual	Method java/util/Stack.size:()I
	iconst_0
	if_icmpne	l1 // return
	ldc	String 
	astore	6
	aload_2
	dup
	pop
	ifnull	l2 // aload_3
	aload_2
	aconst_null
	invokevirtual	Method java/lang/Object.equals:(Ljava/lang/Object;)Z
	ifeq	l3 // new
l2	aload_3
	dup
	pop
	ifnull	l4 // aload_0
	aload_3
	aconst_null
	invokevirtual	Method java/lang/Object.equals:(Ljava/lang/Object;)Z
	ifne	l4 // aload_0
	new	class scala/collection/mutable/StringBuilder
	dup
	invokespecial	Method scala/collection/mutable/StringBuilder."<init>":()V
	ldc	String  SYSTEM \"
	invokevirtual	Method scala/collection/mutable/StringBuilder.append:(Ljava/lang/Object;)Lscala/collection/mutable/StringBuilder;
	aload_3
	invokevirtual	Method scala/collection/mutable/StringBuilder.append:(Ljava/lang/Object;)Lscala/collection/mutable/StringBuilder;
	ldc	int 34
	istore	4
	iload	4
	invokestatic	Method scala/runtime/BoxesRunTime.boxToCharacter:(C)Ljava/lang/Character;
	invokevirtual	Method scala/collection/mutable/StringBuilder.append:(Ljava/lang/Object;)Lscala/collection/mutable/StringBuilder;
	invokevirtual	Method scala/collection/mutable/StringBuilder.toString:()Ljava/lang/String;
	astore	6
	goto	l4 // aload_0
l3	new	class scala/collection/mutable/StringBuilder
	dup
	invokespecial	Method scala/collection/mutable/StringBuilder."<init>":()V
	ldc	String  PUBLIC \"
	invokevirtual	Method scala/collection/mutable/StringBuilder.append:(Ljava/lang/Object;)Lscala/collection/mutable/StringBuilder;
	aload_2
	invokevirtual	Method scala/collection/mutable/StringBuilder.append:(Ljava/lang/Object;)Lscala/collection/mutable/StringBuilder;
	ldc	String \" \"
	invokevirtual	Method scala/collection/mutable/StringBuilder.append:(Ljava/lang/Object;)Lscala/collection/mutable/StringBuilder;
	aload_3
	invokevirtual	Method scala/collection/mutable/StringBuilder.append:(Ljava/lang/Object;)Lscala/collection/mutable/StringBuilder;
	ldc	int 34
	istore	5
	iload	5
	invokestatic	Method scala/runtime/BoxesRunTime.boxToCharacter:(C)Ljava/lang/Character;
	invokevirtual	Method scala/collection/mutable/StringBuilder.append:(Ljava/lang/Object;)Lscala/collection/mutable/StringBuilder;
	invokevirtual	Method scala/collection/mutable/StringBuilder.toString:()Ljava/lang/String;
	astore	6
l4	aload_0
	invokevirtual	Method out:()Ljava/io/OutputStreamWriter;
	new	class scala/collection/mutable/StringBuilder
	dup
	invokespecial	Method scala/collection/mutable/StringBuilder."<init>":()V
	ldc	String <!DOCTYPE 
	invokevirtual	Method scala/collection/mutable/StringBuilder.append:(Ljava/lang/Object;)Lscala/collection/mutable/StringBuilder;
	aload_1
	invokevirtual	Method scala/collection/mutable/StringBuilder.append:(Ljava/lang/Object;)Lscala/collection/mutable/StringBuilder;
	aload	6
	invokevirtual	Method scala/collection/mutable/StringBuilder.append:(Ljava/lang/Object;)Lscala/collection/mutable/StringBuilder;
	ldc	String >\r\n
	invokevirtual	Method scala/collection/mutable/StringBuilder.append:(Ljava/lang/Object;)Lscala/collection/mutable/StringBuilder;
	invokevirtual	Method scala/collection/mutable/StringBuilder.toString:()Ljava/lang/String;
	invokevirtual	Method java/io/OutputStreamWriter.write:(Ljava/lang/String;)V
l1	return
	astore	7
	new	class org/xml/sax/SAXException
	dup
	ldc	String Error while writing DOCTYPE
	aload	7
	invokespecial	Method org/xml/sax/SAXException."<init>":(Ljava/lang/String;Ljava/lang/Exception;)V
	athrow
  Labels:
   	l2 = 34 // aload_3
   	l3 = 84 // new
   	l4 = 126 // aload_0
   	l1 = 162 // return
  Exception table:
   from   to  target type
   126   162   163   Class java/io/IOException

  LocalVariableTable: 
   Start  Length  Slot  Name   Signature
   0      177      0    this       Lscala/xml/include/sax/XIncluder;
   0      177      1    name       Ljava/lang/String;
   0      177      2    publicID       Ljava/lang/String;
   0      177      3    systemID       Ljava/lang/String;
   20      142      6    id       Ljava/lang/String;
   163      14      6    id       Ljava/lang/String;


private java.util.Stack entities();
  Signature: ()Ljava/util/Stack;
  Code:
   Stack=1, Locals=1, Args_size=1
	aload_0
	getfield	Field entities:Ljava/util/Stack;
	areturn
  Labels:
  Signature: length = 0x2
   00 FFFFFF9F 

private void inDTD_$eq(boolean);
  Signature: (Z)V
  Code:
   Stack=2, Locals=2, Args_size=2
	aload_0
	iload_1
	putfield	Field inDTD:Z
	return
  Labels:

private boolean inDTD();
  Signature: ()Z
  Code:
   Stack=1, Locals=1, Args_size=1
	aload_0
	getfield	Field inDTD:Z
	ireturn
  Labels:

public void skippedEntity(java.lang.String);
  Signature: (Ljava/lang/String;)V
  Code:
   Stack=4, Locals=3, Args_size=2
	aload_0
	invokevirtual	Method out:()Ljava/io/OutputStreamWriter;
	new	class scala/collection/mutable/StringBuilder
	dup
	invokespecial	Method scala/collection/mutable/StringBuilder."<init>":()V
	ldc	String &
	invokevirtual	Method scala/collection/mutable/StringBuilder.append:(Ljava/lang/Object;)Lscala/collection/mutable/StringBuilder;
	aload_1
	invokevirtual	Method scala/collection/mutable/StringBuilder.append:(Ljava/lang/Object;)Lscala/collection/mutable/StringBuilder;
	ldc	String ;
	invokevirtual	Method scala/collection/mutable/StringBuilder.append:(Ljava/lang/Object;)Lscala/collection/mutable/StringBuilder;
	invokevirtual	Method scala/collection/mutable/StringBuilder.toString:()Ljava/lang/String;
	invokevirtual	Method java/io/OutputStreamWriter.write:(Ljava/lang/String;)V
	return
	astore_2
	new	class org/xml/sax/SAXException
	dup
	ldc	String Write failed
	aload_2
	invokespecial	Method org/xml/sax/SAXException."<init>":(Ljava/lang/String;Ljava/lang/Exception;)V
	athrow
  Labels:
  Exception table:
   from   to  target type
     0    31    32   Class java/io/IOException

  LocalVariableTable: 
   Start  Length  Slot  Name   Signature
   0      44      0    this       Lscala/xml/include/sax/XIncluder;
   0      44      1    name       Ljava/lang/String;


public void processingInstruction(java.lang.String, java.lang.String);
  Signature: (Ljava/lang/String;Ljava/lang/String;)V
  Code:
   Stack=4, Locals=4, Args_size=3
	aload_0
	invokevirtual	Method out:()Ljava/io/OutputStreamWriter;
	new	class scala/collection/mutable/StringBuilder
	dup
	invokespecial	Method scala/collection/mutable/StringBuilder."<init>":()V
	ldc	String <?
	invokevirtual	Method scala/collection/mutable/StringBuilder.append:(Ljava/lang/Object;)Lscala/collection/mutable/StringBuilder;
	aload_1
	invokevirtual	Method scala/collection/mutable/StringBuilder.append:(Ljava/lang/Object;)Lscala/collection/mutable/StringBuilder;
	ldc	String  
	invokevirtual	Method scala/collection/mutable/StringBuilder.append:(Ljava/lang/Object;)Lscala/collection/mutable/StringBuilder;
	aload_2
	invokevirtual	Method scala/collection/mutable/StringBuilder.append:(Ljava/lang/Object;)Lscala/collection/mutable/StringBuilder;
	ldc	String ?>
	invokevirtual	Method scala/collection/mutable/StringBuilder.append:(Ljava/lang/Object;)Lscala/collection/mutable/StringBuilder;
	invokevirtual	Method scala/collection/mutable/StringBuilder.toString:()Ljava/lang/String;
	invokevirtual	Method java/io/OutputStreamWriter.write:(Ljava/lang/String;)V
	return
	astore_3
	new	class org/xml/sax/SAXException
	dup
	ldc	String Write failed
	aload_3
	invokespecial	Method org/xml/sax/SAXException."<init>":(Ljava/lang/String;Ljava/lang/Exception;)V
	athrow
  Labels:
  Exception table:
   from   to  target type
     0    40    41   Class java/io/IOException

  LocalVariableTable: 
   Start  Length  Slot  Name   Signature
   0      53      0    this       Lscala/xml/include/sax/XIncluder;
   0      53      1    target       Ljava/lang/String;
   0      53      2    data       Ljava/lang/String;


public void ignorableWhitespace(char[], int, int);
  Signature: ([CII)V
  Code:
   Stack=4, Locals=4, Args_size=4
	aload_0
	aload_1
	iload_2
	iload_3
	invokevirtual	Method characters:([CII)V
	return
  Labels:
  LocalVariableTable: 
   Start  Length  Slot  Name   Signature
   0      8      0    this       Lscala/xml/include/sax/XIncluder;
   0      8      1    ch       [C
   0      8      2    start       I
   0      8      3    length       I


public void characters(char[], int, int);
  Signature: ([CII)V
  Code:
   Stack=4, Locals=7, Args_size=4
	iconst_0
	istore	5
l6	iload	5
	iload_3
	if_icmpge	l1 // return
	aload_1
	iload_2
	iload	5
	iadd
	caload
	istore	6
	iload	6
	ldc	int 38
	if_icmpne	l2 // iload
	aload_0
	invokevirtual	Method out:()Ljava/io/OutputStreamWriter;
	ldc	String &amp;
	invokevirtual	Method java/io/OutputStreamWriter.write:(Ljava/lang/String;)V
	goto	l3 // iload
l2	iload	6
	ldc	int 60
	if_icmpne	l4 // iload
	aload_0
	invokevirtual	Method out:()Ljava/io/OutputStreamWriter;
	ldc	String &lt;
	invokevirtual	Method java/io/OutputStreamWriter.write:(Ljava/lang/String;)V
	goto	l3 // iload
l4	iload	6
	ldc	int 62
	if_icmpne	l5 // aload_0
	aload_0
	invokevirtual	Method out:()Ljava/io/OutputStreamWriter;
	ldc	String &gt;
	invokevirtual	Method java/io/OutputStreamWriter.write:(Ljava/lang/String;)V
	goto	l3 // iload
l5	aload_0
	invokevirtual	Method out:()Ljava/io/OutputStreamWriter;
	iload	6
	invokevirtual	Method java/io/OutputStreamWriter.write:(I)V
l3	iload	5
	iconst_1
	iadd
	istore	5
	goto	l6 // iload
l1	return
	astore	4
	new	class org/xml/sax/SAXException
	dup
	ldc	String Write failed
	aload	4
	invokespecial	Method org/xml/sax/SAXException."<init>":(Ljava/lang/String;Ljava/lang/Exception;)V
	athrow
  Labels:
   	l6 = 3 // iload
   	l2 = 36 // iload
   	l4 = 55 // iload
   	l5 = 74 // aload_0
   	l3 = 83 // iload
   	l1 = 92 // return
  Exception table:
   from   to  target type
     0    92    93   Class java/io/IOException

  LocalVariableTable: 
   Start  Length  Slot  Name   Signature
   0      107      0    this       Lscala/xml/include/sax/XIncluder;
   0      107      1    ch       [C
   0      107      2    start       I
   0      107      3    length       I
   3      89      5    i       I
   17      72      6    c       C


public void endElement(java.lang.String, java.lang.String, java.lang.String);
  Signature: (Ljava/lang/String;Ljava/lang/String;Ljava/lang/String;)V
  Code:
   Stack=4, Locals=5, Args_size=4
	aload_0
	invokevirtual	Method out:()Ljava/io/OutputStreamWriter;
	new	class scala/collection/mutable/StringBuilder
	dup
	invokespecial	Method scala/collection/mutable/StringBuilder."<init>":()V
	ldc	String </
	invokevirtual	Method scala/collection/mutable/StringBuilder.append:(Ljava/lang/Object;)Lscala/collection/mutable/StringBuilder;
	aload_3
	invokevirtual	Method scala/collection/mutable/StringBuilder.append:(Ljava/lang/Object;)Lscala/collection/mutable/StringBuilder;
	ldc	String >
	invokevirtual	Method scala/collection/mutable/StringBuilder.append:(Ljava/lang/Object;)Lscala/collection/mutable/StringBuilder;
	invokevirtual	Method scala/collection/mutable/StringBuilder.toString:()Ljava/lang/String;
	invokevirtual	Method java/io/OutputStreamWriter.write:(Ljava/lang/String;)V
	return
	astore	4
	new	class org/xml/sax/SAXException
	dup
	ldc	String Write failed
	aload	4
	invokespecial	Method org/xml/sax/SAXException."<init>":(Ljava/lang/String;Ljava/lang/Exception;)V
	athrow
  Labels:
  Exception table:
   from   to  target type
     0    31    32   Class java/io/IOException

  LocalVariableTable: 
   Start  Length  Slot  Name   Signature
   0      46      0    this       Lscala/xml/include/sax/XIncluder;
   0      46      1    namespaceURI       Ljava/lang/String;
   0      46      2    localName       Ljava/lang/String;
   0      46      3    qualifiedName       Ljava/lang/String;


public void startElement(java.lang.String, java.lang.String, java.lang.String, org.xml.sax.Attributes);
  Signature: (Ljava/lang/String;Ljava/lang/String;Ljava/lang/String;Lorg/xml/sax/Attributes;)V
  Code:
   Stack=4, Locals=13, Args_size=5
	aload_0
	invokevirtual	Method out:()Ljava/io/OutputStreamWriter;
	new	class scala/collection/mutable/StringBuilder
	dup
	invokespecial	Method scala/collection/mutable/StringBuilder."<init>":()V
	ldc	String <
	invokevirtual	Method scala/collection/mutable/StringBuilder.append:(Ljava/lang/Object;)Lscala/collection/mutable/StringBuilder;
	aload_3
	invokevirtual	Method scala/collection/mutable/StringBuilder.append:(Ljava/lang/Object;)Lscala/collection/mutable/StringBuilder;
	invokevirtual	Method scala/collection/mutable/StringBuilder.toString:()Ljava/lang/String;
	invokevirtual	Method java/io/OutputStreamWriter.write:(Ljava/lang/String;)V
	iconst_0
	istore	11
l2	iload	11
	aload	4
	invokeinterface	InterfaceMethod org/xml/sax/Attributes.getLength:()I
	if_icmpge	l1 // aload_0
	aload_0
	invokevirtual	Method out:()Ljava/io/OutputStreamWriter;
	ldc	String  
	invokevirtual	Method java/io/OutputStreamWriter.write:(Ljava/lang/String;)V
	aload_0
	invokevirtual	Method out:()Ljava/io/OutputStreamWriter;
	aload	4
	iload	11
	invokeinterface	InterfaceMethod org/xml/sax/Attributes.getQName:(I)Ljava/lang/String;
	invokevirtual	Method java/io/OutputStreamWriter.write:(Ljava/lang/String;)V
	aload_0
	invokevirtual	Method out:()Ljava/io/OutputStreamWriter;
	ldc	String ='
	invokevirtual	Method java/io/OutputStreamWriter.write:(Ljava/lang/String;)V
	aload	4
	iload	11
	invokeinterface	InterfaceMethod org/xml/sax/Attributes.getValue:(I)Ljava/lang/String;
	astore	5
	aload_0
	invokevirtual	Method out:()Ljava/io/OutputStreamWriter;
	new	class scala/xml/Utility$$anonfun$escape$1
	dup
	pop
	aload	5
	invokespecial	Method scala/xml/Utility$$anonfun$escape$1."<init>":(Ljava/lang/String;)V
	new	class scala/collection/mutable/StringBuilder
	dup
	invokespecial	Method scala/collection/mutable/StringBuilder."<init>":()V
	astore	10
	aload	10
	checkcast	class scala/collection/mutable/StringBuilder
	astore	8
	aload	5
	astore	6
	new	class scala/collection/immutable/StringOps
	dup
	aload	6
	invokespecial	Method scala/collection/immutable/StringOps."<init>":(Ljava/lang/String;)V
	new	class scala/xml/Utility$$anonfun$escape$2
	dup
	invokespecial	Method scala/xml/Utility$$anonfun$escape$2."<init>":()V
	astore	9
	astore	7
	aload	7
	aload	8
	aload	9
	invokestatic	Method scala/collection/IndexedSeqLike$class.foldLeft:(Lscala/collection/IndexedSeqLike;Ljava/lang/Object;Lscala/Function2;)Ljava/lang/Object;
	pop
	aload	10
	invokevirtual	Method scala/collection/mutable/StringBuilder.toString:()Ljava/lang/String;
	invokevirtual	Method java/io/OutputStreamWriter.write:(Ljava/lang/String;)V
	aload_0
	invokevirtual	Method out:()Ljava/io/OutputStreamWriter;
	ldc	String '
	invokevirtual	Method java/io/OutputStreamWriter.write:(Ljava/lang/String;)V
	iload	11
	iconst_1
	iadd
	istore	11
	goto	l2 // iload
l1	aload_0
	invokevirtual	Method out:()Ljava/io/OutputStreamWriter;
	ldc	String >
	invokevirtual	Method java/io/OutputStreamWriter.write:(Ljava/lang/String;)V
	return
	astore	12
	new	class org/xml/sax/SAXException
	dup
	ldc	String Write failed
	aload	12
	invokespecial	Method org/xml/sax/SAXException."<init>":(Ljava/lang/String;Ljava/lang/Exception;)V
	athrow
  Labels:
   	l2 = 29 // iload
   	l1 = 176 // aload_0
  Exception table:
   from   to  target type
     0   185   186   Class java/io/IOException

  LocalVariableTable: 
   Start  Length  Slot  Name   Signature
   0      200      0    this       Lscala/xml/include/sax/XIncluder;
   0      200      1    namespaceURI       Ljava/lang/String;
   0      200      2    localName       Ljava/lang/String;
   0      200      3    qualifiedName       Ljava/lang/String;
   0      200      4    atts       Lorg/xml/sax/Attributes;
   86      87      5    value       Ljava/lang/String;
   109      46      10    sb00       Lscala/collection/mutable/StringBuilder;
   29      156      11    i       I


public void endPrefixMapping(java.lang.String);
  Signature: (Ljava/lang/String;)V
  Code:
   Stack=0, Locals=2, Args_size=2
	return
  Labels:
  LocalVariableTable: 
   Start  Length  Slot  Name   Signature
   0      1      0    this       Lscala/xml/include/sax/XIncluder;
   0      1      1    prefix       Ljava/lang/String;


public void startPrefixMapping(java.lang.String, java.lang.String);
  Signature: (Ljava/lang/String;Ljava/lang/String;)V
  Code:
   Stack=0, Locals=3, Args_size=3
	return
  Labels:
  LocalVariableTable: 
   Start  Length  Slot  Name   Signature
   0      1      0    this       Lscala/xml/include/sax/XIncluder;
   0      1      1    prefix       Ljava/lang/String;
   0      1      2    uri       Ljava/lang/String;


public void endDocument();
  Signature: ()V
  Code:
   Stack=4, Locals=2, Args_size=1
	aload_0
	invokevirtual	Method out:()Ljava/io/OutputStreamWriter;
	invokevirtual	Method java/io/OutputStreamWriter.flush:()V
	return
	astore_1
	new	class org/xml/sax/SAXException
	dup
	ldc	String Flush failed
	aload_1
	invokespecial	Method org/xml/sax/SAXException."<init>":(Ljava/lang/String;Ljava/lang/Exception;)V
	athrow
  Labels:
  Exception table:
   from   to  target type
     0     7     8   Class java/io/IOException

  LocalVariableTable: 
   Start  Length  Slot  Name   Signature
   0      20      0    this       Lscala/xml/include/sax/XIncluder;


public void startDocument();
  Signature: ()V
  Code:
   Stack=4, Locals=2, Args_size=1
	aload_0
	invokevirtual	Method out:()Ljava/io/OutputStreamWriter;
	new	class scala/collection/mutable/StringBuilder
	dup
	invokespecial	Method scala/collection/mutable/StringBuilder."<init>":()V
	ldc_w	String <?xml version='1.0' encoding='
	invokevirtual	Method scala/collection/mutable/StringBuilder.append:(Ljava/lang/Object;)Lscala/collection/mutable/StringBuilder;
	aload_0
	getfield	Field encoding:Ljava/lang/String;
	invokevirtual	Method scala/collection/mutable/StringBuilder.append:(Ljava/lang/Object;)Lscala/collection/mutable/StringBuilder;
	ldc_w	String '?>\r\n
	invokevirtual	Method scala/collection/mutable/StringBuilder.append:(Ljava/lang/Object;)Lscala/collection/mutable/StringBuilder;
	invokevirtual	Method scala/collection/mutable/StringBuilder.toString:()Ljava/lang/String;
	invokevirtual	Method java/io/OutputStreamWriter.write:(Ljava/lang/String;)V
	return
	astore_1
	new	class org/xml/sax/SAXException
	dup
	ldc	String Write failed
	aload_1
	invokespecial	Method org/xml/sax/SAXException."<init>":(Ljava/lang/String;Ljava/lang/Exception;)V
	athrow
  Labels:
  Exception table:
   from   to  target type
     0    36    37   Class java/io/IOException

  LocalVariableTable: 
   Start  Length  Slot  Name   Signature
   0      49      0    this       Lscala/xml/include/sax/XIncluder;


public void setDocumentLocator(org.xml.sax.Locator);
  Signature: (Lorg/xml/sax/Locator;)V
  Code:
   Stack=0, Locals=2, Args_size=2
	return
  Labels:
  LocalVariableTable: 
   Start  Length  Slot  Name   Signature
   0      1      0    this       Lscala/xml/include/sax/XIncluder;
   0      1      1    locator       Lorg/xml/sax/Locator;


public void out_$eq(java.io.OutputStreamWriter);
  Signature: (Ljava/io/OutputStreamWriter;)V
  Code:
   Stack=2, Locals=2, Args_size=2
	aload_0
	aload_1
	putfield	Field out:Ljava/io/OutputStreamWriter;
	return
  Labels:

public java.io.OutputStreamWriter out();
  Signature: ()Ljava/io/OutputStreamWriter;
  Code:
   Stack=1, Locals=1, Args_size=1
	aload_0
	getfield	Field out:Ljava/io/OutputStreamWriter;
	areturn
  Labels:

}

