Compiled from "XIncluder.scala"
public class scala.xml.include.sax.XIncluder extends java.lang.Object implements org.xml.sax.ContentHandler,org.xml.sax.ext.LexicalHandler,scala.ScalaObject
  SourceFile: "XIncluder.scala"
  ScalaSig: length = 0x6B8
   05 00 FFFFFF81 61 06 08 01 02 FFFFFF84 FFFFFF80 FFFFFF80 FFFFFF80 00 0B 02 09
   58 49 6E 63 6C 75 64 65 72 0A 02 03 04 01 03 73
   61 78 0A 02 05 06 01 07 69 6E 63 6C 75 64 65 0A
   02 07 08 01 03 78 6D 6C 0A 01 09 01 05 73 63 61
   6C 61 03 00 13 05 00 0C 14 1C 22 10 02 0D 12 0D
   01 0E 0A 02 0F 10 01 04 6C 61 6E 67 0A 01 11 01
   04 6A 61 76 61 09 02 13 0E 02 06 4F 62 6A 65 63
   74 10 02 15 1A 0D 01 16 0A 02 03 17 0A 02 07 18
   0A 01 19 01 03 6F 72 67 09 02 1B 16 02 0E 43 6F
   6E 74 65 6E 74 48 61 6E 64 6C 65 72 10 02 1D 20
   0D 01 1E 0A 02 1F 16 01 03 65 78 74 09 02 21 1E
   02 0E 4C 65 78 69 63 61 6C 48 61 6E 64 6C 65 72
   10 02 23 24 0D 01 08 09 02 25 08 02 0B 53 63 61
   6C 61 4F 62 6A 65 63 74 08 08 27 00 FFFFFF82 FFFFFF80 FFFFFFA0 FFFFFF80
   04 28 01 04 6F 75 74 73 10 02 29 2C 0D 01 2A 0A
   02 2B 10 01 02 69 6F 09 02 2D 2A 02 0C 4F 75 74
   70 75 74 53 74 72 65 61 6D 08 08 2F 00 FFFFFF82 FFFFFF80 FFFFFFA0
   FFFFFF80 04 30 01 08 65 6E 63 6F 64 69 6E 67 10 02 31
   34 0E 02 23 32 09 02 33 08 01 06 50 72 65 64 65
   66 09 02 35 36 02 06 53 74 72 69 6E 67 0A 02 33
   08 08 05 38 00 FFFFFF84 00 39 01 06 3C 69 6E 69 74 3E
   14 03 3A 3C 3D 10 02 3B 00 0D 01 02 08 05 27 37
   FFFFFFC0 00 28 08 05 2F 37 FFFFFFC0 00 30 08 07 3F 00 FFFFFFC0 FFFFFF80
   FFFFFF84 00 40 01 03 6F 75 74 15 01 41 10 02 29 42 09
   02 43 2A 02 12 4F 75 74 70 75 74 53 74 72 65 61
   6D 57 72 69 74 65 72 08 07 45 00 FFFFFFC0 FFFFFF80 FFFFFF84 00 46
   01 07 6F 75 74 5F 24 65 71 14 02 47 4A 10 02 23
   48 09 02 49 08 02 04 55 6E 69 74 08 07 4B 44 FFFFFF81
   FFFFFF80 FFFFFFC0 00 41 01 03 78 24 31 08 06 4D 00 FFFFFFA0 FFFFFFA0 04
   41 01 04 6F 75 74 20 08 05 4F 00 FFFFFF84 00 50 01 12
   73 65 74 44 6F 63 75 6D 65 6E 74 4C 6F 63 61 74
   6F 72 14 02 47 51 08 05 52 4E FFFFFFC0 00 53 01 07 6C
   6F 63 61 74 6F 72 10 02 15 54 09 02 55 16 02 07
   4C 6F 63 61 74 6F 72 08 05 57 00 FFFFFF84 00 58 01 0D
   73 74 61 72 74 44 6F 63 75 6D 65 6E 74 14 01 47
   08 05 5A 00 FFFFFF84 00 58 01 0B 65 6E 64 44 6F 63 75
   6D 65 6E 74 08 05 5C 00 FFFFFF84 00 5D 01 12 73 74 61
   72 74 50 72 65 66 69 78 4D 61 70 70 69 6E 67 14
   03 47 5E 60 08 05 5F 5B FFFFFFC0 00 30 01 06 70 72 65
   66 69 78 08 05 61 5B FFFFFFC0 00 30 01 03 75 72 69 08
   05 63 00 FFFFFF84 00 64 01 10 65 6E 64 50 72 65 66 69
   78 4D 61 70 70 69 6E 67 14 02 47 65 08 05 5F 62
   FFFFFFC0 00 30 08 05 67 00 FFFFFF84 00 68 01 0C 73 74 61 72
   74 45 6C 65 6D 65 6E 74 14 05 47 69 6B 6D 6F 08
   05 6A 66 FFFFFFC0 00 30 01 0C 6E 61 6D 65 73 70 61 63
   65 55 52 49 08 05 6C 66 FFFFFFC0 00 30 01 09 6C 6F 63
   61 6C 4E 61 6D 65 08 05 6E 66 FFFFFFC0 00 30 01 0D 71
   75 61 6C 69 66 69 65 64 4E 61 6D 65 08 05 70 66
   FFFFFFC0 00 71 01 04 61 74 74 73 10 02 15 72 09 02 73
   16 02 0A 41 74 74 72 69 62 75 74 65 73 08 05 75
   00 FFFFFF84 00 76 01 0A 65 6E 64 45 6C 65 6D 65 6E 74
   14 04 47 77 78 79 08 05 6A 74 FFFFFFC0 00 30 08 05 6C
   74 FFFFFFC0 00 30 08 05 6E 74 FFFFFFC0 00 30 08 05 7B 00 FFFFFF84
   00 7C 01 0A 63 68 61 72 61 63 74 65 72 73 14 06
   47 7D FFFFFF81 05 FFFFFF81 0A 08 05 7E 7A FFFFFFC0 00 7F 01 02 63
   68 10 05 23 FFFFFF81 00 FFFFFF81 02 09 03 FFFFFF81 01 08 02 05 41
   72 72 61 79 10 03 23 FFFFFF81 03 09 03 FFFFFF81 04 08 02 04
   43 68 61 72 08 07 FFFFFF81 06 7A FFFFFFC0 00 FFFFFF81 07 01 05 73
   74 61 72 74 10 03 23 FFFFFF81 08 09 03 FFFFFF81 09 08 02 03
   49 6E 74 08 07 FFFFFF81 0B 7A FFFFFFC0 00 FFFFFF81 07 01 06 6C 65
   6E 67 74 68 08 07 FFFFFF81 0D 00 FFFFFF84 00 FFFFFF81 0E 01 13 69
   67 6E 6F 72 61 62 6C 65 57 68 69 74 65 73 70 61
   63 65 14 07 47 FFFFFF81 0F FFFFFF81 10 FFFFFF81 11 08 06 7E FFFFFF81 0C
   FFFFFFC0 00 7F 08 08 FFFFFF81 06 FFFFFF81 0C FFFFFFC0 00 FFFFFF81 07 08 08 FFFFFF81
   0B FFFFFF81 0C FFFFFFC0 00 FFFFFF81 07 08 07 FFFFFF81 13 00 FFFFFF84 00 FFFFFF81 14
   01 15 70 72 6F 63 65 73 73 69 6E 67 49 6E 73 74
   72 75 63 74 69 6F 6E 14 05 47 FFFFFF81 15 FFFFFF81 17 08 07
   FFFFFF81 16 FFFFFF81 12 FFFFFFC0 00 30 01 06 74 61 72 67 65 74 08
   07 FFFFFF81 18 FFFFFF81 12 FFFFFFC0 00 30 01 04 64 61 74 61 08 07
   FFFFFF81 1A 00 FFFFFF84 00 FFFFFF81 1B 01 0D 73 6B 69 70 70 65 64
   45 6E 74 69 74 79 14 03 47 FFFFFF81 1C 08 07 FFFFFF81 1D FFFFFF81
   19 FFFFFFC0 00 30 01 04 6E 61 6D 65 08 09 FFFFFF81 1F 00 FFFFFFC0
   FFFFFF80 FFFFFF84 04 FFFFFF81 20 01 05 69 6E 44 54 44 15 02 FFFFFF81 21
   10 03 23 FFFFFF81 22 09 03 FFFFFF81 23 08 02 07 42 6F 6F 6C
   65 61 6E 08 09 FFFFFF81 25 00 FFFFFFC0 FFFFFF80 FFFFFF84 04 FFFFFF81 26 01 09
   69 6E 44 54 44 5F 24 65 71 14 03 47 FFFFFF81 27 08 09
   4B FFFFFF81 24 FFFFFF81 FFFFFF80 FFFFFFC0 00 FFFFFF81 21 08 08 FFFFFF81 29 00 FFFFFFA0 FFFFFFA0
   04 FFFFFF81 21 01 06 69 6E 44 54 44 20 08 09 FFFFFF81 2B 00
   FFFFFFC2 FFFFFF80 FFFFFF84 04 FFFFFF81 2C 01 08 65 6E 74 69 74 69 65 73
   15 02 FFFFFF81 2D 10 05 FFFFFF81 2E FFFFFF81 31 30 0D 02 FFFFFF81 2F 0A
   03 FFFFFF81 30 10 01 04 75 74 69 6C 09 04 FFFFFF81 32 FFFFFF81 2F
   02 05 53 74 61 63 6B 08 08 FFFFFF81 34 00 FFFFFFA0 FFFFFF80 04 FFFFFF81
   2D 01 09 65 6E 74 69 74 69 65 73 20 08 07 FFFFFF81 36
   00 FFFFFF84 00 FFFFFF81 37 01 08 73 74 61 72 74 44 54 44 14
   07 47 FFFFFF81 38 FFFFFF81 39 FFFFFF81 3B 08 07 FFFFFF81 1D FFFFFF81 35 FFFFFFC0 00
   30 08 07 FFFFFF81 3A FFFFFF81 35 FFFFFFC0 00 30 01 08 70 75 62 6C
   69 63 49 44 08 07 FFFFFF81 3C FFFFFF81 35 FFFFFFC0 00 30 01 08 73
   79 73 74 65 6D 49 44 08 06 FFFFFF81 3E 00 FFFFFF84 00 58 01
   06 65 6E 64 44 54 44 08 07 FFFFFF81 40 00 FFFFFF84 00 FFFFFF81 41
   01 0B 73 74 61 72 74 45 6E 74 69 74 79 14 03 47
   FFFFFF81 42 08 07 FFFFFF81 1D FFFFFF81 3F FFFFFFC0 00 30 08 07 FFFFFF81 44 00
   FFFFFF84 00 FFFFFF81 45 01 09 65 6E 64 45 6E 74 69 74 79 14
   03 47 FFFFFF81 46 08 07 FFFFFF81 1D FFFFFF81 43 FFFFFFC0 00 30 08 06 FFFFFF81
   48 00 FFFFFF84 00 58 01 0A 73 74 61 72 74 43 44 41 54
   41 08 06 FFFFFF81 4A 00 FFFFFF84 00 58 01 08 65 6E 64 43 44
   41 54 41 08 09 FFFFFF81 4C 00 FFFFFFC0 FFFFFF80 FFFFFF84 04 FFFFFF81 4D 01 06
   66 69 6C 74 65 72 15 02 FFFFFF81 4E 10 03 3B FFFFFF81 4F 09
   03 FFFFFF81 50 02 02 0E 58 49 6E 63 6C 75 64 65 46 69
   6C 74 65 72 08 09 FFFFFF81 52 00 FFFFFFC0 FFFFFF80 FFFFFF84 04 FFFFFF81 53 01
   0A 66 69 6C 74 65 72 5F 24 65 71 14 03 47 FFFFFF81 54
   08 09 4B FFFFFF81 51 FFFFFF81 FFFFFF80 FFFFFFC0 00 FFFFFF81 4E 08 08 FFFFFF81 56 00
   FFFFFFA0 FFFFFFA0 04 FFFFFF81 4E 01 07 66 69 6C 74 65 72 20 08 07
   FFFFFF81 58 00 FFFFFF84 00 FFFFFF81 59 01 09 73 65 74 46 69 6C 74
   65 72 14 03 47 FFFFFF81 5A 08 08 FFFFFF81 4C FFFFFF81 57 FFFFFFC0 00 FFFFFF81
   4E 08 07 FFFFFF81 5C 00 FFFFFF84 00 FFFFFF81 5D 01 07 63 6F 6D 6D
   65 6E 74 14 07 47 FFFFFF81 5E FFFFFF81 5F FFFFFF81 60 08 06 7E FFFFFF81
   5B FFFFFFC0 00 7F 08 08 FFFFFF81 06 FFFFFF81 5B FFFFFFC0 00 FFFFFF81 07 08 08
   FFFFFF81 0B FFFFFF81 5B FFFFFFC0 00 FFFFFF81 07 
  minor version: 0
  major version: 49
  Constant pool:
const #1 = Asciz	SourceFile;
const #2 = Asciz	XIncluder.scala;
const #3 = Asciz	filter;
const #4 = Asciz	Lscala/xml/include/sax/XIncludeFilter;;
const #5 = Asciz	entities;
const #6 = Asciz	Ljava/util/Stack;;
const #7 = Asciz	Ljava/util/Stack<Ljava/lang/String;>;;
const #8 = Asciz	Signature;
const #9 = Asciz	inDTD;
const #10 = Asciz	Z;
const #11 = Asciz	out;
const #12 = Asciz	Ljava/io/OutputStreamWriter;;
const #13 = Asciz	encoding;
const #14 = Asciz	Ljava/lang/String;;
const #15 = Asciz	<init>;
const #16 = Asciz	(Ljava/io/OutputStream;Ljava/lang/String;)V;
const #17 = Asciz	Code;
const #18 = Asciz	LineNumberTable;
const #19 = Asciz	scala/xml/include/sax/XIncluder;
const #20 = class	#19;	//  scala/xml/include/sax/XIncluder
const #21 = NameAndType	#13:#14;//  encoding:Ljava/lang/String;
const #22 = Field	#20.#21;	//  scala/xml/include/sax/XIncluder.encoding:Ljava/lang/String;
const #23 = Asciz	java/lang/Object;
const #24 = class	#23;	//  java/lang/Object
const #25 = Asciz	()V;
const #26 = NameAndType	#15:#25;//  "<init>":()V
const #27 = Method	#24.#26;	//  java/lang/Object."<init>":()V
const #28 = Asciz	java/io/OutputStreamWriter;
const #29 = class	#28;	//  java/io/OutputStreamWriter
const #30 = NameAndType	#15:#16;//  "<init>":(Ljava/io/OutputStream;Ljava/lang/String;)V
const #31 = Method	#29.#30;	//  java/io/OutputStreamWriter."<init>":(Ljava/io/OutputStream;Ljava/lang/String;)V
const #32 = NameAndType	#11:#12;//  out:Ljava/io/OutputStreamWriter;
const #33 = Field	#20.#32;	//  scala/xml/include/sax/XIncluder.out:Ljava/io/OutputStreamWriter;
const #34 = NameAndType	#9:#10;//  inDTD:Z
const #35 = Field	#20.#34;	//  scala/xml/include/sax/XIncluder.inDTD:Z
const #36 = Asciz	java/util/Stack;
const #37 = class	#36;	//  java/util/Stack
const #38 = Method	#37.#26;	//  java/util/Stack."<init>":()V
const #39 = NameAndType	#5:#6;//  entities:Ljava/util/Stack;
const #40 = Field	#20.#39;	//  scala/xml/include/sax/XIncluder.entities:Ljava/util/Stack;
const #41 = NameAndType	#3:#4;//  filter:Lscala/xml/include/sax/XIncludeFilter;
const #42 = Field	#20.#41;	//  scala/xml/include/sax/XIncluder.filter:Lscala/xml/include/sax/XIncludeFilter;
const #43 = Asciz	this;
const #44 = Asciz	Lscala/xml/include/sax/XIncluder;;
const #45 = Asciz	outs;
const #46 = Asciz	Ljava/io/OutputStream;;
const #47 = Asciz	LocalVariableTable;
const #48 = Asciz	comment;
const #49 = Asciz	([CII)V;
const #50 = Asciz	()Z;
const #51 = NameAndType	#9:#50;//  inDTD:()Z
const #52 = Method	#20.#51;	//  scala/xml/include/sax/XIncluder.inDTD:()Z
const #53 = Asciz	()Lscala/xml/include/sax/XIncludeFilter;;
const #54 = NameAndType	#3:#53;//  filter:()Lscala/xml/include/sax/XIncludeFilter;
const #55 = Method	#20.#54;	//  scala/xml/include/sax/XIncluder.filter:()Lscala/xml/include/sax/XIncludeFilter;
const #56 = Asciz	scala/xml/include/sax/XIncludeFilter;
const #57 = class	#56;	//  scala/xml/include/sax/XIncludeFilter
const #58 = Asciz	insideIncludeElement;
const #59 = NameAndType	#58:#50;//  insideIncludeElement:()Z
const #60 = Method	#57.#59;	//  scala/xml/include/sax/XIncludeFilter.insideIncludeElement:()Z
const #61 = Asciz	()Ljava/io/OutputStreamWriter;;
const #62 = NameAndType	#11:#61;//  out:()Ljava/io/OutputStreamWriter;
const #63 = Method	#20.#62;	//  scala/xml/include/sax/XIncluder.out:()Ljava/io/OutputStreamWriter;
const #64 = Asciz	<!--;
const #65 = String	#64;	//  <!--
const #66 = Asciz	write;
const #67 = Asciz	(Ljava/lang/String;)V;
const #68 = NameAndType	#66:#67;//  write:(Ljava/lang/String;)V
const #69 = Method	#29.#68;	//  java/io/OutputStreamWriter.write:(Ljava/lang/String;)V
const #70 = NameAndType	#66:#49;//  write:([CII)V
const #71 = Method	#29.#70;	//  java/io/OutputStreamWriter.write:([CII)V
const #72 = Asciz	-->;
const #73 = String	#72;	//  -->
const #74 = Asciz	org/xml/sax/SAXException;
const #75 = class	#74;	//  org/xml/sax/SAXException
const #76 = Asciz	Write failed;
const #77 = String	#76;	//  Write failed
const #78 = Asciz	(Ljava/lang/String;Ljava/lang/Exception;)V;
const #79 = NameAndType	#15:#78;//  "<init>":(Ljava/lang/String;Ljava/lang/Exception;)V
const #80 = Method	#75.#79;	//  org/xml/sax/SAXException."<init>":(Ljava/lang/String;Ljava/lang/Exception;)V
const #81 = Asciz	java/io/IOException;
const #82 = class	#81;	//  java/io/IOException
const #83 = Asciz	ch;
const #84 = Asciz	[C;
const #85 = Asciz	start;
const #86 = Asciz	I;
const #87 = Asciz	length;
const #88 = Asciz	setFilter;
const #89 = Asciz	(Lscala/xml/include/sax/XIncludeFilter;)V;
const #90 = Asciz	filter_$eq;
const #91 = NameAndType	#90:#89;//  filter_$eq:(Lscala/xml/include/sax/XIncludeFilter;)V
const #92 = Method	#20.#91;	//  scala/xml/include/sax/XIncluder.filter_$eq:(Lscala/xml/include/sax/XIncludeFilter;)V
const #93 = Asciz	endCDATA;
const #94 = Asciz	startCDATA;
const #95 = Asciz	endEntity;
const #96 = Asciz	()Ljava/util/Stack;;
const #97 = NameAndType	#5:#96;//  entities:()Ljava/util/Stack;
const #98 = Method	#20.#97;	//  scala/xml/include/sax/XIncluder.entities:()Ljava/util/Stack;
const #99 = Asciz	pop;
const #100 = Asciz	()Ljava/lang/Object;;
const #101 = NameAndType	#99:#100;//  pop:()Ljava/lang/Object;
const #102 = Method	#37.#101;	//  java/util/Stack.pop:()Ljava/lang/Object;
const #103 = Asciz	name;
const #104 = Asciz	startEntity;
const #105 = Asciz	push;
const #106 = Asciz	(Ljava/lang/Object;)Ljava/lang/Object;;
const #107 = NameAndType	#105:#106;//  push:(Ljava/lang/Object;)Ljava/lang/Object;
const #108 = Method	#37.#107;	//  java/util/Stack.push:(Ljava/lang/Object;)Ljava/lang/Object;
const #109 = Asciz	endDTD;
const #110 = Asciz	startDTD;
const #111 = Asciz	(Ljava/lang/String;Ljava/lang/String;Ljava/lang/String;)V;
const #112 = Asciz	inDTD_$eq;
const #113 = Asciz	(Z)V;
const #114 = NameAndType	#112:#113;//  inDTD_$eq:(Z)V
const #115 = Method	#20.#114;	//  scala/xml/include/sax/XIncluder.inDTD_$eq:(Z)V
const #116 = Asciz	size;
const #117 = Asciz	()I;
const #118 = NameAndType	#116:#117;//  size:()I
const #119 = Method	#37.#118;	//  java/util/Stack.size:()I
const #120 = Asciz	;
const #121 = String	#120;	//  
const #122 = Asciz	equals;
const #123 = Asciz	(Ljava/lang/Object;)Z;
const #124 = NameAndType	#122:#123;//  equals:(Ljava/lang/Object;)Z
const #125 = Method	#24.#124;	//  java/lang/Object.equals:(Ljava/lang/Object;)Z
const #126 = Asciz	scala/collection/mutable/StringBuilder;
const #127 = class	#126;	//  scala/collection/mutable/StringBuilder
const #128 = Method	#127.#26;	//  scala/collection/mutable/StringBuilder."<init>":()V
const #129 = Asciz	 SYSTEM \";
const #130 = String	#129;	//   SYSTEM \"
const #131 = Asciz	append;
const #132 = Asciz	(Ljava/lang/Object;)Lscala/collection/mutable/StringBuilder;;
const #133 = NameAndType	#131:#132;//  append:(Ljava/lang/Object;)Lscala/collection/mutable/StringBuilder;
const #134 = Method	#127.#133;	//  scala/collection/mutable/StringBuilder.append:(Ljava/lang/Object;)Lscala/collection/mutable/StringBuilder;
const #135 = int	34;
const #136 = Asciz	scala/runtime/BoxesRunTime;
const #137 = class	#136;	//  scala/runtime/BoxesRunTime
const #138 = Asciz	boxToCharacter;
const #139 = Asciz	(C)Ljava/lang/Character;;
const #140 = NameAndType	#138:#139;//  boxToCharacter:(C)Ljava/lang/Character;
const #141 = Method	#137.#140;	//  scala/runtime/BoxesRunTime.boxToCharacter:(C)Ljava/lang/Character;
const #142 = Asciz	toString;
const #143 = Asciz	()Ljava/lang/String;;
const #144 = NameAndType	#142:#143;//  toString:()Ljava/lang/String;
const #145 = Method	#127.#144;	//  scala/collection/mutable/StringBuilder.toString:()Ljava/lang/String;
const #146 = Asciz	 PUBLIC \";
const #147 = String	#146;	//   PUBLIC \"
const #148 = Asciz	\" \";
const #149 = String	#148;	//  \" \"
const #150 = Asciz	<!DOCTYPE ;
const #151 = String	#150;	//  <!DOCTYPE 
const #152 = Asciz	>\r\n;
const #153 = String	#152;	//  >\r\n
const #154 = Asciz	Error while writing DOCTYPE;
const #155 = String	#154;	//  Error while writing DOCTYPE
const #156 = Asciz	publicID;
const #157 = Asciz	systemID;
const #158 = Asciz	id;
const #159 = Asciz	()Ljava/util/Stack<Ljava/lang/String;>;;
const #160 = Asciz	skippedEntity;
const #161 = Asciz	&;
const #162 = String	#161;	//  &
const #163 = Asciz	;;
const #164 = String	#163;	//  ;
const #165 = Asciz	processingInstruction;
const #166 = Asciz	(Ljava/lang/String;Ljava/lang/String;)V;
const #167 = Asciz	<?;
const #168 = String	#167;	//  <?
const #169 = Asciz	 ;
const #170 = String	#169;	//   
const #171 = Asciz	?>;
const #172 = String	#171;	//  ?>
const #173 = Asciz	target;
const #174 = Asciz	data;
const #175 = Asciz	ignorableWhitespace;
const #176 = Asciz	characters;
const #177 = NameAndType	#176:#49;//  characters:([CII)V
const #178 = Method	#20.#177;	//  scala/xml/include/sax/XIncluder.characters:([CII)V
const #179 = int	38;
const #180 = Asciz	&amp;;
const #181 = String	#180;	//  &amp;
const #182 = int	60;
const #183 = Asciz	&lt;;
const #184 = String	#183;	//  &lt;
const #185 = int	62;
const #186 = Asciz	&gt;;
const #187 = String	#186;	//  &gt;
const #188 = Asciz	scala/Predef$;
const #189 = class	#188;	//  scala/Predef$
const #190 = Asciz	MODULE$;
const #191 = Asciz	Lscala/Predef$;;
const #192 = NameAndType	#190:#191;//  MODULE$:Lscala/Predef$;
const #193 = Field	#189.#192;	//  scala/Predef$.MODULE$:Lscala/Predef$;
const #194 = Asciz	char2int;
const #195 = Asciz	(C)I;
const #196 = NameAndType	#194:#195;//  char2int:(C)I
const #197 = Method	#189.#196;	//  scala/Predef$.char2int:(C)I
const #198 = Asciz	(I)V;
const #199 = NameAndType	#66:#198;//  write:(I)V
const #200 = Method	#29.#199;	//  java/io/OutputStreamWriter.write:(I)V
const #201 = Asciz	i;
const #202 = Asciz	c;
const #203 = Asciz	C;
const #204 = Asciz	endElement;
const #205 = Asciz	</;
const #206 = String	#205;	//  </
const #207 = Asciz	>;
const #208 = String	#207;	//  >
const #209 = Asciz	namespaceURI;
const #210 = Asciz	localName;
const #211 = Asciz	qualifiedName;
const #212 = Asciz	startElement;
const #213 = Asciz	(Ljava/lang/String;Ljava/lang/String;Ljava/lang/String;Lorg/xml/sax/Attributes;)V;
const #214 = Asciz	<;
const #215 = String	#214;	//  <
const #216 = Asciz	org/xml/sax/Attributes;
const #217 = class	#216;	//  org/xml/sax/Attributes
const #218 = Asciz	getLength;
const #219 = NameAndType	#218:#117;//  getLength:()I
const #220 = InterfaceMethod	#217.#219;	//  org/xml/sax/Attributes.getLength:()I
const #221 = Asciz	getQName;
const #222 = Asciz	(I)Ljava/lang/String;;
const #223 = NameAndType	#221:#222;//  getQName:(I)Ljava/lang/String;
const #224 = InterfaceMethod	#217.#223;	//  org/xml/sax/Attributes.getQName:(I)Ljava/lang/String;
const #225 = Asciz	=';
const #226 = String	#225;	//  ='
const #227 = Asciz	getValue;
const #228 = NameAndType	#227:#222;//  getValue:(I)Ljava/lang/String;
const #229 = InterfaceMethod	#217.#228;	//  org/xml/sax/Attributes.getValue:(I)Ljava/lang/String;
const #230 = Asciz	scala/xml/Utility$;
const #231 = class	#230;	//  scala/xml/Utility$
const #232 = Asciz	Lscala/xml/Utility$;;
const #233 = NameAndType	#190:#232;//  MODULE$:Lscala/xml/Utility$;
const #234 = Field	#231.#233;	//  scala/xml/Utility$.MODULE$:Lscala/xml/Utility$;
const #235 = Asciz	escape;
const #236 = Asciz	(Ljava/lang/String;)Ljava/lang/String;;
const #237 = NameAndType	#235:#236;//  escape:(Ljava/lang/String;)Ljava/lang/String;
const #238 = Method	#231.#237;	//  scala/xml/Utility$.escape:(Ljava/lang/String;)Ljava/lang/String;
const #239 = Asciz	';
const #240 = String	#239;	//  '
const #241 = Asciz	atts;
const #242 = Asciz	Lorg/xml/sax/Attributes;;
const #243 = Asciz	value;
const #244 = Asciz	endPrefixMapping;
const #245 = Asciz	prefix;
const #246 = Asciz	startPrefixMapping;
const #247 = Asciz	uri;
const #248 = Asciz	endDocument;
const #249 = Asciz	flush;
const #250 = NameAndType	#249:#25;//  flush:()V
const #251 = Method	#29.#250;	//  java/io/OutputStreamWriter.flush:()V
const #252 = Asciz	Flush failed;
const #253 = String	#252;	//  Flush failed
const #254 = Asciz	startDocument;
const #255 = Asciz	<?xml version='1.0' encoding=';
const #256 = String	#255;	//  <?xml version='1.0' encoding='
const #257 = Asciz	'?>\r\n;
const #258 = String	#257;	//  '?>\r\n
const #259 = Asciz	setDocumentLocator;
const #260 = Asciz	(Lorg/xml/sax/Locator;)V;
const #261 = Asciz	locator;
const #262 = Asciz	Lorg/xml/sax/Locator;;
const #263 = Asciz	out_$eq;
const #264 = Asciz	(Ljava/io/OutputStreamWriter;)V;
const #265 = Asciz	ScalaSig;
const #266 = Asciz	org/xml/sax/ContentHandler;
const #267 = class	#266;	//  org/xml/sax/ContentHandler
const #268 = Asciz	org/xml/sax/ext/LexicalHandler;
const #269 = class	#268;	//  org/xml/sax/ext/LexicalHandler
const #270 = Asciz	scala/ScalaObject;
const #271 = class	#270;	//  scala/ScalaObject

{
public scala.xml.include.sax.XIncluder(java.io.OutputStream, java.lang.String);
  Code:
   Stack=5, Locals=3, Args_size=3
   0:	aload_0
   1:	aload_2
   2:	putfield	#22; //Field encoding:Ljava/lang/String;
   5:	aload_0
   6:	invokespecial	#27; //Method java/lang/Object."<init>":()V
   9:	aload_0
   10:	new	#29; //class java/io/OutputStreamWriter
   13:	dup
   14:	aload_1
   15:	aload_2
   16:	invokespecial	#31; //Method java/io/OutputStreamWriter."<init>":(Ljava/io/OutputStream;Ljava/lang/String;)V
   19:	putfield	#33; //Field out:Ljava/io/OutputStreamWriter;
   22:	aload_0
   23:	iconst_0
   24:	putfield	#35; //Field inDTD:Z
   27:	aload_0
   28:	new	#37; //class java/util/Stack
   31:	dup
   32:	invokespecial	#38; //Method java/util/Stack."<init>":()V
   35:	putfield	#40; //Field entities:Ljava/util/Stack;
   38:	aload_0
   39:	aconst_null
   40:	pop
   41:	aconst_null
   42:	putfield	#42; //Field filter:Lscala/xml/include/sax/XIncludeFilter;
   45:	return
  LineNumberTable: 
   line 38: 0
   line 41: 9
   line 150: 22
   line 151: 27
   line 184: 38

  LocalVariableTable: 
   Start  Length  Slot  Name   Signature
   0      46      0    this       Lscala/xml/include/sax/XIncluder;
   0      46      1    outs       Ljava/io/OutputStream;
   0      46      2    encoding       Ljava/lang/String;


public void comment(char[], int, int);
  Code:
   Stack=4, Locals=5, Args_size=4
   0:	aload_0
   1:	invokespecial	#52; //Method inDTD:()Z
   4:	ifne	45
   7:	aload_0
   8:	invokespecial	#55; //Method filter:()Lscala/xml/include/sax/XIncludeFilter;
   11:	invokevirtual	#60; //Method scala/xml/include/sax/XIncludeFilter.insideIncludeElement:()Z
   14:	ifne	45
   17:	aload_0
   18:	invokevirtual	#63; //Method out:()Ljava/io/OutputStreamWriter;
   21:	ldc	#65; //String <!--
   23:	invokevirtual	#69; //Method java/io/OutputStreamWriter.write:(Ljava/lang/String;)V
   26:	aload_0
   27:	invokevirtual	#63; //Method out:()Ljava/io/OutputStreamWriter;
   30:	aload_1
   31:	iload_2
   32:	iload_3
   33:	invokevirtual	#71; //Method java/io/OutputStreamWriter.write:([CII)V
   36:	aload_0
   37:	invokevirtual	#63; //Method out:()Ljava/io/OutputStreamWriter;
   40:	ldc	#73; //String -->
   42:	invokevirtual	#69; //Method java/io/OutputStreamWriter.write:(Ljava/lang/String;)V
   45:	return
   46:	astore	4
   48:	new	#75; //class org/xml/sax/SAXException
   51:	dup
   52:	ldc	#77; //String Write failed
   54:	aload	4
   56:	invokespecial	#80; //Method org/xml/sax/SAXException."<init>":(Ljava/lang/String;Ljava/lang/Exception;)V
   59:	athrow
  Exception table:
   from   to  target type
    17    45    46   Class java/io/IOException

  LineNumberTable: 
   line 191: 0
   line 193: 17
   line 194: 26
   line 195: 36
   line 191: 45
   line 198: 46
   line 199: 48

  LocalVariableTable: 
   Start  Length  Slot  Name   Signature
   0      60      0    this       Lscala/xml/include/sax/XIncluder;
   0      60      1    ch       [C
   0      60      2    start       I
   0      60      3    length       I


public void setFilter(scala.xml.include.sax.XIncludeFilter);
  Code:
   Stack=2, Locals=2, Args_size=2
   0:	aload_0
   1:	aload_1
   2:	invokespecial	#92; //Method filter_$eq:(Lscala/xml/include/sax/XIncludeFilter;)V
   5:	return
  LineNumberTable: 
   line 187: 0

  LocalVariableTable: 
   Start  Length  Slot  Name   Signature
   0      6      0    this       Lscala/xml/include/sax/XIncluder;
   0      6      1    filter       Lscala/xml/include/sax/XIncludeFilter;


public void endCDATA();
  Code:
   Stack=0, Locals=1, Args_size=1
   0:	return
  LineNumberTable: 
   line 180: 0


public void startCDATA();
  Code:
   Stack=0, Locals=1, Args_size=1
   0:	return
  LineNumberTable: 
   line 179: 0


public void endEntity(java.lang.String);
  Code:
   Stack=1, Locals=2, Args_size=2
   0:	aload_0
   1:	invokespecial	#98; //Method entities:()Ljava/util/Stack;
   4:	invokevirtual	#102; //Method java/util/Stack.pop:()Ljava/lang/Object;
   7:	pop
   8:	return
  LineNumberTable: 
   line 176: 0

  LocalVariableTable: 
   Start  Length  Slot  Name   Signature
   0      9      0    this       Lscala/xml/include/sax/XIncluder;
   0      9      1    name       Ljava/lang/String;


public void startEntity(java.lang.String);
  Code:
   Stack=2, Locals=2, Args_size=2
   0:	aload_0
   1:	invokespecial	#98; //Method entities:()Ljava/util/Stack;
   4:	aload_1
   5:	invokevirtual	#108; //Method java/util/Stack.push:(Ljava/lang/Object;)Ljava/lang/Object;
   8:	pop
   9:	return
  LineNumberTable: 
   line 172: 0

  LocalVariableTable: 
   Start  Length  Slot  Name   Signature
   0      10      0    this       Lscala/xml/include/sax/XIncluder;
   0      10      1    name       Ljava/lang/String;


public void endDTD();
  Code:
   Stack=0, Locals=1, Args_size=1
   0:	return
  LineNumberTable: 
   line 169: 0


public void startDTD(java.lang.String, java.lang.String, java.lang.String);
  Code:
   Stack=4, Locals=8, Args_size=4
   0:	aload_0
   1:	iconst_1
   2:	invokespecial	#115; //Method inDTD_$eq:(Z)V
   5:	aload_0
   6:	invokespecial	#98; //Method entities:()Ljava/util/Stack;
   9:	invokevirtual	#119; //Method java/util/Stack.size:()I
   12:	iconst_0
   13:	if_icmpne	158
   16:	ldc	#121; //String 
   18:	astore	4
   20:	aload_2
   21:	dup
   22:	astore	5
   24:	ifnull	36
   27:	aload	5
   29:	aconst_null
   30:	invokevirtual	#125; //Method java/lang/Object.equals:(Ljava/lang/Object;)Z
   33:	ifeq	84
   36:	aload_3
   37:	dup
   38:	astore	6
   40:	ifnull	122
   43:	aload	6
   45:	aconst_null
   46:	invokevirtual	#125; //Method java/lang/Object.equals:(Ljava/lang/Object;)Z
   49:	ifne	122
   52:	new	#127; //class scala/collection/mutable/StringBuilder
   55:	dup
   56:	invokespecial	#128; //Method scala/collection/mutable/StringBuilder."<init>":()V
   59:	ldc	#130; //String  SYSTEM \"
   61:	invokevirtual	#134; //Method scala/collection/mutable/StringBuilder.append:(Ljava/lang/Object;)Lscala/collection/mutable/StringBuilder;
   64:	aload_3
   65:	invokevirtual	#134; //Method scala/collection/mutable/StringBuilder.append:(Ljava/lang/Object;)Lscala/collection/mutable/StringBuilder;
   68:	ldc	#135; //int 34
   70:	invokestatic	#141; //Method scala/runtime/BoxesRunTime.boxToCharacter:(C)Ljava/lang/Character;
   73:	invokevirtual	#134; //Method scala/collection/mutable/StringBuilder.append:(Ljava/lang/Object;)Lscala/collection/mutable/StringBuilder;
   76:	invokevirtual	#145; //Method scala/collection/mutable/StringBuilder.toString:()Ljava/lang/String;
   79:	astore	4
   81:	goto	122
   84:	new	#127; //class scala/collection/mutable/StringBuilder
   87:	dup
   88:	invokespecial	#128; //Method scala/collection/mutable/StringBuilder."<init>":()V
   91:	ldc	#147; //String  PUBLIC \"
   93:	invokevirtual	#134; //Method scala/collection/mutable/StringBuilder.append:(Ljava/lang/Object;)Lscala/collection/mutable/StringBuilder;
   96:	aload_2
   97:	invokevirtual	#134; //Method scala/collection/mutable/StringBuilder.append:(Ljava/lang/Object;)Lscala/collection/mutable/StringBuilder;
   100:	ldc	#149; //String \" \"
   102:	invokevirtual	#134; //Method scala/collection/mutable/StringBuilder.append:(Ljava/lang/Object;)Lscala/collection/mutable/StringBuilder;
   105:	aload_3
   106:	invokevirtual	#134; //Method scala/collection/mutable/StringBuilder.append:(Ljava/lang/Object;)Lscala/collection/mutable/StringBuilder;
   109:	ldc	#135; //int 34
   111:	invokestatic	#141; //Method scala/runtime/BoxesRunTime.boxToCharacter:(C)Ljava/lang/Character;
   114:	invokevirtual	#134; //Method scala/collection/mutable/StringBuilder.append:(Ljava/lang/Object;)Lscala/collection/mutable/StringBuilder;
   117:	invokevirtual	#145; //Method scala/collection/mutable/StringBuilder.toString:()Ljava/lang/String;
   120:	astore	4
   122:	aload_0
   123:	invokevirtual	#63; //Method out:()Ljava/io/OutputStreamWriter;
   126:	new	#127; //class scala/collection/mutable/StringBuilder
   129:	dup
   130:	invokespecial	#128; //Method scala/collection/mutable/StringBuilder."<init>":()V
   133:	ldc	#151; //String <!DOCTYPE 
   135:	invokevirtual	#134; //Method scala/collection/mutable/StringBuilder.append:(Ljava/lang/Object;)Lscala/collection/mutable/StringBuilder;
   138:	aload_1
   139:	invokevirtual	#134; //Method scala/collection/mutable/StringBuilder.append:(Ljava/lang/Object;)Lscala/collection/mutable/StringBuilder;
   142:	aload	4
   144:	invokevirtual	#134; //Method scala/collection/mutable/StringBuilder.append:(Ljava/lang/Object;)Lscala/collection/mutable/StringBuilder;
   147:	ldc	#153; //String >\r\n
   149:	invokevirtual	#134; //Method scala/collection/mutable/StringBuilder.append:(Ljava/lang/Object;)Lscala/collection/mutable/StringBuilder;
   152:	invokevirtual	#145; //Method scala/collection/mutable/StringBuilder.toString:()Ljava/lang/String;
   155:	invokevirtual	#69; //Method java/io/OutputStreamWriter.write:(Ljava/lang/String;)V
   158:	return
   159:	astore	7
   161:	new	#75; //class org/xml/sax/SAXException
   164:	dup
   165:	ldc	#155; //String Error while writing DOCTYPE
   167:	aload	7
   169:	invokespecial	#80; //Method org/xml/sax/SAXException."<init>":(Ljava/lang/String;Ljava/lang/Exception;)V
   172:	athrow
  Exception table:
   from   to  target type
   122   158   159   Class java/io/IOException

  LineNumberTable: 
   line 154: 0
   line 156: 5
   line 157: 16
   line 158: 20
   line 159: 36
   line 158: 84
   line 161: 122
   line 153: 158
   line 164: 159
   line 165: 161

  LocalVariableTable: 
   Start  Length  Slot  Name   Signature
   0      173      0    this       Lscala/xml/include/sax/XIncluder;
   0      173      1    name       Ljava/lang/String;
   0      173      2    publicID       Ljava/lang/String;
   0      173      3    systemID       Ljava/lang/String;
   20      138      4    id       Ljava/lang/String;
   159      14      4    id       Ljava/lang/String;


public void skippedEntity(java.lang.String);
  Code:
   Stack=4, Locals=3, Args_size=2
   0:	aload_0
   1:	invokevirtual	#63; //Method out:()Ljava/io/OutputStreamWriter;
   4:	new	#127; //class scala/collection/mutable/StringBuilder
   7:	dup
   8:	invokespecial	#128; //Method scala/collection/mutable/StringBuilder."<init>":()V
   11:	ldc	#162; //String &
   13:	invokevirtual	#134; //Method scala/collection/mutable/StringBuilder.append:(Ljava/lang/Object;)Lscala/collection/mutable/StringBuilder;
   16:	aload_1
   17:	invokevirtual	#134; //Method scala/collection/mutable/StringBuilder.append:(Ljava/lang/Object;)Lscala/collection/mutable/StringBuilder;
   20:	ldc	#164; //String ;
   22:	invokevirtual	#134; //Method scala/collection/mutable/StringBuilder.append:(Ljava/lang/Object;)Lscala/collection/mutable/StringBuilder;
   25:	invokevirtual	#145; //Method scala/collection/mutable/StringBuilder.toString:()Ljava/lang/String;
   28:	invokevirtual	#69; //Method java/io/OutputStreamWriter.write:(Ljava/lang/String;)V
   31:	return
   32:	astore_2
   33:	new	#75; //class org/xml/sax/SAXException
   36:	dup
   37:	ldc	#77; //String Write failed
   39:	aload_2
   40:	invokespecial	#80; //Method org/xml/sax/SAXException."<init>":(Ljava/lang/String;Ljava/lang/Exception;)V
   43:	athrow
  Exception table:
   from   to  target type
     0    31    32   Class java/io/IOException

  LineNumberTable: 
   line 141: 0
   line 140: 31
   line 144: 32
   line 145: 33

  LocalVariableTable: 
   Start  Length  Slot  Name   Signature
   0      44      0    this       Lscala/xml/include/sax/XIncluder;
   0      44      1    name       Ljava/lang/String;


public void processingInstruction(java.lang.String, java.lang.String);
  Code:
   Stack=4, Locals=4, Args_size=3
   0:	aload_0
   1:	invokevirtual	#63; //Method out:()Ljava/io/OutputStreamWriter;
   4:	new	#127; //class scala/collection/mutable/StringBuilder
   7:	dup
   8:	invokespecial	#128; //Method scala/collection/mutable/StringBuilder."<init>":()V
   11:	ldc	#168; //String <?
   13:	invokevirtual	#134; //Method scala/collection/mutable/StringBuilder.append:(Ljava/lang/Object;)Lscala/collection/mutable/StringBuilder;
   16:	aload_1
   17:	invokevirtual	#134; //Method scala/collection/mutable/StringBuilder.append:(Ljava/lang/Object;)Lscala/collection/mutable/StringBuilder;
   20:	ldc	#170; //String  
   22:	invokevirtual	#134; //Method scala/collection/mutable/StringBuilder.append:(Ljava/lang/Object;)Lscala/collection/mutable/StringBuilder;
   25:	aload_2
   26:	invokevirtual	#134; //Method scala/collection/mutable/StringBuilder.append:(Ljava/lang/Object;)Lscala/collection/mutable/StringBuilder;
   29:	ldc	#172; //String ?>
   31:	invokevirtual	#134; //Method scala/collection/mutable/StringBuilder.append:(Ljava/lang/Object;)Lscala/collection/mutable/StringBuilder;
   34:	invokevirtual	#145; //Method scala/collection/mutable/StringBuilder.toString:()Ljava/lang/String;
   37:	invokevirtual	#69; //Method java/io/OutputStreamWriter.write:(Ljava/lang/String;)V
   40:	return
   41:	astore_3
   42:	new	#75; //class org/xml/sax/SAXException
   45:	dup
   46:	ldc	#77; //String Write failed
   48:	aload_3
   49:	invokespecial	#80; //Method org/xml/sax/SAXException."<init>":(Ljava/lang/String;Ljava/lang/Exception;)V
   52:	athrow
  Exception table:
   from   to  target type
     0    40    41   Class java/io/IOException

  LineNumberTable: 
   line 131: 0
   line 130: 40
   line 134: 41
   line 135: 42

  LocalVariableTable: 
   Start  Length  Slot  Name   Signature
   0      53      0    this       Lscala/xml/include/sax/XIncluder;
   0      53      1    target       Ljava/lang/String;
   0      53      2    data       Ljava/lang/String;


public void ignorableWhitespace(char[], int, int);
  Code:
   Stack=4, Locals=4, Args_size=4
   0:	aload_0
   1:	aload_1
   2:	iload_2
   3:	iload_3
   4:	invokevirtual	#178; //Method characters:([CII)V
   7:	return
  LineNumberTable: 
   line 125: 0

  LocalVariableTable: 
   Start  Length  Slot  Name   Signature
   0      8      0    this       Lscala/xml/include/sax/XIncluder;
   0      8      1    ch       [C
   0      8      2    start       I
   0      8      3    length       I


public void characters(char[], int, int);
  Code:
   Stack=4, Locals=7, Args_size=4
   0:	iconst_0
   1:	istore	5
   3:	iload	5
   5:	iload_3
   6:	if_icmpge	98
   9:	aload_1
   10:	iload_2
   11:	iload	5
   13:	iadd
   14:	caload
   15:	istore	6
   17:	iload	6
   19:	ldc	#179; //int 38
   21:	if_icmpne	36
   24:	aload_0
   25:	invokevirtual	#63; //Method out:()Ljava/io/OutputStreamWriter;
   28:	ldc	#181; //String &amp;
   30:	invokevirtual	#69; //Method java/io/OutputStreamWriter.write:(Ljava/lang/String;)V
   33:	goto	89
   36:	iload	6
   38:	ldc	#182; //int 60
   40:	if_icmpne	55
   43:	aload_0
   44:	invokevirtual	#63; //Method out:()Ljava/io/OutputStreamWriter;
   47:	ldc	#184; //String &lt;
   49:	invokevirtual	#69; //Method java/io/OutputStreamWriter.write:(Ljava/lang/String;)V
   52:	goto	89
   55:	iload	6
   57:	ldc	#185; //int 62
   59:	if_icmpne	74
   62:	aload_0
   63:	invokevirtual	#63; //Method out:()Ljava/io/OutputStreamWriter;
   66:	ldc	#187; //String &gt;
   68:	invokevirtual	#69; //Method java/io/OutputStreamWriter.write:(Ljava/lang/String;)V
   71:	goto	89
   74:	aload_0
   75:	invokevirtual	#63; //Method out:()Ljava/io/OutputStreamWriter;
   78:	getstatic	#193; //Field scala/Predef$.MODULE$:Lscala/Predef$;
   81:	iload	6
   83:	invokevirtual	#197; //Method scala/Predef$.char2int:(C)I
   86:	invokevirtual	#200; //Method java/io/OutputStreamWriter.write:(I)V
   89:	iload	5
   91:	iconst_1
   92:	iadd
   93:	istore	5
   95:	goto	3
   98:	return
   99:	astore	4
   101:	new	#75; //class org/xml/sax/SAXException
   104:	dup
   105:	ldc	#77; //String Write failed
   107:	aload	4
   109:	invokespecial	#80; //Method org/xml/sax/SAXException."<init>":(Ljava/lang/String;Ljava/lang/Exception;)V
   112:	athrow
  Exception table:
   from   to  target type
     0    98    99   Class java/io/IOException

  LineNumberTable: 
   line 106: 0
   line 107: 9
   line 108: 17
   line 109: 36
   line 113: 55
   line 114: 74
   line 115: 89
   line 106: 95
   line 105: 98
   line 119: 99
   line 120: 101

  LocalVariableTable: 
   Start  Length  Slot  Name   Signature
   0      113      0    this       Lscala/xml/include/sax/XIncluder;
   0      113      1    ch       [C
   0      113      2    start       I
   0      113      3    length       I
   3      95      5    i       I
   17      78      6    c       C


public void endElement(java.lang.String, java.lang.String, java.lang.String);
  Code:
   Stack=4, Locals=5, Args_size=4
   0:	aload_0
   1:	invokevirtual	#63; //Method out:()Ljava/io/OutputStreamWriter;
   4:	new	#127; //class scala/collection/mutable/StringBuilder
   7:	dup
   8:	invokespecial	#128; //Method scala/collection/mutable/StringBuilder."<init>":()V
   11:	ldc	#206; //String </
   13:	invokevirtual	#134; //Method scala/collection/mutable/StringBuilder.append:(Ljava/lang/Object;)Lscala/collection/mutable/StringBuilder;
   16:	aload_3
   17:	invokevirtual	#134; //Method scala/collection/mutable/StringBuilder.append:(Ljava/lang/Object;)Lscala/collection/mutable/StringBuilder;
   20:	ldc	#208; //String >
   22:	invokevirtual	#134; //Method scala/collection/mutable/StringBuilder.append:(Ljava/lang/Object;)Lscala/collection/mutable/StringBuilder;
   25:	invokevirtual	#145; //Method scala/collection/mutable/StringBuilder.toString:()Ljava/lang/String;
   28:	invokevirtual	#69; //Method java/io/OutputStreamWriter.write:(Ljava/lang/String;)V
   31:	return
   32:	astore	4
   34:	new	#75; //class org/xml/sax/SAXException
   37:	dup
   38:	ldc	#77; //String Write failed
   40:	aload	4
   42:	invokespecial	#80; //Method org/xml/sax/SAXException."<init>":(Ljava/lang/String;Ljava/lang/Exception;)V
   45:	athrow
  Exception table:
   from   to  target type
     0    31    32   Class java/io/IOException

  LineNumberTable: 
   line 94: 0
   line 93: 31
   line 97: 32
   line 98: 34

  LocalVariableTable: 
   Start  Length  Slot  Name   Signature
   0      46      0    this       Lscala/xml/include/sax/XIncluder;
   0      46      1    namespaceURI       Ljava/lang/String;
   0      46      2    localName       Ljava/lang/String;
   0      46      3    qualifiedName       Ljava/lang/String;


public void startElement(java.lang.String, java.lang.String, java.lang.String, org.xml.sax.Attributes);
  Code:
   Stack=4, Locals=8, Args_size=5
   0:	aload_0
   1:	invokevirtual	#63; //Method out:()Ljava/io/OutputStreamWriter;
   4:	new	#127; //class scala/collection/mutable/StringBuilder
   7:	dup
   8:	invokespecial	#128; //Method scala/collection/mutable/StringBuilder."<init>":()V
   11:	ldc	#215; //String <
   13:	invokevirtual	#134; //Method scala/collection/mutable/StringBuilder.append:(Ljava/lang/Object;)Lscala/collection/mutable/StringBuilder;
   16:	aload_3
   17:	invokevirtual	#134; //Method scala/collection/mutable/StringBuilder.append:(Ljava/lang/Object;)Lscala/collection/mutable/StringBuilder;
   20:	invokevirtual	#145; //Method scala/collection/mutable/StringBuilder.toString:()Ljava/lang/String;
   23:	invokevirtual	#69; //Method java/io/OutputStreamWriter.write:(Ljava/lang/String;)V
   26:	iconst_0
   27:	istore	6
   29:	iload	6
   31:	aload	4
   33:	invokeinterface	#220,  1; //InterfaceMethod org/xml/sax/Attributes.getLength:()I
   38:	if_icmpge	119
   41:	aload_0
   42:	invokevirtual	#63; //Method out:()Ljava/io/OutputStreamWriter;
   45:	ldc	#170; //String  
   47:	invokevirtual	#69; //Method java/io/OutputStreamWriter.write:(Ljava/lang/String;)V
   50:	aload_0
   51:	invokevirtual	#63; //Method out:()Ljava/io/OutputStreamWriter;
   54:	aload	4
   56:	iload	6
   58:	invokeinterface	#224,  2; //InterfaceMethod org/xml/sax/Attributes.getQName:(I)Ljava/lang/String;
   63:	invokevirtual	#69; //Method java/io/OutputStreamWriter.write:(Ljava/lang/String;)V
   66:	aload_0
   67:	invokevirtual	#63; //Method out:()Ljava/io/OutputStreamWriter;
   70:	ldc	#226; //String ='
   72:	invokevirtual	#69; //Method java/io/OutputStreamWriter.write:(Ljava/lang/String;)V
   75:	aload	4
   77:	iload	6
   79:	invokeinterface	#229,  2; //InterfaceMethod org/xml/sax/Attributes.getValue:(I)Ljava/lang/String;
   84:	astore	7
   86:	aload_0
   87:	invokevirtual	#63; //Method out:()Ljava/io/OutputStreamWriter;
   90:	getstatic	#234; //Field scala/xml/Utility$.MODULE$:Lscala/xml/Utility$;
   93:	aload	7
   95:	invokevirtual	#238; //Method scala/xml/Utility$.escape:(Ljava/lang/String;)Ljava/lang/String;
   98:	invokevirtual	#69; //Method java/io/OutputStreamWriter.write:(Ljava/lang/String;)V
   101:	aload_0
   102:	invokevirtual	#63; //Method out:()Ljava/io/OutputStreamWriter;
   105:	ldc	#240; //String '
   107:	invokevirtual	#69; //Method java/io/OutputStreamWriter.write:(Ljava/lang/String;)V
   110:	iload	6
   112:	iconst_1
   113:	iadd
   114:	istore	6
   116:	goto	29
   119:	aload_0
   120:	invokevirtual	#63; //Method out:()Ljava/io/OutputStreamWriter;
   123:	ldc	#208; //String >
   125:	invokevirtual	#69; //Method java/io/OutputStreamWriter.write:(Ljava/lang/String;)V
   128:	return
   129:	astore	5
   131:	new	#75; //class org/xml/sax/SAXException
   134:	dup
   135:	ldc	#77; //String Write failed
   137:	aload	5
   139:	invokespecial	#80; //Method org/xml/sax/SAXException."<init>":(Ljava/lang/String;Ljava/lang/Exception;)V
   142:	athrow
  Exception table:
   from   to  target type
     0   128   129   Class java/io/IOException

  LineNumberTable: 
   line 72: 0
   line 73: 26
   line 74: 41
   line 75: 50
   line 76: 66
   line 77: 75
   line 80: 86
   line 81: 101
   line 82: 110
   line 73: 116
   line 84: 119
   line 71: 128
   line 87: 129
   line 88: 131

  LocalVariableTable: 
   Start  Length  Slot  Name   Signature
   0      143      0    this       Lscala/xml/include/sax/XIncluder;
   0      143      1    namespaceURI       Ljava/lang/String;
   0      143      2    localName       Ljava/lang/String;
   0      143      3    qualifiedName       Ljava/lang/String;
   0      143      4    atts       Lorg/xml/sax/Attributes;
   29      99      6    i       I
   86      30      7    value       Ljava/lang/String;


public void endPrefixMapping(java.lang.String);
  Code:
   Stack=0, Locals=2, Args_size=2
   0:	return
  LineNumberTable: 
   line 68: 0

  LocalVariableTable: 
   Start  Length  Slot  Name   Signature
   0      1      0    this       Lscala/xml/include/sax/XIncluder;
   0      1      1    prefix       Ljava/lang/String;


public void startPrefixMapping(java.lang.String, java.lang.String);
  Code:
   Stack=0, Locals=3, Args_size=3
   0:	return
  LineNumberTable: 
   line 66: 0

  LocalVariableTable: 
   Start  Length  Slot  Name   Signature
   0      1      0    this       Lscala/xml/include/sax/XIncluder;
   0      1      1    prefix       Ljava/lang/String;
   0      1      2    uri       Ljava/lang/String;


public void endDocument();
  Code:
   Stack=4, Locals=2, Args_size=1
   0:	aload_0
   1:	invokevirtual	#63; //Method out:()Ljava/io/OutputStreamWriter;
   4:	invokevirtual	#251; //Method java/io/OutputStreamWriter.flush:()V
   7:	return
   8:	astore_1
   9:	new	#75; //class org/xml/sax/SAXException
   12:	dup
   13:	ldc	#253; //String Flush failed
   15:	aload_1
   16:	invokespecial	#80; //Method org/xml/sax/SAXException."<init>":(Ljava/lang/String;Ljava/lang/Exception;)V
   19:	athrow
  Exception table:
   from   to  target type
     0     7     8   Class java/io/IOException

  LineNumberTable: 
   line 58: 0
   line 57: 7
   line 61: 8
   line 62: 9

  LocalVariableTable: 
   Start  Length  Slot  Name   Signature
   0      20      0    this       Lscala/xml/include/sax/XIncluder;


public void startDocument();
  Code:
   Stack=4, Locals=2, Args_size=1
   0:	aload_0
   1:	invokevirtual	#63; //Method out:()Ljava/io/OutputStreamWriter;
   4:	new	#127; //class scala/collection/mutable/StringBuilder
   7:	dup
   8:	invokespecial	#128; //Method scala/collection/mutable/StringBuilder."<init>":()V
   11:	ldc_w	#256; //String <?xml version='1.0' encoding='
   14:	invokevirtual	#134; //Method scala/collection/mutable/StringBuilder.append:(Ljava/lang/Object;)Lscala/collection/mutable/StringBuilder;
   17:	aload_0
   18:	getfield	#22; //Field encoding:Ljava/lang/String;
   21:	invokevirtual	#134; //Method scala/collection/mutable/StringBuilder.append:(Ljava/lang/Object;)Lscala/collection/mutable/StringBuilder;
   24:	ldc_w	#258; //String '?>\r\n
   27:	invokevirtual	#134; //Method scala/collection/mutable/StringBuilder.append:(Ljava/lang/Object;)Lscala/collection/mutable/StringBuilder;
   30:	invokevirtual	#145; //Method scala/collection/mutable/StringBuilder.toString:()Ljava/lang/String;
   33:	invokevirtual	#69; //Method java/io/OutputStreamWriter.write:(Ljava/lang/String;)V
   36:	return
   37:	astore_1
   38:	new	#75; //class org/xml/sax/SAXException
   41:	dup
   42:	ldc	#77; //String Write failed
   44:	aload_1
   45:	invokespecial	#80; //Method org/xml/sax/SAXException."<init>":(Ljava/lang/String;Ljava/lang/Exception;)V
   48:	athrow
  Exception table:
   from   to  target type
     0    36    37   Class java/io/IOException

  LineNumberTable: 
   line 47: 0
   line 48: 4
   line 47: 11
   line 48: 17
   line 47: 33
   line 46: 36
   line 51: 37
   line 52: 38

  LocalVariableTable: 
   Start  Length  Slot  Name   Signature
   0      49      0    this       Lscala/xml/include/sax/XIncluder;


public void setDocumentLocator(org.xml.sax.Locator);
  Code:
   Stack=0, Locals=2, Args_size=2
   0:	return
  LineNumberTable: 
   line 43: 0

  LocalVariableTable: 
   Start  Length  Slot  Name   Signature
   0      1      0    this       Lscala/xml/include/sax/XIncluder;
   0      1      1    locator       Lorg/xml/sax/Locator;


public void out_$eq(java.io.OutputStreamWriter);
  Code:
   Stack=2, Locals=2, Args_size=2
   0:	aload_0
   1:	aload_1
   2:	putfield	#33; //Field out:Ljava/io/OutputStreamWriter;
   5:	return
  LineNumberTable: 
   line 41: 0


public java.io.OutputStreamWriter out();
  Code:
   Stack=1, Locals=1, Args_size=1
   0:	aload_0
   1:	getfield	#33; //Field out:Ljava/io/OutputStreamWriter;
   4:	areturn
  LineNumberTable: 
   line 41: 0


}

