Compiled from "Exception.scala"
public final class scala.util.control.Exception$$anon$5 extends scala.util.control.Exception$Catch
  SourceFile: "Exception.scala"
  Signature: length = 0x2
   00 3F 
  Scala: length = 0x
   
  InnerClass: 
   public Catch=class scala/util/control/Exception$Catch of class scala/util/control/Exception
   public Finally=class scala/util/control/Exception$Finally of class scala/util/control/Exception
   public final $anon$5=class scala/util/control/Exception$$anon$5 of class scala/util/control/Exception
   public final $anonfun$$init$$1=class scala/util/control/Exception$$anon$5$$anonfun$$init$$1 of class scala/util/control/Exception$$anon$5
  minor version: 0
  major version: 49
  Constant pool:
Asciz	SourceFile;
Asciz	Exception.scala;
Asciz	setter$1;
Asciz	Lscala/Function1;;
Asciz	newVal$1;
Asciz	Ljava/lang/Object;;
Asciz	<init>;
Asciz	(Ljava/lang/Object;Ljava/lang/Object;Lscala/Function1;)V;
Asciz	Code;
Asciz	LineNumberTable;
Asciz	scala/util/control/Exception$$anon$5;
class	scala/util/control/Exception$$anon$5
NameAndType	newVal$1:Ljava/lang/Object;
Field	scala/util/control/Exception$$anon$5.newVal$1:Ljava/lang/Object;
NameAndType	setter$1:Lscala/Function1;
Field	scala/util/control/Exception$$anon$5.setter$1:Lscala/Function1;
Asciz	scala/util/control/Exception$;
class	scala/util/control/Exception$
Asciz	MODULE$;
Asciz	Lscala/util/control/Exception$;;
NameAndType	MODULE$:Lscala/util/control/Exception$;
Field	scala/util/control/Exception$.MODULE$:Lscala/util/control/Exception$;
Asciz	nothingCatcher;
Asciz	()Lscala/PartialFunction;;
NameAndType	nothingCatcher:()Lscala/PartialFunction;
Method	scala/util/control/Exception$.nothingCatcher:()Lscala/PartialFunction;
Asciz	scala/Some;
class	scala/Some
Asciz	scala/util/control/Exception$Finally;
class	scala/util/control/Exception$Finally
Asciz	scala/util/control/Exception$$anon$5$$anonfun$$init$$1;
class	scala/util/control/Exception$$anon$5$$anonfun$$init$$1
Asciz	(Ljava/lang/Object;Lscala/Function1;)V;
NameAndType	"<init>":(Ljava/lang/Object;Lscala/Function1;)V
Method	scala/util/control/Exception$$anon$5$$anonfun$$init$$1."<init>":(Ljava/lang/Object;Lscala/Function1;)V
Asciz	(Lscala/Function0;)V;
NameAndType	"<init>":(Lscala/Function0;)V
Method	scala/util/control/Exception$Finally."<init>":(Lscala/Function0;)V
Asciz	(Ljava/lang/Object;)V;
NameAndType	"<init>":(Ljava/lang/Object;)V
Method	scala/Some."<init>":(Ljava/lang/Object;)V
Asciz	scala/util/control/Exception$Catch;
class	scala/util/control/Exception$Catch
Asciz	(Lscala/PartialFunction;Lscala/Option;)V;
NameAndType	"<init>":(Lscala/PartialFunction;Lscala/Option;)V
Method	scala/util/control/Exception$Catch."<init>":(Lscala/PartialFunction;Lscala/Option;)V
Asciz	apply;
Asciz	(Lscala/Function0;)Ljava/lang/Object;;
Asciz	scala/Function1;
class	scala/Function1
Asciz	(Ljava/lang/Object;)Ljava/lang/Object;;
NameAndType	apply:(Ljava/lang/Object;)Ljava/lang/Object;
InterfaceMethod	scala/Function1.apply:(Ljava/lang/Object;)Ljava/lang/Object;
NameAndType	apply:(Lscala/Function0;)Ljava/lang/Object;
Method	scala/util/control/Exception$Catch.apply:(Lscala/Function0;)Ljava/lang/Object;
Asciz	this;
Asciz	Lscala/util/control/Exception$$anon$5;;
Asciz	body;
Asciz	Lscala/Function0;;
Asciz	LocalVariableTable;
Asciz	<U:Ljava/lang/Object;>(Lscala/Function0<TU;>;)TU;;
Asciz	Signature;
Asciz	Lscala/util/control/Exception$Catch<Lscala/runtime/Nothing$;>;;
Asciz	Scala;
Asciz	InnerClasses;
Asciz	scala/util/control/Exception;
class	scala/util/control/Exception
Asciz	Catch;
Asciz	Finally;
Asciz	$anon$5;
Asciz	$anonfun$$init$$1;

{
private final scala.Function1 setter$1;
  Signature: Lscala/Function1;

private final java.lang.Object newVal$1;
  Signature: Ljava/lang/Object;

public scala.util.control.Exception$$anon$5(java.lang.Object, java.lang.Object, scala.Function1);
  Signature: (Ljava/lang/Object;Ljava/lang/Object;Lscala/Function1;)V
  Code:
   Stack=10, Locals=4, Args_size=4
	aload_0
	aload_2
	putfield	Field newVal$1:Ljava/lang/Object;
	aload_0
	aload_3
	putfield	Field setter$1:Lscala/Function1;
	aload_0
	getstatic	Field scala/util/control/Exception$.MODULE$:Lscala/util/control/Exception$;
	invokevirtual	Method scala/util/control/Exception$.nothingCatcher:()Lscala/PartialFunction;
	new	class scala/Some
	dup
	new	class scala/util/control/Exception$Finally
	dup
	new	class scala/util/control/Exception$$anon$5$$anonfun$$init$$1
	dup
	aload_1
	aload_3
	invokespecial	Method scala/util/control/Exception$$anon$5$$anonfun$$init$$1."<init>":(Ljava/lang/Object;Lscala/Function1;)V
	invokespecial	Method scala/util/control/Exception$Finally."<init>":(Lscala/Function0;)V
	invokespecial	Method scala/Some."<init>":(Ljava/lang/Object;)V
	invokespecial	Method scala/util/control/Exception$Catch."<init>":(Lscala/PartialFunction;Lscala/Option;)V
	return
  Labels:

public java.lang.Object apply(scala.Function0);
  Signature: (Lscala/Function0;)Ljava/lang/Object;
  Code:
   Stack=2, Locals=2, Args_size=2
	aload_0
	getfield	Field setter$1:Lscala/Function1;
	aload_0
	getfield	Field newVal$1:Ljava/lang/Object;
	invokeinterface	InterfaceMethod scala/Function1.apply:(Ljava/lang/Object;)Ljava/lang/Object;
	pop
	aload_0
	aload_1
	invokespecial	Method scala/util/control/Exception$Catch.apply:(Lscala/Function0;)Ljava/lang/Object;
	areturn
  Labels:
  LocalVariableTable: 
   Start  Length  Slot  Name   Signature
   0      20      0    this       Lscala/util/control/Exception$$anon$5;
   0      20      1    body       Lscala/Function0;

  Signature: length = 0x2
   00 3D 

}

