Compiled from "Exception.scala"
public final class scala.util.control.Exception$Catch$$anonfun$opt$1 extends java.lang.Object implements scala.Function0,scala.ScalaObject,java.io.Serializable
  SourceFile: "Exception.scala"
  Scala: length = 0x
   
  InnerClass: 
   public Catch=class scala/util/control/Exception$Catch of class scala/util/control/Exception
   public final $anonfun$opt$1=class scala/util/control/Exception$Catch$$anonfun$opt$1 of class scala/util/control/Exception$Catch
  minor version: 0
  major version: 49
  Constant pool:
Asciz	SourceFile;
Asciz	Exception.scala;
Asciz	<clinit>;
Asciz	()V;
Asciz	Code;
Asciz	serialVersionUID;
Asciz	J;
Asciz	scala/util/control/Exception$Catch$$anonfun$opt$1;
class	scala/util/control/Exception$Catch$$anonfun$opt$1
NameAndType	serialVersionUID:J
Field	scala/util/control/Exception$Catch$$anonfun$opt$1.serialVersionUID:J
Asciz	body$2;
Asciz	Lscala/Function0;;
Asciz	<init>;
Asciz	(Lscala/util/control/Exception$Catch;Lscala/Function0;)V;
Asciz	LineNumberTable;
NameAndType	body$2:Lscala/Function0;
Field	scala/util/control/Exception$Catch$$anonfun$opt$1.body$2:Lscala/Function0;
Asciz	java/lang/Object;
class	java/lang/Object
NameAndType	"<init>":()V
Method	java/lang/Object."<init>":()V
Asciz	scala/Function0$class;
class	scala/Function0$class
Asciz	$init$;
Asciz	(Lscala/Function0;)V;
NameAndType	$init$:(Lscala/Function0;)V
Method	scala/Function0$class.$init$:(Lscala/Function0;)V
Asciz	this;
Asciz	Lscala/util/control/Exception$Catch$$anonfun$opt$1;;
Asciz	$outer;
Asciz	Lscala/util/control/Exception$Catch;;
Asciz	LocalVariableTable;
Asciz	(Lscala/util/control/Exception$Catch<TT;>;)V;
Asciz	Signature;
Asciz	apply;
Asciz	()Ljava/lang/Object;;
Asciz	()Lscala/Some;;
NameAndType	apply:()Lscala/Some;
Method	scala/util/control/Exception$Catch$$anonfun$opt$1.apply:()Lscala/Some;
Asciz	scala/Some;
class	scala/Some
Asciz	scala/Function0;
class	scala/Function0
NameAndType	apply:()Ljava/lang/Object;
InterfaceMethod	scala/Function0.apply:()Ljava/lang/Object;
Asciz	(Ljava/lang/Object;)V;
NameAndType	"<init>":(Ljava/lang/Object;)V
Method	scala/Some."<init>":(Ljava/lang/Object;)V
Asciz	()Lscala/Some<TU;>;;
Asciz	toString;
Asciz	()Ljava/lang/String;;
Asciz	(Lscala/Function0;)Ljava/lang/String;;
NameAndType	toString:(Lscala/Function0;)Ljava/lang/String;
Method	scala/Function0$class.toString:(Lscala/Function0;)Ljava/lang/String;
Asciz	Scala;
Asciz	InnerClasses;
Asciz	scala/util/control/Exception$Catch;
class	scala/util/control/Exception$Catch
Asciz	scala/util/control/Exception;
class	scala/util/control/Exception
Asciz	Catch;
Asciz	$anonfun$opt$1;
Asciz	scala/ScalaObject;
class	scala/ScalaObject
Asciz	java/io/Serializable;
class	java/io/Serializable

{
public static final long serialVersionUID;
  Signature: J

private final scala.Function0 body$2;
  Signature: Lscala/Function0;

public static {};
  Signature: ()V
  Code:
   Stack=2, Locals=0, Args_size=0
	lconst_0
	putstatic	Field serialVersionUID:J
	return
  Labels:

public scala.util.control.Exception$Catch$$anonfun$opt$1(scala.util.control.Exception$Catch, scala.Function0);
  Signature: (Lscala/util/control/Exception$Catch;Lscala/Function0;)V
  Code:
   Stack=2, Locals=3, Args_size=3
	aload_0
	aload_2
	putfield	Field body$2:Lscala/Function0;
	aload_0
	invokespecial	Method java/lang/Object."<init>":()V
	aload_0
	invokestatic	Method scala/Function0$class.$init$:(Lscala/Function0;)V
	return
  Labels:
  LocalVariableTable: 
   Start  Length  Slot  Name   Signature
   0      14      0    this       Lscala/util/control/Exception$Catch$$anonfun$opt$1;
   0      14      1    $outer       Lscala/util/control/Exception$Catch;

  Signature: length = 0x2
   00 22 

public final java.lang.Object apply();
  Signature: ()Ljava/lang/Object;
  Code:
   Stack=1, Locals=1, Args_size=1
	aload_0
	invokevirtual	Method apply:()Lscala/Some;
	areturn
  Labels:

public final scala.Some apply();
  Signature: ()Lscala/Some;
  Code:
   Stack=3, Locals=1, Args_size=1
	new	class scala/Some
	dup
	aload_0
	getfield	Field body$2:Lscala/Function0;
	invokeinterface	InterfaceMethod scala/Function0.apply:()Ljava/lang/Object;
	invokespecial	Method scala/Some."<init>":(Ljava/lang/Object;)V
	areturn
  Labels:
  Signature: length = 0x2
   00 32 

public java.lang.String toString();
  Signature: ()Ljava/lang/String;
  Code:
   Stack=1, Locals=1, Args_size=1
	aload_0
	invokestatic	Method scala/Function0$class.toString:(Lscala/Function0;)Ljava/lang/String;
	areturn
  Labels:

}

