Compiled from "Exception.scala"
public final class scala.util.control.Exception$$anonfun$allCatch$1 extends java.lang.Object implements scala.PartialFunction,java.io.Serializable
  SourceFile: "Exception.scala"
  Scala: length = 0x
   
  InnerClass: 
   public final $anonfun$allCatch$1=class scala/util/control/Exception$$anonfun$allCatch$1 of class scala/util/control/Exception
  minor version: 0
  major version: 49
  Constant pool:
Asciz	SourceFile;
Asciz	Exception.scala;
Asciz	<clinit>;
Asciz	()V;
Asciz	Code;
Asciz	serialVersionUID;
Asciz	J;
Asciz	scala/util/control/Exception$$anonfun$allCatch$1;
class	scala/util/control/Exception$$anonfun$allCatch$1
NameAndType	serialVersionUID:J
Field	scala/util/control/Exception$$anonfun$allCatch$1.serialVersionUID:J
Asciz	<init>;
Asciz	LineNumberTable;
Asciz	java/lang/Object;
class	java/lang/Object
NameAndType	"<init>":()V
Method	java/lang/Object."<init>":()V
Asciz	scala/Function1$class;
class	scala/Function1$class
Asciz	$init$;
Asciz	(Lscala/Function1;)V;
NameAndType	$init$:(Lscala/Function1;)V
Method	scala/Function1$class.$init$:(Lscala/Function1;)V
Asciz	scala/PartialFunction$class;
class	scala/PartialFunction$class
Asciz	(Lscala/PartialFunction;)V;
NameAndType	$init$:(Lscala/PartialFunction;)V
Method	scala/PartialFunction$class.$init$:(Lscala/PartialFunction;)V
Asciz	apply;
Asciz	(Ljava/lang/Object;)Ljava/lang/Object;;
Asciz	java/lang/Throwable;
class	java/lang/Throwable
Asciz	(Ljava/lang/Throwable;)Ljava/lang/Object;;
NameAndType	apply:(Ljava/lang/Throwable;)Ljava/lang/Object;
Method	scala/util/control/Exception$$anonfun$allCatch$1.apply:(Ljava/lang/Throwable;)Ljava/lang/Object;
Asciz	this;
Asciz	Lscala/util/control/Exception$$anonfun$allCatch$1;;
Asciz	v1;
Asciz	Ljava/lang/Object;;
Asciz	LocalVariableTable;
Asciz	isDefinedAt;
Asciz	(Ljava/lang/Object;)Z;
Asciz	(Ljava/lang/Throwable;)Z;
NameAndType	isDefinedAt:(Ljava/lang/Throwable;)Z
Method	scala/util/control/Exception$$anonfun$allCatch$1.isDefinedAt:(Ljava/lang/Throwable;)Z
Asciz	x;
Asciz	andThen;
Asciz	(Lscala/Function1;)Lscala/Function1;;
Asciz	scala/PartialFunction;
class	scala/PartialFunction
Asciz	(Lscala/Function1;)Lscala/PartialFunction;;
NameAndType	andThen:(Lscala/Function1;)Lscala/PartialFunction;
InterfaceMethod	scala/PartialFunction.andThen:(Lscala/Function1;)Lscala/PartialFunction;
Asciz	g;
Asciz	Lscala/Function1;;
Asciz	(Ljava/lang/Throwable;)TT;;
Asciz	Signature;
Asciz	compose;
Asciz	(Lscala/Function1;Lscala/Function1;)Lscala/Function1;;
NameAndType	compose:(Lscala/Function1;Lscala/Function1;)Lscala/Function1;
Method	scala/Function1$class.compose:(Lscala/Function1;Lscala/Function1;)Lscala/Function1;
Asciz	toString;
Asciz	()Ljava/lang/String;;
Asciz	(Lscala/Function1;)Ljava/lang/String;;
NameAndType	toString:(Lscala/Function1;)Ljava/lang/String;
Method	scala/Function1$class.toString:(Lscala/Function1;)Ljava/lang/String;
Asciz	lift;
Asciz	()Lscala/Function1;;
Asciz	(Lscala/PartialFunction;)Lscala/Function1;;
NameAndType	lift:(Lscala/PartialFunction;)Lscala/Function1;
Method	scala/PartialFunction$class.lift:(Lscala/PartialFunction;)Lscala/Function1;
Asciz	(Lscala/PartialFunction;Lscala/Function1;)Lscala/PartialFunction;;
NameAndType	andThen:(Lscala/PartialFunction;Lscala/Function1;)Lscala/PartialFunction;
Method	scala/PartialFunction$class.andThen:(Lscala/PartialFunction;Lscala/Function1;)Lscala/PartialFunction;
Asciz	k;
Asciz	orElse;
Asciz	(Lscala/PartialFunction;)Lscala/PartialFunction;;
Asciz	(Lscala/PartialFunction;Lscala/PartialFunction;)Lscala/PartialFunction;;
NameAndType	orElse:(Lscala/PartialFunction;Lscala/PartialFunction;)Lscala/PartialFunction;
Method	scala/PartialFunction$class.orElse:(Lscala/PartialFunction;Lscala/PartialFunction;)Lscala/PartialFunction;
Asciz	that;
Asciz	Lscala/PartialFunction;;
Asciz	Scala;
Asciz	InnerClasses;
Asciz	scala/util/control/Exception;
class	scala/util/control/Exception
Asciz	$anonfun$allCatch$1;
Asciz	java/io/Serializable;
class	java/io/Serializable

{
public static final long serialVersionUID;
  Signature: J

public static {};
  Signature: ()V
  Code:
   Stack=2, Locals=0, Args_size=0
	lconst_0
	putstatic	Field serialVersionUID:J
	return
  Labels:

public scala.util.control.Exception$$anonfun$allCatch$1();
  Signature: ()V
  Code:
   Stack=1, Locals=1, Args_size=1
	aload_0
	invokespecial	Method java/lang/Object."<init>":()V
	aload_0
	invokestatic	Method scala/Function1$class.$init$:(Lscala/Function1;)V
	aload_0
	invokestatic	Method scala/PartialFunction$class.$init$:(Lscala/PartialFunction;)V
	return
  Labels:

public final java.lang.Object apply(java.lang.Object);
  Signature: (Ljava/lang/Object;)Ljava/lang/Object;
  Code:
   Stack=2, Locals=2, Args_size=2
	aload_0
	aload_1
	checkcast	class java/lang/Throwable
	invokevirtual	Method apply:(Ljava/lang/Throwable;)Ljava/lang/Object;
	areturn
  Labels:
  LocalVariableTable: 
   Start  Length  Slot  Name   Signature
   0      9      0    this       Lscala/util/control/Exception$$anonfun$allCatch$1;
   0      9      1    v1       Ljava/lang/Object;


public final boolean isDefinedAt(java.lang.Object);
  Signature: (Ljava/lang/Object;)Z
  Code:
   Stack=2, Locals=2, Args_size=2
	aload_0
	aload_1
	checkcast	class java/lang/Throwable
	invokevirtual	Method isDefinedAt:(Ljava/lang/Throwable;)Z
	ireturn
  Labels:
  LocalVariableTable: 
   Start  Length  Slot  Name   Signature
   0      9      0    this       Lscala/util/control/Exception$$anonfun$allCatch$1;
   0      9      1    x       Ljava/lang/Object;


public scala.Function1 andThen(scala.Function1);
  Signature: (Lscala/Function1;)Lscala/Function1;
  Code:
   Stack=2, Locals=2, Args_size=2
	aload_0
	aload_1
	invokeinterface	InterfaceMethod scala/PartialFunction.andThen:(Lscala/Function1;)Lscala/PartialFunction;
	areturn
  Labels:
  LocalVariableTable: 
   Start  Length  Slot  Name   Signature
   0      8      0    this       Lscala/util/control/Exception$$anonfun$allCatch$1;
   0      8      1    g       Lscala/Function1;


public final boolean isDefinedAt(java.lang.Throwable);
  Signature: (Ljava/lang/Throwable;)Z
  Code:
   Stack=1, Locals=2, Args_size=2
	iconst_1
	ireturn
  Labels:

public final java.lang.Object apply(java.lang.Throwable);
  Signature: (Ljava/lang/Throwable;)Ljava/lang/Object;
  Code:
   Stack=1, Locals=2, Args_size=2
	aload_1
	athrow
  Labels:
  Signature: length = 0x2
   00 38 

public scala.Function1 compose(scala.Function1);
  Signature: (Lscala/Function1;)Lscala/Function1;
  Code:
   Stack=2, Locals=2, Args_size=2
	aload_0
	aload_1
	invokestatic	Method scala/Function1$class.compose:(Lscala/Function1;Lscala/Function1;)Lscala/Function1;
	areturn
  Labels:
  LocalVariableTable: 
   Start  Length  Slot  Name   Signature
   0      6      0    this       Lscala/util/control/Exception$$anonfun$allCatch$1;
   0      6      1    g       Lscala/Function1;


public java.lang.String toString();
  Signature: ()Ljava/lang/String;
  Code:
   Stack=1, Locals=1, Args_size=1
	aload_0
	invokestatic	Method scala/Function1$class.toString:(Lscala/Function1;)Ljava/lang/String;
	areturn
  Labels:

public scala.Function1 lift();
  Signature: ()Lscala/Function1;
  Code:
   Stack=1, Locals=1, Args_size=1
	aload_0
	invokestatic	Method scala/PartialFunction$class.lift:(Lscala/PartialFunction;)Lscala/Function1;
	areturn
  Labels:

public scala.PartialFunction andThen(scala.Function1);
  Signature: (Lscala/Function1;)Lscala/PartialFunction;
  Code:
   Stack=2, Locals=2, Args_size=2
	aload_0
	aload_1
	invokestatic	Method scala/PartialFunction$class.andThen:(Lscala/PartialFunction;Lscala/Function1;)Lscala/PartialFunction;
	areturn
  Labels:
  LocalVariableTable: 
   Start  Length  Slot  Name   Signature
   0      6      0    this       Lscala/util/control/Exception$$anonfun$allCatch$1;
   0      6      1    k       Lscala/Function1;


public scala.PartialFunction orElse(scala.PartialFunction);
  Signature: (Lscala/PartialFunction;)Lscala/PartialFunction;
  Code:
   Stack=2, Locals=2, Args_size=2
	aload_0
	aload_1
	invokestatic	Method scala/PartialFunction$class.orElse:(Lscala/PartialFunction;Lscala/PartialFunction;)Lscala/PartialFunction;
	areturn
  Labels:
  LocalVariableTable: 
   Start  Length  Slot  Name   Signature
   0      6      0    this       Lscala/util/control/Exception$$anonfun$allCatch$1;
   0      6      1    that       Lscala/PartialFunction;


}

