Compiled from "Exception.scala"
public final class scala.util.control.Exception$$anon$5$$anonfun$$init$$1 extends scala.runtime.AbstractFunction0 implements java.io.Serializable
  SourceFile: "Exception.scala"
  Scala: length = 0x
   
  InnerClass: 
   public final $anonfun$$init$$1=class scala/util/control/Exception$$anon$5$$anonfun$$init$$1 of class scala/util/control/Exception$$anon$5
  minor version: 0
  major version: 49
  Constant pool:
Asciz	SourceFile;
Asciz	Exception.scala;
Asciz	<clinit>;
Asciz	()V;
Asciz	Code;
Asciz	serialVersionUID;
Asciz	J;
Asciz	scala/util/control/Exception$$anon$5$$anonfun$$init$$1;
class	scala/util/control/Exception$$anon$5$$anonfun$$init$$1
NameAndType	serialVersionUID:J
Field	scala/util/control/Exception$$anon$5$$anonfun$$init$$1.serialVersionUID:J
Asciz	setter$1;
Asciz	Lscala/Function1;;
Asciz	oldVal$1;
Asciz	Ljava/lang/Object;;
Asciz	<init>;
Asciz	(Ljava/lang/Object;Lscala/Function1;)V;
Asciz	LineNumberTable;
NameAndType	oldVal$1:Ljava/lang/Object;
Field	scala/util/control/Exception$$anon$5$$anonfun$$init$$1.oldVal$1:Ljava/lang/Object;
NameAndType	setter$1:Lscala/Function1;
Field	scala/util/control/Exception$$anon$5$$anonfun$$init$$1.setter$1:Lscala/Function1;
Asciz	scala/runtime/AbstractFunction0;
class	scala/runtime/AbstractFunction0
NameAndType	"<init>":()V
Method	scala/runtime/AbstractFunction0."<init>":()V
Asciz	apply;
Asciz	()Ljava/lang/Object;;
NameAndType	apply:()V
Method	scala/util/control/Exception$$anon$5$$anonfun$$init$$1.apply:()V
Asciz	scala/runtime/BoxedUnit;
class	scala/runtime/BoxedUnit
Asciz	UNIT;
Asciz	Lscala/runtime/BoxedUnit;;
NameAndType	UNIT:Lscala/runtime/BoxedUnit;
Field	scala/runtime/BoxedUnit.UNIT:Lscala/runtime/BoxedUnit;
Asciz	scala/Function1;
class	scala/Function1
Asciz	(Ljava/lang/Object;)Ljava/lang/Object;;
NameAndType	apply:(Ljava/lang/Object;)Ljava/lang/Object;
InterfaceMethod	scala/Function1.apply:(Ljava/lang/Object;)Ljava/lang/Object;
Asciz	Scala;
Asciz	InnerClasses;
Asciz	scala/util/control/Exception$$anon$5;
class	scala/util/control/Exception$$anon$5
Asciz	$anonfun$$init$$1;
Asciz	java/io/Serializable;
class	java/io/Serializable

{
public static final long serialVersionUID;
  Signature: J

public final scala.Function1 setter$1;
  Signature: Lscala/Function1;

public final java.lang.Object oldVal$1;
  Signature: Ljava/lang/Object;

public static {};
  Signature: ()V
  Code:
   Stack=2, Locals=0, Args_size=0
	lconst_0
	putstatic	Field serialVersionUID:J
	return
  Labels:

public scala.util.control.Exception$$anon$5$$anonfun$$init$$1(java.lang.Object, scala.Function1);
  Signature: (Ljava/lang/Object;Lscala/Function1;)V
  Code:
   Stack=2, Locals=3, Args_size=3
	aload_0
	aload_1
	putfield	Field oldVal$1:Ljava/lang/Object;
	aload_0
	aload_2
	putfield	Field setter$1:Lscala/Function1;
	aload_0
	invokespecial	Method scala/runtime/AbstractFunction0."<init>":()V
	return
  Labels:

public final java.lang.Object apply();
  Signature: ()Ljava/lang/Object;
  Code:
   Stack=1, Locals=1, Args_size=1
	aload_0
	invokevirtual	Method apply:()V
	getstatic	Field scala/runtime/BoxedUnit.UNIT:Lscala/runtime/BoxedUnit;
	areturn
  Labels:

public final void apply();
  Signature: ()V
  Code:
   Stack=2, Locals=1, Args_size=1
	aload_0
	getfield	Field setter$1:Lscala/Function1;
	aload_0
	getfield	Field oldVal$1:Ljava/lang/Object;
	invokeinterface	InterfaceMethod scala/Function1.apply:(Ljava/lang/Object;)Ljava/lang/Object;
	pop
	return
  Labels:

}

