Compiled from "Exception.scala"
public class scala.util.control.Exception$Catch extends java.lang.Object implements scala.util.control.Exception$Described,scala.ScalaObject
  SourceFile: "Exception.scala"
  Signature: length = 0x2
   00 FFFFFFD5 
  Scala: length = 0x
   
  InnerClass: 
   public Catch=class scala/util/control/Exception$Catch of class scala/util/control/Exception
   public Finally=class scala/util/control/Exception$Finally of class scala/util/control/Exception
   public abstract Described=class scala/util/control/Exception$Described of class scala/util/control/Exception
   public final $anon$2=class scala/util/control/Exception$Catch$$anon$2 of class scala/util/control/Exception$Catch
   public final $anonfun$opt$1=class scala/util/control/Exception$Catch$$anonfun$opt$1 of class scala/util/control/Exception$Catch
   public final $anonfun$apply$1=class scala/util/control/Exception$Catch$$anonfun$apply$1 of class scala/util/control/Exception$Catch
   public final $anonfun$either$1=class scala/util/control/Exception$Catch$$anonfun$either$1 of class scala/util/control/Exception$Catch
   public final $anonfun$toOption$1=class scala/util/control/Exception$Catch$$anonfun$toOption$1 of class scala/util/control/Exception$Catch
   public final $anonfun$toEither$1=class scala/util/control/Exception$Catch$$anonfun$toEither$1 of class scala/util/control/Exception$Catch
  minor version: 0
  major version: 49
  Constant pool:
Asciz	SourceFile;
Asciz	Exception.scala;
Asciz	scala$util$control$Exception$Described$$_desc;
Asciz	Ljava/lang/String;;
Asciz	name;
Asciz	fin;
Asciz	Lscala/Option;;
Asciz	Lscala/Option<Lscala/util/control/Exception$Finally;>;;
Asciz	Signature;
Asciz	pf;
Asciz	Lscala/PartialFunction;;
Asciz	Lscala/PartialFunction<Ljava/lang/Throwable;TT;>;;
Asciz	<init>;
Asciz	(Lscala/PartialFunction;Lscala/Option;)V;
Asciz	Code;
Asciz	LineNumberTable;
Asciz	scala/util/control/Exception$Catch;
class	scala/util/control/Exception$Catch
NameAndType	pf:Lscala/PartialFunction;
Field	scala/util/control/Exception$Catch.pf:Lscala/PartialFunction;
NameAndType	fin:Lscala/Option;
Field	scala/util/control/Exception$Catch.fin:Lscala/Option;
Asciz	java/lang/Object;
class	java/lang/Object
Asciz	()V;
NameAndType	"<init>":()V
Method	java/lang/Object."<init>":()V
Asciz	scala/util/control/Exception$Described$class;
class	scala/util/control/Exception$Described$class
Asciz	$init$;
Asciz	(Lscala/util/control/Exception$Described;)V;
NameAndType	$init$:(Lscala/util/control/Exception$Described;)V
Method	scala/util/control/Exception$Described$class.$init$:(Lscala/util/control/Exception$Described;)V
Asciz	Catch;
String	Catch
NameAndType	name:Ljava/lang/String;
Field	scala/util/control/Exception$Catch.name:Ljava/lang/String;
Asciz	this;
Asciz	Lscala/util/control/Exception$Catch;;
Asciz	LocalVariableTable;
Asciz	(Lscala/PartialFunction<Ljava/lang/Throwable;TT;>;Lscala/Option<Lscala/util/control/Exception$Finally;>;)V;
Asciz	gd3$1;
Asciz	(Ljava/lang/Throwable;)Z;
Asciz	()Lscala/PartialFunction;;
NameAndType	pf:()Lscala/PartialFunction;
Method	scala/util/control/Exception$Catch.pf:()Lscala/PartialFunction;
Asciz	scala/PartialFunction;
class	scala/PartialFunction
Asciz	isDefinedAt;
Asciz	(Ljava/lang/Object;)Z;
NameAndType	isDefinedAt:(Ljava/lang/Object;)Z
InterfaceMethod	scala/PartialFunction.isDefinedAt:(Ljava/lang/Object;)Z
Asciz	toEither;
Asciz	()Lscala/util/control/Exception$Catch;;
Asciz	scala/util/control/Exception$Catch$$anonfun$toEither$1;
class	scala/util/control/Exception$Catch$$anonfun$toEither$1
Asciz	(Lscala/util/control/Exception$Catch;)V;
NameAndType	"<init>":(Lscala/util/control/Exception$Catch;)V
Method	scala/util/control/Exception$Catch$$anonfun$toEither$1."<init>":(Lscala/util/control/Exception$Catch;)V
Asciz	withApply;
Asciz	(Lscala/Function1;)Lscala/util/control/Exception$Catch;;
NameAndType	withApply:(Lscala/Function1;)Lscala/util/control/Exception$Catch;
Method	scala/util/control/Exception$Catch.withApply:(Lscala/Function1;)Lscala/util/control/Exception$Catch;
Asciz	()Lscala/util/control/Exception$Catch<Lscala/Either<Ljava/lang/Throwable;TT;>;>;;
Asciz	toOption;
Asciz	scala/util/control/Exception$Catch$$anonfun$toOption$1;
class	scala/util/control/Exception$Catch$$anonfun$toOption$1
Method	scala/util/control/Exception$Catch$$anonfun$toOption$1."<init>":(Lscala/util/control/Exception$Catch;)V
Asciz	()Lscala/util/control/Exception$Catch<Lscala/Option<TT;>;>;;
Asciz	scala/util/control/Exception$Catch$$anon$2;
class	scala/util/control/Exception$Catch$$anon$2
Asciz	(Lscala/util/control/Exception$Catch;Lscala/Function1;)V;
NameAndType	"<init>":(Lscala/util/control/Exception$Catch;Lscala/Function1;)V
Method	scala/util/control/Exception$Catch$$anon$2."<init>":(Lscala/util/control/Exception$Catch;Lscala/Function1;)V
Asciz	()Lscala/Option;;
NameAndType	fin:()Lscala/Option;
Method	scala/util/control/Exception$Catch.fin:()Lscala/Option;
NameAndType	"<init>":(Lscala/PartialFunction;Lscala/Option;)V
Method	scala/util/control/Exception$Catch."<init>":(Lscala/PartialFunction;Lscala/Option;)V
Asciz	f$1;
Asciz	Lscala/Function1;;
Asciz	pf2;
Asciz	Ljava/lang/Object;;
Asciz	<U:Ljava/lang/Object;>(Lscala/Function1<Ljava/lang/Throwable;TU;>;)Lscala/util/control/Exception$Catch<TU;>;;
Asciz	either;
Asciz	(Lscala/Function0;)Lscala/Either;;
NameAndType	toEither:()Lscala/util/control/Exception$Catch;
Method	scala/util/control/Exception$Catch.toEither:()Lscala/util/control/Exception$Catch;
Asciz	scala/util/control/Exception$Catch$$anonfun$either$1;
class	scala/util/control/Exception$Catch$$anonfun$either$1
Asciz	(Lscala/util/control/Exception$Catch;Lscala/Function0;)V;
NameAndType	"<init>":(Lscala/util/control/Exception$Catch;Lscala/Function0;)V
Method	scala/util/control/Exception$Catch$$anonfun$either$1."<init>":(Lscala/util/control/Exception$Catch;Lscala/Function0;)V
Asciz	apply;
Asciz	(Lscala/Function0;)Ljava/lang/Object;;
NameAndType	apply:(Lscala/Function0;)Ljava/lang/Object;
Method	scala/util/control/Exception$Catch.apply:(Lscala/Function0;)Ljava/lang/Object;
Asciz	scala/Either;
class	scala/Either
Asciz	body$1;
Asciz	Lscala/Function0;;
Asciz	<U:Ljava/lang/Object;>(Lscala/Function0<TU;>;)Lscala/Either<Ljava/lang/Throwable;TU;>;;
Asciz	opt;
Asciz	(Lscala/Function0;)Lscala/Option;;
NameAndType	toOption:()Lscala/util/control/Exception$Catch;
Method	scala/util/control/Exception$Catch.toOption:()Lscala/util/control/Exception$Catch;
Asciz	scala/util/control/Exception$Catch$$anonfun$opt$1;
class	scala/util/control/Exception$Catch$$anonfun$opt$1
Method	scala/util/control/Exception$Catch$$anonfun$opt$1."<init>":(Lscala/util/control/Exception$Catch;Lscala/Function0;)V
Asciz	scala/Option;
class	scala/Option
Asciz	body$2;
Asciz	<U:Ljava/lang/Object;>(Lscala/Function0<TU;>;)Lscala/Option<TU;>;;
Asciz	andFinally;
Asciz	(Lscala/Function0;)Lscala/util/control/Exception$Catch;;
Asciz	scala/None$;
class	scala/None$
Asciz	MODULE$;
Asciz	Lscala/None$;;
NameAndType	MODULE$:Lscala/None$;
Field	scala/None$.MODULE$:Lscala/None$;
Asciz	equals;
NameAndType	equals:(Ljava/lang/Object;)Z
Method	java/lang/Object.equals:(Ljava/lang/Object;)Z
Asciz	scala/Some;
class	scala/Some
Asciz	scala/util/control/Exception$Finally;
class	scala/util/control/Exception$Finally
Asciz	(Lscala/Function0;)V;
NameAndType	"<init>":(Lscala/Function0;)V
Method	scala/util/control/Exception$Finally."<init>":(Lscala/Function0;)V
Asciz	(Ljava/lang/Object;)V;
NameAndType	"<init>":(Ljava/lang/Object;)V
Method	scala/Some."<init>":(Ljava/lang/Object;)V
Asciz	scala/MatchError;
class	scala/MatchError
Asciz	toString;
Asciz	()Ljava/lang/String;;
NameAndType	toString:()Ljava/lang/String;
Method	scala/Option.toString:()Ljava/lang/String;
Asciz	(Ljava/lang/String;)V;
NameAndType	"<init>":(Ljava/lang/String;)V
Method	scala/MatchError."<init>":(Ljava/lang/String;)V
Asciz	x;
NameAndType	x:Ljava/lang/Object;
Field	scala/Some.x:Ljava/lang/Object;
Asciz	and;
Asciz	(Lscala/Function0;)Lscala/util/control/Exception$Finally;;
NameAndType	and:(Lscala/Function0;)Lscala/util/control/Exception$Finally;
Method	scala/util/control/Exception$Finally.and:(Lscala/Function0;)Lscala/util/control/Exception$Finally;
Asciz	body;
Asciz	temp8;
Asciz	Lscala/Some;;
Asciz	temp9;
Asciz	Lscala/util/control/Exception$Finally;;
Asciz	temp6;
Asciz	(Lscala/Function0<Ljava/lang/Object;>;)Lscala/util/control/Exception$Catch<TT;>;;
Asciz	scala/Function0;
class	scala/Function0
Asciz	()Ljava/lang/Object;;
NameAndType	apply:()Ljava/lang/Object;
InterfaceMethod	scala/Function0.apply:()Ljava/lang/Object;
Asciz	scala/util/control/Exception$Catch$$anonfun$apply$1;
class	scala/util/control/Exception$Catch$$anonfun$apply$1
Method	scala/util/control/Exception$Catch$$anonfun$apply$1."<init>":(Lscala/util/control/Exception$Catch;)V
Asciz	map;
Asciz	(Lscala/Function1;)Lscala/Option;;
NameAndType	map:(Lscala/Function1;)Lscala/Option;
Method	scala/Option.map:(Lscala/Function1;)Lscala/Option;
NameAndType	gd3$1:(Ljava/lang/Throwable;)Z
Method	scala/util/control/Exception$Catch.gd3$1:(Ljava/lang/Throwable;)Z
Asciz	scala/Function1;
class	scala/Function1
Asciz	(Ljava/lang/Object;)Ljava/lang/Object;;
NameAndType	apply:(Ljava/lang/Object;)Ljava/lang/Object;
InterfaceMethod	scala/Function1.apply:(Ljava/lang/Object;)Ljava/lang/Object;
Asciz	java/lang/Throwable;
class	java/lang/Throwable
Method	java/lang/Throwable.toString:()Ljava/lang/String;
Asciz	exceptionResult1;
Asciz	<U:Ljava/lang/Object;>(Lscala/Function0<TU;>;)TU;;
Asciz	or;
Asciz	(Lscala/util/control/Exception$Catch;)Lscala/util/control/Exception$Catch;;
Asciz	(Lscala/PartialFunction;)Lscala/util/control/Exception$Catch;;
NameAndType	or:(Lscala/PartialFunction;)Lscala/util/control/Exception$Catch;
Method	scala/util/control/Exception$Catch.or:(Lscala/PartialFunction;)Lscala/util/control/Exception$Catch;
Asciz	other;
Asciz	<U:Ljava/lang/Object;>(Lscala/util/control/Exception$Catch<TU;>;)Lscala/util/control/Exception$Catch<TU;>;;
Asciz	orElse;
Asciz	(Lscala/PartialFunction;)Lscala/PartialFunction;;
NameAndType	orElse:(Lscala/PartialFunction;)Lscala/PartialFunction;
InterfaceMethod	scala/PartialFunction.orElse:(Lscala/PartialFunction;)Lscala/PartialFunction;
Asciz	<U:Ljava/lang/Object;>(Lscala/PartialFunction<Ljava/lang/Throwable;TU;>;)Lscala/util/control/Exception$Catch<TU;>;;
Asciz	(Lscala/PartialFunction;)V;
Asciz	(Lscala/PartialFunction<Ljava/lang/Throwable;TT;>;)V;
Asciz	()Lscala/Option<Lscala/util/control/Exception$Finally;>;;
Asciz	()Lscala/PartialFunction<Ljava/lang/Throwable;TT;>;;
Asciz	(Lscala/util/control/Exception$Described;)Ljava/lang/String;;
NameAndType	toString:(Lscala/util/control/Exception$Described;)Ljava/lang/String;
Method	scala/util/control/Exception$Described$class.toString:(Lscala/util/control/Exception$Described;)Ljava/lang/String;
Asciz	withDesc;
Asciz	(Ljava/lang/String;)Lscala/util/control/Exception$Described;;
Asciz	(Lscala/util/control/Exception$Described;Ljava/lang/String;)Lscala/util/control/Exception$Described;;
NameAndType	withDesc:(Lscala/util/control/Exception$Described;Ljava/lang/String;)Lscala/util/control/Exception$Described;
Method	scala/util/control/Exception$Described$class.withDesc:(Lscala/util/control/Exception$Described;Ljava/lang/String;)Lscala/util/control/Exception$Described;
Asciz	s;
Asciz	desc;
NameAndType	desc:(Lscala/util/control/Exception$Described;)Ljava/lang/String;
Method	scala/util/control/Exception$Described$class.desc:(Lscala/util/control/Exception$Described;)Ljava/lang/String;
Asciz	scala$util$control$Exception$Described$$_desc_$eq;
NameAndType	scala$util$control$Exception$Described$$_desc:Ljava/lang/String;
Field	scala/util/control/Exception$Catch.scala$util$control$Exception$Described$$_desc:Ljava/lang/String;
Asciz	<T:Ljava/lang/Object;>Ljava/lang/Object;Lscala/util/control/Exception$Described;Lscala/ScalaObject;;
Asciz	Scala;
Asciz	InnerClasses;
Asciz	scala/util/control/Exception;
class	scala/util/control/Exception
Asciz	Finally;
Asciz	scala/util/control/Exception$Described;
class	scala/util/control/Exception$Described
Asciz	Described;
Asciz	$anon$2;
Asciz	$anonfun$opt$1;
Asciz	$anonfun$apply$1;
Asciz	$anonfun$either$1;
Asciz	$anonfun$toOption$1;
Asciz	$anonfun$toEither$1;
Asciz	scala/ScalaObject;
class	scala/ScalaObject

{
private java.lang.String scala$util$control$Exception$Described$$_desc;
  Signature: Ljava/lang/String;

private final java.lang.String name;
  Signature: Ljava/lang/String;

private final scala.Option fin;
  Signature: Lscala/Option;
  Signature: length = 0x2
   00 08 

private final scala.PartialFunction pf;
  Signature: Lscala/PartialFunction;
  Signature: length = 0x2
   00 0C 

public scala.util.control.Exception$Catch(scala.PartialFunction, scala.Option);
  Signature: (Lscala/PartialFunction;Lscala/Option;)V
  Code:
   Stack=2, Locals=3, Args_size=3
	aload_0
	aload_1
	putfield	Field pf:Lscala/PartialFunction;
	aload_0
	aload_2
	putfield	Field fin:Lscala/Option;
	aload_0
	invokespecial	Method java/lang/Object."<init>":()V
	aload_0
	invokestatic	Method scala/util/control/Exception$Described$class.$init$:(Lscala/util/control/Exception$Described;)V
	aload_0
	ldc	String Catch
	putfield	Field name:Ljava/lang/String;
	return
  Labels:
  LocalVariableTable: 
   Start  Length  Slot  Name   Signature
   0      25      0    this       Lscala/util/control/Exception$Catch;
   0      25      1    pf       Lscala/PartialFunction;
   0      25      2    fin       Lscala/Option;

  Signature: length = 0x2
   00 29 

private final boolean gd3$1(java.lang.Throwable);
  Signature: (Ljava/lang/Throwable;)Z
  Code:
   Stack=2, Locals=2, Args_size=2
	aload_0
	invokevirtual	Method pf:()Lscala/PartialFunction;
	aload_1
	invokeinterface	InterfaceMethod scala/PartialFunction.isDefinedAt:(Ljava/lang/Object;)Z
	ireturn
  Labels:

public scala.util.control.Exception$Catch toEither();
  Signature: ()Lscala/util/control/Exception$Catch;
  Code:
   Stack=4, Locals=1, Args_size=1
	aload_0
	new	class scala/util/control/Exception$Catch$$anonfun$toEither$1
	dup
	aload_0
	invokespecial	Method scala/util/control/Exception$Catch$$anonfun$toEither$1."<init>":(Lscala/util/control/Exception$Catch;)V
	invokevirtual	Method withApply:(Lscala/Function1;)Lscala/util/control/Exception$Catch;
	areturn
  Labels:
  Signature: length = 0x2
   00 40 

public scala.util.control.Exception$Catch toOption();
  Signature: ()Lscala/util/control/Exception$Catch;
  Code:
   Stack=4, Locals=1, Args_size=1
	aload_0
	new	class scala/util/control/Exception$Catch$$anonfun$toOption$1
	dup
	aload_0
	invokespecial	Method scala/util/control/Exception$Catch$$anonfun$toOption$1."<init>":(Lscala/util/control/Exception$Catch;)V
	invokevirtual	Method withApply:(Lscala/Function1;)Lscala/util/control/Exception$Catch;
	areturn
  Labels:
  Signature: length = 0x2
   00 45 

public scala.util.control.Exception$Catch withApply(scala.Function1);
  Signature: (Lscala/Function1;)Lscala/util/control/Exception$Catch;
  Code:
   Stack=4, Locals=3, Args_size=2
	new	class scala/util/control/Exception$Catch$$anon$2
	dup
	aload_0
	aload_1
	invokespecial	Method scala/util/control/Exception$Catch$$anon$2."<init>":(Lscala/util/control/Exception$Catch;Lscala/Function1;)V
	astore_2
	new	class scala/util/control/Exception$Catch
	dup
	aload_2
	checkcast	class scala/PartialFunction
	aload_0
	invokevirtual	Method fin:()Lscala/Option;
	invokespecial	Method "<init>":(Lscala/PartialFunction;Lscala/Option;)V
	areturn
  Labels:
  LocalVariableTable: 
   Start  Length  Slot  Name   Signature
   0      26      0    this       Lscala/util/control/Exception$Catch;
   0      26      1    f$1       Lscala/Function1;
   10      15      2    pf2       Ljava/lang/Object;

  Signature: length = 0x2
   00 54 

public scala.Either either(scala.Function0);
  Signature: (Lscala/Function0;)Lscala/Either;
  Code:
   Stack=5, Locals=2, Args_size=2
	aload_0
	invokevirtual	Method toEither:()Lscala/util/control/Exception$Catch;
	new	class scala/util/control/Exception$Catch$$anonfun$either$1
	dup
	aload_0
	aload_1
	invokespecial	Method scala/util/control/Exception$Catch$$anonfun$either$1."<init>":(Lscala/util/control/Exception$Catch;Lscala/Function0;)V
	invokevirtual	Method apply:(Lscala/Function0;)Ljava/lang/Object;
	checkcast	class scala/Either
	areturn
  Labels:
  LocalVariableTable: 
   Start  Length  Slot  Name   Signature
   0      20      0    this       Lscala/util/control/Exception$Catch;
   0      20      1    body$1       Lscala/Function0;

  Signature: length = 0x2
   00 66 

public scala.Option opt(scala.Function0);
  Signature: (Lscala/Function0;)Lscala/Option;
  Code:
   Stack=5, Locals=2, Args_size=2
	aload_0
	invokevirtual	Method toOption:()Lscala/util/control/Exception$Catch;
	new	class scala/util/control/Exception$Catch$$anonfun$opt$1
	dup
	aload_0
	aload_1
	invokespecial	Method scala/util/control/Exception$Catch$$anonfun$opt$1."<init>":(Lscala/util/control/Exception$Catch;Lscala/Function0;)V
	invokevirtual	Method apply:(Lscala/Function0;)Ljava/lang/Object;
	checkcast	class scala/Option
	areturn
  Labels:
  LocalVariableTable: 
   Start  Length  Slot  Name   Signature
   0      20      0    this       Lscala/util/control/Exception$Catch;
   0      20      1    body$2       Lscala/Function0;

  Signature: length = 0x2
   00 71 

public scala.util.control.Exception$Catch andFinally(scala.Function0);
  Signature: (Lscala/Function0;)Lscala/util/control/Exception$Catch;
  Code:
   Stack=8, Locals=5, Args_size=2
	aload_0
	invokevirtual	Method fin:()Lscala/Option;
	astore	4
	getstatic	Field scala/None$.MODULE$:Lscala/None$;
	dup
	ifnonnull	l1 // aload
	pop
	aload	4
	ifnull	l2 // iconst_1
	goto	l3 // aload
l1	aload	4
	invokevirtual	Method java/lang/Object.equals:(Ljava/lang/Object;)Z
	ifeq	l3 // aload
l2	iconst_1
	ifeq	l4 // new
	new	class scala/util/control/Exception$Catch
	dup
	aload_0
	invokevirtual	Method pf:()Lscala/PartialFunction;
	new	class scala/Some
	dup
	new	class scala/util/control/Exception$Finally
	dup
	aload_1
	invokespecial	Method scala/util/control/Exception$Finally."<init>":(Lscala/Function0;)V
	invokespecial	Method scala/Some."<init>":(Ljava/lang/Object;)V
	invokespecial	Method "<init>":(Lscala/PartialFunction;Lscala/Option;)V
	goto	l5 // areturn
l4	new	class scala/MatchError
	dup
	aload	4
	invokevirtual	Method scala/Option.toString:()Ljava/lang/String;
	invokespecial	Method scala/MatchError."<init>":(Ljava/lang/String;)V
	athrow
l3	aload	4
	instanceof	class scala/Some
	ifeq	l6 // new
	aload	4
	checkcast	class scala/Some
	astore_2
	aload_2
	getfield	Field scala/Some.x:Ljava/lang/Object;
	checkcast	class scala/util/control/Exception$Finally
	astore_3
	iconst_1
	ifeq	l7 // new
	new	class scala/util/control/Exception$Catch
	dup
	aload_0
	invokevirtual	Method pf:()Lscala/PartialFunction;
	new	class scala/Some
	dup
	aload_3
	aload_1
	invokevirtual	Method scala/util/control/Exception$Finally.and:(Lscala/Function0;)Lscala/util/control/Exception$Finally;
	invokespecial	Method scala/Some."<init>":(Ljava/lang/Object;)V
	invokespecial	Method "<init>":(Lscala/PartialFunction;Lscala/Option;)V
l5	areturn
l7	new	class scala/MatchError
	dup
	aload	4
	invokevirtual	Method scala/Option.toString:()Ljava/lang/String;
	invokespecial	Method scala/MatchError."<init>":(Ljava/lang/String;)V
	athrow
l6	new	class scala/MatchError
	dup
	aload	4
	invokevirtual	Method scala/Option.toString:()Ljava/lang/String;
	invokespecial	Method scala/MatchError."<init>":(Ljava/lang/String;)V
	athrow
  Labels:
   	l1 = 22 // aload
   	l2 = 30 // iconst_1
   	l4 = 63 // new
   	l3 = 76 // aload
   	l5 = 125 // areturn
   	l7 = 126 // new
   	l6 = 139 // new
  LocalVariableTable: 
   Start  Length  Slot  Name   Signature
   0      152      0    this       Lscala/util/control/Exception$Catch;
   0      152      1    body       Lscala/Function0;
   90      35      2    temp8       Lscala/Some;
   126      13      2    temp8       Lscala/Some;
   98      27      3    temp9       Lscala/util/control/Exception$Finally;
   126      13      3    temp9       Lscala/util/control/Exception$Finally;
   6      146      4    temp6       Lscala/Option;

  Signature: length = 0x2
   00 FFFFFF9D 

public java.lang.Object apply(scala.Function0);
  Signature: (Lscala/Function0;)Ljava/lang/Object;
  Code:
   Stack=4, Locals=5, Args_size=2
	aload_1
	invokeinterface	InterfaceMethod scala/Function0.apply:()Ljava/lang/Object;
	astore_2
	aload_0
	invokevirtual	Method fin:()Lscala/Option;
	new	class scala/util/control/Exception$Catch$$anonfun$apply$1
	dup
	aload_0
	invokespecial	Method scala/util/control/Exception$Catch$$anonfun$apply$1."<init>":(Lscala/util/control/Exception$Catch;)V
	invokevirtual	Method scala/Option.map:(Lscala/Function1;)Lscala/Option;
	pop
	goto	l1 // aload_2
	astore_3
	aload_0
	aload_3
	invokespecial	Method gd3$1:(Ljava/lang/Throwable;)Z
	ifeq	l2 // iconst_1
	aload_0
	invokevirtual	Method pf:()Lscala/PartialFunction;
	aload_3
	invokeinterface	InterfaceMethod scala/Function1.apply:(Ljava/lang/Object;)Ljava/lang/Object;
	astore_2
	aload_0
	invokevirtual	Method fin:()Lscala/Option;
	new	class scala/util/control/Exception$Catch$$anonfun$apply$1
	dup
	aload_0
	invokespecial	Method scala/util/control/Exception$Catch$$anonfun$apply$1."<init>":(Lscala/util/control/Exception$Catch;)V
	invokevirtual	Method scala/Option.map:(Lscala/Function1;)Lscala/Option;
	pop
l1	aload_2
	areturn
l2	iconst_1
	ifeq	l3 // new
	aload_3
	athrow
l3	new	class scala/MatchError
	dup
	aload_3
	invokevirtual	Method java/lang/Throwable.toString:()Ljava/lang/String;
	invokespecial	Method scala/MatchError."<init>":(Ljava/lang/String;)V
	athrow
	astore	4
	aload_0
	invokevirtual	Method fin:()Lscala/Option;
	new	class scala/util/control/Exception$Catch$$anonfun$apply$1
	dup
	aload_0
	invokespecial	Method scala/util/control/Exception$Catch$$anonfun$apply$1."<init>":(Lscala/util/control/Exception$Catch;)V
	invokevirtual	Method scala/Option.map:(Lscala/Function1;)Lscala/Option;
	pop
	aload	4
	athrow
  Labels:
   	l1 = 62 // aload_2
   	l2 = 64 // iconst_1
   	l3 = 70 // new
  Exception table:
   from   to  target type
     0     7    26   any
     0     7    82   any
    26    46    82   any
    64    82    82   any
  LocalVariableTable: 
   Start  Length  Slot  Name   Signature
   0      103      0    this       Lscala/util/control/Exception$Catch;
   0      103      1    body       Lscala/Function0;
   0      63      2    exceptionResult1       Ljava/lang/Object;
   64      39      2    exceptionResult1       Ljava/lang/Object;

  Signature: length = 0x2
   00 FFFFFFB5 

public scala.util.control.Exception$Catch or(scala.util.control.Exception$Catch);
  Signature: (Lscala/util/control/Exception$Catch;)Lscala/util/control/Exception$Catch;
  Code:
   Stack=2, Locals=2, Args_size=2
	aload_0
	aload_1
	invokevirtual	Method pf:()Lscala/PartialFunction;
	invokevirtual	Method or:(Lscala/PartialFunction;)Lscala/util/control/Exception$Catch;
	areturn
  Labels:
  LocalVariableTable: 
   Start  Length  Slot  Name   Signature
   0      9      0    this       Lscala/util/control/Exception$Catch;
   0      9      1    other       Lscala/util/control/Exception$Catch;

  Signature: length = 0x2
   00 FFFFFFBC 

public scala.util.control.Exception$Catch or(scala.PartialFunction);
  Signature: (Lscala/PartialFunction;)Lscala/util/control/Exception$Catch;
  Code:
   Stack=4, Locals=2, Args_size=2
	new	class scala/util/control/Exception$Catch
	dup
	aload_0
	invokevirtual	Method pf:()Lscala/PartialFunction;
	aload_1
	invokeinterface	InterfaceMethod scala/PartialFunction.orElse:(Lscala/PartialFunction;)Lscala/PartialFunction;
	aload_0
	invokevirtual	Method fin:()Lscala/Option;
	invokespecial	Method "<init>":(Lscala/PartialFunction;Lscala/Option;)V
	areturn
  Labels:
  LocalVariableTable: 
   Start  Length  Slot  Name   Signature
   0      22      0    this       Lscala/util/control/Exception$Catch;
   0      22      1    pf2       Lscala/PartialFunction;

  Signature: length = 0x2
   00 FFFFFFC1 

public java.lang.String name();
  Signature: ()Ljava/lang/String;
  Code:
   Stack=1, Locals=1, Args_size=1
	aload_0
	getfield	Field name:Ljava/lang/String;
	areturn
  Labels:

public scala.util.control.Exception$Catch(scala.PartialFunction);
  Signature: (Lscala/PartialFunction;)V
  Code:
   Stack=3, Locals=2, Args_size=2
	aload_0
	aload_1
	getstatic	Field scala/None$.MODULE$:Lscala/None$;
	invokespecial	Method "<init>":(Lscala/PartialFunction;Lscala/Option;)V
	return
  Labels:
  LocalVariableTable: 
   Start  Length  Slot  Name   Signature
   0      9      0    this       Lscala/util/control/Exception$Catch;
   0      9      1    pf       Lscala/PartialFunction;

  Signature: length = 0x2
   00 FFFFFFC3 

public scala.Option fin();
  Signature: ()Lscala/Option;
  Code:
   Stack=1, Locals=1, Args_size=1
	aload_0
	getfield	Field fin:Lscala/Option;
	areturn
  Labels:
  Signature: length = 0x2
   00 FFFFFFC4 

public scala.PartialFunction pf();
  Signature: ()Lscala/PartialFunction;
  Code:
   Stack=1, Locals=1, Args_size=1
	aload_0
	getfield	Field pf:Lscala/PartialFunction;
	areturn
  Labels:
  Signature: length = 0x2
   00 FFFFFFC5 

public java.lang.String toString();
  Signature: ()Ljava/lang/String;
  Code:
   Stack=1, Locals=1, Args_size=1
	aload_0
	invokestatic	Method scala/util/control/Exception$Described$class.toString:(Lscala/util/control/Exception$Described;)Ljava/lang/String;
	areturn
  Labels:

public scala.util.control.Exception$Described withDesc(java.lang.String);
  Signature: (Ljava/lang/String;)Lscala/util/control/Exception$Described;
  Code:
   Stack=2, Locals=2, Args_size=2
	aload_0
	aload_1
	invokestatic	Method scala/util/control/Exception$Described$class.withDesc:(Lscala/util/control/Exception$Described;Ljava/lang/String;)Lscala/util/control/Exception$Described;
	areturn
  Labels:
  LocalVariableTable: 
   Start  Length  Slot  Name   Signature
   0      6      0    this       Lscala/util/control/Exception$Catch;
   0      6      1    s       Ljava/lang/String;


public java.lang.String desc();
  Signature: ()Ljava/lang/String;
  Code:
   Stack=1, Locals=1, Args_size=1
	aload_0
	invokestatic	Method scala/util/control/Exception$Described$class.desc:(Lscala/util/control/Exception$Described;)Ljava/lang/String;
	areturn
  Labels:

public final void scala$util$control$Exception$Described$$_desc_$eq(java.lang.String);
  Signature: (Ljava/lang/String;)V
  Code:
   Stack=2, Locals=2, Args_size=2
	aload_0
	aload_1
	putfield	Field scala$util$control$Exception$Described$$_desc:Ljava/lang/String;
	return
  Labels:

public final java.lang.String scala$util$control$Exception$Described$$_desc();
  Signature: ()Ljava/lang/String;
  Code:
   Stack=1, Locals=1, Args_size=1
	aload_0
	getfield	Field scala$util$control$Exception$Described$$_desc:Ljava/lang/String;
	areturn
  Labels:

}

