Compiled from "Exception.scala"
public final class scala.util.control.Exception$$anon$4 extends java.lang.Object implements scala.PartialFunction
  SourceFile: "Exception.scala"
  Signature: length = 0x2
   00 5C 
  Scala: length = 0x
   
  InnerClass: 
   public final $anon$4=class scala/util/control/Exception$$anon$4 of class scala/util/control/Exception
  minor version: 0
  major version: 49
  Constant pool:
Asciz	SourceFile;
Asciz	Exception.scala;
Asciz	exceptions$1;
Asciz	Lscala/collection/Seq;;
Asciz	orElse;
Asciz	(Lscala/PartialFunction;)Lscala/PartialFunction;;
Asciz	Code;
Asciz	LineNumberTable;
Asciz	scala/PartialFunction$class;
class	scala/PartialFunction$class
Asciz	(Lscala/PartialFunction;Lscala/PartialFunction;)Lscala/PartialFunction;;
NameAndType	orElse:(Lscala/PartialFunction;Lscala/PartialFunction;)Lscala/PartialFunction;
Method	scala/PartialFunction$class.orElse:(Lscala/PartialFunction;Lscala/PartialFunction;)Lscala/PartialFunction;
Asciz	this;
Asciz	Lscala/util/control/Exception$$anon$4;;
Asciz	that;
Asciz	Lscala/PartialFunction;;
Asciz	LocalVariableTable;
Asciz	andThen;
Asciz	(Lscala/Function1;)Lscala/PartialFunction;;
Asciz	(Lscala/PartialFunction;Lscala/Function1;)Lscala/PartialFunction;;
NameAndType	andThen:(Lscala/PartialFunction;Lscala/Function1;)Lscala/PartialFunction;
Method	scala/PartialFunction$class.andThen:(Lscala/PartialFunction;Lscala/Function1;)Lscala/PartialFunction;
Asciz	k;
Asciz	Lscala/Function1;;
Asciz	lift;
Asciz	()Lscala/Function1;;
Asciz	(Lscala/PartialFunction;)Lscala/Function1;;
NameAndType	lift:(Lscala/PartialFunction;)Lscala/Function1;
Method	scala/PartialFunction$class.lift:(Lscala/PartialFunction;)Lscala/Function1;
Asciz	toString;
Asciz	()Ljava/lang/String;;
Asciz	scala/Function1$class;
class	scala/Function1$class
Asciz	(Lscala/Function1;)Ljava/lang/String;;
NameAndType	toString:(Lscala/Function1;)Ljava/lang/String;
Method	scala/Function1$class.toString:(Lscala/Function1;)Ljava/lang/String;
Asciz	compose;
Asciz	(Lscala/Function1;)Lscala/Function1;;
Asciz	(Lscala/Function1;Lscala/Function1;)Lscala/Function1;;
NameAndType	compose:(Lscala/Function1;Lscala/Function1;)Lscala/Function1;
Method	scala/Function1$class.compose:(Lscala/Function1;Lscala/Function1;)Lscala/Function1;
Asciz	g;
Asciz	apply;
Asciz	(Ljava/lang/Throwable;)Lscala/runtime/Nothing$;;
Asciz	x;
Asciz	Ljava/lang/Throwable;;
Asciz	isDefinedAt;
Asciz	(Ljava/lang/Throwable;)Z;
Asciz	scala/util/control/Exception$;
class	scala/util/control/Exception$
Asciz	MODULE$;
Asciz	Lscala/util/control/Exception$;;
NameAndType	MODULE$:Lscala/util/control/Exception$;
Field	scala/util/control/Exception$.MODULE$:Lscala/util/control/Exception$;
Asciz	scala/util/control/Exception$$anon$4;
class	scala/util/control/Exception$$anon$4
NameAndType	exceptions$1:Lscala/collection/Seq;
Field	scala/util/control/Exception$$anon$4.exceptions$1:Lscala/collection/Seq;
Asciz	scala$util$control$Exception$$wouldMatch;
Asciz	(Ljava/lang/Throwable;Lscala/collection/Seq;)Z;
NameAndType	scala$util$control$Exception$$wouldMatch:(Ljava/lang/Throwable;Lscala/collection/Seq;)Z
Method	scala/util/control/Exception$.scala$util$control$Exception$$wouldMatch:(Ljava/lang/Throwable;Lscala/collection/Seq;)Z
Asciz	scala/PartialFunction;
class	scala/PartialFunction
NameAndType	andThen:(Lscala/Function1;)Lscala/PartialFunction;
InterfaceMethod	scala/PartialFunction.andThen:(Lscala/Function1;)Lscala/PartialFunction;
Asciz	(Ljava/lang/Object;)Z;
Asciz	java/lang/Throwable;
class	java/lang/Throwable
NameAndType	isDefinedAt:(Ljava/lang/Throwable;)Z
Method	scala/util/control/Exception$$anon$4.isDefinedAt:(Ljava/lang/Throwable;)Z
Asciz	Ljava/lang/Object;;
Asciz	(Ljava/lang/Object;)Ljava/lang/Object;;
NameAndType	apply:(Ljava/lang/Throwable;)Lscala/runtime/Nothing$;
Method	scala/util/control/Exception$$anon$4.apply:(Ljava/lang/Throwable;)Lscala/runtime/Nothing$;
Asciz	v1;
Asciz	<init>;
Asciz	(Lscala/collection/Seq;)V;
Asciz	java/lang/Object;
class	java/lang/Object
Asciz	()V;
NameAndType	"<init>":()V
Method	java/lang/Object."<init>":()V
Asciz	$init$;
Asciz	(Lscala/Function1;)V;
NameAndType	$init$:(Lscala/Function1;)V
Method	scala/Function1$class.$init$:(Lscala/Function1;)V
Asciz	(Lscala/PartialFunction;)V;
NameAndType	$init$:(Lscala/PartialFunction;)V
Method	scala/PartialFunction$class.$init$:(Lscala/PartialFunction;)V
Asciz	Ljava/lang/Object;Lscala/PartialFunction<Ljava/lang/Throwable;Lscala/runtime/Nothing$;>;;
Asciz	Signature;
Asciz	Scala;
Asciz	InnerClasses;
Asciz	scala/util/control/Exception;
class	scala/util/control/Exception
Asciz	$anon$4;

{
private final scala.collection.Seq exceptions$1;
  Signature: Lscala/collection/Seq;

public scala.PartialFunction orElse(scala.PartialFunction);
  Signature: (Lscala/PartialFunction;)Lscala/PartialFunction;
  Code:
   Stack=2, Locals=2, Args_size=2
	aload_0
	aload_1
	invokestatic	Method scala/PartialFunction$class.orElse:(Lscala/PartialFunction;Lscala/PartialFunction;)Lscala/PartialFunction;
	areturn
  Labels:
  LocalVariableTable: 
   Start  Length  Slot  Name   Signature
   0      6      0    this       Lscala/util/control/Exception$$anon$4;
   0      6      1    that       Lscala/PartialFunction;


public scala.PartialFunction andThen(scala.Function1);
  Signature: (Lscala/Function1;)Lscala/PartialFunction;
  Code:
   Stack=2, Locals=2, Args_size=2
	aload_0
	aload_1
	invokestatic	Method scala/PartialFunction$class.andThen:(Lscala/PartialFunction;Lscala/Function1;)Lscala/PartialFunction;
	areturn
  Labels:
  LocalVariableTable: 
   Start  Length  Slot  Name   Signature
   0      6      0    this       Lscala/util/control/Exception$$anon$4;
   0      6      1    k       Lscala/Function1;


public scala.Function1 lift();
  Signature: ()Lscala/Function1;
  Code:
   Stack=1, Locals=1, Args_size=1
	aload_0
	invokestatic	Method scala/PartialFunction$class.lift:(Lscala/PartialFunction;)Lscala/Function1;
	areturn
  Labels:

public java.lang.String toString();
  Signature: ()Ljava/lang/String;
  Code:
   Stack=1, Locals=1, Args_size=1
	aload_0
	invokestatic	Method scala/Function1$class.toString:(Lscala/Function1;)Ljava/lang/String;
	areturn
  Labels:

public scala.Function1 compose(scala.Function1);
  Signature: (Lscala/Function1;)Lscala/Function1;
  Code:
   Stack=2, Locals=2, Args_size=2
	aload_0
	aload_1
	invokestatic	Method scala/Function1$class.compose:(Lscala/Function1;Lscala/Function1;)Lscala/Function1;
	areturn
  Labels:
  LocalVariableTable: 
   Start  Length  Slot  Name   Signature
   0      6      0    this       Lscala/util/control/Exception$$anon$4;
   0      6      1    g       Lscala/Function1;


public scala.runtime.Nothing$ apply(java.lang.Throwable);
  Signature: (Ljava/lang/Throwable;)Lscala/runtime/Nothing$;
  Code:
   Stack=1, Locals=2, Args_size=2
	aload_1
	athrow
  Labels:
  LocalVariableTable: 
   Start  Length  Slot  Name   Signature
   0      2      0    this       Lscala/util/control/Exception$$anon$4;
   0      2      1    x       Ljava/lang/Throwable;


public boolean isDefinedAt(java.lang.Throwable);
  Signature: (Ljava/lang/Throwable;)Z
  Code:
   Stack=3, Locals=2, Args_size=2
	getstatic	Field scala/util/control/Exception$.MODULE$:Lscala/util/control/Exception$;
	aload_1
	aload_0
	getfield	Field exceptions$1:Lscala/collection/Seq;
	invokevirtual	Method scala/util/control/Exception$.scala$util$control$Exception$$wouldMatch:(Ljava/lang/Throwable;Lscala/collection/Seq;)Z
	ireturn
  Labels:
  LocalVariableTable: 
   Start  Length  Slot  Name   Signature
   0      12      0    this       Lscala/util/control/Exception$$anon$4;
   0      12      1    x       Ljava/lang/Throwable;


public scala.Function1 andThen(scala.Function1);
  Signature: (Lscala/Function1;)Lscala/Function1;
  Code:
   Stack=2, Locals=2, Args_size=2
	aload_0
	aload_1
	invokeinterface	InterfaceMethod scala/PartialFunction.andThen:(Lscala/Function1;)Lscala/PartialFunction;
	areturn
  Labels:
  LocalVariableTable: 
   Start  Length  Slot  Name   Signature
   0      8      0    this       Lscala/util/control/Exception$$anon$4;
   0      8      1    g       Lscala/Function1;


public boolean isDefinedAt(java.lang.Object);
  Signature: (Ljava/lang/Object;)Z
  Code:
   Stack=2, Locals=2, Args_size=2
	aload_0
	aload_1
	checkcast	class java/lang/Throwable
	invokevirtual	Method isDefinedAt:(Ljava/lang/Throwable;)Z
	ireturn
  Labels:
  LocalVariableTable: 
   Start  Length  Slot  Name   Signature
   0      9      0    this       Lscala/util/control/Exception$$anon$4;
   0      9      1    x       Ljava/lang/Object;


public java.lang.Object apply(java.lang.Object);
  Signature: (Ljava/lang/Object;)Ljava/lang/Object;
  Code:
   Stack=2, Locals=2, Args_size=2
	aload_0
	aload_1
	checkcast	class java/lang/Throwable
	invokevirtual	Method apply:(Ljava/lang/Throwable;)Lscala/runtime/Nothing$;
	athrow
  Labels:
  LocalVariableTable: 
   Start  Length  Slot  Name   Signature
   0      9      0    this       Lscala/util/control/Exception$$anon$4;
   0      9      1    v1       Ljava/lang/Object;


public scala.util.control.Exception$$anon$4(scala.collection.Seq);
  Signature: (Lscala/collection/Seq;)V
  Code:
   Stack=2, Locals=2, Args_size=2
	aload_0
	aload_1
	putfield	Field exceptions$1:Lscala/collection/Seq;
	aload_0
	invokespecial	Method java/lang/Object."<init>":()V
	aload_0
	invokestatic	Method scala/Function1$class.$init$:(Lscala/Function1;)V
	aload_0
	invokestatic	Method scala/PartialFunction$class.$init$:(Lscala/PartialFunction;)V
	return
  Labels:

}

