Compiled from "Exception.scala"
public final class scala.util.control.Exception$$anon$5 extends scala.util.control.Exception$Catch
  SourceFile: "Exception.scala"
  Signature: length = 0x2
   00 3F 
  Scala: length = 0x
   
  InnerClass: 
   public #68= #43 of #67; //Catch=class scala/util/control/Exception$Catch of class scala/util/control/Exception
   public final #69= #12 of #67; //$anon$5=class scala/util/control/Exception$$anon$5 of class scala/util/control/Exception
   public #70= #30 of #67; //Finally=class scala/util/control/Exception$Finally of class scala/util/control/Exception
   public final #71= #32 of #12; //$anonfun$$init$$1=class scala/util/control/Exception$$anon$5$$anonfun$$init$$1 of class scala/util/control/Exception$$anon$5
  minor version: 0
  major version: 49
  Constant pool:
const #1 = Asciz	SourceFile;
const #2 = Asciz	Exception.scala;
const #3 = Asciz	setter$1;
const #4 = Asciz	Lscala/Function1;;
const #5 = Asciz	newVal$1;
const #6 = Asciz	Ljava/lang/Object;;
const #7 = Asciz	<init>;
const #8 = Asciz	(Ljava/lang/Object;Ljava/lang/Object;Lscala/Function1;)V;
const #9 = Asciz	Code;
const #10 = Asciz	LineNumberTable;
const #11 = Asciz	scala/util/control/Exception$$anon$5;
const #12 = class	#11;	//  scala/util/control/Exception$$anon$5
const #13 = NameAndType	#5:#6;//  newVal$1:Ljava/lang/Object;
const #14 = Field	#12.#13;	//  scala/util/control/Exception$$anon$5.newVal$1:Ljava/lang/Object;
const #15 = NameAndType	#3:#4;//  setter$1:Lscala/Function1;
const #16 = Field	#12.#15;	//  scala/util/control/Exception$$anon$5.setter$1:Lscala/Function1;
const #17 = Asciz	scala/util/control/Exception$;
const #18 = class	#17;	//  scala/util/control/Exception$
const #19 = Asciz	MODULE$;
const #20 = Asciz	Lscala/util/control/Exception$;;
const #21 = NameAndType	#19:#20;//  MODULE$:Lscala/util/control/Exception$;
const #22 = Field	#18.#21;	//  scala/util/control/Exception$.MODULE$:Lscala/util/control/Exception$;
const #23 = Asciz	nothingCatcher;
const #24 = Asciz	()Lscala/PartialFunction;;
const #25 = NameAndType	#23:#24;//  nothingCatcher:()Lscala/PartialFunction;
const #26 = Method	#18.#25;	//  scala/util/control/Exception$.nothingCatcher:()Lscala/PartialFunction;
const #27 = Asciz	scala/Some;
const #28 = class	#27;	//  scala/Some
const #29 = Asciz	scala/util/control/Exception$Finally;
const #30 = class	#29;	//  scala/util/control/Exception$Finally
const #31 = Asciz	scala/util/control/Exception$$anon$5$$anonfun$$init$$1;
const #32 = class	#31;	//  scala/util/control/Exception$$anon$5$$anonfun$$init$$1
const #33 = Asciz	(Ljava/lang/Object;Lscala/Function1;)V;
const #34 = NameAndType	#7:#33;//  "<init>":(Ljava/lang/Object;Lscala/Function1;)V
const #35 = Method	#32.#34;	//  scala/util/control/Exception$$anon$5$$anonfun$$init$$1."<init>":(Ljava/lang/Object;Lscala/Function1;)V
const #36 = Asciz	(Lscala/Function0;)V;
const #37 = NameAndType	#7:#36;//  "<init>":(Lscala/Function0;)V
const #38 = Method	#30.#37;	//  scala/util/control/Exception$Finally."<init>":(Lscala/Function0;)V
const #39 = Asciz	(Ljava/lang/Object;)V;
const #40 = NameAndType	#7:#39;//  "<init>":(Ljava/lang/Object;)V
const #41 = Method	#28.#40;	//  scala/Some."<init>":(Ljava/lang/Object;)V
const #42 = Asciz	scala/util/control/Exception$Catch;
const #43 = class	#42;	//  scala/util/control/Exception$Catch
const #44 = Asciz	(Lscala/PartialFunction;Lscala/Option;)V;
const #45 = NameAndType	#7:#44;//  "<init>":(Lscala/PartialFunction;Lscala/Option;)V
const #46 = Method	#43.#45;	//  scala/util/control/Exception$Catch."<init>":(Lscala/PartialFunction;Lscala/Option;)V
const #47 = Asciz	apply;
const #48 = Asciz	(Lscala/Function0;)Ljava/lang/Object;;
const #49 = Asciz	scala/Function1;
const #50 = class	#49;	//  scala/Function1
const #51 = Asciz	(Ljava/lang/Object;)Ljava/lang/Object;;
const #52 = NameAndType	#47:#51;//  apply:(Ljava/lang/Object;)Ljava/lang/Object;
const #53 = InterfaceMethod	#50.#52;	//  scala/Function1.apply:(Ljava/lang/Object;)Ljava/lang/Object;
const #54 = NameAndType	#47:#48;//  apply:(Lscala/Function0;)Ljava/lang/Object;
const #55 = Method	#43.#54;	//  scala/util/control/Exception$Catch.apply:(Lscala/Function0;)Ljava/lang/Object;
const #56 = Asciz	this;
const #57 = Asciz	Lscala/util/control/Exception$$anon$5;;
const #58 = Asciz	body;
const #59 = Asciz	Lscala/Function0;;
const #60 = Asciz	LocalVariableTable;
const #61 = Asciz	<U:Ljava/lang/Object;>(Lscala/Function0<TU;>;)TU;;
const #62 = Asciz	Signature;
const #63 = Asciz	Lscala/util/control/Exception$Catch<Lscala/runtime/Nothing$;>;;
const #64 = Asciz	Scala;
const #65 = Asciz	InnerClasses;
const #66 = Asciz	scala/util/control/Exception;
const #67 = class	#66;	//  scala/util/control/Exception
const #68 = Asciz	Catch;
const #69 = Asciz	$anon$5;
const #70 = Asciz	Finally;
const #71 = Asciz	$anonfun$$init$$1;

{
public scala.util.control.Exception$$anon$5(java.lang.Object, java.lang.Object, scala.Function1);
  Code:
   Stack=10, Locals=4, Args_size=4
   0:	aload_0
   1:	aload_2
   2:	putfield	#14; //Field newVal$1:Ljava/lang/Object;
   5:	aload_0
   6:	aload_3
   7:	putfield	#16; //Field setter$1:Lscala/Function1;
   10:	aload_0
   11:	getstatic	#22; //Field scala/util/control/Exception$.MODULE$:Lscala/util/control/Exception$;
   14:	invokevirtual	#26; //Method scala/util/control/Exception$.nothingCatcher:()Lscala/PartialFunction;
   17:	new	#28; //class scala/Some
   20:	dup
   21:	new	#30; //class scala/util/control/Exception$Finally
   24:	dup
   25:	new	#32; //class scala/util/control/Exception$$anon$5$$anonfun$$init$$1
   28:	dup
   29:	aload_1
   30:	aload_3
   31:	invokespecial	#35; //Method scala/util/control/Exception$$anon$5$$anonfun$$init$$1."<init>":(Ljava/lang/Object;Lscala/Function1;)V
   34:	invokespecial	#38; //Method scala/util/control/Exception$Finally."<init>":(Lscala/Function0;)V
   37:	invokespecial	#41; //Method scala/Some."<init>":(Ljava/lang/Object;)V
   40:	invokespecial	#46; //Method scala/util/control/Exception$Catch."<init>":(Lscala/PartialFunction;Lscala/Option;)V
   43:	return
  LineNumberTable: 
   line 183: 0


public java.lang.Object apply(scala.Function0);
  Code:
   Stack=2, Locals=2, Args_size=2
   0:	aload_0
   1:	getfield	#16; //Field setter$1:Lscala/Function1;
   4:	aload_0
   5:	getfield	#14; //Field newVal$1:Ljava/lang/Object;
   8:	invokeinterface	#53,  2; //InterfaceMethod scala/Function1.apply:(Ljava/lang/Object;)Ljava/lang/Object;
   13:	pop
   14:	aload_0
   15:	aload_1
   16:	invokespecial	#55; //Method scala/util/control/Exception$Catch.apply:(Lscala/Function0;)Ljava/lang/Object;
   19:	areturn
  LineNumberTable: 
   line 185: 0
   line 186: 14

  LocalVariableTable: 
   Start  Length  Slot  Name   Signature
   0      20      0    this       Lscala/util/control/Exception$$anon$5;
   0      20      1    body       Lscala/Function0;

  Signature: length = 0x2
   00 3D 

}

