Compiled from "TailRec.scala"
public abstract class scala.util.control.TailRec extends java.lang.Object implements scala.ScalaObject
  SourceFile: "TailRec.scala"
  Signature: length = 0x2
   00 0C 
  ScalaSig: length = 0x724
   05 00 FFFFFF82 01 06 05 01 02 FFFFFF81 00 09 02 07 54 61 69
   6C 52 65 63 0A 02 03 04 01 07 63 6F 6E 74 72 6F
   6C 0A 02 05 06 01 04 75 74 69 6C 0A 01 07 01 05
   73 63 61 6C 61 03 00 15 02 0A 1E 13 03 00 0B 13
   10 02 0C 11 0D 01 0D 0A 02 0E 0F 01 04 6C 61 6E
   67 0A 01 10 01 04 6A 61 76 61 09 02 12 0D 02 06
   4F 62 6A 65 63 74 10 02 14 15 0D 01 06 09 02 16
   06 02 0B 53 63 61 6C 61 4F 62 6A 65 63 74 08 05
   18 00 FFFFFF84 00 19 01 06 3C 69 6E 69 74 3E 14 01 1A
   10 03 1B 00 1C 0D 01 02 10 02 1D 1E 0C 00 04 08
   1F 00 FFFFFF84 FFFFFF80 FFFFFF84 FFFFFFC2 00 20 02 01 41 11 02 21 24 10
   02 14 22 09 02 23 06 02 07 4E 6F 74 68 69 6E 67
   10 02 14 25 09 02 26 06 02 03 41 6E 79 07 05 28
   02 FFFFFF88 02 29 01 07 54 61 69 6C 52 65 63 10 02 1B
   2A 06 08 01 02 FFFFFF84 FFFFFF80 FFFFFF80 FFFFFF88 02 2B 13 03 2A 0B 13
   08 05 18 2A FFFFFF84 00 2D 14 01 29 06 04 2F 2A 40 30
   02 04 43 61 6C 6C 15 02 31 34 13 04 2E 32 13 35
   10 03 1B 00 33 10 02 1D 34 04 08 1F 2E FFFFFF84 FFFFFF80 FFFFFF80
   FFFFFFC2 00 20 10 02 14 36 09 02 37 06 02 07 50 72 6F
   64 75 63 74 08 08 39 2E FFFFFF82 FFFFFFCA FFFFFF80 FFFFFF84 00 3A 01 04
   72 65 73 74 15 01 3B 10 03 14 3C 32 09 02 3D 06
   02 09 46 75 6E 63 74 69 6F 6E 30 08 08 3F 2E FFFFFF82
   FFFFFF88 FFFFFFA0 FFFFFF80 04 3B 01 05 72 65 73 74 20 08 05 18 2E
   FFFFFF84 00 41 14 02 42 44 10 03 43 2E 33 0D 01 2A 08
   05 39 40 FFFFFFC0 00 3B 08 07 46 2E FFFFFF81 FFFFFF80 FFFFFF84 00 47 01
   04 63 6F 70 79 15 02 48 4B 14 02 49 4C 10 03 43
   2E 4A 10 02 1D 4B 04 08 1F 45 FFFFFF84 FFFFFF80 FFFFFF80 FFFFFFC2 00 20
   08 08 4F 39 45 FFFFFF90 FFFFFF80 FFFFFFC0 00 4D 10 03 14 3C 4E 10
   03 1B 00 4A 08 07 50 2E FFFFFF91 FFFFFF80 FFFFFF84 00 51 01 0E 63
   6F 70 79 24 64 65 66 61 75 6C 74 24 31 15 02 3B
   52 04 08 1F 4F FFFFFF84 FFFFFF80 FFFFFF80 FFFFFFC2 00 20 08 08 54 2E FFFFFF84
   FFFFFF80 FFFFFF80 FFFFFF84 20 55 01 08 68 61 73 68 43 6F 64 65 14
   01 56 10 02 14 57 09 02 58 06 02 03 49 6E 74 08
   08 5A 2E FFFFFF84 FFFFFF80 FFFFFF80 FFFFFF84 20 5B 01 08 74 6F 53 74 72
   69 6E 67 14 01 5C 10 02 5D 60 0E 02 14 5E 09 02
   5F 06 01 06 50 72 65 64 65 66 09 02 61 62 02 06
   53 74 72 69 6E 67 0A 02 5F 06 08 08 64 2E FFFFFF84 FFFFFF80
   FFFFFF80 FFFFFF84 20 65 01 06 65 71 75 61 6C 73 14 02 66 69
   10 02 14 67 09 02 68 06 02 07 42 6F 6F 6C 65 61
   6E 08 07 6A 63 FFFFFF81 FFFFFF80 FFFFFFC0 00 24 01 03 78 24 31 08
   08 6C 2E FFFFFF84 FFFFFF80 FFFFFF80 FFFFFF84 20 6D 01 0D 70 72 6F 64 75
   63 74 50 72 65 66 69 78 15 01 6E 10 02 0C 6F 09
   02 61 0D 08 08 71 2E FFFFFF84 FFFFFF80 FFFFFF80 FFFFFF84 20 72 01 0C 70
   72 6F 64 75 63 74 41 72 69 74 79 15 01 56 08 08
   74 2E FFFFFF84 FFFFFF80 FFFFFF80 FFFFFF84 20 75 01 0E 70 72 6F 64 75 63
   74 45 6C 65 6D 65 6E 74 14 02 24 76 08 07 6A 73
   FFFFFF81 FFFFFF80 FFFFFFC0 00 56 08 08 78 2E FFFFFF84 FFFFFF80 FFFFFF80 FFFFFF84 20 79 01
   08 63 61 6E 45 71 75 61 6C 14 02 66 7A 08 07 6A
   77 FFFFFF81 FFFFFF80 FFFFFFC0 00 24 28 02 2E 7C 10 02 14 7D 09 02
   7E 06 02 0C 73 65 72 69 61 6C 69 7A 61 62 6C 65
   07 09 FFFFFF81 00 2A FFFFFF81 FFFFFF80 FFFFFF88 02 FFFFFF81 01 01 04 43 61 6C
   6C 10 03 43 FFFFFF81 02 06 09 2F 2A FFFFFF84 FFFFFF81 FFFFFF80 FFFFFF88 02 FFFFFF81
   03 13 04 FFFFFF81 02 0B 13 08 07 18 FFFFFF81 02 FFFFFF84 00 FFFFFF81 05
   14 02 FFFFFF81 01 08 0A FFFFFF81 07 FFFFFF81 02 FFFFFF81 FFFFFF80 FFFFFF84 40 FFFFFF81 08
   01 05 61 70 70 6C 79 15 04 FFFFFF81 09 FFFFFF81 0C 14 04 FFFFFF81
   0A FFFFFF81 0D 10 04 43 2E FFFFFF81 0B 10 03 1D FFFFFF81 0C 04 09
   1F FFFFFF81 06 FFFFFF84 FFFFFF80 FFFFFF80 FFFFFFC2 00 20 08 07 39 FFFFFF81 06 FFFFFFC0 00
   FFFFFF81 0E 10 04 14 3C FFFFFF81 0F 10 04 1B 00 FFFFFF81 0B 08 0A
   FFFFFF81 11 FFFFFF81 02 FFFFFF81 FFFFFF80 FFFFFF84 40 FFFFFF81 12 01 07 75 6E 61 70
   70 6C 79 15 04 FFFFFF81 13 FFFFFF81 1A 14 04 FFFFFF81 14 FFFFFF81 1B 10
   05 14 FFFFFF81 15 FFFFFF81 17 09 03 FFFFFF81 16 06 02 04 53 6F 6D
   65 10 04 14 3C FFFFFF81 18 10 04 1B 00 FFFFFF81 19 10 03 1D
   FFFFFF81 1A 04 09 1F FFFFFF81 10 FFFFFF84 FFFFFF80 FFFFFF80 FFFFFFC2 00 20 08 08 FFFFFF81
   1C FFFFFF81 10 FFFFFFC0 00 FFFFFF81 1D 01 03 78 24 30 10 04 43 2E
   FFFFFF81 19 06 06 FFFFFF81 1F 2A 40 FFFFFF81 20 02 04 44 6F 6E 65
   15 04 FFFFFF81 21 FFFFFF81 24 13 06 FFFFFF81 1E FFFFFF81 22 13 35 10 04
   1B 00 FFFFFF81 23 10 03 1D FFFFFF81 24 04 09 1F FFFFFF81 1E FFFFFF84 FFFFFF80
   FFFFFF80 FFFFFFC2 00 20 08 0B FFFFFF81 26 FFFFFF81 1E FFFFFF82 FFFFFFCA FFFFFF80 FFFFFF84 00 FFFFFF81
   27 01 06 72 65 73 75 6C 74 15 02 FFFFFF81 23 08 0B FFFFFF81
   29 FFFFFF81 1E FFFFFF82 FFFFFF88 FFFFFFA0 FFFFFF80 04 FFFFFF81 23 01 07 72 65 73 75
   6C 74 20 08 07 18 FFFFFF81 1E FFFFFF84 00 FFFFFF81 2B 14 04 FFFFFF81 2C
   FFFFFF81 2D 10 05 43 FFFFFF81 1E FFFFFF81 23 08 08 FFFFFF81 26 FFFFFF81 2A FFFFFFC0
   00 FFFFFF81 23 08 09 46 FFFFFF81 1E FFFFFF81 FFFFFF80 FFFFFF84 00 FFFFFF81 2F 15 04
   FFFFFF81 30 FFFFFF81 33 14 04 FFFFFF81 31 FFFFFF81 34 10 05 43 FFFFFF81 1E FFFFFF81
   32 10 03 1D FFFFFF81 33 04 09 1F FFFFFF81 2E FFFFFF84 FFFFFF80 FFFFFF80 FFFFFFC2 00
   20 08 0C FFFFFF81 35 FFFFFF81 26 FFFFFF81 2E FFFFFF90 FFFFFF80 FFFFFFC0 00 FFFFFF81 32 08
   09 50 FFFFFF81 1E FFFFFF91 FFFFFF80 FFFFFF84 00 FFFFFF81 36 15 04 FFFFFF81 23 FFFFFF81 37
   04 09 1F FFFFFF81 35 FFFFFF84 FFFFFF80 FFFFFF80 FFFFFFC2 00 20 08 09 54 FFFFFF81 1E
   FFFFFF84 FFFFFF80 FFFFFF80 FFFFFF84 20 55 08 09 5A FFFFFF81 1E FFFFFF84 FFFFFF80 FFFFFF80 FFFFFF84 20
   5B 08 0A 64 FFFFFF81 1E FFFFFF84 FFFFFF80 FFFFFF80 FFFFFF84 20 FFFFFF81 3B 14 03 66
   FFFFFF81 3C 08 08 6A FFFFFF81 3A FFFFFF81 FFFFFF80 FFFFFFC0 00 24 08 09 6C FFFFFF81
   1E FFFFFF84 FFFFFF80 FFFFFF80 FFFFFF84 20 6D 08 09 71 FFFFFF81 1E FFFFFF84 FFFFFF80 FFFFFF80 FFFFFF84
   20 72 08 0A 74 FFFFFF81 1E FFFFFF84 FFFFFF80 FFFFFF80 FFFFFF84 20 FFFFFF81 40 14 03
   24 FFFFFF81 41 08 08 6A FFFFFF81 3F FFFFFF81 FFFFFF80 FFFFFFC0 00 56 08 0A 78
   FFFFFF81 1E FFFFFF84 FFFFFF80 FFFFFF80 FFFFFF84 20 FFFFFF81 43 14 03 66 FFFFFF81 44 08 08
   6A FFFFFF81 42 FFFFFF81 FFFFFF80 FFFFFFC0 00 24 28 03 FFFFFF81 1E 7C 07 09 FFFFFF81
   47 2A FFFFFF81 FFFFFF80 FFFFFF88 02 FFFFFF81 48 01 04 44 6F 6E 65 10 03
   43 FFFFFF81 49 06 0A FFFFFF81 1F 2A FFFFFF84 FFFFFF81 FFFFFF80 FFFFFF88 02 FFFFFF81 4A 13
   04 FFFFFF81 49 0B 13 08 07 18 FFFFFF81 49 FFFFFF84 00 FFFFFF81 4C 14 02
   FFFFFF81 48 08 0A FFFFFF81 07 FFFFFF81 49 FFFFFF81 FFFFFF80 FFFFFF84 40 FFFFFF81 4E 15 04
   FFFFFF81 4F FFFFFF81 52 14 04 FFFFFF81 50 FFFFFF81 53 10 05 43 FFFFFF81 1E FFFFFF81
   51 10 03 1D FFFFFF81 52 04 09 1F FFFFFF81 4D FFFFFF84 FFFFFF80 FFFFFF80 FFFFFFC2 00
   20 08 08 FFFFFF81 26 FFFFFF81 4D FFFFFFC0 00 FFFFFF81 51 08 0A FFFFFF81 11 FFFFFF81
   49 FFFFFF81 FFFFFF80 FFFFFF84 40 FFFFFF81 55 15 04 FFFFFF81 56 FFFFFF81 59 14 04 FFFFFF81
   57 FFFFFF81 5A 10 05 14 FFFFFF81 15 FFFFFF81 58 10 03 1D FFFFFF81 59 04
   09 1F FFFFFF81 54 FFFFFF84 FFFFFF80 FFFFFF80 FFFFFFC2 00 20 08 08 FFFFFF81 1C FFFFFF81 54
   FFFFFFC0 00 FFFFFF81 5B 10 05 43 FFFFFF81 1E FFFFFF81 58 08 07 FFFFFF81 5D 2A
   FFFFFF84 00 FFFFFF81 5E 01 08 74 61 69 6C 63 61 6C 6C 15 04
   FFFFFF81 5F FFFFFF81 62 14 04 FFFFFF81 60 FFFFFF81 63 10 04 43 2E FFFFFF81 61
   10 03 1D FFFFFF81 62 04 09 1F FFFFFF81 5C FFFFFF84 FFFFFF80 FFFFFF80 FFFFFFC2 00 20
   08 08 39 FFFFFF81 5C FFFFFF84 FFFFFFC0 00 FFFFFF81 64 10 05 14 FFFFFF81 65 FFFFFF81
   67 09 03 FFFFFF81 66 06 02 08 3C 62 79 6E 61 6D 65 3E
   10 04 1B 00 FFFFFF81 61 08 07 FFFFFF81 69 2A FFFFFF84 00 FFFFFF81 6A 01
   04 64 6F 6E 65 15 04 FFFFFF81 6B FFFFFF81 6E 14 04 FFFFFF81 6C FFFFFF81
   6F 10 05 43 FFFFFF81 1E FFFFFF81 6D 10 03 1D FFFFFF81 6E 04 09 1F
   FFFFFF81 68 FFFFFF84 FFFFFF80 FFFFFF80 FFFFFFC2 00 20 08 08 FFFFFF81 26 FFFFFF81 68 FFFFFFC0 00
   FFFFFF81 6D 08 07 FFFFFF81 71 2A FFFFFF84 00 FFFFFF81 72 01 0A 74 72 61
   6D 70 6F 6C 69 6E 65 15 04 FFFFFF81 73 FFFFFF81 75 14 04 FFFFFF81
   74 FFFFFF81 76 10 03 1D FFFFFF81 75 04 09 1F FFFFFF81 70 FFFFFF84 FFFFFF80 FFFFFF80
   FFFFFFC2 00 20 08 08 FFFFFF81 77 FFFFFF81 70 FFFFFFC0 00 FFFFFF81 78 01 04 62
   6F 64 79 10 04 1B 00 FFFFFF81 74 08 07 FFFFFF81 7A 2A FFFFFF84 00
   FFFFFF81 7B 01 04 6C 6F 6F 70 15 04 FFFFFF81 7C FFFFFF81 7E 14 04
   FFFFFF81 7D FFFFFF81 7F 10 03 1D FFFFFF81 7E 04 09 1F FFFFFF81 79 FFFFFF84 FFFFFF80
   FFFFFF80 FFFFFFC2 00 20 08 08 FFFFFF81 77 FFFFFF81 79 FFFFFFC0 00 FFFFFF82 00 10 04
   1B 00 FFFFFF81 7D 
  InnerClass: 
   public #19= #16 of #18; //Call=class scala/util/control/TailRec$Call of class scala/util/control/TailRec
   public #22= #21 of #18; //Done=class scala/util/control/TailRec$Done of class scala/util/control/TailRec
  minor version: 0
  major version: 49
  Constant pool:
const #1 = Asciz	SourceFile;
const #2 = Asciz	TailRec.scala;
const #3 = Asciz	<init>;
const #4 = Asciz	()V;
const #5 = Asciz	Code;
const #6 = Asciz	LineNumberTable;
const #7 = Asciz	java/lang/Object;
const #8 = class	#7;	//  java/lang/Object
const #9 = NameAndType	#3:#4;//  "<init>":()V
const #10 = Method	#8.#9;	//  java/lang/Object."<init>":()V
const #11 = Asciz	Signature;
const #12 = Asciz	<A:Ljava/lang/Object;>Ljava/lang/Object;Lscala/ScalaObject;;
const #13 = Asciz	ScalaSig;
const #14 = Asciz	InnerClasses;
const #15 = Asciz	scala/util/control/TailRec$Call;
const #16 = class	#15;	//  scala/util/control/TailRec$Call
const #17 = Asciz	scala/util/control/TailRec;
const #18 = class	#17;	//  scala/util/control/TailRec
const #19 = Asciz	Call;
const #20 = Asciz	scala/util/control/TailRec$Done;
const #21 = class	#20;	//  scala/util/control/TailRec$Done
const #22 = Asciz	Done;
const #23 = Asciz	scala/ScalaObject;
const #24 = class	#23;	//  scala/ScalaObject

{
public scala.util.control.TailRec();
  Code:
   Stack=1, Locals=1, Args_size=1
   0:	aload_0
   1:	invokespecial	#10; //Method java/lang/Object."<init>":()V
   4:	return
  LineNumberTable: 
   line 5: 0

  Signature: length = 0x2
   00 04 

}

