Compiled from "TailRec.scala"
public final class scala.util.control.TailRec$ extends java.lang.Object implements scala.ScalaObject
  SourceFile: "TailRec.scala"
  Scala: length = 0x
   
  InnerClass: 
   public Done=class scala/util/control/TailRec$Done of class scala/util/control/TailRec
   public Call=class scala/util/control/TailRec$Call of class scala/util/control/TailRec
  minor version: 0
  major version: 49
  Constant pool:
Asciz	SourceFile;
Asciz	TailRec.scala;
Asciz	Scala;
Asciz	MODULE$;
Asciz	Lscala/util/control/TailRec$;;
Asciz	<clinit>;
Asciz	()V;
Asciz	Code;
Asciz	scala/util/control/TailRec$;
class	scala/util/control/TailRec$
Asciz	<init>;
NameAndType	"<init>":()V
Method	scala/util/control/TailRec$."<init>":()V
Asciz	LineNumberTable;
Asciz	java/lang/Object;
class	java/lang/Object
Method	java/lang/Object."<init>":()V
NameAndType	MODULE$:Lscala/util/control/TailRec$;
Field	scala/util/control/TailRec$.MODULE$:Lscala/util/control/TailRec$;
Asciz	loop$1;
Asciz	(Lscala/util/control/TailRec;)Ljava/lang/Object;;
Asciz	scala/util/control/TailRec$Call;
class	scala/util/control/TailRec$Call
Asciz	rest;
Asciz	()Lscala/Function0;;
NameAndType	rest:()Lscala/Function0;
Method	scala/util/control/TailRec$Call.rest:()Lscala/Function0;
Asciz	scala/Function0;
class	scala/Function0
Asciz	apply;
Asciz	()Ljava/lang/Object;;
NameAndType	apply:()Ljava/lang/Object;
InterfaceMethod	scala/Function0.apply:()Ljava/lang/Object;
Asciz	scala/util/control/TailRec;
class	scala/util/control/TailRec
Asciz	scala/util/control/TailRec$Done;
class	scala/util/control/TailRec$Done
Asciz	result;
NameAndType	result:()Ljava/lang/Object;
Method	scala/util/control/TailRec$Done.result:()Ljava/lang/Object;
Asciz	scala/MatchError;
class	scala/MatchError
Asciz	toString;
Asciz	()Ljava/lang/String;;
NameAndType	toString:()Ljava/lang/String;
Method	scala/util/control/TailRec.toString:()Ljava/lang/String;
Asciz	(Ljava/lang/String;)V;
NameAndType	"<init>":(Ljava/lang/String;)V
Method	scala/MatchError."<init>":(Ljava/lang/String;)V
Asciz	this;
Asciz	body;
Asciz	Lscala/util/control/TailRec;;
Asciz	temp10;
Asciz	Lscala/util/control/TailRec$Call;;
Asciz	temp11;
Asciz	Lscala/Function0;;
Asciz	temp12;
Asciz	Lscala/util/control/TailRec$Done;;
Asciz	temp13;
Asciz	Ljava/lang/Object;;
Asciz	LocalVariableTable;
Asciz	loop;
Asciz	temp15;
Asciz	temp16;
Asciz	temp17;
Asciz	temp18;
Asciz	<A:Ljava/lang/Object;>(Lscala/util/control/TailRec<TA;>;)TA;;
Asciz	Signature;
Asciz	trampoline;
NameAndType	loop$1:(Lscala/util/control/TailRec;)Ljava/lang/Object;
Method	scala/util/control/TailRec$.loop$1:(Lscala/util/control/TailRec;)Ljava/lang/Object;
Asciz	done;
Asciz	(Ljava/lang/Object;)Lscala/util/control/TailRec$Done;;
Asciz	(Ljava/lang/Object;)V;
NameAndType	"<init>":(Ljava/lang/Object;)V
Method	scala/util/control/TailRec$Done."<init>":(Ljava/lang/Object;)V
Asciz	<A:Ljava/lang/Object;>(TA;)Lscala/util/control/TailRec$Done<TA;>;;
Asciz	tailcall;
Asciz	(Lscala/Function0;)Lscala/util/control/TailRec$Call;;
Asciz	(Lscala/Function0;)V;
NameAndType	"<init>":(Lscala/Function0;)V
Method	scala/util/control/TailRec$Call."<init>":(Lscala/Function0;)V
Asciz	<A:Ljava/lang/Object;>(Lscala/Function0<Lscala/util/control/TailRec<TA;>;>;)Lscala/util/control/TailRec$Call<TA;>;;
Asciz	InnerClasses;
Asciz	Done;
Asciz	Call;
Asciz	scala/ScalaObject;
class	scala/ScalaObject

{
public static final scala.util.control.TailRec$ MODULE$;
  Signature: Lscala/util/control/TailRec$;

public static {};
  Signature: ()V
  Code:
   Stack=1, Locals=0, Args_size=0
	new	class scala/util/control/TailRec$
	invokespecial	Method "<init>":()V
	return
  Labels:

private scala.util.control.TailRec$();
  Signature: ()V
  Code:
   Stack=1, Locals=1, Args_size=1
	aload_0
	invokespecial	Method java/lang/Object."<init>":()V
	aload_0
	putstatic	Field MODULE$:Lscala/util/control/TailRec$;
	return
  Labels:

private final java.lang.Object loop$1(scala.util.control.TailRec);
  Signature: (Lscala/util/control/TailRec;)Ljava/lang/Object;
  Code:
   Stack=3, Locals=6, Args_size=2
l2	aload_1
	instanceof	class scala/util/control/TailRec$Call
	ifeq	l1 // aload_1
	aload_1
	checkcast	class scala/util/control/TailRec$Call
	astore_2
	aload_2
	invokevirtual	Method scala/util/control/TailRec$Call.rest:()Lscala/Function0;
	astore_3
	aload_3
	invokeinterface	InterfaceMethod scala/Function0.apply:()Ljava/lang/Object;
	checkcast	class scala/util/control/TailRec
	astore_1
	goto	l2 // aload_1
l1	aload_1
	instanceof	class scala/util/control/TailRec$Done
	ifeq	l3 // new
	aload_1
	checkcast	class scala/util/control/TailRec$Done
	astore	4
	aload	4
	invokevirtual	Method scala/util/control/TailRec$Done.result:()Ljava/lang/Object;
	astore	5
	aload	5
	areturn
l3	new	class scala/MatchError
	dup
	aload_1
	invokevirtual	Method scala/util/control/TailRec.toString:()Ljava/lang/String;
	invokespecial	Method scala/MatchError."<init>":(Ljava/lang/String;)V
	athrow
  Labels:
   	l2 = 0 // aload_1
   	l1 = 30 // aload_1
   	l3 = 53 // new
  LocalVariableTable: 
   Start  Length  Slot  Name   Signature
   0      65      0    this       Lscala/util/control/TailRec$;
   0      65      1    body       Lscala/util/control/TailRec;
   12      18      2    temp10       Lscala/util/control/TailRec$Call;
   17      13      3    temp11       Lscala/Function0;
   43      9      4    temp12       Lscala/util/control/TailRec$Done;
   50      2      5    temp13       Ljava/lang/Object;


public java.lang.Object loop(scala.util.control.TailRec);
  Signature: (Lscala/util/control/TailRec;)Ljava/lang/Object;
  Code:
   Stack=3, Locals=6, Args_size=2
l2	aload_1
	instanceof	class scala/util/control/TailRec$Call
	ifeq	l1 // aload_1
	aload_1
	checkcast	class scala/util/control/TailRec$Call
	astore_2
	aload_2
	invokevirtual	Method scala/util/control/TailRec$Call.rest:()Lscala/Function0;
	astore_3
	aload_3
	invokeinterface	InterfaceMethod scala/Function0.apply:()Ljava/lang/Object;
	checkcast	class scala/util/control/TailRec
	astore_1
	goto	l2 // aload_1
l1	aload_1
	instanceof	class scala/util/control/TailRec$Done
	ifeq	l3 // new
	aload_1
	checkcast	class scala/util/control/TailRec$Done
	astore	4
	aload	4
	invokevirtual	Method scala/util/control/TailRec$Done.result:()Ljava/lang/Object;
	astore	5
	aload	5
	areturn
l3	new	class scala/MatchError
	dup
	aload_1
	invokevirtual	Method scala/util/control/TailRec.toString:()Ljava/lang/String;
	invokespecial	Method scala/MatchError."<init>":(Ljava/lang/String;)V
	athrow
  Labels:
   	l2 = 0 // aload_1
   	l1 = 30 // aload_1
   	l3 = 53 // new
  LocalVariableTable: 
   Start  Length  Slot  Name   Signature
   0      65      0    this       Lscala/util/control/TailRec$;
   0      65      1    body       Lscala/util/control/TailRec;
   12      18      2    temp15       Lscala/util/control/TailRec$Call;
   17      13      3    temp16       Lscala/Function0;
   43      9      4    temp17       Lscala/util/control/TailRec$Done;
   50      2      5    temp18       Ljava/lang/Object;

  Signature: length = 0x2
   00 43 

public java.lang.Object trampoline(scala.util.control.TailRec);
  Signature: (Lscala/util/control/TailRec;)Ljava/lang/Object;
  Code:
   Stack=2, Locals=2, Args_size=2
	aload_0
	aload_1
	invokespecial	Method loop$1:(Lscala/util/control/TailRec;)Ljava/lang/Object;
	areturn
  Labels:
  LocalVariableTable: 
   Start  Length  Slot  Name   Signature
   0      6      0    this       Lscala/util/control/TailRec$;
   0      6      1    body       Lscala/util/control/TailRec;

  Signature: length = 0x2
   00 43 

public scala.util.control.TailRec$Done done(java.lang.Object);
  Signature: (Ljava/lang/Object;)Lscala/util/control/TailRec$Done;
  Code:
   Stack=3, Locals=2, Args_size=2
	new	class scala/util/control/TailRec$Done
	dup
	aload_1
	invokespecial	Method scala/util/control/TailRec$Done."<init>":(Ljava/lang/Object;)V
	areturn
  Labels:
  LocalVariableTable: 
   Start  Length  Slot  Name   Signature
   0      9      0    this       Lscala/util/control/TailRec$;
   0      9      1    result       Ljava/lang/Object;

  Signature: length = 0x2
   00 4D 

public scala.util.control.TailRec$Call tailcall(scala.Function0);
  Signature: (Lscala/Function0;)Lscala/util/control/TailRec$Call;
  Code:
   Stack=3, Locals=2, Args_size=2
	new	class scala/util/control/TailRec$Call
	dup
	aload_1
	invokespecial	Method scala/util/control/TailRec$Call."<init>":(Lscala/Function0;)V
	areturn
  Labels:
  LocalVariableTable: 
   Start  Length  Slot  Name   Signature
   0      9      0    this       Lscala/util/control/TailRec$;
   0      9      1    rest       Lscala/Function0;

  Signature: length = 0x2
   00 53 

}

