Compiled from "TailRec.scala"
public final class scala.util.control.TailRec$ extends java.lang.Object implements scala.ScalaObject
  SourceFile: "TailRec.scala"
  Scala: length = 0x
   
  InnerClass: 
   public #85= #46 of #35; //Done=class scala/util/control/TailRec$Done of class scala/util/control/TailRec
   public #86= #23 of #35; //Call=class scala/util/control/TailRec$Call of class scala/util/control/TailRec
  minor version: 0
  major version: 49
  Constant pool:
const #1 = Asciz	SourceFile;
const #2 = Asciz	TailRec.scala;
const #3 = Asciz	Scala;
const #4 = Asciz	MODULE$;
const #5 = Asciz	Lscala/util/control/TailRec$;;
const #6 = Asciz	<clinit>;
const #7 = Asciz	()V;
const #8 = Asciz	Code;
const #9 = Asciz	scala/util/control/TailRec$;
const #10 = class	#9;	//  scala/util/control/TailRec$
const #11 = Asciz	<init>;
const #12 = NameAndType	#11:#7;//  "<init>":()V
const #13 = Method	#10.#12;	//  scala/util/control/TailRec$."<init>":()V
const #14 = Asciz	LineNumberTable;
const #15 = Asciz	java/lang/Object;
const #16 = class	#15;	//  java/lang/Object
const #17 = Method	#16.#12;	//  java/lang/Object."<init>":()V
const #18 = NameAndType	#4:#5;//  MODULE$:Lscala/util/control/TailRec$;
const #19 = Field	#10.#18;	//  scala/util/control/TailRec$.MODULE$:Lscala/util/control/TailRec$;
const #20 = Asciz	loop$1;
const #21 = Asciz	(Lscala/util/control/TailRec;)Ljava/lang/Object;;
const #22 = Asciz	scala/util/control/TailRec$Call;
const #23 = class	#22;	//  scala/util/control/TailRec$Call
const #24 = Asciz	rest;
const #25 = Asciz	()Lscala/Function0;;
const #26 = NameAndType	#24:#25;//  rest:()Lscala/Function0;
const #27 = Method	#23.#26;	//  scala/util/control/TailRec$Call.rest:()Lscala/Function0;
const #28 = Asciz	scala/Function0;
const #29 = class	#28;	//  scala/Function0
const #30 = Asciz	apply;
const #31 = Asciz	()Ljava/lang/Object;;
const #32 = NameAndType	#30:#31;//  apply:()Ljava/lang/Object;
const #33 = InterfaceMethod	#29.#32;	//  scala/Function0.apply:()Ljava/lang/Object;
const #34 = Asciz	scala/util/control/TailRec;
const #35 = class	#34;	//  scala/util/control/TailRec
const #36 = Asciz	scala/MatchError;
const #37 = class	#36;	//  scala/MatchError
const #38 = Asciz	toString;
const #39 = Asciz	()Ljava/lang/String;;
const #40 = NameAndType	#38:#39;//  toString:()Ljava/lang/String;
const #41 = Method	#35.#40;	//  scala/util/control/TailRec.toString:()Ljava/lang/String;
const #42 = Asciz	(Ljava/lang/String;)V;
const #43 = NameAndType	#11:#42;//  "<init>":(Ljava/lang/String;)V
const #44 = Method	#37.#43;	//  scala/MatchError."<init>":(Ljava/lang/String;)V
const #45 = Asciz	scala/util/control/TailRec$Done;
const #46 = class	#45;	//  scala/util/control/TailRec$Done
const #47 = Asciz	result;
const #48 = NameAndType	#47:#31;//  result:()Ljava/lang/Object;
const #49 = Method	#46.#48;	//  scala/util/control/TailRec$Done.result:()Ljava/lang/Object;
const #50 = Asciz	this;
const #51 = Asciz	body;
const #52 = Asciz	Lscala/util/control/TailRec;;
const #53 = Asciz	temp10;
const #54 = Asciz	Lscala/util/control/TailRec$Call;;
const #55 = Asciz	temp11;
const #56 = Asciz	Lscala/Function0;;
const #57 = Asciz	temp12;
const #58 = Asciz	Lscala/util/control/TailRec$Done;;
const #59 = Asciz	temp13;
const #60 = Asciz	Ljava/lang/Object;;
const #61 = Asciz	LocalVariableTable;
const #62 = Asciz	loop;
const #63 = Asciz	temp15;
const #64 = Asciz	temp16;
const #65 = Asciz	temp17;
const #66 = Asciz	temp18;
const #67 = Asciz	<A:Ljava/lang/Object;>(Lscala/util/control/TailRec<TA;>;)TA;;
const #68 = Asciz	Signature;
const #69 = Asciz	trampoline;
const #70 = NameAndType	#20:#21;//  loop$1:(Lscala/util/control/TailRec;)Ljava/lang/Object;
const #71 = Method	#10.#70;	//  scala/util/control/TailRec$.loop$1:(Lscala/util/control/TailRec;)Ljava/lang/Object;
const #72 = Asciz	done;
const #73 = Asciz	(Ljava/lang/Object;)Lscala/util/control/TailRec$Done;;
const #74 = Asciz	(Ljava/lang/Object;)V;
const #75 = NameAndType	#11:#74;//  "<init>":(Ljava/lang/Object;)V
const #76 = Method	#46.#75;	//  scala/util/control/TailRec$Done."<init>":(Ljava/lang/Object;)V
const #77 = Asciz	<A:Ljava/lang/Object;>(TA;)Lscala/util/control/TailRec$Done<TA;>;;
const #78 = Asciz	tailcall;
const #79 = Asciz	(Lscala/Function0;)Lscala/util/control/TailRec$Call;;
const #80 = Asciz	(Lscala/Function0;)V;
const #81 = NameAndType	#11:#80;//  "<init>":(Lscala/Function0;)V
const #82 = Method	#23.#81;	//  scala/util/control/TailRec$Call."<init>":(Lscala/Function0;)V
const #83 = Asciz	<A:Ljava/lang/Object;>(Lscala/Function0<Lscala/util/control/TailRec<TA;>;>;)Lscala/util/control/TailRec$Call<TA;>;;
const #84 = Asciz	InnerClasses;
const #85 = Asciz	Done;
const #86 = Asciz	Call;
const #87 = Asciz	scala/ScalaObject;
const #88 = class	#87;	//  scala/ScalaObject

{
public static final scala.util.control.TailRec$ MODULE$;

public static {};
  Code:
   Stack=1, Locals=0, Args_size=0
   0:	new	#10; //class scala/util/control/TailRec$
   3:	invokespecial	#13; //Method "<init>":()V
   6:	return

public java.lang.Object loop(scala.util.control.TailRec);
  Code:
   Stack=3, Locals=6, Args_size=2
   0:	aload_1
   1:	instanceof	#23; //class scala/util/control/TailRec$Call
   4:	ifeq	46
   7:	aload_1
   8:	checkcast	#23; //class scala/util/control/TailRec$Call
   11:	astore_2
   12:	aload_2
   13:	invokevirtual	#27; //Method scala/util/control/TailRec$Call.rest:()Lscala/Function0;
   16:	astore_3
   17:	iconst_1
   18:	ifeq	34
   21:	aload_3
   22:	invokeinterface	#33,  1; //InterfaceMethod scala/Function0.apply:()Ljava/lang/Object;
   27:	checkcast	#35; //class scala/util/control/TailRec
   30:	astore_1
   31:	goto	0
   34:	new	#37; //class scala/MatchError
   37:	dup
   38:	aload_1
   39:	invokevirtual	#41; //Method scala/util/control/TailRec.toString:()Ljava/lang/String;
   42:	invokespecial	#44; //Method scala/MatchError."<init>":(Ljava/lang/String;)V
   45:	athrow
   46:	aload_1
   47:	instanceof	#46; //class scala/util/control/TailRec$Done
   50:	ifeq	85
   53:	aload_1
   54:	checkcast	#46; //class scala/util/control/TailRec$Done
   57:	astore	4
   59:	aload	4
   61:	invokevirtual	#49; //Method scala/util/control/TailRec$Done.result:()Ljava/lang/Object;
   64:	astore	5
   66:	iconst_1
   67:	ifeq	73
   70:	aload	5
   72:	areturn
   73:	new	#37; //class scala/MatchError
   76:	dup
   77:	aload_1
   78:	invokevirtual	#41; //Method scala/util/control/TailRec.toString:()Ljava/lang/String;
   81:	invokespecial	#44; //Method scala/MatchError."<init>":(Ljava/lang/String;)V
   84:	athrow
   85:	new	#37; //class scala/MatchError
   88:	dup
   89:	aload_1
   90:	invokevirtual	#41; //Method scala/util/control/TailRec.toString:()Ljava/lang/String;
   93:	invokespecial	#44; //Method scala/MatchError."<init>":(Ljava/lang/String;)V
   96:	athrow
  LineNumberTable: 
   line 19: 0
   line 21: 17
   line 20: 21
   line 19: 34
   line 21: 66
   line 19: 72

  LocalVariableTable: 
   Start  Length  Slot  Name   Signature
   0      97      0    this       Lscala/util/control/TailRec$;
   0      97      1    body       Lscala/util/control/TailRec;
   12      34      2    temp15       Lscala/util/control/TailRec$Call;
   17      29      3    temp16       Lscala/Function0;
   59      26      4    temp17       Lscala/util/control/TailRec$Done;
   66      19      5    temp18       Ljava/lang/Object;

  Signature: length = 0x2
   00 43 

public java.lang.Object trampoline(scala.util.control.TailRec);
  Code:
   Stack=2, Locals=2, Args_size=2
   0:	aload_0
   1:	aload_1
   2:	invokespecial	#71; //Method loop$1:(Lscala/util/control/TailRec;)Ljava/lang/Object;
   5:	areturn
  LineNumberTable: 
   line 17: 0

  LocalVariableTable: 
   Start  Length  Slot  Name   Signature
   0      6      0    this       Lscala/util/control/TailRec$;
   0      6      1    body       Lscala/util/control/TailRec;

  Signature: length = 0x2
   00 43 

public scala.util.control.TailRec$Done done(java.lang.Object);
  Code:
   Stack=3, Locals=2, Args_size=2
   0:	new	#46; //class scala/util/control/TailRec$Done
   3:	dup
   4:	aload_1
   5:	invokespecial	#76; //Method scala/util/control/TailRec$Done."<init>":(Ljava/lang/Object;)V
   8:	areturn
  LineNumberTable: 
   line 11: 0

  LocalVariableTable: 
   Start  Length  Slot  Name   Signature
   0      9      0    this       Lscala/util/control/TailRec$;
   0      9      1    result       Ljava/lang/Object;

  Signature: length = 0x2
   00 4D 

public scala.util.control.TailRec$Call tailcall(scala.Function0);
  Code:
   Stack=3, Locals=2, Args_size=2
   0:	new	#23; //class scala/util/control/TailRec$Call
   3:	dup
   4:	aload_1
   5:	invokespecial	#82; //Method scala/util/control/TailRec$Call."<init>":(Lscala/Function0;)V
   8:	areturn
  LineNumberTable: 
   line 10: 0

  LocalVariableTable: 
   Start  Length  Slot  Name   Signature
   0      9      0    this       Lscala/util/control/TailRec$;
   0      9      1    rest       Lscala/Function0;

  Signature: length = 0x2
   00 53 

}

