Compiled from "TailRec.scala"
public final class scala.util.control.TailRec$Call$ extends java.lang.Object implements scala.ScalaObject
  SourceFile: "TailRec.scala"
  Scala: length = 0x
   
  InnerClass: 
   public #46= #23 of #45; //Call=class scala/util/control/TailRec$Call of class scala/util/control/TailRec
  minor version: 0
  major version: 49
  Constant pool:
const #1 = Asciz	SourceFile;
const #2 = Asciz	TailRec.scala;
const #3 = Asciz	Scala;
const #4 = Asciz	MODULE$;
const #5 = Asciz	Lscala/util/control/TailRec$Call$;;
const #6 = Asciz	<clinit>;
const #7 = Asciz	()V;
const #8 = Asciz	Code;
const #9 = Asciz	scala/util/control/TailRec$Call$;
const #10 = class	#9;	//  scala/util/control/TailRec$Call$
const #11 = Asciz	<init>;
const #12 = NameAndType	#11:#7;//  "<init>":()V
const #13 = Method	#10.#12;	//  scala/util/control/TailRec$Call$."<init>":()V
const #14 = Asciz	LineNumberTable;
const #15 = Asciz	java/lang/Object;
const #16 = class	#15;	//  java/lang/Object
const #17 = Method	#16.#12;	//  java/lang/Object."<init>":()V
const #18 = NameAndType	#4:#5;//  MODULE$:Lscala/util/control/TailRec$Call$;
const #19 = Field	#10.#18;	//  scala/util/control/TailRec$Call$.MODULE$:Lscala/util/control/TailRec$Call$;
const #20 = Asciz	apply;
const #21 = Asciz	(Lscala/Function0;)Lscala/util/control/TailRec$Call;;
const #22 = Asciz	scala/util/control/TailRec$Call;
const #23 = class	#22;	//  scala/util/control/TailRec$Call
const #24 = Asciz	(Lscala/Function0;)V;
const #25 = NameAndType	#11:#24;//  "<init>":(Lscala/Function0;)V
const #26 = Method	#23.#25;	//  scala/util/control/TailRec$Call."<init>":(Lscala/Function0;)V
const #27 = Asciz	this;
const #28 = Asciz	rest;
const #29 = Asciz	Lscala/Function0;;
const #30 = Asciz	LocalVariableTable;
const #31 = Asciz	unapply;
const #32 = Asciz	(Lscala/util/control/TailRec$Call;)Lscala/Some;;
const #33 = Asciz	scala/Some;
const #34 = class	#33;	//  scala/Some
const #35 = Asciz	()Lscala/Function0;;
const #36 = NameAndType	#28:#35;//  rest:()Lscala/Function0;
const #37 = Method	#23.#36;	//  scala/util/control/TailRec$Call.rest:()Lscala/Function0;
const #38 = Asciz	(Ljava/lang/Object;)V;
const #39 = NameAndType	#11:#38;//  "<init>":(Ljava/lang/Object;)V
const #40 = Method	#34.#39;	//  scala/Some."<init>":(Ljava/lang/Object;)V
const #41 = Asciz	x$0;
const #42 = Asciz	Lscala/util/control/TailRec$Call;;
const #43 = Asciz	InnerClasses;
const #44 = Asciz	scala/util/control/TailRec;
const #45 = class	#44;	//  scala/util/control/TailRec
const #46 = Asciz	Call;
const #47 = Asciz	scala/ScalaObject;
const #48 = class	#47;	//  scala/ScalaObject

{
public static final scala.util.control.TailRec$Call$ MODULE$;

public static {};
  Code:
   Stack=1, Locals=0, Args_size=0
   0:	new	#10; //class scala/util/control/TailRec$Call$
   3:	invokespecial	#13; //Method "<init>":()V
   6:	return

public scala.util.control.TailRec$Call$();
  Code:
   Stack=1, Locals=1, Args_size=1
   0:	aload_0
   1:	invokespecial	#17; //Method java/lang/Object."<init>":()V
   4:	aload_0
   5:	putstatic	#19; //Field MODULE$:Lscala/util/control/TailRec$Call$;
   8:	return
  LineNumberTable: 
   line 7: 0


public scala.util.control.TailRec$Call apply(scala.Function0);
  Code:
   Stack=3, Locals=2, Args_size=2
   0:	new	#23; //class scala/util/control/TailRec$Call
   3:	dup
   4:	aload_1
   5:	invokespecial	#26; //Method scala/util/control/TailRec$Call."<init>":(Lscala/Function0;)V
   8:	areturn
  LineNumberTable: 
   line 7: 0

  LocalVariableTable: 
   Start  Length  Slot  Name   Signature
   0      9      0    this       Lscala/util/control/TailRec$Call$;
   0      9      1    rest       Lscala/Function0;


public scala.Some unapply(scala.util.control.TailRec$Call);
  Code:
   Stack=3, Locals=2, Args_size=2
   0:	new	#34; //class scala/Some
   3:	dup
   4:	aload_1
   5:	invokevirtual	#37; //Method scala/util/control/TailRec$Call.rest:()Lscala/Function0;
   8:	invokespecial	#40; //Method scala/Some."<init>":(Ljava/lang/Object;)V
   11:	areturn
  LineNumberTable: 
   line 7: 0

  LocalVariableTable: 
   Start  Length  Slot  Name   Signature
   0      12      0    this       Lscala/util/control/TailRec$Call$;
   0      12      1    x$0       Lscala/util/control/TailRec$Call;


}

