Compiled from "BaseBerrySethi.scala"
public final class scala.util.automata.BaseBerrySethi$$anonfun$doComp$3 extends java.lang.Object implements scala.Function2,scala.ScalaObject,java.io.Serializable
  SourceFile: "BaseBerrySethi.scala"
  Scala: length = 0x
   
  InnerClass: 
   public final $anonfun$doComp$3=class scala/util/automata/BaseBerrySethi$$anonfun$doComp$3 of class scala/util/automata/BaseBerrySethi
  minor version: 0
  major version: 49
  Constant pool:
Asciz	SourceFile;
Asciz	BaseBerrySethi.scala;
Asciz	<clinit>;
Asciz	()V;
Asciz	Code;
Asciz	serialVersionUID;
Asciz	J;
Asciz	scala/util/automata/BaseBerrySethi$$anonfun$doComp$3;
class	scala/util/automata/BaseBerrySethi$$anonfun$doComp$3
NameAndType	serialVersionUID:J
Field	scala/util/automata/BaseBerrySethi$$anonfun$doComp$3.serialVersionUID:J
Asciz	<init>;
Asciz	(Lscala/util/automata/BaseBerrySethi;)V;
Asciz	LineNumberTable;
Asciz	java/lang/Object;
class	java/lang/Object
NameAndType	"<init>":()V
Method	java/lang/Object."<init>":()V
Asciz	scala/Function2$class;
class	scala/Function2$class
Asciz	$init$;
Asciz	(Lscala/Function2;)V;
NameAndType	$init$:(Lscala/Function2;)V
Method	scala/Function2$class.$init$:(Lscala/Function2;)V
Asciz	this;
Asciz	Lscala/util/automata/BaseBerrySethi$$anonfun$doComp$3;;
Asciz	$outer;
Asciz	Lscala/util/automata/BaseBerrySethi;;
Asciz	LocalVariableTable;
Asciz	apply;
Asciz	(Ljava/lang/Object;Ljava/lang/Object;)Ljava/lang/Object;;
Asciz	scala/collection/immutable/Set;
class	scala/collection/immutable/Set
Asciz	(Lscala/collection/immutable/Set;Lscala/collection/immutable/Set;)Lscala/collection/immutable/Set;;
NameAndType	apply:(Lscala/collection/immutable/Set;Lscala/collection/immutable/Set;)Lscala/collection/immutable/Set;
Method	scala/util/automata/BaseBerrySethi$$anonfun$doComp$3.apply:(Lscala/collection/immutable/Set;Lscala/collection/immutable/Set;)Lscala/collection/immutable/Set;
Asciz	v1;
Asciz	Ljava/lang/Object;;
Asciz	v2;
Asciz	scala/collection/generic/Addable;
class	scala/collection/generic/Addable
Asciz	$plus$plus;
Asciz	(Lscala/collection/Traversable;)Lscala/collection/generic/Addable;;
NameAndType	$plus$plus:(Lscala/collection/Traversable;)Lscala/collection/generic/Addable;
InterfaceMethod	scala/collection/generic/Addable.$plus$plus:(Lscala/collection/Traversable;)Lscala/collection/generic/Addable;
Asciz	(Lscala/collection/immutable/Set<Ljava/lang/Integer;>;Lscala/collection/immutable/Set<Ljava/lang/Integer;>;)Lscala/collection/immutable/Set<Ljava/lang/Integer;>;;
Asciz	Signature;
Asciz	curry;
Asciz	()Lscala/Function1;;
Asciz	(Lscala/Function2;)Lscala/Function1;;
NameAndType	curry:(Lscala/Function2;)Lscala/Function1;
Method	scala/Function2$class.curry:(Lscala/Function2;)Lscala/Function1;
Asciz	toString;
Asciz	()Ljava/lang/String;;
Asciz	(Lscala/Function2;)Ljava/lang/String;;
NameAndType	toString:(Lscala/Function2;)Ljava/lang/String;
Method	scala/Function2$class.toString:(Lscala/Function2;)Ljava/lang/String;
Asciz	Scala;
Asciz	InnerClasses;
Asciz	scala/util/automata/BaseBerrySethi;
class	scala/util/automata/BaseBerrySethi
Asciz	$anonfun$doComp$3;
Asciz	scala/Function2;
class	scala/Function2
Asciz	scala/ScalaObject;
class	scala/ScalaObject
Asciz	java/io/Serializable;
class	java/io/Serializable

{
public static final long serialVersionUID;
  Signature: J

public static {};
  Signature: ()V
  Code:
   Stack=2, Locals=0, Args_size=0
	lconst_0
	putstatic	Field serialVersionUID:J
	return
  Labels:

public scala.util.automata.BaseBerrySethi$$anonfun$doComp$3(scala.util.automata.BaseBerrySethi);
  Signature: (Lscala/util/automata/BaseBerrySethi;)V
  Code:
   Stack=1, Locals=2, Args_size=2
	aload_0
	invokespecial	Method java/lang/Object."<init>":()V
	aload_0
	invokestatic	Method scala/Function2$class.$init$:(Lscala/Function2;)V
	return
  Labels:
  LocalVariableTable: 
   Start  Length  Slot  Name   Signature
   0      9      0    this       Lscala/util/automata/BaseBerrySethi$$anonfun$doComp$3;
   0      9      1    $outer       Lscala/util/automata/BaseBerrySethi;


public final java.lang.Object apply(java.lang.Object, java.lang.Object);
  Signature: (Ljava/lang/Object;Ljava/lang/Object;)Ljava/lang/Object;
  Code:
   Stack=3, Locals=3, Args_size=3
	aload_0
	aload_1
	checkcast	class scala/collection/immutable/Set
	aload_2
	checkcast	class scala/collection/immutable/Set
	invokevirtual	Method apply:(Lscala/collection/immutable/Set;Lscala/collection/immutable/Set;)Lscala/collection/immutable/Set;
	areturn
  Labels:
  LocalVariableTable: 
   Start  Length  Slot  Name   Signature
   0      13      0    this       Lscala/util/automata/BaseBerrySethi$$anonfun$doComp$3;
   0      13      1    v1       Ljava/lang/Object;
   0      13      2    v2       Ljava/lang/Object;


public final scala.collection.immutable.Set apply(scala.collection.immutable.Set, scala.collection.immutable.Set);
  Signature: (Lscala/collection/immutable/Set;Lscala/collection/immutable/Set;)Lscala/collection/immutable/Set;
  Code:
   Stack=2, Locals=3, Args_size=3
	aload_1
	aload_2
	invokeinterface	InterfaceMethod scala/collection/generic/Addable.$plus$plus:(Lscala/collection/Traversable;)Lscala/collection/generic/Addable;
	checkcast	class scala/collection/immutable/Set
	areturn
  Labels:
  Signature: length = 0x2
   00 2E 

public scala.Function1 curry();
  Signature: ()Lscala/Function1;
  Code:
   Stack=1, Locals=1, Args_size=1
	aload_0
	invokestatic	Method scala/Function2$class.curry:(Lscala/Function2;)Lscala/Function1;
	areturn
  Labels:

public java.lang.String toString();
  Signature: ()Ljava/lang/String;
  Code:
   Stack=1, Locals=1, Args_size=1
	aload_0
	invokestatic	Method scala/Function2$class.toString:(Lscala/Function2;)Ljava/lang/String;
	areturn
  Labels:

}

