Compiled from "BaseBerrySethi.scala"
public abstract class scala.util.automata.BaseBerrySethi extends java.lang.Object implements scala.ScalaObject
  SourceFile: "BaseBerrySethi.scala"
  ScalaSig: length = 0x3E3
   05 00 FFFFFF81 13 06 08 01 02 FFFFFF84 FFFFFF80 FFFFFF80 FFFFFF81 00 09 02 0E
   42 61 73 65 42 65 72 72 79 53 65 74 68 69 0A 02
   03 04 01 08 61 75 74 6F 6D 61 74 61 0A 02 05 06
   01 04 75 74 69 6C 0A 01 07 01 05 73 63 61 6C 61
   03 00 13 03 00 0A 12 10 02 0B 10 0D 01 0C 0A 02
   0D 0E 01 04 6C 61 6E 67 0A 01 0F 01 04 6A 61 76
   61 09 02 11 0C 02 06 4F 62 6A 65 63 74 10 02 13
   14 0D 01 06 09 02 15 06 02 0B 53 63 61 6C 61 4F
   62 6A 65 63 74 08 05 17 00 FFFFFF84 00 18 01 06 3C 69
   6E 69 74 3E 14 01 19 10 02 1A 00 0D 01 02 08 07
   0D 00 FFFFFFC2 FFFFFF80 FFFFFF86 00 1C 15 01 1D 10 02 1E 21 0D 01
   1F 0A 02 20 04 01 06 72 65 67 65 78 70 09 02 22
   1F 02 04 42 61 73 65 08 07 24 00 FFFFFFC0 FFFFFF80 FFFFFF84 08 25
   01 03 70 6F 73 15 01 26 10 02 13 27 09 02 28 06
   02 03 49 6E 74 08 07 2A 00 FFFFFFC0 FFFFFF80 FFFFFF84 08 2B 01 07
   70 6F 73 5F 24 65 71 14 02 2C 2F 10 02 13 2D 09
   02 2E 06 02 04 55 6E 69 74 08 07 30 29 FFFFFF81 FFFFFF80 FFFFFFC0
   00 26 01 03 78 24 31 08 06 32 00 FFFFFFA0 FFFFFFA0 04 26 01
   04 70 6F 73 20 08 07 34 00 FFFFFFC0 FFFFFF80 FFFFFF84 08 35 01 0B
   67 6C 6F 62 61 6C 46 69 72 73 74 15 01 36 10 03
   37 3C 26 0D 01 38 0A 02 39 3A 01 09 69 6D 6D 75
   74 61 62 6C 65 0A 02 3B 06 01 0A 63 6F 6C 6C 65
   63 74 69 6F 6E 09 02 3D 38 02 03 53 65 74 08 07
   3F 00 FFFFFFC0 FFFFFF80 FFFFFF84 08 40 01 0F 67 6C 6F 62 61 6C 46
   69 72 73 74 5F 24 65 71 14 02 2C 41 08 07 30 3E
   FFFFFF81 FFFFFF80 FFFFFFC0 00 36 08 06 43 00 FFFFFFA0 FFFFFFA0 04 36 01 0C 67
   6C 6F 62 61 6C 46 69 72 73 74 20 08 07 45 00 FFFFFFC0
   FFFFFF80 FFFFFF84 08 46 01 06 66 6F 6C 6C 6F 77 15 01 47 10
   04 48 4B 26 36 0D 01 49 0A 02 4A 3A 01 07 6D 75
   74 61 62 6C 65 09 02 4C 49 02 07 48 61 73 68 4D
   61 70 08 07 4E 00 FFFFFFC0 FFFFFF80 FFFFFF84 08 4F 01 0A 66 6F 6C
   6C 6F 77 5F 24 65 71 14 02 2C 50 08 07 30 4D FFFFFF81
   FFFFFF80 FFFFFFC0 00 47 08 06 52 00 FFFFFFA0 FFFFFFA0 04 47 01 07 66 6F
   6C 6C 6F 77 20 08 07 54 00 FFFFFFC0 FFFFFF80 FFFFFF84 08 25 01 08
   66 69 6E 61 6C 54 61 67 08 07 56 00 FFFFFFC0 FFFFFF80 FFFFFF84 08
   57 01 0C 66 69 6E 61 6C 54 61 67 5F 24 65 71 14
   02 2C 58 08 07 30 55 FFFFFF81 FFFFFF80 FFFFFFC0 00 26 08 06 5A 00
   FFFFFFA0 FFFFFFA0 04 26 01 09 66 69 6E 61 6C 54 61 67 20 08
   07 5C 00 FFFFFFC0 FFFFFF80 FFFFFF84 08 5D 01 06 66 69 6E 61 6C 73
   15 01 5E 10 04 37 5F 26 26 09 02 60 38 02 03 4D
   61 70 08 07 62 00 FFFFFFC0 FFFFFF80 FFFFFF84 08 63 01 0A 66 69 6E
   61 6C 73 5F 24 65 71 14 02 2C 64 08 07 30 61 FFFFFF81
   FFFFFF80 FFFFFFC0 00 5E 08 06 66 00 FFFFFFA0 FFFFFFA0 04 5E 01 07 66 69
   6E 61 6C 73 20 08 07 68 00 FFFFFFC2 FFFFFF80 FFFFFF84 02 35 01 08
   65 6D 70 74 79 53 65 74 08 06 6A 00 FFFFFFA0 FFFFFF80 06 36
   01 09 65 6D 70 74 79 53 65 74 20 08 05 6C 00 FFFFFF84
   08 6D 01 09 63 6F 6D 70 46 69 72 73 74 14 02 36
   6E 08 05 6F 6B FFFFFFC0 00 70 01 01 72 10 02 71 73 0E
   02 72 1B 0D 01 00 09 02 74 21 02 06 52 65 67 45
   78 70 08 05 76 00 FFFFFF84 08 77 01 08 63 6F 6D 70 4C
   61 73 74 14 02 36 78 08 05 6F 75 FFFFFFC0 00 70 08 05
   7A 00 FFFFFF84 08 7B 01 0A 63 6F 6D 70 46 6F 6C 6C 6F
   77 14 02 36 7C 08 05 6F 79 FFFFFFC0 00 7D 10 04 7E FFFFFF81
   06 70 0E 03 7F FFFFFF81 04 0E 04 FFFFFF81 00 FFFFFF81 03 0D 02 FFFFFF81
   01 0A 03 FFFFFF81 02 08 01 06 3C 72 6F 6F 74 3E 09 01
   07 09 03 FFFFFF81 05 06 01 07 70 61 63 6B 61 67 65 09
   04 FFFFFF81 07 FFFFFF81 08 02 03 53 65 71 0A 03 FFFFFF81 05 06 08
   07 FFFFFF81 0A 00 FFFFFF84 08 FFFFFF81 0B 01 0B 63 6F 6D 70 46 6F
   6C 6C 6F 77 31 14 05 36 FFFFFF81 0C FFFFFF81 0E 08 07 FFFFFF81 0D
   FFFFFF81 09 FFFFFFC0 00 36 01 04 66 6F 6C 31 08 06 6F FFFFFF81 09
   FFFFFFC0 00 70 08 07 FFFFFF81 10 00 FFFFFF84 08 FFFFFF81 11 01 08 74 72
   61 76 65 72 73 65 14 03 2C FFFFFF81 12 08 06 6F FFFFFF81 0F
   FFFFFFC0 00 70 
  InnerClass: 
   public #268= #55 of #214; //Alt=class scala/util/regexp/Base$Alt of class scala/util/regexp/Base
   public #269= #84 of #214; //Meta=class scala/util/regexp/Base$Meta of class scala/util/regexp/Base
   public #270= #81 of #214; //Sequ=class scala/util/regexp/Base$Sequ of class scala/util/regexp/Base
   public #271= #90 of #214; //Star=class scala/util/regexp/Base$Star of class scala/util/regexp/Base
   public abstract #272= #77 of #214; //RegExp=class scala/util/regexp/Base$RegExp of class scala/util/regexp/Base
  minor version: 0
  major version: 49
  Constant pool:
const #1 = Asciz	SourceFile;
const #2 = Asciz	BaseBerrySethi.scala;
const #3 = Asciz	emptySet;
const #4 = Asciz	Lscala/collection/immutable/Set;;
const #5 = Asciz	Lscala/collection/immutable/Set<Ljava/lang/Integer;>;;
const #6 = Asciz	Signature;
const #7 = Asciz	finals;
const #8 = Asciz	Lscala/collection/immutable/Map;;
const #9 = Asciz	Lscala/collection/immutable/Map<Ljava/lang/Integer;Ljava/lang/Integer;>;;
const #10 = Asciz	finalTag;
const #11 = Asciz	I;
const #12 = Asciz	follow;
const #13 = Asciz	Lscala/collection/mutable/HashMap;;
const #14 = Asciz	Lscala/collection/mutable/HashMap<Ljava/lang/Integer;Lscala/collection/immutable/Set<Ljava/lang/Integer;>;>;;
const #15 = Asciz	globalFirst;
const #16 = Asciz	pos;
const #17 = Asciz	<init>;
const #18 = Asciz	()V;
const #19 = Asciz	Code;
const #20 = Asciz	LineNumberTable;
const #21 = Asciz	java/lang/Object;
const #22 = class	#21;	//  java/lang/Object
const #23 = NameAndType	#17:#18;//  "<init>":()V
const #24 = Method	#22.#23;	//  java/lang/Object."<init>":()V
const #25 = Asciz	scala/util/automata/BaseBerrySethi;
const #26 = class	#25;	//  scala/util/automata/BaseBerrySethi
const #27 = NameAndType	#16:#11;//  pos:I
const #28 = Field	#26.#27;	//  scala/util/automata/BaseBerrySethi.pos:I
const #29 = Asciz	scala/collection/immutable/Set$;
const #30 = class	#29;	//  scala/collection/immutable/Set$
const #31 = Asciz	MODULE$;
const #32 = Asciz	Lscala/collection/immutable/Set$;;
const #33 = NameAndType	#31:#32;//  MODULE$:Lscala/collection/immutable/Set$;
const #34 = Field	#30.#33;	//  scala/collection/immutable/Set$.MODULE$:Lscala/collection/immutable/Set$;
const #35 = Asciz	scala/runtime/ScalaRunTime$;
const #36 = class	#35;	//  scala/runtime/ScalaRunTime$
const #37 = Asciz	Lscala/runtime/ScalaRunTime$;;
const #38 = NameAndType	#31:#37;//  MODULE$:Lscala/runtime/ScalaRunTime$;
const #39 = Field	#36.#38;	//  scala/runtime/ScalaRunTime$.MODULE$:Lscala/runtime/ScalaRunTime$;
const #40 = Asciz	boxArray;
const #41 = Asciz	(Ljava/lang/Object;)Lscala/runtime/BoxedArray;;
const #42 = NameAndType	#40:#41;//  boxArray:(Ljava/lang/Object;)Lscala/runtime/BoxedArray;
const #43 = Method	#36.#42;	//  scala/runtime/ScalaRunTime$.boxArray:(Ljava/lang/Object;)Lscala/runtime/BoxedArray;
const #44 = Asciz	apply;
const #45 = Asciz	(Lscala/collection/Sequence;)Lscala/collection/Traversable;;
const #46 = NameAndType	#44:#45;//  apply:(Lscala/collection/Sequence;)Lscala/collection/Traversable;
const #47 = Method	#30.#46;	//  scala/collection/immutable/Set$.apply:(Lscala/collection/Sequence;)Lscala/collection/Traversable;
const #48 = Asciz	scala/collection/immutable/Set;
const #49 = class	#48;	//  scala/collection/immutable/Set
const #50 = NameAndType	#3:#4;//  emptySet:Lscala/collection/immutable/Set;
const #51 = Field	#26.#50;	//  scala/util/automata/BaseBerrySethi.emptySet:Lscala/collection/immutable/Set;
const #52 = Asciz	traverse;
const #53 = Asciz	(Lscala/util/regexp/Base$RegExp;)V;
const #54 = Asciz	scala/util/regexp/Base$Alt;
const #55 = class	#54;	//  scala/util/regexp/Base$Alt
const #56 = Asciz	rs;
const #57 = Asciz	()Lscala/collection/Sequence;;
const #58 = NameAndType	#56:#57;//  rs:()Lscala/collection/Sequence;
const #59 = Method	#55.#58;	//  scala/util/regexp/Base$Alt.rs:()Lscala/collection/Sequence;
const #60 = Asciz	scala/collection/generic/IterableTemplate;
const #61 = class	#60;	//  scala/collection/generic/IterableTemplate
const #62 = Asciz	iterator;
const #63 = Asciz	()Lscala/collection/Iterator;;
const #64 = NameAndType	#62:#63;//  iterator:()Lscala/collection/Iterator;
const #65 = InterfaceMethod	#61.#64;	//  scala/collection/generic/IterableTemplate.iterator:()Lscala/collection/Iterator;
const #66 = Asciz	scala/collection/Iterator;
const #67 = class	#66;	//  scala/collection/Iterator
const #68 = Asciz	hasNext;
const #69 = Asciz	()Z;
const #70 = NameAndType	#68:#69;//  hasNext:()Z
const #71 = InterfaceMethod	#67.#70;	//  scala/collection/Iterator.hasNext:()Z
const #72 = Asciz	next;
const #73 = Asciz	()Ljava/lang/Object;;
const #74 = NameAndType	#72:#73;//  next:()Ljava/lang/Object;
const #75 = InterfaceMethod	#67.#74;	//  scala/collection/Iterator.next:()Ljava/lang/Object;
const #76 = Asciz	scala/util/regexp/Base$RegExp;
const #77 = class	#76;	//  scala/util/regexp/Base$RegExp
const #78 = NameAndType	#52:#53;//  traverse:(Lscala/util/regexp/Base$RegExp;)V
const #79 = Method	#26.#78;	//  scala/util/automata/BaseBerrySethi.traverse:(Lscala/util/regexp/Base$RegExp;)V
const #80 = Asciz	scala/util/regexp/Base$Sequ;
const #81 = class	#80;	//  scala/util/regexp/Base$Sequ
const #82 = Method	#81.#58;	//  scala/util/regexp/Base$Sequ.rs:()Lscala/collection/Sequence;
const #83 = Asciz	scala/util/regexp/Base$Meta;
const #84 = class	#83;	//  scala/util/regexp/Base$Meta
const #85 = Asciz	r;
const #86 = Asciz	()Lscala/util/regexp/Base$RegExp;;
const #87 = NameAndType	#85:#86;//  r:()Lscala/util/regexp/Base$RegExp;
const #88 = Method	#84.#87;	//  scala/util/regexp/Base$Meta.r:()Lscala/util/regexp/Base$RegExp;
const #89 = Asciz	scala/util/regexp/Base$Star;
const #90 = class	#89;	//  scala/util/regexp/Base$Star
const #91 = Method	#90.#87;	//  scala/util/regexp/Base$Star.r:()Lscala/util/regexp/Base$RegExp;
const #92 = Asciz	java/lang/IllegalArgumentException;
const #93 = class	#92;	//  java/lang/IllegalArgumentException
const #94 = Asciz	scala/collection/mutable/StringBuilder;
const #95 = class	#94;	//  scala/collection/mutable/StringBuilder
const #96 = Method	#95.#23;	//  scala/collection/mutable/StringBuilder."<init>":()V
const #97 = Asciz	unexp pattern ;
const #98 = String	#97;	//  unexp pattern 
const #99 = Asciz	append;
const #100 = Asciz	(Ljava/lang/Object;)Lscala/collection/mutable/StringBuilder;;
const #101 = NameAndType	#99:#100;//  append:(Ljava/lang/Object;)Lscala/collection/mutable/StringBuilder;
const #102 = Method	#95.#101;	//  scala/collection/mutable/StringBuilder.append:(Ljava/lang/Object;)Lscala/collection/mutable/StringBuilder;
const #103 = Asciz	getClass;
const #104 = Asciz	()Ljava/lang/Class;;
const #105 = NameAndType	#103:#104;//  getClass:()Ljava/lang/Class;
const #106 = Method	#77.#105;	//  scala/util/regexp/Base$RegExp.getClass:()Ljava/lang/Class;
const #107 = Asciz	toString;
const #108 = Asciz	()Ljava/lang/String;;
const #109 = NameAndType	#107:#108;//  toString:()Ljava/lang/String;
const #110 = Method	#95.#109;	//  scala/collection/mutable/StringBuilder.toString:()Ljava/lang/String;
const #111 = Asciz	(Ljava/lang/String;)V;
const #112 = NameAndType	#17:#111;//  "<init>":(Ljava/lang/String;)V
const #113 = Method	#93.#112;	//  java/lang/IllegalArgumentException."<init>":(Ljava/lang/String;)V
const #114 = Asciz	this;
const #115 = Asciz	Lscala/util/automata/BaseBerrySethi;;
const #116 = Asciz	Lscala/util/regexp/Base$RegExp;;
const #117 = Asciz	temp25;
const #118 = Asciz	temp26;
const #119 = Asciz	Lscala/util/regexp/Base$Alt;;
const #120 = Asciz	x;
const #121 = Asciz	it;
const #122 = Asciz	Lscala/collection/Iterator;;
const #123 = Asciz	temp28;
const #124 = Asciz	Lscala/util/regexp/Base$Sequ;;
const #125 = Asciz	temp30;
const #126 = Asciz	Lscala/util/regexp/Base$Meta;;
const #127 = Asciz	temp31;
const #128 = Asciz	Lscala/util/regexp/Base$Star;;
const #129 = Asciz	temp32;
const #130 = Asciz	LocalVariableTable;
const #131 = Asciz	compFollow1;
const #132 = Asciz	(Lscala/collection/immutable/Set;Lscala/util/regexp/Base$RegExp;)Lscala/collection/immutable/Set;;
const #133 = Asciz	()Lscala/collection/immutable/Set;;
const #134 = NameAndType	#3:#133;//  emptySet:()Lscala/collection/immutable/Set;
const #135 = Method	#26.#134;	//  scala/util/automata/BaseBerrySethi.emptySet:()Lscala/collection/immutable/Set;
const #136 = Asciz	toList;
const #137 = Asciz	()Lscala/collection/immutable/List;;
const #138 = NameAndType	#136:#137;//  toList:()Lscala/collection/immutable/List;
const #139 = InterfaceMethod	#67.#138;	//  scala/collection/Iterator.toList:()Lscala/collection/immutable/List;
const #140 = Asciz	scala/collection/immutable/List;
const #141 = class	#140;	//  scala/collection/immutable/List
const #142 = Asciz	reverse;
const #143 = NameAndType	#142:#137;//  reverse:()Lscala/collection/immutable/List;
const #144 = Method	#141.#143;	//  scala/collection/immutable/List.reverse:()Lscala/collection/immutable/List;
const #145 = Asciz	scala/collection/generic/LinearSequenceTemplate;
const #146 = class	#145;	//  scala/collection/generic/LinearSequenceTemplate
const #147 = InterfaceMethod	#146.#64;	//  scala/collection/generic/LinearSequenceTemplate.iterator:()Lscala/collection/Iterator;
const #148 = NameAndType	#131:#132;//  compFollow1:(Lscala/collection/immutable/Set;Lscala/util/regexp/Base$RegExp;)Lscala/collection/immutable/Set;
const #149 = Method	#26.#148;	//  scala/util/automata/BaseBerrySethi.compFollow1:(Lscala/collection/immutable/Set;Lscala/util/regexp/Base$RegExp;)Lscala/collection/immutable/Set;
const #150 = Asciz	scala/collection/generic/Addable;
const #151 = class	#150;	//  scala/collection/generic/Addable
const #152 = Asciz	$plus$plus;
const #153 = Asciz	(Lscala/collection/Traversable;)Lscala/collection/generic/Addable;;
const #154 = NameAndType	#152:#153;//  $plus$plus:(Lscala/collection/Traversable;)Lscala/collection/generic/Addable;
const #155 = InterfaceMethod	#151.#154;	//  scala/collection/generic/Addable.$plus$plus:(Lscala/collection/Traversable;)Lscala/collection/generic/Addable;
const #156 = Asciz	compFirst;
const #157 = Asciz	(Lscala/util/regexp/Base$RegExp;)Lscala/collection/immutable/Set;;
const #158 = NameAndType	#156:#157;//  compFirst:(Lscala/util/regexp/Base$RegExp;)Lscala/collection/immutable/Set;
const #159 = Method	#26.#158;	//  scala/util/automata/BaseBerrySethi.compFirst:(Lscala/util/regexp/Base$RegExp;)Lscala/collection/immutable/Set;
const #160 = Asciz	isNullable;
const #161 = NameAndType	#160:#69;//  isNullable:()Z
const #162 = Method	#77.#161;	//  scala/util/regexp/Base$RegExp.isNullable:()Z
const #163 = Asciz	unexpected pattern: ;
const #164 = String	#163;	//  unexpected pattern: 
const #165 = Asciz	fol1;
const #166 = Asciz	fol;
const #167 = Asciz	temp17;
const #168 = Asciz	temp18;
const #169 = Asciz	first;
const #170 = Asciz	temp20;
const #171 = Asciz	temp21;
const #172 = Asciz	temp23;
const #173 = Asciz	p;
const #174 = Asciz	(Lscala/collection/immutable/Set<Ljava/lang/Integer;>;Lscala/util/regexp/Base$RegExp;)Lscala/collection/immutable/Set<Ljava/lang/Integer;>;;
const #175 = Asciz	compFollow;
const #176 = Asciz	(Lscala/collection/Sequence;)Lscala/collection/immutable/Set;;
const #177 = Asciz	scala/collection/generic/SequenceTemplate;
const #178 = class	#177;	//  scala/collection/generic/SequenceTemplate
const #179 = Asciz	length;
const #180 = Asciz	()I;
const #181 = NameAndType	#179:#180;//  length:()I
const #182 = InterfaceMethod	#178.#181;	//  scala/collection/generic/SequenceTemplate.length:()I
const #183 = NameAndType	#16:#180;//  pos:()I
const #184 = Method	#26.#183;	//  scala/util/automata/BaseBerrySethi.pos:()I
const #185 = Asciz	scala/runtime/BoxesRunTime;
const #186 = class	#185;	//  scala/runtime/BoxesRunTime
const #187 = Asciz	boxToInteger;
const #188 = Asciz	(I)Ljava/lang/Integer;;
const #189 = NameAndType	#187:#188;//  boxToInteger:(I)Ljava/lang/Integer;
const #190 = Method	#186.#189;	//  scala/runtime/BoxesRunTime.boxToInteger:(I)Ljava/lang/Integer;
const #191 = Asciz	scala/collection/generic/SetTemplate;
const #192 = class	#191;	//  scala/collection/generic/SetTemplate
const #193 = Asciz	$plus;
const #194 = Asciz	(Ljava/lang/Object;)Lscala/collection/generic/SetTemplate;;
const #195 = NameAndType	#193:#194;//  $plus:(Ljava/lang/Object;)Lscala/collection/generic/SetTemplate;
const #196 = InterfaceMethod	#192.#195;	//  scala/collection/generic/SetTemplate.$plus:(Ljava/lang/Object;)Lscala/collection/generic/SetTemplate;
const #197 = Asciz	()Lscala/collection/mutable/HashMap;;
const #198 = NameAndType	#12:#197;//  follow:()Lscala/collection/mutable/HashMap;
const #199 = Method	#26.#198;	//  scala/util/automata/BaseBerrySethi.follow:()Lscala/collection/mutable/HashMap;
const #200 = Asciz	scala/collection/mutable/HashMap;
const #201 = class	#200;	//  scala/collection/mutable/HashMap
const #202 = Asciz	update;
const #203 = Asciz	(Ljava/lang/Object;Ljava/lang/Object;)V;
const #204 = NameAndType	#202:#203;//  update:(Ljava/lang/Object;Ljava/lang/Object;)V
const #205 = Method	#201.#204;	//  scala/collection/mutable/HashMap.update:(Ljava/lang/Object;Ljava/lang/Object;)V
const #206 = Asciz	Lscala/collection/Sequence;;
const #207 = Asciz	(Lscala/collection/Sequence<Lscala/util/regexp/Base$RegExp;>;)Lscala/collection/immutable/Set<Ljava/lang/Integer;>;;
const #208 = Asciz	compLast;
const #209 = Asciz	lang;
const #210 = Asciz	()Lscala/util/regexp/Base;;
const #211 = NameAndType	#209:#210;//  lang:()Lscala/util/regexp/Base;
const #212 = Method	#26.#211;	//  scala/util/automata/BaseBerrySethi.lang:()Lscala/util/regexp/Base;
const #213 = Asciz	scala/util/regexp/Base;
const #214 = class	#213;	//  scala/util/regexp/Base
const #215 = Asciz	Eps;
const #216 = Asciz	()Lscala/util/regexp/Base$Eps$;;
const #217 = NameAndType	#215:#216;//  Eps:()Lscala/util/regexp/Base$Eps$;
const #218 = Method	#214.#217;	//  scala/util/regexp/Base.Eps:()Lscala/util/regexp/Base$Eps$;
const #219 = Asciz	equals;
const #220 = Asciz	(Ljava/lang/Object;)Z;
const #221 = NameAndType	#219:#220;//  equals:(Ljava/lang/Object;)Z
const #222 = Method	#22.#221;	//  java/lang/Object.equals:(Ljava/lang/Object;)Z
const #223 = NameAndType	#208:#157;//  compLast:(Lscala/util/regexp/Base$RegExp;)Lscala/collection/immutable/Set;
const #224 = Method	#26.#223;	//  scala/util/automata/BaseBerrySethi.compLast:(Lscala/util/regexp/Base$RegExp;)Lscala/collection/immutable/Set;
const #225 = Asciz	unexpected pattern ;
const #226 = String	#225;	//  unexpected pattern 
const #227 = Asciz	temp9;
const #228 = Asciz	temp10;
const #229 = Asciz	tmp;
const #230 = Asciz	temp12;
const #231 = Asciz	temp13;
const #232 = Asciz	z;
const #233 = Asciz	temp15;
const #234 = Asciz	temp16;
const #235 = Asciz	(Lscala/util/regexp/Base$RegExp;)Lscala/collection/immutable/Set<Ljava/lang/Integer;>;;
const #236 = Asciz	temp1;
const #237 = Asciz	temp2;
const #238 = Asciz	temp4;
const #239 = Asciz	temp5;
const #240 = Asciz	temp7;
const #241 = Asciz	temp8;
const #242 = Asciz	()Lscala/collection/immutable/Set<Ljava/lang/Integer;>;;
const #243 = Asciz	finals_$eq;
const #244 = Asciz	(Lscala/collection/immutable/Map;)V;
const #245 = NameAndType	#7:#8;//  finals:Lscala/collection/immutable/Map;
const #246 = Field	#26.#245;	//  scala/util/automata/BaseBerrySethi.finals:Lscala/collection/immutable/Map;
const #247 = Asciz	(Lscala/collection/immutable/Map<Ljava/lang/Integer;Ljava/lang/Integer;>;)V;
const #248 = Asciz	()Lscala/collection/immutable/Map;;
const #249 = Asciz	()Lscala/collection/immutable/Map<Ljava/lang/Integer;Ljava/lang/Integer;>;;
const #250 = Asciz	finalTag_$eq;
const #251 = Asciz	(I)V;
const #252 = NameAndType	#10:#11;//  finalTag:I
const #253 = Field	#26.#252;	//  scala/util/automata/BaseBerrySethi.finalTag:I
const #254 = Asciz	follow_$eq;
const #255 = Asciz	(Lscala/collection/mutable/HashMap;)V;
const #256 = NameAndType	#12:#13;//  follow:Lscala/collection/mutable/HashMap;
const #257 = Field	#26.#256;	//  scala/util/automata/BaseBerrySethi.follow:Lscala/collection/mutable/HashMap;
const #258 = Asciz	(Lscala/collection/mutable/HashMap<Ljava/lang/Integer;Lscala/collection/immutable/Set<Ljava/lang/Integer;>;>;)V;
const #259 = Asciz	()Lscala/collection/mutable/HashMap<Ljava/lang/Integer;Lscala/collection/immutable/Set<Ljava/lang/Integer;>;>;;
const #260 = Asciz	globalFirst_$eq;
const #261 = Asciz	(Lscala/collection/immutable/Set;)V;
const #262 = NameAndType	#15:#4;//  globalFirst:Lscala/collection/immutable/Set;
const #263 = Field	#26.#262;	//  scala/util/automata/BaseBerrySethi.globalFirst:Lscala/collection/immutable/Set;
const #264 = Asciz	(Lscala/collection/immutable/Set<Ljava/lang/Integer;>;)V;
const #265 = Asciz	pos_$eq;
const #266 = Asciz	ScalaSig;
const #267 = Asciz	InnerClasses;
const #268 = Asciz	Alt;
const #269 = Asciz	Meta;
const #270 = Asciz	Sequ;
const #271 = Asciz	Star;
const #272 = Asciz	RegExp;
const #273 = Asciz	scala/ScalaObject;
const #274 = class	#273;	//  scala/ScalaObject

{
public scala.util.automata.BaseBerrySethi();
  Code:
   Stack=4, Locals=1, Args_size=1
   0:	aload_0
   1:	invokespecial	#24; //Method java/lang/Object."<init>":()V
   4:	aload_0
   5:	iconst_0
   6:	putfield	#28; //Field pos:I
   9:	aload_0
   10:	getstatic	#34; //Field scala/collection/immutable/Set$.MODULE$:Lscala/collection/immutable/Set$;
   13:	getstatic	#39; //Field scala/runtime/ScalaRunTime$.MODULE$:Lscala/runtime/ScalaRunTime$;
   16:	iconst_0
   17:	newarray int
   19:	invokevirtual	#43; //Method scala/runtime/ScalaRunTime$.boxArray:(Ljava/lang/Object;)Lscala/runtime/BoxedArray;
   22:	invokevirtual	#47; //Method scala/collection/immutable/Set$.apply:(Lscala/collection/Sequence;)Lscala/collection/Traversable;
   25:	checkcast	#49; //class scala/collection/immutable/Set
   28:	putfield	#51; //Field emptySet:Lscala/collection/immutable/Set;
   31:	return
  LineNumberTable: 
   line 24: 0
   line 29: 4
   line 42: 9


public void traverse(scala.util.regexp.Base$RegExp);
  Code:
   Stack=4, Locals=12, Args_size=2
   0:	aload_1
   1:	astore_2
   2:	aload_2
   3:	instanceof	#55; //class scala/util/regexp/Base$Alt
   6:	ifeq	56
   9:	aload_2
   10:	checkcast	#55; //class scala/util/regexp/Base$Alt
   13:	astore_3
   14:	aload_3
   15:	astore	4
   17:	aload	4
   19:	invokevirtual	#59; //Method scala/util/regexp/Base$Alt.rs:()Lscala/collection/Sequence;
   22:	invokeinterface	#65,  1; //InterfaceMethod scala/collection/generic/IterableTemplate.iterator:()Lscala/collection/Iterator;
   27:	astore	5
   29:	aload	5
   31:	invokeinterface	#71,  1; //InterfaceMethod scala/collection/Iterator.hasNext:()Z
   36:	ifeq	163
   39:	aload_0
   40:	aload	5
   42:	invokeinterface	#75,  1; //InterfaceMethod scala/collection/Iterator.next:()Ljava/lang/Object;
   47:	checkcast	#77; //class scala/util/regexp/Base$RegExp
   50:	invokevirtual	#79; //Method traverse:(Lscala/util/regexp/Base$RegExp;)V
   53:	goto	29
   56:	aload_2
   57:	instanceof	#81; //class scala/util/regexp/Base$Sequ
   60:	ifeq	112
   63:	aload_2
   64:	checkcast	#81; //class scala/util/regexp/Base$Sequ
   67:	astore	6
   69:	aload	6
   71:	astore	7
   73:	aload	7
   75:	invokevirtual	#82; //Method scala/util/regexp/Base$Sequ.rs:()Lscala/collection/Sequence;
   78:	invokeinterface	#65,  1; //InterfaceMethod scala/collection/generic/IterableTemplate.iterator:()Lscala/collection/Iterator;
   83:	astore	8
   85:	aload	8
   87:	invokeinterface	#71,  1; //InterfaceMethod scala/collection/Iterator.hasNext:()Z
   92:	ifeq	163
   95:	aload_0
   96:	aload	8
   98:	invokeinterface	#75,  1; //InterfaceMethod scala/collection/Iterator.next:()Ljava/lang/Object;
   103:	checkcast	#77; //class scala/util/regexp/Base$RegExp
   106:	invokevirtual	#79; //Method traverse:(Lscala/util/regexp/Base$RegExp;)V
   109:	goto	85
   112:	aload_2
   113:	instanceof	#84; //class scala/util/regexp/Base$Meta
   116:	ifeq	137
   119:	aload_2
   120:	checkcast	#84; //class scala/util/regexp/Base$Meta
   123:	astore	9
   125:	aload_0
   126:	aload	9
   128:	invokevirtual	#88; //Method scala/util/regexp/Base$Meta.r:()Lscala/util/regexp/Base$RegExp;
   131:	invokevirtual	#79; //Method traverse:(Lscala/util/regexp/Base$RegExp;)V
   134:	goto	163
   137:	aload_2
   138:	instanceof	#90; //class scala/util/regexp/Base$Star
   141:	ifeq	164
   144:	aload_2
   145:	checkcast	#90; //class scala/util/regexp/Base$Star
   148:	astore	10
   150:	aload	10
   152:	invokevirtual	#91; //Method scala/util/regexp/Base$Star.r:()Lscala/util/regexp/Base$RegExp;
   155:	astore	11
   157:	aload_0
   158:	aload	11
   160:	invokevirtual	#79; //Method traverse:(Lscala/util/regexp/Base$RegExp;)V
   163:	return
   164:	new	#93; //class java/lang/IllegalArgumentException
   167:	dup
   168:	new	#95; //class scala/collection/mutable/StringBuilder
   171:	dup
   172:	invokespecial	#96; //Method scala/collection/mutable/StringBuilder."<init>":()V
   175:	ldc	#98; //String unexp pattern 
   177:	invokevirtual	#102; //Method scala/collection/mutable/StringBuilder.append:(Ljava/lang/Object;)Lscala/collection/mutable/StringBuilder;
   180:	aload_1
   181:	invokevirtual	#106; //Method scala/util/regexp/Base$RegExp.getClass:()Ljava/lang/Class;
   184:	invokevirtual	#102; //Method scala/collection/mutable/StringBuilder.append:(Ljava/lang/Object;)Lscala/collection/mutable/StringBuilder;
   187:	invokevirtual	#110; //Method scala/collection/mutable/StringBuilder.toString:()Ljava/lang/String;
   190:	invokespecial	#113; //Method java/lang/IllegalArgumentException."<init>":(Ljava/lang/String;)V
   193:	athrow
  LineNumberTable: 
   line 181: 0
   line 183: 14
   line 184: 17
   line 185: 29
   line 181: 56
   line 186: 69
   line 187: 73
   line 188: 85
   line 181: 112
   line 190: 125
   line 189: 126
   line 190: 128
   line 181: 137
   line 192: 157
   line 191: 158
   line 192: 160
   line 181: 163
   line 194: 164

  LocalVariableTable: 
   Start  Length  Slot  Name   Signature
   0      194      0    this       Lscala/util/automata/BaseBerrySethi;
   0      194      1    r       Lscala/util/regexp/Base$RegExp;
   2      192      2    temp25       Lscala/util/regexp/Base$RegExp;
   14      42      3    temp26       Lscala/util/regexp/Base$Alt;
   17      39      4    x       Lscala/util/regexp/Base$Alt;
   29      27      5    it       Lscala/collection/Iterator;
   69      43      6    temp28       Lscala/util/regexp/Base$Sequ;
   73      39      7    x       Lscala/util/regexp/Base$Sequ;
   85      27      8    it       Lscala/collection/Iterator;
   125      9      9    temp30       Lscala/util/regexp/Base$Meta;
   150      13      10    temp31       Lscala/util/regexp/Base$Star;
   157      6      11    temp32       Lscala/util/regexp/Base$RegExp;


public scala.collection.immutable.Set compFollow1(scala.collection.immutable.Set, scala.util.regexp.Base$RegExp);
  Code:
   Stack=4, Locals=17, Args_size=3
   0:	aload_1
   1:	astore_3
   2:	aload_2
   3:	astore	4
   5:	aload	4
   7:	instanceof	#55; //class scala/util/regexp/Base$Alt
   10:	ifeq	100
   13:	aload	4
   15:	checkcast	#55; //class scala/util/regexp/Base$Alt
   18:	astore	5
   20:	aload	5
   22:	astore	6
   24:	aload_0
   25:	invokevirtual	#135; //Method emptySet:()Lscala/collection/immutable/Set;
   28:	astore	7
   30:	aload	6
   32:	invokevirtual	#59; //Method scala/util/regexp/Base$Alt.rs:()Lscala/collection/Sequence;
   35:	invokeinterface	#65,  1; //InterfaceMethod scala/collection/generic/IterableTemplate.iterator:()Lscala/collection/Iterator;
   40:	invokeinterface	#139,  1; //InterfaceMethod scala/collection/Iterator.toList:()Lscala/collection/immutable/List;
   45:	invokevirtual	#144; //Method scala/collection/immutable/List.reverse:()Lscala/collection/immutable/List;
   48:	invokeinterface	#147,  1; //InterfaceMethod scala/collection/generic/LinearSequenceTemplate.iterator:()Lscala/collection/Iterator;
   53:	astore	8
   55:	aload	8
   57:	invokeinterface	#71,  1; //InterfaceMethod scala/collection/Iterator.hasNext:()Z
   62:	ifeq	95
   65:	aload	7
   67:	aload_0
   68:	aload_3
   69:	aload	8
   71:	invokeinterface	#75,  1; //InterfaceMethod scala/collection/Iterator.next:()Ljava/lang/Object;
   76:	checkcast	#77; //class scala/util/regexp/Base$RegExp
   79:	invokevirtual	#149; //Method compFollow1:(Lscala/collection/immutable/Set;Lscala/util/regexp/Base$RegExp;)Lscala/collection/immutable/Set;
   82:	invokeinterface	#155,  2; //InterfaceMethod scala/collection/generic/Addable.$plus$plus:(Lscala/collection/Traversable;)Lscala/collection/generic/Addable;
   87:	checkcast	#49; //class scala/collection/immutable/Set
   90:	astore	7
   92:	goto	55
   95:	aload	7
   97:	goto	290
   100:	aload	4
   102:	instanceof	#84; //class scala/util/regexp/Base$Meta
   105:	ifeq	128
   108:	aload	4
   110:	checkcast	#84; //class scala/util/regexp/Base$Meta
   113:	astore	9
   115:	aload_0
   116:	aload_1
   117:	aload	9
   119:	invokevirtual	#88; //Method scala/util/regexp/Base$Meta.r:()Lscala/util/regexp/Base$RegExp;
   122:	invokevirtual	#149; //Method compFollow1:(Lscala/collection/immutable/Set;Lscala/util/regexp/Base$RegExp;)Lscala/collection/immutable/Set;
   125:	goto	290
   128:	aload	4
   130:	instanceof	#90; //class scala/util/regexp/Base$Star
   133:	ifeq	179
   136:	aload	4
   138:	checkcast	#90; //class scala/util/regexp/Base$Star
   141:	astore	10
   143:	aload	10
   145:	astore	11
   147:	aload_3
   148:	aload_0
   149:	aload	11
   151:	invokevirtual	#91; //Method scala/util/regexp/Base$Star.r:()Lscala/util/regexp/Base$RegExp;
   154:	invokevirtual	#159; //Method compFirst:(Lscala/util/regexp/Base$RegExp;)Lscala/collection/immutable/Set;
   157:	invokeinterface	#155,  2; //InterfaceMethod scala/collection/generic/Addable.$plus$plus:(Lscala/collection/Traversable;)Lscala/collection/generic/Addable;
   162:	checkcast	#49; //class scala/collection/immutable/Set
   165:	astore_3
   166:	aload_0
   167:	aload_3
   168:	aload	11
   170:	invokevirtual	#91; //Method scala/util/regexp/Base$Star.r:()Lscala/util/regexp/Base$RegExp;
   173:	invokevirtual	#149; //Method compFollow1:(Lscala/collection/immutable/Set;Lscala/util/regexp/Base$RegExp;)Lscala/collection/immutable/Set;
   176:	goto	290
   179:	aload	4
   181:	instanceof	#81; //class scala/util/regexp/Base$Sequ
   184:	ifeq	291
   187:	aload	4
   189:	checkcast	#81; //class scala/util/regexp/Base$Sequ
   192:	astore	12
   194:	aload	12
   196:	astore	13
   198:	aload_0
   199:	invokevirtual	#135; //Method emptySet:()Lscala/collection/immutable/Set;
   202:	astore	14
   204:	aload	13
   206:	invokevirtual	#82; //Method scala/util/regexp/Base$Sequ.rs:()Lscala/collection/Sequence;
   209:	invokeinterface	#65,  1; //InterfaceMethod scala/collection/generic/IterableTemplate.iterator:()Lscala/collection/Iterator;
   214:	invokeinterface	#139,  1; //InterfaceMethod scala/collection/Iterator.toList:()Lscala/collection/immutable/List;
   219:	invokevirtual	#144; //Method scala/collection/immutable/List.reverse:()Lscala/collection/immutable/List;
   222:	invokeinterface	#147,  1; //InterfaceMethod scala/collection/generic/LinearSequenceTemplate.iterator:()Lscala/collection/Iterator;
   227:	astore	15
   229:	aload	15
   231:	invokeinterface	#71,  1; //InterfaceMethod scala/collection/Iterator.hasNext:()Z
   236:	ifeq	288
   239:	aload	15
   241:	invokeinterface	#75,  1; //InterfaceMethod scala/collection/Iterator.next:()Ljava/lang/Object;
   246:	checkcast	#77; //class scala/util/regexp/Base$RegExp
   249:	astore	16
   251:	aload_0
   252:	aload_3
   253:	aload	16
   255:	invokevirtual	#149; //Method compFollow1:(Lscala/collection/immutable/Set;Lscala/util/regexp/Base$RegExp;)Lscala/collection/immutable/Set;
   258:	astore	14
   260:	aload	16
   262:	invokevirtual	#162; //Method scala/util/regexp/Base$RegExp.isNullable:()Z
   265:	ifeq	282
   268:	aload_3
   269:	aload	14
   271:	invokeinterface	#155,  2; //InterfaceMethod scala/collection/generic/Addable.$plus$plus:(Lscala/collection/Traversable;)Lscala/collection/generic/Addable;
   276:	checkcast	#49; //class scala/collection/immutable/Set
   279:	goto	284
   282:	aload	14
   284:	astore_3
   285:	goto	229
   288:	aload	14
   290:	areturn
   291:	new	#93; //class java/lang/IllegalArgumentException
   294:	dup
   295:	new	#95; //class scala/collection/mutable/StringBuilder
   298:	dup
   299:	invokespecial	#96; //Method scala/collection/mutable/StringBuilder."<init>":()V
   302:	ldc	#164; //String unexpected pattern: 
   304:	invokevirtual	#102; //Method scala/collection/mutable/StringBuilder.append:(Ljava/lang/Object;)Lscala/collection/mutable/StringBuilder;
   307:	aload_2
   308:	invokevirtual	#106; //Method scala/util/regexp/Base$RegExp.getClass:()Ljava/lang/Class;
   311:	invokevirtual	#102; //Method scala/collection/mutable/StringBuilder.append:(Ljava/lang/Object;)Lscala/collection/mutable/StringBuilder;
   314:	invokevirtual	#110; //Method scala/collection/mutable/StringBuilder.toString:()Ljava/lang/String;
   317:	invokespecial	#113; //Method java/lang/IllegalArgumentException."<init>":(Ljava/lang/String;)V
   320:	athrow
  LineNumberTable: 
   line 135: 0
   line 136: 2
   line 138: 20
   line 139: 24
   line 140: 30
   line 141: 55
   line 142: 65
   line 143: 95
   line 136: 100
   line 152: 115
   line 151: 117
   line 152: 119
   line 136: 128
   line 154: 143
   line 155: 147
   line 156: 166
   line 136: 179
   line 158: 194
   line 159: 198
   line 160: 204
   line 161: 229
   line 162: 239
   line 163: 251
   line 165: 260
   line 166: 282
   line 164: 284
   line 161: 285
   line 168: 288
   line 134: 290
   line 171: 291

  LocalVariableTable: 
   Start  Length  Slot  Name   Signature
   0      321      0    this       Lscala/util/automata/BaseBerrySethi;
   0      321      1    fol1       Lscala/collection/immutable/Set;
   0      321      2    r       Lscala/util/regexp/Base$RegExp;
   2      319      3    fol       Lscala/collection/immutable/Set;
   5      316      4    temp17       Lscala/util/regexp/Base$RegExp;
   20      77      5    temp18       Lscala/util/regexp/Base$Alt;
   24      73      6    x       Lscala/util/regexp/Base$Alt;
   30      67      7    first       Lscala/collection/immutable/Set;
   55      42      8    it       Lscala/collection/Iterator;
   115      10      9    temp20       Lscala/util/regexp/Base$Meta;
   143      33      10    temp21       Lscala/util/regexp/Base$Star;
   147      29      11    x       Lscala/util/regexp/Base$Star;
   194      96      12    temp23       Lscala/util/regexp/Base$Sequ;
   198      92      13    x       Lscala/util/regexp/Base$Sequ;
   204      86      14    first       Lscala/collection/immutable/Set;
   229      61      15    it       Lscala/collection/Iterator;
   251      34      16    p       Lscala/util/regexp/Base$RegExp;

  Signature: length = 0x2
   00 FFFFFFAE 

public scala.collection.immutable.Set compFollow(scala.collection.Sequence);
  Code:
   Stack=3, Locals=6, Args_size=2
   0:	aload_0
   1:	invokevirtual	#135; //Method emptySet:()Lscala/collection/immutable/Set;
   4:	astore_2
   5:	aload_0
   6:	invokevirtual	#135; //Method emptySet:()Lscala/collection/immutable/Set;
   9:	astore_3
   10:	aload_1
   11:	invokeinterface	#182,  1; //InterfaceMethod scala/collection/generic/SequenceTemplate.length:()I
   16:	iconst_0
   17:	if_icmple	114
   20:	aload_1
   21:	invokeinterface	#65,  1; //InterfaceMethod scala/collection/generic/IterableTemplate.iterator:()Lscala/collection/Iterator;
   26:	invokeinterface	#139,  1; //InterfaceMethod scala/collection/Iterator.toList:()Lscala/collection/immutable/List;
   31:	invokevirtual	#144; //Method scala/collection/immutable/List.reverse:()Lscala/collection/immutable/List;
   34:	invokeinterface	#147,  1; //InterfaceMethod scala/collection/generic/LinearSequenceTemplate.iterator:()Lscala/collection/Iterator;
   39:	astore	4
   41:	aload_3
   42:	aload_0
   43:	invokevirtual	#184; //Method pos:()I
   46:	invokestatic	#190; //Method scala/runtime/BoxesRunTime.boxToInteger:(I)Ljava/lang/Integer;
   49:	invokeinterface	#196,  2; //InterfaceMethod scala/collection/generic/SetTemplate.$plus:(Ljava/lang/Object;)Lscala/collection/generic/SetTemplate;
   54:	checkcast	#49; //class scala/collection/immutable/Set
   57:	astore_3
   58:	aload	4
   60:	invokeinterface	#71,  1; //InterfaceMethod scala/collection/Iterator.hasNext:()Z
   65:	ifeq	114
   68:	aload	4
   70:	invokeinterface	#75,  1; //InterfaceMethod scala/collection/Iterator.next:()Ljava/lang/Object;
   75:	checkcast	#77; //class scala/util/regexp/Base$RegExp
   78:	astore	5
   80:	aload_0
   81:	aload_3
   82:	aload	5
   84:	invokevirtual	#149; //Method compFollow1:(Lscala/collection/immutable/Set;Lscala/util/regexp/Base$RegExp;)Lscala/collection/immutable/Set;
   87:	astore_2
   88:	aload	5
   90:	invokevirtual	#162; //Method scala/util/regexp/Base$RegExp.isNullable:()Z
   93:	ifeq	109
   96:	aload_3
   97:	aload_2
   98:	invokeinterface	#155,  2; //InterfaceMethod scala/collection/generic/Addable.$plus$plus:(Lscala/collection/Traversable;)Lscala/collection/generic/Addable;
   103:	checkcast	#49; //class scala/collection/immutable/Set
   106:	goto	110
   109:	aload_2
   110:	astore_3
   111:	goto	58
   114:	aload_0
   115:	invokevirtual	#199; //Method follow:()Lscala/collection/mutable/HashMap;
   118:	iconst_0
   119:	invokestatic	#190; //Method scala/runtime/BoxesRunTime.boxToInteger:(I)Ljava/lang/Integer;
   122:	aload_3
   123:	invokevirtual	#205; //Method scala/collection/mutable/HashMap.update:(Ljava/lang/Object;Ljava/lang/Object;)V
   126:	aload_3
   127:	areturn
  LineNumberTable: 
   line 108: 0
   line 109: 5
   line 110: 10
   line 112: 20
   line 114: 41
   line 115: 58
   line 116: 68
   line 117: 80
   line 119: 88
   line 120: 109
   line 118: 110
   line 115: 111
   line 123: 114
   line 124: 126

  LocalVariableTable: 
   Start  Length  Slot  Name   Signature
   0      128      0    this       Lscala/util/automata/BaseBerrySethi;
   0      128      1    r       Lscala/collection/Sequence;
   5      122      2    first       Lscala/collection/immutable/Set;
   10      117      3    fol       Lscala/collection/immutable/Set;
   41      73      4    it       Lscala/collection/Iterator;
   80      31      5    p       Lscala/util/regexp/Base$RegExp;

  Signature: length = 0x2
   00 FFFFFFCF 

public scala.collection.immutable.Set compLast(scala.util.regexp.Base$RegExp);
  Code:
   Stack=4, Locals=16, Args_size=2
   0:	aload_1
   1:	astore_2
   2:	aload_2
   3:	instanceof	#55; //class scala/util/regexp/Base$Alt
   6:	ifeq	79
   9:	aload_2
   10:	checkcast	#55; //class scala/util/regexp/Base$Alt
   13:	astore_3
   14:	aload_3
   15:	astore	4
   17:	aload_0
   18:	invokevirtual	#135; //Method emptySet:()Lscala/collection/immutable/Set;
   21:	astore	5
   23:	aload	4
   25:	invokevirtual	#59; //Method scala/util/regexp/Base$Alt.rs:()Lscala/collection/Sequence;
   28:	invokeinterface	#65,  1; //InterfaceMethod scala/collection/generic/IterableTemplate.iterator:()Lscala/collection/Iterator;
   33:	astore	6
   35:	aload	6
   37:	invokeinterface	#71,  1; //InterfaceMethod scala/collection/Iterator.hasNext:()Z
   42:	ifeq	74
   45:	aload	5
   47:	aload_0
   48:	aload	6
   50:	invokeinterface	#75,  1; //InterfaceMethod scala/collection/Iterator.next:()Ljava/lang/Object;
   55:	checkcast	#77; //class scala/util/regexp/Base$RegExp
   58:	invokevirtual	#159; //Method compFirst:(Lscala/util/regexp/Base$RegExp;)Lscala/collection/immutable/Set;
   61:	invokeinterface	#155,  2; //InterfaceMethod scala/collection/generic/Addable.$plus$plus:(Lscala/collection/Traversable;)Lscala/collection/generic/Addable;
   66:	checkcast	#49; //class scala/collection/immutable/Set
   69:	astore	5
   71:	goto	35
   74:	aload	5
   76:	goto	272
   79:	aload_2
   80:	aload_0
   81:	invokevirtual	#212; //Method lang:()Lscala/util/regexp/Base;
   84:	invokevirtual	#218; //Method scala/util/regexp/Base.Eps:()Lscala/util/regexp/Base$Eps$;
   87:	astore	7
   89:	dup
   90:	ifnonnull	102
   93:	pop
   94:	aload	7
   96:	ifnull	110
   99:	goto	117
   102:	aload	7
   104:	invokevirtual	#222; //Method java/lang/Object.equals:(Ljava/lang/Object;)Z
   107:	ifeq	117
   110:	aload_0
   111:	invokevirtual	#135; //Method emptySet:()Lscala/collection/immutable/Set;
   114:	goto	272
   117:	aload_2
   118:	instanceof	#84; //class scala/util/regexp/Base$Meta
   121:	ifeq	142
   124:	aload_2
   125:	checkcast	#84; //class scala/util/regexp/Base$Meta
   128:	astore	8
   130:	aload_0
   131:	aload	8
   133:	invokevirtual	#88; //Method scala/util/regexp/Base$Meta.r:()Lscala/util/regexp/Base$RegExp;
   136:	invokevirtual	#224; //Method compLast:(Lscala/util/regexp/Base$RegExp;)Lscala/collection/immutable/Set;
   139:	goto	272
   142:	aload_2
   143:	instanceof	#81; //class scala/util/regexp/Base$Sequ
   146:	ifeq	246
   149:	aload_2
   150:	checkcast	#81; //class scala/util/regexp/Base$Sequ
   153:	astore	9
   155:	aload	9
   157:	astore	10
   159:	aload_0
   160:	invokevirtual	#135; //Method emptySet:()Lscala/collection/immutable/Set;
   163:	astore	11
   165:	aload	10
   167:	invokevirtual	#82; //Method scala/util/regexp/Base$Sequ.rs:()Lscala/collection/Sequence;
   170:	invokeinterface	#65,  1; //InterfaceMethod scala/collection/generic/IterableTemplate.iterator:()Lscala/collection/Iterator;
   175:	invokeinterface	#139,  1; //InterfaceMethod scala/collection/Iterator.toList:()Lscala/collection/immutable/List;
   180:	invokevirtual	#144; //Method scala/collection/immutable/List.reverse:()Lscala/collection/immutable/List;
   183:	invokeinterface	#147,  1; //InterfaceMethod scala/collection/generic/LinearSequenceTemplate.iterator:()Lscala/collection/Iterator;
   188:	astore	12
   190:	aload	12
   192:	invokeinterface	#71,  1; //InterfaceMethod scala/collection/Iterator.hasNext:()Z
   197:	ifeq	241
   200:	aload	12
   202:	invokeinterface	#75,  1; //InterfaceMethod scala/collection/Iterator.next:()Ljava/lang/Object;
   207:	checkcast	#77; //class scala/util/regexp/Base$RegExp
   210:	astore	13
   212:	aload	11
   214:	aload_0
   215:	aload	13
   217:	invokevirtual	#224; //Method compLast:(Lscala/util/regexp/Base$RegExp;)Lscala/collection/immutable/Set;
   220:	invokeinterface	#155,  2; //InterfaceMethod scala/collection/generic/Addable.$plus$plus:(Lscala/collection/Traversable;)Lscala/collection/generic/Addable;
   225:	checkcast	#49; //class scala/collection/immutable/Set
   228:	astore	11
   230:	aload	13
   232:	invokevirtual	#162; //Method scala/util/regexp/Base$RegExp.isNullable:()Z
   235:	ifne	190
   238:	aload	11
   240:	areturn
   241:	aload	11
   243:	goto	272
   246:	aload_2
   247:	instanceof	#90; //class scala/util/regexp/Base$Star
   250:	ifeq	273
   253:	aload_2
   254:	checkcast	#90; //class scala/util/regexp/Base$Star
   257:	astore	14
   259:	aload	14
   261:	invokevirtual	#91; //Method scala/util/regexp/Base$Star.r:()Lscala/util/regexp/Base$RegExp;
   264:	astore	15
   266:	aload_0
   267:	aload	15
   269:	invokevirtual	#224; //Method compLast:(Lscala/util/regexp/Base$RegExp;)Lscala/collection/immutable/Set;
   272:	areturn
   273:	new	#93; //class java/lang/IllegalArgumentException
   276:	dup
   277:	new	#95; //class scala/collection/mutable/StringBuilder
   280:	dup
   281:	invokespecial	#96; //Method scala/collection/mutable/StringBuilder."<init>":()V
   284:	ldc	#226; //String unexpected pattern 
   286:	invokevirtual	#102; //Method scala/collection/mutable/StringBuilder.append:(Ljava/lang/Object;)Lscala/collection/mutable/StringBuilder;
   289:	aload_1
   290:	invokevirtual	#106; //Method scala/util/regexp/Base$RegExp.getClass:()Ljava/lang/Class;
   293:	invokevirtual	#102; //Method scala/collection/mutable/StringBuilder.append:(Ljava/lang/Object;)Lscala/collection/mutable/StringBuilder;
   296:	invokevirtual	#110; //Method scala/collection/mutable/StringBuilder.toString:()Ljava/lang/String;
   299:	invokespecial	#113; //Method java/lang/IllegalArgumentException."<init>":(Ljava/lang/String;)V
   302:	athrow
  LineNumberTable: 
   line 73: 0
   line 74: 14
   line 75: 17
   line 76: 23
   line 77: 35
   line 78: 74
   line 73: 79
   line 80: 110
   line 73: 117
   line 83: 130
   line 82: 131
   line 83: 133
   line 73: 142
   line 84: 155
   line 85: 159
   line 86: 165
   line 87: 190
   line 88: 200
   line 89: 212
   line 90: 230
   line 91: 238
   line 93: 241
   line 73: 246
   line 95: 266
   line 94: 267
   line 95: 269
   line 73: 272
   line 97: 273

  LocalVariableTable: 
   Start  Length  Slot  Name   Signature
   0      303      0    this       Lscala/util/automata/BaseBerrySethi;
   0      303      1    r       Lscala/util/regexp/Base$RegExp;
   2      301      2    temp9       Lscala/util/regexp/Base$RegExp;
   14      62      3    temp10       Lscala/util/regexp/Base$Alt;
   17      59      4    x       Lscala/util/regexp/Base$Alt;
   23      53      5    tmp       Lscala/collection/immutable/Set;
   35      41      6    it       Lscala/collection/Iterator;
   130      9      8    temp12       Lscala/util/regexp/Base$Meta;
   155      88      9    temp13       Lscala/util/regexp/Base$Sequ;
   159      84      10    x       Lscala/util/regexp/Base$Sequ;
   165      78      11    tmp       Lscala/collection/immutable/Set;
   190      53      12    it       Lscala/collection/Iterator;
   212      29      13    z       Lscala/util/regexp/Base$RegExp;
   259      13      14    temp15       Lscala/util/regexp/Base$Star;
   266      6      15    temp16       Lscala/util/regexp/Base$RegExp;

  Signature: length = 0x2
   00 FFFFFFEB 

public scala.collection.immutable.Set compFirst(scala.util.regexp.Base$RegExp);
  Code:
   Stack=4, Locals=16, Args_size=2
   0:	aload_1
   1:	astore_2
   2:	aload_2
   3:	instanceof	#55; //class scala/util/regexp/Base$Alt
   6:	ifeq	79
   9:	aload_2
   10:	checkcast	#55; //class scala/util/regexp/Base$Alt
   13:	astore_3
   14:	aload_3
   15:	astore	4
   17:	aload_0
   18:	invokevirtual	#135; //Method emptySet:()Lscala/collection/immutable/Set;
   21:	astore	5
   23:	aload	4
   25:	invokevirtual	#59; //Method scala/util/regexp/Base$Alt.rs:()Lscala/collection/Sequence;
   28:	invokeinterface	#65,  1; //InterfaceMethod scala/collection/generic/IterableTemplate.iterator:()Lscala/collection/Iterator;
   33:	astore	6
   35:	aload	6
   37:	invokeinterface	#71,  1; //InterfaceMethod scala/collection/Iterator.hasNext:()Z
   42:	ifeq	74
   45:	aload	5
   47:	aload_0
   48:	aload	6
   50:	invokeinterface	#75,  1; //InterfaceMethod scala/collection/Iterator.next:()Ljava/lang/Object;
   55:	checkcast	#77; //class scala/util/regexp/Base$RegExp
   58:	invokevirtual	#159; //Method compFirst:(Lscala/util/regexp/Base$RegExp;)Lscala/collection/immutable/Set;
   61:	invokeinterface	#155,  2; //InterfaceMethod scala/collection/generic/Addable.$plus$plus:(Lscala/collection/Traversable;)Lscala/collection/generic/Addable;
   66:	checkcast	#49; //class scala/collection/immutable/Set
   69:	astore	5
   71:	goto	35
   74:	aload	5
   76:	goto	259
   79:	aload_2
   80:	aload_0
   81:	invokevirtual	#212; //Method lang:()Lscala/util/regexp/Base;
   84:	invokevirtual	#218; //Method scala/util/regexp/Base.Eps:()Lscala/util/regexp/Base$Eps$;
   87:	astore	7
   89:	dup
   90:	ifnonnull	102
   93:	pop
   94:	aload	7
   96:	ifnull	110
   99:	goto	117
   102:	aload	7
   104:	invokevirtual	#222; //Method java/lang/Object.equals:(Ljava/lang/Object;)Z
   107:	ifeq	117
   110:	aload_0
   111:	invokevirtual	#135; //Method emptySet:()Lscala/collection/immutable/Set;
   114:	goto	259
   117:	aload_2
   118:	instanceof	#84; //class scala/util/regexp/Base$Meta
   121:	ifeq	142
   124:	aload_2
   125:	checkcast	#84; //class scala/util/regexp/Base$Meta
   128:	astore	8
   130:	aload_0
   131:	aload	8
   133:	invokevirtual	#88; //Method scala/util/regexp/Base$Meta.r:()Lscala/util/regexp/Base$RegExp;
   136:	invokevirtual	#159; //Method compFirst:(Lscala/util/regexp/Base$RegExp;)Lscala/collection/immutable/Set;
   139:	goto	259
   142:	aload_2
   143:	instanceof	#81; //class scala/util/regexp/Base$Sequ
   146:	ifeq	233
   149:	aload_2
   150:	checkcast	#81; //class scala/util/regexp/Base$Sequ
   153:	astore	9
   155:	aload	9
   157:	astore	10
   159:	aload_0
   160:	invokevirtual	#135; //Method emptySet:()Lscala/collection/immutable/Set;
   163:	astore	11
   165:	aload	10
   167:	invokevirtual	#82; //Method scala/util/regexp/Base$Sequ.rs:()Lscala/collection/Sequence;
   170:	invokeinterface	#65,  1; //InterfaceMethod scala/collection/generic/IterableTemplate.iterator:()Lscala/collection/Iterator;
   175:	astore	12
   177:	aload	12
   179:	invokeinterface	#71,  1; //InterfaceMethod scala/collection/Iterator.hasNext:()Z
   184:	ifeq	228
   187:	aload	12
   189:	invokeinterface	#75,  1; //InterfaceMethod scala/collection/Iterator.next:()Ljava/lang/Object;
   194:	checkcast	#77; //class scala/util/regexp/Base$RegExp
   197:	astore	13
   199:	aload	11
   201:	aload_0
   202:	aload	13
   204:	invokevirtual	#159; //Method compFirst:(Lscala/util/regexp/Base$RegExp;)Lscala/collection/immutable/Set;
   207:	invokeinterface	#155,  2; //InterfaceMethod scala/collection/generic/Addable.$plus$plus:(Lscala/collection/Traversable;)Lscala/collection/generic/Addable;
   212:	checkcast	#49; //class scala/collection/immutable/Set
   215:	astore	11
   217:	aload	13
   219:	invokevirtual	#162; //Method scala/util/regexp/Base$RegExp.isNullable:()Z
   222:	ifne	177
   225:	aload	11
   227:	areturn
   228:	aload	11
   230:	goto	259
   233:	aload_2
   234:	instanceof	#90; //class scala/util/regexp/Base$Star
   237:	ifeq	260
   240:	aload_2
   241:	checkcast	#90; //class scala/util/regexp/Base$Star
   244:	astore	14
   246:	aload	14
   248:	invokevirtual	#91; //Method scala/util/regexp/Base$Star.r:()Lscala/util/regexp/Base$RegExp;
   251:	astore	15
   253:	aload_0
   254:	aload	15
   256:	invokevirtual	#159; //Method compFirst:(Lscala/util/regexp/Base$RegExp;)Lscala/collection/immutable/Set;
   259:	areturn
   260:	new	#93; //class java/lang/IllegalArgumentException
   263:	dup
   264:	new	#95; //class scala/collection/mutable/StringBuilder
   267:	dup
   268:	invokespecial	#96; //Method scala/collection/mutable/StringBuilder."<init>":()V
   271:	ldc	#226; //String unexpected pattern 
   273:	invokevirtual	#102; //Method scala/collection/mutable/StringBuilder.append:(Ljava/lang/Object;)Lscala/collection/mutable/StringBuilder;
   276:	aload_1
   277:	invokevirtual	#106; //Method scala/util/regexp/Base$RegExp.getClass:()Ljava/lang/Class;
   280:	invokevirtual	#102; //Method scala/collection/mutable/StringBuilder.append:(Ljava/lang/Object;)Lscala/collection/mutable/StringBuilder;
   283:	invokevirtual	#110; //Method scala/collection/mutable/StringBuilder.toString:()Ljava/lang/String;
   286:	invokespecial	#113; //Method java/lang/IllegalArgumentException."<init>":(Ljava/lang/String;)V
   289:	athrow
  LineNumberTable: 
   line 45: 0
   line 46: 14
   line 47: 17
   line 48: 23
   line 49: 35
   line 50: 74
   line 45: 79
   line 52: 110
   line 45: 117
   line 55: 130
   line 54: 131
   line 55: 133
   line 45: 142
   line 56: 155
   line 57: 159
   line 58: 165
   line 59: 177
   line 60: 187
   line 61: 199
   line 62: 217
   line 63: 225
   line 65: 228
   line 45: 233
   line 67: 253
   line 66: 254
   line 67: 256
   line 45: 259
   line 69: 260

  LocalVariableTable: 
   Start  Length  Slot  Name   Signature
   0      290      0    this       Lscala/util/automata/BaseBerrySethi;
   0      290      1    r       Lscala/util/regexp/Base$RegExp;
   2      288      2    temp1       Lscala/util/regexp/Base$RegExp;
   14      62      3    temp2       Lscala/util/regexp/Base$Alt;
   17      59      4    x       Lscala/util/regexp/Base$Alt;
   23      53      5    tmp       Lscala/collection/immutable/Set;
   35      41      6    it       Lscala/collection/Iterator;
   130      9      8    temp4       Lscala/util/regexp/Base$Meta;
   155      75      9    temp5       Lscala/util/regexp/Base$Sequ;
   159      71      10    x       Lscala/util/regexp/Base$Sequ;
   165      65      11    tmp       Lscala/collection/immutable/Set;
   177      53      12    it       Lscala/collection/Iterator;
   199      29      13    z       Lscala/util/regexp/Base$RegExp;
   246      13      14    temp7       Lscala/util/regexp/Base$Star;
   253      6      15    temp8       Lscala/util/regexp/Base$RegExp;

  Signature: length = 0x2
   00 FFFFFFEB 

public final scala.collection.immutable.Set emptySet();
  Code:
   Stack=1, Locals=1, Args_size=1
   0:	aload_0
   1:	getfield	#51; //Field emptySet:Lscala/collection/immutable/Set;
   4:	areturn
  LineNumberTable: 
   line 42: 0

  Signature: length = 0x2
   00 FFFFFFF2 

public void finals_$eq(scala.collection.immutable.Map);
  Code:
   Stack=2, Locals=2, Args_size=2
   0:	aload_0
   1:	aload_1
   2:	putfield	#246; //Field finals:Lscala/collection/immutable/Map;
   5:	return
  LineNumberTable: 
   line 38: 0

  Signature: length = 0x2
   00 FFFFFFF7 

public scala.collection.immutable.Map finals();
  Code:
   Stack=1, Locals=1, Args_size=1
   0:	aload_0
   1:	getfield	#246; //Field finals:Lscala/collection/immutable/Map;
   4:	areturn
  LineNumberTable: 
   line 38: 0

  Signature: length = 0x2
   00 FFFFFFF9 

public void finalTag_$eq(int);
  Code:
   Stack=2, Locals=2, Args_size=2
   0:	aload_0
   1:	iload_1
   2:	putfield	#253; //Field finalTag:I
   5:	return
  LineNumberTable: 
   line 36: 0


public int finalTag();
  Code:
   Stack=1, Locals=1, Args_size=1
   0:	aload_0
   1:	getfield	#253; //Field finalTag:I
   4:	ireturn
  LineNumberTable: 
   line 36: 0


public void follow_$eq(scala.collection.mutable.HashMap);
  Code:
   Stack=2, Locals=2, Args_size=2
   0:	aload_0
   1:	aload_1
   2:	putfield	#257; //Field follow:Lscala/collection/mutable/HashMap;
   5:	return
  LineNumberTable: 
   line 34: 0

  Signature: length = 0x2
   01 02 

public scala.collection.mutable.HashMap follow();
  Code:
   Stack=1, Locals=1, Args_size=1
   0:	aload_0
   1:	getfield	#257; //Field follow:Lscala/collection/mutable/HashMap;
   4:	areturn
  LineNumberTable: 
   line 34: 0

  Signature: length = 0x2
   01 03 

public void globalFirst_$eq(scala.collection.immutable.Set);
  Code:
   Stack=2, Locals=2, Args_size=2
   0:	aload_0
   1:	aload_1
   2:	putfield	#263; //Field globalFirst:Lscala/collection/immutable/Set;
   5:	return
  LineNumberTable: 
   line 31: 0

  Signature: length = 0x2
   01 08 

public scala.collection.immutable.Set globalFirst();
  Code:
   Stack=1, Locals=1, Args_size=1
   0:	aload_0
   1:	getfield	#263; //Field globalFirst:Lscala/collection/immutable/Set;
   4:	areturn
  LineNumberTable: 
   line 31: 0

  Signature: length = 0x2
   00 FFFFFFF2 

public void pos_$eq(int);
  Code:
   Stack=2, Locals=2, Args_size=2
   0:	aload_0
   1:	iload_1
   2:	putfield	#28; //Field pos:I
   5:	return
  LineNumberTable: 
   line 29: 0


public int pos();
  Code:
   Stack=1, Locals=1, Args_size=1
   0:	aload_0
   1:	getfield	#28; //Field pos:I
   4:	ireturn
  LineNumberTable: 
   line 29: 0


public abstract scala.util.regexp.Base lang();

}

