Compiled from "BaseBerrySethi.scala"
public final class scala.util.automata.BaseBerrySethi$$anonfun$compFirst$1 extends java.lang.Object implements scala.Function1,scala.ScalaObject,java.io.Serializable
  SourceFile: "BaseBerrySethi.scala"
  Scala: length = 0x
   
  InnerClass: 
   public abstract RegExp=class scala/util/regexp/Base$RegExp of class scala/util/regexp/Base
   public final $anonfun$compFirst$1=class scala/util/automata/BaseBerrySethi$$anonfun$compFirst$1 of class scala/util/automata/BaseBerrySethi
  minor version: 0
  major version: 49
  Constant pool:
Asciz	SourceFile;
Asciz	BaseBerrySethi.scala;
Asciz	<clinit>;
Asciz	()V;
Asciz	Code;
Asciz	serialVersionUID;
Asciz	J;
Asciz	scala/util/automata/BaseBerrySethi$$anonfun$compFirst$1;
class	scala/util/automata/BaseBerrySethi$$anonfun$compFirst$1
NameAndType	serialVersionUID:J
Field	scala/util/automata/BaseBerrySethi$$anonfun$compFirst$1.serialVersionUID:J
Asciz	$outer;
Asciz	Lscala/util/automata/BaseBerrySethi;;
Asciz	<init>;
Asciz	(Lscala/util/automata/BaseBerrySethi;)V;
Asciz	LineNumberTable;
Asciz	java/lang/NullPointerException;
class	java/lang/NullPointerException
NameAndType	"<init>":()V
Method	java/lang/NullPointerException."<init>":()V
NameAndType	$outer:Lscala/util/automata/BaseBerrySethi;
Field	scala/util/automata/BaseBerrySethi$$anonfun$compFirst$1.$outer:Lscala/util/automata/BaseBerrySethi;
Asciz	java/lang/Object;
class	java/lang/Object
Method	java/lang/Object."<init>":()V
Asciz	scala/Function1$class;
class	scala/Function1$class
Asciz	$init$;
Asciz	(Lscala/Function1;)V;
NameAndType	$init$:(Lscala/Function1;)V
Method	scala/Function1$class.$init$:(Lscala/Function1;)V
Asciz	this;
Asciz	Lscala/util/automata/BaseBerrySethi$$anonfun$compFirst$1;;
Asciz	LocalVariableTable;
Asciz	apply;
Asciz	(Ljava/lang/Object;)Ljava/lang/Object;;
Asciz	scala/util/regexp/Base$RegExp;
class	scala/util/regexp/Base$RegExp
Asciz	(Lscala/util/regexp/Base$RegExp;)Lscala/collection/immutable/Set;;
NameAndType	apply:(Lscala/util/regexp/Base$RegExp;)Lscala/collection/immutable/Set;
Method	scala/util/automata/BaseBerrySethi$$anonfun$compFirst$1.apply:(Lscala/util/regexp/Base$RegExp;)Lscala/collection/immutable/Set;
Asciz	v1;
Asciz	Ljava/lang/Object;;
Asciz	scala/util/automata/BaseBerrySethi;
class	scala/util/automata/BaseBerrySethi
Asciz	compFirst;
NameAndType	compFirst:(Lscala/util/regexp/Base$RegExp;)Lscala/collection/immutable/Set;
Method	scala/util/automata/BaseBerrySethi.compFirst:(Lscala/util/regexp/Base$RegExp;)Lscala/collection/immutable/Set;
Asciz	(Lscala/util/regexp/Base$RegExp;)Lscala/collection/immutable/Set<Ljava/lang/Integer;>;;
Asciz	Signature;
Asciz	andThen;
Asciz	(Lscala/Function1;)Lscala/Function1;;
Asciz	(Lscala/Function1;Lscala/Function1;)Lscala/Function1;;
NameAndType	andThen:(Lscala/Function1;Lscala/Function1;)Lscala/Function1;
Method	scala/Function1$class.andThen:(Lscala/Function1;Lscala/Function1;)Lscala/Function1;
Asciz	g;
Asciz	Lscala/Function1;;
Asciz	compose;
NameAndType	compose:(Lscala/Function1;Lscala/Function1;)Lscala/Function1;
Method	scala/Function1$class.compose:(Lscala/Function1;Lscala/Function1;)Lscala/Function1;
Asciz	toString;
Asciz	()Ljava/lang/String;;
Asciz	(Lscala/Function1;)Ljava/lang/String;;
NameAndType	toString:(Lscala/Function1;)Ljava/lang/String;
Method	scala/Function1$class.toString:(Lscala/Function1;)Ljava/lang/String;
Asciz	Scala;
Asciz	InnerClasses;
Asciz	scala/util/regexp/Base;
class	scala/util/regexp/Base
Asciz	RegExp;
Asciz	$anonfun$compFirst$1;
Asciz	scala/Function1;
class	scala/Function1
Asciz	scala/ScalaObject;
class	scala/ScalaObject
Asciz	java/io/Serializable;
class	java/io/Serializable

{
public static final long serialVersionUID;
  Signature: J

private final scala.util.automata.BaseBerrySethi $outer;
  Signature: Lscala/util/automata/BaseBerrySethi;

public static {};
  Signature: ()V
  Code:
   Stack=2, Locals=0, Args_size=0
	lconst_0
	putstatic	Field serialVersionUID:J
	return
  Labels:

public scala.util.automata.BaseBerrySethi$$anonfun$compFirst$1(scala.util.automata.BaseBerrySethi);
  Signature: (Lscala/util/automata/BaseBerrySethi;)V
  Code:
   Stack=2, Locals=2, Args_size=2
	aload_1
	ifnonnull	l1 // aload_0
	new	class java/lang/NullPointerException
	dup
	invokespecial	Method java/lang/NullPointerException."<init>":()V
	athrow
l1	aload_0
	aload_1
	putfield	Field $outer:Lscala/util/automata/BaseBerrySethi;
	aload_0
	invokespecial	Method java/lang/Object."<init>":()V
	aload_0
	invokestatic	Method scala/Function1$class.$init$:(Lscala/Function1;)V
	return
  Labels:
   	l1 = 12 // aload_0
  LocalVariableTable: 
   Start  Length  Slot  Name   Signature
   0      26      0    this       Lscala/util/automata/BaseBerrySethi$$anonfun$compFirst$1;
   0      26      1    $outer       Lscala/util/automata/BaseBerrySethi;


public final java.lang.Object apply(java.lang.Object);
  Signature: (Ljava/lang/Object;)Ljava/lang/Object;
  Code:
   Stack=2, Locals=3, Args_size=2
	aload_0
	getfield	Field $outer:Lscala/util/automata/BaseBerrySethi;
	astore_2
	aload_0
	aload_1
	checkcast	class scala/util/regexp/Base$RegExp
	invokevirtual	Method apply:(Lscala/util/regexp/Base$RegExp;)Lscala/collection/immutable/Set;
	areturn
  Labels:
  LocalVariableTable: 
   Start  Length  Slot  Name   Signature
   0      14      0    this       Lscala/util/automata/BaseBerrySethi$$anonfun$compFirst$1;
   5      9      1    v1       Ljava/lang/Object;


public final scala.collection.immutable.Set apply(scala.util.regexp.Base$RegExp);
  Signature: (Lscala/util/regexp/Base$RegExp;)Lscala/collection/immutable/Set;
  Code:
   Stack=2, Locals=3, Args_size=2
	aload_0
	getfield	Field $outer:Lscala/util/automata/BaseBerrySethi;
	astore_2
	aload_0
	getfield	Field $outer:Lscala/util/automata/BaseBerrySethi;
	aload_1
	invokevirtual	Method scala/util/automata/BaseBerrySethi.compFirst:(Lscala/util/regexp/Base$RegExp;)Lscala/collection/immutable/Set;
	areturn
  Labels:
  LocalVariableTable: 
   Start  Length  Slot  Name   Signature
   0      14      0    this       Lscala/util/automata/BaseBerrySethi$$anonfun$compFirst$1;

  Signature: length = 0x2
   00 31 

public scala.Function1 andThen(scala.Function1);
  Signature: (Lscala/Function1;)Lscala/Function1;
  Code:
   Stack=2, Locals=2, Args_size=2
	aload_0
	aload_1
	invokestatic	Method scala/Function1$class.andThen:(Lscala/Function1;Lscala/Function1;)Lscala/Function1;
	areturn
  Labels:
  LocalVariableTable: 
   Start  Length  Slot  Name   Signature
   0      6      0    this       Lscala/util/automata/BaseBerrySethi$$anonfun$compFirst$1;
   0      6      1    g       Lscala/Function1;


public scala.Function1 compose(scala.Function1);
  Signature: (Lscala/Function1;)Lscala/Function1;
  Code:
   Stack=2, Locals=2, Args_size=2
	aload_0
	aload_1
	invokestatic	Method scala/Function1$class.compose:(Lscala/Function1;Lscala/Function1;)Lscala/Function1;
	areturn
  Labels:
  LocalVariableTable: 
   Start  Length  Slot  Name   Signature
   0      6      0    this       Lscala/util/automata/BaseBerrySethi$$anonfun$compFirst$1;
   0      6      1    g       Lscala/Function1;


public java.lang.String toString();
  Signature: ()Ljava/lang/String;
  Code:
   Stack=1, Locals=1, Args_size=1
	aload_0
	invokestatic	Method scala/Function1$class.toString:(Lscala/Function1;)Ljava/lang/String;
	areturn
  Labels:

}

