Compiled from "BaseBerrySethi.scala"
public final class scala.util.automata.BaseBerrySethi$$anonfun$compFollow$1 extends java.lang.Object implements scala.Function2,scala.ScalaObject,java.io.Serializable
  SourceFile: "BaseBerrySethi.scala"
  Scala: length = 0x
   
  InnerClass: 
   public abstract #84= #38 of #83; //RegExp=class scala/util/regexp/Base$RegExp of class scala/util/regexp/Base
   public final #85= #9 of #48; //$anonfun$compFollow$1=class scala/util/automata/BaseBerrySethi$$anonfun$compFollow$1 of class scala/util/automata/BaseBerrySethi
  minor version: 0
  major version: 49
  Constant pool:
const #1 = Asciz	SourceFile;
const #2 = Asciz	BaseBerrySethi.scala;
const #3 = Asciz	<clinit>;
const #4 = Asciz	()V;
const #5 = Asciz	Code;
const #6 = Asciz	serialVersionUID;
const #7 = Asciz	J;
const #8 = Asciz	scala/util/automata/BaseBerrySethi$$anonfun$compFollow$1;
const #9 = class	#8;	//  scala/util/automata/BaseBerrySethi$$anonfun$compFollow$1
const #10 = NameAndType	#6:#7;//  serialVersionUID:J
const #11 = Field	#9.#10;	//  scala/util/automata/BaseBerrySethi$$anonfun$compFollow$1.serialVersionUID:J
const #12 = Asciz	$outer;
const #13 = Asciz	Lscala/util/automata/BaseBerrySethi;;
const #14 = Asciz	<init>;
const #15 = Asciz	(Lscala/util/automata/BaseBerrySethi;)V;
const #16 = Asciz	LineNumberTable;
const #17 = Asciz	java/lang/NullPointerException;
const #18 = class	#17;	//  java/lang/NullPointerException
const #19 = NameAndType	#14:#4;//  "<init>":()V
const #20 = Method	#18.#19;	//  java/lang/NullPointerException."<init>":()V
const #21 = NameAndType	#12:#13;//  $outer:Lscala/util/automata/BaseBerrySethi;
const #22 = Field	#9.#21;	//  scala/util/automata/BaseBerrySethi$$anonfun$compFollow$1.$outer:Lscala/util/automata/BaseBerrySethi;
const #23 = Asciz	java/lang/Object;
const #24 = class	#23;	//  java/lang/Object
const #25 = Method	#24.#19;	//  java/lang/Object."<init>":()V
const #26 = Asciz	scala/Function2$class;
const #27 = class	#26;	//  scala/Function2$class
const #28 = Asciz	$init$;
const #29 = Asciz	(Lscala/Function2;)V;
const #30 = NameAndType	#28:#29;//  $init$:(Lscala/Function2;)V
const #31 = Method	#27.#30;	//  scala/Function2$class.$init$:(Lscala/Function2;)V
const #32 = Asciz	this;
const #33 = Asciz	Lscala/util/automata/BaseBerrySethi$$anonfun$compFollow$1;;
const #34 = Asciz	LocalVariableTable;
const #35 = Asciz	apply;
const #36 = Asciz	(Ljava/lang/Object;Ljava/lang/Object;)Ljava/lang/Object;;
const #37 = Asciz	scala/util/regexp/Base$RegExp;
const #38 = class	#37;	//  scala/util/regexp/Base$RegExp
const #39 = Asciz	scala/collection/immutable/Set;
const #40 = class	#39;	//  scala/collection/immutable/Set
const #41 = Asciz	(Lscala/util/regexp/Base$RegExp;Lscala/collection/immutable/Set;)Lscala/collection/immutable/Set;;
const #42 = NameAndType	#35:#41;//  apply:(Lscala/util/regexp/Base$RegExp;Lscala/collection/immutable/Set;)Lscala/collection/immutable/Set;
const #43 = Method	#9.#42;	//  scala/util/automata/BaseBerrySethi$$anonfun$compFollow$1.apply:(Lscala/util/regexp/Base$RegExp;Lscala/collection/immutable/Set;)Lscala/collection/immutable/Set;
const #44 = Asciz	v1;
const #45 = Asciz	Ljava/lang/Object;;
const #46 = Asciz	v2;
const #47 = Asciz	scala/util/automata/BaseBerrySethi;
const #48 = class	#47;	//  scala/util/automata/BaseBerrySethi
const #49 = Asciz	compFollow1;
const #50 = Asciz	(Lscala/collection/immutable/Set;Lscala/util/regexp/Base$RegExp;)Lscala/collection/immutable/Set;;
const #51 = NameAndType	#49:#50;//  compFollow1:(Lscala/collection/immutable/Set;Lscala/util/regexp/Base$RegExp;)Lscala/collection/immutable/Set;
const #52 = Method	#48.#51;	//  scala/util/automata/BaseBerrySethi.compFollow1:(Lscala/collection/immutable/Set;Lscala/util/regexp/Base$RegExp;)Lscala/collection/immutable/Set;
const #53 = Asciz	isNullable;
const #54 = Asciz	()Z;
const #55 = NameAndType	#53:#54;//  isNullable:()Z
const #56 = Method	#38.#55;	//  scala/util/regexp/Base$RegExp.isNullable:()Z
const #57 = Asciz	scala/collection/generic/Addable;
const #58 = class	#57;	//  scala/collection/generic/Addable
const #59 = Asciz	$plus$plus;
const #60 = Asciz	(Lscala/collection/Traversable;)Lscala/collection/generic/Addable;;
const #61 = NameAndType	#59:#60;//  $plus$plus:(Lscala/collection/Traversable;)Lscala/collection/generic/Addable;
const #62 = InterfaceMethod	#58.#61;	//  scala/collection/generic/Addable.$plus$plus:(Lscala/collection/Traversable;)Lscala/collection/generic/Addable;
const #63 = Asciz	p;
const #64 = Asciz	Lscala/util/regexp/Base$RegExp;;
const #65 = Asciz	fol;
const #66 = Asciz	Lscala/collection/immutable/Set;;
const #67 = Asciz	first;
const #68 = Asciz	(Lscala/util/regexp/Base$RegExp;Lscala/collection/immutable/Set<Ljava/lang/Integer;>;)Lscala/collection/immutable/Set<Ljava/lang/Integer;>;;
const #69 = Asciz	Signature;
const #70 = Asciz	curry;
const #71 = Asciz	()Lscala/Function1;;
const #72 = Asciz	(Lscala/Function2;)Lscala/Function1;;
const #73 = NameAndType	#70:#72;//  curry:(Lscala/Function2;)Lscala/Function1;
const #74 = Method	#27.#73;	//  scala/Function2$class.curry:(Lscala/Function2;)Lscala/Function1;
const #75 = Asciz	toString;
const #76 = Asciz	()Ljava/lang/String;;
const #77 = Asciz	(Lscala/Function2;)Ljava/lang/String;;
const #78 = NameAndType	#75:#77;//  toString:(Lscala/Function2;)Ljava/lang/String;
const #79 = Method	#27.#78;	//  scala/Function2$class.toString:(Lscala/Function2;)Ljava/lang/String;
const #80 = Asciz	Scala;
const #81 = Asciz	InnerClasses;
const #82 = Asciz	scala/util/regexp/Base;
const #83 = class	#82;	//  scala/util/regexp/Base
const #84 = Asciz	RegExp;
const #85 = Asciz	$anonfun$compFollow$1;
const #86 = Asciz	scala/Function2;
const #87 = class	#86;	//  scala/Function2
const #88 = Asciz	scala/ScalaObject;
const #89 = class	#88;	//  scala/ScalaObject
const #90 = Asciz	java/io/Serializable;
const #91 = class	#90;	//  java/io/Serializable

{
public static final long serialVersionUID;

public static {};
  Code:
   Stack=2, Locals=0, Args_size=0
   0:	lconst_0
   1:	putstatic	#11; //Field serialVersionUID:J
   4:	return

public scala.util.automata.BaseBerrySethi$$anonfun$compFollow$1(scala.util.automata.BaseBerrySethi);
  Code:
   Stack=2, Locals=2, Args_size=2
   0:	aload_1
   1:	ifnonnull	12
   4:	new	#18; //class java/lang/NullPointerException
   7:	dup
   8:	invokespecial	#20; //Method java/lang/NullPointerException."<init>":()V
   11:	athrow
   12:	aload_0
   13:	aload_1
   14:	putfield	#22; //Field $outer:Lscala/util/automata/BaseBerrySethi;
   17:	aload_0
   18:	invokespecial	#25; //Method java/lang/Object."<init>":()V
   21:	aload_0
   22:	invokestatic	#31; //Method scala/Function2$class.$init$:(Lscala/Function2;)V
   25:	return
  LineNumberTable: 
   line 71: 0

  LocalVariableTable: 
   Start  Length  Slot  Name   Signature
   0      26      0    this       Lscala/util/automata/BaseBerrySethi$$anonfun$compFollow$1;
   0      26      1    $outer       Lscala/util/automata/BaseBerrySethi;


public final java.lang.Object apply(java.lang.Object, java.lang.Object);
  Code:
   Stack=3, Locals=4, Args_size=3
   0:	aload_0
   1:	getfield	#22; //Field $outer:Lscala/util/automata/BaseBerrySethi;
   4:	astore_3
   5:	aload_0
   6:	aload_1
   7:	checkcast	#38; //class scala/util/regexp/Base$RegExp
   10:	aload_2
   11:	checkcast	#40; //class scala/collection/immutable/Set
   14:	invokevirtual	#43; //Method apply:(Lscala/util/regexp/Base$RegExp;Lscala/collection/immutable/Set;)Lscala/collection/immutable/Set;
   17:	areturn
  LineNumberTable: 
   line 71: 0

  LocalVariableTable: 
   Start  Length  Slot  Name   Signature
   0      18      0    this       Lscala/util/automata/BaseBerrySethi$$anonfun$compFollow$1;
   5      13      1    v1       Ljava/lang/Object;
   5      13      2    v2       Ljava/lang/Object;


public final scala.collection.immutable.Set apply(scala.util.regexp.Base$RegExp, scala.collection.immutable.Set);
  Code:
   Stack=3, Locals=5, Args_size=3
   0:	aload_0
   1:	getfield	#22; //Field $outer:Lscala/util/automata/BaseBerrySethi;
   4:	astore	4
   6:	aload_0
   7:	getfield	#22; //Field $outer:Lscala/util/automata/BaseBerrySethi;
   10:	aload_2
   11:	aload_1
   12:	invokevirtual	#52; //Method scala/util/automata/BaseBerrySethi.compFollow1:(Lscala/collection/immutable/Set;Lscala/util/regexp/Base$RegExp;)Lscala/collection/immutable/Set;
   15:	astore_3
   16:	aload_1
   17:	invokevirtual	#56; //Method scala/util/regexp/Base$RegExp.isNullable:()Z
   20:	ifeq	36
   23:	aload_2
   24:	aload_3
   25:	invokeinterface	#62,  2; //InterfaceMethod scala/collection/generic/Addable.$plus$plus:(Lscala/collection/Traversable;)Lscala/collection/generic/Addable;
   30:	checkcast	#40; //class scala/collection/immutable/Set
   33:	goto	37
   36:	aload_3
   37:	areturn
  LineNumberTable: 
   line 72: 0
   line 74: 16
   line 75: 36
   line 71: 37

  LocalVariableTable: 
   Start  Length  Slot  Name   Signature
   0      38      0    this       Lscala/util/automata/BaseBerrySethi$$anonfun$compFollow$1;
   6      32      1    p       Lscala/util/regexp/Base$RegExp;
   6      32      2    fol       Lscala/collection/immutable/Set;
   16      22      3    first       Lscala/collection/immutable/Set;

  Signature: length = 0x2
   00 44 

public scala.Function1 curry();
  Code:
   Stack=1, Locals=1, Args_size=1
   0:	aload_0
   1:	invokestatic	#74; //Method scala/Function2$class.curry:(Lscala/Function2;)Lscala/Function1;
   4:	areturn
  LineNumberTable: 
   line 71: 0


public java.lang.String toString();
  Code:
   Stack=1, Locals=1, Args_size=1
   0:	aload_0
   1:	invokestatic	#79; //Method scala/Function2$class.toString:(Lscala/Function2;)Ljava/lang/String;
   4:	areturn
  LineNumberTable: 
   line 71: 0


}

