Compiled from "BaseBerrySethi.scala"
public final class scala.util.automata.BaseBerrySethi$$anonfun$compFollow1$2 extends scala.runtime.AbstractFunction2 implements java.io.Serializable
  SourceFile: "BaseBerrySethi.scala"
  Scala: length = 0x
   
  InnerClass: 
   public abstract RegExp=class scala/util/regexp/Base$RegExp of class scala/util/regexp/Base
   public final $anonfun$compFollow1$2=class scala/util/automata/BaseBerrySethi$$anonfun$compFollow1$2 of class scala/util/automata/BaseBerrySethi
  minor version: 0
  major version: 49
  Constant pool:
Asciz	SourceFile;
Asciz	BaseBerrySethi.scala;
Asciz	<clinit>;
Asciz	()V;
Asciz	Code;
Asciz	serialVersionUID;
Asciz	J;
Asciz	scala/util/automata/BaseBerrySethi$$anonfun$compFollow1$2;
class	scala/util/automata/BaseBerrySethi$$anonfun$compFollow1$2
NameAndType	serialVersionUID:J
Field	scala/util/automata/BaseBerrySethi$$anonfun$compFollow1$2.serialVersionUID:J
Asciz	$outer;
Asciz	Lscala/util/automata/BaseBerrySethi;;
Asciz	<init>;
Asciz	(Lscala/util/automata/BaseBerrySethi;)V;
Asciz	LineNumberTable;
Asciz	java/lang/NullPointerException;
class	java/lang/NullPointerException
NameAndType	"<init>":()V
Method	java/lang/NullPointerException."<init>":()V
NameAndType	$outer:Lscala/util/automata/BaseBerrySethi;
Field	scala/util/automata/BaseBerrySethi$$anonfun$compFollow1$2.$outer:Lscala/util/automata/BaseBerrySethi;
Asciz	scala/runtime/AbstractFunction2;
class	scala/runtime/AbstractFunction2
Method	scala/runtime/AbstractFunction2."<init>":()V
Asciz	this;
Asciz	Lscala/util/automata/BaseBerrySethi$$anonfun$compFollow1$2;;
Asciz	LocalVariableTable;
Asciz	apply;
Asciz	(Ljava/lang/Object;Ljava/lang/Object;)Ljava/lang/Object;;
Asciz	scala/util/regexp/Base$RegExp;
class	scala/util/regexp/Base$RegExp
Asciz	scala/collection/immutable/Set;
class	scala/collection/immutable/Set
Asciz	(Lscala/util/regexp/Base$RegExp;Lscala/collection/immutable/Set;)Lscala/collection/immutable/Set;;
NameAndType	apply:(Lscala/util/regexp/Base$RegExp;Lscala/collection/immutable/Set;)Lscala/collection/immutable/Set;
Method	scala/util/automata/BaseBerrySethi$$anonfun$compFollow1$2.apply:(Lscala/util/regexp/Base$RegExp;Lscala/collection/immutable/Set;)Lscala/collection/immutable/Set;
Asciz	v1;
Asciz	Ljava/lang/Object;;
Asciz	v2;
Asciz	scala/util/automata/BaseBerrySethi;
class	scala/util/automata/BaseBerrySethi
Asciz	compFollow1;
Asciz	(Lscala/collection/immutable/Set;Lscala/util/regexp/Base$RegExp;)Lscala/collection/immutable/Set;;
NameAndType	compFollow1:(Lscala/collection/immutable/Set;Lscala/util/regexp/Base$RegExp;)Lscala/collection/immutable/Set;
Method	scala/util/automata/BaseBerrySethi.compFollow1:(Lscala/collection/immutable/Set;Lscala/util/regexp/Base$RegExp;)Lscala/collection/immutable/Set;
Asciz	isNullable;
Asciz	()Z;
NameAndType	isNullable:()Z
Method	scala/util/regexp/Base$RegExp.isNullable:()Z
Asciz	scala/collection/generic/Addable;
class	scala/collection/generic/Addable
Asciz	$plus$plus;
Asciz	(Lscala/collection/Traversable;)Lscala/collection/generic/Addable;;
NameAndType	$plus$plus:(Lscala/collection/Traversable;)Lscala/collection/generic/Addable;
InterfaceMethod	scala/collection/generic/Addable.$plus$plus:(Lscala/collection/Traversable;)Lscala/collection/generic/Addable;
Asciz	p;
Asciz	Lscala/util/regexp/Base$RegExp;;
Asciz	fol;
Asciz	Lscala/collection/immutable/Set;;
Asciz	first;
Asciz	(Lscala/util/regexp/Base$RegExp;Lscala/collection/immutable/Set<Ljava/lang/Integer;>;)Lscala/collection/immutable/Set<Ljava/lang/Integer;>;;
Asciz	Signature;
Asciz	Scala;
Asciz	InnerClasses;
Asciz	scala/util/regexp/Base;
class	scala/util/regexp/Base
Asciz	RegExp;
Asciz	$anonfun$compFollow1$2;
Asciz	java/io/Serializable;
class	java/io/Serializable

{
public static final long serialVersionUID;
  Signature: J

public final scala.util.automata.BaseBerrySethi $outer;
  Signature: Lscala/util/automata/BaseBerrySethi;

public static {};
  Signature: ()V
  Code:
   Stack=2, Locals=0, Args_size=0
	lconst_0
	putstatic	Field serialVersionUID:J
	return
  Labels:

public scala.util.automata.BaseBerrySethi$$anonfun$compFollow1$2(scala.util.automata.BaseBerrySethi);
  Signature: (Lscala/util/automata/BaseBerrySethi;)V
  Code:
   Stack=2, Locals=2, Args_size=2
	aload_1
	ifnonnull	l1 // aload_0
	new	class java/lang/NullPointerException
	dup
	invokespecial	Method java/lang/NullPointerException."<init>":()V
	athrow
l1	aload_0
	aload_1
	putfield	Field $outer:Lscala/util/automata/BaseBerrySethi;
	aload_0
	invokespecial	Method scala/runtime/AbstractFunction2."<init>":()V
	return
  Labels:
   	l1 = 12 // aload_0
  LocalVariableTable: 
   Start  Length  Slot  Name   Signature
   0      22      0    this       Lscala/util/automata/BaseBerrySethi$$anonfun$compFollow1$2;
   0      22      1    $outer       Lscala/util/automata/BaseBerrySethi;


public final java.lang.Object apply(java.lang.Object, java.lang.Object);
  Signature: (Ljava/lang/Object;Ljava/lang/Object;)Ljava/lang/Object;
  Code:
   Stack=3, Locals=3, Args_size=3
	aload_0
	aload_1
	checkcast	class scala/util/regexp/Base$RegExp
	aload_2
	checkcast	class scala/collection/immutable/Set
	invokevirtual	Method apply:(Lscala/util/regexp/Base$RegExp;Lscala/collection/immutable/Set;)Lscala/collection/immutable/Set;
	areturn
  Labels:
  LocalVariableTable: 
   Start  Length  Slot  Name   Signature
   0      13      0    this       Lscala/util/automata/BaseBerrySethi$$anonfun$compFollow1$2;
   0      13      1    v1       Ljava/lang/Object;
   0      13      2    v2       Ljava/lang/Object;


public final scala.collection.immutable.Set apply(scala.util.regexp.Base$RegExp, scala.collection.immutable.Set);
  Signature: (Lscala/util/regexp/Base$RegExp;Lscala/collection/immutable/Set;)Lscala/collection/immutable/Set;
  Code:
   Stack=3, Locals=4, Args_size=3
	aload_0
	getfield	Field $outer:Lscala/util/automata/BaseBerrySethi;
	aload_2
	aload_1
	invokevirtual	Method scala/util/automata/BaseBerrySethi.compFollow1:(Lscala/collection/immutable/Set;Lscala/util/regexp/Base$RegExp;)Lscala/collection/immutable/Set;
	astore_3
	aload_1
	invokevirtual	Method scala/util/regexp/Base$RegExp.isNullable:()Z
	ifeq	l1 // aload_3
	aload_2
	aload_3
	invokeinterface	InterfaceMethod scala/collection/generic/Addable.$plus$plus:(Lscala/collection/Traversable;)Lscala/collection/generic/Addable;
	checkcast	class scala/collection/immutable/Set
	goto	l2 // areturn
l1	aload_3
l2	areturn
  Labels:
   	l1 = 30 // aload_3
   	l2 = 31 // areturn
  LocalVariableTable: 
   Start  Length  Slot  Name   Signature
   0      32      0    this       Lscala/util/automata/BaseBerrySethi$$anonfun$compFollow1$2;
   0      32      1    p       Lscala/util/regexp/Base$RegExp;
   0      32      2    fol       Lscala/collection/immutable/Set;
   10      22      3    first       Lscala/collection/immutable/Set;

  Signature: length = 0x2
   00 3E 

}

