Compiled from "BaseBerrySethi.scala"
public abstract class scala.util.automata.BaseBerrySethi extends java.lang.Object implements scala.ScalaObject
  SourceFile: "BaseBerrySethi.scala"
  ScalaSig: length = 0x3DB
   05 00 FFFFFF81 15 06 08 01 02 FFFFFF84 FFFFFF80 FFFFFF80 FFFFFF81 00 09 02 0E
   42 61 73 65 42 65 72 72 79 53 65 74 68 69 0A 02
   03 04 01 08 61 75 74 6F 6D 61 74 61 0A 02 05 06
   01 04 75 74 69 6C 0A 01 07 01 05 73 63 61 6C 61
   03 00 13 03 00 0A 12 10 02 0B 10 0D 01 0C 0A 02
   0D 0E 01 04 6C 61 6E 67 0A 01 0F 01 04 6A 61 76
   61 09 02 11 0C 02 06 4F 62 6A 65 63 74 10 02 13
   14 0D 01 06 09 02 15 06 02 0B 53 63 61 6C 61 4F
   62 6A 65 63 74 08 05 17 00 FFFFFF84 00 18 01 06 3C 69
   6E 69 74 3E 14 01 19 10 02 1A 00 0D 01 02 08 07
   0D 00 FFFFFFC2 FFFFFF80 FFFFFF86 00 1C 15 01 1D 10 02 1E 21 0D 01
   1F 0A 02 20 04 01 06 72 65 67 65 78 70 09 02 22
   1F 02 04 42 61 73 65 08 07 24 00 FFFFFFC0 FFFFFF80 FFFFFF84 08 25
   01 03 70 6F 73 15 01 26 10 02 13 27 09 02 28 06
   02 03 49 6E 74 08 07 2A 00 FFFFFFC0 FFFFFF80 FFFFFF84 08 2B 01 07
   70 6F 73 5F 24 65 71 14 02 2C 2F 10 02 13 2D 09
   02 2E 06 02 04 55 6E 69 74 08 07 30 29 FFFFFF81 FFFFFF80 FFFFFFC0
   00 26 01 03 78 24 31 08 06 32 00 FFFFFFA0 FFFFFFA0 04 26 01
   04 70 6F 73 20 08 07 34 00 FFFFFFC0 FFFFFF80 FFFFFF84 08 35 01 06
   66 6F 6C 6C 6F 77 15 01 36 10 04 37 3C 26 3E 0D
   01 38 0A 02 39 3A 01 07 6D 75 74 61 62 6C 65 0A
   02 3B 06 01 0A 63 6F 6C 6C 65 63 74 69 6F 6E 09
   02 3D 38 02 07 48 61 73 68 4D 61 70 10 03 3F 42
   26 0D 01 40 0A 02 41 3A 01 09 69 6D 6D 75 74 61
   62 6C 65 09 02 43 40 02 03 53 65 74 08 07 45 00
   FFFFFFC0 FFFFFF80 FFFFFF84 08 46 01 0A 66 6F 6C 6C 6F 77 5F 24 65
   71 14 02 2C 47 08 07 30 44 FFFFFF81 FFFFFF80 FFFFFFC0 00 36 08 06
   49 00 FFFFFFA0 FFFFFFA0 04 36 01 07 66 6F 6C 6C 6F 77 20 08
   07 4B 00 FFFFFFC0 FFFFFF80 FFFFFF84 08 25 01 08 66 69 6E 61 6C 54
   61 67 08 07 4D 00 FFFFFFC0 FFFFFF80 FFFFFF84 08 4E 01 0C 66 69 6E
   61 6C 54 61 67 5F 24 65 71 14 02 2C 4F 08 07 30
   4C FFFFFF81 FFFFFF80 FFFFFFC0 00 26 08 06 51 00 FFFFFFA0 FFFFFFA0 04 26 01 09
   66 69 6E 61 6C 54 61 67 20 08 07 53 00 FFFFFFC0 FFFFFF80 FFFFFF84
   08 54 01 06 66 69 6E 61 6C 73 15 01 55 10 04 3F
   56 26 26 09 02 57 40 02 03 4D 61 70 08 07 59 00
   FFFFFFC0 FFFFFF80 FFFFFF84 08 5A 01 0A 66 69 6E 61 6C 73 5F 24 65
   71 14 02 2C 5B 08 07 30 58 FFFFFF81 FFFFFF80 FFFFFFC0 00 55 08 06
   5D 00 FFFFFFA0 FFFFFFA0 04 55 01 07 66 69 6E 61 6C 73 20 08
   07 5F 00 FFFFFFC2 FFFFFF80 FFFFFF84 02 60 01 08 65 6D 70 74 79 53
   65 74 15 01 3E 08 06 62 00 FFFFFFA0 FFFFFF80 06 3E 01 09 65
   6D 70 74 79 53 65 74 20 08 05 64 00 FFFFFF84 04 65 01
   06 64 6F 43 6F 6D 70 14 03 3E 66 6D 08 05 67 63
   FFFFFFC0 00 68 01 01 72 10 02 69 6B 0E 02 6A 1B 0D 01
   00 09 02 6C 21 02 06 52 65 67 45 78 70 08 05 6E
   63 FFFFFFC0 00 6F 01 0C 63 6F 6D 70 46 75 6E 63 74 69
   6F 6E 10 04 13 70 68 3E 09 02 71 06 02 09 46 75
   6E 63 74 69 6F 6E 31 08 05 73 00 FFFFFF84 08 74 01 09
   63 6F 6D 70 46 69 72 73 74 14 02 3E 75 08 05 67
   72 FFFFFFC0 00 68 08 05 77 00 FFFFFF84 08 78 01 08 63 6F 6D
   70 4C 61 73 74 14 02 3E 79 08 05 67 76 FFFFFFC0 00 68
   08 05 7B 00 FFFFFF84 08 7C 01 0A 63 6F 6D 70 46 6F 6C
   6C 6F 77 14 02 3E 7D 08 05 7E 7A FFFFFFC0 00 7F 01 02
   72 73 10 05 FFFFFF81 00 FFFFFF81 08 68 0E 04 FFFFFF81 01 FFFFFF81 06 0E
   04 FFFFFF81 02 FFFFFF81 05 0D 02 FFFFFF81 03 0A 03 FFFFFF81 04 08 01 06
   3C 72 6F 6F 74 3E 09 01 07 09 03 FFFFFF81 07 06 01 07
   70 61 63 6B 61 67 65 09 04 FFFFFF81 09 FFFFFF81 0A 02 03 53
   65 71 0A 03 FFFFFF81 07 06 08 07 FFFFFF81 0C 00 FFFFFF84 08 FFFFFF81 0D
   01 0B 63 6F 6D 70 46 6F 6C 6C 6F 77 31 14 05 3E
   FFFFFF81 0E FFFFFF81 10 08 07 FFFFFF81 0F FFFFFF81 0B FFFFFFC0 00 3E 01 04 66
   6F 6C 31 08 06 67 FFFFFF81 0B FFFFFFC0 00 68 08 07 FFFFFF81 12 00
   FFFFFF84 08 FFFFFF81 13 01 08 74 72 61 76 65 72 73 65 14 03
   2C FFFFFF81 14 08 06 67 FFFFFF81 11 FFFFFFC0 00 68 
  InnerClass: 
   public Alt=class scala/util/regexp/Base$Alt of class scala/util/regexp/Base
   public Star=class scala/util/regexp/Base$Star of class scala/util/regexp/Base
   public Meta=class scala/util/regexp/Base$Meta of class scala/util/regexp/Base
   public Sequ=class scala/util/regexp/Base$Sequ of class scala/util/regexp/Base
   public abstract RegExp=class scala/util/regexp/Base$RegExp of class scala/util/regexp/Base
   public final $anon$1=class scala/Predef$$anon$1 of class scala/Predef
   public final $anonfun$1=class scala/util/automata/BaseBerrySethi$$anonfun$1 of class scala/util/automata/BaseBerrySethi
   public final $anonfun$doComp$3=class scala/util/automata/BaseBerrySethi$$anonfun$doComp$3 of class scala/util/automata/BaseBerrySethi
   public final $anonfun$doComp$2=class scala/util/automata/BaseBerrySethi$$anonfun$doComp$2 of class scala/util/automata/BaseBerrySethi
   public final $anonfun$doComp$1=class scala/util/automata/BaseBerrySethi$$anonfun$doComp$1 of class scala/util/automata/BaseBerrySethi
   public final $anonfun$compLast$1=class scala/util/automata/BaseBerrySethi$$anonfun$compLast$1 of class scala/util/automata/BaseBerrySethi
   public final $anonfun$traverse$2=class scala/util/automata/BaseBerrySethi$$anonfun$traverse$2 of class scala/util/automata/BaseBerrySethi
   public final $anonfun$traverse$1=class scala/util/automata/BaseBerrySethi$$anonfun$traverse$1 of class scala/util/automata/BaseBerrySethi
   public final $anonfun$compFirst$1=class scala/util/automata/BaseBerrySethi$$anonfun$compFirst$1 of class scala/util/automata/BaseBerrySethi
   public final $anonfun$compFollow$1=class scala/util/automata/BaseBerrySethi$$anonfun$compFollow$1 of class scala/util/automata/BaseBerrySethi
   public final $anonfun$compFollow1$2=class scala/util/automata/BaseBerrySethi$$anonfun$compFollow1$2 of class scala/util/automata/BaseBerrySethi
   public final $anonfun$compFollow1$1=class scala/util/automata/BaseBerrySethi$$anonfun$compFollow1$1 of class scala/util/automata/BaseBerrySethi
   public GenericCanBuildFrom=class scala/collection/generic/TraversableFactory$GenericCanBuildFrom of class scala/collection/generic/TraversableFactory
  minor version: 0
  major version: 49
  Constant pool:
Asciz	SourceFile;
Asciz	BaseBerrySethi.scala;
Asciz	emptySet;
Asciz	Lscala/collection/immutable/Set;;
Asciz	Lscala/collection/immutable/Set<Ljava/lang/Integer;>;;
Asciz	Signature;
Asciz	finals;
Asciz	Lscala/collection/immutable/Map;;
Asciz	Lscala/collection/immutable/Map<Ljava/lang/Integer;Ljava/lang/Integer;>;;
Asciz	finalTag;
Asciz	I;
Asciz	follow;
Asciz	Lscala/collection/mutable/HashMap;;
Asciz	Lscala/collection/mutable/HashMap<Ljava/lang/Integer;Lscala/collection/immutable/Set<Ljava/lang/Integer;>;>;;
Asciz	pos;
Asciz	<init>;
Asciz	()V;
Asciz	Code;
Asciz	LineNumberTable;
Asciz	java/lang/Object;
class	java/lang/Object
NameAndType	"<init>":()V
Method	java/lang/Object."<init>":()V
Asciz	scala/util/automata/BaseBerrySethi;
class	scala/util/automata/BaseBerrySethi
NameAndType	pos:I
Field	scala/util/automata/BaseBerrySethi.pos:I
Asciz	scala/collection/immutable/Set$;
class	scala/collection/immutable/Set$
Asciz	MODULE$;
Asciz	Lscala/collection/immutable/Set$;;
NameAndType	MODULE$:Lscala/collection/immutable/Set$;
Field	scala/collection/immutable/Set$.MODULE$:Lscala/collection/immutable/Set$;
Asciz	scala/Predef$;
class	scala/Predef$
Asciz	Lscala/Predef$;;
NameAndType	MODULE$:Lscala/Predef$;
Field	scala/Predef$.MODULE$:Lscala/Predef$;
Asciz	wrapIntArray;
Asciz	([I)Lscala/collection/mutable/WrappedArray;;
NameAndType	wrapIntArray:([I)Lscala/collection/mutable/WrappedArray;
Method	scala/Predef$.wrapIntArray:([I)Lscala/collection/mutable/WrappedArray;
Asciz	apply;
Asciz	(Lscala/collection/Seq;)Lscala/collection/Traversable;;
NameAndType	apply:(Lscala/collection/Seq;)Lscala/collection/Traversable;
Method	scala/collection/immutable/Set$.apply:(Lscala/collection/Seq;)Lscala/collection/Traversable;
Asciz	scala/collection/immutable/Set;
class	scala/collection/immutable/Set
NameAndType	emptySet:Lscala/collection/immutable/Set;
Field	scala/util/automata/BaseBerrySethi.emptySet:Lscala/collection/immutable/Set;
Asciz	traverse;
Asciz	(Lscala/util/regexp/Base$RegExp;)V;
Asciz	scala/util/regexp/Base$Alt;
class	scala/util/regexp/Base$Alt
Asciz	rs;
Asciz	()Lscala/collection/Seq;;
NameAndType	rs:()Lscala/collection/Seq;
Method	scala/util/regexp/Base$Alt.rs:()Lscala/collection/Seq;
Asciz	scala/util/automata/BaseBerrySethi$$anonfun$traverse$1;
class	scala/util/automata/BaseBerrySethi$$anonfun$traverse$1
Asciz	(Lscala/util/automata/BaseBerrySethi;)V;
NameAndType	"<init>":(Lscala/util/automata/BaseBerrySethi;)V
Method	scala/util/automata/BaseBerrySethi$$anonfun$traverse$1."<init>":(Lscala/util/automata/BaseBerrySethi;)V
Asciz	scala/collection/IterableLike;
class	scala/collection/IterableLike
Asciz	foreach;
Asciz	(Lscala/Function1;)V;
NameAndType	foreach:(Lscala/Function1;)V
InterfaceMethod	scala/collection/IterableLike.foreach:(Lscala/Function1;)V
Asciz	scala/MatchError;
class	scala/MatchError
Asciz	scala/util/regexp/Base$RegExp;
class	scala/util/regexp/Base$RegExp
Asciz	toString;
Asciz	()Ljava/lang/String;;
NameAndType	toString:()Ljava/lang/String;
Method	scala/util/regexp/Base$RegExp.toString:()Ljava/lang/String;
Asciz	(Ljava/lang/String;)V;
NameAndType	"<init>":(Ljava/lang/String;)V
Method	scala/MatchError."<init>":(Ljava/lang/String;)V
Asciz	scala/util/regexp/Base$Sequ;
class	scala/util/regexp/Base$Sequ
Method	scala/util/regexp/Base$Sequ.rs:()Lscala/collection/Seq;
Asciz	scala/util/automata/BaseBerrySethi$$anonfun$traverse$2;
class	scala/util/automata/BaseBerrySethi$$anonfun$traverse$2
Method	scala/util/automata/BaseBerrySethi$$anonfun$traverse$2."<init>":(Lscala/util/automata/BaseBerrySethi;)V
Asciz	scala/util/regexp/Base$Meta;
class	scala/util/regexp/Base$Meta
Asciz	r;
Asciz	()Lscala/util/regexp/Base$RegExp;;
NameAndType	r:()Lscala/util/regexp/Base$RegExp;
Method	scala/util/regexp/Base$Meta.r:()Lscala/util/regexp/Base$RegExp;
NameAndType	traverse:(Lscala/util/regexp/Base$RegExp;)V
Method	scala/util/automata/BaseBerrySethi.traverse:(Lscala/util/regexp/Base$RegExp;)V
Asciz	scala/util/regexp/Base$Star;
class	scala/util/regexp/Base$Star
Method	scala/util/regexp/Base$Star.r:()Lscala/util/regexp/Base$RegExp;
Asciz	java/lang/IllegalArgumentException;
class	java/lang/IllegalArgumentException
Asciz	scala/collection/mutable/StringBuilder;
class	scala/collection/mutable/StringBuilder
Method	scala/collection/mutable/StringBuilder."<init>":()V
Asciz	unexp pattern ;
String	unexp pattern 
Asciz	append;
Asciz	(Ljava/lang/Object;)Lscala/collection/mutable/StringBuilder;;
NameAndType	append:(Ljava/lang/Object;)Lscala/collection/mutable/StringBuilder;
Method	scala/collection/mutable/StringBuilder.append:(Ljava/lang/Object;)Lscala/collection/mutable/StringBuilder;
Asciz	getClass;
Asciz	()Ljava/lang/Class;;
NameAndType	getClass:()Ljava/lang/Class;
Method	scala/util/regexp/Base$RegExp.getClass:()Ljava/lang/Class;
Method	scala/collection/mutable/StringBuilder.toString:()Ljava/lang/String;
Method	java/lang/IllegalArgumentException."<init>":(Ljava/lang/String;)V
Asciz	this;
Asciz	Lscala/util/automata/BaseBerrySethi;;
Asciz	Lscala/util/regexp/Base$RegExp;;
Asciz	temp17;
Asciz	Lscala/util/regexp/Base$Alt;;
Asciz	temp18;
Asciz	Lscala/util/regexp/Base$Sequ;;
Asciz	temp19;
Asciz	Lscala/util/regexp/Base$Meta;;
Asciz	temp20;
Asciz	Lscala/util/regexp/Base$Star;;
Asciz	temp21;
Asciz	LocalVariableTable;
Asciz	compFollow1;
Asciz	(Lscala/collection/immutable/Set;Lscala/util/regexp/Base$RegExp;)Lscala/collection/immutable/Set;;
Asciz	scala/util/automata/BaseBerrySethi$$anonfun$compFollow1$1;
class	scala/util/automata/BaseBerrySethi$$anonfun$compFollow1$1
Asciz	(Lscala/util/automata/BaseBerrySethi;Lscala/collection/immutable/Set;)V;
NameAndType	"<init>":(Lscala/util/automata/BaseBerrySethi;Lscala/collection/immutable/Set;)V
Method	scala/util/automata/BaseBerrySethi$$anonfun$compFollow1$1."<init>":(Lscala/util/automata/BaseBerrySethi;Lscala/collection/immutable/Set;)V
Asciz	scala/collection/Seq$;
class	scala/collection/Seq$
Asciz	Lscala/collection/Seq$;;
NameAndType	MODULE$:Lscala/collection/Seq$;
Field	scala/collection/Seq$.MODULE$:Lscala/collection/Seq$;
Asciz	scala/collection/generic/TraversableFactory$GenericCanBuildFrom;
class	scala/collection/generic/TraversableFactory$GenericCanBuildFrom
Asciz	(Lscala/collection/generic/TraversableFactory;)V;
NameAndType	"<init>":(Lscala/collection/generic/TraversableFactory;)V
Method	scala/collection/generic/TraversableFactory$GenericCanBuildFrom."<init>":(Lscala/collection/generic/TraversableFactory;)V
Asciz	scala/collection/SeqLike;
class	scala/collection/SeqLike
Asciz	reverseMap;
Asciz	(Lscala/Function1;Lscala/collection/generic/CanBuildFrom;)Ljava/lang/Object;;
NameAndType	reverseMap:(Lscala/Function1;Lscala/collection/generic/CanBuildFrom;)Ljava/lang/Object;
InterfaceMethod	scala/collection/SeqLike.reverseMap:(Lscala/Function1;Lscala/collection/generic/CanBuildFrom;)Ljava/lang/Object;
Asciz	scala/collection/generic/GenericTraversableTemplate;
class	scala/collection/generic/GenericTraversableTemplate
Asciz	scala/Predef$$anon$1;
class	scala/Predef$$anon$1
Method	scala/Predef$$anon$1."<init>":()V
Asciz	flatten;
Asciz	(Lscala/Function1;)Lscala/collection/Traversable;;
NameAndType	flatten:(Lscala/Function1;)Lscala/collection/Traversable;
InterfaceMethod	scala/collection/generic/GenericTraversableTemplate.flatten:(Lscala/Function1;)Lscala/collection/Traversable;
Asciz	scala/collection/Seq;
class	scala/collection/Seq
NameAndType	compFollow1:(Lscala/collection/immutable/Set;Lscala/util/regexp/Base$RegExp;)Lscala/collection/immutable/Set;
Method	scala/util/automata/BaseBerrySethi.compFollow1:(Lscala/collection/immutable/Set;Lscala/util/regexp/Base$RegExp;)Lscala/collection/immutable/Set;
Asciz	compFirst;
Asciz	(Lscala/util/regexp/Base$RegExp;)Lscala/collection/immutable/Set;;
NameAndType	compFirst:(Lscala/util/regexp/Base$RegExp;)Lscala/collection/immutable/Set;
Method	scala/util/automata/BaseBerrySethi.compFirst:(Lscala/util/regexp/Base$RegExp;)Lscala/collection/immutable/Set;
Asciz	scala/collection/generic/Addable;
class	scala/collection/generic/Addable
Asciz	$plus$plus;
Asciz	(Lscala/collection/Traversable;)Lscala/collection/generic/Addable;;
NameAndType	$plus$plus:(Lscala/collection/Traversable;)Lscala/collection/generic/Addable;
InterfaceMethod	scala/collection/generic/Addable.$plus$plus:(Lscala/collection/Traversable;)Lscala/collection/generic/Addable;
Asciz	scala/util/automata/BaseBerrySethi$$anonfun$compFollow1$2;
class	scala/util/automata/BaseBerrySethi$$anonfun$compFollow1$2
Method	scala/util/automata/BaseBerrySethi$$anonfun$compFollow1$2."<init>":(Lscala/util/automata/BaseBerrySethi;)V
Asciz	foldRight;
Asciz	(Ljava/lang/Object;Lscala/Function2;)Ljava/lang/Object;;
NameAndType	foldRight:(Ljava/lang/Object;Lscala/Function2;)Ljava/lang/Object;
InterfaceMethod	scala/collection/IterableLike.foldRight:(Ljava/lang/Object;Lscala/Function2;)Ljava/lang/Object;
Asciz	unexpected pattern: ;
String	unexpected pattern: 
Asciz	fol1$1;
Asciz	temp11;
Asciz	temp12;
Asciz	temp13;
Asciz	temp15;
Asciz	first;
Asciz	(Lscala/collection/immutable/Set<Ljava/lang/Integer;>;Lscala/util/regexp/Base$RegExp;)Lscala/collection/immutable/Set<Ljava/lang/Integer;>;;
Asciz	compFollow;
Asciz	(Lscala/collection/Seq;)Lscala/collection/immutable/Set;;
Asciz	()Lscala/collection/mutable/HashMap;;
NameAndType	follow:()Lscala/collection/mutable/HashMap;
Method	scala/util/automata/BaseBerrySethi.follow:()Lscala/collection/mutable/HashMap;
Asciz	scala/runtime/BoxesRunTime;
class	scala/runtime/BoxesRunTime
Asciz	boxToInteger;
Asciz	(I)Ljava/lang/Integer;;
NameAndType	boxToInteger:(I)Ljava/lang/Integer;
Method	scala/runtime/BoxesRunTime.boxToInteger:(I)Ljava/lang/Integer;
Asciz	isEmpty;
Asciz	()Z;
NameAndType	isEmpty:()Z
InterfaceMethod	scala/collection/IterableLike.isEmpty:()Z
Asciz	()I;
NameAndType	pos:()I
Method	scala/util/automata/BaseBerrySethi.pos:()I
Asciz	scala/util/automata/BaseBerrySethi$$anonfun$compFollow$1;
class	scala/util/automata/BaseBerrySethi$$anonfun$compFollow$1
Method	scala/util/automata/BaseBerrySethi$$anonfun$compFollow$1."<init>":(Lscala/util/automata/BaseBerrySethi;)V
Asciz	scala/collection/mutable/HashMap;
class	scala/collection/mutable/HashMap
Asciz	update;
Asciz	(Ljava/lang/Object;Ljava/lang/Object;)V;
NameAndType	update:(Ljava/lang/Object;Ljava/lang/Object;)V
Method	scala/collection/mutable/HashMap.update:(Ljava/lang/Object;Ljava/lang/Object;)V
Asciz	scala/collection/MapLike;
class	scala/collection/MapLike
Asciz	(Ljava/lang/Object;)Ljava/lang/Object;;
NameAndType	apply:(Ljava/lang/Object;)Ljava/lang/Object;
InterfaceMethod	scala/collection/MapLike.apply:(Ljava/lang/Object;)Ljava/lang/Object;
Asciz	Lscala/collection/Seq;;
Asciz	(Lscala/collection/Seq<Lscala/util/regexp/Base$RegExp;>;)Lscala/collection/immutable/Set<Ljava/lang/Integer;>;;
Asciz	compLast;
Asciz	scala/util/automata/BaseBerrySethi$$anonfun$compLast$1;
class	scala/util/automata/BaseBerrySethi$$anonfun$compLast$1
Method	scala/util/automata/BaseBerrySethi$$anonfun$compLast$1."<init>":(Lscala/util/automata/BaseBerrySethi;)V
Asciz	doComp;
Asciz	(Lscala/util/regexp/Base$RegExp;Lscala/Function1;)Lscala/collection/immutable/Set;;
NameAndType	doComp:(Lscala/util/regexp/Base$RegExp;Lscala/Function1;)Lscala/collection/immutable/Set;
Method	scala/util/automata/BaseBerrySethi.doComp:(Lscala/util/regexp/Base$RegExp;Lscala/Function1;)Lscala/collection/immutable/Set;
Asciz	(Lscala/util/regexp/Base$RegExp;)Lscala/collection/immutable/Set<Ljava/lang/Integer;>;;
Asciz	scala/util/automata/BaseBerrySethi$$anonfun$compFirst$1;
class	scala/util/automata/BaseBerrySethi$$anonfun$compFirst$1
Method	scala/util/automata/BaseBerrySethi$$anonfun$compFirst$1."<init>":(Lscala/util/automata/BaseBerrySethi;)V
Asciz	scala/util/automata/BaseBerrySethi$$anonfun$doComp$1;
class	scala/util/automata/BaseBerrySethi$$anonfun$doComp$1
Method	scala/util/automata/BaseBerrySethi$$anonfun$doComp$1."<init>":(Lscala/util/automata/BaseBerrySethi;)V
Asciz	scala/collection/TraversableLike;
class	scala/collection/TraversableLike
Asciz	map;
NameAndType	map:(Lscala/Function1;Lscala/collection/generic/CanBuildFrom;)Ljava/lang/Object;
InterfaceMethod	scala/collection/TraversableLike.map:(Lscala/Function1;Lscala/collection/generic/CanBuildFrom;)Ljava/lang/Object;
Asciz	scala/util/automata/BaseBerrySethi$$anonfun$doComp$2;
class	scala/util/automata/BaseBerrySethi$$anonfun$doComp$2
Method	scala/util/automata/BaseBerrySethi$$anonfun$doComp$2."<init>":(Lscala/util/automata/BaseBerrySethi;)V
Asciz	foldLeft;
NameAndType	foldLeft:(Ljava/lang/Object;Lscala/Function2;)Ljava/lang/Object;
InterfaceMethod	scala/collection/TraversableLike.foldLeft:(Ljava/lang/Object;Lscala/Function2;)Ljava/lang/Object;
Asciz	lang;
Asciz	()Lscala/util/regexp/Base;;
NameAndType	lang:()Lscala/util/regexp/Base;
Method	scala/util/automata/BaseBerrySethi.lang:()Lscala/util/regexp/Base;
Asciz	scala/util/regexp/Base;
class	scala/util/regexp/Base
Asciz	Eps;
Asciz	()Lscala/util/regexp/Base$Eps$;;
NameAndType	Eps:()Lscala/util/regexp/Base$Eps$;
Method	scala/util/regexp/Base.Eps:()Lscala/util/regexp/Base$Eps$;
Asciz	equals;
Asciz	(Ljava/lang/Object;)Z;
NameAndType	equals:(Ljava/lang/Object;)Z
Method	java/lang/Object.equals:(Ljava/lang/Object;)Z
Asciz	scala/Function1;
class	scala/Function1
InterfaceMethod	scala/Function1.apply:(Ljava/lang/Object;)Ljava/lang/Object;
Asciz	scala/util/automata/BaseBerrySethi$$anonfun$1;
class	scala/util/automata/BaseBerrySethi$$anonfun$1
Method	scala/util/automata/BaseBerrySethi$$anonfun$1."<init>":(Lscala/util/automata/BaseBerrySethi;)V
Asciz	span;
Asciz	(Lscala/Function1;)Lscala/Tuple2;;
NameAndType	span:(Lscala/Function1;)Lscala/Tuple2;
InterfaceMethod	scala/collection/TraversableLike.span:(Lscala/Function1;)Lscala/Tuple2;
Asciz	scala/Tuple2;
class	scala/Tuple2
Asciz	_1;
Asciz	()Ljava/lang/Object;;
NameAndType	_1:()Ljava/lang/Object;
Method	scala/Tuple2._1:()Ljava/lang/Object;
Asciz	_2;
NameAndType	_2:()Ljava/lang/Object;
Method	scala/Tuple2._2:()Ljava/lang/Object;
NameAndType	"<init>":(Ljava/lang/Object;Ljava/lang/Object;)V
Method	scala/Tuple2."<init>":(Ljava/lang/Object;Ljava/lang/Object;)V
Asciz	take;
Asciz	(I)Ljava/lang/Object;;
NameAndType	take:(I)Ljava/lang/Object;
InterfaceMethod	scala/collection/IterableLike.take:(I)Ljava/lang/Object;
Asciz	scala/collection/Traversable;
class	scala/collection/Traversable
Asciz	(Lscala/collection/Traversable;Lscala/collection/generic/CanBuildFrom;)Ljava/lang/Object;;
NameAndType	$plus$plus:(Lscala/collection/Traversable;Lscala/collection/generic/CanBuildFrom;)Ljava/lang/Object;
InterfaceMethod	scala/collection/TraversableLike.$plus$plus:(Lscala/collection/Traversable;Lscala/collection/generic/CanBuildFrom;)Ljava/lang/Object;
Asciz	scala/util/automata/BaseBerrySethi$$anonfun$doComp$3;
class	scala/util/automata/BaseBerrySethi$$anonfun$doComp$3
Method	scala/util/automata/BaseBerrySethi$$anonfun$doComp$3."<init>":(Lscala/util/automata/BaseBerrySethi;)V
Method	scala/Tuple2.toString:()Ljava/lang/String;
Asciz	unexpected pattern ;
String	unexpected pattern 
Asciz	compFunction;
Asciz	Lscala/Function1;;
Asciz	temp5;
Asciz	temp6;
Asciz	temp7;
Asciz	temp2;
Asciz	temp3;
Asciz	l1;
Asciz	l2;
Asciz	temp1;
Asciz	Lscala/Tuple2;;
Asciz	temp8;
Asciz	temp9;
Asciz	(Lscala/util/regexp/Base$RegExp;Lscala/Function1<Lscala/util/regexp/Base$RegExp;Lscala/collection/immutable/Set<Ljava/lang/Integer;>;>;)Lscala/collection/immutable/Set<Ljava/lang/Integer;>;;
Asciz	()Lscala/collection/immutable/Set;;
Asciz	()Lscala/collection/immutable/Set<Ljava/lang/Integer;>;;
Asciz	finals_$eq;
Asciz	(Lscala/collection/immutable/Map;)V;
NameAndType	finals:Lscala/collection/immutable/Map;
Field	scala/util/automata/BaseBerrySethi.finals:Lscala/collection/immutable/Map;
Asciz	(Lscala/collection/immutable/Map<Ljava/lang/Integer;Ljava/lang/Integer;>;)V;
Asciz	()Lscala/collection/immutable/Map;;
Asciz	()Lscala/collection/immutable/Map<Ljava/lang/Integer;Ljava/lang/Integer;>;;
Asciz	finalTag_$eq;
Asciz	(I)V;
NameAndType	finalTag:I
Field	scala/util/automata/BaseBerrySethi.finalTag:I
Asciz	follow_$eq;
Asciz	(Lscala/collection/mutable/HashMap;)V;
NameAndType	follow:Lscala/collection/mutable/HashMap;
Field	scala/util/automata/BaseBerrySethi.follow:Lscala/collection/mutable/HashMap;
Asciz	(Lscala/collection/mutable/HashMap<Ljava/lang/Integer;Lscala/collection/immutable/Set<Ljava/lang/Integer;>;>;)V;
Asciz	()Lscala/collection/mutable/HashMap<Ljava/lang/Integer;Lscala/collection/immutable/Set<Ljava/lang/Integer;>;>;;
Asciz	pos_$eq;
Asciz	ScalaSig;
Asciz	InnerClasses;
Asciz	Alt;
Asciz	Star;
Asciz	Meta;
Asciz	Sequ;
Asciz	RegExp;
Asciz	scala/Predef;
class	scala/Predef
Asciz	$anon$1;
Asciz	$anonfun$1;
Asciz	$anonfun$doComp$3;
Asciz	$anonfun$doComp$2;
Asciz	$anonfun$doComp$1;
Asciz	$anonfun$compLast$1;
Asciz	$anonfun$traverse$2;
Asciz	$anonfun$traverse$1;
Asciz	$anonfun$compFirst$1;
Asciz	$anonfun$compFollow$1;
Asciz	$anonfun$compFollow1$2;
Asciz	$anonfun$compFollow1$1;
Asciz	scala/collection/generic/TraversableFactory;
class	scala/collection/generic/TraversableFactory
Asciz	GenericCanBuildFrom;
Asciz	scala/ScalaObject;
class	scala/ScalaObject

{
private final scala.collection.immutable.Set emptySet;
  Signature: Lscala/collection/immutable/Set;
  Signature: length = 0x2
   00 05 

private scala.collection.immutable.Map finals;
  Signature: Lscala/collection/immutable/Map;
  Signature: length = 0x2
   00 09 

private int finalTag;
  Signature: I

private scala.collection.mutable.HashMap follow;
  Signature: Lscala/collection/mutable/HashMap;
  Signature: length = 0x2
   00 0E 

private int pos;
  Signature: I

public scala.util.automata.BaseBerrySethi();
  Signature: ()V
  Code:
   Stack=4, Locals=1, Args_size=1
	aload_0
	invokespecial	Method java/lang/Object."<init>":()V
	aload_0
	iconst_0
	putfield	Field pos:I
	aload_0
	getstatic	Field scala/collection/immutable/Set$.MODULE$:Lscala/collection/immutable/Set$;
	getstatic	Field scala/Predef$.MODULE$:Lscala/Predef$;
	iconst_0
	newarray int
	invokevirtual	Method scala/Predef$.wrapIntArray:([I)Lscala/collection/mutable/WrappedArray;
	invokevirtual	Method scala/collection/immutable/Set$.apply:(Lscala/collection/Seq;)Lscala/collection/Traversable;
	checkcast	class scala/collection/immutable/Set
	putfield	Field emptySet:Lscala/collection/immutable/Set;
	return
  Labels:

public void traverse(scala.util.regexp.Base$RegExp);
  Signature: (Lscala/util/regexp/Base$RegExp;)V
  Code:
   Stack=4, Locals=7, Args_size=2
	aload_1
	instanceof	class scala/util/regexp/Base$Alt
	ifeq	l1 // aload_1
	aload_1
	checkcast	class scala/util/regexp/Base$Alt
	astore_2
	iconst_1
	ifeq	l2 // new
	aload_2
	invokevirtual	Method scala/util/regexp/Base$Alt.rs:()Lscala/collection/Seq;
	new	class scala/util/automata/BaseBerrySethi$$anonfun$traverse$1
	dup
	aload_0
	invokespecial	Method scala/util/automata/BaseBerrySethi$$anonfun$traverse$1."<init>":(Lscala/util/automata/BaseBerrySethi;)V
	invokeinterface	InterfaceMethod scala/collection/IterableLike.foreach:(Lscala/Function1;)V
	goto	l3 // return
l2	new	class scala/MatchError
	dup
	aload_1
	invokevirtual	Method scala/util/regexp/Base$RegExp.toString:()Ljava/lang/String;
	invokespecial	Method scala/MatchError."<init>":(Ljava/lang/String;)V
	athrow
l1	aload_1
	instanceof	class scala/util/regexp/Base$Sequ
	ifeq	l4 // aload_1
	aload_1
	checkcast	class scala/util/regexp/Base$Sequ
	astore_3
	iconst_1
	ifeq	l5 // new
	aload_3
	invokevirtual	Method scala/util/regexp/Base$Sequ.rs:()Lscala/collection/Seq;
	new	class scala/util/automata/BaseBerrySethi$$anonfun$traverse$2
	dup
	aload_0
	invokespecial	Method scala/util/automata/BaseBerrySethi$$anonfun$traverse$2."<init>":(Lscala/util/automata/BaseBerrySethi;)V
	invokeinterface	InterfaceMethod scala/collection/IterableLike.foreach:(Lscala/Function1;)V
	goto	l3 // return
l5	new	class scala/MatchError
	dup
	aload_1
	invokevirtual	Method scala/util/regexp/Base$RegExp.toString:()Ljava/lang/String;
	invokespecial	Method scala/MatchError."<init>":(Ljava/lang/String;)V
	athrow
l4	aload_1
	instanceof	class scala/util/regexp/Base$Meta
	ifeq	l6 // aload_1
	aload_1
	checkcast	class scala/util/regexp/Base$Meta
	astore	4
	iconst_1
	ifeq	l7 // new
	aload_0
	aload	4
	invokevirtual	Method scala/util/regexp/Base$Meta.r:()Lscala/util/regexp/Base$RegExp;
	invokevirtual	Method traverse:(Lscala/util/regexp/Base$RegExp;)V
	goto	l3 // return
l7	new	class scala/MatchError
	dup
	aload_1
	invokevirtual	Method scala/util/regexp/Base$RegExp.toString:()Ljava/lang/String;
	invokespecial	Method scala/MatchError."<init>":(Ljava/lang/String;)V
	athrow
l6	aload_1
	instanceof	class scala/util/regexp/Base$Star
	ifeq	l8 // iconst_1
	aload_1
	checkcast	class scala/util/regexp/Base$Star
	astore	5
	aload	5
	invokevirtual	Method scala/util/regexp/Base$Star.r:()Lscala/util/regexp/Base$RegExp;
	astore	6
	iconst_1
	ifeq	l9 // new
	aload_0
	aload	6
	invokevirtual	Method traverse:(Lscala/util/regexp/Base$RegExp;)V
l3	return
l9	new	class scala/MatchError
	dup
	aload_1
	invokevirtual	Method scala/util/regexp/Base$RegExp.toString:()Ljava/lang/String;
	invokespecial	Method scala/MatchError."<init>":(Ljava/lang/String;)V
	athrow
l8	iconst_1
	ifeq	l10 // new
	new	class java/lang/IllegalArgumentException
	dup
	new	class scala/collection/mutable/StringBuilder
	dup
	invokespecial	Method scala/collection/mutable/StringBuilder."<init>":()V
	ldc	String unexp pattern 
	invokevirtual	Method scala/collection/mutable/StringBuilder.append:(Ljava/lang/Object;)Lscala/collection/mutable/StringBuilder;
	aload_1
	invokevirtual	Method scala/util/regexp/Base$RegExp.getClass:()Ljava/lang/Class;
	invokevirtual	Method scala/collection/mutable/StringBuilder.append:(Ljava/lang/Object;)Lscala/collection/mutable/StringBuilder;
	invokevirtual	Method scala/collection/mutable/StringBuilder.toString:()Ljava/lang/String;
	invokespecial	Method java/lang/IllegalArgumentException."<init>":(Ljava/lang/String;)V
	athrow
l10	new	class scala/MatchError
	dup
	aload_1
	invokevirtual	Method scala/util/regexp/Base$RegExp.toString:()Ljava/lang/String;
	invokespecial	Method scala/MatchError."<init>":(Ljava/lang/String;)V
	athrow
  Labels:
   	l2 = 36 // new
   	l1 = 48 // aload_1
   	l5 = 84 // new
   	l4 = 96 // aload_1
   	l7 = 125 // new
   	l6 = 137 // aload_1
   	l3 = 167 // return
   	l9 = 168 // new
   	l8 = 180 // iconst_1
   	l10 = 214 // new
  LocalVariableTable: 
   Start  Length  Slot  Name   Signature
   0      226      0    this       Lscala/util/automata/BaseBerrySethi;
   0      226      1    r       Lscala/util/regexp/Base$RegExp;
   12      36      2    temp17       Lscala/util/regexp/Base$Alt;
   60      36      3    temp18       Lscala/util/regexp/Base$Sequ;
   109      28      4    temp19       Lscala/util/regexp/Base$Meta;
   150      17      5    temp20       Lscala/util/regexp/Base$Star;
   168      12      5    temp20       Lscala/util/regexp/Base$Star;
   157      10      6    temp21       Lscala/util/regexp/Base$RegExp;
   168      12      6    temp21       Lscala/util/regexp/Base$RegExp;


public scala.collection.immutable.Set compFollow1(scala.collection.immutable.Set, scala.util.regexp.Base$RegExp);
  Signature: (Lscala/collection/immutable/Set;Lscala/util/regexp/Base$RegExp;)Lscala/collection/immutable/Set;
  Code:
   Stack=6, Locals=9, Args_size=3
	aload_2
	instanceof	class scala/util/regexp/Base$Alt
	ifeq	l1 // aload_2
	aload_2
	checkcast	class scala/util/regexp/Base$Alt
	astore_3
	iconst_1
	ifeq	l2 // new
	getstatic	Field scala/collection/immutable/Set$.MODULE$:Lscala/collection/immutable/Set$;
	aload_3
	invokevirtual	Method scala/util/regexp/Base$Alt.rs:()Lscala/collection/Seq;
	new	class scala/util/automata/BaseBerrySethi$$anonfun$compFollow1$1
	dup
	aload_0
	aload_1
	invokespecial	Method scala/util/automata/BaseBerrySethi$$anonfun$compFollow1$1."<init>":(Lscala/util/automata/BaseBerrySethi;Lscala/collection/immutable/Set;)V
	getstatic	Field scala/collection/Seq$.MODULE$:Lscala/collection/Seq$;
	astore	4
	new	class scala/collection/generic/TraversableFactory$GenericCanBuildFrom
	dup
	aload	4
	invokespecial	Method scala/collection/generic/TraversableFactory$GenericCanBuildFrom."<init>":(Lscala/collection/generic/TraversableFactory;)V
	invokeinterface	InterfaceMethod scala/collection/SeqLike.reverseMap:(Lscala/Function1;Lscala/collection/generic/CanBuildFrom;)Ljava/lang/Object;
	checkcast	class scala/collection/generic/GenericTraversableTemplate
	new	class scala/Predef$$anon$1
	dup
	invokespecial	Method scala/Predef$$anon$1."<init>":()V
	invokeinterface	InterfaceMethod scala/collection/generic/GenericTraversableTemplate.flatten:(Lscala/Function1;)Lscala/collection/Traversable;
	checkcast	class scala/collection/Seq
	invokevirtual	Method scala/collection/immutable/Set$.apply:(Lscala/collection/Seq;)Lscala/collection/Traversable;
	checkcast	class scala/collection/immutable/Set
	goto	l3 // areturn
l2	new	class scala/MatchError
	dup
	aload_2
	invokevirtual	Method scala/util/regexp/Base$RegExp.toString:()Ljava/lang/String;
	invokespecial	Method scala/MatchError."<init>":(Ljava/lang/String;)V
	athrow
l1	aload_2
	instanceof	class scala/util/regexp/Base$Meta
	ifeq	l4 // aload_2
	aload_2
	checkcast	class scala/util/regexp/Base$Meta
	astore	5
	iconst_1
	ifeq	l5 // new
	aload_0
	aload_1
	aload	5
	invokevirtual	Method scala/util/regexp/Base$Meta.r:()Lscala/util/regexp/Base$RegExp;
	invokevirtual	Method compFollow1:(Lscala/collection/immutable/Set;Lscala/util/regexp/Base$RegExp;)Lscala/collection/immutable/Set;
	goto	l3 // areturn
l5	new	class scala/MatchError
	dup
	aload_2
	invokevirtual	Method scala/util/regexp/Base$RegExp.toString:()Ljava/lang/String;
	invokespecial	Method scala/MatchError."<init>":(Ljava/lang/String;)V
	athrow
l4	aload_2
	instanceof	class scala/util/regexp/Base$Star
	ifeq	l6 // aload_2
	aload_2
	checkcast	class scala/util/regexp/Base$Star
	astore	6
	iconst_1
	ifeq	l7 // new
	aload_0
	aload_1
	aload_0
	aload	6
	invokevirtual	Method scala/util/regexp/Base$Star.r:()Lscala/util/regexp/Base$RegExp;
	invokevirtual	Method compFirst:(Lscala/util/regexp/Base$RegExp;)Lscala/collection/immutable/Set;
	invokeinterface	InterfaceMethod scala/collection/generic/Addable.$plus$plus:(Lscala/collection/Traversable;)Lscala/collection/generic/Addable;
	checkcast	class scala/collection/immutable/Set
	aload	6
	invokevirtual	Method scala/util/regexp/Base$Star.r:()Lscala/util/regexp/Base$RegExp;
	invokevirtual	Method compFollow1:(Lscala/collection/immutable/Set;Lscala/util/regexp/Base$RegExp;)Lscala/collection/immutable/Set;
	goto	l3 // areturn
l7	new	class scala/MatchError
	dup
	aload_2
	invokevirtual	Method scala/util/regexp/Base$RegExp.toString:()Ljava/lang/String;
	invokespecial	Method scala/MatchError."<init>":(Ljava/lang/String;)V
	athrow
l6	aload_2
	instanceof	class scala/util/regexp/Base$Sequ
	ifeq	l8 // iconst_1
	aload_2
	checkcast	class scala/util/regexp/Base$Sequ
	astore	7
	iconst_1
	ifeq	l9 // new
	aload_0
	getfield	Field emptySet:Lscala/collection/immutable/Set;
	astore	8
	aload	7
	invokevirtual	Method scala/util/regexp/Base$Sequ.rs:()Lscala/collection/Seq;
	aload_1
	new	class scala/util/automata/BaseBerrySethi$$anonfun$compFollow1$2
	dup
	aload_0
	invokespecial	Method scala/util/automata/BaseBerrySethi$$anonfun$compFollow1$2."<init>":(Lscala/util/automata/BaseBerrySethi;)V
	invokeinterface	InterfaceMethod scala/collection/IterableLike.foldRight:(Ljava/lang/Object;Lscala/Function2;)Ljava/lang/Object;
	pop
	aload	8
l3	areturn
l9	new	class scala/MatchError
	dup
	aload_2
	invokevirtual	Method scala/util/regexp/Base$RegExp.toString:()Ljava/lang/String;
	invokespecial	Method scala/MatchError."<init>":(Ljava/lang/String;)V
	athrow
l8	iconst_1
	ifeq	l10 // new
	new	class java/lang/IllegalArgumentException
	dup
	new	class scala/collection/mutable/StringBuilder
	dup
	invokespecial	Method scala/collection/mutable/StringBuilder."<init>":()V
	ldc	String unexpected pattern: 
	invokevirtual	Method scala/collection/mutable/StringBuilder.append:(Ljava/lang/Object;)Lscala/collection/mutable/StringBuilder;
	aload_2
	invokevirtual	Method scala/util/regexp/Base$RegExp.getClass:()Ljava/lang/Class;
	invokevirtual	Method scala/collection/mutable/StringBuilder.append:(Ljava/lang/Object;)Lscala/collection/mutable/StringBuilder;
	invokevirtual	Method scala/collection/mutable/StringBuilder.toString:()Ljava/lang/String;
	invokespecial	Method java/lang/IllegalArgumentException."<init>":(Ljava/lang/String;)V
	athrow
l10	new	class scala/MatchError
	dup
	aload_2
	invokevirtual	Method scala/util/regexp/Base$RegExp.toString:()Ljava/lang/String;
	invokespecial	Method scala/MatchError."<init>":(Ljava/lang/String;)V
	athrow
  Labels:
   	l2 = 78 // new
   	l1 = 90 // aload_2
   	l5 = 120 // new
   	l4 = 132 // aload_2
   	l7 = 179 // new
   	l6 = 191 // aload_2
   	l3 = 236 // areturn
   	l9 = 237 // new
   	l8 = 249 // iconst_1
   	l10 = 283 // new
  LocalVariableTable: 
   Start  Length  Slot  Name   Signature
   0      295      0    this       Lscala/util/automata/BaseBerrySethi;
   0      295      1    fol1$1       Lscala/collection/immutable/Set;
   0      295      2    r       Lscala/util/regexp/Base$RegExp;
   12      78      3    temp11       Lscala/util/regexp/Base$Alt;
   103      29      5    temp12       Lscala/util/regexp/Base$Meta;
   145      46      6    temp13       Lscala/util/regexp/Base$Star;
   204      32      7    temp15       Lscala/util/regexp/Base$Sequ;
   237      12      7    temp15       Lscala/util/regexp/Base$Sequ;
   214      22      8    first       Lscala/collection/immutable/Set;

  Signature: length = 0x2
   00 FFFFFFBD 

public scala.collection.immutable.Set compFollow(scala.collection.Seq);
  Signature: (Lscala/collection/Seq;)Lscala/collection/immutable/Set;
  Code:
   Stack=9, Locals=4, Args_size=2
	aload_0
	invokevirtual	Method follow:()Lscala/collection/mutable/HashMap;
	iconst_0
	istore_2
	iload_2
	invokestatic	Method scala/runtime/BoxesRunTime.boxToInteger:(I)Ljava/lang/Integer;
	aload_1
	invokeinterface	InterfaceMethod scala/collection/IterableLike.isEmpty:()Z
	ifeq	l1 // aload_1
	aload_0
	getfield	Field emptySet:Lscala/collection/immutable/Set;
	goto	l2 // invokevirtual
l1	aload_1
	getstatic	Field scala/collection/immutable/Set$.MODULE$:Lscala/collection/immutable/Set$;
	getstatic	Field scala/Predef$.MODULE$:Lscala/Predef$;
	iconst_1
	newarray int
	dup
	iconst_0
	aload_0
	invokevirtual	Method pos:()I
	iastore
	invokevirtual	Method scala/Predef$.wrapIntArray:([I)Lscala/collection/mutable/WrappedArray;
	invokevirtual	Method scala/collection/immutable/Set$.apply:(Lscala/collection/Seq;)Lscala/collection/Traversable;
	new	class scala/util/automata/BaseBerrySethi$$anonfun$compFollow$1
	dup
	aload_0
	invokespecial	Method scala/util/automata/BaseBerrySethi$$anonfun$compFollow$1."<init>":(Lscala/util/automata/BaseBerrySethi;)V
	invokeinterface	InterfaceMethod scala/collection/IterableLike.foldRight:(Ljava/lang/Object;Lscala/Function2;)Ljava/lang/Object;
l2	invokevirtual	Method scala/collection/mutable/HashMap.update:(Ljava/lang/Object;Ljava/lang/Object;)V
	aload_0
	invokevirtual	Method follow:()Lscala/collection/mutable/HashMap;
	iconst_0
	istore_3
	iload_3
	invokestatic	Method scala/runtime/BoxesRunTime.boxToInteger:(I)Ljava/lang/Integer;
	invokeinterface	InterfaceMethod scala/collection/MapLike.apply:(Ljava/lang/Object;)Ljava/lang/Object;
	checkcast	class scala/collection/immutable/Set
	areturn
  Labels:
   	l1 = 26 // aload_1
   	l2 = 62 // invokevirtual
  LocalVariableTable: 
   Start  Length  Slot  Name   Signature
   0      84      0    this       Lscala/util/automata/BaseBerrySethi;
   0      84      1    rs       Lscala/collection/Seq;

  Signature: length = 0x2
   00 FFFFFFDF 

public scala.collection.immutable.Set compLast(scala.util.regexp.Base$RegExp);
  Signature: (Lscala/util/regexp/Base$RegExp;)Lscala/collection/immutable/Set;
  Code:
   Stack=5, Locals=2, Args_size=2
	aload_0
	aload_1
	new	class scala/util/automata/BaseBerrySethi$$anonfun$compLast$1
	dup
	aload_0
	invokespecial	Method scala/util/automata/BaseBerrySethi$$anonfun$compLast$1."<init>":(Lscala/util/automata/BaseBerrySethi;)V
	invokespecial	Method doComp:(Lscala/util/regexp/Base$RegExp;Lscala/Function1;)Lscala/collection/immutable/Set;
	areturn
  Labels:
  LocalVariableTable: 
   Start  Length  Slot  Name   Signature
   0      14      0    this       Lscala/util/automata/BaseBerrySethi;
   0      14      1    r       Lscala/util/regexp/Base$RegExp;

  Signature: length = 0x2
   00 FFFFFFE8 

public scala.collection.immutable.Set compFirst(scala.util.regexp.Base$RegExp);
  Signature: (Lscala/util/regexp/Base$RegExp;)Lscala/collection/immutable/Set;
  Code:
   Stack=5, Locals=2, Args_size=2
	aload_0
	aload_1
	new	class scala/util/automata/BaseBerrySethi$$anonfun$compFirst$1
	dup
	aload_0
	invokespecial	Method scala/util/automata/BaseBerrySethi$$anonfun$compFirst$1."<init>":(Lscala/util/automata/BaseBerrySethi;)V
	invokespecial	Method doComp:(Lscala/util/regexp/Base$RegExp;Lscala/Function1;)Lscala/collection/immutable/Set;
	areturn
  Labels:
  LocalVariableTable: 
   Start  Length  Slot  Name   Signature
   0      14      0    this       Lscala/util/automata/BaseBerrySethi;
   0      14      1    r       Lscala/util/regexp/Base$RegExp;

  Signature: length = 0x2
   00 FFFFFFE8 

private scala.collection.immutable.Set doComp(scala.util.regexp.Base$RegExp, scala.Function1);
  Signature: (Lscala/util/regexp/Base$RegExp;Lscala/Function1;)Lscala/collection/immutable/Set;
  Code:
   Stack=5, Locals=18, Args_size=3
	aload_1
	instanceof	class scala/util/regexp/Base$Alt
	ifeq	l1 // aload_1
	aload_1
	checkcast	class scala/util/regexp/Base$Alt
	astore_3
	iconst_1
	ifeq	l2 // new
	aload_3
	invokevirtual	Method scala/util/regexp/Base$Alt.rs:()Lscala/collection/Seq;
	new	class scala/util/automata/BaseBerrySethi$$anonfun$doComp$1
	dup
	aload_0
	invokespecial	Method scala/util/automata/BaseBerrySethi$$anonfun$doComp$1."<init>":(Lscala/util/automata/BaseBerrySethi;)V
	getstatic	Field scala/collection/Seq$.MODULE$:Lscala/collection/Seq$;
	astore	4
	new	class scala/collection/generic/TraversableFactory$GenericCanBuildFrom
	dup
	aload	4
	invokespecial	Method scala/collection/generic/TraversableFactory$GenericCanBuildFrom."<init>":(Lscala/collection/generic/TraversableFactory;)V
	invokeinterface	InterfaceMethod scala/collection/TraversableLike.map:(Lscala/Function1;Lscala/collection/generic/CanBuildFrom;)Ljava/lang/Object;
	checkcast	class scala/collection/TraversableLike
	aload_0
	getfield	Field emptySet:Lscala/collection/immutable/Set;
	new	class scala/util/automata/BaseBerrySethi$$anonfun$doComp$2
	dup
	aload_0
	invokespecial	Method scala/util/automata/BaseBerrySethi$$anonfun$doComp$2."<init>":(Lscala/util/automata/BaseBerrySethi;)V
	invokeinterface	InterfaceMethod scala/collection/TraversableLike.foldLeft:(Ljava/lang/Object;Lscala/Function2;)Ljava/lang/Object;
	checkcast	class scala/collection/immutable/Set
	goto	l3 // areturn
l2	new	class scala/MatchError
	dup
	aload_1
	invokevirtual	Method scala/util/regexp/Base$RegExp.toString:()Ljava/lang/String;
	invokespecial	Method scala/MatchError."<init>":(Ljava/lang/String;)V
	athrow
l1	aload_1
	aload_0
	invokevirtual	Method lang:()Lscala/util/regexp/Base;
	invokevirtual	Method scala/util/regexp/Base.Eps:()Lscala/util/regexp/Base$Eps$;
	astore	5
	dup
	ifnonnull	l4 // aload
	pop
	aload	5
	ifnull	l5 // iconst_1
	goto	l6 // aload_1
l4	aload	5
	invokevirtual	Method java/lang/Object.equals:(Ljava/lang/Object;)Z
	ifeq	l6 // aload_1
l5	iconst_1
	ifeq	l7 // new
	aload_0
	getfield	Field emptySet:Lscala/collection/immutable/Set;
	goto	l3 // areturn
l7	new	class scala/MatchError
	dup
	aload_1
	invokevirtual	Method scala/util/regexp/Base$RegExp.toString:()Ljava/lang/String;
	invokespecial	Method scala/MatchError."<init>":(Ljava/lang/String;)V
	athrow
l6	aload_1
	instanceof	class scala/util/regexp/Base$Meta
	ifeq	l8 // aload_1
	aload_1
	checkcast	class scala/util/regexp/Base$Meta
	astore	6
	iconst_1
	ifeq	l9 // new
	aload_2
	aload	6
	invokevirtual	Method scala/util/regexp/Base$Meta.r:()Lscala/util/regexp/Base$RegExp;
	invokeinterface	InterfaceMethod scala/Function1.apply:(Ljava/lang/Object;)Ljava/lang/Object;
	checkcast	class scala/collection/immutable/Set
	goto	l3 // areturn
l9	new	class scala/MatchError
	dup
	aload_1
	invokevirtual	Method scala/util/regexp/Base$RegExp.toString:()Ljava/lang/String;
	invokespecial	Method scala/MatchError."<init>":(Ljava/lang/String;)V
	athrow
l8	aload_1
	instanceof	class scala/util/regexp/Base$Sequ
	ifeq	l10 // aload_1
	aload_1
	checkcast	class scala/util/regexp/Base$Sequ
	astore	7
	iconst_1
	ifeq	l11 // new
	aload	7
	invokevirtual	Method scala/util/regexp/Base$Sequ.rs:()Lscala/collection/Seq;
	new	class scala/util/automata/BaseBerrySethi$$anonfun$1
	dup
	aload_0
	invokespecial	Method scala/util/automata/BaseBerrySethi$$anonfun$1."<init>":(Lscala/util/automata/BaseBerrySethi;)V
	invokeinterface	InterfaceMethod scala/collection/TraversableLike.span:(Lscala/Function1;)Lscala/Tuple2;
	astore	15
	aload	15
	ifnull	l12 // new
	aload	15
	invokevirtual	Method scala/Tuple2._1:()Ljava/lang/Object;
	checkcast	class scala/collection/Seq
	astore	8
	aload	15
	invokevirtual	Method scala/Tuple2._2:()Ljava/lang/Object;
	checkcast	class scala/collection/Seq
	astore	9
	iconst_1
	ifeq	l13 // new
	new	class scala/Tuple2
	dup
	aload	8
	aload	9
	invokespecial	Method scala/Tuple2."<init>":(Ljava/lang/Object;Ljava/lang/Object;)V
	astore	10
	aload	10
	invokevirtual	Method scala/Tuple2._1:()Ljava/lang/Object;
	checkcast	class scala/collection/Seq
	astore	11
	aload	10
	invokevirtual	Method scala/Tuple2._2:()Ljava/lang/Object;
	checkcast	class scala/collection/Seq
	astore	12
	aload	11
	aload	12
	iconst_1
	invokeinterface	InterfaceMethod scala/collection/IterableLike.take:(I)Ljava/lang/Object;
	checkcast	class scala/collection/Traversable
	getstatic	Field scala/collection/Seq$.MODULE$:Lscala/collection/Seq$;
	astore	13
	new	class scala/collection/generic/TraversableFactory$GenericCanBuildFrom
	dup
	aload	13
	invokespecial	Method scala/collection/generic/TraversableFactory$GenericCanBuildFrom."<init>":(Lscala/collection/generic/TraversableFactory;)V
	invokeinterface	InterfaceMethod scala/collection/TraversableLike.$plus$plus:(Lscala/collection/Traversable;Lscala/collection/generic/CanBuildFrom;)Ljava/lang/Object;
	checkcast	class scala/collection/TraversableLike
	aload_2
	getstatic	Field scala/collection/Seq$.MODULE$:Lscala/collection/Seq$;
	astore	14
	new	class scala/collection/generic/TraversableFactory$GenericCanBuildFrom
	dup
	aload	14
	invokespecial	Method scala/collection/generic/TraversableFactory$GenericCanBuildFrom."<init>":(Lscala/collection/generic/TraversableFactory;)V
	invokeinterface	InterfaceMethod scala/collection/TraversableLike.map:(Lscala/Function1;Lscala/collection/generic/CanBuildFrom;)Ljava/lang/Object;
	checkcast	class scala/collection/TraversableLike
	aload_0
	getfield	Field emptySet:Lscala/collection/immutable/Set;
	new	class scala/util/automata/BaseBerrySethi$$anonfun$doComp$3
	dup
	aload_0
	invokespecial	Method scala/util/automata/BaseBerrySethi$$anonfun$doComp$3."<init>":(Lscala/util/automata/BaseBerrySethi;)V
	invokeinterface	InterfaceMethod scala/collection/TraversableLike.foldLeft:(Ljava/lang/Object;Lscala/Function2;)Ljava/lang/Object;
	checkcast	class scala/collection/immutable/Set
	goto	l3 // areturn
l13	new	class scala/MatchError
	dup
	aload	15
	invokevirtual	Method scala/Tuple2.toString:()Ljava/lang/String;
	invokespecial	Method scala/MatchError."<init>":(Ljava/lang/String;)V
	athrow
l12	new	class scala/MatchError
	dup
	aload	15
	invokevirtual	Method scala/Tuple2.toString:()Ljava/lang/String;
	invokespecial	Method scala/MatchError."<init>":(Ljava/lang/String;)V
	athrow
l11	new	class scala/MatchError
	dup
	aload_1
	invokevirtual	Method scala/util/regexp/Base$RegExp.toString:()Ljava/lang/String;
	invokespecial	Method scala/MatchError."<init>":(Ljava/lang/String;)V
	athrow
l10	aload_1
	instanceof	class scala/util/regexp/Base$Star
	ifeq	l14 // iconst_1
	aload_1
	checkcast	class scala/util/regexp/Base$Star
	astore	16
	aload	16
	invokevirtual	Method scala/util/regexp/Base$Star.r:()Lscala/util/regexp/Base$RegExp;
	astore	17
	iconst_1
	ifeq	l15 // new
	aload_2
	aload	17
	invokeinterface	InterfaceMethod scala/Function1.apply:(Ljava/lang/Object;)Ljava/lang/Object;
	checkcast	class scala/collection/immutable/Set
l3	areturn
l15	new	class scala/MatchError
	dup
	aload_1
	invokevirtual	Method scala/util/regexp/Base$RegExp.toString:()Ljava/lang/String;
	invokespecial	Method scala/MatchError."<init>":(Ljava/lang/String;)V
	athrow
l14	iconst_1
	ifeq	l16 // new
	new	class java/lang/IllegalArgumentException
	dup
	new	class scala/collection/mutable/StringBuilder
	dup
	invokespecial	Method scala/collection/mutable/StringBuilder."<init>":()V
	ldc_w	String unexpected pattern 
	invokevirtual	Method scala/collection/mutable/StringBuilder.append:(Ljava/lang/Object;)Lscala/collection/mutable/StringBuilder;
	aload_1
	invokevirtual	Method scala/util/regexp/Base$RegExp.getClass:()Ljava/lang/Class;
	invokevirtual	Method scala/collection/mutable/StringBuilder.append:(Ljava/lang/Object;)Lscala/collection/mutable/StringBuilder;
	invokevirtual	Method scala/collection/mutable/StringBuilder.toString:()Ljava/lang/String;
	invokespecial	Method java/lang/IllegalArgumentException."<init>":(Ljava/lang/String;)V
	athrow
l16	new	class scala/MatchError
	dup
	aload_1
	invokevirtual	Method scala/util/regexp/Base$RegExp.toString:()Ljava/lang/String;
	invokespecial	Method scala/MatchError."<init>":(Ljava/lang/String;)V
	athrow
  Labels:
   	l2 = 73 // new
   	l1 = 85 // aload_1
   	l4 = 108 // aload
   	l5 = 116 // iconst_1
   	l7 = 127 // new
   	l6 = 139 // aload_1
   	l9 = 173 // new
   	l8 = 185 // aload_1
   	l13 = 365 // new
   	l12 = 378 // new
   	l11 = 391 // new
   	l10 = 403 // aload_1
   	l3 = 438 // areturn
   	l15 = 439 // new
   	l14 = 451 // iconst_1
   	l16 = 486 // new
  LocalVariableTable: 
   Start  Length  Slot  Name   Signature
   0      498      0    this       Lscala/util/automata/BaseBerrySethi;
   0      498      1    r       Lscala/util/regexp/Base$RegExp;
   0      498      2    compFunction       Lscala/Function1;
   12      73      3    temp5       Lscala/util/regexp/Base$Alt;
   152      33      6    temp6       Lscala/util/regexp/Base$Meta;
   198      205      7    temp7       Lscala/util/regexp/Base$Sequ;
   237      141      8    temp2       Lscala/collection/Seq;
   247      131      9    temp3       Lscala/collection/Seq;
   274      88      11    l1       Lscala/collection/Seq;
   284      78      12    l2       Lscala/collection/Seq;
   222      169      15    temp1       Lscala/Tuple2;
   416      22      16    temp8       Lscala/util/regexp/Base$Star;
   439      12      16    temp8       Lscala/util/regexp/Base$Star;
   423      15      17    temp9       Lscala/util/regexp/Base$RegExp;
   439      12      17    temp9       Lscala/util/regexp/Base$RegExp;

  Signature: length = 0x2
   01 39 

public final scala.collection.immutable.Set emptySet();
  Signature: ()Lscala/collection/immutable/Set;
  Code:
   Stack=1, Locals=1, Args_size=1
	aload_0
	getfield	Field emptySet:Lscala/collection/immutable/Set;
	areturn
  Labels:
  Signature: length = 0x2
   01 3B 

public void finals_$eq(scala.collection.immutable.Map);
  Signature: (Lscala/collection/immutable/Map;)V
  Code:
   Stack=2, Locals=2, Args_size=2
	aload_0
	aload_1
	putfield	Field finals:Lscala/collection/immutable/Map;
	return
  Labels:
  Signature: length = 0x2
   01 40 

public scala.collection.immutable.Map finals();
  Signature: ()Lscala/collection/immutable/Map;
  Code:
   Stack=1, Locals=1, Args_size=1
	aload_0
	getfield	Field finals:Lscala/collection/immutable/Map;
	areturn
  Labels:
  Signature: length = 0x2
   01 42 

public void finalTag_$eq(int);
  Signature: (I)V
  Code:
   Stack=2, Locals=2, Args_size=2
	aload_0
	iload_1
	putfield	Field finalTag:I
	return
  Labels:

public int finalTag();
  Signature: ()I
  Code:
   Stack=1, Locals=1, Args_size=1
	aload_0
	getfield	Field finalTag:I
	ireturn
  Labels:

public void follow_$eq(scala.collection.mutable.HashMap);
  Signature: (Lscala/collection/mutable/HashMap;)V
  Code:
   Stack=2, Locals=2, Args_size=2
	aload_0
	aload_1
	putfield	Field follow:Lscala/collection/mutable/HashMap;
	return
  Labels:
  Signature: length = 0x2
   01 4B 

public scala.collection.mutable.HashMap follow();
  Signature: ()Lscala/collection/mutable/HashMap;
  Code:
   Stack=1, Locals=1, Args_size=1
	aload_0
	getfield	Field follow:Lscala/collection/mutable/HashMap;
	areturn
  Labels:
  Signature: length = 0x2
   01 4C 

public void pos_$eq(int);
  Signature: (I)V
  Code:
   Stack=2, Locals=2, Args_size=2
	aload_0
	iload_1
	putfield	Field pos:I
	return
  Labels:

public int pos();
  Signature: ()I
  Code:
   Stack=1, Locals=1, Args_size=1
	aload_0
	getfield	Field pos:I
	ireturn
  Labels:

public abstract scala.util.regexp.Base lang();
  Signature: ()Lscala/util/regexp/Base;

}

