Compiled from "DetWordAutom.scala"
public abstract class scala.util.automata.DetWordAutom extends java.lang.Object implements scala.ScalaObject
  SourceFile: "DetWordAutom.scala"
  Signature: length = 0x2
   00 FFFFFFC9 
  ScalaSig: length = 0x20F
   05 00 5B 06 05 01 02 FFFFFF81 00 09 02 0C 44 65 74 57
   6F 72 64 41 75 74 6F 6D 0A 02 03 04 01 08 61 75
   74 6F 6D 61 74 61 0A 02 05 06 01 04 75 74 69 6C
   0A 01 07 01 05 73 63 61 6C 61 03 00 15 02 0A 1E
   13 03 00 0B 13 10 02 0C 11 0D 01 0D 0A 02 0E 0F
   01 04 6C 61 6E 67 0A 01 10 01 04 6A 61 76 61 09
   02 12 0D 02 06 4F 62 6A 65 63 74 10 02 14 15 0D
   01 06 09 02 16 06 02 0B 53 63 61 6C 61 4F 62 6A
   65 63 74 08 05 18 00 FFFFFF84 00 19 01 06 3C 69 6E 69
   74 3E 14 01 1A 10 03 1B 00 1C 0D 01 02 10 02 1D
   1E 0C 00 04 08 1F 00 FFFFFF84 FFFFFF80 FFFFFF80 FFFFFFC2 00 20 02 01 54
   11 02 21 24 10 02 14 22 09 02 23 06 02 07 4E 6F
   74 68 69 6E 67 10 02 14 25 09 02 26 06 02 06 41
   6E 79 52 65 66 08 07 28 00 FFFFFFC2 FFFFFF80 FFFFFF86 00 29 01 07
   6E 73 74 61 74 65 73 15 01 2A 10 02 14 2B 09 02
   2C 06 02 03 49 6E 74 08 07 2E 00 FFFFFFC2 FFFFFF80 FFFFFF86 00 2F
   01 06 66 69 6E 61 6C 73 15 01 30 10 03 14 31 2A
   09 02 32 06 02 05 41 72 72 61 79 08 07 34 00 FFFFFFC2
   FFFFFF80 FFFFFF86 00 35 01 05 64 65 6C 74 61 15 01 36 10 03
   14 31 37 10 04 38 3B 1C 2A 0D 01 39 0A 02 3A 06
   01 0A 63 6F 6C 6C 65 63 74 69 6F 6E 09 02 3C 39
   02 03 4D 61 70 08 07 3E 00 FFFFFFC2 FFFFFF80 FFFFFF86 00 2F 01 07
   64 65 66 61 75 6C 74 08 05 40 00 FFFFFF84 00 41 01 07
   69 73 46 69 6E 61 6C 14 02 42 45 10 02 14 43 09
   02 44 06 02 07 42 6F 6F 6C 65 61 6E 08 05 46 3F
   FFFFFFC0 00 2A 01 01 71 08 05 48 00 FFFFFF84 00 49 01 06 69
   73 53 69 6E 6B 14 02 42 4A 08 05 46 47 FFFFFFC0 00 2A
   08 05 4C 00 FFFFFF84 00 4D 01 04 6E 65 78 74 14 03 2A
   4E 4F 08 05 46 4B FFFFFFC0 00 2A 08 05 50 4B FFFFFFC0 00 1C
   01 05 6C 61 62 65 6C 08 05 52 00 FFFFFF84 20 53 01 08
   74 6F 53 74 72 69 6E 67 14 01 54 10 02 55 58 0E
   02 14 56 09 02 57 06 01 06 50 72 65 64 65 66 09
   02 59 5A 02 06 53 74 72 69 6E 67 0A 02 57 06 
  InnerClass: 
   public abstract #206= #136 of #205; //ByOne=class scala/collection/immutable/Range$ByOne of class scala/collection/immutable/Range
   public final #207= #103 of #22; //$anonfun$1=class scala/util/automata/DetWordAutom$$anonfun$1 of class scala/util/automata/DetWordAutom
   public final #208= #138 of #22; //$anonfun$toString$1=class scala/util/automata/DetWordAutom$$anonfun$toString$1 of class scala/util/automata/DetWordAutom
  minor version: 0
  major version: 49
  Constant pool:
const #1 = Asciz	SourceFile;
const #2 = Asciz	DetWordAutom.scala;
const #3 = Asciz	<init>;
const #4 = Asciz	()V;
const #5 = Asciz	Code;
const #6 = Asciz	LineNumberTable;
const #7 = Asciz	java/lang/Object;
const #8 = class	#7;	//  java/lang/Object
const #9 = NameAndType	#3:#4;//  "<init>":()V
const #10 = Method	#8.#9;	//  java/lang/Object."<init>":()V
const #11 = Asciz	Signature;
const #12 = Asciz	toString;
const #13 = Asciz	()Ljava/lang/String;;
const #14 = Asciz	scala/collection/mutable/StringBuilder;
const #15 = class	#14;	//  scala/collection/mutable/StringBuilder
const #16 = Asciz	[DetWordAutom  nstates=;
const #17 = String	#16;	//  [DetWordAutom  nstates=
const #18 = Asciz	(Ljava/lang/String;)V;
const #19 = NameAndType	#3:#18;//  "<init>":(Ljava/lang/String;)V
const #20 = Method	#15.#19;	//  scala/collection/mutable/StringBuilder."<init>":(Ljava/lang/String;)V
const #21 = Asciz	scala/util/automata/DetWordAutom;
const #22 = class	#21;	//  scala/util/automata/DetWordAutom
const #23 = Asciz	nstates;
const #24 = Asciz	()I;
const #25 = NameAndType	#23:#24;//  nstates:()I
const #26 = Method	#22.#25;	//  scala/util/automata/DetWordAutom.nstates:()I
const #27 = Asciz	append;
const #28 = Asciz	(I)Lscala/collection/mutable/StringBuilder;;
const #29 = NameAndType	#27:#28;//  append:(I)Lscala/collection/mutable/StringBuilder;
const #30 = Method	#15.#29;	//  scala/collection/mutable/StringBuilder.append:(I)Lscala/collection/mutable/StringBuilder;
const #31 = Asciz	 finals=;
const #32 = String	#31;	//   finals=
const #33 = Asciz	(Ljava/lang/String;)Lscala/collection/mutable/StringBuilder;;
const #34 = NameAndType	#27:#33;//  append:(Ljava/lang/String;)Lscala/collection/mutable/StringBuilder;
const #35 = Method	#15.#34;	//  scala/collection/mutable/StringBuilder.append:(Ljava/lang/String;)Lscala/collection/mutable/StringBuilder;
const #36 = Asciz	scala/collection/Map$;
const #37 = class	#36;	//  scala/collection/Map$
const #38 = Asciz	MODULE$;
const #39 = Asciz	Lscala/collection/Map$;;
const #40 = NameAndType	#38:#39;//  MODULE$:Lscala/collection/Map$;
const #41 = Field	#37.#40;	//  scala/collection/Map$.MODULE$:Lscala/collection/Map$;
const #42 = Asciz	scala/Predef$;
const #43 = class	#42;	//  scala/Predef$
const #44 = Asciz	Lscala/Predef$;;
const #45 = NameAndType	#38:#44;//  MODULE$:Lscala/Predef$;
const #46 = Field	#43.#45;	//  scala/Predef$.MODULE$:Lscala/Predef$;
const #47 = Asciz	finals;
const #48 = Asciz	()[I;
const #49 = NameAndType	#47:#48;//  finals:()[I
const #50 = Method	#22.#49;	//  scala/util/automata/DetWordAutom.finals:()[I
const #51 = Asciz	intArrayOps;
const #52 = Asciz	([I)Lscala/collection/mutable/ArrayOps;;
const #53 = NameAndType	#51:#52;//  intArrayOps:([I)Lscala/collection/mutable/ArrayOps;
const #54 = Method	#43.#53;	//  scala/Predef$.intArrayOps:([I)Lscala/collection/mutable/ArrayOps;
const #55 = Asciz	scala/Array$;
const #56 = class	#55;	//  scala/Array$
const #57 = Asciz	Lscala/Array$;;
const #58 = NameAndType	#38:#57;//  MODULE$:Lscala/Array$;
const #59 = Field	#56.#58;	//  scala/Array$.MODULE$:Lscala/Array$;
const #60 = Asciz	scala/reflect/ClassManifest$;
const #61 = class	#60;	//  scala/reflect/ClassManifest$
const #62 = Asciz	Lscala/reflect/ClassManifest$;;
const #63 = NameAndType	#38:#62;//  MODULE$:Lscala/reflect/ClassManifest$;
const #64 = Field	#61.#63;	//  scala/reflect/ClassManifest$.MODULE$:Lscala/reflect/ClassManifest$;
const #65 = Asciz	scala/Tuple2;
const #66 = class	#65;	//  scala/Tuple2
const #67 = Asciz	scala/reflect/Manifest$;
const #68 = class	#67;	//  scala/reflect/Manifest$
const #69 = Asciz	Lscala/reflect/Manifest$;;
const #70 = NameAndType	#38:#69;//  MODULE$:Lscala/reflect/Manifest$;
const #71 = Field	#68.#70;	//  scala/reflect/Manifest$.MODULE$:Lscala/reflect/Manifest$;
const #72 = Asciz	Int;
const #73 = Asciz	()Ljava/lang/Object;;
const #74 = NameAndType	#72:#73;//  Int:()Ljava/lang/Object;
const #75 = Method	#68.#74;	//  scala/reflect/Manifest$.Int:()Ljava/lang/Object;
const #76 = Asciz	scala/reflect/OptManifest;
const #77 = class	#76;	//  scala/reflect/OptManifest
const #78 = Asciz	[Ljava/lang/Object;;
const #79 = class	#78;	//  "[Ljava/lang/Object;"
const #80 = Asciz	wrapRefArray;
const #81 = Asciz	([Ljava/lang/Object;)Lscala/collection/mutable/WrappedArray;;
const #82 = NameAndType	#80:#81;//  wrapRefArray:([Ljava/lang/Object;)Lscala/collection/mutable/WrappedArray;
const #83 = Method	#43.#82;	//  scala/Predef$.wrapRefArray:([Ljava/lang/Object;)Lscala/collection/mutable/WrappedArray;
const #84 = Asciz	classType;
const #85 = Asciz	(Ljava/lang/Class;Lscala/reflect/OptManifest;Lscala/collection/Seq;)Lscala/reflect/ClassManifest;;
const #86 = NameAndType	#84:#85;//  classType:(Ljava/lang/Class;Lscala/reflect/OptManifest;Lscala/collection/Seq;)Lscala/reflect/ClassManifest;
const #87 = Method	#61.#86;	//  scala/reflect/ClassManifest$.classType:(Ljava/lang/Class;Lscala/reflect/OptManifest;Lscala/collection/Seq;)Lscala/reflect/ClassManifest;
const #88 = Asciz	canBuildFrom;
const #89 = Asciz	(Lscala/reflect/ClassManifest;)Lscala/collection/generic/CanBuildFrom;;
const #90 = NameAndType	#88:#89;//  canBuildFrom:(Lscala/reflect/ClassManifest;)Lscala/collection/generic/CanBuildFrom;
const #91 = Method	#56.#90;	//  scala/Array$.canBuildFrom:(Lscala/reflect/ClassManifest;)Lscala/collection/generic/CanBuildFrom;
const #92 = Asciz	scala/collection/IndexedSeqLike;
const #93 = class	#92;	//  scala/collection/IndexedSeqLike
const #94 = Asciz	zipWithIndex;
const #95 = Asciz	(Lscala/collection/generic/CanBuildFrom;)Ljava/lang/Object;;
const #96 = NameAndType	#94:#95;//  zipWithIndex:(Lscala/collection/generic/CanBuildFrom;)Ljava/lang/Object;
const #97 = InterfaceMethod	#93.#96;	//  scala/collection/IndexedSeqLike.zipWithIndex:(Lscala/collection/generic/CanBuildFrom;)Ljava/lang/Object;
const #98 = Asciz	refArrayOps;
const #99 = Asciz	([Ljava/lang/Object;)Lscala/collection/mutable/ArrayOps;;
const #100 = NameAndType	#98:#99;//  refArrayOps:([Ljava/lang/Object;)Lscala/collection/mutable/ArrayOps;
const #101 = Method	#43.#100;	//  scala/Predef$.refArrayOps:([Ljava/lang/Object;)Lscala/collection/mutable/ArrayOps;
const #102 = Asciz	scala/util/automata/DetWordAutom$$anonfun$1;
const #103 = class	#102;	//  scala/util/automata/DetWordAutom$$anonfun$1
const #104 = Asciz	(Lscala/util/automata/DetWordAutom;)V;
const #105 = NameAndType	#3:#104;//  "<init>":(Lscala/util/automata/DetWordAutom;)V
const #106 = Method	#103.#105;	//  scala/util/automata/DetWordAutom$$anonfun$1."<init>":(Lscala/util/automata/DetWordAutom;)V
const #107 = Asciz	scala/collection/TraversableLike;
const #108 = class	#107;	//  scala/collection/TraversableLike
const #109 = Asciz	map;
const #110 = Asciz	(Lscala/Function1;Lscala/collection/generic/CanBuildFrom;)Ljava/lang/Object;;
const #111 = NameAndType	#109:#110;//  map:(Lscala/Function1;Lscala/collection/generic/CanBuildFrom;)Ljava/lang/Object;
const #112 = InterfaceMethod	#108.#111;	//  scala/collection/TraversableLike.map:(Lscala/Function1;Lscala/collection/generic/CanBuildFrom;)Ljava/lang/Object;
const #113 = Asciz	[Lscala/Tuple2;;
const #114 = class	#113;	//  "[Lscala/Tuple2;"
const #115 = Asciz	apply;
const #116 = Asciz	(Lscala/collection/Seq;)Lscala/collection/Map;;
const #117 = NameAndType	#115:#116;//  apply:(Lscala/collection/Seq;)Lscala/collection/Map;
const #118 = Method	#37.#117;	//  scala/collection/Map$.apply:(Lscala/collection/Seq;)Lscala/collection/Map;
const #119 = Asciz	scala/collection/MapLike;
const #120 = class	#119;	//  scala/collection/MapLike
const #121 = NameAndType	#12:#13;//  toString:()Ljava/lang/String;
const #122 = InterfaceMethod	#120.#121;	//  scala/collection/MapLike.toString:()Ljava/lang/String;
const #123 = Asciz	 delta=\n;
const #124 = String	#123;	//   delta=\n
const #125 = Asciz	intWrapper;
const #126 = Asciz	(I)Lscala/runtime/RichInt;;
const #127 = NameAndType	#125:#126;//  intWrapper:(I)Lscala/runtime/RichInt;
const #128 = Method	#43.#127;	//  scala/Predef$.intWrapper:(I)Lscala/runtime/RichInt;
const #129 = Asciz	scala/runtime/RichInt;
const #130 = class	#129;	//  scala/runtime/RichInt
const #131 = Asciz	until;
const #132 = Asciz	(I)Lscala/collection/immutable/Range;;
const #133 = NameAndType	#131:#132;//  until:(I)Lscala/collection/immutable/Range;
const #134 = Method	#130.#133;	//  scala/runtime/RichInt.until:(I)Lscala/collection/immutable/Range;
const #135 = Asciz	scala/collection/immutable/Range$ByOne;
const #136 = class	#135;	//  scala/collection/immutable/Range$ByOne
const #137 = Asciz	scala/util/automata/DetWordAutom$$anonfun$toString$1;
const #138 = class	#137;	//  scala/util/automata/DetWordAutom$$anonfun$toString$1
const #139 = Asciz	(Lscala/util/automata/DetWordAutom;Lscala/collection/mutable/StringBuilder;)V;
const #140 = NameAndType	#3:#139;//  "<init>":(Lscala/util/automata/DetWordAutom;Lscala/collection/mutable/StringBuilder;)V
const #141 = Method	#138.#140;	//  scala/util/automata/DetWordAutom$$anonfun$toString$1."<init>":(Lscala/util/automata/DetWordAutom;Lscala/collection/mutable/StringBuilder;)V
const #142 = Asciz	foreach;
const #143 = Asciz	(Lscala/Function1;)V;
const #144 = NameAndType	#142:#143;//  foreach:(Lscala/Function1;)V
const #145 = InterfaceMethod	#136.#144;	//  scala/collection/immutable/Range$ByOne.foreach:(Lscala/Function1;)V
const #146 = Method	#15.#121;	//  scala/collection/mutable/StringBuilder.toString:()Ljava/lang/String;
const #147 = Asciz	this;
const #148 = Asciz	Lscala/util/automata/DetWordAutom;;
const #149 = Asciz	sb$1;
const #150 = Asciz	Lscala/collection/mutable/StringBuilder;;
const #151 = Asciz	Lscala/collection/Map;;
const #152 = Asciz	LocalVariableTable;
const #153 = Asciz	next;
const #154 = Asciz	(ILjava/lang/Object;)I;
const #155 = Asciz	delta;
const #156 = Asciz	()[Lscala/collection/Map;;
const #157 = NameAndType	#155:#156;//  delta:()[Lscala/collection/Map;
const #158 = Method	#22.#157;	//  scala/util/automata/DetWordAutom.delta:()[Lscala/collection/Map;
const #159 = Asciz	get;
const #160 = Asciz	(Ljava/lang/Object;)Lscala/Option;;
const #161 = NameAndType	#159:#160;//  get:(Ljava/lang/Object;)Lscala/Option;
const #162 = InterfaceMethod	#120.#161;	//  scala/collection/MapLike.get:(Ljava/lang/Object;)Lscala/Option;
const #163 = Asciz	scala/Some;
const #164 = class	#163;	//  scala/Some
const #165 = Asciz	x;
const #166 = Asciz	Ljava/lang/Object;;
const #167 = NameAndType	#165:#166;//  x:Ljava/lang/Object;
const #168 = Field	#164.#167;	//  scala/Some.x:Ljava/lang/Object;
const #169 = Asciz	scala/runtime/BoxesRunTime;
const #170 = class	#169;	//  scala/runtime/BoxesRunTime
const #171 = Asciz	unboxToInt;
const #172 = Asciz	(Ljava/lang/Object;)I;
const #173 = NameAndType	#171:#172;//  unboxToInt:(Ljava/lang/Object;)I
const #174 = Method	#170.#173;	//  scala/runtime/BoxesRunTime.unboxToInt:(Ljava/lang/Object;)I
const #175 = Asciz	scala/MatchError;
const #176 = class	#175;	//  scala/MatchError
const #177 = Asciz	scala/Option;
const #178 = class	#177;	//  scala/Option
const #179 = Method	#178.#121;	//  scala/Option.toString:()Ljava/lang/String;
const #180 = Method	#176.#19;	//  scala/MatchError."<init>":(Ljava/lang/String;)V
const #181 = Asciz	default;
const #182 = NameAndType	#181:#48;//  default:()[I
const #183 = Method	#22.#182;	//  scala/util/automata/DetWordAutom.default:()[I
const #184 = Asciz	q;
const #185 = Asciz	I;
const #186 = Asciz	label;
const #187 = Asciz	temp2;
const #188 = Asciz	Lscala/Some;;
const #189 = Asciz	temp3;
const #190 = Asciz	temp1;
const #191 = Asciz	Lscala/Option;;
const #192 = Asciz	(ITT;)I;
const #193 = Asciz	isSink;
const #194 = Asciz	(I)Z;
const #195 = Asciz	isEmpty;
const #196 = Asciz	()Z;
const #197 = NameAndType	#195:#196;//  isEmpty:()Z
const #198 = InterfaceMethod	#120.#197;	//  scala/collection/MapLike.isEmpty:()Z
const #199 = Asciz	isFinal;
const #200 = Asciz	()[Lscala/collection/Map<TT;Ljava/lang/Integer;>;;
const #201 = Asciz	<T:Ljava/lang/Object;>Ljava/lang/Object;Lscala/ScalaObject;;
const #202 = Asciz	ScalaSig;
const #203 = Asciz	InnerClasses;
const #204 = Asciz	scala/collection/immutable/Range;
const #205 = class	#204;	//  scala/collection/immutable/Range
const #206 = Asciz	ByOne;
const #207 = Asciz	$anonfun$1;
const #208 = Asciz	$anonfun$toString$1;
const #209 = Asciz	scala/ScalaObject;
const #210 = class	#209;	//  scala/ScalaObject

{
public scala.util.automata.DetWordAutom();
  Code:
   Stack=1, Locals=1, Args_size=1
   0:	aload_0
   1:	invokespecial	#10; //Method java/lang/Object."<init>":()V
   4:	return
  LineNumberTable: 
   line 27: 0

  Signature: length = 0x2
   00 04 

public java.lang.String toString();
  Code:
   Stack=13, Locals=3, Args_size=1
   0:	new	#15; //class scala/collection/mutable/StringBuilder
   3:	dup
   4:	ldc	#17; //String [DetWordAutom  nstates=
   6:	invokespecial	#20; //Method scala/collection/mutable/StringBuilder."<init>":(Ljava/lang/String;)V
   9:	astore_1
   10:	aload_1
   11:	aload_0
   12:	invokevirtual	#26; //Method nstates:()I
   15:	invokevirtual	#30; //Method scala/collection/mutable/StringBuilder.append:(I)Lscala/collection/mutable/StringBuilder;
   18:	pop
   19:	aload_1
   20:	ldc	#32; //String  finals=
   22:	invokevirtual	#35; //Method scala/collection/mutable/StringBuilder.append:(Ljava/lang/String;)Lscala/collection/mutable/StringBuilder;
   25:	pop
   26:	getstatic	#41; //Field scala/collection/Map$.MODULE$:Lscala/collection/Map$;
   29:	getstatic	#46; //Field scala/Predef$.MODULE$:Lscala/Predef$;
   32:	getstatic	#46; //Field scala/Predef$.MODULE$:Lscala/Predef$;
   35:	getstatic	#46; //Field scala/Predef$.MODULE$:Lscala/Predef$;
   38:	aload_0
   39:	invokevirtual	#50; //Method finals:()[I
   42:	invokevirtual	#54; //Method scala/Predef$.intArrayOps:([I)Lscala/collection/mutable/ArrayOps;
   45:	getstatic	#59; //Field scala/Array$.MODULE$:Lscala/Array$;
   48:	getstatic	#64; //Field scala/reflect/ClassManifest$.MODULE$:Lscala/reflect/ClassManifest$;
   51:	ldc	#66; //class scala/Tuple2
   53:	getstatic	#71; //Field scala/reflect/Manifest$.MODULE$:Lscala/reflect/Manifest$;
   56:	invokevirtual	#75; //Method scala/reflect/Manifest$.Int:()Ljava/lang/Object;
   59:	checkcast	#77; //class scala/reflect/OptManifest
   62:	getstatic	#46; //Field scala/Predef$.MODULE$:Lscala/Predef$;
   65:	iconst_1
   66:	anewarray	#77; //class scala/reflect/OptManifest
   69:	dup
   70:	iconst_0
   71:	getstatic	#71; //Field scala/reflect/Manifest$.MODULE$:Lscala/reflect/Manifest$;
   74:	invokevirtual	#75; //Method scala/reflect/Manifest$.Int:()Ljava/lang/Object;
   77:	checkcast	#77; //class scala/reflect/OptManifest
   80:	aastore
   81:	checkcast	#79; //class "[Ljava/lang/Object;"
   84:	invokevirtual	#83; //Method scala/Predef$.wrapRefArray:([Ljava/lang/Object;)Lscala/collection/mutable/WrappedArray;
   87:	invokevirtual	#87; //Method scala/reflect/ClassManifest$.classType:(Ljava/lang/Class;Lscala/reflect/OptManifest;Lscala/collection/Seq;)Lscala/reflect/ClassManifest;
   90:	invokevirtual	#91; //Method scala/Array$.canBuildFrom:(Lscala/reflect/ClassManifest;)Lscala/collection/generic/CanBuildFrom;
   93:	invokeinterface	#97,  2; //InterfaceMethod scala/collection/IndexedSeqLike.zipWithIndex:(Lscala/collection/generic/CanBuildFrom;)Ljava/lang/Object;
   98:	checkcast	#79; //class "[Ljava/lang/Object;"
   101:	invokevirtual	#101; //Method scala/Predef$.refArrayOps:([Ljava/lang/Object;)Lscala/collection/mutable/ArrayOps;
   104:	new	#103; //class scala/util/automata/DetWordAutom$$anonfun$1
   107:	dup
   108:	aload_0
   109:	invokespecial	#106; //Method scala/util/automata/DetWordAutom$$anonfun$1."<init>":(Lscala/util/automata/DetWordAutom;)V
   112:	getstatic	#59; //Field scala/Array$.MODULE$:Lscala/Array$;
   115:	getstatic	#64; //Field scala/reflect/ClassManifest$.MODULE$:Lscala/reflect/ClassManifest$;
   118:	ldc	#66; //class scala/Tuple2
   120:	getstatic	#71; //Field scala/reflect/Manifest$.MODULE$:Lscala/reflect/Manifest$;
   123:	invokevirtual	#75; //Method scala/reflect/Manifest$.Int:()Ljava/lang/Object;
   126:	checkcast	#77; //class scala/reflect/OptManifest
   129:	getstatic	#46; //Field scala/Predef$.MODULE$:Lscala/Predef$;
   132:	iconst_1
   133:	anewarray	#77; //class scala/reflect/OptManifest
   136:	dup
   137:	iconst_0
   138:	getstatic	#71; //Field scala/reflect/Manifest$.MODULE$:Lscala/reflect/Manifest$;
   141:	invokevirtual	#75; //Method scala/reflect/Manifest$.Int:()Ljava/lang/Object;
   144:	checkcast	#77; //class scala/reflect/OptManifest
   147:	aastore
   148:	checkcast	#79; //class "[Ljava/lang/Object;"
   151:	invokevirtual	#83; //Method scala/Predef$.wrapRefArray:([Ljava/lang/Object;)Lscala/collection/mutable/WrappedArray;
   154:	invokevirtual	#87; //Method scala/reflect/ClassManifest$.classType:(Ljava/lang/Class;Lscala/reflect/OptManifest;Lscala/collection/Seq;)Lscala/reflect/ClassManifest;
   157:	invokevirtual	#91; //Method scala/Array$.canBuildFrom:(Lscala/reflect/ClassManifest;)Lscala/collection/generic/CanBuildFrom;
   160:	invokeinterface	#112,  3; //InterfaceMethod scala/collection/TraversableLike.map:(Lscala/Function1;Lscala/collection/generic/CanBuildFrom;)Ljava/lang/Object;
   165:	checkcast	#114; //class "[Lscala/Tuple2;"
   168:	checkcast	#79; //class "[Ljava/lang/Object;"
   171:	invokevirtual	#83; //Method scala/Predef$.wrapRefArray:([Ljava/lang/Object;)Lscala/collection/mutable/WrappedArray;
   174:	invokevirtual	#118; //Method scala/collection/Map$.apply:(Lscala/collection/Seq;)Lscala/collection/Map;
   177:	astore_2
   178:	aload_1
   179:	aload_2
   180:	invokeinterface	#122,  1; //InterfaceMethod scala/collection/MapLike.toString:()Ljava/lang/String;
   185:	invokevirtual	#35; //Method scala/collection/mutable/StringBuilder.append:(Ljava/lang/String;)Lscala/collection/mutable/StringBuilder;
   188:	pop
   189:	aload_1
   190:	ldc	#124; //String  delta=\n
   192:	invokevirtual	#35; //Method scala/collection/mutable/StringBuilder.append:(Ljava/lang/String;)Lscala/collection/mutable/StringBuilder;
   195:	pop
   196:	getstatic	#46; //Field scala/Predef$.MODULE$:Lscala/Predef$;
   199:	iconst_0
   200:	invokevirtual	#128; //Method scala/Predef$.intWrapper:(I)Lscala/runtime/RichInt;
   203:	aload_0
   204:	invokevirtual	#26; //Method nstates:()I
   207:	invokevirtual	#134; //Method scala/runtime/RichInt.until:(I)Lscala/collection/immutable/Range;
   210:	checkcast	#136; //class scala/collection/immutable/Range$ByOne
   213:	new	#138; //class scala/util/automata/DetWordAutom$$anonfun$toString$1
   216:	dup
   217:	aload_0
   218:	aload_1
   219:	invokespecial	#141; //Method scala/util/automata/DetWordAutom$$anonfun$toString$1."<init>":(Lscala/util/automata/DetWordAutom;Lscala/collection/mutable/StringBuilder;)V
   222:	invokeinterface	#145,  2; //InterfaceMethod scala/collection/immutable/Range$ByOne.foreach:(Lscala/Function1;)V
   227:	aload_1
   228:	invokevirtual	#146; //Method scala/collection/mutable/StringBuilder.toString:()Ljava/lang/String;
   231:	areturn
  LineNumberTable: 
   line 45: 0
   line 57: 10
   line 46: 11
   line 47: 19
   line 48: 26
   line 49: 178
   line 50: 189
   line 52: 196
   line 57: 227

  LocalVariableTable: 
   Start  Length  Slot  Name   Signature
   0      232      0    this       Lscala/util/automata/DetWordAutom;
   10      221      1    sb$1       Lscala/collection/mutable/StringBuilder;
   178      53      2    map       Lscala/collection/Map;


public int next(int, java.lang.Object);
  Code:
   Stack=3, Locals=6, Args_size=3
   0:	aload_0
   1:	invokevirtual	#158; //Method delta:()[Lscala/collection/Map;
   4:	iload_1
   5:	aaload
   6:	aload_2
   7:	invokeinterface	#162,  2; //InterfaceMethod scala/collection/MapLike.get:(Ljava/lang/Object;)Lscala/Option;
   12:	astore	5
   14:	aload	5
   16:	instanceof	#164; //class scala/Some
   19:	ifeq	59
   22:	aload	5
   24:	checkcast	#164; //class scala/Some
   27:	astore_3
   28:	aload_3
   29:	getfield	#168; //Field scala/Some.x:Ljava/lang/Object;
   32:	invokestatic	#174; //Method scala/runtime/BoxesRunTime.unboxToInt:(Ljava/lang/Object;)I
   35:	istore	4
   37:	iconst_1
   38:	ifeq	46
   41:	iload	4
   43:	goto	69
   46:	new	#176; //class scala/MatchError
   49:	dup
   50:	aload	5
   52:	invokevirtual	#179; //Method scala/Option.toString:()Ljava/lang/String;
   55:	invokespecial	#180; //Method scala/MatchError."<init>":(Ljava/lang/String;)V
   58:	athrow
   59:	iconst_1
   60:	ifeq	70
   63:	aload_0
   64:	invokevirtual	#183; //Method default:()[I
   67:	iload_1
   68:	iaload
   69:	ireturn
   70:	new	#176; //class scala/MatchError
   73:	dup
   74:	aload	5
   76:	invokevirtual	#179; //Method scala/Option.toString:()Ljava/lang/String;
   79:	invokespecial	#180; //Method scala/MatchError."<init>":(Ljava/lang/String;)V
   82:	athrow
  LineNumberTable: 
   line 38: 0
   line 37: 22
   line 21: 37
   line 39: 41
   line 38: 46
   line 21: 59
   line 40: 63
   line 38: 69

  LocalVariableTable: 
   Start  Length  Slot  Name   Signature
   0      83      0    this       Lscala/util/automata/DetWordAutom;
   0      83      1    q       I
   0      83      2    label       Ljava/lang/Object;
   28      31      3    temp2       Lscala/Some;
   37      22      4    temp3       I
   14      69      5    temp1       Lscala/Option;

  Signature: length = 0x2
   00 FFFFFFC0 

public boolean isSink(int);
  Code:
   Stack=2, Locals=2, Args_size=2
   0:	aload_0
   1:	invokevirtual	#158; //Method delta:()[Lscala/collection/Map;
   4:	iload_1
   5:	aaload
   6:	invokeinterface	#198,  1; //InterfaceMethod scala/collection/MapLike.isEmpty:()Z
   11:	ifeq	28
   14:	aload_0
   15:	invokevirtual	#183; //Method default:()[I
   18:	iload_1
   19:	iaload
   20:	iload_1
   21:	if_icmpne	28
   24:	iconst_1
   25:	goto	29
   28:	iconst_0
   29:	ireturn
  LineNumberTable: 
   line 35: 0

  LocalVariableTable: 
   Start  Length  Slot  Name   Signature
   0      30      0    this       Lscala/util/automata/DetWordAutom;
   0      30      1    q       I


public boolean isFinal(int);
  Code:
   Stack=2, Locals=2, Args_size=2
   0:	aload_0
   1:	invokevirtual	#50; //Method finals:()[I
   4:	iload_1
   5:	iaload
   6:	iconst_0
   7:	if_icmpeq	14
   10:	iconst_1
   11:	goto	15
   14:	iconst_0
   15:	ireturn
  LineNumberTable: 
   line 34: 0

  LocalVariableTable: 
   Start  Length  Slot  Name   Signature
   0      16      0    this       Lscala/util/automata/DetWordAutom;
   0      16      1    q       I


public abstract int[] default();

public abstract scala.collection.Map[] delta();
  Signature: length = 0x2
   00 FFFFFFC8 

public abstract int[] finals();

public abstract int nstates();

}

