Compiled from "DetWordAutom.scala"
public final class scala.util.automata.DetWordAutom$$anonfun$toString$1 extends java.lang.Object implements scala.Function1,scala.ScalaObject,java.io.Serializable
  SourceFile: "DetWordAutom.scala"
  Scala: length = 0x
   
  InnerClass: 
   public final #124= #9 of #72; //$anonfun$toString$1=class scala/util/automata/DetWordAutom$$anonfun$toString$1 of class scala/util/automata/DetWordAutom
  minor version: 0
  major version: 49
  Constant pool:
const #1 = Asciz	SourceFile;
const #2 = Asciz	DetWordAutom.scala;
const #3 = Asciz	<clinit>;
const #4 = Asciz	()V;
const #5 = Asciz	Code;
const #6 = Asciz	serialVersionUID;
const #7 = Asciz	J;
const #8 = Asciz	scala/util/automata/DetWordAutom$$anonfun$toString$1;
const #9 = class	#8;	//  scala/util/automata/DetWordAutom$$anonfun$toString$1
const #10 = NameAndType	#6:#7;//  serialVersionUID:J
const #11 = Field	#9.#10;	//  scala/util/automata/DetWordAutom$$anonfun$toString$1.serialVersionUID:J
const #12 = Asciz	sb$1;
const #13 = Asciz	Lscala/collection/mutable/StringBuilder;;
const #14 = Asciz	$outer;
const #15 = Asciz	Lscala/util/automata/DetWordAutom;;
const #16 = Asciz	<init>;
const #17 = Asciz	(Lscala/util/automata/DetWordAutom;Lscala/collection/mutable/StringBuilder;)V;
const #18 = Asciz	LineNumberTable;
const #19 = Asciz	java/lang/NullPointerException;
const #20 = class	#19;	//  java/lang/NullPointerException
const #21 = NameAndType	#16:#4;//  "<init>":()V
const #22 = Method	#20.#21;	//  java/lang/NullPointerException."<init>":()V
const #23 = NameAndType	#14:#15;//  $outer:Lscala/util/automata/DetWordAutom;
const #24 = Field	#9.#23;	//  scala/util/automata/DetWordAutom$$anonfun$toString$1.$outer:Lscala/util/automata/DetWordAutom;
const #25 = NameAndType	#12:#13;//  sb$1:Lscala/collection/mutable/StringBuilder;
const #26 = Field	#9.#25;	//  scala/util/automata/DetWordAutom$$anonfun$toString$1.sb$1:Lscala/collection/mutable/StringBuilder;
const #27 = Asciz	java/lang/Object;
const #28 = class	#27;	//  java/lang/Object
const #29 = Method	#28.#21;	//  java/lang/Object."<init>":()V
const #30 = Asciz	scala/Function1$class;
const #31 = class	#30;	//  scala/Function1$class
const #32 = Asciz	$init$;
const #33 = Asciz	(Lscala/Function1;)V;
const #34 = NameAndType	#32:#33;//  $init$:(Lscala/Function1;)V
const #35 = Method	#31.#34;	//  scala/Function1$class.$init$:(Lscala/Function1;)V
const #36 = Asciz	this;
const #37 = Asciz	Lscala/util/automata/DetWordAutom$$anonfun$toString$1;;
const #38 = Asciz	LocalVariableTable;
const #39 = Asciz	(Lscala/util/automata/DetWordAutom<TT;>;)V;
const #40 = Asciz	Signature;
const #41 = Asciz	apply;
const #42 = Asciz	(Ljava/lang/Object;)Ljava/lang/Object;;
const #43 = Asciz	scala/runtime/BoxesRunTime;
const #44 = class	#43;	//  scala/runtime/BoxesRunTime
const #45 = Asciz	unboxToInt;
const #46 = Asciz	(Ljava/lang/Object;)I;
const #47 = NameAndType	#45:#46;//  unboxToInt:(Ljava/lang/Object;)I
const #48 = Method	#44.#47;	//  scala/runtime/BoxesRunTime.unboxToInt:(Ljava/lang/Object;)I
const #49 = Asciz	(I)Ljava/lang/Object;;
const #50 = NameAndType	#41:#49;//  apply:(I)Ljava/lang/Object;
const #51 = Method	#9.#50;	//  scala/util/automata/DetWordAutom$$anonfun$toString$1.apply:(I)Ljava/lang/Object;
const #52 = Asciz	v1;
const #53 = Asciz	Ljava/lang/Object;;
const #54 = Asciz	%d->%s\n;
const #55 = String	#54;	//  %d->%s\n
const #56 = Asciz	scala/collection/immutable/StringOps;
const #57 = class	#56;	//  scala/collection/immutable/StringOps
const #58 = Asciz	(Ljava/lang/String;)V;
const #59 = NameAndType	#16:#58;//  "<init>":(Ljava/lang/String;)V
const #60 = Method	#57.#59;	//  scala/collection/immutable/StringOps."<init>":(Ljava/lang/String;)V
const #61 = Asciz	scala/Predef$;
const #62 = class	#61;	//  scala/Predef$
const #63 = Asciz	MODULE$;
const #64 = Asciz	Lscala/Predef$;;
const #65 = NameAndType	#63:#64;//  MODULE$:Lscala/Predef$;
const #66 = Field	#62.#65;	//  scala/Predef$.MODULE$:Lscala/Predef$;
const #67 = Asciz	boxToInteger;
const #68 = Asciz	(I)Ljava/lang/Integer;;
const #69 = NameAndType	#67:#68;//  boxToInteger:(I)Ljava/lang/Integer;
const #70 = Method	#44.#69;	//  scala/runtime/BoxesRunTime.boxToInteger:(I)Ljava/lang/Integer;
const #71 = Asciz	scala/util/automata/DetWordAutom;
const #72 = class	#71;	//  scala/util/automata/DetWordAutom
const #73 = Asciz	delta;
const #74 = Asciz	()[Lscala/collection/Map;;
const #75 = NameAndType	#73:#74;//  delta:()[Lscala/collection/Map;
const #76 = Method	#72.#75;	//  scala/util/automata/DetWordAutom.delta:()[Lscala/collection/Map;
const #77 = Asciz	genericWrapArray;
const #78 = Asciz	(Ljava/lang/Object;)Lscala/collection/mutable/WrappedArray;;
const #79 = NameAndType	#77:#78;//  genericWrapArray:(Ljava/lang/Object;)Lscala/collection/mutable/WrappedArray;
const #80 = Method	#62.#79;	//  scala/Predef$.genericWrapArray:(Ljava/lang/Object;)Lscala/collection/mutable/WrappedArray;
const #81 = Asciz	scala/collection/immutable/StringLike;
const #82 = class	#81;	//  scala/collection/immutable/StringLike
const #83 = Asciz	format;
const #84 = Asciz	(Lscala/collection/Seq;)Ljava/lang/String;;
const #85 = NameAndType	#83:#84;//  format:(Lscala/collection/Seq;)Ljava/lang/String;
const #86 = InterfaceMethod	#82.#85;	//  scala/collection/immutable/StringLike.format:(Lscala/collection/Seq;)Ljava/lang/String;
const #87 = Asciz	scala/collection/mutable/StringBuilder;
const #88 = class	#87;	//  scala/collection/mutable/StringBuilder
const #89 = Asciz	append;
const #90 = Asciz	(Ljava/lang/String;)Lscala/collection/mutable/StringBuilder;;
const #91 = NameAndType	#89:#90;//  append:(Ljava/lang/String;)Lscala/collection/mutable/StringBuilder;
const #92 = Method	#88.#91;	//  scala/collection/mutable/StringBuilder.append:(Ljava/lang/String;)Lscala/collection/mutable/StringBuilder;
const #93 = Asciz	default;
const #94 = Asciz	()[I;
const #95 = NameAndType	#93:#94;//  default:()[I
const #96 = Method	#72.#95;	//  scala/util/automata/DetWordAutom.default:()[I
const #97 = Asciz	_>%s\n;
const #98 = String	#97;	//  _>%s\n
const #99 = Asciz	scala/runtime/BoxedUnit;
const #100 = class	#99;	//  scala/runtime/BoxedUnit
const #101 = Asciz	UNIT;
const #102 = Asciz	Lscala/runtime/BoxedUnit;;
const #103 = NameAndType	#101:#102;//  UNIT:Lscala/runtime/BoxedUnit;
const #104 = Field	#100.#103;	//  scala/runtime/BoxedUnit.UNIT:Lscala/runtime/BoxedUnit;
const #105 = Asciz	i;
const #106 = Asciz	I;
const #107 = Asciz	andThen;
const #108 = Asciz	(Lscala/Function1;)Lscala/Function1;;
const #109 = Asciz	(Lscala/Function1;Lscala/Function1;)Lscala/Function1;;
const #110 = NameAndType	#107:#109;//  andThen:(Lscala/Function1;Lscala/Function1;)Lscala/Function1;
const #111 = Method	#31.#110;	//  scala/Function1$class.andThen:(Lscala/Function1;Lscala/Function1;)Lscala/Function1;
const #112 = Asciz	g;
const #113 = Asciz	Lscala/Function1;;
const #114 = Asciz	compose;
const #115 = NameAndType	#114:#109;//  compose:(Lscala/Function1;Lscala/Function1;)Lscala/Function1;
const #116 = Method	#31.#115;	//  scala/Function1$class.compose:(Lscala/Function1;Lscala/Function1;)Lscala/Function1;
const #117 = Asciz	toString;
const #118 = Asciz	()Ljava/lang/String;;
const #119 = Asciz	(Lscala/Function1;)Ljava/lang/String;;
const #120 = NameAndType	#117:#119;//  toString:(Lscala/Function1;)Ljava/lang/String;
const #121 = Method	#31.#120;	//  scala/Function1$class.toString:(Lscala/Function1;)Ljava/lang/String;
const #122 = Asciz	Scala;
const #123 = Asciz	InnerClasses;
const #124 = Asciz	$anonfun$toString$1;
const #125 = Asciz	scala/Function1;
const #126 = class	#125;	//  scala/Function1
const #127 = Asciz	scala/ScalaObject;
const #128 = class	#127;	//  scala/ScalaObject
const #129 = Asciz	java/io/Serializable;
const #130 = class	#129;	//  java/io/Serializable

{
public static final long serialVersionUID;

public static {};
  Code:
   Stack=2, Locals=0, Args_size=0
   0:	lconst_0
   1:	putstatic	#11; //Field serialVersionUID:J
   4:	return

public scala.util.automata.DetWordAutom$$anonfun$toString$1(scala.util.automata.DetWordAutom, scala.collection.mutable.StringBuilder);
  Code:
   Stack=2, Locals=3, Args_size=3
   0:	aload_1
   1:	ifnonnull	12
   4:	new	#20; //class java/lang/NullPointerException
   7:	dup
   8:	invokespecial	#22; //Method java/lang/NullPointerException."<init>":()V
   11:	athrow
   12:	aload_0
   13:	aload_1
   14:	putfield	#24; //Field $outer:Lscala/util/automata/DetWordAutom;
   17:	aload_0
   18:	aload_2
   19:	putfield	#26; //Field sb$1:Lscala/collection/mutable/StringBuilder;
   22:	aload_0
   23:	invokespecial	#29; //Method java/lang/Object."<init>":()V
   26:	aload_0
   27:	invokestatic	#35; //Method scala/Function1$class.$init$:(Lscala/Function1;)V
   30:	return
  LineNumberTable: 
   line 52: 0

  LocalVariableTable: 
   Start  Length  Slot  Name   Signature
   0      31      0    this       Lscala/util/automata/DetWordAutom$$anonfun$toString$1;
   0      31      1    $outer       Lscala/util/automata/DetWordAutom;

  Signature: length = 0x2
   00 27 

public final java.lang.Object apply(java.lang.Object);
  Code:
   Stack=2, Locals=3, Args_size=2
   0:	aload_0
   1:	getfield	#24; //Field $outer:Lscala/util/automata/DetWordAutom;
   4:	astore_2
   5:	aload_0
   6:	aload_1
   7:	invokestatic	#48; //Method scala/runtime/BoxesRunTime.unboxToInt:(Ljava/lang/Object;)I
   10:	invokevirtual	#51; //Method apply:(I)Ljava/lang/Object;
   13:	areturn
  LineNumberTable: 
   line 52: 0

  LocalVariableTable: 
   Start  Length  Slot  Name   Signature
   0      14      0    this       Lscala/util/automata/DetWordAutom$$anonfun$toString$1;
   5      9      1    v1       Ljava/lang/Object;


public final java.lang.Object apply(int);
  Code:
   Stack=8, Locals=6, Args_size=2
   0:	aload_0
   1:	getfield	#24; //Field $outer:Lscala/util/automata/DetWordAutom;
   4:	astore	5
   6:	aload_0
   7:	getfield	#26; //Field sb$1:Lscala/collection/mutable/StringBuilder;
   10:	ldc	#55; //String %d->%s\n
   12:	astore_2
   13:	new	#57; //class scala/collection/immutable/StringOps
   16:	dup
   17:	aload_2
   18:	invokespecial	#60; //Method scala/collection/immutable/StringOps."<init>":(Ljava/lang/String;)V
   21:	getstatic	#66; //Field scala/Predef$.MODULE$:Lscala/Predef$;
   24:	iconst_2
   25:	anewarray	#28; //class java/lang/Object
   28:	dup
   29:	iconst_0
   30:	iload_1
   31:	invokestatic	#70; //Method scala/runtime/BoxesRunTime.boxToInteger:(I)Ljava/lang/Integer;
   34:	aastore
   35:	dup
   36:	iconst_1
   37:	aload_0
   38:	getfield	#24; //Field $outer:Lscala/util/automata/DetWordAutom;
   41:	invokevirtual	#76; //Method scala/util/automata/DetWordAutom.delta:()[Lscala/collection/Map;
   44:	iload_1
   45:	aaload
   46:	aastore
   47:	invokevirtual	#80; //Method scala/Predef$.genericWrapArray:(Ljava/lang/Object;)Lscala/collection/mutable/WrappedArray;
   50:	invokeinterface	#86,  2; //InterfaceMethod scala/collection/immutable/StringLike.format:(Lscala/collection/Seq;)Ljava/lang/String;
   55:	invokevirtual	#92; //Method scala/collection/mutable/StringBuilder.append:(Ljava/lang/String;)Lscala/collection/mutable/StringBuilder;
   58:	pop
   59:	iload_1
   60:	aload_0
   61:	getfield	#24; //Field $outer:Lscala/util/automata/DetWordAutom;
   64:	invokevirtual	#96; //Method scala/util/automata/DetWordAutom.default:()[I
   67:	arraylength
   68:	if_icmpge	126
   71:	aload_0
   72:	getfield	#26; //Field sb$1:Lscala/collection/mutable/StringBuilder;
   75:	ldc	#98; //String _>%s\n
   77:	astore_3
   78:	new	#57; //class scala/collection/immutable/StringOps
   81:	dup
   82:	aload_3
   83:	invokespecial	#60; //Method scala/collection/immutable/StringOps."<init>":(Ljava/lang/String;)V
   86:	getstatic	#66; //Field scala/Predef$.MODULE$:Lscala/Predef$;
   89:	iconst_1
   90:	anewarray	#28; //class java/lang/Object
   93:	dup
   94:	iconst_0
   95:	aload_0
   96:	getfield	#24; //Field $outer:Lscala/util/automata/DetWordAutom;
   99:	invokevirtual	#96; //Method scala/util/automata/DetWordAutom.default:()[I
   102:	iload_1
   103:	iaload
   104:	istore	4
   106:	iload	4
   108:	invokestatic	#70; //Method scala/runtime/BoxesRunTime.boxToInteger:(I)Ljava/lang/Integer;
   111:	aastore
   112:	invokevirtual	#80; //Method scala/Predef$.genericWrapArray:(Ljava/lang/Object;)Lscala/collection/mutable/WrappedArray;
   115:	invokeinterface	#86,  2; //InterfaceMethod scala/collection/immutable/StringLike.format:(Lscala/collection/Seq;)Ljava/lang/String;
   120:	invokevirtual	#92; //Method scala/collection/mutable/StringBuilder.append:(Ljava/lang/String;)Lscala/collection/mutable/StringBuilder;
   123:	goto	129
   126:	getstatic	#104; //Field scala/runtime/BoxedUnit.UNIT:Lscala/runtime/BoxedUnit;
   129:	areturn
  LineNumberTable: 
   line 53: 0
   line 54: 59
   line 55: 71
   line 54: 126
   line 52: 129

  LocalVariableTable: 
   Start  Length  Slot  Name   Signature
   0      130      0    this       Lscala/util/automata/DetWordAutom$$anonfun$toString$1;
   6      124      1    i       I


public scala.Function1 andThen(scala.Function1);
  Code:
   Stack=2, Locals=2, Args_size=2
   0:	aload_0
   1:	aload_1
   2:	invokestatic	#111; //Method scala/Function1$class.andThen:(Lscala/Function1;Lscala/Function1;)Lscala/Function1;
   5:	areturn
  LineNumberTable: 
   line 52: 0

  LocalVariableTable: 
   Start  Length  Slot  Name   Signature
   0      6      0    this       Lscala/util/automata/DetWordAutom$$anonfun$toString$1;
   0      6      1    g       Lscala/Function1;


public scala.Function1 compose(scala.Function1);
  Code:
   Stack=2, Locals=2, Args_size=2
   0:	aload_0
   1:	aload_1
   2:	invokestatic	#116; //Method scala/Function1$class.compose:(Lscala/Function1;Lscala/Function1;)Lscala/Function1;
   5:	areturn
  LineNumberTable: 
   line 52: 0

  LocalVariableTable: 
   Start  Length  Slot  Name   Signature
   0      6      0    this       Lscala/util/automata/DetWordAutom$$anonfun$toString$1;
   0      6      1    g       Lscala/Function1;


public java.lang.String toString();
  Code:
   Stack=1, Locals=1, Args_size=1
   0:	aload_0
   1:	invokestatic	#121; //Method scala/Function1$class.toString:(Lscala/Function1;)Ljava/lang/String;
   4:	areturn
  LineNumberTable: 
   line 52: 0


}

