Compiled from "DetWordAutom.scala"
public final class scala.util.automata.DetWordAutom$$anonfun$toString$1 extends java.lang.Object implements scala.Function1,scala.ScalaObject,java.io.Serializable
  SourceFile: "DetWordAutom.scala"
  Scala: length = 0x
   
  InnerClass: 
   public final $anonfun$toString$1=class scala/util/automata/DetWordAutom$$anonfun$toString$1 of class scala/util/automata/DetWordAutom
  minor version: 0
  major version: 49
  Constant pool:
Asciz	SourceFile;
Asciz	DetWordAutom.scala;
Asciz	<clinit>;
Asciz	()V;
Asciz	Code;
Asciz	serialVersionUID;
Asciz	J;
Asciz	scala/util/automata/DetWordAutom$$anonfun$toString$1;
class	scala/util/automata/DetWordAutom$$anonfun$toString$1
NameAndType	serialVersionUID:J
Field	scala/util/automata/DetWordAutom$$anonfun$toString$1.serialVersionUID:J
Asciz	sb$1;
Asciz	Lscala/collection/mutable/StringBuilder;;
Asciz	$outer;
Asciz	Lscala/util/automata/DetWordAutom;;
Asciz	<init>;
Asciz	(Lscala/util/automata/DetWordAutom;Lscala/collection/mutable/StringBuilder;)V;
Asciz	LineNumberTable;
Asciz	java/lang/NullPointerException;
class	java/lang/NullPointerException
NameAndType	"<init>":()V
Method	java/lang/NullPointerException."<init>":()V
NameAndType	$outer:Lscala/util/automata/DetWordAutom;
Field	scala/util/automata/DetWordAutom$$anonfun$toString$1.$outer:Lscala/util/automata/DetWordAutom;
NameAndType	sb$1:Lscala/collection/mutable/StringBuilder;
Field	scala/util/automata/DetWordAutom$$anonfun$toString$1.sb$1:Lscala/collection/mutable/StringBuilder;
Asciz	java/lang/Object;
class	java/lang/Object
Method	java/lang/Object."<init>":()V
Asciz	scala/Function1$class;
class	scala/Function1$class
Asciz	$init$;
Asciz	(Lscala/Function1;)V;
NameAndType	$init$:(Lscala/Function1;)V
Method	scala/Function1$class.$init$:(Lscala/Function1;)V
Asciz	this;
Asciz	Lscala/util/automata/DetWordAutom$$anonfun$toString$1;;
Asciz	LocalVariableTable;
Asciz	(Lscala/util/automata/DetWordAutom<TT;>;)V;
Asciz	Signature;
Asciz	apply;
Asciz	(Ljava/lang/Object;)Ljava/lang/Object;;
Asciz	scala/runtime/BoxesRunTime;
class	scala/runtime/BoxesRunTime
Asciz	unboxToInt;
Asciz	(Ljava/lang/Object;)I;
NameAndType	unboxToInt:(Ljava/lang/Object;)I
Method	scala/runtime/BoxesRunTime.unboxToInt:(Ljava/lang/Object;)I
Asciz	(I)Ljava/lang/Object;;
NameAndType	apply:(I)Ljava/lang/Object;
Method	scala/util/automata/DetWordAutom$$anonfun$toString$1.apply:(I)Ljava/lang/Object;
Asciz	v1;
Asciz	Ljava/lang/Object;;
Asciz	%d->%s\n;
String	%d->%s\n
Asciz	scala/collection/immutable/StringOps;
class	scala/collection/immutable/StringOps
Asciz	(Ljava/lang/String;)V;
NameAndType	"<init>":(Ljava/lang/String;)V
Method	scala/collection/immutable/StringOps."<init>":(Ljava/lang/String;)V
Asciz	scala/Predef$;
class	scala/Predef$
Asciz	MODULE$;
Asciz	Lscala/Predef$;;
NameAndType	MODULE$:Lscala/Predef$;
Field	scala/Predef$.MODULE$:Lscala/Predef$;
Asciz	boxToInteger;
Asciz	(I)Ljava/lang/Integer;;
NameAndType	boxToInteger:(I)Ljava/lang/Integer;
Method	scala/runtime/BoxesRunTime.boxToInteger:(I)Ljava/lang/Integer;
Asciz	scala/util/automata/DetWordAutom;
class	scala/util/automata/DetWordAutom
Asciz	delta;
Asciz	()[Lscala/collection/Map;;
NameAndType	delta:()[Lscala/collection/Map;
Method	scala/util/automata/DetWordAutom.delta:()[Lscala/collection/Map;
Asciz	genericWrapArray;
Asciz	(Ljava/lang/Object;)Lscala/collection/mutable/WrappedArray;;
NameAndType	genericWrapArray:(Ljava/lang/Object;)Lscala/collection/mutable/WrappedArray;
Method	scala/Predef$.genericWrapArray:(Ljava/lang/Object;)Lscala/collection/mutable/WrappedArray;
Asciz	scala/collection/immutable/StringLike;
class	scala/collection/immutable/StringLike
Asciz	format;
Asciz	(Lscala/collection/Seq;)Ljava/lang/String;;
NameAndType	format:(Lscala/collection/Seq;)Ljava/lang/String;
InterfaceMethod	scala/collection/immutable/StringLike.format:(Lscala/collection/Seq;)Ljava/lang/String;
Asciz	scala/collection/mutable/StringBuilder;
class	scala/collection/mutable/StringBuilder
Asciz	append;
Asciz	(Ljava/lang/String;)Lscala/collection/mutable/StringBuilder;;
NameAndType	append:(Ljava/lang/String;)Lscala/collection/mutable/StringBuilder;
Method	scala/collection/mutable/StringBuilder.append:(Ljava/lang/String;)Lscala/collection/mutable/StringBuilder;
Asciz	default;
Asciz	()[I;
NameAndType	default:()[I
Method	scala/util/automata/DetWordAutom.default:()[I
Asciz	_>%s\n;
String	_>%s\n
Asciz	scala/runtime/BoxedUnit;
class	scala/runtime/BoxedUnit
Asciz	UNIT;
Asciz	Lscala/runtime/BoxedUnit;;
NameAndType	UNIT:Lscala/runtime/BoxedUnit;
Field	scala/runtime/BoxedUnit.UNIT:Lscala/runtime/BoxedUnit;
Asciz	i;
Asciz	I;
Asciz	andThen;
Asciz	(Lscala/Function1;)Lscala/Function1;;
Asciz	(Lscala/Function1;Lscala/Function1;)Lscala/Function1;;
NameAndType	andThen:(Lscala/Function1;Lscala/Function1;)Lscala/Function1;
Method	scala/Function1$class.andThen:(Lscala/Function1;Lscala/Function1;)Lscala/Function1;
Asciz	g;
Asciz	Lscala/Function1;;
Asciz	compose;
NameAndType	compose:(Lscala/Function1;Lscala/Function1;)Lscala/Function1;
Method	scala/Function1$class.compose:(Lscala/Function1;Lscala/Function1;)Lscala/Function1;
Asciz	toString;
Asciz	()Ljava/lang/String;;
Asciz	(Lscala/Function1;)Ljava/lang/String;;
NameAndType	toString:(Lscala/Function1;)Ljava/lang/String;
Method	scala/Function1$class.toString:(Lscala/Function1;)Ljava/lang/String;
Asciz	Scala;
Asciz	InnerClasses;
Asciz	$anonfun$toString$1;
Asciz	scala/Function1;
class	scala/Function1
Asciz	scala/ScalaObject;
class	scala/ScalaObject
Asciz	java/io/Serializable;
class	java/io/Serializable

{
public static final long serialVersionUID;
  Signature: J

private final scala.collection.mutable.StringBuilder sb$1;
  Signature: Lscala/collection/mutable/StringBuilder;

private final scala.util.automata.DetWordAutom $outer;
  Signature: Lscala/util/automata/DetWordAutom;

public static {};
  Signature: ()V
  Code:
   Stack=2, Locals=0, Args_size=0
	lconst_0
	putstatic	Field serialVersionUID:J
	return
  Labels:

public scala.util.automata.DetWordAutom$$anonfun$toString$1(scala.util.automata.DetWordAutom, scala.collection.mutable.StringBuilder);
  Signature: (Lscala/util/automata/DetWordAutom;Lscala/collection/mutable/StringBuilder;)V
  Code:
   Stack=2, Locals=3, Args_size=3
	aload_1
	ifnonnull	l1 // aload_0
	new	class java/lang/NullPointerException
	dup
	invokespecial	Method java/lang/NullPointerException."<init>":()V
	athrow
l1	aload_0
	aload_1
	putfield	Field $outer:Lscala/util/automata/DetWordAutom;
	aload_0
	aload_2
	putfield	Field sb$1:Lscala/collection/mutable/StringBuilder;
	aload_0
	invokespecial	Method java/lang/Object."<init>":()V
	aload_0
	invokestatic	Method scala/Function1$class.$init$:(Lscala/Function1;)V
	return
  Labels:
   	l1 = 12 // aload_0
  LocalVariableTable: 
   Start  Length  Slot  Name   Signature
   0      31      0    this       Lscala/util/automata/DetWordAutom$$anonfun$toString$1;
   0      31      1    $outer       Lscala/util/automata/DetWordAutom;

  Signature: length = 0x2
   00 27 

public final java.lang.Object apply(java.lang.Object);
  Signature: (Ljava/lang/Object;)Ljava/lang/Object;
  Code:
   Stack=2, Locals=3, Args_size=2
	aload_0
	getfield	Field $outer:Lscala/util/automata/DetWordAutom;
	astore_2
	aload_0
	aload_1
	invokestatic	Method scala/runtime/BoxesRunTime.unboxToInt:(Ljava/lang/Object;)I
	invokevirtual	Method apply:(I)Ljava/lang/Object;
	areturn
  Labels:
  LocalVariableTable: 
   Start  Length  Slot  Name   Signature
   0      14      0    this       Lscala/util/automata/DetWordAutom$$anonfun$toString$1;
   5      9      1    v1       Ljava/lang/Object;


public final java.lang.Object apply(int);
  Signature: (I)Ljava/lang/Object;
  Code:
   Stack=8, Locals=6, Args_size=2
	aload_0
	getfield	Field $outer:Lscala/util/automata/DetWordAutom;
	astore	5
	aload_0
	getfield	Field sb$1:Lscala/collection/mutable/StringBuilder;
	ldc	String %d->%s\n
	astore_2
	new	class scala/collection/immutable/StringOps
	dup
	aload_2
	invokespecial	Method scala/collection/immutable/StringOps."<init>":(Ljava/lang/String;)V
	getstatic	Field scala/Predef$.MODULE$:Lscala/Predef$;
	iconst_2
	anewarray	class java/lang/Object
	dup
	iconst_0
	iload_1
	invokestatic	Method scala/runtime/BoxesRunTime.boxToInteger:(I)Ljava/lang/Integer;
	aastore
	dup
	iconst_1
	aload_0
	getfield	Field $outer:Lscala/util/automata/DetWordAutom;
	invokevirtual	Method scala/util/automata/DetWordAutom.delta:()[Lscala/collection/Map;
	iload_1
	aaload
	aastore
	invokevirtual	Method scala/Predef$.genericWrapArray:(Ljava/lang/Object;)Lscala/collection/mutable/WrappedArray;
	invokeinterface	InterfaceMethod scala/collection/immutable/StringLike.format:(Lscala/collection/Seq;)Ljava/lang/String;
	invokevirtual	Method scala/collection/mutable/StringBuilder.append:(Ljava/lang/String;)Lscala/collection/mutable/StringBuilder;
	pop
	iload_1
	aload_0
	getfield	Field $outer:Lscala/util/automata/DetWordAutom;
	invokevirtual	Method scala/util/automata/DetWordAutom.default:()[I
	arraylength
	if_icmpge	l1 // getstatic
	aload_0
	getfield	Field sb$1:Lscala/collection/mutable/StringBuilder;
	ldc	String _>%s\n
	astore_3
	new	class scala/collection/immutable/StringOps
	dup
	aload_3
	invokespecial	Method scala/collection/immutable/StringOps."<init>":(Ljava/lang/String;)V
	getstatic	Field scala/Predef$.MODULE$:Lscala/Predef$;
	iconst_1
	anewarray	class java/lang/Object
	dup
	iconst_0
	aload_0
	getfield	Field $outer:Lscala/util/automata/DetWordAutom;
	invokevirtual	Method scala/util/automata/DetWordAutom.default:()[I
	iload_1
	iaload
	istore	4
	iload	4
	invokestatic	Method scala/runtime/BoxesRunTime.boxToInteger:(I)Ljava/lang/Integer;
	aastore
	invokevirtual	Method scala/Predef$.genericWrapArray:(Ljava/lang/Object;)Lscala/collection/mutable/WrappedArray;
	invokeinterface	InterfaceMethod scala/collection/immutable/StringLike.format:(Lscala/collection/Seq;)Ljava/lang/String;
	invokevirtual	Method scala/collection/mutable/StringBuilder.append:(Ljava/lang/String;)Lscala/collection/mutable/StringBuilder;
	goto	l2 // areturn
l1	getstatic	Field scala/runtime/BoxedUnit.UNIT:Lscala/runtime/BoxedUnit;
l2	areturn
  Labels:
   	l1 = 126 // getstatic
   	l2 = 129 // areturn
  LocalVariableTable: 
   Start  Length  Slot  Name   Signature
   0      130      0    this       Lscala/util/automata/DetWordAutom$$anonfun$toString$1;
   6      124      1    i       I


public scala.Function1 andThen(scala.Function1);
  Signature: (Lscala/Function1;)Lscala/Function1;
  Code:
   Stack=2, Locals=2, Args_size=2
	aload_0
	aload_1
	invokestatic	Method scala/Function1$class.andThen:(Lscala/Function1;Lscala/Function1;)Lscala/Function1;
	areturn
  Labels:
  LocalVariableTable: 
   Start  Length  Slot  Name   Signature
   0      6      0    this       Lscala/util/automata/DetWordAutom$$anonfun$toString$1;
   0      6      1    g       Lscala/Function1;


public scala.Function1 compose(scala.Function1);
  Signature: (Lscala/Function1;)Lscala/Function1;
  Code:
   Stack=2, Locals=2, Args_size=2
	aload_0
	aload_1
	invokestatic	Method scala/Function1$class.compose:(Lscala/Function1;Lscala/Function1;)Lscala/Function1;
	areturn
  Labels:
  LocalVariableTable: 
   Start  Length  Slot  Name   Signature
   0      6      0    this       Lscala/util/automata/DetWordAutom$$anonfun$toString$1;
   0      6      1    g       Lscala/Function1;


public java.lang.String toString();
  Signature: ()Ljava/lang/String;
  Code:
   Stack=1, Locals=1, Args_size=1
	aload_0
	invokestatic	Method scala/Function1$class.toString:(Lscala/Function1;)Ljava/lang/String;
	areturn
  Labels:

}

