Compiled from "DetWordAutom.scala"
public abstract class scala.util.automata.DetWordAutom extends java.lang.Object implements scala.ScalaObject
  SourceFile: "DetWordAutom.scala"
  Signature: length = 0x2
   00 FFFFFFC9 
  ScalaSig: length = 0x20F
   05 00 5B 06 05 01 02 FFFFFF81 00 09 02 0C 44 65 74 57
   6F 72 64 41 75 74 6F 6D 0A 02 03 04 01 08 61 75
   74 6F 6D 61 74 61 0A 02 05 06 01 04 75 74 69 6C
   0A 01 07 01 05 73 63 61 6C 61 03 00 15 02 0A 1E
   13 03 00 0B 13 10 02 0C 11 0D 01 0D 0A 02 0E 0F
   01 04 6C 61 6E 67 0A 01 10 01 04 6A 61 76 61 09
   02 12 0D 02 06 4F 62 6A 65 63 74 10 02 14 15 0D
   01 06 09 02 16 06 02 0B 53 63 61 6C 61 4F 62 6A
   65 63 74 08 05 18 00 FFFFFF84 00 19 01 06 3C 69 6E 69
   74 3E 14 01 1A 10 03 1B 00 1C 0D 01 02 10 02 1D
   1E 0C 00 04 08 1F 00 FFFFFF84 FFFFFF80 FFFFFF80 FFFFFFC2 00 20 02 01 54
   11 02 21 24 10 02 14 22 09 02 23 06 02 07 4E 6F
   74 68 69 6E 67 10 02 14 25 09 02 26 06 02 06 41
   6E 79 52 65 66 08 07 28 00 FFFFFFC2 FFFFFF80 FFFFFF86 00 29 01 07
   6E 73 74 61 74 65 73 15 01 2A 10 02 14 2B 09 02
   2C 06 02 03 49 6E 74 08 07 2E 00 FFFFFFC2 FFFFFF80 FFFFFF86 00 2F
   01 06 66 69 6E 61 6C 73 15 01 30 10 03 14 31 2A
   09 02 32 06 02 05 41 72 72 61 79 08 07 34 00 FFFFFFC2
   FFFFFF80 FFFFFF86 00 35 01 05 64 65 6C 74 61 15 01 36 10 03
   14 31 37 10 04 38 3B 1C 2A 0D 01 39 0A 02 3A 06
   01 0A 63 6F 6C 6C 65 63 74 69 6F 6E 09 02 3C 39
   02 03 4D 61 70 08 07 3E 00 FFFFFFC2 FFFFFF80 FFFFFF86 00 2F 01 07
   64 65 66 61 75 6C 74 08 05 40 00 FFFFFF84 00 41 01 07
   69 73 46 69 6E 61 6C 14 02 42 45 10 02 14 43 09
   02 44 06 02 07 42 6F 6F 6C 65 61 6E 08 05 46 3F
   FFFFFFC0 00 2A 01 01 71 08 05 48 00 FFFFFF84 00 49 01 06 69
   73 53 69 6E 6B 14 02 42 4A 08 05 46 47 FFFFFFC0 00 2A
   08 05 4C 00 FFFFFF84 00 4D 01 04 6E 65 78 74 14 03 2A
   4E 4F 08 05 46 4B FFFFFFC0 00 2A 08 05 50 4B FFFFFFC0 00 1C
   01 05 6C 61 62 65 6C 08 05 52 00 FFFFFF84 20 53 01 08
   74 6F 53 74 72 69 6E 67 14 01 54 10 02 55 58 0E
   02 14 56 09 02 57 06 01 06 50 72 65 64 65 66 09
   02 59 5A 02 06 53 74 72 69 6E 67 0A 02 57 06 
  InnerClass: 
   public abstract ByOne=class scala/collection/immutable/Range$ByOne of class scala/collection/immutable/Range
   public final $anonfun$1=class scala/util/automata/DetWordAutom$$anonfun$1 of class scala/util/automata/DetWordAutom
   public final $anonfun$toString$1=class scala/util/automata/DetWordAutom$$anonfun$toString$1 of class scala/util/automata/DetWordAutom
  minor version: 0
  major version: 49
  Constant pool:
Asciz	SourceFile;
Asciz	DetWordAutom.scala;
Asciz	<init>;
Asciz	()V;
Asciz	Code;
Asciz	LineNumberTable;
Asciz	java/lang/Object;
class	java/lang/Object
NameAndType	"<init>":()V
Method	java/lang/Object."<init>":()V
Asciz	Signature;
Asciz	toString;
Asciz	()Ljava/lang/String;;
Asciz	scala/collection/mutable/StringBuilder;
class	scala/collection/mutable/StringBuilder
Asciz	[DetWordAutom  nstates=;
String	[DetWordAutom  nstates=
Asciz	(Ljava/lang/String;)V;
NameAndType	"<init>":(Ljava/lang/String;)V
Method	scala/collection/mutable/StringBuilder."<init>":(Ljava/lang/String;)V
Asciz	scala/util/automata/DetWordAutom;
class	scala/util/automata/DetWordAutom
Asciz	nstates;
Asciz	()I;
NameAndType	nstates:()I
Method	scala/util/automata/DetWordAutom.nstates:()I
Asciz	append;
Asciz	(I)Lscala/collection/mutable/StringBuilder;;
NameAndType	append:(I)Lscala/collection/mutable/StringBuilder;
Method	scala/collection/mutable/StringBuilder.append:(I)Lscala/collection/mutable/StringBuilder;
Asciz	 finals=;
String	 finals=
Asciz	(Ljava/lang/String;)Lscala/collection/mutable/StringBuilder;;
NameAndType	append:(Ljava/lang/String;)Lscala/collection/mutable/StringBuilder;
Method	scala/collection/mutable/StringBuilder.append:(Ljava/lang/String;)Lscala/collection/mutable/StringBuilder;
Asciz	scala/collection/Map$;
class	scala/collection/Map$
Asciz	MODULE$;
Asciz	Lscala/collection/Map$;;
NameAndType	MODULE$:Lscala/collection/Map$;
Field	scala/collection/Map$.MODULE$:Lscala/collection/Map$;
Asciz	scala/Predef$;
class	scala/Predef$
Asciz	Lscala/Predef$;;
NameAndType	MODULE$:Lscala/Predef$;
Field	scala/Predef$.MODULE$:Lscala/Predef$;
Asciz	finals;
Asciz	()[I;
NameAndType	finals:()[I
Method	scala/util/automata/DetWordAutom.finals:()[I
Asciz	intArrayOps;
Asciz	([I)Lscala/collection/mutable/ArrayOps;;
NameAndType	intArrayOps:([I)Lscala/collection/mutable/ArrayOps;
Method	scala/Predef$.intArrayOps:([I)Lscala/collection/mutable/ArrayOps;
Asciz	scala/Array$;
class	scala/Array$
Asciz	Lscala/Array$;;
NameAndType	MODULE$:Lscala/Array$;
Field	scala/Array$.MODULE$:Lscala/Array$;
Asciz	scala/reflect/ClassManifest$;
class	scala/reflect/ClassManifest$
Asciz	Lscala/reflect/ClassManifest$;;
NameAndType	MODULE$:Lscala/reflect/ClassManifest$;
Field	scala/reflect/ClassManifest$.MODULE$:Lscala/reflect/ClassManifest$;
Asciz	scala/Tuple2;
class	scala/Tuple2
Asciz	scala/reflect/Manifest$;
class	scala/reflect/Manifest$
Asciz	Lscala/reflect/Manifest$;;
NameAndType	MODULE$:Lscala/reflect/Manifest$;
Field	scala/reflect/Manifest$.MODULE$:Lscala/reflect/Manifest$;
Asciz	Int;
Asciz	()Lscala/reflect/AnyValManifest;;
NameAndType	Int:()Lscala/reflect/AnyValManifest;
Method	scala/reflect/Manifest$.Int:()Lscala/reflect/AnyValManifest;
Asciz	scala/reflect/OptManifest;
class	scala/reflect/OptManifest
Asciz	[Ljava/lang/Object;;
class	"[Ljava/lang/Object;"
Asciz	wrapRefArray;
Asciz	([Ljava/lang/Object;)Lscala/collection/mutable/WrappedArray;;
NameAndType	wrapRefArray:([Ljava/lang/Object;)Lscala/collection/mutable/WrappedArray;
Method	scala/Predef$.wrapRefArray:([Ljava/lang/Object;)Lscala/collection/mutable/WrappedArray;
Asciz	classType;
Asciz	(Ljava/lang/Class;Lscala/reflect/OptManifest;Lscala/collection/Seq;)Lscala/reflect/ClassManifest;;
NameAndType	classType:(Ljava/lang/Class;Lscala/reflect/OptManifest;Lscala/collection/Seq;)Lscala/reflect/ClassManifest;
Method	scala/reflect/ClassManifest$.classType:(Ljava/lang/Class;Lscala/reflect/OptManifest;Lscala/collection/Seq;)Lscala/reflect/ClassManifest;
Asciz	canBuildFrom;
Asciz	(Lscala/reflect/ClassManifest;)Lscala/collection/generic/CanBuildFrom;;
NameAndType	canBuildFrom:(Lscala/reflect/ClassManifest;)Lscala/collection/generic/CanBuildFrom;
Method	scala/Array$.canBuildFrom:(Lscala/reflect/ClassManifest;)Lscala/collection/generic/CanBuildFrom;
Asciz	scala/collection/IndexedSeqLike;
class	scala/collection/IndexedSeqLike
Asciz	zipWithIndex;
Asciz	(Lscala/collection/generic/CanBuildFrom;)Ljava/lang/Object;;
NameAndType	zipWithIndex:(Lscala/collection/generic/CanBuildFrom;)Ljava/lang/Object;
InterfaceMethod	scala/collection/IndexedSeqLike.zipWithIndex:(Lscala/collection/generic/CanBuildFrom;)Ljava/lang/Object;
Asciz	refArrayOps;
Asciz	([Ljava/lang/Object;)Lscala/collection/mutable/ArrayOps;;
NameAndType	refArrayOps:([Ljava/lang/Object;)Lscala/collection/mutable/ArrayOps;
Method	scala/Predef$.refArrayOps:([Ljava/lang/Object;)Lscala/collection/mutable/ArrayOps;
Asciz	scala/util/automata/DetWordAutom$$anonfun$1;
class	scala/util/automata/DetWordAutom$$anonfun$1
Asciz	(Lscala/util/automata/DetWordAutom;)V;
NameAndType	"<init>":(Lscala/util/automata/DetWordAutom;)V
Method	scala/util/automata/DetWordAutom$$anonfun$1."<init>":(Lscala/util/automata/DetWordAutom;)V
Asciz	scala/collection/TraversableLike;
class	scala/collection/TraversableLike
Asciz	map;
Asciz	(Lscala/Function1;Lscala/collection/generic/CanBuildFrom;)Ljava/lang/Object;;
NameAndType	map:(Lscala/Function1;Lscala/collection/generic/CanBuildFrom;)Ljava/lang/Object;
InterfaceMethod	scala/collection/TraversableLike.map:(Lscala/Function1;Lscala/collection/generic/CanBuildFrom;)Ljava/lang/Object;
Asciz	[Lscala/Tuple2;;
class	"[Lscala/Tuple2;"
Asciz	apply;
Asciz	(Lscala/collection/Seq;)Lscala/collection/Map;;
NameAndType	apply:(Lscala/collection/Seq;)Lscala/collection/Map;
Method	scala/collection/Map$.apply:(Lscala/collection/Seq;)Lscala/collection/Map;
Asciz	scala/collection/MapLike;
class	scala/collection/MapLike
NameAndType	toString:()Ljava/lang/String;
InterfaceMethod	scala/collection/MapLike.toString:()Ljava/lang/String;
Asciz	 delta=\n;
String	 delta=\n
Asciz	intWrapper;
Asciz	(I)Lscala/runtime/RichInt;;
NameAndType	intWrapper:(I)Lscala/runtime/RichInt;
Method	scala/Predef$.intWrapper:(I)Lscala/runtime/RichInt;
Asciz	scala/runtime/RichInt;
class	scala/runtime/RichInt
Asciz	until;
Asciz	(I)Lscala/collection/immutable/Range$ByOne;;
NameAndType	until:(I)Lscala/collection/immutable/Range$ByOne;
Method	scala/runtime/RichInt.until:(I)Lscala/collection/immutable/Range$ByOne;
Asciz	scala/util/automata/DetWordAutom$$anonfun$toString$1;
class	scala/util/automata/DetWordAutom$$anonfun$toString$1
Asciz	(Lscala/util/automata/DetWordAutom;Lscala/collection/mutable/StringBuilder;)V;
NameAndType	"<init>":(Lscala/util/automata/DetWordAutom;Lscala/collection/mutable/StringBuilder;)V
Method	scala/util/automata/DetWordAutom$$anonfun$toString$1."<init>":(Lscala/util/automata/DetWordAutom;Lscala/collection/mutable/StringBuilder;)V
Asciz	scala/collection/immutable/Range$ByOne;
class	scala/collection/immutable/Range$ByOne
Asciz	foreach;
Asciz	(Lscala/Function1;)V;
NameAndType	foreach:(Lscala/Function1;)V
InterfaceMethod	scala/collection/immutable/Range$ByOne.foreach:(Lscala/Function1;)V
Method	scala/collection/mutable/StringBuilder.toString:()Ljava/lang/String;
Asciz	this;
Asciz	Lscala/util/automata/DetWordAutom;;
Asciz	sb$1;
Asciz	Lscala/collection/mutable/StringBuilder;;
Asciz	Lscala/collection/Map;;
Asciz	LocalVariableTable;
Asciz	next;
Asciz	(ILjava/lang/Object;)I;
Asciz	delta;
Asciz	()[Lscala/collection/Map;;
NameAndType	delta:()[Lscala/collection/Map;
Method	scala/util/automata/DetWordAutom.delta:()[Lscala/collection/Map;
Asciz	get;
Asciz	(Ljava/lang/Object;)Lscala/Option;;
NameAndType	get:(Ljava/lang/Object;)Lscala/Option;
InterfaceMethod	scala/collection/MapLike.get:(Ljava/lang/Object;)Lscala/Option;
Asciz	scala/Some;
class	scala/Some
Asciz	x;
Asciz	Ljava/lang/Object;;
NameAndType	x:Ljava/lang/Object;
Field	scala/Some.x:Ljava/lang/Object;
Asciz	scala/runtime/BoxesRunTime;
class	scala/runtime/BoxesRunTime
Asciz	unboxToInt;
Asciz	(Ljava/lang/Object;)I;
NameAndType	unboxToInt:(Ljava/lang/Object;)I
Method	scala/runtime/BoxesRunTime.unboxToInt:(Ljava/lang/Object;)I
Asciz	scala/MatchError;
class	scala/MatchError
Asciz	scala/Option;
class	scala/Option
Method	scala/Option.toString:()Ljava/lang/String;
Method	scala/MatchError."<init>":(Ljava/lang/String;)V
Asciz	default;
NameAndType	default:()[I
Method	scala/util/automata/DetWordAutom.default:()[I
Asciz	q;
Asciz	I;
Asciz	label;
Asciz	temp2;
Asciz	Lscala/Some;;
Asciz	temp3;
Asciz	temp1;
Asciz	Lscala/Option;;
Asciz	(ITT;)I;
Asciz	isSink;
Asciz	(I)Z;
Asciz	isEmpty;
Asciz	()Z;
NameAndType	isEmpty:()Z
InterfaceMethod	scala/collection/MapLike.isEmpty:()Z
Asciz	isFinal;
Asciz	()[Lscala/collection/Map<TT;Ljava/lang/Integer;>;;
Asciz	<T:Ljava/lang/Object;>Ljava/lang/Object;Lscala/ScalaObject;;
Asciz	ScalaSig;
Asciz	InnerClasses;
Asciz	scala/collection/immutable/Range;
class	scala/collection/immutable/Range
Asciz	ByOne;
Asciz	$anonfun$1;
Asciz	$anonfun$toString$1;
Asciz	scala/ScalaObject;
class	scala/ScalaObject

{
public scala.util.automata.DetWordAutom();
  Signature: ()V
  Code:
   Stack=1, Locals=1, Args_size=1
	aload_0
	invokespecial	Method java/lang/Object."<init>":()V
	return
  Labels:
  Signature: length = 0x2
   00 04 

public java.lang.String toString();
  Signature: ()Ljava/lang/String;
  Code:
   Stack=13, Locals=3, Args_size=1
	new	class scala/collection/mutable/StringBuilder
	dup
	ldc	String [DetWordAutom  nstates=
	invokespecial	Method scala/collection/mutable/StringBuilder."<init>":(Ljava/lang/String;)V
	astore_1
	aload_1
	aload_0
	invokevirtual	Method nstates:()I
	invokevirtual	Method scala/collection/mutable/StringBuilder.append:(I)Lscala/collection/mutable/StringBuilder;
	pop
	aload_1
	ldc	String  finals=
	invokevirtual	Method scala/collection/mutable/StringBuilder.append:(Ljava/lang/String;)Lscala/collection/mutable/StringBuilder;
	pop
	getstatic	Field scala/collection/Map$.MODULE$:Lscala/collection/Map$;
	getstatic	Field scala/Predef$.MODULE$:Lscala/Predef$;
	getstatic	Field scala/Predef$.MODULE$:Lscala/Predef$;
	getstatic	Field scala/Predef$.MODULE$:Lscala/Predef$;
	aload_0
	invokevirtual	Method finals:()[I
	invokevirtual	Method scala/Predef$.intArrayOps:([I)Lscala/collection/mutable/ArrayOps;
	getstatic	Field scala/Array$.MODULE$:Lscala/Array$;
	getstatic	Field scala/reflect/ClassManifest$.MODULE$:Lscala/reflect/ClassManifest$;
	ldc	class scala/Tuple2
	getstatic	Field scala/reflect/Manifest$.MODULE$:Lscala/reflect/Manifest$;
	invokevirtual	Method scala/reflect/Manifest$.Int:()Lscala/reflect/AnyValManifest;
	getstatic	Field scala/Predef$.MODULE$:Lscala/Predef$;
	iconst_1
	anewarray	class scala/reflect/OptManifest
	dup
	iconst_0
	getstatic	Field scala/reflect/Manifest$.MODULE$:Lscala/reflect/Manifest$;
	invokevirtual	Method scala/reflect/Manifest$.Int:()Lscala/reflect/AnyValManifest;
	aastore
	checkcast	class "[Ljava/lang/Object;"
	invokevirtual	Method scala/Predef$.wrapRefArray:([Ljava/lang/Object;)Lscala/collection/mutable/WrappedArray;
	invokevirtual	Method scala/reflect/ClassManifest$.classType:(Ljava/lang/Class;Lscala/reflect/OptManifest;Lscala/collection/Seq;)Lscala/reflect/ClassManifest;
	invokevirtual	Method scala/Array$.canBuildFrom:(Lscala/reflect/ClassManifest;)Lscala/collection/generic/CanBuildFrom;
	invokeinterface	InterfaceMethod scala/collection/IndexedSeqLike.zipWithIndex:(Lscala/collection/generic/CanBuildFrom;)Ljava/lang/Object;
	checkcast	class "[Ljava/lang/Object;"
	invokevirtual	Method scala/Predef$.refArrayOps:([Ljava/lang/Object;)Lscala/collection/mutable/ArrayOps;
	new	class scala/util/automata/DetWordAutom$$anonfun$1
	dup
	aload_0
	invokespecial	Method scala/util/automata/DetWordAutom$$anonfun$1."<init>":(Lscala/util/automata/DetWordAutom;)V
	getstatic	Field scala/Array$.MODULE$:Lscala/Array$;
	getstatic	Field scala/reflect/ClassManifest$.MODULE$:Lscala/reflect/ClassManifest$;
	ldc	class scala/Tuple2
	getstatic	Field scala/reflect/Manifest$.MODULE$:Lscala/reflect/Manifest$;
	invokevirtual	Method scala/reflect/Manifest$.Int:()Lscala/reflect/AnyValManifest;
	getstatic	Field scala/Predef$.MODULE$:Lscala/Predef$;
	iconst_1
	anewarray	class scala/reflect/OptManifest
	dup
	iconst_0
	getstatic	Field scala/reflect/Manifest$.MODULE$:Lscala/reflect/Manifest$;
	invokevirtual	Method scala/reflect/Manifest$.Int:()Lscala/reflect/AnyValManifest;
	aastore
	checkcast	class "[Ljava/lang/Object;"
	invokevirtual	Method scala/Predef$.wrapRefArray:([Ljava/lang/Object;)Lscala/collection/mutable/WrappedArray;
	invokevirtual	Method scala/reflect/ClassManifest$.classType:(Ljava/lang/Class;Lscala/reflect/OptManifest;Lscala/collection/Seq;)Lscala/reflect/ClassManifest;
	invokevirtual	Method scala/Array$.canBuildFrom:(Lscala/reflect/ClassManifest;)Lscala/collection/generic/CanBuildFrom;
	invokeinterface	InterfaceMethod scala/collection/TraversableLike.map:(Lscala/Function1;Lscala/collection/generic/CanBuildFrom;)Ljava/lang/Object;
	checkcast	class "[Lscala/Tuple2;"
	checkcast	class "[Ljava/lang/Object;"
	invokevirtual	Method scala/Predef$.wrapRefArray:([Ljava/lang/Object;)Lscala/collection/mutable/WrappedArray;
	invokevirtual	Method scala/collection/Map$.apply:(Lscala/collection/Seq;)Lscala/collection/Map;
	astore_2
	aload_1
	aload_2
	invokeinterface	InterfaceMethod scala/collection/MapLike.toString:()Ljava/lang/String;
	invokevirtual	Method scala/collection/mutable/StringBuilder.append:(Ljava/lang/String;)Lscala/collection/mutable/StringBuilder;
	pop
	aload_1
	ldc	String  delta=\n
	invokevirtual	Method scala/collection/mutable/StringBuilder.append:(Ljava/lang/String;)Lscala/collection/mutable/StringBuilder;
	pop
	getstatic	Field scala/Predef$.MODULE$:Lscala/Predef$;
	iconst_0
	invokevirtual	Method scala/Predef$.intWrapper:(I)Lscala/runtime/RichInt;
	aload_0
	invokevirtual	Method nstates:()I
	invokevirtual	Method scala/runtime/RichInt.until:(I)Lscala/collection/immutable/Range$ByOne;
	new	class scala/util/automata/DetWordAutom$$anonfun$toString$1
	dup
	aload_0
	aload_1
	invokespecial	Method scala/util/automata/DetWordAutom$$anonfun$toString$1."<init>":(Lscala/util/automata/DetWordAutom;Lscala/collection/mutable/StringBuilder;)V
	invokeinterface	InterfaceMethod scala/collection/immutable/Range$ByOne.foreach:(Lscala/Function1;)V
	aload_1
	invokevirtual	Method scala/collection/mutable/StringBuilder.toString:()Ljava/lang/String;
	areturn
  Labels:
  LocalVariableTable: 
   Start  Length  Slot  Name   Signature
   0      217      0    this       Lscala/util/automata/DetWordAutom;
   10      206      1    sb$1       Lscala/collection/mutable/StringBuilder;
   166      50      2    map       Lscala/collection/Map;


public int next(int, java.lang.Object);
  Signature: (ILjava/lang/Object;)I
  Code:
   Stack=3, Locals=6, Args_size=3
	aload_0
	invokevirtual	Method delta:()[Lscala/collection/Map;
	iload_1
	aaload
	aload_2
	invokeinterface	InterfaceMethod scala/collection/MapLike.get:(Ljava/lang/Object;)Lscala/Option;
	astore	5
	aload	5
	instanceof	class scala/Some
	ifeq	l1 // iconst_1
	aload	5
	checkcast	class scala/Some
	astore_3
	aload_3
	getfield	Field scala/Some.x:Ljava/lang/Object;
	invokestatic	Method scala/runtime/BoxesRunTime.unboxToInt:(Ljava/lang/Object;)I
	istore	4
	iconst_1
	ifeq	l2 // new
	iload	4
	goto	l3 // ireturn
l2	new	class scala/MatchError
	dup
	aload	5
	invokevirtual	Method scala/Option.toString:()Ljava/lang/String;
	invokespecial	Method scala/MatchError."<init>":(Ljava/lang/String;)V
	athrow
l1	iconst_1
	ifeq	l4 // new
	aload_0
	invokevirtual	Method default:()[I
	iload_1
	iaload
l3	ireturn
l4	new	class scala/MatchError
	dup
	aload	5
	invokevirtual	Method scala/Option.toString:()Ljava/lang/String;
	invokespecial	Method scala/MatchError."<init>":(Ljava/lang/String;)V
	athrow
  Labels:
   	l2 = 46 // new
   	l1 = 59 // iconst_1
   	l3 = 69 // ireturn
   	l4 = 70 // new
  LocalVariableTable: 
   Start  Length  Slot  Name   Signature
   0      83      0    this       Lscala/util/automata/DetWordAutom;
   0      83      1    q       I
   0      83      2    label       Ljava/lang/Object;
   28      31      3    temp2       Lscala/Some;
   37      22      4    temp3       I
   14      69      5    temp1       Lscala/Option;

  Signature: length = 0x2
   00 FFFFFFC0 

public boolean isSink(int);
  Signature: (I)Z
  Code:
   Stack=2, Locals=2, Args_size=2
	aload_0
	invokevirtual	Method delta:()[Lscala/collection/Map;
	iload_1
	aaload
	invokeinterface	InterfaceMethod scala/collection/MapLike.isEmpty:()Z
	ifeq	l1 // iconst_0
	aload_0
	invokevirtual	Method default:()[I
	iload_1
	iaload
	iload_1
	if_icmpne	l1 // iconst_0
	iconst_1
	goto	l2 // ireturn
l1	iconst_0
l2	ireturn
  Labels:
   	l1 = 28 // iconst_0
   	l2 = 29 // ireturn
  LocalVariableTable: 
   Start  Length  Slot  Name   Signature
   0      30      0    this       Lscala/util/automata/DetWordAutom;
   0      30      1    q       I


public boolean isFinal(int);
  Signature: (I)Z
  Code:
   Stack=2, Locals=2, Args_size=2
	aload_0
	invokevirtual	Method finals:()[I
	iload_1
	iaload
	iconst_0
	if_icmpeq	l1 // iconst_0
	iconst_1
	goto	l2 // ireturn
l1	iconst_0
l2	ireturn
  Labels:
   	l1 = 14 // iconst_0
   	l2 = 15 // ireturn
  LocalVariableTable: 
   Start  Length  Slot  Name   Signature
   0      16      0    this       Lscala/util/automata/DetWordAutom;
   0      16      1    q       I


public abstract int[] default();
  Signature: ()[I

public abstract scala.collection.Map[] delta();
  Signature: ()[Lscala/collection/Map;
  Signature: length = 0x2
   00 FFFFFFC8 

public abstract int[] finals();
  Signature: ()[I

public abstract int nstates();
  Signature: ()I

}

