Compiled from "Inclusion.scala"
public abstract class scala.util.automata.Inclusion$class extends java.lang.Object
  SourceFile: "Inclusion.scala"
  Scala: length = 0x
   
  InnerClass: 
   public final $anonfun$inclusion$1=class scala/util/automata/Inclusion$$anonfun$inclusion$1 of class scala/util/automata/Inclusion
  minor version: 0
  major version: 49
  Constant pool:
Asciz	SourceFile;
Asciz	Inclusion.scala;
Asciz	$init$;
Asciz	(Lscala/util/automata/Inclusion;)V;
Asciz	Code;
Asciz	LineNumberTable;
Asciz	$this;
Asciz	Lscala/util/automata/Inclusion;;
Asciz	LocalVariableTable;
Asciz	decode1$1;
Asciz	(Lscala/util/automata/Inclusion;ILscala/util/automata/DetWordAutom;)I;
Asciz	scala/util/automata/DetWordAutom;
class	scala/util/automata/DetWordAutom
Asciz	nstates;
Asciz	()I;
NameAndType	nstates:()I
Method	scala/util/automata/DetWordAutom.nstates:()I
Asciz	c;
Asciz	I;
Asciz	decode2$1;
Asciz	encode$1;
Asciz	(Lscala/util/automata/Inclusion;IILscala/util/automata/DetWordAutom;)I;
Asciz	q1;
Asciz	q2;
Asciz	inclusion;
Asciz	(Lscala/util/automata/Inclusion;Lscala/util/automata/DetWordAutom;Lscala/util/automata/DetWordAutom;)Z;
Asciz	scala/runtime/IntRef;
class	scala/runtime/IntRef
Asciz	<init>;
Asciz	(I)V;
NameAndType	"<init>":(I)V
Method	scala/runtime/IntRef."<init>":(I)V
Asciz	scala/runtime/BooleanRef;
class	scala/runtime/BooleanRef
Asciz	(Z)V;
NameAndType	"<init>":(Z)V
Method	scala/runtime/BooleanRef."<init>":(Z)V
Asciz	elem;
NameAndType	elem:I
Field	scala/runtime/IntRef.elem:I
Asciz	scala/util/automata/Inclusion$class;
class	scala/util/automata/Inclusion$class
NameAndType	encode$1:(Lscala/util/automata/Inclusion;IILscala/util/automata/DetWordAutom;)I
Method	scala/util/automata/Inclusion$class.encode$1:(Lscala/util/automata/Inclusion;IILscala/util/automata/DetWordAutom;)I
Asciz	Z;
NameAndType	elem:Z
Field	scala/runtime/BooleanRef.elem:Z
Asciz	scala/util/automata/Inclusion;
class	scala/util/automata/Inclusion
Asciz	labels;
Asciz	()Lscala/collection/Seq;;
NameAndType	labels:()Lscala/collection/Seq;
InterfaceMethod	scala/util/automata/Inclusion.labels:()Lscala/collection/Seq;
Asciz	scala/util/automata/Inclusion$$anonfun$inclusion$1;
class	scala/util/automata/Inclusion$$anonfun$inclusion$1
Asciz	(Lscala/util/automata/Inclusion;Lscala/util/automata/DetWordAutom;Lscala/util/automata/DetWordAutom;Lscala/runtime/IntRef;Lscala/runtime/IntRef;I[ILscala/runtime/BooleanRef;Lscala/runtime/IntRef;)V;
NameAndType	"<init>":(Lscala/util/automata/Inclusion;Lscala/util/automata/DetWordAutom;Lscala/util/automata/DetWordAutom;Lscala/runtime/IntRef;Lscala/runtime/IntRef;I[ILscala/runtime/BooleanRef;Lscala/runtime/IntRef;)V
Method	scala/util/automata/Inclusion$$anonfun$inclusion$1."<init>":(Lscala/util/automata/Inclusion;Lscala/util/automata/DetWordAutom;Lscala/util/automata/DetWordAutom;Lscala/runtime/IntRef;Lscala/runtime/IntRef;I[ILscala/runtime/BooleanRef;Lscala/runtime/IntRef;)V
Asciz	scala/collection/IterableLike;
class	scala/collection/IterableLike
Asciz	foreach;
Asciz	(Lscala/Function1;)V;
NameAndType	foreach:(Lscala/Function1;)V
InterfaceMethod	scala/collection/IterableLike.foreach:(Lscala/Function1;)V
NameAndType	decode1$1:(Lscala/util/automata/Inclusion;ILscala/util/automata/DetWordAutom;)I
Method	scala/util/automata/Inclusion$class.decode1$1:(Lscala/util/automata/Inclusion;ILscala/util/automata/DetWordAutom;)I
NameAndType	decode2$1:(Lscala/util/automata/Inclusion;ILscala/util/automata/DetWordAutom;)I
Method	scala/util/automata/Inclusion$class.decode2$1:(Lscala/util/automata/Inclusion;ILscala/util/automata/DetWordAutom;)I
Asciz	dfa1$1;
Asciz	Lscala/util/automata/DetWordAutom;;
Asciz	dfa2$1;
Asciz	q1$1;
Asciz	Lscala/runtime/IntRef;;
Asciz	q2$1;
Asciz	max$1;
Asciz	mark$1;
Asciz	[I;
Asciz	result$1;
Asciz	Lscala/runtime/BooleanRef;;
Asciz	current;
Asciz	last$1;
Asciz	ncurrent;
Asciz	Scala;
Asciz	InnerClasses;
Asciz	$anonfun$inclusion$1;
Asciz	java/lang/Object;
class	java/lang/Object

{
public static void $init$(scala.util.automata.Inclusion);
  Signature: (Lscala/util/automata/Inclusion;)V
  Code:
   Stack=0, Locals=1, Args_size=1
	return
  Labels:
  LocalVariableTable: 
   Start  Length  Slot  Name   Signature
   0      1      0    $this       Lscala/util/automata/Inclusion;


private static final int decode1$1(scala.util.automata.Inclusion, int, scala.util.automata.DetWordAutom);
  Signature: (Lscala/util/automata/Inclusion;ILscala/util/automata/DetWordAutom;)I
  Code:
   Stack=2, Locals=3, Args_size=3
	iload_1
	iconst_1
	isub
	aload_2
	invokevirtual	Method scala/util/automata/DetWordAutom.nstates:()I
	irem
	ireturn
  Labels:
  LocalVariableTable: 
   Start  Length  Slot  Name   Signature
   0      9      0    $this       Lscala/util/automata/Inclusion;
   0      9      1    c       I


private static final int decode2$1(scala.util.automata.Inclusion, int, scala.util.automata.DetWordAutom);
  Signature: (Lscala/util/automata/Inclusion;ILscala/util/automata/DetWordAutom;)I
  Code:
   Stack=2, Locals=3, Args_size=3
	iload_1
	iconst_1
	isub
	aload_2
	invokevirtual	Method scala/util/automata/DetWordAutom.nstates:()I
	idiv
	ireturn
  Labels:
  LocalVariableTable: 
   Start  Length  Slot  Name   Signature
   0      9      0    $this       Lscala/util/automata/Inclusion;
   0      9      1    c       I


public static final int encode$1(scala.util.automata.Inclusion, int, int, scala.util.automata.DetWordAutom);
  Signature: (Lscala/util/automata/Inclusion;IILscala/util/automata/DetWordAutom;)I
  Code:
   Stack=3, Locals=4, Args_size=4
	iconst_1
	iload_1
	iadd
	iload_2
	aload_3
	invokevirtual	Method scala/util/automata/DetWordAutom.nstates:()I
	imul
	iadd
	ireturn
  Labels:
  LocalVariableTable: 
   Start  Length  Slot  Name   Signature
   0      11      0    $this       Lscala/util/automata/Inclusion;
   0      11      1    q1       I
   0      11      2    q2       I


public static boolean inclusion(scala.util.automata.Inclusion, scala.util.automata.DetWordAutom, scala.util.automata.DetWordAutom);
  Signature: (Lscala/util/automata/Inclusion;Lscala/util/automata/DetWordAutom;Lscala/util/automata/DetWordAutom;)Z
  Code:
   Stack=12, Locals=11, Args_size=3
	new	class scala/runtime/IntRef
	dup
	iconst_0
	invokespecial	Method scala/runtime/IntRef."<init>":(I)V
	astore_3
	new	class scala/runtime/IntRef
	dup
	iconst_0
	invokespecial	Method scala/runtime/IntRef."<init>":(I)V
	astore	4
	iconst_1
	aload_1
	invokevirtual	Method scala/util/automata/DetWordAutom.nstates:()I
	aload_2
	invokevirtual	Method scala/util/automata/DetWordAutom.nstates:()I
	imul
	iadd
	istore	5
	iload	5
	newarray int
	astore	6
	new	class scala/runtime/BooleanRef
	dup
	iconst_1
	invokespecial	Method scala/runtime/BooleanRef."<init>":(Z)V
	astore	7
	aload_0
	aload_3
	getfield	Field scala/runtime/IntRef.elem:I
	aload	4
	getfield	Field scala/runtime/IntRef.elem:I
	aload_1
	invokestatic	Method encode$1:(Lscala/util/automata/Inclusion;IILscala/util/automata/DetWordAutom;)I
	istore	8
	new	class scala/runtime/IntRef
	dup
	iload	8
	invokespecial	Method scala/runtime/IntRef."<init>":(I)V
	astore	9
	aload	6
	aload	9
	getfield	Field scala/runtime/IntRef.elem:I
	iload	5
	iastore
l3	iload	8
	iconst_0
	if_icmpeq	l1 // aload
	aload	7
	getfield	Field scala/runtime/BooleanRef.elem:Z
	ifeq	l1 // aload
	aload_0
	invokeinterface	InterfaceMethod scala/util/automata/Inclusion.labels:()Lscala/collection/Seq;
	new	class scala/util/automata/Inclusion$$anonfun$inclusion$1
	dup
	aload_0
	aload_1
	aload_2
	aload_3
	aload	4
	iload	5
	aload	6
	aload	7
	aload	9
	invokespecial	Method scala/util/automata/Inclusion$$anonfun$inclusion$1."<init>":(Lscala/util/automata/Inclusion;Lscala/util/automata/DetWordAutom;Lscala/util/automata/DetWordAutom;Lscala/runtime/IntRef;Lscala/runtime/IntRef;I[ILscala/runtime/BooleanRef;Lscala/runtime/IntRef;)V
	invokeinterface	InterfaceMethod scala/collection/IterableLike.foreach:(Lscala/Function1;)V
	aload	6
	iload	8
	iaload
	istore	10
	iload	10
	iload	5
	if_icmpeq	l2 // iconst_0
	aload_3
	aload_0
	iload	10
	aload_1
	invokestatic	Method decode1$1:(Lscala/util/automata/Inclusion;ILscala/util/automata/DetWordAutom;)I
	putfield	Field scala/runtime/IntRef.elem:I
	aload	4
	aload_0
	iload	10
	aload_1
	invokestatic	Method decode2$1:(Lscala/util/automata/Inclusion;ILscala/util/automata/DetWordAutom;)I
	putfield	Field scala/runtime/IntRef.elem:I
	iload	10
	istore	8
	goto	l3 // iload
l2	iconst_0
	istore	8
	goto	l3 // iload
l1	aload	7
	getfield	Field scala/runtime/BooleanRef.elem:Z
	ireturn
  Labels:
   	l3 = 85 // iload
   	l2 = 175 // iconst_0
   	l1 = 181 // aload
  LocalVariableTable: 
   Start  Length  Slot  Name   Signature
   0      187      0    $this       Lscala/util/automata/Inclusion;
   0      187      1    dfa1$1       Lscala/util/automata/DetWordAutom;
   0      187      2    dfa2$1       Lscala/util/automata/DetWordAutom;
   9      177      3    q1$1       Lscala/runtime/IntRef;
   19      167      4    q2$1       Lscala/runtime/IntRef;
   32      154      5    max$1       I
   38      148      6    mark$1       [I
   48      138      7    result$1       Lscala/runtime/BooleanRef;
   64      122      8    current       I
   75      111      9    last$1       Lscala/runtime/IntRef;
   138      43      10    ncurrent       I


}

