Compiled from "Inclusion.scala"
public final class scala.util.automata.Inclusion$$anonfun$inclusion$1 extends java.lang.Object implements scala.Function1,scala.ScalaObject,java.io.Serializable
  SourceFile: "Inclusion.scala"
  Scala: length = 0x
   
  InnerClass: 
   public final #129= #9 of #128; //$anonfun$inclusion$1=class scala/util/automata/Inclusion$$anonfun$inclusion$1 of class scala/util/automata/Inclusion
  minor version: 0
  major version: 49
  Constant pool:
const #1 = Asciz	SourceFile;
const #2 = Asciz	Inclusion.scala;
const #3 = Asciz	<clinit>;
const #4 = Asciz	()V;
const #5 = Asciz	Code;
const #6 = Asciz	serialVersionUID;
const #7 = Asciz	J;
const #8 = Asciz	scala/util/automata/Inclusion$$anonfun$inclusion$1;
const #9 = class	#8;	//  scala/util/automata/Inclusion$$anonfun$inclusion$1
const #10 = NameAndType	#6:#7;//  serialVersionUID:J
const #11 = Field	#9.#10;	//  scala/util/automata/Inclusion$$anonfun$inclusion$1.serialVersionUID:J
const #12 = Asciz	last$1;
const #13 = Asciz	Lscala/runtime/IntRef;;
const #14 = Asciz	result$1;
const #15 = Asciz	Lscala/runtime/BooleanRef;;
const #16 = Asciz	mark$1;
const #17 = Asciz	[I;
const #18 = Asciz	max$1;
const #19 = Asciz	I;
const #20 = Asciz	q2$1;
const #21 = Asciz	q1$1;
const #22 = Asciz	dfa2$1;
const #23 = Asciz	Lscala/util/automata/DetWordAutom;;
const #24 = Asciz	dfa1$1;
const #25 = Asciz	$outer;
const #26 = Asciz	Lscala/util/automata/Inclusion;;
const #27 = Asciz	<init>;
const #28 = Asciz	(Lscala/util/automata/Inclusion;Lscala/util/automata/DetWordAutom;Lscala/util/automata/DetWordAutom;Lscala/runtime/IntRef;Lscala/runtime/IntRef;I[ILscala/runtime/BooleanRef;Lscala/runtime/IntRef;)V;
const #29 = Asciz	LineNumberTable;
const #30 = Asciz	java/lang/NullPointerException;
const #31 = class	#30;	//  java/lang/NullPointerException
const #32 = NameAndType	#27:#4;//  "<init>":()V
const #33 = Method	#31.#32;	//  java/lang/NullPointerException."<init>":()V
const #34 = NameAndType	#25:#26;//  $outer:Lscala/util/automata/Inclusion;
const #35 = Field	#9.#34;	//  scala/util/automata/Inclusion$$anonfun$inclusion$1.$outer:Lscala/util/automata/Inclusion;
const #36 = NameAndType	#24:#23;//  dfa1$1:Lscala/util/automata/DetWordAutom;
const #37 = Field	#9.#36;	//  scala/util/automata/Inclusion$$anonfun$inclusion$1.dfa1$1:Lscala/util/automata/DetWordAutom;
const #38 = NameAndType	#22:#23;//  dfa2$1:Lscala/util/automata/DetWordAutom;
const #39 = Field	#9.#38;	//  scala/util/automata/Inclusion$$anonfun$inclusion$1.dfa2$1:Lscala/util/automata/DetWordAutom;
const #40 = NameAndType	#21:#13;//  q1$1:Lscala/runtime/IntRef;
const #41 = Field	#9.#40;	//  scala/util/automata/Inclusion$$anonfun$inclusion$1.q1$1:Lscala/runtime/IntRef;
const #42 = NameAndType	#20:#13;//  q2$1:Lscala/runtime/IntRef;
const #43 = Field	#9.#42;	//  scala/util/automata/Inclusion$$anonfun$inclusion$1.q2$1:Lscala/runtime/IntRef;
const #44 = NameAndType	#18:#19;//  max$1:I
const #45 = Field	#9.#44;	//  scala/util/automata/Inclusion$$anonfun$inclusion$1.max$1:I
const #46 = NameAndType	#16:#17;//  mark$1:[I
const #47 = Field	#9.#46;	//  scala/util/automata/Inclusion$$anonfun$inclusion$1.mark$1:[I
const #48 = NameAndType	#14:#15;//  result$1:Lscala/runtime/BooleanRef;
const #49 = Field	#9.#48;	//  scala/util/automata/Inclusion$$anonfun$inclusion$1.result$1:Lscala/runtime/BooleanRef;
const #50 = NameAndType	#12:#13;//  last$1:Lscala/runtime/IntRef;
const #51 = Field	#9.#50;	//  scala/util/automata/Inclusion$$anonfun$inclusion$1.last$1:Lscala/runtime/IntRef;
const #52 = Asciz	java/lang/Object;
const #53 = class	#52;	//  java/lang/Object
const #54 = Method	#53.#32;	//  java/lang/Object."<init>":()V
const #55 = Asciz	scala/Function1$class;
const #56 = class	#55;	//  scala/Function1$class
const #57 = Asciz	$init$;
const #58 = Asciz	(Lscala/Function1;)V;
const #59 = NameAndType	#57:#58;//  $init$:(Lscala/Function1;)V
const #60 = Method	#56.#59;	//  scala/Function1$class.$init$:(Lscala/Function1;)V
const #61 = Asciz	this;
const #62 = Asciz	Lscala/util/automata/Inclusion$$anonfun$inclusion$1;;
const #63 = Asciz	LocalVariableTable;
const #64 = Asciz	(Lscala/util/automata/Inclusion<TA;>;)V;
const #65 = Asciz	Signature;
const #66 = Asciz	apply;
const #67 = Asciz	(Ljava/lang/Object;)Ljava/lang/Object;;
const #68 = Asciz	(Ljava/lang/Object;)V;
const #69 = NameAndType	#66:#68;//  apply:(Ljava/lang/Object;)V
const #70 = Method	#9.#69;	//  scala/util/automata/Inclusion$$anonfun$inclusion$1.apply:(Ljava/lang/Object;)V
const #71 = Asciz	scala/runtime/BoxedUnit;
const #72 = class	#71;	//  scala/runtime/BoxedUnit
const #73 = Asciz	UNIT;
const #74 = Asciz	Lscala/runtime/BoxedUnit;;
const #75 = NameAndType	#73:#74;//  UNIT:Lscala/runtime/BoxedUnit;
const #76 = Field	#72.#75;	//  scala/runtime/BoxedUnit.UNIT:Lscala/runtime/BoxedUnit;
const #77 = Asciz	v1;
const #78 = Asciz	Ljava/lang/Object;;
const #79 = Asciz	scala/runtime/IntRef;
const #80 = class	#79;	//  scala/runtime/IntRef
const #81 = Asciz	elem;
const #82 = NameAndType	#81:#19;//  elem:I
const #83 = Field	#80.#82;	//  scala/runtime/IntRef.elem:I
const #84 = Asciz	scala/util/automata/DetWordAutom;
const #85 = class	#84;	//  scala/util/automata/DetWordAutom
const #86 = Asciz	next;
const #87 = Asciz	(ILjava/lang/Object;)I;
const #88 = NameAndType	#86:#87;//  next:(ILjava/lang/Object;)I
const #89 = Method	#85.#88;	//  scala/util/automata/DetWordAutom.next:(ILjava/lang/Object;)I
const #90 = Asciz	isFinal;
const #91 = Asciz	(I)Z;
const #92 = NameAndType	#90:#91;//  isFinal:(I)Z
const #93 = Method	#85.#92;	//  scala/util/automata/DetWordAutom.isFinal:(I)Z
const #94 = Asciz	scala/runtime/BooleanRef;
const #95 = class	#94;	//  scala/runtime/BooleanRef
const #96 = Asciz	Z;
const #97 = NameAndType	#81:#96;//  elem:Z
const #98 = Field	#95.#97;	//  scala/runtime/BooleanRef.elem:Z
const #99 = Asciz	scala/util/automata/Inclusion$class;
const #100 = class	#99;	//  scala/util/automata/Inclusion$class
const #101 = Asciz	encode$1;
const #102 = Asciz	(Lscala/util/automata/Inclusion;IILscala/util/automata/DetWordAutom;)I;
const #103 = NameAndType	#101:#102;//  encode$1:(Lscala/util/automata/Inclusion;IILscala/util/automata/DetWordAutom;)I
const #104 = Method	#100.#103;	//  scala/util/automata/Inclusion$class.encode$1:(Lscala/util/automata/Inclusion;IILscala/util/automata/DetWordAutom;)I
const #105 = Asciz	letter;
const #106 = Asciz	r1;
const #107 = Asciz	r2;
const #108 = Asciz	test;
const #109 = Asciz	(TA;)V;
const #110 = Asciz	andThen;
const #111 = Asciz	(Lscala/Function1;)Lscala/Function1;;
const #112 = Asciz	(Lscala/Function1;Lscala/Function1;)Lscala/Function1;;
const #113 = NameAndType	#110:#112;//  andThen:(Lscala/Function1;Lscala/Function1;)Lscala/Function1;
const #114 = Method	#56.#113;	//  scala/Function1$class.andThen:(Lscala/Function1;Lscala/Function1;)Lscala/Function1;
const #115 = Asciz	g;
const #116 = Asciz	Lscala/Function1;;
const #117 = Asciz	compose;
const #118 = NameAndType	#117:#112;//  compose:(Lscala/Function1;Lscala/Function1;)Lscala/Function1;
const #119 = Method	#56.#118;	//  scala/Function1$class.compose:(Lscala/Function1;Lscala/Function1;)Lscala/Function1;
const #120 = Asciz	toString;
const #121 = Asciz	()Ljava/lang/String;;
const #122 = Asciz	(Lscala/Function1;)Ljava/lang/String;;
const #123 = NameAndType	#120:#122;//  toString:(Lscala/Function1;)Ljava/lang/String;
const #124 = Method	#56.#123;	//  scala/Function1$class.toString:(Lscala/Function1;)Ljava/lang/String;
const #125 = Asciz	Scala;
const #126 = Asciz	InnerClasses;
const #127 = Asciz	scala/util/automata/Inclusion;
const #128 = class	#127;	//  scala/util/automata/Inclusion
const #129 = Asciz	$anonfun$inclusion$1;
const #130 = Asciz	scala/Function1;
const #131 = class	#130;	//  scala/Function1
const #132 = Asciz	scala/ScalaObject;
const #133 = class	#132;	//  scala/ScalaObject
const #134 = Asciz	java/io/Serializable;
const #135 = class	#134;	//  java/io/Serializable

{
public static final long serialVersionUID;

public static {};
  Code:
   Stack=2, Locals=0, Args_size=0
   0:	lconst_0
   1:	putstatic	#11; //Field serialVersionUID:J
   4:	return

public scala.util.automata.Inclusion$$anonfun$inclusion$1(scala.util.automata.Inclusion, scala.util.automata.DetWordAutom, scala.util.automata.DetWordAutom, scala.runtime.IntRef, scala.runtime.IntRef, int, int[], scala.runtime.BooleanRef, scala.runtime.IntRef);
  Code:
   Stack=2, Locals=10, Args_size=10
   0:	aload_1
   1:	ifnonnull	12
   4:	new	#31; //class java/lang/NullPointerException
   7:	dup
   8:	invokespecial	#33; //Method java/lang/NullPointerException."<init>":()V
   11:	athrow
   12:	aload_0
   13:	aload_1
   14:	putfield	#35; //Field $outer:Lscala/util/automata/Inclusion;
   17:	aload_0
   18:	aload_2
   19:	putfield	#37; //Field dfa1$1:Lscala/util/automata/DetWordAutom;
   22:	aload_0
   23:	aload_3
   24:	putfield	#39; //Field dfa2$1:Lscala/util/automata/DetWordAutom;
   27:	aload_0
   28:	aload	4
   30:	putfield	#41; //Field q1$1:Lscala/runtime/IntRef;
   33:	aload_0
   34:	aload	5
   36:	putfield	#43; //Field q2$1:Lscala/runtime/IntRef;
   39:	aload_0
   40:	iload	6
   42:	putfield	#45; //Field max$1:I
   45:	aload_0
   46:	aload	7
   48:	putfield	#47; //Field mark$1:[I
   51:	aload_0
   52:	aload	8
   54:	putfield	#49; //Field result$1:Lscala/runtime/BooleanRef;
   57:	aload_0
   58:	aload	9
   60:	putfield	#51; //Field last$1:Lscala/runtime/IntRef;
   63:	aload_0
   64:	invokespecial	#54; //Method java/lang/Object."<init>":()V
   67:	aload_0
   68:	invokestatic	#60; //Method scala/Function1$class.$init$:(Lscala/Function1;)V
   71:	return
  LineNumberTable: 
   line 48: 0

  LocalVariableTable: 
   Start  Length  Slot  Name   Signature
   0      72      0    this       Lscala/util/automata/Inclusion$$anonfun$inclusion$1;
   0      72      1    $outer       Lscala/util/automata/Inclusion;

  Signature: length = 0x2
   00 40 

public final java.lang.Object apply(java.lang.Object);
  Code:
   Stack=2, Locals=3, Args_size=2
   0:	aload_0
   1:	getfield	#35; //Field $outer:Lscala/util/automata/Inclusion;
   4:	astore_2
   5:	aload_0
   6:	aload_1
   7:	invokevirtual	#70; //Method apply:(Ljava/lang/Object;)V
   10:	getstatic	#76; //Field scala/runtime/BoxedUnit.UNIT:Lscala/runtime/BoxedUnit;
   13:	areturn
  LineNumberTable: 
   line 48: 0

  LocalVariableTable: 
   Start  Length  Slot  Name   Signature
   0      14      0    this       Lscala/util/automata/Inclusion$$anonfun$inclusion$1;
   5      9      1    v1       Ljava/lang/Object;


public final void apply(java.lang.Object);
  Code:
   Stack=4, Locals=6, Args_size=2
   0:	aload_0
   1:	getfield	#35; //Field $outer:Lscala/util/automata/Inclusion;
   4:	astore	5
   6:	aload_0
   7:	getfield	#37; //Field dfa1$1:Lscala/util/automata/DetWordAutom;
   10:	aload_0
   11:	getfield	#41; //Field q1$1:Lscala/runtime/IntRef;
   14:	getfield	#83; //Field scala/runtime/IntRef.elem:I
   17:	aload_1
   18:	invokevirtual	#89; //Method scala/util/automata/DetWordAutom.next:(ILjava/lang/Object;)I
   21:	istore_2
   22:	aload_0
   23:	getfield	#39; //Field dfa2$1:Lscala/util/automata/DetWordAutom;
   26:	aload_0
   27:	getfield	#43; //Field q2$1:Lscala/runtime/IntRef;
   30:	getfield	#83; //Field scala/runtime/IntRef.elem:I
   33:	aload_1
   34:	invokevirtual	#89; //Method scala/util/automata/DetWordAutom.next:(ILjava/lang/Object;)I
   37:	istore_3
   38:	aload_0
   39:	getfield	#37; //Field dfa1$1:Lscala/util/automata/DetWordAutom;
   42:	iload_2
   43:	invokevirtual	#93; //Method scala/util/automata/DetWordAutom.isFinal:(I)Z
   46:	ifeq	68
   49:	aload_0
   50:	getfield	#39; //Field dfa2$1:Lscala/util/automata/DetWordAutom;
   53:	iload_3
   54:	invokevirtual	#93; //Method scala/util/automata/DetWordAutom.isFinal:(I)Z
   57:	ifne	68
   60:	aload_0
   61:	getfield	#49; //Field result$1:Lscala/runtime/BooleanRef;
   64:	iconst_0
   65:	putfield	#98; //Field scala/runtime/BooleanRef.elem:Z
   68:	aload_0
   69:	getfield	#35; //Field $outer:Lscala/util/automata/Inclusion;
   72:	iload_2
   73:	iload_3
   74:	aload_0
   75:	getfield	#37; //Field dfa1$1:Lscala/util/automata/DetWordAutom;
   78:	invokestatic	#104; //Method scala/util/automata/Inclusion$class.encode$1:(Lscala/util/automata/Inclusion;IILscala/util/automata/DetWordAutom;)I
   81:	istore	4
   83:	aload_0
   84:	getfield	#47; //Field mark$1:[I
   87:	iload	4
   89:	iaload
   90:	iconst_0
   91:	if_icmpne	128
   94:	aload_0
   95:	getfield	#47; //Field mark$1:[I
   98:	aload_0
   99:	getfield	#51; //Field last$1:Lscala/runtime/IntRef;
   102:	getfield	#83; //Field scala/runtime/IntRef.elem:I
   105:	iload	4
   107:	iastore
   108:	aload_0
   109:	getfield	#47; //Field mark$1:[I
   112:	iload	4
   114:	aload_0
   115:	getfield	#45; //Field max$1:I
   118:	iastore
   119:	aload_0
   120:	getfield	#51; //Field last$1:Lscala/runtime/IntRef;
   123:	iload	4
   125:	putfield	#83; //Field scala/runtime/IntRef.elem:I
   128:	return
  LineNumberTable: 
   line 49: 0
   line 50: 22
   line 51: 38
   line 52: 60
   line 53: 68
   line 55: 83
   line 56: 94
   line 57: 108
   line 58: 119
   line 48: 128

  LocalVariableTable: 
   Start  Length  Slot  Name   Signature
   0      129      0    this       Lscala/util/automata/Inclusion$$anonfun$inclusion$1;
   6      123      1    letter       Ljava/lang/Object;
   22      107      2    r1       I
   38      91      3    r2       I
   83      46      4    test       I

  Signature: length = 0x2
   00 6D 

public scala.Function1 andThen(scala.Function1);
  Code:
   Stack=2, Locals=2, Args_size=2
   0:	aload_0
   1:	aload_1
   2:	invokestatic	#114; //Method scala/Function1$class.andThen:(Lscala/Function1;Lscala/Function1;)Lscala/Function1;
   5:	areturn
  LineNumberTable: 
   line 48: 0

  LocalVariableTable: 
   Start  Length  Slot  Name   Signature
   0      6      0    this       Lscala/util/automata/Inclusion$$anonfun$inclusion$1;
   0      6      1    g       Lscala/Function1;


public scala.Function1 compose(scala.Function1);
  Code:
   Stack=2, Locals=2, Args_size=2
   0:	aload_0
   1:	aload_1
   2:	invokestatic	#119; //Method scala/Function1$class.compose:(Lscala/Function1;Lscala/Function1;)Lscala/Function1;
   5:	areturn
  LineNumberTable: 
   line 48: 0

  LocalVariableTable: 
   Start  Length  Slot  Name   Signature
   0      6      0    this       Lscala/util/automata/Inclusion$$anonfun$inclusion$1;
   0      6      1    g       Lscala/Function1;


public java.lang.String toString();
  Code:
   Stack=1, Locals=1, Args_size=1
   0:	aload_0
   1:	invokestatic	#124; //Method scala/Function1$class.toString:(Lscala/Function1;)Ljava/lang/String;
   4:	areturn
  LineNumberTable: 
   line 48: 0


}

