Compiled from "Inclusion.scala"
public final class scala.util.automata.Inclusion$$anonfun$inclusion$1 extends scala.runtime.AbstractFunction1 implements java.io.Serializable
  SourceFile: "Inclusion.scala"
  Scala: length = 0x
   
  InnerClass: 
   public final $anonfun$inclusion$1=class scala/util/automata/Inclusion$$anonfun$inclusion$1 of class scala/util/automata/Inclusion
  minor version: 0
  major version: 49
  Constant pool:
Asciz	SourceFile;
Asciz	Inclusion.scala;
Asciz	<clinit>;
Asciz	()V;
Asciz	Code;
Asciz	serialVersionUID;
Asciz	J;
Asciz	scala/util/automata/Inclusion$$anonfun$inclusion$1;
class	scala/util/automata/Inclusion$$anonfun$inclusion$1
NameAndType	serialVersionUID:J
Field	scala/util/automata/Inclusion$$anonfun$inclusion$1.serialVersionUID:J
Asciz	last$1;
Asciz	Lscala/runtime/IntRef;;
Asciz	result$1;
Asciz	Lscala/runtime/BooleanRef;;
Asciz	mark$1;
Asciz	[I;
Asciz	max$1;
Asciz	I;
Asciz	q2$1;
Asciz	q1$1;
Asciz	dfa2$1;
Asciz	Lscala/util/automata/DetWordAutom;;
Asciz	dfa1$1;
Asciz	$outer;
Asciz	Lscala/util/automata/Inclusion;;
Asciz	<init>;
Asciz	(Lscala/util/automata/Inclusion;Lscala/util/automata/DetWordAutom;Lscala/util/automata/DetWordAutom;Lscala/runtime/IntRef;Lscala/runtime/IntRef;I[ILscala/runtime/BooleanRef;Lscala/runtime/IntRef;)V;
Asciz	LineNumberTable;
Asciz	java/lang/NullPointerException;
class	java/lang/NullPointerException
NameAndType	"<init>":()V
Method	java/lang/NullPointerException."<init>":()V
NameAndType	$outer:Lscala/util/automata/Inclusion;
Field	scala/util/automata/Inclusion$$anonfun$inclusion$1.$outer:Lscala/util/automata/Inclusion;
NameAndType	dfa1$1:Lscala/util/automata/DetWordAutom;
Field	scala/util/automata/Inclusion$$anonfun$inclusion$1.dfa1$1:Lscala/util/automata/DetWordAutom;
NameAndType	dfa2$1:Lscala/util/automata/DetWordAutom;
Field	scala/util/automata/Inclusion$$anonfun$inclusion$1.dfa2$1:Lscala/util/automata/DetWordAutom;
NameAndType	q1$1:Lscala/runtime/IntRef;
Field	scala/util/automata/Inclusion$$anonfun$inclusion$1.q1$1:Lscala/runtime/IntRef;
NameAndType	q2$1:Lscala/runtime/IntRef;
Field	scala/util/automata/Inclusion$$anonfun$inclusion$1.q2$1:Lscala/runtime/IntRef;
NameAndType	max$1:I
Field	scala/util/automata/Inclusion$$anonfun$inclusion$1.max$1:I
NameAndType	mark$1:[I
Field	scala/util/automata/Inclusion$$anonfun$inclusion$1.mark$1:[I
NameAndType	result$1:Lscala/runtime/BooleanRef;
Field	scala/util/automata/Inclusion$$anonfun$inclusion$1.result$1:Lscala/runtime/BooleanRef;
NameAndType	last$1:Lscala/runtime/IntRef;
Field	scala/util/automata/Inclusion$$anonfun$inclusion$1.last$1:Lscala/runtime/IntRef;
Asciz	scala/runtime/AbstractFunction1;
class	scala/runtime/AbstractFunction1
Method	scala/runtime/AbstractFunction1."<init>":()V
Asciz	this;
Asciz	Lscala/util/automata/Inclusion$$anonfun$inclusion$1;;
Asciz	LocalVariableTable;
Asciz	(Lscala/util/automata/Inclusion<TA;>;)V;
Asciz	Signature;
Asciz	apply;
Asciz	(Ljava/lang/Object;)Ljava/lang/Object;;
Asciz	(Ljava/lang/Object;)V;
NameAndType	apply:(Ljava/lang/Object;)V
Method	scala/util/automata/Inclusion$$anonfun$inclusion$1.apply:(Ljava/lang/Object;)V
Asciz	scala/runtime/BoxedUnit;
class	scala/runtime/BoxedUnit
Asciz	UNIT;
Asciz	Lscala/runtime/BoxedUnit;;
NameAndType	UNIT:Lscala/runtime/BoxedUnit;
Field	scala/runtime/BoxedUnit.UNIT:Lscala/runtime/BoxedUnit;
Asciz	v1;
Asciz	Ljava/lang/Object;;
Asciz	scala/runtime/IntRef;
class	scala/runtime/IntRef
Asciz	elem;
NameAndType	elem:I
Field	scala/runtime/IntRef.elem:I
Asciz	scala/util/automata/DetWordAutom;
class	scala/util/automata/DetWordAutom
Asciz	next;
Asciz	(ILjava/lang/Object;)I;
NameAndType	next:(ILjava/lang/Object;)I
Method	scala/util/automata/DetWordAutom.next:(ILjava/lang/Object;)I
Asciz	isFinal;
Asciz	(I)Z;
NameAndType	isFinal:(I)Z
Method	scala/util/automata/DetWordAutom.isFinal:(I)Z
Asciz	scala/runtime/BooleanRef;
class	scala/runtime/BooleanRef
Asciz	Z;
NameAndType	elem:Z
Field	scala/runtime/BooleanRef.elem:Z
Asciz	scala/util/automata/Inclusion$class;
class	scala/util/automata/Inclusion$class
Asciz	encode$1;
Asciz	(Lscala/util/automata/Inclusion;IILscala/util/automata/DetWordAutom;)I;
NameAndType	encode$1:(Lscala/util/automata/Inclusion;IILscala/util/automata/DetWordAutom;)I
Method	scala/util/automata/Inclusion$class.encode$1:(Lscala/util/automata/Inclusion;IILscala/util/automata/DetWordAutom;)I
Asciz	letter;
Asciz	r1;
Asciz	r2;
Asciz	test;
Asciz	(TA;)V;
Asciz	Scala;
Asciz	InnerClasses;
Asciz	scala/util/automata/Inclusion;
class	scala/util/automata/Inclusion
Asciz	$anonfun$inclusion$1;
Asciz	java/io/Serializable;
class	java/io/Serializable

{
public static final long serialVersionUID;
  Signature: J

private final scala.runtime.IntRef last$1;
  Signature: Lscala/runtime/IntRef;

private final scala.runtime.BooleanRef result$1;
  Signature: Lscala/runtime/BooleanRef;

private final int[] mark$1;
  Signature: [I

private final int max$1;
  Signature: I

private final scala.runtime.IntRef q2$1;
  Signature: Lscala/runtime/IntRef;

private final scala.runtime.IntRef q1$1;
  Signature: Lscala/runtime/IntRef;

private final scala.util.automata.DetWordAutom dfa2$1;
  Signature: Lscala/util/automata/DetWordAutom;

private final scala.util.automata.DetWordAutom dfa1$1;
  Signature: Lscala/util/automata/DetWordAutom;

private final scala.util.automata.Inclusion $outer;
  Signature: Lscala/util/automata/Inclusion;

public static {};
  Signature: ()V
  Code:
   Stack=2, Locals=0, Args_size=0
	lconst_0
	putstatic	Field serialVersionUID:J
	return
  Labels:

public scala.util.automata.Inclusion$$anonfun$inclusion$1(scala.util.automata.Inclusion, scala.util.automata.DetWordAutom, scala.util.automata.DetWordAutom, scala.runtime.IntRef, scala.runtime.IntRef, int, int[], scala.runtime.BooleanRef, scala.runtime.IntRef);
  Signature: (Lscala/util/automata/Inclusion;Lscala/util/automata/DetWordAutom;Lscala/util/automata/DetWordAutom;Lscala/runtime/IntRef;Lscala/runtime/IntRef;I[ILscala/runtime/BooleanRef;Lscala/runtime/IntRef;)V
  Code:
   Stack=2, Locals=10, Args_size=10
	aload_1
	ifnonnull	l1 // aload_0
	new	class java/lang/NullPointerException
	dup
	invokespecial	Method java/lang/NullPointerException."<init>":()V
	athrow
l1	aload_0
	aload_1
	putfield	Field $outer:Lscala/util/automata/Inclusion;
	aload_0
	aload_2
	putfield	Field dfa1$1:Lscala/util/automata/DetWordAutom;
	aload_0
	aload_3
	putfield	Field dfa2$1:Lscala/util/automata/DetWordAutom;
	aload_0
	aload	4
	putfield	Field q1$1:Lscala/runtime/IntRef;
	aload_0
	aload	5
	putfield	Field q2$1:Lscala/runtime/IntRef;
	aload_0
	iload	6
	putfield	Field max$1:I
	aload_0
	aload	7
	putfield	Field mark$1:[I
	aload_0
	aload	8
	putfield	Field result$1:Lscala/runtime/BooleanRef;
	aload_0
	aload	9
	putfield	Field last$1:Lscala/runtime/IntRef;
	aload_0
	invokespecial	Method scala/runtime/AbstractFunction1."<init>":()V
	return
  Labels:
   	l1 = 12 // aload_0
  LocalVariableTable: 
   Start  Length  Slot  Name   Signature
   0      68      0    this       Lscala/util/automata/Inclusion$$anonfun$inclusion$1;
   0      68      1    $outer       Lscala/util/automata/Inclusion;

  Signature: length = 0x2
   00 3A 

public final java.lang.Object apply(java.lang.Object);
  Signature: (Ljava/lang/Object;)Ljava/lang/Object;
  Code:
   Stack=2, Locals=2, Args_size=2
	aload_0
	aload_1
	invokevirtual	Method apply:(Ljava/lang/Object;)V
	getstatic	Field scala/runtime/BoxedUnit.UNIT:Lscala/runtime/BoxedUnit;
	areturn
  Labels:
  LocalVariableTable: 
   Start  Length  Slot  Name   Signature
   0      9      0    this       Lscala/util/automata/Inclusion$$anonfun$inclusion$1;
   0      9      1    v1       Ljava/lang/Object;


public final void apply(java.lang.Object);
  Signature: (Ljava/lang/Object;)V
  Code:
   Stack=4, Locals=5, Args_size=2
	aload_0
	getfield	Field dfa1$1:Lscala/util/automata/DetWordAutom;
	aload_0
	getfield	Field q1$1:Lscala/runtime/IntRef;
	getfield	Field scala/runtime/IntRef.elem:I
	aload_1
	invokevirtual	Method scala/util/automata/DetWordAutom.next:(ILjava/lang/Object;)I
	istore_2
	aload_0
	getfield	Field dfa2$1:Lscala/util/automata/DetWordAutom;
	aload_0
	getfield	Field q2$1:Lscala/runtime/IntRef;
	getfield	Field scala/runtime/IntRef.elem:I
	aload_1
	invokevirtual	Method scala/util/automata/DetWordAutom.next:(ILjava/lang/Object;)I
	istore_3
	aload_0
	getfield	Field dfa1$1:Lscala/util/automata/DetWordAutom;
	iload_2
	invokevirtual	Method scala/util/automata/DetWordAutom.isFinal:(I)Z
	ifeq	l1 // aload_0
	aload_0
	getfield	Field dfa2$1:Lscala/util/automata/DetWordAutom;
	iload_3
	invokevirtual	Method scala/util/automata/DetWordAutom.isFinal:(I)Z
	ifne	l1 // aload_0
	aload_0
	getfield	Field result$1:Lscala/runtime/BooleanRef;
	iconst_0
	putfield	Field scala/runtime/BooleanRef.elem:Z
l1	aload_0
	getfield	Field $outer:Lscala/util/automata/Inclusion;
	iload_2
	iload_3
	aload_0
	getfield	Field dfa1$1:Lscala/util/automata/DetWordAutom;
	invokestatic	Method scala/util/automata/Inclusion$class.encode$1:(Lscala/util/automata/Inclusion;IILscala/util/automata/DetWordAutom;)I
	istore	4
	aload_0
	getfield	Field mark$1:[I
	iload	4
	iaload
	iconst_0
	if_icmpne	l2 // return
	aload_0
	getfield	Field mark$1:[I
	aload_0
	getfield	Field last$1:Lscala/runtime/IntRef;
	getfield	Field scala/runtime/IntRef.elem:I
	iload	4
	iastore
	aload_0
	getfield	Field mark$1:[I
	iload	4
	aload_0
	getfield	Field max$1:I
	iastore
	aload_0
	getfield	Field last$1:Lscala/runtime/IntRef;
	iload	4
	putfield	Field scala/runtime/IntRef.elem:I
l2	return
  Labels:
   	l1 = 62 // aload_0
   	l2 = 122 // return
  LocalVariableTable: 
   Start  Length  Slot  Name   Signature
   0      123      0    this       Lscala/util/automata/Inclusion$$anonfun$inclusion$1;
   0      123      1    letter       Ljava/lang/Object;
   16      107      2    r1       I
   32      91      3    r2       I
   77      46      4    test       I

  Signature: length = 0x2
   00 67 

}

