Compiled from "NondetWordAutom.scala"
public final class scala.util.automata.NondetWordAutom$$anonfun$3 extends java.lang.Object implements scala.Function1,scala.ScalaObject,java.io.Serializable
  SourceFile: "NondetWordAutom.scala"
  Scala: length = 0x
   
  InnerClass: 
   public final #112= #15 of #67; //$anonfun$3=class scala/util/automata/NondetWordAutom$$anonfun$3 of class scala/util/automata/NondetWordAutom
  minor version: 0
  major version: 49
  Constant pool:
const #1 = Asciz	SourceFile;
const #2 = Asciz	NondetWordAutom.scala;
const #3 = Asciz	$outer;
const #4 = Asciz	Lscala/util/automata/NondetWordAutom;;
const #5 = Asciz	<init>;
const #6 = Asciz	(Lscala/util/automata/NondetWordAutom;)V;
const #7 = Asciz	Code;
const #8 = Asciz	LineNumberTable;
const #9 = Asciz	java/lang/NullPointerException;
const #10 = class	#9;	//  java/lang/NullPointerException
const #11 = Asciz	()V;
const #12 = NameAndType	#5:#11;//  "<init>":()V
const #13 = Method	#10.#12;	//  java/lang/NullPointerException."<init>":()V
const #14 = Asciz	scala/util/automata/NondetWordAutom$$anonfun$3;
const #15 = class	#14;	//  scala/util/automata/NondetWordAutom$$anonfun$3
const #16 = NameAndType	#3:#4;//  $outer:Lscala/util/automata/NondetWordAutom;
const #17 = Field	#15.#16;	//  scala/util/automata/NondetWordAutom$$anonfun$3.$outer:Lscala/util/automata/NondetWordAutom;
const #18 = Asciz	java/lang/Object;
const #19 = class	#18;	//  java/lang/Object
const #20 = Method	#19.#12;	//  java/lang/Object."<init>":()V
const #21 = Asciz	scala/Function1$class;
const #22 = class	#21;	//  scala/Function1$class
const #23 = Asciz	$init$;
const #24 = Asciz	(Lscala/Function1;)V;
const #25 = NameAndType	#23:#24;//  $init$:(Lscala/Function1;)V
const #26 = Method	#22.#25;	//  scala/Function1$class.$init$:(Lscala/Function1;)V
const #27 = Asciz	this;
const #28 = Asciz	Lscala/util/automata/NondetWordAutom$$anonfun$3;;
const #29 = Asciz	LocalVariableTable;
const #30 = Asciz	(Lscala/util/automata/NondetWordAutom<TT;>;)V;
const #31 = Asciz	Signature;
const #32 = Asciz	apply;
const #33 = Asciz	(Ljava/lang/Object;)Ljava/lang/Object;;
const #34 = Asciz	scala/runtime/BoxesRunTime;
const #35 = class	#34;	//  scala/runtime/BoxesRunTime
const #36 = Asciz	unboxToInt;
const #37 = Asciz	(Ljava/lang/Object;)I;
const #38 = NameAndType	#36:#37;//  unboxToInt:(Ljava/lang/Object;)I
const #39 = Method	#35.#38;	//  scala/runtime/BoxesRunTime.unboxToInt:(Ljava/lang/Object;)I
const #40 = Asciz	(I)Ljava/lang/String;;
const #41 = NameAndType	#32:#40;//  apply:(I)Ljava/lang/String;
const #42 = Method	#15.#41;	//  scala/util/automata/NondetWordAutom$$anonfun$3.apply:(I)Ljava/lang/String;
const #43 = Asciz	v1;
const #44 = Asciz	Ljava/lang/Object;;
const #45 = Asciz	scala/Predef$;
const #46 = class	#45;	//  scala/Predef$
const #47 = Asciz	MODULE$;
const #48 = Asciz	Lscala/Predef$;;
const #49 = NameAndType	#47:#48;//  MODULE$:Lscala/Predef$;
const #50 = Field	#46.#49;	//  scala/Predef$.MODULE$:Lscala/Predef$;
const #51 = Asciz	   %d->%s\n    _>%s\n;
const #52 = String	#51;	//     %d->%s\n    _>%s\n
const #53 = Asciz	stringWrapper;
const #54 = Asciz	(Ljava/lang/String;)Lscala/runtime/RichString;;
const #55 = NameAndType	#53:#54;//  stringWrapper:(Ljava/lang/String;)Lscala/runtime/RichString;
const #56 = Method	#46.#55;	//  scala/Predef$.stringWrapper:(Ljava/lang/String;)Lscala/runtime/RichString;
const #57 = Asciz	scala/runtime/ScalaRunTime$;
const #58 = class	#57;	//  scala/runtime/ScalaRunTime$
const #59 = Asciz	Lscala/runtime/ScalaRunTime$;;
const #60 = NameAndType	#47:#59;//  MODULE$:Lscala/runtime/ScalaRunTime$;
const #61 = Field	#58.#60;	//  scala/runtime/ScalaRunTime$.MODULE$:Lscala/runtime/ScalaRunTime$;
const #62 = Asciz	boxToInteger;
const #63 = Asciz	(I)Ljava/lang/Integer;;
const #64 = NameAndType	#62:#63;//  boxToInteger:(I)Ljava/lang/Integer;
const #65 = Method	#35.#64;	//  scala/runtime/BoxesRunTime.boxToInteger:(I)Ljava/lang/Integer;
const #66 = Asciz	scala/util/automata/NondetWordAutom;
const #67 = class	#66;	//  scala/util/automata/NondetWordAutom
const #68 = Asciz	delta;
const #69 = Asciz	()[Lscala/collection/Map;;
const #70 = NameAndType	#68:#69;//  delta:()[Lscala/collection/Map;
const #71 = Method	#67.#70;	//  scala/util/automata/NondetWordAutom.delta:()[Lscala/collection/Map;
const #72 = Asciz	scala/collection/generic/MapTemplate;
const #73 = class	#72;	//  scala/collection/generic/MapTemplate
const #74 = Asciz	toString;
const #75 = Asciz	()Ljava/lang/String;;
const #76 = NameAndType	#74:#75;//  toString:()Ljava/lang/String;
const #77 = InterfaceMethod	#73.#76;	//  scala/collection/generic/MapTemplate.toString:()Ljava/lang/String;
const #78 = Asciz	default;
const #79 = Asciz	()[Lscala/collection/immutable/BitSet;;
const #80 = NameAndType	#78:#79;//  default:()[Lscala/collection/immutable/BitSet;
const #81 = Method	#67.#80;	//  scala/util/automata/NondetWordAutom.default:()[Lscala/collection/immutable/BitSet;
const #82 = Asciz	scala/collection/generic/SetTemplate;
const #83 = class	#82;	//  scala/collection/generic/SetTemplate
const #84 = InterfaceMethod	#83.#76;	//  scala/collection/generic/SetTemplate.toString:()Ljava/lang/String;
const #85 = Asciz	boxArray;
const #86 = Asciz	(Ljava/lang/Object;)Lscala/runtime/BoxedArray;;
const #87 = NameAndType	#85:#86;//  boxArray:(Ljava/lang/Object;)Lscala/runtime/BoxedArray;
const #88 = Method	#58.#87;	//  scala/runtime/ScalaRunTime$.boxArray:(Ljava/lang/Object;)Lscala/runtime/BoxedArray;
const #89 = Asciz	scala/runtime/RichString;
const #90 = class	#89;	//  scala/runtime/RichString
const #91 = Asciz	format;
const #92 = Asciz	(Lscala/collection/Sequence;)Ljava/lang/String;;
const #93 = NameAndType	#91:#92;//  format:(Lscala/collection/Sequence;)Ljava/lang/String;
const #94 = Method	#90.#93;	//  scala/runtime/RichString.format:(Lscala/collection/Sequence;)Ljava/lang/String;
const #95 = Asciz	i;
const #96 = Asciz	I;
const #97 = Asciz	andThen;
const #98 = Asciz	(Lscala/Function1;)Lscala/Function1;;
const #99 = Asciz	(Lscala/Function1;Lscala/Function1;)Lscala/Function1;;
const #100 = NameAndType	#97:#99;//  andThen:(Lscala/Function1;Lscala/Function1;)Lscala/Function1;
const #101 = Method	#22.#100;	//  scala/Function1$class.andThen:(Lscala/Function1;Lscala/Function1;)Lscala/Function1;
const #102 = Asciz	g;
const #103 = Asciz	Lscala/Function1;;
const #104 = Asciz	compose;
const #105 = NameAndType	#104:#99;//  compose:(Lscala/Function1;Lscala/Function1;)Lscala/Function1;
const #106 = Method	#22.#105;	//  scala/Function1$class.compose:(Lscala/Function1;Lscala/Function1;)Lscala/Function1;
const #107 = Asciz	(Lscala/Function1;)Ljava/lang/String;;
const #108 = NameAndType	#74:#107;//  toString:(Lscala/Function1;)Ljava/lang/String;
const #109 = Method	#22.#108;	//  scala/Function1$class.toString:(Lscala/Function1;)Ljava/lang/String;
const #110 = Asciz	Scala;
const #111 = Asciz	InnerClasses;
const #112 = Asciz	$anonfun$3;
const #113 = Asciz	scala/Function1;
const #114 = class	#113;	//  scala/Function1
const #115 = Asciz	scala/ScalaObject;
const #116 = class	#115;	//  scala/ScalaObject
const #117 = Asciz	java/io/Serializable;
const #118 = class	#117;	//  java/io/Serializable

{
public scala.util.automata.NondetWordAutom$$anonfun$3(scala.util.automata.NondetWordAutom);
  Code:
   Stack=2, Locals=2, Args_size=2
   0:	aload_1
   1:	ifnonnull	12
   4:	new	#10; //class java/lang/NullPointerException
   7:	dup
   8:	invokespecial	#13; //Method java/lang/NullPointerException."<init>":()V
   11:	athrow
   12:	aload_0
   13:	aload_1
   14:	putfield	#17; //Field $outer:Lscala/util/automata/NondetWordAutom;
   17:	aload_0
   18:	invokespecial	#20; //Method java/lang/Object."<init>":()V
   21:	aload_0
   22:	invokestatic	#26; //Method scala/Function1$class.$init$:(Lscala/Function1;)V
   25:	return
  LineNumberTable: 
   line 57: 0

  LocalVariableTable: 
   Start  Length  Slot  Name   Signature
   0      26      0    this       Lscala/util/automata/NondetWordAutom$$anonfun$3;
   0      26      1    $outer       Lscala/util/automata/NondetWordAutom;

  Signature: length = 0x2
   00 1E 

public final java.lang.Object apply(java.lang.Object);
  Code:
   Stack=2, Locals=3, Args_size=2
   0:	aload_0
   1:	getfield	#17; //Field $outer:Lscala/util/automata/NondetWordAutom;
   4:	astore_2
   5:	aload_0
   6:	aload_1
   7:	invokestatic	#39; //Method scala/runtime/BoxesRunTime.unboxToInt:(Ljava/lang/Object;)I
   10:	invokevirtual	#42; //Method apply:(I)Ljava/lang/String;
   13:	areturn
  LineNumberTable: 
   line 57: 0

  LocalVariableTable: 
   Start  Length  Slot  Name   Signature
   0      14      0    this       Lscala/util/automata/NondetWordAutom$$anonfun$3;
   5      9      1    v1       Ljava/lang/Object;


public final java.lang.String apply(int);
  Code:
   Stack=7, Locals=3, Args_size=2
   0:	aload_0
   1:	getfield	#17; //Field $outer:Lscala/util/automata/NondetWordAutom;
   4:	astore_2
   5:	getstatic	#50; //Field scala/Predef$.MODULE$:Lscala/Predef$;
   8:	ldc	#52; //String    %d->%s\n    _>%s\n
   10:	invokevirtual	#56; //Method scala/Predef$.stringWrapper:(Ljava/lang/String;)Lscala/runtime/RichString;
   13:	getstatic	#61; //Field scala/runtime/ScalaRunTime$.MODULE$:Lscala/runtime/ScalaRunTime$;
   16:	iconst_3
   17:	anewarray	#19; //class java/lang/Object
   20:	dup
   21:	iconst_0
   22:	iload_1
   23:	invokestatic	#65; //Method scala/runtime/BoxesRunTime.boxToInteger:(I)Ljava/lang/Integer;
   26:	aastore
   27:	dup
   28:	iconst_1
   29:	aload_0
   30:	getfield	#17; //Field $outer:Lscala/util/automata/NondetWordAutom;
   33:	invokevirtual	#71; //Method scala/util/automata/NondetWordAutom.delta:()[Lscala/collection/Map;
   36:	iload_1
   37:	aaload
   38:	invokeinterface	#77,  1; //InterfaceMethod scala/collection/generic/MapTemplate.toString:()Ljava/lang/String;
   43:	aastore
   44:	dup
   45:	iconst_2
   46:	aload_0
   47:	getfield	#17; //Field $outer:Lscala/util/automata/NondetWordAutom;
   50:	invokevirtual	#81; //Method scala/util/automata/NondetWordAutom.default:()[Lscala/collection/immutable/BitSet;
   53:	iload_1
   54:	aaload
   55:	invokeinterface	#84,  1; //InterfaceMethod scala/collection/generic/SetTemplate.toString:()Ljava/lang/String;
   60:	aastore
   61:	invokevirtual	#88; //Method scala/runtime/ScalaRunTime$.boxArray:(Ljava/lang/Object;)Lscala/runtime/BoxedArray;
   64:	invokevirtual	#94; //Method scala/runtime/RichString.format:(Lscala/collection/Sequence;)Ljava/lang/String;
   67:	areturn
  LineNumberTable: 
   line 57: 0

  LocalVariableTable: 
   Start  Length  Slot  Name   Signature
   0      68      0    this       Lscala/util/automata/NondetWordAutom$$anonfun$3;
   5      63      1    i       I


public scala.Function1 andThen(scala.Function1);
  Code:
   Stack=2, Locals=2, Args_size=2
   0:	aload_0
   1:	aload_1
   2:	invokestatic	#101; //Method scala/Function1$class.andThen:(Lscala/Function1;Lscala/Function1;)Lscala/Function1;
   5:	areturn
  LineNumberTable: 
   line 57: 0

  LocalVariableTable: 
   Start  Length  Slot  Name   Signature
   0      6      0    this       Lscala/util/automata/NondetWordAutom$$anonfun$3;
   0      6      1    g       Lscala/Function1;


public scala.Function1 compose(scala.Function1);
  Code:
   Stack=2, Locals=2, Args_size=2
   0:	aload_0
   1:	aload_1
   2:	invokestatic	#106; //Method scala/Function1$class.compose:(Lscala/Function1;Lscala/Function1;)Lscala/Function1;
   5:	areturn
  LineNumberTable: 
   line 57: 0

  LocalVariableTable: 
   Start  Length  Slot  Name   Signature
   0      6      0    this       Lscala/util/automata/NondetWordAutom$$anonfun$3;
   0      6      1    g       Lscala/Function1;


public java.lang.String toString();
  Code:
   Stack=1, Locals=1, Args_size=1
   0:	aload_0
   1:	invokestatic	#109; //Method scala/Function1$class.toString:(Lscala/Function1;)Ljava/lang/String;
   4:	areturn
  LineNumberTable: 
   line 57: 0


}

