Compiled from "NondetWordAutom.scala"
public final class scala.util.automata.NondetWordAutom$$anonfun$2 extends java.lang.Object implements scala.Function1,scala.ScalaObject,java.io.Serializable
  SourceFile: "NondetWordAutom.scala"
  Scala: length = 0x
   
  InnerClass: 
   public final $anonfun$2=class scala/util/automata/NondetWordAutom$$anonfun$2 of class scala/util/automata/NondetWordAutom
  minor version: 0
  major version: 49
  Constant pool:
Asciz	SourceFile;
Asciz	NondetWordAutom.scala;
Asciz	<clinit>;
Asciz	()V;
Asciz	Code;
Asciz	serialVersionUID;
Asciz	J;
Asciz	scala/util/automata/NondetWordAutom$$anonfun$2;
class	scala/util/automata/NondetWordAutom$$anonfun$2
NameAndType	serialVersionUID:J
Field	scala/util/automata/NondetWordAutom$$anonfun$2.serialVersionUID:J
Asciz	$outer;
Asciz	Lscala/util/automata/NondetWordAutom;;
Asciz	<init>;
Asciz	(Lscala/util/automata/NondetWordAutom;)V;
Asciz	LineNumberTable;
Asciz	java/lang/NullPointerException;
class	java/lang/NullPointerException
NameAndType	"<init>":()V
Method	java/lang/NullPointerException."<init>":()V
NameAndType	$outer:Lscala/util/automata/NondetWordAutom;
Field	scala/util/automata/NondetWordAutom$$anonfun$2.$outer:Lscala/util/automata/NondetWordAutom;
Asciz	java/lang/Object;
class	java/lang/Object
Method	java/lang/Object."<init>":()V
Asciz	scala/Function1$class;
class	scala/Function1$class
Asciz	$init$;
Asciz	(Lscala/Function1;)V;
NameAndType	$init$:(Lscala/Function1;)V
Method	scala/Function1$class.$init$:(Lscala/Function1;)V
Asciz	this;
Asciz	Lscala/util/automata/NondetWordAutom$$anonfun$2;;
Asciz	LocalVariableTable;
Asciz	(Lscala/util/automata/NondetWordAutom<TT;>;)V;
Asciz	Signature;
Asciz	apply;
Asciz	(Ljava/lang/Object;)Ljava/lang/Object;;
Asciz	scala/runtime/BoxesRunTime;
class	scala/runtime/BoxesRunTime
Asciz	unboxToInt;
Asciz	(Ljava/lang/Object;)I;
NameAndType	unboxToInt:(Ljava/lang/Object;)I
Method	scala/runtime/BoxesRunTime.unboxToInt:(Ljava/lang/Object;)I
Asciz	(I)Ljava/lang/String;;
NameAndType	apply:(I)Ljava/lang/String;
Method	scala/util/automata/NondetWordAutom$$anonfun$2.apply:(I)Ljava/lang/String;
Asciz	v1;
Asciz	Ljava/lang/Object;;
Asciz	scala/Predef$;
class	scala/Predef$
Asciz	MODULE$;
Asciz	Lscala/Predef$;;
NameAndType	MODULE$:Lscala/Predef$;
Field	scala/Predef$.MODULE$:Lscala/Predef$;
Asciz	   %d->%s\n    _>%s\n;
String	   %d->%s\n    _>%s\n
Asciz	augmentString;
Asciz	(Ljava/lang/String;)Lscala/collection/immutable/StringOps;;
NameAndType	augmentString:(Ljava/lang/String;)Lscala/collection/immutable/StringOps;
Method	scala/Predef$.augmentString:(Ljava/lang/String;)Lscala/collection/immutable/StringOps;
Asciz	boxToInteger;
Asciz	(I)Ljava/lang/Integer;;
NameAndType	boxToInteger:(I)Ljava/lang/Integer;
Method	scala/runtime/BoxesRunTime.boxToInteger:(I)Ljava/lang/Integer;
Asciz	scala/util/automata/NondetWordAutom;
class	scala/util/automata/NondetWordAutom
Asciz	delta;
Asciz	()[Lscala/collection/Map;;
NameAndType	delta:()[Lscala/collection/Map;
Method	scala/util/automata/NondetWordAutom.delta:()[Lscala/collection/Map;
Asciz	default;
Asciz	()[Lscala/collection/immutable/BitSet;;
NameAndType	default:()[Lscala/collection/immutable/BitSet;
Method	scala/util/automata/NondetWordAutom.default:()[Lscala/collection/immutable/BitSet;
Asciz	genericWrapArray;
Asciz	(Ljava/lang/Object;)Lscala/collection/mutable/WrappedArray;;
NameAndType	genericWrapArray:(Ljava/lang/Object;)Lscala/collection/mutable/WrappedArray;
Method	scala/Predef$.genericWrapArray:(Ljava/lang/Object;)Lscala/collection/mutable/WrappedArray;
Asciz	scala/collection/immutable/StringLike;
class	scala/collection/immutable/StringLike
Asciz	format;
Asciz	(Lscala/collection/Seq;)Ljava/lang/String;;
NameAndType	format:(Lscala/collection/Seq;)Ljava/lang/String;
InterfaceMethod	scala/collection/immutable/StringLike.format:(Lscala/collection/Seq;)Ljava/lang/String;
Asciz	i;
Asciz	I;
Asciz	andThen;
Asciz	(Lscala/Function1;)Lscala/Function1;;
Asciz	(Lscala/Function1;Lscala/Function1;)Lscala/Function1;;
NameAndType	andThen:(Lscala/Function1;Lscala/Function1;)Lscala/Function1;
Method	scala/Function1$class.andThen:(Lscala/Function1;Lscala/Function1;)Lscala/Function1;
Asciz	g;
Asciz	Lscala/Function1;;
Asciz	compose;
NameAndType	compose:(Lscala/Function1;Lscala/Function1;)Lscala/Function1;
Method	scala/Function1$class.compose:(Lscala/Function1;Lscala/Function1;)Lscala/Function1;
Asciz	toString;
Asciz	()Ljava/lang/String;;
Asciz	(Lscala/Function1;)Ljava/lang/String;;
NameAndType	toString:(Lscala/Function1;)Ljava/lang/String;
Method	scala/Function1$class.toString:(Lscala/Function1;)Ljava/lang/String;
Asciz	Scala;
Asciz	InnerClasses;
Asciz	$anonfun$2;
Asciz	scala/Function1;
class	scala/Function1
Asciz	scala/ScalaObject;
class	scala/ScalaObject
Asciz	java/io/Serializable;
class	java/io/Serializable

{
public static final long serialVersionUID;
  Signature: J

private final scala.util.automata.NondetWordAutom $outer;
  Signature: Lscala/util/automata/NondetWordAutom;

public static {};
  Signature: ()V
  Code:
   Stack=2, Locals=0, Args_size=0
	lconst_0
	putstatic	Field serialVersionUID:J
	return
  Labels:

public scala.util.automata.NondetWordAutom$$anonfun$2(scala.util.automata.NondetWordAutom);
  Signature: (Lscala/util/automata/NondetWordAutom;)V
  Code:
   Stack=2, Locals=2, Args_size=2
	aload_1
	ifnonnull	l1 // aload_0
	new	class java/lang/NullPointerException
	dup
	invokespecial	Method java/lang/NullPointerException."<init>":()V
	athrow
l1	aload_0
	aload_1
	putfield	Field $outer:Lscala/util/automata/NondetWordAutom;
	aload_0
	invokespecial	Method java/lang/Object."<init>":()V
	aload_0
	invokestatic	Method scala/Function1$class.$init$:(Lscala/Function1;)V
	return
  Labels:
   	l1 = 12 // aload_0
  LocalVariableTable: 
   Start  Length  Slot  Name   Signature
   0      26      0    this       Lscala/util/automata/NondetWordAutom$$anonfun$2;
   0      26      1    $outer       Lscala/util/automata/NondetWordAutom;

  Signature: length = 0x2
   00 23 

public final java.lang.Object apply(java.lang.Object);
  Signature: (Ljava/lang/Object;)Ljava/lang/Object;
  Code:
   Stack=2, Locals=3, Args_size=2
	aload_0
	getfield	Field $outer:Lscala/util/automata/NondetWordAutom;
	astore_2
	aload_0
	aload_1
	invokestatic	Method scala/runtime/BoxesRunTime.unboxToInt:(Ljava/lang/Object;)I
	invokevirtual	Method apply:(I)Ljava/lang/String;
	areturn
  Labels:
  LocalVariableTable: 
   Start  Length  Slot  Name   Signature
   0      14      0    this       Lscala/util/automata/NondetWordAutom$$anonfun$2;
   5      9      1    v1       Ljava/lang/Object;


public final java.lang.String apply(int);
  Signature: (I)Ljava/lang/String;
  Code:
   Stack=7, Locals=3, Args_size=2
	aload_0
	getfield	Field $outer:Lscala/util/automata/NondetWordAutom;
	astore_2
	getstatic	Field scala/Predef$.MODULE$:Lscala/Predef$;
	ldc	String    %d->%s\n    _>%s\n
	invokevirtual	Method scala/Predef$.augmentString:(Ljava/lang/String;)Lscala/collection/immutable/StringOps;
	getstatic	Field scala/Predef$.MODULE$:Lscala/Predef$;
	iconst_3
	anewarray	class java/lang/Object
	dup
	iconst_0
	iload_1
	invokestatic	Method scala/runtime/BoxesRunTime.boxToInteger:(I)Ljava/lang/Integer;
	aastore
	dup
	iconst_1
	aload_0
	getfield	Field $outer:Lscala/util/automata/NondetWordAutom;
	invokevirtual	Method scala/util/automata/NondetWordAutom.delta:()[Lscala/collection/Map;
	iload_1
	aaload
	aastore
	dup
	iconst_2
	aload_0
	getfield	Field $outer:Lscala/util/automata/NondetWordAutom;
	invokevirtual	Method scala/util/automata/NondetWordAutom.default:()[Lscala/collection/immutable/BitSet;
	iload_1
	aaload
	aastore
	invokevirtual	Method scala/Predef$.genericWrapArray:(Ljava/lang/Object;)Lscala/collection/mutable/WrappedArray;
	invokeinterface	InterfaceMethod scala/collection/immutable/StringLike.format:(Lscala/collection/Seq;)Ljava/lang/String;
	areturn
  Labels:
  LocalVariableTable: 
   Start  Length  Slot  Name   Signature
   0      60      0    this       Lscala/util/automata/NondetWordAutom$$anonfun$2;
   5      55      1    i       I


public scala.Function1 andThen(scala.Function1);
  Signature: (Lscala/Function1;)Lscala/Function1;
  Code:
   Stack=2, Locals=2, Args_size=2
	aload_0
	aload_1
	invokestatic	Method scala/Function1$class.andThen:(Lscala/Function1;Lscala/Function1;)Lscala/Function1;
	areturn
  Labels:
  LocalVariableTable: 
   Start  Length  Slot  Name   Signature
   0      6      0    this       Lscala/util/automata/NondetWordAutom$$anonfun$2;
   0      6      1    g       Lscala/Function1;


public scala.Function1 compose(scala.Function1);
  Signature: (Lscala/Function1;)Lscala/Function1;
  Code:
   Stack=2, Locals=2, Args_size=2
	aload_0
	aload_1
	invokestatic	Method scala/Function1$class.compose:(Lscala/Function1;Lscala/Function1;)Lscala/Function1;
	areturn
  Labels:
  LocalVariableTable: 
   Start  Length  Slot  Name   Signature
   0      6      0    this       Lscala/util/automata/NondetWordAutom$$anonfun$2;
   0      6      1    g       Lscala/Function1;


public java.lang.String toString();
  Signature: ()Ljava/lang/String;
  Code:
   Stack=1, Locals=1, Args_size=1
	aload_0
	invokestatic	Method scala/Function1$class.toString:(Lscala/Function1;)Ljava/lang/String;
	areturn
  Labels:

}

