Compiled from "NondetWordAutom.scala"
public final class scala.util.automata.NondetWordAutom$$anonfun$finalStates$1 extends scala.runtime.AbstractFunction1 implements java.io.Serializable
  SourceFile: "NondetWordAutom.scala"
  Scala: length = 0x
   
  InnerClass: 
   public final $anonfun$finalStates$1=class scala/util/automata/NondetWordAutom$$anonfun$finalStates$1 of class scala/util/automata/NondetWordAutom
  minor version: 0
  major version: 49
  Constant pool:
Asciz	SourceFile;
Asciz	NondetWordAutom.scala;
Asciz	<clinit>;
Asciz	()V;
Asciz	Code;
Asciz	serialVersionUID;
Asciz	J;
Asciz	scala/util/automata/NondetWordAutom$$anonfun$finalStates$1;
class	scala/util/automata/NondetWordAutom$$anonfun$finalStates$1
NameAndType	serialVersionUID:J
Field	scala/util/automata/NondetWordAutom$$anonfun$finalStates$1.serialVersionUID:J
Asciz	$outer;
Asciz	Lscala/util/automata/NondetWordAutom;;
Asciz	apply;
Asciz	(I)Z;
Asciz	LineNumberTable;
NameAndType	$outer:Lscala/util/automata/NondetWordAutom;
Field	scala/util/automata/NondetWordAutom$$anonfun$finalStates$1.$outer:Lscala/util/automata/NondetWordAutom;
Asciz	scala/util/automata/NondetWordAutom;
class	scala/util/automata/NondetWordAutom
Asciz	isFinal;
NameAndType	isFinal:(I)Z
Method	scala/util/automata/NondetWordAutom.isFinal:(I)Z
Asciz	apply$mcZI$sp;
Asciz	this;
Asciz	Lscala/util/automata/NondetWordAutom$$anonfun$finalStates$1;;
Asciz	v1;
Asciz	I;
Asciz	LocalVariableTable;
Asciz	(Ljava/lang/Object;)Ljava/lang/Object;;
Asciz	scala/runtime/BoxesRunTime;
class	scala/runtime/BoxesRunTime
Asciz	unboxToInt;
Asciz	(Ljava/lang/Object;)I;
NameAndType	unboxToInt:(Ljava/lang/Object;)I
Method	scala/runtime/BoxesRunTime.unboxToInt:(Ljava/lang/Object;)I
NameAndType	apply:(I)Z
Method	scala/util/automata/NondetWordAutom$$anonfun$finalStates$1.apply:(I)Z
Asciz	boxToBoolean;
Asciz	(Z)Ljava/lang/Boolean;;
NameAndType	boxToBoolean:(Z)Ljava/lang/Boolean;
Method	scala/runtime/BoxesRunTime.boxToBoolean:(Z)Ljava/lang/Boolean;
Asciz	Ljava/lang/Object;;
Asciz	<init>;
Asciz	(Lscala/util/automata/NondetWordAutom;)V;
Asciz	java/lang/NullPointerException;
class	java/lang/NullPointerException
NameAndType	"<init>":()V
Method	java/lang/NullPointerException."<init>":()V
Asciz	scala/runtime/AbstractFunction1;
class	scala/runtime/AbstractFunction1
Method	scala/runtime/AbstractFunction1."<init>":()V
Asciz	(Lscala/util/automata/NondetWordAutom<TT;>;)V;
Asciz	Signature;
Asciz	Scala;
Asciz	InnerClasses;
Asciz	$anonfun$finalStates$1;
Asciz	java/io/Serializable;
class	java/io/Serializable

{
public static final long serialVersionUID;
  Signature: J

public final scala.util.automata.NondetWordAutom $outer;
  Signature: Lscala/util/automata/NondetWordAutom;

public static {};
  Signature: ()V
  Code:
   Stack=2, Locals=0, Args_size=0
	lconst_0
	putstatic	Field serialVersionUID:J
	return
  Labels:

public final boolean apply(int);
  Signature: (I)Z
  Code:
   Stack=2, Locals=2, Args_size=2
	aload_0
	getfield	Field $outer:Lscala/util/automata/NondetWordAutom;
	iload_1
	invokevirtual	Method scala/util/automata/NondetWordAutom.isFinal:(I)Z
	ireturn
  Labels:

public boolean apply$mcZI$sp(int);
  Signature: (I)Z
  Code:
   Stack=2, Locals=2, Args_size=2
	aload_0
	getfield	Field $outer:Lscala/util/automata/NondetWordAutom;
	iload_1
	invokevirtual	Method scala/util/automata/NondetWordAutom.isFinal:(I)Z
	ireturn
  Labels:
  LocalVariableTable: 
   Start  Length  Slot  Name   Signature
   0      9      0    this       Lscala/util/automata/NondetWordAutom$$anonfun$finalStates$1;
   0      9      1    v1       I


public final java.lang.Object apply(java.lang.Object);
  Signature: (Ljava/lang/Object;)Ljava/lang/Object;
  Code:
   Stack=2, Locals=3, Args_size=2
	aload_0
	aload_1
	invokestatic	Method scala/runtime/BoxesRunTime.unboxToInt:(Ljava/lang/Object;)I
	invokevirtual	Method apply:(I)Z
	istore_2
	iload_2
	invokestatic	Method scala/runtime/BoxesRunTime.boxToBoolean:(Z)Ljava/lang/Boolean;
	areturn
  Labels:
  LocalVariableTable: 
   Start  Length  Slot  Name   Signature
   0      14      0    this       Lscala/util/automata/NondetWordAutom$$anonfun$finalStates$1;
   0      14      1    v1       Ljava/lang/Object;


public scala.util.automata.NondetWordAutom$$anonfun$finalStates$1(scala.util.automata.NondetWordAutom);
  Signature: (Lscala/util/automata/NondetWordAutom;)V
  Code:
   Stack=2, Locals=2, Args_size=2
	aload_1
	ifnonnull	l1 // aload_0
	new	class java/lang/NullPointerException
	dup
	invokespecial	Method java/lang/NullPointerException."<init>":()V
	athrow
l1	aload_0
	aload_1
	putfield	Field $outer:Lscala/util/automata/NondetWordAutom;
	aload_0
	invokespecial	Method scala/runtime/AbstractFunction1."<init>":()V
	return
  Labels:
   	l1 = 12 // aload_0
  LocalVariableTable: 
   Start  Length  Slot  Name   Signature
   0      22      0    this       Lscala/util/automata/NondetWordAutom$$anonfun$finalStates$1;
   0      22      1    $outer       Lscala/util/automata/NondetWordAutom;

  Signature: length = 0x2
   00 35 

}

