Compiled from "NondetWordAutom.scala"
public final class scala.util.automata.NondetWordAutom$$anonfun$next$1 extends java.lang.Object implements scala.Function0,scala.ScalaObject,java.io.Serializable
  SourceFile: "NondetWordAutom.scala"
  Scala: length = 0x
   
  InnerClass: 
   public final $anonfun$next$1=class scala/util/automata/NondetWordAutom$$anonfun$next$1 of class scala/util/automata/NondetWordAutom
  minor version: 0
  major version: 49
  Constant pool:
Asciz	SourceFile;
Asciz	NondetWordAutom.scala;
Asciz	<clinit>;
Asciz	()V;
Asciz	Code;
Asciz	serialVersionUID;
Asciz	J;
Asciz	scala/util/automata/NondetWordAutom$$anonfun$next$1;
class	scala/util/automata/NondetWordAutom$$anonfun$next$1
NameAndType	serialVersionUID:J
Field	scala/util/automata/NondetWordAutom$$anonfun$next$1.serialVersionUID:J
Asciz	q$1;
Asciz	I;
Asciz	$outer;
Asciz	Lscala/util/automata/NondetWordAutom;;
Asciz	<init>;
Asciz	(Lscala/util/automata/NondetWordAutom;I)V;
Asciz	LineNumberTable;
Asciz	java/lang/NullPointerException;
class	java/lang/NullPointerException
NameAndType	"<init>":()V
Method	java/lang/NullPointerException."<init>":()V
NameAndType	$outer:Lscala/util/automata/NondetWordAutom;
Field	scala/util/automata/NondetWordAutom$$anonfun$next$1.$outer:Lscala/util/automata/NondetWordAutom;
NameAndType	q$1:I
Field	scala/util/automata/NondetWordAutom$$anonfun$next$1.q$1:I
Asciz	java/lang/Object;
class	java/lang/Object
Method	java/lang/Object."<init>":()V
Asciz	scala/Function0$class;
class	scala/Function0$class
Asciz	$init$;
Asciz	(Lscala/Function0;)V;
NameAndType	$init$:(Lscala/Function0;)V
Method	scala/Function0$class.$init$:(Lscala/Function0;)V
Asciz	this;
Asciz	Lscala/util/automata/NondetWordAutom$$anonfun$next$1;;
Asciz	LocalVariableTable;
Asciz	(Lscala/util/automata/NondetWordAutom<TT;>;)V;
Asciz	Signature;
Asciz	apply;
Asciz	()Ljava/lang/Object;;
Asciz	()Lscala/collection/immutable/BitSet;;
NameAndType	apply:()Lscala/collection/immutable/BitSet;
Method	scala/util/automata/NondetWordAutom$$anonfun$next$1.apply:()Lscala/collection/immutable/BitSet;
Asciz	scala/util/automata/NondetWordAutom;
class	scala/util/automata/NondetWordAutom
Asciz	default;
Asciz	()[Lscala/collection/immutable/BitSet;;
NameAndType	default:()[Lscala/collection/immutable/BitSet;
Method	scala/util/automata/NondetWordAutom.default:()[Lscala/collection/immutable/BitSet;
Asciz	toString;
Asciz	()Ljava/lang/String;;
Asciz	(Lscala/Function0;)Ljava/lang/String;;
NameAndType	toString:(Lscala/Function0;)Ljava/lang/String;
Method	scala/Function0$class.toString:(Lscala/Function0;)Ljava/lang/String;
Asciz	Scala;
Asciz	InnerClasses;
Asciz	$anonfun$next$1;
Asciz	scala/Function0;
class	scala/Function0
Asciz	scala/ScalaObject;
class	scala/ScalaObject
Asciz	java/io/Serializable;
class	java/io/Serializable

{
public static final long serialVersionUID;
  Signature: J

private final int q$1;
  Signature: I

private final scala.util.automata.NondetWordAutom $outer;
  Signature: Lscala/util/automata/NondetWordAutom;

public static {};
  Signature: ()V
  Code:
   Stack=2, Locals=0, Args_size=0
	lconst_0
	putstatic	Field serialVersionUID:J
	return
  Labels:

public scala.util.automata.NondetWordAutom$$anonfun$next$1(scala.util.automata.NondetWordAutom, int);
  Signature: (Lscala/util/automata/NondetWordAutom;I)V
  Code:
   Stack=2, Locals=3, Args_size=3
	aload_1
	ifnonnull	l1 // aload_0
	new	class java/lang/NullPointerException
	dup
	invokespecial	Method java/lang/NullPointerException."<init>":()V
	athrow
l1	aload_0
	aload_1
	putfield	Field $outer:Lscala/util/automata/NondetWordAutom;
	aload_0
	iload_2
	putfield	Field q$1:I
	aload_0
	invokespecial	Method java/lang/Object."<init>":()V
	aload_0
	invokestatic	Method scala/Function0$class.$init$:(Lscala/Function0;)V
	return
  Labels:
   	l1 = 12 // aload_0
  LocalVariableTable: 
   Start  Length  Slot  Name   Signature
   0      31      0    this       Lscala/util/automata/NondetWordAutom$$anonfun$next$1;
   0      31      1    $outer       Lscala/util/automata/NondetWordAutom;

  Signature: length = 0x2
   00 27 

public final java.lang.Object apply();
  Signature: ()Ljava/lang/Object;
  Code:
   Stack=1, Locals=2, Args_size=1
	aload_0
	getfield	Field $outer:Lscala/util/automata/NondetWordAutom;
	astore_1
	aload_0
	invokevirtual	Method apply:()Lscala/collection/immutable/BitSet;
	areturn
  Labels:
  LocalVariableTable: 
   Start  Length  Slot  Name   Signature
   0      10      0    this       Lscala/util/automata/NondetWordAutom$$anonfun$next$1;


public final scala.collection.immutable.BitSet apply();
  Signature: ()Lscala/collection/immutable/BitSet;
  Code:
   Stack=2, Locals=2, Args_size=1
	aload_0
	getfield	Field $outer:Lscala/util/automata/NondetWordAutom;
	astore_1
	aload_0
	getfield	Field $outer:Lscala/util/automata/NondetWordAutom;
	invokevirtual	Method scala/util/automata/NondetWordAutom.default:()[Lscala/collection/immutable/BitSet;
	aload_0
	getfield	Field q$1:I
	aaload
	areturn
  Labels:
  LocalVariableTable: 
   Start  Length  Slot  Name   Signature
   0      18      0    this       Lscala/util/automata/NondetWordAutom$$anonfun$next$1;


public java.lang.String toString();
  Signature: ()Ljava/lang/String;
  Code:
   Stack=1, Locals=1, Args_size=1
	aload_0
	invokestatic	Method scala/Function0$class.toString:(Lscala/Function0;)Ljava/lang/String;
	areturn
  Labels:

}

