Compiled from "NondetWordAutom.scala"
public abstract class scala.util.automata.NondetWordAutom extends java.lang.Object implements scala.ScalaObject
  SourceFile: "NondetWordAutom.scala"
  Signature: length = 0x2
   00 FFFFFFE0 
  ScalaSig: length = 0x33C
   05 00 FFFFFF81 0B 06 05 01 02 FFFFFF81 00 09 02 0F 4E 6F 6E
   64 65 74 57 6F 72 64 41 75 74 6F 6D 0A 02 03 04
   01 08 61 75 74 6F 6D 61 74 61 0A 02 05 06 01 04
   75 74 69 6C 0A 01 07 01 05 73 63 61 6C 61 03 00
   15 02 0A 1E 13 03 00 0B 13 10 02 0C 11 0D 01 0D
   0A 02 0E 0F 01 04 6C 61 6E 67 0A 01 10 01 04 6A
   61 76 61 09 02 12 0D 02 06 4F 62 6A 65 63 74 10
   02 14 15 0D 01 06 09 02 16 06 02 0B 53 63 61 6C
   61 4F 62 6A 65 63 74 08 05 18 00 FFFFFF84 00 19 01 06
   3C 69 6E 69 74 3E 14 01 1A 10 03 1B 00 1C 0D 01
   02 10 02 1D 1E 0C 00 04 08 1F 00 FFFFFF84 FFFFFF80 FFFFFF80 FFFFFFC2 00
   20 02 01 54 11 02 21 24 10 02 14 22 09 02 23 06
   02 07 4E 6F 74 68 69 6E 67 10 02 14 25 09 02 26
   06 02 06 41 6E 79 52 65 66 08 07 28 00 FFFFFFC2 FFFFFF80 FFFFFF86
   00 29 01 07 6E 73 74 61 74 65 73 15 01 2A 10 02
   14 2B 09 02 2C 06 02 03 49 6E 74 08 07 2E 00 FFFFFFC2
   FFFFFF80 FFFFFF86 00 2F 01 06 6C 61 62 65 6C 73 15 01 30 10
   03 31 39 1C 0E 02 32 37 0E 02 33 36 0D 01 34 0A
   02 35 08 01 06 3C 72 6F 6F 74 3E 09 01 07 09 02
   38 06 01 07 70 61 63 6B 61 67 65 09 02 3A 3B 02
   03 53 65 71 0A 02 38 06 08 07 3D 00 FFFFFFC2 FFFFFF80 FFFFFF86 00
   3E 01 06 66 69 6E 61 6C 73 15 01 3F 10 03 14 40
   2A 09 02 41 06 02 05 41 72 72 61 79 08 07 43 00
   FFFFFFC2 FFFFFF80 FFFFFF86 00 44 01 05 64 65 6C 74 61 15 01 45 10
   03 14 40 46 10 04 47 4A 1C 4C 0D 01 48 0A 02 49
   06 01 0A 63 6F 6C 6C 65 63 74 69 6F 6E 09 02 4B
   48 02 03 4D 61 70 10 02 4D 50 0D 01 4E 0A 02 4F
   48 01 09 69 6D 6D 75 74 61 62 6C 65 09 02 51 4E
   02 06 42 69 74 53 65 74 08 07 53 00 FFFFFFC2 FFFFFF80 FFFFFF86 00
   54 01 07 64 65 66 61 75 6C 74 15 01 55 10 03 14
   40 4C 08 05 57 00 FFFFFF84 02 58 01 07 69 73 46 69 6E
   61 6C 14 02 59 5C 10 02 14 5A 09 02 5B 06 02 07
   42 6F 6F 6C 65 61 6E 08 05 5D 56 FFFFFFC0 00 2A 01 05
   73 74 61 74 65 08 05 5F 00 FFFFFF84 02 60 01 08 66 69
   6E 61 6C 54 61 67 14 02 2A 61 08 05 5D 5E FFFFFFC0 00
   2A 08 05 63 00 FFFFFF84 02 64 01 0D 63 6F 6E 74 61 69
   6E 73 46 69 6E 61 6C 14 02 59 65 08 05 66 62 FFFFFFC0
   00 4C 01 01 51 08 05 68 00 FFFFFF84 02 69 01 07 69 73
   45 6D 70 74 79 15 01 59 08 05 6B 00 FFFFFF84 00 6C 01
   04 6E 65 78 74 14 03 4C 6D 6F 08 05 6E 6A FFFFFFC0 00
   2A 01 01 71 08 05 70 6A FFFFFFC0 00 1C 01 01 61 08 05
   6B 00 FFFFFF84 00 72 14 03 4C 73 74 08 05 66 71 FFFFFFC0 00
   4C 08 05 70 71 FFFFFFC0 00 1C 08 05 76 00 FFFFFF84 00 77 01
   0B 6E 65 78 74 44 65 66 61 75 6C 74 14 02 4C 78
   08 05 66 75 FFFFFFC0 00 4C 08 05 6B 00 FFFFFF84 04 7A 14 03
   4C 7B 7C 08 05 66 79 FFFFFFC0 00 4C 08 05 7D 79 FFFFFFC0 00
   7E 01 01 66 10 04 14 7F 2A 4C 09 03 FFFFFF81 00 06 02
   09 46 75 6E 63 74 69 6F 6E 31 08 07 FFFFFF81 02 00 FFFFFF84
   20 FFFFFF81 03 01 08 74 6F 53 74 72 69 6E 67 14 02 FFFFFF81
   04 10 04 FFFFFF81 05 FFFFFF81 08 0E 03 14 FFFFFF81 06 09 03 FFFFFF81 07
   06 01 06 50 72 65 64 65 66 09 04 FFFFFF81 09 FFFFFF81 0A 02
   06 53 74 72 69 6E 67 0A 03 FFFFFF81 07 06 
  InnerClass: 
   public final #227= #42 of #30; //$anonfun$1=class scala/util/automata/NondetWordAutom$$anonfun$1 of class scala/util/automata/NondetWordAutom
   public final #228= #88 of #30; //$anonfun$3=class scala/util/automata/NondetWordAutom$$anonfun$3 of class scala/util/automata/NondetWordAutom
   public final #229= #53 of #30; //$anonfun$2=class scala/util/automata/NondetWordAutom$$anonfun$2 of class scala/util/automata/NondetWordAutom
   public final #230= #161 of #30; //$anonfun$next$2=class scala/util/automata/NondetWordAutom$$anonfun$next$2 of class scala/util/automata/NondetWordAutom
   public final #231= #178 of #30; //$anonfun$next$1=class scala/util/automata/NondetWordAutom$$anonfun$next$1 of class scala/util/automata/NondetWordAutom
   public final #232= #138 of #30; //$anonfun$next$3=class scala/util/automata/NondetWordAutom$$anonfun$next$3 of class scala/util/automata/NondetWordAutom
   public final #233= #195 of #30; //$anonfun$isEmpty$1=class scala/util/automata/NondetWordAutom$$anonfun$isEmpty$1 of class scala/util/automata/NondetWordAutom
   public final #234= #206 of #30; //$anonfun$containsFinal$1=class scala/util/automata/NondetWordAutom$$anonfun$containsFinal$1 of class scala/util/automata/NondetWordAutom
  minor version: 0
  major version: 49
  Constant pool:
const #1 = Asciz	SourceFile;
const #2 = Asciz	NondetWordAutom.scala;
const #3 = Asciz	<init>;
const #4 = Asciz	()V;
const #5 = Asciz	Code;
const #6 = Asciz	LineNumberTable;
const #7 = Asciz	java/lang/Object;
const #8 = class	#7;	//  java/lang/Object
const #9 = NameAndType	#3:#4;//  "<init>":()V
const #10 = Method	#8.#9;	//  java/lang/Object."<init>":()V
const #11 = Asciz	Signature;
const #12 = Asciz	toString;
const #13 = Asciz	()Ljava/lang/String;;
const #14 = Asciz	scala/collection/Map$;
const #15 = class	#14;	//  scala/collection/Map$
const #16 = Asciz	MODULE$;
const #17 = Asciz	Lscala/collection/Map$;;
const #18 = NameAndType	#16:#17;//  MODULE$:Lscala/collection/Map$;
const #19 = Field	#15.#18;	//  scala/collection/Map$.MODULE$:Lscala/collection/Map$;
const #20 = Asciz	scala/Predef$;
const #21 = class	#20;	//  scala/Predef$
const #22 = Asciz	Lscala/Predef$;;
const #23 = NameAndType	#16:#22;//  MODULE$:Lscala/Predef$;
const #24 = Field	#21.#23;	//  scala/Predef$.MODULE$:Lscala/Predef$;
const #25 = Asciz	intWrapper;
const #26 = Asciz	(I)Lscala/runtime/RichInt;;
const #27 = NameAndType	#25:#26;//  intWrapper:(I)Lscala/runtime/RichInt;
const #28 = Method	#21.#27;	//  scala/Predef$.intWrapper:(I)Lscala/runtime/RichInt;
const #29 = Asciz	scala/util/automata/NondetWordAutom;
const #30 = class	#29;	//  scala/util/automata/NondetWordAutom
const #31 = Asciz	nstates;
const #32 = Asciz	()I;
const #33 = NameAndType	#31:#32;//  nstates:()I
const #34 = Method	#30.#33;	//  scala/util/automata/NondetWordAutom.nstates:()I
const #35 = Asciz	scala/runtime/RichInt;
const #36 = class	#35;	//  scala/runtime/RichInt
const #37 = Asciz	until;
const #38 = Asciz	(I)Lscala/Range;;
const #39 = NameAndType	#37:#38;//  until:(I)Lscala/Range;
const #40 = Method	#36.#39;	//  scala/runtime/RichInt.until:(I)Lscala/Range;
const #41 = Asciz	scala/util/automata/NondetWordAutom$$anonfun$1;
const #42 = class	#41;	//  scala/util/automata/NondetWordAutom$$anonfun$1
const #43 = Asciz	(Lscala/util/automata/NondetWordAutom;)V;
const #44 = NameAndType	#3:#43;//  "<init>":(Lscala/util/automata/NondetWordAutom;)V
const #45 = Method	#42.#44;	//  scala/util/automata/NondetWordAutom$$anonfun$1."<init>":(Lscala/util/automata/NondetWordAutom;)V
const #46 = Asciz	scala/collection/generic/TraversableViewTemplate;
const #47 = class	#46;	//  scala/collection/generic/TraversableViewTemplate
const #48 = Asciz	filter;
const #49 = Asciz	(Lscala/Function1;)Lscala/collection/generic/TraversableView;;
const #50 = NameAndType	#48:#49;//  filter:(Lscala/Function1;)Lscala/collection/generic/TraversableView;
const #51 = InterfaceMethod	#47.#50;	//  scala/collection/generic/TraversableViewTemplate.filter:(Lscala/Function1;)Lscala/collection/generic/TraversableView;
const #52 = Asciz	scala/util/automata/NondetWordAutom$$anonfun$2;
const #53 = class	#52;	//  scala/util/automata/NondetWordAutom$$anonfun$2
const #54 = Method	#53.#44;	//  scala/util/automata/NondetWordAutom$$anonfun$2."<init>":(Lscala/util/automata/NondetWordAutom;)V
const #55 = Asciz	scala/collection/generic/VectorView$;
const #56 = class	#55;	//  scala/collection/generic/VectorView$
const #57 = Asciz	Lscala/collection/generic/VectorView$;;
const #58 = NameAndType	#16:#57;//  MODULE$:Lscala/collection/generic/VectorView$;
const #59 = Field	#56.#58;	//  scala/collection/generic/VectorView$.MODULE$:Lscala/collection/generic/VectorView$;
const #60 = Asciz	builderFactory;
const #61 = Asciz	()Lscala/collection/generic/BuilderFactory;;
const #62 = NameAndType	#60:#61;//  builderFactory:()Lscala/collection/generic/BuilderFactory;
const #63 = Method	#56.#62;	//  scala/collection/generic/VectorView$.builderFactory:()Lscala/collection/generic/BuilderFactory;
const #64 = Asciz	map;
const #65 = Asciz	(Lscala/Function1;Lscala/collection/generic/BuilderFactory;)Ljava/lang/Object;;
const #66 = NameAndType	#64:#65;//  map:(Lscala/Function1;Lscala/collection/generic/BuilderFactory;)Ljava/lang/Object;
const #67 = InterfaceMethod	#47.#66;	//  scala/collection/generic/TraversableViewTemplate.map:(Lscala/Function1;Lscala/collection/generic/BuilderFactory;)Ljava/lang/Object;
const #68 = Asciz	scala/collection/Sequence;
const #69 = class	#68;	//  scala/collection/Sequence
const #70 = Asciz	scala/runtime/ScalaRunTime$;
const #71 = class	#70;	//  scala/runtime/ScalaRunTime$
const #72 = Asciz	Lscala/runtime/ScalaRunTime$;;
const #73 = NameAndType	#16:#72;//  MODULE$:Lscala/runtime/ScalaRunTime$;
const #74 = Field	#71.#73;	//  scala/runtime/ScalaRunTime$.MODULE$:Lscala/runtime/ScalaRunTime$;
const #75 = Asciz	boxArray;
const #76 = Asciz	(Ljava/lang/Object;)Lscala/runtime/BoxedArray;;
const #77 = NameAndType	#75:#76;//  boxArray:(Ljava/lang/Object;)Lscala/runtime/BoxedArray;
const #78 = Method	#71.#77;	//  scala/runtime/ScalaRunTime$.boxArray:(Ljava/lang/Object;)Lscala/runtime/BoxedArray;
const #79 = Asciz	apply;
const #80 = Asciz	(Lscala/collection/Sequence;)Lscala/collection/Map;;
const #81 = NameAndType	#79:#80;//  apply:(Lscala/collection/Sequence;)Lscala/collection/Map;
const #82 = Method	#15.#81;	//  scala/collection/Map$.apply:(Lscala/collection/Sequence;)Lscala/collection/Map;
const #83 = Asciz	scala/collection/generic/MapTemplate;
const #84 = class	#83;	//  scala/collection/generic/MapTemplate
const #85 = NameAndType	#12:#13;//  toString:()Ljava/lang/String;
const #86 = InterfaceMethod	#84.#85;	//  scala/collection/generic/MapTemplate.toString:()Ljava/lang/String;
const #87 = Asciz	scala/util/automata/NondetWordAutom$$anonfun$3;
const #88 = class	#87;	//  scala/util/automata/NondetWordAutom$$anonfun$3
const #89 = Method	#88.#44;	//  scala/util/automata/NondetWordAutom$$anonfun$3."<init>":(Lscala/util/automata/NondetWordAutom;)V
const #90 = Asciz	scala/collection/generic/TraversableTemplate;
const #91 = class	#90;	//  scala/collection/generic/TraversableTemplate
const #92 = Asciz	mkString;
const #93 = NameAndType	#92:#13;//  mkString:()Ljava/lang/String;
const #94 = InterfaceMethod	#91.#93;	//  scala/collection/generic/TraversableTemplate.mkString:()Ljava/lang/String;
const #95 = Asciz	[NondetWordAutom  nstates=%d  finals=%s  delta=\n%s;
const #96 = String	#95;	//  [NondetWordAutom  nstates=%d  finals=%s  delta=\n%s
const #97 = Asciz	stringWrapper;
const #98 = Asciz	(Ljava/lang/String;)Lscala/runtime/RichString;;
const #99 = NameAndType	#97:#98;//  stringWrapper:(Ljava/lang/String;)Lscala/runtime/RichString;
const #100 = Method	#21.#99;	//  scala/Predef$.stringWrapper:(Ljava/lang/String;)Lscala/runtime/RichString;
const #101 = Asciz	scala/runtime/BoxesRunTime;
const #102 = class	#101;	//  scala/runtime/BoxesRunTime
const #103 = Asciz	boxToInteger;
const #104 = Asciz	(I)Ljava/lang/Integer;;
const #105 = NameAndType	#103:#104;//  boxToInteger:(I)Ljava/lang/Integer;
const #106 = Method	#102.#105;	//  scala/runtime/BoxesRunTime.boxToInteger:(I)Ljava/lang/Integer;
const #107 = Asciz	scala/runtime/RichString;
const #108 = class	#107;	//  scala/runtime/RichString
const #109 = Asciz	format;
const #110 = Asciz	(Lscala/collection/Sequence;)Ljava/lang/String;;
const #111 = NameAndType	#109:#110;//  format:(Lscala/collection/Sequence;)Ljava/lang/String;
const #112 = Method	#108.#111;	//  scala/runtime/RichString.format:(Lscala/collection/Sequence;)Ljava/lang/String;
const #113 = Asciz	this;
const #114 = Asciz	Lscala/util/automata/NondetWordAutom;;
const #115 = Asciz	finalString;
const #116 = Asciz	Ljava/lang/String;;
const #117 = Asciz	deltaString;
const #118 = Asciz	LocalVariableTable;
const #119 = Asciz	next;
const #120 = Asciz	(Lscala/collection/immutable/BitSet;Lscala/Function1;)Lscala/collection/immutable/BitSet;;
const #121 = Asciz	scala/collection/immutable/Set$;
const #122 = class	#121;	//  scala/collection/immutable/Set$
const #123 = Asciz	Lscala/collection/immutable/Set$;;
const #124 = NameAndType	#16:#123;//  MODULE$:Lscala/collection/immutable/Set$;
const #125 = Field	#122.#124;	//  scala/collection/immutable/Set$.MODULE$:Lscala/collection/immutable/Set$;
const #126 = Method	#122.#62;	//  scala/collection/immutable/Set$.builderFactory:()Lscala/collection/generic/BuilderFactory;
const #127 = InterfaceMethod	#91.#66;	//  scala/collection/generic/TraversableTemplate.map:(Lscala/Function1;Lscala/collection/generic/BuilderFactory;)Ljava/lang/Object;
const #128 = Asciz	scala/collection/immutable/BitSet$;
const #129 = class	#128;	//  scala/collection/immutable/BitSet$
const #130 = Asciz	Lscala/collection/immutable/BitSet$;;
const #131 = NameAndType	#16:#130;//  MODULE$:Lscala/collection/immutable/BitSet$;
const #132 = Field	#129.#131;	//  scala/collection/immutable/BitSet$.MODULE$:Lscala/collection/immutable/BitSet$;
const #133 = Asciz	empty;
const #134 = Asciz	()Lscala/collection/immutable/BitSet;;
const #135 = NameAndType	#133:#134;//  empty:()Lscala/collection/immutable/BitSet;
const #136 = Method	#129.#135;	//  scala/collection/immutable/BitSet$.empty:()Lscala/collection/immutable/BitSet;
const #137 = Asciz	scala/util/automata/NondetWordAutom$$anonfun$next$3;
const #138 = class	#137;	//  scala/util/automata/NondetWordAutom$$anonfun$next$3
const #139 = Method	#138.#44;	//  scala/util/automata/NondetWordAutom$$anonfun$next$3."<init>":(Lscala/util/automata/NondetWordAutom;)V
const #140 = Asciz	foldLeft;
const #141 = Asciz	(Ljava/lang/Object;Lscala/Function2;)Ljava/lang/Object;;
const #142 = NameAndType	#140:#141;//  foldLeft:(Ljava/lang/Object;Lscala/Function2;)Ljava/lang/Object;
const #143 = InterfaceMethod	#91.#142;	//  scala/collection/generic/TraversableTemplate.foldLeft:(Ljava/lang/Object;Lscala/Function2;)Ljava/lang/Object;
const #144 = Asciz	scala/collection/immutable/BitSet;
const #145 = class	#144;	//  scala/collection/immutable/BitSet
const #146 = Asciz	Q;
const #147 = Asciz	Lscala/collection/immutable/BitSet;;
const #148 = Asciz	f;
const #149 = Asciz	Lscala/Function1;;
const #150 = Asciz	(Lscala/collection/immutable/BitSet;Lscala/Function1<Ljava/lang/Integer;Lscala/collection/immutable/BitSet;>;)Lscala/collection/immutable/BitSet;;
const #151 = Asciz	nextDefault;
const #152 = Asciz	(Lscala/collection/immutable/BitSet;)Lscala/collection/immutable/BitSet;;
const #153 = Asciz	default;
const #154 = Asciz	()[Lscala/collection/immutable/BitSet;;
const #155 = NameAndType	#153:#154;//  default:()[Lscala/collection/immutable/BitSet;
const #156 = Method	#30.#155;	//  scala/util/automata/NondetWordAutom.default:()[Lscala/collection/immutable/BitSet;
const #157 = NameAndType	#119:#120;//  next:(Lscala/collection/immutable/BitSet;Lscala/Function1;)Lscala/collection/immutable/BitSet;
const #158 = Method	#30.#157;	//  scala/util/automata/NondetWordAutom.next:(Lscala/collection/immutable/BitSet;Lscala/Function1;)Lscala/collection/immutable/BitSet;
const #159 = Asciz	(Lscala/collection/immutable/BitSet;Ljava/lang/Object;)Lscala/collection/immutable/BitSet;;
const #160 = Asciz	scala/util/automata/NondetWordAutom$$anonfun$next$2;
const #161 = class	#160;	//  scala/util/automata/NondetWordAutom$$anonfun$next$2
const #162 = Asciz	(Lscala/util/automata/NondetWordAutom;Ljava/lang/Object;)V;
const #163 = NameAndType	#3:#162;//  "<init>":(Lscala/util/automata/NondetWordAutom;Ljava/lang/Object;)V
const #164 = Method	#161.#163;	//  scala/util/automata/NondetWordAutom$$anonfun$next$2."<init>":(Lscala/util/automata/NondetWordAutom;Ljava/lang/Object;)V
const #165 = Asciz	a$1;
const #166 = Asciz	Ljava/lang/Object;;
const #167 = Asciz	(Lscala/collection/immutable/BitSet;TT;)Lscala/collection/immutable/BitSet;;
const #168 = Asciz	(ILjava/lang/Object;)Lscala/collection/immutable/BitSet;;
const #169 = Asciz	delta;
const #170 = Asciz	()[Lscala/collection/Map;;
const #171 = NameAndType	#169:#170;//  delta:()[Lscala/collection/Map;
const #172 = Method	#30.#171;	//  scala/util/automata/NondetWordAutom.delta:()[Lscala/collection/Map;
const #173 = Asciz	get;
const #174 = Asciz	(Ljava/lang/Object;)Lscala/Option;;
const #175 = NameAndType	#173:#174;//  get:(Ljava/lang/Object;)Lscala/Option;
const #176 = InterfaceMethod	#84.#175;	//  scala/collection/generic/MapTemplate.get:(Ljava/lang/Object;)Lscala/Option;
const #177 = Asciz	scala/util/automata/NondetWordAutom$$anonfun$next$1;
const #178 = class	#177;	//  scala/util/automata/NondetWordAutom$$anonfun$next$1
const #179 = Asciz	(Lscala/util/automata/NondetWordAutom;I)V;
const #180 = NameAndType	#3:#179;//  "<init>":(Lscala/util/automata/NondetWordAutom;I)V
const #181 = Method	#178.#180;	//  scala/util/automata/NondetWordAutom$$anonfun$next$1."<init>":(Lscala/util/automata/NondetWordAutom;I)V
const #182 = Asciz	scala/Option;
const #183 = class	#182;	//  scala/Option
const #184 = Asciz	getOrElse;
const #185 = Asciz	(Lscala/Function0;)Ljava/lang/Object;;
const #186 = NameAndType	#184:#185;//  getOrElse:(Lscala/Function0;)Ljava/lang/Object;
const #187 = Method	#183.#186;	//  scala/Option.getOrElse:(Lscala/Function0;)Ljava/lang/Object;
const #188 = Asciz	q$1;
const #189 = Asciz	I;
const #190 = Asciz	a;
const #191 = Asciz	(ITT;)Lscala/collection/immutable/BitSet;;
const #192 = Asciz	isEmpty;
const #193 = Asciz	()Z;
const #194 = Asciz	scala/util/automata/NondetWordAutom$$anonfun$isEmpty$1;
const #195 = class	#194;	//  scala/util/automata/NondetWordAutom$$anonfun$isEmpty$1
const #196 = Method	#195.#44;	//  scala/util/automata/NondetWordAutom$$anonfun$isEmpty$1."<init>":(Lscala/util/automata/NondetWordAutom;)V
const #197 = Asciz	scala/collection/generic/VectorTemplate;
const #198 = class	#197;	//  scala/collection/generic/VectorTemplate
const #199 = Asciz	forall;
const #200 = Asciz	(Lscala/Function1;)Z;
const #201 = NameAndType	#199:#200;//  forall:(Lscala/Function1;)Z
const #202 = InterfaceMethod	#198.#201;	//  scala/collection/generic/VectorTemplate.forall:(Lscala/Function1;)Z
const #203 = Asciz	containsFinal;
const #204 = Asciz	(Lscala/collection/immutable/BitSet;)Z;
const #205 = Asciz	scala/util/automata/NondetWordAutom$$anonfun$containsFinal$1;
const #206 = class	#205;	//  scala/util/automata/NondetWordAutom$$anonfun$containsFinal$1
const #207 = Method	#206.#44;	//  scala/util/automata/NondetWordAutom$$anonfun$containsFinal$1."<init>":(Lscala/util/automata/NondetWordAutom;)V
const #208 = Asciz	exists;
const #209 = NameAndType	#208:#200;//  exists:(Lscala/Function1;)Z
const #210 = InterfaceMethod	#91.#209;	//  scala/collection/generic/TraversableTemplate.exists:(Lscala/Function1;)Z
const #211 = Asciz	finalTag;
const #212 = Asciz	(I)I;
const #213 = Asciz	finals;
const #214 = Asciz	()[I;
const #215 = NameAndType	#213:#214;//  finals:()[I
const #216 = Method	#30.#215;	//  scala/util/automata/NondetWordAutom.finals:()[I
const #217 = Asciz	state;
const #218 = Asciz	isFinal;
const #219 = Asciz	(I)Z;
const #220 = Asciz	()[Lscala/collection/Map<TT;Lscala/collection/immutable/BitSet;>;;
const #221 = Asciz	labels;
const #222 = Asciz	()Lscala/collection/Sequence;;
const #223 = Asciz	()Lscala/collection/Sequence<TT;>;;
const #224 = Asciz	<T:Ljava/lang/Object;>Ljava/lang/Object;Lscala/ScalaObject;;
const #225 = Asciz	ScalaSig;
const #226 = Asciz	InnerClasses;
const #227 = Asciz	$anonfun$1;
const #228 = Asciz	$anonfun$3;
const #229 = Asciz	$anonfun$2;
const #230 = Asciz	$anonfun$next$2;
const #231 = Asciz	$anonfun$next$1;
const #232 = Asciz	$anonfun$next$3;
const #233 = Asciz	$anonfun$isEmpty$1;
const #234 = Asciz	$anonfun$containsFinal$1;
const #235 = Asciz	scala/ScalaObject;
const #236 = class	#235;	//  scala/ScalaObject

{
public scala.util.automata.NondetWordAutom();
  Code:
   Stack=1, Locals=1, Args_size=1
   0:	aload_0
   1:	invokespecial	#10; //Method java/lang/Object."<init>":()V
   4:	return
  LineNumberTable: 
   line 24: 0

  Signature: length = 0x2
   00 04 

public java.lang.String toString();
  Code:
   Stack=6, Locals=5, Args_size=1
   0:	getstatic	#19; //Field scala/collection/Map$.MODULE$:Lscala/collection/Map$;
   3:	getstatic	#24; //Field scala/Predef$.MODULE$:Lscala/Predef$;
   6:	iconst_0
   7:	invokevirtual	#28; //Method scala/Predef$.intWrapper:(I)Lscala/runtime/RichInt;
   10:	aload_0
   11:	invokevirtual	#34; //Method nstates:()I
   14:	invokevirtual	#40; //Method scala/runtime/RichInt.until:(I)Lscala/Range;
   17:	new	#42; //class scala/util/automata/NondetWordAutom$$anonfun$1
   20:	dup
   21:	aload_0
   22:	invokespecial	#45; //Method scala/util/automata/NondetWordAutom$$anonfun$1."<init>":(Lscala/util/automata/NondetWordAutom;)V
   25:	invokeinterface	#51,  2; //InterfaceMethod scala/collection/generic/TraversableViewTemplate.filter:(Lscala/Function1;)Lscala/collection/generic/TraversableView;
   30:	new	#53; //class scala/util/automata/NondetWordAutom$$anonfun$2
   33:	dup
   34:	aload_0
   35:	invokespecial	#54; //Method scala/util/automata/NondetWordAutom$$anonfun$2."<init>":(Lscala/util/automata/NondetWordAutom;)V
   38:	getstatic	#59; //Field scala/collection/generic/VectorView$.MODULE$:Lscala/collection/generic/VectorView$;
   41:	invokevirtual	#63; //Method scala/collection/generic/VectorView$.builderFactory:()Lscala/collection/generic/BuilderFactory;
   44:	invokeinterface	#67,  3; //InterfaceMethod scala/collection/generic/TraversableViewTemplate.map:(Lscala/Function1;Lscala/collection/generic/BuilderFactory;)Ljava/lang/Object;
   49:	astore_2
   50:	aload_2
   51:	instanceof	#69; //class scala/collection/Sequence
   54:	ifeq	61
   57:	aload_2
   58:	goto	68
   61:	getstatic	#74; //Field scala/runtime/ScalaRunTime$.MODULE$:Lscala/runtime/ScalaRunTime$;
   64:	aload_2
   65:	invokevirtual	#78; //Method scala/runtime/ScalaRunTime$.boxArray:(Ljava/lang/Object;)Lscala/runtime/BoxedArray;
   68:	checkcast	#69; //class scala/collection/Sequence
   71:	invokevirtual	#82; //Method scala/collection/Map$.apply:(Lscala/collection/Sequence;)Lscala/collection/Map;
   74:	invokeinterface	#86,  1; //InterfaceMethod scala/collection/generic/MapTemplate.toString:()Ljava/lang/String;
   79:	astore_1
   80:	getstatic	#24; //Field scala/Predef$.MODULE$:Lscala/Predef$;
   83:	iconst_0
   84:	invokevirtual	#28; //Method scala/Predef$.intWrapper:(I)Lscala/runtime/RichInt;
   87:	aload_0
   88:	invokevirtual	#34; //Method nstates:()I
   91:	invokevirtual	#40; //Method scala/runtime/RichInt.until:(I)Lscala/Range;
   94:	new	#88; //class scala/util/automata/NondetWordAutom$$anonfun$3
   97:	dup
   98:	aload_0
   99:	invokespecial	#89; //Method scala/util/automata/NondetWordAutom$$anonfun$3."<init>":(Lscala/util/automata/NondetWordAutom;)V
   102:	getstatic	#59; //Field scala/collection/generic/VectorView$.MODULE$:Lscala/collection/generic/VectorView$;
   105:	invokevirtual	#63; //Method scala/collection/generic/VectorView$.builderFactory:()Lscala/collection/generic/BuilderFactory;
   108:	invokeinterface	#67,  3; //InterfaceMethod scala/collection/generic/TraversableViewTemplate.map:(Lscala/Function1;Lscala/collection/generic/BuilderFactory;)Ljava/lang/Object;
   113:	astore	4
   115:	aload	4
   117:	instanceof	#91; //class scala/collection/generic/TraversableTemplate
   120:	ifeq	128
   123:	aload	4
   125:	goto	136
   128:	getstatic	#74; //Field scala/runtime/ScalaRunTime$.MODULE$:Lscala/runtime/ScalaRunTime$;
   131:	aload	4
   133:	invokevirtual	#78; //Method scala/runtime/ScalaRunTime$.boxArray:(Ljava/lang/Object;)Lscala/runtime/BoxedArray;
   136:	checkcast	#91; //class scala/collection/generic/TraversableTemplate
   139:	invokeinterface	#94,  1; //InterfaceMethod scala/collection/generic/TraversableTemplate.mkString:()Ljava/lang/String;
   144:	astore_3
   145:	getstatic	#24; //Field scala/Predef$.MODULE$:Lscala/Predef$;
   148:	ldc	#96; //String [NondetWordAutom  nstates=%d  finals=%s  delta=\n%s
   150:	invokevirtual	#100; //Method scala/Predef$.stringWrapper:(Ljava/lang/String;)Lscala/runtime/RichString;
   153:	getstatic	#74; //Field scala/runtime/ScalaRunTime$.MODULE$:Lscala/runtime/ScalaRunTime$;
   156:	iconst_3
   157:	anewarray	#8; //class java/lang/Object
   160:	dup
   161:	iconst_0
   162:	aload_0
   163:	invokevirtual	#34; //Method nstates:()I
   166:	invokestatic	#106; //Method scala/runtime/BoxesRunTime.boxToInteger:(I)Ljava/lang/Integer;
   169:	aastore
   170:	dup
   171:	iconst_1
   172:	aload_1
   173:	aastore
   174:	dup
   175:	iconst_2
   176:	aload_3
   177:	aastore
   178:	invokevirtual	#78; //Method scala/runtime/ScalaRunTime$.boxArray:(Ljava/lang/Object;)Lscala/runtime/BoxedArray;
   181:	invokevirtual	#112; //Method scala/runtime/RichString.format:(Lscala/collection/Sequence;)Ljava/lang/String;
   184:	areturn
  LineNumberTable: 
   line 55: 0
   line 57: 68
   line 55: 71
   line 56: 80
   line 57: 94
   line 56: 144
   line 59: 145

  LocalVariableTable: 
   Start  Length  Slot  Name   Signature
   0      185      0    this       Lscala/util/automata/NondetWordAutom;
   80      104      1    finalString       Ljava/lang/String;
   145      39      3    deltaString       Ljava/lang/String;


public scala.collection.immutable.BitSet nextDefault(scala.collection.immutable.BitSet);
  Code:
   Stack=4, Locals=2, Args_size=2
   0:	aload_0
   1:	aload_1
   2:	getstatic	#74; //Field scala/runtime/ScalaRunTime$.MODULE$:Lscala/runtime/ScalaRunTime$;
   5:	aload_0
   6:	invokevirtual	#156; //Method default:()[Lscala/collection/immutable/BitSet;
   9:	invokevirtual	#78; //Method scala/runtime/ScalaRunTime$.boxArray:(Ljava/lang/Object;)Lscala/runtime/BoxedArray;
   12:	invokespecial	#158; //Method next:(Lscala/collection/immutable/BitSet;Lscala/Function1;)Lscala/collection/immutable/BitSet;
   15:	areturn
  LineNumberTable: 
   line 49: 0

  LocalVariableTable: 
   Start  Length  Slot  Name   Signature
   0      16      0    this       Lscala/util/automata/NondetWordAutom;
   0      16      1    Q       Lscala/collection/immutable/BitSet;


public scala.collection.immutable.BitSet next(scala.collection.immutable.BitSet, java.lang.Object);
  Code:
   Stack=6, Locals=3, Args_size=3
   0:	aload_0
   1:	aload_1
   2:	new	#161; //class scala/util/automata/NondetWordAutom$$anonfun$next$2
   5:	dup
   6:	aload_0
   7:	aload_2
   8:	invokespecial	#164; //Method scala/util/automata/NondetWordAutom$$anonfun$next$2."<init>":(Lscala/util/automata/NondetWordAutom;Ljava/lang/Object;)V
   11:	invokespecial	#158; //Method next:(Lscala/collection/immutable/BitSet;Lscala/Function1;)Lscala/collection/immutable/BitSet;
   14:	areturn
  LineNumberTable: 
   line 48: 0

  LocalVariableTable: 
   Start  Length  Slot  Name   Signature
   0      15      0    this       Lscala/util/automata/NondetWordAutom;
   0      15      1    Q       Lscala/collection/immutable/BitSet;
   0      15      2    a$1       Ljava/lang/Object;

  Signature: length = 0x2
   00 FFFFFFA7 

public scala.collection.immutable.BitSet next(int, java.lang.Object);
  Code:
   Stack=5, Locals=3, Args_size=3
   0:	aload_0
   1:	invokevirtual	#172; //Method delta:()[Lscala/collection/Map;
   4:	iload_1
   5:	aaload
   6:	aload_2
   7:	invokeinterface	#176,  2; //InterfaceMethod scala/collection/generic/MapTemplate.get:(Ljava/lang/Object;)Lscala/Option;
   12:	new	#178; //class scala/util/automata/NondetWordAutom$$anonfun$next$1
   15:	dup
   16:	aload_0
   17:	iload_1
   18:	invokespecial	#181; //Method scala/util/automata/NondetWordAutom$$anonfun$next$1."<init>":(Lscala/util/automata/NondetWordAutom;I)V
   21:	invokevirtual	#187; //Method scala/Option.getOrElse:(Lscala/Function0;)Ljava/lang/Object;
   24:	checkcast	#145; //class scala/collection/immutable/BitSet
   27:	areturn
  LineNumberTable: 
   line 45: 0

  LocalVariableTable: 
   Start  Length  Slot  Name   Signature
   0      28      0    this       Lscala/util/automata/NondetWordAutom;
   0      28      1    q$1       I
   0      28      2    a       Ljava/lang/Object;

  Signature: length = 0x2
   00 FFFFFFBF 

public final boolean isEmpty();
  Code:
   Stack=4, Locals=1, Args_size=1
   0:	getstatic	#24; //Field scala/Predef$.MODULE$:Lscala/Predef$;
   3:	iconst_0
   4:	invokevirtual	#28; //Method scala/Predef$.intWrapper:(I)Lscala/runtime/RichInt;
   7:	aload_0
   8:	invokevirtual	#34; //Method nstates:()I
   11:	invokevirtual	#40; //Method scala/runtime/RichInt.until:(I)Lscala/Range;
   14:	new	#195; //class scala/util/automata/NondetWordAutom$$anonfun$isEmpty$1
   17:	dup
   18:	aload_0
   19:	invokespecial	#196; //Method scala/util/automata/NondetWordAutom$$anonfun$isEmpty$1."<init>":(Lscala/util/automata/NondetWordAutom;)V
   22:	invokeinterface	#202,  2; //InterfaceMethod scala/collection/generic/VectorTemplate.forall:(Lscala/Function1;)Z
   27:	ireturn
  LineNumberTable: 
   line 42: 0


public final boolean containsFinal(scala.collection.immutable.BitSet);
  Code:
   Stack=4, Locals=2, Args_size=2
   0:	aload_1
   1:	new	#206; //class scala/util/automata/NondetWordAutom$$anonfun$containsFinal$1
   4:	dup
   5:	aload_0
   6:	invokespecial	#207; //Method scala/util/automata/NondetWordAutom$$anonfun$containsFinal$1."<init>":(Lscala/util/automata/NondetWordAutom;)V
   9:	invokeinterface	#210,  2; //InterfaceMethod scala/collection/generic/TraversableTemplate.exists:(Lscala/Function1;)Z
   14:	ireturn
  LineNumberTable: 
   line 39: 0

  LocalVariableTable: 
   Start  Length  Slot  Name   Signature
   0      15      0    this       Lscala/util/automata/NondetWordAutom;
   0      15      1    Q       Lscala/collection/immutable/BitSet;


public final int finalTag(int);
  Code:
   Stack=2, Locals=2, Args_size=2
   0:	aload_0
   1:	invokevirtual	#216; //Method finals:()[I
   4:	iload_1
   5:	iaload
   6:	ireturn
  LineNumberTable: 
   line 36: 0

  LocalVariableTable: 
   Start  Length  Slot  Name   Signature
   0      7      0    this       Lscala/util/automata/NondetWordAutom;
   0      7      1    state       I


public final boolean isFinal(int);
  Code:
   Stack=2, Locals=2, Args_size=2
   0:	aload_0
   1:	invokevirtual	#216; //Method finals:()[I
   4:	iload_1
   5:	iaload
   6:	iconst_0
   7:	if_icmple	14
   10:	iconst_1
   11:	goto	15
   14:	iconst_0
   15:	ireturn
  LineNumberTable: 
   line 33: 0

  LocalVariableTable: 
   Start  Length  Slot  Name   Signature
   0      16      0    this       Lscala/util/automata/NondetWordAutom;
   0      16      1    state       I


public abstract scala.collection.immutable.BitSet[] default();

public abstract scala.collection.Map[] delta();
  Signature: length = 0x2
   00 FFFFFFDC 

public abstract int[] finals();

public abstract scala.collection.Sequence labels();
  Signature: length = 0x2
   00 FFFFFFDF 

public abstract int nstates();

}

