Compiled from "NondetWordAutom.scala"
public final class scala.util.automata.NondetWordAutom$$anonfun$finalStates$1 extends scala.runtime.AbstractFunction1 implements java.io.Serializable
  SourceFile: "NondetWordAutom.scala"
  Scala: length = 0x
   
  InnerClass: 
   public final #55= #9 of #49; //$anonfun$finalStates$1=class scala/util/automata/NondetWordAutom$$anonfun$finalStates$1 of class scala/util/automata/NondetWordAutom
  minor version: 0
  major version: 49
  Constant pool:
const #1 = Asciz	SourceFile;
const #2 = Asciz	NondetWordAutom.scala;
const #3 = Asciz	<clinit>;
const #4 = Asciz	()V;
const #5 = Asciz	Code;
const #6 = Asciz	serialVersionUID;
const #7 = Asciz	J;
const #8 = Asciz	scala/util/automata/NondetWordAutom$$anonfun$finalStates$1;
const #9 = class	#8;	//  scala/util/automata/NondetWordAutom$$anonfun$finalStates$1
const #10 = NameAndType	#6:#7;//  serialVersionUID:J
const #11 = Field	#9.#10;	//  scala/util/automata/NondetWordAutom$$anonfun$finalStates$1.serialVersionUID:J
const #12 = Asciz	$outer;
const #13 = Asciz	Lscala/util/automata/NondetWordAutom;;
const #14 = Asciz	<init>;
const #15 = Asciz	(Lscala/util/automata/NondetWordAutom;)V;
const #16 = Asciz	LineNumberTable;
const #17 = Asciz	java/lang/NullPointerException;
const #18 = class	#17;	//  java/lang/NullPointerException
const #19 = NameAndType	#14:#4;//  "<init>":()V
const #20 = Method	#18.#19;	//  java/lang/NullPointerException."<init>":()V
const #21 = NameAndType	#12:#13;//  $outer:Lscala/util/automata/NondetWordAutom;
const #22 = Field	#9.#21;	//  scala/util/automata/NondetWordAutom$$anonfun$finalStates$1.$outer:Lscala/util/automata/NondetWordAutom;
const #23 = Asciz	scala/runtime/AbstractFunction1;
const #24 = class	#23;	//  scala/runtime/AbstractFunction1
const #25 = Method	#24.#19;	//  scala/runtime/AbstractFunction1."<init>":()V
const #26 = Asciz	this;
const #27 = Asciz	Lscala/util/automata/NondetWordAutom$$anonfun$finalStates$1;;
const #28 = Asciz	LocalVariableTable;
const #29 = Asciz	(Lscala/util/automata/NondetWordAutom<TT;>;)V;
const #30 = Asciz	Signature;
const #31 = Asciz	apply;
const #32 = Asciz	(Ljava/lang/Object;)Ljava/lang/Object;;
const #33 = Asciz	scala/runtime/BoxesRunTime;
const #34 = class	#33;	//  scala/runtime/BoxesRunTime
const #35 = Asciz	unboxToInt;
const #36 = Asciz	(Ljava/lang/Object;)I;
const #37 = NameAndType	#35:#36;//  unboxToInt:(Ljava/lang/Object;)I
const #38 = Method	#34.#37;	//  scala/runtime/BoxesRunTime.unboxToInt:(Ljava/lang/Object;)I
const #39 = Asciz	(I)Z;
const #40 = NameAndType	#31:#39;//  apply:(I)Z
const #41 = Method	#9.#40;	//  scala/util/automata/NondetWordAutom$$anonfun$finalStates$1.apply:(I)Z
const #42 = Asciz	boxToBoolean;
const #43 = Asciz	(Z)Ljava/lang/Boolean;;
const #44 = NameAndType	#42:#43;//  boxToBoolean:(Z)Ljava/lang/Boolean;
const #45 = Method	#34.#44;	//  scala/runtime/BoxesRunTime.boxToBoolean:(Z)Ljava/lang/Boolean;
const #46 = Asciz	v1;
const #47 = Asciz	Ljava/lang/Object;;
const #48 = Asciz	scala/util/automata/NondetWordAutom;
const #49 = class	#48;	//  scala/util/automata/NondetWordAutom
const #50 = Asciz	isFinal;
const #51 = NameAndType	#50:#39;//  isFinal:(I)Z
const #52 = Method	#49.#51;	//  scala/util/automata/NondetWordAutom.isFinal:(I)Z
const #53 = Asciz	Scala;
const #54 = Asciz	InnerClasses;
const #55 = Asciz	$anonfun$finalStates$1;
const #56 = Asciz	java/io/Serializable;
const #57 = class	#56;	//  java/io/Serializable

{
public static final long serialVersionUID;

public static {};
  Code:
   Stack=2, Locals=0, Args_size=0
   0:	lconst_0
   1:	putstatic	#11; //Field serialVersionUID:J
   4:	return

public scala.util.automata.NondetWordAutom$$anonfun$finalStates$1(scala.util.automata.NondetWordAutom);
  Code:
   Stack=2, Locals=2, Args_size=2
   0:	aload_1
   1:	ifnonnull	12
   4:	new	#18; //class java/lang/NullPointerException
   7:	dup
   8:	invokespecial	#20; //Method java/lang/NullPointerException."<init>":()V
   11:	athrow
   12:	aload_0
   13:	aload_1
   14:	putfield	#22; //Field $outer:Lscala/util/automata/NondetWordAutom;
   17:	aload_0
   18:	invokespecial	#25; //Method scala/runtime/AbstractFunction1."<init>":()V
   21:	return
  LineNumberTable: 
   line 55: 0

  LocalVariableTable: 
   Start  Length  Slot  Name   Signature
   0      22      0    this       Lscala/util/automata/NondetWordAutom$$anonfun$finalStates$1;
   0      22      1    $outer       Lscala/util/automata/NondetWordAutom;

  Signature: length = 0x2
   00 1D 

public final java.lang.Object apply(java.lang.Object);
  Code:
   Stack=2, Locals=3, Args_size=2
   0:	aload_0
   1:	aload_1
   2:	invokestatic	#38; //Method scala/runtime/BoxesRunTime.unboxToInt:(Ljava/lang/Object;)I
   5:	invokevirtual	#41; //Method apply:(I)Z
   8:	istore_2
   9:	iload_2
   10:	invokestatic	#45; //Method scala/runtime/BoxesRunTime.boxToBoolean:(Z)Ljava/lang/Boolean;
   13:	areturn
  LineNumberTable: 
   line 55: 0

  LocalVariableTable: 
   Start  Length  Slot  Name   Signature
   0      14      0    this       Lscala/util/automata/NondetWordAutom$$anonfun$finalStates$1;
   0      14      1    v1       Ljava/lang/Object;


public final boolean apply(int);
  Code:
   Stack=2, Locals=2, Args_size=2
   0:	aload_0
   1:	getfield	#22; //Field $outer:Lscala/util/automata/NondetWordAutom;
   4:	iload_1
   5:	invokevirtual	#52; //Method scala/util/automata/NondetWordAutom.isFinal:(I)Z
   8:	ireturn
  LineNumberTable: 
   line 55: 0


}

