Compiled from "SubsetConstruction.scala"
public final class scala.util.automata.SubsetConstruction$$anonfun$determinize$3 extends java.lang.Object implements scala.Function1,scala.ScalaObject,java.io.Serializable
  SourceFile: "SubsetConstruction.scala"
  Scala: length = 0x
   
  InnerClass: 
   public final $anonfun$determinize$3=class scala/util/automata/SubsetConstruction$$anonfun$determinize$3 of class scala/util/automata/SubsetConstruction
  minor version: 0
  major version: 49
  Constant pool:
Asciz	SourceFile;
Asciz	SubsetConstruction.scala;
Asciz	<clinit>;
Asciz	()V;
Asciz	Code;
Asciz	serialVersionUID;
Asciz	J;
Asciz	scala/util/automata/SubsetConstruction$$anonfun$determinize$3;
class	scala/util/automata/SubsetConstruction$$anonfun$determinize$3
NameAndType	serialVersionUID:J
Field	scala/util/automata/SubsetConstruction$$anonfun$determinize$3.serialVersionUID:J
Asciz	finalsR$1;
Asciz	[I;
Asciz	indexMap$1;
Asciz	Lscala/runtime/ObjectRef;;
Asciz	<init>;
Asciz	(Lscala/util/automata/SubsetConstruction;Lscala/runtime/ObjectRef;[I)V;
Asciz	LineNumberTable;
NameAndType	indexMap$1:Lscala/runtime/ObjectRef;
Field	scala/util/automata/SubsetConstruction$$anonfun$determinize$3.indexMap$1:Lscala/runtime/ObjectRef;
NameAndType	finalsR$1:[I
Field	scala/util/automata/SubsetConstruction$$anonfun$determinize$3.finalsR$1:[I
Asciz	java/lang/Object;
class	java/lang/Object
NameAndType	"<init>":()V
Method	java/lang/Object."<init>":()V
Asciz	scala/Function1$class;
class	scala/Function1$class
Asciz	$init$;
Asciz	(Lscala/Function1;)V;
NameAndType	$init$:(Lscala/Function1;)V
Method	scala/Function1$class.$init$:(Lscala/Function1;)V
Asciz	this;
Asciz	Lscala/util/automata/SubsetConstruction$$anonfun$determinize$3;;
Asciz	$outer;
Asciz	Lscala/util/automata/SubsetConstruction;;
Asciz	LocalVariableTable;
Asciz	(Lscala/util/automata/SubsetConstruction<TT;>;)V;
Asciz	Signature;
Asciz	apply;
Asciz	(Ljava/lang/Object;)Ljava/lang/Object;;
Asciz	scala/Tuple2;
class	scala/Tuple2
Asciz	(Lscala/Tuple2;)V;
NameAndType	apply:(Lscala/Tuple2;)V
Method	scala/util/automata/SubsetConstruction$$anonfun$determinize$3.apply:(Lscala/Tuple2;)V
Asciz	scala/runtime/BoxedUnit;
class	scala/runtime/BoxedUnit
Asciz	UNIT;
Asciz	Lscala/runtime/BoxedUnit;;
NameAndType	UNIT:Lscala/runtime/BoxedUnit;
Field	scala/runtime/BoxedUnit.UNIT:Lscala/runtime/BoxedUnit;
Asciz	v1;
Asciz	Ljava/lang/Object;;
Asciz	_1;
Asciz	()Ljava/lang/Object;;
NameAndType	_1:()Ljava/lang/Object;
Method	scala/Tuple2._1:()Ljava/lang/Object;
Asciz	scala/collection/immutable/BitSet;
class	scala/collection/immutable/BitSet
Asciz	_2;
NameAndType	_2:()Ljava/lang/Object;
Method	scala/Tuple2._2:()Ljava/lang/Object;
Asciz	scala/runtime/BoxesRunTime;
class	scala/runtime/BoxesRunTime
Asciz	unboxToInt;
Asciz	(Ljava/lang/Object;)I;
NameAndType	unboxToInt:(Ljava/lang/Object;)I
Method	scala/runtime/BoxesRunTime.unboxToInt:(Ljava/lang/Object;)I
Asciz	scala/runtime/ObjectRef;
class	scala/runtime/ObjectRef
Asciz	elem;
NameAndType	elem:Ljava/lang/Object;
Field	scala/runtime/ObjectRef.elem:Ljava/lang/Object;
Asciz	scala/collection/Map;
class	scala/collection/Map
Asciz	scala/collection/MapLike;
class	scala/collection/MapLike
NameAndType	apply:(Ljava/lang/Object;)Ljava/lang/Object;
InterfaceMethod	scala/collection/MapLike.apply:(Ljava/lang/Object;)Ljava/lang/Object;
Asciz	scala/MatchError;
class	scala/MatchError
Asciz	toString;
Asciz	()Ljava/lang/String;;
NameAndType	toString:()Ljava/lang/String;
Method	scala/Tuple2.toString:()Ljava/lang/String;
Asciz	(Ljava/lang/String;)V;
NameAndType	"<init>":(Ljava/lang/String;)V
Method	scala/MatchError."<init>":(Ljava/lang/String;)V
Asciz	temp5;
Asciz	Lscala/collection/immutable/BitSet;;
Asciz	temp6;
Asciz	I;
Asciz	(Lscala/Tuple2<Lscala/collection/immutable/BitSet;Ljava/lang/Integer;>;)V;
Asciz	andThen;
Asciz	(Lscala/Function1;)Lscala/Function1;;
Asciz	(Lscala/Function1;Lscala/Function1;)Lscala/Function1;;
NameAndType	andThen:(Lscala/Function1;Lscala/Function1;)Lscala/Function1;
Method	scala/Function1$class.andThen:(Lscala/Function1;Lscala/Function1;)Lscala/Function1;
Asciz	g;
Asciz	Lscala/Function1;;
Asciz	compose;
NameAndType	compose:(Lscala/Function1;Lscala/Function1;)Lscala/Function1;
Method	scala/Function1$class.compose:(Lscala/Function1;Lscala/Function1;)Lscala/Function1;
Asciz	(Lscala/Function1;)Ljava/lang/String;;
NameAndType	toString:(Lscala/Function1;)Ljava/lang/String;
Method	scala/Function1$class.toString:(Lscala/Function1;)Ljava/lang/String;
Asciz	Scala;
Asciz	InnerClasses;
Asciz	scala/util/automata/SubsetConstruction;
class	scala/util/automata/SubsetConstruction
Asciz	$anonfun$determinize$3;
Asciz	scala/Function1;
class	scala/Function1
Asciz	scala/ScalaObject;
class	scala/ScalaObject
Asciz	java/io/Serializable;
class	java/io/Serializable

{
public static final long serialVersionUID;
  Signature: J

private final int[] finalsR$1;
  Signature: [I

private final scala.runtime.ObjectRef indexMap$1;
  Signature: Lscala/runtime/ObjectRef;

public static {};
  Signature: ()V
  Code:
   Stack=2, Locals=0, Args_size=0
	lconst_0
	putstatic	Field serialVersionUID:J
	return
  Labels:

public scala.util.automata.SubsetConstruction$$anonfun$determinize$3(scala.util.automata.SubsetConstruction, scala.runtime.ObjectRef, int[]);
  Signature: (Lscala/util/automata/SubsetConstruction;Lscala/runtime/ObjectRef;[I)V
  Code:
   Stack=2, Locals=4, Args_size=4
	aload_0
	aload_2
	putfield	Field indexMap$1:Lscala/runtime/ObjectRef;
	aload_0
	aload_3
	putfield	Field finalsR$1:[I
	aload_0
	invokespecial	Method java/lang/Object."<init>":()V
	aload_0
	invokestatic	Method scala/Function1$class.$init$:(Lscala/Function1;)V
	return
  Labels:
  LocalVariableTable: 
   Start  Length  Slot  Name   Signature
   0      19      0    this       Lscala/util/automata/SubsetConstruction$$anonfun$determinize$3;
   0      19      1    $outer       Lscala/util/automata/SubsetConstruction;

  Signature: length = 0x2
   00 26 

public final java.lang.Object apply(java.lang.Object);
  Signature: (Ljava/lang/Object;)Ljava/lang/Object;
  Code:
   Stack=2, Locals=2, Args_size=2
	aload_0
	aload_1
	checkcast	class scala/Tuple2
	invokevirtual	Method apply:(Lscala/Tuple2;)V
	getstatic	Field scala/runtime/BoxedUnit.UNIT:Lscala/runtime/BoxedUnit;
	areturn
  Labels:
  LocalVariableTable: 
   Start  Length  Slot  Name   Signature
   0      12      0    this       Lscala/util/automata/SubsetConstruction$$anonfun$determinize$3;
   0      12      1    v1       Ljava/lang/Object;


public final void apply(scala.Tuple2);
  Signature: (Lscala/Tuple2;)V
  Code:
   Stack=3, Locals=4, Args_size=2
	aload_1
	ifnull	l1 // new
	aload_1
	invokevirtual	Method scala/Tuple2._1:()Ljava/lang/Object;
	checkcast	class scala/collection/immutable/BitSet
	astore_2
	aload_1
	invokevirtual	Method scala/Tuple2._2:()Ljava/lang/Object;
	invokestatic	Method scala/runtime/BoxesRunTime.unboxToInt:(Ljava/lang/Object;)I
	istore_3
	iconst_1
	ifeq	l2 // new
	aload_0
	getfield	Field finalsR$1:[I
	aload_0
	getfield	Field indexMap$1:Lscala/runtime/ObjectRef;
	getfield	Field scala/runtime/ObjectRef.elem:Ljava/lang/Object;
	checkcast	class scala/collection/Map
	aload_2
	invokeinterface	InterfaceMethod scala/collection/MapLike.apply:(Ljava/lang/Object;)Ljava/lang/Object;
	invokestatic	Method scala/runtime/BoxesRunTime.unboxToInt:(Ljava/lang/Object;)I
	iload_3
	iastore
	return
l2	new	class scala/MatchError
	dup
	aload_1
	invokevirtual	Method scala/Tuple2.toString:()Ljava/lang/String;
	invokespecial	Method scala/MatchError."<init>":(Ljava/lang/String;)V
	athrow
l1	new	class scala/MatchError
	dup
	aload_1
	invokevirtual	Method scala/Tuple2.toString:()Ljava/lang/String;
	invokespecial	Method scala/MatchError."<init>":(Ljava/lang/String;)V
	athrow
  Labels:
   	l2 = 50 // new
   	l1 = 62 // new
  LocalVariableTable: 
   Start  Length  Slot  Name   Signature
   0      74      0    this       Lscala/util/automata/SubsetConstruction$$anonfun$determinize$3;
   12      50      2    temp5       Lscala/collection/immutable/BitSet;
   20      42      3    temp6       I

  Signature: length = 0x2
   00 5E 

public scala.Function1 andThen(scala.Function1);
  Signature: (Lscala/Function1;)Lscala/Function1;
  Code:
   Stack=2, Locals=2, Args_size=2
	aload_0
	aload_1
	invokestatic	Method scala/Function1$class.andThen:(Lscala/Function1;Lscala/Function1;)Lscala/Function1;
	areturn
  Labels:
  LocalVariableTable: 
   Start  Length  Slot  Name   Signature
   0      6      0    this       Lscala/util/automata/SubsetConstruction$$anonfun$determinize$3;
   0      6      1    g       Lscala/Function1;


public scala.Function1 compose(scala.Function1);
  Signature: (Lscala/Function1;)Lscala/Function1;
  Code:
   Stack=2, Locals=2, Args_size=2
	aload_0
	aload_1
	invokestatic	Method scala/Function1$class.compose:(Lscala/Function1;Lscala/Function1;)Lscala/Function1;
	areturn
  Labels:
  LocalVariableTable: 
   Start  Length  Slot  Name   Signature
   0      6      0    this       Lscala/util/automata/SubsetConstruction$$anonfun$determinize$3;
   0      6      1    g       Lscala/Function1;


public java.lang.String toString();
  Signature: ()Ljava/lang/String;
  Code:
   Stack=1, Locals=1, Args_size=1
	aload_0
	invokestatic	Method scala/Function1$class.toString:(Lscala/Function1;)Ljava/lang/String;
	areturn
  Labels:

}

