Compiled from "SubsetConstruction.scala"
public final class scala.util.automata.SubsetConstruction$$anon$1 extends scala.util.automata.DetWordAutom
  SourceFile: "SubsetConstruction.scala"
  Signature: length = 0x2
   00 29 
  Scala: length = 0x
   
  InnerClass: 
   public final #46= #22 of #45; //$anon$1=class scala/util/automata/SubsetConstruction$$anon$1 of class scala/util/automata/SubsetConstruction
  minor version: 0
  major version: 49
  Constant pool:
const #1 = Asciz	SourceFile;
const #2 = Asciz	SubsetConstruction.scala;
const #3 = Asciz	finals;
const #4 = Asciz	[I;
const #5 = Asciz	default;
const #6 = Asciz	delta;
const #7 = Asciz	[Lscala/collection/Map;;
const #8 = Asciz	[Lscala/collection/Map<TT;Ljava/lang/Integer;>;;
const #9 = Asciz	Signature;
const #10 = Asciz	nstates;
const #11 = Asciz	I;
const #12 = Asciz	<init>;
const #13 = Asciz	(Lscala/util/automata/SubsetConstruction;I[Lscala/collection/Map;[I[I)V;
const #14 = Asciz	Code;
const #15 = Asciz	LineNumberTable;
const #16 = Asciz	scala/util/automata/DetWordAutom;
const #17 = class	#16;	//  scala/util/automata/DetWordAutom
const #18 = Asciz	()V;
const #19 = NameAndType	#12:#18;//  "<init>":()V
const #20 = Method	#17.#19;	//  scala/util/automata/DetWordAutom."<init>":()V
const #21 = Asciz	scala/util/automata/SubsetConstruction$$anon$1;
const #22 = class	#21;	//  scala/util/automata/SubsetConstruction$$anon$1
const #23 = NameAndType	#10:#11;//  nstates:I
const #24 = Field	#22.#23;	//  scala/util/automata/SubsetConstruction$$anon$1.nstates:I
const #25 = NameAndType	#6:#7;//  delta:[Lscala/collection/Map;
const #26 = Field	#22.#25;	//  scala/util/automata/SubsetConstruction$$anon$1.delta:[Lscala/collection/Map;
const #27 = NameAndType	#5:#4;//  default:[I
const #28 = Field	#22.#27;	//  scala/util/automata/SubsetConstruction$$anon$1.default:[I
const #29 = NameAndType	#3:#4;//  finals:[I
const #30 = Field	#22.#29;	//  scala/util/automata/SubsetConstruction$$anon$1.finals:[I
const #31 = Asciz	this;
const #32 = Asciz	Lscala/util/automata/SubsetConstruction$$anon$1;;
const #33 = Asciz	$outer;
const #34 = Asciz	Lscala/util/automata/SubsetConstruction;;
const #35 = Asciz	LocalVariableTable;
const #36 = Asciz	(Lscala/util/automata/SubsetConstruction<TT;>;)V;
const #37 = Asciz	()[I;
const #38 = Asciz	()[Lscala/collection/Map;;
const #39 = Asciz	()[Lscala/collection/Map<TT;Ljava/lang/Integer;>;;
const #40 = Asciz	()I;
const #41 = Asciz	Lscala/util/automata/DetWordAutom<TT;>;;
const #42 = Asciz	Scala;
const #43 = Asciz	InnerClasses;
const #44 = Asciz	scala/util/automata/SubsetConstruction;
const #45 = class	#44;	//  scala/util/automata/SubsetConstruction
const #46 = Asciz	$anon$1;

{
public scala.util.automata.SubsetConstruction$$anon$1(scala.util.automata.SubsetConstruction, int, scala.collection.Map[], int[], int[]);
  Code:
   Stack=2, Locals=6, Args_size=6
   0:	aload_0
   1:	invokespecial	#20; //Method scala/util/automata/DetWordAutom."<init>":()V
   4:	aload_0
   5:	iload_2
   6:	putfield	#24; //Field nstates:I
   9:	aload_0
   10:	aload_3
   11:	putfield	#26; //Field delta:[Lscala/collection/Map;
   14:	aload_0
   15:	aload	4
   17:	putfield	#28; //Field default:[I
   20:	aload_0
   21:	aload	5
   23:	putfield	#30; //Field finals:[I
   26:	return
  LineNumberTable: 
   line 101: 0
   line 102: 4
   line 103: 9
   line 104: 14
   line 105: 20

  LocalVariableTable: 
   Start  Length  Slot  Name   Signature
   0      27      0    this       Lscala/util/automata/SubsetConstruction$$anon$1;
   0      27      1    $outer       Lscala/util/automata/SubsetConstruction;

  Signature: length = 0x2
   00 24 

public int[] finals();
  Code:
   Stack=1, Locals=1, Args_size=1
   0:	aload_0
   1:	getfield	#30; //Field finals:[I
   4:	areturn
  LineNumberTable: 
   line 105: 0


public int[] default();
  Code:
   Stack=1, Locals=1, Args_size=1
   0:	aload_0
   1:	getfield	#28; //Field default:[I
   4:	areturn
  LineNumberTable: 
   line 104: 0


public scala.collection.Map[] delta();
  Code:
   Stack=1, Locals=1, Args_size=1
   0:	aload_0
   1:	getfield	#26; //Field delta:[Lscala/collection/Map;
   4:	areturn
  LineNumberTable: 
   line 103: 0

  Signature: length = 0x2
   00 27 

public int nstates();
  Code:
   Stack=1, Locals=1, Args_size=1
   0:	aload_0
   1:	getfield	#24; //Field nstates:I
   4:	ireturn
  LineNumberTable: 
   line 102: 0


}

