Compiled from "SubsetConstruction.scala"
public final class scala.util.automata.SubsetConstruction$$anonfun$determinize$1 extends java.lang.Object implements scala.Function1,scala.ScalaObject,java.io.Serializable
  SourceFile: "SubsetConstruction.scala"
  Scala: length = 0x
   
  InnerClass: 
   public final #111= #9 of #70; //$anonfun$determinize$1=class scala/util/automata/SubsetConstruction$$anonfun$determinize$1 of class scala/util/automata/SubsetConstruction
  minor version: 0
  major version: 49
  Constant pool:
const #1 = Asciz	SourceFile;
const #2 = Asciz	SubsetConstruction.scala;
const #3 = Asciz	<clinit>;
const #4 = Asciz	()V;
const #5 = Asciz	Code;
const #6 = Asciz	serialVersionUID;
const #7 = Asciz	J;
const #8 = Asciz	scala/util/automata/SubsetConstruction$$anonfun$determinize$1;
const #9 = class	#8;	//  scala/util/automata/SubsetConstruction$$anonfun$determinize$1
const #10 = NameAndType	#6:#7;//  serialVersionUID:J
const #11 = Field	#9.#10;	//  scala/util/automata/SubsetConstruction$$anonfun$determinize$1.serialVersionUID:J
const #12 = Asciz	Pdelta$1;
const #13 = Asciz	Lscala/collection/mutable/HashMap;;
const #14 = Asciz	P$1;
const #15 = Asciz	Lscala/collection/immutable/BitSet;;
const #16 = Asciz	rest$1;
const #17 = Asciz	Lscala/collection/mutable/Stack;;
const #18 = Asciz	finals$1;
const #19 = Asciz	Lscala/runtime/ObjectRef;;
const #20 = Asciz	states$1;
const #21 = Asciz	$outer;
const #22 = Asciz	Lscala/util/automata/SubsetConstruction;;
const #23 = Asciz	<init>;
const #24 = Asciz	(Lscala/util/automata/SubsetConstruction;Lscala/runtime/ObjectRef;Lscala/runtime/ObjectRef;Lscala/collection/mutable/Stack;Lscala/collection/immutable/BitSet;Lscala/collection/mutable/HashMap;)V;
const #25 = Asciz	LineNumberTable;
const #26 = Asciz	java/lang/NullPointerException;
const #27 = class	#26;	//  java/lang/NullPointerException
const #28 = NameAndType	#23:#4;//  "<init>":()V
const #29 = Method	#27.#28;	//  java/lang/NullPointerException."<init>":()V
const #30 = NameAndType	#21:#22;//  $outer:Lscala/util/automata/SubsetConstruction;
const #31 = Field	#9.#30;	//  scala/util/automata/SubsetConstruction$$anonfun$determinize$1.$outer:Lscala/util/automata/SubsetConstruction;
const #32 = NameAndType	#20:#19;//  states$1:Lscala/runtime/ObjectRef;
const #33 = Field	#9.#32;	//  scala/util/automata/SubsetConstruction$$anonfun$determinize$1.states$1:Lscala/runtime/ObjectRef;
const #34 = NameAndType	#18:#19;//  finals$1:Lscala/runtime/ObjectRef;
const #35 = Field	#9.#34;	//  scala/util/automata/SubsetConstruction$$anonfun$determinize$1.finals$1:Lscala/runtime/ObjectRef;
const #36 = NameAndType	#16:#17;//  rest$1:Lscala/collection/mutable/Stack;
const #37 = Field	#9.#36;	//  scala/util/automata/SubsetConstruction$$anonfun$determinize$1.rest$1:Lscala/collection/mutable/Stack;
const #38 = NameAndType	#14:#15;//  P$1:Lscala/collection/immutable/BitSet;
const #39 = Field	#9.#38;	//  scala/util/automata/SubsetConstruction$$anonfun$determinize$1.P$1:Lscala/collection/immutable/BitSet;
const #40 = NameAndType	#12:#13;//  Pdelta$1:Lscala/collection/mutable/HashMap;
const #41 = Field	#9.#40;	//  scala/util/automata/SubsetConstruction$$anonfun$determinize$1.Pdelta$1:Lscala/collection/mutable/HashMap;
const #42 = Asciz	java/lang/Object;
const #43 = class	#42;	//  java/lang/Object
const #44 = Method	#43.#28;	//  java/lang/Object."<init>":()V
const #45 = Asciz	scala/Function1$class;
const #46 = class	#45;	//  scala/Function1$class
const #47 = Asciz	$init$;
const #48 = Asciz	(Lscala/Function1;)V;
const #49 = NameAndType	#47:#48;//  $init$:(Lscala/Function1;)V
const #50 = Method	#46.#49;	//  scala/Function1$class.$init$:(Lscala/Function1;)V
const #51 = Asciz	this;
const #52 = Asciz	Lscala/util/automata/SubsetConstruction$$anonfun$determinize$1;;
const #53 = Asciz	LocalVariableTable;
const #54 = Asciz	(Lscala/util/automata/SubsetConstruction<TT;>;)V;
const #55 = Asciz	Signature;
const #56 = Asciz	apply;
const #57 = Asciz	(Ljava/lang/Object;)Ljava/lang/Object;;
const #58 = Asciz	(Ljava/lang/Object;)V;
const #59 = NameAndType	#56:#58;//  apply:(Ljava/lang/Object;)V
const #60 = Method	#9.#59;	//  scala/util/automata/SubsetConstruction$$anonfun$determinize$1.apply:(Ljava/lang/Object;)V
const #61 = Asciz	scala/runtime/BoxedUnit;
const #62 = class	#61;	//  scala/runtime/BoxedUnit
const #63 = Asciz	UNIT;
const #64 = Asciz	Lscala/runtime/BoxedUnit;;
const #65 = NameAndType	#63:#64;//  UNIT:Lscala/runtime/BoxedUnit;
const #66 = Field	#62.#65;	//  scala/runtime/BoxedUnit.UNIT:Lscala/runtime/BoxedUnit;
const #67 = Asciz	v1;
const #68 = Asciz	Ljava/lang/Object;;
const #69 = Asciz	scala/util/automata/SubsetConstruction;
const #70 = class	#69;	//  scala/util/automata/SubsetConstruction
const #71 = Asciz	nfa;
const #72 = Asciz	()Lscala/util/automata/NondetWordAutom;;
const #73 = NameAndType	#71:#72;//  nfa:()Lscala/util/automata/NondetWordAutom;
const #74 = Method	#70.#73;	//  scala/util/automata/SubsetConstruction.nfa:()Lscala/util/automata/NondetWordAutom;
const #75 = Asciz	scala/util/automata/NondetWordAutom;
const #76 = class	#75;	//  scala/util/automata/NondetWordAutom
const #77 = Asciz	next;
const #78 = Asciz	(Lscala/collection/immutable/BitSet;Ljava/lang/Object;)Lscala/collection/immutable/BitSet;;
const #79 = NameAndType	#77:#78;//  next:(Lscala/collection/immutable/BitSet;Ljava/lang/Object;)Lscala/collection/immutable/BitSet;
const #80 = Method	#76.#79;	//  scala/util/automata/NondetWordAutom.next:(Lscala/collection/immutable/BitSet;Ljava/lang/Object;)Lscala/collection/immutable/BitSet;
const #81 = Asciz	scala/collection/mutable/HashMap;
const #82 = class	#81;	//  scala/collection/mutable/HashMap
const #83 = Asciz	update;
const #84 = Asciz	(Ljava/lang/Object;Ljava/lang/Object;)V;
const #85 = NameAndType	#83:#84;//  update:(Ljava/lang/Object;Ljava/lang/Object;)V
const #86 = Method	#82.#85;	//  scala/collection/mutable/HashMap.update:(Ljava/lang/Object;Ljava/lang/Object;)V
const #87 = Asciz	add$1;
const #88 = Asciz	(Lscala/collection/immutable/BitSet;Lscala/runtime/ObjectRef;Lscala/runtime/ObjectRef;Lscala/collection/mutable/Stack;)V;
const #89 = NameAndType	#87:#88;//  add$1:(Lscala/collection/immutable/BitSet;Lscala/runtime/ObjectRef;Lscala/runtime/ObjectRef;Lscala/collection/mutable/Stack;)V
const #90 = Method	#70.#89;	//  scala/util/automata/SubsetConstruction.add$1:(Lscala/collection/immutable/BitSet;Lscala/runtime/ObjectRef;Lscala/runtime/ObjectRef;Lscala/collection/mutable/Stack;)V
const #91 = Asciz	label;
const #92 = Asciz	Q;
const #93 = Asciz	(TT;)V;
const #94 = Asciz	andThen;
const #95 = Asciz	(Lscala/Function1;)Lscala/Function1;;
const #96 = Asciz	(Lscala/Function1;Lscala/Function1;)Lscala/Function1;;
const #97 = NameAndType	#94:#96;//  andThen:(Lscala/Function1;Lscala/Function1;)Lscala/Function1;
const #98 = Method	#46.#97;	//  scala/Function1$class.andThen:(Lscala/Function1;Lscala/Function1;)Lscala/Function1;
const #99 = Asciz	g;
const #100 = Asciz	Lscala/Function1;;
const #101 = Asciz	compose;
const #102 = NameAndType	#101:#96;//  compose:(Lscala/Function1;Lscala/Function1;)Lscala/Function1;
const #103 = Method	#46.#102;	//  scala/Function1$class.compose:(Lscala/Function1;Lscala/Function1;)Lscala/Function1;
const #104 = Asciz	toString;
const #105 = Asciz	()Ljava/lang/String;;
const #106 = Asciz	(Lscala/Function1;)Ljava/lang/String;;
const #107 = NameAndType	#104:#106;//  toString:(Lscala/Function1;)Ljava/lang/String;
const #108 = Method	#46.#107;	//  scala/Function1$class.toString:(Lscala/Function1;)Ljava/lang/String;
const #109 = Asciz	Scala;
const #110 = Asciz	InnerClasses;
const #111 = Asciz	$anonfun$determinize$1;
const #112 = Asciz	scala/Function1;
const #113 = class	#112;	//  scala/Function1
const #114 = Asciz	scala/ScalaObject;
const #115 = class	#114;	//  scala/ScalaObject
const #116 = Asciz	java/io/Serializable;
const #117 = class	#116;	//  java/io/Serializable

{
public static final long serialVersionUID;

public static {};
  Code:
   Stack=2, Locals=0, Args_size=0
   0:	lconst_0
   1:	putstatic	#11; //Field serialVersionUID:J
   4:	return

public scala.util.automata.SubsetConstruction$$anonfun$determinize$1(scala.util.automata.SubsetConstruction, scala.runtime.ObjectRef, scala.runtime.ObjectRef, scala.collection.mutable.Stack, scala.collection.immutable.BitSet, scala.collection.mutable.HashMap);
  Code:
   Stack=2, Locals=7, Args_size=7
   0:	aload_1
   1:	ifnonnull	12
   4:	new	#27; //class java/lang/NullPointerException
   7:	dup
   8:	invokespecial	#29; //Method java/lang/NullPointerException."<init>":()V
   11:	athrow
   12:	aload_0
   13:	aload_1
   14:	putfield	#31; //Field $outer:Lscala/util/automata/SubsetConstruction;
   17:	aload_0
   18:	aload_2
   19:	putfield	#33; //Field states$1:Lscala/runtime/ObjectRef;
   22:	aload_0
   23:	aload_3
   24:	putfield	#35; //Field finals$1:Lscala/runtime/ObjectRef;
   27:	aload_0
   28:	aload	4
   30:	putfield	#37; //Field rest$1:Lscala/collection/mutable/Stack;
   33:	aload_0
   34:	aload	5
   36:	putfield	#39; //Field P$1:Lscala/collection/immutable/BitSet;
   39:	aload_0
   40:	aload	6
   42:	putfield	#41; //Field Pdelta$1:Lscala/collection/mutable/HashMap;
   45:	aload_0
   46:	invokespecial	#44; //Method java/lang/Object."<init>":()V
   49:	aload_0
   50:	invokestatic	#50; //Method scala/Function1$class.$init$:(Lscala/Function1;)V
   53:	return
  LineNumberTable: 
   line 64: 0

  LocalVariableTable: 
   Start  Length  Slot  Name   Signature
   0      54      0    this       Lscala/util/automata/SubsetConstruction$$anonfun$determinize$1;
   0      54      1    $outer       Lscala/util/automata/SubsetConstruction;

  Signature: length = 0x2
   00 36 

public final java.lang.Object apply(java.lang.Object);
  Code:
   Stack=2, Locals=3, Args_size=2
   0:	aload_0
   1:	getfield	#31; //Field $outer:Lscala/util/automata/SubsetConstruction;
   4:	astore_2
   5:	aload_0
   6:	aload_1
   7:	invokevirtual	#60; //Method apply:(Ljava/lang/Object;)V
   10:	getstatic	#66; //Field scala/runtime/BoxedUnit.UNIT:Lscala/runtime/BoxedUnit;
   13:	areturn
  LineNumberTable: 
   line 64: 0

  LocalVariableTable: 
   Start  Length  Slot  Name   Signature
   0      14      0    this       Lscala/util/automata/SubsetConstruction$$anonfun$determinize$1;
   5      9      1    v1       Ljava/lang/Object;


public final void apply(java.lang.Object);
  Code:
   Stack=5, Locals=4, Args_size=2
   0:	aload_0
   1:	getfield	#31; //Field $outer:Lscala/util/automata/SubsetConstruction;
   4:	astore_3
   5:	aload_0
   6:	getfield	#31; //Field $outer:Lscala/util/automata/SubsetConstruction;
   9:	invokevirtual	#74; //Method scala/util/automata/SubsetConstruction.nfa:()Lscala/util/automata/NondetWordAutom;
   12:	aload_0
   13:	getfield	#39; //Field P$1:Lscala/collection/immutable/BitSet;
   16:	aload_1
   17:	invokevirtual	#80; //Method scala/util/automata/NondetWordAutom.next:(Lscala/collection/immutable/BitSet;Ljava/lang/Object;)Lscala/collection/immutable/BitSet;
   20:	astore_2
   21:	aload_0
   22:	getfield	#41; //Field Pdelta$1:Lscala/collection/mutable/HashMap;
   25:	aload_1
   26:	aload_2
   27:	invokevirtual	#86; //Method scala/collection/mutable/HashMap.update:(Ljava/lang/Object;Ljava/lang/Object;)V
   30:	aload_0
   31:	getfield	#31; //Field $outer:Lscala/util/automata/SubsetConstruction;
   34:	aload_2
   35:	aload_0
   36:	getfield	#33; //Field states$1:Lscala/runtime/ObjectRef;
   39:	aload_0
   40:	getfield	#35; //Field finals$1:Lscala/runtime/ObjectRef;
   43:	aload_0
   44:	getfield	#37; //Field rest$1:Lscala/collection/mutable/Stack;
   47:	invokevirtual	#90; //Method scala/util/automata/SubsetConstruction.add$1:(Lscala/collection/immutable/BitSet;Lscala/runtime/ObjectRef;Lscala/runtime/ObjectRef;Lscala/collection/mutable/Stack;)V
   50:	return
  LineNumberTable: 
   line 65: 0
   line 66: 21
   line 67: 30

  LocalVariableTable: 
   Start  Length  Slot  Name   Signature
   0      51      0    this       Lscala/util/automata/SubsetConstruction$$anonfun$determinize$1;
   5      46      1    label       Ljava/lang/Object;
   21      29      2    Q       Lscala/collection/immutable/BitSet;

  Signature: length = 0x2
   00 5D 

public scala.Function1 andThen(scala.Function1);
  Code:
   Stack=2, Locals=2, Args_size=2
   0:	aload_0
   1:	aload_1
   2:	invokestatic	#98; //Method scala/Function1$class.andThen:(Lscala/Function1;Lscala/Function1;)Lscala/Function1;
   5:	areturn
  LineNumberTable: 
   line 64: 0

  LocalVariableTable: 
   Start  Length  Slot  Name   Signature
   0      6      0    this       Lscala/util/automata/SubsetConstruction$$anonfun$determinize$1;
   0      6      1    g       Lscala/Function1;


public scala.Function1 compose(scala.Function1);
  Code:
   Stack=2, Locals=2, Args_size=2
   0:	aload_0
   1:	aload_1
   2:	invokestatic	#103; //Method scala/Function1$class.compose:(Lscala/Function1;Lscala/Function1;)Lscala/Function1;
   5:	areturn
  LineNumberTable: 
   line 64: 0

  LocalVariableTable: 
   Start  Length  Slot  Name   Signature
   0      6      0    this       Lscala/util/automata/SubsetConstruction$$anonfun$determinize$1;
   0      6      1    g       Lscala/Function1;


public java.lang.String toString();
  Code:
   Stack=1, Locals=1, Args_size=1
   0:	aload_0
   1:	invokestatic	#108; //Method scala/Function1$class.toString:(Lscala/Function1;)Ljava/lang/String;
   4:	areturn
  LineNumberTable: 
   line 64: 0


}

