Compiled from "SubsetConstruction.scala"
public final class scala.util.automata.SubsetConstruction$$anonfun$determinize$1 extends scala.runtime.AbstractFunction1 implements java.io.Serializable
  SourceFile: "SubsetConstruction.scala"
  Scala: length = 0x
   
  InnerClass: 
   public final $anonfun$determinize$1=class scala/util/automata/SubsetConstruction$$anonfun$determinize$1 of class scala/util/automata/SubsetConstruction
  minor version: 0
  major version: 49
  Constant pool:
Asciz	SourceFile;
Asciz	SubsetConstruction.scala;
Asciz	<clinit>;
Asciz	()V;
Asciz	Code;
Asciz	serialVersionUID;
Asciz	J;
Asciz	scala/util/automata/SubsetConstruction$$anonfun$determinize$1;
class	scala/util/automata/SubsetConstruction$$anonfun$determinize$1
NameAndType	serialVersionUID:J
Field	scala/util/automata/SubsetConstruction$$anonfun$determinize$1.serialVersionUID:J
Asciz	$outer;
Asciz	Lscala/util/automata/SubsetConstruction;;
Asciz	states$1;
Asciz	Lscala/runtime/ObjectRef;;
Asciz	finals$1;
Asciz	rest$1;
Asciz	Lscala/collection/mutable/Stack;;
Asciz	P$1;
Asciz	Lscala/collection/immutable/BitSet;;
Asciz	Pdelta$1;
Asciz	Lscala/collection/mutable/HashMap;;
Asciz	apply;
Asciz	(Ljava/lang/Object;)V;
Asciz	LineNumberTable;
NameAndType	$outer:Lscala/util/automata/SubsetConstruction;
Field	scala/util/automata/SubsetConstruction$$anonfun$determinize$1.$outer:Lscala/util/automata/SubsetConstruction;
Asciz	scala/util/automata/SubsetConstruction;
class	scala/util/automata/SubsetConstruction
Asciz	nfa;
Asciz	()Lscala/util/automata/NondetWordAutom;;
NameAndType	nfa:()Lscala/util/automata/NondetWordAutom;
Method	scala/util/automata/SubsetConstruction.nfa:()Lscala/util/automata/NondetWordAutom;
NameAndType	P$1:Lscala/collection/immutable/BitSet;
Field	scala/util/automata/SubsetConstruction$$anonfun$determinize$1.P$1:Lscala/collection/immutable/BitSet;
Asciz	scala/util/automata/NondetWordAutom;
class	scala/util/automata/NondetWordAutom
Asciz	next;
Asciz	(Lscala/collection/immutable/BitSet;Ljava/lang/Object;)Lscala/collection/immutable/BitSet;;
NameAndType	next:(Lscala/collection/immutable/BitSet;Ljava/lang/Object;)Lscala/collection/immutable/BitSet;
Method	scala/util/automata/NondetWordAutom.next:(Lscala/collection/immutable/BitSet;Ljava/lang/Object;)Lscala/collection/immutable/BitSet;
NameAndType	Pdelta$1:Lscala/collection/mutable/HashMap;
Field	scala/util/automata/SubsetConstruction$$anonfun$determinize$1.Pdelta$1:Lscala/collection/mutable/HashMap;
Asciz	scala/collection/mutable/HashMap;
class	scala/collection/mutable/HashMap
Asciz	update;
Asciz	(Ljava/lang/Object;Ljava/lang/Object;)V;
NameAndType	update:(Ljava/lang/Object;Ljava/lang/Object;)V
Method	scala/collection/mutable/HashMap.update:(Ljava/lang/Object;Ljava/lang/Object;)V
NameAndType	states$1:Lscala/runtime/ObjectRef;
Field	scala/util/automata/SubsetConstruction$$anonfun$determinize$1.states$1:Lscala/runtime/ObjectRef;
NameAndType	finals$1:Lscala/runtime/ObjectRef;
Field	scala/util/automata/SubsetConstruction$$anonfun$determinize$1.finals$1:Lscala/runtime/ObjectRef;
NameAndType	rest$1:Lscala/collection/mutable/Stack;
Field	scala/util/automata/SubsetConstruction$$anonfun$determinize$1.rest$1:Lscala/collection/mutable/Stack;
Asciz	add$1;
Asciz	(Lscala/collection/immutable/BitSet;Lscala/runtime/ObjectRef;Lscala/runtime/ObjectRef;Lscala/collection/mutable/Stack;)V;
NameAndType	add$1:(Lscala/collection/immutable/BitSet;Lscala/runtime/ObjectRef;Lscala/runtime/ObjectRef;Lscala/collection/mutable/Stack;)V
Method	scala/util/automata/SubsetConstruction.add$1:(Lscala/collection/immutable/BitSet;Lscala/runtime/ObjectRef;Lscala/runtime/ObjectRef;Lscala/collection/mutable/Stack;)V
Asciz	this;
Asciz	Lscala/util/automata/SubsetConstruction$$anonfun$determinize$1;;
Asciz	label;
Asciz	Ljava/lang/Object;;
Asciz	Q;
Asciz	LocalVariableTable;
Asciz	(TT;)V;
Asciz	Signature;
Asciz	(Ljava/lang/Object;)Ljava/lang/Object;;
NameAndType	apply:(Ljava/lang/Object;)V
Method	scala/util/automata/SubsetConstruction$$anonfun$determinize$1.apply:(Ljava/lang/Object;)V
Asciz	scala/runtime/BoxedUnit;
class	scala/runtime/BoxedUnit
Asciz	UNIT;
Asciz	Lscala/runtime/BoxedUnit;;
NameAndType	UNIT:Lscala/runtime/BoxedUnit;
Field	scala/runtime/BoxedUnit.UNIT:Lscala/runtime/BoxedUnit;
Asciz	v1;
Asciz	<init>;
Asciz	(Lscala/util/automata/SubsetConstruction;Lscala/runtime/ObjectRef;Lscala/runtime/ObjectRef;Lscala/collection/mutable/Stack;Lscala/collection/immutable/BitSet;Lscala/collection/mutable/HashMap;)V;
Asciz	java/lang/NullPointerException;
class	java/lang/NullPointerException
NameAndType	"<init>":()V
Method	java/lang/NullPointerException."<init>":()V
Asciz	scala/runtime/AbstractFunction1;
class	scala/runtime/AbstractFunction1
Method	scala/runtime/AbstractFunction1."<init>":()V
Asciz	(Lscala/util/automata/SubsetConstruction<TT;>;)V;
Asciz	Scala;
Asciz	InnerClasses;
Asciz	$anonfun$determinize$1;
Asciz	java/io/Serializable;
class	java/io/Serializable

{
public static final long serialVersionUID;
  Signature: J

public final scala.util.automata.SubsetConstruction $outer;
  Signature: Lscala/util/automata/SubsetConstruction;

public final scala.runtime.ObjectRef states$1;
  Signature: Lscala/runtime/ObjectRef;

public final scala.runtime.ObjectRef finals$1;
  Signature: Lscala/runtime/ObjectRef;

public final scala.collection.mutable.Stack rest$1;
  Signature: Lscala/collection/mutable/Stack;

public final scala.collection.immutable.BitSet P$1;
  Signature: Lscala/collection/immutable/BitSet;

public final scala.collection.mutable.HashMap Pdelta$1;
  Signature: Lscala/collection/mutable/HashMap;

public static {};
  Signature: ()V
  Code:
   Stack=2, Locals=0, Args_size=0
	lconst_0
	putstatic	Field serialVersionUID:J
	return
  Labels:

public final void apply(java.lang.Object);
  Signature: (Ljava/lang/Object;)V
  Code:
   Stack=5, Locals=3, Args_size=2
	aload_0
	getfield	Field $outer:Lscala/util/automata/SubsetConstruction;
	invokevirtual	Method scala/util/automata/SubsetConstruction.nfa:()Lscala/util/automata/NondetWordAutom;
	aload_0
	getfield	Field P$1:Lscala/collection/immutable/BitSet;
	aload_1
	invokevirtual	Method scala/util/automata/NondetWordAutom.next:(Lscala/collection/immutable/BitSet;Ljava/lang/Object;)Lscala/collection/immutable/BitSet;
	astore_2
	aload_0
	getfield	Field Pdelta$1:Lscala/collection/mutable/HashMap;
	aload_1
	aload_2
	invokevirtual	Method scala/collection/mutable/HashMap.update:(Ljava/lang/Object;Ljava/lang/Object;)V
	aload_0
	getfield	Field $outer:Lscala/util/automata/SubsetConstruction;
	aload_2
	aload_0
	getfield	Field states$1:Lscala/runtime/ObjectRef;
	aload_0
	getfield	Field finals$1:Lscala/runtime/ObjectRef;
	aload_0
	getfield	Field rest$1:Lscala/collection/mutable/Stack;
	invokevirtual	Method scala/util/automata/SubsetConstruction.add$1:(Lscala/collection/immutable/BitSet;Lscala/runtime/ObjectRef;Lscala/runtime/ObjectRef;Lscala/collection/mutable/Stack;)V
	return
  Labels:
  LocalVariableTable: 
   Start  Length  Slot  Name   Signature
   0      46      0    this       Lscala/util/automata/SubsetConstruction$$anonfun$determinize$1;
   0      46      1    label       Ljava/lang/Object;
   16      29      2    Q       Lscala/collection/immutable/BitSet;

  Signature: length = 0x2
   00 42 

public final java.lang.Object apply(java.lang.Object);
  Signature: (Ljava/lang/Object;)Ljava/lang/Object;
  Code:
   Stack=2, Locals=2, Args_size=2
	aload_0
	aload_1
	invokevirtual	Method apply:(Ljava/lang/Object;)V
	getstatic	Field scala/runtime/BoxedUnit.UNIT:Lscala/runtime/BoxedUnit;
	areturn
  Labels:
  LocalVariableTable: 
   Start  Length  Slot  Name   Signature
   0      9      0    this       Lscala/util/automata/SubsetConstruction$$anonfun$determinize$1;
   0      9      1    v1       Ljava/lang/Object;


public scala.util.automata.SubsetConstruction$$anonfun$determinize$1(scala.util.automata.SubsetConstruction, scala.runtime.ObjectRef, scala.runtime.ObjectRef, scala.collection.mutable.Stack, scala.collection.immutable.BitSet, scala.collection.mutable.HashMap);
  Signature: (Lscala/util/automata/SubsetConstruction;Lscala/runtime/ObjectRef;Lscala/runtime/ObjectRef;Lscala/collection/mutable/Stack;Lscala/collection/immutable/BitSet;Lscala/collection/mutable/HashMap;)V
  Code:
   Stack=2, Locals=7, Args_size=7
	aload_1
	ifnonnull	l1 // aload_0
	new	class java/lang/NullPointerException
	dup
	invokespecial	Method java/lang/NullPointerException."<init>":()V
	athrow
l1	aload_0
	aload_1
	putfield	Field $outer:Lscala/util/automata/SubsetConstruction;
	aload_0
	aload_2
	putfield	Field states$1:Lscala/runtime/ObjectRef;
	aload_0
	aload_3
	putfield	Field finals$1:Lscala/runtime/ObjectRef;
	aload_0
	aload	4
	putfield	Field rest$1:Lscala/collection/mutable/Stack;
	aload_0
	aload	5
	putfield	Field P$1:Lscala/collection/immutable/BitSet;
	aload_0
	aload	6
	putfield	Field Pdelta$1:Lscala/collection/mutable/HashMap;
	aload_0
	invokespecial	Method scala/runtime/AbstractFunction1."<init>":()V
	return
  Labels:
   	l1 = 12 // aload_0
  LocalVariableTable: 
   Start  Length  Slot  Name   Signature
   0      50      0    this       Lscala/util/automata/SubsetConstruction$$anonfun$determinize$1;
   0      50      1    $outer       Lscala/util/automata/SubsetConstruction;

  Signature: length = 0x2
   00 57 

}

