Compiled from "SubsetConstruction.scala"
public final class scala.util.automata.SubsetConstruction$$anon$1 extends scala.util.automata.DetWordAutom
  SourceFile: "SubsetConstruction.scala"
  Signature: length = 0x2
   00 29 
  Scala: length = 0x
   
  InnerClass: 
   public final $anon$1=class scala/util/automata/SubsetConstruction$$anon$1 of class scala/util/automata/SubsetConstruction
  minor version: 0
  major version: 49
  Constant pool:
Asciz	SourceFile;
Asciz	SubsetConstruction.scala;
Asciz	finals;
Asciz	[I;
Asciz	default;
Asciz	delta;
Asciz	[Lscala/collection/Map;;
Asciz	[Lscala/collection/Map<TT;Ljava/lang/Integer;>;;
Asciz	Signature;
Asciz	nstates;
Asciz	I;
Asciz	<init>;
Asciz	(Lscala/util/automata/SubsetConstruction;I[Lscala/collection/Map;[I[I)V;
Asciz	Code;
Asciz	LineNumberTable;
Asciz	scala/util/automata/DetWordAutom;
class	scala/util/automata/DetWordAutom
Asciz	()V;
NameAndType	"<init>":()V
Method	scala/util/automata/DetWordAutom."<init>":()V
Asciz	scala/util/automata/SubsetConstruction$$anon$1;
class	scala/util/automata/SubsetConstruction$$anon$1
NameAndType	nstates:I
Field	scala/util/automata/SubsetConstruction$$anon$1.nstates:I
NameAndType	delta:[Lscala/collection/Map;
Field	scala/util/automata/SubsetConstruction$$anon$1.delta:[Lscala/collection/Map;
NameAndType	default:[I
Field	scala/util/automata/SubsetConstruction$$anon$1.default:[I
NameAndType	finals:[I
Field	scala/util/automata/SubsetConstruction$$anon$1.finals:[I
Asciz	this;
Asciz	Lscala/util/automata/SubsetConstruction$$anon$1;;
Asciz	$outer;
Asciz	Lscala/util/automata/SubsetConstruction;;
Asciz	LocalVariableTable;
Asciz	(Lscala/util/automata/SubsetConstruction<TT;>;)V;
Asciz	()[I;
Asciz	()[Lscala/collection/Map;;
Asciz	()[Lscala/collection/Map<TT;Ljava/lang/Integer;>;;
Asciz	()I;
Asciz	Lscala/util/automata/DetWordAutom<TT;>;;
Asciz	Scala;
Asciz	InnerClasses;
Asciz	scala/util/automata/SubsetConstruction;
class	scala/util/automata/SubsetConstruction
Asciz	$anon$1;

{
private final int[] finals;
  Signature: [I

private final int[] default;
  Signature: [I

private final scala.collection.Map[] delta;
  Signature: [Lscala/collection/Map;
  Signature: length = 0x2
   00 08 

private final int nstates;
  Signature: I

public scala.util.automata.SubsetConstruction$$anon$1(scala.util.automata.SubsetConstruction, int, scala.collection.Map[], int[], int[]);
  Signature: (Lscala/util/automata/SubsetConstruction;I[Lscala/collection/Map;[I[I)V
  Code:
   Stack=2, Locals=6, Args_size=6
	aload_0
	invokespecial	Method scala/util/automata/DetWordAutom."<init>":()V
	aload_0
	iload_2
	putfield	Field nstates:I
	aload_0
	aload_3
	putfield	Field delta:[Lscala/collection/Map;
	aload_0
	aload	4
	putfield	Field default:[I
	aload_0
	aload	5
	putfield	Field finals:[I
	return
  Labels:
  LocalVariableTable: 
   Start  Length  Slot  Name   Signature
   0      27      0    this       Lscala/util/automata/SubsetConstruction$$anon$1;
   0      27      1    $outer       Lscala/util/automata/SubsetConstruction;

  Signature: length = 0x2
   00 24 

public int[] finals();
  Signature: ()[I
  Code:
   Stack=1, Locals=1, Args_size=1
	aload_0
	getfield	Field finals:[I
	areturn
  Labels:

public int[] default();
  Signature: ()[I
  Code:
   Stack=1, Locals=1, Args_size=1
	aload_0
	getfield	Field default:[I
	areturn
  Labels:

public scala.collection.Map[] delta();
  Signature: ()[Lscala/collection/Map;
  Code:
   Stack=1, Locals=1, Args_size=1
	aload_0
	getfield	Field delta:[Lscala/collection/Map;
	areturn
  Labels:
  Signature: length = 0x2
   00 27 

public int nstates();
  Signature: ()I
  Code:
   Stack=1, Locals=1, Args_size=1
	aload_0
	getfield	Field nstates:I
	ireturn
  Labels:

}

