Compiled from "SubsetConstruction.scala"
public final class scala.util.automata.SubsetConstruction$$anonfun$determinize$2$$anonfun$apply$1 extends scala.runtime.AbstractFunction1 implements java.io.Serializable
  SourceFile: "SubsetConstruction.scala"
  Scala: length = 0x
   
  InnerClass: 
   public final $anonfun$determinize$2=class scala/util/automata/SubsetConstruction$$anonfun$determinize$2 of class scala/util/automata/SubsetConstruction
   public final $anonfun$apply$1=class scala/util/automata/SubsetConstruction$$anonfun$determinize$2$$anonfun$apply$1 of class scala/util/automata/SubsetConstruction$$anonfun$determinize$2
  minor version: 0
  major version: 49
  Constant pool:
Asciz	SourceFile;
Asciz	SubsetConstruction.scala;
Asciz	<clinit>;
Asciz	()V;
Asciz	Code;
Asciz	serialVersionUID;
Asciz	J;
Asciz	scala/util/automata/SubsetConstruction$$anonfun$determinize$2$$anonfun$apply$1;
class	scala/util/automata/SubsetConstruction$$anonfun$determinize$2$$anonfun$apply$1
NameAndType	serialVersionUID:J
Field	scala/util/automata/SubsetConstruction$$anonfun$determinize$2$$anonfun$apply$1.serialVersionUID:J
Asciz	ntrans$1;
Asciz	Lscala/collection/mutable/HashMap;;
Asciz	qDef$1;
Asciz	I;
Asciz	$outer;
Asciz	Lscala/util/automata/SubsetConstruction$$anonfun$determinize$2;;
Asciz	<init>;
Asciz	(Lscala/util/automata/SubsetConstruction$$anonfun$determinize$2;ILscala/collection/mutable/HashMap;)V;
Asciz	LineNumberTable;
Asciz	java/lang/NullPointerException;
class	java/lang/NullPointerException
NameAndType	"<init>":()V
Method	java/lang/NullPointerException."<init>":()V
NameAndType	$outer:Lscala/util/automata/SubsetConstruction$$anonfun$determinize$2;
Field	scala/util/automata/SubsetConstruction$$anonfun$determinize$2$$anonfun$apply$1.$outer:Lscala/util/automata/SubsetConstruction$$anonfun$determinize$2;
NameAndType	qDef$1:I
Field	scala/util/automata/SubsetConstruction$$anonfun$determinize$2$$anonfun$apply$1.qDef$1:I
NameAndType	ntrans$1:Lscala/collection/mutable/HashMap;
Field	scala/util/automata/SubsetConstruction$$anonfun$determinize$2$$anonfun$apply$1.ntrans$1:Lscala/collection/mutable/HashMap;
Asciz	scala/runtime/AbstractFunction1;
class	scala/runtime/AbstractFunction1
Method	scala/runtime/AbstractFunction1."<init>":()V
Asciz	this;
Asciz	Lscala/util/automata/SubsetConstruction$$anonfun$determinize$2$$anonfun$apply$1;;
Asciz	LocalVariableTable;
Asciz	(Lscala/util/automata/SubsetConstruction<TT;>.$anonfun$determinize$2;)V;
Asciz	Signature;
Asciz	apply;
Asciz	(Ljava/lang/Object;)Ljava/lang/Object;;
Asciz	scala/Tuple2;
class	scala/Tuple2
Asciz	(Lscala/Tuple2;)V;
NameAndType	apply:(Lscala/Tuple2;)V
Method	scala/util/automata/SubsetConstruction$$anonfun$determinize$2$$anonfun$apply$1.apply:(Lscala/Tuple2;)V
Asciz	scala/runtime/BoxedUnit;
class	scala/runtime/BoxedUnit
Asciz	UNIT;
Asciz	Lscala/runtime/BoxedUnit;;
NameAndType	UNIT:Lscala/runtime/BoxedUnit;
Field	scala/runtime/BoxedUnit.UNIT:Lscala/runtime/BoxedUnit;
Asciz	v1;
Asciz	Ljava/lang/Object;;
Asciz	_1;
Asciz	()Ljava/lang/Object;;
NameAndType	_1:()Ljava/lang/Object;
Method	scala/Tuple2._1:()Ljava/lang/Object;
Asciz	_2;
NameAndType	_2:()Ljava/lang/Object;
Method	scala/Tuple2._2:()Ljava/lang/Object;
Asciz	scala/collection/immutable/BitSet;
class	scala/collection/immutable/BitSet
Asciz	scala/util/automata/SubsetConstruction$$anonfun$determinize$2;
class	scala/util/automata/SubsetConstruction$$anonfun$determinize$2
Asciz	indexMap$1;
Asciz	Lscala/runtime/ObjectRef;;
NameAndType	indexMap$1:Lscala/runtime/ObjectRef;
Field	scala/util/automata/SubsetConstruction$$anonfun$determinize$2.indexMap$1:Lscala/runtime/ObjectRef;
Asciz	scala/runtime/ObjectRef;
class	scala/runtime/ObjectRef
Asciz	elem;
NameAndType	elem:Ljava/lang/Object;
Field	scala/runtime/ObjectRef.elem:Ljava/lang/Object;
Asciz	scala/collection/Map;
class	scala/collection/Map
Asciz	scala/collection/MapLike;
class	scala/collection/MapLike
NameAndType	apply:(Ljava/lang/Object;)Ljava/lang/Object;
InterfaceMethod	scala/collection/MapLike.apply:(Ljava/lang/Object;)Ljava/lang/Object;
Asciz	scala/runtime/BoxesRunTime;
class	scala/runtime/BoxesRunTime
Asciz	unboxToInt;
Asciz	(Ljava/lang/Object;)I;
NameAndType	unboxToInt:(Ljava/lang/Object;)I
Method	scala/runtime/BoxesRunTime.unboxToInt:(Ljava/lang/Object;)I
Asciz	boxToInteger;
Asciz	(I)Ljava/lang/Integer;;
NameAndType	boxToInteger:(I)Ljava/lang/Integer;
Method	scala/runtime/BoxesRunTime.boxToInteger:(I)Ljava/lang/Integer;
Asciz	scala/collection/mutable/HashMap;
class	scala/collection/mutable/HashMap
Asciz	update;
Asciz	(Ljava/lang/Object;Ljava/lang/Object;)V;
NameAndType	update:(Ljava/lang/Object;Ljava/lang/Object;)V
Method	scala/collection/mutable/HashMap.update:(Ljava/lang/Object;Ljava/lang/Object;)V
Asciz	scala/MatchError;
class	scala/MatchError
Asciz	toString;
Asciz	()Ljava/lang/String;;
NameAndType	toString:()Ljava/lang/String;
Method	scala/Tuple2.toString:()Ljava/lang/String;
Asciz	(Ljava/lang/String;)V;
NameAndType	"<init>":(Ljava/lang/String;)V
Method	scala/MatchError."<init>":(Ljava/lang/String;)V
Asciz	temp3;
Asciz	Lscala/collection/immutable/BitSet;;
Asciz	temp2;
Asciz	p;
Asciz	(Lscala/Tuple2<TT;Lscala/collection/immutable/BitSet;>;)V;
Asciz	Scala;
Asciz	InnerClasses;
Asciz	scala/util/automata/SubsetConstruction;
class	scala/util/automata/SubsetConstruction
Asciz	$anonfun$determinize$2;
Asciz	$anonfun$apply$1;
Asciz	java/io/Serializable;
class	java/io/Serializable

{
public static final long serialVersionUID;
  Signature: J

public final scala.collection.mutable.HashMap ntrans$1;
  Signature: Lscala/collection/mutable/HashMap;

public final int qDef$1;
  Signature: I

public final scala.util.automata.SubsetConstruction$$anonfun$determinize$2 $outer;
  Signature: Lscala/util/automata/SubsetConstruction$$anonfun$determinize$2;

public static {};
  Signature: ()V
  Code:
   Stack=2, Locals=0, Args_size=0
	lconst_0
	putstatic	Field serialVersionUID:J
	return
  Labels:

public scala.util.automata.SubsetConstruction$$anonfun$determinize$2$$anonfun$apply$1(scala.util.automata.SubsetConstruction$$anonfun$determinize$2, int, scala.collection.mutable.HashMap);
  Signature: (Lscala/util/automata/SubsetConstruction$$anonfun$determinize$2;ILscala/collection/mutable/HashMap;)V
  Code:
   Stack=2, Locals=4, Args_size=4
	aload_1
	ifnonnull	l1 // aload_0
	new	class java/lang/NullPointerException
	dup
	invokespecial	Method java/lang/NullPointerException."<init>":()V
	athrow
l1	aload_0
	aload_1
	putfield	Field $outer:Lscala/util/automata/SubsetConstruction$$anonfun$determinize$2;
	aload_0
	iload_2
	putfield	Field qDef$1:I
	aload_0
	aload_3
	putfield	Field ntrans$1:Lscala/collection/mutable/HashMap;
	aload_0
	invokespecial	Method scala/runtime/AbstractFunction1."<init>":()V
	return
  Labels:
   	l1 = 12 // aload_0
  LocalVariableTable: 
   Start  Length  Slot  Name   Signature
   0      32      0    this       Lscala/util/automata/SubsetConstruction$$anonfun$determinize$2$$anonfun$apply$1;
   0      32      1    $outer       Lscala/util/automata/SubsetConstruction$$anonfun$determinize$2;

  Signature: length = 0x2
   00 25 

public final java.lang.Object apply(java.lang.Object);
  Signature: (Ljava/lang/Object;)Ljava/lang/Object;
  Code:
   Stack=2, Locals=2, Args_size=2
	aload_0
	aload_1
	checkcast	class scala/Tuple2
	invokevirtual	Method apply:(Lscala/Tuple2;)V
	getstatic	Field scala/runtime/BoxedUnit.UNIT:Lscala/runtime/BoxedUnit;
	areturn
  Labels:
  LocalVariableTable: 
   Start  Length  Slot  Name   Signature
   0      12      0    this       Lscala/util/automata/SubsetConstruction$$anonfun$determinize$2$$anonfun$apply$1;
   0      12      1    v1       Ljava/lang/Object;


public final void apply(scala.Tuple2);
  Signature: (Lscala/Tuple2;)V
  Code:
   Stack=3, Locals=5, Args_size=2
	aload_1
	ifnull	l1 // new
	aload_1
	invokevirtual	Method scala/Tuple2._1:()Ljava/lang/Object;
	astore_3
	aload_1
	invokevirtual	Method scala/Tuple2._2:()Ljava/lang/Object;
	checkcast	class scala/collection/immutable/BitSet
	astore_2
	aload_0
	getfield	Field $outer:Lscala/util/automata/SubsetConstruction$$anonfun$determinize$2;
	getfield	Field scala/util/automata/SubsetConstruction$$anonfun$determinize$2.indexMap$1:Lscala/runtime/ObjectRef;
	getfield	Field scala/runtime/ObjectRef.elem:Ljava/lang/Object;
	checkcast	class scala/collection/Map
	aload_2
	invokeinterface	InterfaceMethod scala/collection/MapLike.apply:(Ljava/lang/Object;)Ljava/lang/Object;
	invokestatic	Method scala/runtime/BoxesRunTime.unboxToInt:(Ljava/lang/Object;)I
	istore	4
	iload	4
	aload_0
	getfield	Field qDef$1:I
	if_icmpeq	l2 // return
	aload_0
	getfield	Field ntrans$1:Lscala/collection/mutable/HashMap;
	aload_3
	iload	4
	invokestatic	Method scala/runtime/BoxesRunTime.boxToInteger:(I)Ljava/lang/Integer;
	invokevirtual	Method scala/collection/mutable/HashMap.update:(Ljava/lang/Object;Ljava/lang/Object;)V
l2	return
l1	new	class scala/MatchError
	dup
	aload_1
	invokevirtual	Method scala/Tuple2.toString:()Ljava/lang/String;
	invokespecial	Method scala/MatchError."<init>":(Ljava/lang/String;)V
	athrow
  Labels:
   	l2 = 63 // return
   	l1 = 64 // new
  LocalVariableTable: 
   Start  Length  Slot  Name   Signature
   0      76      0    this       Lscala/util/automata/SubsetConstruction$$anonfun$determinize$2$$anonfun$apply$1;
   17      46      2    temp3       Lscala/collection/immutable/BitSet;
   9      54      3    temp2       Ljava/lang/Object;
   41      22      4    p       I

  Signature: length = 0x2
   00 6D 

}

