Compiled from "SubsetConstruction.scala"
public class scala.util.automata.SubsetConstruction extends java.lang.Object implements scala.ScalaObject
  SourceFile: "SubsetConstruction.scala"
  Signature: length = 0x2
   01 0F 
  ScalaSig: length = 0x1CB
   05 00 4B 06 04 01 02 00 09 02 12 53 75 62 73 65
   74 43 6F 6E 73 74 72 75 63 74 69 6F 6E 0A 02 03
   04 01 08 61 75 74 6F 6D 61 74 61 0A 02 05 06 01
   04 75 74 69 6C 0A 01 07 01 05 73 63 61 6C 61 03
   00 15 02 0A 20 13 03 00 0B 13 10 02 0C 11 0D 01
   0D 0A 02 0E 0F 01 04 6C 61 6E 67 0A 01 10 01 04
   6A 61 76 61 09 02 12 0D 02 06 4F 62 6A 65 63 74
   10 02 14 15 0D 01 06 09 02 16 06 02 0B 53 63 61
   6C 61 4F 62 6A 65 63 74 08 08 18 00 FFFFFF82 FFFFFFC2 FFFFFF80 FFFFFF84
   00 19 01 03 6E 66 61 15 01 1A 10 03 1B 1C 1E 0D
   01 02 09 02 1D 02 02 0F 4E 6F 6E 64 65 74 57 6F
   72 64 41 75 74 6F 6D 10 02 1F 20 0C 00 04 08 21
   00 FFFFFF84 FFFFFF80 FFFFFF80 FFFFFFC2 00 22 02 01 54 11 02 23 26 10 02
   14 24 09 02 25 06 02 07 4E 6F 74 68 69 6E 67 10
   02 14 27 09 02 28 06 02 06 41 6E 79 52 65 66 08
   08 2A 00 FFFFFF82 FFFFFF80 FFFFFFA0 FFFFFF80 04 1A 01 04 6E 66 61 20 08
   05 2C 00 FFFFFF84 00 2D 01 06 3C 69 6E 69 74 3E 14 02
   2E 2F 10 03 1B 00 1E 08 05 18 2B FFFFFFC0 00 1A 08 05
   31 00 FFFFFF84 00 32 01 09 73 65 6C 65 63 74 54 61 67
   14 03 33 36 40 10 02 14 34 09 02 35 06 02 03 49
   6E 74 08 05 37 30 FFFFFFC0 00 38 01 01 51 10 02 39 3E
   0D 01 3A 0A 02 3B 3C 01 09 69 6D 6D 75 74 61 62
   6C 65 0A 02 3D 06 01 0A 63 6F 6C 6C 65 63 74 69
   6F 6E 09 02 3F 3A 02 06 42 69 74 53 65 74 08 05
   41 30 FFFFFFC0 00 42 01 06 66 69 6E 61 6C 73 10 03 14
   43 33 09 02 44 06 02 05 41 72 72 61 79 08 05 46
   00 FFFFFF84 00 47 01 0B 64 65 74 65 72 6D 69 6E 69 7A
   65 15 01 48 10 03 1B 49 1E 09 02 4A 02 02 0C 44
   65 74 57 6F 72 64 41 75 74 6F 6D 
  InnerClass: 
   public final ArrowAssoc=class scala/Predef$ArrowAssoc of class scala/Predef
   public final $anon$1=class scala/util/automata/SubsetConstruction$$anon$1 of class scala/util/automata/SubsetConstruction
   public final $anonfun$selectTag$1=class scala/util/automata/SubsetConstruction$$anonfun$selectTag$1 of class scala/util/automata/SubsetConstruction
   public final $anonfun$containsFinal$1=class scala/util/automata/NondetWordAutom$$anonfun$containsFinal$1 of class scala/util/automata/NondetWordAutom
   public final $anonfun$determinize$1=class scala/util/automata/SubsetConstruction$$anonfun$determinize$1 of class scala/util/automata/SubsetConstruction
   public final $anonfun$determinize$3=class scala/util/automata/SubsetConstruction$$anonfun$determinize$3 of class scala/util/automata/SubsetConstruction
   public final $anonfun$determinize$2=class scala/util/automata/SubsetConstruction$$anonfun$determinize$2 of class scala/util/automata/SubsetConstruction
  minor version: 0
  major version: 49
  Constant pool:
Asciz	SourceFile;
Asciz	SubsetConstruction.scala;
Asciz	nfa;
Asciz	Lscala/util/automata/NondetWordAutom;;
Asciz	Lscala/util/automata/NondetWordAutom<TT;>;;
Asciz	Signature;
Asciz	<init>;
Asciz	(Lscala/util/automata/NondetWordAutom;)V;
Asciz	Code;
Asciz	LineNumberTable;
Asciz	scala/util/automata/SubsetConstruction;
class	scala/util/automata/SubsetConstruction
NameAndType	nfa:Lscala/util/automata/NondetWordAutom;
Field	scala/util/automata/SubsetConstruction.nfa:Lscala/util/automata/NondetWordAutom;
Asciz	java/lang/Object;
class	java/lang/Object
Asciz	()V;
NameAndType	"<init>":()V
Method	java/lang/Object."<init>":()V
Asciz	this;
Asciz	Lscala/util/automata/SubsetConstruction;;
Asciz	LocalVariableTable;
Asciz	(Lscala/util/automata/NondetWordAutom<TT;>;)V;
Asciz	add$1;
Asciz	(Lscala/collection/immutable/BitSet;Lscala/runtime/ObjectRef;Lscala/runtime/ObjectRef;Lscala/collection/mutable/Stack;)V;
Asciz	scala/runtime/ObjectRef;
class	scala/runtime/ObjectRef
Asciz	elem;
Asciz	Ljava/lang/Object;;
NameAndType	elem:Ljava/lang/Object;
Field	scala/runtime/ObjectRef.elem:Ljava/lang/Object;
Asciz	scala/collection/immutable/Set;
class	scala/collection/immutable/Set
Asciz	scala/collection/SetLike;
class	scala/collection/SetLike
Asciz	contains;
Asciz	(Ljava/lang/Object;)Z;
NameAndType	contains:(Ljava/lang/Object;)Z
InterfaceMethod	scala/collection/SetLike.contains:(Ljava/lang/Object;)Z
Asciz	$plus;
Asciz	(Ljava/lang/Object;)Lscala/collection/Set;;
NameAndType	$plus:(Ljava/lang/Object;)Lscala/collection/Set;
InterfaceMethod	scala/collection/SetLike.$plus:(Ljava/lang/Object;)Lscala/collection/Set;
Asciz	scala/collection/mutable/Stack;
class	scala/collection/mutable/Stack
Asciz	push;
Asciz	(Ljava/lang/Object;)Lscala/collection/mutable/Stack;;
NameAndType	push:(Ljava/lang/Object;)Lscala/collection/mutable/Stack;
Method	scala/collection/mutable/Stack.push:(Ljava/lang/Object;)Lscala/collection/mutable/Stack;
Asciz	addFinal$1;
Asciz	(Lscala/collection/immutable/BitSet;Lscala/runtime/ObjectRef;)V;
NameAndType	addFinal$1:(Lscala/collection/immutable/BitSet;Lscala/runtime/ObjectRef;)V
Method	scala/util/automata/SubsetConstruction.addFinal$1:(Lscala/collection/immutable/BitSet;Lscala/runtime/ObjectRef;)V
Asciz	Q;
Asciz	Lscala/collection/immutable/BitSet;;
Asciz	()Lscala/util/automata/NondetWordAutom;;
NameAndType	nfa:()Lscala/util/automata/NondetWordAutom;
Method	scala/util/automata/SubsetConstruction.nfa:()Lscala/util/automata/NondetWordAutom;
Asciz	scala/util/automata/NondetWordAutom$$anonfun$containsFinal$1;
class	scala/util/automata/NondetWordAutom$$anonfun$containsFinal$1
NameAndType	"<init>":(Lscala/util/automata/NondetWordAutom;)V
Method	scala/util/automata/NondetWordAutom$$anonfun$containsFinal$1."<init>":(Lscala/util/automata/NondetWordAutom;)V
Asciz	scala/collection/IterableLike;
class	scala/collection/IterableLike
Asciz	exists;
Asciz	(Lscala/Function1;)Z;
NameAndType	exists:(Lscala/Function1;)Z
InterfaceMethod	scala/collection/IterableLike.exists:(Lscala/Function1;)Z
Asciz	scala/collection/Map;
class	scala/collection/Map
Asciz	scala/util/automata/NondetWordAutom;
class	scala/util/automata/NondetWordAutom
Asciz	finals;
Asciz	()[I;
NameAndType	finals:()[I
Method	scala/util/automata/NondetWordAutom.finals:()[I
Asciz	selectTag;
Asciz	(Lscala/collection/immutable/BitSet;[I)I;
NameAndType	selectTag:(Lscala/collection/immutable/BitSet;[I)I
Method	scala/util/automata/SubsetConstruction.selectTag:(Lscala/collection/immutable/BitSet;[I)I
Asciz	scala/runtime/BoxesRunTime;
class	scala/runtime/BoxesRunTime
Asciz	boxToInteger;
Asciz	(I)Ljava/lang/Integer;;
NameAndType	boxToInteger:(I)Ljava/lang/Integer;
Method	scala/runtime/BoxesRunTime.boxToInteger:(I)Ljava/lang/Integer;
Asciz	scala/collection/MapLike;
class	scala/collection/MapLike
Asciz	updated;
Asciz	(Ljava/lang/Object;Ljava/lang/Object;)Lscala/collection/Map;;
NameAndType	updated:(Ljava/lang/Object;Ljava/lang/Object;)Lscala/collection/Map;
InterfaceMethod	scala/collection/MapLike.updated:(Ljava/lang/Object;Ljava/lang/Object;)Lscala/collection/Map;
Asciz	q;
Asciz	determinize;
Asciz	()Lscala/util/automata/DetWordAutom;;
Asciz	scala/collection/Map$;
class	scala/collection/Map$
Asciz	MODULE$;
Asciz	Lscala/collection/Map$;;
NameAndType	MODULE$:Lscala/collection/Map$;
Field	scala/collection/Map$.MODULE$:Lscala/collection/Map$;
Asciz	scala/Predef$;
class	scala/Predef$
Asciz	Lscala/Predef$;;
NameAndType	MODULE$:Lscala/Predef$;
Field	scala/Predef$.MODULE$:Lscala/Predef$;
Asciz	scala/Tuple2;
class	scala/Tuple2
Asciz	[Ljava/lang/Object;;
class	"[Ljava/lang/Object;"
Asciz	wrapRefArray;
Asciz	([Ljava/lang/Object;)Lscala/collection/mutable/WrappedArray;;
NameAndType	wrapRefArray:([Ljava/lang/Object;)Lscala/collection/mutable/WrappedArray;
Method	scala/Predef$.wrapRefArray:([Ljava/lang/Object;)Lscala/collection/mutable/WrappedArray;
Asciz	apply;
Asciz	(Lscala/collection/Seq;)Lscala/collection/Map;;
NameAndType	apply:(Lscala/collection/Seq;)Lscala/collection/Map;
Method	scala/collection/Map$.apply:(Lscala/collection/Seq;)Lscala/collection/Map;
Asciz	(Ljava/lang/Object;)V;
NameAndType	"<init>":(Ljava/lang/Object;)V
Method	scala/runtime/ObjectRef."<init>":(Ljava/lang/Object;)V
Asciz	scala/collection/immutable/BitSet$;
class	scala/collection/immutable/BitSet$
Asciz	Lscala/collection/immutable/BitSet$;;
NameAndType	MODULE$:Lscala/collection/immutable/BitSet$;
Field	scala/collection/immutable/BitSet$.MODULE$:Lscala/collection/immutable/BitSet$;
Asciz	wrapIntArray;
Asciz	([I)Lscala/collection/mutable/WrappedArray;;
NameAndType	wrapIntArray:([I)Lscala/collection/mutable/WrappedArray;
Method	scala/Predef$.wrapIntArray:([I)Lscala/collection/mutable/WrappedArray;
Asciz	scala/collection/generic/BitSetFactory$class;
class	scala/collection/generic/BitSetFactory$class
Asciz	(Lscala/collection/generic/BitSetFactory;Lscala/collection/Seq;)Lscala/collection/BitSet;;
NameAndType	apply:(Lscala/collection/generic/BitSetFactory;Lscala/collection/Seq;)Lscala/collection/BitSet;
Method	scala/collection/generic/BitSetFactory$class.apply:(Lscala/collection/generic/BitSetFactory;Lscala/collection/Seq;)Lscala/collection/BitSet;
Asciz	scala/collection/immutable/BitSet;
class	scala/collection/immutable/BitSet
Asciz	empty;
Asciz	()Lscala/collection/immutable/BitSet;;
NameAndType	empty:()Lscala/collection/immutable/BitSet;
Method	scala/collection/immutable/BitSet$.empty:()Lscala/collection/immutable/BitSet;
Asciz	Set;
Asciz	()Lscala/collection/immutable/Set$;;
NameAndType	Set:()Lscala/collection/immutable/Set$;
Method	scala/Predef$.Set:()Lscala/collection/immutable/Set$;
Asciz	scala/collection/immutable/Set$;
class	scala/collection/immutable/Set$
Asciz	(Lscala/collection/Seq;)Lscala/collection/Traversable;;
NameAndType	apply:(Lscala/collection/Seq;)Lscala/collection/Traversable;
Method	scala/collection/immutable/Set$.apply:(Lscala/collection/Seq;)Lscala/collection/Traversable;
Asciz	scala/collection/mutable/HashMap;
class	scala/collection/mutable/HashMap
Method	scala/collection/mutable/HashMap."<init>":()V
Asciz	scala/Predef$ArrowAssoc;
class	scala/Predef$ArrowAssoc
Method	scala/Predef$ArrowAssoc."<init>":(Ljava/lang/Object;)V
Asciz	(Ljava/lang/Object;Ljava/lang/Object;)V;
NameAndType	"<init>":(Ljava/lang/Object;Ljava/lang/Object;)V
Method	scala/Tuple2."<init>":(Ljava/lang/Object;Ljava/lang/Object;)V
Method	scala/collection/mutable/Stack."<init>":()V
Asciz	(Ljava/lang/Object;Ljava/lang/Object;Lscala/collection/Seq;)Lscala/collection/mutable/Stack;;
NameAndType	push:(Ljava/lang/Object;Ljava/lang/Object;Lscala/collection/Seq;)Lscala/collection/mutable/Stack;
Method	scala/collection/mutable/Stack.push:(Ljava/lang/Object;Ljava/lang/Object;Lscala/collection/Seq;)Lscala/collection/mutable/Stack;
Asciz	isEmpty;
Asciz	()Z;
NameAndType	isEmpty:()Z
Method	scala/collection/mutable/Stack.isEmpty:()Z
Asciz	scala/collection/TraversableLike;
class	scala/collection/TraversableLike
Asciz	size;
Asciz	()I;
NameAndType	size:()I
InterfaceMethod	scala/collection/TraversableLike.size:()I
Asciz	scala/util/automata/SubsetConstruction$$anonfun$determinize$2;
class	scala/util/automata/SubsetConstruction$$anonfun$determinize$2
Asciz	(Lscala/util/automata/SubsetConstruction;Lscala/runtime/ObjectRef;Lscala/collection/mutable/HashMap;Lscala/runtime/ObjectRef;[Lscala/collection/Map;[I)V;
NameAndType	"<init>":(Lscala/util/automata/SubsetConstruction;Lscala/runtime/ObjectRef;Lscala/collection/mutable/HashMap;Lscala/runtime/ObjectRef;[Lscala/collection/Map;[I)V
Method	scala/util/automata/SubsetConstruction$$anonfun$determinize$2."<init>":(Lscala/util/automata/SubsetConstruction;Lscala/runtime/ObjectRef;Lscala/collection/mutable/HashMap;Lscala/runtime/ObjectRef;[Lscala/collection/Map;[I)V
Asciz	foreach;
Asciz	(Lscala/Function1;)V;
NameAndType	foreach:(Lscala/Function1;)V
InterfaceMethod	scala/collection/IterableLike.foreach:(Lscala/Function1;)V
Asciz	scala/util/automata/SubsetConstruction$$anonfun$determinize$3;
class	scala/util/automata/SubsetConstruction$$anonfun$determinize$3
Asciz	(Lscala/util/automata/SubsetConstruction;Lscala/runtime/ObjectRef;[I)V;
NameAndType	"<init>":(Lscala/util/automata/SubsetConstruction;Lscala/runtime/ObjectRef;[I)V
Method	scala/util/automata/SubsetConstruction$$anonfun$determinize$3."<init>":(Lscala/util/automata/SubsetConstruction;Lscala/runtime/ObjectRef;[I)V
Asciz	scala/util/automata/SubsetConstruction$$anon$1;
class	scala/util/automata/SubsetConstruction$$anon$1
Asciz	(Lscala/util/automata/SubsetConstruction;I[Lscala/collection/Map;[I[I)V;
NameAndType	"<init>":(Lscala/util/automata/SubsetConstruction;I[Lscala/collection/Map;[I[I)V
Method	scala/util/automata/SubsetConstruction$$anon$1."<init>":(Lscala/util/automata/SubsetConstruction;I[Lscala/collection/Map;[I[I)V
Asciz	pop;
Asciz	()Ljava/lang/Object;;
NameAndType	pop:()Ljava/lang/Object;
Method	scala/collection/mutable/Stack.pop:()Ljava/lang/Object;
Asciz	update;
NameAndType	update:(Ljava/lang/Object;Ljava/lang/Object;)V
Method	scala/collection/mutable/HashMap.update:(Ljava/lang/Object;Ljava/lang/Object;)V
Asciz	labels;
Asciz	()Lscala/collection/Seq;;
NameAndType	labels:()Lscala/collection/Seq;
Method	scala/util/automata/NondetWordAutom.labels:()Lscala/collection/Seq;
Asciz	scala/util/automata/SubsetConstruction$$anonfun$determinize$1;
class	scala/util/automata/SubsetConstruction$$anonfun$determinize$1
Asciz	(Lscala/util/automata/SubsetConstruction;Lscala/runtime/ObjectRef;Lscala/runtime/ObjectRef;Lscala/collection/mutable/Stack;Lscala/collection/immutable/BitSet;Lscala/collection/mutable/HashMap;)V;
NameAndType	"<init>":(Lscala/util/automata/SubsetConstruction;Lscala/runtime/ObjectRef;Lscala/runtime/ObjectRef;Lscala/collection/mutable/Stack;Lscala/collection/immutable/BitSet;Lscala/collection/mutable/HashMap;)V
Method	scala/util/automata/SubsetConstruction$$anonfun$determinize$1."<init>":(Lscala/util/automata/SubsetConstruction;Lscala/runtime/ObjectRef;Lscala/runtime/ObjectRef;Lscala/collection/mutable/Stack;Lscala/collection/immutable/BitSet;Lscala/collection/mutable/HashMap;)V
Asciz	nextDefault;
Asciz	(Lscala/collection/immutable/BitSet;)Lscala/collection/immutable/BitSet;;
NameAndType	nextDefault:(Lscala/collection/immutable/BitSet;)Lscala/collection/immutable/BitSet;
Method	scala/util/automata/NondetWordAutom.nextDefault:(Lscala/collection/immutable/BitSet;)Lscala/collection/immutable/BitSet;
NameAndType	add$1:(Lscala/collection/immutable/BitSet;Lscala/runtime/ObjectRef;Lscala/runtime/ObjectRef;Lscala/collection/mutable/Stack;)V
Method	scala/util/automata/SubsetConstruction.add$1:(Lscala/collection/immutable/BitSet;Lscala/runtime/ObjectRef;Lscala/runtime/ObjectRef;Lscala/collection/mutable/Stack;)V
Asciz	sink;
Asciz	q0;
Asciz	nstatesR$1;
Asciz	I;
Asciz	deltaR$1;
Asciz	[Lscala/collection/Map;;
Asciz	defaultR$1;
Asciz	[I;
Asciz	finalsR$1;
Asciz	indexMap$1;
Asciz	Lscala/runtime/ObjectRef;;
Asciz	invIndexMap;
Asciz	Lscala/collection/Map;;
Asciz	ix;
Asciz	delta$1;
Asciz	Lscala/collection/mutable/HashMap;;
Asciz	Pdelta$1;
Asciz	deftrans$1;
Asciz	P$1;
Asciz	Pdef;
Asciz	states$1;
Asciz	finals$1;
Asciz	rest$1;
Asciz	Lscala/collection/mutable/Stack;;
Asciz	()Lscala/util/automata/DetWordAutom<TT;>;;
Asciz	canBuildFrom;
Asciz	()Lscala/collection/generic/CanBuildFrom;;
NameAndType	canBuildFrom:()Lscala/collection/generic/CanBuildFrom;
Method	scala/collection/immutable/BitSet$.canBuildFrom:()Lscala/collection/generic/CanBuildFrom;
Asciz	map;
Asciz	(Lscala/Function1;Lscala/collection/generic/CanBuildFrom;)Ljava/lang/Object;;
NameAndType	map:(Lscala/Function1;Lscala/collection/generic/CanBuildFrom;)Ljava/lang/Object;
InterfaceMethod	scala/collection/TraversableLike.map:(Lscala/Function1;Lscala/collection/generic/CanBuildFrom;)Ljava/lang/Object;
Asciz	scala/util/automata/SubsetConstruction$$anonfun$selectTag$1;
class	scala/util/automata/SubsetConstruction$$anonfun$selectTag$1
Asciz	(Lscala/util/automata/SubsetConstruction;)V;
NameAndType	"<init>":(Lscala/util/automata/SubsetConstruction;)V
Method	scala/util/automata/SubsetConstruction$$anonfun$selectTag$1."<init>":(Lscala/util/automata/SubsetConstruction;)V
Asciz	filter;
Asciz	(Lscala/Function1;)Ljava/lang/Object;;
NameAndType	filter:(Lscala/Function1;)Ljava/lang/Object;
InterfaceMethod	scala/collection/TraversableLike.filter:(Lscala/Function1;)Ljava/lang/Object;
Asciz	scala/math/Ordering$Int$;
class	scala/math/Ordering$Int$
Asciz	Lscala/math/Ordering$Int$;;
NameAndType	MODULE$:Lscala/math/Ordering$Int$;
Field	scala/math/Ordering$Int$.MODULE$:Lscala/math/Ordering$Int$;
Asciz	min;
Asciz	(Lscala/math/Ordering;)Ljava/lang/Object;;
NameAndType	min:(Lscala/math/Ordering;)Ljava/lang/Object;
InterfaceMethod	scala/collection/TraversableLike.min:(Lscala/math/Ordering;)Ljava/lang/Object;
Asciz	unboxToInt;
Asciz	(Ljava/lang/Object;)I;
NameAndType	unboxToInt:(Ljava/lang/Object;)I
Method	scala/runtime/BoxesRunTime.unboxToInt:(Ljava/lang/Object;)I
Asciz	()Lscala/util/automata/NondetWordAutom<TT;>;;
Asciz	<T:Ljava/lang/Object;>Ljava/lang/Object;Lscala/ScalaObject;;
Asciz	ScalaSig;
Asciz	InnerClasses;
Asciz	scala/Predef;
class	scala/Predef
Asciz	ArrowAssoc;
Asciz	$anon$1;
Asciz	$anonfun$selectTag$1;
Asciz	$anonfun$containsFinal$1;
Asciz	$anonfun$determinize$1;
Asciz	$anonfun$determinize$3;
Asciz	$anonfun$determinize$2;
Asciz	scala/ScalaObject;
class	scala/ScalaObject

{
private final scala.util.automata.NondetWordAutom nfa;
  Signature: Lscala/util/automata/NondetWordAutom;
  Signature: length = 0x2
   00 05 

public scala.util.automata.SubsetConstruction(scala.util.automata.NondetWordAutom);
  Signature: (Lscala/util/automata/NondetWordAutom;)V
  Code:
   Stack=2, Locals=2, Args_size=2
	aload_0
	aload_1
	putfield	Field nfa:Lscala/util/automata/NondetWordAutom;
	aload_0
	invokespecial	Method java/lang/Object."<init>":()V
	return
  Labels:
  LocalVariableTable: 
   Start  Length  Slot  Name   Signature
   0      10      0    this       Lscala/util/automata/SubsetConstruction;
   0      10      1    nfa       Lscala/util/automata/NondetWordAutom;

  Signature: length = 0x2
   00 17 

public final void add$1(scala.collection.immutable.BitSet, scala.runtime.ObjectRef, scala.runtime.ObjectRef, scala.collection.mutable.Stack);
  Signature: (Lscala/collection/immutable/BitSet;Lscala/runtime/ObjectRef;Lscala/runtime/ObjectRef;Lscala/collection/mutable/Stack;)V
  Code:
   Stack=3, Locals=5, Args_size=5
	aload_2
	getfield	Field scala/runtime/ObjectRef.elem:Ljava/lang/Object;
	checkcast	class scala/collection/immutable/Set
	aload_1
	invokeinterface	InterfaceMethod scala/collection/SetLike.contains:(Ljava/lang/Object;)Z
	ifne	l1 // return
	aload_2
	aload_2
	getfield	Field scala/runtime/ObjectRef.elem:Ljava/lang/Object;
	checkcast	class scala/collection/immutable/Set
	aload_1
	invokeinterface	InterfaceMethod scala/collection/SetLike.$plus:(Ljava/lang/Object;)Lscala/collection/Set;
	checkcast	class scala/collection/immutable/Set
	putfield	Field scala/runtime/ObjectRef.elem:Ljava/lang/Object;
	aload	4
	aload_1
	invokevirtual	Method scala/collection/mutable/Stack.push:(Ljava/lang/Object;)Lscala/collection/mutable/Stack;
	pop
	aload_0
	aload_1
	aload_3
	invokespecial	Method addFinal$1:(Lscala/collection/immutable/BitSet;Lscala/runtime/ObjectRef;)V
l1	return
  Labels:
   	l1 = 49 // return
  LocalVariableTable: 
   Start  Length  Slot  Name   Signature
   0      50      0    this       Lscala/util/automata/SubsetConstruction;
   0      50      1    Q       Lscala/collection/immutable/BitSet;


private final void addFinal$1(scala.collection.immutable.BitSet, scala.runtime.ObjectRef);
  Signature: (Lscala/collection/immutable/BitSet;Lscala/runtime/ObjectRef;)V
  Code:
   Stack=6, Locals=5, Args_size=3
	aload_0
	invokevirtual	Method nfa:()Lscala/util/automata/NondetWordAutom;
	astore_3
	aload_1
	new	class scala/util/automata/NondetWordAutom$$anonfun$containsFinal$1
	dup
	aload_3
	invokespecial	Method scala/util/automata/NondetWordAutom$$anonfun$containsFinal$1."<init>":(Lscala/util/automata/NondetWordAutom;)V
	invokeinterface	InterfaceMethod scala/collection/IterableLike.exists:(Lscala/Function1;)Z
	ifeq	l1 // return
	aload_2
	aload_2
	getfield	Field scala/runtime/ObjectRef.elem:Ljava/lang/Object;
	checkcast	class scala/collection/Map
	aload_1
	aload_0
	aload_1
	aload_0
	invokevirtual	Method nfa:()Lscala/util/automata/NondetWordAutom;
	invokevirtual	Method scala/util/automata/NondetWordAutom.finals:()[I
	invokevirtual	Method selectTag:(Lscala/collection/immutable/BitSet;[I)I
	istore	4
	iload	4
	invokestatic	Method scala/runtime/BoxesRunTime.boxToInteger:(I)Ljava/lang/Integer;
	invokeinterface	InterfaceMethod scala/collection/MapLike.updated:(Ljava/lang/Object;Ljava/lang/Object;)Lscala/collection/Map;
	putfield	Field scala/runtime/ObjectRef.elem:Ljava/lang/Object;
l1	return
  Labels:
   	l1 = 58 // return
  LocalVariableTable: 
   Start  Length  Slot  Name   Signature
   0      59      0    this       Lscala/util/automata/SubsetConstruction;
   0      59      1    q       Lscala/collection/immutable/BitSet;


public scala.util.automata.DetWordAutom determinize();
  Signature: ()Lscala/util/automata/DetWordAutom;
  Code:
   Stack=11, Locals=20, Args_size=1
	new	class scala/runtime/ObjectRef
	dup
	getstatic	Field scala/collection/Map$.MODULE$:Lscala/collection/Map$;
	getstatic	Field scala/Predef$.MODULE$:Lscala/Predef$;
	iconst_0
	anewarray	class scala/Tuple2
	checkcast	class "[Ljava/lang/Object;"
	invokevirtual	Method scala/Predef$.wrapRefArray:([Ljava/lang/Object;)Lscala/collection/mutable/WrappedArray;
	invokevirtual	Method scala/collection/Map$.apply:(Lscala/collection/Seq;)Lscala/collection/Map;
	invokespecial	Method scala/runtime/ObjectRef."<init>":(Ljava/lang/Object;)V
	astore	9
	getstatic	Field scala/collection/Map$.MODULE$:Lscala/collection/Map$;
	getstatic	Field scala/Predef$.MODULE$:Lscala/Predef$;
	iconst_0
	anewarray	class scala/Tuple2
	checkcast	class "[Ljava/lang/Object;"
	invokevirtual	Method scala/Predef$.wrapRefArray:([Ljava/lang/Object;)Lscala/collection/mutable/WrappedArray;
	invokevirtual	Method scala/collection/Map$.apply:(Lscala/collection/Seq;)Lscala/collection/Map;
	astore	10
	iconst_0
	istore	11
	getstatic	Field scala/collection/immutable/BitSet$.MODULE$:Lscala/collection/immutable/BitSet$;
	getstatic	Field scala/Predef$.MODULE$:Lscala/Predef$;
	iconst_1
	newarray int
	dup
	iconst_0
	iconst_0
	iastore
	invokevirtual	Method scala/Predef$.wrapIntArray:([I)Lscala/collection/mutable/WrappedArray;
	astore_2
	astore_1
	aload_1
	aload_2
	invokestatic	Method scala/collection/generic/BitSetFactory$class.apply:(Lscala/collection/generic/BitSetFactory;Lscala/collection/Seq;)Lscala/collection/BitSet;
	checkcast	class scala/collection/immutable/BitSet
	astore	4
	getstatic	Field scala/collection/immutable/BitSet$.MODULE$:Lscala/collection/immutable/BitSet$;
	invokevirtual	Method scala/collection/immutable/BitSet$.empty:()Lscala/collection/immutable/BitSet;
	astore_3
	new	class scala/runtime/ObjectRef
	dup
	getstatic	Field scala/Predef$.MODULE$:Lscala/Predef$;
	invokevirtual	Method scala/Predef$.Set:()Lscala/collection/immutable/Set$;
	getstatic	Field scala/Predef$.MODULE$:Lscala/Predef$;
	iconst_2
	anewarray	class scala/collection/immutable/BitSet
	dup
	iconst_0
	aload	4
	aastore
	dup
	iconst_1
	aload_3
	aastore
	checkcast	class "[Ljava/lang/Object;"
	invokevirtual	Method scala/Predef$.wrapRefArray:([Ljava/lang/Object;)Lscala/collection/mutable/WrappedArray;
	invokevirtual	Method scala/collection/immutable/Set$.apply:(Lscala/collection/Seq;)Lscala/collection/Traversable;
	checkcast	class scala/collection/immutable/Set
	invokespecial	Method scala/runtime/ObjectRef."<init>":(Ljava/lang/Object;)V
	astore	17
	new	class scala/collection/mutable/HashMap
	dup
	invokespecial	Method scala/collection/mutable/HashMap."<init>":()V
	astore	12
	new	class scala/runtime/ObjectRef
	dup
	getstatic	Field scala/collection/Map$.MODULE$:Lscala/collection/Map$;
	getstatic	Field scala/Predef$.MODULE$:Lscala/Predef$;
	iconst_2
	anewarray	class scala/Tuple2
	dup
	iconst_0
	new	class scala/Predef$ArrowAssoc
	dup
	aload	4
	invokespecial	Method scala/Predef$ArrowAssoc."<init>":(Ljava/lang/Object;)V
	pop
	new	class scala/Tuple2
	dup
	aload	4
	aload_3
	invokespecial	Method scala/Tuple2."<init>":(Ljava/lang/Object;Ljava/lang/Object;)V
	aastore
	dup
	iconst_1
	new	class scala/Predef$ArrowAssoc
	dup
	aload_3
	invokespecial	Method scala/Predef$ArrowAssoc."<init>":(Ljava/lang/Object;)V
	pop
	new	class scala/Tuple2
	dup
	aload_3
	aload_3
	invokespecial	Method scala/Tuple2."<init>":(Ljava/lang/Object;Ljava/lang/Object;)V
	aastore
	checkcast	class "[Ljava/lang/Object;"
	invokevirtual	Method scala/Predef$.wrapRefArray:([Ljava/lang/Object;)Lscala/collection/mutable/WrappedArray;
	invokevirtual	Method scala/collection/Map$.apply:(Lscala/collection/Seq;)Lscala/collection/Map;
	invokespecial	Method scala/runtime/ObjectRef."<init>":(Ljava/lang/Object;)V
	astore	14
	new	class scala/runtime/ObjectRef
	dup
	getstatic	Field scala/collection/Map$.MODULE$:Lscala/collection/Map$;
	getstatic	Field scala/Predef$.MODULE$:Lscala/Predef$;
	iconst_0
	anewarray	class scala/Tuple2
	checkcast	class "[Ljava/lang/Object;"
	invokevirtual	Method scala/Predef$.wrapRefArray:([Ljava/lang/Object;)Lscala/collection/mutable/WrappedArray;
	invokevirtual	Method scala/collection/Map$.apply:(Lscala/collection/Seq;)Lscala/collection/Map;
	invokespecial	Method scala/runtime/ObjectRef."<init>":(Ljava/lang/Object;)V
	astore	18
	new	class scala/collection/mutable/Stack
	dup
	invokespecial	Method scala/collection/mutable/Stack."<init>":()V
	astore	19
	aload	19
	aload_3
	aload	4
	getstatic	Field scala/Predef$.MODULE$:Lscala/Predef$;
	iconst_0
	anewarray	class scala/collection/immutable/BitSet
	checkcast	class "[Ljava/lang/Object;"
	invokevirtual	Method scala/Predef$.wrapRefArray:([Ljava/lang/Object;)Lscala/collection/mutable/WrappedArray;
	invokevirtual	Method scala/collection/mutable/Stack.push:(Ljava/lang/Object;Ljava/lang/Object;Lscala/collection/Seq;)Lscala/collection/mutable/Stack;
	pop
	aload_0
	aload	4
	aload	18
	invokespecial	Method addFinal$1:(Lscala/collection/immutable/BitSet;Lscala/runtime/ObjectRef;)V
l2	aload	19
	invokevirtual	Method scala/collection/mutable/Stack.isEmpty:()Z
	ifeq	l1 // aload
	aload	17
	getfield	Field scala/runtime/ObjectRef.elem:Ljava/lang/Object;
	checkcast	class scala/collection/immutable/Set
	invokeinterface	InterfaceMethod scala/collection/TraversableLike.size:()I
	istore	5
	iload	5
	anewarray	class scala/collection/Map
	astore	6
	iload	5
	newarray int
	astore	7
	iload	5
	newarray int
	astore	8
	aload	17
	getfield	Field scala/runtime/ObjectRef.elem:Ljava/lang/Object;
	checkcast	class scala/collection/immutable/Set
	new	class scala/util/automata/SubsetConstruction$$anonfun$determinize$2
	dup
	aload_0
	aload	9
	aload	12
	aload	14
	aload	6
	aload	7
	invokespecial	Method scala/util/automata/SubsetConstruction$$anonfun$determinize$2."<init>":(Lscala/util/automata/SubsetConstruction;Lscala/runtime/ObjectRef;Lscala/collection/mutable/HashMap;Lscala/runtime/ObjectRef;[Lscala/collection/Map;[I)V
	invokeinterface	InterfaceMethod scala/collection/IterableLike.foreach:(Lscala/Function1;)V
	aload	18
	getfield	Field scala/runtime/ObjectRef.elem:Ljava/lang/Object;
	checkcast	class scala/collection/Map
	new	class scala/util/automata/SubsetConstruction$$anonfun$determinize$3
	dup
	aload_0
	aload	9
	aload	8
	invokespecial	Method scala/util/automata/SubsetConstruction$$anonfun$determinize$3."<init>":(Lscala/util/automata/SubsetConstruction;Lscala/runtime/ObjectRef;[I)V
	invokeinterface	InterfaceMethod scala/collection/IterableLike.foreach:(Lscala/Function1;)V
	new	class scala/util/automata/SubsetConstruction$$anon$1
	dup
	aload_0
	iload	5
	aload	6
	aload	7
	aload	8
	invokespecial	Method scala/util/automata/SubsetConstruction$$anon$1."<init>":(Lscala/util/automata/SubsetConstruction;I[Lscala/collection/Map;[I[I)V
	areturn
l1	aload	19
	invokevirtual	Method scala/collection/mutable/Stack.pop:()Ljava/lang/Object;
	checkcast	class scala/collection/immutable/BitSet
	astore	15
	aload	9
	aload	9
	getfield	Field scala/runtime/ObjectRef.elem:Ljava/lang/Object;
	checkcast	class scala/collection/Map
	aload	15
	iload	11
	invokestatic	Method scala/runtime/BoxesRunTime.boxToInteger:(I)Ljava/lang/Integer;
	invokeinterface	InterfaceMethod scala/collection/MapLike.updated:(Ljava/lang/Object;Ljava/lang/Object;)Lscala/collection/Map;
	putfield	Field scala/runtime/ObjectRef.elem:Ljava/lang/Object;
	aload	10
	iload	11
	invokestatic	Method scala/runtime/BoxesRunTime.boxToInteger:(I)Ljava/lang/Integer;
	aload	15
	invokeinterface	InterfaceMethod scala/collection/MapLike.updated:(Ljava/lang/Object;Ljava/lang/Object;)Lscala/collection/Map;
	astore	10
	iload	11
	iconst_1
	iadd
	istore	11
	new	class scala/collection/mutable/HashMap
	dup
	invokespecial	Method scala/collection/mutable/HashMap."<init>":()V
	astore	13
	aload	12
	aload	15
	aload	13
	invokevirtual	Method scala/collection/mutable/HashMap.update:(Ljava/lang/Object;Ljava/lang/Object;)V
	aload_0
	invokevirtual	Method nfa:()Lscala/util/automata/NondetWordAutom;
	invokevirtual	Method scala/util/automata/NondetWordAutom.labels:()Lscala/collection/Seq;
	new	class scala/util/automata/SubsetConstruction$$anonfun$determinize$1
	dup
	aload_0
	aload	17
	aload	18
	aload	19
	aload	15
	aload	13
	invokespecial	Method scala/util/automata/SubsetConstruction$$anonfun$determinize$1."<init>":(Lscala/util/automata/SubsetConstruction;Lscala/runtime/ObjectRef;Lscala/runtime/ObjectRef;Lscala/collection/mutable/Stack;Lscala/collection/immutable/BitSet;Lscala/collection/mutable/HashMap;)V
	invokeinterface	InterfaceMethod scala/collection/IterableLike.foreach:(Lscala/Function1;)V
	aload_0
	invokevirtual	Method nfa:()Lscala/util/automata/NondetWordAutom;
	aload	15
	invokevirtual	Method scala/util/automata/NondetWordAutom.nextDefault:(Lscala/collection/immutable/BitSet;)Lscala/collection/immutable/BitSet;
	astore	16
	aload	14
	aload	14
	getfield	Field scala/runtime/ObjectRef.elem:Ljava/lang/Object;
	checkcast	class scala/collection/Map
	aload	15
	aload	16
	invokeinterface	InterfaceMethod scala/collection/MapLike.updated:(Ljava/lang/Object;Ljava/lang/Object;)Lscala/collection/Map;
	putfield	Field scala/runtime/ObjectRef.elem:Ljava/lang/Object;
	aload_0
	aload	16
	aload	17
	aload	18
	aload	19
	invokevirtual	Method add$1:(Lscala/collection/immutable/BitSet;Lscala/runtime/ObjectRef;Lscala/runtime/ObjectRef;Lscala/collection/mutable/Stack;)V
	goto	l2 // aload
  Labels:
   	l2 = 278 // aload
   	l1 = 393 // aload
  LocalVariableTable: 
   Start  Length  Slot  Name   Signature
   0      546      0    this       Lscala/util/automata/SubsetConstruction;
   87      305      3    sink       Lscala/collection/immutable/BitSet;
   393      153      3    sink       Lscala/collection/immutable/BitSet;
   80      312      4    q0       Lscala/collection/immutable/BitSet;
   393      153      4    q0       Lscala/collection/immutable/BitSet;
   301      91      5    nstatesR$1       I
   308      84      6    deltaR$1       [Lscala/collection/Map;
   314      78      7    defaultR$1       [I
   320      72      8    finalsR$1       [I
   28      364      9    indexMap$1       Lscala/runtime/ObjectRef;
   393      153      9    indexMap$1       Lscala/runtime/ObjectRef;
   49      343      10    invIndexMap       Lscala/collection/Map;
   393      153      10    invIndexMap       Lscala/collection/Map;
   52      340      11    ix       I
   393      153      11    ix       I
   139      253      12    delta$1       Lscala/collection/mutable/HashMap;
   393      153      12    delta$1       Lscala/collection/mutable/HashMap;
   459      84      13    Pdelta$1       Lscala/collection/mutable/HashMap;
   211      181      14    deftrans$1       Lscala/runtime/ObjectRef;
   393      153      14    deftrans$1       Lscala/runtime/ObjectRef;
   403      140      15    P$1       Lscala/collection/immutable/BitSet;
   509      34      16    Pdef       Lscala/collection/immutable/BitSet;
   130      262      17    states$1       Lscala/runtime/ObjectRef;
   393      153      17    states$1       Lscala/runtime/ObjectRef;
   239      153      18    finals$1       Lscala/runtime/ObjectRef;
   393      153      18    finals$1       Lscala/runtime/ObjectRef;
   248      144      19    rest$1       Lscala/collection/mutable/Stack;
   393      153      19    rest$1       Lscala/collection/mutable/Stack;

  Signature: length = 0x2
   00 FFFFFFEF 

public int selectTag(scala.collection.immutable.BitSet, int[]);
  Signature: (Lscala/collection/immutable/BitSet;[I)I
  Code:
   Stack=4, Locals=3, Args_size=3
	aload_1
	getstatic	Field scala/Predef$.MODULE$:Lscala/Predef$;
	aload_2
	invokevirtual	Method scala/Predef$.wrapIntArray:([I)Lscala/collection/mutable/WrappedArray;
	getstatic	Field scala/collection/immutable/BitSet$.MODULE$:Lscala/collection/immutable/BitSet$;
	invokevirtual	Method scala/collection/immutable/BitSet$.canBuildFrom:()Lscala/collection/generic/CanBuildFrom;
	invokeinterface	InterfaceMethod scala/collection/TraversableLike.map:(Lscala/Function1;Lscala/collection/generic/CanBuildFrom;)Ljava/lang/Object;
	checkcast	class scala/collection/TraversableLike
	new	class scala/util/automata/SubsetConstruction$$anonfun$selectTag$1
	dup
	aload_0
	invokespecial	Method scala/util/automata/SubsetConstruction$$anonfun$selectTag$1."<init>":(Lscala/util/automata/SubsetConstruction;)V
	invokeinterface	InterfaceMethod scala/collection/TraversableLike.filter:(Lscala/Function1;)Ljava/lang/Object;
	checkcast	class scala/collection/TraversableLike
	getstatic	Field scala/math/Ordering$Int$.MODULE$:Lscala/math/Ordering$Int$;
	invokeinterface	InterfaceMethod scala/collection/TraversableLike.min:(Lscala/math/Ordering;)Ljava/lang/Object;
	invokestatic	Method scala/runtime/BoxesRunTime.unboxToInt:(Ljava/lang/Object;)I
	ireturn
  Labels:
  LocalVariableTable: 
   Start  Length  Slot  Name   Signature
   0      50      0    this       Lscala/util/automata/SubsetConstruction;
   0      50      1    Q       Lscala/collection/immutable/BitSet;
   0      50      2    finals       [I


public scala.util.automata.NondetWordAutom nfa();
  Signature: ()Lscala/util/automata/NondetWordAutom;
  Code:
   Stack=1, Locals=1, Args_size=1
	aload_0
	getfield	Field nfa:Lscala/util/automata/NondetWordAutom;
	areturn
  Labels:
  Signature: length = 0x2
   01 0E 

}

